{
  "type": "Feature",
  "properties": {
    "iso:country":"CH",
    "sg:address":"Els\u00e4sserstrasse 20 4056 Basel. Postfach",
    "sg:city":"Basel",
    "sg:orig_category":"Herstellung von Schmuck, Gold U Silberschmiedwaren",
    "sg:phone":"+41 61 262 37 38",
    "sg:postcode":"4051",
    "sg:province":"Basel-Stadt",
    "wof:name":"Define, Seker A. Gold- U. Silberschmuck, Handel",
    "wof:placetype":"venue"
},
  "geometry": {"coordinates":[7.5800619125,47.5687294006],"type":"Point"}
}