{
  "type": "Feature",
  "properties": {
    "iso:country":"CH",
    "sg:address":"Route Du Bugnon 35",
    "sg:city":"Villars-sur-gl\u00e2ne",
    "sg:orig_category":"Sportvereine Fischerei",
    "sg:phone":"+41 56 621 85 03",
    "sg:postcode":"1752",
    "sg:province":"Fribourg",
    "wof:name":"Fischer-club Bremgarten",
    "wof:placetype":"venue"
},
  "geometry": {"coordinates":[8.344452858,47.3506698608],"type":"Point"}
}