{
  "type": "Feature",
  "properties": {
    "iso:country":"CH",
    "sg:address":"Engelgasse 83 4000 Basel. Postfach",
    "sg:city":"Basel",
    "sg:orig_category":"Softwareentwicklung U beratung",
    "sg:phone":"+41 17374774",
    "sg:postcode":"4051",
    "sg:province":"Basel-Stadt",
    "wof:name":"Affolter Engineering",
    "wof:placetype":"venue"
},
  "geometry": {"coordinates":[8.44668293,47.3579521179],"type":"Point"}
}