{
  "type": "Feature",
  "properties": {
    "iso:country":"CH",
    "sg:address":"Schwanengasse 3 3011 Bern. Postfach",
    "sg:city":"Bern",
    "sg:orig_category":"Verkehrsverb\u00e4nde Wirtschaftsverb\u00e4nde Verkehrswesen, Tourismus",
    "sg:phone":"+41 31 311 36 49",
    "sg:postcode":"3001",
    "sg:province":"Bern",
    "wof:name":"Schweiz.strassenverkehrs- Verband",
    "wof:placetype":"venue"
},
  "geometry": {"coordinates":[7.4391279221,46.9470596313],"type":"Point"}
}