{
  "type": "Feature",
  "properties": {
    "iso:country":"CH",
    "sg:address":"Rue De La Sagne 19 1450 Ste-croix Case Postale 298",
    "sg:city":"Ste-croix",
    "sg:orig_category":"Herstellung von Kunststoffwaren Herstellung von Schrauben, Nieten, Ketten U Federn",
    "sg:phone":"+41 24 454 22 72",
    "sg:postcode":"1450",
    "sg:province":"Vaud",
    "wof:name":"Victoria Sa Fabrique De D\u00e9colletages",
    "wof:placetype":"venue"
},
  "geometry": {"coordinates":[6.5010690689,46.8176193237],"type":"Point"}
}