{
  "type": "Feature",
  "properties": {
    "iso:country":"CH",
    "sg:address":"Chamossaire Avenue Du 4",
    "sg:city":"Aigle",
    "sg:orig_category":"Detailhandel mit elektrischen Haushalts-,Radio U Fernsehger\u00e4ten sowie Musikinstrumenten",
    "sg:postcode":"1860",
    "sg:province":"Vaud",
    "wof:name":"Fuego, Patrice Quiquaz",
    "wof:placetype":"venue"
},
  "geometry": {"coordinates":[6.9682760239,46.3164634705],"type":"Point"}
}