{
  "type": "Feature",
  "properties": {
    "iso:country":"CH",
    "sg:address":"Hauptstrasse 44",
    "sg:city":"Sevelen",
    "sg:orig_category":"Sanit\u00e4r, Heizungs U L\u00fcftungsinstallation Sanit\u00e4rinstallation",
    "sg:phone":"+41 81 785 32 22",
    "sg:postcode":"9475",
    "sg:province":"St. Gallen",
    "wof:name":"Stricker",
    "wof:placetype":"venue"
},
  "geometry": {"coordinates":[9.4858875275,47.1208457947],"type":"Point"}
}