{
  "type": "Feature",
  "properties": {
    "iso:country":"CH",
    "sg:address":"Haus Zur M\u00fchle 7064 Tschiertschen. Postfach",
    "sg:city":"Tschiertschen",
    "sg:orig_category":"Sonstige mit der Informatik verbundene T\u00e4tigkeiten",
    "sg:phone":"+41 81 356 10 08",
    "sg:postcode":"7064",
    "sg:province":"Graubunden",
    "wof:name":"Grimm Network Pc/lan-support",
    "wof:placetype":"venue"
},
  "geometry": {"coordinates":[9.6063089371,46.8191223145],"type":"Point"}
}