{
  "type": "Feature",
  "properties": {
    "iso:country":"CH",
    "sg:address":"Falkensteinerstrasse 24",
    "sg:city":"Balsthal",
    "sg:orig_category":"Malerei-Gipserei Stukkateurgewerbe, Gipserei U Verputzerei",
    "sg:phone":"+41 62 391 56 08",
    "sg:postcode":"4710",
    "sg:province":"Solothurn",
    "wof:name":"Renato Antonio Albani Gipsergesch\u00e4ft",
    "wof:placetype":"venue"
},
  "geometry": {"coordinates":[7.6921081543,47.3134384155],"type":"Point"}
}