{
  "type": "Feature",
  "properties": {
    "iso:country":"CH",
    "sg:address":"Rue Couchirard 8",
    "sg:city":"Lausanne",
    "sg:classifiers":[
        {
            "category":"Organizations",
            "subcategory":"Community Association",
            "type":"Services"
        }
    ],
    "sg:phone":"+41 21 624 63 03",
    "sg:postcode":"1004",
    "sg:province":"Vaud",
    "sg:tags":[
        "fire",
        "insulation"
    ],
    "wof:name":"Grand Isolations",
    "wof:placetype":"venue"
},
  "geometry": {"coordinates":[6.6132588387,46.5264663696],"type":"Point"}
}