{
  "type": "Feature",
  "properties": {
    "iso:country":"CH",
    "sg:address":"Via A.nessi 22",
    "sg:city":"Locarno",
    "sg:orig_category":"Unclassifiable Establishments",
    "sg:phone":"+41 32 384 25 21",
    "sg:postcode":"6600",
    "sg:province":"Ticino",
    "wof:name":"Event Horizon Scheidegger",
    "wof:placetype":"venue"
},
  "geometry": {"coordinates":[7.3270831108,47.101474762],"type":"Point"}
}