{
  "type": "Feature",
  "properties": {
    "iso:country":"CH",
    "sg:address":"Voia Principale 35",
    "sg:city":"Lantsch/lenz",
    "sg:orig_category":"Handel mit Motorr\u00e4dern, Teilen U Zubeh\u00f6r Instandhaltung U Reparatur von Automobilen Instandhaltung U",
    "sg:phone":"+41 81 681 19 79",
    "sg:postcode":"7083",
    "sg:province":"Graubunden",
    "wof:name":"Luzi Bl\u00e4si Autoelektro & Motorger\u00e4te",
    "wof:placetype":"venue"
},
  "geometry": {"coordinates":[9.5635290146,46.6848526001],"type":"Point"}
}