{
  "type": "Feature",
  "properties": {
    "iso:country":"CH",
    "sg:address":"Schulhausstrasse 19",
    "sg:city":"Villmergen",
    "sg:classifiers":[
        {
            "category":"Restaurant",
            "type":"Food & Drink"
        }
    ],
    "sg:phone":"+41 56 622 20 51",
    "sg:postcode":"5612",
    "sg:province":"Aargau",
    "wof:name":"Restaurant Burehof",
    "wof:placetype":"venue"
},
  "geometry": {"coordinates":[8.2419252396,47.3482894897],"type":"Point"}
}