{
  "type": "Feature",
  "properties": {
    "iso:country":"CH",
    "sg:address":"Locherzelgstrasse 24",
    "sg:city":"Romanshorn",
    "sg:orig_category":"Non-Classified Establishments",
    "sg:postcode":"8590",
    "sg:province":"Thurgau",
    "wof:name":"Buchlizone Inhaberin Judith Buchli",
    "wof:placetype":"venue"
},
  "geometry": {"coordinates":[9.3616943359,47.5617523193],"type":"Point"}
}