{
  "type": "Feature",
  "properties": {
    "iso:country":"CH",
    "sg:address":"Rathausgasse 35",
    "sg:city":"Lenzburg",
    "sg:orig_category":"Arztpraxen",
    "sg:phone":"+41 62 892 07 06",
    "sg:postcode":"5600",
    "sg:province":"Aargau",
    "wof:name":"Dres Med. M. & T. Graf Spezial\u00e4rzte Fmh",
    "wof:placetype":"venue"
},
  "geometry": {"coordinates":[8.180917,47.387379],"type":"Point"}
}