{
  "type": "Feature",
  "properties": {
    "iso:country":"CH",
    "sg:address":"Rohrwies",
    "sg:city":"Reichenburg",
    "sg:orig_category":"Detailhandel mit elektrischen Haushalts-,Radio U Fernsehger\u00e4ten sowie Musikinstrumenten",
    "sg:postcode":"8864",
    "sg:province":"Schwyz",
    "wof:name":"Radio-tv-service B\u00e4rtschi",
    "wof:placetype":"venue"
},
  "geometry": {"coordinates":[7.5834031105,47.084602356],"type":"Point"}
}