{
  "type": "Feature",
  "properties": {
    "iso:country":"CH",
    "sg:address":"Unter Bendlehn 26",
    "sg:city":"Speicher",
    "sg:orig_category":"Architektur U Ingenieurb\u00fcros Herstellung von Maschinen f\u00fcr die Nahrungsmittel, Getr\u00e4nkeherstellung U",
    "sg:phone":"+41 71 344 45 55",
    "sg:postcode":"9042",
    "sg:province":"Appenzell Ausserrhoden",
    "wof:name":"Trinox Ag Ingenieurb\u00fcro",
    "wof:placetype":"venue"
},
  "geometry": {"coordinates":[9.450563,47.40591],"type":"Point"}
}