{
  "type": "Feature",
  "properties": {
    "iso:country":"CH",
    "sg:address":"Br\u00fcelstrasse 295",
    "sg:city":"G\u00e4chlingen",
    "sg:orig_category":"Detailhandel mit Fahrr\u00e4dern",
    "sg:phone":"+41 19374330",
    "sg:postcode":"8214",
    "sg:province":"Schaffhausen",
    "wof:name":"Hans Sonderegger Haso's Velo & Rehatech",
    "wof:placetype":"venue"
},
  "geometry": {"coordinates":[8.8388719559,47.299697876],"type":"Point"}
}