{
  "type": "Feature",
  "properties": {
    "iso:country":"CH",
    "sg:address":"Route De St-julien 285",
    "sg:city":"Perly",
    "sg:orig_category":"Glaserei Sonstige Bauinstallation",
    "sg:phone":"+41 41 871 05 45",
    "sg:postcode":"1258",
    "sg:province":"Gen\u00e8ve",
    "wof:name":"Peter Montagen Glas-& Metallbaumontagen",
    "wof:placetype":"venue"
},
  "geometry": {"coordinates":[8.631422,46.878841],"type":"Point"}
}