{
  "type": "Feature",
  "properties": {
    "iso:country":"CH",
    "sg:address":"1436",
    "sg:city":"Treycovagnes",
    "sg:orig_category":"Herstellung von Karosserien U Anh\u00e4ngern",
    "sg:phone":"+41 24 445 28 46",
    "sg:postcode":"1436",
    "sg:province":"Vaud",
    "wof:name":"Carrosserie Du Ch\u00e2telard, Rigo Michel",
    "wof:placetype":"venue"
},
  "geometry": {"coordinates":[6.6023898125,46.7754516602],"type":"Point"}
}