{
  "type": "Feature",
  "properties": {
    "iso:country":"CH",
    "sg:address":"Baarerstrasse 71 6300 Zug. Postfach",
    "sg:city":"Zug",
    "sg:orig_category":"Korrespondenz U Nachrichtenb\u00fcros, selbst\u00e4ndige Journalisten",
    "sg:phone":"+41 79 610 51 10",
    "sg:postcode":"6300",
    "sg:province":"Zug",
    "wof:name":"Swiss-image Gmbh",
    "wof:placetype":"venue"
},
  "geometry": {"coordinates":[9.8209514618,46.7950172424],"type":"Point"}
}