{
  "type": "Feature",
  "properties": {
    "iso:country":"CH",
    "sg:address":"Industriestrasse 1",
    "sg:city":"Embrach",
    "sg:orig_category":"Hardwareberatung",
    "sg:phone":"+41 71 740 08 08",
    "sg:postcode":"8424",
    "sg:province":"Z\u00fcrich",
    "wof:name":"Christian's Computer-shop C. Zellweger",
    "wof:placetype":"venue"
},
  "geometry": {"coordinates":[9.6373157501,47.4264755249],"type":"Point"}
}