{
  "type": "Feature",
  "properties": {
    "iso:country":"CH",
    "sg:address":"R\u00e4melig\u00e4ssli 1",
    "sg:city":"Boll",
    "sg:orig_category":"Zimmerei, Dachdeckerei, Bauspenglerei U Abdichtung",
    "sg:phone":"+41 31 839 18 10",
    "sg:postcode":"3067",
    "sg:province":"Bern",
    "wof:name":"Christen Samuel",
    "wof:placetype":"venue"
},
  "geometry": {"coordinates":[7.5540299416,46.9518890381],"type":"Point"}
}