{
  "type": "Feature",
  "properties": {
    "iso:country":"CH",
    "sg:address":"Graumatt 66",
    "sg:city":"Attelwil",
    "sg:orig_category":"Grosshandel mit Holz U Bauelementen aus Holz Herstellung von Konstruktionsteilen, Fertigbauteilen U ",
    "sg:phone":"+41 13028270",
    "sg:postcode":"5056",
    "sg:province":"Aargau",
    "wof:name":"Saxer & Zimmermann Ag",
    "wof:placetype":"venue"
},
  "geometry": {"coordinates":[8.4380941391,47.4535331726],"type":"Point"}
}