{
  "type": "Feature",
  "properties": {
    "iso:country":"CH",
    "sg:address":"Dorfstrasse 57",
    "sg:city":"Bettenhausen",
    "sg:orig_category":"Gasth\u00f6fe/Gasth\u00e4user mit Restaurant",
    "sg:phone":"+41 71 393 38 47",
    "sg:postcode":"3366",
    "sg:province":"Bern",
    "wof:name":"Landgasthof R\u00f6ssli",
    "wof:placetype":"venue"
},
  "geometry": {"coordinates":[9.2117004395,47.4424667358],"type":"Point"}
}