{
  "type": "Feature",
  "properties": {
    "iso:country":"CH",
    "sg:address":"Molliserstrasse 4",
    "sg:city":"Netstal",
    "sg:orig_category":"Schreib U \u00dcbersetzungsb\u00fcros",
    "sg:postcode":"8754",
    "sg:province":"Glarus",
    "wof:name":"Kanzlei Weber",
    "wof:placetype":"venue"
},
  "geometry": {"coordinates":[9.0553436279,47.0632209778],"type":"Point"}
}