{
  "type": "Feature",
  "properties": {
    "iso:country":"CH",
    "sg:address":"Postgasse 18",
    "sg:city":"Bern",
    "sg:orig_category":"Herstellung von Schmuck, Gold U Silberschmiedwaren",
    "sg:phone":"+41 31 311 03 26",
    "sg:postcode":"3011",
    "sg:province":"Bern",
    "wof:name":"Zac Einrahmungen Vergoldungen Marc Bigler",
    "wof:placetype":"venue"
},
  "geometry": {"coordinates":[7.4552788734,46.9491386414],"type":"Point"}
}