{
  "type": "Feature",
  "properties": {
    "iso:country":"CH",
    "sg:address":"Dufour Via 2",
    "sg:city":"Lugano",
    "sg:orig_category":"Fachdetailhandel in Verkaufsr\u00e4umen",
    "sg:postcode":"6900",
    "sg:province":"Ticino",
    "wof:name":"Ars Magna Sa",
    "wof:placetype":"venue"
},
  "geometry": {"coordinates":[8.9517726898,46.0084915161],"type":"Point"}
}