{
  "type": "Feature",
  "properties": {
    "iso:country":"CH",
    "sg:address":"Ch\u00fcblerweg 3 8460 Marthalen. Postfach",
    "sg:city":"Neftenbach",
    "sg:orig_category":"Non-Classified Establishments",
    "sg:postcode":"8413",
    "sg:province":"Z\u00fcrich",
    "wof:name":"Kramh\u00d6ller K\u00c4lte-klimatechnik",
    "wof:placetype":"venue"
},
  "geometry": {"coordinates":[8.3332490921,47.5211181641],"type":"Point"}
}