{
  "type": "Feature",
  "properties": {
    "iso:country":"CH",
    "sg:address":"Tanzplatz",
    "sg:city":"Seelisberg",
    "sg:orig_category":"Detailhandel mit Waren verschiedener Art, Hauptrichtung Nahrungsmittel",
    "sg:phone":"+41 41 820 37 07",
    "sg:postcode":"6377",
    "sg:province":"Uri",
    "wof:name":"R. Huser & A. Truttmann Dorfladen",
    "wof:placetype":"venue"
},
  "geometry": {"coordinates":[8.5846300125,46.9665298462],"type":"Point"}
}