{
  "type": "Feature",
  "properties": {
    "iso:country":"CH",
    "sg:address":"Prattelerstrasse 27 4052 Basel. Postfach",
    "sg:city":"Basel",
    "sg:orig_category":"D\u00e4mmung gegen K\u00e4lte, W\u00e4rme, Schall U Ersch\u00fctterung",
    "sg:phone":"+41 61 312 44 75",
    "sg:postcode":"4020",
    "sg:province":"Basel-Stadt",
    "wof:name":"Werner Isolierwerk Ag K\u00e4lte, W\u00e4rme, Schallisolationen Usw",
    "wof:placetype":"venue"
},
  "geometry": {"coordinates":[7.6129817963,47.5458145142],"type":"Point"}
}