{
  "type": "Feature",
  "properties": {
    "iso:country":"CH",
    "sg:address":"Schmalzgrubenstrasse 2 8842 Unteriberg. Postfach 42",
    "sg:city":"Unteriberg",
    "sg:classifiers":[
        {
            "category":"Travel",
            "subcategory":"Hotels & Motels",
            "type":"Entertainment"
        }
    ],
    "sg:phone":"+41 55 414 60 30",
    "sg:postcode":"8842",
    "sg:province":"Schwyz",
    "sg:tags":[
        "hotels",
        "mit",
        "restaurant"
    ],
    "wof:name":"Landgasthof R\u00f6sslipost",
    "wof:placetype":"venue"
},
  "geometry": {"coordinates":[8.8021450043,47.0593414307],"type":"Point"}
}