{
  "type": "Feature",
  "properties": {
    "iso:country":"CH",
    "sg:address":"Zentralstrasse 81",
    "sg:city":"Neuhausen",
    "sg:orig_category":"Hoch U Tiefbau Stukkateurgewerbe, Gipserei U Verputzerei",
    "sg:phone":"+41 52 672 27 42",
    "sg:postcode":"8212",
    "sg:province":"Schaffhausen",
    "wof:name":"Ciciretti Carmine Gmbh Gipserei, Stukkatur- U. Baugesch\u00e4ft",
    "wof:placetype":"venue"
},
  "geometry": {"coordinates":[8.6209640503,47.6831474304],"type":"Point"}
}