{
  "type": "Feature",
  "properties": {
    "iso:country":"CH",
    "sg:address":"Reusseggstrasse 17",
    "sg:city":"Emmenbr\u00fccke",
    "sg:orig_category":"Architektur U Ingenieurb\u00fcros",
    "sg:phone":"+41 32 913 38 60",
    "sg:postcode":"6020",
    "sg:province":"Luzern",
    "wof:name":"Hynatec, Oldenziel Dr. Daniel M.",
    "wof:placetype":"venue"
},
  "geometry": {"coordinates":[6.835294,47.09679],"type":"Point"}
}