{
  "type": "Feature",
  "properties": {
    "iso:country":"CH",
    "sg:address":"Gantrischweg 15 3063 Ittigen. Postfach",
    "sg:city":"Ittigen",
    "sg:orig_category":"Kauf U Verkauf von Immobilien auf eigene Rechnung Verwaltung von Immobilien",
    "sg:phone":"+41 31 921 86 45",
    "sg:postcode":"3063",
    "sg:province":"Bern",
    "wof:name":"Casa Umbra Kieliger Jolanda Immobilien Usw.",
    "wof:placetype":"venue"
},
  "geometry": {"coordinates":[7.4888339043,46.9805107117],"type":"Point"}
}