{
  "type": "Feature",
  "properties": {
    "iso:country":"CH",
    "sg:address":"Rheinfelderstrasse 27",
    "sg:city":"M\u00f6hlin",
    "sg:orig_category":"Institutionen f\u00fcr psychosoziale F\u00e4lle",
    "sg:phone":"+41 71 223 38 87",
    "sg:postcode":"4313",
    "sg:province":"Aargau",
    "wof:name":"Wohngruppe St.gallen",
    "wof:placetype":"venue"
},
  "geometry": {"coordinates":[9.3671951294,47.4175567627],"type":"Point"}
}