{
  "type": "Feature",
  "properties": {
    "iso:country":"CH",
    "sg:address":"Im Bruggen 12",
    "sg:city":"Wettswil",
    "sg:orig_category":"Herstellung von sonstigen elektrischen Ausr\u00fcstungen",
    "sg:phone":"+41 17004440",
    "sg:postcode":"8907",
    "sg:province":"Z\u00fcrich",
    "wof:name":"Sch\u00fcrch Electronic Ag",
    "wof:placetype":"venue"
},
  "geometry": {"coordinates":[8.4751806259,47.3295593262],"type":"Point"}
}