{
  "type": "Feature",
  "properties": {
    "iso:country":"CH",
    "sg:address":"Gempenstrasse 69 4053 Basel. Postfach",
    "sg:city":"Basel",
    "sg:orig_category":"RESTAURANTS: TEA-ROOMS",
    "sg:phone":"+41 31 332 39 29",
    "sg:postcode":"4051",
    "sg:province":"Basel-Stadt",
    "wof:name":"Genossenschaft Restaurant Brasserie Lorraine",
    "wof:placetype":"venue"
},
  "geometry": {"coordinates":[7.4457011223,46.9579620361],"type":"Point"}
}