{
  "type": "Feature",
  "properties": {
    "iso:country":"CH",
    "sg:address":"3305",
    "sg:city":"Iffwil",
    "sg:orig_category":"Vereine Gesang",
    "sg:postcode":"3305",
    "sg:province":"Bern",
    "wof:name":"M\u00e4nnerchor Iffwil",
    "wof:placetype":"venue"
},
  "geometry": {"coordinates":[7.4820280075,47.0620880127],"type":"Point"}
}