{
  "type": "Feature",
  "properties": {
    "iso:country":"CH",
    "sg:address":"Maienstrasse 6",
    "sg:city":"Grenchen",
    "sg:orig_category":"Grosshandel mit Textilien Grosshandel mit sonstigen Konsumg\u00fctern",
    "sg:phone":"+41 32 652 76 49",
    "sg:postcode":"2540",
    "sg:province":"Solothurn",
    "wof:name":"Albatros, De Giovanni",
    "wof:placetype":"venue"
},
  "geometry": {"coordinates":[7.4041700363,47.1904602051],"type":"Point"}
}