{
  "type": "Feature",
  "properties": {
    "iso:country":"CH",
    "sg:address":"Aeschenplatz 4",
    "sg:city":"Basel",
    "sg:classifiers":[
        {
            "category":"Restaurant",
            "type":"Food & Drink"
        }
    ],
    "sg:phone":"+41 61 271 38 55",
    "sg:postcode":"4052",
    "sg:province":"Basel-Stadt",
    "wof:name":"Restaurant Aeschenplatz",
    "wof:placetype":"venue"
},
  "geometry": {"coordinates":[7.5958971977,47.5512924194],"type":"Point"}
}