{
  "type": "Feature",
  "properties": {
    "iso:country":"CH",
    "sg:address":"Via Luini 22",
    "sg:city":"Locarno",
    "sg:orig_category":"Verlagsgewerbe",
    "sg:phone":"+41 91 752 22 30",
    "sg:postcode":"6600",
    "sg:province":"Ticino",
    "wof:name":"La Rada Edizioni & Spazio Culturale Associazione",
    "wof:placetype":"venue"
},
  "geometry": {"coordinates":[8.8003940582,46.1705741882],"type":"Point"}
}