{
  "type": "Feature",
  "properties": {
    "iso:country":"CH",
    "sg:address":"Mettenwilstrasse 2",
    "sg:city":"Neuenkirch",
    "sg:orig_category":"Unclassifiable Establishments",
    "sg:postcode":"6206",
    "sg:province":"Luzern",
    "wof:name":"Saydah Auto Export + Transport",
    "wof:placetype":"venue"
},
  "geometry": {"coordinates":[8.2032394409,47.1185073853],"type":"Point"}
}