{
  "type": "Feature",
  "properties": {
    "iso:country":"CH",
    "sg:address":"Terreaux Rue Des 1",
    "sg:city":"Moudon",
    "sg:orig_category":"Unternehmensberatung",
    "sg:phone":"+41 21 905 41 15",
    "sg:postcode":"1510",
    "sg:province":"Vaud",
    "wof:name":"Gisal Sa Gestions Industrielles",
    "wof:placetype":"venue"
},
  "geometry": {"coordinates":[6.7962698936,46.6684074402],"type":"Point"}
}