{
  "type": "Feature",
  "properties": {
    "addr:full":"Route De Suisse 132 1290 Versoix Case Postale 247 Versoix Gen\u00e8ve 1290",
    "addr:housenumber":"132;247",
    "addr:postcode":"1290;1290",
    "addr:street":"Route De Suisse;Postale",
    "iso:country":"CH",
    "sg:address":"Route De Suisse 132 1290 Versoix Case Postale 247",
    "sg:city":"Versoix",
    "sg:orig_category":"Architekturb\u00fcros",
    "sg:phone":"+41 22 755 27 43",
    "sg:postcode":"1290",
    "sg:province":"Gen\u00e8ve",
    "wof:name":"Alain Ress\u00e9guier Bureau D'architecture",
    "wof:placetype":"venue"
},
  "geometry": {"coordinates":[6.165844,46.288849],"type":"Point"}
}