{
  "type": "Feature",
  "properties": {
    "iso:country":"CH",
    "sg:address":"Kronenstrasse 12",
    "sg:city":"Adliswil",
    "sg:orig_category":"Architektur U Ingenieurb\u00fcros",
    "sg:phone":"+41 17501661",
    "sg:postcode":"8134",
    "sg:province":"Z\u00fcrich",
    "wof:name":"Ic-management Ag",
    "wof:placetype":"venue"
},
  "geometry": {"coordinates":[8.52687,47.311562],"type":"Point"}
}