{
  "type": "Feature",
  "properties": {
    "iso:country":"CH",
    "sg:address":"Arnier Route D' 8",
    "sg:city":"Belmont-lausanne",
    "sg:orig_category":"Softwareentwicklung U beratung",
    "sg:phone":"+41 21 728 85 01",
    "sg:postcode":"1092",
    "sg:province":"Vaud",
    "wof:name":"Stingray Computer Services, Bardet Christian",
    "wof:placetype":"venue"
},
  "geometry": {"coordinates":[6.6903400421,46.5261383057],"type":"Point"}
}