{
  "type": "Feature",
  "properties": {
    "iso:country":"CH",
    "sg:address":"Avenue Victor-ruffy 4",
    "sg:city":"Lausanne",
    "sg:orig_category":"Arztpraxen",
    "sg:phone":"+41 21 323 43 45",
    "sg:postcode":"1012",
    "sg:province":"Vaud",
    "wof:name":"Dr M\u00e9d. Jean-claude Bianchi M\u00e9decin G\u00e9n\u00e9raliste",
    "wof:placetype":"venue"
},
  "geometry": {"coordinates":[6.647124,46.522575],"type":"Point"}
}