{
  "type": "Feature",
  "properties": {
    "iso:country":"CH",
    "sg:address":"Auf Der Egerta 94",
    "sg:city":"Planken",
    "sg:orig_category":"Innenausbau Zimmerei, Ingenieurholzbau",
    "sg:phone":"+423 373 39 65",
    "sg:postcode":"9498",
    "wof:name":"Walter Schierscher Holzbaumontage Anstalt",
    "wof:placetype":"venue"
},
  "geometry": {"coordinates":[9.5448703766,47.186870575],"type":"Point"}
}