{
  "type": "Feature",
  "properties": {
    "iso:country":"CH",
    "sg:address":"Centro Serrafiorita V.cantonal",
    "sg:city":"Pambio-noranco",
    "sg:orig_category":"Einzelhandel mit Automobilteilen U Zubeh\u00f6r Instandhaltung U Reparatur von Automobilen",
    "sg:phone":"+41 71 688 18 45",
    "sg:postcode":"6915",
    "sg:province":"Ticino",
    "wof:name":"Jakob Haltner Pneuhaus & Garage",
    "wof:placetype":"venue"
},
  "geometry": {"coordinates":[9.1916122437,47.6408920288],"type":"Point"}
}