{
  "type": "Feature",
  "properties": {
    "iso:country":"CH",
    "sg:address":"Rue De Gen\u00e8ve 17",
    "sg:city":"Lausanne",
    "sg:orig_category":"Detailhandel mit Musikinstrumenten Detailhandel mit elektrischen Haushalts-,Radio U Fernsehger\u00e4ten s",
    "sg:phone":"+41 21 312 56 00",
    "sg:postcode":"1003",
    "sg:province":"Vaud",
    "wof:name":"D\u00e9p\u00f4t Vente D'instruments De Musique, Ivan Prokofieff",
    "wof:placetype":"venue"
},
  "geometry": {"coordinates":[6.6285028458,46.5217628479],"type":"Point"}
}