{
  "type": "Feature",
  "properties": {
    "iso:country":"CH",
    "sg:address":"Sorengo Via 25",
    "sg:city":"Lugano",
    "sg:orig_category":"Instandhaltung U Reparatur von Automobilen",
    "sg:phone":"+41 91 966 87 07",
    "sg:postcode":"6900",
    "sg:province":"Ticino",
    "wof:name":"Garage Sorengo Racing Di Savinelli Clemente",
    "wof:placetype":"venue"
},
  "geometry": {"coordinates":[8.9416427612,46.0031089783],"type":"Point"}
}