{
  "type": "Feature",
  "properties": {
    "iso:country":"CH",
    "sg:address":"Salinenstrasse 13",
    "sg:city":"M\u00f6hlin",
    "sg:orig_category":"Allgemeiner Hoch U Tiefbau Allgemeiner Hochbau",
    "sg:phone":"+41 79 446 85 00",
    "sg:postcode":"4313",
    "sg:province":"Aargau",
    "wof:name":"Braccini Bau Ag",
    "wof:placetype":"venue"
},
  "geometry": {"coordinates":[7.836862,47.567593],"type":"Point"}
}