{
  "type": "Feature",
  "properties": {
    "iso:country":"CH",
    "sg:address":"Avenue Des Morgines 12",
    "sg:city":"Petit-lancy",
    "sg:orig_category":"Datenverarbeitungsdienste",
    "sg:phone":"+41 22 879 08 79",
    "sg:postcode":"1213",
    "sg:province":"Gen\u00e8ve",
    "wof:name":"Virtual Telecom Sa",
    "wof:placetype":"venue"
},
  "geometry": {"coordinates":[6.110719,46.191372],"type":"Point"}
}