{
  "type": "Feature",
  "properties": {
    "iso:country":"CH",
    "sg:address":"Hauptstrasse 7408 Cazis. Postfach",
    "sg:city":"Cazis",
    "sg:orig_category":"Tankstellen",
    "sg:postcode":"7408",
    "sg:province":"Graubunden",
    "wof:name":"Shell-tankstelle, Arno Brot",
    "wof:placetype":"venue"
},
  "geometry": {"coordinates":[9.4273872375,46.7245292664],"type":"Point"}
}