{
  "type": "Feature",
  "properties": {
    "iso:country":"CH",
    "sg:address":"Goldsteinstrasse 23 8200 Schaffhausen. Postfach 26",
    "sg:city":"Schaffhausen",
    "sg:orig_category":"Softwareentwicklung U beratung Unternehmensberatung",
    "sg:phone":"+41 19385720",
    "sg:postcode":"8202",
    "sg:province":"Schaffhausen",
    "wof:name":"Celeris Ag Im Internetbereich Usw",
    "wof:placetype":"venue"
},
  "geometry": {"coordinates":[8.8190374374,47.3039855957],"type":"Point"}
}