{
  "type": "Feature",
  "properties": {
    "addr:full":"Via San Gottardo 95 Massagno Ticino 6900",
    "addr:housenumber":"95",
    "addr:postcode":"6900",
    "addr:street":"Via San Gottardo",
    "iso:country":"CH",
    "sg:address":"Via San Gottardo 95",
    "sg:city":"Massagno",
    "sg:orig_category":"Datenverarbeitungsdienste Herstellung von Radio U Fernsehger\u00e4ten sowie phono U videotechnischen Ger\u00e4",
    "sg:phone":"+41 91 950 02 42",
    "sg:postcode":"6900",
    "sg:province":"Ticino",
    "wof:name":"Ticicom Sa",
    "wof:placetype":"venue"
},
  "geometry": {"coordinates":[8.942954,46.01358],"type":"Point"}
}