{
  "type": "Feature",
  "properties": {
    "iso:country":"CH",
    "sg:address":"Alleestrasse 58 8590 Romanshorn. Postfach 83",
    "sg:city":"Romanshorn",
    "sg:orig_category":"Verwaltung von Immobilien Wirtschaftspr\u00fcfung, Steuerberatung U Treuhand",
    "sg:phone":"+41 71 463 24 82",
    "sg:postcode":"8590",
    "sg:province":"Thurgau",
    "wof:name":"Sigman Treuhand Und Verwaltung Ag",
    "wof:placetype":"venue"
},
  "geometry": {"coordinates":[9.3780622482,47.5630722046],"type":"Point"}
}