{
  "type": "Feature",
  "properties": {
    "iso:country":"CH",
    "sg:address":"Weinbergstrasse 18",
    "sg:city":"Salenstein",
    "sg:orig_category":"Fachdetailhandel in Verkaufsr\u00e4umen",
    "sg:postcode":"8268",
    "sg:province":"Thurgau",
    "wof:name":"Dr. Ruth Lyner Hole In One",
    "wof:placetype":"venue"
},
  "geometry": {"coordinates":[9.0568113327,47.6730232239],"type":"Point"}
}