{
  "type": "Feature",
  "properties": {
    "iso:country":"CH",
    "sg:address":"Cases Route Des 19 1890 St-maurice. Postfach",
    "sg:city":"Dailly",
    "sg:orig_category":"Sonstige pers\u00f6nliche Dienstleistungen",
    "sg:phone":"+41 79 487 30 85",
    "sg:postcode":"1890",
    "sg:province":"Valais",
    "wof:name":"Loclight, Coutaz Baptiste Location De Personnel Technique Et De Mat\u00e9riel D'\u00e9clairage",
    "wof:placetype":"venue"
},
  "geometry": {"coordinates":[7.0044598579,46.2167739868],"type":"Point"}
}