{
  "type": "Feature",
  "properties": {
    "iso:country":"CH",
    "sg:address":"Mostelbergstrasse 136",
    "sg:city":"Sattel",
    "sg:orig_category":"Grosshandel mit Eisenwaren sowie Installationsbedarf f\u00fcr Gas, Wasser U Heizung",
    "sg:phone":"+41 22 342 07 00",
    "sg:postcode":"6417",
    "sg:province":"Schwyz",
    "wof:name":"International Sadas Sa",
    "wof:placetype":"venue"
},
  "geometry": {"coordinates":[6.1323451996,46.1880149841],"type":"Point"}
}