{
  "type": "Feature",
  "properties": {
    "iso:country":"CH",
    "sg:address":"Bruggerstrasse 25 5102 Rupperswil. Postfach",
    "sg:city":"Rupperswil",
    "sg:orig_category":"Tankstellen",
    "sg:phone":"+41 62 889 10 70",
    "sg:postcode":"5102",
    "sg:province":"Aargau",
    "wof:name":"Zentral-garage Ag Rupperswil Autogarage. Fahrzeuge, Zubeh\u00f6r Usw.; Handel. Tankstelle",
    "wof:placetype":"venue"
},
  "geometry": {"coordinates":[8.1343669891,47.4068107605],"type":"Point"}
}