{
  "type": "Feature",
  "properties": {
    "iso:country":"CH",
    "sg:address":"Kreuzstrasse 2",
    "sg:city":"Z\u00fcrich",
    "sg:orig_category":"Pensionskassen",
    "sg:phone":"+41 13619612",
    "sg:postcode":"8008",
    "sg:province":"Z\u00fcrich",
    "wof:name":"Personalf\u00fcrsorgestiftung Der Firma Condor Communications Ag",
    "wof:placetype":"venue"
},
  "geometry": {"coordinates":[8.5478029251,47.3623733521],"type":"Point"}
}