{
  "type": "Feature",
  "properties": {
    "iso:country":"CH",
    "sg:address":"Hiltibergstrasse 14",
    "sg:city":"Niederrohrdorf",
    "sg:orig_category":"Kaminfeger",
    "sg:phone":"+41 31 952 79 09",
    "sg:postcode":"5443",
    "sg:province":"Aargau",
    "wof:name":"Beat Von K\u00e4nel Kreiskaminfegermeister",
    "wof:placetype":"venue"
},
  "geometry": {"coordinates":[7.51811409,46.9116363525],"type":"Point"}
}