{
  "type": "Feature",
  "properties": {
    "iso:country":"CH",
    "sg:address":"Hauptstrasse 75",
    "sg:city":"Niederg\u00f6sgen",
    "sg:orig_category":"Detailhandel mit Waren verschiedener Art, Hauptrichtung Nahrungsmittel Grosshandel mit Nahrungsmitte",
    "sg:phone":"+41 62 849 13 11",
    "sg:postcode":"5013",
    "sg:province":"Solothurn",
    "wof:name":"Voramwald L.",
    "wof:placetype":"venue"
},
  "geometry": {"coordinates":[7.9886789322,47.3718299866],"type":"Point"}
}