{
  "type": "Feature",
  "properties": {
    "addr:full":"Schaffhauserstr. 136 Glattbrugg Z\u00fcrich 8152",
    "addr:housenumber":"136",
    "addr:postcode":"8152",
    "iso:country":"CH",
    "sg:address":"Schaffhauserstr. 136",
    "sg:city":"Glattbrugg",
    "sg:classifiers":[
        {
            "category":"Health Services",
            "subcategory":"Medical Lab",
            "type":"Services"
        }
    ],
    "sg:phone":"+41 4118287111",
    "sg:postcode":"8152",
    "sg:province":"Z\u00fcrich",
    "sg:tags":[
        "chemical",
        "pharmaceutical",
        "pharmacy"
    ],
    "wof:name":"Merck Sharp & Dohme-chibret Ag",
    "wof:placetype":"venue"
},
  "geometry": {"coordinates":[8.56769,47.435249],"type":"Point"}
}