{
  "type": "Feature",
  "properties": {
    "iso:country":"CH",
    "sg:address":"Bindenhausstrasse 46",
    "sg:city":"K\u00f6niz",
    "sg:orig_category":"Herstellung von Mess U Kontrollinstrumenten U vorrichtungen",
    "sg:phone":"+41 31 972 31 52",
    "sg:postcode":"3098",
    "sg:province":"Bern",
    "wof:name":"Msp Friedli & Co",
    "wof:placetype":"venue"
},
  "geometry": {"coordinates":[7.3999881744,46.9135932922],"type":"Point"}
}