{
  "type": "Feature",
  "properties": {
    "iso:country":"CH",
    "sg:address":"Rautihalde 10",
    "sg:city":"Z\u00fcrich",
    "sg:orig_category":"Sonstige Kurierdienste",
    "sg:phone":"+41 14316888",
    "sg:postcode":"8048",
    "sg:province":"Z\u00fcrich",
    "wof:name":"Z & B Vertriebs Gmbh. Zeitschriften U. B\u00fccher; Vertrieb Usw.",
    "wof:placetype":"venue"
},
  "geometry": {"coordinates":[8.4746026993,47.3877258301],"type":"Point"}
}