{
  "type": "Feature",
  "properties": {
    "iso:country":"CH",
    "sg:address":"Bernrainstrasse 57",
    "sg:city":"Kreuzlingen",
    "sg:orig_category":"Sonderschulen Wohnheime f\u00fcr Kinder U Jugendliche",
    "sg:phone":"+41 71 672 13 02",
    "sg:postcode":"8280",
    "sg:province":"Thurgau",
    "wof:name":"Sonder-schulheim Bernrain",
    "wof:placetype":"venue"
},
  "geometry": {"coordinates":[9.1602096558,47.643951416],"type":"Point"}
}