{
  "type": "Feature",
  "properties": {
    "iso:country":"CH",
    "sg:address":"Winterthurerstrasse 5",
    "sg:city":"B\u00fclach",
    "sg:orig_category":"Detailhandel mit Geschenkartikeln U Souvenirs",
    "sg:phone":"+41 18621687",
    "sg:postcode":"8180",
    "sg:province":"Z\u00fcrich",
    "wof:name":"Namaste Indian Shop Jozef & Hanny Kis",
    "wof:placetype":"venue"
},
  "geometry": {"coordinates":[8.5408477783,47.5205001831],"type":"Point"}
}