{
  "type": "Feature",
  "properties": {
    "iso:country":"CH",
    "sg:address":"Chauss\u00e9e De La Boine 2",
    "sg:city":"Neuch\u00e2tel",
    "sg:orig_category":"Arztpraxen",
    "sg:phone":"+41 32 724 72 92",
    "sg:postcode":"2000",
    "sg:province":"Neuch\u00e2tel",
    "wof:name":"Dr M\u00e9d. R\u00e9my Clottu M\u00e9decin Sp\u00e9cialiste Fmh",
    "wof:placetype":"venue"
},
  "geometry": {"coordinates":[6.929814,46.993401],"type":"Point"}
}