{
  "type": "Feature",
  "properties": {
    "iso:country":"CH",
    "sg:address":"Rue Du Coll\u00e8ge 2 1860 Aigle Case Postale 299",
    "sg:city":"Aigle",
    "sg:orig_category":"Immobilienwesen Vermietung U Verpachtung von eigenen Immobilien",
    "sg:phone":"+41 21 923 82 80",
    "sg:postcode":"1860",
    "sg:province":"Vaud",
    "wof:name":"Gtv Immob Sa",
    "wof:placetype":"venue"
},
  "geometry": {"coordinates":[6.9702548981,46.3180389404],"type":"Point"}
}