{
  "type": "Feature",
  "properties": {
    "iso:country":"CH",
    "sg:address":"Alfred-schindlerstrasse 10",
    "sg:city":"Ebikon",
    "sg:orig_category":"Herstellung von keramischen Wand U Bodenfliesen U platten",
    "sg:postcode":"6030",
    "sg:province":"Luzern",
    "wof:name":"Landhard Keramik Eberhard Roland",
    "wof:placetype":"venue"
},
  "geometry": {"coordinates":[8.3525371552,47.0867576599],"type":"Point"}
}