{
  "type": "Feature",
  "properties": {
    "iso:country":"CH",
    "sg:address":"Via Balestra 43a",
    "sg:city":"Locarno",
    "sg:orig_category":"Gartenbau",
    "sg:phone":"+41 56 493 46 08",
    "sg:postcode":"6600",
    "sg:province":"Ticino",
    "wof:name":"Diebold & Zgraggen Gartenbau Ag",
    "wof:placetype":"venue"
},
  "geometry": {"coordinates":[8.2883291245,47.4539337158],"type":"Point"}
}