{
  "type": "Feature",
  "properties": {
    "iso:country":"CH",
    "sg:address":"Ringstrasse 12",
    "sg:city":"Z\u00fcrich",
    "sg:orig_category":"Sonstige Kurierdienste",
    "sg:phone":"+41 13212000",
    "sg:postcode":"8057",
    "sg:province":"Z\u00fcrich",
    "wof:name":"I U S Widmer Gmbh",
    "wof:placetype":"venue"
},
  "geometry": {"coordinates":[8.5436573029,47.4023857117],"type":"Point"}
}