{
  "type": "Feature",
  "properties": {
    "iso:country":"CH",
    "sg:address":"Dorfstrasse 15",
    "sg:city":"Brunnadern",
    "sg:orig_category":"Nationale Postdienste",
    "sg:phone":"+41 71 374 11 44",
    "sg:postcode":"9125",
    "sg:province":"St. Gallen",
    "wof:name":"Die Schweizerische Post",
    "wof:placetype":"venue"
},
  "geometry": {"coordinates":[9.1310157776,47.3362121582],"type":"Point"}
}