{
  "type": "Feature",
  "properties": {
    "iso:country":"CH",
    "sg:address":"Eidmattstrasse 51 8000 Z\u00fcrich. Postfach 8032 Z\u00fcrich",
    "sg:city":"Zust",
    "sg:orig_category":"Unternehmensberatung",
    "sg:postcode":"32",
    "wof:name":"Domainshift Ag",
    "wof:placetype":"venue"
},
  "geometry": {"coordinates":[8.5613861084,47.3656196594],"type":"Point"}
}