{
  "type": "Feature",
  "properties": {
    "iso:country":"CH",
    "sg:address":"Bettenstrasse 63",
    "sg:city":"Allschwil",
    "sg:classifiers":[
        {
            "category":"Organizations",
            "subcategory":"Community Association",
            "type":"Services"
        }
    ],
    "sg:phone":"+41 61 481 11 80",
    "sg:postcode":"4123",
    "sg:province":"Basel-Landschaft",
    "sg:tags":[
        "box",
        "cardboard"
    ],
    "wof:name":"Schrempp Ag",
    "wof:placetype":"venue"
},
  "geometry": {"coordinates":[7.555102,47.550888],"type":"Point"}
}