{
  "type": "Feature",
  "properties": {
    "iso:country":"CH",
    "sg:address":"Rue De Clendy 25",
    "sg:city":"Yverdon-les-bains",
    "sg:classifiers":[
        {
            "category":"Travel",
            "subcategory":"Hotels & Motels",
            "type":"Entertainment"
        }
    ],
    "sg:phone":"+41 24 425 25 85",
    "sg:postcode":"1400",
    "sg:province":"Vaud",
    "sg:tags":[
        "hotels",
        "mit",
        "restaurant"
    ],
    "wof:name":"Th\u00e9venaz Gilles",
    "wof:placetype":"venue"
},
  "geometry": {"coordinates":[6.6551089287,46.7784805298],"type":"Point"}
}