{
  "type": "Feature",
  "properties": {
    "iso:country":"CH",
    "sg:address":"Tellstrasse 21",
    "sg:city":"Bellach",
    "sg:orig_category":"Instandhaltung U Reparatur von Automobilen",
    "sg:phone":"+41 32 618 18 13",
    "sg:postcode":"4512",
    "sg:province":"Solothurn",
    "wof:name":"Auto Meier",
    "wof:placetype":"venue"
},
  "geometry": {"coordinates":[7.5057940483,47.2118110657],"type":"Point"}
}