{
  "type": "Feature",
  "properties": {
    "addr:full":"Avenue De Beaulieu 35 Lausanne Vaud 1004",
    "addr:housenumber":"35",
    "addr:postcode":"1004",
    "addr:street":"Avenue De Beaulieu",
    "iso:country":"CH",
    "sg:address":"Avenue De Beaulieu 35",
    "sg:city":"Lausanne",
    "sg:classifiers":[
        {
            "category":"Organizations",
            "subcategory":"Non-profit Organization",
            "type":"Services"
        }
    ],
    "sg:phone":"+41 21 647 12 12",
    "sg:postcode":"1004",
    "sg:province":"Vaud",
    "sg:tags":[
        "alarm",
        "system"
    ],
    "wof:name":"Aa Aabicl\u00e9s Assistance 24h/24 D. Tumini",
    "wof:placetype":"venue"
},
  "geometry": {"coordinates":[6.626436,46.526283],"type":"Point"}
}