{
  "type": "Feature",
  "properties": {
    "iso:country":"CH",
    "sg:address":"Rue Des Gorges 26 2738 Court Case Postale 38",
    "sg:city":"Court",
    "sg:orig_category":"Mechanik Mechanische Werkst\u00e4tten",
    "sg:phone":"+41 32 497 94 19",
    "sg:postcode":"2738",
    "sg:province":"Bern",
    "wof:name":"Andr\u00e9 Frei & Fils Sa Atelier De M\u00e9canique",
    "wof:placetype":"venue"
},
  "geometry": {"coordinates":[7.345138073,47.2422180176],"type":"Point"}
}