{
  "type": "Feature",
  "properties": {
    "iso:country":"CH",
    "sg:address":"Frohburgstrasse 130",
    "sg:city":"Z\u00fcrich",
    "sg:orig_category":"Non-Classified Establishments",
    "sg:postcode":"8057",
    "sg:province":"Z\u00fcrich",
    "wof:name":"H & V Strategic Consulting Ag",
    "wof:placetype":"venue"
},
  "geometry": {"coordinates":[8.5517196655,47.3949317932],"type":"Point"}
}