{
  "type": "Feature",
  "properties": {
    "iso:country":"CH",
    "sg:address":"Rte Des Pr\u00e9alpes 38",
    "sg:city":"Bourguillon",
    "sg:orig_category":"Herstellung von Konstruktionsteilen, Fertigbauteilen U Ausbauelementen aus Holz",
    "sg:postcode":"1722",
    "sg:province":"Fribourg",
    "wof:name":"Oberson & Fils Sa",
    "wof:placetype":"venue"
},
  "geometry": {"coordinates":[7.1759600639,46.8003311157],"type":"Point"}
}