{
  "type": "Feature",
  "properties": {
    "addr:full":"Schosshaldenstrasse 22 Bern Bern 3006",
    "addr:housenumber":"22",
    "addr:postcode":"3006",
    "addr:street":"Schosshaldenstrasse",
    "iso:country":"CH",
    "sg:address":"Schosshaldenstrasse 22",
    "sg:city":"Bern",
    "sg:classifiers":[
        {
            "category":"Professional",
            "subcategory":"Advertising",
            "type":"Services"
        }
    ],
    "sg:phone":"+41 31 971 02 72",
    "sg:postcode":"3006",
    "sg:province":"Bern",
    "sg:tags":[
        "agency"
    ],
    "wof:name":"Schott Merz Werbeagentur",
    "wof:placetype":"venue"
},
  "geometry": {"coordinates":[7.464283,46.946194],"type":"Point"}
}