{
  "type": "Feature",
  "properties": {
    "iso:country":"CH",
    "sg:address":"Morgartenstrasse 6 6003 Luzern. Postfach",
    "sg:city":"Luzern",
    "sg:orig_category":"Interessenvertretungen",
    "sg:postcode":"6003",
    "sg:province":"Luzern",
    "wof:name":"Impuls Begegnungszentren F. Jugendliche Usw",
    "wof:placetype":"venue"
},
  "geometry": {"coordinates":[8.3079223633,47.049118042],"type":"Point"}
}