{
  "type": "Feature",
  "properties": {
    "iso:country":"CH",
    "sg:address":"Heimstrasse 46",
    "sg:city":"Dietikon",
    "sg:orig_category":"Unclassifiable Establishments",
    "sg:phone":"+41 17733200",
    "sg:postcode":"8953",
    "sg:province":"Z\u00fcrich",
    "wof:name":"Sprinx Ag",
    "wof:placetype":"venue"
},
  "geometry": {"coordinates":[8.4010400772,47.4136657715],"type":"Point"}
}