{
  "type": "Feature",
  "properties": {
    "iso:country":"CH",
    "sg:address":"Hofstrasse 1",
    "sg:city":"Luzern",
    "sg:orig_category":"Unclassifiable Establishments",
    "sg:postcode":"6004",
    "sg:province":"Luzern",
    "wof:name":"Dr.med.loretta Barbara Marques Spezial\u00e4rztin Fmh",
    "wof:placetype":"venue"
},
  "geometry": {"coordinates":[8.3107995987,47.0560760498],"type":"Point"}
}