{
  "type": "Feature",
  "properties": {
    "iso:country":"CH",
    "sg:address":"Mategnin Avenue De 21 1217 Meyrin. Postfach",
    "sg:city":"Meyrin",
    "sg:classifiers":[
        {
            "category":"Travel",
            "subcategory":"Hotels & Motels",
            "type":"Entertainment"
        }
    ],
    "sg:phone":"+41 22 989 90 00",
    "sg:postcode":"1217",
    "sg:province":"Gen\u00e8ve",
    "sg:tags":[
        "hotels",
        "mit",
        "restaurant"
    ],
    "wof:name":"Golden Tulip H\u00f4tel Exploitation Gen\u00e8ve Sa H\u00f4tels, Restaurants, Bars, Notamm. D'h\u00f4tels Du Groupe Golden Tulip Etc",
    "wof:placetype":"venue"
},
  "geometry": {"coordinates":[6.0722160339,46.2284431458],"type":"Point"}
}