{
  "type": "Feature",
  "properties": {
    "iso:country":"CH",
    "sg:address":"Rifertstrasse 27",
    "sg:city":"Adliswil",
    "sg:orig_category":"Erbringung von Dienstleistungen f\u00fcr Unternehmen",
    "sg:phone":"+41 17109423",
    "sg:postcode":"8134",
    "sg:province":"Z\u00fcrich",
    "wof:name":"Fdc Crameri F.d.",
    "wof:placetype":"venue"
},
  "geometry": {"coordinates":[8.5348711014,47.3098564148],"type":"Point"}
}