{
  "type": "Feature",
  "properties": {
    "iso:country":"CH",
    "sg:address":"Route D`italie 37",
    "sg:city":"Sion",
    "sg:orig_category":"Handel mit Automobilen",
    "sg:phone":"+41 17820202",
    "sg:postcode":"1951",
    "sg:province":"Valais",
    "wof:name":"Smart Satellit W\u00e4denswil Autostern W\u00e4denswil Ag",
    "wof:placetype":"venue"
},
  "geometry": {"coordinates":[8.6493587494,47.2459144592],"type":"Point"}
}