{
  "type": "Feature",
  "properties": {
    "iso:country":"CH",
    "sg:address":"Riedsortstrasse 31",
    "sg:city":"Weggis",
    "sg:orig_category":"Innenarchitekturb\u00fcros",
    "sg:phone":"+41 41 240 32 32",
    "sg:postcode":"6353",
    "sg:province":"Luzern",
    "wof:name":"Lisbeth L\u00fc\u00f6nd Innenarchitektur",
    "wof:placetype":"venue"
},
  "geometry": {"coordinates":[8.4569826126,47.0253448486],"type":"Point"}
}