{
  "type": "Feature",
  "properties": {
    "iso:country":"CH",
    "sg:address":"Chemin Fran\u00e7ois-chavaz 121a",
    "sg:city":"Onex",
    "sg:orig_category":"Unclassifiable Establishments",
    "sg:postcode":"1213",
    "sg:province":"Gen\u00e8ve",
    "wof:name":"Bta Sa Agence De Gen\u00e8ve",
    "wof:placetype":"venue"
},
  "geometry": {"coordinates":[6.0941929817,46.1878471375],"type":"Point"}
}