{
  "type": "Feature",
  "properties": {
    "iso:country":"CH",
    "sg:address":"H\u00e4ldelistrasse 13b",
    "sg:city":"Neerach",
    "sg:orig_category":"Fahrschulen, Flugschulen",
    "sg:phone":"+41 79 446 25 74",
    "sg:postcode":"8173",
    "sg:province":"Z\u00fcrich",
    "wof:name":"Peter Biner Autofahrschule",
    "wof:placetype":"venue"
},
  "geometry": {"coordinates":[7.8021011353,46.1756629944],"type":"Point"}
}