{
  "type": "Feature",
  "properties": {
    "iso:country":"CH",
    "sg:address":"Langweidstrasse 4",
    "sg:city":"St.gallen",
    "sg:orig_category":"Sportschulen Ski-& Snowboardschulen",
    "sg:phone":"+41 81 833 33 32",
    "sg:postcode":"9000",
    "sg:province":"St. Gallen",
    "wof:name":"Suvretta Ski-& Snowboardschule",
    "wof:placetype":"venue"
},
  "geometry": {"coordinates":[9.8196649551,46.485080719],"type":"Point"}
}