{
  "type": "Feature",
  "properties": {
    "iso:country":"CH",
    "sg:address":"Hauptstrasse 3",
    "sg:city":"Niederg\u00f6sgen",
    "sg:orig_category":"Herstellung von Teppichen Verlegen von Fussboden",
    "sg:phone":"+41 62 849 15 49",
    "sg:postcode":"5013",
    "sg:province":"Solothurn",
    "wof:name":"Meier Andreas Bodenbel\u00e4ge + Bettwaren Ag",
    "wof:placetype":"venue"
},
  "geometry": {"coordinates":[7.9971132278,47.3726997375],"type":"Point"}
}