{
  "type": "Feature",
  "properties": {
    "iso:country":"CH",
    "sg:address":"6033 Buchrain. Postfach 136",
    "sg:city":"Buchrain",
    "sg:orig_category":"Sportvereine Ballsport Fussball",
    "sg:phone":"+41 41 450 36 76",
    "sg:postcode":"6033",
    "sg:province":"Luzern",
    "wof:name":"Fc Perlen-buchrain",
    "wof:placetype":"venue"
},
  "geometry": {"coordinates":[8.3468999863,47.1015892029],"type":"Point"}
}