{
  "type": "Feature",
  "properties": {
    "iso:country":"CH",
    "sg:address":"Bl\u00fcemenen",
    "sg:city":"Einsiedeln",
    "sg:orig_category":"Herstellung von sonstigen elektrischen Ausr\u00fcstungen",
    "sg:phone":"+41 21 320 07 00",
    "sg:postcode":"8840",
    "sg:province":"Schwyz",
    "wof:name":"Gumy \u00e9lectronic.",
    "wof:placetype":"venue"
},
  "geometry": {"coordinates":[6.5943989754,46.5326805115],"type":"Point"}
}