{
  "type": "Feature",
  "properties": {
    "iso:country":"CH",
    "sg:address":"Sch\u00f6nenbuchstrasse 14",
    "sg:city":"Basel",
    "sg:orig_category":"Gartenbau",
    "sg:phone":"+41 61 303 04 14",
    "sg:postcode":"4055",
    "sg:province":"Basel-Stadt",
    "wof:name":"Garten-walther Gartenbau",
    "wof:placetype":"venue"
},
  "geometry": {"coordinates":[7.5712480545,47.5581359863],"type":"Point"}
}