{
  "type": "Feature",
  "properties": {
    "addr:full":"Dorf R\u00fceggisberg Bern 3088",
    "addr:postcode":"3088",
    "addr:street":"Dorf",
    "iso:country":"CH",
    "sg:address":"Dorf",
    "sg:city":"R\u00fceggisberg",
    "sg:orig_category":"Detailhandel mit Brot, Back U S\u00fcsswaren",
    "sg:phone":"+41 31 809 03 12",
    "sg:postcode":"3088",
    "sg:province":"Bern",
    "wof:name":"Heiniger Ulrich, B\u00e4ckerei-lebensmittel",
    "wof:placetype":"venue"
},
  "geometry": {"coordinates":[7.438045,46.822205],"type":"Point"}
}