{
  "type": "Feature",
  "properties": {
    "iso:country":"CH",
    "sg:address":"M\u00f6sliweg 6",
    "sg:city":"Spiez",
    "sg:classifiers":[
        {
            "category":"Insurance",
            "subcategory":"Insurance Agent",
            "type":"Services"
        }
    ],
    "sg:phone":"+41 33 654 04 04",
    "sg:postcode":"3700",
    "sg:province":"Bern",
    "sg:tags":[
        "versicherungsagenturen",
        "-broker"
    ],
    "wof:name":"St\u00f6cklimatt Ag",
    "wof:placetype":"venue"
},
  "geometry": {"coordinates":[7.6828351021,46.6903381348],"type":"Point"}
}