{
  "type": "Feature",
  "properties": {
    "iso:country":"CH",
    "sg:address":"F\u00fcllerichstrasse 51",
    "sg:city":"G\u00fcmligen",
    "sg:orig_category":"Offsetdruck Sonstiges Druckgewerbe",
    "sg:phone":"+41 31 951 24 93",
    "sg:postcode":"3073",
    "sg:province":"Bern",
    "wof:name":"Kr\u00e4mer.",
    "wof:placetype":"venue"
},
  "geometry": {"coordinates":[7.503013134,46.9321403503],"type":"Point"}
}