{
  "type": "Feature",
  "properties": {
    "iso:country":"CH",
    "sg:address":"Brunnmattstrasse 34 3007 Bern. Postfach",
    "sg:city":"Bern",
    "sg:orig_category":"Fachdetailhandel in Verkaufsr\u00e4umen",
    "sg:postcode":"3005",
    "sg:province":"Bern",
    "wof:name":"Handarbeits-ch\u00e4mmerli, Hofer M. & R. Strickgarn, Mercerieartikel, Modebekleidung Usw; Handel",
    "wof:placetype":"venue"
},
  "geometry": {"coordinates":[7.4269990921,46.9440956116],"type":"Point"}
}