{
  "type": "Feature",
  "properties": {
    "iso:country":"CH",
    "sg:address":"Pumpwerkstrasse 23",
    "sg:city":"Regensdorf",
    "sg:orig_category":"Herstellung von elektronischen Bauelementen",
    "sg:postcode":"8105",
    "sg:province":"Z\u00fcrich",
    "wof:name":"Crystal Display Electronics Ag",
    "wof:placetype":"venue"
},
  "geometry": {"coordinates":[8.7577753067,47.2063064575],"type":"Point"}
}