{
  "type": "Feature",
  "properties": {
    "iso:country":"CH",
    "sg:address":"Im D\u00f6rfli 14",
    "sg:city":"Meilen",
    "sg:orig_category":"Schiffsbau ohne Boots U Yachtbau",
    "sg:phone":"+41 19806042",
    "sg:postcode":"8706",
    "sg:province":"Z\u00fcrich",
    "wof:name":"Bootscharter Fridolin Ag",
    "wof:placetype":"venue"
},
  "geometry": {"coordinates":[8.66410923,47.2635536194],"type":"Point"}
}