{
  "type": "Feature",
  "properties": {
    "iso:country":"CH",
    "sg:address":"Hardstrasse 35",
    "sg:city":"Z\u00fcrich",
    "sg:orig_category":"Reparatur von elektrischen Haushaltsger\u00e4ten",
    "sg:phone":"+41 14933215",
    "sg:postcode":"8004",
    "sg:province":"Z\u00fcrich",
    "wof:name":"Wima Mattle Gmbh Waagen & Aufschnittmaschinen",
    "wof:placetype":"venue"
},
  "geometry": {"coordinates":[8.5112304688,47.3793067932],"type":"Point"}
}