{
  "type": "Feature",
  "properties": {
    "iso:country":"CH",
    "sg:address":"Amriswiler Strasse 51",
    "sg:city":"Sitterdorf",
    "sg:orig_category":"Detailhandel mit Fleisch U Fleischwaren Grosshandel mit lebenden Tieren",
    "sg:phone":"+41 71 245 69 25",
    "sg:postcode":"8589",
    "sg:province":"Thurgau",
    "wof:name":"Baumgartner Sebastian",
    "wof:placetype":"venue"
},
  "geometry": {"coordinates":[9.392074585,47.4361152649],"type":"Point"}
}