{
  "type": "Feature",
  "properties": {
    "iso:country":"CH",
    "sg:address":"S\u00e4ntisstrasse 39 8580 Amriswil. Postfach 1462",
    "sg:city":"Amriswil",
    "sg:orig_category":"Grosshandel mit Getreide, Saatgut U Futtermitteln",
    "sg:phone":"+41 71 411 23 91",
    "sg:postcode":"8580",
    "sg:province":"Thurgau",
    "wof:name":"Keller Kurt Ag Amriswil",
    "wof:placetype":"venue"
},
  "geometry": {"coordinates":[9.3071012497,47.5454940796],"type":"Point"}
}