{
  "type": "Feature",
  "properties": {
    "iso:country":"CH",
    "sg:address":"L\u00e4ndliweg 26",
    "sg:city":"W\u00fcrenlos",
    "sg:orig_category":"Unclassifiable Establishments",
    "sg:postcode":"5436",
    "sg:province":"Aargau",
    "wof:name":"Imagepoint Ag",
    "wof:placetype":"venue"
},
  "geometry": {"coordinates":[8.3669042587,47.440158844],"type":"Point"}
}