{
  "type": "Feature",
  "properties": {
    "iso:country":"CH",
    "sg:address":"1689",
    "sg:city":"Ch\u00e2telard-p-romont",
    "sg:orig_category":"Landesverteidigung, Sozialversicherung \u00d6ffentliche Verwaltung",
    "sg:phone":"+41 26 652 23 74",
    "sg:postcode":"1689",
    "sg:province":"Fribourg",
    "wof:name":"Centre De Protection Civile",
    "wof:placetype":"venue"
},
  "geometry": {"coordinates":[-81.1041717529,38.1812782288],"type":"Point"}
}