{
  "type": "Feature",
  "properties": {
    "iso:country":"CH",
    "sg:address":"Industriering 8 3250 Lyss. Postfach",
    "sg:city":"Lyss",
    "sg:orig_category":"Verwaltung von Immobilien",
    "sg:postcode":"3250",
    "sg:province":"Bern",
    "wof:name":"Hl Immobilien Ag",
    "wof:placetype":"venue"
},
  "geometry": {"coordinates":[7.3061118126,47.0854606628],"type":"Point"}
}