{
  "type": "Feature",
  "properties": {
    "iso:country":"CH",
    "sg:address":"Kirchweg 24",
    "sg:city":"Beckenried",
    "sg:orig_category":"Sanit\u00e4r, Heizungs U L\u00fcftungsinstallation",
    "sg:phone":"+41 41 620 66 33",
    "sg:postcode":"6375",
    "sg:province":"Nidwalden",
    "wof:name":"Josef Murer Gmbh",
    "wof:placetype":"venue"
},
  "geometry": {"coordinates":[8.4727239609,46.9664573669],"type":"Point"}
}