{
  "type": "Feature",
  "properties": {
    "iso:country":"CH",
    "sg:address":"Wassbergstrasse 28 Forch 8124 Maur. Postfach",
    "sg:city":"Forch",
    "sg:orig_category":"Architektur U Ingenieurb\u00fcros",
    "sg:postcode":"8127",
    "sg:province":"Z\u00fcrich",
    "wof:name":"Main Gmbh",
    "wof:placetype":"venue"
},
  "geometry": {"coordinates":[8.667613,47.340317],"type":"Point"}
}