{
  "type": "Feature",
  "properties": {
    "iso:country":"CH",
    "sg:address":"M\u00fcnstergasse 18a",
    "sg:city":"Z\u00fcrich",
    "sg:orig_category":"Non-Classified Establishments",
    "sg:postcode":"8001",
    "sg:province":"Z\u00fcrich",
    "wof:name":"Burkhard Ernst Gartengestaltung",
    "wof:placetype":"venue"
},
  "geometry": {"coordinates":[7.5096597672,46.9278717041],"type":"Point"}
}