{
  "type": "Feature",
  "properties": {
    "addr:full":"Chemin Des Clochettes 14 1200 Genf. Postfach Gen\u00e8ve Gen\u00e8ve 1201",
    "addr:housenumber":"14",
    "addr:postcode":"1200 genf. postfach;1201",
    "addr:street":"Chemin Des Clochettes",
    "iso:country":"CH",
    "sg:address":"Chemin Des Clochettes 14 1200 Genf. Postfach",
    "sg:city":"Gen\u00e8ve",
    "sg:orig_category":"Datenbanken",
    "sg:postcode":"1201",
    "sg:province":"Gen\u00e8ve",
    "wof:name":"Poloreve Inc, New York (usa), Succursale De Gen\u00e8ve",
    "wof:placetype":"venue"
},
  "geometry": {"coordinates":[6.158637,46.188534],"type":"Point"}
}