{
  "type": "Feature",
  "properties": {
    "iso:country":"CH",
    "sg:address":"Hauptstrasse",
    "sg:city":"K\u00fcttigkofen",
    "sg:orig_category":"Primarschulen",
    "sg:phone":"+41 32 677 18 30",
    "sg:postcode":"4581",
    "sg:province":"Solothurn",
    "wof:name":"Primarschule",
    "wof:placetype":"venue"
},
  "geometry": {"coordinates":[7.5206341743,47.1533164978],"type":"Point"}
}