{
  "type": "Feature",
  "properties": {
    "iso:country":"CH",
    "sg:address":"Aufhofen 27",
    "sg:city":"Thundorf",
    "sg:orig_category":"Aktivit\u00e4ten der Generalunternehmen im Baugewerbe Allgemeiner Hoch U Tiefbau",
    "sg:phone":"+41 21 866 78 54",
    "sg:postcode":"8512",
    "sg:province":"Thurgau",
    "wof:name":"Erbat S\u00e0rl Entreprise G\u00e9n.du B\u00e2timent",
    "wof:placetype":"venue"
},
  "geometry": {"coordinates":[6.513232,46.658756],"type":"Point"}
}