{
  "type": "Feature",
  "properties": {
    "iso:country":"CH",
    "sg:address":"Kreuzbuchstrasse 27",
    "sg:city":"Luzern",
    "sg:orig_category":"Fotografisches Gewerbe U fotografische Laboratorien",
    "sg:postcode":"6006",
    "sg:province":"Luzern",
    "wof:name":"Koch Josef, Fachphotograph, Photo-studio 9.",
    "wof:placetype":"venue"
},
  "geometry": {"coordinates":[8.332654953,47.0549125671],"type":"Point"}
}