{
  "type": "Feature",
  "properties": {
    "iso:country":"CH",
    "sg:address":"Anwachs",
    "sg:city":"Muolen",
    "sg:orig_category":"Grosshandel mit lebenden Tieren",
    "sg:phone":"+41 71 411 57 77",
    "sg:postcode":"9313",
    "sg:province":"St. Gallen",
    "wof:name":"Gut Arnold",
    "wof:placetype":"venue"
},
  "geometry": {"coordinates":[9.3268699646,47.5196647644],"type":"Point"}
}