{
  "type": "Feature",
  "properties": {
    "iso:country":"CH",
    "sg:address":"Quadratscha 1",
    "sg:city":"Samedan",
    "sg:orig_category":"F\u00fcrsorge\u00e4mter",
    "sg:phone":"+41 81 852 56 39",
    "sg:postcode":"7503",
    "sg:province":"Graubunden",
    "wof:name":"Amtsvormundschaft Engadin, Bergell, M\u00fcnstertal",
    "wof:placetype":"venue"
},
  "geometry": {"coordinates":[9.8735370636,46.5364875793],"type":"Point"}
}