{
  "type": "Feature",
  "properties": {
    "iso:country":"CH",
    "sg:address":"Blattenstrasse 14",
    "sg:city":"Naters",
    "sg:orig_category":"Architektur U Ingenieurb\u00fcros",
    "sg:phone":"+41 71 463 31 35",
    "sg:postcode":"3904",
    "sg:province":"Valais",
    "wof:name":"Vwr Ingenieure Ag",
    "wof:placetype":"venue"
},
  "geometry": {"coordinates":[9.377797,47.564186],"type":"Point"}
}