{
  "type": "Feature",
  "properties": {
    "iso:country":"CH",
    "sg:address":"Dorfstrasse 36",
    "sg:city":"H\u00fcntwangen",
    "sg:orig_category":"Innenarchitekturb\u00fcros",
    "sg:phone":"+41 18690438",
    "sg:postcode":"8194",
    "sg:province":"Z\u00fcrich",
    "wof:name":"Robert R\u00fcsch Innenarchitektur",
    "wof:placetype":"venue"
},
  "geometry": {"coordinates":[8.4937286377,47.5951576233],"type":"Point"}
}