{
  "type": "Feature",
  "properties": {
    "iso:country":"CH",
    "sg:address":"H\u00f6henweg 39",
    "sg:city":"Uetendorf",
    "sg:orig_category":"Sonstiger Grosshandel",
    "sg:postcode":"3661",
    "sg:province":"Bern",
    "wof:name":"Neptun Gmbh",
    "wof:placetype":"venue"
},
  "geometry": {"coordinates":[9.8181848526,46.7882270813],"type":"Point"}
}