{
  "type": "Feature",
  "properties": {
    "iso:country":"CH",
    "sg:address":"Rue Ch\u00e2tellenie 4",
    "sg:city":"St-blaise",
    "sg:orig_category":"Wasserversorgung",
    "sg:phone":"+41 32 753 73 07",
    "sg:postcode":"2072",
    "sg:province":"Neuch\u00e2tel",
    "wof:name":"Watcotec Sa",
    "wof:placetype":"venue"
},
  "geometry": {"coordinates":[6.9897799492,47.0144309998],"type":"Point"}
}