{
  "type": "Feature",
  "properties": {
    "iso:country":"CH",
    "sg:address":"Via Trevani 1",
    "sg:city":"Locarno",
    "sg:orig_category":"Herstellung von Metallkonstruktionen Mechanische Werkst\u00e4tten",
    "sg:phone":"+41 91 751 19 57",
    "sg:postcode":"6600",
    "sg:province":"Ticino",
    "wof:name":"Filomarino Succ.a Guido Crotta Costruzioni In Ferro",
    "wof:placetype":"venue"
},
  "geometry": {"coordinates":[8.7967605591,46.1689987183],"type":"Point"}
}