{
  "type": "Feature",
  "properties": {
    "iso:country":"CH",
    "sg:address":"Prieur\u00e9 Rue Du 32 1202 Gen\u00e8ve. Postfach",
    "sg:city":"Gen\u00e8ve",
    "sg:orig_category":"Herstellung von sonstigen elektrischen Ausr\u00fcstungen",
    "sg:postcode":"1202",
    "sg:province":"Gen\u00e8ve",
    "wof:name":"Electro-detect Sa. Automation Et Construction D'appareils \u00e9lectriques Et \u00e9lectroniques",
    "wof:placetype":"venue"
},
  "geometry": {"coordinates":[6.9035048485,46.982749939],"type":"Point"}
}