{
  "type": "Feature",
  "properties": {
    "iso:country":"CH",
    "sg:address":"Chemin Des Esserts 6 1279 Bogis-bossey. Postfach",
    "sg:city":"Bogis-bossey",
    "sg:orig_category":"Finanzierungsinstitutionen",
    "sg:postcode":"1279",
    "sg:province":"Vaud",
    "wof:name":"Europeiska F\u00f6rs\u00e4kringsm\u00e4klarna Sa",
    "wof:placetype":"venue"
},
  "geometry": {"coordinates":[6.1662039757,46.3506813049],"type":"Point"}
}