{
  "type": "Feature",
  "properties": {
    "iso:country":"CH",
    "sg:address":"Breitmattboden 25",
    "sg:city":"Gipf-oberfrick",
    "sg:orig_category":"Grosshandel mit B\u00fcromaschinen U einrichtungen",
    "sg:phone":"+41 62 871 08 08",
    "sg:postcode":"5073",
    "sg:province":"Aargau",
    "wof:name":"Schenker Enterprise",
    "wof:placetype":"venue"
},
  "geometry": {"coordinates":[8.0042333603,47.5017166138],"type":"Point"}
}