{
  "type": "Feature",
  "properties": {
    "addr:full":"Rue Cr\u00eat-georges 28 Tramelan Bern 2720",
    "addr:housenumber":"28",
    "addr:postcode":"2720",
    "addr:street":"Rue Cre\u0302T-Georges",
    "iso:country":"CH",
    "sg:address":"Rue Cr\u00eat-georges 28",
    "sg:city":"Tramelan",
    "sg:orig_category":"Bau U Wohngenossenschaften",
    "sg:postcode":"2720",
    "sg:province":"Bern",
    "wof:name":"Coop.d'habitation Cr\u00eat-georges",
    "wof:placetype":"venue"
},
  "geometry": {"coordinates":[7.107995,47.224621],"type":"Point"}
}