{
  "type": "Feature",
  "properties": {
    "iso:country":"CH",
    "sg:address":"Rue Du Lac 18",
    "sg:city":"Vevey",
    "sg:orig_category":"Detailhandel mit Geschenkartikeln U Souvenirs",
    "sg:phone":"+41 71 755 19 65",
    "sg:postcode":"1800",
    "sg:province":"Vaud",
    "wof:name":"Dominika Keel Boutique Gwundernase",
    "wof:placetype":"venue"
},
  "geometry": {"coordinates":[9.5393886566,47.3781204224],"type":"Point"}
}