{
  "type": "Feature",
  "properties": {
    "iso:country":"CH",
    "sg:address":"Ch. Du Levant 100",
    "sg:city":"Lausanne",
    "sg:classifiers":[
        {
            "category":"Shopping",
            "subcategory":"Crafts & Fabrics",
            "type":"Retail Goods"
        }
    ],
    "sg:phone":"+41 21 728 36 71",
    "sg:postcode":"1005",
    "sg:province":"Vaud",
    "sg:tags":[
        "textile",
        "clothing"
    ],
    "wof:name":"Unitrac Sa",
    "wof:placetype":"venue"
},
  "geometry": {"coordinates":[6.652016,46.517006],"type":"Point"}
}