{
  "type": "Feature",
  "properties": {
    "iso:country":"CH",
    "sg:address":"3940",
    "sg:city":"Steg",
    "sg:classifiers":[
        {
            "category":"Utilities",
            "subcategory":"Electric",
            "type":"Services"
        }
    ],
    "sg:phone":"+41 27 933 71 00",
    "sg:postcode":"3940",
    "sg:province":"Valais",
    "sg:tags":[
        "electricity",
        "raw",
        "energy",
        "material"
    ],
    "wof:name":"Kraftwerk L\u00d6tschen Ag",
    "wof:placetype":"venue"
},
  "geometry": {"coordinates":[7.7464599609,46.3153114319],"type":"Point"}
}