{
  "type": "Feature",
  "properties": {
    "iso:country":"CH",
    "sg:address":"6981",
    "sg:city":"Bedigliora",
    "sg:orig_category":"Primarschulen",
    "sg:phone":"+41 91 608 18 28",
    "sg:postcode":"6981",
    "sg:province":"Ticino",
    "wof:name":"Scuola Elementare Consortile",
    "wof:placetype":"venue"
},
  "geometry": {"coordinates":[8.8408298492,46.0080795288],"type":"Point"}
}