{
  "type": "Feature",
  "properties": {
    "iso:country":"CH",
    "sg:address":"Chasa Suldanella",
    "sg:city":"Zernez",
    "sg:orig_category":"Kunsthandel Verlagsgewerbe",
    "sg:phone":"+41 828281595",
    "sg:postcode":"7530",
    "sg:province":"Graubunden",
    "wof:name":"Kunstverlag Mirer",
    "wof:placetype":"venue"
},
  "geometry": {"coordinates":[10.0946302414,46.7002983093],"type":"Point"}
}