{
  "type": "Feature",
  "properties": {
    "iso:country":"CH",
    "sg:address":"Serocca",
    "sg:city":"Bioggio",
    "sg:orig_category":"Mechanische Werkst\u00e4tten",
    "sg:phone":"+41 79 605 11 13",
    "sg:postcode":"6934",
    "sg:province":"Ticino",
    "wof:name":"Fabar Sa Riparazione Macchine Per Caff\u00e9",
    "wof:placetype":"venue"
},
  "geometry": {"coordinates":[8.9086551666,46.0143966675],"type":"Point"}
}