{
  "type": "Feature",
  "properties": {
    "iso:country":"CH",
    "sg:address":"Eigerweg 16 3073 G\u00fcmligen. Postfach 10",
    "sg:city":"G\u00fcmligen",
    "sg:orig_category":"Grosshandel mit Radio U Fernsehger\u00e4ten",
    "sg:phone":"+41 41 360 55 45",
    "sg:postcode":"3073",
    "sg:province":"Bern",
    "wof:name":"Trading Point Ag",
    "wof:placetype":"venue"
},
  "geometry": {"coordinates":[8.3324298859,47.0359840393],"type":"Point"}
}