{
  "type": "Feature",
  "properties": {
    "iso:country":"CH",
    "sg:address":"Zimmerlistrasse 3 4663 Aarburg. Postfach 12",
    "sg:city":"Aarburg",
    "sg:orig_category":"RESTAURANTS: TEA-ROOMS",
    "sg:phone":"+41 62 791 32 21",
    "sg:postcode":"4663",
    "sg:province":"Aargau",
    "wof:name":"Erni Beatrix, Rest. Bahnhof",
    "wof:placetype":"venue"
},
  "geometry": {"coordinates":[7.9079771042,47.3198623657],"type":"Point"}
}