{
  "type": "Feature",
  "properties": {
    "iso:country":"CH",
    "sg:address":"2515",
    "sg:city":"Pr\u00eales",
    "sg:orig_category":"Vereine Musik/Blasmusik",
    "sg:postcode":"2515",
    "sg:province":"Bern",
    "wof:name":"Fanfare Harmonie",
    "wof:placetype":"venue"
},
  "geometry": {"coordinates":[-112.009475708,43.5343589783],"type":"Point"}
}