{
  "type": "Feature",
  "properties": {
    "iso:country":"CH",
    "sg:address":"Fabourg Saint-germain 32",
    "sg:city":"Porrentruy",
    "sg:orig_category":"Architektur U Ingenieurb\u00fcros Architekturb\u00fcros",
    "sg:phone":"+41 17611701",
    "sg:postcode":"2900",
    "sg:province":"Jura",
    "wof:name":"Lesco Control Ag",
    "wof:placetype":"venue"
},
  "geometry": {"coordinates":[8.439562,47.275948],"type":"Point"}
}