{
  "type": "Feature",
  "properties": {
    "iso:country":"CH",
    "sg:address":"Grand-rue 74",
    "sg:city":"Lutry",
    "sg:orig_category":"Detailhandel mit Fleisch U Fleischwaren",
    "sg:phone":"+41 21 791 14 03",
    "sg:postcode":"1095",
    "sg:province":"Vaud",
    "wof:name":"Gay Olivier",
    "wof:placetype":"venue"
},
  "geometry": {"coordinates":[6.6868019104,46.501953125],"type":"Point"}
}