{
  "type": "Feature",
  "properties": {
    "iso:country":"CH",
    "sg:address":"8024",
    "sg:city":"Z\u00fcrich",
    "sg:orig_category":"Non-Classified Establishments",
    "sg:postcode":"8024",
    "sg:province":"Z\u00fcrich",
    "wof:name":"Zofam Immo Gmbh",
    "wof:placetype":"venue"
},
  "geometry": {"coordinates":[9.6317558289,47.4314804077],"type":"Point"}
}