{
  "type": "Feature",
  "properties": {
    "iso:country":"CH",
    "sg:address":"Schrofenstrasse 2",
    "sg:city":"Amriswil",
    "sg:orig_category":"Vermietung von Automobilen",
    "sg:phone":"+41 71 411 51 51",
    "sg:postcode":"8580",
    "sg:province":"Thurgau",
    "wof:name":"Hans-peter Allemann Autovermietung",
    "wof:placetype":"venue"
},
  "geometry": {"coordinates":[9.2750062943,47.5448417664],"type":"Point"}
}