{
  "type": "Feature",
  "properties": {
    "iso:country":"CH",
    "sg:address":"Hohlstrasse 90 8004 Z\u00fcrich. Postfach",
    "sg:city":"Z\u00fcrich",
    "sg:orig_category":"Detailhandel mit Fleisch U Fleischwaren",
    "sg:postcode":"8004",
    "sg:province":"Z\u00fcrich",
    "wof:name":"Carmelo Russo, Metzgerei & Fischhandel",
    "wof:placetype":"venue"
},
  "geometry": {"coordinates":[8.5233268738,47.3786888123],"type":"Point"}
}