{
  "type": "Feature",
  "properties": {
    "iso:country":"CH",
    "sg:address":"En Cotty",
    "sg:city":"Montagny-yverdon",
    "sg:orig_category":"Detailhandel mit M\u00f6beln U Haushaltsgegenst\u00e4nden Grosshandel mit M\u00f6beln, Wohnbedarf, Teppichen U Bode",
    "sg:phone":"+41 24 446 25 33",
    "sg:postcode":"1442",
    "sg:province":"Vaud",
    "wof:name":"Puksar Branko",
    "wof:placetype":"venue"
},
  "geometry": {"coordinates":[6.6118950844,46.7916183472],"type":"Point"}
}