{
  "type": "Feature",
  "properties": {
    "iso:country":"CH",
    "sg:address":"Plaine Route De La 20 1026 Denges. Postfach",
    "sg:city":"Denges",
    "sg:orig_category":"Instandhaltung U Reparatur von Automobilen",
    "sg:postcode":"1026",
    "sg:province":"Vaud",
    "wof:name":"Rossier Paul-michel",
    "wof:placetype":"venue"
},
  "geometry": {"coordinates":[6.5408301353,46.534286499],"type":"Point"}
}