{
  "type": "Feature",
  "properties": {
    "iso:country":"CH",
    "sg:address":"Hofmatt",
    "sg:city":"Belpberg",
    "sg:orig_category":"Sportvereine Eissport Eishockey",
    "sg:phone":"+41 31 819 42 87",
    "sg:postcode":"3124",
    "sg:province":"Bern",
    "wof:name":"Eishockey-club Rubigen",
    "wof:placetype":"venue"
},
  "geometry": {"coordinates":[7.5248308182,46.8729095459],"type":"Point"}
}