{
  "type": "Feature",
  "properties": {
    "iso:country":"CH",
    "sg:address":"Im Niederholzboden 2",
    "sg:city":"Riehen",
    "sg:orig_category":"Grosshandel mit Nahrungsmitteln, Getr\u00e4nken U Tabakwaren ohne ausgepr\u00e4gten Schwerpunkt",
    "sg:phone":"+41 61 601 14 82",
    "sg:postcode":"4125",
    "sg:province":"Basel-Stadt",
    "wof:name":"Melsa Lebensmittel-markt Gmbh",
    "wof:placetype":"venue"
},
  "geometry": {"coordinates":[7.6359667778,47.5759124756],"type":"Point"}
}