{
  "type": "Feature",
  "properties": {
    "iso:country":"CH",
    "sg:address":"Allmendstrasse 13 4460 Gelterkinden. Postfach",
    "sg:city":"Gelterkinden",
    "sg:orig_category":"Allgemeiner Hoch U Tiefbau",
    "sg:phone":"+41 61 981 13 60",
    "sg:postcode":"4460",
    "sg:province":"Basel-Landschaft",
    "wof:name":"Graf S\u00f6hne Ag",
    "wof:placetype":"venue"
},
  "geometry": {"coordinates":[7.84953,47.464249],"type":"Point"}
}