{
  "type": "Feature",
  "properties": {
    "iso:country":"CH",
    "sg:address":"9503",
    "sg:city":"Lanterswil",
    "sg:orig_category":"Abbruch U Sprenggewerbe, Erdbewegungsarbeiten Erdbewegungsarbeiten",
    "sg:phone":"+41 79 418 51 56",
    "sg:postcode":"9503",
    "sg:province":"Thurgau",
    "wof:name":"Ernst Aerne Baggerunternehmen",
    "wof:placetype":"venue"
},
  "geometry": {"coordinates":[9.09627,47.520672],"type":"Point"}
}