{
  "type": "Feature",
  "properties": {
    "iso:country":"CH",
    "sg:address":"Rue Du Bourg De L'auge 1",
    "sg:city":"Broc",
    "sg:orig_category":"Detailhandel mit Tabakwaren",
    "sg:phone":"+41 26 921 16 36",
    "sg:postcode":"1636",
    "sg:province":"Fribourg",
    "wof:name":"Lucienne Savary Tabacs",
    "wof:placetype":"venue"
},
  "geometry": {"coordinates":[5.2456002235,46.191444397],"type":"Point"}
}