{
  "type": "Feature",
  "properties": {
    "iso:country":"CH",
    "sg:address":"Wildsbergstr. 29 8606 N\u00e4nikon. Postfach",
    "sg:city":"N\u00e4nikon",
    "sg:orig_category":"Fachdetailhandel in Verkaufsr\u00e4umen",
    "sg:phone":"+41 19408130",
    "sg:postcode":"8606",
    "sg:province":"Z\u00fcrich",
    "wof:name":"Hellstern D. W.",
    "wof:placetype":"venue"
},
  "geometry": {"coordinates":[8.677529335,47.365234375],"type":"Point"}
}