{
  "type": "Feature",
  "properties": {
    "iso:country":"CH",
    "sg:address":"Boissonnet Chemin De 70",
    "sg:city":"Lausanne",
    "sg:orig_category":"Non-Classified Establishments",
    "sg:postcode":"1010",
    "sg:province":"Vaud",
    "wof:name":"Garage De Boissonnet S\u00e0rl",
    "wof:placetype":"venue"
},
  "geometry": {"coordinates":[6.6435279846,46.5413894653],"type":"Point"}
}