{
  "type": "Feature",
  "properties": {
    "iso:country":"CH",
    "sg:address":"Pl Hotel-de-ville 2",
    "sg:city":"Cully",
    "sg:classifiers":[
        {
            "category":"Banks & Credit Unions",
            "subcategory":"Bank",
            "type":"Services"
        }
    ],
    "sg:phone":"+41 21 799 18 32",
    "sg:postcode":"1096",
    "sg:province":"Vaud",
    "wof:name":"Banque Vaudoise De Credit",
    "wof:placetype":"venue"
},
  "geometry": {"coordinates":[6.730835,46.488293],"type":"Point"}
}