{
  "type": "Feature",
  "properties": {
    "iso:country":"CH",
    "sg:address":"Platz 234",
    "sg:city":"Walzenhausen",
    "sg:orig_category":"Naturheil\u00e4rzte and Heilpraktiker",
    "sg:phone":"+41 71 888 57 92",
    "sg:postcode":"9428",
    "sg:province":"Appenzell Ausserrhoden",
    "wof:name":"Richard Kellenberger Naturarzt",
    "wof:placetype":"venue"
},
  "geometry": {"coordinates":[9.6111402512,47.4434013367],"type":"Point"}
}