{
  "type": "Feature",
  "properties": {
    "iso:country":"CH",
    "sg:address":"Dufourstrasse 56 8008 Z\u00fcrich. Postfach",
    "sg:city":"Z\u00fcrich",
    "sg:orig_category":"Non-Classified Establishments",
    "sg:postcode":"8001",
    "sg:province":"Z\u00fcrich",
    "wof:name":"Rotary-stiftung Au",
    "wof:placetype":"venue"
},
  "geometry": {"coordinates":[8.6493587494,47.2459144592],"type":"Point"}
}