{
  "type": "Feature",
  "properties": {
    "iso:country":"CH",
    "sg:address":"Fraumattstrasse 37",
    "sg:city":"Liestal",
    "sg:orig_category":"RESTAURANTS: TEA-ROOMS",
    "sg:postcode":"4410",
    "sg:province":"Basel-Landschaft",
    "wof:name":"M & M Unternehmungen Mumenthaler Silvan",
    "wof:placetype":"venue"
},
  "geometry": {"coordinates":[7.7273349762,47.4971580505],"type":"Point"}
}