{
  "type": "Feature",
  "properties": {
    "iso:country":"CH",
    "sg:address":"Vordere Gasse 24",
    "sg:city":"Wolfwil",
    "sg:orig_category":"Herstellung von Metallerzeugnissen ohne Maschinenbau Herstellung von sonstigen Maschinen f\u00fcr unspezi",
    "sg:phone":"+41 62 926 39 09",
    "sg:postcode":"4628",
    "sg:province":"Solothurn",
    "wof:name":"Duomat W.& R.klook Automatenfabrik",
    "wof:placetype":"venue"
},
  "geometry": {"coordinates":[7.79083395,47.2684898376],"type":"Point"}
}