{
  "type": "Feature",
  "properties": {
    "iso:country":"CH",
    "sg:address":"Hauptstrasse 33",
    "sg:city":"T\u00fcscherz-alferm\u00e9e",
    "sg:orig_category":"Rebbau",
    "sg:phone":"+41 32 322 39 88",
    "sg:postcode":"2512",
    "sg:province":"Bern",
    "wof:name":"Hanspeter R\u00fcfenacht Weinbau",
    "wof:placetype":"venue"
},
  "geometry": {"coordinates":[7.1935749054,47.1129875183],"type":"Point"}
}