{
  "type": "Feature",
  "properties": {
    "iso:country":"CH",
    "sg:address":"Sagenmatt",
    "sg:city":"Luthern",
    "sg:orig_category":"S\u00e4gewerke",
    "sg:phone":"+41 27 973 15 33",
    "sg:postcode":"6156",
    "sg:province":"Luzern",
    "wof:name":"Theodor Werlen S\u00e4gerei",
    "wof:placetype":"venue"
},
  "geometry": {"coordinates":[8.2618379593,46.4867591858],"type":"Point"}
}