{
  "type": "Feature",
  "properties": {
    "iso:country":"CH",
    "sg:address":"Promende Champs-fr\u00e9chets 13",
    "sg:city":"Meyrin",
    "sg:classifiers":[
        {
            "category":"Restaurant",
            "type":"Food & Drink"
        }
    ],
    "sg:phone":"+41 22 782 77 88",
    "sg:postcode":"1217",
    "sg:province":"Gen\u00e8ve",
    "wof:name":"Caf\u00e9-rest.-pizzeria Da Ettore",
    "wof:placetype":"venue"
},
  "geometry": {"coordinates":[6.0792589188,46.238117218],"type":"Point"}
}