{
  "type": "Feature",
  "properties": {
    "iso:country":"CH",
    "sg:address":"Hauptstrasse 23",
    "sg:city":"M\u00fcnchenstein",
    "sg:orig_category":"Grosshandel mit Getr\u00e4nken",
    "sg:postcode":"4142",
    "sg:province":"Basel-Landschaft",
    "wof:name":"Weinhandel Pro Vin Vinothek Bayerlein H.",
    "wof:placetype":"venue"
},
  "geometry": {"coordinates":[7.6210041046,47.5127754211],"type":"Point"}
}