{
  "type": "Feature",
  "properties": {
    "addr:full":"Allmendstrasse 91 Z\u00fcrich Z\u00fcrich 8041",
    "addr:housenumber":"91",
    "addr:postcode":"8041",
    "addr:street":"Allmendstrasse",
    "iso:country":"CH",
    "sg:address":"Allmendstrasse 91",
    "sg:city":"Z\u00fcrich",
    "sg:orig_category":"Allgemeiner Hoch U Tiefbau Schlossereien",
    "sg:phone":"+41 14623778",
    "sg:postcode":"8041",
    "sg:province":"Z\u00fcrich",
    "wof:name":"Scheuber R. Ag",
    "wof:placetype":"venue"
},
  "geometry": {"coordinates":[8.519558,47.342945],"type":"Point"}
}