{
  "type": "Feature",
  "properties": {
    "iso:country":"CH",
    "sg:address":"Chasa Du Parc",
    "sg:city":"Scuol",
    "sg:orig_category":"Sonstige Institutionen des Sozialwesens ohne Beherbergung",
    "sg:phone":"+41 81 864 12 68",
    "sg:postcode":"7550",
    "sg:province":"Graubunden",
    "wof:name":"Sozialdienst Unterengadin-m\u00fcnstertal",
    "wof:placetype":"venue"
},
  "geometry": {"coordinates":[10.3014945984,46.7960891724],"type":"Point"}
}