{
  "type": "Feature",
  "properties": {
    "iso:country":"CH",
    "sg:address":"Zelglistrasse 21",
    "sg:city":"Z\u00fcrich",
    "sg:orig_category":"Maler U Glasergewerbe Tapeziererei",
    "sg:phone":"+41 79 208 02 70",
    "sg:postcode":"8046",
    "sg:province":"Z\u00fcrich",
    "wof:name":"Farbara, Mal- + Tapezierarbeiten Barbara Oerd\u00f6g",
    "wof:placetype":"venue"
},
  "geometry": {"coordinates":[8.5266933441,47.4119606018],"type":"Point"}
}