{
  "type": "Feature",
  "properties": {
    "iso:country":"CH",
    "sg:address":"Sportplatzweg 22",
    "sg:city":"Naters",
    "sg:orig_category":"K\u00fcnstlerische U schriftstellerische T\u00e4tigkeiten U Darbietungen",
    "sg:phone":"+41 27 923 45 45",
    "sg:postcode":"3904",
    "sg:province":"Valais",
    "wof:name":"Bildhauerei Wedekind Rainer.",
    "wof:placetype":"venue"
},
  "geometry": {"coordinates":[7.9984359741,46.3241996765],"type":"Point"}
}