{
  "type": "Feature",
  "properties": {
    "iso:country":"CH",
    "sg:address":"G\u00f6schenenstrasse 70",
    "sg:city":"Basel",
    "sg:orig_category":"Kosmetikinstitute",
    "sg:phone":"+41 61 302 86 90",
    "sg:postcode":"4054",
    "sg:province":"Basel-Stadt",
    "wof:name":"Bella Hernbal Kosmetikinstitut Bella",
    "wof:placetype":"venue"
},
  "geometry": {"coordinates":[7.5596809387,47.5471115112],"type":"Point"}
}