{
  "type": "Feature",
  "properties": {
    "addr:full":"C.postale 234/rue Haute 21 Colombier Neuch\u00e2tel 2013",
    "addr:housenumber":"234 /;21",
    "addr:postcode":"2013",
    "addr:street":"Rue Haute;Neucha\u0302Tel",
    "iso:country":"CH",
    "sg:address":"C.postale 234/rue Haute 21",
    "sg:city":"Colombier",
    "sg:classifiers":[
        {
            "category":"Banks & Credit Unions",
            "subcategory":"Bank",
            "type":"Services"
        }
    ],
    "sg:phone":"+41 26 921 21 05",
    "sg:postcode":"2013",
    "sg:province":"Neuch\u00e2tel",
    "wof:name":"Banque Raiffeisen De Cr\u00e9suz",
    "wof:placetype":"venue"
},
  "geometry": {"coordinates":[7.13374,46.619251],"type":"Point"}
}