{
  "type": "Feature",
  "properties": {
    "addr:full":"Schachenallee 29 Aarau Aargau 5000",
    "addr:housenumber":"29",
    "addr:postcode":"5000",
    "addr:street":"Schachenallee",
    "iso:country":"CH",
    "sg:address":"Schachenallee 29",
    "sg:city":"Aarau",
    "sg:classifiers":[
        {
            "category":"Banks & Credit Unions",
            "subcategory":"Investment Brokerage",
            "type":"Services"
        }
    ],
    "sg:phone":"+41 62 823 46 55",
    "sg:postcode":"5000",
    "sg:province":"Aargau",
    "sg:tags":[
        "dental",
        "cement"
    ],
    "wof:name":"Andreas Frey Dental-technik",
    "wof:placetype":"venue"
},
  "geometry": {"coordinates":[8.04062,47.39027],"type":"Point"}
}