{
  "type": "Feature",
  "properties": {
    "iso:country":"CH",
    "sg:address":"Alte Bernstrasse 14 5036 Oberentfelden. Postfach 54",
    "sg:city":"Oberentfelden",
    "sg:orig_category":"Sanit\u00e4r, Heizungs U L\u00fcftungsinstallation Sanit\u00e4rinstallation",
    "sg:phone":"+41 62 723 14 31",
    "sg:postcode":"5036",
    "sg:province":"Aargau",
    "wof:name":"H. B\u00f6ni",
    "wof:placetype":"venue"
},
  "geometry": {"coordinates":[8.0429582596,47.3544769287],"type":"Point"}
}