{
  "type": "Feature",
  "properties": {
    "iso:country":"CH",
    "sg:address":"B\u00fcndtenweg 26",
    "sg:city":"B\u00f6ckten",
    "sg:orig_category":"Erschliessung von Grundst\u00fccken",
    "sg:postcode":"4461",
    "sg:province":"Basel-Landschaft",
    "wof:name":"Bau-& Wohngen.ergolz",
    "wof:placetype":"venue"
},
  "geometry": {"coordinates":[7.8396868706,47.4640159607],"type":"Point"}
}