{
  "type": "Feature",
  "properties": {
    "iso:country":"CH",
    "sg:address":"Neue Aarburgerstrasse 2",
    "sg:city":"Rothrist",
    "sg:orig_category":"Autotransporte Tiefk\u00fchl Autotransporte international",
    "sg:phone":"+41 62 794 02 50",
    "sg:postcode":"4852",
    "sg:province":"Aargau",
    "wof:name":"Hans Hofer Int.k\u00fchltransporte",
    "wof:placetype":"venue"
},
  "geometry": {"coordinates":[7.87977,47.307072],"type":"Point"}
}