{
  "type": "Feature",
  "properties": {
    "iso:country":"CH",
    "sg:address":"Neugasse 9 6300 Zug. Postfach 534",
    "sg:city":"Zug",
    "sg:orig_category":"Detailhandel mit Uhren U Schmuck Grosshandel mit Geschenkartikeln U Souvenirs",
    "sg:phone":"+41 41 711 78 33",
    "sg:postcode":"6301",
    "sg:province":"Zug",
    "wof:name":"Logo-bijou-geschenke Ag",
    "wof:placetype":"venue"
},
  "geometry": {"coordinates":[8.5157871246,47.1672935486],"type":"Point"}
}