{
  "type": "Feature",
  "properties": {
    "iso:country":"CH",
    "sg:address":"Rotwaldstrasse 5",
    "sg:city":"Bazenheid",
    "sg:orig_category":"Deburring Machines",
    "sg:phone":"+41 71 931 51 76",
    "sg:postcode":"9602",
    "sg:province":"St. Gallen",
    "wof:name":"B\u00f6sch Maschinenbau",
    "wof:placetype":"venue"
},
  "geometry": {"coordinates":[9.072325,47.409061],"type":"Point"}
}