{
  "type": "Feature",
  "properties": {
    "iso:country":"CH",
    "sg:address":"Hauptstrasse",
    "sg:city":"Hochdorf",
    "sg:orig_category":"Fachdetailhandel in Verkaufsr\u00e4umen",
    "sg:phone":"+41 79 353 27 24",
    "sg:postcode":"6280",
    "sg:province":"Luzern",
    "wof:name":"Velos-motos Sidler",
    "wof:placetype":"venue"
},
  "geometry": {"coordinates":[8.2877149582,47.1691398621],"type":"Point"}
}