{
  "type": "Feature",
  "properties": {
    "iso:country":"CH",
    "sg:address":"J\u00f6ri-jennystrasse",
    "sg:city":"Arosa",
    "sg:orig_category":"Malerei Tapeziererei",
    "sg:phone":"+41 81 377 21 31",
    "sg:postcode":"7050",
    "sg:province":"Graubunden",
    "wof:name":"Adrian Altmann Maler-& Tapeziererarbeiten",
    "wof:placetype":"venue"
},
  "geometry": {"coordinates":[9.6822948456,46.7815933228],"type":"Point"}
}