{
  "type": "Feature",
  "properties": {
    "iso:country":"CH",
    "sg:address":"Wiesenstrasse 11",
    "sg:city":"Huttwil",
    "sg:orig_category":"Vermietung U Verpachtung von eigenen Immobilien",
    "sg:postcode":"4950",
    "sg:province":"Bern",
    "wof:name":"Otto Bieri Ag Huttwil",
    "wof:placetype":"venue"
},
  "geometry": {"coordinates":[7.8322868347,47.1151161194],"type":"Point"}
}