{
  "type": "Feature",
  "properties": {
    "iso:country":"CH",
    "sg:address":"Fegergasse 26",
    "sg:city":"Zofingen",
    "sg:orig_category":"Wirtschaftsverb\u00e4nde Industrie, Handel and Gewerbe",
    "sg:phone":"+41 62 752 30 66",
    "sg:postcode":"4800",
    "sg:province":"Aargau",
    "wof:name":"Schweiz.carrosserieverband",
    "wof:placetype":"venue"
},
  "geometry": {"coordinates":[7.9439082146,47.2890815735],"type":"Point"}
}