{
  "type": "Feature",
  "properties": {
    "iso:country":"CH",
    "sg:address":"Luzernerstrasse 13",
    "sg:city":"Kriens",
    "sg:orig_category":"Detailhandel mit Blumen U Pflanzen Fachdetailhandel in Verkaufsr\u00e4umen",
    "sg:phone":"+41 56 631 23 33",
    "sg:postcode":"6010",
    "sg:province":"Luzern",
    "wof:name":"Ambiance Florale Gestaltung Frei Susanne Blumenladen U. Gestaltung Mit Pflanzen",
    "wof:placetype":"venue"
},
  "geometry": {"coordinates":[8.342576,47.351143],"type":"Point"}
}