{
  "type": "Feature",
  "properties": {
    "iso:country":"CH",
    "sg:address":"Huswisenstrasse 6",
    "sg:city":"Lufingen",
    "sg:orig_category":"Detektivb\u00fcros U \u00dcberwachung",
    "sg:postcode":"8426",
    "sg:province":"Z\u00fcrich",
    "wof:name":"Marti Walter, Sicherheitsberatungen",
    "wof:placetype":"venue"
},
  "geometry": {"coordinates":[8.595249176,47.4914474487],"type":"Point"}
}