{
  "type": "Feature",
  "properties": {
    "addr:full":"Landstrasse 37 Untersiggenthal Aargau 5417",
    "addr:housenumber":"37",
    "addr:postcode":"5417",
    "addr:street":"Landstrasse",
    "iso:country":"CH",
    "sg:address":"Landstrasse 37",
    "sg:city":"Untersiggenthal",
    "sg:orig_category":"Blumen U Zierpflanzenbau Detailhandel mit Blumen U Pflanzen",
    "sg:phone":"+41 56 288 13 27",
    "sg:postcode":"5417",
    "sg:province":"Aargau",
    "wof:name":"Hanna Hospenthal",
    "wof:placetype":"venue"
},
  "geometry": {"coordinates":[8.26197,47.497974],"type":"Point"}
}