{
  "type": "Feature",
  "properties": {
    "iso:country":"CH",
    "sg:address":"Gewerbestrasse 11",
    "sg:city":"Lyssach",
    "sg:orig_category":"Grosshandel mit Getreide, Saatgut U Futtermitteln Handelsvermittlung U Grosshandel",
    "sg:phone":"+41 34 445 17 84",
    "sg:postcode":"3421",
    "sg:province":"Bern",
    "wof:name":"Emil Knopf Ag",
    "wof:placetype":"venue"
},
  "geometry": {"coordinates":[7.5831990242,47.0800590515],"type":"Point"}
}