{
  "type": "Feature",
  "properties": {
    "iso:country":"CH",
    "sg:address":"Freiburgstrasse 572",
    "sg:city":"Bern",
    "sg:orig_category":"Softwareentwicklung U beratung Sonstige mit der Informatik verbundene T\u00e4tigkeiten",
    "sg:phone":"+41 31 991 65 61",
    "sg:postcode":"3018",
    "sg:province":"Bern",
    "wof:name":"Fima.b Gmbh",
    "wof:placetype":"venue"
},
  "geometry": {"coordinates":[7.381814003,46.9285392761],"type":"Point"}
}