{
  "type": "Feature",
  "properties": {
    "iso:country":"CH",
    "sg:address":"Morgenstrasse 129",
    "sg:city":"Bern",
    "sg:classifiers":[
        {
            "category":"Utilities",
            "subcategory":"Natural Gas",
            "type":"Services"
        }
    ],
    "sg:phone":"+41 31 992 98 30",
    "sg:postcode":"3018",
    "sg:province":"Bern",
    "sg:tags":[
        "ceiling",
        "lamp"
    ],
    "wof:name":"Selux Ag Schweiz",
    "wof:placetype":"venue"
},
  "geometry": {"coordinates":[7.389421,46.934666],"type":"Point"}
}