{
  "type": "Feature",
  "properties": {
    "iso:country":"CH",
    "sg:address":"Caccia Riva 3",
    "sg:city":"Lugano",
    "sg:orig_category":"RESTAURANTS: TEA-ROOMS",
    "sg:postcode":"6900",
    "sg:province":"Ticino",
    "wof:name":"Tannenbaum Altst\u00e4tten Gmbh",
    "wof:placetype":"venue"
},
  "geometry": {"coordinates":[9.549697876,47.375202179],"type":"Point"}
}