{
  "type": "Feature",
  "properties": {
    "iso:country":"CH",
    "sg:address":"Berneckerstrasse 630",
    "sg:city":"Heerbrugg",
    "sg:orig_category":"Maler U Glasergewerbe Malerei",
    "sg:phone":"+41 71 277 54 74",
    "sg:postcode":"9435",
    "sg:province":"St. Gallen",
    "wof:name":"Malerei Stutz",
    "wof:placetype":"venue"
},
  "geometry": {"coordinates":[9.3328990936,47.4022827148],"type":"Point"}
}