{
  "type": "Feature",
  "properties": {
    "addr:full":"Limmattalstrasse 247 Z\u00fcrich Z\u00fcrich 8049",
    "addr:housenumber":"247",
    "addr:postcode":"8049",
    "addr:street":"Limmattalstrasse",
    "iso:country":"CH",
    "sg:address":"Limmattalstrasse 247",
    "sg:city":"Z\u00fcrich",
    "sg:orig_category":"Arztpraxen",
    "sg:phone":"+41 13424134",
    "sg:postcode":"8049",
    "sg:province":"Z\u00fcrich",
    "wof:name":"Dr.med.viktor Ker\u00e9nyi Spezialarzt Fmh",
    "wof:placetype":"venue"
},
  "geometry": {"coordinates":[8.493589,47.402317],"type":"Point"}
}