{
  "type": "Feature",
  "properties": {
    "iso:country":"CH",
    "sg:address":"Crans",
    "sg:city":"Chermignon",
    "sg:orig_category":"Non-Classified Establishments",
    "sg:postcode":"3971",
    "sg:province":"Valais",
    "wof:name":"Si Riantes Cimes Sa",
    "wof:placetype":"venue"
},
  "geometry": {"coordinates":[7.1587119102,46.3500404358],"type":"Point"}
}