{
  "type": "Feature",
  "properties": {
    "iso:country":"CH",
    "sg:address":"Chemin Neuf 2",
    "sg:city":"Gen\u00e8ve",
    "sg:orig_category":"Druckweiterverarbeitung",
    "sg:postcode":"1207",
    "sg:province":"Gen\u00e8ve",
    "wof:name":"Ren\u00e9 Morf",
    "wof:placetype":"venue"
},
  "geometry": {"coordinates":[6.1589388847,46.2031402588],"type":"Point"}
}