{
  "type": "Feature",
  "properties": {
    "iso:country":"CH",
    "sg:address":"Breitacker 126",
    "sg:city":"Brunegg",
    "sg:orig_category":"G\u00fcterbef\u00f6rderung im Strassenverkehr Lagerh\u00e4user",
    "sg:phone":"+41 62 887 40 40",
    "sg:postcode":"5505",
    "sg:province":"Aargau",
    "wof:name":"Sulser Transport & Lagerhaus Ag Logistik-center Brunegg",
    "wof:placetype":"venue"
},
  "geometry": {"coordinates":[8.2205677032,47.4222946167],"type":"Point"}
}