{
  "type": "Feature",
  "properties": {
    "iso:country":"CH",
    "sg:address":"Bahnhofstrasse 41",
    "sg:city":"Wettingen",
    "sg:orig_category":"Zahnarztpraxen",
    "sg:phone":"+41 56 426 74 64",
    "sg:postcode":"5430",
    "sg:province":"Aargau",
    "wof:name":"Dr. Med. Dent. Ernst Gloor Zahnarzt",
    "wof:placetype":"venue"
},
  "geometry": {"coordinates":[8.3221483231,47.4607543945],"type":"Point"}
}