{
  "type": "Feature",
  "properties": {
    "iso:country":"CH",
    "sg:address":"Ostring 52",
    "sg:city":"Regensdorf",
    "sg:orig_category":"Grosshandel mit Sportartikeln",
    "sg:phone":"+41 18401928",
    "sg:postcode":"8105",
    "sg:province":"Z\u00fcrich",
    "wof:name":"Ak-trade Arthur Kn\u00f6pfli Elektronische Systeme",
    "wof:placetype":"venue"
},
  "geometry": {"coordinates":[8.4692382812,47.4295387268],"type":"Point"}
}