{
  "type": "Feature",
  "properties": {
    "iso:country":"CH",
    "sg:address":"Hauptstrasse 86",
    "sg:city":"Zuzgen",
    "sg:orig_category":"S\u00e4ge, Hobel U Holzimpr\u00e4gnierwerke S\u00e4gewerke",
    "sg:phone":"+41 61 871 04 49",
    "sg:postcode":"4315",
    "sg:province":"Aargau",
    "wof:name":"Anton Intlekofer S\u00e4gerei",
    "wof:placetype":"venue"
},
  "geometry": {"coordinates":[7.9021987915,47.5238075256],"type":"Point"}
}