{
  "type": "Feature",
  "properties": {
    "iso:country":"CH",
    "sg:address":"Tanzhus 9658 Wildhaus. Postfach",
    "sg:city":"Wildhaus",
    "sg:orig_category":"Landesverteidigung, Sozialversicherung \u00d6ffentliche Verwaltung",
    "sg:phone":"+41 27 939 12 70",
    "sg:postcode":"9658",
    "sg:province":"St. Gallen",
    "wof:name":"Zivilschutzstelle Wiler (l\u00f6tschen)",
    "wof:placetype":"venue"
},
  "geometry": {"coordinates":[7.7845520973,46.4042396545],"type":"Point"}
}