{
  "type": "Feature",
  "properties": {
    "iso:country":"CH",
    "sg:address":"Br\u00fcnigstrasse 144 6060 Sarnen. Postfach 1526",
    "sg:city":"Sarnen",
    "sg:orig_category":"Finanzierungsinstitutionen",
    "sg:phone":"+41 41 662 20 80",
    "sg:postcode":"6060",
    "sg:province":"Obwalden",
    "wof:name":"Premium Investment Gmbh Dienstleistungen Im Finanzbereich",
    "wof:placetype":"venue"
},
  "geometry": {"coordinates":[8.2459192276,46.8966217041],"type":"Point"}
}