{
  "type": "Feature",
  "properties": {
    "iso:country":"CH",
    "sg:address":"Gerliswilstrasse 15",
    "sg:city":"Emmenbr\u00fccke",
    "sg:classifiers":[
        {
            "category":"Professional",
            "subcategory":"Employment Agencies",
            "type":"Services"
        }
    ],
    "sg:phone":"+41 61 426 90 80",
    "sg:postcode":"6020",
    "sg:province":"Luzern",
    "sg:tags":[
        "personal",
        "u",
        "stellenvermittlung"
    ],
    "wof:name":"Rav Regionales Arbeitsvermittlungszentrum",
    "wof:placetype":"venue"
},
  "geometry": {"coordinates":[7.5726070404,47.5325775146],"type":"Point"}
}