{
  "type": "Feature",
  "properties": {
    "iso:country":"CH",
    "sg:address":"Weinbergstrasse 37 8006 Z\u00fcrich. Postfach",
    "sg:city":"Z\u00fcrich",
    "sg:orig_category":"RESTAURANTS: TEA-ROOMS",
    "sg:postcode":"8001",
    "sg:province":"Z\u00fcrich",
    "wof:name":"K\u00fcng Kaspar Tea-room Belami",
    "wof:placetype":"venue"
},
  "geometry": {"coordinates":[8.5440502167,47.3796691895],"type":"Point"}
}