{
  "type": "Feature",
  "properties": {
    "addr:full":"Rue De Coutance 29 Gen\u00e8ve Gen\u00e8ve 1201",
    "addr:housenumber":"29",
    "addr:postcode":"1201",
    "addr:street":"Rue De Coutance",
    "iso:country":"CH",
    "sg:address":"Rue De Coutance 29",
    "sg:city":"Gen\u00e8ve",
    "sg:orig_category":"Detailhandel mit Bekleidung Detailhandel mit Herrenbekleidung",
    "sg:phone":"+41 81 833 12 22",
    "sg:postcode":"1201",
    "sg:province":"Gen\u00e8ve",
    "wof:name":"Crameri Myrtha, Men's Fashion",
    "wof:placetype":"venue"
},
  "geometry": {"coordinates":[9.839719,46.497494],"type":"Point"}
}