{
  "type": "Feature",
  "properties": {
    "iso:country":"CH",
    "sg:address":"Unterer Graben 1",
    "sg:city":"St.gallen",
    "sg:orig_category":"Vermietung U Verpachtung von eigenen Immobilien Verwaltung von Immobilien",
    "sg:phone":"+41 71 220 20 70",
    "sg:postcode":"9000",
    "sg:province":"St. Gallen",
    "wof:name":"B\u00dcrke Immo Treuhand",
    "wof:placetype":"venue"
},
  "geometry": {"coordinates":[9.3739852905,47.4261512756],"type":"Point"}
}