{
  "type": "Feature",
  "properties": {
    "iso:country":"CH",
    "sg:address":"S\u00e4gegasse 30",
    "sg:city":"M\u00fcnsingen",
    "sg:orig_category":"G\u00fcterbef\u00f6rderung im Strassenverkehr",
    "sg:phone":"+41 31 721 15 82",
    "sg:postcode":"3110",
    "sg:province":"Bern",
    "wof:name":"Balsiger Peter Transporte",
    "wof:placetype":"venue"
},
  "geometry": {"coordinates":[7.5530910492,46.8739624023],"type":"Point"}
}