{
  "type": "Feature",
  "properties": {
    "iso:country":"CH",
    "sg:address":"Kasernenstrasse 7",
    "sg:city":"B\u00fclach",
    "sg:orig_category":"Detailhandel mit Lederwaren U Reiseartikeln Verlegen von Fussboden",
    "sg:phone":"+41 18601253",
    "sg:postcode":"8180",
    "sg:province":"Z\u00fcrich",
    "wof:name":"Peter Fischli Innenausstattung Lederwaren",
    "wof:placetype":"venue"
},
  "geometry": {"coordinates":[8.5392627716,47.518535614],"type":"Point"}
}