{
  "type": "Feature",
  "properties": {
    "iso:country":"CH",
    "sg:address":"Schwalbenweg 55",
    "sg:city":"Frauenfeld",
    "sg:orig_category":"W\u00e4schereien",
    "sg:phone":"+41 52 722 11 19",
    "sg:postcode":"8500",
    "sg:province":"Thurgau",
    "wof:name":"W\u00f6schh\u00fcsli Reutenen",
    "wof:placetype":"venue"
},
  "geometry": {"coordinates":[8.9004602432,47.5513725281],"type":"Point"}
}