{
  "type": "Feature",
  "properties": {
    "iso:country":"CH",
    "sg:address":"Landstrasse 26 5430 Wettingen. Postfach",
    "sg:city":"Wettingen",
    "sg:orig_category":"Sonstige pers\u00f6nliche Dienstleistungen",
    "sg:phone":"+41 56 430 14 90",
    "sg:postcode":"5430",
    "sg:province":"Aargau",
    "wof:name":"Scmo Meier Beratung, Umsetzung In Den Bereichen Verkauf, Beratung, Marketing, Organisation",
    "wof:placetype":"venue"
},
  "geometry": {"coordinates":[8.3191518784,47.4689865112],"type":"Point"}
}