{
  "type": "Feature",
  "properties": {
    "iso:country":"CH",
    "sg:address":"M\u00fchlackerstrasse 3",
    "sg:city":"Gerlafingen",
    "sg:orig_category":"Sportvereine Ballsport Tennis",
    "sg:phone":"+41 32 675 39 36",
    "sg:postcode":"4563",
    "sg:province":"Solothurn",
    "wof:name":"Tc Gerlafingen",
    "wof:placetype":"venue"
},
  "geometry": {"coordinates":[7.5725011826,47.1683235168],"type":"Point"}
}