{
  "type": "Feature",
  "properties": {
    "iso:country":"CH",
    "sg:address":"Alemannenweg 8",
    "sg:city":"R\u00fcschlikon",
    "sg:orig_category":"Schlossereien",
    "sg:phone":"+41 17246020",
    "sg:postcode":"8803",
    "sg:province":"Z\u00fcrich",
    "wof:name":"Fischer Metallbau Ag Schlosserei",
    "wof:placetype":"venue"
},
  "geometry": {"coordinates":[8.5427675247,47.3096351624],"type":"Point"}
}