{
  "type": "Feature",
  "properties": {
    "iso:country":"CH",
    "sg:address":"Rte De Renens 5",
    "sg:city":"Bussigny-lausanne",
    "sg:orig_category":"Allgemeiner Hoch U Tiefbau",
    "sg:postcode":"1030",
    "sg:province":"Vaud",
    "wof:name":"Domenighini Lindo.",
    "wof:placetype":"venue"
},
  "geometry": {"coordinates":[8.80109,46.321781],"type":"Point"}
}