{
  "type": "Feature",
  "properties": {
    "iso:country":"CH",
    "sg:address":"6675",
    "sg:city":"Cevio",
    "sg:classifiers":[
        {
            "category":"Travel",
            "subcategory":"Hotels & Motels",
            "type":"Entertainment"
        }
    ],
    "sg:phone":"+41 91 755 11 92",
    "sg:postcode":"6675",
    "sg:province":"Ticino",
    "sg:tags":[
        "hotels",
        "mit",
        "restaurant"
    ],
    "wof:name":"Albergo Basodino",
    "wof:placetype":"venue"
},
  "geometry": {"coordinates":[8.5258197784,46.4088592529],"type":"Point"}
}