{
  "type": "Feature",
  "properties": {
    "iso:country":"CH",
    "sg:address":"Beim Bahnhof",
    "sg:city":"Niederglatt",
    "sg:classifiers":[
        {
            "category":"Wholesale",
            "subcategory":"Construction Materials",
            "type":"Manufacturing & Wholesale Goods"
        }
    ],
    "sg:phone":"+41 18510080",
    "sg:postcode":"8172",
    "sg:province":"Z\u00fcrich",
    "sg:tags":[
        "packing",
        "egg"
    ],
    "wof:name":"Propac Ag",
    "wof:placetype":"venue"
},
  "geometry": {"coordinates":[8.5035867691,47.4891586304],"type":"Point"}
}