{
  "type": "Feature",
  "properties": {
    "iso:country":"CH",
    "sg:address":"Wierstrasse 10",
    "sg:city":"Ebnat-kappel",
    "sg:orig_category":"Alters U Pflegeheime Institutionen f\u00fcr Behinderte",
    "sg:phone":"+41 71 993 26 11",
    "sg:postcode":"9642",
    "sg:province":"St. Gallen",
    "wof:name":"Alters-& Pflegeheim",
    "wof:placetype":"venue"
},
  "geometry": {"coordinates":[9.130293,47.262859],"type":"Point"}
}