{
  "type": "Feature",
  "properties": {
    "iso:country":"CH",
    "sg:address":"1732",
    "sg:city":"Arconciel",
    "sg:orig_category":"Verwertung von Milch",
    "sg:postcode":"1732",
    "sg:province":"Fribourg",
    "wof:name":"Jeanmonod Serge",
    "wof:placetype":"venue"
},
  "geometry": {"coordinates":[6.4892830849,46.8666915894],"type":"Point"}
}