{
  "type": "Feature",
  "properties": {
    "iso:country":"CH",
    "sg:address":"Bahnhofstrasse 18 5600 Lenzburg. Postfach",
    "sg:city":"Lenzburg",
    "sg:orig_category":"Gesundheitswesen",
    "sg:postcode":"5600",
    "sg:province":"Aargau",
    "wof:name":"Pendragon Consulting Gmbh Unternehmensberatung Bes. In Medizinischen Bereichen Usw",
    "wof:placetype":"venue"
},
  "geometry": {"coordinates":[8.1755514145,47.3892288208],"type":"Point"}
}