{
  "type": "Feature",
  "properties": {
    "iso:country":"CH",
    "sg:address":"Klingental 8",
    "sg:city":"Basel",
    "sg:classifiers":[
        {
            "category":"Travel",
            "subcategory":"Hotels & Motels",
            "type":"Entertainment"
        }
    ],
    "sg:postcode":"4058",
    "sg:province":"Basel-Stadt",
    "sg:tags":[
        "hotels",
        "mit",
        "restaurant"
    ],
    "wof:name":"Kammrag",
    "wof:placetype":"venue"
},
  "geometry": {"coordinates":[7.5910072327,47.5620918274],"type":"Point"}
}