{
  "type": "Feature",
  "properties": {
    "iso:country":"CH",
    "sg:address":"Campione Via 54",
    "sg:city":"Bissone",
    "sg:orig_category":"Fachdetailhandel mit pharmazeutischen Produkten",
    "sg:postcode":"6816",
    "sg:province":"Ticino",
    "wof:name":"Ate Pharma Handels Ag",
    "wof:placetype":"venue"
},
  "geometry": {"coordinates":[8.6445388794,46.8819274902],"type":"Point"}
}