{
  "type": "Feature",
  "properties": {
    "iso:country":"CH",
    "sg:address":"Romanshornerstrasse 117",
    "sg:city":"Kreuzlingen",
    "sg:orig_category":"Herstellung von rohen \u00d6len U Fetten",
    "sg:postcode":"8280",
    "sg:province":"Thurgau",
    "wof:name":"Km Schneider",
    "wof:placetype":"venue"
},
  "geometry": {"coordinates":[9.1942596436,47.6400909424],"type":"Point"}
}