{
  "type": "Feature",
  "properties": {
    "iso:country":"CH",
    "sg:address":"Im B\u00e4renmoos 6",
    "sg:city":"Oberrieden",
    "sg:orig_category":"Wohnheime",
    "sg:phone":"+41 17201900",
    "sg:postcode":"8942",
    "sg:province":"Z\u00fcrich",
    "wof:name":"Wohnraum F\u00fcr J\u00fcngere Behinderte",
    "wof:placetype":"venue"
},
  "geometry": {"coordinates":[8.5778913498,47.2729377747],"type":"Point"}
}