{
  "type": "Feature",
  "properties": {
    "iso:country":"CH",
    "sg:address":"Bergwerkstrasse 23",
    "sg:city":"Horgen",
    "sg:orig_category":"Sportvereine Wassersport",
    "sg:phone":"+41 17101928",
    "sg:postcode":"8810",
    "sg:province":"Z\u00fcrich",
    "wof:name":"See-club Horgen",
    "wof:placetype":"venue"
},
  "geometry": {"coordinates":[8.6118602753,47.2531585693],"type":"Point"}
}