{
  "type": "Feature",
  "properties": {
    "iso:country":"CH",
    "sg:address":"Weinbergstrasse 139",
    "sg:city":"Z\u00fcrich",
    "sg:orig_category":"Unternehmensberatung",
    "sg:phone":"+41 13651515",
    "sg:postcode":"8006",
    "sg:province":"Z\u00fcrich",
    "wof:name":"May Group Inc.",
    "wof:placetype":"venue"
},
  "geometry": {"coordinates":[8.540263176,47.3888168335],"type":"Point"}
}