{
  "type": "Feature",
  "properties": {
    "iso:country":"CH",
    "sg:address":"Lisone",
    "sg:city":"Cademario",
    "sg:orig_category":"Betrieb von Taxis Regelm\u00e4ssige Personenbef\u00f6rderung im Fernverkehr",
    "sg:phone":"+41 91 605 23 91",
    "sg:postcode":"6936",
    "sg:province":"Ticino",
    "wof:name":"Achille Monti & Co Assuntori Postali-garage-tassi",
    "wof:placetype":"venue"
},
  "geometry": {"coordinates":[8.889474,46.02166],"type":"Point"}
}