{
  "type": "Feature",
  "properties": {
    "addr:full":"Bahnhofmatten 16 Hunzenschwil Aargau 5502",
    "addr:housenumber":"16",
    "addr:postcode":"5502",
    "addr:street":"Bahnhofmatten",
    "iso:country":"CH",
    "sg:address":"Bahnhofmatten 16",
    "sg:city":"Hunzenschwil",
    "sg:orig_category":"Detailhandel mit Computern U Software Versandhandel",
    "sg:postcode":"5502",
    "sg:province":"Aargau",
    "wof:name":"Digisol Gmbh Webdesign & Computerschule",
    "wof:placetype":"venue"
},
  "geometry": {"coordinates":[8.122041,47.387493],"type":"Point"}
}