{
  "type": "Feature",
  "properties": {
    "iso:country":"CH",
    "sg:address":"1873",
    "sg:city":"Val-d'illiez",
    "sg:classifiers":[
        {
            "category":"Restaurant",
            "type":"Food & Drink"
        }
    ],
    "sg:phone":"+41 26 652 22 09",
    "sg:postcode":"1873",
    "sg:province":"Valais",
    "wof:name":"Restaurant Des Treize Cantons",
    "wof:placetype":"venue"
},
  "geometry": {"coordinates":[6.9181799889,46.6950798035],"type":"Point"}
}