{
  "type": "Feature",
  "properties": {
    "iso:country":"CH",
    "sg:address":"Uraniastrasse 30",
    "sg:city":"Z\u00fcrich",
    "sg:orig_category":"Detailhandel mit Computern U Software Sonstiger Grosshandel",
    "sg:phone":"+41 12221440",
    "sg:postcode":"8001",
    "sg:province":"Z\u00fcrich",
    "wof:name":"Portable Shop Z\u00fcrich Mobile Computer",
    "wof:placetype":"venue"
},
  "geometry": {"coordinates":[8.535561,47.373543],"type":"Point"}
}