{
  "type": "Feature",
  "properties": {
    "iso:country":"CH",
    "sg:address":"Via Cantonale 51a 6983 Magliaso. Postfach",
    "sg:city":"Magliaso",
    "sg:orig_category":"Verwaltung von Immobilien",
    "sg:postcode":"6983",
    "sg:province":"Ticino",
    "wof:name":"Pit-stop Malcantonese Sagl Esercizi Pubblici, Import. Di Generi Alimentari Ecc",
    "wof:placetype":"venue"
},
  "geometry": {"coordinates":[8.8853673935,45.9829483032],"type":"Point"}
}