{
  "type": "Feature",
  "properties": {
    "iso:country":"CH",
    "sg:address":"Rue De Bonn\u00e9 12",
    "sg:city":"Reconvilier",
    "sg:classifiers":[
        {
            "category":"Retail",
            "subcategory":"Repair Shop",
            "type":"Services"
        }
    ],
    "sg:phone":"+41 32 481 44 47",
    "sg:postcode":"2732",
    "sg:province":"Bern",
    "sg:tags":[
        "workshop",
        "mechanical"
    ],
    "wof:name":"Cer\u00e9 Sa",
    "wof:placetype":"venue"
},
  "geometry": {"coordinates":[7.2323307991,47.2342071533],"type":"Point"}
}