{
  "type": "Feature",
  "properties": {
    "iso:country":"CH",
    "sg:address":"Rue Graman 68-70",
    "sg:city":"Puplinge",
    "sg:orig_category":"Gemeindeverwaltungen",
    "sg:phone":"+41 22 349 75 56",
    "sg:postcode":"1241",
    "sg:province":"Gen\u00e8ve",
    "wof:name":"Administration Communale De Puplinge",
    "wof:placetype":"venue"
},
  "geometry": {"coordinates":[6.2323198318,46.2109909058],"type":"Point"}
}