{
  "type": "Feature",
  "properties": {
    "iso:country":"CH",
    "sg:address":"Uebergstrasse 194",
    "sg:city":"Hochfelden",
    "sg:orig_category":"Unclassifiable Establishments",
    "sg:postcode":"8182",
    "sg:province":"Z\u00fcrich",
    "wof:name":"Phibajo Export P. Bona",
    "wof:placetype":"venue"
},
  "geometry": {"coordinates":[8.5071172714,47.5176773071],"type":"Point"}
}