{
  "type": "Feature",
  "properties": {
    "iso:country":"CH",
    "sg:address":"Via Al Forte 19",
    "sg:city":"Lugano",
    "sg:orig_category":"Fachdetailhandel in Verkaufsr\u00e4umen",
    "sg:postcode":"6900",
    "sg:province":"Ticino",
    "wof:name":"Binda Francesco",
    "wof:placetype":"venue"
},
  "geometry": {"coordinates":[8.9533481598,46.0056495667],"type":"Point"}
}