{
  "type": "Feature",
  "properties": {
    "iso:country":"CH",
    "sg:address":"Uznacherstrasse 51",
    "sg:city":"Kaltbrunn",
    "sg:orig_category":"Einzelhandel mit Automobilen Herstellung von Karosserien U Anh\u00e4ngern",
    "sg:phone":"+41 55 283 11 67",
    "sg:postcode":"8722",
    "sg:province":"St. Gallen",
    "wof:name":"Peter Nagy Pnc Reisemobile",
    "wof:placetype":"venue"
},
  "geometry": {"coordinates":[9.0136537552,47.2167243958],"type":"Point"}
}