{
  "type": "Feature",
  "properties": {
    "iso:country":"CH",
    "sg:address":"Oberdorfstrasse 58",
    "sg:city":"Seftigen",
    "sg:orig_category":"Elektroinstallation",
    "sg:phone":"+41 71 888 30 50",
    "sg:postcode":"3662",
    "sg:province":"Bern",
    "wof:name":"Siegert Baumontagen",
    "wof:placetype":"venue"
},
  "geometry": {"coordinates":[9.6102619171,47.4591712952],"type":"Point"}
}