{
  "type": "Feature",
  "properties": {
    "iso:country":"CH",
    "sg:address":"Hauptstrasse 1",
    "sg:city":"Sch\u00fcpfheim",
    "sg:orig_category":"Detailhandel mit Getr\u00e4nken Grosshandel mit Getr\u00e4nken",
    "sg:phone":"+41 41 484 26 44",
    "sg:postcode":"6170",
    "sg:province":"Luzern",
    "wof:name":"M. Worni Weine Getr\u00e4nkehandlung",
    "wof:placetype":"venue"
},
  "geometry": {"coordinates":[8.0186233521,46.9530448914],"type":"Point"}
}