{
  "type": "Feature",
  "properties": {
    "addr:full":"Kantosstrasse 41c 3930 Visp. Postfach Visp Valais 3930",
    "addr:housenumber":"41c",
    "addr:postcode":"3930 visp. postfach;3930",
    "addr:street":"Kantosstrasse",
    "iso:country":"CH",
    "sg:address":"Kantosstrasse 41c 3930 Visp. Postfach",
    "sg:city":"Visp",
    "sg:orig_category":"Detailhandel mit B\u00fcromaschinen U einrichtungen Schnelldruck U Kopierservice",
    "sg:phone":"+41 32 913 44 20",
    "sg:postcode":"3930",
    "sg:province":"Valais",
    "wof:name":"Bureautique Redin",
    "wof:placetype":"venue"
},
  "geometry": {"coordinates":[6.820322,47.097332],"type":"Point"}
}