{
  "type": "Feature",
  "properties": {
    "iso:country":"CH",
    "sg:address":"Dorstrasse 11",
    "sg:city":"Mogelsberg",
    "sg:orig_category":"Elektroinstallation",
    "sg:phone":"+41 71 374 21 50",
    "sg:postcode":"9122",
    "sg:province":"St. Gallen",
    "wof:name":"Niklaus Rolf Elektro-telecom",
    "wof:placetype":"venue"
},
  "geometry": {"coordinates":[9.1353769302,47.3621368408],"type":"Point"}
}