{
  "type": "Feature",
  "properties": {
    "iso:country":"CH",
    "sg:address":"S\u00e9beillon Rue De 1004 Lausanne. Postfach",
    "sg:city":"Lausanne",
    "sg:orig_category":"Softwareentwicklung U beratung",
    "sg:phone":"+41 21 620 77 00",
    "sg:postcode":"1003",
    "sg:province":"Vaud",
    "wof:name":"Interwise Europe B.v., Rotterdam, Swiss Branch Lausanne V\u00e9rification Et Analyse De Donn\u00e9es, Services Dans Le Domaine De L'informatique Et De L'internet Etc",
    "wof:placetype":"venue"
},
  "geometry": {"coordinates":[6.6164598465,46.5234909058],"type":"Point"}
}