{
  "type": "Feature",
  "properties": {
    "iso:country":"CH",
    "sg:address":"Rheinl\u00e4nderstrasse 21 4056 Basel. Postfach",
    "sg:city":"Basel",
    "sg:orig_category":"Erschliessung von Grundst\u00fccken",
    "sg:postcode":"4051",
    "sg:province":"Basel-Stadt",
    "wof:name":"Wohngenossenschaft 21",
    "wof:placetype":"venue"
},
  "geometry": {"coordinates":[7.5777468681,47.563293457],"type":"Point"}
}