{
  "type": "Feature",
  "properties": {
    "iso:country":"CH",
    "sg:address":"1625",
    "sg:city":"Maules",
    "sg:orig_category":"Landesverteidigung, Sozialversicherung \u00d6ffentliche Verwaltung",
    "sg:phone":"+41 26 917 84 16",
    "sg:postcode":"1625",
    "sg:province":"Fribourg",
    "wof:name":"Centre De Protection Civile",
    "wof:placetype":"venue"
},
  "geometry": {"coordinates":[6.9904899597,46.6387214661],"type":"Point"}
}