{
  "type": "Feature",
  "properties": {
    "iso:country":"CH",
    "sg:address":"Viale Verbano 3",
    "sg:city":"Muralto",
    "sg:orig_category":"Handelsvermittlung U Grosshandel",
    "sg:phone":"+41 91 743 18 61",
    "sg:postcode":"6600",
    "sg:province":"Ticino",
    "wof:name":"Albert Berger Agenzia Commerciale",
    "wof:placetype":"venue"
},
  "geometry": {"coordinates":[8.8008861542,46.1710090637],"type":"Point"}
}