{
  "type": "Feature",
  "properties": {
    "iso:country":"CH",
    "sg:address":"Hauptstrasse 52",
    "sg:city":"Menziken",
    "sg:orig_category":"Diskotheken, Dancings, Night Clubs",
    "sg:phone":"+41 62 771 15 75",
    "sg:postcode":"5737",
    "sg:province":"Aargau",
    "wof:name":"Dancing Rebstock",
    "wof:placetype":"venue"
},
  "geometry": {"coordinates":[8.188876152,47.2389144897],"type":"Point"}
}