{
  "type": "Feature",
  "properties": {
    "iso:country":"CH",
    "sg:address":"Murbacherstrasse 24 4056 Basel. Postfach",
    "sg:city":"Basel",
    "sg:orig_category":"Instandhaltung U Reparatur von Automobilen",
    "sg:postcode":"4051",
    "sg:province":"Basel-Stadt",
    "wof:name":"Garage Bogni. Autogarage.",
    "wof:placetype":"venue"
},
  "geometry": {"coordinates":[7.5774140358,47.5695953369],"type":"Point"}
}