{
  "type": "Feature",
  "properties": {
    "iso:country":"CH",
    "sg:address":"B\u00fcelisackerstrasse 3",
    "sg:city":"Waltenschwil",
    "sg:orig_category":"Detailhandel mit Milcherzeugnissen U Eiern Verarbeitung von Milch",
    "sg:postcode":"5622",
    "sg:province":"Aargau",
    "wof:name":"K\u00e4sereigenossenschaft Weiningen",
    "wof:placetype":"venue"
},
  "geometry": {"coordinates":[8.8831300735,47.587348938],"type":"Point"}
}