{
  "type": "Feature",
  "properties": {
    "iso:country":"CH",
    "sg:address":"St. Johanns-ring 133",
    "sg:city":"Basel",
    "sg:orig_category":"Vereine Fasnacht",
    "sg:phone":"+41 61 381 63 85",
    "sg:postcode":"4056",
    "sg:province":"Basel-Stadt",
    "wof:name":"Gugge-muusig Bebbi Stompers",
    "wof:placetype":"venue"
},
  "geometry": {"coordinates":[7.574693203,47.5621681213],"type":"Point"}
}