{
  "type": "Feature",
  "properties": {
    "iso:country":"CH",
    "sg:address":"Chollerstrasse 1a 6300 Zug. Postfach",
    "sg:city":"Zug",
    "sg:orig_category":"Detailhandel mit Fahrr\u00e4dern Detailhandel mit Sportartikeln",
    "sg:phone":"+41 41 740 12 92",
    "sg:postcode":"6301",
    "sg:province":"Zug",
    "wof:name":"Velorado Ag Radsport & Langlauf",
    "wof:placetype":"venue"
},
  "geometry": {"coordinates":[8.483754158,47.1830635071],"type":"Point"}
}