{
  "type": "Feature",
  "properties": {
    "iso:country":"CH",
    "sg:address":"Steigstrasse 78",
    "sg:city":"Schaffhausen",
    "sg:orig_category":"Detailhandel mit Musikinstrumenten Detailhandel mit elektrischen Haushalts-,Radio U Fernsehger\u00e4ten s",
    "sg:phone":"+41 52 624 49 79",
    "sg:postcode":"8200",
    "sg:province":"Schaffhausen",
    "wof:name":"Meister Pianos Kommanditgesellschaft",
    "wof:placetype":"venue"
},
  "geometry": {"coordinates":[8.6281518936,47.6980705261],"type":"Point"}
}