{
  "type": "Feature",
  "properties": {
    "iso:country":"CH",
    "sg:address":"Route De Beaumont 2",
    "sg:city":"Fribourg",
    "sg:orig_category":"Versicherungen Generalagenturen",
    "sg:phone":"+41 78 632 59 57",
    "sg:postcode":"1700",
    "sg:province":"Fribourg",
    "wof:name":"Nationale Suisse Assurances Agence G\u00e9n\u00e9rale",
    "wof:placetype":"venue"
},
  "geometry": {"coordinates":[6.8231830597,47.1004486084],"type":"Point"}
}