{
  "type": "Feature",
  "properties": {
    "iso:country":"CH",
    "sg:address":"Gotthardstrasse 35",
    "sg:city":"Thalwil",
    "sg:orig_category":"Detailhandel mit Brot, Back U S\u00fcsswaren",
    "sg:phone":"+41 17201278",
    "sg:postcode":"8800",
    "sg:province":"Z\u00fcrich",
    "wof:name":"Hansruedi & Marita K\u00f6lliker B\u00e4ckerei-konditorei",
    "wof:placetype":"venue"
},
  "geometry": {"coordinates":[8.562922,47.296291],"type":"Point"}
}