{
  "type": "Feature",
  "properties": {
    "iso:country":"CH",
    "sg:address":"Unterer Rheinweg 86",
    "sg:city":"Basel",
    "sg:orig_category":"Architektur U Ingenieurb\u00fcros",
    "sg:phone":"+41 61 261 72 62",
    "sg:postcode":"4057",
    "sg:province":"Basel-Stadt",
    "wof:name":"Hasler Brigitte Innenarchitektur",
    "wof:placetype":"venue"
},
  "geometry": {"coordinates":[7.587054,47.566387],"type":"Point"}
}