{
  "type": "Feature",
  "properties": {
    "iso:country":"CH",
    "sg:address":"Rue Des Moulins 20",
    "sg:city":"Fleurier",
    "sg:orig_category":"Herstellung von Mess U Kontrollinstrumenten U vorrichtungen Mechanische Werkst\u00e4tten",
    "sg:phone":"+41 32 731 70 42",
    "sg:postcode":"2114",
    "sg:province":"Neuch\u00e2tel",
    "wof:name":"Cousson Paul & Cie.",
    "wof:placetype":"venue"
},
  "geometry": {"coordinates":[6.584236145,46.905002594],"type":"Point"}
}