{
  "type": "Feature",
  "properties": {
    "iso:country":"CH",
    "sg:address":"Anwanderweg 7",
    "sg:city":"Balsthal",
    "sg:orig_category":"Herstellung von Konstruktionsteilen, Fertigbauteilen U Ausbauelementen aus Holz",
    "sg:phone":"+41 21 943 30 56",
    "sg:postcode":"4710",
    "sg:province":"Solothurn",
    "wof:name":"Aschi-artisan, Adam",
    "wof:placetype":"venue"
},
  "geometry": {"coordinates":[6.8822221756,46.4711837769],"type":"Point"}
}