{
  "type": "Feature",
  "properties": {
    "iso:country":"CH",
    "sg:address":"Rue De Bourg 28.",
    "sg:city":"Lausanne",
    "sg:orig_category":"Detailhandel mit Tabakwaren Grosshandel mit Tabakwaren",
    "sg:phone":"+41 32 968 56 12",
    "sg:postcode":"1000",
    "sg:province":"Vaud",
    "wof:name":"Matthey Lucienne, Tabac-journaux",
    "wof:placetype":"venue"
},
  "geometry": {"coordinates":[6.833067894,47.1033973694],"type":"Point"}
}