{
  "type": "Feature",
  "properties": {
    "iso:country":"CH",
    "sg:address":"Unterdorf 120",
    "sg:city":"Maschwanden",
    "sg:orig_category":"Herstellung von Metallkonstruktionen",
    "sg:phone":"+41 17683111",
    "sg:postcode":"8933",
    "sg:province":"Z\u00fcrich",
    "wof:name":"Hp Montage Service Habegger",
    "wof:placetype":"venue"
},
  "geometry": {"coordinates":[8.4227304459,47.2335014343],"type":"Point"}
}