{
  "type": "Feature",
  "properties": {
    "iso:country":"CH",
    "sg:address":"Fischingerstrasse 60",
    "sg:city":"Sirnach",
    "sg:orig_category":"Erschliessung von Grundst\u00fccken Kauf U Verkauf von Immobilien auf eigene Rechnung",
    "sg:phone":"+41 71 966 65 83",
    "sg:postcode":"8370",
    "sg:province":"Thurgau",
    "wof:name":"R\u00fctihof Ag Sirnach",
    "wof:placetype":"venue"
},
  "geometry": {"coordinates":[8.99031353,47.4587173462],"type":"Point"}
}