{
  "type": "Feature",
  "properties": {
    "iso:country":"CH",
    "sg:address":"Avenue De Rumine 8 1005 Lausanne Case Postale 3069",
    "sg:city":"Lausanne",
    "sg:orig_category":"Detailhandel mit Antiquit\u00e4ten",
    "sg:phone":"+41 21 312 58 69",
    "sg:postcode":"1002",
    "sg:province":"Vaud",
    "wof:name":"Jean & Monique Roulet Jouets Anciens De Collections",
    "wof:placetype":"venue"
},
  "geometry": {"coordinates":[6.639414,46.5172],"type":"Point"}
}