{
  "type": "Feature",
  "properties": {
    "iso:country":"CH",
    "sg:address":"Rue Du Vieux Moulin",
    "sg:city":"Savi\u00e8se",
    "sg:orig_category":"Sportvereine Ballsport Badminton",
    "sg:phone":"+41 27 395 16 33",
    "sg:postcode":"1965",
    "sg:province":"Valais",
    "wof:name":"Badminton-club Savi\u00e8se",
    "wof:placetype":"venue"
},
  "geometry": {"coordinates":[7.3473768234,46.2495384216],"type":"Point"}
}