{
  "type": "Feature",
  "properties": {
    "iso:country":"CH",
    "sg:address":"Chemin De La For\u00eat 13",
    "sg:city":"Marly",
    "sg:orig_category":"Grosshandel mit B\u00fcromaschinen Grosshandel mit Datenverarbeitungsger\u00e4ten",
    "sg:phone":"+41 26 430 01 71",
    "sg:postcode":"1723",
    "sg:province":"Fribourg",
    "wof:name":"Columbus It Partner Schweiz Ag",
    "wof:placetype":"venue"
},
  "geometry": {"coordinates":[7.1657819748,46.7790603638],"type":"Point"}
}