{
  "type": "Feature",
  "properties": {
    "iso:country":"CH",
    "sg:address":"M\u00fcntschemiergasse 3",
    "sg:city":"Ins",
    "sg:orig_category":"Kosmetikinstitute",
    "sg:phone":"+41 32 313 17 52",
    "sg:postcode":"3232",
    "sg:province":"Bern",
    "wof:name":"Ursula Oertle City-coiffure",
    "wof:placetype":"venue"
},
  "geometry": {"coordinates":[7.107049942,47.0053329468],"type":"Point"}
}