{
  "type": "Feature",
  "properties": {
    "iso:country":"CH",
    "sg:address":"Industriestrasse 50b",
    "sg:city":"Wallisellen",
    "sg:classifiers":[
        {
            "category":"Shopping",
            "subcategory":"Computers & Home Electronics",
            "type":"Retail Goods"
        }
    ],
    "sg:phone":"+41 71 747 58 40",
    "sg:postcode":"8304",
    "sg:province":"Z\u00fcrich",
    "sg:tags":[
        "code",
        "bar",
        "scanner",
        "decoder"
    ],
    "wof:name":"Elcode Ag",
    "wof:placetype":"venue"
},
  "geometry": {"coordinates":[9.647725,47.449432],"type":"Point"}
}