{
  "type": "Feature",
  "properties": {
    "iso:country":"CH",
    "sg:address":"Rosenweg 7 3007 Bern. Postfach",
    "sg:city":"Bern",
    "sg:orig_category":"Herstellung von sonstigen elektrischen Ausr\u00fcstungen",
    "sg:postcode":"3005",
    "sg:province":"Bern",
    "wof:name":"Gruppe F\u00fcr Sicherheit, Benn & Kl\u00e4y Sicherheitsanlagen; Projektierung, Begutachtung Usw",
    "wof:placetype":"venue"
},
  "geometry": {"coordinates":[7.4348611832,46.9367675781],"type":"Point"}
}