{
  "type": "Feature",
  "properties": {
    "iso:country":"CH",
    "sg:address":"Stickereistrasse 9",
    "sg:city":"Balterswil",
    "sg:orig_category":"Allgemeiner Hochbau D\u00e4mmung gegen K\u00e4lte, W\u00e4rme, Schall U Ersch\u00fctterung",
    "sg:phone":"+41 79 696 04 05",
    "sg:postcode":"8362",
    "sg:province":"Thurgau",
    "wof:name":"Beerli Max Ag",
    "wof:placetype":"venue"
},
  "geometry": {"coordinates":[8.93663,47.453213],"type":"Point"}
}