{
  "type": "Feature",
  "properties": {
    "iso:country":"CH",
    "sg:address":"Rue De La Cour 6",
    "sg:city":"Gorgier",
    "sg:orig_category":"Sportschulen Gleitschirm-& Deltaflugschulen",
    "sg:phone":"+41 32 835 33 22",
    "sg:postcode":"2023",
    "sg:province":"Neuch\u00e2tel",
    "wof:name":"Christian Glardon Ecole Neuch\u00e2t.de Vol Libre",
    "wof:placetype":"venue"
},
  "geometry": {"coordinates":[6.7800621986,46.903011322],"type":"Point"}
}