{
  "type": "Feature",
  "properties": {
    "iso:country":"CH",
    "sg:address":"Wildbachstrasse 24",
    "sg:city":"Winterthur",
    "sg:orig_category":"Mit dem Versicherungsgewerbe verbundene T\u00e4tigkeiten",
    "sg:postcode":"8400",
    "sg:province":"Z\u00fcrich",
    "wof:name":"F\u00fcrrutter Consulting",
    "wof:placetype":"venue"
},
  "geometry": {"coordinates":[8.7311429977,47.4963684082],"type":"Point"}
}