{
  "type": "Feature",
  "properties": {
    "iso:country":"CH",
    "sg:address":"Via Pellandini 4",
    "sg:city":"Bellinzona",
    "sg:orig_category":"Grosshandel mit Eisenwaren sowie Installationsbedarf f\u00fcr Gas, Wasser U Heizung Grosshandel mit Erzen",
    "sg:phone":"+41 71 314 06 66",
    "sg:postcode":"6500",
    "sg:province":"Ticino",
    "wof:name":"Sfs Locher Ag",
    "wof:placetype":"venue"
},
  "geometry": {"coordinates":[9.3034305573,47.4068031311],"type":"Point"}
}