{
  "type": "Feature",
  "properties": {
    "iso:country":"CH",
    "sg:address":"Waldburgweg 31",
    "sg:city":"Zollikerberg",
    "sg:orig_category":"Non-Classified Establishments",
    "sg:postcode":"8125",
    "sg:province":"Z\u00fcrich",
    "wof:name":"Florin Communications",
    "wof:placetype":"venue"
},
  "geometry": {"coordinates":[8.5951471329,47.3484764099],"type":"Point"}
}