{
  "type": "Feature",
  "properties": {
    "addr:full":"Bernstrasse 35 Oftringen Aargau 4665",
    "addr:housenumber":"35",
    "addr:postcode":"4665",
    "addr:street":"Bernstrasse",
    "iso:country":"CH",
    "sg:address":"Bernstrasse 35",
    "sg:city":"Oftringen",
    "sg:orig_category":"Bauschreinerei",
    "sg:phone":"+41 62 797 16 12",
    "sg:postcode":"4665",
    "sg:province":"Aargau",
    "wof:name":"Hans-rudolf Hess Schreinerei",
    "wof:placetype":"venue"
},
  "geometry": {"coordinates":[7.90986,47.30809],"type":"Point"}
}