{
  "type": "Feature",
  "properties": {
    "iso:country":"CH",
    "sg:address":"Rue Des Mu\u00ebses 2",
    "sg:city":"Matran",
    "sg:orig_category":"Architektur U Ingenieurb\u00fcros",
    "sg:postcode":"1753",
    "sg:province":"Fribourg",
    "wof:name":"Klima-technik Zaugg",
    "wof:placetype":"venue"
},
  "geometry": {"coordinates":[9.48231,47.167633],"type":"Point"}
}