{
  "type": "Feature",
  "properties": {
    "iso:country":"CH",
    "sg:address":"Oberfeld 21",
    "sg:city":"Root",
    "sg:orig_category":"Handel mit Automobilen",
    "sg:phone":"+41 41 450 33 88",
    "sg:postcode":"6037",
    "sg:province":"Luzern",
    "wof:name":"Bucher Ernst Automobile",
    "wof:placetype":"venue"
},
  "geometry": {"coordinates":[8.3852901459,47.1092224121],"type":"Point"}
}