{
  "type": "Feature",
  "properties": {
    "iso:country":"CH",
    "sg:address":"Route De Choulex 39 1253 Vandoeuvres. Postfach",
    "sg:city":"Vandoeuvres",
    "sg:orig_category":"Non-Classified Establishments",
    "sg:postcode":"1253",
    "sg:province":"Gen\u00e8ve",
    "wof:name":"Formige Guerra S\u00e0rl",
    "wof:placetype":"venue"
},
  "geometry": {"coordinates":[6.2078809738,46.2195281982],"type":"Point"}
}