{
  "type": "Feature",
  "properties": {
    "iso:country":"CH",
    "sg:address":"Invua",
    "sg:city":"Posieux",
    "sg:orig_category":"Gewinnung von Kies U Sand",
    "sg:phone":"+41 26 402 06 81",
    "sg:postcode":"1725",
    "sg:province":"Fribourg",
    "wof:name":"Rograve Sa",
    "wof:placetype":"venue"
},
  "geometry": {"coordinates":[7.0953011513,46.7606010437],"type":"Point"}
}