{
  "type": "Feature",
  "properties": {
    "iso:country":"CH",
    "sg:address":"Hauptstrasse 58",
    "sg:city":"M\u00f6hlin",
    "sg:classifiers":[
        {
            "category":"Restaurant",
            "type":"Food & Drink"
        }
    ],
    "sg:phone":"+41 61 851 46 70",
    "sg:postcode":"4313",
    "sg:province":"Aargau",
    "wof:name":"Restaurant Sonne",
    "wof:placetype":"venue"
},
  "geometry": {"coordinates":[7.8434710503,47.5588684082],"type":"Point"}
}