{
  "type": "Feature",
  "properties": {
    "iso:country":"CH",
    "sg:address":"6280",
    "sg:city":"Hochdorf",
    "sg:classifiers":[
        {
            "category":"Education",
            "subcategory":"Vocational School",
            "type":"Public Place"
        }
    ],
    "sg:postcode":"6280",
    "sg:province":"Luzern",
    "sg:tags":[
        "koch-",
        "haushaltschulen"
    ],
    "wof:name":"Haushaltungsschule",
    "wof:placetype":"venue"
},
  "geometry": {"coordinates":[8.2834501266,47.1605415344],"type":"Point"}
}