{
  "type": "Feature",
  "properties": {
    "iso:country":"CH",
    "sg:address":"6543",
    "sg:city":"Arvigo",
    "sg:orig_category":"Gemeindeverwaltungen",
    "sg:phone":"+41 91 828 14 44",
    "sg:postcode":"6543",
    "sg:province":"Graubunden",
    "wof:name":"Amministrazione Comunale Di Arvigo-braggio-selma-cauco",
    "wof:placetype":"venue"
},
  "geometry": {"coordinates":[9.1141119003,46.302986145],"type":"Point"}
}