{
  "type": "Feature",
  "properties": {
    "iso:country":"CH",
    "sg:address":"Aupr\u00e8s De L''administration Co",
    "sg:city":"Bavois",
    "sg:orig_category":"Erschliessung von Grundst\u00fccken",
    "sg:postcode":"1372",
    "sg:province":"Vaud",
    "wof:name":"Restoroute De Bavois Sa",
    "wof:placetype":"venue"
},
  "geometry": {"coordinates":[6.5652198792,46.6858901978],"type":"Point"}
}