{
  "type": "Feature",
  "properties": {
    "iso:country":"CH",
    "sg:address":"Chemin De La Valletaine 5",
    "sg:city":"Fregi\u00e9court",
    "sg:orig_category":"Landesverteidigung, Sozialversicherung \u00d6ffentliche Verwaltung",
    "sg:phone":"+41 32 462 23 38",
    "sg:postcode":"2953",
    "sg:province":"Jura",
    "wof:name":"Administration Communale Protection Civile",
    "wof:placetype":"venue"
},
  "geometry": {"coordinates":[7.1923317909,47.4113540649],"type":"Point"}
}