{
  "type": "Feature",
  "properties": {
    "iso:country":"CH",
    "sg:address":"Stersm\u00fchlestr. 38",
    "sg:city":"Tentlingen",
    "sg:orig_category":"Herstellung von Konstruktionsteilen, Fertigbauteilen U Ausbauelementen aus Holz",
    "sg:phone":"+41 79 413 49 45",
    "sg:postcode":"1734",
    "sg:province":"Fribourg",
    "wof:name":"Zosso Bernard Ag",
    "wof:placetype":"venue"
},
  "geometry": {"coordinates":[7.1972551346,46.7614135742],"type":"Point"}
}