{
  "type": "Feature",
  "properties": {
    "iso:country":"CH",
    "sg:address":"Rosenhalde 23a",
    "sg:city":"Rorschacherberg",
    "sg:orig_category":"Kosmetikinstitute",
    "sg:phone":"+41 71 755 86 91",
    "sg:postcode":"9404",
    "sg:province":"St. Gallen",
    "wof:name":"Annemarie Saupper Kosmetikinstitut",
    "wof:placetype":"venue"
},
  "geometry": {"coordinates":[9.5607614517,47.373500824],"type":"Point"}
}