{
  "type": "Feature",
  "properties": {
    "iso:country":"CH",
    "sg:address":"Rothusweg 3a",
    "sg:city":"Zug",
    "sg:orig_category":"Finanzierungsinstitutionen",
    "sg:postcode":"6300",
    "sg:province":"Zug",
    "wof:name":"Verinsa Gmbh",
    "wof:placetype":"venue"
},
  "geometry": {"coordinates":[8.5187559128,47.170463562],"type":"Point"}
}