{
  "type": "Feature",
  "properties": {
    "iso:country":"CH",
    "sg:address":"Thunstrasse 93",
    "sg:city":"Bern",
    "sg:orig_category":"Bauingenieurb\u00fcros allgemein",
    "sg:phone":"+41 31 368 02 45",
    "sg:postcode":"3006",
    "sg:province":"Bern",
    "wof:name":"Ernst Kissling Ingenieurb\u00fcro",
    "wof:placetype":"venue"
},
  "geometry": {"coordinates":[7.462918,46.941212],"type":"Point"}
}