{
  "type": "Feature",
  "properties": {
    "iso:country":"CH",
    "sg:address":"Markgr\u00e4flerstrasse 34",
    "sg:city":"Basel",
    "sg:orig_category":"Maler U Glasergewerbe Malerei",
    "sg:phone":"+41 33 654 18 30",
    "sg:postcode":"4057",
    "sg:province":"Basel-Stadt",
    "wof:name":"St\u00e4hli S\u00f6hne",
    "wof:placetype":"venue"
},
  "geometry": {"coordinates":[7.6828708649,46.6671180725],"type":"Point"}
}