{
  "type": "Feature",
  "properties": {
    "iso:country":"CH",
    "sg:address":"Burgfeldweg 2 3006 Bern. Postfach 290",
    "sg:city":"Ostermundigen",
    "sg:orig_category":"Detailhandel mit Textilien Verlegen von Fussboden",
    "sg:phone":"+41 31 931 26 42",
    "sg:postcode":"3072",
    "sg:province":"Bern",
    "wof:name":"Erwin Ruprechter Innendekorationen",
    "wof:placetype":"venue"
},
  "geometry": {"coordinates":[7.4767098427,46.956111908],"type":"Point"}
}