{
  "type": "Feature",
  "properties": {
    "iso:country":"CH",
    "sg:address":"Hexenplatz",
    "sg:city":"Susten",
    "sg:orig_category":"Herstellung von Karosserien U Anh\u00e4ngern",
    "sg:phone":"+41 27 473 10 30",
    "sg:postcode":"3952",
    "sg:province":"Valais",
    "wof:name":"Carrosserie Illgraben Ag",
    "wof:placetype":"venue"
},
  "geometry": {"coordinates":[7.6344380379,46.3100090027],"type":"Point"}
}