{
  "type": "Feature",
  "properties": {
    "iso:country":"CH",
    "sg:address":"D\u00f6rfli 5 6060 Ramersberg. Postfach",
    "sg:city":"Ramersberg",
    "sg:orig_category":"Handelsvermittlung U Grosshandel Markt U Meinungsforschung",
    "sg:phone":"+41 41 660 43 88",
    "sg:postcode":"6060",
    "sg:province":"Obwalden",
    "wof:name":"Matracon Ag",
    "wof:placetype":"venue"
},
  "geometry": {"coordinates":[8.2324790955,46.8978157043],"type":"Point"}
}