{
  "type": "Feature",
  "properties": {
    "iso:country":"CH",
    "sg:address":"Industriestrasse 7",
    "sg:city":"Auw",
    "sg:orig_category":"Nationale Postdienste",
    "sg:phone":"+41 56 668 12 21",
    "sg:postcode":"5644",
    "sg:province":"Aargau",
    "wof:name":"Die Schweizerische Post",
    "wof:placetype":"venue"
},
  "geometry": {"coordinates":[8.3667049408,47.2127571106],"type":"Point"}
}