{
  "type": "Feature",
  "properties": {
    "iso:country":"CH",
    "sg:address":"Althardstrasse 190",
    "sg:city":"Regensdorf",
    "sg:orig_category":"Detailhandel mit elektrischen Haushalts-,Radio U Fernsehger\u00e4ten sowie Musikinstrumenten",
    "sg:phone":"+41 18712030",
    "sg:postcode":"8105",
    "sg:province":"Z\u00fcrich",
    "wof:name":"Z & B Video Ag",
    "wof:placetype":"venue"
},
  "geometry": {"coordinates":[8.4654655457,47.4421234131],"type":"Point"}
}