{
  "type": "Feature",
  "properties": {
    "iso:country":"CH",
    "sg:address":"1542",
    "sg:city":"Rueyres-les-pr\u00e9s",
    "sg:orig_category":"Grosshandel mit Getreide, Saatgut U Futtermitteln",
    "sg:phone":"+41 26 667 13 52",
    "sg:postcode":"1542",
    "sg:province":"Fribourg",
    "wof:name":"Liniger Pierre-andr\u00e9.",
    "wof:placetype":"venue"
},
  "geometry": {"coordinates":[6.9126901627,46.8576507568],"type":"Point"}
}