{
  "type": "Feature",
  "properties": {
    "iso:country":"CH",
    "sg:address":"Kirchstrasse 39 9490 Vaduz. Postfach 1515",
    "sg:city":"Vaduz",
    "sg:orig_category":"Verwaltung von Immobilien Wirtschaftspr\u00fcfung, Steuerberatung U Treuhand",
    "sg:phone":"+423 265 57 75",
    "sg:postcode":"9490",
    "wof:name":"Presenta Treuhand-& Verwaltungs-anstalt",
    "wof:placetype":"venue"
},
  "geometry": {"coordinates":[9.5178403854,47.1365699768],"type":"Point"}
}