{
  "type": "Feature",
  "properties": {
    "iso:country":"CH",
    "sg:address":"Konradstrasse 21",
    "sg:city":"Olten",
    "sg:orig_category":"Versicherungen Hauptagenturen",
    "sg:phone":"+41 62 205 10 60",
    "sg:postcode":"4600",
    "sg:province":"Solothurn",
    "wof:name":"La Suisse Versicherungen Hauptagentur Leben-invest",
    "wof:placetype":"venue"
},
  "geometry": {"coordinates":[7.9004302025,47.350479126],"type":"Point"}
}