{
  "type": "Feature",
  "properties": {
    "iso:country":"CH",
    "sg:address":"Baslerstrasse 46",
    "sg:city":"Olten",
    "sg:orig_category":"Forschung U Entwicklung im Bereich der Naturwissenschaften",
    "sg:phone":"+41 62 212 43 31",
    "sg:postcode":"4600",
    "sg:province":"Solothurn",
    "wof:name":"Arapul Optometric Consulting Aoc Gmbh",
    "wof:placetype":"venue"
},
  "geometry": {"coordinates":[7.9028348923,47.3518447876],"type":"Point"}
}