{
  "type": "Feature",
  "properties": {
    "iso:country":"CH",
    "sg:address":"Steinackerstrasse 35",
    "sg:city":"Urdorf",
    "sg:orig_category":"Sonstiger Grosshandel",
    "sg:phone":"+41 22 793 51 71",
    "sg:postcode":"8902",
    "sg:province":"Z\u00fcrich",
    "wof:name":"Pema-s\u00e9curit\u00e9 Sa",
    "wof:placetype":"venue"
},
  "geometry": {"coordinates":[6.1126742363,46.1801452637],"type":"Point"}
}