{
  "type": "Feature",
  "properties": {
    "iso:country":"CH",
    "sg:address":"Baarerstrasse 110c 6300 Zug. Postfach 2159",
    "sg:city":"Zug",
    "sg:orig_category":"Detailhandel mit M\u00f6beln Detailhandel mit M\u00f6beln U Haushaltsgegenst\u00e4nden",
    "sg:phone":"+41 41 761 14 56",
    "sg:postcode":"6302",
    "sg:province":"Zug",
    "wof:name":"M\u00f6bel Barth Ag.",
    "wof:placetype":"venue"
},
  "geometry": {"coordinates":[8.5189380646,47.1798820496],"type":"Point"}
}