{
  "type": "Feature",
  "properties": {
    "iso:country":"CH",
    "sg:address":"Neuch\u00e2tel Avenue De 50",
    "sg:city":"St-aubin-sauges",
    "sg:orig_category":"Elektrizit\u00e4tsversorgung",
    "sg:phone":"+41 32 835 17 88",
    "sg:postcode":"2024",
    "sg:province":"Neuch\u00e2tel",
    "wof:name":"Porret Service Sa",
    "wof:placetype":"venue"
},
  "geometry": {"coordinates":[6.7632799149,46.8871154785],"type":"Point"}
}