{
  "type": "Feature",
  "properties": {
    "iso:country":"CH",
    "sg:address":"Luzernstrasse 16",
    "sg:city":"Neuenkirch",
    "sg:orig_category":"Gemeindeverwaltungen",
    "sg:phone":"+41 52 674 21 11",
    "sg:postcode":"6206",
    "sg:province":"Luzern",
    "wof:name":"Gemeindeverwaltung Neuhausen Am Rheinfall",
    "wof:placetype":"venue"
},
  "geometry": {"coordinates":[8.6196098328,47.6815681458],"type":"Point"}
}