{
  "type": "Feature",
  "properties": {
    "iso:country":"CH",
    "sg:address":"Vi-longe Chemin De La 13",
    "sg:city":"Onex",
    "sg:orig_category":"Sonstige pers\u00f6nliche Dienstleistungen",
    "sg:phone":"+41 22 870 08 35",
    "sg:postcode":"1213",
    "sg:province":"Gen\u00e8ve",
    "wof:name":"Association Amsi",
    "wof:placetype":"venue"
},
  "geometry": {"coordinates":[6.0982432365,46.1815338135],"type":"Point"}
}