{
  "type": "Feature",
  "properties": {
    "iso:country":"CH",
    "sg:address":"Besson Avenue Fran\u00e7ois- 22",
    "sg:city":"Meyrin",
    "sg:orig_category":"Vermietung von Gebrauchsg\u00fctern",
    "sg:postcode":"1217",
    "sg:province":"Gen\u00e8ve",
    "wof:name":"Mag Two Sarl",
    "wof:placetype":"venue"
},
  "geometry": {"coordinates":[6.0772280693,46.2351493835],"type":"Point"}
}