{
  "type": "Feature",
  "properties": {
    "iso:country":"CH",
    "sg:address":"Riehenring 67",
    "sg:city":"Basel",
    "sg:classifiers":[
        {
            "category":"Restaurant",
            "type":"Food & Drink"
        }
    ],
    "sg:phone":"+41 55 410 12 25",
    "sg:postcode":"4058",
    "sg:province":"Basel-Stadt",
    "wof:name":"Restaurant Ufenau",
    "wof:placetype":"venue"
},
  "geometry": {"coordinates":[8.7781352997,47.2013778687],"type":"Point"}
}