{
  "type": "Feature",
  "properties": {
    "iso:country":"CH",
    "sg:address":"Centralbahnstrasse 7 4051 Basel. Postfach",
    "sg:city":"Basel",
    "sg:orig_category":"Vermietung U Verpachtung von eigenen Immobilien",
    "sg:phone":"+41 61 281 27 07",
    "sg:postcode":"4051",
    "sg:province":"Basel-Stadt",
    "wof:name":"Property Light Ag Entwicklung U. Vermarktung Neuer Formen Von Immobiliareigentums Usw",
    "wof:placetype":"venue"
},
  "geometry": {"coordinates":[7.5883860588,47.548500061],"type":"Point"}
}