{
  "type": "Feature",
  "properties": {
    "iso:country":"CH",
    "sg:address":"Karl B\u00fcgler-strasse 10",
    "sg:city":"Neftenbach",
    "sg:orig_category":"Detailhandel mit M\u00f6beln U Haushaltsgegenst\u00e4nden",
    "sg:phone":"+41 52 315 27 51",
    "sg:postcode":"8413",
    "sg:province":"Z\u00fcrich",
    "wof:name":"Heija M\u00f6bel-abholmarkt Ag",
    "wof:placetype":"venue"
},
  "geometry": {"coordinates":[8.6599369049,47.5187454224],"type":"Point"}
}