{
  "type": "Feature",
  "properties": {
    "iso:country":"CH",
    "sg:address":"Frauenfelderstrasse 2",
    "sg:city":"Sirnach",
    "sg:orig_category":"Architekturb\u00fcros",
    "sg:phone":"+41 22 771 01 02",
    "sg:postcode":"8370",
    "sg:province":"Thurgau",
    "wof:name":"Charles Steiger Bureau D'architecture",
    "wof:placetype":"venue"
},
  "geometry": {"coordinates":[6.104253,46.149029],"type":"Point"}
}