{
  "type": "Feature",
  "properties": {
    "iso:country":"CH",
    "sg:address":"Seonerstrasse 287",
    "sg:city":"Egliswil",
    "sg:orig_category":"Grosshandel mit sonstigen Maschinen U Ausr\u00fcstungen f\u00fcr Industrie, Handel U Schiffahrt Technische, ph",
    "sg:phone":"+41 62 775 21 32",
    "sg:postcode":"5704",
    "sg:province":"Aargau",
    "wof:name":"Istag Ag",
    "wof:placetype":"venue"
},
  "geometry": {"coordinates":[8.1756782532,47.3488845825],"type":"Point"}
}