{
  "type": "Feature",
  "properties": {
    "iso:country":"CH",
    "sg:address":"Landskronstrasse 38 4056 Basel. Postfach",
    "sg:city":"Basel",
    "sg:orig_category":"Detailhandel mit Waren verschiedener Art, Hauptrichtung Nahrungsmittel",
    "sg:phone":"+41 61 321 13 73",
    "sg:postcode":"4051",
    "sg:province":"Basel-Stadt",
    "wof:name":"Shah Enterprises (import & Export) Esswaren, Getr\u00e4nke, Schmuck, Marmor, Kleider; Im, Export",
    "wof:placetype":"venue"
},
  "geometry": {"coordinates":[7.5767021179,47.5684700012],"type":"Point"}
}