{
  "type": "Feature",
  "properties": {
    "addr:full":"Niesenstrasse 6 Konolfingen Bern 3510",
    "addr:housenumber":"6",
    "addr:postcode":"3510",
    "addr:street":"Niesenstrasse;Bern",
    "iso:country":"CH",
    "sg:address":"Niesenstrasse 6",
    "sg:city":"Konolfingen",
    "sg:classifiers":[
        {
            "category":"Banks & Credit Unions",
            "subcategory":"Investment Brokerage",
            "type":"Services"
        }
    ],
    "sg:phone":"+41 31 791 18 91",
    "sg:postcode":"3510",
    "sg:province":"Bern",
    "sg:tags":[
        "axial",
        "fan"
    ],
    "wof:name":"Bonotec Ag",
    "wof:placetype":"venue"
},
  "geometry": {"coordinates":[7.617753,46.878269],"type":"Point"}
}