{
  "type": "Feature",
  "properties": {
    "iso:country":"CH",
    "sg:address":"Industriestrasse 9",
    "sg:city":"Reichenburg",
    "sg:orig_category":"Instandhaltung U Reparatur von Automobilen",
    "sg:phone":"+41 55 444 30 33",
    "sg:postcode":"8864",
    "sg:province":"Schwyz",
    "wof:name":"Michele Cecio Carrosserie",
    "wof:placetype":"venue"
},
  "geometry": {"coordinates":[8.9871530533,47.1702842712],"type":"Point"}
}