{
  "type": "Feature",
  "properties": {
    "iso:country":"CH",
    "sg:address":"Kanalstrasse 10",
    "sg:city":"Mollis",
    "sg:orig_category":"Physiotherapie",
    "sg:phone":"+41 55 612 37 74",
    "sg:postcode":"8753",
    "sg:province":"Glarus",
    "wof:name":"Ren\u00e9 Brandenberger Physiotherapie",
    "wof:placetype":"venue"
},
  "geometry": {"coordinates":[9.0716772079,47.095615387],"type":"Point"}
}