{
  "type": "Feature",
  "properties": {
    "addr:full":"Markgr\u00e4flerstrasse 41 Basel Basel-Stadt 4057",
    "addr:housenumber":"41",
    "addr:postcode":"4057",
    "addr:street":"Markgraeflerstrasse",
    "iso:country":"CH",
    "sg:address":"Markgr\u00e4flerstrasse 41",
    "sg:city":"Basel",
    "sg:orig_category":"Betrieb U technische Hilfsdienste des Kultur U Unterhaltungswesens",
    "sg:phone":"+41 61 683 56 25",
    "sg:postcode":"4057",
    "sg:province":"Basel-Stadt",
    "wof:name":"Creative Events Rufer Caroline",
    "wof:placetype":"venue"
},
  "geometry": {"coordinates":[7.59311,47.570168],"type":"Point"}
}