{
  "type": "Feature",
  "properties": {
    "iso:country":"CH",
    "sg:address":"Gansacherweg 42",
    "sg:city":"Gelterkinden",
    "sg:orig_category":"Bauingenieurb\u00fcros allgemein",
    "sg:phone":"+41 79 453 98 88",
    "sg:postcode":"4460",
    "sg:province":"Basel-Landschaft",
    "wof:name":"Hans D. Boss Ingenieurb\u00fcro",
    "wof:placetype":"venue"
},
  "geometry": {"coordinates":[9.934305,46.572521],"type":"Point"}
}