{
  "type": "Feature",
  "properties": {
    "iso:country":"CH",
    "sg:address":"B\u00e4renfelserstrasse 47",
    "sg:city":"Basel",
    "sg:classifiers":[
        {
            "category":"Home & Garden",
            "subcategory":"Building Materials",
            "type":"Retail Goods"
        }
    ],
    "sg:phone":"+41 61 699 10 10",
    "sg:postcode":"4057",
    "sg:province":"Basel-Stadt",
    "sg:tags":[
        "installation",
        "electric"
    ],
    "wof:name":"Regio Elektro Team Ag",
    "wof:placetype":"venue"
},
  "geometry": {"coordinates":[7.587433815,47.5682067871],"type":"Point"}
}