{
  "type": "Feature",
  "properties": {
    "iso:country":"CH",
    "sg:address":"Anna Heer-strasse 2",
    "sg:city":"Suhr",
    "sg:orig_category":"Detailhandel mit Schreib U Papeteriewaren",
    "sg:phone":"+41 62 842 31 55",
    "sg:postcode":"5034",
    "sg:province":"Aargau",
    "wof:name":"Papeterie Weber",
    "wof:placetype":"venue"
},
  "geometry": {"coordinates":[8.0794353485,47.3727722168],"type":"Point"}
}