{
  "type": "Feature",
  "properties": {
    "iso:country":"CH",
    "sg:address":"Gewerbestrasse 7 3203 M\u00fchleberg. Postfach",
    "sg:city":"M\u00fchleberg",
    "sg:orig_category":"Erschliessung von Grundst\u00fccken",
    "sg:postcode":"3203",
    "sg:province":"Bern",
    "wof:name":"Wohnbaugenossenschaft Hapfere M\u00fchleberg",
    "wof:placetype":"venue"
},
  "geometry": {"coordinates":[7.2748780251,46.9597129822],"type":"Point"}
}