{
  "type": "Feature",
  "properties": {
    "iso:country":"CH",
    "sg:address":"Kesselstrasse 1 8957 Spreitenbach. Postfach 1318",
    "sg:city":"Spreitenbach",
    "sg:orig_category":"Grosshandel mit Eisenwaren sowie Installationsbedarf f\u00fcr Gas, Wasser U Heizung Grosshandel mit sonst",
    "sg:phone":"+41 56 401 32 53",
    "sg:postcode":"8957",
    "sg:province":"Aargau",
    "wof:name":"Torgen (switzerland) Gmbh Industriearmaturen",
    "wof:placetype":"venue"
},
  "geometry": {"coordinates":[8.3731603622,47.4299812317],"type":"Point"}
}