{
  "type": "Feature",
  "properties": {
    "iso:country":"CH",
    "sg:address":"Schutzengelstrasse 34c",
    "sg:city":"Baar",
    "sg:orig_category":"Handel mit Automobilen",
    "sg:postcode":"6340",
    "sg:province":"Zug",
    "wof:name":"Jolex Car + Hifi, Alex Joss",
    "wof:placetype":"venue"
},
  "geometry": {"coordinates":[8.5359869003,47.1978034973],"type":"Point"}
}