{
  "type": "Feature",
  "properties": {
    "iso:country":"CH",
    "sg:address":"Steinenvorstadt 27 4000 Basel. Postfach",
    "sg:city":"Basel",
    "sg:orig_category":"Detektivb\u00fcros U \u00dcberwachung",
    "sg:postcode":"4051",
    "sg:province":"Basel-Stadt",
    "wof:name":"Ihre Sicherheit, Sent\u00fcrk Alim",
    "wof:placetype":"venue"
},
  "geometry": {"coordinates":[7.5891151428,47.5531692505],"type":"Point"}
}