{
  "type": "Feature",
  "properties": {
    "iso:country":"CH",
    "sg:address":"S\u00e4geweg 14",
    "sg:city":"Lyss",
    "sg:orig_category":"Non-Classified Establishments",
    "sg:phone":"+41 32 385 23 76",
    "sg:postcode":"3250",
    "sg:province":"Bern",
    "wof:name":"Ccs Lyss Gmbh",
    "wof:placetype":"venue"
},
  "geometry": {"coordinates":[7.3129110336,47.0666885376],"type":"Point"}
}