{
  "type": "Feature",
  "properties": {
    "iso:country":"CH",
    "sg:address":"Ziegelgasse 14 3714 Frutigen. Postfach",
    "sg:city":"Frutigen",
    "sg:orig_category":"Architektur U Ingenieurb\u00fcros",
    "sg:phone":"+41 33 672 71 71",
    "sg:postcode":"3714",
    "sg:province":"Bern",
    "wof:name":"Ramu Ingenieure Ag",
    "wof:placetype":"venue"
},
  "geometry": {"coordinates":[7.646928,46.590755],"type":"Point"}
}