{
  "type": "Feature",
  "properties": {
    "iso:country":"CH",
    "sg:address":"Bernstrasse 57",
    "sg:city":"Ostermundigen",
    "sg:orig_category":"Detailhandel mit Haustieren U zoologischem Bedarf Fachdetailhandel in Verkaufsr\u00e4umen",
    "sg:phone":"+41 52 763 26 90",
    "sg:postcode":"3072",
    "sg:province":"Bern",
    "wof:name":"Setuna Ag",
    "wof:placetype":"venue"
},
  "geometry": {"coordinates":[9.0056295395,47.6076393127],"type":"Point"}
}