{
  "type": "Feature",
  "properties": {
    "iso:country":"CH",
    "sg:address":"Birchstrasse 3",
    "sg:city":"Z\u00fcrich",
    "sg:orig_category":"Interessenvertretungen",
    "sg:phone":"+41 13619230",
    "sg:postcode":"8057",
    "sg:province":"Z\u00fcrich",
    "wof:name":"Chinese Association For Technology And Economy Eschange In Switzerland",
    "wof:placetype":"venue"
},
  "geometry": {"coordinates":[8.5344219208,47.404209137],"type":"Point"}
}