{
  "type": "Feature",
  "properties": {
    "iso:country":"CH",
    "sg:address":"Brunnenrain 6",
    "sg:city":"Ittigen",
    "sg:classifiers":[
        {
            "category":"Food & Beverages",
            "subcategory":"Specialty",
            "type":"Retail Goods"
        }
    ],
    "sg:phone":"+41 31 302 84 00",
    "sg:postcode":"3063",
    "sg:province":"Bern",
    "sg:tags":[
        "caterer"
    ],
    "wof:name":"K\u00f6stliches F\u00fcr Kenner Party-service",
    "wof:placetype":"venue"
},
  "geometry": {"coordinates":[7.486613,46.979416],"type":"Point"}
}