{
  "type": "Feature",
  "properties": {
    "iso:country":"CH",
    "sg:address":"Sandgruebestrasse 4 6210 Sursee. Postfach 3122",
    "sg:city":"Sursee",
    "sg:orig_category":"Druck ohne Zeitungsdruck Verlagsgewerbe",
    "sg:phone":"+41 41 926 70 10",
    "sg:postcode":"6210",
    "sg:province":"Luzern",
    "wof:name":"Hess Robert Ag",
    "wof:placetype":"venue"
},
  "geometry": {"coordinates":[8.1100902557,47.1765480042],"type":"Point"}
}