{
  "type": "Feature",
  "properties": {
    "iso:country":"CH",
    "sg:address":"Rue Des Remparts 13",
    "sg:city":"Sion",
    "sg:orig_category":"Unternehmensberatung",
    "sg:phone":"+41 27 322 16 25",
    "sg:postcode":"1950",
    "sg:province":"Valais",
    "wof:name":"Rossier G\u00e9rard Conseils",
    "wof:placetype":"venue"
},
  "geometry": {"coordinates":[7.3598232269,46.2313957214],"type":"Point"}
}