{
  "type": "Feature",
  "properties": {
    "iso:country":"CH",
    "sg:address":"Hintergasse 11",
    "sg:city":"B\u00fclach",
    "sg:orig_category":"Aktivit\u00e4ten der Generalunternehmen im Baugewerbe",
    "sg:phone":"+41 56 664 24 15",
    "sg:postcode":"8180",
    "sg:province":"Z\u00fcrich",
    "wof:name":"Ernst Ruckstuhl Eruco Generalbau",
    "wof:placetype":"venue"
},
  "geometry": {"coordinates":[8.317482,47.282578],"type":"Point"}
}