{
  "type": "Feature",
  "properties": {
    "iso:country":"CH",
    "sg:address":"Worblentalstrasse 27",
    "sg:city":"Ittigen",
    "sg:orig_category":"Grosshandel mit Holz U Bauelementen aus Holz Grosshandel mit Holz U Baustoffen",
    "sg:phone":"+41 31 921 23 64",
    "sg:postcode":"3063",
    "sg:province":"Bern",
    "wof:name":"Anliker Ag Holzwerkstoffe",
    "wof:placetype":"venue"
},
  "geometry": {"coordinates":[7.4700260162,46.9787597656],"type":"Point"}
}