{
  "type": "Feature",
  "properties": {
    "iso:country":"CH",
    "sg:address":"Poststrasse 19",
    "sg:city":"Richterswil",
    "sg:orig_category":"Detailhandel mit Waren verschiedener Art, Hauptrichtung Nahrungsmittel Grosshandel mit Nahrungsmitte",
    "sg:phone":"+41 17863013",
    "sg:postcode":"8805",
    "sg:province":"Z\u00fcrich",
    "wof:name":"Peppone Spezialit\u00e4ten Gmbh",
    "wof:placetype":"venue"
},
  "geometry": {"coordinates":[8.7059707642,47.2080802917],"type":"Point"}
}