{
  "type": "Feature",
  "properties": {
    "iso:country":"CH",
    "sg:address":"Via San Gottardo 141",
    "sg:city":"Savosa",
    "sg:orig_category":"Grosshandel mit Datenverarbeitungsger\u00e4ten Grosshandel mit Software",
    "sg:phone":"+41 91 966 17 77",
    "sg:postcode":"6942",
    "sg:province":"Ticino",
    "wof:name":"A & O Computer Ti Sa",
    "wof:placetype":"venue"
},
  "geometry": {"coordinates":[8.9403295517,46.0176696777],"type":"Point"}
}