{
  "type": "Feature",
  "properties": {
    "iso:country":"CH",
    "sg:address":"Bollwerk 21",
    "sg:city":"Bern",
    "sg:orig_category":"Pensionskassen",
    "sg:postcode":"3011",
    "sg:province":"Bern",
    "wof:name":"Arcasia Ag",
    "wof:placetype":"venue"
},
  "geometry": {"coordinates":[7.440723896,46.9499740601],"type":"Point"}
}