{
  "type": "Feature",
  "properties": {
    "iso:country":"CH",
    "sg:address":"Hauptstrasse 3235 Erlach. Postfach",
    "sg:city":"Erlach",
    "sg:orig_category":"RESTAURANTS: TEA-ROOMS",
    "sg:postcode":"3235",
    "sg:province":"Bern",
    "wof:name":"Z\u00fclli Rudolf",
    "wof:placetype":"venue"
},
  "geometry": {"coordinates":[7.0905890465,47.0326766968],"type":"Point"}
}