{
  "type": "Feature",
  "properties": {
    "iso:country":"CH",
    "sg:address":"Via Pentima 14",
    "sg:city":"Gordola",
    "sg:orig_category":"Blumen U Zierpflanzenbau Gem\u00fcsebau",
    "sg:phone":"+41 91 745 14 43",
    "sg:postcode":"6596",
    "sg:province":"Ticino",
    "wof:name":"Renato Pura Fioricoltura & Orticoltura",
    "wof:placetype":"venue"
},
  "geometry": {"coordinates":[8.863185,46.180183],"type":"Point"}
}