{
  "type": "Feature",
  "properties": {
    "iso:country":"CH",
    "sg:address":"F\u00e4rberstrasse 6",
    "sg:city":"Wollerau",
    "sg:classifiers":[
        {
            "category":"Communications",
            "subcategory":"Film & Video Production",
            "type":"Services"
        }
    ],
    "sg:phone":"+41 17848786",
    "sg:postcode":"8832",
    "sg:province":"Schwyz",
    "sg:tags":[
        "dry",
        "transfer",
        "picture"
    ],
    "wof:name":"Walter Waibel Ag",
    "wof:placetype":"venue"
},
  "geometry": {"coordinates":[8.7195358276,47.1902236938],"type":"Point"}
}