{
  "type": "Feature",
  "properties": {
    "iso:country":"CH",
    "sg:address":"Borgo",
    "sg:city":"Brusio",
    "sg:orig_category":"Herstellung von Konstruktionsteilen, Fertigbauteilen U Ausbauelementen aus Holz S\u00e4gewerke",
    "sg:phone":"+41 71 644 92 92",
    "sg:postcode":"7743",
    "sg:province":"Graubunden",
    "wof:name":"Oberholzer L. Ag",
    "wof:placetype":"venue"
},
  "geometry": {"coordinates":[9.1995153427,47.5188674927],"type":"Point"}
}