{
  "type": "Feature",
  "properties": {
    "iso:country":"CH",
    "sg:address":"3001 Bern. Postfach",
    "sg:city":"Bern",
    "sg:orig_category":"Schulpflegen",
    "sg:postcode":"3001",
    "sg:province":"Bern",
    "wof:name":"Primarschulkommission Thun-str\u00e4ttligen Ii",
    "wof:placetype":"venue"
},
  "geometry": {"coordinates":[7.623691082,46.7237892151],"type":"Point"}
}