{
  "type": "Feature",
  "properties": {
    "iso:country":"CH",
    "sg:address":"Tobel 9302 Kronb\u00fchl. Postfach",
    "sg:city":"Kronb\u00fchl",
    "sg:orig_category":"Kalb U Schweine-M\u00e4sterei U Zucht",
    "sg:phone":"+41 71 385 42 31",
    "sg:postcode":"9302",
    "wof:name":"Zollinger Kurt",
    "wof:placetype":"venue"
},
  "geometry": {"coordinates":[9.2743349075,47.4293403625],"type":"Point"}
}