{
  "type": "Feature",
  "properties": {
    "iso:country":"CH",
    "sg:address":"Clarastrasse 22 4058 Basel. Postfach 70",
    "sg:city":"Basel",
    "sg:orig_category":"Fachdetailhandel mit pharmazeutischen Produkten",
    "sg:phone":"+41 61 691 70 26",
    "sg:postcode":"4005",
    "sg:province":"Basel-Stadt",
    "wof:name":"St. Clara-apotheke Dr. R. Taugwalder",
    "wof:placetype":"venue"
},
  "geometry": {"coordinates":[7.5962510109,47.5623817444],"type":"Point"}
}