{
  "type": "Feature",
  "properties": {
    "iso:country":"CH",
    "sg:address":"Hochfeldweg 3",
    "sg:city":"Ebnat-kappel",
    "sg:orig_category":"Physiotherapie",
    "sg:phone":"+41 71 993 30 70",
    "sg:postcode":"9642",
    "sg:province":"St. Gallen",
    "wof:name":"Brigitte Meisser Physiotherapie",
    "wof:placetype":"venue"
},
  "geometry": {"coordinates":[9.1176557541,47.2694587708],"type":"Point"}
}