{
  "type": "Feature",
  "properties": {
    "iso:country":"CH",
    "sg:address":"Rue Du Borgeaud 3a 1196 Gland. Postfach",
    "sg:city":"Gland",
    "sg:orig_category":"Fachdetailhandel mit pharmazeutischen Produkten",
    "sg:phone":"+41 22 364 24 24",
    "sg:postcode":"1196",
    "sg:province":"Vaud",
    "wof:name":"Pharmacie Nouvelle, Mayor Robert & Rudaz Rita Pharmacie",
    "wof:placetype":"venue"
},
  "geometry": {"coordinates":[6.2615017891,46.4234771729],"type":"Point"}
}