{
  "type": "Feature",
  "properties": {
    "iso:country":"CH",
    "sg:address":"Eggstrasse 36c",
    "sg:city":"Oberengstringen",
    "sg:orig_category":"Softwareentwicklung U beratung",
    "sg:phone":"+41 17504422",
    "sg:postcode":"8102",
    "sg:province":"Z\u00fcrich",
    "wof:name":"Lewis Consulting Gmbh",
    "wof:placetype":"venue"
},
  "geometry": {"coordinates":[8.4721374512,47.4072532654],"type":"Point"}
}