{
  "type": "Feature",
  "properties": {
    "iso:country":"CH",
    "sg:address":"En Mussel",
    "sg:city":"Gollion",
    "sg:orig_category":"Kalb U Schweine-M\u00e4sterei U Zucht",
    "sg:phone":"+41 79 611 78 84",
    "sg:postcode":"1124",
    "sg:province":"Vaud",
    "wof:name":"Secoporc Sa",
    "wof:placetype":"venue"
},
  "geometry": {"coordinates":[6.5117697716,46.5858383179],"type":"Point"}
}