{
  "type": "Feature",
  "properties": {
    "iso:country":"CH",
    "sg:address":"Via Besso 11 6900 Lugano. Postfach",
    "sg:city":"Massagno",
    "sg:orig_category":"Grosshandel mit Nahrungsmitteln, Getr\u00e4nken U Tabakwaren Nahrungsmittel-Industrie: Rohstoffe",
    "sg:phone":"+41 91 950 08 70",
    "sg:postcode":"6900",
    "sg:province":"Ticino",
    "wof:name":"Golositalia Sagl Prodotti Tipici Italiani Spec. Alimentari Ecc.; Import., Comm.",
    "wof:placetype":"venue"
},
  "geometry": {"coordinates":[8.9433298111,46.006111145],"type":"Point"}
}