{
  "type": "Feature",
  "properties": {
    "iso:country":"CH",
    "sg:address":"Wangenstrasse 40 3360 Herzogenbuchsee. Postfach",
    "sg:city":"Herzogenbuchsee",
    "sg:orig_category":"Fachdetailhandel in Verkaufsr\u00e4umen",
    "sg:postcode":"3360",
    "sg:province":"Bern",
    "wof:name":"Gleniss Gmbh Schmuckartikel; Herstellung, Kauf, Verkauf, Handel Usw.",
    "wof:placetype":"venue"
},
  "geometry": {"coordinates":[7.7039151192,47.191570282],"type":"Point"}
}