{
  "type": "Feature",
  "properties": {
    "iso:country":"CH",
    "sg:address":"H\u00f6henweg 10",
    "sg:city":"Ibach",
    "sg:orig_category":"Allgemeiner Hochbau Zimmerei, Dachdeckerei, Bauspenglerei U Abdichtung",
    "sg:phone":"+41 41 811 41 91",
    "sg:postcode":"6438",
    "sg:province":"Schwyz",
    "wof:name":"Heinzer Bedachungen & Fassaden Gmbh",
    "wof:placetype":"venue"
},
  "geometry": {"coordinates":[8.651338,47.01231],"type":"Point"}
}