{
  "type": "Feature",
  "properties": {
    "iso:country":"CH",
    "sg:address":"Rue Henri-correvon 21 1400 Yverdon-les-bains. Postfach",
    "sg:city":"Yverdon-les-bains",
    "sg:orig_category":"Softwareentwicklung U beratung",
    "sg:postcode":"1400",
    "sg:province":"Vaud",
    "wof:name":"Hermann Informatique",
    "wof:placetype":"venue"
},
  "geometry": {"coordinates":[6.6561431885,46.7766876221],"type":"Point"}
}