{
  "type": "Feature",
  "properties": {
    "iso:country":"CH",
    "sg:address":"Oberer Steisteg 18",
    "sg:city":"Schwyz",
    "sg:orig_category":"Unclassifiable Establishments",
    "sg:postcode":"6430",
    "sg:province":"Schwyz",
    "wof:name":"Alhebru Ag",
    "wof:placetype":"venue"
},
  "geometry": {"coordinates":[7.5187110901,47.5097618103],"type":"Point"}
}