{
  "type": "Feature",
  "properties": {
    "iso:country":"CH",
    "sg:address":"Dorfstrasse 33",
    "sg:city":"Richterswil",
    "sg:orig_category":"P\u00e9dicure",
    "sg:phone":"+41 17840702",
    "sg:postcode":"8805",
    "sg:province":"Z\u00fcrich",
    "wof:name":"Hanny Binggeli P\u00e9dicure",
    "wof:placetype":"venue"
},
  "geometry": {"coordinates":[8.7053279877,47.2072105408],"type":"Point"}
}