{
  "type": "Feature",
  "properties": {
    "iso:country":"CH",
    "sg:address":"Luegislandstrasse 160",
    "sg:city":"Z\u00fcrich",
    "sg:orig_category":"Schwimmb\u00e4der",
    "sg:phone":"+41 13213264",
    "sg:postcode":"8051",
    "sg:province":"Z\u00fcrich",
    "wof:name":"Freibad Auhof",
    "wof:placetype":"venue"
},
  "geometry": {"coordinates":[8.5715751648,47.4091491699],"type":"Point"}
}