{
  "type": "Feature",
  "properties": {
    "iso:country":"CH",
    "sg:address":"Casa Lina",
    "sg:city":"Avegno",
    "sg:orig_category":"Parkettleger",
    "sg:phone":"+41 91 796 16 87",
    "sg:postcode":"6670",
    "sg:province":"Ticino",
    "wof:name":"Leo Zimmermann Impresa Di Parchett",
    "wof:placetype":"venue"
},
  "geometry": {"coordinates":[8.7435398102,46.2055282593],"type":"Point"}
}