{
  "type": "Feature",
  "properties": {
    "iso:country":"CH",
    "sg:address":"Gotschnastrasse 14 7250 Klosters. Postfach",
    "sg:city":"Klosters",
    "sg:orig_category":"Detailhandel mit B\u00fcchern, Zeitungen, Schreib U Papeteriewaren Detailhandel mit Schreib U Papeteriewa",
    "sg:phone":"+41 81 422 47 57",
    "sg:postcode":"7250",
    "sg:province":"Graubunden",
    "wof:name":"Papeterie Gotschna Gmbh",
    "wof:placetype":"venue"
},
  "geometry": {"coordinates":[9.881408,46.867756],"type":"Point"}
}