{
  "type": "Feature",
  "properties": {
    "iso:country":"CH",
    "sg:address":"9622",
    "sg:city":"Krinau",
    "sg:orig_category":"Sportvereine Sch\u00fctzen",
    "sg:postcode":"9622",
    "sg:province":"St. Gallen",
    "wof:name":"Milit\u00e4rsch\u00fctzenverein",
    "wof:placetype":"venue"
},
  "geometry": {"coordinates":[9.1944704056,47.3053283691],"type":"Point"}
}