{
  "type": "Feature",
  "properties": {
    "iso:country":"CH",
    "sg:address":"K\u00e4sereistrasse 5",
    "sg:city":"Deitingen",
    "sg:orig_category":"Sportvereine Schwingen",
    "sg:postcode":"4543",
    "sg:province":"Solothurn",
    "wof:name":"Schwingklub Kirchberg",
    "wof:placetype":"venue"
},
  "geometry": {"coordinates":[7.6193041801,47.213809967],"type":"Point"}
}