{
  "type": "Feature",
  "properties": {
    "iso:country":"CH",
    "sg:address":"Schwimmbadstrasse 41",
    "sg:city":"Wettingen",
    "sg:orig_category":"Wohnheime",
    "sg:postcode":"5430",
    "sg:province":"Aargau",
    "wof:name":"Senora Ag",
    "wof:placetype":"venue"
},
  "geometry": {"coordinates":[8.3128757477,47.4604644775],"type":"Point"}
}