{
  "type": "Feature",
  "properties": {
    "iso:country":"CH",
    "sg:address":"Br\u00fchlstrasse 57",
    "sg:city":"Biel/bienne",
    "sg:orig_category":"Herstellung von Ger\u00e4ten der Elektrizit\u00e4tserzeugung, -verteilung u.\u00e4. -Herstellung von elektronischen",
    "sg:phone":"+41 41 672 75 11",
    "sg:postcode":"2503",
    "sg:province":"Bern",
    "wof:name":"Csem Centre Suisse D'electron & De Microtechnique Sa",
    "wof:placetype":"venue"
},
  "geometry": {"coordinates":[8.2757520676,46.9359817505],"type":"Point"}
}