{
  "type": "Feature",
  "properties": {
    "iso:country":"CH",
    "sg:address":"1185",
    "sg:city":"Mont-sur-rolle",
    "sg:orig_category":"Gemischte Landwirtschaft",
    "sg:postcode":"1185",
    "sg:province":"Vaud",
    "wof:name":"Soci\u00e9t\u00e9 Coop\u00e9rative Du Domaine De L'azemotaz",
    "wof:placetype":"venue"
},
  "geometry": {"coordinates":[7.1772699356,46.0913352966],"type":"Point"}
}