{
  "type": "Feature",
  "properties": {
    "iso:country":"CH",
    "sg:address":"L\u00f6hrenweg 63",
    "sg:city":"Biel/bienne",
    "sg:orig_category":"Unclassifiable Establishments",
    "sg:postcode":"2504",
    "sg:province":"Bern",
    "wof:name":"Agence G\u00e9rimmob, Charles Riand",
    "wof:placetype":"venue"
},
  "geometry": {"coordinates":[7.4068250656,46.2767829895],"type":"Point"}
}