{
  "type": "Feature",
  "properties": {
    "iso:country":"CH",
    "sg:address":"Satellit A + C 3953 Leuk Stadt. Postfach",
    "sg:city":"Susten",
    "sg:orig_category":"Allgemeiner Hoch U Tiefbau",
    "sg:postcode":"3952",
    "sg:province":"Valais",
    "wof:name":"Meyer Josef Bauunternehmungen",
    "wof:placetype":"venue"
},
  "geometry": {"coordinates":[7.634661,46.316334],"type":"Point"}
}