{
  "type": "Feature",
  "properties": {
    "iso:country":"CH",
    "sg:address":"Bodmerstrasse 7 8002 Z\u00fcrich. Postfach 406",
    "sg:city":"Z\u00fcrich",
    "sg:orig_category":"Finanzierungsinstitutionen",
    "sg:phone":"+41 21 653 45 56",
    "sg:postcode":"8027",
    "sg:province":"Z\u00fcrich",
    "wof:name":"Minmet Financing Company",
    "wof:placetype":"venue"
},
  "geometry": {"coordinates":[6.6491770744,46.5232582092],"type":"Point"}
}