{
  "type": "Feature",
  "properties": {
    "iso:country":"CH",
    "sg:address":"Avenue Sainte-clotilde 13 1200 Genf. Postfach",
    "sg:city":"Gen\u00e8ve",
    "sg:orig_category":"RESTAURANTS: TEA-ROOMS",
    "sg:postcode":"1204",
    "sg:province":"Gen\u00e8ve",
    "wof:name":"Dumont Et Dupraz",
    "wof:placetype":"venue"
},
  "geometry": {"coordinates":[6.1338567734,46.2000961304],"type":"Point"}
}