{
  "type": "Feature",
  "properties": {
    "addr:full":"Huebstrasse 14 Rickenbach Z\u00fcrich 8545",
    "addr:housenumber":"14",
    "addr:postcode":"8545",
    "addr:street":"Huebstrasse",
    "iso:country":"CH",
    "sg:address":"Huebstrasse 14",
    "sg:city":"Rickenbach",
    "sg:classifiers":[
        {
            "category":"Manufacturing",
            "subcategory":"Tools & Machinery",
            "type":"Manufacturing & Wholesale Goods"
        }
    ],
    "sg:phone":"+41 52 337 13 63",
    "sg:postcode":"8545",
    "sg:province":"Z\u00fcrich",
    "sg:tags":[
        "construction",
        "container",
        "apparatus"
    ],
    "wof:name":"Koren Maschinen- Und Apparatebau",
    "wof:placetype":"venue"
},
  "geometry": {"coordinates":[8.794856,47.550438],"type":"Point"}
}