{
  "type": "Feature",
  "properties": {
    "iso:country":"CH",
    "sg:address":"Hauptstrasse 57",
    "sg:city":"Einsiedeln",
    "sg:orig_category":"Detailhandel mit fotografischen Artikeln Fotografisches Gewerbe U fotografische Laboratorien",
    "sg:postcode":"8840",
    "sg:province":"Schwyz",
    "wof:name":"Kaufmann Foto + Studio",
    "wof:placetype":"venue"
},
  "geometry": {"coordinates":[8.2235832214,47.131149292],"type":"Point"}
}