{
  "type": "Feature",
  "properties": {
    "iso:country":"CH",
    "sg:address":"Badenerstrasse 281",
    "sg:city":"Z\u00fcrich",
    "sg:orig_category":"Detailhandel mit M\u00f6beln Innenarchitekturb\u00fcros",
    "sg:phone":"+41 14511828",
    "sg:postcode":"8003",
    "sg:province":"Z\u00fcrich",
    "wof:name":"Domus Mea Patrick Biella Stilm\u00f6bel Innenarchitektur",
    "wof:placetype":"venue"
},
  "geometry": {"coordinates":[8.5142936707,47.3762969971],"type":"Point"}
}