{
  "type": "Feature",
  "properties": {
    "iso:country":"CH",
    "sg:address":"Lindauerstrasse 2 8309 N\u00fcrensdorf. Postfach 225",
    "sg:city":"N\u00fcrensdorf",
    "sg:orig_category":"Handelsvermittlung U Grosshandel",
    "sg:phone":"+41 17153187",
    "sg:postcode":"8309",
    "sg:province":"Z\u00fcrich",
    "wof:name":"Maxolen Import/export Hans Knuchel",
    "wof:placetype":"venue"
},
  "geometry": {"coordinates":[8.5396871567,47.3283348083],"type":"Point"}
}