{
  "type": "Feature",
  "properties": {
    "iso:country":"CH",
    "sg:address":"Dozwiler Strasse 22a",
    "sg:city":"Kesswil",
    "sg:orig_category":"Herstellung von M\u00f6beln",
    "sg:phone":"+41 71 463 56 63",
    "sg:postcode":"8593",
    "sg:province":"Thurgau",
    "wof:name":"Walter Thurnheer Ag Holzwaren",
    "wof:placetype":"venue"
},
  "geometry": {"coordinates":[9.3156385422,47.5907821655],"type":"Point"}
}