{
  "type": "Feature",
  "properties": {
    "iso:country":"CH",
    "sg:address":"Strada San Bartolomeo 7742 Poschiavo. Postfach",
    "sg:city":"Poschiavo",
    "sg:orig_category":"Mechanik Mechanische Werkst\u00e4tten",
    "sg:phone":"+41 81 844 04 38",
    "sg:postcode":"7742",
    "sg:province":"Graubunden",
    "wof:name":"Semadeni Roberto Officina Da Fabbro-meccanico",
    "wof:placetype":"venue"
},
  "geometry": {"coordinates":[10.0566186905,46.3237953186],"type":"Point"}
}