{
  "type": "Feature",
  "properties": {
    "iso:country":"CH",
    "sg:address":"Apfelseestrasse 39",
    "sg:city":"Dornach",
    "sg:orig_category":"Rechtsberatung",
    "sg:postcode":"4143",
    "sg:province":"Solothurn",
    "wof:name":"Pool & Spa Trading J. Erni",
    "wof:placetype":"venue"
},
  "geometry": {"coordinates":[7.6086997986,47.4736785889],"type":"Point"}
}