{
  "type": "Feature",
  "properties": {
    "iso:country":"CH",
    "sg:address":"Rte De Vaudigny",
    "sg:city":"Lugnorre",
    "sg:orig_category":"Vermietung U Verpachtung von eigenen Immobilien",
    "sg:postcode":"1789",
    "sg:province":"Fribourg",
    "wof:name":"S.i. Crasta Sa",
    "wof:placetype":"venue"
},
  "geometry": {"coordinates":[8.5449829102,47.3223114014],"type":"Point"}
}