{
  "type": "Feature",
  "properties": {
    "iso:country":"CH",
    "sg:address":"Route De La Fonderie 6 1700 Freiburg. Postfach",
    "sg:city":"Fribourg",
    "sg:orig_category":"Softwareentwicklung U beratung",
    "sg:postcode":"1702",
    "sg:province":"Fribourg",
    "wof:name":"Softcom Technologies Sa",
    "wof:placetype":"venue"
},
  "geometry": {"coordinates":[7.1533899307,46.7944946289],"type":"Point"}
}