{
  "type": "Feature",
  "properties": {
    "iso:country":"CH",
    "sg:address":"Bahnmatt 4a",
    "sg:city":"Baar",
    "sg:orig_category":"Aktivit\u00e4ten der Krankenschwestern U Hebammen, Hauspflege Gesundheitswesen",
    "sg:phone":"+41 41 769 82 82",
    "sg:postcode":"6340",
    "sg:province":"Zug",
    "wof:name":"Spitex-verein Baar",
    "wof:placetype":"venue"
},
  "geometry": {"coordinates":[8.52214,47.196579],"type":"Point"}
}