{
  "type": "Feature",
  "properties": {
    "iso:country":"CH",
    "sg:address":"Brandisstrasse 25",
    "sg:city":"L\u00fctzelfl\u00fch-goldb",
    "sg:orig_category":"Instandhaltung U Reparatur von Automobilen",
    "sg:phone":"+41 34 461 27 79",
    "sg:postcode":"3432",
    "sg:province":"Bern",
    "wof:name":"Hans Ulrich Blaser",
    "wof:placetype":"venue"
},
  "geometry": {"coordinates":[7.6805877686,47.0093154907],"type":"Point"}
}