{
  "type": "Feature",
  "properties": {
    "iso:country":"CH",
    "sg:address":"Le Closel 10",
    "sg:city":"Marsens",
    "sg:orig_category":"Bauspenglerei Dachdeckerei",
    "sg:phone":"+41 26 915 03 61",
    "sg:postcode":"1633",
    "sg:province":"Fribourg",
    "wof:name":"Jacques Durand S\u00e0rl Chauffage-sanitaire",
    "wof:placetype":"venue"
},
  "geometry": {"coordinates":[7.06457,46.656559],"type":"Point"}
}