{
  "type": "Feature",
  "properties": {
    "addr:full":"Grundstrasse 66 St\u00e4fa Z\u00fcrich 8712",
    "addr:housenumber":"66",
    "addr:postcode":"8712",
    "addr:street":"Grundstrasse;Zuerich",
    "iso:country":"CH",
    "sg:address":"Grundstrasse 66",
    "sg:city":"St\u00e4fa",
    "sg:orig_category":"Datenverarbeitungsdienste Sonstige mit der Informatik verbundene T\u00e4tigkeiten",
    "sg:phone":"+41 55 251 50 30",
    "sg:postcode":"8712",
    "sg:province":"Z\u00fcrich",
    "wof:name":"Ctp Ag",
    "wof:placetype":"venue"
},
  "geometry": {"coordinates":[8.867278,47.267284],"type":"Point"}
}