{
  "type": "Feature",
  "properties": {
    "iso:country":"CH",
    "sg:address":"Ziegeleistrasse 2",
    "sg:city":"Diessenhofen",
    "sg:orig_category":"Herstellung von Seifen, Wasch U Reinigungsmitteln Herstellung von sonstigen Gummiwaren",
    "sg:phone":"+41 41 811 16 26",
    "sg:postcode":"8253",
    "sg:province":"Thurgau",
    "wof:name":"Schlittler & Co. Ag",
    "wof:placetype":"venue"
},
  "geometry": {"coordinates":[8.6310997009,47.0198516846],"type":"Point"}
}