{
  "type": "Feature",
  "properties": {
    "iso:country":"CH",
    "sg:address":"Rue Charles-bonnet 6 1200 Genf. Postfach",
    "sg:city":"Gen\u00e8ve",
    "sg:orig_category":"Unclassifiable Establishments",
    "sg:postcode":"1201",
    "sg:province":"Gen\u00e8ve",
    "wof:name":"Haschi Beteiligungs Ag",
    "wof:placetype":"venue"
},
  "geometry": {"coordinates":[8.2029390335,47.2663993835],"type":"Point"}
}