{
  "type": "Feature",
  "properties": {
    "iso:country":"CH",
    "sg:address":"Sonnenstr. 18",
    "sg:city":"Eggersriet",
    "sg:orig_category":"Finanzierungsinstitutionen",
    "sg:postcode":"9034",
    "sg:province":"St. Gallen",
    "wof:name":"Reichle R. Engineering",
    "wof:placetype":"venue"
},
  "geometry": {"coordinates":[9.4777755737,47.4420166016],"type":"Point"}
}