{
  "type": "Feature",
  "properties": {
    "iso:country":"CH",
    "sg:address":"Bahnhofstrasse 14 5745 Safenwil. Postfach",
    "sg:city":"Safenwil",
    "sg:orig_category":"Handelsvermittlung von Maschinen, technischem Bedarf, Wasser U Luftfahrzeugen Herstellung von Werkze",
    "sg:phone":"+41 62 797 45 33",
    "sg:postcode":"5745",
    "sg:province":"Aargau",
    "wof:name":"Vera Gartenger\u00e4te Ag Gartenger\u00e4te, Rasenm\u00e4her, Schneer\u00e4umeger\u00e4te, Fahrr\u00e4der, Kleinmotorger\u00e4te, Ersatzteile, Werkzeuge; Handel, Service, Reparatur Usw",
    "wof:placetype":"venue"
},
  "geometry": {"coordinates":[7.9839577675,47.3209266663],"type":"Point"}
}