{
  "type": "Feature",
  "properties": {
    "iso:country":"CH",
    "sg:address":"Sihlquai 16",
    "sg:city":"Adliswil",
    "sg:orig_category":"Sportvereine Ballsport Handball",
    "sg:postcode":"8134",
    "sg:province":"Z\u00fcrich",
    "wof:name":"Handballclub Tv Krummenau",
    "wof:placetype":"venue"
},
  "geometry": {"coordinates":[9.1993598938,47.2241897583],"type":"Point"}
}