{
  "type": "Feature",
  "properties": {
    "iso:country":"CH",
    "sg:address":"Dornacherstrasse 146",
    "sg:city":"Basel",
    "sg:orig_category":"Allgemeiner Hoch U Tiefbau Hoch U Tiefbau",
    "sg:phone":"+41 61 361 05 30",
    "sg:postcode":"4053",
    "sg:province":"Basel-Stadt",
    "wof:name":"A-z Geb\u00e4uderenovationen Ag",
    "wof:placetype":"venue"
},
  "geometry": {"coordinates":[7.591143,47.542519],"type":"Point"}
}