{
  "type": "Feature",
  "properties": {
    "iso:country":"CH",
    "sg:address":"St\u00fctzli 3",
    "sg:city":"Glarus",
    "sg:orig_category":"Malerei-Gipserei Stukkateurgewerbe, Gipserei U Verputzerei",
    "sg:phone":"+41 79 437 39 50",
    "sg:postcode":"8750",
    "sg:province":"Glarus",
    "wof:name":"Peter Hefti Gipsergesch\u00e4ft",
    "wof:placetype":"venue"
},
  "geometry": {"coordinates":[9.0604867935,47.0438690186],"type":"Point"}
}