{
  "type": "Feature",
  "properties": {
    "iso:country":"CH",
    "sg:address":"Verger Le",
    "sg:city":"Ch\u00e2teau-d'oex",
    "sg:orig_category":"Non-Classified Establishments",
    "sg:postcode":"1837",
    "wof:name":"Si Terrimob Sa",
    "wof:placetype":"venue"
},
  "geometry": {"coordinates":[6.582526207,46.0658187866],"type":"Point"}
}