{
  "type": "Feature",
  "properties": {
    "iso:country":"CH",
    "sg:address":"T\u00f6sstalstrasse 148",
    "sg:city":"Turbenthal",
    "sg:orig_category":"Saunas Schwimmb\u00e4der",
    "sg:phone":"+41 52 385 15 00",
    "sg:postcode":"8488",
    "sg:province":"Z\u00fcrich",
    "wof:name":"Schwimmbad Neuguet Schwimmbad & Sauna",
    "wof:placetype":"venue"
},
  "geometry": {"coordinates":[8.8459224701,47.4275016785],"type":"Point"}
}