{
  "type": "Feature",
  "properties": {
    "iso:country":"CH",
    "sg:address":"Dornacherplatz 7",
    "sg:city":"Solothurn",
    "sg:orig_category":"Advokaturb\u00fcros Notariate",
    "sg:phone":"+41 32 621 34 34",
    "sg:postcode":"4500",
    "sg:province":"Solothurn",
    "wof:name":"Ida Salvetti Advokatur-& Notariatsb\u00fcro",
    "wof:placetype":"venue"
},
  "geometry": {"coordinates":[7.53755,47.204494],"type":"Point"}
}