{
  "type": "Feature",
  "properties": {
    "addr:full":"Schulhausg\u00e4ssli 61c Sch\u00fcpbach Bern 3535",
    "addr:housenumber":"61c",
    "addr:postcode":"3535",
    "addr:street":"Schulhausgaessli",
    "iso:country":"CH",
    "sg:address":"Schulhausg\u00e4ssli 61c",
    "sg:city":"Sch\u00fcpbach",
    "sg:orig_category":"Autogaragen",
    "sg:phone":"+41 34 497 10 30",
    "sg:postcode":"3535",
    "sg:province":"Bern",
    "wof:name":"A. Haldemann & K.d\u00e4llenbach Garage",
    "wof:placetype":"venue"
},
  "geometry": {"coordinates":[7.73833,46.926201],"type":"Point"}
}