{
  "type": "Feature",
  "properties": {
    "iso:country":"CH",
    "sg:address":"Limmatquai 70",
    "sg:city":"Z\u00fcrich",
    "sg:orig_category":"Handelsvermittlung U Grosshandel",
    "sg:phone":"+41 12526300",
    "sg:postcode":"8001",
    "sg:province":"Z\u00fcrich",
    "wof:name":"Pacifico Bar Macola Ag",
    "wof:placetype":"venue"
},
  "geometry": {"coordinates":[8.5428619385,47.3725509644],"type":"Point"}
}