{
  "type": "Feature",
  "properties": {
    "iso:country":"CH",
    "sg:address":"Wagistrasse 7",
    "sg:city":"Schlieren",
    "sg:orig_category":"Instandhaltung U Reparatur von Automobilen",
    "sg:phone":"+41 71 311 34 33",
    "sg:postcode":"8952",
    "sg:province":"Z\u00fcrich",
    "wof:name":"Garage Schmidhauser Werner.",
    "wof:placetype":"venue"
},
  "geometry": {"coordinates":[9.3082351685,47.4040985107],"type":"Point"}
}