{
  "type": "Feature",
  "properties": {
    "iso:country":"CH",
    "sg:address":"Oltnerstrasse 45",
    "sg:city":"Sch\u00f6nenwerd",
    "sg:orig_category":"Versicherungen Hauptagenturen",
    "sg:phone":"+41 62 849 49 21",
    "sg:postcode":"5012",
    "sg:province":"Solothurn",
    "wof:name":"Die Mobiliar Versicherungen & Vorsorge",
    "wof:placetype":"venue"
},
  "geometry": {"coordinates":[8.0014257431,47.3696136475],"type":"Point"}
}