{
  "type": "Feature",
  "properties": {
    "iso:country":"CH",
    "sg:address":"Herrenmatte",
    "sg:city":"Wimmis",
    "sg:orig_category":"Instandhaltung U Reparatur von Automobilen",
    "sg:phone":"+41 79 208 28 18",
    "sg:postcode":"3752",
    "sg:province":"Bern",
    "wof:name":"Automarkt Herrenmatte Gmbh",
    "wof:placetype":"venue"
},
  "geometry": {"coordinates":[7.6336817741,46.6766548157],"type":"Point"}
}