{
  "type": "Feature",
  "properties": {
    "iso:country":"CH",
    "sg:address":"Ekkehardsteig 3 8006 Z\u00fcrich. Postfach",
    "sg:city":"Z\u00fcrich",
    "sg:orig_category":"Herstellung von k\u00e4lte U lufttechnischen Erzeugnissen f\u00fcr gewerbliche Zwecke",
    "sg:phone":"+41 13628916",
    "sg:postcode":"8001",
    "sg:province":"Z\u00fcrich",
    "wof:name":"Tanner Emil Jun. Umw\u00e4lzpumpen F Heizungs, L\u00fcftungs, Sanit\u00e4r-anlagen; Service, Handel",
    "wof:placetype":"venue"
},
  "geometry": {"coordinates":[8.5439128876,47.3860626221],"type":"Point"}
}