{
  "type": "Feature",
  "properties": {
    "iso:country":"CH",
    "sg:address":"Rennweg 2",
    "sg:city":"Z\u00fcrich",
    "sg:orig_category":"Gold- and Silberschmuck Detailhandel",
    "sg:phone":"+41 12121718",
    "sg:postcode":"8001",
    "sg:province":"Z\u00fcrich",
    "wof:name":"Bernhard Birrer Carat Goldschmiedegesch\u00e4ft",
    "wof:placetype":"venue"
},
  "geometry": {"coordinates":[8.5402297974,47.3724517822],"type":"Point"}
}