{
  "type": "Feature",
  "properties": {
    "iso:country":"CH",
    "sg:address":"1871",
    "sg:city":"Cho\u00ebx",
    "sg:orig_category":"Bauschreinerei",
    "sg:phone":"+41 24 471 10 84",
    "sg:postcode":"1871",
    "sg:province":"Valais",
    "wof:name":"Yves Marclay Menuiserie & Parquets",
    "wof:placetype":"venue"
},
  "geometry": {"coordinates":[6.954794,46.238503],"type":"Point"}
}