{
  "type": "Feature",
  "properties": {
    "iso:country":"CH",
    "sg:address":"Talstrasse 37",
    "sg:city":"Z\u00fcrich",
    "sg:orig_category":"Kunsthandel",
    "sg:phone":"+41 12115240",
    "sg:postcode":"8001",
    "sg:province":"Z\u00fcrich",
    "wof:name":"David Koetser Galerie",
    "wof:placetype":"venue"
},
  "geometry": {"coordinates":[8.5371713638,47.3693618774],"type":"Point"}
}