{
  "type": "Feature",
  "properties": {
    "iso:country":"CH",
    "sg:address":"Unterrechstein 328",
    "sg:city":"Heiden",
    "sg:classifiers":[
        {
            "category":"Wholesale",
            "subcategory":"Wine & Distilled Alcoholic Beverages",
            "type":"Manufacturing & Wholesale Goods"
        }
    ],
    "sg:phone":"+41 71 891 66 06",
    "sg:postcode":"9410",
    "sg:province":"Appenzell Ausserrhoden",
    "sg:tags":[
        "australian"
    ],
    "wof:name":"Rolf Breu Metalldesign",
    "wof:placetype":"venue"
},
  "geometry": {"coordinates":[9.519425,47.433884],"type":"Point"}
}