{
  "type": "Feature",
  "properties": {
    "iso:country":"CH",
    "sg:address":"Gr\u00fczenstrasse 9",
    "sg:city":"D\u00fcbendorf",
    "sg:orig_category":"Wirtschaftspr\u00fcfung, Steuerberatung U Treuhand",
    "sg:phone":"+41 55 240 63 04",
    "sg:postcode":"8600",
    "sg:province":"Z\u00fcrich",
    "wof:name":"Braunschweiler Ueli, B\u00fccherexperte",
    "wof:placetype":"venue"
},
  "geometry": {"coordinates":[8.8404073715,47.2547721863],"type":"Point"}
}