{
  "type": "Feature",
  "properties": {
    "iso:country":"CH",
    "sg:address":"Sonnhaldeweg 52",
    "sg:city":"M\u00fcnsingen",
    "sg:orig_category":"Unclassifiable Establishments",
    "sg:phone":"+41 31 721 04 57",
    "sg:postcode":"3110",
    "sg:province":"Bern",
    "wof:name":"Eh Niggli Gmbh",
    "wof:placetype":"venue"
},
  "geometry": {"coordinates":[7.5675630569,46.8833236694],"type":"Point"}
}