{
  "type": "Feature",
  "properties": {
    "iso:country":"CH",
    "sg:address":"Sismondi Rue 5 1201 Gen\u00e8ve. Postfach",
    "sg:city":"Gen\u00e8ve",
    "sg:orig_category":"RESTAURANTS: TEA-ROOMS",
    "sg:postcode":"1201",
    "sg:province":"Gen\u00e8ve",
    "wof:name":"Brandt Dale",
    "wof:placetype":"venue"
},
  "geometry": {"coordinates":[6.147480011,46.2098388672],"type":"Point"}
}