{
  "type": "Feature",
  "properties": {
    "iso:country":"CH",
    "sg:address":"Hagmattstrasse 4",
    "sg:city":"Trimbach",
    "sg:orig_category":"Sportvereine Turnen",
    "sg:phone":"+41 62 295 08 50",
    "sg:postcode":"4632",
    "sg:province":"Solothurn",
    "wof:name":"Turnverein Trimbach",
    "wof:placetype":"venue"
},
  "geometry": {"coordinates":[7.9019842148,47.3582649231],"type":"Point"}
}