{
  "type": "Feature",
  "properties": {
    "iso:country":"CH",
    "sg:address":"R\u00f6merstrasse West 49 3296 Arch. Postfach 50",
    "sg:city":"Arch",
    "sg:orig_category":"Herstellung von Schrauben, Nieten, Ketten U Federn Herstellung von Werkzeugen",
    "sg:phone":"+41 32 679 55 33",
    "sg:postcode":"3296",
    "sg:province":"Bern",
    "wof:name":"Junker Swiss Technology Ltd",
    "wof:placetype":"venue"
},
  "geometry": {"coordinates":[7.4200329781,47.1642189026],"type":"Point"}
}