{
  "type": "Feature",
  "properties": {
    "iso:country":"CH",
    "sg:address":"Stehlistrasse 6",
    "sg:city":"Obfelden",
    "sg:orig_category":"Erbringung von Dienstleistungen f\u00fcr Unternehmen Grafikateliers, Design",
    "sg:phone":"+41 14226312",
    "sg:postcode":"8912",
    "sg:province":"Z\u00fcrich",
    "wof:name":"Metaretta Design Meier, Vas Meier + Co",
    "wof:placetype":"venue"
},
  "geometry": {"coordinates":[8.4182100296,47.2618904114],"type":"Point"}
}