{
  "type": "Feature",
  "properties": {
    "iso:country":"CH",
    "sg:address":"6722",
    "sg:city":"Corzoneso",
    "sg:orig_category":"Instandhaltung U Reparatur von Automobilen",
    "sg:postcode":"6722",
    "sg:province":"Ticino",
    "wof:name":"Gi-ra Re Sagl",
    "wof:placetype":"venue"
},
  "geometry": {"coordinates":[8.9339704514,46.4467010498],"type":"Point"}
}