{
  "type": "Feature",
  "properties": {
    "addr:full":"Z\u00fcrichstrasse 24a Adliswil Z\u00fcrich 8134",
    "addr:housenumber":"24a",
    "addr:postcode":"8134",
    "addr:street":"Zuerichstrasse",
    "iso:country":"CH",
    "sg:address":"Z\u00fcrichstrasse 24a",
    "sg:city":"Adliswil",
    "sg:orig_category":"Arztpraxen",
    "sg:phone":"+41 17101230",
    "sg:postcode":"8134",
    "sg:province":"Z\u00fcrich",
    "wof:name":"Dr.med.edgar Hegersweiler Arzt F\u00fcr Allgemeine Medizin",
    "wof:placetype":"venue"
},
  "geometry": {"coordinates":[8.528735,47.314133],"type":"Point"}
}