{
  "type": "Feature",
  "properties": {
    "iso:country":"CH",
    "sg:address":"Rainstrasse 1",
    "sg:city":"M\u00fcnchenstein",
    "sg:classifiers":[
        {
            "category":"Travel",
            "subcategory":"Hotels & Motels",
            "type":"Entertainment"
        }
    ],
    "sg:phone":"+41 61 411 80 45",
    "sg:postcode":"4142",
    "sg:province":"Basel-Landschaft",
    "sg:tags":[
        "hotels",
        "mit",
        "restaurant"
    ],
    "wof:name":"Bassis-bitterli, Bruno",
    "wof:placetype":"venue"
},
  "geometry": {"coordinates":[7.61373806,47.5301322937],"type":"Point"}
}