{
  "type": "Feature",
  "properties": {
    "iso:country":"CH",
    "sg:address":"Dorfstrasse 39",
    "sg:city":"Bonstetten",
    "sg:orig_category":"Detailhandel mit Bekleidung",
    "sg:phone":"+41 17001742",
    "sg:postcode":"8906",
    "sg:province":"Z\u00fcrich",
    "wof:name":"Renate Stierli Joyce Mode Boutique",
    "wof:placetype":"venue"
},
  "geometry": {"coordinates":[8.466589,47.314877],"type":"Point"}
}