{
  "type": "Feature",
  "properties": {
    "addr:full":"Frankenstrasse 3 Luzern Luzern 6003",
    "addr:housenumber":"3",
    "addr:postcode":"6003",
    "addr:street":"Frankenstrasse",
    "iso:country":"CH",
    "sg:address":"Frankenstrasse 3",
    "sg:city":"Luzern",
    "sg:orig_category":"Detailhandel mit Computern U Software Sonstige mit der Informatik verbundene T\u00e4tigkeiten",
    "sg:phone":"+41 41 210 10 20",
    "sg:postcode":"6003",
    "sg:province":"Luzern",
    "wof:name":"Olivier Eigensatz One Nine One Computer",
    "wof:placetype":"venue"
},
  "geometry": {"coordinates":[8.309098,47.049282],"type":"Point"}
}