{
  "type": "Feature",
  "properties": {
    "iso:country":"CH",
    "sg:address":"Reitsteinstrasse",
    "sg:city":"R\u00fctihof",
    "sg:orig_category":"Gem\u00fcsebau",
    "sg:phone":"+41 56 493 11 12",
    "sg:postcode":"5406",
    "sg:province":"Aargau",
    "wof:name":"Paul Meier Gem\u00fcsebau",
    "wof:placetype":"venue"
},
  "geometry": {"coordinates":[8.2685632706,47.4352340698],"type":"Point"}
}