{
  "type": "Feature",
  "properties": {
    "iso:country":"CH",
    "sg:address":"Ch\u00e9zard",
    "sg:city":"Ch\u00e9zard-st-martin",
    "sg:orig_category":"Non-Classified Establishments",
    "sg:postcode":"2054",
    "sg:province":"Neuch\u00e2tel",
    "wof:name":"Loup A.",
    "wof:placetype":"venue"
},
  "geometry": {"coordinates":[6.915746212,47.0641593933],"type":"Point"}
}