{
  "type": "Feature",
  "properties": {
    "iso:country":"CH",
    "sg:address":"6386",
    "sg:city":"Wolfenschiessen",
    "sg:orig_category":"Detailhandel mit M\u00f6beln Herstellung von Reiseartikeln, Leder U Sattlerwaren",
    "sg:phone":"+41 41 628 11 85",
    "sg:postcode":"6386",
    "sg:province":"Nidwalden",
    "wof:name":"Josef Christen M\u00f6bel Sattlerei",
    "wof:placetype":"venue"
},
  "geometry": {"coordinates":[8.3956546783,46.9103431702],"type":"Point"}
}