{
  "type": "Feature",
  "properties": {
    "iso:country":"CH",
    "sg:address":"Hauptstrasse 259",
    "sg:city":"Ramsen",
    "sg:orig_category":"Landesverteidigung, Sozialversicherung \u00d6ffentliche Verwaltung",
    "sg:phone":"+41 52 743 11 22",
    "sg:postcode":"8262",
    "sg:province":"Schaffhausen",
    "wof:name":"Zivilschutzstelle Ramsen",
    "wof:placetype":"venue"
},
  "geometry": {"coordinates":[8.8100671768,47.7072296143],"type":"Point"}
}