{
  "type": "Feature",
  "properties": {
    "addr:full":"Schulhausstrasse 36 Ammannsegg Solothurn 4573",
    "addr:housenumber":"36",
    "addr:postcode":"4573",
    "addr:street":"Schulhausstrasse;Solothurn",
    "iso:country":"CH",
    "sg:address":"Schulhausstrasse 36",
    "sg:city":"Ammannsegg",
    "sg:orig_category":"Architektur U Ingenieurb\u00fcros",
    "sg:phone":"+41 32 677 26 60",
    "sg:postcode":"4573",
    "sg:province":"Solothurn",
    "wof:name":"Visini Maurillio",
    "wof:placetype":"venue"
},
  "geometry": {"coordinates":[7.529661,47.171005],"type":"Point"}
}