{
  "type": "Feature",
  "properties": {
    "iso:country":"CH",
    "sg:address":"G\u00e4ssli 41",
    "sg:city":"Alchenstorf",
    "sg:orig_category":"Unclassifiable Establishments",
    "sg:phone":"+41 34 415 19 23",
    "sg:postcode":"3473",
    "sg:province":"Bern",
    "wof:name":"R\u00fcedi B\u00fcromaschinen & Recycling",
    "wof:placetype":"venue"
},
  "geometry": {"coordinates":[7.6441612244,47.1220245361],"type":"Point"}
}