{
  "type": "Feature",
  "properties": {
    "iso:country":"CH",
    "sg:address":"Schulstrasse 21",
    "sg:city":"Steinach",
    "sg:orig_category":"Softwareentwicklung U beratung",
    "sg:phone":"+41 71 440 08 39",
    "sg:postcode":"9323",
    "sg:province":"St. Gallen",
    "wof:name":"Santo Di Paola Sansoft",
    "wof:placetype":"venue"
},
  "geometry": {"coordinates":[9.4408149719,47.5003356934],"type":"Point"}
}