{
  "type": "Feature",
  "properties": {
    "addr:full":"Oeleweg 2 Neuenegg Bern 3176",
    "addr:housenumber":"2",
    "addr:postcode":"3176",
    "addr:street":"Oeleweg;Bern",
    "iso:country":"CH",
    "sg:address":"Oeleweg 2",
    "sg:city":"Neuenegg",
    "sg:orig_category":"Arztpraxen",
    "sg:phone":"+41 31 741 16 16",
    "sg:postcode":"3176",
    "sg:province":"Bern",
    "wof:name":"Dr.med. Beat K\u00f6stner Arzt F.allgemeine Medizin Fmh",
    "wof:placetype":"venue"
},
  "geometry": {"coordinates":[7.303376,46.894043],"type":"Point"}
}