{
  "type": "Feature",
  "properties": {
    "iso:country":"CH",
    "sg:address":"Dottikerstrasse 5",
    "sg:city":"Anglikon",
    "sg:orig_category":"Handel mit Automobilen",
    "sg:phone":"+41 56 610 07 55",
    "sg:postcode":"5611",
    "sg:province":"Aargau",
    "wof:name":"Josef Meier Auto Meier",
    "wof:placetype":"venue"
},
  "geometry": {"coordinates":[8.2646837234,47.3631362915],"type":"Point"}
}