{
  "type": "Feature",
  "properties": {
    "iso:country":"CH",
    "sg:address":"Seetalstrasse 136",
    "sg:city":"Schafisheim",
    "sg:orig_category":"Detailhandel mit Ton U Bildtr\u00e4gern Detailhandel mit elektrischen Haushalts-,Radio U Fernsehger\u00e4ten s",
    "sg:phone":"+41 62 891 84 86",
    "sg:postcode":"5503",
    "sg:province":"Aargau",
    "wof:name":"Herbert Byland Music Shop",
    "wof:placetype":"venue"
},
  "geometry": {"coordinates":[8.1429100037,47.3748207092],"type":"Point"}
}