{
  "type": "Feature",
  "properties": {
    "iso:country":"CH",
    "sg:address":"6018",
    "sg:city":"Buttisholz",
    "sg:orig_category":"Bezirks, Sekundar, Realschulen, Oberstufe der Primarschulen",
    "sg:phone":"+41 41 928 16 91",
    "sg:postcode":"6018",
    "sg:province":"Luzern",
    "wof:name":"Sekundarschule",
    "wof:placetype":"venue"
},
  "geometry": {"coordinates":[8.09376,47.114414],"type":"Point"}
}