{
  "type": "Feature",
  "properties": {
    "iso:country":"CH",
    "sg:address":"Seefeldstrasse 32",
    "sg:city":"Z\u00fcrich",
    "sg:orig_category":"Massagestudios",
    "sg:phone":"+41 12525985",
    "sg:postcode":"8008",
    "sg:province":"Z\u00fcrich",
    "wof:name":"Ren\u00e9e Janina Kaufmann Massagen",
    "wof:placetype":"venue"
},
  "geometry": {"coordinates":[8.5492544174,47.3634529114],"type":"Point"}
}