{
  "type": "Feature",
  "properties": {
    "iso:country":"CH",
    "sg:address":"Seuzachstrasse 23",
    "sg:city":"Neftenbach",
    "sg:orig_category":"Sportvereine Sch\u00fctzen",
    "sg:phone":"+41 52 315 52 15",
    "sg:postcode":"8413",
    "sg:province":"Z\u00fcrich",
    "wof:name":"Sch\u00fctzenverein H\u00fcnikon",
    "wof:placetype":"venue"
},
  "geometry": {"coordinates":[8.6706418991,47.5297927856],"type":"Point"}
}