{
  "type": "Feature",
  "properties": {
    "iso:country":"CH",
    "sg:address":"1450",
    "sg:city":"Ste-croix",
    "sg:classifiers":[
        {
            "category":"Education",
            "subcategory":"Library",
            "type":"Public Place"
        }
    ],
    "sg:phone":"+41 24 454 22 24",
    "sg:postcode":"1450",
    "sg:province":"Vaud",
    "sg:tags":[
        "u",
        "bibliotheken",
        "archive"
    ],
    "wof:name":"Biblioth\u00e8que Populaire",
    "wof:placetype":"venue"
},
  "geometry": {"coordinates":[6.50105,46.824211],"type":"Point"}
}