{
  "type": "Feature",
  "properties": {
    "iso:country":"CH",
    "sg:address":"Sihlweidstrasse 65",
    "sg:city":"Z\u00fcrich",
    "sg:orig_category":"Werbung",
    "sg:postcode":"8041",
    "sg:province":"Z\u00fcrich",
    "wof:name":"Elitas Ag",
    "wof:placetype":"venue"
},
  "geometry": {"coordinates":[8.5175008774,47.327255249],"type":"Point"}
}