{
  "type": "Feature",
  "properties": {
    "iso:country":"CH",
    "sg:address":"Kirchweg 530 Merligen 3655 Sigriswil. Postfach",
    "sg:city":"Merligen",
    "sg:orig_category":"Sonstiger Grosshandel",
    "sg:postcode":"3658",
    "sg:province":"Bern",
    "wof:name":"Stucki + Partner",
    "wof:placetype":"venue"
},
  "geometry": {"coordinates":[7.7135767937,46.7171478271],"type":"Point"}
}