{
  "type": "Feature",
  "properties": {
    "iso:country":"CH",
    "sg:address":"Via Locarno 16",
    "sg:city":"Sementina",
    "sg:classifiers":[
        {
            "category":"Insurance",
            "subcategory":"Insurance Agent",
            "type":"Services"
        }
    ],
    "sg:phone":"+41 91 857 53 45",
    "sg:postcode":"6514",
    "sg:province":"Ticino",
    "sg:tags":[
        "versicherungsagenturen",
        "-broker"
    ],
    "wof:name":"Basilese Assicurazioni Agenzia Mauro Locarnini",
    "wof:placetype":"venue"
},
  "geometry": {"coordinates":[8.9901399612,46.1854820251],"type":"Point"}
}