{
  "type": "Feature",
  "properties": {
    "iso:country":"CH",
    "sg:address":"Avenue Du Tribunal-f\u00e9d\u00e9ral 3",
    "sg:city":"Lausanne",
    "sg:orig_category":"Detailhandel mit Brillen U anderen Sehhilfen",
    "sg:phone":"+41 21 323 66 00",
    "sg:postcode":"1005",
    "sg:province":"Vaud",
    "wof:name":"Alain Schopfer Opticien",
    "wof:placetype":"venue"
},
  "geometry": {"coordinates":[6.638148,46.519756],"type":"Point"}
}