{
  "type": "Feature",
  "properties": {
    "iso:country":"CH",
    "sg:address":"Hohlstrasse 501",
    "sg:city":"Z\u00fcrich",
    "sg:orig_category":"Herstellung von Zucker",
    "sg:phone":"+41 14321622",
    "sg:postcode":"8048",
    "sg:province":"Z\u00fcrich",
    "wof:name":"Hostettler-spezialzucker Ag",
    "wof:placetype":"venue"
},
  "geometry": {"coordinates":[8.4935388565,47.3893165588],"type":"Point"}
}