{
  "type": "Feature",
  "properties": {
    "iso:country":"CH",
    "sg:address":"7516 Maloja. Postfach",
    "sg:city":"Maloja",
    "sg:orig_category":"Herstellung von Konstruktionsteilen, Fertigbauteilen U Ausbauelementen aus Holz",
    "sg:postcode":"7516",
    "sg:province":"Graubunden",
    "wof:name":"Bruno Clal\u00fcna",
    "wof:placetype":"venue"
},
  "geometry": {"coordinates":[9.6952791214,46.401008606],"type":"Point"}
}