{
  "type": "Feature",
  "properties": {
    "iso:country":"CH",
    "sg:address":"Breiteweg 7",
    "sg:city":"Fahrwangen",
    "sg:orig_category":"Vermietung U Verpachtung von eigenen Immobilien Vermittlung von Immobilien",
    "sg:phone":"+41 56 667 38 27",
    "sg:postcode":"5615",
    "sg:province":"Aargau",
    "wof:name":"Parktrade Ag",
    "wof:placetype":"venue"
},
  "geometry": {"coordinates":[8.2442073822,47.3003501892],"type":"Point"}
}