{
  "type": "Feature",
  "properties": {
    "iso:country":"CH",
    "sg:address":"Baarerstrasse 94 6300 Zug. Postfach 2260",
    "sg:city":"Zug",
    "sg:orig_category":"Unternehmensberatung",
    "sg:phone":"+41 41 761 09 44",
    "sg:postcode":"6300",
    "sg:province":"Zug",
    "wof:name":"Scritag P. Hunkeler",
    "wof:placetype":"venue"
},
  "geometry": {"coordinates":[8.5183916092,47.1783332825],"type":"Point"}
}