{
  "type": "Feature",
  "properties": {
    "iso:country":"CH",
    "sg:address":"Libert\u00e9 Place De La 2",
    "sg:city":"Del\u00e9mont",
    "sg:orig_category":"Unclassifiable Establishments",
    "sg:postcode":"2800",
    "sg:province":"Jura",
    "wof:name":"Korsal Holding Sa",
    "wof:placetype":"venue"
},
  "geometry": {"coordinates":[7.3439698219,47.3653564453],"type":"Point"}
}