{
  "type": "Feature",
  "properties": {
    "iso:country":"CH",
    "sg:address":"Z\u00fcrichstrasse 1",
    "sg:city":"Uster",
    "sg:orig_category":"Detailhandel mit Beleuchtungs U Haushaltsgegenst\u00e4nden Detailhandel mit Schreib U Papeteriewaren",
    "sg:phone":"+41 19406156",
    "sg:postcode":"8610",
    "sg:province":"Z\u00fcrich",
    "wof:name":"Schlappritzi Ag Pres\u00e4ntli Haushalt Geschenke",
    "wof:placetype":"venue"
},
  "geometry": {"coordinates":[8.717179,47.348484],"type":"Point"}
}