{
  "type": "Feature",
  "properties": {
    "iso:country":"CH",
    "sg:address":"Sch\u00f6nb\u00fchl 10 6300 Zug. Postfach",
    "sg:city":"Zug",
    "sg:orig_category":"Herstellung von Sportger\u00e4ten",
    "sg:postcode":"6300",
    "sg:province":"Zug",
    "wof:name":"Huwyler & Steinle Sportartikel; Produktion, Handel",
    "wof:placetype":"venue"
},
  "geometry": {"coordinates":[8.519695282,47.164604187],"type":"Point"}
}