{
  "type": "Feature",
  "properties": {
    "iso:country":"CH",
    "sg:address":"Via Alla Castellana",
    "sg:city":"Pazzallo",
    "sg:classifiers":[
        {
            "category":"Restaurant",
            "type":"Food & Drink"
        }
    ],
    "sg:phone":"+41 91 993 00 99",
    "sg:postcode":"6912",
    "sg:province":"Ticino",
    "wof:name":"Mcdonald's Ristorante",
    "wof:placetype":"venue"
},
  "geometry": {"coordinates":[8.9357776642,45.9840316772],"type":"Point"}
}