{
  "type": "Feature",
  "properties": {
    "addr:full":"Els\u00e4sserstrasse 254 Basel Basel-Stadt 4056",
    "addr:housenumber":"254",
    "addr:postcode":"4056",
    "addr:street":"Elsaesserstrasse",
    "iso:country":"CH",
    "sg:address":"Els\u00e4sserstrasse 254",
    "sg:city":"Basel",
    "sg:orig_category":"Detailhandel mit Brot, Back U S\u00fcsswaren",
    "sg:phone":"+41 61 261 11 48",
    "sg:postcode":"4056",
    "sg:province":"Basel-Stadt",
    "wof:name":"Gebr. K\u00fchner Ag",
    "wof:placetype":"venue"
},
  "geometry": {"coordinates":[7.572629,47.576679],"type":"Point"}
}