{
  "type": "Feature",
  "properties": {
    "iso:country":"CH",
    "sg:address":"Dorfstrasse 138",
    "sg:city":"Meilen",
    "sg:orig_category":"Interessenvertretungen",
    "sg:postcode":"8706",
    "sg:province":"Z\u00fcrich",
    "wof:name":"Stiftung Bolleter Alfred Und Margaretha",
    "wof:placetype":"venue"
},
  "geometry": {"coordinates":[8.6460828781,47.2688140869],"type":"Point"}
}