{
  "type": "Feature",
  "properties": {
    "iso:country":"CH",
    "sg:address":"Sendlistrasse 1",
    "sg:city":"Interlaken",
    "sg:orig_category":"Herstellung von Konstruktionsteilen, Fertigbauteilen U Ausbauelementen aus Holz Innenausbau",
    "sg:postcode":"3800",
    "sg:province":"Bern",
    "wof:name":"Wood-life Schreinerei, Peter Michel Schreinerei, M\u00f6bel- U. Innenausbau; Restaurationen U. Reparaturen",
    "wof:placetype":"venue"
},
  "geometry": {"coordinates":[7.8828282356,46.6892662048],"type":"Point"}
}