{
  "type": "Feature",
  "properties": {
    "iso:country":"CH",
    "sg:address":"Umfahrungsstrasse.",
    "sg:city":"Schiers",
    "sg:orig_category":"RESTAURANTS: TEA-ROOMS",
    "sg:postcode":"7220",
    "sg:province":"Graubunden",
    "wof:name":"Rada-disch L.",
    "wof:placetype":"venue"
},
  "geometry": {"coordinates":[9.6886806488,46.9656600952],"type":"Point"}
}