{
  "type": "Feature",
  "properties": {
    "iso:country":"CH",
    "sg:address":"Feilen 9",
    "sg:city":"Stachen",
    "sg:orig_category":"Elektroinstallation",
    "sg:phone":"+41 55 283 20 70",
    "sg:postcode":"9320",
    "sg:province":"Thurgau",
    "wof:name":"Elektro-steiner Ag",
    "wof:placetype":"venue"
},
  "geometry": {"coordinates":[9.0054197311,47.19764328],"type":"Point"}
}