{
  "type": "Feature",
  "properties": {
    "iso:country":"CH",
    "sg:address":"St. Moritzstrasse 21 8006 Z\u00fcrich. Postfach",
    "sg:city":"Z\u00fcrich",
    "sg:orig_category":"Sonstiger Grosshandel",
    "sg:postcode":"8001",
    "sg:province":"Z\u00fcrich",
    "wof:name":"Weltert & Weber Trading Company Produktehandel, -fertigstellung Usw",
    "wof:placetype":"venue"
},
  "geometry": {"coordinates":[8.5403985977,47.3877296448],"type":"Point"}
}