{
  "type": "Feature",
  "properties": {
    "iso:country":"CH",
    "sg:address":"8342",
    "sg:city":"Wernetshausen",
    "sg:orig_category":"RESTAURANTS: TEA-ROOMS",
    "sg:phone":"+41 71 755 11 33",
    "sg:postcode":"8342",
    "sg:province":"Z\u00fcrich",
    "wof:name":"Restaurant Bad Gr\u00fctter A.",
    "wof:placetype":"venue"
},
  "geometry": {"coordinates":[9.5397491455,47.3769721985],"type":"Point"}
}