{
  "type": "Feature",
  "properties": {
    "iso:country":"CH",
    "sg:address":"Geren 6",
    "sg:city":"Tagelswangen",
    "sg:orig_category":"Forschung U Entwicklung im Bereich der Naturwissenschaften Softwareentwicklung U beratung",
    "sg:phone":"+41 32 913 67 73",
    "sg:postcode":"8317",
    "sg:province":"Z\u00fcrich",
    "wof:name":"S.l.t. Sa",
    "wof:placetype":"venue"
},
  "geometry": {"coordinates":[6.8297801018,47.1029129028],"type":"Point"}
}