{
  "type": "Feature",
  "properties": {
    "iso:country":"CH",
    "sg:address":"Tourelle Chemin De La 14 1209 Gen\u00e8ve. Postfach",
    "sg:city":"Gen\u00e8ve",
    "sg:orig_category":"Fachdetailhandel in Verkaufsr\u00e4umen",
    "sg:phone":"+41 41 930 40 70",
    "sg:postcode":"1209",
    "sg:province":"Gen\u00e8ve",
    "wof:name":"Copy Foto Labor Th\u00fcrig",
    "wof:placetype":"venue"
},
  "geometry": {"coordinates":[8.1457843781,47.2257766724],"type":"Point"}
}