{
  "type": "Feature",
  "properties": {
    "iso:country":"CH",
    "sg:address":"Sch\u00f6nenbuchstrasse 6430 Schwyz. Postfach",
    "sg:city":"Ibach",
    "sg:orig_category":"Pensionskassen",
    "sg:postcode":"6438",
    "sg:province":"Schwyz",
    "wof:name":"Wohlfahrtsfonds Der Sand Und Kieswerk Ag Schwyz",
    "wof:placetype":"venue"
},
  "geometry": {"coordinates":[8.6452770233,47.004032135],"type":"Point"}
}