{
  "type": "Feature",
  "properties": {
    "iso:country":"CH",
    "sg:address":"Vicaire-savoyard Rue Du 8 1203 Gen\u00e8ve. Postfach",
    "sg:city":"Gen\u00e8ve",
    "sg:orig_category":"Elektroinstallation",
    "sg:phone":"+41 22 344 23 75",
    "sg:postcode":"1202",
    "sg:province":"Gen\u00e8ve",
    "wof:name":"Vuilleumier Henri",
    "wof:placetype":"venue"
},
  "geometry": {"coordinates":[6.1224608421,46.2041244507],"type":"Point"}
}