{
  "type": "Feature",
  "properties": {
    "iso:country":"CH",
    "sg:address":"Beundenstrasse 21",
    "sg:city":"M\u00f6rigen",
    "sg:orig_category":"Sportvereine Sch\u00fctzen",
    "sg:phone":"+41 71 977 13 73",
    "sg:postcode":"2572",
    "sg:province":"Bern",
    "wof:name":"Sch\u00fctzenver.dussnang-o'wangen",
    "wof:placetype":"venue"
},
  "geometry": {"coordinates":[8.9696502686,47.4314918518],"type":"Point"}
}