{
  "type": "Feature",
  "properties": {
    "iso:country":"CH",
    "sg:address":"Seebuchtstrasse 29",
    "sg:city":"Buochs",
    "sg:orig_category":"Herstellung von Futtermitteln f\u00fcr Nutztiere Mahl U Sch\u00e4lm\u00fchlen",
    "sg:phone":"+41 41 620 30 14",
    "sg:postcode":"6374",
    "sg:province":"Nidwalden",
    "wof:name":"Biomill Sa",
    "wof:placetype":"venue"
},
  "geometry": {"coordinates":[8.4235649109,46.9768218994],"type":"Point"}
}