{
  "type": "Feature",
  "properties": {
    "iso:country":"CH",
    "sg:address":"Technikumstrasse 82",
    "sg:city":"Winterthur",
    "sg:orig_category":"Advokaturb\u00fcros",
    "sg:phone":"+41 31 382 29 82",
    "sg:postcode":"8400",
    "sg:province":"Z\u00fcrich",
    "wof:name":"Dr.urs Leu Advokaturb\u00fcro",
    "wof:placetype":"venue"
},
  "geometry": {"coordinates":[7.45091,46.943394],"type":"Point"}
}