{
  "type": "Feature",
  "properties": {
    "iso:country":"CH",
    "sg:address":"Rue Du Temple 17",
    "sg:city":"Bevaix",
    "sg:orig_category":"Bestattungswesen",
    "sg:phone":"+41 32 730 40 00",
    "sg:postcode":"2022",
    "sg:province":"Neuch\u00e2tel",
    "wof:name":"Eric Tinembart",
    "wof:placetype":"venue"
},
  "geometry": {"coordinates":[6.815,46.931385],"type":"Point"}
}