{
  "type": "Feature",
  "properties": {
    "iso:country":"CH",
    "sg:address":"Halden 89",
    "sg:city":"Schwellbrunn",
    "sg:orig_category":"Schlossereien",
    "sg:phone":"+41 71 352 48 22",
    "sg:postcode":"9103",
    "sg:province":"Appenzell Ausserrhoden",
    "wof:name":"Walter Schoch Schlosserei & Ofenarmaturen",
    "wof:placetype":"venue"
},
  "geometry": {"coordinates":[9.250623703,47.3504829407],"type":"Point"}
}