{
  "type": "Feature",
  "properties": {
    "iso:country":"CH",
    "sg:address":"Gottardo Via San 52 6877 Coldrerio. Postfach",
    "sg:city":"Coldrerio",
    "sg:orig_category":"Handel mit Automobilen",
    "sg:postcode":"6877",
    "sg:province":"Ticino",
    "wof:name":"Colcar Sa Concessionaria Di Autoveicoli Ecc",
    "wof:placetype":"venue"
},
  "geometry": {"coordinates":[8.9860448837,45.8577880859],"type":"Point"}
}