{
  "type": "Feature",
  "properties": {
    "iso:country":"CH",
    "sg:address":"Brauereiweg 23",
    "sg:city":"Rapperswil",
    "sg:classifiers":[
        {
            "category":"Professional",
            "subcategory":"Engineering",
            "type":"Services"
        }
    ],
    "sg:phone":"+41 55 220 64 64",
    "sg:postcode":"8640",
    "sg:province":"Schwyz",
    "sg:tags":[
        "machine",
        "-",
        "mechanical"
    ],
    "wof:name":"System Schultheis Ag",
    "wof:placetype":"venue"
},
  "geometry": {"coordinates":[8.8221273422,47.2341957092],"type":"Point"}
}