{
  "type": "Feature",
  "properties": {
    "iso:country":"CH",
    "sg:address":"Hauptstrasse 18",
    "sg:city":"Sutz",
    "sg:classifiers":[
        {
            "category":"Autos & Motor Vehicles",
            "subcategory":"Fuel & Gas Station",
            "type":"Retail Goods"
        }
    ],
    "sg:phone":"+41 52 672 43 22",
    "sg:postcode":"2572",
    "sg:province":"Bern",
    "sg:tags":[
        "machine",
        "screw",
        "testing",
        "stand"
    ],
    "wof:name":"Russenberger Pr\u00fcfmaschinen Ag",
    "wof:placetype":"venue"
},
  "geometry": {"coordinates":[8.6015205383,47.6755981445],"type":"Point"}
}