{
  "type": "Feature",
  "properties": {
    "iso:country":"CH",
    "sg:address":"B\u00e4rchistrasse 6",
    "sg:city":"Marthalen",
    "sg:orig_category":"Abbruch U Sprenggewerbe, Erdbewegungsarbeiten Erdbewegungsarbeiten",
    "sg:phone":"+41 52 319 24 42",
    "sg:postcode":"8460",
    "sg:province":"Z\u00fcrich",
    "wof:name":"Stutz Ag Baggerunternehmung",
    "wof:placetype":"venue"
},
  "geometry": {"coordinates":[8.660094,47.635178],"type":"Point"}
}