{
  "type": "Feature",
  "properties": {
    "iso:country":"CH",
    "sg:address":"Hesisbohl Hoch-ybrig",
    "sg:city":"Oberiberg",
    "sg:classifiers":[
        {
            "category":"Restaurant",
            "type":"Food & Drink"
        }
    ],
    "sg:phone":"+41 55 414 25 03",
    "sg:postcode":"8843",
    "sg:province":"Schwyz",
    "wof:name":"Restaurant Wild\u00e4-maa",
    "wof:placetype":"venue"
},
  "geometry": {"coordinates":[8.7898454666,47.0042877197],"type":"Point"}
}