{
  "type": "Feature",
  "properties": {
    "iso:country":"CH",
    "sg:address":"Kirchhalde 12",
    "sg:city":"Uttwil",
    "sg:orig_category":"Stukkateurgewerbe, Gipserei U Verputzerei",
    "sg:phone":"+41 71 463 39 76",
    "sg:postcode":"8592",
    "sg:province":"Thurgau",
    "wof:name":"Manfred Rusch Gipsergesch\u00e4ft",
    "wof:placetype":"venue"
},
  "geometry": {"coordinates":[9.3430213928,47.5839233398],"type":"Point"}
}