{
  "type": "Feature",
  "properties": {
    "iso:country":"CH",
    "sg:address":"Rue Des Alpes 32",
    "sg:city":"Fribourg",
    "sg:orig_category":"Herstellung von sonstigen M\u00f6beln",
    "sg:phone":"+41 26 322 21 59",
    "sg:postcode":"1700",
    "sg:province":"Fribourg",
    "wof:name":"Encadrements St-hilaire, Corminboeuf Hilaire",
    "wof:placetype":"venue"
},
  "geometry": {"coordinates":[7.1588969231,46.8050613403],"type":"Point"}
}