{
  "type": "Feature",
  "properties": {
    "iso:country":"CH",
    "sg:address":"Route Corbelets",
    "sg:city":"Leysin",
    "sg:classifiers":[
        {
            "category":"Insurance",
            "subcategory":"Insurance Agent",
            "type":"Services"
        }
    ],
    "sg:phone":"+41 24 494 31 91",
    "sg:postcode":"1854",
    "sg:province":"Vaud",
    "sg:tags":[
        "versicherungsagenturen",
        "-broker"
    ],
    "wof:name":"Winterthur Assurances Agence",
    "wof:placetype":"venue"
},
  "geometry": {"coordinates":[7.0116848946,46.3377990723],"type":"Point"}
}