{
  "type": "Feature",
  "properties": {
    "iso:country":"CH",
    "sg:address":"Chemin Du Bosquet 26 1030 Bussigny-lausanne Case Postale 172",
    "sg:city":"Bussigny-lausanne",
    "sg:orig_category":"Handelsvermittlung U Grosshandel mit Automobilteilen U Zubeh\u00f6r Interessenvertretungen",
    "sg:phone":"+41 21 706 36 15",
    "sg:postcode":"1030",
    "sg:province":"Vaud",
    "wof:name":"Esa Organisation D'achat De La Branche Suisse De L'automobile Et Des V\u00e9hicules \u00e0 Moteur, Succursale De Bussigny-pr\u00e8s-lausanne",
    "wof:placetype":"venue"
},
  "geometry": {"coordinates":[6.5540118217,46.5457611084],"type":"Point"}
}