{
  "type": "Feature",
  "properties": {
    "iso:country":"CH",
    "sg:address":"Ischmattstrasse 7 4573 Ammannsegg. Postfach",
    "sg:city":"Ammannsegg",
    "sg:orig_category":"Herstellung von Betonerzeugnissen f\u00fcr den Bau",
    "sg:postcode":"4573",
    "sg:province":"Solothurn",
    "wof:name":"Fortmann Ag",
    "wof:placetype":"venue"
},
  "geometry": {"coordinates":[7.5245909691,47.1672821045],"type":"Point"}
}