{
  "type": "Feature",
  "properties": {
    "iso:country":"CH",
    "sg:address":"Neustadt 53 8200 Schaffhausen. Postfach 361",
    "sg:city":"Schaffhausen",
    "sg:orig_category":"Grosshandel mit Textilien",
    "sg:postcode":"8201",
    "sg:province":"Schaffhausen",
    "wof:name":"Mayr Friedrich",
    "wof:placetype":"venue"
},
  "geometry": {"coordinates":[8.6321296692,47.6954040527],"type":"Point"}
}