{
  "type": "Feature",
  "properties": {
    "iso:country":"CH",
    "sg:address":"L\u00e4ngfeldweg 91",
    "sg:city":"Biel/bienne",
    "sg:orig_category":"Instandhaltung U Reparatur von Automobilen",
    "sg:postcode":"2504",
    "sg:province":"Bern",
    "wof:name":"Mittelmann Automobile",
    "wof:placetype":"venue"
},
  "geometry": {"coordinates":[9.5429334641,47.4775428772],"type":"Point"}
}