{
  "type": "Feature",
  "properties": {
    "iso:country":"CH",
    "sg:address":"Riva Da S.antoni",
    "sg:city":"Morcote",
    "sg:orig_category":"Gemeindeverwaltungen",
    "sg:phone":"+41 91 996 11 42",
    "sg:postcode":"6922",
    "sg:province":"Ticino",
    "wof:name":"Amministrazione Comunale Di Morcote",
    "wof:placetype":"venue"
},
  "geometry": {"coordinates":[8.9145584106,45.9224433899],"type":"Point"}
}