{
  "type": "Feature",
  "properties": {
    "iso:country":"CH",
    "sg:address":"3919",
    "sg:city":"Blatten(l\u00f6tschen)",
    "sg:classifiers":[
        {
            "category":"Restaurant",
            "type":"Food & Drink"
        }
    ],
    "sg:phone":"+41 27 979 11 39",
    "sg:postcode":"3919",
    "sg:province":"Valais",
    "wof:name":"Restaurant Simplon",
    "wof:placetype":"venue"
},
  "geometry": {"coordinates":[8.0723695755,46.1851615906],"type":"Point"}
}