{
  "type": "Feature",
  "properties": {
    "iso:country":"CH",
    "sg:address":"Seestrasse 57",
    "sg:city":"W\u00e4denswil",
    "sg:orig_category":"Interessenvertretungen",
    "sg:postcode":"8820",
    "sg:province":"Z\u00fcrich",
    "wof:name":"Stiftung W\u00e4denswiler Kulturst\u00e4tten",
    "wof:placetype":"venue"
},
  "geometry": {"coordinates":[8.6788053513,47.2254867554],"type":"Point"}
}