{
  "type": "Feature",
  "properties": {
    "iso:country":"CH",
    "sg:address":"Ch. De Champrilly 27 1000 Lausanne. Postfach",
    "sg:city":"Cery",
    "sg:orig_category":"Non-Classified Establishments",
    "sg:postcode":"1008",
    "sg:province":"Vaud",
    "wof:name":"Guilloud Georges",
    "wof:placetype":"venue"
},
  "geometry": {"coordinates":[6.6075968742,46.5306549072],"type":"Point"}
}