{
  "type": "Feature",
  "properties": {
    "iso:country":"CH",
    "sg:address":"General-dufour-strasse 60",
    "sg:city":"Biel/bienne",
    "sg:orig_category":"Massagestudios",
    "sg:phone":"+41 32 351 61 42",
    "sg:postcode":"2502",
    "sg:province":"Bern",
    "wof:name":"Margrit Allemann Massagen",
    "wof:placetype":"venue"
},
  "geometry": {"coordinates":[7.3840417862,47.1410140991],"type":"Point"}
}