{
  "type": "Feature",
  "properties": {
    "iso:country":"CH",
    "sg:address":"Chesa San Spiert",
    "sg:city":"Pontresina",
    "sg:orig_category":"Unternehmensberatung",
    "sg:phone":"+41 81 842 77 33",
    "sg:postcode":"7504",
    "sg:province":"Graubunden",
    "wof:name":"Oekodata-treuhand, Z\u00f6llig Heinz Peter",
    "wof:placetype":"venue"
},
  "geometry": {"coordinates":[9.9057397842,46.4898681641],"type":"Point"}
}