{
  "type": "Feature",
  "properties": {
    "iso:country":"CH",
    "sg:address":"Dorfstrasse 43 3073 G\u00fcmligen. Postfach",
    "sg:city":"G\u00fcmligen",
    "sg:orig_category":"Softwareentwicklung U beratung",
    "sg:postcode":"3073",
    "sg:province":"Bern",
    "wof:name":"Weinmann Engineering",
    "wof:placetype":"venue"
},
  "geometry": {"coordinates":[7.5082612038,46.9357833862],"type":"Point"}
}