{
  "type": "Feature",
  "properties": {
    "iso:country":"CH",
    "sg:address":"Weinfelderstrasse 42 8580 Amriswil. Postfach",
    "sg:city":"Amriswil",
    "sg:orig_category":"Sonstige mit Sport verbundene T\u00e4tigkeiten",
    "sg:postcode":"8580",
    "sg:province":"Thurgau",
    "wof:name":"Verein Zur F\u00f6rderung Des Schweizer Kinderfussballs",
    "wof:placetype":"venue"
},
  "geometry": {"coordinates":[9.2919340134,47.5450973511],"type":"Point"}
}