{
  "type": "Feature",
  "properties": {
    "iso:country":"CH",
    "sg:address":"Vadianstrasse 7",
    "sg:city":"St.gallen",
    "sg:orig_category":"Sprachschulen",
    "sg:phone":"+41 71 223 62 15",
    "sg:postcode":"9000",
    "sg:province":"St. Gallen",
    "wof:name":"Ep Educational Programs Sg Ag Sprachschule",
    "wof:placetype":"venue"
},
  "geometry": {"coordinates":[9.3733968735,47.4230270386],"type":"Point"}
}