{
  "type": "Feature",
  "properties": {
    "iso:country":"CH",
    "sg:address":"Bahnhofstrasse 9",
    "sg:city":"Triengen",
    "sg:classifiers":[
        {
            "category":"Restaurant",
            "type":"Food & Drink"
        }
    ],
    "sg:phone":"+41 79 239 26 36",
    "sg:postcode":"6234",
    "sg:province":"Luzern",
    "wof:name":"Restaurant Bahnhof",
    "wof:placetype":"venue"
},
  "geometry": {"coordinates":[8.0728178024,47.2351875305],"type":"Point"}
}