{
  "type": "Feature",
  "properties": {
    "iso:country":"CH",
    "sg:address":"Rosenweg 1",
    "sg:city":"Wolfwil",
    "sg:orig_category":"Sanit\u00e4rinstallation",
    "sg:phone":"+41 62 926 24 78",
    "sg:postcode":"4628",
    "sg:province":"Solothurn",
    "wof:name":"Paul Ackermann K\u00fc-ba Reparatur-service",
    "wof:placetype":"venue"
},
  "geometry": {"coordinates":[7.7861218452,47.2699203491],"type":"Point"}
}