{
  "type": "Feature",
  "properties": {
    "iso:country":"CH",
    "sg:address":"Uelisweidstrasse 5",
    "sg:city":"Arni-islisberg",
    "sg:orig_category":"Instandhaltung U Reparatur von Automobilen",
    "sg:phone":"+41 56 634 18 14",
    "sg:postcode":"8905",
    "sg:province":"Aargau",
    "wof:name":"Dimorep Ag",
    "wof:placetype":"venue"
},
  "geometry": {"coordinates":[8.4405622482,47.3242912292],"type":"Point"}
}