{
  "type": "Feature",
  "properties": {
    "iso:country":"CH",
    "sg:address":"Al Ponte",
    "sg:city":"Iragna",
    "sg:orig_category":"Interessenvertretungen",
    "sg:phone":"+41 91 795 15 19",
    "sg:postcode":"6707",
    "sg:province":"Ticino",
    "wof:name":"Tecton Sa, Pf\u00e4ffikon, Succursale Di Iragna",
    "wof:placetype":"venue"
},
  "geometry": {"coordinates":[8.9680175781,46.330280304],"type":"Point"}
}