{
  "type": "Feature",
  "properties": {
    "iso:country":"CH",
    "sg:address":"Herrlimatt 5",
    "sg:city":"Sch\u00f6ftland",
    "sg:orig_category":"Aktivit\u00e4ten der Generalunternehmen im Baugewerbe Allgemeiner Hoch U Tiefbau",
    "sg:phone":"+41 79 602 75 05",
    "sg:postcode":"5040",
    "sg:province":"Aargau",
    "wof:name":"Solidbau M\u00fcller-rappard",
    "wof:placetype":"venue"
},
  "geometry": {"coordinates":[8.039009,47.302212],"type":"Point"}
}