{
  "type": "Feature",
  "properties": {
    "iso:country":"CH",
    "sg:address":"Rue Du Bas-du-ru",
    "sg:city":"Granges-marnand",
    "sg:orig_category":"Detailhandel mit Brot, Back U S\u00fcsswaren",
    "sg:phone":"+41 26 668 27 46",
    "sg:postcode":"1523",
    "sg:province":"Vaud",
    "wof:name":"Gino & Christel Romualdo Boulangerie Au Croissant D'or",
    "wof:placetype":"venue"
},
  "geometry": {"coordinates":[6.88634,46.763344],"type":"Point"}
}