{
  "type": "Feature",
  "properties": {
    "iso:country":"CH",
    "sg:address":"Auberg 1",
    "sg:city":"Basel",
    "sg:classifiers":[
        {
            "category":"Banks & Credit Unions",
            "subcategory":"Financial Services",
            "type":"Services"
        }
    ],
    "sg:phone":"+41 61 277 91 11",
    "sg:postcode":"4002",
    "sg:province":"Basel-Stadt",
    "sg:tags":[
        "banking",
        "finance",
        "insurance"
    ],
    "wof:name":"Wir Bank",
    "wof:placetype":"venue"
},
  "geometry": {"coordinates":[7.586662,47.55143],"type":"Point"}
}