{
  "type": "Feature",
  "properties": {
    "iso:country":"CH",
    "sg:address":"Rue Du Ch\u00e2teau 9a",
    "sg:city":"Peseux",
    "sg:orig_category":"Allgemeiner Hoch U Tiefbau",
    "sg:phone":"+41 32 730 36 40",
    "sg:postcode":"2034",
    "sg:province":"Neuch\u00e2tel",
    "wof:name":"Jegerlehner Olivier",
    "wof:placetype":"venue"
},
  "geometry": {"coordinates":[6.889447,46.988575],"type":"Point"}
}