{
  "type": "Feature",
  "properties": {
    "addr:full":"Rorschacher Strasse 16 St.gallen St. Gallen 9000",
    "addr:housenumber":"16",
    "addr:postcode":"9000",
    "addr:street":"Rorschacher Strasse",
    "iso:country":"CH",
    "sg:address":"Rorschacher Strasse 16",
    "sg:city":"St.gallen",
    "sg:orig_category":"Detailhandel mit Brot, Back U S\u00fcsswaren",
    "sg:phone":"+41 71 243 30 60",
    "sg:postcode":"9000",
    "sg:province":"St. Gallen",
    "wof:name":"Konditorei Zimmermann, Nachfolger Sturzenegger Albert",
    "wof:placetype":"venue"
},
  "geometry": {"coordinates":[9.380606,47.426212],"type":"Point"}
}