{
  "type": "Feature",
  "properties": {
    "iso:country":"CH",
    "sg:address":"Rue P\u00e9dro-meylan 1",
    "sg:city":"Gen\u00e8ve",
    "sg:orig_category":"Sonstiger Fachdetailhandel in Verkaufsr\u00e4umen",
    "sg:phone":"+41 22 735 75 10",
    "sg:postcode":"1208",
    "sg:province":"Gen\u00e8ve",
    "wof:name":"Alain Von Der Weid Bureau Philat\u00e9lique",
    "wof:placetype":"venue"
},
  "geometry": {"coordinates":[6.1635107994,46.1954917908],"type":"Point"}
}