{
  "type": "Feature",
  "properties": {
    "iso:country":"CH",
    "sg:address":"Zugerbergstrasse 6314 Unter\u00e4geri. Postfach 527",
    "sg:city":"Unter\u00e4geri",
    "sg:orig_category":"Herstellung von Drahtwaren Herstellung von Kunststoffwaren",
    "sg:phone":"+41 56 619 93 93",
    "sg:postcode":"6314",
    "sg:province":"Zug",
    "wof:name":"Howag Kabel Ag",
    "wof:placetype":"venue"
},
  "geometry": {"coordinates":[8.2714242935,47.3511161804],"type":"Point"}
}