{
  "type": "Feature",
  "properties": {
    "iso:country":"CH",
    "sg:address":"La Sciaz",
    "sg:city":"Rossini\u00e8re",
    "sg:orig_category":"Bauschreinerei Herstellung von Konstruktionsteilen, Fertigbauteilen U Ausbauelementen aus Holz",
    "sg:phone":"+41 26 924 50 74",
    "sg:postcode":"1836",
    "wof:name":"Neff Jean-pierre",
    "wof:placetype":"venue"
},
  "geometry": {"coordinates":[7.089585,46.46986],"type":"Point"}
}