{
  "type": "Feature",
  "properties": {
    "iso:country":"CH",
    "sg:address":"Juliastrasse 5 8000 Z\u00fcrich. Postfach 8032 Z\u00fcrich",
    "sg:city":"Zust",
    "sg:orig_category":"Non-Classified Establishments",
    "sg:postcode":"32",
    "wof:name":"Text N' Bild Gmbh",
    "wof:placetype":"venue"
},
  "geometry": {"coordinates":[8.5568380356,47.3648529053],"type":"Point"}
}