{
  "type": "Feature",
  "properties": {
    "iso:country":"CH",
    "sg:address":"Punte Franco",
    "sg:city":"Cadenazzo",
    "sg:classifiers":[
        {
            "category":"Airport",
            "type":"Transportation"
        }
    ],
    "sg:phone":"+41 91 850 20 00",
    "sg:postcode":"6593",
    "sg:province":"Ticino",
    "sg:tags":[
        "transport",
        "air"
    ],
    "wof:name":"Mat Transport Sa",
    "wof:placetype":"venue"
},
  "geometry": {"coordinates":[8.952302,46.149578],"type":"Point"}
}