{
  "type": "Feature",
  "properties": {
    "iso:country":"CH",
    "sg:address":"Quai Philippe-suchard 1",
    "sg:city":"Neuch\u00e2tel",
    "sg:classifiers":[
        {
            "category":"Restaurant",
            "type":"Food & Drink"
        }
    ],
    "sg:phone":"+41 32 731 80 50",
    "sg:postcode":"2000",
    "sg:province":"Neuch\u00e2tel",
    "wof:name":"Caf\u00e9 Buena Vista",
    "wof:placetype":"venue"
},
  "geometry": {"coordinates":[6.9064230919,46.9814071655],"type":"Point"}
}