{
  "type": "Feature",
  "properties": {
    "iso:country":"CH",
    "sg:address":"Ob Dem Fichtenrain 73",
    "sg:city":"Therwil",
    "sg:orig_category":"Grosshandel mit Getreide, Saatgut U Futtermitteln",
    "sg:phone":"+41 32 631 16 42",
    "sg:postcode":"4106",
    "sg:province":"Basel-Landschaft",
    "wof:name":"Agricom Gehrig Ag",
    "wof:placetype":"venue"
},
  "geometry": {"coordinates":[7.6535840034,47.2386894226],"type":"Point"}
}