{
  "type": "Feature",
  "properties": {
    "iso:country":"CH",
    "sg:address":"Dorfstrasse 54",
    "sg:city":"Ried-brig",
    "sg:orig_category":"Bauschreinerei",
    "sg:postcode":"3911",
    "sg:province":"Valais",
    "wof:name":"Herbert Behling Schreinerarbeiten",
    "wof:placetype":"venue"
},
  "geometry": {"coordinates":[8.016493,46.314308],"type":"Point"}
}