{
  "type": "Feature",
  "properties": {
    "iso:country":"CH",
    "sg:address":"Melsterb\u00fchl 222",
    "sg:city":"B\u00fchler",
    "sg:classifiers":[
        {
            "category":"Restaurant",
            "type":"Food & Drink"
        }
    ],
    "sg:phone":"+41 61 641 13 60",
    "sg:postcode":"9055",
    "sg:province":"Appenzell Ausserrhoden",
    "wof:name":"Restaurant Sch\u00fctzengarten",
    "wof:placetype":"venue"
},
  "geometry": {"coordinates":[7.6523051262,47.5845527649],"type":"Point"}
}