{
  "type": "Feature",
  "properties": {
    "iso:country":"CH",
    "sg:address":"Champ Hulay Rue Du 10",
    "sg:city":"Bassecourt",
    "sg:orig_category":"Sonstige pers\u00f6nliche Dienstleistungen",
    "sg:phone":"+41 32 426 54 88",
    "sg:postcode":"2854",
    "sg:province":"Jura",
    "wof:name":"Rais Pierre, Lily Rais Succ.",
    "wof:placetype":"venue"
},
  "geometry": {"coordinates":[7.2492442131,47.338924408],"type":"Point"}
}