{
  "type": "Feature",
  "properties": {
    "iso:country":"CH",
    "sg:address":"Oberhof",
    "sg:city":"Fischenthal",
    "sg:classifiers":[
        {
            "category":"Travel",
            "subcategory":"Hotels & Motels",
            "type":"Entertainment"
        }
    ],
    "sg:phone":"+41 55 245 11 18",
    "sg:postcode":"8497",
    "sg:province":"Z\u00fcrich",
    "sg:tags":[
        "hotels",
        "mit",
        "restaurant"
    ],
    "wof:name":"Restaurant Blume",
    "wof:placetype":"venue"
},
  "geometry": {"coordinates":[8.9213924408,47.3309745789],"type":"Point"}
}