{
  "type": "Feature",
  "properties": {
    "iso:country":"CH",
    "sg:address":"Hauptstrasse 90",
    "sg:city":"Sissach",
    "sg:orig_category":"Sonstige pers\u00f6nliche Dienstleistungen",
    "sg:postcode":"4450",
    "sg:province":"Basel-Landschaft",
    "wof:name":"Veit Rausch & Co. Produkt, Raum U. Architektur; Konzept, Kommunikation Usw.",
    "wof:placetype":"venue"
},
  "geometry": {"coordinates":[9.3801603317,47.4246444702],"type":"Point"}
}