{
  "type": "Feature",
  "properties": {
    "iso:country":"CH",
    "sg:address":"Pilgerweg 27",
    "sg:city":"R\u00fcschlikon",
    "sg:orig_category":"Primarschulen",
    "sg:phone":"+41 31 829 07 79",
    "sg:postcode":"8803",
    "sg:province":"Z\u00fcrich",
    "wof:name":"Primarschule Dorf",
    "wof:placetype":"venue"
},
  "geometry": {"coordinates":[7.3561701775,46.9711647034],"type":"Point"}
}