{
  "type": "Feature",
  "properties": {
    "iso:country":"CH",
    "sg:address":"Avenue Des Paquis 36",
    "sg:city":"Morges",
    "sg:orig_category":"Bauspenglerei Sanit\u00e4r, Heizungs U L\u00fcftungsinstallation",
    "sg:phone":"+41 21 801 39 34",
    "sg:postcode":"1110",
    "sg:province":"Vaud",
    "wof:name":"Bonatti & Goel Sa",
    "wof:placetype":"venue"
},
  "geometry": {"coordinates":[6.500944,46.514481],"type":"Point"}
}