{
  "type": "Feature",
  "properties": {
    "iso:country":"CH",
    "sg:address":"Rue Du Cendrier 7",
    "sg:city":"Gen\u00e8ve",
    "sg:orig_category":"Detailhandel mit Damenbekleidung",
    "sg:phone":"+41 22 738 37 67",
    "sg:postcode":"1201",
    "sg:province":"Gen\u00e8ve",
    "wof:name":"Boutique Linea 7 Confection F\u00e9minine",
    "wof:placetype":"venue"
},
  "geometry": {"coordinates":[6.144722,46.206936],"type":"Point"}
}