{
  "type": "Feature",
  "properties": {
    "iso:country":"CH",
    "sg:address":"Grand Place Est 1299 Crans-pr\u00e8s-c\u00e9ligny. Postfach",
    "sg:city":"Crans-sur-sierre",
    "sg:orig_category":"Unclassifiable Establishments",
    "sg:postcode":"3963",
    "sg:province":"Valais",
    "wof:name":"Vue Du Lac Crans Sa",
    "wof:placetype":"venue"
},
  "geometry": {"coordinates":[6.2041549683,46.3574867249],"type":"Point"}
}