{
  "type": "Feature",
  "properties": {
    "iso:country":"CH",
    "sg:address":"Altenbergstrasse 8a",
    "sg:city":"Bern",
    "sg:orig_category":"K\u00fcnstlerische U schriftstellerische T\u00e4tigkeiten U Darbietungen",
    "sg:phone":"+41 31 331 63 81",
    "sg:postcode":"3013",
    "sg:province":"Bern",
    "wof:name":"K.u.k. Highlights, Atelier Opladen, Kunst & Kultur Management",
    "wof:placetype":"venue"
},
  "geometry": {"coordinates":[7.4588022232,46.9500007629],"type":"Point"}
}