{
  "type": "Feature",
  "properties": {
    "iso:country":"CH",
    "sg:address":"Via Rinaldo Simen 9 6830 Chiasso. Postfach Caselle Postale 68",
    "sg:city":"Chiasso",
    "sg:orig_category":"Grosshandel mit B\u00fcromaschinen Grosshandel mit Datenverarbeitungsger\u00e4ten",
    "sg:phone":"+41 91 682 17 94",
    "sg:postcode":"6830",
    "sg:province":"Ticino",
    "wof:name":"Unitime Service Sa Informatica",
    "wof:placetype":"venue"
},
  "geometry": {"coordinates":[9.0255231857,45.8381271362],"type":"Point"}
}