{
  "type": "Feature",
  "properties": {
    "addr:full":"Klosbachstrasse 88 Z\u00fcrich Z\u00fcrich 8032",
    "addr:housenumber":"88",
    "addr:postcode":"8032",
    "addr:street":"Klosbachstrasse",
    "iso:country":"CH",
    "sg:address":"Klosbachstrasse 88",
    "sg:city":"Z\u00fcrich",
    "sg:orig_category":"Detailhandel mit Beleuchtungs U Haushaltsgegenst\u00e4nden Detailhandel mit M\u00f6beln",
    "sg:phone":"+41 13837848",
    "sg:postcode":"8032",
    "sg:province":"Z\u00fcrich",
    "wof:name":"Roger Schnetzler Wohngestaltung",
    "wof:placetype":"venue"
},
  "geometry": {"coordinates":[8.560194,47.36747],"type":"Point"}
}