{
  "type": "Feature",
  "properties": {
    "iso:country":"CH",
    "sg:address":"Grand-rue",
    "sg:city":"Perroy",
    "sg:orig_category":"Rebbau",
    "sg:phone":"+41 21 825 17 21",
    "sg:postcode":"1166",
    "sg:province":"Vaud",
    "wof:name":"Raymond Metzener Viticulteur",
    "wof:placetype":"venue"
},
  "geometry": {"coordinates":[6.3680949211,46.4704589844],"type":"Point"}
}