{
  "type": "Feature",
  "properties": {
    "iso:country":"CH",
    "sg:address":"Bahnhofstrasse",
    "sg:city":"Zweisimmen",
    "sg:orig_category":"Detailhandel mit Uhren U Schmuck Reparatur von Uhren U Schmuck",
    "sg:phone":"+41 33 722 10 17",
    "sg:postcode":"3770",
    "sg:province":"Bern",
    "wof:name":"Martin Augsburger Uhren Bijouterie",
    "wof:placetype":"venue"
},
  "geometry": {"coordinates":[7.3725447655,46.5536994934],"type":"Point"}
}