{
  "type": "Feature",
  "properties": {
    "iso:country":"CH",
    "sg:address":"Hardstrasse 63c",
    "sg:city":"Wettingen",
    "sg:orig_category":"Grafikateliers, Design Softwareentwicklung U beratung",
    "sg:phone":"+41 56 426 70 11",
    "sg:postcode":"5430",
    "sg:province":"Aargau",
    "wof:name":"Schauer Sonja",
    "wof:placetype":"venue"
},
  "geometry": {"coordinates":[8.3367624283,47.4574356079],"type":"Point"}
}