{
  "type": "Feature",
  "properties": {
    "iso:country":"CH",
    "sg:address":"Dorfstrasse 2 5036 Oberentfelden. Postfach",
    "sg:city":"Oberentfelden",
    "sg:orig_category":"RESTAURANTS: TEA-ROOMS",
    "sg:postcode":"5036",
    "sg:province":"Aargau",
    "wof:name":"Gabbiano-freihof Gmbh",
    "wof:placetype":"venue"
},
  "geometry": {"coordinates":[8.0467681885,47.3567276001],"type":"Point"}
}