{
  "type": "Feature",
  "properties": {
    "iso:country":"CH",
    "sg:address":"Rue De L'h\u00f4tel De Ville 11",
    "sg:city":"Estavayer-le-lac",
    "sg:orig_category":"Gemeindeverwaltungen",
    "sg:phone":"+41 26 663 92 40",
    "sg:postcode":"1470",
    "sg:province":"Fribourg",
    "wof:name":"Administration Communale De Estavayer-le-lac",
    "wof:placetype":"venue"
},
  "geometry": {"coordinates":[6.8467497826,46.8488883972],"type":"Point"}
}