{
  "type": "Feature",
  "properties": {
    "iso:country":"CH",
    "sg:address":"Kasernenstrasse 9",
    "sg:city":"D\u00fcbendorf",
    "sg:orig_category":"Unternehmensberatung",
    "sg:phone":"+41 18216133",
    "sg:postcode":"8600",
    "sg:province":"Z\u00fcrich",
    "wof:name":"Sigg Organisation",
    "wof:placetype":"venue"
},
  "geometry": {"coordinates":[8.6271829605,47.4041862488],"type":"Point"}
}