{
  "type": "Feature",
  "properties": {
    "iso:country":"CH",
    "sg:address":"Ch. Du Faubourg-de-cruseilles 1227 Carouge Ge. Postfach",
    "sg:city":"Gen\u00e8ve",
    "sg:orig_category":"Wirtschaftspr\u00fcfung, Steuerberatung U Treuhand",
    "sg:phone":"+41 31 747 01 43",
    "sg:postcode":"1201",
    "sg:province":"Gen\u00e8ve",
    "wof:name":"Nuborg Gmbh",
    "wof:placetype":"venue"
},
  "geometry": {"coordinates":[7.2428770065,46.8986701965],"type":"Point"}
}