{
  "type": "Feature",
  "properties": {
    "iso:country":"CH",
    "sg:address":"Augenweidstrasse 53",
    "sg:city":"Oberwil-lieli",
    "sg:orig_category":"S\u00e4ge, Hobel U Holzimpr\u00e4gnierwerke",
    "sg:phone":"+41 56 633 19 47",
    "sg:postcode":"8966",
    "sg:province":"Aargau",
    "wof:name":"Ad. Stierli S\u00e4gerei-holzhandel Oberwil",
    "wof:placetype":"venue"
},
  "geometry": {"coordinates":[8.390203476,47.3327407837],"type":"Point"}
}