{
  "type": "Feature",
  "properties": {
    "iso:country":"CH",
    "sg:address":"Dorfstrasse 27",
    "sg:city":"H\u00fcnenberg",
    "sg:orig_category":"Fachdetailhandel in Verkaufsr\u00e4umen",
    "sg:phone":"+41 41 780 70 53",
    "sg:postcode":"6331",
    "sg:province":"Zug",
    "wof:name":"Christen Katharina",
    "wof:placetype":"venue"
},
  "geometry": {"coordinates":[8.4248819351,47.1730766296],"type":"Point"}
}