{
  "type": "Feature",
  "properties": {
    "iso:country":"CH",
    "sg:address":"Langackerstrasse 31",
    "sg:city":"Th\u00fcrnen",
    "sg:orig_category":"Sonstiger Grosshandel",
    "sg:postcode":"4441",
    "sg:province":"Basel-Landschaft",
    "wof:name":"Bns Bussinger",
    "wof:placetype":"venue"
},
  "geometry": {"coordinates":[7.8244800568,47.4578132629],"type":"Point"}
}