{
  "type": "Feature",
  "properties": {
    "iso:country":"CH",
    "sg:address":"Canonica Via 16",
    "sg:city":"Lugano",
    "sg:orig_category":"Non-Classified Establishments",
    "sg:postcode":"6900",
    "sg:province":"Ticino",
    "wof:name":"Korita Gmbh",
    "wof:placetype":"venue"
},
  "geometry": {"coordinates":[7.5076799393,46.9599990845],"type":"Point"}
}