{
  "type": "Feature",
  "properties": {
    "addr:full":"Route Des Bl\u00e9s D'or 16 Villars-sur-gl\u00e2ne Fribourg 1752",
    "addr:housenumber":"16",
    "addr:postcode":"1752",
    "addr:street":"Route Des Ble\u0301S D'Or",
    "iso:country":"CH",
    "sg:address":"Route Des Bl\u00e9s D'or 16",
    "sg:city":"Villars-sur-gl\u00e2ne",
    "sg:classifiers":[
        {
            "category":"Building & Trades",
            "subcategory":"Electrical",
            "type":"Services"
        }
    ],
    "sg:phone":"+41 26 402 78 52",
    "sg:postcode":"1752",
    "sg:province":"Fribourg",
    "sg:tags":[
        "installation"
    ],
    "wof:name":"Mtte Electricit\u00e9 Jean Martinez",
    "wof:placetype":"venue"
},
  "geometry": {"coordinates":[7.12437,46.796261],"type":"Point"}
}