{
  "type": "Feature",
  "properties": {
    "iso:country":"CH",
    "sg:address":"M\u00fchleweg 7 9495 Triesen. Postfach",
    "sg:city":"Triesen",
    "sg:orig_category":"Geb\u00e4ude, Wohnungsreinigung",
    "sg:phone":"+41 18335052",
    "sg:postcode":"9495",
    "wof:name":"Geb\u00e4udeunterhalt Luigi De Bonis",
    "wof:placetype":"venue"
},
  "geometry": {"coordinates":[8.6478147507,47.4146461487],"type":"Point"}
}