{
  "type": "Feature",
  "properties": {
    "iso:country":"CH",
    "sg:address":"Feldstrasse 53/41",
    "sg:city":"Urdorf",
    "sg:orig_category":"Sportvereine Turnen",
    "sg:phone":"+41 17341525",
    "sg:postcode":"8902",
    "sg:province":"Z\u00fcrich",
    "wof:name":"M\u00e4nnerriege Urdorf",
    "wof:placetype":"venue"
},
  "geometry": {"coordinates":[8.4223966599,47.3870048523],"type":"Point"}
}