{
  "type": "Feature",
  "properties": {
    "iso:country":"CH",
    "sg:address":"Schwamendingenstrasse 79 8050 Z\u00fcrich",
    "sg:city":"Zust",
    "sg:orig_category":"Non-Classified Establishments",
    "sg:postcode":"50",
    "wof:name":"Massagepraxis Vitalis, Roland John",
    "wof:placetype":"venue"
},
  "geometry": {"coordinates":[8.6391172409,46.8800430298],"type":"Point"}
}