{
  "type": "Feature",
  "properties": {
    "iso:country":"CH",
    "sg:address":"Jurastrasse 101",
    "sg:city":"Grenchen",
    "sg:orig_category":"Sportvereine Orientierungslauf",
    "sg:phone":"+41 32 622 46 22",
    "sg:postcode":"2540",
    "sg:province":"Solothurn",
    "wof:name":"Olg Biberist",
    "wof:placetype":"venue"
},
  "geometry": {"coordinates":[7.4063491821,47.1987495422],"type":"Point"}
}