{
  "type": "Feature",
  "properties": {
    "iso:country":"CH",
    "sg:address":"Via Pauzella",
    "sg:city":"Novazzano",
    "sg:classifiers":[
        {
            "category":"Bars & Pubs",
            "type":"Food & Drink"
        }
    ],
    "sg:phone":"+41 91 647 27 77",
    "sg:postcode":"6883",
    "sg:province":"Ticino",
    "sg:tags":[
        "restaurant"
    ],
    "wof:name":"Restaurant Club House Team Pauzella",
    "wof:placetype":"venue"
},
  "geometry": {"coordinates":[8.968769,45.836987],"type":"Point"}
}