{
  "type": "Feature",
  "properties": {
    "iso:country":"CH",
    "sg:address":"1673",
    "sg:city":"Auboranges",
    "sg:orig_category":"Grosshandel mit Milch, Milcherzeugnissen, Eiern, Speise\u00f6len U Nahrungsfetten",
    "sg:phone":"+41 56 443 21 31",
    "sg:postcode":"1673",
    "sg:province":"Fribourg",
    "wof:name":"Johann Blum Eier & Gerberk\u00e4se Engros",
    "wof:placetype":"venue"
},
  "geometry": {"coordinates":[8.1509151459,47.4299697876],"type":"Point"}
}