{
  "type": "Feature",
  "properties": {
    "iso:country":"CH",
    "sg:address":"Chamerstrasse 45",
    "sg:city":"H\u00fcnenberg",
    "sg:orig_category":"Unternehmensberatung",
    "sg:postcode":"6331",
    "sg:province":"Zug",
    "wof:name":"Intrapars Zug Ag",
    "wof:placetype":"venue"
},
  "geometry": {"coordinates":[8.4333333969,47.1798324585],"type":"Point"}
}