{
  "type": "Feature",
  "properties": {
    "addr:full":"Auhaldenstrasse 16b Turgi Aargau 5300",
    "addr:housenumber":"16b",
    "addr:postcode":"5300",
    "addr:street":"Auhaldenstrasse",
    "iso:country":"CH",
    "sg:address":"Auhaldenstrasse 16b",
    "sg:city":"Turgi",
    "sg:orig_category":"Architekturb\u00fcros",
    "sg:phone":"+41 56 288 09 60",
    "sg:postcode":"5300",
    "sg:province":"Aargau",
    "wof:name":"Frei Architekten & Planer Ag",
    "wof:placetype":"venue"
},
  "geometry": {"coordinates":[8.252895,47.49358],"type":"Point"}
}