{
  "type": "Feature",
  "properties": {
    "iso:country":"CH",
    "sg:address":"St. Margarethen",
    "sg:city":"Nottwil",
    "sg:orig_category":"Verwertung von Milch",
    "sg:postcode":"6207",
    "sg:province":"Luzern",
    "wof:name":"K\u00e4sereigenossenschaft N\u00f6thenhaus",
    "wof:placetype":"venue"
},
  "geometry": {"coordinates":[7.4180898666,46.7700996399],"type":"Point"}
}