{
  "type": "Feature",
  "properties": {
    "iso:country":"CH",
    "sg:address":"Gotthardstrasse 84",
    "sg:city":"Amsteg",
    "sg:orig_category":"Kantonalbanken",
    "sg:phone":"+41 41 870 32 33",
    "sg:postcode":"6474",
    "sg:province":"Uri",
    "wof:name":"Urner Kantonalbank",
    "wof:placetype":"venue"
},
  "geometry": {"coordinates":[8.6631307602,46.8750152588],"type":"Point"}
}