{
  "type": "Feature",
  "properties": {
    "iso:country":"CH",
    "sg:address":"Neuweilerstrasse 88 4054 Basel. Postfach",
    "sg:city":"Basel",
    "sg:orig_category":"Aktivit\u00e4ten der Krankenschwestern U Hebammen, Hauspflege Organisationen des Gesundheitswesen",
    "sg:phone":"+41 61 302 12 25",
    "sg:postcode":"4015",
    "sg:province":"Basel-Stadt",
    "wof:name":"Spitex Prioritas Private Haus-& Krankenpflege",
    "wof:placetype":"venue"
},
  "geometry": {"coordinates":[7.559397,47.546291],"type":"Point"}
}