{
  "type": "Feature",
  "properties": {
    "iso:country":"CH",
    "sg:address":"7523",
    "sg:city":"Madulain",
    "sg:orig_category":"Elektroinstallation Herstellung von Elektromotoren, Generatoren U Transformatoren",
    "sg:phone":"+41 81 854 32 42",
    "sg:postcode":"7523",
    "sg:province":"Graubunden",
    "wof:name":"Elektro Bernina Ag",
    "wof:placetype":"venue"
},
  "geometry": {"coordinates":[9.9365310669,46.5853614807],"type":"Point"}
}