{
  "type": "Feature",
  "properties": {
    "iso:country":"CH",
    "sg:address":"Giarsun",
    "sg:city":"Guarda",
    "sg:orig_category":"Bauschreinerei D\u00e4mmung gegen K\u00e4lte, W\u00e4rme, Schall U Ersch\u00fctterung",
    "sg:phone":"+41 81 862 21 91",
    "sg:postcode":"7545",
    "sg:province":"Graubunden",
    "wof:name":"Barb\u00fcda Gmbh",
    "wof:placetype":"venue"
},
  "geometry": {"coordinates":[10.14382,46.769939],"type":"Point"}
}