{
  "type": "Feature",
  "properties": {
    "iso:country":"CH",
    "sg:address":"Z\u00fcrcherstrasse 73",
    "sg:city":"Thalwil",
    "sg:orig_category":"Instandhaltung U Reparatur von Automobilen",
    "sg:phone":"+41 17223050",
    "sg:postcode":"8800",
    "sg:province":"Z\u00fcrich",
    "wof:name":"Vogelsang Automobilie",
    "wof:placetype":"venue"
},
  "geometry": {"coordinates":[8.5639724731,47.2857093811],"type":"Point"}
}