{
  "type": "Feature",
  "properties": {
    "iso:country":"CH",
    "sg:address":"Holeestrasse 43",
    "sg:city":"Basel",
    "sg:orig_category":"Gesundheitswesen",
    "sg:phone":"+41 61 422 06 43",
    "sg:postcode":"4054",
    "sg:province":"Basel-Stadt",
    "wof:name":"Breitschmid Patrik",
    "wof:placetype":"venue"
},
  "geometry": {"coordinates":[7.5724368095,47.5447311401],"type":"Point"}
}