{
  "type": "Feature",
  "properties": {
    "iso:country":"CH",
    "sg:address":"Blumensteinstrasse 2 3012 Bern. Postfach 5225",
    "sg:city":"Bern",
    "sg:orig_category":"Wirtschaftspr\u00fcfung, Steuerberatung U Treuhand",
    "sg:phone":"+41 31 306 66 66",
    "sg:postcode":"3012",
    "sg:province":"Bern",
    "wof:name":"Ato Treuhand & Datenservice Ag Treuhandb\u00fcro Usw",
    "wof:placetype":"venue"
},
  "geometry": {"coordinates":[7.4273247719,46.9550743103],"type":"Point"}
}