{
  "type": "Feature",
  "properties": {
    "iso:country":"CH",
    "sg:address":"Gattikonerstrasse 127 8136 Gattikon. Postfach",
    "sg:city":"Gattikon",
    "sg:orig_category":"Fachdetailhandel in Verkaufsr\u00e4umen",
    "sg:postcode":"8136",
    "sg:province":"Z\u00fcrich",
    "wof:name":"Gezet Ag",
    "wof:placetype":"venue"
},
  "geometry": {"coordinates":[8.5453252792,47.283039093],"type":"Point"}
}