{
  "type": "Feature",
  "properties": {
    "iso:country":"CH",
    "sg:address":"Sandrainstrasse 68 3007 Bern. Postfach",
    "sg:city":"Bern",
    "sg:orig_category":"RESTAURANTS: TEA-ROOMS",
    "sg:phone":"+41 56 241 13 40",
    "sg:postcode":"3005",
    "sg:province":"Bern",
    "wof:name":"Carpaccio Gmbh Restaurant Usw",
    "wof:placetype":"venue"
},
  "geometry": {"coordinates":[8.3294963837,47.5214424133],"type":"Point"}
}