{
  "type": "Feature",
  "properties": {
    "iso:country":"CH",
    "sg:address":"Tribunal-f\u00e9d\u00e9ral Av. Du 5",
    "sg:city":"Lausanne",
    "sg:orig_category":"Verwaltung von Immobilien",
    "sg:phone":"+41 21 351 44 45",
    "sg:postcode":"1005",
    "sg:province":"Vaud",
    "wof:name":"Arcam S\u00e0rl",
    "wof:placetype":"venue"
},
  "geometry": {"coordinates":[6.638384819,46.5198402405],"type":"Point"}
}