{
  "type": "Feature",
  "properties": {
    "iso:country":"CH",
    "sg:address":"Winterhaldenstrasse 14",
    "sg:city":"Heimberg",
    "sg:orig_category":"Mechanik",
    "sg:postcode":"3627",
    "sg:province":"Bern",
    "wof:name":"Murgotti & Sch\u00fcrch Metall",
    "wof:placetype":"venue"
},
  "geometry": {"coordinates":[7.6027431488,46.7985038757],"type":"Point"}
}