{
  "type": "Feature",
  "properties": {
    "addr:full":"Dorfg. 14 Sumiswald Bern 3454",
    "addr:housenumber":"14",
    "addr:postcode":"3454",
    "addr:street":"Dorfg.",
    "iso:country":"CH",
    "sg:address":"Dorfg. 14",
    "sg:city":"Sumiswald",
    "sg:classifiers":[
        {
            "category":"Shopping",
            "subcategory":"Clothing, Apparel, & Fashions",
            "type":"Retail Goods"
        }
    ],
    "sg:phone":"+41 34 432 33 33",
    "sg:postcode":"3454",
    "sg:province":"Bern",
    "sg:tags":[
        "textile",
        "clothing",
        "clothes"
    ],
    "wof:name":"Marti Berufsbekleidung Ag",
    "wof:placetype":"venue"
},
  "geometry": {"coordinates":[7.737956,47.035275],"type":"Point"}
}