{
  "type": "Feature",
  "properties": {
    "iso:country":"CH",
    "sg:address":"Rue De L' Union 17",
    "sg:city":"Biel/bienne",
    "sg:classifiers":[
        {
            "category":"Manufacturing",
            "subcategory":"Glass & Minerals",
            "type":"Manufacturing & Wholesale Goods"
        }
    ],
    "sg:phone":"+41 32 323 37 37",
    "sg:postcode":"2502",
    "sg:province":"Bern",
    "sg:tags":[
        "cleaning",
        "agent"
    ],
    "wof:name":"Modoptik Yves Perret",
    "wof:placetype":"venue"
},
  "geometry": {"coordinates":[7.245523,47.139729],"type":"Point"}
}