{
  "type": "Feature",
  "properties": {
    "iso:country":"CH",
    "sg:address":"Zur Ranch",
    "sg:city":"Hefenhofen",
    "sg:orig_category":"Grosshandel mit Getreide, Saatgut U Futtermitteln",
    "sg:postcode":"8580",
    "sg:province":"Thurgau",
    "wof:name":"Thurgi-milch Gmbh",
    "wof:placetype":"venue"
},
  "geometry": {"coordinates":[9.3219032288,47.5562171936],"type":"Point"}
}