{
  "type": "Feature",
  "properties": {
    "addr:full":"Florastrasse 12 Littau Luzern 6014",
    "addr:housenumber":"12",
    "addr:postcode":"6014",
    "addr:street":"Florastrasse",
    "iso:country":"CH",
    "sg:address":"Florastrasse 12",
    "sg:city":"Littau",
    "sg:orig_category":"Grosshandel mit Blumen U Pflanzen Herstellung von Werkzeugen",
    "sg:phone":"+41 41 250 64 57",
    "sg:postcode":"6014",
    "sg:province":"Luzern",
    "wof:name":"Beck Ag Samen Und G\u00e4rtnereibedarf",
    "wof:placetype":"venue"
},
  "geometry": {"coordinates":[8.25594,47.056252],"type":"Point"}
}