{
  "type": "Feature",
  "properties": {
    "iso:country":"CH",
    "sg:address":"Feldm\u00fchlestrasse 1",
    "sg:city":"Kriens",
    "sg:orig_category":"D\u00e4mmung gegen K\u00e4lte, W\u00e4rme, Schall U Ersch\u00fctterung",
    "sg:phone":"+41 41 320 64 66",
    "sg:postcode":"6010",
    "sg:province":"Luzern",
    "wof:name":"Frei Bruno Gmbh",
    "wof:placetype":"venue"
},
  "geometry": {"coordinates":[8.2668304443,47.0356407166],"type":"Point"}
}