{
  "type": "Feature",
  "properties": {
    "iso:country":"CH",
    "sg:address":"Avenue De Beauregard 12 1700 Fribourg Case Postale 286",
    "sg:city":"Fribourg",
    "sg:orig_category":"Herstellung von Hebezeugen U F\u00f6rdermitteln",
    "sg:phone":"+41 26 426 36 16",
    "sg:postcode":"1701",
    "sg:province":"Fribourg",
    "wof:name":"Liftec Sa",
    "wof:placetype":"venue"
},
  "geometry": {"coordinates":[7.1475830078,46.802028656],"type":"Point"}
}