{
  "type": "Feature",
  "properties": {
    "iso:country":"CH",
    "sg:address":"Dorfstrasse 51",
    "sg:city":"Pfungen",
    "sg:orig_category":"Malerei",
    "sg:phone":"+41 56 664 30 00",
    "sg:postcode":"8422",
    "sg:province":"Z\u00fcrich",
    "wof:name":"Armando Tamburini Malergesch\u00e4ft",
    "wof:placetype":"venue"
},
  "geometry": {"coordinates":[8.3174819946,47.2825775146],"type":"Point"}
}