{
  "type": "Feature",
  "properties": {
    "iso:country":"CH",
    "sg:address":"Rheinstrasse 81",
    "sg:city":"Pratteln",
    "sg:classifiers":[
        {
            "category":"Coffee & Tea",
            "type":"Food & Drink"
        }
    ],
    "sg:phone":"+41 61 816 61 61",
    "sg:postcode":"4133",
    "sg:province":"Basel-Landschaft",
    "sg:tags":[
        "aromatic"
    ],
    "wof:name":"Promena Ag",
    "wof:placetype":"venue"
},
  "geometry": {"coordinates":[7.710791,47.534691],"type":"Point"}
}