{
  "type": "Feature",
  "properties": {
    "iso:country":"CH",
    "sg:address":"Chriesiweg 4",
    "sg:city":"Gebenstorf",
    "sg:orig_category":"Impregnating Sprays",
    "sg:phone":"+41 56 223 25 81",
    "sg:postcode":"5412",
    "sg:province":"Aargau",
    "wof:name":"Viking Cherrox-vertrieb",
    "wof:placetype":"venue"
},
  "geometry": {"coordinates":[8.2440052032,47.4781265259],"type":"Point"}
}