{
  "type": "Feature",
  "properties": {
    "iso:country":"CH",
    "sg:address":"Via L. Lavizzari 6",
    "sg:city":"Chiasso",
    "sg:orig_category":"Vermietung U Verpachtung von eigenen Immobilien",
    "sg:phone":"+41 33 744 84 04",
    "sg:postcode":"6830",
    "sg:province":"Ticino",
    "wof:name":"Uhu-immobilien Ag",
    "wof:placetype":"venue"
},
  "geometry": {"coordinates":[7.2839550972,46.4762382507],"type":"Point"}
}