{
  "type": "Feature",
  "properties": {
    "iso:country":"CH",
    "sg:address":"St. Alban-rheinweg 74 4052 Basel. Postfach",
    "sg:city":"Basel",
    "sg:orig_category":"Rechtsberatung",
    "sg:phone":"+41 61 205 11 11",
    "sg:postcode":"4006",
    "wof:name":"Mundipharma Laboratories Gmbh",
    "wof:placetype":"venue"
},
  "geometry": {"coordinates":[7.6021060944,47.5546722412],"type":"Point"}
}