{
  "type": "Feature",
  "properties": {
    "iso:country":"CH",
    "sg:address":"Sonnmatt 283",
    "sg:city":"Staffelbach",
    "sg:orig_category":"Vermietung U Verpachtung von eigenen Immobilien",
    "sg:phone":"+41 62 721 22 89",
    "sg:postcode":"5053",
    "sg:province":"Aargau",
    "wof:name":"Suhre Bau Ag",
    "wof:placetype":"venue"
},
  "geometry": {"coordinates":[8.042057991,47.2863616943],"type":"Point"}
}