{
  "type": "Feature",
  "properties": {
    "iso:country":"CH",
    "sg:address":"Route De Bussigny 30",
    "sg:city":"Crissier",
    "sg:orig_category":"Instandhaltung U Reparatur von Automobilen",
    "sg:phone":"+41 21 634 19 32",
    "sg:postcode":"1023",
    "sg:province":"Vaud",
    "wof:name":"Andrighetto & Di Certo S\u00e0rl Garage Central",
    "wof:placetype":"venue"
},
  "geometry": {"coordinates":[6.5737228394,46.540763855],"type":"Point"}
}