{
  "type": "Feature",
  "properties": {
    "iso:country":"CH",
    "sg:address":"Rigiplatz 1 8006 Z\u00fcrich. Postfach",
    "sg:city":"Z\u00fcrich",
    "sg:orig_category":"Architektur U Ingenieurb\u00fcros",
    "sg:phone":"+41 13637579",
    "sg:postcode":"8001",
    "sg:province":"Z\u00fcrich",
    "wof:name":"Leuenberger + Kocher Architekten Ag Architekturb\u00fcro",
    "wof:placetype":"venue"
},
  "geometry": {"coordinates":[8.548591,47.384903],"type":"Point"}
}