{
  "type": "Feature",
  "properties": {
    "iso:country":"CH",
    "sg:address":"Zielweg 8",
    "sg:city":"Flawil",
    "sg:orig_category":"Elektroinstallation",
    "sg:phone":"+41 71 390 04 04",
    "sg:postcode":"9230",
    "sg:province":"St. Gallen",
    "wof:name":"Triconsult Gmbh",
    "wof:placetype":"venue"
},
  "geometry": {"coordinates":[9.1870832443,47.4163627625],"type":"Point"}
}