{
  "type": "Feature",
  "properties": {
    "iso:country":"CH",
    "sg:address":"Ziegelmattstr. 24 3113 Rubigen. Postfach",
    "sg:city":"Rubigen",
    "sg:orig_category":"Unternehmensberatung",
    "sg:phone":"+41 31 722 07 30",
    "sg:postcode":"3113",
    "sg:province":"Bern",
    "wof:name":"Wyss Consulting",
    "wof:placetype":"venue"
},
  "geometry": {"coordinates":[7.5411171913,46.8945465088],"type":"Point"}
}