{
  "type": "Feature",
  "properties": {
    "iso:country":"CH",
    "sg:address":"1720 Corminboeuf Case Postale 12",
    "sg:city":"Corminboeuf",
    "sg:orig_category":"Sportvereine Ballsport Fussball",
    "sg:phone":"+41 32 757 14 98",
    "sg:postcode":"1720",
    "sg:province":"Fribourg",
    "wof:name":"Fc Cornaux",
    "wof:placetype":"venue"
},
  "geometry": {"coordinates":[7.0178799629,47.0336494446],"type":"Point"}
}