{
  "type": "Feature",
  "properties": {
    "iso:country":"CH",
    "sg:address":"J\u00e4gerweg 7 4900 Langenthal. Postfach",
    "sg:city":"Langenthal",
    "sg:orig_category":"Allgemeiner Hoch U Tiefbau",
    "sg:phone":"+41 62 922 36 07",
    "sg:postcode":"4900",
    "sg:province":"Bern",
    "wof:name":"Volante Baumanagement Ausf\u00fchrungsplanung U. Bauleitung Im Hochbau",
    "wof:placetype":"venue"
},
  "geometry": {"coordinates":[7.779386,47.212246],"type":"Point"}
}