{
  "type": "Feature",
  "properties": {
    "iso:country":"CH",
    "sg:address":"Wildeggstrasse 5",
    "sg:city":"St.gallen",
    "sg:orig_category":"Vereine Orchester",
    "sg:postcode":"9000",
    "sg:province":"St. Gallen",
    "wof:name":"C\u00e4cilia-musikgesellschaft",
    "wof:placetype":"venue"
},
  "geometry": {"coordinates":[8.8172197342,47.2253608704],"type":"Point"}
}