{
  "type": "Feature",
  "properties": {
    "iso:country":"CH",
    "sg:address":"4118",
    "sg:city":"Rodersdorf",
    "sg:orig_category":"Schulpflegen",
    "sg:phone":"+41 62 298 21 87",
    "sg:postcode":"4118",
    "sg:province":"Solothurn",
    "wof:name":"Schulkommission Der Gemeinde Rohr Bei Olten",
    "wof:placetype":"venue"
},
  "geometry": {"coordinates":[7.9548649788,47.4095458984],"type":"Point"}
}