{
  "type": "Feature",
  "properties": {
    "iso:country":"CH",
    "sg:address":"Simplemont Chemin 1 1005 Lausanne. Postfach",
    "sg:city":"Lausanne",
    "sg:orig_category":"Betrieb U technische Hilfsdienste des Kultur U Unterhaltungswesens",
    "sg:postcode":"1003",
    "sg:province":"Vaud",
    "wof:name":"Magnetik's Animation, Leipziger Marc",
    "wof:placetype":"venue"
},
  "geometry": {"coordinates":[6.649885,46.518562],"type":"Point"}
}