{
  "type": "Feature",
  "properties": {
    "iso:country":"CH",
    "sg:address":"Avenue De Bel-air 17",
    "sg:city":"Ch\u00eane-bourg",
    "sg:orig_category":"Arztpraxen",
    "sg:phone":"+41 22 348 59 19",
    "sg:postcode":"1225",
    "sg:province":"Gen\u00e8ve",
    "wof:name":"Dr M\u00e9d. Claude-a. Bernheim M\u00e9decin Sp\u00e9cialiste Fmh",
    "wof:placetype":"venue"
},
  "geometry": {"coordinates":[6.194759,46.19783],"type":"Point"}
}