{
  "type": "Feature",
  "properties": {
    "iso:country":"CH",
    "sg:address":"Burgernzielrain 6 3006 Bern. Postfach",
    "sg:city":"Bern",
    "sg:orig_category":"Rechtsberatung",
    "sg:postcode":"3005",
    "sg:province":"Bern",
    "wof:name":"Finastrat Ag Vermittlung Von Gesch\u00e4ften, Rechtsfragenberatung Usw",
    "wof:placetype":"venue"
},
  "geometry": {"coordinates":[7.4692769051,46.9416389465],"type":"Point"}
}