{
  "type": "Feature",
  "properties": {
    "iso:country":"CH",
    "sg:address":"R\u00fctistrasse 14",
    "sg:city":"Uznach",
    "sg:orig_category":"Hardwareberatung",
    "sg:postcode":"8730",
    "sg:province":"St. Gallen",
    "wof:name":"Capricorne Systems, Vu Hong Quang",
    "wof:placetype":"venue"
},
  "geometry": {"coordinates":[6.5650820732,46.5312843323],"type":"Point"}
}