{
  "type": "Feature",
  "properties": {
    "iso:country":"CH",
    "sg:address":"3814",
    "sg:city":"Gsteigwiler",
    "sg:classifiers":[
        {
            "category":"Travel",
            "subcategory":"Hotels & Motels",
            "type":"Entertainment"
        }
    ],
    "sg:phone":"+41 33 823 30 01",
    "sg:postcode":"3814",
    "sg:province":"Bern",
    "sg:tags":[
        "hotels",
        "mit",
        "restaurant"
    ],
    "wof:name":"Hotel Steinbock",
    "wof:placetype":"venue"
},
  "geometry": {"coordinates":[7.8730797768,46.6545562744],"type":"Point"}
}