{
  "type": "Feature",
  "properties": {
    "iso:country":"CH",
    "sg:address":"Postweg 1",
    "sg:city":"Kiesen",
    "sg:orig_category":"Antennenbau Detailhandel mit Radio U Fernsehger\u00e4ten",
    "sg:postcode":"3629",
    "sg:province":"Bern",
    "wof:name":"Mm Electronic M.macellaro",
    "wof:placetype":"venue"
},
  "geometry": {"coordinates":[7.582433,46.818985],"type":"Point"}
}