{
  "type": "Feature",
  "properties": {
    "iso:country":"CH",
    "sg:address":"Leinsiten 1",
    "sg:city":"Engi",
    "sg:orig_category":"Elektro- and elektronische Maschinen Grosshandel",
    "sg:postcode":"8765",
    "sg:province":"Glarus",
    "wof:name":"Hysteria-unterhaltungstechnik Coelestin Meier",
    "wof:placetype":"venue"
},
  "geometry": {"coordinates":[9.1546497345,46.9830780029],"type":"Point"}
}