{
  "type": "Feature",
  "properties": {
    "iso:country":"CH",
    "sg:address":"3032 Hinterkappelen. Postfach",
    "sg:city":"Hinterkappelen",
    "sg:orig_category":"Vereine Musik/Blasmusik",
    "sg:phone":"+41 33 341 11 44",
    "sg:postcode":"3032",
    "sg:province":"Bern",
    "wof:name":"Musikgesellschaft H\u00f6fen-stocken",
    "wof:placetype":"venue"
},
  "geometry": {"coordinates":[7.5717401505,46.7205696106],"type":"Point"}
}