{
  "type": "Feature",
  "properties": {
    "iso:country":"CH",
    "sg:address":"Via Degli Albrizzi 3",
    "sg:city":"Lugano",
    "sg:orig_category":"Dienstleistungen von Beteiligungsgesellschaften",
    "sg:postcode":"6900",
    "sg:province":"Ticino",
    "wof:name":"Rosengarten Sa",
    "wof:placetype":"venue"
},
  "geometry": {"coordinates":[8.9531297684,46.0040893555],"type":"Point"}
}