{
  "type": "Feature",
  "properties": {
    "iso:country":"CH",
    "sg:address":"Rotackerstrasse 34 8304 Wallisellen. Postfach",
    "sg:city":"Wallisellen",
    "sg:orig_category":"Fachdetailhandel in Verkaufsr\u00e4umen",
    "sg:phone":"+41 18302215",
    "sg:postcode":"8304",
    "sg:province":"Z\u00fcrich",
    "wof:name":"Fries Hans-rudolf, Rico-fahrradwerk.",
    "wof:placetype":"venue"
},
  "geometry": {"coordinates":[8.5926065445,47.4142608643],"type":"Point"}
}