{
  "type": "Feature",
  "properties": {
    "iso:country":"CH",
    "sg:address":"D\u00fcrren\u00e4scherstrasse 129",
    "sg:city":"Hallwil",
    "sg:orig_category":"Grosshandel mit B\u00fcromaschinen Grosshandel mit Datenverarbeitungsger\u00e4ten",
    "sg:phone":"+41 61 963 14 14",
    "sg:postcode":"5705",
    "sg:province":"Aargau",
    "wof:name":"Ltec Ag Soft-& Hardware",
    "wof:placetype":"venue"
},
  "geometry": {"coordinates":[7.7491970062,47.3952293396],"type":"Point"}
}