{
  "type": "Feature",
  "properties": {
    "iso:country":"CH",
    "sg:address":"Bernstrasse 1",
    "sg:city":"Thun",
    "sg:orig_category":"Detailhandel mit Ton U Bildtr\u00e4gern Detailhandel mit elektrischen Haushalts-,Radio U Fernsehger\u00e4ten s",
    "sg:phone":"+41 33 222 39 49",
    "sg:postcode":"3600",
    "sg:province":"Bern",
    "wof:name":"Nonstop Music, Kopp Boris",
    "wof:placetype":"venue"
},
  "geometry": {"coordinates":[7.6285629272,46.7620391846],"type":"Point"}
}