{
  "type": "Feature",
  "properties": {
    "iso:country":"CH",
    "sg:address":"Wiesenstrasse 28a",
    "sg:city":"Baden",
    "sg:orig_category":"Architekturb\u00fcros",
    "sg:phone":"+41 71 245 40 55",
    "sg:postcode":"5400",
    "sg:province":"Aargau",
    "wof:name":"Max Stirnemann Architekturb\u00fcro",
    "wof:placetype":"venue"
},
  "geometry": {"coordinates":[9.391315,47.430595],"type":"Point"}
}