{
  "type": "Feature",
  "properties": {
    "iso:country":"CH",
    "sg:address":"Zona Industriale 20",
    "sg:city":"Biasca",
    "sg:orig_category":"Herstellung von Rohren aus Gusseisen Mechanische Werkst\u00e4tten",
    "sg:phone":"+41 91 862 41 87",
    "sg:postcode":"6710",
    "sg:province":"Ticino",
    "wof:name":"Intervalves Sa",
    "wof:placetype":"venue"
},
  "geometry": {"coordinates":[8.9719829559,46.3435173035],"type":"Point"}
}