{
  "type": "Feature",
  "properties": {
    "iso:country":"CH",
    "sg:address":"Via Borghese 20",
    "sg:city":"Locarno",
    "sg:orig_category":"Erbringung von Dienstleistungen f\u00fcr Unternehmen Offsetdruck",
    "sg:phone":"+41 91 751 60 33",
    "sg:postcode":"6600",
    "sg:province":"Ticino",
    "wof:name":"De Marchi Grafiche",
    "wof:placetype":"venue"
},
  "geometry": {"coordinates":[8.7927951813,46.170211792],"type":"Point"}
}