{
  "type": "Feature",
  "properties": {
    "iso:country":"CH",
    "sg:address":"Via Baroffio 2",
    "sg:city":"Lugano",
    "sg:orig_category":"Kinderkrippen U horte",
    "sg:phone":"+41 91 921 32 82",
    "sg:postcode":"6900",
    "sg:province":"Ticino",
    "wof:name":"Nido D'infanzia",
    "wof:placetype":"venue"
},
  "geometry": {"coordinates":[8.9475240707,46.0062141418],"type":"Point"}
}