{
  "type": "Feature",
  "properties": {
    "iso:country":"CH",
    "sg:address":"Milit\u00e4rstrasse 12",
    "sg:city":"Schattdorf",
    "sg:orig_category":"Sportvereine Billard",
    "sg:phone":"+41 41 871 30 85",
    "sg:postcode":"6467",
    "sg:province":"Uri",
    "wof:name":"Billard Club Uri",
    "wof:placetype":"venue"
},
  "geometry": {"coordinates":[8.6423149109,46.8581008911],"type":"Point"}
}