{
  "type": "Feature",
  "properties": {
    "iso:country":"CH",
    "sg:address":"Via Da Mez 26",
    "sg:city":"Poschiavo",
    "sg:orig_category":"Innendekorationsateliers",
    "sg:phone":"+41 56 281 18 10",
    "sg:postcode":"7742",
    "sg:province":"Graubunden",
    "wof:name":"Andrea Graf Vorhangatelier",
    "wof:placetype":"venue"
},
  "geometry": {"coordinates":[8.2424240112,47.5196914673],"type":"Point"}
}