{
  "type": "Feature",
  "properties": {
    "addr:full":"Dahliastrasse 4 8008 Z\u00fcrich. Postfach Z\u00fcrich Z\u00fcrich 8034",
    "addr:housenumber":"4",
    "addr:postcode":"8008 zuerich. postfach;8034",
    "addr:street":"Dahliastrasse",
    "iso:country":"CH",
    "sg:address":"Dahliastrasse 4 8008 Z\u00fcrich. Postfach",
    "sg:city":"Z\u00fcrich",
    "sg:orig_category":"Architektur U Ingenieurb\u00fcros Architekturb\u00fcros",
    "sg:phone":"+41 21 944 12 12",
    "sg:postcode":"8034",
    "sg:province":"Z\u00fcrich",
    "wof:name":"Desponds Daniel Ger Groupe D'\u00e9tude Et De R\u00e9alisation Sa",
    "wof:placetype":"venue"
},
  "geometry": {"coordinates":[6.856727,46.452927],"type":"Point"}
}