{
  "type": "Feature",
  "properties": {
    "iso:country":"CH",
    "sg:address":"Rosenweg 3007 Bern. Postfach",
    "sg:city":"Bern",
    "sg:orig_category":"Kauf U Verkauf von Immobilien auf eigene Rechnung",
    "sg:postcode":"3005",
    "sg:province":"Bern",
    "wof:name":"Albawo Ag Liegenschaften Usw",
    "wof:placetype":"venue"
},
  "geometry": {"coordinates":[7.4349250793,46.9372062683],"type":"Point"}
}