{
  "type": "Feature",
  "properties": {
    "iso:country":"CH",
    "sg:address":"Im Leeacher 30",
    "sg:city":"Hinteregg",
    "sg:orig_category":"Sonstige pers\u00f6nliche Dienstleistungen",
    "sg:postcode":"8132",
    "sg:province":"Z\u00fcrich",
    "wof:name":"Thailine, R. M\u00fcller",
    "wof:placetype":"venue"
},
  "geometry": {"coordinates":[8.6817483902,47.3065223694],"type":"Point"}
}