{
  "type": "Feature",
  "properties": {
    "iso:country":"CH",
    "sg:address":"M\u00fchlebachstrasse 36",
    "sg:city":"Thalwil",
    "sg:classifiers":[
        {
            "category":"Restaurant",
            "type":"Food & Drink"
        }
    ],
    "sg:phone":"+41 34 445 59 79",
    "sg:postcode":"8800",
    "sg:province":"Z\u00fcrich",
    "wof:name":"Trattoria Giardino",
    "wof:placetype":"venue"
},
  "geometry": {"coordinates":[7.5841999054,47.0856933594],"type":"Point"}
}