{
  "type": "Feature",
  "properties": {
    "iso:country":"CH",
    "sg:address":"M\u00fchlh\u00e4usern 2",
    "sg:city":"N\u00e4fels",
    "sg:orig_category":"Druck ohne Zeitungsdruck Offsetdruck",
    "sg:postcode":"8752",
    "sg:province":"Glarus",
    "wof:name":"R + A Print Gmbh",
    "wof:placetype":"venue"
},
  "geometry": {"coordinates":[9.0689897537,47.1001281738],"type":"Point"}
}