{
  "type": "Feature",
  "properties": {
    "iso:country":"CH",
    "sg:address":"Lettenstrasse 8",
    "sg:city":"Rotkreuz",
    "sg:orig_category":"HERSTELLUNG VON GER\u00c4TEN DER ELEKTRIZIT\u00c4TSERZEUGUNG, -VERTEILUNG U.\u00c4 Herstellung von Werkzeugmaschine",
    "sg:phone":"+41 81 756 40 58",
    "sg:postcode":"6343",
    "sg:province":"Zug",
    "wof:name":"Rossell Elektronik Ag",
    "wof:placetype":"venue"
},
  "geometry": {"coordinates":[9.4739122391,47.1663551331],"type":"Point"}
}