{
  "type": "Feature",
  "properties": {
    "addr:full":"Waldeckstrasse 30 Ostermundigen Bern 3072",
    "addr:housenumber":"30",
    "addr:postcode":"3072",
    "addr:street":"Waldeckstrasse",
    "iso:country":"CH",
    "sg:address":"Waldeckstrasse 30",
    "sg:city":"Ostermundigen",
    "sg:orig_category":"Detailhandel mit Brot, Back U S\u00fcsswaren",
    "sg:phone":"+41 31 931 16 04",
    "sg:postcode":"3072",
    "sg:province":"Bern",
    "wof:name":"Alois Immoos B\u00e4ckerei-konditorei",
    "wof:placetype":"venue"
},
  "geometry": {"coordinates":[7.479574,46.955185],"type":"Point"}
}