{
  "type": "Feature",
  "properties": {
    "iso:country":"CH",
    "sg:address":"1041",
    "sg:city":"Bottens",
    "sg:orig_category":"Vorschulen, Kinderg\u00e4rten",
    "sg:phone":"+41 21 881 47 87",
    "sg:postcode":"1041",
    "sg:province":"Vaud",
    "wof:name":"Ecole Enfantine",
    "wof:placetype":"venue"
},
  "geometry": {"coordinates":[6.6604199409,46.6171188354],"type":"Point"}
}