{
  "type": "Feature",
  "properties": {
    "iso:country":"CH",
    "sg:address":"Meylan Rue P\u00e9dro- 7 1208 Gen\u00e8ve. Postfach",
    "sg:city":"Gen\u00e8ve",
    "sg:orig_category":"Pensionskassen",
    "sg:phone":"+41 22 718 98 00",
    "sg:postcode":"1208",
    "sg:province":"Gen\u00e8ve",
    "wof:name":"Fondation De Pr\u00e9voyance Et De Retraite En Faveur Du Personnel De L'ofac",
    "wof:placetype":"venue"
},
  "geometry": {"coordinates":[6.1640701294,46.1952209473],"type":"Point"}
}