{
  "type": "Feature",
  "properties": {
    "addr:full":"Blegistrasse 1 Rotkreuz Zug 6343",
    "addr:housenumber":"1",
    "addr:postcode":"6343",
    "addr:street":"Blegistrasse;Zug",
    "iso:country":"CH",
    "sg:address":"Blegistrasse 1",
    "sg:city":"Rotkreuz",
    "sg:orig_category":"Allgemeiner Hoch U Tiefbau ohne ausgepr\u00e4gten Schwerpunkt Unterhalt U Reparatur im Hoch U Tiefbau",
    "sg:phone":"+41 41 790 04 38",
    "sg:postcode":"6343",
    "sg:province":"Zug",
    "wof:name":"Ebs Bauservice Gmbh",
    "wof:placetype":"venue"
},
  "geometry": {"coordinates":[8.436128,47.14819],"type":"Point"}
}