{
  "type": "Feature",
  "properties": {
    "iso:country":"CH",
    "sg:address":"Funtanatscha 117",
    "sg:city":"Scuol",
    "sg:orig_category":"Sportvereine Eissport Eishockey",
    "sg:phone":"+41 81 864 80 56",
    "sg:postcode":"7550",
    "sg:province":"Graubunden",
    "wof:name":"Eishockey-club Sent",
    "wof:placetype":"venue"
},
  "geometry": {"coordinates":[10.2973098755,46.7956809998],"type":"Point"}
}