{
  "type": "Feature",
  "properties": {
    "iso:country":"CH",
    "sg:address":"Altelsweg 14",
    "sg:city":"Uetendorf",
    "sg:orig_category":"Zimmerei, Dachdeckerei, Bauspenglerei U Abdichtung Zimmerei, Ingenieurholzbau",
    "sg:phone":"+41 33 345 35 43",
    "sg:postcode":"3661",
    "sg:province":"Bern",
    "wof:name":"Waber & Stalder Holzbau",
    "wof:placetype":"venue"
},
  "geometry": {"coordinates":[7.591960907,46.7793769836],"type":"Point"}
}