{
  "type": "Feature",
  "properties": {
    "iso:country":"CH",
    "sg:address":"Steimertenmattweg 13",
    "sg:city":"Lupsingen",
    "sg:orig_category":"Handelsvermittlung U Grosshandel Sonstiger Grosshandel",
    "sg:phone":"+41 22 347 36 26",
    "sg:postcode":"4419",
    "sg:province":"Basel-Landschaft",
    "wof:name":"Glavir Sa",
    "wof:placetype":"venue"
},
  "geometry": {"coordinates":[6.1529989243,46.1954040527],"type":"Point"}
}