{
  "type": "Feature",
  "properties": {
    "iso:country":"CH",
    "sg:address":"Rue Du March\u00e9 40",
    "sg:city":"Gen\u00e8ve",
    "sg:orig_category":"Unclassifiable Establishments",
    "sg:phone":"+41 62 797 22 66",
    "sg:postcode":"1204",
    "sg:province":"Gen\u00e8ve",
    "wof:name":"Banner Batterien (schweiz) Ag",
    "wof:placetype":"venue"
},
  "geometry": {"coordinates":[8.3134536743,46.9878044128],"type":"Point"}
}