{
  "type": "Feature",
  "properties": {
    "iso:country":"CH",
    "sg:address":"Leonhardsstrasse 14",
    "sg:city":"Basel",
    "sg:orig_category":"Bauspenglerei Sanit\u00e4rinstallation",
    "sg:phone":"+41 17881026",
    "sg:postcode":"4051",
    "sg:province":"Basel-Stadt",
    "wof:name":"Hansueli Wagner",
    "wof:placetype":"venue"
},
  "geometry": {"coordinates":[8.635041,47.202759],"type":"Point"}
}