{
  "type": "Feature",
  "properties": {
    "iso:country":"CH",
    "sg:address":"Flurstrasse 93",
    "sg:city":"Z\u00fcrich",
    "sg:orig_category":"Fachdetailhandel in Verkaufsr\u00e4umen",
    "sg:phone":"+41 14013330",
    "sg:postcode":"8047",
    "sg:province":"Z\u00fcrich",
    "wof:name":"Meier Movie Werbung",
    "wof:placetype":"venue"
},
  "geometry": {"coordinates":[8.4920873642,47.3814659119],"type":"Point"}
}