{
  "type": "Feature",
  "properties": {
    "iso:country":"CH",
    "sg:address":"Hardplatz 5",
    "sg:city":"Z\u00fcrich",
    "sg:orig_category":"Unclassifiable Establishments",
    "sg:postcode":"8004",
    "sg:province":"Z\u00fcrich",
    "wof:name":"Audio3000 Figner",
    "wof:placetype":"venue"
},
  "geometry": {"coordinates":[8.5148181915,47.3820381165],"type":"Point"}
}