{
  "type": "Feature",
  "properties": {
    "addr:full":"Vogelsang 73 Biel/bienne Bern 2502",
    "addr:housenumber":"73",
    "addr:postcode":"2502",
    "addr:street":"Vogelsang",
    "iso:country":"CH",
    "sg:address":"Vogelsang 73",
    "sg:city":"Biel/bienne",
    "sg:orig_category":"Architektur U Ingenieurb\u00fcros",
    "sg:phone":"+41 32 322 64 62",
    "sg:postcode":"2502",
    "sg:province":"Bern",
    "wof:name":"Aarsys Ag",
    "wof:placetype":"venue"
},
  "geometry": {"coordinates":[7.242247,47.1451],"type":"Point"}
}