{
  "type": "Feature",
  "properties": {
    "iso:country":"CH",
    "sg:address":"Tscharnerstrasse 10",
    "sg:city":"Bern",
    "sg:orig_category":"Institutionen f\u00fcr Behinderte Sonderschulen",
    "sg:phone":"+41 31 371 20 48",
    "sg:postcode":"3007",
    "sg:province":"Bern",
    "wof:name":"Heilp\u00e4dagogische Sonderschule Der Stadt Bern",
    "wof:placetype":"venue"
},
  "geometry": {"coordinates":[7.4293727875,46.9412727356],"type":"Point"}
}