{
  "type": "Feature",
  "properties": {
    "iso:country":"CH",
    "sg:address":"Breitenbachstrasse",
    "sg:city":"B\u00fcsserach",
    "sg:orig_category":"Vorschulen, Kinderg\u00e4rten",
    "sg:phone":"+41 61 781 14 48",
    "sg:postcode":"4227",
    "sg:province":"Solothurn",
    "wof:name":"Kindergarten",
    "wof:placetype":"venue"
},
  "geometry": {"coordinates":[7.541079998,47.3946609497],"type":"Point"}
}