{
  "type": "Feature",
  "properties": {
    "iso:country":"CH",
    "sg:address":"Weiningerstrasse 48",
    "sg:city":"Unterengstringen",
    "sg:orig_category":"Unternehmensberatung",
    "sg:phone":"+41 62 961 37 06",
    "sg:postcode":"8103",
    "sg:province":"Z\u00fcrich",
    "wof:name":"Wirtschafts Und Finanzberatung Biberstein Annedore",
    "wof:placetype":"venue"
},
  "geometry": {"coordinates":[7.6712012291,47.1730804443],"type":"Point"}
}