{
  "type": "Feature",
  "properties": {
    "iso:country":"CH",
    "sg:address":"Bielstrasse 15",
    "sg:city":"Solothurn",
    "sg:orig_category":"Zahnarztpraxen",
    "sg:phone":"+41 32 622 14 93",
    "sg:postcode":"4500",
    "sg:province":"Solothurn",
    "wof:name":"Dres Thomann & Peter Thomann Zahn\u00e4rzte",
    "wof:placetype":"venue"
},
  "geometry": {"coordinates":[7.5322198868,47.2088661194],"type":"Point"}
}