{
  "type": "Feature",
  "properties": {
    "iso:country":"CH",
    "sg:address":"B\u00fctzbergstrasse 17",
    "sg:city":"Aarwangen",
    "sg:orig_category":"Allgemeiner Hoch U Tiefbau",
    "sg:phone":"+41 62 922 55 02",
    "sg:postcode":"4912",
    "sg:province":"Bern",
    "wof:name":"Beat W\u00e4lchli Festwirtschaften Ag",
    "wof:placetype":"venue"
},
  "geometry": {"coordinates":[7.77248,47.233086],"type":"Point"}
}