{
  "type": "Feature",
  "properties": {
    "iso:country":"CH",
    "sg:address":"Riedmatthof 6372 Ennetmoos. Postfach",
    "sg:city":"Ennetmoos",
    "sg:classifiers":[
        {
            "category":"Mining & Drilling",
            "type":"Manufacturing & Wholesale Goods"
        }
    ],
    "sg:postcode":"6372",
    "sg:province":"Nidwalden",
    "sg:tags":[
        "test",
        "sondierbohrungen",
        "u"
    ],
    "wof:name":"Betatherm, Haas Johann",
    "wof:placetype":"venue"
},
  "geometry": {"coordinates":[8.332159996,46.9535942078],"type":"Point"}
}