{
  "type": "Feature",
  "properties": {
    "iso:country":"CH",
    "sg:address":"Pension Sciora",
    "sg:city":"Promontogno",
    "sg:classifiers":[
        {
            "category":"Travel",
            "subcategory":"Hotels & Motels",
            "type":"Entertainment"
        }
    ],
    "sg:postcode":"7606",
    "sg:province":"Graubunden",
    "sg:tags":[
        "hotels",
        "mit",
        "restaurant"
    ],
    "wof:name":"Pension Sciora, Maraffio Capadrutt Valeria",
    "wof:placetype":"venue"
},
  "geometry": {"coordinates":[9.5540342331,46.3356285095],"type":"Point"}
}