{
  "type": "Feature",
  "properties": {
    "iso:country":"CH",
    "sg:address":"Wilerstrasse 46 9602 Bazenheid. Postfach 120",
    "sg:city":"Bazenheid",
    "sg:orig_category":"Fleischverarbeitung Verarbeitung U Konservierung von Obst U Gem\u00fcse",
    "sg:phone":"+41 71 931 47 92",
    "sg:postcode":"9602",
    "sg:province":"St. Gallen",
    "wof:name":"Micarna Sa",
    "wof:placetype":"venue"
},
  "geometry": {"coordinates":[9.0675325394,47.4158439636],"type":"Point"}
}