{
  "type": "Feature",
  "properties": {
    "iso:country":"CH",
    "sg:address":"L\u00e4gernweg 516 8185 Winkel. Postfach 7",
    "sg:city":"Winkel",
    "sg:orig_category":"Grosshandel mit sonstigen Maschinen U Ausr\u00fcstungen f\u00fcr Industrie, Handel U Schiffahrt",
    "sg:postcode":"8185",
    "sg:province":"Z\u00fcrich",
    "wof:name":"M-center Malters Ranasinghe",
    "wof:placetype":"venue"
},
  "geometry": {"coordinates":[8.1827249527,47.0368156433],"type":"Point"}
}