{
  "type": "Feature",
  "properties": {
    "iso:country":"CH",
    "sg:address":"Bahnhofstrasse 30",
    "sg:city":"Horgen",
    "sg:orig_category":"Handel mit Motorr\u00e4dern, Teilen U Zubeh\u00f6r Instandhaltung U Reparatur von Motorr\u00e4dern",
    "sg:phone":"+41 56 282 14 40",
    "sg:postcode":"8810",
    "sg:province":"Z\u00fcrich",
    "wof:name":"Velo Meier Ag",
    "wof:placetype":"venue"
},
  "geometry": {"coordinates":[8.2879333496,47.4889144897],"type":"Point"}
}