{
  "type": "Feature",
  "properties": {
    "iso:country":"CH",
    "sg:address":"R\u00e9sid.la B\u00e2tiaz",
    "sg:city":"Verbier",
    "sg:orig_category":"Sportvereine Ski",
    "sg:phone":"+41 27 207 16 66",
    "sg:postcode":"1936",
    "sg:province":"Valais",
    "wof:name":"Ski-club Veysonnaz",
    "wof:placetype":"venue"
},
  "geometry": {"coordinates":[7.3358249664,46.1855392456],"type":"Point"}
}