{
  "type": "Feature",
  "properties": {
    "iso:country":"CH",
    "sg:address":"Karstlernstrasse 14",
    "sg:city":"Z\u00fcrich",
    "sg:classifiers":[
        {
            "category":"Communications",
            "subcategory":"Film & Video Production",
            "type":"Services"
        }
    ],
    "sg:phone":"+41 14329414",
    "sg:postcode":"8048",
    "sg:province":"Z\u00fcrich",
    "sg:tags":[
        "videofilmherstellung",
        "u"
    ],
    "wof:name":"Liniger Videoproduktion",
    "wof:placetype":"venue"
},
  "geometry": {"coordinates":[8.4783010483,47.3898391724],"type":"Point"}
}