{
  "type": "Feature",
  "properties": {
    "iso:country":"CH",
    "sg:address":"Z\u00fcrichstrasse 38",
    "sg:city":"Br\u00fcttisellen",
    "sg:orig_category":"Bauschreinerei",
    "sg:phone":"+41 18330034",
    "sg:postcode":"8306",
    "sg:province":"Z\u00fcrich",
    "wof:name":"Burkart Ag Trilgeno",
    "wof:placetype":"venue"
},
  "geometry": {"coordinates":[8.628574,47.422379],"type":"Point"}
}