{
  "type": "Feature",
  "properties": {
    "iso:country":"CH",
    "sg:address":"Grendelstrasse 9",
    "sg:city":"Ennetbaden",
    "sg:orig_category":"Wasserversorgung",
    "sg:phone":"+41 56 222 46 64",
    "sg:postcode":"5408",
    "sg:province":"Aargau",
    "wof:name":"Wasserversorgung Der Gemeinde Ennetbaden",
    "wof:placetype":"venue"
},
  "geometry": {"coordinates":[8.3148393631,47.478263855],"type":"Point"}
}