{
  "type": "Feature",
  "properties": {
    "iso:country":"CH",
    "sg:address":"Kapuzinerstr. 32 Glis",
    "sg:city":"Brig",
    "sg:orig_category":"Non-Classified Establishments",
    "sg:postcode":"3900",
    "sg:province":"Valais",
    "wof:name":"Landext Marty Marco & Co",
    "wof:placetype":"venue"
},
  "geometry": {"coordinates":[7.9876461029,46.3158912659],"type":"Point"}
}