{
  "type": "Feature",
  "properties": {
    "iso:country":"CH",
    "sg:address":"Sonnenbergstrasse",
    "sg:city":"Niederglatt",
    "sg:classifiers":[
        {
            "category":"Banks & Credit Unions",
            "subcategory":"Bank",
            "type":"Services"
        }
    ],
    "sg:phone":"+41 1852994",
    "sg:postcode":"8172",
    "sg:province":"Z\u00fcrich",
    "wof:name":"Bezirkssparkasse Dielsdorf",
    "wof:placetype":"venue"
},
  "geometry": {"coordinates":[8.502723,47.490372],"type":"Point"}
}