{
  "type": "Feature",
  "properties": {
    "iso:country":"CH",
    "sg:address":"6300",
    "sg:city":"Zug",
    "sg:orig_category":"Unternehmensberatung",
    "sg:phone":"+41 41 725 27 27",
    "sg:postcode":"6300",
    "sg:province":"Zug",
    "wof:name":"Magna Management (hungary) Limited Liability Company, Nagymaros, Ungarn, Zweigniederlassung Zug",
    "wof:placetype":"venue"
},
  "geometry": {"coordinates":[8.5168199539,47.1568984985],"type":"Point"}
}