{
  "type": "Feature",
  "properties": {
    "iso:country":"CH",
    "sg:address":"Strengelbacherstrasse 41 4800 Zofingen. Postfach",
    "sg:city":"Zofingen",
    "sg:orig_category":"Vermittlung von Immobilien Verwaltung von Immobilien",
    "sg:postcode":"4800",
    "sg:province":"Aargau",
    "wof:name":"Miro Porlezza Ag",
    "wof:placetype":"venue"
},
  "geometry": {"coordinates":[7.9365911484,47.2821083069],"type":"Point"}
}