{
  "type": "Feature",
  "properties": {
    "addr:full":"Bronschhoferstrasse 69 Wil St. Gallen 9500",
    "addr:housenumber":"69;st.",
    "addr:postcode":"9500",
    "addr:street":"Bronschhoferstrasse;Wil",
    "iso:country":"CH",
    "sg:address":"Bronschhoferstrasse 69",
    "sg:city":"Wil",
    "sg:orig_category":"Anticorrosives",
    "sg:phone":"+41 71 910 08 44",
    "sg:postcode":"9500",
    "sg:province":"St. Gallen",
    "wof:name":"L\u00fcber System Gmbh",
    "wof:placetype":"venue"
},
  "geometry": {"coordinates":[9.039605,47.471188],"type":"Point"}
}