{
  "type": "Feature",
  "properties": {
    "addr:full":"Mittelg\u00e4ustrasse 126 Wangen Solothurn 4612",
    "addr:housenumber":"126",
    "addr:postcode":"4612",
    "addr:street":"Mittelgaeustrasse",
    "iso:country":"CH",
    "sg:address":"Mittelg\u00e4ustrasse 126",
    "sg:city":"Wangen",
    "sg:classifiers":[
        {
            "category":"Banks & Credit Unions",
            "subcategory":"Bank",
            "type":"Services"
        }
    ],
    "sg:phone":"+41 4162325317",
    "sg:postcode":"4612",
    "sg:province":"Solothurn",
    "wof:name":"Schweiz. Mobiliar",
    "wof:placetype":"venue"
},
  "geometry": {"coordinates":[7.865837,47.336403],"type":"Point"}
}