{
  "type": "Feature",
  "properties": {
    "iso:country":"CH",
    "sg:address":"Belv\u00e9d\u00e8restrasse 27b",
    "sg:city":"Zufikon",
    "sg:orig_category":"Politische Parteien CVP",
    "sg:phone":"+41 56 222 97 97",
    "sg:postcode":"5621",
    "sg:province":"Aargau",
    "wof:name":"Cvp Ortspartei Mutschellen",
    "wof:placetype":"venue"
},
  "geometry": {"coordinates":[8.3566112518,47.3545799255],"type":"Point"}
}