{
  "type": "Feature",
  "properties": {
    "iso:country":"CH",
    "sg:address":"3605",
    "sg:city":"Thun",
    "sg:orig_category":"Unclassifiable Establishments",
    "sg:postcode":"3605",
    "wof:name":"Aaeg Associated Architect's Engineer's Group, Inhaber P. Zala",
    "wof:placetype":"venue"
},
  "geometry": {"coordinates":[7.6233401299,46.7525787354],"type":"Point"}
}