{
  "type": "Feature",
  "properties": {
    "iso:country":"CH",
    "sg:address":"Dornacherstrasse 20",
    "sg:city":"Solothurn",
    "sg:orig_category":"Instandhaltung U Reparatur von Automobilen",
    "sg:phone":"+41 32 622 13 60",
    "sg:postcode":"4500",
    "sg:province":"Solothurn",
    "wof:name":"Hafner + Co.",
    "wof:placetype":"venue"
},
  "geometry": {"coordinates":[7.5396380424,47.204158783],"type":"Point"}
}