{
  "type": "Feature",
  "properties": {
    "iso:country":"CH",
    "sg:address":"Sauverny Route De 6",
    "sg:city":"Versoix",
    "sg:orig_category":"Erschliessung von Grundst\u00fccken",
    "sg:postcode":"1290",
    "sg:province":"Gen\u00e8ve",
    "wof:name":"Soci\u00e9t\u00e9 Coop\u00e9rative Val De Travers - Versoix",
    "wof:placetype":"venue"
},
  "geometry": {"coordinates":[6.1648240089,46.2838439941],"type":"Point"}
}