{
  "type": "Feature",
  "properties": {
    "iso:country":"CH",
    "sg:address":"Rue Saint-germain 11",
    "sg:city":"Bussigny-lausanne",
    "sg:orig_category":"Detailhandel mit Brot, Back U S\u00fcsswaren",
    "sg:phone":"+41 21 701 31 01",
    "sg:postcode":"1030",
    "sg:province":"Vaud",
    "wof:name":"Follain Michel",
    "wof:placetype":"venue"
},
  "geometry": {"coordinates":[6.549663,46.550323],"type":"Point"}
}