{
  "type": "Feature",
  "properties": {
    "addr:full":"Route De Ch\u00e2tillon 71 Posieux Fribourg 1725",
    "addr:housenumber":"71",
    "addr:postcode":"1725",
    "addr:street":"Route De Cha\u0302Tillon",
    "iso:country":"CH",
    "sg:address":"Route De Ch\u00e2tillon 71",
    "sg:city":"Posieux",
    "sg:orig_category":"Abfallbeseitigung Herstellung von sonstigen Maschinen f\u00fcr bestimmte Verwendung",
    "sg:phone":"+41 26 400 04 50",
    "sg:postcode":"1725",
    "sg:province":"Fribourg",
    "wof:name":"Saidef",
    "wof:placetype":"venue"
},
  "geometry": {"coordinates":[7.095301,46.760601],"type":"Point"}
}