{
  "type": "Feature",
  "properties": {
    "addr:full":"Utengasse 36 4058 Basel. Postfach Basel Basel-Stadt 4005",
    "addr:housenumber":"36",
    "addr:postcode":"4058;4005",
    "addr:street":"Utengasse;Postfach",
    "iso:country":"CH",
    "sg:address":"Utengasse 36 4058 Basel. Postfach",
    "sg:city":"Basel",
    "sg:orig_category":"Arbeits\u00e4mter",
    "sg:phone":"+41 61 267 81 81",
    "sg:postcode":"4005",
    "sg:province":"Basel-Stadt",
    "wof:name":"Kantonales Arbeitsamt",
    "wof:placetype":"venue"
},
  "geometry": {"coordinates":[7.593236,47.559788],"type":"Point"}
}