{
  "type": "Feature",
  "properties": {
    "iso:country":"CH",
    "sg:address":"Landstrasse 65",
    "sg:city":"Rafz",
    "sg:orig_category":"Hobel U Holzimpr\u00e4gnierwerke Sonstige k\u00fcnstlerische U schriftstellerische T\u00e4tigkeiten U Darbietungen",
    "sg:phone":"+41 18690800",
    "sg:postcode":"8197",
    "sg:province":"Z\u00fcrich",
    "wof:name":"Heinz B\u00fcchi Drechslerei & Kunstgewerbe",
    "wof:placetype":"venue"
},
  "geometry": {"coordinates":[8.5496768951,47.6146659851],"type":"Point"}
}