{
  "type": "Feature",
  "properties": {
    "iso:country":"CH",
    "sg:address":"Bahnhofplatz",
    "sg:city":"Hasle-r\u00fcegsau",
    "sg:orig_category":"Gemeindeverwaltungen",
    "sg:phone":"+41 55 644 30 39",
    "sg:postcode":"3415",
    "sg:province":"Bern",
    "wof:name":"Gemeindeverwaltung Haslen",
    "wof:placetype":"venue"
},
  "geometry": {"coordinates":[9.0576295853,46.9820785522],"type":"Point"}
}