{
  "type": "Feature",
  "properties": {
    "iso:country":"CH",
    "sg:address":"Alpenstrasse 3",
    "sg:city":"Hombrechtikon",
    "sg:orig_category":"Sanit\u00e4rinstallation",
    "sg:phone":"+41 55 244 30 15",
    "sg:postcode":"8634",
    "sg:province":"Z\u00fcrich",
    "wof:name":"Roland Reuteler Sanit\u00e4r-installationen",
    "wof:placetype":"venue"
},
  "geometry": {"coordinates":[8.7728624344,47.2475852966],"type":"Point"}
}