{
  "type": "Feature",
  "properties": {
    "iso:country":"CH",
    "sg:address":"Quellenrain 47",
    "sg:city":"Ittigen",
    "sg:orig_category":"Softwareentwicklung U beratung",
    "sg:postcode":"3063",
    "sg:province":"Bern",
    "wof:name":"Visoft Ag",
    "wof:placetype":"venue"
},
  "geometry": {"coordinates":[7.482817173,46.9808502197],"type":"Point"}
}