{
  "type": "Feature",
  "properties": {
    "iso:country":"CH",
    "sg:address":"Le Carroz",
    "sg:city":"Villars-sous-yens",
    "sg:orig_category":"Instandhaltung U Reparatur von Automobilen",
    "sg:phone":"+41 21 800 30 54",
    "sg:postcode":"1138",
    "wof:name":"Guibert Jean Daniel",
    "wof:placetype":"venue"
},
  "geometry": {"coordinates":[6.4296679497,46.5102958679],"type":"Point"}
}