{
  "type": "Feature",
  "properties": {
    "iso:country":"CH",
    "sg:address":"St. Urban-strasse 3",
    "sg:city":"Sursee",
    "sg:orig_category":"RESTAURANTS: TEA-ROOMS",
    "sg:phone":"+41 41 921 22 62",
    "sg:postcode":"6210",
    "sg:province":"Luzern",
    "wof:name":"Restaurant Bahnh\u00f6fli Kunz Sabina",
    "wof:placetype":"venue"
},
  "geometry": {"coordinates":[8.1075820923,47.1740493774],"type":"Point"}
}