{
  "type": "Feature",
  "properties": {
    "iso:country":"CH",
    "sg:address":"Bergellerstrasse 24",
    "sg:city":"Z\u00fcrich",
    "sg:orig_category":"Softwareentwicklung U beratung",
    "sg:phone":"+41 13422781",
    "sg:postcode":"8049",
    "sg:province":"Z\u00fcrich",
    "wof:name":"Iservices Marques",
    "wof:placetype":"venue"
},
  "geometry": {"coordinates":[8.4937391281,47.4061317444],"type":"Point"}
}