{
  "type": "Feature",
  "properties": {
    "iso:country":"CH",
    "sg:address":"Rue D'italie",
    "sg:city":"1204 Geneva",
    "sg:classifiers":[
        {
            "category":"Banks & Credit Unions",
            "subcategory":"Bank",
            "type":"Services"
        }
    ],
    "sg:phone":"+41 844 840 850",
    "sg:postcode":"6",
    "wof:name":"Bs Bank Schaffhausen",
    "wof:placetype":"venue"
},
  "geometry": {"coordinates":[8.458765,47.697426],"type":"Point"}
}