{
  "type": "Feature",
  "properties": {
    "iso:country":"CH",
    "sg:address":"Baslerstrasse 11 5330 Zurzach. Postfach 116",
    "sg:city":"Zurzach",
    "sg:orig_category":"Kauf U Verkauf von Immobilien auf eigene Rechnung",
    "sg:phone":"+41 56 250 62 70",
    "sg:postcode":"5330",
    "sg:province":"Aargau",
    "wof:name":"Ekz Zurzach Ag",
    "wof:placetype":"venue"
},
  "geometry": {"coordinates":[8.2916660309,47.5895195007],"type":"Point"}
}