{
  "type": "Feature",
  "properties": {
    "iso:country":"CH",
    "sg:address":"Besso Via 27",
    "sg:city":"Lugano",
    "sg:orig_category":"Vermietung U Verpachtung von eigenen Immobilien",
    "sg:postcode":"6900",
    "sg:province":"Ticino",
    "wof:name":"Agez Sa",
    "wof:placetype":"venue"
},
  "geometry": {"coordinates":[8.9405450821,46.0079994202],"type":"Point"}
}