{
  "type": "Feature",
  "properties": {
    "addr:full":"Cholgadenstrasse 5 Niederteufen Appenzell Ausserrhoden 9052",
    "addr:housenumber":"5",
    "addr:postcode":"9052",
    "addr:street":"Cholgadenstrasse;Ausserrhoden",
    "iso:country":"CH",
    "sg:address":"Cholgadenstrasse 5",
    "sg:city":"Niederteufen",
    "sg:orig_category":"Architekturb\u00fcros",
    "sg:phone":"+41 71 333 23 24",
    "sg:postcode":"9052",
    "sg:province":"Appenzell Ausserrhoden",
    "wof:name":"Niethammer & St\u00fcnzi Architekturb\u00fcro",
    "wof:placetype":"venue"
},
  "geometry": {"coordinates":[9.366431,47.394913],"type":"Point"}
}