{
  "type": "Feature",
  "properties": {
    "iso:country":"CH",
    "sg:address":"Grubenstrasse 7",
    "sg:city":"Sch\u00f6nb\u00fchl-urtenen",
    "sg:orig_category":"Vermietung U Verpachtung von eigenen Immobilien",
    "sg:phone":"+41 31 859 34 94",
    "sg:postcode":"3322",
    "sg:province":"Bern",
    "wof:name":"Emct Immobilien Sa",
    "wof:placetype":"venue"
},
  "geometry": {"coordinates":[7.5023989677,47.0196723938],"type":"Point"}
}