{
  "type": "Feature",
  "properties": {
    "iso:country":"CH",
    "sg:address":"Square Poste",
    "sg:city":"Verbier",
    "sg:orig_category":"Sonstiger Fachdetailhandel in Verkaufsr\u00e4umen",
    "sg:phone":"+41 27 771 54 64",
    "sg:postcode":"1936",
    "sg:province":"Valais",
    "wof:name":"Bruno & Anja Kadlubski Min\u00e9raux Pr Collections",
    "wof:placetype":"venue"
},
  "geometry": {"coordinates":[7.2247400284,46.0970802307],"type":"Point"}
}