{
  "type": "Feature",
  "properties": {
    "iso:country":"CH",
    "sg:address":"Versonnex Rue Fran\u00e7ois- 11 1207 Gen\u00e8ve. Postfach",
    "sg:city":"Gen\u00e8ve",
    "sg:orig_category":"Sonstiges Versicherungsgewerbe",
    "sg:phone":"+41 71 633 37 17",
    "sg:postcode":"1201",
    "sg:province":"Gen\u00e8ve",
    "wof:name":"Al - Ba 2000 Gmbh",
    "wof:placetype":"venue"
},
  "geometry": {"coordinates":[9.1590003967,47.5440635681],"type":"Point"}
}