{
  "type": "Feature",
  "properties": {
    "iso:country":"CH",
    "sg:address":"Thunstrasse 111",
    "sg:city":"Bern",
    "sg:orig_category":"Herstellung von Konstruktionsteilen, Fertigbauteilen U Ausbauelementen aus Holz",
    "sg:postcode":"3006",
    "sg:province":"Bern",
    "wof:name":"F Plus Gmbh",
    "wof:placetype":"venue"
},
  "geometry": {"coordinates":[7.4654588699,46.9417114258],"type":"Point"}
}