{
  "type": "Feature",
  "properties": {
    "iso:country":"CH",
    "sg:address":"Weihermattstrasse 1",
    "sg:city":"Niedererlinsbach",
    "sg:orig_category":"Erschliessung von Grundst\u00fccken",
    "sg:postcode":"5015",
    "sg:province":"Solothurn",
    "wof:name":"Gen.alterswohnen Erlinsbach C/o P.pauk Treuhand",
    "wof:placetype":"venue"
},
  "geometry": {"coordinates":[8.0026817322,47.3941802979],"type":"Point"}
}