{
  "type": "Feature",
  "properties": {
    "iso:country":"CH",
    "sg:address":"Via Delta 11 6612 Ascona Casella Postale 405",
    "sg:city":"Ascona",
    "sg:orig_category":"Instandhaltung U Reparatur von Automobilen Tankstellen",
    "sg:phone":"+41 91 791 43 24",
    "sg:postcode":"6612",
    "sg:province":"Ticino",
    "wof:name":"Bertoni Automobili Sa",
    "wof:placetype":"venue"
},
  "geometry": {"coordinates":[8.7698612213,46.1564369202],"type":"Point"}
}