{
  "type": "Feature",
  "properties": {
    "iso:country":"CH",
    "sg:address":"Unterm\u00fcli 9 6300 Zug. Postfach 2729",
    "sg:city":"Zug",
    "sg:orig_category":"Grosshandel mit chemischen Erzeugnissen Grosshandel mit pharmazeutischen Erzeugnissen",
    "sg:phone":"+41 41 711 19 22",
    "sg:postcode":"6302",
    "sg:province":"Zug",
    "wof:name":"Balmer Chemie Ltd, Dublin Zweigniederlassung Zug",
    "wof:placetype":"venue"
},
  "geometry": {"coordinates":[8.5177631378,47.1804656982],"type":"Point"}
}