{
  "type": "Feature",
  "properties": {
    "addr:full":"H\u00f6heweg 84 Biel/bienne Bern 2502",
    "addr:housenumber":"84",
    "addr:postcode":"2502",
    "addr:street":"Hoeheweg",
    "iso:country":"CH",
    "sg:address":"H\u00f6heweg 84",
    "sg:city":"Biel/bienne",
    "sg:orig_category":"Advokaturb\u00fcros",
    "sg:phone":"+41 32 323 67 87",
    "sg:postcode":"2502",
    "sg:province":"Bern",
    "wof:name":"Christine Beerli Advokaturb\u00fcro",
    "wof:placetype":"venue"
},
  "geometry": {"coordinates":[7.244596,47.143135],"type":"Point"}
}