{
  "type": "Feature",
  "properties": {
    "iso:country":"CH",
    "sg:address":"Hegibachstrasse 79",
    "sg:city":"Z\u00fcrich",
    "sg:orig_category":"Kosmetikinstitute",
    "sg:phone":"+41 14226632",
    "sg:postcode":"8032",
    "sg:province":"Z\u00fcrich",
    "wof:name":"Freitag Joachim, Maske Make Up Ausbildungskurse Ausbildungskurse D. Maskenbildnerei, Filmschminktechnik Usw",
    "wof:placetype":"venue"
},
  "geometry": {"coordinates":[8.5654935837,47.3641395569],"type":"Point"}
}