{
  "type": "Feature",
  "properties": {
    "iso:country":"CH",
    "sg:address":"Landhausstrasse 17",
    "sg:city":"Baar",
    "sg:orig_category":"Unclassifiable Establishments",
    "sg:postcode":"6340",
    "sg:province":"Zug",
    "wof:name":"Praxis Harmoush",
    "wof:placetype":"venue"
},
  "geometry": {"coordinates":[8.5183992386,47.1945266724],"type":"Point"}
}