{
  "type": "Feature",
  "properties": {
    "iso:country":"CH",
    "sg:address":"J.c. Rosenburger-strasse 8",
    "sg:city":"M\u00fcnchenstein",
    "sg:orig_category":"Sonstige mit der Informatik verbundene T\u00e4tigkeiten",
    "sg:phone":"+41 61 411 86 16",
    "sg:postcode":"4142",
    "sg:province":"Basel-Landschaft",
    "wof:name":"Mulas System Consulting",
    "wof:placetype":"venue"
},
  "geometry": {"coordinates":[7.6029901505,47.51612854],"type":"Point"}
}