{
  "type": "Feature",
  "properties": {
    "iso:country":"CH",
    "sg:address":"Chemin Ami-argand 9-11",
    "sg:city":"Versoix",
    "sg:orig_category":"Herstellung von sonstigen Metallwaren",
    "sg:phone":"+41 22 755 17 64",
    "sg:postcode":"1290",
    "sg:province":"Gen\u00e8ve",
    "wof:name":"Selba Sa Gravure De Haute Pr\u00e9cision",
    "wof:placetype":"venue"
},
  "geometry": {"coordinates":[6.1644039154,46.2855262756],"type":"Point"}
}