{
  "type": "Feature",
  "properties": {
    "iso:country":"CH",
    "sg:address":"Berthastrasse 7 4500 Solothurn. Postfach",
    "sg:city":"Solothurn",
    "sg:orig_category":"Architekturb\u00fcros",
    "sg:phone":"+41 32 621 56 56",
    "sg:postcode":"4501",
    "sg:province":"Solothurn",
    "wof:name":"Guido Kummer Architekturb\u00fcro",
    "wof:placetype":"venue"
},
  "geometry": {"coordinates":[7.540752,47.204483],"type":"Point"}
}