{
  "type": "Feature",
  "properties": {
    "iso:country":"CH",
    "sg:address":"L\u00e4mmlisbrunnenstrasse 16",
    "sg:city":"St.gallen",
    "sg:orig_category":"Erbringung von Dienstleistungen f\u00fcr Unternehmen",
    "sg:phone":"+41 71 223 56 65",
    "sg:postcode":"9000",
    "sg:province":"St. Gallen",
    "wof:name":"Ioe Inkasso Organisation Ehmke",
    "wof:placetype":"venue"
},
  "geometry": {"coordinates":[9.3808450699,47.4245033264],"type":"Point"}
}