{
  "type": "Feature",
  "properties": {
    "iso:country":"CH",
    "sg:address":"Unterdorfstrasse 12",
    "sg:city":"Sch\u00f6fflisdorf",
    "sg:orig_category":"Herstellung von Ger\u00e4ten der Elektrizit\u00e4tserzeugung, -verteilung u.\u00e4. -Herstellung von sonstigen elek",
    "sg:phone":"+41 18561492",
    "sg:postcode":"8165",
    "sg:province":"Z\u00fcrich",
    "wof:name":"Els-elektronik Gmbh",
    "wof:placetype":"venue"
},
  "geometry": {"coordinates":[8.4159917831,47.4970588684],"type":"Point"}
}