{
  "type": "Feature",
  "properties": {
    "iso:country":"CH",
    "sg:address":"Lindenhof",
    "sg:city":"Mastrils",
    "sg:classifiers":[
        {
            "category":"Building & Trades",
            "subcategory":"Construction",
            "type":"Services"
        }
    ],
    "sg:phone":"+41 81 300 04 30",
    "sg:postcode":"7303",
    "sg:province":"Graubunden",
    "sg:tags":[
        "installation",
        "heating"
    ],
    "wof:name":"Swiss E-technic",
    "wof:placetype":"venue"
},
  "geometry": {"coordinates":[9.541745,46.967045],"type":"Point"}
}