{
  "type": "Feature",
  "properties": {
    "iso:country":"CH",
    "sg:address":"Via Industria",
    "sg:city":"Lamone",
    "sg:orig_category":"Bauschreinerei Einbau von Schreinerwaren",
    "sg:phone":"+41 71 755 65 60",
    "sg:postcode":"6814",
    "sg:province":"Ticino",
    "wof:name":"Schweitzer Ladenbau Ag Ladenbaueinrichtungen Samt Zubeh\u00f6r; Produktion, Handel, Montage Usw",
    "wof:placetype":"venue"
},
  "geometry": {"coordinates":[9.542883,47.382931],"type":"Point"}
}