{
  "type": "Feature",
  "properties": {
    "addr:full":"Rue De Lausanne 80 Gen\u00e8ve Gen\u00e8ve 1202",
    "addr:housenumber":"80",
    "addr:postcode":"1202",
    "addr:street":"Rue De Lausanne",
    "iso:country":"CH",
    "sg:address":"Rue De Lausanne 80",
    "sg:city":"Gen\u00e8ve",
    "sg:orig_category":"Arztpraxen",
    "sg:phone":"+41 22 908 33 00",
    "sg:postcode":"1202",
    "sg:province":"Gen\u00e8ve",
    "wof:name":"Dr M\u00e9d. Danilo Janjic M\u00e9decin Sp\u00e9cialiste Fmh",
    "wof:placetype":"venue"
},
  "geometry": {"coordinates":[6.148029,46.216557],"type":"Point"}
}