{
  "type": "Feature",
  "properties": {
    "iso:country":"CH",
    "sg:address":"Limmatstrasse 55 5300 Turgi. Postfach",
    "sg:city":"Turgi",
    "sg:orig_category":"Oberfl\u00e4chenveredlung U W\u00e4rmebehandlung",
    "sg:phone":"+41 56 201 03 01",
    "sg:postcode":"5300",
    "sg:province":"Aargau",
    "wof:name":"Hasler + Matter Ag",
    "wof:placetype":"venue"
},
  "geometry": {"coordinates":[8.2511901855,47.4945983887],"type":"Point"}
}