{
  "type": "Feature",
  "properties": {
    "iso:country":"CH",
    "sg:address":"Englischgrussstrasse 21",
    "sg:city":"Glis",
    "sg:orig_category":"H\u00f6here Fachschulen Weiterbildungskurse and Seminar Anbieter",
    "sg:phone":"+41 27 924 37 27",
    "sg:postcode":"3902",
    "sg:province":"Valais",
    "wof:name":"Betriebspsycholog.institut Management-fachschule",
    "wof:placetype":"venue"
},
  "geometry": {"coordinates":[7.9836959839,46.3155632019],"type":"Point"}
}