{
  "type": "Feature",
  "properties": {
    "iso:country":"CH",
    "sg:address":"Parkstrasse 4 6410 Goldau. Postfach 16",
    "sg:city":"Goldau",
    "sg:orig_category":"Versicherungen Hauptagenturen",
    "sg:phone":"+41 41 855 50 85",
    "sg:postcode":"6410",
    "sg:province":"Schwyz",
    "wof:name":"Josef Dober Hauptagentur Winterthur-vers.",
    "wof:placetype":"venue"
},
  "geometry": {"coordinates":[8.5481042862,47.0496559143],"type":"Point"}
}