{
  "type": "Feature",
  "properties": {
    "addr:full":"Schollenackerweg 6 Pfeffingen Basel-Landschaft 4148",
    "addr:housenumber":"6",
    "addr:postcode":"4148",
    "addr:street":"Schollenackerweg",
    "iso:country":"CH",
    "sg:address":"Schollenackerweg 6",
    "sg:city":"Pfeffingen",
    "sg:orig_category":"Betrieb von Taxis",
    "sg:phone":"+41 61 751 29 06",
    "sg:postcode":"4148",
    "sg:province":"Basel-Landschaft",
    "wof:name":"Cartax Ag",
    "wof:placetype":"venue"
},
  "geometry": {"coordinates":[7.58408,47.459652],"type":"Point"}
}