{
  "type": "Feature",
  "properties": {
    "iso:country":"CH",
    "sg:address":"Bilchenstrasse 31",
    "sg:city":"Amriswil",
    "sg:orig_category":"Wirtschaftspr\u00fcfung, Steuerberatung U Treuhand",
    "sg:phone":"+41 71 411 08 08",
    "sg:postcode":"8580",
    "sg:province":"Thurgau",
    "wof:name":"Zaugg Consulting",
    "wof:placetype":"venue"
},
  "geometry": {"coordinates":[9.3121747971,47.5347557068],"type":"Point"}
}