{
  "type": "Feature",
  "properties": {
    "iso:country":"CH",
    "sg:address":"Chemin De Grange-collomb 5",
    "sg:city":"Grand-lancy",
    "sg:orig_category":"Herstellung von Teppichen Verlegen von Fliesen U Platten",
    "sg:phone":"+41 22 342 53 10",
    "sg:postcode":"1212",
    "sg:province":"Gen\u00e8ve",
    "wof:name":"Garcia & Constantino Constantino Successeur",
    "wof:placetype":"venue"
},
  "geometry": {"coordinates":[6.1336941719,46.1756515503],"type":"Point"}
}