{
  "type": "Feature",
  "properties": {
    "iso:country":"CH",
    "sg:address":"1636 Broc. Postfach 39",
    "sg:city":"Broc",
    "sg:orig_category":"Sportvereine Ballsport Fussball",
    "sg:phone":"+41 56 442 22 25",
    "sg:postcode":"1636",
    "sg:province":"Fribourg",
    "wof:name":"Fc Brugg",
    "wof:placetype":"venue"
},
  "geometry": {"coordinates":[8.2035999298,47.4864692688],"type":"Point"}
}