{
  "type": "Feature",
  "properties": {
    "iso:country":"CH",
    "sg:address":"Industriestrasse 7 6300 Zug. Postfach",
    "sg:city":"Cham",
    "sg:orig_category":"Hochschulen U h\u00f6here Ausbildung Weiterbildungskurse and Seminar Anbieter",
    "sg:phone":"+41 52 366 50 62",
    "sg:postcode":"6330",
    "sg:province":"Zug",
    "wof:name":"Weber Gabriella Training Berufliche Weiterbildung, Bes. Im Bereich Telefon, Verkaufstraining",
    "wof:placetype":"venue"
},
  "geometry": {"coordinates":[8.8238649368,47.5625343323],"type":"Point"}
}