{
  "type": "Feature",
  "properties": {
    "iso:country":"CH",
    "sg:address":"Levant Rue Du 130",
    "sg:city":"Martigny",
    "sg:orig_category":"Instandhaltung U Reparatur von Automobilen",
    "sg:phone":"+41 27 722 17 37",
    "sg:postcode":"1920",
    "sg:province":"Valais",
    "wof:name":"Besse Gilbert",
    "wof:placetype":"venue"
},
  "geometry": {"coordinates":[7.0874919891,46.1014595032],"type":"Point"}
}