{
  "type": "Feature",
  "properties": {
    "iso:country":"CH",
    "sg:address":"Kreuzstrasse 2",
    "sg:city":"Siebnen",
    "sg:classifiers":[
        {
            "category":"Restaurant",
            "type":"Food & Drink"
        }
    ],
    "sg:phone":"+41 55 440 55 38",
    "sg:postcode":"8854",
    "sg:province":"Schwyz",
    "wof:name":"Restaurant Schwyzerh\u00fcsli",
    "wof:placetype":"venue"
},
  "geometry": {"coordinates":[8.8977336884,47.1826286316],"type":"Point"}
}