{
  "type": "Feature",
  "properties": {
    "iso:country":"CH",
    "sg:address":"B\u00fcrglenweg 6",
    "sg:city":"Konolfingen",
    "sg:orig_category":"Sportvereine Ballsport Volleyball",
    "sg:phone":"+41 71 931 29 82",
    "sg:postcode":"3510",
    "sg:province":"Bern",
    "wof:name":"Volleyballcl.tornado Adliswil",
    "wof:placetype":"venue"
},
  "geometry": {"coordinates":[8.547990799,47.3193702698],"type":"Point"}
}