{
  "type": "Feature",
  "properties": {
    "iso:country":"CH",
    "sg:address":"Rue Du Puits-godet 10",
    "sg:city":"Neuch\u00e2tel",
    "sg:orig_category":"Grosshandel mit B\u00fcromaschinen Grosshandel mit Datenverarbeitungsger\u00e4ten",
    "sg:phone":"+41 32 727 70 20",
    "sg:postcode":"2000",
    "sg:province":"Neuch\u00e2tel",
    "wof:name":"Bull (suisse) Sa",
    "wof:placetype":"venue"
},
  "geometry": {"coordinates":[6.9133257866,46.9985961914],"type":"Point"}
}