{
  "type": "Feature",
  "properties": {
    "iso:country":"CH",
    "sg:address":"Niesenstrasse 14c 2554 Meinisberg. Postfach",
    "sg:city":"Meinisberg",
    "sg:orig_category":"Sonstiger Grosshandel",
    "sg:phone":"+41 32 377 11 41",
    "sg:postcode":"2554",
    "sg:province":"Bern",
    "wof:name":"Duraflex S\u00e0rl Waren; Import U. Export Usw",
    "wof:placetype":"venue"
},
  "geometry": {"coordinates":[7.3443078995,47.1567344666],"type":"Point"}
}