{
  "type": "Feature",
  "properties": {
    "addr:full":"6514 Sementina Ticino 6514",
    "addr:postcode":"6514;6514",
    "iso:country":"CH",
    "sg:address":"6514",
    "sg:city":"Sementina",
    "sg:orig_category":"Bauspenglerei Dachdeckerei",
    "sg:phone":"+41 91 857 51 31",
    "sg:postcode":"6514",
    "sg:province":"Ticino",
    "wof:name":"Moreschi Gianfranco & Co Sa",
    "wof:placetype":"venue"
},
  "geometry": {"coordinates":[8.990273,46.184792],"type":"Point"}
}