{
  "type": "Feature",
  "properties": {
    "iso:country":"CH",
    "sg:address":"Alpenweg 6",
    "sg:city":"B\u00e4tterkinden",
    "sg:orig_category":"Allgemeiner Hoch U Tiefbau",
    "sg:phone":"+41 32 389 52 27",
    "sg:postcode":"3315",
    "sg:province":"Bern",
    "wof:name":"W\u00e4lchli Zimmerei/innenausbau Gmbh",
    "wof:placetype":"venue"
},
  "geometry": {"coordinates":[7.53073,47.149956],"type":"Point"}
}