{
  "type": "Feature",
  "properties": {
    "iso:country":"CH",
    "sg:address":"Buchzelgstrasse 108",
    "sg:city":"Z\u00fcrich",
    "sg:orig_category":"Solarien",
    "sg:phone":"+41 13820084",
    "sg:postcode":"8053",
    "sg:province":"Z\u00fcrich",
    "wof:name":"Somawell Solarium",
    "wof:placetype":"venue"
},
  "geometry": {"coordinates":[8.5919656754,47.3598022461],"type":"Point"}
}