{
  "type": "Feature",
  "properties": {
    "iso:country":"CH",
    "sg:address":"Elisabethenstrasse 57",
    "sg:city":"Bern",
    "sg:orig_category":"Hochschulen U h\u00f6here Ausbildung",
    "sg:phone":"+41 31 991 22 88",
    "sg:postcode":"3014",
    "sg:province":"Bern",
    "wof:name":"Geissler + Wahli",
    "wof:placetype":"venue"
},
  "geometry": {"coordinates":[7.4503078461,46.962223053],"type":"Point"}
}