{
  "type": "Feature",
  "properties": {
    "iso:country":"CH",
    "sg:address":"Les Lammes",
    "sg:city":"Mervelier",
    "sg:orig_category":"Mechanische Werkst\u00e4tten",
    "sg:phone":"+41 32 438 85 18",
    "sg:postcode":"2827",
    "sg:province":"Bern",
    "wof:name":"Emmanuel Joliat Atelier M\u00e9canique",
    "wof:placetype":"venue"
},
  "geometry": {"coordinates":[7.4909501076,47.3446807861],"type":"Point"}
}