{
  "type": "Feature",
  "properties": {
    "iso:country":"CH",
    "sg:address":"Bundesplatz 8 3011 Bern. Postfach",
    "sg:city":"Bern",
    "sg:orig_category":"Interessenvertretungen",
    "sg:postcode":"3005",
    "sg:province":"Bern",
    "wof:name":"Gem\u00e4ldesammlung Emil Bretschger Erhaltung, Erg\u00e4nzung U Allf\u00e4llige Erweiterung Des Kunstgutes Des Stifters Usw",
    "wof:placetype":"venue"
},
  "geometry": {"coordinates":[7.4435129166,46.9471321106],"type":"Point"}
}