{
  "type": "Feature",
  "properties": {
    "iso:country":"CH",
    "sg:address":"3110",
    "sg:city":"M\u00fcnsingen",
    "sg:classifiers":[
        {
            "category":"Education",
            "subcategory":"Vocational School",
            "type":"Public Place"
        }
    ],
    "sg:phone":"+41 31 720 11 11",
    "sg:postcode":"3110",
    "sg:province":"Bern",
    "sg:tags":[
        "koch-",
        "haushaltschulen"
    ],
    "wof:name":"Kant.landwirtschafts-& Haus- Haltungsschule Schwand,sekret.",
    "wof:placetype":"venue"
},
  "geometry": {"coordinates":[7.5629019737,46.8749542236],"type":"Point"}
}