{
  "type": "Feature",
  "properties": {
    "iso:country":"CH",
    "sg:address":"Badenerstrasse 15 5442 Fislisbach. Postfach 95",
    "sg:city":"Fislisbach",
    "sg:orig_category":"Detailhandel mit B\u00fcchern, Zeitungen, Schreib U Papeteriewaren Detailhandel mit Schreib U Papeteriewa",
    "sg:phone":"+41 56 493 77 55",
    "sg:postcode":"5442",
    "sg:province":"Aargau",
    "wof:name":"Papeterie Trost Und Arnold Ag",
    "wof:placetype":"venue"
},
  "geometry": {"coordinates":[8.29155,47.436901],"type":"Point"}
}