{
  "type": "Feature",
  "properties": {
    "iso:country":"CH",
    "sg:address":"6376",
    "sg:city":"Emmetten",
    "sg:classifiers":[
        {
            "category":"Travel",
            "subcategory":"Hotels & Motels",
            "type":"Entertainment"
        }
    ],
    "sg:postcode":"6376",
    "sg:province":"Nidwalden",
    "sg:tags":[
        "hotels",
        "mit",
        "restaurant"
    ],
    "wof:name":"Filliger-n\u00e4pflin Richard, Hotel Post",
    "wof:placetype":"venue"
},
  "geometry": {"coordinates":[8.5198669434,46.9562416077],"type":"Point"}
}