{
  "type": "Feature",
  "properties": {
    "iso:country":"CH",
    "sg:address":"Schulstrasse 147",
    "sg:city":"Mellikon",
    "sg:classifiers":[
        {
            "category":"Sports & Exercise",
            "subcategory":"Playing Field",
            "type":"Entertainment"
        }
    ],
    "sg:phone":"+41 56 243 11 88",
    "sg:postcode":"5465",
    "sg:province":"Aargau",
    "sg:tags":[
        "ecological",
        "agents",
        "cleaning"
    ],
    "wof:name":"Bas Trading",
    "wof:placetype":"venue"
},
  "geometry": {"coordinates":[8.35178,47.567528],"type":"Point"}
}