{
  "type": "Feature",
  "properties": {
    "iso:country":"CH",
    "sg:address":"Buchshalde 265",
    "sg:city":"Uetendorf",
    "sg:orig_category":"Mechanik Schlossereien",
    "sg:phone":"+41 33 345 43 90",
    "sg:postcode":"3661",
    "sg:province":"Bern",
    "wof:name":"Geissler + Frydig Gmbh",
    "wof:placetype":"venue"
},
  "geometry": {"coordinates":[7.5635609627,46.7767906189],"type":"Point"}
}