{
  "type": "Feature",
  "properties": {
    "iso:country":"CH",
    "sg:address":"Gemeindestrasse 924",
    "sg:city":"Ueberstorf",
    "sg:orig_category":"Maler U Glasergewerbe Malerei",
    "sg:phone":"+41 52 672 13 31",
    "sg:postcode":"3182",
    "sg:province":"Fribourg",
    "wof:name":"Beutel Malerei, Spritzwerk, Schriften",
    "wof:placetype":"venue"
},
  "geometry": {"coordinates":[8.6238861084,47.681224823],"type":"Point"}
}