{
  "type": "Feature",
  "properties": {
    "iso:country":"CH",
    "sg:address":"Diethelmstrasse 12 6363 F\u00fcrigen. Postfach",
    "sg:city":"F\u00fcrigen",
    "sg:orig_category":"Elektrizit\u00e4tsversorgung",
    "sg:phone":"+41 41 612 00 31",
    "sg:postcode":"6363",
    "sg:province":"Nidwalden",
    "wof:name":"Unique Environment Ag",
    "wof:placetype":"venue"
},
  "geometry": {"coordinates":[8.3500061035,46.9802131653],"type":"Point"}
}