{
  "type": "Feature",
  "properties": {
    "iso:country":"CH",
    "sg:address":"Ennetb\u00fchlerstrasse 6",
    "sg:city":"Glarus",
    "sg:orig_category":"Technische, physikalische U chemische Untersuchung",
    "sg:phone":"+41 55 646 66 40",
    "sg:postcode":"8750",
    "sg:province":"Glarus",
    "wof:name":"Kantonales Lebensmittelinspektorat",
    "wof:placetype":"venue"
},
  "geometry": {"coordinates":[9.0693683624,47.0416564941],"type":"Point"}
}