{
  "type": "Feature",
  "properties": {
    "iso:country":"CH",
    "sg:address":"Dellenweg 189",
    "sg:city":"Wenslingen",
    "sg:orig_category":"Bauspenglerei Zimmerei, Dachdeckerei, Bauspenglerei U Abdichtung",
    "sg:phone":"+41 62 756 31 79",
    "sg:postcode":"4493",
    "sg:province":"Basel-Landschaft",
    "wof:name":"Wey A. Spenglerei Ag",
    "wof:placetype":"venue"
},
  "geometry": {"coordinates":[8.033137,47.199696],"type":"Point"}
}