{
  "type": "Feature",
  "properties": {
    "iso:country":"CH",
    "sg:address":"Guisan Via 2",
    "sg:city":"Paradiso",
    "sg:orig_category":"Detailhandel mit Radio U Fernsehger\u00e4ten Softwareentwicklung U beratung",
    "sg:phone":"+41 91 993 38 03",
    "sg:postcode":"6902",
    "sg:province":"Ticino",
    "wof:name":"A 1 Tele-video Ed Elettronica Sa",
    "wof:placetype":"venue"
},
  "geometry": {"coordinates":[8.9471750259,45.9904403687],"type":"Point"}
}