{
  "type": "Feature",
  "properties": {
    "iso:country":"CH",
    "sg:address":"Alpenstrasse 14 6300 Zug. Postfach 4864",
    "sg:city":"Zug",
    "sg:orig_category":"Binnenschiffahrt",
    "sg:phone":"+41 18656262",
    "sg:postcode":"6304",
    "sg:province":"Zug",
    "wof:name":"Schifffahrtsgesellschaft Z\u00fcri Rhy Ag",
    "wof:placetype":"venue"
},
  "geometry": {"coordinates":[8.579155,47.529835],"type":"Point"}
}