{
  "type": "Feature",
  "properties": {
    "iso:country":"CH",
    "sg:address":"Saluferstrasse 7",
    "sg:city":"Chur",
    "sg:orig_category":"Instandhaltung U Reparatur von Automobilen",
    "sg:phone":"+41 81 353 56 40",
    "sg:postcode":"7000",
    "sg:province":"Graubunden",
    "wof:name":"Alessandro Sisera Autosattlerei",
    "wof:placetype":"venue"
},
  "geometry": {"coordinates":[9.5326128006,46.8607254028],"type":"Point"}
}