{
  "type": "Feature",
  "properties": {
    "iso:country":"CH",
    "sg:address":"Kr\u00e4hb\u00fchlstrasse 114",
    "sg:city":"Z\u00fcrich",
    "sg:orig_category":"Gartenbau",
    "sg:phone":"+41 12514511",
    "sg:postcode":"8044",
    "sg:province":"Z\u00fcrich",
    "wof:name":"Thomas Leder Garten- & Landschaftsbau",
    "wof:placetype":"venue"
},
  "geometry": {"coordinates":[8.5693941116,47.3785514832],"type":"Point"}
}