{
  "type": "Feature",
  "properties": {
    "iso:country":"CH",
    "sg:address":"Route De Neuch\u00e2tel 2a",
    "sg:city":"St-blaise",
    "sg:orig_category":"Grosshandel mit keramischen Erzeugnissen, Glaswaren U Reinigungsmitteln Herstellung von Baubedarfsar",
    "sg:phone":"+41 71 278 39 38",
    "sg:postcode":"2072",
    "sg:province":"Neuch\u00e2tel",
    "wof:name":"M. & T. Steger Plexiglas-acrylglas",
    "wof:placetype":"venue"
},
  "geometry": {"coordinates":[9.3524017334,47.422706604],"type":"Point"}
}