{
  "type": "Feature",
  "properties": {
    "iso:country":"CH",
    "sg:address":"Burgstrasse 18 3601 Thun. Postfach",
    "sg:city":"Leukerbad",
    "sg:orig_category":"Allgemeiner Hoch U Tiefbau",
    "sg:phone":"+41 27 470 22 63",
    "sg:postcode":"3954",
    "sg:province":"Valais",
    "wof:name":"Palfalvo Ag Generalunternehmensauftr\u00e4ge. Projektierung, Ueberwachung, Architektur Usw",
    "wof:placetype":"venue"
},
  "geometry": {"coordinates":[7.629638,46.761448],"type":"Point"}
}