{
  "type": "Feature",
  "properties": {
    "iso:country":"CH",
    "sg:address":"6523",
    "sg:city":"Preonzo",
    "sg:orig_category":"G\u00fcterbef\u00f6rderung im Strassenverkehr",
    "sg:phone":"+41 91 863 42 73",
    "sg:postcode":"6523",
    "sg:province":"Ticino",
    "wof:name":"Torpala Sa Trasporti & Scavi",
    "wof:placetype":"venue"
},
  "geometry": {"coordinates":[8.9998292923,46.2651481628],"type":"Point"}
}