{
  "type": "Feature",
  "properties": {
    "iso:country":"CH",
    "sg:address":"Freilagerstrasse 5 4142 M\u00fcnchenstein. Postfach",
    "sg:city":"Basel",
    "sg:orig_category":"Detailhandel mit M\u00f6beln U Haushaltsgegenst\u00e4nden Grosshandel mit M\u00f6beln, Wohnbedarf, Teppichen U Bode",
    "sg:phone":"+41 61 331 28 38",
    "sg:postcode":"4024",
    "sg:province":"Basel-Stadt",
    "wof:name":"Nasser Zarnegin",
    "wof:placetype":"venue"
},
  "geometry": {"coordinates":[7.6105399132,47.5333137512],"type":"Point"}
}