{
  "type": "Feature",
  "properties": {
    "iso:country":"CH",
    "sg:address":"Hauptstrasse 136",
    "sg:city":"Sissach",
    "sg:classifiers":[
        {
            "category":"Home & Garden",
            "subcategory":"Kitchen Supply",
            "type":"Retail Goods"
        }
    ],
    "sg:phone":"+41 61 976 90 00",
    "sg:postcode":"4450",
    "sg:province":"Basel-Landschaft",
    "sg:tags":[
        "cupboard"
    ],
    "wof:name":"Heid K\u00fcchen Ag",
    "wof:placetype":"venue"
},
  "geometry": {"coordinates":[7.8026609421,47.4657478333],"type":"Point"}
}