{
  "type": "Feature",
  "properties": {
    "iso:country":"CH",
    "sg:address":"Chemin Du Martinet 27",
    "sg:city":"Lausanne",
    "sg:orig_category":"Detailhandel mit Tabakwaren",
    "sg:postcode":"1007",
    "sg:province":"Vaud",
    "wof:name":"Perruchoud A.",
    "wof:placetype":"venue"
},
  "geometry": {"coordinates":[6.5796151161,46.5362205505],"type":"Point"}
}