{
  "type": "Feature",
  "properties": {
    "iso:country":"CH",
    "sg:address":"Weinbergstrasse 69",
    "sg:city":"Z\u00fcrich",
    "sg:orig_category":"Advokaturb\u00fcros",
    "sg:phone":"+41 13629863",
    "sg:postcode":"8006",
    "sg:province":"Z\u00fcrich",
    "wof:name":"Rusch & Rusch Advokaturb\u00fcro",
    "wof:placetype":"venue"
},
  "geometry": {"coordinates":[8.543441,47.382359],"type":"Point"}
}