{
  "type": "Feature",
  "properties": {
    "iso:country":"CH",
    "sg:address":"Am Gfenngraben 7",
    "sg:city":"D\u00fcbendorf",
    "sg:orig_category":"Architektur U Ingenieurb\u00fcros",
    "sg:postcode":"8600",
    "sg:province":"Z\u00fcrich",
    "wof:name":"Urs M\u00fcller Ing. B\u00fcro F\u00fcr Metall Und Fassadenbau",
    "wof:placetype":"venue"
},
  "geometry": {"coordinates":[8.644945,47.393173],"type":"Point"}
}