{
  "type": "Feature",
  "properties": {
    "iso:country":"CH",
    "sg:address":"Bahnhofstrasse 71",
    "sg:city":"Z\u00fcrich",
    "sg:orig_category":"Druck ohne Zeitungsdruck",
    "sg:phone":"+41 79 222 03 60",
    "sg:postcode":"8001",
    "sg:province":"Z\u00fcrich",
    "wof:name":"Reliefdruck Au, Kn\u00f6pfli Gmbh",
    "wof:placetype":"venue"
},
  "geometry": {"coordinates":[9.6396608353,47.4363212585],"type":"Point"}
}