{
  "type": "Feature",
  "properties": {
    "iso:country":"CH",
    "sg:address":"Oberwilerstr. 14",
    "sg:city":"Gachnang",
    "sg:orig_category":"Interessenvertretungen",
    "sg:postcode":"8547",
    "sg:province":"Thurgau",
    "wof:name":"Stiftung F\u00fcr Alterswohnungen In Gachnang",
    "wof:placetype":"venue"
},
  "geometry": {"coordinates":[8.8532056808,47.5388069153],"type":"Point"}
}