{
  "type": "Feature",
  "properties": {
    "iso:country":"CH",
    "sg:address":"Fadackerstrasse 5",
    "sg:city":"Dietlikon",
    "sg:orig_category":"Fahrschulen, Flugschulen",
    "sg:phone":"+41 18331380",
    "sg:postcode":"8305",
    "sg:province":"Z\u00fcrich",
    "wof:name":"Benjamin Hassler Autofahrschule",
    "wof:placetype":"venue"
},
  "geometry": {"coordinates":[8.6161136627,47.4212036133],"type":"Point"}
}