{
  "type": "Feature",
  "properties": {
    "iso:country":"CH",
    "sg:address":"Gerliswilstrasse 95",
    "sg:city":"Emmenbr\u00fccke",
    "sg:orig_category":"Darlehenskassen U Raiffeisenbanken",
    "sg:postcode":"6020",
    "sg:province":"Luzern",
    "wof:name":"Raiffeisenbank Emmen",
    "wof:placetype":"venue"
},
  "geometry": {"coordinates":[8.273791,47.079277],"type":"Point"}
}