{
  "type": "Feature",
  "properties": {
    "iso:country":"CH",
    "sg:address":"Rousseau Rue 30 1201 Gen\u00e8ve. Postfach",
    "sg:city":"Gen\u00e8ve",
    "sg:orig_category":"Unclassifiable Establishments",
    "sg:postcode":"1201",
    "sg:province":"Gen\u00e8ve",
    "wof:name":"Dipastria J.c. Miklusz Sa",
    "wof:placetype":"venue"
},
  "geometry": {"coordinates":[6.1431999207,46.2077064514],"type":"Point"}
}