{
  "type": "Feature",
  "properties": {
    "iso:country":"CH",
    "sg:address":"Aarauerstrasse 18",
    "sg:city":"Oberentfelden",
    "sg:orig_category":"Detailhandel mit Damenbekleidung Herstellung von W\u00e4sche",
    "sg:phone":"+41 62 723 62 79",
    "sg:postcode":"5036",
    "sg:province":"Aargau",
    "wof:name":"Donna Mode Soleil H\u00e4rdi T.",
    "wof:placetype":"venue"
},
  "geometry": {"coordinates":[8.046415329,47.3586006165],"type":"Point"}
}