{
  "type": "Feature",
  "properties": {
    "addr:full":"Bertiswilstrasse 51 Rothenburg Luzern 6023",
    "addr:housenumber":"51",
    "addr:postcode":"6023",
    "addr:street":"Bertiswilstrasse",
    "iso:country":"CH",
    "sg:address":"Bertiswilstrasse 51",
    "sg:city":"Rothenburg",
    "sg:orig_category":"Allgemeiner Hoch U Tiefbau Hoch U Tiefbau",
    "sg:phone":"+41 41 280 12 94",
    "sg:postcode":"6023",
    "sg:province":"Luzern",
    "wof:name":"Cerutti Hans Ag",
    "wof:placetype":"venue"
},
  "geometry": {"coordinates":[8.267737,47.100246],"type":"Point"}
}