{
  "type": "Feature",
  "properties": {
    "iso:country":"CH",
    "sg:address":"Via Arca 39 6855 Stabio. Postfach",
    "sg:city":"Stabio",
    "sg:orig_category":"Unclassifiable Establishments",
    "sg:postcode":"6855",
    "sg:province":"Ticino",
    "wof:name":"Mombelli Communication Design Organizzazione E Gestione Della Comunicazione",
    "wof:placetype":"venue"
},
  "geometry": {"coordinates":[8.9375,45.8552513123],"type":"Point"}
}