{
  "type": "Feature",
  "properties": {
    "iso:country":"CH",
    "sg:address":"Bahnhofstrasse 27",
    "sg:city":"Spreitenbach",
    "sg:orig_category":"Herstellung von Teppichen Verlegen von Fussboden",
    "sg:phone":"+41 56 401 20 11",
    "sg:postcode":"8957",
    "sg:province":"Aargau",
    "wof:name":"Fischer W. Bodenbel\u00e4ge.",
    "wof:placetype":"venue"
},
  "geometry": {"coordinates":[8.3664321899,47.4194869995],"type":"Point"}
}