{
  "type": "Feature",
  "properties": {
    "iso:country":"CH",
    "sg:address":"H\u00fcgelweg 3",
    "sg:city":"Binningen",
    "sg:orig_category":"Vermietung U Verpachtung von eigenen Immobilien",
    "sg:phone":"+41 61 301 15 09",
    "sg:postcode":"4102",
    "sg:province":"Basel-Landschaft",
    "wof:name":"Immobiliengesellschaft Buche Ag",
    "wof:placetype":"venue"
},
  "geometry": {"coordinates":[7.5631952286,47.5425415039],"type":"Point"}
}