{
  "type": "Feature",
  "properties": {
    "iso:country":"CH",
    "sg:address":"Wenkenr\u00fctistrasse 25",
    "sg:city":"Wattwil",
    "sg:orig_category":"Malerei",
    "sg:phone":"+41 79 697 24 69",
    "sg:postcode":"9630",
    "sg:province":"St. Gallen",
    "wof:name":"Antonio & Paola Gerardi Malergesch\u00e4ft",
    "wof:placetype":"venue"
},
  "geometry": {"coordinates":[9.0796060562,47.3073616028],"type":"Point"}
}