{
  "type": "Feature",
  "properties": {
    "iso:country":"CH",
    "sg:address":"Thunstrasse 14b",
    "sg:city":"M\u00fcnsingen",
    "sg:orig_category":"Gartenbau",
    "sg:phone":"+41 79 439 64 41",
    "sg:postcode":"3110",
    "sg:province":"Bern",
    "wof:name":"Buchschacher Gartenunterhalt",
    "wof:placetype":"venue"
},
  "geometry": {"coordinates":[7.5625448227,46.8716430664],"type":"Point"}
}