{
  "type": "Feature",
  "properties": {
    "iso:country":"CH",
    "sg:address":"Im Sch\u00f6rli 28",
    "sg:city":"D\u00fcbendorf",
    "sg:orig_category":"RESTAURANTS: TEA-ROOMS",
    "sg:phone":"+41 18213003",
    "sg:postcode":"8600",
    "sg:province":"Z\u00fcrich",
    "wof:name":"Restaurant Diablo",
    "wof:placetype":"venue"
},
  "geometry": {"coordinates":[8.637339592,47.3954315186],"type":"Point"}
}