{
  "type": "Feature",
  "properties": {
    "iso:country":"CH",
    "sg:address":"Tramstrasse 7 5034 Suhr. Postfach",
    "sg:city":"Suhr",
    "sg:orig_category":"Unternehmensberatung Vermittlung von Immobilien",
    "sg:phone":"+41 62 855 80 30",
    "sg:postcode":"5034",
    "sg:province":"Aargau",
    "wof:name":"Arco Service Ag Dienstleistungen Im Management U. Im Geb\u00e4udeinfrastrukturmanagement",
    "wof:placetype":"venue"
},
  "geometry": {"coordinates":[8.0798940659,47.3733596802],"type":"Point"}
}