{
  "type": "Feature",
  "properties": {
    "iso:country":"CH",
    "sg:address":"7144",
    "sg:city":"Vella",
    "sg:orig_category":"Organisationen des Gesundheitswesen",
    "sg:phone":"+41 81 931 23 08",
    "sg:postcode":"7144",
    "sg:province":"Graubunden",
    "wof:name":"Samariterverein Vella",
    "wof:placetype":"venue"
},
  "geometry": {"coordinates":[9.1733598709,46.7175865173],"type":"Point"}
}