{
  "type": "Feature",
  "properties": {
    "iso:country":"CH",
    "sg:address":"Moncor Route De 2 1752 Villars-sur-gl\u00e2ne. Postfach",
    "sg:city":"Cormanon",
    "sg:orig_category":"Versandhandel",
    "sg:postcode":"1752",
    "sg:province":"Fribourg",
    "wof:name":"Psd Primium Services Directs S\u00e0rl Activit\u00e9 Li\u00e9e \u00e0 Des Prestations De Services \u00e0 Des Organismes De Vente Par Correspondance Etc",
    "wof:placetype":"venue"
},
  "geometry": {"coordinates":[7.130428791,46.7955818176],"type":"Point"}
}