{
  "type": "Feature",
  "properties": {
    "iso:country":"CH",
    "sg:address":"Bundesstrasse 3",
    "sg:city":"Zug",
    "sg:orig_category":"Unternehmensberatung",
    "sg:phone":"+41 41 726 77 11",
    "sg:postcode":"6300",
    "sg:province":"Zug",
    "wof:name":"Esther I. Weber Verm\u00f6gensberatung",
    "wof:placetype":"venue"
},
  "geometry": {"coordinates":[8.5136566162,47.1713104248],"type":"Point"}
}