{
  "type": "Feature",
  "properties": {
    "iso:country":"CH",
    "sg:address":"Aarwangenstrasse 32",
    "sg:city":"Langenthal",
    "sg:orig_category":"Fachdetailhandel mit pharmazeutischen Produkten",
    "sg:phone":"+41 56 675 56 10",
    "sg:postcode":"4900",
    "sg:province":"Bern",
    "wof:name":"Zentral-apotheke Muri Ag",
    "wof:placetype":"venue"
},
  "geometry": {"coordinates":[8.3174819946,47.2825775146],"type":"Point"}
}