{
  "type": "Feature",
  "properties": {
    "iso:country":"CH",
    "sg:address":"Bodenhostatt 3",
    "sg:city":"Ennetb\u00fcrgen",
    "sg:orig_category":"Verlagsgewerbe",
    "sg:phone":"+41 41 620 52 12",
    "sg:postcode":"6373",
    "sg:province":"Nidwalden",
    "wof:name":"Musenalp Worldwide Online / Musenalp.com",
    "wof:placetype":"venue"
},
  "geometry": {"coordinates":[8.4080896378,46.9839782715],"type":"Point"}
}