{
  "type": "Feature",
  "properties": {
    "iso:country":"CH",
    "sg:address":"1489",
    "sg:city":"Murist",
    "sg:orig_category":"Primarschulen",
    "sg:phone":"+41 26 411 31 12",
    "sg:postcode":"1489",
    "sg:province":"Fribourg",
    "wof:name":"Ecole Primaire",
    "wof:placetype":"venue"
},
  "geometry": {"coordinates":[6.8084278107,46.609588623],"type":"Point"}
}