{
  "type": "Feature",
  "properties": {
    "addr:full":"Gasse Scharnachtal Bern 3722",
    "addr:postcode":"3722",
    "addr:street":"Gasse",
    "iso:country":"CH",
    "sg:address":"Gasse",
    "sg:city":"Scharnachtal",
    "sg:orig_category":"Bauspenglerei Sanit\u00e4rinstallation",
    "sg:phone":"+41 79 422 93 35",
    "sg:postcode":"3722",
    "sg:province":"Bern",
    "wof:name":"Von K\u00e4nel & Sieber Sanit\u00e4re Anlagen & Spenglerei",
    "wof:placetype":"venue"
},
  "geometry": {"coordinates":[7.698617,46.612778],"type":"Point"}
}