{
  "type": "Feature",
  "properties": {
    "iso:country":"CH",
    "sg:address":"Stapfenstrasse 4",
    "sg:city":"K\u00f6niz",
    "sg:orig_category":"Fachdetailhandel mit pharmazeutischen Produkten",
    "sg:phone":"+41 31 971 22 71",
    "sg:postcode":"3098",
    "sg:province":"Bern",
    "wof:name":"Apotheke Im Zentrum Dr. E. Von Hornstein",
    "wof:placetype":"venue"
},
  "geometry": {"coordinates":[7.4149751663,46.9226341248],"type":"Point"}
}