{
  "type": "Feature",
  "properties": {
    "iso:country":"CH",
    "sg:address":"6883 Novazzano. Postfach",
    "sg:city":"Novazzano",
    "sg:orig_category":"Vermietung U Verpachtung von eigenen Immobilien",
    "sg:postcode":"6883",
    "sg:province":"Ticino",
    "wof:name":"Garbinasca Sa",
    "wof:placetype":"venue"
},
  "geometry": {"coordinates":[8.9802398682,45.8421401978],"type":"Point"}
}