{
  "type": "Feature",
  "properties": {
    "iso:country":"CH",
    "sg:address":"Socinstrasse 81",
    "sg:city":"Basel",
    "sg:orig_category":"Architekturb\u00fcros",
    "sg:phone":"+41 55 283 28 38",
    "sg:postcode":"4051",
    "sg:province":"Basel-Stadt",
    "wof:name":"Peter Rosenast Architekturb\u00fcro",
    "wof:placetype":"venue"
},
  "geometry": {"coordinates":[9.016846,47.188965],"type":"Point"}
}