{
  "type": "Feature",
  "properties": {
    "iso:country":"CH",
    "sg:address":"Zi En Reutet D",
    "sg:city":"Collombey",
    "sg:orig_category":"Unclassifiable Establishments",
    "sg:postcode":"1868",
    "sg:province":"Valais",
    "wof:name":"Dav, Weber",
    "wof:placetype":"venue"
},
  "geometry": {"coordinates":[6.945827961,46.2704734802],"type":"Point"}
}