{
  "type": "Feature",
  "properties": {
    "iso:country":"CH",
    "sg:address":"Avenue Henri-dunant 16",
    "sg:city":"Gen\u00e8ve",
    "sg:orig_category":"Detailhandel mit Brot, Back U S\u00fcsswaren",
    "sg:phone":"+41 22 329 12 08",
    "sg:postcode":"1205",
    "sg:province":"Gen\u00e8ve",
    "wof:name":"Christophe Berger Confiserie-p\u00e2tisserie",
    "wof:placetype":"venue"
},
  "geometry": {"coordinates":[6.142105,46.195805],"type":"Point"}
}