{
  "type": "Feature",
  "properties": {
    "iso:country":"CH",
    "sg:address":"Cantonale Via",
    "sg:city":"Pambio-noranco",
    "sg:orig_category":"Maler U Glasergewerbe",
    "sg:phone":"+41 78 693 09 30",
    "sg:postcode":"6915",
    "sg:province":"Ticino",
    "wof:name":"Comby Entreprise De Peinture",
    "wof:placetype":"venue"
},
  "geometry": {"coordinates":[6.8265938759,47.1072921753],"type":"Point"}
}