{
  "type": "Feature",
  "properties": {
    "iso:country":"CH",
    "sg:address":"Hauptstrasse 212",
    "sg:city":"Orpund",
    "sg:orig_category":"Drogerien Sonstiger Fachdetailhandel mit Nahrungsmitteln, Getr\u00e4nken U Tabak in Verkaufsr\u00e4umen",
    "sg:phone":"+41 79 415 15 26",
    "sg:postcode":"2552",
    "sg:province":"Bern",
    "wof:name":"Landmesser Hans Ulrich.",
    "wof:placetype":"venue"
},
  "geometry": {"coordinates":[8.0347061157,46.7540931702],"type":"Point"}
}