{
  "type": "Feature",
  "properties": {
    "iso:country":"CH",
    "sg:address":"Unterriedstrasse 30",
    "sg:city":"Oberrohrdorf",
    "sg:orig_category":"Finanzierungsinstitutionen",
    "sg:postcode":"5452",
    "sg:province":"Aargau",
    "wof:name":"Paclan Ag",
    "wof:placetype":"venue"
},
  "geometry": {"coordinates":[8.8199644089,47.2292785645],"type":"Point"}
}