{
  "type": "Feature",
  "properties": {
    "iso:country":"CH",
    "sg:address":"Beundenweg 2 2500 Biel/bienne. Postfach",
    "sg:city":"Biel/bienne",
    "sg:orig_category":"Detailhandel mit Fleisch U Fleischwaren",
    "sg:postcode":"2500",
    "sg:province":"Bern",
    "wof:name":"Metzgerei Fehlbaum.",
    "wof:placetype":"venue"
},
  "geometry": {"coordinates":[7.2590699196,47.1293144226],"type":"Point"}
}