{
  "type": "Feature",
  "properties": {
    "iso:country":"CH",
    "sg:address":"Rue D'orbe 27",
    "sg:city":"Yverdon-les-bains",
    "sg:orig_category":"Arztpraxen",
    "sg:phone":"+41 24 423 82 82",
    "sg:postcode":"1400",
    "sg:province":"Vaud",
    "wof:name":"Dr M\u00e9d. Cyrille Francillon M\u00e9decin Sp\u00e9cialiste Fmh",
    "wof:placetype":"venue"
},
  "geometry": {"coordinates":[6.64142,46.778629],"type":"Point"}
}