{
  "type": "Feature",
  "properties": {
    "iso:country":"CH",
    "sg:address":"Haldenstrasse Dietingen",
    "sg:city":"Uesslingen",
    "sg:orig_category":"Architektur U Ingenieurb\u00fcros",
    "sg:postcode":"8524",
    "sg:province":"Thurgau",
    "wof:name":"Langhans Ad. Bau-management",
    "wof:placetype":"venue"
},
  "geometry": {"coordinates":[8.831485,47.58028],"type":"Point"}
}