{
  "type": "Feature",
  "properties": {
    "iso:country":"CH",
    "sg:address":"Industriestrasse 1-3 3185 Schmitten Fr. Postfach 2613",
    "sg:city":"Bern",
    "sg:orig_category":"Pensionskassen",
    "sg:postcode":"3005",
    "sg:province":"Bern",
    "wof:name":"F\u00fcrsorge-stiftung Der Schumacher Ag",
    "wof:placetype":"venue"
},
  "geometry": {"coordinates":[7.2522439957,46.8622131348],"type":"Point"}
}