{
  "type": "Feature",
  "properties": {
    "iso:country":"CH",
    "sg:address":"Limmattalstrasse 228",
    "sg:city":"Z\u00fcrich",
    "sg:orig_category":"Tankstellen",
    "sg:phone":"+41 13416044",
    "sg:postcode":"8049",
    "sg:province":"Z\u00fcrich",
    "wof:name":"Agip (suisse) Sa Service-station",
    "wof:placetype":"venue"
},
  "geometry": {"coordinates":[8.4955148697,47.4022865295],"type":"Point"}
}