{
  "type": "Feature",
  "properties": {
    "iso:country":"CH",
    "sg:address":"Bahnhofstrasse 66a",
    "sg:city":"M\u00f6hlin",
    "sg:classifiers":[
        {
            "category":"Shopping",
            "subcategory":"Computers & Home Electronics",
            "type":"Retail Goods"
        }
    ],
    "sg:phone":"+41 61 851 57 52",
    "sg:postcode":"4313",
    "sg:province":"Aargau",
    "sg:tags":[
        "client-server",
        "software"
    ],
    "wof:name":"Smarttrade M. Habl\u00fctzel",
    "wof:placetype":"venue"
},
  "geometry": {"coordinates":[7.842906,47.557213],"type":"Point"}
}