{
  "type": "Feature",
  "properties": {
    "iso:country":"CH",
    "sg:address":"Pierre Rue Saint- 18",
    "sg:city":"Fribourg",
    "sg:orig_category":"Verwaltung von Immobilien",
    "sg:postcode":"1700",
    "sg:province":"Fribourg",
    "wof:name":"Aic Avis Immobilien Consulting Immobilien Usw",
    "wof:placetype":"venue"
},
  "geometry": {"coordinates":[7.5611481667,47.5116729736],"type":"Point"}
}