{
  "type": "Feature",
  "properties": {
    "iso:country":"CH",
    "sg:address":"Route De Fenil",
    "sg:city":"Corsier-sur-vevey",
    "sg:orig_category":"Bauschreinerei Herstellung von Fenstern U T\u00fcren aus Holz",
    "sg:phone":"+41 71 277 59 57",
    "sg:postcode":"1804",
    "sg:province":"Vaud",
    "wof:name":"Haller Fenster Ag",
    "wof:placetype":"venue"
},
  "geometry": {"coordinates":[9.354155,47.419899],"type":"Point"}
}