{
  "type": "Feature",
  "properties": {
    "addr:full":"Schl\u00f6sslistrasse 7 Spiez Bern 3700",
    "addr:housenumber":"7",
    "addr:postcode":"3700",
    "addr:street":"Schloesslistrasse",
    "iso:country":"CH",
    "sg:address":"Schl\u00f6sslistrasse 7",
    "sg:city":"Spiez",
    "sg:orig_category":"Berufsbildende weiterf\u00fchrende Schulen Maturit\u00e4tsschulen, Lehrerseminarien",
    "sg:phone":"+41 33 655 50 30",
    "sg:postcode":"3700",
    "sg:province":"Bern",
    "wof:name":"Oberl\u00e4ndische Schule Spiez",
    "wof:placetype":"venue"
},
  "geometry": {"coordinates":[7.683415,46.685246],"type":"Point"}
}