{
  "type": "Feature",
  "properties": {
    "iso:country":"CH",
    "sg:address":"Steinrain 15",
    "sg:city":"Aarburg",
    "sg:orig_category":"Fachdetailhandel in Verkaufsr\u00e4umen",
    "sg:postcode":"4663",
    "sg:province":"Aargau",
    "wof:name":"Artimo Sa",
    "wof:placetype":"venue"
},
  "geometry": {"coordinates":[7.9069337845,47.323551178],"type":"Point"}
}