{
  "type": "Feature",
  "properties": {
    "iso:country":"CH",
    "sg:address":"Le Pralet",
    "sg:city":"Essertes",
    "sg:orig_category":"Gartenbau Landschaftsplanungsb\u00fcros U Gartenarchitekturb\u00fcros",
    "sg:phone":"+41 21 907 98 14",
    "sg:postcode":"1078",
    "sg:province":"Vaud",
    "wof:name":"Fritz Johner Paysagiste",
    "wof:placetype":"venue"
},
  "geometry": {"coordinates":[6.7812299728,46.5599746704],"type":"Point"}
}