{
  "type": "Feature",
  "properties": {
    "iso:country":"CH",
    "sg:address":"Louis-casa\u00ef Avenue 88",
    "sg:city":"Meyrin",
    "sg:classifiers":[
        {
            "category":"Professional",
            "subcategory":"Employment Agencies",
            "type":"Services"
        }
    ],
    "sg:postcode":"1217",
    "sg:province":"Gen\u00e8ve",
    "sg:tags":[
        "personal",
        "u",
        "stellenvermittlung"
    ],
    "wof:name":"Cgg I Sa",
    "wof:placetype":"venue"
},
  "geometry": {"coordinates":[6.1055707932,46.2263298035],"type":"Point"}
}