{
  "type": "Feature",
  "properties": {
    "iso:country":"CH",
    "sg:address":"Alte Rheinstr. 50",
    "sg:city":"Kriessern",
    "sg:classifiers":[
        {
            "category":"Manufacturing",
            "subcategory":"Metals",
            "type":"Manufacturing & Wholesale Goods"
        }
    ],
    "sg:phone":"+41 71 393 36 33",
    "sg:postcode":"9451",
    "sg:province":"St. Gallen",
    "sg:tags":[
        "metallurgy",
        "metalworking",
        "processing"
    ],
    "wof:name":"Verzinkerei Oberuzwil Ag",
    "wof:placetype":"venue"
},
  "geometry": {"coordinates":[9.1329545975,47.4371452332],"type":"Point"}
}