{
  "type": "Feature",
  "properties": {
    "iso:country":"CH",
    "sg:address":"Rainstrasse 33 6314 Unter\u00e4geri. Postfach 338",
    "sg:city":"Unter\u00e4geri",
    "sg:orig_category":"Herstellung von sonstigen landwirtschaftlichen Maschinen",
    "sg:phone":"+41 41 750 52 57",
    "sg:postcode":"6314",
    "sg:province":"Zug",
    "wof:name":"Karl Merz Landmaschinen",
    "wof:placetype":"venue"
},
  "geometry": {"coordinates":[8.5733003616,47.135093689],"type":"Point"}
}