{
  "type": "Feature",
  "properties": {
    "iso:country":"CH",
    "sg:address":"Les Amatennes 2",
    "sg:city":"Belprahon",
    "sg:orig_category":"Fahrschulen, Flugschulen",
    "sg:phone":"+41 79 321 66 66",
    "sg:postcode":"2744",
    "sg:province":"Bern",
    "wof:name":"Marcel Locher Autofahrschule",
    "wof:placetype":"venue"
},
  "geometry": {"coordinates":[8.4415683746,47.0812110901],"type":"Point"}
}