{
  "type": "Feature",
  "properties": {
    "iso:country":"CH",
    "sg:address":"Via Cittadella 9",
    "sg:city":"Locarno",
    "sg:orig_category":"Detailhandel mit Blumen U Pflanzen",
    "sg:phone":"+41 91 751 53 70",
    "sg:postcode":"6600",
    "sg:province":"Ticino",
    "wof:name":"Verena Mahler Fiorista",
    "wof:placetype":"venue"
},
  "geometry": {"coordinates":[8.794199,46.170033],"type":"Point"}
}