{
  "type": "Feature",
  "properties": {
    "iso:country":"CH",
    "sg:address":"Route De La Morge 9",
    "sg:city":"Conthey",
    "sg:orig_category":"Einbau von Schreinerwaren",
    "sg:phone":"+41 27 346 25 61",
    "sg:postcode":"1964",
    "sg:province":"Valais",
    "wof:name":"Edwin W\u00fcst & Cie Agencement De Cuisines",
    "wof:placetype":"venue"
},
  "geometry": {"coordinates":[7.3123102188,46.2298583984],"type":"Point"}
}