{
  "type": "Feature",
  "properties": {
    "iso:country":"CH",
    "sg:address":"Seestrasse 203",
    "sg:city":"Z\u00fcrich",
    "sg:orig_category":"Museen",
    "sg:phone":"+41 14823144",
    "sg:postcode":"8002",
    "sg:province":"Z\u00fcrich",
    "wof:name":"Muraltengut",
    "wof:placetype":"venue"
},
  "geometry": {"coordinates":[8.5323352814,47.3536224365],"type":"Point"}
}