{
  "type": "Feature",
  "properties": {
    "iso:country":"CH",
    "sg:address":"8907",
    "sg:city":"Wettswil",
    "sg:orig_category":"Primarschulen",
    "sg:phone":"+41 17133600",
    "sg:postcode":"8907",
    "sg:province":"Z\u00fcrich",
    "wof:name":"Primarschule Wolfgraben",
    "wof:placetype":"venue"
},
  "geometry": {"coordinates":[8.5312643051,47.2865447998],"type":"Point"}
}