{
  "type": "Feature",
  "properties": {
    "iso:country":"CH",
    "sg:address":"Ausserfeldstrasse 438",
    "sg:city":"Erschwil",
    "sg:orig_category":"Unternehmensberatung",
    "sg:postcode":"4228",
    "sg:province":"Solothurn",
    "wof:name":"Cmh Consulting-marketing-handel Ag",
    "wof:placetype":"venue"
},
  "geometry": {"coordinates":[7.5426921844,47.3752861023],"type":"Point"}
}