{
  "type": "Feature",
  "properties": {
    "iso:country":"CH",
    "sg:address":"Schulhausstrasse 2",
    "sg:city":"Horw",
    "sg:orig_category":"Architektur U Ingenieurb\u00fcros",
    "sg:phone":"+41 41 310 66 83",
    "sg:postcode":"6048",
    "sg:province":"Luzern",
    "wof:name":"Infanger Ag",
    "wof:placetype":"venue"
},
  "geometry": {"coordinates":[8.309689,47.021576],"type":"Point"}
}