{
  "type": "Feature",
  "properties": {
    "iso:country":"CH",
    "sg:address":"3293",
    "sg:city":"Dotzigen",
    "sg:orig_category":"Wasserversorgung",
    "sg:phone":"+41 32 351 13 77",
    "sg:postcode":"3293",
    "sg:province":"Bern",
    "wof:name":"Wasserversorgung Der Gemeinde Dotzigen",
    "wof:placetype":"venue"
},
  "geometry": {"coordinates":[7.3437600136,47.1229286194],"type":"Point"}
}