{
  "type": "Feature",
  "properties": {
    "iso:country":"CH",
    "sg:address":"Place Saint-fran\u00e7ois 10",
    "sg:city":"Lausanne",
    "sg:classifiers":[
        {
            "category":"Restaurant",
            "type":"Food & Drink"
        }
    ],
    "sg:phone":"+41 22 310 06 92",
    "sg:postcode":"1003",
    "sg:province":"Vaud",
    "wof:name":"Bg Caf\u00e9",
    "wof:placetype":"venue"
},
  "geometry": {"coordinates":[6.1475400925,46.2030181885],"type":"Point"}
}