{
  "type": "Feature",
  "properties": {
    "iso:country":"CH",
    "sg:address":"Nord Rue Du 11 1196 Gland. Postfach",
    "sg:city":"Froideville",
    "sg:orig_category":"Herstellung von Metallkonstruktionen",
    "sg:phone":"+41 21 881 48 14",
    "sg:postcode":"1055",
    "sg:province":"Vaud",
    "wof:name":"Bati Metallique S\u00e0rl",
    "wof:placetype":"venue"
},
  "geometry": {"coordinates":[6.2614498138,46.4224014282],"type":"Point"}
}