{
  "type": "Feature",
  "properties": {
    "iso:country":"CH",
    "sg:address":"B\u00fcmplizstrasse 187 3018 Bern. Postfach 551",
    "sg:city":"Bern",
    "sg:orig_category":"Detailhandel mit elektrischen Haushalts-,Radio U Fernsehger\u00e4ten sowie Musikinstrumenten Grosshandel ",
    "sg:phone":"+41 31 991 91 11",
    "sg:postcode":"3018",
    "sg:province":"Bern",
    "wof:name":"Berna Av Ernst Sch\u00fcrch",
    "wof:placetype":"venue"
},
  "geometry": {"coordinates":[7.3956151009,46.9380302429],"type":"Point"}
}