{
  "type": "Feature",
  "properties": {
    "iso:country":"CH",
    "sg:address":"Ettiswilerstrasse",
    "sg:city":"Willisau",
    "sg:orig_category":"Herstellung von sonstigen Metallwaren",
    "sg:postcode":"6130",
    "sg:province":"Luzern",
    "wof:name":"Fetaplast Gmbh",
    "wof:placetype":"venue"
},
  "geometry": {"coordinates":[7.9962072372,47.1253051758],"type":"Point"}
}