{
  "type": "Feature",
  "properties": {
    "iso:country":"CH",
    "sg:address":"Wengistrasse 31 4500 Solothurn. Postfach",
    "sg:city":"Solothurn",
    "sg:orig_category":"Warenh\u00e4user",
    "sg:phone":"+41 32 623 18 11",
    "sg:postcode":"4502",
    "sg:province":"Solothurn",
    "wof:name":"Abm Au Bon March\u00e9",
    "wof:placetype":"venue"
},
  "geometry": {"coordinates":[7.5318059921,47.2079277039],"type":"Point"}
}