{
  "type": "Feature",
  "properties": {
    "iso:country":"CH",
    "sg:address":"Sainte-c\u00e9cile Avenue 37",
    "sg:city":"Meyrin",
    "sg:orig_category":"Sonstiger spezialisierter Hoch U Tiefbau",
    "sg:postcode":"1217",
    "sg:province":"Gen\u00e8ve",
    "wof:name":"Jos\u00e9 Correia Alves",
    "wof:placetype":"venue"
},
  "geometry": {"coordinates":[6.0826320648,46.2360687256],"type":"Point"}
}