{
  "type": "Feature",
  "properties": {
    "iso:country":"CH",
    "sg:address":"Dorfstrasse 65",
    "sg:city":"Obfelden",
    "sg:orig_category":"Bezirks, Sekundar, Realschulen, Oberstufe der Primarschulen",
    "sg:postcode":"8912",
    "sg:province":"Z\u00fcrich",
    "wof:name":"Oberstufenschule Kirchwies Pfannenstiel B",
    "wof:placetype":"venue"
},
  "geometry": {"coordinates":[8.690055,47.300556],"type":"Point"}
}