{
  "type": "Feature",
  "properties": {
    "iso:country":"CH",
    "sg:address":"Langobardenstrasse 15",
    "sg:city":"Bern",
    "sg:orig_category":"Vorschulen, Kinderg\u00e4rten",
    "sg:phone":"+41 31 992 42 82",
    "sg:postcode":"3018",
    "sg:province":"Bern",
    "wof:name":"Kindergarten St\u00f6ckacker",
    "wof:placetype":"venue"
},
  "geometry": {"coordinates":[7.399187088,46.9451141357],"type":"Point"}
}