{
  "type": "Feature",
  "properties": {
    "iso:country":"CH",
    "sg:address":"Lerchenfeldstrasse 41g 3603 Thun. Postfach 154",
    "sg:city":"Thun",
    "sg:orig_category":"Herstellung von Tanks U Sammelbeh\u00e4ltern aus Metall Reinigungsgewerbe",
    "sg:phone":"+41 33 222 82 89",
    "sg:postcode":"3603",
    "sg:province":"Bern",
    "wof:name":"Schneider",
    "wof:placetype":"venue"
},
  "geometry": {"coordinates":[7.6016368866,46.765045166],"type":"Point"}
}