{
  "type": "Feature",
  "properties": {
    "iso:country":"CH",
    "sg:address":"Albligenstrasse 2 3148 Lanzenh\u00e4usern. Postfach 43",
    "sg:city":"Schwarzenburg",
    "sg:orig_category":"Herstellung von Ger\u00e4ten der Elektrizit\u00e4tserzeugung, -verteilung u.\u00e4. -Herstellung von sonstigen elek",
    "sg:phone":"+41 31 731 11 10",
    "sg:postcode":"3150",
    "sg:province":"Bern",
    "wof:name":"Hans Haussener Ag",
    "wof:placetype":"venue"
},
  "geometry": {"coordinates":[7.3479909897,46.8435401917],"type":"Point"}
}