{
  "type": "Feature",
  "properties": {
    "iso:country":"CH",
    "sg:address":"Turmweg 14",
    "sg:city":"Wollerau",
    "sg:orig_category":"Informatikdienste",
    "sg:phone":"+41 56 470 34 34",
    "sg:postcode":"8832",
    "sg:province":"Schwyz",
    "wof:name":"Wintstar-shop Wintstar-schulungszentrum",
    "wof:placetype":"venue"
},
  "geometry": {"coordinates":[8.2948942184,47.4465789795],"type":"Point"}
}