{
  "type": "Feature",
  "properties": {
    "iso:country":"CH",
    "sg:address":"Kreuzstrasse 2",
    "sg:city":"Zollikofen",
    "sg:orig_category":"Detailhandel mit Waren verschiedener Art, Hauptrichtung Nahrungsmittel Grosshandel mit Nahrungsmitte",
    "sg:phone":"+41 31 747 76 86",
    "sg:postcode":"3052",
    "sg:province":"Bern",
    "wof:name":"Denner-satellit, Oesch Martin",
    "wof:placetype":"venue"
},
  "geometry": {"coordinates":[7.2383570671,46.9035644531],"type":"Point"}
}