{
  "type": "Feature",
  "properties": {
    "iso:country":"CH",
    "sg:address":"Nussbaumweg 7",
    "sg:city":"Allschwil",
    "sg:orig_category":"Malerei",
    "sg:phone":"+41 61 481 19 25",
    "sg:postcode":"4123",
    "sg:province":"Basel-Landschaft",
    "wof:name":"Werner Kilcher Malergesch\u00e4ft",
    "wof:placetype":"venue"
},
  "geometry": {"coordinates":[7.5321397781,47.5468597412],"type":"Point"}
}