{
  "type": "Feature",
  "properties": {
    "iso:country":"CH",
    "sg:address":"Dorfplatz 3",
    "sg:city":"Wattwil",
    "sg:orig_category":"Detailhandel mit Fleisch U Fleischwaren",
    "sg:postcode":"9630",
    "sg:province":"St. Gallen",
    "wof:name":"Metzgerei Zum Hirschen",
    "wof:placetype":"venue"
},
  "geometry": {"coordinates":[-83.1541519165,37.7017097473],"type":"Point"}
}