{
  "type": "Feature",
  "properties": {
    "iso:country":"CH",
    "sg:address":"Weienbrunnenstrasse",
    "sg:city":"M\u00fcswangen",
    "sg:orig_category":"Detailhandel mit Uhren U Schmuck Fachdetailhandel in Verkaufsr\u00e4umen",
    "sg:phone":"+41 41 917 00 18",
    "sg:postcode":"6289",
    "sg:province":"Luzern",
    "wof:name":"Theus Gold & Platin",
    "wof:placetype":"venue"
},
  "geometry": {"coordinates":[8.2895498276,47.2380104065],"type":"Point"}
}