{
  "type": "Feature",
  "properties": {
    "iso:country":"CH",
    "sg:address":"Savoleyres Place De 1936 Verbier. Postfach",
    "sg:city":"Verbier",
    "sg:orig_category":"Fachdetailhandel in Verkaufsr\u00e4umen",
    "sg:postcode":"1936",
    "sg:province":"Valais",
    "wof:name":"Evasion Verbier Sa Commerce D'articles De Sports Et De Loisirs",
    "wof:placetype":"venue"
},
  "geometry": {"coordinates":[7.2229619026,46.0967292786],"type":"Point"}
}