{
  "type": "Feature",
  "properties": {
    "iso:country":"CH",
    "sg:address":"Parkstrasse 22 6353 Weggis. Postfach",
    "sg:city":"Weggis",
    "sg:orig_category":"Detailhandel mit fotografischen Artikeln Fachdetailhandel in Verkaufsr\u00e4umen",
    "sg:phone":"+41 71 383 14 83",
    "sg:postcode":"6353",
    "sg:province":"Luzern",
    "wof:name":"Ammann Prisca Photo Art",
    "wof:placetype":"venue"
},
  "geometry": {"coordinates":[9.2483501434,47.4155082703],"type":"Point"}
}