{
  "type": "Feature",
  "properties": {
    "iso:country":"CH",
    "sg:address":"Mottastrasse 42 3005 Bern. Postfach",
    "sg:city":"Bern",
    "sg:orig_category":"Grosshandel mit Nahrungsmitteln, Getr\u00e4nken U Tabakwaren ohne ausgepr\u00e4gten Schwerpunkt",
    "sg:phone":"+41 31 351 13 16",
    "sg:postcode":"3005",
    "sg:province":"Bern",
    "wof:name":"F. B\u00f6siger Lebensmittel U Milchprodukte; Handel",
    "wof:placetype":"venue"
},
  "geometry": {"coordinates":[7.4520177841,46.9403610229],"type":"Point"}
}