{
  "type": "Feature",
  "properties": {
    "iso:country":"CH",
    "sg:address":"6951",
    "sg:city":"Bogno",
    "sg:orig_category":"Gasth\u00f6fe/Gasth\u00e4user mit Restaurant Kongress- and Tagungshotels mit Restaurant",
    "sg:phone":"+41 91 944 13 03",
    "sg:postcode":"6951",
    "sg:province":"Ticino",
    "wof:name":"Alloggio Locanda San Lucio",
    "wof:placetype":"venue"
},
  "geometry": {"coordinates":[9.0641136169,46.0894584656],"type":"Point"}
}