{
  "type": "Feature",
  "properties": {
    "addr:full":"Rue De Morat 8 1700 Fribourg Case Postale 176 Fribourg Fribourg 1702",
    "addr:housenumber":"8",
    "addr:postcode":"1700;case;176;1702",
    "addr:street":"Rue De Morat;Postale",
    "iso:country":"CH",
    "sg:address":"Rue De Morat 8 1700 Fribourg Case Postale 176",
    "sg:city":"Fribourg",
    "sg:orig_category":"Architekturb\u00fcros",
    "sg:phone":"+41 26 323 21 74",
    "sg:postcode":"1702",
    "sg:province":"Fribourg",
    "wof:name":"Serge Charri\u00e8re Sa Bureau D'architecture",
    "wof:placetype":"venue"
},
  "geometry": {"coordinates":[7.153683,46.803745],"type":"Point"}
}