{
  "type": "Feature",
  "properties": {
    "iso:country":"CH",
    "sg:address":"Gesero Via 16b",
    "sg:city":"Bellinzona",
    "sg:orig_category":"Architektur U Ingenieurb\u00fcros",
    "sg:postcode":"6500",
    "sg:province":"Ticino",
    "wof:name":"Studio Architetti Associati Limoncello, Lentini, Cacchioli E Rapelli",
    "wof:placetype":"venue"
},
  "geometry": {"coordinates":[9.025005,46.202599],"type":"Point"}
}