{
  "type": "Feature",
  "properties": {
    "iso:country":"CH",
    "sg:address":"Bergstrasse 4",
    "sg:city":"Bergdietikon",
    "sg:orig_category":"Herstellung von k\u00e4lte U lufttechnischen Erzeugnissen f\u00fcr gewerbliche Zwecke Installation von Heizung",
    "sg:phone":"+41 79 355 63 61",
    "sg:postcode":"8962",
    "sg:province":"Aargau",
    "wof:name":"Climatech J. Feuerstein",
    "wof:placetype":"venue"
},
  "geometry": {"coordinates":[8.3915185928,47.3954048157],"type":"Point"}
}