{
  "type": "Feature",
  "properties": {
    "iso:country":"CH",
    "sg:address":"3920",
    "sg:city":"Zermatt",
    "sg:orig_category":"G\u00fcterbef\u00f6rderung im Strassenverkehr",
    "sg:postcode":"3920",
    "sg:province":"Valais",
    "wof:name":"Chanton-transporte",
    "wof:placetype":"venue"
},
  "geometry": {"coordinates":[7.7484002113,46.024143219],"type":"Point"}
}