{
  "type": "Feature",
  "properties": {
    "iso:country":"CH",
    "sg:address":"1627",
    "sg:city":"Vaulruz",
    "sg:orig_category":"Interessenvertretungen",
    "sg:postcode":"1627",
    "sg:province":"Fribourg",
    "wof:name":"Soci\u00e9t\u00e9 Coop\u00e9rative Du Ch\u00e2teau De Vaulruz",
    "wof:placetype":"venue"
},
  "geometry": {"coordinates":[6.9905180931,46.6209640503],"type":"Point"}
}