{
  "type": "Feature",
  "properties": {
    "iso:country":"CH",
    "sg:address":"Mayaz",
    "sg:city":"Ste-croix",
    "sg:classifiers":[
        {
            "category":"Restaurant",
            "type":"Food & Drink"
        }
    ],
    "sg:phone":"+41 24 454 24 89",
    "sg:postcode":"1450",
    "sg:province":"Vaud",
    "wof:name":"Restaurant De La Mont",
    "wof:placetype":"venue"
},
  "geometry": {"coordinates":[6.5010499954,46.8242111206],"type":"Point"}
}