{
  "type": "Feature",
  "properties": {
    "iso:country":"CH",
    "sg:address":"Rue De Bernex 271",
    "sg:city":"Bernex",
    "sg:orig_category":"Non-Classified Establishments",
    "sg:postcode":"1233",
    "sg:province":"Gen\u00e8ve",
    "wof:name":"Newage Informatik R. Oettli",
    "wof:placetype":"venue"
},
  "geometry": {"coordinates":[9.0427770615,47.4659233093],"type":"Point"}
}