{
  "type": "Feature",
  "properties": {
    "iso:country":"CH",
    "sg:address":"Riehenring 91",
    "sg:city":"Basel",
    "sg:orig_category":"RESTAURANTS: TEA-ROOMS",
    "sg:phone":"+41 79 333 76 68",
    "sg:postcode":"4058",
    "sg:province":"Basel-Stadt",
    "wof:name":"Restaurant Hongkong Ag",
    "wof:placetype":"venue"
},
  "geometry": {"coordinates":[7.5980911255,47.5651664734],"type":"Point"}
}