{
  "type": "Feature",
  "properties": {
    "iso:country":"CH",
    "sg:address":"Sennweidstrasse 43",
    "sg:city":"Steinhausen",
    "sg:orig_category":"Grosshandel mit Parf\u00fcmerieartikeln U K\u00f6rperpflegemitteln Handels-H\u00e4user U Gesellschaften",
    "sg:phone":"+41 41 740 13 50",
    "sg:postcode":"6312",
    "sg:province":"Zug",
    "wof:name":"Lombagine Cosmetics Ag Konsum- U. Luxusg\u00fcter; Einkauf, Vertrieb Usw",
    "wof:placetype":"venue"
},
  "geometry": {"coordinates":[8.483915329,47.1899223328],"type":"Point"}
}