{
  "type": "Feature",
  "properties": {
    "iso:country":"CH",
    "sg:address":"Postgasse 62",
    "sg:city":"Bern",
    "sg:orig_category":"Bildung and Forschung, Museen",
    "sg:phone":"+41 31 312 13 91",
    "sg:postcode":"3011",
    "sg:province":"Bern",
    "wof:name":"Elk Bern",
    "wof:placetype":"venue"
},
  "geometry": {"coordinates":[7.453432,46.948837],"type":"Point"}
}