{
  "type": "Feature",
  "properties": {
    "addr:full":"Avenue William-fraisse 10 Lausanne Vaud 1006",
    "addr:housenumber":"10",
    "addr:postcode":"1006",
    "addr:street":"Avenue William-Fraisse",
    "iso:country":"CH",
    "sg:address":"Avenue William-fraisse 10",
    "sg:city":"Lausanne",
    "sg:orig_category":"Detailhandel mit Antiquit\u00e4ten Sonstiger Fachdetailhandel in Verkaufsr\u00e4umen",
    "sg:phone":"+41 21 616 70 04",
    "sg:postcode":"1006",
    "sg:province":"Vaud",
    "wof:name":"Regnier Paul Armurerie",
    "wof:placetype":"venue"
},
  "geometry": {"coordinates":[6.625405,46.515816],"type":"Point"}
}