{
  "type": "Feature",
  "properties": {
    "iso:country":"CH",
    "sg:address":"Dammstrasse 35",
    "sg:city":"Z\u00fcrich",
    "sg:orig_category":"Reinigungsgewerbe",
    "sg:phone":"+41 12718923",
    "sg:postcode":"8037",
    "sg:province":"Z\u00fcrich",
    "wof:name":"Barrio Reinigungen",
    "wof:placetype":"venue"
},
  "geometry": {"coordinates":[8.5281667709,47.3922843933],"type":"Point"}
}