{
  "type": "Feature",
  "properties": {
    "iso:country":"CH",
    "sg:address":"Warthausen",
    "sg:city":"Sch\u00e4nis",
    "sg:orig_category":"Detailhandel mit Milcherzeugnissen U Eiern Verarbeitung von Milch",
    "sg:phone":"+41 31 839 11 93",
    "sg:postcode":"8718",
    "sg:province":"St. Gallen",
    "wof:name":"Margrit Hosmann K\u00e4serei Worb",
    "wof:placetype":"venue"
},
  "geometry": {"coordinates":[7.5646810532,46.9261474609],"type":"Point"}
}