{
  "type": "Feature",
  "properties": {
    "iso:country":"CH",
    "sg:address":"Binningerstrasse 129",
    "sg:city":"Allschwil",
    "sg:orig_category":"Instandhaltung U Reparatur von Automobilen",
    "sg:phone":"+41 61 482 17 87",
    "sg:postcode":"4123",
    "sg:province":"Basel-Landschaft",
    "wof:name":"Antonio Maschietto Garage",
    "wof:placetype":"venue"
},
  "geometry": {"coordinates":[7.5507488251,47.5474739075],"type":"Point"}
}