{
  "type": "Feature",
  "properties": {
    "addr:full":"Dorf Entlebuch Luzern 6162",
    "addr:postcode":"6162",
    "addr:street":"Dorf Entlebuch",
    "iso:country":"CH",
    "sg:address":"Dorf",
    "sg:city":"Entlebuch",
    "sg:orig_category":"Detailhandel mit Blumen U Pflanzen Fachdetailhandel in Verkaufsr\u00e4umen",
    "sg:phone":"+41 41 480 14 76",
    "sg:postcode":"6162",
    "sg:province":"Luzern",
    "wof:name":"Blumengalerie Steiner Ag",
    "wof:placetype":"venue"
},
  "geometry": {"coordinates":[8.065155,46.993534],"type":"Point"}
}