{
  "type": "Feature",
  "properties": {
    "iso:country":"CH",
    "sg:address":"Aubepine Chemin De L' 16 1196 Gland. Postfach",
    "sg:city":"Gland",
    "sg:orig_category":"Herstellung von optischen U fotografischen Ger\u00e4ten",
    "sg:phone":"+41 32 374 41 41",
    "sg:postcode":"1196",
    "sg:province":"Vaud",
    "wof:name":"Lastec Ag",
    "wof:placetype":"venue"
},
  "geometry": {"coordinates":[7.2758579254,47.1247749329],"type":"Point"}
}