{
  "type": "Feature",
  "properties": {
    "iso:country":"CH",
    "sg:address":"Hauptstrasse 56 4127 Birsfelden. Postfach 731",
    "sg:city":"Birsfelden",
    "sg:orig_category":"Herstellung von sonstigen Produkten aus nichtmetallischen Mineralien Sonstiger Grosshandel",
    "sg:phone":"+41 61 313 06 06",
    "sg:postcode":"4127",
    "sg:province":"Basel-Landschaft",
    "wof:name":"Sihelco Ag",
    "wof:placetype":"venue"
},
  "geometry": {"coordinates":[7.6212849617,47.5535011292],"type":"Point"}
}