{
  "type": "Feature",
  "properties": {
    "iso:country":"CH",
    "sg:address":"Wanne 9100 Herisau. Postfach",
    "sg:city":"Herisau",
    "sg:orig_category":"Unclassifiable Establishments",
    "sg:phone":"+41 71 350 18 69",
    "sg:postcode":"9100",
    "sg:province":"Appenzell Ausserrhoden",
    "wof:name":"Zellweger Thomas Handwerksarbeiten F\u00fcr Autogewerbe",
    "wof:placetype":"venue"
},
  "geometry": {"coordinates":[9.3045148849,47.3880882263],"type":"Point"}
}