{
  "type": "Feature",
  "properties": {
    "iso:country":"CH",
    "sg:address":"Weirden 3",
    "sg:city":"Lustm\u00fchle",
    "sg:orig_category":"Wartung U Reparatur von B\u00fcromaschinen, Datenverarbeitungsger\u00e4ten U einrichtungen",
    "sg:phone":"+41 71 333 39 21",
    "sg:postcode":"9062",
    "sg:province":"Appenzell Ausserrhoden",
    "wof:name":"Ernst H\u00f6hener Computer",
    "wof:placetype":"venue"
},
  "geometry": {"coordinates":[9.3568115234,47.3980636597],"type":"Point"}
}