{
  "type": "Feature",
  "properties": {
    "iso:country":"CH",
    "sg:address":"Commercialstr. 23",
    "sg:city":"Chur",
    "sg:classifiers":[
        {
            "category":"Home & Garden",
            "subcategory":"Furniture",
            "type":"Retail Goods"
        }
    ],
    "sg:phone":"+41 81 252 63 66",
    "sg:postcode":"7000",
    "sg:province":"Graubunden",
    "sg:tags":[
        "household",
        "wood"
    ],
    "wof:name":"Sprenger M\u00d6bel Ag",
    "wof:placetype":"venue"
},
  "geometry": {"coordinates":[9.5092477798,46.8467178345],"type":"Point"}
}