{
  "type": "Feature",
  "properties": {
    "iso:country":"CH",
    "sg:address":"Surentalstrasse 10",
    "sg:city":"Sursee",
    "sg:orig_category":"Sonstiges Versicherungsgewerbe Versicherungen Generalagenturen",
    "sg:phone":"+41 41 926 05 60",
    "sg:postcode":"6210",
    "sg:province":"Luzern",
    "wof:name":"Stettler Heinz Generalagentur Der Winterthur Leben",
    "wof:placetype":"venue"
},
  "geometry": {"coordinates":[8.1102542877,47.1783409119],"type":"Point"}
}