{
  "type": "Feature",
  "properties": {
    "iso:country":"CH",
    "sg:address":"Reberastrasse 29 9494 Schaan. Postfach 130",
    "sg:city":"Schaan",
    "sg:orig_category":"Elektroinstallation",
    "sg:phone":"+41 79 216 51 65",
    "sg:postcode":"9494",
    "wof:name":"Quaderer & Beck Elektroinstallationen Ag",
    "wof:placetype":"venue"
},
  "geometry": {"coordinates":[9.5108299255,47.1655464172],"type":"Point"}
}