{
  "type": "Feature",
  "properties": {
    "iso:country":"CH",
    "sg:address":"Seestrasse 380",
    "sg:city":"Berlingen",
    "sg:orig_category":"Instandhaltung U Reparatur von Automobilen",
    "sg:phone":"+41 77725672",
    "sg:postcode":"8267",
    "sg:province":"Thurgau",
    "wof:name":"Gss Sportgarage Bruno Schmidlin",
    "wof:placetype":"venue"
},
  "geometry": {"coordinates":[9.0399875641,47.6729469299],"type":"Point"}
}