{
  "type": "Feature",
  "properties": {
    "iso:country":"CH",
    "sg:address":"1276 Gingins. Postfach",
    "sg:city":"Gingins",
    "sg:orig_category":"Mechanik",
    "sg:phone":"+41 31 832 05 00",
    "sg:postcode":"1276",
    "sg:province":"Vaud",
    "wof:name":"Baminox Gmbh",
    "wof:placetype":"venue"
},
  "geometry": {"coordinates":[7.5585289001,46.9363746643],"type":"Point"}
}