{
  "type": "Feature",
  "properties": {
    "iso:country":"CH",
    "sg:address":"Industriering 42 3250 Lyss. Postfach 444",
    "sg:city":"Lyss",
    "sg:orig_category":"Herstellung von Karosserien U Anh\u00e4ngern Herstellung von Metallerzeugnissen ohne Maschinenbau",
    "sg:phone":"+41 32 384 56 51",
    "sg:postcode":"3250",
    "sg:province":"Bern",
    "wof:name":"Hermann Andres Ag",
    "wof:placetype":"venue"
},
  "geometry": {"coordinates":[7.3056120872,47.0882492065],"type":"Point"}
}