{
  "type": "Feature",
  "properties": {
    "iso:country":"CH",
    "sg:address":"Kohlrainstrasse 10",
    "sg:city":"K\u00fcsnacht",
    "sg:classifiers":[
        {
            "category":"Professional",
            "subcategory":"Advertising",
            "type":"Services"
        }
    ],
    "sg:phone":"+41 19120305",
    "sg:postcode":"8700",
    "sg:province":"Z\u00fcrich",
    "sg:tags":[
        "agency"
    ],
    "wof:name":"Bio Talk Gmbh",
    "wof:placetype":"venue"
},
  "geometry": {"coordinates":[8.579844,47.319782],"type":"Point"}
}