{
  "type": "Feature",
  "properties": {
    "iso:country":"CH",
    "sg:address":"Auwiesen R\u00e4terschen 8352 Elsau. Postfach",
    "sg:city":"Elsau",
    "sg:orig_category":"Stukkateurgewerbe, Gipserei U Verputzerei",
    "sg:postcode":"8352",
    "sg:province":"Z\u00fcrich",
    "wof:name":"Bys\u00e4th & Bodenmann.",
    "wof:placetype":"venue"
},
  "geometry": {"coordinates":[8.8004179001,47.4917602539],"type":"Point"}
}