{
  "type": "Feature",
  "properties": {
    "iso:country":"CH",
    "sg:address":"Leenr\u00fctimattweg 2",
    "sg:city":"Niederbipp",
    "sg:classifiers":[
        {
            "category":"Wholesale",
            "subcategory":"Office Equipment",
            "type":"Manufacturing & Wholesale Goods"
        }
    ],
    "sg:phone":"+41 32 633 66 66",
    "sg:postcode":"4704",
    "sg:province":"Bern",
    "sg:tags":[
        "development",
        "designing"
    ],
    "wof:name":"Sumec",
    "wof:placetype":"venue"
},
  "geometry": {"coordinates":[7.701355,47.280666],"type":"Point"}
}