{
  "type": "Feature",
  "properties": {
    "iso:country":"CH",
    "sg:address":"Chemin De L'usine 3",
    "sg:city":"Echallens",
    "sg:orig_category":"Herstellung von Metallerzeugnissen ohne Maschinenbau Herstellung von sonstigen landwirtschaftlichen ",
    "sg:phone":"+41 21 881 18 81",
    "sg:postcode":"1040",
    "sg:province":"Vaud",
    "wof:name":"Henriod Paul S\u00e0rl",
    "wof:placetype":"venue"
},
  "geometry": {"coordinates":[6.6231951714,46.642780304],"type":"Point"}
}