{
  "type": "Feature",
  "properties": {
    "iso:country":"CH",
    "sg:address":"Rossmatt",
    "sg:city":"Lanzenh\u00e4usern",
    "sg:orig_category":"Grosshandel mit lebenden Tieren",
    "sg:phone":"+41 31 731 08 70",
    "sg:postcode":"3148",
    "sg:province":"Bern",
    "wof:name":"Fritz Mast Viehandel",
    "wof:placetype":"venue"
},
  "geometry": {"coordinates":[7.3479909897,46.8435401917],"type":"Point"}
}