{
  "type": "Feature",
  "properties": {
    "iso:country":"CH",
    "sg:address":"Leimgrubenweg 9",
    "sg:city":"Basel",
    "sg:classifiers":[
        {
            "category":"Travel",
            "subcategory":"Hotels & Motels",
            "type":"Entertainment"
        }
    ],
    "sg:postcode":"4053",
    "sg:province":"Basel-Stadt",
    "sg:tags":[
        "hotels",
        "mit",
        "restaurant"
    ],
    "wof:name":"Dreispitz Freizeitanlagen Ag",
    "wof:placetype":"venue"
},
  "geometry": {"coordinates":[7.6081728935,47.5368499756],"type":"Point"}
}