{
  "type": "Feature",
  "properties": {
    "iso:country":"CH",
    "sg:address":"Dorf",
    "sg:city":"Niedermuhlern",
    "sg:orig_category":"Reparatur von Schuhen U Lederwaren",
    "sg:phone":"+41 31 819 00 10",
    "sg:postcode":"3087",
    "sg:province":"Bern",
    "wof:name":"Rudolf Tschirren Schuhmacherei",
    "wof:placetype":"venue"
},
  "geometry": {"coordinates":[7.4653911591,46.8612213135],"type":"Point"}
}