{
  "type": "Feature",
  "properties": {
    "addr:full":"Berghofstrasse 6 Unterlunkhofen Aargau 8918",
    "addr:housenumber":"6",
    "addr:postcode":"8918",
    "addr:street":"Berghofstrasse",
    "iso:country":"CH",
    "sg:address":"Berghofstrasse 6",
    "sg:city":"Unterlunkhofen",
    "sg:orig_category":"Datenverarbeitungsdienste Sonstige mit der Informatik verbundene T\u00e4tigkeiten",
    "sg:phone":"+41 56 640 11 01",
    "sg:postcode":"8918",
    "sg:province":"Aargau",
    "wof:name":"Colcom Gmbh",
    "wof:placetype":"venue"
},
  "geometry": {"coordinates":[8.382073,47.322132],"type":"Point"}
}