{
  "type": "Feature",
  "properties": {
    "addr:full":"Stockerstr. 43 Z\u00fcrich 8039",
    "addr:housenumber":"43",
    "addr:postcode":"8039",
    "addr:street":"Stockerstr.",
    "iso:country":"CH",
    "sg:address":"Stockerstr. 43",
    "sg:city":"Z\u00fcrich",
    "sg:classifiers":[
        {
            "category":"Banks & Credit Unions",
            "subcategory":"Bank",
            "type":"Services"
        }
    ],
    "sg:postcode":"8039",
    "wof:name":"Winterthur Columna",
    "wof:placetype":"venue"
},
  "geometry": {"coordinates":[8.53955,47.37706],"type":"Point"}
}