{
  "type": "Feature",
  "properties": {
    "iso:country":"CH",
    "sg:address":"Im Gapetsch 50 9494 Schaan. Postfach 522",
    "sg:city":"Schaan",
    "sg:orig_category":"Detailhandel mit Radio U Fernsehger\u00e4ten Herstellung von sonstigen elektrischen Ausr\u00fcstungen",
    "sg:phone":"+41 75 233 24 26",
    "sg:postcode":"9494",
    "wof:name":"Elrowa Radio Tv Video Anstalt",
    "wof:placetype":"venue"
},
  "geometry": {"coordinates":[9.5069303513,47.1603813171],"type":"Point"}
}