{
  "type": "Feature",
  "properties": {
    "iso:country":"CH",
    "sg:address":"Bernstrasse 127a",
    "sg:city":"Zollikofen",
    "sg:orig_category":"Detailhandel mit Blumen U Pflanzen",
    "sg:phone":"+41 31 911 30 19",
    "sg:postcode":"3052",
    "sg:province":"Bern",
    "wof:name":"Rothenb\u00fchler Ag Blumengesch\u00e4ft",
    "wof:placetype":"venue"
},
  "geometry": {"coordinates":[7.457896,46.995266],"type":"Point"}
}