{
  "type": "Feature",
  "properties": {
    "iso:country":"CH",
    "sg:address":"Meisenweg 22",
    "sg:city":"Obergerlafingen",
    "sg:orig_category":"Fahrschulen, Flugschulen",
    "sg:phone":"+41 32 675 41 51",
    "sg:postcode":"4564",
    "sg:province":"Bern",
    "wof:name":"Fahrschule Koch & Co",
    "wof:placetype":"venue"
},
  "geometry": {"coordinates":[7.5868520737,47.1657028198],"type":"Point"}
}