{
  "type": "Feature",
  "properties": {
    "iso:country":"CH",
    "sg:address":"Silbergasse 18",
    "sg:city":"Biel/bienne",
    "sg:orig_category":"Wirtschaftspr\u00fcfung, Steuerberatung U Treuhand",
    "sg:phone":"+41 32 323 05 53",
    "sg:postcode":"2502",
    "sg:province":"Bern",
    "wof:name":"Fiblas Gmbh",
    "wof:placetype":"venue"
},
  "geometry": {"coordinates":[7.2462000847,47.133895874],"type":"Point"}
}