{
  "type": "Feature",
  "properties": {
    "iso:country":"CH",
    "sg:address":"Klingellochweg 14",
    "sg:city":"Lupsingen",
    "sg:orig_category":"Vermietung U Verpachtung von eigenen Immobilien",
    "sg:postcode":"4419",
    "sg:province":"Basel-Landschaft",
    "wof:name":"Gr\u00fcenmatt Ag",
    "wof:placetype":"venue"
},
  "geometry": {"coordinates":[7.6873559952,47.4456291199],"type":"Point"}
}