{
  "type": "Feature",
  "properties": {
    "iso:country":"CH",
    "sg:address":"Im Pantloo 4",
    "sg:city":"D\u00fcbendorf",
    "sg:orig_category":"Sportvereine Unihockey",
    "sg:postcode":"8600",
    "sg:province":"Z\u00fcrich",
    "wof:name":"Uht Lc Rapperswil-jona",
    "wof:placetype":"venue"
},
  "geometry": {"coordinates":[8.8296089172,47.2211685181],"type":"Point"}
}