{
  "type": "Feature",
  "properties": {
    "iso:country":"CH",
    "sg:address":"7204",
    "sg:city":"Untervaz",
    "sg:orig_category":"Unternehmensberatung",
    "sg:postcode":"7204",
    "sg:province":"Graubunden",
    "wof:name":"Grms Graf Reinigung Management Service",
    "wof:placetype":"venue"
},
  "geometry": {"coordinates":[8.3144178391,47.1317214966],"type":"Point"}
}