{
  "type": "Feature",
  "properties": {
    "addr:full":"Mengestorferstrasse 54 Gasel Bern 3144",
    "addr:housenumber":"54",
    "addr:postcode":"3144",
    "addr:street":"Mengestorferstrasse",
    "iso:country":"CH",
    "sg:address":"Mengestorferstrasse 54",
    "sg:city":"Gasel",
    "sg:orig_category":"Bauingenieurb\u00fcros Heizung L\u00fcftung Klima",
    "sg:phone":"+41 31 351 53 03",
    "sg:postcode":"3144",
    "sg:province":"Bern",
    "wof:name":"Walter Br\u00f6nnimann Ag Ingenieurb\u00fcro",
    "wof:placetype":"venue"
},
  "geometry": {"coordinates":[7.394201,46.897678],"type":"Point"}
}