{
  "type": "Feature",
  "properties": {
    "iso:country":"CH",
    "sg:address":"Hirschengraben 52",
    "sg:city":"Luzern",
    "sg:orig_category":"Shiatsu-Therapie",
    "sg:phone":"+41 41 240 74 05",
    "sg:postcode":"6003",
    "sg:province":"Luzern",
    "wof:name":"Gabriela Kistler Shiatsu",
    "wof:placetype":"venue"
},
  "geometry": {"coordinates":[8.3011484146,47.0510025024],"type":"Point"}
}