{
  "type": "Feature",
  "properties": {
    "iso:country":"CH",
    "sg:address":"Alte Uznabergstrasse 15",
    "sg:city":"Uznach",
    "sg:classifiers":[
        {
            "category":"Restaurant",
            "type":"Food & Drink"
        }
    ],
    "sg:phone":"+41 55 282 28 17",
    "sg:postcode":"8730",
    "sg:province":"St. Gallen",
    "wof:name":"Gasthaus Felsenburg",
    "wof:placetype":"venue"
},
  "geometry": {"coordinates":[8.9587221146,47.2314033508],"type":"Point"}
}