{
  "type": "Feature",
  "properties": {
    "iso:country":"CH",
    "sg:address":"Jerisberghof 124",
    "sg:city":"Gurbr\u00fc",
    "sg:orig_category":"Buchf\u00fchrung Wirtschaftspr\u00fcfung, Steuerberatung U Treuhand",
    "sg:phone":"+41 31 755 60 37",
    "sg:postcode":"3208",
    "sg:province":"Bern",
    "wof:name":"Primus Treuhand Und Beratungs Gmbh",
    "wof:placetype":"venue"
},
  "geometry": {"coordinates":[7.214565,46.964134],"type":"Point"}
}