{
  "type": "Feature",
  "properties": {
    "iso:country":"CH",
    "sg:address":"Hauptstrasse 27",
    "sg:city":"Bronschhofen",
    "sg:classifiers":[
        {
            "category":"Restaurant",
            "type":"Food & Drink"
        }
    ],
    "sg:phone":"+41 71 911 49 75",
    "sg:postcode":"9552",
    "sg:province":"St. Gallen",
    "wof:name":"Restaurant Sch\u00e4fli",
    "wof:placetype":"venue"
},
  "geometry": {"coordinates":[9.0355081558,47.4770851135],"type":"Point"}
}