{
  "type": "Feature",
  "properties": {
    "iso:country":"CH",
    "sg:address":"St. Jakobs-strasse 54",
    "sg:city":"Basel",
    "sg:orig_category":"Unclassifiable Establishments",
    "sg:phone":"+41 61 316 41 11",
    "sg:postcode":"4052",
    "sg:province":"Basel-Stadt",
    "wof:name":"Pirelli Finance (luxembourg) Sa, Luxemburg, Zweigniederlassung Basel",
    "wof:placetype":"venue"
},
  "geometry": {"coordinates":[7.5974397659,47.5485076904],"type":"Point"}
}