{
  "type": "Feature",
  "properties": {
    "iso:country":"CH",
    "sg:address":"Bahnhofstrasse 6",
    "sg:city":"Laufen",
    "sg:orig_category":"Handel mit Automobilen",
    "sg:phone":"+41 61 763 10 35",
    "sg:postcode":"4242",
    "sg:province":"Basel-Landschaft",
    "wof:name":"Happy Rent Ag",
    "wof:placetype":"venue"
},
  "geometry": {"coordinates":[7.5021181107,47.4199562073],"type":"Point"}
}