{
  "type": "Feature",
  "properties": {
    "iso:country":"CH",
    "sg:address":"Avenue De Miremont 33c",
    "sg:city":"Gen\u00e8ve",
    "sg:orig_category":"Geb\u00e4ude, Wohnungsreinigung",
    "sg:phone":"+41 22 702 09 50",
    "sg:postcode":"1206",
    "sg:province":"Gen\u00e8ve",
    "wof:name":"Uns Services Sa Entreprise De Nettoyage",
    "wof:placetype":"venue"
},
  "geometry": {"coordinates":[6.1576929092,46.1889038086],"type":"Point"}
}