{
  "type": "Feature",
  "properties": {
    "iso:country":"CH",
    "sg:address":"6939",
    "sg:city":"Arosio",
    "sg:orig_category":"Vorschulen, Kinderg\u00e4rten",
    "sg:postcode":"6939",
    "sg:province":"Ticino",
    "wof:name":"Scuola Materna",
    "wof:placetype":"venue"
},
  "geometry": {"coordinates":[8.9027500153,46.0467605591],"type":"Point"}
}