{
  "type": "Feature",
  "properties": {
    "addr:full":"Schauplatzgasse 29 Bern Bern 3011",
    "addr:housenumber":"29",
    "addr:postcode":"3011",
    "addr:street":"Schauplatzgasse",
    "iso:country":"CH",
    "sg:address":"Schauplatzgasse 29",
    "sg:city":"Bern",
    "sg:orig_category":"Detailhandel mit Brot, Back U S\u00fcsswaren",
    "sg:phone":"+41 31 311 71 80",
    "sg:postcode":"3011",
    "sg:province":"Bern",
    "wof:name":"Storchenb\u00e4ckerei Keller Ag",
    "wof:placetype":"venue"
},
  "geometry": {"coordinates":[7.442082,46.947262],"type":"Point"}
}