{
  "type": "Feature",
  "properties": {
    "iso:country":"CH",
    "sg:address":"Poststrasse 13 8907 Wettswil. Postfach",
    "sg:city":"Wettswil",
    "sg:orig_category":"Unclassifiable Establishments",
    "sg:postcode":"8907",
    "sg:province":"Z\u00fcrich",
    "wof:name":"Digital Hug Multimediawerkstatt. Dienstleistungen Im Bereich Der Neuen Medien",
    "wof:placetype":"venue"
},
  "geometry": {"coordinates":[8.471824646,47.3399810791],"type":"Point"}
}