{
  "type": "Feature",
  "properties": {
    "iso:country":"CH",
    "sg:address":"Bodenmattstrasse 2",
    "sg:city":"Geuensee",
    "sg:orig_category":"Einbau von Schreinerwaren Innenausbau",
    "sg:phone":"+41 79 635 95 75",
    "sg:postcode":"6232",
    "sg:province":"Luzern",
    "wof:name":"Fredy Fischer K\u00fcchen-& Innenausbau",
    "wof:placetype":"venue"
},
  "geometry": {"coordinates":[8.1131095886,47.1984291077],"type":"Point"}
}