{
  "type": "Feature",
  "properties": {
    "iso:country":"CH",
    "sg:address":"Dahlienweg 2",
    "sg:city":"Aefligen",
    "sg:orig_category":"Vermietung U Verpachtung von eigenen Immobilien Vermittlung von Immobilien",
    "sg:phone":"+41 61 825 61 11",
    "sg:postcode":"3426",
    "sg:province":"Bern",
    "wof:name":"Buss Immobilien Und Service Ag",
    "wof:placetype":"venue"
},
  "geometry": {"coordinates":[7.6920809746,47.5255203247],"type":"Point"}
}