{
  "type": "Feature",
  "properties": {
    "iso:country":"CH",
    "sg:address":"Bd. De Grancy 19a",
    "sg:city":"Lausanne",
    "sg:orig_category":"Fachdetailhandel in Verkaufsr\u00e4umen",
    "sg:phone":"+41 21 616 96 85",
    "sg:postcode":"1000",
    "sg:province":"Vaud",
    "wof:name":"Vica S\u00e0rl",
    "wof:placetype":"venue"
},
  "geometry": {"coordinates":[6.6293449402,46.515247345],"type":"Point"}
}