{
  "type": "Feature",
  "properties": {
    "iso:country":"CH",
    "sg:address":"Wildensteinerstrasse 26 4416 Bubendorf. Postfach",
    "sg:city":"Bubendorf",
    "sg:orig_category":"Wohnheime",
    "sg:postcode":"4416",
    "sg:province":"Basel-Landschaft",
    "wof:name":"Stiftung Wohn Und Pflegeheim Am Weiher",
    "wof:placetype":"venue"
},
  "geometry": {"coordinates":[7.7357258797,47.4433097839],"type":"Point"}
}