{
  "type": "Feature",
  "properties": {
    "iso:country":"CH",
    "sg:address":"H\u00fcrdweg 10",
    "sg:city":"Galgenen",
    "sg:orig_category":"Herstellung von sonstigen chemischen Erzeugnissen",
    "sg:phone":"+41 55 460 12 13",
    "sg:postcode":"8854",
    "sg:province":"Schwyz",
    "wof:name":"Triatec Marketing-services, Rolf Schmidh\u00e4usler",
    "wof:placetype":"venue"
},
  "geometry": {"coordinates":[8.8772859573,47.1755905151],"type":"Point"}
}