{
  "type": "Feature",
  "properties": {
    "iso:country":"CH",
    "sg:address":"Sinserstrasse",
    "sg:city":"Hagendorn",
    "sg:orig_category":"Instandhaltung U Reparatur von Automobilen",
    "sg:phone":"+41 41 780 22 33",
    "sg:postcode":"6332",
    "sg:province":"Zug",
    "wof:name":"D + A Carrosserie Ag",
    "wof:placetype":"venue"
},
  "geometry": {"coordinates":[8.4322710037,47.2035140991],"type":"Point"}
}