{
  "type": "Feature",
  "properties": {
    "iso:country":"CH",
    "sg:address":"Vert Chemin 33",
    "sg:city":"Corsier-sur-vevey",
    "sg:orig_category":"RESTAURANTS: TEA-ROOMS",
    "sg:postcode":"1804",
    "sg:province":"Vaud",
    "wof:name":"Darest S\u00e0rl",
    "wof:placetype":"venue"
},
  "geometry": {"coordinates":[6.8414001465,46.4704856873],"type":"Point"}
}