{
  "type": "Feature",
  "properties": {
    "iso:country":"CH",
    "sg:address":"Im Feld 196k",
    "sg:city":"Schiers",
    "sg:orig_category":"Wirtschafts- and Arbeitgeberverb\u00e4nde",
    "sg:phone":"+41 81 328 22 37",
    "sg:postcode":"7220",
    "sg:province":"Graubunden",
    "wof:name":"Gewerbeverein Schiers",
    "wof:placetype":"venue"
},
  "geometry": {"coordinates":[9.6870222092,46.9697189331],"type":"Point"}
}