{
  "type": "Feature",
  "properties": {
    "addr:full":"Guisan Av. Du G\u00e9n\u00e9ral 2 3960 Sierre Case Postale 21 Sierre Valais 3960",
    "addr:housenumber":"2;21",
    "addr:postcode":"3960;3960",
    "addr:street":"Guisan Av. Du Ge\u0301Ne\u0301Ral;Postale",
    "iso:country":"CH",
    "sg:address":"Guisan Av. Du G\u00e9n\u00e9ral 2 3960 Sierre Case Postale 21",
    "sg:city":"Sierre",
    "sg:orig_category":"Allgemeinbildende weiterf\u00fchrende Schulen",
    "sg:phone":"+41 27 456 33 88",
    "sg:postcode":"3960",
    "sg:province":"Valais",
    "wof:name":"Ecole Alpha, Bienvenu Lanzi",
    "wof:placetype":"venue"
},
  "geometry": {"coordinates":[7.532137,46.292854],"type":"Point"}
}