{
  "type": "Feature",
  "properties": {
    "iso:country":"CH",
    "sg:address":"Klosterstrasse 3 6390 Engelberg. Postfach",
    "sg:city":"Engelberg",
    "sg:orig_category":"Sonstige Kultur U Unterhaltungseinrichtungen",
    "sg:postcode":"6390",
    "sg:province":"Obwalden",
    "wof:name":"Casino Davos Ag",
    "wof:placetype":"venue"
},
  "geometry": {"coordinates":[9.8220462799,46.7973747253],"type":"Point"}
}