{
  "type": "Feature",
  "properties": {
    "iso:country":"CH",
    "sg:address":"Augustinergasse 44",
    "sg:city":"Z\u00fcrich",
    "sg:orig_category":"Kosmetikinstitute",
    "sg:phone":"+41 12115595",
    "sg:postcode":"8001",
    "sg:province":"Z\u00fcrich",
    "wof:name":"Limelight Kosmetik-institut Hiltbrand Therese Kosmetische Behandlungen, Kosmetikprodukteverkauf",
    "wof:placetype":"venue"
},
  "geometry": {"coordinates":[8.5388832092,47.3723831177],"type":"Point"}
}