{
  "type": "Feature",
  "properties": {
    "addr:full":"Im Guet 1 Rafz Z\u00fcrich 8197",
    "addr:housenumber":"1",
    "addr:postcode":"8197",
    "addr:street":"Im Guet",
    "iso:country":"CH",
    "sg:address":"Im Guet 1",
    "sg:city":"Rafz",
    "sg:orig_category":"Allgemeiner Hoch U Tiefbau Strassenbau",
    "sg:phone":"+41 71 385 15 74",
    "sg:postcode":"8197",
    "sg:province":"Z\u00fcrich",
    "wof:name":"Alder Toni Ag",
    "wof:placetype":"venue"
},
  "geometry": {"coordinates":[9.256072,47.416073],"type":"Point"}
}