{
  "type": "Feature",
  "properties": {
    "iso:country":"CH",
    "sg:address":"L\u00f6wenstrasse 40",
    "sg:city":"Z\u00fcrich",
    "sg:orig_category":"Sonstige mit der Informatik verbundene T\u00e4tigkeiten",
    "sg:postcode":"8001",
    "sg:province":"Z\u00fcrich",
    "wof:name":"Adp Network Services International Inc Wilmington Delaware Usa Zweigniederlassung Z\u00fcrich Edv-dienstleistungen Usw",
    "wof:placetype":"venue"
},
  "geometry": {"coordinates":[8.5364398956,47.3749351501],"type":"Point"}
}