{
  "type": "Feature",
  "properties": {
    "iso:country":"CH",
    "sg:address":"Solothurnerstrasse 14",
    "sg:city":"H\u00e4gendorf",
    "sg:orig_category":"Fachdetailhandel in Verkaufsr\u00e4umen Handelsvermittlung U Grosshandel",
    "sg:phone":"+41 62 216 33 82",
    "sg:postcode":"4614",
    "sg:province":"Solothurn",
    "wof:name":"Heba Sport Baumgartner Heinz",
    "wof:placetype":"venue"
},
  "geometry": {"coordinates":[7.8411750793,47.3323097229],"type":"Point"}
}