{
  "type": "Feature",
  "properties": {
    "iso:country":"CH",
    "sg:address":"Im Oberdorf 52",
    "sg:city":"Eptingen",
    "sg:orig_category":"Architektur U Ingenieurb\u00fcros",
    "sg:phone":"+41 19722690",
    "sg:postcode":"4458",
    "sg:province":"Basel-Landschaft",
    "wof:name":"Egli Ingenieurtechnik Gmbh",
    "wof:placetype":"venue"
},
  "geometry": {"coordinates":[8.792745,47.319801],"type":"Point"}
}