{
  "type": "Feature",
  "properties": {
    "iso:country":"CH",
    "sg:address":"Bachtalen 6332 Hagendorn. Postfach",
    "sg:city":"Zug",
    "sg:orig_category":"Erbringung von Dienstleistungen f\u00fcr Unternehmen",
    "sg:postcode":"6300",
    "sg:province":"Zug",
    "wof:name":"Dimetis (schweiz) Ag Ger\u00e4te, Dienstl. Auf D. Gebiet D. Informationstechnologie Usw.; Vertreib, Handel, Entwicklung, Realisierung, Service",
    "wof:placetype":"venue"
},
  "geometry": {"coordinates":[8.4375801086,47.2078552246],"type":"Point"}
}