{
  "type": "Feature",
  "properties": {
    "iso:country":"CH",
    "sg:address":"R\u00e4ben\u00e4cker 4",
    "sg:city":"T\u00e4gerig",
    "sg:orig_category":"Grosshandel mit Bekleidung Handels-H\u00e4user U Gesellschaften",
    "sg:phone":"+41 17864949",
    "sg:postcode":"5522",
    "sg:province":"Aargau",
    "wof:name":"Inter Selection Ag",
    "wof:placetype":"venue"
},
  "geometry": {"coordinates":[8.7429885864,47.1981811523],"type":"Point"}
}