{
  "type": "Feature",
  "properties": {
    "iso:country":"CH",
    "sg:address":"Gartenweg 14",
    "sg:city":"Berikon",
    "sg:orig_category":"Institutionen f\u00fcr Finanzierungsleasing",
    "sg:phone":"+41 56 633 74 35",
    "sg:postcode":"8965",
    "sg:province":"Aargau",
    "wof:name":"As Leasing-agentur A. Studer",
    "wof:placetype":"venue"
},
  "geometry": {"coordinates":[8.3653450012,47.3609008789],"type":"Point"}
}