{
  "type": "Feature",
  "properties": {
    "iso:country":"CH",
    "sg:address":"Hauptstr.",
    "sg:city":"Wimmis",
    "sg:classifiers":[
        {
            "category":"Banks & Credit Unions",
            "subcategory":"Bank",
            "type":"Services"
        }
    ],
    "sg:phone":"+41 71 737 80 40",
    "sg:postcode":"3752",
    "sg:province":"Bern",
    "wof:name":"Raiffeisenbank Diepoldsau-schmitter",
    "wof:placetype":"venue"
},
  "geometry": {"coordinates":[9.656539,47.384804],"type":"Point"}
}