{
  "type": "Feature",
  "properties": {
    "iso:country":"CH",
    "sg:address":"Hintere Kirchstrasse 3a",
    "sg:city":"Diepoldsau",
    "sg:orig_category":"Patentverwertung Rechtsberatung",
    "sg:phone":"+41 71 730 03 12",
    "sg:postcode":"9444",
    "sg:province":"St. Gallen",
    "wof:name":"Adico Ag",
    "wof:placetype":"venue"
},
  "geometry": {"coordinates":[9.6567935944,47.385799408],"type":"Point"}
}