{
  "type": "Feature",
  "properties": {
    "iso:country":"CH",
    "sg:address":"Hegenheimermattweg 50",
    "sg:city":"Allschwil",
    "sg:classifiers":[
        {
            "category":"Manufacturing",
            "subcategory":"Printing",
            "type":"Manufacturing & Wholesale Goods"
        }
    ],
    "sg:phone":"+41 61 486 84 84",
    "sg:postcode":"4123",
    "sg:province":"Basel-Landschaft",
    "sg:tags":[
        "publishing"
    ],
    "wof:name":"Neue Schwitter Ag",
    "wof:placetype":"venue"
},
  "geometry": {"coordinates":[7.542383194,47.554233551],"type":"Point"}
}