{
  "type": "Feature",
  "properties": {
    "iso:country":"CH",
    "sg:address":"D\u00f6ltschihalde 35 8055 Z\u00fcrich. Postfach",
    "sg:city":"Z\u00fcrich",
    "sg:orig_category":"Markt U Meinungsforschung",
    "sg:phone":"+41 14517111",
    "sg:postcode":"8055",
    "sg:province":"Z\u00fcrich",
    "wof:name":"B\u00fctikofer Ruth, Marketing Mit Wirkungen & Nebenwirkungen",
    "wof:placetype":"venue"
},
  "geometry": {"coordinates":[8.4976301193,47.3636360168],"type":"Point"}
}