{
  "type": "Feature",
  "properties": {
    "iso:country":"CH",
    "sg:address":"Vierjuchartenweg 8 4125 Riehen. Postfach",
    "sg:city":"Riehen",
    "sg:orig_category":"Softwareentwicklung U beratung",
    "sg:postcode":"4125",
    "sg:province":"Basel-Stadt",
    "wof:name":"E-data Hertig Dienstleistungen Im Computerbereich, Bes. Software-entwicklung, Web-design Usw",
    "wof:placetype":"venue"
},
  "geometry": {"coordinates":[7.6437168121,47.5737380981],"type":"Point"}
}