{
  "type": "Feature",
  "properties": {
    "iso:country":"CH",
    "sg:address":"Rue Xavier Stockmar 8",
    "sg:city":"Porrentruy",
    "sg:orig_category":"Non-Classified Establishments",
    "sg:postcode":"2900",
    "sg:province":"Jura",
    "wof:name":"Marbrerie Laville Sa",
    "wof:placetype":"venue"
},
  "geometry": {"coordinates":[7.078458786,47.4214897156],"type":"Point"}
}