{
  "type": "Feature",
  "properties": {
    "iso:country":"CH",
    "sg:address":"Kreuzlingerstrasse 35",
    "sg:city":"Romanshorn",
    "sg:orig_category":"Detailhandel mit Metallwaren, Anstrichmitteln, Glaswaren, Bau U Heimwerkerbedarf",
    "sg:postcode":"8590",
    "sg:province":"Thurgau",
    "wof:name":"Birotex Ag",
    "wof:placetype":"venue"
},
  "geometry": {"coordinates":[9.6370582581,47.428855896],"type":"Point"}
}