{
  "type": "Feature",
  "properties": {
    "iso:country":"CH",
    "sg:address":"Kantonsstrasse 102 8807 Freienbach. Postfach",
    "sg:city":"Freienbach",
    "sg:orig_category":"Kantonalbanken",
    "sg:phone":"+41 55 410 30 33",
    "sg:postcode":"8807",
    "sg:province":"Schwyz",
    "wof:name":"Schwyzer Kantonalbank",
    "wof:placetype":"venue"
},
  "geometry": {"coordinates":[8.7572393417,47.2058105469],"type":"Point"}
}