{
  "type": "Feature",
  "properties": {
    "iso:country":"CH",
    "sg:address":"Griesbach",
    "sg:city":"Schaffhausen",
    "sg:orig_category":"Landw. Genossenschaften Viehzucht",
    "sg:postcode":"8200",
    "sg:province":"Schaffhausen",
    "wof:name":"Viehzuchtgenossenschaft Schaffhausen & Umgebung",
    "wof:placetype":"venue"
},
  "geometry": {"coordinates":[8.608042717,47.7161026001],"type":"Point"}
}