{
  "type": "Feature",
  "properties": {
    "iso:country":"CH",
    "sg:address":"Dorfstrasse 28",
    "sg:city":"Oberhelfenschwil",
    "sg:orig_category":"Gartenbau",
    "sg:phone":"+41 71 374 33 30",
    "sg:postcode":"9621",
    "sg:province":"St. Gallen",
    "wof:name":"Bruno Jud Gartenbau",
    "wof:placetype":"venue"
},
  "geometry": {"coordinates":[9.1116094589,47.3567085266],"type":"Point"}
}