{
  "type": "Feature",
  "properties": {
    "iso:country":"CH",
    "sg:address":"Spitalweg 23.",
    "sg:city":"Brig",
    "sg:orig_category":"Betrieb U technische Hilfsdienste des Kultur U Unterhaltungswesens",
    "sg:postcode":"3900",
    "sg:province":"Valais",
    "wof:name":"Tonstudio Magnani Ermano.",
    "wof:placetype":"venue"
},
  "geometry": {"coordinates":[7.98134,46.318134],"type":"Point"}
}