{
  "type": "Feature",
  "properties": {
    "iso:country":"CH",
    "sg:address":"Schwanden 56",
    "sg:city":"Sch\u00fcpfen",
    "sg:orig_category":"Herstellung von Duft U K\u00f6rperpflegemitteln",
    "sg:phone":"+41 31 879 13 57",
    "sg:postcode":"3054",
    "sg:province":"Bern",
    "wof:name":"Crevo Vogelsanger Hermann",
    "wof:placetype":"venue"
},
  "geometry": {"coordinates":[7.4020261765,47.0393753052],"type":"Point"}
}