{
  "type": "Feature",
  "properties": {
    "iso:country":"CH",
    "sg:address":"Hirschenplatz 1 6215 Berom\u00fcnster. Postfach",
    "sg:city":"Berom\u00fcnster",
    "sg:classifiers":[
        {
            "category":"Insurance",
            "subcategory":"Insurance Agent",
            "type":"Services"
        }
    ],
    "sg:phone":"+41 41 930 20 77",
    "sg:postcode":"6215",
    "sg:province":"Luzern",
    "sg:tags":[
        "versicherungsagenturen",
        "-broker"
    ],
    "wof:name":"Winterthur Versicherungen Agentur",
    "wof:placetype":"venue"
},
  "geometry": {"coordinates":[8.191037178,47.205696106],"type":"Point"}
}