{
  "type": "Feature",
  "properties": {
    "iso:country":"CH",
    "sg:address":"R\u00fctiweg 21",
    "sg:city":"Uster",
    "sg:orig_category":"Sportvereine Ballsport Volleyball",
    "sg:phone":"+41 19413350",
    "sg:postcode":"8610",
    "sg:province":"Z\u00fcrich",
    "wof:name":"Volleyball-club Sc Greifensee",
    "wof:placetype":"venue"
},
  "geometry": {"coordinates":[8.703458786,47.3524131775],"type":"Point"}
}