{
  "type": "Feature",
  "properties": {
    "iso:country":"CH",
    "sg:address":"Centro Magro",
    "sg:city":"Uvrier",
    "sg:orig_category":"Detailhandel mit Schuhen Detailhandel mit Sportartikeln",
    "sg:phone":"+41 27 203 27 02",
    "sg:postcode":"1958",
    "sg:province":"Valais",
    "wof:name":"Dosenbach Chaussures & Sport",
    "wof:placetype":"venue"
},
  "geometry": {"coordinates":[7.4179301262,46.2533912659],"type":"Point"}
}