{
  "type": "Feature",
  "properties": {
    "iso:country":"CH",
    "sg:address":"Lerchenfeldstrasse 38",
    "sg:city":"Thun",
    "sg:orig_category":"Detailhandel mit Brot, Back U S\u00fcsswaren",
    "sg:phone":"+41 33 222 14 10",
    "sg:postcode":"3603",
    "sg:province":"Bern",
    "wof:name":"Kurt Herrmann",
    "wof:placetype":"venue"
},
  "geometry": {"coordinates":[7.601307,46.765503],"type":"Point"}
}