{
  "type": "Feature",
  "properties": {
    "iso:country":"CH",
    "sg:address":"Place Saint-jean 136",
    "sg:city":"Montfaucon",
    "sg:orig_category":"Detailhandel mit Fleisch U Fleischwaren",
    "sg:phone":"+41 32 955 10 65",
    "sg:postcode":"2875",
    "sg:province":"Jura",
    "wof:name":"P\u00e9quignot Georges",
    "wof:placetype":"venue"
},
  "geometry": {"coordinates":[7.0504508018,47.2826080322],"type":"Point"}
}