{
  "type": "Feature",
  "properties": {
    "iso:country":"CH",
    "sg:address":"Sennweidstrasse 45 6300 Zug. Postfach 5352",
    "sg:city":"Zug",
    "sg:orig_category":"Herstellung von sonstigen elektrischen Ausr\u00fcstungen",
    "sg:phone":"+41 41 748 16 00",
    "sg:postcode":"6300",
    "sg:province":"Zug",
    "wof:name":"Sensormatic Ag",
    "wof:placetype":"venue"
},
  "geometry": {"coordinates":[8.5162153244,47.1715087891],"type":"Point"}
}