{
  "type": "Feature",
  "properties": {
    "iso:country":"CH",
    "sg:address":"Lacs Rue Des 27",
    "sg:city":"Sierre",
    "sg:orig_category":"RESTAURANTS: TEA-ROOMS",
    "sg:postcode":"3960",
    "sg:province":"Valais",
    "wof:name":"Freudiger-lehmann Reinhold",
    "wof:placetype":"venue"
},
  "geometry": {"coordinates":[7.5306549072,46.2924041748],"type":"Point"}
}