{
  "type": "Feature",
  "properties": {
    "iso:country":"CH",
    "sg:address":"Bahnhofstrasse 6 3700 Spiez. Postfach 269",
    "sg:city":"Spiez",
    "sg:orig_category":"Detailhandel mit Getr\u00e4nken Grosshandel mit Getr\u00e4nken",
    "sg:phone":"+41 33 654 30 60",
    "sg:postcode":"3700",
    "sg:province":"Bern",
    "wof:name":"Rubin Ag Spiez",
    "wof:placetype":"venue"
},
  "geometry": {"coordinates":[7.6756110191,46.6890335083],"type":"Point"}
}