{
  "type": "Feature",
  "properties": {
    "iso:country":"CH",
    "sg:address":"3556",
    "sg:city":"Trub",
    "sg:orig_category":"Schulpflegen",
    "sg:phone":"+41 34 495 56 47",
    "sg:postcode":"3556",
    "sg:province":"Bern",
    "wof:name":"Primarschulkommission Der Gemeinde Trub",
    "wof:placetype":"venue"
},
  "geometry": {"coordinates":[7.8767929077,46.9407653809],"type":"Point"}
}