{
  "type": "Feature",
  "properties": {
    "iso:country":"CH",
    "sg:address":"Im Rietacker 2",
    "sg:city":"Schaan",
    "sg:orig_category":"Solarien",
    "sg:phone":"+41 32 931 02 26",
    "sg:postcode":"9494",
    "wof:name":"Solarium Soleil Des Tropiques",
    "wof:placetype":"venue"
},
  "geometry": {"coordinates":[6.7502551079,47.0580596924],"type":"Point"}
}