{
  "type": "Feature",
  "properties": {
    "iso:country":"CH",
    "sg:address":"Z\u00fcrcherstrasse 7",
    "sg:city":"Oberengstringen",
    "sg:orig_category":"Fachdetailhandel in Verkaufsr\u00e4umen",
    "sg:phone":"+41 17506750",
    "sg:postcode":"8102",
    "sg:province":"Z\u00fcrich",
    "wof:name":"Blue Moon Betriebs Ag",
    "wof:placetype":"venue"
},
  "geometry": {"coordinates":[8.4764471054,47.4051704407],"type":"Point"}
}