{
  "type": "Feature",
  "properties": {
    "iso:country":"CH",
    "sg:address":"Schulhausstrasse 4",
    "sg:city":"Grabs",
    "sg:orig_category":"Handel mit Motorr\u00e4dern, Teilen U Zubeh\u00f6r Herstellung von Fahrr\u00e4dern Instandhaltung U Reparatur von M",
    "sg:phone":"+41 81 771 70 58",
    "sg:postcode":"9472",
    "sg:province":"St. Gallen",
    "wof:name":"Rt Bike Tech Gmbh Zweirad-gesch\u00e4ft",
    "wof:placetype":"venue"
},
  "geometry": {"coordinates":[9.4460601807,47.1802024841],"type":"Point"}
}