{
  "type": "Feature",
  "properties": {
    "iso:country":"CH",
    "sg:address":"Bergen",
    "sg:city":"Engi",
    "sg:orig_category":"Blumen U Zierpflanzenbau",
    "sg:phone":"+41 79 407 80 16",
    "sg:postcode":"8765",
    "sg:province":"Glarus",
    "wof:name":"Hans B\u00e4bler Gartenbau & G\u00e4rtnerei",
    "wof:placetype":"venue"
},
  "geometry": {"coordinates":[9.151501,46.98539],"type":"Point"}
}