{
  "type": "Feature",
  "properties": {
    "iso:country":"CH",
    "sg:address":"Schulhausstrasse 28",
    "sg:city":"Villmergen",
    "sg:classifiers":[
        {
            "category":"Restaurant",
            "type":"Food & Drink"
        }
    ],
    "sg:phone":"+41 26 322 58 04",
    "sg:postcode":"5612",
    "sg:province":"Aargau",
    "wof:name":"Restaurant Frohmatt",
    "wof:placetype":"venue"
},
  "geometry": {"coordinates":[7.2025809288,46.7855529785],"type":"Point"}
}