{
  "type": "Feature",
  "properties": {
    "iso:country":"CH",
    "sg:address":"Bahnhofstrasse 6",
    "sg:city":"Ins",
    "sg:orig_category":"RESTAURANTS: TEA-ROOMS",
    "sg:phone":"+41 32 313 32 94",
    "sg:postcode":"3232",
    "sg:province":"Bern",
    "wof:name":"Caf\u00e9 M\u00fcnz",
    "wof:placetype":"venue"
},
  "geometry": {"coordinates":[7.1038107872,47.005821228],"type":"Point"}
}