{
  "type": "Feature",
  "properties": {
    "iso:country":"CH",
    "sg:address":"Albisstrasse 13",
    "sg:city":"Baar",
    "sg:orig_category":"Architektur U Ingenieurb\u00fcros",
    "sg:phone":"+41 41 760 60 20",
    "sg:postcode":"6340",
    "sg:province":"Zug",
    "wof:name":"Id Casa Gmbh",
    "wof:placetype":"venue"
},
  "geometry": {"coordinates":[8.524926,47.198215],"type":"Point"}
}