{
  "type": "Feature",
  "properties": {
    "iso:country":"CH",
    "sg:address":"Gansacherweg 3",
    "sg:city":"Gelterkinden",
    "sg:orig_category":"Vereine Musik/Blasmusik",
    "sg:phone":"+41 61 981 24 74",
    "sg:postcode":"4460",
    "sg:province":"Basel-Landschaft",
    "wof:name":"Musikverein Sissach",
    "wof:placetype":"venue"
},
  "geometry": {"coordinates":[7.8585329056,47.4634284973],"type":"Point"}
}