{
  "type": "Feature",
  "properties": {
    "iso:country":"CH",
    "sg:address":"Schwantlen",
    "sg:city":"Ebnat-kappel",
    "sg:orig_category":"Tierheime",
    "sg:phone":"+41 71 993 38 66",
    "sg:postcode":"9642",
    "sg:province":"St. Gallen",
    "wof:name":"Claude Schmid Hundepension",
    "wof:placetype":"venue"
},
  "geometry": {"coordinates":[9.1316318512,47.258731842],"type":"Point"}
}