{
  "type": "Feature",
  "properties": {
    "iso:country":"CH",
    "sg:address":"Galil\u00e9e Rue 15",
    "sg:city":"Yverdon-les-bains",
    "sg:orig_category":"Softwareentwicklung U beratung",
    "sg:postcode":"1400",
    "sg:province":"Vaud",
    "wof:name":"Formation Et Information Aux Technologies Sa F.i.t.",
    "wof:placetype":"venue"
},
  "geometry": {"coordinates":[6.6464729309,46.7649497986],"type":"Point"}
}