{
  "type": "Feature",
  "properties": {
    "iso:country":"CH",
    "sg:address":"Landhausweg 6 5742 K\u00f6lliken. Postfach",
    "sg:city":"K\u00f6lliken",
    "sg:orig_category":"Allgemeiner Hoch U Tiefbau",
    "sg:phone":"+41 62 723 65 20",
    "sg:postcode":"5742",
    "sg:province":"Aargau",
    "wof:name":"Suter Heinz Hallen + Zelte Party- U. Grosszelte Usw.; Handel",
    "wof:placetype":"venue"
},
  "geometry": {"coordinates":[8.018129,47.334988],"type":"Point"}
}