{
  "type": "Feature",
  "properties": {
    "iso:country":"CH",
    "sg:address":"Kantonsstrasse 14",
    "sg:city":"Visp",
    "sg:orig_category":"Gesundheitswesen",
    "sg:postcode":"3930",
    "sg:province":"Valais",
    "wof:name":"Physiotherapie Albrecht",
    "wof:placetype":"venue"
},
  "geometry": {"coordinates":[7.8827219009,46.2920951843],"type":"Point"}
}