{
  "type": "Feature",
  "properties": {
    "iso:country":"CH",
    "sg:address":"Sch\u00f6nb\u00fchlstrand 25",
    "sg:city":"Luzern",
    "sg:orig_category":"Technische B\u00fcros",
    "sg:phone":"+41 52 383 37 87",
    "sg:postcode":"6005",
    "sg:province":"Luzern",
    "wof:name":"Krzyztof Denus Technisches B\u00fcro",
    "wof:placetype":"venue"
},
  "geometry": {"coordinates":[8.8219041824,47.4443893433],"type":"Point"}
}