{
  "type": "Feature",
  "properties": {
    "iso:country":"CH",
    "sg:address":"Linseb\u00fchlstrasse 32",
    "sg:city":"St.gallen",
    "sg:orig_category":"Non-Classified Establishments",
    "sg:postcode":"9000",
    "sg:province":"St. Gallen",
    "wof:name":"A. P. Andrews Gmbh",
    "wof:placetype":"venue"
},
  "geometry": {"coordinates":[9.3820791245,47.4244537354],"type":"Point"}
}