{
  "type": "Feature",
  "properties": {
    "iso:country":"CH",
    "sg:address":"Schindelacker 124 3128 R\u00fcmligen. Postfach",
    "sg:city":"R\u00fcmligen",
    "sg:classifiers":[
        {
            "category":"Travel",
            "subcategory":"Hotels & Motels",
            "type":"Entertainment"
        }
    ],
    "sg:phone":"+41 33 821 04 44",
    "sg:postcode":"3128",
    "sg:province":"Bern",
    "sg:tags":[
        "hotels",
        "mit",
        "restaurant"
    ],
    "wof:name":"Villa Unspunnen Ag",
    "wof:placetype":"venue"
},
  "geometry": {"coordinates":[7.498254776,46.8307495117],"type":"Point"}
}