{
  "type": "Feature",
  "properties": {
    "iso:country":"CH",
    "sg:address":"Turnhallestrasse 16/20",
    "sg:city":"Aarwangen",
    "sg:orig_category":"Primarschulen",
    "sg:phone":"+41 62 922 67 70",
    "sg:postcode":"4912",
    "sg:province":"Bern",
    "wof:name":"Primarschule Sonnhalde",
    "wof:placetype":"venue"
},
  "geometry": {"coordinates":[7.7698869705,47.2366981506],"type":"Point"}
}