{
  "type": "Feature",
  "properties": {
    "iso:country":"CH",
    "sg:address":"Via Luigi Lavizzari 2a",
    "sg:city":"Lugano",
    "sg:orig_category":"Wirtschaftspr\u00fcfung, Steuerberatung U Treuhand",
    "sg:postcode":"6900",
    "sg:province":"Ticino",
    "wof:name":"Faifid Sa",
    "wof:placetype":"venue"
},
  "geometry": {"coordinates":[8.9583902359,46.0060577393],"type":"Point"}
}