{
  "type": "Feature",
  "properties": {
    "iso:country":"CH",
    "sg:address":"Ausserdorfstrasse 1",
    "sg:city":"Pf\u00e4fers",
    "sg:orig_category":"Detailhandel mit Fleisch U Fleischwaren",
    "sg:phone":"+41 81 302 75 70",
    "sg:postcode":"7312",
    "sg:province":"St. Gallen",
    "wof:name":"Thomas Spitz & Karl Schmid St\u00f6rmetzgerei",
    "wof:placetype":"venue"
},
  "geometry": {"coordinates":[9.4996042252,46.988609314],"type":"Point"}
}