{
  "type": "Feature",
  "properties": {
    "iso:country":"CH",
    "sg:address":"Fluhrain",
    "sg:city":"Dieterswil",
    "sg:orig_category":"Wirtschaftspr\u00fcfung, Steuerberatung U Treuhand",
    "sg:postcode":"3256",
    "sg:province":"Bern",
    "wof:name":"Junker Consulting",
    "wof:placetype":"venue"
},
  "geometry": {"coordinates":[7.4488401413,47.0557098389],"type":"Point"}
}