{
  "type": "Feature",
  "properties": {
    "iso:country":"CH",
    "sg:address":"Rue De L'ecluse 30",
    "sg:city":"Neuch\u00e2tel",
    "sg:orig_category":"Gesundheitswesen",
    "sg:phone":"+41 32 723 96 96",
    "sg:postcode":"2000",
    "sg:province":"Neuch\u00e2tel",
    "wof:name":"Irn Institut De Radiologie Neuch\u00e2tel Sa",
    "wof:placetype":"venue"
},
  "geometry": {"coordinates":[6.925962925,46.9928855896],"type":"Point"}
}