{
  "type": "Feature",
  "properties": {
    "iso:country":"CH",
    "sg:address":"Chemin Du Vernand 29",
    "sg:city":"Mont-sur-lausanne",
    "sg:orig_category":"Herstellung von sonstigen landwirtschaftlichen Maschinen Mechanische Werkst\u00e4tten",
    "sg:phone":"+41 21 653 08 70",
    "sg:postcode":"1052",
    "sg:province":"Vaud",
    "wof:name":"Yves Sp\u00e4nhauer Atelier M\u00e9canique",
    "wof:placetype":"venue"
},
  "geometry": {"coordinates":[6.6239771843,46.5682678223],"type":"Point"}
}