{
  "type": "Feature",
  "properties": {
    "iso:country":"CH",
    "sg:address":"Steighalde 1 9404 Rorschacherberg. Postfach",
    "sg:city":"Rorschacherberg",
    "sg:orig_category":"Markt U Meinungsforschung",
    "sg:phone":"+41 56 282 22 10",
    "sg:postcode":"9404",
    "sg:province":"St. Gallen",
    "wof:name":"Bruno Burkart Markethink",
    "wof:placetype":"venue"
},
  "geometry": {"coordinates":[8.2925405502,47.4903907776],"type":"Point"}
}