{
  "type": "Feature",
  "properties": {
    "iso:country":"CH",
    "sg:address":"Via Salici 6",
    "sg:city":"Caslano",
    "sg:orig_category":"Gesundheitswesen",
    "sg:phone":"+41 61 281 23 60",
    "sg:postcode":"6987",
    "sg:province":"Ticino",
    "wof:name":"Sos Internet Ag",
    "wof:placetype":"venue"
},
  "geometry": {"coordinates":[8.876868248,45.9712905884],"type":"Point"}
}