{
  "type": "Feature",
  "properties": {
    "addr:full":"Riehenstrasse 43 Basel Basel-Stadt 4058",
    "addr:housenumber":"43",
    "addr:postcode":"4058",
    "addr:street":"Riehenstrasse",
    "iso:country":"CH",
    "sg:address":"Riehenstrasse 43",
    "sg:city":"Basel",
    "sg:orig_category":"Binnenschiffahrt G\u00fcterbef\u00f6rderung in der Binnenschiffahrt",
    "sg:phone":"+41 61 692 93 90",
    "sg:postcode":"4058",
    "sg:province":"Basel-Stadt",
    "wof:name":"Rigi Schiffahrt Ag",
    "wof:placetype":"venue"
},
  "geometry": {"coordinates":[7.599041,47.561466],"type":"Point"}
}