{
  "type": "Feature",
  "properties": {
    "iso:country":"CH",
    "sg:address":"Einkaufszentrum Parkallee",
    "sg:city":"Bachenb\u00fclach",
    "sg:orig_category":"Detailhandel mit S\u00e4uglings U Kinderbekleidung Herstellung von sonstiger Bekleidung U Bekleidungszube",
    "sg:phone":"+41 18500534",
    "sg:postcode":"8184",
    "sg:province":"Z\u00fcrich",
    "wof:name":"Ch\u00e4ferli B\u00e9b\u00e9-& Kindermode Esther Kycia",
    "wof:placetype":"venue"
},
  "geometry": {"coordinates":[8.548210144,47.5027313232],"type":"Point"}
}