{
  "type": "Feature",
  "properties": {
    "iso:country":"CH",
    "sg:address":"Bel-air Chemin De 3 2000 Neuenburg. Postfach",
    "sg:city":"Neuenburg",
    "sg:orig_category":"Reinigungsgewerbe",
    "sg:postcode":"2000",
    "sg:province":"Neuch\u00e2tel",
    "wof:name":"Nettoyages Speed S\u00e0rl Nettoyages De B\u00e2timents Et De Surfaces. Marchandises, Mat\u00e9riels Etc.; Transport",
    "wof:placetype":"venue"
},
  "geometry": {"coordinates":[6.9310851097,46.9903335571],"type":"Point"}
}