{
  "type": "Feature",
  "properties": {
    "iso:country":"CH",
    "sg:address":"Chemin De La For\u00eat",
    "sg:city":"Givrins",
    "sg:orig_category":"Unclassifiable Establishments",
    "sg:postcode":"1271",
    "sg:province":"Vaud",
    "wof:name":"Grosjean Consulting & Trading",
    "wof:placetype":"venue"
},
  "geometry": {"coordinates":[6.1952958107,46.4376068115],"type":"Point"}
}