{
  "type": "Feature",
  "properties": {
    "addr:full":"Ebnet Sirnach Thurgau 8370",
    "addr:postcode":"8370",
    "addr:street":"Ebnet",
    "iso:country":"CH",
    "sg:address":"Ebnet",
    "sg:city":"Sirnach",
    "sg:orig_category":"Bauschreinerei Einbau von Schreinerwaren",
    "sg:phone":"+41 71 969 36 36",
    "sg:postcode":"8370",
    "sg:province":"Thurgau",
    "wof:name":"Portas Ag",
    "wof:placetype":"venue"
},
  "geometry": {"coordinates":[8.993627,47.4669],"type":"Point"}
}