{
  "type": "Feature",
  "properties": {
    "iso:country":"CH",
    "sg:address":"Oberdorfstrasse 56",
    "sg:city":"Zermatt",
    "sg:orig_category":"D\u00e4mmung gegen K\u00e4lte, W\u00e4rme, Schall U Ersch\u00fctterung Maler U Glasergewerbe",
    "sg:phone":"+41 27 967 47 46",
    "sg:postcode":"3920",
    "sg:province":"Valais",
    "wof:name":"Dionys Imboden Malergesch\u00e4ft",
    "wof:placetype":"venue"
},
  "geometry": {"coordinates":[7.7451229095,46.0186653137],"type":"Point"}
}