{
  "type": "Feature",
  "properties": {
    "iso:country":"CH",
    "sg:address":"Juraweg 6",
    "sg:city":"Dotzigen",
    "sg:orig_category":"Vereine Harmonika and Akkordeon",
    "sg:phone":"+41 32 351 21 52",
    "sg:postcode":"3293",
    "sg:province":"Bern",
    "wof:name":"Harmonika-club B\u00fcren A/aare",
    "wof:placetype":"venue"
},
  "geometry": {"coordinates":[7.3426542282,47.1213531494],"type":"Point"}
}