{
  "type": "Feature",
  "properties": {
    "iso:country":"CH",
    "sg:address":"Eichholzstrasse 16 8706 Meilen. Postfach",
    "sg:city":"Feldmeilen",
    "sg:orig_category":"Markt U Meinungsforschung",
    "sg:phone":"+41 81 258 37 38",
    "sg:postcode":"8706",
    "sg:province":"Z\u00fcrich",
    "wof:name":"Aneva Ag",
    "wof:placetype":"venue"
},
  "geometry": {"coordinates":[9.4732599258,47.1659355164],"type":"Point"}
}