{
  "type": "Feature",
  "properties": {
    "iso:country":"CH",
    "sg:address":"Ch. De La Vuax 13",
    "sg:city":"Etoy",
    "sg:orig_category":"Unclassifiable Establishments",
    "sg:postcode":"1163",
    "sg:province":"Vaud",
    "wof:name":"L\u00fcthi, Daniel",
    "wof:placetype":"venue"
},
  "geometry": {"coordinates":[6.4136629105,46.4854812622],"type":"Point"}
}