{
  "type": "Feature",
  "properties": {
    "iso:country":"CH",
    "sg:address":"8586",
    "sg:city":"Erlen",
    "sg:orig_category":"Elektrizit\u00e4tsversorgung",
    "sg:phone":"+41 71 648 10 01",
    "sg:postcode":"8586",
    "sg:province":"Thurgau",
    "wof:name":"B\u00fchler Waldemar",
    "wof:placetype":"venue"
},
  "geometry": {"coordinates":[9.2330951691,47.5481987],"type":"Point"}
}