{
  "type": "Feature",
  "properties": {
    "addr:full":"Rue De La Fonderie Ardon Valais 1957",
    "addr:postcode":"1957",
    "addr:street":"Rue De La Fonderie",
    "iso:country":"CH",
    "sg:address":"Rue De La Fonderie",
    "sg:city":"Ardon",
    "sg:orig_category":"Detailhandel mit Beleuchtungs U Haushaltsgegenst\u00e4nden",
    "sg:phone":"+41 31 859 16 16",
    "sg:postcode":"1957",
    "sg:province":"Valais",
    "wof:name":"Herrmann Porzellanhaus",
    "wof:placetype":"venue"
},
  "geometry": {"coordinates":[7.494973,47.0173],"type":"Point"}
}