{
  "type": "Feature",
  "properties": {
    "iso:country":"CH",
    "sg:address":"Parkstrasse 19",
    "sg:city":"Weggis",
    "sg:orig_category":"Vermietung U Verpachtung von eigenen Immobilien",
    "sg:postcode":"6353",
    "sg:province":"Luzern",
    "wof:name":"Hohen-fels Immobilien Ag",
    "wof:placetype":"venue"
},
  "geometry": {"coordinates":[8.4276409149,47.0321388245],"type":"Point"}
}