{
  "type": "Feature",
  "properties": {
    "iso:country":"CH",
    "sg:address":"1410",
    "sg:city":"Thierrens",
    "sg:orig_category":"Herstellung von Metallkonstruktionen",
    "sg:phone":"+41 21 905 44 18",
    "sg:postcode":"1410",
    "sg:province":"Vaud",
    "wof:name":"Fardel Claude",
    "wof:placetype":"venue"
},
  "geometry": {"coordinates":[6.7543702126,46.7039604187],"type":"Point"}
}