{
  "type": "Feature",
  "properties": {
    "addr:full":"Hofstrasse 99 Wetzikon Z\u00fcrich 8620",
    "addr:housenumber":"99",
    "addr:postcode":"8620",
    "addr:street":"Hofstrasse",
    "iso:country":"CH",
    "sg:address":"Hofstrasse 99",
    "sg:city":"Wetzikon",
    "sg:classifiers":[
        {
            "category":"Social Services",
            "subcategory":"Job Training",
            "type":"Services"
        }
    ],
    "sg:phone":"+41 19321404",
    "sg:postcode":"8620",
    "sg:province":"Z\u00fcrich",
    "sg:tags":[
        "software",
        "database"
    ],
    "wof:name":"Vid-software Gmbh",
    "wof:placetype":"venue"
},
  "geometry": {"coordinates":[8.79529,47.309746],"type":"Point"}
}