{
  "type": "Feature",
  "properties": {
    "iso:country":"CH",
    "sg:address":"Dorfstrasse 23",
    "sg:city":"W\u00e4ngi",
    "sg:classifiers":[
        {
            "category":"Restaurant",
            "type":"Food & Drink"
        }
    ],
    "sg:phone":"+41 52 378 12 65",
    "sg:postcode":"9545",
    "sg:province":"Thurgau",
    "wof:name":"Restaurant Frohheim",
    "wof:placetype":"venue"
},
  "geometry": {"coordinates":[8.9544124603,47.4993133545],"type":"Point"}
}