{
  "type": "Feature",
  "properties": {
    "iso:country":"CH",
    "sg:address":"3966",
    "sg:city":"Chalais",
    "sg:classifiers":[
        {
            "category":"Restaurant",
            "type":"Food & Drink"
        }
    ],
    "sg:phone":"+41 27 207 30 98",
    "sg:postcode":"3966",
    "sg:province":"Valais",
    "wof:name":"Caf\u00e9 Poste",
    "wof:placetype":"venue"
},
  "geometry": {"coordinates":[7.3746399879,46.2108612061],"type":"Point"}
}