{
  "type": "Feature",
  "properties": {
    "iso:country":"CH",
    "sg:address":"Baarerstrasse 45",
    "sg:city":"Zug",
    "sg:orig_category":"Zahnarztpraxen",
    "sg:phone":"+41 41 711 19 36",
    "sg:postcode":"6300",
    "sg:province":"Zug",
    "wof:name":"Dr.med.dent.peter Aschwanden Zahnarzt",
    "wof:placetype":"venue"
},
  "geometry": {"coordinates":[8.5166530609,47.1740531921],"type":"Point"}
}