{
  "type": "Feature",
  "properties": {
    "iso:country":"CH",
    "sg:address":"Kaistenfeld",
    "sg:city":"Ittenthal",
    "sg:classifiers":[
        {
            "category":"Banks & Credit Unions",
            "subcategory":"Bank",
            "type":"Services"
        }
    ],
    "sg:phone":"+41 4164612469",
    "sg:postcode":"4337",
    "wof:name":"Schweiz. Mobiliar",
    "wof:placetype":"venue"
},
  "geometry": {"coordinates":[8.05975,47.51812],"type":"Point"}
}