{
  "type": "Feature",
  "properties": {
    "addr:full":"Pr\u00e9 Jean Meunier 1 Moutier Bern 2740",
    "addr:housenumber":"1",
    "addr:postcode":"2740",
    "addr:street":"Pre\u0301 Jean Meunier;Bern",
    "iso:country":"CH",
    "sg:address":"Pr\u00e9 Jean Meunier 1",
    "sg:city":"Moutier",
    "sg:orig_category":"Berufsbildende weiterf\u00fchrende Schulen",
    "sg:phone":"+41 32 493 13 31",
    "sg:postcode":"2740",
    "sg:province":"Bern",
    "wof:name":"Ecole Profess.artisanale",
    "wof:placetype":"venue"
},
  "geometry": {"coordinates":[7.380736,47.278671],"type":"Point"}
}