{
  "type": "Feature",
  "properties": {
    "iso:country":"CH",
    "sg:address":"Harschwendi 428",
    "sg:city":"Waldstatt",
    "sg:orig_category":"Mechanische Werkst\u00e4tten",
    "sg:phone":"+41 71 351 64 44",
    "sg:postcode":"9104",
    "sg:province":"Appenzell Ausserrhoden",
    "wof:name":"Werner Marti Pr\u00e4zisionsmechanik",
    "wof:placetype":"venue"
},
  "geometry": {"coordinates":[9.2773580551,47.3563423157],"type":"Point"}
}