{
  "type": "Feature",
  "properties": {
    "iso:country":"CH",
    "sg:address":"Boulevard Carl-vogt 65-67",
    "sg:city":"Gen\u00e8ve",
    "sg:orig_category":"Museen",
    "sg:phone":"+41 22 328 12 18",
    "sg:postcode":"1205",
    "sg:province":"Gen\u00e8ve",
    "wof:name":"Mus\u00e9e D'ethnographie De La Ville De Gen\u00e8ve",
    "wof:placetype":"venue"
},
  "geometry": {"coordinates":[6.1366519928,46.1977272034],"type":"Point"}
}