{
  "type": "Feature",
  "properties": {
    "iso:country":"CH",
    "sg:address":"Grundbach",
    "sg:city":"Wattenwil",
    "sg:orig_category":"Grosshandel mit sonstigen Gebrauchs U Verbrauchsg\u00fctern Herstellung von Radio U Fernsehger\u00e4ten sowie ",
    "sg:phone":"+41 33 359 36 36",
    "sg:postcode":"3665",
    "sg:province":"Bern",
    "wof:name":"Beyeler Musikbox Ag",
    "wof:placetype":"venue"
},
  "geometry": {"coordinates":[7.4869699478,46.7688598633],"type":"Point"}
}