{
  "type": "Feature",
  "properties": {
    "iso:country":"CH",
    "sg:address":"Rugenparkstrasse 8",
    "sg:city":"Interlaken",
    "sg:classifiers":[
        {
            "category":"Travel",
            "subcategory":"Hotels & Motels",
            "type":"Entertainment"
        }
    ],
    "sg:phone":"+41 33 822 28 31",
    "sg:postcode":"3800",
    "sg:province":"Bern",
    "sg:tags":[
        "hotels",
        "mit",
        "restaurant"
    ],
    "wof:name":"Hotel Touriste Kohler Peter",
    "wof:placetype":"venue"
},
  "geometry": {"coordinates":[7.8514728546,46.6813354492],"type":"Point"}
}