{
  "type": "Feature",
  "properties": {
    "iso:country":"CH",
    "sg:address":"Promenade Du Botza 25 1957 Ardon Case Postale 31",
    "sg:city":"Ardon",
    "sg:orig_category":"Herstellung von Tanks U Sammelbeh\u00e4ltern aus Metall Reinigungsgewerbe",
    "sg:phone":"+41 27 346 18 80",
    "sg:postcode":"1957",
    "sg:province":"Valais",
    "wof:name":"Citerna Ardon Sa",
    "wof:placetype":"venue"
},
  "geometry": {"coordinates":[7.2555451393,46.2083091736],"type":"Point"}
}