{
  "type": "Feature",
  "properties": {
    "iso:country":"CH",
    "sg:address":"Jubilaeumstrasse 95 -",
    "sg:city":"Bern",
    "sg:classifiers":[
        {
            "category":"Professional",
            "subcategory":"Art Services",
            "type":"Services"
        }
    ],
    "sg:phone":"+41 31 357 70 11",
    "sg:postcode":"3001",
    "sg:province":"Bern",
    "sg:tags":[
        "export-import"
    ],
    "wof:name":"American Embassy",
    "wof:placetype":"venue"
},
  "geometry": {"coordinates":[7.446429,46.935787],"type":"Point"}
}