{
  "type": "Feature",
  "properties": {
    "iso:country":"CH",
    "sg:address":"Birmensdorferstrasse 364",
    "sg:city":"Z\u00fcrich",
    "sg:classifiers":[
        {
            "category":"Professional",
            "subcategory":"Advertising",
            "type":"Services"
        }
    ],
    "sg:phone":"+41 14504466",
    "sg:postcode":"8055",
    "sg:province":"Z\u00fcrich",
    "sg:tags":[
        "article",
        "glass"
    ],
    "wof:name":"Elomesa Trading Ag",
    "wof:placetype":"venue"
},
  "geometry": {"coordinates":[8.505446,47.369518],"type":"Point"}
}