{
  "type": "Feature",
  "properties": {
    "iso:country":"CH",
    "sg:address":"Lindenweg 19",
    "sg:city":"Pfaffhausen",
    "sg:orig_category":"Politische Parteien CVP",
    "sg:phone":"+41 18254358",
    "sg:postcode":"8118",
    "sg:province":"Z\u00fcrich",
    "wof:name":"Cvp Sektion F\u00e4llanden",
    "wof:placetype":"venue"
},
  "geometry": {"coordinates":[8.6265935898,47.3684272766],"type":"Point"}
}