{
  "type": "Feature",
  "properties": {
    "iso:country":"CH",
    "sg:address":"Auenstrasse 7",
    "sg:city":"Bichelsee",
    "sg:classifiers":[
        {
            "category":"Insurance",
            "subcategory":"Insurance Agent",
            "type":"Services"
        }
    ],
    "sg:phone":"+41 71 971 18 17",
    "sg:postcode":"8363",
    "sg:province":"Thurgau",
    "sg:tags":[
        "versicherungsagenturen",
        "-broker"
    ],
    "wof:name":"Z\u00fcrich Versicherungen Agentur",
    "wof:placetype":"venue"
},
  "geometry": {"coordinates":[8.9249868393,47.4499320984],"type":"Point"}
}