{
  "type": "Feature",
  "properties": {
    "iso:country":"CH",
    "sg:address":"3254 Balm B. Messen. Postfach",
    "sg:city":"Messen",
    "sg:orig_category":"Grosshandel mit Eisenwaren sowie Installationsbedarf f\u00fcr Gas, Wasser U Heizung",
    "sg:phone":"+41 31 765 51 82",
    "sg:postcode":"3254",
    "sg:province":"Solothurn",
    "wof:name":"Lenz Werner.",
    "wof:placetype":"venue"
},
  "geometry": {"coordinates":[-82.59181976319999,33.4613304138],"type":"Point"}
}