{
  "type": "Feature",
  "properties": {
    "iso:country":"CH",
    "sg:address":"Unterdorfstrasse 27",
    "sg:city":"Lausen",
    "sg:orig_category":"Detailhandel mit Blumen U Pflanzen Fachdetailhandel in Verkaufsr\u00e4umen",
    "sg:phone":"+41 61 461 11 66",
    "sg:postcode":"4415",
    "sg:province":"Basel-Landschaft",
    "wof:name":"Blumenhaus Sch\u00e4nzli, Christine Zubler",
    "wof:placetype":"venue"
},
  "geometry": {"coordinates":[7.630255,47.533253],"type":"Point"}
}