{
  "type": "Feature",
  "properties": {
    "iso:country":"CH",
    "sg:address":"S\u00e4genstrasse 3 9472 Grabs. Postfach",
    "sg:city":"Grabs",
    "sg:orig_category":"Softwareentwicklung U beratung",
    "sg:postcode":"9472",
    "sg:province":"St. Gallen",
    "wof:name":"Elitech Gonthier",
    "wof:placetype":"venue"
},
  "geometry": {"coordinates":[6.8332691193,47.1054840088],"type":"Point"}
}