{
  "type": "Feature",
  "properties": {
    "iso:country":"CH",
    "sg:address":"Alfred Strebel-weg 15",
    "sg:city":"Z\u00fcrich",
    "sg:orig_category":"Sonstige Aktivit\u00e4ten der nicht-\u00e4rztlichen Medizinalberufe",
    "sg:phone":"+41 14924985",
    "sg:postcode":"8047",
    "sg:province":"Z\u00fcrich",
    "wof:name":"Margrit Hasler Atemtherapie",
    "wof:placetype":"venue"
},
  "geometry": {"coordinates":[8.4949207306,47.3713645935],"type":"Point"}
}