{
  "type": "Feature",
  "properties": {
    "iso:country":"CH",
    "sg:address":"Oskar Bider-strasse 1",
    "sg:city":"D\u00fcbendorf",
    "sg:orig_category":"Architektur U Ingenieurb\u00fcros",
    "sg:phone":"+41 14313747",
    "sg:postcode":"8600",
    "sg:province":"Z\u00fcrich",
    "wof:name":"Scg Consulting Ag Architektur, Bauprojekte; Organisation, Management Usw",
    "wof:placetype":"venue"
},
  "geometry": {"coordinates":[8.62625,47.39653],"type":"Point"}
}