{
  "type": "Feature",
  "properties": {
    "iso:country":"CH",
    "sg:address":"Romanshornerstrasse 2",
    "sg:city":"L\u00f6mmenschwil",
    "sg:classifiers":[
        {
            "category":"Restaurant",
            "type":"Food & Drink"
        }
    ],
    "sg:phone":"+41 71 298 35 70",
    "sg:postcode":"9308",
    "sg:province":"St. Gallen",
    "wof:name":"Restaurant Thuri's Blumenau",
    "wof:placetype":"venue"
},
  "geometry": {"coordinates":[9.3532142639,47.4946556091],"type":"Point"}
}