{
  "type": "Feature",
  "properties": {
    "addr:full":"Champ De La Vigne 6 Estavayer-le-lac Fribourg 1470",
    "addr:housenumber":"6",
    "addr:postcode":"1470",
    "addr:street":"Champ De La Vigne;Fribourg",
    "iso:country":"CH",
    "sg:address":"Champ De La Vigne 6",
    "sg:city":"Estavayer-le-lac",
    "sg:orig_category":"Bauschreinerei",
    "sg:phone":"+41 26 663 36 56",
    "sg:postcode":"1470",
    "sg:province":"Fribourg",
    "wof:name":"Brasey Marcel Sa",
    "wof:placetype":"venue"
},
  "geometry": {"coordinates":[6.857523,46.848888],"type":"Point"}
}