{
  "type": "Feature",
  "properties": {
    "iso:country":"CH",
    "sg:address":"Derendingerstrasse 27",
    "sg:city":"Luterbach",
    "sg:orig_category":"Manicure Solarien",
    "sg:phone":"+41 32 682 30 84",
    "sg:postcode":"4542",
    "sg:province":"Solothurn",
    "wof:name":"Elsbeth Affolter Kosmetik & Nagelstudio Oasis",
    "wof:placetype":"venue"
},
  "geometry": {"coordinates":[7.5864591599,47.2103919983],"type":"Point"}
}