{
  "type": "Feature",
  "properties": {
    "iso:country":"CH",
    "sg:address":"Chemin D'eysins 51",
    "sg:city":"Nyon",
    "sg:orig_category":"Vermietung U Verpachtung von eigenen Immobilien",
    "sg:phone":"+41 22 362 62 32",
    "sg:postcode":"1260",
    "sg:province":"Vaud",
    "wof:name":"Si Champ Colin 2",
    "wof:placetype":"venue"
},
  "geometry": {"coordinates":[6.2290000916,46.3931808472],"type":"Point"}
}