{
  "type": "Feature",
  "properties": {
    "iso:country":"CH",
    "sg:address":"Sch\u00fctzenmattstrasse 1",
    "sg:city":"B\u00fclach",
    "sg:orig_category":"Grosshandel mit sonstigen Gebrauchs U Verbrauchsg\u00fctern",
    "sg:phone":"+41 18648699",
    "sg:postcode":"8180",
    "sg:province":"Z\u00fcrich",
    "wof:name":"Hagedorn Christoph, Dekoplus By Idee Design",
    "wof:placetype":"venue"
},
  "geometry": {"coordinates":[8.5331268311,47.5279045105],"type":"Point"}
}