{
  "type": "Feature",
  "properties": {
    "iso:country":"CH",
    "sg:address":"Mont Sentier Du 8",
    "sg:city":"Corsier-sur-vevey",
    "sg:orig_category":"Herstellung von Spielwaren",
    "sg:postcode":"1804",
    "sg:province":"Vaud",
    "wof:name":"Mosa\u00efque Editions, Orcel Alain",
    "wof:placetype":"venue"
},
  "geometry": {"coordinates":[6.8414001465,46.4704856873],"type":"Point"}
}