{
  "type": "Feature",
  "properties": {
    "iso:country":"CH",
    "sg:address":"Piazza Cioccaro",
    "sg:city":"Lugano",
    "sg:orig_category":"Detailhandel mit Brillen U anderen Sehhilfen",
    "sg:phone":"+41 22 347 47 66",
    "sg:postcode":"6900",
    "sg:province":"Ticino",
    "wof:name":"Edouard Furst Optique Acoustique",
    "wof:placetype":"venue"
},
  "geometry": {"coordinates":[6.15379,46.191975],"type":"Point"}
}