{
  "type": "Feature",
  "properties": {
    "iso:country":"CH",
    "sg:address":"Blauenstrasse 40",
    "sg:city":"Basel",
    "sg:orig_category":"Sonstiger spezialisierter Hoch U Tiefbau",
    "sg:postcode":"4054",
    "sg:province":"Basel-Stadt",
    "wof:name":"Banz + Reck Kaminbau Ag",
    "wof:placetype":"venue"
},
  "geometry": {"coordinates":[7.5730252266,47.5549049377],"type":"Point"}
}