{
  "type": "Feature",
  "properties": {
    "iso:country":"CH",
    "sg:address":"Randenstrasse 198a",
    "sg:city":"Schaffhausen",
    "sg:orig_category":"Interessenvertretungen",
    "sg:postcode":"8200",
    "sg:province":"Schaffhausen",
    "wof:name":"Interessengemeinschaft Kolping Schaffhausen",
    "wof:placetype":"venue"
},
  "geometry": {"coordinates":[8.6168746948,47.7079086304],"type":"Point"}
}