{
  "type": "Feature",
  "properties": {
    "iso:country":"CH",
    "sg:address":"Blinzernstrasse",
    "sg:city":"K\u00f6niz",
    "sg:orig_category":"Vorschulen, Kinderg\u00e4rten",
    "sg:phone":"+41 31 971 91 55",
    "sg:postcode":"3098",
    "sg:province":"Bern",
    "wof:name":"Kindergarten Blinzern",
    "wof:placetype":"venue"
},
  "geometry": {"coordinates":[7.4188289642,46.9221496582],"type":"Point"}
}