{
  "type": "Feature",
  "properties": {
    "addr:full":"Route De Coffrane 4 Geneveys-coffrane Neuch\u00e2tel 2206",
    "addr:housenumber":"4",
    "addr:postcode":"2206",
    "addr:street":"Route De Coffrane;Geneveys-Coffrane Neucha\u0302Tel",
    "iso:country":"CH",
    "sg:address":"Route De Coffrane 4",
    "sg:city":"Geneveys-coffrane",
    "sg:orig_category":"Bauschreinerei Herstellung von Konstruktionsteilen, Fertigbauteilen U Ausbauelementen aus Holz",
    "sg:phone":"+41 32 857 11 13",
    "sg:postcode":"2206",
    "sg:province":"Neuch\u00e2tel",
    "wof:name":"Sigrist Andr\u00e9 Et Cie",
    "wof:placetype":"venue"
},
  "geometry": {"coordinates":[6.855563,47.015282],"type":"Point"}
}