{
  "type": "Feature",
  "properties": {
    "iso:country":"CH",
    "sg:address":"Kramershaus 16",
    "sg:city":"Heimisbach",
    "sg:orig_category":"Detailhandel mit elektrischen Haushalts-,Radio U Fernsehger\u00e4ten sowie Musikinstrumenten Herstellung ",
    "sg:postcode":"3453",
    "sg:province":"Bern",
    "wof:name":"Kohler Andreas.",
    "wof:placetype":"venue"
},
  "geometry": {"coordinates":[7.7582168579,47.0104446411],"type":"Point"}
}