{
  "type": "Feature",
  "properties": {
    "iso:country":"CH",
    "sg:address":"St. Jakobs-strasse 395 4052 Basel. Postfach",
    "sg:city":"Basel",
    "sg:orig_category":"Betrieb von Sportanlagen",
    "sg:postcode":"4051",
    "sg:province":"Basel-Stadt",
    "wof:name":"Genossenschaft F\u00fcr Die Sprungschanze Schratte Marbach",
    "wof:placetype":"venue"
},
  "geometry": {"coordinates":[7.896792,46.851143],"type":"Point"}
}