{
  "type": "Feature",
  "properties": {
    "iso:country":"CH",
    "sg:address":"Grand-rue 38",
    "sg:city":"Rolle",
    "sg:orig_category":"Wein Detailhandel",
    "sg:phone":"+41 21 825 54 20",
    "sg:postcode":"1180",
    "sg:province":"Vaud",
    "wof:name":"Vinath\u00e8me S\u00e0rl",
    "wof:placetype":"venue"
},
  "geometry": {"coordinates":[6.3393540382,46.4589347839],"type":"Point"}
}