{
  "type": "Feature",
  "properties": {
    "iso:country":"CH",
    "sg:address":"Kasernenstrasse 12",
    "sg:city":"Liestal",
    "sg:orig_category":"Detailhandel mit Teppichen Verlegen von Fussboden",
    "sg:phone":"+41 61 902 12 32",
    "sg:postcode":"4410",
    "sg:province":"Basel-Landschaft",
    "wof:name":"Brodbeck Ag Innendekorationen",
    "wof:placetype":"venue"
},
  "geometry": {"coordinates":[7.7367138863,47.4824981689],"type":"Point"}
}