{
  "type": "Feature",
  "properties": {
    "iso:country":"CH",
    "sg:address":"Rennweg 23",
    "sg:city":"Z\u00fcrich",
    "sg:orig_category":"Unternehmensberatung",
    "sg:phone":"+41 12125626",
    "sg:postcode":"8001",
    "sg:province":"Z\u00fcrich",
    "wof:name":"Benz Peter, Bildungspolitische Beratung, Z\u00fcrich",
    "wof:placetype":"venue"
},
  "geometry": {"coordinates":[8.5394601822,47.372833252],"type":"Point"}
}