{
  "type": "Feature",
  "properties": {
    "iso:country":"CH",
    "sg:address":"Badstrasse 3 8008 Z\u00fcrich. Postfach",
    "sg:city":"Z\u00fcrich",
    "sg:orig_category":"Grosshandel mit sonstigen Konsumg\u00fctern",
    "sg:phone":"+41 19109626",
    "sg:postcode":"8034",
    "sg:province":"Z\u00fcrich",
    "wof:name":"Deltatex Gmbh",
    "wof:placetype":"venue"
},
  "geometry": {"coordinates":[8.6010198593,47.3292121887],"type":"Point"}
}