{
  "type": "Feature",
  "properties": {
    "iso:country":"CH",
    "sg:address":"Feldbergstrasse 96 4057 Basel. Postfach",
    "sg:city":"Basel",
    "sg:orig_category":"Finanzierungsinstitutionen",
    "sg:phone":"+41 61 692 52 14",
    "sg:postcode":"4051",
    "sg:province":"Basel-Stadt",
    "wof:name":"Rohrer Markus Kreditvermittlung",
    "wof:placetype":"venue"
},
  "geometry": {"coordinates":[7.5943331718,47.5667266846],"type":"Point"}
}