{
  "type": "Feature",
  "properties": {
    "iso:country":"CH",
    "sg:address":"Kasernenstrasse 9",
    "sg:city":"B\u00fclach",
    "sg:orig_category":"Detailhandel mit Spielwaren Fachdetailhandel in Verkaufsr\u00e4umen",
    "sg:phone":"+41 18621966",
    "sg:postcode":"8180",
    "sg:province":"Z\u00fcrich",
    "wof:name":"Spielwaren Labyrinth Ag",
    "wof:placetype":"venue"
},
  "geometry": {"coordinates":[8.5391178131,47.5184745789],"type":"Point"}
}