{
  "type": "Feature",
  "properties": {
    "iso:country":"CH",
    "sg:address":"Turnerstrasse 19 4123 Allschwil. Postfach",
    "sg:city":"Allschwil",
    "sg:orig_category":"Bauschreinerei Herstellung von Konstruktionsteilen, Fertigbauteilen U Ausbauelementen aus Holz",
    "sg:phone":"+41 61 482 32 65",
    "sg:postcode":"4123",
    "sg:province":"Basel-Landschaft",
    "wof:name":"Dorfschreinerei Werdenberg Rolf Gmbh Schreinerarbeiten, Warenhandel, Bes. F\u00fcr Das Bau- U. Holzgewerbe Usw",
    "wof:placetype":"venue"
},
  "geometry": {"coordinates":[7.54401,47.55098],"type":"Point"}
}