{
  "type": "Feature",
  "properties": {
    "iso:country":"CH",
    "sg:address":"Haldenstrasse 12",
    "sg:city":"Luzern",
    "sg:orig_category":"Unclassifiable Establishments",
    "sg:phone":"+41 41 410 49 72",
    "sg:postcode":"6006",
    "sg:province":"Luzern",
    "wof:name":"Unitubes Holding Ag",
    "wof:placetype":"venue"
},
  "geometry": {"coordinates":[8.3204393387,47.0553283691],"type":"Point"}
}