{
  "type": "Feature",
  "properties": {
    "iso:country":"CH",
    "sg:address":"Seftigenstrasse 210",
    "sg:city":"Wabern",
    "sg:orig_category":"Detailhandel mit Waren verschiedener Art, Hauptrichtung Nahrungsmittel",
    "sg:phone":"+41 31 961 01 10",
    "sg:postcode":"3084",
    "sg:province":"Bern",
    "wof:name":"M\u00e4rit-laden Wabern",
    "wof:placetype":"venue"
},
  "geometry": {"coordinates":[7.4483141899,46.929901123],"type":"Point"}
}