{
  "type": "Feature",
  "properties": {
    "iso:country":"CH",
    "sg:address":"Chemin Ile-d'epines",
    "sg:city":"St-maurice",
    "sg:orig_category":"Instandhaltung U Reparatur von Automobilen",
    "sg:phone":"+41 24 471 84 11",
    "sg:postcode":"1890",
    "sg:province":"Valais",
    "wof:name":"Garage Des Ilettes Sa",
    "wof:placetype":"venue"
},
  "geometry": {"coordinates":[6.9609351158,46.2472343445],"type":"Point"}
}