{
  "type": "Feature",
  "properties": {
    "iso:country":"CH",
    "sg:address":"Grand-rue 32",
    "sg:city":"Rolle",
    "sg:orig_category":"RESTAURANTS: TEA-ROOMS",
    "sg:phone":"+41 21 825 21 96",
    "sg:postcode":"1180",
    "sg:province":"Vaud",
    "wof:name":"Caf\u00e9 Du Cercle De La C\u00f4te",
    "wof:placetype":"venue"
},
  "geometry": {"coordinates":[6.3396058083,46.4591026306],"type":"Point"}
}