{
  "type": "Feature",
  "properties": {
    "iso:country":"CH",
    "sg:address":"Zentenhausstr. 63",
    "sg:city":"Z\u00fcrich",
    "sg:classifiers":[
        {
            "category":"Wholesale",
            "subcategory":"Machinery & Supplies",
            "type":"Manufacturing & Wholesale Goods"
        }
    ],
    "sg:phone":"+41 4113710330",
    "sg:postcode":"8046",
    "sg:province":"Z\u00fcrich",
    "sg:tags":[
        "handling",
        "material",
        "-",
        "machine",
        "equipment",
        "engineering",
        "mechanical"
    ],
    "wof:name":"L Meili & Co Ag",
    "wof:placetype":"venue"
},
  "geometry": {"coordinates":[8.5077486038,47.4222679138],"type":"Point"}
}