{
  "type": "Feature",
  "properties": {
    "iso:country":"CH",
    "sg:address":"Hauptstrasse 3",
    "sg:city":"K\u00f6lliken",
    "sg:orig_category":"Instandhaltung U Reparatur von Automobilen",
    "sg:postcode":"5742",
    "sg:province":"Aargau",
    "wof:name":"Frederiksen Oluf, Carrosserie Und Autolackiererei",
    "wof:placetype":"venue"
},
  "geometry": {"coordinates":[7.8831877708,46.6988182068],"type":"Point"}
}