{
  "type": "Feature",
  "properties": {
    "iso:country":"CH",
    "sg:address":"Lausanne Rue De 49",
    "sg:city":"Morges",
    "sg:orig_category":"Instandhaltung U Reparatur von Automobilen",
    "sg:phone":"+41 21 804 70 02",
    "sg:postcode":"1110",
    "sg:province":"Vaud",
    "wof:name":"Ivc V\u00e9hicules Industriels Sa",
    "wof:placetype":"venue"
},
  "geometry": {"coordinates":[6.5074782372,46.5167770386],"type":"Point"}
}