{
  "type": "Feature",
  "properties": {
    "iso:country":"CH",
    "sg:address":"Bahnhofstrasse 28",
    "sg:city":"Schwyz",
    "sg:orig_category":"Vermietung U Verpachtung von eigenen Immobilien",
    "sg:postcode":"6430",
    "sg:province":"Schwyz",
    "wof:name":"Obermatt-immobilien Ag",
    "wof:placetype":"venue"
},
  "geometry": {"coordinates":[8.4380941391,47.4535331726],"type":"Point"}
}