{
  "type": "Feature",
  "properties": {
    "iso:country":"CH",
    "sg:address":"Amriswilerstrasse 16",
    "sg:city":"Bischofszell",
    "sg:orig_category":"Fahrschulen, Flugschulen",
    "sg:phone":"+41 71 422 30 71",
    "sg:postcode":"9220",
    "sg:province":"Thurgau",
    "wof:name":"Ernst Kocherhans Autofahrschule",
    "wof:placetype":"venue"
},
  "geometry": {"coordinates":[9.2421503067,47.4991416931],"type":"Point"}
}