{
  "type": "Feature",
  "properties": {
    "iso:country":"CH",
    "sg:address":"Quai Gustave-ador 10",
    "sg:city":"Gen\u00e8ve",
    "sg:orig_category":"Finanzierungsinstitutionen Handelsvermittlung U Grosshandel",
    "sg:phone":"+41 22 736 16 42",
    "sg:postcode":"1207",
    "sg:province":"Gen\u00e8ve",
    "wof:name":"Valtecint Sarl",
    "wof:placetype":"venue"
},
  "geometry": {"coordinates":[6.1561498642,46.2049598694],"type":"Point"}
}