{
  "type": "Feature",
  "properties": {
    "iso:country":"CH",
    "sg:address":"Telmoos 10",
    "sg:city":"Plaffeien",
    "sg:orig_category":"Dachdeckerei Zimmerei, Dachdeckerei, Bauspenglerei U Abdichtung",
    "sg:phone":"+41 26 419 11 01",
    "sg:postcode":"1716",
    "sg:province":"Fribourg",
    "wof:name":"Fasel-piller Ag",
    "wof:placetype":"venue"
},
  "geometry": {"coordinates":[7.291893,46.737591],"type":"Point"}
}