{
  "type": "Feature",
  "properties": {
    "iso:country":"CH",
    "sg:address":"Feldlistrasse 14",
    "sg:city":"Oberegg",
    "sg:classifiers":[
        {
            "category":"Banks & Credit Unions",
            "subcategory":"Bank",
            "type":"Services"
        }
    ],
    "sg:phone":"+41 4171911058",
    "sg:postcode":"9413",
    "sg:province":"Appenzell Innerhoden",
    "wof:name":"Rentenanstalt Swiss Life",
    "wof:placetype":"venue"
},
  "geometry": {"coordinates":[9.553037,47.423901],"type":"Point"}
}