{
  "type": "Feature",
  "properties": {
    "iso:country":"CH",
    "sg:address":"R\u00e4ffelstrasse 25",
    "sg:city":"Z\u00fcrich",
    "sg:classifiers":[
        {
            "category":"Professional",
            "subcategory":"Advertising",
            "type":"Services"
        }
    ],
    "sg:phone":"+41 14633388",
    "sg:postcode":"8045",
    "sg:province":"Z\u00fcrich",
    "sg:tags":[
        "postcard"
    ],
    "wof:name":"Geisseler & Marty",
    "wof:placetype":"venue"
},
  "geometry": {"coordinates":[8.513171,47.363007],"type":"Point"}
}