{
  "type": "Feature",
  "properties": {
    "iso:country":"CH",
    "sg:address":"Rue Dancet 37 1200 Gen\u00e8ve. Postfach",
    "sg:city":"Gen\u00e8ve",
    "sg:orig_category":"Reiseb\u00fcros U Reiseveranstalter",
    "sg:phone":"+41 21 648 35 31",
    "sg:postcode":"1205",
    "sg:province":"Gen\u00e8ve",
    "wof:name":"Corail Voyages Sa",
    "wof:placetype":"venue"
},
  "geometry": {"coordinates":[6.62687397,46.5242881775],"type":"Point"}
}