{
  "type": "Feature",
  "properties": {
    "iso:country":"CH",
    "sg:address":"Universit\u00e4tsstrasse 47",
    "sg:city":"Z\u00fcrich",
    "sg:orig_category":"Unternehmensberatung",
    "sg:phone":"+41 17154366",
    "sg:postcode":"8006",
    "sg:province":"Z\u00fcrich",
    "wof:name":"Global Finance Halfar",
    "wof:placetype":"venue"
},
  "geometry": {"coordinates":[8.5418739319,47.3224487305],"type":"Point"}
}