{
  "type": "Feature",
  "properties": {
    "iso:country":"CH",
    "sg:address":"Milchbuckstrasse 11",
    "sg:city":"Z\u00fcrich",
    "sg:classifiers":[
        {
            "category":"Government",
            "subcategory":"Post Office",
            "type":"Public Place"
        }
    ],
    "sg:phone":"+41 13625017",
    "sg:postcode":"8057",
    "sg:province":"Z\u00fcrich",
    "sg:tags":[
        "caf\u00e9s",
        "tea-rooms"
    ],
    "wof:name":"Caf\u00e9 Bijou",
    "wof:placetype":"venue"
},
  "geometry": {"coordinates":[8.5406694412,47.3951911926],"type":"Point"}
}