{
  "type": "Feature",
  "properties": {
    "iso:country":"CH",
    "sg:address":"Girenbadstrasse 1",
    "sg:city":"Turbenthal",
    "sg:orig_category":"Detailhandel mit Fahrr\u00e4dern",
    "sg:phone":"+41 52 385 35 35",
    "sg:postcode":"8488",
    "sg:province":"Z\u00fcrich",
    "wof:name":"Benito Gruosso Velo-shop",
    "wof:placetype":"venue"
},
  "geometry": {"coordinates":[8.8426847458,47.4411125183],"type":"Point"}
}