{
  "type": "Feature",
  "properties": {
    "iso:country":"CH",
    "sg:address":"Xxxi-d\u00e9cembre Rue Du 42 1207 Gen\u00e8ve. Postfach",
    "sg:city":"Gen\u00e8ve",
    "sg:orig_category":"Allgemeiner Hoch U Tiefbau",
    "sg:postcode":"1207",
    "sg:province":"Gen\u00e8ve",
    "wof:name":"Vertland Constructions Sa",
    "wof:placetype":"venue"
},
  "geometry": {"coordinates":[6.16178,46.200588],"type":"Point"}
}