{
  "type": "Feature",
  "properties": {
    "iso:country":"CH",
    "sg:address":"Wiesenstrasse 11",
    "sg:city":"T\u00fcbach",
    "sg:orig_category":"Foil Stamping Machines",
    "sg:phone":"+41 71 841 71 75",
    "sg:postcode":"9327",
    "sg:province":"St. Gallen",
    "wof:name":"Wolfer Reliefdruck Gmbh",
    "wof:placetype":"venue"
},
  "geometry": {"coordinates":[9.4589548111,47.4860725403],"type":"Point"}
}