{
  "type": "Feature",
  "properties": {
    "iso:country":"CH",
    "sg:address":"Vogelsangstrasse 2",
    "sg:city":"Goldau",
    "sg:orig_category":"Detailhandel mit Milcherzeugnissen U Eiern Detailhandel mit Waren verschiedener Art, Hauptrichtung N",
    "sg:phone":"+41 41 855 18 58",
    "sg:postcode":"6410",
    "sg:province":"Schwyz",
    "wof:name":"Alfons Vogel Milchprodukte Lebensmittel",
    "wof:placetype":"venue"
},
  "geometry": {"coordinates":[8.5479869843,47.0505104065],"type":"Point"}
}