{
  "type": "Feature",
  "properties": {
    "iso:country":"CH",
    "sg:address":"Clairbief",
    "sg:city":"Soubey",
    "sg:classifiers":[
        {
            "category":"Restaurant",
            "type":"Food & Drink"
        }
    ],
    "sg:phone":"+41 32 955 12 20",
    "sg:postcode":"2887",
    "sg:province":"Jura",
    "wof:name":"Caf\u00e9-restaurant Clairbief",
    "wof:placetype":"venue"
},
  "geometry": {"coordinates":[7.0114841461,47.3015708923],"type":"Point"}
}