{
  "type": "Feature",
  "properties": {
    "iso:country":"CH",
    "sg:address":"Sonnhaldenstrasse 1",
    "sg:city":"Kreuzlingen",
    "sg:orig_category":"Herstellung von Sportger\u00e4ten Sonstiger Grosshandel",
    "sg:phone":"+41 71 672 28 39",
    "sg:postcode":"8280",
    "sg:province":"Thurgau",
    "wof:name":"Peter M\u00fcller Netze & Zubeh\u00f6r",
    "wof:placetype":"venue"
},
  "geometry": {"coordinates":[9.166683197,47.6430892944],"type":"Point"}
}