{
  "type": "Feature",
  "properties": {
    "iso:country":"CH",
    "sg:address":"6404",
    "sg:city":"Greppen",
    "sg:orig_category":"S\u00e4ge, Hobel U Holzimpr\u00e4gnierwerke",
    "sg:phone":"+41 41 390 31 32",
    "sg:postcode":"6404",
    "sg:province":"Luzern",
    "wof:name":"Zimmermann H. & Sohn",
    "wof:placetype":"venue"
},
  "geometry": {"coordinates":[8.4229202271,47.0566482544],"type":"Point"}
}