{
  "type": "Feature",
  "properties": {
    "iso:country":"CH",
    "sg:address":"Grubenstrasse 26",
    "sg:city":"Ostermundigen",
    "sg:orig_category":"Unclassifiable Establishments",
    "sg:postcode":"3072",
    "sg:province":"Bern",
    "wof:name":"Alfag Holding Ag",
    "wof:placetype":"venue"
},
  "geometry": {"coordinates":[7.4886260033,46.9601173401],"type":"Point"}
}