{
  "type": "Feature",
  "properties": {
    "iso:country":"CH",
    "sg:address":"Dorfstrasse 15",
    "sg:city":"Kaltbrunn",
    "sg:orig_category":"Architekturb\u00fcros",
    "sg:phone":"+41 55 283 17 12",
    "sg:postcode":"8722",
    "sg:province":"St. Gallen",
    "wof:name":"Kurt Wettstein Architekturb\u00fcro",
    "wof:placetype":"venue"
},
  "geometry": {"coordinates":[9.045242,47.224056],"type":"Point"}
}