{
  "type": "Feature",
  "properties": {
    "addr:full":"Sedelstrasse 7 Emmenbr\u00fccke Luzern 6020",
    "addr:housenumber":"7",
    "addr:postcode":"6020",
    "addr:street":"Sedelstrasse",
    "iso:country":"CH",
    "sg:address":"Sedelstrasse 7",
    "sg:city":"Emmenbr\u00fccke",
    "sg:classifiers":[
        {
            "category":"Banks & Credit Unions",
            "subcategory":"Investment Brokerage",
            "type":"Services"
        }
    ],
    "sg:phone":"+41 41 262 09 06",
    "sg:postcode":"6020",
    "sg:province":"Luzern",
    "sg:tags":[
        "absorption",
        "refrigerator"
    ],
    "wof:name":"Cooltrans Ag",
    "wof:placetype":"venue"
},
  "geometry": {"coordinates":[8.285891,47.069771],"type":"Point"}
}