{
  "type": "Feature",
  "properties": {
    "iso:country":"CH",
    "sg:address":"Unterdorf 1718 Rechthalten. Postfach",
    "sg:city":"Rechthalten",
    "sg:orig_category":"Erschliessung von Grundst\u00fccken",
    "sg:postcode":"1718",
    "sg:province":"Fribourg",
    "wof:name":"Wohnungsbau Gebr. Corpataux & Co Ag",
    "wof:placetype":"venue"
},
  "geometry": {"coordinates":[7.2429170609,46.7664299011],"type":"Point"}
}