{
  "type": "Feature",
  "properties": {
    "iso:country":"CH",
    "sg:address":"Landstrasse 19",
    "sg:city":"Glarus",
    "sg:orig_category":"Sonstiger Grosshandel",
    "sg:postcode":"8750",
    "sg:province":"Glarus",
    "wof:name":"Matchmakers Consulting Ag",
    "wof:placetype":"venue"
},
  "geometry": {"coordinates":[9.0627660751,47.0427474976],"type":"Point"}
}