{
  "type": "Feature",
  "properties": {
    "iso:country":"CH",
    "sg:address":"Seestrasse 155",
    "sg:city":"Horgen",
    "sg:orig_category":"Detailhandel mit medizinischen U orthop\u00e4dischen Artikeln Drogerien",
    "sg:phone":"+41 17254623",
    "sg:postcode":"8810",
    "sg:province":"Z\u00fcrich",
    "wof:name":"Drogerie Bosshardt Centro Verde",
    "wof:placetype":"venue"
},
  "geometry": {"coordinates":[8.5990476608,47.2601165771],"type":"Point"}
}