{
  "type": "Feature",
  "properties": {
    "iso:country":"CH",
    "sg:address":"Gustackerstrasse 14",
    "sg:city":"Bottmingen",
    "sg:orig_category":"Personal U Stellenvermittlung Unternehmensberatung",
    "sg:phone":"+41 61 426 93 08",
    "sg:postcode":"4103",
    "sg:province":"Basel-Landschaft",
    "wof:name":"K. Winzeler & Partner Ag Management Consultants",
    "wof:placetype":"venue"
},
  "geometry": {"coordinates":[7.5680289268,47.525062561],"type":"Point"}
}