{
  "type": "Feature",
  "properties": {
    "iso:country":"CH",
    "sg:address":"Winzerhalde 36a",
    "sg:city":"Z\u00fcrich",
    "sg:orig_category":"Datenverarbeitungsdienste Sonstige mit der Informatik verbundene T\u00e4tigkeiten",
    "sg:phone":"+41 13419060",
    "sg:postcode":"8049",
    "sg:province":"Z\u00fcrich",
    "wof:name":"Connethics Stalder & Partner",
    "wof:placetype":"venue"
},
  "geometry": {"coordinates":[8.490914,47.399872],"type":"Point"}
}