{
  "type": "Feature",
  "properties": {
    "iso:country":"CH",
    "sg:address":"Herrengasse 1a",
    "sg:city":"Balsthal",
    "sg:orig_category":"Markt U Meinungsforschung",
    "sg:phone":"+41 62 391 90 40",
    "sg:postcode":"4710",
    "sg:province":"Solothurn",
    "wof:name":"Centerdesk Gmbh",
    "wof:placetype":"venue"
},
  "geometry": {"coordinates":[7.695734024,47.3159103394],"type":"Point"}
}