{
  "type": "Feature",
  "properties": {
    "iso:country":"CH",
    "sg:address":"Rue De La Rebatte 3",
    "sg:city":"Hauterive",
    "sg:orig_category":"Erbringung von Dienstleistungen f\u00fcr Unternehmen",
    "sg:postcode":"2068",
    "sg:province":"Neuch\u00e2tel",
    "wof:name":"Grafi-tec Nicolier",
    "wof:placetype":"venue"
},
  "geometry": {"coordinates":[6.9937758446,46.2955665588],"type":"Point"}
}