{
  "type": "Feature",
  "properties": {
    "iso:country":"CH",
    "sg:address":"Staldenstrasse 47",
    "sg:city":"Siebnen",
    "sg:orig_category":"Druck ohne Zeitungsdruck",
    "sg:phone":"+41 55 440 76 45",
    "sg:postcode":"8854",
    "sg:province":"Schwyz",
    "wof:name":"Jema Color Laser Print, Masek Jeannine",
    "wof:placetype":"venue"
},
  "geometry": {"coordinates":[8.8947200775,47.1718406677],"type":"Point"}
}