{
  "type": "Feature",
  "properties": {
    "iso:country":"CH",
    "sg:address":"Avenue Du Moulin 2-4",
    "sg:city":"Morges",
    "sg:orig_category":"RESTAURANTS: TEA-ROOMS",
    "sg:phone":"+41 21 801 85 75",
    "sg:postcode":"1110",
    "sg:province":"Vaud",
    "wof:name":"Pizzeria Du Moulin Sa",
    "wof:placetype":"venue"
},
  "geometry": {"coordinates":[6.492623806,46.511516571],"type":"Point"}
}