{
  "type": "Feature",
  "properties": {
    "addr:full":"Hopfenweg 40 Bern Bern 3007",
    "addr:housenumber":"40",
    "addr:postcode":"3007",
    "addr:street":"Hopfenweg",
    "iso:country":"CH",
    "sg:address":"Hopfenweg 40",
    "sg:city":"Bern",
    "sg:classifiers":[
        {
            "category":"Food & Beverages",
            "subcategory":"Specialty",
            "type":"Retail Goods"
        }
    ],
    "sg:phone":"+41 31 372 72 72",
    "sg:postcode":"3007",
    "sg:province":"Bern",
    "sg:tags":[
        "caterer"
    ],
    "wof:name":"Pizza-kurier Pizza-master",
    "wof:placetype":"venue"
},
  "geometry": {"coordinates":[7.428731,46.940811],"type":"Point"}
}