{
  "type": "Feature",
  "properties": {
    "iso:country":"CH",
    "sg:address":"Niederschongau",
    "sg:city":"Schongau",
    "sg:orig_category":"Detailhandel mit Waren verschiedener Art, Hauptrichtung Nahrungsmittel",
    "sg:phone":"+41 41 917 21 41",
    "sg:postcode":"6288",
    "sg:province":"Luzern",
    "wof:name":"Walter Haas Handlung",
    "wof:placetype":"venue"
},
  "geometry": {"coordinates":[8.263215065,47.2792129517],"type":"Point"}
}