{
  "type": "Feature",
  "properties": {
    "iso:country":"CH",
    "sg:address":"Gr\u00e4tzlistrasse 28",
    "sg:city":"Opfikon",
    "sg:orig_category":"Ger\u00fcstbau Sonstiger spezialisierter Hoch U Tiefbau",
    "sg:phone":"+41 52 315 48 41",
    "sg:postcode":"8152",
    "sg:province":"Z\u00fcrich",
    "wof:name":"Fritz Bau U. Ger\u00fcst Ag",
    "wof:placetype":"venue"
},
  "geometry": {"coordinates":[8.5795183182,47.4262962341],"type":"Point"}
}