{
  "type": "Feature",
  "properties": {
    "iso:country":"CH",
    "sg:address":"Heidwiesen 21",
    "sg:city":"Z\u00fcrich",
    "sg:orig_category":"Detailhandel mit elektrischen Haushalts-,Radio U Fernsehger\u00e4ten sowie Musikinstrumenten",
    "sg:postcode":"8051",
    "sg:province":"Z\u00fcrich",
    "wof:name":"Dante Albizzati, Pyramid Records Schallplatten; Verkauf U. Versand",
    "wof:placetype":"venue"
},
  "geometry": {"coordinates":[8.5764665604,47.4074935913],"type":"Point"}
}