{
  "type": "Feature",
  "properties": {
    "iso:country":"CH",
    "sg:address":"Fribourg Route De 32",
    "sg:city":"Marly",
    "sg:orig_category":"Grosshandel mit Getr\u00e4nken",
    "sg:postcode":"1723",
    "sg:province":"Fribourg",
    "wof:name":"Mabillard L\u00e9on Et Famille",
    "wof:placetype":"venue"
},
  "geometry": {"coordinates":[7.1819300652,46.1889343262],"type":"Point"}
}