{
  "type": "Feature",
  "properties": {
    "iso:country":"CH",
    "sg:address":"Benkenstrasse 51",
    "sg:city":"K\u00fcttigen",
    "sg:orig_category":"G\u00fcterbef\u00f6rderung im Strassenverkehr",
    "sg:phone":"+41 62 827 21 18",
    "sg:postcode":"5024",
    "sg:province":"Aargau",
    "wof:name":"R. Basler Transport Ag",
    "wof:placetype":"venue"
},
  "geometry": {"coordinates":[8.039557457,47.4213829041],"type":"Point"}
}