{
  "type": "Feature",
  "properties": {
    "iso:country":"CH",
    "sg:address":"Bahnhofstrasse 5",
    "sg:city":"Amriswil",
    "sg:orig_category":"Detailhandel mit B\u00fcchern Detailhandel mit B\u00fcchern, Zeitungen, Schreib U Papeteriewaren",
    "sg:phone":"+41 71 411 10 26",
    "sg:postcode":"8580",
    "sg:province":"Thurgau",
    "wof:name":"M. Nagel, Papeterie Und Buchhandlung Marktplatz",
    "wof:placetype":"venue"
},
  "geometry": {"coordinates":[9.300033,47.546196],"type":"Point"}
}