{
  "type": "Feature",
  "properties": {
    "iso:country":"CH",
    "sg:address":"Niederhofen 135",
    "sg:city":"Schlossrued",
    "sg:orig_category":"Sonstige mit der Informatik verbundene T\u00e4tigkeiten",
    "sg:phone":"+41 62 721 26 35",
    "sg:postcode":"5044",
    "sg:province":"Aargau",
    "wof:name":"Steiner Consulting",
    "wof:placetype":"venue"
},
  "geometry": {"coordinates":[8.0748672485,47.2898216248],"type":"Point"}
}