{
  "type": "Feature",
  "properties": {
    "iso:country":"CH",
    "sg:address":"G\u00fcterstrasse 9 2502 Biel/bienne. Postfach",
    "sg:city":"Biel/bienne",
    "sg:classifiers":[
        {
            "category":"Restaurant",
            "type":"Food & Drink"
        }
    ],
    "sg:phone":"+41 34 402 42 62",
    "sg:postcode":"2501",
    "sg:province":"Bern",
    "wof:name":"Pizzeria California",
    "wof:placetype":"venue"
},
  "geometry": {"coordinates":[7.757589817,46.9491271973],"type":"Point"}
}