{
  "type": "Feature",
  "properties": {
    "iso:country":"CH",
    "sg:address":"Pilatusstrasse 17",
    "sg:city":"Emmenbr\u00fccke",
    "sg:orig_category":"Kaminfeger",
    "sg:phone":"+41 41 260 12 28",
    "sg:postcode":"6020",
    "sg:province":"Luzern",
    "wof:name":"Josef Fischer Kaminfegergesch\u00e4ft",
    "wof:placetype":"venue"
},
  "geometry": {"coordinates":[8.2817392349,47.0760917664],"type":"Point"}
}