{
  "type": "Feature",
  "properties": {
    "addr:full":"Berom\u00fcnster Luzern 6215",
    "addr:postcode":"6215",
    "addr:street":"Beromuenster",
    "iso:country":"CH",
    "sg:city":"Berom\u00fcnster",
    "sg:classifiers":[
        {
            "category":"Banks & Credit Unions",
            "subcategory":"Bank",
            "type":"Services"
        }
    ],
    "sg:phone":"+41 4141512828",
    "sg:postcode":"6215",
    "sg:province":"Luzern",
    "wof:name":"Luzerner Kantonalbank",
    "wof:placetype":"venue"
},
  "geometry": {"coordinates":[8.19196,47.206455],"type":"Point"}
}