{
  "type": "Feature",
  "properties": {
    "iso:country":"CH",
    "sg:address":"Tissot Avenue 2",
    "sg:city":"Lausanne",
    "sg:orig_category":"Institutionen des Sozialwesens ohne Beherbergung",
    "sg:postcode":"1003",
    "sg:province":"Vaud",
    "wof:name":"Fondation Internationale Pour La Population Et Le D\u00e9veloppement",
    "wof:placetype":"venue"
},
  "geometry": {"coordinates":[6.6335511208,46.5159950256],"type":"Point"}
}