{
  "type": "Feature",
  "properties": {
    "iso:country":"CH",
    "sg:address":"Universit\u00e4tstrasse 112",
    "sg:city":"Z\u00fcrich",
    "sg:orig_category":"Softwareentwicklung U beratung",
    "sg:postcode":"8006",
    "sg:province":"Z\u00fcrich",
    "wof:name":"Pieron Technologies Gmbh",
    "wof:placetype":"venue"
},
  "geometry": {"coordinates":[8.5486803055,47.3850708008],"type":"Point"}
}