{
  "type": "Feature",
  "properties": {
    "iso:country":"CH",
    "sg:address":"Bremgarterstrasse 10",
    "sg:city":"Waltenschwil",
    "sg:orig_category":"Herstellung von Betonerzeugnissen f\u00fcr den Bau Innenausbau",
    "sg:phone":"+41 56 622 00 07",
    "sg:postcode":"5622",
    "sg:province":"Aargau",
    "wof:name":"K\u00e4lin Ag Waltenschwil",
    "wof:placetype":"venue"
},
  "geometry": {"coordinates":[8.3023729324,47.3348426819],"type":"Point"}
}