{
  "type": "Feature",
  "properties": {
    "iso:country":"CH",
    "sg:address":"Bernstrasse 14",
    "sg:city":"Kiesen",
    "sg:orig_category":"Tanzschulen, Tanzlehrer",
    "sg:phone":"+41 31 781 37 27",
    "sg:postcode":"3629",
    "sg:province":"Bern",
    "wof:name":"Balke Tanz & Gymnastik",
    "wof:placetype":"venue"
},
  "geometry": {"coordinates":[7.58375597,46.8249053955],"type":"Point"}
}