{
  "type": "Feature",
  "properties": {
    "iso:country":"CH",
    "sg:address":"Pictet Avenue Ernest- 20 1203 Gen\u00e8ve. Postfach",
    "sg:city":"Gen\u00e8ve",
    "sg:orig_category":"Sonstiger Grosshandel",
    "sg:phone":"+41 22 345 10 66",
    "sg:postcode":"1203",
    "sg:province":"Gen\u00e8ve",
    "wof:name":"Valerca Sa",
    "wof:placetype":"venue"
},
  "geometry": {"coordinates":[6.1250681877,46.2126579285],"type":"Point"}
}