{
  "type": "Feature",
  "properties": {
    "iso:country":"CH",
    "sg:address":"Winterhaldenstrasse 54",
    "sg:city":"Turgi",
    "sg:orig_category":"Sanit\u00e4r, Heizungs U L\u00fcftungsinstallation Sanit\u00e4rinstallation",
    "sg:phone":"+41 56 223 32 42",
    "sg:postcode":"5300",
    "sg:province":"Aargau",
    "wof:name":"Frei Heizung + Sanit\u00e4r Gmbh",
    "wof:placetype":"venue"
},
  "geometry": {"coordinates":[8.2523698807,47.4890365601],"type":"Point"}
}