{
  "type": "Feature",
  "properties": {
    "addr:full":"Pfisternweg 9 Baar Zug 6340",
    "addr:housenumber":"9",
    "addr:postcode":"6340",
    "addr:street":"Pfisternweg;Zug",
    "iso:country":"CH",
    "sg:address":"Pfisternweg 9",
    "sg:city":"Baar",
    "sg:orig_category":"Allgemeiner Hoch U Tiefbau Hoch U Tiefbau",
    "sg:phone":"+41 41 760 15 64",
    "sg:postcode":"6340",
    "sg:province":"Zug",
    "wof:name":"Ansa A.sauvain Baugesch\u00e4ft",
    "wof:placetype":"venue"
},
  "geometry": {"coordinates":[8.534402,47.195633],"type":"Point"}
}