{
  "type": "Feature",
  "properties": {
    "iso:country":"CH",
    "sg:address":"Buobenhofstrasse 27 8852 Altendorf. Postfach",
    "sg:city":"Altendorf",
    "sg:orig_category":"Architektur U Ingenieurb\u00fcros Kunsthandel",
    "sg:phone":"+41 55 442 64 18",
    "sg:postcode":"8852",
    "sg:province":"Schwyz",
    "wof:name":"Archivolto Ag Innenarchitektur-design Kunst",
    "wof:placetype":"venue"
},
  "geometry": {"coordinates":[8.827956,47.18819],"type":"Point"}
}