{
  "type": "Feature",
  "properties": {
    "iso:country":"CH",
    "sg:address":"Gheidweg 36",
    "sg:city":"Olten",
    "sg:orig_category":"Detailhandel mit Fleisch U Fleischwaren",
    "sg:phone":"+41 19351614",
    "sg:postcode":"4600",
    "sg:province":"Solothurn",
    "wof:name":"Emil Zellweger Metzgerei",
    "wof:placetype":"venue"
},
  "geometry": {"coordinates":[8.7583551407,47.3058738708],"type":"Point"}
}