{
  "type": "Feature",
  "properties": {
    "iso:country":"CH",
    "sg:address":"Via Delle Scuole",
    "sg:city":"Lamone",
    "sg:orig_category":"Primarschulen",
    "sg:phone":"+41 91 967 22 94",
    "sg:postcode":"6814",
    "sg:province":"Ticino",
    "wof:name":"Scuola Elementare Consortile Lamone-cadempino",
    "wof:placetype":"venue"
},
  "geometry": {"coordinates":[8.9334497452,46.0397491455],"type":"Point"}
}