{
  "type": "Feature",
  "properties": {
    "iso:country":"CH",
    "sg:address":"Baarerstrasse 43 6300 Zug. Postfach",
    "sg:city":"Zug",
    "sg:orig_category":"Grosshandel mit Erzen U Metallen",
    "sg:postcode":"6300",
    "sg:province":"Zug",
    "wof:name":"Alcumet Product Ag Buntmetalle, Waren; Handel",
    "wof:placetype":"venue"
},
  "geometry": {"coordinates":[8.516579628,47.1738433838],"type":"Point"}
}