{
  "type": "Feature",
  "properties": {
    "iso:country":"CH",
    "sg:address":"Gerechtigkeitsgasse 43",
    "sg:city":"Bern",
    "sg:orig_category":"Fachdetailhandel in Verkaufsr\u00e4umen",
    "sg:phone":"+41 31 311 11 53",
    "sg:postcode":"3011",
    "sg:province":"Bern",
    "wof:name":"Numismatik Klein Beat A.",
    "wof:placetype":"venue"
},
  "geometry": {"coordinates":[7.4537329674,46.9480895996],"type":"Point"}
}