{
  "type": "Feature",
  "properties": {
    "iso:country":"CH",
    "sg:address":"M\u00fchletalweg 2",
    "sg:city":"Olten",
    "sg:orig_category":"Vorschulen, Kinderg\u00e4rten",
    "sg:phone":"+41 62 212 23 60",
    "sg:postcode":"4600",
    "sg:province":"Solothurn",
    "wof:name":"Kindergarten S\u00e4lihof",
    "wof:placetype":"venue"
},
  "geometry": {"coordinates":[7.9168257713,47.3461494446],"type":"Point"}
}