{
  "type": "Feature",
  "properties": {
    "iso:country":"CH",
    "sg:address":"Schipfe 33",
    "sg:city":"Z\u00fcrich",
    "sg:orig_category":"Herstellung von Duft U K\u00f6rperpflegemitteln",
    "sg:phone":"+41 12212684",
    "sg:postcode":"8001",
    "sg:province":"Z\u00fcrich",
    "wof:name":"Gutknecht & Frey Ag",
    "wof:placetype":"venue"
},
  "geometry": {"coordinates":[8.5415773392,47.3727912903],"type":"Point"}
}