{
  "type": "Feature",
  "properties": {
    "iso:country":"CH",
    "sg:address":"Bahnhofstrasse 7",
    "sg:city":"Dagmersellen",
    "sg:orig_category":"Grosshandel mit Geschenkartikeln U Souvenirs",
    "sg:phone":"+41 62 756 26 27",
    "sg:postcode":"6252",
    "sg:province":"Luzern",
    "wof:name":"Frewe Presents Ag Werbegeschenke & Schreibger.",
    "wof:placetype":"venue"
},
  "geometry": {"coordinates":[7.9828047752,47.2174186707],"type":"Point"}
}