{
  "type": "Feature",
  "properties": {
    "iso:country":"CH",
    "sg:address":"3960 Sierre. Postfach",
    "sg:city":"Siders",
    "sg:orig_category":"Grosshandel mit Getr\u00e4nken",
    "sg:postcode":"3960",
    "sg:province":"Valais",
    "wof:name":"Hoirs Les De Philo Carrupt-michellod.",
    "wof:placetype":"venue"
},
  "geometry": {"coordinates":[7.1819300652,46.1889343262],"type":"Point"}
}