{
  "type": "Feature",
  "properties": {
    "iso:country":"CH",
    "sg:address":"Wiggerweg 1 4800 Zofingen. Postfach",
    "sg:city":"Zofingen",
    "sg:orig_category":"Herstellung von sonstigen elektrischen Ausr\u00fcstungen",
    "sg:phone":"+41 62 751 20 65",
    "sg:postcode":"4800",
    "sg:province":"Aargau",
    "wof:name":"S\u00c4msar Gmbh Laser-tontauben-schiessanlagen; Betrieb Und Vermietung. Party-service",
    "wof:placetype":"venue"
},
  "geometry": {"coordinates":[7.9368901253,47.2813529968],"type":"Point"}
}