{
  "type": "Feature",
  "properties": {
    "iso:country":"CH",
    "sg:address":"Quellenweg 9",
    "sg:city":"M\u00fcnchenbuchsee",
    "sg:orig_category":"Architektur U Ingenieurb\u00fcros",
    "sg:phone":"+41 31 869 00 37",
    "sg:postcode":"3053",
    "sg:province":"Bern",
    "wof:name":"Bruno Arn Ag",
    "wof:placetype":"venue"
},
  "geometry": {"coordinates":[7.445925,47.018063],"type":"Point"}
}