{
  "type": "Feature",
  "properties": {
    "iso:country":"CH",
    "sg:address":"Via Posmonte",
    "sg:city":"Agra",
    "sg:orig_category":"Vermietung U Verpachtung von eigenen Immobilien",
    "sg:phone":"+41 91 994 21 55",
    "sg:postcode":"6927",
    "sg:province":"Ticino",
    "wof:name":"Collina Del Tasso Sa",
    "wof:placetype":"venue"
},
  "geometry": {"coordinates":[8.9129209518,45.9708328247],"type":"Point"}
}