{
  "type": "Feature",
  "properties": {
    "iso:country":"CH",
    "sg:address":"Rue Du Vingt-trois Juin 33",
    "sg:city":"Montfaucon",
    "sg:classifiers":[
        {
            "category":"Travel",
            "subcategory":"Hotels & Motels",
            "type":"Entertainment"
        }
    ],
    "sg:phone":"+41 32 955 13 44",
    "sg:postcode":"2875",
    "sg:province":"Jura",
    "sg:tags":[
        "hotels",
        "mit",
        "restaurant"
    ],
    "wof:name":"H\u00f4tel De La Pomme D'or",
    "wof:placetype":"venue"
},
  "geometry": {"coordinates":[7.0517001152,47.2833251953],"type":"Point"}
}