{
  "type": "Feature",
  "properties": {
    "iso:country":"CH",
    "sg:address":"Schulhausstrasse 20",
    "sg:city":"Vilters",
    "sg:orig_category":"Vorschulen, Kinderg\u00e4rten",
    "sg:phone":"+41 81 723 47 23",
    "sg:postcode":"7324",
    "sg:province":"St. Gallen",
    "wof:name":"Kindergarten",
    "wof:placetype":"venue"
},
  "geometry": {"coordinates":[9.4469852448,47.025352478],"type":"Point"}
}