{
  "type": "Feature",
  "properties": {
    "iso:country":"CH",
    "sg:address":"Werkstrasse 2",
    "sg:city":"Chur",
    "sg:orig_category":"Non-Classified Establishments",
    "sg:phone":"+41 81 284 57 77",
    "sg:postcode":"7000",
    "sg:province":"Graubunden",
    "wof:name":"Substantia Ag F\u00fcr Finanzierungen Und Beteiligungen",
    "wof:placetype":"venue"
},
  "geometry": {"coordinates":[9.5267877579,46.856010437],"type":"Point"}
}