{
  "type": "Feature",
  "properties": {
    "iso:country":"CH",
    "sg:address":"Seestrasse 6205 Eich. Postfach 69",
    "sg:city":"Eich",
    "sg:orig_category":"Herstellung von Verbrennungsmotoren U Turbinen ohne Motoren f\u00fcr Luft U Strassenfahrzeuge Mechanische",
    "sg:phone":"+41 41 462 51 51",
    "sg:postcode":"6205",
    "sg:province":"Luzern",
    "wof:name":"Delta Motor Ag",
    "wof:placetype":"venue"
},
  "geometry": {"coordinates":[8.168867,47.150284],"type":"Point"}
}