{
  "type": "Feature",
  "properties": {
    "iso:country":"CH",
    "sg:address":"Schmiedgasse 7-9",
    "sg:city":"Riehen",
    "sg:orig_category":"Detailhandel mit Waren verschiedener Art, Hauptrichtung Nahrungsmittel",
    "sg:phone":"+41 41 670 11 16",
    "sg:postcode":"4125",
    "sg:province":"Basel-Stadt",
    "wof:name":"Coop Center",
    "wof:placetype":"venue"
},
  "geometry": {"coordinates":[8.2692890167,46.9378547668],"type":"Point"}
}