{
  "type": "Feature",
  "properties": {
    "iso:country":"CH",
    "sg:address":"Wildi",
    "sg:city":"Visp",
    "sg:orig_category":"Stukkateurgewerbe, Gipserei U Verputzerei Tapeziererei",
    "sg:phone":"+41 27 946 12 62",
    "sg:postcode":"3930",
    "sg:province":"Valais",
    "wof:name":"Herbert Heinzmann Malergesch\u00e4ft",
    "wof:placetype":"venue"
},
  "geometry": {"coordinates":[7.8827300072,46.2922286987],"type":"Point"}
}