{
  "type": "Feature",
  "properties": {
    "iso:country":"CH",
    "sg:address":"Alte Winterthurerstrasse 31",
    "sg:city":"Wallisellen",
    "sg:classifiers":[
        {
            "category":"Restaurant",
            "type":"Food & Drink"
        }
    ],
    "sg:phone":"+41 71 931 10 21",
    "sg:postcode":"8304",
    "sg:province":"Z\u00fcrich",
    "wof:name":"Wirtschaft Zum Frohsinn Hausen",
    "wof:placetype":"venue"
},
  "geometry": {"coordinates":[9.0491914749,47.4126663208],"type":"Point"}
}