{
  "type": "Feature",
  "properties": {
    "iso:country":"CH",
    "sg:address":"Z\u00fcrcherstrasse 2",
    "sg:city":"Siebnen",
    "sg:orig_category":"RESTAURANTS: TEA-ROOMS",
    "sg:postcode":"8854",
    "sg:province":"Schwyz",
    "wof:name":"Sch\u00e4fer A. & Fl\u00fcck V.",
    "wof:placetype":"venue"
},
  "geometry": {"coordinates":[6.8319001198,47.1032752991],"type":"Point"}
}