{
  "type": "Feature",
  "properties": {
    "iso:country":"CH",
    "sg:address":"3999",
    "sg:city":"Oberwald",
    "sg:orig_category":"Architektur U Ingenieurb\u00fcros",
    "sg:postcode":"3999",
    "sg:province":"Valais",
    "wof:name":"Plot Yacht Concept, Dipl.-ing. Niessner Rainer",
    "wof:placetype":"venue"
},
  "geometry": {"coordinates":[8.345925,46.533363],"type":"Point"}
}