{
  "type": "Feature",
  "properties": {
    "iso:country":"CH",
    "sg:address":"Mettlenstrasse 24",
    "sg:city":"Eglisau",
    "sg:orig_category":"Vereine Gesang Vereine Gesang and Jodler",
    "sg:phone":"+41 18674347",
    "sg:postcode":"8193",
    "sg:province":"Z\u00fcrich",
    "wof:name":"Jodelclub Eglisau",
    "wof:placetype":"venue"
},
  "geometry": {"coordinates":[8.5196628571,47.5740890503],"type":"Point"}
}