{
  "type": "Feature",
  "properties": {
    "iso:country":"CH",
    "sg:address":"Birkenweg 5",
    "sg:city":"Gr\u00e4nichen",
    "sg:orig_category":"Malerei",
    "sg:phone":"+41 61 712 05 75",
    "sg:postcode":"5722",
    "sg:province":"Aargau",
    "wof:name":"Peter Spaar Malergesch\u00e4ft",
    "wof:placetype":"venue"
},
  "geometry": {"coordinates":[7.5876498222,47.4919242859],"type":"Point"}
}