{
  "type": "Feature",
  "properties": {
    "iso:country":"CH",
    "sg:address":"Limmatstrasse 125",
    "sg:city":"Z\u00fcrich",
    "sg:classifiers":[
        {
            "category":"Restaurant",
            "type":"Food & Drink"
        }
    ],
    "sg:phone":"+41 12732843",
    "sg:postcode":"8005",
    "sg:province":"Z\u00fcrich",
    "wof:name":"Pizzeria Eden",
    "wof:placetype":"venue"
},
  "geometry": {"coordinates":[8.5321788788,47.3841247559],"type":"Point"}
}