{
  "type": "Feature",
  "properties": {
    "iso:country":"CH",
    "sg:address":"Luzernerstrasse 32",
    "sg:city":"Littau",
    "sg:orig_category":"Grafikateliers, Design",
    "sg:phone":"+41 41 250 57 21",
    "sg:postcode":"6014",
    "sg:province":"Luzern",
    "wof:name":"Joseph Lindenmann Schriften-& Reklameatelier",
    "wof:placetype":"venue"
},
  "geometry": {"coordinates":[8.2804203033,47.0524177551],"type":"Point"}
}