{
  "type": "Feature",
  "properties": {
    "iso:country":"CH",
    "sg:address":"Aub\u00e9pines Rue Des 15",
    "sg:city":"Sion",
    "sg:orig_category":"Interessenvertretungen",
    "sg:postcode":"1950",
    "sg:province":"Valais",
    "wof:name":"Fondation Aide Sportive Valaisanne (fasv)",
    "wof:placetype":"venue"
},
  "geometry": {"coordinates":[7.365377903,46.2315406799],"type":"Point"}
}