{
  "type": "Feature",
  "properties": {
    "iso:country":"CH",
    "sg:address":"Kindhauserstrasse 14",
    "sg:city":"Effretikon",
    "sg:orig_category":"Autogaragen",
    "sg:phone":"+41 52 343 11 85",
    "sg:postcode":"8307",
    "sg:province":"Z\u00fcrich",
    "wof:name":"Walter Morf Autoreparaturwerkst\u00e4tte",
    "wof:placetype":"venue"
},
  "geometry": {"coordinates":[8.693495,47.410904],"type":"Point"}
}