{
  "type": "Feature",
  "properties": {
    "iso:country":"CH",
    "sg:address":"Hohrain 25",
    "sg:city":"Bangerten",
    "sg:orig_category":"Mechanik Mechanische Werkst\u00e4tten",
    "sg:phone":"+41 31 869 02 57",
    "sg:postcode":"3256",
    "sg:province":"Bern",
    "wof:name":"Buba Fahrzeuge Ag",
    "wof:placetype":"venue"
},
  "geometry": {"coordinates":[7.4397139549,47.0553474426],"type":"Point"}
}