{
  "type": "Feature",
  "properties": {
    "iso:country":"CH",
    "sg:address":"Sch\u00e4nzlistrasse 33",
    "sg:city":"Bern",
    "sg:orig_category":"Non-Classified Establishments",
    "sg:postcode":"3013",
    "sg:province":"Bern",
    "wof:name":"Pd Dr.med. Willy H\u00e4nggi Spezialarzt Fmh",
    "wof:placetype":"venue"
},
  "geometry": {"coordinates":[7.454600811,46.9525337219],"type":"Point"}
}