{
  "type": "Feature",
  "properties": {
    "iso:country":"CH",
    "sg:address":"Brambergstrasse 18 3176 Neuenegg. Postfach",
    "sg:city":"Neuenegg",
    "sg:orig_category":"Grosshandel mit sonstigen Gebrauchs U Verbrauchsg\u00fctern",
    "sg:phone":"+41 31 741 45 81",
    "sg:postcode":"3176",
    "sg:province":"Bern",
    "wof:name":"Kocher Ch. Automaten",
    "wof:placetype":"venue"
},
  "geometry": {"coordinates":[7.2797431946,46.9071464539],"type":"Point"}
}