{
  "type": "Feature",
  "properties": {
    "addr:full":"Tambelstrasse 10 N\u00fcrensdorf Z\u00fcrich 8309",
    "addr:housenumber":"10",
    "addr:postcode":"8309",
    "addr:street":"Tambelstrasse",
    "iso:country":"CH",
    "sg:address":"Tambelstrasse 10",
    "sg:city":"N\u00fcrensdorf",
    "sg:orig_category":"Architektur U Ingenieurb\u00fcros",
    "sg:postcode":"8309",
    "sg:province":"Z\u00fcrich",
    "wof:name":"Bzv - Beratungszentrum F\u00fcr Vorsorge",
    "wof:placetype":"venue"
},
  "geometry": {"coordinates":[8.638892,47.462254],"type":"Point"}
}