{
  "type": "Feature",
  "properties": {
    "iso:country":"CH",
    "sg:address":"4574",
    "sg:city":"Nennigkofen",
    "sg:orig_category":"Pensionskassen",
    "sg:phone":"+41 32 625 70 25",
    "sg:postcode":"4574",
    "sg:province":"Solothurn",
    "wof:name":"Personalf\u00fcrsorgestiftung Der Firma Aeschlimann Ag",
    "wof:placetype":"venue"
},
  "geometry": {"coordinates":[7.4929361343,47.1867485046],"type":"Point"}
}