{
  "type": "Feature",
  "properties": {
    "iso:country":"CH",
    "sg:address":"Dammweg 2",
    "sg:city":"Uzwil",
    "sg:orig_category":"Sportvereine Ballsport Tischtennis",
    "sg:phone":"+41 71 951 16 37",
    "sg:postcode":"9240",
    "sg:province":"St. Gallen",
    "wof:name":"Ttc Uzwil",
    "wof:placetype":"venue"
},
  "geometry": {"coordinates":[9.1319093704,47.4368438721],"type":"Point"}
}