{
  "type": "Feature",
  "properties": {
    "addr:full":"Hammerstrasse 174 Basel Basel-Stadt 4057",
    "addr:housenumber":"174",
    "addr:postcode":"4057",
    "addr:street":"Hammerstrasse",
    "iso:country":"CH",
    "sg:address":"Hammerstrasse 174",
    "sg:city":"Basel",
    "sg:orig_category":"Bauspenglerei Zimmerei, Dachdeckerei, Bauspenglerei U Abdichtung",
    "sg:phone":"+41 31 332 44 52",
    "sg:postcode":"4057",
    "sg:province":"Basel-Stadt",
    "wof:name":"Fasel & Brunner Ag",
    "wof:placetype":"venue"
},
  "geometry": {"coordinates":[7.453355,46.960152],"type":"Point"}
}