{
  "type": "Feature",
  "properties": {
    "iso:country":"CH",
    "sg:address":"Sch\u00e4dr\u00fctistrasse 37 6006 Luzern. Postfach 719",
    "sg:city":"Luzern",
    "sg:orig_category":"Vereine Musik/Blasmusik",
    "sg:postcode":"6002",
    "sg:province":"Luzern",
    "wof:name":"Feldmusik Malters",
    "wof:placetype":"venue"
},
  "geometry": {"coordinates":[8.1382246017,47.0389785767],"type":"Point"}
}