{
  "type": "Feature",
  "properties": {
    "addr:full":"Industriestrasse 21 Bergdietikon Aargau 8962",
    "addr:housenumber":"21",
    "addr:postcode":"8962",
    "addr:street":"Industriestrasse",
    "iso:country":"CH",
    "sg:address":"Industriestrasse 21",
    "sg:city":"Bergdietikon",
    "sg:orig_category":"Autospenglereien",
    "sg:phone":"+41 17405155",
    "sg:postcode":"8962",
    "sg:province":"Aargau",
    "wof:name":"Carrosserie Walter H\u00e4usermann",
    "wof:placetype":"venue"
},
  "geometry": {"coordinates":[8.393324,47.38607],"type":"Point"}
}