{
  "type": "Feature",
  "properties": {
    "iso:country":"CH",
    "sg:address":"Aegertenstrasse 27",
    "sg:city":"Wynau",
    "sg:orig_category":"Maler U Glasergewerbe",
    "sg:phone":"+41 79 407 04 93",
    "sg:postcode":"4923",
    "sg:province":"Bern",
    "wof:name":"Streit Rudolf",
    "wof:placetype":"venue"
},
  "geometry": {"coordinates":[7.819920063,47.2574424744],"type":"Point"}
}