{
  "type": "Feature",
  "properties": {
    "iso:country":"CH",
    "sg:address":"Langholzstrasse 9",
    "sg:city":"H\u00fcnenberg",
    "sg:orig_category":"Hardwareberatung",
    "sg:phone":"+41 41 780 74 19",
    "sg:postcode":"6331",
    "sg:province":"Zug",
    "wof:name":"Htz High Tech Trading Ag",
    "wof:placetype":"venue"
},
  "geometry": {"coordinates":[8.4422340393,47.1706390381],"type":"Point"}
}