{
  "type": "Feature",
  "properties": {
    "iso:country":"CH",
    "sg:address":"Markusstrasse 16 8000 Z\u00fcrich. Postfach",
    "sg:city":"Z\u00fcrich",
    "sg:orig_category":"Unclassifiable Establishments",
    "sg:postcode":"8001",
    "sg:province":"Z\u00fcrich",
    "wof:name":"Anetmedia Gmbh",
    "wof:placetype":"venue"
},
  "geometry": {"coordinates":[8.5373783112,47.3881912231],"type":"Point"}
}