{
  "type": "Feature",
  "properties": {
    "iso:country":"CH",
    "sg:address":"Dachsluketen",
    "sg:city":"Rufi",
    "sg:orig_category":"Non-Classified Establishments",
    "sg:phone":"+41 55 619 58 00",
    "sg:postcode":"8723",
    "sg:province":"St. Gallen",
    "wof:name":"Inrel Ag",
    "wof:placetype":"venue"
},
  "geometry": {"coordinates":[9.0493240356,47.1895561218],"type":"Point"}
}