{
  "type": "Feature",
  "properties": {
    "addr:full":"Avenue De Ch\u00e2telaine 43 Gen\u00e8ve Gen\u00e8ve 1203",
    "addr:housenumber":"43",
    "addr:postcode":"1203",
    "addr:street":"Avenue De Cha\u0302Telaine",
    "iso:country":"CH",
    "sg:address":"Avenue De Ch\u00e2telaine 43",
    "sg:city":"Gen\u00e8ve",
    "sg:orig_category":"Bauspenglerei Zimmerei, Dachdeckerei, Bauspenglerei U Abdichtung",
    "sg:phone":"+41 22 796 47 73",
    "sg:postcode":"1203",
    "sg:province":"Gen\u00e8ve",
    "wof:name":"Curchod Fils Sa Installations Sanitaires Et Ferblanterie",
    "wof:placetype":"venue"
},
  "geometry": {"coordinates":[6.11616,46.210308],"type":"Point"}
}