{
  "type": "Feature",
  "properties": {
    "iso:country":"CH",
    "sg:address":"Rebbergstrasse 135",
    "sg:city":"Meilen",
    "sg:orig_category":"Non-Classified Establishments",
    "sg:postcode":"8706",
    "sg:province":"Z\u00fcrich",
    "wof:name":"E+e; Evaluation + Execution Consulting; Roland Hulliger + Co",
    "wof:placetype":"venue"
},
  "geometry": {"coordinates":[8.6245126724,47.2786636353],"type":"Point"}
}