{
  "type": "Feature",
  "properties": {
    "iso:country":"CH",
    "sg:address":"Via Al Fossato 8",
    "sg:city":"Giubiasco",
    "sg:orig_category":"Maler U Glasergewerbe Stukkateurgewerbe, Gipserei U Verputzerei",
    "sg:phone":"+41 91 857 33 85",
    "sg:postcode":"6512",
    "sg:province":"Ticino",
    "wof:name":"Antonio Corona",
    "wof:placetype":"venue"
},
  "geometry": {"coordinates":[9.0155515671,46.1797027588],"type":"Point"}
}