{
  "type": "Feature",
  "properties": {
    "iso:country":"CH",
    "sg:address":"Zumikerstrasse 33 8702 Zollikon. Postfach",
    "sg:city":"Zollikon",
    "sg:orig_category":"Architektur U Ingenieurb\u00fcros",
    "sg:postcode":"8702",
    "sg:province":"Z\u00fcrich",
    "wof:name":"Innenarchitektur, Limberger R. Innenarchitektur. Planung. Konzepte Und Gestaltung",
    "wof:placetype":"venue"
},
  "geometry": {"coordinates":[8.581923,47.335098],"type":"Point"}
}