{
  "type": "Feature",
  "properties": {
    "iso:country":"CH",
    "sg:address":"Fischerweg 9",
    "sg:city":"Bern",
    "sg:orig_category":"Arztpraxen",
    "sg:phone":"+41 31 301 71 71",
    "sg:postcode":"3012",
    "sg:province":"Bern",
    "wof:name":"Dr.med. Norbert Sch\u00fctz Spezialarzt Fmh",
    "wof:placetype":"venue"
},
  "geometry": {"coordinates":[7.436911,46.954414],"type":"Point"}
}