{
  "type": "Feature",
  "properties": {
    "iso:country":"CH",
    "sg:address":"3792",
    "sg:city":"Saanen",
    "sg:classifiers":[
        {
            "category":"Travel",
            "subcategory":"Hotels & Motels",
            "type":"Entertainment"
        }
    ],
    "sg:phone":"+41 33 744 15 15",
    "sg:postcode":"3792",
    "sg:province":"Bern",
    "sg:tags":[
        "hotels",
        "mit",
        "restaurant"
    ],
    "wof:name":"Hotel Saanerhof",
    "wof:placetype":"venue"
},
  "geometry": {"coordinates":[7.2361397743,46.463218689],"type":"Point"}
}