{
  "type": "Feature",
  "properties": {
    "iso:country":"CH",
    "sg:address":"Regensbergstrasse 1",
    "sg:city":"Kloten",
    "sg:orig_category":"Sonstiger Grosshandel",
    "sg:postcode":"8302",
    "sg:province":"Z\u00fcrich",
    "wof:name":"Saiko & Toth",
    "wof:placetype":"venue"
},
  "geometry": {"coordinates":[8.5760889053,47.4473152161],"type":"Point"}
}