{
  "type": "Feature",
  "properties": {
    "iso:country":"CH",
    "sg:address":"Muristrasse 42",
    "sg:city":"Bern",
    "sg:orig_category":"Detailhandel mit Uhren U Schmuck Fachdetailhandel in Verkaufsr\u00e4umen",
    "sg:phone":"+41 31 351 45 66",
    "sg:postcode":"3006",
    "sg:province":"Bern",
    "wof:name":"Atelier Jacaranda Weber Hugo + Co",
    "wof:placetype":"venue"
},
  "geometry": {"coordinates":[7.4636878967,46.9433364868],"type":"Point"}
}