{
  "type": "Feature",
  "properties": {
    "iso:country":"CH",
    "sg:address":"Feld\u00e4gerten 16",
    "sg:city":"Ober\u00f6nz",
    "sg:orig_category":"Physiotherapie",
    "sg:phone":"+41 41 670 10 15",
    "sg:postcode":"3363",
    "sg:province":"Bern",
    "wof:name":"Wilna Matthysse Physiotherapie",
    "wof:placetype":"venue"
},
  "geometry": {"coordinates":[8.2702703476,46.9404640198],"type":"Point"}
}