{
  "type": "Feature",
  "properties": {
    "iso:country":"CH",
    "sg:address":"3512",
    "sg:city":"Walkringen",
    "sg:orig_category":"Primarschulen",
    "sg:phone":"+41 31 701 13 68",
    "sg:postcode":"3512",
    "sg:province":"Bern",
    "wof:name":"Primarschule",
    "wof:placetype":"venue"
},
  "geometry": {"coordinates":[7.6175780296,46.9424552917],"type":"Point"}
}