{
  "type": "Feature",
  "properties": {
    "iso:country":"CH",
    "sg:address":"Bachd\u00f6rfli 22",
    "sg:city":"N\u00e4fels",
    "sg:orig_category":"Organisationen des Gesundheitswesen",
    "sg:phone":"+41 17640150",
    "sg:postcode":"8752",
    "sg:province":"Glarus",
    "wof:name":"Krankenpflegeverein Oberamt",
    "wof:placetype":"venue"
},
  "geometry": {"coordinates":[8.5353755951,47.2406692505],"type":"Point"}
}