{
  "type": "Feature",
  "properties": {
    "iso:country":"CH",
    "sg:address":"Siglimattstrasse 8",
    "sg:city":"Menziken",
    "sg:orig_category":"Mechanische Werkst\u00e4tten",
    "sg:phone":"+41 62 771 20 73",
    "sg:postcode":"5737",
    "sg:province":"Aargau",
    "wof:name":"Ernst Bolliger Schleiferei",
    "wof:placetype":"venue"
},
  "geometry": {"coordinates":[8.1959953308,47.2337303162],"type":"Point"}
}