{
  "type": "Feature",
  "properties": {
    "iso:country":"CH",
    "sg:address":"M\u00fchlentalstrasse 53",
    "sg:city":"Schaffhausen",
    "sg:orig_category":"Instandhaltung U Reparatur von Automobilen",
    "sg:phone":"+41 52 625 47 82",
    "sg:postcode":"8200",
    "sg:province":"Schaffhausen",
    "wof:name":"M\u00fchlentalgarage Palotas",
    "wof:placetype":"venue"
},
  "geometry": {"coordinates":[8.6291465759,47.702835083],"type":"Point"}
}