{
  "type": "Feature",
  "properties": {
    "iso:country":"CH",
    "sg:address":"Im Rotenbummert 2 9450 L\u00fcchingen. Postfach",
    "sg:city":"L\u00fcchingen",
    "sg:orig_category":"Elektroinstallation",
    "sg:phone":"+41 71 750 04 44",
    "sg:postcode":"9450",
    "sg:province":"St. Gallen",
    "wof:name":"Elektro Frei Rheintal Ag",
    "wof:placetype":"venue"
},
  "geometry": {"coordinates":[9.5516500473,47.385761261],"type":"Point"}
}