{
  "type": "Feature",
  "properties": {
    "iso:country":"CH",
    "sg:address":"Hirslanderstrasse 51",
    "sg:city":"Z\u00fcrich",
    "sg:orig_category":"Architekturb\u00fcros",
    "sg:phone":"+41 14212070",
    "sg:postcode":"8032",
    "sg:province":"Z\u00fcrich",
    "wof:name":"Erich M. & Isabelle Sp\u00e4h Architekturb\u00fcro",
    "wof:placetype":"venue"
},
  "geometry": {"coordinates":[8.571225,47.360638],"type":"Point"}
}