{
  "type": "Feature",
  "properties": {
    "iso:country":"CH",
    "sg:address":"Temple-neuf Rue Du 4",
    "sg:city":"Neuenburg",
    "sg:orig_category":"Herstellung von Uhren Herstellung von medizinischen U chirurgischen Ger\u00e4ten",
    "sg:phone":"+41 21 845 10 30",
    "sg:postcode":"2000",
    "sg:province":"Neuch\u00e2tel",
    "wof:name":"La Pierrette Sa",
    "wof:placetype":"venue"
},
  "geometry": {"coordinates":[6.2048711777,46.5788383484],"type":"Point"}
}