{
  "type": "Feature",
  "properties": {
    "iso:country":"CH",
    "sg:address":"Hotel Simmental 3766 Boltigen. Postfach",
    "sg:city":"Boltigen",
    "sg:classifiers":[
        {
            "category":"Travel",
            "subcategory":"Hotels & Motels",
            "type":"Entertainment"
        }
    ],
    "sg:postcode":"3766",
    "sg:province":"Bern",
    "sg:tags":[
        "hotels",
        "mit",
        "restaurant"
    ],
    "wof:name":"Moser Kurt Hotel-restaurant Simmental",
    "wof:placetype":"venue"
},
  "geometry": {"coordinates":[7.3905181885,46.6289710999],"type":"Point"}
}