{
  "type": "Feature",
  "properties": {
    "iso:country":"CH",
    "sg:address":"Biessenhofen",
    "sg:city":"Amriswil",
    "sg:orig_category":"Detailhandel mit Blumen U Pflanzen",
    "sg:phone":"+41 41 460 28 50",
    "sg:postcode":"8580",
    "sg:province":"Thurgau",
    "wof:name":"Hugo Gabriel",
    "wof:placetype":"venue"
},
  "geometry": {"coordinates":[8.223583,47.131149],"type":"Point"}
}