{
  "type": "Feature",
  "properties": {
    "iso:country":"CH",
    "sg:address":"Rue De La Fin Doie 8",
    "sg:city":"Bassecourt",
    "sg:orig_category":"Instandhaltung U Reparatur von Automobilen Tankstellen",
    "sg:phone":"+41 32 426 70 44",
    "sg:postcode":"2854",
    "sg:province":"Jura",
    "wof:name":"Serge Ross\u00e9 Sa Carrosserie & Garage Du Pray\u00e9",
    "wof:placetype":"venue"
},
  "geometry": {"coordinates":[7.2434229851,47.3354721069],"type":"Point"}
}