{
  "type": "Feature",
  "properties": {
    "iso:country":"CH",
    "sg:address":"Bretzwilerstrasse 2",
    "sg:city":"Nunningen",
    "sg:orig_category":"Gasth\u00f6fe/Gasth\u00e4user mit Restaurant",
    "sg:phone":"+41 31 829 11 00",
    "sg:postcode":"4208",
    "sg:province":"Solothurn",
    "wof:name":"Gasthof Zum Kreuz",
    "wof:placetype":"venue"
},
  "geometry": {"coordinates":[7.353536129,46.9713897705],"type":"Point"}
}