{
  "type": "Feature",
  "properties": {
    "iso:country":"CH",
    "sg:address":"Rodtmattstrasse 110",
    "sg:city":"Bern",
    "sg:orig_category":"Vereine Milit\u00e4r",
    "sg:postcode":"3014",
    "sg:province":"Bern",
    "wof:name":"Milit\u00e4rmotorfahrerverein Z\u00fcrcher Oberland Mvzo",
    "wof:placetype":"venue"
},
  "geometry": {"coordinates":[8.7645559311,47.3022460938],"type":"Point"}
}