{
  "type": "Feature",
  "properties": {
    "iso:country":"CH",
    "sg:address":"Immeuble Genziana B",
    "sg:city":"Montana-vermala",
    "sg:orig_category":"Arztpraxen",
    "sg:phone":"+41 24 495 27 77",
    "sg:postcode":"3962",
    "wof:name":"Dr M\u00e9d. Jacques-yves Lefaure M\u00e9decin G\u00e9n\u00e9raliste",
    "wof:placetype":"venue"
},
  "geometry": {"coordinates":[7.492434,46.314419],"type":"Point"}
}