{
  "type": "Feature",
  "properties": {
    "iso:country":"CH",
    "sg:address":"3285",
    "sg:city":"Galmiz",
    "sg:orig_category":"Allgemeiner Hoch U Tiefbau Allgemeiner Hochbau",
    "sg:phone":"+41 26 670 44 55",
    "sg:postcode":"3285",
    "sg:province":"Fribourg",
    "wof:name":"Suppa Ag, Bauunternehmung",
    "wof:placetype":"venue"
},
  "geometry": {"coordinates":[7.159175,46.94952],"type":"Point"}
}