{
  "type": "Feature",
  "properties": {
    "iso:country":"CH",
    "sg:address":"Gl\u00e2ne Route De La 107",
    "sg:city":"Villars-sur-gl\u00e2ne",
    "sg:orig_category":"Unclassifiable Establishments",
    "sg:phone":"+41 71 855 19 19",
    "sg:postcode":"1752",
    "sg:province":"Fribourg",
    "wof:name":"Vago Kreuzlingen Strassen-& Tiefbauunternehmung",
    "wof:placetype":"venue"
},
  "geometry": {"coordinates":[9.5423784256,47.4828567505],"type":"Point"}
}