{
  "type": "Feature",
  "properties": {
    "iso:country":"CH",
    "sg:address":"Via Alpsu 61",
    "sg:city":"Disentis/must\u00e9r",
    "sg:orig_category":"Bau von Sportanlagen Gartenbau",
    "sg:phone":"+41 81 947 40 50",
    "sg:postcode":"7180",
    "sg:province":"Graubunden",
    "wof:name":"Ignaz Deflorin & Olaf Bahnsen Garten-& Sportanlagen",
    "wof:placetype":"venue"
},
  "geometry": {"coordinates":[8.853363,46.705429],"type":"Point"}
}