{
  "type": "Feature",
  "properties": {
    "addr:full":"Hauptstr. 77 Degersheim St. Gallen 9113",
    "addr:housenumber":"77",
    "addr:postcode":"9113",
    "addr:street":"Hauptstr.",
    "iso:country":"CH",
    "sg:address":"Hauptstr. 77",
    "sg:city":"Degersheim",
    "sg:classifiers":[
        {
            "category":"Banks & Credit Unions",
            "subcategory":"Bank",
            "type":"Services"
        }
    ],
    "sg:phone":"+41 4171541422",
    "sg:postcode":"9113",
    "sg:province":"St. Gallen",
    "wof:name":"St. Gallische, Kantonalbank",
    "wof:placetype":"venue"
},
  "geometry": {"coordinates":[9.19699,47.372837],"type":"Point"}
}