{
  "type": "Feature",
  "properties": {
    "iso:country":"CH",
    "sg:address":"Unterer Altenberg 176",
    "sg:city":"Effingen",
    "sg:orig_category":"Bauspenglerei Schlossereien",
    "sg:phone":"+41 62 876 14 57",
    "sg:postcode":"5078",
    "sg:province":"Aargau",
    "wof:name":"Willy Tinner Spenglerei & Schlosserei",
    "wof:placetype":"venue"
},
  "geometry": {"coordinates":[8.097092,47.485538],"type":"Point"}
}