{
  "type": "Feature",
  "properties": {
    "iso:country":"CH",
    "sg:address":"Bleuen",
    "sg:city":"Oeschenbach",
    "sg:orig_category":"Bauschreinerei Herstellung von Konstruktionsteilen, Fertigbauteilen U Ausbauelementen aus Holz",
    "sg:phone":"+41 62 965 39 59",
    "sg:postcode":"4943",
    "sg:province":"Bern",
    "wof:name":"Wiedmer Ulrich",
    "wof:placetype":"venue"
},
  "geometry": {"coordinates":[7.7536,47.115345],"type":"Point"}
}