{
  "type": "Feature",
  "properties": {
    "iso:country":"CH",
    "sg:address":"Prop\u00e9raz",
    "sg:city":"Troistorrents",
    "sg:orig_category":"Grosshandel mit lebenden Tieren",
    "sg:phone":"+41 24 471 29 71",
    "sg:postcode":"1872",
    "sg:province":"Valais",
    "wof:name":"Andr\u00e9 Lange Commerce De B\u00e9tail",
    "wof:placetype":"venue"
},
  "geometry": {"coordinates":[6.9275779724,46.2398605347],"type":"Point"}
}