{
  "type": "Feature",
  "properties": {
    "iso:country":"CH",
    "sg:address":"Lindstrasse 40",
    "sg:city":"Winterthur",
    "sg:orig_category":"Detailhandel mit B\u00fcchern, Zeitungen, Schreib U Papeteriewaren Detailhandel mit Zeitungen U Zeitschri",
    "sg:phone":"+41 71 278 16 65",
    "sg:postcode":"8400",
    "sg:province":"Z\u00fcrich",
    "wof:name":"Schoch J\u00f6rg Kiosk Lachen",
    "wof:placetype":"venue"
},
  "geometry": {"coordinates":[9.35502,47.419571],"type":"Point"}
}