{
  "type": "Feature",
  "properties": {
    "iso:country":"CH",
    "sg:address":"Schiessstand Sturmboda",
    "sg:city":"Jenaz",
    "sg:orig_category":"Sportvereine Sch\u00fctzen",
    "sg:phone":"+41 81 332 41 49",
    "sg:postcode":"7233",
    "sg:province":"Graubunden",
    "wof:name":"Sch\u00fctzenverein Jenaz",
    "wof:placetype":"venue"
},
  "geometry": {"coordinates":[9.7187948227,46.9290618896],"type":"Point"}
}