{
  "type": "Feature",
  "properties": {
    "iso:country":"CH",
    "sg:address":"Centralstrasse 4",
    "sg:city":"Grenchen",
    "sg:orig_category":"Advokatur, Notariatsb\u00fcros",
    "sg:phone":"+41 71 277 07 07",
    "sg:postcode":"2540",
    "sg:province":"Solothurn",
    "wof:name":"B\u00fcrgi & Dahinden Rechtsanw\u00e4lte",
    "wof:placetype":"venue"
},
  "geometry": {"coordinates":[9.373629,47.426247],"type":"Point"}
}