{
  "type": "Feature",
  "properties": {
    "iso:country":"CH",
    "sg:address":"Maison-rouge 28 3960 Sierre Case Postale 354",
    "sg:city":"Sierre",
    "sg:orig_category":"Sanit\u00e4r U Heizungsinstallation",
    "sg:phone":"+41 27 455 09 45",
    "sg:postcode":"3960",
    "sg:province":"Valais",
    "wof:name":"Elcotherm Ag",
    "wof:placetype":"venue"
},
  "geometry": {"coordinates":[7.5229969025,46.2857246399],"type":"Point"}
}