{
  "type": "Feature",
  "properties": {
    "addr:full":"Kirchb\u00fchlweg 22 Bern Bern 3007",
    "addr:housenumber":"22",
    "addr:postcode":"3007",
    "addr:street":"Kirchbuehlweg",
    "iso:country":"CH",
    "sg:address":"Kirchb\u00fchlweg 22",
    "sg:city":"Bern",
    "sg:orig_category":"Arztpraxen",
    "sg:phone":"+41 31 371 88 33",
    "sg:postcode":"3007",
    "sg:province":"Bern",
    "wof:name":"Dr.med.peter Javet Spezialarzt Fmh",
    "wof:placetype":"venue"
},
  "geometry": {"coordinates":[7.423799,46.942387],"type":"Point"}
}