{
  "type": "Feature",
  "properties": {
    "iso:country":"CH",
    "sg:address":"Seidenfadenstrasse 22",
    "sg:city":"Unterseen",
    "sg:orig_category":"Sicherheitsdienste",
    "sg:postcode":"3800",
    "sg:province":"Bern",
    "wof:name":"Kurt Siegenthaler Sicherheitsdienst",
    "wof:placetype":"venue"
},
  "geometry": {"coordinates":[7.8422517776,46.6863098145],"type":"Point"}
}