{
  "type": "Feature",
  "properties": {
    "iso:country":"CH",
    "sg:address":"Steinacker",
    "sg:city":"Grindelwald",
    "sg:orig_category":"Herstellung von K\u00fcchenm\u00f6beln",
    "sg:phone":"+41 33 853 43 65",
    "sg:postcode":"3818",
    "sg:province":"Bern",
    "wof:name":"Weiss K\u00fcchen Ag",
    "wof:placetype":"venue"
},
  "geometry": {"coordinates":[8.0642585754,46.6308174133],"type":"Point"}
}