{
  "type": "Feature",
  "properties": {
    "iso:country":"CH",
    "sg:address":"Rue De La Pr\u00e9fecture 10",
    "sg:city":"Del\u00e9mont",
    "sg:orig_category":"Vermietung U Verpachtung von eigenen Immobilien",
    "sg:postcode":"2800",
    "sg:province":"Jura",
    "wof:name":"Jmri Promotion Sa",
    "wof:placetype":"venue"
},
  "geometry": {"coordinates":[7.3440089226,47.3660163879],"type":"Point"}
}