{
  "type": "Feature",
  "properties": {
    "addr:full":"Lindenstrasse 18 Binningen Basel-Landschaft 4102",
    "addr:housenumber":"18",
    "addr:postcode":"4102",
    "addr:street":"Lindenstrasse",
    "iso:country":"CH",
    "sg:address":"Lindenstrasse 18",
    "sg:city":"Binningen",
    "sg:classifiers":[
        {
            "category":"Professional",
            "subcategory":"Art Services",
            "type":"Services"
        }
    ],
    "sg:phone":"+41 61 313 00 02",
    "sg:postcode":"4102",
    "sg:province":"Basel-Landschaft",
    "sg:tags":[
        "design",
        "audio-visual"
    ],
    "wof:name":"Av+partner Ag",
    "wof:placetype":"venue"
},
  "geometry": {"coordinates":[7.570151,47.530819],"type":"Point"}
}