{
  "type": "Feature",
  "properties": {
    "iso:country":"CH",
    "sg:address":"Beim Schulhaus",
    "sg:city":"Br\u00fclisau",
    "sg:orig_category":"Wasserversorgung",
    "sg:phone":"+41 71 799 12 77",
    "sg:postcode":"9058",
    "sg:province":"Appenzell Innerhoden",
    "wof:name":"Wasserkorporation R\u00fcte",
    "wof:placetype":"venue"
},
  "geometry": {"coordinates":[9.4545249939,47.2966156006],"type":"Point"}
}