{
  "type": "Feature",
  "properties": {
    "iso:country":"CH",
    "sg:address":"Bahnhofstrasse 14 6430 Schwyz. Postfach 462",
    "sg:city":"Schwyz",
    "sg:orig_category":"Landesverteidigung",
    "sg:phone":"+41 41 819 11 24",
    "sg:postcode":"6431",
    "sg:province":"Schwyz",
    "wof:name":"Milit\u00e4rdepartement Des Kantons Schwyz",
    "wof:placetype":"venue"
},
  "geometry": {"coordinates":[8.6488275528,47.0217971802],"type":"Point"}
}