{
  "type": "Feature",
  "properties": {
    "iso:country":"CH",
    "sg:address":"Dorf",
    "sg:city":"Sangernboden",
    "sg:orig_category":"Erdbewegungsarbeiten G\u00fcterbef\u00f6rderung im Strassenverkehr",
    "sg:phone":"+41 19303724",
    "sg:postcode":"1738",
    "sg:province":"Bern",
    "wof:name":"Zentner Ag Tbt Bagger-& Transportgesch\u00e4ft",
    "wof:placetype":"venue"
},
  "geometry": {"coordinates":[8.7934904099,47.3275604248],"type":"Point"}
}