{
  "type": "Feature",
  "properties": {
    "iso:country":"CH",
    "sg:address":"Kr\u00e4bel",
    "sg:city":"Goldau",
    "sg:orig_category":"Mechanische Werkst\u00e4tten",
    "sg:phone":"+41 56 496 21 61",
    "sg:postcode":"6410",
    "sg:province":"Schwyz",
    "wof:name":"Josef Fischer Mechanische Werkst\u00e4tte",
    "wof:placetype":"venue"
},
  "geometry": {"coordinates":[8.3100805283,47.4007339478],"type":"Point"}
}