{
  "type": "Feature",
  "properties": {
    "iso:country":"CH",
    "sg:address":"Bahnhofstrasse 22",
    "sg:city":"Ebikon",
    "sg:orig_category":"Unclassifiable Establishments",
    "sg:postcode":"6030",
    "sg:province":"Luzern",
    "wof:name":"Club Mate Loscher",
    "wof:placetype":"venue"
},
  "geometry": {"coordinates":[8.3439531326,47.0850372314],"type":"Point"}
}