{
  "type": "Feature",
  "properties": {
    "iso:country":"CH",
    "sg:address":"Hauptstrasse 82",
    "sg:city":"Schwaderloch",
    "sg:orig_category":"Herstellung von Metallkonstruktionen Stahl U Leichtmetallbau",
    "sg:phone":"+41 56 247 17 66",
    "sg:postcode":"5326",
    "sg:province":"Aargau",
    "wof:name":"Fixtr\u00e4ger Ag",
    "wof:placetype":"venue"
},
  "geometry": {"coordinates":[8.1484689713,47.5871505737],"type":"Point"}
}