{
  "type": "Feature",
  "properties": {
    "iso:country":"CH",
    "sg:address":"Mattenstrasse 3",
    "sg:city":"Aegerten",
    "sg:orig_category":"Gymnastik U Fitnesszentren",
    "sg:phone":"+41 32 373 37 43",
    "sg:postcode":"2558",
    "sg:province":"Bern",
    "wof:name":"La Palma Fitness-center",
    "wof:placetype":"venue"
},
  "geometry": {"coordinates":[7.2903270721,47.1194000244],"type":"Point"}
}