{
  "type": "Feature",
  "properties": {
    "iso:country":"CH",
    "sg:address":"Schlachthofstrasse 35 8202 Schaffhausen. Postfach 547",
    "sg:city":"Schaffhausen",
    "sg:orig_category":"Pensionskassen",
    "sg:postcode":"8200",
    "sg:province":"Schaffhausen",
    "wof:name":"Wohlfahrtsfonds F\u00fcr Die Angestellten Und Arbeiter Der Schweizerischen Seil-industrie Ag",
    "wof:placetype":"venue"
},
  "geometry": {"coordinates":[8.6523933411,47.712097168],"type":"Point"}
}