{
  "type": "Feature",
  "properties": {
    "iso:country":"CH",
    "sg:address":"Neugutstrasse 66",
    "sg:city":"D\u00fcbendorf",
    "sg:orig_category":"Interessenvertretungen",
    "sg:postcode":"8600",
    "sg:province":"Z\u00fcrich",
    "wof:name":"Verband Schweizerischer Leasing-berater",
    "wof:placetype":"venue"
},
  "geometry": {"coordinates":[8.6065063477,47.4005508423],"type":"Point"}
}