{
  "type": "Feature",
  "properties": {
    "iso:country":"CH",
    "sg:address":"Steigstrasse 48",
    "sg:city":"Klingnau",
    "sg:orig_category":"Sportvereine Ballsport Tennis",
    "sg:phone":"+41 56 245 28 79",
    "sg:postcode":"5313",
    "sg:province":"Aargau",
    "wof:name":"Tc Triumph International",
    "wof:placetype":"venue"
},
  "geometry": {"coordinates":[8.2470464706,47.5856819153],"type":"Point"}
}