{
  "type": "Feature",
  "properties": {
    "iso:country":"CH",
    "sg:address":"Via Chiasso",
    "sg:city":"Iragna",
    "sg:orig_category":"Maler U Glasergewerbe Malerei",
    "sg:phone":"+41 91 862 13 38",
    "sg:postcode":"6707",
    "sg:province":"Ticino",
    "wof:name":"Sabbadin & Brancato Sa",
    "wof:placetype":"venue"
},
  "geometry": {"coordinates":[8.9680175781,46.330280304],"type":"Point"}
}