{
  "type": "Feature",
  "properties": {
    "iso:country":"CH",
    "sg:address":"Via Tersaggio 8",
    "sg:city":"Comano",
    "sg:orig_category":"Herstellung von Werkzeugmaschinen",
    "sg:phone":"+41 32 341 68 44",
    "sg:postcode":"6949",
    "sg:province":"Ticino",
    "wof:name":"Stein Dr. Hans-ulrich",
    "wof:placetype":"venue"
},
  "geometry": {"coordinates":[8.9608802795,46.0379714966],"type":"Point"}
}