{
  "type": "Feature",
  "properties": {
    "iso:country":"CH",
    "sg:address":"Seeweg 30",
    "sg:city":"Altendorf",
    "sg:orig_category":"Sportvereine Velo Rad-& Motorfahrer-Bund SRB",
    "sg:postcode":"8852",
    "sg:province":"Schwyz",
    "wof:name":"Veloclub Racing Luzern",
    "wof:placetype":"venue"
},
  "geometry": {"coordinates":[8.3082399368,47.0456581116],"type":"Point"}
}