{
  "type": "Feature",
  "properties": {
    "addr:full":"Peney Satigny Gen\u00e8ve 1242",
    "addr:postcode":"1242",
    "iso:country":"CH",
    "sg:address":"Peney",
    "sg:city":"Satigny",
    "sg:orig_category":"Abwasserreinigung",
    "sg:phone":"+41 22 753 13 45",
    "sg:postcode":"1242",
    "sg:province":"Gen\u00e8ve",
    "wof:name":"Station D'epuration Du Nant-d'avril",
    "wof:placetype":"venue"
},
  "geometry": {"coordinates":[6.0426,46.201241],"type":"Point"}
}