{
  "type": "Feature",
  "properties": {
    "iso:country":"CH",
    "sg:address":"Oberer Saltinadamm 4",
    "sg:city":"Brig",
    "sg:orig_category":"Sonstiger Grosshandel",
    "sg:postcode":"3900",
    "sg:province":"Valais",
    "wof:name":"Source Gmbh",
    "wof:placetype":"venue"
},
  "geometry": {"coordinates":[8.7637605667,47.1964530945],"type":"Point"}
}