{
  "type": "Feature",
  "properties": {
    "iso:country":"CH",
    "sg:address":"R\u00f6telbachstrasse 23",
    "sg:city":"Oensingen",
    "sg:orig_category":"Politische Parteien CVP",
    "sg:postcode":"4702",
    "sg:province":"Solothurn",
    "wof:name":"Cvp Ortspartei Oetwil Am See",
    "wof:placetype":"venue"
},
  "geometry": {"coordinates":[8.7217645645,47.269908905],"type":"Point"}
}