{
  "type": "Feature",
  "properties": {
    "iso:country":"CH",
    "sg:address":"Baarerstrasse 112 6300 Zug. Postfach",
    "sg:city":"Zug",
    "sg:orig_category":"Unclassifiable Establishments",
    "sg:postcode":"6300",
    "sg:province":"Zug",
    "wof:name":"Fadi\u00e8se Musique, Robert Flaction",
    "wof:placetype":"venue"
},
  "geometry": {"coordinates":[12.5734100342,42.5029983521],"type":"Point"}
}