{
  "type": "Feature",
  "properties": {
    "iso:country":"CH",
    "sg:address":"Oberebnetstrasse 13",
    "sg:city":"Frick",
    "sg:orig_category":"Wirtschaftspr\u00fcfung, Steuerberatung U Treuhand",
    "sg:phone":"+41 62 871 73 13",
    "sg:postcode":"5070",
    "sg:province":"Aargau",
    "wof:name":"Gss Treuhand Gmbh",
    "wof:placetype":"venue"
},
  "geometry": {"coordinates":[8.0233249664,47.5061149597],"type":"Point"}
}