{
  "type": "Feature",
  "properties": {
    "iso:country":"CH",
    "sg:address":"Neuhof 43",
    "sg:city":"Buus",
    "sg:orig_category":"Spezieller Tiefbau Strassenbau",
    "sg:phone":"+41 61 841 05 39",
    "sg:postcode":"4463",
    "sg:province":"Basel-Landschaft",
    "wof:name":"Simon Gisin Strassen-& Bodensanierungen",
    "wof:placetype":"venue"
},
  "geometry": {"coordinates":[7.8598370552,47.5081520081],"type":"Point"}
}