{
  "type": "Feature",
  "properties": {
    "iso:country":"CH",
    "sg:address":"Boulevard De La Cluse 105",
    "sg:city":"Gen\u00e8ve",
    "sg:orig_category":"Detailhandel mit Waren verschiedener Art, Hauptrichtung Nahrungsmittel",
    "sg:phone":"+41 22 321 11 39",
    "sg:postcode":"1205",
    "sg:province":"Gen\u00e8ve",
    "wof:name":"Bma Magasin D'alimentation",
    "wof:placetype":"venue"
},
  "geometry": {"coordinates":[6.1485280991,46.1956443787],"type":"Point"}
}