{
  "type": "Feature",
  "properties": {
    "addr:full":"Wesemlinrain 20 Luzern Luzern 6006",
    "addr:housenumber":"20",
    "addr:postcode":"6006",
    "addr:street":"Wesemlinrain",
    "iso:country":"CH",
    "sg:address":"Wesemlinrain 20",
    "sg:city":"Luzern",
    "sg:classifiers":[
        {
            "category":"Home & Garden",
            "subcategory":"Building Materials",
            "type":"Retail Goods"
        }
    ],
    "sg:phone":"+41 41 410 71 58",
    "sg:postcode":"6006",
    "sg:province":"Luzern",
    "sg:tags":[
        "glass",
        "enclosures",
        "balcony"
    ],
    "wof:name":"Bruno Zettel Ag",
    "wof:placetype":"venue"
},
  "geometry": {"coordinates":[8.31092,47.060043],"type":"Point"}
}