{
  "type": "Feature",
  "properties": {
    "iso:country":"CH",
    "sg:address":"Reposoir Chemin Du 7",
    "sg:city":"Nyon",
    "sg:orig_category":"G\u00fcterbef\u00f6rderung im Strassenverkehr",
    "sg:phone":"+41 56 282 52 70",
    "sg:postcode":"1260",
    "sg:province":"Vaud",
    "wof:name":"Hertig Hanspeter, Transporte",
    "wof:placetype":"venue"
},
  "geometry": {"coordinates":[8.2968130112,47.4891281128],"type":"Point"}
}