{
  "type": "Feature",
  "properties": {
    "iso:country":"CH",
    "sg:address":"Engi 2",
    "sg:city":"B\u00fctschwil",
    "sg:orig_category":"Zimmerei, Dachdeckerei, Bauspenglerei U Abdichtung",
    "sg:phone":"+41 71 983 18 14",
    "sg:postcode":"9606",
    "sg:province":"St. Gallen",
    "wof:name":"Artho Meinrad Holzbau Ag",
    "wof:placetype":"venue"
},
  "geometry": {"coordinates":[9.0771398544,47.3708953857],"type":"Point"}
}