{
  "type": "Feature",
  "properties": {
    "iso:country":"CH",
    "sg:address":"Ch. De La Bruy\u00e8re 33",
    "sg:city":"Pully",
    "sg:orig_category":"Architektur U Ingenieurb\u00fcros",
    "sg:postcode":"1009",
    "sg:province":"Vaud",
    "wof:name":"Bureau D'ing\u00e9nieur Brunner",
    "wof:placetype":"venue"
},
  "geometry": {"coordinates":[6.664496,46.525482],"type":"Point"}
}