{
  "type": "Feature",
  "properties": {
    "iso:country":"CH",
    "sg:address":"Gemmo Via 11 6900 Lugano. Postfach",
    "sg:city":"Locarno",
    "sg:orig_category":"Interessenvertretungen",
    "sg:postcode":"6604",
    "sg:province":"Ticino",
    "wof:name":"Unione Svizzera Dei Fiduciari, Sezione Ticino",
    "wof:placetype":"venue"
},
  "geometry": {"coordinates":[8.9361124039,46.0086898804],"type":"Point"}
}