{
  "type": "Feature",
  "properties": {
    "iso:country":"CH",
    "sg:address":"Bienenweg 24.",
    "sg:city":"Therwil",
    "sg:orig_category":"Wirtschaftspr\u00fcfung, Steuerberatung U Treuhand",
    "sg:phone":"+41 56 470 06 26",
    "sg:postcode":"4106",
    "sg:province":"Basel-Landschaft",
    "wof:name":"Lanter & Partner Gmbh Treuhand-revisions-steuer-cont",
    "wof:placetype":"venue"
},
  "geometry": {"coordinates":[8.2869291306,47.4561080933],"type":"Point"}
}