{
  "type": "Feature",
  "properties": {
    "iso:country":"CH",
    "sg:address":"Dorfstrasse 3",
    "sg:city":"Niederhasli",
    "sg:orig_category":"Nationale Postdienste",
    "sg:phone":"+41 18501165",
    "sg:postcode":"8155",
    "sg:province":"Z\u00fcrich",
    "wof:name":"Die Schweizerische Post",
    "wof:placetype":"venue"
},
  "geometry": {"coordinates":[8.4844427109,47.4808425903],"type":"Point"}
}