{
  "type": "Feature",
  "properties": {
    "iso:country":"CH",
    "sg:address":"R\u00e4tikonstrasse 13 9490 Vaduz. Postfach 11",
    "sg:city":"Vaduz",
    "sg:orig_category":"Lebensversicherung",
    "sg:phone":"+423 236 15 45",
    "sg:postcode":"9490",
    "wof:name":"Fortuna Lebens-versicherungs Aktiengesellschaft",
    "wof:placetype":"venue"
},
  "geometry": {"coordinates":[9.519118309,47.1345977783],"type":"Point"}
}