{
  "type": "Feature",
  "properties": {
    "iso:country":"CH",
    "sg:address":"Valais Rue Du 20 1202 Gen\u00e8ve. Postfach",
    "sg:city":"Gen\u00e8ve",
    "sg:orig_category":"Herstellung von sonstigen elektrischen Ausr\u00fcstungen",
    "sg:phone":"+41 22 733 30 29",
    "sg:postcode":"1202",
    "sg:province":"Gen\u00e8ve",
    "wof:name":"Rabunal, Electrostar",
    "wof:placetype":"venue"
},
  "geometry": {"coordinates":[6.1414580345,46.2165756226],"type":"Point"}
}