{
  "type": "Feature",
  "properties": {
    "iso:country":"CH",
    "sg:address":"Goldgasse 9 4710 Balsthal. Postfach 213",
    "sg:city":"Balsthal",
    "sg:orig_category":"Drogerien",
    "sg:phone":"+41 62 391 32 76",
    "sg:postcode":"4710",
    "sg:province":"Solothurn",
    "wof:name":"Drogerie M\u00fcller Ag",
    "wof:placetype":"venue"
},
  "geometry": {"coordinates":[7.6954421997,47.31640625],"type":"Point"}
}