{
  "type": "Feature",
  "properties": {
    "iso:country":"CH",
    "sg:address":"Bachtelweg 12",
    "sg:city":"Volketswil",
    "sg:orig_category":"Herstellung von Bergwerks U Baumaschinen",
    "sg:phone":"+41 19460288",
    "sg:postcode":"8604",
    "sg:province":"Z\u00fcrich",
    "wof:name":"Gnehm Albert Gmbh",
    "wof:placetype":"venue"
},
  "geometry": {"coordinates":[8.6819067001,47.3899307251],"type":"Point"}
}