{
  "type": "Feature",
  "properties": {
    "iso:country":"CH",
    "sg:address":"Industriestrasse 30 8112 Otelfingen. Postfach",
    "sg:city":"Otelfingen",
    "sg:orig_category":"Handel mit Motorr\u00e4dern, Teilen U Zubeh\u00f6r Instandhaltung U Reparatur von Motorr\u00e4dern",
    "sg:phone":"+41 18443411",
    "sg:postcode":"8112",
    "sg:province":"Z\u00fcrich",
    "wof:name":"Baltensperger + Partner Ag",
    "wof:placetype":"venue"
},
  "geometry": {"coordinates":[8.401301384,47.4574546814],"type":"Point"}
}