{
  "type": "Feature",
  "properties": {
    "iso:country":"CH",
    "sg:address":"Platz 234",
    "sg:city":"Walzenhausen",
    "sg:orig_category":"Naturheil\u00e4rzte and Heilpraktiker",
    "sg:phone":"+41 71 333 26 27",
    "sg:postcode":"9428",
    "sg:province":"Appenzell Ausserrhoden",
    "wof:name":"Richard Lengwiler Naturheilpraxis",
    "wof:placetype":"venue"
},
  "geometry": {"coordinates":[9.3842172623,47.3907661438],"type":"Point"}
}