{
  "type": "Feature",
  "properties": {
    "iso:country":"CH",
    "sg:address":"Alte Winterthurerstrasse 62 8304 Wallisellen. Postfach",
    "sg:city":"Wallisellen",
    "sg:classifiers":[
        {
            "category":"Restaurant",
            "type":"Food & Drink"
        }
    ],
    "sg:phone":"+41 18313022",
    "sg:postcode":"8304",
    "sg:province":"Z\u00fcrich",
    "wof:name":"Restaurant Hallen-& Freibad",
    "wof:placetype":"venue"
},
  "geometry": {"coordinates":[8.5941991806,47.4178009033],"type":"Point"}
}