{
  "type": "Feature",
  "properties": {
    "iso:country":"CH",
    "sg:address":"Kesswiler Str. 16",
    "sg:city":"Dozwil",
    "sg:classifiers":[
        {
            "category":"Banks & Credit Unions",
            "subcategory":"Bank",
            "type":"Services"
        }
    ],
    "sg:phone":"+41 62 849 23 13",
    "sg:postcode":"8580",
    "sg:province":"Thurgau",
    "wof:name":"Raiffeisenbank D\u00e4niken-gretzenbach",
    "wof:placetype":"venue"
},
  "geometry": {"coordinates":[7.98116,47.35009],"type":"Point"}
}