{
  "type": "Feature",
  "properties": {
    "iso:country":"CH",
    "sg:address":"2873",
    "sg:city":"Saulcy",
    "sg:orig_category":"Stukkateurgewerbe, Gipserei U Verputzerei",
    "sg:phone":"+41 32 433 45 37",
    "sg:postcode":"2873",
    "sg:province":"Jura",
    "wof:name":"Marco Willemin",
    "wof:placetype":"venue"
},
  "geometry": {"coordinates":[7.1539092064,47.3017807007],"type":"Point"}
}