{
  "type": "Feature",
  "properties": {
    "iso:country":"CH",
    "sg:address":"Windeggstrasse 5",
    "sg:city":"Niederurnen",
    "sg:orig_category":"Maler U Glasergewerbe Tapeziererei",
    "sg:phone":"+41 55 610 30 63",
    "sg:postcode":"8867",
    "sg:province":"Glarus",
    "wof:name":"Maler Menzi Ag",
    "wof:placetype":"venue"
},
  "geometry": {"coordinates":[9.0552597046,47.1306648254],"type":"Point"}
}