{
  "type": "Feature",
  "properties": {
    "iso:country":"CH",
    "sg:address":"Schaffhauserstrasse",
    "sg:city":"Uesslingen",
    "sg:classifiers":[
        {
            "category":"Restaurant",
            "type":"Food & Drink"
        }
    ],
    "sg:phone":"+41 62 295 10 98",
    "sg:postcode":"8524",
    "sg:province":"Thurgau",
    "wof:name":"Restaurant Engelberg",
    "wof:placetype":"venue"
},
  "geometry": {"coordinates":[7.9489102364,47.335269928],"type":"Point"}
}