{
  "type": "Feature",
  "properties": {
    "iso:country":"CH",
    "sg:address":"Romanshornerstrasse 115",
    "sg:city":"Wittenbach",
    "sg:orig_category":"Autogaragen",
    "sg:phone":"+41 71 298 44 11",
    "sg:postcode":"9303",
    "wof:name":"Werner Sonderer Garage",
    "wof:placetype":"venue"
},
  "geometry": {"coordinates":[9.373714,47.462959],"type":"Point"}
}