{
  "type": "Feature",
  "properties": {
    "iso:country":"CH",
    "sg:address":"Bahnhofstrasse 15 6003 Luzern. Postfach",
    "sg:city":"Luzern",
    "sg:orig_category":"Polizei",
    "sg:phone":"+41 41 228 51 11",
    "sg:postcode":"6002",
    "sg:province":"Luzern",
    "wof:name":"Polizei-& Umweltschutzdepartement",
    "wof:placetype":"venue"
},
  "geometry": {"coordinates":[8.304391861,47.0503959656],"type":"Point"}
}