{
  "type": "Feature",
  "properties": {
    "iso:country":"CH",
    "sg:address":"Brunnadernstrasse 36",
    "sg:city":"Bern",
    "sg:orig_category":"Unternehmensberatung Weiterbildungskurse and Seminar Anbieter",
    "sg:postcode":"3006",
    "sg:province":"Bern",
    "wof:name":"Bolzer Outdoor Experiences Events",
    "wof:placetype":"venue"
},
  "geometry": {"coordinates":[7.4631662369,46.9393234253],"type":"Point"}
}