{
  "type": "Feature",
  "properties": {
    "iso:country":"CH",
    "sg:address":"Arbonerstrasse 46",
    "sg:city":"Amriswil",
    "sg:classifiers":[
        {
            "category":"Restaurant",
            "type":"Food & Drink"
        }
    ],
    "sg:phone":"+41 71 411 14 28",
    "sg:postcode":"8580",
    "sg:province":"Thurgau",
    "wof:name":"R\u00f6ssli Hemmerswil Restaurant",
    "wof:placetype":"venue"
},
  "geometry": {"coordinates":[9.304933548,47.5439491272],"type":"Point"}
}