{
  "type": "Feature",
  "properties": {
    "iso:country":"CH",
    "sg:address":"Rue Du Colonel Buchwalder 17",
    "sg:city":"Del\u00e9mont",
    "sg:orig_category":"Sportvereine Turnen",
    "sg:phone":"+41 32 422 77 04",
    "sg:postcode":"2800",
    "sg:province":"Jura",
    "wof:name":"St\u00e9 De Gymnastique Choindez",
    "wof:placetype":"venue"
},
  "geometry": {"coordinates":[7.3364171982,47.3644256592],"type":"Point"}
}