{
  "type": "Feature",
  "properties": {
    "iso:country":"CH",
    "sg:address":"Passage",
    "sg:city":"Grindelwald",
    "sg:orig_category":"Grosshandel mit Textilien Stickerei",
    "sg:phone":"+41 33 853 66 75",
    "sg:postcode":"3818",
    "sg:province":"Bern",
    "wof:name":"Classic Textile Gmbh",
    "wof:placetype":"venue"
},
  "geometry": {"coordinates":[8.0346326828,46.624370575],"type":"Point"}
}