{
  "type": "Feature",
  "properties": {
    "iso:country":"CH",
    "sg:address":"Wampflenstrasse 45 8706 Meilen. Postfach",
    "sg:city":"Meilen",
    "sg:orig_category":"Pensionskassen",
    "sg:phone":"+41 13885555",
    "sg:postcode":"8706",
    "sg:province":"Z\u00fcrich",
    "wof:name":"Personalvorsorge-stiftung Der Ata W\u00e4rmez\u00e4hler Ag (bvg)",
    "wof:placetype":"venue"
},
  "geometry": {"coordinates":[8.6433620453,47.2745742798],"type":"Point"}
}