{
  "type": "Feature",
  "properties": {
    "iso:country":"CH",
    "sg:address":"Hauptstrasse 43",
    "sg:city":"K\u00fcttigen",
    "sg:orig_category":"Physiotherapie",
    "sg:phone":"+41 62 827 18 72",
    "sg:postcode":"5024",
    "sg:province":"Aargau",
    "wof:name":"Theres Schaub Physiotherapie",
    "wof:placetype":"venue"
},
  "geometry": {"coordinates":[8.0472135544,47.4166030884],"type":"Point"}
}