{
  "type": "Feature",
  "properties": {
    "iso:country":"CH",
    "sg:address":"Rue Du Vuache 1",
    "sg:city":"Gen\u00e8ve",
    "sg:classifiers":[
        {
            "category":"Restaurant",
            "type":"Food & Drink"
        }
    ],
    "sg:phone":"+41 22 344 83 65",
    "sg:postcode":"1201",
    "sg:province":"Gen\u00e8ve",
    "wof:name":"Restaurant-pizzeria Tirami-su",
    "wof:placetype":"venue"
},
  "geometry": {"coordinates":[6.1379570961,46.2074966431],"type":"Point"}
}