{
  "type": "Feature",
  "properties": {
    "iso:country":"CH",
    "sg:address":"Rosenweg 29 4500 Solothurn. Postfach",
    "sg:city":"Solothurn",
    "sg:orig_category":"Rechtsberatung",
    "sg:postcode":"4500",
    "sg:province":"Solothurn",
    "wof:name":"Amiet Marianne",
    "wof:placetype":"venue"
},
  "geometry": {"coordinates":[7.5461192131,47.2107162476],"type":"Point"}
}