{
  "type": "Feature",
  "properties": {
    "iso:country":"CH",
    "sg:address":"Pfrundmatte 6",
    "sg:city":"Neuenkirch",
    "sg:orig_category":"Grosshandel mit lebenden Tieren",
    "sg:phone":"+41 41 280 13 47",
    "sg:postcode":"6206",
    "sg:province":"Luzern",
    "wof:name":"Wolfisberg Hans",
    "wof:placetype":"venue"
},
  "geometry": {"coordinates":[8.2030706406,47.1008110046],"type":"Point"}
}