{
  "type": "Feature",
  "properties": {
    "iso:country":"CH",
    "sg:address":"Badenerstrasse 333",
    "sg:city":"Z\u00fcrich",
    "sg:orig_category":"Fahrschulen, Flugschulen",
    "sg:phone":"+41 41 340 59 29",
    "sg:postcode":"8003",
    "sg:province":"Z\u00fcrich",
    "wof:name":"Fahrschule-center Am Albisriederplatz Deniz",
    "wof:placetype":"venue"
},
  "geometry": {"coordinates":[8.5113344193,47.3776931763],"type":"Point"}
}