{
  "type": "Feature",
  "properties": {
    "iso:country":"CH",
    "sg:address":"1586",
    "sg:city":"Vallamand",
    "sg:classifiers":[
        {
            "category":"Restaurant",
            "type":"Food & Drink"
        }
    ],
    "sg:phone":"+41 26 677 13 05",
    "sg:postcode":"1586",
    "sg:province":"Vaud",
    "wof:name":"Caf\u00e9 Commerce",
    "wof:placetype":"venue"
},
  "geometry": {"coordinates":[7.0417699814,46.929599762],"type":"Point"}
}