{
  "type": "Feature",
  "properties": {
    "iso:country":"CH",
    "sg:address":"Mittelg\u00e4ustr. 444",
    "sg:city":"Kappel",
    "sg:classifiers":[
        {
            "category":"Banks & Credit Unions",
            "subcategory":"Bank",
            "type":"Services"
        }
    ],
    "sg:phone":"+41 4162461274",
    "sg:postcode":"4616",
    "sg:province":"Solothurn",
    "wof:name":"Raiffeisenbank Kappel-boningen",
    "wof:placetype":"venue"
},
  "geometry": {"coordinates":[7.849198,47.324932],"type":"Point"}
}