{
  "type": "Feature",
  "properties": {
    "iso:country":"CH",
    "sg:address":"Im Zentrum 7b",
    "sg:city":"Adligenswil",
    "sg:orig_category":"Fotografische Ateliers",
    "sg:phone":"+41 41 370 64 35",
    "sg:postcode":"6043",
    "sg:province":"Luzern",
    "wof:name":"Beat Wenzinger Fotograf",
    "wof:placetype":"venue"
},
  "geometry": {"coordinates":[8.3628196716,47.0724906921],"type":"Point"}
}