{
  "type": "Feature",
  "properties": {
    "iso:country":"CH",
    "sg:address":"Roamerstrasse 12 4500 Solothurn. Postfach",
    "sg:city":"Solothurn",
    "sg:orig_category":"Herstellung von Ger\u00e4ten der Elektrizit\u00e4tserzeugung, -verteilung u.\u00e4. -Herstellung von sonstigen elek",
    "sg:phone":"+41 32 622 69 01",
    "sg:postcode":"4503",
    "sg:province":"Solothurn",
    "wof:name":"Reprinta Ag",
    "wof:placetype":"venue"
},
  "geometry": {"coordinates":[7.5217628479,47.2137985229],"type":"Point"}
}