{
  "type": "Feature",
  "properties": {
    "addr:full":"Rue Agasse 45 Gen\u00e8ve Gen\u00e8ve 1208",
    "addr:housenumber":"45",
    "addr:postcode":"1208",
    "addr:street":"Rue Agasse",
    "iso:country":"CH",
    "sg:address":"Rue Agasse 45",
    "sg:city":"Gen\u00e8ve",
    "sg:orig_category":"Arztpraxen",
    "sg:phone":"+41 22 700 33 10",
    "sg:postcode":"1208",
    "sg:province":"Gen\u00e8ve",
    "wof:name":"Drs P. Reust & M. Sinniger M\u00e9decins Sp\u00e9cialistes Fmh",
    "wof:placetype":"venue"
},
  "geometry": {"coordinates":[6.166998,46.197948],"type":"Point"}
}