{
  "type": "Feature",
  "properties": {
    "iso:country":"CH",
    "sg:address":"Kleinfeldstrasse 23 4565 Recherswil. Postfach",
    "sg:city":"Recherswil",
    "sg:orig_category":"Herstellung von Metallerzeugnissen ohne Maschinenbau Maschinenbau",
    "sg:phone":"+41 32 675 22 78",
    "sg:postcode":"4565",
    "sg:province":"Solothurn",
    "wof:name":"Lamec Ag",
    "wof:placetype":"venue"
},
  "geometry": {"coordinates":[7.5903692245,47.1618041992],"type":"Point"}
}