{
  "type": "Feature",
  "properties": {
    "iso:country":"CH",
    "sg:address":"Bachhalteweg 9 3900 Brig. Postfach",
    "sg:city":"Brig",
    "sg:orig_category":"Architektur U Ingenieurb\u00fcros",
    "sg:phone":"+41 91 946 19 79",
    "sg:postcode":"3900",
    "sg:province":"Valais",
    "wof:name":"Bauberatung Escher Gmbh Hochbau- U. Energieberatung, Bauleitung, Planung Usw.; Dienstleistungen",
    "wof:placetype":"venue"
},
  "geometry": {"coordinates":[7.999315,46.314224],"type":"Point"}
}