{
  "type": "Feature",
  "properties": {
    "iso:country":"CH",
    "sg:address":"Bahnhofplatz 4",
    "sg:city":"Baden",
    "sg:orig_category":"Einbau von Schreinerwaren",
    "sg:phone":"+41 56 222 73 40",
    "sg:postcode":"5400",
    "sg:province":"Aargau",
    "wof:name":"K\u00f6slich J\u00fcrgen",
    "wof:placetype":"venue"
},
  "geometry": {"coordinates":[8.3089027405,47.4766464233],"type":"Point"}
}