{
  "type": "Feature",
  "properties": {
    "iso:country":"CH",
    "sg:address":"Eigerstrasse 68 3007 Bern. Postfach",
    "sg:city":"Bern",
    "sg:orig_category":"Reinigungsgewerbe",
    "sg:postcode":"3007",
    "sg:province":"Bern",
    "wof:name":"Galaica Reinigungen Fernandez B\u00fcroreinigungen",
    "wof:placetype":"venue"
},
  "geometry": {"coordinates":[7.4383459091,46.9394760132],"type":"Point"}
}