{
  "type": "Feature",
  "properties": {
    "iso:country":"CH",
    "sg:address":"Corso San Gottardo 8",
    "sg:city":"Chiasso",
    "sg:orig_category":"Detailhandel mit Parf\u00fcmerieartikeln U K\u00f6rperpflegemitteln Parf\u00fcmerien U sonstiger Detailhandel mit k",
    "sg:phone":"+41 27 722 46 43",
    "sg:postcode":"6830",
    "sg:province":"Ticino",
    "wof:name":"Odette Abbet Parfumerie L'origan",
    "wof:placetype":"venue"
},
  "geometry": {"coordinates":[7.0727219582,46.1014289856],"type":"Point"}
}