{
  "type": "Feature",
  "properties": {
    "iso:country":"CH",
    "sg:address":"6685",
    "sg:city":"Bosco/gurin",
    "sg:classifiers":[
        {
            "category":"Restaurant",
            "type":"Food & Drink"
        }
    ],
    "sg:phone":"+41 91 754 17 40",
    "sg:postcode":"6685",
    "sg:province":"Ticino",
    "wof:name":"Ristorante Sciovia Grossalp",
    "wof:placetype":"venue"
},
  "geometry": {"coordinates":[8.4937200546,46.3160095215],"type":"Point"}
}