{
  "type": "Feature",
  "properties": {
    "addr:full":"Chemin Charri\u00e8re-verte 7 1860 Aigle. Postfach Aigle Vaud 1860",
    "addr:housenumber":"7",
    "addr:postcode":"1860 aigle. postfach aigle;1860",
    "addr:street":"Chemin Charrie\u0300Re-Verte",
    "iso:country":"CH",
    "sg:address":"Chemin Charri\u00e8re-verte 7 1860 Aigle. Postfach",
    "sg:city":"Aigle",
    "sg:orig_category":"Betrieb von Sportanlagen",
    "sg:phone":"+41 24661615",
    "sg:postcode":"1860",
    "sg:province":"Vaud",
    "wof:name":"Soci\u00e9t\u00e9 Coop\u00e9rative Piscine Et Minigolf D'aigle",
    "wof:placetype":"venue"
},
  "geometry": {"coordinates":[6.969453,46.31522],"type":"Point"}
}