{
  "type": "Feature",
  "properties": {
    "iso:country":"CH",
    "sg:address":"Via Industria 1",
    "sg:city":"Caslano",
    "sg:orig_category":"Unternehmensberatung",
    "sg:phone":"+41 62 858 11 22",
    "sg:postcode":"6987",
    "sg:province":"Ticino",
    "wof:name":"Bally Services Sa",
    "wof:placetype":"venue"
},
  "geometry": {"coordinates":[8.8767995834,45.9703636169],"type":"Point"}
}