{
  "type": "Feature",
  "properties": {
    "iso:country":"CH",
    "sg:address":"Industrie Lenzb\u00fchl",
    "sg:city":"Sirnach",
    "sg:orig_category":"Instandhaltung U Reparatur von Automobilen",
    "sg:phone":"+41 79 611 04 42",
    "sg:postcode":"8370",
    "sg:province":"Thurgau",
    "wof:name":"Kaiser Autoelektrik Gmbh",
    "wof:placetype":"venue"
},
  "geometry": {"coordinates":[9.4800386429,47.1568565369],"type":"Point"}
}