{
  "type": "Feature",
  "properties": {
    "iso:country":"CH",
    "sg:address":"Sensenau 624",
    "sg:city":"Ueberstorf",
    "sg:orig_category":"Herstellung von Mess U Kontrollinstrumenten U vorrichtungen",
    "sg:phone":"+41 31 889 18 89",
    "sg:postcode":"3182",
    "sg:province":"Fribourg",
    "wof:name":"Willi Schmutz Ag",
    "wof:placetype":"venue"
},
  "geometry": {"coordinates":[7.3517827988,46.8816452026],"type":"Point"}
}