{
  "type": "Feature",
  "properties": {
    "iso:country":"CH",
    "sg:address":"Strit",
    "sg:city":"Pfaffnau",
    "sg:orig_category":"Grosshandel mit lebenden Tieren",
    "sg:phone":"+41 62 754 11 55",
    "sg:postcode":"6264",
    "sg:province":"Luzern",
    "wof:name":"Josef Studer Viehhandel",
    "wof:placetype":"venue"
},
  "geometry": {"coordinates":[7.9124159813,47.2261924744],"type":"Point"}
}