{
  "type": "Feature",
  "properties": {
    "iso:country":"CH",
    "sg:address":"Foribachstrasse",
    "sg:city":"Sarnen",
    "sg:orig_category":"Fischerei- and Jagdverwaltung",
    "sg:phone":"+41 41 660 76 76",
    "sg:postcode":"6060",
    "sg:province":"Obwalden",
    "wof:name":"Kant. Fischerei-& Jagdverwaltung",
    "wof:placetype":"venue"
},
  "geometry": {"coordinates":[8.2540712357,46.8973960876],"type":"Point"}
}