{
  "type": "Feature",
  "properties": {
    "addr:full":"Landstr. 81 Wettingen Aargau 5430",
    "addr:housenumber":"81",
    "addr:postcode":"5430",
    "addr:street":"Landstr.",
    "iso:country":"CH",
    "sg:address":"Landstr. 81",
    "sg:city":"Wettingen",
    "sg:classifiers":[
        {
            "category":"Banks & Credit Unions",
            "subcategory":"Bank",
            "type":"Services"
        }
    ],
    "sg:phone":"+41 4156265312",
    "sg:postcode":"5430",
    "sg:province":"Aargau",
    "wof:name":"Credit Suisse",
    "wof:placetype":"venue"
},
  "geometry": {"coordinates":[8.325459,47.466522],"type":"Point"}
}