{
  "type": "Feature",
  "properties": {
    "iso:country":"CH",
    "sg:address":"Via Nova 87",
    "sg:city":"Domat/ems",
    "sg:orig_category":"Detailhandel mit Gebrauchtwaren in Verkaufsr\u00e4umen",
    "sg:phone":"+41 81 633 39 38",
    "sg:postcode":"7013",
    "sg:province":"Graubunden",
    "wof:name":"Vreni Castelberg Brocki-egga",
    "wof:placetype":"venue"
},
  "geometry": {"coordinates":[9.4517440796,46.8370246887],"type":"Point"}
}