{
  "type": "Feature",
  "properties": {
    "iso:country":"CH",
    "sg:address":"Ernst M\u00fcller-strasse 6 8207 Schaffhausen. Postfach 1126",
    "sg:city":"Schaffhausen",
    "sg:orig_category":"Bau von Strassen, Sportanlagen U Bahnverkehrsstrecken Strassenbau",
    "sg:phone":"+41 52 643 24 21",
    "sg:postcode":"8207",
    "sg:province":"Schaffhausen",
    "wof:name":"Strabus Strassenbau-unternehmung Schaffhausen Ag",
    "wof:placetype":"venue"
},
  "geometry": {"coordinates":[8.669464,47.718491],"type":"Point"}
}