{
  "type": "Feature",
  "properties": {
    "iso:country":"CH",
    "sg:address":"Poststrasse",
    "sg:city":"Vals",
    "sg:orig_category":"Verkehrs- and Tourismusb\u00fcros",
    "sg:phone":"+41 71 999 18 88",
    "sg:postcode":"7132",
    "sg:province":"Graubunden",
    "wof:name":"Kur-& Verkehrsverein Verkehrsb\u00fcro",
    "wof:placetype":"venue"
},
  "geometry": {"coordinates":[9.2867574692,47.1942024231],"type":"Point"}
}