{
  "type": "Feature",
  "properties": {
    "iso:country":"CH",
    "sg:address":"Rue De La Gare 10",
    "sg:city":"Epagnier",
    "sg:orig_category":"Unclassifiable Establishments",
    "sg:postcode":"2074",
    "sg:province":"Neuch\u00e2tel",
    "wof:name":"Imarco Bureau D'architecture",
    "wof:placetype":"venue"
},
  "geometry": {"coordinates":[7.0050392151,47.0089416504],"type":"Point"}
}