{
  "type": "Feature",
  "properties": {
    "iso:country":"CH",
    "sg:address":"Via Pocobelli 8 6900 Lugano. Postfach Caselle Postale 10",
    "sg:city":"Lugano",
    "sg:orig_category":"Herstellung von sonstigen Metallwaren Mechanische Werkst\u00e4tten",
    "sg:phone":"+41 91 647 18 94",
    "sg:postcode":"6903",
    "sg:province":"Ticino",
    "wof:name":"Urbis Sa",
    "wof:placetype":"venue"
},
  "geometry": {"coordinates":[8.9453468323,46.0033035278],"type":"Point"}
}