{
  "type": "Feature",
  "properties": {
    "iso:country":"CH",
    "sg:address":"3976",
    "sg:city":"No\u00ebs",
    "sg:orig_category":"Friedhofs- and Stadtg\u00e4rtnereien",
    "sg:phone":"+41 21 315 57 53",
    "sg:postcode":"3976",
    "sg:province":"Valais",
    "wof:name":"Administration Communale Service Des Parcs & Promenades",
    "wof:placetype":"venue"
},
  "geometry": {"coordinates":[6.6008601189,46.5234413147],"type":"Point"}
}