{
  "type": "Feature",
  "properties": {
    "iso:country":"CH",
    "sg:address":"Blumenrainweg 3",
    "sg:city":"Appenzell",
    "sg:orig_category":"Aktivit\u00e4ten der Krankenschwestern U Hebammen, Hauspflege",
    "sg:phone":"+41 71 787 31 55",
    "sg:postcode":"9050",
    "sg:province":"Appenzell Innerhoden",
    "wof:name":"Spitex-dienste",
    "wof:placetype":"venue"
},
  "geometry": {"coordinates":[9.412606,47.331402],"type":"Point"}
}