{
  "type": "Feature",
  "properties": {
    "iso:country":"CH",
    "sg:address":"Freiestrasse 58",
    "sg:city":"Bern",
    "sg:orig_category":"Sportvereine Turnen",
    "sg:phone":"+41 31 301 49 79",
    "sg:postcode":"3012",
    "sg:province":"Bern",
    "wof:name":"B\u00fcrgerturnverein Stv Bern",
    "wof:placetype":"venue"
},
  "geometry": {"coordinates":[7.4254059792,46.9544487],"type":"Point"}
}