{
  "type": "Feature",
  "properties": {
    "iso:country":"CH",
    "sg:address":"Z\u00fcrcherstrasse 138",
    "sg:city":"Frauenfeld",
    "sg:orig_category":"Warenh\u00e4user",
    "sg:phone":"+41 52 728 86 99",
    "sg:postcode":"8500",
    "sg:province":"Thurgau",
    "wof:name":"Manor",
    "wof:placetype":"venue"
},
  "geometry": {"coordinates":[8.8955030441,47.5543823242],"type":"Point"}
}