{
  "type": "Feature",
  "properties": {
    "addr:full":"Witikonerstrasse 356 Z\u00fcrich Z\u00fcrich 8053",
    "addr:housenumber":"356",
    "addr:postcode":"8053",
    "addr:street":"Witikonerstrasse",
    "iso:country":"CH",
    "sg:address":"Witikonerstrasse 356",
    "sg:city":"Z\u00fcrich",
    "sg:orig_category":"Architekturb\u00fcros Innenarchitekturb\u00fcros",
    "sg:phone":"+41 13811123",
    "sg:postcode":"8053",
    "sg:province":"Z\u00fcrich",
    "wof:name":"Atelier M\u00fcller-hiestand",
    "wof:placetype":"venue"
},
  "geometry": {"coordinates":[8.590968,47.358711],"type":"Point"}
}