{
  "type": "Feature",
  "properties": {
    "iso:country":"CH",
    "sg:address":"Au Village 1567 Delley. Postfach",
    "sg:city":"Delley",
    "sg:orig_category":"Unclassifiable Establishments",
    "sg:phone":"+41 26 677 13 03",
    "sg:postcode":"1567",
    "sg:province":"Fribourg",
    "wof:name":"Delley Transports Entreprise De Transports",
    "wof:placetype":"venue"
},
  "geometry": {"coordinates":[6.9680171013,46.9138946533],"type":"Point"}
}