{
  "type": "Feature",
  "properties": {
    "addr:full":"Schmiedgasse 6 Escholzmatt Luzern 6182",
    "addr:housenumber":"6",
    "addr:postcode":"6182",
    "addr:street":"Schmiedgasse",
    "iso:country":"CH",
    "sg:address":"Schmiedgasse 6",
    "sg:city":"Escholzmatt",
    "sg:orig_category":"Architektur U Ingenieurb\u00fcros",
    "sg:phone":"+41 41 499 90 10",
    "sg:postcode":"6182",
    "sg:province":"Luzern",
    "wof:name":"Stalder Peter Ingenieur Ag",
    "wof:placetype":"venue"
},
  "geometry": {"coordinates":[8.182725,47.036816],"type":"Point"}
}