{
  "type": "Feature",
  "properties": {
    "iso:country":"CH",
    "sg:address":"Rue Centrale 57",
    "sg:city":"Avenches",
    "sg:orig_category":"Allgemeiner Gartenbau Landschaftsplanungsb\u00fcros U Gartenarchitekturb\u00fcros",
    "sg:phone":"+41 55 410 45 50",
    "sg:postcode":"1580",
    "sg:province":"Vaud",
    "wof:name":"Beglinger S\u00f6hne Ag Garten- & Landschaftsbau",
    "wof:placetype":"venue"
},
  "geometry": {"coordinates":[8.773951,47.205479],"type":"Point"}
}