{
  "type": "Feature",
  "properties": {
    "iso:country":"CH",
    "sg:address":"Haldenstrasse 24 Br\u00fcttisellen 8602 Wangen Zh. Postfach",
    "sg:city":"Br\u00fcttisellen",
    "sg:orig_category":"Unclassifiable Establishments",
    "sg:postcode":"8306",
    "sg:province":"Z\u00fcrich",
    "wof:name":"Promar Hygiene Gmbh",
    "wof:placetype":"venue"
},
  "geometry": {"coordinates":[8.6456451416,47.4106559753],"type":"Point"}
}