{
  "type": "Feature",
  "properties": {
    "iso:country":"CH",
    "sg:address":"Stadacherstrasse 35 8320 Fehraltorf. Postfach",
    "sg:city":"Fehraltorf",
    "sg:classifiers":[
        {
            "category":"Professional",
            "subcategory":"Employment Agencies",
            "type":"Services"
        }
    ],
    "sg:phone":"+41 19541983",
    "sg:postcode":"8320",
    "sg:province":"Z\u00fcrich",
    "sg:tags":[
        "personal",
        "u",
        "stellenvermittlung"
    ],
    "wof:name":"Spiegelberg Thomas Executive Search & Consulting Personalvermittlung, Beratungen",
    "wof:placetype":"venue"
},
  "geometry": {"coordinates":[8.7562198639,47.3842887878],"type":"Point"}
}