{
  "type": "Feature",
  "properties": {
    "iso:country":"CH",
    "sg:address":"Le C\u00f4tel 19",
    "sg:city":"Corg\u00e9mont",
    "sg:orig_category":"Zimmerei, Dachdeckerei, Bauspenglerei U Abdichtung",
    "sg:postcode":"2606",
    "sg:province":"Bern",
    "wof:name":"Gr\u00fcnenwald, Jo\u00ebl",
    "wof:placetype":"venue"
},
  "geometry": {"coordinates":[7.133149147,47.1952209473],"type":"Point"}
}