{
  "type": "Feature",
  "properties": {
    "iso:country":"CH",
    "sg:address":"Landstrasse 99",
    "sg:city":"Schaan",
    "sg:orig_category":"Non-Classified Establishments",
    "sg:postcode":"9494",
    "wof:name":"Dr.med. Hermann Ecki Arzt F. Allgemeine Medizin Fmh",
    "wof:placetype":"venue"
},
  "geometry": {"coordinates":[9.5090332031,47.1607818604],"type":"Point"}
}