{
  "type": "Feature",
  "properties": {
    "iso:country":"CH",
    "sg:address":"Olivier Avenue Juste- 6 1006 Lausanne. Postfach",
    "sg:city":"Lausanne",
    "sg:orig_category":"Reiseb\u00fcros U Reiseveranstalter",
    "sg:phone":"+41 17373212",
    "sg:postcode":"1006",
    "sg:province":"Vaud",
    "wof:name":"Ralex Sa",
    "wof:placetype":"venue"
},
  "geometry": {"coordinates":[8.4436788559,47.3558387756],"type":"Point"}
}