{
  "type": "Feature",
  "properties": {
    "iso:country":"CH",
    "sg:address":"6563",
    "sg:city":"Mesocco",
    "sg:orig_category":"Primarschulen",
    "sg:phone":"+41 91 944 15 23",
    "sg:postcode":"6563",
    "sg:province":"Graubunden",
    "wof:name":"Scuola Elementare Centro Scolastico",
    "wof:placetype":"venue"
},
  "geometry": {"coordinates":[9.0501403809,46.087638855],"type":"Point"}
}