{
  "type": "Feature",
  "properties": {
    "iso:country":"CH",
    "sg:address":"Comercialstrasse 24",
    "sg:city":"Chur",
    "sg:orig_category":"Allgemeinbildende weiterf\u00fchrende Schulen",
    "sg:phone":"+41 81 353 57 41",
    "sg:postcode":"7000",
    "sg:province":"Graubunden",
    "wof:name":"Interkonfessionelle B\u00fcndnerische Schule F\u00fcr Gesundheits Und Krankenpflege",
    "wof:placetype":"venue"
},
  "geometry": {"coordinates":[9.508854,46.846725],"type":"Point"}
}