{
  "type": "Feature",
  "properties": {
    "iso:country":"CH",
    "sg:address":"Z\u00fcrcherstrasse 155 8500 Frauenfeld. Postfach 672",
    "sg:city":"Frauenfeld",
    "sg:orig_category":"Non-Classified Establishments",
    "sg:postcode":"8500",
    "sg:province":"Thurgau",
    "wof:name":"N\u00fcssli Special Events St. Gallen Ag",
    "wof:placetype":"venue"
},
  "geometry": {"coordinates":[9.3966960907,47.44008255],"type":"Point"}
}