{
  "type": "Feature",
  "properties": {
    "iso:country":"CH",
    "sg:address":"Dammstrasse 13",
    "sg:city":"Zuchwil",
    "sg:orig_category":"Arbeitnehmerverb\u00e4nde",
    "sg:phone":"+41 32 685 52 39",
    "sg:postcode":"4528",
    "sg:province":"Solothurn",
    "wof:name":"Schweiz.fachverband Der Schul- & Hauswarte,hrn Hugo Schneider",
    "wof:placetype":"venue"
},
  "geometry": {"coordinates":[7.552787,47.204067],"type":"Point"}
}