{
  "type": "Feature",
  "properties": {
    "iso:country":"CH",
    "sg:address":"G\u00fcrtelstrasse 23",
    "sg:city":"Chur",
    "sg:orig_category":"Instandhaltung U Reparatur von Automobilen",
    "sg:postcode":"7000",
    "sg:province":"Graubunden",
    "wof:name":"Hans Furrer",
    "wof:placetype":"venue"
},
  "geometry": {"coordinates":[9.5265493393,46.8533706665],"type":"Point"}
}