{
  "type": "Feature",
  "properties": {
    "addr:full":"Tannenw\u00e4g 1 Rafz Z\u00fcrich 8197",
    "addr:housenumber":"1",
    "addr:postcode":"8197",
    "addr:street":"Tannenwaeg",
    "iso:country":"CH",
    "sg:address":"Tannenw\u00e4g 1",
    "sg:city":"Rafz",
    "sg:classifiers":[
        {
            "category":"Manufacturing",
            "subcategory":"Textiles",
            "type":"Manufacturing & Wholesale Goods"
        }
    ],
    "sg:phone":"+41 4118792121",
    "sg:postcode":"8197",
    "sg:province":"Z\u00fcrich",
    "sg:tags":[
        "clothing",
        "accessory"
    ],
    "wof:name":"Schaad Mode Ag",
    "wof:placetype":"venue"
},
  "geometry": {"coordinates":[8.53862,47.60965],"type":"Point"}
}