{
  "type": "Feature",
  "properties": {
    "iso:country":"CH",
    "sg:address":"8704",
    "sg:city":"Herrliberg",
    "sg:classifiers":[
        {
            "category":"Education",
            "subcategory":"Vocational School",
            "type":"Public Place"
        }
    ],
    "sg:phone":"+41 81 384 21 07",
    "sg:postcode":"8704",
    "sg:province":"Z\u00fcrich",
    "sg:tags":[
        "koch-",
        "haushaltschulen"
    ],
    "wof:name":"Haushaltungsschule",
    "wof:placetype":"venue"
},
  "geometry": {"coordinates":[8.6762781143,47.2663574219],"type":"Point"}
}