{
  "type": "Feature",
  "properties": {
    "iso:country":"CH",
    "sg:address":"Moserstrasse 14b",
    "sg:city":"Bern",
    "sg:orig_category":"Bookbinding, Traditional",
    "sg:phone":"+41 31 333 83 83",
    "sg:postcode":"3014",
    "sg:province":"Bern",
    "wof:name":"Atelier 82",
    "wof:placetype":"venue"
},
  "geometry": {"coordinates":[7.452234,46.956459],"type":"Point"}
}