{
  "type": "Feature",
  "properties": {
    "iso:country":"CH",
    "sg:address":"G\u00e4msenstrasse 2 8006 Z\u00fcrich. Postfach",
    "sg:city":"Z\u00fcrich",
    "sg:orig_category":"Markt U Meinungsforschung Unternehmensberatung",
    "sg:phone":"+41 13669911",
    "sg:postcode":"8042",
    "sg:province":"Z\u00fcrich",
    "wof:name":"Factum Ag F\u00fcr Marketing",
    "wof:placetype":"venue"
},
  "geometry": {"coordinates":[8.5402317047,47.3881340027],"type":"Point"}
}