{
  "type": "Feature",
  "properties": {
    "iso:country":"CH",
    "sg:address":"Unterdorf 17",
    "sg:city":"Mosnang",
    "sg:orig_category":"Detailhandel mit Beleuchtungs U Haushaltsgegenst\u00e4nden",
    "sg:phone":"+41 71 983 27 55",
    "sg:postcode":"9607",
    "sg:province":"St. Gallen",
    "wof:name":"Armin & Christa Meile Eisenwaren-haushalt",
    "wof:placetype":"venue"
},
  "geometry": {"coordinates":[9.04084,47.36351],"type":"Point"}
}