{
  "type": "Feature",
  "properties": {
    "iso:country":"CH",
    "sg:address":"Gummertliweg 7 4702 Oensingen. Postfach 82",
    "sg:city":"Oensingen",
    "sg:orig_category":"Herstellung von Metallkonstruktionen",
    "sg:phone":"+41 71 244 10 19",
    "sg:postcode":"4702",
    "sg:province":"Solothurn",
    "wof:name":"Pacta Montagen Gmbh",
    "wof:placetype":"venue"
},
  "geometry": {"coordinates":[9.3957004547,47.4367752075],"type":"Point"}
}