{
  "type": "Feature",
  "properties": {
    "iso:country":"CH",
    "sg:address":"Neustadt 68 8200 Schaffhausen. Postfach",
    "sg:city":"Schaffhausen",
    "sg:orig_category":"Verwaltung von Immobilien Wirtschaftspr\u00fcfung, Steuerberatung U Treuhand",
    "sg:phone":"+41 79 355 94 62",
    "sg:postcode":"8201",
    "sg:province":"Schaffhausen",
    "wof:name":"Segreda Verwaltungs Und Treuhand-gmbh",
    "wof:placetype":"venue"
},
  "geometry": {"coordinates":[8.6324253082,47.6960945129],"type":"Point"}
}