{
  "type": "Feature",
  "properties": {
    "iso:country":"CH",
    "sg:address":"Birmensdorferstrasse 200",
    "sg:city":"Z\u00fcrich",
    "sg:orig_category":"Parf\u00fcmerien U sonstiger Detailhandel mit kosmetischen Artikeln U K\u00f6rperpflegemitteln",
    "sg:phone":"+41 14516041",
    "sg:postcode":"8003",
    "sg:province":"Z\u00fcrich",
    "wof:name":"Impo Import Parf\u00fcmerien Ag",
    "wof:placetype":"venue"
},
  "geometry": {"coordinates":[8.5163021088,47.3707580566],"type":"Point"}
}