{
  "type": "Feature",
  "properties": {
    "iso:country":"CH",
    "sg:address":"Bielmatten 12",
    "sg:city":"Bellmund",
    "sg:orig_category":"Vermietung U Verpachtung von eigenen Immobilien Verwaltung von Immobilien",
    "sg:phone":"+41 32 331 23 80",
    "sg:postcode":"2564",
    "sg:province":"Bern",
    "wof:name":"Paoluzzo Beatrice",
    "wof:placetype":"venue"
},
  "geometry": {"coordinates":[7.2446899414,47.1094093323],"type":"Point"}
}