{
  "type": "Feature",
  "properties": {
    "iso:country":"CH",
    "sg:address":"Hauensteinstrasse 28",
    "sg:city":"Trimbach",
    "sg:orig_category":"Maurerarbeiten Sonstiger spezialisierter Hoch U Tiefbau",
    "sg:phone":"+41 62 293 28 42",
    "sg:postcode":"4632",
    "sg:province":"Solothurn",
    "wof:name":"K\u00e4gi Ueli Betonbohrungen",
    "wof:placetype":"venue"
},
  "geometry": {"coordinates":[7.881401062,47.3695144653],"type":"Point"}
}