{
  "type": "Feature",
  "properties": {
    "iso:country":"CH",
    "sg:address":"Lutherstrasse 4",
    "sg:city":"Z\u00fcrich",
    "sg:orig_category":"RESTAURANTS: TEA-ROOMS",
    "sg:phone":"+41 12426061",
    "sg:postcode":"8004",
    "sg:province":"Z\u00fcrich",
    "wof:name":"Caf\u00e9 Zino, Heinz & Conchita Von Wartburg",
    "wof:placetype":"venue"
},
  "geometry": {"coordinates":[8.5297002792,47.373840332],"type":"Point"}
}