{
  "type": "Feature",
  "properties": {
    "iso:country":"CH",
    "sg:address":"World Trade Center",
    "sg:city":"Agno",
    "sg:orig_category":"Mit dem Versicherungsgewerbe verbundene T\u00e4tigkeiten Vermittlung von Immobilien",
    "sg:phone":"+41 91 610 29 46",
    "sg:postcode":"6982",
    "sg:province":"Ticino",
    "wof:name":"Indiconsult Di Zahm & Co Ufficio Fiduciario",
    "wof:placetype":"venue"
},
  "geometry": {"coordinates":[8.8993301392,45.9967536926],"type":"Point"}
}