{
  "type": "Feature",
  "properties": {
    "iso:country":"CH",
    "sg:address":"Dorfstr. 124",
    "sg:city":"Oberbuchsiten",
    "sg:orig_category":"Bau von Strassen, Sportanlagen U Bahnverkehrsstrecken",
    "sg:phone":"+41 62 393 27 41",
    "sg:postcode":"4625",
    "sg:province":"Solothurn",
    "wof:name":"Aquafan Wicki F.",
    "wof:placetype":"venue"
},
  "geometry": {"coordinates":[7.765338,47.311836],"type":"Point"}
}