{
  "type": "Feature",
  "properties": {
    "iso:country":"CH",
    "sg:address":"Bahnhofstr. 8",
    "sg:city":"Luzern",
    "sg:classifiers":[
        {
            "category":"Shopping",
            "subcategory":"Clothing, Apparel, & Fashions",
            "type":"Retail Goods"
        }
    ],
    "sg:phone":"+41 41 210 06 50",
    "sg:postcode":"6003",
    "sg:province":"Luzern",
    "sg:tags":[
        "textile",
        "clothing",
        "clothes"
    ],
    "wof:name":"Schild Ag",
    "wof:placetype":"venue"
},
  "geometry": {"coordinates":[8.3048,47.050659],"type":"Point"}
}