{
  "type": "Feature",
  "properties": {
    "iso:country":"CH",
    "sg:address":"Gotthardstrasse 165",
    "sg:city":"Silenen",
    "sg:classifiers":[
        {
            "category":"Restaurant",
            "type":"Food & Drink"
        }
    ],
    "sg:phone":"+41 41 917 07 47",
    "sg:postcode":"6473",
    "sg:province":"Uri",
    "wof:name":"Restaurant Tellimatt",
    "wof:placetype":"venue"
},
  "geometry": {"coordinates":[8.2423648834,47.2556610107],"type":"Point"}
}