{
  "type": "Feature",
  "properties": {
    "iso:country":"CH",
    "sg:address":"Sonnenbergstrasse 7 Tann 8635 D\u00fcrnten. Postfach",
    "sg:city":"F\u00e4gswil",
    "sg:orig_category":"Sonstiger Grosshandel",
    "sg:postcode":"8630",
    "sg:province":"Z\u00fcrich",
    "wof:name":"Hodza Kazim Import-export",
    "wof:placetype":"venue"
},
  "geometry": {"coordinates":[8.8424081802,47.2776527405],"type":"Point"}
}