{
  "type": "Feature",
  "properties": {
    "iso:country":"CH",
    "sg:address":"8646 Wagen. Postfach 258",
    "sg:city":"Wagen",
    "sg:orig_category":"Sportvereine Ballsport Fussball",
    "sg:phone":"+41 55 212 63 21",
    "sg:postcode":"8646",
    "sg:province":"St. Gallen",
    "wof:name":"Fc Wagen",
    "wof:placetype":"venue"
},
  "geometry": {"coordinates":[8.8858652115,47.2311401367],"type":"Point"}
}