{
  "type": "Feature",
  "properties": {
    "iso:country":"CH",
    "sg:address":"1963 V\u00e9troz Case Postale 126",
    "sg:city":"V\u00e9troz",
    "sg:orig_category":"Sportvereine Sch\u00fctzen",
    "sg:postcode":"1963",
    "sg:province":"Valais",
    "wof:name":"St\u00e9 De Tir Armes R\u00e9unies",
    "wof:placetype":"venue"
},
  "geometry": {"coordinates":[6.8579797745,46.9656105042],"type":"Point"}
}