{
  "type": "Feature",
  "properties": {
    "iso:country":"CH",
    "sg:address":"Stollenrain 4 4144 Arlesheim. Postfach 120",
    "sg:city":"Arlesheim",
    "sg:classifiers":[
        {
            "category":"Communications",
            "subcategory":"Film & Video Production",
            "type":"Services"
        }
    ],
    "sg:phone":"+41 61 993 10 20",
    "sg:postcode":"4144",
    "sg:province":"Basel-Landschaft",
    "sg:tags":[
        "videofilmherstellung",
        "u"
    ],
    "wof:name":"Ado-film Gmbh",
    "wof:placetype":"venue"
},
  "geometry": {"coordinates":[7.6121368408,47.4928703308],"type":"Point"}
}