{
  "type": "Feature",
  "properties": {
    "iso:country":"CH",
    "sg:address":"Im Morgen 1",
    "sg:city":"Humlikon",
    "sg:orig_category":"Institutionen f\u00fcr Behinderte Sonderschulen",
    "sg:phone":"+41 52 317 20 81",
    "sg:postcode":"8457",
    "sg:province":"Z\u00fcrich",
    "wof:name":"Heilp\u00e4dagogische Schule",
    "wof:placetype":"venue"
},
  "geometry": {"coordinates":[8.6697616577,47.5745429993],"type":"Point"}
}