{
  "type": "Feature",
  "properties": {
    "iso:country":"CH",
    "sg:address":"G.-f.-heilmann-strasse 49",
    "sg:city":"Biel/bienne",
    "sg:orig_category":"Architekturb\u00fcros",
    "sg:phone":"+41 32 331 64 20",
    "sg:postcode":"2502",
    "sg:province":"Bern",
    "wof:name":"Fred Burkhalter Architekturb\u00fcro",
    "wof:placetype":"venue"
},
  "geometry": {"coordinates":[7.25315,47.14558],"type":"Point"}
}