{
  "type": "Feature",
  "properties": {
    "iso:country":"CH",
    "sg:address":"\u00e0 Tatroz",
    "sg:city":"Remaufens",
    "sg:classifiers":[
        {
            "category":"Communications",
            "subcategory":"Film & Video Production",
            "type":"Services"
        }
    ],
    "sg:postcode":"1617",
    "sg:province":"Fribourg",
    "sg:tags":[
        "videofilmherstellung",
        "u"
    ],
    "wof:name":"Mohler Rainer Films Productions",
    "wof:placetype":"venue"
},
  "geometry": {"coordinates":[6.8788499832,46.5283584595],"type":"Point"}
}