{
  "type": "Feature",
  "properties": {
    "iso:country":"CH",
    "sg:address":"Gespermoosstrasse 5",
    "sg:city":"Grenchen",
    "sg:orig_category":"Unternehmensberatung",
    "sg:phone":"+41 19381213",
    "sg:postcode":"2540",
    "sg:province":"Solothurn",
    "wof:name":"Erwe-consulting Gmbh",
    "wof:placetype":"venue"
},
  "geometry": {"coordinates":[8.8587112427,47.2885780334],"type":"Point"}
}