{
  "type": "Feature",
  "properties": {
    "iso:country":"CH",
    "sg:address":"Mettlenstrasse 12",
    "sg:city":"Eglisau",
    "sg:orig_category":"Sonstige Aktivit\u00e4ten der nicht-\u00e4rztlichen Medizinalberufe",
    "sg:phone":"+41 18670745",
    "sg:postcode":"8193",
    "sg:province":"Z\u00fcrich",
    "wof:name":"Emma Schmid Atemtherapie",
    "wof:placetype":"venue"
},
  "geometry": {"coordinates":[8.5180568695,47.5738143921],"type":"Point"}
}