{
  "type": "Feature",
  "properties": {
    "iso:country":"CH",
    "sg:address":"St. Alban-tal 39 4052 Basel. Postfach",
    "sg:city":"Basel",
    "sg:orig_category":"Handelsvermittlung U Grosshandel Herstellung von Verpackungsmitteln aus Holz",
    "sg:phone":"+41 61 272 14 70",
    "sg:postcode":"4006",
    "wof:name":"Isal Ag Fabrikation V. U. Handel M. Maschinen, Apparaten, Beh\u00e4ltern U. Verpackungsmaterial",
    "wof:placetype":"venue"
},
  "geometry": {"coordinates":[7.6033082008,47.5544891357],"type":"Point"}
}