{
  "type": "Feature",
  "properties": {
    "iso:country":"CH",
    "sg:address":"Hardturmstrasse 82/90 8005 Z\u00fcrich. Postfach",
    "sg:city":"Z\u00fcrich",
    "sg:orig_category":"Verwaltung von Immobilien",
    "sg:phone":"+41 19374271",
    "sg:postcode":"8005",
    "sg:province":"Z\u00fcrich",
    "wof:name":"Felsenhof Hinwil Gmbh",
    "wof:placetype":"venue"
},
  "geometry": {"coordinates":[8.8483171463,47.3010826111],"type":"Point"}
}