{
  "type": "Feature",
  "properties": {
    "iso:country":"CH",
    "sg:address":"Im Wannenboden 2",
    "sg:city":"Pratteln",
    "sg:orig_category":"Maler U Glasergewerbe Malerei",
    "sg:phone":"+41 61 826 21 21",
    "sg:postcode":"4133",
    "sg:province":"Basel-Landschaft",
    "wof:name":"Paul Pfirter & Co. Ag",
    "wof:placetype":"venue"
},
  "geometry": {"coordinates":[7.7132248878,47.5236587524],"type":"Point"}
}