{
  "type": "Feature",
  "properties": {
    "addr:full":"Greter Rohrbachgraben Bern 4938",
    "addr:postcode":"4938",
    "iso:country":"CH",
    "sg:address":"Greter",
    "sg:city":"Rohrbachgraben",
    "sg:orig_category":"Bauschreinerei Herstellung von Konstruktionsteilen, Fertigbauteilen U Ausbauelementen aus Holz",
    "sg:phone":"+41 62 965 24 14",
    "sg:postcode":"4938",
    "sg:province":"Bern",
    "wof:name":"Leuenberger Peter.",
    "wof:placetype":"venue"
},
  "geometry": {"coordinates":[7.794197,47.113712],"type":"Point"}
}