{
  "type": "Feature",
  "properties": {
    "iso:country":"CH",
    "sg:address":"Langstrasse 94",
    "sg:city":"Z\u00fcrich",
    "sg:orig_category":"Reiseb\u00fcros",
    "sg:phone":"+41 12424240",
    "sg:postcode":"8004",
    "sg:province":"Z\u00fcrich",
    "wof:name":"Johnny Olivo Rivas Reiseb\u00fcro Amerika & Karibik",
    "wof:placetype":"venue"
},
  "geometry": {"coordinates":[8.527100563,47.3782730103],"type":"Point"}
}