{
  "type": "Feature",
  "properties": {
    "iso:country":"CH",
    "sg:address":"Untere Hohlgasse 10",
    "sg:city":"Winterthur",
    "sg:orig_category":"Detailhandel mit Geschenkartikeln U Souvenirs",
    "sg:phone":"+41 52 242 74 49",
    "sg:postcode":"8404",
    "sg:province":"Z\u00fcrich",
    "wof:name":"Atelier-l\u00e4deli Bea Weiss Kunsthandwerk",
    "wof:placetype":"venue"
},
  "geometry": {"coordinates":[8.7572135925,47.5064125061],"type":"Point"}
}