{
  "type": "Feature",
  "properties": {
    "iso:country":"CH",
    "sg:address":"Kirchgasse 3780 Gruben B. Gstaad. Postfach 425",
    "sg:city":"Gstaad",
    "sg:orig_category":"Markt U Meinungsforschung",
    "sg:phone":"+41 33 744 07 44",
    "sg:postcode":"3780",
    "sg:province":"Bern",
    "wof:name":"Im Consulting Gstaad Gmbh",
    "wof:placetype":"venue"
},
  "geometry": {"coordinates":[7.2861051559,46.4732818604],"type":"Point"}
}