{
  "type": "Feature",
  "properties": {
    "iso:country":"CH",
    "sg:address":"Route De Chantemerle 58 1763 Granges-paccot Case Postale 100",
    "sg:city":"Granges-paccot",
    "sg:orig_category":"Markt U Meinungsforschung Public-Relations-Agenturen",
    "sg:phone":"+41 26 460 70 80",
    "sg:postcode":"1763",
    "sg:province":"Fribourg",
    "wof:name":"Crausaz & Partenaires Strat\u00e9gie Et Communication Sa Conseil En Marketing Et En Communication Etc",
    "wof:placetype":"venue"
},
  "geometry": {"coordinates":[7.140182972,46.820224762],"type":"Point"}
}