{
  "type": "Feature",
  "properties": {
    "iso:country":"CH",
    "sg:address":"Piazza Stazione 2 6600 Muralto. Postfach",
    "sg:city":"Muralto",
    "sg:orig_category":"Detailhandel mit Bekleidung Detailhandel mit S\u00e4uglings U Kinderbekleidung",
    "sg:phone":"+41 61 641 68 30",
    "sg:postcode":"6600",
    "sg:province":"Ticino",
    "wof:name":"Wundert\u00fcte Schwob & Heim Gmbh",
    "wof:placetype":"venue"
},
  "geometry": {"coordinates":[7.65202,47.58482],"type":"Point"}
}