{
  "type": "Feature",
  "properties": {
    "iso:country":"CH",
    "sg:address":"Lauferbergstrasse 6",
    "sg:city":"Guntmadingen",
    "sg:orig_category":"Non-Classified Establishments",
    "sg:postcode":"8223",
    "sg:province":"Schaffhausen",
    "wof:name":"At It-services Gmbh",
    "wof:placetype":"venue"
},
  "geometry": {"coordinates":[8.5592489243,47.6833267212],"type":"Point"}
}