{
  "type": "Feature",
  "properties": {
    "iso:country":"CH",
    "sg:address":"3997",
    "sg:city":"Bellwald",
    "sg:orig_category":"RESTAURANTS: TEA-ROOMS",
    "sg:phone":"+41 27 971 31 25",
    "sg:postcode":"3997",
    "sg:province":"Valais",
    "wof:name":"Restaurant Fleschen Bellwald Ag",
    "wof:placetype":"venue"
},
  "geometry": {"coordinates":[8.1582765579,46.4262542725],"type":"Point"}
}