{
  "type": "Feature",
  "properties": {
    "iso:country":"CH",
    "sg:address":"Herblingestrasse 119",
    "sg:city":"Schaffhausen",
    "sg:orig_category":"Tierarztpraxis",
    "sg:phone":"+41 52 643 63 33",
    "sg:postcode":"8207",
    "sg:province":"Schaffhausen",
    "wof:name":"Dr.med.vet. Martin K\u00fcng Tierarzt",
    "wof:placetype":"venue"
},
  "geometry": {"coordinates":[8.6618728638,47.7220115662],"type":"Point"}
}