{
  "type": "Feature",
  "properties": {
    "iso:country":"CH",
    "sg:address":"Seestrasse 65",
    "sg:city":"Hergiswil",
    "sg:classifiers":[
        {
            "category":"Military Area",
            "subcategory":"Army Base",
            "type":"Public Place"
        }
    ],
    "sg:phone":"+41 41 630 39 54",
    "sg:postcode":"6052",
    "sg:province":"Nidwalden",
    "sg:tags":[
        "clock",
        "digital"
    ],
    "wof:name":"Cg Collectors Gallery Ag",
    "wof:placetype":"venue"
},
  "geometry": {"coordinates":[8.3145446777,46.9892692566],"type":"Point"}
}