{
  "type": "Feature",
  "properties": {
    "iso:country":"CH",
    "sg:address":"Sur Menu\u00e9 17",
    "sg:city":"Montagne-moutier",
    "sg:orig_category":"Sonstiger spezialisierter Hoch U Tiefbau",
    "sg:phone":"+41 32 493 65 42",
    "sg:postcode":"2740",
    "sg:province":"Bern",
    "wof:name":"Monney Jean-michel",
    "wof:placetype":"venue"
},
  "geometry": {"coordinates":[7.3604550362,47.2700119019],"type":"Point"}
}