{
  "type": "Feature",
  "properties": {
    "iso:country":"CH",
    "sg:address":"Zorzi Largo Franco 12",
    "sg:city":"Locarno",
    "sg:orig_category":"Non-Classified Establishments",
    "sg:postcode":"6600",
    "sg:province":"Ticino",
    "wof:name":"Agenzia Astra Mediazioni Immobiliari Sa",
    "wof:placetype":"venue"
},
  "geometry": {"coordinates":[8.7973003387,46.1697654724],"type":"Point"}
}