{
  "type": "Feature",
  "properties": {
    "iso:country":"CH",
    "sg:address":"Au Melley",
    "sg:city":"Pampigny",
    "sg:orig_category":"Fahrschulen, Flugschulen",
    "sg:phone":"+41 21 800 47 47",
    "sg:postcode":"1142",
    "sg:province":"Vaud",
    "wof:name":"Yann Monayron Auto-\u00e9cole",
    "wof:placetype":"venue"
},
  "geometry": {"coordinates":[6.4247879982,46.5789146423],"type":"Point"}
}