{
  "type": "Feature",
  "properties": {
    "iso:country":"CH",
    "sg:address":"H\u00f6henweg 37",
    "sg:city":"Lupsingen",
    "sg:orig_category":"Sportvereine Velo Rad-& Motorfahrer-Bund SRB",
    "sg:phone":"+41 62 212 48 14",
    "sg:postcode":"4419",
    "sg:province":"Basel-Landschaft",
    "wof:name":"Veloclub Aarburg",
    "wof:placetype":"venue"
},
  "geometry": {"coordinates":[7.874516964,47.3489265442],"type":"Point"}
}