{
  "type": "Feature",
  "properties": {
    "iso:country":"CH",
    "sg:address":"Warpelstrasse 10",
    "sg:city":"D\u00fcdingen",
    "sg:orig_category":"Erschliessung von Grundst\u00fccken",
    "sg:postcode":"3186",
    "sg:province":"Fribourg",
    "wof:name":"Baugenossenschaft Baukonsortium R\u00f6mermatte",
    "wof:placetype":"venue"
},
  "geometry": {"coordinates":[7.2029771805,46.8610496521],"type":"Point"}
}