{
  "type": "Feature",
  "properties": {
    "iso:country":"CH",
    "sg:address":"Mythenstrasse 4 8633 Wolfhausen. Postfach",
    "sg:city":"Wolfhausen",
    "sg:orig_category":"Unternehmensberatung",
    "sg:postcode":"8633",
    "sg:province":"Z\u00fcrich",
    "wof:name":"Vogelsanger Rolf",
    "wof:placetype":"venue"
},
  "geometry": {"coordinates":[8.7938833237,47.2605476379],"type":"Point"}
}