{
  "type": "Feature",
  "properties": {
    "iso:country":"CH",
    "sg:address":"Voa Principala 32",
    "sg:city":"Lenzerheide/lai",
    "sg:orig_category":"Detailhandel mit Geschenkartikeln U Souvenirs Sonstiger Grosshandel",
    "sg:phone":"+41 81 384 67 62",
    "sg:postcode":"7078",
    "sg:province":"Graubunden",
    "wof:name":"Scandinavian Style, Schmid-skretteberg Anne C.",
    "wof:placetype":"venue"
},
  "geometry": {"coordinates":[9.5579042435,46.7251434326],"type":"Point"}
}