{
  "type": "Feature",
  "properties": {
    "iso:country":"CH",
    "sg:address":"Via Lische",
    "sg:city":"Car\u00ec",
    "sg:orig_category":"Instandhaltung U Reparatur von Automobilen Sessellifte and Skilifte",
    "sg:phone":"+41 91 647 45 63",
    "sg:postcode":"6760",
    "sg:province":"Ticino",
    "wof:name":"Carrozzeria Nova Car 2000 Sa",
    "wof:placetype":"venue"
},
  "geometry": {"coordinates":[8.7949810028,46.4794502258],"type":"Point"}
}