{
  "type": "Feature",
  "properties": {
    "iso:country":"CH",
    "sg:address":"Breitenweg 546",
    "sg:city":"Kleinl\u00fctzel",
    "sg:orig_category":"Bauspenglerei Zimmerei, Dachdeckerei, Bauspenglerei U Abdichtung",
    "sg:phone":"+41 61 771 90 00",
    "sg:postcode":"4245",
    "sg:province":"Solothurn",
    "wof:name":"Ludwig Meier + S\u00f6hne Ag",
    "wof:placetype":"venue"
},
  "geometry": {"coordinates":[7.420872,47.422771],"type":"Point"}
}