{
  "type": "Feature",
  "properties": {
    "iso:country":"CH",
    "sg:address":"Seestrasse 14",
    "sg:city":"Ober\u00e4geri",
    "sg:orig_category":"Herstellung von Mess U Kontrollinstrumenten U vorrichtungen Mechanische Werkst\u00e4tten",
    "sg:phone":"+41 22 342 84 91",
    "sg:postcode":"6315",
    "sg:province":"Zug",
    "wof:name":"Inofer, Jean Ingold Et Michel Ferrero",
    "wof:placetype":"venue"
},
  "geometry": {"coordinates":[6.1323451996,46.1880149841],"type":"Point"}
}