{
  "type": "Feature",
  "properties": {
    "iso:country":"CH",
    "sg:address":"Leimbachstrasse 1 8583 Sulgen. Postfach 62",
    "sg:city":"Sulgen",
    "sg:orig_category":"Malerei",
    "sg:phone":"+41 71 642 23 92",
    "sg:postcode":"8583",
    "sg:province":"Thurgau",
    "wof:name":"Markus & Marlis Horat Malergesch\u00e4ft",
    "wof:placetype":"venue"
},
  "geometry": {"coordinates":[9.180683136,47.5469169617],"type":"Point"}
}