{
  "type": "Feature",
  "properties": {
    "iso:country":"CH",
    "sg:address":"Seminarstrasse 98 8000 Z\u00fcrich. Postfach",
    "sg:city":"Z\u00fcrich",
    "sg:orig_category":"Interessenvertretungen",
    "sg:postcode":"8057",
    "sg:province":"Z\u00fcrich",
    "wof:name":"Afghanischer Volksverein",
    "wof:placetype":"venue"
},
  "geometry": {"coordinates":[8.5342092514,47.3952331543],"type":"Point"}
}