{
  "type": "Feature",
  "properties": {
    "iso:country":"CH",
    "sg:address":"Wiesenstrasse 10 9327 T\u00fcbach. Postfach",
    "sg:city":"T\u00fcbach",
    "sg:orig_category":"Herstellung von Wellpapier U pappe sowie von Verpackungsmitteln aus Papier, Karton U Pappe",
    "sg:phone":"+41 71 841 44 55",
    "sg:postcode":"9327",
    "sg:province":"St. Gallen",
    "wof:name":"St\u00e4rkle-moser Ag Druck Und Verpackung",
    "wof:placetype":"venue"
},
  "geometry": {"coordinates":[9.45890522,47.4863853455],"type":"Point"}
}