{
  "type": "Feature",
  "properties": {
    "iso:country":"CH",
    "sg:address":"Z\u00fcrichstrasse 43",
    "sg:city":"N\u00e4nikon",
    "sg:orig_category":"Detailhandel mit Antiquit\u00e4ten",
    "sg:phone":"+41 19416376",
    "sg:postcode":"8606",
    "sg:province":"Z\u00fcrich",
    "wof:name":"Gertrud Gruber Antiquit\u00e4ten",
    "wof:placetype":"venue"
},
  "geometry": {"coordinates":[8.694384,47.369709],"type":"Point"}
}