{
  "type": "Feature",
  "properties": {
    "iso:country":"CH",
    "sg:address":"Immeuble Cresta Anz\u00e8re 1966 Argnoud (ayent). Postfach",
    "sg:city":"Anz\u00e8re",
    "sg:orig_category":"Sonstige mit Sport verbundene T\u00e4tigkeiten",
    "sg:postcode":"1972",
    "sg:province":"Valais",
    "wof:name":"Ecole Suisse De Ski Et Snowboard",
    "wof:placetype":"venue"
},
  "geometry": {"coordinates":[7.4068250656,46.2767829895],"type":"Point"}
}