{
  "type": "Feature",
  "properties": {
    "iso:country":"CH",
    "sg:address":"Zehntenstrasse 17",
    "sg:city":"Thalwil",
    "sg:orig_category":"Grosshandel mit Textil, N\u00e4h U Strickmaschinen Herstellung von Maschinen f\u00fcr die Textil, Bekleidungsh",
    "sg:postcode":"8800",
    "sg:province":"Z\u00fcrich",
    "wof:name":"Texmag Gmbh",
    "wof:placetype":"venue"
},
  "geometry": {"coordinates":[8.5707216263,47.2891120911],"type":"Point"}
}