{
  "type": "Feature",
  "properties": {
    "addr:full":"Birseckstr. 99 Arlesheim Basel-Landschaft 4144",
    "addr:housenumber":"99",
    "addr:postcode":"4144",
    "addr:street":"Birseckstr.",
    "iso:country":"CH",
    "sg:address":"Birseckstr. 99",
    "sg:city":"Arlesheim",
    "sg:classifiers":[
        {
            "category":"Professional",
            "type":"Services"
        }
    ],
    "sg:phone":"+41 61 701 99 33",
    "sg:postcode":"4144",
    "sg:province":"Basel-Landschaft",
    "sg:tags":[
        "transport"
    ],
    "wof:name":"Dhb Distributionsund Handels Ag Basel",
    "wof:placetype":"venue"
},
  "geometry": {"coordinates":[7.608688,47.489544],"type":"Point"}
}