{
  "type": "Feature",
  "properties": {
    "iso:country":"CH",
    "sg:address":"Le Village",
    "sg:city":"Ch\u00e2teau-d'oex",
    "sg:orig_category":"Detailhandel mit Radio U Fernsehger\u00e4ten",
    "sg:phone":"+41 26 924 66 71",
    "sg:postcode":"1837",
    "wof:name":"Lachin Jo\u00ebl",
    "wof:placetype":"venue"
},
  "geometry": {"coordinates":[6.4243469238,45.7476654053],"type":"Point"}
}