{
  "type": "Feature",
  "properties": {
    "iso:country":"CH",
    "sg:address":"Rebbergstrasse 5a",
    "sg:city":"Geroldswil",
    "sg:orig_category":"Unternehmensberatung",
    "sg:phone":"+41 41 920 17 37",
    "sg:postcode":"8954",
    "sg:province":"Z\u00fcrich",
    "wof:name":"Gastro-beratung Frauchiger + Co",
    "wof:placetype":"venue"
},
  "geometry": {"coordinates":[8.1131219864,47.1622848511],"type":"Point"}
}