{
  "type": "Feature",
  "properties": {
    "iso:country":"CH",
    "sg:address":"3997",
    "sg:city":"Bellwald",
    "sg:classifiers":[
        {
            "category":"Insurance",
            "subcategory":"Insurance Agent",
            "type":"Services"
        }
    ],
    "sg:phone":"+41 27 971 16 73",
    "sg:postcode":"3997",
    "sg:province":"Valais",
    "sg:tags":[
        "versicherungsagenturen",
        "-broker"
    ],
    "wof:name":"Die Mobiliar Versicherungen & Vorsorge",
    "wof:placetype":"venue"
},
  "geometry": {"coordinates":[8.1582765579,46.4262542725],"type":"Point"}
}