{
  "type": "Feature",
  "properties": {
    "iso:country":"CH",
    "sg:address":"Bahnhofstrasse 22",
    "sg:city":"Kradolf",
    "sg:orig_category":"Kunsthandel",
    "sg:phone":"+41 71 642 49 84",
    "sg:postcode":"9214",
    "sg:province":"Thurgau",
    "wof:name":"Willi Oertig Kustmaleratelier",
    "wof:placetype":"venue"
},
  "geometry": {"coordinates":[9.2028045654,47.5254058838],"type":"Point"}
}