{
  "type": "Feature",
  "properties": {
    "iso:country":"CH",
    "sg:address":"Hauptstrasse 3472 Wynigen. Postfach 180",
    "sg:city":"Wynigen",
    "sg:orig_category":"Unclassifiable Establishments",
    "sg:postcode":"3472",
    "sg:province":"Bern",
    "wof:name":"Spar-markt Buechen Dogru",
    "wof:placetype":"venue"
},
  "geometry": {"coordinates":[9.5429334641,47.4775428772],"type":"Point"}
}