{
  "type": "Feature",
  "properties": {
    "iso:country":"CH",
    "sg:address":"Im Berg 10 Postfach 84",
    "sg:city":"Russikon",
    "sg:classifiers":[
        {
            "category":"Building & Trades",
            "subcategory":"Construction",
            "type":"Services"
        }
    ],
    "sg:phone":"+41 4119540406",
    "sg:postcode":"8332",
    "sg:province":"Z\u00fcrich",
    "sg:tags":[
        "work",
        "public"
    ],
    "wof:name":"Gartencenter H. Waffenschmidt",
    "wof:placetype":"venue"
},
  "geometry": {"coordinates":[7.2167,51.116699],"type":"Point"}
}