{
  "type": "Feature",
  "properties": {
    "iso:country":"CH",
    "sg:address":"4500 Solothurn. Postfach",
    "sg:city":"Solothurn",
    "sg:orig_category":"Notariate Verwaltung der Rechtspflege, Gerichte",
    "sg:phone":"+41 32 627 76 48",
    "sg:postcode":"4501",
    "sg:province":"Solothurn",
    "wof:name":"Kant. Verwaltung Notariat Lebern",
    "wof:placetype":"venue"
},
  "geometry": {"coordinates":[7.5182700157,47.2069892883],"type":"Point"}
}