{
  "type": "Feature",
  "properties": {
    "iso:country":"CH",
    "sg:address":"Grossteinengasse 1",
    "sg:city":"Oberkulm",
    "sg:classifiers":[
        {
            "category":"Manufacturing",
            "subcategory":"Glass & Minerals",
            "type":"Manufacturing & Wholesale Goods"
        }
    ],
    "sg:phone":"+41 62 768 80 80",
    "sg:postcode":"5727",
    "sg:province":"Aargau",
    "sg:tags":[
        "building",
        "material"
    ],
    "wof:name":"Glas Tr\u00d6sch Ag Isolierglasfabrik",
    "wof:placetype":"venue"
},
  "geometry": {"coordinates":[8.125826,47.295708],"type":"Point"}
}