{
  "type": "Feature",
  "properties": {
    "iso:country":"CH",
    "sg:address":"R\u00f6schenzstr. 12",
    "sg:city":"Laufen",
    "sg:classifiers":[
        {
            "category":"Banks & Credit Unions",
            "subcategory":"Bank",
            "type":"Services"
        }
    ],
    "sg:phone":"+41 61 765 53 33",
    "sg:postcode":"4242",
    "sg:province":"Basel-Landschaft",
    "wof:name":"Bezirkskasse Laufen Ag",
    "wof:placetype":"venue"
},
  "geometry": {"coordinates":[7.499089,47.421543],"type":"Point"}
}