{
  "type": "Feature",
  "properties": {
    "iso:country":"CH",
    "sg:address":"Lindenstrasse 30",
    "sg:city":"Allschwil",
    "sg:orig_category":"Herstellung von k\u00e4lte U lufttechnischen Erzeugnissen f\u00fcr gewerbliche Zwecke",
    "sg:phone":"+41 61 481 67 00",
    "sg:postcode":"4123",
    "sg:province":"Basel-Landschaft",
    "wof:name":"Tomasetti Elio Ag",
    "wof:placetype":"venue"
},
  "geometry": {"coordinates":[7.5609269142,47.5586471558],"type":"Point"}
}