{
  "type": "Feature",
  "properties": {
    "iso:country":"CH",
    "sg:address":"Einsiedlerstrasse 127",
    "sg:city":"Horgen",
    "sg:orig_category":"Vorschulen, Kinderg\u00e4rten",
    "sg:phone":"+41 17255122",
    "sg:postcode":"8810",
    "sg:province":"Z\u00fcrich",
    "wof:name":"Kindergarten Brunnenwiesli",
    "wof:placetype":"venue"
},
  "geometry": {"coordinates":[8.591252327,47.2598800659],"type":"Point"}
}