{
  "type": "Feature",
  "properties": {
    "addr:full":"Gemeindehausplatz 6 Schleitheim Schaffhausen 8226",
    "addr:housenumber":"6",
    "addr:postcode":"8226",
    "addr:street":"Gemeindehausplatz",
    "iso:country":"CH",
    "sg:address":"Gemeindehausplatz 6",
    "sg:city":"Schleitheim",
    "sg:orig_category":"Bauspenglerei Elektroinstallation",
    "sg:phone":"+41 19366464",
    "sg:postcode":"8226",
    "sg:province":"Schaffhausen",
    "wof:name":"Hustech Ag",
    "wof:placetype":"venue"
},
  "geometry": {"coordinates":[8.74968,47.304546],"type":"Point"}
}