{
  "type": "Feature",
  "properties": {
    "iso:country":"CH",
    "sg:address":"Avenue Adrien-lachenal 21",
    "sg:city":"Versoix",
    "sg:orig_category":"Unclassifiable Establishments",
    "sg:postcode":"1290",
    "sg:province":"Gen\u00e8ve",
    "wof:name":"Caf\u00e9 Atlantico",
    "wof:placetype":"venue"
},
  "geometry": {"coordinates":[6.1638460159,46.2818565369],"type":"Point"}
}