{
  "type": "Feature",
  "properties": {
    "iso:country":"CH",
    "sg:address":"Eichb\u00fchlstrasse 14",
    "sg:city":"W\u00e4ngi",
    "sg:orig_category":"Unternehmensberatung",
    "sg:phone":"+41 52 378 10 63",
    "sg:postcode":"9545",
    "sg:province":"Thurgau",
    "wof:name":"E. Stark Ag Unternehmensberatung",
    "wof:placetype":"venue"
},
  "geometry": {"coordinates":[8.951084137,47.5039863586],"type":"Point"}
}