{
  "type": "Feature",
  "properties": {
    "iso:country":"CH",
    "sg:address":"Dorfstrasse 34",
    "sg:city":"Seeberg",
    "sg:orig_category":"Wirtschaftspr\u00fcfung, Steuerberatung U Treuhand",
    "sg:phone":"+41 62 968 10 66",
    "sg:postcode":"3365",
    "sg:province":"Bern",
    "wof:name":"Steffen Treuhand",
    "wof:placetype":"venue"
},
  "geometry": {"coordinates":[7.6664738655,47.1544914246],"type":"Point"}
}