{
  "type": "Feature",
  "properties": {
    "iso:country":"CH",
    "sg:address":"Birmensdorferstrasse 122",
    "sg:city":"Urdorf",
    "sg:orig_category":"Zahnarztpraxen",
    "sg:phone":"+41 17340202",
    "sg:postcode":"8902",
    "sg:province":"Z\u00fcrich",
    "wof:name":"Dr. Med. Dent. Urs Soom Zahnarzt",
    "wof:placetype":"venue"
},
  "geometry": {"coordinates":[8.4226951599,47.3811454773],"type":"Point"}
}