{
  "type": "Feature",
  "properties": {
    "iso:country":"CH",
    "sg:address":"Schmittenweg 5",
    "sg:city":"Flumenthal",
    "sg:orig_category":"Grosshandel mit Fleisch U Fleischwaren Herstellung von Maschinen f\u00fcr die Nahrungsmittel, Getr\u00e4nkeher",
    "sg:phone":"+41 32 637 15 53",
    "sg:postcode":"4534",
    "sg:province":"Solothurn",
    "wof:name":"Z\u00fcrchers Fritz S\u00f6hne, Inhaber Z\u00fcrcher Urs",
    "wof:placetype":"venue"
},
  "geometry": {"coordinates":[7.5943078995,47.2383880615],"type":"Point"}
}