{
  "type": "Feature",
  "properties": {
    "iso:country":"CH",
    "sg:address":"Mittelstr. 13",
    "sg:city":"Langenthal",
    "sg:classifiers":[
        {
            "category":"Home & Garden",
            "subcategory":"Furniture",
            "type":"Retail Goods"
        }
    ],
    "sg:phone":"+41 62 922 26 22",
    "sg:postcode":"4900",
    "sg:province":"Bern",
    "sg:tags":[
        "household",
        "wood"
    ],
    "wof:name":"B\u00d6siger Langenthal",
    "wof:placetype":"venue"
},
  "geometry": {"coordinates":[7.7868819237,47.2086982727],"type":"Point"}
}