{
  "type": "Feature",
  "properties": {
    "iso:country":"CH",
    "sg:address":"Ebel\u00e4ndstrasse 513",
    "sg:city":"Wittnau",
    "sg:orig_category":"Maschinen-Fabrikation",
    "sg:phone":"+41 62 871 90 60",
    "sg:postcode":"5064",
    "sg:province":"Aargau",
    "wof:name":"Hochreuter & Partner Gmbh",
    "wof:placetype":"venue"
},
  "geometry": {"coordinates":[7.9792499542,47.4841690063],"type":"Point"}
}