{
  "type": "Feature",
  "properties": {
    "addr:full":"Schw\u00e4rzistrasse 55 6017 Ruswil. Postfach 269 Ruswil Luzern 6017",
    "addr:housenumber":"55;269",
    "addr:postcode":"6017 ruswil.;6017",
    "addr:street":"Schwaerzistrasse;Postfach",
    "iso:country":"CH",
    "sg:address":"Schw\u00e4rzistrasse 55 6017 Ruswil. Postfach 269",
    "sg:city":"Ruswil",
    "sg:orig_category":"Architektur U Ingenieurb\u00fcros Architekturb\u00fcros",
    "sg:phone":"+41 41 495 15 87",
    "sg:postcode":"6017",
    "sg:province":"Luzern",
    "wof:name":"Geiger Architekturb\u00fcro",
    "wof:placetype":"venue"
},
  "geometry": {"coordinates":[8.118695,47.086941],"type":"Point"}
}