{
  "type": "Feature",
  "properties": {
    "iso:country":"CH",
    "sg:address":"Versonnex Rue Fran\u00e7ois- 15a 1207 Gen\u00e8ve. Postfach",
    "sg:city":"Gen\u00e8ve",
    "sg:orig_category":"Erbringung von Dienstleistungen f\u00fcr Unternehmen",
    "sg:postcode":"1201",
    "sg:province":"Gen\u00e8ve",
    "wof:name":"Versonnex Editions, Christian Bardellini",
    "wof:placetype":"venue"
},
  "geometry": {"coordinates":[6.1561121941,46.202922821],"type":"Point"}
}