{
  "type": "Feature",
  "properties": {
    "iso:country":"CH",
    "sg:address":"St. Gallerstr. 54 9030 Abtwil Sg. Postfach",
    "sg:city":"Engelburg",
    "sg:classifiers":[
        {
            "category":"Travel",
            "subcategory":"Hotels & Motels",
            "type":"Entertainment"
        }
    ],
    "sg:postcode":"9032",
    "sg:province":"St. Gallen",
    "sg:tags":[
        "hotels",
        "mit",
        "restaurant"
    ],
    "wof:name":"Gasthaus R\u00f6ssli Wespe Patricia.",
    "wof:placetype":"venue"
},
  "geometry": {"coordinates":[9.0054197311,47.1976394653],"type":"Point"}
}