{
  "type": "Feature",
  "properties": {
    "iso:country":"CH",
    "sg:address":"Venedig-strasse 27",
    "sg:city":"M\u00fcnchenstein",
    "sg:orig_category":"Herstellung von k\u00e4lte U lufttechnischen Erzeugnissen f\u00fcr gewerbliche Zwecke Sanit\u00e4rinstallation",
    "sg:phone":"+41 61 331 33 00",
    "sg:postcode":"4142",
    "sg:province":"Basel-Landschaft",
    "wof:name":"Haizmann Haustechnik Gmbh",
    "wof:placetype":"venue"
},
  "geometry": {"coordinates":[7.607293129,47.5316085815],"type":"Point"}
}