{
  "type": "Feature",
  "properties": {
    "iso:country":"CH",
    "sg:address":"3961",
    "sg:city":"Grimentz",
    "sg:orig_category":"Vermittlung von Immobilien Verwaltung von Immobilien",
    "sg:phone":"+41 27 476 17 60",
    "sg:postcode":"3961",
    "sg:province":"Valais",
    "wof:name":"Nicolas & Dany Salamin Immobilia-grimentz",
    "wof:placetype":"venue"
},
  "geometry": {"coordinates":[7.5763998032,46.1804466248],"type":"Point"}
}