{
  "type": "Feature",
  "properties": {
    "iso:country":"CH",
    "sg:address":"Langnaustrasse 43",
    "sg:city":"Zollbr\u00fcck",
    "sg:orig_category":"Hoch U Tiefbau",
    "sg:phone":"+41 79 311 88 57",
    "sg:postcode":"3436",
    "sg:province":"Bern",
    "wof:name":"Hans-ulrich Schweizer Bauunternehmung",
    "wof:placetype":"venue"
},
  "geometry": {"coordinates":[7.7511558533,46.9702186584],"type":"Point"}
}