{
  "type": "Feature",
  "properties": {
    "iso:country":"CH",
    "sg:address":"Jargonnant Rue De 2 1207 Gen\u00e8ve. Postfach",
    "sg:city":"Gen\u00e8ve",
    "sg:orig_category":"Unclassifiable Establishments",
    "sg:postcode":"1207",
    "sg:province":"Gen\u00e8ve",
    "wof:name":"Apalaska Sa",
    "wof:placetype":"venue"
},
  "geometry": {"coordinates":[6.1597938538,46.2011184692],"type":"Point"}
}