{
  "type": "Feature",
  "properties": {
    "iso:country":"CH",
    "sg:address":"Rocher Rue Du 35",
    "sg:city":"Neuch\u00e2tel",
    "sg:orig_category":"Fachdetailhandel in Verkaufsr\u00e4umen",
    "sg:phone":"+41 32 725 55 81",
    "sg:postcode":"2000",
    "sg:province":"Neuch\u00e2tel",
    "wof:name":"By Go S\u00e0rl",
    "wof:placetype":"venue"
},
  "geometry": {"coordinates":[6.9305939674,46.9971923828],"type":"Point"}
}