{
  "type": "Feature",
  "properties": {
    "iso:country":"CH",
    "sg:address":"Passage De L'industrie 8",
    "sg:city":"St-imier",
    "sg:orig_category":"Herstellung von Uhren",
    "sg:phone":"+41 32 926 01 01",
    "sg:postcode":"2610",
    "sg:province":"Bern",
    "wof:name":"Miremont Sa",
    "wof:placetype":"venue"
},
  "geometry": {"coordinates":[6.8109102249,47.0915107727],"type":"Point"}
}