{
  "type": "Feature",
  "properties": {
    "iso:country":"CH",
    "sg:address":"Dorfwiesenstrasse 7",
    "sg:city":"Neerach",
    "sg:orig_category":"Non-Classified Establishments",
    "sg:postcode":"8173",
    "sg:province":"Z\u00fcrich",
    "wof:name":"Autoform Ag",
    "wof:placetype":"venue"
},
  "geometry": {"coordinates":[8.4766874313,47.5130157471],"type":"Point"}
}