{
  "type": "Feature",
  "properties": {
    "iso:country":"CH",
    "sg:address":"Hauptstrasse 32",
    "sg:city":"Frick",
    "sg:orig_category":"Unternehmensberatung",
    "sg:phone":"+41 62 871 06 00",
    "sg:postcode":"5070",
    "sg:province":"Aargau",
    "wof:name":"Imp Marketing Partners Ag",
    "wof:placetype":"venue"
},
  "geometry": {"coordinates":[8.0177259445,47.5090942383],"type":"Point"}
}