{
  "type": "Feature",
  "properties": {
    "iso:country":"CH",
    "sg:address":"Chemin Martavaux 8",
    "sg:city":"Nyon",
    "sg:orig_category":"Herstellung von Teppichen Verlegen von Fliesen U Platten",
    "sg:phone":"+41 22 362 25 75",
    "sg:postcode":"1260",
    "sg:province":"Vaud",
    "wof:name":"Perrin Et Lanoir Sa",
    "wof:placetype":"venue"
},
  "geometry": {"coordinates":[6.2286949158,46.380695343],"type":"Point"}
}