{
  "type": "Feature",
  "properties": {
    "iso:country":"CH",
    "sg:address":"Lauriedhofweg 5 6300 Zug. Postfach 2235",
    "sg:city":"Zug",
    "sg:orig_category":"Herstellung von medizinischen U chirurgischen Ger\u00e4ten sowie orthop\u00e4dischen Vorrichtungen Zahntechnis",
    "sg:phone":"+41 61 361 59 44",
    "sg:postcode":"6302",
    "sg:province":"Zug",
    "wof:name":"Zahntechnik D\u00f6beli Ag, Zug",
    "wof:placetype":"venue"
},
  "geometry": {"coordinates":[8.5224323273,47.1764945984],"type":"Point"}
}