{
  "type": "Feature",
  "properties": {
    "iso:country":"CH",
    "sg:address":"Vogesenstrasse 139",
    "sg:city":"Basel",
    "sg:orig_category":"Unclassifiable Establishments",
    "sg:postcode":"4056",
    "sg:province":"Basel-Stadt",
    "wof:name":"Robur Ger\u00fcstbau Gmbh",
    "wof:placetype":"venue"
},
  "geometry": {"coordinates":[7.5741009712,47.5694923401],"type":"Point"}
}