{
  "type": "Feature",
  "properties": {
    "iso:country":"CH",
    "sg:address":"Cours Des Bastions 6 1200 Genf. Postfach",
    "sg:city":"Gen\u00e8ve",
    "sg:orig_category":"Forschung U Entwicklung im Bereich der Naturwissenschaften",
    "sg:postcode":"1201",
    "sg:province":"Gen\u00e8ve",
    "wof:name":"Bio-bits Sa",
    "wof:placetype":"venue"
},
  "geometry": {"coordinates":[6.147646904,46.1979141235],"type":"Point"}
}