{
  "type": "Feature",
  "properties": {
    "iso:country":"CH",
    "sg:address":"Jungholzstrasse 6",
    "sg:city":"Z\u00fcrich",
    "sg:orig_category":"Grosshandel mit B\u00fcromaschinen Herstellung von Radio U Fernsehger\u00e4ten sowie phono U videotechnischen ",
    "sg:phone":"+41 13139311",
    "sg:postcode":"8050",
    "sg:province":"Z\u00fcrich",
    "wof:name":"Csi Consulting Ag",
    "wof:placetype":"venue"
},
  "geometry": {"coordinates":[8.5444135666,47.4127311707],"type":"Point"}
}