{
  "type": "Feature",
  "properties": {
    "iso:country":"CH",
    "sg:address":"Dorfstrasse 2",
    "sg:city":"Effretikon",
    "sg:orig_category":"Detailhandel mit M\u00f6beln U Haushaltsgegenst\u00e4nden Grosshandel mit M\u00f6beln, Wohnbedarf, Teppichen U Bode",
    "sg:phone":"+41 52 343 66 16",
    "sg:postcode":"8307",
    "sg:province":"Z\u00fcrich",
    "wof:name":"Gertrud Kopf Orientteppiche",
    "wof:placetype":"venue"
},
  "geometry": {"coordinates":[8.6875400543,47.4309883118],"type":"Point"}
}