{
  "type": "Feature",
  "properties": {
    "iso:country":"CH",
    "sg:address":"4952",
    "sg:city":"Eriswil",
    "sg:orig_category":"Sportvereine Sch\u00fctzen",
    "sg:phone":"+41 62 962 03 88",
    "sg:postcode":"4952",
    "sg:province":"Bern",
    "wof:name":"Feldsch\u00fctzengesellschaft",
    "wof:placetype":"venue"
},
  "geometry": {"coordinates":[7.8506450653,47.0790901184],"type":"Point"}
}