{
  "type": "Feature",
  "properties": {
    "iso:country":"CH",
    "sg:address":"G\u00e4ssli 55",
    "sg:city":"Oftringen",
    "sg:orig_category":"Sportvereine Alpinismus",
    "sg:phone":"+41 62 797 37 82",
    "sg:postcode":"4665",
    "sg:province":"Aargau",
    "wof:name":"Sac Sektion Zofingen",
    "wof:placetype":"venue"
},
  "geometry": {"coordinates":[7.9200792313,47.3202171326],"type":"Point"}
}