{
  "type": "Feature",
  "properties": {
    "iso:country":"CH",
    "sg:address":"Martinsplatz 8 7000 Chur. Postfach",
    "sg:city":"Landquart",
    "sg:orig_category":"Allgemeiner Hoch U Tiefbau",
    "sg:phone":"+41 81 322 64 84",
    "sg:postcode":"7302",
    "sg:province":"Graubunden",
    "wof:name":"Bianchi Ag",
    "wof:placetype":"venue"
},
  "geometry": {"coordinates":[9.489851,47.014557],"type":"Point"}
}