{
  "type": "Feature",
  "properties": {
    "iso:country":"CH",
    "sg:address":"Knonauerstrasse 21",
    "sg:city":"Cham",
    "sg:orig_category":"Herstellung von Metallkonstruktionen Stahl U Leichtmetallbau",
    "sg:phone":"+41 41 780 15 47",
    "sg:postcode":"6330",
    "sg:province":"Zug",
    "wof:name":"M\u00e4chler Metallbau Ag",
    "wof:placetype":"venue"
},
  "geometry": {"coordinates":[8.4607172012,47.182849884],"type":"Point"}
}