{
  "type": "Feature",
  "properties": {
    "iso:country":"CH",
    "sg:address":"Weidweg 16",
    "sg:city":"Unterentfelden",
    "sg:orig_category":"Sportvereine Orientierungslauf",
    "sg:phone":"+41 19372034",
    "sg:postcode":"5035",
    "sg:province":"Aargau",
    "wof:name":"Ol-verband Z\u00fcrich Olvz",
    "wof:placetype":"venue"
},
  "geometry": {"coordinates":[8.8586683273,47.2879638672],"type":"Point"}
}