{
  "type": "Feature",
  "properties": {
    "iso:country":"CH",
    "sg:address":"Hinterm\u00e4ttlistrasse 1",
    "sg:city":"M\u00e4genwil",
    "sg:orig_category":"Herstellung von Ger\u00e4ten der Elektrizit\u00e4tserzeugung, -verteilung u.\u00e4. -Detailhandel mit Metallwaren, ",
    "sg:phone":"+41 62 889 70 70",
    "sg:postcode":"5506",
    "sg:province":"Aargau",
    "wof:name":"Bbs-anlagenbau Ag",
    "wof:placetype":"venue"
},
  "geometry": {"coordinates":[8.223916,47.410057],"type":"Point"}
}