{
  "type": "Feature",
  "properties": {
    "iso:country":"CH",
    "sg:address":"Frohsinnstrasse 5",
    "sg:city":"Diepoldsau",
    "sg:orig_category":"G\u00fcterbef\u00f6rderung im Strassenverkehr",
    "sg:phone":"+41 71 733 23 38",
    "sg:postcode":"9444",
    "sg:province":"St. Gallen",
    "wof:name":"Kuster Roland Transporte",
    "wof:placetype":"venue"
},
  "geometry": {"coordinates":[9.6586637497,47.3820495605],"type":"Point"}
}