{
  "type": "Feature",
  "properties": {
    "iso:country":"CH",
    "sg:address":"Juraweg 14",
    "sg:city":"Hunzenschwil",
    "sg:orig_category":"Unclassifiable Establishments",
    "sg:phone":"+41 62 897 17 61",
    "sg:postcode":"5502",
    "sg:province":"Aargau",
    "wof:name":"Grill-g\u00e4gg, Grilltischbau, R. Rohr + M. Tsch\u00e4ppeler",
    "wof:placetype":"venue"
},
  "geometry": {"coordinates":[8.1276006699,47.385181427],"type":"Point"}
}