{
  "type": "Feature",
  "properties": {
    "iso:country":"CH",
    "sg:address":"Alte Bernstrasse 14 2558 Aegerten. Postfach",
    "sg:city":"Aegerten",
    "sg:orig_category":"Allgemeiner Hoch U Tiefbau",
    "sg:phone":"+41 26 495 21 11",
    "sg:postcode":"2558",
    "sg:province":"Bern",
    "wof:name":"Dorf-zentrum St. Antoni Gmbh Planung U. Ausf\u00fchrung Von Bauten Usw",
    "wof:placetype":"venue"
},
  "geometry": {"coordinates":[7.260885,46.822182],"type":"Point"}
}