{
  "type": "Feature",
  "properties": {
    "iso:country":"CH",
    "sg:address":"Rue De L'evole 15 2000 Neuenburg. Postfach",
    "sg:city":"Neuenburg",
    "sg:orig_category":"Non-Classified Establishments",
    "sg:postcode":"2000",
    "sg:province":"Neuch\u00e2tel",
    "wof:name":"Shore Islands, S.l., Bilbao, Succursale De Neuch\u00e2tel Titres, Actions, Etc.; Acquisition, D\u00e9tention, Administration Et Gestion",
    "wof:placetype":"venue"
},
  "geometry": {"coordinates":[6.8981690407,47.0409584045],"type":"Point"}
}