{
  "type": "Feature",
  "properties": {
    "iso:country":"CH",
    "sg:address":"Burgerastrasse 28",
    "sg:city":"D\u00fcdingen",
    "sg:orig_category":"Gesundheitswesen",
    "sg:phone":"+41 26 492 05 40",
    "sg:postcode":"3186",
    "sg:province":"Fribourg",
    "wof:name":"Hayoz Anita",
    "wof:placetype":"venue"
},
  "geometry": {"coordinates":[7.1974802017,46.8507041931],"type":"Point"}
}