{
  "type": "Feature",
  "properties": {
    "iso:country":"CH",
    "sg:address":"Jurastrasse 25",
    "sg:city":"Rupperswil",
    "sg:orig_category":"Unclassifiable Establishments",
    "sg:postcode":"5102",
    "sg:province":"Aargau",
    "wof:name":"Rim Rossier Immobilien Management",
    "wof:placetype":"venue"
},
  "geometry": {"coordinates":[8.5441036224,47.3314170837],"type":"Point"}
}