{
  "type": "Feature",
  "properties": {
    "iso:country":"CH",
    "sg:address":"Baumgartenrain 1",
    "sg:city":"Thun",
    "sg:orig_category":"Architektur U Ingenieurb\u00fcros",
    "sg:phone":"+41 19372895",
    "sg:postcode":"3600",
    "sg:province":"Bern",
    "wof:name":"Schwarzenbach Consulting",
    "wof:placetype":"venue"
},
  "geometry": {"coordinates":[8.835345,47.306286],"type":"Point"}
}