{
  "type": "Feature",
  "properties": {
    "iso:country":"CH",
    "sg:address":"Altweg 16",
    "sg:city":"Frauenfeld",
    "sg:orig_category":"Arztpraxen",
    "sg:phone":"+41 56 441 87 02",
    "sg:postcode":"8500",
    "sg:province":"Thurgau",
    "wof:name":"Dr.med.hans-ludwig Felber Arzt F\u00fcr Allgemeine Medizin",
    "wof:placetype":"venue"
},
  "geometry": {"coordinates":[8.207245,47.48661],"type":"Point"}
}