{
  "type": "Feature",
  "properties": {
    "iso:country":"CH",
    "sg:address":"Romont Rue De 30 1700 Fribourg Case Postale 1060",
    "sg:city":"Freiburg",
    "sg:orig_category":"Detailhandel mit Waren verschiedener Art, Hauptrichtung Nichtnahrungsmittel",
    "sg:phone":"+41 34 402 12 58",
    "sg:postcode":"1700",
    "sg:province":"Fribourg",
    "wof:name":"Nordmann & Cie S.a., Zweigniederlassung Langnau I.e.",
    "wof:placetype":"venue"
},
  "geometry": {"coordinates":[7.757589817,46.9491271973],"type":"Point"}
}