{
  "type": "Feature",
  "properties": {
    "iso:country":"CH",
    "sg:address":"Dorfstrasse 66 8126 Zumikon. Postfach 90",
    "sg:city":"Zumikon",
    "sg:orig_category":"Unternehmensberatung Weiterbildungskurse and Seminar Anbieter",
    "sg:phone":"+41 19183260",
    "sg:postcode":"8126",
    "sg:province":"Z\u00fcrich",
    "wof:name":"Walter R. Hofstetter Akm Consulting & Training",
    "wof:placetype":"venue"
},
  "geometry": {"coordinates":[8.6254453659,47.3305053711],"type":"Point"}
}