{
  "type": "Feature",
  "properties": {
    "iso:country":"CH",
    "sg:address":"Hombrechtikerstrasse 3",
    "sg:city":"Jona",
    "sg:orig_category":"Tierarztpraxis",
    "sg:phone":"+41 55 210 38 10",
    "sg:postcode":"8645",
    "sg:province":"St. Gallen",
    "wof:name":"Dr. Med. Vet. Heinz A. M\u00fcller Tierarzt",
    "wof:placetype":"venue"
},
  "geometry": {"coordinates":[8.8194961548,47.2406845093],"type":"Point"}
}