{
  "type": "Feature",
  "properties": {
    "iso:country":"CH",
    "sg:address":"1983",
    "sg:city":"Evol\u00e8ne",
    "sg:orig_category":"Sessellifte and Skilifte",
    "sg:phone":"+41 21 845 52 55",
    "sg:postcode":"1983",
    "sg:province":"Valais",
    "wof:name":"T\u00e9l\u00e9-ski Des Molards Sa",
    "wof:placetype":"venue"
},
  "geometry": {"coordinates":[6.2120499611,46.582359314],"type":"Point"}
}