{
  "type": "Feature",
  "properties": {
    "iso:country":"CH",
    "sg:address":"Feldhoschet 16",
    "sg:city":"Mollis",
    "sg:orig_category":"Sportvereine Turnen",
    "sg:phone":"+41 55 612 40 59",
    "sg:postcode":"8753",
    "sg:province":"Glarus",
    "wof:name":"Turnverein Mollis",
    "wof:placetype":"venue"
},
  "geometry": {"coordinates":[9.0765161514,47.0880088806],"type":"Point"}
}