{
  "type": "Feature",
  "properties": {
    "iso:country":"CH",
    "sg:address":"Hofstrasse 132",
    "sg:city":"Schafisheim",
    "sg:orig_category":"Sportvereine Velo Rad-& Motorfahrer-Bund SRB",
    "sg:postcode":"5503",
    "sg:province":"Aargau",
    "wof:name":"Velo-& Motoclub Schafisheim",
    "wof:placetype":"venue"
},
  "geometry": {"coordinates":[8.1427593231,47.3769226074],"type":"Point"}
}