{
  "type": "Feature",
  "properties": {
    "iso:country":"CH",
    "sg:address":"Chemin De La Criblette 1091 Grandvaux. Postfach",
    "sg:city":"Grandvaux",
    "sg:orig_category":"Grosshandel mit Getreide, Saatgut U Futtermitteln",
    "sg:postcode":"1091",
    "sg:province":"Vaud",
    "wof:name":"Network Distribution, Frass Beno\u00eet",
    "wof:placetype":"venue"
},
  "geometry": {"coordinates":[6.7248702049,46.498374939],"type":"Point"}
}