{
  "type": "Feature",
  "properties": {
    "iso:country":"CH",
    "sg:address":"Achern 49",
    "sg:city":"Frutigen",
    "sg:orig_category":"Bauschreinerei Herstellung von Konstruktionsteilen, Fertigbauteilen U Ausbauelementen aus Holz",
    "sg:phone":"+41 33 671 13 77",
    "sg:postcode":"3714",
    "sg:province":"Bern",
    "wof:name":"Gottlieb Sarbach Schreinerei & Innenausbau",
    "wof:placetype":"venue"
},
  "geometry": {"coordinates":[7.656702,46.566963],"type":"Point"}
}