{
  "type": "Feature",
  "properties": {
    "iso:country":"CH",
    "sg:address":"Bullingerstrasse 62",
    "sg:city":"Z\u00fcrich",
    "sg:orig_category":"Schwimmb\u00e4der",
    "sg:phone":"+41 14916343",
    "sg:postcode":"8004",
    "sg:province":"Z\u00fcrich",
    "wof:name":"Schulhaus Hardau Betriebsleitung Hallenbad",
    "wof:placetype":"venue"
},
  "geometry": {"coordinates":[8.509601593,47.3819007874],"type":"Point"}
}