{
  "type": "Feature",
  "properties": {
    "iso:country":"CH",
    "sg:address":"T\u00f6distrasse 44 8810 Horgen. Postfach",
    "sg:city":"Horgen",
    "sg:orig_category":"Datenverarbeitungsdienste",
    "sg:phone":"+41 17274252",
    "sg:postcode":"8810",
    "sg:province":"Z\u00fcrich",
    "wof:name":"Ballag Ag",
    "wof:placetype":"venue"
},
  "geometry": {"coordinates":[8.584306,47.260662],"type":"Point"}
}