{
  "type": "Feature",
  "properties": {
    "addr:full":"Ch. De La Paumi\u00e8re 20 Ch\u00eane-bougeries Gen\u00e8ve 1224",
    "addr:housenumber":"20",
    "addr:postcode":"1224",
    "addr:street":"Ch. De La Paumie\u0300Re",
    "iso:country":"CH",
    "sg:address":"Ch. De La Paumi\u00e8re 20",
    "sg:city":"Ch\u00eane-bougeries",
    "sg:orig_category":"Allgemeinbildende weiterf\u00fchrende Schulen",
    "sg:postcode":"1224",
    "sg:province":"Gen\u00e8ve",
    "wof:name":"Institution De La Pommi\u00e8re",
    "wof:placetype":"venue"
},
  "geometry": {"coordinates":[6.174315,46.190178],"type":"Point"}
}