{
  "type": "Feature",
  "properties": {
    "iso:country":"CH",
    "sg:address":"Dixence Rue De La 51",
    "sg:city":"Sitten",
    "sg:orig_category":"RESTAURANTS: TEA-ROOMS",
    "sg:postcode":"1950",
    "sg:province":"Valais",
    "wof:name":"Le Stars, Marques Fernandes Paulo",
    "wof:placetype":"venue"
},
  "geometry": {"coordinates":[7.3588571548,46.2280921936],"type":"Point"}
}