{
  "type": "Feature",
  "properties": {
    "iso:country":"CH",
    "sg:address":"Via Locarno 1 6616 Losone. Postfach",
    "sg:city":"Losone",
    "sg:orig_category":"Fachdetailhandel mit pharmazeutischen Produkten",
    "sg:phone":"+41 79 467 68 00",
    "sg:postcode":"6616",
    "sg:province":"Ticino",
    "wof:name":"Farmacia San Lorenzo Di Bianda Gabriele",
    "wof:placetype":"venue"
},
  "geometry": {"coordinates":[8.7607126236,46.1648406982],"type":"Point"}
}