{
  "type": "Feature",
  "properties": {
    "iso:country":"CH",
    "sg:address":"Sch\u00f6neggstrasse 22",
    "sg:city":"Z\u00fcrich",
    "sg:orig_category":"Gymnastik U Fitnesszentren Kosmetikinstitute",
    "sg:phone":"+41 12416808",
    "sg:postcode":"8004",
    "sg:province":"Z\u00fcrich",
    "wof:name":"Beatrice Frischknecht",
    "wof:placetype":"venue"
},
  "geometry": {"coordinates":[8.5266437531,47.3803863525],"type":"Point"}
}