{
  "type": "Feature",
  "properties": {
    "iso:country":"CH",
    "sg:address":"Via Maraini 12 6908 Massagno Caselle. Postfach",
    "sg:city":"Massagno",
    "sg:orig_category":"Non-Classified Establishments",
    "sg:postcode":"6900",
    "sg:province":"Ticino",
    "wof:name":"Swisslawweb Gmbh",
    "wof:placetype":"venue"
},
  "geometry": {"coordinates":[7.9514107704,47.5458488464],"type":"Point"}
}