{
  "type": "Feature",
  "properties": {
    "iso:country":"CH",
    "sg:address":"7530 Zernez. Postfach",
    "sg:city":"Zernez",
    "sg:orig_category":"Elektrizit\u00e4tsversorgung",
    "sg:phone":"+41 81 851 43 11",
    "sg:postcode":"7530",
    "sg:province":"Graubunden",
    "wof:name":"Engadiner Kraftwerke Ag",
    "wof:placetype":"venue"
},
  "geometry": {"coordinates":[10.0946302414,46.7002983093],"type":"Point"}
}