{
  "type": "Feature",
  "properties": {
    "iso:country":"CH",
    "sg:address":"Acherweg 92 6370 Stans. Postfach",
    "sg:city":"Stans",
    "sg:orig_category":"Detailhandel mit Ton U Bildtr\u00e4gern",
    "sg:phone":"+41 31 311 66 30",
    "sg:postcode":"6371",
    "sg:province":"Nidwalden",
    "wof:name":"Stefan Beeli Record Junkie Schallplatten",
    "wof:placetype":"venue"
},
  "geometry": {"coordinates":[7.4518508911,46.948135376],"type":"Point"}
}