{
  "type": "Feature",
  "properties": {
    "iso:country":"CH",
    "sg:address":"Tramstrasse 3",
    "sg:city":"Suhr",
    "sg:classifiers":[
        {
            "category":"Government",
            "subcategory":"Post Office",
            "type":"Public Place"
        }
    ],
    "sg:phone":"+41 62 842 45 56",
    "sg:postcode":"5034",
    "sg:province":"Aargau",
    "sg:tags":[
        "caf\u00e9s",
        "tea-rooms"
    ],
    "wof:name":"Tea-room Hodel",
    "wof:placetype":"venue"
},
  "geometry": {"coordinates":[8.0807008743,47.3725204468],"type":"Point"}
}