{
  "type": "Feature",
  "properties": {
    "iso:country":"CH",
    "sg:address":"Zugerstrasse 91 8820 W\u00e4denswil. Postfach 104",
    "sg:city":"W\u00e4denswil",
    "sg:orig_category":"Bauspenglerei Vermietung U Verpachtung von eigenen Immobilien",
    "sg:phone":"+41 17803490",
    "sg:postcode":"8820",
    "sg:province":"Z\u00fcrich",
    "wof:name":"Brenner Haustechnik Ag",
    "wof:placetype":"venue"
},
  "geometry": {"coordinates":[8.659977,47.231331],"type":"Point"}
}