{
  "type": "Feature",
  "properties": {
    "iso:country":"CH",
    "sg:address":"Marktgasse 8 8400 Winterthur. Postfach",
    "sg:city":"Winterthur",
    "sg:orig_category":"Grosshandel mit elektrischen Haushaltsger\u00e4ten, Radio U Fernsehger\u00e4ten Herstellung von sonstigen elek",
    "sg:phone":"+41 17642060",
    "sg:postcode":"8402",
    "sg:province":"Z\u00fcrich",
    "wof:name":"Domeisen Kurt Ag",
    "wof:placetype":"venue"
},
  "geometry": {"coordinates":[8.5281448364,47.2442779541],"type":"Point"}
}