{
  "type": "Feature",
  "properties": {
    "iso:country":"CH",
    "sg:address":"Auer Strasse 37",
    "sg:city":"Berneck",
    "sg:orig_category":"Herstellung von Gummi U Kunststoffwaren Herstellung von sonstigen Metallwaren",
    "sg:phone":"+41 79 356 79 90",
    "sg:postcode":"9442",
    "sg:province":"St. Gallen",
    "wof:name":"Ernst Sauter Ag",
    "wof:placetype":"venue"
},
  "geometry": {"coordinates":[7.5967187881,47.4978179932],"type":"Point"}
}