{
  "type": "Feature",
  "properties": {
    "iso:country":"CH",
    "sg:address":"Rue Des Grands-pr\u00e9s 71",
    "sg:city":"Bassecourt",
    "sg:orig_category":"Detailhandel mit Waren verschiedener Art, Hauptrichtung Nahrungsmittel",
    "sg:phone":"+41 27 939 12 60",
    "sg:postcode":"2854",
    "sg:province":"Jura",
    "wof:name":"Rosemarie Rieder Vis-\u00e0-vis Lebensmittel",
    "wof:placetype":"venue"
},
  "geometry": {"coordinates":[7.7845520973,46.4042396545],"type":"Point"}
}