{
  "type": "Feature",
  "properties": {
    "iso:country":"CH",
    "sg:address":"8320",
    "sg:city":"Fehraltorf",
    "sg:orig_category":"Unclassifiable Establishments",
    "sg:postcode":"8320",
    "sg:province":"Z\u00fcrich",
    "wof:name":"S",
    "wof:placetype":"venue"
},
  "geometry": {"coordinates":[8.7523164749,47.3878517151],"type":"Point"}
}