{
  "type": "Feature",
  "properties": {
    "iso:country":"CH",
    "sg:address":"Brunnenstrasse 2 8610 Uster. Postfach",
    "sg:city":"Uster",
    "sg:orig_category":"Grosshandel mit Holz U Baustoffen",
    "sg:phone":"+41 19405700",
    "sg:postcode":"8610",
    "sg:province":"Z\u00fcrich",
    "wof:name":"Kies & Beton Ag Uster",
    "wof:placetype":"venue"
},
  "geometry": {"coordinates":[8.7200050354,47.3499832153],"type":"Point"}
}