{
  "type": "Feature",
  "properties": {
    "iso:country":"CH",
    "sg:address":"H\u00fcgelweg 8 6410 Goldau. Postfach 52",
    "sg:city":"Goldau",
    "sg:orig_category":"Aktivit\u00e4ten der Generalunternehmen im Baugewerbe Architektur U Ingenieurb\u00fcros",
    "sg:phone":"+41 41 855 32 00",
    "sg:postcode":"6410",
    "sg:province":"Schwyz",
    "wof:name":"Architekturb\u00fcro Gr\u00e4tzer Robert",
    "wof:placetype":"venue"
},
  "geometry": {"coordinates":[8.551729,47.046753],"type":"Point"}
}