{
  "type": "Feature",
  "properties": {
    "iso:country":"CH",
    "sg:address":"Lindenstrasse 18 8880 Walenstadt. Postfach 9",
    "sg:city":"Walenstadt",
    "sg:orig_category":"Grosshandel mit sonstigen Gebrauchs U Verbrauchsg\u00fctern Sonstiger Fachdetailhandel in Verkaufsr\u00e4umen",
    "sg:phone":"+41 81 735 10 15",
    "sg:postcode":"8880",
    "sg:province":"St. Gallen",
    "wof:name":"Bonderer Hubert, Waffengesch\u00e4ft",
    "wof:placetype":"venue"
},
  "geometry": {"coordinates":[9.315782547,47.1233215332],"type":"Point"}
}