{
  "type": "Feature",
  "properties": {
    "iso:country":"CH",
    "sg:address":"Hauptgasse 18",
    "sg:city":"Solothurn",
    "sg:orig_category":"Arztpraxen",
    "sg:phone":"+41 32 623 87 87",
    "sg:postcode":"4500",
    "sg:province":"Solothurn",
    "wof:name":"Dr.med.dieter Nobs Spezialarzt Fmh",
    "wof:placetype":"venue"
},
  "geometry": {"coordinates":[7.536387,47.206902],"type":"Point"}
}