{
  "type": "Feature",
  "properties": {
    "iso:country":"CH",
    "sg:address":"L\u00e4nggasse 34",
    "sg:city":"Biel/bienne",
    "sg:orig_category":"Grosshandel mit sonstigen Halbwaren Verpackungsgewerbe",
    "sg:phone":"+41 32 342 41 71",
    "sg:postcode":"2504",
    "sg:province":"Bern",
    "wof:name":"Jean-jacques Gr\u00e4nicher Verpackungen",
    "wof:placetype":"venue"
},
  "geometry": {"coordinates":[7.27333498,47.1536407471],"type":"Point"}
}