{
  "type": "Feature",
  "properties": {
    "iso:country":"CH",
    "sg:address":"Valais Rue Du 18",
    "sg:city":"Gen\u00e8ve",
    "sg:orig_category":"Herstellung von Maschinen f\u00fcr die Nahrungsmittel, Getr\u00e4nkeherstellung U die Tabakverarbeitung",
    "sg:postcode":"1202",
    "sg:province":"Gen\u00e8ve",
    "wof:name":"Frozen Concept, P. Abegg & D. Tauss",
    "wof:placetype":"venue"
},
  "geometry": {"coordinates":[6.1416678429,46.2167472839],"type":"Point"}
}