{
  "type": "Feature",
  "properties": {
    "iso:country":"CH",
    "sg:address":"Coteau Rue Du 10 2502 Biel/bienne. Postfach",
    "sg:city":"Biel/bienne",
    "sg:orig_category":"Unclassifiable Establishments",
    "sg:postcode":"2502",
    "sg:province":"Bern",
    "wof:name":"Mandragore Girardin Sa Participations Ect",
    "wof:placetype":"venue"
},
  "geometry": {"coordinates":[7.2572541237,47.1484565735],"type":"Point"}
}