{
  "type": "Feature",
  "properties": {
    "iso:country":"CH",
    "sg:address":"Route De Lavaux 281",
    "sg:city":"Ch\u00e2telard-lutry",
    "sg:orig_category":"Unclassifiable Establishments",
    "sg:postcode":"1095",
    "sg:province":"Vaud",
    "wof:name":"Dominique Peccoud",
    "wof:placetype":"venue"
},
  "geometry": {"coordinates":[6.2243170738,46.2624664307],"type":"Point"}
}