{
  "type": "Feature",
  "properties": {
    "iso:country":"CH",
    "sg:address":"Rebenweg 3a 6331 H\u00fcnenberg. Postfach 430",
    "sg:city":"H\u00fcnenberg",
    "sg:orig_category":"Detailhandel mit Radio U Fernsehger\u00e4ten",
    "sg:phone":"+41 41 783 01 01",
    "sg:postcode":"6331",
    "sg:province":"Zug",
    "wof:name":"De Fernsehdokter Radio-tv",
    "wof:placetype":"venue"
},
  "geometry": {"coordinates":[8.4245128632,47.175693512],"type":"Point"}
}