{
  "type": "Feature",
  "properties": {
    "iso:country":"CH",
    "sg:address":"Eriz",
    "sg:city":"Eriz",
    "sg:classifiers":[
        {
            "category":"Banks & Credit Unions",
            "subcategory":"Bank",
            "type":"Services"
        }
    ],
    "sg:phone":"+41 33531533",
    "sg:postcode":"3619",
    "sg:province":"Bern",
    "wof:name":"Raiffeisenkasse Linden",
    "wof:placetype":"venue"
},
  "geometry": {"coordinates":[7.7775,46.788216],"type":"Point"}
}