{
  "type": "Feature",
  "properties": {
    "addr:full":"Talstrasse 44 Hirschthal Aargau 5042",
    "addr:housenumber":"44",
    "addr:postcode":"5042",
    "addr:street":"Talstrasse",
    "iso:country":"CH",
    "sg:address":"Talstrasse 44",
    "sg:city":"Hirschthal",
    "sg:orig_category":"Detailhandel mit Brennstoffen U Heizmaterial",
    "sg:phone":"+41 79 215 51 00",
    "sg:postcode":"5042",
    "sg:province":"Aargau",
    "wof:name":"Samuel M\u00fcller Holzhandlung",
    "wof:placetype":"venue"
},
  "geometry": {"coordinates":[8.055878,47.317848],"type":"Point"}
}