{
  "type": "Feature",
  "properties": {
    "iso:country":"CH",
    "sg:address":"Zentralstrasse 66",
    "sg:city":"Biel/bienne",
    "sg:orig_category":"Sportvereine Billard",
    "sg:phone":"+41 32 322 12 12",
    "sg:postcode":"2503",
    "sg:province":"Bern",
    "wof:name":"Billard-club Biel",
    "wof:placetype":"venue"
},
  "geometry": {"coordinates":[7.2492198944,47.1341514587],"type":"Point"}
}