{
  "type": "Feature",
  "properties": {
    "iso:country":"CH",
    "sg:address":"Via Passeggiata 24 6828 Balerna Casella Postale 36",
    "sg:city":"Chiasso",
    "sg:orig_category":"G\u00fcterbef\u00f6rderung im Strassenverkehr Lagerung",
    "sg:phone":"+41 91 695 06 04",
    "sg:postcode":"6830",
    "sg:province":"Ticino",
    "wof:name":"Abx Logistics/saima Sa",
    "wof:placetype":"venue"
},
  "geometry": {"coordinates":[9.0313053131,45.8347244263],"type":"Point"}
}