{
  "type": "Feature",
  "properties": {
    "iso:country":"CH",
    "sg:address":"Avenue Louis-weck-reynold 28",
    "sg:city":"Fribourg",
    "sg:orig_category":"Wohnheime f\u00fcr Kinder U Jugendliche",
    "sg:phone":"+41 26 322 71 67",
    "sg:postcode":"1700",
    "sg:province":"Fribourg",
    "wof:name":"Foyer Pour Apprentis",
    "wof:placetype":"venue"
},
  "geometry": {"coordinates":[7.1500868797,46.8080329895],"type":"Point"}
}