{
  "type": "Feature",
  "properties": {
    "addr:full":"M\u00fcnstergasse 62 Bern Bern 3011",
    "addr:housenumber":"62",
    "addr:postcode":"3011",
    "addr:street":"Muenstergasse",
    "iso:country":"CH",
    "sg:address":"M\u00fcnstergasse 62",
    "sg:city":"Bern",
    "sg:orig_category":"Ausstellungs U Messeorganisation Kunsthandel",
    "sg:phone":"+41 31 311 69 64",
    "sg:postcode":"3011",
    "sg:province":"Bern",
    "wof:name":"Raphael Rigassi Galerie",
    "wof:placetype":"venue"
},
  "geometry": {"coordinates":[7.448901,46.947571],"type":"Point"}
}