{
  "type": "Feature",
  "properties": {
    "iso:country":"CH",
    "sg:address":"Rigistrasse 25",
    "sg:city":"Z\u00fcrich",
    "sg:orig_category":"Architekturb\u00fcros",
    "sg:phone":"+41 13617250",
    "sg:postcode":"8006",
    "sg:province":"Z\u00fcrich",
    "wof:name":"Brian Dubois Architekturb\u00fcro",
    "wof:placetype":"venue"
},
  "geometry": {"coordinates":[8.5499343872,47.3847961426],"type":"Point"}
}