{
  "type": "Feature",
  "properties": {
    "iso:country":"CH",
    "sg:address":"Soodring 3 8134 Adliswil. Postfach 1034",
    "sg:city":"Adliswil",
    "sg:orig_category":"Grosshandel mit chemischen Erzeugnissen Herstellung von sonstigen Gummiwaren",
    "sg:phone":"+41 17111313",
    "sg:postcode":"8134",
    "sg:province":"Z\u00fcrich",
    "wof:name":"Furter + Co Ag",
    "wof:placetype":"venue"
},
  "geometry": {"coordinates":[8.5223245621,47.3150138855],"type":"Point"}
}