{
  "type": "Feature",
  "properties": {
    "iso:country":"CH",
    "sg:address":"Baragge Via 13",
    "sg:city":"Giubiasco",
    "sg:orig_category":"Non-Classified Establishments",
    "sg:postcode":"6512",
    "sg:province":"Ticino",
    "wof:name":"Ranye Sa",
    "wof:placetype":"venue"
},
  "geometry": {"coordinates":[8.9927110672,46.1711120605],"type":"Point"}
}