{
  "type": "Feature",
  "properties": {
    "iso:country":"CH",
    "sg:address":"Chemin Des Tourterelles 32",
    "sg:city":"Th\u00f4nex",
    "sg:orig_category":"G\u00fcterbef\u00f6rderung im Strassenverkehr",
    "sg:phone":"+41 22 349 76 24",
    "sg:postcode":"1226",
    "sg:province":"Gen\u00e8ve",
    "wof:name":"Guarnieri Giovanni",
    "wof:placetype":"venue"
},
  "geometry": {"coordinates":[6.2213010788,46.2007865906],"type":"Point"}
}