{
  "type": "Feature",
  "properties": {
    "iso:country":"CH",
    "sg:address":"Route Trey",
    "sg:city":"Middes",
    "sg:orig_category":"Detailhandel mit Damenbekleidung",
    "sg:phone":"+41 32 751 11 33",
    "sg:postcode":"1749",
    "sg:province":"Fribourg",
    "wof:name":"Monique Geiser Boutique Frou-frou",
    "wof:placetype":"venue"
},
  "geometry": {"coordinates":[7.069361,47.055992],"type":"Point"}
}