{
  "type": "Feature",
  "properties": {
    "iso:country":"CH",
    "sg:address":"Chemin Des Ch\u00eanes 3",
    "sg:city":"Coppet",
    "sg:orig_category":"Sanit\u00e4r, Heizungs U L\u00fcftungsinstallation Sanit\u00e4rinstallation",
    "sg:phone":"+41 22 776 02 02",
    "sg:postcode":"1296",
    "sg:province":"Vaud",
    "wof:name":"Mariano Lopez Installations Sanitaires",
    "wof:placetype":"venue"
},
  "geometry": {"coordinates":[6.1949009895,46.3222503662],"type":"Point"}
}