{
  "type": "Feature",
  "properties": {
    "iso:country":"CH",
    "sg:address":"Centro Nord-sud 3",
    "sg:city":"Bioggio",
    "sg:orig_category":"Grosshandel mit sonstigen Maschinen U Ausr\u00fcstungen f\u00fcr Industrie, Handel U Schiffahrt",
    "sg:phone":"+41 91 600 20 80",
    "sg:postcode":"6934",
    "sg:province":"Ticino",
    "wof:name":"Bruno Haag Brunova",
    "wof:placetype":"venue"
},
  "geometry": {"coordinates":[8.908655,46.014397],"type":"Point"}
}