{
  "type": "Feature",
  "properties": {
    "iso:country":"CH",
    "sg:address":"Lyssachstrasse 118",
    "sg:city":"Burgdorf",
    "sg:orig_category":"Autogaragen Autospenglereien",
    "sg:phone":"+41 34 422 07 07",
    "sg:postcode":"3400",
    "sg:province":"Bern",
    "wof:name":"Luigi Casto Garage & Carosserie",
    "wof:placetype":"venue"
},
  "geometry": {"coordinates":[7.609445,47.061642],"type":"Point"}
}