{
  "type": "Feature",
  "properties": {
    "iso:country":"CH",
    "sg:address":"Via Al Lido 3",
    "sg:city":"Viganello",
    "sg:orig_category":"Interessenvertretungen",
    "sg:phone":"+41 91 972 90 10",
    "sg:postcode":"6962",
    "sg:province":"Ticino",
    "wof:name":"Vivere Come Prima",
    "wof:placetype":"venue"
},
  "geometry": {"coordinates":[8.9635868073,46.0112609863],"type":"Point"}
}