{
  "type": "Feature",
  "properties": {
    "iso:country":"CH",
    "sg:address":"Arbonerstr. 25",
    "sg:city":"Neukirch-egnach",
    "sg:classifiers":[
        {
            "category":"Manufacturing",
            "subcategory":"Tools & Machinery",
            "type":"Manufacturing & Wholesale Goods"
        }
    ],
    "sg:phone":"+41 71 474 72 72",
    "sg:postcode":"9315",
    "sg:province":"Thurgau",
    "sg:tags":[
        "metallurgy",
        "metalworking"
    ],
    "wof:name":"Wendt Gmbh Meerbusch",
    "wof:placetype":"venue"
},
  "geometry": {"coordinates":[9.3564996719,47.5063591003],"type":"Point"}
}