{
  "type": "Feature",
  "properties": {
    "iso:country":"CH",
    "sg:address":"Via San Gottardo 64",
    "sg:city":"Bellinzona",
    "sg:orig_category":"Detailhandel mit Damenbekleidung Detailhandel mit S\u00e4uglings U Kinderbekleidung",
    "sg:phone":"+41 91 825 95 20",
    "sg:postcode":"6500",
    "sg:province":"Ticino",
    "wof:name":"Baby Centro Bimbo Sa Art.per Neonati Moda Pr\u00e9maman",
    "wof:placetype":"venue"
},
  "geometry": {"coordinates":[9.0343418121,46.2023506165],"type":"Point"}
}