{
  "type": "Feature",
  "properties": {
    "iso:country":"CH",
    "sg:address":"Rue Du Petit-ch\u00eane 38 1003 Lausanne Case Postale 654",
    "sg:city":"Lausanne",
    "sg:orig_category":"Wirtschaftspr\u00fcfung, Steuerberatung U Treuhand",
    "sg:phone":"+41 21 320 59 81",
    "sg:postcode":"1001",
    "sg:province":"Vaud",
    "wof:name":"Fiduciaire Saga Sa De Gestion Et D'administration",
    "wof:placetype":"venue"
},
  "geometry": {"coordinates":[6.6289992332,46.5177955627],"type":"Point"}
}