{
  "type": "Feature",
  "properties": {
    "iso:country":"CH",
    "sg:address":"Via Campagna 35",
    "sg:city":"Canobbio",
    "sg:orig_category":"Maler U Glasergewerbe",
    "sg:postcode":"6952",
    "sg:province":"Ticino",
    "wof:name":"Broglio Emanuela",
    "wof:placetype":"venue"
},
  "geometry": {"coordinates":[8.9665336609,46.0374488831],"type":"Point"}
}