{
  "type": "Feature",
  "properties": {
    "iso:country":"CH",
    "sg:address":"4577",
    "sg:city":"Hessigkofen",
    "sg:orig_category":"Schulpflegen",
    "sg:postcode":"4577",
    "sg:province":"Solothurn",
    "wof:name":"Primarschulkommission Der Gemeinde Hessigkofen",
    "wof:placetype":"venue"
},
  "geometry": {"coordinates":[7.4580898285,47.140209198],"type":"Point"}
}