{
  "type": "Feature",
  "properties": {
    "iso:country":"CH",
    "sg:address":"Moos 19",
    "sg:city":"Hefenhofen",
    "sg:orig_category":"Oberfl\u00e4chenveredlung U W\u00e4rmebehandlung",
    "sg:phone":"+41 32 666 23 33",
    "sg:postcode":"8580",
    "sg:province":"Thurgau",
    "wof:name":"Buser Oberfl\u00e4chentechnik Ag",
    "wof:placetype":"venue"
},
  "geometry": {"coordinates":[7.5573868752,47.1511878967],"type":"Point"}
}