{
  "type": "Feature",
  "properties": {
    "iso:country":"CH",
    "sg:address":"Freiestrasse 21",
    "sg:city":"Uster",
    "sg:classifiers":[
        {
            "category":"Restaurant",
            "type":"Food & Drink"
        }
    ],
    "sg:phone":"+41 81 413 52 51",
    "sg:postcode":"8610",
    "sg:province":"Z\u00fcrich",
    "wof:name":"Restaurant Steinhof",
    "wof:placetype":"venue"
},
  "geometry": {"coordinates":[9.8235263824,46.7945671082],"type":"Point"}
}