{
  "type": "Feature",
  "properties": {
    "iso:country":"CH",
    "sg:address":"L\u00f6wenstrasse 2",
    "sg:city":"Kreuzlingen",
    "sg:orig_category":"Erbringung von Dienstleistungen f\u00fcr Unternehmen Verwaltung von Immobilien",
    "sg:phone":"+41 71 672 31 82",
    "sg:postcode":"8280",
    "sg:province":"Thurgau",
    "wof:name":"Rubin Consulting Inhaber Wipr\u00e4chtiger W. A.",
    "wof:placetype":"venue"
},
  "geometry": {"coordinates":[9.174861908,47.6478805542],"type":"Point"}
}