{
  "type": "Feature",
  "properties": {
    "iso:country":"CH",
    "sg:address":"Gstalderstrasse 1",
    "sg:city":"Aathal-seegr\u00e4ben",
    "sg:orig_category":"Detailhandel mit Getr\u00e4nken Grosshandel mit Getr\u00e4nken",
    "sg:phone":"+41 16871913",
    "sg:postcode":"8607",
    "sg:province":"Z\u00fcrich",
    "wof:name":"Degu-st\u00fcbli M\u00e4gi Giger Weinhandlung",
    "wof:placetype":"venue"
},
  "geometry": {"coordinates":[8.7434005737,47.1990966797],"type":"Point"}
}