{
  "type": "Feature",
  "properties": {
    "iso:country":"CH",
    "sg:address":"St. Ottilienstrasse 44",
    "sg:city":"Buttisholz",
    "sg:orig_category":"Malerei",
    "sg:phone":"+41 41 928 13 85",
    "sg:postcode":"6018",
    "sg:province":"Luzern",
    "wof:name":"Christian Klemenjak Malergesch\u00e4ft",
    "wof:placetype":"venue"
},
  "geometry": {"coordinates":[8.0973863602,47.1088905334],"type":"Point"}
}