{
  "type": "Feature",
  "properties": {
    "iso:country":"CH",
    "sg:address":"Watterstrasse 94",
    "sg:city":"Regensdorf",
    "sg:orig_category":"Herstellung von elektronischen Bauelementen",
    "sg:postcode":"8105",
    "sg:province":"Z\u00fcrich",
    "wof:name":"Lakisol, Lazic",
    "wof:placetype":"venue"
},
  "geometry": {"coordinates":[8.4682540894,47.4332237244],"type":"Point"}
}