{
  "type": "Feature",
  "properties": {
    "iso:country":"CH",
    "sg:address":"Hintere M\u00fchle",
    "sg:city":"Diessenhofen",
    "sg:orig_category":"Korrespondenz U Nachrichtenb\u00fcros, selbst\u00e4ndige Journalisten",
    "sg:postcode":"8253",
    "sg:province":"Thurgau",
    "wof:name":"Hooker Medical Mezinische Redaktion U. Konzepte F\u00fcr Die Pharmazeutische Industrie Usw",
    "wof:placetype":"venue"
},
  "geometry": {"coordinates":[7.5514340401,47.5179176331],"type":"Point"}
}