{
  "type": "Feature",
  "properties": {
    "iso:country":"CH",
    "sg:address":"Haula",
    "sg:city":"Gurmels",
    "sg:orig_category":"Fahrschulen, Flugschulen",
    "sg:phone":"+41 26 674 33 19",
    "sg:postcode":"3212",
    "sg:province":"Fribourg",
    "wof:name":"Bruno Perny Autofahrschule",
    "wof:placetype":"venue"
},
  "geometry": {"coordinates":[7.1745448112,46.891544342],"type":"Point"}
}