{
  "type": "Feature",
  "properties": {
    "iso:country":"CH",
    "sg:address":"11 Chemin De La D\u00eeme",
    "sg:city":"Genthod",
    "sg:orig_category":"Sportvereine Ballsport Badminton",
    "sg:phone":"+41 21 960 22 38",
    "sg:postcode":"1294",
    "sg:province":"Gen\u00e8ve",
    "wof:name":"Badminton-club Villeneuve",
    "wof:placetype":"venue"
},
  "geometry": {"coordinates":[6.926129818,46.3981781006],"type":"Point"}
}