{
  "type": "Feature",
  "properties": {
    "iso:country":"CH",
    "sg:address":"Avenue De Pratifori 13",
    "sg:city":"Sion",
    "sg:orig_category":"Fachdetailhandel in Verkaufsr\u00e4umen",
    "sg:postcode":"1950",
    "sg:province":"Valais",
    "wof:name":"Boutique Broadway, Mme Claudia Valette",
    "wof:placetype":"venue"
},
  "geometry": {"coordinates":[7.3559727669,46.2306137085],"type":"Point"}
}