{
  "type": "Feature",
  "properties": {
    "iso:country":"CH",
    "sg:address":"Kreuzstrasse 1",
    "sg:city":"Oftringen",
    "sg:orig_category":"RESTAURANTS: TEA-ROOMS",
    "sg:phone":"+41 62 797 12 69",
    "sg:postcode":"4665",
    "sg:province":"Aargau",
    "wof:name":"Kurt Meyer Restaurant Traube",
    "wof:placetype":"venue"
},
  "geometry": {"coordinates":[7.9198441505,47.3132858276],"type":"Point"}
}