{
  "type": "Feature",
  "properties": {
    "addr:full":"Ledi Feutersoey Bern 3784",
    "addr:postcode":"3784",
    "iso:country":"CH",
    "sg:address":"Ledi",
    "sg:city":"Feutersoey",
    "sg:orig_category":"Bauschreinerei",
    "sg:phone":"+41 33 755 11 33",
    "sg:postcode":"3784",
    "sg:province":"Bern",
    "wof:name":"Kurt Bratschi Schreinerei",
    "wof:placetype":"venue"
},
  "geometry": {"coordinates":[7.270662,46.419807],"type":"Point"}
}