{
  "type": "Feature",
  "properties": {
    "iso:country":"CH",
    "sg:address":"Rainackerstrasse 11",
    "sg:city":"Dietikon",
    "sg:orig_category":"Sportvereine",
    "sg:phone":"+41 17414604",
    "sg:postcode":"8953",
    "sg:province":"Z\u00fcrich",
    "wof:name":"Ringklub Z\u00fcrich",
    "wof:placetype":"venue"
},
  "geometry": {"coordinates":[8.390707016,47.4068031311],"type":"Point"}
}