{
  "type": "Feature",
  "properties": {
    "iso:country":"CH",
    "sg:address":"Rue Des Uttins 34 1400 Yverdon-les-bains. Postfach 120",
    "sg:city":"Yverdon-les-bains",
    "sg:orig_category":"Detailhandel mit Metallwaren, Anstrichmitteln, Glaswaren, Bau U Heimwerkerbedarf",
    "sg:phone":"+41 24 445 27 37",
    "sg:postcode":"1400",
    "sg:province":"Vaud",
    "wof:name":"Bonzon Claude",
    "wof:placetype":"venue"
},
  "geometry": {"coordinates":[6.6241707802,46.7839164734],"type":"Point"}
}