{
  "type": "Feature",
  "properties": {
    "addr:full":"Dammweg 57/59 M\u00fcnchenbuchsee Bern 3053",
    "addr:housenumber":"57 / 59",
    "addr:postcode":"3053",
    "addr:street":"Dammweg",
    "iso:country":"CH",
    "sg:address":"Dammweg 57/59",
    "sg:city":"M\u00fcnchenbuchsee",
    "sg:orig_category":"Allgemeiner Hoch U Tiefbau Maurerarbeiten",
    "sg:phone":"+41 31 839 52 94",
    "sg:postcode":"3053",
    "sg:province":"Bern",
    "wof:name":"Zaugg Hansruedi",
    "wof:placetype":"venue"
},
  "geometry": {"coordinates":[7.544254,46.927406],"type":"Point"}
}