{
  "type": "Feature",
  "properties": {
    "iso:country":"CH",
    "sg:address":"Schulhausstrasse 6",
    "sg:city":"Hochfelden",
    "sg:orig_category":"Kosmetikinstitute",
    "sg:phone":"+41 18620242",
    "sg:postcode":"8182",
    "sg:province":"Z\u00fcrich",
    "wof:name":"Gabi Spescha Kosmetikinstitut",
    "wof:placetype":"venue"
},
  "geometry": {"coordinates":[8.5148906708,47.5256996155],"type":"Point"}
}