{
  "type": "Feature",
  "properties": {
    "iso:country":"CH",
    "sg:address":"Monteilly",
    "sg:city":"Champ\u00e9ry",
    "sg:orig_category":"Sportvereine Ballsport Tennis",
    "sg:postcode":"1874",
    "sg:province":"Valais",
    "wof:name":"Tennisclub Charmey",
    "wof:placetype":"venue"
},
  "geometry": {"coordinates":[7.1641640663,46.6192207336],"type":"Point"}
}