{
  "type": "Feature",
  "properties": {
    "iso:country":"CH",
    "sg:address":"Inzlingerstrasse 327",
    "sg:city":"Riehen",
    "sg:orig_category":"Herstellung von Drahtwaren Sonstiger spezialisierter Hoch U Tiefbau",
    "sg:phone":"+41 71 385 92 38",
    "sg:postcode":"4125",
    "sg:province":"Basel-Stadt",
    "wof:name":"B\u00fcchel Peter Ag Gossau",
    "wof:placetype":"venue"
},
  "geometry": {"coordinates":[9.2686271667,47.4195022583],"type":"Point"}
}