{
  "type": "Feature",
  "properties": {
    "iso:country":"CH",
    "sg:address":"3176",
    "sg:city":"Neuenegg",
    "sg:orig_category":"Wasserversorgung",
    "sg:postcode":"3176",
    "sg:province":"Bern",
    "wof:name":"Schlegel-wasserversorgungs-genossenschaft Neuenegg",
    "wof:placetype":"venue"
},
  "geometry": {"coordinates":[7.3022098541,46.8938751221],"type":"Point"}
}