{
  "type": "Feature",
  "properties": {
    "iso:country":"CH",
    "sg:address":"Pilatusring 29",
    "sg:city":"Rothenburg",
    "sg:orig_category":"Architekturb\u00fcros",
    "sg:phone":"+41 41 280 54 78",
    "sg:postcode":"6023",
    "sg:province":"Luzern",
    "wof:name":"Hans Holenstein Architekturb\u00fcro",
    "wof:placetype":"venue"
},
  "geometry": {"coordinates":[8.274354,47.098228],"type":"Point"}
}