{
  "type": "Feature",
  "properties": {
    "iso:country":"CH",
    "sg:address":"H\u00f6heweg 41 3800 Interlaken. Postfach 113",
    "sg:city":"Interlaken",
    "sg:classifiers":[
        {
            "category":"Travel",
            "subcategory":"Hotels & Motels",
            "type":"Entertainment"
        }
    ],
    "sg:phone":"+41 33 828 28 28",
    "sg:postcode":"3800",
    "sg:province":"Bern",
    "sg:tags":[
        "hotels",
        "mit",
        "restaurant"
    ],
    "wof:name":"Grand Hotel Victoria-jungfrau Ag In Interlaken",
    "wof:placetype":"venue"
},
  "geometry": {"coordinates":[7.8570871353,46.686252594],"type":"Point"}
}