{
  "type": "Feature",
  "properties": {
    "addr:full":"Route De Lully 61 1470 Estavayer-le-lac Case Postale 246 Estavayer-le-lac Fribourg 1470",
    "addr:housenumber":"61;246",
    "addr:postcode":"1470;1470",
    "addr:street":"Route De Lully;Case Postale;Fribourg",
    "iso:country":"CH",
    "sg:address":"Route De Lully 61 1470 Estavayer-le-lac Case Postale 246",
    "sg:city":"Estavayer-le-lac",
    "sg:orig_category":"Allgemeiner Hoch U Tiefbau Allgemeiner Hochbau",
    "sg:phone":"+41 26 663 99 97",
    "sg:postcode":"1470",
    "sg:province":"Fribourg",
    "wof:name":"St\u00e9phane Mauron Sa",
    "wof:placetype":"venue"
},
  "geometry": {"coordinates":[6.847806,46.839161],"type":"Point"}
}