{
  "type": "Feature",
  "properties": {
    "addr:full":"Lachenal Rue Adrien- 20 1207 Gen\u00e8ve. Postfach Gen\u00e8ve Gen\u00e8ve 1207",
    "addr:housenumber":"20",
    "addr:postcode":"1207;postfach;1207",
    "addr:street":"Rue Adrien",
    "iso:country":"CH",
    "sg:address":"Lachenal Rue Adrien- 20 1207 Gen\u00e8ve. Postfach",
    "sg:city":"Gen\u00e8ve",
    "sg:orig_category":"Binnenschiffahrt",
    "sg:postcode":"1207",
    "sg:province":"Gen\u00e8ve",
    "wof:name":"Nile Maritime Brokers Sa",
    "wof:placetype":"venue"
},
  "geometry": {"coordinates":[6.15603,46.199745],"type":"Point"}
}