{
  "type": "Feature",
  "properties": {
    "iso:country":"CH",
    "sg:address":"Kirchweg 11",
    "sg:city":"Beckenried",
    "sg:orig_category":"Verlagsgewerbe",
    "sg:phone":"+41 41 624 92 92",
    "sg:postcode":"6375",
    "sg:province":"Nidwalden",
    "wof:name":"Ligra-verlag Ag",
    "wof:placetype":"venue"
},
  "geometry": {"coordinates":[8.4741830826,46.9666175842],"type":"Point"}
}