{
  "type": "Feature",
  "properties": {
    "iso:country":"CH",
    "sg:address":"Lavizzari Via 4",
    "sg:city":"Lugano",
    "sg:orig_category":"Vermietung U Verpachtung von eigenen Immobilien",
    "sg:postcode":"6900",
    "sg:province":"Ticino",
    "wof:name":"Feor Sa",
    "wof:placetype":"venue"
},
  "geometry": {"coordinates":[8.8413286209,45.988571167],"type":"Point"}
}