{
  "type": "Feature",
  "properties": {
    "iso:country":"CH",
    "sg:address":"Bahnhofstrasse 32",
    "sg:city":"Liestal",
    "sg:orig_category":"Erschliessung von Grundst\u00fccken",
    "sg:phone":"+41 61 825 51 11",
    "sg:postcode":"4410",
    "sg:province":"Basel-Landschaft",
    "wof:name":"Stiftung Locacasa Basel-landschaft F\u00fcr Miet-eigentum",
    "wof:placetype":"venue"
},
  "geometry": {"coordinates":[7.7320151329,47.4846687317],"type":"Point"}
}