{
  "type": "Feature",
  "properties": {
    "iso:country":"CH",
    "sg:address":"Wassersch\u00f6pfi 42",
    "sg:city":"Z\u00fcrich",
    "sg:orig_category":"Herstellung von konfektionierten Textilwaren ohne Bekleidung",
    "sg:postcode":"8055",
    "sg:province":"Z\u00fcrich",
    "wof:name":"Intersol W\u00f6gerer W. Storen, -bestandteile Usw; Herstellung, Verkauf",
    "wof:placetype":"venue"
},
  "geometry": {"coordinates":[8.5075283051,47.3665046692],"type":"Point"}
}