{
  "type": "Feature",
  "properties": {
    "iso:country":"CH",
    "sg:address":"B\u00fcchzelglistrasse 81",
    "sg:city":"W\u00fcrenlos",
    "sg:orig_category":"Ingenieurb\u00fcros Umwelttechnik and \u00d6kologie",
    "sg:phone":"+41 56 424 23 37",
    "sg:postcode":"5436",
    "sg:province":"Aargau",
    "wof:name":"Dr.charles Perrin Verfahrens-& Umwelttechnik",
    "wof:placetype":"venue"
},
  "geometry": {"coordinates":[8.3550758362,47.435798645],"type":"Point"}
}