{
  "type": "Feature",
  "properties": {
    "iso:country":"CH",
    "sg:address":"Via Mondacce 183c",
    "sg:city":"Minusio",
    "sg:orig_category":"Grosshandel mit chemischen Erzeugnissen Handelsvermittlung U Grosshandel",
    "sg:phone":"+41 91 745 68 48",
    "sg:postcode":"6648",
    "sg:province":"Ticino",
    "wof:name":"Enitecni Sagl",
    "wof:placetype":"venue"
},
  "geometry": {"coordinates":[8.8345098495,46.1821594238],"type":"Point"}
}