{
  "type": "Feature",
  "properties": {
    "iso:country":"CH",
    "sg:address":"Dorfstrasse 575",
    "sg:city":"Gontenschwil",
    "sg:orig_category":"Sportvereine Turnen",
    "sg:phone":"+41 19361309",
    "sg:postcode":"5728",
    "sg:province":"Aargau",
    "wof:name":"Turnverein Stv Gossau Zh",
    "wof:placetype":"venue"
},
  "geometry": {"coordinates":[8.7672395706,47.3001289368],"type":"Point"}
}