{
  "type": "Feature",
  "properties": {
    "iso:country":"CH",
    "sg:address":"B\u00e4ulerwisenstrasse 8152 Glattbrugg. Postfach",
    "sg:city":"Glattbrugg",
    "sg:orig_category":"Kauf U Verkauf von Immobilien auf eigene Rechnung",
    "sg:postcode":"8152",
    "sg:province":"Z\u00fcrich",
    "wof:name":"Icd-mond Sa",
    "wof:placetype":"venue"
},
  "geometry": {"coordinates":[8.5740098953,47.4292984009],"type":"Point"}
}