{
  "type": "Feature",
  "properties": {
    "iso:country":"CH",
    "sg:address":"Crespera Via 78 6932 Breganzona. Postfach",
    "sg:city":"Paradiso",
    "sg:orig_category":"RESTAURANTS: TEA-ROOMS",
    "sg:postcode":"6900",
    "sg:province":"Ticino",
    "wof:name":"Gregeris Sa",
    "wof:placetype":"venue"
},
  "geometry": {"coordinates":[8.9248876572,46.0064048767],"type":"Point"}
}