{
  "type": "Feature",
  "properties": {
    "iso:country":"CH",
    "sg:address":"9478",
    "sg:city":"Azmoos",
    "sg:orig_category":"Landesverteidigung, Sozialversicherung \u00d6ffentliche Verwaltung",
    "sg:phone":"+41 81 783 11 28",
    "sg:postcode":"9478",
    "sg:province":"St. Gallen",
    "wof:name":"Zivilschutzstelle Wartau",
    "wof:placetype":"venue"
},
  "geometry": {"coordinates":[9.4766798019,47.080291748],"type":"Point"}
}