{
  "type": "Feature",
  "properties": {
    "iso:country":"CH",
    "sg:address":"Dufourstrasse 9",
    "sg:city":"Zollikon",
    "sg:orig_category":"Finanzierungsinstitutionen",
    "sg:phone":"+41 19916166",
    "sg:postcode":"8702",
    "sg:province":"Z\u00fcrich",
    "wof:name":"Global Strategic Recruiting & Consulting, Diem & Partner",
    "wof:placetype":"venue"
},
  "geometry": {"coordinates":[8.5667495728,47.3456802368],"type":"Point"}
}