{
  "type": "Feature",
  "properties": {
    "iso:country":"CH",
    "sg:address":"Bahnhofstrasse 98-100",
    "sg:city":"Z\u00fcrich",
    "sg:orig_category":"Unclassifiable Establishments",
    "sg:postcode":"8001",
    "sg:province":"Z\u00fcrich",
    "wof:name":"Ascentis Capital Ag",
    "wof:placetype":"venue"
},
  "geometry": {"coordinates":[8.5396757126,47.3761405945],"type":"Point"}
}