{
  "type": "Feature",
  "properties": {
    "iso:country":"CH",
    "sg:address":"Chemin Creux",
    "sg:city":"Mont-sur-lausanne",
    "sg:orig_category":"Herstellung von sonstigen elektrischen Ausr\u00fcstungen",
    "sg:postcode":"1052",
    "sg:province":"Vaud",
    "wof:name":"Werner R.-m.",
    "wof:placetype":"venue"
},
  "geometry": {"coordinates":[6.635204792,46.5619773865],"type":"Point"}
}