{
  "type": "Feature",
  "properties": {
    "iso:country":"CH",
    "sg:address":"Felmis",
    "sg:city":"Bauma",
    "sg:orig_category":"Haltung von Gefl\u00fcgel",
    "sg:phone":"+41 52 386 21 39",
    "sg:postcode":"8494",
    "sg:province":"Z\u00fcrich",
    "wof:name":"Rudolf St\u00f6ckli Gefl\u00fcgelzuchtbetriebe",
    "wof:placetype":"venue"
},
  "geometry": {"coordinates":[8.8535060883,47.3754196167],"type":"Point"}
}