{
  "type": "Feature",
  "properties": {
    "iso:country":"CH",
    "sg:address":"Nettenberg 8 9607 Mosnang. Postfach",
    "sg:city":"Mosnang",
    "sg:orig_category":"Fachdetailhandel in Verkaufsr\u00e4umen",
    "sg:phone":"+41 32 935 13 24",
    "sg:postcode":"9607",
    "sg:province":"St. Gallen",
    "wof:name":"Schneider Jacqueline",
    "wof:placetype":"venue"
},
  "geometry": {"coordinates":[6.607708931,46.9826507568],"type":"Point"}
}