{
  "type": "Feature",
  "properties": {
    "iso:country":"CH",
    "sg:address":"Birsstrasse 58 4052 Basel. Postfach",
    "sg:city":"Basel",
    "sg:orig_category":"Grosshandel mit M\u00f6beln, Wohnbedarf, Teppichen U Bodenbel\u00e4gen Instandhaltung U Reparatur von Automobi",
    "sg:phone":"+41 18500083",
    "sg:postcode":"4006",
    "wof:name":"Weidmann H.j. Ag",
    "wof:placetype":"venue"
},
  "geometry": {"coordinates":[8.5099258423,47.4696540833],"type":"Point"}
}