{
  "type": "Feature",
  "properties": {
    "iso:country":"CH",
    "sg:address":"Oberburgstrasse 7 3400 Burgdorf. Postfach",
    "sg:city":"Burgdorf",
    "sg:orig_category":"Fotografische Ateliers",
    "sg:phone":"+41 79 208 90 21",
    "sg:postcode":"3401",
    "sg:province":"Bern",
    "wof:name":"Andreas Marbot Fotografisches Atelier",
    "wof:placetype":"venue"
},
  "geometry": {"coordinates":[7.6244711876,47.0537910461],"type":"Point"}
}