{
  "type": "Feature",
  "properties": {
    "iso:country":"CH",
    "sg:address":"Gerbistrasse 1",
    "sg:city":"Ennenda",
    "sg:orig_category":"Zahnarztpraxen",
    "sg:phone":"+41 55 640 89 32",
    "sg:postcode":"8755",
    "sg:province":"Glarus",
    "wof:name":"Dr. Med. Dent. Milan Skorjanec Zahnarzt",
    "wof:placetype":"venue"
},
  "geometry": {"coordinates":[9.0705842972,47.0446281433],"type":"Point"}
}