{
  "type": "Feature",
  "properties": {
    "iso:country":"CH",
    "sg:address":"Sch\u00fctzenweg 39",
    "sg:city":"Bern",
    "sg:orig_category":"Arztpraxen",
    "sg:phone":"+41 55 210 34 34",
    "sg:postcode":"3014",
    "sg:province":"Bern",
    "wof:name":"Dr.med. Michael A. Brabetz Spezialarzt Fmh",
    "wof:placetype":"venue"
},
  "geometry": {"coordinates":[8.820521,47.232613],"type":"Point"}
}