{
  "type": "Feature",
  "properties": {
    "iso:country":"CH",
    "sg:address":"Elvezia Corso 16",
    "sg:city":"Lugano",
    "sg:orig_category":"Handels-H\u00e4user U Gesellschaften",
    "sg:postcode":"6900",
    "sg:province":"Ticino",
    "wof:name":"Lumbreda Sa",
    "wof:placetype":"venue"
},
  "geometry": {"coordinates":[9.1283597946,46.2375984192],"type":"Point"}
}