{
  "type": "Feature",
  "properties": {
    "iso:country":"CH",
    "sg:address":"Rue De La Gare 17",
    "sg:city":"Nyon",
    "sg:orig_category":"Reiseb\u00fcros",
    "sg:phone":"+41 22 361 88 22",
    "sg:postcode":"1260",
    "sg:province":"Vaud",
    "wof:name":"Voyages-ssr Serv.suisse Tourisme Etudiants",
    "wof:placetype":"venue"
},
  "geometry": {"coordinates":[6.2373929024,46.3828620911],"type":"Point"}
}