{
  "type": "Feature",
  "properties": {
    "iso:country":"CH",
    "sg:address":"Chem De L'ochettaz 2",
    "sg:city":"St-sulpice",
    "sg:classifiers":[
        {
            "category":"Building & Trades",
            "subcategory":"Construction",
            "type":"Services"
        }
    ],
    "sg:phone":"+41 21 694 33 80",
    "sg:postcode":"1025",
    "sg:province":"Vaud",
    "sg:tags":[
        "work",
        "public"
    ],
    "wof:name":"Bourgoz Paysages Sarl",
    "wof:placetype":"venue"
},
  "geometry": {"coordinates":[6.556129,46.513561],"type":"Point"}
}