{
  "type": "Feature",
  "properties": {
    "addr:full":"Ronstrasse 5-7 Ebikon Luzern 6030",
    "addr:housenumber":"5-7",
    "addr:postcode":"6030",
    "addr:street":"Ronstrasse",
    "iso:country":"CH",
    "sg:address":"Ronstrasse 5-7",
    "sg:city":"Ebikon",
    "sg:classifiers":[
        {
            "category":"Home & Garden",
            "subcategory":"Building Materials",
            "type":"Retail Goods"
        }
    ],
    "sg:phone":"+41 41 445 15 15",
    "sg:postcode":"6030",
    "sg:province":"Luzern",
    "sg:tags":[
        "aluminium",
        "window"
    ],
    "wof:name":"Kronenberger Ag",
    "wof:placetype":"venue"
},
  "geometry": {"coordinates":[8.345168,47.087643],"type":"Point"}
}