{
  "type": "Feature",
  "properties": {
    "iso:country":"CH",
    "sg:address":"La Cond\u00e9mine.",
    "sg:city":"Vuadens",
    "sg:orig_category":"Grosshandel mit sonstigen Gebrauchs U Verbrauchsg\u00fctern",
    "sg:postcode":"1628",
    "sg:province":"Fribourg",
    "wof:name":"Sv Diffusions, Vionnet St\u00e9phane.",
    "wof:placetype":"venue"
},
  "geometry": {"coordinates":[7.0251197815,46.6166191101],"type":"Point"}
}