{
  "type": "Feature",
  "properties": {
    "iso:country":"CH",
    "sg:address":"Rue Des Eaux-vives 59",
    "sg:city":"Gen\u00e8ve",
    "sg:orig_category":"Detailhandel mit M\u00f6beln",
    "sg:phone":"+41 22 786 45 40",
    "sg:postcode":"1207",
    "sg:province":"Gen\u00e8ve",
    "wof:name":"Elisa Gassert Meubles Peints Pour Enfants",
    "wof:placetype":"venue"
},
  "geometry": {"coordinates":[6.1596140862,46.2049407959],"type":"Point"}
}