{
  "type": "Feature",
  "properties": {
    "iso:country":"CH",
    "sg:address":"Rue Carteret 42 1200 Genf. Postfach",
    "sg:city":"Genf",
    "sg:orig_category":"Pensionskassen",
    "sg:postcode":"1200",
    "sg:province":"Gen\u00e8ve",
    "wof:name":"Fondation De Secours Des Pharmacies Populaires De Gen\u00e8ve Et Des Soci\u00e9t\u00e9s Affili\u00e9es",
    "wof:placetype":"venue"
},
  "geometry": {"coordinates":[6.142701149,46.2083587646],"type":"Point"}
}