{
  "type": "Feature",
  "properties": {
    "iso:country":"CH",
    "sg:address":"Weissensteinstrasse 15 4500 Solothurn. Postfach",
    "sg:city":"Solothurn",
    "sg:classifiers":[
        {
            "category":"Insurance",
            "subcategory":"Insurance Agent",
            "type":"Services"
        }
    ],
    "sg:phone":"+41 32 625 95 85",
    "sg:postcode":"4503",
    "sg:province":"Solothurn",
    "sg:tags":[
        "versicherungsagenturen",
        "-broker"
    ],
    "wof:name":"Evt-euro Versicherungs-treuhand Ag",
    "wof:placetype":"venue"
},
  "geometry": {"coordinates":[7.527990818,47.2112426758],"type":"Point"}
}