{
  "type": "Feature",
  "properties": {
    "iso:country":"CH",
    "sg:address":"Reinacherstrasse 92 4055 Basel. Postfach",
    "sg:city":"Basel",
    "sg:orig_category":"Maler U Glasergewerbe",
    "sg:phone":"+41 61 301 27 27",
    "sg:postcode":"4009",
    "sg:province":"Basel-Stadt",
    "wof:name":"Frei + Moser Malergesch\u00e4ft Ag",
    "wof:placetype":"venue"
},
  "geometry": {"coordinates":[7.6035151482,47.5381278992],"type":"Point"}
}