{
  "type": "Feature",
  "properties": {
    "iso:country":"CH",
    "sg:address":"Le Canard 1523 Granges-marnand. Postfach",
    "sg:city":"Granges-marnand",
    "sg:orig_category":"Lagerung",
    "sg:postcode":"1523",
    "sg:province":"Vaud",
    "wof:name":"Centre Collecteur De Granges-marnand",
    "wof:placetype":"venue"
},
  "geometry": {"coordinates":[6.8920850754,46.7602348328],"type":"Point"}
}