{
  "type": "Feature",
  "properties": {
    "iso:country":"CH",
    "sg:address":"Breichtenstrasse 7a 3074 Muri B. Bern. Postfach",
    "sg:city":"Bern",
    "sg:orig_category":"Architektur U Ingenieurb\u00fcros Architekturb\u00fcros",
    "sg:phone":"+41 61 701 26 96",
    "sg:postcode":"3005",
    "sg:province":"Bern",
    "wof:name":"R\u00fcegg + Partner Architekten Ag",
    "wof:placetype":"venue"
},
  "geometry": {"coordinates":[7.617908,47.49358],"type":"Point"}
}