{
  "type": "Feature",
  "properties": {
    "iso:country":"CH",
    "sg:address":"Ruelle Sainte-claire 10",
    "sg:city":"Orbe",
    "sg:classifiers":[
        {
            "category":"Restaurant",
            "type":"Food & Drink"
        }
    ],
    "sg:phone":"+41 24 441 15 24",
    "sg:postcode":"1350",
    "sg:province":"Vaud",
    "wof:name":"Caf\u00e9 L'ecu Vaudois",
    "wof:placetype":"venue"
},
  "geometry": {"coordinates":[6.5318808556,46.7237129211],"type":"Point"}
}