{
  "type": "Feature",
  "properties": {
    "iso:country":"CH",
    "sg:address":"1753",
    "sg:city":"Matran",
    "sg:orig_category":"Sportvereine Ballsport Fussball",
    "sg:phone":"+41 26 401 19 88",
    "sg:postcode":"1753",
    "sg:province":"Fribourg",
    "wof:name":"Fc Matran",
    "wof:placetype":"venue"
},
  "geometry": {"coordinates":[7.0887098312,46.7851715088],"type":"Point"}
}