{
  "type": "Feature",
  "properties": {
    "iso:country":"CH",
    "sg:address":"Le Rosex",
    "sg:city":"Vers-l'eglise",
    "sg:orig_category":"Autogaragen",
    "sg:phone":"+41 26 912 77 07",
    "sg:postcode":"1864",
    "sg:province":"Vaud",
    "wof:name":"Garage Du Transval Sa",
    "wof:placetype":"venue"
},
  "geometry": {"coordinates":[7.07528,46.603409],"type":"Point"}
}