{
  "type": "Feature",
  "properties": {
    "iso:country":"CH",
    "sg:address":"Holunderweg 2",
    "sg:city":"B\u00fclach",
    "sg:orig_category":"Detailhandel mit Uhren U Schmuck",
    "sg:phone":"+41 41 410 61 70",
    "sg:postcode":"8180",
    "sg:province":"Z\u00fcrich",
    "wof:name":"Ren\u00e9 Liefert Goldschmied-atelier",
    "wof:placetype":"venue"
},
  "geometry": {"coordinates":[8.3068780899,47.0521659851],"type":"Point"}
}