{
  "type": "Feature",
  "properties": {
    "iso:country":"CH",
    "sg:address":"Zwinglistrasse 3",
    "sg:city":"St.gallen",
    "sg:orig_category":"Softwareentwicklung U beratung",
    "sg:phone":"+41 71 220 31 57",
    "sg:postcode":"9000",
    "sg:province":"St. Gallen",
    "wof:name":"Synecta Informatik Ag",
    "wof:placetype":"venue"
},
  "geometry": {"coordinates":[9.3730640411,47.4266204834],"type":"Point"}
}