{
  "type": "Feature",
  "properties": {
    "iso:country":"CH",
    "sg:address":"Scheidweg",
    "sg:city":"Frasnacht",
    "sg:orig_category":"Pensionskassen",
    "sg:phone":"+41 56 442 18 81",
    "sg:postcode":"9320",
    "sg:province":"Thurgau",
    "wof:name":"Brugger Ferienhaus Salomonstempel Hemberg",
    "wof:placetype":"venue"
},
  "geometry": {"coordinates":[8.2340021133,47.5025482178],"type":"Point"}
}