{
  "type": "Feature",
  "properties": {
    "iso:country":"CH",
    "sg:address":"Rue De Zurich 42",
    "sg:city":"Gen\u00e8ve",
    "sg:orig_category":"Detailhandel mit Beleuchtungs U Haushaltsgegenst\u00e4nden Detailhandel mit Spielwaren",
    "sg:phone":"+41 22 731 93 93",
    "sg:postcode":"1201",
    "sg:province":"Gen\u00e8ve",
    "wof:name":"Arcado Sa Coutellerie",
    "wof:placetype":"venue"
},
  "geometry": {"coordinates":[6.145281,46.21236],"type":"Point"}
}