{
  "type": "Feature",
  "properties": {
    "iso:country":"CH",
    "sg:address":"En Plan",
    "sg:city":"Treyvaux",
    "sg:orig_category":"Malerei RESTAURANTS: TEA-ROOMS",
    "sg:phone":"+41 26 413 18 85",
    "sg:postcode":"1733",
    "sg:province":"Fribourg",
    "wof:name":"Neuhaus Antoine",
    "wof:placetype":"venue"
},
  "geometry": {"coordinates":[7.1228837967,46.7250213623],"type":"Point"}
}