{
  "type": "Feature",
  "properties": {
    "iso:country":"CH",
    "sg:address":"2350",
    "sg:city":"Saignel\u00e9gier",
    "sg:orig_category":"Elektroinstallation",
    "sg:phone":"+41 32 951 12 95",
    "sg:postcode":"2350",
    "sg:province":"Jura",
    "wof:name":"Erard Michel, \u00e9lectricit\u00e9",
    "wof:placetype":"venue"
},
  "geometry": {"coordinates":[6.9954299927,47.2558517456],"type":"Point"}
}