{
  "type": "Feature",
  "properties": {
    "iso:country":"CH",
    "sg:address":"R\u00e4tscheng\u00e4ssli 49 8302 Kloten. Postfach",
    "sg:city":"Kloten",
    "sg:orig_category":"Softwareentwicklung U beratung",
    "sg:postcode":"8302",
    "sg:province":"Z\u00fcrich",
    "wof:name":"Di Rocco Informatik Gmbh Edv Programme; Entwicklung. Dienstleistungen Im Bereich Informatik",
    "wof:placetype":"venue"
},
  "geometry": {"coordinates":[8.5875320435,47.4534187317],"type":"Point"}
}