{
  "type": "Feature",
  "properties": {
    "iso:country":"CH",
    "sg:address":"Alfred-andr\u00e9 Avenue 8",
    "sg:city":"Morges",
    "sg:orig_category":"Unclassifiable Establishments",
    "sg:postcode":"1110",
    "sg:province":"Vaud",
    "wof:name":"Dynaconcept, F. Chevalley",
    "wof:placetype":"venue"
},
  "geometry": {"coordinates":[6.503704071,46.5197753906],"type":"Point"}
}