{
  "type": "Feature",
  "properties": {
    "iso:country":"CH",
    "sg:address":"Obergrundstrasse 109",
    "sg:city":"Luzern",
    "sg:orig_category":"Arbeitnehmerverb\u00e4nde",
    "sg:phone":"+41 41 870 18 02",
    "sg:postcode":"6005",
    "sg:province":"Luzern",
    "wof:name":"Syna - Die Gewerkschaft",
    "wof:placetype":"venue"
},
  "geometry": {"coordinates":[8.639077,46.883224],"type":"Point"}
}