{
  "type": "Feature",
  "properties": {
    "iso:country":"CH",
    "sg:address":"Schwarzenburgstr. 160",
    "sg:city":"Liebefeld",
    "sg:classifiers":[
        {
            "category":"Banks & Credit Unions",
            "subcategory":"Bank",
            "type":"Services"
        }
    ],
    "sg:phone":"+41 31 666 16 00",
    "sg:postcode":"3097",
    "sg:province":"Bern",
    "wof:name":"Berner Kantonalbank (bekb), Real Time Center Ag Bern",
    "wof:placetype":"venue"
},
  "geometry": {"coordinates":[7.420418,46.930927],"type":"Point"}
}