{
  "type": "Feature",
  "properties": {
    "iso:country":"CH",
    "sg:address":"Ettiswilerstrasse 10 6130 Willisau. Postfach",
    "sg:city":"Willisau",
    "sg:orig_category":"Instandhaltung U Reparatur von Automobilen Tankstellen",
    "sg:phone":"+41 41 970 22 44",
    "sg:postcode":"6130",
    "sg:province":"Luzern",
    "wof:name":"Kreuz-garage Willisau Ag",
    "wof:placetype":"venue"
},
  "geometry": {"coordinates":[7.9953999519,47.1245689392],"type":"Point"}
}