{
  "type": "Feature",
  "properties": {
    "iso:country":"CH",
    "sg:address":"Avenue De Morges 24 1000 Lausanne. Postfach",
    "sg:city":"Lausanne",
    "sg:orig_category":"Herstellung von Anstrichmitteln, Druckfarben U Kitten Herstellung von D\u00fcngemitteln U Stickstoffverbi",
    "sg:phone":"+41 71 855 37 44",
    "sg:postcode":"1000",
    "sg:province":"Vaud",
    "wof:name":"Eticoll Gmbh Klebstoffe & Lacke",
    "wof:placetype":"venue"
},
  "geometry": {"coordinates":[9.5094881058,47.4774017334],"type":"Point"}
}