{
  "type": "Feature",
  "properties": {
    "iso:country":"CH",
    "sg:address":"Bachstrasse 2 5623 Boswil. Postfach",
    "sg:city":"Boswil",
    "sg:orig_category":"Zimmerei, Dachdeckerei, Bauspenglerei U Abdichtung",
    "sg:postcode":"5623",
    "sg:province":"Aargau",
    "wof:name":"Elmiger Metallbau",
    "wof:placetype":"venue"
},
  "geometry": {"coordinates":[8.3138818741,47.300994873],"type":"Point"}
}