{
  "type": "Feature",
  "properties": {
    "iso:country":"CH",
    "sg:address":"3983",
    "sg:city":"M\u00f6rel",
    "sg:orig_category":"Fachdetailhandel in Verkaufsr\u00e4umen",
    "sg:postcode":"3983",
    "sg:province":"Valais",
    "wof:name":"Kr\u00fcger Sport, The Ski And Golf Pro-shop.",
    "wof:placetype":"venue"
},
  "geometry": {"coordinates":[8.045340538,46.3555603027],"type":"Point"}
}