{
  "type": "Feature",
  "properties": {
    "iso:country":"CH",
    "sg:address":"Stampfenbachstrasse 52 8006 Z\u00fcrich. Postfach",
    "sg:city":"Z\u00fcrich",
    "sg:orig_category":"Institutionen des Sozialwesens ohne Beherbergung",
    "sg:postcode":"8006",
    "sg:province":"Z\u00fcrich",
    "wof:name":"International Child Foundation Wohlt\u00e4tigkeitsarbeit Zur Pflege, F\u00fcrsorge Usw. Von Bed\u00fcrftigen U. Behinderten Kindern",
    "wof:placetype":"venue"
},
  "geometry": {"coordinates":[8.54271698,47.3808631897],"type":"Point"}
}