{
  "type": "Feature",
  "properties": {
    "iso:country":"CH",
    "sg:address":"Gemeindehausplatz 30",
    "sg:city":"G\u00e4chlingen",
    "sg:classifiers":[
        {
            "category":"Banks & Credit Unions",
            "subcategory":"Bank",
            "type":"Services"
        }
    ],
    "sg:phone":"+41 4153612894",
    "sg:postcode":"8214",
    "sg:province":"Schaffhausen",
    "wof:name":"Spar- U. Leihkasse Neunkirch",
    "wof:placetype":"venue"
},
  "geometry": {"coordinates":[8.49779,47.702171],"type":"Point"}
}