{
  "type": "Feature",
  "properties": {
    "iso:country":"CH",
    "sg:address":"Solothurnerstrasse 3",
    "sg:city":"Olten",
    "sg:orig_category":"Detailhandel mit medizinischen U orthop\u00e4dischen Artikeln Drogerien",
    "sg:phone":"+41 71 911 16 26",
    "sg:postcode":"4600",
    "sg:province":"Solothurn",
    "wof:name":"Maeder Ag Drogerie + Sanit\u00e4tsgesch\u00e4ft",
    "wof:placetype":"venue"
},
  "geometry": {"coordinates":[9.0444450378,47.4624023438],"type":"Point"}
}