{
  "type": "Feature",
  "properties": {
    "iso:country":"CH",
    "sg:address":"Kirchweg 6",
    "sg:city":"Neunkirch",
    "sg:orig_category":"Verlegen von Fliesen U Platten",
    "sg:phone":"+41 52 681 13 06",
    "sg:postcode":"8213",
    "sg:province":"Schaffhausen",
    "wof:name":"Kurt Ochsner Ofenbau & Plattenbel\u00e4ge",
    "wof:placetype":"venue"
},
  "geometry": {"coordinates":[8.4999799728,47.6873893738],"type":"Point"}
}