{
  "type": "Feature",
  "properties": {
    "iso:country":"CH",
    "sg:address":"Bernstrasse 63b",
    "sg:city":"Luzern",
    "sg:orig_category":"Bauschreinerei Herstellung von Konstruktionsteilen, Fertigbauteilen U Ausbauelementen aus Holz",
    "sg:postcode":"6003",
    "sg:province":"Luzern",
    "wof:name":"Gyr Meinrad",
    "wof:placetype":"venue"
},
  "geometry": {"coordinates":[8.283751,47.053017],"type":"Point"}
}