{
  "type": "Feature",
  "properties": {
    "iso:country":"CH",
    "sg:address":"Rue De La Puiserande 9",
    "sg:city":"Gen\u00e8ve",
    "sg:orig_category":"Fachdetailhandel in Verkaufsr\u00e4umen Reparatur von Uhren U Schmuck",
    "sg:phone":"+41 22 329 23 82",
    "sg:postcode":"1205",
    "sg:province":"Gen\u00e8ve",
    "wof:name":"A L'heure Vive, Henry Maystre",
    "wof:placetype":"venue"
},
  "geometry": {"coordinates":[6.1314578056,46.2016792297],"type":"Point"}
}