{
  "type": "Feature",
  "properties": {
    "iso:country":"CH",
    "sg:address":"Haslen 8833 Samstagern. Postfach",
    "sg:city":"Samstagern",
    "sg:orig_category":"Abfallbeseitigung Abwasserreinigung, Abfallbeseitigung U sonstige Entsorgung",
    "sg:phone":"+41 17840216",
    "sg:postcode":"8833",
    "sg:province":"Z\u00fcrich",
    "wof:name":"Hans J\u00f6rg Huber Rohr-& Kanalreinigung",
    "wof:placetype":"venue"
},
  "geometry": {"coordinates":[8.676931,47.192013],"type":"Point"}
}