{
  "type": "Feature",
  "properties": {
    "iso:country":"CH",
    "sg:address":"1666",
    "sg:city":"Grandvillard",
    "sg:orig_category":"Vereine Musik/Blasmusik",
    "sg:postcode":"1666",
    "sg:province":"Fribourg",
    "wof:name":"St\u00e9 De Musique Echo Du Vanil-noir",
    "wof:placetype":"venue"
},
  "geometry": {"coordinates":[7.0855789185,46.5394859314],"type":"Point"}
}