{
  "type": "Feature",
  "properties": {
    "iso:country":"CH",
    "sg:address":"Steinengraben 14",
    "sg:city":"Basel",
    "sg:orig_category":"Unternehmensberatung",
    "sg:postcode":"4051",
    "sg:province":"Basel-Stadt",
    "wof:name":"Human Resource-consulting, M. Gysin",
    "wof:placetype":"venue"
},
  "geometry": {"coordinates":[7.5850729942,47.5546760559],"type":"Point"}
}