{
  "type": "Feature",
  "properties": {
    "iso:country":"CH",
    "sg:address":"Simplon Rue Du 5-7 1207 Gen\u00e8ve. Postfach",
    "sg:city":"Gen\u00e8ve",
    "sg:orig_category":"Detailhandel mit Schuhen U Lederwaren",
    "sg:postcode":"1207",
    "sg:province":"Gen\u00e8ve",
    "wof:name":"Gurtner O.",
    "wof:placetype":"venue"
},
  "geometry": {"coordinates":[6.1577892303,46.2046470642],"type":"Point"}
}