{
  "type": "Feature",
  "properties": {
    "iso:country":"CH",
    "sg:address":"Dorfstrasse 9425 Thal. Postfach",
    "sg:city":"Altenrhein",
    "sg:orig_category":"Non-Classified Establishments",
    "sg:postcode":"9423",
    "sg:province":"St. Gallen",
    "wof:name":"Rinderer E. Pur-tech",
    "wof:placetype":"venue"
},
  "geometry": {"coordinates":[9.5634565353,47.4921302795],"type":"Point"}
}