{
  "type": "Feature",
  "properties": {
    "iso:country":"CH",
    "sg:address":"Im Altried 2 8051 Z\u00fcrich. Postfach",
    "sg:city":"Z\u00fcrich",
    "sg:orig_category":"Softwareentwicklung U beratung",
    "sg:phone":"+41 13201804",
    "sg:postcode":"8051",
    "sg:province":"Z\u00fcrich",
    "wof:name":"Webcall Gmbh",
    "wof:placetype":"venue"
},
  "geometry": {"coordinates":[8.5911140442,47.4053001404],"type":"Point"}
}