{
  "type": "Feature",
  "properties": {
    "iso:country":"CH",
    "sg:address":"Gr\u00fcndenstrasse 5",
    "sg:city":"Flurlingen",
    "sg:orig_category":"Detailhandel mit Waren verschiedener Art, Hauptrichtung Nahrungsmittel",
    "sg:phone":"+41 55 293 58 58",
    "sg:postcode":"8247",
    "sg:province":"Z\u00fcrich",
    "wof:name":"Spar Supermarkt Armin Wyrsch",
    "wof:placetype":"venue"
},
  "geometry": {"coordinates":[9.0054197311,47.19764328],"type":"Point"}
}