{
  "type": "Feature",
  "properties": {
    "iso:country":"CH",
    "sg:address":"Schwantlernegg 16",
    "sg:city":"Gais",
    "sg:orig_category":"Herstellung von Konstruktionsteilen, Fertigbauteilen U Ausbauelementen aus Holz",
    "sg:phone":"+41 71 793 20 30",
    "sg:postcode":"9056",
    "sg:province":"Appenzell Ausserrhoden",
    "wof:name":"Baumberger Peter",
    "wof:placetype":"venue"
},
  "geometry": {"coordinates":[9.4588823318,47.3653488159],"type":"Point"}
}