{
  "type": "Feature",
  "properties": {
    "iso:country":"CH",
    "sg:address":"Hauptstrasse 19 4494 Oltingen. Postfach",
    "sg:city":"Oltingen",
    "sg:orig_category":"Detailhandel mit Fleisch U Fleischwaren",
    "sg:postcode":"4494",
    "sg:province":"Basel-Landschaft",
    "wof:name":"Metzgerei Rickenbacher",
    "wof:placetype":"venue"
},
  "geometry": {"coordinates":[7.9346518517,47.4337501526],"type":"Point"}
}