{
  "type": "Feature",
  "properties": {
    "iso:country":"CH",
    "sg:address":"Bahnhofstrasse 58 7323 Wangs. Postfach",
    "sg:city":"Wangs",
    "sg:orig_category":"Grosshandel mit Obst U Gem\u00fcse Grosshandel mit sonstigen Konsumg\u00fctern",
    "sg:phone":"+41 81 723 37 51",
    "sg:postcode":"7323",
    "sg:province":"St. Gallen",
    "wof:name":"Cash & Carry Angehrn Ag",
    "wof:placetype":"venue"
},
  "geometry": {"coordinates":[9.4330596924,47.0354690552],"type":"Point"}
}