{
  "type": "Feature",
  "properties": {
    "iso:country":"CH",
    "sg:address":"Wyd\u00e4ckerring 148",
    "sg:city":"Z\u00fcrich",
    "sg:orig_category":"Unclassifiable Establishments",
    "sg:postcode":"8047",
    "sg:province":"Z\u00fcrich",
    "wof:name":"Mp Quality Gmbh",
    "wof:placetype":"venue"
},
  "geometry": {"coordinates":[8.4924001694,47.3699913025],"type":"Point"}
}