{
  "type": "Feature",
  "properties": {
    "iso:country":"CH",
    "sg:address":"G\u00fceterstalstrasse 6",
    "sg:city":"Esslingen",
    "sg:orig_category":"Herstellung von Metallkonstruktionen Schlossereien",
    "sg:phone":"+41 79 403 66 12",
    "sg:postcode":"8133",
    "sg:province":"Z\u00fcrich",
    "wof:name":"Hansruedi Baumann Metallbau & Kunstschlosserei",
    "wof:placetype":"venue"
},
  "geometry": {"coordinates":[8.7109460831,47.2894287109],"type":"Point"}
}