{
  "type": "Feature",
  "properties": {
    "iso:country":"CH",
    "sg:address":"Chaumont Chemin De 4",
    "sg:city":"Confignon",
    "sg:orig_category":"Fernmeldedienste",
    "sg:postcode":"1232",
    "sg:province":"Gen\u00e8ve",
    "wof:name":"Arkena Technologies, Guinnard",
    "wof:placetype":"venue"
},
  "geometry": {"coordinates":[6.0849947929,46.1737861633],"type":"Point"}
}