{
  "type": "Feature",
  "properties": {
    "iso:country":"CH",
    "sg:address":"Hauptstrasse 37",
    "sg:city":"H\u00f6chstetten",
    "sg:orig_category":"Elektroinstallation",
    "sg:phone":"+41 34 413 03 02",
    "sg:postcode":"3429",
    "sg:province":"Bern",
    "wof:name":"Kummer Ag Elektro + Telefon",
    "wof:placetype":"venue"
},
  "geometry": {"coordinates":[7.6350140572,47.1429405212],"type":"Point"}
}