{
  "type": "Feature",
  "properties": {
    "iso:country":"CH",
    "sg:address":"Wartenbergstrasse 22",
    "sg:city":"Pratteln",
    "sg:orig_category":"Architektur U Ingenieurb\u00fcros",
    "sg:postcode":"4133",
    "sg:province":"Basel-Landschaft",
    "wof:name":"Enzo Mattana S\u00e0rl",
    "wof:placetype":"venue"
},
  "geometry": {"coordinates":[6.104253,46.149029],"type":"Point"}
}