{
  "type": "Feature",
  "properties": {
    "iso:country":"CH",
    "sg:address":"Waagtalstrasse 12",
    "sg:city":"Unteriberg",
    "sg:orig_category":"Bauschreinerei Herstellung von Konstruktionsteilen, Fertigbauteilen U Ausbauelementen aus Holz",
    "sg:phone":"+41 55 414 11 74",
    "sg:postcode":"8842",
    "sg:province":"Schwyz",
    "wof:name":"Holdener Marcel",
    "wof:placetype":"venue"
},
  "geometry": {"coordinates":[8.801356,47.058491],"type":"Point"}
}