{
  "type": "Feature",
  "properties": {
    "iso:country":"CH",
    "sg:address":"Girizstr. 52 + 54",
    "sg:city":"Biberist",
    "sg:orig_category":"Herstellung von Platten, Folien, Schl\u00e4uchen U Profilen aus Kunststoff",
    "sg:phone":"+41 32 672 45 45",
    "sg:postcode":"4562",
    "sg:province":"Solothurn",
    "wof:name":"Ingold-plastic",
    "wof:placetype":"venue"
},
  "geometry": {"coordinates":[7.5709991455,47.1876602173],"type":"Point"}
}