{
  "type": "Feature",
  "properties": {
    "addr:full":"Sonnenhofstrasse 19 Hinwil Z\u00fcrich 8340",
    "addr:housenumber":"19",
    "addr:postcode":"8340",
    "addr:street":"Sonnenhofstrasse",
    "iso:country":"CH",
    "sg:address":"Sonnenhofstrasse 19",
    "sg:city":"Hinwil",
    "sg:orig_category":"Arztpraxen",
    "sg:phone":"+41 19374281",
    "sg:postcode":"8340",
    "sg:province":"Z\u00fcrich",
    "wof:name":"Dr.med.urs Bernhart Arzt F.allgemeine Medizin Fmh",
    "wof:placetype":"venue"
},
  "geometry": {"coordinates":[8.84324,47.29776],"type":"Point"}
}