{
  "type": "Feature",
  "properties": {
    "iso:country":"CH",
    "sg:address":"Tannenstrasse 97",
    "sg:city":"Embrach",
    "sg:orig_category":"Mechanik Schlossereien",
    "sg:phone":"+41 19752826",
    "sg:postcode":"8424",
    "sg:province":"Z\u00fcrich",
    "wof:name":"Millennium Racing Gmbh",
    "wof:placetype":"venue"
},
  "geometry": {"coordinates":[8.7504301071,47.305065155],"type":"Point"}
}