{
  "type": "Feature",
  "properties": {
    "iso:country":"CH",
    "sg:address":"Seestrasse 54",
    "sg:city":"Thalwil",
    "sg:orig_category":"Schwimmb\u00e4der",
    "sg:phone":"+41 17200260",
    "sg:postcode":"8800",
    "sg:province":"Z\u00fcrich",
    "wof:name":"Strandbad B\u00fcrger",
    "wof:placetype":"venue"
},
  "geometry": {"coordinates":[8.5750799179,47.2874145508],"type":"Point"}
}