{
  "type": "Feature",
  "properties": {
    "iso:country":"CH",
    "sg:address":"Communance 165",
    "sg:city":"Montfaucon",
    "sg:orig_category":"Instandhaltung U Reparatur von Automobilen",
    "sg:postcode":"2875",
    "sg:province":"Jura",
    "wof:name":"Cattin Automobiles",
    "wof:placetype":"venue"
},
  "geometry": {"coordinates":[7.0441231728,47.2780685425],"type":"Point"}
}