{
  "type": "Feature",
  "properties": {
    "iso:country":"CH",
    "sg:address":"Am Bahndamm 38",
    "sg:city":"Basel",
    "sg:orig_category":"Institutionen f\u00fcr Behinderte Sonderschulen",
    "sg:phone":"+41 61 681 90 42",
    "sg:postcode":"4058",
    "sg:province":"Basel-Stadt",
    "wof:name":"R\u00e4geboge Tagesschulheim F\u00fcr Mehrfach Behinderte Kinder",
    "wof:placetype":"venue"
},
  "geometry": {"coordinates":[7.6076631546,47.5722846985],"type":"Point"}
}