{
  "type": "Feature",
  "properties": {
    "addr:full":"Luzernerstrasse 45b Zofingen Aargau 4800",
    "addr:housenumber":"45b",
    "addr:postcode":"4800",
    "addr:street":"Luzernerstrasse",
    "iso:country":"CH",
    "sg:address":"Luzernerstrasse 45b",
    "sg:city":"Zofingen",
    "sg:orig_category":"Dachdeckerei Zimmerei, Dachdeckerei, Bauspenglerei U Abdichtung",
    "sg:phone":"+41 62 751 23 29",
    "sg:postcode":"4800",
    "sg:province":"Aargau",
    "wof:name":"Heiniger Hans, Nachfolger Tschanz G.",
    "wof:placetype":"venue"
},
  "geometry": {"coordinates":[7.95128,47.279629],"type":"Point"}
}