{
  "type": "Feature",
  "properties": {
    "iso:country":"CH",
    "sg:address":"Kornfeldstrasse 13a",
    "sg:city":"Steinach",
    "sg:orig_category":"Softwareentwicklung U beratung",
    "sg:phone":"+41 19911241",
    "sg:postcode":"9323",
    "sg:province":"St. Gallen",
    "wof:name":"Kobler Information Engineering",
    "wof:placetype":"venue"
},
  "geometry": {"coordinates":[8.5992689133,47.3224983215],"type":"Point"}
}