{
  "type": "Feature",
  "properties": {
    "iso:country":"CH",
    "sg:address":"Wynigenstrasse 4 3400 Burgdorf. Postfach",
    "sg:city":"Burgdorf",
    "sg:orig_category":"Gesundheitswesen Herstellung von medizinischen U chirurgischen Ger\u00e4ten",
    "sg:phone":"+41 34 424 03 20",
    "sg:postcode":"3402",
    "sg:province":"Bern",
    "wof:name":"Mds Medical Device Solutions Ag",
    "wof:placetype":"venue"
},
  "geometry": {"coordinates":[7.631082058,47.059211731],"type":"Point"}
}