{
  "type": "Feature",
  "properties": {
    "addr:full":"Bourg-st-bernard 1946 Bourg-st-pierre. Postfach Bourg-st-pierre Valais 1946",
    "addr:housenumber":"1946",
    "addr:postcode":"1946",
    "addr:street":"Bourg-St-Pierre. Postfach Bourg-St-Pierre",
    "iso:country":"CH",
    "sg:address":"Bourg-st-bernard 1946 Bourg-st-pierre. Postfach",
    "sg:city":"Bourg-st-pierre",
    "sg:orig_category":"Allgemeiner Hoch U Tiefbau",
    "sg:phone":"+41 27 787 12 06",
    "sg:postcode":"1946",
    "sg:province":"Valais",
    "wof:name":"Soci\u00e9t\u00e9 Italo-suisse D'exploitation Du Tunnel Du Grand-st-bernard Sa",
    "wof:placetype":"venue"
},
  "geometry": {"coordinates":[7.195489,45.90173],"type":"Point"}
}