{
  "type": "Feature",
  "properties": {
    "iso:country":"CH",
    "sg:address":"La R\u00e9sidence 3963 Crans-sur-sierre. Postfach",
    "sg:city":"Crans-sur-sierre",
    "sg:orig_category":"Unclassifiable Establishments",
    "sg:postcode":"3963",
    "sg:province":"Valais",
    "wof:name":"Si Mikelina",
    "wof:placetype":"venue"
},
  "geometry": {"coordinates":[7.5370411873,46.2938270569],"type":"Point"}
}