{
  "type": "Feature",
  "properties": {
    "iso:country":"CH",
    "sg:address":"Via Beato Berno",
    "sg:city":"Ascona",
    "sg:orig_category":"Kunsthandel",
    "sg:phone":"+41 91 791 36 45",
    "sg:postcode":"6612",
    "sg:province":"Ticino",
    "wof:name":"Galleria Borgo Josef F.w\u00fcest",
    "wof:placetype":"venue"
},
  "geometry": {"coordinates":[8.7682552338,46.1547088623],"type":"Point"}
}