{
  "type": "Feature",
  "properties": {
    "iso:country":"CH",
    "sg:address":"Feldmatt 1",
    "sg:city":"Unterkulm",
    "sg:orig_category":"Unclassifiable Establishments",
    "sg:postcode":"5726",
    "sg:province":"Aargau",
    "wof:name":"Itc R\u00e4tzer Gmbh",
    "wof:placetype":"venue"
},
  "geometry": {"coordinates":[8.1132097244,47.3264045715],"type":"Point"}
}