{
  "type": "Feature",
  "properties": {
    "iso:country":"CH",
    "sg:address":"Weststrasse 24 7000 Chur. Postfach 60",
    "sg:city":"Chur",
    "sg:orig_category":"Sanit\u00e4r U Heizungsinstallation Sanit\u00e4r, Heizungs U L\u00fcftungsinstallation",
    "sg:phone":"+41 22 361 16 52",
    "sg:postcode":"7007",
    "sg:province":"Graubunden",
    "wof:name":"Gilbert Brunschwyler Sa Chauffage Central",
    "wof:placetype":"venue"
},
  "geometry": {"coordinates":[6.2151331902,46.3819084167],"type":"Point"}
}