{
  "type": "Feature",
  "properties": {
    "iso:country":"CH",
    "sg:address":"Gossauerstrasse 14",
    "sg:city":"Hinwil",
    "sg:orig_category":"Erbringung von Dienstleistungen f\u00fcr Unternehmen",
    "sg:phone":"+41 19380466",
    "sg:postcode":"8340",
    "sg:province":"Z\u00fcrich",
    "wof:name":"Move Planung & Design Kunz",
    "wof:placetype":"venue"
},
  "geometry": {"coordinates":[8.837884903,47.2992172241],"type":"Point"}
}