{
  "type": "Feature",
  "properties": {
    "iso:country":"CH",
    "sg:address":"Steinengraben 22",
    "sg:city":"Basel",
    "sg:orig_category":"Detailhandel mit Brot, Back U S\u00fcsswaren",
    "sg:postcode":"4051",
    "sg:province":"Basel-Stadt",
    "wof:name":"Fatocom Ag",
    "wof:placetype":"venue"
},
  "geometry": {"coordinates":[7.585325,47.554218],"type":"Point"}
}