{
  "type": "Feature",
  "properties": {
    "iso:country":"CH",
    "sg:address":"Pfadweid",
    "sg:city":"Cham",
    "sg:orig_category":"Sonstige mit der Informatik verbundene T\u00e4tigkeiten",
    "sg:postcode":"6330",
    "sg:province":"Zug",
    "wof:name":"Gcp Beratungen Ag",
    "wof:placetype":"venue"
},
  "geometry": {"coordinates":[8.4521102905,47.1984634399],"type":"Point"}
}