{
  "type": "Feature",
  "properties": {
    "iso:country":"CH",
    "sg:address":"Karl Stauffer-strasse 11",
    "sg:city":"Z\u00fcrich",
    "sg:orig_category":"Erschliessung von Grundst\u00fccken",
    "sg:phone":"+41 14225033",
    "sg:postcode":"8008",
    "sg:province":"Z\u00fcrich",
    "wof:name":"Gemeinn\u00fctzige Baugenossenschaft Burgmatte",
    "wof:placetype":"venue"
},
  "geometry": {"coordinates":[8.5721931458,47.3561973572],"type":"Point"}
}