{
  "type": "Feature",
  "properties": {
    "addr:full":"Obere Halde 9 Oberschan St. Gallen 9479",
    "addr:housenumber":"9;st.",
    "addr:postcode":"9479",
    "addr:street":"Obere Halde",
    "iso:country":"CH",
    "sg:address":"Obere Halde 9",
    "sg:city":"Oberschan",
    "sg:classifiers":[
        {
            "category":"Structure",
            "subcategory":"Warehouse",
            "type":"Public Place"
        }
    ],
    "sg:phone":"+41 81 740 23 15",
    "sg:postcode":"9479",
    "sg:province":"St. Gallen",
    "sg:tags":[
        "air-conditioning",
        "system"
    ],
    "wof:name":"Bordin Energy Components Gmbh",
    "wof:placetype":"venue"
},
  "geometry": {"coordinates":[9.471125,47.101322],"type":"Point"}
}