{
  "type": "Feature",
  "properties": {
    "iso:country":"CH",
    "sg:address":"Sch\u00fctzenweg 6",
    "sg:city":"Zuchwil",
    "sg:orig_category":"Instandhaltung U Reparatur von Automobilen",
    "sg:phone":"+41 79 422 68 67",
    "sg:postcode":"4528",
    "sg:province":"Solothurn",
    "wof:name":"Carrosserie Hug",
    "wof:placetype":"venue"
},
  "geometry": {"coordinates":[7.5712828636,47.2008476257],"type":"Point"}
}