{
  "type": "Feature",
  "properties": {
    "iso:country":"CH",
    "sg:address":"Via Lococoste 27",
    "sg:city":"Gordola",
    "sg:orig_category":"Architektur U Ingenieurb\u00fcros",
    "sg:phone":"+41 91 745 37 88",
    "sg:postcode":"6596",
    "sg:province":"Ticino",
    "wof:name":"Togni Energie Gmbh Energie, Haustechnik, Bau, Verkehr U \u00d6kologie Usw; Beratung U. Planung",
    "wof:placetype":"venue"
},
  "geometry": {"coordinates":[8.85874,46.185822],"type":"Point"}
}