{
  "type": "Feature",
  "properties": {
    "iso:country":"CH",
    "sg:address":"Chriesbaumweidstrasse 3",
    "sg:city":"Fehraltorf",
    "sg:orig_category":"Dachdeckerei",
    "sg:phone":"+41 19541630",
    "sg:postcode":"8320",
    "sg:province":"Z\u00fcrich",
    "wof:name":"Jakob B\u00fchrer Bedachungen",
    "wof:placetype":"venue"
},
  "geometry": {"coordinates":[8.759495,47.394135],"type":"Point"}
}