{
  "type": "Feature",
  "properties": {
    "iso:country":"CH",
    "sg:address":"Unter-kapf 10 6020 Emmenbr\u00fccke. Postfach",
    "sg:city":"Emmenbr\u00fccke",
    "sg:orig_category":"Sonstiger Grosshandel",
    "sg:postcode":"6020",
    "sg:province":"Luzern",
    "wof:name":"Global Systems Claudio Gubitosa",
    "wof:placetype":"venue"
},
  "geometry": {"coordinates":[8.2777175903,47.091091156],"type":"Point"}
}