{
  "type": "Feature",
  "properties": {
    "iso:country":"CH",
    "sg:address":"Du-roveray Rue 12 1207 Gen\u00e8ve. Postfach",
    "sg:city":"Gen\u00e8ve",
    "sg:orig_category":"Werbung",
    "sg:postcode":"1207",
    "sg:province":"Gen\u00e8ve",
    "wof:name":"Emc Elite Media & Communications Ltd, Londres, Succursale De Gen\u00e8ve",
    "wof:placetype":"venue"
},
  "geometry": {"coordinates":[6.1587848663,46.2052955627],"type":"Point"}
}