{
  "type": "Feature",
  "properties": {
    "iso:country":"CH",
    "sg:address":"Ramuz Avenue C.-f.- 43",
    "sg:city":"Pully",
    "sg:orig_category":"Vermietung U Verpachtung von eigenen Immobilien",
    "sg:phone":"+41 22 885 96 61",
    "sg:postcode":"1009",
    "sg:province":"Vaud",
    "wof:name":"Lago Bat Sa",
    "wof:placetype":"venue"
},
  "geometry": {"coordinates":[6.1420788765,46.1867980957],"type":"Point"}
}