{
  "type": "Feature",
  "properties": {
    "iso:country":"CH",
    "sg:address":"K\u00e4sereistrasse 1",
    "sg:city":"Wigoltingen",
    "sg:orig_category":"Detailhandel mit Milcherzeugnissen U Eiern Verarbeitung von Milch",
    "sg:phone":"+41 52 763 15 72",
    "sg:postcode":"8556",
    "sg:province":"Thurgau",
    "wof:name":"Walter Sturzenegger K\u00e4serei",
    "wof:placetype":"venue"
},
  "geometry": {"coordinates":[9.0311870575,47.5972442627],"type":"Point"}
}