{
  "type": "Feature",
  "properties": {
    "iso:country":"CH",
    "sg:address":"9320 Arbon. Postfach 167",
    "sg:city":"Arbon",
    "sg:orig_category":"Vereine Geselligkeit",
    "sg:postcode":"9320",
    "sg:province":"Thurgau",
    "wof:name":"Oesterreicher-verein",
    "wof:placetype":"venue"
},
  "geometry": {"coordinates":[9.4349451065,47.5160446167],"type":"Point"}
}