{
  "type": "Feature",
  "properties": {
    "iso:country":"CH",
    "sg:address":"Uetlibergstrasse 93",
    "sg:city":"Z\u00fcrich",
    "sg:orig_category":"Grosshandel mit Holz U Baustoffen",
    "sg:phone":"+41 14622464",
    "sg:postcode":"8045",
    "sg:province":"Z\u00fcrich",
    "wof:name":"Hg Commerciale Handelsgen. Des Schweiz. Baumeisterverband",
    "wof:placetype":"venue"
},
  "geometry": {"coordinates":[8.5188560486,47.3615074158],"type":"Point"}
}