{
  "type": "Feature",
  "properties": {
    "iso:country":"CH",
    "sg:address":"Ipsachstrasse 10",
    "sg:city":"Nidau",
    "sg:orig_category":"Elektroinstallation",
    "sg:phone":"+41 32 331 33 11",
    "sg:postcode":"2560",
    "sg:province":"Bern",
    "wof:name":"Baumann Elektroinstallationen Gmbh",
    "wof:placetype":"venue"
},
  "geometry": {"coordinates":[7.2376389503,47.1175041199],"type":"Point"}
}