{
  "type": "Feature",
  "properties": {
    "iso:country":"CH",
    "sg:address":"Dammweg 8 5000 Aarau. Postfach 3543",
    "sg:city":"Aarau",
    "sg:orig_category":"Grosshandel mit chemischen Erzeugnissen Grosshandel mit elektrischen Haushaltsger\u00e4ten",
    "sg:phone":"+41 61 487 87 87",
    "sg:postcode":"5001",
    "sg:province":"Aargau",
    "wof:name":"Reka-reinigungstechnik Ag",
    "wof:placetype":"venue"
},
  "geometry": {"coordinates":[7.5458350182,47.5580291748],"type":"Point"}
}