{
  "type": "Feature",
  "properties": {
    "iso:country":"CH",
    "sg:address":"Honegg",
    "sg:city":"Uebeschi",
    "sg:orig_category":"Vereine Musik/Blasmusik",
    "sg:phone":"+41 33 345 10 93",
    "sg:postcode":"3635",
    "sg:province":"Bern",
    "wof:name":"Musikgesellschaft Blumenstein",
    "wof:placetype":"venue"
},
  "geometry": {"coordinates":[7.5328359604,46.739654541],"type":"Point"}
}