{
  "type": "Feature",
  "properties": {
    "iso:country":"CH",
    "sg:address":"Untere Steingrubenstrasse 19 4500 Solothurn. Postfach",
    "sg:city":"Solothurn",
    "sg:orig_category":"Fotografische Ateliers Fotografisches Gewerbe U fotografische Laboratorien",
    "sg:phone":"+41 32 623 33 41",
    "sg:postcode":"4504",
    "wof:name":"Fotoatelier Hegner Pascal",
    "wof:placetype":"venue"
},
  "geometry": {"coordinates":[7.5350971222,47.211566925],"type":"Point"}
}