{
  "type": "Feature",
  "properties": {
    "addr:full":"Vordere Gasse 22 Kerzers Fribourg 3210",
    "addr:housenumber":"22",
    "addr:postcode":"3210",
    "addr:street":"Vordere Gasse",
    "iso:country":"CH",
    "sg:address":"Vordere Gasse 22",
    "sg:city":"Kerzers",
    "sg:orig_category":"Detailhandel mit Brot, Back U S\u00fcsswaren",
    "sg:phone":"+41 31 755 53 52",
    "sg:postcode":"3210",
    "sg:province":"Fribourg",
    "wof:name":"Kr\u00e4henb\u00fchl Franz.",
    "wof:placetype":"venue"
},
  "geometry": {"coordinates":[7.199659,46.974133],"type":"Point"}
}