{
  "type": "Feature",
  "properties": {
    "iso:country":"CH",
    "sg:address":"Rohrstrasse 9",
    "sg:city":"Engelberg",
    "sg:orig_category":"Druckguss-Werke",
    "sg:postcode":"6390",
    "sg:province":"Obwalden",
    "wof:name":"Fischer Rolf Ag",
    "wof:placetype":"venue"
},
  "geometry": {"coordinates":[8.4015951157,46.8176383972],"type":"Point"}
}