{
  "type": "Feature",
  "properties": {
    "iso:country":"CH",
    "sg:address":"Spitalstrasse 72",
    "sg:city":"Schlieren",
    "sg:orig_category":"Rolladen- and Storenmontage",
    "sg:phone":"+41 17307466",
    "sg:postcode":"8952",
    "sg:province":"Z\u00fcrich",
    "wof:name":"Sveta & Draqica Marjanovic Storenbau",
    "wof:placetype":"venue"
},
  "geometry": {"coordinates":[8.4264993668,47.3957824707],"type":"Point"}
}