{
  "type": "Feature",
  "properties": {
    "iso:country":"CH",
    "sg:address":"Storchengasse 1 6430 Schwyz. Postfach 419",
    "sg:city":"Schwyz",
    "sg:orig_category":"Elektroinstallation",
    "sg:phone":"+41 41 810 00 73",
    "sg:postcode":"6431",
    "sg:province":"Schwyz",
    "wof:name":"Elektroplanung Arnold Daniel",
    "wof:placetype":"venue"
},
  "geometry": {"coordinates":[8.6503295898,47.0214538574],"type":"Point"}
}