{
  "type": "Feature",
  "properties": {
    "iso:country":"CH",
    "sg:address":"Kleeg\u00e4rtenstrasse 7",
    "sg:city":"Visp",
    "sg:orig_category":"Herstellung von keramischen Wand U Bodenfliesen U platten Verlegen von Fliesen U Platten",
    "sg:phone":"+41 79 628 59 78",
    "sg:postcode":"3930",
    "sg:province":"Valais",
    "wof:name":"Bellwald Franco",
    "wof:placetype":"venue"
},
  "geometry": {"coordinates":[7.8812251091,46.2951622009],"type":"Point"}
}