{
  "type": "Feature",
  "properties": {
    "iso:country":"CH",
    "sg:address":"Auenstrasse 15",
    "sg:city":"Widnau",
    "sg:orig_category":"Schreibb\u00fcros",
    "sg:phone":"+41 71 722 96 16",
    "sg:postcode":"9443",
    "sg:province":"St. Gallen",
    "wof:name":"B\u00fcroservice Sperlich",
    "wof:placetype":"venue"
},
  "geometry": {"coordinates":[9.6420955658,47.4008255005],"type":"Point"}
}