{
  "type": "Feature",
  "properties": {
    "iso:country":"CH",
    "sg:address":"Diechtersmattstrasse 4",
    "sg:city":"Giswil",
    "sg:orig_category":"Non-Classified Establishments",
    "sg:phone":"+41 79 218 53 53",
    "sg:postcode":"6074",
    "sg:province":"Obwalden",
    "wof:name":"Taxi Toni Gmbh",
    "wof:placetype":"venue"
},
  "geometry": {"coordinates":[8.1873607635,46.8385047913],"type":"Point"}
}