{
  "type": "Feature",
  "properties": {
    "iso:country":"CH",
    "sg:address":"Sonnmattstrasse",
    "sg:city":"Baden",
    "sg:orig_category":"Vorschulen, Kinderg\u00e4rten",
    "sg:phone":"+41 56 222 11 75",
    "sg:postcode":"5400",
    "sg:province":"Aargau",
    "wof:name":"Kindergarten Sonnmatt",
    "wof:placetype":"venue"
},
  "geometry": {"coordinates":[8.2973966599,47.4693412781],"type":"Point"}
}