{
  "type": "Feature",
  "properties": {
    "iso:country":"CH",
    "sg:address":"Hofmatt 5",
    "sg:city":"Oberrohrdorf",
    "sg:orig_category":"Wirtschaftspr\u00fcfung, Steuerberatung U Treuhand",
    "sg:phone":"+41 56 496 26 57",
    "sg:postcode":"5452",
    "sg:province":"Aargau",
    "wof:name":"Hans Zemp",
    "wof:placetype":"venue"
},
  "geometry": {"coordinates":[8.3143901825,47.4196586609],"type":"Point"}
}