{
  "type": "Feature",
  "properties": {
    "iso:country":"CH",
    "sg:address":"Unterm\u00fcli 6 6300 Zug. Postfach",
    "sg:city":"Zug",
    "sg:orig_category":"Finanzierungsinstitutionen",
    "sg:postcode":"6300",
    "sg:province":"Zug",
    "wof:name":"J.p. Invest Ag Investitionen Im Ber. Konsumg\u00fcter, Bes. Im Handel Und In Der Produktion Von Videokassetten Und Filmen Usw",
    "wof:placetype":"venue"
},
  "geometry": {"coordinates":[8.5216379166,47.167224884],"type":"Point"}
}