{
  "type": "Feature",
  "properties": {
    "iso:country":"CH",
    "sg:address":"Altmannsteinstrasse 20",
    "sg:city":"H\u00f6ri",
    "sg:orig_category":"Herstellung von Metallkonstruktionen Schlossereien",
    "sg:phone":"+41 18602008",
    "sg:postcode":"8181",
    "sg:province":"Z\u00fcrich",
    "wof:name":"Peter Hiltebrand Kunstschlosserei & Metallbau",
    "wof:placetype":"venue"
},
  "geometry": {"coordinates":[8.5148153305,47.5103721619],"type":"Point"}
}