{
  "type": "Feature",
  "properties": {
    "iso:country":"CH",
    "sg:address":"B\u00fcntenstrasse 29",
    "sg:city":"W\u00fcrenlos",
    "sg:orig_category":"Detailhandel mit Schuhen U Lederwaren",
    "sg:phone":"+41 56 424 30 27",
    "sg:postcode":"5436",
    "sg:province":"Aargau",
    "wof:name":"Sadecky Thomas Lic.oec. Hsg, Trend & Trade",
    "wof:placetype":"venue"
},
  "geometry": {"coordinates":[8.3703250885,47.4437446594],"type":"Point"}
}