{
  "type": "Feature",
  "properties": {
    "iso:country":"CH",
    "sg:address":"Z\u00fcrcherstrasse 67 8500 Frauenfeld. Postfach 2169",
    "sg:city":"Frauenfeld",
    "sg:orig_category":"Zahnarztpraxen",
    "sg:phone":"+41 52 720 23 00",
    "sg:postcode":"8502",
    "sg:province":"Thurgau",
    "wof:name":"Dr.med.dent.jacqueline Seydoux Zahn\u00e4rztin",
    "wof:placetype":"venue"
},
  "geometry": {"coordinates":[8.8846759796,47.5525627136],"type":"Point"}
}