{
  "type": "Feature",
  "properties": {
    "iso:country":"CH",
    "sg:address":"Hochb\u00fchlstrasse 6 6003 Luzern. Postfach",
    "sg:city":"Luzern",
    "sg:orig_category":"Wirtschaftspr\u00fcfung, Steuerberatung U Treuhand",
    "sg:phone":"+41 41 240 26 44",
    "sg:postcode":"6003",
    "sg:province":"Luzern",
    "wof:name":"Gloggner Ren\u00e9 X. Treuhand- & Verwaltungsb\u00fcro Treuhand, Verwaltungsb\u00fcro, Bes. Schatzungen, Expertisen Usw",
    "wof:placetype":"venue"
},
  "geometry": {"coordinates":[8.2992677689,47.0493469238],"type":"Point"}
}