{
  "type": "Feature",
  "properties": {
    "iso:country":"CH",
    "sg:address":"Grundstrasse 8",
    "sg:city":"Schwyz",
    "sg:orig_category":"RESTAURANTS: TEA-ROOMS",
    "sg:phone":"+41 41 811 18 60",
    "sg:postcode":"6430",
    "sg:province":"Schwyz",
    "wof:name":"Restaurant Krone, Silvia Stampfli",
    "wof:placetype":"venue"
},
  "geometry": {"coordinates":[8.6576595306,47.0196113586],"type":"Point"}
}