{
  "type": "Feature",
  "properties": {
    "iso:country":"CH",
    "sg:address":"Weidstrasse 93",
    "sg:city":"Jonen",
    "sg:orig_category":"Jugendorganisationen",
    "sg:phone":"+41 56 634 13 71",
    "sg:postcode":"8916",
    "sg:province":"Aargau",
    "wof:name":"Jugendriege Jonen",
    "wof:placetype":"venue"
},
  "geometry": {"coordinates":[8.39432621,47.2934608459],"type":"Point"}
}