{
  "type": "Feature",
  "properties": {
    "iso:country":"CH",
    "sg:address":"Rue Micheli-du-crest 11",
    "sg:city":"Gen\u00e8ve",
    "sg:orig_category":"Detailhandel mit Schuhen",
    "sg:phone":"+41 22 329 80 20",
    "sg:postcode":"1205",
    "sg:province":"Gen\u00e8ve",
    "wof:name":"Chaussures Charles-antonio",
    "wof:placetype":"venue"
},
  "geometry": {"coordinates":[6.1471071243,46.1953277588],"type":"Point"}
}