{
  "type": "Feature",
  "properties": {
    "iso:country":"CH",
    "sg:address":"Rue Abram-louis-breguet 13 2000 Neuenburg. Postfach",
    "sg:city":"Neuenburg",
    "sg:orig_category":"RESTAURANTS: TEA-ROOMS",
    "sg:postcode":"2000",
    "sg:province":"Neuch\u00e2tel",
    "wof:name":"Suky-bar, Roussey S.",
    "wof:placetype":"venue"
},
  "geometry": {"coordinates":[6.9428420067,46.994644165],"type":"Point"}
}