{
  "type": "Feature",
  "properties": {
    "iso:country":"CH",
    "sg:address":"Blessoney Chemin Du 12d 1092 Belmont-lausanne. Postfach",
    "sg:city":"Belmont-lausanne",
    "sg:orig_category":"Handels-H\u00e4user U Gesellschaften",
    "sg:phone":"+41 55 280 28 03",
    "sg:postcode":"1092",
    "sg:province":"Vaud",
    "wof:name":"Groupe Cofinim Sa Op\u00e9rations Commerciales, Immobili\u00e8res, Financi\u00e8res Etc",
    "wof:placetype":"venue"
},
  "geometry": {"coordinates":[6.6782422066,46.519859314],"type":"Point"}
}