{
  "type": "Feature",
  "properties": {
    "iso:country":"CH",
    "sg:address":"Moosweg 6",
    "sg:city":"Guettingen",
    "sg:classifiers":[
        {
            "category":"Professional",
            "subcategory":"Engineering",
            "type":"Services"
        }
    ],
    "sg:phone":"+41 71 695 16 16",
    "sg:postcode":"8594",
    "sg:province":"Thurgau",
    "sg:tags":[
        "machine",
        "-",
        "mechanical"
    ],
    "wof:name":"H Eberli Ag",
    "wof:placetype":"venue"
},
  "geometry": {"coordinates":[9.3012046814,47.603729248],"type":"Point"}
}