{
  "type": "Feature",
  "properties": {
    "iso:country":"CH",
    "sg:address":"Rue De L'avenir 33",
    "sg:city":"Del\u00e9mont",
    "sg:orig_category":"Kaufm\u00e4nnische Berufsschulen",
    "sg:phone":"+41 26 919 66 00",
    "sg:postcode":"2800",
    "sg:province":"Jura",
    "wof:name":"Ecole Professionnelle Artisanale & Commerciale",
    "wof:placetype":"venue"
},
  "geometry": {"coordinates":[7.0570578575,46.627204895],"type":"Point"}
}