{
  "type": "Feature",
  "properties": {
    "iso:country":"CH",
    "sg:address":"Route De Ch\u00eane 67",
    "sg:city":"Gen\u00e8ve",
    "sg:orig_category":"Detailhandel mit Fleisch U Fleischwaren",
    "sg:phone":"+41 19100345",
    "sg:postcode":"1208",
    "sg:province":"Gen\u00e8ve",
    "wof:name":"Robert Ledermann Metzgerei Erlenhof",
    "wof:placetype":"venue"
},
  "geometry": {"coordinates":[8.5907688141,47.3033943176],"type":"Point"}
}