{
  "type": "Feature",
  "properties": {
    "iso:country":"CH",
    "sg:address":"Schlossberg 21",
    "sg:city":"Zuckenriet",
    "sg:orig_category":"Tierarztpraxis",
    "sg:phone":"+41 71 377 19 19",
    "sg:postcode":"9526",
    "sg:province":"St. Gallen",
    "wof:name":"Dr. Med. Vet. Emil Amacker Tierarzt",
    "wof:placetype":"venue"
},
  "geometry": {"coordinates":[9.1735639572,47.3181304932],"type":"Point"}
}