{
  "type": "Feature",
  "properties": {
    "addr:full":"Strehlgasse 32 D\u00fcbendorf Z\u00fcrich 8600",
    "addr:housenumber":"32",
    "addr:postcode":"8600",
    "addr:street":"Strehlgasse",
    "iso:country":"CH",
    "sg:address":"Strehlgasse 32",
    "sg:city":"D\u00fcbendorf",
    "sg:orig_category":"Bauingenieurb\u00fcros allgemein",
    "sg:phone":"+41 32 861 38 28",
    "sg:postcode":"8600",
    "sg:province":"Z\u00fcrich",
    "wof:name":"Pascal Stirnemann Bureau D'ing\u00e9nieur",
    "wof:placetype":"venue"
},
  "geometry": {"coordinates":[6.615056,46.906441],"type":"Point"}
}