{
  "type": "Feature",
  "properties": {
    "addr:full":"General Guisan-strasse 151 Basel Basel-Stadt 4054",
    "addr:housenumber":"151",
    "addr:postcode":"4054",
    "addr:street":"General Guisan-Strasse",
    "iso:country":"CH",
    "sg:address":"General Guisan-strasse 151",
    "sg:city":"Basel",
    "sg:orig_category":"Allgemeiner Hoch U Tiefbau",
    "sg:phone":"+41 61 301 29 00",
    "sg:postcode":"4054",
    "sg:province":"Basel-Stadt",
    "wof:name":"Riag Bau Ag",
    "wof:placetype":"venue"
},
  "geometry": {"coordinates":[7.561765,47.548725],"type":"Point"}
}