{
  "type": "Feature",
  "properties": {
    "iso:country":"CH",
    "sg:address":"Seeli",
    "sg:city":"Tafers",
    "sg:orig_category":"Malerei",
    "sg:phone":"+41 17616592",
    "sg:postcode":"1712",
    "sg:province":"Fribourg",
    "wof:name":"Josef Vogler Malergesch\u00e4ft",
    "wof:placetype":"venue"
},
  "geometry": {"coordinates":[8.4852666855,47.265460968],"type":"Point"}
}