{
  "type": "Feature",
  "properties": {
    "iso:country":"CH",
    "sg:address":"Moillebeau Rue De 52 1209 Gen\u00e8ve Case Postale 162",
    "sg:city":"Gen\u00e8ve",
    "sg:orig_category":"Handelsvermittlung von Brennstoffen, Erzen, Metallen U Chemikalien",
    "sg:postcode":"1209",
    "sg:province":"Gen\u00e8ve",
    "wof:name":"Napac Biotechnology",
    "wof:placetype":"venue"
},
  "geometry": {"coordinates":[9.4182739258,47.4463195801],"type":"Point"}
}