{
  "type": "Feature",
  "properties": {
    "iso:country":"CH",
    "sg:address":"Gober",
    "sg:city":"Doppleschwand",
    "sg:orig_category":"Verwertung von Milch",
    "sg:postcode":"6112",
    "sg:province":"Luzern",
    "wof:name":"K\u00e4sereigenossenschaft Dorf Doppleschwand",
    "wof:placetype":"venue"
},
  "geometry": {"coordinates":[8.0410814285,47.0109786987],"type":"Point"}
}