{
  "type": "Feature",
  "properties": {
    "iso:country":"CH",
    "sg:address":"Boulevard De P\u00e9rolles 7 1700 Fribourg. Postfach",
    "sg:city":"Fribourg",
    "sg:orig_category":"Datenverarbeitungsdienste",
    "sg:phone":"+41 26 322 01 33",
    "sg:postcode":"1701",
    "sg:province":"Fribourg",
    "wof:name":"Telindus Sa Transmission De Donn\u00e9es",
    "wof:placetype":"venue"
},
  "geometry": {"coordinates":[7.151737,46.801235],"type":"Point"}
}