{
  "type": "Feature",
  "properties": {
    "iso:country":"CH",
    "sg:address":"Via Canonica",
    "sg:city":"Tesserete",
    "sg:orig_category":"Architekturb\u00fcros",
    "sg:phone":"+41 91 943 46 07",
    "sg:postcode":"6950",
    "sg:province":"Ticino",
    "wof:name":"Claudio Morandi Studio D'architettura",
    "wof:placetype":"venue"
},
  "geometry": {"coordinates":[8.966892,46.067051],"type":"Point"}
}