{
  "type": "Feature",
  "properties": {
    "iso:country":"CH",
    "sg:address":"Baumg\u00e4rtliring 10",
    "sg:city":"Gelterkinden",
    "sg:orig_category":"Vereine Radio, Film and Foto",
    "sg:postcode":"4460",
    "sg:province":"Basel-Landschaft",
    "wof:name":"Amateur-film-club Rheinfelden",
    "wof:placetype":"venue"
},
  "geometry": {"coordinates":[7.8563361168,47.4676628113],"type":"Point"}
}