{
  "type": "Feature",
  "properties": {
    "iso:country":"CH",
    "sg:address":"Klettgauerstrasse 36",
    "sg:city":"Neuhausen",
    "sg:orig_category":"Detailhandel mit Milcherzeugnissen U Eiern Detailhandel mit Waren verschiedener Art, Hauptrichtung N",
    "sg:phone":"+41 52 672 46 57",
    "sg:postcode":"8212",
    "sg:province":"Schaffhausen",
    "wof:name":"Toni Hartmann Milchprodukte Lebensmittel",
    "wof:placetype":"venue"
},
  "geometry": {"coordinates":[8.612903595,47.6837043762],"type":"Point"}
}