{
  "type": "Feature",
  "properties": {
    "iso:country":"CH",
    "sg:address":"B\u00fcttenbergstrasse 56",
    "sg:city":"Biel/bienne",
    "sg:orig_category":"Sportvereine Flug Delta",
    "sg:phone":"+41 62 293 48 63",
    "sg:postcode":"2504",
    "sg:province":"Bern",
    "wof:name":"Deltaclub Falk Balsthal",
    "wof:placetype":"venue"
},
  "geometry": {"coordinates":[7.8841748238,47.39295578],"type":"Point"}
}