{
  "type": "Feature",
  "properties": {
    "iso:country":"CH",
    "sg:address":"Hafnerstrasse 11",
    "sg:city":"Z\u00fcrich",
    "sg:orig_category":"Detailhandel mit Blumen U Pflanzen Fachdetailhandel in Verkaufsr\u00e4umen",
    "sg:phone":"+41 12732929",
    "sg:postcode":"8005",
    "sg:province":"Z\u00fcrich",
    "wof:name":"Garten Eden H\u00e4usler",
    "wof:placetype":"venue"
},
  "geometry": {"coordinates":[8.534623,47.380856],"type":"Point"}
}