{
  "type": "Feature",
  "properties": {
    "iso:country":"CH",
    "sg:address":"Kengelwiesstrasse 15",
    "sg:city":"Tann",
    "sg:orig_category":"Hoch U Tiefbau Sonstige pers\u00f6nliche Dienstleistungen",
    "sg:phone":"+41 71 455 14 05",
    "sg:postcode":"8632",
    "sg:province":"Z\u00fcrich",
    "wof:name":"Nussbaumer Jakob",
    "wof:placetype":"venue"
},
  "geometry": {"coordinates":[9.3992624283,47.4883117676],"type":"Point"}
}