{
  "type": "Feature",
  "properties": {
    "iso:country":"CH",
    "sg:address":"Gerbergasse 82 4051 Basel. Postfach",
    "sg:city":"Basel",
    "sg:orig_category":"Reiseb\u00fcros U Reiseveranstalter",
    "sg:phone":"+41 12778111",
    "sg:postcode":"4001",
    "sg:province":"Basel-Stadt",
    "wof:name":"Hotelplan Internationale Reiseorganisation Ag",
    "wof:placetype":"venue"
},
  "geometry": {"coordinates":[7.5887408257,47.5549583435],"type":"Point"}
}