{
  "type": "Feature",
  "properties": {
    "iso:country":"CH",
    "sg:address":"Zwidellen 26",
    "sg:city":"Frick",
    "sg:orig_category":"Sonstige pers\u00f6nliche Dienstleistungen",
    "sg:phone":"+41 62 871 61 39",
    "sg:postcode":"5070",
    "sg:province":"Aargau",
    "wof:name":"B\u00dcschi Support",
    "wof:placetype":"venue"
},
  "geometry": {"coordinates":[8.0164136887,47.5055809021],"type":"Point"}
}