{
  "type": "Feature",
  "properties": {
    "iso:country":"CH",
    "sg:address":"1987",
    "sg:city":"H\u00e9r\u00e9mence",
    "sg:orig_category":"Allgemeiner Hoch U Tiefbau Strassenbau",
    "sg:phone":"+41 27 281 11 44",
    "sg:postcode":"1987",
    "sg:province":"Valais",
    "wof:name":"Arthur Sierro & Fils B\u00e2timent & G\u00e9nie Civil Sa",
    "wof:placetype":"venue"
},
  "geometry": {"coordinates":[7.404666,46.183327],"type":"Point"}
}