{
  "type": "Feature",
  "properties": {
    "iso:country":"CH",
    "sg:address":"Luzernerstrsse 44 6030 Ebikon. Postfach",
    "sg:city":"Ebikon",
    "sg:orig_category":"Werbeagenturen",
    "sg:phone":"+41 41 422 06 00",
    "sg:postcode":"6031",
    "sg:province":"Luzern",
    "wof:name":"Kup Werbeagentur Kinzel & Partner",
    "wof:placetype":"venue"
},
  "geometry": {"coordinates":[8.3267002106,47.0733108521],"type":"Point"}
}