{
  "type": "Feature",
  "properties": {
    "iso:country":"CH",
    "sg:address":"Burgisteinstrasse 61a",
    "sg:city":"Wattenwil",
    "sg:orig_category":"Detailhandel mit Fahrr\u00e4dern Handel mit Motorr\u00e4dern, Teilen U Zubeh\u00f6r Instandhaltung U Reparatur von ",
    "sg:postcode":"3665",
    "sg:province":"Bern",
    "wof:name":"K\u00e4thi Hadorn Velos Motos",
    "wof:placetype":"venue"
},
  "geometry": {"coordinates":[7.506939888,46.7747612],"type":"Point"}
}