{
  "type": "Feature",
  "properties": {
    "iso:country":"CH",
    "sg:address":"Rue De La Gare 6",
    "sg:city":"Vallorbe",
    "sg:orig_category":"Detailhandel mit Waren verschiedener Art, Hauptrichtung Nahrungsmittel Fachdetailhandel mit Nahrungs",
    "sg:phone":"+41 21 843 11 62",
    "sg:postcode":"1337",
    "sg:province":"Vaud",
    "wof:name":"Charles Rochat Comestibles",
    "wof:placetype":"venue"
},
  "geometry": {"coordinates":[6.3752441406,46.7120819092],"type":"Point"}
}