{
  "type": "Feature",
  "properties": {
    "iso:country":"CH",
    "sg:address":"Reitbahnstrasse 22",
    "sg:city":"Glarus",
    "sg:orig_category":"Sportvereine Ski",
    "sg:phone":"+41 55 285 63 13",
    "sg:postcode":"8750",
    "sg:province":"Glarus",
    "wof:name":"Skiclub Glarus",
    "wof:placetype":"venue"
},
  "geometry": {"coordinates":[9.0627202988,47.0435028076],"type":"Point"}
}