{
  "type": "Feature",
  "properties": {
    "addr:full":"Route De Champex Orsi\u00e8res Valais 1937",
    "addr:postcode":"1937",
    "addr:street":"Route De Champex",
    "iso:country":"CH",
    "sg:address":"Route De Champex",
    "sg:city":"Orsi\u00e8res",
    "sg:orig_category":"Architekturb\u00fcros",
    "sg:phone":"+41 27 783 19 31",
    "sg:postcode":"1937",
    "sg:province":"Valais",
    "wof:name":"Auguste Gaillard Bureau D'architecture",
    "wof:placetype":"venue"
},
  "geometry": {"coordinates":[7.141589,46.027107],"type":"Point"}
}