{
  "type": "Feature",
  "properties": {
    "iso:country":"CH",
    "sg:address":"Hauptstrasse 95",
    "sg:city":"Sulz",
    "sg:classifiers":[
        {
            "category":"Manufacturing",
            "subcategory":"Furniture",
            "type":"Manufacturing & Wholesale Goods"
        }
    ],
    "sg:phone":"+41 62 875 12 40",
    "sg:postcode":"5085",
    "sg:province":"Aargau",
    "sg:tags":[
        "children's"
    ],
    "wof:name":"Schreinerei Weiss Gmbh",
    "wof:placetype":"venue"
},
  "geometry": {"coordinates":[8.095359,47.532135],"type":"Point"}
}