{
  "type": "Feature",
  "properties": {
    "addr:full":"Studenb\u00fchlstrasse 52 Wollerau Schwyz 8832",
    "addr:housenumber":"52",
    "addr:postcode":"8832",
    "addr:street":"Studenbuehlstrasse;Schwyz",
    "iso:country":"CH",
    "sg:address":"Studenb\u00fchlstrasse 52",
    "sg:city":"Wollerau",
    "sg:classifiers":[
        {
            "category":"Banks & Credit Unions",
            "subcategory":"Bank",
            "type":"Services"
        }
    ],
    "sg:phone":"+41 17845127",
    "sg:postcode":"8832",
    "sg:province":"Schwyz",
    "wof:name":"Rentenanstalt Swiss Life",
    "wof:placetype":"venue"
},
  "geometry": {"coordinates":[8.707954,47.199909],"type":"Point"}
}