{
  "type": "Feature",
  "properties": {
    "addr:full":"Landstrasse 2b Nussbaumen Aargau 5415",
    "addr:housenumber":"2b",
    "addr:postcode":"5415",
    "addr:street":"Landstrasse",
    "iso:country":"CH",
    "sg:address":"Landstrasse 2b",
    "sg:city":"Nussbaumen",
    "sg:classifiers":[
        {
            "category":"Manufacturing",
            "subcategory":"Glass & Minerals",
            "type":"Manufacturing & Wholesale Goods"
        }
    ],
    "sg:phone":"+41 56 282 29 39",
    "sg:postcode":"5415",
    "sg:province":"Aargau",
    "sg:tags":[
        "chemical",
        "consulting"
    ],
    "wof:name":"Schnyder Sicherheit In Der Chemie Ag",
    "wof:placetype":"venue"
},
  "geometry": {"coordinates":[8.293214,47.486698],"type":"Point"}
}