{
  "type": "Feature",
  "properties": {
    "iso:country":"CH",
    "sg:address":"Rue De La Gare 45",
    "sg:city":"Payerne",
    "sg:orig_category":"Erbringung von Dienstleistungen f\u00fcr Unternehmen",
    "sg:phone":"+41 26 660 12 60",
    "sg:postcode":"1530",
    "sg:province":"Vaud",
    "wof:name":"Tinguely H\u00e9l\u00e8ne",
    "wof:placetype":"venue"
},
  "geometry": {"coordinates":[6.9404268265,46.8206634521],"type":"Point"}
}