{
  "type": "Feature",
  "properties": {
    "iso:country":"CH",
    "sg:address":"B\u00e4tterkindenstrasse 5",
    "sg:city":"Limpach",
    "sg:classifiers":[
        {
            "category":"Restaurant",
            "type":"Food & Drink"
        }
    ],
    "sg:phone":"+41 31 767 82 84",
    "sg:postcode":"3317",
    "sg:province":"Bern",
    "wof:name":"Restaurant Zum Kreuz",
    "wof:placetype":"venue"
},
  "geometry": {"coordinates":[7.4948868752,47.1086616516],"type":"Point"}
}