{
  "type": "Feature",
  "properties": {
    "iso:country":"CH",
    "sg:address":"Bernstr. 29",
    "sg:city":"Lyssach",
    "sg:orig_category":"Lagerh\u00e4user, G\u00fcterumschlag, Verteilzentren",
    "sg:phone":"+41 34 445 45 30",
    "sg:postcode":"3421",
    "sg:province":"Bern",
    "wof:name":"Kipfer Fritz Lager Ag",
    "wof:placetype":"venue"
},
  "geometry": {"coordinates":[7.5693421364,47.0725708008],"type":"Point"}
}