{
  "type": "Feature",
  "properties": {
    "iso:country":"CH",
    "sg:address":"Schipfe 10/16",
    "sg:city":"Z\u00fcrich",
    "sg:orig_category":"Bauschreinerei Detailhandel mit Antiquit\u00e4ten U Gebrauchtwaren in Verkaufsr\u00e4umen",
    "sg:phone":"+41 12113434",
    "sg:postcode":"8001",
    "sg:province":"Z\u00fcrich",
    "wof:name":"Vock Dani Antiquit\u00e4ten Ag",
    "wof:placetype":"venue"
},
  "geometry": {"coordinates":[8.541736,47.372963],"type":"Point"}
}