{
  "type": "Feature",
  "properties": {
    "iso:country":"CH",
    "sg:address":"Steinackerstrasse 31 8902 Urdorf. Postfach",
    "sg:city":"Urdorf",
    "sg:orig_category":"Reiseb\u00fcros U Reiseveranstalter",
    "sg:postcode":"8902",
    "sg:province":"Z\u00fcrich",
    "wof:name":"Marlin Reisen Touroperating Gmbh",
    "wof:placetype":"venue"
},
  "geometry": {"coordinates":[8.4191045761,47.3938293457],"type":"Point"}
}