{
  "type": "Feature",
  "properties": {
    "iso:country":"CH",
    "sg:address":"Via Angelo Maspoli 18",
    "sg:city":"Mendrisio",
    "sg:orig_category":"Detailhandel mit Textilien Grosshandel mit Textilien",
    "sg:phone":"+41 91 630 09 94",
    "sg:postcode":"6850",
    "sg:province":"Ticino",
    "wof:name":"Hanro Ag",
    "wof:placetype":"venue"
},
  "geometry": {"coordinates":[8.978729248,45.8752593994],"type":"Point"}
}