{
  "type": "Feature",
  "properties": {
    "iso:country":"CH",
    "sg:address":"Grienbachstrasse 11 6300 Zug. Postfach 55",
    "sg:city":"Zug",
    "sg:orig_category":"Grosshandel mit Tabakwaren Tabakverarbeitung",
    "sg:phone":"+41 41 769 75 00",
    "sg:postcode":"6301",
    "sg:province":"Zug",
    "wof:name":"Mabritab International Ltd",
    "wof:placetype":"venue"
},
  "geometry": {"coordinates":[8.5224514008,47.1836013794],"type":"Point"}
}