{
  "type": "Feature",
  "properties": {
    "iso:country":"CH",
    "sg:address":"Bahnhofstr. 6",
    "sg:city":"Heimberg",
    "sg:classifiers":[
        {
            "category":"Banks & Credit Unions",
            "subcategory":"Bank",
            "type":"Services"
        }
    ],
    "sg:phone":"+41 33 437 18 41",
    "sg:postcode":"3627",
    "sg:province":"Bern",
    "wof:name":"Amtsersparniskasse Thun, Einnehmerei Berger Heinz",
    "wof:placetype":"venue"
},
  "geometry": {"coordinates":[7.60644,46.791096],"type":"Point"}
}