{
  "type": "Feature",
  "properties": {
    "iso:country":"CH",
    "sg:address":"Buchenweg 34",
    "sg:city":"W\u00fcrenlingen",
    "sg:orig_category":"Softwareentwicklung U beratung",
    "sg:phone":"+41 56 290 02 50",
    "sg:postcode":"5303",
    "sg:province":"Aargau",
    "wof:name":"Dtc Double Team Consulting Gmbh",
    "wof:placetype":"venue"
},
  "geometry": {"coordinates":[8.2657575607,47.5204544067],"type":"Point"}
}