{
  "type": "Feature",
  "properties": {
    "addr:full":"Parkweg 1 Thalwil Z\u00fcrich 8800",
    "addr:housenumber":"1",
    "addr:postcode":"8800",
    "addr:street":"Parkweg",
    "iso:country":"CH",
    "sg:address":"Parkweg 1",
    "sg:city":"Thalwil",
    "sg:orig_category":"Bauschreinerei Herstellung von Konstruktionsteilen, Fertigbauteilen U Ausbauelementen aus Holz",
    "sg:phone":"+41 17201697",
    "sg:postcode":"8800",
    "sg:province":"Z\u00fcrich",
    "wof:name":"Bradovka & Co",
    "wof:placetype":"venue"
},
  "geometry": {"coordinates":[8.567179,47.296173],"type":"Point"}
}