{
  "type": "Feature",
  "properties": {
    "iso:country":"CH",
    "sg:address":"Hagenwil 7",
    "sg:city":"Hagenwil",
    "sg:orig_category":"Haltung von Schweinen",
    "sg:phone":"+41 71 411 19 33",
    "sg:postcode":"8580",
    "sg:province":"Thurgau",
    "wof:name":"Josef W\u00fcrth Schweinezucht Bilchen",
    "wof:placetype":"venue"
},
  "geometry": {"coordinates":[9.2995681763,47.54504776],"type":"Point"}
}