{
  "type": "Feature",
  "properties": {
    "iso:country":"CH",
    "sg:address":"Schwertstrasse 9 8200 Schaffhausen. Postfach",
    "sg:city":"Schaffhausen",
    "sg:orig_category":"Detailhandel mit Sportartikeln Reiseb\u00fcros U Reiseveranstalter",
    "sg:phone":"+41 52 633 00 33",
    "sg:postcode":"8201",
    "sg:province":"Schaffhausen",
    "wof:name":"Wamo Reisen Wanzenried, Egolf + Co.",
    "wof:placetype":"venue"
},
  "geometry": {"coordinates":[8.6325616837,47.6972923279],"type":"Point"}
}