{
  "type": "Feature",
  "properties": {
    "iso:country":"CH",
    "sg:address":"Surseestrasse 34",
    "sg:city":"Neuenkirch",
    "sg:orig_category":"Instandhaltung U Reparatur von Automobilen Tankstellen",
    "sg:phone":"+41 41 467 17 17",
    "sg:postcode":"6206",
    "sg:province":"Luzern",
    "wof:name":"Auto Eden Ag",
    "wof:placetype":"venue"
},
  "geometry": {"coordinates":[8.2015037537,47.1035804749],"type":"Point"}
}