{
  "type": "Feature",
  "properties": {
    "addr:full":"Obstwachsstrasse 10 Schmerikon St. Gallen 8716",
    "addr:housenumber":"10",
    "addr:postcode":"8716",
    "addr:street":"Obstwachsstrasse",
    "iso:country":"CH",
    "sg:address":"Obstwachsstrasse 10",
    "sg:city":"Schmerikon",
    "sg:classifiers":[
        {
            "category":"Organizations",
            "subcategory":"Labor Organization",
            "type":"Services"
        }
    ],
    "sg:phone":"+41 55 292 12 56",
    "sg:postcode":"8716",
    "sg:province":"St. Gallen",
    "sg:tags":[
        "cleaning",
        "central",
        "system",
        "vacuum"
    ],
    "wof:name":"Perfekt Elektroinstallationen Gmbh",
    "wof:placetype":"venue"
},
  "geometry": {"coordinates":[8.934725,47.226246],"type":"Point"}
}