{
  "type": "Feature",
  "properties": {
    "iso:country":"CH",
    "sg:address":"1838",
    "sg:city":"Rougemont",
    "sg:classifiers":[
        {
            "category":"Restaurant",
            "type":"Food & Drink"
        }
    ],
    "sg:phone":"+41 26 925 81 42",
    "sg:postcode":"1838",
    "wof:name":"Restaurant Videmanette",
    "wof:placetype":"venue"
},
  "geometry": {"coordinates":[-78.9260559082,36.2178535461],"type":"Point"}
}