{
  "type": "Feature",
  "properties": {
    "iso:country":"CH",
    "sg:address":"Campagna Via Croce 2",
    "sg:city":"Stabio",
    "sg:orig_category":"Grosshandel mit Obst U Gem\u00fcse",
    "sg:postcode":"6855",
    "sg:province":"Ticino",
    "wof:name":"Punto Fresco Sa",
    "wof:placetype":"venue"
},
  "geometry": {"coordinates":[8.9465932846,45.8526115417],"type":"Point"}
}