{
  "type": "Feature",
  "properties": {
    "iso:country":"CH",
    "sg:address":"Via Industria",
    "sg:city":"Lamone",
    "sg:orig_category":"Grosshandel mit Erzen U Metallen Grosshandel mit sonstigen Konsumg\u00fctern",
    "sg:phone":"+41 26 919 77 21",
    "sg:postcode":"6814",
    "sg:province":"Ticino",
    "wof:name":"J. & A. Glasson Bulle Sa",
    "wof:placetype":"venue"
},
  "geometry": {"coordinates":[7.0468211174,46.6155128479],"type":"Point"}
}