{
  "type": "Feature",
  "properties": {
    "iso:country":"CH",
    "sg:address":"Fruthwilerstrasse 22",
    "sg:city":"Ermatingen",
    "sg:classifiers":[
        {
            "category":"Restaurant",
            "type":"Food & Drink"
        }
    ],
    "sg:phone":"+41 71 664 24 04",
    "sg:postcode":"8272",
    "sg:province":"Thurgau",
    "wof:name":"Restaurant Rebstock",
    "wof:placetype":"venue"
},
  "geometry": {"coordinates":[9.0799646378,47.6675300598],"type":"Point"}
}