{
  "type": "Feature",
  "properties": {
    "iso:country":"CH",
    "sg:address":"Oberr\u00fctelistrasse 13",
    "sg:city":"Mollis",
    "sg:classifiers":[
        {
            "category":"Internet Cafe",
            "subcategory":"None",
            "type":"Food & Drink"
        }
    ],
    "sg:postcode":"8753",
    "sg:province":"Glarus",
    "sg:tags":[
        "informatikdienste",
        "provider"
    ],
    "wof:name":"Conet Gmbh Informatik Dienstleistungen",
    "wof:placetype":"venue"
},
  "geometry": {"coordinates":[9.0696020126,47.0913581848],"type":"Point"}
}