{
  "type": "Feature",
  "properties": {
    "iso:country":"CH",
    "sg:address":"Museggstrasse 8a",
    "sg:city":"Luzern",
    "sg:orig_category":"Softwareentwicklung U beratung",
    "sg:phone":"+41 41 410 10 66",
    "sg:postcode":"6004",
    "sg:province":"Luzern",
    "wof:name":"De Marc Sa",
    "wof:placetype":"venue"
},
  "geometry": {"coordinates":[8.3097190857,47.0557479858],"type":"Point"}
}