{
  "type": "Feature",
  "properties": {
    "iso:country":"CH",
    "sg:address":"2926 Boncourt. Postfach",
    "sg:city":"Boncourt",
    "sg:orig_category":"Tabakverarbeitung",
    "sg:phone":"+41 62 765 55 55",
    "sg:postcode":"2926",
    "sg:province":"Jura",
    "wof:name":"Villiger S\u00f6hne Ag",
    "wof:placetype":"venue"
},
  "geometry": {"coordinates":[8.1618499756,47.247089386],"type":"Point"}
}