{
  "type": "Feature",
  "properties": {
    "iso:country":"CH",
    "sg:address":"Rathausplatz 18",
    "sg:city":"Glarus",
    "sg:orig_category":"RESTAURANTS: TEA-ROOMS",
    "sg:postcode":"8750",
    "sg:province":"Glarus",
    "wof:name":"Tirreno Gmbh",
    "wof:placetype":"venue"
},
  "geometry": {"coordinates":[8.5110044479,47.4709587097],"type":"Point"}
}