{
  "type": "Feature",
  "properties": {
    "iso:country":"CH",
    "sg:address":"Industriestrasse 1",
    "sg:city":"Lostorf",
    "sg:orig_category":"Instandhaltung U Reparatur von Automobilen",
    "sg:phone":"+41 62 295 15 18",
    "sg:postcode":"4654",
    "sg:province":"Solothurn",
    "wof:name":"Garage Carrosserie Gubler Martin",
    "wof:placetype":"venue"
},
  "geometry": {"coordinates":[7.9493041039,47.373462677],"type":"Point"}
}