{
  "type": "Feature",
  "properties": {
    "iso:country":"CH",
    "sg:address":"H\u00e4userrain 66",
    "sg:city":"Zeglingen",
    "sg:orig_category":"Landw. Genossenschaften Alpgenossenschaften",
    "sg:phone":"+41 61 981 23 71",
    "sg:postcode":"4495",
    "sg:province":"Basel-Landschaft",
    "wof:name":"Weidengenossenschaft W.breitenstein",
    "wof:placetype":"venue"
},
  "geometry": {"coordinates":[7.9099311829,47.4159240723],"type":"Point"}
}