{
  "type": "Feature",
  "properties": {
    "iso:country":"CH",
    "sg:address":"Route De Neuch\u00e2tel 41",
    "sg:city":"Prilly",
    "sg:orig_category":"W\u00e4scherei U chemische Reinigung",
    "sg:postcode":"1008",
    "sg:province":"Vaud",
    "wof:name":"Blanchisserie H. B\u00fcchler",
    "wof:placetype":"venue"
},
  "geometry": {"coordinates":[6.6087679863,46.5360832214],"type":"Point"}
}