{
  "type": "Feature",
  "properties": {
    "iso:country":"CH",
    "sg:address":"Spitzwaldstr 215",
    "sg:city":"Allschwil",
    "sg:classifiers":[
        {
            "category":"Banks & Credit Unions",
            "subcategory":"Bank",
            "type":"Services"
        }
    ],
    "sg:phone":"+41 61 481 22 11",
    "sg:postcode":"4123",
    "sg:province":"Basel-Landschaft",
    "wof:name":"Schweiz. Bankgesellschaft",
    "wof:placetype":"venue"
},
  "geometry": {"coordinates":[7.552953,47.547035],"type":"Point"}
}