{
  "type": "Feature",
  "properties": {
    "iso:country":"CH",
    "sg:address":"Sch\u00fctzengass 2 8226 Schleitheim. Postfach",
    "sg:city":"Schleitheim",
    "sg:orig_category":"Pensionskassen",
    "sg:postcode":"8226",
    "sg:province":"Schaffhausen",
    "wof:name":"Personalf\u00fcrsorgestiftung Der Firma Willi Messerli Ag",
    "wof:placetype":"venue"
},
  "geometry": {"coordinates":[9.1668395996,47.5790901184],"type":"Point"}
}