{
  "type": "Feature",
  "properties": {
    "iso:country":"CH",
    "sg:address":"Pelzgasse 23 5000 Aarau. Postfach",
    "sg:city":"Aarau",
    "sg:orig_category":"Detailhandel mit Radio U Fernsehger\u00e4ten",
    "sg:phone":"+41 62 824 55 58",
    "sg:postcode":"5001",
    "sg:province":"Aargau",
    "wof:name":"Walter Kyburz Radio-television-service",
    "wof:placetype":"venue"
},
  "geometry": {"coordinates":[8.0447864532,47.3923797607],"type":"Point"}
}