{
  "type": "Feature",
  "properties": {
    "iso:country":"CH",
    "sg:address":"Nidelbadstrasse 38",
    "sg:city":"Z\u00fcrich",
    "sg:orig_category":"Sonstige Aktivit\u00e4ten der nicht-\u00e4rztlichen Medizinalberufe",
    "sg:phone":"+41 81 756 07 82",
    "sg:postcode":"8038",
    "sg:province":"Z\u00fcrich",
    "wof:name":"Elsbeth Eggenberger Atemtherapie",
    "wof:placetype":"venue"
},
  "geometry": {"coordinates":[9.476931572,47.166973114],"type":"Point"}
}