{
  "type": "Feature",
  "properties": {
    "iso:country":"CH",
    "sg:address":"Rue De La Moli\u00e8re 7",
    "sg:city":"Del\u00e9mont",
    "sg:orig_category":"Detailhandel mit Bekleidung",
    "sg:phone":"+41 32 422 12 66",
    "sg:postcode":"2800",
    "sg:province":"Jura",
    "wof:name":"Santini Modes & Chapellerie Succr Jurot-santini",
    "wof:placetype":"venue"
},
  "geometry": {"coordinates":[7.347732,47.363701],"type":"Point"}
}