{
  "type": "Feature",
  "properties": {
    "iso:country":"CH",
    "sg:address":"Schulstrasse 2 8590 Romanshorn. Postfach",
    "sg:city":"Romanshorn",
    "sg:orig_category":"Unternehmensberatung",
    "sg:postcode":"8590",
    "sg:province":"Thurgau",
    "wof:name":"Spielmann Consulting Ag",
    "wof:placetype":"venue"
},
  "geometry": {"coordinates":[9.3739824295,47.5647544861],"type":"Point"}
}