{
  "type": "Feature",
  "properties": {
    "iso:country":"CH",
    "sg:address":"Kreuzlingerstrasse 41b",
    "sg:city":"Romanshorn",
    "sg:orig_category":"Fahrschulen, Flugschulen",
    "sg:phone":"+41 79 447 80 27",
    "sg:postcode":"8590",
    "sg:province":"Thurgau",
    "wof:name":"Hugo M\u00fcller Autofahrschule",
    "wof:placetype":"venue"
},
  "geometry": {"coordinates":[9.3661203384,47.5702590942],"type":"Point"}
}