{
  "type": "Feature",
  "properties": {
    "iso:country":"CH",
    "sg:address":"L\u00fcssihof",
    "sg:city":"Zug",
    "sg:orig_category":"Grosshandel mit sonstigen Konsumg\u00fctern",
    "sg:phone":"+41 41 712 39 39",
    "sg:postcode":"6300",
    "sg:province":"Zug",
    "wof:name":"Urs Bischof Gold-art",
    "wof:placetype":"venue"
},
  "geometry": {"coordinates":[8.5200052261,47.1764259338],"type":"Point"}
}