{
  "type": "Feature",
  "properties": {
    "iso:country":"CH",
    "sg:address":"Hirschweg 21",
    "sg:city":"Seen",
    "sg:orig_category":"Interessenvertretungen",
    "sg:phone":"+41 52 212 01 17",
    "sg:postcode":"8405",
    "sg:province":"Z\u00fcrich",
    "wof:name":"Erholungsheim Im Winkel F\u00fcr Die Krankenschwestern Des Kantonsspitals Winterthur",
    "wof:placetype":"venue"
},
  "geometry": {"coordinates":[8.7693500519,47.4825515747],"type":"Point"}
}