{
  "type": "Feature",
  "properties": {
    "iso:country":"CH",
    "sg:address":"Chemin De Beau-val 9",
    "sg:city":"Lausanne",
    "sg:orig_category":"Organisationen der Wohlfahrtspflege",
    "sg:phone":"+41 71 672 96 38",
    "sg:postcode":"1012",
    "sg:province":"Vaud",
    "wof:name":"Verein Ekkharthof Heil-& Bildungsst\u00e4tte",
    "wof:placetype":"venue"
},
  "geometry": {"coordinates":[9.1937875748,47.6247749329],"type":"Point"}
}