{
  "type": "Feature",
  "properties": {
    "iso:country":"CH",
    "sg:address":"Vorstadt 32 6300 Zug. Postfach",
    "sg:city":"Zug",
    "sg:orig_category":"Handels-H\u00e4user U Gesellschaften",
    "sg:postcode":"6300",
    "sg:province":"Zug",
    "wof:name":"Agamemnon Ltd Handelsgesch\u00e4fte; Vermittlung, Beratung",
    "wof:placetype":"venue"
},
  "geometry": {"coordinates":[8.5143957138,47.1694755554],"type":"Point"}
}