{
  "type": "Feature",
  "properties": {
    "iso:country":"CH",
    "sg:address":"Baslerstrasse 29",
    "sg:city":"Z\u00fcrich",
    "sg:orig_category":"Herstellung von Elektromotoren, Generatoren U Transformatoren",
    "sg:phone":"+41 14056060",
    "sg:postcode":"8048",
    "sg:province":"Z\u00fcrich",
    "wof:name":"Intelsa Ag Telefon, Schwachstromanlagen Usw.; Projektierung, Berwchnung",
    "wof:placetype":"venue"
},
  "geometry": {"coordinates":[8.5025491714,47.3845100403],"type":"Point"}
}