{
  "type": "Feature",
  "properties": {
    "iso:country":"CH",
    "sg:address":"Hubacherstrasse 12 8105 Regensdorf. Postfach",
    "sg:city":"Regensdorf",
    "sg:orig_category":"Mit dem Versicherungsgewerbe verbundene T\u00e4tigkeiten",
    "sg:postcode":"8105",
    "sg:province":"Z\u00fcrich",
    "wof:name":"1 Zu 1 Versicherungstreuhand Grieder Rolf",
    "wof:placetype":"venue"
},
  "geometry": {"coordinates":[8.462720871,47.4287490845],"type":"Point"}
}