{
  "type": "Feature",
  "properties": {
    "iso:country":"CH",
    "sg:address":"Kirchgasse 26",
    "sg:city":"Z\u00fcrich",
    "sg:orig_category":"Detailhandel mit Antiquit\u00e4ten",
    "sg:phone":"+41 52 364 10 88",
    "sg:postcode":"8001",
    "sg:province":"Z\u00fcrich",
    "wof:name":"Elisabeth Studer Antiquit\u00e4ten",
    "wof:placetype":"venue"
},
  "geometry": {"coordinates":[8.88351,47.502998],"type":"Point"}
}