{
  "type": "Feature",
  "properties": {
    "iso:country":"CH",
    "sg:address":"Grand-rue 22",
    "sg:city":"Pruntrut",
    "sg:orig_category":"Non-Classified Establishments",
    "sg:postcode":"2900",
    "sg:province":"Jura",
    "wof:name":"L'arcade Et Son Caf\u00e9, Nathalie Lombardo-cattin",
    "wof:placetype":"venue"
},
  "geometry": {"coordinates":[6.1406412125,46.1861915588],"type":"Point"}
}