{
  "type": "Feature",
  "properties": {
    "iso:country":"CH",
    "sg:address":"Bahnhofplatz 5 6060 Sarnen. Postfach 448",
    "sg:city":"Sarnen",
    "sg:orig_category":"Herstellung von sonstigen elektrischen Ausr\u00fcstungen",
    "sg:phone":"+41 41 637 32 50",
    "sg:postcode":"6060",
    "sg:province":"Obwalden",
    "wof:name":"Leico Leiser Ag",
    "wof:placetype":"venue"
},
  "geometry": {"coordinates":[8.2471590042,46.8949890137],"type":"Point"}
}