{
  "type": "Feature",
  "properties": {
    "iso:country":"CH",
    "sg:address":"Blumenweg 7",
    "sg:city":"Buchrain",
    "sg:orig_category":"Unternehmensberatung",
    "sg:phone":"+41 41 440 23 10",
    "sg:postcode":"6033",
    "sg:province":"Luzern",
    "wof:name":"Wolfisberg Daniel, Unternehmensberatung Und Kaderschulung",
    "wof:placetype":"venue"
},
  "geometry": {"coordinates":[8.3516359329,47.0988578796],"type":"Point"}
}