{
  "type": "Feature",
  "properties": {
    "iso:country":"CH",
    "sg:address":"Alpenblickstrasse 54",
    "sg:city":"Horgen",
    "sg:orig_category":"Bau U Wohngenossenschaften",
    "sg:phone":"+41 17252155",
    "sg:postcode":"8810",
    "sg:province":"Z\u00fcrich",
    "wof:name":"Mietergenossensch.alpenblick",
    "wof:placetype":"venue"
},
  "geometry": {"coordinates":[8.583564,47.265263],"type":"Point"}
}