{
  "type": "Feature",
  "properties": {
    "iso:country":"CH",
    "sg:address":"Merkurstrasse 64",
    "sg:city":"Z\u00fcrich",
    "sg:orig_category":"Sonstiges Verlagsgewerbe",
    "sg:phone":"+41 12520767",
    "sg:postcode":"8032",
    "sg:province":"Z\u00fcrich",
    "wof:name":"Swissedit Dr. Wolfram Schneider-lastin",
    "wof:placetype":"venue"
},
  "geometry": {"coordinates":[8.5563459396,47.3679962158],"type":"Point"}
}