{
  "type": "Feature",
  "properties": {
    "iso:country":"CH",
    "sg:address":"Chilegass 10",
    "sg:city":"Volketswil",
    "sg:orig_category":"Datenverarbeitungsdienste Softwareentwicklung U beratung",
    "sg:phone":"+41 19451220",
    "sg:postcode":"8604",
    "sg:province":"Z\u00fcrich",
    "wof:name":"Datisca Ag",
    "wof:placetype":"venue"
},
  "geometry": {"coordinates":[8.691424,47.389034],"type":"Point"}
}