{
  "type": "Feature",
  "properties": {
    "iso:country":"CH",
    "sg:address":"Langhaus 3",
    "sg:city":"Baden",
    "sg:orig_category":"Unternehmensberatung Wirtschaftspr\u00fcfung, Steuerberatung U Treuhand",
    "sg:phone":"+41 56 203 18 88",
    "sg:postcode":"5400",
    "sg:province":"Aargau",
    "wof:name":"Arthur Andersen Ag",
    "wof:placetype":"venue"
},
  "geometry": {"coordinates":[8.3065128326,47.4762496948],"type":"Point"}
}