{
  "type": "Feature",
  "properties": {
    "iso:country":"CH",
    "sg:address":"Neuenburgerstrasse 10",
    "sg:city":"Aarau",
    "sg:orig_category":"Handelsvermittlung U Grosshandel mit Automobilen Herstellung von Hebezeugen U F\u00f6rdermitteln",
    "sg:phone":"+41 62 824 47 77",
    "sg:postcode":"5004",
    "sg:province":"Aargau",
    "wof:name":"Hill Logistik Gmbh",
    "wof:placetype":"venue"
},
  "geometry": {"coordinates":[8.0625200272,47.400352478],"type":"Point"}
}