{
  "type": "Feature",
  "properties": {
    "iso:country":"CH",
    "sg:address":"Impasse Pierre Fleur 7",
    "sg:city":"Payerne",
    "sg:orig_category":"G\u00fcterbef\u00f6rderung im Strassenverkehr",
    "sg:postcode":"1530",
    "sg:province":"Vaud",
    "wof:name":"Schenker Franz",
    "wof:placetype":"venue"
},
  "geometry": {"coordinates":[6.942964077,46.8177146912],"type":"Point"}
}