{
  "type": "Feature",
  "properties": {
    "iso:country":"CH",
    "sg:address":"Furkastrasse 27",
    "sg:city":"Brig",
    "sg:orig_category":"Detailhandel mit Waren verschiedener Art, Hauptrichtung Nahrungsmittel",
    "sg:phone":"+41 27 923 25 05",
    "sg:postcode":"3900",
    "sg:province":"Valais",
    "wof:name":"Denner Ag Super-discount",
    "wof:placetype":"venue"
},
  "geometry": {"coordinates":[7.9853200912,46.3184432983],"type":"Point"}
}