{
  "type": "Feature",
  "properties": {
    "iso:country":"CH",
    "sg:address":"Hauptstrasse 12 4410 Liestal. Postfach",
    "sg:city":"Liestal",
    "sg:orig_category":"Unclassifiable Establishments",
    "sg:postcode":"4410",
    "sg:province":"Basel-Landschaft",
    "wof:name":"Martine Junod Naturopathe",
    "wof:placetype":"venue"
},
  "geometry": {"coordinates":[6.8729848862,46.9847488403],"type":"Point"}
}