{
  "type": "Feature",
  "properties": {
    "iso:country":"CH",
    "sg:address":"Fl\u00fchgasse 21 8008 Z\u00fcrich. Postfach",
    "sg:city":"Z\u00fcrich",
    "sg:orig_category":"Werbung",
    "sg:postcode":"8001",
    "sg:province":"Z\u00fcrich",
    "wof:name":"Gruber, Projekte F\u00fcr Kommunikation Werbekonzepte F. D. Kommunikationsbranche; Entw.",
    "wof:placetype":"venue"
},
  "geometry": {"coordinates":[8.5645885468,47.3494491577],"type":"Point"}
}