{
  "type": "Feature",
  "properties": {
    "iso:country":"CH",
    "sg:address":"Z\u00e4hringerstrasse 24 8000 Z\u00fcrich. Postfach",
    "sg:city":"Z\u00fcrich",
    "sg:orig_category":"Erwachsenenbildung U Unterricht",
    "sg:phone":"+41 34 445 82 78",
    "sg:postcode":"8001",
    "sg:province":"Z\u00fcrich",
    "wof:name":"Manax Supporting Gmbh Management, Support- U. Umsetzungs- Beziehungsweise Beratungsdienstl. Usw.",
    "wof:placetype":"venue"
},
  "geometry": {"coordinates":[7.5919728279,47.0835876465],"type":"Point"}
}