{
  "type": "Feature",
  "properties": {
    "iso:country":"CH",
    "sg:address":"Altstetterstrasse 279 8047 Z\u00fcrich. Postfach",
    "sg:city":"Z\u00fcrich",
    "sg:orig_category":"Grosshandel mit Bekleidung Grosshandel mit Sportartikeln",
    "sg:phone":"+41 14929013",
    "sg:postcode":"8047",
    "sg:province":"Z\u00fcrich",
    "wof:name":"Max K. Eisenbarth Sport-& Mode-import",
    "wof:placetype":"venue"
},
  "geometry": {"coordinates":[8.4834489822,47.3787193298],"type":"Point"}
}