{
  "type": "Feature",
  "properties": {
    "iso:country":"CH",
    "sg:address":"Boiron Route Du 5",
    "sg:city":"Nyon",
    "sg:orig_category":"Softwareentwicklung U beratung",
    "sg:phone":"+41 79 415 00 49",
    "sg:postcode":"1260",
    "sg:province":"Vaud",
    "wof:name":"Jle Informatique, Jean-luc Eggimann",
    "wof:placetype":"venue"
},
  "geometry": {"coordinates":[6.7705950737,46.5937194824],"type":"Point"}
}