{
  "type": "Feature",
  "properties": {
    "iso:country":"CH",
    "sg:address":"Sonnhalde 22 4410 Liestal. Postfach 297",
    "sg:city":"Liestal",
    "sg:orig_category":"Grosshandel mit elektrischen Haushaltsger\u00e4ten, Radio U Fernsehger\u00e4ten Handelsvermittlung U Grosshand",
    "sg:phone":"+41 61 921 38 50",
    "sg:postcode":"4410",
    "sg:province":"Basel-Landschaft",
    "wof:name":"Liplan H.& P.salath\u00e9",
    "wof:placetype":"venue"
},
  "geometry": {"coordinates":[7.7482190132,47.4825782776],"type":"Point"}
}