{
  "type": "Feature",
  "properties": {
    "iso:country":"CH",
    "sg:address":"Dorfstr. 2. 8240 Thayngen. Postfach",
    "sg:city":"Thayngen",
    "sg:classifiers":[
        {
            "category":"Travel",
            "subcategory":"Hotels & Motels",
            "type":"Entertainment"
        }
    ],
    "sg:postcode":"8240",
    "sg:province":"Schaffhausen",
    "sg:tags":[
        "hotels",
        "mit",
        "restaurant"
    ],
    "wof:name":"H\u00e4gele Walter",
    "wof:placetype":"venue"
},
  "geometry": {"coordinates":[8.7076416016,47.7472457886],"type":"Point"}
}