{
  "type": "Feature",
  "properties": {
    "iso:country":"CH",
    "sg:address":"Alemannenstrasse 50",
    "sg:city":"Bern",
    "sg:orig_category":"Grosshandel mit Obst U Gem\u00fcse",
    "sg:postcode":"3018",
    "sg:province":"Bern",
    "wof:name":"Heime Fr\u00fcchte Gmbh",
    "wof:placetype":"venue"
},
  "geometry": {"coordinates":[7.3941922188,46.9428405762],"type":"Point"}
}