{
  "type": "Feature",
  "properties": {
    "iso:country":"CH",
    "sg:address":"Rainstrasse 66",
    "sg:city":"Z\u00fcrich",
    "sg:orig_category":"Sonstige mit der Informatik verbundene T\u00e4tigkeiten",
    "sg:phone":"+41 14825623",
    "sg:postcode":"8038",
    "sg:province":"Z\u00fcrich",
    "wof:name":"Miloradovic P. It-beratung",
    "wof:placetype":"venue"
},
  "geometry": {"coordinates":[8.5265216827,47.344909668],"type":"Point"}
}