{
  "type": "Feature",
  "properties": {
    "iso:country":"CH",
    "sg:address":"H\u00f6heweg 4 3800 Interlaken. Postfach 39",
    "sg:city":"Interlaken",
    "sg:orig_category":"Fachdetailhandel mit pharmazeutischen Produkten Kosmetikinstitute",
    "sg:phone":"+41 33 828 34 28",
    "sg:postcode":"3800",
    "sg:province":"Bern",
    "wof:name":"Apotheke Dr.portmann Ag",
    "wof:placetype":"venue"
},
  "geometry": {"coordinates":[7.8554611206,46.6852226257],"type":"Point"}
}