{
  "type": "Feature",
  "properties": {
    "iso:country":"CH",
    "sg:address":"Spitalstrasse 43 3280 Meyriez. Postfach",
    "sg:city":"Meyriez",
    "sg:orig_category":"Herstellung von Dauerbackwaren Unternehmensberatung",
    "sg:phone":"+41 26 670 64 76",
    "sg:postcode":"3280",
    "sg:province":"Fribourg",
    "wof:name":"Schmid Consulting Gmbh Dienstleistungen, Beratungen Im Industriellen Sektor, Bes. In Der Backwarenherstellung Usw",
    "wof:placetype":"venue"
},
  "geometry": {"coordinates":[7.1071028709,46.9221038818],"type":"Point"}
}