{
  "type": "Feature",
  "properties": {
    "iso:country":"CH",
    "sg:address":"Herblingerstrasse 101",
    "sg:city":"Schaffhausen",
    "sg:orig_category":"Fotografische Ateliers Fotografische Laboratorien",
    "sg:phone":"+41 52 643 68 01",
    "sg:postcode":"8207",
    "sg:province":"Schaffhausen",
    "wof:name":"Erika Aries Foto Dreispitz",
    "wof:placetype":"venue"
},
  "geometry": {"coordinates":[8.6600818634,47.7213096619],"type":"Point"}
}