{
  "type": "Feature",
  "properties": {
    "iso:country":"CH",
    "sg:address":"Rue Du Cygne 3",
    "sg:city":"Porrentruy",
    "sg:orig_category":"Fahrschulen, Flugschulen",
    "sg:phone":"+41 79 311 81 80",
    "sg:postcode":"2900",
    "sg:province":"Jura",
    "wof:name":"Alex Weissbaum Auto-\u00e9cole",
    "wof:placetype":"venue"
},
  "geometry": {"coordinates":[7.0763630867,47.4149398804],"type":"Point"}
}