{
  "type": "Feature",
  "properties": {
    "iso:country":"CH",
    "sg:address":"Alfred Escher-strasse 23 8002 Z\u00fcrich. Postfach 168",
    "sg:city":"Z\u00fcrich",
    "sg:orig_category":"Satzherstellung U Reproduktion",
    "sg:phone":"+41 12803445",
    "sg:postcode":"8027",
    "sg:province":"Z\u00fcrich",
    "wof:name":"Kronenberg Digital Gmbh Fotosatz, Lithos Usw.; Herstellung",
    "wof:placetype":"venue"
},
  "geometry": {"coordinates":[8.5331735611,47.3637275696],"type":"Point"}
}