{
  "type": "Feature",
  "properties": {
    "iso:country":"CH",
    "sg:address":"Obachstrasse 10 4500 Solothurn. Postfach",
    "sg:city":"Solothurn",
    "sg:orig_category":"Wirtschaftspr\u00fcfung, Steuerberatung U Treuhand",
    "sg:phone":"+41 32 622 27 22",
    "sg:postcode":"4500",
    "sg:province":"Solothurn",
    "wof:name":"B\u00fcrgschaftsgenossenschaft Des Solothurnischen Gewerbes Bsg",
    "wof:placetype":"venue"
},
  "geometry": {"coordinates":[7.5323500633,47.2053794861],"type":"Point"}
}