{
  "type": "Feature",
  "properties": {
    "iso:country":"CH",
    "sg:address":"Bleiche 335",
    "sg:city":"Trogen",
    "sg:orig_category":"G\u00fcterbef\u00f6rderung im Strassenverkehr",
    "sg:phone":"+41 71 868 78 88",
    "sg:postcode":"9043",
    "sg:province":"Appenzell Ausserrhoden",
    "wof:name":"Alder Transporte + Kranarbeiten Ag",
    "wof:placetype":"venue"
},
  "geometry": {"coordinates":[9.4733724594,47.4080352783],"type":"Point"}
}