{
  "type": "Feature",
  "properties": {
    "iso:country":"CH",
    "sg:address":"Trogener Strasse 5",
    "sg:city":"Speicher",
    "sg:classifiers":[
        {
            "category":"Shopping",
            "subcategory":"Pharmacy",
            "type":"Retail Goods"
        }
    ],
    "sg:phone":"+41 71 343 70 30",
    "sg:postcode":"9042",
    "sg:province":"Appenzell Ausserrhoden",
    "sg:tags":[
        "supplement",
        "dietary"
    ],
    "wof:name":"Hans Rentsch Ag",
    "wof:placetype":"venue"
},
  "geometry": {"coordinates":[9.4471054077,47.4077148438],"type":"Point"}
}