{
  "type": "Feature",
  "properties": {
    "iso:country":"CH",
    "sg:address":"Kellerg\u00e4sslein 7",
    "sg:city":"Basel",
    "sg:orig_category":"Unclassifiable Establishments",
    "sg:postcode":"4051",
    "sg:province":"Basel-Stadt",
    "wof:name":"Sonnenwasser Stefan Wisard",
    "wof:placetype":"venue"
},
  "geometry": {"coordinates":[7.5861592293,47.5592041016],"type":"Point"}
}