{
  "type": "Feature",
  "properties": {
    "iso:country":"CH",
    "sg:address":"Hasenberg",
    "sg:city":"Walenstadt",
    "sg:orig_category":"Zimmerei, Dachdeckerei, Bauspenglerei U Abdichtung",
    "sg:phone":"+41 33 755 11 60",
    "sg:postcode":"8880",
    "sg:province":"St. Gallen",
    "wof:name":"Marti Gebr. & Co",
    "wof:placetype":"venue"
},
  "geometry": {"coordinates":[7.2674098015,46.3868637085],"type":"Point"}
}