{
  "type": "Feature",
  "properties": {
    "iso:country":"CH",
    "sg:address":"Bergstrasse 30 8954 Geroldswil. Postfach",
    "sg:city":"Geroldswil",
    "sg:orig_category":"Handelsvermittlung von Textilien, Bekleidung, Schuhen U Lederwaren",
    "sg:postcode":"8954",
    "sg:province":"Z\u00fcrich",
    "wof:name":"Altorfer Rolf",
    "wof:placetype":"venue"
},
  "geometry": {"coordinates":[8.4120111465,47.4256401062],"type":"Point"}
}