{
  "type": "Feature",
  "properties": {
    "iso:country":"CH",
    "sg:address":"Spitalgasse 4 3011 Bern. Postfach",
    "sg:city":"Bern",
    "sg:orig_category":"WIRTSCHAFTSVERB\u00c4NDE WIRTSCHAFTS-& HANDELSF\u00d6RDER",
    "sg:phone":"+41 31 311 62 96",
    "sg:postcode":"3001",
    "sg:province":"Bern",
    "wof:name":"Gesellschaft Zur F\u00f6rderung Der Schweizerischen Wirtschaft",
    "wof:placetype":"venue"
},
  "geometry": {"coordinates":[7.4431920052,46.9482421875],"type":"Point"}
}