{
  "type": "Feature",
  "properties": {
    "iso:country":"CH",
    "sg:address":"Holenstock 1",
    "sg:city":"Einsiedeln",
    "sg:orig_category":"Betrieb von Sportanlagen",
    "sg:postcode":"8840",
    "sg:province":"Schwyz",
    "wof:name":"Sporthalle Eschbach Ag",
    "wof:placetype":"venue"
},
  "geometry": {"coordinates":[8.737219,47.126762],"type":"Point"}
}