{
  "type": "Feature",
  "properties": {
    "iso:country":"CH",
    "sg:address":"Rue Des Alpes 49",
    "sg:city":"Crissier",
    "sg:orig_category":"RESTAURANTS: TEA-ROOMS",
    "sg:postcode":"1023",
    "sg:province":"Vaud",
    "wof:name":"Gianadda Mariella",
    "wof:placetype":"venue"
},
  "geometry": {"coordinates":[6.5800461769,46.5415687561],"type":"Point"}
}