{
  "type": "Feature",
  "properties": {
    "iso:country":"CH",
    "sg:address":"St\u00e4dtchen 7",
    "sg:city":"Aarburg",
    "sg:orig_category":"Detailhandel mit Brillen U anderen Sehhilfen Detailhandel mit Uhren U Schmuck",
    "sg:postcode":"4663",
    "sg:province":"Aargau",
    "wof:name":"Sp\u00f6rri + Co, Optik, Uhren Und Bijouterie",
    "wof:placetype":"venue"
},
  "geometry": {"coordinates":[7.89865,47.32085],"type":"Point"}
}