{
  "type": "Feature",
  "properties": {
    "iso:country":"CH",
    "sg:address":"Reppischtalstrasse 57",
    "sg:city":"Stallikon",
    "sg:orig_category":"Grafikateliers, Design Herstellung von sonstigen Maschinen f\u00fcr bestimmte Verwendung",
    "sg:phone":"+41 17779545",
    "sg:postcode":"8143",
    "sg:province":"Z\u00fcrich",
    "wof:name":"Koller Grafik + Reklamen",
    "wof:placetype":"venue"
},
  "geometry": {"coordinates":[8.4901990891,47.3260612488],"type":"Point"}
}