{
  "type": "Feature",
  "properties": {
    "iso:country":"CH",
    "sg:address":"Neumarktstrasse 52 2503 Biel/bienne. Postfach",
    "sg:city":"Biel/bienne",
    "sg:orig_category":"RESTAURANTS: TEA-ROOMS",
    "sg:postcode":"2503",
    "sg:province":"Bern",
    "wof:name":"Eintracht Biel Gastro Ag",
    "wof:placetype":"venue"
},
  "geometry": {"coordinates":[7.2504057884,47.137966156],"type":"Point"}
}