{
  "type": "Feature",
  "properties": {
    "iso:country":"CH",
    "sg:address":"Rue Des P\u00e2les 17 2900 Porrentruy Case Postale 268",
    "sg:city":"Pruntrut",
    "sg:orig_category":"Herstellung von Ger\u00e4ten der Elektrizit\u00e4tserzeugung, -verteilung u.\u00e4. -Herstellung von elektronischen",
    "sg:phone":"+41 32 466 13 83",
    "sg:postcode":"2900",
    "sg:province":"Jura",
    "wof:name":"Allectronic Sa",
    "wof:placetype":"venue"
},
  "geometry": {"coordinates":[7.0667338371,47.4114646912],"type":"Point"}
}