{
  "type": "Feature",
  "properties": {
    "iso:country":"CH",
    "sg:address":"Mettlenweg 9b",
    "sg:city":"Biel/bienne",
    "sg:orig_category":"Unternehmensberatung",
    "sg:phone":"+41 32 341 58 58",
    "sg:postcode":"2504",
    "sg:province":"Bern",
    "wof:name":"Jean-luc Tten It's Time To I",
    "wof:placetype":"venue"
},
  "geometry": {"coordinates":[7.2751131058,47.1464195251],"type":"Point"}
}