{
  "type": "Feature",
  "properties": {
    "iso:country":"CH",
    "sg:address":"Bachwiesenstrasse 2",
    "sg:city":"Seuzach",
    "sg:orig_category":"Primarschulen",
    "sg:phone":"+41 52 335 20 86",
    "sg:postcode":"8472",
    "sg:province":"Z\u00fcrich",
    "wof:name":"Primarschule In Der Birch",
    "wof:placetype":"venue"
},
  "geometry": {"coordinates":[8.7374076843,47.5348434448],"type":"Point"}
}