{
  "type": "Feature",
  "properties": {
    "iso:country":"CH",
    "sg:address":"Industriestrasse 11 6343 Rotkreuz. Postfach",
    "sg:city":"Rotkreuz",
    "sg:orig_category":"Non-Classified Establishments",
    "sg:phone":"+41 41 798 29 30",
    "sg:postcode":"6343",
    "sg:province":"Zug",
    "wof:name":"Qualito Ag Warenhandel, Bes. Mittels Elektronischer Medien",
    "wof:placetype":"venue"
},
  "geometry": {"coordinates":[8.4310493469,47.1514205933],"type":"Point"}
}