{
  "type": "Feature",
  "properties": {
    "iso:country":"CH",
    "sg:address":"Holderstrasse 19",
    "sg:city":"Basel",
    "sg:orig_category":"G\u00fcterbef\u00f6rderung im Strassenverkehr",
    "sg:phone":"+41 79 248 35 05",
    "sg:postcode":"4057",
    "sg:province":"Basel-Stadt",
    "wof:name":"Roland Jacot Transporte",
    "wof:placetype":"venue"
},
  "geometry": {"coordinates":[7.5906510353,47.5761795044],"type":"Point"}
}