{
  "type": "Feature",
  "properties": {
    "iso:country":"CH",
    "sg:address":"Thurgauerstrasse 76",
    "sg:city":"Z\u00fcrich",
    "sg:orig_category":"Elektroinstallation",
    "sg:phone":"+41 13003100",
    "sg:postcode":"8050",
    "sg:province":"Z\u00fcrich",
    "wof:name":"Steiner + F\u00e4h",
    "wof:placetype":"venue"
},
  "geometry": {"coordinates":[8.5544576645,47.4172439575],"type":"Point"}
}