{
  "type": "Feature",
  "properties": {
    "iso:country":"CH",
    "sg:address":"Stockerstrasse 47",
    "sg:city":"Horgen",
    "sg:orig_category":"Selbst\u00e4ndige bildende K\u00fcnstler",
    "sg:phone":"+41 79 610 44 17",
    "sg:postcode":"8810",
    "sg:province":"Z\u00fcrich",
    "wof:name":"Benjamin Margelisch Bildhauer-atelier",
    "wof:placetype":"venue"
},
  "geometry": {"coordinates":[8.5898675919,47.2612915039],"type":"Point"}
}