{
  "type": "Feature",
  "properties": {
    "iso:country":"CH",
    "sg:address":"Neuhardstrasse 27",
    "sg:city":"Olten",
    "sg:orig_category":"Wirtschaftspr\u00fcfung, Steuerberatung U Treuhand",
    "sg:postcode":"4600",
    "sg:province":"Solothurn",
    "wof:name":"Kissling-consulting",
    "wof:placetype":"venue"
},
  "geometry": {"coordinates":[7.9097242355,47.3497238159],"type":"Point"}
}