{
  "type": "Feature",
  "properties": {
    "iso:country":"CH",
    "sg:address":"Landoltstrasse 3 8032 Z\u00fcrich. Postfach 8032 Z\u00fcrich",
    "sg:city":"Zust",
    "sg:orig_category":"Werbegrafikateliers",
    "sg:phone":"+41 12504717",
    "sg:postcode":"32",
    "wof:name":"Witzig Kommunikationsgestaltung Gmbh",
    "wof:placetype":"venue"
},
  "geometry": {"coordinates":[8.5502233505,47.3825378418],"type":"Point"}
}