{
  "type": "Feature",
  "properties": {
    "iso:country":"CH",
    "sg:address":"Im Dreispitz 2",
    "sg:city":"Glattbrugg",
    "sg:orig_category":"Druck ohne Zeitungsdruck",
    "sg:postcode":"8152",
    "sg:province":"Z\u00fcrich",
    "wof:name":"Pulfer Eric.",
    "wof:placetype":"venue"
},
  "geometry": {"coordinates":[6.5110449791,46.6563453674],"type":"Point"}
}