{
  "type": "Feature",
  "properties": {
    "iso:country":"CH",
    "sg:address":"Viale Cattori 11",
    "sg:city":"Paradiso",
    "sg:orig_category":"Non-Classified Establishments",
    "sg:postcode":"6900",
    "sg:province":"Ticino",
    "wof:name":"Prada Holding B.v.swiss Branch",
    "wof:placetype":"venue"
},
  "geometry": {"coordinates":[8.9440021515,45.9921798706],"type":"Point"}
}