{
  "type": "Feature",
  "properties": {
    "iso:country":"CH",
    "sg:address":"Route Principale 2d",
    "sg:city":"Villeret",
    "sg:orig_category":"Unclassifiable Establishments",
    "sg:postcode":"2613",
    "sg:province":"Bern",
    "wof:name":"O. Schmocker S\u00e0rl",
    "wof:placetype":"venue"
},
  "geometry": {"coordinates":[7.0210652351,47.1591033936],"type":"Point"}
}