{
  "type": "Feature",
  "properties": {
    "iso:country":"CH",
    "sg:address":"Lengwiler Strasse 17",
    "sg:city":"Bottighofen",
    "sg:orig_category":"Allgemeiner Hoch U Tiefbau Erdbewegungsarbeiten",
    "sg:phone":"+41 71 688 48 70",
    "sg:postcode":"8598",
    "sg:province":"Thurgau",
    "wof:name":"Hartmann Hanspeter",
    "wof:placetype":"venue"
},
  "geometry": {"coordinates":[9.201044,47.632862],"type":"Point"}
}