{
  "type": "Feature",
  "properties": {
    "iso:country":"CH",
    "sg:address":"Basadingerstrasse 18",
    "sg:city":"Diessenhofen",
    "sg:orig_category":"Unternehmensberatung",
    "sg:phone":"+41 27 934 19 17",
    "sg:postcode":"8253",
    "sg:province":"Thurgau",
    "wof:name":"Felchlin M.n. Consulting",
    "wof:placetype":"venue"
},
  "geometry": {"coordinates":[8.8542575836,47.2888031006],"type":"Point"}
}