{
  "type": "Feature",
  "properties": {
    "iso:country":"CH",
    "sg:address":"Bertastrasse 6",
    "sg:city":"Uster",
    "sg:orig_category":"Sonstige Aktivit\u00e4ten der nicht-\u00e4rztlichen Medizinalberufe",
    "sg:phone":"+41 26 496 26 20",
    "sg:postcode":"8610",
    "sg:province":"Z\u00fcrich",
    "wof:name":"Bruno Tr\u00f6ller Akupunkt-massage",
    "wof:placetype":"venue"
},
  "geometry": {"coordinates":[7.2483010292,46.8598594666],"type":"Point"}
}