{
  "type": "Feature",
  "properties": {
    "iso:country":"CH",
    "sg:address":"Via Bellinzona 2",
    "sg:city":"Biasca",
    "sg:orig_category":"Fachdetailhandel mit pharmazeutischen Produkten",
    "sg:phone":"+41 91 862 37 35",
    "sg:postcode":"6710",
    "sg:province":"Ticino",
    "wof:name":"Baggi Ivana Farmacia Stazione",
    "wof:placetype":"venue"
},
  "geometry": {"coordinates":[8.9732923508,46.3531761169],"type":"Point"}
}