{
  "type": "Feature",
  "properties": {
    "iso:country":"CH",
    "sg:address":"Rosswiesstrasse 29",
    "sg:city":"Bubikon",
    "sg:orig_category":"Herstellung von sonstigen Werkzeugmaschinen Schlossereien",
    "sg:phone":"+41 26 494 14 54",
    "sg:postcode":"8608",
    "sg:province":"Z\u00fcrich",
    "wof:name":"Herzog Forsttechnik",
    "wof:placetype":"venue"
},
  "geometry": {"coordinates":[7.2517352104,46.7967453003],"type":"Point"}
}