{
  "type": "Feature",
  "properties": {
    "iso:country":"CH",
    "sg:address":"Molini Via Ai",
    "sg:city":"Losone",
    "sg:orig_category":"Herstellung von Mess U Kontrollinstrumenten U vorrichtungen",
    "sg:phone":"+41 91 791 00 23",
    "sg:postcode":"6616",
    "sg:province":"Ticino",
    "wof:name":"Lormatec Di Mauro Lorenzetti",
    "wof:placetype":"venue"
},
  "geometry": {"coordinates":[8.7579011917,46.1639938354],"type":"Point"}
}