{
  "type": "Feature",
  "properties": {
    "iso:country":"CH",
    "sg:address":"Unterer Paletzeyweg 16",
    "sg:city":"Worben",
    "sg:orig_category":"Bauspenglerei Sanit\u00e4r, Heizungs U L\u00fcftungsinstallation",
    "sg:phone":"+41 32 384 49 35",
    "sg:postcode":"3252",
    "sg:province":"Bern",
    "wof:name":"Galli Hermann",
    "wof:placetype":"venue"
},
  "geometry": {"coordinates":[7.29416,47.106724],"type":"Point"}
}