{
  "type": "Feature",
  "properties": {
    "iso:country":"CH",
    "sg:address":"B\u00e4rengasse 10",
    "sg:city":"Z\u00fcrich",
    "sg:orig_category":"Detailhandel mit Damenbekleidung",
    "sg:phone":"+41 12212508",
    "sg:postcode":"8001",
    "sg:province":"Z\u00fcrich",
    "wof:name":"Popken & Co Ulla Popken Mode",
    "wof:placetype":"venue"
},
  "geometry": {"coordinates":[8.537171,47.370022],"type":"Point"}
}