{
  "type": "Feature",
  "properties": {
    "iso:country":"CH",
    "sg:address":"Route De Condoz 8",
    "sg:city":"Villars-sur-gl\u00e2ne",
    "sg:orig_category":"Grosshandel mit Milch, Milcherzeugnissen, Eiern, Speise\u00f6len U Nahrungsfetten Sonstiger Fachdetailhan",
    "sg:phone":"+41 26 402 20 02",
    "sg:postcode":"1752",
    "sg:province":"Fribourg",
    "wof:name":"F. Macheret Sa",
    "wof:placetype":"venue"
},
  "geometry": {"coordinates":[7.1227831841,46.7866668701],"type":"Point"}
}