{
  "type": "Feature",
  "properties": {
    "iso:country":"CH",
    "sg:address":"Rue De L'eglise 7 1956 St-pierre-clages. Postfach",
    "sg:city":"St-pierre-clages",
    "sg:orig_category":"Grosshandel mit Getr\u00e4nken",
    "sg:postcode":"1956",
    "wof:name":"Cave Du Prieur\u00e9, Pont Antoine & Fils Sa Cave Et Commerce De Vins",
    "wof:placetype":"venue"
},
  "geometry": {"coordinates":[-109.8162078857,48.2440681458],"type":"Point"}
}