{
  "type": "Feature",
  "properties": {
    "iso:country":"CH",
    "sg:address":"Heideweg 13",
    "sg:city":"Biel/bienne",
    "sg:orig_category":"Resistor Components",
    "sg:phone":"+41 32 365 27 29",
    "sg:postcode":"2503",
    "sg:province":"Bern",
    "wof:name":"Digitool Heinrich Sch\u00f6chlin",
    "wof:placetype":"venue"
},
  "geometry": {"coordinates":[7.2542448044,47.1270599365],"type":"Point"}
}