{
  "type": "Feature",
  "properties": {
    "addr:full":"1983 Evol\u00e8ne Valais 1983",
    "addr:postcode":"1983;1983",
    "iso:country":"CH",
    "sg:address":"1983",
    "sg:city":"Evol\u00e8ne",
    "sg:classifiers":[
        {
            "category":"Bars & Pubs",
            "type":"Food & Drink"
        }
    ],
    "sg:phone":"+41 27 283 12 02",
    "sg:postcode":"1983",
    "sg:province":"Valais",
    "sg:tags":[
        "restaurant"
    ],
    "wof:name":"Taverne Evol\u00e9narde & Bar",
    "wof:placetype":"venue"
},
  "geometry": {"coordinates":[7.496159,46.114475],"type":"Point"}
}