{
  "type": "Feature",
  "properties": {
    "iso:country":"CH",
    "sg:address":"Rue Du Jura 22",
    "sg:city":"Gland",
    "sg:orig_category":"Erbringung von Dienstleistungen f\u00fcr Unternehmen",
    "sg:phone":"+41 22 364 28 66",
    "sg:postcode":"1196",
    "sg:province":"Vaud",
    "wof:name":"W\u00e4lti Claude-alain",
    "wof:placetype":"venue"
},
  "geometry": {"coordinates":[6.2623538971,46.425365448],"type":"Point"}
}