{
  "type": "Feature",
  "properties": {
    "iso:country":"CH",
    "sg:address":"Chr\u00fczmatte 20 6247 Sch\u00f6tz. Postfach 60",
    "sg:city":"Sch\u00f6tz",
    "sg:orig_category":"Herstellung von Teppichen Verlegen von Fussboden",
    "sg:phone":"+41 81 422 26 90",
    "sg:postcode":"6247",
    "sg:province":"Luzern",
    "wof:name":"Schmid Gebr. Ag Klosters",
    "wof:placetype":"venue"
},
  "geometry": {"coordinates":[9.8656625748,46.8862533569],"type":"Point"}
}