{
  "type": "Feature",
  "properties": {
    "iso:country":"CH",
    "sg:address":"Bankstrasse 14",
    "sg:city":"Weinfelden",
    "sg:orig_category":"Vorschulen, Kinderg\u00e4rten",
    "sg:phone":"+41 71 622 80 33",
    "sg:postcode":"8570",
    "sg:province":"Thurgau",
    "wof:name":"Kindergarten",
    "wof:placetype":"venue"
},
  "geometry": {"coordinates":[9.1056985855,47.5693969727],"type":"Point"}
}