{
  "type": "Feature",
  "properties": {
    "iso:country":"CH",
    "sg:address":"Langrietstrasse 7",
    "sg:city":"Neuhausen",
    "sg:orig_category":"Sportvereine Ski",
    "sg:phone":"+41 52 672 40 97",
    "sg:postcode":"8212",
    "sg:province":"Schaffhausen",
    "wof:name":"Skiclub Schaffhausen",
    "wof:placetype":"venue"
},
  "geometry": {"coordinates":[8.6014537811,47.6781806946],"type":"Point"}
}