{
  "type": "Feature",
  "properties": {
    "iso:country":"CH",
    "sg:address":"Listrighalde 17",
    "sg:city":"Emmenbr\u00fccke",
    "sg:orig_category":"Non-Classified Establishments",
    "sg:postcode":"6020",
    "sg:province":"Luzern",
    "wof:name":"Salto Gmbh Alu-gel\u00e4nder",
    "wof:placetype":"venue"
},
  "geometry": {"coordinates":[8.2672424316,47.0771446228],"type":"Point"}
}