{
  "type": "Feature",
  "properties": {
    "iso:country":"CH",
    "sg:address":"Calandastrasse 4 7000 Chur. Postfach",
    "sg:city":"Chur",
    "sg:orig_category":"Bibliotheken U Archive Organisationen der Wohlfahrtspflege",
    "sg:phone":"+41 81 353 12 01",
    "sg:postcode":"7004",
    "sg:province":"Graubunden",
    "wof:name":"Pro Juventute",
    "wof:placetype":"venue"
},
  "geometry": {"coordinates":[9.529674,46.855652],"type":"Point"}
}