{
  "type": "Feature",
  "properties": {
    "iso:country":"CH",
    "sg:address":"Chemin De Jussy-l'eglise 1",
    "sg:city":"Jussy",
    "sg:orig_category":"Detailhandel mit Waren verschiedener Art, Hauptrichtung Nahrungsmittel",
    "sg:postcode":"1254",
    "sg:province":"Gen\u00e8ve",
    "wof:name":"Syndicat Agricole De La Chaux",
    "wof:placetype":"venue"
},
  "geometry": {"coordinates":[6.4778800011,46.6214408875],"type":"Point"}
}