{
  "type": "Feature",
  "properties": {
    "iso:country":"CH",
    "sg:address":"Zur Blumenau",
    "sg:city":"Aadorf",
    "sg:orig_category":"Sportvereine Sch\u00fctzen",
    "sg:phone":"+41 33 251 17 47",
    "sg:postcode":"8355",
    "sg:province":"Thurgau",
    "wof:name":"Sch\u00fctzenges.meiersmaad",
    "wof:placetype":"venue"
},
  "geometry": {"coordinates":[7.753059864,46.7361297607],"type":"Point"}
}