{
  "type": "Feature",
  "properties": {
    "iso:country":"CH",
    "sg:address":"Route De La Gl\u00e2ne 119",
    "sg:city":"Villars-sur-gl\u00e2ne",
    "sg:classifiers":[
        {
            "category":"Travel",
            "subcategory":"Hotels & Motels",
            "type":"Entertainment"
        }
    ],
    "sg:phone":"+41 32 861 26 98",
    "sg:postcode":"1752",
    "sg:province":"Fribourg",
    "sg:tags":[
        "hotels",
        "mit",
        "restaurant"
    ],
    "wof:name":"H\u00f4tel Du Moulin",
    "wof:placetype":"venue"
},
  "geometry": {"coordinates":[6.5715141296,46.908290863],"type":"Point"}
}