{
  "type": "Feature",
  "properties": {
    "iso:country":"CH",
    "sg:address":"Route De La Gemmi 81",
    "sg:city":"Sierre",
    "sg:orig_category":"Bestattungswesen",
    "sg:phone":"+41 27 455 19 73",
    "sg:postcode":"3960",
    "sg:province":"Valais",
    "wof:name":"F\u00e9lix Eggs Et Fils Sa",
    "wof:placetype":"venue"
},
  "geometry": {"coordinates":[7.557053,46.300819],"type":"Point"}
}