{
  "type": "Feature",
  "properties": {
    "addr:full":"Rue De Champr\u00e9veyres 1 Neuch\u00e2tel Neuch\u00e2tel 2000",
    "addr:housenumber":"1",
    "addr:postcode":"2000",
    "addr:street":"Rue De Champre\u0301Veyres",
    "iso:country":"CH",
    "sg:address":"Rue De Champr\u00e9veyres 1",
    "sg:city":"Neuch\u00e2tel",
    "sg:orig_category":"Detailhandel mit Blumen U Pflanzen",
    "sg:postcode":"2000",
    "sg:province":"Neuch\u00e2tel",
    "wof:name":"Flore Design, Schmid Yves",
    "wof:placetype":"venue"
},
  "geometry": {"coordinates":[6.961617,47.005539],"type":"Point"}
}