{
  "type": "Feature",
  "properties": {
    "iso:country":"CH",
    "sg:address":"Churerstrasse 52 8852 Altendorf. Postfach",
    "sg:city":"Altendorf",
    "sg:orig_category":"Architektur U Ingenieurb\u00fcros Laboratorien biologisch",
    "sg:phone":"+41 55 442 62 24",
    "sg:postcode":"8852",
    "sg:province":"Schwyz",
    "wof:name":"Institut F\u00fcr Erdstrahlen Und Elektrosmog Schnellmann Remo",
    "wof:placetype":"venue"
},
  "geometry": {"coordinates":[8.837302,47.190083],"type":"Point"}
}