{
  "type": "Feature",
  "properties": {
    "iso:country":"CH",
    "sg:address":"Bahnhofstrasse 17",
    "sg:city":"Aarau",
    "sg:orig_category":"Detailhandel mit Brillen U anderen Sehhilfen Detailhandel mit medizinischen U orthop\u00e4dischen Artikel",
    "sg:phone":"+41 62 824 80 78",
    "sg:postcode":"5000",
    "sg:province":"Aargau",
    "wof:name":"Moosberger Walter, H\u00f6rger\u00e4teakustiker, Boniswil",
    "wof:placetype":"venue"
},
  "geometry": {"coordinates":[8.046291,47.390965],"type":"Point"}
}