{
  "type": "Feature",
  "properties": {
    "iso:country":"CH",
    "sg:address":"6593",
    "sg:city":"Cadenazzo",
    "sg:orig_category":"Forschung U Entwicklung Obstbau",
    "sg:phone":"+41 91 850 20 30",
    "sg:postcode":"6593",
    "sg:province":"Ticino",
    "wof:name":"Stazioni Federali Di Ricerche Agronomiche Centro Cadenazzo",
    "wof:placetype":"venue"
},
  "geometry": {"coordinates":[8.9563798904,46.1506309509],"type":"Point"}
}