{
  "type": "Feature",
  "properties": {
    "iso:country":"CH",
    "sg:address":"Rue Des Monts 2",
    "sg:city":"Cernier",
    "sg:orig_category":"Herstellung von Konstruktionsteilen, Fertigbauteilen U Ausbauelementen aus Holz",
    "sg:phone":"+41 79 310 72 43",
    "sg:postcode":"2053",
    "sg:province":"Neuch\u00e2tel",
    "wof:name":"Menuiserie-eb\u00e9nisterie, Jeanneret & Mettraux",
    "wof:placetype":"venue"
},
  "geometry": {"coordinates":[6.8964600563,47.0584869385],"type":"Point"}
}