{
  "type": "Feature",
  "properties": {
    "iso:country":"CH",
    "sg:address":"9443",
    "sg:city":"Widnau",
    "sg:orig_category":"Schulpflegen",
    "sg:postcode":"9443",
    "sg:province":"St. Gallen",
    "wof:name":"Schulrat Der Gemeinde Wiesen",
    "wof:placetype":"venue"
},
  "geometry": {"coordinates":[9.7150802612,46.704498291],"type":"Point"}
}