{
  "type": "Feature",
  "properties": {
    "iso:country":"CH",
    "sg:address":"Furkastrasse",
    "sg:city":"Lax",
    "sg:orig_category":"Sonstiges Versicherungsgewerbe",
    "sg:phone":"+41 27 957 10 63",
    "sg:postcode":"3994",
    "sg:province":"Valais",
    "wof:name":"Krankenkasse Des Saastales",
    "wof:placetype":"venue"
},
  "geometry": {"coordinates":[7.9367241859,46.1232452393],"type":"Point"}
}