{
  "type": "Feature",
  "properties": {
    "iso:country":"CH",
    "sg:address":"Via Cabione 11f",
    "sg:city":"Lugano",
    "sg:orig_category":"Sonstiger Fachdetailhandel mit Nahrungsmitteln, Getr\u00e4nken U Tabak in Verkaufsr\u00e4umen",
    "sg:phone":"+41 32 931 52 05",
    "sg:postcode":"6900",
    "sg:province":"Ticino",
    "wof:name":"D. Perret-gentil",
    "wof:placetype":"venue"
},
  "geometry": {"coordinates":[6.8148818016,47.0494384766],"type":"Point"}
}