{
  "type": "Feature",
  "properties": {
    "addr:full":"Oltingerstrasse 27 Basel Basel-Stadt 4055",
    "addr:housenumber":"27",
    "addr:postcode":"4055",
    "addr:street":"Oltingerstrasse",
    "iso:country":"CH",
    "sg:address":"Oltingerstrasse 27",
    "sg:city":"Basel",
    "sg:orig_category":"Architekturb\u00fcros",
    "sg:phone":"+41 61 312 56 93",
    "sg:postcode":"4055",
    "sg:province":"Basel-Stadt",
    "wof:name":"Ren\u00e9 Sch\u00e4rer Architekturb\u00fcro",
    "wof:placetype":"venue"
},
  "geometry": {"coordinates":[7.561832,47.566757],"type":"Point"}
}