{
  "type": "Feature",
  "properties": {
    "iso:country":"CH",
    "sg:address":"Route Du Marchairuz",
    "sg:city":"Bi\u00e8re",
    "sg:orig_category":"Detailhandel mit Fleisch U Fleischwaren",
    "sg:phone":"+41 21 809 50 20",
    "sg:postcode":"1145",
    "sg:province":"Vaud",
    "wof:name":"Boucherie Gomez Miguel",
    "wof:placetype":"venue"
},
  "geometry": {"coordinates":[6.3322110176,46.5387496948],"type":"Point"}
}