{
  "type": "Feature",
  "properties": {
    "iso:country":"CH",
    "sg:address":"St\u00f6ckackerstrasse 50 3027 Bern. Postfach",
    "sg:city":"Bern",
    "sg:orig_category":"Landesverteidigung, Sozialversicherung \u00d6ffentliche Verwaltung",
    "sg:phone":"+41 31 992 03 51",
    "sg:postcode":"3030",
    "sg:province":"Bern",
    "wof:name":"Automobilwerkst\u00e4tte Ptt",
    "wof:placetype":"venue"
},
  "geometry": {"coordinates":[7.403231144,46.9476013184],"type":"Point"}
}