{
  "type": "Feature",
  "properties": {
    "iso:country":"CH",
    "sg:address":"La Cure",
    "sg:city":"Saubraz",
    "sg:orig_category":"Herstellung von Ger\u00e4ten der Elektrizit\u00e4tserzeugung, -verteilung u.\u00e4. -Herstellung von elektronischen",
    "sg:phone":"+41 21 828 38 26",
    "sg:postcode":"1189",
    "sg:province":"Vaud",
    "wof:name":"Hrc Technologie Sa",
    "wof:placetype":"venue"
},
  "geometry": {"coordinates":[6.3310799599,46.516960144],"type":"Point"}
}