{
  "type": "Feature",
  "properties": {
    "iso:country":"CH",
    "sg:address":"Menznauerstrasse 17",
    "sg:city":"Willisau",
    "sg:classifiers":[
        {
            "category":"Manufacturing",
            "subcategory":"Wood Products",
            "type":"Manufacturing & Wholesale Goods"
        }
    ],
    "sg:phone":"+41 41 970 16 16",
    "sg:postcode":"6130",
    "sg:province":"Luzern",
    "sg:tags":[
        "laminated"
    ],
    "wof:name":"Gebr. K\u00fcng Ag",
    "wof:placetype":"venue"
},
  "geometry": {"coordinates":[8.0008859634,47.1187667847],"type":"Point"}
}