{
  "type": "Feature",
  "properties": {
    "iso:country":"CH",
    "sg:address":"Elsterweg 5a",
    "sg:city":"Thun",
    "sg:orig_category":"Herstellung von Werkzeugen",
    "sg:phone":"+41 33 222 28 23",
    "sg:postcode":"3600",
    "sg:province":"Bern",
    "wof:name":"Diamantschleiftechnik Jirenec Helmut",
    "wof:placetype":"venue"
},
  "geometry": {"coordinates":[7.6035509109,46.7677574158],"type":"Point"}
}