{
  "type": "Feature",
  "properties": {
    "iso:country":"CH",
    "sg:address":"Allmendstrasse 39",
    "sg:city":"Gunzgen",
    "sg:orig_category":"Pulvermetallurgie Schmieden, Pressen, Stanzen U Profilwalzen von Metallen",
    "sg:phone":"+41 62 216 42 63",
    "sg:postcode":"4617",
    "sg:province":"Solothurn",
    "wof:name":"Hans B\u00fchrer Stanzformenbau",
    "wof:placetype":"venue"
},
  "geometry": {"coordinates":[7.8356947899,47.3128051758],"type":"Point"}
}