{
  "type": "Feature",
  "properties": {
    "addr:full":"Friedbergstrasse 1 9512 Rossr\u00fcti. Postfach Rossr\u00fcti St. Gallen 9512",
    "addr:housenumber":"1",
    "addr:postcode":"9512;9512",
    "addr:street":"Friedbergstrasse;Postfach Rossrueti",
    "iso:country":"CH",
    "sg:address":"Friedbergstrasse 1 9512 Rossr\u00fcti. Postfach",
    "sg:city":"Rossr\u00fcti",
    "sg:orig_category":"Architektur U Ingenieurb\u00fcros",
    "sg:postcode":"9512",
    "sg:province":"St. Gallen",
    "wof:name":"Scherrer + Scherrer Ingenieurb\u00fcro Gmbh",
    "wof:placetype":"venue"
},
  "geometry": {"coordinates":[9.05809,47.474461],"type":"Point"}
}