{
  "type": "Feature",
  "properties": {
    "iso:country":"CH",
    "sg:address":"Kreuzbergstrasse 8",
    "sg:city":"Dagmersellen",
    "sg:orig_category":"Stukkateurgewerbe, Gipserei U Verputzerei",
    "sg:phone":"+41 62 756 10 45",
    "sg:postcode":"6252",
    "sg:province":"Luzern",
    "wof:name":"Narciso Melchiorri Ag Gipsergesch\u00e4ft",
    "wof:placetype":"venue"
},
  "geometry": {"coordinates":[7.9891300201,47.2149581909],"type":"Point"}
}