{
  "type": "Feature",
  "properties": {
    "iso:country":"CH",
    "sg:address":"Rue Centrale 9 1095 Ch\u00e2telard-lutry Case Postale 368",
    "sg:city":"Ch\u00e2telard-lutry",
    "sg:orig_category":"Architektur U Ingenieurb\u00fcros Architekturb\u00fcros",
    "sg:phone":"+41 21 323 91 31",
    "sg:postcode":"1095",
    "sg:province":"Vaud",
    "wof:name":"Atelier D'architecture Wuarin M. Et Hintermeister J. S\u00e0rl",
    "wof:placetype":"venue"
},
  "geometry": {"coordinates":[6.685757,46.503281],"type":"Point"}
}