{
  "type": "Feature",
  "properties": {
    "iso:country":"CH",
    "sg:address":"Chamerstrasse 50",
    "sg:city":"Zug",
    "sg:orig_category":"Architektur U Ingenieurb\u00fcros",
    "sg:postcode":"6300",
    "sg:province":"Zug",
    "wof:name":"Perm Motor Company Ag",
    "wof:placetype":"venue"
},
  "geometry": {"coordinates":[8.505776,47.173832],"type":"Point"}
}