{
  "type": "Feature",
  "properties": {
    "iso:country":"CH",
    "sg:address":"Viale Papio 10",
    "sg:city":"Ascona",
    "sg:orig_category":"Polizei",
    "sg:phone":"+41 91 792 13 13",
    "sg:postcode":"6612",
    "sg:province":"Ticino",
    "wof:name":"Polizia Comunale",
    "wof:placetype":"venue"
},
  "geometry": {"coordinates":[8.7706947327,46.1556587219],"type":"Point"}
}