{
  "type": "Feature",
  "properties": {
    "iso:country":"CH",
    "sg:address":"6644",
    "sg:city":"Orselina",
    "sg:orig_category":"Reiseb\u00fcros U Reiseveranstalter",
    "sg:phone":"+41 91 735 30 30",
    "sg:postcode":"6644",
    "sg:province":"Ticino",
    "wof:name":"Cardada Impianti Turistici Sa",
    "wof:placetype":"venue"
},
  "geometry": {"coordinates":[8.7967700958,46.1801109314],"type":"Point"}
}