{
  "type": "Feature",
  "properties": {
    "iso:country":"CH",
    "sg:address":"Mellingerstrasse 22",
    "sg:city":"Baden",
    "sg:orig_category":"Bau U Wohngenossenschaften",
    "sg:phone":"+41 17804084",
    "sg:postcode":"5400",
    "sg:province":"Aargau",
    "wof:name":"Baugen.quellenstrasse",
    "wof:placetype":"venue"
},
  "geometry": {"coordinates":[8.655665,47.23851],"type":"Point"}
}