{
  "type": "Feature",
  "properties": {
    "iso:country":"CH",
    "sg:address":"Fribourg Route De 14",
    "sg:city":"Marly",
    "sg:orig_category":"Erbringung von Dienstleistungen f\u00fcr Unternehmen",
    "sg:postcode":"1723",
    "sg:province":"Fribourg",
    "wof:name":"Moder Gian Peider",
    "wof:placetype":"venue"
},
  "geometry": {"coordinates":[8.9789562225,46.1534881592],"type":"Point"}
}