{
  "type": "Feature",
  "properties": {
    "iso:country":"CH",
    "sg:address":"Glattalstrasse 127",
    "sg:city":"Z\u00fcrich",
    "sg:orig_category":"Wartung U Reparatur von B\u00fcromaschinen, Datenverarbeitungsger\u00e4ten U einrichtungen",
    "sg:phone":"+41 13031434",
    "sg:postcode":"8052",
    "sg:province":"Z\u00fcrich",
    "wof:name":"Erwin Heim Computer Service Heim",
    "wof:placetype":"venue"
},
  "geometry": {"coordinates":[8.5444774628,47.4298324585],"type":"Point"}
}