{
  "type": "Feature",
  "properties": {
    "iso:country":"CH",
    "sg:address":"Rietstrasse 15",
    "sg:city":"D\u00e4llikon",
    "sg:orig_category":"Herstellung von Metallkonstruktionen",
    "sg:phone":"+41 18450020",
    "sg:postcode":"8108",
    "sg:province":"Z\u00fcrich",
    "wof:name":"Werner Patrick",
    "wof:placetype":"venue"
},
  "geometry": {"coordinates":[8.4310894012,47.4480247498],"type":"Point"}
}