{
  "type": "Feature",
  "properties": {
    "iso:country":"CH",
    "sg:address":"Litternaring 12",
    "sg:city":"Visp",
    "sg:orig_category":"Detektivb\u00fcros U \u00dcberwachung",
    "sg:phone":"+41 61 403 97 77",
    "sg:postcode":"3930",
    "sg:province":"Valais",
    "wof:name":"Professional Security Design, Gr\u00fcninger A.",
    "wof:placetype":"venue"
},
  "geometry": {"coordinates":[7.5626268387,47.5098991394],"type":"Point"}
}