{
  "type": "Feature",
  "properties": {
    "iso:country":"CH",
    "sg:address":"Hinterbergstrasse 107",
    "sg:city":"Volketswil",
    "sg:orig_category":"Wirtschaftspr\u00fcfung, Steuerberatung U Treuhand",
    "sg:postcode":"8604",
    "sg:province":"Z\u00fcrich",
    "wof:name":"Zlauwinen Treuhand Gmbh",
    "wof:placetype":"venue"
},
  "geometry": {"coordinates":[8.6978549957,47.391242981],"type":"Point"}
}