{
  "type": "Feature",
  "properties": {
    "iso:country":"CH",
    "sg:address":"Bifangstrasse 24 5022 Rombach. Postfach",
    "sg:city":"Rombach",
    "sg:orig_category":"Fachdetailhandel in Verkaufsr\u00e4umen",
    "sg:postcode":"5022",
    "sg:province":"Aargau",
    "wof:name":"Almu Import-export Oruc Rafet",
    "wof:placetype":"venue"
},
  "geometry": {"coordinates":[8.0439729691,47.4026985168],"type":"Point"}
}