{
  "type": "Feature",
  "properties": {
    "iso:country":"CH",
    "sg:address":"Via Locarno",
    "sg:city":"Ascona",
    "sg:orig_category":"Vermietung von Automobilen",
    "sg:phone":"+41 91 791 44 55",
    "sg:postcode":"6612",
    "sg:province":"Ticino",
    "wof:name":"Avis-autonoleggio Sa",
    "wof:placetype":"venue"
},
  "geometry": {"coordinates":[8.7699813843,46.157283783],"type":"Point"}
}