{
  "type": "Feature",
  "properties": {
    "iso:country":"CH",
    "sg:address":"Rue Du Mont-blanc 7 1201 Gen\u00e8ve Case Postale",
    "sg:city":"Gen\u00e8ve",
    "sg:orig_category":"G\u00fcterbef\u00f6rderung im Strassenverkehr",
    "sg:phone":"+41 22 341 38 20",
    "sg:postcode":"1201",
    "sg:province":"Gen\u00e8ve",
    "wof:name":"Ermefer Sa",
    "wof:placetype":"venue"
},
  "geometry": {"coordinates":[6.145963192,46.2077217102],"type":"Point"}
}