{
  "type": "Feature",
  "properties": {
    "iso:country":"CH",
    "sg:address":"Seilerstrasse 9 3011 Bern. Postfach",
    "sg:city":"Bern",
    "sg:orig_category":"Non-Classified Establishments",
    "sg:postcode":"3005",
    "sg:province":"Bern",
    "wof:name":"Swiss Immo-team S\u00e0rl",
    "wof:placetype":"venue"
},
  "geometry": {"coordinates":[6.6915769577,46.8376922607],"type":"Point"}
}