{
  "type": "Feature",
  "properties": {
    "iso:country":"CH",
    "sg:address":"Vicolo Valscesa 4",
    "sg:city":"Arbedo",
    "sg:orig_category":"Unclassifiable Establishments",
    "sg:postcode":"6517",
    "sg:province":"Ticino",
    "wof:name":"Enrico Morali Sagl Impianti Sanitari",
    "wof:placetype":"venue"
},
  "geometry": {"coordinates":[9.0459117889,46.2165718079],"type":"Point"}
}