{
  "type": "Feature",
  "properties": {
    "iso:country":"CH",
    "sg:city":"Kallern",
    "sg:classifiers":[
        {
            "category":"Banks & Credit Unions",
            "subcategory":"Bank",
            "type":"Services"
        }
    ],
    "sg:phone":"+41 4157461375",
    "sg:postcode":"5625",
    "sg:province":"Aargau",
    "wof:name":"Neue Aargauer Bank",
    "wof:placetype":"venue"
},
  "geometry": {"coordinates":[8.294955,47.317726],"type":"Point"}
}