{
  "type": "Feature",
  "properties": {
    "iso:country":"CH",
    "sg:address":"Moulin-du-choc",
    "sg:city":"Romanel-sur-morges",
    "sg:orig_category":"Mechanische Werkst\u00e4tten",
    "sg:phone":"+41 79 621 91 87",
    "sg:postcode":"1122",
    "sg:province":"Vaud",
    "wof:name":"Smp \u00e9lectrom\u00e9canique",
    "wof:placetype":"venue"
},
  "geometry": {"coordinates":[6.5264410973,46.561340332],"type":"Point"}
}