{
  "type": "Feature",
  "properties": {
    "iso:country":"CH",
    "sg:address":"Grand Rue 52",
    "sg:city":"Montreux",
    "sg:orig_category":"Fachdetailhandel in Verkaufsr\u00e4umen",
    "sg:postcode":"1820",
    "sg:province":"Vaud",
    "wof:name":"H\u00fcttinger J\u00fcrg",
    "wof:placetype":"venue"
},
  "geometry": {"coordinates":[6.910077095,46.4341621399],"type":"Point"}
}