{
  "type": "Feature",
  "properties": {
    "addr:full":"Avenue De Crochetan 2 Monthey Valais 1870",
    "addr:housenumber":"2",
    "addr:postcode":"1870",
    "addr:street":"Avenue De Crochetan",
    "iso:country":"CH",
    "sg:address":"Avenue De Crochetan 2",
    "sg:city":"Monthey",
    "sg:orig_category":"Detailhandel mit Bekleidung Detailhandel mit Damenbekleidung",
    "sg:phone":"+41 32 631 22 85",
    "sg:postcode":"1870",
    "sg:province":"Valais",
    "wof:name":"Transit Boutique",
    "wof:placetype":"venue"
},
  "geometry": {"coordinates":[7.65545,47.234394],"type":"Point"}
}