{
  "type": "Feature",
  "properties": {
    "iso:country":"CH",
    "sg:address":"Avenue Du Moulin 3-5",
    "sg:city":"Morges",
    "sg:orig_category":"Architektur U Ingenieurb\u00fcros",
    "sg:phone":"+41 55 282 48 00",
    "sg:postcode":"1110",
    "sg:province":"Vaud",
    "wof:name":"Faisst + Partner Ag",
    "wof:placetype":"venue"
},
  "geometry": {"coordinates":[8.921343,47.240734],"type":"Point"}
}