{
  "type": "Feature",
  "properties": {
    "iso:country":"CH",
    "sg:address":"Kasernenstrasse 4",
    "sg:city":"Herisau",
    "sg:orig_category":"Sanit\u00e4r, Heizungs U L\u00fcftungsinstallation",
    "sg:phone":"+41 71 352 10 62",
    "sg:postcode":"9100",
    "sg:province":"Appenzell Ausserrhoden",
    "wof:name":"Keller Edwin Ag Herisau",
    "wof:placetype":"venue"
},
  "geometry": {"coordinates":[9.280954361,47.3857383728],"type":"Point"}
}