{
  "type": "Feature",
  "properties": {
    "iso:country":"CH",
    "sg:address":"Aeschengraben 12",
    "sg:city":"Basel",
    "sg:classifiers":[
        {
            "category":"Banks & Credit Unions",
            "subcategory":"Bank",
            "type":"Services"
        }
    ],
    "sg:phone":"+41 4161235827",
    "sg:postcode":"4010",
    "sg:province":"Basel-Stadt",
    "wof:name":"Internationale, Genossenschaftsbank Ag",
    "wof:placetype":"venue"
},
  "geometry": {"coordinates":[7.593653,47.55093],"type":"Point"}
}