{
  "type": "Feature",
  "properties": {
    "iso:country":"CH",
    "sg:address":"Via San Gottardo",
    "sg:city":"Taverne",
    "sg:orig_category":"Detailhandel mit Waren verschiedener Art, Hauptrichtung Nahrungsmittel",
    "sg:phone":"+41 91 945 13 85",
    "sg:postcode":"6807",
    "sg:province":"Ticino",
    "wof:name":"Migros Ticino",
    "wof:placetype":"venue"
},
  "geometry": {"coordinates":[8.9354047775,46.0682640076],"type":"Point"}
}