{
  "type": "Feature",
  "properties": {
    "iso:country":"CH",
    "sg:address":"Place De La Gare 1",
    "sg:city":"Nyon",
    "sg:orig_category":"Allgemeinbildende weiterf\u00fchrende Schulen Coiffeursalons",
    "sg:phone":"+41 22 361 41 69",
    "sg:postcode":"1260",
    "sg:province":"Vaud",
    "wof:name":"Victoria Varidel Coiffure Romantica",
    "wof:placetype":"venue"
},
  "geometry": {"coordinates":[6.235941,46.383789],"type":"Point"}
}