{
  "type": "Feature",
  "properties": {
    "iso:country":"CH",
    "sg:address":"6746",
    "sg:city":"Lavorgo",
    "sg:orig_category":"Gewinnung von Natursteinen f\u00fcr den Bau Herstellung von sonstigen Produkten aus nichtmetallischen Min",
    "sg:phone":"+41 91 865 11 37",
    "sg:postcode":"6746",
    "sg:province":"Ticino",
    "wof:name":"Maria Berta Industria Del Granito",
    "wof:placetype":"venue"
},
  "geometry": {"coordinates":[8.840929985,46.440448761],"type":"Point"}
}