{
  "type": "Feature",
  "properties": {
    "iso:country":"CH",
    "sg:address":"Seefeldstrasse 7",
    "sg:city":"Z\u00fcrich",
    "sg:orig_category":"Sonstiges Versicherungsgewerbe Unfall U Schadenversicherung",
    "sg:phone":"+41 91 993 11 44",
    "sg:postcode":"8008",
    "sg:province":"Z\u00fcrich",
    "wof:name":"Neptunia Marine Insurance Ltd, Succursale Di Paradiso Ogni Genere Di Assicurazione Nel Ramo Dei Trasporti Part. In Quello Marittimo Ecc",
    "wof:placetype":"venue"
},
  "geometry": {"coordinates":[8.9491043091,45.9908752441],"type":"Point"}
}