{
  "type": "Feature",
  "properties": {
    "addr:full":"8754 Netstal Glarus 8754",
    "addr:housenumber":"8754",
    "addr:postcode":"8754",
    "addr:street":"Netstal Glarus",
    "iso:country":"CH",
    "sg:address":"8754",
    "sg:city":"Netstal",
    "sg:orig_category":"Detailhandel mit Brot, Back U S\u00fcsswaren",
    "sg:phone":"+41 55 640 20 67",
    "sg:postcode":"8754",
    "sg:province":"Glarus",
    "wof:name":"Villiger-bamert J.",
    "wof:placetype":"venue"
},
  "geometry": {"coordinates":[9.0357,47.06609],"type":"Point"}
}