{
  "type": "Feature",
  "properties": {
    "iso:country":"CH",
    "sg:address":"Steinbockstrasse 4",
    "sg:city":"Chur",
    "sg:orig_category":"Gymnastik U Fitnesszentren Saunas, Solarien, Fitnesszentren U \u00e4hnliches",
    "sg:phone":"+41 81 252 90 52",
    "sg:postcode":"7000",
    "sg:province":"Graubunden",
    "wof:name":"City-fit Chur Ag Swiss Training",
    "wof:placetype":"venue"
},
  "geometry": {"coordinates":[9.5294685364,46.8523483276],"type":"Point"}
}