{
  "type": "Feature",
  "properties": {
    "iso:country":"CH",
    "sg:address":"Effingerstrasse 85",
    "sg:city":"Bern",
    "sg:orig_category":"Maler U Glasergewerbe Stukkateurgewerbe, Gipserei U Verputzerei",
    "sg:phone":"+41 79 300 35 16",
    "sg:postcode":"3008",
    "sg:province":"Bern",
    "wof:name":"Rechsteiner Nik Ag",
    "wof:placetype":"venue"
},
  "geometry": {"coordinates":[7.4440221786,46.9582138062],"type":"Point"}
}