{
  "type": "Feature",
  "properties": {
    "iso:country":"CH",
    "sg:address":"Harderstrasse 35 3800 Interlaken. Postfach",
    "sg:city":"Interlaken",
    "sg:orig_category":"Unternehmensberatung",
    "sg:postcode":"3800",
    "sg:province":"Bern",
    "wof:name":"Daxer H. + S. Gmbh Beratung Von Unternehmen Im Giessereibereich Usw.",
    "wof:placetype":"venue"
},
  "geometry": {"coordinates":[7.8555989265,46.6881713867],"type":"Point"}
}