{
  "type": "Feature",
  "properties": {
    "iso:country":"CH",
    "sg:address":"Torgasse 2",
    "sg:city":"Lenzburg",
    "sg:orig_category":"Herstellung von medizinischen U chirurgischen Ger\u00e4ten sowie orthop\u00e4dischen Vorrichtungen",
    "sg:postcode":"5600",
    "sg:province":"Aargau",
    "wof:name":"Dentalie Ag",
    "wof:placetype":"venue"
},
  "geometry": {"coordinates":[8.1787433624,47.3876419067],"type":"Point"}
}