{
  "type": "Feature",
  "properties": {
    "iso:country":"CH",
    "sg:address":"Beim Bahnhof 6312 Steinhausen. Postfach 508",
    "sg:city":"Steinhausen",
    "sg:orig_category":"Handelsvermittlung U Grosshandel Handelsvermittlung U Grosshandel mit Automobilteilen U Zubeh\u00f6r",
    "sg:phone":"+41 41 741 23 69",
    "sg:postcode":"6312",
    "sg:province":"Zug",
    "wof:name":"Wild Handels Ag Auto-ersatzteile",
    "wof:placetype":"venue"
},
  "geometry": {"coordinates":[8.4789571762,47.1931533813],"type":"Point"}
}