{
  "type": "Feature",
  "properties": {
    "iso:country":"CH",
    "sg:address":"Route Du Vieux-moulin 32",
    "sg:city":"Granges-paccot",
    "sg:orig_category":"Bauspenglerei Sanit\u00e4r, Heizungs U L\u00fcftungsinstallation",
    "sg:phone":"+41 26 466 62 65",
    "sg:postcode":"1763",
    "sg:province":"Fribourg",
    "wof:name":"Neuhaus Ch. Installations Sanitaires Sa",
    "wof:placetype":"venue"
},
  "geometry": {"coordinates":[7.14723,46.822422],"type":"Point"}
}