{
  "type": "Feature",
  "properties": {
    "iso:country":"CH",
    "sg:address":"Strada Regina 22",
    "sg:city":"Manno",
    "sg:orig_category":"Werbegrafikateliers",
    "sg:phone":"+41 91 605 47 37",
    "sg:postcode":"6928",
    "sg:province":"Ticino",
    "wof:name":"Daniele Garbarino Studio Grafico",
    "wof:placetype":"venue"
},
  "geometry": {"coordinates":[8.9189462662,46.0346908569],"type":"Point"}
}