{
  "type": "Feature",
  "properties": {
    "addr:full":"Quellenstrasse 4 8134 Adliswil. Postfach Adliswil Z\u00fcrich 8134",
    "addr:housenumber":"4",
    "addr:postcode":"8134 adliswil. postfach;8134",
    "addr:street":"Quellenstrasse",
    "iso:country":"CH",
    "sg:address":"Quellenstrasse 4 8134 Adliswil. Postfach",
    "sg:city":"Adliswil",
    "sg:orig_category":"Betrieb von Taxis",
    "sg:phone":"+41 17092727",
    "sg:postcode":"8134",
    "sg:province":"Z\u00fcrich",
    "wof:name":"Aaa-ace-taxi-kurierzentrale Z\u00fcrich-see Tzs24 Zaric M. & Denic J.",
    "wof:placetype":"venue"
},
  "geometry": {"coordinates":[8.514438,47.319798],"type":"Point"}
}