{
  "type": "Feature",
  "properties": {
    "iso:country":"CH",
    "sg:address":"Rue Des Moulins 21",
    "sg:city":"Yverdon-les-bains",
    "sg:orig_category":"Handel mit Motorr\u00e4dern, Teilen U Zubeh\u00f6r Instandhaltung U Reparatur von Motorr\u00e4dern",
    "sg:phone":"+41 56 633 53 04",
    "sg:postcode":"1400",
    "sg:province":"Vaud",
    "wof:name":"Velos Franz Gebr. Peterhans Ag",
    "wof:placetype":"venue"
},
  "geometry": {"coordinates":[8.3469600677,47.3521118164],"type":"Point"}
}