{
  "type": "Feature",
  "properties": {
    "iso:country":"CH",
    "sg:address":"Rosengartenstrasse 18 9400 Rorschach. Postfach",
    "sg:city":"Rorschach",
    "sg:orig_category":"Detailhandel mit Bekleidung",
    "sg:postcode":"9400",
    "sg:province":"St. Gallen",
    "wof:name":"Outfit Mode Ag",
    "wof:placetype":"venue"
},
  "geometry": {"coordinates":[9.487893,47.472851],"type":"Point"}
}