{
  "type": "Feature",
  "properties": {
    "addr:full":"Rosengartenstrasse 18 9400 Rorschach. Postfach Rorschach St. Gallen 9400",
    "addr:housenumber":"18",
    "addr:postcode":"9400 rorschach. postfach;9400",
    "addr:street":"Rosengartenstrasse",
    "iso:country":"CH",
    "sg:address":"Rosengartenstrasse 18 9400 Rorschach. Postfach",
    "sg:city":"Rorschach",
    "sg:orig_category":"Detailhandel mit Bekleidung",
    "sg:postcode":"9400",
    "sg:province":"St. Gallen",
    "wof:name":"Outfit Mode Ag",
    "wof:placetype":"venue"
},
  "geometry": {"coordinates":[9.487893,47.472851],"type":"Point"}
}