{
  "type": "Feature",
  "properties": {
    "iso:country":"CH",
    "sg:address":"Amriswilerstrasse 61",
    "sg:city":"Weinfelden",
    "sg:orig_category":"Instandhaltung U Reparatur von Automobilen",
    "sg:postcode":"8570",
    "sg:province":"Thurgau",
    "wof:name":"Huber Max",
    "wof:placetype":"venue"
},
  "geometry": {"coordinates":[6.9261350632,46.39818573],"type":"Point"}
}