{
  "type": "Feature",
  "properties": {
    "iso:country":"CH",
    "sg:address":"Landstrasse 130 Busslingen",
    "sg:city":"Remetschwil",
    "sg:orig_category":"Ger\u00fcstbau Sonstiger spezialisierter Hoch U Tiefbau",
    "sg:phone":"+41 79 234 66 35",
    "sg:postcode":"5453",
    "sg:province":"Aargau",
    "wof:name":"Blume + Clerc Ger\u00fcstbau",
    "wof:placetype":"venue"
},
  "geometry": {"coordinates":[8.3271303177,47.4077911377],"type":"Point"}
}