{
  "type": "Feature",
  "properties": {
    "iso:country":"CH",
    "sg:address":"Zandone 6616 Losone. Postfach Caselle Postale 638",
    "sg:city":"Losone",
    "sg:orig_category":"Zimmerei, Dachdeckerei, Bauspenglerei U Abdichtung Zimmerei, Ingenieurholzbau",
    "sg:phone":"+41 22 300 16 28",
    "sg:postcode":"6616",
    "sg:province":"Ticino",
    "wof:name":"Entreprise Couferap Sa",
    "wof:placetype":"venue"
},
  "geometry": {"coordinates":[6.1334619522,46.1801261902],"type":"Point"}
}