{
  "type": "Feature",
  "properties": {
    "iso:country":"CH",
    "sg:address":"Querstrasse 10 8050 Z\u00fcrich. Postfach",
    "sg:city":"Z\u00fcrich",
    "sg:orig_category":"Fachdetailhandel mit pharmazeutischen Produkten",
    "sg:phone":"+41 13118322",
    "sg:postcode":"8050",
    "sg:province":"Z\u00fcrich",
    "wof:name":"Marktplatz-apotheke, Dr. H. + M. H\u00e4mmig",
    "wof:placetype":"venue"
},
  "geometry": {"coordinates":[8.545211792,47.4100227356],"type":"Point"}
}