{
  "type": "Feature",
  "properties": {
    "addr:full":"Seestrasse 291 Horgen Z\u00fcrich 8810",
    "addr:housenumber":"291",
    "addr:postcode":"8810",
    "addr:street":"Seestrasse",
    "iso:country":"CH",
    "sg:address":"Seestrasse 291",
    "sg:city":"Horgen",
    "sg:classifiers":[
        {
            "category":"Government",
            "subcategory":"Fire Station",
            "type":"Public Place"
        }
    ],
    "sg:phone":"+41 17182288",
    "sg:postcode":"8810",
    "sg:province":"Z\u00fcrich",
    "sg:tags":[
        "door"
    ],
    "wof:name":"Bertschinger - Tell Ag",
    "wof:placetype":"venue"
},
  "geometry": {"coordinates":[8.60616,47.25761],"type":"Point"}
}