{
  "type": "Feature",
  "properties": {
    "iso:country":"CH",
    "sg:address":"Rue Du Simplon 1",
    "sg:city":"Vevey",
    "sg:orig_category":"RESTAURANTS: TEA-ROOMS",
    "sg:phone":"+41 21 921 14 13",
    "sg:postcode":"1800",
    "sg:province":"Vaud",
    "wof:name":"Restaurant Des Trois Sifflets",
    "wof:placetype":"venue"
},
  "geometry": {"coordinates":[6.8460741043,46.4592971802],"type":"Point"}
}