{
  "type": "Feature",
  "properties": {
    "iso:country":"CH",
    "sg:address":"Port-des-p\u00eacheurs",
    "sg:city":"Auvernier",
    "sg:orig_category":"Fische and Fischprodukte Grosshandel",
    "sg:phone":"+41 32 731 60 16",
    "sg:postcode":"2012",
    "sg:province":"Neuch\u00e2tel",
    "wof:name":"Progin Commerce De Poissons",
    "wof:placetype":"venue"
},
  "geometry": {"coordinates":[6.8740320206,46.9713516235],"type":"Point"}
}