{
  "type": "Feature",
  "properties": {
    "iso:country":"CH",
    "sg:address":"Gerberngasse 7",
    "sg:city":"Thun",
    "sg:orig_category":"Industrie, Maschinenbau",
    "sg:phone":"+41 33 222 15 20",
    "sg:postcode":"3600",
    "sg:province":"Bern",
    "wof:name":"Netdoc",
    "wof:placetype":"venue"
},
  "geometry": {"coordinates":[7.628109,46.759914],"type":"Point"}
}