{
  "type": "Feature",
  "properties": {
    "iso:country":"CH",
    "sg:address":"Zuntwisweg 8",
    "sg:city":"Gutenswil",
    "sg:orig_category":"Geb\u00e4ude, Wohnungsreinigung Reinigungsgewerbe",
    "sg:phone":"+41 19460755",
    "sg:postcode":"8605",
    "sg:province":"Z\u00fcrich",
    "wof:name":"Dalcher Gartenpflege - Hauswartung Gartenarbeiten, Kleine Gartenum\u00e4nderungen, Hauswartungen",
    "wof:placetype":"venue"
},
  "geometry": {"coordinates":[8.7141599655,47.3856811523],"type":"Point"}
}