{
  "type": "Feature",
  "properties": {
    "iso:country":"CH",
    "sg:address":"Rue De Lausanne 56",
    "sg:city":"Morges",
    "sg:orig_category":"Schlankheitsinstitute",
    "sg:phone":"+41 21 802 40 01",
    "sg:postcode":"1110",
    "sg:province":"Vaud",
    "wof:name":"Institut Lignes Du Corps Patricia Ahlgren",
    "wof:placetype":"venue"
},
  "geometry": {"coordinates":[6.5068020821,46.5163192749],"type":"Point"}
}