{
  "type": "Feature",
  "properties": {
    "iso:country":"CH",
    "sg:address":"Tscharnerstrasse 11",
    "sg:city":"Bern",
    "sg:orig_category":"Kinderkrippen U horte",
    "sg:phone":"+41 61 701 10 37",
    "sg:postcode":"3007",
    "sg:province":"Bern",
    "wof:name":"Kinderspielgruppe M\u00fcsli O.h\u00e4berli & E.freiburghaus",
    "wof:placetype":"venue"
},
  "geometry": {"coordinates":[7.6052942276,47.4827537537],"type":"Point"}
}