{
  "type": "Feature",
  "properties": {
    "iso:country":"CH",
    "sg:address":"Lausanne Rue De 27",
    "sg:city":"Sion",
    "sg:orig_category":"Interessenvertretungen",
    "sg:postcode":"1950",
    "sg:province":"Valais",
    "wof:name":"Forum De Crans-montana Sa",
    "wof:placetype":"venue"
},
  "geometry": {"coordinates":[7.358109951,46.2321510315],"type":"Point"}
}