{
  "type": "Feature",
  "properties": {
    "iso:country":"CH",
    "sg:address":"Route Champs Des Fontaines 9",
    "sg:city":"Fribourg",
    "sg:orig_category":"Allgemeiner Hoch U Tiefbau ohne ausgepr\u00e4gten Schwerpunkt Unterhalt U Reparatur im Hoch U Tiefbau",
    "sg:phone":"+41 26 466 40 28",
    "sg:postcode":"1700",
    "sg:province":"Fribourg",
    "wof:name":"Franco Cassone Le Sp\u00e9cialiste Du B\u00e2timent",
    "wof:placetype":"venue"
},
  "geometry": {"coordinates":[7.144431,46.809196],"type":"Point"}
}