{
  "type": "Feature",
  "properties": {
    "addr:full":"Place Saint-jaques Etoy Vaud 1163",
    "addr:postcode":"1163",
    "addr:street":"Place Saint-Jaques",
    "iso:country":"CH",
    "sg:address":"Place Saint-jaques",
    "sg:city":"Etoy",
    "sg:orig_category":"Detailhandel mit Brot, Back U S\u00fcsswaren RESTAURANTS: TEA-ROOMS",
    "sg:phone":"+41 21 808 82 66",
    "sg:postcode":"1163",
    "sg:province":"Vaud",
    "wof:name":"G\u00e9rard Fornerod Boulangerie & P\u00e2tisserie",
    "wof:placetype":"venue"
},
  "geometry": {"coordinates":[6.419359,46.485516],"type":"Point"}
}