{
  "type": "Feature",
  "properties": {
    "addr:full":"7743 Brusio Graubunden 7743",
    "addr:housenumber":"7743",
    "addr:postcode":"7743",
    "addr:street":"Brusio Graubunden",
    "iso:country":"CH",
    "sg:address":"7743",
    "sg:city":"Brusio",
    "sg:orig_category":"Detailhandel mit Brot, Back U S\u00fcsswaren Detailhandel mit Waren verschiedener Art, Hauptrichtung Nahr",
    "sg:postcode":"7743",
    "sg:province":"Graubunden",
    "wof:name":"Chammartin Andr\u00e9.",
    "wof:placetype":"venue"
},
  "geometry": {"coordinates":[6.88758,46.834801],"type":"Point"}
}