{
  "type": "Feature",
  "properties": {
    "iso:country":"CH",
    "sg:address":"Hochwangstrasse",
    "sg:city":"Zizers",
    "sg:orig_category":"Grosshandel mit Textilien Textilveredlung",
    "sg:phone":"+41 56 611 04 05",
    "sg:postcode":"7205",
    "sg:province":"Graubunden",
    "wof:name":"Textile Inspiration Keller + Erzinger Ag",
    "wof:placetype":"venue"
},
  "geometry": {"coordinates":[8.2781887054,47.3421058655],"type":"Point"}
}