{
  "type": "Feature",
  "properties": {
    "iso:country":"CH",
    "sg:address":"Im M\u00e4tteli",
    "sg:city":"Merligen",
    "sg:orig_category":"Detailhandel mit Brennstoffen U Heizmaterial G\u00fcterbef\u00f6rderung im Strassenverkehr",
    "sg:phone":"+41 33 252 82 82",
    "sg:postcode":"3658",
    "sg:province":"Bern",
    "wof:name":"Sorgen Ag Autotransporte, Abfallentsorgung",
    "wof:placetype":"venue"
},
  "geometry": {"coordinates":[7.74058,46.69487],"type":"Point"}
}