{
  "type": "Feature",
  "properties": {
    "addr:full":"Brunnenplatz 12 Huttwil Bern 4950",
    "addr:housenumber":"12",
    "addr:postcode":"4950",
    "addr:street":"Brunnenplatz",
    "iso:country":"CH",
    "sg:address":"Brunnenplatz 12",
    "sg:city":"Huttwil",
    "sg:orig_category":"Detailhandel mit Brot, Back U S\u00fcsswaren",
    "sg:phone":"+41 62 962 27 16",
    "sg:postcode":"4950",
    "sg:province":"Bern",
    "wof:name":"Lienhart Urs",
    "wof:placetype":"venue"
},
  "geometry": {"coordinates":[7.849788,47.113331],"type":"Point"}
}