{
  "type": "Feature",
  "properties": {
    "iso:country":"CH",
    "sg:address":"Rue Du Vidollet 3 1200 Genf. Postfach",
    "sg:city":"Gen\u00e8ve",
    "sg:orig_category":"K\u00fcnstlerische U schriftstellerische T\u00e4tigkeiten U Darbietungen",
    "sg:postcode":"1201",
    "sg:province":"Gen\u00e8ve",
    "wof:name":"Teraplus, Schneider-deillon Sophie",
    "wof:placetype":"venue"
},
  "geometry": {"coordinates":[6.9246211052,46.3967247009],"type":"Point"}
}