{
  "type": "Feature",
  "properties": {
    "iso:country":"CH",
    "sg:address":"Chemin Des Champs P\u00e9nys 3",
    "sg:city":"Mies",
    "sg:orig_category":"Grosshandel mit Getreide, Saatgut U Futtermitteln Handelsvermittlung U Grosshandel",
    "sg:phone":"+41 22 950 99 99",
    "sg:postcode":"1295",
    "sg:province":"Vaud",
    "wof:name":"Geti Trade Sa",
    "wof:placetype":"venue"
},
  "geometry": {"coordinates":[6.1622219086,46.2992324829],"type":"Point"}
}