{
  "type": "Feature",
  "properties": {
    "iso:country":"CH",
    "sg:address":"Sagenstrasse 8",
    "sg:city":"Pfaffnau",
    "sg:orig_category":"Elektroinstallation Herstellung von Elektromotoren, Generatoren U Transformatoren",
    "sg:phone":"+41 62 754 16 44",
    "sg:postcode":"6264",
    "sg:province":"Luzern",
    "wof:name":"Elektro K\u00f6pfli Ag",
    "wof:placetype":"venue"
},
  "geometry": {"coordinates":[7.8958911896,47.2277488708],"type":"Point"}
}