{
  "type": "Feature",
  "properties": {
    "iso:country":"CH",
    "sg:address":"Burgstrasse 26",
    "sg:city":"St.gallen",
    "sg:classifiers":[
        {
            "category":"Restaurant",
            "type":"Food & Drink"
        }
    ],
    "sg:phone":"+41 71 277 90 10",
    "sg:postcode":"9000",
    "sg:province":"St. Gallen",
    "wof:name":"Pizzeria Il Castello Pizzakurier-service",
    "wof:placetype":"venue"
},
  "geometry": {"coordinates":[9.3627490997,47.4195785522],"type":"Point"}
}