{
  "type": "Feature",
  "properties": {
    "iso:country":"CH",
    "sg:address":"Untertalweg 55",
    "sg:city":"Arlesheim",
    "sg:orig_category":"Pensionskassen",
    "sg:phone":"+41 61 703 06 40",
    "sg:postcode":"4144",
    "sg:province":"Basel-Landschaft",
    "wof:name":"Personalf\u00fcrsorgestiftung Der Firma Wolf Hunziker Ag",
    "wof:placetype":"venue"
},
  "geometry": {"coordinates":[7.6106228828,47.4989929199],"type":"Point"}
}