{
  "type": "Feature",
  "properties": {
    "iso:country":"CH",
    "sg:address":"Tennis Chemin Du",
    "sg:city":"Echandens",
    "sg:orig_category":"Betrieb U technische Hilfsdienste des Kultur U Unterhaltungswesens",
    "sg:phone":"+41 21 702 31 43",
    "sg:postcode":"1026",
    "sg:province":"Vaud",
    "wof:name":"Bowling Miami Sa",
    "wof:placetype":"venue"
},
  "geometry": {"coordinates":[6.54083,46.534286],"type":"Point"}
}