{
  "type": "Feature",
  "properties": {
    "iso:country":"CH",
    "sg:address":"Mont-blanc Avenue Du 32",
    "sg:city":"Gland",
    "sg:orig_category":"Non-Classified Establishments",
    "sg:postcode":"1196",
    "sg:province":"Vaud",
    "wof:name":"Fergo S\u00e0rl",
    "wof:placetype":"venue"
},
  "geometry": {"coordinates":[6.2722067833,46.4151725769],"type":"Point"}
}