{
  "type": "Feature",
  "properties": {
    "iso:country":"CH",
    "sg:address":"Immeuble Alexandra C 3971 Chermignon. Postfach",
    "sg:city":"Crans-sur-sierre",
    "sg:orig_category":"Fachdetailhandel in Verkaufsr\u00e4umen",
    "sg:phone":"+41 31 301 93 50",
    "sg:postcode":"3963",
    "sg:province":"Valais",
    "wof:name":"Zulo Vertriebsagentur Zutter Louis",
    "wof:placetype":"venue"
},
  "geometry": {"coordinates":[7.4372119904,46.9778747559],"type":"Point"}
}