{
  "type": "Feature",
  "properties": {
    "iso:country":"CH",
    "sg:address":"Rue De Montbrillant 87 1200 Gen\u00e8ve. Postfach",
    "sg:city":"Gen\u00e8ve",
    "sg:orig_category":"RESTAURANTS: TEA-ROOMS",
    "sg:phone":"+41 22 734 35 45",
    "sg:postcode":"1202",
    "sg:province":"Gen\u00e8ve",
    "wof:name":"Iseli Georges",
    "wof:placetype":"venue"
},
  "geometry": {"coordinates":[6.1399607658,46.2211151123],"type":"Point"}
}