{
  "type": "Feature",
  "properties": {
    "iso:country":"CH",
    "sg:address":"Poststrasse 8",
    "sg:city":"Dietikon",
    "sg:orig_category":"Wirtschaftspr\u00fcfung, Steuerberatung U Treuhand",
    "sg:phone":"+41 17404716",
    "sg:postcode":"8953",
    "sg:province":"Z\u00fcrich",
    "wof:name":"Vontax Treuhand Und Steuerrechtspraxis, Bizzozero-w\u00fcrth R.",
    "wof:placetype":"venue"
},
  "geometry": {"coordinates":[8.4056434631,47.403755188],"type":"Point"}
}