{
  "type": "Feature",
  "properties": {
    "iso:country":"CH",
    "sg:address":"St. Gallerstrasse 41",
    "sg:city":"Jona",
    "sg:orig_category":"Detailhandel mit Fleisch U Fleischwaren Detailhandel mit Waren verschiedener Art, Hauptrichtung Nahr",
    "sg:phone":"+41 19510330",
    "sg:postcode":"8645",
    "sg:province":"St. Gallen",
    "wof:name":"Epa Superdiscount Metzgerei Im Dorfmarkt",
    "wof:placetype":"venue"
},
  "geometry": {"coordinates":[8.7815437317,47.3674468994],"type":"Point"}
}