{
  "type": "Feature",
  "properties": {
    "iso:country":"CH",
    "sg:address":"Oberes Eichholz 21",
    "sg:city":"Koppigen",
    "sg:orig_category":"Politische Parteien FDP",
    "sg:phone":"+41 34 413 13 53",
    "sg:postcode":"3425",
    "sg:province":"Bern",
    "wof:name":"Fdp Sektion Koppigen",
    "wof:placetype":"venue"
},
  "geometry": {"coordinates":[7.592813015,47.1320152283],"type":"Point"}
}