{
  "type": "Feature",
  "properties": {
    "iso:country":"CH",
    "sg:address":"Bd De P\u00e9rolles 34 1700 Freiburg. Postfach",
    "sg:city":"Fribourg",
    "sg:orig_category":"Spezialkreditinstitute",
    "sg:postcode":"1701",
    "sg:province":"Fribourg",
    "wof:name":"Soci\u00e9t\u00e9 Coop\u00e9rative De Cautionnement Du Fc Fribourg",
    "wof:placetype":"venue"
},
  "geometry": {"coordinates":[7.1532888412,46.7986450195],"type":"Point"}
}