{
  "type": "Feature",
  "properties": {
    "iso:country":"CH",
    "sg:address":"Lintheschergasse 21 8001 Z\u00fcrich. Postfach 6825",
    "sg:city":"Z\u00fcrich",
    "sg:orig_category":"Erbringung von Dienstleistungen f\u00fcr Unternehmen Unternehmensberatung",
    "sg:phone":"+41 19121436",
    "sg:postcode":"8023",
    "sg:province":"Z\u00fcrich",
    "wof:name":"Mussetti Sacchetto Y. & Partner - Externes Personalmanagement",
    "wof:placetype":"venue"
},
  "geometry": {"coordinates":[8.579366684,47.3207511902],"type":"Point"}
}