{
  "type": "Feature",
  "properties": {
    "iso:country":"CH",
    "sg:address":"Hasenweid 1",
    "sg:city":"Olten",
    "sg:orig_category":"Erbringung von Dienstleistungen f\u00fcr Unternehmen",
    "sg:postcode":"4600",
    "sg:province":"Solothurn",
    "wof:name":"Westiform Holding Ag",
    "wof:placetype":"venue"
},
  "geometry": {"coordinates":[7.3741831779,46.9222640991],"type":"Point"}
}