{
  "type": "Feature",
  "properties": {
    "iso:country":"CH",
    "sg:address":"Bruggerstrasse 4 5103 Wildegg. Postfach",
    "sg:city":"Wildegg",
    "sg:orig_category":"RESTAURANTS: TEA-ROOMS",
    "sg:postcode":"5103",
    "sg:province":"Aargau",
    "wof:name":"Restaurant Schmiedstube, Marcel Guillod",
    "wof:placetype":"venue"
},
  "geometry": {"coordinates":[8.1655063629,47.4151878357],"type":"Point"}
}