{
  "type": "Feature",
  "properties": {
    "iso:country":"CH",
    "sg:address":"Ochsengasse 23",
    "sg:city":"Sch\u00f6nholzerswilen",
    "sg:orig_category":"Baugewerbe Herstellung von Konstruktionsteilen, Fertigbauteilen U Ausbauelementen aus Holz",
    "sg:phone":"+41 79 221 97 78",
    "sg:postcode":"8577",
    "sg:province":"Thurgau",
    "wof:name":"Remaag Ag",
    "wof:placetype":"venue"
},
  "geometry": {"coordinates":[9.141491,47.516827],"type":"Point"}
}