{
  "type": "Feature",
  "properties": {
    "iso:country":"CH",
    "sg:address":"Bellinzona Via 31",
    "sg:city":"Giubiasco",
    "sg:orig_category":"Unclassifiable Establishments",
    "sg:postcode":"6512",
    "sg:province":"Ticino",
    "wof:name":"Info-village, Patrick Haissly",
    "wof:placetype":"venue"
},
  "geometry": {"coordinates":[5.9946498871,46.1506690979],"type":"Point"}
}