{
  "type": "Feature",
  "properties": {
    "iso:country":"CH",
    "sg:address":"Sagenplatz 4",
    "sg:city":"Einsiedeln",
    "sg:classifiers":[
        {
            "category":"Restaurant",
            "type":"Food & Drink"
        }
    ],
    "sg:phone":"+41 55 412 66 94",
    "sg:postcode":"8840",
    "sg:province":"Schwyz",
    "wof:name":"Restaurant P\u00f6stli",
    "wof:placetype":"venue"
},
  "geometry": {"coordinates":[8.7451171875,47.1281051636],"type":"Point"}
}