{
  "type": "Feature",
  "properties": {
    "addr:full":"Morgentalstrasse 27 8355 Aadorf. Postfach 118 Aadorf Thurgau 8355",
    "addr:housenumber":"27;118",
    "addr:postcode":"8355 aadorf.;8355",
    "addr:street":"Morgentalstrasse;Postfach",
    "iso:country":"CH",
    "sg:address":"Morgentalstrasse 27 8355 Aadorf. Postfach 118",
    "sg:city":"Aadorf",
    "sg:orig_category":"Dachdeckerei Zimmerei, Dachdeckerei, Bauspenglerei U Abdichtung",
    "sg:phone":"+41 52 365 13 12",
    "sg:postcode":"8355",
    "sg:province":"Thurgau",
    "wof:name":"Wahrenberger E. Ag.",
    "wof:placetype":"venue"
},
  "geometry": {"coordinates":[8.89542,47.493843],"type":"Point"}
}