{
  "type": "Feature",
  "properties": {
    "iso:country":"CH",
    "sg:address":"Frymannstrasse 15 8041 Z\u00fcrich. Postfach",
    "sg:city":"Z\u00fcrich",
    "sg:orig_category":"Detailhandel mit elektrischen Haushalts-,Radio U Fernsehger\u00e4ten sowie Musikinstrumenten",
    "sg:postcode":"8041",
    "sg:province":"Z\u00fcrich",
    "wof:name":"Aeschbach & Torretti, Hot Guitars And More",
    "wof:placetype":"venue"
},
  "geometry": {"coordinates":[8.1805334091,47.2574195862],"type":"Point"}
}