{
  "type": "Feature",
  "properties": {
    "iso:country":"CH",
    "sg:address":"6802",
    "sg:city":"Rivera",
    "sg:orig_category":"RESTAURANTS: TEA-ROOMS",
    "sg:phone":"+41 91 946 12 94",
    "sg:postcode":"6802",
    "sg:province":"Ticino",
    "wof:name":"Leoni Annamaria",
    "wof:placetype":"venue"
},
  "geometry": {"coordinates":[8.9231395721,46.1164894104],"type":"Point"}
}