{
  "type": "Feature",
  "properties": {
    "iso:country":"CH",
    "sg:address":"Schulstrasse 1 7012 Felsberg. Postfach",
    "sg:city":"Felsberg",
    "sg:orig_category":"Gemeindeverwaltungen",
    "sg:phone":"+41 81 252 96 19",
    "sg:postcode":"7012",
    "sg:province":"Graubunden",
    "wof:name":"Gemeindeverwaltung Felsberg",
    "wof:placetype":"venue"
},
  "geometry": {"coordinates":[9.4761610031,46.8449783325],"type":"Point"}
}