{
  "type": "Feature",
  "properties": {
    "iso:country":"CH",
    "sg:address":"Zelgstrasse 78",
    "sg:city":"Adliswil",
    "sg:orig_category":"Reparatur von Uhren U Schmuck",
    "sg:phone":"+41 17107163",
    "sg:postcode":"8134",
    "sg:province":"Z\u00fcrich",
    "wof:name":"Fritz Berntrag Uhrmacher",
    "wof:placetype":"venue"
},
  "geometry": {"coordinates":[8.5198955536,47.3136253357],"type":"Point"}
}