{
  "type": "Feature",
  "properties": {
    "iso:country":"CH",
    "sg:address":"Fringeliweg 21",
    "sg:city":"B\u00e4rschwil",
    "sg:orig_category":"Zimmerei, Dachdeckerei, Bauspenglerei U Abdichtung Zimmerei, Ingenieurholzbau",
    "sg:phone":"+41 61 761 68 25",
    "sg:postcode":"4252",
    "sg:province":"Solothurn",
    "wof:name":"Georg Stegm\u00fcller Zimmerei",
    "wof:placetype":"venue"
},
  "geometry": {"coordinates":[7.4725527763,47.3813018799],"type":"Point"}
}