{
  "type": "Feature",
  "properties": {
    "addr:full":"Seestrasse 5 Horgen Z\u00fcrich 8810",
    "addr:housenumber":"5",
    "addr:postcode":"8810",
    "addr:street":"Seestrasse",
    "iso:country":"CH",
    "sg:address":"Seestrasse 5",
    "sg:city":"Horgen",
    "sg:classifiers":[
        {
            "category":"Building & Trades",
            "subcategory":"Construction",
            "type":"Services"
        }
    ],
    "sg:phone":"+41 17254228",
    "sg:postcode":"8810",
    "sg:province":"Z\u00fcrich",
    "sg:tags":[
        "yard",
        "boat"
    ],
    "wof:name":"Faul Ag",
    "wof:placetype":"venue"
},
  "geometry": {"coordinates":[8.586922,47.269428],"type":"Point"}
}