{
  "type": "Feature",
  "properties": {
    "iso:country":"CH",
    "sg:address":"Schwellbrunnerstrasse 16 9100 Herisau. Postfach",
    "sg:city":"Herisau",
    "sg:orig_category":"Verlegen von Fussboden",
    "sg:phone":"+41 71 352 51 58",
    "sg:postcode":"9100",
    "sg:province":"Appenzell Ausserrhoden",
    "wof:name":"Gebr\u00fcder Fuchs",
    "wof:placetype":"venue"
},
  "geometry": {"coordinates":[9.2703819275,47.3831863403],"type":"Point"}
}