{
  "type": "Feature",
  "properties": {
    "iso:country":"CH",
    "sg:address":"Eigerplatz 5",
    "sg:city":"Bern",
    "sg:orig_category":"Handels-H\u00e4user U Gesellschaften",
    "sg:postcode":"3007",
    "sg:province":"Bern",
    "wof:name":"Koch Trade",
    "wof:placetype":"venue"
},
  "geometry": {"coordinates":[7.4314570427,46.9408226013],"type":"Point"}
}