{
  "type": "Feature",
  "properties": {
    "iso:country":"CH",
    "sg:address":"Lagerstrasse 8",
    "sg:city":"Chur",
    "sg:orig_category":"Unclassifiable Establishments",
    "sg:phone":"+41 81 286 96 20",
    "sg:postcode":"7000",
    "sg:province":"Graubunden",
    "wof:name":"Cresta Beteiligungen Chur Ag",
    "wof:placetype":"venue"
},
  "geometry": {"coordinates":[9.522485733,46.8527412415],"type":"Point"}
}