{
  "type": "Feature",
  "properties": {
    "iso:country":"CH",
    "sg:address":"Bischofszellerstrasse 8",
    "sg:city":"Gossau",
    "sg:classifiers":[
        {
            "category":"Manufacturing",
            "subcategory":"Glass & Minerals",
            "type":"Manufacturing & Wholesale Goods"
        }
    ],
    "sg:phone":"+41 71 385 33 33",
    "sg:postcode":"9200",
    "sg:province":"St. Gallen",
    "sg:tags":[
        "resistant",
        "item",
        "household",
        "made",
        "heat"
    ],
    "wof:name":"Gebr\u00fcder Gemperli Ag",
    "wof:placetype":"venue"
},
  "geometry": {"coordinates":[9.2460746765,47.4161758423],"type":"Point"}
}