{
  "type": "Feature",
  "properties": {
    "iso:country":"CH",
    "sg:address":"Bergfried",
    "sg:city":"Oberrickenbach",
    "sg:orig_category":"Sessellifte and Skilifte",
    "sg:phone":"+41 41 628 11 70",
    "sg:postcode":"6387",
    "sg:province":"Nidwalden",
    "wof:name":"Skilift Wissibach J.waser",
    "wof:placetype":"venue"
},
  "geometry": {"coordinates":[8.3898601532,46.8960189819],"type":"Point"}
}