{
  "type": "Feature",
  "properties": {
    "iso:country":"CH",
    "sg:address":"1735",
    "sg:city":"Giffers",
    "sg:orig_category":"Primarschulen",
    "sg:phone":"+41 26 418 19 15",
    "sg:postcode":"1735",
    "sg:province":"Fribourg",
    "wof:name":"Primarschule",
    "wof:placetype":"venue"
},
  "geometry": {"coordinates":[7.2161898613,46.7434501648],"type":"Point"}
}