{
  "type": "Feature",
  "properties": {
    "iso:country":"CH",
    "sg:address":"Gaswerkstrasse 13 8500 Frauenfeld. Postfach 3131",
    "sg:city":"Frauenfeld",
    "sg:orig_category":"Elektrizit\u00e4tsversorgung Gasversorgung",
    "sg:phone":"+41 52 724 53 45",
    "sg:postcode":"8503",
    "sg:province":"Thurgau",
    "wof:name":"Werkbetrieb Frauenfeld Elektrizit\u00e4t Erdgas Wasser",
    "wof:placetype":"venue"
},
  "geometry": {"coordinates":[8.8945579529,47.5592422485],"type":"Point"}
}