{
  "type": "Feature",
  "properties": {
    "iso:country":"CH",
    "sg:address":"Stapferstrasse 21",
    "sg:city":"Z\u00fcrich",
    "sg:orig_category":"Non-Classified Establishments",
    "sg:postcode":"8006",
    "sg:province":"Z\u00fcrich",
    "wof:name":"Cvf, I. Kn\u00f6pfel",
    "wof:placetype":"venue"
},
  "geometry": {"coordinates":[8.5461940765,47.383430481],"type":"Point"}
}