{
  "type": "Feature",
  "properties": {
    "iso:country":"CH",
    "sg:address":"2720",
    "sg:city":"Tramlingen",
    "sg:orig_category":"Alters U Pflegeheime Interessenvertretungen",
    "sg:phone":"+41 32 487 40 09",
    "sg:postcode":"2720",
    "sg:province":"Bern",
    "wof:name":"Home Et Colonie D'habitation Les Lovieres",
    "wof:placetype":"venue"
},
  "geometry": {"coordinates":[7.1003,47.223141],"type":"Point"}
}