{
  "type": "Feature",
  "properties": {
    "addr:full":"Hofwilstrasse 4 Moosseedorf Bern 3302",
    "addr:housenumber":"4",
    "addr:postcode":"3302",
    "addr:street":"Hofwilstrasse",
    "iso:country":"CH",
    "sg:address":"Hofwilstrasse 4",
    "sg:city":"Moosseedorf",
    "sg:classifiers":[
        {
            "category":"Banks & Credit Unions",
            "subcategory":"Bank",
            "type":"Services"
        }
    ],
    "sg:phone":"+41 31 859 37 37",
    "sg:postcode":"3302",
    "sg:province":"Bern",
    "wof:name":"Spar + Leihkasse Bern",
    "wof:placetype":"venue"
},
  "geometry": {"coordinates":[7.481507,47.016762],"type":"Point"}
}