{
  "type": "Feature",
  "properties": {
    "iso:country":"CH",
    "sg:address":"Weidstrasse 4",
    "sg:city":"Bronschhofen",
    "sg:orig_category":"Fahrschulen, Flugschulen",
    "sg:phone":"+41 79 236 70 36",
    "sg:postcode":"9552",
    "sg:province":"St. Gallen",
    "wof:name":"Karl Sch\u00f6nenberger Autofahrschule",
    "wof:placetype":"venue"
},
  "geometry": {"coordinates":[9.0329732895,47.4844474792],"type":"Point"}
}