{
  "type": "Feature",
  "properties": {
    "iso:country":"CH",
    "sg:address":"Saleggi",
    "sg:city":"Losone",
    "sg:orig_category":"Vermietung U Verpachtung von eigenen Immobilien",
    "sg:postcode":"6616",
    "sg:province":"Ticino",
    "wof:name":"Supermeda Ag",
    "wof:placetype":"venue"
},
  "geometry": {"coordinates":[8.7672901154,46.1682853699],"type":"Point"}
}