{
  "type": "Feature",
  "properties": {
    "iso:country":"CH",
    "sg:address":"Place Du Tunnel 13",
    "sg:city":"Lausanne",
    "sg:orig_category":"Tanzschulen, Tanzlehrer",
    "sg:phone":"+41 21 320 31 67",
    "sg:postcode":"1005",
    "sg:province":"Vaud",
    "wof:name":"Claude Blanc Ecole De Danse",
    "wof:placetype":"venue"
},
  "geometry": {"coordinates":[6.6345901489,46.5262718201],"type":"Point"}
}