{
  "type": "Feature",
  "properties": {
    "iso:country":"CH",
    "sg:address":"Bahnhofstrasse 7 3186 D\u00fcdingen. Postfach 226",
    "sg:city":"D\u00fcdingen",
    "sg:orig_category":"Non-Classified Establishments",
    "sg:phone":"+41 26 493 33 44",
    "sg:postcode":"3186",
    "sg:province":"Fribourg",
    "wof:name":"Sensat Ag Hifi-tv-video-satellit Bang&olufsen",
    "wof:placetype":"venue"
},
  "geometry": {"coordinates":[7.1917500496,46.8505897522],"type":"Point"}
}