{
  "type": "Feature",
  "properties": {
    "iso:country":"CH",
    "sg:address":"Hohlstrasse 507",
    "sg:city":"Z\u00fcrich",
    "sg:orig_category":"Pensionskassen",
    "sg:phone":"+41 14321340",
    "sg:postcode":"8048",
    "sg:province":"Z\u00fcrich",
    "wof:name":"Personalf\u00fcrsorgestiftung Der Firma Hefti, Ag, Chemische Fabrik",
    "wof:placetype":"venue"
},
  "geometry": {"coordinates":[8.4932861328,47.3893890381],"type":"Point"}
}