{
  "type": "Feature",
  "properties": {
    "iso:country":"CH",
    "sg:address":"Neue Perlenstrasse 2 6037 Root. Postfach 26",
    "sg:city":"Root",
    "sg:orig_category":"Dachdeckerei Zimmerei, Dachdeckerei, Bauspenglerei U Abdichtung",
    "sg:phone":"+41 41 450 21 40",
    "sg:postcode":"6037",
    "sg:province":"Luzern",
    "wof:name":"Baumann Guido Bedachungen",
    "wof:placetype":"venue"
},
  "geometry": {"coordinates":[8.388046,47.114204],"type":"Point"}
}