{
  "type": "Feature",
  "properties": {
    "iso:country":"CH",
    "sg:address":"Viale C. Olgiati 20",
    "sg:city":"Giubiasco",
    "sg:classifiers":[
        {
            "category":"Banks & Credit Unions",
            "subcategory":"Bank",
            "type":"Services"
        }
    ],
    "sg:phone":"+41 4192278144",
    "sg:postcode":"6512",
    "sg:province":"Ticino",
    "wof:name":"Rentenanstalt Swiss Life",
    "wof:placetype":"venue"
},
  "geometry": {"coordinates":[9.014093,46.17617],"type":"Point"}
}