{
  "type": "Feature",
  "properties": {
    "iso:country":"CH",
    "sg:address":"H\u00e4nib\u00fcel 8",
    "sg:city":"Zug",
    "sg:orig_category":"Unclassifiable Establishments",
    "sg:postcode":"6300",
    "sg:province":"Zug",
    "wof:name":"Reiluma Anlage Ag",
    "wof:placetype":"venue"
},
  "geometry": {"coordinates":[8.5172328949,47.1581573486],"type":"Point"}
}