{
  "type": "Feature",
  "properties": {
    "iso:country":"CH",
    "sg:address":"Gurzelenstrasse 4",
    "sg:city":"Bellach",
    "sg:orig_category":"Herstellung von k\u00e4lte U lufttechnischen Erzeugnissen f\u00fcr gewerbliche Zwecke",
    "sg:phone":"+41 32 617 42 29",
    "sg:postcode":"4512",
    "sg:province":"Solothurn",
    "wof:name":"Dura-coat Ag",
    "wof:placetype":"venue"
},
  "geometry": {"coordinates":[7.5042347908,47.2103538513],"type":"Point"}
}