{
  "type": "Feature",
  "properties": {
    "iso:country":"CH",
    "sg:address":"Grubenstrasse 107",
    "sg:city":"Sch\u00f6nb\u00fchl-urtenen",
    "sg:orig_category":"Einzelhandel mit Automobilteilen U Zubeh\u00f6r",
    "sg:phone":"+41 79 669 17 14",
    "sg:postcode":"3322",
    "sg:province":"Bern",
    "wof:name":"Irchel Pneu Christian Lienhard",
    "wof:placetype":"venue"
},
  "geometry": {"coordinates":[8.5679149628,47.5490951538],"type":"Point"}
}