{
  "type": "Feature",
  "properties": {
    "iso:country":"CH",
    "sg:address":"Buchmattweg 7",
    "sg:city":"Nusshof",
    "sg:orig_category":"Architektur U Ingenieurb\u00fcros",
    "sg:postcode":"4453",
    "sg:province":"Basel-Landschaft",
    "wof:name":"Junker Fritz, Architekturb\u00fcro",
    "wof:placetype":"venue"
},
  "geometry": {"coordinates":[7.802826,47.492386],"type":"Point"}
}