{
  "type": "Feature",
  "properties": {
    "iso:country":"CH",
    "sg:address":"7606",
    "sg:city":"Promontogno",
    "sg:orig_category":"Schulpflegen",
    "sg:postcode":"7606",
    "sg:province":"Graubunden",
    "wof:name":"Delegazione Scolastica Del Comune Di Bosco Luganese",
    "wof:placetype":"venue"
},
  "geometry": {"coordinates":[8.9050197601,46.0297584534],"type":"Point"}
}