{
  "type": "Feature",
  "properties": {
    "iso:country":"CH",
    "sg:address":"Kehracker 602",
    "sg:city":"Schmiedrued",
    "sg:orig_category":"K\u00fcnstlerische U schriftstellerische T\u00e4tigkeiten U Darbietungen",
    "sg:postcode":"5046",
    "sg:province":"Aargau",
    "wof:name":"Konzeptionen Leutwyler",
    "wof:placetype":"venue"
},
  "geometry": {"coordinates":[8.1050767899,47.273525238],"type":"Point"}
}