{
  "type": "Feature",
  "properties": {
    "addr:full":"Rischli S\u00f6renberg Luzern 6174",
    "addr:postcode":"6174",
    "addr:street":"Soerenberg",
    "iso:country":"CH",
    "sg:address":"Rischli",
    "sg:city":"S\u00f6renberg",
    "sg:orig_category":"Campingpl\u00e4tze",
    "sg:phone":"+41 41 488 15 77",
    "sg:postcode":"6174",
    "sg:province":"Luzern",
    "wof:name":"Markus Bieri Camping",
    "wof:placetype":"venue"
},
  "geometry": {"coordinates":[8.025284,46.825745],"type":"Point"}
}