{
  "type": "Feature",
  "properties": {
    "iso:country":"CH",
    "sg:address":"Rue Centrale 19",
    "sg:city":"Morges",
    "sg:orig_category":"Detailhandel mit Spielwaren",
    "sg:phone":"+41 21 803 18 66",
    "sg:postcode":"1110",
    "sg:province":"Vaud",
    "wof:name":"Antoine Villinger Articles De P\u00eache Et De Chasse",
    "wof:placetype":"venue"
},
  "geometry": {"coordinates":[6.4965238571,46.5101661682],"type":"Point"}
}