{
  "type": "Feature",
  "properties": {
    "iso:country":"CH",
    "sg:address":"Blumenweg 6 3427 Utzenstorf. Postfach",
    "sg:city":"Utzenstorf",
    "sg:orig_category":"Non-Classified Establishments",
    "sg:phone":"+41 32 665 40 57",
    "sg:postcode":"3427",
    "sg:province":"Bern",
    "wof:name":"Iff Hans-peter",
    "wof:placetype":"venue"
},
  "geometry": {"coordinates":[7.5580029488,47.1333999634],"type":"Point"}
}