{
  "type": "Feature",
  "properties": {
    "iso:country":"CH",
    "sg:address":"General Guisan-strasse 80",
    "sg:city":"Basel",
    "sg:orig_category":"Architektur U Ingenieurb\u00fcros",
    "sg:phone":"+41 61 301 56 56",
    "sg:postcode":"4054",
    "sg:province":"Basel-Stadt",
    "wof:name":"Markus Enderlin Konstruktionsb\u00fcro",
    "wof:placetype":"venue"
},
  "geometry": {"coordinates":[7.565986,47.55003],"type":"Point"}
}