{
  "type": "Feature",
  "properties": {
    "addr:full":"Hauptstrasse 150 Leimbach Aargau 5733",
    "addr:housenumber":"150",
    "addr:postcode":"5733",
    "addr:street":"Hauptstrasse",
    "iso:country":"CH",
    "sg:address":"Hauptstrasse 150",
    "sg:city":"Leimbach",
    "sg:orig_category":"Sheet Metal Blanks, Rounds, Discs And Rings",
    "sg:phone":"+41 62 771 24 66",
    "sg:postcode":"5733",
    "sg:province":"Aargau",
    "wof:name":"Mec Service Center Ag",
    "wof:placetype":"venue"
},
  "geometry": {"coordinates":[8.171834,47.270107],"type":"Point"}
}