{
  "type": "Feature",
  "properties": {
    "iso:country":"CH",
    "sg:address":"Greifenseestrasse 9",
    "sg:city":"Schwerzenbach",
    "sg:orig_category":"Grafikateliers, Design Siebdruck",
    "sg:phone":"+41 17844464",
    "sg:postcode":"8603",
    "sg:province":"Z\u00fcrich",
    "wof:name":"Bruno Wihler Schriften Siebdruck",
    "wof:placetype":"venue"
},
  "geometry": {"coordinates":[8.7349157333,47.2001190186],"type":"Point"}
}