{
  "type": "Feature",
  "properties": {
    "iso:country":"CH",
    "sg:address":"St\u00f6ckliweg 11",
    "sg:city":"Heiden",
    "sg:orig_category":"Architekturb\u00fcros",
    "sg:phone":"+41 71 891 51 91",
    "sg:postcode":"9410",
    "sg:province":"Appenzell Ausserrhoden",
    "wof:name":"Tam\u00e0s Luk\u00e0cs Architekturb\u00fcro",
    "wof:placetype":"venue"
},
  "geometry": {"coordinates":[9.537544,47.451309],"type":"Point"}
}