{
  "type": "Feature",
  "properties": {
    "iso:country":"CH",
    "sg:address":"Ackerstrasse 18",
    "sg:city":"Steckborn",
    "sg:orig_category":"Sonstige pers\u00f6nliche Dienstleistungen",
    "sg:phone":"+41 21 922 01 49",
    "sg:postcode":"8266",
    "sg:province":"Thurgau",
    "wof:name":"Kalaguna Sante, Bigler Jean-pierre Conseils Dans Le Dom. De L'alimentation, De Cosm\u00e9tiques Etc",
    "wof:placetype":"venue"
},
  "geometry": {"coordinates":[5.1808700562,45.8973388672],"type":"Point"}
}