{
  "type": "Feature",
  "properties": {
    "iso:country":"CH",
    "sg:address":"Weberhus 6130 Willisau. Postfach",
    "sg:city":"Daiwil",
    "sg:orig_category":"Wasserversorgung",
    "sg:postcode":"6126",
    "sg:province":"Luzern",
    "wof:name":"Wasserversorgungsgenossenschaft Daiwil",
    "wof:placetype":"venue"
},
  "geometry": {"coordinates":[7.9928841591,47.1222229004],"type":"Point"}
}