{
  "type": "Feature",
  "properties": {
    "iso:country":"CH",
    "sg:address":"Hauptstrasse 3 5314 Kleind\u00f6ttingen. Postfach",
    "sg:city":"Kleind\u00f6ttingen",
    "sg:orig_category":"Detailhandel mit Radio U Fernsehger\u00e4ten Detailhandel mit elektrischen Haushalts-,Radio U Fernsehger\u00e4",
    "sg:phone":"+41 56 245 31 33",
    "sg:postcode":"5314",
    "sg:province":"Aargau",
    "wof:name":"Fernseh-video E. Eggimann",
    "wof:placetype":"venue"
},
  "geometry": {"coordinates":[8.2498960495,47.5720748901],"type":"Point"}
}