{
  "type": "Feature",
  "properties": {
    "iso:country":"CH",
    "sg:address":"Hungerb\u00fchlstrasse 7",
    "sg:city":"Embrach",
    "sg:orig_category":"Allgemeiner Hoch U Tiefbau Handelsvermittlung U Grosshandel",
    "sg:phone":"+41 18656500",
    "sg:postcode":"8424",
    "sg:province":"Z\u00fcrich",
    "wof:name":"Festzeltvermietung Amsler & Gutknecht Ag",
    "wof:placetype":"venue"
},
  "geometry": {"coordinates":[8.594826,47.50602],"type":"Point"}
}