{
  "type": "Feature",
  "properties": {
    "iso:country":"CH",
    "sg:address":"Via Car\u00e0 22",
    "sg:city":"Breganzona",
    "sg:orig_category":"Herstellung U Zusammensetzung von Uhren",
    "sg:phone":"+41 32 913 69 20",
    "sg:postcode":"6932",
    "sg:province":"Ticino",
    "wof:name":"Michel Vo\u00eblin Atelier De Polissage",
    "wof:placetype":"venue"
},
  "geometry": {"coordinates":[6.8183150291,47.0972137451],"type":"Point"}
}