{
  "type": "Feature",
  "properties": {
    "iso:country":"CH",
    "sg:address":"Sunnhaldenstrasse 2",
    "sg:city":"Euthal",
    "sg:orig_category":"Sanit\u00e4rinstallation",
    "sg:phone":"+41 55 412 53 53",
    "sg:postcode":"8844",
    "sg:province":"Schwyz",
    "wof:name":"Sanit\u00e4r K\u00e4lin Gmbh",
    "wof:placetype":"venue"
},
  "geometry": {"coordinates":[8.8126401901,47.0973701477],"type":"Point"}
}