{
  "type": "Feature",
  "properties": {
    "iso:country":"CH",
    "sg:address":"Solothurnstrasse 21 4702 Oensingen. Postfach 348",
    "sg:city":"Oensingen",
    "sg:orig_category":"Giessereiindustrie Herstellung von Metallerzeugnissen ohne Maschinenbau",
    "sg:phone":"+41 62 388 18 18",
    "sg:postcode":"4702",
    "sg:province":"Solothurn",
    "wof:name":"Druag Druckguss Ag Oensingen",
    "wof:placetype":"venue"
},
  "geometry": {"coordinates":[7.706717968,47.2866134644],"type":"Point"}
}