{
  "type": "Feature",
  "properties": {
    "iso:country":"CH",
    "sg:address":"Corso San Gottardo 6",
    "sg:city":"Chiasso",
    "sg:orig_category":"Warenh\u00e4user",
    "sg:phone":"+41 91 682 41 41",
    "sg:postcode":"6830",
    "sg:province":"Ticino",
    "wof:name":"Manor",
    "wof:placetype":"venue"
},
  "geometry": {"coordinates":[9.033000946,45.8328208923],"type":"Point"}
}