{
  "type": "Feature",
  "properties": {
    "addr:full":"Hobelwerkweg 8 Winterthur Z\u00fcrich 8404",
    "addr:housenumber":"8",
    "addr:postcode":"8404",
    "addr:street":"Hobelwerkweg",
    "iso:country":"CH",
    "sg:address":"Hobelwerkweg 8",
    "sg:city":"Winterthur",
    "sg:orig_category":"Bezirks, Sekundar, Realschulen, Oberstufe der Primarschulen Primarschulen",
    "sg:postcode":"8404",
    "sg:province":"Z\u00fcrich",
    "wof:name":"Primarschule & Oberstufe Hegifeld",
    "wof:placetype":"venue"
},
  "geometry": {"coordinates":[8.763645,47.509068],"type":"Point"}
}