{
  "type": "Feature",
  "properties": {
    "iso:country":"CH",
    "sg:address":"B\u00e4derstrasse 32",
    "sg:city":"Baden",
    "sg:orig_category":"Lightning And Surge Arresters",
    "sg:phone":"+41 56 493 72 72",
    "sg:postcode":"5400",
    "sg:province":"Aargau",
    "wof:name":"Hiv Ag",
    "wof:placetype":"venue"
},
  "geometry": {"coordinates":[8.3130397797,47.480381012],"type":"Point"}
}