{
  "type": "Feature",
  "properties": {
    "iso:country":"CH",
    "sg:address":"All\u00e9e Des Soupirs 2",
    "sg:city":"Porrentruy",
    "sg:classifiers":[
        {
            "category":"Shopping",
            "subcategory":"Shoes",
            "type":"Retail Goods"
        }
    ],
    "sg:phone":"+41 32 466 17 21",
    "sg:postcode":"2900",
    "sg:province":"Jura",
    "sg:tags":[
        "children's"
    ],
    "wof:name":"Minerva Manufacture De Chaussures S.a.",
    "wof:placetype":"venue"
},
  "geometry": {"coordinates":[7.074371,47.41864],"type":"Point"}
}