{
  "type": "Feature",
  "properties": {
    "iso:country":"CH",
    "sg:address":"Poststrasse 132 8957 Spreitenbach. Postfach",
    "sg:city":"Spreitenbach",
    "sg:orig_category":"Herstellung von Schl\u00f6ssern U Beschl\u00e4gen",
    "sg:postcode":"8957",
    "sg:province":"Aargau",
    "wof:name":"Studer Sicherheitstechnik Schl\u00fcsselservice",
    "wof:placetype":"venue"
},
  "geometry": {"coordinates":[8.3594331741,47.4259147644],"type":"Point"}
}