{
  "type": "Feature",
  "properties": {
    "iso:country":"CH",
    "sg:address":"Centralbahnstrasse 14 4051 Basel. Postfach",
    "sg:city":"Basel",
    "sg:classifiers":[
        {
            "category":"Restaurant",
            "type":"Food & Drink"
        }
    ],
    "sg:phone":"+41 61 272 05 05",
    "sg:postcode":"4002",
    "sg:province":"Basel-Stadt",
    "wof:name":"Bahnhof Restaurants Basel",
    "wof:placetype":"venue"
},
  "geometry": {"coordinates":[7.5886759758,47.5480880737],"type":"Point"}
}