{
  "type": "Feature",
  "properties": {
    "iso:country":"CH",
    "sg:address":"Aux Ecuries 1",
    "sg:city":"Faoug",
    "sg:orig_category":"Mit Sport verbundene T\u00e4tigkeiten",
    "sg:phone":"+41 26 672 23 72",
    "sg:postcode":"1595",
    "sg:province":"Bern",
    "wof:name":"Man\u00e8ge & \u00e9cole D'\u00e9quitation De Fous",
    "wof:placetype":"venue"
},
  "geometry": {"coordinates":[7.0753560066,46.9055900574],"type":"Point"}
}