{
  "type": "Feature",
  "properties": {
    "iso:country":"CH",
    "sg:address":"Dennliweg 37",
    "sg:city":"Langenthal",
    "sg:orig_category":"Abwasserreinigung, Abfallbeseitigung U sonstige Entsorgung Spezieller Tiefbau",
    "sg:phone":"+41 21 633 10 70",
    "sg:postcode":"4900",
    "sg:province":"Bern",
    "wof:name":"Liaudet Assainissement Sa",
    "wof:placetype":"venue"
},
  "geometry": {"coordinates":[6.593976,46.527843],"type":"Point"}
}