{
  "type": "Feature",
  "properties": {
    "iso:country":"CH",
    "sg:address":"M\u00fchlematt",
    "sg:city":"Eriz",
    "sg:orig_category":"S\u00e4gewerke",
    "sg:phone":"+41 33 453 14 78",
    "sg:postcode":"3619",
    "sg:province":"Bern",
    "wof:name":"Peter Kropf S\u00e4gerei",
    "wof:placetype":"venue"
},
  "geometry": {"coordinates":[7.7791228294,46.7862586975],"type":"Point"}
}