{
  "type": "Feature",
  "properties": {
    "iso:country":"CH",
    "sg:address":"Bremgartenstrasse 119",
    "sg:city":"Bern",
    "sg:orig_category":"Interessenvertretungen",
    "sg:postcode":"3012",
    "sg:province":"Bern",
    "wof:name":"Stiftung Ern\u00e4hrung Und Diabetes",
    "wof:placetype":"venue"
},
  "geometry": {"coordinates":[7.4274439812,46.9587936401],"type":"Point"}
}