{
  "type": "Feature",
  "properties": {
    "iso:country":"CH",
    "sg:address":"Buchholzstrasse 63",
    "sg:city":"Z\u00fcrich",
    "sg:orig_category":"Geb\u00e4ude, Wohnungsreinigung",
    "sg:phone":"+41 71 385 90 10",
    "sg:postcode":"8053",
    "sg:province":"Z\u00fcrich",
    "wof:name":"Tip-top Geb\u00e4udereinigung Hanspeter Nussbaumer",
    "wof:placetype":"venue"
},
  "geometry": {"coordinates":[9.261713028,47.4139289856],"type":"Point"}
}