{
  "type": "Feature",
  "properties": {
    "iso:country":"CH",
    "sg:address":"Gare Place De La 19",
    "sg:city":"Morges",
    "sg:orig_category":"Herstellung von W\u00e4sche",
    "sg:postcode":"1110",
    "sg:province":"Vaud",
    "wof:name":"Baz\u00e9o, Sautebin D.",
    "wof:placetype":"venue"
},
  "geometry": {"coordinates":[6.4987850189,46.5085639954],"type":"Point"}
}