{
  "type": "Feature",
  "properties": {
    "iso:country":"CH",
    "sg:address":"Staltigstrasse 8",
    "sg:city":"Glattfelden",
    "sg:orig_category":"Blumen U Zierpflanzenbau Detailhandel mit Blumen U Pflanzen",
    "sg:phone":"+41 18670327",
    "sg:postcode":"8192",
    "sg:province":"Z\u00fcrich",
    "wof:name":"Max Meili",
    "wof:placetype":"venue"
},
  "geometry": {"coordinates":[8.504483,47.556927],"type":"Point"}
}