{
  "type": "Feature",
  "properties": {
    "addr:full":"Hardstrasse 21 Wettingen Aargau 5430",
    "addr:housenumber":"21",
    "addr:postcode":"5430",
    "addr:street":"Hardstrasse",
    "iso:country":"CH",
    "sg:address":"Hardstrasse 21",
    "sg:city":"Wettingen",
    "sg:orig_category":"Clean-Room Measurement Technology",
    "sg:phone":"+41 56 427 39 21",
    "sg:postcode":"5430",
    "sg:province":"Aargau",
    "wof:name":"H. R. W. Steuerungen",
    "wof:placetype":"venue"
},
  "geometry": {"coordinates":[8.328406,47.461536],"type":"Point"}
}