{
  "type": "Feature",
  "properties": {
    "iso:country":"CH",
    "sg:address":"Turnhallestrasse 4",
    "sg:city":"Luterbach",
    "sg:orig_category":"Primarschulen",
    "sg:phone":"+41 52 383 24 08",
    "sg:postcode":"4542",
    "sg:province":"Solothurn",
    "wof:name":"Primarschule",
    "wof:placetype":"venue"
},
  "geometry": {"coordinates":[8.7941188812,47.4457397461],"type":"Point"}
}