{
  "type": "Feature",
  "properties": {
    "iso:country":"CH",
    "sg:address":"Route De Suisse 41",
    "sg:city":"Versoix",
    "sg:orig_category":"RESTAURANTS: TEA-ROOMS",
    "sg:postcode":"1290",
    "sg:province":"Gen\u00e8ve",
    "wof:name":"Annick David-thonney",
    "wof:placetype":"venue"
},
  "geometry": {"coordinates":[6.1684951782,46.2778053284],"type":"Point"}
}