{
  "type": "Feature",
  "properties": {
    "iso:country":"CH",
    "sg:address":"Lindhofstrasse 9",
    "sg:city":"M\u00f6nchaltorf",
    "sg:orig_category":"Grosshandel mit elektrischen Haushaltsger\u00e4ten, Radio U Fernsehger\u00e4ten",
    "sg:phone":"+41 19480308",
    "sg:postcode":"8617",
    "sg:province":"Z\u00fcrich",
    "wof:name":"Herta Roth Import Von Elektr.ger\u00e4ten",
    "wof:placetype":"venue"
},
  "geometry": {"coordinates":[8.7225456238,47.3123092651],"type":"Point"}
}