{
  "type": "Feature",
  "properties": {
    "iso:country":"CH",
    "sg:address":"Bahnhofstrasse 4/4a 9000 St. Gallen. Postfach",
    "sg:city":"St.gallen",
    "sg:orig_category":"Elektroinstallation",
    "sg:phone":"+41 71 242 76 76",
    "sg:postcode":"9000",
    "sg:province":"St. Gallen",
    "wof:name":"Atel Elektrosanit\u00e4r Ag",
    "wof:placetype":"venue"
},
  "geometry": {"coordinates":[9.3733358383,47.4259414673],"type":"Point"}
}