{
  "type": "Feature",
  "properties": {
    "addr:full":"Lausanne Rue De 1950 Sion. Postfach Sitten Valais 1950",
    "addr:postcode":"1950",
    "addr:street":"Rue De 1950 Sion. Postfach",
    "iso:country":"CH",
    "sg:address":"Lausanne Rue De 1950 Sion. Postfach",
    "sg:city":"Sitten",
    "sg:classifiers":[
        {
            "category":"Bars & Pubs",
            "type":"Food & Drink"
        }
    ],
    "sg:phone":"+41 41 872 14 74",
    "sg:postcode":"1950",
    "sg:province":"Valais",
    "wof:name":"Rha-bar-ber, Marty Barbetrieb",
    "wof:placetype":"venue"
},
  "geometry": {"coordinates":[8.644539,46.881927],"type":"Point"}
}