{
  "type": "Feature",
  "properties": {
    "iso:country":"CH",
    "sg:address":"Nebikerstrasse 7 6247 Sch\u00f6tz. Postfach",
    "sg:city":"Sch\u00f6tz",
    "sg:orig_category":"Detailhandel mit Radio U Fernsehger\u00e4ten Detailhandel mit elektrischen Haushalts-,Radio U Fernsehger\u00e4",
    "sg:phone":"+41 41 980 17 17",
    "sg:postcode":"6247",
    "sg:province":"Luzern",
    "wof:name":"Landolt J.",
    "wof:placetype":"venue"
},
  "geometry": {"coordinates":[7.9884390831,47.1720848083],"type":"Point"}
}