{
  "type": "Feature",
  "properties": {
    "iso:country":"CH",
    "sg:address":"Rue De La Gare",
    "sg:city":"Collombey",
    "sg:classifiers":[
        {
            "category":"Government",
            "subcategory":"Post Office",
            "type":"Public Place"
        }
    ],
    "sg:phone":"+41 21 866 15 88",
    "sg:postcode":"1868",
    "sg:province":"Valais",
    "sg:tags":[
        "caf\u00e9s",
        "tea-rooms"
    ],
    "wof:name":"Tea-room La Moisson D'or S\u00e0rl",
    "wof:placetype":"venue"
},
  "geometry": {"coordinates":[6.5134987831,46.6585845947],"type":"Point"}
}