{
  "type": "Feature",
  "properties": {
    "iso:country":"CH",
    "sg:address":"Brandbachstrasse 10",
    "sg:city":"Dietlikon",
    "sg:orig_category":"Markt U Meinungsforschung",
    "sg:phone":"+41 56 442 11 30",
    "sg:postcode":"8305",
    "sg:province":"Z\u00fcrich",
    "wof:name":"Inter Market & Distribution Ag Imd",
    "wof:placetype":"venue"
},
  "geometry": {"coordinates":[8.2171897888,47.4657363892],"type":"Point"}
}