{
  "type": "Feature",
  "properties": {
    "iso:country":"CH",
    "sg:address":"Kantonsstrasse 56",
    "sg:city":"Freienbach",
    "sg:orig_category":"Architektur U Ingenieurb\u00fcros",
    "sg:postcode":"8807",
    "sg:province":"Schwyz",
    "wof:name":"Im Bauleitung Ag",
    "wof:placetype":"venue"
},
  "geometry": {"coordinates":[8.75269,47.20681],"type":"Point"}
}