{
  "type": "Feature",
  "properties": {
    "iso:country":"CH",
    "sg:address":"2016 Cortaillod. Postfach 85",
    "sg:city":"Cortaillod",
    "sg:orig_category":"Sportvereine Ballsport Fussball",
    "sg:phone":"+41 32 842 20 62",
    "sg:postcode":"2016",
    "sg:province":"Neuch\u00e2tel",
    "wof:name":"Fc Cortaillod",
    "wof:placetype":"venue"
},
  "geometry": {"coordinates":[6.8464298248,46.943031311],"type":"Point"}
}