{
  "type": "Feature",
  "properties": {
    "iso:country":"CH",
    "sg:address":"Sports Avenue Des",
    "sg:city":"Yverdon-les-bains",
    "sg:orig_category":"Interessenvertretungen",
    "sg:phone":"+41 32 931 82 44",
    "sg:postcode":"1400",
    "sg:province":"Vaud",
    "wof:name":"Fondation Du Service D'aide Familiale Du Locle",
    "wof:placetype":"venue"
},
  "geometry": {"coordinates":[6.7492442131,47.0588569641],"type":"Point"}
}