{
  "type": "Feature",
  "properties": {
    "iso:country":"CH",
    "sg:address":"Dorfstrasse 4",
    "sg:city":"Thal",
    "sg:orig_category":"Allgemeiner Hoch U Tiefbau",
    "sg:phone":"+41 71 747 64 30",
    "sg:postcode":"9425",
    "sg:province":"St. Gallen",
    "wof:name":"Gautschi Ag",
    "wof:placetype":"venue"
},
  "geometry": {"coordinates":[9.62208,47.45594],"type":"Point"}
}