{
  "type": "Feature",
  "properties": {
    "iso:country":"CH",
    "sg:address":"Poststrasse 1",
    "sg:city":"Wynau",
    "sg:orig_category":"Nationale Postdienste",
    "sg:phone":"+41 62 929 32 00",
    "sg:postcode":"4923",
    "sg:province":"Bern",
    "wof:name":"Die Schweizerische Post",
    "wof:placetype":"venue"
},
  "geometry": {"coordinates":[7.8158102036,47.2556838989],"type":"Point"}
}