{
  "type": "Feature",
  "properties": {
    "iso:country":"CH",
    "sg:address":"Rue Du Centre 11",
    "sg:city":"Fontainemelon",
    "sg:orig_category":"Reinigungsgewerbe",
    "sg:postcode":"2052",
    "sg:province":"Neuch\u00e2tel",
    "wof:name":"Matile P., Nettoyages",
    "wof:placetype":"venue"
},
  "geometry": {"coordinates":[6.8907208443,47.0569458008],"type":"Point"}
}