{
  "type": "Feature",
  "properties": {
    "iso:country":"CH",
    "sg:address":"8401 Winterthur. Postfach 611",
    "sg:city":"Winterthur",
    "sg:orig_category":"Betrieb von Taxis",
    "sg:phone":"+41 52 242 33 33",
    "sg:postcode":"8401",
    "sg:province":"Z\u00fcrich",
    "wof:name":"Piccadilly Tours Londonbusse",
    "wof:placetype":"venue"
},
  "geometry": {"coordinates":[8.72616,47.499882],"type":"Point"}
}