{
  "type": "Feature",
  "properties": {
    "iso:country":"CH",
    "sg:address":"Hardturmstrasse 134",
    "sg:city":"Z\u00fcrich",
    "sg:orig_category":"Ger\u00fcstbau",
    "sg:phone":"+41 14342434",
    "sg:postcode":"8005",
    "sg:province":"Z\u00fcrich",
    "wof:name":"Sch\u00e4rer Blitzger\u00fcst Ag Bauger\u00fcste Usw; Fabrikat., Montage, Verkauf, Vermietung",
    "wof:placetype":"venue"
},
  "geometry": {"coordinates":[8.5109376907,47.3941268921],"type":"Point"}
}