{
  "type": "Feature",
  "properties": {
    "iso:country":"CH",
    "sg:address":"1907",
    "sg:city":"Mayens-de-saxon",
    "sg:orig_category":"Gewinnung von Natursteinen f\u00fcr den Bau Herstellung von sonstigen Produkten aus nichtmetallischen Min",
    "sg:phone":"+41 27 956 11 32",
    "sg:postcode":"1907",
    "sg:province":"Valais",
    "wof:name":"Quarzitsteinbr\u00fcche Walter Lochmatter",
    "wof:placetype":"venue"
},
  "geometry": {"coordinates":[7.8021011353,46.1756629944],"type":"Point"}
}