{
  "type": "Feature",
  "properties": {
    "iso:country":"CH",
    "sg:address":"Rue Du Temple 25",
    "sg:city":"St-aubin-sauges",
    "sg:orig_category":"B\u00e4ckereien Konditoreien",
    "sg:phone":"+41 32 968 76 34",
    "sg:postcode":"2024",
    "sg:province":"Neuch\u00e2tel",
    "wof:name":"Boulangerie Croissant Show",
    "wof:placetype":"venue"
},
  "geometry": {"coordinates":[6.167782,46.285534],"type":"Point"}
}