{
  "type": "Feature",
  "properties": {
    "iso:country":"CH",
    "sg:address":"Seestrasse 867",
    "sg:city":"Meilen",
    "sg:orig_category":"Grosshandel mit Getr\u00e4nken Rebbau",
    "sg:phone":"+41 19230125",
    "sg:postcode":"8706",
    "sg:province":"Z\u00fcrich",
    "wof:name":"Schwarzenbach H., Weinbau",
    "wof:placetype":"venue"
},
  "geometry": {"coordinates":[8.6507797241,47.2660903931],"type":"Point"}
}