{
  "type": "Feature",
  "properties": {
    "iso:country":"CH",
    "sg:address":"Rue De La Gare 10",
    "sg:city":"Peseux",
    "sg:orig_category":"Sportvereine Turnen Vereine Damen",
    "sg:phone":"+41 32 731 67 20",
    "sg:postcode":"2034",
    "sg:province":"Neuch\u00e2tel",
    "wof:name":"Sous-section F\u00e9minine De Gymn.",
    "wof:placetype":"venue"
},
  "geometry": {"coordinates":[6.8855838776,46.9843673706],"type":"Point"}
}