{
  "type": "Feature",
  "properties": {
    "iso:country":"CH",
    "sg:address":"Waldburgweg 31",
    "sg:city":"Zollikerberg",
    "sg:orig_category":"Detailhandel mit elektrischen Haushalts, Radio U Fernsehger\u00e4ten ohne ausgepr\u00e4gten Schwerpunkt Elektr",
    "sg:phone":"+41 81 837 32 32",
    "sg:postcode":"8125",
    "sg:province":"Z\u00fcrich",
    "wof:name":"Pomatti Ag",
    "wof:placetype":"venue"
},
  "geometry": {"coordinates":[9.8370447159,46.4876785278],"type":"Point"}
}