{
  "type": "Feature",
  "properties": {
    "iso:country":"CH",
    "sg:address":"Bernstrasse 133 3052 Zollikofen. Postfach",
    "sg:city":"Zollikofen",
    "sg:orig_category":"Reiseb\u00fcros U Reiseveranstalter",
    "sg:phone":"+41 31 911 27 17",
    "sg:postcode":"3052",
    "sg:province":"Bern",
    "wof:name":"Luna Tours Ag",
    "wof:placetype":"venue"
},
  "geometry": {"coordinates":[7.4581398964,46.9957695007],"type":"Point"}
}