{
  "type": "Feature",
  "properties": {
    "iso:country":"CH",
    "sg:address":"Moosrainweg 9",
    "sg:city":"Wiedlisbach",
    "sg:orig_category":"Sportvereine Ski",
    "sg:phone":"+41 32 636 27 34",
    "sg:postcode":"4537",
    "sg:province":"Bern",
    "wof:name":"Ski-club Jura",
    "wof:placetype":"venue"
},
  "geometry": {"coordinates":[7.6474671364,47.2451248169],"type":"Point"}
}