{
  "type": "Feature",
  "properties": {
    "iso:country":"CH",
    "sg:address":"Knoblezweg 10",
    "sg:city":"Niederg\u00f6sgen",
    "sg:orig_category":"Erschliessung von Grundst\u00fccken",
    "sg:postcode":"5013",
    "sg:province":"Solothurn",
    "wof:name":"Bau-& Wohngen.schachen",
    "wof:placetype":"venue"
},
  "geometry": {"coordinates":[7.9825191498,47.3713493347],"type":"Point"}
}