{
  "type": "Feature",
  "properties": {
    "iso:country":"CH",
    "sg:address":"Schildstrasse 10",
    "sg:city":"Schaffhausen",
    "sg:orig_category":"Interessenvertretungen",
    "sg:phone":"+41 52 625 84 06",
    "sg:postcode":"8200",
    "sg:province":"Schaffhausen",
    "wof:name":"Stiftung Kolping Adolph",
    "wof:placetype":"venue"
},
  "geometry": {"coordinates":[8.6458082199,47.6982460022],"type":"Point"}
}