{
  "type": "Feature",
  "properties": {
    "iso:country":"CH",
    "sg:address":"Alpenstrasse 26",
    "sg:city":"G\u00fcmligen",
    "sg:orig_category":"Arztpraxen",
    "sg:phone":"+41 31 951 10 52",
    "sg:postcode":"3073",
    "sg:province":"Bern",
    "wof:name":"Dr.med.christoph Von R\u00fctte Arzt F.allgemeine Medizin Fmh",
    "wof:placetype":"venue"
},
  "geometry": {"coordinates":[7.498451,46.935356],"type":"Point"}
}