{
  "type": "Feature",
  "properties": {
    "iso:country":"CH",
    "sg:address":"Wermatswilerstrasse 6",
    "sg:city":"Fehraltorf",
    "sg:orig_category":"Pensionskassen",
    "sg:phone":"+41 19541212",
    "sg:postcode":"8320",
    "sg:province":"Z\u00fcrich",
    "wof:name":"Wohlfahrtsfonds Der E. Schellenberg Textildruck Ag",
    "wof:placetype":"venue"
},
  "geometry": {"coordinates":[8.7542228699,47.3856811523],"type":"Point"}
}