{
  "type": "Feature",
  "properties": {
    "iso:country":"CH",
    "sg:address":"Avenue De Miremont 7b",
    "sg:city":"Gen\u00e8ve",
    "sg:orig_category":"B\u00e4ckereien Konditoreien",
    "sg:phone":"+41 22 346 12 50",
    "sg:postcode":"1206",
    "sg:province":"Gen\u00e8ve",
    "wof:name":"A\u00efda De Sousa & Angelo Zorzi Boulangerie Et P\u00e2tisserie",
    "wof:placetype":"venue"
},
  "geometry": {"coordinates":[6.153685,46.191551],"type":"Point"}
}