{
  "type": "Feature",
  "properties": {
    "iso:country":"CH",
    "sg:address":"Birsigstrasse 115",
    "sg:city":"Basel",
    "sg:orig_category":"Sonstige mit der Informatik verbundene T\u00e4tigkeiten",
    "sg:phone":"+41 79 302 52 62",
    "sg:postcode":"4054",
    "sg:province":"Basel-Stadt",
    "wof:name":"Esat Gmbh",
    "wof:placetype":"venue"
},
  "geometry": {"coordinates":[7.5777850151,47.5503425598],"type":"Point"}
}