{
  "type": "Feature",
  "properties": {
    "iso:country":"CH",
    "sg:address":"Bahnhofstrasse 6",
    "sg:city":"Horgen",
    "sg:orig_category":"W\u00e4scherei U chemische Reinigung",
    "sg:phone":"+41 17255860",
    "sg:postcode":"8810",
    "sg:province":"Z\u00fcrich",
    "wof:name":"Textilpflege Horgen, Pia Opriessnig",
    "wof:placetype":"venue"
},
  "geometry": {"coordinates":[8.596578598,47.2612724304],"type":"Point"}
}