{
  "type": "Feature",
  "properties": {
    "iso:country":"CH",
    "sg:address":"Kloosmattstrasse 5",
    "sg:city":"Aarburg",
    "sg:orig_category":"Herstellung von sonstigen Fahrzeugen",
    "sg:phone":"+41 33 345 13 60",
    "sg:postcode":"4663",
    "sg:province":"Aargau",
    "wof:name":"Fritz Oester Wagnerei",
    "wof:placetype":"venue"
},
  "geometry": {"coordinates":[7.5609102249,46.8069267273],"type":"Point"}
}