{
  "type": "Feature",
  "properties": {
    "iso:country":"CH",
    "sg:address":"Rue D'horloge",
    "sg:city":"Buchillon",
    "sg:orig_category":"Non-Classified Establishments",
    "sg:postcode":"1164",
    "sg:province":"Vaud",
    "wof:name":"Si La Reine Des Bois E",
    "wof:placetype":"venue"
},
  "geometry": {"coordinates":[6.423227787,46.4705734253],"type":"Point"}
}