{
  "type": "Feature",
  "properties": {
    "iso:country":"CH",
    "sg:address":"Gartenstrasse 23",
    "sg:city":"Sch\u00f6nenwerd",
    "sg:orig_category":"Grosshandel mit sonstigen Maschinen U Ausr\u00fcstungen f\u00fcr Industrie, Handel U Schiffahrt Herstellung vo",
    "sg:phone":"+41 62 849 40 50",
    "sg:postcode":"5012",
    "sg:province":"Solothurn",
    "wof:name":"Wyser Ag Sch\u00f6nenwerd",
    "wof:placetype":"venue"
},
  "geometry": {"coordinates":[8.0052070618,47.3759117126],"type":"Point"}
}