{
  "type": "Feature",
  "properties": {
    "iso:country":"CH",
    "sg:address":"Avenue De L'ermitage 43",
    "sg:city":"Ch\u00eane-bougeries",
    "sg:classifiers":[
        {
            "category":"Travel",
            "subcategory":"Hotels & Motels",
            "type":"Entertainment"
        }
    ],
    "sg:postcode":"1224",
    "sg:province":"Gen\u00e8ve",
    "sg:tags":[
        "hotels",
        "mit",
        "restaurant"
    ],
    "wof:name":"H\u00f4tel Du Cheval-blanc Sa",
    "wof:placetype":"venue"
},
  "geometry": {"coordinates":[6.1789197922,46.1950073242],"type":"Point"}
}