{
  "type": "Feature",
  "properties": {
    "iso:country":"CH",
    "sg:address":"8784",
    "sg:city":"Braunwald",
    "sg:classifiers":[
        {
            "category":"Restaurant",
            "type":"Food & Drink"
        }
    ],
    "sg:phone":"+41 55 643 17 36",
    "sg:postcode":"8784",
    "sg:province":"Glarus",
    "wof:name":"Restaurant Uhu",
    "wof:placetype":"venue"
},
  "geometry": {"coordinates":[8.9982004166,46.9389533997],"type":"Point"}
}