{
  "type": "Feature",
  "properties": {
    "iso:country":"CH",
    "sg:address":"Landstrasse 81",
    "sg:city":"Wettingen",
    "sg:orig_category":"Unclassifiable Establishments",
    "sg:phone":"+41 52 213 69 37",
    "sg:postcode":"5430",
    "sg:province":"Aargau",
    "wof:name":"Belhold Ag",
    "wof:placetype":"venue"
},
  "geometry": {"coordinates":[8.3254585266,47.4665222168],"type":"Point"}
}