{
  "type": "Feature",
  "properties": {
    "iso:country":"CH",
    "sg:address":"1971",
    "sg:city":"Grimisuat",
    "sg:orig_category":"Wirtschaftspr\u00fcfung, Steuerberatung U Treuhand",
    "sg:phone":"+41 27 398 17 60",
    "sg:postcode":"1971",
    "sg:province":"Valais",
    "wof:name":"Fidugrim Joseph B\u00fctzberger Bureau Fiduciaire",
    "wof:placetype":"venue"
},
  "geometry": {"coordinates":[7.3788700104,46.2545089722],"type":"Point"}
}