{
  "type": "Feature",
  "properties": {
    "iso:country":"CH",
    "sg:address":"Turnhallenstrasse 6",
    "sg:city":"Mettschlatt",
    "sg:orig_category":"Tierheime",
    "sg:phone":"+41 52 657 15 88",
    "sg:postcode":"8252",
    "sg:province":"Thurgau",
    "wof:name":"Ernst Benz Hundeferienheim",
    "wof:placetype":"venue"
},
  "geometry": {"coordinates":[8.6988162994,47.6564865112],"type":"Point"}
}