{
  "type": "Feature",
  "properties": {
    "iso:country":"CH",
    "sg:address":"Chemin De La Glaci\u00e8re 7",
    "sg:city":"Caux",
    "sg:orig_category":"Interessenvertretungen",
    "sg:postcode":"1824",
    "sg:province":"Vaud",
    "wof:name":"Lake Geneva Forum",
    "wof:placetype":"venue"
},
  "geometry": {"coordinates":[6.9390521049,46.4345550537],"type":"Point"}
}