{
  "type": "Feature",
  "properties": {
    "iso:country":"CH",
    "sg:address":"H\u00f6heweg 115 3800 Interlaken. Postfach 446",
    "sg:city":"Interlaken",
    "sg:orig_category":"RESTAURANTS: TEA-ROOMS",
    "sg:phone":"+41 33 822 23 23",
    "sg:postcode":"3800",
    "sg:province":"Bern",
    "wof:name":"Restaurant Des Alpes, Soche",
    "wof:placetype":"venue"
},
  "geometry": {"coordinates":[7.861374855,46.6881065369],"type":"Point"}
}