{
  "type": "Feature",
  "properties": {
    "iso:country":"CH",
    "sg:address":"Dorfstrasse 22",
    "sg:city":"Belp",
    "sg:orig_category":"Herstellung von sonstigen landwirtschaftlichen Maschinen",
    "sg:phone":"+41 31 819 02 03",
    "sg:postcode":"3123",
    "sg:province":"Bern",
    "wof:name":"Stucki Landtechnik Ag",
    "wof:placetype":"venue"
},
  "geometry": {"coordinates":[7.4985909462,46.8917655945],"type":"Point"}
}