{
  "type": "Feature",
  "properties": {
    "iso:country":"CH",
    "sg:address":"Brunngasse 52",
    "sg:city":"Bern",
    "sg:orig_category":"Non-Classified Establishments",
    "sg:postcode":"3011",
    "sg:province":"Bern",
    "wof:name":"Hmc H\u00f6gstedt Management Consulting",
    "wof:placetype":"venue"
},
  "geometry": {"coordinates":[7.4486660957,46.949005127],"type":"Point"}
}