{
  "type": "Feature",
  "properties": {
    "iso:country":"CH",
    "sg:address":"Via Monte Ceneri 11",
    "sg:city":"Giubiasco",
    "sg:orig_category":"Tankstellen",
    "sg:phone":"+41 91 857 03 12",
    "sg:postcode":"6512",
    "sg:province":"Ticino",
    "wof:name":"Esso Morobbia Marco Lovaldi Stazione Di Servizio",
    "wof:placetype":"venue"
},
  "geometry": {"coordinates":[9.0078325272,46.1705055237],"type":"Point"}
}