{
  "type": "Feature",
  "properties": {
    "addr:full":"Madeleine Rue De La 10 1204 Gen\u00e8ve. Postfach Gen\u00e8ve Gen\u00e8ve 1201",
    "addr:housenumber":"10",
    "addr:postcode":"1204;postfach;1201",
    "addr:street":"Rue De La",
    "iso:country":"CH",
    "sg:address":"Madeleine Rue De La 10 1204 Gen\u00e8ve. Postfach",
    "sg:city":"Gen\u00e8ve",
    "sg:orig_category":"Betrieb U technische Hilfsdienste des Kultur U Unterhaltungswesens",
    "sg:postcode":"1201",
    "sg:province":"Gen\u00e8ve",
    "wof:name":"Soci\u00e9t\u00e9 De La Salle Centrale De La Madeleine",
    "wof:placetype":"venue"
},
  "geometry": {"coordinates":[6.148457,46.202221],"type":"Point"}
}