{
  "type": "Feature",
  "properties": {
    "iso:country":"CH",
    "sg:address":"Gewerbestrasse 2",
    "sg:city":"Frauenfeld",
    "sg:orig_category":"Einzelhandel mit Automobilteilen U Zubeh\u00f6r Herstellung von Bereifungen",
    "sg:phone":"+41 79 407 22 45",
    "sg:postcode":"8500",
    "sg:province":"Thurgau",
    "wof:name":"Pjv Pneuhaus Wil Ag",
    "wof:placetype":"venue"
},
  "geometry": {"coordinates":[9.0677604675,47.4651298523],"type":"Point"}
}