{
  "type": "Feature",
  "properties": {
    "iso:country":"CH",
    "sg:address":"Rue Du Grand-st-jean 5",
    "sg:city":"Lausanne",
    "sg:orig_category":"Fotografische Ateliers",
    "sg:phone":"+41 21 312 35 88",
    "sg:postcode":"1003",
    "sg:province":"Vaud",
    "wof:name":"Suzi Pilet Atelier De Photographie",
    "wof:placetype":"venue"
},
  "geometry": {"coordinates":[6.6317429543,46.521156311],"type":"Point"}
}