{
  "type": "Feature",
  "properties": {
    "iso:country":"CH",
    "sg:address":"Avenue Georgette 5 1003 Lausanne. Postfach",
    "sg:city":"Lausanne",
    "sg:orig_category":"K\u00fcnstlerische Schulen",
    "sg:phone":"+41 21 312 09 81",
    "sg:postcode":"1002",
    "sg:province":"Vaud",
    "wof:name":"Institut De Rebaupierre Ecole Sup\u00e9rieure De Musique",
    "wof:placetype":"venue"
},
  "geometry": {"coordinates":[6.6378908157,46.5169029236],"type":"Point"}
}