{
  "type": "Feature",
  "properties": {
    "iso:country":"CH",
    "sg:address":"Clendy Rue De 9 1400 Yverdon-les-bains. Postfach",
    "sg:city":"Cheseaux-nor\u00e9az",
    "sg:orig_category":"RESTAURANTS: TEA-ROOMS",
    "sg:postcode":"1400",
    "sg:province":"Vaud",
    "wof:name":"De Jesus Oliveira Maria Tea-room Saudade",
    "wof:placetype":"venue"
},
  "geometry": {"coordinates":[6.6542129517,46.7782478333],"type":"Point"}
}