{
  "type": "Feature",
  "properties": {
    "iso:country":"CH",
    "sg:address":"Laxstrasse 8890 Flums. Postfach 93",
    "sg:city":"Flums",
    "sg:orig_category":"Chemin\u00e9e- and Ofenbau",
    "sg:phone":"+41 81 710 09 65",
    "sg:postcode":"8890",
    "sg:province":"St. Gallen",
    "wof:name":"Paul Stoop Ag Ofen- & Chemin\u00e9ebau",
    "wof:placetype":"venue"
},
  "geometry": {"coordinates":[9.343662,47.097645],"type":"Point"}
}