{
  "type": "Feature",
  "properties": {
    "iso:country":"CH",
    "sg:address":"Vorstadt 27 8200 Schaffhausen. Postfach 636",
    "sg:city":"Schaffhausen",
    "sg:orig_category":"Advokaturb\u00fcros",
    "sg:phone":"+41 41 262 01 10",
    "sg:postcode":"8201",
    "sg:province":"Schaffhausen",
    "wof:name":"Christoph Zurm\u00fchle Advokaturb\u00fcro",
    "wof:placetype":"venue"
},
  "geometry": {"coordinates":[8.2752,47.077477],"type":"Point"}
}