{
  "type": "Feature",
  "properties": {
    "iso:country":"CH",
    "sg:address":"Kramgasse 60",
    "sg:city":"Bern",
    "sg:orig_category":"Kunsthandel",
    "sg:phone":"+41 31 311 25 26",
    "sg:postcode":"3011",
    "sg:province":"Bern",
    "wof:name":"Altstadt-galerie Ag Gem\u00e4lde-ausstellung",
    "wof:placetype":"venue"
},
  "geometry": {"coordinates":[7.4495038986,46.948097229],"type":"Point"}
}