{
  "type": "Feature",
  "properties": {
    "iso:country":"CH",
    "sg:address":"Wildensteinerstrasse 12",
    "sg:city":"Bubendorf",
    "sg:orig_category":"Detailhandel mit Teppichen Verlegen von Fussboden",
    "sg:phone":"+41 19312936",
    "sg:postcode":"4416",
    "sg:province":"Basel-Landschaft",
    "wof:name":"Wyss Stephan Ag Naturprodukte; Herstellung, Handel",
    "wof:placetype":"venue"
},
  "geometry": {"coordinates":[7.7356991768,47.4446678162],"type":"Point"}
}