{
  "type": "Feature",
  "properties": {
    "iso:country":"CH",
    "sg:address":"Maison Du Paysan 1964 Conthey. Postfach",
    "sg:city":"Conthey",
    "sg:orig_category":"Interessenvertretungen",
    "sg:postcode":"1964",
    "sg:province":"Valais",
    "wof:name":"Interprofession De La Vigne Et Du Vin Du Valais",
    "wof:placetype":"venue"
},
  "geometry": {"coordinates":[7.2982797623,46.224319458],"type":"Point"}
}