{
  "type": "Feature",
  "properties": {
    "iso:country":"CH",
    "sg:address":"8499",
    "sg:city":"Sternenberg",
    "sg:orig_category":"Sportvereine Sch\u00fctzen",
    "sg:phone":"+41 52 386 16 39",
    "sg:postcode":"8499",
    "sg:province":"Z\u00fcrich",
    "wof:name":"Sch\u00fctzenverein",
    "wof:placetype":"venue"
},
  "geometry": {"coordinates":[8.9102401733,47.3872947693],"type":"Point"}
}