{
  "type": "Feature",
  "properties": {
    "iso:country":"CH",
    "sg:address":"Dorfstrasse 49",
    "sg:city":"Fisibach",
    "sg:orig_category":"Sportvereine Turnen Vereine Damen",
    "sg:postcode":"5467",
    "sg:province":"Aargau",
    "wof:name":"Damenriege",
    "wof:placetype":"venue"
},
  "geometry": {"coordinates":[8.4068927765,47.5636863708],"type":"Point"}
}