{
  "type": "Feature",
  "properties": {
    "iso:country":"CH",
    "sg:address":"6953 Lugaggia. Postfach",
    "sg:city":"Lugaggia",
    "sg:orig_category":"Herstellung von chemischen Grundstoffen Herstellung von sonstigen landwirtschaftlichen Maschinen",
    "sg:phone":"+41 91 930 01 93",
    "sg:postcode":"6953",
    "sg:province":"Ticino",
    "wof:name":"Bioagrotec Di Storni Achille Prodotti Multifunzionali Per L'agricoltura, Floricoltura Ecc.; Comm.",
    "wof:placetype":"venue"
},
  "geometry": {"coordinates":[8.9708499908,46.055480957],"type":"Point"}
}