{
  "type": "Feature",
  "properties": {
    "iso:country":"CH",
    "sg:address":"Place Du Pr\u00e9-de-foire 3",
    "sg:city":"Martigny",
    "sg:orig_category":"G\u00fcterbef\u00f6rderung im Strassenverkehr",
    "sg:phone":"+41 27 723 15 31",
    "sg:postcode":"1920",
    "sg:province":"Valais",
    "wof:name":"Thierrin Transports S\u00e0rl",
    "wof:placetype":"venue"
},
  "geometry": {"coordinates":[7.0646848679,46.0925712585],"type":"Point"}
}