{
  "type": "Feature",
  "properties": {
    "iso:country":"CH",
    "sg:address":"Schlosswarte",
    "sg:city":"Balsthal",
    "sg:orig_category":"Museen",
    "sg:phone":"+41 62 391 54 32",
    "sg:postcode":"4710",
    "sg:province":"Solothurn",
    "wof:name":"Museum Alt-falkenstein",
    "wof:placetype":"venue"
},
  "geometry": {"coordinates":[7.6906189919,47.3071365356],"type":"Point"}
}