{
  "type": "Feature",
  "properties": {
    "iso:country":"CH",
    "sg:address":"Chemin Du Poste 1",
    "sg:city":"Chavannes-de-bogis",
    "sg:orig_category":"Sonstige mit der Informatik verbundene T\u00e4tigkeiten",
    "sg:phone":"+41 22 960 98 20",
    "sg:postcode":"1279",
    "sg:province":"Vaud",
    "wof:name":"Goelaan Sa Commercialisat. De Syst\u00e8mes, Services Informatiques \u00e0 Base De Solutions Logiciels Etc",
    "wof:placetype":"venue"
},
  "geometry": {"coordinates":[6.1621499062,46.3435401917],"type":"Point"}
}