{
  "type": "Feature",
  "properties": {
    "addr:full":"Baarerstrasse 53 Zug Zug 6300",
    "addr:housenumber":"53",
    "addr:postcode":"6300",
    "addr:street":"Baarerstrasse;Zug",
    "iso:country":"CH",
    "sg:address":"Baarerstrasse 53",
    "sg:city":"Zug",
    "sg:orig_category":"Architektur U Ingenieurb\u00fcros",
    "sg:phone":"+41 41 728 71 10",
    "sg:postcode":"6300",
    "sg:province":"Zug",
    "wof:name":"Unimo Real Estate Ag",
    "wof:placetype":"venue"
},
  "geometry": {"coordinates":[8.516937,47.17469],"type":"Point"}
}