{
  "type": "Feature",
  "properties": {
    "iso:country":"CH",
    "sg:address":"Allmendstrasse 42 3600 Thun. Postfach 1228",
    "sg:city":"Thun",
    "sg:orig_category":"Autotransporte M\u00f6bel Autotransporte international",
    "sg:phone":"+41 32 913 02 23",
    "sg:postcode":"3601",
    "sg:province":"Bern",
    "wof:name":"Transports Mauron Sa",
    "wof:placetype":"venue"
},
  "geometry": {"coordinates":[6.826032,47.101254],"type":"Point"}
}