{
  "type": "Feature",
  "properties": {
    "iso:country":"CH",
    "sg:address":"Bernstrasse 67",
    "sg:city":"Konolfingen",
    "sg:classifiers":[
        {
            "category":"Restaurant",
            "type":"Food & Drink"
        }
    ],
    "sg:phone":"+41 31 791 01 35",
    "sg:postcode":"3510",
    "sg:province":"Bern",
    "wof:name":"Restaurant Sternen",
    "wof:placetype":"venue"
},
  "geometry": {"coordinates":[7.6045379639,46.8773574829],"type":"Point"}
}