{
  "type": "Feature",
  "properties": {
    "iso:country":"CH",
    "sg:address":"Jurastrasse 24",
    "sg:city":"Biberist",
    "sg:orig_category":"Herstellung von Werkzeugen",
    "sg:phone":"+41 32 672 32 46",
    "sg:postcode":"4562",
    "sg:province":"Solothurn",
    "wof:name":"Ren\u00e9 Schibler Werkzeugbau",
    "wof:placetype":"venue"
},
  "geometry": {"coordinates":[7.558866024,47.1911277771],"type":"Point"}
}