{
  "type": "Feature",
  "properties": {
    "iso:country":"CH",
    "sg:address":"Alte Baarerstrasse 1",
    "sg:city":"Zug",
    "sg:orig_category":"Handelsvermittlung von Textilien, Bekleidung, Schuhen U Lederwaren",
    "sg:postcode":"6300",
    "sg:province":"Zug",
    "wof:name":"Textilagentur E. Scholz",
    "wof:placetype":"venue"
},
  "geometry": {"coordinates":[8.5246400833,47.1728401184],"type":"Point"}
}