{
  "type": "Feature",
  "properties": {
    "iso:country":"CH",
    "sg:address":"Ringstrasse 7",
    "sg:city":"Frutigen",
    "sg:orig_category":"Geb\u00e4ude, Wohnungsreinigung",
    "sg:phone":"+41 33 671 42 49",
    "sg:postcode":"3714",
    "sg:province":"Bern",
    "wof:name":"Jakob Altorfer Reinigungsdienst",
    "wof:placetype":"venue"
},
  "geometry": {"coordinates":[7.6481928825,46.5846786499],"type":"Point"}
}