{
  "type": "Feature",
  "properties": {
    "iso:country":"CH",
    "sg:address":"Asylstrasse",
    "sg:city":"Horgen",
    "sg:orig_category":"Pensionskassen",
    "sg:phone":"+41 17281111",
    "sg:postcode":"8810",
    "sg:province":"Z\u00fcrich",
    "wof:name":"Personalvorsorgestiftung Spital Zimmerberg",
    "wof:placetype":"venue"
},
  "geometry": {"coordinates":[8.5893220901,47.2633972168],"type":"Point"}
}