{
  "type": "Feature",
  "properties": {
    "iso:country":"CH",
    "sg:address":"Schneidergasse 26",
    "sg:city":"Basel",
    "sg:orig_category":"Detailhandel mit Geschenkartikeln U Souvenirs Detailhandel mit Tabakwaren",
    "sg:phone":"+41 61 261 13 61",
    "sg:postcode":"4051",
    "sg:province":"Basel-Stadt",
    "wof:name":"Fischer Beatrice Geschenkartikelhandel",
    "wof:placetype":"venue"
},
  "geometry": {"coordinates":[7.5865740776,47.5577964783],"type":"Point"}
}