{
  "type": "Feature",
  "properties": {
    "addr:full":"Seestrasse 51 Gersau Schwyz 6442",
    "addr:housenumber":"51",
    "addr:postcode":"6442",
    "addr:street":"Seestrasse;Schwyz",
    "iso:country":"CH",
    "sg:address":"Seestrasse 51",
    "sg:city":"Gersau",
    "sg:orig_category":"Arztpraxen",
    "sg:phone":"+41 41 828 12 44",
    "sg:postcode":"6442",
    "sg:province":"Schwyz",
    "wof:name":"Dr.med.rudolf V\u00f6lkle Arzt F.allgemeine Medizin Fmh",
    "wof:placetype":"venue"
},
  "geometry": {"coordinates":[8.522162,46.99276],"type":"Point"}
}