{
  "type": "Feature",
  "properties": {
    "iso:country":"CH",
    "sg:address":"Pl. De L'h\u00f4tel-de-ville 2",
    "sg:city":"Morges",
    "sg:orig_category":"Interessenvertretungen",
    "sg:postcode":"1110",
    "sg:province":"Vaud",
    "wof:name":"Fondation Pernet Georges Et Anny",
    "wof:placetype":"venue"
},
  "geometry": {"coordinates":[5.4520339966,46.4692268372],"type":"Point"}
}