{
  "type": "Feature",
  "properties": {
    "iso:country":"CH",
    "sg:address":"Schimmelstrasse 7",
    "sg:city":"Z\u00fcrich",
    "sg:orig_category":"Reiseb\u00fcros U Reiseveranstalter",
    "sg:phone":"+41 14617073",
    "sg:postcode":"8003",
    "sg:province":"Z\u00fcrich",
    "wof:name":"Perfect Travel Lapidot J.",
    "wof:placetype":"venue"
},
  "geometry": {"coordinates":[8.5253620148,47.3697090149],"type":"Point"}
}