{
  "type": "Feature",
  "properties": {
    "iso:country":"CH",
    "sg:address":"Aegertenstrasse 32",
    "sg:city":"Z\u00fcrich",
    "sg:orig_category":"Eisenbahnverkehr",
    "sg:postcode":"8003",
    "sg:province":"Z\u00fcrich",
    "wof:name":"Moser Bahn Und Elektrotechnik Gmbh",
    "wof:placetype":"venue"
},
  "geometry": {"coordinates":[8.5229520798,47.3692131042],"type":"Point"}
}