{
  "type": "Feature",
  "properties": {
    "iso:country":"CH",
    "sg:address":"Denkmalstrasse 11",
    "sg:city":"Luzern",
    "sg:orig_category":"Museen",
    "sg:phone":"+41 41 410 40 64",
    "sg:postcode":"6006",
    "sg:province":"Luzern",
    "wof:name":"Alpineum Alpen Panorama Museum",
    "wof:placetype":"venue"
},
  "geometry": {"coordinates":[8.3102760315,47.057975769],"type":"Point"}
}