{
  "type": "Feature",
  "properties": {
    "iso:country":"CH",
    "sg:address":"Lindenstrasse 2",
    "sg:city":"Buttwil",
    "sg:orig_category":"Grosshandel mit Maschinen U Ausr\u00fcstungen Grosshandel mit sonstigen Maschinen U Ausr\u00fcstungen f\u00fcr Indu",
    "sg:phone":"+41 56 664 23 36",
    "sg:postcode":"5632",
    "sg:province":"Aargau",
    "wof:name":"Lange Gmbh",
    "wof:placetype":"venue"
},
  "geometry": {"coordinates":[8.3118391037,47.2667808533],"type":"Point"}
}