{
  "type": "Feature",
  "properties": {
    "iso:country":"CH",
    "sg:address":"6939",
    "sg:city":"Arosio",
    "sg:classifiers":[
        {
            "category":"Restaurant",
            "type":"Food & Drink"
        }
    ],
    "sg:phone":"+41 91 609 11 31",
    "sg:postcode":"6939",
    "sg:province":"Ticino",
    "wof:name":"Osteria Della Campagna",
    "wof:placetype":"venue"
},
  "geometry": {"coordinates":[8.9027500153,46.0467605591],"type":"Point"}
}