{
  "type": "Feature",
  "properties": {
    "iso:country":"CH",
    "sg:address":"B\u00fchlstrasse 9",
    "sg:city":"Schaffhausen",
    "sg:orig_category":"Unclassifiable Establishments",
    "sg:postcode":"8200",
    "sg:province":"Schaffhausen",
    "wof:name":"Tcm St. Moritz Ag Trad.chinesische Medizin",
    "wof:placetype":"venue"
},
  "geometry": {"coordinates":[9.8371305466,46.4979324341],"type":"Point"}
}