{
  "type": "Feature",
  "properties": {
    "iso:country":"CH",
    "sg:address":"Sonnhaldenstrasse 3",
    "sg:city":"Z\u00fcrich",
    "sg:orig_category":"Gesundheitswesen Organisationen des Gesundheitswesen",
    "sg:phone":"+41 12625363",
    "sg:postcode":"8032",
    "sg:province":"Z\u00fcrich",
    "wof:name":"Betreuungsdienst Kitchen M.",
    "wof:placetype":"venue"
},
  "geometry": {"coordinates":[8.5617494583,47.3668136597],"type":"Point"}
}