{
  "type": "Feature",
  "properties": {
    "addr:full":"Passwangstrasse 23 4226 Breitenbach. Postfach 332 Breitenbach Solothurn 4226",
    "addr:housenumber":"23;332",
    "addr:postcode":"4226 breitenbach.;4226",
    "addr:street":"Passwangstrasse;Postfach",
    "iso:country":"CH",
    "sg:address":"Passwangstrasse 23 4226 Breitenbach. Postfach 332",
    "sg:city":"Breitenbach",
    "sg:orig_category":"Detailhandel mit Brillen U anderen Sehhilfen Fachdetailhandel in Verkaufsr\u00e4umen",
    "sg:phone":"+41 61 781 33 77",
    "sg:postcode":"4226",
    "sg:province":"Solothurn",
    "wof:name":"Waldner Augenoptik",
    "wof:placetype":"venue"
},
  "geometry": {"coordinates":[7.543421,47.405704],"type":"Point"}
}