{
  "type": "Feature",
  "properties": {
    "addr:full":"Rue De La Plaine 5 Yverdon-les-bains Vaud 1400",
    "addr:housenumber":"5",
    "addr:postcode":"1400",
    "addr:street":"Rue De La Plaine",
    "iso:country":"CH",
    "sg:address":"Rue De La Plaine 5",
    "sg:city":"Yverdon-les-bains",
    "sg:orig_category":"Detailhandel mit Beleuchtungs U Haushaltsgegenst\u00e4nden Einbau von Schreinerwaren",
    "sg:phone":"+41 24 424 24 62",
    "sg:postcode":"1400",
    "sg:province":"Vaud",
    "wof:name":"Fust Sa",
    "wof:placetype":"venue"
},
  "geometry": {"coordinates":[6.642353,46.778034],"type":"Point"}
}