{
  "type": "Feature",
  "properties": {
    "iso:country":"CH",
    "sg:address":"Landstr. 1c",
    "sg:city":"Burgistein",
    "sg:orig_category":"Instandhaltung U Reparatur von Automobilen",
    "sg:phone":"+41 33 356 21 51",
    "sg:postcode":"3664",
    "sg:province":"Bern",
    "wof:name":"Stockhorn-garage, Albert B\u00fchler",
    "wof:placetype":"venue"
},
  "geometry": {"coordinates":[7.5183367729,46.7932929993],"type":"Point"}
}