{
  "type": "Feature",
  "properties": {
    "iso:country":"CH",
    "sg:address":"Z\u00fcberwangen",
    "sg:city":"Z\u00fcberwangen",
    "sg:orig_category":"Verwertung von Milch",
    "sg:postcode":"9523",
    "sg:province":"St. Gallen",
    "wof:name":"K\u00e4sereigenossenschaft Weiern",
    "wof:placetype":"venue"
},
  "geometry": {"coordinates":[9.08934021,47.4658203125],"type":"Point"}
}