{
  "type": "Feature",
  "properties": {
    "iso:country":"CH",
    "sg:address":"Steinacherstrasse 35",
    "sg:city":"Urdorf",
    "sg:orig_category":"Instandhaltung U Reparatur von Automobilen",
    "sg:phone":"+41 17771935",
    "sg:postcode":"8902",
    "sg:province":"Z\u00fcrich",
    "wof:name":"Carrosserie Grogg Urdorf Ag",
    "wof:placetype":"venue"
},
  "geometry": {"coordinates":[8.4198961258,47.3942718506],"type":"Point"}
}