{
  "type": "Feature",
  "properties": {
    "iso:country":"CH",
    "sg:address":"In Der Brunnmatt 2",
    "sg:city":"Unterengstringen",
    "sg:orig_category":"Grosshandel mit pharmazeutischen Erzeugnissen, medizinischen U orthop\u00e4dischen Artikeln",
    "sg:phone":"+41 17502921",
    "sg:postcode":"8103",
    "sg:province":"Z\u00fcrich",
    "wof:name":"Medical Products, Gerhard Kraatz",
    "wof:placetype":"venue"
},
  "geometry": {"coordinates":[8.4470748901,47.4148788452],"type":"Point"}
}