{
  "type": "Feature",
  "properties": {
    "iso:country":"CH",
    "sg:address":"Vorderdorfstrasse 5",
    "sg:city":"Oberegg",
    "sg:orig_category":"Herstellung von keramischen Haushaltswaren U Ziergegenst\u00e4nden",
    "sg:phone":"+41 71 891 42 77",
    "sg:postcode":"9413",
    "sg:province":"Appenzell Innerhoden",
    "wof:name":"Elsa Gamba Chum & Lueg Keramikatelier",
    "wof:placetype":"venue"
},
  "geometry": {"coordinates":[9.5538864136,47.4217720032],"type":"Point"}
}