{
  "type": "Feature",
  "properties": {
    "iso:country":"CH",
    "sg:address":"Eggen",
    "sg:city":"Amsoldingen",
    "sg:orig_category":"Bauschreinerei Herstellung von Konstruktionsteilen, Fertigbauteilen U Ausbauelementen aus Holz",
    "sg:phone":"+41 33 341 11 57",
    "sg:postcode":"3633",
    "sg:province":"Bern",
    "wof:name":"Inderm\u00fchle Innenausbau Ag",
    "wof:placetype":"venue"
},
  "geometry": {"coordinates":[7.575826,46.729313],"type":"Point"}
}