{
  "type": "Feature",
  "properties": {
    "iso:country":"CH",
    "sg:address":"J.-c. Heerstrasse 1b",
    "sg:city":"D\u00fcrnten",
    "sg:orig_category":"Architekturb\u00fcros",
    "sg:phone":"+41 55 240 11 67",
    "sg:postcode":"8635",
    "sg:province":"Z\u00fcrich",
    "wof:name":"Walter Rigamonti Architektur-& Planungsb\u00fcro",
    "wof:placetype":"venue"
},
  "geometry": {"coordinates":[8.87327,47.27615],"type":"Point"}
}