{
  "type": "Feature",
  "properties": {
    "iso:country":"CH",
    "sg:address":"Via Barchee 21",
    "sg:city":"Losone",
    "sg:orig_category":"Gem\u00fcsebau",
    "sg:phone":"+41 91 646 86 78",
    "sg:postcode":"6616",
    "sg:province":"Ticino",
    "wof:name":"Oberti Fratelli Orticoltura",
    "wof:placetype":"venue"
},
  "geometry": {"coordinates":[8.9727640152,45.8888816833],"type":"Point"}
}