{
  "type": "Feature",
  "properties": {
    "iso:country":"CH",
    "sg:address":"Anglikerstrasse 96",
    "sg:city":"Villmergen",
    "sg:orig_category":"Sportvereine Ballsport Tischtennis",
    "sg:phone":"+41 56 621 30 84",
    "sg:postcode":"5612",
    "sg:province":"Aargau",
    "wof:name":"Ttc Wohlen",
    "wof:placetype":"venue"
},
  "geometry": {"coordinates":[8.2518177032,47.3508682251],"type":"Point"}
}