{
  "type": "Feature",
  "properties": {
    "iso:country":"CH",
    "sg:address":"Baselstrasse 53",
    "sg:city":"Riehen",
    "sg:orig_category":"Sonstige Institutionen des Sozialwesens ohne Beherbergung",
    "sg:phone":"+41 41 870 04 14",
    "sg:postcode":"4125",
    "sg:province":"Basel-Stadt",
    "wof:name":"Opferhilfe-beratungsstelle Uri",
    "wof:placetype":"venue"
},
  "geometry": {"coordinates":[8.6079673767,46.8822975159],"type":"Point"}
}