{
  "type": "Feature",
  "properties": {
    "iso:country":"CH",
    "sg:address":"Melchenb\u00fchlweg 8",
    "sg:city":"Bern",
    "sg:orig_category":"Kunsthandel",
    "sg:phone":"+41 31 939 15 15",
    "sg:postcode":"3006",
    "sg:province":"Bern",
    "wof:name":"Galerie Papillon",
    "wof:placetype":"venue"
},
  "geometry": {"coordinates":[7.4762182236,46.9505195618],"type":"Point"}
}