{
  "type": "Feature",
  "properties": {
    "iso:country":"CH",
    "sg:address":"1610",
    "sg:city":"Oron-la-ville",
    "sg:classifiers":[
        {
            "category":"Travel",
            "subcategory":"Hotels & Motels",
            "type":"Entertainment"
        }
    ],
    "sg:phone":"+41 21 691 65 45",
    "sg:postcode":"1610",
    "sg:province":"Vaud",
    "sg:tags":[
        "hotels",
        "mit",
        "restaurant"
    ],
    "wof:name":"Piotet Thierry",
    "wof:placetype":"venue"
},
  "geometry": {"coordinates":[6.5606751442,46.525177002],"type":"Point"}
}