{
  "type": "Feature",
  "properties": {
    "iso:country":"CH",
    "sg:address":"Buckhauserstrasse 24 8048 Z\u00fcrich. Postfach",
    "sg:city":"Z\u00fcrich",
    "sg:orig_category":"Detailhandel mit elektrischen Haushalts-,Radio U Fernsehger\u00e4ten sowie Musikinstrumenten",
    "sg:postcode":"8048",
    "sg:province":"Z\u00fcrich",
    "wof:name":"Disky Communications Schweiz Gmbh Produkte, Bes. Ton, Bildtr\u00e4ger; Kauf, Verkauf, Vertrieb",
    "wof:placetype":"venue"
},
  "geometry": {"coordinates":[8.492726326,47.3845863342],"type":"Point"}
}