{
  "type": "Feature",
  "properties": {
    "iso:country":"CH",
    "sg:address":"Gallizistrasse 10",
    "sg:city":"Buttwil",
    "sg:orig_category":"Grosshandel mit Eisenwaren sowie Installationsbedarf f\u00fcr Gas, Wasser U Heizung Instandhaltung U Repa",
    "sg:phone":"+41 79 207 90 54",
    "sg:postcode":"5632",
    "sg:province":"Aargau",
    "wof:name":"M\u00fcller's Service & Verkauf Von Garagenbedarf",
    "wof:placetype":"venue"
},
  "geometry": {"coordinates":[8.3106060028,47.2658233643],"type":"Point"}
}