{
  "type": "Feature",
  "properties": {
    "iso:country":"CH",
    "sg:address":"Route D'ollon 8",
    "sg:city":"Aigle",
    "sg:orig_category":"Dauerkulturbau Rebbau",
    "sg:phone":"+41 24 466 25 13",
    "sg:postcode":"1860",
    "sg:province":"Vaud",
    "wof:name":"Junod Georges Et Cie Sa",
    "wof:placetype":"venue"
},
  "geometry": {"coordinates":[7.483685,46.291245],"type":"Point"}
}