{
  "type": "Feature",
  "properties": {
    "iso:country":"CH",
    "sg:address":"Schwarzenburgstrasse 291",
    "sg:city":"K\u00f6niz",
    "sg:orig_category":"Einrahmungen",
    "sg:phone":"+41 31 971 01 87",
    "sg:postcode":"3098",
    "sg:province":"Bern",
    "wof:name":"Italo Magnaguagno Rahmenfabrik Pro Arte",
    "wof:placetype":"venue"
},
  "geometry": {"coordinates":[7.4137101173,46.9220314026],"type":"Point"}
}