{
  "type": "Feature",
  "properties": {
    "iso:country":"CH",
    "sg:address":"Im Zentrum 23",
    "sg:city":"Volketswil",
    "sg:orig_category":"Herstellung von sonstigen Metallwaren",
    "sg:phone":"+41 19456356",
    "sg:postcode":"8604",
    "sg:province":"Z\u00fcrich",
    "wof:name":"W-bau Gmbh",
    "wof:placetype":"venue"
},
  "geometry": {"coordinates":[8.6810178757,47.387512207],"type":"Point"}
}