{
  "type": "Feature",
  "properties": {
    "iso:country":"CH",
    "sg:address":"Ausmattstrasse 1",
    "sg:city":"Muttenz",
    "sg:orig_category":"Sonstige Aktivit\u00e4ten der nicht-\u00e4rztlichen Medizinalberufe",
    "sg:phone":"+41 52 235 03 17",
    "sg:postcode":"4132",
    "sg:province":"Basel-Landschaft",
    "wof:name":"Sibylle Graf Ennapro Graf",
    "wof:placetype":"venue"
},
  "geometry": {"coordinates":[8.7607221603,47.4835586548],"type":"Point"}
}