{
  "type": "Feature",
  "properties": {
    "iso:country":"CH",
    "sg:address":"B\u00e4rengasse",
    "sg:city":"Zofingen",
    "sg:orig_category":"Versicherungen Generalagenturen",
    "sg:phone":"+41 62 751 15 40",
    "sg:postcode":"4800",
    "sg:province":"Aargau",
    "wof:name":"Winterthur-versicherungen Generalagentur",
    "wof:placetype":"venue"
},
  "geometry": {"coordinates":[7.9442601204,47.2903900146],"type":"Point"}
}