{
  "type": "Feature",
  "properties": {
    "iso:country":"CH",
    "sg:address":"Gibelstrasse 58 2540 Grenchen. Postfach",
    "sg:city":"Grenchen",
    "sg:orig_category":"Werbung",
    "sg:phone":"+41 32 968 00 20",
    "sg:postcode":"2540",
    "sg:province":"Solothurn",
    "wof:name":"G\u00f6tz C. & G.",
    "wof:placetype":"venue"
},
  "geometry": {"coordinates":[6.8276081085,47.1069221497],"type":"Point"}
}