{
  "type": "Feature",
  "properties": {
    "iso:country":"CH",
    "sg:address":"Sonnef\u00e4ld 22",
    "sg:city":"Rafz",
    "sg:orig_category":"Arztpraxen",
    "sg:phone":"+41 17840438",
    "sg:postcode":"8197",
    "sg:province":"Z\u00fcrich",
    "wof:name":"Dr.med.alfons Zortea Arzt F.allgemeine Medizin Fmh",
    "wof:placetype":"venue"
},
  "geometry": {"coordinates":[8.829636,47.228085],"type":"Point"}
}