{
  "type": "Feature",
  "properties": {
    "iso:country":"CH",
    "sg:address":"3627",
    "sg:city":"Heimberg",
    "sg:orig_category":"Herstellung von Brot U Backwaren Herstellung von Dauerbackwaren",
    "sg:phone":"+41 33 437 17 61",
    "sg:postcode":"3627",
    "sg:province":"Bern",
    "wof:name":"Chocolat Ammann Ag",
    "wof:placetype":"venue"
},
  "geometry": {"coordinates":[7.6062150002,46.7919998169],"type":"Point"}
}