{
  "type": "Feature",
  "properties": {
    "addr:full":"Rue Du Grand-verger 14 Martigny Valais 1920",
    "addr:housenumber":"14",
    "addr:postcode":"1920",
    "addr:street":"Rue Du Grand-Verger",
    "iso:country":"CH",
    "sg:address":"Rue Du Grand-verger 14",
    "sg:city":"Martigny",
    "sg:orig_category":"Detailhandel mit Blumen U Pflanzen Fachdetailhandel in Verkaufsr\u00e4umen",
    "sg:phone":"+41 41 870 61 61",
    "sg:postcode":"1920",
    "sg:province":"Valais",
    "wof:name":"Casa Fiori, Sicher Und Lussmann",
    "wof:placetype":"venue"
},
  "geometry": {"coordinates":[8.650059,46.874519],"type":"Point"}
}