{
  "type": "Feature",
  "properties": {
    "iso:country":"CH",
    "sg:address":"Route Des Cerisier 12 1723 Marly. Postfach",
    "sg:city":"Marly",
    "sg:orig_category":"Erbringung von sonstigen Dienstleistungen f\u00fcr Unterhaltung, Erholung U Freizeit",
    "sg:postcode":"1723",
    "sg:province":"Fribourg",
    "wof:name":"Bmg Music Management Boin Et Marti Management De Groupes De Musique",
    "wof:placetype":"venue"
},
  "geometry": {"coordinates":[7.1628937721,46.7731819153],"type":"Point"}
}