{
  "type": "Feature",
  "properties": {
    "iso:country":"CH",
    "sg:address":"Grand'rue 23",
    "sg:city":"Moudon",
    "sg:orig_category":"Detailhandel mit Brot, Back U S\u00fcsswaren",
    "sg:phone":"+41 21 905 10 73",
    "sg:postcode":"1510",
    "sg:province":"Vaud",
    "wof:name":"Claude Paquier Boulangerie & P\u00e2tisserie",
    "wof:placetype":"venue"
},
  "geometry": {"coordinates":[6.796222,46.669727],"type":"Point"}
}