{
  "type": "Feature",
  "properties": {
    "iso:country":"CH",
    "sg:address":"Taastrasse 16",
    "sg:city":"Degersheim",
    "sg:orig_category":"Herstellung von Ger\u00e4ten der Elektrizit\u00e4tserzeugung, -verteilung u.\u00e4. -Herstellung von elektronischen",
    "sg:phone":"+41 71 370 00 60",
    "sg:postcode":"9113",
    "sg:province":"St. Gallen",
    "wof:name":"Ritel Ag",
    "wof:placetype":"venue"
},
  "geometry": {"coordinates":[9.1929187775,47.373626709],"type":"Point"}
}