{
  "type": "Feature",
  "properties": {
    "addr:full":"Avenue Des Platanes 13 Sierre Valais 3960",
    "addr:housenumber":"13",
    "addr:postcode":"3960",
    "addr:street":"Avenue Des Platanes",
    "iso:country":"CH",
    "sg:address":"Avenue Des Platanes 13",
    "sg:city":"Sierre",
    "sg:orig_category":"Bauschreinerei Zimmerei, Ingenieurholzbau",
    "sg:phone":"+41 27 456 35 58",
    "sg:postcode":"3960",
    "sg:province":"Valais",
    "wof:name":"Olivier Schallbetter Menuiserie & Charpente",
    "wof:placetype":"venue"
},
  "geometry": {"coordinates":[7.529665,46.289673],"type":"Point"}
}