{
  "type": "Feature",
  "properties": {
    "iso:country":"CH",
    "sg:address":"1981",
    "sg:city":"Vex",
    "sg:classifiers":[
        {
            "category":"Restaurant",
            "type":"Food & Drink"
        }
    ],
    "sg:phone":"+41 81 833 10 90",
    "sg:postcode":"1981",
    "sg:province":"Valais",
    "wof:name":"Restaurant Chesa Al Parc",
    "wof:placetype":"venue"
},
  "geometry": {"coordinates":[9.8443536758,46.5006065369],"type":"Point"}
}