{
  "type": "Feature",
  "properties": {
    "iso:country":"CH",
    "sg:address":"Eichenweg 31",
    "sg:city":"Embrach",
    "sg:orig_category":"Vereine Hundedressur",
    "sg:phone":"+41 18650281",
    "sg:postcode":"8424",
    "sg:province":"Z\u00fcrich",
    "wof:name":"Schweiz.rottweiler-hunde-club",
    "wof:placetype":"venue"
},
  "geometry": {"coordinates":[8.594417572,47.5095558167],"type":"Point"}
}