{
  "type": "Feature",
  "properties": {
    "iso:country":"CH",
    "sg:address":"Thalstrasse 11",
    "sg:city":"Kloten",
    "sg:orig_category":"RESTAURANTS: TEA-ROOMS",
    "sg:phone":"+41 18032203",
    "sg:postcode":"8302",
    "sg:province":"Z\u00fcrich",
    "wof:name":"Kunar Gastro Gmbh",
    "wof:placetype":"venue"
},
  "geometry": {"coordinates":[8.5823860168,47.4571762085],"type":"Point"}
}