{
  "type": "Feature",
  "properties": {
    "iso:country":"CH",
    "sg:address":"Baldismoosstrasse 39 6043 Adligenswil. Postfach 375",
    "sg:city":"Adligenswil",
    "sg:orig_category":"G\u00fcterbef\u00f6rderung im Strassenverkehr",
    "sg:phone":"+41 34 435 11 34",
    "sg:postcode":"6043",
    "sg:province":"Luzern",
    "wof:name":"Reinhard Otto Transporte",
    "wof:placetype":"venue"
},
  "geometry": {"coordinates":[7.7211608887,47.0666160583],"type":"Point"}
}