{
  "type": "Feature",
  "properties": {
    "iso:country":"CH",
    "sg:address":"Gradinata Forgh\u00e9e 2 6900 Massagno. Postfach",
    "sg:city":"Massagno",
    "sg:orig_category":"Dienstleistungen von Beteiligungsgesellschaften",
    "sg:postcode":"6900",
    "sg:province":"Ticino",
    "wof:name":"Infood Sa, Lussemburgo, Succursale Di Massagno",
    "wof:placetype":"venue"
},
  "geometry": {"coordinates":[8.9431638718,46.0128517151],"type":"Point"}
}