{
  "type": "Feature",
  "properties": {
    "iso:country":"CH",
    "sg:address":"Rue Des Cordiers 12",
    "sg:city":"Gen\u00e8ve",
    "sg:orig_category":"Grosshandel mit Werkzeugmaschinen Grosshandel mit chemischen Erzeugnissen",
    "sg:phone":"+41 22 736 94 42",
    "sg:postcode":"1207",
    "sg:province":"Gen\u00e8ve",
    "wof:name":"Totalwood Systems Inc.succle Colles Industr.& Mach.-outils",
    "wof:placetype":"venue"
},
  "geometry": {"coordinates":[6.1630439758,46.2029342651],"type":"Point"}
}