{
  "type": "Feature",
  "properties": {
    "iso:country":"CH",
    "sg:address":"8427",
    "sg:city":"Freienstein",
    "sg:orig_category":"Schulpflegen",
    "sg:phone":"+41 41 460 34 33",
    "sg:postcode":"8427",
    "sg:province":"Z\u00fcrich",
    "wof:name":"Schulpflegen Der Gemeinden Sempach Stadt & Station",
    "wof:placetype":"venue"
},
  "geometry": {"coordinates":[8.2235832214,47.131149292],"type":"Point"}
}