{
  "type": "Feature",
  "properties": {
    "iso:country":"CH",
    "sg:address":"Jurastrasse 19",
    "sg:city":"Alchenfl\u00fch",
    "sg:orig_category":"Landesverteidigung, Sozialversicherung \u00d6ffentliche Verwaltung",
    "sg:phone":"+41 34 445 43 45",
    "sg:postcode":"3422",
    "sg:province":"Bern",
    "wof:name":"Zivilschutzstelle R\u00fcdtligen-alchenfl\u00fch",
    "wof:placetype":"venue"
},
  "geometry": {"coordinates":[7.5773768425,47.0841598511],"type":"Point"}
}