{
  "type": "Feature",
  "properties": {
    "iso:country":"CH",
    "sg:address":"Route De Neuveville 40",
    "sg:city":"Pr\u00eales",
    "sg:orig_category":"Instandhaltung U Reparatur von Automobilen",
    "sg:phone":"+41 32 315 02 50",
    "sg:postcode":"2515",
    "sg:province":"Bern",
    "wof:name":"Garage Des 3 Sapins Sa",
    "wof:placetype":"venue"
},
  "geometry": {"coordinates":[7.1240148544,47.0899848938],"type":"Point"}
}