{
  "type": "Feature",
  "properties": {
    "iso:country":"CH",
    "sg:address":"3317",
    "sg:city":"Limpach",
    "sg:orig_category":"Herstellung von sonstigen landwirtschaftlichen Maschinen",
    "sg:phone":"+41 31 765 53 50",
    "sg:postcode":"3317",
    "sg:province":"Bern",
    "wof:name":"B\u00e4rtschi Andreas",
    "wof:placetype":"venue"
},
  "geometry": {"coordinates":[7.4944682121,47.108669281],"type":"Point"}
}