{
  "type": "Feature",
  "properties": {
    "iso:country":"CH",
    "sg:address":"Bachmattweg 8",
    "sg:city":"Oftringen",
    "sg:orig_category":"Grosshandel mit Eisenwaren sowie Installationsbedarf f\u00fcr Gas, Wasser U Heizung Grosshandel mit Masch",
    "sg:postcode":"4665",
    "sg:province":"Aargau",
    "wof:name":"Emb-pumpen Ag",
    "wof:placetype":"venue"
},
  "geometry": {"coordinates":[7.9248280525,47.3190231323],"type":"Point"}
}