{
  "type": "Feature",
  "properties": {
    "addr:full":"Dorfstrasse 73 Friltschen Thurgau 9504",
    "addr:housenumber":"73",
    "addr:postcode":"9504",
    "addr:street":"Dorfstrasse",
    "iso:country":"CH",
    "sg:address":"Dorfstrasse 73",
    "sg:city":"Friltschen",
    "sg:orig_category":"Bauschreinerei",
    "sg:phone":"+41 71 655 11 66",
    "sg:postcode":"9504",
    "sg:province":"Thurgau",
    "wof:name":"Peter B\u00f6tschi Schreinerei",
    "wof:placetype":"venue"
},
  "geometry": {"coordinates":[9.085578,47.537724],"type":"Point"}
}