{
  "type": "Feature",
  "properties": {
    "iso:country":"CH",
    "sg:address":"Via Cantonale",
    "sg:city":"Mezzovico",
    "sg:orig_category":"Grosshandel mit Parf\u00fcmerieartikeln U K\u00f6rperpflegemitteln Grosshandel mit pharmazeutischen Erzeugniss",
    "sg:phone":"+41 91 930 66 03",
    "sg:postcode":"6805",
    "sg:province":"Ticino",
    "wof:name":"Epikure Drug Delivery Systems Sa",
    "wof:placetype":"venue"
},
  "geometry": {"coordinates":[8.9198827744,46.0879859924],"type":"Point"}
}