{
  "type": "Feature",
  "properties": {
    "iso:country":"CH",
    "sg:address":"Chemin De La Fl\u00e9ch\u00e8re 15 1255 Veyrier. Postfach",
    "sg:city":"Veyrier",
    "sg:orig_category":"Softwareentwicklung U beratung",
    "sg:postcode":"1255",
    "sg:province":"Gen\u00e8ve",
    "wof:name":"Itc Services S\u00e0rl",
    "wof:placetype":"venue"
},
  "geometry": {"coordinates":[6.1862139702,46.1665229797],"type":"Point"}
}