{
  "type": "Feature",
  "properties": {
    "iso:country":"CH",
    "sg:address":"Allmend",
    "sg:city":"Merenschwand",
    "sg:orig_category":"Haltung von Schweinen",
    "sg:phone":"+41 56 664 10 63",
    "sg:postcode":"5634",
    "sg:province":"Aargau",
    "wof:name":"Othmar Koller Schweinezucht Eichhof",
    "wof:placetype":"venue"
},
  "geometry": {"coordinates":[8.3895454407,47.2615966797],"type":"Point"}
}