{
  "type": "Feature",
  "properties": {
    "iso:country":"CH",
    "sg:address":"Via Serafino Balestra 43a",
    "sg:city":"Locarno",
    "sg:orig_category":"Vereine Abstinenten",
    "sg:phone":"+41 91 751 75 82",
    "sg:postcode":"6600",
    "sg:province":"Ticino",
    "wof:name":"Societ\u00e0 Croce Blu",
    "wof:placetype":"venue"
},
  "geometry": {"coordinates":[8.7989406586,46.1607589722],"type":"Point"}
}