{
  "type": "Feature",
  "properties": {
    "iso:country":"CH",
    "sg:address":"Marktgasse 32",
    "sg:city":"Rheinfelden",
    "sg:orig_category":"Architekturb\u00fcros",
    "sg:phone":"+41 61 831 17 17",
    "sg:postcode":"4310",
    "sg:province":"Aargau",
    "wof:name":"Franz-josef Steiger Architekturb\u00fcro",
    "wof:placetype":"venue"
},
  "geometry": {"coordinates":[7.792524,47.555302],"type":"Point"}
}