{
  "type": "Feature",
  "properties": {
    "iso:country":"CH",
    "sg:address":"Fabrikstrasse 64 4133 Pratteln. Postfach 1843",
    "sg:city":"Pratteln",
    "sg:orig_category":"Herstellung von Anstrichmitteln, Druckfarben U Kitten Herstellung von sonstigen chemischen Erzeugnis",
    "sg:phone":"+41 61 821 50 55",
    "sg:postcode":"4133",
    "sg:province":"Basel-Landschaft",
    "wof:name":"Sun Chemical Ag",
    "wof:placetype":"venue"
},
  "geometry": {"coordinates":[7.6917848587,47.5205154419],"type":"Point"}
}