{
  "type": "Feature",
  "properties": {
    "iso:country":"CH",
    "sg:address":"La Mauguettaz",
    "sg:city":"Yvonand",
    "sg:orig_category":"Verarbeitung von Milch Verwertung von Milch",
    "sg:postcode":"1462",
    "sg:province":"Vaud",
    "wof:name":"Soci\u00e9t\u00e9 De Laiterie De La Sarraz",
    "wof:placetype":"venue"
},
  "geometry": {"coordinates":[6.5128378868,46.6583976746],"type":"Point"}
}