{
  "type": "Feature",
  "properties": {
    "addr:full":"Geerenstrasse 2a 8157 Dielsdorf. Postfach 213 Dielsdorf Z\u00fcrich 8157",
    "addr:housenumber":"2a;213",
    "addr:postcode":"8157 dielsdorf.;8157",
    "addr:street":"Geerenstrasse;Postfach",
    "iso:country":"CH",
    "sg:address":"Geerenstrasse 2a 8157 Dielsdorf. Postfach 213",
    "sg:city":"Dielsdorf",
    "sg:orig_category":"Detailhandel mit B\u00fcchern Detailhandel mit B\u00fcchern, Zeitungen, Schreib U Papeteriewaren",
    "sg:phone":"+41 18533282",
    "sg:postcode":"8157",
    "sg:province":"Z\u00fcrich",
    "wof:name":"Buchhandlung Zum Geeren Ag",
    "wof:placetype":"venue"
},
  "geometry": {"coordinates":[8.456193,47.481979],"type":"Point"}
}