{
  "type": "Feature",
  "properties": {
    "iso:country":"CH",
    "sg:address":"Mittliszelgstr. 5",
    "sg:city":"Romanshorn",
    "sg:classifiers":[
        {
            "category":"Manufacturing",
            "subcategory":"Metals",
            "type":"Manufacturing & Wholesale Goods"
        }
    ],
    "sg:phone":"+41 71 461 20 22",
    "sg:postcode":"8590",
    "sg:province":"Thurgau",
    "sg:tags":[
        "metallurgy",
        "steel",
        "metalworking"
    ],
    "wof:name":"R + M Herzog Ag",
    "wof:placetype":"venue"
},
  "geometry": {"coordinates":[9.3615703583,47.55809021],"type":"Point"}
}