{
  "type": "Feature",
  "properties": {
    "iso:country":"CH",
    "sg:address":"Rue Marterey 5 1005 Lausanne Case Postale 2813",
    "sg:city":"Lausanne",
    "sg:orig_category":"Wirtschaftspr\u00fcfung, Steuerberatung U Treuhand",
    "sg:phone":"+41 21 321 81 21",
    "sg:postcode":"1002",
    "sg:province":"Vaud",
    "wof:name":"Fibexa Sa Soci\u00e9t\u00e9 Fiduciaire",
    "wof:placetype":"venue"
},
  "geometry": {"coordinates":[6.6379141808,46.5203781128],"type":"Point"}
}