{
  "type": "Feature",
  "properties": {
    "iso:country":"CH",
    "sg:address":"Florimont Chemin De 22 1400 Yverdon-les-bains. Postfach",
    "sg:city":"Cheseaux-nor\u00e9az",
    "sg:orig_category":"Interessenvertretungen",
    "sg:postcode":"1400",
    "sg:province":"Vaud",
    "wof:name":"Fondation Vaudoise Du Patrimoine Scolaire",
    "wof:placetype":"venue"
},
  "geometry": {"coordinates":[6.6591482162,46.7720756531],"type":"Point"}
}