{
  "type": "Feature",
  "properties": {
    "iso:country":"CH",
    "sg:address":"5627",
    "sg:city":"Besenb\u00fcren",
    "sg:orig_category":"Vereine Frauen",
    "sg:postcode":"5627",
    "sg:province":"Aargau",
    "wof:name":"Frauen-& T\u00f6chterverein",
    "wof:placetype":"venue"
},
  "geometry": {"coordinates":[8.344420433,47.3123092651],"type":"Point"}
}