{
  "type": "Feature",
  "properties": {
    "iso:country":"CH",
    "sg:address":"Avenue De Senarclens 5",
    "sg:city":"Bellevue",
    "sg:orig_category":"Vereine Hundedressur",
    "sg:phone":"+41 22 774 45 64",
    "sg:postcode":"1293",
    "sg:province":"Gen\u00e8ve",
    "wof:name":"Grup.dressage De La St\u00e9 Canine",
    "wof:placetype":"venue"
},
  "geometry": {"coordinates":[6.1472949982,46.2528648376],"type":"Point"}
}