{
  "type": "Feature",
  "properties": {
    "iso:country":"CH",
    "sg:address":"Muntegn 66",
    "sg:city":"Vicosoprano",
    "sg:orig_category":"Herstellung von Mess U Kontrollinstrumenten U vorrichtungen",
    "sg:postcode":"7603",
    "sg:province":"Graubunden",
    "wof:name":"Keller Werner Glocken - L\u00e4utmaschinen - Turmuhren, Vormals Glockenl\u00e4utanlagen Wymann Alois",
    "wof:placetype":"venue"
},
  "geometry": {"coordinates":[8.0744695663,47.1829185486],"type":"Point"}
}