{
  "type": "Feature",
  "properties": {
    "iso:country":"CH",
    "sg:address":"Fischerweg 6",
    "sg:city":"Zwingen",
    "sg:orig_category":"Fachdetailhandel in Verkaufsr\u00e4umen",
    "sg:postcode":"4222",
    "sg:province":"Basel-Landschaft",
    "wof:name":"Fellmann Emilio",
    "wof:placetype":"venue"
},
  "geometry": {"coordinates":[8.3200368881,47.13256073],"type":"Point"}
}