{
  "type": "Feature",
  "properties": {
    "iso:country":"CH",
    "sg:address":"Untere Breite 148",
    "sg:city":"Mettau",
    "sg:orig_category":"Wirtschaftspr\u00fcfung, Steuerberatung U Treuhand",
    "sg:phone":"+41 62 875 00 77",
    "sg:postcode":"5274",
    "sg:province":"Aargau",
    "wof:name":"Weber B\u00fcroservice Gmbh",
    "wof:placetype":"venue"
},
  "geometry": {"coordinates":[8.1259098053,47.5650672913],"type":"Point"}
}