{
  "type": "Feature",
  "properties": {
    "iso:country":"CH",
    "sg:address":"Rankackerweg 26",
    "sg:city":"Pratteln",
    "sg:orig_category":"Interessenvertretungen",
    "sg:phone":"+41 61 821 03 70",
    "sg:postcode":"4133",
    "sg:province":"Basel-Landschaft",
    "wof:name":"Stiftung F\u00fcr Orts Und Flurnamen-forschung Baselland",
    "wof:placetype":"venue"
},
  "geometry": {"coordinates":[7.7105178833,47.5220527649],"type":"Point"}
}