{
  "type": "Feature",
  "properties": {
    "iso:country":"CH",
    "sg:address":"De Castellaplatz 19 3280 Greng. Postfach 179",
    "sg:city":"Greng",
    "sg:orig_category":"Gemeindeverwaltungen",
    "sg:phone":"+41 26 672 18 82",
    "sg:postcode":"3280",
    "sg:province":"Fribourg",
    "wof:name":"Gemeindeverwaltung Greng",
    "wof:placetype":"venue"
},
  "geometry": {"coordinates":[7.0906448364,46.9137535095],"type":"Point"}
}