{
  "type": "Feature",
  "properties": {
    "iso:country":"CH",
    "sg:address":"Beckenriederstrasse",
    "sg:city":"Buochs",
    "sg:orig_category":"Unternehmensberatung",
    "sg:postcode":"6374",
    "sg:province":"Nidwalden",
    "wof:name":"Agro-treuhand Gmbh Uri, Nid Und Obwalden",
    "wof:placetype":"venue"
},
  "geometry": {"coordinates":[8.4294652939,46.9743156433],"type":"Point"}
}