{
  "type": "Feature",
  "properties": {
    "iso:country":"CH",
    "sg:address":"Rue De La Corraterie 9",
    "sg:city":"Gen\u00e8ve",
    "sg:orig_category":"Detailhandel mit Textilien Grosshandel mit Textilien",
    "sg:phone":"+41 22 810 02 25",
    "sg:postcode":"1204",
    "sg:province":"Gen\u00e8ve",
    "wof:name":"Autentica, Heinzelmann Susanna",
    "wof:placetype":"venue"
},
  "geometry": {"coordinates":[6.1434979439,46.2028160095],"type":"Point"}
}