{
  "type": "Feature",
  "properties": {
    "iso:country":"CH",
    "sg:address":"Carouge Rue De 13 1205 Gen\u00e8ve. Postfach",
    "sg:city":"Gen\u00e8ve",
    "sg:orig_category":"Herstellung von W\u00e4sche",
    "sg:phone":"+41 22 731 51 64",
    "sg:postcode":"1205",
    "sg:province":"Gen\u00e8ve",
    "wof:name":"Micheline Lagarde",
    "wof:placetype":"venue"
},
  "geometry": {"coordinates":[6.1433200836,46.1966972351],"type":"Point"}
}