{
  "type": "Feature",
  "properties": {
    "iso:country":"CH",
    "sg:address":"Chemin Des Pontets 4",
    "sg:city":"Grand-lancy",
    "sg:orig_category":"G\u00fcterbef\u00f6rderung im Strassenverkehr",
    "sg:phone":"+41 22 794 58 11",
    "sg:postcode":"1212",
    "sg:province":"Gen\u00e8ve",
    "wof:name":"Fernand Rochat Transports & D\u00e9m\u00e9nagements",
    "wof:placetype":"venue"
},
  "geometry": {"coordinates":[6.1237668991,46.1746482849],"type":"Point"}
}