{
  "type": "Feature",
  "properties": {
    "iso:country":"CH",
    "sg:address":"Burgweg 4 8162 Steinmaur. Postfach",
    "sg:city":"Steinmaur",
    "sg:orig_category":"Kauf U Verkauf von Immobilien auf eigene Rechnung",
    "sg:postcode":"8162",
    "sg:province":"Z\u00fcrich",
    "wof:name":"Burgstein Ag Liegenschaften Usw",
    "wof:placetype":"venue"
},
  "geometry": {"coordinates":[8.4466867447,47.4914321899],"type":"Point"}
}