{
  "type": "Feature",
  "properties": {
    "iso:country":"CH",
    "sg:address":"Brauerstrasse 110",
    "sg:city":"Z\u00fcrich",
    "sg:orig_category":"G\u00fcterbef\u00f6rderung im Strassenverkehr",
    "sg:phone":"+41 848 555 555",
    "sg:postcode":"8004",
    "sg:province":"Z\u00fcrich",
    "wof:name":"Carigiet Ag",
    "wof:placetype":"venue"
},
  "geometry": {"coordinates":[8.4348077774,47.4201469421],"type":"Point"}
}