{
  "type": "Feature",
  "properties": {
    "iso:country":"CH",
    "sg:address":"Riehenstrasse 163",
    "sg:city":"Basel",
    "sg:orig_category":"Fussreflexzonenmassage",
    "sg:phone":"+41 19326333",
    "sg:postcode":"4058",
    "sg:province":"Basel-Stadt",
    "wof:name":"Andreas Gut Fussreflexzonenmassage",
    "wof:placetype":"venue"
},
  "geometry": {"coordinates":[8.7941865921,47.3205528259],"type":"Point"}
}