{
  "type": "Feature",
  "properties": {
    "iso:country":"CH",
    "sg:address":"Avenue De Chanel 12",
    "sg:city":"Morges",
    "sg:orig_category":"Fahrschulen, Flugschulen",
    "sg:phone":"+41 79 449 11 66",
    "sg:postcode":"1110",
    "sg:province":"Vaud",
    "wof:name":"Christophe Demont Auto-\u00e9cole",
    "wof:placetype":"venue"
},
  "geometry": {"coordinates":[6.4946508408,46.5152854919],"type":"Point"}
}