{
  "type": "Feature",
  "properties": {
    "iso:country":"CH",
    "sg:address":"L\u00f6bernstrasse 10",
    "sg:city":"Cham",
    "sg:orig_category":"Grosshandel mit keramischen Erzeugnissen,Glaswaren U Tapeten K\u00fcnstlerische U schriftstellerische T\u00e4t",
    "sg:phone":"+41 41 780 63 77",
    "sg:postcode":"6330",
    "sg:province":"Zug",
    "wof:name":"Glasdecor Straub",
    "wof:placetype":"venue"
},
  "geometry": {"coordinates":[8.4617643356,47.1852340698],"type":"Point"}
}