{
  "type": "Feature",
  "properties": {
    "iso:country":"CH",
    "sg:address":"Findeln",
    "sg:city":"Zermatt",
    "sg:orig_category":"RESTAURANTS: TEA-ROOMS",
    "sg:phone":"+41 27 967 25 52",
    "sg:postcode":"3920",
    "sg:province":"Valais",
    "wof:name":"Restaurant Chez Vrony",
    "wof:placetype":"venue"
},
  "geometry": {"coordinates":[7.7646398544,46.010848999],"type":"Point"}
}