{
  "type": "Feature",
  "properties": {
    "iso:country":"CH",
    "sg:address":"Peter Merian-strasse 58 4052 Basel. Postfach",
    "sg:city":"Basel",
    "sg:orig_category":"Vermietung U Verpachtung von eigenen Immobilien",
    "sg:postcode":"4052",
    "sg:province":"Basel-Stadt",
    "wof:name":"Horselection Ag",
    "wof:placetype":"venue"
},
  "geometry": {"coordinates":[9.1283597946,46.2375984192],"type":"Point"}
}