{
  "type": "Feature",
  "properties": {
    "iso:country":"CH",
    "sg:address":"Mutschellenstrasse 22",
    "sg:city":"Bellikon",
    "sg:orig_category":"Herstellung von \u00d6fen U Brennern Verlegen von Fliesen U Platten",
    "sg:phone":"+41 71 944 14 56",
    "sg:postcode":"5454",
    "sg:province":"Aargau",
    "wof:name":"Eggenberger Mathias",
    "wof:placetype":"venue"
},
  "geometry": {"coordinates":[9.1234006882,47.4656410217],"type":"Point"}
}