{
  "type": "Feature",
  "properties": {
    "iso:country":"CH",
    "sg:address":"Route De Courtemblin 2 2950 Courgenay. Postfach",
    "sg:city":"Courgenay",
    "sg:orig_category":"RESTAURANTS: TEA-ROOMS",
    "sg:postcode":"2950",
    "sg:province":"Jura",
    "wof:name":"Zurbach Julien",
    "wof:placetype":"venue"
},
  "geometry": {"coordinates":[7.1272001266,47.4029884338],"type":"Point"}
}