{
  "type": "Feature",
  "properties": {
    "iso:country":"CH",
    "sg:address":"Habsburgerstrasse 26",
    "sg:city":"Luzern",
    "sg:orig_category":"Detailhandel mit medizinischen U orthop\u00e4dischen Artikeln Sonstige Aktivit\u00e4ten der nicht-\u00e4rztlichen M",
    "sg:phone":"+41 41 210 86 83",
    "sg:postcode":"6003",
    "sg:province":"Luzern",
    "wof:name":"Gelbart Ag Orthop\u00e4die-& Rehabilitationstechnik",
    "wof:placetype":"venue"
},
  "geometry": {"coordinates":[8.3066358566,47.0467910767],"type":"Point"}
}