{
  "type": "Feature",
  "properties": {
    "iso:country":"CH",
    "sg:address":"Grand-rue",
    "sg:city":"Ch\u00e2teau-d'oex",
    "sg:orig_category":"Elektroinstallation",
    "sg:phone":"+41 26 924 68 25",
    "sg:postcode":"1837",
    "wof:name":"Henchoz Louis-fernand",
    "wof:placetype":"venue"
},
  "geometry": {"coordinates":[0.9477999806,45.3775024414],"type":"Point"}
}