{
  "type": "Feature",
  "properties": {
    "iso:country":"CH",
    "sg:address":"Route De Divonne 44",
    "sg:city":"Nyon",
    "sg:orig_category":"Erbringung von Dienstleistungen f\u00fcr Unternehmen Verlagsgewerbe",
    "sg:phone":"+41 22 361 90 25",
    "sg:postcode":"1260",
    "sg:province":"Vaud",
    "wof:name":"Adi-presse F. D\u00e9ruaz Badel Edition",
    "wof:placetype":"venue"
},
  "geometry": {"coordinates":[6.2230110168,46.3833999634],"type":"Point"}
}