{
  "type": "Feature",
  "properties": {
    "iso:country":"CH",
    "sg:address":"Rue De L'avenir 3",
    "sg:city":"Morges",
    "sg:orig_category":"Arztpraxen",
    "sg:phone":"+41 21 802 29 93",
    "sg:postcode":"1110",
    "sg:province":"Vaud",
    "wof:name":"Dr M\u00e9d. Dominique Morzier M\u00e9decin Sp\u00e9cialiste Fmh",
    "wof:placetype":"venue"
},
  "geometry": {"coordinates":[6.495444,46.50956],"type":"Point"}
}