{
  "type": "Feature",
  "properties": {
    "iso:country":"CH",
    "sg:address":"Funkwiesenstrasse 22 8050 Z\u00fcrich",
    "sg:city":"Zust",
    "sg:orig_category":"Sonstiger Grosshandel",
    "sg:phone":"+41 21 634 89 28",
    "sg:postcode":"50",
    "wof:name":"Barbezat Christian",
    "wof:placetype":"venue"
},
  "geometry": {"coordinates":[6.5848379135,46.5311813354],"type":"Point"}
}