{
  "type": "Feature",
  "properties": {
    "iso:country":"CH",
    "sg:address":"Avenue Marc-peter 10a",
    "sg:city":"Versoix",
    "sg:orig_category":"Finanzierungsinstitutionen",
    "sg:phone":"+41 22 810 14 13",
    "sg:postcode":"1290",
    "sg:province":"Gen\u00e8ve",
    "wof:name":"Financial And Consulting Trust Fact Sa",
    "wof:placetype":"venue"
},
  "geometry": {"coordinates":[6.1623001099,46.2838592529],"type":"Point"}
}