{
  "type": "Feature",
  "properties": {
    "iso:country":"CH",
    "sg:address":"Poststrasse 12",
    "sg:city":"Ernetschwil",
    "sg:orig_category":"Bauingenieurb\u00fcros Hochbau Bauingenieurb\u00fcros allgemein",
    "sg:phone":"+41 55 280 23 08",
    "sg:postcode":"8725",
    "sg:province":"St. Gallen",
    "wof:name":"Felix Th\u00fcrlemann Ingenieurb\u00fcro",
    "wof:placetype":"venue"
},
  "geometry": {"coordinates":[8.99893,47.238564],"type":"Point"}
}