{
  "type": "Feature",
  "properties": {
    "iso:country":"CH",
    "sg:address":"Industriestrasse 31 6300 Zug. Postfach 2003",
    "sg:city":"Zug",
    "sg:orig_category":"Handelsvermittlung U Grosshandel Handelsvermittlung von Brennstoffen, Erzen, Metallen U Chemikalien",
    "sg:phone":"+41 41 712 07 77",
    "sg:postcode":"6302",
    "sg:province":"Zug",
    "wof:name":"Heinzel Wilfried Ag",
    "wof:placetype":"venue"
},
  "geometry": {"coordinates":[8.5194377899,47.1763191223],"type":"Point"}
}