{
  "type": "Feature",
  "properties": {
    "iso:country":"CH",
    "sg:address":"3755 Horboden. Postfach",
    "sg:city":"Horboden",
    "sg:orig_category":"RESTAURANTS: TEA-ROOMS",
    "sg:postcode":"3755",
    "sg:province":"Bern",
    "wof:name":"Restaurant Horboden, Neukomm",
    "wof:placetype":"venue"
},
  "geometry": {"coordinates":[7.5608119965,46.6320457458],"type":"Point"}
}