{
  "type": "Feature",
  "properties": {
    "iso:country":"CH",
    "sg:address":"Bleichestrasse 37 8400 Winterthur. Postfach 1121",
    "sg:city":"Winterthur",
    "sg:orig_category":"Softwareentwicklung U beratung Sonstige mit der Informatik verbundene T\u00e4tigkeiten",
    "sg:phone":"+41 52 222 60 66",
    "sg:postcode":"8401",
    "sg:province":"Z\u00fcrich",
    "wof:name":"Cosobe Computer Software Beratung Ag",
    "wof:placetype":"venue"
},
  "geometry": {"coordinates":[8.7193307877,47.5064430237],"type":"Point"}
}