{
  "type": "Feature",
  "properties": {
    "iso:country":"CH",
    "sg:address":"Murg\u00e8res Chemin Des",
    "sg:city":"St-maurice",
    "sg:orig_category":"Handel mit Automobilteilen U Zubeh\u00f6r",
    "sg:phone":"+41 79 233 65 38",
    "sg:postcode":"1890",
    "sg:province":"Valais",
    "wof:name":"Melbo S\u00e0rl",
    "wof:placetype":"venue"
},
  "geometry": {"coordinates":[7.0044598579,46.2167739868],"type":"Point"}
}