{
  "type": "Feature",
  "properties": {
    "iso:country":"CH",
    "sg:address":"Orm\u00f4ne",
    "sg:city":"Savi\u00e8se",
    "sg:orig_category":"Interessenvertretungen U sonstige Vereinigungen",
    "sg:postcode":"1965",
    "sg:province":"Valais",
    "wof:name":"Assoc.suisse De Bowling",
    "wof:placetype":"venue"
},
  "geometry": {"coordinates":[6.5818109512,46.5322151184],"type":"Point"}
}