{
  "type": "Feature",
  "properties": {
    "iso:country":"CH",
    "sg:address":"Risi",
    "sg:city":"M\u00fchlehorn",
    "sg:orig_category":"Unclassifiable Establishments",
    "sg:phone":"+41 55 614 11 20",
    "sg:postcode":"8874",
    "sg:province":"Glarus",
    "wof:name":"Riko Dogs Gmbh",
    "wof:placetype":"venue"
},
  "geometry": {"coordinates":[9.1724395752,47.1164665222],"type":"Point"}
}