{
  "type": "Feature",
  "properties": {
    "iso:country":"CH",
    "sg:address":"Hostetstrasse 1",
    "sg:city":"Berneck",
    "sg:orig_category":"Markt U Meinungsforschung Unternehmensberatung",
    "sg:phone":"+41 21 633 14 50",
    "sg:postcode":"9442",
    "sg:province":"St. Gallen",
    "wof:name":"Mcc Marti Fran\u00e7ois",
    "wof:placetype":"venue"
},
  "geometry": {"coordinates":[6.5812921524,46.5375938416],"type":"Point"}
}