{
  "type": "Feature",
  "properties": {
    "iso:country":"CH",
    "sg:address":"Klosterplatz",
    "sg:city":"Solothurn",
    "sg:orig_category":"Saunas, Solarien, Fitnesszentren U \u00e4hnliches",
    "sg:postcode":"4500",
    "sg:province":"Solothurn",
    "wof:name":"Sun Beach Solarium Von Siebenthal",
    "wof:placetype":"venue"
},
  "geometry": {"coordinates":[7.5392651558,47.2072982788],"type":"Point"}
}