{
  "type": "Feature",
  "properties": {
    "iso:country":"CH",
    "sg:address":"Untere Bahnhofstrasse 9a",
    "sg:city":"Amriswil",
    "sg:orig_category":"D\u00e4mmung gegen K\u00e4lte, W\u00e4rme, Schall U Ersch\u00fctterung",
    "sg:phone":"+41 56 621 21 43",
    "sg:postcode":"8580",
    "sg:province":"Thurgau",
    "wof:name":"Saranovic Zoki",
    "wof:placetype":"venue"
},
  "geometry": {"coordinates":[8.2688484192,47.3510437012],"type":"Point"}
}