{
  "type": "Feature",
  "properties": {
    "iso:country":"CH",
    "sg:address":"Gotthardstrasse 9 6438 Ibach. Postfach",
    "sg:city":"Ibach",
    "sg:orig_category":"Non-Classified Establishments",
    "sg:postcode":"6438",
    "sg:province":"Schwyz",
    "wof:name":"Paag Beteiligungen Ag",
    "wof:placetype":"venue"
},
  "geometry": {"coordinates":[8.6361808777,47.0102043152],"type":"Point"}
}