{
  "type": "Feature",
  "properties": {
    "addr:full":"Rue De L'envers 2 Tavannes Bern 2710",
    "addr:housenumber":"2",
    "addr:postcode":"2710",
    "addr:street":"Rue De L'Envers",
    "iso:country":"CH",
    "sg:address":"Rue De L'envers 2",
    "sg:city":"Tavannes",
    "sg:orig_category":"Architekturb\u00fcros",
    "sg:phone":"+41 32 481 13 55",
    "sg:postcode":"2710",
    "sg:province":"Bern",
    "wof:name":"J.-c. Pr\u00eatre & G.-j. Haefeli Archiplan At.d'architecture",
    "wof:placetype":"venue"
},
  "geometry": {"coordinates":[7.19965,47.220039],"type":"Point"}
}