{
  "type": "Feature",
  "properties": {
    "iso:country":"CH",
    "sg:address":"Lyon-strasse 14",
    "sg:city":"Basel",
    "sg:classifiers":[
        {
            "category":"Manufacturing",
            "subcategory":"Tools & Machinery",
            "type":"Manufacturing & Wholesale Goods"
        }
    ],
    "sg:phone":"+41 61 331 10 25",
    "sg:postcode":"4053",
    "sg:province":"Basel-Stadt",
    "sg:tags":[
        "construction",
        "container",
        "apparatus"
    ],
    "wof:name":"Kurt Jost Ag",
    "wof:placetype":"venue"
},
  "geometry": {"coordinates":[7.607596,47.53569],"type":"Point"}
}