{
  "type": "Feature",
  "properties": {
    "iso:country":"CH",
    "sg:address":"Rue De L'arquebuse 12 1204 Gen\u00e8ve Case Postale 71",
    "sg:city":"Gen\u00e8ve",
    "sg:orig_category":"Wirtschaftspr\u00fcfung, Steuerberatung U Treuhand",
    "sg:phone":"+41 22 807 20 00",
    "sg:postcode":"1204",
    "sg:province":"Gen\u00e8ve",
    "wof:name":"Radcliffes Trustee Company Sa",
    "wof:placetype":"venue"
},
  "geometry": {"coordinates":[6.1391868591,46.2025146484],"type":"Point"}
}