{
  "type": "Feature",
  "properties": {
    "iso:country":"CH",
    "sg:address":"Bahnhofstrasse 11",
    "sg:city":"Sachseln",
    "sg:orig_category":"Interessenvertretungen",
    "sg:phone":"+41 31 359 12 10",
    "sg:postcode":"6072",
    "sg:province":"Obwalden",
    "wof:name":"Fmh Services",
    "wof:placetype":"venue"
},
  "geometry": {"coordinates":[7.4869909286,46.9317207336],"type":"Point"}
}