{
  "type": "Feature",
  "properties": {
    "iso:country":"CH",
    "sg:address":"Multergasse 2",
    "sg:city":"St.gallen",
    "sg:orig_category":"Vermietung U Verpachtung von eigenen Immobilien",
    "sg:postcode":"9000",
    "sg:province":"St. Gallen",
    "wof:name":"Baettig Ag",
    "wof:placetype":"venue"
},
  "geometry": {"coordinates":[9.376162529,47.4247741699],"type":"Point"}
}