{
  "type": "Feature",
  "properties": {
    "iso:country":"CH",
    "sg:address":"Teufener Strasse 36",
    "sg:city":"St.gallen",
    "sg:orig_category":"Pensionskassen",
    "sg:postcode":"9000",
    "sg:province":"St. Gallen",
    "wof:name":"Personalf\u00fcrsorgestiftung Der Ehb Aktiengesellschaft",
    "wof:placetype":"venue"
},
  "geometry": {"coordinates":[7.5961918831,47.4960289001],"type":"Point"}
}