{
  "type": "Feature",
  "properties": {
    "iso:country":"CH",
    "sg:address":"Rickenstrasse 5 8050 Z\u00fcrich. Postfach",
    "sg:city":"Z\u00fcrich",
    "sg:orig_category":"Detailhandel mit Brennstoffen U Heizmaterial Grosshandel mit festen Brennstoffen U Mineral\u00f6lerzeugni",
    "sg:phone":"+41 13021919",
    "sg:postcode":"8052",
    "sg:province":"Z\u00fcrich",
    "wof:name":"Steinmann Eugen Z\u00fcrich Ag",
    "wof:placetype":"venue"
},
  "geometry": {"coordinates":[8.5415,47.4179],"type":"Point"}
}