{
  "type": "Feature",
  "properties": {
    "iso:country":"CH",
    "sg:address":"Hauptstrasse 31 4447 K\u00e4nerkinden. Postfach",
    "sg:city":"K\u00e4nerkinden",
    "sg:orig_category":"Unclassifiable Establishments",
    "sg:phone":"+41 62 299 24 78",
    "sg:postcode":"4447",
    "sg:province":"Basel-Landschaft",
    "wof:name":"Alija Sulejman Transporte",
    "wof:placetype":"venue"
},
  "geometry": {"coordinates":[7.8358998299,47.4115371704],"type":"Point"}
}