{
  "type": "Feature",
  "properties": {
    "addr:full":"Konstanzerstrasse 9 Rossr\u00fcti St. Gallen 9512",
    "addr:housenumber":"9;st.",
    "addr:postcode":"9512",
    "addr:street":"Konstanzerstrasse",
    "iso:country":"CH",
    "sg:address":"Konstanzerstrasse 9",
    "sg:city":"Rossr\u00fcti",
    "sg:orig_category":"Dauerkulturbau Detailhandel mit Getr\u00e4nken",
    "sg:phone":"+41 71 911 10 11",
    "sg:postcode":"9512",
    "sg:province":"St. Gallen",
    "wof:name":"Ehrat-weine Ag Wil",
    "wof:placetype":"venue"
},
  "geometry": {"coordinates":[9.059551,47.472462],"type":"Point"}
}