{
  "type": "Feature",
  "properties": {
    "iso:country":"CH",
    "sg:address":"Einschlagweg 37 3400 Burgdorf. Postfach 525",
    "sg:city":"Burgdorf",
    "sg:orig_category":"Fachdetailhandel in Verkaufsr\u00e4umen Sonstiger Fachdetailhandel in Verkaufsr\u00e4umen",
    "sg:phone":"+41 79 407 78 54",
    "sg:postcode":"3401",
    "sg:province":"Bern",
    "wof:name":"Forstreuter Ag",
    "wof:placetype":"venue"
},
  "geometry": {"coordinates":[7.6288561821,47.0488815308],"type":"Point"}
}