{
  "type": "Feature",
  "properties": {
    "iso:country":"CH",
    "sg:address":"Weststrasse 1",
    "sg:city":"M\u00e4genwil",
    "sg:orig_category":"Grosshandel mit Eisenwaren sowie Installationsbedarf f\u00fcr Gas, Wasser U Heizung Grosshandel mit Holz ",
    "sg:phone":"+41 19314412",
    "sg:postcode":"5506",
    "sg:province":"Aargau",
    "wof:name":"Syntha Ag",
    "wof:placetype":"venue"
},
  "geometry": {"coordinates":[8.8061571121,47.3328895569],"type":"Point"}
}