{
  "type": "Feature",
  "properties": {
    "iso:country":"CH",
    "sg:address":"Ernst Z\u00f6beli-strasse 10",
    "sg:city":"Z\u00fcrich",
    "sg:orig_category":"Herstellung von Mess U Kontrollinstrumenten U vorrichtungen",
    "sg:postcode":"8048",
    "sg:province":"Z\u00fcrich",
    "wof:name":"Calisto Attilio Pr\u00e4zisionsschaberei, Maschinenrevisionen",
    "wof:placetype":"venue"
},
  "geometry": {"coordinates":[8.4741649628,47.3920822144],"type":"Point"}
}