{
  "type": "Feature",
  "properties": {
    "iso:country":"CH",
    "sg:address":"Oberdorf 25",
    "sg:city":"N\u00e4fels",
    "sg:orig_category":"Detailhandel mit S\u00e4uglings U Kinderbekleidung Grosshandel mit elektrischen Haushaltsger\u00e4ten",
    "sg:phone":"+41 55 622 32 30",
    "sg:postcode":"8752",
    "sg:province":"Glarus",
    "wof:name":"Felber Babyshop N\u00e4hcenter",
    "wof:placetype":"venue"
},
  "geometry": {"coordinates":[9.062707901,47.0964126587],"type":"Point"}
}