{
  "type": "Feature",
  "properties": {
    "iso:country":"CH",
    "sg:address":"6900 Lugano. Postfach Caselle Postale 3235",
    "sg:city":"Lugano",
    "sg:orig_category":"Politische Vereinigungen",
    "sg:phone":"+41 91 646 93 22",
    "sg:postcode":"6901",
    "sg:province":"Ticino",
    "wof:name":"Partito Ticinese Del Lavoro",
    "wof:placetype":"venue"
},
  "geometry": {"coordinates":[8.9535598755,46.0047798157],"type":"Point"}
}