{
  "type": "Feature",
  "properties": {
    "iso:country":"CH",
    "sg:city":"Unterterzen",
    "sg:classifiers":[
        {
            "category":"Banks & Credit Unions",
            "subcategory":"Bank",
            "type":"Services"
        }
    ],
    "sg:phone":"+41 41 854 17 63",
    "sg:postcode":"8882",
    "sg:province":"St. Gallen",
    "wof:name":"Raiffeisenbank Quarten",
    "wof:placetype":"venue"
},
  "geometry": {"coordinates":[9.25304,47.113514],"type":"Point"}
}