{
  "type": "Feature",
  "properties": {
    "iso:country":"CH",
    "sg:address":"Eichenweg 80. 8400 Winterthur. Postfach",
    "sg:city":"Winterthur",
    "sg:orig_category":"Grosshandel mit Getr\u00e4nken",
    "sg:postcode":"8400",
    "sg:province":"Z\u00fcrich",
    "wof:name":"Wegenstein Wine Cellar",
    "wof:placetype":"venue"
},
  "geometry": {"coordinates":[8.5873479843,47.3219871521],"type":"Point"}
}