{
  "type": "Feature",
  "properties": {
    "iso:country":"CH",
    "sg:address":"Rue De Langallerie 4",
    "sg:city":"Lausanne",
    "sg:orig_category":"Grosshandel mit Textilien Handelsvermittlung von Waren ohne ausgepr\u00e4gten Schwerpunkt",
    "sg:postcode":"1003",
    "sg:province":"Vaud",
    "wof:name":"Gpc G\u00e9pard Pacific Finance Sa",
    "wof:placetype":"venue"
},
  "geometry": {"coordinates":[6.6380472183,46.5199203491],"type":"Point"}
}