{
  "type": "Feature",
  "properties": {
    "iso:country":"CH",
    "sg:address":"Hauptstrasse 57",
    "sg:city":"L\u00fcterswil",
    "sg:orig_category":"Detailhandel mit Getr\u00e4nken",
    "sg:phone":"+41 32 351 29 55",
    "sg:postcode":"4584",
    "sg:province":"Solothurn",
    "wof:name":"Gl\u00e4ser & Schmitt Mettkellerei",
    "wof:placetype":"venue"
},
  "geometry": {"coordinates":[7.435087204,47.1210098267],"type":"Point"}
}