{
  "type": "Feature",
  "properties": {
    "iso:country":"CH",
    "sg:address":"Im Sch\u00f6rli 3",
    "sg:city":"D\u00fcbendorf",
    "sg:orig_category":"Unclassifiable Establishments",
    "sg:phone":"+41 18243070",
    "sg:postcode":"8600",
    "sg:province":"Z\u00fcrich",
    "wof:name":"Bideco Holding Ag",
    "wof:placetype":"venue"
},
  "geometry": {"coordinates":[8.6395969391,47.3946342468],"type":"Point"}
}