{
  "type": "Feature",
  "properties": {
    "iso:country":"CH",
    "sg:address":"Ortschwabenstrasse 3",
    "sg:city":"Uettligen",
    "sg:orig_category":"Ingenieurb\u00fcros Geologie",
    "sg:phone":"+41 12721455",
    "sg:postcode":"3043",
    "sg:province":"Bern",
    "wof:name":"Gysi Leoni Mader Ag Ingenieurb\u00fcro",
    "wof:placetype":"venue"
},
  "geometry": {"coordinates":[8.0736656189,47.386806488],"type":"Point"}
}