{
  "type": "Feature",
  "properties": {
    "iso:country":"CH",
    "sg:address":"Via Locarno 10",
    "sg:city":"Sementina",
    "sg:classifiers":[
        {
            "category":"Travel",
            "subcategory":"Hotels & Motels",
            "type":"Entertainment"
        }
    ],
    "sg:phone":"+41 91 857 24 31",
    "sg:postcode":"6514",
    "sg:province":"Ticino",
    "sg:tags":[
        "hotels",
        "mit",
        "restaurant"
    ],
    "wof:name":"Albergo Cereda Di Galli Vittorio E Cristina",
    "wof:placetype":"venue"
},
  "geometry": {"coordinates":[8.9911489487,46.1857948303],"type":"Point"}
}