{
  "type": "Feature",
  "properties": {
    "iso:country":"CH",
    "sg:address":"Am Steinlibach 8",
    "sg:city":"Thal",
    "sg:orig_category":"Organisationen der Wohlfahrtspflege",
    "sg:phone":"+41 71 888 20 85",
    "sg:postcode":"9425",
    "sg:province":"St. Gallen",
    "wof:name":"Pro Juventute Bezirkssekretariat",
    "wof:placetype":"venue"
},
  "geometry": {"coordinates":[9.5609922409,47.4701843262],"type":"Point"}
}