{
  "type": "Feature",
  "properties": {
    "iso:country":"CH",
    "sg:address":"Sprenggi 1",
    "sg:city":"M\u00fchlethurnen",
    "sg:orig_category":"Non-Classified Establishments",
    "sg:phone":"+41 32 485 70 67",
    "sg:postcode":"3127",
    "sg:province":"Bern",
    "wof:name":"Balmer Invest",
    "wof:placetype":"venue"
},
  "geometry": {"coordinates":[7.2235150337,47.191608429],"type":"Point"}
}