{
  "type": "Feature",
  "properties": {
    "iso:country":"CH",
    "sg:address":"M\u00fchle",
    "sg:city":"Neudorf",
    "sg:orig_category":"Mahl U Sch\u00e4lm\u00fchlen",
    "sg:postcode":"6025",
    "sg:province":"Luzern",
    "wof:name":"Winiger Viktor",
    "wof:placetype":"venue"
},
  "geometry": {"coordinates":[8.2094106674,47.1761894226],"type":"Point"}
}