{
  "type": "Feature",
  "properties": {
    "iso:country":"CH",
    "sg:address":"Bahnhofstrasse 15",
    "sg:city":"Sursee",
    "sg:orig_category":"Pensionskassen",
    "sg:postcode":"6210",
    "sg:province":"Luzern",
    "wof:name":"Personalvorsorgestiftung Der Firma Belimo Automation",
    "wof:placetype":"venue"
},
  "geometry": {"coordinates":[8.793598175,47.3154792786],"type":"Point"}
}