{
  "type": "Feature",
  "properties": {
    "iso:country":"CH",
    "sg:address":"Bahnhofstrasse 1",
    "sg:city":"Dottikon",
    "sg:orig_category":"Herstellung von Konstruktionsteilen, Fertigbauteilen U Ausbauelementen aus Holz",
    "sg:postcode":"5605",
    "sg:province":"Aargau",
    "wof:name":"Alb. Furter Glaserei M\u00f6bel Schreinerei",
    "wof:placetype":"venue"
},
  "geometry": {"coordinates":[8.2429552078,47.3827285767],"type":"Point"}
}