{
  "type": "Feature",
  "properties": {
    "iso:country":"CH",
    "sg:address":"Prulay Rue De La 45",
    "sg:city":"Meyrin",
    "sg:orig_category":"Erbringung von Dienstleistungen f\u00fcr Unternehmen",
    "sg:phone":"+41 22 782 67 10",
    "sg:postcode":"1217",
    "sg:province":"Gen\u00e8ve",
    "wof:name":"Gotep Cr\u00e9ation, Notario",
    "wof:placetype":"venue"
},
  "geometry": {"coordinates":[6.0722160339,46.2284431458],"type":"Point"}
}