{
  "type": "Feature",
  "properties": {
    "iso:country":"CH",
    "sg:address":"Langensteinenstrasse 2",
    "sg:city":"Z\u00fcrich",
    "sg:orig_category":"Non-Classified Establishments",
    "sg:phone":"+41 2419003",
    "sg:postcode":"8057",
    "sg:province":"Z\u00fcrich",
    "wof:name":"Gasser's Bistro",
    "wof:placetype":"venue"
},
  "geometry": {"coordinates":[8.5456380844,47.3958015442],"type":"Point"}
}