{
  "type": "Feature",
  "properties": {
    "addr:full":"Thunstrasse 50 - P.o. Box 265 - Bern Bern 3005",
    "addr:housenumber":"50 p.o.",
    "addr:postcode":"3005",
    "addr:street":"Thunstrasse;Box 265 Bern",
    "iso:country":"CH",
    "sg:address":"Thunstrasse 50 - P.o. Box 265 -",
    "sg:city":"Bern",
    "sg:classifiers":[
        {
            "category":"Professional",
            "subcategory":"Art Services",
            "type":"Services"
        }
    ],
    "sg:phone":"+41 22 918 24 78",
    "sg:postcode":"3005",
    "sg:province":"Bern",
    "sg:tags":[
        "export-import"
    ],
    "wof:name":"British General Consulate",
    "wof:placetype":"venue"
},
  "geometry": {"coordinates":[6.137516,46.218929],"type":"Point"}
}