{
  "type": "Feature",
  "properties": {
    "iso:country":"CH",
    "sg:address":"Avant Muglins 3",
    "sg:city":"Scuol",
    "sg:orig_category":"Maler U Glasergewerbe Malerei",
    "sg:phone":"+41 81 864 92 61",
    "sg:postcode":"7550",
    "sg:province":"Graubunden",
    "wof:name":"Stocker Edgar",
    "wof:placetype":"venue"
},
  "geometry": {"coordinates":[10.3056297302,46.7954483032],"type":"Point"}
}