{
  "type": "Feature",
  "properties": {
    "iso:country":"CH",
    "sg:address":"Neuweg 2a 5614 Sarmenstorf. Postfach",
    "sg:city":"Sarmenstorf",
    "sg:orig_category":"Sonstige Kurierdienste",
    "sg:postcode":"5614",
    "sg:province":"Aargau",
    "wof:name":"Trans Express, Steinmann Rolf",
    "wof:placetype":"venue"
},
  "geometry": {"coordinates":[8.2498502731,47.3057899475],"type":"Point"}
}