{
  "type": "Feature",
  "properties": {
    "iso:country":"CH",
    "sg:address":"Chriesihoger 4",
    "sg:city":"Strengelbach",
    "sg:orig_category":"Vereine Harmonika and Akkordeon",
    "sg:postcode":"4802",
    "sg:province":"Aargau",
    "wof:name":"Harmonika Club Brittnau",
    "wof:placetype":"venue"
},
  "geometry": {"coordinates":[7.923178196,47.2782478333],"type":"Point"}
}