{
  "type": "Feature",
  "properties": {
    "iso:country":"CH",
    "sg:address":"Steinwiesstrasse 37 8000 Z\u00fcrich. Postfach 8032 Z\u00fcrich",
    "sg:city":"Zust",
    "sg:orig_category":"Rechtsberatung",
    "sg:phone":"+41 12525649",
    "sg:postcode":"32",
    "wof:name":"Scherrer Steuerberatungen",
    "wof:placetype":"venue"
},
  "geometry": {"coordinates":[8.5535669327,47.3706283569],"type":"Point"}
}