{
  "type": "Feature",
  "properties": {
    "iso:country":"CH",
    "sg:address":"Z\u00fcrcher Strasse 53",
    "sg:city":"St.gallen",
    "sg:orig_category":"Detailhandel mit Radio U Fernsehger\u00e4ten",
    "sg:phone":"+41 71 278 81 11",
    "sg:postcode":"9000",
    "sg:province":"St. Gallen",
    "wof:name":"Roland H\u00e4berli Radio-tv",
    "wof:placetype":"venue"
},
  "geometry": {"coordinates":[9.352350235,47.4183425903],"type":"Point"}
}