{
  "type": "Feature",
  "properties": {
    "iso:country":"CH",
    "sg:address":"Oberschw\u00e4ndenen",
    "sg:city":"Filzbach",
    "sg:orig_category":"Erbringung von Dienstleistungen f\u00fcr Unternehmen",
    "sg:phone":"+41 55 614 50 60",
    "sg:postcode":"8757",
    "sg:province":"Glarus",
    "wof:name":"Tal Alp Design Ag",
    "wof:placetype":"venue"
},
  "geometry": {"coordinates":[9.1327552795,47.1191749573],"type":"Point"}
}