{
  "type": "Feature",
  "properties": {
    "iso:country":"CH",
    "sg:address":"Grossmatte 7",
    "sg:city":"Littau",
    "sg:orig_category":"Herstellung von Zement",
    "sg:phone":"+41 32 954 10 28",
    "sg:postcode":"6014",
    "sg:province":"Luzern",
    "wof:name":"Baume David",
    "wof:placetype":"venue"
},
  "geometry": {"coordinates":[7.0049629211,47.2118835449],"type":"Point"}
}