{
  "type": "Feature",
  "properties": {
    "iso:country":"CH",
    "sg:address":"Via Trevano 55 6900 Lugano. Postfach",
    "sg:city":"Lugano",
    "sg:orig_category":"Betrieb U technische Hilfsdienste des Kultur U Unterhaltungswesens",
    "sg:postcode":"6900",
    "sg:province":"Ticino",
    "wof:name":"Sotell - Servizi Per L'organizzazione Del Tempo Libero E Del Lavoro",
    "wof:placetype":"venue"
},
  "geometry": {"coordinates":[8.956082,46.017258],"type":"Point"}
}