{
  "type": "Feature",
  "properties": {
    "iso:country":"CH",
    "sg:address":"Viollier Avenue 13",
    "sg:city":"Nyon",
    "sg:orig_category":"Sonstiges Versicherungsgewerbe",
    "sg:postcode":"1260",
    "sg:province":"Vaud",
    "wof:name":"Marmet Jacques Courtier En Assurances",
    "wof:placetype":"venue"
},
  "geometry": {"coordinates":[6.2371740341,46.3846130371],"type":"Point"}
}