{
  "type": "Feature",
  "properties": {
    "iso:country":"CH",
    "sg:address":"Rheineckerstrasse 12",
    "sg:city":"Thal",
    "sg:orig_category":"Wasserversorgung",
    "sg:phone":"+41 71 886 90 80",
    "sg:postcode":"9425",
    "sg:province":"St. Gallen",
    "wof:name":"Cwg Gmbh",
    "wof:placetype":"venue"
},
  "geometry": {"coordinates":[9.570857048,47.4645118713],"type":"Point"}
}