{
  "type": "Feature",
  "properties": {
    "iso:country":"CH",
    "sg:address":"R\u00fctenenstrasse 7",
    "sg:city":"Killwangen",
    "sg:orig_category":"Unternehmensberatung",
    "sg:phone":"+41 55 422 22 11",
    "sg:postcode":"8956",
    "sg:province":"Aargau",
    "wof:name":"Ug Management Ag",
    "wof:placetype":"venue"
},
  "geometry": {"coordinates":[8.7831096649,47.1618118286],"type":"Point"}
}