{
  "type": "Feature",
  "properties": {
    "iso:country":"CH",
    "sg:address":"Bungartstrasse 8",
    "sg:city":"Maschwanden",
    "sg:orig_category":"Allgemeiner Hoch U Tiefbau",
    "sg:postcode":"8933",
    "sg:province":"Z\u00fcrich",
    "wof:name":"B\u00fctler Markus",
    "wof:placetype":"venue"
},
  "geometry": {"coordinates":[8.428801,47.234192],"type":"Point"}
}