{
  "type": "Feature",
  "properties": {
    "iso:country":"CH",
    "sg:address":"Trevano Via 95 6900 Lugano. Postfach",
    "sg:city":"Lugano",
    "sg:orig_category":"Unclassifiable Establishments",
    "sg:postcode":"6900",
    "sg:province":"Ticino",
    "wof:name":"Sport Mngt Di Vauclair Geoffrey E Foglia Francesco Procuratori E Manager Sportivi, Marketing Ecc",
    "wof:placetype":"venue"
},
  "geometry": {"coordinates":[8.9585523605,46.0215835571],"type":"Point"}
}