{
  "type": "Feature",
  "properties": {
    "iso:country":"CH",
    "sg:address":"1040",
    "sg:city":"Echallens",
    "sg:orig_category":"Grosshandel mit Getreide, Saatgut U Futtermitteln",
    "sg:phone":"+41 56 225 20 51",
    "sg:postcode":"1040",
    "sg:province":"Vaud",
    "wof:name":"Copex Handels Gmbh",
    "wof:placetype":"venue"
},
  "geometry": {"coordinates":[8.2607555389,47.458114624],"type":"Point"}
}