{
  "type": "Feature",
  "properties": {
    "iso:country":"CH",
    "sg:address":"Breitenb\u00fchlweg 26",
    "sg:city":"Oberkulm",
    "sg:orig_category":"Politische Parteien SVP",
    "sg:phone":"+41 62 776 42 64",
    "sg:postcode":"5727",
    "sg:province":"Aargau",
    "wof:name":"Svp Ortspartei Oberkulm",
    "wof:placetype":"venue"
},
  "geometry": {"coordinates":[8.1316347122,47.297908783],"type":"Point"}
}