{
  "type": "Feature",
  "properties": {
    "iso:country":"CH",
    "sg:address":"Oberdorfstrasse 5 3612 Steffisburg. Postfach",
    "sg:city":"Steffisburg",
    "sg:orig_category":"Sonstiges Versicherungsgewerbe",
    "sg:phone":"+41 33 437 44 30",
    "sg:postcode":"3612",
    "sg:province":"Bern",
    "wof:name":"Krankenkasse Steffisburg",
    "wof:placetype":"venue"
},
  "geometry": {"coordinates":[7.63433218,46.7791519165],"type":"Point"}
}