{
  "type": "Feature",
  "properties": {
    "iso:country":"CH",
    "sg:address":"B\u00fchl",
    "sg:city":"Feutersoey",
    "sg:orig_category":"Sportschulen Ski-& Snowboardschulen",
    "sg:phone":"+41 79 434 57 52",
    "sg:postcode":"3784",
    "sg:province":"Bern",
    "wof:name":"Jakob Walker Ski-unterricht",
    "wof:placetype":"venue"
},
  "geometry": {"coordinates":[7.2712907791,46.4164085388],"type":"Point"}
}