{
  "type": "Feature",
  "properties": {
    "iso:country":"CH",
    "sg:address":"Latura",
    "sg:city":"Buchen",
    "sg:orig_category":"Herstellung von Konstruktionsteilen, Fertigbauteilen U Ausbauelementen aus Holz Zimmerei, Ingenieurh",
    "sg:phone":"+41 81 328 21 91",
    "sg:postcode":"7223",
    "sg:province":"Graubunden",
    "wof:name":"Christian Kasper Holzbau",
    "wof:placetype":"venue"
},
  "geometry": {"coordinates":[9.718706131,46.9409866333],"type":"Point"}
}