{
  "type": "Feature",
  "properties": {
    "iso:country":"CH",
    "sg:address":"Hellm\u00fchlenstrasse 24d 8580 Amriswil. Postfach 1015",
    "sg:city":"Amriswil",
    "sg:orig_category":"Sportvereine Minigolf",
    "sg:phone":"+41 71 411 17 42",
    "sg:postcode":"8580",
    "sg:province":"Thurgau",
    "wof:name":"Mc Amriswil",
    "wof:placetype":"venue"
},
  "geometry": {"coordinates":[9.2959308624,47.5438652039],"type":"Point"}
}