{
  "type": "Feature",
  "properties": {
    "iso:country":"CH",
    "sg:address":"Landenbergstrasse 24",
    "sg:city":"Z\u00fcrich",
    "sg:orig_category":"Detailhandel mit Zeitungen U Zeitschriften Kioske",
    "sg:phone":"+41 12723103",
    "sg:postcode":"8037",
    "sg:province":"Z\u00fcrich",
    "wof:name":"Emil Bertschinger Kiosk R\u00f6schibachplatz",
    "wof:placetype":"venue"
},
  "geometry": {"coordinates":[8.5286951065,47.392791748],"type":"Point"}
}