{
  "type": "Feature",
  "properties": {
    "iso:country":"CH",
    "sg:address":"Unterdorfstrasse 75",
    "sg:city":"Widnau",
    "sg:orig_category":"Herstellung von Metallkonstruktionen",
    "sg:postcode":"9443",
    "sg:province":"St. Gallen",
    "wof:name":"Jegen-montagen.",
    "wof:placetype":"venue"
},
  "geometry": {"coordinates":[8.5421571732,47.3348312378],"type":"Point"}
}