{
  "type": "Feature",
  "properties": {
    "iso:country":"CH",
    "sg:address":"Neuhausstrasse 30",
    "sg:city":"Basel",
    "sg:classifiers":[
        {
            "category":"Wholesale",
            "subcategory":"Chemicals & Plastics",
            "type":"Manufacturing & Wholesale Goods"
        }
    ],
    "sg:phone":"+41 61 638 90 30",
    "sg:postcode":"4019",
    "sg:province":"Basel-Stadt",
    "sg:tags":[
        "article",
        "articles",
        "hollow",
        "blown"
    ],
    "wof:name":"Densa Ag",
    "wof:placetype":"venue"
},
  "geometry": {"coordinates":[7.596625,47.582256],"type":"Point"}
}