{
  "type": "Feature",
  "properties": {
    "iso:country":"CH",
    "sg:address":"Place Du 23 Juin 8",
    "sg:city":"Saignel\u00e9gier",
    "sg:classifiers":[
        {
            "category":"Restaurant",
            "type":"Food & Drink"
        }
    ],
    "sg:phone":"+41 32 951 11 79",
    "sg:postcode":"2350",
    "sg:province":"Jura",
    "wof:name":"Caf\u00e9 De La Poste",
    "wof:placetype":"venue"
},
  "geometry": {"coordinates":[6.9960861206,47.2562065125],"type":"Point"}
}