{
  "type": "Feature",
  "properties": {
    "iso:country":"CH",
    "sg:address":"Bachofenstrasse 19",
    "sg:city":"Basel",
    "sg:orig_category":"Herstellung von Schmuck, Gold U Silberschmiedwaren",
    "sg:postcode":"4053",
    "sg:province":"Basel-Stadt",
    "wof:name":"Schnydrig Gaston",
    "wof:placetype":"venue"
},
  "geometry": {"coordinates":[7.6331739426,46.317489624],"type":"Point"}
}