{
  "type": "Feature",
  "properties": {
    "iso:country":"CH",
    "sg:address":"Sackzelg 34",
    "sg:city":"Z\u00fcrich",
    "sg:orig_category":"Sportvereine Turnen",
    "sg:postcode":"8047",
    "sg:province":"Z\u00fcrich",
    "wof:name":"Satus-m\u00e4nnerriege Albisrieden",
    "wof:placetype":"venue"
},
  "geometry": {"coordinates":[8.4976053238,47.3747711182],"type":"Point"}
}