{
  "type": "Feature",
  "properties": {
    "addr:full":"Kannenfeldplatz 4 Basel Basel-Stadt 4056",
    "addr:housenumber":"4",
    "addr:postcode":"4056",
    "addr:street":"Kannenfeldplatz",
    "iso:country":"CH",
    "sg:address":"Kannenfeldplatz 4",
    "sg:city":"Basel",
    "sg:orig_category":"Detailhandel mit Bekleidung Detailhandel mit Sportartikeln",
    "sg:phone":"+41 61 382 62 02",
    "sg:postcode":"4056",
    "sg:province":"Basel-Stadt",
    "wof:name":"Taucherhelm, Meier & Wenger",
    "wof:placetype":"venue"
},
  "geometry": {"coordinates":[7.574003,47.565594],"type":"Point"}
}