{
  "type": "Feature",
  "properties": {
    "iso:country":"CH",
    "sg:address":"Schulweg 2",
    "sg:city":"Hombrechtikon",
    "sg:orig_category":"Vorschulen, Kinderg\u00e4rten",
    "sg:phone":"+41 55 244 61 16",
    "sg:postcode":"8634",
    "sg:province":"Z\u00fcrich",
    "wof:name":"Kindergarten Altes D\u00f6rfli",
    "wof:placetype":"venue"
},
  "geometry": {"coordinates":[8.7649497986,47.2520828247],"type":"Point"}
}