{
  "type": "Feature",
  "properties": {
    "iso:country":"CH",
    "sg:address":"Via Dei Faggi 1 6912 Pazzallo. Postfach",
    "sg:city":"Chiasso",
    "sg:orig_category":"Handelsvermittlung U Grosshandel Nutzfahrzeuge Grosshandel",
    "sg:phone":"+41 17130136",
    "sg:postcode":"6830",
    "sg:province":"Ticino",
    "wof:name":"Heinz Rothmund Bus-import",
    "wof:placetype":"venue"
},
  "geometry": {"coordinates":[8.5377788544,47.2876968384],"type":"Point"}
}