{
  "type": "Feature",
  "properties": {
    "iso:country":"CH",
    "sg:address":"Bahnhofstrasse 12 3270 Aarberg. Postfach",
    "sg:city":"Aarberg",
    "sg:orig_category":"Allgemeiner Hoch U Tiefbau",
    "sg:postcode":"3270",
    "sg:province":"Bern",
    "wof:name":"M\u00fcller Aarberg Ag Bauunternehmung Usw.",
    "wof:placetype":"venue"
},
  "geometry": {"coordinates":[7.275518,47.042667],"type":"Point"}
}