{
  "type": "Feature",
  "properties": {
    "iso:country":"CH",
    "sg:address":"Breitbachstrasse 39",
    "sg:city":"Strengelbach",
    "sg:orig_category":"Vermietung U Verpachtung von eigenen Immobilien",
    "sg:postcode":"4802",
    "sg:province":"Aargau",
    "wof:name":"Scacchi Immobilien Ag",
    "wof:placetype":"venue"
},
  "geometry": {"coordinates":[7.9322838783,47.276134491],"type":"Point"}
}