{
  "type": "Feature",
  "properties": {
    "iso:country":"CH",
    "sg:address":"Avenue Du Midi 8",
    "sg:city":"Sion",
    "sg:orig_category":"Finanzierungsinstitutionen",
    "sg:postcode":"1950",
    "sg:province":"Valais",
    "wof:name":"Accountants & Financial Advisers Sa, Afa.",
    "wof:placetype":"venue"
},
  "geometry": {"coordinates":[7.3589577675,46.2306518555],"type":"Point"}
}