{
  "type": "Feature",
  "properties": {
    "iso:country":"CH",
    "sg:address":"Altgasse 82",
    "sg:city":"Baar",
    "sg:orig_category":"D\u00e4mmung gegen K\u00e4lte, W\u00e4rme, Schall U Ersch\u00fctterung",
    "sg:phone":"+41 32 757 31 31",
    "sg:postcode":"6340",
    "sg:province":"Zug",
    "wof:name":"Sablisol Sa Isolations",
    "wof:placetype":"venue"
},
  "geometry": {"coordinates":[7.0298018456,47.0446815491],"type":"Point"}
}