{
  "type": "Feature",
  "properties": {
    "addr:full":"Anderhalbacher Feutersoey Bern 3784",
    "addr:postcode":"3784",
    "iso:country":"CH",
    "sg:address":"Anderhalbacher",
    "sg:city":"Feutersoey",
    "sg:orig_category":"Bau U Wohngenossenschaften",
    "sg:postcode":"3784",
    "sg:province":"Bern",
    "wof:name":"Wohnbaugen.schachen",
    "wof:placetype":"venue"
},
  "geometry": {"coordinates":[8.317905,47.130466],"type":"Point"}
}