{
  "type": "Feature",
  "properties": {
    "iso:country":"CH",
    "sg:address":"Spitalring 7b",
    "sg:city":"Wolhusen",
    "sg:orig_category":"Sportvereine Unihockey",
    "sg:phone":"+41 41 490 17 33",
    "sg:postcode":"6110",
    "sg:province":"Luzern",
    "wof:name":"Uhc Wolhusen",
    "wof:placetype":"venue"
},
  "geometry": {"coordinates":[8.0693273544,47.0672340393],"type":"Point"}
}