{
  "type": "Feature",
  "properties": {
    "iso:country":"CH",
    "sg:address":"Route De La Coula",
    "sg:city":"Ch\u00e2tel-st-denis",
    "sg:orig_category":"Drogerien Parf\u00fcmerien U sonstiger Detailhandel mit kosmetischen Artikeln U K\u00f6rperpflegemitteln",
    "sg:phone":"+41 71 385 42 58",
    "sg:postcode":"1618",
    "sg:province":"Fribourg",
    "wof:name":"Josef Agosti Drogerie Neudorf",
    "wof:placetype":"venue"
},
  "geometry": {"coordinates":[9.2573957443,47.4171447754],"type":"Point"}
}