{
  "type": "Feature",
  "properties": {
    "iso:country":"CH",
    "sg:address":"Rue Fritz-marchand 18",
    "sg:city":"Montagne-sonvilier",
    "sg:orig_category":"Non-Classified Establishments",
    "sg:postcode":"2615",
    "sg:province":"Bern",
    "wof:name":"Celing It-service Gmbh",
    "wof:placetype":"venue"
},
  "geometry": {"coordinates":[-105.89307403559999,39.3157958984],"type":"Point"}
}