{
  "type": "Feature",
  "properties": {
    "iso:country":"CH",
    "sg:address":"Impasse Du Castel 11",
    "sg:city":"Fribourg",
    "sg:orig_category":"Public-Relations-Agenturen Werbeagenturen",
    "sg:phone":"+41 26 481 46 88",
    "sg:postcode":"1700",
    "sg:province":"Fribourg",
    "wof:name":"Markus Reck Reck Mcc",
    "wof:placetype":"venue"
},
  "geometry": {"coordinates":[7.1748661995,46.8171424866],"type":"Point"}
}