{
  "type": "Feature",
  "properties": {
    "iso:country":"CH",
    "sg:address":"Bachstrasse 33",
    "sg:city":"Berlingen",
    "sg:classifiers":[
        {
            "category":"Restaurant",
            "type":"Food & Drink"
        }
    ],
    "sg:phone":"+41 52 761 32 32",
    "sg:postcode":"8267",
    "sg:province":"Thurgau",
    "wof:name":"Restaurant Adler",
    "wof:placetype":"venue"
},
  "geometry": {"coordinates":[9.0162248611,47.6740646362],"type":"Point"}
}