{
  "type": "Feature",
  "properties": {
    "iso:country":"CH",
    "sg:address":"Oberlehn",
    "sg:city":"Quarten",
    "sg:orig_category":"Erschliessung von Grundst\u00fccken",
    "sg:postcode":"8883",
    "sg:province":"St. Gallen",
    "wof:name":"Genossenschaft F\u00fcr Landwirtschaftliches Bauen Der Pol. Gemeinde Quarten.",
    "wof:placetype":"venue"
},
  "geometry": {"coordinates":[9.2496938705,47.1067428589],"type":"Point"}
}