{
  "type": "Feature",
  "properties": {
    "iso:country":"CH",
    "sg:address":"Eichhaldenstr. 416. 5322 Koblenz. Postfach",
    "sg:city":"Baden",
    "sg:orig_category":"Herstellung von Schmuck, Gold U Silberschmiedwaren",
    "sg:postcode":"5400",
    "sg:province":"Aargau",
    "wof:name":"Finnstyle Frau A. M\u00fcller-levist\u00f6",
    "wof:placetype":"venue"
},
  "geometry": {"coordinates":[8.2373199463,47.6053390503],"type":"Point"}
}