{
  "type": "Feature",
  "properties": {
    "iso:country":"CH",
    "sg:address":"Deutsche Strasse 11",
    "sg:city":"Trimmis",
    "sg:classifiers":[
        {
            "category":"Restaurant",
            "type":"Food & Drink"
        }
    ],
    "sg:phone":"+41 81 353 54 19",
    "sg:postcode":"7203",
    "sg:province":"Graubunden",
    "wof:name":"Restaurant Zur R\u00fcfe",
    "wof:placetype":"venue"
},
  "geometry": {"coordinates":[9.5579681396,46.9059753418],"type":"Point"}
}