{
  "type": "Feature",
  "properties": {
    "addr:full":"Theilingerstrasse 36 Theilingen Z\u00fcrich 8484",
    "addr:housenumber":"36",
    "addr:postcode":"8484",
    "addr:street":"Theilingerstrasse",
    "iso:country":"CH",
    "sg:address":"Theilingerstrasse 36",
    "sg:city":"Theilingen",
    "sg:orig_category":"Architektur U Ingenieurb\u00fcros",
    "sg:phone":"+41 52 394 31 03",
    "sg:postcode":"8484",
    "sg:province":"Z\u00fcrich",
    "wof:name":"Iten Planungs Full Service",
    "wof:placetype":"venue"
},
  "geometry": {"coordinates":[8.767609,47.420944],"type":"Point"}
}