{
  "type": "Feature",
  "properties": {
    "iso:country":"CH",
    "sg:address":"R\u00fctiweg 24",
    "sg:city":"Flawil",
    "sg:orig_category":"Vereine Haus- and Grundeigent\u00fcmer",
    "sg:phone":"+41 56 496 20 48",
    "sg:postcode":"9230",
    "sg:province":"St. Gallen",
    "wof:name":"Hauseigent\u00fcmerverband Freiamt",
    "wof:placetype":"venue"
},
  "geometry": {"coordinates":[8.344452858,47.3506698608],"type":"Point"}
}