{
  "type": "Feature",
  "properties": {
    "iso:country":"CH",
    "sg:address":"Wengelacher 1 3800 Interlaken. Postfach 173",
    "sg:city":"Interlaken",
    "sg:orig_category":"Grosshandel mit Milch, Milcherzeugnissen, Eiern, Speise\u00f6len U Nahrungsfetten",
    "sg:phone":"+41 33 823 45 00",
    "sg:postcode":"3800",
    "sg:province":"Bern",
    "wof:name":"Ernst-peter Josi K\u00e4se Engros",
    "wof:placetype":"venue"
},
  "geometry": {"coordinates":[7.8534369469,46.6844787598],"type":"Point"}
}