{
  "type": "Feature",
  "properties": {
    "iso:country":"CH",
    "sg:address":"Gladbachstrasse 46",
    "sg:city":"Z\u00fcrich",
    "sg:orig_category":"Reiseb\u00fcros U Reiseveranstalter",
    "sg:postcode":"8044",
    "sg:province":"Z\u00fcrich",
    "wof:name":"Farmotel, Noirjean P.-a.",
    "wof:placetype":"venue"
},
  "geometry": {"coordinates":[7.2728447914,47.1238021851],"type":"Point"}
}