{
  "type": "Feature",
  "properties": {
    "iso:country":"CH",
    "sg:address":"Casino Avenue Du 45",
    "sg:city":"Montreux",
    "sg:classifiers":[
        {
            "category":"Travel",
            "subcategory":"Hotels & Motels",
            "type":"Entertainment"
        }
    ],
    "sg:phone":"+41 31 738 80 40",
    "sg:postcode":"1820",
    "sg:province":"Vaud",
    "sg:tags":[
        "hotels",
        "mit",
        "restaurant"
    ],
    "wof:name":"Fanger Wolf",
    "wof:placetype":"venue"
},
  "geometry": {"coordinates":[7.4019579887,46.7949676514],"type":"Point"}
}