{
  "type": "Feature",
  "properties": {
    "iso:country":"CH",
    "sg:address":"Mattweg 151",
    "sg:city":"Arlesheim",
    "sg:orig_category":"Vereine Z\u00fcnfte",
    "sg:phone":"+41 61 701 85 60",
    "sg:postcode":"4144",
    "sg:province":"Basel-Landschaft",
    "wof:name":"Zunft Zu G\u00e4rtnern",
    "wof:placetype":"venue"
},
  "geometry": {"coordinates":[7.6171250343,47.5053596497],"type":"Point"}
}