{
  "type": "Feature",
  "properties": {
    "addr:full":"Pfungen Z\u00fcrich 8422",
    "addr:postcode":"8422",
    "iso:country":"CH",
    "sg:city":"Pfungen",
    "sg:orig_category":"Wirtschaft U Handel, Allgemeines zu Wirtschaft U Handel",
    "sg:postcode":"8422",
    "sg:province":"Z\u00fcrich",
    "wof:name":"Nacht-express-system Gmbh",
    "wof:placetype":"venue"
},
  "geometry": {"coordinates":[8.6422,47.516327],"type":"Point"}
}