{
  "type": "Feature",
  "properties": {
    "iso:country":"CH",
    "sg:address":"Caroline Chemin De La 2-4",
    "sg:city":"Petit-lancy",
    "sg:orig_category":"Herstellung von Metallkonstruktionen",
    "sg:phone":"+41 22 793 84 77",
    "sg:postcode":"1213",
    "sg:province":"Gen\u00e8ve",
    "wof:name":"Sun 7 Sa",
    "wof:placetype":"venue"
},
  "geometry": {"coordinates":[6.1001057625,46.1837158203],"type":"Point"}
}