{
  "type": "Feature",
  "properties": {
    "addr:full":"Zugerstrasse 197 Neu\u00e4geri Zug 6314",
    "addr:housenumber":"197",
    "addr:postcode":"6314",
    "addr:street":"Zugerstrasse;Zug",
    "iso:country":"CH",
    "sg:address":"Zugerstrasse 197",
    "sg:city":"Neu\u00e4geri",
    "sg:orig_category":"Ausbaugewerbe Verlegen von Fliesen U Platten",
    "sg:phone":"+41 41 750 21 92",
    "sg:postcode":"6314",
    "sg:province":"Zug",
    "wof:name":"Mastel Ag",
    "wof:placetype":"venue"
},
  "geometry": {"coordinates":[8.56285,47.152779],"type":"Point"}
}