{
  "type": "Feature",
  "properties": {
    "iso:country":"CH",
    "sg:address":"Itaslenstrasse 7",
    "sg:city":"Dussnang",
    "sg:orig_category":"Schlossereien Sonstige Bauinstallation",
    "sg:phone":"+41 34 445 98 73",
    "sg:postcode":"8374",
    "sg:province":"Thurgau",
    "wof:name":"Bernhard Sahli Montagen & Reparatur-service",
    "wof:placetype":"venue"
},
  "geometry": {"coordinates":[7.5851020813,47.0825080872],"type":"Point"}
}