{
  "type": "Feature",
  "properties": {
    "addr:full":"Worbstrasse 187 G\u00fcmligen Bern 3073",
    "addr:housenumber":"187",
    "addr:postcode":"3073",
    "addr:street":"Worbstrasse",
    "iso:country":"CH",
    "sg:address":"Worbstrasse 187",
    "sg:city":"G\u00fcmligen",
    "sg:classifiers":[
        {
            "category":"Manufacturing",
            "subcategory":"Electronics",
            "type":"Manufacturing & Wholesale Goods"
        }
    ],
    "sg:phone":"+41 31 999 66 90",
    "sg:postcode":"3073",
    "sg:province":"Bern",
    "sg:tags":[
        "industrial",
        "cable"
    ],
    "wof:name":"Concable Ag",
    "wof:placetype":"venue"
},
  "geometry": {"coordinates":[7.502936,46.934673],"type":"Point"}
}