{
  "type": "Feature",
  "properties": {
    "iso:country":"CH",
    "sg:address":"Baslerstrasse 323",
    "sg:city":"Allschwil",
    "sg:classifiers":[
        {
            "category":"Restaurant",
            "type":"Food & Drink"
        }
    ],
    "sg:phone":"+41 61 483 08 88",
    "sg:postcode":"4123",
    "sg:province":"Basel-Landschaft",
    "wof:name":"Pizzeria Casa Nostra",
    "wof:placetype":"venue"
},
  "geometry": {"coordinates":[7.5609030724,47.5578842163],"type":"Point"}
}