{
  "type": "Feature",
  "properties": {
    "iso:country":"CH",
    "sg:address":"Avenue De La Gare",
    "sg:city":"Ardon",
    "sg:orig_category":"Bahnhofbuffets Restaurants",
    "sg:phone":"+41 27 306 78 00",
    "sg:postcode":"1957",
    "sg:province":"Valais",
    "wof:name":"Buffet De La Gare",
    "wof:placetype":"venue"
},
  "geometry": {"coordinates":[7.26433,46.21302],"type":"Point"}
}