{
  "type": "Feature",
  "properties": {
    "iso:country":"CH",
    "sg:address":"Adlerstrasse 24",
    "sg:city":"Magden",
    "sg:orig_category":"Arztpraxen",
    "sg:phone":"+41 61 841 20 70",
    "sg:postcode":"4312",
    "sg:province":"Aargau",
    "wof:name":"Dr.med.leonhard Schmid Spezialarzt Fmh",
    "wof:placetype":"venue"
},
  "geometry": {"coordinates":[7.812806,47.526016],"type":"Point"}
}