{
  "type": "Feature",
  "properties": {
    "addr:full":"Dorf 213 Waldstatt Appenzell Ausserrhoden 9104",
    "addr:housenumber":"213",
    "addr:postcode":"9104",
    "addr:street":"Dorf;Ausserrhoden",
    "iso:country":"CH",
    "sg:address":"Dorf 213",
    "sg:city":"Waldstatt",
    "sg:orig_category":"Detailhandel mit Brennstoffen U Heizmaterial G\u00fcterbef\u00f6rderung im Strassenverkehr",
    "sg:phone":"+41 71 351 22 10",
    "sg:postcode":"9104",
    "sg:province":"Appenzell Ausserrhoden",
    "wof:name":"Ernst Kamm",
    "wof:placetype":"venue"
},
  "geometry": {"coordinates":[9.280953,47.355694],"type":"Point"}
}