{
  "type": "Feature",
  "properties": {
    "iso:country":"CH",
    "sg:address":"Kolinplatz 2 6300 Zug. Postfach 69",
    "sg:city":"Zug",
    "sg:orig_category":"Reiseb\u00fcros",
    "sg:phone":"+41 41 710 60 60",
    "sg:postcode":"6301",
    "sg:province":"Zug",
    "wof:name":"Crystal Travel Ag",
    "wof:placetype":"venue"
},
  "geometry": {"coordinates":[8.515376091,47.1663856506],"type":"Point"}
}