{
  "type": "Feature",
  "properties": {
    "iso:country":"CH",
    "sg:address":"Siewerdtstrasse 10 8050 Z\u00fcrich. Postfach",
    "sg:city":"Z\u00fcrich",
    "sg:orig_category":"Gewinnung von Kies U Sand Herstellung von Betonerzeugnissen f\u00fcr den Bau",
    "sg:phone":"+41 13186868",
    "sg:postcode":"8050",
    "sg:province":"Z\u00fcrich",
    "wof:name":"Hcb Holderbank Ag Zement - Beton - Bindemittel",
    "wof:placetype":"venue"
},
  "geometry": {"coordinates":[8.5480136871,47.4120559692],"type":"Point"}
}