{
  "type": "Feature",
  "properties": {
    "iso:country":"CH",
    "sg:address":"Hertensteinstrasse 24",
    "sg:city":"Luzern",
    "sg:orig_category":"Chemische Reinigung",
    "sg:phone":"+41 41 410 68 78",
    "sg:postcode":"6004",
    "sg:province":"Luzern",
    "wof:name":"Ghelma Ag Textilreinigung",
    "wof:placetype":"venue"
},
  "geometry": {"coordinates":[8.309455,47.055016],"type":"Point"}
}