{
  "type": "Feature",
  "properties": {
    "iso:country":"CH",
    "sg:address":"Spiegelberg 82 4933 R\u00fctschelen. Postfach",
    "sg:city":"R\u00fctschelen",
    "sg:orig_category":"Allgemeiner Hoch U Tiefbau",
    "sg:postcode":"4933",
    "sg:province":"Bern",
    "wof:name":"Christen & Russ Baugesch\u00e4ft",
    "wof:placetype":"venue"
},
  "geometry": {"coordinates":[7.775196,47.167633],"type":"Point"}
}