{
  "type": "Feature",
  "properties": {
    "iso:country":"CH",
    "sg:address":"Rue De Gen\u00e8ve 129",
    "sg:city":"Th\u00f4nex",
    "sg:orig_category":"Sonstige Kultur U Unterhaltungseinrichtungen Spielsalons",
    "sg:phone":"+41 22 349 38 56",
    "sg:postcode":"1226",
    "sg:province":"Gen\u00e8ve",
    "wof:name":"Centre Sportif De Billard Th\u00f4nex, Mme Salgado",
    "wof:placetype":"venue"
},
  "geometry": {"coordinates":[6.2042961121,46.1928291321],"type":"Point"}
}