{
  "type": "Feature",
  "properties": {
    "iso:country":"CH",
    "sg:address":"Kantonsstrasse 38 3930 Visp. Postfach",
    "sg:city":"Visp",
    "sg:orig_category":"Herstellung von Anstrichmitteln, Druckfarben U Kitten Herstellung von sonstigen organischen Grundsto",
    "sg:phone":"+41 61 467 66 00",
    "sg:postcode":"3930",
    "sg:province":"Valais",
    "wof:name":"Ctw Strassenbaustoffe Ag",
    "wof:placetype":"venue"
},
  "geometry": {"coordinates":[7.6526389122,47.5312805176],"type":"Point"}
}