{
  "type": "Feature",
  "properties": {
    "iso:country":"CH",
    "sg:address":"Wiesenschanzweg 36",
    "sg:city":"Basel",
    "sg:orig_category":"Mechanik",
    "sg:phone":"+41 61 692 57 74",
    "sg:postcode":"4057",
    "sg:province":"Basel-Stadt",
    "wof:name":"V. D'angelo",
    "wof:placetype":"venue"
},
  "geometry": {"coordinates":[7.5951747894,47.5728263855],"type":"Point"}
}