{
  "type": "Feature",
  "properties": {
    "iso:country":"CH",
    "sg:address":"La Pr\u00e9fecture",
    "sg:city":"Bulle",
    "sg:orig_category":"Interessenvertretungen",
    "sg:postcode":"1630",
    "sg:province":"Fribourg",
    "wof:name":"Fondation Sauvons Le Clos Grand-jacques",
    "wof:placetype":"venue"
},
  "geometry": {"coordinates":[6.6092648506,46.9078826904],"type":"Point"}
}