{
  "type": "Feature",
  "properties": {
    "iso:country":"CH",
    "sg:address":"Tottikonstrasse 13",
    "sg:city":"Stans",
    "sg:orig_category":"Grosshandel mit Textilien",
    "sg:phone":"+41 41 610 73 32",
    "sg:postcode":"6370",
    "sg:province":"Nidwalden",
    "wof:name":"Matsura, R. Achermann",
    "wof:placetype":"venue"
},
  "geometry": {"coordinates":[8.3663921356,46.9596862793],"type":"Point"}
}