{
  "type": "Feature",
  "properties": {
    "iso:country":"CH",
    "sg:address":"Gewerbestrasse 5",
    "sg:city":"Cham",
    "sg:orig_category":"Herstellung von Sportger\u00e4ten",
    "sg:postcode":"6330",
    "sg:province":"Zug",
    "wof:name":"Sportger\u00e4te Hinnen Otto",
    "wof:placetype":"venue"
},
  "geometry": {"coordinates":[8.2773313522,46.9412918091],"type":"Point"}
}