{
  "type": "Feature",
  "properties": {
    "iso:country":"CH",
    "sg:address":"Etzelstrasse 10",
    "sg:city":"Richterswil",
    "sg:orig_category":"Erschliessung von Grundst\u00fccken",
    "sg:phone":"+41 71 855 20 68",
    "sg:postcode":"8805",
    "sg:province":"Z\u00fcrich",
    "wof:name":"Eisenbahner-baugenossenschaft Rorschach",
    "wof:placetype":"venue"
},
  "geometry": {"coordinates":[9.5060224533,47.4761695862],"type":"Point"}
}