{
  "type": "Feature",
  "properties": {
    "iso:country":"CH",
    "sg:address":"Beim Lindenbaum 23",
    "sg:city":"Allschwil",
    "sg:orig_category":"Gartenbau",
    "sg:phone":"+41 61 481 77 21",
    "sg:postcode":"4123",
    "sg:province":"Basel-Landschaft",
    "wof:name":"Hansj\u00f6rg Hess G\u00e4rtnerei",
    "wof:placetype":"venue"
},
  "geometry": {"coordinates":[7.5399641991,47.5572814941],"type":"Point"}
}