{
  "type": "Feature",
  "properties": {
    "iso:country":"CH",
    "sg:address":"Route De Gletterens",
    "sg:city":"Portalban",
    "sg:orig_category":"Grosshandel mit Wein U Spirituosen Grosshandel mit sonstigen Getr\u00e4nken",
    "sg:phone":"+41 26 677 28 28",
    "sg:postcode":"1568",
    "sg:province":"Fribourg",
    "wof:name":"A. Delley & Fils Sa Commerce De Boissons",
    "wof:placetype":"venue"
},
  "geometry": {"coordinates":[6.9564819336,46.9175491333],"type":"Point"}
}