{
  "type": "Feature",
  "properties": {
    "iso:country":"CH",
    "sg:address":"L\u00f6wenhof 4",
    "sg:city":"Beringen",
    "sg:orig_category":"Sanit\u00e4r, Heizungs U L\u00fcftungsinstallation",
    "sg:postcode":"8222",
    "sg:province":"Schaffhausen",
    "wof:name":"Sch\u00e4llibaum H.",
    "wof:placetype":"venue"
},
  "geometry": {"coordinates":[8.5740919113,47.6978416443],"type":"Point"}
}