{
  "type": "Feature",
  "properties": {
    "iso:country":"CH",
    "sg:address":"Au Village 25",
    "sg:city":"Glovelier",
    "sg:orig_category":"Non-Classified Establishments",
    "sg:postcode":"2855",
    "sg:province":"Jura",
    "wof:name":"Dm Garage S. \u00e0 R.l.",
    "wof:placetype":"venue"
},
  "geometry": {"coordinates":[7.2009749413,47.3326759338],"type":"Point"}
}