{
  "type": "Feature",
  "properties": {
    "iso:country":"CH",
    "sg:address":"Pian S.giacomo",
    "sg:city":"Mesocco",
    "sg:classifiers":[
        {
            "category":"Travel",
            "subcategory":"Hotels & Motels",
            "type":"Entertainment"
        }
    ],
    "sg:phone":"+41 91 756 60 40",
    "sg:postcode":"6563",
    "sg:province":"Graubunden",
    "sg:tags":[
        "hotels",
        "mit",
        "restaurant"
    ],
    "wof:name":"Albergo Monte Br\u00e9 Sagl",
    "wof:placetype":"venue"
},
  "geometry": {"coordinates":[8.7849693298,46.174697876],"type":"Point"}
}