{
  "type": "Feature",
  "properties": {
    "iso:country":"CH",
    "sg:address":"Allmei 7",
    "sg:city":"Visp",
    "sg:orig_category":"Handel mit Automobilen",
    "sg:postcode":"3930",
    "sg:province":"Valais",
    "wof:name":"Mk Handels Und Reparatur Ag",
    "wof:placetype":"venue"
},
  "geometry": {"coordinates":[7.874958992,46.294052124],"type":"Point"}
}