{
  "type": "Feature",
  "properties": {
    "iso:country":"CH",
    "sg:address":"Rue De Rive 19",
    "sg:city":"Nyon",
    "sg:orig_category":"Detailhandel mit Sportartikeln Schmieden",
    "sg:phone":"+41 21 960 18 09",
    "sg:postcode":"1260",
    "sg:province":"Vaud",
    "wof:name":"Charles Gailloud",
    "wof:placetype":"venue"
},
  "geometry": {"coordinates":[6.9259128571,46.3976020813],"type":"Point"}
}