{
  "type": "Feature",
  "properties": {
    "iso:country":"CH",
    "sg:address":"Gellertstrasse 33",
    "sg:city":"Basel",
    "sg:orig_category":"Erwachsenenbildung U Unterricht Sprachschulen",
    "sg:phone":"+41 61 312 41 44",
    "sg:postcode":"4052",
    "sg:province":"Basel-Stadt",
    "wof:name":"Verein Freie Musikschule",
    "wof:placetype":"venue"
},
  "geometry": {"coordinates":[7.6123209,47.55128479],"type":"Point"}
}