{
  "type": "Feature",
  "properties": {
    "iso:country":"CH",
    "sg:address":"Siewerdtstrasse 69 8050 Z\u00fcrich",
    "sg:city":"Zust",
    "sg:orig_category":"Pensionskassen",
    "sg:phone":"+41 71 333 10 23",
    "sg:postcode":"50",
    "wof:name":"Personalf\u00fcrsorgestiftung A. Vogel, Biologische Heilmittel Gmbh",
    "wof:placetype":"venue"
},
  "geometry": {"coordinates":[9.3621683121,47.3862419128],"type":"Point"}
}