{
  "type": "Feature",
  "properties": {
    "iso:country":"CH",
    "sg:address":"Arnold Baumgartner-strasse 5 2540 Grenchen. Postfach 709",
    "sg:city":"Grenchen",
    "sg:orig_category":"Herstellung von optischen Instrumenten Herstellung von optischen U fotografischen Ger\u00e4ten",
    "sg:phone":"+41 32 652 90 78",
    "sg:postcode":"2540",
    "sg:province":"Solothurn",
    "wof:name":"Ls Laser Systems Ag",
    "wof:placetype":"venue"
},
  "geometry": {"coordinates":[7.3878531456,47.2021408081],"type":"Point"}
}