{
  "type": "Feature",
  "properties": {
    "iso:country":"CH",
    "sg:address":"M\u00fchlebachstrasse 70",
    "sg:city":"Z\u00fcrich",
    "sg:orig_category":"Pensionskassen",
    "sg:phone":"+41 12622270",
    "sg:postcode":"8008",
    "sg:province":"Z\u00fcrich",
    "wof:name":"Vorsorgestiftung Des Schweizerischen Hauseigent\u00fcmerverbandes",
    "wof:placetype":"venue"
},
  "geometry": {"coordinates":[8.5525312424,47.3626480103],"type":"Point"}
}