{
  "type": "Feature",
  "properties": {
    "iso:country":"CH",
    "sg:address":"Route De Crans",
    "sg:city":"Lens",
    "sg:orig_category":"Detailhandel mit Radio U Fernsehger\u00e4ten Detailhandel mit elektrischen Haushalts-,Radio U Fernsehger\u00e4",
    "sg:phone":"+41 27 483 14 89",
    "sg:postcode":"1978",
    "sg:province":"Valais",
    "wof:name":"R Et B Radio-tv, Tornare",
    "wof:placetype":"venue"
},
  "geometry": {"coordinates":[7.4502239227,46.2898712158],"type":"Point"}
}