{
  "type": "Feature",
  "properties": {
    "iso:country":"CH",
    "sg:address":"4566",
    "sg:city":"Kriegstetten",
    "sg:orig_category":"Unclassifiable Establishments",
    "sg:phone":"+41 32 675 51 55",
    "sg:postcode":"4566",
    "sg:province":"Solothurn",
    "wof:name":"Elektra Oekingen-halten.",
    "wof:placetype":"venue"
},
  "geometry": {"coordinates":[7.5980668068,47.1751251221],"type":"Point"}
}