{
  "type": "Feature",
  "properties": {
    "iso:country":"CH",
    "sg:address":"Grand-rue 56",
    "sg:city":"Tramelan",
    "sg:orig_category":"Architektur U Ingenieurb\u00fcros",
    "sg:phone":"+41 32 487 64 13",
    "sg:postcode":"2720",
    "sg:province":"Bern",
    "wof:name":"Zimmermann Et Tellenbach Sa, Succursale De Tramelan",
    "wof:placetype":"venue"
},
  "geometry": {"coordinates":[7.100302,47.223145],"type":"Point"}
}