{
  "type": "Feature",
  "properties": {
    "iso:country":"CH",
    "sg:address":"Poststrasse 25",
    "sg:city":"St.gallen",
    "sg:orig_category":"Detailhandel mit Bekleidung",
    "sg:phone":"+41 71 222 35 94",
    "sg:postcode":"9000",
    "sg:province":"St. Gallen",
    "wof:name":"Detlef Haderer Holenstein Modes",
    "wof:placetype":"venue"
},
  "geometry": {"coordinates":[9.37155,47.424],"type":"Point"}
}