{
  "type": "Feature",
  "properties": {
    "iso:country":"CH",
    "sg:address":"Zeughausstrasse 8887 Mels. Postfach 127",
    "sg:city":"Mels",
    "sg:orig_category":"Oberfl\u00e4chenveredlung U W\u00e4rmebehandlung",
    "sg:phone":"+41 61 717 90 20",
    "sg:postcode":"8887",
    "sg:province":"St. Gallen",
    "wof:name":"Karl Haas & Co. Ag Metallveredlung",
    "wof:placetype":"venue"
},
  "geometry": {"coordinates":[7.5909199715,47.4933052063],"type":"Point"}
}