{
  "type": "Feature",
  "properties": {
    "iso:country":"CH",
    "sg:address":"Rue De Montsalvens 18",
    "sg:city":"Broc",
    "sg:orig_category":"Zahnarztpraxen",
    "sg:phone":"+41 32 913 21 53",
    "sg:postcode":"1636",
    "sg:province":"Fribourg",
    "wof:name":"Dr M\u00e9d.dent.milorad Jokanovic M\u00e9decin-dentiste",
    "wof:placetype":"venue"
},
  "geometry": {"coordinates":[6.8246650696,47.101436615],"type":"Point"}
}