{
  "type": "Feature",
  "properties": {
    "iso:country":"CH",
    "sg:address":"Unterdorfstrasse 25",
    "sg:city":"Seon",
    "sg:orig_category":"Softwareentwicklung U beratung",
    "sg:phone":"+41 31 808 07 07",
    "sg:postcode":"5703",
    "sg:province":"Aargau",
    "wof:name":"Informatiq Gmbh",
    "wof:placetype":"venue"
},
  "geometry": {"coordinates":[8.1612119675,47.34815979],"type":"Point"}
}