{
  "type": "Feature",
  "properties": {
    "addr:full":"Bolligenstrasse 94 Bolligen Bern 3065",
    "addr:housenumber":"94",
    "addr:postcode":"3065",
    "addr:street":"Bolligenstrasse",
    "iso:country":"CH",
    "sg:address":"Bolligenstrasse 94",
    "sg:city":"Bolligen",
    "sg:classifiers":[
        {
            "category":"Banks & Credit Unions",
            "subcategory":"Bank",
            "type":"Services"
        }
    ],
    "sg:phone":"+41 31 921 58 66",
    "sg:postcode":"3065",
    "sg:province":"Bern",
    "wof:name":"Schweiz. Bankgesellschaft",
    "wof:placetype":"venue"
},
  "geometry": {"coordinates":[7.496856,46.970798],"type":"Point"}
}