{
  "type": "Feature",
  "properties": {
    "iso:country":"CH",
    "sg:address":"8335",
    "sg:city":"Oberhittnau",
    "sg:orig_category":"Vorschulen, Kinderg\u00e4rten",
    "sg:phone":"+41 19502900",
    "sg:postcode":"8335",
    "sg:province":"Z\u00fcrich",
    "wof:name":"Kindergarten Oberhittnau",
    "wof:placetype":"venue"
},
  "geometry": {"coordinates":[8.8222799301,47.3610916138],"type":"Point"}
}