{
  "type": "Feature",
  "properties": {
    "iso:country":"CH",
    "sg:address":"Felsenaustrasse 25 7000 Chur. Postfach 263",
    "sg:city":"Chur",
    "sg:orig_category":"Verwaltung von Immobilien",
    "sg:phone":"+41 81 284 00 24",
    "sg:postcode":"7000",
    "sg:province":"Graubunden",
    "wof:name":"Rossi Immobilien",
    "wof:placetype":"venue"
},
  "geometry": {"coordinates":[9.514131546,46.8557281494],"type":"Point"}
}