{
  "type": "Feature",
  "properties": {
    "iso:country":"CH",
    "sg:address":"M\u00fcnchwilerstrasse 19 9546 Tuttwil. Postfach",
    "sg:city":"Tuttwil",
    "sg:orig_category":"Finanzierungsinstitutionen",
    "sg:phone":"+41 52 378 31 62",
    "sg:postcode":"9546",
    "sg:province":"Thurgau",
    "wof:name":"Datec Projektmanagement Teufer Daniel",
    "wof:placetype":"venue"
},
  "geometry": {"coordinates":[8.9412202835,47.4820137024],"type":"Point"}
}