{
  "type": "Feature",
  "properties": {
    "iso:country":"CH",
    "sg:address":"Hintereggstrasse 36",
    "sg:city":"Br\u00fcgglen",
    "sg:orig_category":"Fotografische Ateliers",
    "sg:phone":"+41 79 631 94 87",
    "sg:postcode":"4582",
    "sg:province":"Solothurn",
    "wof:name":"Urs Kohler Fotografisches Atelier",
    "wof:placetype":"venue"
},
  "geometry": {"coordinates":[7.4962930679,47.143661499],"type":"Point"}
}