{
  "type": "Feature",
  "properties": {
    "iso:country":"CH",
    "sg:address":"Grand-rue 75",
    "sg:city":"Morges",
    "sg:orig_category":"Arztpraxen",
    "sg:phone":"+41 21 801 69 88",
    "sg:postcode":"1110",
    "sg:province":"Vaud",
    "wof:name":"Dr M\u00e9d. Eliane Charbon M\u00e9decin Sp\u00e9cialiste Fmh",
    "wof:placetype":"venue"
},
  "geometry": {"coordinates":[6.498189,46.508705],"type":"Point"}
}