{
  "type": "Feature",
  "properties": {
    "iso:country":"CH",
    "sg:address":"Jakobstrasse 56 2500 Biel/bienne. Postfach 8154",
    "sg:city":"Biel/bienne",
    "sg:orig_category":"Herstellung von Werkzeugmaschinen",
    "sg:phone":"+41 32 341 34 86",
    "sg:postcode":"2500",
    "sg:province":"Bern",
    "wof:name":"Schnyder Sa",
    "wof:placetype":"venue"
},
  "geometry": {"coordinates":[7.2745399475,47.1490020752],"type":"Point"}
}