{
  "type": "Feature",
  "properties": {
    "iso:country":"CH",
    "sg:address":"Trouillat Rue Joseph- 11",
    "sg:city":"Pruntrut",
    "sg:orig_category":"Non-Classified Establishments",
    "sg:postcode":"2900",
    "sg:province":"Jura",
    "wof:name":"Pizzeria Cialina, Livio Ciampi",
    "wof:placetype":"venue"
},
  "geometry": {"coordinates":[7.0738101006,47.4174957275],"type":"Point"}
}