{
  "type": "Feature",
  "properties": {
    "iso:country":"CH",
    "sg:address":"Flurstrasse 4 2558 Aegerten. Postfach 183",
    "sg:city":"Aegerten",
    "sg:orig_category":"Datenverarbeitungsdienste Unternehmensberatung",
    "sg:phone":"+41 32 373 53 31",
    "sg:postcode":"2558",
    "sg:province":"Bern",
    "wof:name":"Consilex Ag",
    "wof:placetype":"venue"
},
  "geometry": {"coordinates":[7.293651,47.119785],"type":"Point"}
}