{
  "type": "Feature",
  "properties": {
    "iso:country":"CH",
    "sg:address":"Allmendweg 16",
    "sg:city":"Herzogenbuchsee",
    "sg:orig_category":"Vereine Musik/Blasmusik",
    "sg:phone":"+41 62 961 10 84",
    "sg:postcode":"3360",
    "sg:province":"Bern",
    "wof:name":"Musikgesellschaft B\u00fctzberg",
    "wof:placetype":"venue"
},
  "geometry": {"coordinates":[7.717069149,47.1912841797],"type":"Point"}
}