{
  "type": "Feature",
  "properties": {
    "iso:country":"CH",
    "sg:address":"3800",
    "sg:city":"Interlaken",
    "sg:orig_category":"Schulpflegen",
    "sg:postcode":"3800",
    "sg:province":"Bern",
    "wof:name":"Sekundarschulkommission Der Gemeinde Interlaken",
    "wof:placetype":"venue"
},
  "geometry": {"coordinates":[7.8534369469,46.6844787598],"type":"Point"}
}