{
  "type": "Feature",
  "properties": {
    "iso:country":"CH",
    "sg:address":"Hornweg 5",
    "sg:city":"M\u00fchleberg",
    "sg:orig_category":"Grosshandel mit lebenden Tieren",
    "sg:phone":"+41 31 751 00 49",
    "sg:postcode":"3203",
    "sg:province":"Bern",
    "wof:name":"H. Krummen",
    "wof:placetype":"venue"
},
  "geometry": {"coordinates":[7.2694091797,46.9644203186],"type":"Point"}
}