{
  "type": "Feature",
  "properties": {
    "iso:country":"CH",
    "sg:address":"\u00c4cherli 65",
    "sg:city":"Alterswil",
    "sg:classifiers":[
        {
            "category":"Professional",
            "subcategory":"Art Services",
            "type":"Services"
        }
    ],
    "sg:phone":"+41 26 494 03 83",
    "sg:postcode":"1715",
    "sg:province":"Fribourg",
    "sg:tags":[
        "homepage",
        "designing"
    ],
    "wof:name":"Aginet Ag",
    "wof:placetype":"venue"
},
  "geometry": {"coordinates":[7.2548508644,46.7977333069],"type":"Point"}
}