{
  "type": "Feature",
  "properties": {
    "iso:country":"CH",
    "sg:address":"Buechental 3",
    "sg:city":"Oberb\u00fcren",
    "sg:orig_category":"Vermietung U Verpachtung von eigenen Immobilien",
    "sg:postcode":"9245",
    "sg:province":"St. Gallen",
    "wof:name":"Immofust Ag",
    "wof:placetype":"venue"
},
  "geometry": {"coordinates":[9.1553268433,47.4462356567],"type":"Point"}
}