{
  "type": "Feature",
  "properties": {
    "iso:country":"CH",
    "sg:address":"Bahnhofplatz 1 8001 Z\u00fcrich. Postfach",
    "sg:city":"Z\u00fcrich",
    "sg:orig_category":"Versicherungen Generalagenturen",
    "sg:phone":"+41 12117411",
    "sg:postcode":"8023",
    "sg:province":"Z\u00fcrich",
    "wof:name":"Winterthur-versicherungen Generalagentur Bahnhof",
    "wof:placetype":"venue"
},
  "geometry": {"coordinates":[8.5412092209,47.3768119812],"type":"Point"}
}