{
  "type": "Feature",
  "properties": {
    "iso:country":"CH",
    "sg:address":"Chemin Des L\u00e9ch\u00e8res 8",
    "sg:city":"Meyrin",
    "sg:orig_category":"G\u00fcterbef\u00f6rderung im Strassenverkehr",
    "sg:postcode":"1217",
    "sg:province":"Gen\u00e8ve",
    "wof:name":"Klecker Eveline",
    "wof:placetype":"venue"
},
  "geometry": {"coordinates":[6.0684609413,46.2221260071],"type":"Point"}
}