{
  "type": "Feature",
  "properties": {
    "iso:country":"CH",
    "sg:address":"Rue Des Alpes 5",
    "sg:city":"Gen\u00e8ve",
    "sg:orig_category":"Gewinnung von Kies U Sand Herstellung von sonstigen Produkten aus nichtmetallischen Mineralien",
    "sg:phone":"+41 22 731 40 28",
    "sg:postcode":"1201",
    "sg:province":"Gen\u00e8ve",
    "wof:name":"Grave Sa",
    "wof:placetype":"venue"
},
  "geometry": {"coordinates":[6.1481971741,46.2081871033],"type":"Point"}
}