{
  "type": "Feature",
  "properties": {
    "iso:country":"CH",
    "sg:address":"Tramweg 39",
    "sg:city":"Arth",
    "sg:orig_category":"Wirtschaftspr\u00fcfung, Steuerberatung U Treuhand",
    "sg:phone":"+41 81 833 11 03",
    "sg:postcode":"6415",
    "sg:province":"Schwyz",
    "wof:name":"B + S St. Moritz, Brodmann Peter + Claire",
    "wof:placetype":"venue"
},
  "geometry": {"coordinates":[9.8381910324,46.4970664978],"type":"Point"}
}