{
  "type": "Feature",
  "properties": {
    "iso:country":"CH",
    "sg:address":"Tulpenstrasse 3",
    "sg:city":"D\u00fcbendorf",
    "sg:orig_category":"Arztpraxen",
    "sg:phone":"+41 18203880",
    "sg:postcode":"8600",
    "sg:province":"Z\u00fcrich",
    "wof:name":"Dr.med.danuta St\u00e4heli Spezial\u00e4rztin Fmh",
    "wof:placetype":"venue"
},
  "geometry": {"coordinates":[8.617318,47.398849],"type":"Point"}
}