{
  "type": "Feature",
  "properties": {
    "addr:full":"Chilchweg 11 6073 Fl\u00fceli-ranft. Postfach Fl\u00fceli-ranft Obwalden 6073",
    "addr:housenumber":"11",
    "addr:postcode":"6073;6073",
    "addr:street":"Chilchweg;Postfach",
    "iso:country":"CH",
    "sg:address":"Chilchweg 11 6073 Fl\u00fceli-ranft. Postfach",
    "sg:city":"Fl\u00fceli-ranft",
    "sg:orig_category":"Allgemeiner Hoch U Tiefbau",
    "sg:postcode":"6073",
    "sg:province":"Obwalden",
    "wof:name":"Ress-haas",
    "wof:placetype":"venue"
},
  "geometry": {"coordinates":[8.228328,46.860973],"type":"Point"}
}