{
  "type": "Feature",
  "properties": {
    "iso:country":"CH",
    "sg:address":"Lenggasse 10",
    "sg:city":"Meiringen",
    "sg:orig_category":"Herstellung von Konstruktionsteilen, Fertigbauteilen U Ausbauelementen aus Holz",
    "sg:phone":"+41 33 971 19 07",
    "sg:postcode":"3860",
    "sg:province":"Bern",
    "wof:name":"Jaggi Ag Meiringen",
    "wof:placetype":"venue"
},
  "geometry": {"coordinates":[8.190527916,46.7268333435],"type":"Point"}
}