{
  "type": "Feature",
  "properties": {
    "addr:full":"Stokarbergstrasse 21 Schaffhausen Schaffhausen 8200",
    "addr:housenumber":"21",
    "addr:postcode":"8200",
    "addr:street":"Stokarbergstrasse",
    "iso:country":"CH",
    "sg:address":"Stokarbergstrasse 21",
    "sg:city":"Schaffhausen",
    "sg:classifiers":[
        {
            "category":"Social Services",
            "subcategory":"Retirement Home",
            "type":"Services"
        }
    ],
    "sg:phone":"+41 52 624 78 73",
    "sg:postcode":"8200",
    "sg:province":"Schaffhausen",
    "sg:tags":[
        "pflegeheime",
        "u",
        "alters"
    ],
    "wof:name":"St\u00e4dt.altersheim Steig",
    "wof:placetype":"venue"
},
  "geometry": {"coordinates":[8.62535,47.697891],"type":"Point"}
}