{
  "type": "Feature",
  "properties": {
    "iso:country":"CH",
    "sg:address":"1933",
    "sg:city":"Sembrancher",
    "sg:classifiers":[
        {
            "category":"Travel",
            "subcategory":"Hotels & Motels",
            "type":"Entertainment"
        }
    ],
    "sg:phone":"+41 27 785 21 30",
    "sg:postcode":"1933",
    "sg:province":"Valais",
    "sg:tags":[
        "mit",
        "restaurant"
    ],
    "wof:name":"Motel La Prairie",
    "wof:placetype":"venue"
},
  "geometry": {"coordinates":[7.1504249573,46.0785903931],"type":"Point"}
}