{
  "type": "Feature",
  "properties": {
    "iso:country":"CH",
    "sg:address":"Lerchenfeldstrasse 33",
    "sg:city":"Thun",
    "sg:orig_category":"Sonstige mit Sport verbundene T\u00e4tigkeiten",
    "sg:phone":"+41 33 223 67 50",
    "sg:postcode":"3603",
    "sg:province":"Bern",
    "wof:name":"Messerli + Partner, Tauchtechnik Gmbh",
    "wof:placetype":"venue"
},
  "geometry": {"coordinates":[7.6022558212,46.7653617859],"type":"Point"}
}