{
  "type": "Feature",
  "properties": {
    "iso:country":"CH",
    "sg:address":"T\u00f6sstalstrasse 247 8400 Winterthur. Postfach",
    "sg:city":"Seen",
    "sg:orig_category":"Glaserei",
    "sg:phone":"+41 52 212 05 86",
    "sg:postcode":"8405",
    "sg:province":"Z\u00fcrich",
    "wof:name":"Honegger Glas Ag Reparaturservice",
    "wof:placetype":"venue"
},
  "geometry": {"coordinates":[8.7364253998,47.4962158203],"type":"Point"}
}