{
  "type": "Feature",
  "properties": {
    "iso:country":"CH",
    "sg:address":"Chemin Du Polny 38 B 1066 Epalinges Case Postale 149",
    "sg:city":"Epalinges",
    "sg:orig_category":"Herstellung von Ger\u00e4ten der Elektrizit\u00e4tserzeugung, -verteilung u.\u00e4. -Herstellung von Mess U Kontrol",
    "sg:phone":"+41 55 415 75 75",
    "sg:postcode":"1066",
    "sg:province":"Vaud",
    "wof:name":"Lem Elmes Zweigniederlassung Dor Lem Sa",
    "wof:placetype":"venue"
},
  "geometry": {"coordinates":[8.778427124,47.2024307251],"type":"Point"}
}