{
  "type": "Feature",
  "properties": {
    "iso:country":"CH",
    "sg:address":"Route Cantonale",
    "sg:city":"Etoy",
    "sg:orig_category":"Gem\u00fcsebau Obstbau",
    "sg:phone":"+41 21 807 14 20",
    "sg:postcode":"1163",
    "sg:province":"Vaud",
    "wof:name":"Jean-daniel Collomb Cultures Fruiti\u00e8res",
    "wof:placetype":"venue"
},
  "geometry": {"coordinates":[6.4193058014,46.4849510193],"type":"Point"}
}