{
  "type": "Feature",
  "properties": {
    "iso:country":"CH",
    "sg:address":"Oberwiesenweg 2 8226 Schleitheim. Postfach 133",
    "sg:city":"Schleitheim",
    "sg:orig_category":"Herstellung von Kunststoffwaren Herstellung von Platten, Folien, Schl\u00e4uchen U Profilen aus Kunststof",
    "sg:phone":"+41 52 680 17 21",
    "sg:postcode":"8226",
    "sg:province":"Schaffhausen",
    "wof:name":"Gonon Isolation Ag (sa)",
    "wof:placetype":"venue"
},
  "geometry": {"coordinates":[8.458399,47.748993],"type":"Point"}
}