{
  "type": "Feature",
  "properties": {
    "iso:country":"CH",
    "sg:address":"Badenerstrasse 41 8003 Z\u00fcrich. Postfach",
    "sg:city":"Z\u00fcrich",
    "sg:orig_category":"Sonstiger Grosshandel",
    "sg:postcode":"8004",
    "sg:province":"Z\u00fcrich",
    "wof:name":"Daroma Ag",
    "wof:placetype":"venue"
},
  "geometry": {"coordinates":[8.5186195374,47.3751411438],"type":"Point"}
}