{
  "type": "Feature",
  "properties": {
    "iso:country":"CH",
    "sg:address":"Bachmattstrasse 53",
    "sg:city":"Z\u00fcrich",
    "sg:orig_category":"Erbringung von Dienstleistungen f\u00fcr Unternehmen",
    "sg:postcode":"8048",
    "sg:province":"Z\u00fcrich",
    "wof:name":"Othenin D\u00e9cor S\u00e0rl",
    "wof:placetype":"venue"
},
  "geometry": {"coordinates":[6.5610051155,46.8027954102],"type":"Point"}
}