{
  "type": "Feature",
  "properties": {
    "iso:country":"CH",
    "sg:address":"Rue Du Temple 23",
    "sg:city":"Le Locle",
    "sg:classifiers":[
        {
            "category":"Banks & Credit Unions",
            "subcategory":"Bank",
            "type":"Services"
        }
    ],
    "sg:phone":"+41 39312501",
    "sg:postcode":"2400",
    "sg:province":"Neuch\u00e2tel",
    "wof:name":"Credit Foncier Neuch\u00e2telois",
    "wof:placetype":"venue"
},
  "geometry": {"coordinates":[6.747798,47.057064],"type":"Point"}
}