{
  "type": "Feature",
  "properties": {
    "iso:country":"CH",
    "sg:address":"L\u00e4nggassstrasse 32",
    "sg:city":"Bern",
    "sg:orig_category":"Ackerbau",
    "sg:phone":"+41 31 305 20 50",
    "sg:postcode":"3012",
    "sg:province":"Bern",
    "wof:name":"Ming. Gmbh Projektmanagement Und Beratung",
    "wof:placetype":"venue"
},
  "geometry": {"coordinates":[7.432365,46.95348],"type":"Point"}
}