{
  "type": "Feature",
  "properties": {
    "iso:country":"CH",
    "sg:address":"Nussgasse 4",
    "sg:city":"Z\u00fcrich",
    "sg:orig_category":"Unclassifiable Establishments",
    "sg:postcode":"8008",
    "sg:province":"Z\u00fcrich",
    "wof:name":"Hypercomm Ag",
    "wof:placetype":"venue"
},
  "geometry": {"coordinates":[8.5589122772,47.3525390625],"type":"Point"}
}