{
  "type": "Feature",
  "properties": {
    "iso:country":"CH",
    "sg:address":"Brunngasse 1",
    "sg:city":"B\u00fclach",
    "sg:orig_category":"Detailhandel mit fotografischen Artikeln",
    "sg:phone":"+41 18601517",
    "sg:postcode":"8180",
    "sg:province":"Z\u00fcrich",
    "wof:name":"Foto H\u00e4x Bild Express R.stettler & M.keller",
    "wof:placetype":"venue"
},
  "geometry": {"coordinates":[8.5414733887,47.5176582336],"type":"Point"}
}