{
  "type": "Feature",
  "properties": {
    "iso:country":"CH",
    "sg:address":"Avenue D'a\u00efre 89bis",
    "sg:city":"Gen\u00e8ve",
    "sg:orig_category":"Grafikateliers, Design Siebdruck",
    "sg:phone":"+41 71 755 15 33",
    "sg:postcode":"1203",
    "sg:province":"Gen\u00e8ve",
    "wof:name":"Victor Sasso Reklamen & Farben",
    "wof:placetype":"venue"
},
  "geometry": {"coordinates":[9.5504379272,47.3757743835],"type":"Point"}
}