{
  "type": "Feature",
  "properties": {
    "iso:country":"CH",
    "sg:address":"Piazza Grande 18 6600 Locarno. Postfach",
    "sg:city":"Locarno",
    "sg:orig_category":"Bau\u00e4mter",
    "sg:phone":"+41 91 751 01 51",
    "sg:postcode":"6601",
    "sg:province":"Ticino",
    "wof:name":"Ufficio Delle Costruzioni",
    "wof:placetype":"venue"
},
  "geometry": {"coordinates":[8.795309,46.169659],"type":"Point"}
}