{
  "type": "Feature",
  "properties": {
    "addr:full":"Monbijoustrasse 71 Bern Bern 3007",
    "addr:housenumber":"71",
    "addr:postcode":"3007",
    "addr:street":"Monbijoustrasse",
    "iso:country":"CH",
    "sg:address":"Monbijoustrasse 71",
    "sg:city":"Bern",
    "sg:orig_category":"Detailhandel mit Computern U Software Versandhandel",
    "sg:phone":"+41 31 372 56 20",
    "sg:postcode":"3007",
    "sg:province":"Bern",
    "wof:name":"Media Clever Gmbh Informatik",
    "wof:placetype":"venue"
},
  "geometry": {"coordinates":[7.435977,46.940411],"type":"Point"}
}