{
  "type": "Feature",
  "properties": {
    "iso:country":"CH",
    "sg:address":"Pardiel 3",
    "sg:city":"Untervaz",
    "sg:orig_category":"Finanzierungsinstitutionen",
    "sg:postcode":"7204",
    "sg:province":"Graubunden",
    "wof:name":"Ifi Finance And Investment Ag",
    "wof:placetype":"venue"
},
  "geometry": {"coordinates":[9.536564827,46.9312553406],"type":"Point"}
}