{
  "type": "Feature",
  "properties": {
    "iso:country":"CH",
    "sg:address":"Ca'rustica",
    "sg:city":"Neggio",
    "sg:orig_category":"Unclassifiable Establishments",
    "sg:postcode":"6991",
    "sg:province":"Ticino",
    "wof:name":"R3a Ufficio D'ingeneria",
    "wof:placetype":"venue"
},
  "geometry": {"coordinates":[8.8783597946,45.9906196594],"type":"Point"}
}