{
  "type": "Feature",
  "properties": {
    "iso:country":"CH",
    "sg:address":"Hertensteinstrasse 3",
    "sg:city":"Luzern",
    "sg:orig_category":"Reiseb\u00fcros U Reiseveranstalter Sprachschulen",
    "sg:phone":"+41 55 260 16 80",
    "sg:postcode":"6004",
    "sg:province":"Luzern",
    "wof:name":"Travelling Teacher Tours Glanzmann-wilson Jennifer J.",
    "wof:placetype":"venue"
},
  "geometry": {"coordinates":[8.8587970734,47.2503013611],"type":"Point"}
}