{
  "type": "Feature",
  "properties": {
    "iso:country":"CH",
    "sg:address":"Parvenda Voa 3 7078 Lenzerheide/lai. Postfach",
    "sg:city":"Lenzerheide/lai",
    "sg:orig_category":"Stukkateurgewerbe, Gipserei U Verputzerei",
    "sg:postcode":"7078",
    "sg:province":"Graubunden",
    "wof:name":"Gipsergesch\u00e4ft Hossmann",
    "wof:placetype":"venue"
},
  "geometry": {"coordinates":[9.5543212891,46.7293624878],"type":"Point"}
}