{
  "type": "Feature",
  "properties": {
    "iso:country":"CH",
    "sg:address":"Kornfeldweg 9 5400 Baden. Postfach",
    "sg:city":"Baden",
    "sg:orig_category":"Hardwareberatung",
    "sg:postcode":"5400",
    "sg:province":"Aargau",
    "wof:name":"Digitalpower Tatli T.",
    "wof:placetype":"venue"
},
  "geometry": {"coordinates":[8.2896413803,47.4826965332],"type":"Point"}
}