{
  "type": "Feature",
  "properties": {
    "iso:country":"CH",
    "sg:address":"Gewerbestrasse 5 6330 Cham. Postfach",
    "sg:city":"Cham",
    "sg:orig_category":"Grosshandel mit Getr\u00e4nken",
    "sg:phone":"+41 41 741 33 06",
    "sg:postcode":"6330",
    "sg:province":"Zug",
    "wof:name":"Dufour Lionel Gmbh Qualit\u00e4tsweine, Getr\u00e4nke; Handel, Bes. Auf Dem Wege Des Telemarketings",
    "wof:placetype":"venue"
},
  "geometry": {"coordinates":[8.4734659195,47.1885452271],"type":"Point"}
}