{
  "type": "Feature",
  "properties": {
    "addr:full":"Industriestrasse 64c Arlesheim Basel-Landschaft 4144",
    "addr:housenumber":"64c",
    "addr:postcode":"4144",
    "addr:street":"Industriestrasse",
    "iso:country":"CH",
    "sg:address":"Industriestrasse 64c",
    "sg:city":"Arlesheim",
    "sg:orig_category":"Bauschreinerei Herstellung von Metallkonstruktionen",
    "sg:phone":"+41 61 753 06 80",
    "sg:postcode":"4144",
    "sg:province":"Basel-Landschaft",
    "wof:name":"Vertical Technik Ag Sportger\u00e4te F\u00fcr Skater Usw.; Herstellung, Vermietung, Verkauf",
    "wof:placetype":"venue"
},
  "geometry": {"coordinates":[7.616532,47.507973],"type":"Point"}
}