{
  "type": "Feature",
  "properties": {
    "iso:country":"CH",
    "sg:address":"Obergasse 26",
    "sg:city":"Winterthur",
    "sg:orig_category":"Sonstiger Fachdetailhandel in Verkaufsr\u00e4umen",
    "sg:phone":"+41 52 212 11 76",
    "sg:postcode":"8400",
    "sg:province":"Z\u00fcrich",
    "wof:name":"Boutique Sigi Ruth Fr\u00fch Schmuck & Accessoires",
    "wof:placetype":"venue"
},
  "geometry": {"coordinates":[8.7305278778,47.4992408752],"type":"Point"}
}