{
  "type": "Feature",
  "properties": {
    "iso:country":"CH",
    "sg:address":"Petit-ch\u00eane Rue Du 5 1003 Lausanne Case Postale",
    "sg:city":"Lausanne",
    "sg:orig_category":"Fachdetailhandel in Verkaufsr\u00e4umen",
    "sg:phone":"+41 21 312 72 28",
    "sg:postcode":"1003",
    "sg:province":"Vaud",
    "wof:name":"Darbellay A. Commerce D'horlogerie, Bijouterie, Orf\u00e8vrerie.",
    "wof:placetype":"venue"
},
  "geometry": {"coordinates":[6.6319742203,46.519115448],"type":"Point"}
}