{
  "type": "Feature",
  "properties": {
    "iso:country":"CH",
    "sg:address":"Place De La Gare 1",
    "sg:city":"Nyon",
    "sg:orig_category":"Interessenvertretungen",
    "sg:postcode":"1260",
    "sg:province":"Vaud",
    "wof:name":"Fondation D'entraide Boudhique Internationale (f.e.i.)",
    "wof:placetype":"venue"
},
  "geometry": {"coordinates":[6.2359409332,46.3837890625],"type":"Point"}
}