{
  "type": "Feature",
  "properties": {
    "iso:country":"CH",
    "sg:address":"Austrasse 44 8045 Z\u00fcrich. Postfach",
    "sg:city":"Z\u00fcrich",
    "sg:orig_category":"Pensionskassen",
    "sg:phone":"+41 14656969",
    "sg:postcode":"8036",
    "sg:province":"Z\u00fcrich",
    "wof:name":"Z\u00fcrich Pensionskassen- Beratung Ag",
    "wof:placetype":"venue"
},
  "geometry": {"coordinates":[8.5196733475,47.3647956848],"type":"Point"}
}