{
  "type": "Feature",
  "properties": {
    "addr:full":"Im Schossacher 9 D\u00fcbendorf Z\u00fcrich 8600",
    "addr:housenumber":"9",
    "addr:postcode":"8600",
    "addr:street":"Im Schossacher;Zuerich",
    "iso:country":"CH",
    "sg:address":"Im Schossacher 9",
    "sg:city":"D\u00fcbendorf",
    "sg:orig_category":"Architekturb\u00fcros",
    "sg:phone":"+41 18217755",
    "sg:postcode":"8600",
    "sg:province":"Z\u00fcrich",
    "wof:name":"Gabriel Dal Maso Architekturb\u00fcro",
    "wof:placetype":"venue"
},
  "geometry": {"coordinates":[8.640554,47.394325],"type":"Point"}
}