{
  "type": "Feature",
  "properties": {
    "iso:country":"CH",
    "sg:address":"Rue De Tr\u00e9velin 18 1170 Aubonne. Postfach",
    "sg:city":"Aubonne",
    "sg:orig_category":"Elektroinstallation",
    "sg:phone":"+41 21 808 56 00",
    "sg:postcode":"1170",
    "sg:province":"Vaud",
    "wof:name":"Automation Industrielle, De Wurstemberger Marc",
    "wof:placetype":"venue"
},
  "geometry": {"coordinates":[6.390941143,46.494430542],"type":"Point"}
}