{
  "type": "Feature",
  "properties": {
    "iso:country":"CH",
    "sg:address":"L\u00e4ndtestrasse 47 2503 Biel/bienne Case Postale 394",
    "sg:city":"Biel/bienne",
    "sg:orig_category":"Detailhandel mit Waren verschiedener Art, Hauptrichtung Nahrungsmittel Grosshandel mit Nahrungsmitte",
    "sg:phone":"+41 32 322 83 04",
    "sg:postcode":"2501",
    "sg:province":"Bern",
    "wof:name":"Probst Henri Ag",
    "wof:placetype":"venue"
},
  "geometry": {"coordinates":[7.2389740944,47.131893158],"type":"Point"}
}