{
  "type": "Feature",
  "properties": {
    "iso:country":"CH",
    "sg:address":"Heinrich-wild-strasse",
    "sg:city":"Heerbrugg",
    "sg:orig_category":"Grosshandel mit Foto U Kinoger\u00e4ten, feinmechanischen U optischen Erzeugnissen Herstellung von optisc",
    "sg:phone":"+41 71 727 31 31",
    "sg:postcode":"9435",
    "sg:province":"St. Gallen",
    "wof:name":"Leica Mikrosystems Ag",
    "wof:placetype":"venue"
},
  "geometry": {"coordinates":[9.626955986,47.4117050171],"type":"Point"}
}