{
  "type": "Feature",
  "properties": {
    "addr:full":"Therwilerstrasse 69 Reinach Basel-Landschaft 4153",
    "addr:housenumber":"69",
    "addr:postcode":"4153",
    "addr:street":"Therwilerstrasse",
    "iso:country":"CH",
    "sg:address":"Therwilerstrasse 69",
    "sg:city":"Reinach",
    "sg:classifiers":[
        {
            "category":"Manufacturing",
            "subcategory":"Tools & Machinery",
            "type":"Manufacturing & Wholesale Goods"
        }
    ],
    "sg:phone":"+41 61 711 07 87",
    "sg:postcode":"4153",
    "sg:province":"Basel-Landschaft",
    "sg:tags":[
        "construction",
        "container",
        "apparatus"
    ],
    "wof:name":"B\u00e4rtschi Maschinenbau",
    "wof:placetype":"venue"
},
  "geometry": {"coordinates":[7.576344,47.493881],"type":"Point"}
}