{
  "type": "Feature",
  "properties": {
    "iso:country":"CH",
    "sg:address":"Allmendstrasse 21",
    "sg:city":"Fehraltorf",
    "sg:classifiers":[
        {
            "category":"Wholesale",
            "subcategory":"Chemicals & Plastics",
            "type":"Manufacturing & Wholesale Goods"
        }
    ],
    "sg:phone":"+41 19548030",
    "sg:postcode":"8320",
    "sg:province":"Z\u00fcrich",
    "sg:tags":[
        "cleaning",
        "surface"
    ],
    "wof:name":"Oro Clean Chemie Ag",
    "wof:placetype":"venue"
},
  "geometry": {"coordinates":[8.740418,47.392651],"type":"Point"}
}