{
  "type": "Feature",
  "properties": {
    "iso:country":"CH",
    "sg:address":"Br\u00fcnigstrasse 51",
    "sg:city":"Meiringen",
    "sg:orig_category":"Vereine Frauen Vereine Gemeinn\u00fctzige",
    "sg:postcode":"3860",
    "sg:province":"Bern",
    "wof:name":"Coop Frauenbund Sekt.meiringen",
    "wof:placetype":"venue"
},
  "geometry": {"coordinates":[8.1766195297,46.7317085266],"type":"Point"}
}