{
  "type": "Feature",
  "properties": {
    "iso:country":"CH",
    "sg:address":"Obere Kohlhalden 40",
    "sg:city":"Speicher",
    "sg:orig_category":"Grosshandel mit Getreide, Saatgut U Futtermitteln",
    "sg:phone":"+41 62 875 27 28",
    "sg:postcode":"9042",
    "sg:province":"Appenzell Ausserrhoden",
    "wof:name":"Wiler Trotte",
    "wof:placetype":"venue"
},
  "geometry": {"coordinates":[8.1541252136,47.5600814819],"type":"Point"}
}