{
  "type": "Feature",
  "properties": {
    "iso:country":"CH",
    "sg:address":"Giorgio Via San 7",
    "sg:city":"Coldrerio",
    "sg:orig_category":"Herstellung von elektronischen Bauelementen",
    "sg:phone":"+41 81 413 44 45",
    "sg:postcode":"6877",
    "sg:province":"Ticino",
    "wof:name":"Mega Data Egerer",
    "wof:placetype":"venue"
},
  "geometry": {"coordinates":[9.8209161758,46.7938766479],"type":"Point"}
}