{
  "type": "Feature",
  "properties": {
    "iso:country":"CH",
    "sg:address":"Rennweg 62",
    "sg:city":"Biel/bienne",
    "sg:orig_category":"Non-Classified Establishments",
    "sg:postcode":"2504",
    "sg:province":"Bern",
    "wof:name":"Wood Unlimited Ag",
    "wof:placetype":"venue"
},
  "geometry": {"coordinates":[7.266201973,47.1440238953],"type":"Point"}
}