{
  "type": "Feature",
  "properties": {
    "iso:country":"CH",
    "sg:address":"H\u00e4usern",
    "sg:city":"Toos",
    "sg:orig_category":"Gartenbau",
    "sg:phone":"+41 71 633 29 84",
    "sg:postcode":"8577",
    "sg:province":"Thurgau",
    "wof:name":"Markus Allemann Naturg\u00e4rten",
    "wof:placetype":"venue"
},
  "geometry": {"coordinates":[9.1416034698,47.5152435303],"type":"Point"}
}