{
  "type": "Feature",
  "properties": {
    "iso:country":"CH",
    "sg:address":"Hammerstrasse 42 4000 Basel. Postfach",
    "sg:city":"Basel",
    "sg:orig_category":"Wirtschaftspr\u00fcfung, Steuerberatung U Treuhand",
    "sg:postcode":"4051",
    "sg:province":"Basel-Stadt",
    "wof:name":"Hupfer William B.",
    "wof:placetype":"venue"
},
  "geometry": {"coordinates":[7.5975618362,47.5614624023],"type":"Point"}
}