{
  "type": "Feature",
  "properties": {
    "iso:country":"CH",
    "sg:address":"1716",
    "sg:city":"Plaffeien",
    "sg:orig_category":"Schulpflegen",
    "sg:postcode":"1716",
    "sg:province":"Fribourg",
    "wof:name":"Sekundarschulkommission Der Gemeinde Plaffeien",
    "wof:placetype":"venue"
},
  "geometry": {"coordinates":[7.2868709564,46.7410163879],"type":"Point"}
}