{
  "type": "Feature",
  "properties": {
    "iso:country":"CH",
    "sg:address":"St. Jakobs-strasse 54",
    "sg:city":"Basel",
    "sg:orig_category":"Wirtschaftspr\u00fcfung, Steuerberatung U Treuhand",
    "sg:postcode":"4052",
    "sg:province":"Basel-Stadt",
    "wof:name":"Pit Offices Gmbh",
    "wof:placetype":"venue"
},
  "geometry": {"coordinates":[7.8751392365,47.3442192078],"type":"Point"}
}