{
  "type": "Feature",
  "properties": {
    "iso:country":"CH",
    "sg:address":"Jupiterstrasse 5 3015 Bern. Postfach",
    "sg:city":"Bern",
    "sg:orig_category":"Architektur U Ingenieurb\u00fcros",
    "sg:postcode":"3005",
    "sg:province":"Bern",
    "wof:name":"Planungsb\u00fcro Gallus Pfiffner",
    "wof:placetype":"venue"
},
  "geometry": {"coordinates":[9.468462,47.165565],"type":"Point"}
}