{
  "type": "Feature",
  "properties": {
    "iso:country":"CH",
    "sg:address":"Bois-des-iles Route Du 1",
    "sg:city":"Collex",
    "sg:orig_category":"RESTAURANTS: TEA-ROOMS",
    "sg:phone":"+41 22 774 04 08",
    "sg:postcode":"1239",
    "sg:province":"Gen\u00e8ve",
    "wof:name":"Laurent Feusier",
    "wof:placetype":"venue"
},
  "geometry": {"coordinates":[6.1250801086,46.2722396851],"type":"Point"}
}