{
  "type": "Feature",
  "properties": {
    "iso:country":"CH",
    "sg:address":"Dorfstrasse 3",
    "sg:city":"Oberweningen",
    "sg:orig_category":"Internet Provider Softwareentwicklung U beratung",
    "sg:phone":"+41 19388032",
    "sg:postcode":"8165",
    "sg:province":"Z\u00fcrich",
    "wof:name":"Lognet Ag",
    "wof:placetype":"venue"
},
  "geometry": {"coordinates":[8.8190374374,47.3039855957],"type":"Point"}
}