{
  "type": "Feature",
  "properties": {
    "iso:country":"CH",
    "sg:address":"Florastrasse 22 6014 Littau. Postfach",
    "sg:city":"Littau",
    "sg:orig_category":"Softwareentwicklung U beratung",
    "sg:postcode":"6014",
    "sg:province":"Luzern",
    "wof:name":"Infonda Gmbh",
    "wof:placetype":"venue"
},
  "geometry": {"coordinates":[8.2559404373,47.0562515259],"type":"Point"}
}