{
  "type": "Feature",
  "properties": {
    "iso:country":"CH",
    "sg:address":"Corso Bello 13 6850 Mendrisio. Postfach",
    "sg:city":"Mendrisio",
    "sg:orig_category":"Detailhandel mit Schuhen U Lederwaren Zurichtung U F\u00e4rben von Fellen, Herstellung von Pelzwaren",
    "sg:phone":"+41 91 682 21 94",
    "sg:postcode":"6850",
    "sg:province":"Ticino",
    "wof:name":"Novapel Sa",
    "wof:placetype":"venue"
},
  "geometry": {"coordinates":[9.0158262253,45.8467254639],"type":"Point"}
}