{
  "type": "Feature",
  "properties": {
    "iso:country":"CH",
    "sg:address":"Hinter-sch\u00f6niseistrasse 4",
    "sg:city":"S\u00f6renberg",
    "sg:orig_category":"Personenbef\u00f6rderung im Linienverkehr zu Land",
    "sg:phone":"+41 41 488 12 36",
    "sg:postcode":"6174",
    "sg:province":"Luzern",
    "wof:name":"Bergbahnen S\u00f6renberg Ag",
    "wof:placetype":"venue"
},
  "geometry": {"coordinates":[8.0341415405,46.820854187],"type":"Point"}
}