{
  "type": "Feature",
  "properties": {
    "iso:country":"CH",
    "sg:address":"J.c. Heerstrasse 23 D 8635 D\u00fcrnten. Postfach",
    "sg:city":"D\u00fcrnten",
    "sg:orig_category":"Erbringung von Dienstleistungen f\u00fcr Unternehmen Rechts U Unternehmensberatung, Buchf\u00fchrung",
    "sg:phone":"+41 55 240 46 50",
    "sg:postcode":"8635",
    "sg:province":"Z\u00fcrich",
    "wof:name":"Bewis Scheidegger Betriebswirtschaftliche Dienstleistungen",
    "wof:placetype":"venue"
},
  "geometry": {"coordinates":[8.8741521835,47.2759361267],"type":"Point"}
}