{
  "type": "Feature",
  "properties": {
    "addr:full":"Ch.du Pont-du-centenaire 118 Plan-les-ouates Gen\u00e8ve 1228",
    "addr:housenumber":"118",
    "addr:postcode":"1228",
    "addr:street":"Pont-Du-Centenaire",
    "iso:country":"CH",
    "sg:address":"Ch.du Pont-du-centenaire 118",
    "sg:city":"Plan-les-ouates",
    "sg:orig_category":"Herstellung von elektrischen Lampen U Leuchten Sonstige Bauinstallation",
    "sg:phone":"+41 22 794 21 27",
    "sg:postcode":"1228",
    "sg:province":"Gen\u00e8ve",
    "wof:name":"Arco N\u00e9on Color Sa",
    "wof:placetype":"venue"
},
  "geometry": {"coordinates":[6.109141,46.16888],"type":"Point"}
}