{
  "type": "Feature",
  "properties": {
    "iso:country":"CH",
    "sg:address":"G\u00e4uggelistrasse 7",
    "sg:city":"Chur",
    "sg:classifiers":[
        {
            "category":"Professional",
            "subcategory":"Printing & Photocopies",
            "type":"Services"
        }
    ],
    "sg:phone":"+41 81 250 11 55",
    "sg:postcode":"7000",
    "sg:province":"Graubunden",
    "sg:tags":[
        "embroidery"
    ],
    "wof:name":"Print Box Ag",
    "wof:placetype":"venue"
},
  "geometry": {"coordinates":[9.5303459167,46.8508644104],"type":"Point"}
}