{
  "type": "Feature",
  "properties": {
    "iso:country":"CH",
    "sg:address":"Rathausgasse 50 3011 Bern. Postfach",
    "sg:city":"Bern",
    "sg:orig_category":"RESTAURANTS: TEA-ROOMS",
    "sg:phone":"+41 56 441 13 54",
    "sg:postcode":"3005",
    "sg:province":"Bern",
    "wof:name":"Steig Gastro Gmbh",
    "wof:placetype":"venue"
},
  "geometry": {"coordinates":[8.2113628387,47.4622650146],"type":"Point"}
}