{
  "type": "Feature",
  "properties": {
    "iso:country":"CH",
    "sg:address":"Rue Du L\u00e9man 13",
    "sg:city":"Martigny",
    "sg:orig_category":"Kosmetikinstitute",
    "sg:phone":"+41 27 722 58 79",
    "sg:postcode":"1920",
    "sg:province":"Valais",
    "wof:name":"Daisy Vicino Institut De Beaut\u00e9 Silhouette",
    "wof:placetype":"venue"
},
  "geometry": {"coordinates":[7.0764951706,46.1043739319],"type":"Point"}
}