{
  "type": "Feature",
  "properties": {
    "iso:country":"CH",
    "sg:address":"S\u00e4gereistrasse 17",
    "sg:city":"Glattbrugg",
    "sg:orig_category":"Grosshandel mit medizinischen U orthop\u00e4dischen Artikeln Herstellung von medizinischen U chirurgische",
    "sg:phone":"+41 18295060",
    "sg:postcode":"8152",
    "sg:province":"Z\u00fcrich",
    "wof:name":"Novadent Ag",
    "wof:placetype":"venue"
},
  "geometry": {"coordinates":[8.5599718094,47.4311218262],"type":"Point"}
}