{
  "type": "Feature",
  "properties": {
    "iso:country":"CH",
    "sg:address":"Sonnhaldenstrasse 30",
    "sg:city":"H\u00fcnenberg",
    "sg:orig_category":"Softwareentwicklung U beratung",
    "sg:phone":"+41 41 781 50 10",
    "sg:postcode":"6331",
    "sg:province":"Zug",
    "wof:name":"Flexcom Ag",
    "wof:placetype":"venue"
},
  "geometry": {"coordinates":[8.4241437912,47.1772994995],"type":"Point"}
}