{
  "type": "Feature",
  "properties": {
    "iso:country":"CH",
    "sg:address":"7203",
    "sg:city":"Trimmis",
    "sg:orig_category":"Sportvereine Sch\u00fctzen",
    "sg:phone":"+41 62 293 52 29",
    "sg:postcode":"7203",
    "sg:province":"Graubunden",
    "wof:name":"Feldsch\u00fctzengesellschaft",
    "wof:placetype":"venue"
},
  "geometry": {"coordinates":[9.5628290176,46.8994636536],"type":"Point"}
}