{
  "type": "Feature",
  "properties": {
    "iso:country":"CH",
    "sg:address":"Untertalweg 32 Pf 360",
    "sg:city":"Arlesheim",
    "sg:classifiers":[
        {
            "category":"Professional",
            "subcategory":"Engineering",
            "type":"Services"
        }
    ],
    "sg:phone":"+41 61 706 33 33",
    "sg:postcode":"4144",
    "sg:province":"Basel-Landschaft",
    "sg:tags":[
        "electricity",
        "energy",
        "material",
        "-",
        "machine",
        "raw",
        "mechanical"
    ],
    "wof:name":"Gasverbund Mittelland Ag",
    "wof:placetype":"venue"
},
  "geometry": {"coordinates":[7.6206297874,47.4940643311],"type":"Point"}
}