{
  "type": "Feature",
  "properties": {
    "iso:country":"CH",
    "sg:address":"J\u00e4gerweg 12",
    "sg:city":"Bern",
    "sg:orig_category":"Satzherstellung U Reproduktion",
    "sg:phone":"+41 31 348 07 22",
    "sg:postcode":"3014",
    "sg:province":"Bern",
    "wof:name":"Make Up Typografie Schneider Herbert Typografisches Atelier, Satz U Belichtung I Bereich Desktop-publishing",
    "wof:placetype":"venue"
},
  "geometry": {"coordinates":[7.4516849518,46.9579353333],"type":"Point"}
}