{
  "type": "Feature",
  "properties": {
    "iso:country":"CH",
    "sg:address":"Rietstrasse 90",
    "sg:city":"Schaffhausen",
    "sg:orig_category":"Vermietung U Verpachtung von eigenen Immobilien",
    "sg:phone":"+41 52 624 77 33",
    "sg:postcode":"8200",
    "sg:province":"Schaffhausen",
    "wof:name":"Erlenpark Ag",
    "wof:placetype":"venue"
},
  "geometry": {"coordinates":[8.6182947159,47.7025337219],"type":"Point"}
}