{
  "type": "Feature",
  "properties": {
    "iso:country":"CH",
    "sg:address":"K\u00fcngoltstrasse 14 4500 Solothurn. Postfach",
    "sg:city":"Solothurn",
    "sg:orig_category":"Grosshandel mit Maschinen U Ausr\u00fcstungen",
    "sg:phone":"+41 32 623 63 63",
    "sg:postcode":"4503",
    "sg:province":"Solothurn",
    "wof:name":"Gebr\u00fcder Schaerer Chem.reinigungs-einrichtungen",
    "wof:placetype":"venue"
},
  "geometry": {"coordinates":[7.5251250267,47.2104072571],"type":"Point"}
}