{
  "type": "Feature",
  "properties": {
    "iso:country":"CH",
    "sg:address":"Vordere Vorstadt 14",
    "sg:city":"Aarau",
    "sg:orig_category":"Detailhandel mit Spielwaren Fachdetailhandel in Verkaufsr\u00e4umen",
    "sg:phone":"+41 62 822 03 02",
    "sg:postcode":"5000",
    "sg:province":"Aargau",
    "wof:name":"Spielstatt Gmbh",
    "wof:placetype":"venue"
},
  "geometry": {"coordinates":[8.0447177887,47.390953064],"type":"Point"}
}