{
  "type": "Feature",
  "properties": {
    "iso:country":"CH",
    "sg:address":"Friedmattstrasse 7",
    "sg:city":"Reiden",
    "sg:orig_category":"Unclassifiable Establishments",
    "sg:phone":"+41 62 749 05 02",
    "sg:postcode":"6260",
    "sg:province":"Luzern",
    "wof:name":"Cariv Ag",
    "wof:placetype":"venue"
},
  "geometry": {"coordinates":[7.9689598083,47.2429008484],"type":"Point"}
}