{
  "type": "Feature",
  "properties": {
    "iso:country":"CH",
    "sg:address":"Route Ferney 169",
    "sg:city":"Gen\u00e8ve",
    "sg:classifiers":[
        {
            "category":"Banks & Credit Unions",
            "subcategory":"Bank",
            "type":"Services"
        }
    ],
    "sg:phone":"+41 22987727",
    "sg:postcode":"1202",
    "sg:province":"Gen\u00e8ve",
    "wof:name":"Banque Hypoth\u00e9caire, Du Canton De Geneve",
    "wof:placetype":"venue"
},
  "geometry": {"coordinates":[6.133698,46.224297],"type":"Point"}
}