{
  "type": "Feature",
  "properties": {
    "iso:country":"CH",
    "sg:address":"Haldenstrasse 21",
    "sg:city":"Stilli",
    "sg:orig_category":"Gem\u00fcsebau",
    "sg:phone":"+41 56 284 14 79",
    "sg:postcode":"5233",
    "sg:province":"Aargau",
    "wof:name":"Alois Sidler Gem\u00fcsebau",
    "wof:placetype":"venue"
},
  "geometry": {"coordinates":[8.2306232452,47.5167350769],"type":"Point"}
}