{
  "type": "Feature",
  "properties": {
    "iso:country":"CH",
    "sg:address":"Via Municipio 2",
    "sg:city":"Muralto",
    "sg:orig_category":"Primarschulen",
    "sg:postcode":"6600",
    "sg:province":"Ticino",
    "wof:name":"Scuola Elementare",
    "wof:placetype":"venue"
},
  "geometry": {"coordinates":[8.9410152435,46.0101051331],"type":"Point"}
}