{
  "type": "Feature",
  "properties": {
    "iso:country":"CH",
    "sg:address":"Route De Begnins 13",
    "sg:city":"Gland",
    "sg:orig_category":"Nationale Postdienste",
    "sg:phone":"+41 22 364 10 50",
    "sg:postcode":"1196",
    "sg:province":"Vaud",
    "wof:name":"La Poste Suisse",
    "wof:placetype":"venue"
},
  "geometry": {"coordinates":[6.2661690712,46.4203033447],"type":"Point"}
}