{
  "type": "Feature",
  "properties": {
    "iso:country":"CH",
    "sg:address":"Neum\u00fchlestrasse 1",
    "sg:city":"Amriswil",
    "sg:orig_category":"Malerei",
    "sg:phone":"+41 71 411 58 85",
    "sg:postcode":"8580",
    "sg:province":"Thurgau",
    "wof:name":"Helmut Giselbrecht Malergesch\u00e4ft",
    "wof:placetype":"venue"
},
  "geometry": {"coordinates":[9.2947778702,47.5508728027],"type":"Point"}
}