{
  "type": "Feature",
  "properties": {
    "iso:country":"CH",
    "sg:address":"Bahnhofstrasse 3945 Gampel. Postfach 119",
    "sg:city":"Gampel",
    "sg:orig_category":"Unclassifiable Establishments",
    "sg:phone":"+41 27 932 39 39",
    "sg:postcode":"3945",
    "sg:province":"Valais",
    "wof:name":"Kw Mittal Ag",
    "wof:placetype":"venue"
},
  "geometry": {"coordinates":[7.7447009087,46.3143196106],"type":"Point"}
}