{
  "type": "Feature",
  "properties": {
    "iso:country":"CH",
    "sg:address":"Landshutstrasse 13",
    "sg:city":"B\u00e4tterkinden",
    "sg:orig_category":"Detailhandel mit Damenbekleidung Herstellung von W\u00e4sche",
    "sg:phone":"+41 32 665 20 55",
    "sg:postcode":"3315",
    "sg:province":"Bern",
    "wof:name":"Boutique Buba Heidi Aebi",
    "wof:placetype":"venue"
},
  "geometry": {"coordinates":[7.541408062,47.1310157776],"type":"Point"}
}