{
  "type": "Feature",
  "properties": {
    "iso:country":"CH",
    "sg:address":"Bahnhofstrasse 17",
    "sg:city":"Aarau",
    "sg:orig_category":"RESTAURANTS: TEA-ROOMS",
    "sg:postcode":"5000",
    "sg:province":"Aargau",
    "wof:name":"Hot - Dog Aarau P. Amsler",
    "wof:placetype":"venue"
},
  "geometry": {"coordinates":[8.0462913513,47.3909645081],"type":"Point"}
}