{
  "type": "Feature",
  "properties": {
    "iso:country":"CH",
    "sg:address":"6930",
    "sg:city":"Bedano",
    "sg:classifiers":[
        {
            "category":"Travel",
            "subcategory":"Hotels & Motels",
            "type":"Entertainment"
        }
    ],
    "sg:phone":"+41 91 945 03 33",
    "sg:postcode":"6930",
    "sg:province":"Ticino",
    "sg:tags":[
        "hotels",
        "mit",
        "restaurant"
    ],
    "wof:name":"Albergo Osteria Carletti",
    "wof:placetype":"venue"
},
  "geometry": {"coordinates":[8.917090416,46.0536994934],"type":"Point"}
}