{
  "type": "Feature",
  "properties": {
    "iso:country":"CH",
    "sg:address":"Mattenweg 3a",
    "sg:city":"Schattdorf",
    "sg:orig_category":"Grosshandel mit Schmuck Grosshandel mit Uhren",
    "sg:phone":"+41 41 870 00 92",
    "sg:postcode":"6467",
    "sg:province":"Uri",
    "wof:name":"Kesef Ag Uhren/schmuck-export &-import",
    "wof:placetype":"venue"
},
  "geometry": {"coordinates":[8.6548938751,46.8667907715],"type":"Point"}
}