{
  "type": "Feature",
  "properties": {
    "iso:country":"CH",
    "sg:address":"Centre Commercial 1274 Signy. Postfach",
    "sg:city":"Grens",
    "sg:orig_category":"Detailhandel mit elektrischen Haushalts-,Radio U Fernsehger\u00e4ten sowie Musikinstrumenten",
    "sg:postcode":"1274",
    "sg:province":"Vaud",
    "wof:name":"Master Market Techno Frigo S\u00e0rl",
    "wof:placetype":"venue"
},
  "geometry": {"coordinates":[6.1920938492,46.3949508667],"type":"Point"}
}