{
  "type": "Feature",
  "properties": {
    "iso:country":"CH",
    "sg:address":"Feldbergstrasse 30",
    "sg:city":"Basel",
    "sg:orig_category":"Fahrschulen, Flugschulen",
    "sg:phone":"+41 79 322 26 32",
    "sg:postcode":"4057",
    "sg:province":"Basel-Stadt",
    "wof:name":"Easy Drive Fahrschule, Bischofberger + Blaser",
    "wof:placetype":"venue"
},
  "geometry": {"coordinates":[7.5897932053,47.5659255981],"type":"Point"}
}