{
  "type": "Feature",
  "properties": {
    "addr:full":"Avenue Du 14 Avril 1b Renens Vaud 1020",
    "addr:housenumber":"1b",
    "addr:postcode":"1020",
    "addr:street":"Avenue Du 14 Avril",
    "iso:country":"CH",
    "sg:address":"Avenue Du 14 Avril 1b",
    "sg:city":"Renens",
    "sg:classifiers":[
        {
            "category":"Professional",
            "subcategory":"Art Services",
            "type":"Services"
        }
    ],
    "sg:phone":"+41 21 671 05 85",
    "sg:postcode":"1020",
    "sg:province":"Vaud",
    "sg:tags":[
        "concept",
        "design"
    ],
    "wof:name":"Almag Concept S.a.",
    "wof:placetype":"venue"
},
  "geometry": {"coordinates":[6.579761,46.53952],"type":"Point"}
}