{
  "type": "Feature",
  "properties": {
    "addr:full":"Route De Lausanne 39 Grandson Vaud 1422",
    "addr:housenumber":"39",
    "addr:postcode":"1422",
    "addr:street":"Route De Lausanne",
    "iso:country":"CH",
    "sg:address":"Route De Lausanne 39",
    "sg:city":"Grandson",
    "sg:orig_category":"Autogaragen Einzelhandel mit Automobilen",
    "sg:phone":"+41 24 445 25 33",
    "sg:postcode":"1422",
    "sg:province":"Vaud",
    "wof:name":"Canv S.a. Garage, Agence Subaru",
    "wof:placetype":"venue"
},
  "geometry": {"coordinates":[6.628105,46.798061],"type":"Point"}
}