{
  "type": "Feature",
  "properties": {
    "iso:country":"CH",
    "sg:address":"Rotwandstrasse 64",
    "sg:city":"Z\u00fcrich",
    "sg:orig_category":"Detailhandel mit Ton U Bildtr\u00e4gern",
    "sg:phone":"+41 12914660",
    "sg:postcode":"8004",
    "sg:province":"Z\u00fcrich",
    "wof:name":"Recrec Laden Cd & Vinyl",
    "wof:placetype":"venue"
},
  "geometry": {"coordinates":[8.5294065475,47.3757667542],"type":"Point"}
}