{
  "type": "Feature",
  "properties": {
    "iso:country":"CH",
    "sg:address":"Rinkenbach 41 9050 Appenzell. Postfach",
    "sg:city":"Appenzell",
    "sg:orig_category":"Oberfl\u00e4chenveredlung U W\u00e4rmebehandlung",
    "sg:postcode":"9050",
    "sg:province":"Appenzell Innerhoden",
    "wof:name":"Ignacio S\u00e0rl",
    "wof:placetype":"venue"
},
  "geometry": {"coordinates":[6.9041571617,47.1766586304],"type":"Point"}
}