{
  "type": "Feature",
  "properties": {
    "iso:country":"CH",
    "sg:address":"Boulevard Carl-vogt 82",
    "sg:city":"Gen\u00e8ve",
    "sg:orig_category":"Abbruch U Sprenggewerbe Erdbewegungsarbeiten",
    "sg:phone":"+41 22 328 13 07",
    "sg:postcode":"1205",
    "sg:province":"Gen\u00e8ve",
    "wof:name":"Antonio Puopolo Transports & Terrassements",
    "wof:placetype":"venue"
},
  "geometry": {"coordinates":[6.138853,46.196301],"type":"Point"}
}