{
  "type": "Feature",
  "properties": {
    "iso:country":"CH",
    "sg:address":"Ruchlistrasse 15 6312 Steinhausen. Postfach",
    "sg:city":"Steinhausen",
    "sg:orig_category":"Architektur U Ingenieurb\u00fcros",
    "sg:phone":"+41 41 740 41 72",
    "sg:postcode":"6312",
    "sg:province":"Zug",
    "wof:name":"Jans Adrian Haus-technik Gmbh Bauorganisation. Bautechnische Arbeiten; Beratung, Ausf\u00fchrung",
    "wof:placetype":"venue"
},
  "geometry": {"coordinates":[8.483401,47.201389],"type":"Point"}
}