{
  "type": "Feature",
  "properties": {
    "iso:country":"CH",
    "sg:address":"Sonnenstrasse 7",
    "sg:city":"Brig",
    "sg:orig_category":"Kinos",
    "sg:phone":"+41 27 923 16 58",
    "sg:postcode":"3900",
    "sg:province":"Valais",
    "wof:name":"Kino Capitol",
    "wof:placetype":"venue"
},
  "geometry": {"coordinates":[7.9868879318,46.3177947998],"type":"Point"}
}