{
  "type": "Feature",
  "properties": {
    "iso:country":"CH",
    "sg:address":"Im Fennen 11",
    "sg:city":"Niederurnen",
    "sg:orig_category":"RESTAURANTS: TEA-ROOMS",
    "sg:phone":"+41 55 610 30 80",
    "sg:postcode":"8867",
    "sg:province":"Glarus",
    "wof:name":"Walkatt Gmbh",
    "wof:placetype":"venue"
},
  "geometry": {"coordinates":[9.0414676666,47.1348152161],"type":"Point"}
}