{
  "type": "Feature",
  "properties": {
    "iso:country":"CH",
    "sg:address":"Im Biel",
    "sg:city":"Brig",
    "sg:orig_category":"W\u00e4scherei U chemische Reinigung",
    "sg:phone":"+41 79 628 02 42",
    "sg:postcode":"3900",
    "sg:province":"Valais",
    "wof:name":"Tex-clean Partner Gmbh",
    "wof:placetype":"venue"
},
  "geometry": {"coordinates":[7.9876461029,46.3158912659],"type":"Point"}
}