{
  "type": "Feature",
  "properties": {
    "iso:country":"CH",
    "sg:address":"Morgartenstrasse 18 6315 Ober\u00e4geri. Postfach",
    "sg:city":"Ober\u00e4geri",
    "sg:orig_category":"Verwaltung von Immobilien",
    "sg:postcode":"6315",
    "sg:province":"Zug",
    "wof:name":"Nussbaumer Immobilien Ag Immobilien Usw",
    "wof:placetype":"venue"
},
  "geometry": {"coordinates":[8.6178188324,47.1336593628],"type":"Point"}
}