{
  "type": "Feature",
  "properties": {
    "iso:country":"CH",
    "sg:address":"Wassergasse 14",
    "sg:city":"Rheinfelden",
    "sg:orig_category":"Herstellung von Schmuck, Gold U Silberschmiedwaren",
    "sg:phone":"+41 61 831 32 12",
    "sg:postcode":"4310",
    "sg:province":"Aargau",
    "wof:name":"Regula Stindt-niederberger Rahmenatelier Die Vergolderei",
    "wof:placetype":"venue"
},
  "geometry": {"coordinates":[7.7944221497,47.5537986755],"type":"Point"}
}