{
  "type": "Feature",
  "properties": {
    "iso:country":"CH",
    "sg:address":"Avenue Des Alpes 27bis",
    "sg:city":"Montreux",
    "sg:orig_category":"Innendekorationsateliers",
    "sg:phone":"+41 21 963 62 05",
    "sg:postcode":"1820",
    "sg:province":"Vaud",
    "wof:name":"Jean-pierre Cavallini Ensemblier-d\u00e9corateur",
    "wof:placetype":"venue"
},
  "geometry": {"coordinates":[6.9106287956,46.4341583252],"type":"Point"}
}