{
  "type": "Feature",
  "properties": {
    "iso:country":"CH",
    "sg:address":"Rue Des Grands-pr\u00e9s 2",
    "sg:city":"Bassecourt",
    "sg:classifiers":[
        {
            "category":"Government",
            "subcategory":"Post Office",
            "type":"Public Place"
        }
    ],
    "sg:phone":"+41 32 426 50 81",
    "sg:postcode":"2854",
    "sg:province":"Jura",
    "sg:tags":[
        "caf\u00e9s",
        "tea-rooms"
    ],
    "wof:name":"Bar \u00e0 Caf\u00e9 Le Cristal",
    "wof:placetype":"venue"
},
  "geometry": {"coordinates":[7.2423100471,47.3389892578],"type":"Point"}
}