{
  "type": "Feature",
  "properties": {
    "iso:country":"CH",
    "sg:address":"Socinstrasse 31",
    "sg:city":"Basel",
    "sg:orig_category":"Gesundheitswesen",
    "sg:phone":"+41 79 667 41 13",
    "sg:postcode":"4051",
    "sg:province":"Basel-Stadt",
    "wof:name":"Stern Consult",
    "wof:placetype":"venue"
},
  "geometry": {"coordinates":[7.5788888931,47.5569992065],"type":"Point"}
}