{
  "type": "Feature",
  "properties": {
    "iso:country":"CH",
    "sg:address":"Hinteregg",
    "sg:city":"Romoos",
    "sg:orig_category":"Detailhandel mit Milcherzeugnissen U Eiern Verwertung von Milch",
    "sg:phone":"+41 41 480 13 83",
    "sg:postcode":"6113",
    "sg:province":"Luzern",
    "wof:name":"Lorenz + Muri Pia Ag",
    "wof:placetype":"venue"
},
  "geometry": {"coordinates":[8.030380249,47.024597168],"type":"Point"}
}