{
  "type": "Feature",
  "properties": {
    "addr:full":"Galeries B.-constant 1 Lausanne Vaud 1003",
    "addr:housenumber":"1",
    "addr:postcode":"1003",
    "iso:country":"CH",
    "sg:address":"Galeries B.-constant 1",
    "sg:city":"Lausanne",
    "sg:classifiers":[
        {
            "category":"Bars & Pubs",
            "type":"Food & Drink"
        }
    ],
    "sg:phone":"+41 21 944 38 28",
    "sg:postcode":"1003",
    "sg:province":"Vaud",
    "sg:tags":[
        "restaurant"
    ],
    "wof:name":"Restaurant & Bar L' Etrier",
    "wof:placetype":"venue"
},
  "geometry": {"coordinates":[6.858897,46.455063],"type":"Point"}
}