{
  "type": "Feature",
  "properties": {
    "iso:country":"CH",
    "sg:address":"Route De Cossonay 78 1008 Prilly. Postfach",
    "sg:city":"Prilly",
    "sg:orig_category":"Elektroinstallation",
    "sg:phone":"+41 21 634 58 12",
    "sg:postcode":"1008",
    "sg:province":"Vaud",
    "wof:name":"Electro Services Partners S\u00e0rl Prestation De Services Dans Les Domaines De L'\u00e9lectricit\u00e9, Des T\u00e9l\u00e9communications Etc",
    "wof:placetype":"venue"
},
  "geometry": {"coordinates":[6.6003937721,46.5381546021],"type":"Point"}
}