{
  "type": "Feature",
  "properties": {
    "iso:country":"CH",
    "sg:address":"Route Du Levant 6",
    "sg:city":"Fribourg",
    "sg:orig_category":"Non-Classified Establishments",
    "sg:postcode":"1700",
    "sg:province":"Fribourg",
    "wof:name":"Warning Discoth\u00e8que, Magnin Christophe",
    "wof:placetype":"venue"
},
  "geometry": {"coordinates":[7.1414690018,46.7972106934],"type":"Point"}
}