{
  "type": "Feature",
  "properties": {
    "iso:country":"CH",
    "sg:address":"Spycherweg 5",
    "sg:city":"Maisprach",
    "sg:orig_category":"Werbegrafikateliers",
    "sg:phone":"+41 61 841 22 48",
    "sg:postcode":"4464",
    "sg:province":"Basel-Landschaft",
    "wof:name":"Christian L\u00fcscher Grafik",
    "wof:placetype":"venue"
},
  "geometry": {"coordinates":[7.848074913,47.5246734619],"type":"Point"}
}