{
  "type": "Feature",
  "properties": {
    "iso:country":"CH",
    "sg:address":"Meisenstrasse 8a",
    "sg:city":"Niederuzwil",
    "sg:orig_category":"Politische Parteien CVP",
    "sg:phone":"+41 71 393 16 09",
    "sg:postcode":"9244",
    "sg:province":"St. Gallen",
    "wof:name":"Cvp Ortspartei Niederwil",
    "wof:placetype":"venue"
},
  "geometry": {"coordinates":[9.2117004395,47.4424667358],"type":"Point"}
}