{
  "type": "Feature",
  "properties": {
    "iso:country":"CH",
    "sg:address":"Dorf 23 9107 Urn\u00e4sch. Postfach 30",
    "sg:city":"Urn\u00e4sch",
    "sg:orig_category":"Sportvereine Ski",
    "sg:phone":"+41 71 229 39 29",
    "sg:postcode":"9107",
    "sg:province":"Appenzell Ausserrhoden",
    "wof:name":"Skiclub Urn\u00e4sch B\u00f6mm.s\u00e4ntis",
    "wof:placetype":"venue"
},
  "geometry": {"coordinates":[9.2841997147,47.3178596497],"type":"Point"}
}