{
  "type": "Feature",
  "properties": {
    "iso:country":"CH",
    "sg:address":"Grand-rue 12",
    "sg:city":"Tavannes",
    "sg:orig_category":"Vermietung U Verpachtung von eigenen Immobilien",
    "sg:postcode":"2710",
    "sg:province":"Bern",
    "wof:name":"Cab Consultim S\u00e0rl",
    "wof:placetype":"venue"
},
  "geometry": {"coordinates":[7.2002749443,47.2200775146],"type":"Point"}
}