{
  "type": "Feature",
  "properties": {
    "addr:full":"Avenue De La Gare 17 Sion Valais 1950",
    "addr:housenumber":"17",
    "addr:postcode":"1950",
    "addr:street":"Avenue De La Gare",
    "iso:country":"CH",
    "sg:address":"Avenue De La Gare 17",
    "sg:city":"Sion",
    "sg:orig_category":"Arztpraxen",
    "sg:phone":"+41 27 323 45 45",
    "sg:postcode":"1950",
    "sg:province":"Valais",
    "wof:name":"Dr M\u00e9d. Bernard Bonvin M\u00e9decin Sp\u00e9cialiste Fmh",
    "wof:placetype":"venue"
},
  "geometry": {"coordinates":[7.358313,46.229652],"type":"Point"}
}