{
  "type": "Feature",
  "properties": {
    "addr:full":"Gaswerkstrasse 66a Langenthal Bern 4900",
    "addr:housenumber":"66a",
    "addr:postcode":"4900",
    "addr:street":"Gaswerkstrasse;Bern",
    "iso:country":"CH",
    "sg:address":"Gaswerkstrasse 66a",
    "sg:city":"Langenthal",
    "sg:orig_category":"Bauspenglerei Zimmerei, Dachdeckerei, Bauspenglerei U Abdichtung",
    "sg:phone":"+41 62 922 11 77",
    "sg:postcode":"4900",
    "sg:province":"Bern",
    "wof:name":"S\u00e4gesser + Oberli Ag",
    "wof:placetype":"venue"
},
  "geometry": {"coordinates":[7.790539,47.229439],"type":"Point"}
}