{
  "type": "Feature",
  "properties": {
    "iso:country":"CH",
    "sg:address":"1986",
    "sg:city":"Arolla",
    "sg:orig_category":"Betrieb von Taxis",
    "sg:phone":"+41 27 283 11 65",
    "sg:postcode":"1986",
    "sg:province":"Valais",
    "wof:name":"Denis Anz\u00e9vui Taxis",
    "wof:placetype":"venue"
},
  "geometry": {"coordinates":[7.48768,46.038712],"type":"Point"}
}