{
  "type": "Feature",
  "properties": {
    "iso:country":"CH",
    "sg:address":"Rue De La Berg\u00e8re 26 1242 Satigny Case Postale 10",
    "sg:city":"Satigny",
    "sg:orig_category":"Herstellung von sonstigen landwirtschaftlichen Maschinen",
    "sg:phone":"+41 21 906 95 09",
    "sg:postcode":"1242",
    "sg:province":"Gen\u00e8ve",
    "wof:name":"Gr\u00fcter Monika Maschinen Waagen Landw. Artikel.",
    "wof:placetype":"venue"
},
  "geometry": {"coordinates":[8.3012399673,47.1279983521],"type":"Point"}
}