{
  "type": "Feature",
  "properties": {
    "iso:country":"CH",
    "sg:address":"Ibelweg 24 6300 Zug. Postfach",
    "sg:city":"Zug",
    "sg:orig_category":"Stukkateurgewerbe, Gipserei U Verputzerei",
    "sg:postcode":"6300",
    "sg:province":"Zug",
    "wof:name":"Wyss Marcel Gipsergesch\u00e4ft",
    "wof:placetype":"venue"
},
  "geometry": {"coordinates":[8.5254011154,47.1822319031],"type":"Point"}
}