{
  "type": "Feature",
  "properties": {
    "iso:country":"CH",
    "sg:address":"Horiastrasse 18",
    "sg:city":"D\u00fcdingen",
    "sg:orig_category":"Sportvereine Ballsport Squash",
    "sg:phone":"+41 26 493 18 07",
    "sg:postcode":"3186",
    "sg:province":"Fribourg",
    "wof:name":"Squash Club Sense",
    "wof:placetype":"venue"
},
  "geometry": {"coordinates":[7.1926188469,46.8431739807],"type":"Point"}
}