{
  "type": "Feature",
  "properties": {
    "iso:country":"CH",
    "sg:address":"Florastrasse 9",
    "sg:city":"Uzwil",
    "sg:orig_category":"Sanit\u00e4r, Heizungs U L\u00fcftungsinstallation",
    "sg:phone":"+41 71 951 34 45",
    "sg:postcode":"9240",
    "sg:province":"St. Gallen",
    "wof:name":"Nuster Heizungen Ag, Uzwil",
    "wof:placetype":"venue"
},
  "geometry": {"coordinates":[9.1365976334,47.4361152649],"type":"Point"}
}