{
  "type": "Feature",
  "properties": {
    "iso:country":"CH",
    "sg:address":"Wilhof 155b",
    "sg:city":"Birrwil",
    "sg:orig_category":"Organisationen des Gesundheitswesen",
    "sg:phone":"+41 62 772 11 79",
    "sg:postcode":"5708",
    "sg:province":"Aargau",
    "wof:name":"Samariterverein",
    "wof:placetype":"venue"
},
  "geometry": {"coordinates":[8.1992673874,47.2858467102],"type":"Point"}
}