{
  "type": "Feature",
  "properties": {
    "iso:country":"CH",
    "sg:address":"Route De Salavaux",
    "sg:city":"Faoug",
    "sg:orig_category":"Bauschreinerei Einbau von Schreinerwaren",
    "sg:phone":"+41 71 983 54 66",
    "sg:postcode":"1595",
    "sg:province":"Bern",
    "wof:name":"Hans & Roland Scherrer Ag Schreinerei & K\u00fcchenbau",
    "wof:placetype":"venue"
},
  "geometry": {"coordinates":[9.06551,47.380821],"type":"Point"}
}