{
  "type": "Feature",
  "properties": {
    "iso:country":"CH",
    "sg:address":"Dorfstrasse",
    "sg:city":"Nufenen",
    "sg:orig_category":"Primarschulen",
    "sg:postcode":"7437",
    "sg:province":"Graubunden",
    "wof:name":"Primarschule",
    "wof:placetype":"venue"
},
  "geometry": {"coordinates":[9.2413291931,46.539768219],"type":"Point"}
}