{
  "type": "Feature",
  "properties": {
    "iso:country":"CH",
    "sg:address":"Harnischgasse",
    "sg:city":"Sursee",
    "sg:orig_category":"Interessenvertretungen",
    "sg:phone":"+41 41 921 94 62",
    "sg:postcode":"6210",
    "sg:province":"Luzern",
    "wof:name":"Stiftung Somehuus Sursee",
    "wof:placetype":"venue"
},
  "geometry": {"coordinates":[8.1100349426,47.1721038818],"type":"Point"}
}