{
  "type": "Feature",
  "properties": {
    "iso:country":"CH",
    "sg:address":"Vordere Vorstadt 17",
    "sg:city":"Aarau",
    "sg:orig_category":"RESTAURANTS: TEA-ROOMS",
    "sg:postcode":"5000",
    "sg:province":"Aargau",
    "wof:name":"Mistral Le Bar Lienhard Gabriele",
    "wof:placetype":"venue"
},
  "geometry": {"coordinates":[8.0451021194,47.3910255432],"type":"Point"}
}