{
  "type": "Feature",
  "properties": {
    "iso:country":"CH",
    "sg:address":"Reussd\u00f6rflistrasse 17",
    "sg:city":"Gebenstorf",
    "sg:orig_category":"Detailhandel mit elektrischen Haushalts-,Radio U Fernsehger\u00e4ten sowie Musikinstrumenten",
    "sg:phone":"+41 56 223 44 69",
    "sg:postcode":"5412",
    "sg:province":"Aargau",
    "wof:name":"Svs-systems Gmbh",
    "wof:placetype":"venue"
},
  "geometry": {"coordinates":[8.2271242142,47.4804992676],"type":"Point"}
}