{
  "type": "Feature",
  "properties": {
    "iso:country":"CH",
    "sg:address":"Hauptstrasse 76",
    "sg:city":"Staad",
    "sg:classifiers":[
        {
            "category":"Professional",
            "subcategory":"Computer Services",
            "type":"Services"
        }
    ],
    "sg:phone":"+41 71 850 01 75",
    "sg:postcode":"9422",
    "sg:province":"St. Gallen",
    "sg:tags":[
        "development",
        "software"
    ],
    "wof:name":"Btc Computerservice Gmbh",
    "wof:placetype":"venue"
},
  "geometry": {"coordinates":[9.5433320999,47.4836082458],"type":"Point"}
}