{
  "type": "Feature",
  "properties": {
    "iso:country":"CH",
    "sg:address":"Bahnhofstrasse 61",
    "sg:city":"Frauenfeld",
    "sg:orig_category":"Sportvereine Renn-& Reitsport",
    "sg:phone":"+41 52 721 66 11",
    "sg:postcode":"8500",
    "sg:province":"Thurgau",
    "wof:name":"Rennverein Frauenfeld",
    "wof:placetype":"venue"
},
  "geometry": {"coordinates":[8.8941926956,47.5563278198],"type":"Point"}
}