{
  "type": "Feature",
  "properties": {
    "iso:country":"CH",
    "sg:address":"Rainstrasse 371 8706 Meilen. Postfach",
    "sg:city":"Meilen",
    "sg:orig_category":"Unternehmensberatung",
    "sg:postcode":"8706",
    "sg:province":"Z\u00fcrich",
    "wof:name":"Menti Marketing",
    "wof:placetype":"venue"
},
  "geometry": {"coordinates":[8.6361503601,47.2723617554],"type":"Point"}
}