{
  "type": "Feature",
  "properties": {
    "iso:country":"CH",
    "sg:address":"Unterer Hardeggweg 23",
    "sg:city":"Steffisburg",
    "sg:orig_category":"Datenverarbeitungsdienste",
    "sg:phone":"+41 33 438 08 68",
    "sg:postcode":"3612",
    "sg:province":"Bern",
    "wof:name":"Wild Informatik Ag",
    "wof:placetype":"venue"
},
  "geometry": {"coordinates":[7.619052,46.780918],"type":"Point"}
}