{
  "type": "Feature",
  "properties": {
    "iso:country":"CH",
    "sg:address":"Les Vergers A",
    "sg:city":"Corcelles-payerne",
    "sg:orig_category":"Herstellung von Musikinstrumenten",
    "sg:phone":"+41 26 660 63 40",
    "sg:postcode":"1562",
    "sg:province":"Vaud",
    "wof:name":"Maurer Kurt, Atelier De Pianos",
    "wof:placetype":"venue"
},
  "geometry": {"coordinates":[6.9608740807,46.8332138062],"type":"Point"}
}