{
  "type": "Feature",
  "properties": {
    "iso:country":"CH",
    "sg:address":"Chemin De Bouleyres 42b",
    "sg:city":"Bulle",
    "sg:orig_category":"Herstellung von elektrischen Lampen U Leuchten",
    "sg:phone":"+41 26 913 72 00",
    "sg:postcode":"1630",
    "sg:province":"Fribourg",
    "wof:name":"Lumi\u00e8re Et Son, Genin Thierry",
    "wof:placetype":"venue"
},
  "geometry": {"coordinates":[7.0630021095,46.6162986755],"type":"Point"}
}