{
  "type": "Feature",
  "properties": {
    "iso:country":"CH",
    "sg:address":"Br\u00fcggliacher 50",
    "sg:city":"Oberrohrdorf",
    "sg:orig_category":"Unternehmensberatung Werbeberatung",
    "sg:phone":"+41 56 470 70 27",
    "sg:postcode":"5452",
    "sg:province":"Aargau",
    "wof:name":"Roger Bernet Rob. D-sein.",
    "wof:placetype":"venue"
},
  "geometry": {"coordinates":[8.3140678406,47.4211807251],"type":"Point"}
}