{
  "type": "Feature",
  "properties": {
    "iso:country":"CH",
    "sg:address":"Bahnsteig 1",
    "sg:city":"Neuhausen",
    "sg:orig_category":"Wirtschaftspr\u00fcfung, Steuerberatung U Treuhand",
    "sg:phone":"+41 52 675 50 75",
    "sg:postcode":"8212",
    "sg:province":"Schaffhausen",
    "wof:name":"Niedermann Treuhand Ag",
    "wof:placetype":"venue"
},
  "geometry": {"coordinates":[8.6230401993,47.6824417114],"type":"Point"}
}