{
  "type": "Feature",
  "properties": {
    "iso:country":"CH",
    "sg:address":"Unterdorf 25",
    "sg:city":"Sch\u00f6nengrund",
    "sg:classifiers":[
        {
            "category":"Restaurant",
            "type":"Food & Drink"
        }
    ],
    "sg:phone":"+41 41 448 10 30",
    "sg:postcode":"9105",
    "sg:province":"Appenzell Ausserrhoden",
    "wof:name":"Restaurant R\u00f6ssli",
    "wof:placetype":"venue"
},
  "geometry": {"coordinates":[8.3209123611,47.1315536499],"type":"Point"}
}