{
  "type": "Feature",
  "properties": {
    "iso:country":"CH",
    "sg:address":"Rue De Eglise Catholique 1",
    "sg:city":"Montreux",
    "sg:orig_category":"Detailhandel mit Radio U Fernsehger\u00e4ten Detailhandel mit elektrischen Haushalts-,Radio U Fernsehger\u00e4",
    "sg:phone":"+41 21 963 84 00",
    "sg:postcode":"1820",
    "sg:province":"Vaud",
    "wof:name":"Riviera Tv G\u00e9rald Ferrari S\u00e0rl Activit\u00e9 Se Rapp. Au Domaine De L'audio-visuel, Du Multi-m\u00e9dia, En Partic. Mat\u00e9riel Radio-tv- Vid\u00e9o-hi-fi, Satellites; Commerce, Loc. Etc",
    "wof:placetype":"venue"
},
  "geometry": {"coordinates":[6.9110898972,46.4312896729],"type":"Point"}
}