{
  "type": "Feature",
  "properties": {
    "iso:country":"CH",
    "sg:address":"Hinterbergstrasse 40",
    "sg:city":"Steinhausen",
    "sg:orig_category":"Detailhandel mit Milcherzeugnissen U Eiern",
    "sg:phone":"+41 41 240 06 06",
    "sg:postcode":"6312",
    "sg:province":"Zug",
    "wof:name":"Rast Lebensmittel Ag",
    "wof:placetype":"venue"
},
  "geometry": {"coordinates":[8.3025970459,47.0508728027],"type":"Point"}
}