{
  "type": "Feature",
  "properties": {
    "iso:country":"CH",
    "sg:address":"Rorschacher Strasse 11a",
    "sg:city":"Rheineck",
    "sg:orig_category":"Vorschulen, Kinderg\u00e4rten",
    "sg:phone":"+41 71 888 55 52",
    "sg:postcode":"9424",
    "sg:province":"St. Gallen",
    "wof:name":"Kindergarten Rorschacher Str.",
    "wof:placetype":"venue"
},
  "geometry": {"coordinates":[9.5866765976,47.4681053162],"type":"Point"}
}