{
  "type": "Feature",
  "properties": {
    "iso:country":"CH",
    "sg:address":"Kasernenstrasse 4",
    "sg:city":"Bachenb\u00fclach",
    "sg:orig_category":"Detailhandel mit Antiquit\u00e4ten Detailhandel mit M\u00f6beln",
    "sg:phone":"+41 18603563",
    "sg:postcode":"8184",
    "sg:province":"Z\u00fcrich",
    "wof:name":"Markus Ginsig Antiquit\u00e4ten Zum Holzwurm",
    "wof:placetype":"venue"
},
  "geometry": {"coordinates":[8.535965,47.50322],"type":"Point"}
}