{
  "type": "Feature",
  "properties": {
    "iso:country":"CH",
    "sg:address":"Sasselli Via 14/16",
    "sg:city":"Agno",
    "sg:orig_category":"Detailhandel mit Bekleidung",
    "sg:postcode":"6982",
    "sg:province":"Ticino",
    "wof:name":"Regina Fashion Sa",
    "wof:placetype":"venue"
},
  "geometry": {"coordinates":[8.824461,46.190022],"type":"Point"}
}