{
  "type": "Feature",
  "properties": {
    "iso:country":"CH",
    "sg:address":"Oberdorf",
    "sg:city":"Sch\u00f6tz",
    "sg:orig_category":"Mechanik",
    "sg:postcode":"6247",
    "sg:province":"Luzern",
    "wof:name":"Felber O. & Co",
    "wof:placetype":"venue"
},
  "geometry": {"coordinates":[7.9904499054,47.1678695679],"type":"Point"}
}