{
  "type": "Feature",
  "properties": {
    "addr:full":"Z\u00fcrcherstrasse 21 Uznach St. Gallen 8730",
    "addr:housenumber":"21",
    "addr:postcode":"8730",
    "addr:street":"Zuercherstrasse",
    "iso:country":"CH",
    "sg:address":"Z\u00fcrcherstrasse 21",
    "sg:city":"Uznach",
    "sg:orig_category":"Dachdeckerei D\u00e4mmung gegen K\u00e4lte, W\u00e4rme, Schall U Ersch\u00fctterung",
    "sg:phone":"+41 55 210 12 51",
    "sg:postcode":"8730",
    "sg:province":"St. Gallen",
    "wof:name":"P. Beerli Gmbh Flach-steilbedachungen",
    "wof:placetype":"venue"
},
  "geometry": {"coordinates":[8.981516,47.226154],"type":"Point"}
}