{
  "type": "Feature",
  "properties": {
    "iso:country":"CH",
    "sg:address":"Schaffhauserstrasse 5",
    "sg:city":"Oerlingen",
    "sg:classifiers":[
        {
            "category":"Restaurant",
            "type":"Food & Drink"
        }
    ],
    "sg:phone":"+41 52 319 11 36",
    "sg:postcode":"8461",
    "sg:province":"Z\u00fcrich",
    "wof:name":"Restaurant Traube",
    "wof:placetype":"venue"
},
  "geometry": {"coordinates":[8.6766033173,47.6223678589],"type":"Point"}
}