{
  "type": "Feature",
  "properties": {
    "iso:country":"CH",
    "sg:address":"B\u00fchlstrasse 7",
    "sg:city":"Sirnach",
    "sg:orig_category":"Herstellung von nachrichtentechnischen Ger\u00e4ten U Einrichtungen",
    "sg:phone":"+41 79 696 38 29",
    "sg:postcode":"8370",
    "sg:province":"Thurgau",
    "wof:name":"Alber Kommunikationstechnik",
    "wof:placetype":"venue"
},
  "geometry": {"coordinates":[8.9834117889,47.4651298523],"type":"Point"}
}