{
  "type": "Feature",
  "properties": {
    "iso:country":"CH",
    "sg:address":"Reichenbachstrasse 77",
    "sg:city":"Bern",
    "sg:orig_category":"Nationale Postdienste",
    "sg:phone":"+41 61 421 39 01",
    "sg:postcode":"3004",
    "sg:province":"Bern",
    "wof:name":"Die Schweizerische Post Binningen 2 Schafmatten",
    "wof:placetype":"venue"
},
  "geometry": {"coordinates":[7.5714259148,47.5334320068],"type":"Point"}
}