{
  "type": "Feature",
  "properties": {
    "iso:country":"CH",
    "sg:address":"Rue De Pr\u00e9barreau 1",
    "sg:city":"Neuch\u00e2tel",
    "sg:orig_category":"D\u00e4mmung gegen K\u00e4lte, W\u00e4rme, Schall U Ersch\u00fctterung Zimmerei, Dachdeckerei, Bauspenglerei U Abdichtun",
    "sg:phone":"+41 32 724 19 10",
    "sg:postcode":"2000",
    "sg:province":"Neuch\u00e2tel",
    "wof:name":"Essima Etanch\u00e9it\u00e9 Sa",
    "wof:placetype":"venue"
},
  "geometry": {"coordinates":[6.9247927666,46.9921455383],"type":"Point"}
}