{
  "type": "Feature",
  "properties": {
    "addr:full":"Badenerstrasse 119 8004 Z\u00fcrich. Postfach Z\u00fcrich Z\u00fcrich 8001",
    "addr:housenumber":"119",
    "addr:postcode":"8004 zuerich. postfach;8001",
    "addr:street":"Badenerstrasse",
    "iso:country":"CH",
    "sg:address":"Badenerstrasse 119 8004 Z\u00fcrich. Postfach",
    "sg:city":"Z\u00fcrich",
    "sg:orig_category":"Detailhandel mit Bekleidung",
    "sg:phone":"+41 79 407 11 72",
    "sg:postcode":"8001",
    "sg:province":"Z\u00fcrich",
    "wof:name":"Boutique Vulcania Gmbh Designer Mode U. Accessories; Import, Handel, Verkauf, Vermittlung",
    "wof:placetype":"venue"
},
  "geometry": {"coordinates":[8.524001,47.374214],"type":"Point"}
}