{
  "type": "Feature",
  "properties": {
    "iso:country":"CH",
    "sg:address":"Gewerbestrasse 10",
    "sg:city":"Sissach",
    "sg:orig_category":"Wirtschaftspr\u00fcfung, Steuerberatung U Treuhand",
    "sg:phone":"+41 61 973 19 19",
    "sg:postcode":"4450",
    "sg:province":"Basel-Landschaft",
    "wof:name":"Rr Treuhand Gmbh",
    "wof:placetype":"venue"
},
  "geometry": {"coordinates":[7.8033361435,47.4669570923],"type":"Point"}
}