{
  "type": "Feature",
  "properties": {
    "iso:country":"CH",
    "sg:address":"Z\u00fcrcherstrasse 234",
    "sg:city":"Frauenfeld",
    "sg:orig_category":"Unclassifiable Establishments",
    "sg:postcode":"8500",
    "sg:province":"Thurgau",
    "wof:name":"Restaurant 'orchid-thai-garten' Inhaberin S. Ngoenka Strupat",
    "wof:placetype":"venue"
},
  "geometry": {"coordinates":[8.901342392,47.5598678589],"type":"Point"}
}