{
  "type": "Feature",
  "properties": {
    "iso:country":"CH",
    "sg:address":"Baslerstrasse 7",
    "sg:city":"Rheinfelden",
    "sg:orig_category":"Vermietung U Verpachtung von eigenen Immobilien",
    "sg:postcode":"4310",
    "sg:province":"Aargau",
    "wof:name":"Terso Ag",
    "wof:placetype":"venue"
},
  "geometry": {"coordinates":[9.4925899506,47.4757537842],"type":"Point"}
}