{
  "type": "Feature",
  "properties": {
    "iso:country":"CH",
    "sg:address":"Pr\u00e9-bryant 4 1510 Moudon Case Postale 225",
    "sg:city":"Moudon",
    "sg:orig_category":"Gewinnung von Kies U Sand Herstellung von sonstigen Produkten aus nichtmetallischen Mineralien",
    "sg:phone":"+41 21 905 20 72",
    "sg:postcode":"1510",
    "sg:province":"Vaud",
    "wof:name":"Victor Rod Sa Gravi\u00e8res & Transports",
    "wof:placetype":"venue"
},
  "geometry": {"coordinates":[6.8003668785,46.6674957275],"type":"Point"}
}