{
  "type": "Feature",
  "properties": {
    "iso:country":"CH",
    "sg:address":"Mont\u00e9zillon 2203 Rochefort. Postfach",
    "sg:city":"Rochefort",
    "sg:orig_category":"Erbringung von Dienstleistungen f\u00fcr Unternehmen",
    "sg:postcode":"2203",
    "wof:name":"Antal Tony D\u00e9coration D\u00e9coration D'int\u00e9rieur, Rev\u00eatement De Sols, Rembourrage De Meubles Etc",
    "wof:placetype":"venue"
},
  "geometry": {"coordinates":[6.8369398117,46.9864311218],"type":"Point"}
}