{
  "type": "Feature",
  "properties": {
    "iso:country":"CH",
    "sg:address":"Grosserstrasse 52 8841 Gross. Postfach",
    "sg:city":"Gross",
    "sg:orig_category":"Stukkateurgewerbe, Gipserei U Verputzerei",
    "sg:phone":"+41 55 412 44 86",
    "sg:postcode":"8841",
    "sg:province":"Schwyz",
    "wof:name":"August Gyr & Sohn Gmbh",
    "wof:placetype":"venue"
},
  "geometry": {"coordinates":[8.7763147354,47.1148643494],"type":"Point"}
}