{
  "type": "Feature",
  "properties": {
    "iso:country":"CH",
    "sg:address":"Chollerstrasse 39",
    "sg:city":"Zug",
    "sg:orig_category":"Herstellung von sonstigen elektrischen Ausr\u00fcstungen",
    "sg:phone":"+41 41 741 84 27",
    "sg:postcode":"6300",
    "sg:province":"Zug",
    "wof:name":"Richard Hotel Ag",
    "wof:placetype":"venue"
},
  "geometry": {"coordinates":[8.4926977158,47.1865921021],"type":"Point"}
}