{
  "type": "Feature",
  "properties": {
    "iso:country":"CH",
    "sg:address":"Rue Du Pr\u00e9-des-cloches 18",
    "sg:city":"Vouvry",
    "sg:orig_category":"Sportvereine Turnen Vereine Damen",
    "sg:postcode":"1896",
    "sg:province":"Valais",
    "wof:name":"St\u00e9 De Gymnastique & Sport",
    "wof:placetype":"venue"
},
  "geometry": {"coordinates":[6.8888831139,46.3403205872],"type":"Point"}
}