{
  "type": "Feature",
  "properties": {
    "iso:country":"CH",
    "sg:address":"1201",
    "sg:city":"Gen\u00e8ve",
    "sg:orig_category":"Instandhaltung U Reparatur von Automobilen RESTAURANTS: TEA-ROOMS",
    "sg:phone":"+41 22 738 78 24",
    "sg:postcode":"1201",
    "sg:province":"Gen\u00e8ve",
    "wof:name":"Savary Alain Caf\u00e9-restaurant La Croix-f\u00e9d\u00e9rale",
    "wof:placetype":"venue"
},
  "geometry": {"coordinates":[6.1550297737,46.2156715393],"type":"Point"}
}