{
  "type": "Feature",
  "properties": {
    "iso:country":"CH",
    "sg:address":"Route De Lausanne 33",
    "sg:city":"Mont-sur-lausanne",
    "sg:orig_category":"Detailhandel mit Waren verschiedener Art, Hauptrichtung Nahrungsmittel",
    "sg:phone":"+41 21 652 47 44",
    "sg:postcode":"1052",
    "sg:province":"Vaud",
    "wof:name":"Coop Vaud Chablais Valaisan",
    "wof:placetype":"venue"
},
  "geometry": {"coordinates":[6.6347618103,46.5541572571],"type":"Point"}
}