{
  "type": "Feature",
  "properties": {
    "iso:country":"CH",
    "sg:address":"Echallens Avenue D' 107 1004 Lausanne. Postfach",
    "sg:city":"Lausanne",
    "sg:orig_category":"Unclassifiable Establishments",
    "sg:postcode":"1004",
    "sg:province":"Vaud",
    "wof:name":"Si Le Versant Sa",
    "wof:placetype":"venue"
},
  "geometry": {"coordinates":[6.8227171898,47.1001586914],"type":"Point"}
}