{
  "type": "Feature",
  "properties": {
    "iso:country":"CH",
    "sg:address":"Sonnmatt 128",
    "sg:city":"Birr",
    "sg:orig_category":"Herstellung von Radio U Fernsehger\u00e4ten sowie phono U videotechnischen Ger\u00e4ten",
    "sg:phone":"+41 56 450 00 62",
    "sg:postcode":"5242",
    "sg:province":"Aargau",
    "wof:name":"Egc Computer Technik Eggenschwiler Peter",
    "wof:placetype":"venue"
},
  "geometry": {"coordinates":[8.1975822449,47.4373817444],"type":"Point"}
}