{
  "type": "Feature",
  "properties": {
    "iso:country":"CH",
    "sg:address":"1686 Grangettes-romont. Postfach",
    "sg:city":"Grangettes-romont",
    "sg:orig_category":"Haltung von Rindern",
    "sg:postcode":"1686",
    "sg:province":"Fribourg",
    "wof:name":"Syndicat D'\u00e9levage De La Race Bovine Pie Noir De Grangettes",
    "wof:placetype":"venue"
},
  "geometry": {"coordinates":[6.9610929489,46.6757926941],"type":"Point"}
}