{
  "type": "Feature",
  "properties": {
    "iso:country":"CH",
    "sg:address":"Sagenmattstrasse 4",
    "sg:city":"Finstersee",
    "sg:orig_category":"Handels-H\u00e4user U Gesellschaften",
    "sg:postcode":"6313",
    "sg:province":"Zug",
    "wof:name":"Schuler Ag Finstersee",
    "wof:placetype":"venue"
},
  "geometry": {"coordinates":[8.628074646,47.1680297852],"type":"Point"}
}