{
  "type": "Feature",
  "properties": {
    "iso:country":"CH",
    "sg:address":"Rue Du Maupas 87",
    "sg:city":"Lausanne",
    "sg:orig_category":"Druck ohne Zeitungsdruck Offsetdruck",
    "sg:phone":"+41 21 648 75 75",
    "sg:postcode":"1004",
    "sg:province":"Vaud",
    "wof:name":"Imprimerie Du Dauphin, Pahud Jos\u00e9",
    "wof:placetype":"venue"
},
  "geometry": {"coordinates":[6.621940136,46.527053833],"type":"Point"}
}