{
  "type": "Feature",
  "properties": {
    "iso:country":"CH",
    "sg:address":"Luxburgstr. 35a",
    "sg:city":"Egnach",
    "sg:orig_category":"Fachdetailhandel in Verkaufsr\u00e4umen",
    "sg:postcode":"9322",
    "sg:province":"Thurgau",
    "wof:name":"Kaderli A Art. 2000",
    "wof:placetype":"venue"
},
  "geometry": {"coordinates":[9.3842153549,47.5488204956],"type":"Point"}
}