{
  "type": "Feature",
  "properties": {
    "iso:country":"CH",
    "sg:address":"Via Canonico Ghiringhelli 49 6500 Bellinzona Casella Postale",
    "sg:city":"Bellinzona",
    "sg:orig_category":"Herstellung von k\u00e4lte U lufttechnischen Erzeugnissen f\u00fcr gewerbliche Zwecke",
    "sg:phone":"+41 91 825 40 21",
    "sg:postcode":"6500",
    "sg:province":"Ticino",
    "wof:name":"Verilux Sa",
    "wof:placetype":"venue"
},
  "geometry": {"coordinates":[9.0241193771,46.1944618225],"type":"Point"}
}