{
  "type": "Feature",
  "properties": {
    "iso:country":"CH",
    "sg:address":"9565",
    "sg:city":"Oppikon",
    "sg:orig_category":"Detailhandel mit Waren verschiedener Art, Hauptrichtung Nahrungsmittel",
    "sg:phone":"+41 56 450 38 21",
    "sg:postcode":"9565",
    "sg:province":"Thurgau",
    "wof:name":"Martin Staub Pickpay Partner",
    "wof:placetype":"venue"
},
  "geometry": {"coordinates":[8.2076044083,47.4834594727],"type":"Point"}
}