{
  "type": "Feature",
  "properties": {
    "iso:country":"CH",
    "sg:address":"4922",
    "sg:city":"Thunstetten",
    "sg:orig_category":"Vereine Gesang",
    "sg:postcode":"4922",
    "sg:province":"Bern",
    "wof:name":"Gemischter Chor Thunstetten",
    "wof:placetype":"venue"
},
  "geometry": {"coordinates":[7.75395298,47.2041740417],"type":"Point"}
}