{
  "type": "Feature",
  "properties": {
    "iso:country":"CH",
    "sg:address":"Zollstrasse 6 9490 Vaduz. Postfach 1261",
    "sg:city":"Vaduz",
    "sg:classifiers":[
        {
            "category":"Professional",
            "subcategory":"Employment Agencies",
            "type":"Services"
        }
    ],
    "sg:phone":"+41 75 232 10 88",
    "sg:postcode":"9490",
    "sg:tags":[
        "personal",
        "u",
        "stellenvermittlung"
    ],
    "wof:name":"Ren\u00e9 Gusset Personalberatung Ag",
    "wof:placetype":"venue"
},
  "geometry": {"coordinates":[9.5212078094,47.1329269409],"type":"Point"}
}