{
  "type": "Feature",
  "properties": {
    "iso:country":"CH",
    "sg:address":"Feldeggstrasse 26",
    "sg:city":"Sch\u00f6nb\u00fchl-urtenen",
    "sg:orig_category":"Stukkateurgewerbe, Gipserei U Verputzerei",
    "sg:phone":"+41 34 422 35 50",
    "sg:postcode":"3322",
    "sg:province":"Bern",
    "wof:name":"Kernen Kurt",
    "wof:placetype":"venue"
},
  "geometry": {"coordinates":[7.5073690414,47.0178451538],"type":"Point"}
}