{
  "type": "Feature",
  "properties": {
    "iso:country":"CH",
    "sg:address":"Bipschal",
    "sg:city":"Ligerz",
    "sg:orig_category":"Dauerkulturbau",
    "sg:postcode":"2514",
    "sg:province":"Bern",
    "wof:name":"Gredinger Weinbau Und Weinhandel",
    "wof:placetype":"venue"
},
  "geometry": {"coordinates":[7.144992,47.087746],"type":"Point"}
}