{
  "type": "Feature",
  "properties": {
    "iso:country":"CH",
    "sg:address":"Hintergasse 17",
    "sg:city":"M\u00fcnsingen",
    "sg:orig_category":"Bauschreinerei Herstellung von M\u00f6beln verschiedener Art",
    "sg:phone":"+41 31 721 12 36",
    "sg:postcode":"3110",
    "sg:province":"Bern",
    "wof:name":"A & S Design M\u00f6bel Batt",
    "wof:placetype":"venue"
},
  "geometry": {"coordinates":[7.565635,46.875774],"type":"Point"}
}