{
  "type": "Feature",
  "properties": {
    "iso:country":"CH",
    "sg:address":"Rue Alexandre Cailler 7",
    "sg:city":"Broc",
    "sg:orig_category":"Architektur U Ingenieurb\u00fcros",
    "sg:phone":"+41 26 921 28 78",
    "sg:postcode":"1636",
    "sg:province":"Fribourg",
    "wof:name":"Hydrap S\u00e0rl Bureau D'\u00e9tude",
    "wof:placetype":"venue"
},
  "geometry": {"coordinates":[7.097598,46.603912],"type":"Point"}
}