{
  "type": "Feature",
  "properties": {
    "iso:country":"CH",
    "sg:address":"Grand-pont 23",
    "sg:city":"Sion",
    "sg:orig_category":"Unclassifiable Establishments",
    "sg:postcode":"1950",
    "sg:province":"Valais",
    "wof:name":"Le March\u00e9 Du Cheval-blanc Comestibles \u00e9picerie Fine",
    "wof:placetype":"venue"
},
  "geometry": {"coordinates":[7.3603749275,46.2346611023],"type":"Point"}
}