{
  "type": "Feature",
  "properties": {
    "iso:country":"CH",
    "sg:address":"Berglistrasse 20",
    "sg:city":"Luzern",
    "sg:orig_category":"Pensionskassen",
    "sg:phone":"+41 41 310 11 62",
    "sg:postcode":"6005",
    "sg:province":"Luzern",
    "wof:name":"F\u00fcrsorgestiftung Heim Im Bergli",
    "wof:placetype":"venue"
},
  "geometry": {"coordinates":[8.2986059189,47.0450019836],"type":"Point"}
}