{
  "type": "Feature",
  "properties": {
    "iso:country":"CH",
    "sg:address":"Gerbestrasse 5",
    "sg:city":"Einsiedeln",
    "sg:orig_category":"Wohnheime",
    "sg:postcode":"8840",
    "sg:province":"Schwyz",
    "wof:name":"Genossenschaft F\u00fcr Alterssiedlungen Einsiedeln.",
    "wof:placetype":"venue"
},
  "geometry": {"coordinates":[8.7500228882,47.1326446533],"type":"Point"}
}