{
  "type": "Feature",
  "properties": {
    "iso:country":"CH",
    "sg:address":"Wildbachstrasse 85",
    "sg:city":"Z\u00fcrich",
    "sg:orig_category":"Fernmeldedienste",
    "sg:phone":"+41 13821432",
    "sg:postcode":"8008",
    "sg:province":"Z\u00fcrich",
    "wof:name":"Live Telegram, The Illegal De Botton Eagle",
    "wof:placetype":"venue"
},
  "geometry": {"coordinates":[8.5594787598,47.3530921936],"type":"Point"}
}