{
  "type": "Feature",
  "properties": {
    "iso:country":"CH",
    "sg:address":"Schwarzackerstrasse 58/3",
    "sg:city":"Kaiseraugst",
    "sg:orig_category":"Vermietung U Verpachtung von eigenen Immobilien",
    "sg:phone":"+41 61 813 09 51",
    "sg:postcode":"4303",
    "sg:province":"Aargau",
    "wof:name":"Ankli Claude, Immobilien",
    "wof:placetype":"venue"
},
  "geometry": {"coordinates":[7.730246067,47.5347557068],"type":"Point"}
}