{
  "type": "Feature",
  "properties": {
    "iso:country":"CH",
    "sg:address":"Austrasse 103",
    "sg:city":"Basel",
    "sg:orig_category":"Vermietung U Verpachtung von eigenen Immobilien",
    "sg:postcode":"4051",
    "sg:province":"Basel-Stadt",
    "wof:name":"Bilbal Ag",
    "wof:placetype":"venue"
},
  "geometry": {"coordinates":[7.5768699646,47.5552902222],"type":"Point"}
}