{
  "type": "Feature",
  "properties": {
    "iso:country":"CH",
    "sg:address":"Unterneuhaus 232",
    "sg:city":"Wilchingen",
    "sg:orig_category":"Herstellung von Betonerzeugnissen f\u00fcr den Bau",
    "sg:phone":"+41 52 681 21 32",
    "sg:postcode":"8217",
    "sg:province":"Schaffhausen",
    "wof:name":"K\u00fclling Ag",
    "wof:placetype":"venue"
},
  "geometry": {"coordinates":[8.4635124207,47.6796951294],"type":"Point"}
}