{
  "type": "Feature",
  "properties": {
    "iso:country":"CH",
    "sg:address":"Bottigenstrasse 6",
    "sg:city":"Bern",
    "sg:orig_category":"Erschliessung von Grundst\u00fccken",
    "sg:phone":"+41 31 992 09 64",
    "sg:postcode":"3000",
    "sg:province":"Bern",
    "wof:name":"Baugenossenschaft Br\u00fcnnen-eichholz",
    "wof:placetype":"venue"
},
  "geometry": {"coordinates":[7.389772892,46.9397354126],"type":"Point"}
}