{
  "type": "Feature",
  "properties": {
    "iso:country":"CH",
    "sg:address":"8596 Scherzingen. Postfach",
    "sg:city":"Scherzingen",
    "sg:orig_category":"W\u00e4schereien",
    "sg:phone":"+41 71 686 20 02",
    "sg:postcode":"8596",
    "sg:province":"Thurgau",
    "wof:name":"Zentralw\u00e4scherei Kanton Thurgau",
    "wof:placetype":"venue"
},
  "geometry": {"coordinates":[9.2290496826,47.6274681091],"type":"Point"}
}