{
  "type": "Feature",
  "properties": {
    "iso:country":"CH",
    "sg:address":"Jurastrasse 9",
    "sg:city":"Bern",
    "sg:orig_category":"Sportvereine Automobil",
    "sg:postcode":"3013",
    "sg:province":"Bern",
    "wof:name":"Auto-moto-club Bern",
    "wof:placetype":"venue"
},
  "geometry": {"coordinates":[7.443816185,46.9572563171],"type":"Point"}
}