{
  "type": "Feature",
  "properties": {
    "iso:country":"CH",
    "sg:address":"Orbe Rue D' 93",
    "sg:city":"Yverdon-les-bains",
    "sg:orig_category":"Hardwareberatung",
    "sg:postcode":"1400",
    "sg:province":"Vaud",
    "wof:name":"Magma-computer, Graber",
    "wof:placetype":"venue"
},
  "geometry": {"coordinates":[9.5628242493,47.3171920776],"type":"Point"}
}