{
  "type": "Feature",
  "properties": {
    "iso:country":"CH",
    "sg:address":"Baarerstrasse 53 6300 Zug. Postfach",
    "sg:city":"Zug",
    "sg:orig_category":"Unclassifiable Establishments",
    "sg:phone":"+41 41 728 71 10",
    "sg:postcode":"6300",
    "sg:province":"Zug",
    "wof:name":"Unimo Real Estate Holding Ag Beteiligungen Usw",
    "wof:placetype":"venue"
},
  "geometry": {"coordinates":[8.5169372559,47.1746902466],"type":"Point"}
}