{
  "type": "Feature",
  "properties": {
    "iso:country":"CH",
    "sg:address":"Arnold B\u00f6cklin-strasse 15",
    "sg:city":"Basel",
    "sg:orig_category":"Herstellung von medizinischen U chirurgischen Ger\u00e4ten sowie orthop\u00e4dischen Vorrichtungen",
    "sg:postcode":"4051",
    "sg:province":"Basel-Stadt",
    "wof:name":"Vestoboy Sa",
    "wof:placetype":"venue"
},
  "geometry": {"coordinates":[8.9789562225,46.1534881592],"type":"Point"}
}