{
  "type": "Feature",
  "properties": {
    "iso:country":"CH",
    "sg:address":"Rainstrasse 35a",
    "sg:city":"Unter\u00e4geri",
    "sg:orig_category":"Softwareentwicklung U beratung",
    "sg:phone":"+41 41 754 40 20",
    "sg:postcode":"6314",
    "sg:province":"Zug",
    "wof:name":"Gloor Electronics",
    "wof:placetype":"venue"
},
  "geometry": {"coordinates":[8.5729598999,47.1350440979],"type":"Point"}
}