{
  "type": "Feature",
  "properties": {
    "iso:country":"CH",
    "sg:address":"L\u00f6wenplatz 1",
    "sg:city":"Jegenstorf",
    "sg:orig_category":"Non-Classified Establishments",
    "sg:phone":"+41 31 761 02 02",
    "sg:postcode":"3303",
    "sg:province":"Bern",
    "wof:name":"Gasthof Zum L\u00f6wen",
    "wof:placetype":"venue"
},
  "geometry": {"coordinates":[7.5063519478,47.048500061],"type":"Point"}
}