{
  "type": "Feature",
  "properties": {
    "iso:country":"CH",
    "sg:address":"Zugerstrasse 6",
    "sg:city":"W\u00e4denswil",
    "sg:orig_category":"Detailhandel mit Waren verschiedener Art, Hauptrichtung Nahrungsmittel",
    "sg:phone":"+41 17803786",
    "sg:postcode":"8820",
    "sg:province":"Z\u00fcrich",
    "wof:name":"Coop Z\u00fcrichsee-linth",
    "wof:placetype":"venue"
},
  "geometry": {"coordinates":[8.6381282806,47.2379646301],"type":"Point"}
}