{
  "type": "Feature",
  "properties": {
    "iso:country":"CH",
    "sg:address":"Contrada Antica 3",
    "sg:city":"Muzzano",
    "sg:orig_category":"Fotografisches Gewerbe U fotografische Laboratorien Satzherstellung U Reproduktion",
    "sg:phone":"+41 91 966 25 45",
    "sg:postcode":"6933",
    "sg:province":"Ticino",
    "wof:name":"Fotocomposizione Taiana Ernesto Sergio Taiana",
    "wof:placetype":"venue"
},
  "geometry": {"coordinates":[8.9225177765,45.9976882935],"type":"Point"}
}