{
  "type": "Feature",
  "properties": {
    "iso:country":"CH",
    "sg:address":"Place De Saint-fran\u00e7ois 15",
    "sg:city":"Lausanne",
    "sg:orig_category":"Nationale Postdienste",
    "sg:phone":"+41 24 494 14 06",
    "sg:postcode":"1003",
    "sg:province":"Vaud",
    "wof:name":"La Poste Suisse Leysin 1",
    "wof:placetype":"venue"
},
  "geometry": {"coordinates":[7.0177397728,46.3473091125],"type":"Point"}
}