{
  "type": "Feature",
  "properties": {
    "iso:country":"CH",
    "sg:address":"Beim Bahnhof 3812 Wilderswil. Postfach",
    "sg:city":"Wilderswil",
    "sg:orig_category":"Fachdetailhandel in Verkaufsr\u00e4umen",
    "sg:postcode":"3812",
    "sg:province":"Bern",
    "wof:name":"Alpin Center Gmbh",
    "wof:placetype":"venue"
},
  "geometry": {"coordinates":[7.8698549271,46.6668663025],"type":"Point"}
}