{
  "type": "Feature",
  "properties": {
    "iso:country":"CH",
    "sg:address":"Kaiserstrasse 26",
    "sg:city":"Rheinfelden",
    "sg:orig_category":"Grosshandel mit Kaffee, Tee, Kakao U Gew\u00fcrzen Grosshandel mit elektrischen Haushaltsger\u00e4ten",
    "sg:phone":"+41 61 831 33 00",
    "sg:postcode":"4310",
    "sg:province":"Aargau",
    "wof:name":"Markus Heller V.i.c. Very Important Coffee",
    "wof:placetype":"venue"
},
  "geometry": {"coordinates":[7.7890400887,47.552028656],"type":"Point"}
}