{
  "type": "Feature",
  "properties": {
    "iso:country":"CH",
    "sg:address":"Rue Centrale 8",
    "sg:city":"Bex",
    "sg:classifiers":[
        {
            "category":"Travel",
            "subcategory":"Hotels & Motels",
            "type":"Entertainment"
        }
    ],
    "sg:postcode":"1880",
    "sg:province":"Vaud",
    "sg:tags":[
        "hotels",
        "mit",
        "restaurant"
    ],
    "wof:name":"Montandon, Mme Raymonde",
    "wof:placetype":"venue"
},
  "geometry": {"coordinates":[7.0136580467,46.2512550354],"type":"Point"}
}