{
  "type": "Feature",
  "properties": {
    "iso:country":"CH",
    "sg:address":"Gr\u00fcnweg 18",
    "sg:city":"Pieterlen",
    "sg:orig_category":"Architektur U Ingenieurb\u00fcros Architekturb\u00fcros",
    "sg:phone":"+41 32 377 17 11",
    "sg:postcode":"2542",
    "sg:province":"Bern",
    "wof:name":"Tda Gmbh",
    "wof:placetype":"venue"
},
  "geometry": {"coordinates":[7.345639,47.177006],"type":"Point"}
}