{
  "type": "Feature",
  "properties": {
    "addr:full":"Heuelstrasse 7 Thalwil Z\u00fcrich 8800",
    "addr:housenumber":"7",
    "addr:postcode":"8800",
    "addr:street":"Heuelstrasse",
    "iso:country":"CH",
    "sg:address":"Heuelstrasse 7",
    "sg:city":"Thalwil",
    "sg:orig_category":"Architektur U Ingenieurb\u00fcros",
    "sg:phone":"+41 17723454",
    "sg:postcode":"8800",
    "sg:province":"Z\u00fcrich",
    "wof:name":"B\u00e4nziger+bacchetta+fehlmann+partner Ingenieure + Planer Sia Usic",
    "wof:placetype":"venue"
},
  "geometry": {"coordinates":[8.5545,47.295738],"type":"Point"}
}