{
  "type": "Feature",
  "properties": {
    "iso:country":"CH",
    "sg:address":"Wellbergstrasse 11 6244 Nebikon. Postfach",
    "sg:city":"Nebikon",
    "sg:orig_category":"Detailhandel mit Blumen U Pflanzen",
    "sg:phone":"+41 62 756 46 35",
    "sg:postcode":"6244",
    "sg:province":"Luzern",
    "wof:name":"Ingrid Kaufmann Blumengesch\u00e4ft",
    "wof:placetype":"venue"
},
  "geometry": {"coordinates":[7.9746,47.187149],"type":"Point"}
}