{
  "type": "Feature",
  "properties": {
    "iso:country":"CH",
    "sg:address":"6516 Cugnasco. Postfach",
    "sg:city":"Cugnasco",
    "sg:orig_category":"Non-Classified Establishments",
    "sg:postcode":"6516",
    "sg:province":"Ticino",
    "wof:name":"Bravo Fabio",
    "wof:placetype":"venue"
},
  "geometry": {"coordinates":[8.9177446365,46.1752510071],"type":"Point"}
}