{
  "type": "Feature",
  "properties": {
    "iso:country":"CH",
    "sg:address":"Br\u00fcggstrasse 41",
    "sg:city":"Biel/bienne",
    "sg:orig_category":"Sportschulen Fern\u00f6stliche Kampfsportarten",
    "sg:phone":"+41 32 365 44 75",
    "sg:postcode":"2503",
    "sg:province":"Bern",
    "wof:name":"Shotokan Karate Club Bienne",
    "wof:placetype":"venue"
},
  "geometry": {"coordinates":[7.2533841133,47.130821228],"type":"Point"}
}