{
  "type": "Feature",
  "properties": {
    "iso:country":"CH",
    "sg:address":"Ziegelfeldstrasse 1",
    "sg:city":"Olten",
    "sg:classifiers":[
        {
            "category":"Professional",
            "subcategory":"Employment Agencies",
            "type":"Services"
        }
    ],
    "sg:phone":"+41 62 205 60 20",
    "sg:postcode":"4600",
    "sg:province":"Solothurn",
    "sg:tags":[
        "personal",
        "u",
        "stellenvermittlung"
    ],
    "wof:name":"Personalberatung Das Team Ag",
    "wof:placetype":"venue"
},
  "geometry": {"coordinates":[7.9011659622,47.3519248962],"type":"Point"}
}