{
  "type": "Feature",
  "properties": {
    "iso:country":"CH",
    "sg:address":"Steinentorstrasse 18 4051 Basel. Postfach 1662",
    "sg:city":"Basel",
    "sg:orig_category":"Fachdetailhandel in Verkaufsr\u00e4umen Sonstiger Fachdetailhandel in Verkaufsr\u00e4umen",
    "sg:phone":"+41 61 271 09 10",
    "sg:postcode":"4001",
    "sg:province":"Basel-Stadt",
    "wof:name":"Raymond Kuhn Ag",
    "wof:placetype":"venue"
},
  "geometry": {"coordinates":[7.5888671875,47.5516929626],"type":"Point"}
}