{
  "type": "Feature",
  "properties": {
    "iso:country":"CH",
    "sg:address":"Luppmenstrasse 3",
    "sg:city":"Fehraltorf",
    "sg:orig_category":"Hardwareberatung Informatikdienste",
    "sg:phone":"+41 19566080",
    "sg:postcode":"8320",
    "sg:province":"Z\u00fcrich",
    "wof:name":"W3 Internet Services Gmbh",
    "wof:placetype":"venue"
},
  "geometry": {"coordinates":[8.7479391098,47.3869590759],"type":"Point"}
}