{
  "type": "Feature",
  "properties": {
    "iso:country":"CH",
    "sg:address":"Seeweg 3",
    "sg:city":"Goldach",
    "sg:orig_category":"Sonstige Personenbef\u00f6rderung im Landverkehr",
    "sg:phone":"+41 71 841 01 76",
    "sg:postcode":"9403",
    "sg:province":"St. Gallen",
    "wof:name":"Ebneter-car",
    "wof:placetype":"venue"
},
  "geometry": {"coordinates":[9.4784650803,47.4787597656],"type":"Point"}
}