{
  "type": "Feature",
  "properties": {
    "iso:country":"CH",
    "sg:address":"Wismetstrasse 11a",
    "sg:city":"Weesen",
    "sg:classifiers":[
        {
            "category":"Banks & Credit Unions",
            "subcategory":"Bank",
            "type":"Services"
        }
    ],
    "sg:phone":"+41 4158431315",
    "sg:postcode":"8872",
    "sg:province":"St. Gallen",
    "wof:name":"Rentenanstalt Swiss Life",
    "wof:placetype":"venue"
},
  "geometry": {"coordinates":[9.090623,47.133751],"type":"Point"}
}