{
  "type": "Feature",
  "properties": {
    "iso:country":"CH",
    "sg:address":"Kronenplatz 6",
    "sg:city":"Lenzburg",
    "sg:classifiers":[
        {
            "category":"Professional",
            "subcategory":"Employment Agencies",
            "type":"Services"
        }
    ],
    "sg:postcode":"5600",
    "sg:province":"Aargau",
    "sg:tags":[
        "personal",
        "u",
        "stellenvermittlung"
    ],
    "wof:name":"Job-line Spycher",
    "wof:placetype":"venue"
},
  "geometry": {"coordinates":[7.515226841,46.9583206177],"type":"Point"}
}