{
  "type": "Feature",
  "properties": {
    "iso:country":"CH",
    "sg:address":"Beundengasse 15",
    "sg:city":"Lyss",
    "sg:orig_category":"Unclassifiable Establishments",
    "sg:postcode":"3250",
    "sg:province":"Bern",
    "wof:name":"Arpromotion Andr\u00e9 Rhyner",
    "wof:placetype":"venue"
},
  "geometry": {"coordinates":[7.3001480103,47.0732574463],"type":"Point"}
}