{
  "type": "Feature",
  "properties": {
    "iso:country":"CH",
    "sg:address":"Bahnweg 5a 4542 Luterbach. Postfach",
    "sg:city":"Luterbach",
    "sg:orig_category":"Architektur U Ingenieurb\u00fcros Architekturb\u00fcros",
    "sg:phone":"+41 32 682 21 72",
    "sg:postcode":"4542",
    "sg:province":"Solothurn",
    "wof:name":"Ochsenbein Kurt, Dipl Arch. Htl + Partner Ag",
    "wof:placetype":"venue"
},
  "geometry": {"coordinates":[7.592308,47.218212],"type":"Point"}
}