{
  "type": "Feature",
  "properties": {
    "iso:country":"CH",
    "sg:address":"Route De Peney 147",
    "sg:city":"Vernier",
    "sg:orig_category":"Instandhaltung U Reparatur von Automobilen",
    "sg:phone":"+41 22 341 33 43",
    "sg:postcode":"1214",
    "sg:province":"Gen\u00e8ve",
    "wof:name":"Tom Car Service, Tsetsis",
    "wof:placetype":"venue"
},
  "geometry": {"coordinates":[6.0725607872,46.2095184326],"type":"Point"}
}