{
  "type": "Feature",
  "properties": {
    "iso:country":"CH",
    "sg:address":"Viale Stazione 17a",
    "sg:city":"Bellinzona",
    "sg:orig_category":"Detailhandel mit Herrenbekleidung Herstellung von Oberbekleidung",
    "sg:phone":"+41 91 825 15 13",
    "sg:postcode":"6500",
    "sg:province":"Ticino",
    "wof:name":"San Giovanni Confezioni Sa",
    "wof:placetype":"venue"
},
  "geometry": {"coordinates":[9.026184082,46.1937332153],"type":"Point"}
}