{
  "type": "Feature",
  "properties": {
    "iso:country":"CH",
    "sg:address":"Alpenstrasse 12 6300 Zug. Postfach",
    "sg:city":"Zug",
    "sg:orig_category":"Grosshandel mit Holz U Baustoffen",
    "sg:postcode":"6300",
    "sg:province":"Zug",
    "wof:name":"Lanai Ag",
    "wof:placetype":"venue"
},
  "geometry": {"coordinates":[8.5149440765,47.1725082397],"type":"Point"}
}