{
  "type": "Feature",
  "properties": {
    "iso:country":"CH",
    "sg:address":"7742",
    "sg:city":"Poschiavo",
    "sg:classifiers":[
        {
            "category":"Travel",
            "subcategory":"Hotels & Motels",
            "type":"Entertainment"
        }
    ],
    "sg:postcode":"7742",
    "sg:province":"Graubunden",
    "sg:tags":[
        "hotels",
        "mit",
        "restaurant"
    ],
    "wof:name":"Largiad\u00e8r",
    "wof:placetype":"venue"
},
  "geometry": {"coordinates":[7.6710968018,47.171043396],"type":"Point"}
}