{
  "type": "Feature",
  "properties": {
    "iso:country":"CH",
    "sg:address":"Altstetterstrasse 206",
    "sg:city":"Z\u00fcrich",
    "sg:orig_category":"Hoch U Tiefbau",
    "sg:phone":"+41 79 312 13 16",
    "sg:postcode":"8048",
    "sg:province":"Z\u00fcrich",
    "wof:name":"Hermann Eicher Baugesch\u00e4ft",
    "wof:placetype":"venue"
},
  "geometry": {"coordinates":[9.0426130295,47.4067001343],"type":"Point"}
}