{
  "type": "Feature",
  "properties": {
    "iso:country":"CH",
    "sg:address":"Birchstrasse 6",
    "sg:city":"Seuzach",
    "sg:orig_category":"Detailhandel mit Damenbekleidung",
    "sg:phone":"+41 19109855",
    "sg:postcode":"8472",
    "sg:province":"Z\u00fcrich",
    "wof:name":"Erica Walter Couture Erica",
    "wof:placetype":"venue"
},
  "geometry": {"coordinates":[8.577571,47.326801],"type":"Point"}
}