{
  "type": "Feature",
  "properties": {
    "iso:country":"CH",
    "sg:address":"Gros-ch\u00eane Avenue Du 26",
    "sg:city":"Onex",
    "sg:orig_category":"Unclassifiable Establishments",
    "sg:postcode":"1213",
    "sg:province":"Gen\u00e8ve",
    "wof:name":"Association Natives",
    "wof:placetype":"venue"
},
  "geometry": {"coordinates":[6.1044049263,46.1888237],"type":"Point"}
}