{
  "type": "Feature",
  "properties": {
    "iso:country":"CH",
    "sg:address":"Multergasse 2a 9006 St. Gallen. Postfach",
    "sg:city":"Ebmatingen",
    "sg:orig_category":"Verwaltung von Immobilien",
    "sg:postcode":"8123",
    "sg:province":"Z\u00fcrich",
    "wof:name":"Cooperativa Camana",
    "wof:placetype":"venue"
},
  "geometry": {"coordinates":[8.9375896454,45.9293632507],"type":"Point"}
}