{
  "type": "Feature",
  "properties": {
    "iso:country":"CH",
    "sg:address":"Via Moretto 7",
    "sg:city":"Sorengo",
    "sg:orig_category":"Herstellung von sonstigen Nahrungsmitteln",
    "sg:postcode":"6924",
    "sg:province":"Ticino",
    "wof:name":"Il Fungo Sagl",
    "wof:placetype":"venue"
},
  "geometry": {"coordinates":[8.9349184036,46.0047302246],"type":"Point"}
}