{
  "type": "Feature",
  "properties": {
    "iso:country":"CH",
    "sg:address":"Spichermatt 17",
    "sg:city":"Stans",
    "sg:orig_category":"Werbung",
    "sg:phone":"+41 41 620 75 77",
    "sg:postcode":"6370",
    "sg:province":"Nidwalden",
    "wof:name":"H\u00fcttmann Roland",
    "wof:placetype":"venue"
},
  "geometry": {"coordinates":[8.361451149,46.9659843445],"type":"Point"}
}