{
  "type": "Feature",
  "properties": {
    "iso:country":"CH",
    "sg:address":"1936",
    "sg:city":"Verbier",
    "sg:orig_category":"Elektroinstallation Herstellung von sonstigen elektrischen Ausr\u00fcstungen",
    "sg:phone":"+41 27 771 64 12",
    "sg:postcode":"1936",
    "sg:province":"Valais",
    "wof:name":"Baillifard-veuthey Sa Installations \u00e9lectriques",
    "wof:placetype":"venue"
},
  "geometry": {"coordinates":[7.2229599953,46.0967216492],"type":"Point"}
}