{
  "type": "Feature",
  "properties": {
    "iso:country":"CH",
    "sg:address":"Allmend 31",
    "sg:city":"Gunzgen",
    "sg:classifiers":[
        {
            "category":"Restaurant",
            "type":"Food & Drink"
        }
    ],
    "sg:phone":"+41 62 216 12 06",
    "sg:postcode":"4617",
    "sg:province":"Solothurn",
    "wof:name":"Restaurant Waldegg",
    "wof:placetype":"venue"
},
  "geometry": {"coordinates":[7.8330349922,47.3138008118],"type":"Point"}
}