{
  "type": "Feature",
  "properties": {
    "iso:country":"CH",
    "sg:address":"Bahnhofstrasse 2",
    "sg:city":"Rothrist",
    "sg:orig_category":"RESTAURANTS: TEA-ROOMS",
    "sg:postcode":"4852",
    "sg:province":"Aargau",
    "wof:name":"Face-rest Ag",
    "wof:placetype":"venue"
},
  "geometry": {"coordinates":[7.8796691895,47.3056526184],"type":"Point"}
}