{
  "type": "Feature",
  "properties": {
    "iso:country":"CH",
    "sg:address":"3999",
    "sg:city":"Oberwald",
    "sg:orig_category":"Bau von Strassen, Sportanlagen U Bahnverkehrsstrecken",
    "sg:postcode":"3999",
    "sg:province":"Valais",
    "wof:name":"Pharo Ag, Schneer\u00e4umung.",
    "wof:placetype":"venue"
},
  "geometry": {"coordinates":[8.345925,46.533363],"type":"Point"}
}