{
  "type": "Feature",
  "properties": {
    "iso:country":"CH",
    "sg:address":"Freiestrasse 48",
    "sg:city":"Thun",
    "sg:orig_category":"Maler U Glasergewerbe Stukkateurgewerbe, Gipserei U Verputzerei",
    "sg:phone":"+41 33 336 83 30",
    "sg:postcode":"3604",
    "sg:province":"Bern",
    "wof:name":"W. D\u00e4llenbach Ag",
    "wof:placetype":"venue"
},
  "geometry": {"coordinates":[7.6235170364,46.7423744202],"type":"Point"}
}