{
  "type": "Feature",
  "properties": {
    "iso:country":"CH",
    "sg:address":"M\u00e4rwiler Strasse 26",
    "sg:city":"Affeltrangen",
    "sg:orig_category":"Herstellung von Teppichen Verlegen von Fussboden",
    "sg:phone":"+41 71 917 12 35",
    "sg:postcode":"9556",
    "sg:province":"Thurgau",
    "wof:name":"Marius M\u00fcller",
    "wof:placetype":"venue"
},
  "geometry": {"coordinates":[9.0338821411,47.5257606506],"type":"Point"}
}