{
  "type": "Feature",
  "properties": {
    "iso:country":"CH",
    "sg:address":"1945",
    "sg:city":"Liddes",
    "sg:orig_category":"Bauschreinerei Herstellung von Konstruktionsteilen, Fertigbauteilen U Ausbauelementen aus Holz",
    "sg:phone":"+41 27 783 22 66",
    "sg:postcode":"1945",
    "sg:province":"Valais",
    "wof:name":"Jean-marc M\u00e9troz Menuiserie",
    "wof:placetype":"venue"
},
  "geometry": {"coordinates":[7.186204,45.991467],"type":"Point"}
}