{
  "type": "Feature",
  "properties": {
    "iso:country":"CH",
    "sg:address":"Kirchenstrasse 44",
    "sg:city":"Oberiberg",
    "sg:orig_category":"Gemeindeverwaltungen",
    "sg:phone":"+41 55 414 13 03",
    "sg:postcode":"8843",
    "sg:province":"Schwyz",
    "wof:name":"Gemeindeverwaltung Oberiberg",
    "wof:placetype":"venue"
},
  "geometry": {"coordinates":[8.7869262695,47.0411987305],"type":"Point"}
}