{
  "type": "Feature",
  "properties": {
    "iso:country":"CH",
    "sg:address":"Hofmattstrasse 37a",
    "sg:city":"Huttwil",
    "sg:classifiers":[
        {
            "category":"Professional",
            "subcategory":"Art Services",
            "type":"Services"
        }
    ],
    "sg:phone":"+41 62 962 28 72",
    "sg:postcode":"4950",
    "sg:province":"Bern",
    "sg:tags":[
        "design"
    ],
    "wof:name":"Atelier J\u00f6rg H\u00e4geli Gmbh",
    "wof:placetype":"venue"
},
  "geometry": {"coordinates":[7.842964,47.113445],"type":"Point"}
}