{
  "type": "Feature",
  "properties": {
    "iso:country":"CH",
    "sg:address":"Maggenberg 1",
    "sg:city":"Tafers",
    "sg:classifiers":[
        {
            "category":"Education",
            "subcategory":"Library",
            "type":"Public Place"
        }
    ],
    "sg:phone":"+41 26 494 42 10",
    "sg:postcode":"1712",
    "sg:province":"Fribourg",
    "sg:tags":[
        "u",
        "bibliotheken",
        "archive"
    ],
    "wof:name":"Spital Des Sensebezirks",
    "wof:placetype":"venue"
},
  "geometry": {"coordinates":[7.212368,46.810589],"type":"Point"}
}