{
  "type": "Feature",
  "properties": {
    "iso:country":"CH",
    "sg:address":"Aegetli 1",
    "sg:city":"Thal",
    "sg:classifiers":[
        {
            "category":"Wholesale",
            "subcategory":"Meat",
            "type":"Manufacturing & Wholesale Goods"
        }
    ],
    "sg:phone":"+41 26 912 81 91",
    "sg:postcode":"9425",
    "sg:province":"St. Gallen",
    "sg:tags":[
        "food",
        "cooked",
        "product",
        "related"
    ],
    "wof:name":"Salami Sa",
    "wof:placetype":"venue"
},
  "geometry": {"coordinates":[7.0640048981,46.6109008789],"type":"Point"}
}