{
  "type": "Feature",
  "properties": {
    "iso:country":"CH",
    "sg:address":"Feldkircherstrasse 75",
    "sg:city":"Schaan",
    "sg:orig_category":"Gartenbau",
    "sg:phone":"+423 233 10 91",
    "sg:postcode":"9494",
    "wof:name":"Wolfgang Walser Gartenpflege",
    "wof:placetype":"venue"
},
  "geometry": {"coordinates":[9.5181112289,47.1715888977],"type":"Point"}
}