{
  "type": "Feature",
  "properties": {
    "iso:country":"CH",
    "sg:address":"H\u00f6glerstrasse 36",
    "sg:city":"D\u00fcbendorf",
    "sg:orig_category":"Handel mit Automobilen",
    "sg:postcode":"8600",
    "sg:province":"Z\u00fcrich",
    "wof:name":"Ce Gmbh D\u00fcbendorf",
    "wof:placetype":"venue"
},
  "geometry": {"coordinates":[8.6135787964,47.3918190002],"type":"Point"}
}