{
  "type": "Feature",
  "properties": {
    "iso:country":"CH",
    "sg:address":"Quai Turrettini 1",
    "sg:city":"Geneva",
    "sg:classifiers":[
        {
            "category":"Travel",
            "subcategory":"Travel Agent",
            "type":"Entertainment"
        }
    ],
    "sg:phone":"+41 4122909000",
    "sg:postcode":"1201",
    "sg:province":"Gen\u00e8ve",
    "wof:name":"Mandarin Oriental Hotel Du Rhone",
    "wof:placetype":"venue"
},
  "geometry": {"coordinates":[6.1399888992,46.2055549622],"type":"Point"}
}