{
  "type": "Feature",
  "properties": {
    "iso:country":"CH",
    "sg:address":"Remparts Rue Des 5",
    "sg:city":"Sion",
    "sg:orig_category":"Detailhandel mit Bekleidung",
    "sg:phone":"+41 81 833 33 27",
    "sg:postcode":"1950",
    "sg:province":"Valais",
    "wof:name":"Kriemler-m\u00fcller Ag",
    "wof:placetype":"venue"
},
  "geometry": {"coordinates":[9.838191,46.497066],"type":"Point"}
}