{
  "type": "Feature",
  "properties": {
    "iso:country":"CH",
    "sg:address":"Gen\u00e8ve Route De",
    "sg:city":"Tolochenaz",
    "sg:orig_category":"Handel mit Motorr\u00e4dern, Teilen U Zubeh\u00f6r Instandhaltung U Reparatur von Motorr\u00e4dern",
    "sg:phone":"+41 21 802 22 22",
    "sg:postcode":"1131",
    "sg:province":"Vaud",
    "wof:name":"Moto-bolle S\u00e0rl",
    "wof:placetype":"venue"
},
  "geometry": {"coordinates":[6.4742050171,46.5053062439],"type":"Point"}
}