{
  "type": "Feature",
  "properties": {
    "iso:country":"CH",
    "sg:address":"Mettschlatterstrasse 10",
    "sg:city":"Schlatt",
    "sg:orig_category":"Shopping U Fachgesch\u00e4fte, Haushalt",
    "sg:phone":"+41 52 646 01 36",
    "sg:postcode":"8252",
    "sg:province":"Thurgau",
    "wof:name":"Zwergenland Ag",
    "wof:placetype":"venue"
},
  "geometry": {"coordinates":[8.701651,47.659901],"type":"Point"}
}