{
  "type": "Feature",
  "properties": {
    "iso:country":"CH",
    "sg:address":"Hinterwies 48",
    "sg:city":"Speicher",
    "sg:orig_category":"Architektur U Ingenieurb\u00fcros",
    "sg:phone":"+41 71 344 25 82",
    "sg:postcode":"9042",
    "sg:province":"Appenzell Ausserrhoden",
    "wof:name":"Herz Ingenieurb\u00fcro F\u00fcr Elektrische Anlagen",
    "wof:placetype":"venue"
},
  "geometry": {"coordinates":[9.436183,47.417103],"type":"Point"}
}