{
  "type": "Feature",
  "properties": {
    "iso:country":"CH",
    "sg:address":"Nollisweid 53",
    "sg:city":"Appenzell",
    "sg:orig_category":"Detailhandel mit Parf\u00fcmerieartikeln U K\u00f6rperpflegemitteln",
    "sg:phone":"+41 56 442 37 37",
    "sg:postcode":"9050",
    "sg:province":"Appenzell Innerhoden",
    "wof:name":"Parf\u00fcmerie Neumarktplatz Krucker + Co",
    "wof:placetype":"venue"
},
  "geometry": {"coordinates":[8.20789814,47.4831619263],"type":"Point"}
}