{
  "type": "Feature",
  "properties": {
    "iso:country":"CH",
    "sg:address":"Engstringerstrasse 43c 8952 Schlieren. Postfach",
    "sg:city":"Schlieren",
    "sg:orig_category":"Handel mit Automobilen",
    "sg:phone":"+41 17307003",
    "sg:postcode":"8952",
    "sg:province":"Z\u00fcrich",
    "wof:name":"Automobile Derungs I. Gmbh Automobile; Handel, Reparatur",
    "wof:placetype":"venue"
},
  "geometry": {"coordinates":[8.4476528168,47.4049034119],"type":"Point"}
}