{
  "type": "Feature",
  "properties": {
    "iso:country":"CH",
    "sg:address":"Buechraiweg 13",
    "sg:city":"Oberrohrdorf",
    "sg:orig_category":"Softwareentwicklung U beratung",
    "sg:phone":"+41 21 922 36 17",
    "sg:postcode":"5452",
    "sg:province":"Aargau",
    "wof:name":"Magnenat Andr\u00e9 S\u00e0rl Vente De Mat\u00e9riel Informatique, Consultant Dans Le Dom. De L'informatique",
    "wof:placetype":"venue"
},
  "geometry": {"coordinates":[6.8834300041,46.4704742432],"type":"Point"}
}