{
  "type": "Feature",
  "properties": {
    "iso:country":"CH",
    "sg:address":"Langmattweg 3",
    "sg:city":"Ormalingen",
    "sg:classifiers":[
        {
            "category":"Wholesale",
            "subcategory":"Chemicals & Plastics",
            "type":"Manufacturing & Wholesale Goods"
        }
    ],
    "sg:phone":"+41 61 983 04 50",
    "sg:postcode":"4466",
    "sg:province":"Basel-Landschaft",
    "sg:tags":[
        "dyestuff"
    ],
    "wof:name":"L + S Ag",
    "wof:placetype":"venue"
},
  "geometry": {"coordinates":[7.8653588295,47.4697303772],"type":"Point"}
}