{
  "type": "Feature",
  "properties": {
    "iso:country":"CH",
    "sg:address":"Inselstrasse 40",
    "sg:city":"Basel",
    "sg:orig_category":"Herstellung von sonstigen Produkten aus nichtmetallischen Mineralien",
    "sg:phone":"+41 61 683 27 28",
    "sg:postcode":"4057",
    "sg:province":"Basel-Stadt",
    "wof:name":"Dmg Rizzo",
    "wof:placetype":"venue"
},
  "geometry": {"coordinates":[7.5884919167,47.5773582458],"type":"Point"}
}