{
  "type": "Feature",
  "properties": {
    "iso:country":"CH",
    "sg:address":"Perrey-very",
    "sg:city":"Brenles",
    "sg:orig_category":"Sanit\u00e4r, Heizungs U L\u00fcftungsinstallation Sanit\u00e4rinstallation",
    "sg:phone":"+41 21 691 46 50",
    "sg:postcode":"1683",
    "sg:province":"Vaud",
    "wof:name":"Chauffarex Sa",
    "wof:placetype":"venue"
},
  "geometry": {"coordinates":[6.5708589554,46.5162086487],"type":"Point"}
}