{
  "type": "Feature",
  "properties": {
    "addr:full":"Avenue G\u00e9n\u00e9ral-guisan 19 3960 Sierre Case Postale 439 Sierre Valais 3960",
    "addr:housenumber":"19;439",
    "addr:postcode":"3960;3960",
    "addr:street":"Avenue Ge\u0301Ne\u0301Ral-Guisan;Postale",
    "iso:country":"CH",
    "sg:address":"Avenue G\u00e9n\u00e9ral-guisan 19 3960 Sierre Case Postale 439",
    "sg:city":"Sierre",
    "sg:orig_category":"Advokaturb\u00fcros",
    "sg:phone":"+41 27 455 45 55",
    "sg:postcode":"3960",
    "sg:province":"Valais",
    "wof:name":"Edmond Perruchoud Etude D'avocat",
    "wof:placetype":"venue"
},
  "geometry": {"coordinates":[7.530097,46.292152],"type":"Point"}
}