{
  "type": "Feature",
  "properties": {
    "iso:country":"CH",
    "sg:address":"Cras Chemin Des 27 2900 Porrentruy. Postfach",
    "sg:city":"Porrentruy",
    "sg:orig_category":"Sonstiger spezialisierter Hoch U Tiefbau",
    "sg:phone":"+41 32 466 84 69",
    "sg:postcode":"2900",
    "sg:province":"Jura",
    "wof:name":"Bangerter Jean-daniel Entreprise G\u00e9n\u00e9rale De Construction, Notamm. L'ex\u00e9cution De Travaux De Ma\u00e7onnerie, De G\u00e9nie Civil Etc",
    "wof:placetype":"venue"
},
  "geometry": {"coordinates":[7.0782270432,47.4170303345],"type":"Point"}
}