{
  "type": "Feature",
  "properties": {
    "iso:country":"CH",
    "sg:address":"Widenospen 3",
    "sg:city":"Ottenbach",
    "sg:orig_category":"Rechts U Unternehmensberatung, Buchf\u00fchrung Wirtschaftspr\u00fcfung, Steuerberatung U Treuhand",
    "sg:phone":"+41 56 483 25 55",
    "sg:postcode":"8913",
    "sg:province":"Z\u00fcrich",
    "wof:name":"Divor Ag Vorsorgeeinrichtung",
    "wof:placetype":"venue"
},
  "geometry": {"coordinates":[8.2950334549,47.4472694397],"type":"Point"}
}