{
  "type": "Feature",
  "properties": {
    "iso:country":"CH",
    "sg:address":"Avry-centre Route De Matran 9",
    "sg:city":"Avry-sur-matran",
    "sg:orig_category":"Detailhandel mit Sportartikeln",
    "sg:phone":"+41 26 470 10 20",
    "sg:postcode":"1754",
    "sg:province":"Fribourg",
    "wof:name":"Dany-sport Sa",
    "wof:placetype":"venue"
},
  "geometry": {"coordinates":[7.0721960068,46.7883262634],"type":"Point"}
}