{
  "type": "Feature",
  "properties": {
    "iso:country":"CH",
    "sg:address":"Place De La Fontaine 4",
    "sg:city":"Peseux",
    "sg:orig_category":"Bijouterien",
    "sg:phone":"+41 32 731 66 20",
    "sg:postcode":"2034",
    "sg:province":"Neuch\u00e2tel",
    "wof:name":"Sylvain Hoffmann Bijouterie-horlogerie",
    "wof:placetype":"venue"
},
  "geometry": {"coordinates":[6.889803,46.986645],"type":"Point"}
}