{
  "type": "Feature",
  "properties": {
    "iso:country":"CH",
    "sg:address":"Z\u00fcrichstrasse 106",
    "sg:city":"Z\u00fcrich",
    "sg:classifiers":[
        {
            "category":"Industrial Area",
            "type":"Public Place"
        }
    ],
    "sg:phone":"+41 22 884 20 20",
    "sg:postcode":"8134",
    "sg:province":"Z\u00fcrich",
    "sg:tags":[
        "large",
        "private"
    ],
    "wof:name":"Patek Philippe Geneva",
    "wof:placetype":"venue"
},
  "geometry": {"coordinates":[6.111207962,46.1667175293],"type":"Point"}
}