{
  "type": "Feature",
  "properties": {
    "iso:country":"CH",
    "sg:address":"Via Cantonale 40",
    "sg:city":"Comano",
    "sg:orig_category":"Nationale Postdienste",
    "sg:phone":"+41 91 794 11 06",
    "sg:postcode":"6949",
    "sg:province":"Ticino",
    "wof:name":"La Posta Svizzera",
    "wof:placetype":"venue"
},
  "geometry": {"coordinates":[8.8057250977,46.1342468262],"type":"Point"}
}