{
  "type": "Feature",
  "properties": {
    "iso:country":"CH",
    "sg:address":"Baslerstrasse 20",
    "sg:city":"Oftringen",
    "sg:orig_category":"Sanit\u00e4r U Heizungsinstallation",
    "sg:phone":"+41 71 242 69 59",
    "sg:postcode":"4665",
    "sg:province":"Aargau",
    "wof:name":"Oertli Service Ag",
    "wof:placetype":"venue"
},
  "geometry": {"coordinates":[9.3947153091,47.443649292],"type":"Point"}
}