{
  "type": "Feature",
  "properties": {
    "iso:country":"CH",
    "sg:address":"Centrale Rue 34",
    "sg:city":"Avenches",
    "sg:orig_category":"Detailhandel mit Brot, Back U S\u00fcsswaren",
    "sg:phone":"+41 26 675 11 26",
    "sg:postcode":"1580",
    "sg:province":"Vaud",
    "wof:name":"Aeby Sa",
    "wof:placetype":"venue"
},
  "geometry": {"coordinates":[7.039729,46.879654],"type":"Point"}
}