{
  "type": "Feature",
  "properties": {
    "iso:country":"CH",
    "sg:address":"T\u00f6sstalstrasse 224b 8405 Iberg (winterthur). Postfach 136",
    "sg:city":"Winterthur",
    "sg:orig_category":"Rechtsberatung Verwaltung von Immobilien",
    "sg:phone":"+41 71 913 20 70",
    "sg:postcode":"8411",
    "sg:province":"Z\u00fcrich",
    "wof:name":"Lt B\u00fchler Treuhand",
    "wof:placetype":"venue"
},
  "geometry": {"coordinates":[9.0476093292,47.4658126831],"type":"Point"}
}