{
  "type": "Feature",
  "properties": {
    "iso:country":"CH",
    "sg:address":"Fliederstrasse 3 8152 Glattbrugg. Postfach",
    "sg:city":"Glattbrugg",
    "sg:orig_category":"Sanit\u00e4r, Heizungs U L\u00fcftungsinstallation Sanit\u00e4rinstallation",
    "sg:phone":"+41 18106352",
    "sg:postcode":"8152",
    "sg:province":"Z\u00fcrich",
    "wof:name":"Vollrath Ag",
    "wof:placetype":"venue"
},
  "geometry": {"coordinates":[8.5642337799,47.4312667847],"type":"Point"}
}