{
  "type": "Feature",
  "properties": {
    "addr:full":"Glattalstrasse 76 8052 Z\u00fcrich. Postfach 425 Z\u00fcrich Z\u00fcrich 8052",
    "addr:housenumber":"76;425",
    "addr:postcode":"8052 zuerich.;8052",
    "addr:street":"Glattalstrasse;Postfach",
    "iso:country":"CH",
    "sg:address":"Glattalstrasse 76 8052 Z\u00fcrich. Postfach 425",
    "sg:city":"Z\u00fcrich",
    "sg:orig_category":"Bauingenieurb\u00fcros Heizung L\u00fcftung Klima Bauingenieurb\u00fcros Sanit\u00e4r",
    "sg:phone":"+41 13084020",
    "sg:postcode":"8052",
    "sg:province":"Z\u00fcrich",
    "wof:name":"Hunziker + Urban Haustechnik Ag",
    "wof:placetype":"venue"
},
  "geometry": {"coordinates":[8.546516,47.427189],"type":"Point"}
}