{
  "type": "Feature",
  "properties": {
    "iso:country":"CH",
    "sg:address":"3781",
    "sg:city":"Turbach",
    "sg:orig_category":"Primarschulen",
    "sg:postcode":"3781",
    "sg:province":"Bern",
    "wof:name":"Primarschule",
    "wof:placetype":"venue"
},
  "geometry": {"coordinates":[7.3304600716,46.4784317017],"type":"Point"}
}