{
  "type": "Feature",
  "properties": {
    "iso:country":"CH",
    "sg:address":"Bachstrasse 7",
    "sg:city":"Herisau",
    "sg:classifiers":[
        {
            "category":"Professional",
            "subcategory":"Employment Agencies",
            "type":"Services"
        }
    ],
    "sg:postcode":"9100",
    "sg:province":"Appenzell Ausserrhoden",
    "sg:tags":[
        "personal",
        "u",
        "stellenvermittlung"
    ],
    "wof:name":"Star Model Productions, B. M\u00fcller",
    "wof:placetype":"venue"
},
  "geometry": {"coordinates":[9.2800731659,47.3865852356],"type":"Point"}
}