{
  "type": "Feature",
  "properties": {
    "iso:country":"CH",
    "sg:address":"Via Santeri 15 7130 Ilanz. Postfach 251",
    "sg:city":"Ilanz",
    "sg:orig_category":"Hoch U Tiefbau Kauf U Verkauf von Immobilien auf eigene Rechnung",
    "sg:phone":"+41 81 925 28 68",
    "sg:postcode":"7130",
    "sg:province":"Graubunden",
    "wof:name":"Candrian L. Ag",
    "wof:placetype":"venue"
},
  "geometry": {"coordinates":[9.199514389,46.7730064392],"type":"Point"}
}