{
  "type": "Feature",
  "properties": {
    "iso:country":"CH",
    "sg:address":"Langenbruckstrasse 485",
    "sg:city":"M\u00fcmliswil",
    "sg:orig_category":"Allgemeiner Hoch U Tiefbau",
    "sg:phone":"+41 62 386 70 00",
    "sg:postcode":"4717",
    "sg:province":"Solothurn",
    "wof:name":"Roth J. Baugesch\u00e4ft Ag",
    "wof:placetype":"venue"
},
  "geometry": {"coordinates":[7.710891,47.344479],"type":"Point"}
}