{
  "type": "Feature",
  "properties": {
    "iso:country":"CH",
    "sg:address":"Kirchgasse 1",
    "sg:city":"Oensingen",
    "sg:orig_category":"Detailhandel mit Lederwaren U Reiseartikeln Herstellung von Reiseartikeln, Leder U Sattlerwaren",
    "sg:postcode":"4702",
    "sg:province":"Solothurn",
    "wof:name":"Roland Utz Inneneinrichtungen",
    "wof:placetype":"venue"
},
  "geometry": {"coordinates":[7.7235307693,47.2907562256],"type":"Point"}
}