{
  "type": "Feature",
  "properties": {
    "iso:country":"CH",
    "sg:address":"Avenue Eug\u00e8ne-pittard 56",
    "sg:city":"Gen\u00e8ve",
    "sg:orig_category":"Sanit\u00e4rinstallation",
    "sg:phone":"+41 32 968 38 62",
    "sg:postcode":"1206",
    "sg:province":"Gen\u00e8ve",
    "wof:name":"Charles Maurer Installation Sanitaire",
    "wof:placetype":"venue"
},
  "geometry": {"coordinates":[6.8460998535,47.1084709167],"type":"Point"}
}