{
  "type": "Feature",
  "properties": {
    "iso:country":"CH",
    "sg:address":"Obmoos 4",
    "sg:city":"Zug",
    "sg:orig_category":"Wirtschaftspr\u00fcfung, Steuerberatung U Treuhand",
    "sg:postcode":"6300",
    "sg:province":"Zug",
    "wof:name":"Box 308 Gmbh",
    "wof:placetype":"venue"
},
  "geometry": {"coordinates":[8.522359848,47.1680870056],"type":"Point"}
}