{
  "type": "Feature",
  "properties": {
    "addr:full":"Cham Zug 6330",
    "addr:postcode":"6330",
    "addr:street":"Zug",
    "iso:country":"CH",
    "sg:city":"Cham",
    "sg:orig_category":"Freizeit, Musik",
    "sg:postcode":"6330",
    "sg:province":"Zug",
    "wof:name":"Peterhans-software",
    "wof:placetype":"venue"
},
  "geometry": {"coordinates":[8.458923,47.18079],"type":"Point"}
}