{
  "type": "Feature",
  "properties": {
    "iso:country":"CH",
    "sg:address":"Guarda",
    "sg:city":"Guarda",
    "sg:classifiers":[
        {
            "category":"Banks & Credit Unions",
            "subcategory":"Bank",
            "type":"Services"
        }
    ],
    "sg:phone":"+41 81 862 21 88",
    "sg:postcode":"7545",
    "sg:province":"Graubunden",
    "wof:name":"Graub\u00fcndner Kantonalbank",
    "wof:placetype":"venue"
},
  "geometry": {"coordinates":[10.15055,46.775314],"type":"Point"}
}