{
  "type": "Feature",
  "properties": {
    "iso:country":"CH",
    "sg:address":"Burgerfeldstrasse 19",
    "sg:city":"Uznach",
    "sg:orig_category":"Sonstige pers\u00f6nliche Dienstleistungen",
    "sg:postcode":"8730",
    "sg:province":"St. Gallen",
    "wof:name":"Ecole D'\u00e9volution Personnelle Et Spirituelle, Mann\u00e9 Joy",
    "wof:placetype":"venue"
},
  "geometry": {"coordinates":[6.6908230782,46.5134887695],"type":"Point"}
}