{
  "type": "Feature",
  "properties": {
    "addr:full":"Repfergasse 26 Schaffhausen Schaffhausen 8200",
    "addr:housenumber":"26",
    "addr:postcode":"8200",
    "addr:street":"Repfergasse",
    "iso:country":"CH",
    "sg:address":"Repfergasse 26",
    "sg:city":"Schaffhausen",
    "sg:orig_category":"Detailhandel mit B\u00fcchern Detailhandel mit B\u00fcchern, Zeitungen, Schreib U Papeteriewaren",
    "sg:phone":"+41 52 625 50 50",
    "sg:postcode":"8200",
    "sg:province":"Schaffhausen",
    "wof:name":"Christliche Buchhandlung Eckstein",
    "wof:placetype":"venue"
},
  "geometry": {"coordinates":[8.635954,47.697834],"type":"Point"}
}