{
  "type": "Feature",
  "properties": {
    "iso:country":"CH",
    "sg:address":"M\u00fclibachstrasse 36",
    "sg:city":"M\u00f6nchaltorf",
    "sg:classifiers":[
        {
            "category":"Home & Garden",
            "subcategory":"Building Materials",
            "type":"Retail Goods"
        }
    ],
    "sg:phone":"+41 18252530",
    "sg:postcode":"8617",
    "sg:province":"Z\u00fcrich",
    "sg:tags":[
        "paris",
        "plaster"
    ],
    "wof:name":"Fritz Grob Ag",
    "wof:placetype":"venue"
},
  "geometry": {"coordinates":[8.7169828415,47.3075790405],"type":"Point"}
}