{
  "type": "Feature",
  "properties": {
    "iso:country":"CH",
    "sg:address":"Hauptstrasse 17",
    "sg:city":"Fischingen",
    "sg:orig_category":"Detailhandel mit Milcherzeugnissen U Eiern",
    "sg:phone":"+41 26 470 12 23",
    "sg:postcode":"8376",
    "sg:province":"Thurgau",
    "wof:name":"Roland Vonlanthen Laiterie",
    "wof:placetype":"venue"
},
  "geometry": {"coordinates":[7.0381999016,46.7760009766],"type":"Point"}
}