{
  "type": "Feature",
  "properties": {
    "iso:country":"CH",
    "sg:address":"B\u00fchlstrasse 70",
    "sg:city":"Sulgen",
    "sg:orig_category":"Sonstige Kreditinstitute ohne Spezialkreditinstitute",
    "sg:phone":"+41 71 640 05 70",
    "sg:postcode":"8583",
    "sg:province":"Thurgau",
    "wof:name":"Prime Helvetia Finanz- Dienstleistungen Ag",
    "wof:placetype":"venue"
},
  "geometry": {"coordinates":[9.1734676361,47.5421829224],"type":"Point"}
}