{
  "type": "Feature",
  "properties": {
    "iso:country":"CH",
    "sg:address":"Giessh\u00fcbelstrasse 106",
    "sg:city":"Z\u00fcrich",
    "sg:orig_category":"Mechanik Schlossereien",
    "sg:phone":"+41 81 325 12 62",
    "sg:postcode":"8045",
    "sg:province":"Z\u00fcrich",
    "wof:name":"Hertner S\u00f6hne",
    "wof:placetype":"venue"
},
  "geometry": {"coordinates":[9.6389751434,46.9900741577],"type":"Point"}
}