{
  "type": "Feature",
  "properties": {
    "iso:country":"CH",
    "sg:address":"Primerose Chemin De 2",
    "sg:city":"Lausanne",
    "sg:orig_category":"Grosshandel mit Tabakwaren",
    "sg:postcode":"1007",
    "sg:province":"Vaud",
    "wof:name":"Sklentzas Evangelos",
    "wof:placetype":"venue"
},
  "geometry": {"coordinates":[6.6167998314,46.5147476196],"type":"Point"}
}