{
  "type": "Feature",
  "properties": {
    "iso:country":"CH",
    "sg:address":"8566",
    "sg:city":"Neuwilen",
    "sg:orig_category":"Sportvereine Sch\u00fctzen",
    "sg:phone":"+41 52 761 18 69",
    "sg:postcode":"8566",
    "sg:province":"Thurgau",
    "wof:name":"Feldsch\u00fctzengesellschaft",
    "wof:placetype":"venue"
},
  "geometry": {"coordinates":[9.1345396042,47.6218490601],"type":"Point"}
}