{
  "type": "Feature",
  "properties": {
    "addr:full":"3904 Naters Valais 3904",
    "addr:housenumber":"3904",
    "addr:postcode":"3904",
    "iso:country":"CH",
    "sg:address":"3904",
    "sg:city":"Naters",
    "sg:orig_category":"Bezirks, Sekundar, Realschulen, Oberstufe der Primarschulen",
    "sg:postcode":"3904",
    "sg:province":"Valais",
    "wof:name":"Sekundarschule",
    "wof:placetype":"venue"
},
  "geometry": {"coordinates":[7.936724,46.123245],"type":"Point"}
}