{
  "type": "Feature",
  "properties": {
    "iso:country":"CH",
    "sg:address":"Schaufelbergerstrasse 31 8055 Z\u00fcrich. Postfach 973",
    "sg:city":"Z\u00fcrich",
    "sg:orig_category":"Verm\u00f6gensverwaltung",
    "sg:phone":"+41 14913831",
    "sg:postcode":"8055",
    "sg:province":"Z\u00fcrich",
    "wof:name":"Hermann Brand Verm\u00f6gensverwaltung",
    "wof:placetype":"venue"
},
  "geometry": {"coordinates":[8.5025911331,47.37159729],"type":"Point"}
}