{
  "type": "Feature",
  "properties": {
    "iso:country":"CH",
    "sg:address":"Diepoldsauerstrasse 20",
    "sg:city":"Widnau",
    "sg:orig_category":"Allgemeiner Hoch U Tiefbau",
    "sg:postcode":"9443",
    "sg:province":"St. Gallen",
    "wof:name":"Ma-ta Bau- & Verwaltungs Ag",
    "wof:placetype":"venue"
},
  "geometry": {"coordinates":[8.95279,47.175179],"type":"Point"}
}