{
  "type": "Feature",
  "properties": {
    "iso:country":"CH",
    "sg:address":"Hohlstrasse 271",
    "sg:city":"Z\u00fcrich",
    "sg:orig_category":"Detailhandel mit Fleisch U Fleischwaren Fleischverarbeitung",
    "sg:phone":"+41 14921532",
    "sg:postcode":"8004",
    "sg:province":"Z\u00fcrich",
    "wof:name":"Konya Kasabi, \u00d6zdemir Ragip",
    "wof:placetype":"venue"
},
  "geometry": {"coordinates":[8.5134553909,47.3830947876],"type":"Point"}
}