{
  "type": "Feature",
  "properties": {
    "iso:country":"CH",
    "sg:address":"Diemtigtalstrasse",
    "sg:city":"Oey",
    "sg:orig_category":"Elektroinstallation",
    "sg:phone":"+41 33 681 82 82",
    "sg:postcode":"3753",
    "sg:province":"Bern",
    "wof:name":"Fritz R\u00f6thlisberger Elektroinstallationen",
    "wof:placetype":"venue"
},
  "geometry": {"coordinates":[7.5771698952,46.6595993042],"type":"Point"}
}