{
  "type": "Feature",
  "properties": {
    "addr:full":"6917 Barbengo Ticino 6917",
    "addr:housenumber":"6917",
    "addr:postcode":"6917",
    "addr:street":"Barbengo Ticino",
    "iso:country":"CH",
    "sg:address":"6917",
    "sg:city":"Barbengo",
    "sg:orig_category":"Dachdeckerei Herstellung von sonstigen Metallwaren",
    "sg:phone":"+41 32 931 49 57",
    "sg:postcode":"6917",
    "sg:province":"Ticino",
    "wof:name":"Jean Vernetti Ferblanterie & Couverture",
    "wof:placetype":"venue"
},
  "geometry": {"coordinates":[6.751572,47.058102],"type":"Point"}
}