{
  "type": "Feature",
  "properties": {
    "addr:full":"Avenue De La Gare 5 Lausanne Vaud 1003",
    "addr:housenumber":"5",
    "addr:postcode":"1003",
    "addr:street":"Avenue De La Gare",
    "iso:country":"CH",
    "sg:address":"Avenue De La Gare 5",
    "sg:city":"Lausanne",
    "sg:orig_category":"Arztpraxen",
    "sg:phone":"+41 21 312 28 61",
    "sg:postcode":"1003",
    "sg:province":"Vaud",
    "wof:name":"Dr M\u00e9d. Fran\u00e7ois Aeby M\u00e9decin Sp\u00e9cialiste",
    "wof:placetype":"venue"
},
  "geometry": {"coordinates":[6.636744,46.516163],"type":"Point"}
}