{
  "type": "Feature",
  "properties": {
    "iso:country":"CH",
    "sg:address":"6775 Ambr\u00ec. Postfach",
    "sg:city":"Ambr\u00ec",
    "sg:orig_category":"Non-Classified Establishments",
    "sg:postcode":"6775",
    "sg:province":"Ticino",
    "wof:name":"Jovic Radinko",
    "wof:placetype":"venue"
},
  "geometry": {"coordinates":[8.6940097809,46.5097007751],"type":"Point"}
}