{
  "type": "Feature",
  "properties": {
    "addr:full":"Schwarzenbergstrasse 9 K\u00e4giswil Obwalden 6056",
    "addr:housenumber":"9",
    "addr:postcode":"6056",
    "addr:street":"Schwarzenbergstrasse;Obwalden",
    "iso:country":"CH",
    "sg:address":"Schwarzenbergstrasse 9",
    "sg:city":"K\u00e4giswil",
    "sg:orig_category":"Bauspenglerei Sanit\u00e4rinstallation U Spenglerei",
    "sg:phone":"+41 55 444 23 93",
    "sg:postcode":"6056",
    "sg:province":"Obwalden",
    "wof:name":"Christian Fenk Spenglerei",
    "wof:placetype":"venue"
},
  "geometry": {"coordinates":[8.95279,47.175179],"type":"Point"}
}