{
  "type": "Feature",
  "properties": {
    "iso:country":"CH",
    "sg:address":"Bodenmattstrasse 22",
    "sg:city":"Wallbach",
    "sg:orig_category":"Non-Classified Establishments",
    "sg:postcode":"4323",
    "sg:province":"Aargau",
    "wof:name":"Sandro K\u00f6rkel Gmbh",
    "wof:placetype":"venue"
},
  "geometry": {"coordinates":[7.9006271362,47.5582809448],"type":"Point"}
}