{
  "type": "Feature",
  "properties": {
    "iso:country":"CH",
    "sg:address":"Burgstrasse 184",
    "sg:city":"Meilen",
    "sg:orig_category":"Erbringung von sonstigen Dienstleistungen f\u00fcr Unterhaltung, Erholung U Freizeit",
    "sg:postcode":"8706",
    "sg:province":"Z\u00fcrich",
    "wof:name":"Presser-mohlmann Elsje",
    "wof:placetype":"venue"
},
  "geometry": {"coordinates":[8.6464529037,47.2754592896],"type":"Point"}
}