{
  "type": "Feature",
  "properties": {
    "iso:country":"CH",
    "sg:address":"Gotthardstrasse 114",
    "sg:city":"Ibach",
    "sg:orig_category":"Alters U Pflegeheime Gartenbau",
    "sg:phone":"+41 41 818 37 00",
    "sg:postcode":"6438",
    "sg:province":"Schwyz",
    "wof:name":"Alters-& Pflegeheim Eigenwies",
    "wof:placetype":"venue"
},
  "geometry": {"coordinates":[8.645186,47.012779],"type":"Point"}
}