{
  "type": "Feature",
  "properties": {
    "iso:country":"CH",
    "sg:address":"Berglistrasse 23",
    "sg:city":"B\u00fclach",
    "sg:orig_category":"Detailhandel mit Lederwaren U Reiseartikeln Herstellung von Reiseartikeln, Leder U Sattlerwaren",
    "sg:phone":"+41 18622054",
    "sg:postcode":"8180",
    "sg:province":"Z\u00fcrich",
    "wof:name":"Tony Garcia Tony Leder Atelier Sattlerei",
    "wof:placetype":"venue"
},
  "geometry": {"coordinates":[8.5461530685,47.5233764648],"type":"Point"}
}