{
  "type": "Feature",
  "properties": {
    "iso:country":"CH",
    "sg:address":"Rue Principale 36",
    "sg:city":"B\u00e9vilard",
    "sg:orig_category":"Detailhandel mit Fleisch U Fleischwaren",
    "sg:phone":"+41 32 492 17 83",
    "sg:postcode":"2735",
    "sg:province":"Bern",
    "wof:name":"Boucherie Krebs Sa",
    "wof:placetype":"venue"
},
  "geometry": {"coordinates":[7.2831449509,47.2364654541],"type":"Point"}
}