{
  "type": "Feature",
  "properties": {
    "iso:country":"CH",
    "sg:address":"Gerenweg 4",
    "sg:city":"Gipf-oberfrick",
    "sg:orig_category":"Detailhandel mit Waren verschiedener Art, Hauptrichtung Nahrungsmittel",
    "sg:phone":"+41 62 871 12 79",
    "sg:postcode":"5073",
    "sg:province":"Aargau",
    "wof:name":"Landi Gipf-oberfrick",
    "wof:placetype":"venue"
},
  "geometry": {"coordinates":[8.0088367462,47.5013504028],"type":"Point"}
}