{
  "type": "Feature",
  "properties": {
    "iso:country":"CH",
    "sg:address":"Oberdorfstrasse 1",
    "sg:city":"Flaach",
    "sg:orig_category":"Herstellung von sonstigen landwirtschaftlichen Maschinen Schmieden",
    "sg:phone":"+41 52 318 11 41",
    "sg:postcode":"8416",
    "sg:province":"Z\u00fcrich",
    "wof:name":"Willi J\u00e4ggli Schmiede & Landw.maschinen",
    "wof:placetype":"venue"
},
  "geometry": {"coordinates":[8.6112356186,47.5753364563],"type":"Point"}
}