{
  "type": "Feature",
  "properties": {
    "iso:country":"CH",
    "sg:address":"Heidenacherstrasse 5",
    "sg:city":"St. Erhard",
    "sg:classifiers":[
        {
            "category":"Banks & Credit Unions",
            "subcategory":"Bank",
            "type":"Services"
        }
    ],
    "sg:phone":"+41 4145212685",
    "sg:postcode":"6212",
    "sg:province":"Luzern",
    "wof:name":"Schweiz. Mobiliar",
    "wof:placetype":"venue"
},
  "geometry": {"coordinates":[8.07447,47.182919],"type":"Point"}
}