{
  "type": "Feature",
  "properties": {
    "addr:full":"Feldrietstrasse 3 Andwil St. Gallen 9204",
    "addr:housenumber":"3;st.",
    "addr:postcode":"9204",
    "addr:street":"Feldrietstrasse",
    "iso:country":"CH",
    "sg:address":"Feldrietstrasse 3",
    "sg:city":"Andwil",
    "sg:classifiers":[
        {
            "category":"Building & Trades",
            "subcategory":"Construction",
            "type":"Services"
        }
    ],
    "sg:phone":"+41 71 383 45 30",
    "sg:postcode":"9204",
    "sg:province":"St. Gallen",
    "sg:tags":[
        "ceiling",
        "dowel"
    ],
    "wof:name":"Hsw Monteco Gmbh",
    "wof:placetype":"venue"
},
  "geometry": {"coordinates":[9.278,47.442005],"type":"Point"}
}