{
  "type": "Feature",
  "properties": {
    "iso:country":"CH",
    "sg:address":"Chnewisstrasse 8 6078 Lungern. Postfach",
    "sg:city":"Lungern",
    "sg:orig_category":"Herstellung von Konstruktionsteilen, Fertigbauteilen U Ausbauelementen aus Holz Herstellung von Schr",
    "sg:phone":"+41 27 281 30 20",
    "sg:postcode":"6078",
    "sg:province":"Obwalden",
    "wof:name":"Morand & D\u00e9litroz",
    "wof:placetype":"venue"
},
  "geometry": {"coordinates":[7.4412097931,46.1751708984],"type":"Point"}
}