{
  "type": "Feature",
  "properties": {
    "iso:country":"CH",
    "sg:address":"Langensandstrasse 23",
    "sg:city":"Luzern",
    "sg:orig_category":"Handels-H\u00e4user U Gesellschaften",
    "sg:postcode":"6005",
    "sg:province":"Luzern",
    "wof:name":"Alfatrade Gmbh",
    "wof:placetype":"venue"
},
  "geometry": {"coordinates":[8.3275680542,47.0372085571],"type":"Point"}
}