{
  "type": "Feature",
  "properties": {
    "iso:country":"CH",
    "sg:address":"M\u00fcnchhaldenstrasse 19",
    "sg:city":"Z\u00fcrich",
    "sg:orig_category":"Gymnastik U Fitnesszentren",
    "sg:phone":"+41 17131022",
    "sg:postcode":"8008",
    "sg:province":"Z\u00fcrich",
    "wof:name":"Fitissimo Fitness-center Im Tennis-& Squash Center Sihltal",
    "wof:placetype":"venue"
},
  "geometry": {"coordinates":[8.5419101715,47.2911300659],"type":"Point"}
}