{
  "type": "Feature",
  "properties": {
    "addr:full":"Wiesenstrasse 18 Z\u00fcrich Z\u00fcrich 8008",
    "addr:housenumber":"18",
    "addr:postcode":"8008",
    "addr:street":"Wiesenstrasse",
    "iso:country":"CH",
    "sg:address":"Wiesenstrasse 18",
    "sg:city":"Z\u00fcrich",
    "sg:orig_category":"Arztpraxen",
    "sg:phone":"+41 13820141",
    "sg:postcode":"8008",
    "sg:province":"Z\u00fcrich",
    "wof:name":"Dr.med. Vlado Muzar Spezialarzt Fmh",
    "wof:placetype":"venue"
},
  "geometry": {"coordinates":[8.553078,47.362316],"type":"Point"}
}