{
  "type": "Feature",
  "properties": {
    "iso:country":"CH",
    "sg:address":"Gotthardstrasse 21 8002 Z\u00fcrich. Postfach",
    "sg:city":"Z\u00fcrich",
    "sg:orig_category":"Sonstiges Versicherungsgewerbe",
    "sg:postcode":"8001",
    "sg:province":"Z\u00fcrich",
    "wof:name":"Elvia Leben, Generalagentur Herzog Robert",
    "wof:placetype":"venue"
},
  "geometry": {"coordinates":[8.5367679596,47.3658905029],"type":"Point"}
}