{
  "type": "Feature",
  "properties": {
    "addr:full":"Motorenstrasse 100 Wetzikon Z\u00fcrich 8620",
    "addr:housenumber":"100",
    "addr:postcode":"8620",
    "addr:street":"Motorenstrasse",
    "iso:country":"CH",
    "sg:address":"Motorenstrasse 100",
    "sg:city":"Wetzikon",
    "sg:orig_category":"Cnc Cutting, Cnc Chip Removal",
    "sg:phone":"+41 19313400",
    "sg:postcode":"8620",
    "sg:province":"Z\u00fcrich",
    "wof:name":"Unimec Fabrikations Ag",
    "wof:placetype":"venue"
},
  "geometry": {"coordinates":[8.793551,47.332329],"type":"Point"}
}