{
  "type": "Feature",
  "properties": {
    "iso:country":"CH",
    "sg:address":"Rue De L'ouriette 129",
    "sg:city":"Aubonne",
    "sg:orig_category":"Architektur U Ingenieurb\u00fcros Solarenergieanlagen and Solarzellen Herstellung",
    "sg:phone":"+41 21 821 22 80",
    "sg:postcode":"1170",
    "sg:province":"Vaud",
    "wof:name":"Solaronix Sa",
    "wof:placetype":"venue"
},
  "geometry": {"coordinates":[6.307631,46.508732],"type":"Point"}
}