{
  "type": "Feature",
  "properties": {
    "iso:country":"CH",
    "sg:address":"Winterhaldenstrasse 7",
    "sg:city":"Heimberg",
    "sg:orig_category":"Detailhandel mit M\u00f6beln Detailhandel mit M\u00f6beln U Haushaltsgegenst\u00e4nden",
    "sg:phone":"+41 33 437 99 27",
    "sg:postcode":"3627",
    "sg:province":"Bern",
    "wof:name":"Sismo M\u00f6bel Ag Heimberg",
    "wof:placetype":"venue"
},
  "geometry": {"coordinates":[7.6027231216,46.7979621887],"type":"Point"}
}