{
  "type": "Feature",
  "properties": {
    "iso:country":"CH",
    "sg:address":"Saurenbachstrasse 32",
    "sg:city":"M\u00e4nnedorf",
    "sg:orig_category":"Elektroinstallation",
    "sg:phone":"+41 21 903 15 04",
    "sg:postcode":"8708",
    "sg:province":"Z\u00fcrich",
    "wof:name":"Stucki Fr\u00e8res",
    "wof:placetype":"venue"
},
  "geometry": {"coordinates":[6.755589962,46.5689620972],"type":"Point"}
}