{
  "type": "Feature",
  "properties": {
    "iso:country":"CH",
    "sg:address":"Hauptstrasse 3920 Zermatt. Postfach 412",
    "sg:city":"Zermatt",
    "sg:orig_category":"Unclassifiable Establishments",
    "sg:postcode":"3920",
    "sg:province":"Valais",
    "wof:name":"Hotel B\u00e4ren Ringgenberg Gmbh",
    "wof:placetype":"venue"
},
  "geometry": {"coordinates":[7.8832502365,46.6986885071],"type":"Point"}
}