{
  "type": "Feature",
  "properties": {
    "iso:country":"CH",
    "sg:address":"Rizlina",
    "sg:city":"Triesenberg",
    "sg:classifiers":[
        {
            "category":"Restaurant",
            "type":"Food & Drink"
        }
    ],
    "sg:postcode":"9497",
    "wof:name":"Berggasthaus Rizlina",
    "wof:placetype":"venue"
},
  "geometry": {"coordinates":[9.5522871017,47.1203155518],"type":"Point"}
}