{
  "type": "Feature",
  "properties": {
    "iso:country":"CH",
    "sg:address":"Bahnhofstrasse 29",
    "sg:city":"Fehraltorf",
    "sg:orig_category":"Detailhandel mit Waren verschiedener Art, Hauptrichtung Nahrungsmittel",
    "sg:phone":"+41 19551454",
    "sg:postcode":"8320",
    "sg:province":"Z\u00fcrich",
    "wof:name":"Migros-markt",
    "wof:placetype":"venue"
},
  "geometry": {"coordinates":[8.7513141632,47.3856468201],"type":"Point"}
}