{
  "type": "Feature",
  "properties": {
    "iso:country":"CH",
    "sg:address":"Seidenhofstrasse 5",
    "sg:city":"Lucerne",
    "sg:classifiers":[
        {
            "category":"Travel",
            "subcategory":"Travel Agent",
            "type":"Entertainment"
        }
    ],
    "sg:postcode":"6002",
    "sg:province":"Luzern",
    "wof:name":"Best Western Hotel Merian Am Rhein",
    "wof:placetype":"venue"
},
  "geometry": {"coordinates":[7.5912289619,47.5607070923],"type":"Point"}
}