{
  "type": "Feature",
  "properties": {
    "iso:country":"CH",
    "sg:address":"Ruchweid 9",
    "sg:city":"Oberlunkhofen",
    "sg:orig_category":"Elektro- and elektronische Maschinen Grosshandel",
    "sg:phone":"+41 21 971 14 00",
    "sg:postcode":"8917",
    "sg:province":"Aargau",
    "wof:name":"Akermann Components Sa",
    "wof:placetype":"venue"
},
  "geometry": {"coordinates":[6.8568320274,46.4578323364],"type":"Point"}
}