{
  "type": "Feature",
  "properties": {
    "iso:country":"CH",
    "sg:address":"Route De B\u00e2le",
    "sg:city":"Soyhi\u00e8res",
    "sg:classifiers":[
        {
            "category":"Bars & Pubs",
            "type":"Food & Drink"
        }
    ],
    "sg:phone":"+41 62 822 58 40",
    "sg:postcode":"2805",
    "sg:province":"Jura",
    "sg:tags":[
        "restaurant"
    ],
    "wof:name":"Cult-caf\u00e9 Sonnenhof",
    "wof:placetype":"venue"
},
  "geometry": {"coordinates":[8.063772,47.3899],"type":"Point"}
}