{
  "type": "Feature",
  "properties": {
    "iso:country":"CH",
    "sg:address":"Chemin De La Planchette 8a",
    "sg:city":"Aigle",
    "sg:orig_category":"Physiotherapie",
    "sg:phone":"+41 71 244 73 76",
    "sg:postcode":"1860",
    "sg:province":"Vaud",
    "wof:name":"Rose-marie Raschle Physikalische Therapie",
    "wof:placetype":"venue"
},
  "geometry": {"coordinates":[9.3895711899,47.4372520447],"type":"Point"}
}