{
  "type": "Feature",
  "properties": {
    "iso:country":"CH",
    "sg:address":"Fellenbergstrasse 218",
    "sg:city":"Z\u00fcrich",
    "sg:orig_category":"Erschliessung von Grundst\u00fccken",
    "sg:phone":"+41 14011230",
    "sg:postcode":"8047",
    "sg:province":"Z\u00fcrich",
    "wof:name":"Gemeinn\u00fctzige Baugenossenschaft Limmattal",
    "wof:placetype":"venue"
},
  "geometry": {"coordinates":[8.4972820282,47.3743591309],"type":"Point"}
}