{
  "type": "Feature",
  "properties": {
    "iso:country":"CH",
    "sg:address":"Avenue De Rochettaz 61",
    "sg:city":"Pully",
    "sg:orig_category":"Bauingenieurb\u00fcros allgemein",
    "sg:phone":"+41 27 722 90 20",
    "sg:postcode":"1009",
    "sg:province":"Vaud",
    "wof:name":"Jean-claude Huber Bureau D'ing\u00e9nieurs",
    "wof:placetype":"venue"
},
  "geometry": {"coordinates":[7.078447,46.105595],"type":"Point"}
}