{
  "type": "Feature",
  "properties": {
    "iso:country":"CH",
    "sg:address":"Bahnhofstrasse 21 6300 Zug. Postfach",
    "sg:city":"Zug",
    "sg:orig_category":"Rechtsberatung",
    "sg:postcode":"6304",
    "sg:province":"Zug",
    "wof:name":"Lixtherm Ag",
    "wof:placetype":"venue"
},
  "geometry": {"coordinates":[8.6447219849,47.4118766785],"type":"Point"}
}