{
  "type": "Feature",
  "properties": {
    "addr:full":"Ostermundigenstrasse 60 3006 Bern. Postfach Bern Bern 3005",
    "addr:housenumber":"60",
    "addr:postcode":"3006;postfach;3005",
    "addr:street":"Ostermundigenstrasse",
    "iso:country":"CH",
    "sg:address":"Ostermundigenstrasse 60 3006 Bern. Postfach",
    "sg:city":"Bern",
    "sg:orig_category":"Detailhandel mit Antiquit\u00e4ten U Gebrauchtwaren in Verkaufsr\u00e4umen",
    "sg:postcode":"3005",
    "sg:province":"Bern",
    "wof:name":"Gift-shop & Secondhand Herren V. Gebraucht. Kleider U Geschenke; Handel",
    "wof:placetype":"venue"
},
  "geometry": {"coordinates":[7.471129,46.953304],"type":"Point"}
}