{
  "type": "Feature",
  "properties": {
    "iso:country":"CH",
    "sg:address":"Franzenmattweg 2 6315 Ober\u00e4geri. Postfach",
    "sg:city":"Ober\u00e4geri",
    "sg:orig_category":"Betrieb von Sportanlagen Grosshandel mit Sportartikeln",
    "sg:phone":"+41 41 750 21 74",
    "sg:postcode":"6315",
    "sg:province":"Zug",
    "wof:name":"Fst Freizeit Sport Und Touristik Ag",
    "wof:placetype":"venue"
},
  "geometry": {"coordinates":[8.612237,47.133816],"type":"Point"}
}