{
  "type": "Feature",
  "properties": {
    "iso:country":"CH",
    "sg:address":"Alberich Zwyssigstrasse 28",
    "sg:city":"Wettingen",
    "sg:orig_category":"Kauf U Verkauf von Immobilien auf eigene Rechnung",
    "sg:postcode":"5430",
    "sg:province":"Aargau",
    "wof:name":"Ren\u00e9 Pl\u00fcss Immobilien",
    "wof:placetype":"venue"
},
  "geometry": {"coordinates":[8.3207759857,47.4615631104],"type":"Point"}
}