{
  "type": "Feature",
  "properties": {
    "iso:country":"CH",
    "sg:address":"Rathaus 8500 Frauenfeld. Postfach",
    "sg:city":"Frauenfeld",
    "sg:orig_category":"Landesverteidigung, Sozialversicherung \u00d6ffentliche Verwaltung",
    "sg:phone":"+41 52 724 52 73",
    "sg:postcode":"8501",
    "sg:province":"Thurgau",
    "wof:name":"Zivilschutzstelle Stadt Frauenfeld",
    "wof:placetype":"venue"
},
  "geometry": {"coordinates":[8.8979101181,47.5553817749],"type":"Point"}
}