{
  "type": "Feature",
  "properties": {
    "iso:country":"CH",
    "sg:address":"L\u00e4ngst\u00e4g 6",
    "sg:city":"Sursee",
    "sg:orig_category":"Rechtsberatung Unternehmensberatung",
    "sg:phone":"+41 41 921 01 21",
    "sg:postcode":"6210",
    "sg:province":"Luzern",
    "wof:name":"Hss H\u00e4fliger Steiner Schiess",
    "wof:placetype":"venue"
},
  "geometry": {"coordinates":[8.1084470749,47.1729774475],"type":"Point"}
}