{
  "type": "Feature",
  "properties": {
    "iso:country":"CH",
    "sg:address":"Herrenfeld",
    "sg:city":"Maienfeld",
    "sg:orig_category":"Architekturb\u00fcros",
    "sg:phone":"+41 81 300 44 88",
    "sg:postcode":"7304",
    "sg:province":"Graubunden",
    "wof:name":"Hans Rudolf Matzinger Architekturb\u00fcro",
    "wof:placetype":"venue"
},
  "geometry": {"coordinates":[9.53224,47.006863],"type":"Point"}
}