{
  "type": "Feature",
  "properties": {
    "iso:country":"CH",
    "sg:address":"Via Navesco 12",
    "sg:city":"Savosa",
    "sg:orig_category":"Instandhaltung U Reparatur von Automobilen",
    "sg:phone":"+41 91 966 60 21",
    "sg:postcode":"6942",
    "sg:province":"Ticino",
    "wof:name":"Claudio Masciadri Elettrauto",
    "wof:placetype":"venue"
},
  "geometry": {"coordinates":[8.9488115311,46.0207099915],"type":"Point"}
}