{
  "type": "Feature",
  "properties": {
    "iso:country":"CH",
    "sg:address":"Place De Gottefrey",
    "sg:city":"Saxon",
    "sg:orig_category":"Detailhandel mit Uhren U Schmuck Fachdetailhandel in Verkaufsr\u00e4umen",
    "sg:phone":"+41 27 744 19 73",
    "sg:postcode":"1907",
    "sg:province":"Valais",
    "wof:name":"Andr\u00e9 Rhoner Horlogerie-bijouterie",
    "wof:placetype":"venue"
},
  "geometry": {"coordinates":[7.1738901138,46.1487731934],"type":"Point"}
}