{
  "type": "Feature",
  "properties": {
    "iso:country":"CH",
    "sg:address":"3718",
    "sg:city":"Kandersteg",
    "sg:orig_category":"Personenbef\u00f6rderung im Linienverkehr zu Land",
    "sg:phone":"+41 33 675 11 18",
    "sg:postcode":"3718",
    "sg:province":"Bern",
    "wof:name":"Sesselbahn Kandersteg-oeschinen Ag",
    "wof:placetype":"venue"
},
  "geometry": {"coordinates":[7.6730470657,46.4949836731],"type":"Point"}
}