{
  "type": "Feature",
  "properties": {
    "iso:country":"CH",
    "sg:address":"Consiglio Mezzano Via 37",
    "sg:city":"Orselina",
    "sg:orig_category":"Institutionen des Sozialwesens ohne Beherbergung",
    "sg:postcode":"6644",
    "sg:province":"Ticino",
    "wof:name":"Fondazione Rafaela",
    "wof:placetype":"venue"
},
  "geometry": {"coordinates":[8.7996692657,46.1772499084],"type":"Point"}
}