{
  "type": "Feature",
  "properties": {
    "iso:country":"CH",
    "sg:address":"Industriestrasse 9",
    "sg:city":"St\u00e4fa",
    "sg:orig_category":"Vermietung U Verpachtung von eigenen Immobilien",
    "sg:phone":"+41 91 683 50 24",
    "sg:postcode":"8712",
    "sg:province":"Z\u00fcrich",
    "wof:name":"Ghitello Sa",
    "wof:placetype":"venue"
},
  "geometry": {"coordinates":[9.0153245926,45.8462257385],"type":"Point"}
}