{
  "type": "Feature",
  "properties": {
    "iso:country":"CH",
    "sg:address":"Rue De L'ecluse 32",
    "sg:city":"Neuch\u00e2tel",
    "sg:classifiers":[
        {
            "category":"Restaurant",
            "type":"Food & Drink"
        }
    ],
    "sg:phone":"+41 32 721 36 21",
    "sg:postcode":"2000",
    "sg:province":"Neuch\u00e2tel",
    "wof:name":"Caf\u00e9-restaurant La Gondola",
    "wof:placetype":"venue"
},
  "geometry": {"coordinates":[6.9258799553,46.9928359985],"type":"Point"}
}