{
  "type": "Feature",
  "properties": {
    "iso:country":"CH",
    "sg:address":"Ostring 36",
    "sg:city":"Regensdorf",
    "sg:orig_category":"Herstellung von sonstigen elektrischen Ausr\u00fcstungen",
    "sg:postcode":"8105",
    "sg:province":"Z\u00fcrich",
    "wof:name":"Primelec, Florin D. Elektronische Ger\u00e4te; Entwicklung U. Herstellung",
    "wof:placetype":"venue"
},
  "geometry": {"coordinates":[8.4697132111,47.4302024841],"type":"Point"}
}