{
  "type": "Feature",
  "properties": {
    "addr:full":"T\u00f6distrasse 48 Z\u00fcrich Z\u00fcrich 8002",
    "addr:housenumber":"48",
    "addr:postcode":"8002",
    "addr:street":"Toedistrasse",
    "iso:country":"CH",
    "sg:address":"T\u00f6distrasse 48",
    "sg:city":"Z\u00fcrich",
    "sg:orig_category":"Allgemeiner Hoch U Tiefbau",
    "sg:postcode":"8002",
    "sg:province":"Z\u00fcrich",
    "wof:name":"Mb Messmer + Bernold Immobilien Ag",
    "wof:placetype":"venue"
},
  "geometry": {"coordinates":[8.533875,47.367531],"type":"Point"}
}