{
  "type": "Feature",
  "properties": {
    "iso:country":"CH",
    "sg:address":"1914",
    "sg:city":"Is\u00e9rables",
    "sg:orig_category":"Vereine Musik/Blasmusik",
    "sg:phone":"+41 27 776 23 77",
    "sg:postcode":"1914",
    "sg:province":"Valais",
    "wof:name":"St\u00e9 De Musique L'avenir",
    "wof:placetype":"venue"
},
  "geometry": {"coordinates":[7.2124481201,46.0804595947],"type":"Point"}
}