{
  "type": "Feature",
  "properties": {
    "iso:country":"CH",
    "sg:address":"Vogelacherstr. 440",
    "sg:city":"Niederweningen",
    "sg:orig_category":"Herstellung von Schl\u00f6ssern U Beschl\u00e4gen",
    "sg:postcode":"8166",
    "sg:province":"Z\u00fcrich",
    "wof:name":"Egger Roger",
    "wof:placetype":"venue"
},
  "geometry": {"coordinates":[8.3743000031,47.5114784241],"type":"Point"}
}