{
  "type": "Feature",
  "properties": {
    "iso:country":"CH",
    "sg:address":"Grundstrasse 12",
    "sg:city":"Rotkreuz",
    "sg:orig_category":"Buchf\u00fchrung Wirtschaftspr\u00fcfung, Steuerberatung U Treuhand",
    "sg:phone":"+41 81 832 18 68",
    "sg:postcode":"6343",
    "sg:province":"Zug",
    "wof:name":"Rohrer Gebhard Treuhand Und Finanzberatung Verm\u00f6gensverwaltung U. Anlageberatung Usw",
    "wof:placetype":"venue"
},
  "geometry": {"coordinates":[9.833499,46.489895],"type":"Point"}
}