{
  "type": "Feature",
  "properties": {
    "iso:country":"CH",
    "sg:address":"L\u00e4ngenbergstrasse 13",
    "sg:city":"Schaffhausen",
    "sg:orig_category":"Handelsvermittlung U Grosshandel mit Automobilteilen U Zubeh\u00f6r",
    "sg:phone":"+41 52 644 57 10",
    "sg:postcode":"8200",
    "sg:province":"Schaffhausen",
    "wof:name":"Derendinger Ag Autobestandteile Autozubeh\u00f6r",
    "wof:placetype":"venue"
},
  "geometry": {"coordinates":[8.6281433105,47.7277259827],"type":"Point"}
}