{
  "type": "Feature",
  "properties": {
    "iso:country":"CH",
    "sg:address":"Kornweg 4",
    "sg:city":"Mellingen",
    "sg:orig_category":"Grosshandel mit Blumen U Pflanzen",
    "sg:phone":"+41 56 491 30 61",
    "sg:postcode":"5507",
    "sg:province":"Aargau",
    "wof:name":"Grato Gmbh",
    "wof:placetype":"venue"
},
  "geometry": {"coordinates":[8.2719955444,47.4113311768],"type":"Point"}
}