{
  "type": "Feature",
  "properties": {
    "iso:country":"CH",
    "sg:address":"Avenue Des Cerisiers 8",
    "sg:city":"Crissier",
    "sg:orig_category":"Elektroinstallation Sonstiger Grosshandel",
    "sg:phone":"+41 21 634 60 60",
    "sg:postcode":"1023",
    "sg:province":"Vaud",
    "wof:name":"Finivol Assistance",
    "wof:placetype":"venue"
},
  "geometry": {"coordinates":[6.5788850784,46.5400657654],"type":"Point"}
}