{
  "type": "Feature",
  "properties": {
    "iso:country":"CH",
    "sg:address":"Caroline Chemin De La 18a 1213 Petit-lancy. Postfach",
    "sg:city":"Petit-lancy",
    "sg:orig_category":"Zeitschriftenverlag Zeitungsdruck",
    "sg:phone":"+41 22 342 23 31",
    "sg:postcode":"1213",
    "sg:province":"Gen\u00e8ve",
    "wof:name":"Imprimerie Dumaret & Cie Sa",
    "wof:placetype":"venue"
},
  "geometry": {"coordinates":[6.142428875,46.1850395203],"type":"Point"}
}