{
  "type": "Feature",
  "properties": {
    "iso:country":"CH",
    "sg:address":"Hauptstrasse 34",
    "sg:city":"Glarus",
    "sg:orig_category":"Finanzierungsinstitutionen",
    "sg:postcode":"8750",
    "sg:province":"Glarus",
    "wof:name":"Lust & Christensen Investment Gmbh",
    "wof:placetype":"venue"
},
  "geometry": {"coordinates":[9.067817688,47.0403556824],"type":"Point"}
}