{
  "type": "Feature",
  "properties": {
    "iso:country":"CH",
    "sg:address":"Oberhasli Lu",
    "sg:city":"Emmen",
    "sg:orig_category":"Verwertung von Milch",
    "sg:postcode":"6032",
    "sg:province":"Luzern",
    "wof:name":"K\u00e4sereigenossenschaft Hasum",
    "wof:placetype":"venue"
},
  "geometry": {"coordinates":[9.3020200729,47.4868774414],"type":"Point"}
}