{
  "type": "Feature",
  "properties": {
    "iso:country":"CH",
    "sg:address":"Beim Bahnhof",
    "sg:city":"Hettlingen",
    "sg:orig_category":"Black Colours",
    "sg:phone":"+41 52 316 17 33",
    "sg:postcode":"8442",
    "sg:province":"Z\u00fcrich",
    "wof:name":"Epple Druckfarben Gmbh",
    "wof:placetype":"venue"
},
  "geometry": {"coordinates":[8.694976,47.545193],"type":"Point"}
}