{
  "type": "Feature",
  "properties": {
    "iso:country":"CH",
    "sg:address":"Plazza Da Cum\u00fcn",
    "sg:city":"Poschiavo",
    "sg:orig_category":"RESTAURANTS: TEA-ROOMS",
    "sg:phone":"+41 81 844 01 73",
    "sg:postcode":"7742",
    "sg:province":"Graubunden",
    "wof:name":"Albergo Albrici",
    "wof:placetype":"venue"
},
  "geometry": {"coordinates":[10.0579719543,46.3266944885],"type":"Point"}
}