{
  "type": "Feature",
  "properties": {
    "iso:country":"CH",
    "sg:address":"4432",
    "sg:city":"Lampenberg",
    "sg:classifiers":[
        {
            "category":"Restaurant",
            "type":"Food & Drink"
        }
    ],
    "sg:phone":"+41 61 951 10 26",
    "sg:postcode":"4432",
    "sg:province":"Basel-Landschaft",
    "wof:name":"Restaurant Sch\u00fctzen",
    "wof:placetype":"venue"
},
  "geometry": {"coordinates":[7.7530398369,47.4284095764],"type":"Point"}
}