{
  "type": "Feature",
  "properties": {
    "iso:country":"CH",
    "sg:address":"8245",
    "sg:city":"Feuerthalen",
    "sg:orig_category":"Gesundheitswesen",
    "sg:postcode":"8245",
    "sg:province":"Z\u00fcrich",
    "wof:name":"24 H Pflege Gmbh",
    "wof:placetype":"venue"
},
  "geometry": {"coordinates":[8.6455898285,47.6896018982],"type":"Point"}
}