{
  "type": "Feature",
  "properties": {
    "iso:country":"CH",
    "sg:address":"Reservatstrasse 1",
    "sg:city":"Dietikon",
    "sg:orig_category":"Instandhaltung U Reparatur von Automobilen",
    "sg:phone":"+41 17438080",
    "sg:postcode":"8953",
    "sg:province":"Z\u00fcrich",
    "wof:name":"Vetterli Nutzfahrzeuge Dietikon Gmbh",
    "wof:placetype":"venue"
},
  "geometry": {"coordinates":[8.4012317657,47.4143638611],"type":"Point"}
}