{
  "type": "Feature",
  "properties": {
    "iso:country":"CH",
    "sg:address":"Birmannsgasse 1 4055 Basel. Postfach",
    "sg:city":"Basel",
    "sg:orig_category":"K\u00fcnstlerische U schriftstellerische T\u00e4tigkeiten U Darbietungen",
    "sg:phone":"+41 61 261 35 14",
    "sg:postcode":"4051",
    "sg:province":"Basel-Stadt",
    "wof:name":"Verein Gute Schriften",
    "wof:placetype":"venue"
},
  "geometry": {"coordinates":[7.579349041,47.5582046509],"type":"Point"}
}