{
  "type": "Feature",
  "properties": {
    "iso:country":"CH",
    "sg:address":"Vierlinden",
    "sg:city":"Unterb\u00f6zberg",
    "sg:orig_category":"Arztpraxen",
    "sg:phone":"+41 56 441 35 17",
    "sg:postcode":"5224",
    "sg:province":"Aargau",
    "wof:name":"Dr.med.g\u00fcnther Sandfuchs Arzt F\u00fcr Allgemeine Medizin",
    "wof:placetype":"venue"
},
  "geometry": {"coordinates":[8.15872,47.479542],"type":"Point"}
}