{
  "type": "Feature",
  "properties": {
    "iso:country":"CH",
    "sg:address":"Sennhofweg 12 4852 Rothrist. Postfach",
    "sg:city":"Rothrist",
    "sg:orig_category":"Wohnheime",
    "sg:postcode":"4852",
    "sg:province":"Aargau",
    "wof:name":"Verein F\u00fcr Alterswohnungen Der Gemeinde Rothrist",
    "wof:placetype":"venue"
},
  "geometry": {"coordinates":[7.8911042213,47.3038444519],"type":"Point"}
}