{
  "type": "Feature",
  "properties": {
    "addr:full":"Hegenheimermattweg 65 Allschwil Basel-Landschaft 4123",
    "addr:housenumber":"65",
    "addr:postcode":"4123",
    "addr:street":"Hegenheimermattweg",
    "iso:country":"CH",
    "sg:address":"Hegenheimermattweg 65",
    "sg:city":"Allschwil",
    "sg:orig_category":"Architektur U Ingenieurb\u00fcros",
    "sg:phone":"+41 71 388 11 00",
    "sg:postcode":"4123",
    "sg:province":"Basel-Landschaft",
    "wof:name":"Eigenmann Engineering Ag",
    "wof:placetype":"venue"
},
  "geometry": {"coordinates":[9.255148,47.414398],"type":"Point"}
}