{
  "type": "Feature",
  "properties": {
    "addr:full":"Interlakenstrasse 75 Faulensee Bern 3705",
    "addr:housenumber":"75",
    "addr:postcode":"3705",
    "addr:street":"Interlakenstrasse",
    "iso:country":"CH",
    "sg:address":"Interlakenstrasse 75",
    "sg:city":"Faulensee",
    "sg:orig_category":"Detailhandel mit Brot, Back U S\u00fcsswaren Detailhandel mit Waren verschiedener Art, Hauptrichtung Nahr",
    "sg:phone":"+41 31 809 02 37",
    "sg:postcode":"3705",
    "sg:province":"Bern",
    "wof:name":"Ernst Herren",
    "wof:placetype":"venue"
},
  "geometry": {"coordinates":[7.448586,46.781631],"type":"Point"}
}