{
  "type": "Feature",
  "properties": {
    "iso:country":"CH",
    "sg:address":"Croisettes Chemin Des 15",
    "sg:city":"Epalinges",
    "sg:orig_category":"Elektroinstallation",
    "sg:postcode":"1066",
    "sg:province":"Vaud",
    "wof:name":"Gavillet G\u00e9rald",
    "wof:placetype":"venue"
},
  "geometry": {"coordinates":[6.6602940559,46.5451049805],"type":"Point"}
}