{
  "type": "Feature",
  "properties": {
    "iso:country":"CH",
    "sg:address":"Emmentalstrasse 19",
    "sg:city":"Oberburg",
    "sg:orig_category":"Mechanische Werkst\u00e4tten",
    "sg:phone":"+41 34 422 65 50",
    "sg:postcode":"3414",
    "sg:province":"Bern",
    "wof:name":"Kurt Marti Mechanische Werkst\u00e4tte",
    "wof:placetype":"venue"
},
  "geometry": {"coordinates":[7.6268649101,47.0384788513],"type":"Point"}
}