{
  "type": "Feature",
  "properties": {
    "iso:country":"CH",
    "sg:address":"Rubigenstrasse 95a",
    "sg:city":"Worb",
    "sg:orig_category":"Grosshandel mit elektrischen Haushaltsger\u00e4ten",
    "sg:phone":"+41 31 981 02 55",
    "sg:postcode":"3076",
    "sg:province":"Bern",
    "wof:name":"Novelan Ag",
    "wof:placetype":"venue"
},
  "geometry": {"coordinates":[7.3778400421,46.9255905151],"type":"Point"}
}