{
  "type": "Feature",
  "properties": {
    "iso:country":"CH",
    "sg:address":"7078",
    "sg:city":"Lenzerheide/lai",
    "sg:orig_category":"Sportvereine Ballsport Fussball",
    "sg:phone":"+41 61 401 41 62",
    "sg:postcode":"7078",
    "sg:province":"Graubunden",
    "wof:name":"Fc Oberwil",
    "wof:placetype":"venue"
},
  "geometry": {"coordinates":[7.5535798073,47.5189781189],"type":"Point"}
}