{
  "type": "Feature",
  "properties": {
    "iso:country":"CH",
    "sg:address":"Via Entadavos",
    "sg:city":"Ruschein",
    "sg:orig_category":"Zimmerei, Ingenieurholzbau",
    "sg:phone":"+41 34 445 02 76",
    "sg:postcode":"7154",
    "sg:province":"Graubunden",
    "wof:name":"Daniel K\u00e4mpfer Zimmerei-& Parkettarbeiten",
    "wof:placetype":"venue"
},
  "geometry": {"coordinates":[7.568983078,47.0876655579],"type":"Point"}
}