{
  "type": "Feature",
  "properties": {
    "iso:country":"CH",
    "sg:address":"Via Santo Stefano 1",
    "sg:city":"Muralto",
    "sg:orig_category":"Arztpraxen",
    "sg:phone":"+41 91 743 35 42",
    "sg:postcode":"6600",
    "sg:province":"Ticino",
    "wof:name":"Dott.med.thomas Lehmann Medico Generico Fmh",
    "wof:placetype":"venue"
},
  "geometry": {"coordinates":[8.804383,46.173119],"type":"Point"}
}