{
  "type": "Feature",
  "properties": {
    "iso:country":"CH",
    "sg:address":"3632",
    "sg:city":"Niederstocken",
    "sg:orig_category":"Landesverteidigung, Sozialversicherung \u00d6ffentliche Verwaltung",
    "sg:phone":"+41 33 341 12 12",
    "sg:postcode":"3632",
    "sg:province":"Bern",
    "wof:name":"Zivilschutzstelle Niederstocken",
    "wof:placetype":"venue"
},
  "geometry": {"coordinates":[7.5628299713,46.7058601379],"type":"Point"}
}