{
  "type": "Feature",
  "properties": {
    "iso:country":"CH",
    "sg:address":"Rue Du Lac 48",
    "sg:city":"Yverdon-les-bains",
    "sg:classifiers":[
        {
            "category":"Manufacturing",
            "subcategory":"Glass & Minerals",
            "type":"Manufacturing & Wholesale Goods"
        }
    ],
    "sg:phone":"+41 24 425 22 60",
    "sg:postcode":"1400",
    "sg:province":"Vaud",
    "sg:tags":[
        "cleaning",
        "agent"
    ],
    "wof:name":"Schwarz-gloor Opticien Sa",
    "wof:placetype":"venue"
},
  "geometry": {"coordinates":[6.638271,46.780369],"type":"Point"}
}