{
  "type": "Feature",
  "properties": {
    "iso:country":"CH",
    "sg:address":"Rheinstr. 121",
    "sg:city":"Liestal",
    "sg:classifiers":[
        {
            "category":"Building & Trades",
            "subcategory":"Construction",
            "type":"Services"
        }
    ],
    "sg:phone":"+41 61 905 11 11",
    "sg:postcode":"4410",
    "sg:province":"Basel-Landschaft",
    "sg:tags":[
        "work",
        "public"
    ],
    "wof:name":"Ziegler Ag",
    "wof:placetype":"venue"
},
  "geometry": {"coordinates":[7.721806,47.497688],"type":"Point"}
}