{
  "type": "Feature",
  "properties": {
    "iso:country":"CH",
    "sg:address":"Im Langhag 11",
    "sg:city":"Effretikon",
    "sg:orig_category":"Handel mit Automobilen Herstellung von sonstigen elektrischen Ausr\u00fcstungen",
    "sg:phone":"+41 31 381 61 61",
    "sg:postcode":"8307",
    "sg:province":"Z\u00fcrich",
    "wof:name":"Walker & Cie. Ag",
    "wof:placetype":"venue"
},
  "geometry": {"coordinates":[7.4322299957,46.9442024231],"type":"Point"}
}