{
  "type": "Feature",
  "properties": {
    "iso:country":"CH",
    "sg:address":"Rue Du Grand-pont 2bis 1003 Lausanne. Postfach",
    "sg:city":"Lausanne",
    "sg:orig_category":"Allgemeiner Hoch U Tiefbau Allgemeiner Hochbau",
    "sg:phone":"+41 21 320 13 61",
    "sg:postcode":"1002",
    "sg:province":"Vaud",
    "wof:name":"Pizzera & Poletti Sa",
    "wof:placetype":"venue"
},
  "geometry": {"coordinates":[6.631956,46.520081],"type":"Point"}
}