{
  "type": "Feature",
  "properties": {
    "iso:country":"CH",
    "sg:address":"Via Dei Paoli 36",
    "sg:city":"Minusio",
    "sg:orig_category":"Sonderschulen Wohnheime f\u00fcr Kinder U Jugendliche",
    "sg:phone":"+41 91 646 12 42",
    "sg:postcode":"6648",
    "sg:province":"Ticino",
    "wof:name":"Istituto St.angelo",
    "wof:placetype":"venue"
},
  "geometry": {"coordinates":[9.0029449463,45.8624382019],"type":"Point"}
}