{
  "type": "Feature",
  "properties": {
    "iso:country":"CH",
    "sg:address":"Oezlige 2 6215 Berom\u00fcnster. Postfach",
    "sg:city":"Berom\u00fcnster",
    "sg:orig_category":"Softwareentwicklung U beratung",
    "sg:postcode":"6215",
    "sg:province":"Luzern",
    "wof:name":"Ineichen Advice Gmbh Computer Hard- U. Software; Handel. Beratung In Versicherungs- U. Vorsorgefragen Usw",
    "wof:placetype":"venue"
},
  "geometry": {"coordinates":[8.1944198608,47.2040100098],"type":"Point"}
}