{
  "type": "Feature",
  "properties": {
    "iso:country":"CH",
    "sg:address":"Bethlehemstrasse 110",
    "sg:city":"Bern",
    "sg:orig_category":"Detailhandel mit Waren verschiedener Art, Hauptrichtung Nahrungsmittel",
    "sg:phone":"+41 31 992 42 30",
    "sg:postcode":"3018",
    "sg:province":"Bern",
    "wof:name":"Migros-markt St\u00f6ckacker",
    "wof:placetype":"venue"
},
  "geometry": {"coordinates":[7.399600029,46.944065094],"type":"Point"}
}