{
  "type": "Feature",
  "properties": {
    "iso:country":"CH",
    "sg:address":"Z.industrielle En Budron B1",
    "sg:city":"Mont-sur-lausanne",
    "sg:orig_category":"Bauschreinerei Herstellung von Konstruktionsteilen, Fertigbauteilen U Ausbauelementen aus Holz",
    "sg:phone":"+41 21 652 60 90",
    "sg:postcode":"1052",
    "sg:province":"Vaud",
    "wof:name":"Golay J.",
    "wof:placetype":"venue"
},
  "geometry": {"coordinates":[6.635395,46.556896],"type":"Point"}
}