{
  "type": "Feature",
  "properties": {
    "iso:country":"CH",
    "sg:address":"Wilen 1077",
    "sg:city":"Walzenhausen",
    "sg:orig_category":"Naturheil\u00e4rzte and Heilpraktiker",
    "sg:phone":"+41 71 888 10 73",
    "sg:postcode":"9428",
    "sg:province":"Appenzell Ausserrhoden",
    "wof:name":"Werner Sampl Naturarzt",
    "wof:placetype":"venue"
},
  "geometry": {"coordinates":[9.6202058792,47.4409484863],"type":"Point"}
}