{
  "type": "Feature",
  "properties": {
    "iso:country":"CH",
    "sg:address":"Wiesenstrasse 29",
    "sg:city":"Dietikon",
    "sg:orig_category":"Sonstiger Grosshandel",
    "sg:postcode":"8953",
    "sg:province":"Z\u00fcrich",
    "wof:name":"Mls Schlegel S\u00e0rl",
    "wof:placetype":"venue"
},
  "geometry": {"coordinates":[8.4206762314,47.3957824707],"type":"Point"}
}