{
  "type": "Feature",
  "properties": {
    "iso:country":"CH",
    "sg:address":"Alpenstrasse 90",
    "sg:city":"Zollikofen",
    "sg:orig_category":"Finanzierungsinstitutionen",
    "sg:phone":"+41 31 914 16 66",
    "sg:postcode":"3052",
    "sg:province":"Bern",
    "wof:name":"Constantinidis & Co. Fina Trust Finanzdienstleistungen",
    "wof:placetype":"venue"
},
  "geometry": {"coordinates":[7.4401512146,46.9985580444],"type":"Point"}
}