{
  "type": "Feature",
  "properties": {
    "iso:country":"CH",
    "sg:address":"S\u00e4ntisweg 2 8212 Neuhausen. Postfach",
    "sg:city":"Neuhausen",
    "sg:orig_category":"Unclassifiable Establishments",
    "sg:postcode":"8212",
    "sg:province":"Schaffhausen",
    "wof:name":"Cibien Patrick Transporte",
    "wof:placetype":"venue"
},
  "geometry": {"coordinates":[8.6089277267,47.6821784973],"type":"Point"}
}