{
  "type": "Feature",
  "properties": {
    "iso:country":"CH",
    "sg:address":"Aargauerstrasse 12",
    "sg:city":"Berom\u00fcnster",
    "sg:classifiers":[
        {
            "category":"Manufacturing",
            "subcategory":"Printing",
            "type":"Manufacturing & Wholesale Goods"
        }
    ],
    "sg:phone":"+41 41 932 40 50",
    "sg:postcode":"6215",
    "sg:province":"Luzern",
    "sg:tags":[
        "house",
        "book"
    ],
    "wof:name":"Wallimann Druck Und Verlag Ag",
    "wof:placetype":"venue"
},
  "geometry": {"coordinates":[8.191583,47.209038],"type":"Point"}
}