{
  "type": "Feature",
  "properties": {
    "iso:country":"CH",
    "sg:address":"Falkenstrasse 4",
    "sg:city":"Z\u00fcrich",
    "sg:orig_category":"Werbeagenturen Werbegrafikateliers",
    "sg:phone":"+41 61 401 37 00",
    "sg:postcode":"8008",
    "sg:province":"Z\u00fcrich",
    "wof:name":"Km Design M\u00fcller",
    "wof:placetype":"venue"
},
  "geometry": {"coordinates":[7.5587449074,47.5101737976],"type":"Point"}
}