{
  "type": "Feature",
  "properties": {
    "iso:country":"CH",
    "sg:address":"Vordere Gasse 16",
    "sg:city":"Kerzers",
    "sg:orig_category":"Versicherungen Hauptagenturen",
    "sg:phone":"+41 31 755 72 12",
    "sg:postcode":"3210",
    "sg:province":"Fribourg",
    "wof:name":"Z\u00fcrich-versicherungen Hauptagentur Michael M\u00f6hl",
    "wof:placetype":"venue"
},
  "geometry": {"coordinates":[7.1989412308,46.9744682312],"type":"Point"}
}