{
  "type": "Feature",
  "properties": {
    "iso:country":"CH",
    "sg:address":"Chamerstrasse 170",
    "sg:city":"H\u00fcnenberg",
    "sg:orig_category":"Non-Classified Establishments",
    "sg:postcode":"6331",
    "sg:province":"Zug",
    "wof:name":"Gamma Consulting & Catering Ag",
    "wof:placetype":"venue"
},
  "geometry": {"coordinates":[9.8377914429,46.4982910156],"type":"Point"}
}