{
  "type": "Feature",
  "properties": {
    "iso:country":"CH",
    "sg:address":"Gartenstrasse 10",
    "sg:city":"Flums",
    "sg:orig_category":"Offsetdruck",
    "sg:phone":"+41 81 733 41 74",
    "sg:postcode":"8890",
    "sg:province":"St. Gallen",
    "wof:name":"Flumser Drucki",
    "wof:placetype":"venue"
},
  "geometry": {"coordinates":[9.3435087204,47.0937538147],"type":"Point"}
}