{
  "type": "Feature",
  "properties": {
    "iso:country":"CH",
    "sg:address":"Schwandweg 5",
    "sg:city":"Schindellegi",
    "sg:classifiers":[
        {
            "category":"Manufacturing",
            "subcategory":"Tools & Machinery",
            "type":"Manufacturing & Wholesale Goods"
        }
    ],
    "sg:phone":"+41 41 785 20 90",
    "sg:postcode":"8834",
    "sg:province":"Schwyz",
    "sg:tags":[
        "equipment",
        "measurement",
        "-",
        "precision",
        "instrument"
    ],
    "wof:name":"Spiess Elektrizit\u00c4ts-erzeugnisse Ag",
    "wof:placetype":"venue"
},
  "geometry": {"coordinates":[8.7104673386,47.1820259094],"type":"Point"}
}