{
  "type": "Feature",
  "properties": {
    "iso:country":"CH",
    "sg:address":"Kantonsstr.",
    "sg:city":"Sch\u00fcbelbach",
    "sg:orig_category":"Pensionskassen",
    "sg:postcode":"8862",
    "sg:province":"Schwyz",
    "wof:name":"Wohlfahrtsfonds Der Ruoss-kistler E. Ag.",
    "wof:placetype":"venue"
},
  "geometry": {"coordinates":[8.9304103851,47.1734237671],"type":"Point"}
}