{
  "type": "Feature",
  "properties": {
    "iso:country":"CH",
    "sg:address":"Moserstrasse 18",
    "sg:city":"Schaffhausen",
    "sg:orig_category":"RESTAURANTS: TEA-ROOMS",
    "sg:phone":"+41 52 625 19 07",
    "sg:postcode":"8200",
    "sg:province":"Schaffhausen",
    "wof:name":"Pizzeria Pazza",
    "wof:placetype":"venue"
},
  "geometry": {"coordinates":[8.6394309998,47.6953468323],"type":"Point"}
}