{
  "type": "Feature",
  "properties": {
    "addr:full":"Waldibachweg 11 Emmen Luzern 6032",
    "addr:housenumber":"11",
    "addr:postcode":"6032",
    "addr:street":"Waldibachweg",
    "iso:country":"CH",
    "sg:address":"Waldibachweg 11",
    "sg:city":"Emmen",
    "sg:orig_category":"Allgemeiner Hoch U Tiefbau Allgemeiner Hochbau",
    "sg:phone":"+41 41 260 68 78",
    "sg:postcode":"6032",
    "sg:province":"Luzern",
    "wof:name":"Huwiler Erwin Bauunternehmung",
    "wof:placetype":"venue"
},
  "geometry": {"coordinates":[8.318562,47.109657],"type":"Point"}
}