{
  "type": "Feature",
  "properties": {
    "iso:country":"CH",
    "sg:address":"Rte Du Grand-pr\u00e9 26 1700 Fribourg. Postfach",
    "sg:city":"Freiburg",
    "sg:orig_category":"Sonstiger Grosshandel",
    "sg:phone":"+41 26 323 17 71",
    "sg:postcode":"1700",
    "sg:province":"Fribourg",
    "wof:name":"Basons Sa",
    "wof:placetype":"venue"
},
  "geometry": {"coordinates":[7.1388859749,46.7979698181],"type":"Point"}
}