{
  "type": "Feature",
  "properties": {
    "iso:country":"CH",
    "sg:address":"B\u00e4rengasse 23",
    "sg:city":"Zofingen",
    "sg:orig_category":"Aktivit\u00e4ten der Krankenschwestern U Hebammen, Hauspflege",
    "sg:phone":"+41 62 751 19 19",
    "sg:postcode":"4800",
    "sg:province":"Aargau",
    "wof:name":"Verein Spitex Zofingen/m\u00fchlethal",
    "wof:placetype":"venue"
},
  "geometry": {"coordinates":[7.945176,47.290543],"type":"Point"}
}