{
  "type": "Feature",
  "properties": {
    "iso:country":"CH",
    "sg:address":"Terrassenweg",
    "sg:city":"Grindelwald",
    "sg:orig_category":"Detailhandel mit M\u00f6beln U Haushaltsgegenst\u00e4nden",
    "sg:postcode":"3818",
    "sg:province":"Bern",
    "wof:name":"Marmota Ag",
    "wof:placetype":"venue"
},
  "geometry": {"coordinates":[8.0461292267,46.6298942566],"type":"Point"}
}