{
  "type": "Feature",
  "properties": {
    "iso:country":"CH",
    "sg:address":"Bernstrasse 31",
    "sg:city":"Ober\u00f6nz",
    "sg:orig_category":"Elektroinstallation",
    "sg:phone":"+41 62 961 86 46",
    "sg:postcode":"3363",
    "sg:province":"Bern",
    "wof:name":"Rebmann Elektro Ag",
    "wof:placetype":"venue"
},
  "geometry": {"coordinates":[7.6966180801,47.1803817749],"type":"Point"}
}