{
  "type": "Feature",
  "properties": {
    "iso:country":"CH",
    "sg:address":"Haus La Pala Sporz 60 7078 Lenzerheide/lai. Postfach",
    "sg:city":"Lenzerheide/lai",
    "sg:orig_category":"Vermietung U Verpachtung von eigenen Immobilien",
    "sg:postcode":"7078",
    "sg:province":"Graubunden",
    "wof:name":"Gerliane Sa",
    "wof:placetype":"venue"
},
  "geometry": {"coordinates":[9.5578527451,46.7245788574],"type":"Point"}
}