{
  "type": "Feature",
  "properties": {
    "iso:country":"CH",
    "sg:address":"Seidenhofstrasse 14",
    "sg:city":"Luzern",
    "sg:orig_category":"Sonstige mit Sport verbundene T\u00e4tigkeiten Unternehmensberatung",
    "sg:phone":"+41 41 210 52 02",
    "sg:postcode":"6003",
    "sg:province":"Luzern",
    "wof:name":"Jost Interevent Ag",
    "wof:placetype":"venue"
},
  "geometry": {"coordinates":[8.3077402115,47.0495796204],"type":"Point"}
}