{
  "type": "Feature",
  "properties": {
    "addr:full":"Via Lucmagn 88 Disentis/must\u00e9r Graubunden 7180",
    "addr:housenumber":"88",
    "addr:postcode":"7180",
    "addr:street":"Via Lucmagn",
    "iso:country":"CH",
    "sg:address":"Via Lucmagn 88",
    "sg:city":"Disentis/must\u00e9r",
    "sg:orig_category":"Bauschreinerei Glaserei",
    "sg:phone":"+41 81 947 49 26",
    "sg:postcode":"7180",
    "sg:province":"Graubunden",
    "wof:name":"Hubert Deflorin Schreinerei & Glaserei",
    "wof:placetype":"venue"
},
  "geometry": {"coordinates":[8.852871,46.702621],"type":"Point"}
}