{
  "type": "Feature",
  "properties": {
    "iso:country":"CH",
    "sg:address":"Marktgasse 61 3011 Bern. Postfach",
    "sg:city":"Bern",
    "sg:orig_category":"Grosshandel mit Nahrungsmitteln, Getr\u00e4nken U Tabakwaren ohne ausgepr\u00e4gten Schwerpunkt",
    "sg:phone":"+41 41 781 02 02",
    "sg:postcode":"3005",
    "sg:province":"Bern",
    "wof:name":"Hans M\u00fcller Ag, Lebensmittel En Gros",
    "wof:placetype":"venue"
},
  "geometry": {"coordinates":[8.3145179749,47.4047241211],"type":"Point"}
}