{
  "type": "Feature",
  "properties": {
    "iso:country":"CH",
    "sg:address":"En Saugey. 1291 Commugny. Postfach",
    "sg:city":"Commugny",
    "sg:orig_category":"Sonstiger Grosshandel",
    "sg:postcode":"1291",
    "sg:province":"Vaud",
    "wof:name":"Corimpex, Chevalier Petra.",
    "wof:placetype":"venue"
},
  "geometry": {"coordinates":[6.1700701714,46.3143615723],"type":"Point"}
}