{
  "type": "Feature",
  "properties": {
    "iso:country":"CH",
    "sg:address":"Baslerstrasse 66",
    "sg:city":"Trimbach",
    "sg:orig_category":"Grosshandel mit Eisenwaren sowie Installationsbedarf f\u00fcr Gas, Wasser U Heizung Herstellung von Werkz",
    "sg:phone":"+41 62 291 16 10",
    "sg:postcode":"4632",
    "sg:province":"Solothurn",
    "wof:name":"Peier Isidor",
    "wof:placetype":"venue"
},
  "geometry": {"coordinates":[7.9826569557,47.3559417725],"type":"Point"}
}