{
  "type": "Feature",
  "properties": {
    "iso:country":"CH",
    "sg:address":"Rue Des Lilas 1",
    "sg:city":"Yverdon-les-bains",
    "sg:orig_category":"Wirtschaftspr\u00fcfung, Steuerberatung U Treuhand",
    "sg:phone":"+41 24 425 88 91",
    "sg:postcode":"1400",
    "sg:province":"Vaud",
    "wof:name":"Fiduciaire Billaud Alain, Comptable Dipl\u00f4m\u00e9",
    "wof:placetype":"venue"
},
  "geometry": {"coordinates":[6.6547222137,46.7768554688],"type":"Point"}
}