{
  "type": "Feature",
  "properties": {
    "iso:country":"CH",
    "sg:address":"Schweizerhofquai 2",
    "sg:city":"Luzern",
    "sg:orig_category":"Internet Provider Softwareentwicklung U beratung",
    "sg:phone":"+41 71 282 46 37",
    "sg:postcode":"6004",
    "sg:province":"Luzern",
    "wof:name":"Computer Arts Ag Software-vertrieb",
    "wof:placetype":"venue"
},
  "geometry": {"coordinates":[9.412686348,47.4320831299],"type":"Point"}
}