{
  "type": "Feature",
  "properties": {
    "iso:country":"CH",
    "sg:address":"Meienberg",
    "sg:city":"Sins",
    "sg:orig_category":"Sanit\u00e4r, Heizungs U L\u00fcftungsinstallation",
    "sg:phone":"+41 79 623 51 60",
    "sg:postcode":"5643",
    "sg:province":"Aargau",
    "wof:name":"Kubru-handel H\u00e4cki K.",
    "wof:placetype":"venue"
},
  "geometry": {"coordinates":[8.3816509247,47.1963233948],"type":"Point"}
}