{
  "type": "Feature",
  "properties": {
    "iso:country":"CH",
    "sg:address":"Weiherstrasse 20",
    "sg:city":"Zofingen",
    "sg:orig_category":"Herstellung von B\u00e4ndern, Gurten, Posamenten U Schl\u00e4uchen Weberei",
    "sg:phone":"+41 21 647 43 43",
    "sg:postcode":"4800",
    "sg:province":"Aargau",
    "wof:name":"Robert Taillens Manufacture De Tuyaux",
    "wof:placetype":"venue"
},
  "geometry": {"coordinates":[6.6341991425,46.5326690674],"type":"Point"}
}