{
  "type": "Feature",
  "properties": {
    "iso:country":"CH",
    "sg:address":"Schwyzerstrasse 43",
    "sg:city":"Brunnen",
    "sg:orig_category":"Autospenglereien",
    "sg:phone":"+41 55 246 37 07",
    "sg:postcode":"6440",
    "sg:province":"Schwyz",
    "wof:name":"Carrosserie Liborio Calamia",
    "wof:placetype":"venue"
},
  "geometry": {"coordinates":[8.939035,47.269386],"type":"Point"}
}