{
  "type": "Feature",
  "properties": {
    "iso:country":"CH",
    "sg:address":"Hochstr. 3. 8200 Schaffhausen. Postfach 471",
    "sg:city":"Schaffhausen",
    "sg:orig_category":"Druck ohne Zeitungsdruck",
    "sg:postcode":"8201",
    "sg:province":"Schaffhausen",
    "wof:name":"Schmid Peter Siebdruckerei.",
    "wof:placetype":"venue"
},
  "geometry": {"coordinates":[8.6340150833,47.7004852295],"type":"Point"}
}