{
  "type": "Feature",
  "properties": {
    "iso:country":"CH",
    "sg:address":"Via Pretorio 2",
    "sg:city":"Lugano",
    "sg:classifiers":[
        {
            "category":"Bars & Pubs",
            "type":"Food & Drink"
        }
    ],
    "sg:phone":"+41 91 923 76 94",
    "sg:postcode":"6900",
    "sg:province":"Ticino",
    "sg:tags":[
        "restaurant"
    ],
    "wof:name":"Investors'club Bar",
    "wof:placetype":"venue"
},
  "geometry": {"coordinates":[8.951731,46.005409],"type":"Point"}
}