{
  "type": "Feature",
  "properties": {
    "iso:country":"CH",
    "sg:address":"Z\u00fcrichbergstrasse 74",
    "sg:city":"Z\u00fcrich",
    "sg:orig_category":"Markt U Meinungsforschung",
    "sg:phone":"+41 12613094",
    "sg:postcode":"8044",
    "sg:province":"Z\u00fcrich",
    "wof:name":"Notter Werner M. Marketing, Managementberatung",
    "wof:placetype":"venue"
},
  "geometry": {"coordinates":[8.5600681305,47.3763008118],"type":"Point"}
}