{
  "type": "Feature",
  "properties": {
    "iso:country":"CH",
    "sg:address":"Chemin Des Palettes 26",
    "sg:city":"Grand-lancy",
    "sg:orig_category":"Markt U Meinungsforschung",
    "sg:postcode":"1212",
    "sg:province":"Gen\u00e8ve",
    "wof:name":"Bays Marketing",
    "wof:placetype":"venue"
},
  "geometry": {"coordinates":[6.1178808212,46.1768302917],"type":"Point"}
}