{
  "type": "Feature",
  "properties": {
    "addr:full":"March\u00e9 Rue Du 20 1204 Gen\u00e8ve. Postfach Gen\u00e8ve Gen\u00e8ve 1204",
    "addr:postcode":"1204;postfach;1204",
    "addr:street":"Rue Du 20",
    "iso:country":"CH",
    "sg:address":"March\u00e9 Rue Du 20 1204 Gen\u00e8ve. Postfach",
    "sg:city":"Gen\u00e8ve",
    "sg:orig_category":"Allgemeiner Hoch U Tiefbau",
    "sg:postcode":"1204",
    "sg:province":"Gen\u00e8ve",
    "wof:name":"Ufi Sa",
    "wof:placetype":"venue"
},
  "geometry": {"coordinates":[6.146583,46.203117],"type":"Point"}
}