{
  "type": "Feature",
  "properties": {
    "iso:country":"CH",
    "sg:address":"General-dufour-strasse 33",
    "sg:city":"Biel/bienne",
    "sg:orig_category":"Detailhandel mit Radio U Fernsehger\u00e4ten",
    "sg:phone":"+41 32 342 33 70",
    "sg:postcode":"2502",
    "sg:province":"Bern",
    "wof:name":"Feusier Engineering Sa",
    "wof:placetype":"venue"
},
  "geometry": {"coordinates":[7.2489709854,47.1406440735],"type":"Point"}
}