{
  "type": "Feature",
  "properties": {
    "iso:country":"CH",
    "sg:address":"Via Pradello",
    "sg:city":"Bioggio",
    "sg:orig_category":"Gartenbau",
    "sg:phone":"+41 91 605 39 13",
    "sg:postcode":"6934",
    "sg:province":"Ticino",
    "wof:name":"Giacomo-nino Giudici Giardiniere",
    "wof:placetype":"venue"
},
  "geometry": {"coordinates":[8.9099750519,46.0134391785],"type":"Point"}
}