{
  "type": "Feature",
  "properties": {
    "iso:country":"CH",
    "sg:address":"Bifangstrasse 25 5022 Rombach. Postfach 173",
    "sg:city":"Rombach",
    "sg:orig_category":"Buchverlag Verlagsgewerbe",
    "sg:phone":"+41 19101410",
    "sg:postcode":"5022",
    "sg:province":"Aargau",
    "wof:name":"Industrie Und Wirtschafts-verlag Ag",
    "wof:placetype":"venue"
},
  "geometry": {"coordinates":[8.585867,47.321152],"type":"Point"}
}