{
  "type": "Feature",
  "properties": {
    "iso:country":"CH",
    "sg:address":"Lausanne Rue De 37",
    "sg:city":"Gen\u00e8ve",
    "sg:orig_category":"Interessenvertretungen",
    "sg:postcode":"1201",
    "sg:province":"Gen\u00e8ve",
    "wof:name":"Fondation De La Soci\u00e9t\u00e9 De La Musique L'esp\u00e9rance, La Sagne",
    "wof:placetype":"venue"
},
  "geometry": {"coordinates":[6.7978801727,47.0380058289],"type":"Point"}
}