{
  "type": "Feature",
  "properties": {
    "iso:country":"CH",
    "sg:address":"Nauenstrasse 63a",
    "sg:city":"Basel",
    "sg:classifiers":[
        {
            "category":"Professional",
            "subcategory":"Engineering",
            "type":"Services"
        }
    ],
    "sg:phone":"+41 61 272 93 90",
    "sg:postcode":"4052",
    "sg:province":"Basel-Stadt",
    "sg:tags":[
        "environment",
        "technology",
        "appliance"
    ],
    "wof:name":"Pentol-enviro Ag",
    "wof:placetype":"venue"
},
  "geometry": {"coordinates":[7.594108,47.546986],"type":"Point"}
}