{
  "type": "Feature",
  "properties": {
    "iso:country":"CH",
    "sg:address":"Grond Plaz",
    "sg:city":"M\u00fcstair",
    "sg:orig_category":"Interessenvertretungen",
    "sg:phone":"+41 81 851 62 26",
    "sg:postcode":"7537",
    "sg:province":"Graubunden",
    "wof:name":"Pro Kloster St. Johann In M\u00fcstair",
    "wof:placetype":"venue"
},
  "geometry": {"coordinates":[10.4475326538,46.6291351318],"type":"Point"}
}