{
  "type": "Feature",
  "properties": {
    "iso:country":"CH",
    "sg:address":"Hagenbuchstrasse 31",
    "sg:city":"St.gallen",
    "sg:orig_category":"Architektur U Ingenieurb\u00fcros",
    "sg:phone":"+41 71 244 01 75",
    "sg:postcode":"9000",
    "sg:province":"St. Gallen",
    "wof:name":"Vitaconcept Ag",
    "wof:placetype":"venue"
},
  "geometry": {"coordinates":[9.399921,47.429668],"type":"Point"}
}