{
  "type": "Feature",
  "properties": {
    "addr:full":"Pl. Bel-air 9-11 Nyon Vaud 1260",
    "addr:housenumber":"9-11",
    "addr:postcode":"1260",
    "addr:street":"Pl. Bel-Air",
    "iso:country":"CH",
    "sg:address":"Pl. Bel-air 9-11",
    "sg:city":"Nyon",
    "sg:classifiers":[
        {
            "category":"Banks & Credit Unions",
            "subcategory":"Bank",
            "type":"Services"
        }
    ],
    "sg:postcode":"1260",
    "sg:province":"Vaud",
    "wof:name":"Conafor Finance Ag",
    "wof:placetype":"venue"
},
  "geometry": {"coordinates":[8.53955,47.37706],"type":"Point"}
}