{
  "type": "Feature",
  "properties": {
    "iso:country":"CH",
    "sg:address":"Rue Du Centre 6",
    "sg:city":"Vevey",
    "sg:orig_category":"Tin Items, Customized",
    "sg:phone":"+41 21 921 22 26",
    "sg:postcode":"1800",
    "sg:province":"Vaud",
    "wof:name":"Dominique Moriggi",
    "wof:placetype":"venue"
},
  "geometry": {"coordinates":[6.8450140953,46.4592132568],"type":"Point"}
}