{
  "type": "Feature",
  "properties": {
    "iso:country":"CH",
    "sg:address":"Unterdorfstrasse 4",
    "sg:city":"Gr\u00e4nichen",
    "sg:orig_category":"Sanit\u00e4r U Heizungsinstallation Sanit\u00e4rinstallation",
    "sg:phone":"+41 62 842 17 66",
    "sg:postcode":"5722",
    "sg:province":"Aargau",
    "wof:name":"Heinz Widmer Sanit\u00e4re Anlagen & Heizungen",
    "wof:placetype":"venue"
},
  "geometry": {"coordinates":[8.0949316025,47.3612823486],"type":"Point"}
}