{
  "type": "Feature",
  "properties": {
    "iso:country":"CH",
    "sg:address":"Renfer Rue Johann- 10 2502 Biel/bienne. Postfach",
    "sg:city":"Biel/bienne",
    "sg:orig_category":"Unclassifiable Establishments",
    "sg:postcode":"2504",
    "sg:province":"Bern",
    "wof:name":"Paulux",
    "wof:placetype":"venue"
},
  "geometry": {"coordinates":[7.2472572327,47.1408882141],"type":"Point"}
}