{
  "type": "Feature",
  "properties": {
    "iso:country":"CH",
    "sg:address":"Horwerstrasse 3",
    "sg:city":"Kriens",
    "sg:orig_category":"Primarschulen",
    "sg:phone":"+41 71 766 11 56",
    "sg:postcode":"6010",
    "sg:province":"Luzern",
    "wof:name":"Primarschule Dorf",
    "wof:placetype":"venue"
},
  "geometry": {"coordinates":[9.5384302139,47.2947883606],"type":"Point"}
}