{
  "type": "Feature",
  "properties": {
    "iso:country":"CH",
    "sg:address":"Tannacker 18",
    "sg:city":"Jens",
    "sg:orig_category":"Detailhandel mit elektrischen Haushalts-,Radio U Fernsehger\u00e4ten sowie Musikinstrumenten",
    "sg:postcode":"2565",
    "sg:province":"Bern",
    "wof:name":"Blockfl\u00f6tenl\u00e4deli Mathys E.",
    "wof:placetype":"venue"
},
  "geometry": {"coordinates":[7.262570858,47.1019325256],"type":"Point"}
}