{
  "type": "Feature",
  "properties": {
    "iso:country":"CH",
    "sg:address":"Hauptstrasse",
    "sg:city":"H\u00e4usernmoos",
    "sg:orig_category":"Gartenbau",
    "sg:phone":"+41 34 435 17 28",
    "sg:postcode":"3463",
    "sg:province":"Bern",
    "wof:name":"Urs Oppliger Gartenbau",
    "wof:placetype":"venue"
},
  "geometry": {"coordinates":[7.7491631508,47.078830719],"type":"Point"}
}