{
  "type": "Feature",
  "properties": {
    "iso:country":"CH",
    "sg:address":"1997",
    "sg:city":"Haute-nendaz",
    "sg:orig_category":"Kinderkrippen U horte",
    "sg:postcode":"1997",
    "sg:province":"Valais",
    "wof:name":"Garderie D'enfants Les Ecluses",
    "wof:placetype":"venue"
},
  "geometry": {"coordinates":[7.2981100082,46.1841506958],"type":"Point"}
}