{
  "type": "Feature",
  "properties": {
    "iso:country":"CH",
    "sg:address":"Planchamp",
    "sg:city":"Miex",
    "sg:orig_category":"Grosshandel mit sonstigen Gebrauchs U Verbrauchsg\u00fctern",
    "sg:phone":"+41 24 481 39 73",
    "sg:postcode":"1896",
    "sg:province":"Valais",
    "wof:name":"Diffusion Froidevaux Nouveaut\u00e9s Art.d\u00e9monstrations",
    "wof:placetype":"venue"
},
  "geometry": {"coordinates":[6.8908228874,46.3360748291],"type":"Point"}
}