{
  "type": "Feature",
  "properties": {
    "iso:country":"CH",
    "sg:address":"Froburgstrasse 17",
    "sg:city":"Olten",
    "sg:orig_category":"Arztpraxen",
    "sg:phone":"+41 62 212 13 73",
    "sg:postcode":"4600",
    "sg:province":"Solothurn",
    "wof:name":"Dr.med.rolf Walser Arzt F.allgemeine Medizin Fmh",
    "wof:placetype":"venue"
},
  "geometry": {"coordinates":[7.902957,47.351913],"type":"Point"}
}