{
  "type": "Feature",
  "properties": {
    "iso:country":"CH",
    "sg:address":"Willadingenstrasse 30",
    "sg:city":"Recherswil",
    "sg:orig_category":"Herstellung von Schrauben, Nieten, Ketten U Federn",
    "sg:phone":"+41 32 675 13 42",
    "sg:postcode":"4565",
    "sg:province":"Solothurn",
    "wof:name":"Born Robert",
    "wof:placetype":"venue"
},
  "geometry": {"coordinates":[7.5959038734,47.1610832214],"type":"Point"}
}