{
  "type": "Feature",
  "properties": {
    "iso:country":"CH",
    "sg:address":"Birmensdorferstr. 79",
    "sg:city":"Urdorf",
    "sg:classifiers":[
        {
            "category":"Banks & Credit Unions",
            "subcategory":"Bank",
            "type":"Services"
        }
    ],
    "sg:phone":"+41 17358000",
    "sg:postcode":"8902",
    "sg:province":"Z\u00fcrich",
    "wof:name":"Schweiz. Bankgesellschaft, Zentrum Spitzacker",
    "wof:placetype":"venue"
},
  "geometry": {"coordinates":[8.421562,47.384991],"type":"Point"}
}