{
  "type": "Feature",
  "properties": {
    "iso:country":"CH",
    "sg:address":"Seestrasse 30",
    "sg:city":"Horn",
    "sg:orig_category":"Erbringung von Dienstleistungen f\u00fcr Unternehmen Satzherstellung U Reproduktion",
    "sg:phone":"+41 34 445 64 56",
    "sg:postcode":"9326",
    "sg:province":"Thurgau",
    "wof:name":"Atelier 3s F\u00fcr Werbung, Grafik Und Satz Schranz Alfred",
    "wof:placetype":"venue"
},
  "geometry": {"coordinates":[7.5777068138,47.0907058716],"type":"Point"}
}