{
  "type": "Feature",
  "properties": {
    "iso:country":"CH",
    "sg:address":"Dorfstrasse 29",
    "sg:city":"Lyssach",
    "sg:orig_category":"G\u00fcterbef\u00f6rderung im Strassenverkehr",
    "sg:phone":"+41 34 445 19 22",
    "sg:postcode":"3421",
    "sg:province":"Bern",
    "wof:name":"B\u00fcrki Reisen & Transporte",
    "wof:placetype":"venue"
},
  "geometry": {"coordinates":[7.5776371956,47.067440033],"type":"Point"}
}