{
  "type": "Feature",
  "properties": {
    "iso:country":"CH",
    "sg:address":"Eichwisstrasse 27",
    "sg:city":"Hombrechtikon",
    "sg:orig_category":"Softwareentwicklung U beratung Sonstige mit der Informatik verbundene T\u00e4tigkeiten",
    "sg:postcode":"8634",
    "sg:province":"Z\u00fcrich",
    "wof:name":"Andr\u00e9 W. Spuler Consulting",
    "wof:placetype":"venue"
},
  "geometry": {"coordinates":[8.7814903259,47.2513313293],"type":"Point"}
}