{
  "type": "Feature",
  "properties": {
    "iso:country":"CH",
    "sg:address":"Sur-les-c\u00f4tes 1",
    "sg:city":"Courgenay",
    "sg:orig_category":"Allgemeiner Hoch U Tiefbau Bauschreinerei",
    "sg:phone":"+41 79 354 73 73",
    "sg:postcode":"2950",
    "sg:province":"Jura",
    "wof:name":"Balmer & Gillioz S\u00e0rl Menuiserie G\u00e9n\u00e9rale Etc",
    "wof:placetype":"venue"
},
  "geometry": {"coordinates":[7.11642,47.407337],"type":"Point"}
}