{
  "type": "Feature",
  "properties": {
    "iso:country":"CH",
    "sg:address":"Bahnhofstrasse 18b",
    "sg:city":"Burgdorf",
    "sg:orig_category":"Gesundheitswesen R\u00f6ntgeninstitute",
    "sg:phone":"+41 34 420 37 37",
    "sg:postcode":"3400",
    "sg:province":"Bern",
    "wof:name":"Mri Regio Rodiag Emmental",
    "wof:placetype":"venue"
},
  "geometry": {"coordinates":[7.6242389679,47.0594291687],"type":"Point"}
}