{
  "type": "Feature",
  "properties": {
    "iso:country":"CH",
    "sg:address":"Dorfplatz 7",
    "sg:city":"Arlesheim",
    "sg:orig_category":"Detailhandel mit Schuhen",
    "sg:phone":"+41 61 701 46 42",
    "sg:postcode":"4144",
    "sg:province":"Basel-Landschaft",
    "wof:name":"Huber Schuh Ag",
    "wof:placetype":"venue"
},
  "geometry": {"coordinates":[7.6208081245,47.4935874939],"type":"Point"}
}