{
  "type": "Feature",
  "properties": {
    "iso:country":"CH",
    "sg:address":"Grand Rue 46",
    "sg:city":"Montreux",
    "sg:classifiers":[
        {
            "category":"Manufacturing",
            "subcategory":"Jewelry",
            "type":"Manufacturing & Wholesale Goods"
        }
    ],
    "sg:phone":"+41 21 963 16 14",
    "sg:postcode":"1820",
    "sg:province":"Vaud",
    "sg:tags":[
        "gemstone",
        "gold",
        "jewellery"
    ],
    "wof:name":"Alden S.\u00e0.r.l.",
    "wof:placetype":"venue"
},
  "geometry": {"coordinates":[6.9101910591,46.4340248108],"type":"Point"}
}