{
  "type": "Feature",
  "properties": {
    "iso:country":"CH",
    "sg:address":"Rue Louis-favre 13",
    "sg:city":"Gen\u00e8ve",
    "sg:orig_category":"Vermietung von Automobilen",
    "sg:phone":"+41 22 733 79 45",
    "sg:postcode":"1201",
    "sg:province":"Gen\u00e8ve",
    "wof:name":"Discount Car Sa",
    "wof:placetype":"venue"
},
  "geometry": {"coordinates":[6.1367092133,46.2109642029],"type":"Point"}
}