{
  "type": "Feature",
  "properties": {
    "addr:full":"Dolderstrasse 109 Z\u00fcrich Z\u00fcrich 8032",
    "addr:housenumber":"109",
    "addr:postcode":"8032",
    "addr:street":"Dolderstrasse",
    "iso:country":"CH",
    "sg:address":"Dolderstrasse 109",
    "sg:city":"Z\u00fcrich",
    "sg:orig_category":"Advokaturb\u00fcros",
    "sg:phone":"+41 56 664 22 19",
    "sg:postcode":"8032",
    "sg:province":"Z\u00fcrich",
    "wof:name":"Dr.heidi Etter Advokaturb\u00fcro",
    "wof:placetype":"venue"
},
  "geometry": {"coordinates":[8.317482,47.282578],"type":"Point"}
}