{
  "type": "Feature",
  "properties": {
    "iso:country":"CH",
    "sg:address":"Avenue De L' Avant-poste",
    "sg:city":"Lausanne",
    "sg:classifiers":[
        {
            "category":"Government",
            "subcategory":"Fire Station",
            "type":"Public Place"
        }
    ],
    "sg:phone":"+41 21 693 86 18",
    "sg:postcode":"1005",
    "sg:province":"Vaud",
    "sg:tags":[
        "explosion",
        "coating",
        "surface",
        "equipment",
        "protection",
        "safety",
        "systems",
        "operation"
    ],
    "wof:name":"Ecosafe Sa",
    "wof:placetype":"venue"
},
  "geometry": {"coordinates":[6.6428990364,46.5178375244],"type":"Point"}
}