{
  "type": "Feature",
  "properties": {
    "addr:full":"Vuiteboeuf Vuiteboeuf Vaud 1445",
    "addr:postcode":"1445",
    "iso:country":"CH",
    "sg:address":"Vuiteboeuf",
    "sg:city":"Vuiteboeuf",
    "sg:classifiers":[
        {
            "category":"Banks & Credit Unions",
            "subcategory":"Bank",
            "type":"Services"
        }
    ],
    "sg:phone":"+41 24 459 19 47",
    "sg:postcode":"1445",
    "sg:province":"Vaud",
    "wof:name":"Raiffeisen",
    "wof:placetype":"venue"
},
  "geometry": {"coordinates":[6.548868,46.806992],"type":"Point"}
}