{
  "type": "Feature",
  "properties": {
    "iso:country":"CH",
    "sg:address":"Au Grand Faubourg",
    "sg:city":"Montricher",
    "sg:orig_category":"Herstellung von sonstigen landwirtschaftlichen Maschinen",
    "sg:phone":"+41 21 864 43 68",
    "sg:postcode":"1147",
    "sg:province":"Vaud",
    "wof:name":"Amez-droz Laurend, Delaval Equipement De Fermes Et De Machines \u00e0 Traire",
    "wof:placetype":"venue"
},
  "geometry": {"coordinates":[6.3808660507,46.602191925],"type":"Point"}
}