{
  "type": "Feature",
  "properties": {
    "iso:country":"CH",
    "sg:address":"Stadtturmstrasse 16",
    "sg:city":"Baden",
    "sg:orig_category":"Wirtschaftspr\u00fcfung, Steuerberatung U Treuhand",
    "sg:phone":"+41 31 981 03 31",
    "sg:postcode":"5400",
    "sg:province":"Aargau",
    "wof:name":"Intertreuhand A. K\u00e4ser",
    "wof:placetype":"venue"
},
  "geometry": {"coordinates":[7.3751912117,46.9260139465],"type":"Point"}
}