{
  "type": "Feature",
  "properties": {
    "iso:country":"CH",
    "sg:address":"Madetswilerstrasse 29",
    "sg:city":"Russikon",
    "sg:orig_category":"Weberei",
    "sg:phone":"+41 19540449",
    "sg:postcode":"8332",
    "sg:province":"Z\u00fcrich",
    "wof:name":"Wr Weberei Russikon Ag",
    "wof:placetype":"venue"
},
  "geometry": {"coordinates":[8.7794275284,47.3962440491],"type":"Point"}
}