{
  "type": "Feature",
  "properties": {
    "iso:country":"CH",
    "sg:address":"Kreuzlingerstrasse 41",
    "sg:city":"Romanshorn",
    "sg:orig_category":"Handel mit Motorr\u00e4dern, Teilen U Zubeh\u00f6r Instandhaltung U Reparatur von Motorr\u00e4dern",
    "sg:phone":"+41 71 463 55 44",
    "sg:postcode":"8590",
    "sg:province":"Thurgau",
    "wof:name":"Kawasaki-motos R\u00fcegger Arno",
    "wof:placetype":"venue"
},
  "geometry": {"coordinates":[9.3661203384,47.5702590942],"type":"Point"}
}