{
  "type": "Feature",
  "properties": {
    "iso:country":"CH",
    "sg:address":"Gablerstrasse 48",
    "sg:city":"Z\u00fcrich",
    "sg:orig_category":"Detailhandel mit Waren verschiedener Art, Hauptrichtung Nahrungsmittel Detailhandel mit Waren versch",
    "sg:phone":"+41 12025804",
    "sg:postcode":"8002",
    "sg:province":"Z\u00fcrich",
    "wof:name":"Primo-lebensmittel Ivanovic",
    "wof:placetype":"venue"
},
  "geometry": {"coordinates":[8.527100563,47.3585166931],"type":"Point"}
}