{
  "type": "Feature",
  "properties": {
    "iso:country":"CH",
    "sg:address":"Gewerbehaus Mahalla",
    "sg:city":"Richterswil",
    "sg:orig_category":"Tanzschulen, Tanzlehrer",
    "sg:phone":"+41 17847424",
    "sg:postcode":"8805",
    "sg:province":"Z\u00fcrich",
    "wof:name":"Tanzschule Panama",
    "wof:placetype":"venue"
},
  "geometry": {"coordinates":[8.7051200867,47.2075004578],"type":"Point"}
}