{
  "type": "Feature",
  "properties": {
    "iso:country":"CH",
    "sg:address":"Ottersbachstrasse 2 9430 St. Margrethen Sg. Postfach 341",
    "sg:city":"Diepoldsau",
    "sg:orig_category":"Sportvereine Turnen",
    "sg:phone":"+41 71 744 50 18",
    "sg:postcode":"9444",
    "sg:province":"St. Gallen",
    "wof:name":"Turnverein Stv Diepoldsau",
    "wof:placetype":"venue"
},
  "geometry": {"coordinates":[9.6447658539,47.446559906],"type":"Point"}
}