{
  "type": "Feature",
  "properties": {
    "iso:country":"CH",
    "sg:address":"Industriestrasse 43",
    "sg:city":"B\u00f6singen",
    "sg:orig_category":"Unclassifiable Establishments",
    "sg:postcode":"3178",
    "sg:province":"Fribourg",
    "wof:name":"Zentrums Ag Auried",
    "wof:placetype":"venue"
},
  "geometry": {"coordinates":[7.229118824,46.9007301331],"type":"Point"}
}