{
  "type": "Feature",
  "properties": {
    "iso:country":"CH",
    "sg:address":"In Der Luberzen 19 8010 Z\u00fcrich-m\u00fclligen. Postfach",
    "sg:city":"Z\u00fcrich-m\u00fclligen",
    "sg:orig_category":"Detailhandel mit Bekleidung",
    "sg:phone":"+41 17363333",
    "sg:postcode":"8010",
    "sg:province":"Z\u00fcrich",
    "wof:name":"Pkz Burger-kehl & Co Ag",
    "wof:placetype":"venue"
},
  "geometry": {"coordinates":[8.53801,47.369091],"type":"Point"}
}