{
  "type": "Feature",
  "properties": {
    "iso:country":"CH",
    "sg:address":"Steigenweg 162",
    "sg:city":"Blauen",
    "sg:orig_category":"Malerei-Gipserei Stukkateurgewerbe, Gipserei U Verputzerei",
    "sg:phone":"+41 61 761 53 33",
    "sg:postcode":"4223",
    "sg:province":"Basel-Landschaft",
    "wof:name":"Fredy Imbach Gipserei",
    "wof:placetype":"venue"
},
  "geometry": {"coordinates":[7.5215997696,47.4516487122],"type":"Point"}
}