{
  "type": "Feature",
  "properties": {
    "iso:country":"CH",
    "sg:address":"Rigistrasse 96",
    "sg:city":"Weggis",
    "sg:orig_category":"Zimmerei, Ingenieurholzbau",
    "sg:phone":"+41 41 390 07 08",
    "sg:postcode":"6353",
    "sg:province":"Luzern",
    "wof:name":"Philipp & Wolfgang Stalder Holzbau",
    "wof:placetype":"venue"
},
  "geometry": {"coordinates":[8.4449615479,47.0344696045],"type":"Point"}
}