{
  "type": "Feature",
  "properties": {
    "iso:country":"CH",
    "sg:address":"Allmendstrasse 1 Postfach 63",
    "sg:city":"Sachseln",
    "sg:classifiers":[
        {
            "category":"Manufacturing",
            "subcategory":"Wood Products",
            "type":"Manufacturing & Wholesale Goods"
        }
    ],
    "sg:phone":"+41 41 660 33 22",
    "sg:postcode":"6072",
    "sg:province":"Obwalden",
    "sg:tags":[
        "professional",
        "furniture"
    ],
    "wof:name":"Reinhard Ag Sachseln",
    "wof:placetype":"venue"
},
  "geometry": {"coordinates":[-6.2731690407,53.3594474792],"type":"Point"}
}