{
  "type": "Feature",
  "properties": {
    "iso:country":"CH",
    "sg:address":"M\u00fcntschemiergasse 1",
    "sg:city":"Ins",
    "sg:orig_category":"Polizei",
    "sg:phone":"+41 32 313 15 55",
    "sg:postcode":"3232",
    "sg:province":"Bern",
    "wof:name":"Kantonale Polizei",
    "wof:placetype":"venue"
},
  "geometry": {"coordinates":[7.1064581871,47.0054893494],"type":"Point"}
}