{
  "type": "Feature",
  "properties": {
    "iso:country":"CH",
    "sg:address":"Bolligenstrasse 52",
    "sg:city":"Bern",
    "sg:orig_category":"Gesundheitswesen",
    "sg:phone":"+41 2093938",
    "sg:postcode":"3006",
    "sg:province":"Bern",
    "wof:name":"Medi-consult Werner Sabine",
    "wof:placetype":"venue"
},
  "geometry": {"coordinates":[8.4647512436,47.3650474548],"type":"Point"}
}