{
  "type": "Feature",
  "properties": {
    "iso:country":"CH",
    "sg:address":"Usterstrasse 78",
    "sg:city":"D\u00fcbendorf",
    "sg:orig_category":"Zahnarztpraxen",
    "sg:phone":"+41 18218538",
    "sg:postcode":"8600",
    "sg:province":"Z\u00fcrich",
    "wof:name":"Dr. Med. Dent. J\u00fcrg Genelin Zahnarzt",
    "wof:placetype":"venue"
},
  "geometry": {"coordinates":[8.6277589798,47.3962936401],"type":"Point"}
}