{
  "type": "Feature",
  "properties": {
    "iso:country":"CH",
    "sg:address":"Zentralstrasse 42 6031 Ebikon. Postfach 70",
    "sg:city":"Ebikon",
    "sg:orig_category":"Architektur U Ingenieurb\u00fcros",
    "sg:phone":"+41 41 440 43 33",
    "sg:postcode":"6030",
    "sg:province":"Luzern",
    "wof:name":"Agba Ag \u00ac Arbeitsgemeinschaft Beratender Agronomen",
    "wof:placetype":"venue"
},
  "geometry": {"coordinates":[8.344182,47.083416],"type":"Point"}
}