{
  "type": "Feature",
  "properties": {
    "iso:country":"CH",
    "sg:address":"Lindenmatt 3",
    "sg:city":"Illgau",
    "sg:orig_category":"Unternehmensberatung",
    "sg:phone":"+41 34 409 17 17",
    "sg:postcode":"6434",
    "sg:province":"Schwyz",
    "wof:name":"Marufia Ag",
    "wof:placetype":"venue"
},
  "geometry": {"coordinates":[7.4969968796,46.9271469116],"type":"Point"}
}