{
  "type": "Feature",
  "properties": {
    "iso:country":"CH",
    "sg:address":"Bolleystrasse 11 8006 Z\u00fcrich. Postfach",
    "sg:city":"Z\u00fcrich",
    "sg:orig_category":"Sonstiger Grosshandel",
    "sg:phone":"+41 12528770",
    "sg:postcode":"8001",
    "sg:province":"Z\u00fcrich",
    "wof:name":"Dragon Trade Ag Waren Usw; Handel, Finanz- U. Handelsgesch\u00e4fte",
    "wof:placetype":"venue"
},
  "geometry": {"coordinates":[8.549036026,47.3814277649],"type":"Point"}
}