{
  "type": "Feature",
  "properties": {
    "iso:country":"CH",
    "sg:address":"Sumpfstrasse 5 6300 Zug. Postfach",
    "sg:city":"Zug",
    "sg:orig_category":"Non-Classified Establishments",
    "sg:postcode":"6300",
    "sg:province":"Zug",
    "wof:name":"Koya Ag",
    "wof:placetype":"venue"
},
  "geometry": {"coordinates":[8.4905786514,47.1863517761],"type":"Point"}
}