{
  "type": "Feature",
  "properties": {
    "iso:country":"CH",
    "sg:address":"Apollostrasse 21 8032 Z\u00fcrich",
    "sg:city":"Zust",
    "sg:orig_category":"Sonstige mit der Informatik verbundene T\u00e4tigkeiten",
    "sg:phone":"+41 13803083",
    "sg:postcode":"32",
    "wof:name":"Steinmann Consulting Edv-beratung",
    "wof:placetype":"venue"
},
  "geometry": {"coordinates":[8.5679702759,47.3668403625],"type":"Point"}
}