{
  "type": "Feature",
  "properties": {
    "iso:country":"CH",
    "sg:address":"Rosenweg 14 8413 Neftenbach. Postfach 231",
    "sg:city":"Neftenbach",
    "sg:orig_category":"Herstellung von Fenstern U T\u00fcren aus Holz Herstellung von Konstruktionsteilen, Fertigbauteilen U Aus",
    "sg:phone":"+41 52 315 14 21",
    "sg:postcode":"8413",
    "sg:province":"Z\u00fcrich",
    "wof:name":"Rietiker Ernst Ag",
    "wof:placetype":"venue"
},
  "geometry": {"coordinates":[8.6717634201,47.5222167969],"type":"Point"}
}