{
  "type": "Feature",
  "properties": {
    "iso:country":"CH",
    "sg:address":"Oberst\u00f6cken 14",
    "sg:city":"Unteriberg",
    "sg:orig_category":"Herstellung von Metallkonstruktionen",
    "sg:phone":"+41 55 414 28 40",
    "sg:postcode":"8842",
    "sg:province":"Schwyz",
    "wof:name":"Cavelti Urs",
    "wof:placetype":"venue"
},
  "geometry": {"coordinates":[8.8001813889,47.0598564148],"type":"Point"}
}