{
  "type": "Feature",
  "properties": {
    "iso:country":"CH",
    "sg:address":"Rheinfeldstrasse 600",
    "sg:city":"Wallbach",
    "sg:orig_category":"Massagestudios P\u00e9dicure",
    "sg:phone":"+41 61 861 14 83",
    "sg:postcode":"4323",
    "sg:province":"Aargau",
    "wof:name":"Petra Kaufmann",
    "wof:placetype":"venue"
},
  "geometry": {"coordinates":[7.9040498734,47.5551109314],"type":"Point"}
}