{
  "type": "Feature",
  "properties": {
    "addr:full":"Vispastrasse 34 Zermatt Valais 3920",
    "addr:housenumber":"34",
    "addr:postcode":"3920",
    "addr:street":"Vispastrasse",
    "iso:country":"CH",
    "sg:address":"Vispastrasse 34",
    "sg:city":"Zermatt",
    "sg:orig_category":"Detailhandel mit B\u00fcchern, Zeitungen, Schreib U Papeteriewaren Detailhandel mit Sportartikeln",
    "sg:phone":"+41 27 967 49 45",
    "sg:postcode":"3920",
    "sg:province":"Valais",
    "wof:name":"John-william Tidey Tipee Sport",
    "wof:placetype":"venue"
},
  "geometry": {"coordinates":[7.751867,46.022522],"type":"Point"}
}