{
  "type": "Feature",
  "properties": {
    "iso:country":"CH",
    "sg:address":"Ey 3665 Wattenwil. Postfach 84",
    "sg:city":"Wattenwil",
    "sg:orig_category":"Textilgewerbe",
    "sg:phone":"+41 33 356 16 06",
    "sg:postcode":"3665",
    "sg:province":"Bern",
    "wof:name":"Filtra Ag",
    "wof:placetype":"venue"
},
  "geometry": {"coordinates":[7.5083260536,46.76745224],"type":"Point"}
}