{
  "type": "Feature",
  "properties": {
    "iso:country":"CH",
    "sg:address":"Aebnitstrasse 60 3073 G\u00fcmligen. Postfach",
    "sg:city":"G\u00fcmligen",
    "sg:orig_category":"Sonstige mit der Informatik verbundene T\u00e4tigkeiten",
    "sg:phone":"+41 31 951 03 00",
    "sg:postcode":"3073",
    "sg:province":"Bern",
    "wof:name":"Arcoffice Gmbh",
    "wof:placetype":"venue"
},
  "geometry": {"coordinates":[7.4975600243,46.9316864014],"type":"Point"}
}