{
  "type": "Feature",
  "properties": {
    "iso:country":"CH",
    "sg:address":"Industriestrasse 5",
    "sg:city":"Lupfig",
    "sg:orig_category":"Kauf U Verkauf von Immobilien auf eigene Rechnung Vermietung U Verpachtung von eigenen Immobilien",
    "sg:phone":"+41 56 444 02 02",
    "sg:postcode":"5242",
    "sg:province":"Aargau",
    "wof:name":"Mythen Immobilien Ag",
    "wof:placetype":"venue"
},
  "geometry": {"coordinates":[8.2127523422,47.4445228577],"type":"Point"}
}