{
  "type": "Feature",
  "properties": {
    "iso:country":"CH",
    "sg:address":"Prantan\u00e4r",
    "sg:city":"Walenstadt",
    "sg:orig_category":"Haltung von Schweinen",
    "sg:phone":"+41 81 735 21 66",
    "sg:postcode":"8880",
    "sg:province":"St. Gallen",
    "wof:name":"Othmar Schwizer Jun. Schweinezucht",
    "wof:placetype":"venue"
},
  "geometry": {"coordinates":[9.3137950897,47.1127586365],"type":"Point"}
}