{
  "type": "Feature",
  "properties": {
    "iso:country":"CH",
    "sg:address":"Route De Courroux 7",
    "sg:city":"Vicques",
    "sg:orig_category":"Bauschreinerei Herstellung von Konstruktionsteilen, Fertigbauteilen U Ausbauelementen aus Holz",
    "sg:phone":"+41 32 435 65 25",
    "sg:postcode":"2824",
    "sg:province":"Jura",
    "wof:name":"Mce Marti S\u00e0rl",
    "wof:placetype":"venue"
},
  "geometry": {"coordinates":[7.407409,47.34903],"type":"Point"}
}