{
  "type": "Feature",
  "properties": {
    "iso:country":"CH",
    "sg:address":"1555",
    "sg:city":"Villarzel",
    "sg:orig_category":"Schlossereien",
    "sg:phone":"+41 56 631 60 24",
    "sg:postcode":"1555",
    "sg:province":"Vaud",
    "wof:name":"Ren\u00e9 Bassi Schlosserei",
    "wof:placetype":"venue"
},
  "geometry": {"coordinates":[8.3384504318,47.3492393494],"type":"Point"}
}