{
  "type": "Feature",
  "properties": {
    "iso:country":"CH",
    "sg:address":"Grundm\u00fchle 5",
    "sg:city":"Willisau",
    "sg:orig_category":"Organisationen der Wohlfahrtspflege",
    "sg:phone":"+41 41 970 32 72",
    "sg:postcode":"6130",
    "sg:province":"Luzern",
    "wof:name":"Pro Juventute",
    "wof:placetype":"venue"
},
  "geometry": {"coordinates":[7.9818072319,47.119846344],"type":"Point"}
}