{
  "type": "Feature",
  "properties": {
    "iso:country":"CH",
    "sg:address":"Corso S.gottardo 85",
    "sg:city":"Chiasso",
    "sg:orig_category":"G\u00fcterbef\u00f6rderung im Strassenverkehr",
    "sg:phone":"+41 34 493 36 48",
    "sg:postcode":"6830",
    "sg:province":"Ticino",
    "wof:name":"Oswald Aschwanden Holztransportunternehmung",
    "wof:placetype":"venue"
},
  "geometry": {"coordinates":[7.9048290253,46.8615722656],"type":"Point"}
}