{
  "type": "Feature",
  "properties": {
    "iso:country":"CH",
    "sg:address":"Route Des Avouillons 4",
    "sg:city":"Gland",
    "sg:orig_category":"Reinigungsgewerbe Verlegen von Fliesen U Platten",
    "sg:phone":"+41 22 364 17 14",
    "sg:postcode":"1196",
    "sg:province":"Vaud",
    "wof:name":"Pr\u00e9tot Nettoyage Sa",
    "wof:placetype":"venue"
},
  "geometry": {"coordinates":[6.2690029144,46.4162101746],"type":"Point"}
}