{
  "type": "Feature",
  "properties": {
    "iso:country":"CH",
    "sg:address":"Via Cantonale 8",
    "sg:city":"Lugano",
    "sg:orig_category":"Versicherungen Generalagenturen",
    "sg:phone":"+41 91 923 53 01",
    "sg:postcode":"6900",
    "sg:province":"Ticino",
    "wof:name":"Northern Assurance Agenzia Generale Luigi Morelli",
    "wof:placetype":"venue"
},
  "geometry": {"coordinates":[8.9503984451,46.0078544617],"type":"Point"}
}