{
  "type": "Feature",
  "properties": {
    "addr:full":"Landenbergstrasse 41 Luzern Luzern 6005",
    "addr:housenumber":"41",
    "addr:postcode":"6005",
    "addr:street":"Landenbergstrasse",
    "iso:country":"CH",
    "sg:address":"Landenbergstrasse 41",
    "sg:city":"Luzern",
    "sg:classifiers":[
        {
            "category":"Autos & Motor Vehicles",
            "subcategory":"Fuel & Gas Station",
            "type":"Retail Goods"
        }
    ],
    "sg:phone":"+41 41 360 51 41",
    "sg:postcode":"6005",
    "sg:province":"Luzern",
    "sg:tags":[
        "engine",
        "petrol",
        "turbine",
        "diesel"
    ],
    "wof:name":"Brennstoff Ag",
    "wof:placetype":"venue"
},
  "geometry": {"coordinates":[8.315672,47.046421],"type":"Point"}
}