{
  "type": "Feature",
  "properties": {
    "iso:country":"CH",
    "sg:address":"Bergstrasse 5",
    "sg:city":"Luzern",
    "sg:classifiers":[
        {
            "category":"Professional",
            "subcategory":"Employment Agencies",
            "type":"Services"
        }
    ],
    "sg:phone":"+41 22 322 25 25",
    "sg:postcode":"6004",
    "sg:province":"Luzern",
    "sg:tags":[
        "personal",
        "u",
        "stellenvermittlung"
    ],
    "wof:name":"Kalitec Services Sa S\u00e9lection De Personnel",
    "wof:placetype":"venue"
},
  "geometry": {"coordinates":[6.1479868889,46.2105407715],"type":"Point"}
}