{
  "type": "Feature",
  "properties": {
    "iso:country":"CH",
    "sg:address":"Wynernstrasse 22",
    "sg:city":"Wettingen",
    "sg:orig_category":"Elektroinstallation",
    "sg:phone":"+41 56 426 55 28",
    "sg:postcode":"5430",
    "sg:province":"Aargau",
    "wof:name":"Lebag Elektroinstallationen Ag",
    "wof:placetype":"venue"
},
  "geometry": {"coordinates":[8.3288021088,47.4602890015],"type":"Point"}
}