{
  "type": "Feature",
  "properties": {
    "addr:full":"Balkenweg 8 Gelterkinden Basel-Landschaft 4460",
    "addr:housenumber":"8",
    "addr:postcode":"4460",
    "addr:street":"Balkenweg",
    "iso:country":"CH",
    "sg:address":"Balkenweg 8",
    "sg:city":"Gelterkinden",
    "sg:orig_category":"Allgemeiner Hochbau Erdbewegungsarbeiten",
    "sg:phone":"+41 61 981 10 48",
    "sg:postcode":"4460",
    "sg:province":"Basel-Landschaft",
    "wof:name":"Beat Mazzon Tiefbau & Transporte",
    "wof:placetype":"venue"
},
  "geometry": {"coordinates":[7.853871,47.462898],"type":"Point"}
}