{
  "type": "Feature",
  "properties": {
    "iso:country":"CH",
    "sg:address":"Route Des Peupliers 4-6",
    "sg:city":"Conthey",
    "sg:orig_category":"HERSTELLUNG VON GER\u00c4TEN DER ELEKTRIZIT\u00c4TSERZEUGUNG, -VERTEILUNG U.\u00c4 Herstellung von Metallerzeugniss",
    "sg:phone":"+41 27 346 15 28",
    "sg:postcode":"1964",
    "sg:province":"Valais",
    "wof:name":"Comitec Sa Prod.de Micro-pi\u00e8ces",
    "wof:placetype":"venue"
},
  "geometry": {"coordinates":[7.3054680824,46.2199440002],"type":"Point"}
}