{
  "type": "Feature",
  "properties": {
    "iso:country":"CH",
    "sg:address":"Zeltweg 4",
    "sg:city":"Z\u00fcrich",
    "sg:classifiers":[
        {
            "category":"Bars & Pubs",
            "type":"Food & Drink"
        }
    ],
    "sg:phone":"+41 56 282 15 80",
    "sg:postcode":"8032",
    "sg:province":"Z\u00fcrich",
    "sg:tags":[
        "restaurant"
    ],
    "wof:name":"Restaurant & Bar Drei Sterne",
    "wof:placetype":"venue"
},
  "geometry": {"coordinates":[8.292557,47.486652],"type":"Point"}
}