{
  "type": "Feature",
  "properties": {
    "iso:country":"CH",
    "sg:address":"Dorfstrasse 21",
    "sg:city":"Udligenswil",
    "sg:orig_category":"Architektur U Ingenieurb\u00fcros",
    "sg:phone":"+41 41 371 14 41",
    "sg:postcode":"6044",
    "sg:province":"Luzern",
    "wof:name":"Ingenieurb\u00fcro F\u00fcr Microelectronic Eichholzer",
    "wof:placetype":"venue"
},
  "geometry": {"coordinates":[8.399592,47.087475],"type":"Point"}
}