{
  "type": "Feature",
  "properties": {
    "iso:country":"CH",
    "sg:address":"Hauptstrasse 96",
    "sg:city":"Schlarigna",
    "sg:orig_category":"Instandhaltung U Reparatur von Automobilen",
    "sg:phone":"+41 34 402 31 31",
    "sg:postcode":"7505",
    "sg:province":"Graubunden",
    "wof:name":"Peter Fuhrer Ag",
    "wof:placetype":"venue"
},
  "geometry": {"coordinates":[7.757589817,46.9491271973],"type":"Point"}
}