{
  "type": "Feature",
  "properties": {
    "iso:country":"CH",
    "sg:address":"Route De La C\u00f4te 22 1615 Bossonnens Case Postale 49",
    "sg:city":"Bossonnens",
    "sg:orig_category":"Sonstiger Grosshandel",
    "sg:phone":"+41 21 961 25 48",
    "sg:postcode":"1615",
    "sg:province":"Fribourg",
    "wof:name":"Lenka Huckova S\u00e0rl",
    "wof:placetype":"venue"
},
  "geometry": {"coordinates":[6.8533120155,46.5291404724],"type":"Point"}
}