{
  "type": "Feature",
  "properties": {
    "iso:country":"CH",
    "sg:address":"Rue De La Corraterie 16",
    "sg:city":"Gen\u00e8ve",
    "sg:orig_category":"Detailhandel mit Damenbekleidung",
    "sg:phone":"+41 22 310 52 10",
    "sg:postcode":"1204",
    "sg:province":"Gen\u00e8ve",
    "wof:name":"Boutique Camelia Lingerie",
    "wof:placetype":"venue"
},
  "geometry": {"coordinates":[6.143136,46.202709],"type":"Point"}
}