{
  "type": "Feature",
  "properties": {
    "iso:country":"CH",
    "sg:address":"8845 Studen Sz. Postfach 53",
    "sg:city":"Euthal",
    "sg:orig_category":"Grosshandel mit Nahrungsmitteln, Getr\u00e4nken U Tabakwaren Grosshandel mit Tabakwaren",
    "sg:postcode":"8844",
    "sg:province":"Schwyz",
    "wof:name":"M Tabaco Zigarrenimport",
    "wof:placetype":"venue"
},
  "geometry": {"coordinates":[8.8399848938,47.0724411011],"type":"Point"}
}