{
  "type": "Feature",
  "properties": {
    "iso:country":"CH",
    "sg:address":"Via San Martino 3",
    "sg:city":"Vezia",
    "sg:classifiers":[
        {
            "category":"Restaurant",
            "type":"Food & Drink"
        }
    ],
    "sg:phone":"+41 91 966 87 60",
    "sg:postcode":"6943",
    "sg:province":"Ticino",
    "wof:name":"Ristorante Boccalino",
    "wof:placetype":"venue"
},
  "geometry": {"coordinates":[8.9381284714,46.0238952637],"type":"Point"}
}