{
  "type": "Feature",
  "properties": {
    "iso:country":"CH",
    "sg:address":"Zetzwilerstrasse",
    "sg:city":"Gontenschwil",
    "sg:classifiers":[
        {
            "category":"Home & Garden",
            "subcategory":"Kitchen Supply",
            "type":"Retail Goods"
        }
    ],
    "sg:phone":"+41 62 773 11 70",
    "sg:postcode":"5728",
    "sg:province":"Aargau",
    "sg:tags":[
        "household",
        "dishwasher"
    ],
    "wof:name":"R. Hunziker Ag",
    "wof:placetype":"venue"
},
  "geometry": {"coordinates":[8.1454591751,47.2819747925],"type":"Point"}
}