{
  "type": "Feature",
  "properties": {
    "iso:country":"CH",
    "sg:address":"Kantonsstrasse",
    "sg:city":"Horw",
    "sg:orig_category":"Detailhandel mit Zeitungen U Zeitschriften Kioske",
    "sg:phone":"+41 41 340 73 85",
    "sg:postcode":"6048",
    "sg:province":"Luzern",
    "wof:name":"Maria Garattini Kiosk Waldegg",
    "wof:placetype":"venue"
},
  "geometry": {"coordinates":[8.3078393936,47.0119438171],"type":"Point"}
}