{
  "type": "Feature",
  "properties": {
    "iso:country":"CH",
    "sg:address":"Reinacherstrasse 153",
    "sg:city":"Basel",
    "sg:orig_category":"Handel mit Automobilen",
    "sg:phone":"+41 61 335 15 00",
    "sg:postcode":"4053",
    "sg:province":"Basel-Stadt",
    "wof:name":"Assko Automobile Ag",
    "wof:placetype":"venue"
},
  "geometry": {"coordinates":[7.6051287651,47.533870697],"type":"Point"}
}