{
  "type": "Feature",
  "properties": {
    "iso:country":"CH",
    "sg:address":"R\u00fcschlistrasse 22 2500 Biel/bienne. Postfach",
    "sg:city":"Biel/bienne",
    "sg:orig_category":"Interessenvertretungen",
    "sg:postcode":"2502",
    "sg:province":"Bern",
    "wof:name":"Stiftung Junge Schweizer Oper",
    "wof:placetype":"venue"
},
  "geometry": {"coordinates":[7.2447199821,47.1373977661],"type":"Point"}
}