{
  "type": "Feature",
  "properties": {
    "iso:country":"CH",
    "sg:address":"Marktgasse 37 3011 Bern. Postfach 6362",
    "sg:city":"Bern",
    "sg:orig_category":"Regionalbanken U Sparkassen",
    "sg:phone":"+41 31 312 03 12",
    "sg:postcode":"3001",
    "sg:province":"Bern",
    "wof:name":"Burgerliche Ersparniskasse Bern",
    "wof:placetype":"venue"
},
  "geometry": {"coordinates":[7.4452261925,46.9479026794],"type":"Point"}
}