{
  "type": "Feature",
  "properties": {
    "iso:country":"CH",
    "sg:address":"T\u00f6sstalstrasse 244a 8405 Seen. Postfach",
    "sg:city":"Winterthur",
    "sg:orig_category":"Unclassifiable Establishments",
    "sg:phone":"+41 52 232 17 77",
    "sg:postcode":"8405",
    "sg:province":"Z\u00fcrich",
    "wof:name":"B\u00fcrgin Gartenpflege",
    "wof:placetype":"venue"
},
  "geometry": {"coordinates":[8.7597494125,47.4841308594],"type":"Point"}
}