{
  "type": "Feature",
  "properties": {
    "iso:country":"CH",
    "sg:address":"Spittel 6",
    "sg:city":"Herisau",
    "sg:classifiers":[
        {
            "category":"Restaurant",
            "type":"Food & Drink"
        }
    ],
    "sg:phone":"+41 71 351 18 30",
    "sg:postcode":"9100",
    "sg:province":"Appenzell Ausserrhoden",
    "wof:name":"Gasthaus Freihof",
    "wof:placetype":"venue"
},
  "geometry": {"coordinates":[9.2766771317,47.387462616],"type":"Point"}
}