{
  "type": "Feature",
  "properties": {
    "iso:country":"CH",
    "sg:address":"Unterdettingenstrasse 21",
    "sg:city":"Hinterkappelen",
    "sg:orig_category":"Effektenvermittlung Broker",
    "sg:phone":"+41 31 901 14 15",
    "sg:postcode":"3032",
    "sg:province":"Bern",
    "wof:name":"Sfm Studer Conseil En Management",
    "wof:placetype":"venue"
},
  "geometry": {"coordinates":[7.3866410255,46.9679946899],"type":"Point"}
}