{
  "type": "Feature",
  "properties": {
    "iso:country":"CH",
    "sg:address":"Mattenenge 3 3011 Bern. Postfach",
    "sg:city":"Bern",
    "sg:orig_category":"Herstellung von sonstigen chemischen Erzeugnissen",
    "sg:postcode":"3005",
    "sg:province":"Bern",
    "wof:name":"Robert Fuhrer Chem.-techn. Produkte; Verkauf.",
    "wof:placetype":"venue"
},
  "geometry": {"coordinates":[7.4580588341,46.9491043091],"type":"Point"}
}