{
  "type": "Feature",
  "properties": {
    "iso:country":"CH",
    "sg:address":"N\u00fcschelerstrasse 1 8001 Z\u00fcrich. Postfach",
    "sg:city":"Z\u00fcrich",
    "sg:orig_category":"Interessenvertretungen",
    "sg:postcode":"8001",
    "sg:province":"Z\u00fcrich",
    "wof:name":"Stiftung Schweizer Monatshefte Finanzielle Weiterf\u00fchrung D. Schweiz. Monatshefte Usw.",
    "wof:placetype":"venue"
},
  "geometry": {"coordinates":[8.5373077393,47.3711204529],"type":"Point"}
}