{
  "type": "Feature",
  "properties": {
    "iso:country":"CH",
    "sg:city":"Rickenbach",
    "sg:orig_category":"Wirtschaft U Handel, Arbeit, Allgemeines zum Thema Arbeit",
    "sg:postcode":"4613",
    "sg:province":"Solothurn",
    "wof:name":"Human Line",
    "wof:placetype":"venue"
},
  "geometry": {"coordinates":[7.85655,47.339371],"type":"Point"}
}