{
  "type": "Feature",
  "properties": {
    "iso:country":"CH",
    "sg:address":"Obergoldbach",
    "sg:city":"Obergoldbach",
    "sg:orig_category":"RESTAURANTS: TEA-ROOMS",
    "sg:phone":"+41 31 701 03 41",
    "sg:postcode":"3434",
    "sg:province":"Bern",
    "wof:name":"Oppliger Ernst",
    "wof:placetype":"venue"
},
  "geometry": {"coordinates":[7.6737618446,46.9615936279],"type":"Point"}
}