{
  "type": "Feature",
  "properties": {
    "iso:country":"CH",
    "sg:address":"Bernstrasse 102",
    "sg:city":"Zollikofen",
    "sg:orig_category":"Instandhaltung U Reparatur von Automobilen",
    "sg:phone":"+41 56 618 70 90",
    "sg:postcode":"3052",
    "sg:province":"Bern",
    "wof:name":"E. L\u00e4uffer Ag",
    "wof:placetype":"venue"
},
  "geometry": {"coordinates":[8.2910175323,47.3471755981],"type":"Point"}
}