{
  "type": "Feature",
  "properties": {
    "iso:country":"CH",
    "sg:address":"Veeboden",
    "sg:city":"Entlebuch",
    "sg:orig_category":"Sportvereine Ballsport Tennis",
    "sg:phone":"+41 41 480 27 07",
    "sg:postcode":"6162",
    "sg:province":"Luzern",
    "wof:name":"Tc Entlebuch",
    "wof:placetype":"venue"
},
  "geometry": {"coordinates":[8.0708618164,46.9898643494],"type":"Point"}
}