{
  "type": "Feature",
  "properties": {
    "iso:country":"CH",
    "sg:address":"Avenue Mon-loisir 7",
    "sg:city":"Lausanne",
    "sg:orig_category":"Elektroinstallation",
    "sg:phone":"+41 21 616 10 86",
    "sg:postcode":"1006",
    "sg:province":"Vaud",
    "wof:name":"Michel Jaquier Installations T\u00e9lephoniques",
    "wof:placetype":"venue"
},
  "geometry": {"coordinates":[6.6330089569,46.5120124817],"type":"Point"}
}