{
  "type": "Feature",
  "properties": {
    "iso:country":"CH",
    "sg:address":"Via Del Sole 15",
    "sg:city":"Ascona",
    "sg:orig_category":"Konsulate",
    "sg:phone":"+41 91 791 48 55",
    "sg:postcode":"6612",
    "sg:province":"Ticino",
    "wof:name":"Consolato Della Norvegia",
    "wof:placetype":"venue"
},
  "geometry": {"coordinates":[8.7744121552,46.1557235718],"type":"Point"}
}