{
  "type": "Feature",
  "properties": {
    "iso:country":"CH",
    "sg:address":"Hutmatt 168",
    "sg:city":"Utzigen",
    "sg:orig_category":"Bauschreinerei Herstellung von Konstruktionsteilen, Fertigbauteilen U Ausbauelementen aus Holz",
    "sg:postcode":"3068",
    "sg:province":"Bern",
    "wof:name":"Grunder Ag Schreinerei & Bestattungen",
    "wof:placetype":"venue"
},
  "geometry": {"coordinates":[7.565515,46.960808],"type":"Point"}
}