{
  "type": "Feature",
  "properties": {
    "iso:country":"CH",
    "sg:address":"Gl\u00e4rnischstrasse 4 8820 W\u00e4denswil. Postfach 554",
    "sg:city":"W\u00e4denswil",
    "sg:orig_category":"Versicherungen Hauptagenturen",
    "sg:phone":"+41 17808288",
    "sg:postcode":"8820",
    "sg:province":"Z\u00fcrich",
    "wof:name":"Die Mobiliar Versicherungen & Vorsorge",
    "wof:placetype":"venue"
},
  "geometry": {"coordinates":[8.6686649323,47.2302055359],"type":"Point"}
}