{
  "type": "Feature",
  "properties": {
    "addr:full":"Rue Des Deux-ponts 27 1200 Genf. Postfach Gen\u00e8ve Gen\u00e8ve 1201",
    "addr:housenumber":"27",
    "addr:postcode":"1200 genf. postfach;1201",
    "addr:street":"Rue Des Deux-Ponts",
    "iso:country":"CH",
    "sg:address":"Rue Des Deux-ponts 27 1200 Genf. Postfach",
    "sg:city":"Gen\u00e8ve",
    "sg:orig_category":"Detailhandel mit Brot, Back U S\u00fcsswaren",
    "sg:postcode":"1201",
    "sg:province":"Gen\u00e8ve",
    "wof:name":"Boulangerie - Tea-room Deux-ponts, Martins",
    "wof:placetype":"venue"
},
  "geometry": {"coordinates":[6.129691,46.200615],"type":"Point"}
}