{
  "type": "Feature",
  "properties": {
    "iso:country":"CH",
    "sg:address":"3916",
    "sg:city":"Ferden",
    "sg:classifiers":[
        {
            "category":"Restaurant",
            "type":"Food & Drink"
        }
    ],
    "sg:phone":"+41 19105778",
    "sg:postcode":"3916",
    "sg:province":"Valais",
    "wof:name":"Restaurant Kunsteisbahn",
    "wof:placetype":"venue"
},
  "geometry": {"coordinates":[8.6050662994,47.3277244568],"type":"Point"}
}