{
  "type": "Feature",
  "properties": {
    "iso:country":"CH",
    "sg:address":"B\u00e4renloch 1",
    "sg:city":"Chur",
    "sg:orig_category":"Finanzierungsinstitutionen",
    "sg:phone":"+41 81 921 44 55",
    "sg:postcode":"7000",
    "sg:province":"Graubunden",
    "wof:name":"Val Signina Holding Ag",
    "wof:placetype":"venue"
},
  "geometry": {"coordinates":[9.5325145721,46.8478965759],"type":"Point"}
}