{
  "type": "Feature",
  "properties": {
    "iso:country":"CH",
    "sg:address":"Rosenmattweg 58",
    "sg:city":"Tenniken",
    "sg:classifiers":[
        {
            "category":"Government",
            "subcategory":"Fire Station",
            "type":"Public Place"
        }
    ],
    "sg:phone":"+41 61 973 83 30",
    "sg:postcode":"4456",
    "sg:province":"Basel-Landschaft",
    "sg:tags":[
        "thermal",
        "power",
        "block-type"
    ],
    "wof:name":"Hwt Motorentechnik",
    "wof:placetype":"venue"
},
  "geometry": {"coordinates":[7.8142,47.438591],"type":"Point"}
}