{
  "type": "Feature",
  "properties": {
    "iso:country":"CH",
    "sg:address":"Senago Via",
    "sg:city":"Pazzallo",
    "sg:orig_category":"Detektivb\u00fcros U \u00dcberwachung",
    "sg:phone":"+41 91 994 50 67",
    "sg:postcode":"6912",
    "sg:province":"Ticino",
    "wof:name":"Cm Investigazioni Di Calderari Moreno",
    "wof:placetype":"venue"
},
  "geometry": {"coordinates":[8.9382839203,45.9828186035],"type":"Point"}
}