{
  "type": "Feature",
  "properties": {
    "iso:country":"CH",
    "sg:address":"Oeliweg 2",
    "sg:city":"Marthalen",
    "sg:orig_category":"Sanit\u00e4rinstallation Tank Reinigung and Revision",
    "sg:phone":"+41 52 319 30 30",
    "sg:postcode":"8460",
    "sg:province":"Z\u00fcrich",
    "wof:name":"Zeindler Haustechnik Gmbh Sanit\u00c4r & Heizung",
    "wof:placetype":"venue"
},
  "geometry": {"coordinates":[8.6515445709,47.6286888123],"type":"Point"}
}