{
  "type": "Feature",
  "properties": {
    "iso:country":"CH",
    "sg:address":"Gurmels",
    "sg:city":"Gurmels",
    "sg:classifiers":[
        {
            "category":"Banks & Credit Unions",
            "subcategory":"Bank",
            "type":"Services"
        }
    ],
    "sg:phone":"+41 26 674 30 30",
    "sg:postcode":"3212",
    "sg:province":"Fribourg",
    "wof:name":"Raiffeisenbank",
    "wof:placetype":"venue"
},
  "geometry": {"coordinates":[7.17323,46.888309],"type":"Point"}
}