{
  "type": "Feature",
  "properties": {
    "iso:country":"CH",
    "sg:address":"Baarerstrasse 43",
    "sg:city":"Zug",
    "sg:orig_category":"Architektur U Ingenieurb\u00fcros",
    "sg:phone":"+41 41 711 19 14",
    "sg:postcode":"6300",
    "sg:province":"Zug",
    "wof:name":"Brunnschweiler Heer Ag",
    "wof:placetype":"venue"
},
  "geometry": {"coordinates":[8.51658,47.173843],"type":"Point"}
}