{
  "type": "Feature",
  "properties": {
    "iso:country":"CH",
    "sg:address":"Chemin De Mapraz 2 1226 Th\u00f4nex. Postfach",
    "sg:city":"Ch\u00eane-bourg",
    "sg:orig_category":"Bauspenglerei Zimmerei, Dachdeckerei, Bauspenglerei U Abdichtung",
    "sg:phone":"+41 22 348 77 18",
    "sg:postcode":"1225",
    "sg:province":"Gen\u00e8ve",
    "wof:name":"Grazinao Bertizzolo Installations Sanitaires",
    "wof:placetype":"venue"
},
  "geometry": {"coordinates":[6.190212,46.187267],"type":"Point"}
}