{
  "type": "Feature",
  "properties": {
    "iso:country":"CH",
    "sg:address":"Route De La Ferme 9",
    "sg:city":"Estavayer-le-lac",
    "sg:orig_category":"Fachdetailhandel in Verkaufsr\u00e4umen",
    "sg:postcode":"1470",
    "sg:province":"Fribourg",
    "wof:name":"Mod\u00e8le Passion S\u00e0rl",
    "wof:placetype":"venue"
},
  "geometry": {"coordinates":[6.8538298607,46.8454818726],"type":"Point"}
}