{
  "type": "Feature",
  "properties": {
    "iso:country":"CH",
    "sg:address":"3961",
    "sg:city":"Vissoie",
    "sg:orig_category":"Stukkateurgewerbe, Gipserei U Verputzerei",
    "sg:phone":"+41 27 475 13 40",
    "sg:postcode":"3961",
    "sg:province":"Valais",
    "wof:name":"Luc Crettaz Gypserie & Peinture",
    "wof:placetype":"venue"
},
  "geometry": {"coordinates":[7.5864248276,46.2146835327],"type":"Point"}
}