{
  "type": "Feature",
  "properties": {
    "iso:country":"CH",
    "sg:address":"Talackerstrasse 17 8065 Z\u00fcrich. Postfach",
    "sg:city":"Z\u00fcrich",
    "sg:orig_category":"Handelsvermittlung von Textilien, Bekleidung, Schuhen U Lederwaren",
    "sg:postcode":"8065",
    "sg:province":"Z\u00fcrich",
    "wof:name":"Modeagentur Gianni Bertoldo",
    "wof:placetype":"venue"
},
  "geometry": {"coordinates":[8.5370502472,47.3706207275],"type":"Point"}
}