{
  "type": "Feature",
  "properties": {
    "iso:country":"CH",
    "sg:address":"Oberfeldstr 118",
    "sg:city":"Gunzgen",
    "sg:orig_category":"Pulvermetallurgie Schmieden, Pressen, Stanzen U Profilwalzen von Metallen",
    "sg:phone":"+41 62 216 26 27",
    "sg:postcode":"4617",
    "sg:province":"Solothurn",
    "wof:name":"Lsb Stanzformenbau Ag",
    "wof:placetype":"venue"
},
  "geometry": {"coordinates":[7.8315401077,47.3117408752],"type":"Point"}
}