{
  "type": "Feature",
  "properties": {
    "addr:full":"Silberwisstrasse 14 G\u00e4hwil St. Gallen 9534",
    "addr:housenumber":"14;st.",
    "addr:postcode":"9534",
    "addr:street":"Silberwisstrasse",
    "iso:country":"CH",
    "sg:address":"Silberwisstrasse 14",
    "sg:city":"G\u00e4hwil",
    "sg:classifiers":[
        {
            "category":"Manufacturing",
            "subcategory":"Tools & Machinery",
            "type":"Manufacturing & Wholesale Goods"
        }
    ],
    "sg:phone":"+41 71 931 44 30",
    "sg:postcode":"9534",
    "sg:province":"St. Gallen",
    "sg:tags":[
        "part",
        "turned",
        "cnc"
    ],
    "wof:name":"Wehrli Fertigungstechnik",
    "wof:placetype":"venue"
},
  "geometry": {"coordinates":[9.002861,47.396393],"type":"Point"}
}