{
  "type": "Feature",
  "properties": {
    "iso:country":"CH",
    "sg:address":"9473 Gams. Postfach 51",
    "sg:city":"Gams",
    "sg:orig_category":"Instandhaltung U Reparatur von Automobilen Schmieden",
    "sg:phone":"+41 32 935 13 35",
    "sg:postcode":"9473",
    "sg:province":"St. Gallen",
    "wof:name":"Schmid Et Co.",
    "wof:placetype":"venue"
},
  "geometry": {"coordinates":[6.6076431274,46.9809684753],"type":"Point"}
}