{
  "type": "Feature",
  "properties": {
    "iso:country":"CH",
    "sg:address":"Valegia Via 19",
    "sg:city":"Montagnola",
    "sg:orig_category":"Verwaltung von Immobilien",
    "sg:postcode":"6926",
    "sg:province":"Ticino",
    "wof:name":"Ciosso Sa",
    "wof:placetype":"venue"
},
  "geometry": {"coordinates":[8.9150333405,45.9833717346],"type":"Point"}
}