{
  "type": "Feature",
  "properties": {
    "iso:country":"CH",
    "sg:address":"Bernstrasse 70",
    "sg:city":"Kehrsatz",
    "sg:orig_category":"Gymnastik U Fitnesszentren",
    "sg:phone":"+41 71 636 17 88",
    "sg:postcode":"3122",
    "sg:province":"Bern",
    "wof:name":"Judith Huber Stauffer-studio",
    "wof:placetype":"venue"
},
  "geometry": {"coordinates":[9.1671361923,47.5793037415],"type":"Point"}
}