{
  "type": "Feature",
  "properties": {
    "iso:country":"CH",
    "sg:address":"Zum H\u00f6lzli 33",
    "sg:city":"Winterthur",
    "sg:orig_category":"Organisationen der Wohlfahrtspflege",
    "sg:phone":"+41 52 233 59 26",
    "sg:postcode":"8405",
    "sg:province":"Z\u00fcrich",
    "wof:name":"Pro Juventute Bezirkssekretariat",
    "wof:placetype":"venue"
},
  "geometry": {"coordinates":[8.7737979889,47.4831085205],"type":"Point"}
}