{
  "type": "Feature",
  "properties": {
    "iso:country":"CH",
    "sg:address":"Burgerstrasse 17 6003 Luzern. Postfach",
    "sg:city":"Luzern",
    "sg:orig_category":"Garne U Zwirne",
    "sg:postcode":"6003",
    "sg:province":"Luzern",
    "wof:name":"Strickgarn-einkaufsgenossenschaft Steg",
    "wof:placetype":"venue"
},
  "geometry": {"coordinates":[8.3028726578,47.0501403809],"type":"Point"}
}