{
  "type": "Feature",
  "properties": {
    "iso:country":"CH",
    "sg:address":"3754 Diemtigen. Postfach",
    "sg:city":"Schwenden",
    "sg:classifiers":[
        {
            "category":"Travel",
            "subcategory":"Hotels & Motels",
            "type":"Entertainment"
        }
    ],
    "sg:postcode":"3757",
    "sg:province":"Bern",
    "sg:tags":[
        "hotels",
        "mit",
        "restaurant"
    ],
    "wof:name":"Ulrich Erb",
    "wof:placetype":"venue"
},
  "geometry": {"coordinates":[7.5575098991,46.6429710388],"type":"Point"}
}