{
  "type": "Feature",
  "properties": {
    "iso:country":"CH",
    "sg:address":"Badenerstrasse 18",
    "sg:city":"Schlieren",
    "sg:orig_category":"Herstellung von Konstruktionsteilen, Fertigbauteilen U Ausbauelementen aus Holz",
    "sg:phone":"+41 17304458",
    "sg:postcode":"8952",
    "sg:province":"Z\u00fcrich",
    "wof:name":"Z\u00fcrrer Walter",
    "wof:placetype":"venue"
},
  "geometry": {"coordinates":[8.4448480606,47.3975830078],"type":"Point"}
}