{
  "type": "Feature",
  "properties": {
    "iso:country":"CH",
    "sg:address":"Piazza Monte Ceneri 9",
    "sg:city":"Rovio",
    "sg:orig_category":"Grosshandel mit Tabakwaren",
    "sg:postcode":"6821",
    "sg:province":"Ticino",
    "wof:name":"Tabak-sud-import Sa",
    "wof:placetype":"venue"
},
  "geometry": {"coordinates":[8.9870500565,45.9332351685],"type":"Point"}
}