{
  "type": "Feature",
  "properties": {
    "iso:country":"CH",
    "sg:address":"Rainstrasse 5",
    "sg:city":"Jona",
    "sg:orig_category":"Detailhandel mit Damenbekleidung",
    "sg:phone":"+41 55 212 11 28",
    "sg:postcode":"8645",
    "sg:province":"St. Gallen",
    "wof:name":"Midinette S.-m.heiniger Atelier F\u00fcr Damenbekleidung",
    "wof:placetype":"venue"
},
  "geometry": {"coordinates":[8.838726,47.232826],"type":"Point"}
}