{
  "type": "Feature",
  "properties": {
    "iso:country":"CH",
    "sg:address":"Avenue Rosemont 5",
    "sg:city":"Lausanne",
    "sg:orig_category":"Finanzierungsinstitutionen",
    "sg:phone":"+41 21 321 19 19",
    "sg:postcode":"1006",
    "sg:province":"Vaud",
    "wof:name":"Cog\u00e9finance Sa",
    "wof:placetype":"venue"
},
  "geometry": {"coordinates":[6.6350569725,46.5159606934],"type":"Point"}
}