{
  "type": "Feature",
  "properties": {
    "addr:full":"B\u00e4rengasse 26 Aarburg Aargau 4663",
    "addr:housenumber":"26",
    "addr:postcode":"4663",
    "addr:street":"Baerengasse",
    "iso:country":"CH",
    "sg:address":"B\u00e4rengasse 26",
    "sg:city":"Aarburg",
    "sg:orig_category":"Industrie, Sonstige Industrieunternehmungen",
    "sg:phone":"+41 5147693456",
    "sg:postcode":"4663",
    "sg:province":"Aargau",
    "wof:name":"Golden Wood",
    "wof:placetype":"venue"
},
  "geometry": {"coordinates":[-73.53800200000001,45.465824],"type":"Point"}
}