{
  "type": "Feature",
  "properties": {
    "iso:country":"CH",
    "sg:address":"K\u00f6nizstrasse 189 3097 Liebefeld. Postfach 11",
    "sg:city":"Liebefeld",
    "sg:orig_category":"Unternehmensberatung",
    "sg:phone":"+41 31 972 57 27",
    "sg:postcode":"3097",
    "sg:province":"Bern",
    "wof:name":"Umiker Unternehmensberatung Gmbh",
    "wof:placetype":"venue"
},
  "geometry": {"coordinates":[7.4157471657,46.93409729],"type":"Point"}
}