{
  "type": "Feature",
  "properties": {
    "iso:country":"CH",
    "sg:address":"Chemin De La Halle 2",
    "sg:city":"B\u00e9vilard",
    "sg:orig_category":"Primarschulen",
    "sg:phone":"+41 32 492 17 65",
    "sg:postcode":"2735",
    "sg:province":"Bern",
    "wof:name":"Ecole Primaire",
    "wof:placetype":"venue"
},
  "geometry": {"coordinates":[7.2844481468,47.2363014221],"type":"Point"}
}