{
  "type": "Feature",
  "properties": {
    "iso:country":"CH",
    "sg:address":"B\u00fcrlisb\u00fcel 9475 Sevelen. Postfach",
    "sg:city":"Sevelen",
    "sg:orig_category":"Herstellung von sonstigen Nahrungsmitteln",
    "sg:postcode":"9475",
    "sg:province":"St. Gallen",
    "wof:name":"Vitalfood Wyler Nahrungsmittel; Neuentwicklung Usw.",
    "wof:placetype":"venue"
},
  "geometry": {"coordinates":[9.4822540283,47.1234169006],"type":"Point"}
}