{
  "type": "Feature",
  "properties": {
    "iso:country":"CH",
    "sg:address":"Rue Des Mouettes 16",
    "sg:city":"Yverdon-les-bains",
    "sg:orig_category":"Softwareentwicklung U beratung",
    "sg:postcode":"1400",
    "sg:province":"Vaud",
    "wof:name":"Du Mo Informatik, Gemeindetreuhand Ag",
    "wof:placetype":"venue"
},
  "geometry": {"coordinates":[7.6187448502,46.7323303223],"type":"Point"}
}