{
  "type": "Feature",
  "properties": {
    "iso:country":"CH",
    "sg:address":"Klosterberg 15",
    "sg:city":"Basel",
    "sg:orig_category":"Datenverarbeitungsdienste",
    "sg:phone":"+41 55 240 75 57",
    "sg:postcode":"4051",
    "sg:province":"Basel-Stadt",
    "wof:name":"Adrian Schnyder Edv-dienstleistungen",
    "wof:placetype":"venue"
},
  "geometry": {"coordinates":[8.86229,47.250717],"type":"Point"}
}