{
  "type": "Feature",
  "properties": {
    "iso:country":"CH",
    "sg:address":"Mettlenstrasse 1",
    "sg:city":"Etziken",
    "sg:orig_category":"Finanzierungsinstitutionen",
    "sg:phone":"+41 32 614 40 51",
    "sg:postcode":"4554",
    "sg:province":"Solothurn",
    "wof:name":"Anchalifinanz Gmbh",
    "wof:placetype":"venue"
},
  "geometry": {"coordinates":[7.6471691132,47.1858444214],"type":"Point"}
}