{
  "type": "Feature",
  "properties": {
    "iso:country":"CH",
    "sg:address":"Hauptstrasse 35",
    "sg:city":"Birsfelden",
    "sg:orig_category":"Detailhandel Reparatur von Gebrauchsg\u00fctern Vermietung von Gebrauchsg\u00fctern",
    "sg:phone":"+41 61 373 14 30",
    "sg:postcode":"4127",
    "sg:province":"Basel-Landschaft",
    "wof:name":"Joe's Multimedia Ag",
    "wof:placetype":"venue"
},
  "geometry": {"coordinates":[7.620554924,47.5540161133],"type":"Point"}
}