{
  "type": "Feature",
  "properties": {
    "iso:country":"CH",
    "sg:address":"T\u00e4scherloch 730",
    "sg:city":"Triesenberg",
    "sg:classifiers":[
        {
            "category":"Restaurant",
            "type":"Food & Drink"
        }
    ],
    "sg:phone":"+423 262 89 78",
    "sg:postcode":"9497",
    "wof:name":"Caf\u00e9 Heustr\u00e4ffl",
    "wof:placetype":"venue"
},
  "geometry": {"coordinates":[9.5426206589,47.1128997803],"type":"Point"}
}