{
  "type": "Feature",
  "properties": {
    "addr:full":"Kirchstrasse 11 Dietikon Z\u00fcrich 8953",
    "addr:housenumber":"11",
    "addr:postcode":"8953",
    "addr:street":"Kirchstrasse",
    "iso:country":"CH",
    "sg:address":"Kirchstrasse 11",
    "sg:city":"Dietikon",
    "sg:orig_category":"Chemische Industrie Herstellung von sonstigen organischen Grundstoffen U Chemikalien",
    "sg:phone":"+41 17300587",
    "sg:postcode":"8953",
    "sg:province":"Z\u00fcrich",
    "wof:name":"Gafner Ernst Ag",
    "wof:placetype":"venue"
},
  "geometry": {"coordinates":[8.402393,47.406342],"type":"Point"}
}