{
  "type": "Feature",
  "properties": {
    "iso:country":"CH",
    "sg:address":"Rue Centrale 40",
    "sg:city":"Conthey",
    "sg:orig_category":"Detailhandel mit Waren verschiedener Art, Hauptrichtung Nahrungsmittel",
    "sg:phone":"+41 27 346 11 35",
    "sg:postcode":"1964",
    "sg:province":"Valais",
    "wof:name":"Coop Plan-conthey",
    "wof:placetype":"venue"
},
  "geometry": {"coordinates":[7.3069877625,46.2307167053],"type":"Point"}
}