{
  "type": "Feature",
  "properties": {
    "iso:country":"CH",
    "sg:address":"M\u00fcrini 27",
    "sg:city":"Ried-brig",
    "sg:orig_category":"Sonstiger spezialisierter Hoch U Tiefbau",
    "sg:phone":"+41 27 952 15 40",
    "sg:postcode":"3911",
    "sg:province":"Valais",
    "wof:name":"Clemenz Kundenmaurer Gmbh",
    "wof:placetype":"venue"
},
  "geometry": {"coordinates":[7.8695178032,46.2319335938],"type":"Point"}
}