{
  "type": "Feature",
  "properties": {
    "iso:country":"CH",
    "sg:address":"1405",
    "sg:city":"Pomy",
    "sg:orig_category":"Instandhaltung U Reparatur von Automobilen",
    "sg:phone":"+41 24 425 86 43",
    "sg:postcode":"1405",
    "sg:province":"Vaud",
    "wof:name":"Carrosserie Fran\u00e7ois Ottonin",
    "wof:placetype":"venue"
},
  "geometry": {"coordinates":[6.6688499451,46.7578010559],"type":"Point"}
}