{
  "type": "Feature",
  "properties": {
    "iso:country":"CH",
    "sg:address":"Dorfstrasse 7",
    "sg:city":"Birrhard",
    "sg:classifiers":[
        {
            "category":"Structure",
            "subcategory":"Tower",
            "type":"Public Place"
        }
    ],
    "sg:phone":"+41 56 225 26 66",
    "sg:postcode":"5244",
    "sg:province":"Aargau",
    "sg:tags":[
        "awning",
        "marquee"
    ],
    "wof:name":"Rolsa Storenbau",
    "wof:placetype":"venue"
},
  "geometry": {"coordinates":[8.2420682907,47.4314155579],"type":"Point"}
}