{
  "type": "Feature",
  "properties": {
    "iso:country":"CH",
    "sg:address":"Baarerstrasse 14",
    "sg:city":"Zug",
    "sg:orig_category":"Datenverarbeitungsdienste Sonstige mit der Informatik verbundene T\u00e4tigkeiten",
    "sg:phone":"+41 56 640 07 88",
    "sg:postcode":"6300",
    "sg:province":"Zug",
    "wof:name":"Mgcs, Gysel Martin Computer Services Ag",
    "wof:placetype":"venue"
},
  "geometry": {"coordinates":[8.516651,47.172081],"type":"Point"}
}