{
  "type": "Feature",
  "properties": {
    "iso:country":"CH",
    "sg:address":"Bachmattstrasse 2 4622 Egerkingen. Postfach 256",
    "sg:city":"Egerkingen",
    "sg:orig_category":"Finanzierungsinstitutionen",
    "sg:phone":"+41 41 711 44 34",
    "sg:postcode":"4622",
    "sg:province":"Solothurn",
    "wof:name":"Ms Makler Service Ag",
    "wof:placetype":"venue"
},
  "geometry": {"coordinates":[7.8031191826,47.3242149353],"type":"Point"}
}