{
  "type": "Feature",
  "properties": {
    "iso:country":"CH",
    "sg:address":"Sarganserstrasse 34",
    "sg:city":"Vilters",
    "sg:classifiers":[
        {
            "category":"Travel",
            "subcategory":"Hotels & Motels",
            "type":"Entertainment"
        }
    ],
    "sg:phone":"+41 19200039",
    "sg:postcode":"7324",
    "sg:province":"St. Gallen",
    "sg:tags":[
        "hotels",
        "mit",
        "restaurant"
    ],
    "wof:name":"Gasthaus Rundi, Meier Werner",
    "wof:placetype":"venue"
},
  "geometry": {"coordinates":[8.6784477234,47.2719116211],"type":"Point"}
}