{
  "type": "Feature",
  "properties": {
    "iso:country":"CH",
    "sg:address":"B\u00f6hl 273",
    "sg:city":"Waldstatt",
    "sg:orig_category":"Herstellung von Metallerzeugnissen ohne Maschinenbau",
    "sg:phone":"+41 71 351 42 78",
    "sg:postcode":"9104",
    "sg:province":"Appenzell Ausserrhoden",
    "wof:name":"Karl Kr\u00fcsi Profilpresswerk",
    "wof:placetype":"venue"
},
  "geometry": {"coordinates":[9.2844648361,47.354385376],"type":"Point"}
}