{
  "type": "Feature",
  "properties": {
    "iso:country":"CH",
    "sg:address":"Klybeckstrasse 126 4057 Basel. Postfach",
    "sg:city":"Basel",
    "sg:orig_category":"Forstwirtschaft ohne Dienstleistungen in der Forstwirtschaft",
    "sg:postcode":"4051",
    "sg:province":"Basel-Stadt",
    "wof:name":"Forstunternehmen Gebr\u00fcder Flury Ag",
    "wof:placetype":"venue"
},
  "geometry": {"coordinates":[7.6615247726,47.1808280945],"type":"Point"}
}