{
  "type": "Feature",
  "properties": {
    "addr:full":"Kalchtaren 1 Schongau Luzern 6288",
    "addr:housenumber":"1",
    "addr:postcode":"6288",
    "addr:street":"Kalchtaren",
    "iso:country":"CH",
    "sg:address":"Kalchtaren 1",
    "sg:city":"Schongau",
    "sg:classifiers":[
        {
            "category":"Professional",
            "subcategory":"Engineering",
            "type":"Services"
        }
    ],
    "sg:phone":"+41 41 917 10 15",
    "sg:postcode":"6288",
    "sg:province":"Luzern",
    "sg:tags":[
        "civil",
        "underground"
    ],
    "wof:name":"Alois Weibel Gmbh",
    "wof:placetype":"venue"
},
  "geometry": {"coordinates":[8.282082,47.269203],"type":"Point"}
}