{
  "type": "Feature",
  "properties": {
    "iso:country":"CH",
    "sg:address":"Z\u00fcrcherstrasse 36",
    "sg:city":"Volketswil",
    "sg:orig_category":"Detailhandel mit B\u00fcchern, Zeitungen, Schreib U Papeteriewaren",
    "sg:postcode":"8604",
    "sg:province":"Z\u00fcrich",
    "wof:name":"Logooffice Ag",
    "wof:placetype":"venue"
},
  "geometry": {"coordinates":[8.65721,47.394089],"type":"Point"}
}