{
  "type": "Feature",
  "properties": {
    "iso:country":"CH",
    "sg:address":"Birststrasse 10",
    "sg:city":"Baar",
    "sg:orig_category":"Unclassifiable Establishments",
    "sg:postcode":"6340",
    "sg:province":"Zug",
    "wof:name":"K\u00fcnzi Treuhand, Controlling & Consulting",
    "wof:placetype":"venue"
},
  "geometry": {"coordinates":[8.5324430466,47.1986236572],"type":"Point"}
}