{
  "type": "Feature",
  "properties": {
    "iso:country":"CH",
    "sg:address":"Untere Bisr\u00fctistrasse 28",
    "sg:city":"Bischofszell",
    "sg:orig_category":"Kosmetikinstitute",
    "sg:phone":"+41 31 951 27 87",
    "sg:postcode":"9220",
    "sg:province":"Thurgau",
    "wof:name":"Sandra Tellenbach Kosmetikinstitut Aloe",
    "wof:placetype":"venue"
},
  "geometry": {"coordinates":[7.4793868065,46.9354743958],"type":"Point"}
}