{
  "type": "Feature",
  "properties": {
    "iso:country":"CH",
    "sg:address":"St\u00e4dtchen 8",
    "sg:city":"Uznach",
    "sg:orig_category":"Detailhandel mit Damenbekleidung Detailhandel mit Herrenbekleidung",
    "sg:phone":"+41 55 280 42 94",
    "sg:postcode":"8730",
    "sg:province":"St. Gallen",
    "wof:name":"Jeans-huus Boutique",
    "wof:placetype":"venue"
},
  "geometry": {"coordinates":[8.9852409363,47.2248497009],"type":"Point"}
}