{
  "type": "Feature",
  "properties": {
    "iso:country":"CH",
    "sg:address":"Schaffhauserstrasse 81",
    "sg:city":"Schaffhausen",
    "sg:orig_category":"Tankstellen",
    "sg:phone":"+41 12144111",
    "sg:postcode":"8200",
    "sg:province":"Schaffhausen",
    "wof:name":"Esso Rheinfall Carmelo Colombo",
    "wof:placetype":"venue"
},
  "geometry": {"coordinates":[8.6048116684,47.6944274902],"type":"Point"}
}