{
  "type": "Feature",
  "properties": {
    "addr:full":"Staatsstrasse 10 Niederb\u00fcren St. Gallen 9246",
    "addr:housenumber":"10;st.",
    "addr:postcode":"9246",
    "addr:street":"Staatsstrasse",
    "iso:country":"CH",
    "sg:address":"Staatsstrasse 10",
    "sg:city":"Niederb\u00fcren",
    "sg:classifiers":[
        {
            "category":"Manufacturing",
            "subcategory":"Tools & Machinery",
            "type":"Manufacturing & Wholesale Goods"
        }
    ],
    "sg:phone":"+41 71 424 26 00",
    "sg:postcode":"9246",
    "sg:province":"St. Gallen",
    "sg:tags":[
        "chucking"
    ],
    "wof:name":"Springmann Ag",
    "wof:placetype":"venue"
},
  "geometry": {"coordinates":[9.199939,47.464756],"type":"Point"}
}