{
  "type": "Feature",
  "properties": {
    "iso:country":"CH",
    "sg:address":"T\u00fcffenwies 7",
    "sg:city":"Z\u00fcrich",
    "sg:orig_category":"Grafikateliers, Design Siebdruck",
    "sg:phone":"+41 14312723",
    "sg:postcode":"8064",
    "sg:province":"Z\u00fcrich",
    "wof:name":"Hans Cadisch Beschriftungen & Siebdruck",
    "wof:placetype":"venue"
},
  "geometry": {"coordinates":[8.4926424026,47.3970031738],"type":"Point"}
}