{
  "type": "Feature",
  "properties": {
    "iso:country":"CH",
    "sg:address":"Canova Via 18",
    "sg:city":"Lugano",
    "sg:orig_category":"Finanzierungsinstitutionen",
    "sg:postcode":"6900",
    "sg:province":"Ticino",
    "wof:name":"Argo-nautic Sa",
    "wof:placetype":"venue"
},
  "geometry": {"coordinates":[8.9546422958,46.0042686462],"type":"Point"}
}