{
  "type": "Feature",
  "properties": {
    "iso:country":"CH",
    "sg:address":"Kornfeldstrasse 22 5210 Windisch. Postfach",
    "sg:city":"Windisch",
    "sg:orig_category":"Wohnheime",
    "sg:postcode":"5210",
    "sg:province":"Aargau",
    "wof:name":"Stiftung Windrose Soziale Eingliederung Von Behinderten Menschen Im Wohn- U. Freizeitbereich Usw",
    "wof:placetype":"venue"
},
  "geometry": {"coordinates":[8.2109632492,47.4734306335],"type":"Point"}
}