{
  "type": "Feature",
  "properties": {
    "addr:full":"Murtenstrasse 147 Bern Bern 3008",
    "addr:housenumber":"147",
    "addr:postcode":"3008",
    "addr:street":"Murtenstrasse",
    "iso:country":"CH",
    "sg:address":"Murtenstrasse 147",
    "sg:city":"Bern",
    "sg:classifiers":[
        {
            "category":"Manufacturing",
            "subcategory":"Motor Vehicles & Parts",
            "type":"Manufacturing & Wholesale Goods"
        }
    ],
    "sg:phone":"+41 71 969 40 30",
    "sg:postcode":"3008",
    "sg:province":"Bern",
    "sg:tags":[
        "aluminium",
        "processing",
        "sheet"
    ],
    "wof:name":"Jakob Ag",
    "wof:placetype":"venue"
},
  "geometry": {"coordinates":[9.00223,47.490181],"type":"Point"}
}