{
  "type": "Feature",
  "properties": {
    "iso:country":"CH",
    "sg:address":"Im Postb\u00fcro",
    "sg:city":"Diessenbach",
    "sg:classifiers":[
        {
            "category":"Banks & Credit Unions",
            "subcategory":"Bank",
            "type":"Services"
        }
    ],
    "sg:phone":"+41 32813861",
    "sg:postcode":"3274",
    "sg:province":"Bern",
    "wof:name":"Spar- & Leihkasse, Des Amtsbezirks B\u00fcren",
    "wof:placetype":"venue"
},
  "geometry": {"coordinates":[12.975058,48.909233],"type":"Point"}
}