{
  "type": "Feature",
  "properties": {
    "iso:country":"CH",
    "sg:address":"Avenue Rollier",
    "sg:city":"Leysin",
    "sg:orig_category":"Detailhandel mit fotografischen Artikeln Fachdetailhandel in Verkaufsr\u00e4umen",
    "sg:phone":"+41 24 494 13 52",
    "sg:postcode":"1854",
    "sg:province":"Vaud",
    "wof:name":"Photo Nicca",
    "wof:placetype":"venue"
},
  "geometry": {"coordinates":[7.0082349777,46.3417396545],"type":"Point"}
}