{
  "type": "Feature",
  "properties": {
    "iso:country":"CH",
    "sg:address":"Luzernerstrasse 75",
    "sg:city":"Luzern",
    "sg:classifiers":[
        {
            "category":"Train Station",
            "subcategory":"Light Rail",
            "type":"Transportation"
        }
    ],
    "sg:phone":"+41 41 420 18 01",
    "sg:postcode":"6030",
    "sg:province":"Luzern",
    "sg:tags":[
        "lighting"
    ],
    "wof:name":"Baltensweiler Ag Atelier F\u00fcr Beleuchtungstechnik",
    "wof:placetype":"venue"
},
  "geometry": {"coordinates":[8.3409900665,47.081653595],"type":"Point"}
}