{
  "type": "Feature",
  "properties": {
    "iso:country":"CH",
    "sg:address":"Birkenstrasse 20",
    "sg:city":"Br\u00fcttisellen",
    "sg:orig_category":"Sanit\u00e4r U Heizungsinstallation",
    "sg:phone":"+41 18352222",
    "sg:postcode":"8306",
    "sg:province":"Z\u00fcrich",
    "wof:name":"Kalorbau Ag Heizungsanlagen",
    "wof:placetype":"venue"
},
  "geometry": {"coordinates":[8.626294136,47.4182472229],"type":"Point"}
}