{
  "type": "Feature",
  "properties": {
    "iso:country":"CH",
    "sg:address":"Aeschenplatz 3 4052 Basel. Postfach",
    "sg:city":"Basel",
    "sg:orig_category":"Pensionskassen",
    "sg:phone":"+41 32 323 77 61",
    "sg:postcode":"4051",
    "sg:province":"Basel-Stadt",
    "wof:name":"Fondation Commission Paritaire Rmb/ftmh",
    "wof:placetype":"venue"
},
  "geometry": {"coordinates":[7.5948791504,47.5516624451],"type":"Point"}
}