{
  "type": "Feature",
  "properties": {
    "iso:country":"CH",
    "sg:address":"Ottenbacherstrasse 15-17",
    "sg:city":"Zwillikon",
    "sg:orig_category":"Interessenvertretungen Primarschulen",
    "sg:phone":"+41 17614870",
    "sg:postcode":"8909",
    "sg:province":"Z\u00fcrich",
    "wof:name":"Sonderp\u00e4dagogische Tagesschule F\u00fcr Wahrnehmungsf\u00f6rderung",
    "wof:placetype":"venue"
},
  "geometry": {"coordinates":[8.4422702789,47.2892112732],"type":"Point"}
}