{
  "type": "Feature",
  "properties": {
    "addr:full":"Eaux-vives Rue Des 7 Gen\u00e8ve Gen\u00e8ve 1207",
    "addr:housenumber":"eaux-vives",
    "addr:postcode":"1207",
    "addr:street":"Rue Des 7",
    "iso:country":"CH",
    "sg:address":"Eaux-vives Rue Des 7",
    "sg:city":"Gen\u00e8ve",
    "sg:orig_category":"Detailhandel mit Brot, Back U S\u00fcsswaren",
    "sg:postcode":"1207",
    "sg:province":"Gen\u00e8ve",
    "wof:name":"Mateus C\u00e9line Et S\u00e9bastien",
    "wof:placetype":"venue"
},
  "geometry": {"coordinates":[6.156103,46.201817],"type":"Point"}
}