{
  "type": "Feature",
  "properties": {
    "iso:country":"CH",
    "sg:address":"Birkenstrasse 44",
    "sg:city":"Basel",
    "sg:orig_category":"Interessenvertretungen",
    "sg:postcode":"4055",
    "sg:province":"Basel-Stadt",
    "wof:name":"Stiftung Hinrichsen Kurt",
    "wof:placetype":"venue"
},
  "geometry": {"coordinates":[7.5725412369,47.5565490723],"type":"Point"}
}