{
  "type": "Feature",
  "properties": {
    "iso:country":"CH",
    "sg:address":"Kantonsstrasse 30",
    "sg:city":"Visp",
    "sg:orig_category":"Pensionskassen",
    "sg:phone":"+41 12156300",
    "sg:postcode":"3930",
    "sg:province":"Valais",
    "wof:name":"Personalvorsorgestiftung Der Oz Bankers Ag",
    "wof:placetype":"venue"
},
  "geometry": {"coordinates":[8.7781352997,47.2013778687],"type":"Point"}
}