{
  "type": "Feature",
  "properties": {
    "iso:country":"CH",
    "sg:address":"Grabenhaldenstrasse 18 8583 Sulgen. Postfach 80",
    "sg:city":"Sulgen",
    "sg:orig_category":"Wirtschaftspr\u00fcfung, Steuerberatung U Treuhand",
    "sg:phone":"+41 71 642 44 12",
    "sg:postcode":"8583",
    "sg:province":"Thurgau",
    "wof:name":"Reforminkasso + Treuhand Gmbh",
    "wof:placetype":"venue"
},
  "geometry": {"coordinates":[9.1923418045,47.5400352478],"type":"Point"}
}