{
  "type": "Feature",
  "properties": {
    "iso:country":"CH",
    "sg:address":"Blankweg 27",
    "sg:city":"Ostermundigen",
    "sg:orig_category":"Non-Classified Establishments",
    "sg:postcode":"3072",
    "sg:province":"Bern",
    "wof:name":"Trans-chem Stalder J.",
    "wof:placetype":"venue"
},
  "geometry": {"coordinates":[7.4938130379,46.9559631348],"type":"Point"}
}