{
  "type": "Feature",
  "properties": {
    "iso:country":"CH",
    "sg:address":"Heiselstrasse 124",
    "sg:city":"Niederhasli",
    "sg:orig_category":"Sonstige pers\u00f6nliche Dienstleistungen",
    "sg:phone":"+41 18512021",
    "sg:postcode":"8155",
    "sg:province":"Z\u00fcrich",
    "wof:name":"Evb Esther Vonbank Bilger",
    "wof:placetype":"venue"
},
  "geometry": {"coordinates":[8.4975032806,47.4814453125],"type":"Point"}
}