{
  "type": "Feature",
  "properties": {
    "iso:country":"CH",
    "sg:address":"Dammstrasse 61",
    "sg:city":"Zollikon",
    "sg:orig_category":"Werbeagenturen",
    "sg:phone":"+41 13918273",
    "sg:postcode":"8702",
    "sg:province":"Z\u00fcrich",
    "wof:name":"Roger Biemann Ideen Konzepte Texte",
    "wof:placetype":"venue"
},
  "geometry": {"coordinates":[8.5684747696,47.3404922485],"type":"Point"}
}