{
  "type": "Feature",
  "properties": {
    "iso:country":"CH",
    "sg:address":"Rue Sautter 11",
    "sg:city":"Gen\u00e8ve",
    "sg:classifiers":[
        {
            "category":"Restaurant",
            "type":"Food & Drink"
        }
    ],
    "sg:phone":"+41 22 342 18 13",
    "sg:postcode":"1205",
    "sg:province":"Gen\u00e8ve",
    "wof:name":"Caf\u00e9 Lion D'or De Carouge",
    "wof:placetype":"venue"
},
  "geometry": {"coordinates":[6.1402220726,46.1804504395],"type":"Point"}
}