{
  "type": "Feature",
  "properties": {
    "iso:country":"CH",
    "sg:address":"Untere M\u00fchle",
    "sg:city":"Sch\u00fcpbach",
    "sg:orig_category":"Physiotherapie",
    "sg:phone":"+41 34 497 22 38",
    "sg:postcode":"3535",
    "sg:province":"Bern",
    "wof:name":"Margrit W\u00fcrger Physiotherapie",
    "wof:placetype":"venue"
},
  "geometry": {"coordinates":[7.7352838516,46.9267997742],"type":"Point"}
}