{
  "type": "Feature",
  "properties": {
    "iso:country":"CH",
    "sg:address":"Sch\u00fctzenweg 2d",
    "sg:city":"Thusis",
    "sg:orig_category":"Bestattungswesen",
    "sg:phone":"+41 81 651 20 75",
    "sg:postcode":"7430",
    "sg:province":"Graubunden",
    "wof:name":"Wilhelm Ag Bestattungsinstitut",
    "wof:placetype":"venue"
},
  "geometry": {"coordinates":[9.440192,46.704636],"type":"Point"}
}