{
  "type": "Feature",
  "properties": {
    "iso:country":"CH",
    "sg:address":"Feldstrasse 510",
    "sg:city":"Geroldswil",
    "sg:orig_category":"Fernmeldedienste",
    "sg:phone":"+41 14052997",
    "sg:postcode":"8954",
    "sg:province":"Z\u00fcrich",
    "wof:name":"Telan 1 Ag",
    "wof:placetype":"venue"
},
  "geometry": {"coordinates":[8.4085931778,47.423122406],"type":"Point"}
}