{
  "type": "Feature",
  "properties": {
    "iso:country":"CH",
    "sg:address":"Heerenrainli 6",
    "sg:city":"Hirzel",
    "sg:orig_category":"Erschliessung von Grundst\u00fccken",
    "sg:postcode":"8816",
    "sg:province":"Z\u00fcrich",
    "wof:name":"Bau Und Wohngenossenschaft Linde",
    "wof:placetype":"venue"
},
  "geometry": {"coordinates":[8.6102819443,47.2152671814],"type":"Point"}
}