{
  "type": "Feature",
  "properties": {
    "iso:country":"CH",
    "sg:address":"Chemin De Chantemerle 26",
    "sg:city":"Nyon",
    "sg:orig_category":"Elektroinstallation",
    "sg:phone":"+41 22 994 49 49",
    "sg:postcode":"1260",
    "sg:province":"Vaud",
    "wof:name":"Hanhart Jacques.",
    "wof:placetype":"venue"
},
  "geometry": {"coordinates":[6.2346467972,46.3939399719],"type":"Point"}
}