{
  "type": "Feature",
  "properties": {
    "iso:country":"CH",
    "sg:address":"Dammstrasse 36",
    "sg:city":"Solothurn",
    "sg:orig_category":"D\u00e4mmung gegen K\u00e4lte, W\u00e4rme, Schall U Ersch\u00fctterung",
    "sg:phone":"+41 21 882 52 40",
    "sg:postcode":"4500",
    "sg:province":"Solothurn",
    "wof:name":"Rolf Dreher Travaux D'isolation",
    "wof:placetype":"venue"
},
  "geometry": {"coordinates":[6.6604199409,46.6171188354],"type":"Point"}
}