{
  "type": "Feature",
  "properties": {
    "iso:country":"CH",
    "sg:address":"Chemin De Mancy 30",
    "sg:city":"V\u00e9senaz",
    "sg:classifiers":[
        {
            "category":"Government",
            "subcategory":"Fire Station",
            "type":"Public Place"
        }
    ],
    "sg:phone":"+41 22 752 23 69",
    "sg:postcode":"1222",
    "sg:province":"Gen\u00e8ve",
    "sg:tags":[
        "component",
        "watch",
        "clock"
    ],
    "wof:name":"Ren\u00e9 Etter Atelier M\u00e9canique",
    "wof:placetype":"venue"
},
  "geometry": {"coordinates":[6.203777,46.24609],"type":"Point"}
}