{
  "type": "Feature",
  "properties": {
    "iso:country":"CH",
    "sg:address":"Chemin De La Grande-fin",
    "sg:city":"Vallorbe",
    "sg:orig_category":"Vermietung U Verpachtung von eigenen Immobilien Vermittlung von Immobilien",
    "sg:phone":"+41 32 351 25 45",
    "sg:postcode":"1337",
    "sg:province":"Vaud",
    "wof:name":"Immo Schneider Ag",
    "wof:placetype":"venue"
},
  "geometry": {"coordinates":[7.3598508835,47.1384849548],"type":"Point"}
}