{
  "type": "Feature",
  "properties": {
    "iso:country":"CH",
    "sg:address":"Hafnersberg 3",
    "sg:city":"St.gallen",
    "sg:orig_category":"Allgemeiner Hoch U Tiefbau Allgemeiner Hochbau",
    "sg:phone":"+41 71 311 45 53",
    "sg:postcode":"9000",
    "sg:province":"St. Gallen",
    "wof:name":"Schmidhauser Alex Gmbh",
    "wof:placetype":"venue"
},
  "geometry": {"coordinates":[9.381518,47.424088],"type":"Point"}
}