{
  "type": "Feature",
  "properties": {
    "iso:country":"CH",
    "sg:address":"Bruderwald 9043 Trogen. Postfach 21",
    "sg:city":"Trogen",
    "sg:orig_category":"Landwirtschaftliche Genossenschaften",
    "sg:postcode":"9043",
    "sg:province":"Appenzell Ausserrhoden",
    "wof:name":"Land-& Alpwirtschaftliche Genossenschaft Trogen",
    "wof:placetype":"venue"
},
  "geometry": {"coordinates":[9.479719162,47.3974189758],"type":"Point"}
}