{
  "type": "Feature",
  "properties": {
    "iso:country":"CH",
    "sg:address":"Industrieplatz 4",
    "sg:city":"Neuhausen",
    "sg:orig_category":"Grosshandel mit Nahrungsmitteln, Getr\u00e4nken U Tabakwaren ohne ausgepr\u00e4gten Schwerpunkt",
    "sg:postcode":"8212",
    "sg:province":"Schaffhausen",
    "wof:name":"Roberto's Food-importe Eichmann",
    "wof:placetype":"venue"
},
  "geometry": {"coordinates":[8.6185321808,47.6796531677],"type":"Point"}
}