{
  "type": "Feature",
  "properties": {
    "iso:country":"CH",
    "sg:address":"Rigistrasse 1",
    "sg:city":"Zug",
    "sg:orig_category":"Herstellung von Maschinen f\u00fcr die Nahrungsmittel, Getr\u00e4nkeherstellung U die Tabakverarbeitung",
    "sg:phone":"+41 41 711 05 11",
    "sg:postcode":"6300",
    "sg:province":"Zug",
    "wof:name":"Cerex Ag",
    "wof:placetype":"venue"
},
  "geometry": {"coordinates":[8.5145177841,47.1705703735],"type":"Point"}
}