{
  "type": "Feature",
  "properties": {
    "iso:country":"CH",
    "sg:address":"5325",
    "sg:city":"Leibstadt",
    "sg:orig_category":"Vereine Musik/Blasmusik",
    "sg:postcode":"5325",
    "sg:province":"Aargau",
    "wof:name":"Musikgesellschaft",
    "wof:placetype":"venue"
},
  "geometry": {"coordinates":[8.1745605469,47.590259552],"type":"Point"}
}