{
  "type": "Feature",
  "properties": {
    "iso:country":"CH",
    "sg:address":"Rue De La Dixence 48",
    "sg:city":"Sion",
    "sg:orig_category":"Architektur U Ingenieurb\u00fcros",
    "sg:phone":"+41 27 203 34 25",
    "sg:postcode":"1950",
    "sg:province":"Valais",
    "wof:name":"Lietti Pierre-alain.",
    "wof:placetype":"venue"
},
  "geometry": {"coordinates":[7.371509,46.227558],"type":"Point"}
}