{
  "type": "Feature",
  "properties": {
    "iso:country":"CH",
    "sg:address":"1260",
    "sg:city":"Nyon",
    "sg:orig_category":"Polizei",
    "sg:phone":"+41 24 475 75 75",
    "sg:postcode":"1260",
    "sg:province":"Vaud",
    "wof:name":"Police Municipale",
    "wof:placetype":"venue"
},
  "geometry": {"coordinates":[6.9471468925,46.2516288757],"type":"Point"}
}