{
  "type": "Feature",
  "properties": {
    "iso:country":"CH",
    "sg:address":"Oetwilerstrasse 31",
    "sg:city":"H\u00fcttikon",
    "sg:orig_category":"Wirtschaftspr\u00fcfung, Steuerberatung U Treuhand",
    "sg:postcode":"8115",
    "sg:province":"Z\u00fcrich",
    "wof:name":"L\u00fcssi Office Gmbh",
    "wof:placetype":"venue"
},
  "geometry": {"coordinates":[8.3873653412,47.4442863464],"type":"Point"}
}