{
  "type": "Feature",
  "properties": {
    "iso:country":"CH",
    "sg:address":"Schwanenfelsstrasse 10a",
    "sg:city":"Neuhausen",
    "sg:orig_category":"Fotografisches Gewerbe U fotografische Laboratorien",
    "sg:postcode":"8212",
    "sg:province":"Schaffhausen",
    "wof:name":"Wessendorf Karin, Fotographin",
    "wof:placetype":"venue"
},
  "geometry": {"coordinates":[8.6189823151,47.6878509521],"type":"Point"}
}