{
  "type": "Feature",
  "properties": {
    "iso:country":"CH",
    "sg:address":"Route Cantonale",
    "sg:city":"Riddes",
    "sg:orig_category":"Detailhandel mit Waren verschiedener Art, Hauptrichtung Nahrungsmittel",
    "sg:phone":"+41 27 306 44 45",
    "sg:postcode":"1908",
    "sg:province":"Valais",
    "wof:name":"Pam Sa",
    "wof:placetype":"venue"
},
  "geometry": {"coordinates":[7.2157649994,46.1690216064],"type":"Point"}
}