{
  "type": "Feature",
  "properties": {
    "iso:country":"CH",
    "sg:address":"B\u00fchlstrasse 40 3012 Bern. Postfach",
    "sg:city":"Bern",
    "sg:orig_category":"Betrieb von Taxis",
    "sg:phone":"+41 31 301 83 34",
    "sg:postcode":"3005",
    "sg:province":"Bern",
    "wof:name":"Fr. Wyssen Taxiunternehmung",
    "wof:placetype":"venue"
},
  "geometry": {"coordinates":[7.431503,46.952579],"type":"Point"}
}