{
  "type": "Feature",
  "properties": {
    "iso:country":"CH",
    "sg:address":"Rue H.f.sandoz 46",
    "sg:city":"Tavannes",
    "sg:classifiers":[
        {
            "category":"Education",
            "subcategory":"Library",
            "type":"Public Place"
        }
    ],
    "sg:phone":"+41 32 481 20 40",
    "sg:postcode":"2710",
    "sg:province":"Bern",
    "sg:tags":[
        "u",
        "bibliotheken",
        "archive"
    ],
    "wof:name":"Biblioth\u00e8que Municipale",
    "wof:placetype":"venue"
},
  "geometry": {"coordinates":[7.202045,47.22076],"type":"Point"}
}