{
  "type": "Feature",
  "properties": {
    "iso:country":"CH",
    "sg:address":"Via Al Giardino Tenero 6598 Tenero. Postfach",
    "sg:city":"Tenero",
    "sg:orig_category":"Grosshandel mit sonstigen Gebrauchs U Verbrauchsg\u00fctern",
    "sg:postcode":"6598",
    "sg:province":"Ticino",
    "wof:name":"L'armeria B&b Sa",
    "wof:placetype":"venue"
},
  "geometry": {"coordinates":[8.850810051,46.180683136],"type":"Point"}
}