{
  "type": "Feature",
  "properties": {
    "iso:country":"CH",
    "sg:address":"Bahnhofstrasse 10 6300 Zug. Postfach 255",
    "sg:city":"Zug",
    "sg:orig_category":"Privatbanken",
    "sg:phone":"+41 22 310 00 77",
    "sg:postcode":"6301",
    "sg:province":"Zug",
    "wof:name":"Mourgue D'algue & Cie",
    "wof:placetype":"venue"
},
  "geometry": {"coordinates":[6.1499857903,46.2018737793],"type":"Point"}
}