{
  "type": "Feature",
  "properties": {
    "iso:country":"CH",
    "sg:address":"St. Antonistrasse 9",
    "sg:city":"Sarnen",
    "sg:orig_category":"Sportvereine Eissport Curling",
    "sg:phone":"+41 41 660 94 62",
    "sg:postcode":"6060",
    "sg:province":"Obwalden",
    "wof:name":"C.c.melchsee-frutt",
    "wof:placetype":"venue"
},
  "geometry": {"coordinates":[8.2489128113,46.8952484131],"type":"Point"}
}