{
  "type": "Feature",
  "properties": {
    "iso:country":"CH",
    "sg:address":"Sonnegg 5 Ballwil 6276 Hohenrain. Postfach",
    "sg:city":"Ballwil",
    "sg:orig_category":"Mechanik",
    "sg:phone":"+41 41 910 43 44",
    "sg:postcode":"6275",
    "sg:province":"Luzern",
    "wof:name":"Gawlick Sven Pipeline-service",
    "wof:placetype":"venue"
},
  "geometry": {"coordinates":[8.3156652451,47.1791915894],"type":"Point"}
}