{
  "type": "Feature",
  "properties": {
    "iso:country":"CH",
    "sg:address":"Stepackerstrasse 6",
    "sg:city":"H\u00fcntwangen",
    "sg:orig_category":"Sonstige k\u00fcnstlerische U schriftstellerische T\u00e4tigkeiten U Darbietungen",
    "sg:phone":"+41 18690713",
    "sg:postcode":"8194",
    "sg:province":"Z\u00fcrich",
    "wof:name":"Brigitta Sigrist Porzellanmal-atelier",
    "wof:placetype":"venue"
},
  "geometry": {"coordinates":[8.4911460876,47.5954017639],"type":"Point"}
}