{
  "type": "Feature",
  "properties": {
    "iso:country":"CH",
    "sg:address":"Grafenau 12 6300 Zug. Postfach",
    "sg:city":"Zug",
    "sg:orig_category":"Herstellung von Seifen, Wasch U Reinigungsmitteln",
    "sg:phone":"+41 41 729 25 11",
    "sg:postcode":"6301",
    "sg:province":"Zug",
    "wof:name":"Lever Faberg\u00e9 Gmbh",
    "wof:placetype":"venue"
},
  "geometry": {"coordinates":[8.51193,47.174255],"type":"Point"}
}