{
  "type": "Feature",
  "properties": {
    "iso:country":"CH",
    "sg:address":"Eichholzstrasse 23",
    "sg:city":"Balgach",
    "sg:orig_category":"Grosshandel mit Maschinen U Ausr\u00fcstungen Oberfl\u00e4chenveredlung U W\u00e4rmebehandlung",
    "sg:phone":"+41 71 720 06 55",
    "sg:postcode":"9436",
    "sg:province":"St. Gallen",
    "wof:name":"Ms-oberfl\u00e4chentechnik Ag",
    "wof:placetype":"venue"
},
  "geometry": {"coordinates":[9.6126842499,47.4064674377],"type":"Point"}
}