{
  "type": "Feature",
  "properties": {
    "iso:country":"CH",
    "sg:address":"Mauerrain 5",
    "sg:city":"Bern",
    "sg:orig_category":"Tanzschulen, Tanzlehrer",
    "sg:phone":"+41 31 301 21 26",
    "sg:postcode":"3012",
    "sg:province":"Bern",
    "wof:name":"Doron-tanz-seminare Tanz-& Ballettschule",
    "wof:placetype":"venue"
},
  "geometry": {"coordinates":[7.4345798492,46.9491157532],"type":"Point"}
}