{
  "type": "Feature",
  "properties": {
    "iso:country":"CH",
    "sg:address":"W\u00fchre 7",
    "sg:city":"Z\u00fcrich",
    "sg:orig_category":"Detailhandel mit Damenbekleidung Herstellung von W\u00e4sche",
    "sg:phone":"+41 12118009",
    "sg:postcode":"8001",
    "sg:province":"Z\u00fcrich",
    "wof:name":"Manuela San Martin Morejon-jaquet",
    "wof:placetype":"venue"
},
  "geometry": {"coordinates":[8.5418376923,47.3705406189],"type":"Point"}
}