{
  "type": "Feature",
  "properties": {
    "iso:country":"CH",
    "sg:address":"Chemin De La Charri\u00e8re 8",
    "sg:city":"St-maurice",
    "sg:orig_category":"Herstellung von M\u00f6beln verschiedener Art Zimmerei",
    "sg:phone":"+41 24 485 14 82",
    "sg:postcode":"1890",
    "sg:province":"Valais",
    "wof:name":"Josian Barman S\u00e0rl Eb\u00e9nisterie & Menuiserie",
    "wof:placetype":"venue"
},
  "geometry": {"coordinates":[7.010368824,46.200466156],"type":"Point"}
}