{
  "type": "Feature",
  "properties": {
    "iso:country":"CH",
    "sg:address":"Ulmenstrasse 3",
    "sg:city":"Kreuzlingen",
    "sg:orig_category":"Maler U Glasergewerbe",
    "sg:phone":"+41 71 672 62 65",
    "sg:postcode":"8280",
    "sg:province":"Thurgau",
    "wof:name":"Malergesch\u00e4ft Bauer Andreas",
    "wof:placetype":"venue"
},
  "geometry": {"coordinates":[9.1648521423,47.6411132812],"type":"Point"}
}