{
  "type": "Feature",
  "properties": {
    "iso:country":"CH",
    "sg:address":"Choiseul Avenue 21a",
    "sg:city":"Versoix",
    "sg:orig_category":"Interessenvertretungen",
    "sg:phone":"+41 22 755 32 32",
    "sg:postcode":"1290",
    "sg:province":"Gen\u00e8ve",
    "wof:name":"Actions En Sante Publique",
    "wof:placetype":"venue"
},
  "geometry": {"coordinates":[6.1633958817,46.2889289856],"type":"Point"}
}