{
  "type": "Feature",
  "properties": {
    "iso:country":"CH",
    "sg:address":"Waldhaus",
    "sg:city":"B\u00fcrgenstock",
    "sg:orig_category":"Unternehmensberatung",
    "sg:phone":"+41 41 610 45 59",
    "sg:postcode":"6363",
    "sg:province":"Nidwalden",
    "wof:name":"Bsi Management Stadelmann Barbara",
    "wof:placetype":"venue"
},
  "geometry": {"coordinates":[8.3868732452,46.9969520569],"type":"Point"}
}