{
  "type": "Feature",
  "properties": {
    "iso:country":"CH",
    "sg:address":"Tramstrasse 22",
    "sg:city":"Pratteln",
    "sg:orig_category":"Schreib U \u00dcbersetzungsb\u00fcros",
    "sg:phone":"+41 61 821 51 77",
    "sg:postcode":"4133",
    "sg:province":"Basel-Landschaft",
    "wof:name":"Maja Gasser \u00dcbersetzungen",
    "wof:placetype":"venue"
},
  "geometry": {"coordinates":[7.6954641342,47.5201530457],"type":"Point"}
}