{
  "type": "Feature",
  "properties": {
    "iso:country":"CH",
    "sg:address":"H\u00fcbelistrasse 11 3612 Steffisburg. Postfach",
    "sg:city":"Steffisburg",
    "sg:orig_category":"Unclassifiable Establishments",
    "sg:phone":"+41 33 221 05 32",
    "sg:postcode":"3612",
    "sg:province":"Bern",
    "wof:name":"Inovavision, Basda K. Web-hosting, Web-design, Internet, Pc-hard- U. Software Usw.",
    "wof:placetype":"venue"
},
  "geometry": {"coordinates":[7.6318788528,46.7643966675],"type":"Point"}
}