{
  "type": "Feature",
  "properties": {
    "iso:country":"CH",
    "sg:address":"2723",
    "sg:city":"Mont-tramelan",
    "sg:classifiers":[
        {
            "category":"Government",
            "subcategory":"Post Office",
            "type":"Public Place"
        }
    ],
    "sg:phone":"+41 32 487 42 71",
    "sg:postcode":"2723",
    "sg:province":"Bern",
    "sg:tags":[
        "die",
        "poststellen"
    ],
    "wof:name":"La Poste",
    "wof:placetype":"venue"
},
  "geometry": {"coordinates":[7.0548901558,47.2105331421],"type":"Point"}
}