{
  "type": "Feature",
  "properties": {
    "iso:country":"CH",
    "sg:address":"Sauffaz Chemin De 5",
    "sg:city":"Penthalaz",
    "sg:orig_category":"Non-Classified Establishments",
    "sg:postcode":"1305",
    "sg:province":"Vaud",
    "wof:name":"Gregorio S.a., Succursale De Penthalaz",
    "wof:placetype":"venue"
},
  "geometry": {"coordinates":[6.5243401527,46.610294342],"type":"Point"}
}