{
  "type": "Feature",
  "properties": {
    "iso:country":"CH",
    "sg:address":"Maiengasse 24",
    "sg:city":"Allschwil",
    "sg:orig_category":"Fahrschulen, Flugschulen",
    "sg:phone":"+41 61 481 97 77",
    "sg:postcode":"4123",
    "sg:province":"Basel-Landschaft",
    "wof:name":"Marc Fernando Fahrschule",
    "wof:placetype":"venue"
},
  "geometry": {"coordinates":[7.5473780632,47.5550270081],"type":"Point"}
}