{
  "type": "Feature",
  "properties": {
    "iso:country":"CH",
    "sg:address":"Schwimmbadstrasse 33",
    "sg:city":"Wettingen",
    "sg:orig_category":"Fotografische Ateliers Fotografisches Gewerbe U fotografische Laboratorien",
    "sg:phone":"+41 22 734 23 15",
    "sg:postcode":"5430",
    "sg:province":"Aargau",
    "wof:name":"Smb Studio Mad Blend Sa",
    "wof:placetype":"venue"
},
  "geometry": {"coordinates":[6.1383957863,46.2119522095],"type":"Point"}
}