{
  "type": "Feature",
  "properties": {
    "iso:country":"CH",
    "sg:address":"Sonnenwiesenstrasse 14",
    "sg:city":"Kreuzlingen",
    "sg:orig_category":"Allgemeiner Hochbau Zimmerei, Dachdeckerei, Bauspenglerei U Abdichtung",
    "sg:phone":"+41 71 385 79 85",
    "sg:postcode":"8280",
    "sg:province":"Thurgau",
    "wof:name":"Egle + Co",
    "wof:placetype":"venue"
},
  "geometry": {"coordinates":[9.273976,47.433266],"type":"Point"}
}