{
  "type": "Feature",
  "properties": {
    "iso:country":"CH",
    "sg:address":"Route Principale 15",
    "sg:city":"Vicques",
    "sg:orig_category":"RESTAURANTS: TEA-ROOMS",
    "sg:postcode":"2824",
    "sg:province":"Jura",
    "wof:name":"Fu, Shun Ling",
    "wof:placetype":"venue"
},
  "geometry": {"coordinates":[7.4108638763,47.3486366272],"type":"Point"}
}