{
  "type": "Feature",
  "properties": {
    "iso:country":"CH",
    "sg:address":"H\u00f6henstrasse 20",
    "sg:city":"Flurlingen",
    "sg:orig_category":"Druckweiterverarbeitung",
    "sg:phone":"+41 52 659 43 23",
    "sg:postcode":"8247",
    "sg:province":"Z\u00fcrich",
    "wof:name":"Wassermann Grafikdesign",
    "wof:placetype":"venue"
},
  "geometry": {"coordinates":[8.630364418,47.6853752136],"type":"Point"}
}