{
  "type": "Feature",
  "properties": {
    "iso:country":"CH",
    "sg:address":"Schiffl\u00e4ndestrasse 23 5000 Aarau. Postfach",
    "sg:city":"Aarau",
    "sg:orig_category":"Softwareentwicklung U beratung",
    "sg:phone":"+41 56 633 66 13",
    "sg:postcode":"5000",
    "sg:province":"Aargau",
    "wof:name":"M\u00fcller Robert Software-service",
    "wof:placetype":"venue"
},
  "geometry": {"coordinates":[8.2893133163,47.3465042114],"type":"Point"}
}