{
  "type": "Feature",
  "properties": {
    "iso:country":"CH",
    "sg:address":"Limmattalstrasse 10",
    "sg:city":"Geroldswil",
    "sg:orig_category":"R\u00fcckgewinnung U Vorbereitung f\u00fcr die Wiederverwertung Recycling von nichtmetallischen Altmaterialien",
    "sg:postcode":"8954",
    "sg:province":"Z\u00fcrich",
    "wof:name":"Rw Recycla Wertstoffe Ag",
    "wof:placetype":"venue"
},
  "geometry": {"coordinates":[8.4140501022,47.4195709229],"type":"Point"}
}