{
  "type": "Feature",
  "properties": {
    "iso:country":"CH",
    "sg:address":"Riant-mont Avenue De 6 1004 Lausanne. Postfach",
    "sg:city":"Lausanne",
    "sg:orig_category":"Elektroinstallation",
    "sg:phone":"+41 22 343 90 90",
    "sg:postcode":"1003",
    "sg:province":"Vaud",
    "wof:name":"Reelsa",
    "wof:placetype":"venue"
},
  "geometry": {"coordinates":[6.1436300278,46.1834945679],"type":"Point"}
}