{
  "type": "Feature",
  "properties": {
    "iso:country":"CH",
    "sg:address":"Kleinh\u00fcningerstrasse 171 4057 Basel. Postfach",
    "sg:city":"Basel",
    "sg:orig_category":"Kauf U Verkauf von Immobilien auf eigene Rechnung",
    "sg:postcode":"4051",
    "sg:province":"Basel-Stadt",
    "wof:name":"Barkuma Ag Liegenschaftenhandel Usw",
    "wof:placetype":"venue"
},
  "geometry": {"coordinates":[7.5906171799,47.5796508789],"type":"Point"}
}