{
  "type": "Feature",
  "properties": {
    "iso:country":"CH",
    "sg:address":"Alte Steinhauserstrasse 1",
    "sg:city":"Cham",
    "sg:orig_category":"Elektro- and elektronische Maschinen Grosshandel",
    "sg:phone":"+41 79 341 76 09",
    "sg:postcode":"6330",
    "sg:province":"Zug",
    "wof:name":"Kabelnet Ag Vertrieb V.lwl-& Cu-datenkabel",
    "wof:placetype":"venue"
},
  "geometry": {"coordinates":[8.4739131927,47.1866035461],"type":"Point"}
}