{
  "type": "Feature",
  "properties": {
    "iso:country":"CH",
    "sg:address":"Auenring 27",
    "sg:city":"Bassersdorf",
    "sg:orig_category":"Detailhandel mit M\u00f6beln U Haushaltsgegenst\u00e4nden",
    "sg:postcode":"8303",
    "sg:province":"Z\u00fcrich",
    "wof:name":"Kiracar.",
    "wof:placetype":"venue"
},
  "geometry": {"coordinates":[8.6219835281,47.4410934448],"type":"Point"}
}