{
  "type": "Feature",
  "properties": {
    "iso:country":"CH",
    "sg:address":"4571",
    "sg:city":"L\u00fcterkofen-ichert",
    "sg:orig_category":"Sportvereine Sch\u00fctzen",
    "sg:phone":"+41 32 675 67 28",
    "sg:postcode":"4571",
    "sg:province":"Solothurn",
    "wof:name":"Standsch\u00fctzengesellschaft",
    "wof:placetype":"venue"
},
  "geometry": {"coordinates":[7.5095710754,47.1624641418],"type":"Point"}
}