{
  "type": "Feature",
  "properties": {
    "iso:country":"CH",
    "sg:address":"B\u00e4rchistrass 9",
    "sg:city":"Marthalen",
    "sg:orig_category":"Instandhaltung U Reparatur von Automobilen",
    "sg:phone":"+41 52 319 26 16",
    "sg:postcode":"8460",
    "sg:province":"Z\u00fcrich",
    "wof:name":"Seeben-garage Gmbh",
    "wof:placetype":"venue"
},
  "geometry": {"coordinates":[8.6494474411,47.6258430481],"type":"Point"}
}