{
  "type": "Feature",
  "properties": {
    "iso:country":"CH",
    "sg:address":"Corso Enrico Pestalozzi 9",
    "sg:city":"Lugano",
    "sg:orig_category":"Finanzierungsinstitutionen",
    "sg:phone":"+41 91 910 06 11",
    "sg:postcode":"6900",
    "sg:province":"Ticino",
    "wof:name":"Cititrust (switzerland) Ltd, Succursale Di Lugano",
    "wof:placetype":"venue"
},
  "geometry": {"coordinates":[8.9522428513,46.00623703],"type":"Point"}
}