{
  "type": "Feature",
  "properties": {
    "iso:country":"CH",
    "sg:address":"Neunbrunnenstrasse 211",
    "sg:city":"Z\u00fcrich",
    "sg:orig_category":"Sonstiger Grosshandel",
    "sg:postcode":"8046",
    "sg:province":"Z\u00fcrich",
    "wof:name":"Folta Impex Import & Export Warenimport, -export, -handel",
    "wof:placetype":"venue"
},
  "geometry": {"coordinates":[8.5297393799,47.4155426025],"type":"Point"}
}