{
  "type": "Feature",
  "properties": {
    "iso:country":"CH",
    "sg:address":"Neuhausstrasse 12 4057 Basel. Postfach",
    "sg:city":"Basel",
    "sg:orig_category":"Sonstiger Grosshandel",
    "sg:postcode":"4051",
    "sg:province":"Basel-Stadt",
    "wof:name":"R\u00fcdiger H.j. & Co Handel Mit Waren Aller Art. Uebernahme V. Buchhaltungsauftraegen Usw",
    "wof:placetype":"venue"
},
  "geometry": {"coordinates":[7.5934128761,47.5824737549],"type":"Point"}
}