{
  "type": "Feature",
  "properties": {
    "iso:country":"CH",
    "sg:address":"L\u00e4nggasse 36b 3600 Thun. Postfach Postfach",
    "sg:city":"Thun",
    "sg:orig_category":"Sonstige Institutionen des Sozialwesens ohne Beherbergung",
    "sg:postcode":"3602",
    "sg:province":"Bern",
    "wof:name":"Michael Gross Trial Sozialp\u00e4d.familienberat.",
    "wof:placetype":"venue"
},
  "geometry": {"coordinates":[7.6223797798,46.7521591187],"type":"Point"}
}