{
  "type": "Feature",
  "properties": {
    "iso:country":"CH",
    "sg:address":"Auf Der Holle 28",
    "sg:city":"Zullwil",
    "sg:orig_category":"Detailhandel mit elektrischen Haushalts-,Radio U Fernsehger\u00e4ten sowie Musikinstrumenten Sonstige Hil",
    "sg:phone":"+41 61 791 06 11",
    "sg:postcode":"4234",
    "sg:province":"Solothurn",
    "wof:name":"Tonstudio Amos Ag",
    "wof:placetype":"venue"
},
  "geometry": {"coordinates":[7.6001501083,47.3907203674],"type":"Point"}
}