{
  "type": "Feature",
  "properties": {
    "iso:country":"CH",
    "sg:address":"Dorstrasse 321",
    "sg:city":"Heiligenschwendi",
    "sg:classifiers":[
        {
            "category":"Travel",
            "subcategory":"Hotels & Motels",
            "type":"Entertainment"
        }
    ],
    "sg:postcode":"3625",
    "sg:province":"Bern",
    "sg:tags":[
        "hotels",
        "mit",
        "restaurant"
    ],
    "wof:name":"Hotel Niesenblick Heiligenschwendi Ag",
    "wof:placetype":"venue"
},
  "geometry": {"coordinates":[7.6868338585,46.7500076294],"type":"Point"}
}