{
  "type": "Feature",
  "properties": {
    "iso:country":"CH",
    "sg:address":"Dreib\u00fcndenstrasse 78",
    "sg:city":"Chur",
    "sg:orig_category":"Softwareentwicklung U beratung",
    "sg:postcode":"7000",
    "sg:province":"Graubunden",
    "wof:name":"Bw Soft Support Ag",
    "wof:placetype":"venue"
},
  "geometry": {"coordinates":[9.5229997635,46.861869812],"type":"Point"}
}