{
  "type": "Feature",
  "properties": {
    "iso:country":"CH",
    "sg:address":"Industrielle Rue 62",
    "sg:city":"Montagne-moutier",
    "sg:orig_category":"Handels-H\u00e4user U Gesellschaften",
    "sg:phone":"+41 32 493 62 68",
    "sg:postcode":"2740",
    "sg:province":"Bern",
    "wof:name":"Rocaries Consulting",
    "wof:placetype":"venue"
},
  "geometry": {"coordinates":[7.3724632263,47.2787246704],"type":"Point"}
}