{
  "type": "Feature",
  "properties": {
    "addr:full":"Grabenackerstrasse 11 M\u00fcnchenstein Basel-Landschaft 4142",
    "addr:housenumber":"11",
    "addr:postcode":"4142",
    "addr:street":"Grabenackerstrasse",
    "iso:country":"CH",
    "sg:address":"Grabenackerstrasse 11",
    "sg:city":"M\u00fcnchenstein",
    "sg:orig_category":"Arztpraxen",
    "sg:phone":"+41 61 411 52 52",
    "sg:postcode":"4142",
    "sg:province":"Basel-Landschaft",
    "wof:name":"Dr.med.hans Rudolf Schlienger Arzt F.allgemeine Medizin Fmh",
    "wof:placetype":"venue"
},
  "geometry": {"coordinates":[7.605352,47.522034],"type":"Point"}
}