{
  "type": "Feature",
  "properties": {
    "iso:country":"CH",
    "sg:address":"Dorfstrasse 33",
    "sg:city":"Windisch",
    "sg:orig_category":"Architektur U Ingenieurb\u00fcros",
    "sg:phone":"+41 56 441 93 36",
    "sg:postcode":"5210",
    "sg:province":"Aargau",
    "wof:name":"Q-met Gmbh",
    "wof:placetype":"venue"
},
  "geometry": {"coordinates":[8.224868,47.481831],"type":"Point"}
}