{
  "type": "Feature",
  "properties": {
    "iso:country":"CH",
    "sg:address":"Wissenbach",
    "sg:city":"Mettmenstetten",
    "sg:orig_category":"Unclassifiable Establishments",
    "sg:postcode":"8932",
    "sg:province":"Z\u00fcrich",
    "wof:name":"A. Sch\u00f6nenberger S\u00f6hne Baumschule & Pflanzencenter",
    "wof:placetype":"venue"
},
  "geometry": {"coordinates":[8.473534584,47.233997345],"type":"Point"}
}