{
  "type": "Feature",
  "properties": {
    "iso:country":"CH",
    "sg:address":"Unterdorf",
    "sg:city":"Kleinwangen",
    "sg:orig_category":"Bauschreinerei Innenausbau",
    "sg:phone":"+41 41 910 14 87",
    "sg:postcode":"6277",
    "sg:province":"Luzern",
    "wof:name":"Hans-ruedi Leu Schreinerei & Innenausbau",
    "wof:placetype":"venue"
},
  "geometry": {"coordinates":[8.298523,47.207664],"type":"Point"}
}