{
  "type": "Feature",
  "properties": {
    "iso:country":"CH",
    "sg:address":"Staatsstrasse 9478 Azmoos. Postfach",
    "sg:city":"Weite",
    "sg:orig_category":"RESTAURANTS: TEA-ROOMS",
    "sg:postcode":"9476",
    "sg:province":"St. Gallen",
    "wof:name":"Bernold",
    "wof:placetype":"venue"
},
  "geometry": {"coordinates":[9.4766893387,47.0802955627],"type":"Point"}
}