{
  "type": "Feature",
  "properties": {
    "iso:country":"CH",
    "sg:address":"Widengasse 19c",
    "sg:city":"Frick",
    "sg:orig_category":"Finanzierungsinstitutionen",
    "sg:postcode":"5070",
    "sg:province":"Aargau",
    "wof:name":"Santalucia Finanzberatung",
    "wof:placetype":"venue"
},
  "geometry": {"coordinates":[8.0248451233,47.5070228577],"type":"Point"}
}