{
  "type": "Feature",
  "properties": {
    "iso:country":"CH",
    "sg:address":"Ringstrasse 9",
    "sg:city":"Allschwil",
    "sg:orig_category":"Herstellung von industriellen Prozesssteuerungsanlagen",
    "sg:postcode":"4123",
    "sg:province":"Basel-Landschaft",
    "wof:name":"Induprocessing Knutti",
    "wof:placetype":"venue"
},
  "geometry": {"coordinates":[7.3157129288,47.0305671692],"type":"Point"}
}