{
  "type": "Feature",
  "properties": {
    "iso:country":"CH",
    "sg:address":"Scaletta Via 3",
    "sg:city":"Muzzano",
    "sg:orig_category":"Baugewerbe Mechanische Werkst\u00e4tten",
    "sg:phone":"+41 21 784 26 05",
    "sg:postcode":"6933",
    "sg:province":"Ticino",
    "wof:name":"Rlco Rossi Line Construction Sa",
    "wof:placetype":"venue"
},
  "geometry": {"coordinates":[6.652606,46.52684],"type":"Point"}
}