{
  "type": "Feature",
  "properties": {
    "iso:country":"CH",
    "sg:address":"8713",
    "sg:city":"Uerikon",
    "sg:orig_category":"Primarschulen",
    "sg:postcode":"8713",
    "sg:province":"Z\u00fcrich",
    "wof:name":"Primarschule Moritzberg",
    "wof:placetype":"venue"
},
  "geometry": {"coordinates":[8.758769989,47.2344284058],"type":"Point"}
}