{
  "type": "Feature",
  "properties": {
    "iso:country":"CH",
    "sg:address":"Rue Des Moulins 2",
    "sg:city":"Travers",
    "sg:orig_category":"Detailhandel mit Fleisch U Fleischwaren",
    "sg:phone":"+41 32 863 35 36",
    "sg:postcode":"2105",
    "sg:province":"Neuch\u00e2tel",
    "wof:name":"St\u00e9phane D\u00e4nzer Boucherie",
    "wof:placetype":"venue"
},
  "geometry": {"coordinates":[6.6721158028,46.9386940002],"type":"Point"}
}