{
  "type": "Feature",
  "properties": {
    "iso:country":"CH",
    "sg:address":"3965",
    "sg:city":"Chippis",
    "sg:orig_category":"Pensionskassen",
    "sg:phone":"+41 27 457 51 11",
    "sg:postcode":"3965",
    "sg:province":"Valais",
    "wof:name":"Fondation De Pr\u00e9voyance Alusuisse Lonza Group Sa",
    "wof:placetype":"venue"
},
  "geometry": {"coordinates":[7.5419597626,46.274269104],"type":"Point"}
}