{
  "type": "Feature",
  "properties": {
    "iso:country":"CH",
    "sg:address":"Metallstrasse 9 6300 Zug. Postfach 4331",
    "sg:city":"Zug",
    "sg:orig_category":"Revision Wirtschaftspr\u00fcfung, Steuerberatung U Treuhand",
    "sg:phone":"+41 71 911 64 37",
    "sg:postcode":"6304",
    "sg:province":"Zug",
    "wof:name":"Horus Treuhand Gmbh",
    "wof:placetype":"venue"
},
  "geometry": {"coordinates":[9.0463685989,47.4699134827],"type":"Point"}
}