{
  "type": "Feature",
  "properties": {
    "iso:country":"CH",
    "sg:address":"Alte Rheinstrasse 29",
    "sg:city":"Kriessern",
    "sg:orig_category":"Tapping Devices",
    "sg:phone":"+41 71 757 59 00",
    "sg:postcode":"9451",
    "sg:province":"St. Gallen",
    "wof:name":"Tic Ag Tapmatic International Coorp.",
    "wof:placetype":"venue"
},
  "geometry": {"coordinates":[9.6114244461,47.3607177734],"type":"Point"}
}