{
  "type": "Feature",
  "properties": {
    "iso:country":"CH",
    "sg:address":"Ponte Brolla",
    "sg:city":"Tegna",
    "sg:orig_category":"Verwaltung von Immobilien",
    "sg:postcode":"6652",
    "sg:province":"Ticino",
    "wof:name":"Kellerhals Rudolf",
    "wof:placetype":"venue"
},
  "geometry": {"coordinates":[8.7480897903,46.1866798401],"type":"Point"}
}