{
  "type": "Feature",
  "properties": {
    "iso:country":"CH",
    "sg:address":"Promenade-noirerue De La 3 2000 Neuch\u00e2tel. Postfach",
    "sg:city":"Neuenburg",
    "sg:orig_category":"Grosshandel mit sonstigen Maschinen U Ausr\u00fcstungen f\u00fcr Industrie, Handel U Schiffahrt",
    "sg:phone":"+41 32 724 03 33",
    "sg:postcode":"2000",
    "sg:province":"Neuch\u00e2tel",
    "wof:name":"Hudine Sa",
    "wof:placetype":"venue"
},
  "geometry": {"coordinates":[6.927590847,46.9902915955],"type":"Point"}
}