{
  "type": "Feature",
  "properties": {
    "iso:country":"CH",
    "sg:address":"Kichstrasse 3 4536 Attiswil. Postfach",
    "sg:city":"Attiswil",
    "sg:orig_category":"Herstellung von elektrischen Lampen U Leuchten",
    "sg:phone":"+41 21 869 70 11",
    "sg:postcode":"4536",
    "sg:province":"Bern",
    "wof:name":"Audio Light Michoud Christian",
    "wof:placetype":"venue"
},
  "geometry": {"coordinates":[6.4675898552,46.555770874],"type":"Point"}
}