{
  "type": "Feature",
  "properties": {
    "iso:country":"CH",
    "sg:address":"Riedmattstrasse 14",
    "sg:city":"R\u00fcmlang",
    "sg:classifiers":[
        {
            "category":"Professional",
            "subcategory":"Advertising",
            "type":"Services"
        }
    ],
    "sg:phone":"+41 18171233",
    "sg:postcode":"8153",
    "sg:province":"Z\u00fcrich",
    "sg:tags":[
        "article",
        "cardboard"
    ],
    "wof:name":"Cartwork Ag",
    "wof:placetype":"venue"
},
  "geometry": {"coordinates":[8.522045,47.460827],"type":"Point"}
}