{
  "type": "Feature",
  "properties": {
    "iso:country":"CH",
    "sg:address":"1376",
    "sg:city":"Goumoens-la-ville",
    "sg:orig_category":"Verwertung von Milch",
    "sg:postcode":"1376",
    "sg:province":"Vaud",
    "wof:name":"Soci\u00e9t\u00e9 De Laiterie De Goumo\u00ebns-la-ville",
    "wof:placetype":"venue"
},
  "geometry": {"coordinates":[6.6045541763,46.6579742432],"type":"Point"}
}