{
  "type": "Feature",
  "properties": {
    "iso:country":"CH",
    "sg:address":"Alpe Des Chaux",
    "sg:city":"Gryon",
    "sg:orig_category":"Reiseb\u00fcros U Reiseveranstalter",
    "sg:phone":"+41 24 498 15 51",
    "sg:postcode":"1882",
    "sg:province":"Vaud",
    "wof:name":"Soci\u00e9t\u00e9 D'animation Et De Services Sa",
    "wof:placetype":"venue"
},
  "geometry": {"coordinates":[7.100924015,46.2900695801],"type":"Point"}
}