{
  "type": "Feature",
  "properties": {
    "iso:country":"CH",
    "sg:address":"Industriepark Altgraben 468a",
    "sg:city":"H\u00e4rkingen",
    "sg:orig_category":"Architektur U Ingenieurb\u00fcros",
    "sg:phone":"+41 62 398 20 70",
    "sg:postcode":"4624",
    "sg:province":"Solothurn",
    "wof:name":"Duralloy Engineering",
    "wof:placetype":"venue"
},
  "geometry": {"coordinates":[7.817022,47.309055],"type":"Point"}
}