{
  "type": "Feature",
  "properties": {
    "iso:country":"CH",
    "sg:address":"Bernstrasse 39",
    "sg:city":"Jegenstorf",
    "sg:orig_category":"Laser Telemetering Systems",
    "sg:phone":"+41 31 762 05 45",
    "sg:postcode":"3303",
    "sg:province":"Bern",
    "wof:name":"Intorig Gmbh",
    "wof:placetype":"venue"
},
  "geometry": {"coordinates":[7.505273819,47.0450820923],"type":"Point"}
}