{
  "type": "Feature",
  "properties": {
    "iso:country":"CH",
    "sg:address":"Pioda 1a",
    "sg:city":"Crana",
    "sg:orig_category":"Grosshandel mit Holz U Bauelementen aus Holz Grosshandel mit Holz U Baustoffen",
    "sg:phone":"+41 91 797 17 04",
    "sg:postcode":"6611",
    "sg:province":"Ticino",
    "wof:name":"Armand Cortes Importazione Di Legname",
    "wof:placetype":"venue"
},
  "geometry": {"coordinates":[8.6099214554,46.2046813965],"type":"Point"}
}