{
  "type": "Feature",
  "properties": {
    "iso:country":"CH",
    "sg:address":"Kanzleistrasse 103",
    "sg:city":"Z\u00fcrich",
    "sg:classifiers":[
        {
            "category":"Restaurant",
            "type":"Food & Drink"
        }
    ],
    "sg:phone":"+41 12414229",
    "sg:postcode":"8004",
    "sg:province":"Z\u00fcrich",
    "wof:name":"Restaurant Carlos",
    "wof:placetype":"venue"
},
  "geometry": {"coordinates":[8.5222578049,47.3761711121],"type":"Point"}
}