{
  "type": "Feature",
  "properties": {
    "iso:country":"CH",
    "sg:address":"Boulevard James-fazy 18",
    "sg:city":"Gen\u00e8ve",
    "sg:orig_category":"Erbringung von sonstigen Dienstleistungen f\u00fcr Unterhaltung, Erholung U Freizeit Sonstige Hilfsdienst",
    "sg:phone":"+41 22 731 79 63",
    "sg:postcode":"1201",
    "sg:province":"Gen\u00e8ve",
    "wof:name":"Agence Artistique Bornoz",
    "wof:placetype":"venue"
},
  "geometry": {"coordinates":[6.1409897804,46.208240509],"type":"Point"}
}