{
  "type": "Feature",
  "properties": {
    "iso:country":"CH",
    "sg:address":"Klingental 17",
    "sg:city":"Basel",
    "sg:classifiers":[
        {
            "category":"Education",
            "subcategory":"Vocational School",
            "type":"Public Place"
        }
    ],
    "sg:phone":"+41 61 683 37 02",
    "sg:postcode":"4058",
    "sg:province":"Basel-Stadt",
    "sg:tags":[
        "technical",
        "course",
        "training",
        "seminar"
    ],
    "wof:name":"Birvani Ag",
    "wof:placetype":"venue"
},
  "geometry": {"coordinates":[7.5900020599,47.5621757507],"type":"Point"}
}