{
  "type": "Feature",
  "properties": {
    "iso:country":"CH",
    "sg:address":"Rue Du Rh\u00f4ne 118 1204 Gen\u00e8ve Case Postale 6364",
    "sg:city":"Gen\u00e8ve",
    "sg:orig_category":"Effektenvermittlung Broker",
    "sg:phone":"+41 22 704 06 33",
    "sg:postcode":"1201",
    "sg:province":"Gen\u00e8ve",
    "wof:name":"Acies Asset Management Sa",
    "wof:placetype":"venue"
},
  "geometry": {"coordinates":[6.1547689438,46.2024841309],"type":"Point"}
}