{
  "type": "Feature",
  "properties": {
    "iso:country":"CH",
    "sg:address":"B\u00e4chigenstrasse 5a",
    "sg:city":"Arnegg",
    "sg:orig_category":"Grosshandel mit Eisenwaren sowie Installationsbedarf f\u00fcr Gas, Wasser U Heizung Wasserversorgung",
    "sg:phone":"+41 79 209 94 34",
    "sg:postcode":"9212",
    "sg:province":"St. Gallen",
    "wof:name":"Diener Gebr. Ag",
    "wof:placetype":"venue"
},
  "geometry": {"coordinates":[9.255490303,47.4429893494],"type":"Point"}
}