{
  "type": "Feature",
  "properties": {
    "iso:country":"CH",
    "sg:address":"Tramstrasse 28",
    "sg:city":"Diepoldsau",
    "sg:orig_category":"Tankstellen",
    "sg:phone":"+41 71 730 03 80",
    "sg:postcode":"9444",
    "sg:province":"St. Gallen",
    "wof:name":"Agip (suisse) Sa",
    "wof:placetype":"venue"
},
  "geometry": {"coordinates":[9.6505537033,47.3894615173],"type":"Point"}
}