{
  "type": "Feature",
  "properties": {
    "iso:country":"CH",
    "sg:address":"Dychweg 8",
    "sg:city":"Arlesheim",
    "sg:orig_category":"Herstellung von Betonerzeugnissen f\u00fcr den Bau",
    "sg:phone":"+41 61 706 96 10",
    "sg:postcode":"4144",
    "sg:province":"Basel-Landschaft",
    "wof:name":"Ringo-t\u00fcren Ag",
    "wof:placetype":"venue"
},
  "geometry": {"coordinates":[7.6081881523,47.4958572388],"type":"Point"}
}