{
  "type": "Feature",
  "properties": {
    "iso:country":"CH",
    "sg:address":"2903",
    "sg:city":"Villars-sur-font",
    "sg:orig_category":"Primarschulen",
    "sg:phone":"+41 32 466 49 84",
    "sg:postcode":"2903",
    "sg:province":"Jura",
    "wof:name":"Ecole Primaire De Villars",
    "wof:placetype":"venue"
},
  "geometry": {"coordinates":[7.0733299255,47.3839988708],"type":"Point"}
}