{
  "type": "Feature",
  "properties": {
    "iso:country":"CH",
    "sg:address":"Montalinstrasse",
    "sg:city":"Felsberg",
    "sg:orig_category":"Wohnheime",
    "sg:postcode":"7012",
    "sg:province":"Graubunden",
    "wof:name":"Stiftung Altersheim Felsberg",
    "wof:placetype":"venue"
},
  "geometry": {"coordinates":[9.4842700958,46.8464660645],"type":"Point"}
}