{
  "type": "Feature",
  "properties": {
    "iso:country":"CH",
    "sg:address":"Hauptstrasse 25 3186 D\u00fcdingen. Postfach 95",
    "sg:city":"D\u00fcdingen",
    "sg:classifiers":[
        {
            "category":"Travel",
            "subcategory":"Hotels & Motels",
            "type":"Entertainment"
        }
    ],
    "sg:phone":"+41 19100804",
    "sg:postcode":"3186",
    "sg:province":"Fribourg",
    "sg:tags":[
        "hotels",
        "mit",
        "restaurant"
    ],
    "wof:name":"Hotel Central",
    "wof:placetype":"venue"
},
  "geometry": {"coordinates":[8.5796003342,47.319103241],"type":"Point"}
}