{
  "type": "Feature",
  "properties": {
    "iso:country":"CH",
    "sg:address":"Lindauerstrasse 32",
    "sg:city":"N\u00fcrensdorf",
    "sg:orig_category":"G\u00fcterbef\u00f6rderung im Strassenverkehr",
    "sg:phone":"+41 79 608 57 32",
    "sg:postcode":"8309",
    "sg:province":"Z\u00fcrich",
    "wof:name":"Charles M\u00fcller Transporte",
    "wof:placetype":"venue"
},
  "geometry": {"coordinates":[8.6514091492,47.444229126],"type":"Point"}
}