{
  "type": "Feature",
  "properties": {
    "iso:country":"CH",
    "sg:address":"De-luserna Avenue 12 1203 Gen\u00e8ve. Postfach",
    "sg:city":"Gen\u00e8ve",
    "sg:classifiers":[
        {
            "category":"Travel",
            "subcategory":"Hotels & Motels",
            "type":"Entertainment"
        }
    ],
    "sg:postcode":"1203",
    "sg:province":"Gen\u00e8ve",
    "sg:tags":[
        "hotels",
        "mit",
        "restaurant"
    ],
    "wof:name":"Walther Antonio",
    "wof:placetype":"venue"
},
  "geometry": {"coordinates":[9.7641716003,46.4287643433],"type":"Point"}
}