{
  "type": "Feature",
  "properties": {
    "iso:country":"CH",
    "sg:address":"Z\u00fcrcherstrasse 76",
    "sg:city":"Neuenhof",
    "sg:orig_category":"Detailhandel mit Waren verschiedener Art, Hauptrichtung Nahrungsmittel Fachdetailhandel mit Nahrungs",
    "sg:phone":"+41 56 406 47 46",
    "sg:postcode":"5432",
    "sg:province":"Aargau",
    "wof:name":"B. Riggio Gmbh Specialit\u00e0 Italiana",
    "wof:placetype":"venue"
},
  "geometry": {"coordinates":[8.3215703964,47.4536628723],"type":"Point"}
}