{
  "type": "Feature",
  "properties": {
    "iso:country":"CH",
    "sg:address":"Niedermattweg 11",
    "sg:city":"Tenniken",
    "sg:orig_category":"R\u00fcckgewinnung U Vorbereitung f\u00fcr die Wiederverwertung Recycling",
    "sg:phone":"+41 61 971 51 50",
    "sg:postcode":"4456",
    "sg:province":"Basel-Landschaft",
    "wof:name":"Hoppe Otto, Autoersatzteile Und Motoren Occasionsersatzteile, Motoren; Handel",
    "wof:placetype":"venue"
},
  "geometry": {"coordinates":[7.8093848228,47.4390487671],"type":"Point"}
}