{
  "type": "Feature",
  "properties": {
    "iso:country":"CH",
    "sg:address":"Dammstrasse 5",
    "sg:city":"Z\u00fcrich",
    "sg:orig_category":"K\u00fcnstlerische U schriftstellerische T\u00e4tigkeiten U Darbietungen",
    "sg:phone":"+41 21 731 44 51",
    "sg:postcode":"8037",
    "sg:province":"Z\u00fcrich",
    "wof:name":"Maibat Sa",
    "wof:placetype":"venue"
},
  "geometry": {"coordinates":[6.6933631897,46.506275177],"type":"Point"}
}