{
  "type": "Feature",
  "properties": {
    "addr:full":"St. Gallerstrasse 82 8400 Winterthur. Postfach 932 Winterthur Z\u00fcrich 8401",
    "addr:housenumber":"82;932",
    "addr:postcode":"8400;8401",
    "addr:street":"St. Gallerstrasse;Postfach",
    "iso:country":"CH",
    "sg:address":"St. Gallerstrasse 82 8400 Winterthur. Postfach 932",
    "sg:city":"Winterthur",
    "sg:orig_category":"Architektur U Ingenieurb\u00fcros Grosshandel mit B\u00fcrom\u00f6beln",
    "sg:phone":"+41 71 385 95 90",
    "sg:postcode":"8401",
    "sg:province":"Z\u00fcrich",
    "wof:name":"Wanko Design Gmbh",
    "wof:placetype":"venue"
},
  "geometry": {"coordinates":[9.254742,47.416878],"type":"Point"}
}