{
  "type": "Feature",
  "properties": {
    "iso:country":"CH",
    "sg:address":"G\u00e4tterli 25",
    "sg:city":"Bachenb\u00fclach",
    "sg:orig_category":"Unclassifiable Establishments",
    "sg:postcode":"8184",
    "sg:province":"Z\u00fcrich",
    "wof:name":"Meier + Rohrer Gmbh",
    "wof:placetype":"venue"
},
  "geometry": {"coordinates":[8.5485334396,47.5072898865],"type":"Point"}
}