{
  "type": "Feature",
  "properties": {
    "iso:country":"CH",
    "sg:address":"Waldegg",
    "sg:city":"Zollbr\u00fcck",
    "sg:orig_category":"Herstellung von sonstigen landwirtschaftlichen Maschinen",
    "sg:phone":"+41 34 496 10 10",
    "sg:postcode":"3436",
    "sg:province":"Bern",
    "wof:name":"Hans Brechb\u00fchl Ag",
    "wof:placetype":"venue"
},
  "geometry": {"coordinates":[7.7407269478,46.9797325134],"type":"Point"}
}