{
  "type": "Feature",
  "properties": {
    "iso:country":"CH",
    "sg:address":"Route De Malagnou 48",
    "sg:city":"Gen\u00e8ve",
    "sg:orig_category":"Kosmetikinstitute",
    "sg:phone":"+41 32 913 41 41",
    "sg:postcode":"1208",
    "sg:province":"Gen\u00e8ve",
    "wof:name":"Martine Frei Institut De Beaut\u00e9 Privil\u00e8ge",
    "wof:placetype":"venue"
},
  "geometry": {"coordinates":[6.8229870796,47.099899292],"type":"Point"}
}