{
  "type": "Feature",
  "properties": {
    "iso:country":"CH",
    "sg:address":"J\u00f6chlerweg 9",
    "sg:city":"Baar",
    "sg:orig_category":"Fussboden, Fliesen U Plattenlegerei, Tapeziererei",
    "sg:phone":"+41 77423147",
    "sg:postcode":"6340",
    "sg:province":"Zug",
    "wof:name":"Parkett Gschwend + Beck Ag",
    "wof:placetype":"venue"
},
  "geometry": {"coordinates":[8.5250816345,47.202003479],"type":"Point"}
}