{
  "type": "Feature",
  "properties": {
    "iso:country":"CH",
    "sg:address":"Sous-caran Chemin De 6 A 1222 V\u00e9senaz. Postfach",
    "sg:city":"Gen\u00e8ve",
    "sg:orig_category":"Fotografisches Gewerbe U fotografische Laboratorien",
    "sg:phone":"+41 22 345 97 00",
    "sg:postcode":"1200",
    "sg:province":"Gen\u00e8ve",
    "wof:name":"Lightmotif, Ch. Et V. Blatt",
    "wof:placetype":"venue"
},
  "geometry": {"coordinates":[6.1976928711,46.2444114685],"type":"Point"}
}