{
  "type": "Feature",
  "properties": {
    "iso:country":"CH",
    "sg:address":"Gubelstrasse 23",
    "sg:city":"Z\u00fcrich",
    "sg:orig_category":"Buchverlag Verlagsgewerbe",
    "sg:postcode":"8050",
    "sg:province":"Z\u00fcrich",
    "wof:name":"Advent-verlag Z\u00fcrich",
    "wof:placetype":"venue"
},
  "geometry": {"coordinates":[8.544214,47.408096],"type":"Point"}
}