{
  "type": "Feature",
  "properties": {
    "iso:country":"CH",
    "sg:address":"Zugerstrasse 29",
    "sg:city":"Dornach",
    "sg:orig_category":"Grosshandel mit Eisenwaren sowie Installationsbedarf f\u00fcr Gas, Wasser U Heizung Herstellung von k\u00e4lte",
    "sg:phone":"+41 61 703 16 66",
    "sg:postcode":"4143",
    "sg:province":"Solothurn",
    "wof:name":"Klimatec Gordon R.",
    "wof:placetype":"venue"
},
  "geometry": {"coordinates":[7.6227798462,47.4770317078],"type":"Point"}
}