{
  "type": "Feature",
  "properties": {
    "iso:country":"CH",
    "sg:address":"Belmontstrasse 1",
    "sg:city":"Chur",
    "sg:orig_category":"Unclassifiable Establishments",
    "sg:postcode":"7000",
    "sg:province":"Graubunden",
    "wof:name":"Stamm Peter, Primo Markt Lacuna",
    "wof:placetype":"venue"
},
  "geometry": {"coordinates":[9.52617836,46.8617095947],"type":"Point"}
}