{
  "type": "Feature",
  "properties": {
    "iso:country":"CH",
    "sg:address":"Obergrundstrasse 65",
    "sg:city":"Luzern",
    "sg:orig_category":"Personal U Stellenvermittlung Unternehmensberatung",
    "sg:phone":"+41 21 321 66 66",
    "sg:postcode":"6003",
    "sg:province":"Luzern",
    "wof:name":"Adecco Management & Consulting Sa",
    "wof:placetype":"venue"
},
  "geometry": {"coordinates":[6.6385908127,46.5199813843],"type":"Point"}
}