{
  "type": "Feature",
  "properties": {
    "iso:country":"CH",
    "sg:address":"St. Gallerstrasse 18b",
    "sg:city":"Arbon",
    "sg:orig_category":"Physiotherapie",
    "sg:phone":"+41 19108106",
    "sg:postcode":"9320",
    "sg:province":"Thurgau",
    "wof:name":"Roman Ruetz Physiotherapie",
    "wof:placetype":"venue"
},
  "geometry": {"coordinates":[8.5826597214,47.3185997009],"type":"Point"}
}