{
  "type": "Feature",
  "properties": {
    "iso:country":"CH",
    "sg:address":"Burgerstrasse 22",
    "sg:city":"Luzern",
    "sg:orig_category":"Zahnarztpraxen",
    "sg:phone":"+41 41 210 76 65",
    "sg:postcode":"6003",
    "sg:province":"Luzern",
    "wof:name":"Dr. Med. Dent. Hilde Ettlin Zahn\u00e4rztin",
    "wof:placetype":"venue"
},
  "geometry": {"coordinates":[8.3025112152,47.0494194031],"type":"Point"}
}