{
  "type": "Feature",
  "properties": {
    "iso:country":"CH",
    "sg:address":"Marktplatz",
    "sg:city":"Tiefencastel",
    "sg:orig_category":"Instandhaltung U Reparatur von Automobilen",
    "sg:phone":"+41 81 681 17 16",
    "sg:postcode":"7450",
    "sg:province":"Graubunden",
    "wof:name":"Durisch Werner",
    "wof:placetype":"venue"
},
  "geometry": {"coordinates":[9.5771245956,46.6626968384],"type":"Point"}
}