{
  "type": "Feature",
  "properties": {
    "addr:full":"1446 Baulmes Vaud 1446",
    "addr:postcode":"1446;1446",
    "iso:country":"CH",
    "sg:address":"1446",
    "sg:city":"Baulmes",
    "sg:orig_category":"Allgemeiner Hoch U Tiefbau Stukkateurgewerbe, Gipserei U Verputzerei",
    "sg:phone":"+41 71 944 13 92",
    "sg:postcode":"1446",
    "sg:province":"Vaud",
    "wof:name":"Zwick Peter Gips Gmbh",
    "wof:placetype":"venue"
},
  "geometry": {"coordinates":[9.113952,47.47665],"type":"Point"}
}