{
  "type": "Feature",
  "properties": {
    "iso:country":"CH",
    "sg:address":"Aareweg 25 3270 Aarberg. Postfach 130",
    "sg:city":"Aarberg",
    "sg:orig_category":"Elektroinstallation",
    "sg:phone":"+41 79 251 27 25",
    "sg:postcode":"3270",
    "sg:province":"Bern",
    "wof:name":"Wittwer Energietechnik Gmbh",
    "wof:placetype":"venue"
},
  "geometry": {"coordinates":[7.2764530182,47.0504951477],"type":"Point"}
}