{
  "type": "Feature",
  "properties": {
    "iso:country":"CH",
    "sg:address":"Haus Collina",
    "sg:city":"Arosa",
    "sg:classifiers":[
        {
            "category":"Travel",
            "subcategory":"Hotels & Motels",
            "type":"Entertainment"
        }
    ],
    "sg:postcode":"7050",
    "sg:province":"Graubunden",
    "sg:tags":[
        "hotels",
        "mit",
        "restaurant"
    ],
    "wof:name":"Hotel Obersee Ag Arosa",
    "wof:placetype":"venue"
},
  "geometry": {"coordinates":[9.6847801208,46.7792053223],"type":"Point"}
}