{
  "type": "Feature",
  "properties": {
    "iso:country":"CH",
    "sg:address":"Aathalstrasse 28",
    "sg:city":"Uster",
    "sg:orig_category":"Non-Classified Establishments",
    "sg:postcode":"8610",
    "sg:province":"Z\u00fcrich",
    "wof:name":"Merkam Holding Ag",
    "wof:placetype":"venue"
},
  "geometry": {"coordinates":[9.532699585,47.4808540344],"type":"Point"}
}