{
  "type": "Feature",
  "properties": {
    "iso:country":"CH",
    "sg:address":"Riedlistrasse 56",
    "sg:city":"Belp",
    "sg:orig_category":"Grafikateliers, Design",
    "sg:phone":"+41 31 819 33 83",
    "sg:postcode":"3123",
    "sg:province":"Bern",
    "wof:name":"Roberto Bortoli Bortoli Vides.ch",
    "wof:placetype":"venue"
},
  "geometry": {"coordinates":[7.5069408417,46.8788719177],"type":"Point"}
}