{
  "type": "Feature",
  "properties": {
    "iso:country":"CH",
    "sg:address":"Landstrasse 29",
    "sg:city":"Wolfhausen",
    "sg:orig_category":"Elektroinstallation",
    "sg:phone":"+41 55 286 20 80",
    "sg:postcode":"8633",
    "sg:province":"Z\u00fcrich",
    "wof:name":"Karl Egli Ag",
    "wof:placetype":"venue"
},
  "geometry": {"coordinates":[8.9250049591,47.2413787842],"type":"Point"}
}