{
  "type": "Feature",
  "properties": {
    "iso:country":"CH",
    "sg:address":"Surtuor 20",
    "sg:city":"Samedan",
    "sg:orig_category":"Architekturb\u00fcros",
    "sg:phone":"+41 81 851 10 70",
    "sg:postcode":"7503",
    "sg:province":"Graubunden",
    "wof:name":"Kurt Lazzarini Architekturb\u00fcro",
    "wof:placetype":"venue"
},
  "geometry": {"coordinates":[9.868693,46.534267],"type":"Point"}
}