{
  "type": "Feature",
  "properties": {
    "iso:country":"CH",
    "sg:address":"Rue Hugo-de-senger 7",
    "sg:city":"Gen\u00e8ve",
    "sg:orig_category":"Herstellung von Bergwerks U Baumaschinen",
    "sg:phone":"+41 22 329 67 26",
    "sg:postcode":"1205",
    "sg:province":"Gen\u00e8ve",
    "wof:name":"Renovoto Sa",
    "wof:placetype":"venue"
},
  "geometry": {"coordinates":[6.1412711143,46.1936912537],"type":"Point"}
}