{
  "type": "Feature",
  "properties": {
    "iso:country":"CH",
    "sg:address":"Bederstrasse 51 8002 Z\u00fcrich. Postfach",
    "sg:city":"Z\u00fcrich",
    "sg:orig_category":"Schreib U \u00dcbersetzungsb\u00fcros",
    "sg:postcode":"8001",
    "sg:province":"Z\u00fcrich",
    "wof:name":"Beat Steinmann, D'arts Uebersetzungen",
    "wof:placetype":"venue"
},
  "geometry": {"coordinates":[8.5283603668,47.363735199],"type":"Point"}
}