{
  "type": "Feature",
  "properties": {
    "iso:country":"CH",
    "sg:address":"Gewerbestrasse 6 6438 Ibach. Postfach",
    "sg:city":"Ibach",
    "sg:orig_category":"Instandhaltung U Reparatur von Automobilen",
    "sg:postcode":"6438",
    "sg:province":"Schwyz",
    "wof:name":"Oldtimer & Classic Cars Scheidegger & Iseli Oldtimer; Renovation, Reparatur",
    "wof:placetype":"venue"
},
  "geometry": {"coordinates":[8.6340761185,47.0126876831],"type":"Point"}
}