{
  "type": "Feature",
  "properties": {
    "iso:country":"CH",
    "sg:address":"Dorfstrasse 21 8902 Urdorf. Postfach",
    "sg:city":"Urdorf",
    "sg:orig_category":"Non-Classified Establishments",
    "sg:postcode":"8902",
    "sg:province":"Z\u00fcrich",
    "wof:name":"Gartengestaltung Akeret",
    "wof:placetype":"venue"
},
  "geometry": {"coordinates":[7.5665688515,46.9278717041],"type":"Point"}
}