{
  "type": "Feature",
  "properties": {
    "iso:country":"CH",
    "sg:address":"Zelgstrasse 13",
    "sg:city":"Z\u00fcrich",
    "sg:orig_category":"Interessenvertretungen",
    "sg:phone":"+41 71 385 39 40",
    "sg:postcode":"8003",
    "sg:province":"Z\u00fcrich",
    "wof:name":"Verband Schweizerischer Tilsiterhandelsfirmen (v.s.t.h.)",
    "wof:placetype":"venue"
},
  "geometry": {"coordinates":[9.2437915802,47.4097518921],"type":"Point"}
}