{
  "type": "Feature",
  "properties": {
    "iso:country":"CH",
    "sg:address":"Schulstrasse 76",
    "sg:city":"Landquart",
    "sg:orig_category":"Grosshandel mit Sportartikeln Webdesign",
    "sg:postcode":"7302",
    "sg:province":"Graubunden",
    "wof:name":"Martin Andeer Top Sportswear Online",
    "wof:placetype":"venue"
},
  "geometry": {"coordinates":[9.5621204376,46.9591407776],"type":"Point"}
}