{
  "type": "Feature",
  "properties": {
    "iso:country":"CH",
    "sg:address":"Lindenstrasse 6",
    "sg:city":"M\u00e4nnedorf",
    "sg:orig_category":"Vereine Damen Vereine Gesang",
    "sg:phone":"+41 19205957",
    "sg:postcode":"8708",
    "sg:province":"Z\u00fcrich",
    "wof:name":"Frauen-& T\u00f6chterchor",
    "wof:placetype":"venue"
},
  "geometry": {"coordinates":[8.7038211823,47.2562217712],"type":"Point"}
}