{
  "type": "Feature",
  "properties": {
    "iso:country":"CH",
    "sg:address":"Z\u00fcrcherstrasse 143",
    "sg:city":"Dietikon",
    "sg:orig_category":"Textilgewerbe",
    "sg:phone":"+41 17421762",
    "sg:postcode":"8953",
    "sg:province":"Z\u00fcrich",
    "wof:name":"Walter Leiser Storen-& Rolladenfabrikation",
    "wof:placetype":"venue"
},
  "geometry": {"coordinates":[8.4177503586,47.3990783691],"type":"Point"}
}