{
  "type": "Feature",
  "properties": {
    "iso:country":"CH",
    "sg:address":"Sch\u00fctzenstrasse 12a",
    "sg:city":"Heimberg",
    "sg:orig_category":"Unternehmensberatung",
    "sg:phone":"+41 33 437 18 56",
    "sg:postcode":"3627",
    "sg:province":"Bern",
    "wof:name":"Wb Ogi Hansruedi",
    "wof:placetype":"venue"
},
  "geometry": {"coordinates":[7.6022148132,46.7930374146],"type":"Point"}
}