{
  "type": "Feature",
  "properties": {
    "iso:country":"CH",
    "sg:address":"Chemin De Russilles 3",
    "sg:city":"Marly",
    "sg:classifiers":[
        {
            "category":"Insurance",
            "subcategory":"Insurance Agent",
            "type":"Services"
        }
    ],
    "sg:phone":"+41 26 436 49 74",
    "sg:postcode":"1723",
    "sg:province":"Fribourg",
    "sg:tags":[
        "versicherungsagenturen",
        "-broker"
    ],
    "wof:name":"B\u00e2loise Assurances Agence G\u00e9n\u00e9rale",
    "wof:placetype":"venue"
},
  "geometry": {"coordinates":[7.166613102,46.7782821655],"type":"Point"}
}