{
  "type": "Feature",
  "properties": {
    "iso:country":"CH",
    "sg:address":"Hauptstrasse 46",
    "sg:city":"Balgach",
    "sg:orig_category":"Drogerien",
    "sg:phone":"+41 71 722 25 51",
    "sg:postcode":"9436",
    "sg:province":"St. Gallen",
    "wof:name":"Erich Koller Drogerie",
    "wof:placetype":"venue"
},
  "geometry": {"coordinates":[9.60567379,47.4068870544],"type":"Point"}
}