{
  "type": "Feature",
  "properties": {
    "iso:country":"CH",
    "sg:address":"Scheunenstrasse 18",
    "sg:city":"Burgdorf",
    "sg:orig_category":"Detailhandel mit elektrischen Haushalts-,Radio U Fernsehger\u00e4ten sowie Musikinstrumenten",
    "sg:postcode":"3400",
    "sg:province":"Bern",
    "wof:name":"Speed Music Sonney & Cie Cd, Dvd, Jeux Vid\u00e9o Etc.; Vente",
    "wof:placetype":"venue"
},
  "geometry": {"coordinates":[6.7475280762,47.0592842102],"type":"Point"}
}