{
  "type": "Feature",
  "properties": {
    "iso:country":"CH",
    "sg:address":"Obere Egg 3",
    "sg:city":"Magden",
    "sg:orig_category":"Politische Parteien CVP",
    "sg:phone":"+41 71 222 33 84",
    "sg:postcode":"4312",
    "sg:province":"Aargau",
    "wof:name":"Cvp Ortspartei Marbach",
    "wof:placetype":"venue"
},
  "geometry": {"coordinates":[9.5790300369,47.3841705322],"type":"Point"}
}