{
  "type": "Feature",
  "properties": {
    "iso:country":"CH",
    "sg:address":"Grubenstrasse 4",
    "sg:city":"Urdorf",
    "sg:orig_category":"Bauingenieurb\u00fcros Hochbau Bauingenieurb\u00fcros Tiefbau",
    "sg:phone":"+41 17364300",
    "sg:postcode":"8902",
    "sg:province":"Z\u00fcrich",
    "wof:name":"Funk & Gutknecht Ag Dipl. Bauingenieure Eth Sia",
    "wof:placetype":"venue"
},
  "geometry": {"coordinates":[8.42012,47.392197],"type":"Point"}
}