{
  "type": "Feature",
  "properties": {
    "iso:country":"CH",
    "sg:address":"Utengasse 31",
    "sg:city":"Basel",
    "sg:orig_category":"Grosshandel mit Geschenkartikeln U Souvenirs",
    "sg:phone":"+41 71 313 96 77",
    "sg:postcode":"4058",
    "sg:province":"Basel-Stadt",
    "wof:name":"Product Design Gmbh Werbeartikel",
    "wof:placetype":"venue"
},
  "geometry": {"coordinates":[9.3128166199,47.4085845947],"type":"Point"}
}