{
  "type": "Feature",
  "properties": {
    "iso:country":"CH",
    "sg:address":"Hauptstrasse 45",
    "sg:city":"Ipsach",
    "sg:orig_category":"Leichtmetallgiesserei",
    "sg:postcode":"2563",
    "sg:province":"Bern",
    "wof:name":"Altmann Casting Ag",
    "wof:placetype":"venue"
},
  "geometry": {"coordinates":[7.2306780815,47.1129188538],"type":"Point"}
}