{
  "type": "Feature",
  "properties": {
    "addr:full":"Meilistrasse 12 Winterthur Z\u00fcrich 8400",
    "addr:housenumber":"12",
    "addr:postcode":"8400",
    "addr:street":"Meilistrasse",
    "iso:country":"CH",
    "sg:address":"Meilistrasse 12",
    "sg:city":"Winterthur",
    "sg:orig_category":"Architektur U Ingenieurb\u00fcros",
    "sg:phone":"+41 17371025",
    "sg:postcode":"8400",
    "sg:province":"Z\u00fcrich",
    "wof:name":"Erb Heinrich",
    "wof:placetype":"venue"
},
  "geometry": {"coordinates":[8.45939,47.35294],"type":"Point"}
}