{
  "type": "Feature",
  "properties": {
    "addr:full":"Blumenrain 3 Basel Basel-Stadt 4051",
    "addr:housenumber":"3",
    "addr:postcode":"4051",
    "addr:street":"Blumenrain",
    "iso:country":"CH",
    "sg:address":"Blumenrain 3",
    "sg:city":"Basel",
    "sg:orig_category":"Advokaturb\u00fcros Notariate",
    "sg:phone":"+41 61 269 98 00",
    "sg:postcode":"4051",
    "sg:province":"Basel-Stadt",
    "wof:name":"Bertschi Bichsel & Wyss Advokatur- & Notariatsb\u00fcro",
    "wof:placetype":"venue"
},
  "geometry": {"coordinates":[7.587271,47.560345],"type":"Point"}
}