{
  "type": "Feature",
  "properties": {
    "iso:country":"CH",
    "sg:address":"Borghetto Via 20",
    "sg:city":"Giubiasco",
    "sg:orig_category":"Handel mit Motorr\u00e4dern, Teilen U Zubeh\u00f6r Instandhaltung U Reparatur von Motorr\u00e4dern",
    "sg:phone":"+41 91 858 26 41",
    "sg:postcode":"6512",
    "sg:province":"Ticino",
    "wof:name":"Valbryan Sa",
    "wof:placetype":"venue"
},
  "geometry": {"coordinates":[9.0127010345,46.1739082336],"type":"Point"}
}