{
  "type": "Feature",
  "properties": {
    "iso:country":"CH",
    "sg:address":"Eisenbahnweg 25 Goldau 6415 Arth. Postfach",
    "sg:city":"Goldau",
    "sg:orig_category":"Herstellung von Metallkonstruktionen",
    "sg:postcode":"6410",
    "sg:province":"Schwyz",
    "wof:name":"Kaufmann Ag, Goldau",
    "wof:placetype":"venue"
},
  "geometry": {"coordinates":[8.5223703384,47.0628089905],"type":"Point"}
}