{
  "type": "Feature",
  "properties": {
    "iso:country":"CH",
    "sg:address":"Rohrstrasse 8",
    "sg:city":"Schlieren",
    "sg:orig_category":"Grosshandel mit Holz U Baustoffen Handelsvermittlung von Waren ohne ausgepr\u00e4gten Schwerpunkt",
    "sg:phone":"+41 17306025",
    "sg:postcode":"8952",
    "sg:province":"Z\u00fcrich",
    "wof:name":"Ok Baustoffe Kuhn Otto",
    "wof:placetype":"venue"
},
  "geometry": {"coordinates":[8.446890831,47.4040107727],"type":"Point"}
}