{
  "type": "Feature",
  "properties": {
    "iso:country":"CH",
    "sg:address":"Zugerstrasse 77",
    "sg:city":"Baar",
    "sg:orig_category":"Aktivit\u00e4ten der Generalunternehmen im Baugewerbe Ingenieurb\u00fcros divers",
    "sg:phone":"+41 41 766 63 63",
    "sg:postcode":"6340",
    "sg:province":"Zug",
    "wof:name":"Fiber.dat Ag",
    "wof:placetype":"venue"
},
  "geometry": {"coordinates":[8.519997,47.183048],"type":"Point"}
}