{
  "type": "Feature",
  "properties": {
    "addr:full":"Studenm\u00e4ttelistrasse 32f Birmensdorf Z\u00fcrich 8903",
    "addr:housenumber":"32f",
    "addr:postcode":"8903",
    "addr:street":"Studenmaettelistrasse",
    "iso:country":"CH",
    "sg:address":"Studenm\u00e4ttelistrasse 32f",
    "sg:city":"Birmensdorf",
    "sg:classifiers":[
        {
            "category":"Utilities",
            "subcategory":"Electric",
            "type":"Services"
        }
    ],
    "sg:phone":"+41 17374444",
    "sg:postcode":"8903",
    "sg:province":"Z\u00fcrich",
    "sg:tags":[
        "current",
        "low-voltage",
        "capacitor"
    ],
    "wof:name":"Amitron Ag",
    "wof:placetype":"venue"
},
  "geometry": {"coordinates":[8.440505,47.353592],"type":"Point"}
}