{
  "type": "Feature",
  "properties": {
    "iso:country":"CH",
    "sg:address":"Berg Waltenstein",
    "sg:city":"Schlatt",
    "sg:orig_category":"Herstellung von Duft U K\u00f6rperpflegemitteln",
    "sg:phone":"+41 52 730 03 93",
    "sg:postcode":"8418",
    "sg:province":"Z\u00fcrich",
    "wof:name":"Vision Trading Gmbh",
    "wof:placetype":"venue"
},
  "geometry": {"coordinates":[8.8282833099,47.4700393677],"type":"Point"}
}