{
  "type": "Feature",
  "properties": {
    "iso:country":"CH",
    "sg:address":"Rossh\u00e4usernstrasse 20",
    "sg:city":"Bern",
    "sg:orig_category":"Herstellung von k\u00e4lte U lufttechnischen Erzeugnissen f\u00fcr gewerbliche Zwecke",
    "sg:phone":"+41 31 926 12 01",
    "sg:postcode":"3020",
    "sg:province":"Bern",
    "wof:name":"Frigonorm Ag",
    "wof:placetype":"venue"
},
  "geometry": {"coordinates":[7.3324680328,46.9426651001],"type":"Point"}
}