{
  "type": "Feature",
  "properties": {
    "iso:country":"CH",
    "sg:address":"Vernettes Les",
    "sg:city":"Montpreveyres",
    "sg:orig_category":"Werbung",
    "sg:phone":"+41 21 925 86 00",
    "sg:postcode":"1081",
    "sg:province":"Vaud",
    "wof:name":"Pimento Communications S\u00e0rl",
    "wof:placetype":"venue"
},
  "geometry": {"coordinates":[5.1808700562,45.8973388672],"type":"Point"}
}