{
  "type": "Feature",
  "properties": {
    "iso:country":"CH",
    "sg:address":"Route De Torgon 1895 Vionnaz. Postfach",
    "sg:city":"Vionnaz",
    "sg:orig_category":"Autoreiseunternehmen Reiseb\u00fcros",
    "sg:phone":"+41 24 481 29 53",
    "sg:postcode":"1895",
    "sg:province":"Valais",
    "wof:name":"Torgon Excursions",
    "wof:placetype":"venue"
},
  "geometry": {"coordinates":[6.882793,46.31575],"type":"Point"}
}