{
  "type": "Feature",
  "properties": {
    "iso:country":"CH",
    "sg:address":"Bogenstrasse 5 9326 Horn. Postfach 29",
    "sg:city":"Horn",
    "sg:orig_category":"Datenverarbeitungsdienste Forschung U Entwicklung im Bereich der Naturwissenschaften",
    "sg:phone":"+41 71 841 19 21",
    "sg:postcode":"9326",
    "sg:province":"Thurgau",
    "wof:name":"Adnovum Ag",
    "wof:placetype":"venue"
},
  "geometry": {"coordinates":[9.465064,47.493908],"type":"Point"}
}