{
  "type": "Feature",
  "properties": {
    "addr:full":"Industriestrasse 2 Zwingen Basel-Landschaft 4222",
    "addr:housenumber":"2",
    "addr:postcode":"4222",
    "addr:street":"Industriestrasse",
    "iso:country":"CH",
    "sg:address":"Industriestrasse 2",
    "sg:city":"Zwingen",
    "sg:orig_category":"Bauingenieurb\u00fcros allgemein",
    "sg:phone":"+41 61 765 98 80",
    "sg:postcode":"4222",
    "sg:province":"Basel-Landschaft",
    "wof:name":"Peter Jermann Ingenieurb\u00fcro",
    "wof:placetype":"venue"
},
  "geometry": {"coordinates":[7.512832,47.429127],"type":"Point"}
}