{
  "type": "Feature",
  "properties": {
    "iso:country":"CH",
    "sg:address":"Obere Wengi",
    "sg:city":"Matzendorf",
    "sg:orig_category":"Haltung von Rindern",
    "sg:postcode":"4713",
    "sg:province":"Solothurn",
    "wof:name":"Fleckviehzuchtgenossenschaft Brunnersberg.",
    "wof:placetype":"venue"
},
  "geometry": {"coordinates":[7.6245350838,47.3240242004],"type":"Point"}
}