{
  "type": "Feature",
  "properties": {
    "iso:country":"CH",
    "sg:address":"Wehntalerstrasse 46",
    "sg:city":"Z\u00fcrich",
    "sg:orig_category":"Herstellung von Kakao, Schokoladeerzeugnissen U Zuckerwaren",
    "sg:postcode":"8057",
    "sg:province":"Z\u00fcrich",
    "wof:name":"Z\u00fcrcher Philippe",
    "wof:placetype":"venue"
},
  "geometry": {"coordinates":[6.8588747978,46.965801239],"type":"Point"}
}