{
  "type": "Feature",
  "properties": {
    "iso:country":"CH",
    "sg:address":"Bahnhofstrasse 73",
    "sg:city":"Wettingen",
    "sg:orig_category":"Religi\u00f6se Vereinigungen divers",
    "sg:phone":"+41 56 426 38 66",
    "sg:postcode":"5430",
    "sg:province":"Aargau",
    "wof:name":"Freie Evang.gemeinde Baden-wettingen",
    "wof:placetype":"venue"
},
  "geometry": {"coordinates":[8.3266391754,47.4625816345],"type":"Point"}
}