{
  "type": "Feature",
  "properties": {
    "iso:country":"CH",
    "sg:address":"Route Du Nant-d'avril 146 1217 Meyrin. Postfach",
    "sg:city":"Meyrin",
    "sg:orig_category":"Mechanik",
    "sg:phone":"+41 27 306 49 87",
    "sg:postcode":"1217",
    "sg:province":"Gen\u00e8ve",
    "wof:name":"Buchard Christian",
    "wof:placetype":"venue"
},
  "geometry": {"coordinates":[7.1819300652,46.1889343262],"type":"Point"}
}