{
  "type": "Feature",
  "properties": {
    "iso:country":"CH",
    "sg:address":"Stockerstrasse 10 8002 Z\u00fcrich. Postfach 5139",
    "sg:city":"Z\u00fcrich",
    "sg:orig_category":"Futtermittel, Heu and Stroh Grosshandel Getreide Grosshandel",
    "sg:phone":"+41 12028650",
    "sg:postcode":"8022",
    "sg:province":"Z\u00fcrich",
    "wof:name":"Bunge Ag Getreide & Futtermittel Engros",
    "wof:placetype":"venue"
},
  "geometry": {"coordinates":[8.5364398956,47.3653755188],"type":"Point"}
}