{
  "type": "Feature",
  "properties": {
    "iso:country":"CH",
    "sg:address":"Hochbordstrasse 9",
    "sg:city":"D\u00fcbendorf",
    "sg:orig_category":"Grosshandel mit sonstigen Gebrauchs U Verbrauchsg\u00fctern",
    "sg:postcode":"8600",
    "sg:province":"Z\u00fcrich",
    "wof:name":"Cewe Color Fotoservice Ag",
    "wof:placetype":"venue"
},
  "geometry": {"coordinates":[8.6018724442,47.4010505676],"type":"Point"}
}