{
  "type": "Feature",
  "properties": {
    "iso:country":"CH",
    "sg:address":"Finsterr\u00fctistrasse 3",
    "sg:city":"Adliswil",
    "sg:orig_category":"Non-Classified Establishments",
    "sg:postcode":"8134",
    "sg:province":"Z\u00fcrich",
    "wof:name":"Wymann Webdesign",
    "wof:placetype":"venue"
},
  "geometry": {"coordinates":[8.5235233307,47.3014030457],"type":"Point"}
}