{
  "type": "Feature",
  "properties": {
    "iso:country":"CH",
    "sg:address":"Altgasse 50",
    "sg:city":"Baar",
    "sg:orig_category":"Datenverarbeitungsdienste Sonstige mit der Informatik verbundene T\u00e4tigkeiten",
    "sg:phone":"+41 79 643 48 29",
    "sg:postcode":"6340",
    "sg:province":"Zug",
    "wof:name":"Wyss-edv",
    "wof:placetype":"venue"
},
  "geometry": {"coordinates":[8.516125,47.192108],"type":"Point"}
}