{
  "type": "Feature",
  "properties": {
    "iso:country":"CH",
    "sg:address":"Dorf 190",
    "sg:city":"Waldstatt",
    "sg:orig_category":"Detailhandel mit medizinischen U orthop\u00e4dischen Artikeln Drogerien",
    "sg:phone":"+41 71 351 22 13",
    "sg:postcode":"9104",
    "sg:province":"Appenzell Ausserrhoden",
    "wof:name":"Brigitte Bischofberger Drogerie",
    "wof:placetype":"venue"
},
  "geometry": {"coordinates":[9.2836885452,47.3568878174],"type":"Point"}
}