{
  "type": "Feature",
  "properties": {
    "iso:country":"CH",
    "sg:address":"Industria Via",
    "sg:city":"Biasca",
    "sg:orig_category":"Herstellung von sonstigen organischen Grundstoffen U Chemikalien",
    "sg:phone":"+41 91 985 21 21",
    "sg:postcode":"6710",
    "sg:province":"Ticino",
    "wof:name":"Helsinn Advanced Synthesis Sa",
    "wof:placetype":"venue"
},
  "geometry": {"coordinates":[8.9632768631,46.3505363464],"type":"Point"}
}