{
  "type": "Feature",
  "properties": {
    "iso:country":"CH",
    "sg:address":"H\u00f6nggerstrasse 27 8000 Z\u00fcrich. Postfach",
    "sg:city":"Z\u00fcrich",
    "sg:orig_category":"Satzherstellung U Reproduktion",
    "sg:postcode":"8037",
    "sg:province":"Z\u00fcrich",
    "wof:name":"Axcel Informatik Arpagaus Th.",
    "wof:placetype":"venue"
},
  "geometry": {"coordinates":[8.5261583328,47.3910675049],"type":"Point"}
}