{
  "type": "Feature",
  "properties": {
    "iso:country":"CH",
    "sg:address":"Via Al Forte 1",
    "sg:city":"Lugano",
    "sg:classifiers":[
        {
            "category":"Banks & Credit Unions",
            "subcategory":"Bank",
            "type":"Services"
        }
    ],
    "sg:postcode":"6901",
    "sg:province":"Ticino",
    "wof:name":"First Austrian Finanz Ag",
    "wof:placetype":"venue"
},
  "geometry": {"coordinates":[8.53955,47.37706],"type":"Point"}
}