{
  "type": "Feature",
  "properties": {
    "iso:country":"CH",
    "sg:address":"Steinm\u00fchleplatz 1",
    "sg:city":"Z\u00fcrich",
    "sg:orig_category":"Detailhandel mit Schuhen U Lederwaren",
    "sg:phone":"+41 14507474",
    "sg:postcode":"8001",
    "sg:province":"Z\u00fcrich",
    "wof:name":"K\u00f6nix Schuhe Ag",
    "wof:placetype":"venue"
},
  "geometry": {"coordinates":[8.5365314484,47.3736000061],"type":"Point"}
}