{
  "type": "Feature",
  "properties": {
    "iso:country":"CH",
    "sg:address":"Dorfmattweg 47",
    "sg:city":"M\u00fcnsingen",
    "sg:orig_category":"Blumen U Zierpflanzenbau Detailhandel mit Blumen U Pflanzen",
    "sg:phone":"+41 31 721 13 26",
    "sg:postcode":"3110",
    "sg:province":"Bern",
    "wof:name":"Walter Bichsel",
    "wof:placetype":"venue"
},
  "geometry": {"coordinates":[7.553511,46.871513],"type":"Point"}
}