{
  "type": "Feature",
  "properties": {
    "iso:country":"CH",
    "sg:address":"H\u00f6henweg 3",
    "sg:city":"Konolfingen",
    "sg:orig_category":"Detailhandel mit Metallwaren, Anstrichmitteln, Glaswaren, Bau U Heimwerkerbedarf",
    "sg:postcode":"3510",
    "sg:province":"Bern",
    "wof:name":"Robert Luginb\u00fchl",
    "wof:placetype":"venue"
},
  "geometry": {"coordinates":[7.6248459816,46.8849372864],"type":"Point"}
}