{
  "type": "Feature",
  "properties": {
    "iso:country":"CH",
    "sg:address":"Reichsgasse 14",
    "sg:city":"Schwyz",
    "sg:orig_category":"RESTAURANTS: TEA-ROOMS",
    "sg:phone":"+41 41 811 13 31",
    "sg:postcode":"6430",
    "sg:province":"Schwyz",
    "wof:name":"Restaurant H\u00f6fli",
    "wof:placetype":"venue"
},
  "geometry": {"coordinates":[8.6562995911,47.0210494995],"type":"Point"}
}