{
  "type": "Feature",
  "properties": {
    "iso:country":"CH",
    "sg:address":"Via Alla Riva 99 6648 Minusio. Postfach Caselle Postale 1169",
    "sg:city":"Minusio",
    "sg:classifiers":[
        {
            "category":"Travel",
            "subcategory":"Hotels & Motels",
            "type":"Entertainment"
        }
    ],
    "sg:phone":"+41 91 743 15 05",
    "sg:postcode":"6648",
    "sg:province":"Ticino",
    "sg:tags":[
        "hotels",
        "mit",
        "restaurant"
    ],
    "wof:name":"Albergo Casa Al Lago",
    "wof:placetype":"venue"
},
  "geometry": {"coordinates":[8.8289899826,46.1775627136],"type":"Point"}
}