{
  "type": "Feature",
  "properties": {
    "iso:country":"CH",
    "sg:address":"Thurgauerstrasse 72 8050 Z\u00fcrich",
    "sg:city":"Zust",
    "sg:orig_category":"Erbringung von Dienstleistungen f\u00fcr Unternehmen",
    "sg:postcode":"50",
    "wof:name":"Rvg Verpackungs-grafik, K. R\u00f6ssler",
    "wof:placetype":"venue"
},
  "geometry": {"coordinates":[8.4404354095,47.2727775574],"type":"Point"}
}