{
  "type": "Feature",
  "properties": {
    "iso:country":"CH",
    "sg:address":"Bahnhofstrasse 30",
    "sg:city":"D\u00fcbendorf",
    "sg:orig_category":"Herstellung von Pumpen U Kompressoren",
    "sg:phone":"+41 18217076",
    "sg:postcode":"8600",
    "sg:province":"Z\u00fcrich",
    "wof:name":"Hunger Hydraulik (schweiz) Ag",
    "wof:placetype":"venue"
},
  "geometry": {"coordinates":[8.6197214127,47.3979797363],"type":"Point"}
}