{
  "type": "Feature",
  "properties": {
    "iso:country":"CH",
    "sg:address":"Place St-jacques 3",
    "sg:city":"Etoy",
    "sg:orig_category":"Nationale Postdienste",
    "sg:phone":"+41 32 935 11 35",
    "sg:postcode":"1163",
    "sg:province":"Vaud",
    "wof:name":"La Poste Suisse",
    "wof:placetype":"venue"
},
  "geometry": {"coordinates":[6.6068201065,46.9808044434],"type":"Point"}
}