{
  "type": "Feature",
  "properties": {
    "iso:country":"CH",
    "sg:address":"7503 Samedan. Postfach 215",
    "sg:city":"Samedan",
    "sg:orig_category":"Vereine Frauen Vereine Gemeinn\u00fctzige",
    "sg:phone":"+41 56 282 20 50",
    "sg:postcode":"7503",
    "sg:province":"Graubunden",
    "wof:name":"Gemeinn\u00fctziger Frauenverein",
    "wof:placetype":"venue"
},
  "geometry": {"coordinates":[9.8728370667,46.535358429],"type":"Point"}
}