{
  "type": "Feature",
  "properties": {
    "iso:country":"CH",
    "sg:address":"Steinackerweg 8",
    "sg:city":"Turbenthal",
    "sg:orig_category":"Grosshandel mit Eisenwaren sowie Installationsbedarf f\u00fcr Gas, Wasser U Heizung",
    "sg:phone":"+41 52 385 31 33",
    "sg:postcode":"8488",
    "sg:province":"Z\u00fcrich",
    "wof:name":"Wicki Edith Import-export",
    "wof:placetype":"venue"
},
  "geometry": {"coordinates":[8.840502739,47.4454612732],"type":"Point"}
}