{
  "type": "Feature",
  "properties": {
    "iso:country":"CH",
    "sg:address":"Chemin Du Ch\u00e2teau-bloch 10 1214 Vernier. Postfach",
    "sg:city":"Vernier",
    "sg:classifiers":[
        {
            "category":"Professional",
            "subcategory":"Employment Agencies",
            "type":"Services"
        }
    ],
    "sg:postcode":"1214",
    "sg:province":"Gen\u00e8ve",
    "sg:tags":[
        "personal",
        "u",
        "stellenvermittlung"
    ],
    "wof:name":"Monster Suisse Sa Placement De Personnel Et Prestations De Services Dans Le Dom. Du Placement De Personnel",
    "wof:placetype":"venue"
},
  "geometry": {"coordinates":[6.1002898216,46.2071914673],"type":"Point"}
}