{
  "type": "Feature",
  "properties": {
    "iso:country":"CH",
    "sg:address":"Grundstrasse 2",
    "sg:city":"Ganterschwil",
    "sg:orig_category":"Verwertung von Milch",
    "sg:postcode":"9608",
    "sg:province":"St. Gallen",
    "wof:name":"Dorfk\u00e4serei Stadelmann",
    "wof:placetype":"venue"
},
  "geometry": {"coordinates":[9.0882205963,47.3817253113],"type":"Point"}
}