{
  "type": "Feature",
  "properties": {
    "iso:country":"CH",
    "sg:address":"Kanalgasse 1",
    "sg:city":"Biel/bienne",
    "sg:orig_category":"Detailhandel mit Uhren U Schmuck",
    "sg:phone":"+41 32 323 10 70",
    "sg:postcode":"2502",
    "sg:province":"Bern",
    "wof:name":"Anna Kohler Schmuckatelier",
    "wof:placetype":"venue"
},
  "geometry": {"coordinates":[7.2456970215,47.1403884888],"type":"Point"}
}