{
  "type": "Feature",
  "properties": {
    "iso:country":"CH",
    "sg:address":"Friedackerstrasse 19",
    "sg:city":"R\u00fcmlang",
    "sg:orig_category":"Herstellung von keramischen Wand U Bodenfliesen U platten Verlegen von Fliesen U Platten",
    "sg:phone":"+41 18171097",
    "sg:postcode":"8153",
    "sg:province":"Z\u00fcrich",
    "wof:name":"Vogel Charles Ag",
    "wof:placetype":"venue"
},
  "geometry": {"coordinates":[8.5326213837,47.4481964111],"type":"Point"}
}