{
  "type": "Feature",
  "properties": {
    "iso:country":"CH",
    "sg:address":"H\u00f6henweg 18 6417 Sattel. Postfach 24",
    "sg:city":"Sattel",
    "sg:orig_category":"Werbeagenturen Werbegrafikateliers",
    "sg:phone":"+41 41 836 80 11",
    "sg:postcode":"6417",
    "sg:province":"Schwyz",
    "wof:name":"Bgk Werbeagentur",
    "wof:placetype":"venue"
},
  "geometry": {"coordinates":[8.6442327499,47.0692443848],"type":"Point"}
}