{
  "type": "Feature",
  "properties": {
    "iso:country":"CH",
    "sg:address":"Obstgartenstrasse 14 8303 Bassersdorf. Postfach",
    "sg:city":"Bassersdorf",
    "sg:orig_category":"Fernmeldedienste",
    "sg:postcode":"8303",
    "sg:province":"Z\u00fcrich",
    "wof:name":"Kreuzinger Mobiles",
    "wof:placetype":"venue"
},
  "geometry": {"coordinates":[8.6202630997,47.442199707],"type":"Point"}
}