{
  "type": "Feature",
  "properties": {
    "iso:country":"CH",
    "sg:address":"Obermahren 102",
    "sg:city":"Lostorf",
    "sg:orig_category":"Haltung von Schafen, Ziegen, Pferden U Eseln Tierheime",
    "sg:phone":"+41 62 298 33 79",
    "sg:postcode":"4654",
    "sg:province":"Solothurn",
    "wof:name":"Pferdepension Brigitta Von Rohr",
    "wof:placetype":"venue"
},
  "geometry": {"coordinates":[7.9161510468,47.379524231],"type":"Point"}
}