{
  "type": "Feature",
  "properties": {
    "iso:country":"CH",
    "sg:address":"Route De La Croix-blanche 33",
    "sg:city":"Epalinges",
    "sg:orig_category":"Elektroinstallation Herstellung von Elektromotoren, Generatoren U Transformatoren",
    "sg:phone":"+41 21 784 50 23",
    "sg:postcode":"1066",
    "sg:province":"Vaud",
    "wof:name":"Electro-contact S\u00e0rl Electricit\u00e9 T\u00e9l\u00e9com",
    "wof:placetype":"venue"
},
  "geometry": {"coordinates":[6.6733498573,46.5483512878],"type":"Point"}
}