{
  "type": "Feature",
  "properties": {
    "iso:country":"CH",
    "sg:address":"Langackerweg 6",
    "sg:city":"Niederhasli",
    "sg:orig_category":"Detailhandel mit Metallwaren, Anstrichmitteln, Glaswaren, Bau U Heimwerkerbedarf Detailhandel mit Te",
    "sg:phone":"+41 18502926",
    "sg:postcode":"8155",
    "sg:province":"Z\u00fcrich",
    "wof:name":"Bastelstube Yvonne Maag",
    "wof:placetype":"venue"
},
  "geometry": {"coordinates":[8.4860162735,47.4829711914],"type":"Point"}
}