{
  "type": "Feature",
  "properties": {
    "iso:country":"CH",
    "sg:address":"Grundstrasse 12",
    "sg:city":"Rotkreuz",
    "sg:orig_category":"Elektrizit\u00e4tsversorgung",
    "sg:phone":"+41 41 790 38 08",
    "sg:postcode":"6343",
    "sg:province":"Zug",
    "wof:name":"Evs-environmental Management Systems Gmbh",
    "wof:placetype":"venue"
},
  "geometry": {"coordinates":[8.4302759171,47.145690918],"type":"Point"}
}