{
  "type": "Feature",
  "properties": {
    "iso:country":"CH",
    "sg:address":"Steinen",
    "sg:city":"Beckenried",
    "sg:orig_category":"S\u00e4ge, Hobel U Holzimpr\u00e4gnierwerke",
    "sg:postcode":"6375",
    "sg:province":"Nidwalden",
    "wof:name":"Murer Gebr. Ag",
    "wof:placetype":"venue"
},
  "geometry": {"coordinates":[8.473195076,46.9684066772],"type":"Point"}
}