{
  "type": "Feature",
  "properties": {
    "iso:country":"CH",
    "sg:address":"Mu\u00ebses Route Des 1 1753 Matran. Postfach",
    "sg:city":"Matran",
    "sg:orig_category":"Mechanik",
    "sg:phone":"+41 22 342 56 46",
    "sg:postcode":"1753",
    "sg:province":"Fribourg",
    "wof:name":"Cl\u00e9 Carouge Beck Marcel",
    "wof:placetype":"venue"
},
  "geometry": {"coordinates":[6.1394500732,46.1843643188],"type":"Point"}
}