{
  "type": "Feature",
  "properties": {
    "addr:full":"Murtenstrasse 141 Bern Bern 3008",
    "addr:housenumber":"141",
    "addr:postcode":"3008",
    "addr:street":"Murtenstrasse",
    "iso:country":"CH",
    "sg:address":"Murtenstrasse 141",
    "sg:city":"Bern",
    "sg:orig_category":"Bauspenglerei Sanit\u00e4r, Heizungs U L\u00fcftungsinstallation",
    "sg:phone":"+41 31 311 71 26",
    "sg:postcode":"3008",
    "sg:province":"Bern",
    "wof:name":"B. + U. Buchschacher Ag",
    "wof:placetype":"venue"
},
  "geometry": {"coordinates":[7.409646,46.949127],"type":"Point"}
}