{
  "type": "Feature",
  "properties": {
    "iso:country":"CH",
    "sg:address":"Sporrengasse 1",
    "sg:city":"Beggingen",
    "sg:orig_category":"Interessenvertretungen",
    "sg:postcode":"8228",
    "sg:province":"Schaffhausen",
    "wof:name":"Stiftung Flick-schudel Anna",
    "wof:placetype":"venue"
},
  "geometry": {"coordinates":[8.5369205475,47.7667694092],"type":"Point"}
}