{
  "type": "Feature",
  "properties": {
    "iso:country":"CH",
    "sg:address":"Route De L'eglise 1b 1752 Villars-sur-gl\u00e2ne Case Postale 94",
    "sg:city":"Villars-sur-gl\u00e2ne",
    "sg:orig_category":"Dienstleistungen von Beteiligungsgesellschaften Finanzierungsinstitutionen",
    "sg:phone":"+41 26 424 60 70",
    "sg:postcode":"1752",
    "sg:province":"Fribourg",
    "wof:name":"Baudet Marc - Arcadis Bureau De Gestion Et Courtage",
    "wof:placetype":"venue"
},
  "geometry": {"coordinates":[7.1170048714,46.7903213501],"type":"Point"}
}