{
  "type": "Feature",
  "properties": {
    "iso:country":"CH",
    "sg:address":"Schlossrebenrain 1",
    "sg:city":"Binningen",
    "sg:orig_category":"Verwaltung der Rechtspflege, Gerichte",
    "sg:phone":"+41 61 421 49 49",
    "sg:postcode":"4102",
    "sg:province":"Basel-Landschaft",
    "wof:name":"Notariat & Grundbuchamt",
    "wof:placetype":"venue"
},
  "geometry": {"coordinates":[7.5761179924,47.5390357971],"type":"Point"}
}