{
  "type": "Feature",
  "properties": {
    "iso:country":"CH",
    "sg:address":"Rue Du Pont 12",
    "sg:city":"Lausanne",
    "sg:orig_category":"Architekturb\u00fcros",
    "sg:phone":"+41 21 320 83 18",
    "sg:postcode":"1003",
    "sg:province":"Vaud",
    "wof:name":"Fran\u00e7ois Jolliet & Pier Lovat Bureau D'architecture",
    "wof:placetype":"venue"
},
  "geometry": {"coordinates":[6.633128,46.52121],"type":"Point"}
}