{
  "type": "Feature",
  "properties": {
    "iso:country":"CH",
    "sg:address":"Viale Stazione 9",
    "sg:city":"Bellinzona",
    "sg:classifiers":[
        {
            "category":"Banks & Credit Unions",
            "subcategory":"Bank",
            "type":"Services"
        }
    ],
    "sg:phone":"+41 91 821 65 11",
    "sg:postcode":"6500",
    "sg:province":"Ticino",
    "wof:name":"Banca Della Svizzera Italiana, Bsi",
    "wof:placetype":"venue"
},
  "geometry": {"coordinates":[9.024345,46.192612],"type":"Point"}
}