{
  "type": "Feature",
  "properties": {
    "iso:country":"CH",
    "sg:address":"Flurstrasse 32 8000 Z\u00fcrich. Postfach",
    "sg:city":"Z\u00fcrich",
    "sg:orig_category":"Softwareentwicklung U beratung",
    "sg:phone":"+41 14052100",
    "sg:postcode":"8000",
    "sg:province":"Z\u00fcrich",
    "wof:name":"Kdlabs Ag Produkte Und Dienstleistungen Im Ber. Informatik, Bes. Knowledge Discovery Usw.; Herstellung, Verkauf, Handel",
    "wof:placetype":"venue"
},
  "geometry": {"coordinates":[8.4944095612,47.384021759],"type":"Point"}
}