{
  "type": "Feature",
  "properties": {
    "addr:full":"Industriegel\u00e4nde Bodio Ticino 6743",
    "addr:postcode":"6743",
    "iso:country":"CH",
    "sg:address":"Industriegel\u00e4nde",
    "sg:city":"Bodio",
    "sg:orig_category":"Graphite Powder",
    "sg:phone":"+41 91 873 20 10",
    "sg:postcode":"6743",
    "sg:province":"Ticino",
    "wof:name":"Timcal Sa Graphite Und Technologien",
    "wof:placetype":"venue"
},
  "geometry": {"coordinates":[8.900875,46.381405],"type":"Point"}
}