{
  "type": "Feature",
  "properties": {
    "addr:full":"Hauptstr. 164 Hottwil Aargau 5277",
    "addr:housenumber":"164",
    "addr:postcode":"5277",
    "addr:street":"Hauptstr.",
    "iso:country":"CH",
    "sg:address":"Hauptstr. 164",
    "sg:city":"Hottwil",
    "sg:classifiers":[
        {
            "category":"Banks & Credit Unions",
            "subcategory":"Bank",
            "type":"Services"
        }
    ],
    "sg:phone":"+41 62 875 18 18",
    "sg:postcode":"5277",
    "sg:province":"Aargau",
    "wof:name":"Raiffeisenbank",
    "wof:placetype":"venue"
},
  "geometry": {"coordinates":[8.160208,47.546711],"type":"Point"}
}