{
  "type": "Feature",
  "properties": {
    "iso:country":"CH",
    "sg:address":"Ubrio Via 32",
    "sg:city":"Losone",
    "sg:orig_category":"Herstellung von sonstigen Maschinen f\u00fcr bestimmte Verwendung",
    "sg:postcode":"6616",
    "sg:province":"Ticino",
    "wof:name":"Imfeld Trasporti Sagl",
    "wof:placetype":"venue"
},
  "geometry": {"coordinates":[8.7610340118,46.1727828979],"type":"Point"}
}