{
  "type": "Feature",
  "properties": {
    "iso:country":"CH",
    "sg:address":"Sentupada",
    "sg:city":"Sumvitg",
    "sg:classifiers":[
        {
            "category":"Banks & Credit Unions",
            "subcategory":"Bank",
            "type":"Services"
        }
    ],
    "sg:phone":"+41 81 943 10 78",
    "sg:postcode":"7175",
    "sg:province":"Graubunden",
    "wof:name":"Raiffeisenbank",
    "wof:placetype":"venue"
},
  "geometry": {"coordinates":[8.935793,46.72736],"type":"Point"}
}