{
  "type": "Feature",
  "properties": {
    "iso:country":"CH",
    "sg:address":"Zugerstrasse 26",
    "sg:city":"Cham",
    "sg:classifiers":[
        {
            "category":"Restaurant",
            "type":"Food & Drink"
        }
    ],
    "sg:phone":"+41 41 780 38 31",
    "sg:postcode":"6330",
    "sg:province":"Zug",
    "wof:name":"Restaurant Gr\u00fctli",
    "wof:placetype":"venue"
},
  "geometry": {"coordinates":[8.4627962112,47.1814651489],"type":"Point"}
}