{
  "type": "Feature",
  "properties": {
    "iso:country":"CH",
    "sg:address":"3822 Lauterbrunnen. Postfach",
    "sg:city":"Wengen",
    "sg:orig_category":"Interessenvertretungen",
    "sg:postcode":"3823",
    "sg:province":"Bern",
    "wof:name":"Hans R. H\u00e4mmerli-stiftung",
    "wof:placetype":"venue"
},
  "geometry": {"coordinates":[9.8237752914,46.7992477417],"type":"Point"}
}