{
  "type": "Feature",
  "properties": {
    "iso:country":"CH",
    "sg:address":"Chemin Du Vernay 1196 Gland Case Postale 149",
    "sg:city":"Gland",
    "sg:orig_category":"Bauspenglerei Dachdeckerei",
    "sg:phone":"+41 22 364 11 58",
    "sg:postcode":"1196",
    "sg:province":"Vaud",
    "wof:name":"Roland Voutat Sa Inst.sanitaires & Ferblanterie",
    "wof:placetype":"venue"
},
  "geometry": {"coordinates":[6.27207,46.422554],"type":"Point"}
}