{
  "type": "Feature",
  "properties": {
    "iso:country":"CH",
    "sg:address":"Hauptstrasse 33",
    "sg:city":"Sommeri",
    "sg:orig_category":"Unclassifiable Establishments",
    "sg:phone":"+41 71 410 00 51",
    "sg:postcode":"8580",
    "sg:province":"Thurgau",
    "wof:name":"Th Architektur Gmbh",
    "wof:placetype":"venue"
},
  "geometry": {"coordinates":[9.2868404388,47.5688018799],"type":"Point"}
}