{
  "type": "Feature",
  "properties": {
    "iso:country":"CH",
    "sg:address":"Via Giuseppe Motta 26",
    "sg:city":"Mendrisio",
    "sg:orig_category":"Herstellung von Teigwaren",
    "sg:phone":"+41 91 646 80 19",
    "sg:postcode":"6850",
    "sg:province":"Ticino",
    "wof:name":"Bruno Croci Laboratorio Di Pasta Fresca",
    "wof:placetype":"venue"
},
  "geometry": {"coordinates":[8.9849720001,45.8688163757],"type":"Point"}
}