{
  "type": "Feature",
  "properties": {
    "iso:country":"CH",
    "sg:address":"Schulstrasse 29",
    "sg:city":"Z\u00fcrich",
    "sg:orig_category":"Massagestudios",
    "sg:phone":"+41 13132969",
    "sg:postcode":"8050",
    "sg:province":"Z\u00fcrich",
    "wof:name":"Claudia Steiger Massagepraxis",
    "wof:placetype":"venue"
},
  "geometry": {"coordinates":[8.5440664291,47.4090118408],"type":"Point"}
}