{
  "type": "Feature",
  "properties": {
    "iso:country":"CH",
    "sg:address":"Freiburgstrasse 310",
    "sg:city":"Bern",
    "sg:orig_category":"Instandhaltung U Reparatur von Automobilen",
    "sg:phone":"+41 31 747 72 32",
    "sg:postcode":"3018",
    "sg:province":"Bern",
    "wof:name":"Autogarage Scheibler Richard.",
    "wof:placetype":"venue"
},
  "geometry": {"coordinates":[7.2355771065,46.9054489136],"type":"Point"}
}