{
  "type": "Feature",
  "properties": {
    "iso:country":"CH",
    "sg:address":"3945 Gampel. Postfach 34",
    "sg:city":"Gampel",
    "sg:orig_category":"Verkehrs- and Tourismusb\u00fcros",
    "sg:phone":"+41 27 932 24 60",
    "sg:postcode":"3945",
    "sg:province":"Valais",
    "wof:name":"Verkehrsverein Gampel-bratsch",
    "wof:placetype":"venue"
},
  "geometry": {"coordinates":[7.7440090179,46.3165092468],"type":"Point"}
}