{
  "type": "Feature",
  "properties": {
    "iso:country":"CH",
    "sg:address":"La Stampa Via Alla Stampa",
    "sg:city":"Cadro",
    "sg:orig_category":"Verwaltung der Strafvollzuganstalten Wohnheime",
    "sg:phone":"+41 91 935 06 00",
    "sg:postcode":"6965",
    "sg:province":"Ticino",
    "wof:name":"Penitenziario Di Stato Del Cantone Ticino",
    "wof:placetype":"venue"
},
  "geometry": {"coordinates":[8.9743824005,46.0413742065],"type":"Point"}
}