{
  "type": "Feature",
  "properties": {
    "iso:country":"CH",
    "sg:address":"Neugasse 6",
    "sg:city":"Z\u00fcrich",
    "sg:orig_category":"Unclassifiable Establishments",
    "sg:postcode":"8005",
    "sg:province":"Z\u00fcrich",
    "wof:name":"Dela Re S.a., Luxembourg, Zweigniederlassung Z\u00fcrich",
    "wof:placetype":"venue"
},
  "geometry": {"coordinates":[8.5320081711,47.381362915],"type":"Point"}
}