{
  "type": "Feature",
  "properties": {
    "iso:country":"CH",
    "sg:address":"Engi",
    "sg:city":"Bernhardzell",
    "sg:classifiers":[
        {
            "category":"Restaurant",
            "type":"Food & Drink"
        }
    ],
    "sg:phone":"+41 71 433 13 38",
    "sg:postcode":"9304",
    "sg:province":"St. Gallen",
    "wof:name":"Restaurant R\u00f6ssli",
    "wof:placetype":"venue"
},
  "geometry": {"coordinates":[9.3437681198,47.4695091248],"type":"Point"}
}