{
  "type": "Feature",
  "properties": {
    "iso:country":"CH",
    "sg:address":"Route Du Port 11-12",
    "sg:city":"Pully",
    "sg:orig_category":"Erbringung von Dienstleistungen f\u00fcr Unternehmen Innendekorationsateliers",
    "sg:phone":"+41 21 728 45 66",
    "sg:postcode":"1009",
    "sg:province":"Vaud",
    "wof:name":"Francine Guex D\u00e9coration D'int\u00e9rieur",
    "wof:placetype":"venue"
},
  "geometry": {"coordinates":[6.6630511284,46.5062599182],"type":"Point"}
}