{
  "type": "Feature",
  "properties": {
    "iso:country":"CH",
    "sg:address":"G\u00e4ssliacker 13",
    "sg:city":"Tecknau",
    "sg:orig_category":"Instandhaltung U Reparatur von Automobilen",
    "sg:phone":"+41 61 981 20 86",
    "sg:postcode":"4492",
    "sg:province":"Basel-Landschaft",
    "wof:name":"W\u00fcthrich Ch.",
    "wof:placetype":"venue"
},
  "geometry": {"coordinates":[7.88078022,47.4501228333],"type":"Point"}
}