{
  "type": "Feature",
  "properties": {
    "iso:country":"CH",
    "sg:address":"Lohwisstrasse 46",
    "sg:city":"Ebmatingen",
    "sg:orig_category":"Anticorrosive Films",
    "sg:phone":"+41 18699170",
    "sg:postcode":"8123",
    "sg:province":"Z\u00fcrich",
    "wof:name":"Brangs + Heinrich Ag",
    "wof:placetype":"venue"
},
  "geometry": {"coordinates":[8.506732,47.597546],"type":"Point"}
}