{
  "type": "Feature",
  "properties": {
    "iso:country":"CH",
    "sg:address":"W\u00fclflingerstrasse 227",
    "sg:city":"Winterthur",
    "sg:orig_category":"Handel mit Automobilen Handelsvermittlung U Grosshandel mit Automobilen",
    "sg:phone":"+41 41 630 30 31",
    "sg:postcode":"8408",
    "sg:province":"Z\u00fcrich",
    "wof:name":"A + B Handels Gmbh Automobile, Waren; Handel Usw",
    "wof:placetype":"venue"
},
  "geometry": {"coordinates":[8.3142662048,46.9925308228],"type":"Point"}
}