{
  "type": "Feature",
  "properties": {
    "iso:country":"CH",
    "sg:address":"Chriesmattweg 9 8600 D\u00fcbendorf. Postfach",
    "sg:city":"D\u00fcbendorf",
    "sg:orig_category":"Sonstige mit der Informatik verbundene T\u00e4tigkeiten",
    "sg:phone":"+41 18220967",
    "sg:postcode":"8600",
    "sg:province":"Z\u00fcrich",
    "wof:name":"Guming Consulting Gmbh Informatik; Dienstleistungen, Bes. Beratungen",
    "wof:placetype":"venue"
},
  "geometry": {"coordinates":[8.6261329651,47.4060516357],"type":"Point"}
}