{
  "type": "Feature",
  "properties": {
    "iso:country":"CH",
    "sg:address":"Gewerbestrasse 5",
    "sg:city":"Cham",
    "sg:orig_category":"Grosshandel mit Parf\u00fcmerieartikeln U K\u00f6rperpflegemitteln Herstellung von pharmazeutischen Grundstoff",
    "sg:phone":"+41 79 321 84 70",
    "sg:postcode":"6330",
    "sg:province":"Zug",
    "wof:name":"Everest Pharma Gmbh",
    "wof:placetype":"venue"
},
  "geometry": {"coordinates":[8.4734659195,47.1885452271],"type":"Point"}
}