{
  "type": "Feature",
  "properties": {
    "iso:country":"CH",
    "sg:address":"Chemin Du Pr\u00e9-gabet 38",
    "sg:city":"Aire-la-ville",
    "sg:orig_category":"Physiotherapie",
    "sg:phone":"+41 22 794 00 55",
    "sg:postcode":"1288",
    "sg:province":"Gen\u00e8ve",
    "wof:name":"Fabienne Cell\u00e9rier Physioth\u00e9rapie",
    "wof:placetype":"venue"
},
  "geometry": {"coordinates":[6.0421619415,46.189289093],"type":"Point"}
}