{
  "type": "Feature",
  "properties": {
    "iso:country":"CH",
    "sg:address":"Presinge Route De 85",
    "sg:city":"Puplinge",
    "sg:orig_category":"Mechanik",
    "sg:postcode":"1241",
    "sg:province":"Gen\u00e8ve",
    "wof:name":"K\u00fcbel-wilsdorf Florian",
    "wof:placetype":"venue"
},
  "geometry": {"coordinates":[6.232375145,46.21118927],"type":"Point"}
}