{
  "type": "Feature",
  "properties": {
    "addr:full":"Moosmattstrasse 4 Berom\u00fcnster Luzern 6215",
    "addr:housenumber":"4",
    "addr:postcode":"6215",
    "addr:street":"Moosmattstrasse",
    "iso:country":"CH",
    "sg:address":"Moosmattstrasse 4",
    "sg:city":"Berom\u00fcnster",
    "sg:orig_category":"Allgemeiner Hoch U Tiefbau",
    "sg:phone":"+41 41 930 26 71",
    "sg:postcode":"6215",
    "sg:province":"Luzern",
    "wof:name":"Hofer Bauunternehmung",
    "wof:placetype":"venue"
},
  "geometry": {"coordinates":[8.200036,47.203087],"type":"Point"}
}