{
  "type": "Feature",
  "properties": {
    "iso:country":"CH",
    "sg:address":"Bahnhofstrasse 2 6383 Dallenwil. Postfach",
    "sg:city":"Dallenwil",
    "sg:orig_category":"RESTAURANTS: TEA-ROOMS",
    "sg:postcode":"6383",
    "sg:province":"Nidwalden",
    "wof:name":"Martins Luis Isabel Gmbh Dienstleistungen Im Restaurationsbereich. Gastgewerbliche Betriebe Usw",
    "wof:placetype":"venue"
},
  "geometry": {"coordinates":[8.3912239075,46.9329376221],"type":"Point"}
}