{
  "type": "Feature",
  "properties": {
    "iso:country":"CH",
    "sg:address":"Industriestrasse 9-11",
    "sg:city":"Aadorf",
    "sg:classifiers":[
        {
            "category":"Banks & Credit Unions",
            "subcategory":"Investment Brokerage",
            "type":"Services"
        }
    ],
    "sg:phone":"+41 52 368 02 68",
    "sg:postcode":"8355",
    "sg:province":"Thurgau",
    "sg:tags":[
        "condition",
        "work",
        "assembly",
        "room",
        "clean"
    ],
    "wof:name":"Alme Ag",
    "wof:placetype":"venue"
},
  "geometry": {"coordinates":[8.899831,47.496902],"type":"Point"}
}