{
  "type": "Feature",
  "properties": {
    "iso:country":"CH",
    "sg:address":"Hauptstrasse 29",
    "sg:city":"Ligerz",
    "sg:orig_category":"Dauerkulturbau Rebbau",
    "sg:phone":"+41 79 446 32 43",
    "sg:postcode":"2514",
    "sg:province":"Bern",
    "wof:name":"Auberson & Fils Propri\u00e9taires-encaveurs",
    "wof:placetype":"venue"
},
  "geometry": {"coordinates":[7.094986,47.06834],"type":"Point"}
}