{
  "type": "Feature",
  "properties": {
    "iso:country":"CH",
    "sg:address":"Centralbahnstrasse 19",
    "sg:city":"Basel",
    "sg:orig_category":"Pensionskassen",
    "sg:postcode":"4051",
    "sg:province":"Basel-Stadt",
    "wof:name":"Personalf\u00fcrsorgestiftung Der Aslantrans Ag",
    "wof:placetype":"venue"
},
  "geometry": {"coordinates":[7.5917267799,47.5471954346],"type":"Point"}
}