{
  "type": "Feature",
  "properties": {
    "iso:country":"CH",
    "sg:address":"Rousseaustrasse 72",
    "sg:city":"Z\u00fcrich",
    "sg:orig_category":"Unclassifiable Establishments",
    "sg:postcode":"8037",
    "sg:province":"Z\u00fcrich",
    "wof:name":"Sonja M. Balestra Naturheilpraxis",
    "wof:placetype":"venue"
},
  "geometry": {"coordinates":[8.531961441,47.3908157349],"type":"Point"}
}