{
  "type": "Feature",
  "properties": {
    "iso:country":"CH",
    "sg:address":"Allmendstrasse 92",
    "sg:city":"Uetendorf",
    "sg:orig_category":"Sanit\u00e4r U Heizungsinstallation Sanit\u00e4rinstallation",
    "sg:phone":"+41 71 351 55 22",
    "sg:postcode":"3661",
    "sg:province":"Bern",
    "wof:name":"Beat Und Ruedi Eugster Gmbh",
    "wof:placetype":"venue"
},
  "geometry": {"coordinates":[9.2422275543,47.3834190369],"type":"Point"}
}