{
  "type": "Feature",
  "properties": {
    "iso:country":"CH",
    "sg:address":"La Cour 63",
    "sg:city":"Chevenez",
    "sg:orig_category":"Sonstige pers\u00f6nliche Dienstleistungen",
    "sg:phone":"+41 32 476 66 39",
    "sg:postcode":"2906",
    "sg:province":"Jura",
    "wof:name":"La Clef Du Bonheur, P\u00e9riat Carole",
    "wof:placetype":"venue"
},
  "geometry": {"coordinates":[6.9996199608,47.3915290833],"type":"Point"}
}