{
  "type": "Feature",
  "properties": {
    "iso:country":"CH",
    "sg:address":"Z\u00fcrcherstrasse 4 8730 Uznach. Postfach",
    "sg:city":"Uznach",
    "sg:classifiers":[
        {
            "category":"Restaurant",
            "type":"Food & Drink"
        }
    ],
    "sg:phone":"+41 55 280 42 67",
    "sg:postcode":"8730",
    "sg:province":"St. Gallen",
    "wof:name":"Restaurant P\u00f6stli",
    "wof:placetype":"venue"
},
  "geometry": {"coordinates":[8.9837112427,47.2249145508],"type":"Point"}
}