{
  "type": "Feature",
  "properties": {
    "iso:country":"CH",
    "sg:address":"Rue J.-gab.-eynard 8",
    "sg:city":"Gen\u00e8ve",
    "sg:orig_category":"Bauingenieurb\u00fcros allgemein",
    "sg:phone":"+41 22 310 67 66",
    "sg:postcode":"1205",
    "sg:province":"Gen\u00e8ve",
    "wof:name":"Blanchut & Bertrand S\u00e0rl Entreprise G\u00e9n.d'ing\u00e9nierie",
    "wof:placetype":"venue"
},
  "geometry": {"coordinates":[6.148285,46.198025],"type":"Point"}
}