{
  "type": "Feature",
  "properties": {
    "iso:country":"CH",
    "sg:address":"Pedemonte Via 12",
    "sg:city":"Viganello",
    "sg:orig_category":"Vermietung U Verpachtung von eigenen Immobilien",
    "sg:postcode":"6962",
    "sg:province":"Ticino",
    "wof:name":"Topazio Sa",
    "wof:placetype":"venue"
},
  "geometry": {"coordinates":[8.9684677124,46.0106773376],"type":"Point"}
}