{
  "type": "Feature",
  "properties": {
    "iso:country":"CH",
    "sg:address":"Via Franco Zorzi 40",
    "sg:city":"Bellinzona",
    "sg:orig_category":"Instandhaltung U Reparatur von Automobilen Vermietung von Automobilen",
    "sg:phone":"+41 91 825 31 52",
    "sg:postcode":"6500",
    "sg:province":"Ticino",
    "wof:name":"Autoservizio Saleggi Di Ponzio Alberto",
    "wof:placetype":"venue"
},
  "geometry": {"coordinates":[9.0131130219,46.1818351746],"type":"Point"}
}