{
  "type": "Feature",
  "properties": {
    "iso:country":"CH",
    "sg:address":"Helv\u00e9tique Bvd 34 1207 Gen\u00e8ve. Postfach",
    "sg:city":"Gen\u00e8ve",
    "sg:orig_category":"Sonstiger Grosshandel",
    "sg:postcode":"1207",
    "sg:province":"Gen\u00e8ve",
    "wof:name":"Carmina Ag",
    "wof:placetype":"venue"
},
  "geometry": {"coordinates":[6.1550579071,46.2017555237],"type":"Point"}
}