{
  "type": "Feature",
  "properties": {
    "iso:country":"CH",
    "sg:address":"Aegerten 31",
    "sg:city":"K\u00f6lliken",
    "sg:orig_category":"Herstellung von sonstigen Metallwaren",
    "sg:postcode":"5742",
    "sg:province":"Aargau",
    "wof:name":"Bhb Gmbh",
    "wof:placetype":"venue"
},
  "geometry": {"coordinates":[8.0057640076,47.3287200928],"type":"Point"}
}