{
  "type": "Feature",
  "properties": {
    "addr:full":"Rte De Courtavon 43 Mi\u00e9court Jura 2946",
    "addr:housenumber":"43",
    "addr:postcode":"2946",
    "addr:street":"Rte De Courtavon;Jura",
    "iso:country":"CH",
    "sg:address":"Rte De Courtavon 43",
    "sg:city":"Mi\u00e9court",
    "sg:classifiers":[
        {
            "category":"Banks & Credit Unions",
            "subcategory":"Bank",
            "type":"Services"
        }
    ],
    "sg:phone":"+41 32 462 31 66",
    "sg:postcode":"2946",
    "sg:province":"Jura",
    "wof:name":"Raiffeisen",
    "wof:placetype":"venue"
},
  "geometry": {"coordinates":[7.179493,47.429909],"type":"Point"}
}