{
  "type": "Feature",
  "properties": {
    "iso:country":"CH",
    "sg:address":"Untere Hohlgasse 6 8400 Winterthur. Postfach",
    "sg:city":"Winterthur",
    "sg:orig_category":"Wasserversorgung",
    "sg:postcode":"8404",
    "sg:province":"Z\u00fcrich",
    "wof:name":"Rocchetti Wasser-technik",
    "wof:placetype":"venue"
},
  "geometry": {"coordinates":[8.7567310333,47.5068016052],"type":"Point"}
}