{
  "type": "Feature",
  "properties": {
    "iso:country":"CH",
    "sg:address":"M\u00fchlestrasse 26",
    "sg:city":"R\u00fcschlikon",
    "sg:orig_category":"Forschung U Entwicklung im Bereich der Naturwissenschaften",
    "sg:postcode":"8803",
    "sg:province":"Z\u00fcrich",
    "wof:name":"Schweizerische Arbeitsgemeinschaft F\u00fcr Computerchemie",
    "wof:placetype":"venue"
},
  "geometry": {"coordinates":[8.5573940277,47.3059883118],"type":"Point"}
}