{
  "type": "Feature",
  "properties": {
    "iso:country":"CH",
    "sg:address":"Hofackerstrasse 2",
    "sg:city":"Dielsdorf",
    "sg:orig_category":"Vorschulen, Kinderg\u00e4rten",
    "sg:phone":"+41 18530782",
    "sg:postcode":"8157",
    "sg:province":"Z\u00fcrich",
    "wof:name":"Kindergarten Hofacker",
    "wof:placetype":"venue"
},
  "geometry": {"coordinates":[8.454916954,47.4852752686],"type":"Point"}
}