{
  "type": "Feature",
  "properties": {
    "iso:country":"CH",
    "sg:address":"Mussard Rue Henri- 2 1208 Gen\u00e8ve. Postfach",
    "sg:city":"Gen\u00e8ve",
    "sg:orig_category":"Unclassifiable Establishments",
    "sg:postcode":"1201",
    "sg:province":"Gen\u00e8ve",
    "wof:name":"Hodepar Sa",
    "wof:placetype":"venue"
},
  "geometry": {"coordinates":[6.163105011,46.19871521],"type":"Point"}
}