{
  "type": "Feature",
  "properties": {
    "iso:country":"CH",
    "sg:address":"Mariettaweg 4",
    "sg:city":"Frick",
    "sg:orig_category":"Bauspenglerei Sanit\u00e4rinstallation U Spenglerei",
    "sg:phone":"+41 62 871 42 70",
    "sg:postcode":"5070",
    "sg:province":"Aargau",
    "wof:name":"Ernst Lenz Ag",
    "wof:placetype":"venue"
},
  "geometry": {"coordinates":[8.02333,47.509052],"type":"Point"}
}