{
  "type": "Feature",
  "properties": {
    "iso:country":"CH",
    "sg:address":"Kreuzmatte 12",
    "sg:city":"Reiden",
    "sg:orig_category":"Instandhaltung U Reparatur von Automobilen",
    "sg:phone":"+41 79 354 54 04",
    "sg:postcode":"6260",
    "sg:province":"Luzern",
    "wof:name":"Garage Baumgartner H.r. Ag",
    "wof:placetype":"venue"
},
  "geometry": {"coordinates":[7.9616041183,47.2469100952],"type":"Point"}
}