{
  "type": "Feature",
  "properties": {
    "iso:country":"CH",
    "sg:address":"M\u00f6serwies Eggerstanden 9050 R\u00fcte. Postfach",
    "sg:city":"Appenzell",
    "sg:orig_category":"Herstellung von Zement",
    "sg:postcode":"9050",
    "sg:province":"Appenzell Innerhoden",
    "wof:name":"Toni Hautle Gmbh",
    "wof:placetype":"venue"
},
  "geometry": {"coordinates":[9.42091465,47.3290977478],"type":"Point"}
}