{
  "type": "Feature",
  "properties": {
    "addr:full":"M\u00fcrliweg 2 Mollis Glarus 8753",
    "addr:housenumber":"2",
    "addr:postcode":"8753",
    "addr:street":"Muerliweg",
    "iso:country":"CH",
    "sg:address":"M\u00fcrliweg 2",
    "sg:city":"Mollis",
    "sg:orig_category":"Bauschreinerei Herstellung von Konstruktionsteilen, Fertigbauteilen U Ausbauelementen aus Holz",
    "sg:phone":"+41 55 612 39 51",
    "sg:postcode":"8753",
    "sg:province":"Glarus",
    "wof:name":"Urs Guler Bauschreinerei",
    "wof:placetype":"venue"
},
  "geometry": {"coordinates":[9.074863,47.091515],"type":"Point"}
}