{
  "type": "Feature",
  "properties": {
    "iso:country":"CH",
    "sg:address":"Reutistrasse 7",
    "sg:city":"Kreuzlingen",
    "sg:orig_category":"Sanit\u00e4r U Heizungsinstallation Sanit\u00e4r, Heizungs U L\u00fcftungsinstallation",
    "sg:phone":"+41 71 688 47 34",
    "sg:postcode":"8280",
    "sg:province":"Thurgau",
    "wof:name":"G\u00fcnter Welte Heizungen",
    "wof:placetype":"venue"
},
  "geometry": {"coordinates":[9.1979780197,47.6399726868],"type":"Point"}
}