{
  "type": "Feature",
  "properties": {
    "iso:country":"CH",
    "sg:address":"Breitenrainplatz 38",
    "sg:city":"Bern",
    "sg:orig_category":"Detailhandel mit Fleisch U Fleischwaren",
    "sg:phone":"+41 31 331 93 60",
    "sg:postcode":"3014",
    "sg:province":"Bern",
    "wof:name":"Metzgerei Schori Ag",
    "wof:placetype":"venue"
},
  "geometry": {"coordinates":[7.4543361664,46.9586982727],"type":"Point"}
}