{
  "type": "Feature",
  "properties": {
    "iso:country":"CH",
    "sg:address":"Gurnigelstrasse 1",
    "sg:city":"Nidau",
    "sg:orig_category":"Offsetdruck",
    "sg:phone":"+41 32 365 57 27",
    "sg:postcode":"2560",
    "sg:province":"Bern",
    "wof:name":"Hanni Gribi Buchdruckerei",
    "wof:placetype":"venue"
},
  "geometry": {"coordinates":[7.2423329353,47.1280593872],"type":"Point"}
}