{
  "type": "Feature",
  "properties": {
    "iso:country":"CH",
    "sg:address":"Industriestrasse Postfach 823",
    "sg:city":"Hochdorf",
    "sg:classifiers":[
        {
            "category":"Utilities",
            "subcategory":"Electric",
            "type":"Services"
        }
    ],
    "sg:phone":"+41 41 914 11 11",
    "sg:postcode":"6281",
    "sg:province":"Luzern",
    "sg:tags":[
        "electricity",
        "raw",
        "energy",
        "material"
    ],
    "wof:name":"Elektrizit\u00c4tswerk Hochdorf Ag",
    "wof:placetype":"venue"
},
  "geometry": {"coordinates":[7.08604002,51.2439613342],"type":"Point"}
}