{
  "type": "Feature",
  "properties": {
    "iso:country":"CH",
    "sg:address":"Grand-rue 17",
    "sg:city":"Ch\u00e9zard-st-martin",
    "sg:orig_category":"Detailhandel mit Metallwaren, Anstrichmitteln, Glaswaren, Bau U Heimwerkerbedarf",
    "sg:phone":"+41 32 853 36 00",
    "sg:postcode":"2054",
    "sg:province":"Neuch\u00e2tel",
    "wof:name":"Ga\u00efa Distribution, Vadi Douce Et Jacques",
    "wof:placetype":"venue"
},
  "geometry": {"coordinates":[6.9190487862,47.0632400513],"type":"Point"}
}