{
  "type": "Feature",
  "properties": {
    "iso:country":"CH",
    "sg:address":"Talackerstrasse 17",
    "sg:city":"Glattbrugg",
    "sg:classifiers":[
        {
            "category":"Shopping",
            "subcategory":"Clothing, Apparel, & Fashions",
            "type":"Retail Goods"
        }
    ],
    "sg:phone":"+41 18293080",
    "sg:postcode":"8152",
    "sg:province":"Z\u00fcrich",
    "sg:tags":[
        "children's",
        "clothing"
    ],
    "wof:name":"Attias Textiles Sa",
    "wof:placetype":"venue"
},
  "geometry": {"coordinates":[8.5612,47.42585],"type":"Point"}
}