{
  "type": "Feature",
  "properties": {
    "iso:country":"CH",
    "sg:address":"Kilchbergstrasse 24",
    "sg:city":"Adliswil",
    "sg:orig_category":"Forschung U Entwicklung im Bereich der Naturwissenschaften",
    "sg:phone":"+41 17102804",
    "sg:postcode":"8134",
    "sg:province":"Z\u00fcrich",
    "wof:name":"Reichlin Dr. Anita",
    "wof:placetype":"venue"
},
  "geometry": {"coordinates":[8.5302715302,47.3128356934],"type":"Point"}
}