{
  "type": "Feature",
  "properties": {
    "iso:country":"CH",
    "sg:address":"Gottardo Via San 111",
    "sg:city":"Balerna",
    "sg:orig_category":"Herstellung von Seifen, Wasch U Reinigungsmitteln",
    "sg:phone":"+41 55 246 44 44",
    "sg:postcode":"6828",
    "sg:province":"Ticino",
    "wof:name":"Santop Gmbh Reinigungsmittel, -papier, Spendersysteme; Handel. Handtuchautomaten; Vermietung",
    "wof:placetype":"venue"
},
  "geometry": {"coordinates":[8.9413003922,47.2884101868],"type":"Point"}
}