{
  "type": "Feature",
  "properties": {
    "iso:country":"CH",
    "sg:address":"Chemin De La Cure 11",
    "sg:city":"Lausanne",
    "sg:orig_category":"Arztpraxen",
    "sg:phone":"+41 21 652 83 57",
    "sg:postcode":"1012",
    "sg:province":"Vaud",
    "wof:name":"Dr M\u00e9d. Ren\u00e9 Delaloye M\u00e9decin Sp\u00e9cialiste Fmh",
    "wof:placetype":"venue"
},
  "geometry": {"coordinates":[6.65765,46.529137],"type":"Point"}
}