{
  "type": "Feature",
  "properties": {
    "iso:country":"CH",
    "sg:address":"Eggh\u00f6lzlistrasse 1a",
    "sg:city":"Bern",
    "sg:orig_category":"Fussreflexzonenmassage",
    "sg:phone":"+41 31 352 66 40",
    "sg:postcode":"3006",
    "sg:province":"Bern",
    "wof:name":"Erika Moser Fussreflexzonenmassagen",
    "wof:placetype":"venue"
},
  "geometry": {"coordinates":[7.475151062,46.9367713928],"type":"Point"}
}