{
  "type": "Feature",
  "properties": {
    "addr:full":"Mattenweg 1 W\u00e4denswil Z\u00fcrich 8820",
    "addr:housenumber":"1",
    "addr:postcode":"8820",
    "addr:street":"Mattenweg;Zuerich",
    "iso:country":"CH",
    "sg:address":"Mattenweg 1",
    "sg:city":"W\u00e4denswil",
    "sg:classifiers":[
        {
            "category":"Manufacturing",
            "subcategory":"Printing",
            "type":"Manufacturing & Wholesale Goods"
        }
    ],
    "sg:phone":"+41 17802433",
    "sg:postcode":"8820",
    "sg:province":"Z\u00fcrich",
    "sg:tags":[
        "system",
        "digital"
    ],
    "wof:name":"Heinrich Mantel Ag",
    "wof:placetype":"venue"
},
  "geometry": {"coordinates":[8.673622,47.227802],"type":"Point"}
}