{
  "type": "Feature",
  "properties": {
    "iso:country":"CH",
    "sg:address":"Sagenblickstrasse 31",
    "sg:city":"Ebikon",
    "sg:orig_category":"Architekturb\u00fcros",
    "sg:phone":"+41 41 440 66 20",
    "sg:postcode":"6030",
    "sg:province":"Luzern",
    "wof:name":"Marco Wey & Henri Vogel Architektengemeinschaft",
    "wof:placetype":"venue"
},
  "geometry": {"coordinates":[8.341254,47.073269],"type":"Point"}
}