{
  "type": "Feature",
  "properties": {
    "iso:country":"CH",
    "sg:address":"Baldernstrasse 5",
    "sg:city":"Adliswil",
    "sg:orig_category":"Vereine Harmonika and Akkordeon",
    "sg:phone":"+41 17131514",
    "sg:postcode":"8134",
    "sg:province":"Z\u00fcrich",
    "wof:name":"Akkordeon Orchester Adliswil",
    "wof:placetype":"venue"
},
  "geometry": {"coordinates":[8.5378904343,47.2870101929],"type":"Point"}
}