{
  "type": "Feature",
  "properties": {
    "iso:country":"CH",
    "sg:address":"S\u00e4getstrasse 25",
    "sg:city":"Jegenstorf",
    "sg:orig_category":"Wirtschaftspr\u00fcfung, Steuerberatung U Treuhand",
    "sg:postcode":"3303",
    "sg:province":"Bern",
    "wof:name":"Salvisberg Baupromotion + Immobilien Ag Filiale Jegenstorf",
    "wof:placetype":"venue"
},
  "geometry": {"coordinates":[7.5074400902,47.0521240234],"type":"Point"}
}