{
  "type": "Feature",
  "properties": {
    "iso:country":"CH",
    "sg:address":"Sonnenbergstr. 23",
    "sg:city":"Uster",
    "sg:orig_category":"Herstellung von Radio U Fernsehger\u00e4ten sowie phono U videotechnischen Ger\u00e4ten",
    "sg:phone":"+41 79 421 71 64",
    "sg:postcode":"8610",
    "sg:province":"Z\u00fcrich",
    "wof:name":"Bachofen Electronic Games",
    "wof:placetype":"venue"
},
  "geometry": {"coordinates":[8.7052001953,47.3514099121],"type":"Point"}
}