{
  "type": "Feature",
  "properties": {
    "iso:country":"CH",
    "sg:address":"Borrweg 64",
    "sg:city":"Z\u00fcrich",
    "sg:orig_category":"Elektroinstallation",
    "sg:phone":"+41 14610664",
    "sg:postcode":"8055",
    "sg:province":"Z\u00fcrich",
    "wof:name":"Kiraly E.",
    "wof:placetype":"venue"
},
  "geometry": {"coordinates":[8.5063486099,47.36145401],"type":"Point"}
}