{
  "type": "Feature",
  "properties": {
    "iso:country":"CH",
    "sg:address":"Eichfeldstrasse 3a",
    "sg:city":"Jona",
    "sg:orig_category":"Vereine Frauen Vereine Gemeinn\u00fctzige",
    "sg:phone":"+41 55 210 64 26",
    "sg:postcode":"8645",
    "sg:province":"St. Gallen",
    "wof:name":"Gemeinn\u00fctziger Frauenverein",
    "wof:placetype":"venue"
},
  "geometry": {"coordinates":[8.8330698013,47.2287902832],"type":"Point"}
}