{
  "type": "Feature",
  "properties": {
    "iso:country":"CH",
    "sg:address":"Binzm\u00fchlestrasse 45",
    "sg:city":"Z\u00fcrich",
    "sg:orig_category":"Non-Classified Establishments",
    "sg:postcode":"8050",
    "sg:province":"Z\u00fcrich",
    "wof:name":"Miz, M. Kosic",
    "wof:placetype":"venue"
},
  "geometry": {"coordinates":[8.5449647903,47.4137382507],"type":"Point"}
}