{
  "type": "Feature",
  "properties": {
    "iso:country":"CH",
    "sg:address":"Sihlbruggstrasse 105 6340 Baar. Postfach",
    "sg:city":"Baar",
    "sg:orig_category":"Schreib U \u00dcbersetzungsb\u00fcros",
    "sg:postcode":"6340",
    "sg:province":"Zug",
    "wof:name":"Alleva Gabriele Uebersetzungen",
    "wof:placetype":"venue"
},
  "geometry": {"coordinates":[8.5390930176,47.1977767944],"type":"Point"}
}