{
  "type": "Feature",
  "properties": {
    "iso:country":"CH",
    "sg:address":"H\u00f6rnliberg 1",
    "sg:city":"Niederhelfenschwil",
    "sg:orig_category":"Detailhandel mit Brot, Back U S\u00fcsswaren",
    "sg:postcode":"9527",
    "sg:province":"St. Gallen",
    "wof:name":"Thalmann-kunz B.",
    "wof:placetype":"venue"
},
  "geometry": {"coordinates":[7.96201,47.119591],"type":"Point"}
}