{
  "type": "Feature",
  "properties": {
    "iso:country":"CH",
    "sg:address":"Fonderie Rue De La 14",
    "sg:city":"Ardon",
    "sg:orig_category":"Unternehmensberatung",
    "sg:phone":"+41 27 306 25 58",
    "sg:postcode":"1957",
    "sg:province":"Valais",
    "wof:name":"Delaloye Jean-pierre",
    "wof:placetype":"venue"
},
  "geometry": {"coordinates":[7.2555451393,46.2083091736],"type":"Point"}
}