{
  "type": "Feature",
  "properties": {
    "iso:country":"CH",
    "sg:address":"Dorfstrasse 36",
    "sg:city":"Selzach",
    "sg:orig_category":"Sonstiger spezialisierter Hoch U Tiefbau",
    "sg:phone":"+41 32 641 31 36",
    "sg:postcode":"2545",
    "sg:province":"Solothurn",
    "wof:name":"Arcorace Gmbh",
    "wof:placetype":"venue"
},
  "geometry": {"coordinates":[7.4531798363,47.2065887451],"type":"Point"}
}