{
  "type": "Feature",
  "properties": {
    "iso:country":"CH",
    "sg:address":"M\u00fchlefuhr",
    "sg:city":"Ennenda",
    "sg:orig_category":"Stukkateurgewerbe, Gipserei U Verputzerei",
    "sg:phone":"+41 58615648",
    "sg:postcode":"8755",
    "sg:province":"Glarus",
    "wof:name":"Quadri Ag",
    "wof:placetype":"venue"
},
  "geometry": {"coordinates":[9.0826072693,47.0260696411],"type":"Point"}
}