{
  "type": "Feature",
  "properties": {
    "iso:country":"CH",
    "sg:address":"Zofingerstrasse 33",
    "sg:city":"Brittnau",
    "sg:orig_category":"Non-Classified Establishments",
    "sg:phone":"+41 62 751 86 24",
    "sg:postcode":"4805",
    "sg:province":"Aargau",
    "wof:name":"Walter Fehr, Unabh\u00e4ngiger Wintergartenberater",
    "wof:placetype":"venue"
},
  "geometry": {"coordinates":[7.9486241341,47.2733955383],"type":"Point"}
}