{
  "type": "Feature",
  "properties": {
    "iso:country":"CH",
    "sg:address":"Gartenstrasse 8c",
    "sg:city":"Baar",
    "sg:orig_category":"Sanit\u00e4r, Heizungs U L\u00fcftungsinstallation",
    "sg:phone":"+41 79 414 11 62",
    "sg:postcode":"6340",
    "sg:province":"Zug",
    "wof:name":"Frank Roger",
    "wof:placetype":"venue"
},
  "geometry": {"coordinates":[8.5263681412,47.1978149414],"type":"Point"}
}