{
  "type": "Feature",
  "properties": {
    "iso:country":"CH",
    "sg:address":"Pfaffenholzstrasse 4",
    "sg:city":"Frauenfeld",
    "sg:orig_category":"Interessenvertretungen",
    "sg:postcode":"8500",
    "sg:province":"Thurgau",
    "wof:name":"Thurg. Liga F\u00fcr Krebsbek\u00e4mpfung.",
    "wof:placetype":"venue"
},
  "geometry": {"coordinates":[8.9101266861,47.5495414734],"type":"Point"}
}