{
  "type": "Feature",
  "properties": {
    "iso:country":"CH",
    "sg:address":"Konsumstrasse 22",
    "sg:city":"Uzwil",
    "sg:orig_category":"Detailhandel mit Waren verschiedener Art, Hauptrichtung Nahrungsmittel",
    "sg:phone":"+41 71 951 14 14",
    "sg:postcode":"9240",
    "sg:province":"St. Gallen",
    "wof:name":"Coop Center",
    "wof:placetype":"venue"
},
  "geometry": {"coordinates":[9.1338176727,47.4366149902],"type":"Point"}
}