{
  "type": "Feature",
  "properties": {
    "iso:country":"CH",
    "sg:address":"Bundesplatz 1 6300 Zug. Postfach",
    "sg:city":"Zug",
    "sg:orig_category":"Non-Classified Establishments",
    "sg:phone":"+41 41 711 01 15",
    "sg:postcode":"6300",
    "sg:province":"Zug",
    "wof:name":"Sagapha Ag",
    "wof:placetype":"venue"
},
  "geometry": {"coordinates":[8.5155754089,47.1706352234],"type":"Point"}
}