{
  "type": "Feature",
  "properties": {
    "iso:country":"CH",
    "sg:address":"Wallisellerstrasse 30a",
    "sg:city":"Glattbrugg",
    "sg:orig_category":"Baugewerbe",
    "sg:phone":"+41 19306127",
    "sg:postcode":"8152",
    "sg:province":"Z\u00fcrich",
    "wof:name":"Bwt Bau Ag",
    "wof:placetype":"venue"
},
  "geometry": {"coordinates":[8.808319,47.331757],"type":"Point"}
}