{
  "type": "Feature",
  "properties": {
    "addr:full":"La Libert\u00e9 Kriens Luzern 6010",
    "addr:postcode":"6010",
    "addr:street":"La",
    "iso:country":"CH",
    "sg:address":"La Libert\u00e9",
    "sg:city":"Kriens",
    "sg:orig_category":"Architektur U Ingenieurb\u00fcros",
    "sg:postcode":"6010",
    "sg:province":"Luzern",
    "wof:name":"Eima Gmbh",
    "wof:placetype":"venue"
},
  "geometry": {"coordinates":[8.85994,47.188072],"type":"Point"}
}