{
  "type": "Feature",
  "properties": {
    "iso:country":"CH",
    "sg:address":"Route Des Rottes 31",
    "sg:city":"Conthey",
    "sg:orig_category":"Sanit\u00e4r, Heizungs U L\u00fcftungsinstallation Sanit\u00e4rinstallation",
    "sg:phone":"+41 24 492 26 77",
    "sg:postcode":"1964",
    "sg:province":"Valais",
    "wof:name":"Sanichau Service Des Ormonts Sa",
    "wof:placetype":"venue"
},
  "geometry": {"coordinates":[7.1587119102,46.3500404358],"type":"Point"}
}