{
  "type": "Feature",
  "properties": {
    "addr:full":"Bahnhofstr. 25 Schwanden Glarus 8762",
    "addr:housenumber":"25",
    "addr:postcode":"8762",
    "addr:street":"Bahnhofstr.",
    "iso:country":"CH",
    "sg:address":"Bahnhofstr. 25",
    "sg:city":"Schwanden",
    "sg:classifiers":[
        {
            "category":"Banks & Credit Unions",
            "subcategory":"Bank",
            "type":"Services"
        }
    ],
    "sg:postcode":"8762",
    "sg:province":"Glarus",
    "wof:name":"Globe Nuclear Services And Supply Gnss Limited",
    "wof:placetype":"venue"
},
  "geometry": {"coordinates":[7.90402,47.352112],"type":"Point"}
}