{
  "type": "Feature",
  "properties": {
    "iso:country":"CH",
    "sg:address":"Feldkircher Strasse 50",
    "sg:city":"Schaan",
    "sg:orig_category":"Handelsvermittlung U Grosshandel",
    "sg:phone":"+423 233 34 22",
    "sg:postcode":"9494",
    "wof:name":"Eurotrend Ag",
    "wof:placetype":"venue"
},
  "geometry": {"coordinates":[9.5160188675,47.1702003479],"type":"Point"}
}