{
  "type": "Feature",
  "properties": {
    "iso:country":"CH",
    "sg:address":"S\u00e4ntisstrasse 1 8305 Dietlikon. Postfach",
    "sg:city":"Dietlikon",
    "sg:orig_category":"Zahnarztpraxen",
    "sg:phone":"+41 18333940",
    "sg:postcode":"8305",
    "sg:province":"Z\u00fcrich",
    "wof:name":"Dr. Med. Dent. Ralph Burri Zahnarzt",
    "wof:placetype":"venue"
},
  "geometry": {"coordinates":[8.6192073822,47.4221343994],"type":"Point"}
}