{
  "type": "Feature",
  "properties": {
    "iso:country":"CH",
    "sg:address":"Bahnhofstrasse 20",
    "sg:city":"Naters",
    "sg:orig_category":"Arztpraxen",
    "sg:phone":"+41 27 924 24 09",
    "sg:postcode":"3904",
    "sg:province":"Valais",
    "wof:name":"Dr.med.hermann Schmidt Spezialarzt Fmh",
    "wof:placetype":"venue"
},
  "geometry": {"coordinates":[7.985676,46.323769],"type":"Point"}
}