{
  "type": "Feature",
  "properties": {
    "addr:full":"Stockbergstrasse 9 Siebnen Schwyz 8854",
    "addr:housenumber":"9",
    "addr:postcode":"8854",
    "addr:street":"Stockbergstrasse;Schwyz",
    "iso:country":"CH",
    "sg:address":"Stockbergstrasse 9",
    "sg:city":"Siebnen",
    "sg:classifiers":[
        {
            "category":"Social Services",
            "subcategory":"Retirement Home",
            "type":"Services"
        }
    ],
    "sg:phone":"+41 55 440 10 64",
    "sg:postcode":"8854",
    "sg:province":"Schwyz",
    "sg:tags":[
        "pflegeheime",
        "u",
        "alters"
    ],
    "wof:name":"Alters-& Pflegeheim",
    "wof:placetype":"venue"
},
  "geometry": {"coordinates":[8.90243,47.174999],"type":"Point"}
}