{
  "type": "Feature",
  "properties": {
    "iso:country":"CH",
    "sg:address":"Aariedstrasse",
    "sg:city":"Giswil",
    "sg:orig_category":"Bauschreinerei Herstellung von M\u00f6beln verschiedener Art",
    "sg:phone":"+41 41 676 70 10",
    "sg:postcode":"6074",
    "sg:province":"Obwalden",
    "wof:name":"M\u00f6bel Ab\u00e4cherli Ag",
    "wof:placetype":"venue"
},
  "geometry": {"coordinates":[8.182778,46.831253],"type":"Point"}
}