{
  "type": "Feature",
  "properties": {
    "iso:country":"CH",
    "sg:address":"Heuweg 7",
    "sg:city":"Oftringen",
    "sg:orig_category":"Unternehmensberatung",
    "sg:postcode":"4665",
    "sg:province":"Aargau",
    "wof:name":"W\u00fcsba Gmbh",
    "wof:placetype":"venue"
},
  "geometry": {"coordinates":[7.9161047935,47.3166389465],"type":"Point"}
}