{
  "type": "Feature",
  "properties": {
    "iso:country":"CH",
    "sg:address":"Dorfstrasse 14",
    "sg:city":"Aesch",
    "sg:orig_category":"Herstellung von sonstigen elektrischen Ausr\u00fcstungen Sonstiger spezialisierter Hoch U Tiefbau",
    "sg:phone":"+41 55 246 40 54",
    "sg:postcode":"8904",
    "sg:province":"Z\u00fcrich",
    "wof:name":"Egli & Massi Ag",
    "wof:placetype":"venue"
},
  "geometry": {"coordinates":[8.8602399826,47.2541809082],"type":"Point"}
}