{
  "type": "Feature",
  "properties": {
    "iso:country":"CH",
    "sg:address":"Le Montchalon",
    "sg:city":"Ch\u00e2teau-d'oex",
    "sg:orig_category":"G\u00fcterbef\u00f6rderung im Strassenverkehr",
    "sg:phone":"+41 79 230 22 69",
    "sg:postcode":"1837",
    "wof:name":"Robert Gander Transports",
    "wof:placetype":"venue"
},
  "geometry": {"coordinates":[4.5561590195,46.4010238647],"type":"Point"}
}