{
  "type": "Feature",
  "properties": {
    "iso:country":"CH",
    "sg:address":"Riva Paradiso 26",
    "sg:city":"Lugano",
    "sg:orig_category":"Handel mit Motorr\u00e4dern, Teilen U Zubeh\u00f6r Handelsvermittlung U Grosshandel mit Automobilen Instandhal",
    "sg:phone":"+41 91 985 11 70",
    "sg:postcode":"6900",
    "sg:province":"Ticino",
    "wof:name":"Cagiva Motor (suisse) Sa",
    "wof:placetype":"venue"
},
  "geometry": {"coordinates":[8.940448761,45.9968452454],"type":"Point"}
}