{
  "type": "Feature",
  "properties": {
    "iso:country":"CH",
    "sg:address":"Rietbergstrasse 26",
    "sg:city":"Goldach",
    "sg:classifiers":[
        {
            "category":"Professional",
            "subcategory":"Accounting & Tax Preparation",
            "type":"Services"
        }
    ],
    "sg:postcode":"9403",
    "sg:province":"St. Gallen",
    "sg:tags":[
        "u",
        "yachtbau",
        "boot"
    ],
    "wof:name":"Baumgartner Nicolas",
    "wof:placetype":"venue"
},
  "geometry": {"coordinates":[6.923261,46.393078],"type":"Point"}
}