{
  "type": "Feature",
  "properties": {
    "iso:country":"CH",
    "sg:address":"Im Weidgrund 8",
    "sg:city":"D\u00fcbendorf",
    "sg:orig_category":"Vereine Quartier",
    "sg:phone":"+41 18212382",
    "sg:postcode":"8600",
    "sg:province":"Z\u00fcrich",
    "wof:name":"Verein Wohnliches D\u00fcbendorf",
    "wof:placetype":"venue"
},
  "geometry": {"coordinates":[8.6316041946,47.3891143799],"type":"Point"}
}