{
  "type": "Feature",
  "properties": {
    "iso:country":"CH",
    "sg:address":"Grossmattstrasse 8 8964 Rudolfstetten. Postfach",
    "sg:city":"Rudolfstetten",
    "sg:orig_category":"Handels-H\u00e4user U Gesellschaften",
    "sg:postcode":"8964",
    "sg:province":"Aargau",
    "wof:name":"Castolin Eutectic International Sa",
    "wof:placetype":"venue"
},
  "geometry": {"coordinates":[6.5580701828,46.5100784302],"type":"Point"}
}