{
  "type": "Feature",
  "properties": {
    "iso:country":"CH",
    "sg:address":"Unterhof 7104 Versam. Postfach",
    "sg:city":"Versam",
    "sg:orig_category":"Allgemeiner Hoch U Tiefbau",
    "sg:postcode":"7104",
    "sg:province":"Graubunden",
    "wof:name":"Blockhaus Versam Ag Blockh\u00e4user, Holzh\u00e4user; Erstellung, Beratung",
    "wof:placetype":"venue"
},
  "geometry": {"coordinates":[9.3397,46.790611],"type":"Point"}
}