{
  "type": "Feature",
  "properties": {
    "iso:country":"CH",
    "sg:address":"Steinwichslenstrasse 22",
    "sg:city":"Niederteufen",
    "sg:orig_category":"Sonstiger Grosshandel",
    "sg:phone":"+41 71 333 35 50",
    "sg:postcode":"9052",
    "sg:province":"Appenzell Ausserrhoden",
    "wof:name":"Salma Gmbh",
    "wof:placetype":"venue"
},
  "geometry": {"coordinates":[9.3652000427,47.3894271851],"type":"Point"}
}