{
  "type": "Feature",
  "properties": {
    "iso:country":"CH",
    "sg:address":"Bann",
    "sg:city":"Steinhausen",
    "sg:orig_category":"Mit Sport verbundene T\u00e4tigkeiten Sonstige mit Sport verbundene T\u00e4tigkeiten",
    "sg:phone":"+41 41 741 59 59",
    "sg:postcode":"6312",
    "sg:province":"Zug",
    "wof:name":"Roland Straub Reitzentrum Bann",
    "wof:placetype":"venue"
},
  "geometry": {"coordinates":[8.4868392944,47.2068138123],"type":"Point"}
}