{
  "type": "Feature",
  "properties": {
    "iso:country":"CH",
    "sg:address":"Grubenstrasse 93",
    "sg:city":"Schaffhausen",
    "sg:orig_category":"Non-Classified Establishments",
    "sg:postcode":"8200",
    "sg:province":"Schaffhausen",
    "wof:name":"Tierpraxis Godenzi",
    "wof:placetype":"venue"
},
  "geometry": {"coordinates":[8.6483392715,47.7029724121],"type":"Point"}
}