{
  "type": "Feature",
  "properties": {
    "iso:country":"CH",
    "sg:address":"Rotfarb",
    "sg:city":"Uznach",
    "sg:orig_category":"Herstellung von Schreinerwaren ohne ausgepr\u00e4gten Schwerpunkt",
    "sg:phone":"+41 55 280 55 50",
    "sg:postcode":"8730",
    "sg:province":"St. Gallen",
    "wof:name":"Walter R\u00fcegg Holzbau Gewerbezentrum",
    "wof:placetype":"venue"
},
  "geometry": {"coordinates":[8.9852361679,47.2249984741],"type":"Point"}
}