{
  "type": "Feature",
  "properties": {
    "iso:country":"CH",
    "sg:address":"Zeughausgasse 9",
    "sg:city":"Zug",
    "sg:orig_category":"Unternehmensberatung",
    "sg:phone":"+41 41 710 53 53",
    "sg:postcode":"6300",
    "sg:province":"Zug",
    "wof:name":"Cbr Business Reframing Ltd",
    "wof:placetype":"venue"
},
  "geometry": {"coordinates":[8.5162611008,47.1669158936],"type":"Point"}
}