{
  "type": "Feature",
  "properties": {
    "iso:country":"CH",
    "sg:address":"8905",
    "sg:city":"Arni-islisberg",
    "sg:orig_category":"Sportvereine Sch\u00fctzen",
    "sg:postcode":"8905",
    "sg:province":"Aargau",
    "wof:name":"Sch\u00fctzengesellschaft",
    "wof:placetype":"venue"
},
  "geometry": {"coordinates":[8.4237298965,47.3199081421],"type":"Point"}
}