{
  "type": "Feature",
  "properties": {
    "iso:country":"CH",
    "sg:address":"B\u00e4lliz 67",
    "sg:city":"Thun",
    "sg:orig_category":"Architekturb\u00fcros",
    "sg:phone":"+41 33 222 07 77",
    "sg:postcode":"3600",
    "sg:province":"Bern",
    "wof:name":"Peter Anneler Aha Architektur Anneler Htl",
    "wof:placetype":"venue"
},
  "geometry": {"coordinates":[7.629737,46.757401],"type":"Point"}
}