{
  "type": "Feature",
  "properties": {
    "iso:country":"CH",
    "sg:address":"Rue Du Bourg 15",
    "sg:city":"Martigny",
    "sg:orig_category":"Detailhandel mit Waren verschiedener Art, Hauptrichtung Nahrungsmittel",
    "sg:phone":"+41 27 722 43 22",
    "sg:postcode":"1920",
    "sg:province":"Valais",
    "wof:name":"Vis-\u00e0-vis Alimentation Valrh\u00f4ne Sa",
    "wof:placetype":"venue"
},
  "geometry": {"coordinates":[7.0648818016,46.0908927917],"type":"Point"}
}