{
  "type": "Feature",
  "properties": {
    "iso:country":"CH",
    "sg:address":"7603",
    "sg:city":"Vicosoprano",
    "sg:classifiers":[
        {
            "category":"Education",
            "subcategory":"Vocational School",
            "type":"Public Place"
        }
    ],
    "sg:postcode":"7603",
    "sg:province":"Graubunden",
    "sg:tags":[
        "koch-",
        "haushaltschulen"
    ],
    "wof:name":"Scuola Di Economia Domestica",
    "wof:placetype":"venue"
},
  "geometry": {"coordinates":[9.6207332611,46.3508033752],"type":"Point"}
}