{
  "type": "Feature",
  "properties": {
    "iso:country":"CH",
    "sg:address":"Rue Peillonnex 29",
    "sg:city":"Ch\u00eane-bourg",
    "sg:orig_category":"Fleischverarbeitung",
    "sg:postcode":"1225",
    "sg:province":"Gen\u00e8ve",
    "wof:name":"I. Frangi Sa",
    "wof:placetype":"venue"
},
  "geometry": {"coordinates":[6.197163105,46.1950874329],"type":"Point"}
}