{
  "type": "Feature",
  "properties": {
    "iso:country":"CH",
    "sg:address":"Grand'rue 9 1162 St-prex. Postfach",
    "sg:city":"St-prex",
    "sg:orig_category":"Architektur U Ingenieurb\u00fcros Architekturb\u00fcros",
    "sg:phone":"+41 21 806 26 91",
    "sg:postcode":"1162",
    "sg:province":"Vaud",
    "wof:name":"Le Trait Architecture Et Conseils Sa",
    "wof:placetype":"venue"
},
  "geometry": {"coordinates":[6.460371,46.479099],"type":"Point"}
}