{
  "type": "Feature",
  "properties": {
    "iso:country":"CH",
    "sg:address":"Sandbuckstrasse 13",
    "sg:city":"Neerach",
    "sg:orig_category":"Unternehmensberatung",
    "sg:phone":"+41 31 829 14 58",
    "sg:postcode":"8173",
    "sg:province":"Z\u00fcrich",
    "wof:name":"Opti Consult Rolf Widmer Logistikberatung",
    "wof:placetype":"venue"
},
  "geometry": {"coordinates":[7.3613538742,46.9776687622],"type":"Point"}
}