{
  "type": "Feature",
  "properties": {
    "iso:country":"CH",
    "sg:address":"Napoleonstr. 9 3930 Visp. Postfach",
    "sg:city":"Visp",
    "sg:orig_category":"Architektur U Ingenieurb\u00fcros",
    "sg:postcode":"3930",
    "sg:province":"Valais",
    "wof:name":"Arw (arbeitsgemeinschaft F\u00fcr Raumplanung Und Wirtschaftsfragen) Furger & Aufdereggen, Planer Und Berater.",
    "wof:placetype":"venue"
},
  "geometry": {"coordinates":[7.884339,46.291412],"type":"Point"}
}