{
  "type": "Feature",
  "properties": {
    "iso:country":"CH",
    "sg:address":"Meierhofweg 20",
    "sg:city":"Pratteln",
    "sg:orig_category":"Malerei",
    "sg:phone":"+41 61 821 52 75",
    "sg:postcode":"4133",
    "sg:province":"Basel-Landschaft",
    "wof:name":"Fred Zulauf Malergesch\u00e4ft",
    "wof:placetype":"venue"
},
  "geometry": {"coordinates":[7.7013897896,47.518321991],"type":"Point"}
}