{
  "type": "Feature",
  "properties": {
    "iso:country":"CH",
    "sg:address":"Rue Du 23-juin 50",
    "sg:city":"Del\u00e9mont",
    "sg:orig_category":"Detailhandel mit Milcherzeugnissen U Eiern Verarbeitung von Milch",
    "sg:phone":"+41 32 422 14 86",
    "sg:postcode":"2800",
    "sg:province":"Jura",
    "wof:name":"Laiterie Centrale Del\u00e9mont",
    "wof:placetype":"venue"
},
  "geometry": {"coordinates":[7.3421440125,47.3645629883],"type":"Point"}
}