{
  "type": "Feature",
  "properties": {
    "iso:country":"CH",
    "sg:address":"Duboule Chemin Mo\u00efse- 43 1209 Gen\u00e8ve. Postfach",
    "sg:city":"Gen\u00e8ve",
    "sg:orig_category":"Softwareentwicklung U beratung",
    "sg:postcode":"1209",
    "sg:province":"Gen\u00e8ve",
    "wof:name":"Jn S\u00e0rl",
    "wof:placetype":"venue"
},
  "geometry": {"coordinates":[6.9182190895,46.6966667175],"type":"Point"}
}