{
  "type": "Feature",
  "properties": {
    "iso:country":"CH",
    "sg:address":"Staufergutstrasse 13",
    "sg:city":"Oftringen",
    "sg:orig_category":"Stukkateurgewerbe, Gipserei U Verputzerei",
    "sg:postcode":"4665",
    "sg:province":"Aargau",
    "wof:name":"Enzo Gipsergesch\u00e4ft Gmbh",
    "wof:placetype":"venue"
},
  "geometry": {"coordinates":[8.4359149933,47.0837173462],"type":"Point"}
}