{
  "type": "Feature",
  "properties": {
    "iso:country":"CH",
    "sg:address":"T\u00f6sstalstrasse 125",
    "sg:city":"Turbenthal",
    "sg:classifiers":[
        {
            "category":"Restaurant",
            "type":"Food & Drink"
        }
    ],
    "sg:phone":"+41 52 385 22 12",
    "sg:postcode":"8488",
    "sg:province":"Z\u00fcrich",
    "wof:name":"Restaurant Kreuzstrasse",
    "wof:placetype":"venue"
},
  "geometry": {"coordinates":[8.8475093842,47.4355049133],"type":"Point"}
}