{
  "type": "Feature",
  "properties": {
    "iso:country":"CH",
    "sg:address":"St\u00e4blistrasse 113",
    "sg:city":"Umiken",
    "sg:orig_category":"Herstellung von Elektromotoren, Generatoren U Transformatoren",
    "sg:phone":"+41 56 442 05 04",
    "sg:postcode":"5222",
    "sg:province":"Aargau",
    "wof:name":"Sch\u00f6ndorf Gmbh",
    "wof:placetype":"venue"
},
  "geometry": {"coordinates":[8.1881113052,47.4839706421],"type":"Point"}
}