{
  "type": "Feature",
  "properties": {
    "iso:country":"CH",
    "sg:address":"Sperrstrasse 2",
    "sg:city":"Basel",
    "sg:orig_category":"Sprachschulen \u00dcbersetzungsb\u00fcros",
    "sg:phone":"+41 61 681 53 44",
    "sg:postcode":"4057",
    "sg:province":"Basel-Stadt",
    "wof:name":"Elias Almarza",
    "wof:placetype":"venue"
},
  "geometry": {"coordinates":[7.5914502144,47.5643081665],"type":"Point"}
}