{
  "type": "Feature",
  "properties": {
    "iso:country":"CH",
    "sg:address":"Vorderdorf",
    "sg:city":"Sigriswil",
    "sg:orig_category":"Grosshandel mit Nahrungsmitteln, Getr\u00e4nken U Tabakwaren ohne ausgepr\u00e4gten Schwerpunkt",
    "sg:postcode":"3655",
    "sg:province":"Bern",
    "wof:name":"Margrit Tschan-weber",
    "wof:placetype":"venue"
},
  "geometry": {"coordinates":[7.734705925,46.7036437988],"type":"Point"}
}