{
  "type": "Feature",
  "properties": {
    "iso:country":"CH",
    "sg:address":"1695",
    "sg:city":"Rueyres-st-laurent",
    "sg:orig_category":"G\u00fcterbef\u00f6rderung im Strassenverkehr Sonstiger Fachdetailhandel mit Nahrungsmitteln, Getr\u00e4nken U Taba",
    "sg:phone":"+41 26 411 28 37",
    "sg:postcode":"1695",
    "sg:province":"Fribourg",
    "wof:name":"Jo\u00ebl Galster Transport De Lait",
    "wof:placetype":"venue"
},
  "geometry": {"coordinates":[7.033080101,46.715511322],"type":"Point"}
}