{
  "type": "Feature",
  "properties": {
    "iso:country":"CH",
    "sg:address":"Industriestrasse 7",
    "sg:city":"Kr\u00e4iligen",
    "sg:orig_category":"Gartenbau",
    "sg:phone":"+41 79 439 77 15",
    "sg:postcode":"3315",
    "sg:province":"Bern",
    "wof:name":"Felix Meili Pflanzencenter & Gartenbau",
    "wof:placetype":"venue"
},
  "geometry": {"coordinates":[7.5389471054,47.1312561035],"type":"Point"}
}