{
  "type": "Feature",
  "properties": {
    "iso:country":"CH",
    "sg:address":"Sternmattstrasse 19",
    "sg:city":"Luzern",
    "sg:orig_category":"\u00dcbersetzungsb\u00fcros",
    "sg:phone":"+41 41 360 60 79",
    "sg:postcode":"6005",
    "sg:province":"Luzern",
    "wof:name":"Niobe Federica Huser Uebersetzungen",
    "wof:placetype":"venue"
},
  "geometry": {"coordinates":[8.3099918365,47.0398674011],"type":"Point"}
}