{
  "type": "Feature",
  "properties": {
    "iso:country":"CH",
    "sg:address":"Rue Du Midi 8 1009 Pully Case Postale 56",
    "sg:city":"Pully",
    "sg:orig_category":"Elektroinstallation",
    "sg:phone":"+41 21 728 32 00",
    "sg:postcode":"1009",
    "sg:province":"Vaud",
    "wof:name":"Bally Pully Sa",
    "wof:placetype":"venue"
},
  "geometry": {"coordinates":[6.660243988,46.5094223022],"type":"Point"}
}