{
  "type": "Feature",
  "properties": {
    "iso:country":"CH",
    "sg:address":"Sennweidstrasse 35",
    "sg:city":"Steinhausen",
    "sg:orig_category":"Werbevermittlung",
    "sg:phone":"+41 79 279 32 79",
    "sg:postcode":"6312",
    "sg:province":"Zug",
    "wof:name":"Bruno F\u00e4h Werbeatelier",
    "wof:placetype":"venue"
},
  "geometry": {"coordinates":[8.4819154739,47.190246582],"type":"Point"}
}