{
  "type": "Feature",
  "properties": {
    "iso:country":"CH",
    "sg:address":"B\u00e4lliz 12",
    "sg:city":"Thun",
    "sg:orig_category":"Arztpraxen",
    "sg:phone":"+41 33 222 18 22",
    "sg:postcode":"3600",
    "sg:province":"Bern",
    "wof:name":"Pd Dr.med.konrad Michel Spezialarzt Fmh",
    "wof:placetype":"venue"
},
  "geometry": {"coordinates":[7.626171,46.759766],"type":"Point"}
}