{
  "type": "Feature",
  "properties": {
    "iso:country":"CH",
    "sg:address":"Grand-rue 3",
    "sg:city":"Payerne",
    "sg:orig_category":"Darlehenskassen U Raiffeisenbanken",
    "sg:phone":"+41 26 662 46 00",
    "sg:postcode":"1530",
    "sg:province":"Vaud",
    "wof:name":"Banque Raiffeisen De La Broye",
    "wof:placetype":"venue"
},
  "geometry": {"coordinates":[6.939315,46.821541],"type":"Point"}
}