{
  "type": "Feature",
  "properties": {
    "iso:country":"CH",
    "sg:address":"Glasson Rue Nicolas 5b",
    "sg:city":"Bulle",
    "sg:orig_category":"Interessenvertretungen",
    "sg:postcode":"1630",
    "sg:province":"Fribourg",
    "wof:name":"Parloca Fribourg, Fondation Pour La Location-participation",
    "wof:placetype":"venue"
},
  "geometry": {"coordinates":[7.0555691719,46.6174583435],"type":"Point"}
}