{
  "type": "Feature",
  "properties": {
    "iso:country":"CH",
    "sg:address":"Haberholzstrasse 16",
    "sg:city":"Niederhasli",
    "sg:orig_category":"Sonstige mit der Informatik verbundene T\u00e4tigkeiten",
    "sg:postcode":"8155",
    "sg:province":"Z\u00fcrich",
    "wof:name":"Stutz Cad-support Gmbh",
    "wof:placetype":"venue"
},
  "geometry": {"coordinates":[8.9413003922,47.2884101868],"type":"Point"}
}