{
  "type": "Feature",
  "properties": {
    "iso:country":"CH",
    "sg:address":"Rosswiesstrasse 27",
    "sg:city":"Bubikon",
    "sg:orig_category":"Pensionskassen",
    "sg:phone":"+41 55 253 42 20",
    "sg:postcode":"8608",
    "sg:province":"Z\u00fcrich",
    "wof:name":"Personalstiftung Der Dorma T\u00fcrautomatik",
    "wof:placetype":"venue"
},
  "geometry": {"coordinates":[8.8255386353,47.2704048157],"type":"Point"}
}