{
  "type": "Feature",
  "properties": {
    "iso:country":"CH",
    "sg:address":"Via Da Vegnas 7",
    "sg:city":"Rh\u00e4z\u00fcns",
    "sg:orig_category":"Forst\u00e4mter",
    "sg:phone":"+41 81 641 21 44",
    "sg:postcode":"7403",
    "sg:province":"Graubunden",
    "wof:name":"Revierforstamt",
    "wof:placetype":"venue"
},
  "geometry": {"coordinates":[9.3944511414,46.7977027893],"type":"Point"}
}