{
  "type": "Feature",
  "properties": {
    "iso:country":"CH",
    "sg:address":"R\u00fctschigasse 3",
    "sg:city":"Otelfingen",
    "sg:orig_category":"Dachdeckerei Zimmerei, Dachdeckerei, Bauspenglerei U Abdichtung",
    "sg:phone":"+41 18451500",
    "sg:postcode":"8112",
    "sg:province":"Z\u00fcrich",
    "wof:name":"Rechsteiner Bauspenglerei Bedachungen Und Renovationen",
    "wof:placetype":"venue"
},
  "geometry": {"coordinates":[8.387277,47.462219],"type":"Point"}
}