{
  "type": "Feature",
  "properties": {
    "iso:country":"CH",
    "sg:address":"Alte Lengnauerstrasse 97",
    "sg:city":"Freienwil",
    "sg:orig_category":"Reiseb\u00fcros U Reiseveranstalter",
    "sg:phone":"+41 56 203 79 39",
    "sg:postcode":"5423",
    "sg:province":"Aargau",
    "wof:name":"S.t.o. Swiss & Surinam Travel Organisation Langer Claudia M.",
    "wof:placetype":"venue"
},
  "geometry": {"coordinates":[8.3292655945,47.5054740906],"type":"Point"}
}