{
  "type": "Feature",
  "properties": {
    "iso:country":"CH",
    "sg:address":"Neugasse 89",
    "sg:city":"Z\u00fcrich",
    "sg:orig_category":"Grafikateliers, Design",
    "sg:phone":"+41 19290516",
    "sg:postcode":"8005",
    "sg:province":"Z\u00fcrich",
    "wof:name":"Isabelle Linsi Grafik",
    "wof:placetype":"venue"
},
  "geometry": {"coordinates":[8.7199325562,47.2706565857],"type":"Point"}
}