{
  "type": "Feature",
  "properties": {
    "iso:country":"CH",
    "sg:address":"Wettingerstrasse 17 5400 Baden. Postfach",
    "sg:city":"Baden",
    "sg:orig_category":"Non-Classified Establishments",
    "sg:postcode":"5400",
    "sg:province":"Aargau",
    "wof:name":"Internet Explorer Gmbh Werbe, Marketing- U. Verkaufsf\u00f6rderprojekte Via Internet; Beratung, Planung, Erstellung",
    "wof:placetype":"venue"
},
  "geometry": {"coordinates":[8.3121376038,47.4721336365],"type":"Point"}
}