{
  "type": "Feature",
  "properties": {
    "iso:country":"CH",
    "sg:address":"Solothurnstrasse 120",
    "sg:city":"Grenchen",
    "sg:orig_category":"Detailhandel mit Schuhen Detailhandel mit Schuhen U Lederwaren",
    "sg:phone":"+41 21 636 45 36",
    "sg:postcode":"2540",
    "sg:province":"Solothurn",
    "wof:name":"Hac Sa Halle Aux Chaussures",
    "wof:placetype":"venue"
},
  "geometry": {"coordinates":[7.4059419632,47.1938972473],"type":"Point"}
}