{
  "type": "Feature",
  "properties": {
    "iso:country":"CH",
    "sg:address":"R\u00f6merhalde 3",
    "sg:city":"Zofingen",
    "sg:orig_category":"Sanit\u00e4r, Heizungs U L\u00fcftungsinstallation Sanit\u00e4rinstallation",
    "sg:phone":"+41 79 406 99 80",
    "sg:postcode":"4800",
    "sg:province":"Aargau",
    "wof:name":"M\u00fcller Und Mathys Ag",
    "wof:placetype":"venue"
},
  "geometry": {"coordinates":[7.9506459236,47.2812232971],"type":"Point"}
}