{
  "type": "Feature",
  "properties": {
    "iso:country":"CH",
    "sg:address":"Grand-rue 56",
    "sg:city":"Ch\u00e9zard-st-martin",
    "sg:orig_category":"Gemeindeverwaltungen",
    "sg:phone":"+41 32 853 22 82",
    "sg:postcode":"2054",
    "sg:province":"Neuch\u00e2tel",
    "wof:name":"Administration Communale De Ch\u00e9zard-saint-martin",
    "wof:placetype":"venue"
},
  "geometry": {"coordinates":[6.9275932312,47.0645675659],"type":"Point"}
}