{
  "type": "Feature",
  "properties": {
    "iso:country":"CH",
    "sg:address":"Via Leoncavallo 14",
    "sg:city":"Brissago",
    "sg:orig_category":"Detailhandel mit Brot, Back U S\u00fcsswaren",
    "sg:phone":"+41 79 621 78 48",
    "sg:postcode":"6614",
    "sg:province":"Ticino",
    "wof:name":"El Prestin De Brisag Sa",
    "wof:placetype":"venue"
},
  "geometry": {"coordinates":[8.711123,46.119987],"type":"Point"}
}