{
  "type": "Feature",
  "properties": {
    "iso:country":"CH",
    "sg:address":"Chemin Du Canal 5",
    "sg:city":"Nyon",
    "sg:orig_category":"Handelsvermittlung U Grosshandel",
    "sg:phone":"+41 55 260 18 70",
    "sg:postcode":"1260",
    "sg:province":"Vaud",
    "wof:name":"Fsg Fischer Gmbh",
    "wof:placetype":"venue"
},
  "geometry": {"coordinates":[8.8546886444,47.2514572144],"type":"Point"}
}