{
  "type": "Feature",
  "properties": {
    "iso:country":"CH",
    "sg:address":"Hindelbankstrasse 33",
    "sg:city":"Hettiswil",
    "sg:classifiers":[
        {
            "category":"Restaurant",
            "type":"Food & Drink"
        }
    ],
    "sg:phone":"+41 34 411 11 95",
    "sg:postcode":"3325",
    "sg:province":"Bern",
    "wof:name":"Restaurant Kreuz",
    "wof:placetype":"venue"
},
  "geometry": {"coordinates":[7.5490021706,47.0312728882],"type":"Point"}
}