{
  "type": "Feature",
  "properties": {
    "addr:full":"Nordring 36 Bern Bern 3013",
    "addr:housenumber":"36",
    "addr:postcode":"3013",
    "addr:street":"Nordring",
    "iso:country":"CH",
    "sg:address":"Nordring 36",
    "sg:city":"Bern",
    "sg:orig_category":"Autogaragen",
    "sg:phone":"+41 31 333 16 66",
    "sg:postcode":"3013",
    "sg:province":"Bern",
    "wof:name":"Auto Zumstein Garage",
    "wof:placetype":"venue"
},
  "geometry": {"coordinates":[7.44713,46.95789],"type":"Point"}
}