{
  "type": "Feature",
  "properties": {
    "iso:country":"CH",
    "sg:address":"Romanshornerstrasse 253",
    "sg:city":"Hefenhofen",
    "sg:orig_category":"Verarbeitung von Milch Verwertung von Milch",
    "sg:phone":"+41 71 411 72 15",
    "sg:postcode":"8580",
    "sg:province":"Thurgau",
    "wof:name":"K\u00e4serei Studer Ag",
    "wof:placetype":"venue"
},
  "geometry": {"coordinates":[9.3166303635,47.5527191162],"type":"Point"}
}