{
  "type": "Feature",
  "properties": {
    "iso:country":"CH",
    "sg:address":"Dorf",
    "sg:city":"Plaffeien",
    "sg:orig_category":"Detailhandel mit Fleisch U Fleischwaren",
    "sg:postcode":"1716",
    "sg:province":"Fribourg",
    "wof:name":"Riedo-junge F.",
    "wof:placetype":"venue"
},
  "geometry": {"coordinates":[7.2852349281,46.7418861389],"type":"Point"}
}