{
  "type": "Feature",
  "properties": {
    "iso:country":"CH",
    "sg:address":"Haldenstrasse 45",
    "sg:city":"Biel/bienne",
    "sg:orig_category":"Herstellung von Werkzeugmaschinen",
    "sg:phone":"+41 32 341 23 08",
    "sg:postcode":"2500",
    "sg:province":"Bern",
    "wof:name":"Profila Gmbh",
    "wof:placetype":"venue"
},
  "geometry": {"coordinates":[7.2591810226,47.1502342224],"type":"Point"}
}