{
  "type": "Feature",
  "properties": {
    "iso:country":"CH",
    "sg:address":"Huttwilstrasse 33",
    "sg:city":"Lotzwil",
    "sg:orig_category":"Detailhandel mit Uhren U Schmuck Reparatur von Uhren U Schmuck",
    "sg:phone":"+41 62 923 25 67",
    "sg:postcode":"4932",
    "sg:province":"Bern",
    "wof:name":"Markus Ruch Uhren-bijouterie",
    "wof:placetype":"venue"
},
  "geometry": {"coordinates":[7.7922911644,47.1886787415],"type":"Point"}
}