{
  "type": "Feature",
  "properties": {
    "iso:country":"CH",
    "sg:address":"Bolgengasse 3770 Zweisimmen. Postfach 250",
    "sg:city":"Zweisimmen",
    "sg:orig_category":"Vermittlung von Immobilien Verwaltung von Immobilien",
    "sg:phone":"+41 33 722 11 21",
    "sg:postcode":"3770",
    "sg:province":"Bern",
    "wof:name":"Simbau Ag",
    "wof:placetype":"venue"
},
  "geometry": {"coordinates":[7.3717370033,46.5559120178],"type":"Point"}
}