{
  "type": "Feature",
  "properties": {
    "iso:country":"CH",
    "sg:address":"Kreuzstrasse 6370 Stans. Postfach 1231",
    "sg:city":"Stans",
    "sg:orig_category":"Verwaltung der Strafvollzuganstalten Wohnheime",
    "sg:phone":"+41 41 618 48 48",
    "sg:postcode":"6371",
    "sg:province":"Nidwalden",
    "wof:name":"Gef\u00e4ngnis Stans",
    "wof:placetype":"venue"
},
  "geometry": {"coordinates":[8.3862352371,46.9652786255],"type":"Point"}
}