{
  "type": "Feature",
  "properties": {
    "iso:country":"CH",
    "sg:address":"Grand Rue 70",
    "sg:city":"Montreux",
    "sg:orig_category":"Unclassifiable Establishments",
    "sg:postcode":"1820",
    "sg:province":"Vaud",
    "wof:name":"J.y. Lambert, Consultant",
    "wof:placetype":"venue"
},
  "geometry": {"coordinates":[6.9095492363,46.4358482361],"type":"Point"}
}