{
  "type": "Feature",
  "properties": {
    "iso:country":"CH",
    "sg:address":"Hauptstrasse 46 7472 Surava. Postfach",
    "sg:city":"Surava",
    "sg:orig_category":"Herstellung von Dauerbackwaren",
    "sg:phone":"+41 81 681 11 80",
    "sg:postcode":"7472",
    "sg:province":"Graubunden",
    "wof:name":"Zwieback Laim Ag",
    "wof:placetype":"venue"
},
  "geometry": {"coordinates":[9.6153678894,46.6665725708],"type":"Point"}
}