{
  "type": "Feature",
  "properties": {
    "iso:country":"CH",
    "sg:address":"Via Pignora",
    "sg:city":"Novazzano",
    "sg:orig_category":"Grosshandel mit Nahrungsmitteln, Getr\u00e4nken U Tabakwaren ohne ausgepr\u00e4gten Schwerpunkt Tankstellen",
    "sg:phone":"+41 91 647 16 48",
    "sg:postcode":"6883",
    "sg:province":"Ticino",
    "wof:name":"Marazzi Franca.",
    "wof:placetype":"venue"
},
  "geometry": {"coordinates":[8.9622793198,45.8409843445],"type":"Point"}
}