{
  "type": "Feature",
  "properties": {
    "iso:country":"CH",
    "sg:address":"6314 Unter\u00e4geri. Postfach 555",
    "sg:city":"Unter\u00e4geri",
    "sg:orig_category":"Sportvereine Unihockey",
    "sg:postcode":"6314",
    "sg:province":"Zug",
    "wof:name":"Uhc Zuger Highlands",
    "wof:placetype":"venue"
},
  "geometry": {"coordinates":[8.5838346481,47.1374053955],"type":"Point"}
}