{
  "type": "Feature",
  "properties": {
    "iso:country":"CH",
    "sg:address":"Route Du Pont-butin 12",
    "sg:city":"Petit-lancy",
    "sg:classifiers":[
        {
            "category":"Restaurant",
            "type":"Food & Drink"
        }
    ],
    "sg:phone":"+41 21 903 39 39",
    "sg:postcode":"1213",
    "sg:province":"Gen\u00e8ve",
    "wof:name":"Caf\u00e9-restaurant Le Raisin",
    "wof:placetype":"venue"
},
  "geometry": {"coordinates":[6.7559499741,46.5768814087],"type":"Point"}
}