{
  "type": "Feature",
  "properties": {
    "iso:country":"CH",
    "sg:address":"Avenue Alexandre Vinet 17",
    "sg:city":"Clarens",
    "sg:orig_category":"Drogerien Sonstiger Fachdetailhandel mit Nahrungsmitteln, Getr\u00e4nken U Tabak in Verkaufsr\u00e4umen",
    "sg:phone":"+41 21 964 10 31",
    "sg:postcode":"1815",
    "sg:province":"Vaud",
    "wof:name":"Sun Store Sa",
    "wof:placetype":"venue"
},
  "geometry": {"coordinates":[6.8930578232,46.44140625],"type":"Point"}
}