{
  "type": "Feature",
  "properties": {
    "addr:full":"8752 N\u00e4fels Glarus 8752",
    "addr:housenumber":"8752",
    "addr:postcode":"8752",
    "addr:street":"Naefels Glarus",
    "iso:country":"CH",
    "sg:address":"8752",
    "sg:city":"N\u00e4fels",
    "sg:orig_category":"Detailhandel mit Brot, Back U S\u00fcsswaren",
    "sg:postcode":"8752",
    "sg:province":"Glarus",
    "wof:name":"M\u00fcller-romer, A.",
    "wof:placetype":"venue"
},
  "geometry": {"coordinates":[9.062575,47.099964],"type":"Point"}
}