{
  "type": "Feature",
  "properties": {
    "iso:country":"CH",
    "sg:address":"Meichten",
    "sg:city":"Altb\u00fcron",
    "sg:orig_category":"G\u00fcterbef\u00f6rderung im Strassenverkehr",
    "sg:phone":"+41 79 442 16 28",
    "sg:postcode":"6147",
    "sg:province":"Luzern",
    "wof:name":"Knupp Transport Ag",
    "wof:placetype":"venue"
},
  "geometry": {"coordinates":[7.8829421997,47.182258606],"type":"Point"}
}