{
  "type": "Feature",
  "properties": {
    "iso:country":"CH",
    "sg:address":"Schaffhauserstrasse 24",
    "sg:city":"Neuhausen",
    "sg:orig_category":"Studenten Organisationen",
    "sg:phone":"+41 32 725 85 84",
    "sg:postcode":"8212",
    "sg:province":"Schaffhausen",
    "wof:name":"Industria Neocomensis C/o Ecole Sup.de Commerce",
    "wof:placetype":"venue"
},
  "geometry": {"coordinates":[6.9392580986,46.9934005737],"type":"Point"}
}