{
  "type": "Feature",
  "properties": {
    "iso:country":"CH",
    "sg:address":"L\u00e4gerenstrasse 19",
    "sg:city":"Schleinikon",
    "sg:orig_category":"Detailhandel mit Getr\u00e4nken G\u00fcterbef\u00f6rderung im Strassenverkehr",
    "sg:phone":"+41 18560429",
    "sg:postcode":"8165",
    "sg:province":"Z\u00fcrich",
    "wof:name":"Andreas Meister Transporte & Weinhandel",
    "wof:placetype":"venue"
},
  "geometry": {"coordinates":[8.3918008804,47.4966621399],"type":"Point"}
}