{
  "type": "Feature",
  "properties": {
    "iso:country":"CH",
    "sg:address":"Via Camana",
    "sg:city":"Cadro",
    "sg:orig_category":"Mechanische Werkst\u00e4tten",
    "sg:phone":"+41 91 943 40 60",
    "sg:postcode":"6965",
    "sg:province":"Ticino",
    "wof:name":"Angelo Polli Officina Meccanica",
    "wof:placetype":"venue"
},
  "geometry": {"coordinates":[8.9841995239,46.0451660156],"type":"Point"}
}