{
  "type": "Feature",
  "properties": {
    "iso:country":"CH",
    "sg:address":"Neudorf 12",
    "sg:city":"Oberb\u00fcren",
    "sg:orig_category":"Allgemeiner Gartenbau",
    "sg:phone":"+41 71 385 64 55",
    "sg:postcode":"9245",
    "sg:province":"St. Gallen",
    "wof:name":"Maurer Ag, Gartenbau Und Baumschulen",
    "wof:placetype":"venue"
},
  "geometry": {"coordinates":[9.274096,47.413376],"type":"Point"}
}