{
  "type": "Feature",
  "properties": {
    "iso:country":"CH",
    "sg:address":"Goethestrasse 20 8000 Z\u00fcrich. Postfach",
    "sg:city":"Z\u00fcrich",
    "sg:orig_category":"Herstellung von medizinischen U chirurgischen Ger\u00e4ten sowie orthop\u00e4dischen Vorrichtungen",
    "sg:postcode":"8001",
    "sg:province":"Z\u00fcrich",
    "wof:name":"Liquid Spirit Baumann",
    "wof:placetype":"venue"
},
  "geometry": {"coordinates":[9.4759025574,47.1664772034],"type":"Point"}
}