{
  "type": "Feature",
  "properties": {
    "iso:country":"CH",
    "sg:address":"Furkastrasse 25 3900 Brig. Postfach 709",
    "sg:city":"Brig",
    "sg:orig_category":"Unternehmensberatung Wirtschaftspr\u00fcfung, Steuerberatung U Treuhand",
    "sg:phone":"+41 27 923 07 07",
    "sg:postcode":"3900",
    "sg:province":"Valais",
    "wof:name":"Widar Treuhand Ag",
    "wof:placetype":"venue"
},
  "geometry": {"coordinates":[7.9854960442,46.3182907104],"type":"Point"}
}