{
  "type": "Feature",
  "properties": {
    "iso:country":"CH",
    "sg:address":"Rue De La Cit\u00e9 3",
    "sg:city":"Gen\u00e8ve",
    "sg:classifiers":[
        {
            "category":"Restaurant",
            "type":"Food & Drink"
        }
    ],
    "sg:phone":"+41 22 818 00 84",
    "sg:postcode":"1204",
    "sg:province":"Gen\u00e8ve",
    "wof:name":"Caf\u00e9 Le P'tit Cano",
    "wof:placetype":"venue"
},
  "geometry": {"coordinates":[6.1438970566,46.2036972046],"type":"Point"}
}