{
  "type": "Feature",
  "properties": {
    "iso:country":"CH",
    "sg:address":"Langgr\u00fctstrasse 37",
    "sg:city":"Z\u00fcrich",
    "sg:orig_category":"Vereine Harmonika and Akkordeon",
    "sg:postcode":"8047",
    "sg:province":"Z\u00fcrich",
    "wof:name":"Harmonie Club Stadt-z\u00fcrich",
    "wof:placetype":"venue"
},
  "geometry": {"coordinates":[8.5008192062,47.3729400635],"type":"Point"}
}