{
  "type": "Feature",
  "properties": {
    "iso:country":"CH",
    "sg:address":"Giacomettistrasse 25a",
    "sg:city":"Bern",
    "sg:orig_category":"Zahntechnische Laboratorien",
    "sg:phone":"+41 31 351 04 61",
    "sg:postcode":"3006",
    "sg:province":"Bern",
    "wof:name":"Gemo Pro-rep Service Gmbh Zahnprothesen-reparaturen",
    "wof:placetype":"venue"
},
  "geometry": {"coordinates":[7.4729437828,46.9460067749],"type":"Point"}
}