{
  "type": "Feature",
  "properties": {
    "iso:country":"CH",
    "sg:address":"1524",
    "sg:city":"Marnand",
    "sg:orig_category":"Stukkateurgewerbe, Gipserei U Verputzerei",
    "sg:postcode":"1524",
    "sg:province":"Vaud",
    "wof:name":"Jomini R.",
    "wof:placetype":"venue"
},
  "geometry": {"coordinates":[6.9024100304,46.762840271],"type":"Point"}
}