{
  "type": "Feature",
  "properties": {
    "iso:country":"CH",
    "sg:address":"Rue Saint-paul 11",
    "sg:city":"Fribourg",
    "sg:orig_category":"Detailhandel mit Tabakwaren",
    "sg:phone":"+41 26 322 40 26",
    "sg:postcode":"1700",
    "sg:province":"Fribourg",
    "wof:name":"Marie-ang\u00e8le Savary Tabacs",
    "wof:placetype":"venue"
},
  "geometry": {"coordinates":[7.1515359879,46.7991371155],"type":"Point"}
}