{
  "type": "Feature",
  "properties": {
    "iso:country":"CH",
    "sg:address":"Feldbergstrasse 67",
    "sg:city":"Basel",
    "sg:orig_category":"Fachdetailhandel mit pharmazeutischen Produkten",
    "sg:phone":"+41 61 692 40 70",
    "sg:postcode":"4057",
    "sg:province":"Basel-Stadt",
    "wof:name":"Horburg-apotheke, Leo Freyer",
    "wof:placetype":"venue"
},
  "geometry": {"coordinates":[7.5922632217,47.5665664673],"type":"Point"}
}