{
  "type": "Feature",
  "properties": {
    "iso:country":"CH",
    "sg:address":"Engelgasse 83 4052 Basel. Postfach",
    "sg:city":"Basel",
    "sg:orig_category":"Herstellung von Duft U K\u00f6rperpflegemitteln",
    "sg:phone":"+41 14929358",
    "sg:postcode":"4051",
    "sg:province":"Basel-Stadt",
    "wof:name":"Christine Fausch P\u00e9dicure",
    "wof:placetype":"venue"
},
  "geometry": {"coordinates":[8.4568185806,47.3730697632],"type":"Point"}
}