{
  "type": "Feature",
  "properties": {
    "iso:country":"CH",
    "sg:address":"Schaffhauserstrasse 361",
    "sg:city":"Z\u00fcrich",
    "sg:orig_category":"Reiseb\u00fcros",
    "sg:phone":"+41 13114466",
    "sg:postcode":"8050",
    "sg:province":"Z\u00fcrich",
    "wof:name":"Wasteels Reisen Ag",
    "wof:placetype":"venue"
},
  "geometry": {"coordinates":[8.5464477539,47.4108581543],"type":"Point"}
}