{
  "type": "Feature",
  "properties": {
    "iso:country":"CH",
    "sg:address":"Mallieu Chemin De 13",
    "sg:city":"Pully",
    "sg:orig_category":"Erwachsenenbildung U Unterricht",
    "sg:phone":"+41 21 729 63 65",
    "sg:postcode":"1009",
    "sg:province":"Vaud",
    "wof:name":"Cadig, H\u00fcrlimann Boris",
    "wof:placetype":"venue"
},
  "geometry": {"coordinates":[6.6598000526,46.5102577209],"type":"Point"}
}