{
  "type": "Feature",
  "properties": {
    "iso:country":"CH",
    "sg:address":"Gaswerkstrasse 66 D 4900 Langenthal. Postfach",
    "sg:city":"Langenthal",
    "sg:orig_category":"Herstellung von Konstruktionsteilen, Fertigbauteilen U Ausbauelementen aus Holz",
    "sg:postcode":"4900",
    "sg:province":"Bern",
    "wof:name":"Nicolier Fran\u00e7ois",
    "wof:placetype":"venue"
},
  "geometry": {"coordinates":[7.1587119102,46.3500404358],"type":"Point"}
}