{
  "type": "Feature",
  "properties": {
    "iso:country":"CH",
    "sg:address":"7545",
    "sg:city":"Guarda",
    "sg:orig_category":"Vereine Gesang",
    "sg:postcode":"7545",
    "sg:province":"Graubunden",
    "wof:name":"Gemischter Chor Guarda",
    "wof:placetype":"venue"
},
  "geometry": {"coordinates":[10.1505498886,46.7753143311],"type":"Point"}
}