{
  "type": "Feature",
  "properties": {
    "iso:country":"CH",
    "sg:address":"Grotzenm\u00fchlestrasse 8840 Einsiedeln. Postfach 124",
    "sg:city":"Einsiedeln",
    "sg:orig_category":"Siebdruck",
    "sg:phone":"+41 55 412 33 77",
    "sg:postcode":"8840",
    "sg:province":"Schwyz",
    "wof:name":"Erich Inderfurth Siebdruck",
    "wof:placetype":"venue"
},
  "geometry": {"coordinates":[8.7383642197,47.1256904602],"type":"Point"}
}