{
  "type": "Feature",
  "properties": {
    "iso:country":"CH",
    "sg:address":"Via Al Ponte 1/3",
    "sg:city":"Lugano",
    "sg:orig_category":"Einzelhandel mit Automobilen Handel mit Automobilen",
    "sg:phone":"+41 91 968 25 27",
    "sg:postcode":"6900",
    "sg:province":"Ticino",
    "wof:name":"Autobesso Sagl",
    "wof:placetype":"venue"
},
  "geometry": {"coordinates":[8.9409408569,46.00806427],"type":"Point"}
}