{
  "type": "Feature",
  "properties": {
    "iso:country":"CH",
    "sg:address":"Littisbach",
    "sg:city":"Boltigen",
    "sg:orig_category":"Verwertung von Milch",
    "sg:postcode":"3766",
    "sg:province":"Bern",
    "wof:name":"Milchverwertungsgenossenschaft Weissenbach-eschi",
    "wof:placetype":"venue"
},
  "geometry": {"coordinates":[7.3731198311,46.5949897766],"type":"Point"}
}