{
  "type": "Feature",
  "properties": {
    "iso:country":"CH",
    "sg:address":"Kl\u00f6sterligasse 2",
    "sg:city":"Zofingen",
    "sg:orig_category":"Advokaturb\u00fcros Notariate",
    "sg:phone":"+41 62 751 84 09",
    "sg:postcode":"4800",
    "sg:province":"Aargau",
    "wof:name":"Peter Clavadetscher Advokatur-& Notariatsb\u00fcro",
    "wof:placetype":"venue"
},
  "geometry": {"coordinates":[7.94754,47.287781],"type":"Point"}
}