{
  "type": "Feature",
  "properties": {
    "iso:country":"CH",
    "sg:address":"Breitenweg 5",
    "sg:city":"Thun",
    "sg:orig_category":"Fussreflexzonenmassage P\u00e9dicure",
    "sg:phone":"+41 33 335 51 02",
    "sg:postcode":"3604",
    "sg:province":"Bern",
    "wof:name":"Margrit Brenzikofer",
    "wof:placetype":"venue"
},
  "geometry": {"coordinates":[7.6261258125,46.7344665527],"type":"Point"}
}