{
  "type": "Feature",
  "properties": {
    "iso:country":"CH",
    "sg:address":"Im Gr\u00fcnen Hof 14",
    "sg:city":"Kreuzlingen",
    "sg:orig_category":"Handel mit Automobilen",
    "sg:phone":"+41 79 696 32 88",
    "sg:postcode":"8280",
    "sg:province":"Thurgau",
    "wof:name":"Seiler Werner Ag",
    "wof:placetype":"venue"
},
  "geometry": {"coordinates":[9.1692237854,47.6472549438],"type":"Point"}
}