{
  "type": "Feature",
  "properties": {
    "iso:country":"CH",
    "sg:address":"Deitingenstrasse 4",
    "sg:city":"Subingen",
    "sg:orig_category":"Detailhandel mit Getr\u00e4nken",
    "sg:postcode":"4553",
    "sg:province":"Solothurn",
    "wof:name":"Tannaretto - Tanner`s Schnaps-paradies",
    "wof:placetype":"venue"
},
  "geometry": {"coordinates":[7.6153240204,47.1959648132],"type":"Point"}
}