{
  "type": "Feature",
  "properties": {
    "iso:country":"CH",
    "sg:address":"Route De Monblesson 17",
    "sg:city":"Epalinges",
    "sg:orig_category":"Herstellung von sonstigen elektrischen Ausr\u00fcstungen",
    "sg:phone":"+41 21 784 05 96",
    "sg:postcode":"1066",
    "sg:province":"Vaud",
    "wof:name":"Moreillon Pierre A.",
    "wof:placetype":"venue"
},
  "geometry": {"coordinates":[6.671476841,46.5444602966],"type":"Point"}
}