{
  "type": "Feature",
  "properties": {
    "iso:country":"CH",
    "sg:address":"Route De Denges 28 Bt A",
    "sg:city":"Lonay",
    "sg:orig_category":"RESTAURANTS: TEA-ROOMS",
    "sg:postcode":"1027",
    "sg:province":"Vaud",
    "wof:name":"Menzar Et Cie",
    "wof:placetype":"venue"
},
  "geometry": {"coordinates":[6.8996601105,47.0372200012],"type":"Point"}
}