{
  "type": "Feature",
  "properties": {
    "addr:full":"Rue Des Gorges 4 2738 Court. Postfach Court Bern 2738",
    "addr:housenumber":"4",
    "addr:postcode":"2738 court.;2738",
    "addr:street":"Rue Des Gorges;Postfach Court",
    "iso:country":"CH",
    "sg:address":"Rue Des Gorges 4 2738 Court. Postfach",
    "sg:city":"Court",
    "sg:orig_category":"Allgemeiner Hoch U Tiefbau Bauschreinerei",
    "sg:phone":"+41 32 497 00 17",
    "sg:postcode":"2738",
    "sg:province":"Bern",
    "wof:name":"Topiscine S\u00e0rl Entreprise G\u00e9n\u00e9rale De Construction, Notamm. R\u00e9novation B\u00e2timents Et Installation De Piscines Etc",
    "wof:placetype":"venue"
},
  "geometry": {"coordinates":[7.341513,47.240871],"type":"Point"}
}