{
  "type": "Feature",
  "properties": {
    "iso:country":"CH",
    "sg:address":"Gibelinstrasse 25 4500 Solothurn. Postfach",
    "sg:city":"Solothurn",
    "sg:orig_category":"Interessenvertretungen",
    "sg:phone":"+41 32 622 69 34",
    "sg:postcode":"4503",
    "sg:province":"Solothurn",
    "wof:name":"Svk Schweizerischer Verband F\u00fcr Gemeinschaftsaufgaben Der Krankenversicherer",
    "wof:placetype":"venue"
},
  "geometry": {"coordinates":[7.5257458687,47.2085266113],"type":"Point"}
}