{
  "type": "Feature",
  "properties": {
    "iso:country":"CH",
    "sg:address":"Milit\u00e4rstrasse 85 8004 Z\u00fcrich. Postfach",
    "sg:city":"Z\u00fcrich",
    "sg:orig_category":"Reiseb\u00fcros U Reiseveranstalter",
    "sg:phone":"+41 12421615",
    "sg:postcode":"8021",
    "sg:province":"Z\u00fcrich",
    "wof:name":"Voyages Wasteels Sa Zweigniederlassung Z\u00fcrich Intern. Reisen, Transporte Usw",
    "wof:placetype":"venue"
},
  "geometry": {"coordinates":[8.5298566818,47.378742218],"type":"Point"}
}