{
  "type": "Feature",
  "properties": {
    "iso:country":"CH",
    "sg:address":"Dorfstrasse 48",
    "sg:city":"Z\u00fcrich",
    "sg:orig_category":"Unclassifiable Establishments",
    "sg:postcode":"8037",
    "sg:province":"Z\u00fcrich",
    "wof:name":"F\u00e4ssler Dominik, Transportunternehmungen",
    "wof:placetype":"venue"
},
  "geometry": {"coordinates":[8.8322639465,47.073425293],"type":"Point"}
}