{
  "type": "Feature",
  "properties": {
    "iso:country":"CH",
    "sg:address":"8805 Richterswil. Postfach 6264",
    "sg:city":"Richterswil",
    "sg:orig_category":"Sportvereine Ballsport Fussball",
    "sg:phone":"+41 17842430",
    "sg:postcode":"8805",
    "sg:province":"Z\u00fcrich",
    "wof:name":"Fc Richterswil",
    "wof:placetype":"venue"
},
  "geometry": {"coordinates":[8.7051200867,47.2075004578],"type":"Point"}
}