{
  "type": "Feature",
  "properties": {
    "iso:country":"CH",
    "sg:address":"Schellenmattweg 5",
    "sg:city":"Kriens",
    "sg:orig_category":"Mechanik",
    "sg:phone":"+41 61 961 80 44",
    "sg:postcode":"6010",
    "sg:province":"Luzern",
    "wof:name":"Kurt Hans",
    "wof:placetype":"venue"
},
  "geometry": {"coordinates":[7.7512731552,47.3939476013],"type":"Point"}
}