{
  "type": "Feature",
  "properties": {
    "iso:country":"CH",
    "sg:address":"Heuweg 25",
    "sg:city":"Oftringen",
    "sg:orig_category":"Fahrschulen, Flugschulen",
    "sg:phone":"+41 79 648 46 24",
    "sg:postcode":"4665",
    "sg:province":"Aargau",
    "wof:name":"Giuseppe Pizzolante Autofahrschule",
    "wof:placetype":"venue"
},
  "geometry": {"coordinates":[7.9161138535,47.3169364929],"type":"Point"}
}