{
  "type": "Feature",
  "properties": {
    "iso:country":"CH",
    "sg:address":"Schulstrasse 29",
    "sg:city":"Frick",
    "sg:orig_category":"Elektroinstallation",
    "sg:phone":"+41 32 963 11 77",
    "sg:postcode":"5070",
    "sg:province":"Aargau",
    "wof:name":"Jost Olivier",
    "wof:placetype":"venue"
},
  "geometry": {"coordinates":[6.9292798042,47.1269111633],"type":"Point"}
}