{
  "type": "Feature",
  "properties": {
    "iso:country":"CH",
    "sg:address":"Gemeindestrasse 51",
    "sg:city":"Z\u00fcrich",
    "sg:orig_category":"Detailhandel mit Blumen U Pflanzen Fachdetailhandel in Verkaufsr\u00e4umen",
    "sg:phone":"+41 12511931",
    "sg:postcode":"8032",
    "sg:province":"Z\u00fcrich",
    "wof:name":"Helene Imoberdorf Blumenhaus Hottingerplatz",
    "wof:placetype":"venue"
},
  "geometry": {"coordinates":[8.555185,47.369564],"type":"Point"}
}