{
  "type": "Feature",
  "properties": {
    "iso:country":"CH",
    "sg:address":"Schanzenstrasse 4",
    "sg:city":"Basel",
    "sg:orig_category":"Vermietung U Verpachtung von eigenen Immobilien",
    "sg:phone":"+41 17717166",
    "sg:postcode":"4056",
    "sg:province":"Basel-Stadt",
    "wof:name":"St. John's Ag",
    "wof:placetype":"venue"
},
  "geometry": {"coordinates":[8.5488967896,47.3176040649],"type":"Point"}
}