{
  "type": "Feature",
  "properties": {
    "iso:country":"CH",
    "sg:address":"Henauerstrasse 58 9244 Niederuzwil. Postfach",
    "sg:city":"Niederuzwil",
    "sg:orig_category":"Bausteine Fabrikation, Handel",
    "sg:postcode":"9244",
    "sg:province":"St. Gallen",
    "wof:name":"Trajic Unterlagsb\u00f6den",
    "wof:placetype":"venue"
},
  "geometry": {"coordinates":[9.131658,47.449051],"type":"Point"}
}