{
  "type": "Feature",
  "properties": {
    "iso:country":"CH",
    "sg:address":"Hauptstrasse 69",
    "sg:city":"Muotathal",
    "sg:orig_category":"Interessenvertretungen U sonstige Vereinigungen",
    "sg:postcode":"6436",
    "sg:province":"Schwyz",
    "wof:name":"Schwyzer Schwingerkant.-verb.",
    "wof:placetype":"venue"
},
  "geometry": {"coordinates":[8.7621965408,46.9729270935],"type":"Point"}
}