{
  "type": "Feature",
  "properties": {
    "iso:country":"CH",
    "sg:address":"Chemin De La Traverse 5",
    "sg:city":"Aubonne",
    "sg:orig_category":"Sonstiger Grosshandel",
    "sg:postcode":"1170",
    "sg:province":"Vaud",
    "wof:name":"Schnyder Robert",
    "wof:placetype":"venue"
},
  "geometry": {"coordinates":[6.3915262222,46.4919929504],"type":"Point"}
}