{
  "type": "Feature",
  "properties": {
    "iso:country":"CH",
    "sg:address":"M\u00fchlebachstrasse 43",
    "sg:city":"Z\u00fcrich",
    "sg:orig_category":"Personal U Stellenvermittlung Unternehmensberatung",
    "sg:phone":"+41 12606090",
    "sg:postcode":"8008",
    "sg:province":"Z\u00fcrich",
    "wof:name":"Demuth, Eleonore",
    "wof:placetype":"venue"
},
  "geometry": {"coordinates":[8.5516881943,47.3639755249],"type":"Point"}
}