{
  "type": "Feature",
  "properties": {
    "iso:country":"CH",
    "sg:address":"Chemin Du Pr\u00e9de-la-croix 26",
    "sg:city":"Collonge-bellerive",
    "sg:orig_category":"Herstellung von sonstigen M\u00f6beln",
    "sg:postcode":"1245",
    "sg:province":"Gen\u00e8ve",
    "wof:name":"Mugnier Philippe",
    "wof:placetype":"venue"
},
  "geometry": {"coordinates":[6.199821949,46.2390480042],"type":"Point"}
}