{
  "type": "Feature",
  "properties": {
    "addr:full":"Landstrasse 9 Adelboden Bern 3715",
    "addr:housenumber":"9",
    "addr:postcode":"3715",
    "addr:street":"Landstrasse",
    "iso:country":"CH",
    "sg:address":"Landstrasse 9",
    "sg:city":"Adelboden",
    "sg:orig_category":"Architekturb\u00fcros",
    "sg:phone":"+41 33 673 15 03",
    "sg:postcode":"3715",
    "sg:province":"Bern",
    "wof:name":"Pieren & Co Ag Architekturb\u00fcro",
    "wof:placetype":"venue"
},
  "geometry": {"coordinates":[7.562557,46.493176],"type":"Point"}
}