{
  "type": "Feature",
  "properties": {
    "iso:country":"CH",
    "sg:address":"Bahnhofstrasse 50/52 6312 Steinhausen. Postfach 26",
    "sg:city":"Steinhausen",
    "sg:orig_category":"Herstellung von Kork, Flecht U Korbwaren Herstellung von Metallerzeugnissen ohne Maschinenbau",
    "sg:phone":"+41 31 301 34 51",
    "sg:postcode":"6312",
    "sg:province":"Zug",
    "wof:name":"Vereinigte Blindenwerkst\u00e4tten Bern",
    "wof:placetype":"venue"
},
  "geometry": {"coordinates":[7.4331068993,46.9570274353],"type":"Point"}
}