{
  "type": "Feature",
  "properties": {
    "iso:country":"CH",
    "sg:address":"Kantonsschulstrasse 1",
    "sg:city":"Z\u00fcrich",
    "sg:orig_category":"Sonstiger Grosshandel",
    "sg:postcode":"8001",
    "sg:province":"Z\u00fcrich",
    "wof:name":"Epw Seifert Heinrich",
    "wof:placetype":"venue"
},
  "geometry": {"coordinates":[8.5510406494,47.315246582],"type":"Point"}
}