{
  "type": "Feature",
  "properties": {
    "iso:country":"CH",
    "sg:address":"Rue Jaquet-droz 2",
    "sg:city":"Neuenburg",
    "sg:orig_category":"Handel mit Motorr\u00e4dern, Teilen U Zubeh\u00f6r Instandhaltung U Reparatur von Motorr\u00e4dern",
    "sg:phone":"+41 32 721 41 10",
    "sg:postcode":"2000",
    "sg:province":"Neuch\u00e2tel",
    "wof:name":"Carolillo, V\u00e9los",
    "wof:placetype":"venue"
},
  "geometry": {"coordinates":[6.9478878975,46.9978752136],"type":"Point"}
}