{
  "type": "Feature",
  "properties": {
    "addr:full":"Route Du Village 33 Blonay Vaud 1807",
    "addr:housenumber":"33",
    "addr:postcode":"1807",
    "addr:street":"Route Du Village",
    "iso:country":"CH",
    "sg:address":"Route Du Village 33",
    "sg:city":"Blonay",
    "sg:orig_category":"Detailhandel mit Brot, Back U S\u00fcsswaren",
    "sg:phone":"+41 22 300 04 05",
    "sg:postcode":"1807",
    "sg:province":"Vaud",
    "wof:name":"Fran\u00e7ois Wolfisberg Jr. Boulangerie & P\u00e2tisserie",
    "wof:placetype":"venue"
},
  "geometry": {"coordinates":[6.140698,46.184898],"type":"Point"}
}