{
  "type": "Feature",
  "properties": {
    "addr:full":"Route Du Signal 21 Lausanne Vaud 1018",
    "addr:housenumber":"21",
    "addr:postcode":"1018",
    "addr:street":"Route Du Signal",
    "iso:country":"CH",
    "sg:address":"Route Du Signal 21",
    "sg:city":"Lausanne",
    "sg:orig_category":"Bauingenieurb\u00fcros Eisenbetonbau Bauingenieurb\u00fcros allgemein",
    "sg:phone":"+41 21 312 45 66",
    "sg:postcode":"1018",
    "sg:province":"Vaud",
    "wof:name":"Arthur Spagnol Bureau D'ing\u00e9nieur",
    "wof:placetype":"venue"
},
  "geometry": {"coordinates":[6.637172,46.532463],"type":"Point"}
}