{
  "type": "Feature",
  "properties": {
    "iso:country":"CH",
    "sg:address":"Freier Platz 6 8200 Schaffhausen. Postfach",
    "sg:city":"Schaffhausen",
    "sg:orig_category":"Unternehmensberatung",
    "sg:phone":"+41 61 721 50 18",
    "sg:postcode":"8200",
    "sg:province":"Schaffhausen",
    "wof:name":"Zihlmann & Partner Unternehmensberatung",
    "wof:placetype":"venue"
},
  "geometry": {"coordinates":[7.5284509659,47.5066566467],"type":"Point"}
}