{
  "type": "Feature",
  "properties": {
    "iso:country":"CH",
    "sg:address":"Hinterdorfstrasse 5",
    "sg:city":"Sch\u00f6fflisdorf",
    "sg:orig_category":"Schlossereien Schmieden",
    "sg:phone":"+41 18561115",
    "sg:postcode":"8165",
    "sg:province":"Z\u00fcrich",
    "wof:name":"Werner Hirt Schmiede & Schlosserei",
    "wof:placetype":"venue"
},
  "geometry": {"coordinates":[8.4154424667,47.499961853],"type":"Point"}
}