{
  "type": "Feature",
  "properties": {
    "iso:country":"CH",
    "sg:address":"Stroppelstrasse 16",
    "sg:city":"Untersiggenthal",
    "sg:orig_category":"Mechanik",
    "sg:postcode":"5417",
    "sg:province":"Aargau",
    "wof:name":"Frutig-aufranc Yvette",
    "wof:placetype":"venue"
},
  "geometry": {"coordinates":[-6.2257637978,53.3287658691],"type":"Point"}
}