{
  "type": "Feature",
  "properties": {
    "iso:country":"CH",
    "sg:address":"Rhodanie Avenue De 60",
    "sg:city":"Lausanne",
    "sg:orig_category":"Grosshandel mit sonstigen Gebrauchs U Verbrauchsg\u00fctern",
    "sg:phone":"+41 41 850 13 53",
    "sg:postcode":"1007",
    "sg:province":"Vaud",
    "wof:name":"Diamas Ag",
    "wof:placetype":"venue"
},
  "geometry": {"coordinates":[8.4397115707,47.0805091858],"type":"Point"}
}