{
  "type": "Feature",
  "properties": {
    "iso:country":"CH",
    "sg:address":"Raamattenstrasse 14 5621 Zufikon. Postfach",
    "sg:city":"Zufikon",
    "sg:orig_category":"Herstellung von Anstrichmitteln, Druckfarben U Kitten Unternehmensberatung",
    "sg:phone":"+41 56 633 45 87",
    "sg:postcode":"5621",
    "sg:province":"Aargau",
    "wof:name":"Bela Consult Ag Farben, Lacke Usw.; Beratung, Einkauf, Verkauf",
    "wof:placetype":"venue"
},
  "geometry": {"coordinates":[8.3541316986,47.3542671204],"type":"Point"}
}