{
  "type": "Feature",
  "properties": {
    "iso:country":"CH",
    "sg:address":"Dorfplatz 2",
    "sg:city":"Rumisberg",
    "sg:orig_category":"Primarschulen",
    "sg:postcode":"4539",
    "sg:province":"Bern",
    "wof:name":"Primarschule",
    "wof:placetype":"venue"
},
  "geometry": {"coordinates":[7.6427721977,47.2624473572],"type":"Point"}
}