{
  "type": "Feature",
  "properties": {
    "iso:country":"CH",
    "sg:address":"Winkelstrasse 13",
    "sg:city":"Bannwil",
    "sg:orig_category":"Grosshandel mit lebenden Tieren",
    "sg:phone":"+41 62 963 24 37",
    "sg:postcode":"4913",
    "sg:province":"Bern",
    "wof:name":"Fritz Staub Viehhandel",
    "wof:placetype":"venue"
},
  "geometry": {"coordinates":[7.7302918434,47.2385101318],"type":"Point"}
}