{
  "type": "Feature",
  "properties": {
    "iso:country":"CH",
    "sg:address":"Route Du Grand-lancy 2 Grand-lancy 1200 Genf. Postfach",
    "sg:city":"Grand-lancy",
    "sg:classifiers":[
        {
            "category":"Professional",
            "subcategory":"Employment Agencies",
            "type":"Services"
        }
    ],
    "sg:phone":"+41 21 921 02 21",
    "sg:postcode":"1212",
    "sg:province":"Gen\u00e8ve",
    "sg:tags":[
        "personal",
        "u",
        "stellenvermittlung"
    ],
    "wof:name":"Cabinet Sr Conseils, Rogivue Serge Conseils En Ressources Humaines",
    "wof:placetype":"venue"
},
  "geometry": {"coordinates":[5.1808700562,45.8973388672],"type":"Point"}
}