{
  "type": "Feature",
  "properties": {
    "iso:country":"CH",
    "sg:address":"Luzernstrasse 15",
    "sg:city":"Derendingen",
    "sg:orig_category":"Detektivb\u00fcros U \u00dcberwachung",
    "sg:phone":"+41 32 682 10 06",
    "sg:postcode":"4552",
    "sg:province":"Solothurn",
    "wof:name":"\u00dcbewag Gmbh",
    "wof:placetype":"venue"
},
  "geometry": {"coordinates":[7.5833230019,47.2004470825],"type":"Point"}
}