{
  "type": "Feature",
  "properties": {
    "iso:country":"CH",
    "sg:address":"Haus Felsenburg",
    "sg:city":"Freienbach",
    "sg:orig_category":"Unternehmensberatung",
    "sg:postcode":"8807",
    "sg:province":"Schwyz",
    "wof:name":"E.m.s. Management Systems Ag",
    "wof:placetype":"venue"
},
  "geometry": {"coordinates":[8.7577753067,47.2063064575],"type":"Point"}
}