{
  "type": "Feature",
  "properties": {
    "iso:country":"CH",
    "sg:address":"Via Torraccia 17 6883 Novazzano. Postfach Caselle Postale 16",
    "sg:city":"Novazzano",
    "sg:orig_category":"G\u00fcterbef\u00f6rderung im Strassenverkehr Handelsvermittlung U Grosshandel",
    "sg:phone":"+41 91 683 23 38",
    "sg:postcode":"6883",
    "sg:province":"Ticino",
    "wof:name":"Fattorini Autotrasporti Sagl",
    "wof:placetype":"venue"
},
  "geometry": {"coordinates":[8.9970684052,45.840461731],"type":"Point"}
}