{
  "type": "Feature",
  "properties": {
    "iso:country":"CH",
    "sg:address":"Rue De La Plaine 25",
    "sg:city":"Yverdon-les-bains",
    "sg:orig_category":"K\u00fcnstlerische U schriftstellerische T\u00e4tigkeiten U Darbietungen Sonstige k\u00fcnstlerische U schriftstell",
    "sg:phone":"+41 24 425 05 12",
    "sg:postcode":"1400",
    "sg:province":"Vaud",
    "wof:name":"Galerie-atelier Yvart, Nicoloff Ortrud",
    "wof:placetype":"venue"
},
  "geometry": {"coordinates":[6.6435399055,46.7777481079],"type":"Point"}
}