{
  "type": "Feature",
  "properties": {
    "iso:country":"CH",
    "sg:address":"4577",
    "sg:city":"Hessigkofen",
    "sg:orig_category":"Detailhandel mit Waren verschiedener Art, Hauptrichtung Nahrungsmittel",
    "sg:phone":"+41 32 661 10 13",
    "sg:postcode":"4577",
    "sg:province":"Solothurn",
    "wof:name":"Landi Bucheggberg",
    "wof:placetype":"venue"
},
  "geometry": {"coordinates":[7.4580898285,47.140209198],"type":"Point"}
}