{
  "type": "Feature",
  "properties": {
    "iso:country":"CH",
    "sg:address":"Zeughausgasse 9 6330 Cham. Postfach 65",
    "sg:city":"Cham",
    "sg:orig_category":"Herstellung von Kunststoff in Prim\u00e4rformen",
    "sg:phone":"+41 61 467 93 93",
    "sg:postcode":"6330",
    "sg:province":"Zug",
    "wof:name":"Plastomatic Ag",
    "wof:placetype":"venue"
},
  "geometry": {"coordinates":[7.6558318138,47.5280189514],"type":"Point"}
}