{
  "type": "Feature",
  "properties": {
    "iso:country":"CH",
    "sg:address":"7557",
    "sg:city":"Vn\u00e0",
    "sg:orig_category":"Pensionen mit Restaurant",
    "sg:phone":"+41 81 866 31 27",
    "sg:postcode":"7557",
    "sg:province":"Graubunden",
    "wof:name":"Pensiun Arina",
    "wof:placetype":"venue"
},
  "geometry": {"coordinates":[10.364824295,46.8425788879],"type":"Point"}
}