{
  "type": "Feature",
  "properties": {
    "iso:country":"CH",
    "sg:address":"L\u00e4chlerstrasse 11 8634 Hombrechtikon. Postfach 23",
    "sg:city":"Hombrechtikon",
    "sg:orig_category":"Herstellung von k\u00e4lte U lufttechnischen Erzeugnissen f\u00fcr gewerbliche Zwecke Installation von Heizung",
    "sg:phone":"+41 55 244 44 42",
    "sg:postcode":"8634",
    "sg:province":"Z\u00fcrich",
    "wof:name":"K\u00e4lte + Klima-service Z\u00fcrrer Ag",
    "wof:placetype":"venue"
},
  "geometry": {"coordinates":[8.7648983002,47.2513847351],"type":"Point"}
}