{
  "type": "Feature",
  "properties": {
    "iso:country":"CH",
    "sg:address":"Route Du Jura 37",
    "sg:city":"Fribourg",
    "sg:classifiers":[
        {
            "category":"Shopping",
            "subcategory":"Stationery & Office Supplies",
            "type":"Retail Goods"
        }
    ],
    "sg:phone":"+41 26 347 26 26",
    "sg:postcode":"1700",
    "sg:province":"Fribourg",
    "sg:tags":[
        "furniture"
    ],
    "wof:name":"Interoffice Labastrou S.a.",
    "wof:placetype":"venue"
},
  "geometry": {"coordinates":[7.148337841,46.8096008301],"type":"Point"}
}