{
  "type": "Feature",
  "properties": {
    "iso:country":"CH",
    "sg:address":"Volkshausstrasse 20",
    "sg:city":"Wattwil",
    "sg:orig_category":"Physiotherapie",
    "sg:phone":"+41 26 912 24 42",
    "sg:postcode":"9630",
    "sg:province":"St. Gallen",
    "wof:name":"Physiotherapie Tour-de-tr\u00eame",
    "wof:placetype":"venue"
},
  "geometry": {"coordinates":[7.0607609749,46.6106643677],"type":"Point"}
}