{
  "type": "Feature",
  "properties": {
    "iso:country":"CH",
    "sg:address":"En Belli\u00e8re 1808 Corsier-les-monts. Postfach",
    "sg:city":"Corsier-les-monts",
    "sg:orig_category":"Sonstige pers\u00f6nliche Dienstleistungen",
    "sg:postcode":"1808",
    "sg:province":"Vaud",
    "wof:name":"Fermetures Id\u00e9ales S\u00e0rl Travaux En Rapport Avec Le B\u00e2timent, Notamm. La Fourniture Etc",
    "wof:placetype":"venue"
},
  "geometry": {"coordinates":[6.8812398911,46.5034866333],"type":"Point"}
}