{
  "type": "Feature",
  "properties": {
    "iso:country":"CH",
    "sg:address":"Flurstr. 34. 8309 N\u00fcrensdorf. Postfach",
    "sg:city":"Kloten",
    "sg:orig_category":"Reiseb\u00fcros U Reiseveranstalter",
    "sg:phone":"+41 18364341",
    "sg:postcode":"8302",
    "sg:province":"Z\u00fcrich",
    "wof:name":"Holenweger Reisen",
    "wof:placetype":"venue"
},
  "geometry": {"coordinates":[8.648815155,47.4469451904],"type":"Point"}
}