{
  "type": "Feature",
  "properties": {
    "iso:country":"CH",
    "sg:address":"Holbeinstrasse 34 8008 Z\u00fcrich. Postfach",
    "sg:city":"Z\u00fcrich",
    "sg:orig_category":"Sonstige mit Sport verbundene T\u00e4tigkeiten",
    "sg:postcode":"8008",
    "sg:province":"Z\u00fcrich",
    "wof:name":"F\u00e4h-forster Xaver",
    "wof:placetype":"venue"
},
  "geometry": {"coordinates":[9.2548904419,47.4220199585],"type":"Point"}
}