{
  "type": "Feature",
  "properties": {
    "iso:country":"CH",
    "sg:address":"Peierackerweg 3",
    "sg:city":"Uster",
    "sg:orig_category":"Vorschulen, Kinderg\u00e4rten",
    "sg:phone":"+41 19153689",
    "sg:postcode":"8610",
    "sg:province":"Z\u00fcrich",
    "wof:name":"Kindergarten Wanne",
    "wof:placetype":"venue"
},
  "geometry": {"coordinates":[8.6002149582,47.2987823486],"type":"Point"}
}