{
  "type": "Feature",
  "properties": {
    "iso:country":"CH",
    "sg:address":"Weggismattstrasse 23",
    "sg:city":"Luzern",
    "sg:classifiers":[
        {
            "category":"Communications",
            "type":"Services"
        }
    ],
    "sg:phone":"+41 41 429 02 02",
    "sg:postcode":"6004",
    "sg:province":"Luzern",
    "sg:tags":[
        "administration",
        "network"
    ],
    "wof:name":"Net-design Ag",
    "wof:placetype":"venue"
},
  "geometry": {"coordinates":[8.3084812164,47.064666748],"type":"Point"}
}