{
  "type": "Feature",
  "properties": {
    "iso:country":"CH",
    "sg:address":"Risciana Via 12",
    "sg:city":"Gentilino",
    "sg:orig_category":"Finanzierungsinstitutionen",
    "sg:postcode":"6925",
    "sg:province":"Ticino",
    "wof:name":"Your Office Sa",
    "wof:placetype":"venue"
},
  "geometry": {"coordinates":[8.9276647568,45.9918823242],"type":"Point"}
}