{
  "type": "Feature",
  "properties": {
    "iso:country":"CH",
    "sg:address":"Mattenweg 21 5607 H\u00e4gglingen. Postfach",
    "sg:city":"H\u00e4gglingen",
    "sg:orig_category":"Non-Classified Establishments",
    "sg:phone":"+41 56 610 10 61",
    "sg:postcode":"5607",
    "sg:province":"Aargau",
    "wof:name":"E-prosol Ag Systeme Der Informations- U. Kommunikationstechnologie; Entwicklung, Herstellung, Vertrieb Usw",
    "wof:placetype":"venue"
},
  "geometry": {"coordinates":[8.2544927597,47.389503479],"type":"Point"}
}