{
  "type": "Feature",
  "properties": {
    "iso:country":"CH",
    "sg:address":"Affolternstrasse 52",
    "sg:city":"Z\u00fcrich",
    "sg:orig_category":"Berufliche Weiterbildung, Erwachsenenbildung Hochschulen U h\u00f6here Ausbildung",
    "sg:phone":"+41 13182823",
    "sg:postcode":"8050",
    "sg:province":"Z\u00fcrich",
    "wof:name":"Abb Lernzentren",
    "wof:placetype":"venue"
},
  "geometry": {"coordinates":[8.542021,47.411194],"type":"Point"}
}