{
  "type": "Feature",
  "properties": {
    "iso:country":"CH",
    "sg:address":"Webergasse 7.",
    "sg:city":"Schaffhausen",
    "sg:orig_category":"Detailhandel mit elektrischen Haushalts-,Radio U Fernsehger\u00e4ten sowie Musikinstrumenten",
    "sg:postcode":"8200",
    "sg:province":"Schaffhausen",
    "wof:name":"Rainbow Music Daniel Bollinger.",
    "wof:placetype":"venue"
},
  "geometry": {"coordinates":[8.6365013123,47.698184967],"type":"Point"}
}