{
  "type": "Feature",
  "properties": {
    "iso:country":"CH",
    "sg:address":"Farbgasse 23",
    "sg:city":"Langenthal",
    "sg:orig_category":"Reparatur von Schuhen U Lederwaren",
    "sg:phone":"+41 62 922 16 02",
    "sg:postcode":"4900",
    "sg:province":"Bern",
    "wof:name":"Karl Wojacek Mass-schuhmacherei",
    "wof:placetype":"venue"
},
  "geometry": {"coordinates":[7.7888407707,47.2106781006],"type":"Point"}
}