{
  "type": "Feature",
  "properties": {
    "iso:country":"CH",
    "sg:address":"Bachstrasse 31",
    "sg:city":"Lenzburg",
    "sg:orig_category":"Organisationen des Gesundheitswesen",
    "sg:phone":"+41 62 891 90 79",
    "sg:postcode":"5600",
    "sg:province":"Aargau",
    "wof:name":"Krankenpflegeverein Des Bezirks Lenzburg",
    "wof:placetype":"venue"
},
  "geometry": {"coordinates":[8.1767396927,47.3841247559],"type":"Point"}
}