{
  "type": "Feature",
  "properties": {
    "iso:country":"CH",
    "sg:address":"Hintere Hauptgasse 20",
    "sg:city":"Zofingen",
    "sg:classifiers":[
        {
            "category":"Education",
            "subcategory":"Library",
            "type":"Public Place"
        }
    ],
    "sg:phone":"+41 52 741 49 44",
    "sg:postcode":"4800",
    "sg:province":"Aargau",
    "sg:tags":[
        "u",
        "bibliotheken",
        "archive"
    ],
    "wof:name":"Stadtbibliothek Stein Am Rhein Haus Zum Rosenegg",
    "wof:placetype":"venue"
},
  "geometry": {"coordinates":[8.859425,47.658581],"type":"Point"}
}