{
  "type": "Feature",
  "properties": {
    "iso:country":"CH",
    "sg:address":"Berninastrasse 17",
    "sg:city":"Z\u00fcrich",
    "sg:orig_category":"Rechtsberatung",
    "sg:phone":"+41 12513010",
    "sg:postcode":"8057",
    "sg:province":"Z\u00fcrich",
    "wof:name":"Ingrid Brawer Rechts-& Steuerberatung",
    "wof:placetype":"venue"
},
  "geometry": {"coordinates":[8.5511426926,47.4027023315],"type":"Point"}
}