{
  "type": "Feature",
  "properties": {
    "iso:country":"CH",
    "sg:address":"Aarwangenstrasse 82",
    "sg:city":"Langenthal",
    "sg:classifiers":[
        {
            "category":"Travel",
            "subcategory":"Hotels & Motels",
            "type":"Entertainment"
        }
    ],
    "sg:phone":"+41 62 923 83 00",
    "sg:postcode":"4900",
    "sg:province":"Bern",
    "sg:tags":[
        "hotels",
        "mit",
        "restaurant"
    ],
    "wof:name":"Hotel Langenthal Gmbh",
    "wof:placetype":"venue"
},
  "geometry": {"coordinates":[7.7792410851,47.2238006592],"type":"Point"}
}