{
  "type": "Feature",
  "properties": {
    "iso:country":"CH",
    "sg:address":"Bertrand Avenue Alfred- 3 1206 Gen\u00e8ve. Postfach",
    "sg:city":"Gen\u00e8ve",
    "sg:orig_category":"Sonstiger Grosshandel",
    "sg:postcode":"1207",
    "sg:province":"Gen\u00e8ve",
    "wof:name":"Kayros S\u00e0rl",
    "wof:placetype":"venue"
},
  "geometry": {"coordinates":[6.1549730301,46.1934661865],"type":"Point"}
}