{
  "type": "Feature",
  "properties": {
    "iso:country":"CH",
    "sg:address":"T\u00f6sstalstrasse 54",
    "sg:city":"Winterthur",
    "sg:orig_category":"Kinderkrippen U horte",
    "sg:phone":"+41 52 212 62 69",
    "sg:postcode":"8400",
    "sg:province":"Z\u00fcrich",
    "wof:name":"Kinderkrippe Des Frauenbundes Winterthur Bambi",
    "wof:placetype":"venue"
},
  "geometry": {"coordinates":[8.7368469238,47.4956054688],"type":"Point"}
}