{
  "type": "Feature",
  "properties": {
    "iso:country":"CH",
    "sg:address":"R\u00fcbliweg 151",
    "sg:city":"H\u00e4rkingen",
    "sg:orig_category":"W\u00e4scherei U chemische Reinigung",
    "sg:phone":"+41 62 398 29 57",
    "sg:postcode":"4624",
    "sg:province":"Solothurn",
    "wof:name":"Pelikan-service Ag",
    "wof:placetype":"venue"
},
  "geometry": {"coordinates":[7.8243398666,47.3115615845],"type":"Point"}
}