{
  "type": "Feature",
  "properties": {
    "iso:country":"CH",
    "sg:address":"Wildensteinerstrasse 16",
    "sg:city":"Lampenberg",
    "sg:orig_category":"Herstellung von Konstruktionsteilen, Fertigbauteilen U Ausbauelementen aus Holz",
    "sg:phone":"+41 61 951 14 86",
    "sg:postcode":"4432",
    "sg:province":"Basel-Landschaft",
    "wof:name":"Holzhandwerk Handschin Gmbh",
    "wof:placetype":"venue"
},
  "geometry": {"coordinates":[7.7554469109,47.4256515503],"type":"Point"}
}