{
  "type": "Feature",
  "properties": {
    "iso:country":"CH",
    "sg:address":"Eptingerstrasse 58",
    "sg:city":"Muttenz",
    "sg:orig_category":"G\u00fcterbef\u00f6rderung im Strassenverkehr",
    "sg:phone":"+41 61 461 57 12",
    "sg:postcode":"4132",
    "sg:province":"Basel-Landschaft",
    "wof:name":"Franz Rothermann Transporte",
    "wof:placetype":"venue"
},
  "geometry": {"coordinates":[7.6554369926,47.5273017883],"type":"Point"}
}