{
  "type": "Feature",
  "properties": {
    "iso:country":"CH",
    "sg:address":"Unterfelsbach 405",
    "sg:city":"Gams",
    "sg:orig_category":"Office, Building, Fa\u00e7ade, Industry, Hospital Cleaning Services",
    "sg:phone":"+41 71 311 81 13",
    "sg:postcode":"9473",
    "sg:province":"St. Gallen",
    "wof:name":"Benz Ag",
    "wof:placetype":"venue"
},
  "geometry": {"coordinates":[9.2996959686,47.405040741],"type":"Point"}
}