{
  "type": "Feature",
  "properties": {
    "iso:country":"CH",
    "sg:address":"M\u00fchlenstrasse 21",
    "sg:city":"Villmergen",
    "sg:orig_category":"G\u00fcterbef\u00f6rderung im Strassenverkehr",
    "sg:phone":"+41 56 622 10 13",
    "sg:postcode":"5612",
    "sg:province":"Aargau",
    "wof:name":"Oskar Leuppi Transporte",
    "wof:placetype":"venue"
},
  "geometry": {"coordinates":[8.248793602,47.3484039307],"type":"Point"}
}