{
  "type": "Feature",
  "properties": {
    "iso:country":"CH",
    "sg:address":"Simplon Rue Du 8b 1006 Lausanne. Postfach",
    "sg:city":"Lausanne",
    "sg:orig_category":"Non-Classified Establishments",
    "sg:postcode":"1003",
    "sg:province":"Vaud",
    "wof:name":"Microbeads Ag Strahlmittel F. Oberfl\u00e4chenbearbeitung",
    "wof:placetype":"venue"
},
  "geometry": {"coordinates":[-105.89307403559999,39.3157958984],"type":"Point"}
}