{
  "type": "Feature",
  "properties": {
    "iso:country":"CH",
    "sg:address":"Hinterhagweg 1 4443 Wittinsburg. Postfach",
    "sg:city":"Wittinsburg",
    "sg:orig_category":"Herstellung von Konstruktionsteilen, Fertigbauteilen U Ausbauelementen aus Holz",
    "sg:phone":"+41 62 299 01 27",
    "sg:postcode":"4443",
    "sg:province":"Basel-Landschaft",
    "wof:name":"Schreinerei Marbet",
    "wof:placetype":"venue"
},
  "geometry": {"coordinates":[7.8412680626,47.4244613647],"type":"Point"}
}