{
  "type": "Feature",
  "properties": {
    "iso:country":"CH",
    "sg:address":"Ch. De La Rippaz 16.",
    "sg:city":"Vandoeuvres",
    "sg:orig_category":"Grosshandel mit Getr\u00e4nken",
    "sg:postcode":"1253",
    "sg:province":"Gen\u00e8ve",
    "wof:name":"Clarina Firmenich",
    "wof:placetype":"venue"
},
  "geometry": {"coordinates":[6.1989340782,46.2282180786],"type":"Point"}
}