{
  "type": "Feature",
  "properties": {
    "iso:country":"CH",
    "sg:address":"Hubelmatte",
    "sg:city":"Krattigen",
    "sg:orig_category":"Detailhandel mit Brot, Back U S\u00fcsswaren Detailhandel mit Waren verschiedener Art, Hauptrichtung Nahr",
    "sg:phone":"+41 79 210 36 08",
    "sg:postcode":"3704",
    "sg:province":"Bern",
    "wof:name":"Albert Schranz",
    "wof:placetype":"venue"
},
  "geometry": {"coordinates":[7.7278847694,46.6610832214],"type":"Point"}
}