{
  "type": "Feature",
  "properties": {
    "iso:country":"CH",
    "sg:address":"Zi Petits-champs 11a-b",
    "sg:city":"Yverdon-les-bains",
    "sg:classifiers":[
        {
            "category":"Utilities",
            "subcategory":"Mobile Phone",
            "type":"Services"
        }
    ],
    "sg:phone":"+41 24 426 04 20",
    "sg:postcode":"1400",
    "sg:province":"Vaud",
    "sg:tags":[
        "telecommunication",
        "audio-visual"
    ],
    "wof:name":"Relec S.a.",
    "wof:placetype":"venue"
},
  "geometry": {"coordinates":[6.64142,46.778633],"type":"Point"}
}