{
  "type": "Feature",
  "properties": {
    "iso:country":"CH",
    "sg:address":"Via Albarelle",
    "sg:city":"Ascona",
    "sg:classifiers":[
        {
            "category":"Travel",
            "subcategory":"Hotels & Motels",
            "type":"Entertainment"
        }
    ],
    "sg:phone":"+41 91 791 20 55",
    "sg:postcode":"6612",
    "sg:province":"Ticino",
    "sg:tags":[
        "hotels",
        "mit",
        "restaurant"
    ],
    "wof:name":"Lugalago Sa",
    "wof:placetype":"venue"
},
  "geometry": {"coordinates":[8.7724790573,46.1515922546],"type":"Point"}
}