{
  "type": "Feature",
  "properties": {
    "iso:country":"CH",
    "sg:address":"Hauptstrasse 40",
    "sg:city":"Diegten",
    "sg:orig_category":"Polizei",
    "sg:phone":"+41 61 971 22 29",
    "sg:postcode":"4457",
    "sg:province":"Basel-Landschaft",
    "wof:name":"Kantonaler Polizeiposten",
    "wof:placetype":"venue"
},
  "geometry": {"coordinates":[7.8091878891,47.4098625183],"type":"Point"}
}