{
  "type": "Feature",
  "properties": {
    "iso:country":"CH",
    "sg:address":"Faubourg Du Lac 9",
    "sg:city":"Neuch\u00e2tel",
    "sg:orig_category":"Fahrschulen, Flugschulen",
    "sg:phone":"+41 79 637 24 47",
    "sg:postcode":"2000",
    "sg:province":"Neuch\u00e2tel",
    "wof:name":"Philippe Storz Auto-\u00e9cole Drive In",
    "wof:placetype":"venue"
},
  "geometry": {"coordinates":[6.9330019951,46.9921722412],"type":"Point"}
}