{
  "type": "Feature",
  "properties": {
    "addr:full":"Wiesenbergstrasse 10 Dallenwil Nidwalden 6383",
    "addr:housenumber":"10",
    "addr:postcode":"6383",
    "addr:street":"Wiesenbergstrasse",
    "iso:country":"CH",
    "sg:address":"Wiesenbergstrasse 10",
    "sg:city":"Dallenwil",
    "sg:orig_category":"Bauschreinerei Innenausbau",
    "sg:phone":"+41 79 340 81 81",
    "sg:postcode":"6383",
    "sg:province":"Nidwalden",
    "wof:name":"Adolph Niederberger Schreinerei & Innenausbau",
    "wof:placetype":"venue"
},
  "geometry": {"coordinates":[8.388542,46.926521],"type":"Point"}
}