{
  "type": "Feature",
  "properties": {
    "iso:country":"CH",
    "sg:address":"Rebenweg 262",
    "sg:city":"Hornussen",
    "sg:orig_category":"Detailhandel mit Beleuchtungs U Haushaltsgegenst\u00e4nden Detailhandel mit elektrischen Haushalts, Radio",
    "sg:phone":"+41 21 923 56 11",
    "sg:postcode":"5075",
    "sg:province":"Aargau",
    "wof:name":"Soci\u00e9t\u00e9 Romande D'electricit\u00e9 Centre Sre-menager",
    "wof:placetype":"venue"
},
  "geometry": {"coordinates":[6.843275,46.462135],"type":"Point"}
}