{
  "type": "Feature",
  "properties": {
    "iso:country":"CH",
    "sg:address":"Bahnhofstrasse 4 2502 Biel/bienne. Postfach",
    "sg:city":"Biel/bienne",
    "sg:classifiers":[
        {
            "category":"Bars & Pubs",
            "type":"Food & Drink"
        }
    ],
    "sg:phone":"+41 32 322 21 14",
    "sg:postcode":"2501",
    "sg:province":"Bern",
    "sg:tags":[
        "restaurant"
    ],
    "wof:name":"Caf\u00e9 Bar-hasard",
    "wof:placetype":"venue"
},
  "geometry": {"coordinates":[7.243405,47.132797],"type":"Point"}
}