{
  "type": "Feature",
  "properties": {
    "iso:country":"CH",
    "sg:address":"1407",
    "sg:city":"Donneloye",
    "sg:classifiers":[
        {
            "category":"Restaurant",
            "type":"Food & Drink"
        }
    ],
    "sg:phone":"+41 24 433 11 95",
    "sg:postcode":"1407",
    "sg:province":"Vaud",
    "wof:name":"Restaurant Des Champs",
    "wof:placetype":"venue"
},
  "geometry": {"coordinates":[6.7151279449,46.7428970337],"type":"Point"}
}