{
  "type": "Feature",
  "properties": {
    "iso:country":"CH",
    "sg:address":"B\u00fcntlistrasse.",
    "sg:city":"Grabs",
    "sg:orig_category":"Zimmerei, Dachdeckerei, Bauspenglerei U Abdichtung",
    "sg:phone":"+41 81 771 35 57",
    "sg:postcode":"9472",
    "sg:province":"St. Gallen",
    "wof:name":"Hans Zogg, Holzbau",
    "wof:placetype":"venue"
},
  "geometry": {"coordinates":[9.4404144287,47.1830291748],"type":"Point"}
}