{
  "type": "Feature",
  "properties": {
    "iso:country":"CH",
    "sg:address":"6822",
    "sg:city":"Arogno",
    "sg:orig_category":"Detailhandel mit Blumen U Pflanzen",
    "sg:phone":"+41 91 649 86 28",
    "sg:postcode":"6822",
    "sg:province":"Ticino",
    "wof:name":"Gualtiero Cereghetti Fiorista",
    "wof:placetype":"venue"
},
  "geometry": {"coordinates":[8.986733,45.958897],"type":"Point"}
}