{
  "type": "Feature",
  "properties": {
    "iso:country":"CH",
    "sg:address":"Rue De La Mor\u00e2che 7",
    "sg:city":"Nyon",
    "sg:orig_category":"Gartenbau Landschaftsplanungsb\u00fcros U Gartenarchitekturb\u00fcros",
    "sg:phone":"+41 22 362 08 23",
    "sg:postcode":"1260",
    "sg:province":"Vaud",
    "wof:name":"Santiago Rodriguez Entreprise Paysag\u00e8re",
    "wof:placetype":"venue"
},
  "geometry": {"coordinates":[6.2353801727,46.383140564],"type":"Point"}
}