{
  "type": "Feature",
  "properties": {
    "addr:full":"Affolternstrasse 103 Z\u00fcrich Z\u00fcrich 8050",
    "addr:housenumber":"103",
    "addr:postcode":"8050",
    "addr:street":"Affolternstrasse",
    "iso:country":"CH",
    "sg:address":"Affolternstrasse 103",
    "sg:city":"Z\u00fcrich",
    "sg:orig_category":"Bauschreinerei Glaserei",
    "sg:phone":"+41 71 761 03 04",
    "sg:postcode":"8050",
    "sg:province":"Z\u00fcrich",
    "wof:name":"Peter Z\u00e4ch Schreinerei & Glaserei",
    "wof:placetype":"venue"
},
  "geometry": {"coordinates":[9.56208,47.314926],"type":"Point"}
}