{
  "type": "Feature",
  "properties": {
    "addr:full":"Avenue D'echallens 133-135 Lausanne Vaud 1004",
    "addr:postcode":"133-135;1004",
    "addr:street":"Avenue D'Echallens",
    "iso:country":"CH",
    "sg:address":"Avenue D'echallens 133-135",
    "sg:city":"Lausanne",
    "sg:orig_category":"Bauschreinerei Herstellung von Konstruktionsteilen, Fertigbauteilen U Ausbauelementen aus Holz",
    "sg:phone":"+41 79 347 11 33",
    "sg:postcode":"1004",
    "sg:province":"Vaud",
    "wof:name":"Ballenegger Marc & Cie Sa",
    "wof:placetype":"venue"
},
  "geometry": {"coordinates":[6.61873,46.533489],"type":"Point"}
}