{
  "type": "Feature",
  "properties": {
    "iso:country":"CH",
    "sg:address":"Spitzackerstrasse 17",
    "sg:city":"Z\u00fcrich",
    "sg:orig_category":"Fotografische Ateliers",
    "sg:phone":"+41 13632500",
    "sg:postcode":"8057",
    "sg:province":"Z\u00fcrich",
    "wof:name":"Alex Fellner Fotografisches Atelier",
    "wof:placetype":"venue"
},
  "geometry": {"coordinates":[8.5381889343,47.3977279663],"type":"Point"}
}