{
  "type": "Feature",
  "properties": {
    "iso:country":"CH",
    "sg:address":"Bitziusstrasse 40",
    "sg:city":"Bern",
    "sg:orig_category":"Unternehmensberatung",
    "sg:phone":"+41 31 351 25 25",
    "sg:postcode":"3006",
    "sg:province":"Bern",
    "wof:name":"Ic Infraconsult Ag",
    "wof:placetype":"venue"
},
  "geometry": {"coordinates":[7.4682297707,46.950214386],"type":"Point"}
}