{
  "type": "Feature",
  "properties": {
    "iso:country":"CH",
    "sg:address":"R\u00e9seau Communal",
    "sg:city":"Lucens",
    "sg:orig_category":"Wasserversorgung",
    "sg:phone":"+41 21 906 82 84",
    "sg:postcode":"1522",
    "sg:province":"Vaud",
    "wof:name":"Service Des Eaux De La Commune De Lucens",
    "wof:placetype":"venue"
},
  "geometry": {"coordinates":[6.8418149948,46.7074050903],"type":"Point"}
}