{
  "type": "Feature",
  "properties": {
    "iso:country":"CH",
    "sg:address":"Ferdinand Hodler-strasse 8 8049 Z\u00fcrich. Postfach",
    "sg:city":"Z\u00fcrich",
    "sg:orig_category":"Handel mit Motorr\u00e4dern, Teilen U Zubeh\u00f6r Instandhaltung U Reparatur von Motorr\u00e4dern",
    "sg:postcode":"8049",
    "sg:province":"Z\u00fcrich",
    "wof:name":"Repond Marcel.",
    "wof:placetype":"venue"
},
  "geometry": {"coordinates":[6.5824589729,46.5384101868],"type":"Point"}
}