{
  "type": "Feature",
  "properties": {
    "iso:country":"CH",
    "sg:address":"Lindenstrasse 4",
    "sg:city":"Liestal",
    "sg:orig_category":"Detailhandel mit Waren verschiedener Art, Hauptrichtung Nahrungsmittel Grosshandel mit Nahrungsmitte",
    "sg:phone":"+41 61 921 96 67",
    "sg:postcode":"4410",
    "sg:province":"Basel-Landschaft",
    "wof:name":"Paolella, Pasquale",
    "wof:placetype":"venue"
},
  "geometry": {"coordinates":[7.7366170883,47.4853820801],"type":"Point"}
}