{
  "type": "Feature",
  "properties": {
    "iso:country":"CH",
    "sg:address":"Centralstrasse 27 3800 Interlaken. Postfach",
    "sg:city":"Interlaken",
    "sg:orig_category":"Architektur U Ingenieurb\u00fcros",
    "sg:postcode":"3800",
    "sg:province":"Bern",
    "wof:name":"Gasser Peter + Co",
    "wof:placetype":"venue"
},
  "geometry": {"coordinates":[7.85498,46.684662],"type":"Point"}
}