{
  "type": "Feature",
  "properties": {
    "iso:country":"CH",
    "sg:address":"L\u00f6wenstrasse 5",
    "sg:city":"Romanshorn",
    "sg:classifiers":[
        {
            "category":"Restaurant",
            "type":"Food & Drink"
        }
    ],
    "sg:phone":"+41 27 283 13 12",
    "sg:postcode":"8590",
    "sg:province":"Thurgau",
    "wof:name":"Restaurant Cord\u00e9e",
    "wof:placetype":"venue"
},
  "geometry": {"coordinates":[7.508395195,46.0821838379],"type":"Point"}
}