{
  "type": "Feature",
  "properties": {
    "iso:country":"CH",
    "sg:address":"Rue D'italie 35",
    "sg:city":"Vevey",
    "sg:orig_category":"Detailhandel mit Geschenkartikeln U Souvenirs",
    "sg:phone":"+41 81 413 03 90",
    "sg:postcode":"1800",
    "sg:province":"Vaud",
    "wof:name":"Franco Moro The Davoser",
    "wof:placetype":"venue"
},
  "geometry": {"coordinates":[9.8215179443,46.7958564758],"type":"Point"}
}