{
  "type": "Feature",
  "properties": {
    "iso:country":"CH",
    "sg:address":"Rosswiesstrasse 25",
    "sg:city":"Bubikon",
    "sg:orig_category":"Offsetdruck Sonstiges Druckgewerbe",
    "sg:phone":"+41 31 964 01 54",
    "sg:postcode":"8608",
    "sg:province":"Z\u00fcrich",
    "wof:name":"Benno Sachs Copy Quick",
    "wof:placetype":"venue"
},
  "geometry": {"coordinates":[7.4720258713,46.9537391663],"type":"Point"}
}