{
  "type": "Feature",
  "properties": {
    "iso:country":"CH",
    "sg:address":"Kyburgerstrasse 15 5000 Aarau. Postfach",
    "sg:city":"Aarau",
    "sg:classifiers":[
        {
            "category":"Insurance",
            "subcategory":"Insurance Agent",
            "type":"Services"
        }
    ],
    "sg:phone":"+41 62 836 81 81",
    "sg:postcode":"5001",
    "sg:province":"Aargau",
    "sg:tags":[
        "versicherungsagenturen",
        "-broker"
    ],
    "wof:name":"Eidg.invalidenversicherung",
    "wof:placetype":"venue"
},
  "geometry": {"coordinates":[8.0486564636,47.3829994202],"type":"Point"}
}