{
  "type": "Feature",
  "properties": {
    "addr:full":"Im Seewadel 17 R\u00fcschlikon Z\u00fcrich 8803",
    "addr:housenumber":"17",
    "addr:postcode":"8803",
    "addr:street":"Im Seewadel;Zuerich",
    "iso:country":"CH",
    "sg:address":"Im Seewadel 17",
    "sg:city":"R\u00fcschlikon",
    "sg:orig_category":"Allgemeiner Hoch U Tiefbau",
    "sg:phone":"+41 17209212",
    "sg:postcode":"8803",
    "sg:province":"Z\u00fcrich",
    "wof:name":"Schildknecht Bauleitungen + Generalunternehmung",
    "wof:placetype":"venue"
},
  "geometry": {"coordinates":[8.55375,47.301003],"type":"Point"}
}