{
  "type": "Feature",
  "properties": {
    "iso:country":"CH",
    "sg:address":"Obstgartenstrasse 7",
    "sg:city":"Oberembrach",
    "sg:orig_category":"Handelsvermittlung U Grosshandel Herstellung von sonstigen chemischen Erzeugnissen",
    "sg:phone":"+41 18652137",
    "sg:postcode":"8425",
    "sg:province":"Z\u00fcrich",
    "wof:name":"Faeka Zivilschutzeinrichtungen Martin & Silvia Zollinger",
    "wof:placetype":"venue"
},
  "geometry": {"coordinates":[8.6198406219,47.4885482788],"type":"Point"}
}