{
  "type": "Feature",
  "properties": {
    "iso:country":"CH",
    "sg:address":"Unterdorfstrasse 25",
    "sg:city":"Berikon",
    "sg:orig_category":"Herstellung von Mess U Kontrollinstrumenten U vorrichtungen",
    "sg:phone":"+41 56 631 68 68",
    "sg:postcode":"8965",
    "sg:province":"Aargau",
    "wof:name":"Delco Controls Ag",
    "wof:placetype":"venue"
},
  "geometry": {"coordinates":[8.375246048,47.3503417969],"type":"Point"}
}