{
  "type": "Feature",
  "properties": {
    "iso:country":"CH",
    "sg:address":"Olivenweg 50",
    "sg:city":"Bern",
    "sg:orig_category":"Softwareentwicklung U beratung",
    "sg:postcode":"3018",
    "sg:province":"Bern",
    "wof:name":"Computerxpert Pischedda",
    "wof:placetype":"venue"
},
  "geometry": {"coordinates":[7.3889670372,46.9408226013],"type":"Point"}
}