{
  "type": "Feature",
  "properties": {
    "iso:country":"CH",
    "sg:address":"Effingerstrasse 8 3011 Bern. Postfach 7948",
    "sg:city":"Bern",
    "sg:orig_category":"Interessenvertretungen",
    "sg:phone":"+41 52 233 35 25",
    "sg:postcode":"3001",
    "sg:province":"Bern",
    "wof:name":"Swissrail Export Association",
    "wof:placetype":"venue"
},
  "geometry": {"coordinates":[7.4363241196,46.9459381104],"type":"Point"}
}