{
  "type": "Feature",
  "properties": {
    "iso:country":"CH",
    "sg:address":"6461",
    "sg:city":"Isenthal",
    "sg:orig_category":"Primarschulen",
    "sg:phone":"+41 41 878 10 05",
    "sg:postcode":"6461",
    "sg:province":"Uri",
    "wof:name":"Primarschule",
    "wof:placetype":"venue"
},
  "geometry": {"coordinates":[8.564499855,46.9107208252],"type":"Point"}
}