{
  "type": "Feature",
  "properties": {
    "iso:country":"CH",
    "sg:address":"Route De Vevey 105",
    "sg:city":"Ch\u00e2tel-st-denis",
    "sg:orig_category":"Elektro- and elektronische Maschinen Grosshandel",
    "sg:phone":"+41 21 948 08 80",
    "sg:postcode":"1618",
    "sg:province":"Fribourg",
    "wof:name":"Opto Logic Sa Composants \u00e9lectroniques",
    "wof:placetype":"venue"
},
  "geometry": {"coordinates":[6.8994212151,46.52318573],"type":"Point"}
}