{
  "type": "Feature",
  "properties": {
    "iso:country":"CH",
    "sg:address":"5607",
    "sg:city":"H\u00e4gglingen",
    "sg:orig_category":"Bezirks, Sekundar, Realschulen, Oberstufe der Primarschulen",
    "sg:phone":"+41 56 554 42 56",
    "sg:postcode":"5607",
    "sg:province":"Aargau",
    "wof:name":"Sekundarschule",
    "wof:placetype":"venue"
},
  "geometry": {"coordinates":[8.34098,47.274239],"type":"Point"}
}