{
  "type": "Feature",
  "properties": {
    "iso:country":"CH",
    "sg:address":"K\u00fchboden",
    "sg:city":"Fiesch",
    "sg:orig_category":"RESTAURANTS: TEA-ROOMS",
    "sg:phone":"+41 27 971 24 76",
    "sg:postcode":"3984",
    "sg:province":"Valais",
    "wof:name":"Holzer Hans, Restaurant Bergfreund",
    "wof:placetype":"venue"
},
  "geometry": {"coordinates":[8.1005601883,46.4109344482],"type":"Point"}
}