{
  "type": "Feature",
  "properties": {
    "iso:country":"CH",
    "sg:address":"Bettenstrasse 31",
    "sg:city":"Istighofen",
    "sg:orig_category":"Wirtschaftsverb\u00e4nde Gewerbeverb\u00e4nde/-vereine",
    "sg:phone":"+41 71 622 63 10",
    "sg:postcode":"8575",
    "sg:province":"Thurgau",
    "wof:name":"Gewerbeverein B\u00fcrglen Tg Pr\u00e4s.herrn J\u00fcrg Engler",
    "wof:placetype":"venue"
},
  "geometry": {"coordinates":[9.1468887329,47.5428733826],"type":"Point"}
}