{
  "type": "Feature",
  "properties": {
    "iso:country":"CH",
    "sg:address":"Martinsacker",
    "sg:city":"Niederbipp",
    "sg:orig_category":"Landw. Genossenschaften Viehzucht",
    "sg:phone":"+41 71 971 19 34",
    "sg:postcode":"4704",
    "sg:province":"Bern",
    "wof:name":"Braunviehzuchtgenossenschaft Oberhofen O.roggensinger",
    "wof:placetype":"venue"
},
  "geometry": {"coordinates":[8.9748058319,47.4660263062],"type":"Point"}
}