{
  "type": "Feature",
  "properties": {
    "iso:country":"CH",
    "sg:address":"Speerstrasse 24",
    "sg:city":"Horgen",
    "sg:orig_category":"Erschliessung von Grundst\u00fccken",
    "sg:phone":"+41 17250846",
    "sg:postcode":"8810",
    "sg:province":"Z\u00fcrich",
    "wof:name":"Baugenossenschaft Tannenbach",
    "wof:placetype":"venue"
},
  "geometry": {"coordinates":[8.5831975937,47.2666053772],"type":"Point"}
}