{
  "type": "Feature",
  "properties": {
    "iso:country":"CH",
    "sg:address":"Turnhallenweg 9 8803 R\u00fcschlikon. Postfach 323",
    "sg:city":"R\u00fcschlikon",
    "sg:orig_category":"Detailhandel mit Schuhen U Lederwaren Herstellung von Reiseartikeln, Leder U Sattlerwaren",
    "sg:phone":"+41 17241766",
    "sg:postcode":"8803",
    "sg:province":"Z\u00fcrich",
    "wof:name":"Salko Lederwaren Ag",
    "wof:placetype":"venue"
},
  "geometry": {"coordinates":[8.5558004379,47.3076934814],"type":"Point"}
}