{
  "type": "Feature",
  "properties": {
    "iso:country":"CH",
    "sg:address":"Wasgenring 74",
    "sg:city":"Basel",
    "sg:orig_category":"Vereine Gesang",
    "sg:phone":"+41 61 382 13 66",
    "sg:postcode":"4055",
    "sg:province":"Basel-Stadt",
    "wof:name":"M\u00e4nnerchor Frohsinn",
    "wof:placetype":"venue"
},
  "geometry": {"coordinates":[7.5641551018,47.5611610413],"type":"Point"}
}