{
  "type": "Feature",
  "properties": {
    "iso:country":"CH",
    "sg:address":"Chemin Du Guinchet",
    "sg:city":"Collombey",
    "sg:orig_category":"Malerei Stukkateurgewerbe, Gipserei U Verputzerei",
    "sg:postcode":"1868",
    "sg:province":"Valais",
    "wof:name":"Kilian Maurer Gypserie Peinture",
    "wof:placetype":"venue"
},
  "geometry": {"coordinates":[6.9468150139,46.2744865417],"type":"Point"}
}