{
  "type": "Feature",
  "properties": {
    "iso:country":"CH",
    "sg:address":"Via Carducci 1 6900 Lugano. Postfach Caselle Postale 3251",
    "sg:city":"Lugano",
    "sg:orig_category":"Advokaturb\u00fcros Notariate",
    "sg:phone":"+41 91 922 74 52",
    "sg:postcode":"6901",
    "sg:province":"Ticino",
    "wof:name":"Marco Piotrkowski Studio Legale & Notarile",
    "wof:placetype":"venue"
},
  "geometry": {"coordinates":[8.953021,46.005226],"type":"Point"}
}