{
  "type": "Feature",
  "properties": {
    "iso:country":"CH",
    "sg:address":"Dorfstrasse 7",
    "sg:city":"Oberengstringen",
    "sg:orig_category":"Markt U Meinungsforschung",
    "sg:postcode":"8102",
    "sg:province":"Z\u00fcrich",
    "wof:name":"Muther Marketing + Management",
    "wof:placetype":"venue"
},
  "geometry": {"coordinates":[8.4591751099,47.406211853],"type":"Point"}
}