{
  "type": "Feature",
  "properties": {
    "iso:country":"CH",
    "sg:address":"Route De Pr\u00e9jeux 16",
    "sg:city":"Sion",
    "sg:orig_category":"Unclassifiable Establishments",
    "sg:postcode":"1950",
    "sg:province":"Valais",
    "wof:name":"Hostettler Bernard",
    "wof:placetype":"venue"
},
  "geometry": {"coordinates":[6.5818691254,46.538734436],"type":"Point"}
}