{
  "type": "Feature",
  "properties": {
    "iso:country":"CH",
    "sg:address":"Bolligenstrasse 30b",
    "sg:city":"Bern",
    "sg:orig_category":"Non-Classified Establishments",
    "sg:postcode":"3006",
    "sg:province":"Bern",
    "wof:name":"Grunder R. Communication Consult",
    "wof:placetype":"venue"
},
  "geometry": {"coordinates":[7.4663510323,46.9535598755],"type":"Point"}
}