{
  "type": "Feature",
  "properties": {
    "addr:full":"Piazza G. Pedrazzini 7a Locarno Ticino 6600",
    "addr:housenumber":"7a",
    "addr:postcode":"6600",
    "addr:street":"Piazza G. Pedrazzini;Ticino",
    "iso:country":"CH",
    "sg:address":"Piazza G. Pedrazzini 7a",
    "sg:city":"Locarno",
    "sg:orig_category":"Advokaturb\u00fcros Notariate",
    "sg:phone":"+41 91 751 74 52",
    "sg:postcode":"6600",
    "sg:province":"Ticino",
    "wof:name":"Dott.candido Lanini Studio Legale & Notarile",
    "wof:placetype":"venue"
},
  "geometry": {"coordinates":[8.799135,46.166924],"type":"Point"}
}