{
  "type": "Feature",
  "properties": {
    "iso:country":"CH",
    "sg:address":"Zugerbergstrasse 21 6300 Zug. Postfach",
    "sg:city":"Zug",
    "sg:orig_category":"Unclassifiable Establishments",
    "sg:postcode":"6300",
    "sg:province":"Zug",
    "wof:name":"Loyalty Holding Ag Beteiligungen Usw",
    "wof:placetype":"venue"
},
  "geometry": {"coordinates":[8.5192527771,47.1588058472],"type":"Point"}
}