{
  "type": "Feature",
  "properties": {
    "iso:country":"CH",
    "sg:address":"Steinerstrasse 10",
    "sg:city":"Diessenhofen",
    "sg:orig_category":"Verwaltung der Rechtspflege, Gerichte",
    "sg:phone":"+41 71 477 20 40",
    "sg:postcode":"8253",
    "sg:province":"Thurgau",
    "wof:name":"Grundbuchamt & Notariat Kreis Egnach",
    "wof:placetype":"venue"
},
  "geometry": {"coordinates":[9.3702707291,47.5288734436],"type":"Point"}
}