{
  "type": "Feature",
  "properties": {
    "iso:country":"CH",
    "sg:address":"Chemin Des Sauges 1",
    "sg:city":"Lausanne",
    "sg:orig_category":"Instandhaltung U Reparatur von Automobilen",
    "sg:phone":"+41 21 646 70 57",
    "sg:postcode":"1018",
    "sg:province":"Vaud",
    "wof:name":"Garage De La Bl\u00e9cherette Sa",
    "wof:placetype":"venue"
},
  "geometry": {"coordinates":[6.6207537651,46.5408325195],"type":"Point"}
}