{
  "type": "Feature",
  "properties": {
    "iso:country":"CH",
    "sg:address":"St. Niklausstrasse 20",
    "sg:city":"Solothurn",
    "sg:orig_category":"Non-Classified Establishments",
    "sg:postcode":"4500",
    "sg:province":"Solothurn",
    "wof:name":"Casaport Gmbh",
    "wof:placetype":"venue"
},
  "geometry": {"coordinates":[7.5411581993,47.2131767273],"type":"Point"}
}