{
  "type": "Feature",
  "properties": {
    "iso:country":"CH",
    "sg:address":"Dorfstrasse 37",
    "sg:city":"Hilterfingen",
    "sg:classifiers":[
        {
            "category":"Food & Beverages",
            "subcategory":"Fruits & Vegetables",
            "type":"Retail Goods"
        }
    ],
    "sg:phone":"+41 33 243 23 23",
    "sg:postcode":"3652",
    "sg:province":"Bern",
    "sg:tags":[
        "flower",
        "seed"
    ],
    "wof:name":"Rudolf Roggli Ag",
    "wof:placetype":"venue"
},
  "geometry": {"coordinates":[7.658502,46.737171],"type":"Point"}
}