{
  "type": "Feature",
  "properties": {
    "iso:country":"CH",
    "sg:address":"7504",
    "sg:city":"Pontresina",
    "sg:orig_category":"Bezirks, Sekundar, Realschulen, Oberstufe der Primarschulen",
    "sg:phone":"+41 81 842 75 16",
    "sg:postcode":"7504",
    "sg:province":"Graubunden",
    "wof:name":"Sekundarschule",
    "wof:placetype":"venue"
},
  "geometry": {"coordinates":[9.90191,46.493515],"type":"Point"}
}