{
  "type": "Feature",
  "properties": {
    "iso:country":"CH",
    "sg:address":"Thurgauerstrasse 16",
    "sg:city":"Rorschach",
    "sg:orig_category":"Softwareentwicklung U beratung",
    "sg:phone":"+41 71 841 66 60",
    "sg:postcode":"9400",
    "sg:province":"St. Gallen",
    "wof:name":"Btm Computer Barbieri + Co",
    "wof:placetype":"venue"
},
  "geometry": {"coordinates":[9.4877233505,47.4794960022],"type":"Point"}
}