{
  "type": "Feature",
  "properties": {
    "iso:country":"CH",
    "sg:address":"Kindergartenstrasse 4",
    "sg:city":"Seon",
    "sg:orig_category":"Vorschulen, Kinderg\u00e4rten",
    "sg:phone":"+41 62 775 25 08",
    "sg:postcode":"5703",
    "sg:province":"Aargau",
    "wof:name":"Kindergarten Unterdorf",
    "wof:placetype":"venue"
},
  "geometry": {"coordinates":[8.1601333618,47.3478088379],"type":"Point"}
}