{
  "type": "Feature",
  "properties": {
    "iso:country":"CH",
    "sg:address":"Sources Chemin Des",
    "sg:city":"F\u00e9chy",
    "sg:orig_category":"Finanzierungsinstitutionen",
    "sg:phone":"+41 21 807 12 41",
    "sg:postcode":"1173",
    "sg:province":"Vaud",
    "wof:name":"Schilter Yves Finance",
    "wof:placetype":"venue"
},
  "geometry": {"coordinates":[6.3701400757,46.4815368652],"type":"Point"}
}