{
  "type": "Feature",
  "properties": {
    "iso:country":"CH",
    "sg:address":"Rue Neuch\u00e2tel 1",
    "sg:city":"Yverdon",
    "sg:classifiers":[
        {
            "category":"Banks & Credit Unions",
            "subcategory":"Bank",
            "type":"Services"
        }
    ],
    "sg:phone":"+41 24 423 32 33",
    "sg:postcode":"1400",
    "sg:province":"Vaud",
    "wof:name":"Union De Banques Suisses",
    "wof:placetype":"venue"
},
  "geometry": {"coordinates":[6.670759,46.781742],"type":"Point"}
}