{
  "type": "Feature",
  "properties": {
    "iso:country":"CH",
    "sg:address":"Dorfplatz",
    "sg:city":"Wildhaus",
    "sg:orig_category":"Detailhandel mit Waren verschiedener Art, Hauptrichtung Nahrungsmittel",
    "sg:phone":"+41 71 999 11 53",
    "sg:postcode":"9658",
    "sg:province":"St. Gallen",
    "wof:name":"Coop Ostschweiz",
    "wof:placetype":"venue"
},
  "geometry": {"coordinates":[9.351433754,47.2034492493],"type":"Point"}
}