{
  "type": "Feature",
  "properties": {
    "iso:country":"CH",
    "sg:address":"Sur-le-bontenier 31",
    "sg:city":"Courgenay",
    "sg:orig_category":"Schlossereien Stahl U Leichtmetallbau",
    "sg:phone":"+41 21 634 60 45",
    "sg:postcode":"2950",
    "sg:province":"Jura",
    "wof:name":"Fl Metallerie S\u00e0rl Constr.m\u00e9talliques-ferronnerie",
    "wof:placetype":"venue"
},
  "geometry": {"coordinates":[6.5931801796,46.5288963318],"type":"Point"}
}