{
  "type": "Feature",
  "properties": {
    "iso:country":"CH",
    "sg:address":"R\u00fctistrasse 6060 Sarnen. Postfach 1464",
    "sg:city":"Sarnen",
    "sg:classifiers":[
        {
            "category":"Education",
            "subcategory":"Vocational School",
            "type":"Public Place"
        }
    ],
    "sg:phone":"+41 71 911 90 94",
    "sg:postcode":"6060",
    "sg:province":"Obwalden",
    "sg:tags":[
        "koch-",
        "haushaltschulen"
    ],
    "wof:name":"Kochschule Bissfest",
    "wof:placetype":"venue"
},
  "geometry": {"coordinates":[9.047492981,47.465221405],"type":"Point"}
}