{
  "type": "Feature",
  "properties": {
    "iso:country":"CH",
    "sg:address":"Ancienne Boucherie",
    "sg:city":"Borex",
    "sg:orig_category":"Detailhandel mit Waren verschiedener Art, Hauptrichtung Nahrungsmittel",
    "sg:postcode":"1277",
    "sg:province":"Vaud",
    "wof:name":"Borex Poissons - Crottet Jean-bernard Et Claus Larsen",
    "wof:placetype":"venue"
},
  "geometry": {"coordinates":[6.1765651703,46.3785209656],"type":"Point"}
}