{
  "type": "Feature",
  "properties": {
    "iso:country":"CH",
    "sg:address":"7742 Poschiavo. Postfach",
    "sg:city":"Poschiavo",
    "sg:orig_category":"Detailhandel mit Waren verschiedener Art, Hauptrichtung Nahrungsmittel",
    "sg:postcode":"7742",
    "sg:province":"Graubunden",
    "wof:name":"Bongel Sa",
    "wof:placetype":"venue"
},
  "geometry": {"coordinates":[6.1341581345,46.1822624207],"type":"Point"}
}