{
  "type": "Feature",
  "properties": {
    "iso:country":"CH",
    "sg:address":"Pr\u00e9-polly Chemin De 14 1233 Bernex. Postfach",
    "sg:city":"Bernex",
    "sg:orig_category":"Sonstiger spezialisierter Hoch U Tiefbau",
    "sg:postcode":"1233",
    "sg:province":"Gen\u00e8ve",
    "wof:name":"Goldie Olivier",
    "wof:placetype":"venue"
},
  "geometry": {"coordinates":[6.8592319489,46.458026886],"type":"Point"}
}