{
  "type": "Feature",
  "properties": {
    "iso:country":"CH",
    "sg:address":"6562",
    "sg:city":"Soazza",
    "sg:orig_category":"Allgemeiner Hoch U Tiefbau",
    "sg:postcode":"6562",
    "sg:province":"Graubunden",
    "wof:name":"Ferrari E Toschini.",
    "wof:placetype":"venue"
},
  "geometry": {"coordinates":[9.22181,46.365547],"type":"Point"}
}