{
  "type": "Feature",
  "properties": {
    "iso:country":"CH",
    "sg:address":"Place De La Poste 6",
    "sg:city":"Develier",
    "sg:orig_category":"Schlossereien",
    "sg:phone":"+41 32 423 10 39",
    "sg:postcode":"2802",
    "sg:province":"Jura",
    "wof:name":"Reynold Mertenat Serrurerie",
    "wof:placetype":"venue"
},
  "geometry": {"coordinates":[7.296423912,47.3581047058],"type":"Point"}
}