{
  "type": "Feature",
  "properties": {
    "iso:country":"CH",
    "sg:address":"Buch 455",
    "sg:city":"Egnach",
    "sg:orig_category":"Herstellung von keramischen Wand U Bodenfliesen U platten Verlegen von Fliesen U Platten",
    "sg:phone":"+41 71 477 15 22",
    "sg:postcode":"9322",
    "sg:province":"Thurgau",
    "wof:name":"Bruno De Boni Plattenbel\u00e4ge Chemin\u00e9es",
    "wof:placetype":"venue"
},
  "geometry": {"coordinates":[9.383805275,47.5392799377],"type":"Point"}
}