{
  "type": "Feature",
  "properties": {
    "iso:country":"CH",
    "sg:address":"Gampelengasse 19",
    "sg:city":"Ins",
    "sg:orig_category":"Detailhandel mit M\u00f6beln Verlegen von Fussboden",
    "sg:postcode":"3232",
    "sg:province":"Bern",
    "wof:name":"Hurni, Gerhard",
    "wof:placetype":"venue"
},
  "geometry": {"coordinates":[7.1002030373,47.0058479309],"type":"Point"}
}