{
  "type": "Feature",
  "properties": {
    "iso:country":"CH",
    "sg:address":"Haldenweid 25",
    "sg:city":"Schenkon",
    "sg:orig_category":"Vermietung U Verpachtung von eigenen Immobilien",
    "sg:postcode":"6214",
    "sg:province":"Luzern",
    "wof:name":"Objektiva Ag",
    "wof:placetype":"venue"
},
  "geometry": {"coordinates":[8.1363801956,47.1822814941],"type":"Point"}
}