{
  "type": "Feature",
  "properties": {
    "iso:country":"CH",
    "sg:address":"Allmeindstrasse 16",
    "sg:city":"Rothenthurm",
    "sg:orig_category":"Zahnarztpraxen",
    "sg:phone":"+41 41 838 15 30",
    "sg:postcode":"6418",
    "sg:province":"Schwyz",
    "wof:name":"Dr.med.dent. Johann Baer Zahnarzt",
    "wof:placetype":"venue"
},
  "geometry": {"coordinates":[8.6800498962,47.1103591919],"type":"Point"}
}