{
  "type": "Feature",
  "properties": {
    "iso:country":"CH",
    "sg:address":"Bahnhofstrasse 82",
    "sg:city":"Schwyz",
    "sg:orig_category":"Zahnarztpraxen",
    "sg:phone":"+41 41 811 53 53",
    "sg:postcode":"6430",
    "sg:province":"Schwyz",
    "wof:name":"Dr. Med. Dent. Arnold Von Euw Zahnarzt",
    "wof:placetype":"venue"
},
  "geometry": {"coordinates":[8.639632225,47.0232658386],"type":"Point"}
}