{
  "type": "Feature",
  "properties": {
    "iso:country":"CH",
    "sg:address":"Hauptstrasse 1",
    "sg:city":"Hermrigen",
    "sg:orig_category":"Sportvereine Triathlon Laufen, Schwimmen, Velo",
    "sg:postcode":"3274",
    "sg:province":"Bern",
    "wof:name":"Tri Team Bern",
    "wof:placetype":"venue"
},
  "geometry": {"coordinates":[7.3815188408,46.9263648987],"type":"Point"}
}