{
  "type": "Feature",
  "properties": {
    "iso:country":"CH",
    "sg:address":"Opfikonerstrasse 63 8304 Wallisellen. Postfach",
    "sg:city":"Wallisellen",
    "sg:orig_category":"Sonstige mit der Informatik verbundene T\u00e4tigkeiten",
    "sg:phone":"+41 18310931",
    "sg:postcode":"8304",
    "sg:province":"Z\u00fcrich",
    "wof:name":"Edv-beratung Und Support Edgar Tibolla",
    "wof:placetype":"venue"
},
  "geometry": {"coordinates":[8.5811481476,47.4193611145],"type":"Point"}
}