{
  "type": "Feature",
  "properties": {
    "iso:country":"CH",
    "sg:address":"Laupenstrasse 27 3008 Bern. Postfach",
    "sg:city":"Bern",
    "sg:orig_category":"Unclassifiable Establishments",
    "sg:postcode":"3005",
    "sg:province":"Bern",
    "wof:name":"Amaya Beteiligungen Usw",
    "wof:placetype":"venue"
},
  "geometry": {"coordinates":[7.4326701164,46.9474182129],"type":"Point"}
}