{
  "type": "Feature",
  "properties": {
    "iso:country":"CH",
    "sg:address":"5400 Baden. Postfach 146",
    "sg:city":"Baden",
    "sg:orig_category":"Non-Classified Establishments",
    "sg:postcode":"5401",
    "sg:province":"Aargau",
    "wof:name":"Bip Baden Berufsintegrationsprogramm",
    "wof:placetype":"venue"
},
  "geometry": {"coordinates":[8.2923898697,47.4712409973],"type":"Point"}
}