{
  "type": "Feature",
  "properties": {
    "iso:country":"CH",
    "sg:address":"C\u00f4tes-de-montbenon Rue 8 1003 Lausanne. Postfach",
    "sg:city":"Gen\u00e8ve",
    "sg:orig_category":"Non-Classified Establishments",
    "sg:postcode":"1201",
    "sg:province":"Gen\u00e8ve",
    "wof:name":"Lysis Trading S.a.",
    "wof:placetype":"venue"
},
  "geometry": {"coordinates":[6.6281709671,46.5209388733],"type":"Point"}
}