{
  "type": "Feature",
  "properties": {
    "iso:country":"CH",
    "sg:address":"Motta Via Giuseppe 23",
    "sg:city":"Mendrisio",
    "sg:orig_category":"Markt U Meinungsforschung",
    "sg:phone":"+41 91 646 92 82",
    "sg:postcode":"6850",
    "sg:province":"Ticino",
    "wof:name":"Bmc Biomedical Consult Sa",
    "wof:placetype":"venue"
},
  "geometry": {"coordinates":[8.9819288254,45.8682098389],"type":"Point"}
}