{
  "type": "Feature",
  "properties": {
    "iso:country":"CH",
    "sg:address":"Oberebnet",
    "sg:city":"Adligenswil",
    "sg:orig_category":"Herstellung von Metallkonstruktionen",
    "sg:postcode":"6043",
    "sg:province":"Luzern",
    "wof:name":"Banz F. - Montage - Technische Arbeiten - Gartenbau",
    "wof:placetype":"venue"
},
  "geometry": {"coordinates":[8.3629655838,47.0713844299],"type":"Point"}
}