{
  "type": "Feature",
  "properties": {
    "iso:country":"CH",
    "sg:address":"3946",
    "sg:city":"Turtmann",
    "sg:orig_category":"Vereine Gesang",
    "sg:postcode":"3946",
    "sg:province":"Valais",
    "wof:name":"M\u00e4nnerchor Turtmann",
    "wof:placetype":"venue"
},
  "geometry": {"coordinates":[7.7031202316,46.3017997742],"type":"Point"}
}