{
  "type": "Feature",
  "properties": {
    "iso:country":"CH",
    "sg:address":"Rue Du Dr Ti\u00e8che 12",
    "sg:city":"Reconvilier",
    "sg:orig_category":"Landesverteidigung, Sozialversicherung \u00d6ffentliche Verwaltung",
    "sg:phone":"+41 79 425 95 30",
    "sg:postcode":"2732",
    "sg:province":"Bern",
    "wof:name":"Centre De Protection Civile",
    "wof:placetype":"venue"
},
  "geometry": {"coordinates":[6.7714600563,46.5960960388],"type":"Point"}
}