{
  "type": "Feature",
  "properties": {
    "iso:country":"CH",
    "sg:address":"Dorfstrasse 28",
    "sg:city":"M\u00fchlethurnen",
    "sg:orig_category":"Massagestudios",
    "sg:phone":"+41 31 809 23 24",
    "sg:postcode":"3127",
    "sg:province":"Bern",
    "wof:name":"Beat Weisskopf & Erika Gr\u00e4del Massage-praxis",
    "wof:placetype":"venue"
},
  "geometry": {"coordinates":[7.5057001114,46.8165359497],"type":"Point"}
}