{
  "type": "Feature",
  "properties": {
    "iso:country":"CH",
    "sg:address":"Route De Couvet 8",
    "sg:city":"Boveresse",
    "sg:orig_category":"Sportschulen Wassersport",
    "sg:phone":"+41 32 861 36 02",
    "sg:postcode":"2113",
    "sg:province":"Neuch\u00e2tel",
    "wof:name":"Hydrotec Ecole De Plong\u00e9e",
    "wof:placetype":"venue"
},
  "geometry": {"coordinates":[6.6015949249,46.917755127],"type":"Point"}
}