{
  "type": "Feature",
  "properties": {
    "iso:country":"CH",
    "sg:address":"Uferstrasse 12",
    "sg:city":"F\u00fcllinsdorf",
    "sg:orig_category":"Non-Classified Establishments",
    "sg:phone":"+41 61 901 39 89",
    "sg:postcode":"4414",
    "sg:province":"Basel-Landschaft",
    "wof:name":"Waldag Holding Ag",
    "wof:placetype":"venue"
},
  "geometry": {"coordinates":[7.724421978,47.5116767883],"type":"Point"}
}