{
  "type": "Feature",
  "properties": {
    "iso:country":"CH",
    "sg:address":"Hirschengraben 19 6003 Luzern. Postfach",
    "sg:city":"Luzern",
    "sg:orig_category":"Verwaltung der Rechtspflege, Gerichte",
    "sg:phone":"+41 41 228 51 11",
    "sg:postcode":"6002",
    "sg:province":"Luzern",
    "wof:name":"Kantonales Verwaltungsgericht",
    "wof:placetype":"venue"
},
  "geometry": {"coordinates":[8.3028335571,47.0488433838],"type":"Point"}
}