{
  "type": "Feature",
  "properties": {
    "iso:country":"CH",
    "sg:address":"Ladhuebstrasse 15",
    "sg:city":"Wittenbach",
    "sg:orig_category":"Kunsthandel",
    "sg:phone":"+41 71 298 41 11",
    "sg:postcode":"9303",
    "wof:name":"Josef John Galerie",
    "wof:placetype":"venue"
},
  "geometry": {"coordinates":[9.3707313538,47.4626464844],"type":"Point"}
}