{
  "type": "Feature",
  "properties": {
    "iso:country":"CH",
    "sg:address":"Sch\u00fcrmattstrasse 4",
    "sg:city":"Villigen",
    "sg:orig_category":"Pensionskassen",
    "sg:phone":"+41 55 451 91 11",
    "sg:postcode":"5234",
    "sg:province":"Aargau",
    "wof:name":"Personalf\u00fcrsorgestiftung Der Firma Est\u00e9e Lauder Ag Lachen",
    "wof:placetype":"venue"
},
  "geometry": {"coordinates":[8.8615226746,47.1878585815],"type":"Point"}
}