{
  "type": "Feature",
  "properties": {
    "iso:country":"CH",
    "sg:address":"Stadthausstrasse 6",
    "sg:city":"Huttwil",
    "sg:orig_category":"Sportvereine Turnen",
    "sg:phone":"+41 62 962 37 70",
    "sg:postcode":"4950",
    "sg:province":"Bern",
    "wof:name":"Turnverein Huttwil",
    "wof:placetype":"venue"
},
  "geometry": {"coordinates":[7.8481030464,47.1133613586],"type":"Point"}
}