{
  "type": "Feature",
  "properties": {
    "iso:country":"CH",
    "sg:address":"8261",
    "sg:city":"Hemishofen",
    "sg:orig_category":"Schulpflegen",
    "sg:phone":"+41 52 741 21 90",
    "sg:postcode":"8261",
    "sg:province":"Schaffhausen",
    "wof:name":"Schulrat Der Gemeinde Hemishofen",
    "wof:placetype":"venue"
},
  "geometry": {"coordinates":[8.8312530518,47.6779136658],"type":"Point"}
}