{
  "type": "Feature",
  "properties": {
    "iso:country":"CH",
    "sg:address":"Hinterhostattstrasse 4",
    "sg:city":"Emmetten",
    "sg:orig_category":"Herstellung von sonstigen Maschinen f\u00fcr unspezifische Verwendung",
    "sg:phone":"+41 41 622 13 13",
    "sg:postcode":"6376",
    "sg:province":"Nidwalden",
    "wof:name":"Anlagebau & Managementsystem Ag",
    "wof:placetype":"venue"
},
  "geometry": {"coordinates":[8.514591217,46.9559402466],"type":"Point"}
}