{
  "type": "Feature",
  "properties": {
    "iso:country":"CH",
    "sg:address":"Tisserands Rue Des 2",
    "sg:city":"Moudon",
    "sg:orig_category":"Herstellung von Teilen U Zubeh\u00f6r f\u00fcr Automobile",
    "sg:postcode":"1510",
    "sg:province":"Vaud",
    "wof:name":"Cs Tuning, Da Silveira Carlos Costa",
    "wof:placetype":"venue"
},
  "geometry": {"coordinates":[6.7990322113,46.6696586609],"type":"Point"}
}