{
  "type": "Feature",
  "properties": {
    "iso:country":"CH",
    "sg:address":"Route De Vissigen 18",
    "sg:city":"Sion",
    "sg:orig_category":"Herstellung von Karosserien U Anh\u00e4ngern",
    "sg:phone":"+41 27 203 32 32",
    "sg:postcode":"1950",
    "sg:province":"Valais",
    "wof:name":"Carrosserie Roch Henri & Cie",
    "wof:placetype":"venue"
},
  "geometry": {"coordinates":[7.3710808754,46.2299575806],"type":"Point"}
}