{
  "type": "Feature",
  "properties": {
    "iso:country":"CH",
    "sg:address":"3951",
    "sg:city":"Agarn",
    "sg:orig_category":"Herstellung von Karosserien U Anh\u00e4ngern",
    "sg:phone":"+41 27 932 14 96",
    "sg:postcode":"3951",
    "sg:province":"Valais",
    "wof:name":"Traugott Kalbermatten Garage",
    "wof:placetype":"venue"
},
  "geometry": {"coordinates":[7.7611880302,46.3158798218],"type":"Point"}
}