{
  "type": "Feature",
  "properties": {
    "iso:country":"CH",
    "sg:address":"Locarno Via 43",
    "sg:city":"Losone",
    "sg:orig_category":"Detailhandel mit Brot, Back U S\u00fcsswaren",
    "sg:postcode":"6616",
    "sg:province":"Ticino",
    "wof:name":"Panetteria Giordano Alberto",
    "wof:placetype":"venue"
},
  "geometry": {"coordinates":[8.7207,46.146099],"type":"Point"}
}