{
  "type": "Feature",
  "properties": {
    "iso:country":"CH",
    "sg:address":"Herrenacker 13",
    "sg:city":"Schaffhausen",
    "sg:orig_category":"Vermietung U Verpachtung von eigenen Immobilien",
    "sg:phone":"+41 52 624 89 10",
    "sg:postcode":"8200",
    "sg:province":"Schaffhausen",
    "wof:name":"Randenburg-immobilien Ag",
    "wof:placetype":"venue"
},
  "geometry": {"coordinates":[8.6332559586,47.6951751709],"type":"Point"}
}