{
  "type": "Feature",
  "properties": {
    "iso:country":"CH",
    "sg:address":"Mariahilfgasse 7",
    "sg:city":"Luzern",
    "sg:orig_category":"Wohnheime",
    "sg:phone":"+41 41 410 61 61",
    "sg:postcode":"6004",
    "sg:province":"Luzern",
    "wof:name":"Von Tscharner Albert-stiftung",
    "wof:placetype":"venue"
},
  "geometry": {"coordinates":[8.3052978516,47.0535736084],"type":"Point"}
}