{
  "type": "Feature",
  "properties": {
    "iso:country":"CH",
    "sg:address":"Bahnhofstrasse 9",
    "sg:city":"Heimberg",
    "sg:orig_category":"Herstellung von Erzeugnissen aus Beton, Gips U Zement",
    "sg:phone":"+41 33 439 57 57",
    "sg:postcode":"3627",
    "sg:province":"Bern",
    "wof:name":"Rigips Ag Werk Heimberg",
    "wof:placetype":"venue"
},
  "geometry": {"coordinates":[7.606762886,46.7899131775],"type":"Point"}
}