{
  "type": "Feature",
  "properties": {
    "iso:country":"CH",
    "sg:address":"Avenue Vinet 16",
    "sg:city":"Lausanne",
    "sg:orig_category":"P\u00e9dicure",
    "sg:phone":"+41 32 913 18 14",
    "sg:postcode":"1004",
    "sg:province":"Vaud",
    "wof:name":"Fran\u00e7oise Guye Sommer P\u00e9dicure",
    "wof:placetype":"venue"
},
  "geometry": {"coordinates":[6.8245549202,47.1023979187],"type":"Point"}
}