{
  "type": "Feature",
  "properties": {
    "iso:country":"CH",
    "sg:address":"Marktgasse 25",
    "sg:city":"Winterthur",
    "sg:orig_category":"Sonstige Kultur U Unterhaltungseinrichtungen",
    "sg:phone":"+41 52 212 14 96",
    "sg:postcode":"8400",
    "sg:province":"Z\u00fcrich",
    "wof:name":"Ursula Bienz Marionettentheater Im Waaghaus",
    "wof:placetype":"venue"
},
  "geometry": {"coordinates":[8.7291088104,47.4995498657],"type":"Point"}
}