{
  "type": "Feature",
  "properties": {
    "iso:country":"CH",
    "sg:address":"Wil 10",
    "sg:city":"Muotathal",
    "sg:orig_category":"Detailhandel mit Waren verschiedener Art, Hauptrichtung Nahrungsmittel",
    "sg:postcode":"6436",
    "sg:province":"Schwyz",
    "wof:name":"Landwirtschaftliche Genossenschaft Muotathal.",
    "wof:placetype":"venue"
},
  "geometry": {"coordinates":[8.7607250214,46.9768829346],"type":"Point"}
}