{
  "type": "Feature",
  "properties": {
    "iso:country":"CH",
    "sg:address":"Via Penate 7",
    "sg:city":"Mendrisio",
    "sg:orig_category":"Detailhandel mit M\u00f6beln Detailhandel mit M\u00f6beln U Haushaltsgegenst\u00e4nden",
    "sg:phone":"+41 91 646 10 47",
    "sg:postcode":"6850",
    "sg:province":"Ticino",
    "wof:name":"Exp\u00f2 Arredo Sa",
    "wof:placetype":"venue"
},
  "geometry": {"coordinates":[8.9795846939,45.8775634766],"type":"Point"}
}