{
  "type": "Feature",
  "properties": {
    "iso:country":"CH",
    "sg:address":"In Den Klosterreben 9",
    "sg:city":"Basel",
    "sg:classifiers":[
        {
            "category":"Autos & Motor Vehicles",
            "subcategory":"Recreational Vehicle Sales",
            "type":"Retail Goods"
        }
    ],
    "sg:phone":"+41 81 322 81 25",
    "sg:postcode":"4052",
    "sg:province":"Basel-Stadt",
    "sg:tags":[
        "sportvereine",
        "go-kart",
        "kart"
    ],
    "wof:name":"Kart-club Graub\u00fcnden",
    "wof:placetype":"venue"
},
  "geometry": {"coordinates":[9.576338768,46.982383728],"type":"Point"}
}