{
  "type": "Feature",
  "properties": {
    "iso:country":"CH",
    "sg:address":"Molkenstrasse 15",
    "sg:city":"Z\u00fcrich",
    "sg:orig_category":"Datenverarbeitungsdienste Softwareentwicklung U beratung",
    "sg:phone":"+41 12477727",
    "sg:postcode":"8004",
    "sg:province":"Z\u00fcrich",
    "wof:name":"Pv Computing Ag",
    "wof:placetype":"venue"
},
  "geometry": {"coordinates":[8.526576,47.376476],"type":"Point"}
}