{
  "type": "Feature",
  "properties": {
    "iso:country":"CH",
    "sg:address":"Forchstr. 21",
    "sg:city":"Z\u00fcrich",
    "sg:classifiers":[
        {
            "category":"Professional",
            "subcategory":"Business Services",
            "type":"Services"
        }
    ],
    "sg:phone":"+41 21 613 35 70",
    "sg:postcode":"8032",
    "sg:province":"Z\u00fcrich",
    "sg:tags":[
        "body",
        "advice"
    ],
    "wof:name":"Osec Business Network Switzerland",
    "wof:placetype":"venue"
},
  "geometry": {"coordinates":[6.62607,46.510571],"type":"Point"}
}