{
  "type": "Feature",
  "properties": {
    "iso:country":"CH",
    "sg:address":"Le Bourg",
    "sg:city":"Oron-la-ville",
    "sg:classifiers":[
        {
            "category":"Insurance",
            "subcategory":"Insurance Agent",
            "type":"Services"
        }
    ],
    "sg:phone":"+41 21 907 99 55",
    "sg:postcode":"1610",
    "sg:province":"Vaud",
    "sg:tags":[
        "versicherungsagenturen",
        "-broker"
    ],
    "wof:name":"Winterthur Assurances Agence Antoine Bacher",
    "wof:placetype":"venue"
},
  "geometry": {"coordinates":[6.8259868622,46.5721969604],"type":"Point"}
}