{
  "type": "Feature",
  "properties": {
    "iso:country":"CH",
    "sg:address":"Bahnhofstrasse 10",
    "sg:city":"Chur",
    "sg:orig_category":"Unclassifiable Establishments",
    "sg:postcode":"7000",
    "sg:province":"Graubunden",
    "wof:name":"Pegasus Aviation Ltd.",
    "wof:placetype":"venue"
},
  "geometry": {"coordinates":[9.5294218063,46.852722168],"type":"Point"}
}