{
  "type": "Feature",
  "properties": {
    "iso:country":"CH",
    "sg:address":"Les Corsalettes",
    "sg:city":"Corcelles-payerne",
    "sg:orig_category":"Haltung von Schweinen",
    "sg:phone":"+41 26 660 65 91",
    "sg:postcode":"1562",
    "sg:province":"Vaud",
    "wof:name":"Porcherie D'\u00e9levage Cebaco Sa",
    "wof:placetype":"venue"
},
  "geometry": {"coordinates":[6.9837098122,46.8327560425],"type":"Point"}
}