{
  "type": "Feature",
  "properties": {
    "iso:country":"CH",
    "sg:address":"Avenue De B\u00e9thusy 36",
    "sg:city":"Lausanne",
    "sg:orig_category":"Grosshandel mit Schreibwaren, B\u00fcchern U Zeitungen",
    "sg:phone":"+41 21 320 80 57",
    "sg:postcode":"1005",
    "sg:province":"Vaud",
    "wof:name":"Arcadie Diffusion Livres",
    "wof:placetype":"venue"
},
  "geometry": {"coordinates":[6.6463108063,46.5213928223],"type":"Point"}
}