{
  "type": "Feature",
  "properties": {
    "iso:country":"CH",
    "sg:address":"Route De La Gl\u00e2ne 107",
    "sg:city":"Villars-sur-gl\u00e2ne",
    "sg:orig_category":"Architektur U Ingenieurb\u00fcros",
    "sg:phone":"+41 26 402 48 52",
    "sg:postcode":"1752",
    "sg:province":"Fribourg",
    "wof:name":"Duchein Sa",
    "wof:placetype":"venue"
},
  "geometry": {"coordinates":[7.14293,46.791622],"type":"Point"}
}