{
  "type": "Feature",
  "properties": {
    "iso:country":"CH",
    "sg:address":"2735 B\u00e9vilard Case Postale",
    "sg:city":"B\u00e9vilard",
    "sg:orig_category":"Herstellung von Werkzeugen Maschinenbau",
    "sg:phone":"+41 21 922 65 65",
    "sg:postcode":"2735",
    "sg:province":"Bern",
    "wof:name":"Mahon & Fils Sa Machines Outils & Outillage",
    "wof:placetype":"venue"
},
  "geometry": {"coordinates":[6.3048892021,46.3652610779],"type":"Point"}
}