{
  "type": "Feature",
  "properties": {
    "addr:full":"Zollikonstrasse 20 Binz Z\u00fcrich 8122",
    "addr:housenumber":"20",
    "addr:postcode":"8122",
    "addr:street":"Zollikonstrasse",
    "iso:country":"CH",
    "sg:address":"Zollikonstrasse 20",
    "sg:city":"Binz",
    "sg:orig_category":"Architekturb\u00fcros",
    "sg:phone":"+41 33 823 15 31",
    "sg:postcode":"8122",
    "sg:province":"Z\u00fcrich",
    "wof:name":"Ueli Von Allmen Architekturb\u00fcro",
    "wof:placetype":"venue"
},
  "geometry": {"coordinates":[7.867059,46.678864],"type":"Point"}
}