{
  "type": "Feature",
  "properties": {
    "iso:country":"CH",
    "sg:address":"Freilagerstrasse 11",
    "sg:city":"Z\u00fcrich",
    "sg:orig_category":"Bauschreinerei Herstellung von M\u00f6beln verschiedener Art",
    "sg:phone":"+41 14015201",
    "sg:postcode":"8047",
    "sg:province":"Z\u00fcrich",
    "wof:name":"Peter Hanhart Bau-& M\u00f6belschreinerei",
    "wof:placetype":"venue"
},
  "geometry": {"coordinates":[8.492134,47.378334],"type":"Point"}
}