{
  "type": "Feature",
  "properties": {
    "iso:country":"CH",
    "sg:address":"Dornacherstrasse 10 4600 Olten. Postfach",
    "sg:city":"Olten",
    "sg:orig_category":"Reiseb\u00fcros Verkehrsverb\u00e4nde",
    "sg:phone":"+41 62 212 82 32",
    "sg:postcode":"4603",
    "sg:province":"Solothurn",
    "wof:name":"Touring-club Der Schweiz Tcs Gesch\u00e4ftsstelle & Reiseb\u00fcro",
    "wof:placetype":"venue"
},
  "geometry": {"coordinates":[7.9015188217,47.3517456055],"type":"Point"}
}