{
  "type": "Feature",
  "properties": {
    "iso:country":"CH",
    "sg:address":"T\u00f6distrasse 2a",
    "sg:city":"Jona",
    "sg:orig_category":"Herstellung von sonstigen Maschinen f\u00fcr unspezifische Verwendung",
    "sg:postcode":"8645",
    "sg:province":"St. Gallen",
    "wof:name":"Arnold Feuerschutz Total",
    "wof:placetype":"venue"
},
  "geometry": {"coordinates":[8.8333187103,47.2266616821],"type":"Point"}
}