{
  "type": "Feature",
  "properties": {
    "iso:country":"CH",
    "sg:address":"K\u00e4sereistrasse 188 8581 Schocherswil. Postfach",
    "sg:city":"Schocherswil",
    "sg:orig_category":"Instandhaltung U Reparatur von Automobilen",
    "sg:phone":"+41 56 621 95 55",
    "sg:postcode":"8581",
    "sg:province":"Thurgau",
    "wof:name":"Garage Rohrbach Ag",
    "wof:placetype":"venue"
},
  "geometry": {"coordinates":[8.2673177719,47.3608627319],"type":"Point"}
}