{
  "type": "Feature",
  "properties": {
    "iso:country":"CH",
    "sg:address":"Avenue De La Vallombreuse 91",
    "sg:city":"Prilly",
    "sg:orig_category":"Instandhaltung U Reparatur von Automobilen Tankstellen",
    "sg:phone":"+41 21 647 93 93",
    "sg:postcode":"1008",
    "sg:province":"Vaud",
    "wof:name":"Stifani Fr\u00e8res Garage & Station-service",
    "wof:placetype":"venue"
},
  "geometry": {"coordinates":[6.6109161377,46.538772583],"type":"Point"}
}