{
  "type": "Feature",
  "properties": {
    "iso:country":"CH",
    "sg:address":"Reppischtalstrasse 312",
    "sg:city":"Stallikon",
    "sg:orig_category":"Instandhaltung U Reparatur von Automobilen",
    "sg:phone":"+41 17000529",
    "sg:postcode":"8143",
    "sg:province":"Z\u00fcrich",
    "wof:name":"Garage Langenegger Ag",
    "wof:placetype":"venue"
},
  "geometry": {"coordinates":[8.4916152954,47.3151817322],"type":"Point"}
}