{
  "type": "Feature",
  "properties": {
    "iso:country":"CH",
    "sg:address":"Jupiterstrasse 26",
    "sg:city":"Z\u00fcrich",
    "sg:orig_category":"Bauingenieurb\u00fcros Heizung L\u00fcftung Klima Planer f\u00fcr Alternativenergie and Solararchitektur",
    "sg:phone":"+41 41 240 40 20",
    "sg:postcode":"8032",
    "sg:province":"Z\u00fcrich",
    "wof:name":"Rolf M\u00f6sle Ingenieurb\u00fcro",
    "wof:placetype":"venue"
},
  "geometry": {"coordinates":[8.290327,47.057026],"type":"Point"}
}