{
  "type": "Feature",
  "properties": {
    "addr:full":"Rue Du Pasquier 9 Fleurier Neuch\u00e2tel 2114",
    "addr:housenumber":"9",
    "addr:postcode":"2114",
    "addr:street":"Rue Du Pasquier;Fleurier Neucha\u0302Tel",
    "iso:country":"CH",
    "sg:address":"Rue Du Pasquier 9",
    "sg:city":"Fleurier",
    "sg:classifiers":[
        {
            "category":"Education",
            "subcategory":"Library",
            "type":"Public Place"
        }
    ],
    "sg:phone":"+41 32 861 12 72",
    "sg:postcode":"2114",
    "sg:province":"Neuch\u00e2tel",
    "sg:tags":[
        "u",
        "bibliotheken",
        "archive"
    ],
    "wof:name":"Biblioth\u00e8que De La Paroisse \u00e9vang\u00e9lique R\u00e9form\u00e9e",
    "wof:placetype":"venue"
},
  "geometry": {"coordinates":[6.583306,46.900463],"type":"Point"}
}