{
  "type": "Feature",
  "properties": {
    "iso:country":"CH",
    "sg:address":"Schneidersmatt 24a",
    "sg:city":"W\u00fcnnewil",
    "sg:orig_category":"Saunas, Solarien, Fitnesszentren U \u00e4hnliches",
    "sg:postcode":"3184",
    "sg:province":"Fribourg",
    "wof:name":"Sauna-club Miriam",
    "wof:placetype":"venue"
},
  "geometry": {"coordinates":[7.272195816,46.8663978577],"type":"Point"}
}