{
  "type": "Feature",
  "properties": {
    "iso:country":"CH",
    "sg:address":"1352",
    "sg:city":"Agiez",
    "sg:orig_category":"Bauschreinerei Herstellung von M\u00f6beln verschiedener Art",
    "sg:phone":"+41 24 441 26 08",
    "sg:postcode":"1352",
    "sg:province":"Vaud",
    "wof:name":"Jean Schwendimann Menuiserie & \u00e9b\u00e9nisterie",
    "wof:placetype":"venue"
},
  "geometry": {"coordinates":[6.50547,46.716011],"type":"Point"}
}