{
  "type": "Feature",
  "properties": {
    "iso:country":"CH",
    "sg:address":"Pulverhausweg 11 5033 Buchs Ag. Postfach",
    "sg:city":"Aarau",
    "sg:orig_category":"Ger\u00fcstbau Strassenbau",
    "sg:phone":"+41 62 837 80 00",
    "sg:postcode":"5001",
    "sg:province":"Aargau",
    "wof:name":"Valli Ag Strassenbau",
    "wof:placetype":"venue"
},
  "geometry": {"coordinates":[8.0680418015,47.3962631226],"type":"Point"}
}