{
  "type": "Feature",
  "properties": {
    "iso:country":"CH",
    "sg:address":"T\u00f6sstalstrasse 29 8400 Winterthur. Postfach 22",
    "sg:city":"Winterthur",
    "sg:orig_category":"Herstellung von Radio U Fernsehger\u00e4ten sowie phono U videotechnischen Ger\u00e4ten",
    "sg:phone":"+41 52 212 90 90",
    "sg:postcode":"8402",
    "sg:province":"Z\u00fcrich",
    "wof:name":"Wincomm Wireless Communication Widmer Hansj\u00f6rg",
    "wof:placetype":"venue"
},
  "geometry": {"coordinates":[8.7343254089,47.4973182678],"type":"Point"}
}