{
  "type": "Feature",
  "properties": {
    "iso:country":"CH",
    "sg:address":"Freiburgstrasse 31 Schwarzenburg 3150 Wahlern. Postfach",
    "sg:city":"Schwarzenburg",
    "sg:orig_category":"Allgemeiner Hoch U Tiefbau",
    "sg:phone":"+41 31 731 04 85",
    "sg:postcode":"3150",
    "sg:province":"Bern",
    "wof:name":"Emboras Gmbh",
    "wof:placetype":"venue"
},
  "geometry": {"coordinates":[7.352717,46.826733],"type":"Point"}
}