{
  "type": "Feature",
  "properties": {
    "iso:country":"CH",
    "sg:address":"Rue Des Photographes 12",
    "sg:city":"Gen\u00e8ve",
    "sg:orig_category":"Bauschreinerei Herstellung von M\u00f6beln verschiedener Art",
    "sg:phone":"+41 26 912 83 12",
    "sg:postcode":"1207",
    "sg:province":"Gen\u00e8ve",
    "wof:name":"Antoine Zenoni Eb\u00e9nisterie",
    "wof:placetype":"venue"
},
  "geometry": {"coordinates":[7.066395,46.607971],"type":"Point"}
}