{
  "type": "Feature",
  "properties": {
    "iso:country":"CH",
    "sg:address":"Zielstrasse 38",
    "sg:city":"Appenzell",
    "sg:orig_category":"Interessenvertretungen",
    "sg:phone":"+41 17648181",
    "sg:postcode":"9050",
    "sg:province":"Appenzell Innerhoden",
    "wof:name":"Stiftung Albisbrunn",
    "wof:placetype":"venue"
},
  "geometry": {"coordinates":[8.5362262726,47.2415924072],"type":"Point"}
}