{
  "type": "Feature",
  "properties": {
    "addr:full":"Steinwiesstrasse 76 Z\u00fcrich Z\u00fcrich 8032",
    "addr:housenumber":"76",
    "addr:postcode":"8032",
    "addr:street":"Steinwiesstrasse",
    "iso:country":"CH",
    "sg:address":"Steinwiesstrasse 76",
    "sg:city":"Z\u00fcrich",
    "sg:orig_category":"Detailhandel mit Blumen U Pflanzen",
    "sg:phone":"+41 12511502",
    "sg:postcode":"8032",
    "sg:province":"Z\u00fcrich",
    "wof:name":"Dimitrios Rofas Blumengesch\u00e4ft",
    "wof:placetype":"venue"
},
  "geometry": {"coordinates":[8.556563,47.371353],"type":"Point"}
}