{
  "type": "Feature",
  "properties": {
    "iso:country":"CH",
    "sg:address":"Via Lugano 12 6500 Bellinzona. Postfach Caselle Postale 1441",
    "sg:city":"Bellinzona",
    "sg:orig_category":"Verkehrs- and Tourismusb\u00fcros",
    "sg:phone":"+41 91 825 70 56",
    "sg:postcode":"6501",
    "sg:province":"Ticino",
    "wof:name":"Ente Ticinese Per Il Turismo",
    "wof:placetype":"venue"
},
  "geometry": {"coordinates":[9.0210485458,46.1876449585],"type":"Point"}
}