{
  "type": "Feature",
  "properties": {
    "iso:country":"CH",
    "sg:address":"Pavillons Rue Des 11 1205 Gen\u00e8ve Case Postale 167",
    "sg:city":"Gen\u00e8ve",
    "sg:orig_category":"Werbung",
    "sg:phone":"+41 22 807 22 88",
    "sg:postcode":"1205",
    "sg:province":"Gen\u00e8ve",
    "wof:name":"Publi R\u00e9gie Sa",
    "wof:placetype":"venue"
},
  "geometry": {"coordinates":[6.1396098137,46.196647644],"type":"Point"}
}