{
  "type": "Feature",
  "properties": {
    "iso:country":"CH",
    "sg:address":"3208",
    "sg:city":"Gurbr\u00fc",
    "sg:orig_category":"Herstellung von Konstruktionsteilen, Fertigbauteilen U Ausbauelementen aus Holz",
    "sg:phone":"+41 31 755 52 63",
    "sg:postcode":"3208",
    "sg:province":"Bern",
    "wof:name":"Gebr\u00fcder St\u00e4hli Ag",
    "wof:placetype":"venue"
},
  "geometry": {"coordinates":[7.2148799896,46.9616508484],"type":"Point"}
}