{
  "type": "Feature",
  "properties": {
    "iso:country":"CH",
    "sg:address":"Stadtplatz 15",
    "sg:city":"Aarberg",
    "sg:orig_category":"Detailhandel mit Fleisch U Fleischwaren",
    "sg:phone":"+41 32 392 12 71",
    "sg:postcode":"3270",
    "sg:province":"Bern",
    "wof:name":"Ernst G\u00e4umann Metzgerei",
    "wof:placetype":"venue"
},
  "geometry": {"coordinates":[7.2765240669,47.0444831848],"type":"Point"}
}