{
  "type": "Feature",
  "properties": {
    "iso:country":"CH",
    "sg:address":"Poststrasse 9 6300 Zug. Postfach",
    "sg:city":"Zug",
    "sg:orig_category":"Sonstige mit der Informatik verbundene T\u00e4tigkeiten",
    "sg:postcode":"6300",
    "sg:province":"Zug",
    "wof:name":"Comptek Informatik Ag Hard Und Software; Vertrieb. Dienstleistungen Im Edv-bereich",
    "wof:placetype":"venue"
},
  "geometry": {"coordinates":[8.5158243179,47.1677322388],"type":"Point"}
}