{
  "type": "Feature",
  "properties": {
    "iso:country":"CH",
    "sg:address":"Rue De L'est 33",
    "sg:city":"Montagne-moutier",
    "sg:orig_category":"Herstellung von Schrauben, Nieten, Ketten U Federn Mechanik",
    "sg:phone":"+41 32 493 35 48",
    "sg:postcode":"2740",
    "sg:province":"Bern",
    "wof:name":"Awm Wisard Et M\u00fcller Sa",
    "wof:placetype":"venue"
},
  "geometry": {"coordinates":[7.3724598885,47.2787208557],"type":"Point"}
}