{
  "type": "Feature",
  "properties": {
    "iso:country":"CH",
    "sg:address":"Obergass 57",
    "sg:city":"Eglisau",
    "sg:orig_category":"Bezirks, Sekundar, Realschulen, Oberstufe der Primarschulen",
    "sg:phone":"+41 18670450",
    "sg:postcode":"8193",
    "sg:province":"Z\u00fcrich",
    "wof:name":"Sekundarschule St\u00e4dtli",
    "wof:placetype":"venue"
},
  "geometry": {"coordinates":[8.526191,47.575645],"type":"Point"}
}