{
  "type": "Feature",
  "properties": {
    "iso:country":"CH",
    "sg:address":"Route De Peissy 41 1242 Satigny Case Postale 32",
    "sg:city":"Satigny",
    "sg:orig_category":"Detailhandel mit Getr\u00e4nken Rebbau",
    "sg:phone":"+41 22 753 11 08",
    "sg:postcode":"1242",
    "sg:province":"Gen\u00e8ve",
    "wof:name":"Jean-charles Crousaz",
    "wof:placetype":"venue"
},
  "geometry": {"coordinates":[6.0227460861,46.2119865417],"type":"Point"}
}