{
  "type": "Feature",
  "properties": {
    "iso:country":"CH",
    "sg:address":"Z\u00fcrcherstrasse 282",
    "sg:city":"Frauenfeld",
    "sg:orig_category":"Fachdetailhandel mit Nahrungsmitteln, Getr\u00e4nken U Tabakwaren in Verkaufsr\u00e4umen",
    "sg:phone":"+41 71 633 30 31",
    "sg:postcode":"8500",
    "sg:province":"Thurgau",
    "wof:name":"Yildirim-market T\u00fcrkische Spezialit\u00e4ten",
    "wof:placetype":"venue"
},
  "geometry": {"coordinates":[9.1538200378,47.5495376587],"type":"Point"}
}