{
  "type": "Feature",
  "properties": {
    "iso:country":"CH",
    "sg:address":"Blumenstrasse 7",
    "sg:city":"Berneck",
    "sg:orig_category":"Non-Classified Establishments",
    "sg:postcode":"9442",
    "sg:province":"St. Gallen",
    "wof:name":"Elektro-kuhn Ag",
    "wof:placetype":"venue"
},
  "geometry": {"coordinates":[9.6198711395,47.425163269],"type":"Point"}
}