{
  "type": "Feature",
  "properties": {
    "iso:country":"CH",
    "sg:address":"Walligrundstrasse 27 3931 Eyholz Case Postale 354",
    "sg:city":"Visp",
    "sg:orig_category":"Reiseb\u00fcros U Reiseveranstalter",
    "sg:phone":"+41 27 946 44 44",
    "sg:postcode":"3930",
    "sg:province":"Valais",
    "wof:name":"Zerzuben Touristik Ag",
    "wof:placetype":"venue"
},
  "geometry": {"coordinates":[7.9039268494,46.29429245],"type":"Point"}
}