{
  "type": "Feature",
  "properties": {
    "iso:country":"CH",
    "sg:address":"Murggenstrasse 36",
    "sg:city":"N\u00e4nikon",
    "sg:orig_category":"Hydrological Systems",
    "sg:phone":"+41 19429022",
    "sg:postcode":"8606",
    "sg:province":"Z\u00fcrich",
    "wof:name":"Geoprotect Gmbh",
    "wof:placetype":"venue"
},
  "geometry": {"coordinates":[8.6863517761,47.3714256287],"type":"Point"}
}