{
  "type": "Feature",
  "properties": {
    "iso:country":"CH",
    "sg:address":"Blumenstrasse 7",
    "sg:city":"Wittenbach",
    "sg:orig_category":"Kauf U Verkauf von Immobilien auf eigene Rechnung",
    "sg:phone":"+41 71 298 33 68",
    "sg:postcode":"9303",
    "wof:name":"Frei Consulting",
    "wof:placetype":"venue"
},
  "geometry": {"coordinates":[9.3836803436,47.4655723572],"type":"Point"}
}