{
  "type": "Feature",
  "properties": {
    "iso:country":"CH",
    "sg:address":"Eschenstrasse 9",
    "sg:city":"Goldach",
    "sg:classifiers":[
        {
            "category":"Utilities",
            "subcategory":"Electric",
            "type":"Services"
        }
    ],
    "sg:phone":"+41 71 841 88 88",
    "sg:postcode":"9403",
    "sg:province":"St. Gallen",
    "sg:tags":[
        "planing",
        "metal"
    ],
    "wof:name":"Eichmann Holz Ag",
    "wof:placetype":"venue"
},
  "geometry": {"coordinates":[9.4697504044,47.4771995544],"type":"Point"}
}