{
  "type": "Feature",
  "properties": {
    "iso:country":"CH",
    "sg:address":"Hauptstrasse 55",
    "sg:city":"Sutz",
    "sg:orig_category":"Sanit\u00e4r U Heizungsinstallation Sanit\u00e4rinstallation",
    "sg:phone":"+41 32 397 11 27",
    "sg:postcode":"2572",
    "sg:province":"Bern",
    "wof:name":"Hermann Ryser",
    "wof:placetype":"venue"
},
  "geometry": {"coordinates":[7.2149572372,47.0971107483],"type":"Point"}
}