{
  "type": "Feature",
  "properties": {
    "iso:country":"CH",
    "sg:address":"Boujean Rue De 183 2504 Biel/bienne. Postfach",
    "sg:city":"Biel/bienne",
    "sg:orig_category":"Sonstiger Grosshandel",
    "sg:phone":"+41 32412956",
    "sg:postcode":"2504",
    "sg:province":"Bern",
    "wof:name":"De Cicco Fran\u00e7oise",
    "wof:placetype":"venue"
},
  "geometry": {"coordinates":[7.2668309212,47.1527786255],"type":"Point"}
}