{
  "type": "Feature",
  "properties": {
    "iso:country":"CH",
    "sg:address":"Rue De Gen\u00e8ve 134",
    "sg:city":"Th\u00f4nex",
    "sg:classifiers":[
        {
            "category":"Banks & Credit Unions",
            "subcategory":"Bank",
            "type":"Services"
        }
    ],
    "sg:phone":"+41 22 348 47 64",
    "sg:postcode":"1226",
    "sg:province":"Gen\u00e8ve",
    "wof:name":"Cr\u00e9dito Predial Portugu\u00eas, Bureau De Repr\u00e9sentation",
    "wof:placetype":"venue"
},
  "geometry": {"coordinates":[6.204031,46.192455],"type":"Point"}
}