{
  "type": "Feature",
  "properties": {
    "iso:country":"CH",
    "sg:address":"3803",
    "sg:city":"Beatenberg",
    "sg:classifiers":[
        {
            "category":"Restaurant",
            "type":"Food & Drink"
        }
    ],
    "sg:phone":"+41 33 841 11 51",
    "sg:postcode":"3803",
    "sg:province":"Bern",
    "wof:name":"Restaurant Hohwald",
    "wof:placetype":"venue"
},
  "geometry": {"coordinates":[7.7930397987,46.6966781616],"type":"Point"}
}