{
  "type": "Feature",
  "properties": {
    "iso:country":"CH",
    "sg:address":"Arbonerstrasse 23",
    "sg:city":"Amriswil",
    "sg:orig_category":"Vermietung U Verpachtung von eigenen Immobilien",
    "sg:phone":"+41 71 411 47 43",
    "sg:postcode":"8580",
    "sg:province":"Thurgau",
    "wof:name":"Genossenschaft Der Henri Dunant Loge Nr. 25",
    "wof:placetype":"venue"
},
  "geometry": {"coordinates":[9.3026838303,47.5446586609],"type":"Point"}
}