{
  "type": "Feature",
  "properties": {
    "iso:country":"CH",
    "sg:address":"Via Biee",
    "sg:city":"Pura",
    "sg:orig_category":"Unclassifiable Establishments",
    "sg:postcode":"6984",
    "sg:province":"Ticino",
    "wof:name":"Studio Comunic-azione Sagl",
    "wof:placetype":"venue"
},
  "geometry": {"coordinates":[8.8686580658,45.9879798889],"type":"Point"}
}