{
  "type": "Feature",
  "properties": {
    "iso:country":"CH",
    "sg:address":"Hauptstrasse 144",
    "sg:city":"Orpund",
    "sg:orig_category":"Detailhandel mit Fleisch U Fleischwaren",
    "sg:phone":"+41 19300584",
    "sg:postcode":"2552",
    "sg:province":"Bern",
    "wof:name":"Hans Niffeler Metzgerei-wursterei",
    "wof:placetype":"venue"
},
  "geometry": {"coordinates":[8.806429863,47.3309326172],"type":"Point"}
}