{
  "type": "Feature",
  "properties": {
    "iso:country":"CH",
    "sg:address":"Seestrasse 849",
    "sg:city":"Meilen",
    "sg:orig_category":"Massagestudios Naturheil\u00e4rzte and Heilpraktiker",
    "sg:phone":"+41 19234875",
    "sg:postcode":"8706",
    "sg:province":"Z\u00fcrich",
    "wof:name":"Adrian Maurer Naturheilpraxis & Massagen",
    "wof:placetype":"venue"
},
  "geometry": {"coordinates":[8.6507797241,47.2660903931],"type":"Point"}
}