{
  "type": "Feature",
  "properties": {
    "iso:country":"CH",
    "sg:address":"Chemin Des P\u00e9toleyres 25 1110 Morges. Postfach",
    "sg:city":"Morges",
    "sg:orig_category":"Berufsbildende weiterf\u00fchrende Schulen",
    "sg:postcode":"1110",
    "sg:province":"Vaud",
    "wof:name":"Radec, Fran\u00e7ois Radice",
    "wof:placetype":"venue"
},
  "geometry": {"coordinates":[6.561132,46.525433],"type":"Point"}
}