{
  "type": "Feature",
  "properties": {
    "iso:country":"CH",
    "sg:address":"Chemin De La Jardini\u00e8re 7",
    "sg:city":"Nyon",
    "sg:orig_category":"Sonstige mit der Informatik verbundene T\u00e4tigkeiten",
    "sg:phone":"+41 22 362 45 68",
    "sg:postcode":"1260",
    "sg:province":"Vaud",
    "wof:name":"Maurice Gay, Service Informatique",
    "wof:placetype":"venue"
},
  "geometry": {"coordinates":[6.2246379852,46.382598877],"type":"Point"}
}