{
  "type": "Feature",
  "properties": {
    "iso:country":"CH",
    "sg:address":"Feigelstrasse 35",
    "sg:city":"Olten",
    "sg:orig_category":"Werbung",
    "sg:phone":"+41 62 212 06 35",
    "sg:postcode":"4600",
    "sg:province":"Solothurn",
    "wof:name":"Pr-agentur Pl\u00fcss Gabriele",
    "wof:placetype":"venue"
},
  "geometry": {"coordinates":[7.8935599327,47.3517036438],"type":"Point"}
}