{
  "type": "Feature",
  "properties": {
    "iso:country":"CH",
    "sg:address":"Chemin De La Perche 14b",
    "sg:city":"Porrentruy",
    "sg:orig_category":"Mechanische Werkst\u00e4tten",
    "sg:phone":"+41 32 345 20 20",
    "sg:postcode":"2900",
    "sg:province":"Jura",
    "wof:name":"Roland Oppliger Diamant- & Cbn-werkzeuge",
    "wof:placetype":"venue"
},
  "geometry": {"coordinates":[7.3634147644,47.1084861755],"type":"Point"}
}