{
  "type": "Feature",
  "properties": {
    "iso:country":"CH",
    "sg:address":"1543",
    "sg:city":"Grandcour",
    "sg:orig_category":"Schulpflegen",
    "sg:postcode":"1543",
    "sg:province":"Vaud",
    "wof:name":"Commission Scolaire De L'ecole Primaire",
    "wof:placetype":"venue"
},
  "geometry": {"coordinates":[6.9286150932,46.8717956543],"type":"Point"}
}