{
  "type": "Feature",
  "properties": {
    "iso:country":"CH",
    "sg:address":"Kasernenstrasse 19 8180 B\u00fclach. Postfach 188",
    "sg:city":"B\u00fclach",
    "sg:orig_category":"Architektur U Ingenieurb\u00fcros Architekturb\u00fcros",
    "sg:phone":"+41 18601715",
    "sg:postcode":"8180",
    "sg:province":"Z\u00fcrich",
    "wof:name":"Architekturb\u00fcro Meier Oskar Ag",
    "wof:placetype":"venue"
},
  "geometry": {"coordinates":[8.537947,47.518005],"type":"Point"}
}