{
  "type": "Feature",
  "properties": {
    "iso:country":"CH",
    "sg:address":"Reichsgasse 71",
    "sg:city":"Chur",
    "sg:orig_category":"Herstellung von Metallkonstruktionen",
    "sg:phone":"+41 55 415 66 36",
    "sg:postcode":"7000",
    "sg:province":"Graubunden",
    "wof:name":"Swissprofil Gmbh",
    "wof:placetype":"venue"
},
  "geometry": {"coordinates":[8.7833595276,47.2014961243],"type":"Point"}
}