{
  "type": "Feature",
  "properties": {
    "iso:country":"CH",
    "sg:address":"R\u00fcteli 6074 Giswil. Postfach 254",
    "sg:city":"Giswil",
    "sg:orig_category":"Vermietung U Verpachtung von eigenen Immobilien Vermittlung von Immobilien",
    "sg:phone":"+41 41 460 34 22",
    "sg:postcode":"6074",
    "sg:province":"Obwalden",
    "wof:name":"Yucca Immobilien Ag",
    "wof:placetype":"venue"
},
  "geometry": {"coordinates":[8.2235832214,47.131149292],"type":"Point"}
}