{
  "type": "Feature",
  "properties": {
    "iso:country":"CH",
    "sg:address":"Chamerstrasse 16",
    "sg:city":"Zug",
    "sg:orig_category":"Handel mit Automobilen",
    "sg:phone":"+41 33 783 20 10",
    "sg:postcode":"6300",
    "sg:province":"Zug",
    "wof:name":"Oskar Siegenthaler",
    "wof:placetype":"venue"
},
  "geometry": {"coordinates":[7.4232048988,46.6524391174],"type":"Point"}
}