{
  "type": "Feature",
  "properties": {
    "iso:country":"CH",
    "sg:address":"Talgut-zentrum 5 3063 Ittigen. Postfach",
    "sg:city":"Ittigen",
    "sg:orig_category":"Drogerien Sonstiger Fachdetailhandel mit Nahrungsmitteln, Getr\u00e4nken U Tabak in Verkaufsr\u00e4umen",
    "sg:phone":"+41 31 921 11 88",
    "sg:postcode":"3063",
    "sg:province":"Bern",
    "wof:name":"Siegfried Ag Drogerie & Reformhaus",
    "wof:placetype":"venue"
},
  "geometry": {"coordinates":[7.4832668304,46.9738006592],"type":"Point"}
}