{
  "type": "Feature",
  "properties": {
    "iso:country":"CH",
    "sg:address":"Dorfplatz 7a",
    "sg:city":"Stans",
    "sg:orig_category":"Weiterbildungskurse and Seminar Anbieter",
    "sg:phone":"+41 41 612 22 77",
    "sg:postcode":"6370",
    "sg:province":"Nidwalden",
    "wof:name":"Chiq Schweiz.institut F\u00fcr Integrales Qualit\u00e4tsmanagement",
    "wof:placetype":"venue"
},
  "geometry": {"coordinates":[8.3660135269,46.9568405151],"type":"Point"}
}