{
  "type": "Feature",
  "properties": {
    "iso:country":"CH",
    "sg:address":"Dorfstrasse",
    "sg:city":"Weisslingen",
    "sg:orig_category":"Grosshandel mit Textilien",
    "sg:phone":"+41 52 384 20 80",
    "sg:postcode":"8484",
    "sg:province":"Z\u00fcrich",
    "wof:name":"Hausammann + Moos Ag",
    "wof:placetype":"venue"
},
  "geometry": {"coordinates":[8.7631874084,47.4331054688],"type":"Point"}
}