{
  "type": "Feature",
  "properties": {
    "iso:country":"CH",
    "sg:address":"Gutenbergstrasse 22 3011 Bern. Postfach",
    "sg:city":"Bern",
    "sg:orig_category":"Interessenvertretungen",
    "sg:postcode":"3005",
    "sg:province":"Bern",
    "wof:name":"Evangelisch Freikirchliche Gemeinden Verbreitung Des Evangeliums Usw",
    "wof:placetype":"venue"
},
  "geometry": {"coordinates":[7.4346880913,46.9442405701],"type":"Point"}
}