{
  "type": "Feature",
  "properties": {
    "iso:country":"CH",
    "sg:address":"Alfred-schindlerstrasse 22 6030 Ebikon. Postfach",
    "sg:city":"Ebikon",
    "sg:orig_category":"Non-Classified Establishments",
    "sg:postcode":"6030",
    "sg:province":"Luzern",
    "wof:name":"Pizza-blitz, Schwarz Pizza- U. Teigwaren-hauslieferdienst",
    "wof:placetype":"venue"
},
  "geometry": {"coordinates":[8.3521718979,47.0873718262],"type":"Point"}
}