{
  "type": "Feature",
  "properties": {
    "addr:full":"Neuhor\u00fcti 7 Wolhusen Luzern 6110",
    "addr:housenumber":"7",
    "addr:postcode":"6110",
    "addr:street":"Neuhorueti",
    "iso:country":"CH",
    "sg:address":"Neuhor\u00fcti 7",
    "sg:city":"Wolhusen",
    "sg:orig_category":"Bauschreinerei",
    "sg:phone":"+41 41 490 23 77",
    "sg:postcode":"6110",
    "sg:province":"Luzern",
    "wof:name":"Josef Aregger Schreinerei",
    "wof:placetype":"venue"
},
  "geometry": {"coordinates":[8.073255,47.058941],"type":"Point"}
}