{
  "type": "Feature",
  "properties": {
    "iso:country":"CH",
    "sg:address":"Sagenstrasse 45",
    "sg:city":"Pfaffnau",
    "sg:orig_category":"Bauschreinerei Herstellung von Konstruktionsteilen, Fertigbauteilen U Ausbauelementen aus Holz",
    "sg:phone":"+41 62 754 18 81",
    "sg:postcode":"6264",
    "sg:province":"Luzern",
    "wof:name":"Lichtsteiner & Kunz Schreinerei-innenausbau",
    "wof:placetype":"venue"
},
  "geometry": {"coordinates":[7.894721,47.229321],"type":"Point"}
}