{
  "type": "Feature",
  "properties": {
    "addr:full":"Via Del Sole 31 Muralto Ticino 6600",
    "addr:housenumber":"31",
    "addr:postcode":"6600",
    "addr:street":"Via Del Sole",
    "iso:country":"CH",
    "sg:address":"Via Del Sole 31",
    "sg:city":"Muralto",
    "sg:orig_category":"Br\u00fccken U Tunnelbau Herstellung von sonstigen Metallwaren",
    "sg:phone":"+41 41 280 90 55",
    "sg:postcode":"6600",
    "sg:province":"Ticino",
    "wof:name":"Tecton-atisol Ag Abdichtungs-& Gussasphaltbau",
    "wof:placetype":"venue"
},
  "geometry": {"coordinates":[8.275493,47.078087],"type":"Point"}
}