{
  "type": "Feature",
  "properties": {
    "iso:country":"CH",
    "sg:address":"Winkelb\u00fcel 4 6043 Adligenswil. Postfach",
    "sg:city":"Adligenswil",
    "sg:orig_category":"Interessenvertretungen",
    "sg:postcode":"6043",
    "sg:province":"Luzern",
    "wof:name":"Verband Schweizerischer Mental Und Pers\u00f6nlichkeits-trainer Vsmpt F\u00f6rderung D. Professionellen Ausbildung V. Mental Und Pers\u00f6nlichkeits-trainerinnen, -trainern",
    "wof:placetype":"venue"
},
  "geometry": {"coordinates":[8.3792352676,47.0725250244],"type":"Point"}
}