{
  "type": "Feature",
  "properties": {
    "iso:country":"CH",
    "sg:address":"Chemin De Plein-champs 42",
    "sg:city":"Puplinge",
    "sg:orig_category":"Grosshandel mit Holz U Baustoffen Grosshandel mit chemischen Erzeugnissen",
    "sg:phone":"+41 52 320 99 99",
    "sg:postcode":"1241",
    "sg:province":"Gen\u00e8ve",
    "wof:name":"Pci Bauprodukte Ag",
    "wof:placetype":"venue"
},
  "geometry": {"coordinates":[6.8748230934,46.9835014343],"type":"Point"}
}