{
  "type": "Feature",
  "properties": {
    "iso:country":"CH",
    "sg:address":"Flurhofstrasse 154",
    "sg:city":"St.gallen",
    "sg:orig_category":"Herstellung von sonstigen Waren aus Papier, Karton U Pappe Herstellung von sonstigen chemischen Erze",
    "sg:phone":"+41 79 691 30 30",
    "sg:postcode":"9000",
    "sg:province":"St. Gallen",
    "wof:name":"Adhesive Ag",
    "wof:placetype":"venue"
},
  "geometry": {"coordinates":[8.4284582138,47.3662643433],"type":"Point"}
}