{
  "type": "Feature",
  "properties": {
    "iso:country":"CH",
    "sg:address":"Talstrasse 4",
    "sg:city":"Oberstammheim",
    "sg:orig_category":"Mechanische Werkst\u00e4tten",
    "sg:phone":"+41 52 745 19 57",
    "sg:postcode":"8477",
    "sg:province":"Z\u00fcrich",
    "wof:name":"Richard Forster Mechanische Werkstatt",
    "wof:placetype":"venue"
},
  "geometry": {"coordinates":[8.7985668182,47.633026123],"type":"Point"}
}