{
  "type": "Feature",
  "properties": {
    "iso:country":"CH",
    "sg:address":"Isch",
    "sg:city":"Grindelwald",
    "sg:orig_category":"Detailhandel mit Waren verschiedener Art, Hauptrichtung Nahrungsmittel",
    "sg:phone":"+41 33 853 21 14",
    "sg:postcode":"3818",
    "sg:province":"Bern",
    "wof:name":"Antonia Brawand Handlung",
    "wof:placetype":"venue"
},
  "geometry": {"coordinates":[8.0499563217,46.628704071],"type":"Point"}
}