{
  "type": "Feature",
  "properties": {
    "iso:country":"CH",
    "sg:address":"Hubelweg 1",
    "sg:city":"Herzogenbuchsee",
    "sg:orig_category":"Vorschulen, Kinderg\u00e4rten",
    "sg:phone":"+41 31 859 40 54",
    "sg:postcode":"3360",
    "sg:province":"Bern",
    "wof:name":"Kindergarten",
    "wof:placetype":"venue"
},
  "geometry": {"coordinates":[7.5247058868,47.0181274414],"type":"Point"}
}