{
  "type": "Feature",
  "properties": {
    "iso:country":"CH",
    "sg:address":"Eisenbahnweg 14 6415 Arth. Postfach",
    "sg:city":"Goldau",
    "sg:orig_category":"Stukkateurgewerbe, Gipserei U Verputzerei",
    "sg:postcode":"6410",
    "sg:province":"Schwyz",
    "wof:name":"Donnarummo F., Gipsergesch\u00e4ft",
    "wof:placetype":"venue"
},
  "geometry": {"coordinates":[8.5514163971,47.0481529236],"type":"Point"}
}