{
  "type": "Feature",
  "properties": {
    "iso:country":"CH",
    "sg:address":"4458",
    "sg:city":"Eptingen",
    "sg:orig_category":"Sportvereine Sch\u00fctzen",
    "sg:postcode":"4458",
    "sg:province":"Basel-Landschaft",
    "wof:name":"Sch\u00fctzengesellschaft",
    "wof:placetype":"venue"
},
  "geometry": {"coordinates":[7.820827961,47.3850898743],"type":"Point"}
}