{
  "type": "Feature",
  "properties": {
    "iso:country":"CH",
    "sg:address":"Weissacherweg 30",
    "sg:city":"Rumisberg",
    "sg:orig_category":"Gesundheitswesen",
    "sg:phone":"+41 32 636 11 26",
    "sg:postcode":"4539",
    "sg:province":"Bern",
    "wof:name":"Hi Humanistisches Institut F\u00fcr Integration Gmbh",
    "wof:placetype":"venue"
},
  "geometry": {"coordinates":[7.6443772316,47.2695541382],"type":"Point"}
}