{
  "type": "Feature",
  "properties": {
    "iso:country":"CH",
    "sg:address":"Petersgraben 15",
    "sg:city":"Basel",
    "sg:orig_category":"Detailhandel KLEINE GESCH\u00c4FTE Reparatur von Gebrauchsg\u00fctern",
    "sg:phone":"+41 61 261 43 66",
    "sg:postcode":"4051",
    "sg:province":"Basel-Stadt",
    "wof:name":"Prairie Wind Native American Arts & Crafts Amerikanische Waren; Import, Export, Verkauf. Galerie",
    "wof:placetype":"venue"
},
  "geometry": {"coordinates":[7.5851340294,47.560344696],"type":"Point"}
}