{
  "type": "Feature",
  "properties": {
    "iso:country":"CH",
    "sg:address":"Kaisermatt 3",
    "sg:city":"Densb\u00fcren",
    "sg:classifiers":[
        {
            "category":"Professional",
            "subcategory":"Engineering",
            "type":"Services"
        }
    ],
    "sg:phone":"+41 62 867 92 92",
    "sg:postcode":"5026",
    "sg:province":"Aargau",
    "sg:tags":[
        "machine",
        "-",
        "mechanical"
    ],
    "wof:name":"Senntech Ag",
    "wof:placetype":"venue"
},
  "geometry": {"coordinates":[8.0499544144,47.45677948],"type":"Point"}
}