{
  "type": "Feature",
  "properties": {
    "iso:country":"CH",
    "sg:address":"Dorfstrasse 16",
    "sg:city":"Dorfstrasse 16",
    "sg:orig_category":"Detailhandel mit Waren verschiedener Art, Hauptrichtung Nahrungsmittel",
    "sg:postcode":"8560",
    "sg:province":"Thurgau",
    "wof:name":"Landwirtschaftliche Konsumgenossenschaft M\u00e4rstetten",
    "wof:placetype":"venue"
},
  "geometry": {"coordinates":[9.068403244,47.5921401978],"type":"Point"}
}