{
  "type": "Feature",
  "properties": {
    "iso:country":"CH",
    "sg:address":"Botyre",
    "sg:city":"Ayent",
    "sg:orig_category":"G\u00fcterbef\u00f6rderung im Strassenverkehr",
    "sg:phone":"+41 27 398 13 10",
    "sg:postcode":"1966",
    "sg:province":"Valais",
    "wof:name":"Florian D\u00e9l\u00e9troz Transports",
    "wof:placetype":"venue"
},
  "geometry": {"coordinates":[7.4068198204,46.2767791748],"type":"Point"}
}