{
  "type": "Feature",
  "properties": {
    "iso:country":"CH",
    "sg:address":"F\u00e4rberweg 2",
    "sg:city":"Lenzburg",
    "sg:orig_category":"Institutionen f\u00fcr Behinderte Wohnheime",
    "sg:phone":"+41 56 619 51 51",
    "sg:postcode":"5600",
    "sg:province":"Aargau",
    "wof:name":"Stiftung F\u00fcr Behinderte Im Freiamt",
    "wof:placetype":"venue"
},
  "geometry": {"coordinates":[8.2780704498,47.3505363464],"type":"Point"}
}