{
  "type": "Feature",
  "properties": {
    "iso:country":"CH",
    "sg:address":"Watterstrasse 95 8105 Regensdorf. Postfach",
    "sg:city":"Regensdorf",
    "sg:orig_category":"Dienstleistungen von Beteiligungsgesellschaften",
    "sg:postcode":"8105",
    "sg:province":"Z\u00fcrich",
    "wof:name":"Admindispo Gmbh B\u00fcro Zur Unterst\u00fctzung Von Klein, Mittelbetrieben, Bes. F\u00fcr Administrations- U. Buchhaltungsarbeiten",
    "wof:placetype":"venue"
},
  "geometry": {"coordinates":[8.4681377411,47.4335708618],"type":"Point"}
}