{
  "type": "Feature",
  "properties": {
    "iso:country":"CH",
    "sg:address":"Rue De La Dixence 19a",
    "sg:city":"Sion",
    "sg:orig_category":"Erbringung von Dienstleistungen f\u00fcr Unternehmen Public-Relations-Agenturen",
    "sg:phone":"+41 27 323 77 24",
    "sg:postcode":"1950",
    "sg:province":"Valais",
    "wof:name":"Svd Design S\u00e0rl",
    "wof:placetype":"venue"
},
  "geometry": {"coordinates":[7.3636322021,46.2306938171],"type":"Point"}
}