{
  "type": "Feature",
  "properties": {
    "iso:country":"CH",
    "sg:address":"Zeughausgasse 3",
    "sg:city":"Bern",
    "sg:orig_category":"RESTAURANTS: TEA-ROOMS",
    "sg:postcode":"3011",
    "sg:province":"Bern",
    "wof:name":"Vonlanten Paula",
    "wof:placetype":"venue"
},
  "geometry": {"coordinates":[7.1783599854,46.7523612976],"type":"Point"}
}