{
  "type": "Feature",
  "properties": {
    "iso:country":"CH",
    "sg:address":"Lyssachstrasse 13 3400 Burgdorf. Postfach 587",
    "sg:city":"Burgdorf",
    "sg:orig_category":"Detailhandel mit B\u00fcromaschinen U einrichtungen",
    "sg:phone":"+41 81 756 33 10",
    "sg:postcode":"3401",
    "sg:province":"Bern",
    "wof:name":"B\u00fcro Marxer",
    "wof:placetype":"venue"
},
  "geometry": {"coordinates":[9.462694,47.16938],"type":"Point"}
}