{
  "type": "Feature",
  "properties": {
    "iso:country":"CH",
    "sg:address":"5036 Oberentfelden. Postfach 134",
    "sg:city":"Oberentfelden",
    "sg:orig_category":"Sportvereine Ballsport Tennis",
    "sg:phone":"+41 62 723 82 63",
    "sg:postcode":"5036",
    "sg:province":"Aargau",
    "wof:name":"Tennisclub Entfelden",
    "wof:placetype":"venue"
},
  "geometry": {"coordinates":[8.0466556549,47.3560371399],"type":"Point"}
}