{
  "type": "Feature",
  "properties": {
    "iso:country":"CH",
    "sg:address":"Forchstrasse 261 8032 Z\u00fcrich. Postfach 374",
    "sg:city":"Z\u00fcrich",
    "sg:orig_category":"Kauf U Verkauf von Immobilien auf eigene Rechnung Vermittlung von Immobilien",
    "sg:phone":"+41 14212080",
    "sg:postcode":"8029",
    "wof:name":"Tanner & Stump Immobilien-treuhand Ag",
    "wof:placetype":"venue"
},
  "geometry": {"coordinates":[8.5713338852,47.3583374023],"type":"Point"}
}