{
  "type": "Feature",
  "properties": {
    "addr:full":"Seftigenstrasse 362 Wabern Bern 3084",
    "addr:housenumber":"362",
    "addr:postcode":"3084",
    "addr:street":"Seftigenstrasse",
    "iso:country":"CH",
    "sg:address":"Seftigenstrasse 362",
    "sg:city":"Wabern",
    "sg:orig_category":"Detailhandel mit Blumen U Pflanzen Fachdetailhandel in Verkaufsr\u00e4umen",
    "sg:phone":"+41 31 961 35 00",
    "sg:postcode":"3084",
    "sg:province":"Bern",
    "wof:name":"Blumenboutique Gerber",
    "wof:placetype":"venue"
},
  "geometry": {"coordinates":[7.459555,46.923023],"type":"Point"}
}