{
  "type": "Feature",
  "properties": {
    "addr:full":"Bollwerk 19 Bern Bern 3011",
    "addr:housenumber":"19",
    "addr:postcode":"3011",
    "addr:street":"Bollwerk",
    "iso:country":"CH",
    "sg:address":"Bollwerk 19",
    "sg:city":"Bern",
    "sg:orig_category":"Shopping U Fachgesch\u00e4fte, Sonstige Shoppinggelegenheiten",
    "sg:phone":"+41 62 963 00 43",
    "sg:postcode":"3011",
    "sg:province":"Bern",
    "wof:name":"Posterstore Gmbh",
    "wof:placetype":"venue"
},
  "geometry": {"coordinates":[7.440734,46.949825],"type":"Point"}
}