{
  "type": "Feature",
  "properties": {
    "iso:country":"CH",
    "sg:address":"Miex",
    "sg:city":"Miex",
    "sg:orig_category":"Betrieb von Taxis",
    "sg:phone":"+41 24 481 19 24",
    "sg:postcode":"1896",
    "sg:province":"Valais",
    "wof:name":"Vuadens Andre Transports S\u00e0rl",
    "wof:placetype":"venue"
},
  "geometry": {"coordinates":[6.890823,46.336075],"type":"Point"}
}