{
  "type": "Feature",
  "properties": {
    "iso:country":"CH",
    "sg:address":"Rue Des Pr\u00e9s 1",
    "sg:city":"Reconvilier",
    "sg:orig_category":"Malerei",
    "sg:phone":"+41 32 481 11 41",
    "sg:postcode":"2732",
    "sg:province":"Bern",
    "wof:name":"Louis Monnin Entreprise De Peinture",
    "wof:placetype":"venue"
},
  "geometry": {"coordinates":[7.2226700783,47.2331733704],"type":"Point"}
}