{
  "type": "Feature",
  "properties": {
    "iso:country":"CH",
    "sg:address":"Vergers Rue Des 14",
    "sg:city":"Sion",
    "sg:orig_category":"Herstellung von Papier, Karton U Pappe",
    "sg:phone":"+41 27 327 30 90",
    "sg:postcode":"1950",
    "sg:province":"Valais",
    "wof:name":"Techinvest Trading Ltd",
    "wof:placetype":"venue"
},
  "geometry": {"coordinates":[7.3593702316,46.2316703796],"type":"Point"}
}