{
  "type": "Feature",
  "properties": {
    "iso:country":"CH",
    "sg:address":"Neudorfstrasse 21",
    "sg:city":"Uzwil",
    "sg:orig_category":"Fahrschulen, Flugschulen",
    "sg:phone":"+41 79 436 18 80",
    "sg:postcode":"9240",
    "sg:province":"St. Gallen",
    "wof:name":"Arthur Oppliger Turi's Fahrschule",
    "wof:placetype":"venue"
},
  "geometry": {"coordinates":[9.1320238113,47.4408531189],"type":"Point"}
}