{
  "type": "Feature",
  "properties": {
    "iso:country":"CH",
    "sg:address":"Werkstrasse 33",
    "sg:city":"Dagmersellen",
    "sg:orig_category":"Herstellung von Metallerzeugnissen ohne Maschinenbau",
    "sg:phone":"+41 32 913 26 18",
    "sg:postcode":"6252",
    "sg:province":"Luzern",
    "wof:name":"Relief Sa",
    "wof:placetype":"venue"
},
  "geometry": {"coordinates":[6.8271231651,47.0981864929],"type":"Point"}
}