{
  "type": "Feature",
  "properties": {
    "addr:full":"Auwiesenstrasse 10 Sulgen Thurgau 8583",
    "addr:housenumber":"10",
    "addr:postcode":"8583",
    "addr:street":"Auwiesenstrasse",
    "iso:country":"CH",
    "sg:address":"Auwiesenstrasse 10",
    "sg:city":"Sulgen",
    "sg:orig_category":"Berufsbildende weiterf\u00fchrende Schulen",
    "sg:phone":"+41 71 911 27 70",
    "sg:postcode":"8583",
    "sg:province":"Thurgau",
    "wof:name":"Ortega Wirtschaftsschule Wil, Dietrich Peter",
    "wof:placetype":"venue"
},
  "geometry": {"coordinates":[9.041173,47.464699],"type":"Point"}
}