{
  "type": "Feature",
  "properties": {
    "iso:country":"CH",
    "sg:address":"8606 Greifensee. Postfach 9",
    "sg:city":"Greifensee",
    "sg:orig_category":"Vereine Frauen Vereine Gemeinn\u00fctzige",
    "sg:postcode":"8606",
    "sg:province":"Z\u00fcrich",
    "wof:name":"Frauenverein Greifensee",
    "wof:placetype":"venue"
},
  "geometry": {"coordinates":[8.677529335,47.365234375],"type":"Point"}
}