{
  "type": "Feature",
  "properties": {
    "addr:full":"Amriswilerstrasse 1 Romanshorn Thurgau 8590",
    "addr:housenumber":"1",
    "addr:postcode":"8590",
    "addr:street":"Amriswilerstrasse",
    "iso:country":"CH",
    "sg:address":"Amriswilerstrasse 1",
    "sg:city":"Romanshorn",
    "sg:orig_category":"Allgemeiner Hoch U Tiefbau",
    "sg:phone":"+41 91 794 20 53",
    "sg:postcode":"8590",
    "sg:province":"Thurgau",
    "wof:name":"Spinella Carmelo.",
    "wof:placetype":"venue"
},
  "geometry": {"coordinates":[8.81384,46.133289],"type":"Point"}
}