{
  "type": "Feature",
  "properties": {
    "iso:country":"CH",
    "sg:address":"Leonhardsstrasse 53",
    "sg:city":"Basel",
    "sg:orig_category":"Arztpraxen",
    "sg:phone":"+41 61 272 75 95",
    "sg:postcode":"4051",
    "sg:province":"Basel-Stadt",
    "wof:name":"Dr.med.peter Kern Spezialarzt",
    "wof:placetype":"venue"
},
  "geometry": {"coordinates":[7.583375,47.55394],"type":"Point"}
}