{
  "type": "Feature",
  "properties": {
    "iso:country":"CH",
    "sg:address":"Aesch",
    "sg:city":"Flawil",
    "sg:orig_category":"Herstellung von sonstigen landwirtschaftlichen Maschinen",
    "sg:phone":"+41 79 620 18 80",
    "sg:postcode":"9230",
    "sg:province":"St. Gallen",
    "wof:name":"Schilliger & Sohn",
    "wof:placetype":"venue"
},
  "geometry": {"coordinates":[9.1888751984,47.4148368835],"type":"Point"}
}