{
  "type": "Feature",
  "properties": {
    "iso:country":"CH",
    "sg:address":"Dornacherstrasse 117",
    "sg:city":"Basel",
    "sg:orig_category":"Unclassifiable Establishments",
    "sg:postcode":"4053",
    "sg:province":"Basel-Stadt",
    "wof:name":"Canis Gmbh",
    "wof:placetype":"venue"
},
  "geometry": {"coordinates":[8.8471822739,47.1914176941],"type":"Point"}
}