{
  "type": "Feature",
  "properties": {
    "iso:country":"CH",
    "sg:address":"Stadelgasse 2",
    "sg:city":"Bischofszell",
    "sg:orig_category":"Reparatur von Schuhen U Lederwaren",
    "sg:phone":"+41 71 422 37 61",
    "sg:postcode":"9220",
    "sg:province":"Thurgau",
    "wof:name":"Giuseppe Gallizzi Schuhreparaturen",
    "wof:placetype":"venue"
},
  "geometry": {"coordinates":[9.2418069839,47.4941596985],"type":"Point"}
}