{
  "type": "Feature",
  "properties": {
    "addr:full":"Max-buri-strasse 14 Burgdorf Bern 3400",
    "addr:housenumber":"14",
    "addr:postcode":"3400",
    "addr:street":"Max-Buri-Strasse",
    "iso:country":"CH",
    "sg:address":"Max-buri-strasse 14",
    "sg:city":"Burgdorf",
    "sg:orig_category":"Allgemeiner Hoch U Tiefbau Hoch U Tiefbau",
    "sg:phone":"+41 34 423 22 33",
    "sg:postcode":"3400",
    "sg:province":"Bern",
    "wof:name":"Wiedmer Bau",
    "wof:placetype":"venue"
},
  "geometry": {"coordinates":[7.615069,47.05785],"type":"Point"}
}