{
  "type": "Feature",
  "properties": {
    "iso:country":"CH",
    "sg:address":"Winkelstrasse 1",
    "sg:city":"Riniken",
    "sg:orig_category":"Grosshandel mit elektrischen Haushaltsger\u00e4ten",
    "sg:phone":"+41 56 441 08 66",
    "sg:postcode":"5223",
    "sg:province":"Aargau",
    "wof:name":"Hans-rudolf Obrist Handel M.haushaltapparaten",
    "wof:placetype":"venue"
},
  "geometry": {"coordinates":[8.1895093918,47.495223999],"type":"Point"}
}