{
  "type": "Feature",
  "properties": {
    "iso:country":"CH",
    "sg:address":"M\u00fchlefeld 3 6018 Buttisholz. Postfach 121",
    "sg:city":"Buttisholz",
    "sg:orig_category":"Konkurs- and Betreibungs\u00e4mter",
    "sg:phone":"+41 41 928 12 22",
    "sg:postcode":"6018",
    "sg:province":"Luzern",
    "wof:name":"Konkursamt Sursee",
    "wof:placetype":"venue"
},
  "geometry": {"coordinates":[8.095038414,47.1140289307],"type":"Point"}
}