{
  "type": "Feature",
  "properties": {
    "iso:country":"CH",
    "sg:address":"Terbinerstrasse 21",
    "sg:city":"Visp",
    "sg:orig_category":"HOTELS: OHNE RESTAURANT",
    "sg:phone":"+41 71 999 14 04",
    "sg:postcode":"3930",
    "sg:province":"Valais",
    "wof:name":"Pension Koller",
    "wof:placetype":"venue"
},
  "geometry": {"coordinates":[9.2849197388,47.1935844421],"type":"Point"}
}