{
  "type": "Feature",
  "properties": {
    "iso:country":"CH",
    "sg:address":"Stettemerstrasse 127",
    "sg:city":"Schaffhausen",
    "sg:orig_category":"Gesundheitswesen",
    "sg:phone":"+41 79 467 80 20",
    "sg:postcode":"8207",
    "sg:province":"Schaffhausen",
    "wof:name":"Seidenklang, Praxis F\u00fcr Naturheilkunde",
    "wof:placetype":"venue"
},
  "geometry": {"coordinates":[8.6576824188,47.7249221802],"type":"Point"}
}