{
  "type": "Feature",
  "properties": {
    "iso:country":"CH",
    "sg:address":"Gerechtigkeitsgasse 36",
    "sg:city":"Bern",
    "sg:orig_category":"Aktivit\u00e4ten der Generalunternehmen im Baugewerbe",
    "sg:phone":"+41 31 311 27 55",
    "sg:postcode":"3011",
    "sg:province":"Bern",
    "wof:name":"Abs Atelier F\u00fcr Architektur & Altbausanierung Ag",
    "wof:placetype":"venue"
},
  "geometry": {"coordinates":[7.454728,46.948566],"type":"Point"}
}