{
  "type": "Feature",
  "properties": {
    "iso:country":"CH",
    "sg:address":"Simmi",
    "sg:city":"Gams",
    "sg:orig_category":"Haltung von Gefl\u00fcgel",
    "sg:phone":"+41 81 771 19 55",
    "sg:postcode":"9473",
    "sg:province":"St. Gallen",
    "wof:name":"Hans Betschart Gefl\u00fcgelfarm",
    "wof:placetype":"venue"
},
  "geometry": {"coordinates":[9.4422750473,47.2040710449],"type":"Point"}
}