{
  "type": "Feature",
  "properties": {
    "iso:country":"CH",
    "sg:address":"Bodenwis 80 8493 Saland. Postfach",
    "sg:city":"Saland",
    "sg:orig_category":"Unclassifiable Establishments",
    "sg:phone":"+41 52 386 17 95",
    "sg:postcode":"8493",
    "sg:province":"Z\u00fcrich",
    "wof:name":"Ttb System Engineering Gmbh",
    "wof:placetype":"venue"
},
  "geometry": {"coordinates":[8.8541097641,47.3906326294],"type":"Point"}
}