{
  "type": "Feature",
  "properties": {
    "iso:country":"CH",
    "sg:address":"Village Rue Du 4 1424 Champagne. Postfach",
    "sg:city":"Champagne",
    "sg:orig_category":"M\u00f6belschreinereien",
    "sg:postcode":"1424",
    "sg:province":"Vaud",
    "wof:name":"Chevailler Agencement Meubles Sur Mesure Etc.; Fabrication",
    "wof:placetype":"venue"
},
  "geometry": {"coordinates":[6.6586098671,46.8312110901],"type":"Point"}
}