{
  "type": "Feature",
  "properties": {
    "iso:country":"CH",
    "sg:address":"Pf\u00e4ndwiesenstrasse 5",
    "sg:city":"Opfikon",
    "sg:orig_category":"Bauschreinerei",
    "sg:phone":"+41 18104029",
    "sg:postcode":"8152",
    "sg:province":"Z\u00fcrich",
    "wof:name":"Helmut Jucks Schreinerei",
    "wof:placetype":"venue"
},
  "geometry": {"coordinates":[8.573323,47.432877],"type":"Point"}
}