{
  "type": "Feature",
  "properties": {
    "iso:country":"CH",
    "sg:address":"Hauptstr. 169",
    "sg:city":"Bubendorf",
    "sg:classifiers":[
        {
            "category":"Professional",
            "subcategory":"Engineering",
            "type":"Services"
        }
    ],
    "sg:phone":"+41 61 931 10 00",
    "sg:postcode":"4416",
    "sg:province":"Basel-Landschaft",
    "sg:tags":[
        "machine",
        "chemistry",
        "-",
        "mechanical"
    ],
    "wof:name":"K\u00dcnzi Acs",
    "wof:placetype":"venue"
},
  "geometry": {"coordinates":[7.731726,47.440922],"type":"Point"}
}