{
  "type": "Feature",
  "properties": {
    "iso:country":"CH",
    "sg:address":"Ibergstrasse 29",
    "sg:city":"Bischofszell",
    "sg:orig_category":"Herstellung von Teppichen Verlegen von Fliesen U Platten",
    "sg:phone":"+41 71 422 37 31",
    "sg:postcode":"9220",
    "sg:province":"Thurgau",
    "wof:name":"Friederich",
    "wof:placetype":"venue"
},
  "geometry": {"coordinates":[9.2366809845,47.5028762817],"type":"Point"}
}