{
  "type": "Feature",
  "properties": {
    "iso:country":"CH",
    "sg:address":"Fr\u00e9d\u00e9ric Ingold-weg 5 2500 Biel/bienne. Postfach",
    "sg:city":"Biel/bienne",
    "sg:orig_category":"Unclassifiable Establishments",
    "sg:postcode":"2500",
    "sg:province":"Bern",
    "wof:name":"Hermo Ag",
    "wof:placetype":"venue"
},
  "geometry": {"coordinates":[7.2579159737,47.1461524963],"type":"Point"}
}