{
  "type": "Feature",
  "properties": {
    "iso:country":"CH",
    "sg:address":"Avenue De La Gare 24",
    "sg:city":"Del\u00e9mont",
    "sg:orig_category":"Kosmetikinstitute",
    "sg:phone":"+41 79 321 99 22",
    "sg:postcode":"2800",
    "sg:province":"Jura",
    "wof:name":"Viviane Jufer Institut De Beaut\u00e9 Aliz\u00e9s",
    "wof:placetype":"venue"
},
  "geometry": {"coordinates":[7.348982811,47.3647956848],"type":"Point"}
}