{
  "type": "Feature",
  "properties": {
    "iso:country":"CH",
    "sg:address":"Industriestrasse 31",
    "sg:city":"Dietlikon",
    "sg:orig_category":"Non-Classified Establishments",
    "sg:postcode":"8305",
    "sg:province":"Z\u00fcrich",
    "wof:name":"Gala Concept Ag Gastronomie-& Ladeneinricht.",
    "wof:placetype":"venue"
},
  "geometry": {"coordinates":[8.6185569763,47.4122657776],"type":"Point"}
}