{
  "type": "Feature",
  "properties": {
    "iso:country":"CH",
    "sg:address":"Plam Dil Bl\u00e4si 3 7078 Lenzerheide/lai. Postfach 20",
    "sg:city":"Lenzerheide/lai",
    "sg:orig_category":"Elektroinstallation",
    "sg:phone":"+41 81 384 11 97",
    "sg:postcode":"7078",
    "sg:province":"Graubunden",
    "wof:name":"Brazerol & St\u00f6ckli Ag, Elektro-technik",
    "wof:placetype":"venue"
},
  "geometry": {"coordinates":[9.560461998,46.7204284668],"type":"Point"}
}