{
  "type": "Feature",
  "properties": {
    "iso:country":"CH",
    "sg:address":"Aegeristrasse 5",
    "sg:city":"Sattel",
    "sg:orig_category":"Betrieb von Taxis",
    "sg:phone":"+41 22 342 92 90",
    "sg:postcode":"6417",
    "sg:province":"Schwyz",
    "wof:name":"Vouillamoz L\u00e9on",
    "wof:placetype":"venue"
},
  "geometry": {"coordinates":[6.141425,46.183311],"type":"Point"}
}