{
  "type": "Feature",
  "properties": {
    "iso:country":"CH",
    "sg:address":"Wismetstrasse 13 8872 Weesen. Postfach",
    "sg:city":"Weesen",
    "sg:classifiers":[
        {
            "category":"Professional",
            "subcategory":"Employment Agencies",
            "type":"Services"
        }
    ],
    "sg:postcode":"8872",
    "sg:province":"St. Gallen",
    "sg:tags":[
        "personal",
        "u",
        "stellenvermittlung"
    ],
    "wof:name":"Gaillard Michel, Bauarbeiten Im Akkord",
    "wof:placetype":"venue"
},
  "geometry": {"coordinates":[9.0904808044,47.1338272095],"type":"Point"}
}