{
  "type": "Feature",
  "properties": {
    "iso:country":"CH",
    "sg:address":"Sch\u00fctzenmattstrasse 9 4051 Basel. Postfach",
    "sg:city":"Basel",
    "sg:orig_category":"Physiotherapie",
    "sg:phone":"+41 61 262 21 21",
    "sg:postcode":"4003",
    "sg:province":"Basel-Stadt",
    "wof:name":"Lukas Baumann Medical Fitness",
    "wof:placetype":"venue"
},
  "geometry": {"coordinates":[7.5824270248,47.5568656921],"type":"Point"}
}