{
  "type": "Feature",
  "properties": {
    "iso:country":"CH",
    "sg:address":"2829",
    "sg:city":"Vermes",
    "sg:orig_category":"Verwertung von Milch",
    "sg:postcode":"2829",
    "sg:province":"Jura",
    "wof:name":"Soci\u00e9t\u00e9 De Laiterie De Vermes",
    "wof:placetype":"venue"
},
  "geometry": {"coordinates":[7.4739551544,47.3289413452],"type":"Point"}
}