{
  "type": "Feature",
  "properties": {
    "iso:country":"CH",
    "sg:address":"Vogelaustrasse 30",
    "sg:city":"Dietikon",
    "sg:orig_category":"Institutionen f\u00fcr Behinderte Sonderschulen",
    "sg:postcode":"8953",
    "sg:province":"Z\u00fcrich",
    "wof:name":"Stiftung Solvita Heilp\u00e4dag.schule Limmattal",
    "wof:placetype":"venue"
},
  "geometry": {"coordinates":[8.4122486115,47.3964004517],"type":"Point"}
}