{
  "type": "Feature",
  "properties": {
    "iso:country":"CH",
    "sg:address":"Saint-th\u00e9odule Rue 12",
    "sg:city":"Sion",
    "sg:orig_category":"Architektur U Ingenieurb\u00fcros",
    "sg:postcode":"1950",
    "sg:province":"Valais",
    "wof:name":"Oesch Christian",
    "wof:placetype":"venue"
},
  "geometry": {"coordinates":[7.471835,46.929111],"type":"Point"}
}