{
  "type": "Feature",
  "properties": {
    "iso:country":"CH",
    "sg:address":"Longemalle Place De 6-8 1204 Gen\u00e8ve. Postfach",
    "sg:city":"Gen\u00e8ve",
    "sg:orig_category":"Handels-H\u00e4user U Gesellschaften",
    "sg:postcode":"1201",
    "sg:province":"Gen\u00e8ve",
    "wof:name":"Magline Sa Activit\u00e9s Commerciales Et Financi\u00e8res Dans Le Dom. Nutritionnel, Di\u00e9t\u00e9tique, Cosm\u00e9tique Etc",
    "wof:placetype":"venue"
},
  "geometry": {"coordinates":[6.1497988701,46.2033653259],"type":"Point"}
}