{
  "type": "Feature",
  "properties": {
    "iso:country":"CH",
    "sg:address":"Hafenstrasse 120 4127 Birsfelden. Postfach",
    "sg:city":"Birsfelden",
    "sg:orig_category":"Fernmeldedienste",
    "sg:phone":"+41 31 312 17 75",
    "sg:postcode":"4127",
    "sg:province":"Basel-Landschaft",
    "wof:name":"Arocom Ag Kommunikationstechnik; Handel, Dienstleistungen Usw",
    "wof:placetype":"venue"
},
  "geometry": {"coordinates":[7.6348347664,47.5576286316],"type":"Point"}
}