{
  "type": "Feature",
  "properties": {
    "iso:country":"CH",
    "sg:address":"Rue De La R\u00f4tisserie 29",
    "sg:city":"Gen\u00e8ve",
    "sg:orig_category":"Dienstleistungen von Beteiligungsgesellschaften Grosshandel mit festen Brennstoffen U Mineral\u00f6lerzeu",
    "sg:phone":"+41 22 817 10 60",
    "sg:postcode":"1204",
    "sg:province":"Gen\u00e8ve",
    "wof:name":"Taurus Petroleum Sa",
    "wof:placetype":"venue"
},
  "geometry": {"coordinates":[6.1475892067,46.2026901245],"type":"Point"}
}