{
  "type": "Feature",
  "properties": {
    "iso:country":"CH",
    "sg:address":"Baselstrasse 30",
    "sg:city":"Dagmersellen",
    "sg:orig_category":"Darlehenskassen U Raiffeisenbanken",
    "sg:phone":"+41 33 849 16 62",
    "sg:postcode":"6252",
    "sg:province":"Luzern",
    "wof:name":"Raiffeisenbank",
    "wof:placetype":"venue"
},
  "geometry": {"coordinates":[7.928803,46.717098],"type":"Point"}
}