{
  "type": "Feature",
  "properties": {
    "iso:country":"CH",
    "sg:address":"Chemin D'eysins 53a",
    "sg:city":"Nyon",
    "sg:orig_category":"Softwareentwicklung U beratung",
    "sg:phone":"+41 21 731 41 40",
    "sg:postcode":"1260",
    "sg:province":"Vaud",
    "wof:name":"Unilog Sa",
    "wof:placetype":"venue"
},
  "geometry": {"coordinates":[6.6639499664,46.5902061462],"type":"Point"}
}