{
  "type": "Feature",
  "properties": {
    "iso:country":"CH",
    "sg:address":"Chemin Du Ch\u00eane 6",
    "sg:city":"Corcelles-payerne",
    "sg:orig_category":"Tierarztpraxis",
    "sg:phone":"+41 32 751 30 76",
    "sg:postcode":"1562",
    "sg:province":"Vaud",
    "wof:name":"Dr M\u00e9d. V\u00e9t. Peter Hanzal M\u00e9decin V\u00e9t\u00e9rinaire",
    "wof:placetype":"venue"
},
  "geometry": {"coordinates":[7.090241909,47.0653533936],"type":"Point"}
}