{
  "type": "Feature",
  "properties": {
    "iso:country":"CH",
    "sg:address":"Via Emilio Bossi 12",
    "sg:city":"Chiasso",
    "sg:orig_category":"Detailhandel mit B\u00fcchern, Zeitungen, Schreib U Papeteriewaren",
    "sg:postcode":"6830",
    "sg:province":"Ticino",
    "wof:name":"Cartoleria Grasselli Carla",
    "wof:placetype":"venue"
},
  "geometry": {"coordinates":[9.03149,45.834686],"type":"Point"}
}