{
  "type": "Feature",
  "properties": {
    "iso:country":"CH",
    "sg:address":"St-cergue Route De",
    "sg:city":"Tr\u00e9lex",
    "sg:orig_category":"Wohnheime",
    "sg:postcode":"1270",
    "sg:province":"Vaud",
    "wof:name":"Fondation L'or\u00e9e Pour L'\u00e9panouissement Des Handicap\u00e9s Mentaux",
    "wof:placetype":"venue"
},
  "geometry": {"coordinates":[6.2042160034,46.4165382385],"type":"Point"}
}