{
  "type": "Feature",
  "properties": {
    "addr:full":"Drei Seen Hof Nussbaumen Thurgau 8537",
    "addr:postcode":"8537",
    "iso:country":"CH",
    "sg:address":"Drei Seen Hof",
    "sg:city":"Nussbaumen",
    "sg:classifiers":[
        {
            "category":"Government",
            "subcategory":"Fire Station",
            "type":"Public Place"
        }
    ],
    "sg:phone":"+41 52 745 31 31",
    "sg:postcode":"8537",
    "sg:province":"Thurgau",
    "sg:tags":[
        "filter",
        "air"
    ],
    "wof:name":"Arroyo-produkte",
    "wof:placetype":"venue"
},
  "geometry": {"coordinates":[8.827455,47.624763],"type":"Point"}
}