{
  "type": "Feature",
  "properties": {
    "iso:country":"CH",
    "sg:address":"Chemin Des Aulnes 15a",
    "sg:city":"Biel/bienne",
    "sg:classifiers":[
        {
            "category":"Government",
            "subcategory":"Fire Station",
            "type":"Public Place"
        }
    ],
    "sg:phone":"+41 32 365 81 08",
    "sg:postcode":"2503",
    "sg:province":"Bern",
    "sg:tags":[
        "component",
        "watch",
        "clock"
    ],
    "wof:name":"Jismaa Etablissement",
    "wof:placetype":"venue"
},
  "geometry": {"coordinates":[7.25451,47.123566],"type":"Point"}
}