{
  "type": "Feature",
  "properties": {
    "iso:country":"CH",
    "sg:address":"Mornex Chemin De 3",
    "sg:city":"Lausanne",
    "sg:orig_category":"Non-Classified Establishments",
    "sg:postcode":"1003",
    "sg:province":"Vaud",
    "wof:name":"Cabinet Indigo S\u00e0rl",
    "wof:placetype":"venue"
},
  "geometry": {"coordinates":[6.8667049408,46.6004562378],"type":"Point"}
}