{
  "type": "Feature",
  "properties": {
    "iso:country":"CH",
    "sg:address":"M\u00fchlehaldenstrasse 18",
    "sg:city":"Dietikon",
    "sg:orig_category":"Fachdetailhandel mit pharmazeutischen Produkten",
    "sg:postcode":"8953",
    "sg:province":"Z\u00fcrich",
    "wof:name":"Kemper R. Preventa",
    "wof:placetype":"venue"
},
  "geometry": {"coordinates":[8.3975973129,47.3999252319],"type":"Point"}
}