{
  "type": "Feature",
  "properties": {
    "iso:country":"CH",
    "sg:address":"Weltistrasse 6",
    "sg:city":"Zollikon",
    "sg:orig_category":"Forschung U Entwicklung im Bereich der Naturwissenschaften",
    "sg:phone":"+41 13913136",
    "sg:postcode":"8702",
    "sg:province":"Z\u00fcrich",
    "wof:name":"Freymond Potential Research",
    "wof:placetype":"venue"
},
  "geometry": {"coordinates":[8.5760240555,47.3347167969],"type":"Point"}
}