{
  "type": "Feature",
  "properties": {
    "iso:country":"CH",
    "sg:address":"Riedstrasse 10",
    "sg:city":"Dietikon",
    "sg:classifiers":[
        {
            "category":"Restaurant",
            "type":"Food & Drink"
        }
    ],
    "sg:postcode":"8953",
    "sg:province":"Z\u00fcrich",
    "wof:name":"Euro Muzik Gmbh",
    "wof:placetype":"venue"
},
  "geometry": {"coordinates":[7.8657898903,47.3410415649],"type":"Point"}
}