{
  "type": "Feature",
  "properties": {
    "iso:country":"CH",
    "sg:address":"Rietenbergweg 11",
    "sg:city":"Villmergen",
    "sg:orig_category":"S\u00e4ge, Hobel U Holzimpr\u00e4gnierwerke",
    "sg:phone":"+41 56 621 04 00",
    "sg:postcode":"5612",
    "sg:province":"Aargau",
    "wof:name":"Bruma Brunner M. Holzbearbeitung",
    "wof:placetype":"venue"
},
  "geometry": {"coordinates":[8.2404632568,47.3475952148],"type":"Point"}
}