{
  "type": "Feature",
  "properties": {
    "iso:country":"CH",
    "sg:address":"Le Vieux-bourg 9",
    "sg:city":"Denges",
    "sg:orig_category":"Wirtschaftspr\u00fcfung, Steuerberatung U Treuhand",
    "sg:phone":"+41 21 801 66 30",
    "sg:postcode":"1026",
    "sg:province":"Vaud",
    "wof:name":"Hm Comptabilit\u00e9 Mermod H\u00e9l\u00e8ne",
    "wof:placetype":"venue"
},
  "geometry": {"coordinates":[6.5414271355,46.5236434937],"type":"Point"}
}