{
  "type": "Feature",
  "properties": {
    "iso:country":"CH",
    "sg:address":"Nordringstrasse 28 4702 Oensingen. Postfach",
    "sg:city":"Oensingen",
    "sg:orig_category":"Herstellung von Betonerzeugnissen f\u00fcr den Bau Herstellung von Elektromotoren, Generatoren U Transfor",
    "sg:phone":"+41 62 396 22 77",
    "sg:postcode":"4702",
    "sg:province":"Solothurn",
    "wof:name":"Sema Ag",
    "wof:placetype":"venue"
},
  "geometry": {"coordinates":[7.7143797874,47.284034729],"type":"Point"}
}