{
  "type": "Feature",
  "properties": {
    "iso:country":"CH",
    "sg:address":"Krummturmstrasse 15 4500 Solothurn. Postfach 442",
    "sg:city":"Solothurn",
    "sg:orig_category":"Politische Parteien FDP",
    "sg:phone":"+41 71 923 12 32",
    "sg:postcode":"4502",
    "sg:province":"Solothurn",
    "wof:name":"Fdp Des Kantons Thurgau",
    "wof:placetype":"venue"
},
  "geometry": {"coordinates":[-77.13302612299999,40.4769287109],"type":"Point"}
}