{
  "type": "Feature",
  "properties": {
    "iso:country":"CH",
    "sg:address":"Dorfstrasse 37",
    "sg:city":"W\u00fcrenlos",
    "sg:orig_category":"Vermietung U Verpachtung von eigenen Immobilien",
    "sg:postcode":"5436",
    "sg:province":"Aargau",
    "wof:name":"Basema Ag",
    "wof:placetype":"venue"
},
  "geometry": {"coordinates":[8.3648834229,47.443321228],"type":"Point"}
}