{
  "type": "Feature",
  "properties": {
    "iso:country":"CH",
    "sg:address":"Sch\u00e4dr\u00fctihalde 16",
    "sg:city":"Luzern",
    "sg:orig_category":"Architektur U Ingenieurb\u00fcros Innenarchitekturb\u00fcros",
    "sg:phone":"+41 41 370 85 05",
    "sg:postcode":"6006",
    "sg:province":"Luzern",
    "wof:name":"Drognitz Volker R.",
    "wof:placetype":"venue"
},
  "geometry": {"coordinates":[8.347408,47.058067],"type":"Point"}
}