{
  "type": "Feature",
  "properties": {
    "iso:country":"CH",
    "sg:address":"Rossmarktplatz 17 4500 Solothurn. Postfach",
    "sg:city":"Solothurn",
    "sg:orig_category":"Arbeitnehmerverb\u00e4nde",
    "sg:postcode":"4502",
    "sg:province":"Solothurn",
    "wof:name":"Soc.dei Capi Di Polizia Delle Citt\u00e0 Svizzere",
    "wof:placetype":"venue"
},
  "geometry": {"coordinates":[8.95356,46.00478],"type":"Point"}
}