{
  "type": "Feature",
  "properties": {
    "iso:country":"CH",
    "sg:address":"Passage Malbuisson 19",
    "sg:city":"Gen\u00e8ve",
    "sg:orig_category":"Detailhandel mit Radio U Fernsehger\u00e4ten Detailhandel mit elektrischen Haushalts-,Radio U Fernsehger\u00e4",
    "sg:phone":"+41 22 311 12 11",
    "sg:postcode":"1204",
    "sg:province":"Gen\u00e8ve",
    "wof:name":"City-disc Ag",
    "wof:placetype":"venue"
},
  "geometry": {"coordinates":[6.1463751793,46.2035140991],"type":"Point"}
}