{
  "type": "Feature",
  "properties": {
    "addr:full":"Ruelle Du Temple 2 Cheseaux-lausanne Vaud 1033",
    "addr:housenumber":"2",
    "addr:postcode":"1033",
    "addr:street":"Ruelle Du Temple",
    "iso:country":"CH",
    "sg:address":"Ruelle Du Temple 2",
    "sg:city":"Cheseaux-lausanne",
    "sg:orig_category":"Detailhandel mit Antiquit\u00e4ten Sonstiger Fachdetailhandel in Verkaufsr\u00e4umen",
    "sg:phone":"+41 79 219 18 58",
    "sg:postcode":"1033",
    "sg:province":"Vaud",
    "wof:name":"Emile Joyet Armes Anciennes",
    "wof:placetype":"venue"
},
  "geometry": {"coordinates":[6.6057,46.584667],"type":"Point"}
}