{
  "type": "Feature",
  "properties": {
    "iso:country":"CH",
    "sg:address":"B\u00fchlmattstrasse 167",
    "sg:city":"Schupfart",
    "sg:orig_category":"Grosshandel mit Spielwaren Herstellung von sonstigen Erzeugnissen",
    "sg:phone":"+41 79 333 96 67",
    "sg:postcode":"4325",
    "sg:province":"Aargau",
    "wof:name":"Amsler Warenhaus & Festartikel Ag",
    "wof:placetype":"venue"
},
  "geometry": {"coordinates":[7.9671401978,47.5147285461],"type":"Point"}
}