{
  "type": "Feature",
  "properties": {
    "iso:country":"CH",
    "sg:address":"Im Hof 2 Oberwil B. D\u00e4gerlen",
    "sg:city":"Rutschwil-d\u00e4gerlen",
    "sg:orig_category":"Abbruch U Sprenggewerbe, Erdbewegungsarbeiten",
    "sg:postcode":"8471",
    "sg:province":"Z\u00fcrich",
    "wof:name":"Hauser Albert",
    "wof:placetype":"venue"
},
  "geometry": {"coordinates":[8.715782,47.573483],"type":"Point"}
}