{
  "type": "Feature",
  "properties": {
    "iso:country":"CH",
    "sg:address":"Junkerbifangstrasse 8 4800 Zofingen. Postfach 1107",
    "sg:city":"Zofingen",
    "sg:orig_category":"Herstellung von Bekleidung U Pelzwaren Informatikdienste",
    "sg:phone":"+41 62 751 26 01",
    "sg:postcode":"4800",
    "sg:province":"Aargau",
    "wof:name":"Gertsch Consulting & Mode Vision Beratung In Der Textilen Kette & Cad Dienstleistungen",
    "wof:placetype":"venue"
},
  "geometry": {"coordinates":[7.946064949,47.2839660645],"type":"Point"}
}