{
  "type": "Feature",
  "properties": {
    "iso:country":"CH",
    "sg:address":"Dorf 6 6231 Schlierbach. Postfach 63",
    "sg:city":"Schlierbach",
    "sg:orig_category":"Allgemeiner Hochbau Strassenbau",
    "sg:phone":"+41 41 933 26 05",
    "sg:postcode":"6231",
    "sg:province":"Luzern",
    "wof:name":"Hans Hartmann",
    "wof:placetype":"venue"
},
  "geometry": {"coordinates":[8.111481,47.223953],"type":"Point"}
}