{
  "type": "Feature",
  "properties": {
    "iso:country":"CH",
    "sg:address":"Bahnhofstrasse 14 8708 M\u00e4nnedorf. Postfach",
    "sg:city":"M\u00e4nnedorf",
    "sg:orig_category":"Pensionskassen",
    "sg:phone":"+41 19221300",
    "sg:postcode":"8708",
    "sg:province":"Z\u00fcrich",
    "wof:name":"Stiftung Der Gewerbebank M\u00e4nnedorf F\u00fcr Personalf\u00fcrsorge",
    "wof:placetype":"venue"
},
  "geometry": {"coordinates":[8.6919050217,47.2532920837],"type":"Point"}
}