{
  "type": "Feature",
  "properties": {
    "iso:country":"CH",
    "sg:address":"M\u00f6\u00f6sli",
    "sg:city":"Alchenstorf",
    "sg:classifiers":[
        {
            "category":"Insurance",
            "subcategory":"Insurance Agent",
            "type":"Services"
        }
    ],
    "sg:phone":"+41 34 415 10 34",
    "sg:postcode":"3473",
    "sg:province":"Bern",
    "sg:tags":[
        "versicherungsagenturen",
        "-broker"
    ],
    "wof:name":"Winterthur Versicherungen Agentur Hans-ulrich Stettler",
    "wof:placetype":"venue"
},
  "geometry": {"coordinates":[7.6282539368,47.1223945618],"type":"Point"}
}