{
  "type": "Feature",
  "properties": {
    "iso:country":"CH",
    "sg:address":"La Chavanne",
    "sg:city":"V\u00e9rossaz",
    "sg:orig_category":"Zimmerei, Ingenieurholzbau",
    "sg:phone":"+41 24 485 26 12",
    "sg:postcode":"1891",
    "sg:province":"Valais",
    "wof:name":"G\u00e9rard Vo\u00ebffray Constr.de Chalets,charpente",
    "wof:placetype":"venue"
},
  "geometry": {"coordinates":[6.980714798,46.2162895203],"type":"Point"}
}