{
  "type": "Feature",
  "properties": {
    "iso:country":"CH",
    "sg:address":"Sch\u00fctzenstrasse 8",
    "sg:city":"Steffisburg",
    "sg:orig_category":"G\u00fcterbef\u00f6rderung im Strassenverkehr",
    "sg:phone":"+41 33 437 08 90",
    "sg:postcode":"3612",
    "sg:province":"Bern",
    "wof:name":"Heimann Hans-rudolf, Transporte",
    "wof:placetype":"venue"
},
  "geometry": {"coordinates":[7.6315951347,46.7886505127],"type":"Point"}
}