{
  "type": "Feature",
  "properties": {
    "iso:country":"CH",
    "sg:address":"Route De St-georges 47",
    "sg:city":"Petit Lancy",
    "sg:classifiers":[
        {
            "category":"Banks & Credit Unions",
            "subcategory":"Bank",
            "type":"Services"
        }
    ],
    "sg:phone":"+41 22 375 59 15",
    "sg:postcode":"1213",
    "sg:province":"Gen\u00e8ve",
    "wof:name":"Schweizerischer Bankverein",
    "wof:placetype":"venue"
},
  "geometry": {"coordinates":[6.122446,46.194725],"type":"Point"}
}