{
  "type": "Feature",
  "properties": {
    "iso:country":"CH",
    "sg:address":"Steinbruch",
    "sg:city":"Ostermundigen",
    "sg:orig_category":"Gewinnung von Natursteinen f\u00fcr den Bau Herstellung von Betonerzeugnissen f\u00fcr den Bau",
    "sg:phone":"+41 31 931 95 94",
    "sg:postcode":"3072",
    "sg:province":"Bern",
    "wof:name":"Carlo Bernasconi Ag",
    "wof:placetype":"venue"
},
  "geometry": {"coordinates":[7.4948449135,46.9519767761],"type":"Point"}
}