{
  "type": "Feature",
  "properties": {
    "iso:country":"CH",
    "sg:address":"Solothurnstrasse 31",
    "sg:city":"Jegenstorf",
    "sg:orig_category":"Finanzierungsinstitutionen",
    "sg:postcode":"3303",
    "sg:province":"Bern",
    "wof:name":"Gramazit Ag",
    "wof:placetype":"venue"
},
  "geometry": {"coordinates":[7.5113101006,47.0535697937],"type":"Point"}
}