{
  "type": "Feature",
  "properties": {
    "iso:country":"CH",
    "sg:address":"Route Du V\u00e9lodrome 35",
    "sg:city":"Plan-les-ouates",
    "sg:orig_category":"Sonstiger Grosshandel",
    "sg:phone":"+41 22 884 16 30",
    "sg:postcode":"1228",
    "sg:province":"Gen\u00e8ve",
    "wof:name":"Digest Sa",
    "wof:placetype":"venue"
},
  "geometry": {"coordinates":[6.1100468636,46.1707420349],"type":"Point"}
}