{
  "type": "Feature",
  "properties": {
    "iso:country":"CH",
    "sg:address":"Grenzweg 1 3098 K\u00f6niz. Postfach",
    "sg:city":"Liebefeld",
    "sg:orig_category":"Werbung",
    "sg:postcode":"3097",
    "sg:province":"Bern",
    "wof:name":"Max M\u00f6ssinger",
    "wof:placetype":"venue"
},
  "geometry": {"coordinates":[7.4230108261,46.9339065552],"type":"Point"}
}