{
  "type": "Feature",
  "properties": {
    "iso:country":"CH",
    "sg:address":"Landstrasse 36 8197 Rafz. Postfach",
    "sg:city":"Rafz",
    "sg:orig_category":"Fussboden, Fliesen U Plattenlegerei, Tapeziererei Verlegen von Fliesen U Platten",
    "sg:phone":"+41 79 437 16 49",
    "sg:postcode":"8197",
    "sg:province":"Z\u00fcrich",
    "wof:name":"Baur Ulrich",
    "wof:placetype":"venue"
},
  "geometry": {"coordinates":[8.5425367355,47.6121063232],"type":"Point"}
}