{
  "type": "Feature",
  "properties": {
    "iso:country":"CH",
    "sg:address":"Wegastrasse 1",
    "sg:city":"Allschwil",
    "sg:orig_category":"Hardwareberatung",
    "sg:postcode":"4123",
    "sg:province":"Basel-Landschaft",
    "wof:name":"Surfers Paradise Oeschger & Gerber",
    "wof:placetype":"venue"
},
  "geometry": {"coordinates":[7.5593180656,47.5570220947],"type":"Point"}
}