{
  "type": "Feature",
  "properties": {
    "iso:country":"CH",
    "sg:address":"Kreuzwiesen 9",
    "sg:city":"Z\u00fcrich",
    "sg:orig_category":"Sportvereine Ballsport Tennis",
    "sg:phone":"+41 13201482",
    "sg:postcode":"8051",
    "sg:province":"Z\u00fcrich",
    "wof:name":"Tc Buchegg",
    "wof:placetype":"venue"
},
  "geometry": {"coordinates":[8.5746526718,47.4068260193],"type":"Point"}
}