{
  "type": "Feature",
  "properties": {
    "iso:country":"CH",
    "sg:address":"Buerstrasse 7",
    "sg:city":"Lostorf",
    "sg:orig_category":"Grosshandel mit lebenden Tieren",
    "sg:postcode":"4654",
    "sg:province":"Solothurn",
    "wof:name":"Stall Senn Ag",
    "wof:placetype":"venue"
},
  "geometry": {"coordinates":[7.9567170143,47.3764228821],"type":"Point"}
}