{
  "type": "Feature",
  "properties": {
    "iso:country":"CH",
    "sg:address":"Dorfstrasse 53",
    "sg:city":"Freienstein",
    "sg:orig_category":"Stukkateurgewerbe, Gipserei U Verputzerei",
    "sg:postcode":"8427",
    "sg:province":"Z\u00fcrich",
    "wof:name":"R. Marfurt, Gipsergesch\u00e4ft",
    "wof:placetype":"venue"
},
  "geometry": {"coordinates":[8.5848779678,47.5314712524],"type":"Point"}
}