{
  "type": "Feature",
  "properties": {
    "iso:country":"CH",
    "sg:address":"Gotthelfstrasse 101 4054 Basel. Postfach",
    "sg:city":"Basel",
    "sg:orig_category":"Sonstiger Grosshandel",
    "sg:phone":"+41 61 302 03 08",
    "sg:postcode":"4051",
    "sg:province":"Basel-Stadt",
    "wof:name":"Aza Wolski Import Export Warenhandel, Bes. Textilien, Lederartikel, Lebensmittel. Im, Export",
    "wof:placetype":"venue"
},
  "geometry": {"coordinates":[7.5683460236,47.5569076538],"type":"Point"}
}