{
  "type": "Feature",
  "properties": {
    "iso:country":"CH",
    "sg:address":"B\u00e4lliz 57 3600 Thun. Postfach",
    "sg:city":"Thun",
    "sg:orig_category":"Detailhandel mit Bekleidung Detailhandel mit Pelzwaren",
    "sg:phone":"+41 33 222 18 31",
    "sg:postcode":"3601",
    "sg:province":"Bern",
    "wof:name":"Weber Pelze, Inh. Isler-weber E.",
    "wof:placetype":"venue"
},
  "geometry": {"coordinates":[7.628706,46.757782],"type":"Point"}
}