{
  "type": "Feature",
  "properties": {
    "addr:full":"Schulstrasse 3 W\u00e4ldi Thurgau 8564",
    "addr:housenumber":"3",
    "addr:postcode":"8564",
    "addr:street":"Schulstrasse;Thurgau",
    "iso:country":"CH",
    "sg:address":"Schulstrasse 3",
    "sg:city":"W\u00e4ldi",
    "sg:orig_category":"Dachdeckerei",
    "sg:phone":"+41 62 298 17 40",
    "sg:postcode":"8564",
    "sg:province":"Thurgau",
    "wof:name":"Willy W\u00fcest Bedachungen",
    "wof:placetype":"venue"
},
  "geometry": {"coordinates":[7.957262,47.415276],"type":"Point"}
}