{
  "type": "Feature",
  "properties": {
    "iso:country":"CH",
    "sg:address":"Badenerstrasse 41 8000 Z\u00fcrich. Postfach",
    "sg:city":"Z\u00fcrich",
    "sg:orig_category":"Unternehmensberatung",
    "sg:postcode":"8004",
    "sg:province":"Z\u00fcrich",
    "wof:name":"Baitsch Christoph Organisationsberatung",
    "wof:placetype":"venue"
},
  "geometry": {"coordinates":[8.5288295746,47.3732452393],"type":"Point"}
}