{
  "type": "Feature",
  "properties": {
    "iso:country":"CH",
    "sg:address":"Schulstrasse 10 9402 M\u00f6rschwil. Postfach 11",
    "sg:city":"M\u00f6rschwil",
    "sg:orig_category":"Primarschulen",
    "sg:phone":"+41 71 866 24 36",
    "sg:postcode":"9402",
    "sg:province":"St. Gallen",
    "wof:name":"Primarschule Gallusschulhaus",
    "wof:placetype":"venue"
},
  "geometry": {"coordinates":[9.4266166687,47.4680213928],"type":"Point"}
}