{
  "type": "Feature",
  "properties": {
    "iso:country":"CH",
    "sg:address":"Nidaugasse 46 2500 Biel/bienne. Postfach",
    "sg:city":"Biel/bienne",
    "sg:orig_category":"Detailhandel mit Bekleidung",
    "sg:postcode":"2502",
    "sg:province":"Bern",
    "wof:name":"Wantz & Br\u00fcgger Boutique Bel Etage",
    "wof:placetype":"venue"
},
  "geometry": {"coordinates":[7.246244,47.138962],"type":"Point"}
}