{
  "type": "Feature",
  "properties": {
    "iso:country":"CH",
    "sg:address":"Solothurnerstrasse 31",
    "sg:city":"Basel",
    "sg:orig_category":"Schaustellergewerbe U Vergn\u00fcgungsparks",
    "sg:postcode":"4053",
    "sg:province":"Basel-Stadt",
    "wof:name":"Howald Grillbraterei & Vergn\u00fcgungsbetriebe Ag",
    "wof:placetype":"venue"
},
  "geometry": {"coordinates":[7.5910520554,47.5446815491],"type":"Point"}
}