{
  "type": "Feature",
  "properties": {
    "iso:country":"CH",
    "sg:address":"Tromg\u00e4ssli 7 3303 Jegenstorf. Postfach 38",
    "sg:city":"Jegenstorf",
    "sg:orig_category":"Maler U Glasergewerbe Stukkateurgewerbe, Gipserei U Verputzerei",
    "sg:phone":"+41 31 761 00 31",
    "sg:postcode":"3303",
    "sg:province":"Bern",
    "wof:name":"Haller E. Ag, Malerei & Gipserei",
    "wof:placetype":"venue"
},
  "geometry": {"coordinates":[7.5035238266,47.0471687317],"type":"Point"}
}