{
  "type": "Feature",
  "properties": {
    "iso:country":"CH",
    "sg:address":"Z. I. En Vanel 1880 Bex Case Postale 276",
    "sg:city":"Bex",
    "sg:orig_category":"Herstellung von Metallkonstruktionen Stahl U Leichtmetallbau",
    "sg:phone":"+41 24 463 02 22",
    "sg:postcode":"1880",
    "sg:province":"Vaud",
    "wof:name":"Meili Alfred Sa Bex, Constructions M\u00e9talliques",
    "wof:placetype":"venue"
},
  "geometry": {"coordinates":[7.015681,46.250259],"type":"Point"}
}