{
  "type": "Feature",
  "properties": {
    "iso:country":"CH",
    "sg:address":"Haldenweg 32",
    "sg:city":"Herisau",
    "sg:orig_category":"Sportvereine Turnen Damen",
    "sg:phone":"+41 71 351 51 08",
    "sg:postcode":"9100",
    "sg:province":"Appenzell Ausserrhoden",
    "wof:name":"Frauenturnverein",
    "wof:placetype":"venue"
},
  "geometry": {"coordinates":[9.2875318527,47.3870544434],"type":"Point"}
}