{
  "type": "Feature",
  "properties": {
    "iso:country":"CH",
    "sg:address":"Langnaustrasse 2",
    "sg:city":"Z\u00e4ziwil",
    "sg:orig_category":"Gasth\u00f6fe/Gasth\u00e4user mit Restaurant",
    "sg:phone":"+41 31 711 05 36",
    "sg:postcode":"3532",
    "sg:province":"Bern",
    "wof:name":"Gasthof Z. Krone",
    "wof:placetype":"venue"
},
  "geometry": {"coordinates":[7.6618452072,46.9017448425],"type":"Point"}
}