{
  "type": "Feature",
  "properties": {
    "iso:country":"CH",
    "sg:address":"Vermont Rue De 53",
    "sg:city":"Genf",
    "sg:orig_category":"Reiseb\u00fcros U Reiseveranstalter",
    "sg:phone":"+41 41 870 01 54",
    "sg:postcode":"1200",
    "sg:province":"Gen\u00e8ve",
    "wof:name":"Milosavljevic Reisen",
    "wof:placetype":"venue"
},
  "geometry": {"coordinates":[8.6497831345,46.8757858276],"type":"Point"}
}