{
  "type": "Feature",
  "properties": {
    "iso:country":"CH",
    "sg:address":"B\u00fcren 5",
    "sg:city":"Gansingen",
    "sg:orig_category":"RESTAURANTS: TEA-ROOMS",
    "sg:postcode":"5272",
    "sg:province":"Aargau",
    "wof:name":"Erdin Erben Jos.",
    "wof:placetype":"venue"
},
  "geometry": {"coordinates":[8.1384716034,47.5326423645],"type":"Point"}
}