{
  "type": "Feature",
  "properties": {
    "iso:country":"CH",
    "sg:address":"Pont-neuf",
    "sg:city":"Corcelles-payerne",
    "sg:orig_category":"Unternehmensberatung Weiterbildungskurse and Seminar Anbieter",
    "sg:phone":"+41 26 660 52 67",
    "sg:postcode":"1562",
    "sg:province":"Vaud",
    "wof:name":"Huthwaite Schweiz Gmbh",
    "wof:placetype":"venue"
},
  "geometry": {"coordinates":[6.9533548355,46.8540458679],"type":"Point"}
}