{
  "type": "Feature",
  "properties": {
    "iso:country":"CH",
    "sg:address":"Gerstacherstrasse 9 8123 Ebmatingen. Postfach",
    "sg:city":"Ebmatingen",
    "sg:orig_category":"Unternehmensberatung",
    "sg:phone":"+41 19801067",
    "sg:postcode":"8123",
    "sg:province":"Z\u00fcrich",
    "wof:name":"Consit Ag",
    "wof:placetype":"venue"
},
  "geometry": {"coordinates":[8.6361598969,47.3520240784],"type":"Point"}
}