{
  "type": "Feature",
  "properties": {
    "iso:country":"CH",
    "sg:address":"Neuhausstrasse 21",
    "sg:city":"Basel",
    "sg:orig_category":"Instandhaltung U Reparatur von Automobilen",
    "sg:phone":"+41 61 631 28 00",
    "sg:postcode":"4057",
    "sg:province":"Basel-Stadt",
    "wof:name":"Garage Koffel H. Ag",
    "wof:placetype":"venue"
},
  "geometry": {"coordinates":[7.5939831734,47.582698822],"type":"Point"}
}