{
  "type": "Feature",
  "properties": {
    "iso:country":"CH",
    "sg:address":"Neubr\u00fcckstrasse 105 3012 Bern. Postfach",
    "sg:city":"Bern",
    "sg:orig_category":"Handels-H\u00e4user U Gesellschaften",
    "sg:postcode":"3005",
    "sg:province":"Bern",
    "wof:name":"Menato Elena Handelsagentur",
    "wof:placetype":"venue"
},
  "geometry": {"coordinates":[7.4353709221,46.9592857361],"type":"Point"}
}