{
  "type": "Feature",
  "properties": {
    "iso:country":"CH",
    "sg:address":"Alte Landstrasse 5 8800 Thalwil. Postfach 3179",
    "sg:city":"Thalwil",
    "sg:orig_category":"Oberfl\u00e4chenveredlung U W\u00e4rmebehandlung",
    "sg:phone":"+41 41 260 35 35",
    "sg:postcode":"8800",
    "sg:province":"Z\u00fcrich",
    "wof:name":"Galva Ag, Metallveredlung",
    "wof:placetype":"venue"
},
  "geometry": {"coordinates":[8.288731575,47.0695228577],"type":"Point"}
}