{
  "type": "Feature",
  "properties": {
    "iso:country":"CH",
    "sg:address":"Hubelstrasse",
    "sg:city":"Obernau",
    "sg:orig_category":"Primarschulen",
    "sg:postcode":"6012",
    "sg:province":"Luzern",
    "wof:name":"Primarschule Obernau 2",
    "wof:placetype":"venue"
},
  "geometry": {"coordinates":[8.2527971268,47.0311126709],"type":"Point"}
}