{
  "type": "Feature",
  "properties": {
    "iso:country":"CH",
    "sg:address":"Eaux-vives Place Des 6",
    "sg:city":"Gen\u00e8ve",
    "sg:orig_category":"Unclassifiable Establishments",
    "sg:postcode":"1207",
    "sg:province":"Gen\u00e8ve",
    "wof:name":"Close Trustees (switzerland) Sa",
    "wof:placetype":"venue"
},
  "geometry": {"coordinates":[6.1663861275,46.2004928589],"type":"Point"}
}