{
  "type": "Feature",
  "properties": {
    "iso:country":"CH",
    "sg:address":"Grundstrasse 13 8126 Zumikon. Postfach 35",
    "sg:city":"Zumikon",
    "sg:orig_category":"Markt U Meinungsforschung Public-Relations-Agenturen",
    "sg:phone":"+41 62 205 15 35",
    "sg:postcode":"8126",
    "sg:province":"Z\u00fcrich",
    "wof:name":"Gm Promotion Ag",
    "wof:placetype":"venue"
},
  "geometry": {"coordinates":[7.8644337654,47.3423233032],"type":"Point"}
}