{
  "type": "Feature",
  "properties": {
    "iso:country":"CH",
    "sg:address":"Chlotengasse 12",
    "sg:city":"Tagelswangen",
    "sg:classifiers":[
        {
            "category":"Professional",
            "subcategory":"Advertising",
            "type":"Services"
        }
    ],
    "sg:phone":"+41 52 355 34 34",
    "sg:postcode":"8317",
    "sg:province":"Z\u00fcrich",
    "sg:tags":[
        "postcard"
    ],
    "wof:name":"Marty Druckmedien Ag",
    "wof:placetype":"venue"
},
  "geometry": {"coordinates":[8.669973,47.430679],"type":"Point"}
}