{
  "type": "Feature",
  "properties": {
    "iso:country":"CH",
    "sg:address":"Rue Caroline 6",
    "sg:city":"Gen\u00e8ve",
    "sg:orig_category":"Herstellung von keramischen Haushaltswaren U Ziergegenst\u00e4nden",
    "sg:postcode":"1200",
    "sg:province":"Gen\u00e8ve",
    "wof:name":"Mulattieri-boudet Christiane.",
    "wof:placetype":"venue"
},
  "geometry": {"coordinates":[6.1384549141,46.1920051575],"type":"Point"}
}