{
  "type": "Feature",
  "properties": {
    "iso:country":"CH",
    "sg:address":"Place De La Gare 2",
    "sg:city":"Sion",
    "sg:orig_category":"Sportschulen Fern\u00f6stliche Kampfsportarten",
    "sg:phone":"+41 32 931 01 51",
    "sg:postcode":"1950",
    "sg:province":"Valais",
    "wof:name":"Karat\u00e9-do Dojo",
    "wof:placetype":"venue"
},
  "geometry": {"coordinates":[6.7543091774,47.0572166443],"type":"Point"}
}