{
  "type": "Feature",
  "properties": {
    "iso:country":"CH",
    "sg:address":"Rue Du 31-d\u00e9cembre 24",
    "sg:city":"Gen\u00e8ve",
    "sg:orig_category":"Detektivb\u00fcros U \u00dcberwachung",
    "sg:phone":"+41 22 735 41 58",
    "sg:postcode":"1207",
    "sg:province":"Gen\u00e8ve",
    "wof:name":"Claude Balivet Surveillance Chaufferie",
    "wof:placetype":"venue"
},
  "geometry": {"coordinates":[6.159318924,46.2036972046],"type":"Point"}
}