{
  "type": "Feature",
  "properties": {
    "iso:country":"CH",
    "sg:address":"P\u00e9quignat Rue Pierre- 7",
    "sg:city":"Porrentruy",
    "sg:orig_category":"Detailhandel mit Waren verschiedener Art, Hauptrichtung Nahrungsmittel",
    "sg:postcode":"2900",
    "sg:province":"Jura",
    "wof:name":"Christian Brugnerotto",
    "wof:placetype":"venue"
},
  "geometry": {"coordinates":[7.0742611885,47.4172363281],"type":"Point"}
}