{
  "type": "Feature",
  "properties": {
    "iso:country":"CH",
    "sg:address":"5412",
    "sg:city":"Gebenstorf",
    "sg:orig_category":"Sportvereine Sch\u00fctzen",
    "sg:phone":"+41 56 223 20 63",
    "sg:postcode":"5412",
    "sg:province":"Aargau",
    "wof:name":"Freisch\u00fctzen Gebenstorf",
    "wof:placetype":"venue"
},
  "geometry": {"coordinates":[8.2375450134,47.480758667],"type":"Point"}
}