{
  "type": "Feature",
  "properties": {
    "iso:country":"CH",
    "sg:address":"Klosbachstrasse 8",
    "sg:city":"Z\u00fcrich",
    "sg:orig_category":"Detailhandel mit Brillen U anderen Sehhilfen",
    "sg:phone":"+41 13837283",
    "sg:postcode":"8032",
    "sg:province":"Z\u00fcrich",
    "wof:name":"Max Halder Optiker",
    "wof:placetype":"venue"
},
  "geometry": {"coordinates":[8.55521,47.365097],"type":"Point"}
}