{
  "type": "Feature",
  "properties": {
    "iso:country":"CH",
    "sg:address":"Route De Rolle 27 1162 St-prex. Postfach 28",
    "sg:city":"St-prex",
    "sg:orig_category":"Einzelhandel mit Automobilen Instandhaltung U Reparatur von Automobilen",
    "sg:phone":"+41 21 806 13 68",
    "sg:postcode":"1162",
    "sg:province":"Vaud",
    "wof:name":"Garage Samuel Beutler Agence Renault",
    "wof:placetype":"venue"
},
  "geometry": {"coordinates":[6.4523510933,46.4797706604],"type":"Point"}
}