{
  "type": "Feature",
  "properties": {
    "iso:country":"CH",
    "sg:address":"Rue Des Bouchers 95",
    "sg:city":"Fribourg",
    "sg:orig_category":"Grosshandel mit Nahrungsmitteln, Getr\u00e4nken U Tabakwaren ohne ausgepr\u00e4gten Schwerpunkt",
    "sg:postcode":"1700",
    "sg:province":"Fribourg",
    "wof:name":"Wenger Mme E.",
    "wof:placetype":"venue"
},
  "geometry": {"coordinates":[7.1651701927,46.8056182861],"type":"Point"}
}