{
  "type": "Feature",
  "properties": {
    "iso:country":"CH",
    "sg:address":"Schaub Rue 43",
    "sg:city":"Gen\u00e8ve",
    "sg:orig_category":"Sonstige mit der Informatik verbundene T\u00e4tigkeiten",
    "sg:postcode":"1202",
    "sg:province":"Gen\u00e8ve",
    "wof:name":"Pi Prestations Informatiques Sarl",
    "wof:placetype":"venue"
},
  "geometry": {"coordinates":[6.1307830811,46.2143592834],"type":"Point"}
}