{
  "type": "Feature",
  "properties": {
    "iso:country":"CH",
    "sg:address":"Rue Du Conseil 8",
    "sg:city":"Vevey",
    "sg:orig_category":"Zahnkliniken",
    "sg:phone":"+41 21 925 59 10",
    "sg:postcode":"1800",
    "sg:province":"Vaud",
    "wof:name":"Clinique Dentaire Scolaire",
    "wof:placetype":"venue"
},
  "geometry": {"coordinates":[6.8438491821,46.4595909119],"type":"Point"}
}