{
  "type": "Feature",
  "properties": {
    "addr:full":"1188 Gimel Vaud 1188",
    "addr:housenumber":"1188",
    "addr:postcode":"1188",
    "addr:street":"Gimel",
    "iso:country":"CH",
    "sg:address":"1188",
    "sg:city":"Gimel",
    "sg:orig_category":"Allgemeiner Hoch U Tiefbau Maurerarbeiten",
    "sg:phone":"+41 32 484 93 57",
    "sg:postcode":"1188",
    "sg:province":"Vaud",
    "wof:name":"Denis Carnal Entreprise De Ma\u00e7onnerie",
    "wof:placetype":"venue"
},
  "geometry": {"coordinates":[7.243018,47.274029],"type":"Point"}
}