{
  "type": "Feature",
  "properties": {
    "iso:country":"CH",
    "sg:address":"Steinackerstrasse 43",
    "sg:city":"Urdorf",
    "sg:orig_category":"Grosshandel mit Milch, Milcherzeugnissen, Eiern, Speise\u00f6len U Nahrungsfetten",
    "sg:postcode":"8902",
    "sg:province":"Z\u00fcrich",
    "wof:name":"Egw Eier Gefl\u00fcgel Wild Ag",
    "wof:placetype":"venue"
},
  "geometry": {"coordinates":[9.2117004395,47.4424667358],"type":"Point"}
}