{
  "type": "Feature",
  "properties": {
    "iso:country":"CH",
    "sg:address":"Gerbegasse 6",
    "sg:city":"Kloten",
    "sg:orig_category":"Arztpraxen",
    "sg:phone":"+41 18136855",
    "sg:postcode":"8302",
    "sg:province":"Z\u00fcrich",
    "wof:name":"Dr.med.maja Giger Aerztin F\u00fcr Allg.medizin Fmh",
    "wof:placetype":"venue"
},
  "geometry": {"coordinates":[8.581588,47.452358],"type":"Point"}
}