{
  "type": "Feature",
  "properties": {
    "iso:country":"CH",
    "sg:address":"Avenue Adrien-jeandin 1",
    "sg:city":"Th\u00f4nex",
    "sg:orig_category":"Vorschulen, Kinderg\u00e4rten",
    "sg:postcode":"1226",
    "sg:province":"Gen\u00e8ve",
    "wof:name":"Ecole Enfantine I & Ii Adrien-jeandin",
    "wof:placetype":"venue"
},
  "geometry": {"coordinates":[6.2023777962,46.1910743713],"type":"Point"}
}