{
  "type": "Feature",
  "properties": {
    "iso:country":"CH",
    "sg:address":"Avenue De Lavaux 36 1009 Pully Case Postale 102",
    "sg:city":"Pully",
    "sg:orig_category":"Kinos",
    "sg:phone":"+41 21 728 69 69",
    "sg:postcode":"1009",
    "sg:province":"Vaud",
    "wof:name":"Cin\u00e9ma City Club",
    "wof:placetype":"venue"
},
  "geometry": {"coordinates":[6.6583919525,46.5123062134],"type":"Point"}
}