{
  "type": "Feature",
  "properties": {
    "iso:country":"CH",
    "sg:address":"Lischweg 49",
    "sg:city":"Vordemwald",
    "sg:orig_category":"Sportvereine Velo Rad-& Motorfahrer-Bund SRB",
    "sg:phone":"+41 79 422 84 14",
    "sg:postcode":"4803",
    "sg:province":"Aargau",
    "wof:name":"Radfahrer-verein Vordemwald",
    "wof:placetype":"venue"
},
  "geometry": {"coordinates":[7.8965702057,47.2745285034],"type":"Point"}
}