{
  "type": "Feature",
  "properties": {
    "iso:country":"CH",
    "sg:address":"Ackerstrasse 81 L",
    "sg:city":"Volketswil",
    "sg:orig_category":"Sonstige mit der Informatik verbundene T\u00e4tigkeiten",
    "sg:postcode":"8604",
    "sg:province":"Z\u00fcrich",
    "wof:name":"Ebersp\u00e4cher-hottinger Consulting",
    "wof:placetype":"venue"
},
  "geometry": {"coordinates":[8.6897258759,47.3896369934],"type":"Point"}
}