{
  "type": "Feature",
  "properties": {
    "addr:full":"Hilgestrasse 2 Sch\u00f6tz Luzern 6247",
    "addr:housenumber":"2",
    "addr:postcode":"6247",
    "addr:street":"Hilgestrasse",
    "iso:country":"CH",
    "sg:address":"Hilgestrasse 2",
    "sg:city":"Sch\u00f6tz",
    "sg:classifiers":[
        {
            "category":"Real Estate",
            "subcategory":"Real Estate Operator",
            "type":"Services"
        }
    ],
    "sg:phone":"+41 41 984 28 42",
    "sg:postcode":"6247",
    "sg:province":"Luzern",
    "sg:tags":[
        "pump",
        "centrifugal"
    ],
    "wof:name":"Hilge Pumpen Ag",
    "wof:placetype":"venue"
},
  "geometry": {"coordinates":[7.98461,47.179676],"type":"Point"}
}