{
  "type": "Feature",
  "properties": {
    "iso:country":"CH",
    "sg:address":"Schellenrain 9",
    "sg:city":"Sursee",
    "sg:classifiers":[
        {
            "category":"Manufacturing",
            "subcategory":"Signs",
            "type":"Manufacturing & Wholesale Goods"
        }
    ],
    "sg:phone":"+41 41 921 68 88",
    "sg:postcode":"6210",
    "sg:province":"Luzern",
    "sg:tags":[
        "car",
        "lettering"
    ],
    "wof:name":"Pinato Graphics Ag",
    "wof:placetype":"venue"
},
  "geometry": {"coordinates":[8.105009,47.167835],"type":"Point"}
}