{
  "type": "Feature",
  "properties": {
    "iso:country":"CH",
    "sg:address":"Gellertstrasse 18",
    "sg:city":"Basel",
    "sg:orig_category":"Herstellung von Industriegasen",
    "sg:phone":"+41 21 694 80 80",
    "sg:postcode":"4052",
    "sg:province":"Basel-Stadt",
    "wof:name":"Socsil-inter Sa Gaz M\u00e9dicaux Pompes",
    "wof:placetype":"venue"
},
  "geometry": {"coordinates":[6.5682821274,46.5356864929],"type":"Point"}
}