{
  "type": "Feature",
  "properties": {
    "iso:country":"CH",
    "sg:address":"1268",
    "sg:city":"Begnins",
    "sg:classifiers":[
        {
            "category":"Travel",
            "subcategory":"Hotels & Motels",
            "type":"Entertainment"
        }
    ],
    "sg:postcode":"1268",
    "sg:province":"Vaud",
    "sg:tags":[
        "hotels",
        "mit",
        "restaurant"
    ],
    "wof:name":"Mennet Laurence",
    "wof:placetype":"venue"
},
  "geometry": {"coordinates":[6.2470698357,46.4407958984],"type":"Point"}
}