{
  "type": "Feature",
  "properties": {
    "iso:country":"CH",
    "sg:address":"Place De L'eglise 3 1580 Avenches. Postfach",
    "sg:city":"Avenches",
    "sg:orig_category":"Verkehrs- and Tourismusb\u00fcros",
    "sg:phone":"+41 26 675 11 59",
    "sg:postcode":"1580",
    "sg:province":"Vaud",
    "wof:name":"Office Du Tourisme & Soci\u00e9t\u00e9 De D\u00e9veloppement",
    "wof:placetype":"venue"
},
  "geometry": {"coordinates":[7.0407800674,46.8800582886],"type":"Point"}
}