{
  "type": "Feature",
  "properties": {
    "iso:country":"CH",
    "sg:address":"F\u00fcrstenlandstrasse 96 9000 St.gallen. Postfach 9014 St. Gallen",
    "sg:city":"Zust",
    "sg:orig_category":"Pensionskassen",
    "sg:postcode":"14",
    "wof:name":"Pensionskasse Der Diethelm-gruppe",
    "wof:placetype":"venue"
},
  "geometry": {"coordinates":[9.349199295,47.4141464233],"type":"Point"}
}