{
  "type": "Feature",
  "properties": {
    "iso:country":"CH",
    "sg:address":"Dorfstrasse 30 6442 Gersau. Postfach 6",
    "sg:city":"Gersau",
    "sg:orig_category":"Detailhandel mit Radio U Fernsehger\u00e4ten",
    "sg:phone":"+41 41 828 14 12",
    "sg:postcode":"6442",
    "sg:province":"Schwyz",
    "wof:name":"Richard Nigg Ag",
    "wof:placetype":"venue"
},
  "geometry": {"coordinates":[8.5255184174,46.9918899536],"type":"Point"}
}