{
  "type": "Feature",
  "properties": {
    "iso:country":"CH",
    "sg:address":"In Der Gandstrasse 30",
    "sg:city":"Zumikon",
    "sg:orig_category":"Massagestudios",
    "sg:phone":"+41 31 971 58 35",
    "sg:postcode":"8126",
    "sg:province":"Z\u00fcrich",
    "wof:name":"Doris Stalder Massagen",
    "wof:placetype":"venue"
},
  "geometry": {"coordinates":[7.4149589539,46.9066772461],"type":"Point"}
}