{
  "type": "Feature",
  "properties": {
    "iso:country":"CH",
    "sg:address":"Stampa Via Alla 6965 Cadro. Postfach",
    "sg:city":"Cadro",
    "sg:orig_category":"Instandhaltung U Reparatur von Automobilen",
    "sg:postcode":"6965",
    "sg:province":"Ticino",
    "wof:name":"Rm Automeccanica Industriale Sa Veicoli Leggeri, Pesanti Ecc.; Compravendita, Importazione, Esportazione",
    "wof:placetype":"venue"
},
  "geometry": {"coordinates":[8.9743824005,46.0413742065],"type":"Point"}
}