{
  "type": "Feature",
  "properties": {
    "addr:full":"Chemin Des Croisettes 23 Epalinges Vaud 1066",
    "addr:housenumber":"23",
    "addr:postcode":"1066",
    "addr:street":"Chemin Des Croisettes",
    "iso:country":"CH",
    "sg:address":"Chemin Des Croisettes 23",
    "sg:city":"Epalinges",
    "sg:orig_category":"Architektur U Ingenieurb\u00fcros Architekturb\u00fcros",
    "sg:phone":"+41 21 657 20 60",
    "sg:postcode":"1066",
    "sg:province":"Vaud",
    "wof:name":"Archeotech Sa",
    "wof:placetype":"venue"
},
  "geometry": {"coordinates":[6.659637,46.544403],"type":"Point"}
}