{
  "type": "Feature",
  "properties": {
    "iso:country":"CH",
    "sg:address":"Landenbergstrasse 35 6000 Luzern. Postfach",
    "sg:city":"Luzern",
    "sg:orig_category":"Bau von Strassen, Sportanlagen U Bahnverkehrsstrecken",
    "sg:postcode":"6003",
    "sg:province":"Luzern",
    "wof:name":"Hinke Schwimmbad Schweiz Ag",
    "wof:placetype":"venue"
},
  "geometry": {"coordinates":[8.31659,47.045795],"type":"Point"}
}