{
  "type": "Feature",
  "properties": {
    "iso:country":"CH",
    "sg:address":"Rue De La Barre 8",
    "sg:city":"Lausanne",
    "sg:classifiers":[
        {
            "category":"Bars & Pubs",
            "type":"Food & Drink"
        }
    ],
    "sg:phone":"+41 71 911 55 75",
    "sg:postcode":"1005",
    "sg:province":"Vaud",
    "wof:name":"J & B Pub",
    "wof:placetype":"venue"
},
  "geometry": {"coordinates":[9.040277,47.463184],"type":"Point"}
}