{
  "type": "Feature",
  "properties": {
    "addr:full":"Herrenmattstrasse 4 Flamatt Fribourg 3175",
    "addr:housenumber":"4",
    "addr:postcode":"3175",
    "addr:street":"Herrenmattstrasse",
    "iso:country":"CH",
    "sg:address":"Herrenmattstrasse 4",
    "sg:city":"Flamatt",
    "sg:orig_category":"Autogaragen",
    "sg:phone":"+41 31 741 63 60",
    "sg:postcode":"3175",
    "sg:province":"Fribourg",
    "wof:name":"Garage Heimberg",
    "wof:placetype":"venue"
},
  "geometry": {"coordinates":[7.328376,46.890228],"type":"Point"}
}