{
  "type": "Feature",
  "properties": {
    "addr:full":"W\u00fclflingerstrasse 151 Winterthur Z\u00fcrich 8408",
    "addr:housenumber":"151",
    "addr:postcode":"8408",
    "addr:street":"Wuelflingerstrasse",
    "iso:country":"CH",
    "sg:address":"W\u00fclflingerstrasse 151",
    "sg:city":"Winterthur",
    "sg:orig_category":"Blumen U Zierpflanzenbau Detailhandel mit Blumen U Pflanzen",
    "sg:phone":"+41 52 222 97 80",
    "sg:postcode":"8408",
    "sg:province":"Z\u00fcrich",
    "wof:name":"Stift H\u00f6fli",
    "wof:placetype":"venue"
},
  "geometry": {"coordinates":[8.705036,47.50872],"type":"Point"}
}