{
  "type": "Feature",
  "properties": {
    "iso:country":"CH",
    "sg:address":"Rheinstrasse 29 4410 Liestal. Postfach",
    "sg:city":"Liestal",
    "sg:orig_category":"Friedhofs- and Stadtg\u00e4rtnereien",
    "sg:phone":"+41 22 418 50 25",
    "sg:postcode":"4410",
    "sg:province":"Basel-Landschaft",
    "wof:name":"Service Des Espaces Verts & De L'environnement (seve)",
    "wof:placetype":"venue"
},
  "geometry": {"coordinates":[6.1493778229,46.219367981],"type":"Point"}
}