{
  "type": "Feature",
  "properties": {
    "iso:country":"CH",
    "sg:address":"Z\u00fcrcherstrasse 68",
    "sg:city":"Thalwil",
    "sg:classifiers":[
        {
            "category":"Manufacturing",
            "subcategory":"Electronics",
            "type":"Manufacturing & Wholesale Goods"
        }
    ],
    "sg:postcode":"8800",
    "sg:tags":[
        "gps-receiver",
        "geotagging"
    ],
    "sg:website":"http://www.u-blox.com",
    "wof:name":"u-blox",
    "wof:placetype":"venue"
},
  "geometry": {"coordinates":[8.5654615,47.2849669],"type":"Point"}
}