{
  "type": "Feature",
  "properties": {
    "iso:country":"CH",
    "sg:address":"Altenburgstrasse 68",
    "sg:city":"Wettingen",
    "sg:orig_category":"Architekturb\u00fcros",
    "sg:phone":"+41 56 621 89 81",
    "sg:postcode":"5430",
    "sg:province":"Aargau",
    "wof:name":"Hup Architekten & Planer H\u00e4fliger",
    "wof:placetype":"venue"
},
  "geometry": {"coordinates":[8.271916,47.348072],"type":"Point"}
}