{
  "type": "Feature",
  "properties": {
    "iso:country":"CH",
    "sg:address":"Zeughausgasse 20",
    "sg:city":"Bern",
    "sg:orig_category":"Detailhandel mit Ton U Bildtr\u00e4gern Detailhandel mit elektrischen Haushalts-,Radio U Fernsehger\u00e4ten s",
    "sg:phone":"+41 32 913 21 11",
    "sg:postcode":"3011",
    "sg:province":"Bern",
    "wof:name":"Man-musique, Fernando Eugenio Mannello",
    "wof:placetype":"venue"
},
  "geometry": {"coordinates":[6.8195672035,47.0968971252],"type":"Point"}
}