{
  "type": "Feature",
  "properties": {
    "iso:country":"CH",
    "sg:address":"Feldkircherstrasse 13 9494 Schaan. Postfach 243",
    "sg:city":"Schaan",
    "sg:orig_category":"Offsetdruck Satzherstellung U Reproduktion",
    "sg:phone":"+423 239 50 50",
    "sg:postcode":"9494",
    "wof:name":"Gutenberg Ag Satz & Druck",
    "wof:placetype":"venue"
},
  "geometry": {"coordinates":[9.5116100311,47.1680717468],"type":"Point"}
}