{
  "type": "Feature",
  "properties": {
    "iso:country":"CH",
    "sg:address":"Rheinstrasse 180",
    "sg:city":"Chur",
    "sg:orig_category":"Maler U Glasergewerbe",
    "sg:phone":"+41 79 459 12 76",
    "sg:postcode":"7000",
    "sg:province":"Graubunden",
    "wof:name":"Furger Gerry Gmbh Malergesch\u00e4ft Usw",
    "wof:placetype":"venue"
},
  "geometry": {"coordinates":[8.6330652237,46.8769760132],"type":"Point"}
}