{
  "type": "Feature",
  "properties": {
    "iso:country":"CH",
    "sg:address":"La Plaine",
    "sg:city":"Vufflens-la-ville",
    "sg:orig_category":"Grosshandel mit sonstigen Maschinen U Ausr\u00fcstungen f\u00fcr Industrie, Handel U Schiffahrt",
    "sg:phone":"+41 21 869 93 25",
    "sg:postcode":"1302",
    "sg:province":"Vaud",
    "wof:name":"Cometro Sa",
    "wof:placetype":"venue"
},
  "geometry": {"coordinates":[6.529583931,46.576625824],"type":"Point"}
}