{
  "type": "Feature",
  "properties": {
    "iso:country":"CH",
    "sg:address":"Schmidshof Oppikon",
    "sg:city":"Oppikon",
    "sg:orig_category":"Herstellung von sonstigen landwirtschaftlichen Maschinen",
    "sg:postcode":"9565",
    "sg:province":"Thurgau",
    "wof:name":"Tschann J. Ag",
    "wof:placetype":"venue"
},
  "geometry": {"coordinates":[9.0787296295,47.5577392578],"type":"Point"}
}