{
  "type": "Feature",
  "properties": {
    "iso:country":"CH",
    "sg:address":"Chemin Des Grand-puits 66",
    "sg:city":"Meyrin",
    "sg:orig_category":"Elektroinstallation",
    "sg:phone":"+41 22 782 10 50",
    "sg:postcode":"1217",
    "sg:province":"Gen\u00e8ve",
    "wof:name":"Entreprise G\u00e9n\u00e9rale D'\u00e9lectricit\u00e9 Peyer Christian",
    "wof:placetype":"venue"
},
  "geometry": {"coordinates":[6.0726480484,46.2267532349],"type":"Point"}
}