{
  "type": "Feature",
  "properties": {
    "addr:full":"Feldeggstrasse 89 Z\u00fcrich Z\u00fcrich 8008",
    "addr:housenumber":"89",
    "addr:postcode":"8008",
    "addr:street":"Feldeggstrasse",
    "iso:country":"CH",
    "sg:address":"Feldeggstrasse 89",
    "sg:city":"Z\u00fcrich",
    "sg:orig_category":"Architekturb\u00fcros",
    "sg:phone":"+41 12621511",
    "sg:postcode":"8008",
    "sg:province":"Z\u00fcrich",
    "wof:name":"J\u00fcrg Haas Architekturb\u00fcro",
    "wof:placetype":"venue"
},
  "geometry": {"coordinates":[8.554527,47.362724],"type":"Point"}
}