{
  "type": "Feature",
  "properties": {
    "iso:country":"CH",
    "sg:address":"Br\u00fchl 11",
    "sg:city":"Wolfwil",
    "sg:orig_category":"Allgemeiner Hoch U Tiefbau Schlossereien",
    "sg:phone":"+41 62 926 26 62",
    "sg:postcode":"4628",
    "sg:province":"Solothurn",
    "wof:name":"Wullschleger K.",
    "wof:placetype":"venue"
},
  "geometry": {"coordinates":[7.79935,47.268673],"type":"Point"}
}