{
  "type": "Feature",
  "properties": {
    "iso:country":"CH",
    "sg:address":"Fraisse Avenue William- 6",
    "sg:city":"Lausanne",
    "sg:classifiers":[
        {
            "category":"Education",
            "subcategory":"Library",
            "type":"Public Place"
        }
    ],
    "sg:phone":"+41 31 631 46 07",
    "sg:postcode":"1006",
    "sg:province":"Vaud",
    "sg:tags":[
        "u",
        "bibliotheken",
        "archive"
    ],
    "wof:name":"Fachbereichsbibliothek B\u00fchlplatz",
    "wof:placetype":"venue"
},
  "geometry": {"coordinates":[7.428188,46.952049],"type":"Point"}
}