{
  "type": "Feature",
  "properties": {
    "iso:country":"CH",
    "sg:address":"7029",
    "sg:city":"Peist",
    "sg:orig_category":"Sportvereine Turnen Vereine Damen",
    "sg:phone":"+41 52 242 30 71",
    "sg:postcode":"7029",
    "sg:province":"Graubunden",
    "wof:name":"Damenturnverein Pf\u00e4ffikon Zh",
    "wof:placetype":"venue"
},
  "geometry": {"coordinates":[8.7815437317,47.3674468994],"type":"Point"}
}