{
  "type": "Feature",
  "properties": {
    "iso:country":"CH",
    "sg:address":"Zelgliring 7",
    "sg:city":"Brittnau",
    "sg:orig_category":"Sportvereine Velo Rad-& Motorfahrer-Bund SRB",
    "sg:phone":"+41 62 751 06 33",
    "sg:postcode":"4805",
    "sg:province":"Aargau",
    "wof:name":"Radfahrer-verein Brittnau",
    "wof:placetype":"venue"
},
  "geometry": {"coordinates":[7.9412031174,47.2617034912],"type":"Point"}
}