{
  "type": "Feature",
  "properties": {
    "iso:country":"CH",
    "sg:address":"M\u00fchlebachstrasse 174",
    "sg:city":"Z\u00fcrich",
    "sg:orig_category":"Grosshandel mit sonstigen Maschinen U Ausr\u00fcstungen f\u00fcr Industrie, Handel U Schiffahrt",
    "sg:phone":"+41 13898890",
    "sg:postcode":"8008",
    "sg:province":"Z\u00fcrich",
    "wof:name":"Kones Ag",
    "wof:placetype":"venue"
},
  "geometry": {"coordinates":[8.5586051941,47.3564796448],"type":"Point"}
}