{
  "type": "Feature",
  "properties": {
    "iso:country":"CH",
    "sg:address":"Wildensteinerstrasse 21",
    "sg:city":"Muttenz",
    "sg:orig_category":"Reinigungsgewerbe Sanit\u00e4rinstallation",
    "sg:phone":"+41 26 652 31 61",
    "sg:postcode":"4132",
    "sg:province":"Basel-Landschaft",
    "wof:name":"Saniclean S\u00e0rl",
    "wof:placetype":"venue"
},
  "geometry": {"coordinates":[6.9227828979,46.6983680725],"type":"Point"}
}