{
  "type": "Feature",
  "properties": {
    "iso:country":"CH",
    "sg:address":"H\u00f6henweg 15",
    "sg:city":"Schaffhausen",
    "sg:orig_category":"Unternehmensberatung",
    "sg:phone":"+41 18507894",
    "sg:postcode":"8200",
    "sg:province":"Schaffhausen",
    "wof:name":"Wolfgang T. M\u00fcller Inex Wtm",
    "wof:placetype":"venue"
},
  "geometry": {"coordinates":[8.5024929047,47.4818725586],"type":"Point"}
}