{
  "type": "Feature",
  "properties": {
    "iso:country":"CH",
    "sg:address":"Gr\u00fcneck 7130 Ilanz. Postfach",
    "sg:city":"Ilanz",
    "sg:orig_category":"Instandhaltung U Reparatur von Automobilen",
    "sg:phone":"+41 81 925 11 36",
    "sg:postcode":"7130",
    "sg:province":"Graubunden",
    "wof:name":"Giger Reto",
    "wof:placetype":"venue"
},
  "geometry": {"coordinates":[9.1915130615,46.7753143311],"type":"Point"}
}