{
  "type": "Feature",
  "properties": {
    "iso:country":"CH",
    "sg:address":"Calandastrasse 13",
    "sg:city":"Zizers",
    "sg:orig_category":"Physiotherapie",
    "sg:phone":"+41 71 911 64 12",
    "sg:postcode":"7205",
    "sg:province":"Graubunden",
    "wof:name":"Physiotherapie St.peter",
    "wof:placetype":"venue"
},
  "geometry": {"coordinates":[9.0446472168,47.4638175964],"type":"Point"}
}