{
  "type": "Feature",
  "properties": {
    "iso:country":"CH",
    "sg:address":"Rue De Bernex 357 1200 Genf. Postfach",
    "sg:city":"Gen\u00e8ve",
    "sg:orig_category":"Sonstiger spezialisierter Hoch U Tiefbau",
    "sg:postcode":"1201",
    "sg:province":"Gen\u00e8ve",
    "wof:name":"Entreprise De Ma\u00e7onnerie Et B\u00e9ton Arm\u00e9 Victor Favre Sa",
    "wof:placetype":"venue"
},
  "geometry": {"coordinates":[6.6014800072,46.6362991333],"type":"Point"}
}