{
  "type": "Feature",
  "properties": {
    "iso:country":"CH",
    "sg:address":"Chemin Du Gibart 20",
    "sg:city":"Corminboeuf",
    "sg:orig_category":"Allgemeiner Hoch U Tiefbau Elektroinstallation",
    "sg:phone":"+41 26 475 22 80",
    "sg:postcode":"1720",
    "sg:province":"Fribourg",
    "wof:name":"Electricit\u00e9 Golliard S\u00e0rl",
    "wof:placetype":"venue"
},
  "geometry": {"coordinates":[7.09376,46.807209],"type":"Point"}
}