{
  "type": "Feature",
  "properties": {
    "iso:country":"CH",
    "sg:address":"Juchlishaus",
    "sg:city":"Rossh\u00e4usern",
    "sg:orig_category":"Organisationen des Gesundheitswesen",
    "sg:phone":"+41 77724495",
    "sg:postcode":"3204",
    "sg:province":"Bern",
    "wof:name":"Samariterverein M\u00fcllheim/umg.",
    "wof:placetype":"venue"
},
  "geometry": {"coordinates":[9.0121898651,47.604434967],"type":"Point"}
}