{
  "type": "Feature",
  "properties": {
    "addr:full":"H\u00f6henweg 13 6300 Zug. Postfach 431 Zug Zug 6301",
    "addr:housenumber":"13;431",
    "addr:postcode":"6300;6301",
    "addr:street":"Hoehenweg;Postfach;Zug",
    "iso:country":"CH",
    "sg:address":"H\u00f6henweg 13 6300 Zug. Postfach 431",
    "sg:city":"Zug",
    "sg:orig_category":"Datenverarbeitungsdienste Sonstige mit der Informatik verbundene T\u00e4tigkeiten",
    "sg:phone":"+41 41 711 56 40",
    "sg:postcode":"6301",
    "sg:province":"Zug",
    "wof:name":"Flying Coach Gmbh",
    "wof:placetype":"venue"
},
  "geometry": {"coordinates":[8.51926,47.166084],"type":"Point"}
}