{
  "type": "Feature",
  "properties": {
    "iso:country":"CH",
    "sg:address":"Saalhofstrasse 1",
    "sg:city":"Erlinsbach",
    "sg:orig_category":"Mechanische Werkst\u00e4tten",
    "sg:phone":"+41 62 844 20 50",
    "sg:postcode":"5018",
    "sg:province":"Solothurn",
    "wof:name":"Roger Weidmann Mech.werkstatt",
    "wof:placetype":"venue"
},
  "geometry": {"coordinates":[8.0042333603,47.40807724],"type":"Point"}
}