{
  "type": "Feature",
  "properties": {
    "iso:country":"CH",
    "sg:address":"Rebstockstrasse 2",
    "sg:city":"Ruswil",
    "sg:orig_category":"Bausteine Fabrikation, Handel",
    "sg:phone":"+41 41 495 15 22",
    "sg:postcode":"6017",
    "sg:province":"Luzern",
    "wof:name":"Bucher Jost, Fliess Und Unterlagsb\u00f6den",
    "wof:placetype":"venue"
},
  "geometry": {"coordinates":[8.123038,47.082977],"type":"Point"}
}