{
  "type": "Feature",
  "properties": {
    "iso:country":"CH",
    "sg:address":"Chlaffentalstr. 14",
    "sg:city":"Neuhausen",
    "sg:orig_category":"Softwareentwicklung U beratung",
    "sg:postcode":"8212",
    "sg:province":"Schaffhausen",
    "wof:name":"Schramm Computershop",
    "wof:placetype":"venue"
},
  "geometry": {"coordinates":[8.5953025818,47.6737327576],"type":"Point"}
}