{
  "type": "Feature",
  "properties": {
    "iso:country":"CH",
    "sg:address":"Hinterdorfstrasse 28",
    "sg:city":"Schwyz",
    "sg:orig_category":"Grosshandel mit chemischen Erzeugnissen Grosshandel mit sonstigen Halbwaren",
    "sg:phone":"+41 41 811 41 44",
    "sg:postcode":"6430",
    "sg:province":"Schwyz",
    "wof:name":"Klinger Kunststoffe",
    "wof:placetype":"venue"
},
  "geometry": {"coordinates":[8.6595602036,47.019947052],"type":"Point"}
}