{
  "type": "Feature",
  "properties": {
    "iso:country":"CH",
    "sg:address":"M\u00fchlemattstrasse 15",
    "sg:city":"Luzern",
    "sg:orig_category":"Allgemeiner Hoch U Tiefbau",
    "sg:phone":"+41 41 467 07 29",
    "sg:postcode":"6004",
    "sg:province":"Luzern",
    "wof:name":"Duss & Co. Bau",
    "wof:placetype":"venue"
},
  "geometry": {"coordinates":[8.301436,47.056183],"type":"Point"}
}