{
  "type": "Feature",
  "properties": {
    "iso:country":"CH",
    "sg:address":"M\u00fchlegasse 42a",
    "sg:city":"K\u00fcblis",
    "sg:orig_category":"Detailhandel mit Getr\u00e4nken G\u00fcterbef\u00f6rderung im Strassenverkehr",
    "sg:phone":"+41 81 332 19 22",
    "sg:postcode":"7240",
    "sg:province":"Graubunden",
    "wof:name":"Josias Brunner",
    "wof:placetype":"venue"
},
  "geometry": {"coordinates":[9.7780122757,46.9136276245],"type":"Point"}
}