{
  "type": "Feature",
  "properties": {
    "iso:country":"CH",
    "sg:address":"Benknerstrasse 72",
    "sg:city":"Kaltbrunn",
    "sg:orig_category":"Instandhaltung U Reparatur von Automobilen",
    "sg:phone":"+41 55 293 54 34",
    "sg:postcode":"8722",
    "sg:province":"St. Gallen",
    "wof:name":"Bl\u00f6chlinger's Werkstatt",
    "wof:placetype":"venue"
},
  "geometry": {"coordinates":[9.0181417465,47.2069587708],"type":"Point"}
}