{
  "type": "Feature",
  "properties": {
    "iso:country":"CH",
    "sg:address":"Engelstrasse 3 8004 Z\u00fcrich. Postfach 288",
    "sg:city":"Z\u00fcrich",
    "sg:orig_category":"G\u00fcterbef\u00f6rderung im Strassenverkehr",
    "sg:phone":"+41 12424080",
    "sg:postcode":"8031",
    "sg:province":"Z\u00fcrich",
    "wof:name":"Max E. Neeser Transporte",
    "wof:placetype":"venue"
},
  "geometry": {"coordinates":[8.5218400955,47.3749732971],"type":"Point"}
}