{
  "type": "Feature",
  "properties": {
    "iso:country":"CH",
    "sg:address":"Via Br\u00fcga",
    "sg:city":"Lamone",
    "sg:orig_category":"Hoch U Tiefbau",
    "sg:phone":"+41 91 966 34 89",
    "sg:postcode":"6814",
    "sg:province":"Ticino",
    "wof:name":"Vito Brugnoli",
    "wof:placetype":"venue"
},
  "geometry": {"coordinates":[8.9260196686,46.0466194153],"type":"Point"}
}