{
  "type": "Feature",
  "properties": {
    "iso:country":"CH",
    "sg:address":"Steinbitzweg 146",
    "sg:city":"Auenstein",
    "sg:orig_category":"Non-Classified Establishments",
    "sg:postcode":"5105",
    "sg:province":"Aargau",
    "wof:name":"Weber + Co",
    "wof:placetype":"venue"
},
  "geometry": {"coordinates":[8.1349811554,47.4167022705],"type":"Point"}
}