{
  "type": "Feature",
  "properties": {
    "iso:country":"CH",
    "sg:address":"Schafmattweg 55",
    "sg:city":"Binningen",
    "sg:orig_category":"Vermietung U Verpachtung von eigenen Immobilien",
    "sg:phone":"+41 61 272 53 34",
    "sg:postcode":"4102",
    "sg:province":"Basel-Landschaft",
    "wof:name":"M & L Immobilien Ag",
    "wof:placetype":"venue"
},
  "geometry": {"coordinates":[7.5706958771,47.5310707092],"type":"Point"}
}