{
  "type": "Feature",
  "properties": {
    "iso:country":"CH",
    "sg:address":"Rue De L'eglise 16",
    "sg:city":"Del\u00e9mont",
    "sg:orig_category":"Arztpraxen",
    "sg:phone":"+41 32 422 60 10",
    "sg:postcode":"2800",
    "sg:province":"Jura",
    "wof:name":"Dr M\u00e9d. Charles Broquet M\u00e9decin G\u00e9n\u00e9raliste Fmh",
    "wof:placetype":"venue"
},
  "geometry": {"coordinates":[7.343448,47.364803],"type":"Point"}
}