{
  "type": "Feature",
  "properties": {
    "addr:full":"Gubelstrasse 15 Zug Zug 6300",
    "addr:housenumber":"15",
    "addr:postcode":"6300",
    "addr:street":"Gubelstrasse;Zug",
    "iso:country":"CH",
    "sg:address":"Gubelstrasse 15",
    "sg:city":"Zug",
    "sg:orig_category":"Architektur U Ingenieurb\u00fcros",
    "sg:phone":"+41 81 756 29 69",
    "sg:postcode":"6300",
    "sg:province":"Zug",
    "wof:name":"Lampert Heinz, Konstruktionsb\u00fcro",
    "wof:placetype":"venue"
},
  "geometry": {"coordinates":[9.472457,47.161247],"type":"Point"}
}