{
  "type": "Feature",
  "properties": {
    "iso:country":"CH",
    "sg:address":"Genfergasse 20",
    "sg:city":"Bern",
    "sg:orig_category":"Grosshandel mit sonstigen Gebrauchs U Verbrauchsg\u00fctern",
    "sg:postcode":"3011",
    "sg:province":"Bern",
    "wof:name":"Riopedra, Inh. Benincasa L.",
    "wof:placetype":"venue"
},
  "geometry": {"coordinates":[7.4415187836,46.9511184692],"type":"Point"}
}