{
  "type": "Feature",
  "properties": {
    "iso:country":"CH",
    "sg:address":"Via Campagna 22",
    "sg:city":"Canobbio",
    "sg:orig_category":"Interessenvertretungen",
    "sg:postcode":"6952",
    "sg:province":"Ticino",
    "wof:name":"Associazione Ticinese Fra Le Imprese Di Pavimentazioni Stradali",
    "wof:placetype":"venue"
},
  "geometry": {"coordinates":[8.9661397934,46.0376701355],"type":"Point"}
}