{
  "type": "Feature",
  "properties": {
    "iso:country":"CH",
    "sg:address":"Alleestrasse 21",
    "sg:city":"Romanshorn",
    "sg:orig_category":"Erschliessung von Grundst\u00fccken",
    "sg:postcode":"8590",
    "sg:province":"Thurgau",
    "wof:name":"Wohnbaugen.holzgass",
    "wof:placetype":"venue"
},
  "geometry": {"coordinates":[9.3768568039,47.566444397],"type":"Point"}
}