{
  "type": "Feature",
  "properties": {
    "iso:country":"CH",
    "sg:address":"Sch\u00fcler Rue Ernst- 41",
    "sg:city":"Biel/bienne",
    "sg:orig_category":"Herstellung von sonstigen elektrischen Ausr\u00fcstungen",
    "sg:postcode":"2502",
    "sg:province":"Bern",
    "wof:name":"Mc Elektro Gmbh",
    "wof:placetype":"venue"
},
  "geometry": {"coordinates":[7.2511649132,47.1409492493],"type":"Point"}
}