{
  "type": "Feature",
  "properties": {
    "iso:country":"CH",
    "sg:address":"Eggb\u00fchlstrasse 21-25 8000 Z\u00fcrich. Postfach 8050 Z\u00fcrich",
    "sg:city":"Zust",
    "sg:orig_category":"Handel mit Automobilteilen U Zubeh\u00f6r",
    "sg:postcode":"50",
    "wof:name":"Cairbon By Bestclean Autopflege + Autozubeh\u00f6r S. Durante",
    "wof:placetype":"venue"
},
  "geometry": {"coordinates":[8.5428361893,47.4160957336],"type":"Point"}
}