{
  "type": "Feature",
  "properties": {
    "iso:country":"CH",
    "sg:address":"Industriestr. 173",
    "sg:city":"B\u00f6singen",
    "sg:classifiers":[
        {
            "category":"Professional",
            "subcategory":"Engineering",
            "type":"Services"
        }
    ],
    "sg:phone":"+41 31 740 31 00",
    "sg:postcode":"3178",
    "sg:province":"Fribourg",
    "sg:tags":[
        "machine",
        "-",
        "mechanical"
    ],
    "wof:name":"Spiro International Sa",
    "wof:placetype":"venue"
},
  "geometry": {"coordinates":[7.2209029198,46.8989257812],"type":"Point"}
}