{
  "type": "Feature",
  "properties": {
    "iso:country":"CH",
    "sg:address":"Grand-rue 22",
    "sg:city":"Malleray",
    "sg:orig_category":"Erschliessung von Grundst\u00fccken",
    "sg:postcode":"2735",
    "sg:province":"Bern",
    "wof:name":"Soci\u00e9t\u00e9 Coop\u00e9rative D'habitation Dynamic Habitat",
    "wof:placetype":"venue"
},
  "geometry": {"coordinates":[7.274225235,47.2383651733],"type":"Point"}
}