{
  "type": "Feature",
  "properties": {
    "iso:country":"CH",
    "sg:address":"Poststrasse 22",
    "sg:city":"Chur",
    "sg:orig_category":"Unternehmensberatung",
    "sg:phone":"+41 81 252 20 26",
    "sg:postcode":"7000",
    "sg:province":"Graubunden",
    "wof:name":"Kingstone Management Ag",
    "wof:placetype":"venue"
},
  "geometry": {"coordinates":[9.5322647095,46.8492965698],"type":"Point"}
}