{
  "type": "Feature",
  "properties": {
    "iso:country":"CH",
    "sg:address":"Obertilistrasse 1",
    "sg:city":"Adliswil",
    "sg:orig_category":"Hardwareberatung",
    "sg:phone":"+41 17101150",
    "sg:postcode":"8134",
    "sg:province":"Z\u00fcrich",
    "wof:name":"B\u00f6sch Elektronik",
    "wof:placetype":"venue"
},
  "geometry": {"coordinates":[8.528380394,47.3089981079],"type":"Point"}
}