{
  "type": "Feature",
  "properties": {
    "iso:country":"CH",
    "sg:address":"Cevio",
    "sg:city":"Cevio",
    "sg:classifiers":[
        {
            "category":"Banks & Credit Unions",
            "subcategory":"Bank",
            "type":"Services"
        }
    ],
    "sg:phone":"+41 91 754 17 78",
    "sg:postcode":"6675",
    "sg:province":"Ticino",
    "wof:name":"Raiffeisen Di Cavergno-cevio",
    "wof:placetype":"venue"
},
  "geometry": {"coordinates":[8.602025,46.316906],"type":"Point"}
}