{
  "type": "Feature",
  "properties": {
    "iso:country":"CH",
    "sg:address":"8784 Braunwald. Postfach 122",
    "sg:city":"Glarus",
    "sg:orig_category":"Vereine Musik/Blasmusik",
    "sg:phone":"+41 55 410 59 41",
    "sg:postcode":"8750",
    "sg:province":"Glarus",
    "wof:name":"Glarner Tambourenverein",
    "wof:placetype":"venue"
},
  "geometry": {"coordinates":[8.7679948807,47.1994628906],"type":"Point"}
}