{
  "type": "Feature",
  "properties": {
    "iso:country":"CH",
    "sg:address":"Hegenheimerstrasse 23",
    "sg:city":"Allschwil",
    "sg:classifiers":[
        {
            "category":"Food & Beverages",
            "subcategory":"Meat & Fish",
            "type":"Retail Goods"
        }
    ],
    "sg:phone":"+41 61 481 40 03",
    "sg:postcode":"4123",
    "sg:province":"Basel-Landschaft",
    "sg:tags":[
        "oil",
        "fat",
        "animal"
    ],
    "wof:name":"H. Moebius & Fils",
    "wof:placetype":"venue"
},
  "geometry": {"coordinates":[7.53689,47.552299],"type":"Point"}
}