{
  "type": "Feature",
  "properties": {
    "iso:country":"CH",
    "sg:address":"7302",
    "sg:city":"Landquart",
    "sg:orig_category":"Vereine Gesang",
    "sg:phone":"+41 81 322 13 60",
    "sg:postcode":"7302",
    "sg:province":"Graubunden",
    "wof:name":"M\u00e4nnerchor Landquart",
    "wof:placetype":"venue"
},
  "geometry": {"coordinates":[9.5868701935,46.9626312256],"type":"Point"}
}