{
  "type": "Feature",
  "properties": {
    "iso:country":"CH",
    "sg:address":"St. Alban-rheinweg 164",
    "sg:city":"Basel",
    "sg:orig_category":"Herstellung von Medikamenten U sonstigen pharmazeutischen Erzeugnissen",
    "sg:postcode":"4052",
    "sg:province":"Basel-Stadt",
    "wof:name":"David M. Jacobs",
    "wof:placetype":"venue"
},
  "geometry": {"coordinates":[7.6083068848,47.5554122925],"type":"Point"}
}