{
  "type": "Feature",
  "properties": {
    "addr:full":"Chamerstrasse 6 H\u00fcnenberg Zug 6331",
    "addr:housenumber":"6",
    "addr:postcode":"6331",
    "addr:street":"Chamerstrasse;Huenenberg Zug",
    "iso:country":"CH",
    "sg:address":"Chamerstrasse 6",
    "sg:city":"H\u00fcnenberg",
    "sg:orig_category":"Detailhandel mit Brot, Back U S\u00fcsswaren",
    "sg:phone":"+41 41 780 80 35",
    "sg:postcode":"6331",
    "sg:province":"Zug",
    "wof:name":"B\u00e4ckerei Hotz Ag",
    "wof:placetype":"venue"
},
  "geometry": {"coordinates":[8.427138,47.174377],"type":"Point"}
}