{
  "type": "Feature",
  "properties": {
    "addr:full":"Thurgauerstr. 54 Z\u00fcrich Z\u00fcrich 8050",
    "addr:housenumber":"54",
    "addr:postcode":"8050",
    "addr:street":"Thurgauerstr.",
    "iso:country":"CH",
    "sg:address":"Thurgauerstr. 54",
    "sg:city":"Z\u00fcrich",
    "sg:classifiers":[
        {
            "category":"Professional",
            "subcategory":"Advertising",
            "type":"Services"
        }
    ],
    "sg:phone":"+41 4113085252",
    "sg:postcode":"8050",
    "sg:province":"Z\u00fcrich",
    "sg:tags":[
        "communication",
        "medium"
    ],
    "wof:name":"Zogg Kettiger Gasser Ag",
    "wof:placetype":"venue"
},
  "geometry": {"coordinates":[8.552603,47.415638],"type":"Point"}
}