{
  "type": "Feature",
  "properties": {
    "iso:country":"CH",
    "sg:address":"Ringstrasse 15",
    "sg:city":"Zug",
    "sg:orig_category":"Markt U Meinungsforschung Werbeberatung",
    "sg:phone":"+41 41 726 30 80",
    "sg:postcode":"6300",
    "sg:province":"Zug",
    "wof:name":"Wissmann Patrick Marketing & Kommunikation",
    "wof:placetype":"venue"
},
  "geometry": {"coordinates":[8.5226774216,47.1673736572],"type":"Point"}
}