{
  "type": "Feature",
  "properties": {
    "iso:country":"CH",
    "sg:address":"Vorders\u00e4ge",
    "sg:city":"Goldingen",
    "sg:orig_category":"Verwertung von Milch",
    "sg:postcode":"8638",
    "sg:province":"St. Gallen",
    "wof:name":"K\u00e4sereigenossenschaft Vorders\u00e4ge",
    "wof:placetype":"venue"
},
  "geometry": {"coordinates":[8.9692306519,47.262878418],"type":"Point"}
}