{
  "type": "Feature",
  "properties": {
    "iso:country":"CH",
    "sg:address":"Bahnhofstrasse 3",
    "sg:city":"B\u00fclach",
    "sg:classifiers":[
        {
            "category":"Banks & Credit Unions",
            "subcategory":"Bank",
            "type":"Services"
        }
    ],
    "sg:phone":"+41 18721717",
    "sg:postcode":"8180",
    "sg:province":"Z\u00fcrich",
    "wof:name":"Z\u00fcrcher Kantonalbank",
    "wof:placetype":"venue"
},
  "geometry": {"coordinates":[8.539956,47.519611],"type":"Point"}
}