{
  "type": "Feature",
  "properties": {
    "iso:country":"CH",
    "sg:address":"Eichwaldstrasse 13",
    "sg:city":"Luzern",
    "sg:orig_category":"Herstellung von Metallkonstruktionen",
    "sg:postcode":"6005",
    "sg:province":"Luzern",
    "wof:name":"Isenschmid Ag Metall Und Energie Zweigniederlassung Luzern",
    "wof:placetype":"venue"
},
  "geometry": {"coordinates":[8.3009052277,47.0382766724],"type":"Point"}
}