{
  "type": "Feature",
  "properties": {
    "iso:country":"CH",
    "sg:address":"Rue De Bourg 35",
    "sg:city":"Lausanne",
    "sg:orig_category":"Detailhandel mit M\u00f6beln Tapezierer/Dekorateure",
    "sg:phone":"+41 21 323 86 86",
    "sg:postcode":"1003",
    "sg:province":"Vaud",
    "wof:name":"Histoire De Plaire Sa",
    "wof:placetype":"venue"
},
  "geometry": {"coordinates":[6.6358909607,46.5200958252],"type":"Point"}
}