{
  "type": "Feature",
  "properties": {
    "iso:country":"CH",
    "sg:address":"Speicherstrasse 16",
    "sg:city":"St.gallen",
    "sg:orig_category":"Gesundheitswesen",
    "sg:phone":"+41 71 223 68 30",
    "sg:postcode":"9000",
    "sg:province":"St. Gallen",
    "wof:name":"Parta Private Haus Und Krankenpflege Engeli",
    "wof:placetype":"venue"
},
  "geometry": {"coordinates":[9.3835687637,47.424331665],"type":"Point"}
}