{
  "type": "Feature",
  "properties": {
    "iso:country":"CH",
    "sg:address":"Burgunderweg 3 2500 Biel/bienne. Postfach",
    "sg:city":"Biel/bienne",
    "sg:orig_category":"Sonstige mit Sport verbundene T\u00e4tigkeiten",
    "sg:postcode":"2505",
    "sg:province":"Bern",
    "wof:name":"Verein Zur Erschliessung Der Langlaufpisten Les Pr\u00e8s-d'orvin-chasseral",
    "wof:placetype":"venue"
},
  "geometry": {"coordinates":[7.213602066,47.1286354065],"type":"Point"}
}