{
  "type": "Feature",
  "properties": {
    "iso:country":"CH",
    "sg:address":"Via Miravalle 22",
    "sg:city":"Massagno",
    "sg:orig_category":"Grosshandel mit B\u00fcromaschinen",
    "sg:phone":"+41 91 967 30 55",
    "sg:postcode":"6900",
    "sg:province":"Ticino",
    "wof:name":"Fobelmac Sa",
    "wof:placetype":"venue"
},
  "geometry": {"coordinates":[8.9496421814,46.015499115],"type":"Point"}
}