{
  "type": "Feature",
  "properties": {
    "iso:country":"CH",
    "sg:address":"St. Margrethenstrasse 2",
    "sg:city":"Chur",
    "sg:classifiers":[
        {
            "category":"Bars & Pubs",
            "type":"Food & Drink"
        }
    ],
    "sg:phone":"+41 81 252 88 77",
    "sg:postcode":"7000",
    "sg:province":"Graubunden",
    "sg:tags":[
        "restaurant"
    ],
    "wof:name":"F1-bar",
    "wof:placetype":"venue"
},
  "geometry": {"coordinates":[9.528864,46.84737],"type":"Point"}
}