{
  "type": "Feature",
  "properties": {
    "iso:country":"CH",
    "sg:address":"Corpataux",
    "sg:city":"Magnedens",
    "sg:orig_category":"Architektur U Ingenieurb\u00fcros",
    "sg:phone":"+41 56 282 34 58",
    "sg:postcode":"1727",
    "sg:province":"Fribourg",
    "wof:name":"Descom Engineering Jetzer Raimund",
    "wof:placetype":"venue"
},
  "geometry": {"coordinates":[8.297448,47.490341],"type":"Point"}
}