{
  "type": "Feature",
  "properties": {
    "iso:country":"CH",
    "sg:address":"Golattenmattgasse 3",
    "sg:city":"Aarau",
    "sg:orig_category":"Kunsthandel",
    "sg:phone":"+41 62 824 40 74",
    "sg:postcode":"5000",
    "sg:province":"Aargau",
    "wof:name":"Rudolf & Gertrud H\u00e4ny Boutique Zum Goldige N\u00fc\u00fcteli",
    "wof:placetype":"venue"
},
  "geometry": {"coordinates":[8.0443563461,47.3919258118],"type":"Point"}
}