{
  "type": "Feature",
  "properties": {
    "iso:country":"CH",
    "sg:address":"Rue De La Poste 8",
    "sg:city":"St-aubin-sauges",
    "sg:orig_category":"Versicherungen Hauptagenturen",
    "sg:phone":"+41 34 402 25 03",
    "sg:postcode":"2024",
    "sg:province":"Neuch\u00e2tel",
    "wof:name":"Schweizer-union Versicherungen Hauptagentur Emmental",
    "wof:placetype":"venue"
},
  "geometry": {"coordinates":[7.757589817,46.9491271973],"type":"Point"}
}