{
  "type": "Feature",
  "properties": {
    "iso:country":"CH",
    "sg:address":"8497",
    "sg:city":"Fischenthal",
    "sg:classifiers":[
        {
            "category":"Education",
            "subcategory":"Vocational School",
            "type":"Public Place"
        }
    ],
    "sg:postcode":"8497",
    "sg:province":"Z\u00fcrich",
    "sg:tags":[
        "koch-",
        "haushaltschulen"
    ],
    "wof:name":"Haushaltungsschule",
    "wof:placetype":"venue"
},
  "geometry": {"coordinates":[8.9219503403,47.3322257996],"type":"Point"}
}