{
  "type": "Feature",
  "properties": {
    "iso:country":"CH",
    "sg:address":"Neuve Rue 10",
    "sg:city":"Ste-croix",
    "sg:orig_category":"Interessenvertretungen",
    "sg:postcode":"1450",
    "sg:province":"Vaud",
    "wof:name":"Fondation Dr Henri Mutrux",
    "wof:placetype":"venue"
},
  "geometry": {"coordinates":[6.5012121201,46.8224945068],"type":"Point"}
}