{
  "type": "Feature",
  "properties": {
    "iso:country":"CH",
    "sg:address":"Wysshaltenstrasse 33",
    "sg:city":"Sch\u00fcbelbach",
    "sg:orig_category":"Hochschulen U h\u00f6here Ausbildung",
    "sg:postcode":"8862",
    "sg:province":"Schwyz",
    "wof:name":"A. Meyer, Schulung F\u00fcr Geb\u00e4udewartung Und Geb\u00e4udeunterhalt Ag",
    "wof:placetype":"venue"
},
  "geometry": {"coordinates":[8.9400682449,47.1723480225],"type":"Point"}
}