{
  "type": "Feature",
  "properties": {
    "iso:country":"CH",
    "sg:address":"B\u00fcntgasse 2",
    "sg:city":"N\u00e4fels",
    "sg:classifiers":[
        {
            "category":"Utilities",
            "subcategory":"Electric",
            "type":"Services"
        }
    ],
    "sg:phone":"+41 55 618 71 71",
    "sg:postcode":"8752",
    "sg:province":"Glarus",
    "sg:tags":[
        "electricity",
        "raw",
        "energy",
        "material"
    ],
    "wof:name":"Ew N\u00c4fels",
    "wof:placetype":"venue"
},
  "geometry": {"coordinates":[9.0610666275,47.0978851318],"type":"Point"}
}