{
  "type": "Feature",
  "properties": {
    "iso:country":"CH",
    "sg:address":"Tour Rue De La 10 1004 Lausanne. Postfach",
    "sg:city":"Lausanne",
    "sg:orig_category":"Herstellung von Oberbekleidung",
    "sg:postcode":"1003",
    "sg:province":"Vaud",
    "wof:name":"Martinez Manuel & Cie. Commerce De Pr\u00eat-\u00e0-porter.",
    "wof:placetype":"venue"
},
  "geometry": {"coordinates":[6.6258969307,46.5077896118],"type":"Point"}
}