{
  "type": "Feature",
  "properties": {
    "iso:country":"CH",
    "sg:address":"Rue Des Philosophes 69",
    "sg:city":"Yverdon-les-bains",
    "sg:orig_category":"Gartenbau Landschaftsplanungsb\u00fcros U Gartenarchitekturb\u00fcros",
    "sg:phone":"+41 24 425 42 88",
    "sg:postcode":"1400",
    "sg:province":"Vaud",
    "wof:name":"Philippe Jolivet Paysagiste",
    "wof:placetype":"venue"
},
  "geometry": {"coordinates":[6.6436338425,46.7740097046],"type":"Point"}
}