{
  "type": "Feature",
  "properties": {
    "addr:full":"Baselstrasse 17 Riehen Basel-Stadt 4125",
    "addr:housenumber":"17",
    "addr:postcode":"4125",
    "addr:street":"Baselstrasse",
    "iso:country":"CH",
    "sg:address":"Baselstrasse 17",
    "sg:city":"Riehen",
    "sg:orig_category":"Detailhandel mit Bekleidung",
    "sg:phone":"+41 61 641 55 75",
    "sg:postcode":"4125",
    "sg:province":"Basel-Stadt",
    "wof:name":"La Nuance Ballmann Dietlind",
    "wof:placetype":"venue"
},
  "geometry": {"coordinates":[7.648373,47.583557],"type":"Point"}
}