{
  "type": "Feature",
  "properties": {
    "iso:country":"CH",
    "sg:address":"Rebacker 2",
    "sg:city":"Herbligen",
    "sg:orig_category":"Unclassifiable Establishments",
    "sg:postcode":"3671",
    "sg:province":"Bern",
    "wof:name":"Zb\u00e4ren Andreas Sportive",
    "wof:placetype":"venue"
},
  "geometry": {"coordinates":[7.6059718132,46.8295402527],"type":"Point"}
}