{
  "type": "Feature",
  "properties": {
    "iso:country":"CH",
    "sg:address":"Feldbergstrasse 115",
    "sg:city":"Basel",
    "sg:orig_category":"Schnelldruck U Kopierservice Siebdruck",
    "sg:phone":"+41 61 693 10 71",
    "sg:postcode":"4057",
    "sg:province":"Basel-Stadt",
    "wof:name":"Yusuf Balcin Alfa Druck/copyshop",
    "wof:placetype":"venue"
},
  "geometry": {"coordinates":[7.5954399109,47.567199707],"type":"Point"}
}