{
  "type": "Feature",
  "properties": {
    "iso:country":"CH",
    "sg:address":"Via Concordia 2",
    "sg:city":"Lugano",
    "sg:orig_category":"Einzelhandel mit Automobilteilen U Zubeh\u00f6r",
    "sg:phone":"+41 24 472 78 78",
    "sg:postcode":"6900",
    "sg:province":"Ticino",
    "wof:name":"Automobile Import Garage Multimarques Sa",
    "wof:placetype":"venue"
},
  "geometry": {"coordinates":[6.9327712059,46.2784500122],"type":"Point"}
}