{
  "type": "Feature",
  "properties": {
    "iso:country":"CH",
    "sg:address":"Parkettstrasse 4 3432 L\u00fctzelfl\u00fch-goldb. Postfach",
    "sg:city":"L\u00fctzelfl\u00fch-goldb",
    "sg:orig_category":"Detailhandel mit elektrischen Haushalts-,Radio U Fernsehger\u00e4ten sowie Musikinstrumenten",
    "sg:postcode":"3432",
    "sg:province":"Bern",
    "wof:name":"Heinz Zwahlen",
    "wof:placetype":"venue"
},
  "geometry": {"coordinates":[7.6835370064,47.0035438538],"type":"Point"}
}