{
  "type": "Feature",
  "properties": {
    "iso:country":"CH",
    "sg:address":"Wiedenstrasse 15",
    "sg:city":"Steinach",
    "sg:classifiers":[
        {
            "category":"Military Area",
            "subcategory":"Naval Base",
            "type":"Public Place"
        }
    ],
    "sg:phone":"+41 12621211",
    "sg:postcode":"9323",
    "sg:province":"St. Gallen",
    "sg:tags":[
        "shelf",
        "cantilever"
    ],
    "wof:name":"Sipag Lagertechnik Ag",
    "wof:placetype":"venue"
},
  "geometry": {"coordinates":[8.574999,47.345001],"type":"Point"}
}