{
  "type": "Feature",
  "properties": {
    "iso:country":"CH",
    "sg:address":"Fagostrasse 7 6235 Winikon. Postfach",
    "sg:city":"Winikon",
    "sg:orig_category":"Herstellung von Maschinen f\u00fcr die Nahrungsmittel, Getr\u00e4nkeherstellung U die Tabakverarbeitung",
    "sg:phone":"+41 41 933 02 44",
    "sg:postcode":"6235",
    "sg:province":"Luzern",
    "wof:name":"Grawi Kaufmann Hans & Co Trocknungsanlagen Usw",
    "wof:placetype":"venue"
},
  "geometry": {"coordinates":[8.056303978,47.2393569946],"type":"Point"}
}