{
  "type": "Feature",
  "properties": {
    "iso:country":"CH",
    "sg:address":"Trottenstrasse 23",
    "sg:city":"Seuzach",
    "sg:orig_category":"Gartenbau",
    "sg:phone":"+41 22 771 11 88",
    "sg:postcode":"8472",
    "sg:province":"Z\u00fcrich",
    "wof:name":"Luc Barthassat Cr\u00e9ation De Parcs & Jardins",
    "wof:placetype":"venue"
},
  "geometry": {"coordinates":[6.1042528152,46.1490287781],"type":"Point"}
}