{
  "type": "Feature",
  "properties": {
    "iso:country":"CH",
    "sg:address":"Rue Du Coll\u00e8ge 4",
    "sg:city":"Corsier-sur-vevey",
    "sg:orig_category":"Gartenbau",
    "sg:phone":"+41 79 632 48 44",
    "sg:postcode":"1804",
    "sg:province":"Vaud",
    "wof:name":"K\u00e4ser Joseph.",
    "wof:placetype":"venue"
},
  "geometry": {"coordinates":[6.8447909355,46.4709205627],"type":"Point"}
}