{
  "type": "Feature",
  "properties": {
    "iso:country":"CH",
    "sg:address":"Schloss-strasse 43",
    "sg:city":"Oberdiessbach",
    "sg:orig_category":"Herstellung von Konstruktionsteilen, Fertigbauteilen U Ausbauelementen aus Holz",
    "sg:phone":"+41 31 771 35 37",
    "sg:postcode":"3672",
    "sg:province":"Bern",
    "wof:name":"W & W Wymann & Weidner",
    "wof:placetype":"venue"
},
  "geometry": {"coordinates":[7.6255130768,46.8395423889],"type":"Point"}
}