{
  "type": "Feature",
  "properties": {
    "iso:country":"CH",
    "sg:address":"Salen-reutenen 8508 Homburg. Postfach",
    "sg:city":"Homburg",
    "sg:orig_category":"Unclassifiable Establishments",
    "sg:phone":"+41 21 921 83 42",
    "sg:postcode":"8508",
    "sg:province":"Thurgau",
    "wof:name":"Herzog, Dr. Med. Et Mme Paul",
    "wof:placetype":"venue"
},
  "geometry": {"coordinates":[6.8834300041,46.4704742432],"type":"Point"}
}