{
  "type": "Feature",
  "properties": {
    "iso:country":"CH",
    "sg:address":"Ober-holenweg 21",
    "sg:city":"Jaun",
    "sg:orig_category":"G\u00fcterbef\u00f6rderung im Strassenverkehr",
    "sg:phone":"+41 32 485 16 66",
    "sg:postcode":"1656",
    "sg:province":"Fribourg",
    "wof:name":"Willy Urfer Transports & D\u00e9m\u00e9nagements",
    "wof:placetype":"venue"
},
  "geometry": {"coordinates":[7.2181568146,47.1907234192],"type":"Point"}
}