{
  "type": "Feature",
  "properties": {
    "iso:country":"CH",
    "sg:address":"Vorstadtstrasse 30",
    "sg:city":"Dietikon",
    "sg:orig_category":"Sonstige pers\u00f6nliche Dienstleistungen",
    "sg:phone":"+41 17415705",
    "sg:postcode":"8953",
    "sg:province":"Z\u00fcrich",
    "wof:name":"Pro Fonda Gmbh",
    "wof:placetype":"venue"
},
  "geometry": {"coordinates":[8.4002990723,47.4078521729],"type":"Point"}
}