{
  "type": "Feature",
  "properties": {
    "iso:country":"CH",
    "sg:address":"Hasenlohweg 1",
    "sg:city":"Ober\u00e4geri",
    "sg:orig_category":"Rechtsberatung",
    "sg:phone":"+41 41 750 77 22",
    "sg:postcode":"6315",
    "sg:province":"Zug",
    "wof:name":"Huber Max Immobilienberatung",
    "wof:placetype":"venue"
},
  "geometry": {"coordinates":[8.6059122086,47.1394615173],"type":"Point"}
}