{
  "type": "Feature",
  "properties": {
    "iso:country":"CH",
    "sg:address":"Chalet L\u00e4rchli",
    "sg:city":"Wengen",
    "sg:orig_category":"Bauschreinerei Innenausbau",
    "sg:phone":"+41 33 855 16 45",
    "sg:postcode":"3823",
    "sg:province":"Bern",
    "wof:name":"Christian Von Allmen Schreinerei & Chaletbau",
    "wof:placetype":"venue"
},
  "geometry": {"coordinates":[7.9216,46.605194],"type":"Point"}
}