{
  "type": "Feature",
  "properties": {
    "addr:full":"Dorfstrasse 6 6467 Schattdorf. Postfach 15 Schattdorf Uri 6467",
    "addr:housenumber":"6;15",
    "addr:postcode":"6467 schattdorf.;6467",
    "addr:street":"Dorfstrasse;Postfach;Uri",
    "iso:country":"CH",
    "sg:address":"Dorfstrasse 6 6467 Schattdorf. Postfach 15",
    "sg:city":"Schattdorf",
    "sg:orig_category":"Aktivit\u00e4ten der Generalunternehmen im Baugewerbe Architektur U Ingenieurb\u00fcros",
    "sg:phone":"+41 41 870 00 08",
    "sg:postcode":"6467",
    "sg:province":"Uri",
    "wof:name":"Rebau Gmbh",
    "wof:placetype":"venue"
},
  "geometry": {"coordinates":[8.655018,46.865688],"type":"Point"}
}