{
  "type": "Feature",
  "properties": {
    "iso:country":"CH",
    "sg:address":"Augwilerstrasse 84",
    "sg:city":"Lufingen",
    "sg:orig_category":"Sonstiger Grosshandel",
    "sg:phone":"+41 18143472",
    "sg:postcode":"8426",
    "sg:province":"Z\u00fcrich",
    "wof:name":"Imex - Trade, Gemperle E.",
    "wof:placetype":"venue"
},
  "geometry": {"coordinates":[8.6020622253,47.4723854065],"type":"Point"}
}