{
  "type": "Feature",
  "properties": {
    "iso:country":"CH",
    "sg:address":"Grueneburg 170",
    "sg:city":"Kleinb\u00f6singen",
    "sg:orig_category":"Dachdeckerei Zimmerei, Dachdeckerei, Bauspenglerei U Abdichtung",
    "sg:phone":"+41 26 674 21 08",
    "sg:postcode":"3213",
    "sg:province":"Fribourg",
    "wof:name":"Krattinger Marcel",
    "wof:placetype":"venue"
},
  "geometry": {"coordinates":[7.192225,46.88694],"type":"Point"}
}