{
  "type": "Feature",
  "properties": {
    "iso:country":"CH",
    "sg:address":"7462",
    "sg:city":"Salouf",
    "sg:classifiers":[
        {
            "category":"Restaurant",
            "type":"Food & Drink"
        }
    ],
    "sg:phone":"+41 81 684 26 04",
    "sg:postcode":"7462",
    "sg:province":"Graubunden",
    "wof:name":"Restaurant Alpina",
    "wof:placetype":"venue"
},
  "geometry": {"coordinates":[9.5760545731,46.624546051],"type":"Point"}
}