{
  "type": "Feature",
  "properties": {
    "iso:country":"CH",
    "sg:address":"Zugerstrasse 15 6330 Cham. Postfach 479",
    "sg:city":"Cham",
    "sg:orig_category":"Reiseb\u00fcros U Reiseveranstalter",
    "sg:phone":"+41 33 744 49 31",
    "sg:postcode":"6330",
    "sg:province":"Zug",
    "wof:name":"Reiseb\u00fcro Eggenberg Ag",
    "wof:placetype":"venue"
},
  "geometry": {"coordinates":[7.2861051559,46.4732818604],"type":"Point"}
}