{
  "type": "Feature",
  "properties": {
    "iso:country":"CH",
    "sg:address":"Alte Landstrasse 1",
    "sg:city":"S\u00f6renberg",
    "sg:orig_category":"Detailhandel mit elektrischen Haushalts, Radio U Fernsehger\u00e4ten ohne ausgepr\u00e4gten Schwerpunkt Elektr",
    "sg:phone":"+41 79 340 89 84",
    "sg:postcode":"6174",
    "sg:province":"Luzern",
    "wof:name":"Erwin Bucher",
    "wof:placetype":"venue"
},
  "geometry": {"coordinates":[8.035030365,46.8212738037],"type":"Point"}
}