{
  "type": "Feature",
  "properties": {
    "iso:country":"CH",
    "sg:address":"Chemin De Renens 1",
    "sg:city":"Lausanne",
    "sg:orig_category":"Zahnkliniken",
    "sg:phone":"+41 21 624 75 35",
    "sg:postcode":"1004",
    "sg:province":"Vaud",
    "wof:name":"Service Dentaire Scolaire",
    "wof:placetype":"venue"
},
  "geometry": {"coordinates":[6.6159658432,46.5266075134],"type":"Point"}
}