{
  "type": "Feature",
  "properties": {
    "iso:country":"CH",
    "sg:address":"Rue De La Poste",
    "sg:city":"Verbier",
    "sg:orig_category":"Detailhandel mit Textilien",
    "sg:phone":"+41 27 771 55 50",
    "sg:postcode":"1936",
    "sg:province":"Valais",
    "wof:name":"Hestia Drap, \u00e9ponge, Nappage",
    "wof:placetype":"venue"
},
  "geometry": {"coordinates":[7.2247400284,46.0970802307],"type":"Point"}
}