{
  "type": "Feature",
  "properties": {
    "iso:country":"CH",
    "sg:address":"Josefstrasse 77",
    "sg:city":"Z\u00fcrich",
    "sg:orig_category":"Fachdetailhandel in Verkaufsr\u00e4umen",
    "sg:phone":"+41 14406120",
    "sg:postcode":"8005",
    "sg:province":"Z\u00fcrich",
    "wof:name":"Schedler Ag",
    "wof:placetype":"venue"
},
  "geometry": {"coordinates":[8.5311965942,47.3825874329],"type":"Point"}
}