{
  "type": "Feature",
  "properties": {
    "iso:country":"CH",
    "sg:address":"Unterwilrain 16",
    "sg:city":"Littau",
    "sg:orig_category":"Herstellung von Automobilen",
    "sg:phone":"+41 41 250 01 77",
    "sg:postcode":"6014",
    "sg:province":"Luzern",
    "wof:name":"Gr\u00fcnenfelder W. Ag",
    "wof:placetype":"venue"
},
  "geometry": {"coordinates":[8.2715740204,47.0490875244],"type":"Point"}
}