{
  "type": "Feature",
  "properties": {
    "iso:country":"CH",
    "sg:address":"Gewerbehaus Schwarz",
    "sg:city":"Bubikon",
    "sg:orig_category":"Betrieb U technische Hilfsdienste des Kultur U Unterhaltungswesens",
    "sg:postcode":"8608",
    "sg:province":"Z\u00fcrich",
    "wof:name":"Spielakademie Brienz Ag",
    "wof:placetype":"venue"
},
  "geometry": {"coordinates":[8.031923,46.754013],"type":"Point"}
}