{
  "type": "Feature",
  "properties": {
    "iso:country":"CH",
    "sg:address":"Industriestrasse 52",
    "sg:city":"Zug",
    "sg:orig_category":"RESTAURANTS: TEA-ROOMS",
    "sg:phone":"+41 55 442 44 84",
    "sg:postcode":"6300",
    "sg:province":"Zug",
    "wof:name":"Caf\u00e9 D\u00f6rfli, Kessler Godi",
    "wof:placetype":"venue"
},
  "geometry": {"coordinates":[8.8524017334,47.1931114197],"type":"Point"}
}