{
  "type": "Feature",
  "properties": {
    "iso:country":"CH",
    "sg:address":"Poststrasse 12",
    "sg:city":"Richterswil",
    "sg:orig_category":"Detailhandel mit Waren verschiedener Art, Hauptrichtung Nahrungsmittel",
    "sg:phone":"+41 17840450",
    "sg:postcode":"8805",
    "sg:province":"Z\u00fcrich",
    "wof:name":"Coop Z\u00fcrichsee-linth",
    "wof:placetype":"venue"
},
  "geometry": {"coordinates":[8.7059106827,47.2083969116],"type":"Point"}
}