{
  "type": "Feature",
  "properties": {
    "iso:country":"CH",
    "sg:address":"F\u00e4lmisstrasse 18 8833 Samstagern. Postfach",
    "sg:city":"Samstagern",
    "sg:orig_category":"Hardwareberatung",
    "sg:phone":"+41 17849758",
    "sg:postcode":"8833",
    "sg:province":"Z\u00fcrich",
    "wof:name":"Adc Computers A. Gilio",
    "wof:placetype":"venue"
},
  "geometry": {"coordinates":[8.6773672104,47.1901855469],"type":"Point"}
}