{
  "type": "Feature",
  "properties": {
    "iso:country":"CH",
    "sg:address":"Immeuble La Crois\u00e9e A 3963 Crans-sur-sierre Case Postale 77",
    "sg:city":"Crans-sur-sierre",
    "sg:orig_category":"Grosshandel mit chemischen Erzeugnissen Grosshandel mit sonstigen Maschinen U Ausr\u00fcstungen f\u00fcr Indus",
    "sg:phone":"+41 61 756 05 10",
    "sg:postcode":"3963",
    "sg:province":"Valais",
    "wof:name":"Sth Spring Trading Ag Chemikalien, Chemierohstoffe, \u00d6le Usw; Handel",
    "wof:placetype":"venue"
},
  "geometry": {"coordinates":[7.595788002,47.4733123779],"type":"Point"}
}