{
  "type": "Feature",
  "properties": {
    "iso:country":"CH",
    "sg:address":"Zwiegartenstrasse 20",
    "sg:city":"Schlieren",
    "sg:orig_category":"Allgemeiner Hoch U Tiefbau",
    "sg:postcode":"8952",
    "sg:province":"Z\u00fcrich",
    "wof:name":"Kor Ag",
    "wof:placetype":"venue"
},
  "geometry": {"coordinates":[8.450915,47.396042],"type":"Point"}
}