{
  "type": "Feature",
  "properties": {
    "iso:country":"CH",
    "sg:address":"Windeggstrasse 26 8200 Schaffhausen. Postfach",
    "sg:city":"Schaffhausen",
    "sg:orig_category":"Grosshandel mit Textilien",
    "sg:phone":"+41 52 624 72 34",
    "sg:postcode":"8203",
    "sg:province":"Schaffhausen",
    "wof:name":"Bhalla S.r.",
    "wof:placetype":"venue"
},
  "geometry": {"coordinates":[8.6562261581,47.6944313049],"type":"Point"}
}