{
  "type": "Feature",
  "properties": {
    "iso:country":"CH",
    "sg:city":"Aarberg Be",
    "sg:orig_category":"Medizin, Pharmaprodukte",
    "sg:postcode":"3270",
    "sg:province":"Bern",
    "wof:name":"Intercosina Ag - Dr.r.a.eckstein Kosmetik",
    "wof:placetype":"venue"
},
  "geometry": {"coordinates":[7.275655,47.042568],"type":"Point"}
}