{
  "type": "Feature",
  "properties": {
    "iso:country":"CH",
    "sg:address":"Weltpoststrasse 16",
    "sg:city":"Bern",
    "sg:orig_category":"Arztpraxen",
    "sg:phone":"+41 31 351 21 21",
    "sg:postcode":"3015",
    "sg:province":"Bern",
    "wof:name":"Dr.med.roland Wettstein Spezialarzt Fmh",
    "wof:placetype":"venue"
},
  "geometry": {"coordinates":[7.475501,46.938171],"type":"Point"}
}