{
  "type": "Feature",
  "properties": {
    "iso:country":"CH",
    "sg:address":"Beuge 4",
    "sg:city":"N\u00e4fels",
    "sg:orig_category":"Grosshandel mit Wein U Spirituosen",
    "sg:phone":"+41 55 612 11 46",
    "sg:postcode":"8752",
    "sg:province":"Glarus",
    "wof:name":"Josef Landolt Walhalla Getr\u00e4nke Engros",
    "wof:placetype":"venue"
},
  "geometry": {"coordinates":[9.0622005463,47.098236084],"type":"Point"}
}