{
  "type": "Feature",
  "properties": {
    "iso:country":"CH",
    "sg:address":"Altmannsteinstrasse 32",
    "sg:city":"H\u00f6ri",
    "sg:orig_category":"Finanzierungsinstitutionen Kauf U Verkauf von Immobilien auf eigene Rechnung",
    "sg:phone":"+41 18604460",
    "sg:postcode":"8181",
    "sg:province":"Z\u00fcrich",
    "wof:name":"Romifida Ag",
    "wof:placetype":"venue"
},
  "geometry": {"coordinates":[8.5176000595,47.5113296509],"type":"Point"}
}