{
  "type": "Feature",
  "properties": {
    "iso:country":"CH",
    "sg:address":"Ausserdorf 13",
    "sg:city":"Azmoos",
    "sg:orig_category":"Direct Voltage Converters Dc/Dc Converters For Vehicles And Ships",
    "sg:phone":"+41 32 967 88 00",
    "sg:postcode":"9478",
    "sg:province":"St. Gallen",
    "wof:name":"Switch Craft S.a.",
    "wof:placetype":"venue"
},
  "geometry": {"coordinates":[6.8286328316,47.1137428284],"type":"Point"}
}