{
  "type": "Feature",
  "properties": {
    "iso:country":"CH",
    "sg:address":"Buchsistrasse 16",
    "sg:city":"Th\u00f6rigen",
    "sg:orig_category":"G\u00fcterbef\u00f6rderung im Strassenverkehr",
    "sg:phone":"+41 62 961 30 01",
    "sg:postcode":"3367",
    "sg:province":"Bern",
    "wof:name":"Niklaus Br\u00fcgger Transporte",
    "wof:placetype":"venue"
},
  "geometry": {"coordinates":[7.7245311737,47.1770973206],"type":"Point"}
}