{
  "type": "Feature",
  "properties": {
    "iso:country":"CH",
    "sg:address":"Landhausstrasse 3",
    "sg:city":"Dozwil",
    "sg:orig_category":"Herstellung von Elektromotoren, Generatoren U Transformatoren",
    "sg:phone":"+41 32 351 23 17",
    "sg:postcode":"8580",
    "sg:province":"Thurgau",
    "wof:name":"Energieversorgung B\u00fcren Ag",
    "wof:placetype":"venue"
},
  "geometry": {"coordinates":[7.3720650673,47.1392173767],"type":"Point"}
}