{
  "type": "Feature",
  "properties": {
    "iso:country":"CH",
    "sg:address":"Dorfstrasse 13",
    "sg:city":"Neuendorf",
    "sg:orig_category":"RESTAURANTS: TEA-ROOMS",
    "sg:postcode":"4623",
    "sg:province":"Solothurn",
    "wof:name":"Waldis-kissling Hans",
    "wof:placetype":"venue"
},
  "geometry": {"coordinates":[7.7876272202,47.2999534607],"type":"Point"}
}