{
  "type": "Feature",
  "properties": {
    "addr:full":"Wolfacher 25 Rain Luzern 6026",
    "addr:housenumber":"25",
    "addr:postcode":"6026",
    "addr:street":"Wolfacher",
    "iso:country":"CH",
    "sg:address":"Wolfacher 25",
    "sg:city":"Rain",
    "sg:orig_category":"Allgemeiner Hoch U Tiefbau",
    "sg:phone":"+41 41 420 42 11",
    "sg:postcode":"6026",
    "sg:province":"Luzern",
    "wof:name":"Dmi Design Minder Daniel",
    "wof:placetype":"venue"
},
  "geometry": {"coordinates":[8.246365,47.128139],"type":"Point"}
}