{
  "type": "Feature",
  "properties": {
    "iso:country":"CH",
    "sg:address":"Lindenplatz 5",
    "sg:city":"Gr\u00e4nichen",
    "sg:orig_category":"Notariate",
    "sg:phone":"+41 62 842 67 77",
    "sg:postcode":"5722",
    "sg:province":"Aargau",
    "wof:name":"Markus Hofmann Notariatsb\u00fcro",
    "wof:placetype":"venue"
},
  "geometry": {"coordinates":[8.0979499817,47.3598213196],"type":"Point"}
}