{
  "type": "Feature",
  "properties": {
    "iso:country":"CH",
    "sg:address":"Dorfplatz 4",
    "sg:city":"Lostorf",
    "sg:orig_category":"Sonstiger Detailhandel mit Waren verschiedener Art, Hauptrichtung Nichtnahrungsmittel",
    "sg:phone":"+41 62 298 20 24",
    "sg:postcode":"4654",
    "sg:province":"Solothurn",
    "wof:name":"Star Flower Bitterli Bl\u00fctenessenzen Und Naturheilmittel; Handel",
    "wof:placetype":"venue"
},
  "geometry": {"coordinates":[7.9466328621,47.3865203857],"type":"Point"}
}