{
  "type": "Feature",
  "properties": {
    "iso:country":"CH",
    "sg:address":"Chemin Des Fayards 7 1032 Romanel-s-lausanne Case Postale 39",
    "sg:city":"Romanel-s-lausanne",
    "sg:orig_category":"Bauschreinerei Innenausbau",
    "sg:phone":"+41 21 644 38 38",
    "sg:postcode":"1032",
    "sg:province":"Vaud",
    "wof:name":"Agencement Ledermann Sa",
    "wof:placetype":"venue"
},
  "geometry": {"coordinates":[6.60169,46.569359],"type":"Point"}
}