{
  "type": "Feature",
  "properties": {
    "iso:country":"CH",
    "sg:address":"Route Des Pralettes 1",
    "sg:city":"Marly",
    "sg:orig_category":"Drogerien Fachdetailhandel mit pharmazeutischen Produkten",
    "sg:phone":"+41 26 651 90 30",
    "sg:postcode":"1723",
    "sg:province":"Fribourg",
    "wof:name":"Pharmacie-droguerie Du Levant",
    "wof:placetype":"venue"
},
  "geometry": {"coordinates":[6.9115872383,46.6901626587],"type":"Point"}
}