{
  "type": "Feature",
  "properties": {
    "addr:full":"Spitalgasse 34 Bern Bern 3011",
    "addr:housenumber":"34",
    "addr:postcode":"3011",
    "addr:street":"Spitalgasse",
    "iso:country":"CH",
    "sg:address":"Spitalgasse 34",
    "sg:city":"Bern",
    "sg:orig_category":"Detailhandel mit Blumen U Pflanzen Fachdetailhandel in Verkaufsr\u00e4umen",
    "sg:phone":"+41 31 311 43 23",
    "sg:postcode":"3011",
    "sg:province":"Bern",
    "wof:name":"Petite Fleur Gmbh",
    "wof:placetype":"venue"
},
  "geometry": {"coordinates":[7.441833,46.948002],"type":"Point"}
}