{
  "type": "Feature",
  "properties": {
    "iso:country":"CH",
    "sg:address":"Chemin Poya",
    "sg:city":"Oron-la-ville",
    "sg:orig_category":"Detailhandel mit Fleisch U Fleischwaren",
    "sg:phone":"+41 21 907 71 22",
    "sg:postcode":"1610",
    "sg:province":"Vaud",
    "wof:name":"Michel Sonney Boucherie Chevalines",
    "wof:placetype":"venue"
},
  "geometry": {"coordinates":[6.8276119232,46.5722045898],"type":"Point"}
}