{
  "type": "Feature",
  "properties": {
    "iso:country":"CH",
    "sg:address":"Altgraben 29",
    "sg:city":"H\u00e4rkingen",
    "sg:orig_category":"Grosshandel mit Holz U Baustoffen Herstellung von Konstruktionsteilen, Fertigbauteilen U Ausbaueleme",
    "sg:phone":"+41 62 398 03 08",
    "sg:postcode":"4624",
    "sg:province":"Solothurn",
    "wof:name":"Pede T\u00fcren-center Peter R\u00fctti",
    "wof:placetype":"venue"
},
  "geometry": {"coordinates":[7.8110098839,47.3167648315],"type":"Point"}
}