{
  "type": "Feature",
  "properties": {
    "iso:country":"CH",
    "sg:address":"Bahnhofstrasse 40 6210 Sursee. Postfach 3062",
    "sg:city":"Sursee",
    "sg:orig_category":"Architektur U Ingenieurb\u00fcros Architekturb\u00fcros",
    "sg:phone":"+41 41 921 17 31",
    "sg:postcode":"6210",
    "sg:province":"Luzern",
    "wof:name":"Architektur Und Bauleitung Hunziker & Wetterwald Ag",
    "wof:placetype":"venue"
},
  "geometry": {"coordinates":[8.099561,47.171638],"type":"Point"}
}