{
  "type": "Feature",
  "properties": {
    "iso:country":"CH",
    "sg:address":"Funtanella 10",
    "sg:city":"Samedan",
    "sg:orig_category":"Detektivb\u00fcros U \u00dcberwachung",
    "sg:postcode":"7503",
    "sg:province":"Graubunden",
    "wof:name":"Srt-security International Ag Sicherheitsdienstleistungscenter",
    "wof:placetype":"venue"
},
  "geometry": {"coordinates":[9.8676509857,46.5327453613],"type":"Point"}
}