{
  "type": "Feature",
  "properties": {
    "iso:country":"CH",
    "sg:address":"Rte Montagne-de-boujean 47 2500 Biel/bienne. Postfach",
    "sg:city":"Biel/bienne",
    "sg:orig_category":"Pensionskassen",
    "sg:postcode":"2504",
    "sg:province":"Bern",
    "wof:name":"Fonds De Pr\u00e9voyance En Faveur Du Personnel De La Fabrique De Cadrans Von Kaenel & Cie Sa.",
    "wof:placetype":"venue"
},
  "geometry": {"coordinates":[7.2899799347,47.1467399597],"type":"Point"}
}