{
  "type": "Feature",
  "properties": {
    "iso:country":"CH",
    "sg:address":"Rue Principale 42",
    "sg:city":"Evionnaz",
    "sg:orig_category":"Nationale Postdienste",
    "sg:phone":"+41 27 767 12 91",
    "sg:postcode":"1902",
    "sg:province":"Valais",
    "wof:name":"La Poste Suisse",
    "wof:placetype":"venue"
},
  "geometry": {"coordinates":[7.0235872269,46.1776657104],"type":"Point"}
}