{
  "type": "Feature",
  "properties": {
    "iso:country":"CH",
    "sg:address":"1543",
    "sg:city":"Grandcour",
    "sg:orig_category":"Verwertung von Milch",
    "sg:postcode":"1543",
    "sg:province":"Vaud",
    "wof:name":"Soci\u00e9t\u00e9 De Laiterie De Grandcour",
    "wof:placetype":"venue"
},
  "geometry": {"coordinates":[6.9286150932,46.8717956543],"type":"Point"}
}