{
  "type": "Feature",
  "properties": {
    "iso:country":"CH",
    "sg:address":"Etzelstrasse 42 8038 Z\u00fcrich. Postfach 982",
    "sg:city":"Z\u00fcrich",
    "sg:orig_category":"Grosshandel mit sonstigen Konsumg\u00fctern",
    "sg:phone":"+41 14874050",
    "sg:postcode":"8038",
    "sg:province":"Z\u00fcrich",
    "wof:name":"Legler International Ag Verm\u00f6gensverwaltung, Bes. Handel, Umarbeitung V. Textilprodukte Usw",
    "wof:placetype":"venue"
},
  "geometry": {"coordinates":[8.530913353,47.3469047546],"type":"Point"}
}