{
  "type": "Feature",
  "properties": {
    "iso:country":"CH",
    "sg:address":"Colline Chemin De La 11",
    "sg:city":"Lausanne",
    "sg:orig_category":"G\u00fcterbef\u00f6rderung im Strassenverkehr",
    "sg:phone":"+41 21 624 35 51",
    "sg:postcode":"1007",
    "sg:province":"Vaud",
    "wof:name":"Cevey & Cie, Successeur De Cevey Transports",
    "wof:placetype":"venue"
},
  "geometry": {"coordinates":[6.610640049,46.5221061707],"type":"Point"}
}