{
  "type": "Feature",
  "properties": {
    "iso:country":"CH",
    "sg:address":"Eggwiesstrasse 60",
    "sg:city":"Russikon",
    "sg:orig_category":"Werbeagenturen Werbegrafikateliers",
    "sg:phone":"+41 19540085",
    "sg:postcode":"8332",
    "sg:province":"Z\u00fcrich",
    "wof:name":"Peter Metzger Grafik & Werbeberatung",
    "wof:placetype":"venue"
},
  "geometry": {"coordinates":[8.7702655792,47.3992424011],"type":"Point"}
}