{
  "type": "Feature",
  "properties": {
    "iso:country":"CH",
    "sg:address":"Route Du Petit-moncor 1 1752 Cormanon. Postfach",
    "sg:city":"Cormanon",
    "sg:orig_category":"Mechanik",
    "sg:postcode":"1752",
    "sg:province":"Fribourg",
    "wof:name":"Delatech Sa",
    "wof:placetype":"venue"
},
  "geometry": {"coordinates":[7.130428791,46.7955818176],"type":"Point"}
}