{
  "type": "Feature",
  "properties": {
    "iso:country":"CH",
    "sg:address":"S\u00e4gli 8",
    "sg:city":"Speicher",
    "sg:orig_category":"Datenverarbeitungsdienste Markt U Meinungsforschung",
    "sg:phone":"+41 71 344 11 08",
    "sg:postcode":"9042",
    "sg:province":"Appenzell Ausserrhoden",
    "wof:name":"Burkhard & Co Marketing & Informatik",
    "wof:placetype":"venue"
},
  "geometry": {"coordinates":[9.452396,47.403358],"type":"Point"}
}