{
  "type": "Feature",
  "properties": {
    "iso:country":"CH",
    "sg:address":"Oberdorfstrasse 58",
    "sg:city":"Seftigen",
    "sg:orig_category":"Elektroinstallation",
    "sg:phone":"+41 32 931 45 28",
    "sg:postcode":"3662",
    "sg:province":"Bern",
    "wof:name":"Siegenthaler & Choffet Sa Entreprise D'\u00e9lectricit\u00e9",
    "wof:placetype":"venue"
},
  "geometry": {"coordinates":[6.7523207664,47.0589866638],"type":"Point"}
}