{
  "type": "Feature",
  "properties": {
    "iso:country":"CH",
    "sg:address":"Schw\u00e4ntenmos 14",
    "sg:city":"Zumikon",
    "sg:orig_category":"Innendekorationsateliers",
    "sg:phone":"+41 19180312",
    "sg:postcode":"8126",
    "sg:province":"Z\u00fcrich",
    "wof:name":"Erwin Keller Tapezierer-dekorateurgesch\u00e4ft",
    "wof:placetype":"venue"
},
  "geometry": {"coordinates":[8.6196470261,47.3388710022],"type":"Point"}
}