{
  "type": "Feature",
  "properties": {
    "iso:country":"CH",
    "sg:address":"Kornweg 17",
    "sg:city":"Oftringen",
    "sg:orig_category":"Instandhaltung U Reparatur von Automobilen",
    "sg:phone":"+41 62 789 50 85",
    "sg:postcode":"4665",
    "sg:province":"Aargau",
    "wof:name":"Auto Logo Ag",
    "wof:placetype":"venue"
},
  "geometry": {"coordinates":[7.9330019951,47.306186676],"type":"Point"}
}