{
  "type": "Feature",
  "properties": {
    "iso:country":"CH",
    "sg:address":"Dorfstrasse 11",
    "sg:city":"Oberegg",
    "sg:orig_category":"Instandhaltung U Reparatur von Automobilen",
    "sg:phone":"+41 79 406 63 63",
    "sg:postcode":"9413",
    "sg:province":"Appenzell Innerhoden",
    "wof:name":"Koller Peter",
    "wof:placetype":"venue"
},
  "geometry": {"coordinates":[9.277264595,47.1907463074],"type":"Point"}
}