{
  "type": "Feature",
  "properties": {
    "iso:country":"CH",
    "sg:address":"Murtenstrasse 47",
    "sg:city":"Frauenkappelen",
    "sg:orig_category":"Detailhandel mit Brot, Back U S\u00fcsswaren",
    "sg:phone":"+41 31 926 21 02",
    "sg:postcode":"3202",
    "sg:province":"Bern",
    "wof:name":"Hans & P. Marti B\u00e4ckerei-konditorei",
    "wof:placetype":"venue"
},
  "geometry": {"coordinates":[7.338085,46.954304],"type":"Point"}
}