{
  "type": "Feature",
  "properties": {
    "iso:country":"CH",
    "sg:address":"Chemin Du Relai 5 1258 Perly Case Postale 71",
    "sg:city":"Perly",
    "sg:orig_category":"Hardwareberatung Softwareentwicklung U beratung",
    "sg:phone":"+41 22 771 04 44",
    "sg:postcode":"1258",
    "sg:province":"Gen\u00e8ve",
    "wof:name":"Microprog Sa",
    "wof:placetype":"venue"
},
  "geometry": {"coordinates":[6.093228817,46.1560935974],"type":"Point"}
}