{
  "type": "Feature",
  "properties": {
    "addr:full":"Marktgasse 10b Rheinfelden Aargau 4310",
    "addr:housenumber":"10b",
    "addr:postcode":"4310",
    "addr:street":"Marktgasse",
    "iso:country":"CH",
    "sg:address":"Marktgasse 10b",
    "sg:city":"Rheinfelden",
    "sg:orig_category":"Arztpraxen",
    "sg:phone":"+41 61 831 27 00",
    "sg:postcode":"4310",
    "sg:province":"Aargau",
    "wof:name":"Dr.med.hans-j\u00f6rg Boerlin Spezialarzt Fmh",
    "wof:placetype":"venue"
},
  "geometry": {"coordinates":[7.793801,47.555382],"type":"Point"}
}