{
  "type": "Feature",
  "properties": {
    "iso:country":"CH",
    "sg:address":"Plannaz Chemin De 11",
    "sg:city":"Gland",
    "sg:orig_category":"Detailhandel mit Waren verschiedener Art, Hauptrichtung Nahrungsmittel",
    "sg:phone":"+41 22 364 40 64",
    "sg:postcode":"1196",
    "sg:province":"Vaud",
    "wof:name":"Euro Marroni, Merlino Dr. S.",
    "wof:placetype":"venue"
},
  "geometry": {"coordinates":[6.2614498138,46.4224014282],"type":"Point"}
}