{
  "type": "Feature",
  "properties": {
    "iso:country":"CH",
    "sg:address":"Via Suot Chesas 8",
    "sg:city":"Champf\u00e8r",
    "sg:orig_category":"Vermietung U Verpachtung von eigenen Immobilien",
    "sg:phone":"+41 81 833 65 61",
    "sg:postcode":"7512",
    "sg:province":"Graubunden",
    "wof:name":"Donema Ag",
    "wof:placetype":"venue"
},
  "geometry": {"coordinates":[9.8134450912,46.4791183472],"type":"Point"}
}