{
  "type": "Feature",
  "properties": {
    "iso:country":"CH",
    "sg:address":"Parc Scientifique Epfl",
    "sg:city":"Lausanne",
    "sg:orig_category":"Herstellung von medizinischen U chirurgischen Ger\u00e4ten Herstellung von medizinischen U chirurgischen ",
    "sg:phone":"+41 22 367 24 08",
    "sg:postcode":"1015",
    "sg:province":"Vaud",
    "wof:name":"Endoart Sa",
    "wof:placetype":"venue"
},
  "geometry": {"coordinates":[6.5793399811,46.520160675],"type":"Point"}
}