{
  "type": "Feature",
  "properties": {
    "iso:country":"CH",
    "sg:address":"Rue Du Vallon 32",
    "sg:city":"Lausanne",
    "sg:orig_category":"Druck ohne Zeitungsdruck Offsetdruck",
    "sg:phone":"+41 21 320 46 20",
    "sg:postcode":"1005",
    "sg:province":"Vaud",
    "wof:name":"Imprimerie Closson Alain",
    "wof:placetype":"venue"
},
  "geometry": {"coordinates":[6.6387529373,46.5266265869],"type":"Point"}
}