{
  "type": "Feature",
  "properties": {
    "iso:country":"CH",
    "sg:address":"Obere Gasse 9 7000 Chur. Postfach",
    "sg:city":"Chur",
    "sg:classifiers":[
        {
            "category":"Manufacturing",
            "subcategory":"Metals",
            "type":"Manufacturing & Wholesale Goods"
        }
    ],
    "sg:phone":"+41 81 252 13 33",
    "sg:postcode":"7000",
    "sg:province":"Graubunden",
    "sg:tags":[
        "edelstahl",
        "u",
        "blank"
    ],
    "wof:name":"Moosberger Ch.",
    "wof:placetype":"venue"
},
  "geometry": {"coordinates":[9.530686,46.848557],"type":"Point"}
}