{
  "type": "Feature",
  "properties": {
    "iso:country":"CH",
    "sg:address":"B\u00fchlholz",
    "sg:city":"Grindelwald",
    "sg:orig_category":"G\u00fcterbef\u00f6rderung im Strassenverkehr",
    "sg:postcode":"3818",
    "sg:province":"Bern",
    "wof:name":"Wenger Kaspar",
    "wof:placetype":"venue"
},
  "geometry": {"coordinates":[8.0171051025,46.6285095215],"type":"Point"}
}