{
  "type": "Feature",
  "properties": {
    "iso:country":"CH",
    "sg:address":"Bahnhofstrasse 1",
    "sg:city":"Igis",
    "sg:orig_category":"Fachdetailhandel mit pharmazeutischen Produkten",
    "sg:postcode":"7206",
    "sg:province":"Graubunden",
    "wof:name":"Bahnhof Apotheke Landquart, Villa Dr. S.",
    "wof:placetype":"venue"
},
  "geometry": {"coordinates":[9.5733108521,46.9458618164],"type":"Point"}
}