{
  "type": "Feature",
  "properties": {
    "iso:country":"CH",
    "sg:address":"Seestrasse 57",
    "sg:city":"Horn",
    "sg:orig_category":"Kauf U Verkauf von Immobilien auf eigene Rechnung",
    "sg:postcode":"9326",
    "sg:province":"Thurgau",
    "wof:name":"Kawa Beteiligungen Gmbh",
    "wof:placetype":"venue"
},
  "geometry": {"coordinates":[9.4655332565,47.4951248169],"type":"Point"}
}