{
  "type": "Feature",
  "properties": {
    "iso:country":"CH",
    "sg:address":"Sch\u00fcpfgasse 41",
    "sg:city":"Faulensee",
    "sg:orig_category":"Sonstige k\u00fcnstlerische U schriftstellerische T\u00e4tigkeiten U Darbietungen",
    "sg:phone":"+41 33 654 77 66",
    "sg:postcode":"3705",
    "sg:province":"Bern",
    "wof:name":"Radscha Atelier Kyburz & W\u00fcthrich",
    "wof:placetype":"venue"
},
  "geometry": {"coordinates":[7.700553894,46.6758499146],"type":"Point"}
}