{
  "type": "Feature",
  "properties": {
    "iso:country":"CH",
    "sg:address":"Im Rick 4",
    "sg:city":"Zihlschlacht",
    "sg:orig_category":"Unternehmensberatung",
    "sg:postcode":"8588",
    "sg:province":"Thurgau",
    "wof:name":"Dr. Schefer & Partner, Consultants",
    "wof:placetype":"venue"
},
  "geometry": {"coordinates":[9.257226944,47.5177764893],"type":"Point"}
}