{
  "type": "Feature",
  "properties": {
    "iso:country":"CH",
    "sg:address":"Gewerbehallenstrasse 4",
    "sg:city":"Wallisellen",
    "sg:orig_category":"Grosshandel mit Textilien Grosshandel mit sonstigen Konsumg\u00fctern",
    "sg:phone":"+41 18307010",
    "sg:postcode":"8304",
    "sg:province":"Z\u00fcrich",
    "wof:name":"Tcw Texcare Ag",
    "wof:placetype":"venue"
},
  "geometry": {"coordinates":[8.574886322,47.4147644043],"type":"Point"}
}