{
  "type": "Feature",
  "properties": {
    "iso:country":"CH",
    "sg:address":"Rathausgasse 26",
    "sg:city":"Bern",
    "sg:orig_category":"Herstellung von Schmuck, Gold U Silberschmiedwaren Kunsthandel",
    "sg:phone":"+41 31 311 02 50",
    "sg:postcode":"3011",
    "sg:province":"Bern",
    "wof:name":"Heinz Huber",
    "wof:placetype":"venue"
},
  "geometry": {"coordinates":[7.4502840042,46.9485969543],"type":"Point"}
}