{
  "type": "Feature",
  "properties": {
    "iso:country":"CH",
    "sg:address":"Avenue William-fraisse 9",
    "sg:city":"Lausanne",
    "sg:orig_category":"Zahnarztpraxen",
    "sg:phone":"+41 21 616 55 37",
    "sg:postcode":"1006",
    "sg:province":"Vaud",
    "wof:name":"Dr M\u00e9d. Dent. Yves Nerini M\u00e9decin-dentiste",
    "wof:placetype":"venue"
},
  "geometry": {"coordinates":[6.6254558563,46.5158843994],"type":"Point"}
}