{
  "type": "Feature",
  "properties": {
    "iso:country":"CH",
    "sg:address":"Herrlisberg",
    "sg:city":"W\u00e4denswil",
    "sg:orig_category":"Mechanische Werkst\u00e4tten",
    "sg:phone":"+41 17803709",
    "sg:postcode":"8820",
    "sg:province":"Z\u00fcrich",
    "wof:name":"Hansheinrich Herter Mechanische Werkst\u00e4tte",
    "wof:placetype":"venue"
},
  "geometry": {"coordinates":[8.6567115784,47.2202720642],"type":"Point"}
}