{
  "type": "Feature",
  "properties": {
    "addr:full":"Wasserwerkstrasse 93 Z\u00fcrich Z\u00fcrich 8037",
    "addr:housenumber":"93",
    "addr:postcode":"8037",
    "addr:street":"Wasserwerkstrasse",
    "iso:country":"CH",
    "sg:address":"Wasserwerkstrasse 93",
    "sg:city":"Z\u00fcrich",
    "sg:orig_category":"Architektur U Ingenieurb\u00fcros",
    "sg:phone":"+41 13622777",
    "sg:postcode":"8037",
    "sg:province":"Z\u00fcrich",
    "wof:name":"Planungsb\u00fcro Matta Thomas R. B\u00fcro F\u00fcr Raumplanung",
    "wof:placetype":"venue"
},
  "geometry": {"coordinates":[8.53358,47.387135],"type":"Point"}
}