{
  "type": "Feature",
  "properties": {
    "iso:country":"CH",
    "sg:address":"6014",
    "sg:city":"Littau",
    "sg:classifiers":[
        {
            "category":"Travel",
            "subcategory":"Hotels & Motels",
            "type":"Entertainment"
        }
    ],
    "sg:phone":"+41 41 850 11 38",
    "sg:postcode":"6014",
    "sg:province":"Luzern",
    "sg:tags":[
        "hotels",
        "mit",
        "restaurant"
    ],
    "wof:name":"Achermann O. Hotel Bahnhof.",
    "wof:placetype":"venue"
},
  "geometry": {"coordinates":[8.4353914261,47.0831871033],"type":"Point"}
}