{
  "type": "Feature",
  "properties": {
    "iso:country":"CH",
    "sg:address":"Rue Des Terreaux 7",
    "sg:city":"Lausanne",
    "sg:orig_category":"Mit dem Versicherungsgewerbe verbundene T\u00e4tigkeiten",
    "sg:phone":"+41 21 312 41 91",
    "sg:postcode":"1003",
    "sg:province":"Vaud",
    "wof:name":"Cabinet D'assurances Et De Gestion, R. Atakurt Analyses Et Gestion De Portefeuilles D'assurances Etc",
    "wof:placetype":"venue"
},
  "geometry": {"coordinates":[6.628136158,46.5222244263],"type":"Point"}
}