{
  "type": "Feature",
  "properties": {
    "iso:country":"CH",
    "sg:address":"Hinterfultigen",
    "sg:city":"R\u00fceggisberg",
    "sg:orig_category":"Verwertung von Milch",
    "sg:postcode":"3088",
    "sg:province":"Bern",
    "wof:name":"K\u00e4sereigenossenschaft Hinterfultigen",
    "wof:placetype":"venue"
},
  "geometry": {"coordinates":[7.4284648895,46.7916717529],"type":"Point"}
}