{
  "type": "Feature",
  "properties": {
    "iso:country":"CH",
    "sg:address":"Corso San Gottardo 35",
    "sg:city":"Chiasso",
    "sg:orig_category":"Handelsvermittlung U Grosshandel",
    "sg:phone":"+41 91 682 73 31",
    "sg:postcode":"6830",
    "sg:province":"Ticino",
    "wof:name":"Far-com Sa",
    "wof:placetype":"venue"
},
  "geometry": {"coordinates":[9.0298109055,45.8340835571],"type":"Point"}
}