{
  "type": "Feature",
  "properties": {
    "iso:country":"CH",
    "sg:address":"Flurstrasse 26",
    "sg:city":"Bern",
    "sg:orig_category":"Sonstige pers\u00f6nliche Dienstleistungen Unternehmensberatung",
    "sg:phone":"+41 16861626",
    "sg:postcode":"3014",
    "sg:province":"Bern",
    "wof:name":"Color Motion Gmbh",
    "wof:placetype":"venue"
},
  "geometry": {"coordinates":[8.6445760727,47.1927070618],"type":"Point"}
}