{
  "type": "Feature",
  "properties": {
    "iso:country":"CH",
    "sg:address":"R\u00f6sslistrasse 2",
    "sg:city":"Wagen",
    "sg:orig_category":"Detailhandel mit S\u00e4uglings U Kinderbekleidung",
    "sg:phone":"+41 55 212 49 20",
    "sg:postcode":"8646",
    "sg:province":"St. Gallen",
    "wof:name":"Zwerglib\u00f6rse",
    "wof:placetype":"venue"
},
  "geometry": {"coordinates":[8.8892402649,47.2313842773],"type":"Point"}
}