{
  "type": "Feature",
  "properties": {
    "iso:country":"CH",
    "sg:address":"Hauptstrasse 8 8280 Kreuzlingen. Postfach",
    "sg:city":"Kreuzlingen",
    "sg:classifiers":[
        {
            "category":"Government",
            "subcategory":"Post Office",
            "type":"Public Place"
        }
    ],
    "sg:phone":"+41 71 672 50 80",
    "sg:postcode":"8280",
    "sg:province":"Thurgau",
    "sg:tags":[
        "caf\u00e9s",
        "tea-rooms"
    ],
    "wof:name":"Caf\u00e9 M\u00f6ve",
    "wof:placetype":"venue"
},
  "geometry": {"coordinates":[9.1732606888,47.6542663574],"type":"Point"}
}