{
  "type": "Feature",
  "properties": {
    "iso:country":"CH",
    "sg:address":"Schwanenstrasse 32",
    "sg:city":"Einsiedeln",
    "sg:orig_category":"Sonstige Finanzierungsinstitutionen",
    "sg:phone":"+41 55 418 81 50",
    "sg:postcode":"8840",
    "sg:province":"Schwyz",
    "wof:name":"Zfe Zentrum F\u00fcr Erfolg Gmbh",
    "wof:placetype":"venue"
},
  "geometry": {"coordinates":[8.7485132217,47.1261329651],"type":"Point"}
}