{
  "type": "Feature",
  "properties": {
    "iso:country":"CH",
    "sg:address":"Ulmenstrasse 48",
    "sg:city":"Frauenfeld",
    "sg:orig_category":"M\u00f6belschreinereien",
    "sg:phone":"+41 52 720 87 29",
    "sg:postcode":"8500",
    "sg:province":"Thurgau",
    "wof:name":"M\u00f6bel - Wohnen - Design Schranz Gmbh",
    "wof:placetype":"venue"
},
  "geometry": {"coordinates":[8.8773241043,47.5515899658],"type":"Point"}
}