{
  "type": "Feature",
  "properties": {
    "iso:country":"CH",
    "sg:address":"Avenue Du Rothorn 26 3960 Sierre Case Postale 548",
    "sg:city":"Sierre",
    "sg:orig_category":"Bauspenglerei Dachdeckerei",
    "sg:phone":"+41 27 456 53 14",
    "sg:postcode":"3960",
    "sg:province":"Valais",
    "wof:name":"Lehner Andr\u00e9 Install. Sanit., Ferblanterie, Couverture.",
    "wof:placetype":"venue"
},
  "geometry": {"coordinates":[7.530923,46.293526],"type":"Point"}
}