{
  "type": "Feature",
  "properties": {
    "iso:country":"CH",
    "sg:address":"Schulmattstrasse 11",
    "sg:city":"Ittigen",
    "sg:orig_category":"Herstellung von Teppichen",
    "sg:phone":"+41 31 921 04 20",
    "sg:postcode":"3063",
    "sg:province":"Bern",
    "wof:name":"Urs Staub Teppiche + Bodenbel\u00e4ge Gmbh",
    "wof:placetype":"venue"
},
  "geometry": {"coordinates":[7.4796447754,46.9746704102],"type":"Point"}
}