{
  "type": "Feature",
  "properties": {
    "iso:country":"CH",
    "sg:address":"Via Jauch 1 6500 Bellinzona. Postfach",
    "sg:city":"Bellinzona",
    "sg:orig_category":"Grossbanken",
    "sg:phone":"+41 91 801 31 11",
    "sg:postcode":"6501",
    "sg:province":"Ticino",
    "wof:name":"Ubs Sa",
    "wof:placetype":"venue"
},
  "geometry": {"coordinates":[9.0202159882,46.1904945374],"type":"Point"}
}