{
  "type": "Feature",
  "properties": {
    "iso:country":"CH",
    "sg:address":"1976",
    "sg:city":"Erde",
    "sg:classifiers":[
        {
            "category":"Restaurant",
            "type":"Food & Drink"
        }
    ],
    "sg:phone":"+41 17864611",
    "sg:postcode":"1976",
    "sg:province":"Valais",
    "wof:name":"Restaurant Dapa",
    "wof:placetype":"venue"
},
  "geometry": {"coordinates":[8.7280254364,47.2012557983],"type":"Point"}
}