{
  "type": "Feature",
  "properties": {
    "iso:country":"CH",
    "sg:address":"Ch. De La M\u00e8re-voie 84 1228 Plan-les-ouates Case Postale",
    "sg:city":"Plan-les-ouates",
    "sg:orig_category":"Zimmerei, Dachdeckerei, Bauspenglerei U Abdichtung",
    "sg:phone":"+41 22 794 35 93",
    "sg:postcode":"1228",
    "sg:province":"Gen\u00e8ve",
    "wof:name":"Fleury Jean-marie Ferblanterie Et Entretien De Toitures",
    "wof:placetype":"venue"
},
  "geometry": {"coordinates":[6.115653038,46.1689033508],"type":"Point"}
}