{
  "type": "Feature",
  "properties": {
    "iso:country":"CH",
    "sg:address":"Oberg\u00fctschrain 2 6003 Luzern. Postfach",
    "sg:city":"Luzern",
    "sg:orig_category":"Pensionskassen",
    "sg:postcode":"6003",
    "sg:province":"Luzern",
    "wof:name":"Wohlfahrtsfonds Der Therma Ag",
    "wof:placetype":"venue"
},
  "geometry": {"coordinates":[9.0856952667,47.0004196167],"type":"Point"}
}