{
  "type": "Feature",
  "properties": {
    "iso:country":"CH",
    "sg:address":"Albisstrasse 26",
    "sg:city":"Adliswil",
    "sg:orig_category":"Detailhandel mit elektrischen Haushalts-,Radio U Fernsehger\u00e4ten sowie Musikinstrumenten",
    "sg:phone":"+41 71 755 26 25",
    "sg:postcode":"8134",
    "sg:province":"Z\u00fcrich",
    "wof:name":"Hutter Beatrice",
    "wof:placetype":"venue"
},
  "geometry": {"coordinates":[9.5392332077,47.3778457642],"type":"Point"}
}