{
  "type": "Feature",
  "properties": {
    "iso:country":"CH",
    "sg:address":"S\u00fcdegg",
    "sg:city":"Visp",
    "sg:orig_category":"Grosshandel mit lebenden Tieren",
    "sg:phone":"+41 41 610 41 18",
    "sg:postcode":"3930",
    "sg:province":"Valais",
    "wof:name":"Anton Zelger Viehhandel",
    "wof:placetype":"venue"
},
  "geometry": {"coordinates":[8.3849983215,46.9632797241],"type":"Point"}
}