{
  "type": "Feature",
  "properties": {
    "iso:country":"CH",
    "sg:address":"Bergli 11",
    "sg:city":"Knonau",
    "sg:orig_category":"Finanzierungsinstitutionen",
    "sg:phone":"+41 17670881",
    "sg:postcode":"8934",
    "sg:province":"Z\u00fcrich",
    "wof:name":"Nigg Rainer W. Allfinanzberatung",
    "wof:placetype":"venue"
},
  "geometry": {"coordinates":[8.4571247101,47.2251319885],"type":"Point"}
}