{
  "type": "Feature",
  "properties": {
    "iso:country":"CH",
    "sg:address":"Fuchshofstrasse 6",
    "sg:city":"H\u00fcntwangen",
    "sg:orig_category":"Sportvereine Sch\u00fctzen Pistolen-& Gewehr",
    "sg:phone":"+41 18692165",
    "sg:postcode":"8194",
    "sg:province":"Z\u00fcrich",
    "wof:name":"Pistolenclub B\u00fclach",
    "wof:placetype":"venue"
},
  "geometry": {"coordinates":[8.491771698,47.5975189209],"type":"Point"}
}