{
  "type": "Feature",
  "properties": {
    "iso:country":"CH",
    "sg:address":"Aachen 9402 M\u00f6rschwil. Postfach",
    "sg:city":"M\u00f6rschwil",
    "sg:classifiers":[
        {
            "category":"Professional",
            "subcategory":"Employment Agencies",
            "type":"Services"
        }
    ],
    "sg:postcode":"9402",
    "sg:province":"St. Gallen",
    "sg:tags":[
        "personal",
        "u",
        "stellenvermittlung"
    ],
    "wof:name":"Maschinenring Bodensee Gmbh Arbeitskr\u00e4fte U. Lohnarbeiter; Vermittlung. Landwirtschaftliche Produkte U. Baumaterial; Handel",
    "wof:placetype":"venue"
},
  "geometry": {"coordinates":[9.4302978516,47.4812049866],"type":"Point"}
}