{
  "type": "Feature",
  "properties": {
    "addr:full":"Schachenstrasse 9 W\u00f6schnau Solothurn 5012",
    "addr:housenumber":"9",
    "addr:postcode":"5012",
    "addr:street":"Schachenstrasse;Solothurn",
    "iso:country":"CH",
    "sg:address":"Schachenstrasse 9",
    "sg:city":"W\u00f6schnau",
    "sg:orig_category":"Assembling, Disassembling",
    "sg:phone":"+41 62 849 75 50",
    "sg:postcode":"5012",
    "sg:province":"Solothurn",
    "wof:name":"Peter R\u00f6thlisberger Ag",
    "wof:placetype":"venue"
},
  "geometry": {"coordinates":[8.022865,47.386299],"type":"Point"}
}