{
  "type": "Feature",
  "properties": {
    "iso:country":"CH",
    "sg:address":"Drosselweg 5",
    "sg:city":"D\u00fcdingen",
    "sg:orig_category":"Wirtschaftspr\u00fcfung, Steuerberatung U Treuhand",
    "sg:phone":"+41 19912330",
    "sg:postcode":"3186",
    "sg:province":"Fribourg",
    "wof:name":"Kessler Treuhand",
    "wof:placetype":"venue"
},
  "geometry": {"coordinates":[8.5925073624,47.3221817017],"type":"Point"}
}