{
  "type": "Feature",
  "properties": {
    "iso:country":"CH",
    "sg:address":"Route De La-capite 151a",
    "sg:city":"V\u00e9senaz",
    "sg:orig_category":"Kunsthandel",
    "sg:phone":"+41 22 752 50 02",
    "sg:postcode":"1222",
    "sg:province":"Gen\u00e8ve",
    "wof:name":"Dani\u00e8le Geisendorf Galerie La Collection",
    "wof:placetype":"venue"
},
  "geometry": {"coordinates":[6.2049088478,46.2359886169],"type":"Point"}
}