{
  "type": "Feature",
  "properties": {
    "iso:country":"CH",
    "sg:address":"Steinb\u00fcelstrasse 9",
    "sg:city":"Dinhard",
    "sg:orig_category":"Herstellung von sonstigen Maschinen f\u00fcr bestimmte Verwendung",
    "sg:phone":"+41 52 305 20 60",
    "sg:postcode":"8474",
    "sg:province":"Z\u00fcrich",
    "wof:name":"Bruni Ag Grafische Maschinen",
    "wof:placetype":"venue"
},
  "geometry": {"coordinates":[8.7491827011,47.5546875],"type":"Point"}
}