{
  "type": "Feature",
  "properties": {
    "iso:country":"CH",
    "sg:address":"Fischerstrasse 5",
    "sg:city":"Schaffhausen",
    "sg:orig_category":"Innenausbau",
    "sg:phone":"+41 62 216 07 20",
    "sg:postcode":"8200",
    "sg:province":"Schaffhausen",
    "wof:name":"Beracon Ag",
    "wof:placetype":"venue"
},
  "geometry": {"coordinates":[7.8542900085,47.3250198364],"type":"Point"}
}