{
  "type": "Feature",
  "properties": {
    "addr:full":"Dorfstrasse 50 Wila Z\u00fcrich 8492",
    "addr:housenumber":"50",
    "addr:postcode":"8492",
    "addr:street":"Dorfstrasse",
    "iso:country":"CH",
    "sg:address":"Dorfstrasse 50",
    "sg:city":"Wila",
    "sg:orig_category":"Anticorrosives",
    "sg:phone":"+41 52 385 14 15",
    "sg:postcode":"8492",
    "sg:province":"Z\u00fcrich",
    "wof:name":"Gebr. Fahrni Oberfl\u00e4chentechnik Gmbh",
    "wof:placetype":"venue"
},
  "geometry": {"coordinates":[8.846028,47.419601],"type":"Point"}
}