{
  "type": "Feature",
  "properties": {
    "iso:country":"CH",
    "sg:address":"Salisstrasse 23 7000 Chur. Postfach",
    "sg:city":"Haldenstein",
    "sg:orig_category":"Herstellung von Metallkonstruktionen",
    "sg:postcode":"7023",
    "sg:province":"Graubunden",
    "wof:name":"Tobler Paul Ag",
    "wof:placetype":"venue"
},
  "geometry": {"coordinates":[9.5345077515,46.8550071716],"type":"Point"}
}