{
  "type": "Feature",
  "properties": {
    "iso:country":"CH",
    "sg:address":"Mitteldorfstrasse 272",
    "sg:city":"Oeschgen",
    "sg:orig_category":"Glaserei",
    "sg:phone":"+41 62 871 47 03",
    "sg:postcode":"5072",
    "sg:province":"Aargau",
    "wof:name":"Stefan Keiser Glaserei",
    "wof:placetype":"venue"
},
  "geometry": {"coordinates":[8.0192165375,47.5179367065],"type":"Point"}
}