{
  "type": "Feature",
  "properties": {
    "iso:country":"CH",
    "sg:address":"Br\u00fchlstrasse 31",
    "sg:city":"Erlinsbach",
    "sg:orig_category":"Fahrschulen, Flugschulen",
    "sg:phone":"+41 79 204 80 08",
    "sg:postcode":"5018",
    "sg:province":"Solothurn",
    "wof:name":"Dieter Suter Autofahrschule",
    "wof:placetype":"venue"
},
  "geometry": {"coordinates":[8.012134552,47.4027099609],"type":"Point"}
}