{
  "type": "Feature",
  "properties": {
    "addr:full":"Luzernstr. 5 Aeschi Solothurn 4556",
    "addr:housenumber":"5",
    "addr:postcode":"4556",
    "addr:street":"Luzernstr.;Aeschi Solothurn",
    "iso:country":"CH",
    "sg:address":"Luzernstr. 5",
    "sg:city":"Aeschi",
    "sg:classifiers":[
        {
            "category":"Banks & Credit Unions",
            "subcategory":"Bank",
            "type":"Services"
        }
    ],
    "sg:phone":"+41 62 961 13 84",
    "sg:postcode":"4556",
    "sg:province":"Solothurn",
    "wof:name":"Raiffeisenbank",
    "wof:placetype":"venue"
},
  "geometry": {"coordinates":[7.659867,47.182007],"type":"Point"}
}