{
  "type": "Feature",
  "properties": {
    "addr:full":"R\u00fctistrasse 8 Z\u00fcberwangen St. Gallen 9523",
    "addr:housenumber":"8;st.",
    "addr:postcode":"9523",
    "addr:street":"Ruetistrasse",
    "iso:country":"CH",
    "sg:address":"R\u00fctistrasse 8",
    "sg:city":"Z\u00fcberwangen",
    "sg:orig_category":"Architekturb\u00fcros",
    "sg:phone":"+41 71 944 13 24",
    "sg:postcode":"9523",
    "sg:province":"St. Gallen",
    "wof:name":"Locher Walter Bau- U. Architekturb\u00fcro",
    "wof:placetype":"venue"
},
  "geometry": {"coordinates":[9.083077,47.468552],"type":"Point"}
}