{
  "type": "Feature",
  "properties": {
    "iso:country":"CH",
    "sg:address":"Rue De Montbrillant 76",
    "sg:city":"Gen\u00e8ve",
    "sg:orig_category":"Kinderkrippen U horte",
    "sg:phone":"+41 22 733 07 48",
    "sg:postcode":"1202",
    "sg:province":"Gen\u00e8ve",
    "wof:name":"Cr\u00e8che Montbrillant",
    "wof:placetype":"venue"
},
  "geometry": {"coordinates":[6.1414132118,46.2194137573],"type":"Point"}
}