{
  "type": "Feature",
  "properties": {
    "iso:country":"CH",
    "sg:address":"Seestrasse 42",
    "sg:city":"R\u00fcschlikon",
    "sg:orig_category":"Instandhaltung U Reparatur von Automobilen",
    "sg:phone":"+41 17241022",
    "sg:postcode":"8803",
    "sg:province":"Z\u00fcrich",
    "wof:name":"Garage K\u00fcry Gmbh",
    "wof:placetype":"venue"
},
  "geometry": {"coordinates":[8.5567893982,47.3105239868],"type":"Point"}
}