{
  "type": "Feature",
  "properties": {
    "iso:country":"CH",
    "sg:address":"Rue De La Place-d'armes 6",
    "sg:city":"Fleurier",
    "sg:classifiers":[
        {
            "category":"Restaurant",
            "type":"Food & Drink"
        }
    ],
    "sg:phone":"+41 32 861 10 36",
    "sg:postcode":"2114",
    "sg:province":"Neuch\u00e2tel",
    "wof:name":"Caf\u00e9 De La Place D'armes",
    "wof:placetype":"venue"
},
  "geometry": {"coordinates":[6.5785961151,46.902633667],"type":"Point"}
}