{
  "type": "Feature",
  "properties": {
    "addr:full":"Av. Ritz 10. 1950 Sion. Postfach Sitten Valais 1950",
    "addr:housenumber":"10",
    "addr:postcode":"1950;1950",
    "addr:street":"Av. Ritz",
    "iso:country":"CH",
    "sg:address":"Av. Ritz 10. 1950 Sion. Postfach",
    "sg:city":"Sitten",
    "sg:orig_category":"Dauerkulturbau",
    "sg:phone":"+41 27 322 11 59",
    "sg:postcode":"1950",
    "sg:province":"Valais",
    "wof:name":"Pitteloud Marius & Fils.",
    "wof:placetype":"venue"
},
  "geometry": {"coordinates":[7.35852,46.23513],"type":"Point"}
}