{
  "type": "Feature",
  "properties": {
    "iso:country":"CH",
    "sg:address":"Place De Rome",
    "sg:city":"Martigny",
    "sg:orig_category":"Fachdetailhandel in Verkaufsr\u00e4umen",
    "sg:postcode":"1920",
    "sg:province":"Valais",
    "wof:name":"Liautaud Didier",
    "wof:placetype":"venue"
},
  "geometry": {"coordinates":[6.9876022339,46.2100830078],"type":"Point"}
}