{
  "type": "Feature",
  "properties": {
    "iso:country":"CH",
    "sg:address":"M\u00fchlebachstrasse 27",
    "sg:city":"Thalwil",
    "sg:classifiers":[
        {
            "category":"Professional",
            "subcategory":"Advertising",
            "type":"Services"
        }
    ],
    "sg:phone":"+41 17225311",
    "sg:postcode":"8800",
    "sg:province":"Z\u00fcrich",
    "sg:tags":[
        "agency"
    ],
    "wof:name":"Jf Werbung Gmbh",
    "wof:placetype":"venue"
},
  "geometry": {"coordinates":[8.567155,47.293446],"type":"Point"}
}