{
  "type": "Feature",
  "properties": {
    "iso:country":"CH",
    "sg:address":"Moulins Rue Des 51",
    "sg:city":"Neuch\u00e2tel",
    "sg:orig_category":"Grosshandel mit pharmazeutischen Erzeugnissen, medizinischen U orthop\u00e4dischen Artikeln",
    "sg:phone":"+41 32 385 18 66",
    "sg:postcode":"2000",
    "sg:province":"Neuch\u00e2tel",
    "wof:name":"Ultra Dental, K. Sch\u00f6ler",
    "wof:placetype":"venue"
},
  "geometry": {"coordinates":[7.31564188,47.0981178284],"type":"Point"}
}