{
  "type": "Feature",
  "properties": {
    "iso:country":"CH",
    "sg:address":"Carouge Rue De 68 1205 Gen\u00e8ve. Postfach",
    "sg:city":"Gen\u00e8ve",
    "sg:orig_category":"RESTAURANTS: TEA-ROOMS",
    "sg:postcode":"1201",
    "sg:province":"Gen\u00e8ve",
    "wof:name":"G. Mazza-stenz",
    "wof:placetype":"venue"
},
  "geometry": {"coordinates":[6.143725872,46.19298172],"type":"Point"}
}