{
  "type": "Feature",
  "properties": {
    "iso:country":"CH",
    "sg:address":"Route Des Dents-du-midi 31",
    "sg:city":"Collombey",
    "sg:orig_category":"Unclassifiable Establishments",
    "sg:phone":"+41 81 833 10 36",
    "sg:postcode":"1868",
    "sg:province":"Valais",
    "wof:name":"Chantarella Betriebsgesellschaft Mbh",
    "wof:placetype":"venue"
},
  "geometry": {"coordinates":[9.8283987045,46.4995422363],"type":"Point"}
}