{
  "type": "Feature",
  "properties": {
    "iso:country":"CH",
    "sg:address":"Badenerstrasse 63",
    "sg:city":"Dietikon",
    "sg:orig_category":"Sonstiger Grosshandel",
    "sg:phone":"+41 14326140",
    "sg:postcode":"8953",
    "sg:province":"Z\u00fcrich",
    "wof:name":"Export & Import Mijatovic",
    "wof:placetype":"venue"
},
  "geometry": {"coordinates":[8.393409729,47.4077224731],"type":"Point"}
}