{
  "type": "Feature",
  "properties": {
    "iso:country":"CH",
    "sg:address":"Landbergstrasse 41",
    "sg:city":"Flawil",
    "sg:orig_category":"Vorschulen, Kinderg\u00e4rten",
    "sg:phone":"+41 19305688",
    "sg:postcode":"9230",
    "sg:province":"St. Gallen",
    "wof:name":"Kindergarten Feld",
    "wof:placetype":"venue"
},
  "geometry": {"coordinates":[8.8053884506,47.3296585083],"type":"Point"}
}