{
  "type": "Feature",
  "properties": {
    "addr:full":"Hofstrasse 62d Z\u00fcrich Z\u00fcrich 8032",
    "addr:housenumber":"62d",
    "addr:postcode":"8032",
    "addr:street":"Hofstrasse",
    "iso:country":"CH",
    "sg:address":"Hofstrasse 62d",
    "sg:city":"Z\u00fcrich",
    "sg:orig_category":"Arztpraxen",
    "sg:phone":"+41 12625866",
    "sg:postcode":"8032",
    "sg:province":"Z\u00fcrich",
    "wof:name":"Dr.med.anne Glantz Spezial\u00e4rztin Fmh",
    "wof:placetype":"venue"
},
  "geometry": {"coordinates":[8.561845,47.372425],"type":"Point"}
}