{
  "type": "Feature",
  "properties": {
    "iso:country":"CH",
    "sg:address":"3752",
    "sg:city":"Wimmis",
    "sg:orig_category":"Landw. Genossenschaften Viehzucht",
    "sg:postcode":"3752",
    "sg:province":"Bern",
    "wof:name":"Viehzuchtgenossenschaft",
    "wof:placetype":"venue"
},
  "geometry": {"coordinates":[7.6349601746,46.6744842529],"type":"Point"}
}