{
  "type": "Feature",
  "properties": {
    "iso:country":"CH",
    "sg:address":"Badrain 7",
    "sg:city":"Sursee",
    "sg:classifiers":[
        {
            "category":"Banks & Credit Unions",
            "subcategory":"Bank",
            "type":"Services"
        }
    ],
    "sg:phone":"+41 4145215863",
    "sg:postcode":"6210",
    "sg:province":"Luzern",
    "wof:name":"Rentenanstalt Swiss Life",
    "wof:placetype":"venue"
},
  "geometry": {"coordinates":[8.107833,47.169945],"type":"Point"}
}