{
  "type": "Feature",
  "properties": {
    "iso:country":"CH",
    "sg:address":"Sch\u00fctzenstrasse 31",
    "sg:city":"Winterthur",
    "sg:classifiers":[
        {
            "category":"Professional",
            "subcategory":"Employment Agencies",
            "type":"Services"
        }
    ],
    "sg:phone":"+41 52 223 12 12",
    "sg:postcode":"8400",
    "sg:province":"Z\u00fcrich",
    "sg:tags":[
        "personal",
        "u",
        "stellenvermittlung"
    ],
    "wof:name":"Selecteam Gmbh Personalberatung",
    "wof:placetype":"venue"
},
  "geometry": {"coordinates":[8.7188854218,47.5033302307],"type":"Point"}
}