{
  "type": "Feature",
  "properties": {
    "iso:country":"CH",
    "sg:address":"Kehlhofrain 4 6043 Adligenswil. Postfach",
    "sg:city":"Adligenswil",
    "sg:orig_category":"Fachdetailhandel in Verkaufsr\u00e4umen Sonstige Unterhaltung",
    "sg:phone":"+41 41 372 07 11",
    "sg:postcode":"6043",
    "sg:province":"Luzern",
    "wof:name":"Pierre Magic-studio, Greiner Pierre",
    "wof:placetype":"venue"
},
  "geometry": {"coordinates":[8.3625593185,47.0765457153],"type":"Point"}
}