{
  "type": "Feature",
  "properties": {
    "iso:country":"CH",
    "sg:address":"Bahnhofstrasse 80",
    "sg:city":"Salgesch",
    "sg:classifiers":[
        {
            "category":"Travel",
            "subcategory":"Hotels & Motels",
            "type":"Entertainment"
        }
    ],
    "sg:phone":"+41 27 455 18 38",
    "sg:postcode":"3970",
    "sg:province":"Valais",
    "sg:tags":[
        "hotels",
        "mit",
        "restaurant"
    ],
    "wof:name":"Hotel & Restaurant Rhone, Markus Constantin",
    "wof:placetype":"venue"
},
  "geometry": {"coordinates":[7.5783948898,46.3094787598],"type":"Point"}
}