{
  "type": "Feature",
  "properties": {
    "iso:country":"CH",
    "sg:address":"Storchenwiese 11",
    "sg:city":"B\u00fclach",
    "sg:orig_category":"Maschinen-Fabrikation",
    "sg:phone":"+41 18605145",
    "sg:postcode":"8180",
    "sg:province":"Z\u00fcrich",
    "wof:name":"Ingenieurb\u00fcro Sp\u00fchler",
    "wof:placetype":"venue"
},
  "geometry": {"coordinates":[8.5311231613,47.5149765015],"type":"Point"}
}