{
  "type": "Feature",
  "properties": {
    "addr:full":"Ch. Du Champ-des-filles 31 Plan-les-ouates Gen\u00e8ve 1228",
    "addr:housenumber":"31",
    "addr:postcode":"1228",
    "addr:street":"Ch. Du Champ-Des-Filles",
    "iso:country":"CH",
    "sg:address":"Ch. Du Champ-des-filles 31",
    "sg:city":"Plan-les-ouates",
    "sg:orig_category":"Anticorrosives",
    "sg:phone":"+41 22 794 64 54",
    "sg:postcode":"1228",
    "sg:province":"Gen\u00e8ve",
    "wof:name":"Charrin",
    "wof:placetype":"venue"
},
  "geometry": {"coordinates":[6.106204,46.165627],"type":"Point"}
}