{
  "type": "Feature",
  "properties": {
    "iso:country":"CH",
    "sg:address":"2610",
    "sg:city":"St-imier",
    "sg:orig_category":"Fachdetailhandel in Verkaufsr\u00e4umen",
    "sg:phone":"+41 32 941 42 96",
    "sg:postcode":"2610",
    "sg:province":"Bern",
    "wof:name":"Huguenin Denis Francis.",
    "wof:placetype":"venue"
},
  "geometry": {"coordinates":[6.9958171844,47.1520423889],"type":"Point"}
}