{
  "type": "Feature",
  "properties": {
    "iso:country":"CH",
    "sg:address":"Route Cantonale",
    "sg:city":"No\u00ebs",
    "sg:orig_category":"Instandhaltung U Reparatur von Automobilen",
    "sg:phone":"+41 79 449 23 81",
    "sg:postcode":"3976",
    "sg:province":"Valais",
    "wof:name":"Bayard M. Et B. Garage Du Sud No\u00ebs/sierre.",
    "wof:placetype":"venue"
},
  "geometry": {"coordinates":[7.5055451393,46.2809448242],"type":"Point"}
}