{
  "type": "Feature",
  "properties": {
    "iso:country":"CH",
    "sg:address":"Stationsstrasse 66 8424 Embrach. Postfach 355",
    "sg:city":"Embrach",
    "sg:orig_category":"Non-Classified Establishments",
    "sg:phone":"+41 18663030",
    "sg:postcode":"8424",
    "sg:province":"Z\u00fcrich",
    "wof:name":"Diener Ag Precision Machining",
    "wof:placetype":"venue"
},
  "geometry": {"coordinates":[8.5900144577,47.5153808594],"type":"Point"}
}