{
  "type": "Feature",
  "properties": {
    "iso:country":"CH",
    "sg:address":"Unterm\u00fcli 9 6300 Zug. Postfach 2729",
    "sg:city":"Zug",
    "sg:orig_category":"Grosshandel mit medizinischen U orthop\u00e4dischen Artikeln",
    "sg:phone":"+41 41 711 31 42",
    "sg:postcode":"6302",
    "sg:province":"Zug",
    "wof:name":"Milford Sa Op\u00e9rations Commerciales Ou Financi\u00e8res Etc",
    "wof:placetype":"venue"
},
  "geometry": {"coordinates":[8.5177631378,47.1804656982],"type":"Point"}
}