{
  "type": "Feature",
  "properties": {
    "iso:country":"CH",
    "sg:address":"Aeussere Baselstrasse 326 4125 Riehen. Postfach",
    "sg:city":"Riehen",
    "sg:orig_category":"Sonstiger Grosshandel",
    "sg:postcode":"4125",
    "sg:province":"Basel-Stadt",
    "wof:name":"Impandex Gmbh Waren; Handel, Import, Export",
    "wof:placetype":"venue"
},
  "geometry": {"coordinates":[7.6291499138,47.5731811523],"type":"Point"}
}