{
  "type": "Feature",
  "properties": {
    "iso:country":"CH",
    "sg:address":"Petersgraben 15",
    "sg:city":"Basel",
    "sg:orig_category":"Detailhandel mit Fahrr\u00e4dern Fachdetailhandel in Verkaufsr\u00e4umen",
    "sg:phone":"+41 61 261 85 25",
    "sg:postcode":"4051",
    "sg:province":"Basel-Stadt",
    "wof:name":"Bikeshop Basel Rohr + Co",
    "wof:placetype":"venue"
},
  "geometry": {"coordinates":[7.5851340294,47.560344696],"type":"Point"}
}