{
  "type": "Feature",
  "properties": {
    "addr:full":"Br\u00fcelstrasse 1 Mettmenstetten Z\u00fcrich 8932",
    "addr:housenumber":"1",
    "addr:postcode":"8932",
    "addr:street":"Brueelstrasse",
    "iso:country":"CH",
    "sg:address":"Br\u00fcelstrasse 1",
    "sg:city":"Mettmenstetten",
    "sg:orig_category":"Arztpraxen",
    "sg:phone":"+41 17670144",
    "sg:postcode":"8932",
    "sg:province":"Z\u00fcrich",
    "wof:name":"Dr.med.j\u00fcrg B\u00e4nninger Arzt F.allgemeine Medizin Fmh",
    "wof:placetype":"venue"
},
  "geometry": {"coordinates":[8.46818,47.243607],"type":"Point"}
}