{
  "type": "Feature",
  "properties": {
    "iso:country":"CH",
    "sg:address":"Lehngasse 69",
    "sg:city":"Wilderswil",
    "sg:orig_category":"Sanit\u00e4r, Heizungs U L\u00fcftungsinstallation Sanit\u00e4rinstallation",
    "sg:phone":"+41 12610046",
    "sg:postcode":"3812",
    "sg:province":"Bern",
    "wof:name":"Goldenbohm & Co",
    "wof:placetype":"venue"
},
  "geometry": {"coordinates":[8.5799007416,47.3171730042],"type":"Point"}
}