{
  "type": "Feature",
  "properties": {
    "iso:country":"CH",
    "sg:address":"Zentrum Meierwis 8606 Greifensee. Postfach 65",
    "sg:city":"Greifensee",
    "sg:orig_category":"Detailhandel mit Brillen U anderen Sehhilfen Fachdetailhandel in Verkaufsr\u00e4umen",
    "sg:phone":"+41 61 461 74 40",
    "sg:postcode":"8606",
    "sg:province":"Z\u00fcrich",
    "wof:name":"Opticus Ramstein",
    "wof:placetype":"venue"
},
  "geometry": {"coordinates":[7.64704,47.526279],"type":"Point"}
}