{
  "type": "Feature",
  "properties": {
    "iso:country":"CH",
    "sg:address":"Bernstrasse 79",
    "sg:city":"Rothrist",
    "sg:classifiers":[
        {
            "category":"Social Services",
            "subcategory":"Child Care",
            "type":"Services"
        }
    ],
    "sg:phone":"+41 62 794 28 26",
    "sg:postcode":"4852",
    "sg:province":"Aargau",
    "sg:tags":[
        "consulting",
        "management"
    ],
    "wof:name":"Co-assist",
    "wof:placetype":"venue"
},
  "geometry": {"coordinates":[7.8951220512,47.3045806885],"type":"Point"}
}