{
  "type": "Feature",
  "properties": {
    "iso:country":"CH",
    "sg:address":"Heuigstrasse 161",
    "sg:city":"B\u00f6zen",
    "sg:orig_category":"Tierarztpraxis",
    "sg:phone":"+41 62 876 12 13",
    "sg:postcode":"5076",
    "sg:province":"Aargau",
    "wof:name":"Dr. Med. Vet. Urs Frei Tierarzt",
    "wof:placetype":"venue"
},
  "geometry": {"coordinates":[8.0859775543,47.4976654053],"type":"Point"}
}