{
  "type": "Feature",
  "properties": {
    "addr:full":"M\u00e4rtplatz 19 Effretikon Z\u00fcrich 8307",
    "addr:housenumber":"19",
    "addr:postcode":"8307",
    "addr:street":"Maertplatz",
    "iso:country":"CH",
    "sg:address":"M\u00e4rtplatz 19",
    "sg:city":"Effretikon",
    "sg:classifiers":[
        {
            "category":"Social Services",
            "subcategory":"Retirement Home",
            "type":"Services"
        }
    ],
    "sg:phone":"+41 52 355 19 90",
    "sg:postcode":"8307",
    "sg:province":"Z\u00fcrich",
    "sg:tags":[
        "pflegeheime",
        "u",
        "alters"
    ],
    "wof:name":"Altersheim Bruggwiesen",
    "wof:placetype":"venue"
},
  "geometry": {"coordinates":[8.685609,47.427753],"type":"Point"}
}