{
  "type": "Feature",
  "properties": {
    "iso:country":"CH",
    "sg:address":"M\u00f6\u00f6slimatten 13",
    "sg:city":"Ettiswil",
    "sg:orig_category":"Instandhaltung U Reparatur von Automobilen R\u00fcckgewinnung U Vorbereitung f\u00fcr die Wiederverwertung Rec",
    "sg:phone":"+41 41 980 27 47",
    "sg:postcode":"6218",
    "sg:province":"Luzern",
    "wof:name":"Walter Brun Garage & Autoverwertung",
    "wof:placetype":"venue"
},
  "geometry": {"coordinates":[8.0225019455,47.1460876465],"type":"Point"}
}