{
  "type": "Feature",
  "properties": {
    "iso:country":"CH",
    "sg:address":"Welschlandstrasse 29b",
    "sg:city":"B\u00fctzberg",
    "sg:orig_category":"Zimmerei, Ingenieurholzbau",
    "sg:phone":"+41 33 822 07 47",
    "sg:postcode":"4922",
    "sg:province":"Bern",
    "wof:name":"Von Allmen Ag Holzbau & Bedachungen",
    "wof:placetype":"venue"
},
  "geometry": {"coordinates":[7.888710022,46.6998710632],"type":"Point"}
}