{
  "type": "Feature",
  "properties": {
    "addr:full":"Schleifeweg 1 Ermensee Luzern 6294",
    "addr:housenumber":"1",
    "addr:postcode":"6294",
    "addr:street":"Schleifeweg",
    "iso:country":"CH",
    "sg:address":"Schleifeweg 1",
    "sg:city":"Ermensee",
    "sg:orig_category":"Detailhandel mit Brot, Back U S\u00fcsswaren Detailhandel mit Waren verschiedener Art, Hauptrichtung Nahr",
    "sg:phone":"+41 52 365 22 84",
    "sg:postcode":"6294",
    "sg:province":"Luzern",
    "wof:name":"Josef Ruckstuhl",
    "wof:placetype":"venue"
},
  "geometry": {"coordinates":[8.896527,47.478111],"type":"Point"}
}