{
  "type": "Feature",
  "properties": {
    "addr:full":"Caneggio Caneggio Ticino 6837",
    "addr:postcode":"6837",
    "iso:country":"CH",
    "sg:address":"Caneggio",
    "sg:city":"Caneggio",
    "sg:classifiers":[
        {
            "category":"Banks & Credit Unions",
            "subcategory":"Bank",
            "type":"Services"
        }
    ],
    "sg:phone":"+41 91 684 15 26",
    "sg:postcode":"6837",
    "sg:province":"Ticino",
    "wof:name":"Raiffeisen Di Caneggio",
    "wof:placetype":"venue"
},
  "geometry": {"coordinates":[9.031005,45.872269],"type":"Point"}
}