{
  "type": "Feature",
  "properties": {
    "iso:country":"CH",
    "sg:address":"Bahnhofstrasse 2",
    "sg:city":"Widnau",
    "sg:orig_category":"Detailhandel mit Damenbekleidung Detailhandel mit Herrenbekleidung",
    "sg:phone":"+41 71 722 00 22",
    "sg:postcode":"9443",
    "sg:province":"St. Gallen",
    "wof:name":"Weber Bekleidung Ag",
    "wof:placetype":"venue"
},
  "geometry": {"coordinates":[9.6289691925,47.4077415466],"type":"Point"}
}