{
  "type": "Feature",
  "properties": {
    "iso:country":"CH",
    "sg:address":"Rue De La Tournelle 19",
    "sg:city":"Orbe",
    "sg:orig_category":"Allgemeiner Hoch U Tiefbau",
    "sg:postcode":"1350",
    "sg:province":"Vaud",
    "wof:name":"Ferrario Natale",
    "wof:placetype":"venue"
},
  "geometry": {"coordinates":[8.947175,45.99044],"type":"Point"}
}