{
  "type": "Feature",
  "properties": {
    "iso:country":"CH",
    "sg:address":"3942",
    "sg:city":"Raron",
    "sg:orig_category":"Organisationen der Wohlfahrtspflege",
    "sg:phone":"+41 27 934 25 56",
    "sg:postcode":"3942",
    "sg:province":"Valais",
    "wof:name":"Pro Juventute Frau Margrit Brandschen",
    "wof:placetype":"venue"
},
  "geometry": {"coordinates":[7.8000950813,46.3097190857],"type":"Point"}
}