{
  "type": "Feature",
  "properties": {
    "iso:country":"CH",
    "sg:address":"Klosterberg 15",
    "sg:city":"Basel",
    "sg:orig_category":"Detailhandel mit Antiquit\u00e4ten",
    "sg:phone":"+41 61 271 70 33",
    "sg:postcode":"4051",
    "sg:province":"Basel-Stadt",
    "wof:name":"Lydia Th\u00fcring Antiquit\u00e4ten",
    "wof:placetype":"venue"
},
  "geometry": {"coordinates":[7.590311,47.551922],"type":"Point"}
}