{
  "type": "Feature",
  "properties": {
    "iso:country":"CH",
    "sg:address":"Hans Huber-strasse 41",
    "sg:city":"Solothurn",
    "sg:orig_category":"Physiotherapie",
    "sg:phone":"+41 32 622 42 14",
    "sg:postcode":"4500",
    "sg:province":"Solothurn",
    "wof:name":"Christine Fossa Physiotherapie",
    "wof:placetype":"venue"
},
  "geometry": {"coordinates":[7.5283122063,47.2009010315],"type":"Point"}
}