{
  "type": "Feature",
  "properties": {
    "iso:country":"CH",
    "sg:address":"Neunbrunnenstrasse 55 8050 Z\u00fcrich. Postfach 145",
    "sg:city":"Z\u00fcrich",
    "sg:orig_category":"Herstellung von Holzstoff, Papier, Karton U Pappe Herstellung von sonstigen Waren aus Papier, Karton",
    "sg:phone":"+41 13086688",
    "sg:postcode":"8057",
    "sg:province":"Z\u00fcrich",
    "wof:name":"Selfix Ag Etiketten, Selbstklebe-etiketten Usw; Herst., Handel",
    "wof:placetype":"venue"
},
  "geometry": {"coordinates":[8.5385875702,47.4168243408],"type":"Point"}
}