{
  "type": "Feature",
  "properties": {
    "iso:country":"CH",
    "sg:address":"Hallerstrasse 10",
    "sg:city":"Bern",
    "sg:orig_category":"Non-Classified Establishments",
    "sg:postcode":"3012",
    "sg:province":"Bern",
    "wof:name":"Mark Oertli New Copy Store",
    "wof:placetype":"venue"
},
  "geometry": {"coordinates":[9.3962278366,47.4314193726],"type":"Point"}
}