{
  "type": "Feature",
  "properties": {
    "iso:country":"CH",
    "sg:address":"Oerlikonerstrasse 43",
    "sg:city":"Z\u00fcrich",
    "sg:classifiers":[
        {
            "category":"Restaurant",
            "type":"Food & Drink"
        }
    ],
    "sg:phone":"+41 13113064",
    "sg:postcode":"8057",
    "sg:province":"Z\u00fcrich",
    "wof:name":"Restaurant La Fattoria",
    "wof:placetype":"venue"
},
  "geometry": {"coordinates":[8.5445537567,47.4024200439],"type":"Point"}
}