{
  "type": "Feature",
  "properties": {
    "iso:country":"CH",
    "sg:address":"Unterer Rheinweg 90 4057 Basel. Postfach",
    "sg:city":"Basel",
    "sg:orig_category":"Unternehmensberatung",
    "sg:phone":"+41 61 683 47 00",
    "sg:postcode":"4057",
    "sg:province":"Basel-Stadt",
    "wof:name":"Abiba Consulting Ag Betriebs, Management, Organisations- U. Unternehmensberatung Usw",
    "wof:placetype":"venue"
},
  "geometry": {"coordinates":[7.5870041847,47.5665473938],"type":"Point"}
}