{
  "type": "Feature",
  "properties": {
    "iso:country":"CH",
    "sg:address":"Uraniastrasse 26",
    "sg:city":"Z\u00fcrich",
    "sg:orig_category":"Pensionskassen",
    "sg:postcode":"8001",
    "sg:province":"Z\u00fcrich",
    "wof:name":"Pensionskasse Kentaur",
    "wof:placetype":"venue"
},
  "geometry": {"coordinates":[7.6784548759,47.0036315918],"type":"Point"}
}