{
  "type": "Feature",
  "properties": {
    "iso:country":"CH",
    "sg:address":"L\u00f6wenstrasse 25",
    "sg:city":"Z\u00fcrich",
    "sg:orig_category":"Reiseb\u00fcros",
    "sg:phone":"+41 34 437 14 87",
    "sg:postcode":"8001",
    "sg:province":"Z\u00fcrich",
    "wof:name":"Emmental Tours Ag",
    "wof:placetype":"venue"
},
  "geometry": {"coordinates":[7.7977042198,47.0437088013],"type":"Point"}
}