{
  "type": "Feature",
  "properties": {
    "iso:country":"CH",
    "sg:address":"Cours Des Bastions 4",
    "sg:city":"Gen\u00e8ve",
    "sg:orig_category":"Rechtsberatung Vermittlung von Immobilien",
    "sg:phone":"+41 41 226 16 16",
    "sg:postcode":"1205",
    "sg:province":"Gen\u00e8ve",
    "wof:name":"Contrust Finance Ag Beratung In Den Bereichen Recht, Steuern, Wirtschaft Usw",
    "wof:placetype":"venue"
},
  "geometry": {"coordinates":[8.3037347794,47.0435409546],"type":"Point"}
}