{
  "type": "Feature",
  "properties": {
    "addr:full":"Schweighofstrasse 405a 8055 Z\u00fcrich. Postfach Z\u00fcrich Z\u00fcrich 8055",
    "addr:housenumber":"405a",
    "addr:postcode":"8055 zuerich. postfach;8055",
    "addr:street":"Schweighofstrasse",
    "iso:country":"CH",
    "sg:address":"Schweighofstrasse 405a 8055 Z\u00fcrich. Postfach",
    "sg:city":"Z\u00fcrich",
    "sg:orig_category":"Softwareentwicklung U beratung",
    "sg:phone":"+41 12427777",
    "sg:postcode":"8055",
    "sg:province":"Z\u00fcrich",
    "wof:name":"Io Solutions Ag",
    "wof:placetype":"venue"
},
  "geometry": {"coordinates":[8.685983,47.271645],"type":"Point"}
}