{
  "type": "Feature",
  "properties": {
    "iso:country":"CH",
    "sg:address":"Via Borgo 11 6612 Ascona. Postfach Casa Postale",
    "sg:city":"Ascona",
    "sg:orig_category":"Fachdetailhandel in Verkaufsr\u00e4umen",
    "sg:postcode":"6612",
    "sg:province":"Ticino",
    "wof:name":"Ryf Bernhard Succursale Di Ascona Apparecchi Ottici E Microscopi",
    "wof:placetype":"venue"
},
  "geometry": {"coordinates":[8.7681274414,46.156124115],"type":"Point"}
}