{
  "type": "Feature",
  "properties": {
    "addr:full":"7180 Disentis/must\u00e9r Graubunden 7180",
    "addr:postcode":"7180;7180",
    "iso:country":"CH",
    "sg:address":"7180",
    "sg:city":"Disentis/must\u00e9r",
    "sg:classifiers":[
        {
            "category":"Education",
            "subcategory":"Library",
            "type":"Public Place"
        }
    ],
    "sg:postcode":"7180",
    "sg:province":"Graubunden",
    "sg:tags":[
        "u",
        "bibliotheken",
        "archive"
    ],
    "wof:name":"Stiftsbibliothek",
    "wof:placetype":"venue"
},
  "geometry": {"coordinates":[8.853129,46.704601],"type":"Point"}
}