{
  "type": "Feature",
  "properties": {
    "iso:country":"CH",
    "sg:address":"Zil",
    "sg:city":"Sennwald",
    "sg:classifiers":[
        {
            "category":"Professional",
            "subcategory":"Employment Agencies",
            "type":"Services"
        }
    ],
    "sg:postcode":"9466",
    "sg:province":"St. Gallen",
    "sg:tags":[
        "personal",
        "u",
        "stellenvermittlung"
    ],
    "wof:name":"Maach Frontline All-roundservice",
    "wof:placetype":"venue"
},
  "geometry": {"coordinates":[9.5059843063,47.2649078369],"type":"Point"}
}