{
  "type": "Feature",
  "properties": {
    "iso:country":"CH",
    "sg:address":"Weinbergweg 2",
    "sg:city":"Ennetbaden",
    "sg:orig_category":"Herstellung von Maschinen f\u00fcr die Nahrungsmittel, Getr\u00e4nkeherstellung U die Tabakverarbeitung Herste",
    "sg:phone":"+41 56 222 28 66",
    "sg:postcode":"5408",
    "sg:province":"Aargau",
    "wof:name":"E.a. Weber Ag, M\u00fchlen Und Maschinenbau",
    "wof:placetype":"venue"
},
  "geometry": {"coordinates":[8.3165445328,47.4820823669],"type":"Point"}
}