{
  "type": "Feature",
  "properties": {
    "iso:country":"CH",
    "sg:address":"Thorbergstrasse 3",
    "sg:city":"Krauchthal",
    "sg:orig_category":"Stukkateurgewerbe, Gipserei U Verputzerei",
    "sg:phone":"+41 62 822 45 24",
    "sg:postcode":"3326",
    "sg:province":"Bern",
    "wof:name":"E. B\u00fctikofer",
    "wof:placetype":"venue"
},
  "geometry": {"coordinates":[8.076921463,47.4008750916],"type":"Point"}
}