{
  "type": "Feature",
  "properties": {
    "addr:full":"Schindellegistrasse 67 Pf\u00e4ffikon Schwyz 8808",
    "addr:housenumber":"67",
    "addr:postcode":"8808",
    "addr:street":"Schindellegistrasse;Schwyz",
    "iso:country":"CH",
    "sg:address":"Schindellegistrasse 67",
    "sg:city":"Pf\u00e4ffikon",
    "sg:classifiers":[
        {
            "category":"Professional",
            "subcategory":"Advertising",
            "type":"Services"
        }
    ],
    "sg:phone":"+41 55 410 18 88",
    "sg:postcode":"8808",
    "sg:province":"Schwyz",
    "sg:tags":[
        "construction",
        "site",
        "panel"
    ],
    "wof:name":"Notter Reklame",
    "wof:placetype":"venue"
},
  "geometry": {"coordinates":[8.765299,47.196838],"type":"Point"}
}