{
  "type": "Feature",
  "properties": {
    "iso:country":"CH",
    "sg:address":"Bahnhofstrasse 20",
    "sg:city":"Brunnen",
    "sg:orig_category":"Kinesiologie",
    "sg:phone":"+41 41 820 09 10",
    "sg:postcode":"6440",
    "sg:province":"Schwyz",
    "wof:name":"Brigitta Camenzind Kinesiologie",
    "wof:placetype":"venue"
},
  "geometry": {"coordinates":[8.6063146591,46.9950370789],"type":"Point"}
}