{
  "type": "Feature",
  "properties": {
    "iso:country":"CH",
    "sg:address":"Dorfstrasse 66",
    "sg:city":"Geroldswil",
    "sg:orig_category":"Detailhandel mit Blumen U Pflanzen",
    "sg:phone":"+41 17485556",
    "sg:postcode":"8954",
    "sg:province":"Z\u00fcrich",
    "wof:name":"Kuhnys Bluemeeggli",
    "wof:placetype":"venue"
},
  "geometry": {"coordinates":[8.412637,47.422092],"type":"Point"}
}