{
  "type": "Feature",
  "properties": {
    "iso:country":"CH",
    "sg:address":"Hinterdorfstrasse 5",
    "sg:city":"Wittenwil",
    "sg:orig_category":"G\u00fcterbef\u00f6rderung im Strassenverkehr",
    "sg:phone":"+41 52 365 45 61",
    "sg:postcode":"9547",
    "sg:province":"Thurgau",
    "wof:name":"K\u00e4gi Ag Transporte",
    "wof:placetype":"venue"
},
  "geometry": {"coordinates":[8.9217967987,47.5054321289],"type":"Point"}
}