{
  "type": "Feature",
  "properties": {
    "iso:country":"CH",
    "sg:address":"Rutzenacker",
    "sg:city":"Kaltbrunn",
    "sg:orig_category":"Grosshandel mit Getreide, Saatgut U Futtermitteln",
    "sg:phone":"+41 55 283 13 46",
    "sg:postcode":"8722",
    "sg:province":"St. Gallen",
    "wof:name":"Zahner Josef",
    "wof:placetype":"venue"
},
  "geometry": {"coordinates":[9.03657341,47.211807251],"type":"Point"}
}