{
  "type": "Feature",
  "properties": {
    "addr:full":"General-dufour-strasse 4 Biel/bienne Bern 2502",
    "addr:housenumber":"4",
    "addr:postcode":"2502",
    "addr:street":"General-Dufour-Strasse",
    "iso:country":"CH",
    "sg:address":"General-dufour-strasse 4",
    "sg:city":"Biel/bienne",
    "sg:orig_category":"Detailhandel mit B\u00fcchern Detailhandel mit Ton U Bildtr\u00e4gern",
    "sg:phone":"+41 41 871 11 10",
    "sg:postcode":"2502",
    "sg:province":"Bern",
    "wof:name":"Ex Libris Ag",
    "wof:placetype":"venue"
},
  "geometry": {"coordinates":[8.65083,46.871815],"type":"Point"}
}