{
  "type": "Feature",
  "properties": {
    "iso:country":"CH",
    "sg:address":"Am Herrenbrunnen 4",
    "sg:city":"Balsthal",
    "sg:orig_category":"Sonstige pers\u00f6nliche Dienstleistungen Unternehmensberatung",
    "sg:phone":"+41 62 391 59 20",
    "sg:postcode":"4710",
    "sg:province":"Solothurn",
    "wof:name":"Th Consulting Heutschi Thomas",
    "wof:placetype":"venue"
},
  "geometry": {"coordinates":[7.696641922,47.3205718994],"type":"Point"}
}