{
  "type": "Feature",
  "properties": {
    "addr:full":"Via Al Motto 1 Gordola Ticino 6596",
    "addr:housenumber":"1",
    "addr:postcode":"6596",
    "addr:street":"Via Al Motto",
    "iso:country":"CH",
    "sg:address":"Via Al Motto 1",
    "sg:city":"Gordola",
    "sg:orig_category":"Bestattungswesen",
    "sg:phone":"+41 91 745 10 64",
    "sg:postcode":"6596",
    "sg:province":"Ticino",
    "wof:name":"Bruno Rossi Fu Quirino",
    "wof:placetype":"venue"
},
  "geometry": {"coordinates":[8.864636,46.180527],"type":"Point"}
}