{
  "type": "Feature",
  "properties": {
    "iso:country":"CH",
    "sg:address":"Rosenbergstrasse 87",
    "sg:city":"St.gallen",
    "sg:orig_category":"Sonstige mit der Informatik verbundene T\u00e4tigkeiten",
    "sg:postcode":"9000",
    "sg:province":"St. Gallen",
    "wof:name":"Astonishing Gmbh",
    "wof:placetype":"venue"
},
  "geometry": {"coordinates":[9.3655700684,47.4223251343],"type":"Point"}
}