{
  "type": "Feature",
  "properties": {
    "iso:country":"CH",
    "sg:address":"Liebegg 9",
    "sg:city":"Gr\u00e4nichen",
    "sg:orig_category":"Grosshandel mit Nahrungsmitteln, Getr\u00e4nken U Tabakwaren ohne ausgepr\u00e4gten Schwerpunkt",
    "sg:phone":"+41 62 842 40 55",
    "sg:postcode":"5722",
    "sg:province":"Aargau",
    "wof:name":"Dora Widmer-richner",
    "wof:placetype":"venue"
},
  "geometry": {"coordinates":[8.1211853027,47.3386497498],"type":"Point"}
}