{
  "type": "Feature",
  "properties": {
    "iso:country":"CH",
    "sg:address":"Feldstrasse 6",
    "sg:city":"Horn",
    "sg:orig_category":"Unclassifiable Establishments",
    "sg:postcode":"9326",
    "sg:province":"Thurgau",
    "wof:name":"Josef Popp Bauten/transporte",
    "wof:placetype":"venue"
},
  "geometry": {"coordinates":[9.4612007141,47.4957923889],"type":"Point"}
}