{
  "type": "Feature",
  "properties": {
    "iso:country":"CH",
    "sg:address":"8182",
    "sg:city":"Hochfelden",
    "sg:orig_category":"Primarschulen",
    "sg:phone":"+41 18601665",
    "sg:postcode":"8182",
    "sg:province":"Z\u00fcrich",
    "wof:name":"Primarschule Wisacher",
    "wof:placetype":"venue"
},
  "geometry": {"coordinates":[8.5158004761,47.5234146118],"type":"Point"}
}