{
  "type": "Feature",
  "properties": {
    "iso:country":"CH",
    "sg:address":"Liebensberg",
    "sg:city":"Gachnang",
    "sg:orig_category":"Haltung von Rindern",
    "sg:postcode":"8547",
    "sg:province":"Thurgau",
    "wof:name":"Braunviehzuchtgenossenschaft Bertschikon H.h\u00fcbscher",
    "wof:placetype":"venue"
},
  "geometry": {"coordinates":[8.8380002975,47.5431518555],"type":"Point"}
}