{
  "type": "Feature",
  "properties": {
    "iso:country":"CH",
    "sg:address":"4710 Balsthal. Postfach 11",
    "sg:city":"Balsthal",
    "sg:orig_category":"Interessenvertretungen",
    "sg:postcode":"4710",
    "sg:province":"Solothurn",
    "wof:name":"Von B\u00fcren Ida Und Lydia Stiftung",
    "wof:placetype":"venue"
},
  "geometry": {"coordinates":[9.6374015808,46.9872550964],"type":"Point"}
}