{
  "type": "Feature",
  "properties": {
    "iso:country":"CH",
    "sg:address":"Platz 7",
    "sg:city":"Mels",
    "sg:orig_category":"Drogerien",
    "sg:phone":"+41 81 302 11 57",
    "sg:postcode":"8887",
    "sg:province":"St. Gallen",
    "wof:name":"Kressig Drogerie Ag",
    "wof:placetype":"venue"
},
  "geometry": {"coordinates":[9.5012578964,47.0039138794],"type":"Point"}
}