{
  "type": "Feature",
  "properties": {
    "iso:country":"CH",
    "sg:address":"K\u00f6llikerstrasse 32",
    "sg:city":"Oberentfelden",
    "sg:orig_category":"Detailhandel mit Antiquit\u00e4ten U Gebrauchtwaren in Verkaufsr\u00e4umen Detailhandel mit M\u00f6beln",
    "sg:phone":"+41 62 724 12 40",
    "sg:postcode":"5036",
    "sg:province":"Aargau",
    "wof:name":"Brockenstube Tell-m\u00e4rt",
    "wof:placetype":"venue"
},
  "geometry": {"coordinates":[8.0427312851,47.3531455994],"type":"Point"}
}