{
  "type": "Feature",
  "properties": {
    "iso:country":"CH",
    "sg:address":"1836",
    "sg:city":"Rossini\u00e8re",
    "sg:orig_category":"Sportvereine Sch\u00fctzen",
    "sg:postcode":"1836",
    "wof:name":"St\u00e9 De Tir Armes De Guerre",
    "wof:placetype":"venue"
},
  "geometry": {"coordinates":[6.9295902252,46.3618087769],"type":"Point"}
}