{
  "type": "Feature",
  "properties": {
    "iso:country":"CH",
    "sg:address":"Muhenstrasse 13",
    "sg:city":"Oberentfelden",
    "sg:orig_category":"Fotografische Ateliers",
    "sg:phone":"+41 62 723 69 63",
    "sg:postcode":"5036",
    "sg:province":"Aargau",
    "wof:name":"Hannes Kirchhof Fotografisches Atelier",
    "wof:placetype":"venue"
},
  "geometry": {"coordinates":[8.0472345352,47.3542861938],"type":"Point"}
}