{
  "type": "Feature",
  "properties": {
    "iso:country":"CH",
    "sg:address":"Bellot Rue Fran\u00e7ois- 6 1206 Gen\u00e8ve. Postfach",
    "sg:city":"Gen\u00e8ve",
    "sg:orig_category":"Unclassifiable Establishments",
    "sg:phone":"+41 41 790 00 06",
    "sg:postcode":"1206",
    "sg:province":"Gen\u00e8ve",
    "wof:name":"Gotic Wellness, E. Haas",
    "wof:placetype":"venue"
},
  "geometry": {"coordinates":[8.4382047653,47.1558494568],"type":"Point"}
}