{
  "type": "Feature",
  "properties": {
    "iso:country":"CH",
    "sg:address":"Efringerstrasse 94 4057 Basel. Postfach",
    "sg:city":"Basel",
    "sg:orig_category":"Veterin\u00e4rwesen",
    "sg:phone":"+41 61 692 83 19",
    "sg:postcode":"4057",
    "sg:province":"Basel-Stadt",
    "wof:name":"Animal Physio Michel P. Physiotherapeutische Behandlung U. Rehabilitation F\u00fcr Haustiere",
    "wof:placetype":"venue"
},
  "geometry": {"coordinates":[7.5963630676,47.5705490112],"type":"Point"}
}