{
  "type": "Feature",
  "properties": {
    "iso:country":"CH",
    "sg:address":"Holzh\u00e4usern",
    "sg:city":"Amlikon-bissegg",
    "sg:orig_category":"Sportvereine Turnen",
    "sg:phone":"+41 71 655 12 90",
    "sg:postcode":"8514",
    "sg:province":"Thurgau",
    "wof:name":"Turnverein M\u00e4rwil",
    "wof:placetype":"venue"
},
  "geometry": {"coordinates":[9.0475540161,47.5529556274],"type":"Point"}
}