{
  "type": "Feature",
  "properties": {
    "iso:country":"CH",
    "sg:address":"Rosengartenstrasse 53",
    "sg:city":"Hochdorf",
    "sg:orig_category":"Fernmeldedienste",
    "sg:phone":"+41 41 910 49 77",
    "sg:postcode":"6280",
    "sg:province":"Luzern",
    "wof:name":"Ostertag Gmbh",
    "wof:placetype":"venue"
},
  "geometry": {"coordinates":[8.2963037491,47.1631088257],"type":"Point"}
}