{
  "type": "Feature",
  "properties": {
    "iso:country":"CH",
    "sg:address":"Bildst\u00f6ckliweg 8",
    "sg:city":"Arlesheim",
    "sg:orig_category":"Sportvereine Ballsport Tischtennis",
    "sg:postcode":"4144",
    "sg:province":"Basel-Landschaft",
    "wof:name":"Ttc Sporting Basel",
    "wof:placetype":"venue"
},
  "geometry": {"coordinates":[7.621819973,47.496471405],"type":"Point"}
}