{
  "type": "Feature",
  "properties": {
    "iso:country":"CH",
    "sg:address":"Via Motta 34",
    "sg:city":"Biasca",
    "sg:classifiers":[
        {
            "category":"Arena",
            "subcategory":"Sports Club",
            "type":"Entertainment"
        }
    ],
    "sg:phone":"+41 91 862 14 10",
    "sg:postcode":"6710",
    "sg:province":"Ticino",
    "sg:tags":[
        "karate",
        "judo",
        "sportvereine"
    ],
    "wof:name":"Judo Kwai Biasca",
    "wof:placetype":"venue"
},
  "geometry": {"coordinates":[8.9677095413,46.3638038635],"type":"Point"}
}