{
  "type": "Feature",
  "properties": {
    "iso:country":"CH",
    "sg:address":"Dorfstrasse 11",
    "sg:city":"Engelberg",
    "sg:orig_category":"Unclassifiable Establishments",
    "sg:phone":"+41 41 637 00 04",
    "sg:postcode":"6390",
    "sg:province":"Obwalden",
    "wof:name":"Swiss Alp Shop Gmbh",
    "wof:placetype":"venue"
},
  "geometry": {"coordinates":[8.4063119888,46.8212127686],"type":"Point"}
}