{
  "type": "Feature",
  "properties": {
    "iso:country":"CH",
    "sg:address":"Chemin Des Primev\u00e8res 45",
    "sg:city":"Fribourg",
    "sg:orig_category":"Herstellung von Sportger\u00e4ten",
    "sg:postcode":"1702",
    "sg:province":"Fribourg",
    "wof:name":"Textinvest Sa",
    "wof:placetype":"venue"
},
  "geometry": {"coordinates":[7.1410579681,46.8052902222],"type":"Point"}
}