{
  "type": "Feature",
  "properties": {
    "iso:country":"CH",
    "sg:address":"Seestrasse 48a 8942 Oberrieden. Postfach",
    "sg:city":"Oberrieden",
    "sg:orig_category":"Herstellung von sonstigen Holzwaren",
    "sg:phone":"+41 17723666",
    "sg:postcode":"8942",
    "sg:province":"Z\u00fcrich",
    "wof:name":"Mpbea Br\u00e4m",
    "wof:placetype":"venue"
},
  "geometry": {"coordinates":[8.5815429688,47.2758979797],"type":"Point"}
}