{
  "type": "Feature",
  "properties": {
    "iso:country":"CH",
    "sg:address":"Im Unterzelg 10",
    "sg:city":"Berikon",
    "sg:orig_category":"Wirtschaftspr\u00fcfung, Steuerberatung U Treuhand",
    "sg:postcode":"8965",
    "sg:province":"Aargau",
    "wof:name":"Bauen Gilbert, Eidg. Dipl. Buchhalter",
    "wof:placetype":"venue"
},
  "geometry": {"coordinates":[8.3685750961,47.3529853821],"type":"Point"}
}