{
  "type": "Feature",
  "properties": {
    "iso:country":"CH",
    "sg:address":"Unterer Platz 1063",
    "sg:city":"Walzenhausen",
    "sg:orig_category":"Fachdetailhandel in Verkaufsr\u00e4umen",
    "sg:postcode":"9428",
    "sg:province":"Appenzell Ausserrhoden",
    "wof:name":"Aqua Halter",
    "wof:placetype":"venue"
},
  "geometry": {"coordinates":[9.6124219894,47.4426498413],"type":"Point"}
}