{
  "type": "Feature",
  "properties": {
    "iso:country":"CH",
    "sg:address":"Rue Du Maupas 22",
    "sg:city":"Lausanne",
    "sg:orig_category":"Detailhandel mit Fleisch U Fleischwaren",
    "sg:phone":"+41 21 646 44 75",
    "sg:postcode":"1004",
    "sg:province":"Vaud",
    "wof:name":"Ren\u00e9 Schaller Boucherie Du Maupas",
    "wof:placetype":"venue"
},
  "geometry": {"coordinates":[6.6256718636,46.5251350403],"type":"Point"}
}