{
  "type": "Feature",
  "properties": {
    "iso:country":"CH",
    "sg:address":"Rothusweg 4 6300 Zug. Postfach",
    "sg:city":"Zug",
    "sg:orig_category":"Unclassifiable Establishments",
    "sg:phone":"+41 17241440",
    "sg:postcode":"6300",
    "sg:province":"Zug",
    "wof:name":"Wassner Holding Ag",
    "wof:placetype":"venue"
},
  "geometry": {"coordinates":[8.5189399719,47.1706352234],"type":"Point"}
}