{
  "type": "Feature",
  "properties": {
    "iso:country":"CH",
    "sg:address":"Aubrigstrasse 16",
    "sg:city":"Horgen",
    "sg:orig_category":"Vorschulen, Kinderg\u00e4rten",
    "sg:phone":"+41 17258500",
    "sg:postcode":"8810",
    "sg:province":"Z\u00fcrich",
    "wof:name":"Kindergarten Kottenrain",
    "wof:placetype":"venue"
},
  "geometry": {"coordinates":[8.6012525558,47.2542419434],"type":"Point"}
}