{
  "type": "Feature",
  "properties": {
    "iso:country":"CH",
    "sg:address":"Obertor 8",
    "sg:city":"Winterthur",
    "sg:orig_category":"Psychotherapie",
    "sg:phone":"+41 52 202 71 03",
    "sg:postcode":"8400",
    "sg:province":"Z\u00fcrich",
    "wof:name":"Dagmar Ambass Psychotherapie",
    "wof:placetype":"venue"
},
  "geometry": {"coordinates":[8.7329044342,47.5001716614],"type":"Point"}
}