{
  "type": "Feature",
  "properties": {
    "iso:country":"CH",
    "sg:address":"Industriestrasse 7 8117 F\u00e4llanden. Postfach 218",
    "sg:city":"F\u00e4llanden",
    "sg:orig_category":"Grosshandel mit festen Brennstoffen U Mineral\u00f6lerzeugnissen",
    "sg:phone":"+41 19054020",
    "sg:postcode":"8117",
    "sg:province":"Z\u00fcrich",
    "wof:name":"Union Brikett-verkauf Ag",
    "wof:placetype":"venue"
},
  "geometry": {"coordinates":[8.6419286728,47.3763465881],"type":"Point"}
}