{
  "type": "Feature",
  "properties": {
    "iso:country":"CH",
    "sg:address":"Industriestrasse 8890 Flums. Postfach 2",
    "sg:city":"Flums",
    "sg:orig_category":"Rechtsberatung",
    "sg:phone":"+41 81 734 15 01",
    "sg:postcode":"8890",
    "sg:province":"St. Gallen",
    "wof:name":"Pamag Ag",
    "wof:placetype":"venue"
},
  "geometry": {"coordinates":[9.3465270996,47.0968208313],"type":"Point"}
}