{
  "type": "Feature",
  "properties": {
    "iso:country":"CH",
    "sg:address":"Bergli",
    "sg:city":"Linthal",
    "sg:orig_category":"Betrieb von Sportanlagen",
    "sg:postcode":"8783",
    "sg:province":"Glarus",
    "wof:name":"Interessengemeinschaft F\u00fcr Sportanlagen Linthal.",
    "wof:placetype":"venue"
},
  "geometry": {"coordinates":[8.978665,46.908779],"type":"Point"}
}