{
  "type": "Feature",
  "properties": {
    "iso:country":"CH",
    "sg:address":"Rue Du Bourg 3",
    "sg:city":"Aigle",
    "sg:orig_category":"Reiseb\u00fcros",
    "sg:phone":"+41 24 468 10 10",
    "sg:postcode":"1860",
    "sg:province":"Vaud",
    "wof:name":"Boomerang Voyages Sa Agence De Voyages",
    "wof:placetype":"venue"
},
  "geometry": {"coordinates":[6.9687700272,46.3182220459],"type":"Point"}
}