{
  "type": "Feature",
  "properties": {
    "iso:country":"CH",
    "sg:address":"Z.i. Les Hugues",
    "sg:city":"Cressier",
    "sg:classifiers":[
        {
            "category":"Autos & Motor Vehicles",
            "subcategory":"Fuel & Gas Station",
            "type":"Retail Goods"
        }
    ],
    "sg:phone":"+41 32 758 61 11",
    "sg:postcode":"2088",
    "sg:province":"Neuch\u00e2tel",
    "sg:tags":[
        "engine",
        "petrol",
        "turbine",
        "diesel"
    ],
    "wof:name":"Petroplus Refining Cressier S.a.",
    "wof:placetype":"venue"
},
  "geometry": {"coordinates":[7.0369849205,47.0522041321],"type":"Point"}
}