{
  "type": "Feature",
  "properties": {
    "iso:country":"CH",
    "sg:address":"Simplon Rue Du 45 1006 Lausanne. Postfach",
    "sg:city":"Lausanne",
    "sg:orig_category":"Hochschulen U h\u00f6here Ausbildung",
    "sg:postcode":"1003",
    "sg:province":"Vaud",
    "wof:name":"La Quang-hoa Cours Pr\u00e9paratoires Aux Examens De Maturit\u00e9 Etc",
    "wof:placetype":"venue"
},
  "geometry": {"coordinates":[6.627436161,46.5163154602],"type":"Point"}
}