{
  "type": "Feature",
  "properties": {
    "iso:country":"CH",
    "sg:address":"Zwingenstrasse 3",
    "sg:city":"Brislach",
    "sg:orig_category":"Bauschreinerei Glaserei",
    "sg:phone":"+41 61 781 26 12",
    "sg:postcode":"4225",
    "sg:province":"Basel-Landschaft",
    "wof:name":"Valentin Schnider Schreinerei & Glaserei",
    "wof:placetype":"venue"
},
  "geometry": {"coordinates":[7.542545,47.419006],"type":"Point"}
}