{
  "type": "Feature",
  "properties": {
    "iso:country":"CH",
    "sg:address":"Kl\u00f6sterlistrasse 7",
    "sg:city":"Kriens",
    "sg:orig_category":"Vereine Gesang and Jodler",
    "sg:phone":"+41 41 320 84 82",
    "sg:postcode":"6010",
    "sg:province":"Luzern",
    "wof:name":"Jodlerdoppelquartett Sportfreunde Luzern",
    "wof:placetype":"venue"
},
  "geometry": {"coordinates":[8.2759599686,47.0302886963],"type":"Point"}
}