{
  "type": "Feature",
  "properties": {
    "iso:country":"CH",
    "sg:address":"Rue De La Ribe 7 2823 Courcelon. Postfach",
    "sg:city":"Courcelon",
    "sg:orig_category":"Interessenvertretungen",
    "sg:postcode":"2823",
    "sg:province":"Jura",
    "wof:name":"Fondation Alo\u00efs Erb",
    "wof:placetype":"venue"
},
  "geometry": {"coordinates":[7.3899388313,47.3599205017],"type":"Point"}
}