{
  "type": "Feature",
  "properties": {
    "iso:country":"CH",
    "sg:address":"Chiemerstrasse",
    "sg:city":"Immensee",
    "sg:orig_category":"Mechanische Werkst\u00e4tten",
    "sg:phone":"+41 41 850 26 66",
    "sg:postcode":"6405",
    "sg:province":"Schwyz",
    "wof:name":"Peter Schneider Mechanische Werkst\u00e4tte",
    "wof:placetype":"venue"
},
  "geometry": {"coordinates":[8.4635753632,47.0969161987],"type":"Point"}
}