{
  "type": "Feature",
  "properties": {
    "iso:country":"CH",
    "sg:address":"Schwadernaustrasse 63 2558 Aegerten. Postfach",
    "sg:city":"Aegerten",
    "sg:orig_category":"Erbringung von Dienstleistungen f\u00fcr Unternehmen",
    "sg:postcode":"2558",
    "sg:province":"Bern",
    "wof:name":"Hedica Beschriftungstechniken Ag Beschriftungstechniken; Produktion, Handel, Dienstleistungen",
    "wof:placetype":"venue"
},
  "geometry": {"coordinates":[7.2965269089,47.1246261597],"type":"Point"}
}