{
  "type": "Feature",
  "properties": {
    "iso:country":"CH",
    "sg:address":"Sch\u00f6neggweg 30",
    "sg:city":"M\u00fcnchenbuchsee",
    "sg:orig_category":"Pensionskassen",
    "sg:postcode":"3053",
    "sg:province":"Bern",
    "wof:name":"Personalf\u00fcrsorgestiftung Der Firma Markus Ign. M\u00fcller, M\u00f6belwerkst\u00e4tten Und Innenausbau, Sempach",
    "wof:placetype":"venue"
},
  "geometry": {"coordinates":[8.2235832214,47.131149292],"type":"Point"}
}