{
  "type": "Feature",
  "properties": {
    "iso:country":"CH",
    "sg:address":"Dumas Avenue 24 1206 Gen\u00e8ve. Postfach",
    "sg:city":"Gen\u00e8ve",
    "sg:orig_category":"Herstellung von elektronischen Bauelementen",
    "sg:postcode":"1206",
    "sg:province":"Gen\u00e8ve",
    "wof:name":"Pricitec Gmbh",
    "wof:placetype":"venue"
},
  "geometry": {"coordinates":[8.536819458,47.294467926],"type":"Point"}
}