{
  "type": "Feature",
  "properties": {
    "iso:country":"CH",
    "sg:address":"Mariahilf 31",
    "sg:city":"D\u00fcdingen",
    "sg:orig_category":"Massagestudios",
    "sg:phone":"+41 26 493 22 60",
    "sg:postcode":"3186",
    "sg:province":"Fribourg",
    "wof:name":"Peter G\u00f6tschmann Massagen",
    "wof:placetype":"venue"
},
  "geometry": {"coordinates":[7.204668045,46.8269996643],"type":"Point"}
}