{
  "type": "Feature",
  "properties": {
    "iso:country":"CH",
    "sg:address":"Sch\u00f6ngrund 29",
    "sg:city":"Rotkreuz",
    "sg:orig_category":"Unclassifiable Establishments",
    "sg:phone":"+41 41 792 15 56",
    "sg:postcode":"6343",
    "sg:province":"Zug",
    "wof:name":"Netstep Informatik Gmbh",
    "wof:placetype":"venue"
},
  "geometry": {"coordinates":[8.4276599884,47.1462631226],"type":"Point"}
}