{
  "type": "Feature",
  "properties": {
    "iso:country":"CH",
    "sg:address":"Rheinstrasse 53",
    "sg:city":"Balzers",
    "sg:orig_category":"Sanit\u00e4r U Heizungsinstallation Sanit\u00e4rinstallation",
    "sg:phone":"+41 81 416 10 10",
    "sg:postcode":"9496",
    "wof:name":"Frei Sanit\u00e4r Ag",
    "wof:placetype":"venue"
},
  "geometry": {"coordinates":[9.8355503082,46.8000297546],"type":"Point"}
}