{
  "type": "Feature",
  "properties": {
    "iso:country":"CH",
    "sg:address":"1002 Lausanne Case Postale 3162",
    "sg:city":"Lausanne",
    "sg:orig_category":"Sportvereine Wassersport Rudern",
    "sg:postcode":"1002",
    "sg:province":"Vaud",
    "wof:name":"Lausanne-sports Section D'aviron",
    "wof:placetype":"venue"
},
  "geometry": {"coordinates":[6.6334500313,46.5194282532],"type":"Point"}
}