{
  "type": "Feature",
  "properties": {
    "iso:country":"CH",
    "sg:address":"Vadianstrasse 37 9000 St.gallen. Postfach",
    "sg:city":"Arbon",
    "sg:orig_category":"Unternehmensberatung Wirtschaftspr\u00fcfung, Steuerberatung U Treuhand",
    "sg:phone":"+41 71 447 88 77",
    "sg:postcode":"9320",
    "sg:province":"Thurgau",
    "wof:name":"Ag F\u00fcr Steuerberatung S+a Nationale U. Internationale Steuer- U. Unternehmensberatung",
    "wof:placetype":"venue"
},
  "geometry": {"coordinates":[9.3700551987,47.4213218689],"type":"Point"}
}