{
  "type": "Feature",
  "properties": {
    "iso:country":"CH",
    "sg:address":"Bellevue 7",
    "sg:city":"Marin-epagnier",
    "sg:orig_category":"Grosshandel mit B\u00fcromaschinen Grosshandel mit Datenverarbeitungsger\u00e4ten",
    "sg:phone":"+41 32 755 73 33",
    "sg:postcode":"2074",
    "sg:province":"Neuch\u00e2tel",
    "wof:name":"Id Informatique & D\u00e9veloppement Sa",
    "wof:placetype":"venue"
},
  "geometry": {"coordinates":[7.005469799,47.0093574524],"type":"Point"}
}