{
  "type": "Feature",
  "properties": {
    "iso:country":"CH",
    "sg:address":"Oberer Graben 6",
    "sg:city":"St. Gallen",
    "sg:classifiers":[
        {
            "category":"Banks & Credit Unions",
            "subcategory":"Bank",
            "type":"Services"
        }
    ],
    "sg:phone":"+41 71 223 18 12",
    "sg:postcode":"9001",
    "sg:province":"St. Gallen",
    "wof:name":"Ersparnisanstalt, Der Stadt St. Gallen",
    "wof:placetype":"venue"
},
  "geometry": {"coordinates":[9.374097,47.425488],"type":"Point"}
}