{
  "type": "Feature",
  "properties": {
    "iso:country":"CH",
    "sg:address":"Schlucht",
    "sg:city":"Ebnat",
    "sg:orig_category":"Allgemeiner Hoch U Tiefbau",
    "sg:phone":"+41 71 990 01 01",
    "sg:postcode":"9642",
    "sg:province":"St. Gallen",
    "wof:name":"Bauzeitlos Giezendanner",
    "wof:placetype":"venue"
},
  "geometry": {"coordinates":[9.1167,47.25],"type":"Point"}
}