{
  "type": "Feature",
  "properties": {
    "iso:country":"CH",
    "sg:address":"Aspistrasse 4",
    "sg:city":"Brunnenthal",
    "sg:orig_category":"Non-Classified Establishments",
    "sg:postcode":"3307",
    "sg:province":"Solothurn",
    "wof:name":"Gemhelp, Ruedi Ziegler",
    "wof:placetype":"venue"
},
  "geometry": {"coordinates":[7.4704079628,47.0886535645],"type":"Point"}
}