{
  "type": "Feature",
  "properties": {
    "iso:country":"CH",
    "sg:address":"Sonnenbergstrasse 16",
    "sg:city":"Chur",
    "sg:orig_category":"Sonstige mit Sport verbundene T\u00e4tigkeiten",
    "sg:postcode":"7000",
    "sg:province":"Graubunden",
    "wof:name":"Destefani R.",
    "wof:placetype":"venue"
},
  "geometry": {"coordinates":[9.5363025665,46.8578796387],"type":"Point"}
}