{
  "type": "Feature",
  "properties": {
    "iso:country":"CH",
    "sg:address":"Schlosstalstrasse 36",
    "sg:city":"Winterthur",
    "sg:classifiers":[
        {
            "category":"Professional",
            "subcategory":"Advertising",
            "type":"Services"
        }
    ],
    "sg:phone":"+41 52 202 51 20",
    "sg:postcode":"8406",
    "sg:province":"Z\u00fcrich",
    "sg:tags":[
        "agency"
    ],
    "wof:name":"Hic Et Nunc Communication",
    "wof:placetype":"venue"
},
  "geometry": {"coordinates":[8.703333,47.496269],"type":"Point"}
}