{
  "type": "Feature",
  "properties": {
    "addr:full":"Aspstrasse 4 Ober-ohringen Seuzach Z\u00fcrich 8472",
    "addr:housenumber":"4",
    "addr:postcode":"8472",
    "addr:street":"Aspstrasse",
    "iso:country":"CH",
    "sg:address":"Aspstrasse 4 Ober-ohringen",
    "sg:city":"Seuzach",
    "sg:orig_category":"Autogaragen Autospenglereien",
    "sg:phone":"+41 52 320 01 15",
    "sg:postcode":"8472",
    "sg:province":"Z\u00fcrich",
    "wof:name":"Carrosserie & Garage Moser Ag",
    "wof:placetype":"venue"
},
  "geometry": {"coordinates":[8.7309,47.536324],"type":"Point"}
}