{
  "type": "Feature",
  "properties": {
    "iso:country":"CH",
    "sg:address":"Schanzenstrasse 4 3008 Bern. Postfach 5864",
    "sg:city":"Bern",
    "sg:orig_category":"Nationale Postdienste",
    "sg:phone":"+41 71 385 29 80",
    "sg:postcode":"3001",
    "sg:province":"Bern",
    "wof:name":"Die Schweizerische Post Gossau Sg 1",
    "wof:placetype":"venue"
},
  "geometry": {"coordinates":[9.2504940033,47.4135513306],"type":"Point"}
}