{
  "type": "Feature",
  "properties": {
    "iso:country":"CH",
    "sg:address":"Poststrasse 30 6300 Zug. Postfach 1248",
    "sg:city":"Zug",
    "sg:orig_category":"Unfall U Schadenversicherung",
    "sg:phone":"+41 21 641 61 20",
    "sg:postcode":"6301",
    "sg:province":"Zug",
    "wof:name":"Coop Protection Juridique Agence Romandie",
    "wof:placetype":"venue"
},
  "geometry": {"coordinates":[6.6260700226,46.5257492065],"type":"Point"}
}