{
  "type": "Feature",
  "properties": {
    "iso:country":"CH",
    "sg:address":"Sonnenbergstrasse 6",
    "sg:city":"Chur",
    "sg:orig_category":"Blumen U Zierpflanzenbau Detailhandel mit Blumen U Pflanzen",
    "sg:phone":"+41 81 353 27 47",
    "sg:postcode":"7000",
    "sg:province":"Graubunden",
    "wof:name":"Joos Anton",
    "wof:placetype":"venue"
},
  "geometry": {"coordinates":[9.534838,46.857754],"type":"Point"}
}