{
  "type": "Feature",
  "properties": {
    "iso:country":"CH",
    "sg:address":"Hauptstrasse 74 C 7231 Pragg-jenaz. Postfach",
    "sg:city":"Pragg-jenaz",
    "sg:orig_category":"Architektur U Ingenieurb\u00fcros",
    "sg:postcode":"7231",
    "sg:province":"Graubunden",
    "wof:name":"Paulweber Alwin Gmbh",
    "wof:placetype":"venue"
},
  "geometry": {"coordinates":[9.709212,46.939247],"type":"Point"}
}