{
  "type": "Feature",
  "properties": {
    "iso:country":"CH",
    "sg:address":"Bernstrasse 6",
    "sg:city":"Jegenstorf",
    "sg:orig_category":"Fachdetailhandel mit pharmazeutischen Produkten",
    "sg:phone":"+41 31 761 33 30",
    "sg:postcode":"3303",
    "sg:province":"Bern",
    "wof:name":"M\u00fchlen-apotheke Gmbh",
    "wof:placetype":"venue"
},
  "geometry": {"coordinates":[7.5065031052,47.0497627258],"type":"Point"}
}