{
  "type": "Feature",
  "properties": {
    "iso:country":"CH",
    "sg:address":"7306",
    "sg:city":"Fl\u00e4sch",
    "sg:orig_category":"Sportvereine Turnen",
    "sg:phone":"+41 41 870 52 92",
    "sg:postcode":"7306",
    "sg:province":"Graubunden",
    "wof:name":"Turnverein Stv Fl\u00fcelen",
    "wof:placetype":"venue"
},
  "geometry": {"coordinates":[8.6154851913,46.8801040649],"type":"Point"}
}