{
  "type": "Feature",
  "properties": {
    "iso:country":"CH",
    "sg:address":"1552",
    "sg:city":"Trey",
    "sg:orig_category":"Bezirks, Sekundar, Realschulen, Oberstufe der Primarschulen Primarschulen",
    "sg:phone":"+41 26 668 10 62",
    "sg:postcode":"1552",
    "sg:province":"Vaud",
    "wof:name":"Institut Cornamusaz",
    "wof:placetype":"venue"
},
  "geometry": {"coordinates":[6.93353,46.784512],"type":"Point"}
}