{
  "type": "Feature",
  "properties": {
    "iso:country":"CH",
    "sg:address":"Chemin De Clamogne 21",
    "sg:city":"Aubonne",
    "sg:orig_category":"Instandhaltung U Reparatur von Automobilen",
    "sg:phone":"+41 21 808 52 52",
    "sg:postcode":"1170",
    "sg:province":"Vaud",
    "wof:name":"Garage Durand Pierre-andr\u00e9 Sa",
    "wof:placetype":"venue"
},
  "geometry": {"coordinates":[6.3973550797,46.4882240295],"type":"Point"}
}