{
  "type": "Feature",
  "properties": {
    "iso:country":"CH",
    "sg:address":"Mattenstrasse 2 8112 Otelfingen. Postfach",
    "sg:city":"Otelfingen",
    "sg:orig_category":"Grosshandel mit Blumen U Pflanzen Grosshandel mit landwirtschaftlichen Maschinen U Ger\u00e4ten",
    "sg:phone":"+41 18472727",
    "sg:postcode":"8112",
    "sg:province":"Z\u00fcrich",
    "wof:name":"Silent Ag Kompaktschlepper & Maschinencenter",
    "wof:placetype":"venue"
},
  "geometry": {"coordinates":[8.4050769806,47.4580993652],"type":"Point"}
}