{
  "type": "Feature",
  "properties": {
    "iso:country":"CH",
    "sg:address":"Schulstrasse 20",
    "sg:city":"Rorschach",
    "sg:orig_category":"Sonstiger Fachdetailhandel in Verkaufsr\u00e4umen",
    "sg:phone":"+41 79 686 40 09",
    "sg:postcode":"9400",
    "sg:province":"St. Gallen",
    "wof:name":"Anton R\u00fcedi Briefmarken",
    "wof:placetype":"venue"
},
  "geometry": {"coordinates":[9.4951868057,47.4745674133],"type":"Point"}
}