{
  "type": "Feature",
  "properties": {
    "iso:country":"CH",
    "sg:address":"Centrale De Croix",
    "sg:city":"Icogne",
    "sg:orig_category":"Elektrizit\u00e4tsversorgung",
    "sg:phone":"+41 27 398 27 20",
    "sg:postcode":"1977",
    "sg:province":"Valais",
    "wof:name":"Electricit\u00e9 De La Lienne Sa",
    "wof:placetype":"venue"
},
  "geometry": {"coordinates":[7.438272953,46.2908935547],"type":"Point"}
}