{
  "type": "Feature",
  "properties": {
    "iso:country":"CH",
    "sg:address":"Burghaldenstrasse 25",
    "sg:city":"Lenzburg",
    "sg:orig_category":"Detailhandel mit Bekleidung Detailhandel mit Damenbekleidung",
    "sg:phone":"+41 62 892 00 51",
    "sg:postcode":"5600",
    "sg:province":"Aargau",
    "wof:name":"Boutique X-elle, Heine E.",
    "wof:placetype":"venue"
},
  "geometry": {"coordinates":[8.179863,47.385719],"type":"Point"}
}