{
  "type": "Feature",
  "properties": {
    "iso:country":"CH",
    "sg:address":"Oberhauserstrasse 45",
    "sg:city":"Glattbrugg",
    "sg:orig_category":"Vorschulen, Kinderg\u00e4rten",
    "sg:phone":"+41 71 385 33 83",
    "sg:postcode":"8152",
    "sg:province":"Z\u00fcrich",
    "wof:name":"Kindergarten Haldenb\u00fcel",
    "wof:placetype":"venue"
},
  "geometry": {"coordinates":[9.2484464645,47.4176826477],"type":"Point"}
}