{
  "type": "Feature",
  "properties": {
    "iso:country":"CH",
    "sg:address":"Bahnhofstrasse 76 9240 Uzwil. Postfach 121",
    "sg:city":"Uzwil",
    "sg:orig_category":"Versicherungen Generalagenturen",
    "sg:phone":"+41 71 955 46 46",
    "sg:postcode":"9240",
    "sg:province":"St. Gallen",
    "wof:name":"Heinz Aeschbacher Winterthur Leben Generalagentur",
    "wof:placetype":"venue"
},
  "geometry": {"coordinates":[9.1324615479,47.4364013672],"type":"Point"}
}