{
  "type": "Feature",
  "properties": {
    "iso:country":"CH",
    "sg:address":"Voie-creuse La 21",
    "sg:city":"Gen\u00e8ve",
    "sg:orig_category":"Grosshandel mit Erzen U Metallen",
    "sg:phone":"+41 22 734 94 04",
    "sg:postcode":"1202",
    "sg:province":"Gen\u00e8ve",
    "wof:name":"S & K Trading Company Sa",
    "wof:placetype":"venue"
},
  "geometry": {"coordinates":[6.1427960396,46.2203598022],"type":"Point"}
}