{
  "type": "Feature",
  "properties": {
    "iso:country":"CH",
    "sg:address":"Holeestrasse 9",
    "sg:city":"Basel",
    "sg:orig_category":"Sonstige mit Sport verbundene T\u00e4tigkeiten",
    "sg:postcode":"4054",
    "sg:province":"Basel-Stadt",
    "wof:name":"Freespeed Basel",
    "wof:placetype":"venue"
},
  "geometry": {"coordinates":[7.5745410919,47.5443000793],"type":"Point"}
}