{
  "type": "Feature",
  "properties": {
    "iso:country":"CH",
    "sg:address":"Gyrischachen 44 3400 Burgdorf. Postfach",
    "sg:city":"Burgdorf",
    "sg:orig_category":"Baugewerbe Mechanische Werkst\u00e4tten",
    "sg:phone":"+41 34 422 06 89",
    "sg:postcode":"3402",
    "sg:province":"Bern",
    "wof:name":"Andreas Eggimann Montagen & Maschinenbau",
    "wof:placetype":"venue"
},
  "geometry": {"coordinates":[7.630443,47.063469],"type":"Point"}
}