{
  "type": "Feature",
  "properties": {
    "iso:country":"CH",
    "sg:address":"Roggenhausenstrasse 51",
    "sg:city":"Unterentfelden",
    "sg:classifiers":[
        {
            "category":"Banks & Credit Unions",
            "subcategory":"Bank",
            "type":"Services"
        }
    ],
    "sg:phone":"+41 4164437680",
    "sg:postcode":"5035",
    "sg:province":"Aargau",
    "wof:name":"Schweiz. Mobiliar",
    "wof:placetype":"venue"
},
  "geometry": {"coordinates":[8.039461,47.369015],"type":"Point"}
}