{
  "type": "Feature",
  "properties": {
    "iso:country":"CH",
    "sg:address":"Hegifeldstrasse 60 8400 Winterthur. Postfach",
    "sg:city":"Oberwinterthur",
    "sg:orig_category":"Gesundheitswesen",
    "sg:postcode":"8404",
    "sg:province":"Z\u00fcrich",
    "wof:name":"Know-how F\u00fcr Pers\u00f6nlichkeitsentfaltung Nordt E.",
    "wof:placetype":"venue"
},
  "geometry": {"coordinates":[8.7674894333,47.5075416565],"type":"Point"}
}