{
  "type": "Feature",
  "properties": {
    "addr:full":"Rue De Lausanne 8 Sion Valais 1950",
    "addr:housenumber":"8",
    "addr:postcode":"1950",
    "addr:street":"Rue De Lausanne",
    "iso:country":"CH",
    "sg:address":"Rue De Lausanne 8",
    "sg:city":"Sion",
    "sg:orig_category":"Detailhandel mit B\u00fcromaschinen U einrichtungen",
    "sg:phone":"+41 27 322 17 33",
    "sg:postcode":"1950",
    "sg:province":"Valais",
    "wof:name":"Felix Bureautique Sa",
    "wof:placetype":"venue"
},
  "geometry": {"coordinates":[7.359448,46.232815],"type":"Point"}
}