{
  "type": "Feature",
  "properties": {
    "iso:country":"CH",
    "sg:address":"Im Bungert 2",
    "sg:city":"Oetwil",
    "sg:orig_category":"Elektroinstallation",
    "sg:phone":"+41 17478060",
    "sg:postcode":"8955",
    "sg:province":"Z\u00fcrich",
    "wof:name":"Walter Ruosch Ruosch Telefonie",
    "wof:placetype":"venue"
},
  "geometry": {"coordinates":[8.392165184,47.429561615],"type":"Point"}
}