{
  "type": "Feature",
  "properties": {
    "iso:country":"CH",
    "sg:address":"Kalofen 9",
    "sg:city":"Grosswangen",
    "sg:orig_category":"Sonstiger Grosshandel",
    "sg:phone":"+41 41 980 44 70",
    "sg:postcode":"6022",
    "sg:province":"Luzern",
    "wof:name":"Kagro Trading Fries-oberli Patricia",
    "wof:placetype":"venue"
},
  "geometry": {"coordinates":[8.0501451492,47.1298370361],"type":"Point"}
}