{
  "type": "Feature",
  "properties": {
    "iso:country":"CH",
    "sg:address":"Strada Cantonale Sorte",
    "sg:city":"Lostallo",
    "sg:orig_category":"Hochschulen U h\u00f6here Ausbildung",
    "sg:phone":"+41 91 830 16 33",
    "sg:postcode":"6558",
    "sg:province":"Graubunden",
    "wof:name":"La Scala Walthard & Co",
    "wof:placetype":"venue"
},
  "geometry": {"coordinates":[9.1959848404,46.3131256104],"type":"Point"}
}