{
  "type": "Feature",
  "properties": {
    "iso:country":"CH",
    "sg:address":"Chapfstrasse 245",
    "sg:city":"R\u00fcdlingen",
    "sg:orig_category":"Handelsvermittlung",
    "sg:phone":"+41 18675578",
    "sg:postcode":"8455",
    "sg:province":"Schaffhausen",
    "wof:name":"Andreas Bachmann Projects",
    "wof:placetype":"venue"
},
  "geometry": {"coordinates":[8.5720300674,47.5793533325],"type":"Point"}
}