{
  "type": "Feature",
  "properties": {
    "iso:country":"CH",
    "sg:address":"Industriestrasse 16",
    "sg:city":"Zwingen",
    "sg:orig_category":"Herstellung von Konstruktionsteilen, Fertigbauteilen U Ausbauelementen aus Holz",
    "sg:phone":"+41 61 761 19 34",
    "sg:postcode":"4222",
    "sg:province":"Basel-Landschaft",
    "wof:name":"Otto Faller Ag",
    "wof:placetype":"venue"
},
  "geometry": {"coordinates":[7.5129108429,47.4294891357],"type":"Point"}
}