{
  "type": "Feature",
  "properties": {
    "iso:country":"CH",
    "sg:address":"Berg 711",
    "sg:city":"Trogen",
    "sg:orig_category":"Detailhandel mit Teppichen",
    "sg:phone":"+41 71 344 19 51",
    "sg:postcode":"9043",
    "sg:province":"Appenzell Ausserrhoden",
    "wof:name":"Jakob Rechsteiner Orientteppiche",
    "wof:placetype":"venue"
},
  "geometry": {"coordinates":[9.4629926682,47.4053726196],"type":"Point"}
}