{
  "type": "Feature",
  "properties": {
    "iso:country":"CH",
    "sg:address":"Farbgasse 49",
    "sg:city":"Langenthal",
    "sg:orig_category":"Herstellung von medizinischen U chirurgischen Ger\u00e4ten sowie orthop\u00e4dischen Vorrichtungen Zahntechnis",
    "sg:phone":"+41 62 922 41 08",
    "sg:postcode":"4900",
    "sg:province":"Bern",
    "wof:name":"Burkart Martin",
    "wof:placetype":"venue"
},
  "geometry": {"coordinates":[7.7885098457,47.208694458],"type":"Point"}
}