{
  "type": "Feature",
  "properties": {
    "addr:full":"Rue Winkelried 4 Gen\u00e8ve Gen\u00e8ve 1201",
    "addr:housenumber":"4",
    "addr:postcode":"1201",
    "addr:street":"Rue Winkelried",
    "iso:country":"CH",
    "sg:address":"Rue Winkelried 4",
    "sg:city":"Gen\u00e8ve",
    "sg:orig_category":"Architektur U Ingenieurb\u00fcros",
    "sg:postcode":"1201",
    "sg:province":"Gen\u00e8ve",
    "wof:name":"Temis Ag",
    "wof:placetype":"venue"
},
  "geometry": {"coordinates":[7.251735,46.796745],"type":"Point"}
}