{
  "type": "Feature",
  "properties": {
    "iso:country":"CH",
    "sg:address":"Route De Lausanne 4",
    "sg:city":"Romanel-s-lausanne",
    "sg:orig_category":"Gem\u00fcsebau Sonstige pers\u00f6nliche Dienstleistungen",
    "sg:phone":"+41 21 691 51 26",
    "sg:postcode":"1032",
    "sg:province":"Vaud",
    "wof:name":"Grandchamp Andr\u00e9",
    "wof:placetype":"venue"
},
  "geometry": {"coordinates":[6.5564260483,46.5133590698],"type":"Point"}
}