{
  "type": "Feature",
  "properties": {
    "iso:country":"CH",
    "sg:address":"Fruthwilerstrasse 14",
    "sg:city":"Ermatingen",
    "sg:orig_category":"Motoren Grosshandel",
    "sg:phone":"+41 71 664 14 53",
    "sg:postcode":"8272",
    "sg:province":"Thurgau",
    "wof:name":"Ernst M\u00e4ndli Bootsmotoren",
    "wof:placetype":"venue"
},
  "geometry": {"coordinates":[9.0800304413,47.6679267883],"type":"Point"}
}