{
  "type": "Feature",
  "properties": {
    "iso:country":"CH",
    "sg:address":"Bremgartenstrasse 61",
    "sg:city":"Aristau",
    "sg:orig_category":"RESTAURANTS: TEA-ROOMS",
    "sg:phone":"+41 56 664 44 64",
    "sg:postcode":"5628",
    "sg:province":"Aargau",
    "wof:name":"Restaurant Aristauerhof",
    "wof:placetype":"venue"
},
  "geometry": {"coordinates":[8.3611307144,47.2975578308],"type":"Point"}
}