{
  "type": "Feature",
  "properties": {
    "iso:country":"CH",
    "sg:address":"Bahnhofstrasse 69",
    "sg:city":"M\u00fcnchenwiler",
    "sg:orig_category":"Gartenbau",
    "sg:phone":"+41 26 670 11 06",
    "sg:postcode":"1797",
    "sg:province":"Bern",
    "wof:name":"Bernhard Baumberger & Sohn Garten-& Landschaftsbau",
    "wof:placetype":"venue"
},
  "geometry": {"coordinates":[7.1146678925,46.9119338989],"type":"Point"}
}