{
  "type": "Feature",
  "properties": {
    "iso:country":"CH",
    "sg:address":"Uetlibergstrasse 354",
    "sg:city":"Z\u00fcrich",
    "sg:orig_category":"Autogaragen",
    "sg:phone":"+41 79 218 28 39",
    "sg:postcode":"8045",
    "sg:province":"Z\u00fcrich",
    "wof:name":"Mario Pedranzini Garage Allcars",
    "wof:placetype":"venue"
},
  "geometry": {"coordinates":[9.83233,46.796329],"type":"Point"}
}