{
  "type": "Feature",
  "properties": {
    "iso:country":"CH",
    "sg:address":"Neubergstrasse 6",
    "sg:city":"Zurzach",
    "sg:orig_category":"Primarschulen",
    "sg:phone":"+41 56 249 21 30",
    "sg:postcode":"5330",
    "sg:province":"Aargau",
    "wof:name":"Primarschule,ek,kk Schulhaus Tiergarten",
    "wof:placetype":"venue"
},
  "geometry": {"coordinates":[8.2942667007,47.584602356],"type":"Point"}
}