{
  "type": "Feature",
  "properties": {
    "iso:country":"CH",
    "sg:address":"Im Unterried",
    "sg:city":"D\u00fcbendorf",
    "sg:orig_category":"Unclassifiable Establishments",
    "sg:postcode":"8600",
    "sg:province":"Z\u00fcrich",
    "wof:name":"'piazza Navona' Art Club Gmbh",
    "wof:placetype":"venue"
},
  "geometry": {"coordinates":[8.6224098206,47.4043540955],"type":"Point"}
}