{
  "type": "Feature",
  "properties": {
    "iso:country":"CH",
    "sg:address":"Schmelzistrasse 47",
    "sg:city":"Erschwil",
    "sg:classifiers":[
        {
            "category":"Restaurant",
            "type":"Food & Drink"
        }
    ],
    "sg:phone":"+41 61 781 40 10",
    "sg:postcode":"4228",
    "sg:province":"Solothurn",
    "wof:name":"Restaurant Kreuz",
    "wof:placetype":"venue"
},
  "geometry": {"coordinates":[7.5416398048,47.371799469],"type":"Point"}
}