{
  "type": "Feature",
  "properties": {
    "iso:country":"CH",
    "sg:address":"Selhofen 44",
    "sg:city":"Kehrsatz",
    "sg:orig_category":"Grosshandel mit Blumen U Pflanzen",
    "sg:phone":"+41 31 961 04 06",
    "sg:postcode":"3122",
    "sg:province":"Bern",
    "wof:name":"Mollet Hydro Ag",
    "wof:placetype":"venue"
},
  "geometry": {"coordinates":[7.4770998955,46.9172897339],"type":"Point"}
}