{
  "type": "Feature",
  "properties": {
    "iso:country":"CH",
    "sg:address":"Alte Landstrasse 36",
    "sg:city":"Herznach",
    "sg:orig_category":"Autospenglereien",
    "sg:phone":"+41 62 878 15 88",
    "sg:postcode":"5027",
    "sg:province":"Aargau",
    "wof:name":"Arnold Thalmann Carrosserie",
    "wof:placetype":"venue"
},
  "geometry": {"coordinates":[8.052248,47.47905],"type":"Point"}
}