{
  "type": "Feature",
  "properties": {
    "iso:country":"CH",
    "sg:address":"Chemin De La Cl\u00f4ture 6",
    "sg:city":"Biel/bienne",
    "sg:classifiers":[
        {
            "category":"Shopping",
            "subcategory":"Jewelry",
            "type":"Retail Goods"
        }
    ],
    "sg:phone":"+41 91 683 18 25",
    "sg:postcode":"2502",
    "sg:province":"Bern",
    "sg:tags":[
        "watch"
    ],
    "wof:name":"Bermi Watch Sa",
    "wof:placetype":"venue"
},
  "geometry": {"coordinates":[9.0166091919,45.8534584045],"type":"Point"}
}