{
  "type": "Feature",
  "properties": {
    "iso:country":"CH",
    "sg:address":"M\u00fchleweg 11",
    "sg:city":"Langenthal",
    "sg:orig_category":"Saunas, Solarien, Fitnesszentren U \u00e4hnliches",
    "sg:postcode":"4900",
    "sg:province":"Bern",
    "wof:name":"Pura Vida Gmbh",
    "wof:placetype":"venue"
},
  "geometry": {"coordinates":[8.7815437317,47.3674468994],"type":"Point"}
}