{
  "type": "Feature",
  "properties": {
    "iso:country":"CH",
    "sg:address":"Z\u00fcrcherstrasse 1 8193 Eglisau. Postfach",
    "sg:city":"Eglisau",
    "sg:orig_category":"Bauspenglerei Sanit\u00e4r, Heizungs U L\u00fcftungsinstallation",
    "sg:phone":"+41 18670357",
    "sg:postcode":"8193",
    "sg:province":"Z\u00fcrich",
    "wof:name":"Bertschi & Co Ag",
    "wof:placetype":"venue"
},
  "geometry": {"coordinates":[8.52189,47.57431],"type":"Point"}
}