{
  "type": "Feature",
  "properties": {
    "addr:full":"Guldenenstrasse 6 Uster Z\u00fcrich 8610",
    "addr:housenumber":"6",
    "addr:postcode":"8610",
    "addr:street":"Guldenenstrasse",
    "iso:country":"CH",
    "sg:address":"Guldenenstrasse 6",
    "sg:city":"Uster",
    "sg:classifiers":[
        {
            "category":"Building & Trades",
            "subcategory":"Construction",
            "type":"Services"
        }
    ],
    "sg:phone":"+41 22 342 39 67",
    "sg:postcode":"8610",
    "sg:province":"Z\u00fcrich",
    "sg:tags":[
        "insulation",
        "heat",
        "work",
        "cold"
    ],
    "wof:name":"Isolation Franz Fuchsgruber",
    "wof:placetype":"venue"
},
  "geometry": {"coordinates":[6.141425,46.183311],"type":"Point"}
}