{
  "type": "Feature",
  "properties": {
    "iso:country":"CH",
    "sg:address":"Engadinstrasse 2",
    "sg:city":"Chur",
    "sg:orig_category":"Zahnarztpraxen",
    "sg:phone":"+41 81 252 27 89",
    "sg:postcode":"7000",
    "sg:province":"Graubunden",
    "wof:name":"Dr. Med. Dent. Dieter Tschappu Zahnarzt",
    "wof:placetype":"venue"
},
  "geometry": {"coordinates":[9.5286464691,46.8523788452],"type":"Point"}
}