{
  "type": "Feature",
  "properties": {
    "iso:country":"CH",
    "sg:address":"Rue De La Conf\u00e9d\u00e9ration 15 1204 Gen\u00e8ve Case Postale 271",
    "sg:city":"Gen\u00e8ve",
    "sg:orig_category":"Grosshandel mit festen Brennstoffen U Mineral\u00f6lerzeugnissen",
    "sg:phone":"+41 22 319 74 10",
    "sg:postcode":"1204",
    "sg:province":"Gen\u00e8ve",
    "wof:name":"Wincor Sa",
    "wof:placetype":"venue"
},
  "geometry": {"coordinates":[6.1453061104,46.2036209106],"type":"Point"}
}