{
  "type": "Feature",
  "properties": {
    "addr:full":"Chemin Du Pr\u00e9-du-couvent 5a Ch\u00eane-bougeries Gen\u00e8ve 1224",
    "addr:housenumber":"5a",
    "addr:postcode":"1224",
    "addr:street":"Chemin Du Pre\u0301-Du-Couvent",
    "iso:country":"CH",
    "sg:address":"Chemin Du Pr\u00e9-du-couvent 5a",
    "sg:city":"Ch\u00eane-bougeries",
    "sg:orig_category":"Bezirks, Sekundar, Realschulen, Oberstufe der Primarschulen",
    "sg:phone":"+41 22 348 31 97",
    "sg:postcode":"1224",
    "sg:province":"Gen\u00e8ve",
    "wof:name":"Ecole Secondaire Gradelle",
    "wof:placetype":"venue"
},
  "geometry": {"coordinates":[6.181872,46.203358],"type":"Point"}
}