{
  "type": "Feature",
  "properties": {
    "iso:country":"CH",
    "sg:address":"Alte Bernstrasse 6",
    "sg:city":"Aegerten",
    "sg:orig_category":"Autolackierereien Autospenglereien",
    "sg:phone":"+41 79 371 98 19",
    "sg:postcode":"2558",
    "sg:province":"Bern",
    "wof:name":"Dorfplatz-carrosserie Automalerei & Spenglerei",
    "wof:placetype":"venue"
},
  "geometry": {"coordinates":[7.288783,47.121159],"type":"Point"}
}