{
  "type": "Feature",
  "properties": {
    "iso:country":"CH",
    "sg:address":"Fischerh\u00fcbel 194",
    "sg:city":"Gontenschwil",
    "sg:orig_category":"Architekturb\u00fcros",
    "sg:phone":"+41 62 773 12 38",
    "sg:postcode":"5728",
    "sg:province":"Aargau",
    "wof:name":"Udo Kalweit Architekturb\u00fcro",
    "wof:placetype":"venue"
},
  "geometry": {"coordinates":[8.146846,47.268932],"type":"Point"}
}