{
  "type": "Feature",
  "properties": {
    "iso:country":"CH",
    "sg:address":"Rue Cit\u00e9-de-la-corderie",
    "sg:city":"Gen\u00e8ve",
    "sg:orig_category":"Elektroinstallation Instandhaltung U Reparatur von Automobilen",
    "sg:phone":"+41 91 646 24 84",
    "sg:postcode":"1201",
    "sg:province":"Gen\u00e8ve",
    "wof:name":"Pierfranco Brazzola Autoelettricit\u00e0",
    "wof:placetype":"venue"
},
  "geometry": {"coordinates":[9.0076999664,45.8654785156],"type":"Point"}
}