{
  "type": "Feature",
  "properties": {
    "iso:country":"CH",
    "sg:address":"6528",
    "sg:city":"Camorino",
    "sg:orig_category":"Herstellung von k\u00e4lte U lufttechnischen Erzeugnissen f\u00fcr gewerbliche Zwecke Installation von Heizung",
    "sg:phone":"+41 91 857 07 44",
    "sg:postcode":"6528",
    "sg:province":"Ticino",
    "wof:name":"Clima Sa",
    "wof:placetype":"venue"
},
  "geometry": {"coordinates":[9.0069608688,46.1635017395],"type":"Point"}
}