{
  "type": "Feature",
  "properties": {
    "iso:country":"CH",
    "sg:address":"Industriestrasse 11 3210 Kerzers. Postfach",
    "sg:city":"Kerzers",
    "sg:orig_category":"Grosshandel mit Erzen U Metallen Grosshandel mit M\u00f6beln, Wohnbedarf, Teppichen U Bodenbel\u00e4gen",
    "sg:phone":"+41 31 750 73 73",
    "sg:postcode":"3210",
    "sg:province":"Fribourg",
    "wof:name":"Vicom Baubedarf Ag",
    "wof:placetype":"venue"
},
  "geometry": {"coordinates":[7.1846289635,46.9688034058],"type":"Point"}
}