{
  "type": "Feature",
  "properties": {
    "iso:country":"CH",
    "sg:address":"Obere Bisr\u00fctistrasse 3 9220 Bischofszell. Postfach",
    "sg:city":"Bischofszell",
    "sg:orig_category":"Herstellung von Kunststoffwaren Kunststoff-Produkte",
    "sg:phone":"+41 71 420 06 11",
    "sg:postcode":"9220",
    "sg:province":"Thurgau",
    "wof:name":"Kalex Kunststofftechnik Ag Extrusions- U. Kunststoffprodukte; Entwicklung, Herstellung, Vermarktung",
    "wof:placetype":"venue"
},
  "geometry": {"coordinates":[9.245598793,47.4922676086],"type":"Point"}
}