{
  "type": "Feature",
  "properties": {
    "iso:country":"CH",
    "sg:address":"Voa Principala Lenzerheide/lai 7082 Vaz/obervaz. Postfach",
    "sg:city":"Lenzerheide/lai",
    "sg:orig_category":"Non-Classified Establishments",
    "sg:postcode":"7078",
    "sg:province":"Graubunden",
    "wof:name":"Art Of Hair, Claudia Filter",
    "wof:placetype":"venue"
},
  "geometry": {"coordinates":[8.7918205261,47.3617134094],"type":"Point"}
}