{
  "type": "Feature",
  "properties": {
    "iso:country":"CH",
    "sg:address":"Kramgasse 17",
    "sg:city":"Bern",
    "sg:orig_category":"Detailhandel mit Spielwaren",
    "sg:phone":"+41 31 311 21 81",
    "sg:postcode":"3011",
    "sg:province":"Bern",
    "wof:name":"B\u00fcchi Modellautos",
    "wof:placetype":"venue"
},
  "geometry": {"coordinates":[7.4514331818,46.9478492737],"type":"Point"}
}