{
  "type": "Feature",
  "properties": {
    "addr:full":"Oberdorf 19 Rafz Z\u00fcrich 8197",
    "addr:housenumber":"19",
    "addr:postcode":"8197",
    "addr:street":"Oberdorf",
    "iso:country":"CH",
    "sg:address":"Oberdorf 19",
    "sg:city":"Rafz",
    "sg:orig_category":"Autoelektro and -elektronik Werkst\u00e4tten Autogaragen",
    "sg:phone":"+41 33 336 14 44",
    "sg:postcode":"8197",
    "sg:province":"Z\u00fcrich",
    "wof:name":"Hugo Wenger Autoelektro-service & Garage",
    "wof:placetype":"venue"
},
  "geometry": {"coordinates":[7.627005,46.731274],"type":"Point"}
}