{
  "type": "Feature",
  "properties": {
    "iso:country":"CH",
    "sg:address":"Rue De La Sagnette 8 2710 Tavannes. Postfach",
    "sg:city":"Tavannes",
    "sg:orig_category":"Non-Classified Establishments",
    "sg:postcode":"2710",
    "sg:province":"Bern",
    "wof:name":"Rolog S\u00e0rl",
    "wof:placetype":"venue"
},
  "geometry": {"coordinates":[7.1951489449,47.2222671509],"type":"Point"}
}