{
  "type": "Feature",
  "properties": {
    "iso:country":"CH",
    "sg:address":"Res. Pian Scairolo 1",
    "sg:city":"Grancia",
    "sg:orig_category":"Detailhandel mit Bekleidung",
    "sg:postcode":"6916",
    "sg:province":"Ticino",
    "wof:name":"Wild Berry Sa",
    "wof:placetype":"venue"
},
  "geometry": {"coordinates":[8.925066,45.966976],"type":"Point"}
}