{
  "type": "Feature",
  "properties": {
    "iso:country":"CH",
    "sg:address":"Kirchgasse 13",
    "sg:city":"Ettingen",
    "sg:orig_category":"Erschliessung von Grundst\u00fccken",
    "sg:postcode":"4107",
    "sg:province":"Basel-Landschaft",
    "wof:name":"Swe Stiftung F\u00fcr Wohnungsbau Ettingen",
    "wof:placetype":"venue"
},
  "geometry": {"coordinates":[7.54271698,47.4801445007],"type":"Point"}
}