{
  "type": "Feature",
  "properties": {
    "iso:country":"CH",
    "sg:address":"Marktstrasse 6 2540 Grenchen. Postfach 974",
    "sg:city":"Grenchen",
    "sg:orig_category":"Detailhandel mit Brot, Back U S\u00fcsswaren RESTAURANTS: TEA-ROOMS",
    "sg:phone":"+41 32 652 26 46",
    "sg:postcode":"2540",
    "sg:province":"Solothurn",
    "wof:name":"Ivo Brotschi Confiserie",
    "wof:placetype":"venue"
},
  "geometry": {"coordinates":[7.397706,47.193573],"type":"Point"}
}