{
  "type": "Feature",
  "properties": {
    "iso:country":"CH",
    "sg:address":"Schulstrasse 4",
    "sg:city":"Schlieren",
    "sg:orig_category":"Allgemeiner Hoch U Tiefbau",
    "sg:phone":"+41 17732244",
    "sg:postcode":"8952",
    "sg:province":"Z\u00fcrich",
    "wof:name":"Siegfried Bau Ag",
    "wof:placetype":"venue"
},
  "geometry": {"coordinates":[8.44874,47.396198],"type":"Point"}
}