{
  "type": "Feature",
  "properties": {
    "iso:country":"CH",
    "sg:address":"Lindenrainweg 1a 3324 Hindelbank. Postfach",
    "sg:city":"Hindelbank",
    "sg:orig_category":"Maler U Glasergewerbe",
    "sg:postcode":"3324",
    "sg:province":"Bern",
    "wof:name":"Malerei + Gipserei Wittwer",
    "wof:placetype":"venue"
},
  "geometry": {"coordinates":[7.5377278328,47.0412101746],"type":"Point"}
}