{
  "type": "Feature",
  "properties": {
    "iso:country":"CH",
    "sg:address":"Rue De Temple 1 2738 Court. Postfach",
    "sg:city":"Court",
    "sg:orig_category":"Wohnheime",
    "sg:postcode":"2738",
    "sg:province":"Bern",
    "wof:name":"Home La Fontaine Jacques-alain Lehmann",
    "wof:placetype":"venue"
},
  "geometry": {"coordinates":[7.3365769386,47.2393951416],"type":"Point"}
}