{
  "type": "Feature",
  "properties": {
    "iso:country":"CH",
    "sg:address":"Dorf 758",
    "sg:city":"Hundwil",
    "sg:orig_category":"Sportvereine Eissport Schlittschuh",
    "sg:phone":"+41 71 368 50 80",
    "sg:postcode":"9064",
    "sg:province":"Appenzell Ausserrhoden",
    "wof:name":"Eisclub St.gallen",
    "wof:placetype":"venue"
},
  "geometry": {"coordinates":[9.3177967072,47.3635864258],"type":"Point"}
}