{
  "type": "Feature",
  "properties": {
    "iso:country":"CH",
    "sg:address":"Bergstrasse 38 8280 Kreuzlingen. Postfach",
    "sg:city":"Kreuzlingen",
    "sg:orig_category":"Grosshandel mit Eisenwaren sowie Installationsbedarf f\u00fcr Gas, Wasser U Heizung Handelsvermittlung U ",
    "sg:phone":"+41 71 671 20 60",
    "sg:postcode":"8280",
    "sg:province":"Thurgau",
    "wof:name":"Schl\u00e4pfer + Partner Gmbh",
    "wof:placetype":"venue"
},
  "geometry": {"coordinates":[9.1673145294,47.6416778564],"type":"Point"}
}