{
  "type": "Feature",
  "properties": {
    "iso:country":"CH",
    "sg:address":"Lettenring 21",
    "sg:city":"D\u00e4nikon",
    "sg:classifiers":[
        {
            "category":"Professional",
            "subcategory":"Art Services",
            "type":"Services"
        }
    ],
    "sg:phone":"+41 18847071",
    "sg:postcode":"8114",
    "sg:province":"Z\u00fcrich",
    "sg:tags":[
        "product",
        "design"
    ],
    "wof:name":"A-s-m Advanced-sano-marketing",
    "wof:placetype":"venue"
},
  "geometry": {"coordinates":[8.409877,47.445427],"type":"Point"}
}