{
  "type": "Feature",
  "properties": {
    "iso:country":"CH",
    "sg:address":"Via Al Nido 7 6900 Lugano. Postfach",
    "sg:city":"Lugano",
    "sg:orig_category":"Markt U Meinungsforschung",
    "sg:postcode":"6900",
    "sg:province":"Ticino",
    "wof:name":"Publistudio Di Bianca Semeria",
    "wof:placetype":"venue"
},
  "geometry": {"coordinates":[8.9429826736,46.0072250366],"type":"Point"}
}