{
  "type": "Feature",
  "properties": {
    "iso:country":"CH",
    "sg:address":"Hauptstrasse",
    "sg:city":"Rohrbach",
    "sg:orig_category":"Detailhandel mit Fleisch U Fleischwaren Grosshandel mit lebenden Tieren",
    "sg:phone":"+41 62 965 13 19",
    "sg:postcode":"4938",
    "sg:province":"Bern",
    "wof:name":"Rudolf Appenzeller Metzgerei & Viehhandel",
    "wof:placetype":"venue"
},
  "geometry": {"coordinates":[7.8223772049,47.130405426],"type":"Point"}
}