{
  "type": "Feature",
  "properties": {
    "iso:country":"CH",
    "sg:address":"Via Nassa 21",
    "sg:city":"Lugano",
    "sg:orig_category":"Arztpraxen",
    "sg:phone":"+41 91 923 48 75",
    "sg:postcode":"6900",
    "sg:province":"Ticino",
    "wof:name":"Dott.med.stefano Ermanni Specialista Fmh",
    "wof:placetype":"venue"
},
  "geometry": {"coordinates":[8.949594,46.001686],"type":"Point"}
}