{
  "type": "Feature",
  "properties": {
    "iso:country":"CH",
    "sg:address":"Chemin Pr\u00e9-olivier.",
    "sg:city":"Versoix",
    "sg:orig_category":"Sonstiger spezialisierter Hoch U Tiefbau",
    "sg:phone":"+41 22 755 46 13",
    "sg:postcode":"1290",
    "sg:province":"Gen\u00e8ve",
    "wof:name":"Sharp Michael.",
    "wof:placetype":"venue"
},
  "geometry": {"coordinates":[6.1671500206,46.280292511],"type":"Point"}
}