{
  "type": "Feature",
  "properties": {
    "addr:full":"Hauptstrasse 158 Ormalingen Basel-Landschaft 4466",
    "addr:housenumber":"158",
    "addr:postcode":"4466",
    "addr:street":"Hauptstrasse",
    "iso:country":"CH",
    "sg:address":"Hauptstrasse 158",
    "sg:city":"Ormalingen",
    "sg:orig_category":"Blumen U Zierpflanzenbau Grosshandel mit Blumen U Pflanzen",
    "sg:phone":"+41 61 981 46 59",
    "sg:postcode":"4466",
    "sg:province":"Basel-Landschaft",
    "wof:name":"Blumen Schaffner Ag Ormalingen",
    "wof:placetype":"venue"
},
  "geometry": {"coordinates":[7.873425,47.469513],"type":"Point"}
}