{
  "type": "Feature",
  "properties": {
    "iso:country":"CH",
    "sg:address":"Ringstrasse 39 4600 Olten. Postfach",
    "sg:city":"Olten",
    "sg:orig_category":"RESTAURANTS: TEA-ROOMS",
    "sg:phone":"+41 62 212 22 14",
    "sg:postcode":"4600",
    "sg:province":"Solothurn",
    "wof:name":"Baumann Karoline Und Edwin",
    "wof:placetype":"venue"
},
  "geometry": {"coordinates":[7.8994150162,47.3508033752],"type":"Point"}
}