{
  "type": "Feature",
  "properties": {
    "addr:full":"Badenerstrasse 18 8004 Z\u00fcrich. Postfach Z\u00fcrich Z\u00fcrich 8026",
    "addr:housenumber":"18",
    "addr:postcode":"8004 zuerich. postfach;8026",
    "addr:street":"Badenerstrasse",
    "iso:country":"CH",
    "sg:address":"Badenerstrasse 18 8004 Z\u00fcrich. Postfach",
    "sg:city":"Z\u00fcrich",
    "sg:orig_category":"Bauingenieurb\u00fcros Hochbau Bauingenieurb\u00fcros allgemein",
    "sg:phone":"+41 12412230",
    "sg:postcode":"8026",
    "sg:province":"Z\u00fcrich",
    "wof:name":"Knecht & W\u00fcrmli Beratende Ingenieure Asic",
    "wof:placetype":"venue"
},
  "geometry": {"coordinates":[8.53038,47.373631],"type":"Point"}
}