{
  "type": "Feature",
  "properties": {
    "iso:country":"CH",
    "sg:address":"Route De Rougemont 9",
    "sg:city":"Soral",
    "sg:orig_category":"Rebbau",
    "sg:phone":"+41 22 756 12 00",
    "sg:postcode":"1286",
    "sg:province":"Gen\u00e8ve",
    "wof:name":"Georges Th\u00e9venoz Viticulteur",
    "wof:placetype":"venue"
},
  "geometry": {"coordinates":[6.0445427895,46.1440811157],"type":"Point"}
}