{
  "type": "Feature",
  "properties": {
    "iso:country":"CH",
    "sg:address":"Schulstrasse 46",
    "sg:city":"Ilanz",
    "sg:orig_category":"Detailhandel mit Antiquit\u00e4ten Reparatur von Uhren U Schmuck",
    "sg:phone":"+41 79 449 37 00",
    "sg:postcode":"7130",
    "sg:province":"Graubunden",
    "wof:name":"Jean Zurbuchen Aux Antiquit\u00e9s D'horlogerie",
    "wof:placetype":"venue"
},
  "geometry": {"coordinates":[6.829373,47.10107],"type":"Point"}
}