{
  "type": "Feature",
  "properties": {
    "iso:country":"CH",
    "sg:address":"Baslerstrasse 5080 Laufenburg. Postfach 8",
    "sg:city":"Laufenburg",
    "sg:orig_category":"Elektrizit\u00e4tsversorgung",
    "sg:postcode":"5080",
    "sg:province":"Aargau",
    "wof:name":"Energiekorporation R\u00e4tia.",
    "wof:placetype":"venue"
},
  "geometry": {"coordinates":[9.5652751923,46.9360046387],"type":"Point"}
}