{
  "type": "Feature",
  "properties": {
    "iso:country":"CH",
    "sg:address":"Dorfstrasse 10",
    "sg:city":"Oberramsern",
    "sg:orig_category":"RESTAURANTS: TEA-ROOMS",
    "sg:postcode":"4588",
    "sg:province":"Solothurn",
    "wof:name":"Hofer-lehmann Erika",
    "wof:placetype":"venue"
},
  "geometry": {"coordinates":[7.4652919769,47.1149559021],"type":"Point"}
}