{
  "type": "Feature",
  "properties": {
    "iso:country":"CH",
    "sg:address":"Favre Rue Louis- 26 2000 Neuenburg. Postfach",
    "sg:city":"Neuch\u00e2tel",
    "sg:orig_category":"Maler U Glasergewerbe",
    "sg:phone":"+41 32 753 08 00",
    "sg:postcode":"2000",
    "sg:province":"Neuch\u00e2tel",
    "wof:name":"Forma Peinture Fortis Entreprise De Peinture, Papier Peints Etc",
    "wof:placetype":"venue"
},
  "geometry": {"coordinates":[6.9304628372,46.9949913025],"type":"Point"}
}