{
  "type": "Feature",
  "properties": {
    "iso:country":"CH",
    "sg:address":"Buchacker 52 3429 H\u00f6chstetten. Postfach",
    "sg:city":"Hellsau",
    "sg:orig_category":"Herstellung von Karosserien U Anh\u00e4ngern",
    "sg:phone":"+41 34 413 21 71",
    "sg:postcode":"3429",
    "sg:province":"Bern",
    "wof:name":"Hyundai Center H.ruch",
    "wof:placetype":"venue"
},
  "geometry": {"coordinates":[7.639154911,47.143409729],"type":"Point"}
}