{
  "type": "Feature",
  "properties": {
    "iso:country":"CH",
    "sg:address":"Hauptstrasse 8",
    "sg:city":"Langenbruck",
    "sg:classifiers":[
        {
            "category":"Travel",
            "subcategory":"Hotels & Motels",
            "type":"Entertainment"
        }
    ],
    "sg:phone":"+41 62 390 12 12",
    "sg:postcode":"4438",
    "sg:province":"Basel-Landschaft",
    "sg:tags":[
        "hotels",
        "mit",
        "restaurant"
    ],
    "wof:name":"Hotel Frohsinn",
    "wof:placetype":"venue"
},
  "geometry": {"coordinates":[7.769466877,47.3468666077],"type":"Point"}
}