{
  "type": "Feature",
  "properties": {
    "iso:country":"CH",
    "sg:address":"Langhagweg 47.",
    "sg:city":"Laufen",
    "sg:orig_category":"Instandhaltung U Reparatur von Automobilen",
    "sg:phone":"+41 79 215 78 78",
    "sg:postcode":"4242",
    "sg:province":"Basel-Landschaft",
    "wof:name":"Carrosserie Imhof.",
    "wof:placetype":"venue"
},
  "geometry": {"coordinates":[7.5060667992,47.4179229736],"type":"Point"}
}