{
  "type": "Feature",
  "properties": {
    "addr:full":"Freier Platz 3 8207 Schaffhausen. Postfach Schaffhausen Schaffhausen 8207",
    "addr:housenumber":"3",
    "addr:postcode":"8207 schaffhausen. postfach;8207",
    "addr:street":"Freier Platz",
    "iso:country":"CH",
    "sg:address":"Freier Platz 3 8207 Schaffhausen. Postfach",
    "sg:city":"Schaffhausen",
    "sg:orig_category":"Betrieb von Taxis G\u00fcterbef\u00f6rderung im Strassenverkehr",
    "sg:phone":"+41 52 624 40 00",
    "sg:postcode":"8207",
    "sg:province":"Schaffhausen",
    "wof:name":"Vito Reisen + Transporte Ag",
    "wof:placetype":"venue"
},
  "geometry": {"coordinates":[8.640547,47.695549],"type":"Point"}
}