{
  "type": "Feature",
  "properties": {
    "iso:country":"CH",
    "sg:address":"Espistr. 457",
    "sg:city":"Schneisingen",
    "sg:orig_category":"Unternehmensberatung",
    "sg:postcode":"5425",
    "sg:province":"Aargau",
    "wof:name":"Kaelin Oscar & Partner",
    "wof:placetype":"venue"
},
  "geometry": {"coordinates":[8.3536996841,47.5213394165],"type":"Point"}
}