{
  "type": "Feature",
  "properties": {
    "iso:country":"CH",
    "sg:address":"Dorfstrasse 14",
    "sg:city":"Wettingen",
    "sg:orig_category":"RESTAURANTS: TEA-ROOMS",
    "sg:postcode":"5430",
    "sg:province":"Aargau",
    "wof:name":"Joh. Brun",
    "wof:placetype":"venue"
},
  "geometry": {"coordinates":[8.3297538757,47.4669189453],"type":"Point"}
}