{
  "type": "Feature",
  "properties": {
    "iso:country":"CH",
    "sg:address":"Bahnhofstrasse 11",
    "sg:city":"B\u00fclach",
    "sg:classifiers":[
        {
            "category":"Professional",
            "subcategory":"Employment Agencies",
            "type":"Services"
        }
    ],
    "sg:phone":"+41 18863200",
    "sg:postcode":"8180",
    "sg:province":"Z\u00fcrich",
    "sg:tags":[
        "personal",
        "u",
        "stellenvermittlung"
    ],
    "wof:name":"Actuel Job Personalberatung Furrer & Partner",
    "wof:placetype":"venue"
},
  "geometry": {"coordinates":[8.5399227142,47.5201454163],"type":"Point"}
}