{
  "type": "Feature",
  "properties": {
    "iso:country":"CH",
    "sg:address":"Impasse Pra D'amont 1a 1753 Matran. Postfach",
    "sg:city":"Matran",
    "sg:orig_category":"Non-Classified Establishments",
    "sg:postcode":"1753",
    "sg:province":"Fribourg",
    "wof:name":"Schenkel A. Communication",
    "wof:placetype":"venue"
},
  "geometry": {"coordinates":[7.0887098312,46.7851715088],"type":"Point"}
}