{
  "type": "Feature",
  "properties": {
    "addr:full":"Bahnhofstr. 23 Brugg Aargau 5200",
    "addr:housenumber":"23",
    "addr:postcode":"5200",
    "addr:street":"Bahnhofstr.",
    "iso:country":"CH",
    "sg:address":"Bahnhofstr. 23",
    "sg:city":"Brugg",
    "sg:classifiers":[
        {
            "category":"Banks & Credit Unions",
            "subcategory":"Bank",
            "type":"Services"
        }
    ],
    "sg:phone":"+41 56 619 95 11",
    "sg:postcode":"5200",
    "sg:province":"Aargau",
    "wof:name":"Aargauische Kantonalbank",
    "wof:placetype":"venue"
},
  "geometry": {"coordinates":[8.272479,47.349735],"type":"Point"}
}