{
  "type": "Feature",
  "properties": {
    "iso:country":"CH",
    "sg:address":"Oberwiesenstrasse 5 8304 Wallisellen. Postfach 189",
    "sg:city":"Wallisellen",
    "sg:orig_category":"Herstellung von Farbstoffen U Pigmenten Herstellung von sonstigen Metallwaren",
    "sg:phone":"+41 18302004",
    "sg:postcode":"8304",
    "sg:province":"Z\u00fcrich",
    "wof:name":"Signal Ag",
    "wof:placetype":"venue"
},
  "geometry": {"coordinates":[8.5885877609,47.4121704102],"type":"Point"}
}