{
  "type": "Feature",
  "properties": {
    "iso:country":"CH",
    "sg:address":"Ried",
    "sg:city":"Gibswil-ried",
    "sg:orig_category":"Sportvereine Sch\u00fctzen Armbrust",
    "sg:phone":"+41 18187745",
    "sg:postcode":"8498",
    "sg:province":"Z\u00fcrich",
    "wof:name":"Armbrustsch\u00fctzenverein R\u00fcmlang",
    "wof:placetype":"venue"
},
  "geometry": {"coordinates":[8.4335775375,47.4614143372],"type":"Point"}
}