{
  "type": "Feature",
  "properties": {
    "iso:country":"CH",
    "sg:address":"Hauptstrase 94",
    "sg:city":"L\u00f6hningen",
    "sg:orig_category":"Institutionen f\u00fcr Behinderte",
    "sg:phone":"+41 71 642 48 65",
    "sg:postcode":"8224",
    "sg:province":"Schaffhausen",
    "wof:name":"Haus Miranda Sozialtherapeut. Lebensgemeinschaft",
    "wof:placetype":"venue"
},
  "geometry": {"coordinates":[9.1888065338,47.5717964172],"type":"Point"}
}