{
  "type": "Feature",
  "properties": {
    "iso:country":"CH",
    "sg:address":"Unterm\u00fcli 7",
    "sg:city":"Zug",
    "sg:orig_category":"Sonstige mit dem Kreditgewerbe verbundene T\u00e4tigkeiten",
    "sg:phone":"+41 41 760 11 61",
    "sg:postcode":"6300",
    "sg:province":"Zug",
    "wof:name":"Institutional Investment Research Ag",
    "wof:placetype":"venue"
},
  "geometry": {"coordinates":[8.5177021027,47.1804161072],"type":"Point"}
}