{
  "type": "Feature",
  "properties": {
    "iso:country":"CH",
    "sg:address":"Eschenrain 15a",
    "sg:city":"Steinhausen",
    "sg:orig_category":"Maler U Glasergewerbe",
    "sg:phone":"+41 41 741 25 15",
    "sg:postcode":"6312",
    "sg:province":"Zug",
    "wof:name":"Wyss Erich Ag",
    "wof:placetype":"venue"
},
  "geometry": {"coordinates":[8.4923448563,47.1972618103],"type":"Point"}
}