{
  "type": "Feature",
  "properties": {
    "iso:country":"CH",
    "sg:address":"Contrada Cavenue Pellanda 9",
    "sg:city":"Biasca",
    "sg:orig_category":"Arztpraxen",
    "sg:phone":"+41 91 827 43 44",
    "sg:postcode":"6710",
    "sg:province":"Ticino",
    "wof:name":"Dott.med. Daniele T\u00f6nz Specialista",
    "wof:placetype":"venue"
},
  "geometry": {"coordinates":[9.12836,46.237598],"type":"Point"}
}