{
  "type": "Feature",
  "properties": {
    "iso:country":"CH",
    "sg:address":"Bachtalenweg 3",
    "sg:city":"Zeiningen",
    "sg:orig_category":"Maler U Glasergewerbe Tapeziererei",
    "sg:phone":"+41 61 851 45 26",
    "sg:postcode":"4314",
    "sg:province":"Aargau",
    "wof:name":"Rolf Guthauser Malergesch\u00e4ft",
    "wof:placetype":"venue"
},
  "geometry": {"coordinates":[7.8685879707,47.5405387878],"type":"Point"}
}