{
  "type": "Feature",
  "properties": {
    "addr:full":"Dienerstrasse 36 Z\u00fcrich Z\u00fcrich 8004",
    "addr:housenumber":"36",
    "addr:postcode":"8004",
    "addr:street":"Dienerstrasse",
    "iso:country":"CH",
    "sg:address":"Dienerstrasse 36",
    "sg:city":"Z\u00fcrich",
    "sg:orig_category":"Detailhandel mit Damenbekleidung",
    "sg:phone":"+41 12414321",
    "sg:postcode":"8004",
    "sg:province":"Z\u00fcrich",
    "wof:name":"Better Bodies Shop",
    "wof:placetype":"venue"
},
  "geometry": {"coordinates":[8.527495,47.378399],"type":"Point"}
}