{
  "type": "Feature",
  "properties": {
    "iso:country":"CH",
    "sg:address":"Marktgasse 18",
    "sg:city":"St.gallen",
    "sg:orig_category":"Grosshandel mit Textilien",
    "sg:postcode":"9000",
    "sg:province":"St. Gallen",
    "wof:name":"Carosella & Co Textil",
    "wof:placetype":"venue"
},
  "geometry": {"coordinates":[9.3762512207,47.4251976013],"type":"Point"}
}