{
  "type": "Feature",
  "properties": {
    "iso:country":"CH",
    "sg:address":"Gewerbeweg 14 9490 Vaduz. Postfach 81",
    "sg:city":"Vaduz",
    "sg:orig_category":"Regelm\u00e4ssige Personenbef\u00f6rderung im Fernverkehr",
    "sg:phone":"+423 232 81 33",
    "sg:postcode":"9490",
    "wof:name":"Otto Frommelt Anstalt Postautounternehmen",
    "wof:placetype":"venue"
},
  "geometry": {"coordinates":[9.5226240158,47.124671936],"type":"Point"}
}