{
  "type": "Feature",
  "properties": {
    "iso:country":"CH",
    "sg:address":"St. Gallerstrasse 120",
    "sg:city":"Jona",
    "sg:orig_category":"Detailhandel Fachdetailhandel in Verkaufsr\u00e4umen Reparatur von Gebrauchsg\u00fctern",
    "sg:phone":"+41 55 216 25 55",
    "sg:postcode":"8645",
    "sg:province":"St. Gallen",
    "wof:name":"Beate Uhse Erotik-megastore",
    "wof:placetype":"venue"
},
  "geometry": {"coordinates":[8.8489217758,47.2299308777],"type":"Point"}
}