{
  "type": "Feature",
  "properties": {
    "iso:country":"CH",
    "sg:address":"3913",
    "sg:city":"Rosswald",
    "sg:orig_category":"Detailhandel mit Waren verschiedener Art, Hauptrichtung Nahrungsmittel",
    "sg:phone":"+41 22 361 22 12",
    "sg:postcode":"3913",
    "sg:province":"Valais",
    "wof:name":"Ir\u00e8ne Castellini Produits D'italie",
    "wof:placetype":"venue"
},
  "geometry": {"coordinates":[6.2376990318,46.3823661804],"type":"Point"}
}