{
  "type": "Feature",
  "properties": {
    "iso:country":"CH",
    "sg:address":"Via Crena",
    "sg:city":"Comano",
    "sg:orig_category":"Allgemeiner Hoch U Tiefbau Hoch U Tiefbau",
    "sg:phone":"+41 91 942 75 29",
    "sg:postcode":"6949",
    "sg:province":"Ticino",
    "wof:name":"Giuseppe Pietra Impresa Costruzioni",
    "wof:placetype":"venue"
},
  "geometry": {"coordinates":[8.958835,46.039406],"type":"Point"}
}