{
  "type": "Feature",
  "properties": {
    "iso:country":"CH",
    "sg:address":"Rue De L'avenir 12",
    "sg:city":"Del\u00e9mont",
    "sg:orig_category":"Unclassifiable Establishments",
    "sg:postcode":"2800",
    "sg:province":"Jura",
    "wof:name":"Baltremo Holding Sa",
    "wof:placetype":"venue"
},
  "geometry": {"coordinates":[7.3490409851,47.3645515442],"type":"Point"}
}