{
  "type": "Feature",
  "properties": {
    "iso:country":"CH",
    "sg:address":"Rue De La Croix-d'or 3",
    "sg:city":"Hauterive",
    "sg:orig_category":"Rebbau Wein Detailhandel",
    "sg:phone":"+41 21 946 17 39",
    "sg:postcode":"2068",
    "sg:province":"Neuch\u00e2tel",
    "wof:name":"Daniel Rogivue",
    "wof:placetype":"venue"
},
  "geometry": {"coordinates":[7.0218009949,46.9203529358],"type":"Point"}
}