{
  "type": "Feature",
  "properties": {
    "iso:country":"CH",
    "sg:address":"Rue De L'h\u00f4pital 19",
    "sg:city":"Neuch\u00e2tel",
    "sg:orig_category":"Drogerien",
    "sg:phone":"+41 32 725 24 52",
    "sg:postcode":"2000",
    "sg:province":"Neuch\u00e2tel",
    "wof:name":"Droguerie Schneitter",
    "wof:placetype":"venue"
},
  "geometry": {"coordinates":[6.941450119,46.9826812744],"type":"Point"}
}