{
  "type": "Feature",
  "properties": {
    "iso:country":"CH",
    "sg:address":"Grange-\u00e0-janin",
    "sg:city":"Villars-le-terroir",
    "sg:orig_category":"Interessenvertretungen",
    "sg:postcode":"1040",
    "sg:province":"Vaud",
    "wof:name":"Association Suisse Pour Les Enfants Pr\u00e9coces Aider Les Parents Et Les Professionnels De L'\u00e9ducation \u00e0 D\u00e9tecter Les Enfants Intellect. Pr\u00e9coces, Prom. Une \u00e9ducation Adapt\u00e9e \u00e0 Ces Enfants",
    "wof:placetype":"venue"
},
  "geometry": {"coordinates":[6.6426448822,46.6537857056],"type":"Point"}
}