{
  "type": "Feature",
  "properties": {
    "iso:country":"CH",
    "sg:address":"Schwerzistrasse 6",
    "sg:city":"Freienbach",
    "sg:classifiers":[
        {
            "category":"Manufacturing",
            "subcategory":"Wood Products",
            "type":"Manufacturing & Wholesale Goods"
        }
    ],
    "sg:phone":"+41 55 415 41 41",
    "sg:postcode":"8807",
    "sg:province":"Schwyz",
    "sg:tags":[
        "made",
        "display"
    ],
    "wof:name":"Lomb Art Ag",
    "wof:placetype":"venue"
},
  "geometry": {"coordinates":[8.7587518692,47.2014312744],"type":"Point"}
}