{
  "type": "Feature",
  "properties": {
    "iso:country":"CH",
    "sg:address":"Sonnenhofstrasse 3",
    "sg:city":"Hochfelden",
    "sg:orig_category":"Dachdeckerei Zimmerei, Dachdeckerei, Bauspenglerei U Abdichtung",
    "sg:phone":"+41 79 456 89 41",
    "sg:postcode":"8182",
    "sg:province":"Z\u00fcrich",
    "wof:name":"Renggli R. Isolier-bau Ag",
    "wof:placetype":"venue"
},
  "geometry": {"coordinates":[8.20601,47.11536],"type":"Point"}
}