{
  "type": "Feature",
  "properties": {
    "iso:country":"CH",
    "sg:address":"Riedhofstrasse 277",
    "sg:city":"Z\u00fcrich",
    "sg:orig_category":"Sanit\u00e4r, Heizungs U L\u00fcftungsinstallation Sanit\u00e4rinstallation",
    "sg:phone":"+41 13419880",
    "sg:postcode":"8049",
    "sg:province":"Z\u00fcrich",
    "wof:name":"W. Greb, Sanit\u00e4re Anlagen, Inhaber Kurt Greb",
    "wof:placetype":"venue"
},
  "geometry": {"coordinates":[8.4863729477,47.4068450928],"type":"Point"}
}