{
  "type": "Feature",
  "properties": {
    "iso:country":"CH",
    "sg:address":"Weierstrasse 11",
    "sg:city":"St\u00e4fa",
    "sg:orig_category":"Herstellung von sonstigen chemischen Erzeugnissen",
    "sg:phone":"+41 19267777",
    "sg:postcode":"8712",
    "sg:province":"Z\u00fcrich",
    "wof:name":"Ehrensperger Pageris Ag",
    "wof:placetype":"venue"
},
  "geometry": {"coordinates":[8.735657692,47.2374725342],"type":"Point"}
}