{
  "type": "Feature",
  "properties": {
    "iso:country":"CH",
    "sg:address":"Peney Le Jorat",
    "sg:city":"Peney Le Jorat",
    "sg:classifiers":[
        {
            "category":"Banks & Credit Unions",
            "subcategory":"Bank",
            "type":"Services"
        }
    ],
    "sg:phone":"+41 21 903 30 90",
    "sg:postcode":"1059",
    "sg:province":"Vaud",
    "wof:name":"Banque Raiffeisen",
    "wof:placetype":"venue"
},
  "geometry": {"coordinates":[6.73002,46.63269],"type":"Point"}
}