{
  "type": "Feature",
  "properties": {
    "addr:full":"R\u00fcttihubelbad 3512 Walkringen. Postfach 44 Walkringen Bern 3512",
    "addr:housenumber":"44",
    "addr:postcode":"3512 walkringen.;3512",
    "addr:street":"Postfach;Bern",
    "iso:country":"CH",
    "sg:address":"R\u00fcttihubelbad 3512 Walkringen. Postfach 44",
    "sg:city":"Walkringen",
    "sg:orig_category":"Alters U Pflegeheime Institutionen f\u00fcr Behinderte",
    "sg:phone":"+41 31 700 81 81",
    "sg:postcode":"3512",
    "sg:province":"Bern",
    "wof:name":"Alterswohn-& Pflegeheim Friedrich Eymann-haus",
    "wof:placetype":"venue"
},
  "geometry": {"coordinates":[7.599446,46.940098],"type":"Point"}
}