{
  "type": "Feature",
  "properties": {
    "iso:country":"CH",
    "sg:address":"Avenue De Lonay 23",
    "sg:city":"Morges",
    "sg:orig_category":"Schlossereien",
    "sg:phone":"+41 22 342 56 46",
    "sg:postcode":"1110",
    "sg:province":"Vaud",
    "wof:name":"Marcel Beck Cl\u00e9-carouge",
    "wof:placetype":"venue"
},
  "geometry": {"coordinates":[6.1394500732,46.1843643188],"type":"Point"}
}