{
  "type": "Feature",
  "properties": {
    "iso:country":"CH",
    "sg:address":"Unterstrasse 23",
    "sg:city":"Herzogenbuchsee",
    "sg:classifiers":[
        {
            "category":"Restaurant",
            "type":"Food & Drink"
        }
    ],
    "sg:phone":"+41 62 961 25 25",
    "sg:postcode":"3360",
    "sg:province":"Bern",
    "wof:name":"Restaurant Jura",
    "wof:placetype":"venue"
},
  "geometry": {"coordinates":[7.7029781342,47.189994812],"type":"Point"}
}