{
  "type": "Feature",
  "properties": {
    "iso:country":"CH",
    "sg:address":"B\u00fcchelistrasse 9a",
    "sg:city":"Liestal",
    "sg:orig_category":"D\u00e4mmung gegen K\u00e4lte, W\u00e4rme, Schall U Ersch\u00fctterung Malerei",
    "sg:phone":"+41 61 911 91 76",
    "sg:postcode":"4410",
    "sg:province":"Basel-Landschaft",
    "wof:name":"Andr\u00e9 Schreiber Ag Malergesch\u00e4ft",
    "wof:placetype":"venue"
},
  "geometry": {"coordinates":[7.7364339828,47.4834518433],"type":"Point"}
}