{
  "type": "Feature",
  "properties": {
    "iso:country":"CH",
    "sg:address":"8755 Ennenda. Postfach 111",
    "sg:city":"Ennenda",
    "sg:orig_category":"Sportschulen Fern\u00f6stliche Kampfsportarten Sportvereine Judo and Karate",
    "sg:postcode":"8755",
    "sg:province":"Glarus",
    "wof:name":"Js Yama Neko Ennenda",
    "wof:placetype":"venue"
},
  "geometry": {"coordinates":[9.078795433,47.0329093933],"type":"Point"}
}