{
  "type": "Feature",
  "properties": {
    "iso:country":"CH",
    "sg:address":"Place-d'armes Rue De La 3 2000 Neuch\u00e2tel. Postfach",
    "sg:city":"Neuenburg",
    "sg:orig_category":"Fachdetailhandel in Verkaufsr\u00e4umen",
    "sg:postcode":"2000",
    "sg:province":"Neuch\u00e2tel",
    "wof:name":"Sandoz Fr\u00e8res S.a.",
    "wof:placetype":"venue"
},
  "geometry": {"coordinates":[6.9302248955,46.9898376465],"type":"Point"}
}