{
  "type": "Feature",
  "properties": {
    "iso:country":"CH",
    "sg:address":"La Ciba 148",
    "sg:city":"Courtion",
    "sg:orig_category":"Verlegen von Fliesen U Platten",
    "sg:phone":"+41 26 476 03 00",
    "sg:postcode":"1721",
    "sg:province":"Fribourg",
    "wof:name":"Martial Lottas Lz Carrelage",
    "wof:placetype":"venue"
},
  "geometry": {"coordinates":[7.0689468384,46.8570098877],"type":"Point"}
}