{
  "type": "Feature",
  "properties": {
    "iso:country":"CH",
    "sg:address":"Oberlandstrasse 99",
    "sg:city":"Uster",
    "sg:orig_category":"Oberfl\u00e4chenveredlung U W\u00e4rmebehandlung",
    "sg:phone":"+41 19451134",
    "sg:postcode":"8610",
    "sg:province":"Z\u00fcrich",
    "wof:name":"N\u00fcssli W.",
    "wof:placetype":"venue"
},
  "geometry": {"coordinates":[8.7187566757,47.3526802063],"type":"Point"}
}