{
  "type": "Feature",
  "properties": {
    "iso:country":"CH",
    "sg:address":"Rue Des Voisins 20",
    "sg:city":"Gen\u00e8ve",
    "sg:orig_category":"Detailhandel mit Antiquit\u00e4ten Detailhandel mit M\u00f6beln",
    "sg:phone":"+41 22 329 00 75",
    "sg:postcode":"1205",
    "sg:province":"Gen\u00e8ve",
    "wof:name":"Edith Moor Antiquit\u00e9s Meubles Au Picpus",
    "wof:placetype":"venue"
},
  "geometry": {"coordinates":[6.144239,46.195473],"type":"Point"}
}