{
  "type": "Feature",
  "properties": {
    "iso:country":"CH",
    "sg:address":"M\u00fchleweg 7",
    "sg:city":"Steffisburg",
    "sg:orig_category":"Dienstleistungen im Gartenbau Elektroinstallation",
    "sg:phone":"+41 22 307 18 00",
    "sg:postcode":"3612",
    "sg:province":"Bern",
    "wof:name":"Iss Commultiservice Ag",
    "wof:placetype":"venue"
},
  "geometry": {"coordinates":[6.12774086,46.1870918274],"type":"Point"}
}