{
  "type": "Feature",
  "properties": {
    "addr:full":"Les Grandes Vignes Treycovagnes Vaud 1436",
    "addr:postcode":"1436",
    "addr:street":"Les Grandes Vignes",
    "iso:country":"CH",
    "sg:address":"Les Grandes Vignes",
    "sg:city":"Treycovagnes",
    "sg:orig_category":"Allgemeiner Hoch U Tiefbau",
    "sg:postcode":"1436",
    "sg:province":"Vaud",
    "wof:name":"Schaffner H. R. Fassadenplanungen + Bauleitungen",
    "wof:placetype":"venue"
},
  "geometry": {"coordinates":[8.268127,47.327068],"type":"Point"}
}