{
  "type": "Feature",
  "properties": {
    "iso:country":"CH",
    "sg:address":"Via Enrico Guisan 6",
    "sg:city":"Chiasso",
    "sg:orig_category":"Grosshandel mit pharmazeutischen Erzeugnissen Sanit\u00e4r, Heizungs U L\u00fcftungsinstallation",
    "sg:phone":"+41 91 683 69 88",
    "sg:postcode":"6830",
    "sg:province":"Ticino",
    "wof:name":"Sokosi Pharma Sa",
    "wof:placetype":"venue"
},
  "geometry": {"coordinates":[9.0221452713,45.8330726624],"type":"Point"}
}