{
  "type": "Feature",
  "properties": {
    "iso:country":"CH",
    "sg:address":"Chlosterweg 14",
    "sg:city":"Sch\u00fcpfheim",
    "sg:classifiers":[
        {
            "category":"Education",
            "subcategory":"Library",
            "type":"Public Place"
        }
    ],
    "sg:phone":"+41 31 332 47 50",
    "sg:postcode":"6170",
    "sg:province":"Luzern",
    "sg:tags":[
        "u",
        "bibliotheken",
        "archive"
    ],
    "wof:name":"Regionalbibliothek Bern Zweigstelle Breitenrain",
    "wof:placetype":"venue"
},
  "geometry": {"coordinates":[7.45501,46.959255],"type":"Point"}
}