{
  "type": "Feature",
  "properties": {
    "addr:full":"Rue De La Gare 2 Peseux Neuch\u00e2tel 2034",
    "addr:housenumber":"2",
    "addr:postcode":"2034",
    "addr:street":"Rue De La Gare;Neucha\u0302Tel",
    "iso:country":"CH",
    "sg:address":"Rue De La Gare 2",
    "sg:city":"Peseux",
    "sg:orig_category":"Bauschreinerei Herstellung von M\u00f6beln verschiedener Art",
    "sg:phone":"+41 71 983 27 33",
    "sg:postcode":"2034",
    "sg:province":"Neuch\u00e2tel",
    "wof:name":"Fraefel Ag Badezimmer M\u00f6bel",
    "wof:placetype":"venue"
},
  "geometry": {"coordinates":[9.061353,47.379608],"type":"Point"}
}