{
  "type": "Feature",
  "properties": {
    "iso:country":"CH",
    "sg:address":"Camping-park St. Tropez",
    "sg:city":"Vinelz",
    "sg:orig_category":"Campingpl\u00e4tze",
    "sg:postcode":"3234",
    "sg:province":"Bern",
    "wof:name":"Haefeli-bader K.",
    "wof:placetype":"venue"
},
  "geometry": {"coordinates":[7.109823,47.03529],"type":"Point"}
}