{
  "type": "Feature",
  "properties": {
    "iso:country":"CH",
    "sg:address":"Gare Place De La 11",
    "sg:city":"Nyon",
    "sg:orig_category":"Zahnarztpraxen",
    "sg:postcode":"1260",
    "sg:province":"Vaud",
    "wof:name":"Abcdent S\u00e0rl Cabinets Dentaires",
    "wof:placetype":"venue"
},
  "geometry": {"coordinates":[6.2390799522,46.3823661804],"type":"Point"}
}