{
  "type": "Feature",
  "properties": {
    "iso:country":"CH",
    "sg:address":"Via Principale 56",
    "sg:city":"Campocologno",
    "sg:orig_category":"Nationale Postdienste",
    "sg:phone":"+41 81 846 51 36",
    "sg:postcode":"7744",
    "sg:province":"Graubunden",
    "wof:name":"La Posta Svizzera",
    "wof:placetype":"venue"
},
  "geometry": {"coordinates":[10.1414909363,46.2340354919],"type":"Point"}
}