{
  "type": "Feature",
  "properties": {
    "iso:country":"CH",
    "sg:address":"S-chadatsch",
    "sg:city":"Strada",
    "sg:orig_category":"Verwaltung der Rechtspflege, Gerichte",
    "sg:phone":"+41 81 866 35 37",
    "sg:postcode":"7558",
    "sg:province":"Graubunden",
    "wof:name":"Kreisamt Ramosch",
    "wof:placetype":"venue"
},
  "geometry": {"coordinates":[10.4352025986,46.8624916077],"type":"Point"}
}