{
  "type": "Feature",
  "properties": {
    "iso:country":"CH",
    "sg:address":"Juchstrasse 10",
    "sg:city":"Magden",
    "sg:orig_category":"Verwaltung von Immobilien",
    "sg:phone":"+41 61 841 15 38",
    "sg:postcode":"4312",
    "sg:province":"Aargau",
    "wof:name":"H\u00fcrzeler Immobilien Ag",
    "wof:placetype":"venue"
},
  "geometry": {"coordinates":[7.8103909492,47.5298881531],"type":"Point"}
}