{
  "type": "Feature",
  "properties": {
    "iso:country":"CH",
    "sg:address":"Felsplattenstrasse 18",
    "sg:city":"Basel",
    "sg:orig_category":"Non-Classified Establishments",
    "sg:postcode":"4055",
    "sg:province":"Basel-Stadt",
    "wof:name":"Tschannen Consulting Ag, Zweigniederlassung In Basel",
    "wof:placetype":"venue"
},
  "geometry": {"coordinates":[7.561041832,47.5640563965],"type":"Point"}
}