{
  "type": "Feature",
  "properties": {
    "iso:country":"CH",
    "sg:address":"Im R\u00f6tel 10a 6300 Zug. Postfach 613",
    "sg:city":"Zug",
    "sg:orig_category":"Handels-H\u00e4user U Gesellschaften",
    "sg:postcode":"6300",
    "sg:province":"Zug",
    "wof:name":"Ita S\u00e0rl",
    "wof:placetype":"venue"
},
  "geometry": {"coordinates":[6.6814861298,46.5581054688],"type":"Point"}
}