{
  "type": "Feature",
  "properties": {
    "iso:country":"CH",
    "sg:address":"Via Plazzas 14",
    "sg:city":"Bonaduz",
    "sg:orig_category":"Architektur U Ingenieurb\u00fcros",
    "sg:phone":"+41 81 641 17 57",
    "sg:postcode":"7402",
    "sg:province":"Graubunden",
    "wof:name":"Bieler Walter Ag, Ingenieurb\u00fcro F\u00fcr Holzkonstruktionen",
    "wof:placetype":"venue"
},
  "geometry": {"coordinates":[9.405508,46.811382],"type":"Point"}
}