{
  "type": "Feature",
  "properties": {
    "iso:country":"CH",
    "sg:address":"Kirchenrainstrasse 27",
    "sg:city":"Tann",
    "sg:orig_category":"Massagestudios P\u00e9dicure",
    "sg:phone":"+41 55 240 44 71",
    "sg:postcode":"8632",
    "sg:province":"Z\u00fcrich",
    "wof:name":"Annelies Altorfer Massagen & Fusspflege",
    "wof:placetype":"venue"
},
  "geometry": {"coordinates":[8.850399971,47.2607345581],"type":"Point"}
}