{
  "type": "Feature",
  "properties": {
    "iso:country":"CH",
    "sg:address":"G\u00fcterstrasse 74",
    "sg:city":"Basel",
    "sg:orig_category":"Reparatur von Schuhen U Lederwaren",
    "sg:phone":"+41 61 271 57 67",
    "sg:postcode":"4053",
    "sg:province":"Basel-Stadt",
    "wof:name":"As Schuhe & Schl\u00fcsselservice Ahmet Selvi",
    "wof:placetype":"venue"
},
  "geometry": {"coordinates":[7.5842199326,47.5467681885],"type":"Point"}
}