{
  "type": "Feature",
  "properties": {
    "iso:country":"CH",
    "sg:address":"Garnmarkt 1 8400 Winterthur. Postfach",
    "sg:city":"Winterthur",
    "sg:orig_category":"Unclassifiable Establishments",
    "sg:postcode":"8400",
    "sg:province":"Z\u00fcrich",
    "wof:name":"Konrad Edmond, Successeur De Denisard L\u00e9opold",
    "wof:placetype":"venue"
},
  "geometry": {"coordinates":[5.1808700562,45.8973388672],"type":"Point"}
}