{
  "type": "Feature",
  "properties": {
    "iso:country":"CH",
    "sg:address":"Casa Da Scola",
    "sg:city":"Dardin",
    "sg:classifiers":[
        {
            "category":"Banks & Credit Unions",
            "subcategory":"Bank",
            "type":"Services"
        }
    ],
    "sg:phone":"+41 81 941 22 88",
    "sg:postcode":"7164",
    "sg:province":"Graubunden",
    "wof:name":"Raiffeisen",
    "wof:placetype":"venue"
},
  "geometry": {"coordinates":[9.049131,46.758362],"type":"Point"}
}