{
  "type": "Feature",
  "properties": {
    "addr:full":"Bahnhofstrasse 6 Kloten Z\u00fcrich 8302",
    "addr:housenumber":"6",
    "addr:postcode":"8302",
    "addr:street":"Bahnhofstrasse",
    "iso:country":"CH",
    "sg:address":"Bahnhofstrasse 6",
    "sg:city":"Kloten",
    "sg:orig_category":"Chemische Reinigung",
    "sg:phone":"+41 18141470",
    "sg:postcode":"8302",
    "sg:province":"Z\u00fcrich",
    "wof:name":"Willi Lirgg Kleenothek Textilreinigung",
    "wof:placetype":"venue"
},
  "geometry": {"coordinates":[8.582679,47.449074],"type":"Point"}
}