{
  "type": "Feature",
  "properties": {
    "iso:country":"CH",
    "sg:address":"Stanserstrasse",
    "sg:city":"Stansstad",
    "sg:classifiers":[
        {
            "category":"Manufacturing",
            "subcategory":"Wood Products",
            "type":"Manufacturing & Wholesale Goods"
        }
    ],
    "sg:phone":"+41 41 610 11 73",
    "sg:postcode":"6362",
    "sg:province":"Nidwalden",
    "sg:tags":[
        "lumber"
    ],
    "wof:name":"Murer Holzwerke Ag",
    "wof:placetype":"venue"
},
  "geometry": {"coordinates":[8.3412437439,46.9760055542],"type":"Point"}
}