{
  "type": "Feature",
  "properties": {
    "iso:country":"CH",
    "sg:address":"3968",
    "sg:city":"Veyras",
    "sg:orig_category":"Mechanik",
    "sg:phone":"+41 32 731 85 60",
    "sg:postcode":"3968",
    "sg:province":"Valais",
    "wof:name":"Ruvolo Luciano",
    "wof:placetype":"venue"
},
  "geometry": {"coordinates":[6.8612399101,46.98828125],"type":"Point"}
}