{
  "type": "Feature",
  "properties": {
    "iso:country":"CH",
    "sg:address":"1885",
    "sg:city":"Chesi\u00e8res",
    "sg:orig_category":"Vermietung von Automobilen",
    "sg:phone":"+41 24 495 24 40",
    "sg:postcode":"1885",
    "sg:province":"Vaud",
    "wof:name":"Jean-fran\u00e7ois Besson Garage",
    "wof:placetype":"venue"
},
  "geometry": {"coordinates":[7.0434799194,46.301109314],"type":"Point"}
}