{
  "type": "Feature",
  "properties": {
    "iso:country":"CH",
    "sg:address":"Velturrietstrasse 5",
    "sg:city":"Sevelen",
    "sg:orig_category":"Arztpraxen",
    "sg:phone":"+41 81 785 16 66",
    "sg:postcode":"9475",
    "sg:province":"St. Gallen",
    "wof:name":"Dr.med.thomas Metzler Arzt F.allgemeine Medizin Fmh",
    "wof:placetype":"venue"
},
  "geometry": {"coordinates":[9.489027,47.123734],"type":"Point"}
}