{
  "type": "Feature",
  "properties": {
    "iso:country":"CH",
    "sg:address":"Voa Principala 53",
    "sg:city":"Lenzerheide/lai",
    "sg:orig_category":"Detailhandel mit Geschenkartikeln U Souvenirs",
    "sg:phone":"+41 81 384 18 66",
    "sg:postcode":"7078",
    "sg:province":"Graubunden",
    "wof:name":"Boutique Burtscher",
    "wof:placetype":"venue"
},
  "geometry": {"coordinates":[9.5570726395,46.729183197],"type":"Point"}
}