{
  "type": "Feature",
  "properties": {
    "iso:country":"CH",
    "sg:address":"Via Parco 3",
    "sg:city":"Bellinzona",
    "sg:orig_category":"Unternehmensberatung",
    "sg:postcode":"6500",
    "sg:province":"Ticino",
    "wof:name":"Hunziker Eugen Business Promotion Engineering And Consulting Bp",
    "wof:placetype":"venue"
},
  "geometry": {"coordinates":[9.0192298889,46.1943283081],"type":"Point"}
}