{
  "type": "Feature",
  "properties": {
    "iso:country":"CH",
    "sg:address":"Untere Br\u00fchlstrasse 33",
    "sg:city":"Zofingen",
    "sg:orig_category":"Handel mit Automobilen",
    "sg:phone":"+41 62 751 99 11",
    "sg:postcode":"4800",
    "sg:province":"Aargau",
    "wof:name":"Haller Automobile",
    "wof:placetype":"venue"
},
  "geometry": {"coordinates":[7.9311628342,47.2964820862],"type":"Point"}
}