{
  "type": "Feature",
  "properties": {
    "iso:country":"CH",
    "sg:address":"Speerstr. 20",
    "sg:city":"Freienbach",
    "sg:orig_category":"Herstellung von sonstigen Maschinen f\u00fcr unspezifische Verwendung",
    "sg:postcode":"8807",
    "sg:province":"Schwyz",
    "wof:name":"Met Industrieanlagen Ag",
    "wof:placetype":"venue"
},
  "geometry": {"coordinates":[8.7327976227,47.1965484619],"type":"Point"}
}