{
  "type": "Feature",
  "properties": {
    "iso:country":"CH",
    "sg:address":"Schmittenacker 19",
    "sg:city":"L\u00e4ufelfingen",
    "sg:orig_category":"Non-Classified Establishments",
    "sg:postcode":"4448",
    "sg:province":"Basel-Landschaft",
    "wof:name":"Walter M\u00e4gerli M\u00e4gerli Technik",
    "wof:placetype":"venue"
},
  "geometry": {"coordinates":[7.8596320152,47.393573761],"type":"Point"}
}