{
  "type": "Feature",
  "properties": {
    "iso:country":"CH",
    "sg:address":"Carteret Rue Antoine- 2 1202 Gen\u00e8ve. Postfach",
    "sg:city":"Gen\u00e8ve",
    "sg:orig_category":"Non-Classified Establishments",
    "sg:postcode":"1202",
    "sg:province":"Gen\u00e8ve",
    "wof:name":"Coop\u00e9rative Immobili\u00e8re Le Niton",
    "wof:placetype":"venue"
},
  "geometry": {"coordinates":[6.1317811012,46.2109527588],"type":"Point"}
}