{
  "type": "Feature",
  "properties": {
    "iso:country":"CH",
    "sg:address":"H\u00e4gglingerstrasse 33",
    "sg:city":"Dottikon",
    "sg:orig_category":"Vereine Milit\u00e4r",
    "sg:postcode":"5605",
    "sg:province":"Aargau",
    "wof:name":"Unteroffiziersverein Freiamt",
    "wof:placetype":"venue"
},
  "geometry": {"coordinates":[8.2418546677,47.3860054016],"type":"Point"}
}