{
  "type": "Feature",
  "properties": {
    "iso:country":"CH",
    "sg:address":"Maumoulin",
    "sg:city":"Villargiroud",
    "sg:orig_category":"Architektur U Ingenieurb\u00fcros Architekturb\u00fcros",
    "sg:phone":"+41 22 343 50 92",
    "sg:postcode":"1694",
    "sg:province":"Fribourg",
    "wof:name":"Jacques Beck",
    "wof:placetype":"venue"
},
  "geometry": {"coordinates":[6.134783,46.186832],"type":"Point"}
}