{
  "type": "Feature",
  "properties": {
    "iso:country":"CH",
    "sg:address":"Oberibergerstr. 24",
    "sg:city":"Unteriberg",
    "sg:classifiers":[
        {
            "category":"Banks & Credit Unions",
            "subcategory":"Bank",
            "type":"Services"
        }
    ],
    "sg:phone":"+41 31 711 27 25",
    "sg:postcode":"8842",
    "sg:province":"Schwyz",
    "wof:name":"Raiffeisenbank Zaeziwil",
    "wof:placetype":"venue"
},
  "geometry": {"coordinates":[7.66186,46.901871],"type":"Point"}
}