{
  "type": "Feature",
  "properties": {
    "iso:country":"CH",
    "sg:address":"Passage De Premier-ao\u00fbt 3",
    "sg:city":"Grand-lancy",
    "sg:orig_category":"G\u00fcterbef\u00f6rderung im Strassenverkehr",
    "sg:postcode":"1212",
    "sg:province":"Gen\u00e8ve",
    "wof:name":"Lm Sa",
    "wof:placetype":"venue"
},
  "geometry": {"coordinates":[6.1217122078,46.1826820374],"type":"Point"}
}