{
  "type": "Feature",
  "properties": {
    "iso:country":"CH",
    "sg:address":"Zunstrasse 11",
    "sg:city":"Glattbrugg",
    "sg:orig_category":"Instandhaltung U Reparatur von Automobilen",
    "sg:phone":"+41 18109272",
    "sg:postcode":"8152",
    "sg:province":"Z\u00fcrich",
    "wof:name":"H. Hitz Toyota-garage",
    "wof:placetype":"venue"
},
  "geometry": {"coordinates":[8.570019722,47.4250984192],"type":"Point"}
}