{
  "type": "Feature",
  "properties": {
    "iso:country":"CH",
    "sg:address":"Gartenstrasse 1",
    "sg:city":"M\u00fcnsingen",
    "sg:orig_category":"Detailhandel mit Beleuchtungs U Haushaltsgegenst\u00e4nden Herstellung von Anstrichmitteln, Druckfarben U",
    "sg:phone":"+41 31 721 46 45",
    "sg:postcode":"3110",
    "sg:province":"Bern",
    "wof:name":"Farben Probst, Inhaber L\u00fcthi Samuel",
    "wof:placetype":"venue"
},
  "geometry": {"coordinates":[7.562783,46.873116],"type":"Point"}
}