{
  "type": "Feature",
  "properties": {
    "iso:country":"CH",
    "sg:address":"8890",
    "sg:city":"Flums",
    "sg:orig_category":"Vereine Vogel-& Naturschutz",
    "sg:phone":"+41 81 733 17 84",
    "sg:postcode":"8890",
    "sg:province":"St. Gallen",
    "wof:name":"Ornithologischer Verein Flums",
    "wof:placetype":"venue"
},
  "geometry": {"coordinates":[9.3476495743,47.0880584717],"type":"Point"}
}