{
  "type": "Feature",
  "properties": {
    "iso:country":"CH",
    "sg:address":"C\u00f4tes-de-montbenon Rue 16",
    "sg:city":"Lausanne",
    "sg:orig_category":"Erbringung von Dienstleistungen f\u00fcr Unternehmen",
    "sg:phone":"+41 21 323 15 88",
    "sg:postcode":"1003",
    "sg:province":"Vaud",
    "wof:name":"Dezign, Zingg Lora",
    "wof:placetype":"venue"
},
  "geometry": {"coordinates":[6.6262578964,46.5213851929],"type":"Point"}
}