{
  "type": "Feature",
  "properties": {
    "iso:country":"CH",
    "sg:address":"Waldhofstrasse 4 6314 Unter\u00e4geri. Postfach",
    "sg:city":"Unter\u00e4geri",
    "sg:orig_category":"Herstellung von Werkzeugmaschinen",
    "sg:postcode":"6314",
    "sg:province":"Zug",
    "wof:name":"Sch\u00f6pfer Oskar",
    "wof:placetype":"venue"
},
  "geometry": {"coordinates":[8.3312196732,47.5191307068],"type":"Point"}
}