{
  "type": "Feature",
  "properties": {
    "iso:country":"CH",
    "sg:address":"Blauenstrasse 1",
    "sg:city":"Bottmingen",
    "sg:orig_category":"Vorschulen, Kinderg\u00e4rten",
    "sg:phone":"+41 61 421 80 43",
    "sg:postcode":"4103",
    "sg:province":"Basel-Landschaft",
    "wof:name":"Kindergarten",
    "wof:placetype":"venue"
},
  "geometry": {"coordinates":[7.5689349174,47.5265312195],"type":"Point"}
}