{
  "type": "Feature",
  "properties": {
    "iso:country":"CH",
    "sg:address":"Hasenmattstrasse 2",
    "sg:city":"Langenthal",
    "sg:orig_category":"Unclassifiable Establishments",
    "sg:postcode":"4900",
    "sg:province":"Bern",
    "wof:name":"Avesco Rent Ag",
    "wof:placetype":"venue"
},
  "geometry": {"coordinates":[7.7777662277,47.2159843445],"type":"Point"}
}