{
  "type": "Feature",
  "properties": {
    "iso:country":"CH",
    "sg:address":"Panoramastrasse 16",
    "sg:city":"Giswil",
    "sg:orig_category":"Feuerwehr Herstellung von Metallerzeugnissen ohne Maschinenbau",
    "sg:phone":"+41 41 675 17 15",
    "sg:postcode":"6074",
    "sg:province":"Obwalden",
    "wof:name":"Pagg Components & Systems Ag",
    "wof:placetype":"venue"
},
  "geometry": {"coordinates":[8.1812171936,46.8334693909],"type":"Point"}
}