{
  "type": "Feature",
  "properties": {
    "iso:country":"CH",
    "sg:address":"Eggetlistrasse 37",
    "sg:city":"Zweisimmen",
    "sg:orig_category":"Elektroinstallation",
    "sg:phone":"+41 33 729 84 84",
    "sg:postcode":"3770",
    "sg:province":"Bern",
    "wof:name":"Elektro Nafzger",
    "wof:placetype":"venue"
},
  "geometry": {"coordinates":[7.3721761703,46.5596008301],"type":"Point"}
}