{
  "type": "Feature",
  "properties": {
    "iso:country":"CH",
    "sg:address":"Grand-torry Route Du 11",
    "sg:city":"Fribourg",
    "sg:orig_category":"Non-Classified Establishments",
    "sg:postcode":"1700",
    "sg:province":"Fribourg",
    "wof:name":"Pilles Lunch Box, Imgarten Peter",
    "wof:placetype":"venue"
},
  "geometry": {"coordinates":[8.817899704,47.2275695801],"type":"Point"}
}