{
  "type": "Feature",
  "properties": {
    "iso:country":"CH",
    "sg:address":"Avenue De Tourbillon 23 1950 Sion Case Postale 437",
    "sg:city":"Sion",
    "sg:orig_category":"Instandhaltung U Reparatur von Automobilen Vermietung von Automobilen",
    "sg:phone":"+41 27 322 20 77",
    "sg:postcode":"1951",
    "sg:province":"Valais",
    "wof:name":"Couturier Sa Garage Ateliers Et Carrosserie",
    "wof:placetype":"venue"
},
  "geometry": {"coordinates":[7.3628978729,46.2291297913],"type":"Point"}
}