{
  "type": "Feature",
  "properties": {
    "iso:country":"CH",
    "sg:address":"Lindenstrasse 22",
    "sg:city":"Oberdiessbach",
    "sg:orig_category":"Wasserversorgung",
    "sg:postcode":"3672",
    "sg:province":"Bern",
    "wof:name":"Kiesenbachgenossenschaft",
    "wof:placetype":"venue"
},
  "geometry": {"coordinates":[7.6225137711,46.8353385925],"type":"Point"}
}