{
  "type": "Feature",
  "properties": {
    "iso:country":"CH",
    "sg:address":"2065 Grand-savagnier Case Postale 55",
    "sg:city":"Grand-savagnier",
    "sg:orig_category":"Sportvereine Eissport Eishockey",
    "sg:phone":"+41 32 384 14 26",
    "sg:postcode":"2065",
    "sg:province":"Neuch\u00e2tel",
    "wof:name":"Hockey-club Seedorf Pinguins",
    "wof:placetype":"venue"
},
  "geometry": {"coordinates":[7.3157129288,47.0305671692],"type":"Point"}
}