{
  "type": "Feature",
  "properties": {
    "iso:country":"CH",
    "sg:address":"Planche-inf\u00e9rieure 4 Case Postale 1068",
    "sg:city":"Fribourg",
    "sg:classifiers":[
        {
            "category":"Utilities",
            "type":"Services"
        }
    ],
    "sg:phone":"+41 26 322 30 35",
    "sg:postcode":"1701",
    "sg:province":"Fribourg",
    "sg:tags":[
        "raw",
        "energy",
        "material"
    ],
    "wof:name":"Services Industriels La Ville De Fribourg",
    "wof:placetype":"venue"
},
  "geometry": {"coordinates":[3.1512200832,48.734161377],"type":"Point"}
}