{
  "type": "Feature",
  "properties": {
    "iso:country":"CH",
    "sg:address":"Luzernstrasse 38",
    "sg:city":"Etziken",
    "sg:orig_category":"Politische Parteien FDP",
    "sg:postcode":"4554",
    "sg:province":"Solothurn",
    "wof:name":"Fdp Ortspartei Etziken",
    "wof:placetype":"venue"
},
  "geometry": {"coordinates":[7.6492319107,47.1870651245],"type":"Point"}
}