{
  "type": "Feature",
  "properties": {
    "iso:country":"CH",
    "sg:address":"Balfrinstrasse 3",
    "sg:city":"Visp",
    "sg:orig_category":"Detailhandel mit Schuhen",
    "sg:phone":"+41 27 945 16 30",
    "sg:postcode":"3930",
    "sg:province":"Valais",
    "wof:name":"Karl V\u00f6gele Ag",
    "wof:placetype":"venue"
},
  "geometry": {"coordinates":[7.8825778961,46.2930755615],"type":"Point"}
}