{
  "type": "Feature",
  "properties": {
    "iso:country":"CH",
    "sg:address":"Z.i. Le Devin",
    "sg:city":"Moudon",
    "sg:orig_category":"Pensionskassen",
    "sg:phone":"+41 21 905 23 08",
    "sg:postcode":"1510",
    "sg:province":"Vaud",
    "wof:name":"Fonds De Pr\u00e9voyance De Model Emballages Sa",
    "wof:placetype":"venue"
},
  "geometry": {"coordinates":[6.8003668785,46.6674957275],"type":"Point"}
}