{
  "type": "Feature",
  "properties": {
    "iso:country":"CH",
    "sg:address":"Ch\u00e2teauneuf",
    "sg:city":"Sion",
    "sg:orig_category":"Herstellung von Karosserien U Anh\u00e4ngern",
    "sg:postcode":"1950",
    "sg:province":"Valais",
    "wof:name":"Cms Camp Mobil Service Stauber Roland",
    "wof:placetype":"venue"
},
  "geometry": {"coordinates":[7.5851202011,46.9452018738],"type":"Point"}
}