{
  "type": "Feature",
  "properties": {
    "iso:country":"CH",
    "sg:address":"Sonnrain 3",
    "sg:city":"Sch\u00f6tz",
    "sg:orig_category":"Vermietung U Verpachtung von eigenen Immobilien Vermittlung von Immobilien",
    "sg:phone":"+41 41 980 25 38",
    "sg:postcode":"6247",
    "sg:province":"Luzern",
    "wof:name":"Grunimmo Ag Sch\u00f6tz",
    "wof:placetype":"venue"
},
  "geometry": {"coordinates":[7.9854512215,47.1744346619],"type":"Point"}
}