{
  "type": "Feature",
  "properties": {
    "iso:country":"CH",
    "sg:address":"Via Gaggiolo",
    "sg:city":"Stabio",
    "sg:classifiers":[
        {
            "category":"Transit Center",
            "subcategory":"Freight",
            "type":"Transportation"
        }
    ],
    "sg:phone":"+41 91 641 61 41",
    "sg:postcode":"6855",
    "sg:province":"Ticino",
    "sg:tags":[
        "fibre",
        "polyester"
    ],
    "wof:name":"Noyfil S.a.",
    "wof:placetype":"venue"
},
  "geometry": {"coordinates":[8.9288854599,45.8457298279],"type":"Point"}
}