{
  "type": "Feature",
  "properties": {
    "iso:country":"CH",
    "sg:address":"Via Giacomo Brentani 9",
    "sg:city":"Lugano",
    "sg:orig_category":"Grosshandel mit Erzen U Metallen",
    "sg:postcode":"6900",
    "sg:province":"Ticino",
    "wof:name":"D.m.p. Distribuzione Metalli Preziosi Sa",
    "wof:placetype":"venue"
},
  "geometry": {"coordinates":[8.9594650269,46.0191688538],"type":"Point"}
}