{
  "type": "Feature",
  "properties": {
    "iso:country":"CH",
    "sg:address":"Kleinfeldstrasse 3 4656 Starrkirch-wil. Postfach",
    "sg:city":"Starrkirch-wil",
    "sg:orig_category":"Herstellung von konfektionierten Textilwaren ohne Bekleidung",
    "sg:postcode":"4656",
    "sg:province":"Solothurn",
    "wof:name":"Webco Gmbh",
    "wof:placetype":"venue"
},
  "geometry": {"coordinates":[8.7577753067,47.2063064575],"type":"Point"}
}