{
  "type": "Feature",
  "properties": {
    "iso:country":"CH",
    "sg:address":"Im Tobel 44",
    "sg:city":"Meilen",
    "sg:orig_category":"Gesundheitswesen Sonstiges Gesundheitswesen",
    "sg:phone":"+41 12624068",
    "sg:postcode":"8706",
    "sg:province":"Z\u00fcrich",
    "wof:name":"Transmedical Gmbh",
    "wof:placetype":"venue"
},
  "geometry": {"coordinates":[8.6206569672,47.2825164795],"type":"Point"}
}