{
  "type": "Feature",
  "properties": {
    "iso:country":"CH",
    "sg:address":"3654",
    "sg:city":"Gunten",
    "sg:orig_category":"Sportvereine Sch\u00fctzen",
    "sg:phone":"+41 62 964 13 84",
    "sg:postcode":"3654",
    "sg:province":"Bern",
    "wof:name":"Feldsch\u00fctzengesellschaft",
    "wof:placetype":"venue"
},
  "geometry": {"coordinates":[7.7014298439,46.7128295898],"type":"Point"}
}