{
  "type": "Feature",
  "properties": {
    "iso:country":"CH",
    "sg:address":"Emmersbergstrasse 63",
    "sg:city":"Schaffhausen",
    "sg:orig_category":"Aktivit\u00e4ten der Generalunternehmen im Baugewerbe Allgemeiner Hoch U Tiefbau",
    "sg:phone":"+41 52 624 47 24",
    "sg:postcode":"8200",
    "sg:province":"Schaffhausen",
    "wof:name":"Genubau Ag",
    "wof:placetype":"venue"
},
  "geometry": {"coordinates":[8.64099,47.7005],"type":"Point"}
}