{
  "type": "Feature",
  "properties": {
    "iso:country":"CH",
    "sg:address":"Rue De Fer 11",
    "sg:city":"Del\u00e9mont",
    "sg:orig_category":"Vermittlung von Immobilien Verwaltung von Immobilien",
    "sg:phone":"+41 32 724 42 40",
    "sg:postcode":"2800",
    "sg:province":"Jura",
    "wof:name":"Fiduciaire Muller Et Christe Sa",
    "wof:placetype":"venue"
},
  "geometry": {"coordinates":[6.9302549362,46.9915733337],"type":"Point"}
}