{
  "type": "Feature",
  "properties": {
    "iso:country":"CH",
    "sg:address":"Bahnhofstrasse 14",
    "sg:city":"Naters",
    "sg:orig_category":"Handel mit Motorr\u00e4dern, Teilen U Zubeh\u00f6r Instandhaltung U Reparatur von Automobilen Instandhaltung U",
    "sg:phone":"+41 71 222 93 20",
    "sg:postcode":"3904",
    "sg:province":"Valais",
    "wof:name":"Marc Landert Honda-motorr\u00e4der",
    "wof:placetype":"venue"
},
  "geometry": {"coordinates":[9.3668317795,47.4180259705],"type":"Point"}
}