{
  "type": "Feature",
  "properties": {
    "iso:country":"CH",
    "sg:address":"M\u00fchlesteig 6",
    "sg:city":"Binningen",
    "sg:orig_category":"Erwachsenenbildung U Unterricht Sprachschulen",
    "sg:phone":"+41 79 219 76 17",
    "sg:postcode":"4102",
    "sg:province":"Basel-Landschaft",
    "wof:name":"English House & Kidstalk Ag",
    "wof:placetype":"venue"
},
  "geometry": {"coordinates":[7.5742897987,47.5317993164],"type":"Point"}
}