{
  "type": "Feature",
  "properties": {
    "iso:country":"CH",
    "sg:address":"Oberdorfweg 2",
    "sg:city":"Herzogenbuchsee",
    "sg:orig_category":"Hoch U Tiefbau Innenausbau",
    "sg:phone":"+41 62 961 36 84",
    "sg:postcode":"3360",
    "sg:province":"Bern",
    "wof:name":"M. Leuthold & Susanne Teoli Renovationen & Innenausbau",
    "wof:placetype":"venue"
},
  "geometry": {"coordinates":[7.7107229233,47.186870575],"type":"Point"}
}