{
  "type": "Feature",
  "properties": {
    "iso:country":"CH",
    "sg:address":"Route De Thonon 85 A",
    "sg:city":"Collonge-bellerive",
    "sg:orig_category":"Finanzierungsinstitutionen",
    "sg:postcode":"1245",
    "sg:province":"Gen\u00e8ve",
    "wof:name":"Rouge-ovale Sa",
    "wof:placetype":"venue"
},
  "geometry": {"coordinates":[6.2131848335,46.246963501],"type":"Point"}
}