{
  "type": "Feature",
  "properties": {
    "iso:country":"CH",
    "sg:address":"Boulevard De P\u00e9rolles 17",
    "sg:city":"Fribourg",
    "sg:orig_category":"Wirtschaftsverb\u00e4nde Industrie, Handel and Gewerbe",
    "sg:phone":"+41 26 322 14 22",
    "sg:postcode":"1700",
    "sg:province":"Fribourg",
    "wof:name":"F\u00e9d.fribourgeoise Immobili\u00e8re",
    "wof:placetype":"venue"
},
  "geometry": {"coordinates":[7.1521830559,46.8002433777],"type":"Point"}
}