{
  "type": "Feature",
  "properties": {
    "iso:country":"CH",
    "sg:address":"Im Blatt",
    "sg:city":"B\u00fcrchen",
    "sg:orig_category":"Beherbergungsgewerbe Wohnheime",
    "sg:phone":"+41 27 934 18 95",
    "sg:postcode":"3935",
    "sg:province":"Valais",
    "wof:name":"Ferienheim Bethania, Gattlen Erna",
    "wof:placetype":"venue"
},
  "geometry": {"coordinates":[7.833143,46.276684],"type":"Point"}
}