{
  "type": "Feature",
  "properties": {
    "iso:country":"CH",
    "sg:address":"Metzgerrainle 6 6004 Luzern. Postfach",
    "sg:city":"Luzern",
    "sg:orig_category":"Pensionskassen",
    "sg:phone":"+41 41 419 70 10",
    "sg:postcode":"6003",
    "sg:province":"Luzern",
    "wof:name":"Personalf\u00fcrsorgestiftung Der Marghitola Ag, Luzern",
    "wof:placetype":"venue"
},
  "geometry": {"coordinates":[8.304101944,47.0517845154],"type":"Point"}
}