{
  "type": "Feature",
  "properties": {
    "iso:country":"CH",
    "sg:address":"Zwischen Den Toren 14",
    "sg:city":"Aarau",
    "sg:classifiers":[
        {
            "category":"Bars & Pubs",
            "type":"Food & Drink"
        }
    ],
    "sg:postcode":"5000",
    "sg:province":"Aargau",
    "wof:name":"Sofi Gmbh",
    "wof:placetype":"venue"
},
  "geometry": {"coordinates":[8.044524,47.392181],"type":"Point"}
}