{
  "type": "Feature",
  "properties": {
    "iso:country":"CH",
    "sg:address":"Chemin Du Vaugueny 10",
    "sg:city":"Epalinges",
    "sg:orig_category":"Sonstiger Grosshandel",
    "sg:postcode":"1066",
    "sg:province":"Vaud",
    "wof:name":"Biscay Arnaud.",
    "wof:placetype":"venue"
},
  "geometry": {"coordinates":[6.6587548256,46.5461463928],"type":"Point"}
}