{
  "type": "Feature",
  "properties": {
    "iso:country":"CH",
    "sg:address":"Geiselfeldstrasse 17",
    "sg:city":"Gerlafingen",
    "sg:orig_category":"Grosshandel mit Nahrungsmitteln, Getr\u00e4nken U Tabakwaren ohne ausgepr\u00e4gten Schwerpunkt",
    "sg:postcode":"4563",
    "sg:province":"Solothurn",
    "wof:name":"Sezeng\u00f6z Oender",
    "wof:placetype":"venue"
},
  "geometry": {"coordinates":[7.5791020393,47.1716308594],"type":"Point"}
}