{
  "type": "Feature",
  "properties": {
    "iso:country":"CH",
    "sg:address":"Altenbergstrasse 9",
    "sg:city":"Bern",
    "sg:orig_category":"Kinderkrippen U horte",
    "sg:phone":"+41 31 332 25 65",
    "sg:postcode":"3013",
    "sg:province":"Bern",
    "wof:name":"Kinderkrippe Altenberg",
    "wof:placetype":"venue"
},
  "geometry": {"coordinates":[7.4576840401,46.9503326416],"type":"Point"}
}