{
  "type": "Feature",
  "properties": {
    "iso:country":"CH",
    "sg:address":"Mont-blanc Quai Du 3 1201 Gen\u00e8ve. Postfach",
    "sg:city":"Gen\u00e8ve",
    "sg:orig_category":"Unternehmensberatung",
    "sg:phone":"+41 22 715 30 00",
    "sg:postcode":"1201",
    "sg:province":"Gen\u00e8ve",
    "wof:name":"Galaxy Management Sa",
    "wof:placetype":"venue"
},
  "geometry": {"coordinates":[6.1478619576,46.207244873],"type":"Point"}
}