{
  "type": "Feature",
  "properties": {
    "iso:country":"CH",
    "sg:address":"Bahnhofstr. 15a 3066 Stettlen. Postfach",
    "sg:city":"Stettlen",
    "sg:orig_category":"K\u00fcnstlerische U schriftstellerische T\u00e4tigkeiten U Darbietungen",
    "sg:phone":"+41 26 477 17 86",
    "sg:postcode":"3066",
    "sg:province":"Bern",
    "wof:name":"Genilloud Paul Sa",
    "wof:placetype":"venue"
},
  "geometry": {"coordinates":[7.5238618851,46.9575424194],"type":"Point"}
}