{
  "type": "Feature",
  "properties": {
    "iso:country":"CH",
    "sg:address":"Stofel",
    "sg:city":"Peterzell",
    "sg:orig_category":"Maler U Glasergewerbe",
    "sg:postcode":"9127",
    "sg:province":"St. Gallen",
    "wof:name":"Malergesch\u00e4ft B\u00fcrki Inhaber Guldener Max",
    "wof:placetype":"venue"
},
  "geometry": {"coordinates":[7.5594010353,46.9292526245],"type":"Point"}
}