{
  "type": "Feature",
  "properties": {
    "addr:full":"Dellenstrasse 53 Trimbach Solothurn 4632",
    "addr:housenumber":"53",
    "addr:postcode":"4632",
    "addr:street":"Dellenstrasse",
    "iso:country":"CH",
    "sg:address":"Dellenstrasse 53",
    "sg:city":"Trimbach",
    "sg:orig_category":"Baugewerbe Herstellung von Metallkonstruktionen",
    "sg:phone":"+41 56 290 13 70",
    "sg:postcode":"4632",
    "sg:province":"Solothurn",
    "wof:name":"Ide Ag Montagen",
    "wof:placetype":"venue"
},
  "geometry": {"coordinates":[8.292617,47.487206],"type":"Point"}
}