{
  "type": "Feature",
  "properties": {
    "iso:country":"CH",
    "sg:address":"9613",
    "sg:city":"M\u00fchlr\u00fcti",
    "sg:orig_category":"Sportvereine Jagd",
    "sg:postcode":"9613",
    "sg:province":"St. Gallen",
    "wof:name":"Jagdgesellschaft M\u00fchlr\u00fcti",
    "wof:placetype":"venue"
},
  "geometry": {"coordinates":[8.9856042862,47.3714294434],"type":"Point"}
}