{
  "type": "Feature",
  "properties": {
    "iso:country":"CH",
    "sg:address":"Villa La Chaux",
    "sg:city":"St-gingolph",
    "sg:orig_category":"Grosshandel mit Holz U Baustoffen",
    "sg:postcode":"1898",
    "sg:province":"Valais",
    "wof:name":"Geci Diffusion - Germann Christian",
    "wof:placetype":"venue"
},
  "geometry": {"coordinates":[6.8108258247,46.3890609741],"type":"Point"}
}