{
  "type": "Feature",
  "properties": {
    "iso:country":"CH",
    "sg:address":"Route Du Platy 37c",
    "sg:city":"Villars-sur-gl\u00e2ne",
    "sg:orig_category":"Grosshandel mit lebenden Tieren",
    "sg:phone":"+41 22 798 16 79",
    "sg:postcode":"1752",
    "sg:province":"Fribourg",
    "wof:name":"Emile Zuccone Commerce De Moutons",
    "wof:placetype":"venue"
},
  "geometry": {"coordinates":[6.1117429733,46.2287139893],"type":"Point"}
}