{
  "type": "Feature",
  "properties": {
    "iso:country":"CH",
    "sg:address":"Ch. De L'esparcette 5",
    "sg:city":"Crissier",
    "sg:orig_category":"Reiseb\u00fcros U Reiseveranstalter",
    "sg:postcode":"1023",
    "sg:province":"Vaud",
    "wof:name":"Iberrail Georges Sand",
    "wof:placetype":"venue"
},
  "geometry": {"coordinates":[8.5455379486,47.3309326172],"type":"Point"}
}