{
  "type": "Feature",
  "properties": {
    "iso:country":"CH",
    "sg:address":"Kienersr\u00fcti",
    "sg:city":"Uttigen",
    "sg:orig_category":"Haltung von Rindern",
    "sg:postcode":"3628",
    "sg:province":"Bern",
    "wof:name":"Viehzuchtgenossenschaft Kirchdorf Ii",
    "wof:placetype":"venue"
},
  "geometry": {"coordinates":[7.5478601456,46.8207092285],"type":"Point"}
}