{
  "type": "Feature",
  "properties": {
    "iso:country":"CH",
    "sg:address":"Grundstrasse 28 8048 Z\u00fcrich. Postfach",
    "sg:city":"Z\u00fcrich",
    "sg:orig_category":"Betrieb von Taxis",
    "sg:phone":"+41 14012105",
    "sg:postcode":"8048",
    "sg:province":"Z\u00fcrich",
    "wof:name":"Rossi Giuseppe Taxibetrieb",
    "wof:placetype":"venue"
},
  "geometry": {"coordinates":[8.497589,47.385399],"type":"Point"}
}