{
  "type": "Feature",
  "properties": {
    "iso:country":"CH",
    "sg:address":"Route De Champriond 3",
    "sg:city":"Fribourg",
    "sg:orig_category":"Psychotherapie",
    "sg:phone":"+41 26 424 18 03",
    "sg:postcode":"1700",
    "sg:province":"Fribourg",
    "wof:name":"Evelyne Chardonnens Psychoth\u00e9rapie",
    "wof:placetype":"venue"
},
  "geometry": {"coordinates":[7.1422920227,46.7943077087],"type":"Point"}
}