{
  "type": "Feature",
  "properties": {
    "iso:country":"CH",
    "sg:address":"Holenstock 1",
    "sg:city":"Einsiedeln",
    "sg:orig_category":"Wirtschaftspr\u00fcfung, Steuerberatung U Treuhand",
    "sg:phone":"+41 55 412 54 31",
    "sg:postcode":"8840",
    "sg:province":"Schwyz",
    "wof:name":"Conto-controlling, Bisig Alex",
    "wof:placetype":"venue"
},
  "geometry": {"coordinates":[8.7372188568,47.1267623901],"type":"Point"}
}