{
  "type": "Feature",
  "properties": {
    "iso:country":"CH",
    "sg:address":"Bahnhofstrasse",
    "sg:city":"Sisikon",
    "sg:orig_category":"Bauingenieurb\u00fcros Hochbau Bauingenieurb\u00fcros allgemein",
    "sg:phone":"+41 55 251 53 20",
    "sg:postcode":"6452",
    "sg:province":"Schwyz",
    "wof:name":"Aschwanden & Partner Ingenieure & Planer Eth/sia Ag",
    "wof:placetype":"venue"
},
  "geometry": {"coordinates":[8.848832,47.258869],"type":"Point"}
}