{
  "type": "Feature",
  "properties": {
    "iso:country":"CH",
    "sg:address":"Lavaux Avenue De 101",
    "sg:city":"Pully",
    "sg:orig_category":"Non-Classified Establishments",
    "sg:postcode":"1009",
    "sg:province":"Vaud",
    "wof:name":"Smart Ventures Ag",
    "wof:placetype":"venue"
},
  "geometry": {"coordinates":[8.7771053314,47.2004928589],"type":"Point"}
}