{
  "type": "Feature",
  "properties": {
    "iso:country":"CH",
    "sg:address":"1895",
    "sg:city":"Vionnaz",
    "sg:orig_category":"Elektrizit\u00e4tsversorgung Elektroinstallation",
    "sg:phone":"+41 24 472 74 43",
    "sg:postcode":"1895",
    "sg:province":"Valais",
    "wof:name":"Gu\u00e9rin-guinnard \u00e9lectricit\u00e9 Sa",
    "wof:placetype":"venue"
},
  "geometry": {"coordinates":[6.8994240761,46.3116989136],"type":"Point"}
}