{
  "type": "Feature",
  "properties": {
    "iso:country":"CH",
    "sg:address":"Bahnhofstrasse 9",
    "sg:city":"Baar",
    "sg:classifiers":[
        {
            "category":"Autos & Motor Vehicles",
            "subcategory":"Auto Supplies",
            "type":"Retail Goods"
        }
    ],
    "sg:phone":"+41 41 761 88 87",
    "sg:postcode":"6340",
    "sg:province":"Zug",
    "sg:tags":[
        "clutch"
    ],
    "wof:name":"Schlumpf Industrieprodukte Gmbh",
    "wof:placetype":"venue"
},
  "geometry": {"coordinates":[8.524498,47.195431],"type":"Point"}
}