{
  "type": "Feature",
  "properties": {
    "iso:country":"CH",
    "sg:address":"Sch\u00f6nenwerderstrasse 12",
    "sg:city":"Oberentfelden",
    "sg:orig_category":"Malerei",
    "sg:phone":"+41 62 723 21 74",
    "sg:postcode":"5036",
    "sg:province":"Aargau",
    "wof:name":"Markus Furter Maler Furter",
    "wof:placetype":"venue"
},
  "geometry": {"coordinates":[8.0448007584,47.3568496704],"type":"Point"}
}