{
  "type": "Feature",
  "properties": {
    "iso:country":"CH",
    "sg:address":"Frontenex Route De 62 1207 Gen\u00e8ve. Postfach",
    "sg:city":"Gen\u00e8ve",
    "sg:orig_category":"Unclassifiable Establishments",
    "sg:postcode":"1207",
    "sg:province":"Gen\u00e8ve",
    "wof:name":"F.p.p. Film Production Partners Sa Films; Production Et Exploitation",
    "wof:placetype":"venue"
},
  "geometry": {"coordinates":[6.1671380997,46.203338623],"type":"Point"}
}