{
  "type": "Feature",
  "properties": {
    "iso:country":"CH",
    "sg:address":"R\u00e4melg\u00e4ssli 36",
    "sg:city":"Boll",
    "sg:orig_category":"Non-Classified Establishments",
    "sg:phone":"+41 31 839 15 73",
    "sg:postcode":"3067",
    "sg:province":"Bern",
    "wof:name":"Rei Plan Gmbh",
    "wof:placetype":"venue"
},
  "geometry": {"coordinates":[7.5531101227,46.9509506226],"type":"Point"}
}