{
  "type": "Feature",
  "properties": {
    "iso:country":"CH",
    "sg:address":"In Der Looren 26 8000 Z\u00fcrich. Postfach",
    "sg:city":"Z\u00fcrich",
    "sg:orig_category":"K\u00fcnstlerische U schriftstellerische T\u00e4tigkeiten U Darbietungen",
    "sg:postcode":"8053",
    "sg:province":"Z\u00fcrich",
    "wof:name":"Glarean Gmbh",
    "wof:placetype":"venue"
},
  "geometry": {"coordinates":[8.594329834,47.3643074036],"type":"Point"}
}