{
  "type": "Feature",
  "properties": {
    "iso:country":"CH",
    "sg:address":"Thunstrasse 55 3110 M\u00fcnsingen. Postfach",
    "sg:city":"M\u00fcnsingen",
    "sg:orig_category":"Pensionskassen",
    "sg:phone":"+41 31 720 72 72",
    "sg:postcode":"3110",
    "sg:province":"Bern",
    "wof:name":"Personalvorsorgestiftung Der Usm U. Sch\u00e4rer S\u00f6hne Ag",
    "wof:placetype":"venue"
},
  "geometry": {"coordinates":[7.5663781166,46.8666877747],"type":"Point"}
}