{
  "type": "Feature",
  "properties": {
    "iso:country":"CH",
    "sg:address":"Elisabethenanlage 25 4051 Basel. Postfach",
    "sg:city":"Basel",
    "sg:orig_category":"Grosshandel mit Textilien Grosshandel mit sonstigen Halbwaren",
    "sg:phone":"+41 61 272 28 06",
    "sg:postcode":"4002",
    "sg:province":"Basel-Stadt",
    "wof:name":"Wollhandel Ag Rohwolle, Haare, Tierische U. Pflanzliche Abf\u00e4lle; Handel",
    "wof:placetype":"venue"
},
  "geometry": {"coordinates":[7.5879797935,47.5487823486],"type":"Point"}
}