{
  "type": "Feature",
  "properties": {
    "iso:country":"CH",
    "sg:address":"Seidenhofstrasse 12",
    "sg:city":"Luzern",
    "sg:orig_category":"Detailhandel mit Parf\u00fcmerieartikeln U K\u00f6rperpflegemitteln Grosshandel mit Parf\u00fcmerieartikeln U K\u00f6rpe",
    "sg:phone":"+41 41 210 25 20",
    "sg:postcode":"6003",
    "sg:province":"Luzern",
    "wof:name":"Edenia Ag",
    "wof:placetype":"venue"
},
  "geometry": {"coordinates":[8.3074378967,47.0497398376],"type":"Point"}
}