{
  "type": "Feature",
  "properties": {
    "iso:country":"CH",
    "sg:address":"Le Coin",
    "sg:city":"Pampigny",
    "sg:classifiers":[
        {
            "category":"Insurance",
            "subcategory":"Insurance Agent",
            "type":"Services"
        }
    ],
    "sg:phone":"+41 21 800 36 49",
    "sg:postcode":"1142",
    "sg:province":"Vaud",
    "sg:tags":[
        "versicherungsagenturen",
        "-broker"
    ],
    "wof:name":"B\u00e2loise Assurances Agence Pascal Berthoud",
    "wof:placetype":"venue"
},
  "geometry": {"coordinates":[6.4278230667,46.5800819397],"type":"Point"}
}