{
  "type": "Feature",
  "properties": {
    "iso:country":"CH",
    "sg:address":"Bahnhofplatz 7",
    "sg:city":"Sarnen",
    "sg:orig_category":"Detailhandel mit Schreib U Papeteriewaren Detailhandel mit fotografischen Artikeln",
    "sg:phone":"+41 41 660 45 20",
    "sg:postcode":"6060",
    "sg:province":"Obwalden",
    "wof:name":"Margrit Ab\u00e4cherli Papeterie-photo",
    "wof:placetype":"venue"
},
  "geometry": {"coordinates":[8.2473115921,46.8955230713],"type":"Point"}
}