{
  "type": "Feature",
  "properties": {
    "iso:country":"CH",
    "sg:address":"Seetalstrasse 98 6032 Emmen. Postfach 620",
    "sg:city":"Emmen",
    "sg:orig_category":"Detailhandel mit Fleisch U Fleischwaren",
    "sg:phone":"+41 41 260 69 25",
    "sg:postcode":"6032",
    "sg:province":"Luzern",
    "wof:name":"Alban Frick Metzgerei",
    "wof:placetype":"venue"
},
  "geometry": {"coordinates":[8.3005390167,47.0769958496],"type":"Point"}
}