{
  "type": "Feature",
  "properties": {
    "iso:country":"CH",
    "sg:address":"Le Ch\u00eanois 171",
    "sg:city":"Bo\u00e9court",
    "sg:orig_category":"Herstellung von Metallerzeugnissen ohne Maschinenbau Satzherstellung U Reproduktion",
    "sg:phone":"+41 32 426 60 02",
    "sg:postcode":"2856",
    "sg:province":"Jura",
    "wof:name":"Norbert Viatte Clich\u00e9s",
    "wof:placetype":"venue"
},
  "geometry": {"coordinates":[7.2149381638,47.3506546021],"type":"Point"}
}