{
  "type": "Feature",
  "properties": {
    "iso:country":"CH",
    "sg:address":"Tellen 13",
    "sg:city":"Hohentannen",
    "sg:orig_category":"RESTAURANTS: TEA-ROOMS",
    "sg:phone":"+41 71 642 14 37",
    "sg:postcode":"9216",
    "sg:province":"Thurgau",
    "wof:name":"Restaurant Wartegg",
    "wof:placetype":"venue"
},
  "geometry": {"coordinates":[9.2106657028,47.5081367493],"type":"Point"}
}