{
  "type": "Feature",
  "properties": {
    "addr:full":"Chemin Des Grandes-vies 25 Porrentruy Jura 2900",
    "addr:housenumber":"25",
    "addr:postcode":"2900",
    "addr:street":"Chemin Des Grandes-Vies;Jura",
    "iso:country":"CH",
    "sg:address":"Chemin Des Grandes-vies 25",
    "sg:city":"Porrentruy",
    "sg:orig_category":"Annealing And Hardening Muffles",
    "sg:phone":"+41 32 465 96 00",
    "sg:postcode":"2900",
    "sg:province":"Jura",
    "wof:name":"Thermic Service Sa",
    "wof:placetype":"venue"
},
  "geometry": {"coordinates":[7.081076,47.430374],"type":"Point"}
}