{
  "type": "Feature",
  "properties": {
    "iso:country":"CH",
    "sg:address":"Landstrasse 88 5073 Gipf-oberfrick. Postfach 24",
    "sg:city":"W\u00f6lflinswil",
    "sg:orig_category":"Wirtschaftspr\u00fcfung, Steuerberatung U Treuhand",
    "sg:phone":"+41 62 871 09 39",
    "sg:postcode":"5063",
    "sg:province":"Aargau",
    "wof:name":"Werthm\u00fcller Treuhand",
    "wof:placetype":"venue"
},
  "geometry": {"coordinates":[7.9965291023,47.4909515381],"type":"Point"}
}