{
  "type": "Feature",
  "properties": {
    "iso:country":"CH",
    "sg:address":"Rue De Lausanne 91 1700 Fribourg Case Postale 706",
    "sg:city":"Fribourg",
    "sg:classifiers":[
        {
            "category":"Restaurant",
            "type":"Food & Drink"
        }
    ],
    "sg:phone":"+41 26 322 83 06",
    "sg:postcode":"1701",
    "sg:province":"Fribourg",
    "wof:name":"Chalet Suisse Restaurant Le Plaza",
    "wof:placetype":"venue"
},
  "geometry": {"coordinates":[7.1565489769,46.8052177429],"type":"Point"}
}