{
  "type": "Feature",
  "properties": {
    "iso:country":"CH",
    "sg:address":"Friesenbergstrasse 40",
    "sg:city":"Z\u00fcrich",
    "sg:orig_category":"Fachdetailhandel in Verkaufsr\u00e4umen Handel mit Motorr\u00e4dern, Teilen U Zubeh\u00f6r Instandhaltung U Reparat",
    "sg:phone":"+41 14633080",
    "sg:postcode":"8055",
    "sg:province":"Z\u00fcrich",
    "wof:name":"Roller-shop, Bucher D.",
    "wof:placetype":"venue"
},
  "geometry": {"coordinates":[8.5116043091,47.3684463501],"type":"Point"}
}