{
  "type": "Feature",
  "properties": {
    "iso:country":"CH",
    "sg:address":"Spalenring 62 4055 Basel. Postfach",
    "sg:city":"Basel",
    "sg:orig_category":"Pensionskassen",
    "sg:phone":"+41 61 281 30 77",
    "sg:postcode":"4051",
    "sg:province":"Basel-Stadt",
    "wof:name":"Personalf\u00fcrsorgestiftung Der Buser + Minder, Architekten Fsai",
    "wof:placetype":"venue"
},
  "geometry": {"coordinates":[7.5743508339,47.5589065552],"type":"Point"}
}