{
  "type": "Feature",
  "properties": {
    "addr:full":"Badstrasse 15 Baden Aargau 5400",
    "addr:housenumber":"15",
    "addr:postcode":"5400",
    "addr:street":"Badstrasse",
    "iso:country":"CH",
    "sg:address":"Badstrasse 15",
    "sg:city":"Baden",
    "sg:classifiers":[
        {
            "category":"Bars & Pubs",
            "type":"Food & Drink"
        }
    ],
    "sg:phone":"+41 56 222 26 78",
    "sg:postcode":"5400",
    "sg:province":"Aargau",
    "sg:tags":[
        "restaurant"
    ],
    "wof:name":"Restaurant & Bar City Tak's",
    "wof:placetype":"venue"
},
  "geometry": {"coordinates":[8.308087,47.474789],"type":"Point"}
}