{
  "type": "Feature",
  "properties": {
    "iso:country":"CH",
    "sg:address":"Ausserfeld 10",
    "sg:city":"B\u00fctschwil",
    "sg:orig_category":"Fahrschulen, Flugschulen",
    "sg:phone":"+41 71 983 20 70",
    "sg:postcode":"9606",
    "sg:province":"St. Gallen",
    "wof:name":"Walter Stillhart Autofahrschule",
    "wof:placetype":"venue"
},
  "geometry": {"coordinates":[9.0766124725,47.3508491516],"type":"Point"}
}