{
  "type": "Feature",
  "properties": {
    "iso:country":"CH",
    "sg:address":"Greifenseestrasse 39",
    "sg:city":"D\u00fcbendorf",
    "sg:orig_category":"Maler U Glasergewerbe Malerei",
    "sg:phone":"+41 18202528",
    "sg:postcode":"8600",
    "sg:province":"Z\u00fcrich",
    "wof:name":"Pm Malergesch\u00e4ft Janine Knup",
    "wof:placetype":"venue"
},
  "geometry": {"coordinates":[8.6302461624,47.3898086548],"type":"Point"}
}