{
  "type": "Feature",
  "properties": {
    "iso:country":"CH",
    "sg:address":"Moosgasse 1",
    "sg:city":"Pieterlen",
    "sg:orig_category":"Bauschreinerei",
    "sg:phone":"+41 32 351 46 94",
    "sg:postcode":"2542",
    "sg:province":"Bern",
    "wof:name":"Theodor Weber Schreinerei",
    "wof:placetype":"venue"
},
  "geometry": {"coordinates":[7.335179,47.174057],"type":"Point"}
}