{
  "type": "Feature",
  "properties": {
    "iso:country":"CH",
    "sg:address":"Kirchrainweg 8",
    "sg:city":"Kriens",
    "sg:orig_category":"Bezirks, Sekundar, Realschulen, Oberstufe der Primarschulen",
    "sg:postcode":"6010",
    "sg:province":"Luzern",
    "wof:name":"Sekundarschule Kirchb\u00fchl 2",
    "wof:placetype":"venue"
},
  "geometry": {"coordinates":[8.277987,47.032406],"type":"Point"}
}