{
  "type": "Feature",
  "properties": {
    "addr:full":"Rigistrasse 13 Z\u00fcrich Z\u00fcrich 8006",
    "addr:housenumber":"13",
    "addr:postcode":"8006",
    "addr:street":"Rigistrasse",
    "iso:country":"CH",
    "sg:address":"Rigistrasse 13",
    "sg:city":"Z\u00fcrich",
    "sg:classifiers":[
        {
            "category":"Professional",
            "subcategory":"Advertising",
            "type":"Services"
        }
    ],
    "sg:phone":"+41 13686363",
    "sg:postcode":"8006",
    "sg:province":"Z\u00fcrich",
    "sg:tags":[
        "agency"
    ],
    "wof:name":"Mrm Partners Worldwide",
    "wof:placetype":"venue"
},
  "geometry": {"coordinates":[8.548891,47.385483],"type":"Point"}
}