{
  "type": "Feature",
  "properties": {
    "iso:country":"CH",
    "sg:address":"Thesenacher 45",
    "sg:city":"Zumikon",
    "sg:orig_category":"Sonstige mit Sport verbundene T\u00e4tigkeiten",
    "sg:phone":"+41 19190418",
    "sg:postcode":"8126",
    "sg:province":"Z\u00fcrich",
    "wof:name":"Lsm Lautenbach Sponsorship Management",
    "wof:placetype":"venue"
},
  "geometry": {"coordinates":[8.6284227371,47.3278617859],"type":"Point"}
}