{
  "type": "Feature",
  "properties": {
    "iso:country":"CH",
    "sg:address":"Im Grien",
    "sg:city":"Dotzigen",
    "sg:orig_category":"Fischzucht, Teichwirtschaft",
    "sg:phone":"+41 32 351 48 55",
    "sg:postcode":"3293",
    "sg:province":"Bern",
    "wof:name":"Kurt Arn Fischzucht",
    "wof:placetype":"venue"
},
  "geometry": {"coordinates":[7.3421421051,47.120098114],"type":"Point"}
}