{
  "type": "Feature",
  "properties": {
    "iso:country":"CH",
    "sg:address":"Rue Juste-olivier 22",
    "sg:city":"Nyon",
    "sg:orig_category":"Sonstige Hilfs U Nebent\u00e4tigkeiten f\u00fcr den Landverkehr",
    "sg:phone":"+41 22 361 02 62",
    "sg:postcode":"1260",
    "sg:province":"Vaud",
    "wof:name":"Parking Perdtemps-centre Sa",
    "wof:placetype":"venue"
},
  "geometry": {"coordinates":[6.2381072044,46.3849716187],"type":"Point"}
}