{
  "type": "Feature",
  "properties": {
    "iso:country":"CH",
    "sg:address":"Max Gublerstrasse 29",
    "sg:city":"Unterengstringen",
    "sg:orig_category":"Geb\u00e4ude, Wohnungsreinigung",
    "sg:phone":"+41 56 622 06 32",
    "sg:postcode":"8103",
    "sg:province":"Z\u00fcrich",
    "wof:name":"Gisa Ruf The Valentinos",
    "wof:placetype":"venue"
},
  "geometry": {"coordinates":[8.2703018188,47.3499259949],"type":"Point"}
}