{
  "type": "Feature",
  "properties": {
    "iso:country":"CH",
    "sg:address":"Auen",
    "sg:city":"Matt",
    "sg:orig_category":"Bau U Wohngenossenschaften Erschliessung von Grundst\u00fccken",
    "sg:postcode":"8766",
    "sg:province":"Glarus",
    "wof:name":"Wohnbaugenossenschaft Matt",
    "wof:placetype":"venue"
},
  "geometry": {"coordinates":[9.172404,46.960045],"type":"Point"}
}