{
  "type": "Feature",
  "properties": {
    "iso:country":"CH",
    "sg:address":"Pionierstrasse 10 8400 Winterthur. Postfach",
    "sg:city":"Neftenbach",
    "sg:orig_category":"Detailhandel mit Waren verschiedener Art, Hauptrichtung Nahrungsmittel Grosshandel mit Getr\u00e4nken",
    "sg:phone":"+41 71 333 45 65",
    "sg:postcode":"8413",
    "sg:province":"Z\u00fcrich",
    "wof:name":"Yvonne's Weinkabinett Ag",
    "wof:placetype":"venue"
},
  "geometry": {"coordinates":[9.3881559372,47.3905830383],"type":"Point"}
}