{
  "type": "Feature",
  "properties": {
    "iso:country":"CH",
    "sg:address":"Suhrerstrasse 35",
    "sg:city":"Oberentfelden",
    "sg:orig_category":"Sportvereine Turnen Vereine Damen",
    "sg:phone":"+41 76 370 93 79",
    "sg:postcode":"5036",
    "sg:province":"Aargau",
    "wof:name":"Damenriege Suhr",
    "wof:placetype":"venue"
},
  "geometry": {"coordinates":[8.0511045456,47.3585853577],"type":"Point"}
}