{
  "type": "Feature",
  "properties": {
    "iso:country":"CH",
    "sg:address":"Bernhard Fiechter",
    "sg:city":"R\u00fctschelen",
    "sg:orig_category":"Wirtschaft U Handel, Wirtschaftliche Beratungsdienste",
    "sg:phone":"+41 62",
    "sg:postcode":"4933",
    "sg:province":"Bern",
    "wof:name":"Bernhard Fiechter",
    "wof:placetype":"venue"
},
  "geometry": {"coordinates":[7.774465,47.17448],"type":"Point"}
}