{
  "type": "Feature",
  "properties": {
    "iso:country":"CH",
    "sg:address":"Via Generoso 6",
    "sg:city":"Lugano",
    "sg:orig_category":"Finanzierungsinstitutionen Handelsvermittlung U Grosshandel",
    "sg:phone":"+41 22 329 36 11",
    "sg:postcode":"6900",
    "sg:province":"Ticino",
    "wof:name":"Kipley Sa",
    "wof:placetype":"venue"
},
  "geometry": {"coordinates":[6.1445670128,46.2072143555],"type":"Point"}
}