{
  "type": "Feature",
  "properties": {
    "iso:country":"CH",
    "sg:address":"1485 Nuvilly. Postfach",
    "sg:city":"Nuvilly",
    "sg:orig_category":"Herstellung von konfektionierten Textilwaren ohne Bekleidung",
    "sg:postcode":"1485",
    "sg:province":"Fribourg",
    "wof:name":"Chuard Christine",
    "wof:placetype":"venue"
},
  "geometry": {"coordinates":[6.8323998451,46.7809104919],"type":"Point"}
}