{
  "type": "Feature",
  "properties": {
    "iso:country":"CH",
    "sg:address":"Bachtalstrasse 13",
    "sg:city":"Ennetbaden",
    "sg:orig_category":"Grosshandel mit festen Brennstoffen U Mineral\u00f6lerzeugnissen",
    "sg:phone":"+41 61 871 02 22",
    "sg:postcode":"5408",
    "sg:province":"Aargau",
    "wof:name":"Resouma Ag",
    "wof:placetype":"venue"
},
  "geometry": {"coordinates":[8.3162755966,47.4796104431],"type":"Point"}
}