{
  "type": "Feature",
  "properties": {
    "iso:country":"CH",
    "sg:address":"Landstrasse 92",
    "sg:city":"Adelboden",
    "sg:orig_category":"G\u00fcterbef\u00f6rderung im Strassenverkehr",
    "sg:phone":"+41 33 673 13 14",
    "sg:postcode":"3715",
    "sg:province":"Bern",
    "wof:name":"Gottfried Fuhrer Transporte",
    "wof:placetype":"venue"
},
  "geometry": {"coordinates":[7.5693597794,46.49451828],"type":"Point"}
}