{
  "type": "Feature",
  "properties": {
    "iso:country":"CH",
    "sg:address":"Murtenstrasse 13",
    "sg:city":"Kerzers",
    "sg:orig_category":"Bau U Wohngenossenschaften",
    "sg:postcode":"3210",
    "sg:province":"Fribourg",
    "wof:name":"Liberale Wohnbaugen.kerzers",
    "wof:placetype":"venue"
},
  "geometry": {"coordinates":[7.194524,46.974239],"type":"Point"}
}