{
  "type": "Feature",
  "properties": {
    "iso:country":"CH",
    "sg:address":"Socinstrasse 13",
    "sg:city":"Basel",
    "sg:orig_category":"Religi\u00f6se Vereinigungen divers",
    "sg:phone":"+41 61 261 32 81",
    "sg:postcode":"4051",
    "sg:province":"Basel-Stadt",
    "wof:name":"Freie Evang.gesellschaft C.f.spittler Haus",
    "wof:placetype":"venue"
},
  "geometry": {"coordinates":[7.5793070793,47.5576858521],"type":"Point"}
}