{
  "type": "Feature",
  "properties": {
    "iso:country":"CH",
    "sg:address":"Bernstrasse 129",
    "sg:city":"Zollikofen",
    "sg:orig_category":"Detailhandel mit elektrischen Haushalts-,Radio U Fernsehger\u00e4ten sowie Musikinstrumenten",
    "sg:phone":"+41 31 911 50 85",
    "sg:postcode":"3052",
    "sg:province":"Bern",
    "wof:name":"Z Zambelli Diego",
    "wof:placetype":"venue"
},
  "geometry": {"coordinates":[7.4579749107,46.9954338074],"type":"Point"}
}