{
  "type": "Feature",
  "properties": {
    "iso:country":"CH",
    "sg:address":"Wiesenstrasse 29",
    "sg:city":"Dietikon",
    "sg:orig_category":"Handelsvermittlung U Grosshandel Sonstiger Grosshandel",
    "sg:phone":"+41 17744131",
    "sg:postcode":"8953",
    "sg:province":"Z\u00fcrich",
    "wof:name":"Office Trends Gmbh",
    "wof:placetype":"venue"
},
  "geometry": {"coordinates":[8.4206762314,47.3957824707],"type":"Point"}
}