{
  "type": "Feature",
  "properties": {
    "iso:country":"CH",
    "sg:address":"Scholtinoss 22 9527 Niederhelfenschwil. Postfach",
    "sg:city":"Niederhelfenschwil",
    "sg:orig_category":"Handelsvermittlung U Grosshandel Softwareentwicklung U beratung",
    "sg:phone":"+41 79 445 63 63",
    "sg:postcode":"9527",
    "sg:province":"St. Gallen",
    "wof:name":"Hobor & Partner Gmbh",
    "wof:placetype":"venue"
},
  "geometry": {"coordinates":[9.1869659424,47.4787597656],"type":"Point"}
}