{
  "type": "Feature",
  "properties": {
    "iso:country":"CH",
    "sg:address":"Br\u00fcckfeldstrasse 25",
    "sg:city":"Bern",
    "sg:orig_category":"Physiotherapie",
    "sg:phone":"+41 31 301 69 38",
    "sg:postcode":"3012",
    "sg:province":"Bern",
    "wof:name":"Rolf Wilhelmi Physiotherapie",
    "wof:placetype":"venue"
},
  "geometry": {"coordinates":[7.4353590012,46.9566040039],"type":"Point"}
}