{
  "type": "Feature",
  "properties": {
    "addr:full":"Zentralstrasse 2 Z\u00fcrich Z\u00fcrich 8003",
    "addr:housenumber":"2",
    "addr:postcode":"8003",
    "addr:street":"Zentralstrasse",
    "iso:country":"CH",
    "sg:address":"Zentralstrasse 2",
    "sg:city":"Z\u00fcrich",
    "sg:classifiers":[
        {
            "category":"Home & Garden",
            "subcategory":"Furniture",
            "type":"Retail Goods"
        }
    ],
    "sg:phone":"+41 14623344",
    "sg:postcode":"8003",
    "sg:province":"Z\u00fcrich",
    "sg:tags":[
        "aluminium"
    ],
    "wof:name":"Ergosan Gmbh",
    "wof:placetype":"venue"
},
  "geometry": {"coordinates":[8.520936,47.370201],"type":"Point"}
}