{
  "type": "Feature",
  "properties": {
    "iso:country":"CH",
    "sg:address":"Champ Du Moulin",
    "sg:city":"Cr\u00e9mines",
    "sg:orig_category":"Herstellung der Ausstattung von Uhren Herstellung von Schrauben, Nieten, Ketten U Federn",
    "sg:phone":"+41 32 499 95 06",
    "sg:postcode":"2746",
    "sg:province":"Bern",
    "wof:name":"Jean Baertschi Sa Fabrication De D\u00e9colletages",
    "wof:placetype":"venue"
},
  "geometry": {"coordinates":[7.4443969727,47.281047821],"type":"Point"}
}