{
  "type": "Feature",
  "properties": {
    "addr:full":"H\u00f6henstrasse 8 Feuerthalen Z\u00fcrich 8245",
    "addr:housenumber":"8",
    "addr:postcode":"8245",
    "addr:street":"Hoehenstrasse",
    "iso:country":"CH",
    "sg:address":"H\u00f6henstrasse 8",
    "sg:city":"Feuerthalen",
    "sg:orig_category":"Bauingenieurb\u00fcros allgemein",
    "sg:phone":"+41 21 635 41 18",
    "sg:postcode":"8245",
    "sg:province":"Z\u00fcrich",
    "wof:name":"Laurent Renaud Bureau D'ing\u00e9nieur",
    "wof:placetype":"venue"
},
  "geometry": {"coordinates":[6.561132,46.525433],"type":"Point"}
}