{
  "type": "Feature",
  "properties": {
    "iso:country":"CH",
    "sg:address":"Chemin Haccius 27",
    "sg:city":"Grand-lancy",
    "sg:orig_category":"Sportvereine Ballsport Volleyball",
    "sg:phone":"+41 22 794 90 78",
    "sg:postcode":"1212",
    "sg:province":"Gen\u00e8ve",
    "wof:name":"Volleyball-club Peps",
    "wof:placetype":"venue"
},
  "geometry": {"coordinates":[6.1157360077,46.1769104004],"type":"Point"}
}