{
  "type": "Feature",
  "properties": {
    "iso:country":"CH",
    "sg:address":"Bahnhofstrasse 16 6037 Root. Postfach 362",
    "sg:city":"Root",
    "sg:orig_category":"Kantonalbanken",
    "sg:phone":"+41 41 206 73 73",
    "sg:postcode":"6037",
    "sg:province":"Luzern",
    "wof:name":"Luzerner Kantonalbank",
    "wof:placetype":"venue"
},
  "geometry": {"coordinates":[8.3920326233,47.1173591614],"type":"Point"}
}