{
  "type": "Feature",
  "properties": {
    "iso:country":"CH",
    "sg:address":"Pierre Rue Saint- 10",
    "sg:city":"Fribourg",
    "sg:orig_category":"Grosshandel mit Erzen U Metallen",
    "sg:postcode":"1700",
    "sg:province":"Fribourg",
    "wof:name":"Next Trade & Finance Sa",
    "wof:placetype":"venue"
},
  "geometry": {"coordinates":[7.1555271149,46.8039703369],"type":"Point"}
}