{
  "type": "Feature",
  "properties": {
    "iso:country":"CH",
    "sg:address":"Stadthausstr. 87.",
    "sg:city":"Winterthur",
    "sg:orig_category":"Detailhandel mit Parf\u00fcmerieartikeln U K\u00f6rperpflegemitteln",
    "sg:postcode":"8400",
    "sg:province":"Z\u00fcrich",
    "wof:name":"Parf\u00fcmerie R\u00fcegger H. Frau",
    "wof:placetype":"venue"
},
  "geometry": {"coordinates":[8.7286529541,47.5000457764],"type":"Point"}
}