{
  "type": "Feature",
  "properties": {
    "iso:country":"CH",
    "sg:address":"Fabrikstrasse 7",
    "sg:city":"Ebertswil",
    "sg:orig_category":"Elektroinstallation",
    "sg:phone":"+41 17642525",
    "sg:postcode":"8925",
    "sg:province":"Z\u00fcrich",
    "wof:name":"Elektro Maag & Wetli Ag",
    "wof:placetype":"venue"
},
  "geometry": {"coordinates":[8.5475330353,47.2264022827],"type":"Point"}
}