{
  "type": "Feature",
  "properties": {
    "iso:country":"CH",
    "sg:address":"Ringstrasse 14 8057 Z\u00fcrich. Postfach",
    "sg:city":"Z\u00fcrich",
    "sg:orig_category":"Unternehmensberatung Wirtschaftspr\u00fcfung, Steuerberatung U Treuhand",
    "sg:phone":"+41 41 631 06 10",
    "sg:postcode":"8057",
    "sg:province":"Z\u00fcrich",
    "wof:name":"Iag Treuhand Gmbh",
    "wof:placetype":"venue"
},
  "geometry": {"coordinates":[8.3103094101,46.9836463928],"type":"Point"}
}