{
  "type": "Feature",
  "properties": {
    "iso:country":"CH",
    "sg:address":"Weite Gasse 32",
    "sg:city":"Baden",
    "sg:classifiers":[
        {
            "category":"Banks & Credit Unions",
            "subcategory":"Bank",
            "type":"Services"
        }
    ],
    "sg:phone":"+41 56 222 94 15",
    "sg:postcode":"5400",
    "sg:province":"Aargau",
    "wof:name":"Raiffeisenbank, Wettingen-baden",
    "wof:placetype":"venue"
},
  "geometry": {"coordinates":[8.307937,47.472458],"type":"Point"}
}