{
  "type": "Feature",
  "properties": {
    "iso:country":"CH",
    "sg:address":"Steinenvorstadt 4",
    "sg:city":"Basel",
    "sg:orig_category":"Detailhandel mit Bekleidung Detailhandel mit Damenbekleidung",
    "sg:phone":"+41 12611255",
    "sg:postcode":"4051",
    "sg:province":"Basel-Stadt",
    "wof:name":"Vero Moda Retail Ag",
    "wof:placetype":"venue"
},
  "geometry": {"coordinates":[7.588823,47.553986],"type":"Point"}
}