{
  "type": "Feature",
  "properties": {
    "iso:country":"CH",
    "sg:address":"3927",
    "sg:city":"Herbriggen",
    "sg:orig_category":"Schulpflegen",
    "sg:postcode":"3927",
    "sg:province":"Valais",
    "wof:name":"Schulkommission Der Gemeinde Herbriggen",
    "wof:placetype":"venue"
},
  "geometry": {"coordinates":[7.7912697792,46.1358184814],"type":"Point"}
}