{
  "type": "Feature",
  "properties": {
    "iso:country":"CH",
    "sg:address":"Panoramaweg 23",
    "sg:city":"Ortschwaben",
    "sg:orig_category":"Herstellung von medizinischen U chirurgischen Ger\u00e4ten sowie orthop\u00e4dischen Vorrichtungen Zahntechnis",
    "sg:phone":"+41 31 829 00 54",
    "sg:postcode":"3042",
    "sg:province":"Bern",
    "wof:name":"J\u00fcrg Spichtin Dental-labor",
    "wof:placetype":"venue"
},
  "geometry": {"coordinates":[7.4022011757,46.9951934814],"type":"Point"}
}