{
  "type": "Feature",
  "properties": {
    "iso:country":"CH",
    "sg:address":"9050",
    "sg:city":"Appenzell",
    "sg:classifiers":[
        {
            "category":"Travel",
            "subcategory":"Hotels & Motels",
            "type":"Entertainment"
        }
    ],
    "sg:postcode":"9050",
    "sg:province":"Appenzell Innerhoden",
    "sg:tags":[
        "hotels",
        "mit",
        "restaurant"
    ],
    "wof:name":"Erich H\u00f6gger-pichler",
    "wof:placetype":"venue"
},
  "geometry": {"coordinates":[9.496629715,47.4421195984],"type":"Point"}
}