{
  "type": "Feature",
  "properties": {
    "iso:country":"CH",
    "sg:address":"Grubenstieg 5",
    "sg:city":"Schaffhausen",
    "sg:classifiers":[
        {
            "category":"Personal",
            "subcategory":"Nail Salon",
            "type":"Services"
        }
    ],
    "sg:phone":"+41 52 625 09 55",
    "sg:postcode":"8200",
    "sg:province":"Schaffhausen",
    "sg:tags":[
        "manicure"
    ],
    "wof:name":"B. Bienz & B.niederhauser Nail-kosmetik Studio B",
    "wof:placetype":"venue"
},
  "geometry": {"coordinates":[8.6422271729,47.7028770447],"type":"Point"}
}