{
  "type": "Feature",
  "properties": {
    "iso:country":"CH",
    "sg:address":"Oberwiesen 610",
    "sg:city":"Hallau",
    "sg:orig_category":"Detailhandel mit M\u00f6beln U Haushaltsgegenst\u00e4nden",
    "sg:postcode":"8215",
    "sg:province":"Schaffhausen",
    "wof:name":"Tibetan Carpets Meier-sharlhey Tsamcho",
    "wof:placetype":"venue"
},
  "geometry": {"coordinates":[8.4565496445,47.6997718811],"type":"Point"}
}