{
  "type": "Feature",
  "properties": {
    "iso:country":"CH",
    "sg:address":"L\u00fcmenstrasse 230",
    "sg:city":"Aedermannsdorf",
    "sg:orig_category":"Grosshandel mit Holz U Baustoffen Verlegen von Fliesen U Platten",
    "sg:phone":"+41 62 394 10 80",
    "sg:postcode":"4714",
    "sg:province":"Solothurn",
    "wof:name":"Peter R\u00f6\u00f6sli Gmbh Keramische Wand-& Bodenbel\u00e4ge",
    "wof:placetype":"venue"
},
  "geometry": {"coordinates":[7.6027917862,47.3058662415],"type":"Point"}
}