{
  "type": "Feature",
  "properties": {
    "iso:country":"CH",
    "sg:address":"Hauptstrasse 20",
    "sg:city":"K\u00fcnten",
    "sg:orig_category":"Nationale Postdienste",
    "sg:phone":"+41 56 496 11 94",
    "sg:postcode":"5444",
    "sg:province":"Aargau",
    "wof:name":"Die Schweizerische Post",
    "wof:placetype":"venue"
},
  "geometry": {"coordinates":[8.328754425,47.3907432556],"type":"Point"}
}