{
  "type": "Feature",
  "properties": {
    "iso:country":"CH",
    "sg:address":"3973",
    "sg:city":"Venth\u00f4ne",
    "sg:orig_category":"Architektur U Ingenieurb\u00fcros -\u00dcbersetzungsb\u00fcros",
    "sg:phone":"+41 27 455 53 70",
    "sg:postcode":"3973",
    "sg:province":"Valais",
    "wof:name":"Pierre Grandjean Bureau D'\u00e9tude & De Traduction",
    "wof:placetype":"venue"
},
  "geometry": {"coordinates":[7.52177,46.306629],"type":"Point"}
}