{
  "type": "Feature",
  "properties": {
    "iso:country":"CH",
    "sg:address":"Route De La-b\u00e2tie 40 1290 Versoix Case Postale 69",
    "sg:city":"Collex",
    "sg:orig_category":"Feuerl\u00f6schapparate Herstellung Feuerwehr",
    "sg:phone":"+41 22 779 40 70",
    "sg:postcode":"1239",
    "sg:province":"Gen\u00e8ve",
    "wof:name":"Etablissement Camille Godard Sa",
    "wof:placetype":"venue"
},
  "geometry": {"coordinates":[6.1306729317,46.2843971252],"type":"Point"}
}