{
  "type": "Feature",
  "properties": {
    "iso:country":"CH",
    "sg:address":"Obstgartenstrasse 12",
    "sg:city":"Kloten",
    "sg:orig_category":"Handel mit Automobilen",
    "sg:phone":"+41 71 633 17 45",
    "sg:postcode":"8302",
    "sg:province":"Z\u00fcrich",
    "wof:name":"Knaus Otto Automobile",
    "wof:placetype":"venue"
},
  "geometry": {"coordinates":[9.1517753601,47.5546875],"type":"Point"}
}