{
  "type": "Feature",
  "properties": {
    "iso:country":"CH",
    "sg:address":"Corso San Gottardo 72",
    "sg:city":"Chiasso",
    "sg:orig_category":"Arztpraxen",
    "sg:phone":"+41 91 682 44 84",
    "sg:postcode":"6830",
    "sg:province":"Ticino",
    "wof:name":"Dott.med.giovanni Ceracchini Medico Generico Fmh",
    "wof:placetype":"venue"
},
  "geometry": {"coordinates":[9.026975,45.835766],"type":"Point"}
}