{
  "type": "Feature",
  "properties": {
    "iso:country":"CH",
    "sg:address":"Bronschhoferstrasse 16",
    "sg:city":"Wil",
    "sg:classifiers":[
        {
            "category":"Professional",
            "subcategory":"Management & Consulting",
            "type":"Services"
        }
    ],
    "sg:phone":"+41 71 912 22 30",
    "sg:postcode":"9500",
    "sg:province":"St. Gallen",
    "sg:tags":[
        "hr",
        "resource",
        "consultancy",
        "human"
    ],
    "wof:name":"Reelpart Ag",
    "wof:placetype":"venue"
},
  "geometry": {"coordinates":[9.0427770615,47.4659233093],"type":"Point"}
}