{
  "type": "Feature",
  "properties": {
    "iso:country":"CH",
    "sg:address":"M\u00f6nchmattweg 5 5036 Oberentfelden. Postfach 229",
    "sg:city":"Oberentfelden",
    "sg:orig_category":"Herstellung von sonstigen elektrischen Ausr\u00fcstungen",
    "sg:phone":"+41 62 723 05 10",
    "sg:postcode":"5036",
    "sg:province":"Aargau",
    "wof:name":"Amstein + Walthert Sicherheit Ag",
    "wof:placetype":"venue"
},
  "geometry": {"coordinates":[8.0497074127,47.3596916199],"type":"Point"}
}