{
  "type": "Feature",
  "properties": {
    "iso:country":"CH",
    "sg:address":"Avenue Collonges 33",
    "sg:city":"Lausanne",
    "sg:orig_category":"Grosshandel mit B\u00fcromaschinen Grosshandel mit Datenverarbeitungsger\u00e4ten",
    "sg:phone":"+41 21 648 52 78",
    "sg:postcode":"1004",
    "sg:province":"Vaud",
    "wof:name":"Cds A.senouci Informatique",
    "wof:placetype":"venue"
},
  "geometry": {"coordinates":[6.6190180779,46.5297050476],"type":"Point"}
}