{
  "type": "Feature",
  "properties": {
    "iso:country":"CH",
    "sg:address":"Via Baldassare Fontana 4",
    "sg:city":"Chiasso",
    "sg:orig_category":"Grosshandel mit elektrischen Haushaltsger\u00e4ten, Radio U Fernsehger\u00e4ten Herstellung von sonstigen elek",
    "sg:phone":"+41 91 683 02 31",
    "sg:postcode":"6830",
    "sg:province":"Ticino",
    "wof:name":"Permontaggio Sa",
    "wof:placetype":"venue"
},
  "geometry": {"coordinates":[9.0230073929,45.837097168],"type":"Point"}
}