{
  "type": "Feature",
  "properties": {
    "iso:country":"CH",
    "sg:address":"Rue De La Poste 2",
    "sg:city":"Echallens",
    "sg:orig_category":"Detailhandel mit Fleisch U Fleischwaren",
    "sg:phone":"+41 21 881 69 00",
    "sg:postcode":"1040",
    "sg:province":"Vaud",
    "wof:name":"Abdelkader Rezgui Boucherie",
    "wof:placetype":"venue"
},
  "geometry": {"coordinates":[6.6349320412,46.6410293579],"type":"Point"}
}