{
  "type": "Feature",
  "properties": {
    "iso:country":"CH",
    "sg:address":"B\u00e4rengasse 25",
    "sg:city":"Z\u00fcrich",
    "sg:classifiers":[
        {
            "category":"Banks & Credit Unions",
            "subcategory":"Bank",
            "type":"Services"
        }
    ],
    "sg:phone":"+41 12121240",
    "sg:postcode":"8001",
    "sg:province":"Z\u00fcrich",
    "wof:name":"Svenska, Handelsbanken Ab",
    "wof:placetype":"venue"
},
  "geometry": {"coordinates":[8.536811,47.369473],"type":"Point"}
}