{
  "type": "Feature",
  "properties": {
    "addr:full":"1965 Chandolin-savi\u00e8se Valais 1965",
    "addr:housenumber":"1965",
    "addr:postcode":"1965",
    "addr:street":"Chandolin-Savie\u0300Se Valais",
    "iso:country":"CH",
    "sg:address":"1965",
    "sg:city":"Chandolin-savi\u00e8se",
    "sg:orig_category":"Bauschreinerei Herstellung von Konstruktionsteilen, Fertigbauteilen U Ausbauelementen aus Holz",
    "sg:phone":"+41 79 351 30 48",
    "sg:postcode":"1965",
    "sg:province":"Valais",
    "wof:name":"Decarli Pierre",
    "wof:placetype":"venue"
},
  "geometry": {"coordinates":[6.99538,46.296612],"type":"Point"}
}