{
  "type": "Feature",
  "properties": {
    "addr:full":"Dreilindenstrasse 8 Meggen Luzern 6045",
    "addr:housenumber":"8",
    "addr:postcode":"6045",
    "addr:street":"Dreilindenstrasse",
    "iso:country":"CH",
    "sg:address":"Dreilindenstrasse 8",
    "sg:city":"Meggen",
    "sg:orig_category":"Bauinstallation",
    "sg:phone":"+41 79 338 78 55",
    "sg:postcode":"6045",
    "sg:province":"Luzern",
    "wof:name":"Top Allround Scheurer Daniel",
    "wof:placetype":"venue"
},
  "geometry": {"coordinates":[8.370373,47.046825],"type":"Point"}
}