{
  "type": "Feature",
  "properties": {
    "iso:country":"CH",
    "sg:address":"Weststrasse 6",
    "sg:city":"Langenthal",
    "sg:orig_category":"Non-Classified Establishments",
    "sg:postcode":"4900",
    "sg:province":"Bern",
    "wof:name":"Wick Andreas",
    "wof:placetype":"venue"
},
  "geometry": {"coordinates":[7.7785887718,47.2227706909],"type":"Point"}
}