{
  "type": "Feature",
  "properties": {
    "iso:country":"CH",
    "sg:address":"Nauern - Egg",
    "sg:city":"Einsiedeln",
    "sg:orig_category":"S\u00e4ge, Hobel U Holzimpr\u00e4gnierwerke",
    "sg:phone":"+41 55 412 12 67",
    "sg:postcode":"8840",
    "sg:province":"Schwyz",
    "wof:name":"K\u00e4lin Peter",
    "wof:placetype":"venue"
},
  "geometry": {"coordinates":[8.7460803986,47.1273155212],"type":"Point"}
}