{
  "type": "Feature",
  "properties": {
    "iso:country":"CH",
    "sg:address":"4562",
    "sg:city":"Biberist",
    "sg:orig_category":"Landw. Genossenschaften Viehzucht",
    "sg:postcode":"4562",
    "sg:province":"Solothurn",
    "wof:name":"Fleckviehzuchtgenossenschaft",
    "wof:placetype":"venue"
},
  "geometry": {"coordinates":[7.5569939613,47.1813812256],"type":"Point"}
}