{
  "type": "Feature",
  "properties": {
    "iso:country":"CH",
    "sg:address":"March\u00e9-aux-chevaux 5",
    "sg:city":"Del\u00e9mont",
    "sg:orig_category":"Dienstleistungen von Beteiligungsgesellschaften",
    "sg:postcode":"2800",
    "sg:province":"Jura",
    "wof:name":"Utina Sa",
    "wof:placetype":"venue"
},
  "geometry": {"coordinates":[7.3437280655,47.3672294617],"type":"Point"}
}