{
  "type": "Feature",
  "properties": {
    "iso:country":"CH",
    "sg:address":"Tischenloostrasse 27",
    "sg:city":"Thalwil",
    "sg:orig_category":"Grosshandel mit elektrischen Haushaltsger\u00e4ten, Radio U Fernsehger\u00e4ten",
    "sg:postcode":"8800",
    "sg:province":"Z\u00fcrich",
    "wof:name":"Elektronik R\u00fcdis\u00fchli B.",
    "wof:placetype":"venue"
},
  "geometry": {"coordinates":[8.5755195618,47.2842788696],"type":"Point"}
}