{
  "type": "Feature",
  "properties": {
    "iso:country":"CH",
    "sg:address":"2738",
    "sg:city":"Court",
    "sg:orig_category":"Pensionskassen",
    "sg:postcode":"2738",
    "sg:province":"Bern",
    "wof:name":"Fondation Oscar Li\u00e9nard",
    "wof:placetype":"venue"
},
  "geometry": {"coordinates":[6.9533801079,46.6943054199],"type":"Point"}
}