{
  "type": "Feature",
  "properties": {
    "iso:country":"CH",
    "sg:address":"Neudorf 2",
    "sg:city":"Oberb\u00fcren",
    "sg:orig_category":"Zahnarztpraxen",
    "sg:phone":"+41 56 633 26 60",
    "sg:postcode":"9245",
    "sg:province":"St. Gallen",
    "wof:name":"Dr. Med. Dent. Stephan Gottet Zahnarzt",
    "wof:placetype":"venue"
},
  "geometry": {"coordinates":[8.3463277817,47.3495903015],"type":"Point"}
}