{
  "type": "Feature",
  "properties": {
    "iso:country":"CH",
    "sg:address":"Platella",
    "sg:city":"Trin",
    "sg:orig_category":"Physiotherapie",
    "sg:phone":"+41 81 635 13 45",
    "sg:postcode":"7014",
    "sg:province":"Graubunden",
    "wof:name":"Margret Trafelet Thudium Physiotherapie",
    "wof:placetype":"venue"
},
  "geometry": {"coordinates":[9.3596086502,46.8287086487],"type":"Point"}
}