{
  "type": "Feature",
  "properties": {
    "iso:country":"CH",
    "sg:address":"6043 Adligenswil. Postfach 427",
    "sg:city":"Adligenswil",
    "sg:orig_category":"Bau\u00e4mter",
    "sg:phone":"+41 71 998 60 30",
    "sg:postcode":"6043",
    "sg:province":"Luzern",
    "wof:name":"Bauamt Der Gemeinde Alt St. Johann",
    "wof:placetype":"venue"
},
  "geometry": {"coordinates":[9.28492,47.193584],"type":"Point"}
}