{
  "type": "Feature",
  "properties": {
    "iso:country":"CH",
    "sg:address":"T\u00f6pferweg 17",
    "sg:city":"Steffisburg",
    "sg:orig_category":"R\u00fcckgewinnung U Vorbereitung f\u00fcr die Wiederverwertung Recycling R\u00fcckgewinnung U Vorbereitung f\u00fcr die",
    "sg:phone":"+41 33 437 52 44",
    "sg:postcode":"3613",
    "sg:province":"Bern",
    "wof:name":"Uhlmann Recycling Ag",
    "wof:placetype":"venue"
},
  "geometry": {"coordinates":[7.6136870384,46.7755699158],"type":"Point"}
}