{
  "type": "Feature",
  "properties": {
    "iso:country":"CH",
    "sg:address":"Chemin Fran\u00e7ois-chavaz 20",
    "sg:city":"Onex",
    "sg:orig_category":"Softwareentwicklung U beratung",
    "sg:phone":"+41 22 792 67 24",
    "sg:postcode":"1213",
    "sg:province":"Gen\u00e8ve",
    "wof:name":"Azot Software Development S\u00e0rl",
    "wof:placetype":"venue"
},
  "geometry": {"coordinates":[6.0981168747,46.1856460571],"type":"Point"}
}