{
  "type": "Feature",
  "properties": {
    "iso:country":"CH",
    "sg:address":"Verbier 1934 Le Ch\u00e2ble Vs. Postfach",
    "sg:city":"Verbier",
    "sg:orig_category":"Dienstleistungen von Beteiligungsgesellschaften",
    "sg:postcode":"1936",
    "sg:province":"Valais",
    "wof:name":"Picchio S.",
    "wof:placetype":"venue"
},
  "geometry": {"coordinates":[7.2124481201,46.0804595947],"type":"Point"}
}