{
  "type": "Feature",
  "properties": {
    "iso:country":"CH",
    "sg:address":"Unterterzen",
    "sg:city":"Unterterzen",
    "sg:classifiers":[
        {
            "category":"Banks & Credit Unions",
            "subcategory":"Bank",
            "type":"Services"
        }
    ],
    "sg:phone":"+41 32 675 20 20",
    "sg:postcode":"8882",
    "sg:province":"St. Gallen",
    "wof:name":"Raiffeisenbank Recherswil",
    "wof:placetype":"venue"
},
  "geometry": {"coordinates":[7.60422,47.160809],"type":"Point"}
}