{
  "type": "Feature",
  "properties": {
    "iso:country":"CH",
    "sg:address":"B\u00f6hnirainstrasse 13",
    "sg:city":"Thalwil",
    "sg:orig_category":"Detailhandel mit Metallwaren, Anstrichmitteln, Glaswaren, Bau U Heimwerkerbedarf",
    "sg:phone":"+41 17231277",
    "sg:postcode":"8800",
    "sg:province":"Z\u00fcrich",
    "wof:name":"Pfister & Co",
    "wof:placetype":"venue"
},
  "geometry": {"coordinates":[8.5644140244,47.2838134766],"type":"Point"}
}