{
  "type": "Feature",
  "properties": {
    "iso:country":"CH",
    "sg:address":"Village Place Du",
    "sg:city":"Monnaz",
    "sg:orig_category":"Herstellung von Konstruktionsteilen, Fertigbauteilen U Ausbauelementen aus Holz",
    "sg:postcode":"1125",
    "sg:province":"Vaud",
    "wof:name":"Cruchon J.-p.",
    "wof:placetype":"venue"
},
  "geometry": {"coordinates":[6.4791522026,46.5285568237],"type":"Point"}
}