{
  "type": "Feature",
  "properties": {
    "iso:country":"CH",
    "sg:address":"N\u00e4geligasse 25.",
    "sg:city":"Stans",
    "sg:orig_category":"Herstellung von medizinischen U chirurgischen Ger\u00e4ten sowie orthop\u00e4dischen Vorrichtungen",
    "sg:postcode":"6370",
    "sg:province":"Nidwalden",
    "wof:name":"Dentaltechnik Spichtig.",
    "wof:placetype":"venue"
},
  "geometry": {"coordinates":[8.3630065918,46.9580192566],"type":"Point"}
}