{
  "type": "Feature",
  "properties": {
    "iso:country":"CH",
    "sg:address":"2716",
    "sg:city":"Sornetan",
    "sg:orig_category":"Darlehenskassen U Raiffeisenbanken",
    "sg:phone":"+41 32 484 95 46",
    "sg:postcode":"2716",
    "sg:province":"Bern",
    "wof:name":"Banque Raiffeisen",
    "wof:placetype":"venue"
},
  "geometry": {"coordinates":[7.216495,47.274391],"type":"Point"}
}