{
  "type": "Feature",
  "properties": {
    "iso:country":"CH",
    "sg:address":"Friedhofweg 8",
    "sg:city":"Huttwil",
    "sg:orig_category":"Sportvereine Sch\u00fctzen Pistolen-& Gewehr",
    "sg:phone":"+41 62 962 16 56",
    "sg:postcode":"4950",
    "sg:province":"Bern",
    "wof:name":"Sch\u00fctzengesellschaft",
    "wof:placetype":"venue"
},
  "geometry": {"coordinates":[7.8512248993,47.1127738953],"type":"Point"}
}