{
  "type": "Feature",
  "properties": {
    "iso:country":"CH",
    "sg:address":"Schlossstrasse 14",
    "sg:city":"B\u00fctzberg",
    "sg:classifiers":[
        {
            "category":"Communications",
            "subcategory":"Film & Video Production",
            "type":"Services"
        }
    ],
    "sg:phone":"+41 62 958 53 40",
    "sg:postcode":"4922",
    "sg:province":"Bern",
    "sg:tags":[
        "glass",
        "cutting",
        "mirror"
    ],
    "wof:name":"Interieur Glastr\u00f6sch Ag",
    "wof:placetype":"venue"
},
  "geometry": {"coordinates":[7.748706,47.214745],"type":"Point"}
}