{
  "type": "Feature",
  "properties": {
    "iso:country":"CH",
    "sg:address":"Rue Emmer-de-vattel 60",
    "sg:city":"Neuch\u00e2tel",
    "sg:orig_category":"Sicherheitsdienste",
    "sg:phone":"+41 32 724 52 48",
    "sg:postcode":"2000",
    "sg:province":"Neuch\u00e2tel",
    "wof:name":"Spars Alexander M\u00fcller",
    "wof:placetype":"venue"
},
  "geometry": {"coordinates":[6.9131917953,46.9931411743],"type":"Point"}
}