{
  "type": "Feature",
  "properties": {
    "iso:country":"CH",
    "sg:address":"Minderweg 26",
    "sg:city":"Burgdorf",
    "sg:orig_category":"Elektroinstallation",
    "sg:phone":"+41 34 423 24 22",
    "sg:postcode":"3400",
    "sg:province":"Bern",
    "wof:name":"Walter Duppenthaler Elektrotechn.unternehmung",
    "wof:placetype":"venue"
},
  "geometry": {"coordinates":[7.6170678139,47.0543556213],"type":"Point"}
}