{
  "type": "Feature",
  "properties": {
    "iso:country":"CH",
    "sg:address":"Via S. Franscini 7",
    "sg:city":"Giubiasco",
    "sg:orig_category":"Unclassifiable Establishments",
    "sg:postcode":"6512",
    "sg:province":"Ticino",
    "wof:name":"Immobiliare Trocadero S.a.",
    "wof:placetype":"venue"
},
  "geometry": {"coordinates":[9.0159950256,46.1768112183],"type":"Point"}
}