{
  "type": "Feature",
  "properties": {
    "iso:country":"CH",
    "sg:address":"Im Langhag 11 8307 Effretikon. Postfach",
    "sg:city":"Br\u00fcttisellen",
    "sg:orig_category":"Markt U Meinungsforschung",
    "sg:postcode":"8306",
    "sg:province":"Z\u00fcrich",
    "wof:name":"Hts Marketing Ltd",
    "wof:placetype":"venue"
},
  "geometry": {"coordinates":[8.6872377396,47.4390563965],"type":"Point"}
}