{
  "type": "Feature",
  "properties": {
    "iso:country":"CH",
    "sg:address":"Route Des Casernes",
    "sg:city":"Bi\u00e8re",
    "sg:classifiers":[
        {
            "category":"Restaurant",
            "type":"Food & Drink"
        }
    ],
    "sg:phone":"+41 22 756 12 36",
    "sg:postcode":"1145",
    "sg:province":"Vaud",
    "wof:name":"Restaurant Le Renfort",
    "wof:placetype":"venue"
},
  "geometry": {"coordinates":[5.9946498871,46.1506690979],"type":"Point"}
}