{
  "type": "Feature",
  "properties": {
    "iso:country":"CH",
    "sg:address":"Neumatt",
    "sg:city":"W\u00e4denswil",
    "sg:orig_category":"Allgemeiner Hoch U Tiefbau Allgemeiner Hochbau",
    "sg:phone":"+41 17803483",
    "sg:postcode":"8820",
    "sg:province":"Z\u00fcrich",
    "wof:name":"Piantas C. S\u00f6hne.",
    "wof:placetype":"venue"
},
  "geometry": {"coordinates":[8.65527,47.212212],"type":"Point"}
}