{
  "type": "Feature",
  "properties": {
    "iso:country":"CH",
    "sg:address":"Nord 33",
    "sg:city":"Walzenhausen",
    "sg:orig_category":"Institutionen f\u00fcr Suchtkranke Institutionen f\u00fcr psychosoziale F\u00e4lle",
    "sg:phone":"+41 71 888 14 31",
    "sg:postcode":"9428",
    "sg:province":"Appenzell Ausserrhoden",
    "wof:name":"Christl.rehabilitationshaus",
    "wof:placetype":"venue"
},
  "geometry": {"coordinates":[9.5987272263,47.4504776001],"type":"Point"}
}