{
  "type": "Feature",
  "properties": {
    "iso:country":"CH",
    "sg:address":"Favre Avenue William- 10 1207 Gen\u00e8ve. Postfach",
    "sg:city":"Gen\u00e8ve",
    "sg:orig_category":"Non-Classified Establishments",
    "sg:postcode":"1207",
    "sg:province":"Gen\u00e8ve",
    "wof:name":"Cig, R. Gross",
    "wof:placetype":"venue"
},
  "geometry": {"coordinates":[6.1630849838,46.2062416077],"type":"Point"}
}