{
  "type": "Feature",
  "properties": {
    "iso:country":"CH",
    "sg:address":"Bernstrasse 104",
    "sg:city":"Bern",
    "sg:classifiers":[
        {
            "category":"Travel",
            "subcategory":"Hotels & Motels",
            "type":"Entertainment"
        }
    ],
    "sg:phone":"+41 31 992 10 11",
    "sg:postcode":"3018",
    "sg:province":"Bern",
    "sg:tags":[
        "hotels",
        "mit",
        "restaurant"
    ],
    "wof:name":"Br\u00fcgger Walter.",
    "wof:placetype":"venue"
},
  "geometry": {"coordinates":[7.3907217979,46.9403419495],"type":"Point"}
}