{
  "type": "Feature",
  "properties": {
    "iso:country":"CH",
    "sg:address":"Brauerstrasse 55",
    "sg:city":"Z\u00fcrich",
    "sg:orig_category":"G\u00fcterbef\u00f6rderung im Strassenverkehr Lagerung",
    "sg:phone":"+41 12421919",
    "sg:postcode":"8004",
    "sg:province":"Z\u00fcrich",
    "wof:name":"Seiler Transport Z\u00fcrich Ag",
    "wof:placetype":"venue"
},
  "geometry": {"coordinates":[8.5258598328,47.3782615662],"type":"Point"}
}