{
  "type": "Feature",
  "properties": {
    "iso:country":"CH",
    "sg:address":"4703",
    "sg:city":"Kestenholz",
    "sg:orig_category":"Vereine Musik/Blasmusik",
    "sg:phone":"+41 62 393 27 53",
    "sg:postcode":"4703",
    "sg:province":"Solothurn",
    "wof:name":"Musikgesellschaft Eintracht",
    "wof:placetype":"venue"
},
  "geometry": {"coordinates":[7.7537951469,47.2831115723],"type":"Point"}
}