{
  "type": "Feature",
  "properties": {
    "iso:country":"CH",
    "sg:address":"Vogelherd",
    "sg:city":"Rorschacherberg",
    "sg:orig_category":"Bauschreinerei",
    "sg:phone":"+41 34 495 61 16",
    "sg:postcode":"9404",
    "sg:province":"St. Gallen",
    "wof:name":"Hansruedi Wittwer Schreinerei",
    "wof:placetype":"venue"
},
  "geometry": {"coordinates":[7.908681,46.967705],"type":"Point"}
}