{
  "type": "Feature",
  "properties": {
    "iso:country":"CH",
    "sg:address":"Nassacherstrasse 8 Bisikon 8307 Effretikon. Postfach",
    "sg:city":"Effretikon",
    "sg:orig_category":"Verwaltung von Immobilien",
    "sg:postcode":"8307",
    "sg:province":"Z\u00fcrich",
    "wof:name":"Acasa Immobilienmarketing Bolliger Roman H. Dr.",
    "wof:placetype":"venue"
},
  "geometry": {"coordinates":[8.6866388321,47.4289779663],"type":"Point"}
}