{
  "type": "Feature",
  "properties": {
    "iso:country":"CH",
    "sg:address":"Route De Rougemont 65",
    "sg:city":"Soral",
    "sg:classifiers":[
        {
            "category":"Restaurant",
            "type":"Food & Drink"
        }
    ],
    "sg:phone":"+41 22 756 33 50",
    "sg:postcode":"1286",
    "sg:province":"Gen\u00e8ve",
    "wof:name":"Caf\u00e9-restaurant Ecu De Gen\u00e8ve",
    "wof:placetype":"venue"
},
  "geometry": {"coordinates":[6.0427289009,46.1418457031],"type":"Point"}
}