{
  "type": "Feature",
  "properties": {
    "iso:country":"CH",
    "sg:address":"Badstrasse 2",
    "sg:city":"Heiden",
    "sg:orig_category":"Detailhandel mit Textilien",
    "sg:phone":"+41 71 891 23 45",
    "sg:postcode":"9410",
    "sg:province":"Appenzell Ausserrhoden",
    "wof:name":"Doris Curiger Widler Stoffe-mercerie",
    "wof:placetype":"venue"
},
  "geometry": {"coordinates":[9.5308036804,47.4457893372],"type":"Point"}
}