{
  "type": "Feature",
  "properties": {
    "iso:country":"CH",
    "sg:address":"Route Des Iles",
    "sg:city":"Bouveret",
    "sg:orig_category":"Schiffs U Bootsbau",
    "sg:phone":"+41 24 481 34 40",
    "sg:postcode":"1897",
    "sg:province":"Valais",
    "wof:name":"Dominique Menut",
    "wof:placetype":"venue"
},
  "geometry": {"coordinates":[6.8655920029,46.3789024353],"type":"Point"}
}