{
  "type": "Feature",
  "properties": {
    "iso:country":"CH",
    "sg:address":"Neugasse 41",
    "sg:city":"St.gallen",
    "sg:orig_category":"Detailhandel mit Antiquit\u00e4ten Kunsthandel",
    "sg:phone":"+41 32 631 00 45",
    "sg:postcode":"9000",
    "sg:province":"St. Gallen",
    "wof:name":"Galerie W Antiquit\u00e4ten",
    "wof:placetype":"venue"
},
  "geometry": {"coordinates":[7.654147,47.235741],"type":"Point"}
}