{
  "type": "Feature",
  "properties": {
    "iso:country":"CH",
    "sg:address":"8834",
    "sg:city":"Schindellegi",
    "sg:orig_category":"Vereine Vogel-& Naturschutz",
    "sg:postcode":"8834",
    "sg:province":"Schwyz",
    "wof:name":"Ornithologischer Verein Schindellegi & Umgebung",
    "wof:placetype":"venue"
},
  "geometry": {"coordinates":[8.7132101059,47.1750717163],"type":"Point"}
}