{
  "type": "Feature",
  "properties": {
    "iso:country":"CH",
    "sg:address":"La Jorette",
    "sg:city":"Torgon",
    "sg:classifiers":[
        {
            "category":"Restaurant",
            "type":"Food & Drink"
        }
    ],
    "sg:phone":"+41 24 481 29 43",
    "sg:postcode":"1899",
    "sg:province":"Valais",
    "wof:name":"Caf\u00e9 La Sergnaz",
    "wof:placetype":"venue"
},
  "geometry": {"coordinates":[6.8765802383,46.3203086853],"type":"Point"}
}