{
  "type": "Feature",
  "properties": {
    "iso:country":"CH",
    "sg:address":"Bodenstrasse 30",
    "sg:city":"Andermatt",
    "sg:orig_category":"G\u00fcterbef\u00f6rderung im Strassenverkehr",
    "sg:phone":"+41 56 633 16 66",
    "sg:postcode":"6490",
    "sg:province":"Uri",
    "wof:name":"Riechsteiner & Weber Ag Sachen- U. Personentransporte. Baumaterialien U. Landesprodukten; Handel",
    "wof:placetype":"venue"
},
  "geometry": {"coordinates":[8.3174819946,47.2825775146],"type":"Point"}
}