{
  "type": "Feature",
  "properties": {
    "iso:country":"CH",
    "sg:address":"Sch\u00f6nauerweg 20",
    "sg:city":"Wegenstetten",
    "sg:orig_category":"Saunas, Solarien, Fitnesszentren U \u00e4hnliches",
    "sg:phone":"+41 61 871 06 64",
    "sg:postcode":"4317",
    "sg:province":"Aargau",
    "wof:name":"Solarium O Sole Mio Gmbh",
    "wof:placetype":"venue"
},
  "geometry": {"coordinates":[7.9295167923,47.4990539551],"type":"Point"}
}