{
  "type": "Feature",
  "properties": {
    "iso:country":"CH",
    "sg:address":"Amselweg 16",
    "sg:city":"Bennau",
    "sg:orig_category":"Sportvereine Sch\u00fctzen Pistolen-& Gewehr",
    "sg:phone":"+41 55 412 59 41",
    "sg:postcode":"8836",
    "sg:province":"Schwyz",
    "wof:name":"Pistolensch\u00fctzen Einsiedeln",
    "wof:placetype":"venue"
},
  "geometry": {"coordinates":[8.7297849655,47.1484451294],"type":"Point"}
}