{
  "type": "Feature",
  "properties": {
    "addr:full":"Zugerstrasse 25 W\u00e4denswil Z\u00fcrich 8820",
    "addr:housenumber":"25",
    "addr:postcode":"8820",
    "addr:street":"Zugerstrasse;Zuerich",
    "iso:country":"CH",
    "sg:address":"Zugerstrasse 25",
    "sg:city":"W\u00e4denswil",
    "sg:orig_category":"Detailhandel mit Blumen U Pflanzen",
    "sg:phone":"+41 17800325",
    "sg:postcode":"8820",
    "sg:province":"Z\u00fcrich",
    "wof:name":"Ueli M\u00fcller Blumengesch\u00e4ft",
    "wof:placetype":"venue"
},
  "geometry": {"coordinates":[8.669889,47.22958],"type":"Point"}
}