{
  "type": "Feature",
  "properties": {
    "iso:country":"CH",
    "sg:address":"Morgartenstrasse 5",
    "sg:city":"Z\u00fcrich",
    "sg:orig_category":"Detailhandel mit Metallwaren, Anstrichmitteln, Glaswaren, Bau U Heimwerkerbedarf Handelsvermittlung ",
    "sg:phone":"+41 17371990",
    "sg:postcode":"8004",
    "sg:province":"Z\u00fcrich",
    "wof:name":"Quickly Ag",
    "wof:placetype":"venue"
},
  "geometry": {"coordinates":[8.4433307648,47.3497695923],"type":"Point"}
}