{
  "type": "Feature",
  "properties": {
    "iso:country":"CH",
    "sg:address":"Birmensdorferstrasse 12",
    "sg:city":"Oberwil-lieli",
    "sg:classifiers":[
        {
            "category":"Military Area",
            "subcategory":"Air Force Base",
            "type":"Public Place"
        }
    ],
    "sg:phone":"+41 56 633 15 61",
    "sg:postcode":"8966",
    "sg:province":"Aargau",
    "sg:tags":[
        "window",
        "skylight",
        "dormer"
    ],
    "wof:name":"Meier Haustec Ag",
    "wof:placetype":"venue"
},
  "geometry": {"coordinates":[8.3949022293,47.3412437439],"type":"Point"}
}