{
  "type": "Feature",
  "properties": {
    "iso:country":"CH",
    "sg:address":"Storchengasse 4",
    "sg:city":"Zofingen",
    "sg:orig_category":"Grosshandel mit Foto U Kinoger\u00e4ten, feinmechanischen U optischen Erzeugnissen Sonstiger Grosshandel",
    "sg:phone":"+41 62 752 41 47",
    "sg:postcode":"4800",
    "sg:province":"Aargau",
    "wof:name":"Fews Gmbh",
    "wof:placetype":"venue"
},
  "geometry": {"coordinates":[7.9465179443,47.2873535156],"type":"Point"}
}