{
  "type": "Feature",
  "properties": {
    "iso:country":"CH",
    "sg:address":"Stade Rue Du 37",
    "sg:city":"Bulle",
    "sg:orig_category":"Detailhandel mit elektrischen Haushalts-,Radio U Fernsehger\u00e4ten sowie Musikinstrumenten",
    "sg:phone":"+41 26 912 98 70",
    "sg:postcode":"1630",
    "sg:province":"Fribourg",
    "wof:name":"Grevi-tambour, Dupasquier Raphy & Wirz Pierrot",
    "wof:placetype":"venue"
},
  "geometry": {"coordinates":[7.0573811531,46.6186027527],"type":"Point"}
}