{
  "type": "Feature",
  "properties": {
    "iso:country":"CH",
    "sg:address":"Gl\u00e4rnischstrasse 9",
    "sg:city":"B\u00e4retswil",
    "sg:orig_category":"Sanit\u00e4r, Heizungs U L\u00fcftungsinstallation",
    "sg:postcode":"8344",
    "sg:province":"Z\u00fcrich",
    "wof:name":"A. Steiner Ag",
    "wof:placetype":"venue"
},
  "geometry": {"coordinates":[8.8501729965,47.3398323059],"type":"Point"}
}