{
  "type": "Feature",
  "properties": {
    "iso:country":"CH",
    "sg:address":"Palud En 1630 Bulle Case Postale 332",
    "sg:city":"Bulle",
    "sg:orig_category":"Grosshandel mit keramischen Erzeugnissen, Glaswaren U Reinigungsmitteln",
    "sg:phone":"+41 26 919 66 80",
    "sg:postcode":"1630",
    "sg:province":"Fribourg",
    "wof:name":"Heglas Bulle Sa Verres Isolants, Vitrages De Tout Genre Etc.; Fabr, Vente",
    "wof:placetype":"venue"
},
  "geometry": {"coordinates":[7.0636868477,46.6228752136],"type":"Point"}
}