{
  "type": "Feature",
  "properties": {
    "iso:country":"CH",
    "sg:address":"Via Collina D'oro 94",
    "sg:city":"Montagnola",
    "sg:orig_category":"Darlehenskassen U Raiffeisenbanken",
    "sg:phone":"+41 91 648 14 42",
    "sg:postcode":"6926",
    "sg:province":"Ticino",
    "wof:name":"Banca Raiffeisen",
    "wof:placetype":"venue"
},
  "geometry": {"coordinates":[8.97631,45.904182],"type":"Point"}
}