{
  "type": "Feature",
  "properties": {
    "iso:country":"CH",
    "sg:address":"Z\u00fcrichstrasse 13",
    "sg:city":"Mettmenstetten",
    "sg:orig_category":"Detailhandel mit Blumen U Pflanzen Fachdetailhandel in Verkaufsr\u00e4umen",
    "sg:phone":"+41 17670909",
    "sg:postcode":"8932",
    "sg:province":"Z\u00fcrich",
    "wof:name":"Fleur Creative Christine Nick Hugentobler",
    "wof:placetype":"venue"
},
  "geometry": {"coordinates":[8.460471,47.247028],"type":"Point"}
}