{
  "type": "Feature",
  "properties": {
    "iso:country":"CH",
    "sg:address":"Solothurnstrasse 4",
    "sg:city":"Jegenstorf",
    "sg:orig_category":"Haltung von Rindern",
    "sg:postcode":"3303",
    "sg:province":"Bern",
    "wof:name":"Besamungsgenossenschaft (fbg) Bek\u00e4mpfung V. Geschlechtskrankheiten Beim Rindvieh, Bes. D. Trichomonadenseuche Usw",
    "wof:placetype":"venue"
},
  "geometry": {"coordinates":[8.3174819946,47.2825775146],"type":"Point"}
}