{
  "type": "Feature",
  "properties": {
    "iso:country":"CH",
    "sg:address":"W\u00fcrenloserstrasse 2",
    "sg:city":"Killwangen",
    "sg:orig_category":"Grosshandel mit sonstigen Gebrauchs U Verbrauchsg\u00fctern",
    "sg:phone":"+41 56 410 18 53",
    "sg:postcode":"8956",
    "sg:province":"Aargau",
    "wof:name":"Sch\u00fcpbach & G\u00f6s Automaten Gmbh",
    "wof:placetype":"venue"
},
  "geometry": {"coordinates":[8.3580169678,47.4327926636],"type":"Point"}
}