{
  "type": "Feature",
  "properties": {
    "iso:country":"CH",
    "sg:address":"R\u00f6tistrasse 1",
    "sg:city":"Solothurn",
    "sg:orig_category":"Berufliche Weiterbildung, Erwachsenenbildung",
    "sg:phone":"+41 79 251 01 34",
    "sg:postcode":"4500",
    "sg:province":"Solothurn",
    "wof:name":"Schulberatung Interlink",
    "wof:placetype":"venue"
},
  "geometry": {"coordinates":[7.54243,47.204971],"type":"Point"}
}