{
  "type": "Feature",
  "properties": {
    "addr:full":"Vadianstrasse 38 St.gallen St. Gallen 9000",
    "addr:housenumber":"38",
    "addr:postcode":"9000",
    "addr:street":"Vadianstrasse",
    "iso:country":"CH",
    "sg:address":"Vadianstrasse 38",
    "sg:city":"St.gallen",
    "sg:orig_category":"Advokaturb\u00fcros",
    "sg:phone":"+41 12243040",
    "sg:postcode":"9000",
    "sg:province":"St. Gallen",
    "wof:name":"Markus & Roman Stieger Advokaturb\u00fcro",
    "wof:placetype":"venue"
},
  "geometry": {"coordinates":[9.369933,47.421455],"type":"Point"}
}