{
  "type": "Feature",
  "properties": {
    "iso:country":"CH",
    "sg:address":"Pfistergasse 52",
    "sg:city":"Zofingen",
    "sg:orig_category":"Reiseb\u00fcros U Reiseveranstalter",
    "sg:postcode":"4800",
    "sg:province":"Aargau",
    "wof:name":"Loher Reisen",
    "wof:placetype":"venue"
},
  "geometry": {"coordinates":[9.5634069443,47.3186531067],"type":"Point"}
}