{
  "type": "Feature",
  "properties": {
    "iso:country":"CH",
    "sg:address":"Ursellen 54",
    "sg:city":"Konolfingen",
    "sg:orig_category":"Sanit\u00e4r, Heizungs U L\u00fcftungsinstallation Sanit\u00e4rinstallation",
    "sg:phone":"+41 31 791 00 10",
    "sg:postcode":"3510",
    "sg:province":"Bern",
    "wof:name":"Tschanz Haustechnik Gmbh",
    "wof:placetype":"venue"
},
  "geometry": {"coordinates":[7.6040267944,46.8809127808],"type":"Point"}
}