{
  "type": "Feature",
  "properties": {
    "iso:country":"CH",
    "sg:address":"1036",
    "sg:city":"Sullens",
    "sg:orig_category":"Instandhaltung U Reparatur von Automobilen",
    "sg:postcode":"1036",
    "sg:province":"Vaud",
    "wof:name":"Reichenbach Electricien-automobile.",
    "wof:placetype":"venue"
},
  "geometry": {"coordinates":[6.5671100616,46.5916404724],"type":"Point"}
}