{
  "type": "Feature",
  "properties": {
    "iso:country":"CH",
    "sg:address":"Wiesenstrasse 1 8374 Dussnang. Postfach",
    "sg:city":"Dussnang",
    "sg:orig_category":"Allgemeinbildende weiterf\u00fchrende Schulen",
    "sg:postcode":"8374",
    "sg:province":"Thurgau",
    "wof:name":"Andr\u00e9 Magnin, Seb Schule Zur Erweiterung Des Bewusstseins",
    "wof:placetype":"venue"
},
  "geometry": {"coordinates":[8.961967,47.435879],"type":"Point"}
}