{
  "type": "Feature",
  "properties": {
    "iso:country":"CH",
    "sg:address":"Berghofstrasse 10",
    "sg:city":"Wolhusen",
    "sg:classifiers":[
        {
            "category":"Education",
            "subcategory":"Library",
            "type":"Public Place"
        }
    ],
    "sg:phone":"+41 71 971 28 77",
    "sg:postcode":"6110",
    "sg:province":"Luzern",
    "sg:tags":[
        "u",
        "bibliotheken",
        "archive"
    ],
    "wof:name":"Schul-& Gemeindebibliothek",
    "wof:placetype":"venue"
},
  "geometry": {"coordinates":[8.96496,47.46291],"type":"Point"}
}