{
  "type": "Feature",
  "properties": {
    "iso:country":"CH",
    "sg:address":"Moosmattstrasse 25a",
    "sg:city":"Luzern",
    "sg:orig_category":"Grosshandel mit pharmazeutischen Erzeugnissen, medizinischen U orthop\u00e4dischen Artikeln",
    "sg:postcode":"6005",
    "sg:province":"Luzern",
    "wof:name":"Artemis Gmbh",
    "wof:placetype":"venue"
},
  "geometry": {"coordinates":[8.3043870926,47.0392837524],"type":"Point"}
}