{
  "type": "Feature",
  "properties": {
    "iso:country":"CH",
    "sg:address":"Salvatorenstrasse 49",
    "sg:city":"Chur",
    "sg:orig_category":"Allgemeiner Hochbau Architektur U Ingenieurb\u00fcros",
    "sg:phone":"+41 81 253 64 60",
    "sg:postcode":"7000",
    "sg:province":"Graubunden",
    "wof:name":"Amak San Gmbh",
    "wof:placetype":"venue"
},
  "geometry": {"coordinates":[9.520125,46.849339],"type":"Point"}
}