{
  "type": "Feature",
  "properties": {
    "iso:country":"CH",
    "sg:address":"Rindermarkt 14",
    "sg:city":"Z\u00fcrich",
    "sg:orig_category":"Werbegrafikateliers",
    "sg:phone":"+41 12522297",
    "sg:postcode":"8001",
    "sg:province":"Z\u00fcrich",
    "wof:name":"Dani Lienhard Grafik",
    "wof:placetype":"venue"
},
  "geometry": {"coordinates":[8.5446634293,47.3722686768],"type":"Point"}
}