{
  "type": "Feature",
  "properties": {
    "iso:country":"CH",
    "sg:address":"Steinenvorstadt 30",
    "sg:city":"Basel",
    "sg:orig_category":"Interessenvertretungen",
    "sg:phone":"+41 61 281 90 20",
    "sg:postcode":"4051",
    "sg:province":"Basel-Stadt",
    "wof:name":"Cindy-stiftung Finanzierung V. Forschungsprojekten F\u00fcr D. Herstellung V. Med. Heilmitteln Zur Krebsbehandlung",
    "wof:placetype":"venue"
},
  "geometry": {"coordinates":[7.5884327888,47.5527877808],"type":"Point"}
}