{
  "type": "Feature",
  "properties": {
    "iso:country":"CH",
    "sg:address":"Rue Sadaz 5",
    "sg:city":"Chavornay",
    "sg:orig_category":"Arztpraxen",
    "sg:phone":"+41 24 441 41 49",
    "sg:postcode":"1373",
    "sg:province":"Vaud",
    "wof:name":"Drs M\u00e9d.p.& M. De Vevey M\u00e9decins G\u00e9n\u00e9ralistes Fmh",
    "wof:placetype":"venue"
},
  "geometry": {"coordinates":[6.572067,46.713364],"type":"Point"}
}