{
  "type": "Feature",
  "properties": {
    "iso:country":"CH",
    "sg:address":"Avenue De La Gare 14",
    "sg:city":"Vevey",
    "sg:orig_category":"Handelsvermittlung U Grosshandel",
    "sg:phone":"+41 21 922 87 04",
    "sg:postcode":"1800",
    "sg:province":"Vaud",
    "wof:name":"Marc Rist Import-export",
    "wof:placetype":"venue"
},
  "geometry": {"coordinates":[6.8437848091,46.462059021],"type":"Point"}
}