{
  "type": "Feature",
  "properties": {
    "iso:country":"CH",
    "sg:address":"Bahnhofstr. 625 9313 Muolen. Postfach",
    "sg:city":"Muolen",
    "sg:orig_category":"Markt U Meinungsforschung",
    "sg:phone":"+41 71 411 01 22",
    "sg:postcode":"9313",
    "sg:province":"St. Gallen",
    "wof:name":"Agentur G\u00e4hwiler",
    "wof:placetype":"venue"
},
  "geometry": {"coordinates":[9.3374595642,47.5165481567],"type":"Point"}
}