{
  "type": "Feature",
  "properties": {
    "iso:country":"CH",
    "sg:address":"Aeusserer Giessenweg 34 3110 M\u00fcnsingen. Postfach",
    "sg:city":"M\u00fcnsingen",
    "sg:orig_category":"Unclassifiable Establishments",
    "sg:postcode":"3110",
    "sg:province":"Bern",
    "wof:name":"Sch\u00e4fer Gartenbau Ag",
    "wof:placetype":"venue"
},
  "geometry": {"coordinates":[7.5468688011,46.8729743958],"type":"Point"}
}