{
  "type": "Feature",
  "properties": {
    "iso:country":"CH",
    "sg:address":"Baslerstrasse 74 4600 Olten. Postfach",
    "sg:city":"Olten",
    "sg:orig_category":"Versicherungen Hauptagenturen",
    "sg:phone":"+41 62 212 66 46",
    "sg:postcode":"4601",
    "sg:province":"Solothurn",
    "wof:name":"Genfer-versicherungen Hauptagentur Olten",
    "wof:placetype":"venue"
},
  "geometry": {"coordinates":[7.9025731087,47.3530235291],"type":"Point"}
}