{
  "type": "Feature",
  "properties": {
    "iso:country":"CH",
    "sg:address":"Dorfg\u00e4ssli 4",
    "sg:city":"H\u00fcnenberg",
    "sg:orig_category":"Datenverarbeitungsdienste Sonstige mit der Informatik verbundene T\u00e4tigkeiten",
    "sg:phone":"+41 41 780 43 66",
    "sg:postcode":"6331",
    "sg:province":"Zug",
    "wof:name":"Stein Statistics Ag Statistische Beratung",
    "wof:placetype":"venue"
},
  "geometry": {"coordinates":[8.425564,47.175152],"type":"Point"}
}