{
  "type": "Feature",
  "properties": {
    "iso:country":"CH",
    "sg:address":"1147",
    "sg:city":"Montricher",
    "sg:classifiers":[
        {
            "category":"Travel",
            "subcategory":"Hotels & Motels",
            "type":"Entertainment"
        }
    ],
    "sg:phone":"+41 33 951 42 04",
    "sg:postcode":"1147",
    "sg:province":"Vaud",
    "sg:tags":[
        "hotels",
        "mit",
        "restaurant"
    ],
    "wof:name":"Contrapunkt Ag",
    "wof:placetype":"venue"
},
  "geometry": {"coordinates":[8.0554924011,46.7590522766],"type":"Point"}
}