{
  "type": "Feature",
  "properties": {
    "iso:country":"CH",
    "sg:address":"Metallstrasse 9 6300 Zug. Postfach",
    "sg:city":"Zug",
    "sg:orig_category":"Eisenbahnverkehr",
    "sg:phone":"+41 52 740 31 09",
    "sg:postcode":"6300",
    "sg:province":"Zug",
    "wof:name":"Slb Steiner Liliput Bahn Ag",
    "wof:placetype":"venue"
},
  "geometry": {"coordinates":[8.8525028229,47.6520652771],"type":"Point"}
}