{
  "type": "Feature",
  "properties": {
    "addr:full":"Les Villageoises A Chernex Vaud 1822",
    "addr:housenumber":"1822",
    "iso:country":"CH",
    "sg:address":"Les Villageoises A",
    "sg:city":"Chernex",
    "sg:orig_category":"Bauschreinerei Herstellung von M\u00f6beln verschiedener Art",
    "sg:phone":"+41 79 214 14 31",
    "sg:postcode":"1822",
    "sg:province":"Vaud",
    "wof:name":"Dino Campanaro Menuiserie & \u00e9b\u00e9nisterie",
    "wof:placetype":"venue"
},
  "geometry": {"coordinates":[6.911375,46.443546],"type":"Point"}
}