{
  "type": "Feature",
  "properties": {
    "addr:full":"Lettenstr. 1 Jonen Aargau 8916",
    "addr:housenumber":"1",
    "addr:postcode":"8916",
    "addr:street":"Lettenstr.",
    "iso:country":"CH",
    "sg:address":"Lettenstr. 1",
    "sg:city":"Jonen",
    "sg:classifiers":[
        {
            "category":"Banks & Credit Unions",
            "subcategory":"Bank",
            "type":"Services"
        }
    ],
    "sg:phone":"+41 62 869 80 20",
    "sg:postcode":"8916",
    "sg:province":"Aargau",
    "wof:name":"Raiffeisenbank Kaisten-ittenthal",
    "wof:placetype":"venue"
},
  "geometry": {"coordinates":[8.04521,47.53788],"type":"Point"}
}