{
  "type": "Feature",
  "properties": {
    "iso:country":"CH",
    "sg:address":"Vorderhof",
    "sg:city":"Grabs",
    "sg:classifiers":[
        {
            "category":"Home & Garden",
            "subcategory":"Furniture",
            "type":"Retail Goods"
        }
    ],
    "sg:phone":"+41 81 771 44 41",
    "sg:postcode":"9472",
    "sg:province":"St. Gallen",
    "sg:tags":[
        "household",
        "wood"
    ],
    "wof:name":"Michael Hilty Ag",
    "wof:placetype":"venue"
},
  "geometry": {"coordinates":[9.4432144165,47.1822662354],"type":"Point"}
}