{
  "type": "Feature",
  "properties": {
    "addr:full":"Alte Passwangstrasse 506 M\u00fcmliswil Solothurn 4717",
    "addr:housenumber":"506",
    "addr:postcode":"4717",
    "addr:street":"Alte Passwangstrasse;Solothurn",
    "iso:country":"CH",
    "sg:address":"Alte Passwangstrasse 506",
    "sg:city":"M\u00fcmliswil",
    "sg:classifiers":[
        {
            "category":"Education",
            "subcategory":"Vocational School",
            "type":"Public Place"
        }
    ],
    "sg:phone":"+41 62 391 17 17",
    "sg:postcode":"4717",
    "sg:province":"Solothurn",
    "sg:tags":[
        "assembly",
        "testing",
        "printed",
        "circuit",
        "pcb",
        "board"
    ],
    "wof:name":"Gpv Electronics Ag",
    "wof:placetype":"venue"
},
  "geometry": {"coordinates":[7.701157,47.344727],"type":"Point"}
}