{
  "type": "Feature",
  "properties": {
    "iso:country":"CH",
    "sg:address":"Elfenauweg 38 3006 Bern. Postfach",
    "sg:city":"Bern",
    "sg:orig_category":"Wirtschafts U Arbeitgeberverb\u00e4nde",
    "sg:postcode":"3005",
    "sg:province":"Bern",
    "wof:name":"Interbusiness, Wirtschaftliche Arbeitsgemeinschaft Wirtschaftl. F\u00f6rderung Ihrer Mitglieder Durch Zweckdienliche Beratung",
    "wof:placetype":"venue"
},
  "geometry": {"coordinates":[7.4670190811,46.9374198914],"type":"Point"}
}