{
  "type": "Feature",
  "properties": {
    "iso:country":"CH",
    "sg:address":"Kirchgasse 9",
    "sg:city":"Eschenz",
    "sg:orig_category":"Kunsthandel",
    "sg:phone":"+41 52 741 53 50",
    "sg:postcode":"8264",
    "sg:province":"Thurgau",
    "wof:name":"Stanislav Oriesek Schwelle Wochenendgalerie",
    "wof:placetype":"venue"
},
  "geometry": {"coordinates":[8.8762559891,47.646648407],"type":"Point"}
}