{
  "type": "Feature",
  "properties": {
    "iso:country":"CH",
    "sg:address":"Poststrasse 23",
    "sg:city":"Biel/bienne",
    "sg:classifiers":[
        {
            "category":"Education",
            "subcategory":"Library",
            "type":"Public Place"
        }
    ],
    "sg:phone":"+41 32 341 69 36",
    "sg:postcode":"2504",
    "sg:province":"Bern",
    "sg:tags":[
        "u",
        "bibliotheken",
        "archive"
    ],
    "wof:name":"Volksbibliothek Mett",
    "wof:placetype":"venue"
},
  "geometry": {"coordinates":[7.273104,47.146904],"type":"Point"}
}