{
  "type": "Feature",
  "properties": {
    "iso:country":"CH",
    "sg:address":"Allmendweg",
    "sg:city":"Menznau",
    "sg:orig_category":"Institutionen f\u00fcr Behinderte",
    "sg:phone":"+41 41 493 20 27",
    "sg:postcode":"6122",
    "sg:province":"Luzern",
    "wof:name":"Stiftung F\u00fcr Schwerbehinderte Wohngruppe Blochwil",
    "wof:placetype":"venue"
},
  "geometry": {"coordinates":[8.0428199768,47.0847396851],"type":"Point"}
}