{
  "type": "Feature",
  "properties": {
    "iso:country":"CH",
    "sg:address":"Alter Kirchweg 23 4800 Zofingen. Postfach",
    "sg:city":"Zofingen",
    "sg:orig_category":"Sonstiger Grosshandel",
    "sg:postcode":"4800",
    "sg:province":"Aargau",
    "wof:name":"Mega-mart Gmbh Warenhandel. Marketing-dienstleistungen",
    "wof:placetype":"venue"
},
  "geometry": {"coordinates":[7.9553089142,47.2785873413],"type":"Point"}
}