{
  "type": "Feature",
  "properties": {
    "iso:country":"CH",
    "sg:address":"Agape-zentrum Murggen 8873 Amden. Postfach 19",
    "sg:city":"Amden",
    "sg:orig_category":"Institutionen f\u00fcr Suchtkranke Tagesheime f\u00fcr Behinderte, gesch\u00fctzte Werkst\u00e4tten",
    "sg:phone":"+41 62 887 80 80",
    "sg:postcode":"8873",
    "sg:province":"St. Gallen",
    "wof:name":"Effingerhort Reha-haus F\u00fcr Alkoholabh\u00e4ngige",
    "wof:placetype":"venue"
},
  "geometry": {"coordinates":[8.173500061,47.4317588806],"type":"Point"}
}