{
  "type": "Feature",
  "properties": {
    "iso:country":"CH",
    "sg:address":"Chemin De La R\u00e9gie 6",
    "sg:city":"Del\u00e9mont",
    "sg:orig_category":"Reinigungsgewerbe",
    "sg:phone":"+41 32 422 40 78",
    "sg:postcode":"2800",
    "sg:province":"Jura",
    "wof:name":"E. Zopp\u00e9, Entreprise De Nettoyage",
    "wof:placetype":"venue"
},
  "geometry": {"coordinates":[7.3470377922,47.3616371155],"type":"Point"}
}