{
  "type": "Feature",
  "properties": {
    "iso:country":"CH",
    "sg:address":"Libellenstrasse 58",
    "sg:city":"Luzern",
    "sg:orig_category":"Selbst\u00e4ndige bildende K\u00fcnstler",
    "sg:phone":"+41 41 497 34 21",
    "sg:postcode":"6004",
    "sg:province":"Luzern",
    "wof:name":"Georges Gisler Glasmaleratelier",
    "wof:placetype":"venue"
},
  "geometry": {"coordinates":[8.3104848862,47.0647392273],"type":"Point"}
}