{
  "type": "Feature",
  "properties": {
    "addr:full":"Oberstrasse 24 8274 T\u00e4gerwilen. Postfach 50 T\u00e4gerwilen Thurgau 8274",
    "addr:housenumber":"24;50",
    "addr:postcode":"8274;8274",
    "addr:street":"Oberstrasse;Postfach;Thurgau",
    "iso:country":"CH",
    "sg:address":"Oberstrasse 24 8274 T\u00e4gerwilen. Postfach 50",
    "sg:city":"T\u00e4gerwilen",
    "sg:orig_category":"Bauspenglerei Sanit\u00e4r, Heizungs U L\u00fcftungsinstallation",
    "sg:phone":"+41 32 351 26 22",
    "sg:postcode":"8274",
    "sg:province":"Thurgau",
    "wof:name":"Burri Kurt Ag",
    "wof:placetype":"venue"
},
  "geometry": {"coordinates":[7.359985,47.106586],"type":"Point"}
}