{
  "type": "Feature",
  "properties": {
    "iso:country":"CH",
    "sg:address":"R\u00f6merstrasse 2",
    "sg:city":"Dietikon",
    "sg:orig_category":"Instandhaltung U Reparatur von Automobilen",
    "sg:phone":"+41 17408149",
    "sg:postcode":"8953",
    "sg:province":"Z\u00fcrich",
    "wof:name":"Ciga City Garage P. Volkart",
    "wof:placetype":"venue"
},
  "geometry": {"coordinates":[8.39640522,47.4063796997],"type":"Point"}
}