{
  "type": "Feature",
  "properties": {
    "iso:country":"CH",
    "sg:address":"Bois-gentil Chemin Du 32 1018 Lausanne. Postfach",
    "sg:city":"Lausanne",
    "sg:orig_category":"Erbringung von Dienstleistungen f\u00fcr Unternehmen",
    "sg:postcode":"1018",
    "sg:province":"Vaud",
    "wof:name":"Jaccoud Catherine Meubles Et Articles De D\u00e9coration",
    "wof:placetype":"venue"
},
  "geometry": {"coordinates":[6.6250500679,46.5374984741],"type":"Point"}
}