{
  "type": "Feature",
  "properties": {
    "addr:full":"Breitmattweg 21a 3173 Oberwangen B. Bern. Postfach K\u00f6niz Bern 3098",
    "addr:housenumber":"21a",
    "addr:postcode":"3173;3098",
    "addr:street":"Breitmattweg",
    "iso:country":"CH",
    "sg:address":"Breitmattweg 21a 3173 Oberwangen B. Bern. Postfach",
    "sg:city":"K\u00f6niz",
    "sg:orig_category":"Detailhandel mit Beleuchtungs U Haushaltsgegenst\u00e4nden Herstellung von keramischen Haushaltswaren U Z",
    "sg:phone":"+41 32 322 18 15",
    "sg:postcode":"3098",
    "sg:province":"Bern",
    "wof:name":"Roger Blaser Sa Bienne",
    "wof:placetype":"venue"
},
  "geometry": {"coordinates":[7.245618,47.139881],"type":"Point"}
}