{
  "type": "Feature",
  "properties": {
    "iso:country":"CH",
    "sg:address":"Cotterd En",
    "sg:city":"Prez-vers-nor\u00e9az",
    "sg:orig_category":"Sonstiger Grosshandel",
    "sg:postcode":"1746",
    "sg:province":"Fribourg",
    "wof:name":"Seres S\u00e0rl",
    "wof:placetype":"venue"
},
  "geometry": {"coordinates":[7.0174498558,46.7857093811],"type":"Point"}
}