{
  "type": "Feature",
  "properties": {
    "iso:country":"CH",
    "sg:address":"Plache-sup\u00e9rieure 16 1700 Fribourg Case Postale 15",
    "sg:city":"Fribourg",
    "sg:orig_category":"Unternehmensberatung",
    "sg:phone":"+41 26 322 77 41",
    "sg:postcode":"1704",
    "sg:province":"Fribourg",
    "wof:name":"Alfred Oggier Cabinet De Consultants",
    "wof:placetype":"venue"
},
  "geometry": {"coordinates":[7.1625490189,46.8028755188],"type":"Point"}
}