{
  "type": "Feature",
  "properties": {
    "addr:full":"Maglio Valcolla Ticino 6951",
    "addr:housenumber":"6951",
    "iso:country":"CH",
    "sg:address":"Maglio",
    "sg:city":"Valcolla",
    "sg:classifiers":[
        {
            "category":"Banks & Credit Unions",
            "subcategory":"Bank",
            "type":"Services"
        }
    ],
    "sg:phone":"+41 4191971209",
    "sg:postcode":"6951",
    "sg:province":"Ticino",
    "wof:name":"Cassa Raiffeisen Di Val Colla, Istituto Bancario",
    "wof:placetype":"venue"
},
  "geometry": {"coordinates":[9.02126,46.08065],"type":"Point"}
}