{
  "type": "Feature",
  "properties": {
    "iso:country":"CH",
    "sg:address":"Schlegelhaus",
    "sg:city":"Grindelwald",
    "sg:orig_category":"RESTAURANTS: TEA-ROOMS",
    "sg:phone":"+41 33 853 52 39",
    "sg:postcode":"3818",
    "sg:province":"Bern",
    "wof:name":"Restaurant Onkel Tom's H\u00fctte",
    "wof:placetype":"venue"
},
  "geometry": {"coordinates":[8.0466918945,46.6306915283],"type":"Point"}
}