{
  "type": "Feature",
  "properties": {
    "iso:country":"CH",
    "sg:address":"Landenbergstrasse 14",
    "sg:city":"Luzern",
    "sg:orig_category":"Wirtschaftspr\u00fcfung, Steuerberatung U Treuhand",
    "sg:phone":"+41 41 360 86 08",
    "sg:postcode":"6005",
    "sg:province":"Luzern",
    "wof:name":"Peter Scheck Treuhandb\u00fcro",
    "wof:placetype":"venue"
},
  "geometry": {"coordinates":[8.3191404343,47.0444412231],"type":"Point"}
}