{
  "type": "Feature",
  "properties": {
    "iso:country":"CH",
    "sg:address":"Eisengasse 37 5600 Lenzburg. Postfach",
    "sg:city":"Derendingen",
    "sg:orig_category":"Elektroinstallation Herstellung von Elektromotoren, Generatoren U Transformatoren",
    "sg:phone":"+41 62 886 36 66",
    "sg:postcode":"4552",
    "sg:province":"Solothurn",
    "wof:name":"Elektro-bau Ag Rothrist, Zweigniederlassung Derendingen Schwachstrom, Starkstromanlagen Usw.; Beratung, Projektierung",
    "wof:placetype":"venue"
},
  "geometry": {"coordinates":[8.1812267303,47.3875656128],"type":"Point"}
}