{
  "type": "Feature",
  "properties": {
    "iso:country":"CH",
    "sg:address":"Vor Adams-garten 12",
    "sg:city":"Roggenburg",
    "sg:orig_category":"Fussreflexzonenmassage",
    "sg:phone":"+41 61 403 07 37",
    "sg:postcode":"2814",
    "sg:province":"Basel-Landschaft",
    "wof:name":"Monika Hue Hammel Fussreflexzonenmassage",
    "wof:placetype":"venue"
},
  "geometry": {"coordinates":[7.5531439781,47.5156517029],"type":"Point"}
}