{
  "type": "Feature",
  "properties": {
    "iso:country":"CH",
    "sg:address":"Gerliswilstrasse 66",
    "sg:city":"Emmenbr\u00fccke",
    "sg:orig_category":"Arztpraxen",
    "sg:phone":"+41 41 262 02 40",
    "sg:postcode":"6020",
    "sg:province":"Luzern",
    "wof:name":"Dres Kramis & Werkmann Kramis \u00c4rzte F\u00fcr Allg.medizin Fmh",
    "wof:placetype":"venue"
},
  "geometry": {"coordinates":[8.275889,47.076366],"type":"Point"}
}