{
  "type": "Feature",
  "properties": {
    "iso:country":"CH",
    "sg:address":"R\u00fcttenenweg 2",
    "sg:city":"M\u00f6hlin",
    "sg:orig_category":"M\u00f6belschreinereien",
    "sg:phone":"+41 71 761 16 86",
    "sg:postcode":"4313",
    "sg:province":"Aargau",
    "wof:name":"K\u00fcng Ag Oberriet",
    "wof:placetype":"venue"
},
  "geometry": {"coordinates":[9.5765380859,47.3312225342],"type":"Point"}
}