{
  "type": "Feature",
  "properties": {
    "addr:full":"Sonnenterrasse 13 6404 Greppen. Postfach Greppen Luzern 6404",
    "addr:housenumber":"13",
    "addr:postcode":"6404;6404",
    "addr:street":"Sonnenterrasse;Postfach",
    "iso:country":"CH",
    "sg:address":"Sonnenterrasse 13 6404 Greppen. Postfach",
    "sg:city":"Greppen",
    "sg:orig_category":"Architektur U Ingenieurb\u00fcros",
    "sg:phone":"+41 41 922 07 77",
    "sg:postcode":"6404",
    "sg:province":"Luzern",
    "wof:name":"Norbert Frey Architekturb\u00fcro Gmbh",
    "wof:placetype":"venue"
},
  "geometry": {"coordinates":[8.428853,47.052872],"type":"Point"}
}