{
  "type": "Feature",
  "properties": {
    "iso:country":"CH",
    "sg:address":"Lindenhof",
    "sg:city":"Benzenschwil",
    "sg:orig_category":"Detailhandel mit Milcherzeugnissen U Eiern Verarbeitung von Milch",
    "sg:postcode":"5636",
    "sg:province":"Aargau",
    "wof:name":"K\u00e4sereigenossenschaft Benzenschwil-wallenschwil",
    "wof:placetype":"venue"
},
  "geometry": {"coordinates":[8.3588781357,47.2479743958],"type":"Point"}
}