{
  "type": "Feature",
  "properties": {
    "iso:country":"CH",
    "sg:address":"Avenue Calas 8",
    "sg:city":"Gen\u00e8ve",
    "sg:orig_category":"Schreib U \u00dcbersetzungsb\u00fcros -\u00dcbersetzungsb\u00fcros",
    "sg:phone":"+41 22 789 10 70",
    "sg:postcode":"1206",
    "sg:province":"Gen\u00e8ve",
    "wof:name":"Transpose Sa",
    "wof:placetype":"venue"
},
  "geometry": {"coordinates":[6.153470993,46.1894035339],"type":"Point"}
}