{
  "type": "Feature",
  "properties": {
    "iso:country":"CH",
    "sg:address":"Ettiswilerstrasse 5",
    "sg:city":"Willisau",
    "sg:orig_category":"Sonstige Institutionen des Sozialwesens ohne Beherbergung",
    "sg:phone":"+41 41 970 25 91",
    "sg:postcode":"6130",
    "sg:province":"Luzern",
    "wof:name":"M\u00fctter-& V\u00e4terberatung",
    "wof:placetype":"venue"
},
  "geometry": {"coordinates":[7.9953999519,47.1245689392],"type":"Point"}
}