{
  "type": "Feature",
  "properties": {
    "iso:country":"CH",
    "sg:address":"B\u00f6hlerstrasse",
    "sg:city":"Unterkulm",
    "sg:orig_category":"Verwertung von Milch",
    "sg:postcode":"5726",
    "sg:province":"Aargau",
    "wof:name":"K\u00e4sereigenossenschaft Unterkulm",
    "wof:placetype":"venue"
},
  "geometry": {"coordinates":[8.1052646637,47.3108253479],"type":"Point"}
}