{
  "type": "Feature",
  "properties": {
    "iso:country":"CH",
    "sg:address":"Wylerstrasse 125",
    "sg:city":"Bern 65",
    "sg:classifiers":[
        {
            "category":"Travel",
            "subcategory":"Travel Agent",
            "type":"Entertainment"
        }
    ],
    "sg:phone":"+41 4151220462",
    "sg:postcode":"3000",
    "sg:province":"Bern",
    "wof:name":"Swiss Travel System/swiss Federal Railways",
    "wof:placetype":"venue"
},
  "geometry": {"coordinates":[7.4476928711,46.963092804],"type":"Point"}
}