{
  "type": "Feature",
  "properties": {
    "iso:country":"CH",
    "sg:address":"M\u00fchlackerstrasse 199",
    "sg:city":"Z\u00fcrich",
    "sg:orig_category":"Herstellung von elektrischen Lampen U Leuchten Sonstige Bauinstallation",
    "sg:phone":"+41 31 980 22 22",
    "sg:postcode":"8046",
    "sg:province":"Z\u00fcrich",
    "wof:name":"Westiform International Ag",
    "wof:placetype":"venue"
},
  "geometry": {"coordinates":[7.3741831779,46.9222640991],"type":"Point"}
}