{
  "type": "Feature",
  "properties": {
    "iso:country":"CH",
    "sg:address":"Bremgartnerstrasse 101",
    "sg:city":"Dietikon",
    "sg:orig_category":"Grosshandel mit sonstigen Gebrauchs U Verbrauchsg\u00fctern",
    "sg:postcode":"8953",
    "sg:province":"Z\u00fcrich",
    "wof:name":"Sonderegger Rico",
    "wof:placetype":"venue"
},
  "geometry": {"coordinates":[8.3987579346,47.3967208862],"type":"Point"}
}