{
  "type": "Feature",
  "properties": {
    "iso:country":"CH",
    "sg:address":"Heuberg 12 4051 Basel. Postfach",
    "sg:city":"Basel",
    "sg:classifiers":[
        {
            "category":"Internet Cafe",
            "subcategory":"None",
            "type":"Food & Drink"
        }
    ],
    "sg:phone":"+41 61 260 11 16",
    "sg:postcode":"4051",
    "sg:province":"Basel-Stadt",
    "sg:tags":[
        "finanzierungsinstitutionen",
        "provider"
    ],
    "wof:name":"Matrixs Ag",
    "wof:placetype":"venue"
},
  "geometry": {"coordinates":[7.585340023,47.5563392639],"type":"Point"}
}