{
  "type": "Feature",
  "properties": {
    "iso:country":"CH",
    "sg:address":"Wildensteinerstrasse 6 4052 Basel. Postfach",
    "sg:city":"Basel",
    "sg:orig_category":"Erschliessung von Grundst\u00fccken",
    "sg:postcode":"4051",
    "sg:province":"Basel-Stadt",
    "wof:name":"Wohngenossenschaft Woba-basel",
    "wof:placetype":"venue"
},
  "geometry": {"coordinates":[7.6145992279,47.5538635254],"type":"Point"}
}