{
  "type": "Feature",
  "properties": {
    "iso:country":"CH",
    "sg:address":"Zentweg 30",
    "sg:city":"Bern",
    "sg:orig_category":"Herstellung von Metallerzeugnissen ohne Maschinenbau Herstellung von Metallkonstruktionen",
    "sg:phone":"+41 31 931 64 44",
    "sg:postcode":"3006",
    "sg:province":"Bern",
    "wof:name":"Hacro R. Ackermann",
    "wof:placetype":"venue"
},
  "geometry": {"coordinates":[7.4760460854,46.9567718506],"type":"Point"}
}