{
  "type": "Feature",
  "properties": {
    "iso:country":"CH",
    "sg:address":"Murackerstrasse 31",
    "sg:city":"Lenzburg",
    "sg:orig_category":"Sportvereine Velo Rad-& Motorfahrer-Bund SRB",
    "sg:postcode":"5600",
    "sg:province":"Aargau",
    "wof:name":"Radfahrer-verein Lenzburg",
    "wof:placetype":"venue"
},
  "geometry": {"coordinates":[8.1648254395,47.3905410767],"type":"Point"}
}