{
  "type": "Feature",
  "properties": {
    "iso:country":"CH",
    "sg:address":"Chemin De Florimont 34",
    "sg:city":"Yverdon-les-bains",
    "sg:orig_category":"Bauschreinerei Herstellung von Konstruktionsteilen, Fertigbauteilen U Ausbauelementen aus Holz",
    "sg:phone":"+41 27 398 12 45",
    "sg:postcode":"1400",
    "sg:province":"Vaud",
    "wof:name":"Aymon Georges",
    "wof:placetype":"venue"
},
  "geometry": {"coordinates":[7.406825,46.276783],"type":"Point"}
}