{
  "type": "Feature",
  "properties": {
    "iso:country":"CH",
    "sg:address":"Route De Malagnou 39",
    "sg:city":"Gen\u00e8ve",
    "sg:orig_category":"Softwareentwicklung U beratung Sonstige mit der Informatik verbundene T\u00e4tigkeiten",
    "sg:phone":"+41 33 336 36 75",
    "sg:postcode":"1208",
    "sg:province":"Gen\u00e8ve",
    "wof:name":"Doris Glogger Edv-dienstleistungen",
    "wof:placetype":"venue"
},
  "geometry": {"coordinates":[7.6338949203,46.714302063],"type":"Point"}
}