{
  "type": "Feature",
  "properties": {
    "iso:country":"CH",
    "sg:address":"Moulins Rue Des 51",
    "sg:city":"Neuch\u00e2tel",
    "sg:orig_category":"Unternehmensberatung",
    "sg:postcode":"2000",
    "sg:province":"Neuch\u00e2tel",
    "wof:name":"Florham Consulting Sa",
    "wof:placetype":"venue"
},
  "geometry": {"coordinates":[6.927230835,46.9932136536],"type":"Point"}
}