{
  "type": "Feature",
  "properties": {
    "iso:country":"CH",
    "sg:address":"Sch\u00f6neggstrasse 42",
    "sg:city":"Dietikon",
    "sg:orig_category":"Softwareentwicklung U beratung",
    "sg:phone":"+41 17401957",
    "sg:postcode":"8953",
    "sg:province":"Z\u00fcrich",
    "wof:name":"Innovate Solutions Gmbh",
    "wof:placetype":"venue"
},
  "geometry": {"coordinates":[8.4067897797,47.4001312256],"type":"Point"}
}