{
  "type": "Feature",
  "properties": {
    "iso:country":"CH",
    "sg:address":"Z\u00fcrichstrasse 40",
    "sg:city":"Einsiedeln",
    "sg:classifiers":[
        {
            "category":"Building & Trades",
            "subcategory":"Plumbing",
            "type":"Services"
        }
    ],
    "sg:phone":"+41 55 412 82 17",
    "sg:postcode":"8840",
    "sg:province":"Schwyz",
    "sg:tags":[
        "supraregional",
        "gas"
    ],
    "wof:name":"Ernst Hiestand",
    "wof:placetype":"venue"
},
  "geometry": {"coordinates":[8.744511,47.132],"type":"Point"}
}