{
  "type": "Feature",
  "properties": {
    "iso:country":"CH",
    "sg:address":"Eisengasse 6",
    "sg:city":"Luzern",
    "sg:orig_category":"Detailhandel mit Bekleidung",
    "sg:phone":"+41 41 410 93 37",
    "sg:postcode":"6004",
    "sg:province":"Luzern",
    "wof:name":"Da Soul Ag Streetwear",
    "wof:placetype":"venue"
},
  "geometry": {"coordinates":[8.306539,47.05257],"type":"Point"}
}