{
  "type": "Feature",
  "properties": {
    "iso:country":"CH",
    "sg:address":"Gewerbestrasse 16",
    "sg:city":"Niederhasli",
    "sg:orig_category":"Herstellung von Papier, Karton U Pappe Oberfl\u00e4chenveredlung U W\u00e4rmebehandlung",
    "sg:phone":"+41 18528585",
    "sg:postcode":"8155",
    "sg:province":"Z\u00fcrich",
    "wof:name":"Star Coating Ag",
    "wof:placetype":"venue"
},
  "geometry": {"coordinates":[8.4959192276,47.4793167114],"type":"Point"}
}