{
  "type": "Feature",
  "properties": {
    "iso:country":"CH",
    "sg:address":"Sternenweg 1 4702 Oensingen. Postfach",
    "sg:city":"Oensingen",
    "sg:orig_category":"Fachdetailhandel in Verkaufsr\u00e4umen Herstellung von sonstiger Bekleidung U Bekleidungszubeh\u00f6r",
    "sg:phone":"+41 17131172",
    "sg:postcode":"4702",
    "sg:province":"Solothurn",
    "wof:name":"Sun Wear Gmbh",
    "wof:placetype":"venue"
},
  "geometry": {"coordinates":[8.5421686172,47.2913475037],"type":"Point"}
}