{
  "type": "Feature",
  "properties": {
    "iso:country":"CH",
    "sg:address":"Portstrasse 32",
    "sg:city":"Biel/bienne",
    "sg:orig_category":"Instandhaltung U Reparatur von Automobilen Tankstellen",
    "sg:phone":"+41 32 365 04 88",
    "sg:postcode":"2503",
    "sg:province":"Bern",
    "wof:name":"Francauto Gmbh",
    "wof:placetype":"venue"
},
  "geometry": {"coordinates":[7.2596101761,47.1248207092],"type":"Point"}
}