{
  "type": "Feature",
  "properties": {
    "iso:country":"CH",
    "sg:address":"Konradstrasse 15 8400 Winterthur. Postfach 610",
    "sg:city":"Winterthur",
    "sg:orig_category":"Werbevermittlung Werbung",
    "sg:phone":"+41 21 962 80 40",
    "sg:postcode":"8401",
    "sg:province":"Z\u00fcrich",
    "wof:name":"Publicit\u00e9 Zufferey Sa",
    "wof:placetype":"venue"
},
  "geometry": {"coordinates":[6.9116148949,46.4303359985],"type":"Point"}
}