{
  "type": "Feature",
  "properties": {
    "iso:country":"CH",
    "sg:address":"Bahnhofplatz 7",
    "sg:city":"L\u00fctzelfl\u00fch-goldb",
    "sg:classifiers":[
        {
            "category":"Travel",
            "subcategory":"Hotels & Motels",
            "type":"Entertainment"
        }
    ],
    "sg:postcode":"3432",
    "sg:province":"Bern",
    "sg:tags":[
        "hotels",
        "mit",
        "restaurant"
    ],
    "wof:name":"Gasthof Bahnhof, Blaser Werner",
    "wof:placetype":"venue"
},
  "geometry": {"coordinates":[7.6818227768,47.0049781799],"type":"Point"}
}