{
  "type": "Feature",
  "properties": {
    "iso:country":"CH",
    "sg:address":"Talackerstrasse 17 Tmc 286",
    "sg:city":"Glattbrugg",
    "sg:orig_category":"Grosshandel mit Bekleidung Handelsvermittlung von Textilien, Bekleidung, Schuhen U Lederwaren",
    "sg:phone":"+41 18292658",
    "sg:postcode":"8152",
    "sg:province":"Z\u00fcrich",
    "wof:name":"Mmm Modeagentur Marion M. M\u00fcller",
    "wof:placetype":"venue"
},
  "geometry": {"coordinates":[8.5740098953,47.4292984009],"type":"Point"}
}