{
  "type": "Feature",
  "properties": {
    "iso:country":"CH",
    "sg:address":"Kindergartenstrasse 1",
    "sg:city":"Romanshorn",
    "sg:orig_category":"Berufsbildende weiterf\u00fchrende Schulen",
    "sg:phone":"+41 71 463 41 40",
    "sg:postcode":"8590",
    "sg:province":"Thurgau",
    "wof:name":"Berufsschule F\u00fcr Verkauf",
    "wof:placetype":"venue"
},
  "geometry": {"coordinates":[9.37426,47.564571],"type":"Point"}
}