{
  "type": "Feature",
  "properties": {
    "iso:country":"CH",
    "sg:address":"Quartiere Maghetti",
    "sg:city":"Lugano",
    "sg:orig_category":"Detailhandel mit B\u00fcchern Detailhandel mit B\u00fcchern, Zeitungen, Schreib U Papeteriewaren",
    "sg:phone":"+41 91 923 57 69",
    "sg:postcode":"6900",
    "sg:province":"Ticino",
    "wof:name":"Libreria W\u00e4lti",
    "wof:placetype":"venue"
},
  "geometry": {"coordinates":[8.953345,46.005192],"type":"Point"}
}