{
  "type": "Feature",
  "properties": {
    "iso:country":"CH",
    "sg:address":"Dorenbachstrasse 77",
    "sg:city":"Binningen",
    "sg:orig_category":"Gesundheitswesen Massagestudios",
    "sg:phone":"+41 61 301 11 15",
    "sg:postcode":"4102",
    "sg:province":"Basel-Landschaft",
    "wof:name":"Herrli Susanne Massagepraxis",
    "wof:placetype":"venue"
},
  "geometry": {"coordinates":[7.5681271553,47.5449676514],"type":"Point"}
}