{
  "type": "Feature",
  "properties": {
    "iso:country":"CH",
    "sg:address":"Strada Giovanni Caccia",
    "sg:city":"Morcote",
    "sg:orig_category":"Bauspenglerei Sanit\u00e4rinstallation",
    "sg:phone":"+41 91 996 33 51",
    "sg:postcode":"6922",
    "sg:province":"Ticino",
    "wof:name":"Marco Andreoni",
    "wof:placetype":"venue"
},
  "geometry": {"coordinates":[8.91977,45.926315],"type":"Point"}
}