{
  "type": "Feature",
  "properties": {
    "iso:country":"CH",
    "sg:address":"Kirchrain 14",
    "sg:city":"Therwil",
    "sg:orig_category":"Interessenvertretungen Museen",
    "sg:phone":"+41 81 833 43 33",
    "sg:postcode":"4106",
    "sg:province":"Basel-Landschaft",
    "wof:name":"Engadiner Museum In St.moritz",
    "wof:placetype":"venue"
},
  "geometry": {"coordinates":[9.8353681564,46.4940109253],"type":"Point"}
}