{
  "type": "Feature",
  "properties": {
    "iso:country":"CH",
    "sg:address":"Vers-le-pas",
    "sg:city":"Troistorrents",
    "sg:orig_category":"Handel mit Automobilen",
    "sg:phone":"+41 24 477 15 77",
    "sg:postcode":"1872",
    "sg:province":"Valais",
    "wof:name":"Udressy Automobiles",
    "wof:placetype":"venue"
},
  "geometry": {"coordinates":[6.9203820229,46.2314872742],"type":"Point"}
}