{
  "type": "Feature",
  "properties": {
    "iso:country":"CH",
    "sg:address":"St\u00e4hlibuck",
    "sg:city":"Frauenfeld",
    "sg:classifiers":[
        {
            "category":"Restaurant",
            "type":"Food & Drink"
        }
    ],
    "sg:phone":"+41 41 488 11 92",
    "sg:postcode":"8500",
    "sg:province":"Thurgau",
    "wof:name":"Restaurant St\u00e4ldeli",
    "wof:placetype":"venue"
},
  "geometry": {"coordinates":[8.0160770416,46.8834953308],"type":"Point"}
}