{
  "type": "Feature",
  "properties": {
    "iso:country":"CH",
    "sg:address":"Place Isaac-mercier 3 1200 Genf. Postfach",
    "sg:city":"Gen\u00e8ve",
    "sg:orig_category":"Unternehmensberatung",
    "sg:phone":"+41 19100017",
    "sg:postcode":"1201",
    "sg:province":"Gen\u00e8ve",
    "wof:name":"Chemex Management Ag Unternehmensberatung",
    "wof:placetype":"venue"
},
  "geometry": {"coordinates":[8.5825977325,47.3120613098],"type":"Point"}
}