{
  "type": "Feature",
  "properties": {
    "iso:country":"CH",
    "sg:address":"Schmedgass 6 9490 Vaduz. Postfach 672",
    "sg:city":"Vaduz",
    "sg:orig_category":"Rechtsberatung Unternehmensberatung",
    "sg:phone":"+41 19110766",
    "sg:postcode":"9490",
    "wof:name":"Siegrist Dr. Consulting",
    "wof:placetype":"venue"
},
  "geometry": {"coordinates":[8.5926761627,47.303691864],"type":"Point"}
}