{
  "type": "Feature",
  "properties": {
    "iso:country":"CH",
    "sg:address":"Rue Petit-senn 6",
    "sg:city":"Gen\u00e8ve",
    "sg:orig_category":"Konsulate",
    "sg:phone":"+41 22 700 47 00",
    "sg:postcode":"1207",
    "sg:province":"Gen\u00e8ve",
    "wof:name":"Consulat De Su\u00e8de",
    "wof:placetype":"venue"
},
  "geometry": {"coordinates":[6.1559100151,46.2020301819],"type":"Point"}
}