{
  "type": "Feature",
  "properties": {
    "iso:country":"CH",
    "sg:address":"Route De Tercier 8 1807 Blonay. Postfach",
    "sg:city":"Blonay",
    "sg:orig_category":"Architektur U Ingenieurb\u00fcros Architekturb\u00fcros",
    "sg:phone":"+41 21 943 54 84",
    "sg:postcode":"1807",
    "sg:province":"Vaud",
    "wof:name":"Atelier D'architecture, Gippa A.",
    "wof:placetype":"venue"
},
  "geometry": {"coordinates":[6.895081,46.464157],"type":"Point"}
}