{
  "type": "Feature",
  "properties": {
    "iso:country":"CH",
    "sg:address":"Im Lindhof 8",
    "sg:city":"M\u00f6nchaltorf",
    "sg:orig_category":"Dienstleistungen im Gartenbau Gartencenter",
    "sg:phone":"+41 19482424",
    "sg:postcode":"8617",
    "sg:province":"Z\u00fcrich",
    "wof:name":"Rund Ums Gr\u00fcn Ag",
    "wof:placetype":"venue"
},
  "geometry": {"coordinates":[8.7383317947,47.3189964294],"type":"Point"}
}