{
  "type": "Feature",
  "properties": {
    "iso:country":"CH",
    "sg:address":"Fenkernstrasse 2",
    "sg:city":"Kriens",
    "sg:orig_category":"Detailhandel mit Brot, Back U S\u00fcsswaren",
    "sg:phone":"+41 41 320 13 83",
    "sg:postcode":"6010",
    "sg:province":"Luzern",
    "wof:name":"Sch\u00fcssler Gmbh B\u00e4ckerei-konditorei",
    "wof:placetype":"venue"
},
  "geometry": {"coordinates":[8.277634,47.033978],"type":"Point"}
}