{
  "type": "Feature",
  "properties": {
    "iso:country":"CH",
    "sg:address":"Sundgauerstrasse 18",
    "sg:city":"Basel",
    "sg:orig_category":"Instandhaltung U Reparatur von Automobilen",
    "sg:phone":"+41 61 322 50 50",
    "sg:postcode":"4055",
    "sg:province":"Basel-Stadt",
    "wof:name":"Garage Heibo, Borer Heinz",
    "wof:placetype":"venue"
},
  "geometry": {"coordinates":[7.5629549026,47.5653953552],"type":"Point"}
}