{
  "type": "Feature",
  "properties": {
    "iso:country":"CH",
    "sg:address":"Schiffenen 17",
    "sg:city":"D\u00fcdingen",
    "sg:orig_category":"Herstellung von Schrauben, Nieten, Ketten U Federn",
    "sg:phone":"+41 26 493 14 40",
    "sg:postcode":"3186",
    "sg:province":"Fribourg",
    "wof:name":"Schertenleib Peter",
    "wof:placetype":"venue"
},
  "geometry": {"coordinates":[7.1919398308,46.8796730042],"type":"Point"}
}