{
  "type": "Feature",
  "properties": {
    "iso:country":"CH",
    "sg:address":"Fuchsnest",
    "sg:city":"Hinterforst",
    "sg:orig_category":"Fa\u00e7ade Construction, Fa\u00e7ade Lining Services",
    "sg:phone":"+41 71 755 35 20",
    "sg:postcode":"9452",
    "sg:province":"St. Gallen",
    "wof:name":"Sh-partner Gmbh",
    "wof:placetype":"venue"
},
  "geometry": {"coordinates":[9.5264339447,47.3619270325],"type":"Point"}
}