{
  "type": "Feature",
  "properties": {
    "iso:country":"CH",
    "sg:address":"Chemin Des Oisillons 4",
    "sg:city":"Morges",
    "sg:orig_category":"Grosshandel mit Datenverarbeitungsger\u00e4ten Hardwareberatung",
    "sg:phone":"+41 21 802 40 95",
    "sg:postcode":"1110",
    "sg:province":"Vaud",
    "wof:name":"Orpam, Gabella Josiane",
    "wof:placetype":"venue"
},
  "geometry": {"coordinates":[6.4939599037,46.5191230774],"type":"Point"}
}