{
  "type": "Feature",
  "properties": {
    "iso:country":"CH",
    "sg:address":"Worbstrasse 166",
    "sg:city":"G\u00fcmligen",
    "sg:orig_category":"Zahnarztpraxen",
    "sg:phone":"+41 31 951 51 11",
    "sg:postcode":"3073",
    "sg:province":"Bern",
    "wof:name":"Dres Med.dent. D.& S. Heiniger Zahn\u00e4rzte",
    "wof:placetype":"venue"
},
  "geometry": {"coordinates":[7.4998340607,46.9347953796],"type":"Point"}
}