{
  "type": "Feature",
  "properties": {
    "iso:country":"CH",
    "sg:address":"Via Brogeda 3",
    "sg:city":"Chiasso",
    "sg:orig_category":"G\u00fcterbef\u00f6rderung im Strassenverkehr",
    "sg:phone":"+41 91 682 70 21",
    "sg:postcode":"6830",
    "sg:province":"Ticino",
    "wof:name":"Trans Service Sa Trasporti Internazionali E Sdoganementi",
    "wof:placetype":"venue"
},
  "geometry": {"coordinates":[9.0354356766,45.8373565674],"type":"Point"}
}