{
  "type": "Feature",
  "properties": {
    "iso:country":"CH",
    "sg:address":"Rue Du Vieux-four 21",
    "sg:city":"Aire-la-ville",
    "sg:orig_category":"Politische Parteien CVP",
    "sg:phone":"+41 22 757 12 33",
    "sg:postcode":"1288",
    "sg:province":"Gen\u00e8ve",
    "wof:name":"Jeunes D\u00e9mocrates-chr\u00e9tiens Ge",
    "wof:placetype":"venue"
},
  "geometry": {"coordinates":[6.0437998772,46.1895713806],"type":"Point"}
}