{
  "type": "Feature",
  "properties": {
    "iso:country":"CH",
    "sg:address":"Burgdorfstrasse 19",
    "sg:city":"Oberdiessbach",
    "sg:orig_category":"Baugewerbe",
    "sg:postcode":"3672",
    "sg:province":"Bern",
    "wof:name":"Hans Locher Zargen-montagen",
    "wof:placetype":"venue"
},
  "geometry": {"coordinates":[9.393555,47.431656],"type":"Point"}
}