{
  "type": "Feature",
  "properties": {
    "iso:country":"CH",
    "sg:address":"Fliederweg 13",
    "sg:city":"Unterentfelden",
    "sg:orig_category":"Mechanik Mechanische Werkst\u00e4tten",
    "sg:phone":"+41 32 968 35 55",
    "sg:postcode":"5035",
    "sg:province":"Aargau",
    "wof:name":"Mbc M\u00e9canique Sa",
    "wof:placetype":"venue"
},
  "geometry": {"coordinates":[6.8385510445,47.1013450623],"type":"Point"}
}