{
  "type": "Feature",
  "properties": {
    "iso:country":"CH",
    "sg:address":"1837",
    "sg:city":"Ch\u00e2teau-d'oex",
    "sg:orig_category":"Detailhandel mit B\u00fcchern, Zeitungen, Schreib U Papeteriewaren",
    "sg:phone":"+41 26 924 68 21",
    "sg:postcode":"1837",
    "wof:name":"Paltenghi Jean-marc",
    "wof:placetype":"venue"
},
  "geometry": {"coordinates":[0.68584,45.246052],"type":"Point"}
}