{
  "type": "Feature",
  "properties": {
    "iso:country":"CH",
    "sg:address":"Rue Juste Olivier 1517",
    "sg:city":"Nyon",
    "sg:orig_category":"Detailhandel mit Waren verschiedener Art, Hauptrichtung Nahrungsmittel",
    "sg:phone":"+41 22 361 60 01",
    "sg:postcode":"1260",
    "sg:province":"Vaud",
    "wof:name":"Denner Top Superdiscount",
    "wof:placetype":"venue"
},
  "geometry": {"coordinates":[6.2384500504,46.3850402832],"type":"Point"}
}