{
  "type": "Feature",
  "properties": {
    "iso:country":"CH",
    "sg:address":"Winterthurerstrasse 511",
    "sg:city":"Z\u00fcrich",
    "sg:orig_category":"Arztpraxen",
    "sg:phone":"+41 13251050",
    "sg:postcode":"8051",
    "sg:province":"Z\u00fcrich",
    "wof:name":"Dr.med.andrea F. Cadotsch Spezialarzt Fmh",
    "wof:placetype":"venue"
},
  "geometry": {"coordinates":[8.571732,47.403885],"type":"Point"}
}