{
  "type": "Feature",
  "properties": {
    "iso:country":"CH",
    "sg:address":"Alpenstrasse 9",
    "sg:city":"Luzern",
    "sg:orig_category":"Detailhandel mit Damenbekleidung Detailhandel mit Pelzwaren",
    "sg:phone":"+41 41 410 21 20",
    "sg:postcode":"6004",
    "sg:province":"Luzern",
    "wof:name":"Elsbeth Von Arx Mode Mit Tradition",
    "wof:placetype":"venue"
},
  "geometry": {"coordinates":[8.3105602264,47.0556678772],"type":"Point"}
}