{
  "type": "Feature",
  "properties": {
    "iso:country":"CH",
    "sg:address":"4226 Breitenbach. Postfach 156",
    "sg:city":"Breitenbach",
    "sg:orig_category":"Sportvereine Ballsport Fussball",
    "sg:phone":"+41 56 633 87 42",
    "sg:postcode":"4226",
    "sg:province":"Solothurn",
    "wof:name":"Fc Bremgarten",
    "wof:placetype":"venue"
},
  "geometry": {"coordinates":[8.3392972946,47.3517303467],"type":"Point"}
}