{
  "type": "Feature",
  "properties": {
    "iso:country":"CH",
    "sg:address":"Rue Des Bonnes-luites 61",
    "sg:city":"Martigny",
    "sg:orig_category":"Grosshandel mit Obst U Gem\u00fcse",
    "sg:phone":"+41 79 332 28 28",
    "sg:postcode":"1920",
    "sg:province":"Valais",
    "wof:name":"Jean-no\u00ebl Moret Fruits & L\u00e9gumes",
    "wof:placetype":"venue"
},
  "geometry": {"coordinates":[7.0818099976,46.1091651917],"type":"Point"}
}