{
  "type": "Feature",
  "properties": {
    "iso:country":"CH",
    "sg:address":"G\u00f6ldlinstrasse 14a",
    "sg:city":"Sursee",
    "sg:orig_category":"Bauschreinerei Herstellung von Fenstern U T\u00fcren aus Holz",
    "sg:phone":"+41 41 921 26 73",
    "sg:postcode":"6210",
    "sg:province":"Luzern",
    "wof:name":"Franz Bieri Fensterbau & Schreinerei",
    "wof:placetype":"venue"
},
  "geometry": {"coordinates":[8.112205,47.169861],"type":"Point"}
}