{
  "type": "Feature",
  "properties": {
    "iso:country":"CH",
    "sg:address":"Alleestr. 7 8280 Kreuzlingen. Postfach",
    "sg:city":"Kreuzlingen",
    "sg:orig_category":"Detailhandel mit B\u00fcchern, Zeitungen, Schreib U Papeteriewaren",
    "sg:phone":"+41 55 240 38 31",
    "sg:postcode":"8280",
    "sg:province":"Thurgau",
    "wof:name":"K\u00f6hler A. Ag",
    "wof:placetype":"venue"
},
  "geometry": {"coordinates":[8.851564,47.258945],"type":"Point"}
}