{
  "type": "Feature",
  "properties": {
    "iso:country":"CH",
    "sg:address":"Avenue Du Simplon 100b",
    "sg:city":"Monthey",
    "sg:orig_category":"Detailhandel mit Teppichen Verlegen von Fussboden",
    "sg:phone":"+41 79 310 03 88",
    "sg:postcode":"1870",
    "sg:province":"Valais",
    "wof:name":"Jordan Tapis Rev\u00eatements De Sols Parquets",
    "wof:placetype":"venue"
},
  "geometry": {"coordinates":[6.9624929428,46.2456245422],"type":"Point"}
}