{
  "type": "Feature",
  "properties": {
    "iso:country":"CH",
    "sg:address":"Oberdorfstr. 6 9113 Degersheim. Postfach",
    "sg:city":"Wolfertswil",
    "sg:orig_category":"Verwertung von Milch",
    "sg:postcode":"9116",
    "sg:province":"St. Gallen",
    "wof:name":"K\u00e4serei Kn\u00f6rr",
    "wof:placetype":"venue"
},
  "geometry": {"coordinates":[9.181810379,47.3932418823],"type":"Point"}
}