{
  "type": "Feature",
  "properties": {
    "addr:full":"Via Carzo 9 Paradiso Ticino 6900",
    "addr:housenumber":"9",
    "addr:postcode":"6900",
    "addr:street":"Via Carzo",
    "iso:country":"CH",
    "sg:address":"Via Carzo 9",
    "sg:city":"Paradiso",
    "sg:orig_category":"B\u00e4ckereien",
    "sg:phone":"+41 81 413 15 65",
    "sg:postcode":"6900",
    "sg:province":"Ticino",
    "wof:name":"Charly's B\u00e4ckerei Conditorei Ag",
    "wof:placetype":"venue"
},
  "geometry": {"coordinates":[9.818411,46.791237],"type":"Point"}
}