{
  "type": "Feature",
  "properties": {
    "iso:country":"CH",
    "sg:address":"Unter-hettis",
    "sg:city":"Riemenstalden",
    "sg:orig_category":"Haltung von Rindern",
    "sg:postcode":"6452",
    "sg:province":"Schwyz",
    "wof:name":"Viehzuchtgenossenschaft Riemenstalden",
    "wof:placetype":"venue"
},
  "geometry": {"coordinates":[8.6660728455,46.9467315674],"type":"Point"}
}