{
  "type": "Feature",
  "properties": {
    "iso:country":"CH",
    "sg:address":"Ponte Piazza 9",
    "sg:city":"Mendrisio",
    "sg:orig_category":"Grosshandel mit Textilien",
    "sg:postcode":"6850",
    "sg:province":"Ticino",
    "wof:name":"Digard Trading Ltd, Douglas, Isola Di Man, Succursale Di Mendrisio",
    "wof:placetype":"venue"
},
  "geometry": {"coordinates":[8.9880838394,45.870098114],"type":"Point"}
}