{
  "type": "Feature",
  "properties": {
    "iso:country":"CH",
    "sg:address":"Rappenstrasse 13",
    "sg:city":"Effretikon",
    "sg:orig_category":"Sportvereine Ballsport Handball",
    "sg:postcode":"8307",
    "sg:province":"Z\u00fcrich",
    "wof:name":"Gr\u00fcn-weiss Utzenstorf",
    "wof:placetype":"venue"
},
  "geometry": {"coordinates":[7.5540518761,47.1519165039],"type":"Point"}
}