{
  "type": "Feature",
  "properties": {
    "iso:country":"CH",
    "sg:address":"Dorfstrasse 1",
    "sg:city":"Einigen",
    "sg:orig_category":"Gartenbau",
    "sg:phone":"+41 79 310 26 46",
    "sg:postcode":"3646",
    "sg:province":"Bern",
    "wof:name":"G\u00e4rtnerei Einigen Marianne Philippin",
    "wof:placetype":"venue"
},
  "geometry": {"coordinates":[7.6497130394,46.70677948],"type":"Point"}
}