{
  "type": "Feature",
  "properties": {
    "iso:country":"CH",
    "sg:address":"Flurhofstrasse 154",
    "sg:city":"St.gallen",
    "sg:orig_category":"Herstellung von sonstigen Waren aus Papier, Karton U Pappe",
    "sg:phone":"+41 71 282 21 26",
    "sg:postcode":"9000",
    "sg:province":"St. Gallen",
    "wof:name":"Sk-etikettenfabrik Ag",
    "wof:placetype":"venue"
},
  "geometry": {"coordinates":[9.4033842087,47.4315567017],"type":"Point"}
}