{
  "type": "Feature",
  "properties": {
    "iso:country":"CH",
    "sg:address":"Nefenstrasse 30 9434 Au Sg. Postfach",
    "sg:city":"Heerbrugg",
    "sg:orig_category":"Non-Classified Establishments",
    "sg:phone":"+41 71 727 51 51",
    "sg:postcode":"9435",
    "sg:province":"St. Gallen",
    "wof:name":"Sfs Handels Holding Ag",
    "wof:placetype":"venue"
},
  "geometry": {"coordinates":[9.6351919174,47.4310073853],"type":"Point"}
}