{
  "type": "Feature",
  "properties": {
    "iso:country":"CH",
    "sg:address":"4632",
    "sg:city":"Trimbach",
    "sg:orig_category":"Wirtschaftsverb\u00e4nde Gewerbeverb\u00e4nde/-vereine",
    "sg:phone":"+41 52 319 11 75",
    "sg:postcode":"4632",
    "sg:province":"Solothurn",
    "wof:name":"Gewerbeverein Tr\u00fcllikon-benken",
    "wof:placetype":"venue"
},
  "geometry": {"coordinates":[8.6530704498,47.6534919739],"type":"Point"}
}