{
  "type": "Feature",
  "properties": {
    "iso:country":"CH",
    "sg:address":"Chalet Les M\u00e9l\u00e8zes 3962 Montana. Postfach",
    "sg:city":"Montana",
    "sg:orig_category":"Vermietung von Gebrauchsg\u00fctern",
    "sg:phone":"+41 26 676 01 17",
    "sg:postcode":"3962",
    "wof:name":"Schneider Locations",
    "wof:placetype":"venue"
},
  "geometry": {"coordinates":[6.99000597,46.8513832092],"type":"Point"}
}