{
  "type": "Feature",
  "properties": {
    "iso:country":"CH",
    "sg:address":"R\u00fctenenstrasse 6b",
    "sg:city":"Oberengstringen",
    "sg:orig_category":"Softwareentwicklung U beratung",
    "sg:phone":"+41 17752224",
    "sg:postcode":"8102",
    "sg:province":"Z\u00fcrich",
    "wof:name":"Soft House, Bruno Mathieu",
    "wof:placetype":"venue"
},
  "geometry": {"coordinates":[8.4632453918,47.4131355286],"type":"Point"}
}