{
  "type": "Feature",
  "properties": {
    "iso:country":"CH",
    "sg:address":"Riedgasse 5 4912 Aarwangen. Postfach",
    "sg:city":"Aarwangen",
    "sg:orig_category":"Landwirtschaftliche Genossenschaften",
    "sg:phone":"+41 62 922 24 20",
    "sg:postcode":"4912",
    "sg:province":"Bern",
    "wof:name":"Landw.genossenschaft Aarwangen & Umgebung",
    "wof:placetype":"venue"
},
  "geometry": {"coordinates":[7.769744873,47.2410697937],"type":"Point"}
}