{
  "type": "Feature",
  "properties": {
    "iso:country":"CH",
    "sg:address":"Oberdorf 68.",
    "sg:city":"Beringen",
    "sg:orig_category":"Allgemeiner Hoch U Tiefbau",
    "sg:phone":"+41 71 757 87 57",
    "sg:postcode":"8222",
    "sg:province":"Schaffhausen",
    "wof:name":"Hasler F. Ag",
    "wof:placetype":"venue"
},
  "geometry": {"coordinates":[9.547438,47.382423],"type":"Point"}
}