{
  "type": "Feature",
  "properties": {
    "iso:country":"CH",
    "sg:address":"Sch\u00fcrh\u00f6lzlistrasse 272",
    "sg:city":"Glattbrugg",
    "sg:orig_category":"Unclassifiable Establishments",
    "sg:postcode":"8152",
    "sg:province":"Z\u00fcrich",
    "wof:name":"Freitag Architektur Gmbh",
    "wof:placetype":"venue"
},
  "geometry": {"coordinates":[8.6309499741,47.0294799805],"type":"Point"}
}