{
  "type": "Feature",
  "properties": {
    "iso:country":"CH",
    "sg:address":"Netzibodenstrasse 21",
    "sg:city":"Pratteln",
    "sg:orig_category":"Non-Classified Establishments",
    "sg:postcode":"4133",
    "sg:province":"Basel-Landschaft",
    "wof:name":"Asag Auto-service Ag Filiale Pratteln-netziboden",
    "wof:placetype":"venue"
},
  "geometry": {"coordinates":[7.7027540207,47.5317001343],"type":"Point"}
}