{
  "type": "Feature",
  "properties": {
    "iso:country":"CH",
    "sg:address":"Chemin Du Riant-coteau 11",
    "sg:city":"Gland",
    "sg:orig_category":"Sonstiger Detailhandel mit Metallwaren, Anstrichmitteln, Glaswaren, Bau U Heimwerkerbedarf",
    "sg:phone":"+41 22 301 40 80",
    "sg:postcode":"1196",
    "sg:province":"Vaud",
    "wof:name":"Jordan Peinture Sa",
    "wof:placetype":"venue"
},
  "geometry": {"coordinates":[6.1426239014,46.1857185364],"type":"Point"}
}