{
  "type": "Feature",
  "properties": {
    "iso:country":"CH",
    "sg:address":"Fischerweg 17 3012 Bern. Postfach",
    "sg:city":"Bern",
    "sg:orig_category":"Handels-H\u00e4user U Gesellschaften",
    "sg:phone":"+41 56 622 82 71",
    "sg:postcode":"3005",
    "sg:province":"Bern",
    "wof:name":"Heinz Gr\u00e4ser, Handelsagentur",
    "wof:placetype":"venue"
},
  "geometry": {"coordinates":[8.2877264023,47.3446998596],"type":"Point"}
}