{
  "type": "Feature",
  "properties": {
    "iso:country":"CH",
    "sg:address":"1718",
    "sg:city":"Rechthalten",
    "sg:orig_category":"Sportvereine Sch\u00fctzen",
    "sg:postcode":"1718",
    "sg:province":"Fribourg",
    "wof:name":"Sch\u00fctzengesellschaft",
    "wof:placetype":"venue"
},
  "geometry": {"coordinates":[7.2161898613,46.7434501648],"type":"Point"}
}