{
  "type": "Feature",
  "properties": {
    "iso:country":"CH",
    "sg:address":"Via Passeggiata 24",
    "sg:city":"Balerna",
    "sg:classifiers":[
        {
            "category":"Airport",
            "type":"Transportation"
        }
    ],
    "sg:phone":"+41 91 695 06 06",
    "sg:postcode":"6828",
    "sg:province":"Ticino",
    "sg:tags":[
        "air-freight",
        "forwarders"
    ],
    "wof:name":"Abx Logistic / Saima Sa",
    "wof:placetype":"venue"
},
  "geometry": {"coordinates":[9.011195,45.835854],"type":"Point"}
}