{
  "type": "Feature",
  "properties": {
    "iso:country":"CH",
    "sg:address":"Ringstrasse 37 7000 Chur. Postfach 170",
    "sg:city":"Chur",
    "sg:orig_category":"Elektroinstallation",
    "sg:phone":"+41 81 253 07 08",
    "sg:postcode":"7006",
    "sg:province":"Graubunden",
    "wof:name":"Giger + Storz",
    "wof:placetype":"venue"
},
  "geometry": {"coordinates":[9.5151882172,46.8547096252],"type":"Point"}
}