{
  "type": "Feature",
  "properties": {
    "iso:country":"CH",
    "sg:address":"Frontenex Avenue De 6 1207 Gen\u00e8ve. Postfach",
    "sg:city":"Gen\u00e8ve",
    "sg:orig_category":"Grosshandel mit sonstigen Maschinen U Ausr\u00fcstungen f\u00fcr Industrie, Handel U Schiffahrt",
    "sg:postcode":"1207",
    "sg:province":"Gen\u00e8ve",
    "wof:name":"Onechem Ltd., Hamilton, Geneva Branch E-commerce Pour L'industrie Chimique Etc.; Vente Et Marketing",
    "wof:placetype":"venue"
},
  "geometry": {"coordinates":[6.1570000648,46.2016677856],"type":"Point"}
}