{
  "type": "Feature",
  "properties": {
    "iso:country":"CH",
    "sg:address":"Seeblickstrasse 10c",
    "sg:city":"Kreuzlingen",
    "sg:orig_category":"Elektroinstallation Informatikdienste",
    "sg:phone":"+41 71 672 30 30",
    "sg:postcode":"8280",
    "sg:province":"Thurgau",
    "wof:name":"Elektro Schwarz Gmbh",
    "wof:placetype":"venue"
},
  "geometry": {"coordinates":[9.1653614044,47.6420326233],"type":"Point"}
}