{
  "type": "Feature",
  "properties": {
    "iso:country":"CH",
    "sg:address":"Kleinfeldstrasse 9",
    "sg:city":"Winznau",
    "sg:orig_category":"Fussreflexzonenmassage",
    "sg:phone":"+41 79 683 72 00",
    "sg:postcode":"4652",
    "sg:province":"Solothurn",
    "wof:name":"Sonja M\u00e4chler Fussreflexzonen-massage",
    "wof:placetype":"venue"
},
  "geometry": {"coordinates":[7.9325389862,47.3632926941],"type":"Point"}
}