{
  "type": "Feature",
  "properties": {
    "iso:country":"CH",
    "sg:address":"Place Du March\u00e9 3",
    "sg:city":"Aubonne",
    "sg:orig_category":"Erbringung von Dienstleistungen f\u00fcr Unternehmen Innendekorationsateliers",
    "sg:phone":"+41 21 807 25 46",
    "sg:postcode":"1170",
    "sg:province":"Vaud",
    "wof:name":"Image De Marc, M.-h. Vallon",
    "wof:placetype":"venue"
},
  "geometry": {"coordinates":[6.3915982246,46.4951019287],"type":"Point"}
}