{
  "type": "Feature",
  "properties": {
    "iso:country":"CH",
    "sg:address":"Albert-anker-weg 12 2502 Biel/bienne Case Postale 869",
    "sg:city":"Biel/bienne",
    "sg:orig_category":"Schreib U \u00dcbersetzungsb\u00fcros -\u00dcbersetzungsb\u00fcros",
    "sg:phone":"+41 32 322 17 17",
    "sg:postcode":"2502",
    "sg:province":"Bern",
    "wof:name":"Dactyquick Sa",
    "wof:placetype":"venue"
},
  "geometry": {"coordinates":[7.2391781807,47.1358032227],"type":"Point"}
}