{
  "type": "Feature",
  "properties": {
    "iso:country":"CH",
    "sg:address":"Impasse Alphonse-albert 5",
    "sg:city":"Hauterive",
    "sg:orig_category":"Herstellung der Ausstattung von Uhren Herstellung von Uhren",
    "sg:phone":"+41 32 654 10 54",
    "sg:postcode":"2068",
    "sg:province":"Neuch\u00e2tel",
    "wof:name":"Estima Ag",
    "wof:placetype":"venue"
},
  "geometry": {"coordinates":[7.3872637749,47.1983184814],"type":"Point"}
}