{
  "type": "Feature",
  "properties": {
    "addr:full":"Avenue De La Gare 18 1950 Sion Case Postale 6 Sion Valais 1951",
    "addr:housenumber":"18;6",
    "addr:postcode":"1950;1951",
    "addr:street":"Avenue De La Gare;Postale",
    "iso:country":"CH",
    "sg:address":"Avenue De La Gare 18 1950 Sion Case Postale 6",
    "sg:city":"Sion",
    "sg:orig_category":"Arbeitnehmerverb\u00e4nde",
    "sg:postcode":"1951",
    "sg:province":"Valais",
    "wof:name":"Assoc.suisse Des Employ\u00e9s De Banque,sect.vs,monsieur J.praz",
    "wof:placetype":"venue"
},
  "geometry": {"coordinates":[7.358678,46.229713],"type":"Point"}
}