{
  "type": "Feature",
  "properties": {
    "iso:country":"CH",
    "sg:address":"Quellenstrasse 6",
    "sg:city":"Z\u00fcrich",
    "sg:orig_category":"RESTAURANTS: TEA-ROOMS",
    "sg:postcode":"8005",
    "sg:province":"Z\u00fcrich",
    "wof:name":"Netsang",
    "wof:placetype":"venue"
},
  "geometry": {"coordinates":[8.5278205872,47.3844070435],"type":"Point"}
}