{
  "type": "Feature",
  "properties": {
    "iso:country":"CH",
    "sg:address":"5018",
    "sg:city":"Erlinsbach",
    "sg:orig_category":"Primarschulen",
    "sg:phone":"+41 62 844 20 49",
    "sg:postcode":"5018",
    "sg:province":"Solothurn",
    "wof:name":"Primarschule Schulhaus 1882",
    "wof:placetype":"venue"
},
  "geometry": {"coordinates":[8.0058498383,47.4123191833],"type":"Point"}
}