{
  "type": "Feature",
  "properties": {
    "iso:country":"CH",
    "sg:address":"Dorfplatz 2 6374 Buochs. Postfach 244",
    "sg:city":"Buochs",
    "sg:orig_category":"HOTELS: MIT RESTAURANT Kongress- and Tagungshotels mit Restaurant",
    "sg:phone":"+41 41 620 08 20",
    "sg:postcode":"6374",
    "sg:province":"Nidwalden",
    "wof:name":"Hotel Krone",
    "wof:placetype":"venue"
},
  "geometry": {"coordinates":[8.4205350876,46.9734802246],"type":"Point"}
}