{
  "type": "Feature",
  "properties": {
    "iso:country":"CH",
    "sg:address":"Verger Des Planches 1860 Aigle. Postfach",
    "sg:city":"Aigle",
    "sg:orig_category":"Herstellung von Konstruktionsteilen, Fertigbauteilen U Ausbauelementen aus Holz",
    "sg:postcode":"1860",
    "sg:province":"Vaud",
    "wof:name":"Boitech Sa",
    "wof:placetype":"venue"
},
  "geometry": {"coordinates":[6.9701099396,46.3175544739],"type":"Point"}
}