{
  "type": "Feature",
  "properties": {
    "iso:country":"CH",
    "sg:address":"Beim Tenniscenter",
    "sg:city":"Fiesch",
    "sg:orig_category":"Instandhaltung U Reparatur von Automobilen",
    "sg:phone":"+41 32 931 82 80",
    "sg:postcode":"3984",
    "sg:province":"Valais",
    "wof:name":"Garage Et Carrosserie Burkhalter",
    "wof:placetype":"venue"
},
  "geometry": {"coordinates":[6.7501001358,47.0513153076],"type":"Point"}
}