{
  "type": "Feature",
  "properties": {
    "iso:country":"CH",
    "sg:address":"1407",
    "sg:city":"Donneloye",
    "sg:orig_category":"Primarschulen",
    "sg:postcode":"1407",
    "sg:province":"Vaud",
    "wof:name":"Ecole Primaire",
    "wof:placetype":"venue"
},
  "geometry": {"coordinates":[6.7151279449,46.7428970337],"type":"Point"}
}