{
  "type": "Feature",
  "properties": {
    "iso:country":"CH",
    "sg:address":"Kirchgasse 11",
    "sg:city":"Oberburg",
    "sg:orig_category":"Vorschulen, Kinderg\u00e4rten",
    "sg:phone":"+41 34 422 12 88",
    "sg:postcode":"3414",
    "sg:province":"Bern",
    "wof:name":"Kindergarten Bei Der Kirche",
    "wof:placetype":"venue"
},
  "geometry": {"coordinates":[7.6206440926,47.0394096375],"type":"Point"}
}