{
  "type": "Feature",
  "properties": {
    "iso:country":"CH",
    "sg:address":"Zenzachweg 12",
    "sg:city":"Wintersingen",
    "sg:orig_category":"Sonstige mit der Informatik verbundene T\u00e4tigkeiten",
    "sg:phone":"+41 87877850",
    "sg:postcode":"4451",
    "sg:province":"Basel-Landschaft",
    "wof:name":"Richinfo Gmbh",
    "wof:placetype":"venue"
},
  "geometry": {"coordinates":[7.8314352036,47.4944763184],"type":"Point"}
}