{
  "type": "Feature",
  "properties": {
    "iso:country":"CH",
    "sg:address":"Langstrasse 14",
    "sg:city":"Z\u00fcrich",
    "sg:orig_category":"Betrieb U technische Hilfsdienste des Kultur U Unterhaltungswesens Sonstige Hilfsdienste des Kultur ",
    "sg:phone":"+41 12410321",
    "sg:postcode":"8004",
    "sg:province":"Z\u00fcrich",
    "wof:name":"Studio Anklang Koch Philippe",
    "wof:placetype":"venue"
},
  "geometry": {"coordinates":[8.524708,47.374912],"type":"Point"}
}