{
  "type": "Feature",
  "properties": {
    "iso:country":"CH",
    "sg:address":"H\u00f6heweg 115 3800 Interlaken. Postfach 446",
    "sg:city":"Interlaken",
    "sg:orig_category":"RESTAURANTS: TEA-ROOMS",
    "sg:phone":"+41 32 913 63 48",
    "sg:postcode":"3800",
    "sg:province":"Bern",
    "wof:name":"Restaurant Des Chasseurs S\u00e0rl",
    "wof:placetype":"venue"
},
  "geometry": {"coordinates":[6.8207449913,47.1014595032],"type":"Point"}
}