{
  "type": "Feature",
  "properties": {
    "iso:country":"CH",
    "sg:address":"Sonneland 9",
    "sg:city":"Neuenkirch",
    "sg:orig_category":"Wirtschaftspr\u00fcfung, Steuerberatung U Treuhand",
    "sg:phone":"+41 41 467 28 49",
    "sg:postcode":"6206",
    "sg:province":"Luzern",
    "wof:name":"Hans Amstalden Treuhandb\u00fcro",
    "wof:placetype":"venue"
},
  "geometry": {"coordinates":[8.19734478,47.1002426147],"type":"Point"}
}