{
  "type": "Feature",
  "properties": {
    "iso:country":"CH",
    "sg:address":"Bonergasse 22 4057 Basel. Postfach",
    "sg:city":"Basel",
    "sg:orig_category":"Interessenvertretungen",
    "sg:phone":"+41 61 639 91 50",
    "sg:postcode":"4051",
    "sg:province":"Basel-Stadt",
    "wof:name":"Stiftung Eo-ausgleichs-erg\u00e4nzungskasse Des Verbands Basler Elektro-installationsfirmen",
    "wof:placetype":"venue"
},
  "geometry": {"coordinates":[7.5915260315,47.5842933655],"type":"Point"}
}