{
  "type": "Feature",
  "properties": {
    "iso:country":"CH",
    "sg:address":"Via Guisan 16 6900 Paradiso. Postfach Caselle Postale 185",
    "sg:city":"Paradiso",
    "sg:orig_category":"Grosshandel mit festen Brennstoffen U Mineral\u00f6lerzeugnissen",
    "sg:phone":"+41 91 994 82 91",
    "sg:postcode":"6900",
    "sg:province":"Ticino",
    "wof:name":"Termoil Sa",
    "wof:placetype":"venue"
},
  "geometry": {"coordinates":[8.9468545914,45.9908218384],"type":"Point"}
}