{
  "type": "Feature",
  "properties": {
    "iso:country":"CH",
    "sg:address":"Chemin Louis-d\u00e9gailler 9a",
    "sg:city":"Versoix",
    "sg:orig_category":"Bauspenglerei Sanit\u00e4rinstallation",
    "sg:phone":"+41 22 755 42 82",
    "sg:postcode":"1290",
    "sg:province":"Gen\u00e8ve",
    "wof:name":"G\u00e9rard Schmid Inst.sanitaires & Ferblanterie",
    "wof:placetype":"venue"
},
  "geometry": {"coordinates":[6.163068,46.280499],"type":"Point"}
}