{
  "type": "Feature",
  "properties": {
    "iso:country":"CH",
    "sg:address":"3863",
    "sg:city":"Nessental",
    "sg:orig_category":"Primarschulen",
    "sg:phone":"+41 33 975 11 79",
    "sg:postcode":"3863",
    "sg:province":"Bern",
    "wof:name":"Primarschule",
    "wof:placetype":"venue"
},
  "geometry": {"coordinates":[8.2956600189,46.720451355],"type":"Point"}
}