{
  "type": "Feature",
  "properties": {
    "iso:country":"CH",
    "sg:address":"Rainlih\u00f6he 31",
    "sg:city":"Horw",
    "sg:orig_category":"Sportvereine Eissport Curling",
    "sg:phone":"+41 41 854 31 31",
    "sg:postcode":"6048",
    "sg:province":"Luzern",
    "wof:name":"C.c.k\u00fcssnacht Am Rigi",
    "wof:placetype":"venue"
},
  "geometry": {"coordinates":[8.4392709732,47.0756225586],"type":"Point"}
}