{
  "type": "Feature",
  "properties": {
    "iso:country":"CH",
    "sg:address":"Via Besso 7",
    "sg:city":"Lugano",
    "sg:orig_category":"Fachdetailhandel mit pharmazeutischen Produkten",
    "sg:phone":"+41 91 966 07 22",
    "sg:postcode":"6900",
    "sg:province":"Ticino",
    "wof:name":"Farmacia P.asilio-san Nicolao",
    "wof:placetype":"venue"
},
  "geometry": {"coordinates":[8.9437675476,46.0058555603],"type":"Point"}
}