{
  "type": "Feature",
  "properties": {
    "iso:country":"CH",
    "sg:address":"Nauenstrasse 55 4052 Basel. Postfach",
    "sg:city":"Basel",
    "sg:orig_category":"Buchverlag Verlagsgewerbe",
    "sg:phone":"+41 61 272 90 09",
    "sg:postcode":"4002",
    "sg:province":"Basel-Stadt",
    "wof:name":"Becker Dr. & Partner Ag, Verlag F\u00fcr Ganzheitsmedizin",
    "wof:placetype":"venue"
},
  "geometry": {"coordinates":[7.593923,47.547077],"type":"Point"}
}