{
  "type": "Feature",
  "properties": {
    "addr:full":"1941 Voll\u00e8ges Valais 1941",
    "addr:housenumber":"1941",
    "addr:postcode":"1941",
    "iso:country":"CH",
    "sg:address":"1941",
    "sg:city":"Voll\u00e8ges",
    "sg:orig_category":"Dachdeckerei Zimmerei, Ingenieurholzbau",
    "sg:phone":"+41 27 785 14 03",
    "sg:postcode":"1941",
    "sg:province":"Valais",
    "wof:name":"Frossard Fr\u00e8res Charpente & Couverture",
    "wof:placetype":"venue"
},
  "geometry": {"coordinates":[7.16936,46.087112],"type":"Point"}
}