{
  "type": "Feature",
  "properties": {
    "iso:country":"CH",
    "sg:address":"1441",
    "sg:city":"Valeyres-montagny",
    "sg:orig_category":"Landesverteidigung, Sozialversicherung \u00d6ffentliche Verwaltung",
    "sg:phone":"+41 24 459 18 16",
    "sg:postcode":"1441",
    "sg:province":"Vaud",
    "wof:name":"Centre De Protection Civile",
    "wof:placetype":"venue"
},
  "geometry": {"coordinates":[6.5610051155,46.8027954102],"type":"Point"}
}