{
  "type": "Feature",
  "properties": {
    "addr:full":"B\u00fchlstrasse 70 8583 Sulgen. Postfach Luzern Luzern 6003",
    "addr:housenumber":"70",
    "addr:postcode":"8583 sulgen. postfach;6003",
    "addr:street":"Buehlstrasse",
    "iso:country":"CH",
    "sg:address":"B\u00fchlstrasse 70 8583 Sulgen. Postfach",
    "sg:city":"Luzern",
    "sg:orig_category":"Allgemeiner Hoch U Tiefbau",
    "sg:postcode":"6003",
    "sg:province":"Luzern",
    "wof:name":"Burger Bau-allround Gmbh",
    "wof:placetype":"venue"
},
  "geometry": {"coordinates":[8.172459,47.426491],"type":"Point"}
}