{
  "type": "Feature",
  "properties": {
    "addr:full":"Zugerstrasse 56f Cham Zug 6330",
    "addr:housenumber":"56f",
    "addr:postcode":"6330",
    "addr:street":"Zugerstrasse;Zug",
    "iso:country":"CH",
    "sg:address":"Zugerstrasse 56f",
    "sg:city":"Cham",
    "sg:orig_category":"Arztpraxen",
    "sg:phone":"+41 41 780 74 88",
    "sg:postcode":"6330",
    "sg:province":"Zug",
    "wof:name":"Dr.med.markus Nuber Spezialarzt",
    "wof:placetype":"venue"
},
  "geometry": {"coordinates":[8.46794,47.18203],"type":"Point"}
}