{
  "type": "Feature",
  "properties": {
    "iso:country":"CH",
    "sg:address":"Wilerstrasse 33",
    "sg:city":"Bazenheid",
    "sg:orig_category":"Offsetdruck",
    "sg:phone":"+41 71 930 01 65",
    "sg:postcode":"9602",
    "sg:province":"St. Gallen",
    "wof:name":"Schneider Scherrer Ag Satz & Druck",
    "wof:placetype":"venue"
},
  "geometry": {"coordinates":[9.0678043365,47.4138755798],"type":"Point"}
}