{
  "type": "Feature",
  "properties": {
    "iso:country":"CH",
    "sg:address":"Gemeindestrasse 11",
    "sg:city":"Widen",
    "sg:orig_category":"Datenverarbeitungsdienste",
    "sg:phone":"+41 56 633 60 04",
    "sg:postcode":"8967",
    "sg:province":"Aargau",
    "wof:name":"Ren\u00e9 Barro Edv-beratung",
    "wof:placetype":"venue"
},
  "geometry": {"coordinates":[8.358508,47.367462],"type":"Point"}
}