{
  "type": "Feature",
  "properties": {
    "iso:country":"CH",
    "sg:address":"Schulstrasse 14 5070 Frick. Postfach",
    "sg:city":"Frick",
    "sg:orig_category":"Herstellung von Maschinen f\u00fcr die Textil, Bekleidungsherstellung U die Lederverarbeitung Herstellung",
    "sg:phone":"+41 62 865 51 11",
    "sg:postcode":"5070",
    "sg:province":"Aargau",
    "wof:name":"Jakob M\u00fcller Ag Maschinenfabrik",
    "wof:placetype":"venue"
},
  "geometry": {"coordinates":[8.0208625793,47.5054321289],"type":"Point"}
}