{
  "type": "Feature",
  "properties": {
    "iso:country":"CH",
    "sg:address":"6594",
    "sg:city":"Contone",
    "sg:orig_category":"Sonstiger Grosshandel",
    "sg:postcode":"6594",
    "sg:province":"Ticino",
    "wof:name":"Koller A.",
    "wof:placetype":"venue"
},
  "geometry": {"coordinates":[9.223862648,47.1962242126],"type":"Point"}
}