{
  "type": "Feature",
  "properties": {
    "iso:country":"CH",
    "sg:address":"Kanalstrasse 30",
    "sg:city":"Vaduz",
    "sg:orig_category":"Herstellung von Metallerzeugnissen ohne Maschinenbau",
    "sg:postcode":"9490",
    "wof:name":"Isag Apparate & Ger\u00e4tebau",
    "wof:placetype":"venue"
},
  "geometry": {"coordinates":[9.5213031769,47.1239280701],"type":"Point"}
}