{
  "type": "Feature",
  "properties": {
    "iso:country":"CH",
    "sg:address":"1675",
    "sg:city":"Vauderens",
    "sg:orig_category":"Detailhandel mit Waren verschiedener Art, Hauptrichtung Nahrungsmittel Grosshandel mit Nahrungsmitte",
    "sg:phone":"+41 33 849 13 49",
    "sg:postcode":"1675",
    "sg:province":"Fribourg",
    "wof:name":"Pizzati-grossmann Theres",
    "wof:placetype":"venue"
},
  "geometry": {"coordinates":[7.963599205,46.737651825],"type":"Point"}
}