{
  "type": "Feature",
  "properties": {
    "iso:country":"CH",
    "sg:address":"B\u00fcndtetalweg 28",
    "sg:city":"Obermumpf",
    "sg:orig_category":"Erdbewegungsarbeiten",
    "sg:phone":"+41 62 873 11 08",
    "sg:postcode":"4324",
    "sg:province":"Aargau",
    "wof:name":"Josef Meichtry Baggerbetrieb",
    "wof:placetype":"venue"
},
  "geometry": {"coordinates":[7.9327669144,47.5353507996],"type":"Point"}
}