{
  "type": "Feature",
  "properties": {
    "iso:country":"CH",
    "sg:address":"In Der Weid 17",
    "sg:city":"Goldach",
    "sg:orig_category":"Einzelhandel mit Automobilen Instandhaltung U Reparatur von Automobilen",
    "sg:phone":"+41 71 222 19 13",
    "sg:postcode":"9403",
    "sg:province":"St. Gallen",
    "wof:name":"Abc Automobile Ag",
    "wof:placetype":"venue"
},
  "geometry": {"coordinates":[9.4676218033,47.4682426453],"type":"Point"}
}