{
  "type": "Feature",
  "properties": {
    "addr:full":"Oberer Breitenweg 12 3652 Hilterfingen. Postfach Hilterfingen Bern 3652",
    "addr:housenumber":"12",
    "addr:postcode":"3652 hilterfingen. postfach;3652",
    "addr:street":"Oberer Breitenweg",
    "iso:country":"CH",
    "sg:address":"Oberer Breitenweg 12 3652 Hilterfingen. Postfach",
    "sg:city":"Hilterfingen",
    "sg:orig_category":"Architektur U Ingenieurb\u00fcros",
    "sg:postcode":"3652",
    "sg:province":"Bern",
    "wof:name":"Acrobat Services Gmbh Technische Ingenieurdienstleistungen In Der Medizintechnik Usw.",
    "wof:placetype":"venue"
},
  "geometry": {"coordinates":[7.655929,46.743023],"type":"Point"}
}