{
  "type": "Feature",
  "properties": {
    "iso:country":"CH",
    "sg:address":"Hauptstrasse 5",
    "sg:city":"Lienz",
    "sg:classifiers":[
        {
            "category":"Banks & Credit Unions",
            "subcategory":"Bank",
            "type":"Services"
        }
    ],
    "sg:phone":"+41 33 744 35 03",
    "sg:postcode":"9464",
    "sg:province":"St. Gallen",
    "wof:name":"Raiffeisenbank Saanenland",
    "wof:placetype":"venue"
},
  "geometry": {"coordinates":[7.33046,46.478432],"type":"Point"}
}