{
  "type": "Feature",
  "properties": {
    "iso:country":"CH",
    "sg:address":"Dorfstr. 22",
    "sg:city":"Gersau",
    "sg:classifiers":[
        {
            "category":"Banks & Credit Unions",
            "subcategory":"Bank",
            "type":"Services"
        }
    ],
    "sg:phone":"+41 33 972 10 80",
    "sg:postcode":"6442",
    "sg:province":"Schwyz",
    "wof:name":"Raiffeisenbank Innertkirchen",
    "wof:placetype":"venue"
},
  "geometry": {"coordinates":[8.22809,46.705429],"type":"Point"}
}