{
  "type": "Feature",
  "properties": {
    "iso:country":"CH",
    "sg:address":"Hauptstrasse 84",
    "sg:city":"Aesch",
    "sg:classifiers":[
        {
            "category":"Manufacturing",
            "subcategory":"Printing",
            "type":"Manufacturing & Wholesale Goods"
        }
    ],
    "sg:phone":"+41 71 282 48 80",
    "sg:postcode":"4147",
    "sg:province":"Basel-Landschaft",
    "sg:tags":[
        "house",
        "book"
    ],
    "wof:name":"Niedermann Druck Ag",
    "wof:placetype":"venue"
},
  "geometry": {"coordinates":[9.41591,47.443989],"type":"Point"}
}