{
  "type": "Feature",
  "properties": {
    "iso:country":"CH",
    "sg:address":"Eymattstrasse 109",
    "sg:city":"Hinterkappelen",
    "sg:orig_category":"Fahrschulen, Flugschulen",
    "sg:phone":"+41 79 652 02 00",
    "sg:postcode":"3032",
    "sg:province":"Bern",
    "wof:name":"Liz Gerber Autofahrschule",
    "wof:placetype":"venue"
},
  "geometry": {"coordinates":[7.3730387688,46.924331665],"type":"Point"}
}