{
  "type": "Feature",
  "properties": {
    "iso:country":"CH",
    "sg:address":"Redingstrasse 2",
    "sg:city":"Kreuzlingen",
    "sg:orig_category":"Sportvereine",
    "sg:phone":"+41 71 672 79 45",
    "sg:postcode":"8280",
    "sg:province":"Thurgau",
    "wof:name":"Selbstverteidigungs-club Svck",
    "wof:placetype":"venue"
},
  "geometry": {"coordinates":[9.1641483307,47.6474990845],"type":"Point"}
}