{
  "type": "Feature",
  "properties": {
    "iso:country":"CH",
    "sg:address":"Rietstasse 10",
    "sg:city":"Zollikon",
    "sg:orig_category":"Architektur U Ingenieurb\u00fcros",
    "sg:phone":"+41 13915965",
    "sg:postcode":"8702",
    "sg:province":"Z\u00fcrich",
    "wof:name":"Pegazo Technische Beratungen Peter W. Gassmann",
    "wof:placetype":"venue"
},
  "geometry": {"coordinates":[8.573865,47.340435],"type":"Point"}
}