{
  "type": "Feature",
  "properties": {
    "iso:country":"CH",
    "sg:address":"Lindenstrasse 42",
    "sg:city":"Allschwil",
    "sg:orig_category":"Elektroinstallation Herstellung von Radio U Fernsehger\u00e4ten sowie phono U videotechnischen Ger\u00e4ten",
    "sg:phone":"+41 61 483 04 83",
    "sg:postcode":"4123",
    "sg:province":"Basel-Landschaft",
    "wof:name":"Ammann Heinz Elektro-telekommunikationsinstallationen",
    "wof:placetype":"venue"
},
  "geometry": {"coordinates":[7.5614848137,47.5590286255],"type":"Point"}
}