{
  "type": "Feature",
  "properties": {
    "iso:country":"CH",
    "sg:address":"Zollstrasse 95 8212 Neuhausen. Postfach",
    "sg:city":"Neuhausen",
    "sg:orig_category":"Detailhandel mit M\u00f6beln U Haushaltsgegenst\u00e4nden",
    "sg:postcode":"8212",
    "sg:province":"Schaffhausen",
    "wof:name":"Aks M\u00f6belparadies Erdogan M.",
    "wof:placetype":"venue"
},
  "geometry": {"coordinates":[8.5997533798,47.6750297546],"type":"Point"}
}