{
  "type": "Feature",
  "properties": {
    "iso:country":"CH",
    "sg:address":"Obergasse 2",
    "sg:city":"Uznach",
    "sg:orig_category":"Shiatsu-Therapie",
    "sg:phone":"+41 55 280 63 17",
    "sg:postcode":"8730",
    "sg:province":"St. Gallen",
    "wof:name":"Edith Zimmermann Massagen & Shiatsu",
    "wof:placetype":"venue"
},
  "geometry": {"coordinates":[8.9851236343,47.2244338989],"type":"Point"}
}