{
  "type": "Feature",
  "properties": {
    "iso:country":"CH",
    "sg:address":"Route D'yverdon 12",
    "sg:city":"Pr\u00e9verenges",
    "sg:orig_category":"Detailhandel mit Fleisch U Fleischwaren",
    "sg:phone":"+41 21 802 13 13",
    "sg:postcode":"1028",
    "sg:province":"Vaud",
    "wof:name":"Beef Club Home Service Sa",
    "wof:placetype":"venue"
},
  "geometry": {"coordinates":[6.7836098671,46.8176498413],"type":"Point"}
}