{
  "type": "Feature",
  "properties": {
    "iso:country":"CH",
    "sg:address":"Balgriststrasse 106 8008 Z\u00fcrich. Postfach",
    "sg:city":"Z\u00fcrich",
    "sg:orig_category":"Druck ohne Zeitungsdruck",
    "sg:phone":"+41 13811662",
    "sg:postcode":"8001",
    "sg:province":"Z\u00fcrich",
    "wof:name":"Silkprint Kettner R. Reklameplakate, Druckauftr\u00e4ge Im Siebdruckverfahren Usw",
    "wof:placetype":"venue"
},
  "geometry": {"coordinates":[8.5787038803,47.3539428711],"type":"Point"}
}