{
  "type": "Feature",
  "properties": {
    "iso:country":"CH",
    "sg:address":"Westquaistrasse 12",
    "sg:city":"Basel",
    "sg:orig_category":"Buchf\u00fchrung Wirtschaftspr\u00fcfung, Steuerberatung U Treuhand",
    "sg:phone":"+41 19301754",
    "sg:postcode":"4057",
    "sg:province":"Basel-Stadt",
    "wof:name":"Orga Office Gmbh",
    "wof:placetype":"venue"
},
  "geometry": {"coordinates":[8.805441,47.327877],"type":"Point"}
}