{
  "type": "Feature",
  "properties": {
    "iso:country":"CH",
    "sg:address":"Letzistrasse 39",
    "sg:city":"Altendorf",
    "sg:classifiers":[
        {
            "category":"Manufacturing",
            "subcategory":"Wood Products",
            "type":"Manufacturing & Wholesale Goods"
        }
    ],
    "sg:phone":"+41 55 442 55 55",
    "sg:postcode":"8852",
    "sg:province":"Schwyz",
    "sg:tags":[
        "interior",
        "fixture"
    ],
    "wof:name":"M. Keller Holzbau Ag",
    "wof:placetype":"venue"
},
  "geometry": {"coordinates":[8.8099193573,47.1978111267],"type":"Point"}
}