{
  "type": "Feature",
  "properties": {
    "iso:country":"CH",
    "sg:address":"Stationsstrasse 37",
    "sg:city":"Liebefeld",
    "sg:classifiers":[
        {
            "category":"Manufacturing",
            "subcategory":"Wood Products",
            "type":"Manufacturing & Wholesale Goods"
        }
    ],
    "sg:phone":"+41 31 971 11 63",
    "sg:postcode":"3097",
    "sg:province":"Bern",
    "sg:tags":[
        "varnish"
    ],
    "wof:name":"B\u00f6hme Ag",
    "wof:placetype":"venue"
},
  "geometry": {"coordinates":[7.4215040207,46.9318389893],"type":"Point"}
}