{
  "type": "Feature",
  "properties": {
    "addr:full":"Bellevuestrasse 14 Hochdorf Luzern 6280",
    "addr:housenumber":"14",
    "addr:postcode":"6280",
    "addr:street":"Bellevuestrasse",
    "iso:country":"CH",
    "sg:address":"Bellevuestrasse 14",
    "sg:city":"Hochdorf",
    "sg:orig_category":"Ausbaugewerbe Verlegen von Fliesen U Platten",
    "sg:phone":"+41 41 910 11 31",
    "sg:postcode":"6280",
    "sg:province":"Luzern",
    "wof:name":"Langenegger Ofenbau Ag",
    "wof:placetype":"venue"
},
  "geometry": {"coordinates":[8.288061,47.170479],"type":"Point"}
}