{
  "type": "Feature",
  "properties": {
    "iso:country":"CH",
    "sg:address":"Ruopigenplatz 8",
    "sg:city":"Littau",
    "sg:orig_category":"Instandhaltung U Reparatur von Automobilen",
    "sg:postcode":"6014",
    "sg:province":"Luzern",
    "wof:name":"Paganucci Fahrzeug-vertrieb",
    "wof:placetype":"venue"
},
  "geometry": {"coordinates":[8.2610559464,47.0491065979],"type":"Point"}
}