{
  "type": "Feature",
  "properties": {
    "iso:country":"CH",
    "sg:address":"La R\u00e9sidence",
    "sg:city":"Champex",
    "sg:orig_category":"Handelsvermittlung U Grosshandel",
    "sg:phone":"+41 27 783 38 60",
    "sg:postcode":"1938",
    "sg:province":"Valais",
    "wof:name":"Biro Universal Technology S\u00e0rl",
    "wof:placetype":"venue"
},
  "geometry": {"coordinates":[7.118265152,46.028553009],"type":"Point"}
}