{
  "type": "Feature",
  "properties": {
    "iso:country":"CH",
    "sg:address":"Baumenrainweg 297",
    "sg:city":"B\u00e4rschwil",
    "sg:classifiers":[
        {
            "category":"Insurance",
            "subcategory":"Insurance Agent",
            "type":"Services"
        }
    ],
    "sg:phone":"+41 61 761 68 82",
    "sg:postcode":"4252",
    "sg:province":"Solothurn",
    "sg:tags":[
        "versicherungsagenturen",
        "-broker"
    ],
    "wof:name":"Alfons Jeker Agentur Helvetia Feuer",
    "wof:placetype":"venue"
},
  "geometry": {"coordinates":[7.4705791473,47.3810043335],"type":"Point"}
}