{
  "type": "Feature",
  "properties": {
    "addr:full":"R\u00fctschelengasse 1 3400 Burgdorf. Postfach Burgdorf Bern 3402",
    "addr:housenumber":"1",
    "addr:postcode":"3400 burgdorf. postfach;3402",
    "addr:street":"Ruetschelengasse;Bern",
    "iso:country":"CH",
    "sg:address":"R\u00fctschelengasse 1 3400 Burgdorf. Postfach",
    "sg:city":"Burgdorf",
    "sg:orig_category":"Bars Diskotheken, Dancings, Night Clubs",
    "sg:phone":"+41 34 422 52 25",
    "sg:postcode":"3402",
    "sg:province":"Bern",
    "wof:name":"Nightclub Falken Gmbh",
    "wof:placetype":"venue"
},
  "geometry": {"coordinates":[7.627293,47.055759],"type":"Point"}
}