{
  "type": "Feature",
  "properties": {
    "iso:country":"CH",
    "sg:address":"Im Wingert 36a",
    "sg:city":"Z\u00fcrich",
    "sg:orig_category":"Architektur U Ingenieurb\u00fcros",
    "sg:postcode":"8049",
    "sg:province":"Z\u00fcrich",
    "wof:name":"Baupool Gmbh",
    "wof:placetype":"venue"
},
  "geometry": {"coordinates":[8.50908,47.40028],"type":"Point"}
}