{
  "type": "Feature",
  "properties": {
    "iso:country":"CH",
    "sg:address":"Dorfstrasse 43",
    "sg:city":"Rothenbrunnen",
    "sg:orig_category":"Herstellung von sonstigen landwirtschaftlichen Maschinen",
    "sg:phone":"+41 81 655 18 80",
    "sg:postcode":"7405",
    "sg:province":"Graubunden",
    "wof:name":"Caluori & Caminada Landmaschinen",
    "wof:placetype":"venue"
},
  "geometry": {"coordinates":[9.4286813736,46.7676696777],"type":"Point"}
}