{
  "type": "Feature",
  "properties": {
    "iso:country":"CH",
    "sg:address":"Kernstrasse 65 8004 Z\u00fcrich. Postfach",
    "sg:city":"Z\u00fcrich",
    "sg:orig_category":"Verlegen von Fliesen U Platten Verlegen von Fussboden",
    "sg:phone":"+41 12416931",
    "sg:postcode":"8026",
    "sg:province":"Z\u00fcrich",
    "wof:name":"F\u00fcrst & Naef Ag Unterlagsb\u00f6den, Fugenlose Bodenbel\u00e4ge; Ausf\u00fchrung Usw",
    "wof:placetype":"venue"
},
  "geometry": {"coordinates":[8.5262994766,47.3785095215],"type":"Point"}
}