{
  "type": "Feature",
  "properties": {
    "iso:country":"CH",
    "sg:address":"Route De Frontenex 124",
    "sg:city":"Gen\u00e8ve",
    "sg:orig_category":"Geb\u00e4ude, Wohnungsreinigung Reinigungsgewerbe",
    "sg:phone":"+41 79 626 16 55",
    "sg:postcode":"1208",
    "sg:province":"Gen\u00e8ve",
    "wof:name":"City Net Services S\u00e0rl",
    "wof:placetype":"venue"
},
  "geometry": {"coordinates":[6.1732521057,46.2057151794],"type":"Point"}
}