{
  "type": "Feature",
  "properties": {
    "addr:full":"Spitalgasse 15 4900 Langenthal. Postfach Langenthal Bern 4900",
    "addr:housenumber":"15",
    "addr:postcode":"4900;postfach;4900",
    "addr:street":"Spitalgasse",
    "iso:country":"CH",
    "sg:address":"Spitalgasse 15 4900 Langenthal. Postfach",
    "sg:city":"Langenthal",
    "sg:orig_category":"Aktivit\u00e4ten der Generalunternehmen im Baugewerbe Architektur U Ingenieurb\u00fcros",
    "sg:phone":"+41 62 923 25 20",
    "sg:postcode":"4900",
    "sg:province":"Bern",
    "wof:name":"Tfk Baupartner Ag",
    "wof:placetype":"venue"
},
  "geometry": {"coordinates":[7.790207,47.21154],"type":"Point"}
}