{
  "type": "Feature",
  "properties": {
    "iso:country":"CH",
    "sg:address":"Steinmatten 3920 Zermatt. Postfach",
    "sg:city":"Zermatt",
    "sg:classifiers":[
        {
            "category":"Travel",
            "subcategory":"Hotels & Motels",
            "type":"Entertainment"
        }
    ],
    "sg:postcode":"3920",
    "sg:province":"Valais",
    "sg:tags":[
        "hotels",
        "mit",
        "restaurant"
    ],
    "wof:name":"Hotel Garni Antika, Julen Alois & Moritz",
    "wof:placetype":"venue"
},
  "geometry": {"coordinates":[7.7481899261,46.0169715881],"type":"Point"}
}