{
  "type": "Feature",
  "properties": {
    "iso:country":"CH",
    "sg:address":"Ziegeleistrasse 2",
    "sg:city":"Frauenfeld",
    "sg:orig_category":"Herstellung von sonstigen elektrischen Ausr\u00fcstungen",
    "sg:postcode":"8500",
    "sg:province":"Thurgau",
    "wof:name":"Alarmtec Gmbh",
    "wof:placetype":"venue"
},
  "geometry": {"coordinates":[8.9022130966,47.5617523193],"type":"Point"}
}