{
  "type": "Feature",
  "properties": {
    "iso:country":"CH",
    "sg:address":"Laupenstrasse 2",
    "sg:city":"Goldingen",
    "sg:orig_category":"Detailhandel mit Getr\u00e4nken Detailhandel mit Waren verschiedener Art, Hauptrichtung Nahrungsmittel",
    "sg:phone":"+41 55 284 11 07",
    "sg:postcode":"8638",
    "sg:province":"St. Gallen",
    "wof:name":"Landi Goldingen",
    "wof:placetype":"venue"
},
  "geometry": {"coordinates":[8.9601716995,47.264213562],"type":"Point"}
}