{
  "type": "Feature",
  "properties": {
    "iso:country":"CH",
    "sg:address":"Route Du Mont Carmel 2 1762 Givisiez Case Postale 91",
    "sg:city":"Givisiez",
    "sg:orig_category":"Versicherungen Generalagenturen",
    "sg:phone":"+41 26 460 42 42",
    "sg:postcode":"1762",
    "sg:province":"Fribourg",
    "wof:name":"Helvetia Patria Assurances Agence G\u00e9n\u00e9rale Entreprises",
    "wof:placetype":"venue"
},
  "geometry": {"coordinates":[7.1361670494,46.8129806519],"type":"Point"}
}