{
  "type": "Feature",
  "properties": {
    "iso:country":"CH",
    "sg:address":"Hofweg 11",
    "sg:city":"Bern",
    "sg:orig_category":"Rechtsberatung",
    "sg:postcode":"3013",
    "sg:province":"Bern",
    "wof:name":"Ip2h Ag",
    "wof:placetype":"venue"
},
  "geometry": {"coordinates":[7.4453549385,46.9570426941],"type":"Point"}
}