{
  "type": "Feature",
  "properties": {
    "iso:country":"CH",
    "sg:address":"Am Bach 8252 Schlatt Tg. Postfach",
    "sg:city":"Mettschlatt",
    "sg:orig_category":"Fernmeldedienste",
    "sg:postcode":"8252",
    "sg:province":"Thurgau",
    "wof:name":"Genossenschaft Bach - Paradies",
    "wof:placetype":"venue"
},
  "geometry": {"coordinates":[8.6875743866,47.6787719727],"type":"Point"}
}