{
  "type": "Feature",
  "properties": {
    "iso:country":"CH",
    "sg:address":"Gr\u00fcttstrasse 8",
    "sg:city":"Derendingen",
    "sg:orig_category":"Mechanik Mechanische Werkst\u00e4tten",
    "sg:phone":"+41 18441973",
    "sg:postcode":"4552",
    "sg:province":"Solothurn",
    "wof:name":"Steffen J. + B. Mech. Werkst\u00e4tte",
    "wof:placetype":"venue"
},
  "geometry": {"coordinates":[8.4058427811,47.4468154907],"type":"Point"}
}