{
  "type": "Feature",
  "properties": {
    "addr:full":"Luzernerstrasse 12 Zofingen Aargau 4800",
    "addr:housenumber":"12",
    "addr:postcode":"4800",
    "addr:street":"Luzernerstrasse",
    "iso:country":"CH",
    "sg:address":"Luzernerstrasse 12",
    "sg:city":"Zofingen",
    "sg:classifiers":[
        {
            "category":"Autos & Motor Vehicles",
            "subcategory":"Auto Supplies",
            "type":"Retail Goods"
        }
    ],
    "sg:phone":"+41 62 789 33 30",
    "sg:postcode":"4800",
    "sg:province":"Aargau",
    "sg:tags":[
        "automobile",
        "painting"
    ],
    "wof:name":"Jakob Hauser Ag",
    "wof:placetype":"venue"
},
  "geometry": {"coordinates":[7.94758,47.285599],"type":"Point"}
}