{
  "type": "Feature",
  "properties": {
    "iso:country":"CH",
    "sg:address":"Dorfstrasse 397",
    "sg:city":"Ueberstorf",
    "sg:orig_category":"Diskotheken, Dancings, Night Clubs",
    "sg:phone":"+41 31 741 17 94",
    "sg:postcode":"3182",
    "sg:province":"Fribourg",
    "wof:name":"Restaurant Mascotte & Disco-bar",
    "wof:placetype":"venue"
},
  "geometry": {"coordinates":[7.3164391518,46.8675575256],"type":"Point"}
}