{
  "type": "Feature",
  "properties": {
    "iso:country":"CH",
    "sg:address":"Jakobsbrunnenstrasse 2",
    "sg:city":"Wila",
    "sg:orig_category":"Haltung von Gefl\u00fcgel",
    "sg:phone":"+41 52 385 29 33",
    "sg:postcode":"8492",
    "sg:province":"Z\u00fcrich",
    "wof:name":"Gefl\u00fcgelfarm Gm\u00fcr Ag",
    "wof:placetype":"venue"
},
  "geometry": {"coordinates":[8.8542985916,47.4163894653],"type":"Point"}
}