{
  "type": "Feature",
  "properties": {
    "iso:country":"CH",
    "sg:address":"Bernstrasse 31",
    "sg:city":"Schlieren",
    "sg:orig_category":"Diskotheken, Dancings, Night Clubs RESTAURANTS: TEA-ROOMS",
    "sg:phone":"+41 17305727",
    "sg:postcode":"8952",
    "sg:province":"Z\u00fcrich",
    "wof:name":"Restaurant/dancing Sax Varela Vargas M.",
    "wof:placetype":"venue"
},
  "geometry": {"coordinates":[8.4503774643,47.4020500183],"type":"Point"}
}