{
  "type": "Feature",
  "properties": {
    "iso:country":"CH",
    "sg:address":"Seestrasse 164",
    "sg:city":"Steckborn",
    "sg:orig_category":"Grosshandel mit Geschenkartikeln U Souvenirs Grosshandel mit keramischen Erzeugnissen,Glaswaren U Ta",
    "sg:phone":"+41 52 770 22 50",
    "sg:postcode":"8266",
    "sg:province":"Thurgau",
    "wof:name":"Seidenberg Collection Keramik & Tonwaren Import",
    "wof:placetype":"venue"
},
  "geometry": {"coordinates":[8.9778165817,47.6637458801],"type":"Point"}
}