{
  "type": "Feature",
  "properties": {
    "iso:country":"CH",
    "sg:address":"Rue Centrale 25 1880 Bex. Postfach",
    "sg:city":"Bex",
    "sg:orig_category":"Arztpraxen",
    "sg:phone":"+41 24 463 10 63",
    "sg:postcode":"1880",
    "sg:province":"Vaud",
    "wof:name":"Dr M\u00e9d. Nicole M\u00fchlemann M\u00e9decin G\u00e9n\u00e9raliste",
    "wof:placetype":"venue"
},
  "geometry": {"coordinates":[7.01458,46.250839],"type":"Point"}
}