{
  "type": "Feature",
  "properties": {
    "iso:country":"CH",
    "sg:address":"L\u00f6wenstrasse 29",
    "sg:city":"Z\u00fcrich",
    "sg:classifiers":[
        {
            "category":"Taxi",
            "type":"Transportation"
        }
    ],
    "sg:phone":"+41 12151111",
    "sg:postcode":"8001",
    "sg:province":"Z\u00fcrich",
    "sg:tags":[
        "air"
    ],
    "wof:name":"South African Airways (pty) Ltd.",
    "wof:placetype":"venue"
},
  "geometry": {"coordinates":[8.53583,47.374706],"type":"Point"}
}