{
  "type": "Feature",
  "properties": {
    "iso:country":"CH",
    "sg:address":"Bahnhofstrasse 3",
    "sg:city":"Kerzers",
    "sg:classifiers":[
        {
            "category":"Travel",
            "subcategory":"Hotels & Motels",
            "type":"Entertainment"
        }
    ],
    "sg:phone":"+41 31555316",
    "sg:postcode":"3210",
    "sg:province":"Fribourg",
    "sg:tags":[
        "hotels",
        "mit",
        "restaurant"
    ],
    "wof:name":"Club Caf\u00e9 Bahnhof Venanzio Berno",
    "wof:placetype":"venue"
},
  "geometry": {"coordinates":[7.1940579414,46.9748306274],"type":"Point"}
}