{
  "type": "Feature",
  "properties": {
    "iso:country":"CH",
    "sg:address":"Freiburgstrasse 18 3010 Bern. Postfach",
    "sg:city":"Bern",
    "sg:orig_category":"Interessenvertretungen",
    "sg:postcode":"3010",
    "sg:province":"Bern",
    "wof:name":"Meyer-schneider-stiftung Allj\u00e4hrliche Weihnachtsbescherung An Arme Und Alleinstehende Patienten Usw.",
    "wof:placetype":"venue"
},
  "geometry": {"coordinates":[7.4254832268,46.947517395],"type":"Point"}
}