{
  "type": "Feature",
  "properties": {
    "iso:country":"CH",
    "sg:address":"Distelweg 7",
    "sg:city":"W\u00fcrenlingen",
    "sg:orig_category":"Architektur U Ingenieurb\u00fcros",
    "sg:phone":"+41 56 281 14 35",
    "sg:postcode":"5303",
    "sg:province":"Aargau",
    "wof:name":"Haus + Plan Architektur Gmbh",
    "wof:placetype":"venue"
},
  "geometry": {"coordinates":[8.253325,47.529182],"type":"Point"}
}