{
  "type": "Feature",
  "properties": {
    "iso:country":"CH",
    "sg:address":"Neuweilerstrasse 10",
    "sg:city":"Allschwil",
    "sg:orig_category":"Detailhandel mit Fahrr\u00e4dern",
    "sg:phone":"+41 61 481 56 55",
    "sg:postcode":"4123",
    "sg:province":"Basel-Landschaft",
    "wof:name":"A. Kilcher Velos-motos",
    "wof:placetype":"venue"
},
  "geometry": {"coordinates":[7.5355000496,47.5500488281],"type":"Point"}
}