{
  "type": "Feature",
  "properties": {
    "iso:country":"CH",
    "sg:address":"Via Stefano Franscini 18",
    "sg:city":"Chiasso",
    "sg:classifiers":[
        {
            "category":"Bars & Pubs",
            "type":"Food & Drink"
        }
    ],
    "sg:phone":"+41 91 682 35 92",
    "sg:postcode":"6830",
    "sg:province":"Ticino",
    "wof:name":"Bar Botega",
    "wof:placetype":"venue"
},
  "geometry": {"coordinates":[9.031497,45.835968],"type":"Point"}
}