{
  "type": "Feature",
  "properties": {
    "iso:country":"CH",
    "sg:address":"Industriering Nord 5",
    "sg:city":"Lyss",
    "sg:classifiers":[
        {
            "category":"Manufacturing",
            "subcategory":"Rubber & Plastics",
            "type":"Manufacturing & Wholesale Goods"
        }
    ],
    "sg:phone":"+41 32 387 95 00",
    "sg:postcode":"3250",
    "sg:province":"Bern",
    "wof:name":"Hera Ag Kunststofftechnologie",
    "wof:placetype":"venue"
},
  "geometry": {"coordinates":[7.3053560257,47.0852661133],"type":"Point"}
}