{
  "type": "Feature",
  "properties": {
    "iso:country":"CH",
    "sg:address":"Zugerstrasse 20 8820 W\u00e4denswil. Postfach 29",
    "sg:city":"W\u00e4denswil",
    "sg:orig_category":"Warenh\u00e4user",
    "sg:phone":"+41 17801655",
    "sg:postcode":"8820",
    "sg:province":"Z\u00fcrich",
    "wof:name":"Abm Au Bon March\u00e9",
    "wof:placetype":"venue"
},
  "geometry": {"coordinates":[8.6708192825,47.2298316956],"type":"Point"}
}