{
  "type": "Feature",
  "properties": {
    "iso:country":"CH",
    "sg:address":"Marktgasse 11",
    "sg:city":"Baar",
    "sg:classifiers":[
        {
            "category":"Banks & Credit Unions",
            "subcategory":"Bank",
            "type":"Services"
        }
    ],
    "sg:phone":"+41 52 646 08 40",
    "sg:postcode":"6340",
    "sg:province":"Zug",
    "wof:name":"Raiffeisenbank Basadingen",
    "wof:placetype":"venue"
},
  "geometry": {"coordinates":[8.74385,47.659222],"type":"Point"}
}