{
  "type": "Feature",
  "properties": {
    "iso:country":"CH",
    "sg:address":"1884",
    "sg:city":"Villars-sur-ollon",
    "sg:orig_category":"Allgemeinbildende weiterf\u00fchrende Schulen Primarschulen",
    "sg:phone":"+41 24 495 21 54",
    "sg:postcode":"1884",
    "sg:province":"Vaud",
    "wof:name":"Coll\u00e8ge Alpin Beau-soleil Sa",
    "wof:placetype":"venue"
},
  "geometry": {"coordinates":[7.055,46.296959],"type":"Point"}
}