{
  "type": "Feature",
  "properties": {
    "iso:country":"CH",
    "sg:address":"Bodenackerstrasse 23",
    "sg:city":"Bottmingen",
    "sg:orig_category":"Sportvereine Ballsport Tennis",
    "sg:postcode":"4103",
    "sg:province":"Basel-Landschaft",
    "wof:name":"Tc Rankhof",
    "wof:placetype":"venue"
},
  "geometry": {"coordinates":[7.5876979828,47.5265693665],"type":"Point"}
}