{
  "type": "Feature",
  "properties": {
    "iso:country":"CH",
    "sg:address":"Chamerstrasse 30",
    "sg:city":"Zug",
    "sg:orig_category":"Wirtschaftspr\u00fcfung, Steuerberatung U Treuhand",
    "sg:phone":"+41 41 711 94 88",
    "sg:postcode":"6300",
    "sg:province":"Zug",
    "wof:name":"Firi Treuhand Ag",
    "wof:placetype":"venue"
},
  "geometry": {"coordinates":[8.5089349747,47.1728401184],"type":"Point"}
}