{
  "type": "Feature",
  "properties": {
    "iso:country":"CH",
    "sg:address":"Dorfplatz 77",
    "sg:city":"Oppligen",
    "sg:orig_category":"Hardwareberatung",
    "sg:phone":"+41 31 782 08 08",
    "sg:postcode":"3629",
    "sg:province":"Bern",
    "wof:name":"Pauli Netsystems",
    "wof:placetype":"venue"
},
  "geometry": {"coordinates":[7.594930172,46.8192901611],"type":"Point"}
}