{
  "type": "Feature",
  "properties": {
    "iso:country":"CH",
    "sg:address":"Bahnhofstrasse 30 6300 Zug. Postfach",
    "sg:city":"Zug",
    "sg:orig_category":"Rechtsberatung",
    "sg:phone":"+41 56 664 20 08",
    "sg:postcode":"6300",
    "sg:province":"Zug",
    "wof:name":"Nietlispach Dr. Iur. Fritz",
    "wof:placetype":"venue"
},
  "geometry": {"coordinates":[8.3174819946,47.2825775146],"type":"Point"}
}