{
  "type": "Feature",
  "properties": {
    "iso:country":"CH",
    "sg:address":"R\u00fcediswilerstrasse 35",
    "sg:city":"Ruswil",
    "sg:orig_category":"Sportvereine Ski",
    "sg:phone":"+41 41 495 34 67",
    "sg:postcode":"6017",
    "sg:province":"Luzern",
    "wof:name":"Skiclub Alpina Ruswil",
    "wof:placetype":"venue"
},
  "geometry": {"coordinates":[8.1184530258,47.085483551],"type":"Point"}
}