{
  "type": "Feature",
  "properties": {
    "iso:country":"CH",
    "sg:address":"Grundstrasse 6",
    "sg:city":"Zumikon",
    "sg:orig_category":"Datenbanken",
    "sg:postcode":"8126",
    "sg:province":"Z\u00fcrich",
    "wof:name":"Creative Netdesign Amato & Co",
    "wof:placetype":"venue"
},
  "geometry": {"coordinates":[8.623719,47.330002],"type":"Point"}
}