{
  "type": "Feature",
  "properties": {
    "iso:country":"CH",
    "sg:address":"La Rocaille",
    "sg:city":"Lens",
    "sg:orig_category":"Vermietung U Verpachtung von eigenen Immobilien",
    "sg:postcode":"1978",
    "sg:province":"Valais",
    "wof:name":"Alano Sa",
    "wof:placetype":"venue"
},
  "geometry": {"coordinates":[8.9712247849,45.9057006836],"type":"Point"}
}