{
  "type": "Feature",
  "properties": {
    "addr:full":"Lenzenhohlenstrasse 30 Moosseedorf Bern 3302",
    "addr:housenumber":"30",
    "addr:postcode":"3302",
    "addr:street":"Lenzenhohlenstrasse",
    "iso:country":"CH",
    "sg:address":"Lenzenhohlenstrasse 30",
    "sg:city":"Moosseedorf",
    "sg:orig_category":"Architektur U Ingenieurb\u00fcros Architekturb\u00fcros",
    "sg:phone":"+41 31 859 16 60",
    "sg:postcode":"3302",
    "sg:province":"Bern",
    "wof:name":"Architekturb\u00fcro Sommer J\u00fcrg",
    "wof:placetype":"venue"
},
  "geometry": {"coordinates":[7.490672,47.010338],"type":"Point"}
}