{
  "type": "Feature",
  "properties": {
    "iso:country":"CH",
    "sg:address":"Wuhrmattstrasse 30",
    "sg:city":"Zofingen",
    "sg:orig_category":"Softwareentwicklung U beratung",
    "sg:postcode":"4800",
    "sg:province":"Aargau",
    "wof:name":"Wetter Othmar, Proconsult",
    "wof:placetype":"venue"
},
  "geometry": {"coordinates":[7.9451799393,47.2815704346],"type":"Point"}
}