{
  "type": "Feature",
  "properties": {
    "iso:country":"CH",
    "sg:address":"Rebgasse 4 4410 Liestal. Postfach",
    "sg:city":"Liestal",
    "sg:orig_category":"Wirtschaftspr\u00fcfung, Steuerberatung U Treuhand",
    "sg:postcode":"4410",
    "sg:province":"Basel-Landschaft",
    "wof:name":"Llk Treuhand Ag",
    "wof:placetype":"venue"
},
  "geometry": {"coordinates":[7.7339758873,47.4859046936],"type":"Point"}
}