{
  "type": "Feature",
  "properties": {
    "iso:country":"CH",
    "sg:address":"Rue Des Prises 17",
    "sg:city":"Gorgier",
    "sg:orig_category":"Dachdeckerei Zimmerei, Dachdeckerei, Bauspenglerei U Abdichtung",
    "sg:phone":"+41 32 835 28 47",
    "sg:postcode":"2023",
    "sg:province":"Neuch\u00e2tel",
    "wof:name":"Entreprise De Couverture Quartier-dit-maire Gilbert, Loertscher & Cie Successeurs.",
    "wof:placetype":"venue"
},
  "geometry": {"coordinates":[6.778836,46.903934],"type":"Point"}
}