{
  "type": "Feature",
  "properties": {
    "iso:country":"CH",
    "sg:address":"2953",
    "sg:city":"Fregi\u00e9court-pleuj",
    "sg:orig_category":"Sportvereine Sch\u00fctzen",
    "sg:postcode":"2953",
    "sg:province":"Jura",
    "wof:name":"St\u00e9 De Tir La Baroche Pleujouse",
    "wof:placetype":"venue"
},
  "geometry": {"coordinates":[7.2113790512,47.4111747742],"type":"Point"}
}