{
  "type": "Feature",
  "properties": {
    "iso:country":"CH",
    "sg:address":"Badenerstrasse 46",
    "sg:city":"Dietikon",
    "sg:orig_category":"Satzherstellung U Reproduktion",
    "sg:phone":"+41 17400404",
    "sg:postcode":"8953",
    "sg:province":"Z\u00fcrich",
    "wof:name":"F+p Belichtungsservice Gmbh",
    "wof:placetype":"venue"
},
  "geometry": {"coordinates":[8.3945236206,47.4075775146],"type":"Point"}
}