{
  "type": "Feature",
  "properties": {
    "iso:country":"CH",
    "sg:address":"Grubenweg 4",
    "sg:city":"Oftringen",
    "sg:orig_category":"Kosmetikinstitute",
    "sg:phone":"+41 62 797 62 20",
    "sg:postcode":"4665",
    "sg:province":"Aargau",
    "wof:name":"Jasmine Wyss Kosmetikinstitut Jasmine",
    "wof:placetype":"venue"
},
  "geometry": {"coordinates":[7.9256920815,47.3121566772],"type":"Point"}
}