{
  "type": "Feature",
  "properties": {
    "iso:country":"CH",
    "sg:address":"Chalet Betula 3981 Blitzingen. Postfach",
    "sg:city":"Bettmeralp",
    "sg:orig_category":"Grosshandel mit Nahrungsmitteln, Getr\u00e4nken U Tabakwaren ohne ausgepr\u00e4gten Schwerpunkt",
    "sg:postcode":"3992",
    "sg:province":"Valais",
    "wof:name":"Eyholzer Und Studer Gmbh",
    "wof:placetype":"venue"
},
  "geometry": {"coordinates":[8.1907701492,46.4355049133],"type":"Point"}
}