{
  "type": "Feature",
  "properties": {
    "iso:country":"CH",
    "sg:address":"Dorf",
    "sg:city":"Neuheim",
    "sg:orig_category":"Mechanik",
    "sg:postcode":"6345",
    "sg:province":"Zug",
    "wof:name":"Obrist E.",
    "wof:placetype":"venue"
},
  "geometry": {"coordinates":[8.5754499435,47.2051849365],"type":"Point"}
}