{
  "type": "Feature",
  "properties": {
    "iso:country":"CH",
    "sg:address":"Im Zinggen 9",
    "sg:city":"Ossingen",
    "sg:orig_category":"Architektur U Ingenieurb\u00fcros",
    "sg:phone":"+41 24 499 10 21",
    "sg:postcode":"8475",
    "sg:province":"Z\u00fcrich",
    "wof:name":"Paul Fran\u00e7ois Consulting",
    "wof:placetype":"venue"
},
  "geometry": {"coordinates":[6.990611,46.294674],"type":"Point"}
}