{
  "type": "Feature",
  "properties": {
    "iso:country":"CH",
    "sg:address":"Oristalstr. 65",
    "sg:city":"Liestal",
    "sg:orig_category":"Medizin, Pharmaprodukte",
    "sg:phone":"+41 61 925 05 05",
    "sg:postcode":"4410",
    "sg:province":"Basel-Landschaft",
    "wof:name":"Reductil By Knoll Ag",
    "wof:placetype":"venue"
},
  "geometry": {"coordinates":[7.729501,47.478794],"type":"Point"}
}