{
  "type": "Feature",
  "properties": {
    "iso:country":"CH",
    "sg:address":"Hauptstrasse 26 6170 Sch\u00fcpfheim. Postfach 62",
    "sg:city":"Sch\u00fcpfheim",
    "sg:orig_category":"Detailhandel mit Radio U Fernsehger\u00e4ten Fotografisches Gewerbe U fotografische Laboratorien",
    "sg:phone":"+41 41 484 13 76",
    "sg:postcode":"6170",
    "sg:province":"Luzern",
    "wof:name":"Fotostudio Teuffer & Co",
    "wof:placetype":"venue"
},
  "geometry": {"coordinates":[8.017367363,46.9512557983],"type":"Point"}
}