{
  "type": "Feature",
  "properties": {
    "iso:country":"CH",
    "sg:address":"Fusterli",
    "sg:city":"Udligenswil",
    "sg:orig_category":"Herstellung von Karosserien U Anh\u00e4ngern Herstellung von sonstigen konfektionierten Textilwaren ohne ",
    "sg:phone":"+41 41 371 03 86",
    "sg:postcode":"6044",
    "sg:province":"Luzern",
    "wof:name":"Josef Egger Ehz Zelte & Blachen",
    "wof:placetype":"venue"
},
  "geometry": {"coordinates":[8.401014328,47.1005592346],"type":"Point"}
}