{
  "type": "Feature",
  "properties": {
    "iso:country":"CH",
    "sg:address":"Br\u00fcckenstrasse 71",
    "sg:city":"Bern",
    "sg:orig_category":"Maturit\u00e4tsschulen, Lehrerseminarien",
    "sg:phone":"+41 31 371 05 18",
    "sg:postcode":"3005",
    "sg:province":"Bern",
    "wof:name":"St\u00e4dt.lehrerinnen-,lehrer-& Kinderg\u00e4rtnerinnenseminar",
    "wof:placetype":"venue"
},
  "geometry": {"coordinates":[7.4395232201,46.9415588379],"type":"Point"}
}