{
  "type": "Feature",
  "properties": {
    "iso:country":"CH",
    "sg:address":"Industriestrasse 11",
    "sg:city":"Safnern",
    "sg:orig_category":"Oberfl\u00e4chenveredlung U W\u00e4rmebehandlung",
    "sg:phone":"+41 32 355 33 32",
    "sg:postcode":"2553",
    "sg:province":"Bern",
    "wof:name":"Walker Mst Metall Spritz Technik",
    "wof:placetype":"venue"
},
  "geometry": {"coordinates":[7.3319191933,47.155670166],"type":"Point"}
}