{
  "type": "Feature",
  "properties": {
    "iso:country":"CH",
    "sg:address":"6133",
    "sg:city":"H\u00fcbeli",
    "sg:orig_category":"Verarbeitung von Milch Verwertung von Milch",
    "sg:postcode":"6133",
    "sg:province":"Luzern",
    "wof:name":"K\u00e4sereigenossenschaft Opfersei & Umgebung",
    "wof:placetype":"venue"
},
  "geometry": {"coordinates":[7.9620099068,47.1195907593],"type":"Point"}
}