{
  "type": "Feature",
  "properties": {
    "iso:country":"CH",
    "sg:address":"M\u00fchlenstrasse 211",
    "sg:city":"Wilchingen",
    "sg:orig_category":"Bauschreinerei Herstellung von Konstruktionsteilen, Fertigbauteilen U Ausbauelementen aus Holz",
    "sg:phone":"+41 52 681 13 65",
    "sg:postcode":"8217",
    "sg:province":"Schaffhausen",
    "wof:name":"Aigner Alois",
    "wof:placetype":"venue"
},
  "geometry": {"coordinates":[8.468007,47.675011],"type":"Point"}
}