{
  "type": "Feature",
  "properties": {
    "iso:country":"CH",
    "sg:address":"Ahornweidstrasse 2 8844 Euthal. Postfach 68",
    "sg:city":"Euthal",
    "sg:orig_category":"Architekturb\u00fcros Vermittlung von Immobilien",
    "sg:phone":"+41 55 412 91 01",
    "sg:postcode":"8844",
    "sg:province":"Schwyz",
    "wof:name":"Richard Ochsner Architekturb\u00fcro",
    "wof:placetype":"venue"
},
  "geometry": {"coordinates":[8.813115,47.097206],"type":"Point"}
}