{
  "type": "Feature",
  "properties": {
    "iso:country":"CH",
    "sg:address":"Hofmattstrasse 12",
    "sg:city":"Herzogenbuchsee",
    "sg:orig_category":"Installation von Heizungs, L\u00fcftungs U Klimaanlagen",
    "sg:phone":"+41 62 961 00 44",
    "sg:postcode":"3360",
    "sg:province":"Bern",
    "wof:name":"Reado Gissi Air Tech Heizungs-& L\u00fcftungstechnik",
    "wof:placetype":"venue"
},
  "geometry": {"coordinates":[7.6993641853,47.1927719116],"type":"Point"}
}