{
  "type": "Feature",
  "properties": {
    "iso:country":"CH",
    "sg:address":"Rue De Pr\u00e9-fleuri 8b 1950 Sion Case Postale 907",
    "sg:city":"Sion",
    "sg:orig_category":"Sonstiges Versicherungsgewerbe",
    "sg:phone":"+41 27 322 27 22",
    "sg:postcode":"1951",
    "sg:province":"Valais",
    "wof:name":"Borgeat Assurances Sa",
    "wof:placetype":"venue"
},
  "geometry": {"coordinates":[7.3569488525,46.2294692993],"type":"Point"}
}