{
  "type": "Feature",
  "properties": {
    "iso:country":"CH",
    "sg:address":"Z\u00fcrichstrasse 11",
    "sg:city":"B\u00fctzberg",
    "sg:orig_category":"Herstellung von Pumpen U Kompressoren",
    "sg:postcode":"4922",
    "sg:province":"Bern",
    "wof:name":"Ulrich Wyss Ag",
    "wof:placetype":"venue"
},
  "geometry": {"coordinates":[7.7512722015,47.2167434692],"type":"Point"}
}