{
  "type": "Feature",
  "properties": {
    "iso:country":"CH",
    "sg:address":"In Den Klostermatten 10 4052 Basel. Postfach",
    "sg:city":"Basel",
    "sg:orig_category":"Sonstiger Grosshandel",
    "sg:phone":"+41 61 373 37 37",
    "sg:postcode":"4006",
    "wof:name":"Twen Trade Gmbh",
    "wof:placetype":"venue"
},
  "geometry": {"coordinates":[7.6170978546,47.551525116],"type":"Point"}
}