{
  "type": "Feature",
  "properties": {
    "addr:full":"B\u00fchlackerstrasse 7 Schlieren Z\u00fcrich 8952",
    "addr:housenumber":"7",
    "addr:postcode":"8952",
    "addr:street":"Buehlackerstrasse",
    "iso:country":"CH",
    "sg:address":"B\u00fchlackerstrasse 7",
    "sg:city":"Schlieren",
    "sg:classifiers":[
        {
            "category":"Food & Beverages",
            "subcategory":"Specialty",
            "type":"Retail Goods"
        }
    ],
    "sg:phone":"+41 17313333",
    "sg:postcode":"8952",
    "sg:province":"Z\u00fcrich",
    "sg:tags":[
        "caterer"
    ],
    "wof:name":"Fingerfood Service Monika Saxer",
    "wof:placetype":"venue"
},
  "geometry": {"coordinates":[8.449745,47.39492],"type":"Point"}
}