{
  "type": "Feature",
  "properties": {
    "iso:country":"CH",
    "sg:address":"Aroserstrasse",
    "sg:city":"Maladers",
    "sg:orig_category":"Mechanik Schlossereien",
    "sg:phone":"+41 81 252 52 18",
    "sg:postcode":"7026",
    "sg:province":"Graubunden",
    "wof:name":"Eggler Jakob Ag",
    "wof:placetype":"venue"
},
  "geometry": {"coordinates":[9.555528,46.835346],"type":"Point"}
}