{
  "type": "Feature",
  "properties": {
    "iso:country":"CH",
    "sg:address":"9428",
    "sg:city":"Walzenhausen",
    "sg:orig_category":"Vermietung U Verpachtung von eigenen Immobilien",
    "sg:phone":"+41 61 711 46 11",
    "sg:postcode":"9428",
    "sg:province":"Appenzell Ausserrhoden",
    "wof:name":"Rlf Fabriggli Ag",
    "wof:placetype":"venue"
},
  "geometry": {"coordinates":[7.5950908661,47.5036697388],"type":"Point"}
}