{
  "type": "Feature",
  "properties": {
    "iso:country":"CH",
    "sg:address":"Niesenstrasse 9",
    "sg:city":"Interlaken",
    "sg:orig_category":"Detailhandel mit Waren verschiedener Art, Hauptrichtung Nahrungsmittel Grosshandel mit Nahrungsmitte",
    "sg:phone":"+41 33 823 29 21",
    "sg:postcode":"3800",
    "sg:province":"Bern",
    "wof:name":"Delicias Algarve. Jos\u00e9 Sebastiao",
    "wof:placetype":"venue"
},
  "geometry": {"coordinates":[7.8547382355,46.6826286316],"type":"Point"}
}