{
  "type": "Feature",
  "properties": {
    "iso:country":"CH",
    "sg:address":"Tabi\u00f2 Via 5 6500 Bellinzona. Postfach Casa Postale",
    "sg:city":"Bellinzona",
    "sg:orig_category":"W\u00e4scherei U chemische Reinigung",
    "sg:postcode":"6500",
    "sg:province":"Ticino",
    "wof:name":"Immolinda Sa Lavanderie; Installaz., Gestione. Attrezzature, Materiali P. Lavanderia; Comm.",
    "wof:placetype":"venue"
},
  "geometry": {"coordinates":[9.0241193771,46.1944618225],"type":"Point"}
}