{
  "type": "Feature",
  "properties": {
    "iso:country":"CH",
    "sg:address":"Kaufplatz 2",
    "sg:city":"Visp",
    "sg:orig_category":"Kosmetikinstitute",
    "sg:phone":"+41 27 946 02 46",
    "sg:postcode":"3930",
    "sg:province":"Valais",
    "wof:name":"Holzer & Rieben Kosmetik Ambiente",
    "wof:placetype":"venue"
},
  "geometry": {"coordinates":[7.8815479279,46.2909927368],"type":"Point"}
}