{
  "type": "Feature",
  "properties": {
    "iso:country":"CH",
    "sg:address":"Rue De Cossonay 13",
    "sg:city":"Prilly",
    "sg:orig_category":"Zahnarztpraxen",
    "sg:phone":"+41 21 624 25 00",
    "sg:postcode":"1008",
    "sg:province":"Vaud",
    "wof:name":"Dr M\u00e9d. Dent. Willy Burri M\u00e9decin-dentiste",
    "wof:placetype":"venue"
},
  "geometry": {"coordinates":[6.6066632271,46.5337371826],"type":"Point"}
}