{
  "type": "Feature",
  "properties": {
    "iso:country":"CH",
    "sg:address":"St. Peter 7",
    "sg:city":"Balzers",
    "sg:orig_category":"Ingenieurb\u00fcros Elektro",
    "sg:postcode":"9496",
    "wof:name":"Amk Energie-technik Ag Energieplanung",
    "wof:placetype":"venue"
},
  "geometry": {"coordinates":[9.4971923828,47.0606498718],"type":"Point"}
}