{
  "type": "Feature",
  "properties": {
    "iso:country":"CH",
    "sg:address":"Im Baumgarten 19",
    "sg:city":"Russikon",
    "sg:orig_category":"Grosshandel mit sonstigen Maschinen U Ausr\u00fcstungen f\u00fcr Industrie, Handel U Schiffahrt",
    "sg:phone":"+41 19500500",
    "sg:postcode":"8332",
    "sg:province":"Z\u00fcrich",
    "wof:name":"Fl\u00fceler Trade Agency",
    "wof:placetype":"venue"
},
  "geometry": {"coordinates":[8.7759141922,47.3938407898],"type":"Point"}
}