{
  "type": "Feature",
  "properties": {
    "addr:full":"Chauss\u00e9e De Treycovagnes 15 Yverdon-les-bains Vaud 1400",
    "addr:housenumber":"15",
    "addr:postcode":"1400",
    "addr:street":"Chausse\u0301E De Treycovagnes",
    "iso:country":"CH",
    "sg:address":"Chauss\u00e9e De Treycovagnes 15",
    "sg:city":"Yverdon-les-bains",
    "sg:orig_category":"Autospenglereien",
    "sg:phone":"+41 79 224 23 77",
    "sg:postcode":"1400",
    "sg:province":"Vaud",
    "wof:name":"Edgar Sumi Carrosserie De L'industrie",
    "wof:placetype":"venue"
},
  "geometry": {"coordinates":[6.623336,46.778667],"type":"Point"}
}