{
  "type": "Feature",
  "properties": {
    "iso:country":"CH",
    "sg:address":"Al Cairello",
    "sg:city":"Manno",
    "sg:orig_category":"Erdbewegungsarbeiten G\u00fcterbef\u00f6rderung im Strassenverkehr",
    "sg:phone":"+41 91 605 48 94",
    "sg:postcode":"6928",
    "sg:province":"Ticino",
    "wof:name":"Bileo Sa Trasporti & Scavi Meccanici",
    "wof:placetype":"venue"
},
  "geometry": {"coordinates":[8.919005394,46.0345535278],"type":"Point"}
}