{
  "type": "Feature",
  "properties": {
    "iso:country":"CH",
    "sg:address":"Place Du Vingt-trois Juin 4 2350 Saignel\u00e9gier. Postfach",
    "sg:city":"Saignel\u00e9gier",
    "sg:classifiers":[
        {
            "category":"Restaurant",
            "type":"Food & Drink"
        }
    ],
    "sg:phone":"+41 32 951 18 26",
    "sg:postcode":"2350",
    "sg:province":"Jura",
    "wof:name":"Caf\u00e9 Central",
    "wof:placetype":"venue"
},
  "geometry": {"coordinates":[6.9966711998,47.2562026978],"type":"Point"}
}