{
  "type": "Feature",
  "properties": {
    "iso:country":"CH",
    "sg:address":"Riehenstrasse 60",
    "sg:city":"Basel",
    "sg:orig_category":"Softwareentwicklung U beratung",
    "sg:phone":"+41 61 681 22 11",
    "sg:postcode":"4058",
    "sg:province":"Basel-Stadt",
    "wof:name":"Byron Informatik Ag",
    "wof:placetype":"venue"
},
  "geometry": {"coordinates":[7.5998950005,47.5618133545],"type":"Point"}
}