{
  "type": "Feature",
  "properties": {
    "iso:country":"CH",
    "sg:address":"In Der Looren 33",
    "sg:city":"Z\u00fcrich",
    "sg:orig_category":"Herstellung von sonstigen Erzeugnissen",
    "sg:phone":"+41 91 683 18 51",
    "sg:postcode":"8053",
    "sg:province":"Z\u00fcrich",
    "wof:name":"Diplomat Sa Fabbr.di Accendisigari",
    "wof:placetype":"venue"
},
  "geometry": {"coordinates":[9.0503702164,45.870098114],"type":"Point"}
}