{
  "type": "Feature",
  "properties": {
    "iso:country":"CH",
    "sg:address":"Birchli 3",
    "sg:city":"Einsiedeln",
    "sg:orig_category":"Fahrschulen, Flugschulen",
    "sg:phone":"+41 79 406 85 48",
    "sg:postcode":"8840",
    "sg:province":"Schwyz",
    "wof:name":"Tony Oechslin Autofahrschule",
    "wof:placetype":"venue"
},
  "geometry": {"coordinates":[8.7588605881,47.1306266785],"type":"Point"}
}