{
  "type": "Feature",
  "properties": {
    "iso:country":"CH",
    "sg:address":"Buchlistrasse 39 4704 Niederbipp. Postfach 171",
    "sg:city":"Niederbipp",
    "sg:orig_category":"Elektroinstallation",
    "sg:phone":"+41 32 633 17 70",
    "sg:postcode":"4704",
    "sg:province":"Bern",
    "wof:name":"Elektro Werner Gmbh",
    "wof:placetype":"venue"
},
  "geometry": {"coordinates":[7.6827230453,47.2655982971],"type":"Point"}
}