{
  "type": "Feature",
  "properties": {
    "iso:country":"CH",
    "sg:address":"Brunneng\u00e4ssli 5",
    "sg:city":"Giffers",
    "sg:orig_category":"Erbringung von Dienstleistungen f\u00fcr Unternehmen",
    "sg:phone":"+41 56 450 31 02",
    "sg:postcode":"1735",
    "sg:province":"Fribourg",
    "wof:name":"Createam Ag",
    "wof:placetype":"venue"
},
  "geometry": {"coordinates":[7.2105650902,46.7592163086],"type":"Point"}
}