{
  "type": "Feature",
  "properties": {
    "iso:country":"CH",
    "sg:address":"W\u00e4sserwies 11",
    "sg:city":"St\u00e4fa",
    "sg:orig_category":"Grosshandel mit Nahrungsmitteln, Getr\u00e4nken U Tabakwaren Grosshandel mit Parf\u00fcmerieartikeln U K\u00f6rperp",
    "sg:phone":"+41 22 301 08 20",
    "sg:postcode":"8712",
    "sg:province":"Z\u00fcrich",
    "wof:name":"Ms Distri-pharma Group Sa",
    "wof:placetype":"venue"
},
  "geometry": {"coordinates":[6.1434750557,46.1856079102],"type":"Point"}
}