{
  "type": "Feature",
  "properties": {
    "iso:country":"CH",
    "sg:address":"Centrale Rue 14",
    "sg:city":"Court",
    "sg:orig_category":"Sanit\u00e4r, Heizungs U L\u00fcftungsinstallation",
    "sg:postcode":"2738",
    "sg:province":"Bern",
    "wof:name":"Nussbaumer Sa, Port Louis, Succursale De Court",
    "wof:placetype":"venue"
},
  "geometry": {"coordinates":[7.3383998871,47.2398338318],"type":"Point"}
}