{
  "type": "Feature",
  "properties": {
    "iso:country":"CH",
    "sg:address":"Z\u00fcrichstrasse 38c",
    "sg:city":"Br\u00fcttisellen",
    "sg:orig_category":"Erbringung von Dienstleistungen f\u00fcr Unternehmen Grafikateliers, Design",
    "sg:phone":"+41 18330207",
    "sg:postcode":"8306",
    "sg:province":"Z\u00fcrich",
    "wof:name":"Art-line Gestaltungsatelier Roger Inglin",
    "wof:placetype":"venue"
},
  "geometry": {"coordinates":[8.6285743713,47.42237854],"type":"Point"}
}