{
  "type": "Feature",
  "properties": {
    "iso:country":"CH",
    "sg:address":"Baumgartenweg 6a",
    "sg:city":"Therwil",
    "sg:orig_category":"Tierarztpraxis",
    "sg:phone":"+41 81 416 77 77",
    "sg:postcode":"4106",
    "sg:province":"Basel-Landschaft",
    "wof:name":"Dr. Med. Vet. Leonhard Weber Tierarzt",
    "wof:placetype":"venue"
},
  "geometry": {"coordinates":[9.8537597656,46.8327331543],"type":"Point"}
}