{
  "type": "Feature",
  "properties": {
    "iso:country":"CH",
    "sg:address":"Bahnhofstrasse 71",
    "sg:city":"Z\u00fcrich",
    "sg:orig_category":"Unclassifiable Establishments",
    "sg:postcode":"8001",
    "sg:province":"Z\u00fcrich",
    "wof:name":"Corum Verm\u00f6gensverwaltung Ag",
    "wof:placetype":"venue"
},
  "geometry": {"coordinates":[8.5382347107,47.3741378784],"type":"Point"}
}