{
  "type": "Feature",
  "properties": {
    "iso:country":"CH",
    "sg:address":"Buchserstrasse 41a",
    "sg:city":"Dielsdorf",
    "sg:orig_category":"Markt U Meinungsforschung",
    "sg:postcode":"8157",
    "sg:province":"Z\u00fcrich",
    "wof:name":"Gfeller Urs",
    "wof:placetype":"venue"
},
  "geometry": {"coordinates":[8.452922821,47.4753952026],"type":"Point"}
}