{
  "type": "Feature",
  "properties": {
    "iso:country":"CH",
    "sg:address":"Landstrasse 148",
    "sg:city":"Nussbaumen",
    "sg:classifiers":[
        {
            "category":"Banks & Credit Unions",
            "subcategory":"Bank",
            "type":"Services"
        }
    ],
    "sg:phone":"+41 4156823030",
    "sg:postcode":"5415",
    "sg:province":"Aargau",
    "wof:name":"Gewerbebank Baden",
    "wof:placetype":"venue"
},
  "geometry": {"coordinates":[8.291409,47.487255],"type":"Point"}
}