{
  "type": "Feature",
  "properties": {
    "iso:country":"CH",
    "sg:address":"Hirzbodenweg 114",
    "sg:city":"Basel",
    "sg:orig_category":"Technische, physikalische U chemische Untersuchung",
    "sg:postcode":"4052",
    "sg:province":"Basel-Stadt",
    "wof:name":"Ores Stiftung F\u00fcr Die Erforschung Der Marinen Umwelt",
    "wof:placetype":"venue"
},
  "geometry": {"coordinates":[7.60587883,47.5477981567],"type":"Point"}
}