{
  "type": "Feature",
  "properties": {
    "iso:country":"CH",
    "sg:address":"Boulevard De La Cluse 17",
    "sg:city":"Gen\u00e8ve",
    "sg:orig_category":"Detailhandel mit Waren verschiedener Art, Hauptrichtung Nahrungsmittel Sonstiger Fachdetailhandel mi",
    "sg:phone":"+41 22 320 62 80",
    "sg:postcode":"1205",
    "sg:province":"Gen\u00e8ve",
    "wof:name":"Galicia Alimentation Joana Carvalho-homem",
    "wof:placetype":"venue"
},
  "geometry": {"coordinates":[6.1444177628,46.1887588501],"type":"Point"}
}