{
  "type": "Feature",
  "properties": {
    "iso:country":"CH",
    "sg:address":"Alte Wolleraustrasse 44",
    "sg:city":"Wollerau",
    "sg:orig_category":"Wirtschaftspr\u00fcfung, Steuerberatung U Treuhand",
    "sg:phone":"+41 17842360",
    "sg:postcode":"8832",
    "sg:province":"Schwyz",
    "wof:name":"Ruth Roffler - Treuhandb\u00fcro / Buchhaltungen",
    "wof:placetype":"venue"
},
  "geometry": {"coordinates":[8.7139167786,47.1978683472],"type":"Point"}
}