{
  "type": "Feature",
  "properties": {
    "iso:country":"CH",
    "sg:address":"Oetlingerstrasse 53",
    "sg:city":"Basel",
    "sg:classifiers":[
        {
            "category":"Government",
            "subcategory":"Post Office",
            "type":"Public Place"
        }
    ],
    "sg:phone":"+41 61 692 98 98",
    "sg:postcode":"4057",
    "sg:province":"Basel-Stadt",
    "sg:tags":[
        "caf\u00e9s",
        "tea-rooms"
    ],
    "wof:name":"Caf\u00e9 Ticino",
    "wof:placetype":"venue"
},
  "geometry": {"coordinates":[7.590294838,47.5677452087],"type":"Point"}
}