{
  "type": "Feature",
  "properties": {
    "iso:country":"CH",
    "sg:address":"Viale Carlo Cattaneo 1",
    "sg:city":"Lugano",
    "sg:orig_category":"Unclassifiable Establishments",
    "sg:postcode":"6900",
    "sg:province":"Ticino",
    "wof:name":"Fakema Holding Ag",
    "wof:placetype":"venue"
},
  "geometry": {"coordinates":[9.5314855576,47.4801254272],"type":"Point"}
}