{
  "type": "Feature",
  "properties": {
    "iso:country":"CH",
    "sg:address":"Hauptstrasse 37",
    "sg:city":"Gempen",
    "sg:orig_category":"Politische Parteien FDP",
    "sg:postcode":"4145",
    "sg:province":"Solothurn",
    "wof:name":"Fdp Ortspartei Gempen",
    "wof:placetype":"venue"
},
  "geometry": {"coordinates":[7.6583781242,47.4760627747],"type":"Point"}
}