{
  "type": "Feature",
  "properties": {
    "iso:country":"CH",
    "sg:address":"Ottenweg 16",
    "sg:city":"Z\u00fcrich",
    "sg:orig_category":"Werbegrafikateliers",
    "sg:phone":"+41 12610135",
    "sg:postcode":"8008",
    "sg:province":"Z\u00fcrich",
    "wof:name":"Nadiv & Partner Visuelle Kommunikation",
    "wof:placetype":"venue"
},
  "geometry": {"coordinates":[8.5538759232,47.3635368347],"type":"Point"}
}