{
  "type": "Feature",
  "properties": {
    "iso:country":"CH",
    "sg:address":"Rte Des Coudres 16",
    "sg:city":"C\u00e9ligny",
    "sg:orig_category":"RESTAURANTS: TEA-ROOMS",
    "sg:postcode":"1298",
    "sg:province":"Gen\u00e8ve",
    "wof:name":"Geoffray Et Pegatoquet",
    "wof:placetype":"venue"
},
  "geometry": {"coordinates":[6.1942501068,46.3509635925],"type":"Point"}
}