{
  "type": "Feature",
  "properties": {
    "iso:country":"CH",
    "sg:address":"Talstrasse 66",
    "sg:city":"Z\u00fcrich",
    "sg:orig_category":"Detailhandel mit M\u00f6beln U Haushaltsgegenst\u00e4nden Verlegen von Fussboden",
    "sg:phone":"+41 12125640",
    "sg:postcode":"8001",
    "sg:province":"Z\u00fcrich",
    "wof:name":"Amobilia Inneneinrichtungen Gmbh",
    "wof:placetype":"venue"
},
  "geometry": {"coordinates":[8.5351200104,47.3709793091],"type":"Point"}
}