{
  "type": "Feature",
  "properties": {
    "iso:country":"CH",
    "sg:address":"Route D'arzier 59",
    "sg:city":"St-cergue",
    "sg:orig_category":"Detailhandel mit Brot, Back U S\u00fcsswaren",
    "sg:phone":"+41 22 360 12 75",
    "sg:postcode":"1264",
    "sg:province":"Vaud",
    "wof:name":"Martin Jaussi Boulangerie & P\u00e2tisserie",
    "wof:placetype":"venue"
},
  "geometry": {"coordinates":[6.15758,46.446411],"type":"Point"}
}