{
  "type": "Feature",
  "properties": {
    "iso:country":"CH",
    "sg:address":"Edikerstrasse 5a",
    "sg:city":"D\u00fcrnten",
    "sg:orig_category":"Detailhandel mit M\u00f6beln U Haushaltsgegenst\u00e4nden Detailhandel mit Textilien",
    "sg:phone":"+41 55 210 08 02",
    "sg:postcode":"8635",
    "sg:province":"Z\u00fcrich",
    "wof:name":"Sleep & Dream, Baltensweiler Reto",
    "wof:placetype":"venue"
},
  "geometry": {"coordinates":[8.8430204391,47.2792282104],"type":"Point"}
}