{
  "type": "Feature",
  "properties": {
    "iso:country":"CH",
    "sg:address":"Heilbronnerstrasse 19",
    "sg:city":"Solothurn",
    "sg:orig_category":"Arztpraxen",
    "sg:phone":"+41 32 622 43 33",
    "sg:postcode":"4500",
    "sg:province":"Solothurn",
    "wof:name":"Dr.med.bruno Greusing Spezialarzt Fmh",
    "wof:placetype":"venue"
},
  "geometry": {"coordinates":[7.528311,47.207157],"type":"Point"}
}