{
  "type": "Feature",
  "properties": {
    "iso:country":"CH",
    "sg:address":"Corso San Gottardo 105",
    "sg:city":"Chiasso",
    "sg:orig_category":"Reparatur von Schuhen U Lederwaren",
    "sg:phone":"+41 91 683 62 53",
    "sg:postcode":"6830",
    "sg:province":"Ticino",
    "wof:name":"Ottavio Malaspina Calzoleria",
    "wof:placetype":"venue"
},
  "geometry": {"coordinates":[9.0242376328,45.8367805481],"type":"Point"}
}