{
  "type": "Feature",
  "properties": {
    "iso:country":"CH",
    "sg:address":"Rue Des Philosophes 16",
    "sg:city":"Yverdon-les-bains",
    "sg:orig_category":"Sanit\u00e4rinstallation Zimmerei, Dachdeckerei, Bauspenglerei U Abdichtung",
    "sg:phone":"+41 24 425 29 24",
    "sg:postcode":"1400",
    "sg:province":"Vaud",
    "wof:name":"Carrel Ren\u00e9",
    "wof:placetype":"venue"
},
  "geometry": {"coordinates":[6.6444067955,46.7755050659],"type":"Point"}
}