{
  "type": "Feature",
  "properties": {
    "iso:country":"CH",
    "sg:address":"Oberdorfstrasse 6a",
    "sg:city":"Baar",
    "sg:orig_category":"Betrieb U technische Hilfsdienste des Kultur U Unterhaltungswesens",
    "sg:phone":"+41 41 761 00 81",
    "sg:postcode":"6340",
    "sg:province":"Zug",
    "wof:name":"Feier-plan H\u00fcsser Frau.",
    "wof:placetype":"venue"
},
  "geometry": {"coordinates":[8.529996,47.195915],"type":"Point"}
}