{
  "type": "Feature",
  "properties": {
    "iso:country":"CH",
    "sg:address":"1131",
    "sg:city":"Tolochenaz",
    "sg:orig_category":"Schulpflegen",
    "sg:phone":"+41 26 663 54 62",
    "sg:postcode":"1131",
    "sg:province":"Vaud",
    "wof:name":"Commission Scolaire De L'ecole Primaire",
    "wof:placetype":"venue"
},
  "geometry": {"coordinates":[6.4640598297,46.5057106018],"type":"Point"}
}