{
  "type": "Feature",
  "properties": {
    "iso:country":"CH",
    "sg:address":"Neum\u00fchlequai 6 8001 Z\u00fcrich. Postfach 2265",
    "sg:city":"Z\u00fcrich",
    "sg:orig_category":"Werbevermittlung",
    "sg:phone":"+41 844 844 040",
    "sg:postcode":"8021",
    "sg:province":"Z\u00fcrich",
    "wof:name":"Publimedia Sa Beratung U. Abwicklung F\u00fcr Printwerbung",
    "wof:placetype":"venue"
},
  "geometry": {"coordinates":[8.5434951782,47.3772850037],"type":"Point"}
}