{
  "type": "Feature",
  "properties": {
    "iso:country":"CH",
    "sg:address":"Krachenrain 58",
    "sg:city":"Basel",
    "sg:orig_category":"Vereine Milit\u00e4r",
    "sg:phone":"+41 61 361 85 76",
    "sg:postcode":"4059",
    "sg:province":"Basel-Stadt",
    "wof:name":"Schw.verwaltungsoffiziersges.",
    "wof:placetype":"venue"
},
  "geometry": {"coordinates":[7.5925540924,47.5345420837],"type":"Point"}
}