{
  "type": "Feature",
  "properties": {
    "iso:country":"CH",
    "sg:address":"Avenue Alfred Cortot 7d",
    "sg:city":"Nyon",
    "sg:orig_category":"Gesundheitswesen",
    "sg:phone":"+41 22 362 27 66",
    "sg:postcode":"1260",
    "sg:province":"Vaud",
    "wof:name":"Docteur Meredith Patrick",
    "wof:placetype":"venue"
},
  "geometry": {"coordinates":[6.2316851616,46.3849372864],"type":"Point"}
}