{
  "type": "Feature",
  "properties": {
    "iso:country":"CH",
    "sg:address":"S\u00e9beillon Rue De 1",
    "sg:city":"Lausanne",
    "sg:orig_category":"Unclassifiable Establishments",
    "sg:postcode":"1004",
    "sg:province":"Vaud",
    "wof:name":"Etat De Si\u00e8ge S\u00e0rl",
    "wof:placetype":"venue"
},
  "geometry": {"coordinates":[6.6188678741,46.5233535767],"type":"Point"}
}