{
  "type": "Feature",
  "properties": {
    "iso:country":"CH",
    "sg:address":"Hornimattstrasse 2 5103 Wildegg. Postfach 230",
    "sg:city":"Wildegg",
    "sg:orig_category":"Elektrizit\u00e4tsversorgung Wasserversorgung",
    "sg:phone":"+41 62 887 10 74",
    "sg:postcode":"5103",
    "sg:province":"Aargau",
    "wof:name":"Rtb Regionale Technische Betriebe",
    "wof:placetype":"venue"
},
  "geometry": {"coordinates":[8.1669054031,47.4159812927],"type":"Point"}
}