{
  "type": "Feature",
  "properties": {
    "iso:country":"CH",
    "sg:address":"Violette Rue Jean- 15 1205 Gen\u00e8ve. Postfach",
    "sg:city":"Gen\u00e8ve",
    "sg:orig_category":"RESTAURANTS: TEA-ROOMS",
    "sg:phone":"+41 22 345 89 86",
    "sg:postcode":"1205",
    "sg:province":"Gen\u00e8ve",
    "wof:name":"Conte L.",
    "wof:placetype":"venue"
},
  "geometry": {"coordinates":[6.1450958252,46.1942863464],"type":"Point"}
}