{
  "type": "Feature",
  "properties": {
    "iso:country":"CH",
    "sg:address":"H\u00fcnigenstrasse 23",
    "sg:city":"Konolfingen",
    "sg:orig_category":"Softwareentwicklung U beratung Sonstiger Grosshandel",
    "sg:phone":"+41 31 791 30 60",
    "sg:postcode":"3510",
    "sg:province":"Bern",
    "wof:name":"Dandor Gmbh",
    "wof:placetype":"venue"
},
  "geometry": {"coordinates":[7.6252088547,46.8785591125],"type":"Point"}
}