{
  "type": "Feature",
  "properties": {
    "iso:country":"CH",
    "sg:address":"Zwingenstrasse 54",
    "sg:city":"Brislach",
    "sg:orig_category":"Organisationen des Gesundheitswesen",
    "sg:phone":"+41 61 781 15 67",
    "sg:postcode":"4225",
    "sg:province":"Basel-Landschaft",
    "wof:name":"Samariterverein Breitenbach",
    "wof:placetype":"venue"
},
  "geometry": {"coordinates":[7.5398950577,47.4238739014],"type":"Point"}
}