{
  "type": "Feature",
  "properties": {
    "iso:country":"CH",
    "sg:address":"Industriestrasse 28",
    "sg:city":"Lenzburg",
    "sg:orig_category":"Non-Classified Establishments",
    "sg:phone":"+41 62 892 07 08",
    "sg:postcode":"5600",
    "sg:province":"Aargau",
    "wof:name":"Reaktor Ag Medienwerkstatt",
    "wof:placetype":"venue"
},
  "geometry": {"coordinates":[8.1646318436,47.3918113708],"type":"Point"}
}