{
  "type": "Feature",
  "properties": {
    "iso:country":"CH",
    "sg:address":"Avenue Vinet 19",
    "sg:city":"Lausanne",
    "sg:orig_category":"Kinesiologie Sonstiger Grosshandel",
    "sg:phone":"+41 21 648 11 01",
    "sg:postcode":"1004",
    "sg:province":"Vaud",
    "wof:name":"Arca Sante Sa, Port-louis, Succursale De Lausanne",
    "wof:placetype":"venue"
},
  "geometry": {"coordinates":[6.6295847893,46.525554657],"type":"Point"}
}