{
  "type": "Feature",
  "properties": {
    "iso:country":"CH",
    "sg:address":"Bahnhofstrasse 16",
    "sg:city":"Root",
    "sg:orig_category":"Gesundheitswesen",
    "sg:postcode":"6037",
    "sg:province":"Luzern",
    "wof:name":"Praxis Spuhler M. + P.",
    "wof:placetype":"venue"
},
  "geometry": {"coordinates":[8.3920326233,47.1173591614],"type":"Point"}
}