{
  "type": "Feature",
  "properties": {
    "iso:country":"CH",
    "sg:address":"Berglistrasse 8 8505 Pfyn. Postfach",
    "sg:city":"Pfyn",
    "sg:orig_category":"Werbung",
    "sg:postcode":"8505",
    "sg:province":"Thurgau",
    "wof:name":"Locher.advertising",
    "wof:placetype":"venue"
},
  "geometry": {"coordinates":[8.9537439346,47.5944976807],"type":"Point"}
}