{
  "type": "Feature",
  "properties": {
    "iso:country":"CH",
    "sg:address":"Rue Des Sels 16",
    "sg:city":"Del\u00e9mont",
    "sg:orig_category":"Sportvereine Ballsport Volleyball",
    "sg:phone":"+41 32 422 38 49",
    "sg:postcode":"2800",
    "sg:province":"Jura",
    "wof:name":"Volleyball-club De Del\u00e9mont",
    "wof:placetype":"venue"
},
  "geometry": {"coordinates":[7.3397459984,47.3645935059],"type":"Point"}
}