{
  "type": "Feature",
  "properties": {
    "iso:country":"CH",
    "sg:address":"Gewerbestrasse 3 8500 Frauenfeld. Postfach",
    "sg:city":"Frauenfeld",
    "sg:orig_category":"Gesundheitswesen Medizinische Labors",
    "sg:phone":"+41 52 720 80 20",
    "sg:postcode":"8501",
    "sg:province":"Thurgau",
    "wof:name":"Ilamed Ag Institut F\u00fcr Labormedizin",
    "wof:placetype":"venue"
},
  "geometry": {"coordinates":[8.8790473938,47.5560417175],"type":"Point"}
}