{
  "type": "Feature",
  "properties": {
    "addr:full":"Alte Rheinstrasse 87 Embrach Z\u00fcrich 8424",
    "addr:housenumber":"87",
    "addr:postcode":"8424",
    "addr:street":"Alte Rheinstrasse",
    "iso:country":"CH",
    "sg:address":"Alte Rheinstrasse 87",
    "sg:city":"Embrach",
    "sg:classifiers":[
        {
            "category":"Manufacturing",
            "subcategory":"Chemicals & Compounds",
            "type":"Manufacturing & Wholesale Goods"
        }
    ],
    "sg:phone":"+41 18650424",
    "sg:postcode":"8424",
    "sg:province":"Z\u00fcrich",
    "sg:tags":[
        "ceramic"
    ],
    "wof:name":"Landert Keramik Ag",
    "wof:placetype":"venue"
},
  "geometry": {"coordinates":[8.583614,47.521442],"type":"Point"}
}