{
  "type": "Feature",
  "properties": {
    "iso:country":"CH",
    "sg:address":"Chemin Des Osches 75",
    "sg:city":"Pully",
    "sg:orig_category":"Zahnarztpraxen",
    "sg:phone":"+41 21 728 02 25",
    "sg:postcode":"1009",
    "sg:province":"Vaud",
    "wof:name":"Dr M\u00e9d. Dent. Georges Herzog M\u00e9decin-dentiste",
    "wof:placetype":"venue"
},
  "geometry": {"coordinates":[6.6547808647,46.5086517334],"type":"Point"}
}