{
  "type": "Feature",
  "properties": {
    "iso:country":"CH",
    "sg:address":"Grossbruggerweg 3",
    "sg:city":"Chur",
    "sg:orig_category":"Herstellung von elektrischen Lampen U Leuchten Lampen and Beleuchtungsk\u00f6rper Grosshandel",
    "sg:phone":"+41 81 250 30 10",
    "sg:postcode":"7000",
    "sg:province":"Graubunden",
    "wof:name":"Phil's Concert & Showtechnique, Benesch Ph.",
    "wof:placetype":"venue"
},
  "geometry": {"coordinates":[9.5085639954,46.8579101562],"type":"Point"}
}