{
  "type": "Feature",
  "properties": {
    "iso:country":"CH",
    "sg:address":"M\u00fchlentalstrasse 34 8200 Schaffhausen. Postfach",
    "sg:city":"Schaffhausen",
    "sg:classifiers":[
        {
            "category":"Restaurant",
            "type":"Food & Drink"
        }
    ],
    "sg:phone":"+41 52 625 25 37",
    "sg:postcode":"8201",
    "sg:province":"Schaffhausen",
    "wof:name":"Restaurant Central",
    "wof:placetype":"venue"
},
  "geometry": {"coordinates":[8.6300888062,47.7012367249],"type":"Point"}
}