{
  "type": "Feature",
  "properties": {
    "iso:country":"CH",
    "sg:address":"Route De La Caquerelle 52k",
    "sg:city":"Bo\u00e9court",
    "sg:classifiers":[
        {
            "category":"Travel",
            "subcategory":"Hotels & Motels",
            "type":"Entertainment"
        }
    ],
    "sg:phone":"+41 32 426 75 94",
    "sg:postcode":"2856",
    "sg:province":"Jura",
    "sg:tags":[
        "mit",
        "restaurant"
    ],
    "wof:name":"Motel Le Ch\u00eanois",
    "wof:placetype":"venue"
},
  "geometry": {"coordinates":[7.2126479149,47.3532562256],"type":"Point"}
}