{
  "type": "Feature",
  "properties": {
    "iso:country":"CH",
    "sg:address":"Im Langen Loh 181",
    "sg:city":"Basel",
    "sg:orig_category":"Laboratoriums-Chemikalien",
    "sg:postcode":"4054",
    "sg:province":"Basel-Stadt",
    "wof:name":"Apch Marti Consulting",
    "wof:placetype":"venue"
},
  "geometry": {"coordinates":[7.5609111786,47.5501213074],"type":"Point"}
}