{
  "type": "Feature",
  "properties": {
    "iso:country":"CH",
    "sg:address":"Avenue De Rossfeld 3960 Sierre. Postfach",
    "sg:city":"Visp",
    "sg:orig_category":"Grosshandel mit Holz U Bauelementen aus Holz Grosshandel mit Holz U Baustoffen",
    "sg:phone":"+41 27 455 33 77",
    "sg:postcode":"3930",
    "sg:province":"Valais",
    "wof:name":"Bringhen Ag",
    "wof:placetype":"venue"
},
  "geometry": {"coordinates":[7.519961834,46.285987854],"type":"Point"}
}