{
  "type": "Feature",
  "properties": {
    "iso:country":"CH",
    "sg:address":"In Der W\u00e4ssrig 8240 Thayngen. Postfach",
    "sg:city":"Thayngen",
    "sg:orig_category":"Autotransporte international",
    "sg:phone":"+41 52 653 13 06",
    "sg:postcode":"8240",
    "sg:province":"Schaffhausen",
    "wof:name":"Danzas Ag",
    "wof:placetype":"venue"
},
  "geometry": {"coordinates":[8.612422,47.792828],"type":"Point"}
}