{
  "type": "Feature",
  "properties": {
    "iso:country":"CH",
    "sg:address":"B\u00e4lliz 67",
    "sg:city":"Thun",
    "sg:orig_category":"Detailhandel mit Damenbekleidung",
    "sg:phone":"+41 33 222 20 28",
    "sg:postcode":"3600",
    "sg:province":"Bern",
    "wof:name":"Ursula Fl\u00fcck Brautparadies",
    "wof:placetype":"venue"
},
  "geometry": {"coordinates":[7.629737,46.757401],"type":"Point"}
}