{
  "type": "Feature",
  "properties": {
    "iso:country":"CH",
    "sg:address":"Via Pietro Magistra 22a",
    "sg:city":"Locarno",
    "sg:orig_category":"Vereine Radio, Film and Foto",
    "sg:postcode":"6600",
    "sg:province":"Ticino",
    "wof:name":"English Film Club",
    "wof:placetype":"venue"
},
  "geometry": {"coordinates":[8.772608757,46.1713981628],"type":"Point"}
}