{
  "type": "Feature",
  "properties": {
    "iso:country":"CH",
    "sg:address":"Wiesentalstrasse 120",
    "sg:city":"Chur",
    "sg:orig_category":"Einzelhandel mit Automobilteilen U Zubeh\u00f6r",
    "sg:phone":"+423 373 31 15",
    "sg:postcode":"7000",
    "sg:province":"Graubunden",
    "wof:name":"Pag Ag Pneucenter & Autoreparaturen",
    "wof:placetype":"venue"
},
  "geometry": {"coordinates":[9.5510749817,47.2096252441],"type":"Point"}
}