{
  "type": "Feature",
  "properties": {
    "iso:country":"CH",
    "sg:address":"Blumenstrasse 8",
    "sg:city":"Rorschach",
    "sg:orig_category":"Fussboden, Fliesen U Plattenlegerei, Tapeziererei",
    "sg:postcode":"9400",
    "sg:province":"St. Gallen",
    "wof:name":"Kabashi Parkett",
    "wof:placetype":"venue"
},
  "geometry": {"coordinates":[8.3366804123,47.3527145386],"type":"Point"}
}