{
  "type": "Feature",
  "properties": {
    "iso:country":"CH",
    "sg:address":"Bergstrasse 57",
    "sg:city":"Regensdorf",
    "sg:orig_category":"Herstellung von sonstigen elektrischen Ausr\u00fcstungen",
    "sg:postcode":"8105",
    "sg:province":"Z\u00fcrich",
    "wof:name":"Storni Armando",
    "wof:placetype":"venue"
},
  "geometry": {"coordinates":[8.4627351761,47.4276695251],"type":"Point"}
}