{
  "type": "Feature",
  "properties": {
    "iso:country":"CH",
    "sg:address":"Via Quatorta",
    "sg:city":"Lumino",
    "sg:orig_category":"Unterhalt U Reparatur im Hoch U Tiefbau",
    "sg:phone":"+41 91 829 19 38",
    "sg:postcode":"6533",
    "sg:province":"Ticino",
    "wof:name":"Edil-casa Sa",
    "wof:placetype":"venue"
},
  "geometry": {"coordinates":[9.0534095764,46.225151062],"type":"Point"}
}