{
  "type": "Feature",
  "properties": {
    "iso:country":"CH",
    "sg:address":"Hauptstr. 28",
    "sg:city":"Rh\u00e4z\u00fcns",
    "sg:orig_category":"RESTAURANTS: TEA-ROOMS",
    "sg:postcode":"7403",
    "sg:province":"Graubunden",
    "wof:name":"Tschal\u00e8r Marcel.",
    "wof:placetype":"venue"
},
  "geometry": {"coordinates":[9.3990020752,46.8054656982],"type":"Point"}
}