{
  "type": "Feature",
  "properties": {
    "iso:country":"CH",
    "sg:address":"Quaderstrasse 22",
    "sg:city":"Chur",
    "sg:orig_category":"Detailhandel mit Radio U Fernsehger\u00e4ten",
    "sg:phone":"+41 81 252 18 82",
    "sg:postcode":"7000",
    "sg:province":"Graubunden",
    "wof:name":"Fust Ag Tv Hi-fi Video",
    "wof:placetype":"venue"
},
  "geometry": {"coordinates":[9.5338039398,46.8523254395],"type":"Point"}
}