{
  "type": "Feature",
  "properties": {
    "iso:country":"CH",
    "sg:address":"Gehrenstrasse 19",
    "sg:city":"Flawil",
    "sg:orig_category":"Wirtschaftspr\u00fcfung, Steuerberatung U Treuhand",
    "sg:phone":"+41 71 393 63 06",
    "sg:postcode":"9230",
    "sg:province":"St. Gallen",
    "wof:name":"Getrag-treuhand, Gehrig M.",
    "wof:placetype":"venue"
},
  "geometry": {"coordinates":[9.1844921112,47.4089508057],"type":"Point"}
}