{
  "type": "Feature",
  "properties": {
    "iso:country":"CH",
    "sg:address":"5708",
    "sg:city":"Birrwil",
    "sg:orig_category":"Vereine Gesang",
    "sg:phone":"+41 62 776 26 40",
    "sg:postcode":"5708",
    "sg:province":"Aargau",
    "wof:name":"Gemischter Chor",
    "wof:placetype":"venue"
},
  "geometry": {"coordinates":[8.1267595291,47.328540802],"type":"Point"}
}