{
  "type": "Feature",
  "properties": {
    "iso:country":"CH",
    "sg:address":"Corso Pestalozzi 4a",
    "sg:city":"Lugano",
    "sg:orig_category":"Detailhandel mit Geschenkartikeln U Souvenirs",
    "sg:phone":"+41 91 923 39 16",
    "sg:postcode":"6900",
    "sg:province":"Ticino",
    "wof:name":"Doris Weinberg Boutique Fiorentina",
    "wof:placetype":"venue"
},
  "geometry": {"coordinates":[8.9513549805,46.0061340332],"type":"Point"}
}