{
  "type": "Feature",
  "properties": {
    "iso:country":"CH",
    "sg:address":"Ch. De La D\u00eeme 7",
    "sg:city":"Creux-de-genthod",
    "sg:orig_category":"Sonstige pers\u00f6nliche Dienstleistungen",
    "sg:phone":"+41 22 774 29 76",
    "sg:postcode":"1294",
    "sg:province":"Gen\u00e8ve",
    "wof:name":"Mayoraz Mme R. Info-base",
    "wof:placetype":"venue"
},
  "geometry": {"coordinates":[6.147840023,46.2619895935],"type":"Point"}
}