{
  "type": "Feature",
  "properties": {
    "iso:country":"CH",
    "sg:address":"Museumpassage",
    "sg:city":"Z\u00fcrich",
    "sg:orig_category":"Detailhandel mit Damenbekleidung Detailhandel mit Herrenbekleidung",
    "sg:phone":"+41 12213692",
    "sg:postcode":"8001",
    "sg:province":"Z\u00fcrich",
    "wof:name":"Universal-sport Genossenschaft",
    "wof:placetype":"venue"
},
  "geometry": {"coordinates":[8.537571907,47.379535675],"type":"Point"}
}