{
  "type": "Feature",
  "properties": {
    "iso:country":"CH",
    "sg:address":"Route De St-cergue 307",
    "sg:city":"Nyon",
    "sg:orig_category":"Datenverarbeitungsdienste",
    "sg:phone":"+41 22 990 27 00",
    "sg:postcode":"1260",
    "sg:province":"Vaud",
    "wof:name":"Info Plus Informatique",
    "wof:placetype":"venue"
},
  "geometry": {"coordinates":[6.225828,46.396461],"type":"Point"}
}