{
  "type": "Feature",
  "properties": {
    "iso:country":"CH",
    "sg:address":"Zimmelstrasse 34a",
    "sg:city":"Unter\u00e4geri",
    "sg:orig_category":"Softwareentwicklung U beratung",
    "sg:phone":"+41 17152515",
    "sg:postcode":"6314",
    "sg:province":"Zug",
    "wof:name":"Chez Fritz Ag",
    "wof:placetype":"venue"
},
  "geometry": {"coordinates":[8.5754766464,47.1366386414],"type":"Point"}
}