{
  "type": "Feature",
  "properties": {
    "iso:country":"CH",
    "sg:address":"Bodmerstrasse 7",
    "sg:city":"Z\u00fcrich",
    "sg:orig_category":"Forschung U Entwicklung im Bereich der Naturwissenschaften Grosshandel mit medizinischen U orthop\u00e4di",
    "sg:phone":"+41 21 968 16 00",
    "sg:postcode":"8002",
    "sg:province":"Z\u00fcrich",
    "wof:name":"Condor Dental Research Compagny Sa",
    "wof:placetype":"venue"
},
  "geometry": {"coordinates":[6.9342560768,46.3926467896],"type":"Point"}
}