{
  "type": "Feature",
  "properties": {
    "iso:country":"CH",
    "sg:address":"8556 Wigoltingen. Postfach",
    "sg:city":"Wigoltingen",
    "sg:orig_category":"Wasserversorgung",
    "sg:phone":"+41 71 744 32 88",
    "sg:postcode":"8556",
    "sg:province":"Thurgau",
    "wof:name":"Wasserwerk Au-balgach-rebstein Widnau Pr\u00e4s.walter Giger",
    "wof:placetype":"venue"
},
  "geometry": {"coordinates":[9.6351919174,47.4310073853],"type":"Point"}
}