{
  "type": "Feature",
  "properties": {
    "iso:country":"CH",
    "sg:address":"6416",
    "sg:city":"Steinerberg",
    "sg:orig_category":"Haltung von Rindern",
    "sg:postcode":"6416",
    "sg:province":"Schwyz",
    "wof:name":"Viehzuchtgenossenschaft Steinerberg-r\u00f6ssligass",
    "wof:placetype":"venue"
},
  "geometry": {"coordinates":[8.5840892792,47.0531196594],"type":"Point"}
}