{
  "type": "Feature",
  "properties": {
    "iso:country":"CH",
    "sg:address":"Posatweg 6",
    "sg:city":"Courgevaux",
    "sg:orig_category":"Herstellung von \u00d6fen U Brennern",
    "sg:phone":"+41 26 670 33 77",
    "sg:postcode":"1796",
    "sg:province":"Fribourg",
    "wof:name":"Etter Werner",
    "wof:placetype":"venue"
},
  "geometry": {"coordinates":[7.1129832268,46.9071350098],"type":"Point"}
}