{
  "type": "Feature",
  "properties": {
    "iso:country":"CH",
    "sg:address":"6543",
    "sg:city":"Arvigo",
    "sg:orig_category":"G\u00fcterbef\u00f6rderung im Strassenverkehr S\u00e4gewerke",
    "sg:phone":"+41 91 828 12 02",
    "sg:postcode":"6543",
    "sg:province":"Graubunden",
    "wof:name":"Raimondo Denicola Segheria",
    "wof:placetype":"venue"
},
  "geometry": {"coordinates":[9.1141119003,46.302986145],"type":"Point"}
}