{
  "type": "Feature",
  "properties": {
    "iso:country":"CH",
    "sg:address":"Rue De La Cit\u00e9 24 1200 Genf. Postfach",
    "sg:city":"Gen\u00e8ve",
    "sg:orig_category":"Grosshandel mit Getr\u00e4nken",
    "sg:postcode":"1201",
    "sg:province":"Gen\u00e8ve",
    "wof:name":"Galerie Vinum, Job\u00e9 L. Et Hebri A.",
    "wof:placetype":"venue"
},
  "geometry": {"coordinates":[6.1442651749,46.2026023865],"type":"Point"}
}