{
  "type": "Feature",
  "properties": {
    "iso:country":"CH",
    "sg:address":"Zeughausstrasse 55",
    "sg:city":"Z\u00fcrich",
    "sg:orig_category":"Detailhandel mit Antiquit\u00e4ten Kunsthandel",
    "sg:phone":"+41 12422850",
    "sg:postcode":"8004",
    "sg:province":"Z\u00fcrich",
    "wof:name":"Bikini Design Antiquit\u00e4ten Galerie",
    "wof:placetype":"venue"
},
  "geometry": {"coordinates":[8.529489,47.376186],"type":"Point"}
}