{
  "type": "Feature",
  "properties": {
    "iso:country":"CH",
    "sg:address":"An Der Ron 7 6280 Hochdorf. Postfach 42",
    "sg:city":"Hochdorf",
    "sg:orig_category":"Herstellung von Fenstern U T\u00fcren aus Holz Herstellung von Konstruktionsteilen, Fertigbauteilen U Aus",
    "sg:phone":"+41 14820666",
    "sg:postcode":"6281",
    "sg:province":"Luzern",
    "wof:name":"4b Bachmann Ag",
    "wof:placetype":"venue"
},
  "geometry": {"coordinates":[8.5295629501,47.3245811462],"type":"Point"}
}