{
  "type": "Feature",
  "properties": {
    "iso:country":"CH",
    "sg:address":"Hardweg 12",
    "sg:city":"Matzingen",
    "sg:orig_category":"Unclassifiable Establishments",
    "sg:postcode":"9548",
    "sg:province":"Thurgau",
    "wof:name":"Zbescht By Brux Inhaberin Myriam Brux",
    "wof:placetype":"venue"
},
  "geometry": {"coordinates":[8.9376869202,47.5183372498],"type":"Point"}
}