{
  "type": "Feature",
  "properties": {
    "iso:country":"CH",
    "sg:address":"Zurlindenstrasse 213 8003 Z\u00fcrich. Postfach",
    "sg:city":"Z\u00fcrich",
    "sg:classifiers":[
        {
            "category":"Communications",
            "subcategory":"Radio Station",
            "type":"Services"
        }
    ],
    "sg:phone":"+41 14504017",
    "sg:postcode":"8036",
    "sg:province":"Z\u00fcrich",
    "sg:tags":[
        "fernsehanstalten",
        "u"
    ],
    "wof:name":"B\u00fcro4, Corti, Hunziker, Robert, Wullschleger, Gestaltung + Kommunikation",
    "wof:placetype":"venue"
},
  "geometry": {"coordinates":[8.5142631531,47.374546051],"type":"Point"}
}