{
  "type": "Feature",
  "properties": {
    "iso:country":"CH",
    "sg:address":"Landstrasse 4 5436 W\u00fcrenlos. Postfach",
    "sg:city":"W\u00fcrenlos",
    "sg:orig_category":"Grosshandel mit Erzen U Metallen Grosshandel mit Getreide, Saatgut U Futtermitteln",
    "sg:phone":"+41 56 424 01 51",
    "sg:postcode":"5436",
    "sg:province":"Aargau",
    "wof:name":"Peterhans Handwerker-center Ag",
    "wof:placetype":"venue"
},
  "geometry": {"coordinates":[8.3498048782,47.452293396],"type":"Point"}
}