{
  "type": "Feature",
  "properties": {
    "iso:country":"CH",
    "sg:address":"Grand'rue 22",
    "sg:city":"Founex",
    "sg:orig_category":"Rebbau",
    "sg:phone":"+41 79 225 57 21",
    "sg:postcode":"1297",
    "sg:province":"Vaud",
    "wof:name":"Fran\u00e7ois Deblu\u00eb Domaine Les Fancous",
    "wof:placetype":"venue"
},
  "geometry": {"coordinates":[6.1922469139,46.3314247131],"type":"Point"}
}