{
  "type": "Feature",
  "properties": {
    "iso:country":"CH",
    "sg:address":"Mandement Route Du 17 1217 Meyrin. Postfach",
    "sg:city":"Meyrin",
    "sg:orig_category":"Allgemeiner Hoch U Tiefbau",
    "sg:postcode":"1217",
    "sg:province":"Gen\u00e8ve",
    "wof:name":"Genfac, Althaus Fran\u00e7ois R\u00e9novation De Fa\u00e7ades, Pierres Etc",
    "wof:placetype":"venue"
},
  "geometry": {"coordinates":[6.060012,46.22921],"type":"Point"}
}