{
  "type": "Feature",
  "properties": {
    "iso:country":"CH",
    "sg:address":"Tr\u00fcmmernstr. 45",
    "sg:city":"Kaufdorf",
    "sg:orig_category":"Allgemeiner Hoch U Tiefbau",
    "sg:postcode":"3126",
    "sg:province":"Bern",
    "wof:name":"Pumaton Ag",
    "wof:placetype":"venue"
},
  "geometry": {"coordinates":[9.394304,47.44046],"type":"Point"}
}