{
  "type": "Feature",
  "properties": {
    "iso:country":"CH",
    "sg:address":"Passage Perdonnet 1 1000 Lausanne. Postfach",
    "sg:city":"Lausanne",
    "sg:orig_category":"Herstellung von Teppichen",
    "sg:phone":"+41 52 385 47 60",
    "sg:postcode":"1000",
    "sg:province":"Vaud",
    "wof:name":"H\u00e4berlin Gmbh",
    "wof:placetype":"venue"
},
  "geometry": {"coordinates":[8.8478269577,47.4188346863],"type":"Point"}
}