{
  "type": "Feature",
  "properties": {
    "iso:country":"CH",
    "sg:address":"Dorfstrasse 12",
    "sg:city":"Fl\u00fcelen",
    "sg:orig_category":"Unclassifiable Establishments",
    "sg:postcode":"6454",
    "sg:province":"Uri",
    "wof:name":"Gasser Felstechnik Ag Lungern, Zweigniederlassung Fl\u00fcelen",
    "wof:placetype":"venue"
},
  "geometry": {"coordinates":[8.6255197525,46.9020996094],"type":"Point"}
}