{
  "type": "Feature",
  "properties": {
    "iso:country":"CH",
    "sg:address":"Schaffhauserstrasse 202",
    "sg:city":"Z\u00fcrich",
    "sg:orig_category":"Betrieb von Taxis",
    "sg:phone":"+41 13122624",
    "sg:postcode":"8057",
    "sg:province":"Z\u00fcrich",
    "wof:name":"Luciano Quadri Taxi",
    "wof:placetype":"venue"
},
  "geometry": {"coordinates":[8.544565,47.400776],"type":"Point"}
}