{
  "type": "Feature",
  "properties": {
    "iso:country":"CH",
    "sg:address":"Strassmatte 7",
    "sg:city":"Sursee",
    "sg:orig_category":"Vereine Z\u00fcnfte",
    "sg:phone":"+41 41 921 10 27",
    "sg:postcode":"6210",
    "sg:province":"Luzern",
    "wof:name":"Ruuggli-zunft",
    "wof:placetype":"venue"
},
  "geometry": {"coordinates":[8.0911922455,47.1733627319],"type":"Point"}
}