{
  "type": "Feature",
  "properties": {
    "iso:country":"CH",
    "sg:address":"Henneus",
    "sg:city":"Billens",
    "sg:orig_category":"G\u00fcterbef\u00f6rderung im Strassenverkehr",
    "sg:postcode":"1681",
    "sg:province":"Fribourg",
    "wof:name":"Dumas Jean",
    "wof:placetype":"venue"
},
  "geometry": {"coordinates":[6.8952560425,46.6855583191],"type":"Point"}
}