{
  "type": "Feature",
  "properties": {
    "iso:country":"CH",
    "sg:address":"Eugen Huber-strasse 15",
    "sg:city":"Z\u00fcrich",
    "sg:orig_category":"Sportvereine Turnen",
    "sg:phone":"+41 12612044",
    "sg:postcode":"8048",
    "sg:province":"Z\u00fcrich",
    "wof:name":"Turn-& Sportverein Riesbach",
    "wof:placetype":"venue"
},
  "geometry": {"coordinates":[8.4842185974,47.3851203918],"type":"Point"}
}