{
  "type": "Feature",
  "properties": {
    "iso:country":"CH",
    "sg:address":"D\u00e4rligenstrasse 2",
    "sg:city":"Interlaken",
    "sg:orig_category":"Detailhandel mit Waren verschiedener Art, Hauptrichtung Nichtnahrungsmittel Handelsvermittlung U Gro",
    "sg:phone":"+41 33 823 31 69",
    "sg:postcode":"3800",
    "sg:province":"Bern",
    "wof:name":"Miladin Matic Skandalpreis Lagerverkauf",
    "wof:placetype":"venue"
},
  "geometry": {"coordinates":[7.8419151306,46.6715583801],"type":"Point"}
}