{
  "type": "Feature",
  "properties": {
    "iso:country":"CH",
    "sg:address":"Bielstrasse 80 4500 Solothurn. Postfach",
    "sg:city":"Solothurn",
    "sg:orig_category":"Herstellung von sonstigen Maschinen f\u00fcr unspezifische Verwendung",
    "sg:phone":"+41 32 625 93 11",
    "sg:postcode":"4500",
    "sg:province":"Solothurn",
    "wof:name":"Bamotec Ag",
    "wof:placetype":"venue"
},
  "geometry": {"coordinates":[7.5247621536,47.2112312317],"type":"Point"}
}