{
  "type": "Feature",
  "properties": {
    "iso:country":"CH",
    "sg:address":"Bernstrasse 11 3175 Flamatt. Postfach",
    "sg:city":"Flamatt",
    "sg:orig_category":"Erschliessung von Grundst\u00fccken",
    "sg:postcode":"3175",
    "sg:province":"Fribourg",
    "wof:name":"Biotop I",
    "wof:placetype":"venue"
},
  "geometry": {"coordinates":[6.5952038765,46.5426979065],"type":"Point"}
}