{
  "type": "Feature",
  "properties": {
    "iso:country":"CH",
    "sg:address":"Grand-rue 21",
    "sg:city":"Corg\u00e9mont",
    "sg:orig_category":"Detailhandel mit Brot, Back U S\u00fcsswaren",
    "sg:phone":"+41 32 489 12 28",
    "sg:postcode":"2606",
    "sg:province":"Bern",
    "wof:name":"Jean-denis Steiner Boulangerie & P\u00e2tisserie",
    "wof:placetype":"venue"
},
  "geometry": {"coordinates":[7.143814,47.194088],"type":"Point"}
}