{
  "type": "Feature",
  "properties": {
    "iso:country":"CH",
    "sg:address":"Hauptstrasse 13",
    "sg:city":"Muhen",
    "sg:classifiers":[
        {
            "category":"Bars & Pubs",
            "type":"Food & Drink"
        }
    ],
    "sg:phone":"+41 62 723 53 22",
    "sg:postcode":"5037",
    "sg:province":"Aargau",
    "wof:name":"Pub Casino",
    "wof:placetype":"venue"
},
  "geometry": {"coordinates":[8.053636,47.342369],"type":"Point"}
}