{
  "type": "Feature",
  "properties": {
    "iso:country":"CH",
    "sg:address":"Bellariastrasse 11 8002 Z\u00fcrich. Postfach",
    "sg:city":"Z\u00fcrich",
    "sg:orig_category":"Markt U Meinungsforschung",
    "sg:postcode":"8001",
    "sg:province":"Z\u00fcrich",
    "wof:name":"Adoro, R. Ammann Marketingberatung; Handel M. Waren Aller Art",
    "wof:placetype":"venue"
},
  "geometry": {"coordinates":[8.531170845,47.3545303345],"type":"Point"}
}