{
  "type": "Feature",
  "properties": {
    "iso:country":"CH",
    "sg:address":"Surbtalstrasse 22",
    "sg:city":"D\u00f6ttingen",
    "sg:orig_category":"Bauschreinerei Herstellung von Radio U Fernsehger\u00e4ten sowie phono U videotechnischen Ger\u00e4ten",
    "sg:phone":"+41 19322873",
    "sg:postcode":"5312",
    "sg:province":"Aargau",
    "wof:name":"Acr Weideli & Co",
    "wof:placetype":"venue"
},
  "geometry": {"coordinates":[8.791998,47.319672],"type":"Point"}
}