{
  "type": "Feature",
  "properties": {
    "iso:country":"CH",
    "sg:address":"Industrie Rue De L' 45",
    "sg:city":"Bulle",
    "sg:orig_category":"Pensionskassen",
    "sg:postcode":"1630",
    "sg:province":"Fribourg",
    "wof:name":"Personalf\u00fcrsorgestiftung Der Liebherr-gesellschaften In Der Schweiz",
    "wof:placetype":"venue"
},
  "geometry": {"coordinates":[7.0335249901,46.6226463318],"type":"Point"}
}