{
  "type": "Feature",
  "properties": {
    "iso:country":"CH",
    "sg:address":"Stationsstrasse 24",
    "sg:city":"Ennetb\u00fcrgen",
    "sg:classifiers":[
        {
            "category":"Restaurant",
            "type":"Food & Drink"
        }
    ],
    "sg:phone":"+41 41 620 04 10",
    "sg:postcode":"6373",
    "sg:province":"Nidwalden",
    "wof:name":"Restaurant Schl\u00fcssel",
    "wof:placetype":"venue"
},
  "geometry": {"coordinates":[8.4181671143,46.9870948792],"type":"Point"}
}