{
  "type": "Feature",
  "properties": {
    "iso:country":"CH",
    "sg:address":"Am Schanzengraben 15 8000 Z\u00fcrich. Postfach",
    "sg:city":"Z\u00fcrich",
    "sg:orig_category":"Interessenvertretungen",
    "sg:postcode":"8001",
    "sg:province":"Z\u00fcrich",
    "wof:name":"Integras, Fachverband Sozial Und Heilp\u00e4dagogik",
    "wof:placetype":"venue"
},
  "geometry": {"coordinates":[8.5362234116,47.3686676025],"type":"Point"}
}