{
  "type": "Feature",
  "properties": {
    "iso:country":"CH",
    "sg:address":"Riburgerstrasse 16",
    "sg:city":"M\u00f6hlin",
    "sg:orig_category":"Detailhandel mit Fleisch U Fleischwaren",
    "sg:phone":"+41 61 851 10 00",
    "sg:postcode":"4313",
    "sg:province":"Aargau",
    "wof:name":"Walter Oderbolz Metzgerei",
    "wof:placetype":"venue"
},
  "geometry": {"coordinates":[7.8405170441,47.5648956299],"type":"Point"}
}