{
  "type": "Feature",
  "properties": {
    "iso:country":"CH",
    "sg:address":"Dorfstr. 94",
    "sg:city":"Wohlenschwil",
    "sg:orig_category":"Schreib U \u00dcbersetzungsb\u00fcros",
    "sg:phone":"+41 56 491 35 36",
    "sg:postcode":"5512",
    "sg:province":"Aargau",
    "wof:name":"Brito Odarda Brigitte",
    "wof:placetype":"venue"
},
  "geometry": {"coordinates":[8.2605791092,47.4208831787],"type":"Point"}
}