{
  "type": "Feature",
  "properties": {
    "iso:country":"CH",
    "sg:address":"Av.du Bois-de-la-chapelle 17",
    "sg:city":"Onex",
    "sg:orig_category":"Vorschulen, Kinderg\u00e4rten",
    "sg:phone":"+41 22 793 11 55",
    "sg:postcode":"1213",
    "sg:province":"Gen\u00e8ve",
    "wof:name":"Ecole Enfantine Racettes I-iv",
    "wof:placetype":"venue"
},
  "geometry": {"coordinates":[6.1068811417,46.1906661987],"type":"Point"}
}