{
  "type": "Feature",
  "properties": {
    "iso:country":"CH",
    "sg:address":"Rue Centrale",
    "sg:city":"Orsi\u00e8res",
    "sg:orig_category":"HOTELS: MIT RESTAURANT Kongress- and Tagungshotels mit Restaurant",
    "sg:phone":"+41 27 783 11 38",
    "sg:postcode":"1937",
    "sg:province":"Valais",
    "wof:name":"H\u00f4tel Union",
    "wof:placetype":"venue"
},
  "geometry": {"coordinates":[7.1461839676,46.0304603577],"type":"Point"}
}