{
  "type": "Feature",
  "properties": {
    "iso:country":"CH",
    "sg:address":"Chemin Des Dailles 2",
    "sg:city":"Cugy",
    "sg:classifiers":[
        {
            "category":"Utilities",
            "type":"Services"
        }
    ],
    "sg:phone":"+41 21 731 07 00",
    "sg:postcode":"1053",
    "sg:province":"Vaud",
    "sg:tags":[
        "electric",
        "steam",
        "hot-water",
        "boiler"
    ],
    "wof:name":"Isolux Sa",
    "wof:placetype":"venue"
},
  "geometry": {"coordinates":[6.6413908005,46.5890045166],"type":"Point"}
}