{
  "type": "Feature",
  "properties": {
    "iso:country":"CH",
    "sg:address":"1030 Bussigny-lausanne. Postfach",
    "sg:city":"Bussigny-lausanne",
    "sg:orig_category":"Detailhandel mit Waren verschiedener Art, Hauptrichtung Nahrungsmittel",
    "sg:phone":"+41 62 893 45 03",
    "sg:postcode":"1030",
    "sg:province":"Vaud",
    "wof:name":"Hp. & K. Eichenberger Denner Satellit",
    "wof:placetype":"venue"
},
  "geometry": {"coordinates":[8.1834096909,47.4161987305],"type":"Point"}
}