{
  "type": "Feature",
  "properties": {
    "iso:country":"CH",
    "sg:address":"Via Alpsu 87 Sedrun 7188 Tujetsch. Postfach",
    "sg:city":"Sedrun",
    "sg:orig_category":"RESTAURANTS: TEA-ROOMS",
    "sg:postcode":"7188",
    "sg:province":"Graubunden",
    "wof:name":"Knopp-wyss Andrea, Restaurant Badus",
    "wof:placetype":"venue"
},
  "geometry": {"coordinates":[8.7735700607,46.6795310974],"type":"Point"}
}