{
  "type": "Feature",
  "properties": {
    "iso:country":"CH",
    "sg:address":"Bankstrasse 30",
    "sg:city":"Glarus",
    "sg:orig_category":"Arztpraxen",
    "sg:phone":"+41 55 640 54 54",
    "sg:postcode":"8750",
    "sg:province":"Glarus",
    "wof:name":"Dr.med.ludwig B\u00fcsser Arzt F.allgemeine Medizin Fmh",
    "wof:placetype":"venue"
},
  "geometry": {"coordinates":[9.067938,47.040329],"type":"Point"}
}