{
  "type": "Feature",
  "properties": {
    "iso:country":"CH",
    "sg:address":"3987",
    "sg:city":"Riederalp",
    "sg:orig_category":"Sportvereine Ballsport Tennis",
    "sg:postcode":"3987",
    "sg:province":"Valais",
    "wof:name":"Tennisclub Riva San Vitale",
    "wof:placetype":"venue"
},
  "geometry": {"coordinates":[8.9712247849,45.9057006836],"type":"Point"}
}