{
  "type": "Feature",
  "properties": {
    "iso:country":"CH",
    "sg:address":"Talstrasse 60 A",
    "sg:city":"Hirschthal",
    "sg:orig_category":"Non-Classified Establishments",
    "sg:postcode":"5042",
    "sg:province":"Aargau",
    "wof:name":"A. Meier Gartenbau Ag",
    "wof:placetype":"venue"
},
  "geometry": {"coordinates":[8.067896843,47.3159179688],"type":"Point"}
}