{
  "type": "Feature",
  "properties": {
    "iso:country":"CH",
    "sg:address":"Mythenstrasse 5 6410 Goldau. Postfach 21",
    "sg:city":"Goldau",
    "sg:orig_category":"Detailhandel mit Radio U Fernsehger\u00e4ten Herstellung von Radio U Fernsehger\u00e4ten sowie phono U videote",
    "sg:phone":"+41 41 855 13 52",
    "sg:postcode":"6410",
    "sg:province":"Schwyz",
    "wof:name":"Expert K\u00e4lin C\u00e4sar Inhaber Abegg Remo",
    "wof:placetype":"venue"
},
  "geometry": {"coordinates":[8.5493078232,47.0509757996],"type":"Point"}
}