{
  "type": "Feature",
  "properties": {
    "iso:country":"CH",
    "sg:address":"Rennweg 40 4052 Basel. Postfach",
    "sg:city":"Basel",
    "sg:orig_category":"Pensionskassen",
    "sg:phone":"+41 41 499 90 60",
    "sg:postcode":"4051",
    "sg:province":"Basel-Stadt",
    "wof:name":"Wohlfahrtsstiftung Der Josef Renggli Ag, Bauunternehmung, Malters",
    "wof:placetype":"venue"
},
  "geometry": {"coordinates":[8.1827249527,47.0368156433],"type":"Point"}
}