{
  "type": "Feature",
  "properties": {
    "iso:country":"CH",
    "sg:address":"3308",
    "sg:city":"Grafenried",
    "sg:orig_category":"Vereine Vogel-& Naturschutz",
    "sg:postcode":"3308",
    "sg:province":"Bern",
    "wof:name":"Ornithologischer Verein Grafenried & Umgebung",
    "wof:placetype":"venue"
},
  "geometry": {"coordinates":[7.5074801445,47.0782394409],"type":"Point"}
}