{
  "type": "Feature",
  "properties": {
    "iso:country":"CH",
    "sg:address":"Rue Des Sports 15 1926 Fully Case Postale 258",
    "sg:city":"Fully",
    "sg:orig_category":"Grosshandel mit Getr\u00e4nken Grosshandel mit Wein U Spirituosen",
    "sg:phone":"+41 27 746 13 27",
    "sg:postcode":"1926",
    "sg:province":"Valais",
    "wof:name":"Laurent Th\u00e9taz Famille Vins Sa",
    "wof:placetype":"venue"
},
  "geometry": {"coordinates":[7.1117601395,46.1372108459],"type":"Point"}
}