{
  "type": "Feature",
  "properties": {
    "iso:country":"CH",
    "sg:address":"Rebwiesstrasse 12",
    "sg:city":"Zollikon",
    "sg:orig_category":"Detailhandel mit elektrischen Haushalts-,Radio U Fernsehger\u00e4ten sowie Musikinstrumenten",
    "sg:phone":"+41 13913480",
    "sg:postcode":"8702",
    "sg:province":"Z\u00fcrich",
    "wof:name":"Cd Vision, C. Dolmetsch",
    "wof:placetype":"venue"
},
  "geometry": {"coordinates":[8.5823278427,47.3476524353],"type":"Point"}
}