{
  "type": "Feature",
  "properties": {
    "iso:country":"CH",
    "sg:address":"Socinstrasse 14 4051 Basel. Postfach 2833",
    "sg:city":"Basel",
    "sg:orig_category":"Advokaturb\u00fcros",
    "sg:phone":"+41 71 223 44 33",
    "sg:postcode":"4002",
    "sg:province":"Basel-Stadt",
    "wof:name":"Flurin Turnes Advokaturb\u00fcro",
    "wof:placetype":"venue"
},
  "geometry": {"coordinates":[9.374848,47.424622],"type":"Point"}
}