{
  "type": "Feature",
  "properties": {
    "iso:country":"CH",
    "sg:address":"St. Jakobs-strasse 54",
    "sg:city":"Basel",
    "sg:orig_category":"Wirtschaftspr\u00fcfung, Steuerberatung U Treuhand",
    "sg:phone":"+41 21 312 27 39",
    "sg:postcode":"4052",
    "sg:province":"Basel-Stadt",
    "wof:name":"Pittet Y. Fiduciaire",
    "wof:placetype":"venue"
},
  "geometry": {"coordinates":[6.6325621605,46.5261306763],"type":"Point"}
}