{
  "type": "Feature",
  "properties": {
    "iso:country":"CH",
    "sg:address":"Murgenthalstrasse 41",
    "sg:city":"Langenthal",
    "sg:orig_category":"Non-Classified Establishments",
    "sg:postcode":"4900",
    "sg:province":"Bern",
    "wof:name":"Diesel Fritz Gmbh",
    "wof:placetype":"venue"
},
  "geometry": {"coordinates":[7.7913298607,47.2271881104],"type":"Point"}
}