{
  "type": "Feature",
  "properties": {
    "iso:country":"CH",
    "sg:address":"Sagem\u00fcli",
    "sg:city":"Ruswil",
    "sg:orig_category":"Grosshandel mit Holz U Bauelementen aus Holz S\u00e4gewerke",
    "sg:phone":"+41 41 495 10 53",
    "sg:postcode":"6017",
    "sg:province":"Luzern",
    "wof:name":"Alois B\u00fchlmann",
    "wof:placetype":"venue"
},
  "geometry": {"coordinates":[8.1267347336,47.0835609436],"type":"Point"}
}