{
  "type": "Feature",
  "properties": {
    "iso:country":"CH",
    "sg:address":"Letzigraben 168",
    "sg:city":"Z\u00fcrich",
    "sg:orig_category":"Handelsvermittlung U Grosshandel Handelsvermittlung U Grosshandel mit Automobilteilen U Zubeh\u00f6r",
    "sg:phone":"+41 21 845 40 59",
    "sg:postcode":"8047",
    "sg:province":"Z\u00fcrich",
    "wof:name":"Michel Golay Fournitures Pour Automobiles",
    "wof:placetype":"venue"
},
  "geometry": {"coordinates":[6.2272391319,46.6016998291],"type":"Point"}
}