{
  "type": "Feature",
  "properties": {
    "iso:country":"CH",
    "sg:address":"1716 Plaffeien. Postfach",
    "sg:city":"Plaffeien",
    "sg:orig_category":"Polizei",
    "sg:phone":"+41 31 738 88 44",
    "sg:postcode":"1716",
    "sg:province":"Fribourg",
    "wof:name":"Kantonale Polizei",
    "wof:placetype":"venue"
},
  "geometry": {"coordinates":[7.4069471359,46.7818603516],"type":"Point"}
}