{
  "type": "Feature",
  "properties": {
    "iso:country":"CH",
    "sg:address":"Luzernerstrasse 11",
    "sg:city":"Hitzkirch",
    "sg:orig_category":"Detailhandel mit Fleisch U Fleischwaren",
    "sg:phone":"+41 41 917 12 23",
    "sg:postcode":"6285",
    "sg:province":"Luzern",
    "wof:name":"Bitzi Metzg Ag",
    "wof:placetype":"venue"
},
  "geometry": {"coordinates":[8.2641267776,47.2236442566],"type":"Point"}
}