{
  "type": "Feature",
  "properties": {
    "iso:country":"CH",
    "sg:address":"5442 Fislisbach. Postfach 4",
    "sg:city":"Fislisbach",
    "sg:orig_category":"Sportvereine Turnen",
    "sg:postcode":"5442",
    "sg:province":"Aargau",
    "wof:name":"Turnverein Stv Fislisbach",
    "wof:placetype":"venue"
},
  "geometry": {"coordinates":[8.2914400101,47.4361915588],"type":"Point"}
}