{
  "type": "Feature",
  "properties": {
    "iso:country":"CH",
    "sg:address":"Hauptstr. 4",
    "sg:city":"Kriegstetten",
    "sg:orig_category":"Allgemeiner Hoch U Tiefbau",
    "sg:postcode":"4566",
    "sg:province":"Solothurn",
    "wof:name":"Steiner + M\u00fcller, Geb\u00e4udesanierungen.",
    "wof:placetype":"venue"
},
  "geometry": {"coordinates":[7.596215,47.180798],"type":"Point"}
}