{
  "type": "Feature",
  "properties": {
    "iso:country":"CH",
    "sg:address":"Obergrundstrasse 28",
    "sg:city":"Luzern",
    "sg:orig_category":"Saunas, Solarien, Fitnesszentren U \u00e4hnliches",
    "sg:postcode":"6003",
    "sg:province":"Luzern",
    "wof:name":"Funny Sun Gmbh",
    "wof:placetype":"venue"
},
  "geometry": {"coordinates":[8.3114833832,46.9857254028],"type":"Point"}
}