{
  "type": "Feature",
  "properties": {
    "iso:country":"CH",
    "sg:address":"Sonneggstrasse 54",
    "sg:city":"Z\u00fcrich",
    "sg:orig_category":"Sonstige Aktivit\u00e4ten der nicht-\u00e4rztlichen Medizinalberufe",
    "sg:phone":"+41 12526152",
    "sg:postcode":"8006",
    "sg:province":"Z\u00fcrich",
    "wof:name":"Maria Rosenfelder Atemtherapie",
    "wof:placetype":"venue"
},
  "geometry": {"coordinates":[8.5458688736,47.3811073303],"type":"Point"}
}