{
  "type": "Feature",
  "properties": {
    "iso:country":"CH",
    "sg:address":"Via Serafino Balestra 27 6900 Lugano. Postfach",
    "sg:city":"Lugano",
    "sg:orig_category":"Fachdetailhandel in Verkaufsr\u00e4umen",
    "sg:postcode":"6900",
    "sg:province":"Ticino",
    "wof:name":"Mercanti D'oro G. & G. Sagl Oggetti Preziosi, Semipreziosi, Oro; Comm., Import. Ecc",
    "wof:placetype":"venue"
},
  "geometry": {"coordinates":[8.9577894211,46.0079498291],"type":"Point"}
}