{
  "type": "Feature",
  "properties": {
    "addr:full":"Rue Du Ch\u00e2teau 1 Broc Fribourg 1636",
    "addr:housenumber":"1",
    "addr:postcode":"1636",
    "addr:street":"Rue Du Cha\u0302Teau",
    "iso:country":"CH",
    "sg:address":"Rue Du Ch\u00e2teau 1",
    "sg:city":"Broc",
    "sg:orig_category":"Detailhandel mit Blumen U Pflanzen",
    "sg:phone":"+41 26 921 16 26",
    "sg:postcode":"1636",
    "sg:province":"Fribourg",
    "wof:name":"Jean-marie Savary Sa Fleuriste Pr\u00e9-fleuri",
    "wof:placetype":"venue"
},
  "geometry": {"coordinates":[7.101312,46.602581],"type":"Point"}
}