{
  "type": "Feature",
  "properties": {
    "iso:country":"CH",
    "sg:address":"St. Gallerstrasse 64 8352 R\u00e4terschen. Postfach 129",
    "sg:city":"R\u00e4terschen",
    "sg:orig_category":"Detailhandel mit Waren verschiedener Art, Hauptrichtung Nahrungsmittel",
    "sg:phone":"+41 52 363 10 22",
    "sg:postcode":"8352",
    "sg:province":"Z\u00fcrich",
    "wof:name":"Landi Elsau",
    "wof:placetype":"venue"
},
  "geometry": {"coordinates":[8.7974224091,47.4980163574],"type":"Point"}
}