{
  "type": "Feature",
  "properties": {
    "iso:country":"CH",
    "sg:address":"3979",
    "sg:city":"Gr\u00f4ne",
    "sg:orig_category":"Landesverteidigung, Sozialversicherung \u00d6ffentliche Verwaltung",
    "sg:phone":"+41 27 458 18 54",
    "sg:postcode":"3979",
    "sg:province":"Valais",
    "wof:name":"Centre De Protection Civile",
    "wof:placetype":"venue"
},
  "geometry": {"coordinates":[7.4571409225,46.2511062622],"type":"Point"}
}