{
  "type": "Feature",
  "properties": {
    "iso:country":"CH",
    "sg:address":"Avenue De Rossfeld 24",
    "sg:city":"Sierre",
    "sg:orig_category":"Politische Parteien SP",
    "sg:phone":"+41 27 455 87 19",
    "sg:postcode":"3960",
    "sg:province":"Valais",
    "wof:name":"Parti Socialiste De Sierre",
    "wof:placetype":"venue"
},
  "geometry": {"coordinates":[7.5193247795,46.2851753235],"type":"Point"}
}