{
  "type": "Feature",
  "properties": {
    "iso:country":"CH",
    "sg:address":"Alfred-cortot Avenue 7d",
    "sg:city":"Nyon",
    "sg:orig_category":"Werbung",
    "sg:postcode":"1260",
    "sg:province":"Vaud",
    "wof:name":"Sama Sa Sports Advertising Management Agency",
    "wof:placetype":"venue"
},
  "geometry": {"coordinates":[6.2316851616,46.3849372864],"type":"Point"}
}