{
  "type": "Feature",
  "properties": {
    "iso:country":"CH",
    "sg:address":"Schmitterstrasse 57",
    "sg:city":"Diepoldsau",
    "sg:orig_category":"Grosshandel mit Eisenwaren sowie Installationsbedarf f\u00fcr Gas, Wasser U Heizung Herstellung von Heizk",
    "sg:phone":"+41 17442929",
    "sg:postcode":"9444",
    "sg:province":"St. Gallen",
    "wof:name":"Vaillant Gmbh",
    "wof:placetype":"venue"
},
  "geometry": {"coordinates":[8.3944854736,47.4198493958],"type":"Point"}
}