{
  "type": "Feature",
  "properties": {
    "iso:country":"CH",
    "sg:address":"Henri Dunant-strasse 31",
    "sg:city":"Biel/bienne",
    "sg:orig_category":"Sportvereine Turnen",
    "sg:phone":"+41 31 701 00 80",
    "sg:postcode":"2504",
    "sg:province":"Bern",
    "wof:name":"Turnverein Stv Biglen",
    "wof:placetype":"venue"
},
  "geometry": {"coordinates":[7.6671600342,46.9350700378],"type":"Point"}
}