{
  "type": "Feature",
  "properties": {
    "iso:country":"CH",
    "sg:address":"Industriestrasse 1 8117 F\u00e4llanden. Postfach",
    "sg:city":"F\u00e4llanden",
    "sg:orig_category":"Herstellung von sonstigen Holzwaren",
    "sg:phone":"+41 12421015",
    "sg:postcode":"8117",
    "sg:province":"Z\u00fcrich",
    "wof:name":"Bucher Oliver Ag",
    "wof:placetype":"venue"
},
  "geometry": {"coordinates":[8.5796537399,47.3184738159],"type":"Point"}
}