{
  "type": "Feature",
  "properties": {
    "iso:country":"CH",
    "sg:address":"S\u00e4gematt 3",
    "sg:city":"Biglen",
    "sg:orig_category":"Gem\u00fcsebau Herstellung von Nahrungsmitteln undGetr\u00e4nken",
    "sg:phone":"+41 31 701 20 35",
    "sg:postcode":"3507",
    "sg:province":"Bern",
    "wof:name":"Hedwig Iseli Champignonkulturen",
    "wof:placetype":"venue"
},
  "geometry": {"coordinates":[7.6206507683,46.928062439],"type":"Point"}
}