{
  "type": "Feature",
  "properties": {
    "addr:full":"Station D'enrobage Sorens Fribourg 1642",
    "addr:postcode":"sorens;1642",
    "iso:country":"CH",
    "sg:address":"Station D'enrobage",
    "sg:city":"Sorens",
    "sg:orig_category":"Aktivit\u00e4ten der Generalunternehmen im Baugewerbe Allgemeiner Hochbau",
    "sg:phone":"+41 26 913 12 55",
    "sg:postcode":"1642",
    "sg:province":"Fribourg",
    "wof:name":"Grisoni-zaugg Sa",
    "wof:placetype":"venue"
},
  "geometry": {"coordinates":[7.060474,46.621899],"type":"Point"}
}