{
  "type": "Feature",
  "properties": {
    "iso:country":"CH",
    "sg:address":"Industriestrasse 1",
    "sg:city":"Olten",
    "sg:orig_category":"Druck ohne Zeitungsdruck",
    "sg:phone":"+41 62 296 69 75",
    "sg:postcode":"4600",
    "sg:province":"Solothurn",
    "wof:name":"Offsetdruck Keller",
    "wof:placetype":"venue"
},
  "geometry": {"coordinates":[7.9083762169,47.3583450317],"type":"Point"}
}