{
  "type": "Feature",
  "properties": {
    "iso:country":"CH",
    "sg:address":"R\u00f6ssligasse 2",
    "sg:city":"Niederlenz",
    "sg:orig_category":"RESTAURANTS: TEA-ROOMS",
    "sg:phone":"+41 62 891 29 16",
    "sg:postcode":"5702",
    "sg:province":"Aargau",
    "wof:name":"Rodel Hans-j\u00fcrg",
    "wof:placetype":"venue"
},
  "geometry": {"coordinates":[8.1768503189,47.4011726379],"type":"Point"}
}