{
  "type": "Feature",
  "properties": {
    "iso:country":"CH",
    "sg:address":"Zentralstrasse 10/12",
    "sg:city":"Ebikon",
    "sg:orig_category":"Herstellung von Spielwaren",
    "sg:phone":"+41 41 440 02 29",
    "sg:postcode":"6030",
    "sg:province":"Luzern",
    "wof:name":"Anton Gantner Tony-spiel",
    "wof:placetype":"venue"
},
  "geometry": {"coordinates":[8.3386116028,47.0798568726],"type":"Point"}
}