{
  "type": "Feature",
  "properties": {
    "iso:country":"CH",
    "sg:address":"Burgstrasse 32",
    "sg:city":"Meilen",
    "sg:orig_category":"Unclassifiable Establishments",
    "sg:phone":"+41 31 301 25 15",
    "sg:postcode":"8706",
    "sg:province":"Z\u00fcrich",
    "wof:name":"Damenturnverein Stv Bremgarten",
    "wof:placetype":"venue"
},
  "geometry": {"coordinates":[7.4388170242,46.977268219],"type":"Point"}
}