{
  "type": "Feature",
  "properties": {
    "iso:country":"CH",
    "sg:address":"Courfaivre Route De",
    "sg:city":"Soulce",
    "sg:orig_category":"Grosshandel mit elektrischen Haushaltsger\u00e4ten, Radio U Fernsehger\u00e4ten",
    "sg:postcode":"2864",
    "sg:province":"Jura",
    "wof:name":"T\u00e9l\u00e9commandes Service S\u00e0rl",
    "wof:placetype":"venue"
},
  "geometry": {"coordinates":[7.2649998665,47.3058395386],"type":"Point"}
}