{
  "type": "Feature",
  "properties": {
    "iso:country":"CH",
    "sg:address":"Baselstrasse 75",
    "sg:city":"Grellingen",
    "sg:classifiers":[
        {
            "category":"Sports & Exercise",
            "subcategory":"Tennis Court",
            "type":"Entertainment"
        }
    ],
    "sg:phone":"+41 79 669 41 21",
    "sg:postcode":"4203",
    "sg:province":"Basel-Landschaft",
    "sg:tags":[
        "squash-centers",
        "hallen",
        "tennis-"
    ],
    "wof:name":"Top-ten-tennis",
    "wof:placetype":"venue"
},
  "geometry": {"coordinates":[7.5980610847,47.4434432983],"type":"Point"}
}