{
  "type": "Feature",
  "properties": {
    "iso:country":"CH",
    "sg:address":"Rue St-jean 11",
    "sg:city":"Nyon",
    "sg:orig_category":"Pensionskassen",
    "sg:postcode":"1260",
    "sg:province":"Vaud",
    "wof:name":"Fonds De Pr\u00e9voyance De La Caisse D'epargne De Nyon",
    "wof:placetype":"venue"
},
  "geometry": {"coordinates":[6.2392320633,46.3831367493],"type":"Point"}
}