{
  "type": "Feature",
  "properties": {
    "iso:country":"CH",
    "sg:address":"St\u00f6ckliweg 15",
    "sg:city":"Thun",
    "sg:orig_category":"Solarien",
    "sg:phone":"+41 33 336 11 31",
    "sg:postcode":"3604",
    "sg:province":"Bern",
    "wof:name":"Mario Rohrer Solarium Beauty-line",
    "wof:placetype":"venue"
},
  "geometry": {"coordinates":[7.6273522377,46.7392997742],"type":"Point"}
}