{
  "type": "Feature",
  "properties": {
    "iso:country":"CH",
    "sg:address":"Eigentalstrasse 7 8309 N\u00fcrensdorf. Postfach",
    "sg:city":"N\u00fcrensdorf",
    "sg:orig_category":"Non-Classified Establishments",
    "sg:postcode":"8309",
    "sg:province":"Z\u00fcrich",
    "wof:name":"Weber & Obrist Dienstleistungen Im Kommunikationsbereich",
    "wof:placetype":"venue"
},
  "geometry": {"coordinates":[8.6455011368,47.4468383789],"type":"Point"}
}