{
  "type": "Feature",
  "properties": {
    "iso:country":"CH",
    "sg:address":"Rue De La C\u00f4te 109",
    "sg:city":"Neuch\u00e2tel",
    "sg:orig_category":"Architektur U Ingenieurb\u00fcros",
    "sg:phone":"+41 32 721 15 60",
    "sg:postcode":"2000",
    "sg:province":"Neuch\u00e2tel",
    "wof:name":"Micro-beam S\u00e0rl",
    "wof:placetype":"venue"
},
  "geometry": {"coordinates":[6.922557,46.993927],"type":"Point"}
}