{
  "type": "Feature",
  "properties": {
    "iso:country":"CH",
    "sg:address":"Under Neuhus 3",
    "sg:city":"Ruswil",
    "sg:orig_category":"Grosshandel mit B\u00fcromaschinen Grosshandel mit Datenverarbeitungsger\u00e4ten",
    "sg:phone":"+41 41 496 00 05",
    "sg:postcode":"6017",
    "sg:province":"Luzern",
    "wof:name":"Matter Data Computer Gmbh",
    "wof:placetype":"venue"
},
  "geometry": {"coordinates":[8.1145648956,47.0873565674],"type":"Point"}
}