{
  "type": "Feature",
  "properties": {
    "iso:country":"CH",
    "sg:address":"Schlattberg",
    "sg:city":"Luchsingen",
    "sg:orig_category":"Interessenvertretungen",
    "sg:phone":"+41 55 643 28 50",
    "sg:postcode":"8775",
    "sg:province":"Glarus",
    "wof:name":"Genossenschaft Schlattberg",
    "wof:placetype":"venue"
},
  "geometry": {"coordinates":[9.0271606445,46.9649658203],"type":"Point"}
}