{
  "type": "Feature",
  "properties": {
    "iso:country":"CH",
    "sg:address":"Meirwis",
    "sg:city":"Greifensee",
    "sg:orig_category":"Chemische Reinigung",
    "sg:phone":"+41 19404559",
    "sg:postcode":"8606",
    "sg:province":"Z\u00fcrich",
    "wof:name":"Josef Steiner Chemische Reinigung Tip Top",
    "wof:placetype":"venue"
},
  "geometry": {"coordinates":[8.677499,47.369228],"type":"Point"}
}