{
  "type": "Feature",
  "properties": {
    "iso:country":"CH",
    "sg:address":"Rue Du Chasseron 2",
    "sg:city":"Yverdon-les-bains",
    "sg:orig_category":"Stukkateurgewerbe, Gipserei U Verputzerei",
    "sg:phone":"+41 24 425 17 36",
    "sg:postcode":"1400",
    "sg:province":"Vaud",
    "wof:name":"Apoth\u00e9loz Fernand",
    "wof:placetype":"venue"
},
  "geometry": {"coordinates":[6.6307420731,46.7792434692],"type":"Point"}
}