{
  "type": "Feature",
  "properties": {
    "iso:country":"CH",
    "sg:address":"B\u00fcrglistrasse 18",
    "sg:city":"Wallisellen",
    "sg:orig_category":"Handelsvermittlung U Grosshandel Sonstiger Grosshandel",
    "sg:phone":"+41 18305905",
    "sg:postcode":"8304",
    "sg:province":"Z\u00fcrich",
    "wof:name":"Outdoors Direct Ag",
    "wof:placetype":"venue"
},
  "geometry": {"coordinates":[8.5979204178,47.4153327942],"type":"Point"}
}