{
  "type": "Feature",
  "properties": {
    "iso:country":"CH",
    "sg:address":"Hochhaus",
    "sg:city":"Sarnen",
    "sg:classifiers":[
        {
            "category":"Building & Trades",
            "subcategory":"Construction",
            "type":"Services"
        }
    ],
    "sg:phone":"+41 41 666 32 32",
    "sg:postcode":"6060",
    "sg:province":"Obwalden",
    "sg:tags":[
        "insulating",
        "material",
        "engineering"
    ],
    "wof:name":"Sarna-granol Ag",
    "wof:placetype":"venue"
},
  "geometry": {"coordinates":[8.246049881,46.9038887024],"type":"Point"}
}