{
  "type": "Feature",
  "properties": {
    "iso:country":"CH",
    "sg:address":"Rue Du Village 57",
    "sg:city":"Chardonne",
    "sg:orig_category":"Erdbewegungsarbeiten G\u00fcterbef\u00f6rderung im Strassenverkehr",
    "sg:phone":"+41 21 922 69 59",
    "sg:postcode":"1803",
    "sg:province":"Vaud",
    "wof:name":"Grandchamp Services Sa",
    "wof:placetype":"venue"
},
  "geometry": {"coordinates":[6.8258800507,46.4763450623],"type":"Point"}
}