{
  "type": "Feature",
  "properties": {
    "iso:country":"CH",
    "sg:address":"Avenue Henri-dunant 11",
    "sg:city":"Gen\u00e8ve",
    "sg:classifiers":[
        {
            "category":"Restaurant",
            "type":"Food & Drink"
        }
    ],
    "sg:phone":"+41 22 329 09 98",
    "sg:postcode":"1205",
    "sg:province":"Gen\u00e8ve",
    "wof:name":"Caf\u00e9 Petit Vaudois Sa",
    "wof:placetype":"venue"
},
  "geometry": {"coordinates":[6.1421451569,46.1964111328],"type":"Point"}
}