{
  "type": "Feature",
  "properties": {
    "iso:country":"CH",
    "sg:address":"Via Gemmo 5b",
    "sg:city":"Sorengo",
    "sg:orig_category":"Politische Vereinigungen",
    "sg:phone":"+41 71 288 60 29",
    "sg:postcode":"6924",
    "sg:province":"Ticino",
    "wof:name":"Pfg Politische Frauengruppe",
    "wof:placetype":"venue"
},
  "geometry": {"coordinates":[9.4123220444,47.4432067871],"type":"Point"}
}