{
  "type": "Feature",
  "properties": {
    "addr:full":"Chemin Du Pertuis-du-sault 18 Neuch\u00e2tel Neuch\u00e2tel 2000",
    "addr:housenumber":"18",
    "addr:postcode":"2000",
    "addr:street":"Chemin Du Pertuis-Du-Sault",
    "iso:country":"CH",
    "sg:address":"Chemin Du Pertuis-du-sault 18",
    "sg:city":"Neuch\u00e2tel",
    "sg:classifiers":[
        {
            "category":"Social Services",
            "subcategory":"Retirement Home",
            "type":"Services"
        }
    ],
    "sg:phone":"+41 32 725 47 96",
    "sg:postcode":"2000",
    "sg:province":"Neuch\u00e2tel",
    "sg:tags":[
        "pflegeheime",
        "u",
        "alters"
    ],
    "wof:name":"Home De L'ermitage Pour Personnes \u00e2g\u00e9es",
    "wof:placetype":"venue"
},
  "geometry": {"coordinates":[6.932111,46.998283],"type":"Point"}
}