{
  "type": "Feature",
  "properties": {
    "iso:country":"CH",
    "sg:address":"Route De Base 50 1228 Plan-les-ouates. Postfach",
    "sg:city":"Plan-les-ouates",
    "sg:orig_category":"G\u00fcterbef\u00f6rderung im Strassenverkehr",
    "sg:phone":"+41 22 794 68 67",
    "sg:postcode":"1228",
    "sg:province":"Gen\u00e8ve",
    "wof:name":"Agema Sa Transports",
    "wof:placetype":"venue"
},
  "geometry": {"coordinates":[6.1058931351,46.170375824],"type":"Point"}
}