{
  "type": "Feature",
  "properties": {
    "iso:country":"CH",
    "sg:address":"Grossbachstrasse 1",
    "sg:city":"Gross",
    "sg:orig_category":"Sanit\u00e4r U Heizungsinstallation Sanit\u00e4rinstallation",
    "sg:phone":"+41 55 412 25 51",
    "sg:postcode":"8841",
    "sg:province":"Schwyz",
    "wof:name":"Louis K\u00e4lin Sanit\u00e4r & Heizungen",
    "wof:placetype":"venue"
},
  "geometry": {"coordinates":[8.7783718109,47.1123123169],"type":"Point"}
}