{
  "type": "Feature",
  "properties": {
    "addr:full":"Altikerstrasse 12 Niederneunforn Thurgau 8525",
    "addr:housenumber":"12",
    "addr:postcode":"8525",
    "addr:street":"Altikerstrasse;Thurgau",
    "iso:country":"CH",
    "sg:address":"Altikerstrasse 12",
    "sg:city":"Niederneunforn",
    "sg:orig_category":"Detailhandel mit Antiquit\u00e4ten",
    "sg:phone":"+41 71 223 25 37",
    "sg:postcode":"8525",
    "sg:province":"Thurgau",
    "wof:name":"Ren\u00e9 & Trudi Sch\u00e4rer Antiquit\u00e4ten",
    "wof:placetype":"venue"
},
  "geometry": {"coordinates":[9.364828,47.42667],"type":"Point"}
}