{
  "type": "Feature",
  "properties": {
    "iso:country":"CH",
    "sg:address":"Hochwachtstrasse 28",
    "sg:city":"St.gallen",
    "sg:orig_category":"Allgemeiner Hoch U Tiefbau Allgemeiner Hochbau",
    "sg:phone":"+41 71 277 17 09",
    "sg:postcode":"9000",
    "sg:province":"St. Gallen",
    "wof:name":"Campi Ag",
    "wof:placetype":"venue"
},
  "geometry": {"coordinates":[9.358623,47.412014],"type":"Point"}
}