{
  "type": "Feature",
  "properties": {
    "iso:country":"CH",
    "sg:address":"M\u00fchleweg 2-4 3360 Herzogenbuchsee. Postfach 144",
    "sg:city":"Herzogenbuchsee",
    "sg:orig_category":"Herstellung von sonstigen Nahrungsmitteln Mahl U Sch\u00e4lm\u00fchlen",
    "sg:phone":"+41 62 956 75 75",
    "sg:postcode":"3360",
    "sg:province":"Bern",
    "wof:name":"Haefliger Ag",
    "wof:placetype":"venue"
},
  "geometry": {"coordinates":[7.6998491287,47.187664032],"type":"Point"}
}