{
  "type": "Feature",
  "properties": {
    "iso:country":"CH",
    "sg:address":"Voa Principala 11",
    "sg:city":"Valbella",
    "sg:orig_category":"Versicherungen Hauptagenturen",
    "sg:phone":"+41 21 961 18 18",
    "sg:postcode":"7077",
    "sg:province":"Graubunden",
    "wof:name":"Genevoise Assurances Agce Principale De La Riviera",
    "wof:placetype":"venue"
},
  "geometry": {"coordinates":[6.9103112221,46.4337730408],"type":"Point"}
}