{
  "type": "Feature",
  "properties": {
    "iso:country":"CH",
    "sg:address":"Rue Achille-merguin 25",
    "sg:city":"Porrentruy",
    "sg:orig_category":"Pensionskassen",
    "sg:postcode":"2900",
    "sg:province":"Jura",
    "wof:name":"Fondation De Pr\u00e9voyance En Faveur Du Personnel De La Maison Joseph Bonvallat",
    "wof:placetype":"venue"
},
  "geometry": {"coordinates":[7.0717430115,47.4149475098],"type":"Point"}
}