{
  "type": "Feature",
  "properties": {
    "iso:country":"CH",
    "sg:address":"Bachmattstrasse 2",
    "sg:city":"Z\u00fcrich",
    "sg:orig_category":"Handelsvermittlung von Textilien, Bekleidung, Schuhen U Lederwaren",
    "sg:postcode":"8048",
    "sg:province":"Z\u00fcrich",
    "wof:name":"Mustis Travel Apaydin",
    "wof:placetype":"venue"
},
  "geometry": {"coordinates":[8.4849910736,47.3916130066],"type":"Point"}
}