{
  "type": "Feature",
  "properties": {
    "iso:country":"CH",
    "sg:address":"Neuengasse 7",
    "sg:city":"Bern",
    "sg:orig_category":"Zahntechnische Laboratorien",
    "sg:phone":"+41 31 311 22 83",
    "sg:postcode":"3011",
    "sg:province":"Bern",
    "wof:name":"Walter Seiler Labor F\u00fcr Gebissreparaturen",
    "wof:placetype":"venue"
},
  "geometry": {"coordinates":[7.442969799,46.948841095],"type":"Point"}
}