{
  "type": "Feature",
  "properties": {
    "iso:country":"CH",
    "sg:address":"Route De Montoz 9 2735 B\u00e9vilard Case Postale 362",
    "sg:city":"B\u00e9vilard",
    "sg:orig_category":"Architektur U Ingenieurb\u00fcros Herstellung von Schrauben, Nieten, Ketten U Federn",
    "sg:phone":"+41 32 492 10 12",
    "sg:postcode":"2735",
    "sg:province":"Bern",
    "wof:name":"Helios A. Charpilloz Sa",
    "wof:placetype":"venue"
},
  "geometry": {"coordinates":[7.283745,47.235405],"type":"Point"}
}