{
  "type": "Feature",
  "properties": {
    "iso:country":"CH",
    "sg:address":"Austrasse 3",
    "sg:city":"Ebnat",
    "sg:orig_category":"Sportvereine Turnen Vereine Damen",
    "sg:phone":"+41 71 993 25 29",
    "sg:postcode":"9642",
    "sg:province":"St. Gallen",
    "wof:name":"Frauenturnver.stv Ebnat-kappel",
    "wof:placetype":"venue"
},
  "geometry": {"coordinates":[9.1148777008,47.271030426],"type":"Point"}
}