{
  "type": "Feature",
  "properties": {
    "iso:country":"CH",
    "sg:address":"H\u00f6nggerstrasse 115 8037 Z\u00fcrich. Postfach",
    "sg:city":"Z\u00fcrich",
    "sg:orig_category":"RESTAURANTS: TEA-ROOMS",
    "sg:postcode":"8037",
    "sg:province":"Z\u00fcrich",
    "wof:name":"Restaurants Terrasse Sa",
    "wof:placetype":"venue"
},
  "geometry": {"coordinates":[8.5190238953,47.3952102661],"type":"Point"}
}