{
  "type": "Feature",
  "properties": {
    "iso:country":"CH",
    "sg:address":"Residenza Ai Platani 4",
    "sg:city":"Vezia",
    "sg:orig_category":"Arztpraxen",
    "sg:phone":"+41 91 960 17 60",
    "sg:postcode":"6943",
    "sg:province":"Ticino",
    "wof:name":"Dott.med.franco Muggli Specialista Fmh",
    "wof:placetype":"venue"
},
  "geometry": {"coordinates":[8.935845,46.030331],"type":"Point"}
}