{
  "type": "Feature",
  "properties": {
    "iso:country":"CH",
    "sg:address":"H\u00f6rnlistrasse 15",
    "sg:city":"D\u00fcbendorf",
    "sg:orig_category":"Herstellung von Transportbeton",
    "sg:phone":"+41 18823900",
    "sg:postcode":"8600",
    "sg:province":"Z\u00fcrich",
    "wof:name":"Betonwerk B\u00fcrkle Gmbh",
    "wof:placetype":"venue"
},
  "geometry": {"coordinates":[8.6327648163,47.3949356079],"type":"Point"}
}