{
  "type": "Feature",
  "properties": {
    "iso:country":"CH",
    "sg:address":"Rebmattli 22",
    "sg:city":"Baar",
    "sg:orig_category":"Unclassifiable Establishments",
    "sg:phone":"+41 41 763 23 80",
    "sg:postcode":"6340",
    "sg:province":"Zug",
    "wof:name":"Kentia Holding Ag",
    "wof:placetype":"venue"
},
  "geometry": {"coordinates":[8.5147686005,47.2040863037],"type":"Point"}
}