{
  "type": "Feature",
  "properties": {
    "iso:country":"CH",
    "sg:address":"Otzenbach 163",
    "sg:city":"Riggisberg",
    "sg:orig_category":"Vereine Frauen Vereine Gemeinn\u00fctzige",
    "sg:postcode":"3132",
    "sg:province":"Bern",
    "wof:name":"Coop Frauenbund Riggisberg",
    "wof:placetype":"venue"
},
  "geometry": {"coordinates":[7.4624009132,46.814365387],"type":"Point"}
}