{
  "type": "Feature",
  "properties": {
    "iso:country":"CH",
    "sg:address":"Walthersburgstrasse 3",
    "sg:city":"Aarau",
    "sg:classifiers":[
        {
            "category":"Social Services",
            "subcategory":"Retirement Home",
            "type":"Services"
        }
    ],
    "sg:phone":"+41 41 632 81 81",
    "sg:postcode":"5000",
    "sg:province":"Aargau",
    "sg:tags":[
        "pflegeheime",
        "u",
        "alters"
    ],
    "wof:name":"Seniorenzentrum Zwyden",
    "wof:placetype":"venue"
},
  "geometry": {"coordinates":[8.309961,46.987846],"type":"Point"}
}