{
  "type": "Feature",
  "properties": {
    "iso:country":"CH",
    "sg:address":"Grossm\u00fcnsterplatz 6",
    "sg:city":"Z\u00fcrich",
    "sg:orig_category":"Detailhandel mit Uhren U Schmuck Fachdetailhandel in Verkaufsr\u00e4umen",
    "sg:phone":"+41 12521821",
    "sg:postcode":"8000",
    "sg:province":"Z\u00fcrich",
    "wof:name":"Jucker Fritz",
    "wof:placetype":"venue"
},
  "geometry": {"coordinates":[8.5442056656,47.3696975708],"type":"Point"}
}