{
  "type": "Feature",
  "properties": {
    "iso:country":"CH",
    "sg:address":"Talackerstrasse 29",
    "sg:city":"Glattbrugg",
    "sg:orig_category":"Markt U Meinungsforschung",
    "sg:phone":"+41 18110786",
    "sg:postcode":"8152",
    "sg:province":"Z\u00fcrich",
    "wof:name":"Cuenca Juan Lic.rer.pol. Marketingberatung",
    "wof:placetype":"venue"
},
  "geometry": {"coordinates":[8.5609855652,47.4261283875],"type":"Point"}
}