{
  "type": "Feature",
  "properties": {
    "iso:country":"CH",
    "sg:address":"Rebbergstrasse 48",
    "sg:city":"Ennetbaden",
    "sg:orig_category":"Politische Parteien CVP",
    "sg:phone":"+41 56 222 97 97",
    "sg:postcode":"5408",
    "sg:province":"Aargau",
    "wof:name":"Cvp Ortspartei Ennetbaden",
    "wof:placetype":"venue"
},
  "geometry": {"coordinates":[8.3214550018,47.4821510315],"type":"Point"}
}