{
  "type": "Feature",
  "properties": {
    "addr:full":"S\u00e4listrasse 3 Oftringen Aargau 4665",
    "addr:housenumber":"3",
    "addr:postcode":"4665",
    "addr:street":"Saelistrasse",
    "iso:country":"CH",
    "sg:address":"S\u00e4listrasse 3",
    "sg:city":"Oftringen",
    "sg:orig_category":"Arbeitnehmerverb\u00e4nde",
    "sg:phone":"+41 62 797 68 84",
    "sg:postcode":"4665",
    "sg:province":"Aargau",
    "wof:name":"Metzgerei-personalverb.der Schweiz,herrn Rudolf Meister",
    "wof:placetype":"venue"
},
  "geometry": {"coordinates":[7.917807,47.315918],"type":"Point"}
}