{
  "type": "Feature",
  "properties": {
    "iso:country":"CH",
    "sg:address":"Bielstrasse 18",
    "sg:city":"Solothurn",
    "sg:orig_category":"Saunas, Solarien, Fitnesszentren U \u00e4hnliches",
    "sg:postcode":"4500",
    "sg:province":"Solothurn",
    "wof:name":"R Solar Gmbh",
    "wof:placetype":"venue"
},
  "geometry": {"coordinates":[7.5319519043,47.209148407],"type":"Point"}
}