{
  "type": "Feature",
  "properties": {
    "iso:country":"CH",
    "sg:address":"6500 Bellinzona. Postfach Caselle Postale 697",
    "sg:city":"Bellinzona",
    "sg:orig_category":"Sportvereine Ballsport Tennis",
    "sg:phone":"+41 32 841 24 37",
    "sg:postcode":"6501",
    "sg:province":"Ticino",
    "wof:name":"Tennis-club Colombier",
    "wof:placetype":"venue"
},
  "geometry": {"coordinates":[6.8714780807,46.962436676],"type":"Point"}
}