{
  "type": "Feature",
  "properties": {
    "iso:country":"CH",
    "sg:address":"Schulstrasse 24",
    "sg:city":"Zufikon",
    "sg:orig_category":"Maschinen-Fabrikation",
    "sg:phone":"+41 56 641 05 05",
    "sg:postcode":"5621",
    "sg:province":"Aargau",
    "wof:name":"Hrs Engineering Gmbh",
    "wof:placetype":"venue"
},
  "geometry": {"coordinates":[8.358959198,47.3466072083],"type":"Point"}
}