{
  "type": "Feature",
  "properties": {
    "iso:country":"CH",
    "sg:address":"Quai De La Sorne 5",
    "sg:city":"Del\u00e9mont",
    "sg:orig_category":"Fotografische Ateliers Fotografisches Gewerbe U fotografische Laboratorien",
    "sg:phone":"+41 18504982",
    "sg:postcode":"2800",
    "sg:province":"Jura",
    "wof:name":"Antonio Ferraro Fotografisches Atelier",
    "wof:placetype":"venue"
},
  "geometry": {"coordinates":[8.5112161636,47.4710884094],"type":"Point"}
}