{
  "type": "Feature",
  "properties": {
    "iso:country":"CH",
    "sg:address":"Niesenweg 9",
    "sg:city":"M\u00fcnsingen",
    "sg:orig_category":"Detailhandel mit Bekleidung",
    "sg:phone":"+41 31 721 70 10",
    "sg:postcode":"3110",
    "sg:province":"Bern",
    "wof:name":"Schnyder's Jeans & Tops",
    "wof:placetype":"venue"
},
  "geometry": {"coordinates":[7.555985,46.872192],"type":"Point"}
}