{
  "type": "Feature",
  "properties": {
    "iso:country":"CH",
    "sg:address":"Althardstrasse 80 8105 Regensdorf. Postfach",
    "sg:city":"Regensdorf",
    "sg:orig_category":"Unclassifiable Establishments",
    "sg:postcode":"8105",
    "sg:province":"Z\u00fcrich",
    "wof:name":"Addon (schweiz) Ag",
    "wof:placetype":"venue"
},
  "geometry": {"coordinates":[8.4700708389,47.438495636],"type":"Point"}
}