{
  "type": "Feature",
  "properties": {
    "iso:country":"CH",
    "sg:address":"S\u00e4gereistrasse 7",
    "sg:city":"Neuhausen",
    "sg:orig_category":"Sanit\u00e4r U Heizungsinstallation",
    "sg:phone":"+41 52 672 20 26",
    "sg:postcode":"8212",
    "sg:province":"Schaffhausen",
    "wof:name":"Armin Reutimann Heizungen",
    "wof:placetype":"venue"
},
  "geometry": {"coordinates":[8.6151313782,47.6839065552],"type":"Point"}
}