{
  "type": "Feature",
  "properties": {
    "iso:country":"CH",
    "sg:address":"Austrasse 60",
    "sg:city":"Z\u00fcrich",
    "sg:orig_category":"Baugewerbe Herstellung von Hebezeugen U F\u00f6rdermitteln",
    "sg:phone":"+41 79 236 29 66",
    "sg:postcode":"8045",
    "sg:province":"Z\u00fcrich",
    "wof:name":"Delphin Cakmak Y.",
    "wof:placetype":"venue"
},
  "geometry": {"coordinates":[8.520039,47.364014],"type":"Point"}
}