{
  "type": "Feature",
  "properties": {
    "addr:full":"Gartenmatt 3 B\u00fclach Z\u00fcrich 8180",
    "addr:housenumber":"3",
    "addr:postcode":"8180",
    "addr:street":"Gartenmatt;Zuerich",
    "iso:country":"CH",
    "sg:address":"Gartenmatt 3",
    "sg:city":"B\u00fclach",
    "sg:classifiers":[
        {
            "category":"Restaurant",
            "type":"Food & Drink"
        }
    ],
    "sg:phone":"+41 18621662",
    "sg:postcode":"8180",
    "sg:province":"Z\u00fcrich",
    "sg:tags":[
        "restaurants",
        "tea-rooms",
        "caterer"
    ],
    "wof:name":"Take Away Pizza Express Arlecchino N.cappello",
    "wof:placetype":"venue"
},
  "geometry": {"coordinates":[8.542936,47.518341],"type":"Point"}
}