{
  "type": "Feature",
  "properties": {
    "iso:country":"CH",
    "sg:address":"Allmendweg 61",
    "sg:city":"Laufen",
    "sg:orig_category":"Datenverarbeitungsdienste Hardwareberatung",
    "sg:phone":"+41 71 230 08 51",
    "sg:postcode":"4242",
    "sg:province":"Basel-Landschaft",
    "wof:name":"Netlink Ag Edv-netzwerk Beratungen",
    "wof:placetype":"venue"
},
  "geometry": {"coordinates":[9.370527,47.42223],"type":"Point"}
}