{
  "type": "Feature",
  "properties": {
    "iso:country":"CH",
    "sg:address":"R\u00f6ntgenstrasse 22 8005 Z\u00fcrich. Postfach 7529",
    "sg:city":"Z\u00fcrich",
    "sg:orig_category":"Handelsvermittlung U Grosshandel",
    "sg:phone":"+41 12727870",
    "sg:postcode":"8023",
    "sg:province":"Z\u00fcrich",
    "wof:name":"Bosshard & Co Ag",
    "wof:placetype":"venue"
},
  "geometry": {"coordinates":[8.5276889801,47.3834877014],"type":"Point"}
}