{
  "type": "Feature",
  "properties": {
    "iso:country":"CH",
    "sg:address":"Rickstrasse 37",
    "sg:city":"Speicherschwendi",
    "sg:orig_category":"Architekturb\u00fcros",
    "sg:phone":"+41 71 344 49 55",
    "sg:postcode":"9037",
    "sg:province":"Appenzell Ausserrhoden",
    "wof:name":"Ronald Hofer Architekturb\u00fcro",
    "wof:placetype":"venue"
},
  "geometry": {"coordinates":[9.446176,47.424892],"type":"Point"}
}