{
  "type": "Feature",
  "properties": {
    "iso:country":"CH",
    "sg:address":"Mattenweg 14",
    "sg:city":"Giswil",
    "sg:orig_category":"Malerei",
    "sg:phone":"+41 41 675 16 30",
    "sg:postcode":"6074",
    "sg:province":"Obwalden",
    "wof:name":"Robert Halter Malergesch\u00e4ft",
    "wof:placetype":"venue"
},
  "geometry": {"coordinates":[8.1863174438,46.8405723572],"type":"Point"}
}