{
  "type": "Feature",
  "properties": {
    "iso:country":"CH",
    "sg:address":"Dorni 261g",
    "sg:city":"Walkringen",
    "sg:orig_category":"Softwareentwicklung U beratung",
    "sg:phone":"+41 31 702 00 51",
    "sg:postcode":"3512",
    "sg:province":"Bern",
    "wof:name":"Evergreen Informatic Service Gmbh",
    "wof:placetype":"venue"
},
  "geometry": {"coordinates":[7.6116700172,46.9461593628],"type":"Point"}
}