{
  "type": "Feature",
  "properties": {
    "iso:country":"CH",
    "sg:address":"Mattenstrasse 11 3073 G\u00fcmligen. Postfach 176",
    "sg:city":"G\u00fcmligen",
    "sg:orig_category":"Mit dem Versicherungsgewerbe verbundene T\u00e4tigkeiten Versicherungsgewerbe",
    "sg:phone":"+41 31 959 35 35",
    "sg:postcode":"3073",
    "sg:province":"Bern",
    "wof:name":"Krachpelz Ag Assekuranz Beratungen",
    "wof:placetype":"venue"
},
  "geometry": {"coordinates":[7.5105957985,46.9334335327],"type":"Point"}
}