{
  "type": "Feature",
  "properties": {
    "iso:country":"CH",
    "sg:address":"Z\u00fcrcherstrasse 132",
    "sg:city":"Frauenfeld",
    "sg:orig_category":"Reiseb\u00fcros U Reiseveranstalter",
    "sg:phone":"+41 52 721 41 10",
    "sg:postcode":"8500",
    "sg:province":"Thurgau",
    "wof:name":"Sharr Express Zekiri",
    "wof:placetype":"venue"
},
  "geometry": {"coordinates":[8.8946504593,47.554069519],"type":"Point"}
}