{
  "type": "Feature",
  "properties": {
    "iso:country":"CH",
    "sg:address":"Avenue Ch\u00e2teau De La Cour 13",
    "sg:city":"Sierre",
    "sg:orig_category":"Non-Classified Establishments",
    "sg:postcode":"3960",
    "sg:province":"Valais",
    "wof:name":"Jean-yves Epiney",
    "wof:placetype":"venue"
},
  "geometry": {"coordinates":[7.5327858925,46.2947731018],"type":"Point"}
}