{
  "type": "Feature",
  "properties": {
    "iso:country":"CH",
    "sg:address":"Chemin De La Ch\u00e8vre 6 Zi Les",
    "sg:city":"Yverdon-les-bains",
    "sg:orig_category":"Grosshandel mit Getreide, Saatgut U Futtermitteln",
    "sg:phone":"+41 24 447 84 84",
    "sg:postcode":"1400",
    "sg:province":"Vaud",
    "wof:name":"Aubry Materiel Sa",
    "wof:placetype":"venue"
},
  "geometry": {"coordinates":[6.6414198875,46.7786331177],"type":"Point"}
}