{
  "type": "Feature",
  "properties": {
    "iso:country":"CH",
    "sg:address":"Hauptstrasse 38",
    "sg:city":"Ipsach",
    "sg:orig_category":"Fachdetailhandel in Verkaufsr\u00e4umen",
    "sg:postcode":"2563",
    "sg:province":"Bern",
    "wof:name":"Stettler J\u00f6rg",
    "wof:placetype":"venue"
},
  "geometry": {"coordinates":[7.2310009003,47.1135101318],"type":"Point"}
}