{
  "type": "Feature",
  "properties": {
    "iso:country":"CH",
    "sg:address":"Birrfeldstrasse 4b",
    "sg:city":"M\u00fclligen",
    "sg:orig_category":"Sportvereine Orientierungslauf",
    "sg:postcode":"5243",
    "sg:province":"Aargau",
    "wof:name":"Olg Cordoba Baden-brugg",
    "wof:placetype":"venue"
},
  "geometry": {"coordinates":[8.239235878,47.457195282],"type":"Point"}
}