{
  "type": "Feature",
  "properties": {
    "addr:full":"Freie Strasse 52 Basel Basel-Stadt 4001",
    "addr:housenumber":"52",
    "addr:postcode":"4001",
    "addr:street":"Freie Strasse",
    "iso:country":"CH",
    "sg:address":"Freie Strasse 52",
    "sg:city":"Basel",
    "sg:orig_category":"Bestattungswesen",
    "sg:phone":"+41 61 261 15 68",
    "sg:postcode":"4001",
    "sg:province":"Basel-Stadt",
    "wof:name":"Bestattungen Bieli Inh.beat Burkart",
    "wof:placetype":"venue"
},
  "geometry": {"coordinates":[7.59022,47.555695],"type":"Point"}
}