{
  "type": "Feature",
  "properties": {
    "iso:country":"CH",
    "sg:address":"Blochmonterstrasse 4",
    "sg:city":"Basel",
    "sg:orig_category":"Gesundheitswesen",
    "sg:phone":"+41 61 281 04 34",
    "sg:postcode":"4054",
    "sg:province":"Basel-Stadt",
    "wof:name":"Physiotherapie Zoomove Daniel F\u00f6ry Urs Herrmann",
    "wof:placetype":"venue"
},
  "geometry": {"coordinates":[7.5748081207,47.5473709106],"type":"Point"}
}