{
  "type": "Feature",
  "properties": {
    "addr:full":"Schl\u00f6sslipark Oberaach Thurgau 8587",
    "addr:postcode":"8587",
    "iso:country":"CH",
    "sg:address":"Schl\u00f6sslipark",
    "sg:city":"Oberaach",
    "sg:classifiers":[
        {
            "category":"Professional",
            "subcategory":"Engineering",
            "type":"Services"
        }
    ],
    "sg:phone":"+41 71 311 16 16",
    "sg:postcode":"8587",
    "sg:province":"Thurgau",
    "sg:tags":[
        "machine",
        "-",
        "mechanical"
    ],
    "wof:name":"Konvekta Ag",
    "wof:placetype":"venue"
},
  "geometry": {"coordinates":[9.296014,47.403381],"type":"Point"}
}