{
  "type": "Feature",
  "properties": {
    "iso:country":"CH",
    "sg:address":"Wigetshof",
    "sg:city":"Oberhelfenschwil",
    "sg:classifiers":[
        {
            "category":"Restaurant",
            "type":"Food & Drink"
        }
    ],
    "sg:phone":"+41 71 983 12 20",
    "sg:postcode":"9621",
    "sg:province":"St. Gallen",
    "wof:name":"Restaurant Storchen",
    "wof:placetype":"venue"
},
  "geometry": {"coordinates":[9.0923099518,47.3455696106],"type":"Point"}
}