{
  "type": "Feature",
  "properties": {
    "iso:country":"CH",
    "sg:address":"Waldestrasse 1",
    "sg:city":"R\u00fceterswil",
    "sg:orig_category":"Detailhandel mit Waren verschiedener Art, Hauptrichtung Nahrungsmittel",
    "sg:phone":"+41 55 284 16 68",
    "sg:postcode":"8735",
    "sg:province":"St. Gallen",
    "wof:name":"Josef Gisler",
    "wof:placetype":"venue"
},
  "geometry": {"coordinates":[8.9875459671,47.2594337463],"type":"Point"}
}