{
  "type": "Feature",
  "properties": {
    "iso:country":"CH",
    "sg:address":"Hauptstrasse 147 6182 Escholzmatt. Postfach 164",
    "sg:city":"Escholzmatt",
    "sg:orig_category":"Detailhandel mit Blumen U Pflanzen Gartenbau",
    "sg:phone":"+41 81 302 23 47",
    "sg:postcode":"6182",
    "sg:province":"Luzern",
    "wof:name":"Erwin Tester",
    "wof:placetype":"venue"
},
  "geometry": {"coordinates":[9.496011,47.00946],"type":"Point"}
}