{
  "type": "Feature",
  "properties": {
    "iso:country":"CH",
    "sg:address":"Wettsteinallee 14 4058 Basel. Postfach",
    "sg:city":"Basel",
    "sg:orig_category":"Fotografisches Gewerbe U fotografische Laboratorien",
    "sg:phone":"+41 81 833 35 38",
    "sg:postcode":"4058",
    "sg:province":"Basel-Stadt",
    "wof:name":"Fotoatelier Schmidt",
    "wof:placetype":"venue"
},
  "geometry": {"coordinates":[9.8373908997,46.485458374],"type":"Point"}
}