{
  "type": "Feature",
  "properties": {
    "iso:country":"CH",
    "sg:address":"Sch\u00fctzenstrasse 12",
    "sg:city":"Heimberg",
    "sg:orig_category":"Rolladen- and Storenmontage",
    "sg:phone":"+41 33 438 22 59",
    "sg:postcode":"3627",
    "sg:province":"Bern",
    "wof:name":"Maurer-storenservice",
    "wof:placetype":"venue"
},
  "geometry": {"coordinates":[7.6022148132,46.7930374146],"type":"Point"}
}