{
  "type": "Feature",
  "properties": {
    "iso:country":"CH",
    "sg:address":"G\u00e9n\u00e9ral-guisan Avenue 111 1009 Pully. Postfach",
    "sg:city":"Pully",
    "sg:orig_category":"Finanzierungsinstitutionen",
    "sg:postcode":"1009",
    "sg:province":"Vaud",
    "wof:name":"Sb Invest S\u00e0rl Investissements, Notamm. Dans Le Domaine De La Restauration Et De L'h\u00f4tellerie",
    "wof:placetype":"venue"
},
  "geometry": {"coordinates":[6.6456961632,46.5064811707],"type":"Point"}
}