{
  "type": "Feature",
  "properties": {
    "iso:country":"CH",
    "sg:address":"Kurhausstrasse 66 8032 Z\u00fcrich. Postfach",
    "sg:city":"Z\u00fcrich",
    "sg:orig_category":"Golfpl\u00e4tze Restaurants",
    "sg:phone":"+41 12615045",
    "sg:postcode":"8030",
    "wof:name":"Golf-club Dolder Z\u00fcrich",
    "wof:placetype":"venue"
},
  "geometry": {"coordinates":[8.5740222931,47.3722457886],"type":"Point"}
}