{
  "type": "Feature",
  "properties": {
    "iso:country":"CH",
    "sg:address":"Fischmarkt 15",
    "sg:city":"Zug",
    "sg:orig_category":"RESTAURANTS: TEA-ROOMS",
    "sg:phone":"+41 41 711 90 91",
    "sg:postcode":"6300",
    "sg:province":"Zug",
    "wof:name":"Restaurant Fischm\u00e4rt",
    "wof:placetype":"venue"
},
  "geometry": {"coordinates":[8.5149993896,47.1661643982],"type":"Point"}
}