{
  "type": "Feature",
  "properties": {
    "addr:full":"Glattalstrasse 520 R\u00fcmlang Z\u00fcrich 8153",
    "addr:housenumber":"520",
    "addr:postcode":"8153",
    "addr:street":"Glattalstrasse;Zuerich",
    "iso:country":"CH",
    "sg:address":"Glattalstrasse 520",
    "sg:city":"R\u00fcmlang",
    "sg:classifiers":[
        {
            "category":"Professional",
            "subcategory":"Accounting & Tax Preparation",
            "type":"Services"
        }
    ],
    "sg:phone":"+41 71 282 87 87",
    "sg:postcode":"8153",
    "sg:province":"Z\u00fcrich",
    "sg:tags":[
        "cardboard",
        "display"
    ],
    "wof:name":"K+d Ag Karton + Design",
    "wof:placetype":"venue"
},
  "geometry": {"coordinates":[9.419021,47.440125],"type":"Point"}
}