{
  "type": "Feature",
  "properties": {
    "iso:country":"CH",
    "sg:address":"B\u00fcndten 8",
    "sg:city":"K\u00e4nerkinden",
    "sg:orig_category":"Bauspenglerei Sanit\u00e4r, Heizungs U L\u00fcftungsinstallation",
    "sg:phone":"+41 62 299 55 44",
    "sg:postcode":"4447",
    "sg:province":"Basel-Landschaft",
    "wof:name":"Sanitec Biedert",
    "wof:placetype":"venue"
},
  "geometry": {"coordinates":[7.835686,47.412537],"type":"Point"}
}