{
  "type": "Feature",
  "properties": {
    "iso:country":"CH",
    "sg:address":"Marktgasse 20",
    "sg:city":"Biel/bienne",
    "sg:orig_category":"Detailhandel mit Bekleidung Detailhandel mit Damenbekleidung",
    "sg:phone":"+41 12611255",
    "sg:postcode":"2502",
    "sg:province":"Bern",
    "wof:name":"Vero Moda Retail Ag",
    "wof:placetype":"venue"
},
  "geometry": {"coordinates":[7.246808,47.139999],"type":"Point"}
}