{
  "type": "Feature",
  "properties": {
    "iso:country":"CH",
    "sg:address":"Lindenweg 7",
    "sg:city":"Humlikon",
    "sg:orig_category":"Allgemeiner Hoch U Tiefbau Hoch U Tiefbau",
    "sg:phone":"+41 79 659 61 69",
    "sg:postcode":"8457",
    "sg:province":"Z\u00fcrich",
    "wof:name":"Ruh Baugesch\u00e4ft",
    "wof:placetype":"venue"
},
  "geometry": {"coordinates":[8.672002,47.577011],"type":"Point"}
}