{
  "type": "Feature",
  "properties": {
    "iso:country":"CH",
    "sg:address":"6600 Muralto. Postfach Caselle Postale 75",
    "sg:city":"Muralto",
    "sg:orig_category":"Sportvereine Eissport Eishockey",
    "sg:postcode":"6600",
    "sg:province":"Ticino",
    "wof:name":"Hockey-club Giubiasco 92",
    "wof:placetype":"venue"
},
  "geometry": {"coordinates":[8.8009500504,46.1727714539],"type":"Point"}
}