{
  "type": "Feature",
  "properties": {
    "iso:country":"CH",
    "sg:address":"Unterm\u00fcli 7",
    "sg:city":"Zug",
    "sg:orig_category":"Grosshandel mit Textilien",
    "sg:phone":"+41 71 411 66 34",
    "sg:postcode":"6300",
    "sg:province":"Zug",
    "wof:name":"Texnit Ag",
    "wof:placetype":"venue"
},
  "geometry": {"coordinates":[8.9950037003,47.4833374023],"type":"Point"}
}