{
  "type": "Feature",
  "properties": {
    "iso:country":"CH",
    "sg:address":"Birkenstrasse 21",
    "sg:city":"Tuggen",
    "sg:orig_category":"Fahrschulen, Flugschulen",
    "sg:phone":"+41 79 200 14 55",
    "sg:postcode":"8856",
    "sg:province":"Schwyz",
    "wof:name":"Andreas Huber Autofahrschule",
    "wof:placetype":"venue"
},
  "geometry": {"coordinates":[8.947388649,47.2060966492],"type":"Point"}
}