{
  "type": "Feature",
  "properties": {
    "iso:country":"CH",
    "sg:address":"Bundesg. 35",
    "sg:city":"Bern",
    "sg:classifiers":[
        {
            "category":"Banks & Credit Unions",
            "subcategory":"Financial Services",
            "type":"Services"
        }
    ],
    "sg:phone":"+41 31 389 61 11",
    "sg:postcode":"3001",
    "sg:province":"Bern",
    "sg:tags":[
        "banking",
        "finance",
        "insurance"
    ],
    "wof:name":"Die Mobiliar",
    "wof:placetype":"venue"
},
  "geometry": {"coordinates":[7.44821,46.948021],"type":"Point"}
}