{
  "type": "Feature",
  "properties": {
    "iso:country":"CH",
    "sg:address":"Chesa Gaudenzi 7512 Champf\u00e8r. Postfach",
    "sg:city":"Champf\u00e8r",
    "sg:orig_category":"Architektur U Ingenieurb\u00fcros",
    "sg:phone":"+41 81 833 48 48",
    "sg:postcode":"7512",
    "sg:province":"Graubunden",
    "wof:name":"Fanzun Chr. & S\u00f6hne Ag, Diplomierte Ingenieure Und Architekten",
    "wof:placetype":"venue"
},
  "geometry": {"coordinates":[9.81107,46.478001],"type":"Point"}
}