{
  "type": "Feature",
  "properties": {
    "iso:country":"CH",
    "sg:address":"Weberg\u00e4sschen 5",
    "sg:city":"Riehen",
    "sg:orig_category":"Non-Classified Establishments",
    "sg:postcode":"4125",
    "sg:province":"Basel-Stadt",
    "wof:name":"Parf\u00fcmerie Am W\u00e4berg\u00e4ssli, Blatter",
    "wof:placetype":"venue"
},
  "geometry": {"coordinates":[7.6512107849,47.5849952698],"type":"Point"}
}