{
  "type": "Feature",
  "properties": {
    "iso:country":"CH",
    "sg:address":"Route Du Simplon 50",
    "sg:city":"Sierre",
    "sg:orig_category":"RESTAURANTS: TEA-ROOMS",
    "sg:phone":"+41 27 455 12 95",
    "sg:postcode":"3960",
    "sg:province":"Valais",
    "wof:name":"Caf\u00e9-restaurant Le Belv\u00e9d\u00e8re S\u00e0rl",
    "wof:placetype":"venue"
},
  "geometry": {"coordinates":[7.5433831215,46.296836853],"type":"Point"}
}