{
  "type": "Feature",
  "properties": {
    "iso:country":"CH",
    "sg:address":"Talstrasse 59",
    "sg:city":"Fl\u00fch",
    "sg:orig_category":"Zimmerei, Dachdeckerei, Bauspenglerei U Abdichtung Zimmerei, Ingenieurholzbau",
    "sg:phone":"+41 61 421 01 20",
    "sg:postcode":"4112",
    "sg:province":"Solothurn",
    "wof:name":"Werner Bettinger Holzbau & Bedachungen",
    "wof:placetype":"venue"
},
  "geometry": {"coordinates":[7.4996547699,47.482131958],"type":"Point"}
}