{
  "type": "Feature",
  "properties": {
    "iso:country":"CH",
    "sg:address":"Birkenweg 5",
    "sg:city":"Sch\u00f6ftland",
    "sg:classifiers":[
        {
            "category":"Social Services",
            "subcategory":"Retirement Home",
            "type":"Services"
        }
    ],
    "sg:phone":"+41 62 721 11 71",
    "sg:postcode":"5040",
    "sg:province":"Aargau",
    "sg:tags":[
        "pflegeheime",
        "u",
        "alters"
    ],
    "wof:name":"Altersheim Sch\u00f6ftland",
    "wof:placetype":"venue"
},
  "geometry": {"coordinates":[8.053068,47.30806],"type":"Point"}
}