{
  "type": "Feature",
  "properties": {
    "iso:country":"CH",
    "sg:address":"Rue Pr\u00e9vost-martin 21",
    "sg:city":"Gen\u00e8ve",
    "sg:classifiers":[
        {
            "category":"Restaurant",
            "type":"Food & Drink"
        }
    ],
    "sg:phone":"+41 22 320 70 48",
    "sg:postcode":"1205",
    "sg:province":"Gen\u00e8ve",
    "wof:name":"Restaurant Aux Baroudeurs",
    "wof:placetype":"venue"
},
  "geometry": {"coordinates":[6.1459522247,46.1948051453],"type":"Point"}
}