{
  "type": "Feature",
  "properties": {
    "iso:country":"CH",
    "sg:address":"Steinhaldenstrasse 8",
    "sg:city":"Geroldswil",
    "sg:orig_category":"Werbung",
    "sg:postcode":"8954",
    "sg:province":"Z\u00fcrich",
    "wof:name":"Salt Communications Gmbh",
    "wof:placetype":"venue"
},
  "geometry": {"coordinates":[8.4144449234,47.4187049866],"type":"Point"}
}