{
  "type": "Feature",
  "properties": {
    "iso:country":"CH",
    "sg:address":"Planzette Rue De 21",
    "sg:city":"Sierre",
    "sg:orig_category":"Unternehmensberatung",
    "sg:phone":"+41 27 455 52 08",
    "sg:postcode":"3960",
    "sg:province":"Valais",
    "wof:name":"Berchtold Rose-marie Consulting",
    "wof:placetype":"venue"
},
  "geometry": {"coordinates":[7.5391201973,46.2898788452],"type":"Point"}
}