{
  "type": "Feature",
  "properties": {
    "iso:country":"CH",
    "sg:address":"Sarganserstrasse 9",
    "sg:city":"Mels",
    "sg:orig_category":"Werbevermittlung",
    "sg:phone":"+41 81 723 55 75",
    "sg:postcode":"8887",
    "sg:province":"St. Gallen",
    "wof:name":"Publicitas Sa",
    "wof:placetype":"venue"
},
  "geometry": {"coordinates":[9.4223632812,47.0479736328],"type":"Point"}
}