{
  "type": "Feature",
  "properties": {
    "iso:country":"CH",
    "sg:address":"Chemin Du Publiet 16",
    "sg:city":"Marly",
    "sg:orig_category":"Vermietung U Verpachtung von eigenen Immobilien",
    "sg:postcode":"1723",
    "sg:province":"Fribourg",
    "wof:name":"Maimmob Ag",
    "wof:placetype":"venue"
},
  "geometry": {"coordinates":[8.3860731125,46.957824707],"type":"Point"}
}