{
  "type": "Feature",
  "properties": {
    "iso:country":"CH",
    "sg:address":"Stegr\u00fcteli",
    "sg:city":"Galgenen",
    "sg:orig_category":"Allgemeiner Hoch U Tiefbau",
    "sg:phone":"+41 55 440 47 77",
    "sg:postcode":"8854",
    "sg:province":"Schwyz",
    "wof:name":"Wissgem Handel & Montagen Gmbh",
    "wof:placetype":"venue"
},
  "geometry": {"coordinates":[8.87522,47.182331],"type":"Point"}
}