{
  "type": "Feature",
  "properties": {
    "iso:country":"CH",
    "sg:address":"Via Da Cul",
    "sg:city":"Zernez",
    "sg:orig_category":"G\u00fcterbef\u00f6rderung im Strassenverkehr",
    "sg:phone":"+41 81 856 10 62",
    "sg:postcode":"7530",
    "sg:province":"Graubunden",
    "wof:name":"Mayolani Sa Transporte",
    "wof:placetype":"venue"
},
  "geometry": {"coordinates":[10.0894927979,46.6971702576],"type":"Point"}
}