{
  "type": "Feature",
  "properties": {
    "iso:country":"CH",
    "sg:address":"Lerchenfeldstrasse 15a",
    "sg:city":"Thun",
    "sg:orig_category":"Vereine Frauen Vereine Gemeinn\u00fctzige",
    "sg:phone":"+41 33 336 03 62",
    "sg:postcode":"3603",
    "sg:province":"Bern",
    "wof:name":"Gemeinn. Frauenverein Thun",
    "wof:placetype":"venue"
},
  "geometry": {"coordinates":[7.6027932167,46.7661705017],"type":"Point"}
}