{
  "type": "Feature",
  "properties": {
    "iso:country":"CH",
    "sg:address":"Leutschenbachstr. 95 (achtung Nur Postadresse!)",
    "sg:city":"Z\u00fcrich",
    "sg:orig_category":"Herstellung von Mess U Kontrollinstrumenten U vorrichtungen",
    "sg:phone":"+41 32 652 78 71",
    "sg:postcode":"8050",
    "sg:province":"Z\u00fcrich",
    "wof:name":"Fluri Edgar",
    "wof:placetype":"venue"
},
  "geometry": {"coordinates":[7.3620438576,47.1780815125],"type":"Point"}
}