{
  "type": "Feature",
  "properties": {
    "iso:country":"CH",
    "sg:address":"Tanzplatz 19",
    "sg:city":"Schaan",
    "sg:orig_category":"Malerei",
    "sg:phone":"+423 232 16 14",
    "sg:postcode":"9494",
    "wof:name":"Kurt Frick Malergesch\u00e4ft",
    "wof:placetype":"venue"
},
  "geometry": {"coordinates":[9.50963974,47.1610794067],"type":"Point"}
}