{
  "type": "Feature",
  "properties": {
    "iso:country":"CH",
    "sg:address":"Diepoldsauerstrasse 3",
    "sg:city":"Widnau",
    "sg:orig_category":"Detailhandel mit Fahrr\u00e4dern",
    "sg:phone":"+41 71 722 25 73",
    "sg:postcode":"9443",
    "sg:province":"St. Gallen",
    "wof:name":"Eustachius Spirig Velohandlung",
    "wof:placetype":"venue"
},
  "geometry": {"coordinates":[9.6369495392,47.4006996155],"type":"Point"}
}