{
  "type": "Feature",
  "properties": {
    "iso:country":"CH",
    "sg:address":"Route De Meyrin 171",
    "sg:city":"Vernier",
    "sg:orig_category":"Reparatur von Schuhen U Lederwaren Schl\u00fcsselservice",
    "sg:phone":"+41 22 341 41 30",
    "sg:postcode":"1214",
    "sg:province":"Gen\u00e8ve",
    "wof:name":"Minit Switzerland Mister Minit Schuhrep.",
    "wof:placetype":"venue"
},
  "geometry": {"coordinates":[6.0958089828,46.2222442627],"type":"Point"}
}