{
  "type": "Feature",
  "properties": {
    "iso:country":"CH",
    "sg:address":"Route D'yverdon 72",
    "sg:city":"Payerne",
    "sg:orig_category":"Blumen U Zierpflanzenbau",
    "sg:phone":"+41 71 385 16 85",
    "sg:postcode":"1530",
    "sg:province":"Vaud",
    "wof:name":"Max Belser G\u00e4rtnerei",
    "wof:placetype":"venue"
},
  "geometry": {"coordinates":[9.246405,47.418484],"type":"Point"}
}