{
  "type": "Feature",
  "properties": {
    "iso:country":"CH",
    "sg:address":"8524",
    "sg:city":"Uesslingen",
    "sg:orig_category":"Sportvereine Sch\u00fctzen",
    "sg:phone":"+41 52 746 14 58",
    "sg:postcode":"8524",
    "sg:province":"Thurgau",
    "wof:name":"Feldsch\u00fctzengesellschaft",
    "wof:placetype":"venue"
},
  "geometry": {"coordinates":[8.8314800262,47.580280304],"type":"Point"}
}