{
  "type": "Feature",
  "properties": {
    "iso:country":"CH",
    "sg:address":"Dorfstrasse 6",
    "sg:city":"Gals",
    "sg:orig_category":"Fahrschulen, Flugschulen",
    "sg:phone":"+41 32 338 24 44",
    "sg:postcode":"2076",
    "wof:name":"Hans Richard Autofahrschule",
    "wof:placetype":"venue"
},
  "geometry": {"coordinates":[7.0489802361,47.0271072388],"type":"Point"}
}