{
  "type": "Feature",
  "properties": {
    "iso:country":"CH",
    "sg:address":"Alte Stationsstrasse 6",
    "sg:city":"Niederweningen",
    "sg:orig_category":"Softwareentwicklung U beratung",
    "sg:phone":"+41 18856085",
    "sg:postcode":"8166",
    "sg:province":"Z\u00fcrich",
    "wof:name":"Ozzi-data Gmbh",
    "wof:placetype":"venue"
},
  "geometry": {"coordinates":[8.3796386719,47.5072288513],"type":"Point"}
}