{
  "type": "Feature",
  "properties": {
    "addr:full":"Thunstrasse 22 3074 Muri B. Bern. Postfach Bern Bern 3001",
    "addr:housenumber":"22",
    "addr:postcode":"3074;3001",
    "addr:street":"Thunstrasse",
    "iso:country":"CH",
    "sg:address":"Thunstrasse 22 3074 Muri B. Bern. Postfach",
    "sg:city":"Bern",
    "sg:orig_category":"Architekturb\u00fcros",
    "sg:phone":"+41 41 850 48 47",
    "sg:postcode":"3001",
    "sg:province":"Bern",
    "wof:name":"Heinz V. H\u00fcsler Architekturb\u00fcro",
    "wof:placetype":"venue"
},
  "geometry": {"coordinates":[8.442277,47.086357],"type":"Point"}
}