{
  "type": "Feature",
  "properties": {
    "iso:country":"CH",
    "sg:address":"Chemin Aux-folies 16",
    "sg:city":"Bellevue",
    "sg:orig_category":"Herstellung von elektronischen Bauelementen",
    "sg:phone":"+41 22 774 17 27",
    "sg:postcode":"1293",
    "sg:province":"Gen\u00e8ve",
    "wof:name":"Ibc Retail Systemes Sa",
    "wof:placetype":"venue"
},
  "geometry": {"coordinates":[6.1437458992,46.2543907166],"type":"Point"}
}