{
  "type": "Feature",
  "properties": {
    "iso:country":"CH",
    "sg:address":"Reitnauerstrasse",
    "sg:city":"Winikon",
    "sg:orig_category":"Sanit\u00e4rinstallation",
    "sg:phone":"+41 41 933 05 35",
    "sg:postcode":"6235",
    "sg:province":"Luzern",
    "wof:name":"Richard Leupi Sanit\u00e4re Anlagen",
    "wof:placetype":"venue"
},
  "geometry": {"coordinates":[8.0528497696,47.2394294739],"type":"Point"}
}