{
  "type": "Feature",
  "properties": {
    "iso:country":"CH",
    "sg:address":"Rue De Vermont 62",
    "sg:city":"Gen\u00e8ve",
    "sg:orig_category":"Grosshandel mit festen Brennstoffen U Mineral\u00f6lerzeugnissen Mineral\u00f6lverarbeitung",
    "sg:phone":"+41 21 697 02 72",
    "sg:postcode":"1202",
    "sg:province":"Gen\u00e8ve",
    "wof:name":"Asphaltex Trading Sa",
    "wof:placetype":"venue"
},
  "geometry": {"coordinates":[6.5430197716,46.5123901367],"type":"Point"}
}