{
  "type": "Feature",
  "properties": {
    "iso:country":"CH",
    "sg:address":"Route De Frontenex 43",
    "sg:city":"Gen\u00e8ve",
    "sg:classifiers":[
        {
            "category":"Restaurant",
            "type":"Food & Drink"
        }
    ],
    "sg:phone":"+41 22 735 05 22",
    "sg:postcode":"1207",
    "sg:province":"Gen\u00e8ve",
    "wof:name":"Caf\u00e9 La Renaissance Chez Mait\u00e9",
    "wof:placetype":"venue"
},
  "geometry": {"coordinates":[6.1630311012,46.2021026611],"type":"Point"}
}