{
  "type": "Feature",
  "properties": {
    "iso:country":"CH",
    "sg:address":"6838",
    "sg:city":"Cabbio",
    "sg:classifiers":[
        {
            "category":"Restaurant",
            "type":"Food & Drink"
        }
    ],
    "sg:phone":"+41 91 684 13 61",
    "sg:postcode":"6838",
    "sg:province":"Ticino",
    "wof:name":"Ristorante Posta",
    "wof:placetype":"venue"
},
  "geometry": {"coordinates":[9.0454540253,45.8984184265],"type":"Point"}
}