{
  "type": "Feature",
  "properties": {
    "iso:country":"CH",
    "sg:address":"Chrummb\u00fcel",
    "sg:city":"Br\u00fctten",
    "sg:orig_category":"Grosshandel mit landwirtschaftlichen Maschinen U Ger\u00e4ten Herstellung von sonstigen landwirtschaftlic",
    "sg:phone":"+41 34 423 18 92",
    "sg:postcode":"8311",
    "sg:province":"Z\u00fcrich",
    "wof:name":"Braun Christian",
    "wof:placetype":"venue"
},
  "geometry": {"coordinates":[7.5921020508,47.0849876404],"type":"Point"}
}