{
  "type": "Feature",
  "properties": {
    "iso:country":"CH",
    "sg:address":"Place St-fran\u00e7ois 1 1000 Lausanne. Postfach",
    "sg:city":"Lausanne",
    "sg:orig_category":"Unclassifiable Establishments",
    "sg:postcode":"1003",
    "sg:province":"Vaud",
    "wof:name":"Si Avenue Des Alpes 104, Montreux",
    "wof:placetype":"venue"
},
  "geometry": {"coordinates":[6.6321568489,46.5198173523],"type":"Point"}
}