{
  "type": "Feature",
  "properties": {
    "addr:full":"Binningerstrasse 40 4054 Basel. Postfach Basel Basel-Stadt 4011",
    "addr:housenumber":"40",
    "addr:postcode":"4054;4011",
    "addr:street":"Binningerstrasse;Postfach",
    "iso:country":"CH",
    "sg:address":"Binningerstrasse 40 4054 Basel. Postfach",
    "sg:city":"Basel",
    "sg:orig_category":"Botanische U zoologische G\u00e4rten sowie Naturparks",
    "sg:phone":"+41 61 281 00 00",
    "sg:postcode":"4011",
    "sg:province":"Basel-Stadt",
    "wof:name":"Zoologischer Garten Basel",
    "wof:placetype":"venue"
},
  "geometry": {"coordinates":[7.582756,47.548882],"type":"Point"}
}