{
  "type": "Feature",
  "properties": {
    "iso:country":"CH",
    "sg:address":"Seestrasse 47",
    "sg:city":"Fl\u00fcelen",
    "sg:orig_category":"Allgemeiner Hoch U Tiefbau",
    "sg:postcode":"6454",
    "sg:province":"Uri",
    "wof:name":"Fischer Renovationen",
    "wof:placetype":"venue"
},
  "geometry": {"coordinates":[8.621632,46.913399],"type":"Point"}
}