{
  "type": "Feature",
  "properties": {
    "iso:country":"CH",
    "sg:address":"Marktgasse 2",
    "sg:city":"Appenzell",
    "sg:orig_category":"Verwaltung der Volkswirtschaft",
    "sg:phone":"+41 71 243 57 57",
    "sg:postcode":"9050",
    "sg:province":"Appenzell Innerhoden",
    "wof:name":"Volkswirtschaftsdepartement Sekretariat",
    "wof:placetype":"venue"
},
  "geometry": {"coordinates":[9.4097957611,47.3310165405],"type":"Point"}
}