{
  "type": "Feature",
  "properties": {
    "iso:country":"CH",
    "sg:address":"S\u00fcdstrasse 5",
    "sg:city":"M\u00fcnsingen",
    "sg:orig_category":"Instandhaltung U Reparatur von Automobilen",
    "sg:phone":"+41 31 721 56 35",
    "sg:postcode":"3110",
    "sg:province":"Bern",
    "wof:name":"Awa Garage D'astolfo Stefano",
    "wof:placetype":"venue"
},
  "geometry": {"coordinates":[7.5633420944,46.8680381775],"type":"Point"}
}