{
  "type": "Feature",
  "properties": {
    "iso:country":"CH",
    "sg:address":"B\u00fcelwiesstrasse 36",
    "sg:city":"Algetshausen",
    "sg:orig_category":"Detailhandel mit Waren verschiedener Art, Hauptrichtung Nahrungsmittel",
    "sg:phone":"+41 71 951 57 41",
    "sg:postcode":"9249",
    "sg:province":"St. Gallen",
    "wof:name":"Alois Steiger Obst & Gem\u00fcse",
    "wof:placetype":"venue"
},
  "geometry": {"coordinates":[9.1027040482,47.4494895935],"type":"Point"}
}