{
  "type": "Feature",
  "properties": {
    "addr:full":"Dreispitzstr. 5 4000 Basel. Postfach Basel Basel-Stadt 4000",
    "addr:housenumber":"5",
    "addr:postcode":"4000;4000",
    "addr:street":"Dreispitzstr.;Postfach",
    "iso:country":"CH",
    "sg:address":"Dreispitzstr. 5 4000 Basel. Postfach",
    "sg:city":"Basel",
    "sg:orig_category":"Allgemeiner Hoch U Tiefbau",
    "sg:postcode":"4000",
    "sg:province":"Basel-Stadt",
    "wof:name":"Conforti Sa",
    "wof:placetype":"venue"
},
  "geometry": {"coordinates":[7.212448,46.08046],"type":"Point"}
}