{
  "type": "Feature",
  "properties": {
    "iso:country":"CH",
    "sg:address":"Benevis 90 Case Postale",
    "sg:city":"Loveresse",
    "sg:classifiers":[
        {
            "category":"Manufacturing",
            "subcategory":"Metals",
            "type":"Manufacturing & Wholesale Goods"
        }
    ],
    "sg:phone":"+41 26 665 10 71",
    "sg:postcode":"2732",
    "sg:province":"Bern",
    "sg:tags":[
        "metallurgy",
        "metalworking",
        "processing"
    ],
    "wof:name":"Boram Sa",
    "wof:placetype":"venue"
},
  "geometry": {"coordinates":[6.8680329323,46.8162384033],"type":"Point"}
}