{
  "type": "Feature",
  "properties": {
    "iso:country":"CH",
    "sg:address":"3900 Gamsen. Postfach",
    "sg:city":"Glis",
    "sg:orig_category":"Abwasserreinigung",
    "sg:phone":"+41 27 922 27 37",
    "sg:postcode":"3902",
    "sg:province":"Valais",
    "wof:name":"Ara Briglina",
    "wof:placetype":"venue"
},
  "geometry": {"coordinates":[7.953801,46.305187],"type":"Point"}
}