{
  "type": "Feature",
  "properties": {
    "addr:full":"F\u00f6hrenweg 15 Balzers 9496",
    "addr:housenumber":"15",
    "addr:postcode":"9496",
    "addr:street":"Foehrenweg",
    "iso:country":"CH",
    "sg:address":"F\u00f6hrenweg 15",
    "sg:city":"Balzers",
    "sg:orig_category":"Detailhandel mit Brennstoffen U Heizmaterial G\u00fcterbef\u00f6rderung im Strassenverkehr",
    "sg:phone":"+41 81 933 10 09",
    "sg:postcode":"9496",
    "wof:name":"Ren\u00e9 Cavegn",
    "wof:placetype":"venue"
},
  "geometry": {"coordinates":[9.11139,46.747791],"type":"Point"}
}