{
  "type": "Feature",
  "properties": {
    "iso:country":"CH",
    "sg:address":"Luzernstrasse 29",
    "sg:city":"Subingen",
    "sg:orig_category":"Zimmerei, Dachdeckerei, Bauspenglerei U Abdichtung",
    "sg:postcode":"4553",
    "sg:province":"Solothurn",
    "wof:name":"Weber Bedachungen",
    "wof:placetype":"venue"
},
  "geometry": {"coordinates":[7.6120147705,47.1965255737],"type":"Point"}
}