{
  "type": "Feature",
  "properties": {
    "iso:country":"CH",
    "sg:address":"Scheideggweg 7",
    "sg:city":"Goldau",
    "sg:orig_category":"Herstellung von Schreinerwaren ohne ausgepr\u00e4gten Schwerpunkt Herstellung von sonstigen Fahrzeugen",
    "sg:phone":"+41 52 345 10 72",
    "sg:postcode":"6410",
    "sg:province":"Schwyz",
    "wof:name":"Martin Meili Schreinerei & Wagnerei",
    "wof:placetype":"venue"
},
  "geometry": {"coordinates":[8.7180166245,47.4354248047],"type":"Point"}
}