{
  "type": "Feature",
  "properties": {
    "iso:country":"CH",
    "sg:address":"Geissmattstrasse 60 6004 Luzern. Postfach",
    "sg:city":"Luzern",
    "sg:orig_category":"Institutionen des Sozialwesens ohne Beherbergung",
    "sg:postcode":"6003",
    "sg:province":"Luzern",
    "wof:name":"Jobdach",
    "wof:placetype":"venue"
},
  "geometry": {"coordinates":[8.3011522293,47.0583534241],"type":"Point"}
}