{
  "type": "Feature",
  "properties": {
    "iso:country":"CH",
    "sg:address":"3472",
    "sg:city":"Wynigen",
    "sg:orig_category":"Vereine Vogel-& Naturschutz",
    "sg:postcode":"3472",
    "sg:province":"Bern",
    "wof:name":"Ornithologischer Verein Wynigen & Umgebung",
    "wof:placetype":"venue"
},
  "geometry": {"coordinates":[7.667828083,47.1060791016],"type":"Point"}
}