{
  "type": "Feature",
  "properties": {
    "iso:country":"CH",
    "sg:address":"Im Holderbaum 29",
    "sg:city":"Bauma",
    "sg:orig_category":"Kaminfeger",
    "sg:phone":"+41 52 386 10 76",
    "sg:postcode":"8494",
    "sg:province":"Z\u00fcrich",
    "wof:name":"Christoph Duvaud Kaminfegergesch\u00e4ft",
    "wof:placetype":"venue"
},
  "geometry": {"coordinates":[8.8843202591,47.3673400879],"type":"Point"}
}