{
  "type": "Feature",
  "properties": {
    "iso:country":"CH",
    "sg:address":"Chalet Le Pinson 3963 Crans-sur-sierre. Postfach",
    "sg:city":"Crans-sur-sierre",
    "sg:orig_category":"Vermietung U Verpachtung von eigenen Immobilien",
    "sg:postcode":"3963",
    "sg:province":"Valais",
    "wof:name":"Eichb\u00fchl-immobilien Ag St. Gallen Liegenschaften-gesch\u00e4fte Usw.",
    "wof:placetype":"venue"
},
  "geometry": {"coordinates":[9.3889522552,47.4378051758],"type":"Point"}
}