{
  "type": "Feature",
  "properties": {
    "iso:country":"CH",
    "sg:address":"Schwyzerstrasse 21c",
    "sg:city":"Brunnen",
    "sg:orig_category":"Unclassifiable Establishments",
    "sg:phone":"+41 41 852 07 30",
    "sg:postcode":"6440",
    "sg:province":"Schwyz",
    "wof:name":"Tsch\u00fcmperlin F.a. Holding Ag",
    "wof:placetype":"venue"
},
  "geometry": {"coordinates":[8.4448652267,47.0884056091],"type":"Point"}
}