{
  "type": "Feature",
  "properties": {
    "iso:country":"CH",
    "sg:address":"Fontanettes Chemin Des 3 1807 Blonay. Postfach",
    "sg:city":"Blonay",
    "sg:orig_category":"Instandhaltung U Reparatur von Automobilen",
    "sg:postcode":"1807",
    "sg:province":"Vaud",
    "wof:name":"Garage Vall\u00e9lian",
    "wof:placetype":"venue"
},
  "geometry": {"coordinates":[6.895596981,46.4777755737],"type":"Point"}
}