{
  "type": "Feature",
  "properties": {
    "iso:country":"CH",
    "sg:address":"Grand'rue 1071 Chexbres. Postfach",
    "sg:city":"Chexbres",
    "sg:orig_category":"Grosshandel mit Getr\u00e4nken",
    "sg:postcode":"1071",
    "sg:province":"Vaud",
    "wof:name":"Flovin S\u00e0rl",
    "wof:placetype":"venue"
},
  "geometry": {"coordinates":[6.7762470245,46.4821128845],"type":"Point"}
}