{
  "type": "Feature",
  "properties": {
    "iso:country":"CH",
    "sg:address":"Davidsbodenstrasse 58 4056 Basel. Postfach",
    "sg:city":"Basel",
    "sg:orig_category":"Herstellung von Metallkonstruktionen",
    "sg:postcode":"4051",
    "sg:province":"Basel-Stadt",
    "wof:name":"Smi Blum Mettalbau, Revisionen Im Montagebereich Usw",
    "wof:placetype":"venue"
},
  "geometry": {"coordinates":[7.5757417679,47.566822052],"type":"Point"}
}