{
  "type": "Feature",
  "properties": {
    "iso:country":"CH",
    "sg:address":"Oberdorfstrasse",
    "sg:city":"Saanen",
    "sg:orig_category":"Herstellung von Metallkonstruktionen",
    "sg:postcode":"3792",
    "sg:province":"Bern",
    "wof:name":"Martin M\u00fcrner",
    "wof:placetype":"venue"
},
  "geometry": {"coordinates":[6.1339907646,46.1876029968],"type":"Point"}
}