{
  "type": "Feature",
  "properties": {
    "iso:country":"CH",
    "sg:address":"Hausmatt 7",
    "sg:city":"Immensee",
    "sg:orig_category":"Autoreiseunternehmen",
    "sg:phone":"+41 79 641 65 80",
    "sg:postcode":"6405",
    "sg:province":"Schwyz",
    "wof:name":"Josef Ehrler Autoreisen",
    "wof:placetype":"venue"
},
  "geometry": {"coordinates":[8.46099,47.096298],"type":"Point"}
}