{
  "type": "Feature",
  "properties": {
    "iso:country":"CH",
    "sg:address":"Reichsgasse 3 7000 Chur. Postfach 152",
    "sg:city":"Chur",
    "sg:orig_category":"Personal U Stellenvermittlung Unternehmensberatung",
    "sg:phone":"+41 81 250 08 50",
    "sg:postcode":"7002",
    "sg:province":"Graubunden",
    "wof:name":"Cottiati Personaltreuhand Ag",
    "wof:placetype":"venue"
},
  "geometry": {"coordinates":[9.5340223312,46.851146698],"type":"Point"}
}