{
  "type": "Feature",
  "properties": {
    "iso:country":"CH",
    "sg:address":"Sonnenhof 1 8117 F\u00e4llanden. Postfach",
    "sg:city":"Benglen",
    "sg:orig_category":"Werbung",
    "sg:postcode":"8121",
    "sg:province":"Z\u00fcrich",
    "wof:name":"Schwartz & Schwartz",
    "wof:placetype":"venue"
},
  "geometry": {"coordinates":[8.6365938187,47.3585777283],"type":"Point"}
}