{
  "type": "Feature",
  "properties": {
    "iso:country":"CH",
    "sg:address":"Chemin De Ruffy 7",
    "sg:city":"Lonay",
    "sg:orig_category":"Technische B\u00fcros Heizung, L\u00fcftung, Klima",
    "sg:phone":"+41 21 801 45 08",
    "sg:postcode":"1027",
    "sg:province":"Vaud",
    "wof:name":"Ren\u00e9 Goldenschue Bureau Technique",
    "wof:placetype":"venue"
},
  "geometry": {"coordinates":[6.5167021751,46.5261192322],"type":"Point"}
}