{
  "type": "Feature",
  "properties": {
    "iso:country":"CH",
    "sg:address":"Tunnel Rue Du 15 1005 Lausanne. Postfach",
    "sg:city":"Lausanne",
    "sg:orig_category":"Schaustellergewerbe U Vergn\u00fcgungsparks",
    "sg:postcode":"1005",
    "sg:province":"Vaud",
    "wof:name":"Top Ten Line Detoledo Agence Artistique",
    "wof:placetype":"venue"
},
  "geometry": {"coordinates":[6.6343660355,46.5264320374],"type":"Point"}
}