{
  "type": "Feature",
  "properties": {
    "iso:country":"CH",
    "sg:address":"Kronengasse 2",
    "sg:city":"Baden",
    "sg:orig_category":"Kosmetikinstitute",
    "sg:phone":"+41 56 209 13 00",
    "sg:postcode":"5400",
    "sg:province":"Aargau",
    "wof:name":"Vera Rudolf Kosmetisches Institut",
    "wof:placetype":"venue"
},
  "geometry": {"coordinates":[8.309926033,47.472568512],"type":"Point"}
}