{
  "type": "Feature",
  "properties": {
    "iso:country":"CH",
    "sg:address":"Hinterzweienstrasse 75",
    "sg:city":"Muttenz",
    "sg:orig_category":"Sonstige Kultur U Unterhaltungseinrichtungen",
    "sg:postcode":"4132",
    "sg:province":"Basel-Landschaft",
    "wof:name":"Ck Enterprises Ag",
    "wof:placetype":"venue"
},
  "geometry": {"coordinates":[7.6381750107,47.52759552],"type":"Point"}
}