{
  "type": "Feature",
  "properties": {
    "iso:country":"CH",
    "sg:address":"Bollwerk 21 3011 Bern. Postfach",
    "sg:city":"Bern",
    "sg:orig_category":"Kinos",
    "sg:phone":"+41 31 311 25 00",
    "sg:postcode":"3005",
    "sg:province":"Bern",
    "wof:name":"Marti Urs Kinos Actualis",
    "wof:placetype":"venue"
},
  "geometry": {"coordinates":[7.440723896,46.9499740601],"type":"Point"}
}