{
  "type": "Feature",
  "properties": {
    "iso:country":"CH",
    "sg:address":"Avenue Du Simplon 100 1870 Monthey Case Postale 7",
    "sg:city":"Monthey",
    "sg:orig_category":"Handel mit Automobilteilen U Zubeh\u00f6r Handelsvermittlung U Grosshandel mit Automobilteilen U Zubeh\u00f6r",
    "sg:phone":"+41 24 471 87 62",
    "sg:postcode":"1870",
    "sg:province":"Valais",
    "wof:name":"V\u00e9rolet Marcel Monthey Sa",
    "wof:placetype":"venue"
},
  "geometry": {"coordinates":[6.9624929428,46.2456245422],"type":"Point"}
}