{
  "type": "Feature",
  "properties": {
    "iso:country":"CH",
    "sg:address":"Wartenbergstrasse 4a",
    "sg:city":"Pratteln",
    "sg:orig_category":"Handelsvermittlung U Grosshandel mit Automobilen",
    "sg:phone":"+41 61 821 58 32",
    "sg:postcode":"4133",
    "sg:province":"Basel-Landschaft",
    "wof:name":"Mone Nikolov",
    "wof:placetype":"venue"
},
  "geometry": {"coordinates":[7.6892981529,47.5168571472],"type":"Point"}
}