{
  "type": "Feature",
  "properties": {
    "iso:country":"CH",
    "sg:address":"Schulstrasse 43",
    "sg:city":"Landquart",
    "sg:orig_category":"Gartenbau",
    "sg:phone":"+41 81 322 12 47",
    "sg:postcode":"7302",
    "sg:province":"Graubunden",
    "wof:name":"Ernst Gensetter Pflanzenkulturen",
    "wof:placetype":"venue"
},
  "geometry": {"coordinates":[9.5592851639,46.9627532959],"type":"Point"}
}