{
  "type": "Feature",
  "properties": {
    "iso:country":"CH",
    "sg:address":"Stockackerweg 10 4704 Niederbipp. Postfach 121",
    "sg:city":"Niederbipp",
    "sg:orig_category":"Herstellung von Metallerzeugnissen ohne Maschinenbau Herstellung von landwirtschaftlichen Maschinen",
    "sg:phone":"+41 32 633 23 63",
    "sg:postcode":"4704",
    "sg:province":"Bern",
    "wof:name":"Speriwa, Sperisen + Co",
    "wof:placetype":"venue"
},
  "geometry": {"coordinates":[7.6898,47.266651],"type":"Point"}
}