{
  "type": "Feature",
  "properties": {
    "iso:country":"CH",
    "sg:address":"Dorfstrasse 34",
    "sg:city":"Vinelz",
    "sg:orig_category":"Gemeindeverwaltungen",
    "sg:phone":"+41 32 338 16 66",
    "sg:postcode":"3234",
    "sg:province":"Bern",
    "wof:name":"Gemeindeverwaltung Vinelz",
    "wof:placetype":"venue"
},
  "geometry": {"coordinates":[7.1128969193,47.0342636108],"type":"Point"}
}