{
  "type": "Feature",
  "properties": {
    "iso:country":"CH",
    "sg:address":"Z\u00fcrichstrasse 5",
    "sg:city":"Luzern",
    "sg:orig_category":"Detailhandel mit Bekleidung Detailhandel mit Damenbekleidung",
    "sg:phone":"+41 41 410 07 17",
    "sg:postcode":"6004",
    "sg:province":"Luzern",
    "wof:name":"Truns Mass-corner Luzern Masskonfektion",
    "wof:placetype":"venue"
},
  "geometry": {"coordinates":[8.310325,47.056435],"type":"Point"}
}