{
  "type": "Feature",
  "properties": {
    "iso:country":"CH",
    "sg:address":"Alte Winterthurerstrasse 78",
    "sg:city":"Wallisellen",
    "sg:orig_category":"Herstellung von sonstigen landwirtschaftlichen Maschinen",
    "sg:phone":"+41 18300732",
    "sg:postcode":"8304",
    "sg:province":"Z\u00fcrich",
    "wof:name":"Maurer U. Gmbh",
    "wof:placetype":"venue"
},
  "geometry": {"coordinates":[8.5966072083,47.4189071655],"type":"Point"}
}