{
  "type": "Feature",
  "properties": {
    "iso:country":"CH",
    "sg:address":"Boulevard De P\u00e9rolles 15 1700 Fribourg Case Postale 841",
    "sg:city":"Fribourg",
    "sg:orig_category":"Kinos",
    "sg:phone":"+41 26 322 40 77",
    "sg:postcode":"1701",
    "sg:province":"Fribourg",
    "wof:name":"Cin\u00e9ma Corso 1 & 2",
    "wof:placetype":"venue"
},
  "geometry": {"coordinates":[7.1521191597,46.8003845215],"type":"Point"}
}