{
  "type": "Feature",
  "properties": {
    "iso:country":"CH",
    "sg:address":"Hauptstrasse 9",
    "sg:city":"Hochdorf",
    "sg:orig_category":"Detailhandel mit Brot, Back U S\u00fcsswaren",
    "sg:phone":"+41 41 910 15 22",
    "sg:postcode":"6280",
    "sg:province":"Luzern",
    "wof:name":"Hansruedi Sticher B\u00e4ckerei-konditorei",
    "wof:placetype":"venue"
},
  "geometry": {"coordinates":[8.290398,47.166279],"type":"Point"}
}