{
  "type": "Feature",
  "properties": {
    "iso:country":"CH",
    "sg:address":"Junkholz 8514 Amlikon. Postfach",
    "sg:city":"Amlikon",
    "sg:orig_category":"Handel mit Motorr\u00e4dern, Teilen U Zubeh\u00f6r Instandhaltung U Reparatur von Motorr\u00e4dern",
    "sg:phone":"+41 34 445 22 82",
    "sg:postcode":"8514",
    "sg:province":"Thurgau",
    "wof:name":"Hansrudolf Hofer-k\u00e4gi",
    "wof:placetype":"venue"
},
  "geometry": {"coordinates":[7.5799298286,47.090057373],"type":"Point"}
}