{
  "type": "Feature",
  "properties": {
    "iso:country":"CH",
    "sg:address":"Lachenweg 18",
    "sg:city":"Riehen",
    "sg:orig_category":"Sportvereine P\u00e9tanque",
    "sg:postcode":"4125",
    "sg:province":"Basel-Stadt",
    "wof:name":"P\u00e9tanque-club Montetan",
    "wof:placetype":"venue"
},
  "geometry": {"coordinates":[6.612639904,46.5063896179],"type":"Point"}
}