{
  "type": "Feature",
  "properties": {
    "iso:country":"CH",
    "sg:address":"Via Locarno 50",
    "sg:city":"Losone",
    "sg:orig_category":"Landwirtschaft, Jagd U damit verbundene Dienstleistungen",
    "sg:phone":"+41 71 951 82 71",
    "sg:postcode":"6616",
    "sg:province":"Ticino",
    "wof:name":"B\u00fchler Ag Gutsbetrieb",
    "wof:placetype":"venue"
},
  "geometry": {"coordinates":[9.1329545975,47.4371452332],"type":"Point"}
}