{
  "type": "Feature",
  "properties": {
    "iso:country":"CH",
    "sg:address":"Bergstrasse 2 8712 St\u00e4fa. Postfach 535",
    "sg:city":"St\u00e4fa",
    "sg:orig_category":"Bau\u00e4mter",
    "sg:phone":"+41 62 293 25 12",
    "sg:postcode":"8712",
    "sg:province":"Z\u00fcrich",
    "wof:name":"Baukommission Der Gemeinde Wisen",
    "wof:placetype":"venue"
},
  "geometry": {"coordinates":[7.89593,47.393608],"type":"Point"}
}