{
  "type": "Feature",
  "properties": {
    "iso:country":"CH",
    "sg:address":"Im Berg 60",
    "sg:city":"Sissach",
    "sg:orig_category":"Herstellung von elektrischen Lampen U Leuchten",
    "sg:postcode":"4450",
    "sg:province":"Basel-Landschaft",
    "wof:name":"Luminex Ag",
    "wof:placetype":"venue"
},
  "geometry": {"coordinates":[7.8194937706,47.4660301208],"type":"Point"}
}