{
  "type": "Feature",
  "properties": {
    "iso:country":"CH",
    "sg:address":"Widumstrasse 7",
    "sg:city":"Schwerzenbach",
    "sg:orig_category":"Politische Parteien CVP",
    "sg:phone":"+41 17881520",
    "sg:postcode":"8603",
    "sg:province":"Z\u00fcrich",
    "wof:name":"Cvp Sektion Sch\u00f6nenberg",
    "wof:placetype":"venue"
},
  "geometry": {"coordinates":[8.6492576599,47.1982040405],"type":"Point"}
}