{
  "type": "Feature",
  "properties": {
    "iso:country":"CH",
    "sg:address":"Route De Pr\u00e9verenges 6",
    "sg:city":"Denges",
    "sg:orig_category":"R\u00fcckgewinnung U Vorbereitung f\u00fcr die Wiederverwertung Recycling von Schrott R\u00fcckgewinnung U Vorberei",
    "sg:phone":"+41 21 803 30 52",
    "sg:postcode":"1026",
    "sg:province":"Vaud",
    "wof:name":"Metabader S\u00e0rl",
    "wof:placetype":"venue"
},
  "geometry": {"coordinates":[6.5361800194,46.5250282288],"type":"Point"}
}