{
  "type": "Feature",
  "properties": {
    "iso:country":"CH",
    "sg:address":"Chemin De La Traverse 15",
    "sg:city":"Aubonne",
    "sg:orig_category":"Hom\u00f6opathie Naturheil\u00e4rzte and Heilpraktiker",
    "sg:phone":"+41 21 807 47 15",
    "sg:postcode":"1170",
    "sg:province":"Vaud",
    "wof:name":"Eliane Rochat Th\u00e9rapie Naturelle",
    "wof:placetype":"venue"
},
  "geometry": {"coordinates":[6.3915510178,46.4928016663],"type":"Point"}
}