{
  "type": "Feature",
  "properties": {
    "iso:country":"CH",
    "sg:address":"Via Magatti 3 6900 Lugano Casella Postale 77",
    "sg:city":"Lugano",
    "sg:orig_category":"Finanzierungsinstitutionen Wirtschaftspr\u00fcfung, Steuerberatung U Treuhand",
    "sg:phone":"+41 91 924 92 40",
    "sg:postcode":"6903",
    "sg:province":"Ticino",
    "wof:name":"Advanced Capital Sa",
    "wof:placetype":"venue"
},
  "geometry": {"coordinates":[8.9461364746,45.9767837524],"type":"Point"}
}