{
  "type": "Feature",
  "properties": {
    "iso:country":"CH",
    "sg:address":"Via Maggio 5",
    "sg:city":"Lugano",
    "sg:orig_category":"Grosshandel mit Erzen U Metallen Handelsvermittlung von Maschinen, technischem Bedarf, Wasser U Luft",
    "sg:phone":"+41 91 972 71 35",
    "sg:postcode":"6900",
    "sg:province":"Ticino",
    "wof:name":"Vepracom Sa",
    "wof:placetype":"venue"
},
  "geometry": {"coordinates":[8.9615440369,46.0081291199],"type":"Point"}
}