{
  "type": "Feature",
  "properties": {
    "iso:country":"CH",
    "sg:address":"Sosa",
    "sg:city":"Zernez",
    "sg:orig_category":"Gewinnung von Kies U Sand Gewinnung von Natursteinen f\u00fcr den Bau",
    "sg:phone":"+41 81 856 12 62",
    "sg:postcode":"7530",
    "sg:province":"Graubunden",
    "wof:name":"Sosa Gera Sa Steinbruch & Kieswerk",
    "wof:placetype":"venue"
},
  "geometry": {"coordinates":[10.0934457779,46.7039413452],"type":"Point"}
}