{
  "type": "Feature",
  "properties": {
    "iso:country":"CH",
    "sg:address":"3979",
    "sg:city":"Gr\u00f4ne",
    "sg:orig_category":"RESTAURANTS: TEA-ROOMS",
    "sg:phone":"+41 27 458 37 18",
    "sg:postcode":"3979",
    "sg:province":"Valais",
    "wof:name":"Rudaz Rose-may",
    "wof:placetype":"venue"
},
  "geometry": {"coordinates":[7.4571409225,46.2511062622],"type":"Point"}
}