{
  "type": "Feature",
  "properties": {
    "iso:country":"CH",
    "sg:address":"Winkelacker",
    "sg:city":"Altnau",
    "sg:orig_category":"Wasserversorgung",
    "sg:phone":"+41 56 634 25 36",
    "sg:postcode":"8595",
    "sg:province":"Thurgau",
    "wof:name":"Ap Systems Keller Dieter",
    "wof:placetype":"venue"
},
  "geometry": {"coordinates":[8.4385242462,47.3228569031],"type":"Point"}
}