{
  "type": "Feature",
  "properties": {
    "iso:country":"CH",
    "sg:address":"St\u00fcdlerstrasse 23",
    "sg:city":"Ottenbach",
    "sg:orig_category":"Herstellung von sonstigen Maschinen f\u00fcr unspezifische Verwendung Stahl U Leichtmetallbau",
    "sg:phone":"+41 17612351",
    "sg:postcode":"8913",
    "sg:province":"Z\u00fcrich",
    "wof:name":"Ramseier Ag",
    "wof:placetype":"venue"
},
  "geometry": {"coordinates":[8.3987369537,47.2829971313],"type":"Point"}
}