{
  "type": "Feature",
  "properties": {
    "iso:country":"CH",
    "sg:address":"Rue Du Clos 15",
    "sg:city":"Vevey",
    "sg:orig_category":"Primarschulen",
    "sg:phone":"+41 21 925 59 67",
    "sg:postcode":"1800",
    "sg:province":"Vaud",
    "wof:name":"Ecole Primaire Coll\u00e8ge Du Clos",
    "wof:placetype":"venue"
},
  "geometry": {"coordinates":[6.846362114,46.4607963562],"type":"Point"}
}