{
  "type": "Feature",
  "properties": {
    "iso:country":"CH",
    "sg:address":"Rieterstrasse 83",
    "sg:city":"Z\u00fcrich",
    "sg:orig_category":"Detailhandel mit S\u00e4uglings U Kinderbekleidung",
    "sg:phone":"+41 12020819",
    "sg:postcode":"8002",
    "sg:province":"Z\u00fcrich",
    "wof:name":"Chinderlade",
    "wof:placetype":"venue"
},
  "geometry": {"coordinates":[8.526266098,47.3542785645],"type":"Point"}
}