{
  "type": "Feature",
  "properties": {
    "iso:country":"CH",
    "sg:address":"Letten 168",
    "sg:city":"Scherz",
    "sg:orig_category":"Gartenbau",
    "sg:phone":"+41 56 444 05 43",
    "sg:postcode":"5246",
    "sg:province":"Aargau",
    "wof:name":"Matthias Messerli Gartenbau",
    "wof:placetype":"venue"
},
  "geometry": {"coordinates":[8.1804304123,47.4469184875],"type":"Point"}
}