{
  "type": "Feature",
  "properties": {
    "iso:country":"CH",
    "sg:address":"Dietisberg 52",
    "sg:city":"W\u00fcnnewil",
    "sg:orig_category":"RESTAURANTS: TEA-ROOMS",
    "sg:phone":"+41 26 496 19 74",
    "sg:postcode":"3184",
    "sg:province":"Fribourg",
    "wof:name":"Bidu Mr Tschannen Beat",
    "wof:placetype":"venue"
},
  "geometry": {"coordinates":[7.2884159088,46.8666725159],"type":"Point"}
}