{
  "type": "Feature",
  "properties": {
    "addr:full":"Gartenweg 2 Sissach Basel-Landschaft 4450",
    "addr:housenumber":"2",
    "addr:postcode":"4450",
    "addr:street":"Gartenweg",
    "iso:country":"CH",
    "sg:address":"Gartenweg 2",
    "sg:city":"Sissach",
    "sg:orig_category":"Bauspenglerei Sanit\u00e4rinstallation",
    "sg:postcode":"4450",
    "sg:province":"Basel-Landschaft",
    "wof:name":"Gebr. John Ag",
    "wof:placetype":"venue"
},
  "geometry": {"coordinates":[7.812468,47.463272],"type":"Point"}
}