{
  "type": "Feature",
  "properties": {
    "iso:country":"CH",
    "sg:address":"Forb\u00fcelstrasse 16 8245 Feuerthalen. Postfach",
    "sg:city":"Feuerthalen",
    "sg:orig_category":"Herstellung von elektronischen Bauelementen",
    "sg:postcode":"8245",
    "sg:province":"Z\u00fcrich",
    "wof:name":"Hy-line Ag Elektronische Bauteile U. Systeme; Herstellung, Vertrieb",
    "wof:placetype":"venue"
},
  "geometry": {"coordinates":[8.6528902054,47.6870498657],"type":"Point"}
}