{
  "type": "Feature",
  "properties": {
    "iso:country":"CH",
    "sg:address":"6715",
    "sg:city":"Dongio",
    "sg:orig_category":"Bauschreinerei Herstellung von Konstruktionsteilen, Fertigbauteilen U Ausbauelementen aus Holz",
    "sg:phone":"+41 91 871 25 86",
    "sg:postcode":"6715",
    "sg:province":"Ticino",
    "wof:name":"Truaisch & Derighetti Sagl Falegnameria Arred.cucine",
    "wof:placetype":"venue"
},
  "geometry": {"coordinates":[8.95226,46.439709],"type":"Point"}
}