{
  "type": "Feature",
  "properties": {
    "iso:country":"CH",
    "sg:address":"Seestrasse 130",
    "sg:city":"Steckborn",
    "sg:classifiers":[
        {
            "category":"Restaurant",
            "type":"Food & Drink"
        }
    ],
    "sg:phone":"+41 52 761 24 07",
    "sg:postcode":"8266",
    "sg:province":"Thurgau",
    "wof:name":"Restaurant Sonne",
    "wof:placetype":"venue"
},
  "geometry": {"coordinates":[8.98138237,47.6659431458],"type":"Point"}
}