{
  "type": "Feature",
  "properties": {
    "iso:country":"CH",
    "sg:address":"Stauffacherstrasse 147",
    "sg:city":"Z\u00fcrich",
    "sg:orig_category":"RESTAURANTS: TEA-ROOMS",
    "sg:phone":"+41 12420805",
    "sg:postcode":"8004",
    "sg:province":"Z\u00fcrich",
    "wof:name":"Caravelle, Moser W.",
    "wof:placetype":"venue"
},
  "geometry": {"coordinates":[8.5225505829,47.3773803711],"type":"Point"}
}