{
  "type": "Feature",
  "properties": {
    "iso:country":"CH",
    "sg:address":"Rue De Bellevue 17",
    "sg:city":"Fontainemelon",
    "sg:orig_category":"HERSTELLUNG VON GER\u00c4TEN DER ELEKTRIZIT\u00c4TSERZEUGUNG, -VERTEILUNG U.\u00c4 Herstellung von Radio U Fernsehg",
    "sg:phone":"+41 79 447 26 71",
    "sg:postcode":"2052",
    "sg:province":"Neuch\u00e2tel",
    "wof:name":"Swox Telecom, Weber L.",
    "wof:placetype":"venue"
},
  "geometry": {"coordinates":[6.8858618736,47.0552253723],"type":"Point"}
}