{
  "type": "Feature",
  "properties": {
    "iso:country":"CH",
    "sg:address":"7554",
    "sg:city":"Sent",
    "sg:orig_category":"Bezirks, Sekundar, Realschulen, Oberstufe der Primarschulen",
    "sg:phone":"+41 81 864 05 52",
    "sg:postcode":"7554",
    "sg:province":"Graubunden",
    "wof:name":"Sekundarschule",
    "wof:placetype":"venue"
},
  "geometry": {"coordinates":[10.337835,46.816792],"type":"Point"}
}