{
  "type": "Feature",
  "properties": {
    "iso:country":"CH",
    "sg:address":"Neugasse 42",
    "sg:city":"Z\u00fcrich",
    "sg:classifiers":[
        {
            "category":"Bars & Pubs",
            "type":"Food & Drink"
        }
    ],
    "sg:phone":"+41 12729595",
    "sg:postcode":"8005",
    "sg:province":"Z\u00fcrich",
    "wof:name":"Chicago Bar",
    "wof:placetype":"venue"
},
  "geometry": {"coordinates":[8.530079,47.382561],"type":"Point"}
}