{
  "type": "Feature",
  "properties": {
    "iso:country":"CH",
    "sg:address":"Uznacherstrasse 3",
    "sg:city":"Kaltbrunn",
    "sg:orig_category":"Pensionskassen",
    "sg:phone":"+41 55 293 34 34",
    "sg:postcode":"8722",
    "sg:province":"St. Gallen",
    "wof:name":"Pensionskasse Vom Linthgebiet Pkl",
    "wof:placetype":"venue"
},
  "geometry": {"coordinates":[9.0244493484,47.2134056091],"type":"Point"}
}