{
  "type": "Feature",
  "properties": {
    "iso:country":"CH",
    "sg:address":"K\u00fcntwilerstrasse 50b",
    "sg:city":"Rotkreuz",
    "sg:orig_category":"Massagestudios",
    "sg:phone":"+41 41 790 00 44",
    "sg:postcode":"6343",
    "sg:province":"Zug",
    "wof:name":"Fredy Eicher Massagepraxis",
    "wof:placetype":"venue"
},
  "geometry": {"coordinates":[8.4263963699,47.1360740662],"type":"Point"}
}