{
  "type": "Feature",
  "properties": {
    "iso:country":"CH",
    "sg:address":"Kappelisackerstrasse 69",
    "sg:city":"Ittigen",
    "sg:orig_category":"Unclassifiable Establishments",
    "sg:postcode":"3063",
    "sg:province":"Bern",
    "wof:name":"Jelia S\u00e0rl",
    "wof:placetype":"venue"
},
  "geometry": {"coordinates":[6.8299050331,47.102809906],"type":"Point"}
}