{
  "type": "Feature",
  "properties": {
    "iso:country":"CH",
    "sg:address":"Weissensteinstrasse 11 4513 Langendorf. Postfach",
    "sg:city":"Langendorf",
    "sg:orig_category":"Fachdetailhandel mit pharmazeutischen Produkten",
    "sg:phone":"+41 32 622 21 47",
    "sg:postcode":"4513",
    "sg:province":"Solothurn",
    "wof:name":"Dr.josef Brunner Weissenstein-apotheke",
    "wof:placetype":"venue"
},
  "geometry": {"coordinates":[7.5144572258,47.2193374634],"type":"Point"}
}