{
  "type": "Feature",
  "properties": {
    "iso:country":"CH",
    "sg:address":"6043 Adligenswil. Postfach 361",
    "sg:city":"Adligenswil",
    "sg:orig_category":"Polizei",
    "sg:phone":"+41 41 370 11 17",
    "sg:postcode":"6043",
    "sg:province":"Luzern",
    "wof:name":"Kantonale Polizei",
    "wof:placetype":"venue"
},
  "geometry": {"coordinates":[8.3629655838,47.0713844299],"type":"Point"}
}