{
  "type": "Feature",
  "properties": {
    "iso:country":"CH",
    "sg:address":"Etzelstrasse 13 5430 Wettingen. Postfach 99",
    "sg:city":"Wettingen",
    "sg:orig_category":"Ingenieurb\u00fcros Elektro Ingenieurb\u00fcros Maschinenbau",
    "sg:phone":"+41 55 440 12 03",
    "sg:postcode":"5430",
    "sg:province":"Aargau",
    "wof:name":"Walter & Christoph Koller Ingenieurb\u00fcro",
    "wof:placetype":"venue"
},
  "geometry": {"coordinates":[8.8822011948,47.1988563538],"type":"Point"}
}