{
  "type": "Feature",
  "properties": {
    "iso:country":"CH",
    "sg:address":"Schul\u00e9weg 13",
    "sg:city":"Oberentfelden",
    "sg:orig_category":"Arztpraxen",
    "sg:phone":"+41 62 723 53 33",
    "sg:postcode":"5036",
    "sg:province":"Aargau",
    "wof:name":"Dr.med.hanspeter D\u00f6belin Arzt F.allgemeine Medizin Fmh",
    "wof:placetype":"venue"
},
  "geometry": {"coordinates":[8.049719,47.35281],"type":"Point"}
}