{
  "type": "Feature",
  "properties": {
    "iso:country":"CH",
    "sg:address":"Gewerbestrasse 8 6438 Ibach. Postfach",
    "sg:city":"Ibach",
    "sg:orig_category":"Maler U Glasergewerbe",
    "sg:postcode":"6438",
    "sg:province":"Schwyz",
    "wof:name":"Malergesch\u00e4ft Schmid",
    "wof:placetype":"venue"
},
  "geometry": {"coordinates":[8.6341352463,47.0129394531],"type":"Point"}
}