{
  "type": "Feature",
  "properties": {
    "addr:full":"Les Neigles Fribourg Fribourg 1700",
    "addr:postcode":"1700",
    "iso:country":"CH",
    "sg:address":"Les Neigles",
    "sg:city":"Fribourg",
    "sg:orig_category":"Abfallbeseitigung Abwasserreinigung",
    "sg:phone":"+41 26 484 59 01",
    "sg:postcode":"1700",
    "sg:province":"Fribourg",
    "wof:name":"Station D'\u00e9puration Des Eaux",
    "wof:placetype":"venue"
},
  "geometry": {"coordinates":[7.164717,46.811218],"type":"Point"}
}