{
  "type": "Feature",
  "properties": {
    "iso:country":"CH",
    "sg:address":"Brunnmattstrasse 47",
    "sg:city":"Bern",
    "sg:orig_category":"Herstellung von Medikamenten U sonstigen pharmazeutischen Erzeugnissen Unternehmensberatung",
    "sg:phone":"+41 31 371 16 16",
    "sg:postcode":"3007",
    "sg:province":"Bern",
    "wof:name":"Kkh Ag",
    "wof:placetype":"venue"
},
  "geometry": {"coordinates":[7.4266672134,46.9427680969],"type":"Point"}
}