{
  "type": "Feature",
  "properties": {
    "iso:country":"CH",
    "sg:address":"Vogesenstrasse 108",
    "sg:city":"Basel",
    "sg:classifiers":[
        {
            "category":"Professional",
            "subcategory":"Computer Services",
            "type":"Services"
        }
    ],
    "sg:phone":"+41 79 321 67 09",
    "sg:postcode":"4056",
    "sg:province":"Basel-Stadt",
    "sg:tags":[
        "development",
        "software"
    ],
    "wof:name":"Comcepta Ag",
    "wof:placetype":"venue"
},
  "geometry": {"coordinates":[7.5758581161,47.5684928894],"type":"Point"}
}