{
  "type": "Feature",
  "properties": {
    "iso:country":"CH",
    "sg:address":"Mon-repos Avenue 15",
    "sg:city":"Lausanne",
    "sg:orig_category":"Vermietung U Verpachtung von eigenen Immobilien",
    "sg:postcode":"1005",
    "sg:province":"Vaud",
    "wof:name":"Sa Rue St-fran\u00e7ois No 4",
    "wof:placetype":"venue"
},
  "geometry": {"coordinates":[6.6406750679,46.5189323425],"type":"Point"}
}