{
  "type": "Feature",
  "properties": {
    "iso:country":"CH",
    "sg:address":"Rehabilitationsklinik",
    "sg:city":"Knoblisb\u00fchl",
    "sg:classifiers":[
        {
            "category":"Arena",
            "subcategory":"Sports Club",
            "type":"Entertainment"
        }
    ],
    "sg:postcode":"8881",
    "sg:province":"St. Gallen",
    "sg:tags":[
        "karate",
        "judo",
        "sportvereine"
    ],
    "wof:name":"Karate Club Walenstadt",
    "wof:placetype":"venue"
},
  "geometry": {"coordinates":[9.2854585648,47.1364822388],"type":"Point"}
}