{
  "type": "Feature",
  "properties": {
    "iso:country":"CH",
    "sg:address":"Rue Du Vieux-village 71",
    "sg:city":"Ardon",
    "sg:classifiers":[
        {
            "category":"Restaurant",
            "type":"Food & Drink"
        }
    ],
    "sg:phone":"+41 27 307 11 50",
    "sg:postcode":"1957",
    "sg:province":"Valais",
    "wof:name":"Caf\u00e9 Central",
    "wof:placetype":"venue"
},
  "geometry": {"coordinates":[7.2555789948,46.2114639282],"type":"Point"}
}