{
  "type": "Feature",
  "properties": {
    "iso:country":"CH",
    "sg:address":"Bahnhofstrasse 1",
    "sg:city":"Weinfelden",
    "sg:orig_category":"Spielsalons",
    "sg:phone":"+41 71 622 18 33",
    "sg:postcode":"8570",
    "sg:province":"Thurgau",
    "wof:name":"Spielsalon Papillon",
    "wof:placetype":"venue"
},
  "geometry": {"coordinates":[9.1061077118,47.566783905],"type":"Point"}
}