{
  "type": "Feature",
  "properties": {
    "iso:country":"CH",
    "sg:address":"Rheinstrasse 28",
    "sg:city":"Schaffhausen",
    "sg:orig_category":"Handel mit Motorr\u00e4dern, Teilen U Zubeh\u00f6r Instandhaltung U Reparatur von Automobilen Instandhaltung U",
    "sg:phone":"+41 52 625 15 16",
    "sg:postcode":"8200",
    "sg:province":"Schaffhausen",
    "wof:name":"Vespa Town V.& G.g\u00fcr & Ch.b\u00fchler",
    "wof:placetype":"venue"
},
  "geometry": {"coordinates":[8.6331062317,47.6939926147],"type":"Point"}
}