{
  "type": "Feature",
  "properties": {
    "iso:country":"CH",
    "sg:address":"Neue Stockstrasse 23",
    "sg:city":"K\u00fcttigen",
    "sg:orig_category":"Polizei",
    "sg:phone":"+41 56 441 65 00",
    "sg:postcode":"5024",
    "sg:province":"Aargau",
    "wof:name":"Kantonspolizei",
    "wof:placetype":"venue"
},
  "geometry": {"coordinates":[8.2079238892,47.4831848145],"type":"Point"}
}