{
  "type": "Feature",
  "properties": {
    "addr:full":"Baselstrasse 56a 4144 Arlesheim. Postfach Arlesheim Basel-Landschaft 4144",
    "addr:housenumber":"56a",
    "addr:postcode":"4144 arlesheim. postfach;4144",
    "addr:street":"Baselstrasse",
    "iso:country":"CH",
    "sg:address":"Baselstrasse 56a 4144 Arlesheim. Postfach",
    "sg:city":"Arlesheim",
    "sg:orig_category":"B\u00e4ckereien Herstellung von Dauerbackwaren",
    "sg:phone":"+41 61 701 73 82",
    "sg:postcode":"4144",
    "sg:province":"Basel-Landschaft",
    "wof:name":"B\u00e4cker Kiosk Gmbh",
    "wof:placetype":"venue"
},
  "geometry": {"coordinates":[7.619489,47.501884],"type":"Point"}
}