{
  "type": "Feature",
  "properties": {
    "iso:country":"CH",
    "sg:address":"Obere Gasse 17",
    "sg:city":"Baden",
    "sg:orig_category":"Herstellung von medizinischen U chirurgischen Ger\u00e4ten sowie orthop\u00e4dischen Vorrichtungen",
    "sg:phone":"+41 56 222 34 00",
    "sg:postcode":"5400",
    "sg:province":"Aargau",
    "wof:name":"Glauser Ag",
    "wof:placetype":"venue"
},
  "geometry": {"coordinates":[8.3068933487,47.4726600647],"type":"Point"}
}