{
  "type": "Feature",
  "properties": {
    "addr:full":"Allweg Kerns Obwalden 6064",
    "addr:postcode":"6064",
    "addr:street":"Allweg",
    "iso:country":"CH",
    "sg:address":"Allweg",
    "sg:city":"Kerns",
    "sg:orig_category":"Bauschreinerei",
    "sg:phone":"+41 41 660 53 92",
    "sg:postcode":"6064",
    "sg:province":"Obwalden",
    "wof:name":"Josef Von Rotz Schreinerei",
    "wof:placetype":"venue"
},
  "geometry": {"coordinates":[8.275,46.900822],"type":"Point"}
}