{
  "type": "Feature",
  "properties": {
    "iso:country":"CH",
    "sg:address":"Raaschberg",
    "sg:city":"Flawil",
    "sg:orig_category":"Detailhandel mit Uhren U Schmuck",
    "sg:phone":"+41 31 371 37 38",
    "sg:postcode":"9230",
    "sg:province":"St. Gallen",
    "wof:name":"Ueli Tr\u00f6hler Goldschmied/ Bijouterie",
    "wof:placetype":"venue"
},
  "geometry": {"coordinates":[7.4329061508,46.9420394897],"type":"Point"}
}