{
  "type": "Feature",
  "properties": {
    "iso:country":"CH",
    "sg:address":"Dorfstrasse 44",
    "sg:city":"Wislikofen",
    "sg:classifiers":[
        {
            "category":"Banks & Credit Unions",
            "subcategory":"Bank",
            "type":"Services"
        }
    ],
    "sg:phone":"+41 62 926 13 51",
    "sg:postcode":"8439",
    "wof:name":"Raiffeisenbank Wolfwil-schwarzh\u00e4usen-bannwil",
    "wof:placetype":"venue"
},
  "geometry": {"coordinates":[7.799469,47.269878],"type":"Point"}
}