{
  "type": "Feature",
  "properties": {
    "iso:country":"CH",
    "sg:address":"Route De Courgenay 36",
    "sg:city":"Porrentruy",
    "sg:orig_category":"Sportvereine Alpinismus",
    "sg:phone":"+41 32 466 67 42",
    "sg:postcode":"2900",
    "sg:province":"Jura",
    "wof:name":"Sac Section Jura",
    "wof:placetype":"venue"
},
  "geometry": {"coordinates":[7.0817050934,47.4158744812],"type":"Point"}
}