{
  "type": "Feature",
  "properties": {
    "iso:country":"CH",
    "sg:address":"Rue Du Coll\u00e8ge 1523 Granges-marnand Case Postale 55",
    "sg:city":"Granges-marnand",
    "sg:orig_category":"Herstellung von Metallkonstruktionen Sanit\u00e4r, Heizungs U L\u00fcftungsinstallation",
    "sg:phone":"+41 26 668 10 42",
    "sg:postcode":"1523",
    "sg:province":"Vaud",
    "wof:name":"Rapin Fr\u00e8res",
    "wof:placetype":"venue"
},
  "geometry": {"coordinates":[6.8873357773,46.7608222961],"type":"Point"}
}