{
  "type": "Feature",
  "properties": {
    "iso:country":"CH",
    "sg:address":"Rue Du Temple-neuf 11",
    "sg:city":"Neuch\u00e2tel",
    "sg:orig_category":"Reiseb\u00fcros",
    "sg:phone":"+41 32 724 46 86",
    "sg:postcode":"2000",
    "sg:province":"Neuch\u00e2tel",
    "wof:name":"Imholz Agences Sa",
    "wof:placetype":"venue"
},
  "geometry": {"coordinates":[6.9294710159,46.9911079407],"type":"Point"}
}