{
  "type": "Feature",
  "properties": {
    "addr:full":"Rheinstrasse 121 Liestal Basel-Landschaft 4410",
    "addr:housenumber":"121",
    "addr:postcode":"4410",
    "addr:street":"Rheinstrasse",
    "iso:country":"CH",
    "sg:address":"Rheinstrasse 121",
    "sg:city":"Liestal",
    "sg:orig_category":"Allgemeiner Hoch U Tiefbau Strassenbau",
    "sg:phone":"+41 71 333 10 72",
    "sg:postcode":"4410",
    "sg:province":"Basel-Landschaft",
    "wof:name":"Beat H\u00f6rler Ag",
    "wof:placetype":"venue"
},
  "geometry": {"coordinates":[9.362168,47.386242],"type":"Point"}
}