{
  "type": "Feature",
  "properties": {
    "iso:country":"CH",
    "sg:address":"L'ile \u00e0 Brizet",
    "sg:city":"Echandens",
    "sg:orig_category":"Sportvereine Ballsport Tennis",
    "sg:phone":"+41 21 701 21 20",
    "sg:postcode":"1026",
    "sg:province":"Vaud",
    "wof:name":"Tennis-club La Venoge",
    "wof:placetype":"venue"
},
  "geometry": {"coordinates":[6.5517730713,46.5500564575],"type":"Point"}
}