{
  "type": "Feature",
  "properties": {
    "iso:country":"CH",
    "sg:address":"Ueberlandstrasse 101",
    "sg:city":"D\u00fcbendorf",
    "sg:classifiers":[
        {
            "category":"Personal",
            "subcategory":"Sauna",
            "type":"Services"
        }
    ],
    "sg:phone":"+41 33 733 17 42",
    "sg:postcode":"8600",
    "sg:province":"Z\u00fcrich",
    "wof:name":"Doris Siegrist Sauna",
    "wof:placetype":"venue"
},
  "geometry": {"coordinates":[7.43171978,46.4701118469],"type":"Point"}
}