{
  "type": "Feature",
  "properties": {
    "iso:country":"CH",
    "sg:address":"Gr\u00fcssenh\u00f6lzliweg",
    "sg:city":"Pratteln",
    "sg:orig_category":"Betrieb von Sportanlagen",
    "sg:postcode":"4133",
    "sg:province":"Basel-Landschaft",
    "wof:name":"Genossenschaft Gr\u00fcssen",
    "wof:placetype":"venue"
},
  "geometry": {"coordinates":[7.693135,47.52853],"type":"Point"}
}