{
  "type": "Feature",
  "properties": {
    "iso:country":"CH",
    "sg:address":"Riedstrasse 8",
    "sg:city":"Dietikon",
    "sg:orig_category":"Grosshandel mit Textilien",
    "sg:phone":"+41 14001616",
    "sg:postcode":"8953",
    "sg:province":"Z\u00fcrich",
    "wof:name":"Ultra Tex Clothing Gmbh",
    "wof:placetype":"venue"
},
  "geometry": {"coordinates":[8.3944854736,47.4198493958],"type":"Point"}
}