{
  "type": "Feature",
  "properties": {
    "iso:country":"CH",
    "sg:address":"Lettenstrasse 12",
    "sg:city":"Mogelsberg",
    "sg:orig_category":"Allgemeiner Hoch U Tiefbau Hoch U Tiefbau",
    "sg:phone":"+41 71 374 27 06",
    "sg:postcode":"9122",
    "sg:province":"St. Gallen",
    "wof:name":"Binder Robert Ag",
    "wof:placetype":"venue"
},
  "geometry": {"coordinates":[9.135636,47.36013],"type":"Point"}
}