{
  "type": "Feature",
  "properties": {
    "addr:full":"Poststrasse 3 Humlikon Z\u00fcrich 8457",
    "addr:housenumber":"3",
    "addr:postcode":"8457",
    "addr:street":"Poststrasse;Zuerich",
    "iso:country":"CH",
    "sg:address":"Poststrasse 3",
    "sg:city":"Humlikon",
    "sg:orig_category":"Architektur U Ingenieurb\u00fcros Herstellung von Verbrennungsmotoren U Turbinen ohne Motoren f\u00fcr Luft U ",
    "sg:phone":"+41 52 317 40 57",
    "sg:postcode":"8457",
    "sg:province":"Z\u00fcrich",
    "wof:name":"Kaech Motors Ag",
    "wof:placetype":"venue"
},
  "geometry": {"coordinates":[8.671624,47.576271],"type":"Point"}
}