{
  "type": "Feature",
  "properties": {
    "iso:country":"CH",
    "sg:address":"4203",
    "sg:city":"Grellingen",
    "sg:orig_category":"Sportvereine Ballsport Handball",
    "sg:phone":"+41 61 741 11 56",
    "sg:postcode":"4203",
    "sg:province":"Basel-Landschaft",
    "wof:name":"Tv Grellingen",
    "wof:placetype":"venue"
},
  "geometry": {"coordinates":[7.5888900757,47.4391212463],"type":"Point"}
}