{
  "type": "Feature",
  "properties": {
    "iso:country":"CH",
    "sg:address":"Rue Des Anciens-bains 4",
    "sg:city":"Rolle",
    "sg:orig_category":"Notariate",
    "sg:phone":"+41 21 822 52 20",
    "sg:postcode":"1180",
    "sg:province":"Vaud",
    "wof:name":"Claude Bally Notaire",
    "wof:placetype":"venue"
},
  "geometry": {"coordinates":[6.3401618004,46.4601783752],"type":"Point"}
}