{
  "type": "Feature",
  "properties": {
    "iso:country":"CH",
    "sg:address":"Z\u00fcrcher Strasse 31 9427 Wolfhalden. Postfach",
    "sg:city":"St.gallen",
    "sg:classifiers":[
        {
            "category":"Travel",
            "subcategory":"Hotels & Motels",
            "type":"Entertainment"
        }
    ],
    "sg:postcode":"9000",
    "sg:province":"St. Gallen",
    "sg:tags":[
        "hotels",
        "mit",
        "restaurant"
    ],
    "wof:name":"Heimgartner-wittber Kurt",
    "wof:placetype":"venue"
},
  "geometry": {"coordinates":[9.5497522354,47.453414917],"type":"Point"}
}