{
  "type": "Feature",
  "properties": {
    "iso:country":"CH",
    "sg:address":"M\u00e4dergutstrasse 61",
    "sg:city":"Bern",
    "sg:orig_category":"Non-Classified Establishments",
    "sg:postcode":"3018",
    "sg:province":"Bern",
    "wof:name":"Marmex Gmbh",
    "wof:placetype":"venue"
},
  "geometry": {"coordinates":[7.3846268654,46.9379806519],"type":"Point"}
}