{
  "type": "Feature",
  "properties": {
    "iso:country":"CH",
    "sg:address":"Z\u00fcrcherstrasse 59",
    "sg:city":"Tagelswangen",
    "sg:classifiers":[
        {
            "category":"Retail",
            "subcategory":"Repair Shop",
            "type":"Services"
        }
    ],
    "sg:phone":"+41 52 343 21 21",
    "sg:postcode":"8317",
    "sg:province":"Z\u00fcrich",
    "sg:tags":[
        "machine",
        "bookbinding"
    ],
    "wof:name":"W. Gantenbein",
    "wof:placetype":"venue"
},
  "geometry": {"coordinates":[8.66749,47.430668],"type":"Point"}
}