{
  "type": "Feature",
  "properties": {
    "iso:country":"CH",
    "sg:address":"Trevano Via 4",
    "sg:city":"Lugano",
    "sg:orig_category":"Detailhandel mit M\u00f6beln U Haushaltsgegenst\u00e4nden",
    "sg:phone":"+41 91 971 08 10",
    "sg:postcode":"6900",
    "sg:province":"Ticino",
    "wof:name":"Ferrari Aurelio",
    "wof:placetype":"venue"
},
  "geometry": {"coordinates":[8.9552078247,46.0130233765],"type":"Point"}
}