{
  "type": "Feature",
  "properties": {
    "iso:country":"CH",
    "sg:address":"Museumstrasse 3 6060 Sarnen. Postfach 34",
    "sg:city":"Sarnen",
    "sg:orig_category":"Versicherungen Hauptagenturen",
    "sg:phone":"+41 41 660 73 20",
    "sg:postcode":"6060",
    "sg:province":"Obwalden",
    "wof:name":"Basler Versicherungen Hauptagentur Obwalden",
    "wof:placetype":"venue"
},
  "geometry": {"coordinates":[8.2475309372,46.8981056213],"type":"Point"}
}