{
  "type": "Feature",
  "properties": {
    "iso:country":"CH",
    "sg:address":"Kapellgasse 22",
    "sg:city":"Luzern",
    "sg:orig_category":"RESTAURANTS: TEA-ROOMS",
    "sg:phone":"+41 71 222 75 01",
    "sg:postcode":"6004",
    "sg:province":"Luzern",
    "wof:name":"Restaurant Goldener Ochsen",
    "wof:placetype":"venue"
},
  "geometry": {"coordinates":[9.3659591675,47.418170929],"type":"Point"}
}