{
  "type": "Feature",
  "properties": {
    "iso:country":"CH",
    "sg:address":"St. Alban-rheinweg 244",
    "sg:city":"Basel",
    "sg:orig_category":"Elektrizit\u00e4tsversorgung",
    "sg:phone":"+41 61 312 80 59",
    "sg:postcode":"4052",
    "sg:province":"Basel-Stadt",
    "wof:name":"Mangold Abwasser Und Bel\u00fcftungssysteme Ag",
    "wof:placetype":"venue"
},
  "geometry": {"coordinates":[7.6149010658,47.5569915771],"type":"Point"}
}