{
  "type": "Feature",
  "properties": {
    "iso:country":"CH",
    "sg:address":"Oberlandstrasse 68",
    "sg:city":"Uster",
    "sg:orig_category":"Sportvereine Unihockey",
    "sg:postcode":"8610",
    "sg:province":"Z\u00fcrich",
    "wof:name":"Uhc Oetwil-geroldswil",
    "wof:placetype":"venue"
},
  "geometry": {"coordinates":[8.4348802567,47.419719696],"type":"Point"}
}