{
  "type": "Feature",
  "properties": {
    "iso:country":"CH",
    "sg:address":"T\u00f6sstalstrasse 44",
    "sg:city":"Turbenthal",
    "sg:orig_category":"Detailhandel mit Geschenkartikeln U Souvenirs Herstellung von sonstigen Erzeugnissen",
    "sg:phone":"+41 52 385 56 18",
    "sg:postcode":"8488",
    "sg:province":"Z\u00fcrich",
    "wof:name":"Gabriela Steiner Zwergenl\u00e4deli & Geschenkbout.",
    "wof:placetype":"venue"
},
  "geometry": {"coordinates":[8.8433456421,47.4402122498],"type":"Point"}
}