{
  "type": "Feature",
  "properties": {
    "iso:country":"CH",
    "sg:address":"Waagtalstrasse 8",
    "sg:city":"Unteriberg",
    "sg:orig_category":"Malerei",
    "sg:phone":"+41 79 407 49 68",
    "sg:postcode":"8842",
    "sg:province":"Schwyz",
    "wof:name":"Hans-rudolf Frauenfelder Malergesch\u00e4ft",
    "wof:placetype":"venue"
},
  "geometry": {"coordinates":[8.8014717102,47.0587387085],"type":"Point"}
}