{
  "type": "Feature",
  "properties": {
    "iso:country":"CH",
    "sg:address":"B\u00fcndtetalweg 28",
    "sg:city":"Obermumpf",
    "sg:orig_category":"Erdbewegungsarbeiten",
    "sg:phone":"+423 373 17 14",
    "sg:postcode":"4324",
    "sg:province":"Aargau",
    "wof:name":"Josef Meier Baggerbetrieb",
    "wof:placetype":"venue"
},
  "geometry": {"coordinates":[9.541352272,47.2190284729],"type":"Point"}
}