{
  "type": "Feature",
  "properties": {
    "iso:country":"CH",
    "sg:address":"Kapplerstrasse 19",
    "sg:city":"Ebnat",
    "sg:orig_category":"Betrieb von Taxis K\u00fcnstlerische U schriftstellerische T\u00e4tigkeiten U Darbietungen",
    "sg:phone":"+41 71 993 19 89",
    "sg:postcode":"9642",
    "sg:province":"St. Gallen",
    "wof:name":"Menzi Ulrich.",
    "wof:placetype":"venue"
},
  "geometry": {"coordinates":[9.120078,47.265434],"type":"Point"}
}