{
  "type": "Feature",
  "properties": {
    "iso:country":"CH",
    "sg:address":"Seefeldquai 17 8008 Z\u00fcrich. Postfach",
    "sg:city":"Z\u00fcrich",
    "sg:orig_category":"Non-Classified Establishments",
    "sg:phone":"+41 13886161",
    "sg:postcode":"8001",
    "sg:province":"Z\u00fcrich",
    "wof:name":"Platina Finanz Ag Beteiligungen, Bes. An Banken, Finanzinstitute Usw",
    "wof:placetype":"venue"
},
  "geometry": {"coordinates":[8.5478124619,47.3596954346],"type":"Point"}
}