{
  "type": "Feature",
  "properties": {
    "addr:full":"M\u00fcnsterhof 17/ K\u00e4mbelgasse 6 8001 Z\u00fcrich. Postfach Z\u00fcrich Z\u00fcrich 8001",
    "addr:housenumber":"17 /;6",
    "addr:postcode":"8001 zuerich. postfach;8001",
    "addr:street":"Muensterhof;Kaembelgasse",
    "iso:country":"CH",
    "sg:address":"M\u00fcnsterhof 17/ K\u00e4mbelgasse 6 8001 Z\u00fcrich. Postfach",
    "sg:city":"Z\u00fcrich",
    "sg:orig_category":"Banken sonstige",
    "sg:postcode":"8001",
    "sg:province":"Z\u00fcrich",
    "wof:name":"Mirabaud & Cie, Zweigniederlassung Z\u00fcrich",
    "wof:placetype":"venue"
},
  "geometry": {"coordinates":[8.53955,47.37706],"type":"Point"}
}