{
  "type": "Feature",
  "properties": {
    "addr:full":"Bahnhofstrasse 6 Klosters Graubunden 7250",
    "addr:housenumber":"6",
    "addr:postcode":"7250",
    "addr:street":"Bahnhofstrasse",
    "iso:country":"CH",
    "sg:address":"Bahnhofstrasse 6",
    "sg:city":"Klosters",
    "sg:orig_category":"Advokaturb\u00fcros Notariate",
    "sg:phone":"+41 81 422 38 22",
    "sg:postcode":"7250",
    "sg:province":"Graubunden",
    "wof:name":"Christian Clopath Advokatur-& Notariatsb\u00fcro",
    "wof:placetype":"venue"
},
  "geometry": {"coordinates":[9.881655,46.868404],"type":"Point"}
}