{
  "type": "Feature",
  "properties": {
    "iso:country":"CH",
    "sg:address":"Aeuss. Kanalstr. 31",
    "sg:city":"Niederg\u00f6sgen",
    "sg:classifiers":[
        {
            "category":"Manufacturing",
            "subcategory":"Motor Vehicles & Parts",
            "type":"Manufacturing & Wholesale Goods"
        }
    ],
    "sg:phone":"+41 62 858 30 80",
    "sg:postcode":"5013",
    "sg:province":"Solothurn",
    "sg:tags":[
        "engine",
        "machine",
        "engineering",
        "-",
        "mechanical"
    ],
    "wof:name":"Kaufmann Ag Elektromotorenbau",
    "wof:placetype":"venue"
},
  "geometry": {"coordinates":[7.9894609451,47.3675918579],"type":"Point"}
}