{
  "type": "Feature",
  "properties": {
    "iso:country":"CH",
    "sg:address":"Bahnhofstrasse 5",
    "sg:city":"Lenzburg",
    "sg:orig_category":"Reparatur von Schuhen U Lederwaren",
    "sg:phone":"+41 62 891 80 61",
    "sg:postcode":"5600",
    "sg:province":"Aargau",
    "wof:name":"Beat Simmen Schuh-& Schl\u00fcsselservice",
    "wof:placetype":"venue"
},
  "geometry": {"coordinates":[8.1773414612,47.3880844116],"type":"Point"}
}