{
  "type": "Feature",
  "properties": {
    "iso:country":"CH",
    "sg:address":"Wiesenbergstrasse 12",
    "sg:city":"Dallenwil",
    "sg:orig_category":"Abbruch U Sprenggewerbe, Erdbewegungsarbeiten",
    "sg:phone":"+41 79 606 86 18",
    "sg:postcode":"6383",
    "sg:province":"Nidwalden",
    "wof:name":"Ch. Berlinger Ag",
    "wof:placetype":"venue"
},
  "geometry": {"coordinates":[8.388126,46.926414],"type":"Point"}
}