{
  "type": "Feature",
  "properties": {
    "iso:country":"CH",
    "sg:address":"Fischingerstrasse 66 8370 Sirnach. Postfach 108",
    "sg:city":"Sirnach",
    "sg:orig_category":"Film U Videofilmherstellung Vervielf\u00e4ltigung von bespielten Bildtr\u00e4gern",
    "sg:phone":"+41 71 966 66 66",
    "sg:postcode":"8370",
    "sg:province":"Thurgau",
    "wof:name":"Merlin Production Gmbh Videokopierwerk & Cd Kopierwerk",
    "wof:placetype":"venue"
},
  "geometry": {"coordinates":[8.9885787964,47.4575653076],"type":"Point"}
}