{
  "type": "Feature",
  "properties": {
    "iso:country":"CH",
    "sg:address":"1906",
    "sg:city":"Charrat",
    "sg:orig_category":"Herstellung von sonstigen landwirtschaftlichen Maschinen",
    "sg:postcode":"1906",
    "sg:province":"Valais",
    "wof:name":"Chapuis Alain",
    "wof:placetype":"venue"
},
  "geometry": {"coordinates":[6.7701849937,46.5957489014],"type":"Point"}
}