{
  "type": "Feature",
  "properties": {
    "addr:full":"Fistel Fischenthal Z\u00fcrich 8497",
    "addr:postcode":"8497",
    "iso:country":"CH",
    "sg:address":"Fistel",
    "sg:city":"Fischenthal",
    "sg:orig_category":"Baugewerbe",
    "sg:phone":"+41 55 245 20 46",
    "sg:postcode":"8497",
    "sg:province":"Z\u00fcrich",
    "wof:name":"Mostra Montagen",
    "wof:placetype":"venue"
},
  "geometry": {"coordinates":[8.92173,47.326111],"type":"Point"}
}