{
  "type": "Feature",
  "properties": {
    "iso:country":"CH",
    "sg:address":"Rue Des Bouchers 10 1700 Fribourg Case Postale 105",
    "sg:city":"Fribourg",
    "sg:classifiers":[
        {
            "category":"Government",
            "subcategory":"Post Office",
            "type":"Public Place"
        }
    ],
    "sg:phone":"+41 27 952 12 54",
    "sg:postcode":"1702",
    "sg:province":"Fribourg",
    "sg:tags":[
        "caf\u00e9s",
        "tea-rooms"
    ],
    "wof:name":"Tea-room Central",
    "wof:placetype":"venue"
},
  "geometry": {"coordinates":[7.8664298058,46.2315216064],"type":"Point"}
}