{
  "type": "Feature",
  "properties": {
    "iso:country":"CH",
    "sg:address":"Neuhusstrasse 11 8633 Wolfhausen. Postfach",
    "sg:city":"Wolfhausen",
    "sg:orig_category":"Bauspenglerei Sanit\u00e4rinstallation",
    "sg:phone":"+41 55 243 17 26",
    "sg:postcode":"8633",
    "sg:province":"Z\u00fcrich",
    "wof:name":"Peterer Josef Haustechnik Ag",
    "wof:placetype":"venue"
},
  "geometry": {"coordinates":[8.801215,47.257175],"type":"Point"}
}