{
  "type": "Feature",
  "properties": {
    "iso:country":"CH",
    "sg:address":"Primelweg 16",
    "sg:city":"Flawil",
    "sg:orig_category":"Sonstiger Grosshandel",
    "sg:phone":"+41 71 222 08 08",
    "sg:postcode":"9230",
    "sg:province":"St. Gallen",
    "wof:name":"Pinares Gmbh",
    "wof:placetype":"venue"
},
  "geometry": {"coordinates":[9.1725282669,47.413269043],"type":"Point"}
}