{
  "type": "Feature",
  "properties": {
    "iso:country":"CH",
    "sg:address":"6746",
    "sg:city":"Lavorgo",
    "sg:orig_category":"Sanit\u00e4r, Heizungs U L\u00fcftungsinstallation",
    "sg:postcode":"6746",
    "sg:province":"Ticino",
    "wof:name":"L'artigiano Martella Luigi Sagl",
    "wof:placetype":"venue"
},
  "geometry": {"coordinates":[8.840929985,46.440448761],"type":"Point"}
}