{
  "type": "Feature",
  "properties": {
    "iso:country":"CH",
    "sg:address":"Schwerzlen",
    "sg:city":"Inwil",
    "sg:orig_category":"Verwertung von Milch",
    "sg:postcode":"6034",
    "sg:province":"Luzern",
    "wof:name":"Milchverwertungsgenossenschaft Butwil",
    "wof:placetype":"venue"
},
  "geometry": {"coordinates":[8.3672504425,47.1376342773],"type":"Point"}
}