{
  "type": "Feature",
  "properties": {
    "iso:country":"CH",
    "sg:address":"Rue J.-j.-lallemand 11",
    "sg:city":"Neuch\u00e2tel",
    "sg:orig_category":"Arztpraxen",
    "sg:phone":"+41 32 725 43 43",
    "sg:postcode":"2000",
    "sg:province":"Neuch\u00e2tel",
    "wof:name":"Dr M\u00e9d. Jean-marc Burgat M\u00e9decin Sp\u00e9cialiste Fmh",
    "wof:placetype":"venue"
},
  "geometry": {"coordinates":[6.935882,46.992165],"type":"Point"}
}