{
  "type": "Feature",
  "properties": {
    "iso:country":"CH",
    "sg:address":"Im Loch 2",
    "sg:city":"Rumisberg",
    "sg:orig_category":"Zimmerei, Dachdeckerei, Bauspenglerei U Abdichtung",
    "sg:postcode":"4539",
    "sg:province":"Bern",
    "wof:name":"Holzarbeiten Und Umbauten Ischi Ernst",
    "wof:placetype":"venue"
},
  "geometry": {"coordinates":[7.6417651176,47.2617950439],"type":"Point"}
}