{
  "type": "Feature",
  "properties": {
    "addr:full":"Chemin Vignes 16 Lugnorre Fribourg 1789",
    "addr:housenumber":"16",
    "addr:postcode":"1789",
    "addr:street":"Chemin Vignes",
    "iso:country":"CH",
    "sg:address":"Chemin Vignes 16",
    "sg:city":"Lugnorre",
    "sg:classifiers":[
        {
            "category":"Banks & Credit Unions",
            "subcategory":"Bank",
            "type":"Services"
        }
    ],
    "sg:phone":"+41 37732230",
    "sg:postcode":"1789",
    "sg:province":"Fribourg",
    "wof:name":"Rentenanstalt Swiss Life",
    "wof:placetype":"venue"
},
  "geometry": {"coordinates":[7.082371,46.947933],"type":"Point"}
}