{
  "type": "Feature",
  "properties": {
    "iso:country":"CH",
    "sg:address":"Neustadtgasse 1",
    "sg:city":"Z\u00fcrich",
    "sg:orig_category":"Kunsthandel",
    "sg:phone":"+41 12524060",
    "sg:postcode":"8001",
    "sg:province":"Z\u00fcrich",
    "wof:name":"Werner Frei Galerie Trittligasse",
    "wof:placetype":"venue"
},
  "geometry": {"coordinates":[8.5453901291,47.3697090149],"type":"Point"}
}