{
  "type": "Feature",
  "properties": {
    "iso:country":"CH",
    "sg:address":"Sch\u00f6nenstrasse 39",
    "sg:city":"R\u00fcschlikon",
    "sg:orig_category":"Sportvereine Fechten",
    "sg:phone":"+41 17240122",
    "sg:postcode":"8803",
    "sg:province":"Z\u00fcrich",
    "wof:name":"Fechtclub Z\u00fcrich-oberland",
    "wof:placetype":"venue"
},
  "geometry": {"coordinates":[8.5513687134,47.3138198853],"type":"Point"}
}