{
  "type": "Feature",
  "properties": {
    "iso:country":"CH",
    "sg:address":"Via Serafino Balestra 27 6900 Lugano. Postfach",
    "sg:city":"Lugano",
    "sg:orig_category":"Non-Classified Establishments",
    "sg:postcode":"6900",
    "sg:province":"Ticino",
    "wof:name":"Green Dream Gmbh",
    "wof:placetype":"venue"
},
  "geometry": {"coordinates":[7.5996518135,47.4736175537],"type":"Point"}
}