{
  "type": "Feature",
  "properties": {
    "addr:full":"Seefeldstrasse 134 Z\u00fcrich Z\u00fcrich 8008",
    "addr:housenumber":"134",
    "addr:postcode":"8008",
    "addr:street":"Seefeldstrasse",
    "iso:country":"CH",
    "sg:address":"Seefeldstrasse 134",
    "sg:city":"Z\u00fcrich",
    "sg:orig_category":"Detailhandel mit Blumen U Pflanzen",
    "sg:phone":"+41 13830626",
    "sg:postcode":"8008",
    "sg:province":"Z\u00fcrich",
    "wof:name":"Blumen Art, Weber Rosmarie Blumengesch\u00e4ft",
    "wof:placetype":"venue"
},
  "geometry": {"coordinates":[8.554447,47.357468],"type":"Point"}
}