{
  "type": "Feature",
  "properties": {
    "iso:country":"CH",
    "sg:address":"Gr\u00fcngasse 27 8004 Z\u00fcrich. Postfach",
    "sg:city":"Z\u00fcrich",
    "sg:orig_category":"Herstellung von Spielwaren",
    "sg:postcode":"8001",
    "sg:province":"Z\u00fcrich",
    "wof:name":"Corotech Balmer Roger",
    "wof:placetype":"venue"
},
  "geometry": {"coordinates":[8.9986572266,47.4736595154],"type":"Point"}
}