{
  "type": "Feature",
  "properties": {
    "iso:country":"CH",
    "sg:address":"Gutstrasse 12",
    "sg:city":"Z\u00fcrich",
    "sg:orig_category":"W\u00e4scherei U chemische Reinigung",
    "sg:phone":"+41 14632150",
    "sg:postcode":"8055",
    "sg:province":"Z\u00fcrich",
    "wof:name":"Henzel Kleiderreinigungen Ag Birmensdorferstrasse",
    "wof:placetype":"venue"
},
  "geometry": {"coordinates":[8.5089321136,47.3707542419],"type":"Point"}
}