{
  "type": "Feature",
  "properties": {
    "iso:country":"CH",
    "sg:address":"Industriestrasse 9",
    "sg:city":"W\u00fcrenlingen",
    "sg:orig_category":"Allgemeiner Hoch U Tiefbau",
    "sg:phone":"+41 56 281 18 14",
    "sg:postcode":"5303",
    "sg:province":"Aargau",
    "wof:name":"Birchmeier Urs",
    "wof:placetype":"venue"
},
  "geometry": {"coordinates":[8.234877,47.525047],"type":"Point"}
}