{
  "type": "Feature",
  "properties": {
    "iso:country":"CH",
    "sg:address":"Bauerngasse 19",
    "sg:city":"Laufen",
    "sg:orig_category":"Binnenschiffahrt",
    "sg:phone":"+41 61 763 95 40",
    "sg:postcode":"4242",
    "sg:province":"Basel-Landschaft",
    "wof:name":"Charterboat-ferien, Thommen E. + M. Ag",
    "wof:placetype":"venue"
},
  "geometry": {"coordinates":[7.501042,47.422878],"type":"Point"}
}