{
  "type": "Feature",
  "properties": {
    "iso:country":"CH",
    "sg:address":"1997",
    "sg:city":"Haute-nendaz",
    "sg:classifiers":[
        {
            "category":"Government",
            "subcategory":"Post Office",
            "type":"Public Place"
        }
    ],
    "sg:phone":"+41 27 288 23 21",
    "sg:postcode":"1997",
    "sg:province":"Valais",
    "sg:tags":[
        "caf\u00e9s",
        "tea-rooms"
    ],
    "wof:name":"Tea-room Oiseau Bleu",
    "wof:placetype":"venue"
},
  "geometry": {"coordinates":[7.2981100082,46.1841506958],"type":"Point"}
}