{
  "type": "Feature",
  "properties": {
    "iso:country":"CH",
    "sg:address":"Holderstrasse 15 4057 Basel. Postfach",
    "sg:city":"Basel",
    "sg:orig_category":"Grosshandel mit Holz U Baustoffen",
    "sg:phone":"+41 61 631 11 20",
    "sg:postcode":"4051",
    "sg:province":"Basel-Stadt",
    "wof:name":"Schmidt S\u00f6hne Ag Holzhandelsgesch\u00e4ft, Hobelwerk",
    "wof:placetype":"venue"
},
  "geometry": {"coordinates":[7.5902671814,47.5762748718],"type":"Point"}
}