{
  "type": "Feature",
  "properties": {
    "iso:country":"CH",
    "sg:address":"Lavaterstrasse 61",
    "sg:city":"Z\u00fcrich",
    "sg:orig_category":"Wirtschaftspr\u00fcfung, Steuerberatung U Treuhand",
    "sg:phone":"+41 41 410 01 20",
    "sg:postcode":"8002",
    "sg:province":"Z\u00fcrich",
    "wof:name":"Sintrag Treuhand Luzern Ag",
    "wof:placetype":"venue"
},
  "geometry": {"coordinates":[8.3057079315,47.0529098511],"type":"Point"}
}