{
  "type": "Feature",
  "properties": {
    "iso:country":"CH",
    "sg:address":"Bahnhofstrasse 28",
    "sg:city":"Effretikon",
    "sg:classifiers":[
        {
            "category":"Professional",
            "subcategory":"Computer Services",
            "type":"Services"
        }
    ],
    "sg:phone":"+41 52 347 01 23",
    "sg:postcode":"8307",
    "sg:province":"Z\u00fcrich",
    "sg:tags":[
        "development",
        "software"
    ],
    "wof:name":"Eurolink Software-entwicklung",
    "wof:placetype":"venue"
},
  "geometry": {"coordinates":[8.6870679855,47.4269256592],"type":"Point"}
}