{
  "type": "Feature",
  "properties": {
    "iso:country":"CH",
    "sg:address":"Chalet La Rocaille",
    "sg:city":"Eysins",
    "sg:orig_category":"Detailhandel mit Uhren U Schmuck",
    "sg:phone":"+41 22 361 56 60",
    "sg:postcode":"1262",
    "sg:province":"Vaud",
    "wof:name":"Renate Bramaz Atelier Bijouterie",
    "wof:placetype":"venue"
},
  "geometry": {"coordinates":[6.2057700157,46.3805732727],"type":"Point"}
}