{
  "type": "Feature",
  "properties": {
    "iso:country":"CH",
    "sg:address":"M\u00fchlebachstrasse 32",
    "sg:city":"Z\u00fcrich",
    "sg:orig_category":"Fachdetailhandel in Verkaufsr\u00e4umen",
    "sg:postcode":"8008",
    "sg:province":"Z\u00fcrich",
    "wof:name":"Euroflor 2000 Gmbh",
    "wof:placetype":"venue"
},
  "geometry": {"coordinates":[8.4384937286,47.0824775696],"type":"Point"}
}