{
  "type": "Feature",
  "properties": {
    "iso:country":"CH",
    "sg:address":"Schl\u00f6sslistrasse 11",
    "sg:city":"W\u00fcnnewil",
    "sg:orig_category":"Vorschulen, Kinderg\u00e4rten",
    "sg:postcode":"3184",
    "sg:province":"Fribourg",
    "wof:name":"Kindergarten Schl\u00f6ssli",
    "wof:placetype":"venue"
},
  "geometry": {"coordinates":[7.2776770592,46.8727531433],"type":"Point"}
}