{
  "type": "Feature",
  "properties": {
    "iso:country":"CH",
    "sg:address":"Grossackerstrasse 100",
    "sg:city":"Z\u00fcrich",
    "sg:orig_category":"K\u00fcnstlerische U schriftstellerische T\u00e4tigkeiten U Darbietungen",
    "sg:postcode":"8041",
    "sg:province":"Z\u00fcrich",
    "wof:name":"Lakotahae Casanova Indianisch. Handwerk; Imp., Handel",
    "wof:placetype":"venue"
},
  "geometry": {"coordinates":[8.5095252991,47.3247795105],"type":"Point"}
}