{
  "type": "Feature",
  "properties": {
    "addr:full":"Seeblickstrasse 11b T\u00e4gerwilen Thurgau 8274",
    "addr:housenumber":"11b taegerwilen",
    "addr:postcode":"8274",
    "addr:street":"Seeblickstrasse",
    "iso:country":"CH",
    "sg:address":"Seeblickstrasse 11b",
    "sg:city":"T\u00e4gerwilen",
    "sg:orig_category":"Architektur U Ingenieurb\u00fcros",
    "sg:postcode":"8274",
    "sg:province":"Thurgau",
    "wof:name":"M.i.t.c. Maintenance & It-center Gmbh",
    "wof:placetype":"venue"
},
  "geometry": {"coordinates":[9.125922,47.654175],"type":"Point"}
}