{
  "type": "Feature",
  "properties": {
    "iso:country":"CH",
    "sg:address":"Stockhornstrasse 22",
    "sg:city":"Zollikofen",
    "sg:orig_category":"Verlagsgewerbe",
    "sg:phone":"+41 31 914 03 14",
    "sg:postcode":"3052",
    "sg:province":"Bern",
    "wof:name":"Berge-magazin C/o Dr.peter Meyer",
    "wof:placetype":"venue"
},
  "geometry": {"coordinates":[7.4479122162,47.0005607605],"type":"Point"}
}