{
  "type": "Feature",
  "properties": {
    "iso:country":"CH",
    "sg:address":"Via Salens 21",
    "sg:city":"Bonaduz",
    "sg:orig_category":"Sportvereine Triathlon Laufen, Schwimmen, Velo",
    "sg:phone":"+41 81 641 22 72",
    "sg:postcode":"7402",
    "sg:province":"Graubunden",
    "wof:name":"Lg Bonaduz Triathlon",
    "wof:placetype":"venue"
},
  "geometry": {"coordinates":[9.4056940079,46.8110313416],"type":"Point"}
}