{
  "type": "Feature",
  "properties": {
    "iso:country":"CH",
    "sg:address":"Baslerstrasse 42",
    "sg:city":"Bottmingen",
    "sg:orig_category":"Wohnheime",
    "sg:phone":"+41 61 421 84 60",
    "sg:postcode":"4103",
    "sg:province":"Basel-Landschaft",
    "wof:name":"Wohnheim F\u00fcr Asylbewerber",
    "wof:placetype":"venue"
},
  "geometry": {"coordinates":[7.5731887817,47.5260238647],"type":"Point"}
}