{
  "type": "Feature",
  "properties": {
    "iso:country":"CH",
    "sg:address":"Louisenbergstrasse 7",
    "sg:city":"Mannenbach-salenst",
    "sg:orig_category":"Allgemeiner Hoch U Tiefbau Hoch U Tiefbau",
    "sg:phone":"+41 71 664 18 86",
    "sg:postcode":"8268",
    "sg:province":"Thurgau",
    "wof:name":"Keller-hagmann Robert",
    "wof:placetype":"venue"
},
  "geometry": {"coordinates":[9.055097,47.673397],"type":"Point"}
}