{
  "type": "Feature",
  "properties": {
    "iso:country":"CH",
    "sg:address":"K\u00e4pfnerweg 2",
    "sg:city":"Horgen",
    "sg:orig_category":"Dienstleistungen von Beteiligungsgesellschaften Verwaltung von Immobilien",
    "sg:phone":"+41 17254222",
    "sg:postcode":"8810",
    "sg:province":"Z\u00fcrich",
    "wof:name":"Bruppacher Verwaltungs Ag",
    "wof:placetype":"venue"
},
  "geometry": {"coordinates":[8.6158952713,47.2540740967],"type":"Point"}
}