{
  "type": "Feature",
  "properties": {
    "iso:country":"CH",
    "sg:address":"6537",
    "sg:city":"Grono",
    "sg:classifiers":[
        {
            "category":"Bars & Pubs",
            "type":"Food & Drink"
        }
    ],
    "sg:phone":"+41 91 827 29 66",
    "sg:postcode":"6537",
    "sg:province":"Graubunden",
    "wof:name":"Bar Centrale",
    "wof:placetype":"venue"
},
  "geometry": {"coordinates":[9.146434,46.247814],"type":"Point"}
}