{
  "type": "Feature",
  "properties": {
    "iso:country":"CH",
    "sg:address":"Emmentalstrasse 32",
    "sg:city":"Oberburg",
    "sg:orig_category":"Nationale Postdienste",
    "sg:phone":"+41 34 422 10 26",
    "sg:postcode":"3414",
    "sg:province":"Bern",
    "wof:name":"Die Schweizerische Post",
    "wof:placetype":"venue"
},
  "geometry": {"coordinates":[7.6252231598,47.0396003723],"type":"Point"}
}