{
  "type": "Feature",
  "properties": {
    "iso:country":"CH",
    "sg:address":"Richtersmattweg 2",
    "sg:city":"Sch\u00fcpfen",
    "sg:orig_category":"Instandhaltung U Reparatur von Automobilen",
    "sg:phone":"+41 31 879 00 20",
    "sg:postcode":"3054",
    "sg:province":"Bern",
    "wof:name":"Toni Aeberhard Carrosserie",
    "wof:placetype":"venue"
},
  "geometry": {"coordinates":[7.3821592331,47.0444450378],"type":"Point"}
}