{
  "type": "Feature",
  "properties": {
    "iso:country":"CH",
    "sg:address":"Route De Vevey 165 1616 Attalens. Postfach",
    "sg:city":"Attalens",
    "sg:orig_category":"S\u00e4ge, Hobel U Holzimpr\u00e4gnierwerke",
    "sg:postcode":"1616",
    "sg:province":"Fribourg",
    "wof:name":"S.c. Atelier De Polissage Or/acier, Fernandes Dos Santon & Coelho",
    "wof:placetype":"venue"
},
  "geometry": {"coordinates":[6.8215551376,47.098072052],"type":"Point"}
}