{
  "type": "Feature",
  "properties": {
    "iso:country":"CH",
    "sg:address":"Rue Des Remparts 3",
    "sg:city":"Yverdon-les-bains",
    "sg:orig_category":"Detailhandel Reparatur von Gebrauchsg\u00fctern Vermietung von Gebrauchsg\u00fctern",
    "sg:phone":"+41 24 426 43 40",
    "sg:postcode":"1400",
    "sg:province":"Vaud",
    "wof:name":"Vid\u00e9o Folies, Olivier Ischy",
    "wof:placetype":"venue"
},
  "geometry": {"coordinates":[6.6413650513,46.7793121338],"type":"Point"}
}