{
  "type": "Feature",
  "properties": {
    "iso:country":"CH",
    "sg:address":"Bundesplatz 1 6300 Zug. Postfach 4358",
    "sg:city":"Zug",
    "sg:orig_category":"Architektur U Ingenieurb\u00fcros",
    "sg:phone":"+41 41 710 40 05",
    "sg:postcode":"6304",
    "sg:province":"Zug",
    "wof:name":"Kenny J.p. Corporation Ag",
    "wof:placetype":"venue"
},
  "geometry": {"coordinates":[8.515575,47.170635],"type":"Point"}
}