{
  "type": "Feature",
  "properties": {
    "iso:country":"CH",
    "sg:address":"Grand-rue 6",
    "sg:city":"Rolle",
    "sg:orig_category":"Verkehrs- and Tourismusb\u00fcros",
    "sg:phone":"+41 21 825 15 35",
    "sg:postcode":"1180",
    "sg:province":"Vaud",
    "wof:name":"Office Du Tourisme",
    "wof:placetype":"venue"
},
  "geometry": {"coordinates":[6.3412761688,46.460609436],"type":"Point"}
}