{
  "type": "Feature",
  "properties": {
    "iso:country":"CH",
    "sg:address":"1564",
    "sg:city":"Domdidier",
    "sg:orig_category":"Detailhandel mit Uhren U Schmuck Fachdetailhandel in Verkaufsr\u00e4umen",
    "sg:phone":"+41 26 675 21 36",
    "sg:postcode":"1564",
    "sg:province":"Fribourg",
    "wof:name":"Gachoud Michel",
    "wof:placetype":"venue"
},
  "geometry": {"coordinates":[7.0151348114,46.8653068542],"type":"Point"}
}