{
  "type": "Feature",
  "properties": {
    "iso:country":"CH",
    "sg:address":"Chemin De Primerose 6",
    "sg:city":"Lausanne",
    "sg:orig_category":"Verlegen von Fliesen U Platten",
    "sg:phone":"+41 21 616 93 87",
    "sg:postcode":"1007",
    "sg:province":"Vaud",
    "wof:name":"Giovanni Saccomano Entreprise De Carrelage",
    "wof:placetype":"venue"
},
  "geometry": {"coordinates":[6.6167998314,46.5147476196],"type":"Point"}
}