{
  "type": "Feature",
  "properties": {
    "iso:country":"CH",
    "sg:address":"Eichholzstrasse 28-30 9436 Balgach. Postfach 148",
    "sg:city":"Balgach",
    "sg:orig_category":"Grosshandel mit Textilien Stickerei",
    "sg:phone":"+41 71 931 12 43",
    "sg:postcode":"9436",
    "sg:province":"St. Gallen",
    "wof:name":"Keller Alfred Stickerei",
    "wof:placetype":"venue"
},
  "geometry": {"coordinates":[9.0613527298,47.3796081543],"type":"Point"}
}