{
  "type": "Feature",
  "properties": {
    "iso:country":"CH",
    "sg:address":"B\u00fchlwiesenstrasse 17",
    "sg:city":"N\u00fcrensdorf",
    "sg:orig_category":"Sanit\u00e4r, Heizungs U L\u00fcftungsinstallation Sanit\u00e4rinstallation",
    "sg:phone":"+41 18366383",
    "sg:postcode":"8309",
    "sg:province":"Z\u00fcrich",
    "wof:name":"Sch\u00e4ppi & Meier Ag",
    "wof:placetype":"venue"
},
  "geometry": {"coordinates":[8.6441907883,47.4469528198],"type":"Point"}
}