{
  "type": "Feature",
  "properties": {
    "iso:country":"CH",
    "sg:address":"Grand-lancy Route Du 41 1212 Grand-lancy Case Postale",
    "sg:city":"Grand-lancy",
    "sg:orig_category":"Fernmeldedienste",
    "sg:phone":"+41 22 705 11 11",
    "sg:postcode":"1212",
    "sg:province":"Gen\u00e8ve",
    "wof:name":"T\u00e9l\u00e9lancy Sa",
    "wof:placetype":"venue"
},
  "geometry": {"coordinates":[6.1220579147,46.1839103699],"type":"Point"}
}