{
  "type": "Feature",
  "properties": {
    "iso:country":"CH",
    "sg:address":"6982",
    "sg:city":"Agno",
    "sg:orig_category":"Grosshandel mit B\u00fcromaschinen Herstellung von sonstigen Waren aus Papier, Karton U Pappe",
    "sg:phone":"+41 91 605 21 50",
    "sg:postcode":"6982",
    "sg:province":"Ticino",
    "wof:name":"Incomsa Sa",
    "wof:placetype":"venue"
},
  "geometry": {"coordinates":[8.8993301392,45.9967536926],"type":"Point"}
}