{
  "type": "Feature",
  "properties": {
    "iso:country":"CH",
    "sg:address":"M\u00fchlegasse 20.",
    "sg:city":"Olten",
    "sg:orig_category":"RESTAURANTS: TEA-ROOMS",
    "sg:phone":"+41 62 212 88 01",
    "sg:postcode":"4600",
    "sg:province":"Solothurn",
    "wof:name":"Restaurant Zur Alten Post Stapfer Patrice",
    "wof:placetype":"venue"
},
  "geometry": {"coordinates":[7.8692212105,47.3426475525],"type":"Point"}
}