{
  "type": "Feature",
  "properties": {
    "iso:country":"CH",
    "sg:address":"Blumenweg 2",
    "sg:city":"Zizers",
    "sg:orig_category":"Architektur U Ingenieurb\u00fcros Vermittlung von Immobilien",
    "sg:phone":"+41 41 852 13 13",
    "sg:postcode":"7205",
    "sg:province":"Graubunden",
    "wof:name":"Consin Consult Gmbh Baumanagementaufgaben, Bau Und Projektleitungsmandaten Usw",
    "wof:placetype":"venue"
},
  "geometry": {"coordinates":[8.443079,47.083469],"type":"Point"}
}