{
  "type": "Feature",
  "properties": {
    "iso:country":"CH",
    "sg:address":"Case Postale",
    "sg:city":"Chaux De Fonds",
    "sg:classifiers":[
        {
            "category":"Banks & Credit Unions",
            "subcategory":"Bank",
            "type":"Services"
        }
    ],
    "sg:postcode":"2302",
    "sg:province":"Neuch\u00e2tel",
    "wof:name":"Cr\u00e9dit Foncier Neuch\u00e2telois",
    "wof:placetype":"venue"
},
  "geometry": {"coordinates":[6.92976,46.989632],"type":"Point"}
}