{
  "type": "Feature",
  "properties": {
    "iso:country":"CH",
    "sg:address":"Boulevard D'arcangier 17",
    "sg:city":"Vevey",
    "sg:orig_category":"Grosshandel mit sonstigen Halbwaren Herstellung von sonstigen Maschinen f\u00fcr unspezifische Verwendung",
    "sg:phone":"+41 21 944 41 60",
    "sg:postcode":"1800",
    "sg:province":"Vaud",
    "wof:name":"Novapack S\u00e0rl",
    "wof:placetype":"venue"
},
  "geometry": {"coordinates":[6.8472099304,46.4384384155],"type":"Point"}
}