{
  "type": "Feature",
  "properties": {
    "iso:country":"CH",
    "sg:address":"Chemin De Gilly 12",
    "sg:city":"Grand-lancy",
    "sg:orig_category":"Herstellung von sonstigen elektrischen Ausr\u00fcstungen",
    "sg:phone":"+41 22 793 51 71",
    "sg:postcode":"1212",
    "sg:province":"Gen\u00e8ve",
    "wof:name":"Pema S\u00e9curit\u00e9 Sa.",
    "wof:placetype":"venue"
},
  "geometry": {"coordinates":[6.1126651764,46.182220459],"type":"Point"}
}