{
  "type": "Feature",
  "properties": {
    "iso:country":"CH",
    "sg:address":"Weberweg 11",
    "sg:city":"Steffisburg",
    "sg:orig_category":"Architekturb\u00fcros",
    "sg:phone":"+41 33 437 51 31",
    "sg:postcode":"3612",
    "sg:province":"Bern",
    "wof:name":"Willi Blunier Architekturb\u00fcro",
    "wof:placetype":"venue"
},
  "geometry": {"coordinates":[7.625768,46.772854],"type":"Point"}
}