{
  "type": "Feature",
  "properties": {
    "iso:country":"CH",
    "sg:address":"Bahnhofstrasse 173 9244 Niederuzwil. Postfach 137",
    "sg:city":"Uzwil",
    "sg:orig_category":"Zahnarztpraxen",
    "sg:phone":"+41 71 951 49 49",
    "sg:postcode":"9240",
    "sg:province":"St. Gallen",
    "wof:name":"Dr. Med. Dent. Franz Keller Zahnarzt",
    "wof:placetype":"venue"
},
  "geometry": {"coordinates":[9.1490268707,47.4460067749],"type":"Point"}
}