{
  "type": "Feature",
  "properties": {
    "iso:country":"CH",
    "sg:address":"Z\u00fcrichstrasse 12 8610 Uster. Postfach 46",
    "sg:city":"Uster",
    "sg:orig_category":"Wirtschaftspr\u00fcfung, Steuerberatung U Treuhand",
    "sg:phone":"+41 19059150",
    "sg:postcode":"8610",
    "sg:province":"Z\u00fcrich",
    "wof:name":"A-z Treuhand, K\u00e4lin Ludwig",
    "wof:placetype":"venue"
},
  "geometry": {"coordinates":[8.716501236,47.3492012024],"type":"Point"}
}