{
  "type": "Feature",
  "properties": {
    "iso:country":"CH",
    "sg:address":"Neuquartierstrasse 13",
    "sg:city":"Biberist",
    "sg:orig_category":"Erbringung von Dienstleistungen f\u00fcr Unternehmen Innendekorationsateliers",
    "sg:phone":"+41 32 672 50 69",
    "sg:postcode":"4562",
    "sg:province":"Solothurn",
    "wof:name":"Edwin Fund Innenausstattungen",
    "wof:placetype":"venue"
},
  "geometry": {"coordinates":[7.5649662018,47.182849884],"type":"Point"}
}