{
  "type": "Feature",
  "properties": {
    "iso:country":"CH",
    "sg:address":"Avenue Louis-rendu 81",
    "sg:city":"Meyrin",
    "sg:orig_category":"RESTAURANTS: TEA-ROOMS",
    "sg:postcode":"1217",
    "sg:province":"Gen\u00e8ve",
    "wof:name":"Restaurant Ailes Les Diaz Cecilia",
    "wof:placetype":"venue"
},
  "geometry": {"coordinates":[6.0719799995,46.2356681824],"type":"Point"}
}