{
  "type": "Feature",
  "properties": {
    "iso:country":"CH",
    "sg:address":"1562",
    "sg:city":"Corcelles-payerne",
    "sg:orig_category":"Detailhandel mit Waren verschiedener Art, Hauptrichtung Nahrungsmittel",
    "sg:phone":"+41 26 660 23 68",
    "sg:postcode":"1562",
    "sg:province":"Vaud",
    "wof:name":"St\u00e9 D'agriculture De Corcelles-pr\u00e8s-payerne",
    "wof:placetype":"venue"
},
  "geometry": {"coordinates":[6.9492001534,46.8255996704],"type":"Point"}
}