{
  "type": "Feature",
  "properties": {
    "iso:country":"CH",
    "sg:address":"Rundbuckstrasse 6",
    "sg:city":"Neuhausen",
    "sg:orig_category":"Berufsorganisationen",
    "sg:postcode":"8212",
    "sg:province":"Schaffhausen",
    "wof:name":"Gewerbehaus Rundbuck Ag",
    "wof:placetype":"venue"
},
  "geometry": {"coordinates":[8.604025,47.675259],"type":"Point"}
}