{
  "type": "Feature",
  "properties": {
    "iso:country":"CH",
    "sg:address":"Hausmatten 2",
    "sg:city":"Rottenschwil",
    "sg:orig_category":"Unclassifiable Establishments",
    "sg:postcode":"8919",
    "sg:province":"Aargau",
    "wof:name":"Horat Informatik Systeme Gmbh",
    "wof:placetype":"venue"
},
  "geometry": {"coordinates":[8.9527902603,47.1751785278],"type":"Point"}
}