{
  "type": "Feature",
  "properties": {
    "iso:country":"CH",
    "sg:address":"Vechigenstrasse 42",
    "sg:city":"Worb",
    "sg:orig_category":"Gesundheitswesen",
    "sg:phone":"+41 31 839 90 09",
    "sg:postcode":"3076",
    "sg:province":"Bern",
    "wof:name":"Leuenberger M. Handwell Massage",
    "wof:placetype":"venue"
},
  "geometry": {"coordinates":[7.5617570877,46.9353218079],"type":"Point"}
}