{
  "type": "Feature",
  "properties": {
    "iso:country":"CH",
    "sg:address":"Neuhofweg 2 6045 Meggen. Postfach",
    "sg:city":"Meggen",
    "sg:orig_category":"Herstellung von Bergwerks U Baumaschinen",
    "sg:postcode":"6045",
    "sg:province":"Luzern",
    "wof:name":"B\u00e4chler Baumaschinen Gmbh Bau- U. Landmaschinen, Fahrzeuge Usw.; Handel",
    "wof:placetype":"venue"
},
  "geometry": {"coordinates":[8.3286409378,47.1272926331],"type":"Point"}
}