{
  "type": "Feature",
  "properties": {
    "iso:country":"CH",
    "sg:address":"Engenb\u00fchl 130",
    "sg:city":"Hallwil",
    "sg:orig_category":"Herstellung von Metallerzeugnissen ohne Maschinenbau Herstellung von Tanks U Sammelbeh\u00e4ltern aus Met",
    "sg:phone":"+41 71 744 22 36",
    "sg:postcode":"5705",
    "sg:province":"Aargau",
    "wof:name":"Betec Beh\u00e4lter, Stallbau Und G\u00fclletechnik Ag",
    "wof:placetype":"venue"
},
  "geometry": {"coordinates":[9.6347312927,47.4368057251],"type":"Point"}
}