{
  "type": "Feature",
  "properties": {
    "iso:country":"CH",
    "sg:address":"Landstrasse 76",
    "sg:city":"Wettingen",
    "sg:classifiers":[
        {
            "category":"Government",
            "subcategory":"Post Office",
            "type":"Public Place"
        }
    ],
    "sg:phone":"+41 56 426 74 25",
    "sg:postcode":"5430",
    "sg:province":"Aargau",
    "sg:tags":[
        "caf\u00e9s",
        "tea-rooms"
    ],
    "wof:name":"Caf\u00e9 Au Bijou",
    "wof:placetype":"venue"
},
  "geometry": {"coordinates":[8.3240318298,47.4668273926],"type":"Point"}
}