{
  "type": "Feature",
  "properties": {
    "iso:country":"CH",
    "sg:address":"Gubelstrasse 37",
    "sg:city":"Z\u00fcrich",
    "sg:classifiers":[
        {
            "category":"Professional",
            "subcategory":"Advertising",
            "type":"Services"
        }
    ],
    "sg:phone":"+41 13101540",
    "sg:postcode":"8050",
    "sg:province":"Z\u00fcrich",
    "sg:tags":[
        "agency"
    ],
    "wof:name":"Alipes Ag",
    "wof:placetype":"venue"
},
  "geometry": {"coordinates":[8.543245,47.408501],"type":"Point"}
}