{
  "type": "Feature",
  "properties": {
    "iso:country":"CH",
    "sg:address":"Austrasse 102",
    "sg:city":"Basel",
    "sg:orig_category":"Sportvereine Eissport Curling",
    "sg:postcode":"4051",
    "sg:province":"Basel-Stadt",
    "wof:name":"Curling Club Basel-basilisk",
    "wof:placetype":"venue"
},
  "geometry": {"coordinates":[7.5781021118,47.5552444458],"type":"Point"}
}