{
  "type": "Feature",
  "properties": {
    "iso:country":"CH",
    "sg:address":"Rue Ste-claire 6",
    "sg:city":"Vevey",
    "sg:orig_category":"Werbung",
    "sg:phone":"+41 31 380 70 00",
    "sg:postcode":"1800",
    "sg:province":"Vaud",
    "wof:name":"Adesso Ag",
    "wof:placetype":"venue"
},
  "geometry": {"coordinates":[7.4257650375,46.9436302185],"type":"Point"}
}