{
  "type": "Feature",
  "properties": {
    "iso:country":"CH",
    "sg:address":"Sole Riva",
    "sg:city":"Astano",
    "sg:orig_category":"Sonstige pers\u00f6nliche Dienstleistungen",
    "sg:phone":"+41 91 608 16 46",
    "sg:postcode":"6999",
    "sg:province":"Ticino",
    "wof:name":"Gosteli Urs",
    "wof:placetype":"venue"
},
  "geometry": {"coordinates":[8.8184947968,46.011806488],"type":"Point"}
}