{
  "type": "Feature",
  "properties": {
    "iso:country":"CH",
    "sg:address":"T\u00f6sstalstrasse 54",
    "sg:city":"Turbenthal",
    "sg:orig_category":"Herstellung von Konstruktionsteilen, Fertigbauteilen U Ausbauelementen aus Holz",
    "sg:postcode":"8488",
    "sg:province":"Z\u00fcrich",
    "wof:name":"Egg-heller Alb.",
    "wof:placetype":"venue"
},
  "geometry": {"coordinates":[8.8446178436,47.4387397766],"type":"Point"}
}