{
  "type": "Feature",
  "properties": {
    "iso:country":"CH",
    "sg:address":"Bahnhofstrasse",
    "sg:city":"Saanen",
    "sg:orig_category":"Sportvereine Sch\u00fctzen",
    "sg:postcode":"3792",
    "sg:province":"Bern",
    "wof:name":"Milit\u00e4rsch\u00fctzen Mannried",
    "wof:placetype":"venue"
},
  "geometry": {"coordinates":[7.2603650093,46.4894561768],"type":"Point"}
}