{
  "type": "Feature",
  "properties": {
    "iso:country":"CH",
    "sg:address":"Via Ciseri 2b",
    "sg:city":"Locarno",
    "sg:orig_category":"Public-Relations-Agenturen Werbung",
    "sg:phone":"+41 91 751 11 11",
    "sg:postcode":"6600",
    "sg:province":"Ticino",
    "wof:name":"Publiticino Sagl",
    "wof:placetype":"venue"
},
  "geometry": {"coordinates":[8.7991313934,46.1693115234],"type":"Point"}
}