{
  "type": "Feature",
  "properties": {
    "iso:country":"CH",
    "sg:address":"Avenue De La Vallonnette 2",
    "sg:city":"Lausanne",
    "sg:orig_category":"Detailhandel mit Waren verschiedener Art, Hauptrichtung Nahrungsmittel",
    "sg:phone":"+41 21 652 98 34",
    "sg:postcode":"1012",
    "sg:province":"Vaud",
    "wof:name":"Restaurant Migros Mm Chailly",
    "wof:placetype":"venue"
},
  "geometry": {"coordinates":[6.6515631676,46.5272102356],"type":"Point"}
}