{
  "type": "Feature",
  "properties": {
    "iso:country":"CH",
    "sg:address":"Rue De Gen\u00e8ve 122 1226 Th\u00f4nex Case Postale 56",
    "sg:city":"Th\u00f4nex",
    "sg:orig_category":"Architektur U Ingenieurb\u00fcros Patentverwertung",
    "sg:phone":"+41 22 349 05 70",
    "sg:postcode":"1226",
    "sg:province":"Gen\u00e8ve",
    "wof:name":"Ardin & Cie Sa Bureau D'ing\u00e9nieurs",
    "wof:placetype":"venue"
},
  "geometry": {"coordinates":[6.203012,46.192657],"type":"Point"}
}