{
  "type": "Feature",
  "properties": {
    "iso:country":"CH",
    "sg:address":"Tellistrasse 64",
    "sg:city":"Aarau",
    "sg:orig_category":"Sonstiger Grosshandel",
    "sg:postcode":"5000",
    "sg:province":"Aargau",
    "wof:name":"Constores Gmbh",
    "wof:placetype":"venue"
},
  "geometry": {"coordinates":[8.057103157,47.3973731995],"type":"Point"}
}