{
  "type": "Feature",
  "properties": {
    "iso:country":"CH",
    "sg:address":"Z\u00fcrcherstrasse 26",
    "sg:city":"Feuerthalen",
    "sg:orig_category":"Innendekorationsateliers",
    "sg:phone":"+41 41 870 86 59",
    "sg:postcode":"8245",
    "sg:province":"Z\u00fcrich",
    "wof:name":"Hansj\u00f6rg Furger Innenausstattung",
    "wof:placetype":"venue"
},
  "geometry": {"coordinates":[8.6422796249,46.8823242188],"type":"Point"}
}