{
  "type": "Feature",
  "properties": {
    "iso:country":"CH",
    "sg:address":"Albonago Via 42",
    "sg:city":"Viganello",
    "sg:orig_category":"Technische, physikalische U chemische Untersuchung",
    "sg:postcode":"6962",
    "sg:province":"Ticino",
    "wof:name":"Soldimpex Di Britta Soldati-krantz",
    "wof:placetype":"venue"
},
  "geometry": {"coordinates":[8.9735946655,46.0135231018],"type":"Point"}
}