{
  "type": "Feature",
  "properties": {
    "iso:country":"CH",
    "sg:address":"Ottikerstrasse 34",
    "sg:city":"Z\u00fcrich",
    "sg:orig_category":"Grosshandel mit Sportartikeln",
    "sg:phone":"+41 13501114",
    "sg:postcode":"8006",
    "sg:province":"Z\u00fcrich",
    "wof:name":"Virma Sportline Sportartikel Sportausr\u00fcstung",
    "wof:placetype":"venue"
},
  "geometry": {"coordinates":[8.546245575,47.3859786987],"type":"Point"}
}