{
  "type": "Feature",
  "properties": {
    "iso:country":"CH",
    "sg:address":"Vandoeuvres Place De 14",
    "sg:city":"Vandoeuvres",
    "sg:orig_category":"Non-Classified Establishments",
    "sg:postcode":"1253",
    "sg:province":"Gen\u00e8ve",
    "wof:name":"Dozio Jacques, Quercus",
    "wof:placetype":"venue"
},
  "geometry": {"coordinates":[6.2023730278,46.2211112976],"type":"Point"}
}