{
  "type": "Feature",
  "properties": {
    "iso:country":"CH",
    "sg:address":"Eichstrasse 42",
    "sg:city":"St\u00e4fa",
    "sg:orig_category":"Fachdetailhandel in Verkaufsr\u00e4umen",
    "sg:phone":"+41 79 336 32 62",
    "sg:postcode":"8712",
    "sg:province":"Z\u00fcrich",
    "wof:name":"Blumengesch\u00e4ft Efeulaube, Pfeiffer C.",
    "wof:placetype":"venue"
},
  "geometry": {"coordinates":[8.7417049408,47.2368164062],"type":"Point"}
}