{
  "type": "Feature",
  "properties": {
    "iso:country":"CH",
    "sg:address":"Lausanne Route De 25",
    "sg:city":"Yverdon-les-bains",
    "sg:orig_category":"Grosshandel mit Getr\u00e4nken",
    "sg:phone":"+41 19365156",
    "sg:postcode":"1400",
    "sg:province":"Vaud",
    "wof:name":"Valanzano Wein Und Getr\u00e4nkehandel",
    "wof:placetype":"venue"
},
  "geometry": {"coordinates":[8.7510881424,47.3051338196],"type":"Point"}
}