{
  "type": "Feature",
  "properties": {
    "iso:country":"CH",
    "sg:address":"Oberalpstrasse 8",
    "sg:city":"Disentis/must\u00e9r",
    "sg:orig_category":"Chucking Systems For Measurement Machines",
    "sg:phone":"+41 81 936 43 30",
    "sg:postcode":"7180",
    "sg:province":"Graubunden",
    "wof:name":"Sgm Ag",
    "wof:placetype":"venue"
},
  "geometry": {"coordinates":[8.853129,46.704601],"type":"Point"}
}