{
  "type": "Feature",
  "properties": {
    "iso:country":"CH",
    "sg:address":"Kantonsstrasse 49",
    "sg:city":"Horw",
    "sg:orig_category":"Architektur U Ingenieurb\u00fcros Architekturb\u00fcros",
    "sg:phone":"+41 41 342 08 70",
    "sg:postcode":"6048",
    "sg:province":"Luzern",
    "wof:name":"Truttmann Und Reichenbach Ag",
    "wof:placetype":"venue"
},
  "geometry": {"coordinates":[8.309616,47.022552],"type":"Point"}
}