{
  "type": "Feature",
  "properties": {
    "iso:country":"CH",
    "sg:address":"Muzy Rue 13",
    "sg:city":"Gen\u00e8ve",
    "sg:orig_category":"Verwaltung von Immobilien",
    "sg:postcode":"1207",
    "sg:province":"Gen\u00e8ve",
    "wof:name":"Gcr S\u00e0rl",
    "wof:placetype":"venue"
},
  "geometry": {"coordinates":[6.1567678452,46.2036018372],"type":"Point"}
}