{
  "type": "Feature",
  "properties": {
    "iso:country":"CH",
    "sg:address":"Rue Hans-hugi 4 2500 Biel/bienne. Postfach",
    "sg:city":"Biel/bienne",
    "sg:orig_category":"Sanit\u00e4r, Heizungs U L\u00fcftungsinstallation",
    "sg:postcode":"2502",
    "sg:province":"Bern",
    "wof:name":"Paerli-chiquet Sa",
    "wof:placetype":"venue"
},
  "geometry": {"coordinates":[7.2454380989,47.1331291199],"type":"Point"}
}