{
  "type": "Feature",
  "properties": {
    "iso:country":"CH",
    "sg:address":"M\u00fchleweg 475",
    "sg:city":"Staffelbach",
    "sg:orig_category":"Vereine Gesang",
    "sg:phone":"+41 33 657 12 81",
    "sg:postcode":"5053",
    "sg:province":"Aargau",
    "wof:name":"M\u00e4nnerchor Reutigen",
    "wof:placetype":"venue"
},
  "geometry": {"coordinates":[7.6173901558,46.7084465027],"type":"Point"}
}