{
  "type": "Feature",
  "properties": {
    "iso:country":"CH",
    "sg:address":"Chemin De La Greube 36",
    "sg:city":"Vernier",
    "sg:orig_category":"Finanzierungsinstitutionen",
    "sg:postcode":"1214",
    "sg:province":"Gen\u00e8ve",
    "wof:name":"Mpst Sa",
    "wof:placetype":"venue"
},
  "geometry": {"coordinates":[6.0788598061,46.2075386047],"type":"Point"}
}