{
  "type": "Feature",
  "properties": {
    "iso:country":"CH",
    "sg:address":"Laliforcha 1",
    "sg:city":"Bavois",
    "sg:orig_category":"Gartenbau Landschaftsplanungsb\u00fcros U Gartenarchitekturb\u00fcros",
    "sg:phone":"+41 24 441 51 27",
    "sg:postcode":"1372",
    "sg:province":"Vaud",
    "wof:name":"Leuba Paysagiste Entreprise De Paysagisme",
    "wof:placetype":"venue"
},
  "geometry": {"coordinates":[6.5659098625,46.6830406189],"type":"Point"}
}