{
  "type": "Feature",
  "properties": {
    "iso:country":"CH",
    "sg:address":"Kronbergstrasse 9 9230 Flawil. Postfach",
    "sg:city":"Flawil",
    "sg:orig_category":"Sonstige mit der Informatik verbundene T\u00e4tigkeiten",
    "sg:postcode":"9230",
    "sg:province":"St. Gallen",
    "wof:name":"Grob I. - Computing Pc-support, Edv-schulung, Hard- U. Software; Handel",
    "wof:placetype":"venue"
},
  "geometry": {"coordinates":[9.1768312454,47.4178237915],"type":"Point"}
}