{
  "type": "Feature",
  "properties": {
    "iso:country":"CH",
    "sg:address":"Avenue De La Gare 6",
    "sg:city":"Sion",
    "sg:orig_category":"Fahrschulen, Flugschulen",
    "sg:phone":"+41 27 322 15 58",
    "sg:postcode":"1950",
    "sg:province":"Valais",
    "wof:name":"Michel & Ingrid Alder Auto-\u00e9cole",
    "wof:placetype":"venue"
},
  "geometry": {"coordinates":[7.3592739105,46.2284965515],"type":"Point"}
}