{
  "type": "Feature",
  "properties": {
    "addr:full":"Bielstrasse 30 Solothurn Solothurn 4500",
    "addr:housenumber":"30",
    "addr:postcode":"4500",
    "addr:street":"Bielstrasse",
    "iso:country":"CH",
    "sg:address":"Bielstrasse 30",
    "sg:city":"Solothurn",
    "sg:orig_category":"Architekturb\u00fcros",
    "sg:phone":"+41 21 944 15 72",
    "sg:postcode":"4500",
    "sg:province":"Solothurn",
    "wof:name":"Stanex Sa Bureau D'architecture",
    "wof:placetype":"venue"
},
  "geometry": {"coordinates":[6.859652,46.451668],"type":"Point"}
}