{
  "type": "Feature",
  "properties": {
    "iso:country":"CH",
    "sg:address":"Avenue De B\u00e9thusy 91",
    "sg:city":"Lausanne",
    "sg:orig_category":"Arztpraxen",
    "sg:phone":"+41 21 652 14 94",
    "sg:postcode":"1012",
    "sg:province":"Vaud",
    "wof:name":"Dr M\u00e9d. Willy Corthay M\u00e9decin G\u00e9n\u00e9raliste Fmh",
    "wof:placetype":"venue"
},
  "geometry": {"coordinates":[6.651434,46.526814],"type":"Point"}
}