{
  "type": "Feature",
  "properties": {
    "iso:country":"CH",
    "sg:address":"Clos Rue Du 9-11 1207 Gen\u00e8ve. Postfach",
    "sg:city":"Gen\u00e8ve",
    "sg:orig_category":"Herstellung von sonstigen Nahrungsmitteln",
    "sg:phone":"+41 71 740 08 85",
    "sg:postcode":"1207",
    "sg:province":"Gen\u00e8ve",
    "wof:name":"Bavint Gmbh",
    "wof:placetype":"venue"
},
  "geometry": {"coordinates":[9.6449604034,47.4465293884],"type":"Point"}
}