{
  "type": "Feature",
  "properties": {
    "iso:country":"CH",
    "sg:address":"Weststrasse 77",
    "sg:city":"Z\u00fcrich",
    "sg:orig_category":"Detailhandel mit Radio U Fernsehger\u00e4ten",
    "sg:phone":"+41 14628683",
    "sg:postcode":"8003",
    "sg:province":"Z\u00fcrich",
    "wof:name":"Video-laden Vz, Genossenschaft F\u00fcr Medienarbeit",
    "wof:placetype":"venue"
},
  "geometry": {"coordinates":[8.5216312408,47.3708686829],"type":"Point"}
}