{
  "type": "Feature",
  "properties": {
    "iso:country":"CH",
    "sg:address":"Altstetterstrasse 251 8048 Z\u00fcrich. Postfach",
    "sg:city":"Z\u00fcrich",
    "sg:orig_category":"Unclassifiable Establishments",
    "sg:postcode":"8048",
    "sg:province":"Z\u00fcrich",
    "wof:name":"Hirschi Information Technology Internetdienstleistungen, Bes. Handelst\u00e4tigkeiten, Web Design Usw",
    "wof:placetype":"venue"
},
  "geometry": {"coordinates":[8.4836835861,47.3805770874],"type":"Point"}
}