{
  "type": "Feature",
  "properties": {
    "iso:country":"CH",
    "sg:address":"Eichholzstrasse",
    "sg:city":"D\u00fcrnten",
    "sg:orig_category":"Vereine Gefl\u00fcgel- and Kaninchenzucht",
    "sg:phone":"+41 55 240 59 49",
    "sg:postcode":"8635",
    "sg:province":"Z\u00fcrich",
    "wof:name":"Kleintier-z\u00fcchter-ver.ktzvd",
    "wof:placetype":"venue"
},
  "geometry": {"coordinates":[8.8689193726,47.2716140747],"type":"Point"}
}