{
  "type": "Feature",
  "properties": {
    "iso:country":"CH",
    "sg:address":"Rue Centrale 53 2740 Montagne-moutier Case Postale 120",
    "sg:city":"Montagne-moutier",
    "sg:orig_category":"Detailhandel mit B\u00fcchern Detailhandel mit B\u00fcchern, Zeitungen, Schreib U Papeteriewaren",
    "sg:phone":"+41 32 493 12 61",
    "sg:postcode":"2740",
    "sg:province":"Bern",
    "wof:name":"Van Bogaert, Succ. Borruat H.",
    "wof:placetype":"venue"
},
  "geometry": {"coordinates":[7.372962,47.27951],"type":"Point"}
}