{
  "type": "Feature",
  "properties": {
    "iso:country":"CH",
    "sg:address":"Philosophes Bvd Des 6 1205 Gen\u00e8ve. Postfach",
    "sg:city":"Gen\u00e8ve",
    "sg:classifiers":[
        {
            "category":"Bars & Pubs",
            "type":"Food & Drink"
        }
    ],
    "sg:postcode":"1205",
    "sg:province":"Gen\u00e8ve",
    "wof:name":"Vouillamoz Laure Et Gaubicher Nathalie Bar-restaurant Loretta Et Nana",
    "wof:placetype":"venue"
},
  "geometry": {"coordinates":[6.143767,46.197414],"type":"Point"}
}