{
  "type": "Feature",
  "properties": {
    "iso:country":"CH",
    "sg:address":"Libernstrasse 24 8112 Otelfingen. Postfach",
    "sg:city":"Otelfingen",
    "sg:orig_category":"Fahrschulen, Flugschulen",
    "sg:postcode":"8112",
    "sg:province":"Z\u00fcrich",
    "wof:name":"Alphabet Fuhrparkmanagement (schweiz) Ag Fahrzeugfuhrpark Usw.; Betreuung, Verwaltung",
    "wof:placetype":"venue"
},
  "geometry": {"coordinates":[8.4009981155,47.4587898254],"type":"Point"}
}