{
  "type": "Feature",
  "properties": {
    "iso:country":"CH",
    "sg:address":"Via Rovedo 9",
    "sg:city":"Locarno",
    "sg:orig_category":"Herstellung von Metallkonstruktionen",
    "sg:phone":"+41 91 751 28 82",
    "sg:postcode":"6600",
    "sg:province":"Ticino",
    "wof:name":"Finroll Sagl",
    "wof:placetype":"venue"
},
  "geometry": {"coordinates":[8.7885818481,46.1668510437],"type":"Point"}
}