{
  "type": "Feature",
  "properties": {
    "iso:country":"CH",
    "sg:address":"Schlossstrasse 8",
    "sg:city":"Pratteln",
    "sg:orig_category":"Unclassifiable Establishments",
    "sg:postcode":"4133",
    "sg:province":"Basel-Landschaft",
    "wof:name":"Lingg Kilchmann Brigitt Kosmetik",
    "wof:placetype":"venue"
},
  "geometry": {"coordinates":[7.6937708855,47.5214042664],"type":"Point"}
}