{
  "type": "Feature",
  "properties": {
    "iso:country":"CH",
    "sg:address":"Fuchsronsstrasse 10",
    "sg:city":"Galgenen",
    "sg:orig_category":"Hoch U Tiefbau",
    "sg:phone":"+41 32 493 62 48",
    "sg:postcode":"8854",
    "sg:province":"Schwyz",
    "wof:name":"Fr\u00e9dy H\u00e4nzi Entreprise De Construction",
    "wof:placetype":"venue"
},
  "geometry": {"coordinates":[7.369743824,47.2791595459],"type":"Point"}
}