{
  "type": "Feature",
  "properties": {
    "iso:country":"CH",
    "sg:address":"M\u00fchlestrasse",
    "sg:city":"Ennenda",
    "sg:orig_category":"Herstellung von Reiseartikeln, Leder U Sattlerwaren Instandhaltung U Reparatur von Automobilen",
    "sg:phone":"+41 55 640 65 35",
    "sg:postcode":"8755",
    "sg:province":"Glarus",
    "wof:name":"Nafzger A., Autosattlerei",
    "wof:placetype":"venue"
},
  "geometry": {"coordinates":[9.0768098831,47.0366096497],"type":"Point"}
}