{
  "type": "Feature",
  "properties": {
    "iso:country":"CH",
    "sg:address":"Buganella 9475 Sevelen. Postfach",
    "sg:city":"Sevelen",
    "sg:orig_category":"Sanit\u00e4r U Heizungsinstallation Sanit\u00e4rinstallation",
    "sg:phone":"+41 81 785 33 10",
    "sg:postcode":"9475",
    "sg:province":"St. Gallen",
    "wof:name":"Andreas Sprecher Haustechnik & Oelbrennerservice Gmbh",
    "wof:placetype":"venue"
},
  "geometry": {"coordinates":[9.4953451157,47.1244697571],"type":"Point"}
}