{
  "type": "Feature",
  "properties": {
    "iso:country":"CH",
    "sg:address":"Wehntalerstrasse 11",
    "sg:city":"Oberweningen",
    "sg:classifiers":[
        {
            "category":"Building & Trades",
            "subcategory":"Plumbing",
            "type":"Services"
        }
    ],
    "sg:phone":"+41 18571111",
    "sg:postcode":"8165",
    "sg:province":"Z\u00fcrich",
    "sg:tags":[
        "waterproofing",
        "basement"
    ],
    "wof:name":"Rascor International Ag",
    "wof:placetype":"venue"
},
  "geometry": {"coordinates":[8.409191,47.499847],"type":"Point"}
}