{
  "type": "Feature",
  "properties": {
    "iso:country":"CH",
    "sg:address":"H\u00f6libachstrasse 110",
    "sg:city":"Obfelden",
    "sg:orig_category":"Softwareentwicklung U beratung",
    "sg:postcode":"8912",
    "sg:province":"Z\u00fcrich",
    "wof:name":"Redics - Diethelm Reto Information And Communication Systems",
    "wof:placetype":"venue"
},
  "geometry": {"coordinates":[8.8919439316,47.1855316162],"type":"Point"}
}