{
  "type": "Feature",
  "properties": {
    "iso:country":"CH",
    "sg:address":"Benkenstrasse 64",
    "sg:city":"Binningen",
    "sg:orig_category":"Pensionskassen Unternehmensberatung",
    "sg:phone":"+41 22 300 38 31",
    "sg:postcode":"4102",
    "sg:province":"Basel-Landschaft",
    "wof:name":"Hpr Sa Pr\u00e9voyance Prof.& Assurances",
    "wof:placetype":"venue"
},
  "geometry": {"coordinates":[6.135931015,46.1879501343],"type":"Point"}
}