{
  "type": "Feature",
  "properties": {
    "iso:country":"CH",
    "sg:address":"Waldheimstrasse 18",
    "sg:city":"Grenchen",
    "sg:orig_category":"Herstellung von Konstruktionsteilen, Fertigbauteilen U Ausbauelementen aus Holz",
    "sg:phone":"+41 32 652 28 41",
    "sg:postcode":"2540",
    "sg:province":"Solothurn",
    "wof:name":"Fuchs Rudolf Schreinerei-reparaturen Und Service",
    "wof:placetype":"venue"
},
  "geometry": {"coordinates":[7.3832058907,47.2013587952],"type":"Point"}
}