{
  "type": "Feature",
  "properties": {
    "iso:country":"CH",
    "sg:address":"Baarermattstrasse 14 6300 Zug. Postfach 4135",
    "sg:city":"Zug",
    "sg:orig_category":"Kauf U Verkauf von Immobilien auf eigene Rechnung Vermittlung von Immobilien",
    "sg:phone":"+41 41 766 03 03",
    "sg:postcode":"6304",
    "sg:province":"Zug",
    "wof:name":"Engel&v\u00f6lkers Ag",
    "wof:placetype":"venue"
},
  "geometry": {"coordinates":[8.5264101028,47.1817588806],"type":"Point"}
}