{
  "type": "Feature",
  "properties": {
    "addr:full":"Aeschstrasse 6b 8127 Forch. Postfach Forch Z\u00fcrich 8127",
    "addr:housenumber":"6b",
    "addr:postcode":"8127 forch. postfach;8127",
    "addr:street":"Aeschstrasse",
    "iso:country":"CH",
    "sg:address":"Aeschstrasse 6b 8127 Forch. Postfach",
    "sg:city":"Forch",
    "sg:orig_category":"Architektur U Ingenieurb\u00fcros",
    "sg:postcode":"8127",
    "sg:province":"Z\u00fcrich",
    "wof:name":"Integrated Process Engineering Stalder Eugen",
    "wof:placetype":"venue"
},
  "geometry": {"coordinates":[8.655075,47.328751],"type":"Point"}
}