{
  "type": "Feature",
  "properties": {
    "iso:country":"CH",
    "sg:address":"Im Wigarten 5",
    "sg:city":"Pratteln",
    "sg:orig_category":"Grosshandel mit sonstigen Maschinen U Ausr\u00fcstungen f\u00fcr Industrie, Handel U Schiffahrt Unternehmensbe",
    "sg:phone":"+41 55 210 70 38",
    "sg:postcode":"4133",
    "sg:province":"Basel-Landschaft",
    "wof:name":"Willi Christ Engineering Logistiksysteme",
    "wof:placetype":"venue"
},
  "geometry": {"coordinates":[8.8951406479,47.2196731567],"type":"Point"}
}