{
  "type": "Feature",
  "properties": {
    "iso:country":"CH",
    "sg:address":"Ruelle Des Fins 7",
    "sg:city":"Hauterive",
    "sg:orig_category":"Politische Parteien SP",
    "sg:phone":"+41 32 422 40 94",
    "sg:postcode":"2068",
    "sg:province":"Neuch\u00e2tel",
    "wof:name":"Parti Socialiste Jurassien",
    "wof:placetype":"venue"
},
  "geometry": {"coordinates":[7.3421111107,47.3660354614],"type":"Point"}
}