{
  "type": "Feature",
  "properties": {
    "iso:country":"CH",
    "sg:address":"Rossfueter 1 9475 Sevelen. Postfach",
    "sg:city":"Sevelen",
    "sg:orig_category":"Grosshandel mit Erzen U Metallen",
    "sg:postcode":"9475",
    "sg:province":"St. Gallen",
    "wof:name":"K\u00fcng J. Ag, Schrott Und Metall",
    "wof:placetype":"venue"
},
  "geometry": {"coordinates":[8.8545198441,47.193862915],"type":"Point"}
}