{
  "type": "Feature",
  "properties": {
    "addr:full":"Avenue Blanc 49 1202 Gen\u00e8ve. Postfach Gen\u00e8ve Gen\u00e8ve 1202",
    "addr:housenumber":"49",
    "addr:postcode":"1202;postfach;1202",
    "addr:street":"Avenue Blanc",
    "iso:country":"CH",
    "sg:address":"Avenue Blanc 49 1202 Gen\u00e8ve. Postfach",
    "sg:city":"Gen\u00e8ve",
    "sg:orig_category":"Datenverarbeitungsdienste Effekten U Warenterminb\u00f6rsen",
    "sg:phone":"+41 22 818 08 08",
    "sg:postcode":"1202",
    "sg:province":"Gen\u00e8ve",
    "wof:name":"Silvermat Sa Commerce Sur Internet De Mati\u00e8res Et Produits, Notamm. Achat, Vente Etc. De Mati\u00e8res Premieres Etc",
    "wof:placetype":"venue"
},
  "geometry": {"coordinates":[6.147856,46.221012],"type":"Point"}
}