{
  "type": "Feature",
  "properties": {
    "iso:country":"CH",
    "sg:address":"R\u00f6merstrasse 185",
    "sg:city":"Stadel(winterthur)",
    "sg:orig_category":"Detailhandel mit Brot, Back U S\u00fcsswaren",
    "sg:phone":"+41 52 242 12 40",
    "sg:postcode":"8404",
    "sg:province":"Z\u00fcrich",
    "wof:name":"B\u00e4ckerei-konditorei Gredler & Co",
    "wof:placetype":"venue"
},
  "geometry": {"coordinates":[8.758223,47.506569],"type":"Point"}
}