{
  "type": "Feature",
  "properties": {
    "iso:country":"CH",
    "sg:address":"Habsburgerstrasse 21 6000 Luzern. Postfach",
    "sg:city":"Luzern",
    "sg:orig_category":"Hochschulen U h\u00f6here Ausbildung",
    "sg:postcode":"6003",
    "sg:province":"Luzern",
    "wof:name":"Schweizerisches Verkehrs-p\u00e4dagogisches Institut Ag (vpi)",
    "wof:placetype":"venue"
},
  "geometry": {"coordinates":[8.3074893951,47.0468177795],"type":"Point"}
}