{
  "type": "Feature",
  "properties": {
    "iso:country":"CH",
    "sg:address":"Cioccaro Piazza 2",
    "sg:city":"Lugano",
    "sg:orig_category":"Handels-H\u00e4user U Gesellschaften",
    "sg:postcode":"6900",
    "sg:province":"Ticino",
    "wof:name":"Schneider A.f.",
    "wof:placetype":"venue"
},
  "geometry": {"coordinates":[8.9501075745,46.004573822],"type":"Point"}
}