{
  "type": "Feature",
  "properties": {
    "iso:country":"CH",
    "sg:address":"Brennereistrasse 3",
    "sg:city":"Subingen",
    "sg:orig_category":"Verlegen von Fussboden",
    "sg:phone":"+41 32 614 41 56",
    "sg:postcode":"4553",
    "sg:province":"Solothurn",
    "wof:name":"Bau-& Wohnkeramik Meier Natur-& Formsteinarbeiten",
    "wof:placetype":"venue"
},
  "geometry": {"coordinates":[7.6166391373,47.2000846863],"type":"Point"}
}