{
  "type": "Feature",
  "properties": {
    "iso:country":"CH",
    "sg:address":"Bahnhofstrasse 40",
    "sg:city":"Dulliken",
    "sg:orig_category":"Bauingenieurb\u00fcros Hochbau Bauingenieurb\u00fcros allgemein",
    "sg:phone":"+41 62 295 10 86",
    "sg:postcode":"4657",
    "sg:province":"Solothurn",
    "wof:name":"Hans-rudolf Maurer Ingenieurb\u00fcro",
    "wof:placetype":"venue"
},
  "geometry": {"coordinates":[7.945021,47.349415],"type":"Point"}
}