{
  "type": "Feature",
  "properties": {
    "iso:country":"CH",
    "sg:address":"Antonio Via Sant 10",
    "sg:city":"Locarno",
    "sg:orig_category":"Unclassifiable Establishments",
    "sg:postcode":"6600",
    "sg:province":"Ticino",
    "wof:name":"Trattoria Fiorentina Sa",
    "wof:placetype":"venue"
},
  "geometry": {"coordinates":[8.7924890518,46.1695175171],"type":"Point"}
}