{
  "type": "Feature",
  "properties": {
    "iso:country":"CH",
    "sg:address":"Holderenstrasse 12",
    "sg:city":"Rehetobel",
    "sg:orig_category":"Sonstiges Textilgewerbe",
    "sg:phone":"+41 27 957 21 79",
    "sg:postcode":"9038",
    "sg:province":"Appenzell Ausserrhoden",
    "wof:name":"Kaufhaus Burgener Albina, Nachfolgerin Schaller Paula",
    "wof:placetype":"venue"
},
  "geometry": {"coordinates":[7.9367241859,46.1232452393],"type":"Point"}
}