{
  "type": "Feature",
  "properties": {
    "iso:country":"CH",
    "sg:address":"Via Teatro",
    "sg:city":"Bellinzona",
    "sg:orig_category":"Fachdetailhandel in Verkaufsr\u00e4umen",
    "sg:postcode":"6500",
    "sg:province":"Ticino",
    "wof:name":"Chicherio Paolo",
    "wof:placetype":"venue"
},
  "geometry": {"coordinates":[9.0220098495,46.1910552979],"type":"Point"}
}