{
  "type": "Feature",
  "properties": {
    "iso:country":"CH",
    "sg:address":"Rue Des Remparts 9 1400 Yverdon-les-bains. Postfach",
    "sg:city":"Lugano",
    "sg:orig_category":"Herstellung von elektronischen Bauelementen Sonstige mit der Informatik verbundene T\u00e4tigkeiten",
    "sg:phone":"+41 32 926 63 33",
    "sg:postcode":"6900",
    "sg:province":"Ticino",
    "wof:name":"Suicopro S\u00e0rl",
    "wof:placetype":"venue"
},
  "geometry": {"coordinates":[6.8141241074,47.0926094055],"type":"Point"}
}