{
  "type": "Feature",
  "properties": {
    "iso:country":"CH",
    "sg:address":"Ch. Des Cr\u00eats-de-champel 34 1206 Gen\u00e8ve. Postfach",
    "sg:city":"Gen\u00e8ve",
    "sg:orig_category":"Grosshandel mit sonstigen Gebrauchs U Verbrauchsg\u00fctern",
    "sg:postcode":"1206",
    "sg:province":"Gen\u00e8ve",
    "wof:name":"Artcao, Cottier E. Articles Publicitaires; Merchandising, D\u00e9veloppement, Promotion",
    "wof:placetype":"venue"
},
  "geometry": {"coordinates":[6.1566228867,46.1867828369],"type":"Point"}
}