{
  "type": "Feature",
  "properties": {
    "iso:country":"CH",
    "sg:address":"Fr\u00f6schenlochstrasse 11",
    "sg:city":"Oensingen",
    "sg:orig_category":"Herstellung von sonstigen Maschinen f\u00fcr bestimmte Verwendung R\u00fcckgewinnung U Vorbereitung f\u00fcr die Wi",
    "sg:phone":"+41 62 396 38 38",
    "sg:postcode":"4702",
    "sg:province":"Solothurn",
    "wof:name":"Bv Kompostieranlage Oensingen Ag",
    "wof:placetype":"venue"
},
  "geometry": {"coordinates":[7.7412800789,47.2925682068],"type":"Point"}
}