{
  "type": "Feature",
  "properties": {
    "iso:country":"CH",
    "sg:address":"Wallisellenstrasse 55",
    "sg:city":"D\u00fcbendorf",
    "sg:orig_category":"Mechanische Werkst\u00e4tten",
    "sg:phone":"+41 18200653",
    "sg:postcode":"8600",
    "sg:province":"Z\u00fcrich",
    "wof:name":"Ernst H\u00e4nni Ag Pr\u00e4zisions Mechanik",
    "wof:placetype":"venue"
},
  "geometry": {"coordinates":[8.6160707474,47.4002952576],"type":"Point"}
}