{
  "type": "Feature",
  "properties": {
    "iso:country":"CH",
    "sg:address":"Buchenstrasse 3 6210 Sursee. Postfach",
    "sg:city":"Sursee",
    "sg:orig_category":"Druckweiterverarbeitung Satzherstellung U Reproduktion",
    "sg:phone":"+41 56 426 91 92",
    "sg:postcode":"6210",
    "sg:province":"Luzern",
    "wof:name":"Schmocker Ag Wort & Bild",
    "wof:placetype":"venue"
},
  "geometry": {"coordinates":[8.3189163208,47.4621505737],"type":"Point"}
}