{
  "type": "Feature",
  "properties": {
    "iso:country":"CH",
    "sg:address":"1145",
    "sg:city":"Bi\u00e8re",
    "sg:orig_category":"Schlossereien",
    "sg:phone":"+41 21 809 55 49",
    "sg:postcode":"1145",
    "sg:province":"Vaud",
    "wof:name":"Jacky Urfer Serrures",
    "wof:placetype":"venue"
},
  "geometry": {"coordinates":[6.3328051567,46.5380134583],"type":"Point"}
}