{
  "type": "Feature",
  "properties": {
    "iso:country":"CH",
    "sg:address":"6803",
    "sg:city":"Camignolo",
    "sg:orig_category":"Landesverteidigung, Sozialversicherung \u00d6ffentliche Verwaltung",
    "sg:phone":"+41 91 946 13 63",
    "sg:postcode":"6803",
    "sg:province":"Ticino",
    "wof:name":"Centro Di Protezione Civile Di Camignolo",
    "wof:placetype":"venue"
},
  "geometry": {"coordinates":[8.9504499435,46.1043701172],"type":"Point"}
}