{
  "type": "Feature",
  "properties": {
    "iso:country":"CH",
    "sg:address":"Villigerstrasse 370",
    "sg:city":"Remigen",
    "sg:orig_category":"Aktivit\u00e4ten der Krankenschwestern U Hebammen, Hauspflege Organisationen des Gesundheitswesen",
    "sg:phone":"+41 56 284 27 44",
    "sg:postcode":"5236",
    "sg:province":"Aargau",
    "wof:name":"Haus-& Krankenpflegeverein Spitex-b\u00fcro",
    "wof:placetype":"venue"
},
  "geometry": {"coordinates":[8.189433,47.514793],"type":"Point"}
}