{
  "type": "Feature",
  "properties": {
    "iso:country":"CH",
    "sg:address":"Route Du Poyet 16",
    "sg:city":"Romont",
    "sg:classifiers":[
        {
            "category":"Building & Trades",
            "subcategory":"Construction",
            "type":"Services"
        }
    ],
    "sg:phone":"+41 26 652 10 10",
    "sg:postcode":"1680",
    "sg:province":"Fribourg",
    "sg:tags":[
        "insulation",
        "heat",
        "work",
        "cold"
    ],
    "wof:name":"Maternini & Fils Sa",
    "wof:placetype":"venue"
},
  "geometry": {"coordinates":[6.9208049774,46.6975975037],"type":"Point"}
}