{
  "type": "Feature",
  "properties": {
    "iso:country":"CH",
    "sg:address":"Stutzrain 46",
    "sg:city":"Luzern",
    "sg:orig_category":"Detailhandel mit Bekleidung Textilgewerbe",
    "sg:phone":"+41 41 361 08 85",
    "sg:postcode":"6005",
    "sg:province":"Luzern",
    "wof:name":"Imacona Zubeh\u00f6r Ag",
    "wof:placetype":"venue"
},
  "geometry": {"coordinates":[8.33356,47.024792],"type":"Point"}
}