{
  "type": "Feature",
  "properties": {
    "iso:country":"CH",
    "sg:address":"Soolstrasse 26 8905 Arni-islisberg. Postfach",
    "sg:city":"Bonstetten",
    "sg:orig_category":"Unternehmensberatung",
    "sg:phone":"+41 18450914",
    "sg:postcode":"8906",
    "sg:province":"Z\u00fcrich",
    "wof:name":"Orgware Gmbh",
    "wof:placetype":"venue"
},
  "geometry": {"coordinates":[8.8431529999,47.2975006104],"type":"Point"}
}