{
  "type": "Feature",
  "properties": {
    "iso:country":"CH",
    "sg:address":"Grabenstrasse 12",
    "sg:city":"Bischofszell",
    "sg:orig_category":"Detailhandel mit elektrischen Haushaltsger\u00e4ten Elektroinstallation",
    "sg:phone":"+41 71 422 18 63",
    "sg:postcode":"9220",
    "sg:province":"Thurgau",
    "wof:name":"Elektro Niklaus Ag",
    "wof:placetype":"venue"
},
  "geometry": {"coordinates":[9.2410516739,47.4962158203],"type":"Point"}
}