{
  "type": "Feature",
  "properties": {
    "iso:country":"CH",
    "sg:address":"Rue De La Douane 85 H",
    "sg:city":"Fahy",
    "sg:orig_category":"Unclassifiable Establishments",
    "sg:phone":"+41 32 476 01 10",
    "sg:postcode":"2916",
    "sg:province":"Jura",
    "wof:name":"Gefco (suisse) Sa",
    "wof:placetype":"venue"
},
  "geometry": {"coordinates":[6.9486298561,47.4190559387],"type":"Point"}
}