{
  "type": "Feature",
  "properties": {
    "iso:country":"CH",
    "sg:address":"1034",
    "sg:city":"Boussens",
    "sg:orig_category":"Softwareentwicklung U beratung",
    "sg:postcode":"1034",
    "sg:province":"Vaud",
    "wof:name":"Master Computing, Marclay Ursula",
    "wof:placetype":"venue"
},
  "geometry": {"coordinates":[6.5845799446,46.6043014526],"type":"Point"}
}