{
  "type": "Feature",
  "properties": {
    "iso:country":"CH",
    "sg:address":"Chr\u00fczlistrasse 2 6210 Sursee. Postfach",
    "sg:city":"Sursee",
    "sg:orig_category":"Herstellung von Spielwaren",
    "sg:postcode":"6210",
    "sg:province":"Luzern",
    "wof:name":"Peter Tschopp Modelleisenbahnen Gmbh",
    "wof:placetype":"venue"
},
  "geometry": {"coordinates":[8.1057357788,47.1723327637],"type":"Point"}
}