{
  "type": "Feature",
  "properties": {
    "iso:country":"CH",
    "sg:address":"Vergers Rue Des 43",
    "sg:city":"Chippis",
    "sg:orig_category":"Non-Classified Establishments",
    "sg:postcode":"3965",
    "sg:province":"Valais",
    "wof:name":"G\u00e9rard Et Laurent Elsig, Gypserie-peinture S\u00e0rl",
    "wof:placetype":"venue"
},
  "geometry": {"coordinates":[7.5415549278,46.2804908752],"type":"Point"}
}