{
  "type": "Feature",
  "properties": {
    "iso:country":"CH",
    "sg:address":"Jenatschstrasse 1 8002 Z\u00fcrich. Postfach",
    "sg:city":"Z\u00fcrich",
    "sg:orig_category":"Interessenvertretungen",
    "sg:postcode":"8002",
    "sg:province":"Z\u00fcrich",
    "wof:name":"F\u00fcrsorgestiftung Der Firma Traco Trading Co Ltd",
    "wof:placetype":"venue"
},
  "geometry": {"coordinates":[8.5341739655,47.3635063171],"type":"Point"}
}