{
  "type": "Feature",
  "properties": {
    "iso:country":"CH",
    "sg:address":"F\u00fcrst Franz Josef Strasse 38",
    "sg:city":"Vaduz",
    "sg:orig_category":"Vorschulen, Kinderg\u00e4rten",
    "sg:postcode":"9490",
    "wof:name":"Kindergarten Vorschule Ebenholz",
    "wof:placetype":"venue"
},
  "geometry": {"coordinates":[9.5151958466,47.1488990784],"type":"Point"}
}