{
  "type": "Feature",
  "properties": {
    "iso:country":"CH",
    "sg:address":"Weiteren 21b 9523 Z\u00fcberwangen. Postfach",
    "sg:city":"Z\u00fcberwangen",
    "sg:orig_category":"Maler U Glasergewerbe",
    "sg:phone":"+41 71 944 23 25",
    "sg:postcode":"9523",
    "sg:province":"St. Gallen",
    "wof:name":"Max Kappler, Malerarbeiten",
    "wof:placetype":"venue"
},
  "geometry": {"coordinates":[9.0850353241,47.4658584595],"type":"Point"}
}