{
  "type": "Feature",
  "properties": {
    "iso:country":"CH",
    "sg:address":"Ibelweg 19a",
    "sg:city":"Zug",
    "sg:classifiers":[
        {
            "category":"Manufacturing",
            "subcategory":"Paper Products",
            "type":"Manufacturing & Wholesale Goods"
        }
    ],
    "sg:phone":"+41 41 760 32 82",
    "sg:postcode":"6300",
    "sg:province":"Zug",
    "sg:tags":[
        "design"
    ],
    "wof:name":"Consol Glaswerkstatt",
    "wof:placetype":"venue"
},
  "geometry": {"coordinates":[8.524991,47.182209],"type":"Point"}
}