{
  "type": "Feature",
  "properties": {
    "iso:country":"CH",
    "sg:address":"Pilatusstrasse 6",
    "sg:city":"M\u00f6hlin",
    "sg:orig_category":"Unternehmensberatung",
    "sg:phone":"+41 61 853 91 40",
    "sg:postcode":"4313",
    "sg:province":"Aargau",
    "wof:name":"Bamert Consulting",
    "wof:placetype":"venue"
},
  "geometry": {"coordinates":[7.8494157791,47.5569419861],"type":"Point"}
}