{
  "type": "Feature",
  "properties": {
    "iso:country":"CH",
    "sg:address":"Talstrasse 39",
    "sg:city":"Z\u00fcrich",
    "sg:orig_category":"Handels-H\u00e4user U Gesellschaften",
    "sg:phone":"+41 19109082",
    "sg:postcode":"8001",
    "sg:province":"Z\u00fcrich",
    "wof:name":"Seiz Ch. Ag",
    "wof:placetype":"venue"
},
  "geometry": {"coordinates":[8.5873155594,47.3209114075],"type":"Point"}
}