{
  "type": "Feature",
  "properties": {
    "iso:country":"CH",
    "sg:address":"Lessingstrasse 5 8002 Z\u00fcrich. Postfach",
    "sg:city":"Z\u00fcrich",
    "sg:orig_category":"Vermietung U Verpachtung von eigenen Immobilien",
    "sg:postcode":"8002",
    "sg:province":"Z\u00fcrich",
    "wof:name":"Immobilien Ag Z\u00e4hringer",
    "wof:placetype":"venue"
},
  "geometry": {"coordinates":[8.5240602493,47.3588752747],"type":"Point"}
}