{
  "type": "Feature",
  "properties": {
    "iso:country":"CH",
    "sg:address":"Alte Landstrasse 25",
    "sg:city":"Zollikon",
    "sg:orig_category":"Pensionskassen",
    "sg:postcode":"8702",
    "sg:province":"Z\u00fcrich",
    "wof:name":"Hilfskasse Des Schweizerischen Verbandes Der Arztgehilfinnen",
    "wof:placetype":"venue"
},
  "geometry": {"coordinates":[8.5717935562,47.3437461853],"type":"Point"}
}