{
  "type": "Feature",
  "properties": {
    "iso:country":"CH",
    "sg:address":"Hintere Gasse 13",
    "sg:city":"Riggisberg",
    "sg:orig_category":"Herstellung von keramischen Haushaltswaren U Ziergegenst\u00e4nden",
    "sg:phone":"+41 31 809 18 08",
    "sg:postcode":"3132",
    "sg:province":"Bern",
    "wof:name":"Ruth Schmid",
    "wof:placetype":"venue"
},
  "geometry": {"coordinates":[7.4761199951,46.809803009],"type":"Point"}
}