{
  "type": "Feature",
  "properties": {
    "iso:country":"CH",
    "sg:address":"Buchenstrasse 65",
    "sg:city":"Speicher",
    "sg:orig_category":"Hoch U Tiefbau",
    "sg:phone":"+41 71 344 28 36",
    "sg:postcode":"9042",
    "sg:province":"Appenzell Ausserrhoden",
    "wof:name":"Walter Graf Bauunternehmen",
    "wof:placetype":"venue"
},
  "geometry": {"coordinates":[9.4448680878,47.4158401489],"type":"Point"}
}