{
  "type": "Feature",
  "properties": {
    "iso:country":"CH",
    "sg:address":"Laubeggstrasse 37 3006 Bern. Postfach",
    "sg:city":"Bern",
    "sg:orig_category":"Religi\u00f6se Vereinigungen",
    "sg:postcode":"3005",
    "sg:province":"Bern",
    "wof:name":"Si De L'\u00e9glise Libre De La C\u00f4te-aux-f\u00e9es",
    "wof:placetype":"venue"
},
  "geometry": {"coordinates":[6.4908499718,46.8687477112],"type":"Point"}
}