{
  "type": "Feature",
  "properties": {
    "iso:country":"CH",
    "sg:address":"Badenerstrasse 41",
    "sg:city":"Z\u00fcrich",
    "sg:orig_category":"Detailhandel mit Damenbekleidung",
    "sg:phone":"+41 12402491",
    "sg:postcode":"8004",
    "sg:province":"Z\u00fcrich",
    "wof:name":"Andra Dessous Nachtw\u00e4sche Str\u00fcmpfe",
    "wof:placetype":"venue"
},
  "geometry": {"coordinates":[8.52883,47.373245],"type":"Point"}
}