{
  "type": "Feature",
  "properties": {
    "iso:country":"CH",
    "sg:address":"Rue Bellerive 3960 Sierre Case Postale 374",
    "sg:city":"Sierre",
    "sg:orig_category":"Grosshandel mit sonstigen Halbwaren Herstellung von Papier, Karton U Pappe",
    "sg:phone":"+41 27 458 18 00",
    "sg:postcode":"3960",
    "sg:province":"Valais",
    "wof:name":"Normpack Sa",
    "wof:placetype":"venue"
},
  "geometry": {"coordinates":[7.5177750587,46.2779960632],"type":"Point"}
}