{
  "type": "Feature",
  "properties": {
    "iso:country":"CH",
    "sg:address":"Rue Des Moulins 46",
    "sg:city":"Yverdon-les-bains",
    "sg:orig_category":"Herstellung von Karosserien U Anh\u00e4ngern",
    "sg:postcode":"1400",
    "sg:province":"Vaud",
    "wof:name":"T\u00e9taz J.",
    "wof:placetype":"venue"
},
  "geometry": {"coordinates":[6.6352138519,46.777141571],"type":"Point"}
}