{
  "type": "Feature",
  "properties": {
    "iso:country":"CH",
    "sg:address":"Schwarztorstrasse 11 -",
    "sg:city":"Bern",
    "sg:classifiers":[
        {
            "category":"Professional",
            "subcategory":"Art Services",
            "type":"Services"
        }
    ],
    "sg:phone":"+41 31 372 78 87",
    "sg:postcode":"3007",
    "sg:province":"Bern",
    "sg:tags":[
        "export-import"
    ],
    "wof:name":"Costa Rica Embassy",
    "wof:placetype":"venue"
},
  "geometry": {"coordinates":[7.436045,46.94289],"type":"Point"}
}