{
  "type": "Feature",
  "properties": {
    "iso:country":"CH",
    "sg:address":"Josefstrasse 12 8000 Z\u00fcrich. Postfach",
    "sg:city":"Z\u00fcrich",
    "sg:orig_category":"Erbringung von Dienstleistungen f\u00fcr Unternehmen",
    "sg:postcode":"8001",
    "sg:province":"Z\u00fcrich",
    "wof:name":"Boutellier Myriam Grafik + Konzept",
    "wof:placetype":"venue"
},
  "geometry": {"coordinates":[8.5341434479,47.3807945251],"type":"Point"}
}