{
  "type": "Feature",
  "properties": {
    "iso:country":"CH",
    "sg:address":"Boujean Route De 138 2503 Biel/bienne. Postfach",
    "sg:city":"Biel/bienne",
    "sg:orig_category":"Herstellung von Seifen, Wasch U Reinigungsmitteln",
    "sg:postcode":"2503",
    "sg:province":"Bern",
    "wof:name":"Moreno Discount, A. Scarna",
    "wof:placetype":"venue"
},
  "geometry": {"coordinates":[7.2472572327,47.1408882141],"type":"Point"}
}