{
  "type": "Feature",
  "properties": {
    "iso:country":"CH",
    "sg:address":"Rosenfeldweg 33",
    "sg:city":"St.gallen",
    "sg:orig_category":"Sportvereine Ballsport Badminton",
    "sg:phone":"+41 71 277 18 34",
    "sg:postcode":"9000",
    "sg:province":"St. Gallen",
    "wof:name":"Badminton-club Rotmonten Sg",
    "wof:placetype":"venue"
},
  "geometry": {"coordinates":[9.3493070602,47.4209213257],"type":"Point"}
}