{
  "type": "Feature",
  "properties": {
    "iso:country":"CH",
    "sg:address":"Schlossweg 63c",
    "sg:city":"Dornach",
    "sg:orig_category":"Unternehmensberatung",
    "sg:phone":"+41 56 443 08 45",
    "sg:postcode":"4143",
    "sg:province":"Solothurn",
    "wof:name":"Impulse Consulting Vogel Dr. A. Unternehmensberatung F\u00fcr Die Industrie, Bes. Str\u00f6mungs, Maschinenbau",
    "wof:placetype":"venue"
},
  "geometry": {"coordinates":[8.1391372681,47.4461860657],"type":"Point"}
}