{
  "type": "Feature",
  "properties": {
    "iso:country":"CH",
    "sg:address":"Murtenstrasse 3",
    "sg:city":"Bern",
    "sg:orig_category":"Detailhandel mit Getr\u00e4nken Detailhandel mit Waren verschiedener Art, Hauptrichtung Nahrungsmittel",
    "sg:phone":"+41 31 381 07 18",
    "sg:postcode":"3008",
    "sg:province":"Bern",
    "wof:name":"Frischmarkt El Mawla Getr\u00e4nke-hauslieferdienst",
    "wof:placetype":"venue"
},
  "geometry": {"coordinates":[7.4273262024,46.9483337402],"type":"Point"}
}