{
  "type": "Feature",
  "properties": {
    "iso:country":"CH",
    "sg:address":"Hohlstrasse 201 8004 Z\u00fcrich. Postfach",
    "sg:city":"Z\u00fcrich",
    "sg:orig_category":"Fernmeldedienste",
    "sg:phone":"+41 12987777",
    "sg:postcode":"8031",
    "sg:province":"Z\u00fcrich",
    "wof:name":"Internet Access Ag",
    "wof:placetype":"venue"
},
  "geometry": {"coordinates":[8.5173215866,47.3811950684],"type":"Point"}
}