{
  "type": "Feature",
  "properties": {
    "addr:full":"Weinfelderstrasse 128a Amriswil Thurgau 8580",
    "addr:housenumber":"128a",
    "addr:postcode":"8580",
    "addr:street":"Weinfelderstrasse",
    "iso:country":"CH",
    "sg:address":"Weinfelderstrasse 128a",
    "sg:city":"Amriswil",
    "sg:orig_category":"Betrieb U technische Hilfsdienste des Kultur U Unterhaltungswesens",
    "sg:postcode":"8580",
    "sg:province":"Thurgau",
    "wof:name":"B\u00e4nziger Irene, Club Service",
    "wof:placetype":"venue"
},
  "geometry": {"coordinates":[9.272199,47.544842],"type":"Point"}
}