{
  "type": "Feature",
  "properties": {
    "iso:country":"CH",
    "sg:address":"Via Emilio Bossi 24",
    "sg:city":"Chiasso",
    "sg:orig_category":"Verwaltung von Immobilien",
    "sg:postcode":"6830",
    "sg:province":"Ticino",
    "wof:name":"Arna Sa",
    "wof:placetype":"venue"
},
  "geometry": {"coordinates":[9.0315494537,45.8352012634],"type":"Point"}
}