{
  "type": "Feature",
  "properties": {
    "iso:country":"CH",
    "sg:address":"Wangenstrasse 40 3360 Herzogenbuchsee. Postfach",
    "sg:city":"Herzogenbuchsee",
    "sg:orig_category":"Fachdetailhandel in Verkaufsr\u00e4umen",
    "sg:phone":"+41 19917333",
    "sg:postcode":"3360",
    "sg:province":"Bern",
    "wof:name":"Global Art Source Gmbh",
    "wof:placetype":"venue"
},
  "geometry": {"coordinates":[8.6072845459,47.2955513],"type":"Point"}
}