{
  "type": "Feature",
  "properties": {
    "iso:country":"CH",
    "sg:address":"Bernstrasse 13 3302 Moosseedorf. Postfach 134",
    "sg:city":"Moosseedorf",
    "sg:orig_category":"Verlegen von Fliesen U Platten Verlegen von Fussboden",
    "sg:phone":"+41 31 858 44 11",
    "sg:postcode":"3302",
    "sg:province":"Bern",
    "wof:name":"Marti Ag Bern Bauunternehmung",
    "wof:placetype":"venue"
},
  "geometry": {"coordinates":[7.4724669456,47.0131340027],"type":"Point"}
}