{
  "type": "Feature",
  "properties": {
    "iso:country":"CH",
    "sg:address":"Impasse Reine Berthe 1",
    "sg:city":"Payerne",
    "sg:orig_category":"Reparatur von Schuhen U Lederwaren",
    "sg:phone":"+41 26 660 16 10",
    "sg:postcode":"1530",
    "sg:province":"Vaud",
    "wof:name":"Francis Rapin Cordonnerie",
    "wof:placetype":"venue"
},
  "geometry": {"coordinates":[6.9369931221,46.8190383911],"type":"Point"}
}