{
  "type": "Feature",
  "properties": {
    "iso:country":"CH",
    "sg:address":"Rossberg",
    "sg:city":"Steinen",
    "sg:classifiers":[
        {
            "category":"Restaurant",
            "type":"Food & Drink"
        }
    ],
    "sg:phone":"+41 41 832 15 59",
    "sg:postcode":"6422",
    "sg:province":"Schwyz",
    "wof:name":"Restaurant Waldegg",
    "wof:placetype":"venue"
},
  "geometry": {"coordinates":[8.6108551025,47.0520935059],"type":"Point"}
}