{
  "type": "Feature",
  "properties": {
    "addr:full":"Conseil-g\u00e9n\u00e9ral Rue Du 20 1205 Gen\u00e8ve. Postfach Gen\u00e8ve Gen\u00e8ve 1201",
    "addr:postcode":"1205;postfach;1201",
    "addr:street":"Rue Du 20",
    "iso:country":"CH",
    "sg:address":"Conseil-g\u00e9n\u00e9ral Rue Du 20 1205 Gen\u00e8ve. Postfach",
    "sg:city":"Gen\u00e8ve",
    "sg:orig_category":"Architektur U Ingenieurb\u00fcros",
    "sg:postcode":"1201",
    "sg:province":"Gen\u00e8ve",
    "wof:name":"Sei Ing\u00e9nieurs Conseils Sa De La Soci\u00e9t\u00e9 Suisse D'electricit\u00e9 Et De Traction Gen\u00e8ve",
    "wof:placetype":"venue"
},
  "geometry": {"coordinates":[6.142701,46.208359],"type":"Point"}
}