{
  "type": "Feature",
  "properties": {
    "iso:country":"CH",
    "sg:address":"5080",
    "sg:city":"Laufenburg",
    "sg:orig_category":"Wirtschaftsverb\u00e4nde Industrie, Handel and Gewerbe",
    "sg:phone":"+41 62 869 63 63",
    "sg:postcode":"5080",
    "sg:province":"Aargau",
    "wof:name":"Verein.export.elektrizit\u00e4ts- Unternehm.,eg-laufenburg Ag",
    "wof:placetype":"venue"
},
  "geometry": {"coordinates":[8.0596504211,47.5564002991],"type":"Point"}
}