{
  "type": "Feature",
  "properties": {
    "iso:country":"CH",
    "sg:address":"4418",
    "sg:city":"Reigoldswil",
    "sg:orig_category":"Verkehrs- and Tourismusb\u00fcros",
    "sg:postcode":"4418",
    "sg:province":"Basel-Landschaft",
    "wof:name":"Verkehrs-& Versch\u00f6nerungs- Verein Reigoldswil",
    "wof:placetype":"venue"
},
  "geometry": {"coordinates":[7.6917262077,47.3970870972],"type":"Point"}
}