{
  "type": "Feature",
  "properties": {
    "iso:country":"CH",
    "sg:address":"Stapfenstrasse 5",
    "sg:city":"K\u00f6niz",
    "sg:orig_category":"Detailhandel mit Waren verschiedener Art, Hauptrichtung Nahrungsmittel",
    "sg:phone":"+41 31 971 38 51",
    "sg:postcode":"3098",
    "sg:province":"Bern",
    "wof:name":"Coop Super Center K\u00f6niz Stapfenm\u00e4rit",
    "wof:placetype":"venue"
},
  "geometry": {"coordinates":[7.4153881073,46.922958374],"type":"Point"}
}