{
  "type": "Feature",
  "properties": {
    "iso:country":"CH",
    "sg:address":"Rehhalde",
    "sg:city":"Cham",
    "sg:orig_category":"Mechanik",
    "sg:postcode":"6330",
    "sg:province":"Zug",
    "wof:name":"Werder Bernhard, Werkzeugschleiferei.",
    "wof:placetype":"venue"
},
  "geometry": {"coordinates":[8.4397754669,47.2038612366],"type":"Point"}
}