{
  "type": "Feature",
  "properties": {
    "iso:country":"CH",
    "sg:address":"Aeschstrasse 112",
    "sg:city":"Ebmatingen",
    "sg:orig_category":"Sportvereine Ski",
    "sg:phone":"+41 41 871 01 23",
    "sg:postcode":"8123",
    "sg:province":"Z\u00fcrich",
    "wof:name":"Skiclub Edelweiss B\u00fcrglen",
    "wof:placetype":"venue"
},
  "geometry": {"coordinates":[8.671339035,46.8765258789],"type":"Point"}
}