{
  "type": "Feature",
  "properties": {
    "iso:country":"CH",
    "sg:address":"Els\u00e4sserstrasse 256",
    "sg:city":"Basel",
    "sg:orig_category":"Grossbanken",
    "sg:phone":"+41 61 327 43 43",
    "sg:postcode":"4056",
    "sg:province":"Basel-Stadt",
    "wof:name":"Ubs Ag Filiale Lysb\u00fcchel",
    "wof:placetype":"venue"
},
  "geometry": {"coordinates":[7.5725240707,47.5767593384],"type":"Point"}
}