{
  "type": "Feature",
  "properties": {
    "iso:country":"CH",
    "sg:address":"Dorfstrasse 22",
    "sg:city":"R\u00fctschelen",
    "sg:orig_category":"Schmieden",
    "sg:phone":"+41 62 922 38 23",
    "sg:postcode":"4933",
    "sg:province":"Bern",
    "wof:name":"Hans Zurfl\u00fch Mechanische Schmiede",
    "wof:placetype":"venue"
},
  "geometry": {"coordinates":[7.7743468285,47.1745262146],"type":"Point"}
}