{
  "type": "Feature",
  "properties": {
    "iso:country":"CH",
    "sg:address":"Stollen",
    "sg:city":"Altendorf",
    "sg:orig_category":"Detailhandel mit Milcherzeugnissen U Eiern Verarbeitung von Milch",
    "sg:phone":"+41 55 442 15 42",
    "sg:postcode":"8852",
    "sg:province":"Schwyz",
    "wof:name":"Cyrill R\u00fcttimann K\u00e4serei",
    "wof:placetype":"venue"
},
  "geometry": {"coordinates":[8.8292293549,47.1925735474],"type":"Point"}
}