{
  "type": "Feature",
  "properties": {
    "iso:country":"CH",
    "sg:address":"Rue St-didier 2",
    "sg:city":"Collombey",
    "sg:orig_category":"Detailhandel mit Brot, Back U S\u00fcsswaren",
    "sg:phone":"+41 24 471 78 18",
    "sg:postcode":"1868",
    "sg:province":"Valais",
    "wof:name":"Roger Corminboeuf Boulangerie & P\u00e2tisserie",
    "wof:placetype":"venue"
},
  "geometry": {"coordinates":[6.947152,46.267834],"type":"Point"}
}