{
  "type": "Feature",
  "properties": {
    "addr:full":"Ennetb\u00fcrgerstr. 47 Buochs Nidwalden 6374",
    "addr:housenumber":"47",
    "addr:postcode":"6374",
    "addr:street":"Ennetbuergerstr.",
    "iso:country":"CH",
    "sg:address":"Ennetb\u00fcrgerstr. 47",
    "sg:city":"Buochs",
    "sg:classifiers":[
        {
            "category":"Manufacturing",
            "subcategory":"Chemicals & Compounds",
            "type":"Manufacturing & Wholesale Goods"
        }
    ],
    "sg:phone":"+41 21 637 17 17",
    "sg:postcode":"6374",
    "sg:province":"Nidwalden",
    "sg:tags":[
        "pharmaceutical",
        "chemistry",
        "-",
        "by-product"
    ],
    "wof:name":"Vernis Claessens S.a.",
    "wof:placetype":"venue"
},
  "geometry": {"coordinates":[6.584172,46.533394],"type":"Point"}
}