{
  "type": "Feature",
  "properties": {
    "iso:country":"CH",
    "sg:address":"Feldmattstrasse 18",
    "sg:city":"Emmen",
    "sg:orig_category":"Autogaragen Autolackierereien",
    "sg:phone":"+41 41 260 66 63",
    "sg:postcode":"6032",
    "sg:province":"Luzern",
    "wof:name":"Burri Emmen Ag Garage & Autospritzwerk",
    "wof:placetype":"venue"
},
  "geometry": {"coordinates":[8.324647,47.108082],"type":"Point"}
}