{
  "type": "Feature",
  "properties": {
    "iso:country":"CH",
    "sg:address":"Hubel",
    "sg:city":"Sch\u00f6nried",
    "sg:orig_category":"Wohnheime",
    "sg:phone":"+41 33 744 28 77",
    "sg:postcode":"3778",
    "sg:province":"Bern",
    "wof:name":"Ferienheim Buebeb\u00e4rg",
    "wof:placetype":"venue"
},
  "geometry": {"coordinates":[7.2904629707,46.5082130432],"type":"Point"}
}