{
  "type": "Feature",
  "properties": {
    "iso:country":"CH",
    "sg:address":"Rue Du Coppet 20",
    "sg:city":"Monthey",
    "sg:classifiers":[
        {
            "category":"Restaurant",
            "type":"Food & Drink"
        }
    ],
    "sg:phone":"+41 24 471 14 22",
    "sg:postcode":"1870",
    "sg:province":"Valais",
    "wof:name":"Caf\u00e9 Bellevue",
    "wof:placetype":"venue"
},
  "geometry": {"coordinates":[6.9513640404,46.2529029846],"type":"Point"}
}