{
  "type": "Feature",
  "properties": {
    "iso:country":"CH",
    "sg:address":"Schmiedengasse 28 3400 Burgdorf. Postfach",
    "sg:city":"Burgdorf",
    "sg:orig_category":"Aktivit\u00e4ten der Generalunternehmen im Baugewerbe Architektur U Ingenieurb\u00fcros",
    "sg:phone":"+41 34 427 77 77",
    "sg:postcode":"3401",
    "sg:province":"Bern",
    "wof:name":"Moser + Partner Ag Architektur Und Ingenieurb\u00fcro, Generalunternehmung",
    "wof:placetype":"venue"
},
  "geometry": {"coordinates":[7.625097,47.055492],"type":"Point"}
}