{
  "type": "Feature",
  "properties": {
    "iso:country":"CH",
    "sg:address":"Erlachstrasse 35",
    "sg:city":"Z\u00fcrich",
    "sg:orig_category":"Werbegrafikateliers",
    "sg:phone":"+41 61 722 06 40",
    "sg:postcode":"8003",
    "sg:province":"Z\u00fcrich",
    "wof:name":"Art Technologies Schneider & Schneider",
    "wof:placetype":"venue"
},
  "geometry": {"coordinates":[7.5154700279,47.5077400208],"type":"Point"}
}