{
  "type": "Feature",
  "properties": {
    "iso:country":"CH",
    "sg:address":"8466",
    "sg:city":"Tr\u00fcllikon",
    "sg:orig_category":"Vorschulen, Kinderg\u00e4rten",
    "sg:phone":"+41 52 319 22 19",
    "sg:postcode":"8466",
    "sg:province":"Z\u00fcrich",
    "wof:name":"Kindergarten",
    "wof:placetype":"venue"
},
  "geometry": {"coordinates":[8.6983699799,47.6336517334],"type":"Point"}
}