{
  "type": "Feature",
  "properties": {
    "addr:full":"B\u00f6rsenstrasse 16 8001 Z\u00fcrich. Postfach 5138 Z\u00fcrich Z\u00fcrich 8022",
    "addr:housenumber":"16",
    "addr:postcode":"8001 zuerich. postfach 5138;8022",
    "addr:street":"Boersenstrasse",
    "iso:country":"CH",
    "sg:address":"B\u00f6rsenstrasse 16 8001 Z\u00fcrich. Postfach 5138",
    "sg:city":"Z\u00fcrich",
    "sg:orig_category":"Aktivit\u00e4t der Bankinstitute",
    "sg:phone":"+41 12654444",
    "sg:postcode":"8022",
    "sg:province":"Z\u00fcrich",
    "wof:name":"Lb (swiss) Privatbank Ag Effekten, Anlagebank Usw",
    "wof:placetype":"venue"
},
  "geometry": {"coordinates":[8.540646,47.368114],"type":"Point"}
}