{
  "type": "Feature",
  "properties": {
    "iso:country":"CH",
    "sg:address":"Chemin Du Boisy 39 1004 Lausanne. Postfach",
    "sg:city":"Lausanne",
    "sg:orig_category":"Fernmeldedienste",
    "sg:phone":"+41 21 646 12 81",
    "sg:postcode":"1003",
    "sg:province":"Vaud",
    "wof:name":"Digitv Sa",
    "wof:placetype":"venue"
},
  "geometry": {"coordinates":[6.614481926,46.5355148315],"type":"Point"}
}