{
  "type": "Feature",
  "properties": {
    "iso:country":"CH",
    "sg:address":"B\u00fcndtenweg 34",
    "sg:city":"H\u00f6lstein",
    "sg:classifiers":[
        {
            "category":"Professional",
            "subcategory":"Engineering",
            "type":"Services"
        }
    ],
    "sg:phone":"+41 61 951 13 75",
    "sg:postcode":"4434",
    "sg:province":"Basel-Landschaft",
    "wof:name":"Air-jet Ag",
    "wof:placetype":"venue"
},
  "geometry": {"coordinates":[7.7709918022,47.4256362915],"type":"Point"}
}