{
  "type": "Feature",
  "properties": {
    "iso:country":"CH",
    "sg:address":"Route Des Pralettes",
    "sg:city":"Marly",
    "sg:orig_category":"Detailhandel mit Waren verschiedener Art, Hauptrichtung Nahrungsmittel",
    "sg:phone":"+41 26 436 23 86",
    "sg:postcode":"1723",
    "sg:province":"Fribourg",
    "wof:name":"Migros Marly-centre",
    "wof:placetype":"venue"
},
  "geometry": {"coordinates":[7.1784071922,46.7683448792],"type":"Point"}
}