{
  "type": "Feature",
  "properties": {
    "iso:country":"CH",
    "sg:address":"H\u00f6hestrasse 71",
    "sg:city":"Zollikon",
    "sg:orig_category":"Architekturb\u00fcros",
    "sg:phone":"+41 13912122",
    "sg:postcode":"8702",
    "sg:province":"Z\u00fcrich",
    "wof:name":"Arnold Schawalder Architekturb\u00fcro",
    "wof:placetype":"venue"
},
  "geometry": {"coordinates":[8.580355,47.340965],"type":"Point"}
}