{
  "type": "Feature",
  "properties": {
    "iso:country":"CH",
    "sg:address":"Breitestrasse 1a",
    "sg:city":"Zihlschlacht",
    "sg:orig_category":"Elektroinstallation",
    "sg:postcode":"8588",
    "sg:province":"Thurgau",
    "wof:name":"Hansueli R\u00f6sti",
    "wof:placetype":"venue"
},
  "geometry": {"coordinates":[7.3968400955,46.507598877],"type":"Point"}
}