{
  "type": "Feature",
  "properties": {
    "iso:country":"CH",
    "sg:address":"Rue De Bourg 25",
    "sg:city":"Lausanne",
    "sg:orig_category":"Hundesalons",
    "sg:phone":"+41 21 312 55 34",
    "sg:postcode":"1003",
    "sg:province":"Vaud",
    "wof:name":"Natascha Rapin Salon Pr Chiens Au Joli Chien",
    "wof:placetype":"venue"
},
  "geometry": {"coordinates":[6.6355462074,46.5201568604],"type":"Point"}
}