{
  "type": "Feature",
  "properties": {
    "iso:country":"CH",
    "sg:address":"Avenue Verdeil 36",
    "sg:city":"Lausanne",
    "sg:orig_category":"Architekturb\u00fcros Detailhandel mit Waren verschiedener Art, Hauptrichtung Nahrungsmittel",
    "sg:phone":"+41 21 729 46 60",
    "sg:postcode":"1005",
    "sg:province":"Vaud",
    "wof:name":"Englert F.",
    "wof:placetype":"venue"
},
  "geometry": {"coordinates":[6.650756,46.518425],"type":"Point"}
}