{
  "type": "Feature",
  "properties": {
    "iso:country":"CH",
    "sg:address":"L\u00e4rchenweg 3 Birchwil",
    "sg:city":"N\u00fcrensdorf",
    "sg:orig_category":"Nachrichten\u00fcbermittlung Radio U Fernsehanstalten",
    "sg:phone":"+41 31 350 92 22",
    "sg:postcode":"8309",
    "sg:province":"Z\u00fcrich",
    "wof:name":"Swissinfo/schweizer Radio International Ein Unternehmen Der Srg Ssr Id\u00e9e Suisse",
    "wof:placetype":"venue"
},
  "geometry": {"coordinates":[7.4738278389,46.9438514709],"type":"Point"}
}