{
  "type": "Feature",
  "properties": {
    "iso:country":"CH",
    "sg:address":"Bohlstrasse 2a",
    "sg:city":"Uznach",
    "sg:orig_category":"G\u00fcterbef\u00f6rderung im Strassenverkehr Sonstige Personenbef\u00f6rderung im Landverkehr",
    "sg:phone":"+41 55 280 64 26",
    "sg:postcode":"8730",
    "sg:province":"St. Gallen",
    "wof:name":"Kurt Paul K\u00fchne Kasar Auto Allrounder",
    "wof:placetype":"venue"
},
  "geometry": {"coordinates":[8.9944124222,47.2210388184],"type":"Point"}
}