{
  "type": "Feature",
  "properties": {
    "iso:country":"CH",
    "sg:address":"5643 Sins. Postfach",
    "sg:city":"Sins",
    "sg:orig_category":"Handels-H\u00e4user U Gesellschaften",
    "sg:postcode":"5643",
    "sg:province":"Aargau",
    "wof:name":"Dres Ag.",
    "wof:placetype":"venue"
},
  "geometry": {"coordinates":[8.3962402344,47.188243866],"type":"Point"}
}