{
  "type": "Feature",
  "properties": {
    "addr:full":"Habsburgstrasse 35 Luzern Luzern 6003",
    "addr:housenumber":"35",
    "addr:postcode":"6003",
    "addr:street":"Habsburgstrasse",
    "iso:country":"CH",
    "sg:address":"Habsburgstrasse 35",
    "sg:city":"Luzern",
    "sg:orig_category":"Architekturb\u00fcros",
    "sg:phone":"+41 41 210 88 70",
    "sg:postcode":"6003",
    "sg:province":"Luzern",
    "wof:name":"Kunz & Portmann Architekturb\u00fcro",
    "wof:placetype":"venue"
},
  "geometry": {"coordinates":[8.305862,47.04615],"type":"Point"}
}