{
  "type": "Feature",
  "properties": {
    "iso:country":"CH",
    "sg:address":"Sempacherstrasse 1",
    "sg:city":"Luzern",
    "sg:orig_category":"Finanzierungsinstitutionen",
    "sg:phone":"+41 41 220 12 15",
    "sg:postcode":"6003",
    "sg:province":"Luzern",
    "wof:name":"Ficon Holzgang Gmbh",
    "wof:placetype":"venue"
},
  "geometry": {"coordinates":[8.307179451,47.0491943359],"type":"Point"}
}