{
  "type": "Feature",
  "properties": {
    "iso:country":"CH",
    "sg:address":"Rue De Rive 6b",
    "sg:city":"Nyon",
    "sg:orig_category":"Unternehmensberatung",
    "sg:phone":"+41 22 361 40 69",
    "sg:postcode":"1260",
    "sg:province":"Vaud",
    "wof:name":"Kenneth Dogra The Amerac Consultancy",
    "wof:placetype":"venue"
},
  "geometry": {"coordinates":[6.2452669144,46.3847084045],"type":"Point"}
}