{
  "type": "Feature",
  "properties": {
    "iso:country":"CH",
    "sg:address":"Steinmattstrasse 38",
    "sg:city":"Zermatt",
    "sg:orig_category":"Sanit\u00e4rinstallation",
    "sg:phone":"+41 27 967 26 27",
    "sg:postcode":"3920",
    "sg:province":"Valais",
    "wof:name":"Furrer & Sohn Sanit\u00e4r-installationen",
    "wof:placetype":"venue"
},
  "geometry": {"coordinates":[7.7484030724,46.018409729],"type":"Point"}
}