{
  "type": "Feature",
  "properties": {
    "iso:country":"CH",
    "sg:address":"K\u00f6nizstrasse 265 3097 Liebefeld. Postfach",
    "sg:city":"Liebefeld",
    "sg:orig_category":"Detailhandel mit Schuhen Detailhandel mit Schuhen U Lederwaren",
    "sg:phone":"+41 21 801 30 93",
    "sg:postcode":"3097",
    "sg:province":"Bern",
    "wof:name":"Fessler Jean-pierre",
    "wof:placetype":"venue"
},
  "geometry": {"coordinates":[6.4981660843,46.5091514587],"type":"Point"}
}