{
  "type": "Feature",
  "properties": {
    "iso:country":"CH",
    "sg:address":"Puits-saint-pierrerue Du 1 1204 Gen\u00e8ve. Postfach",
    "sg:city":"Gen\u00e8ve",
    "sg:orig_category":"RESTAURANTS: TEA-ROOMS",
    "sg:phone":"+41 22 310 91 72",
    "sg:postcode":"1204",
    "sg:province":"Gen\u00e8ve",
    "wof:name":"A. Granges",
    "wof:placetype":"venue"
},
  "geometry": {"coordinates":[6.1473960876,46.2013549805],"type":"Point"}
}