{
  "type": "Feature",
  "properties": {
    "iso:country":"CH",
    "sg:address":"Bahnhofstrasse 6",
    "sg:city":"Wasen",
    "sg:classifiers":[
        {
            "category":"Banks & Credit Unions",
            "subcategory":"Bank",
            "type":"Services"
        }
    ],
    "sg:phone":"+41 34771337",
    "sg:postcode":"3457",
    "sg:province":"Bern",
    "wof:name":"Spar- U. Leihkasse Sumiswald",
    "wof:placetype":"venue"
},
  "geometry": {"coordinates":[7.793924,47.043026],"type":"Point"}
}