{
  "type": "Feature",
  "properties": {
    "iso:country":"CH",
    "sg:address":"Badenerstrasse 682",
    "sg:city":"Z\u00fcrich",
    "sg:orig_category":"Softwareentwicklung U beratung",
    "sg:phone":"+41 14402965",
    "sg:postcode":"8045",
    "sg:province":"Z\u00fcrich",
    "wof:name":"Bitplane Ag Edv-produkte Bes Software, Hardware Usw.; Entw., Vertrieb",
    "wof:placetype":"venue"
},
  "geometry": {"coordinates":[8.4853191376,47.3881072998],"type":"Point"}
}