{
  "type": "Feature",
  "properties": {
    "iso:country":"CH",
    "sg:address":"Brotheiteri",
    "sg:city":"Niederh\u00fcnigen",
    "sg:orig_category":"Gartenbau",
    "sg:postcode":"3504",
    "sg:province":"Bern",
    "wof:name":"Arvenbaumschule Walter Zurbuchen",
    "wof:placetype":"venue"
},
  "geometry": {"coordinates":[7.6350870132,46.8770141602],"type":"Point"}
}