{
  "type": "Feature",
  "properties": {
    "iso:country":"CH",
    "sg:address":"In Der Rebhalden 11",
    "sg:city":"Urdorf",
    "sg:orig_category":"Architektur U Ingenieurb\u00fcros",
    "sg:phone":"+41 17340557",
    "sg:postcode":"8902",
    "sg:province":"Z\u00fcrich",
    "wof:name":"Ingenieurb\u00fcro Mazan Ag",
    "wof:placetype":"venue"
},
  "geometry": {"coordinates":[8.433224,47.385887],"type":"Point"}
}