{
  "type": "Feature",
  "properties": {
    "iso:country":"CH",
    "sg:address":"Ouchy Avenue D' 43 1006 Lausanne. Postfach",
    "sg:city":"Lausanne",
    "sg:orig_category":"RESTAURANTS: TEA-ROOMS",
    "sg:phone":"+41 21 616 22 33",
    "sg:postcode":"1006",
    "sg:province":"Vaud",
    "wof:name":"Blanc Bernadette Caf\u00e9-restaurant De La Croix-d'ouchy",
    "wof:placetype":"venue"
},
  "geometry": {"coordinates":[6.6385297775,46.5106391907],"type":"Point"}
}