{
  "type": "Feature",
  "properties": {
    "iso:country":"CH",
    "sg:address":"Untere Einschlagstrasse 5",
    "sg:city":"Wynau",
    "sg:orig_category":"Verwaltung von Immobilien Wirtschaftspr\u00fcfung, Steuerberatung U Treuhand",
    "sg:phone":"+41 62 918 10 20",
    "sg:postcode":"4923",
    "sg:province":"Bern",
    "wof:name":"Vorstadt Treuhand Ag",
    "wof:placetype":"venue"
},
  "geometry": {"coordinates":[7.8227028847,47.2572364807],"type":"Point"}
}