{
  "type": "Feature",
  "properties": {
    "iso:country":"CH",
    "sg:address":"2207",
    "sg:city":"Coffrane",
    "sg:orig_category":"Primarschulen",
    "sg:phone":"+41 32 853 68 62",
    "sg:postcode":"2207",
    "sg:province":"Neuch\u00e2tel",
    "wof:name":"Ecole Primaire",
    "wof:placetype":"venue"
},
  "geometry": {"coordinates":[6.8742251396,47.0492553711],"type":"Point"}
}