{
  "type": "Feature",
  "properties": {
    "iso:country":"CH",
    "sg:address":"Rue De La Pierre-perc\u00e9e 28",
    "sg:city":"Courgenay",
    "sg:orig_category":"Maschinen and Apparate divers Grosshandel",
    "sg:phone":"+41 32 471 15 56",
    "sg:postcode":"2950",
    "sg:province":"Jura",
    "wof:name":"Lucette Glauser Automates \u00e0 Musique",
    "wof:placetype":"venue"
},
  "geometry": {"coordinates":[7.1179227829,47.4069519043],"type":"Point"}
}