{
  "type": "Feature",
  "properties": {
    "iso:country":"CH",
    "sg:address":"Riedthofstrasse 214 8105 Regensdorf. Postfach",
    "sg:city":"Z\u00fcrich",
    "sg:orig_category":"Lagerh\u00e4user, G\u00fcterumschlag, Verteilzentren",
    "sg:phone":"+41 22 818 11 11",
    "sg:postcode":"8045",
    "sg:province":"Z\u00fcrich",
    "wof:name":"Brunschwig & Cie Sa",
    "wof:placetype":"venue"
},
  "geometry": {"coordinates":[6.1414251328,46.1833114624],"type":"Point"}
}