{
  "type": "Feature",
  "properties": {
    "iso:country":"CH",
    "sg:address":"Rheinstrasse 39",
    "sg:city":"Felsberg",
    "sg:orig_category":"Bau U Wohngenossenschaften",
    "sg:phone":"+41 81 252 39 54",
    "sg:postcode":"7012",
    "sg:province":"Graubunden",
    "wof:name":"Wohnbaugenossenschaft Felsberg",
    "wof:placetype":"venue"
},
  "geometry": {"coordinates":[9.484634,46.845894],"type":"Point"}
}