{
  "type": "Feature",
  "properties": {
    "iso:country":"CH",
    "sg:address":"Bleulerstrasse 16",
    "sg:city":"Z\u00fcrich",
    "sg:orig_category":"Architektur U Ingenieurb\u00fcros Architekturb\u00fcros",
    "sg:phone":"+41 71 245 70 70",
    "sg:postcode":"8008",
    "sg:province":"Z\u00fcrich",
    "wof:name":"Richle + R\u00fcesch Architekten Ag",
    "wof:placetype":"venue"
},
  "geometry": {"coordinates":[9.387293,47.434761],"type":"Point"}
}