{
  "type": "Feature",
  "properties": {
    "iso:country":"CH",
    "sg:address":"Geimoosstrasse 12",
    "sg:city":"St\u00e4fa",
    "sg:orig_category":"Detailhandel mit Teppichen Verlegen von Fussboden",
    "sg:phone":"+41 19265574",
    "sg:postcode":"8712",
    "sg:province":"Z\u00fcrich",
    "wof:name":"Rolf Steiger Teppichgesch\u00e4ft",
    "wof:placetype":"venue"
},
  "geometry": {"coordinates":[8.7311086655,47.2424850464],"type":"Point"}
}