{
  "type": "Feature",
  "properties": {
    "iso:country":"CH",
    "sg:address":"1974",
    "sg:city":"Arbaz",
    "sg:orig_category":"Primarschulen",
    "sg:phone":"+41 27 764 15 10",
    "sg:postcode":"1974",
    "sg:province":"Valais",
    "wof:name":"Ecole Primaire",
    "wof:placetype":"venue"
},
  "geometry": {"coordinates":[7.3841748238,46.273109436],"type":"Point"}
}