{
  "type": "Feature",
  "properties": {
    "iso:country":"CH",
    "sg:address":"Von Roll-areal 57",
    "sg:city":"Balsthal",
    "sg:orig_category":"Softwareentwicklung U beratung",
    "sg:phone":"+41 62 391 86 86",
    "sg:postcode":"4710",
    "sg:province":"Solothurn",
    "wof:name":"Electro Cube Ag",
    "wof:placetype":"venue"
},
  "geometry": {"coordinates":[7.6974248886,47.3006782532],"type":"Point"}
}