{
  "type": "Feature",
  "properties": {
    "iso:country":"CH",
    "sg:address":"Hauptstrasse 5 6280 Hochdorf. Postfach 34",
    "sg:city":"Hochdorf",
    "sg:orig_category":"Finanzierungsinstitutionen",
    "sg:postcode":"6280",
    "sg:province":"Luzern",
    "wof:name":"Esbi Ag",
    "wof:placetype":"venue"
},
  "geometry": {"coordinates":[8.2905950546,47.1663360596],"type":"Point"}
}