{
  "type": "Feature",
  "properties": {
    "iso:country":"CH",
    "sg:address":"Neubruchstrasse 31",
    "sg:city":"Winterthur",
    "sg:orig_category":"Sonstige pers\u00f6nliche Dienstleistungen",
    "sg:postcode":"8406",
    "sg:province":"Z\u00fcrich",
    "wof:name":"Angel Lifestyle Gmbh",
    "wof:placetype":"venue"
},
  "geometry": {"coordinates":[8.6979017258,47.4832382202],"type":"Point"}
}