{
  "type": "Feature",
  "properties": {
    "iso:country":"CH",
    "sg:address":"Avenue D.-jeanrichard 2 2114 Fleurier Case Postale 353",
    "sg:city":"Fleurier",
    "sg:orig_category":"Herstellung von sonstigen elektrischen Ausr\u00fcstungen",
    "sg:phone":"+41 32 861 11 31",
    "sg:postcode":"2114",
    "sg:province":"Neuch\u00e2tel",
    "wof:name":"Pulzer Electronic",
    "wof:placetype":"venue"
},
  "geometry": {"coordinates":[6.5827231407,46.9054412842],"type":"Point"}
}