{
  "type": "Feature",
  "properties": {
    "iso:country":"CH",
    "sg:address":"Delsbergerstrasse 82",
    "sg:city":"Laufen",
    "sg:classifiers":[
        {
            "category":"Travel",
            "subcategory":"Hotels & Motels",
            "type":"Entertainment"
        }
    ],
    "sg:phone":"+41 33 822 23 53",
    "sg:postcode":"4242",
    "sg:province":"Basel-Landschaft",
    "sg:tags":[
        "hotels",
        "mit",
        "restaurant"
    ],
    "wof:name":"Hotel Brienzersee",
    "wof:placetype":"venue"
},
  "geometry": {"coordinates":[7.8984708786,46.702583313],"type":"Point"}
}