{
  "type": "Feature",
  "properties": {
    "iso:country":"CH",
    "sg:address":"K\u00fcttigerstrasse 42",
    "sg:city":"Aarau",
    "sg:orig_category":"Detailhandel mit M\u00f6beln U Haushaltsgegenst\u00e4nden",
    "sg:phone":"+41 62 823 15 15",
    "sg:postcode":"5000",
    "sg:province":"Aargau",
    "wof:name":"Fmt-hirsbrunner Wohnmarkt Ag",
    "wof:placetype":"venue"
},
  "geometry": {"coordinates":[8.042012,47.398861],"type":"Point"}
}