{
  "type": "Feature",
  "properties": {
    "iso:country":"CH",
    "sg:address":"Route D'hauteville 2",
    "sg:city":"St-l\u00e9gier",
    "sg:orig_category":"Farben and Lacke Detailhandel Tapeten Detailhandel",
    "sg:postcode":"1806",
    "sg:province":"Vaud",
    "wof:name":"Novorama Sa",
    "wof:placetype":"venue"
},
  "geometry": {"coordinates":[6.8943781853,46.4655380249],"type":"Point"}
}