{
  "type": "Feature",
  "properties": {
    "iso:country":"CH",
    "sg:address":"Im Kupferschmied 8 4663 Aarburg. Postfach",
    "sg:city":"Aarburg",
    "sg:orig_category":"Herstellung von Metallkonstruktionen",
    "sg:postcode":"4663",
    "sg:province":"Aargau",
    "wof:name":"Dibrani Gmbh Montage Im Bausektor, Bes. Im Bereich Fensterbau",
    "wof:placetype":"venue"
},
  "geometry": {"coordinates":[7.8997440338,47.3292541504],"type":"Point"}
}