{
  "type": "Feature",
  "properties": {
    "iso:country":"CH",
    "sg:address":"Marktstrasse 2",
    "sg:city":"Sarnen",
    "sg:orig_category":"Sonstiger Fachdetailhandel in Verkaufsr\u00e4umen",
    "sg:phone":"+41 41 660 16 77",
    "sg:postcode":"6060",
    "sg:province":"Obwalden",
    "wof:name":"Leopold Von Wyl B\u00e9b\u00e9haus Kinderwagen",
    "wof:placetype":"venue"
},
  "geometry": {"coordinates":[8.2486801147,46.8961601257],"type":"Point"}
}