{
  "type": "Feature",
  "properties": {
    "iso:country":"CH",
    "sg:address":"Grand-rue 62",
    "sg:city":"Payerne",
    "sg:orig_category":"Detailhandel mit Waren verschiedener Art, Hauptrichtung Nahrungsmittel Grosshandel mit Obst U Gem\u00fcse",
    "sg:phone":"+41 26 660 27 88",
    "sg:postcode":"1530",
    "sg:province":"Vaud",
    "wof:name":"Cantaluppi Sa",
    "wof:placetype":"venue"
},
  "geometry": {"coordinates":[6.936732769,46.8212280273],"type":"Point"}
}