{
  "type": "Feature",
  "properties": {
    "iso:country":"CH",
    "sg:address":"Roger-de-lessert Rue 1164 Buchillon. Postfach",
    "sg:city":"Buchillon",
    "sg:orig_category":"Unclassifiable Establishments",
    "sg:phone":"+41 21 634 97 50",
    "sg:postcode":"1164",
    "sg:province":"Vaud",
    "wof:name":"Ampa Finance Holding Sa",
    "wof:placetype":"venue"
},
  "geometry": {"coordinates":[6.4219899178,46.4703712463],"type":"Point"}
}