{
  "type": "Feature",
  "properties": {
    "iso:country":"CH",
    "sg:address":"3513",
    "sg:city":"Bigenthal",
    "sg:orig_category":"Sportvereine Sch\u00fctzen",
    "sg:phone":"+41 52 745 12 14",
    "sg:postcode":"3513",
    "sg:province":"Bern",
    "wof:name":"Sch\u00fctzengesellschaft",
    "wof:placetype":"venue"
},
  "geometry": {"coordinates":[7.6249299049,46.9669494629],"type":"Point"}
}