{
  "type": "Feature",
  "properties": {
    "iso:country":"CH",
    "sg:address":"K\u00e4serei",
    "sg:city":"Bumbach",
    "sg:orig_category":"Sportvereine Schwingen",
    "sg:phone":"+41 34 493 39 60",
    "sg:postcode":"6197",
    "sg:province":"Bern",
    "wof:name":"Schwingklub Schangnau-siehen",
    "wof:placetype":"venue"
},
  "geometry": {"coordinates":[7.8605628014,46.8275260925],"type":"Point"}
}