{
  "type": "Feature",
  "properties": {
    "iso:country":"CH",
    "sg:address":"Werkstrasse 4",
    "sg:city":"Chur",
    "sg:orig_category":"Vereine Musik/Blasmusik",
    "sg:phone":"+41 81 284 04 31",
    "sg:postcode":"7000",
    "sg:province":"Graubunden",
    "wof:name":"Musikgesellschaft Alpina",
    "wof:placetype":"venue"
},
  "geometry": {"coordinates":[9.5264291763,46.8561592102],"type":"Point"}
}