{
  "type": "Feature",
  "properties": {
    "iso:country":"CH",
    "sg:address":"Schulhausstrasse 4 9247 Henau. Postfach",
    "sg:city":"Henau",
    "sg:orig_category":"Grosshandel mit B\u00fcromaschinen U einrichtungen",
    "sg:phone":"+41 71 955 95 95",
    "sg:postcode":"9247",
    "sg:province":"St. Gallen",
    "wof:name":"Rwd Henau Ag",
    "wof:placetype":"venue"
},
  "geometry": {"coordinates":[9.117351532,47.4542007446],"type":"Point"}
}