{
  "type": "Feature",
  "properties": {
    "addr:full":"Bahnhofstrasse 5 3900 Brig. Postfach Brig Valais 3900",
    "addr:housenumber":"5",
    "addr:postcode":"3900;postfach;3900",
    "addr:street":"Bahnhofstrasse",
    "iso:country":"CH",
    "sg:address":"Bahnhofstrasse 5 3900 Brig. Postfach",
    "sg:city":"Brig",
    "sg:orig_category":"Detailhandel mit Brot, Back U S\u00fcsswaren",
    "sg:phone":"+41 27 923 35 25",
    "sg:postcode":"3900",
    "sg:province":"Valais",
    "wof:name":"Fritz Volken B\u00e4ckerei-konditorei",
    "wof:placetype":"venue"
},
  "geometry": {"coordinates":[7.988399,46.318226],"type":"Point"}
}