{
  "type": "Feature",
  "properties": {
    "iso:country":"CH",
    "sg:address":"Oberach 6",
    "sg:city":"Rehetobel",
    "sg:orig_category":"Einbau von Schreinerwaren Herstellung von K\u00fcchenm\u00f6beln",
    "sg:phone":"+41 71 877 21 48",
    "sg:postcode":"9038",
    "sg:province":"Appenzell Ausserrhoden",
    "wof:name":"Schott- Grossk\u00fccheneinrichtungen",
    "wof:placetype":"venue"
},
  "geometry": {"coordinates":[9.5011034012,47.4298248291],"type":"Point"}
}