{
  "type": "Feature",
  "properties": {
    "iso:country":"CH",
    "sg:address":"R\u00f6merstr. 20 4500 Solothurn. Postfach",
    "sg:city":"Solothurn",
    "sg:orig_category":"Pensionskassen",
    "sg:postcode":"4500",
    "sg:province":"Solothurn",
    "wof:name":"Alters- & F\u00fcrsorge-fonds F\u00fcr Das Personal Der Firma Gubelmann & Cie, In Wetzikon",
    "wof:placetype":"venue"
},
  "geometry": {"coordinates":[8.8039503098,47.3208084106],"type":"Point"}
}