{
  "type": "Feature",
  "properties": {
    "iso:country":"CH",
    "sg:address":"Freiestrasse 45",
    "sg:city":"Amriswil",
    "sg:orig_category":"Grosshandel mit Sportartikeln",
    "sg:phone":"+41 71 411 11 69",
    "sg:postcode":"8580",
    "sg:province":"Thurgau",
    "wof:name":"Tandem Gmbh Sportartikel-import/export",
    "wof:placetype":"venue"
},
  "geometry": {"coordinates":[9.2945165634,47.5494766235],"type":"Point"}
}