{
  "type": "Feature",
  "properties": {
    "iso:country":"CH",
    "sg:address":"Route De Lossy 8",
    "sg:city":"Belfaux",
    "sg:classifiers":[
        {
            "category":"Mining & Drilling",
            "type":"Manufacturing & Wholesale Goods"
        }
    ],
    "sg:phone":"+41 26 475 26 25",
    "sg:postcode":"1782",
    "sg:province":"Fribourg",
    "sg:tags":[
        "ground"
    ],
    "wof:name":"Geotherm Sa",
    "wof:placetype":"venue"
},
  "geometry": {"coordinates":[7.1080107689,46.8223838806],"type":"Point"}
}