{
  "type": "Feature",
  "properties": {
    "iso:country":"CH",
    "sg:address":"Bethl\u00e9em Chemin De 8 1700 Fribourg. Postfach",
    "sg:city":"Fribourg",
    "sg:orig_category":"Kauf U Verkauf von Immobilien auf eigene Rechnung",
    "sg:postcode":"1700",
    "sg:province":"Fribourg",
    "wof:name":"Royal Resorts Caribbean Sa D\u00e9tention De Tous Biens Pour Son Compte Principalement Ou Pour Le Compte De Tiers Etc",
    "wof:placetype":"venue"
},
  "geometry": {"coordinates":[7.1536831856,46.8037452698],"type":"Point"}
}