{
  "type": "Feature",
  "properties": {
    "iso:country":"CH",
    "sg:address":"6527",
    "sg:city":"Lodrino",
    "sg:orig_category":"Non-Classified Establishments",
    "sg:phone":"+41 91 863 16 43",
    "sg:postcode":"6527",
    "sg:province":"Ticino",
    "wof:name":"Sa Figli Fu Bignasca Francesco",
    "wof:placetype":"venue"
},
  "geometry": {"coordinates":[8.9811306,46.2996673584],"type":"Point"}
}