{
  "type": "Feature",
  "properties": {
    "iso:country":"CH",
    "sg:address":"Hauptgasse 22a",
    "sg:city":"Appenzell",
    "sg:orig_category":"Grosshandel mit Parf\u00fcmerieartikeln U K\u00f6rperpflegemitteln Herstellung von Duft U K\u00f6rperpflegemitteln",
    "sg:phone":"+41 71 780 08 82",
    "sg:postcode":"9050",
    "sg:province":"Appenzell Innerhoden",
    "wof:name":"Simex Trading Ag",
    "wof:placetype":"venue"
},
  "geometry": {"coordinates":[9.4089279175,47.330871582],"type":"Point"}
}