{
  "type": "Feature",
  "properties": {
    "iso:country":"CH",
    "sg:address":"6523",
    "sg:city":"Preonzo",
    "sg:orig_category":"Allgemeiner Hoch U Tiefbau",
    "sg:phone":"+41 41 260 25 40",
    "sg:postcode":"6523",
    "sg:province":"Ticino",
    "wof:name":"Metraplan Ag",
    "wof:placetype":"venue"
},
  "geometry": {"coordinates":[8.311483,46.985725],"type":"Point"}
}