{
  "type": "Feature",
  "properties": {
    "iso:country":"CH",
    "sg:address":"Hinterer R\u00fctzelenweg 2 4704 Niederbipp. Postfach",
    "sg:city":"Niederbipp",
    "sg:orig_category":"Autogaragen Instandhaltung U Reparatur von Automobilen",
    "sg:phone":"+41 32 633 29 18",
    "sg:postcode":"4704",
    "sg:province":"Bern",
    "wof:name":"Ad Garage Landert Gmbh",
    "wof:placetype":"venue"
},
  "geometry": {"coordinates":[7.683639,47.26688],"type":"Point"}
}