{
  "type": "Feature",
  "properties": {
    "iso:country":"CH",
    "sg:address":"Burgstrasse 28",
    "sg:city":"Glarus",
    "sg:orig_category":"Sonstiger Grosshandel",
    "sg:postcode":"8750",
    "sg:province":"Glarus",
    "wof:name":"Global, Handels Und Beteiligungs Ag",
    "wof:placetype":"venue"
},
  "geometry": {"coordinates":[9.0686101913,47.041179657],"type":"Point"}
}