{
  "type": "Feature",
  "properties": {
    "iso:country":"CH",
    "sg:address":"Delsbergerstrasse 31 4242 Laufen. Postfach 127",
    "sg:city":"Laufen",
    "sg:orig_category":"F\u00fcrsorge\u00e4mter",
    "sg:phone":"+41 61 761 70 74",
    "sg:postcode":"4242",
    "sg:province":"Basel-Landschaft",
    "wof:name":"Amtsvormundschaft Des Kreises Laufen",
    "wof:placetype":"venue"
},
  "geometry": {"coordinates":[7.5005230904,47.4195976257],"type":"Point"}
}