{
  "type": "Feature",
  "properties": {
    "iso:country":"CH",
    "sg:address":"Via S. Maddalena",
    "sg:city":"Taverne",
    "sg:orig_category":"Reiseb\u00fcros U Reiseveranstalter",
    "sg:phone":"+41 91 945 52 78",
    "sg:postcode":"6807",
    "sg:province":"Ticino",
    "wof:name":"La Bottega Dei Viaggi Di D'alessio-negrini Sandra",
    "wof:placetype":"venue"
},
  "geometry": {"coordinates":[8.9349155426,46.0676002502],"type":"Point"}
}