{
  "type": "Feature",
  "properties": {
    "iso:country":"CH",
    "sg:address":"Bahnhofstrasse 78",
    "sg:city":"Z\u00fcrich",
    "sg:orig_category":"Detailhandel mit Uhren U Schmuck Reparatur von Uhren U Schmuck",
    "sg:phone":"+41 12121447",
    "sg:postcode":"8001",
    "sg:province":"Z\u00fcrich",
    "wof:name":"Christ Uhren & Schmuck Ag",
    "wof:placetype":"venue"
},
  "geometry": {"coordinates":[8.5390253067,47.3748817444],"type":"Point"}
}