{
  "type": "Feature",
  "properties": {
    "iso:country":"CH",
    "sg:address":"Petit-ch\u00eane Rue Du 38",
    "sg:city":"Lausanne",
    "sg:orig_category":"Herstellung von sonstigen Nahrungsmitteln",
    "sg:phone":"+41 21 903 03 20",
    "sg:postcode":"1003",
    "sg:province":"Vaud",
    "wof:name":"Grosjean Produits Alimentaires Sa",
    "wof:placetype":"venue"
},
  "geometry": {"coordinates":[6.6289992332,46.5177955627],"type":"Point"}
}