{
  "type": "Feature",
  "properties": {
    "iso:country":"CH",
    "sg:address":"S\u00e4gegasse 27",
    "sg:city":"Burgdorf",
    "sg:orig_category":"Unclassifiable Establishments",
    "sg:phone":"+41 34 422 66 44",
    "sg:postcode":"3400",
    "sg:province":"Bern",
    "wof:name":"Baumann & Co Ag, Burgdorf",
    "wof:placetype":"venue"
},
  "geometry": {"coordinates":[7.6299748421,47.0543785095],"type":"Point"}
}