{
  "type": "Feature",
  "properties": {
    "iso:country":"CH",
    "sg:address":"Bergackerweg 5 4802 Strengelbach. Postfach 57",
    "sg:city":"Strengelbach",
    "sg:orig_category":"Herstellung von K\u00fcchenm\u00f6beln",
    "sg:phone":"+41 62 746 86 86",
    "sg:postcode":"4802",
    "sg:province":"Aargau",
    "wof:name":"Alpnach-k\u00fcchen Ag",
    "wof:placetype":"venue"
},
  "geometry": {"coordinates":[7.9298391342,47.2771530151],"type":"Point"}
}