{
  "type": "Feature",
  "properties": {
    "iso:country":"CH",
    "sg:address":"8953 Dietikon 2. Postfach 78",
    "sg:city":"Dietikon",
    "sg:orig_category":"Baugewerbe Immobilienwesen",
    "sg:phone":"+41 79 336 15 25",
    "sg:postcode":"8953",
    "sg:province":"Z\u00fcrich",
    "wof:name":"Mesitec Mettler Sicherheitstechnik",
    "wof:placetype":"venue"
},
  "geometry": {"coordinates":[8.40369,47.403889],"type":"Point"}
}