{
  "type": "Feature",
  "properties": {
    "iso:country":"CH",
    "sg:address":"Autostradale Nord",
    "sg:city":"Bellinzona",
    "sg:orig_category":"Tankstellen",
    "sg:phone":"+41 91 825 04 27",
    "sg:postcode":"6500",
    "sg:province":"Ticino",
    "wof:name":"Area Di Servizio Bellinzona Nord Lucerna-chiasso Shell",
    "wof:placetype":"venue"
},
  "geometry": {"coordinates":[9.0241193771,46.1944618225],"type":"Point"}
}