{
  "type": "Feature",
  "properties": {
    "iso:country":"CH",
    "sg:address":"Staldenstrasse 3",
    "sg:city":"Gebenstorf",
    "sg:orig_category":"Grosshandel mit Eisenwaren sowie Installationsbedarf f\u00fcr Gas, Wasser U Heizung Herstellung von Metal",
    "sg:postcode":"5412",
    "sg:province":"Aargau",
    "wof:name":"Paul Manzoni",
    "wof:placetype":"venue"
},
  "geometry": {"coordinates":[8.2447576523,47.4843254089],"type":"Point"}
}