{
  "type": "Feature",
  "properties": {
    "iso:country":"CH",
    "sg:address":"Waldeggstrasse 81",
    "sg:city":"Winterthur",
    "sg:orig_category":"Bauschreinerei Innenausbau",
    "sg:phone":"+41 33 733 11 31",
    "sg:postcode":"8405",
    "sg:province":"Z\u00fcrich",
    "wof:name":"Kurt Schmid Schreinerei & Innenausbau",
    "wof:placetype":"venue"
},
  "geometry": {"coordinates":[7.444872,46.459221],"type":"Point"}
}