{
  "type": "Feature",
  "properties": {
    "iso:country":"CH",
    "sg:address":"T\u00e4fernstr. 30 5405 Baden",
    "sg:city":"D\u00e4ttwil",
    "sg:classifiers":[
        {
            "category":"Utilities",
            "subcategory":"Telephone",
            "type":"Services"
        }
    ],
    "sg:phone":"+41 56 484 11 11",
    "sg:postcode":"5",
    "sg:tags":[
        "information",
        "peripheral",
        "-",
        "telecommunication",
        "technology"
    ],
    "wof:name":"Brother Schweiz Ag",
    "wof:placetype":"venue"
},
  "geometry": {"coordinates":[8.287886,47.452225],"type":"Point"}
}