{
  "type": "Feature",
  "properties": {
    "iso:country":"CH",
    "sg:address":"Route De B\u00e2le 25",
    "sg:city":"Del\u00e9mont",
    "sg:classifiers":[
        {
            "category":"Travel",
            "subcategory":"Hotels & Motels",
            "type":"Entertainment"
        }
    ],
    "sg:phone":"+41 21 963 61 81",
    "sg:postcode":"2800",
    "sg:province":"Jura",
    "sg:tags":[
        "hotels",
        "mit",
        "restaurant"
    ],
    "wof:name":"H\u00f4tel Le Parc-righi",
    "wof:placetype":"venue"
},
  "geometry": {"coordinates":[6.926030159,46.4337882996],"type":"Point"}
}