{
  "type": "Feature",
  "properties": {
    "iso:country":"CH",
    "sg:address":"Rue De Lausanne 3 1530 Payerne Case Postale 399",
    "sg:city":"Payerne",
    "sg:orig_category":"Handel mit Motorr\u00e4dern, Teilen U Zubeh\u00f6r Instandhaltung U Reparatur von Motorr\u00e4dern",
    "sg:phone":"+41 26 660 25 13",
    "sg:postcode":"1530",
    "sg:province":"Vaud",
    "wof:name":"Staehelin B.",
    "wof:placetype":"venue"
},
  "geometry": {"coordinates":[6.93648386,46.8204116821],"type":"Point"}
}