{
  "type": "Feature",
  "properties": {
    "iso:country":"CH",
    "sg:address":"Freiburgstrasse 2",
    "sg:city":"Tafers",
    "sg:classifiers":[
        {
            "category":"Travel",
            "subcategory":"Hotels & Motels",
            "type":"Entertainment"
        }
    ],
    "sg:phone":"+41 26 494 53 13",
    "sg:postcode":"1712",
    "sg:province":"Fribourg",
    "sg:tags":[
        "hotels",
        "mit",
        "restaurant"
    ],
    "wof:name":"S\u00e0rl H\u00f4tel Taverna-tafers",
    "wof:placetype":"venue"
},
  "geometry": {"coordinates":[7.215528965,46.8149185181],"type":"Point"}
}