{
  "type": "Feature",
  "properties": {
    "iso:country":"CH",
    "sg:address":"Iselisberg",
    "sg:city":"Uesslingen",
    "sg:orig_category":"Bauschreinerei Herstellung von Konstruktionsteilen, Fertigbauteilen U Ausbauelementen aus Holz",
    "sg:phone":"+41 52 746 11 40",
    "sg:postcode":"8524",
    "sg:province":"Thurgau",
    "wof:name":"Otto W\u00e4geli Ag Bau- & M\u00f6belschreinerei",
    "wof:placetype":"venue"
},
  "geometry": {"coordinates":[8.82819,47.58654],"type":"Point"}
}