{
  "type": "Feature",
  "properties": {
    "iso:country":"CH",
    "sg:address":"L\u00e4nggassstrasse 26",
    "sg:city":"Bern",
    "sg:orig_category":"Arztpraxen",
    "sg:phone":"+41 31 381 89 08",
    "sg:postcode":"3012",
    "sg:province":"Bern",
    "wof:name":"Dr.med. Regula Bosshard Durrer Spezial\u00e4rztin Fmh",
    "wof:placetype":"venue"
},
  "geometry": {"coordinates":[7.445718,46.948017],"type":"Point"}
}