{
  "type": "Feature",
  "properties": {
    "iso:country":"CH",
    "sg:address":"Centre Commercial Migros Marin",
    "sg:city":"Marin-centre",
    "sg:orig_category":"Unclassifiable Establishments",
    "sg:phone":"+41 32 753 75 00",
    "sg:postcode":"2074",
    "sg:province":"Neuch\u00e2tel",
    "wof:name":"Cinq \u00e0 Sec Marin Sa",
    "wof:placetype":"venue"
},
  "geometry": {"coordinates":[7.0109200478,47.0136299133],"type":"Point"}
}