{
  "type": "Feature",
  "properties": {
    "iso:country":"CH",
    "sg:address":"Sch\u00f6ttlerstrasse 4",
    "sg:city":"Appenzell",
    "sg:orig_category":"Herstellung von sonstigen elektrischen Ausr\u00fcstungen",
    "sg:postcode":"9050",
    "sg:province":"Appenzell Innerhoden",
    "wof:name":"Cte D\u00f6rig",
    "wof:placetype":"venue"
},
  "geometry": {"coordinates":[9.4151382446,47.3224411011],"type":"Point"}
}