{
  "type": "Feature",
  "properties": {
    "iso:country":"CH",
    "sg:address":"Impasse Du Ch\u00e2teau 3",
    "sg:city":"Farvagny",
    "sg:orig_category":"Nationale Postdienste",
    "sg:phone":"+41 26 411 11 02",
    "sg:postcode":"1726",
    "sg:province":"Fribourg",
    "wof:name":"La Poste Suisse",
    "wof:placetype":"venue"
},
  "geometry": {"coordinates":[7.0651750565,46.7221488953],"type":"Point"}
}