{
  "type": "Feature",
  "properties": {
    "addr:full":"Lindauring 6 Rothenburg Luzern 6023",
    "addr:housenumber":"6",
    "addr:postcode":"6023",
    "addr:street":"Lindauring",
    "iso:country":"CH",
    "sg:address":"Lindauring 6",
    "sg:city":"Rothenburg",
    "sg:orig_category":"Aktivit\u00e4ten der Generalunternehmen im Baugewerbe Architektur U Ingenieurb\u00fcros",
    "sg:phone":"+41 41 289 31 31",
    "sg:postcode":"6023",
    "sg:province":"Luzern",
    "wof:name":"Cerutti Partner Architekten Ag",
    "wof:placetype":"venue"
},
  "geometry": {"coordinates":[8.268302,47.100716],"type":"Point"}
}