{
  "type": "Feature",
  "properties": {
    "iso:country":"CH",
    "sg:address":"Forchstrasse 67 8032 Z\u00fcrich. Postfach 104",
    "sg:city":"Z\u00fcrich",
    "sg:orig_category":"Grosshandel mit Geschenkartikeln U Souvenirs Grosshandel mit sonstigen Gebrauchs U Verbrauchsg\u00fctern",
    "sg:phone":"+41 13817404",
    "sg:postcode":"8032",
    "sg:province":"Z\u00fcrich",
    "wof:name":"Novodecor Ag.",
    "wof:placetype":"venue"
},
  "geometry": {"coordinates":[8.5584840775,47.3627281189],"type":"Point"}
}