{
  "type": "Feature",
  "properties": {
    "iso:country":"CH",
    "sg:address":"Seidenweg 7",
    "sg:city":"Bern",
    "sg:orig_category":"Detailhandel Handel mit Motorr\u00e4dern, Teilen U Zubeh\u00f6r Instandhaltung U Reparatur von Motorr\u00e4dern Rep",
    "sg:phone":"+41 31 302 55 25",
    "sg:postcode":"3012",
    "sg:province":"Bern",
    "wof:name":"Max N\u00f6thiger Motorr\u00e4der",
    "wof:placetype":"venue"
},
  "geometry": {"coordinates":[7.4324450493,46.9542541504],"type":"Point"}
}