{
  "type": "Feature",
  "properties": {
    "iso:country":"CH",
    "sg:address":"Dorfstrasse 12",
    "sg:city":"Safenwil",
    "sg:orig_category":"Herstellung von Teilen U Zubeh\u00f6r f\u00fcr Automobile Instandhaltung U Reparatur von Automobilen",
    "sg:phone":"+41 55 210 88 44",
    "sg:postcode":"5745",
    "sg:province":"Aargau",
    "wof:name":"Rehm Autoelektrik Rapperswil",
    "wof:placetype":"venue"
},
  "geometry": {"coordinates":[8.8264083862,47.2294540405],"type":"Point"}
}