{
  "type": "Feature",
  "properties": {
    "iso:country":"CH",
    "sg:address":"Waaghausgasse 2",
    "sg:city":"Bern",
    "sg:orig_category":"Technische, physikalische U chemische Untersuchung",
    "sg:phone":"+41 31 312 11 33",
    "sg:postcode":"3011",
    "sg:province":"Bern",
    "wof:name":"B\u00fcro 84, Arbeitsgemeinschaft F\u00fcr Angewandte Oekologie",
    "wof:placetype":"venue"
},
  "geometry": {"coordinates":[7.4440422058,46.948261261],"type":"Point"}
}