{
  "type": "Feature",
  "properties": {
    "iso:country":"CH",
    "sg:address":"Chamerstrasse 79 6300 Zug. Postfach 3301",
    "sg:city":"Zug",
    "sg:orig_category":"Markt U Meinungsforschung",
    "sg:postcode":"6300",
    "sg:province":"Zug",
    "wof:name":"Edu Marketing Gmbh",
    "wof:placetype":"venue"
},
  "geometry": {"coordinates":[7.5549287796,47.5092124939],"type":"Point"}
}