{
  "type": "Feature",
  "properties": {
    "iso:country":"CH",
    "sg:address":"Poststrasse 2 5502 Hunzenschwil. Postfach 173",
    "sg:city":"Hunzenschwil",
    "sg:orig_category":"Detailhandel mit Brot, Back U S\u00fcsswaren",
    "sg:phone":"+41 62 897 12 35",
    "sg:postcode":"5502",
    "sg:province":"Aargau",
    "wof:name":"Urs Kohler B\u00e4ckerei-konditorei",
    "wof:placetype":"venue"
},
  "geometry": {"coordinates":[8.121992,47.386211],"type":"Point"}
}