{
  "type": "Feature",
  "properties": {
    "iso:country":"CH",
    "sg:address":"Zugerstrasse 7",
    "sg:city":"Unter\u00e4geri",
    "sg:orig_category":"Grosshandel mit B\u00fcromaschinen Grosshandel mit Datenverarbeitungsger\u00e4ten",
    "sg:postcode":"6314",
    "sg:province":"Zug",
    "wof:name":"Iten Informatik",
    "wof:placetype":"venue"
},
  "geometry": {"coordinates":[8.5835561752,47.1372947693],"type":"Point"}
}