{
  "type": "Feature",
  "properties": {
    "iso:country":"CH",
    "sg:address":"Sabli\u00e8res Rue Des 5",
    "sg:city":"Satigny",
    "sg:orig_category":"Elektrizit\u00e4tsversorgung",
    "sg:phone":"+41 79 439 05 75",
    "sg:postcode":"1242",
    "sg:province":"Gen\u00e8ve",
    "wof:name":"Frike Electronic Ag Elektronische Solartechnische Ger\u00e4te, Analgen, Apparate Im Bereich Strassenbau-signalisation; Entwicklung, Produktion Usw",
    "wof:placetype":"venue"
},
  "geometry": {"coordinates":[8.5079030991,47.6043167114],"type":"Point"}
}