{
  "type": "Feature",
  "properties": {
    "iso:country":"CH",
    "sg:address":"Sandacker 9 8052 Z\u00fcrich. Postfach",
    "sg:city":"Z\u00fcrich",
    "sg:orig_category":"Grosshandel mit Holz U Baustoffen Herstellung von konfektionierten Textilwaren ohne Bekleidung",
    "sg:phone":"+41 13020888",
    "sg:postcode":"8052",
    "sg:province":"Z\u00fcrich",
    "wof:name":"Siema Storen Gmbh",
    "wof:placetype":"venue"
},
  "geometry": {"coordinates":[8.5523881912,47.422832489],"type":"Point"}
}