{
  "type": "Feature",
  "properties": {
    "iso:country":"CH",
    "sg:address":"Chalet Clos Mar",
    "sg:city":"Verbier",
    "sg:orig_category":"Non-Classified Establishments",
    "sg:postcode":"1936",
    "sg:province":"Valais",
    "wof:name":"Gefu Oberle",
    "wof:placetype":"venue"
},
  "geometry": {"coordinates":[8.1570396423,47.2199440002],"type":"Point"}
}