{
  "type": "Feature",
  "properties": {
    "iso:country":"CH",
    "sg:address":"Franscini Viale S. 6500 Bellinzona. Postfach Casa Postale",
    "sg:city":"Bellinzona",
    "sg:orig_category":"Fotografisches Gewerbe U fotografische Laboratorien",
    "sg:phone":"+41 91 821 11 11",
    "sg:postcode":"6500",
    "sg:province":"Ticino",
    "wof:name":"Salvioni Sa Fotocomposizione, Fotografia, Fotolitografia, Montaggio Ecc",
    "wof:placetype":"venue"
},
  "geometry": {"coordinates":[9.0163679123,46.1914482117],"type":"Point"}
}