{
  "type": "Feature",
  "properties": {
    "iso:country":"CH",
    "sg:address":"Spitalstrasse 9",
    "sg:city":"Bauma",
    "sg:orig_category":"Gesundheitswesen",
    "sg:postcode":"8494",
    "sg:province":"Z\u00fcrich",
    "wof:name":"Chirurgische Arztpraxis, Kaiser Dr. Med. Christoph",
    "wof:placetype":"venue"
},
  "geometry": {"coordinates":[8.8842477798,47.3682556152],"type":"Point"}
}