{
  "type": "Feature",
  "properties": {
    "iso:country":"CH",
    "sg:address":"Rue De La Pontaise 13",
    "sg:city":"Lausanne",
    "sg:orig_category":"Detailhandel mit Geschenkartikeln U Souvenirs",
    "sg:phone":"+41 27 939 12 14",
    "sg:postcode":"1018",
    "sg:province":"Vaud",
    "wof:name":"Madeleine Henzen Boutique Madeleine",
    "wof:placetype":"venue"
},
  "geometry": {"coordinates":[7.7845520973,46.4042396545],"type":"Point"}
}