{
  "type": "Feature",
  "properties": {
    "iso:country":"CH",
    "sg:address":"Grundweg 131",
    "sg:city":"Wenslingen",
    "sg:orig_category":"Verarbeitung von Milch Verwertung von Milch",
    "sg:phone":"+41 61 991 03 08",
    "sg:postcode":"4493",
    "sg:province":"Basel-Landschaft",
    "wof:name":"Milch Und Landwirtschaftliche Genossenschaft Wenslingen",
    "wof:placetype":"venue"
},
  "geometry": {"coordinates":[7.9091348648,47.4393005371],"type":"Point"}
}