{
  "type": "Feature",
  "properties": {
    "iso:country":"CH",
    "sg:address":"Solothurnstrasse 138 2504 Biel/bienne Case Postale 1132",
    "sg:city":"Biel/bienne",
    "sg:orig_category":"Grosshandel mit B\u00fcrom\u00f6beln Herstellung von sonstigen Maschinen f\u00fcr unspezifische Verwendung",
    "sg:phone":"+41 32 344 29 44",
    "sg:postcode":"2501",
    "sg:province":"Bern",
    "wof:name":"Allemand Fr\u00e8res Sa",
    "wof:placetype":"venue"
},
  "geometry": {"coordinates":[7.2823300362,47.1612052917],"type":"Point"}
}