{
  "type": "Feature",
  "properties": {
    "iso:country":"CH",
    "sg:address":"Oristalstrasse 37",
    "sg:city":"Liestal",
    "sg:orig_category":"Softwareentwicklung U beratung",
    "sg:phone":"+41 61 921 39 20",
    "sg:postcode":"4410",
    "sg:province":"Basel-Landschaft",
    "wof:name":"Regenass Mark Gmbh",
    "wof:placetype":"venue"
},
  "geometry": {"coordinates":[7.7310581207,47.4808692932],"type":"Point"}
}