{
  "type": "Feature",
  "properties": {
    "iso:country":"CH",
    "sg:address":"Sandstrasse 11",
    "sg:city":"Moosseedorf",
    "sg:orig_category":"RESTAURANTS: TEA-ROOMS",
    "sg:phone":"+41 31 859 57 55",
    "sg:postcode":"3302",
    "sg:province":"Bern",
    "wof:name":"Caf\u00e9 Linden, Rosmarie Gottier",
    "wof:placetype":"venue"
},
  "geometry": {"coordinates":[7.484128952,47.0153694153],"type":"Point"}
}