{
  "type": "Feature",
  "properties": {
    "iso:country":"CH",
    "sg:address":"Rue Du L\u00e9man 8 1820 Montreux Case Postale",
    "sg:city":"Montreux",
    "sg:orig_category":"Herstellung von Karosserien U Anh\u00e4ngern",
    "sg:postcode":"1820",
    "sg:province":"Vaud",
    "wof:name":"Carrosserie Regamey. Carrosserie, T\u00f4lerie, Peinture.",
    "wof:placetype":"venue"
},
  "geometry": {"coordinates":[6.891146183,46.4555511475],"type":"Point"}
}