{
  "type": "Feature",
  "properties": {
    "iso:country":"CH",
    "sg:address":"Engerfeldstrasse 18",
    "sg:city":"Rheinfelden",
    "sg:classifiers":[
        {
            "category":"Education",
            "subcategory":"Vocational School",
            "type":"Public Place"
        }
    ],
    "sg:postcode":"4310",
    "sg:province":"Aargau",
    "sg:tags":[
        "koch-",
        "haushaltschulen"
    ],
    "wof:name":"Haushaltungsschule",
    "wof:placetype":"venue"
},
  "geometry": {"coordinates":[7.3591217995,46.9135665894],"type":"Point"}
}