{
  "type": "Feature",
  "properties": {
    "iso:country":"CH",
    "sg:address":"Pfungenerstrasse 3",
    "sg:city":"Oberembrach",
    "sg:orig_category":"Mechanik Schlossereien",
    "sg:phone":"+41 34 445 22 17",
    "sg:postcode":"8425",
    "sg:province":"Z\u00fcrich",
    "wof:name":"Oberli Schlosserei Und Landmaschinen Ag",
    "wof:placetype":"venue"
},
  "geometry": {"coordinates":[7.5684700012,47.0947875977],"type":"Point"}
}