{
  "type": "Feature",
  "properties": {
    "iso:country":"CH",
    "sg:address":"Hammerstrasse 200",
    "sg:city":"Basel",
    "sg:orig_category":"Detailhandel mit Fleisch U Fleischwaren",
    "sg:phone":"+41 61 692 57 75",
    "sg:postcode":"4057",
    "sg:province":"Basel-Stadt",
    "wof:name":"B\u00fckl\u00fc Ag Metzgerei & Partyservice",
    "wof:placetype":"venue"
},
  "geometry": {"coordinates":[7.5952658653,47.5705566406],"type":"Point"}
}