{
  "type": "Feature",
  "properties": {
    "iso:country":"CH",
    "sg:address":"Sundgauerstrasse 13",
    "sg:city":"Basel",
    "sg:orig_category":"Grosshandel mit Obst U Gem\u00fcse",
    "sg:phone":"+41 61 321 33 10",
    "sg:postcode":"4055",
    "sg:province":"Basel-Stadt",
    "wof:name":"G\u00f6ssler Max Gem\u00fcse- & Fr\u00fcchtehandel",
    "wof:placetype":"venue"
},
  "geometry": {"coordinates":[7.5625891685,47.565284729],"type":"Point"}
}