{
  "type": "Feature",
  "properties": {
    "iso:country":"CH",
    "sg:address":"Gerberngasse 8",
    "sg:city":"Bern",
    "sg:orig_category":"Grosshandel mit Nahrungsmitteln, Getr\u00e4nken U Tabakwaren ohne ausgepr\u00e4gten Schwerpunkt",
    "sg:postcode":"3011",
    "sg:province":"Bern",
    "wof:name":"M. Schwab",
    "wof:placetype":"venue"
},
  "geometry": {"coordinates":[7.4574508667,46.9481468201],"type":"Point"}
}