{
  "type": "Feature",
  "properties": {
    "addr:full":"Rue Liotard 58 Gen\u00e8ve Gen\u00e8ve 1202",
    "addr:housenumber":"58",
    "addr:postcode":"1202",
    "addr:street":"Rue Liotard",
    "iso:country":"CH",
    "sg:address":"Rue Liotard 58",
    "sg:city":"Gen\u00e8ve",
    "sg:orig_category":"Arztpraxen",
    "sg:phone":"+41 22 345 19 20",
    "sg:postcode":"1202",
    "sg:province":"Gen\u00e8ve",
    "wof:name":"Dr M\u00e9d. Haw-tzer Chen M\u00e9decin Sp\u00e9cialiste Fmh",
    "wof:placetype":"venue"
},
  "geometry": {"coordinates":[6.128594,46.212791],"type":"Point"}
}