{
  "type": "Feature",
  "properties": {
    "iso:country":"CH",
    "sg:address":"Musslistrasse 12",
    "sg:city":"Nunningen",
    "sg:orig_category":"Betrieb U technische Hilfsdienste des Kultur U Unterhaltungswesens Sonstige Hilfsdienste des Kultur ",
    "sg:phone":"+41 61 795 96 60",
    "sg:postcode":"4208",
    "sg:province":"Solothurn",
    "wof:name":"Greenwood Recording Studios Ag",
    "wof:placetype":"venue"
},
  "geometry": {"coordinates":[7.625916,47.39418],"type":"Point"}
}