{
  "type": "Feature",
  "properties": {
    "iso:country":"CH",
    "sg:address":"Grubenstrasse 30",
    "sg:city":"Ober\u00e4geri",
    "sg:orig_category":"Fachdetailhandel in Verkaufsr\u00e4umen Grosshandel mit Sportartikeln",
    "sg:phone":"+41 79 415 63 23",
    "sg:postcode":"6315",
    "sg:province":"Zug",
    "wof:name":"Ibex Sport Gmbh",
    "wof:placetype":"venue"
},
  "geometry": {"coordinates":[8.6073989868,47.1408882141],"type":"Point"}
}