{
  "type": "Feature",
  "properties": {
    "iso:country":"CH",
    "sg:address":"Rue Des Corbaz 13",
    "sg:city":"Belmont-lausanne",
    "sg:orig_category":"Physiotherapie",
    "sg:phone":"+41 21 729 88 17",
    "sg:postcode":"1092",
    "sg:province":"Vaud",
    "wof:name":"Jean-louis Golano Physioth\u00e9rapie",
    "wof:placetype":"venue"
},
  "geometry": {"coordinates":[6.679060936,46.5208778381],"type":"Point"}
}