{
  "type": "Feature",
  "properties": {
    "iso:country":"CH",
    "sg:address":"Stettbachstrasse 8",
    "sg:city":"D\u00fcbendorf",
    "sg:orig_category":"Grosshandel mit sonstigen Maschinen U Ausr\u00fcstungen f\u00fcr Industrie, Handel U Schiffahrt Handelsvermitt",
    "sg:phone":"+41 18221380",
    "sg:postcode":"8600",
    "sg:province":"Z\u00fcrich",
    "wof:name":"Weldtec Gmbh",
    "wof:placetype":"venue"
},
  "geometry": {"coordinates":[8.6014413834,47.3949623108],"type":"Point"}
}