{
  "type": "Feature",
  "properties": {
    "iso:country":"CH",
    "sg:address":"Neudorfstrasse 8",
    "sg:city":"Steinhausen",
    "sg:orig_category":"Non-Classified Establishments",
    "sg:postcode":"6312",
    "sg:province":"Zug",
    "wof:name":"Caruso Teamwork Dienstleistungen",
    "wof:placetype":"venue"
},
  "geometry": {"coordinates":[8.4831457138,47.1978645325],"type":"Point"}
}