{
  "type": "Feature",
  "properties": {
    "addr:full":"Immostrasse 15 Immensee Schwyz 6405",
    "addr:housenumber":"15",
    "addr:postcode":"6405",
    "addr:street":"Immostrasse;Schwyz",
    "iso:country":"CH",
    "sg:address":"Immostrasse 15",
    "sg:city":"Immensee",
    "sg:classifiers":[
        {
            "category":"Social Services",
            "subcategory":"Retirement Home",
            "type":"Services"
        }
    ],
    "sg:phone":"+41 55 246 14 21",
    "sg:postcode":"6405",
    "sg:province":"Schwyz",
    "sg:tags":[
        "pflegeheime",
        "u",
        "alters"
    ],
    "wof:name":"Alters-& Pflegeheim Tabor",
    "wof:placetype":"venue"
},
  "geometry": {"coordinates":[8.9413,47.28841],"type":"Point"}
}