{
  "type": "Feature",
  "properties": {
    "iso:country":"CH",
    "sg:address":"Archstrasse 125",
    "sg:city":"Grenchen",
    "sg:orig_category":"Sportvereine Fischerei",
    "sg:phone":"+41 32 652 91 86",
    "sg:postcode":"2540",
    "sg:province":"Solothurn",
    "wof:name":"Fischerverein Grenchen- Bettlach",
    "wof:placetype":"venue"
},
  "geometry": {"coordinates":[7.4217100143,47.1733818054],"type":"Point"}
}