{
  "type": "Feature",
  "properties": {
    "addr:full":"Chemin De La Fruiti\u00e8re 16 Collex Gen\u00e8ve 1239",
    "addr:housenumber":"16",
    "addr:postcode":"1239",
    "addr:street":"Chemin De La Fruitie\u0300Re",
    "iso:country":"CH",
    "sg:address":"Chemin De La Fruiti\u00e8re 16",
    "sg:city":"Collex",
    "sg:orig_category":"Autospenglereien",
    "sg:phone":"+41 22 774 23 22",
    "sg:postcode":"1239",
    "sg:province":"Gen\u00e8ve",
    "wof:name":"Michel Girod Carrosserie",
    "wof:placetype":"venue"
},
  "geometry": {"coordinates":[6.122916,46.271313],"type":"Point"}
}