{
  "type": "Feature",
  "properties": {
    "iso:country":"CH",
    "sg:address":"Via Emilio Bossi 4 6830 Chiasso Case Postale 139",
    "sg:city":"Chiasso",
    "sg:orig_category":"Reiseb\u00fcros U Reiseveranstalter",
    "sg:phone":"+41 91 682 29 49",
    "sg:postcode":"6830",
    "sg:province":"Ticino",
    "wof:name":"Top Tour 2000 Sa",
    "wof:placetype":"venue"
},
  "geometry": {"coordinates":[9.0310878754,45.8338317871],"type":"Point"}
}