{
  "type": "Feature",
  "properties": {
    "iso:country":"CH",
    "sg:address":"Baarerstrasse 63",
    "sg:city":"Zug",
    "sg:orig_category":"Herstellung von gewirktem U gestricktem Stoff Spinnstoffaufbereitung U Spinnerei",
    "sg:phone":"+41 41 710 76 24",
    "sg:postcode":"6300",
    "sg:province":"Zug",
    "wof:name":"W. Fein & Sons Ag",
    "wof:placetype":"venue"
},
  "geometry": {"coordinates":[8.5173740387,47.1761703491],"type":"Point"}
}