{
  "type": "Feature",
  "properties": {
    "iso:country":"CH",
    "sg:address":"Lindenweg 6",
    "sg:city":"Menziken",
    "sg:orig_category":"P\u00e9dicure",
    "sg:phone":"+41 62 771 72 15",
    "sg:postcode":"5737",
    "sg:province":"Aargau",
    "wof:name":"Monika Merz P\u00e9dicure",
    "wof:placetype":"venue"
},
  "geometry": {"coordinates":[8.1831817627,47.2455406189],"type":"Point"}
}