{
  "type": "Feature",
  "properties": {
    "iso:country":"CH",
    "sg:address":"Rue Du Rh\u00f4ne 19",
    "sg:city":"Gen\u00e8ve",
    "sg:classifiers":[
        {
            "category":"Banks & Credit Unions",
            "subcategory":"Bank",
            "type":"Services"
        }
    ],
    "sg:phone":"+41 13088800",
    "sg:postcode":"1204",
    "sg:province":"Gen\u00e8ve",
    "wof:name":"Deka Bank (schweiz) Ag",
    "wof:placetype":"venue"
},
  "geometry": {"coordinates":[8.54944,47.413521],"type":"Point"}
}