{
  "type": "Feature",
  "properties": {
    "iso:country":"CH",
    "sg:address":"Freiestrsse 131",
    "sg:city":"Z\u00fcrich",
    "sg:orig_category":"Hochschulen U h\u00f6here Ausbildung Softwareentwicklung U beratung",
    "sg:phone":"+41 22 823 00 63",
    "sg:postcode":"8032",
    "sg:province":"Z\u00fcrich",
    "wof:name":"Cmck Solutions S\u00e0rl Analyses Et Conseil Sur Les Besoins Des Entreprises En Mati\u00e8re De Formation, De Connaissances Et De Comp\u00e9tences Etc",
    "wof:placetype":"venue"
},
  "geometry": {"coordinates":[6.1299247742,46.1842193604],"type":"Point"}
}