{
  "type": "Feature",
  "properties": {
    "iso:country":"CH",
    "sg:address":"Kappeliweg 10/12",
    "sg:city":"Herzogenbuchsee",
    "sg:orig_category":"Erschliessung von Grundst\u00fccken",
    "sg:phone":"+41 31 311 44 43",
    "sg:postcode":"3360",
    "sg:province":"Bern",
    "wof:name":"Baugenossenschaft Karl Staufferstrasse",
    "wof:placetype":"venue"
},
  "geometry": {"coordinates":[7.4498019218,46.9473266602],"type":"Point"}
}