{
  "type": "Feature",
  "properties": {
    "iso:country":"CH",
    "sg:address":"Klosterplatz 17.",
    "sg:city":"Olten",
    "sg:orig_category":"RESTAURANTS: TEA-ROOMS",
    "sg:postcode":"4600",
    "sg:province":"Solothurn",
    "wof:name":"Studer-feigenwinter Marie.",
    "wof:placetype":"venue"
},
  "geometry": {"coordinates":[7.9040470123,47.3503112793],"type":"Point"}
}