{
  "type": "Feature",
  "properties": {
    "addr:full":"Seetalstrasse 15 Schafisheim Aargau 5503",
    "addr:housenumber":"15",
    "addr:postcode":"5503",
    "addr:street":"Seetalstrasse",
    "iso:country":"CH",
    "sg:address":"Seetalstrasse 15",
    "sg:city":"Schafisheim",
    "sg:orig_category":"Detailhandel mit Bekleidung Detailhandel mit Damenbekleidung",
    "sg:phone":"+41 22 342 82 56",
    "sg:postcode":"5503",
    "sg:province":"Aargau",
    "wof:name":"Binz Gauthey-victoria Maria",
    "wof:placetype":"venue"
},
  "geometry": {"coordinates":[6.143475,46.185608],"type":"Point"}
}