{
  "type": "Feature",
  "properties": {
    "iso:country":"CH",
    "sg:address":"Dorfstrasse 7",
    "sg:city":"Ersigen",
    "sg:orig_category":"G\u00fcterbef\u00f6rderung im Strassenverkehr",
    "sg:phone":"+41 34 445 42 67",
    "sg:postcode":"3423",
    "sg:province":"Bern",
    "wof:name":"Fritz Gerber Transporte",
    "wof:placetype":"venue"
},
  "geometry": {"coordinates":[7.5919981003,47.0893249512],"type":"Point"}
}