{
  "type": "Feature",
  "properties": {
    "iso:country":"CH",
    "sg:address":"Z\u00fcrcherstrasse 109a",
    "sg:city":"Baden",
    "sg:orig_category":"Markt U Meinungsforschung Unternehmensberatung",
    "sg:phone":"+41 71 923 84 84",
    "sg:postcode":"5400",
    "sg:province":"Aargau",
    "wof:name":"Wbs Marketing Und Werbeagentur Ag",
    "wof:placetype":"venue"
},
  "geometry": {"coordinates":[9.0484466553,47.4563751221],"type":"Point"}
}