{
  "type": "Feature",
  "properties": {
    "iso:country":"CH",
    "sg:address":"Corso San Gottardo 52 6830 Chiasso. Postfach Caselle Postale 219",
    "sg:city":"Chiasso",
    "sg:orig_category":"Versicherungen Generalagenturen",
    "sg:phone":"+41 79 620 91 82",
    "sg:postcode":"6830",
    "sg:province":"Ticino",
    "wof:name":"Rentenanstalt/swiss Life Agenzia Generale Di Chiasso",
    "wof:placetype":"venue"
},
  "geometry": {"coordinates":[9.0286865234,45.8349075317],"type":"Point"}
}