{
  "type": "Feature",
  "properties": {
    "iso:country":"CH",
    "sg:address":"Chemin De Bois-caran 7",
    "sg:city":"Collonge-bellerive",
    "sg:orig_category":"Softwareentwicklung U beratung",
    "sg:phone":"+41 22 796 33 43",
    "sg:postcode":"1245",
    "sg:province":"Gen\u00e8ve",
    "wof:name":"Volet Software Engineering Sa",
    "wof:placetype":"venue"
},
  "geometry": {"coordinates":[6.1973390579,46.2481498718],"type":"Point"}
}