{
  "type": "Feature",
  "properties": {
    "iso:country":"CH",
    "sg:address":"Brugg\u00e4cherstrasse 24",
    "sg:city":"M\u00f6nchaltorf",
    "sg:orig_category":"Dienstleistungen von Beteiligungsgesellschaften",
    "sg:phone":"+41 19480706",
    "sg:postcode":"8617",
    "sg:province":"Z\u00fcrich",
    "wof:name":"Finus Ag",
    "wof:placetype":"venue"
},
  "geometry": {"coordinates":[8.7165498734,47.3115615845],"type":"Point"}
}