{
  "type": "Feature",
  "properties": {
    "iso:country":"CH",
    "sg:address":"Werkhofstrasse 19",
    "sg:city":"Solothurn",
    "sg:orig_category":"Architektur U Ingenieurb\u00fcros Architekturb\u00fcros",
    "sg:phone":"+41 32 622 88 73",
    "sg:postcode":"4500",
    "sg:province":"Solothurn",
    "wof:name":"Widmer Wehrle Blaser, Architekten Ag",
    "wof:placetype":"venue"
},
  "geometry": {"coordinates":[7.535653,47.210251],"type":"Point"}
}