{
  "type": "Feature",
  "properties": {
    "iso:country":"CH",
    "sg:address":"B\u00fchlstrasse 6",
    "sg:city":"Egerkingen",
    "sg:orig_category":"Politische Vereinigungen",
    "sg:phone":"+41 62 398 00 85",
    "sg:postcode":"4622",
    "sg:province":"Solothurn",
    "wof:name":"Ig Pro Egerkingen",
    "wof:placetype":"venue"
},
  "geometry": {"coordinates":[7.7962698936,47.3226356506],"type":"Point"}
}