{
  "type": "Feature",
  "properties": {
    "iso:country":"CH",
    "sg:address":"Marktstrasse 6",
    "sg:city":"Frauenfeld",
    "sg:orig_category":"Tierarztpraxis",
    "sg:phone":"+41 52 720 96 11",
    "sg:postcode":"8500",
    "sg:province":"Thurgau",
    "wof:name":"Dr. Med. Vet. Eveline Buff Tier\u00e4rztin",
    "wof:placetype":"venue"
},
  "geometry": {"coordinates":[8.8998689651,47.5533905029],"type":"Point"}
}