{
  "type": "Feature",
  "properties": {
    "addr:full":"Rue Centrale 6 Bex Vaud 1880",
    "addr:housenumber":"6",
    "addr:postcode":"1880",
    "addr:street":"Rue Centrale",
    "iso:country":"CH",
    "sg:address":"Rue Centrale 6",
    "sg:city":"Bex",
    "sg:orig_category":"Darlehenskassen U Raiffeisenbanken",
    "sg:phone":"+41 24 463 22 76",
    "sg:postcode":"1880",
    "sg:province":"Vaud",
    "wof:name":"Banque Raiffeisen Du Chablais Vaudois",
    "wof:placetype":"venue"
},
  "geometry": {"coordinates":[7.013456,46.251202],"type":"Point"}
}