{
  "type": "Feature",
  "properties": {
    "iso:country":"CH",
    "sg:address":"Industrieweg 43 3612 Steffisburg. Postfach",
    "sg:city":"Steffisburg",
    "sg:orig_category":"Herstellung von Konstruktionsteilen, Fertigbauteilen U Ausbauelementen aus Holz",
    "sg:postcode":"3613",
    "sg:province":"Bern",
    "wof:name":"Raumpunkt, Schreinerei + Drechslerei Stoller & Aebischer",
    "wof:placetype":"venue"
},
  "geometry": {"coordinates":[7.6236858368,46.7720222473],"type":"Point"}
}