{
  "type": "Feature",
  "properties": {
    "iso:country":"CH",
    "sg:address":"Oberdorfstrasse 54 8600 D\u00fcbendorf. Postfach",
    "sg:city":"D\u00fcbendorf",
    "sg:orig_category":"Finanzierungsinstitutionen",
    "sg:phone":"+41 18224100",
    "sg:postcode":"8600",
    "sg:province":"Z\u00fcrich",
    "wof:name":"Sunman Financial Services",
    "wof:placetype":"venue"
},
  "geometry": {"coordinates":[8.6227273941,47.3936767578],"type":"Point"}
}