{
  "type": "Feature",
  "properties": {
    "iso:country":"CH",
    "sg:address":"Lindenweg 2",
    "sg:city":"B\u00f6nigen",
    "sg:orig_category":"Landesverteidigung, Sozialversicherung \u00d6ffentliche Verwaltung",
    "sg:phone":"+41 33 822 01 30",
    "sg:postcode":"3806",
    "sg:province":"Bern",
    "wof:name":"Zivilschutzstelle B\u00f6ningen Bei Interlaken",
    "wof:placetype":"venue"
},
  "geometry": {"coordinates":[7.8941001892,46.6866989136],"type":"Point"}
}