{
  "type": "Feature",
  "properties": {
    "iso:country":"CH",
    "sg:address":"Bergholz",
    "sg:city":"Amlikon",
    "sg:orig_category":"Non-Classified Establishments",
    "sg:postcode":"8514",
    "sg:province":"Thurgau",
    "wof:name":"Elektra-genossenschaft Amlikon",
    "wof:placetype":"venue"
},
  "geometry": {"coordinates":[9.0524330139,47.5677490234],"type":"Point"}
}