{
  "type": "Feature",
  "properties": {
    "iso:country":"CH",
    "sg:address":"Einschlagweg 67 3400 Burgdorf. Postfach Postfach",
    "sg:city":"Burgdorf",
    "sg:orig_category":"Allgemeiner Hoch U Tiefbau Hoch U Tiefbau",
    "sg:phone":"+41 34 422 98 76",
    "sg:postcode":"3401",
    "sg:province":"Bern",
    "wof:name":"B\u00fcrki Bau Ag Burgdorf",
    "wof:placetype":"venue"
},
  "geometry": {"coordinates":[7.628767,47.047249],"type":"Point"}
}