{
  "type": "Feature",
  "properties": {
    "iso:country":"CH",
    "sg:address":"6454",
    "sg:city":"Fl\u00fcelen",
    "sg:orig_category":"Allgemeiner Hoch U Tiefbau ohne ausgepr\u00e4gten Schwerpunkt",
    "sg:phone":"+41 41 874 53 53",
    "sg:postcode":"6454",
    "sg:province":"Uri",
    "wof:name":"Verkehrspolizei Werkhof",
    "wof:placetype":"venue"
},
  "geometry": {"coordinates":[8.62481,46.900517],"type":"Point"}
}