{
  "type": "Feature",
  "properties": {
    "iso:country":"CH",
    "sg:address":"Leimbankweg 12",
    "sg:city":"Blauen",
    "sg:orig_category":"Interessenvertretungen U sonstige Vereinigungen",
    "sg:phone":"+41 61 761 11 01",
    "sg:postcode":"4223",
    "sg:province":"Basel-Landschaft",
    "wof:name":"Turnverband Dorneck-thierstein",
    "wof:placetype":"venue"
},
  "geometry": {"coordinates":[7.5176501274,47.4485206604],"type":"Point"}
}