{
  "type": "Feature",
  "properties": {
    "iso:country":"CH",
    "sg:address":"Centre Commercial R.gare 19",
    "sg:city":"Morges",
    "sg:orig_category":"Reparatur von Schuhen U Lederwaren Schl\u00fcsselservice",
    "sg:phone":"+41 32 914 10 09",
    "sg:postcode":"1110",
    "sg:province":"Vaud",
    "wof:name":"Minit Switzerland Ltd.",
    "wof:placetype":"venue"
},
  "geometry": {"coordinates":[6.8272418976,47.1003303528],"type":"Point"}
}