{
  "type": "Feature",
  "properties": {
    "iso:country":"CH",
    "sg:address":"Fruttstrasse 17",
    "sg:city":"Luzern",
    "sg:orig_category":"Architektur U Ingenieurb\u00fcros",
    "sg:phone":"+41 41 361 20 88",
    "sg:postcode":"6005",
    "sg:province":"Luzern",
    "wof:name":"El Architekten Gmbh",
    "wof:placetype":"venue"
},
  "geometry": {"coordinates":[8.310543,47.042553],"type":"Point"}
}