{
  "type": "Feature",
  "properties": {
    "iso:country":"CH",
    "sg:address":"Bahnhofstrasse 1 5070 Frick. Postfach",
    "sg:city":"Frick",
    "sg:orig_category":"Forstwirtschaft ohne Dienstleistungen in der Forstwirtschaft",
    "sg:phone":"+41 62 871 77 20",
    "sg:postcode":"5070",
    "sg:province":"Aargau",
    "wof:name":"Wahlen Forst + Garten Forst, Gartenbauunternehmen Usw",
    "wof:placetype":"venue"
},
  "geometry": {"coordinates":[8.018529892,47.5083694458],"type":"Point"}
}