{
  "type": "Feature",
  "properties": {
    "iso:country":"CH",
    "sg:address":"Via Serafino Balestra 11",
    "sg:city":"Locarno",
    "sg:classifiers":[
        {
            "category":"Restaurant",
            "type":"Food & Drink"
        }
    ],
    "sg:phone":"+41 91 751 59 96",
    "sg:postcode":"6600",
    "sg:province":"Ticino",
    "wof:name":"Snack-bar Tie Break",
    "wof:placetype":"venue"
},
  "geometry": {"coordinates":[8.7967720032,46.1664276123],"type":"Point"}
}