{
  "type": "Feature",
  "properties": {
    "iso:country":"CH",
    "sg:address":"3945",
    "sg:city":"Niedergampel",
    "sg:orig_category":"Politische Parteien CVP",
    "sg:phone":"+41 27 924 88 22",
    "sg:postcode":"3945",
    "sg:province":"Valais",
    "wof:name":"Cvp Ortspartei Niedergampel",
    "wof:placetype":"venue"
},
  "geometry": {"coordinates":[7.7135300636,46.3121490479],"type":"Point"}
}