{
  "type": "Feature",
  "properties": {
    "iso:country":"CH",
    "sg:address":"Oberdorfstrasse 20",
    "sg:city":"W\u00e4denswil",
    "sg:orig_category":"Unclassifiable Establishments",
    "sg:phone":"+41 17803958",
    "sg:postcode":"8820",
    "sg:province":"Z\u00fcrich",
    "wof:name":"Schulthess H., G\u00e4rtnerei",
    "wof:placetype":"venue"
},
  "geometry": {"coordinates":[8.6689815521,47.2285232544],"type":"Point"}
}