{
  "type": "Feature",
  "properties": {
    "iso:country":"CH",
    "sg:address":"Aemetstrasse 4",
    "sg:city":"B\u00e4retswil",
    "sg:orig_category":"Herstellung von Anstrichmitteln, Druckfarben U Kitten",
    "sg:phone":"+41 56 441 10 24",
    "sg:postcode":"8344",
    "sg:province":"Z\u00fcrich",
    "wof:name":"Karl-peter Esser Lackfabrik",
    "wof:placetype":"venue"
},
  "geometry": {"coordinates":[8.2003889084,47.4743995667],"type":"Point"}
}