{
  "type": "Feature",
  "properties": {
    "addr:full":"Bahnhofstrasse 2 Zug Zug 6300",
    "addr:housenumber":"2",
    "addr:postcode":"6300",
    "addr:street":"Bahnhofstrasse;Zug",
    "iso:country":"CH",
    "sg:address":"Bahnhofstrasse 2",
    "sg:city":"Zug",
    "sg:orig_category":"Advokaturb\u00fcros Notariate",
    "sg:phone":"+41 41 710 22 78",
    "sg:postcode":"6300",
    "sg:province":"Zug",
    "wof:name":"Roland Straub Advokatur-& Notariatsb\u00fcro",
    "wof:placetype":"venue"
},
  "geometry": {"coordinates":[8.515888,47.168224],"type":"Point"}
}