{
  "type": "Feature",
  "properties": {
    "iso:country":"CH",
    "sg:address":"Cardinal Passage Du 2e",
    "sg:city":"Fribourg",
    "sg:orig_category":"Architektur U Ingenieurb\u00fcros",
    "sg:phone":"+41 26 429 02 29",
    "sg:postcode":"1700",
    "sg:province":"Fribourg",
    "wof:name":"Architecture & Design, Petitpierre V.",
    "wof:placetype":"venue"
},
  "geometry": {"coordinates":[7.153683,46.803745],"type":"Point"}
}