{
  "type": "Feature",
  "properties": {
    "iso:country":"CH",
    "sg:address":"Guinchet Chemin Du 56 B 1868 Collombey. Postfach",
    "sg:city":"Collombey",
    "sg:orig_category":"Stukkateurgewerbe, Gipserei U Verputzerei",
    "sg:phone":"+41 21 922 72 10",
    "sg:postcode":"1868",
    "sg:province":"Valais",
    "wof:name":"Bertholet J.-j.",
    "wof:placetype":"venue"
},
  "geometry": {"coordinates":[6.8339929581,46.483089447],"type":"Point"}
}