{
  "type": "Feature",
  "properties": {
    "iso:country":"CH",
    "sg:address":"Bernstrasse 12",
    "sg:city":"Murten",
    "sg:orig_category":"Detailhandel mit Damenbekleidung Detailhandel mit Herrenbekleidung",
    "sg:phone":"+41 26 670 17 67",
    "sg:postcode":"3280",
    "sg:province":"Fribourg",
    "wof:name":"Charles V\u00f6gele Mode Ag",
    "wof:placetype":"venue"
},
  "geometry": {"coordinates":[7.1210417747,46.929561615],"type":"Point"}
}