{
  "type": "Feature",
  "properties": {
    "addr:full":"Buechstrasse 20 Jona St. Gallen 8645",
    "addr:housenumber":"20;st.",
    "addr:postcode":"8645",
    "addr:street":"Buechstrasse;Jona",
    "iso:country":"CH",
    "sg:address":"Buechstrasse 20",
    "sg:city":"Jona",
    "sg:classifiers":[
        {
            "category":"Home & Garden",
            "subcategory":"Household Appliances",
            "type":"Retail Goods"
        }
    ],
    "sg:phone":"+41 55 224 21 11",
    "sg:postcode":"8645",
    "sg:province":"St. Gallen",
    "sg:tags":[
        "improvement",
        "air-humidifiers",
        "air",
        "ambient"
    ],
    "wof:name":"Turmix Ag",
    "wof:placetype":"venue"
},
  "geometry": {"coordinates":[8.866188,47.225758],"type":"Point"}
}