{
  "type": "Feature",
  "properties": {
    "addr:full":"Chemin Des Marais 162 1255 Veyrier Case Postale 159 Veyrier Gen\u00e8ve 1255",
    "addr:housenumber":"162",
    "addr:postcode":"1255;1255",
    "addr:street":"Chemin Des Marais;Postale 159",
    "iso:country":"CH",
    "sg:address":"Chemin Des Marais 162 1255 Veyrier Case Postale 159",
    "sg:city":"Veyrier",
    "sg:classifiers":[
        {
            "category":"Social Services",
            "subcategory":"Retirement Home",
            "type":"Services"
        }
    ],
    "sg:phone":"+41 22 744 02 84",
    "sg:postcode":"1255",
    "sg:province":"Gen\u00e8ve",
    "sg:tags":[
        "pflegeheime",
        "u",
        "alters"
    ],
    "wof:name":"R\u00e9sidence Les Ch\u00e2taigniers Pour Personnes \u00e2g\u00e9es",
    "wof:placetype":"venue"
},
  "geometry": {"coordinates":[6.182467,46.163952],"type":"Point"}
}