{
  "type": "Feature",
  "properties": {
    "iso:country":"CH",
    "sg:address":"1261",
    "sg:city":"Marchissy",
    "sg:orig_category":"Handelsvermittlung U Grosshandel",
    "sg:phone":"+41 22 368 14 07",
    "sg:postcode":"1261",
    "sg:province":"Vaud",
    "wof:name":"Fatalit\u00e9 Diffusion Fournitures Pr Magasins",
    "wof:placetype":"venue"
},
  "geometry": {"coordinates":[6.2470231056,46.4884986877],"type":"Point"}
}