{
  "type": "Feature",
  "properties": {
    "iso:country":"CH",
    "sg:address":"Stand Rue Du 12 1204 Gen\u00e8ve. Postfach",
    "sg:city":"Gen\u00e8ve",
    "sg:orig_category":"Pensionskassen",
    "sg:postcode":"1204",
    "sg:province":"Gen\u00e8ve",
    "wof:name":"Soci\u00e9t\u00e9 De Secours Mutuels De M\u00e9zi\u00e8res",
    "wof:placetype":"venue"
},
  "geometry": {"coordinates":[6.9275698662,46.6799888611],"type":"Point"}
}