{
  "type": "Feature",
  "properties": {
    "iso:country":"CH",
    "sg:address":"Zwillikerstrasse 13",
    "sg:city":"Ottenbach",
    "sg:orig_category":"Sportvereine Renn-& Reitsport",
    "sg:phone":"+41 17612337",
    "sg:postcode":"8913",
    "sg:province":"Z\u00fcrich",
    "wof:name":"Kavallerieverein Zh & Umg.",
    "wof:placetype":"venue"
},
  "geometry": {"coordinates":[8.4076480865,47.2835578918],"type":"Point"}
}