{
  "type": "Feature",
  "properties": {
    "iso:country":"CH",
    "sg:address":"8155",
    "sg:city":"Niederhasli",
    "sg:classifiers":[
        {
            "category":"Education",
            "subcategory":"Vocational School",
            "type":"Public Place"
        }
    ],
    "sg:phone":"+41 71 377 12 21",
    "sg:postcode":"8155",
    "sg:province":"Z\u00fcrich",
    "sg:tags":[
        "koch-",
        "haushaltschulen"
    ],
    "wof:name":"Haushaltungsschule",
    "wof:placetype":"venue"
},
  "geometry": {"coordinates":[8.4839477539,47.4812355042],"type":"Point"}
}