{
  "type": "Feature",
  "properties": {
    "iso:country":"CH",
    "sg:address":"Ottenweg 35 8008 Z\u00fcrich. Postfach",
    "sg:city":"Z\u00fcrich",
    "sg:orig_category":"Allgemeiner Hoch U Tiefbau",
    "sg:postcode":"8001",
    "sg:province":"Z\u00fcrich",
    "wof:name":"Generalplan Baumanagement Ag",
    "wof:placetype":"venue"
},
  "geometry": {"coordinates":[8.819964,47.229279],"type":"Point"}
}