{
  "type": "Feature",
  "properties": {
    "iso:country":"CH",
    "sg:address":"Via Vira 1 6942 Savosa Casella Postale 462",
    "sg:city":"Savosa",
    "sg:orig_category":"Technische, physikalische U chemische Untersuchung",
    "sg:postcode":"6942",
    "sg:province":"Ticino",
    "wof:name":"Laboratorium B\u00f6hme Dr. M.",
    "wof:placetype":"venue"
},
  "geometry": {"coordinates":[9.4083957672,47.503692627],"type":"Point"}
}