{
  "type": "Feature",
  "properties": {
    "iso:country":"CH",
    "sg:address":"Curtinatsch",
    "sg:city":"Ardez",
    "sg:orig_category":"Maurerarbeiten Sonstiger spezialisierter Hoch U Tiefbau",
    "sg:phone":"+41 81 862 24 66",
    "sg:postcode":"7546",
    "sg:province":"Graubunden",
    "wof:name":"L\u00fczzi & Lucrezia Koch Maurergesch\u00e4ft",
    "wof:placetype":"venue"
},
  "geometry": {"coordinates":[10.2062702179,46.7762641907],"type":"Point"}
}