{
  "type": "Feature",
  "properties": {
    "iso:country":"CH",
    "sg:address":"Hauptstrasse 38",
    "sg:city":"Aadorf",
    "sg:orig_category":"Dachdeckerei Zimmerei, Dachdeckerei, Bauspenglerei U Abdichtung",
    "sg:phone":"+41 34 445 21 61",
    "sg:postcode":"8355",
    "sg:province":"Thurgau",
    "wof:name":"Janitsch Niklaus.",
    "wof:placetype":"venue"
},
  "geometry": {"coordinates":[7.570573,47.09441],"type":"Point"}
}