{
  "type": "Feature",
  "properties": {
    "iso:country":"CH",
    "sg:address":"Techno-p\u00f4le 1",
    "sg:city":"Sierre",
    "sg:classifiers":[
        {
            "category":"Professional",
            "subcategory":"Accounting & Tax Preparation",
            "type":"Services"
        }
    ],
    "sg:phone":"+41 27 451 20 00",
    "sg:postcode":"3960",
    "sg:province":"Valais",
    "sg:tags":[
        "financial",
        "software"
    ],
    "wof:name":"Dextra S.a.",
    "wof:placetype":"venue"
},
  "geometry": {"coordinates":[7.5384831429,46.2837677002],"type":"Point"}
}