{
  "type": "Feature",
  "properties": {
    "iso:country":"CH",
    "sg:address":"Hirschengraben 41",
    "sg:city":"Luzern",
    "sg:orig_category":"Mechanische Werkst\u00e4tten",
    "sg:phone":"+41 41 240 50 88",
    "sg:postcode":"6003",
    "sg:province":"Luzern",
    "wof:name":"Reimer & Co Nachf.w.& E.wyss",
    "wof:placetype":"venue"
},
  "geometry": {"coordinates":[8.30148983,47.0501899719],"type":"Point"}
}