{
  "type": "Feature",
  "properties": {
    "iso:country":"CH",
    "sg:address":"Selli\u00e8res Chemin Des 4 1214 Vernier. Postfach",
    "sg:city":"Vernier",
    "sg:orig_category":"RESTAURANTS: TEA-ROOMS",
    "sg:postcode":"1214",
    "sg:province":"Gen\u00e8ve",
    "wof:name":"Impala Franco Restaurant Taverne Du Valais",
    "wof:placetype":"venue"
},
  "geometry": {"coordinates":[6.0999398232,46.2148132324],"type":"Point"}
}