{
  "type": "Feature",
  "properties": {
    "iso:country":"CH",
    "sg:address":"Essanestrasse 316",
    "sg:city":"Eschen",
    "sg:orig_category":"Architekturb\u00fcros",
    "sg:phone":"+41 75 373 22 79",
    "sg:postcode":"9492",
    "wof:name":"Atelier Wilfried Gassner Architekturb\u00fcro",
    "wof:placetype":"venue"
},
  "geometry": {"coordinates":[9.51084,47.210541],"type":"Point"}
}