{
  "type": "Feature",
  "properties": {
    "iso:country":"CH",
    "sg:address":"Wolfetslohstrasse 3",
    "sg:city":"Wettswil",
    "sg:orig_category":"Sportvereine Wassersport Schwimmen",
    "sg:phone":"+41 17000256",
    "sg:postcode":"8907",
    "sg:province":"Z\u00fcrich",
    "wof:name":"Schwimmclub",
    "wof:placetype":"venue"
},
  "geometry": {"coordinates":[8.477722168,47.3329048157],"type":"Point"}
}