{
  "type": "Feature",
  "properties": {
    "iso:country":"CH",
    "sg:address":"France Avenue De 80",
    "sg:city":"Lausanne",
    "sg:orig_category":"Allgemeinbildende weiterf\u00fchrende Schulen",
    "sg:postcode":"1004",
    "sg:province":"Vaud",
    "wof:name":"Ecole De R\u00e9flexologie Bayly Switzerland, No\u00eblle Weyeneth",
    "wof:placetype":"venue"
},
  "geometry": {"coordinates":[6.632335,46.519596],"type":"Point"}
}