{
  "type": "Feature",
  "properties": {
    "iso:country":"CH",
    "sg:address":"Goldackerweg 5",
    "sg:city":"Z\u00fcrich",
    "sg:orig_category":"Glaserei",
    "sg:phone":"+41 13025265",
    "sg:postcode":"8047",
    "sg:province":"Z\u00fcrich",
    "wof:name":"Mario Vergata Verglasungen",
    "wof:placetype":"venue"
},
  "geometry": {"coordinates":[8.4876365662,47.3711967468],"type":"Point"}
}