{
  "type": "Feature",
  "properties": {
    "iso:country":"CH",
    "sg:address":"Falkenstrasse 25 8008 Z\u00fcrich. Postfach",
    "sg:city":"Z\u00fcrich",
    "sg:orig_category":"Handelsvermittlung von sonstigen Waren Herstellung von Medikamenten U sonstigen pharmazeutischen Erz",
    "sg:phone":"+41 12683012",
    "sg:postcode":"8008",
    "sg:province":"Z\u00fcrich",
    "wof:name":"Rotpunkt Pharma Ag Serviceunternehmen F\u00fcr Apotheken, Bes. Im Bereich Beschaffung, Marketing",
    "wof:placetype":"venue"
},
  "geometry": {"coordinates":[8.54845047,47.3659515381],"type":"Point"}
}