{
  "type": "Feature",
  "properties": {
    "iso:country":"CH",
    "sg:address":"Hinterwilerstrasse 287",
    "sg:city":"Uerkheim",
    "sg:orig_category":"Allgemeiner Hoch U Tiefbau Hoch U Tiefbau",
    "sg:phone":"+41 18334547",
    "sg:postcode":"4813",
    "sg:province":"Aargau",
    "wof:name":"Baer, Bauunternehmung.",
    "wof:placetype":"venue"
},
  "geometry": {"coordinates":[8.644192,47.412247],"type":"Point"}
}