{
  "type": "Feature",
  "properties": {
    "iso:country":"CH",
    "sg:address":"Waldstrasse 4",
    "sg:city":"Schaffhausen",
    "sg:orig_category":"Druck ohne Zeitungsdruck Verlagsgewerbe",
    "sg:phone":"+41 52 625 58 72",
    "sg:postcode":"8200",
    "sg:province":"Schaffhausen",
    "wof:name":"Bolli & B\u00f6cherer Ag",
    "wof:placetype":"venue"
},
  "geometry": {"coordinates":[8.6347703934,47.7082748413],"type":"Point"}
}