{
  "type": "Feature",
  "properties": {
    "iso:country":"CH",
    "sg:address":"Kasernenstrasse 44",
    "sg:city":"Liestal",
    "sg:orig_category":"Abwasserreinigung, Abfallbeseitigung U sonstige Entsorgung Spezieller Tiefbau",
    "sg:phone":"+41 79 645 77 17",
    "sg:postcode":"4410",
    "sg:province":"Basel-Landschaft",
    "wof:name":"Stutz Max",
    "wof:placetype":"venue"
},
  "geometry": {"coordinates":[7.739871,47.481079],"type":"Point"}
}