{
  "type": "Feature",
  "properties": {
    "iso:country":"CH",
    "sg:address":"Kurhausstrasse 41",
    "sg:city":"Dussnang",
    "sg:classifiers":[
        {
            "category":"Restaurant",
            "type":"Food & Drink"
        }
    ],
    "sg:phone":"+41 71 977 15 36",
    "sg:postcode":"8374",
    "sg:province":"Thurgau",
    "wof:name":"Restaurant Ochsen",
    "wof:placetype":"venue"
},
  "geometry": {"coordinates":[8.959438324,47.4308242798],"type":"Point"}
}