{
  "type": "Feature",
  "properties": {
    "iso:country":"CH",
    "sg:address":"Werdenberg",
    "sg:city":"Werdenberg",
    "sg:classifiers":[
        {
            "category":"Banks & Credit Unions",
            "subcategory":"Bank",
            "type":"Services"
        }
    ],
    "sg:phone":"+41 81 772 16 86",
    "sg:postcode":"9470",
    "sg:province":"St. Gallen",
    "wof:name":"Schweizer Verband, Der Raiffeisenbanken",
    "wof:placetype":"venue"
},
  "geometry": {"coordinates":[9.46269,47.16938],"type":"Point"}
}