{
  "type": "Feature",
  "properties": {
    "iso:country":"CH",
    "sg:address":"Dammstrasse 21 4500 Solothurn. Postfach",
    "sg:city":"Solothurn",
    "sg:orig_category":"Unclassifiable Establishments",
    "sg:postcode":"4500",
    "sg:province":"Solothurn",
    "wof:name":"Mnht Holding Ag Beteiligungen Usw",
    "wof:placetype":"venue"
},
  "geometry": {"coordinates":[7.5324511528,47.205871582],"type":"Point"}
}