{
  "type": "Feature",
  "properties": {
    "addr:full":"Pilatusstrasse 20 4663 Aarburg. Postfach Aarburg Aargau 4663",
    "addr:housenumber":"20",
    "addr:postcode":"4663 aarburg. postfach;4663",
    "addr:street":"Pilatusstrasse",
    "iso:country":"CH",
    "sg:address":"Pilatusstrasse 20 4663 Aarburg. Postfach",
    "sg:city":"Aarburg",
    "sg:orig_category":"Bauschreinerei Herstellung von Konstruktionsteilen, Fertigbauteilen U Ausbauelementen aus Holz",
    "sg:phone":"+41 62 791 64 41",
    "sg:postcode":"4663",
    "sg:province":"Aargau",
    "wof:name":"Gugelmann Innenausbau Ag",
    "wof:placetype":"venue"
},
  "geometry": {"coordinates":[7.902243,47.318253],"type":"Point"}
}