{
  "type": "Feature",
  "properties": {
    "iso:country":"CH",
    "sg:address":"Les Revez",
    "sg:city":"Collonges",
    "sg:orig_category":"Blumen U Zierpflanzenbau Fachdetailhandel in Verkaufsr\u00e4umen",
    "sg:phone":"+41 27 767 15 85",
    "sg:postcode":"1903",
    "sg:province":"Valais",
    "wof:name":"Mottiez & Cie Fleurs",
    "wof:placetype":"venue"
},
  "geometry": {"coordinates":[7.031515,46.171524],"type":"Point"}
}