{
  "type": "Feature",
  "properties": {
    "iso:country":"CH",
    "sg:address":"Usterstrasse 61",
    "sg:city":"D\u00fcbendorf",
    "sg:orig_category":"Detailhandel mit Sportartikeln Fachdetailhandel in Verkaufsr\u00e4umen",
    "sg:phone":"+41 18211473",
    "sg:postcode":"8600",
    "sg:province":"Z\u00fcrich",
    "wof:name":"Wolfensberger Sport Ag",
    "wof:placetype":"venue"
},
  "geometry": {"coordinates":[8.6254110336,47.3966674805],"type":"Point"}
}