{
  "type": "Feature",
  "properties": {
    "iso:country":"CH",
    "sg:address":"Ohmstrasse 14",
    "sg:city":"Z\u00fcrich",
    "sg:orig_category":"Versicherungen Hauptagenturen",
    "sg:phone":"+41 13113290",
    "sg:postcode":"8050",
    "sg:province":"Z\u00fcrich",
    "wof:name":"Die Mobiliar Versicherungen & Vorsorge",
    "wof:placetype":"venue"
},
  "geometry": {"coordinates":[8.5458774567,47.4112854004],"type":"Point"}
}