{
  "type": "Feature",
  "properties": {
    "iso:country":"CH",
    "sg:address":"Rue Du Temple 11",
    "sg:city":"B\u00f4le",
    "sg:orig_category":"Stukkateurgewerbe, Gipserei U Verputzerei",
    "sg:phone":"+41 32 842 54 52",
    "sg:postcode":"2014",
    "sg:province":"Neuch\u00e2tel",
    "wof:name":"Barbier & Cruciato S\u00e0rl Pl\u00e2trerie & Peinture",
    "wof:placetype":"venue"
},
  "geometry": {"coordinates":[6.840927124,46.9667854309],"type":"Point"}
}