{
  "type": "Feature",
  "properties": {
    "iso:country":"CH",
    "sg:address":"Rue De L'eglise 13",
    "sg:city":"Bo\u00e9court",
    "sg:orig_category":"Vorschulen, Kinderg\u00e4rten",
    "sg:phone":"+41 32 926 08 61",
    "sg:postcode":"2856",
    "sg:province":"Jura",
    "wof:name":"Ecole Enfantine",
    "wof:placetype":"venue"
},
  "geometry": {"coordinates":[6.8369669914,47.103767395],"type":"Point"}
}