{
  "type": "Feature",
  "properties": {
    "iso:country":"CH",
    "sg:address":"Bahnweg 2",
    "sg:city":"Laupen",
    "sg:classifiers":[
        {
            "category":"Manufacturing",
            "subcategory":"Paper Products",
            "type":"Manufacturing & Wholesale Goods"
        }
    ],
    "sg:phone":"+41 31 747 33 00",
    "sg:postcode":"3177",
    "sg:province":"Bern",
    "sg:tags":[
        "blister",
        "cards",
        "environment-friendly"
    ],
    "wof:name":"Poly Laupen Ag",
    "wof:placetype":"venue"
},
  "geometry": {"coordinates":[7.236317,46.905712],"type":"Point"}
}