{
  "type": "Feature",
  "properties": {
    "iso:country":"CH",
    "sg:address":"Route St-l\u00e9gier 21 1807 Blonay Case Postale 133",
    "sg:city":"Blonay",
    "sg:orig_category":"Stukkateurgewerbe, Gipserei U Verputzerei",
    "sg:phone":"+41 21 943 19 29",
    "sg:postcode":"1807",
    "sg:province":"Vaud",
    "wof:name":"Th\u00e9raulaz Sa",
    "wof:placetype":"venue"
},
  "geometry": {"coordinates":[6.8913040161,46.4676094055],"type":"Point"}
}