{
  "type": "Feature",
  "properties": {
    "iso:country":"CH",
    "sg:address":"Im Moos 11",
    "sg:city":"Effretikon",
    "sg:orig_category":"Grosshandel mit B\u00fcromaschinen Grosshandel mit Datenverarbeitungsger\u00e4ten",
    "sg:phone":"+41 52 343 85 90",
    "sg:postcode":"8307",
    "sg:province":"Z\u00fcrich",
    "wof:name":"Comgra Zollinger",
    "wof:placetype":"venue"
},
  "geometry": {"coordinates":[8.6915426254,47.4253768921],"type":"Point"}
}