{
  "type": "Feature",
  "properties": {
    "iso:country":"CH",
    "sg:address":"F\u00f6hrenstrasse 33",
    "sg:city":"Schaffhausen",
    "sg:orig_category":"Detailhandel mit Getr\u00e4nken Detailhandel mit Waren verschiedener Art, Hauptrichtung Nahrungsmittel",
    "sg:phone":"+41 32 725 12 34",
    "sg:postcode":"8200",
    "sg:province":"Schaffhausen",
    "wof:name":"Alimentation Aux Gourmets Sa",
    "wof:placetype":"venue"
},
  "geometry": {"coordinates":[6.9287719727,46.991230011],"type":"Point"}
}