{
  "type": "Feature",
  "properties": {
    "iso:country":"CH",
    "sg:address":"Steinh\u00f6lzlistrasse 7 8247 Flurlingen. Postfach",
    "sg:city":"Niederuzwil",
    "sg:orig_category":"Detailhandel mit M\u00f6beln U Haushaltsgegenst\u00e4nden",
    "sg:postcode":"9244",
    "sg:province":"St. Gallen",
    "wof:name":"M\u00f6bel-waebers-fundgrube Ag",
    "wof:placetype":"venue"
},
  "geometry": {"coordinates":[8.7815437317,47.3674468994],"type":"Point"}
}