{
  "type": "Feature",
  "properties": {
    "iso:country":"CH",
    "sg:address":"Emile-ganguillet-weg 27a",
    "sg:city":"Biel/bienne",
    "sg:orig_category":"Wohnheime",
    "sg:phone":"+41 32 365 11 98",
    "sg:postcode":"2503",
    "sg:province":"Bern",
    "wof:name":"Wohnst\u00e4tte Anker",
    "wof:placetype":"venue"
},
  "geometry": {"coordinates":[7.2552571297,47.1253929138],"type":"Point"}
}