{
  "type": "Feature",
  "properties": {
    "iso:country":"CH",
    "sg:address":"Langackerweg 30",
    "sg:city":"Niederhasli",
    "sg:orig_category":"Unclassifiable Establishments",
    "sg:phone":"+41 18505990",
    "sg:postcode":"8155",
    "sg:province":"Z\u00fcrich",
    "wof:name":"Nefertiti Bankett Und Partyservice Tolba A. Bankett, Partyservice",
    "wof:placetype":"venue"
},
  "geometry": {"coordinates":[8.4895019531,47.4817085266],"type":"Point"}
}