{
  "type": "Feature",
  "properties": {
    "iso:country":"CH",
    "sg:address":"Ziegeleistrasse 10",
    "sg:city":"Appenzell",
    "sg:orig_category":"Kaminfeger",
    "sg:phone":"+41 71 787 12 44",
    "sg:postcode":"9050",
    "sg:province":"Appenzell Innerhoden",
    "wof:name":"Josef Rusch Kaminfegergesch\u00e4ft",
    "wof:placetype":"venue"
},
  "geometry": {"coordinates":[9.4071426392,47.3256225586],"type":"Point"}
}