{
  "type": "Feature",
  "properties": {
    "iso:country":"CH",
    "sg:address":"Grande Rue 17",
    "sg:city":"Grandval",
    "sg:classifiers":[
        {
            "category":"Retail",
            "subcategory":"Repair Shop",
            "type":"Services"
        }
    ],
    "sg:phone":"+41 32 499 97 35",
    "sg:postcode":"2745",
    "sg:province":"Bern",
    "sg:tags":[
        "workshop",
        "mechanical"
    ],
    "wof:name":"Fran\u00e7is Ischy Sa",
    "wof:placetype":"venue"
},
  "geometry": {"coordinates":[7.419508934,47.2822761536],"type":"Point"}
}