{
  "type": "Feature",
  "properties": {
    "iso:country":"CH",
    "sg:address":"Ziegelh\u00fctte 589",
    "sg:city":"Flaach",
    "sg:orig_category":"RESTAURANTS: TEA-ROOMS",
    "sg:phone":"+41 61 721 10 34",
    "sg:postcode":"8416",
    "sg:province":"Z\u00fcrich",
    "wof:name":"Restaurant Zihlmann, Suter Stefan",
    "wof:placetype":"venue"
},
  "geometry": {"coordinates":[7.5278820992,47.5065765381],"type":"Point"}
}