{
  "type": "Feature",
  "properties": {
    "addr:full":"Quai Des Bergues 29 Gen\u00e8ve Gen\u00e8ve 1201",
    "addr:housenumber":"29",
    "addr:postcode":"1201",
    "addr:street":"Quai Des Bergues",
    "iso:country":"CH",
    "sg:address":"Quai Des Bergues 29",
    "sg:city":"Gen\u00e8ve",
    "sg:orig_category":"Arztpraxen",
    "sg:phone":"+41 22 732 95 00",
    "sg:postcode":"1201",
    "sg:province":"Gen\u00e8ve",
    "wof:name":"Dr M\u00e9d. Harry Boillat M\u00e9decin Sp\u00e9cialiste Fmh",
    "wof:placetype":"venue"
},
  "geometry": {"coordinates":[6.145936,46.206654],"type":"Point"}
}