{
  "type": "Feature",
  "properties": {
    "iso:country":"CH",
    "sg:address":"Rue Rodo 5",
    "sg:city":"Gen\u00e8ve",
    "sg:orig_category":"Primarschulen",
    "sg:phone":"+41 22 771 16 26",
    "sg:postcode":"1205",
    "sg:province":"Gen\u00e8ve",
    "wof:name":"Ecole Primaire La Bossenaz",
    "wof:placetype":"venue"
},
  "geometry": {"coordinates":[6.1364598274,46.145401001],"type":"Point"}
}