{
  "type": "Feature",
  "properties": {
    "iso:country":"CH",
    "sg:address":"Weckingen 12",
    "sg:city":"Warth",
    "sg:orig_category":"Verwertung von Milch",
    "sg:postcode":"8532",
    "sg:province":"Thurgau",
    "wof:name":"K\u00e4sereigenossenschaft Weiningen",
    "wof:placetype":"venue"
},
  "geometry": {"coordinates":[8.8733491898,47.5838813782],"type":"Point"}
}