{
  "type": "Feature",
  "properties": {
    "iso:country":"CH",
    "sg:address":"Route Suisse 9a",
    "sg:city":"Mies",
    "sg:orig_category":"Instandhaltung U Reparatur von Automobilen",
    "sg:postcode":"1295",
    "sg:province":"Vaud",
    "wof:name":"Garage Du Rond-point, Hajj D.",
    "wof:placetype":"venue"
},
  "geometry": {"coordinates":[6.1678080559,46.2968559265],"type":"Point"}
}