{
  "type": "Feature",
  "properties": {
    "iso:country":"CH",
    "sg:address":"Seestrasse 5",
    "sg:city":"St\u00e4fa",
    "sg:orig_category":"Physiotherapie",
    "sg:phone":"+41 19267550",
    "sg:postcode":"8712",
    "sg:province":"Z\u00fcrich",
    "wof:name":"Adriaan & Susan Brouwer Physiotherapie",
    "wof:placetype":"venue"
},
  "geometry": {"coordinates":[8.714509964,47.2409591675],"type":"Point"}
}