{
  "type": "Feature",
  "properties": {
    "iso:country":"CH",
    "sg:address":"Rue Guill.-techtermann 2 1700 Fribourg. Postfach",
    "sg:city":"Fribourg",
    "sg:orig_category":"Kinderkrippen U horte",
    "sg:phone":"+41 32 757 11 86",
    "sg:postcode":"1701",
    "sg:province":"Fribourg",
    "wof:name":"Garderie D'enfants Cure Catholique Romaine",
    "wof:placetype":"venue"
},
  "geometry": {"coordinates":[7.0351037979,47.0506706238],"type":"Point"}
}