{
  "type": "Feature",
  "properties": {
    "iso:country":"CH",
    "sg:address":"Kottenrainweg 13",
    "sg:city":"Horgen",
    "sg:orig_category":"Architektur U Ingenieurb\u00fcros",
    "sg:phone":"+41 17258726",
    "sg:postcode":"8810",
    "sg:province":"Z\u00fcrich",
    "wof:name":"Westafin Ag",
    "wof:placetype":"venue"
},
  "geometry": {"coordinates":[8.602941,47.25528],"type":"Point"}
}