{
  "type": "Feature",
  "properties": {
    "iso:country":"CH",
    "sg:address":"7477",
    "sg:city":"Filisur",
    "sg:orig_category":"G\u00fcterbef\u00f6rderung im Strassenverkehr",
    "sg:phone":"+41 81 404 16 23",
    "sg:postcode":"7477",
    "sg:province":"Graubunden",
    "wof:name":"Peter Heinrich Transporte",
    "wof:placetype":"venue"
},
  "geometry": {"coordinates":[9.6858797073,46.6734809875],"type":"Point"}
}