{
  "type": "Feature",
  "properties": {
    "iso:country":"CH",
    "sg:address":"Grand Rue 42",
    "sg:city":"Montreux",
    "sg:orig_category":"RESTAURANTS: TEA-ROOMS",
    "sg:postcode":"1820",
    "sg:province":"Vaud",
    "wof:name":"Restaurant Chinois \u00abla Fleur De Lotus\u00bb Lam",
    "wof:placetype":"venue"
},
  "geometry": {"coordinates":[6.9187831879,46.6973342896],"type":"Point"}
}