{
  "type": "Feature",
  "properties": {
    "iso:country":"CH",
    "sg:address":"Dorf 90",
    "sg:city":"Birrwil",
    "sg:orig_category":"Bauschreinerei Herstellung von Konstruktionsteilen, Fertigbauteilen U Ausbauelementen aus Holz",
    "sg:phone":"+41 62 772 13 55",
    "sg:postcode":"5708",
    "sg:province":"Aargau",
    "wof:name":"B\u00e4chtold Hanspeter, Schreinerei",
    "wof:placetype":"venue"
},
  "geometry": {"coordinates":[8.195035,47.290249],"type":"Point"}
}