{
  "type": "Feature",
  "properties": {
    "iso:country":"CH",
    "sg:address":"M\u00fchlemattweg 49",
    "sg:city":"Magden",
    "sg:orig_category":"Grosshandel mit B\u00fcromaschinen Grosshandel mit Datenverarbeitungsger\u00e4ten",
    "sg:phone":"+41 61 843 00 30",
    "sg:postcode":"4312",
    "sg:province":"Aargau",
    "wof:name":"Stern & Partner Ag Edv Hard-& Software",
    "wof:placetype":"venue"
},
  "geometry": {"coordinates":[7.8158960342,47.5188293457],"type":"Point"}
}