{
  "type": "Feature",
  "properties": {
    "iso:country":"CH",
    "sg:address":"Baarerstrasse 6",
    "sg:city":"Zug",
    "sg:orig_category":"Interessenvertretungen",
    "sg:postcode":"6300",
    "sg:province":"Zug",
    "wof:name":"Momentous-stiftung",
    "wof:placetype":"venue"
},
  "geometry": {"coordinates":[8.5163192749,47.1712226868],"type":"Point"}
}