{
  "type": "Feature",
  "properties": {
    "iso:country":"CH",
    "sg:address":"8231",
    "sg:city":"Hemmental",
    "sg:orig_category":"Primarschulen",
    "sg:phone":"+41 52 646 29 70",
    "sg:postcode":"8231",
    "sg:province":"Schaffhausen",
    "wof:name":"Primarschule",
    "wof:placetype":"venue"
},
  "geometry": {"coordinates":[8.6988096237,47.6564788818],"type":"Point"}
}