{
  "type": "Feature",
  "properties": {
    "iso:country":"CH",
    "sg:address":"Flurstrasse 33",
    "sg:city":"Hagendorn",
    "sg:orig_category":"Herstellung von sonstigen Maschinen f\u00fcr unspezifische Verwendung Sonstiger Grosshandel",
    "sg:phone":"+41 41 783 22 66",
    "sg:postcode":"6332",
    "sg:province":"Zug",
    "wof:name":"Jadena Peter Metzger",
    "wof:placetype":"venue"
},
  "geometry": {"coordinates":[8.4297485352,47.2013587952],"type":"Point"}
}