{
  "type": "Feature",
  "properties": {
    "iso:country":"CH",
    "sg:address":"Ruchonnet Avenue Louis- 27",
    "sg:city":"Lausanne",
    "sg:orig_category":"Non-Classified Establishments",
    "sg:postcode":"1003",
    "sg:province":"Vaud",
    "wof:name":"Alys Technologies Sa",
    "wof:placetype":"venue"
},
  "geometry": {"coordinates":[6.6250009537,46.5188064575],"type":"Point"}
}