{
  "type": "Feature",
  "properties": {
    "iso:country":"CH",
    "sg:address":"Im Ried 10",
    "sg:city":"Zwingen",
    "sg:orig_category":"Instandhaltung U Reparatur von Automobilen",
    "sg:postcode":"4222",
    "sg:province":"Basel-Landschaft",
    "wof:name":"Autimag",
    "wof:placetype":"venue"
},
  "geometry": {"coordinates":[9.3514728546,47.4177513123],"type":"Point"}
}