{
  "type": "Feature",
  "properties": {
    "iso:country":"CH",
    "sg:address":"L\u00f6wenstrasse 1",
    "sg:city":"M\u00fchlau",
    "sg:orig_category":"RESTAURANTS: TEA-ROOMS",
    "sg:phone":"+41 56 668 12 46",
    "sg:postcode":"5642",
    "sg:province":"Aargau",
    "wof:name":"El Loco Ag",
    "wof:placetype":"venue"
},
  "geometry": {"coordinates":[8.390039444,47.2289428711],"type":"Point"}
}