{
  "type": "Feature",
  "properties": {
    "iso:country":"CH",
    "sg:address":"Kirchstrasse 3a",
    "sg:city":"Liebefeld",
    "sg:orig_category":"Grosshandel mit pharmazeutischen Erzeugnissen",
    "sg:phone":"+41 31 971 55 73",
    "sg:postcode":"3097",
    "sg:province":"Bern",
    "wof:name":"Nelly M\u00fcller Mimex Import-export",
    "wof:placetype":"venue"
},
  "geometry": {"coordinates":[7.4283747673,46.9307670593],"type":"Point"}
}