{
  "type": "Feature",
  "properties": {
    "iso:country":"CH",
    "sg:address":"Mauvoisin",
    "sg:city":"Fionnay",
    "sg:classifiers":[
        {
            "category":"Travel",
            "subcategory":"Hotels & Motels",
            "type":"Entertainment"
        }
    ],
    "sg:phone":"+41 27 778 11 30",
    "sg:postcode":"1948",
    "sg:province":"Valais",
    "sg:tags":[
        "hotels",
        "mit",
        "restaurant"
    ],
    "wof:name":"H\u00f4tel Mauvoisin",
    "wof:placetype":"venue"
},
  "geometry": {"coordinates":[7.307404995,46.0331001282],"type":"Point"}
}