{
  "type": "Feature",
  "properties": {
    "iso:country":"CH",
    "sg:address":"Rue Du Moulin 20",
    "sg:city":"Montagne-moutier",
    "sg:classifiers":[
        {
            "category":"Professional",
            "subcategory":"Employment Agencies",
            "type":"Services"
        }
    ],
    "sg:phone":"+41 32 493 46 06",
    "sg:postcode":"2740",
    "sg:province":"Bern",
    "sg:tags":[
        "personal",
        "u",
        "stellenvermittlung"
    ],
    "wof:name":"Paul Cramatte Bureau De Placement",
    "wof:placetype":"venue"
},
  "geometry": {"coordinates":[7.3689460754,47.2780418396],"type":"Point"}
}