{
  "type": "Feature",
  "properties": {
    "iso:country":"CH",
    "sg:address":"Champoussin",
    "sg:city":"Val-d'illiez",
    "sg:orig_category":"Detailhandel mit Waren verschiedener Art, Hauptrichtung Nahrungsmittel",
    "sg:phone":"+41 24 477 22 80",
    "sg:postcode":"1873",
    "sg:province":"Valais",
    "wof:name":"Eggen Ernest",
    "wof:placetype":"venue"
},
  "geometry": {"coordinates":[6.8638601303,46.2090797424],"type":"Point"}
}