{
  "type": "Feature",
  "properties": {
    "iso:country":"CH",
    "sg:address":"Rue De La Gare 4",
    "sg:city":"Peseux",
    "sg:orig_category":"Hardness Testers, Durometers",
    "sg:phone":"+41 32 557 56 00",
    "sg:postcode":"2034",
    "sg:province":"Neuch\u00e2tel",
    "wof:name":"Csm Instruments Ag",
    "wof:placetype":"venue"
},
  "geometry": {"coordinates":[6.8859930038,46.9855003357],"type":"Point"}
}