{
  "type": "Feature",
  "properties": {
    "addr:full":"Untertor 4 8400 Winterthur. Postfach 272 Winterthur Z\u00fcrich 8401",
    "addr:housenumber":"4;272",
    "addr:postcode":"8400;8401",
    "addr:street":"Untertor;Postfach",
    "iso:country":"CH",
    "sg:address":"Untertor 4 8400 Winterthur. Postfach 272",
    "sg:city":"Winterthur",
    "sg:orig_category":"Detailhandel mit Brillen U anderen Sehhilfen Fachdetailhandel in Verkaufsr\u00e4umen",
    "sg:phone":"+41 52 212 03 03",
    "sg:postcode":"8401",
    "sg:province":"Z\u00fcrich",
    "wof:name":"Optiker Zwicker Ag Winterthur",
    "wof:placetype":"venue"
},
  "geometry": {"coordinates":[8.726143,47.499443],"type":"Point"}
}