{
  "type": "Feature",
  "properties": {
    "iso:country":"CH",
    "sg:address":"7111",
    "sg:city":"Pitasch",
    "sg:orig_category":"Gemeindeverwaltungen",
    "sg:phone":"+41 81 931 23 23",
    "sg:postcode":"7111",
    "sg:province":"Graubunden",
    "wof:name":"Canzlia Communala Pitasch",
    "wof:placetype":"venue"
},
  "geometry": {"coordinates":[9.2177419662,46.7314033508],"type":"Point"}
}