{
  "type": "Feature",
  "properties": {
    "iso:country":"CH",
    "sg:address":"Grabenstrasse 9",
    "sg:city":"Frauenfeld",
    "sg:orig_category":"Vermietung U Verpachtung von eigenen Immobilien Vermittlung von Immobilien",
    "sg:phone":"+41 52 721 23 14",
    "sg:postcode":"8500",
    "sg:province":"Thurgau",
    "wof:name":"Werner J. Ing. Ag",
    "wof:placetype":"venue"
},
  "geometry": {"coordinates":[8.8969430923,47.5567893982],"type":"Point"}
}