{
  "type": "Feature",
  "properties": {
    "iso:country":"CH",
    "sg:address":"Gartenweg 5",
    "sg:city":"Rudolfstetten",
    "sg:orig_category":"Unternehmensberatung",
    "sg:phone":"+41 56 633 00 38",
    "sg:postcode":"8964",
    "sg:province":"Aargau",
    "wof:name":"Projectos Ag",
    "wof:placetype":"venue"
},
  "geometry": {"coordinates":[8.36951828,47.3629302979],"type":"Point"}
}