{
  "type": "Feature",
  "properties": {
    "iso:country":"CH",
    "sg:address":"6746",
    "sg:city":"Lavorgo",
    "sg:orig_category":"Detailhandel mit Fleisch U Fleischwaren",
    "sg:phone":"+41 91 865 11 44",
    "sg:postcode":"6746",
    "sg:province":"Ticino",
    "wof:name":"Donato Mattioli Macelleria-salumeria",
    "wof:placetype":"venue"
},
  "geometry": {"coordinates":[8.840929985,46.440448761],"type":"Point"}
}