{
  "type": "Feature",
  "properties": {
    "iso:country":"CH",
    "sg:address":"Molkenstrasse 21",
    "sg:city":"Z\u00fcrich",
    "sg:orig_category":"Sonstige mit der Informatik verbundene T\u00e4tigkeiten",
    "sg:phone":"+41 16831168",
    "sg:postcode":"8004",
    "sg:province":"Z\u00fcrich",
    "wof:name":"Topcons Keel",
    "wof:placetype":"venue"
},
  "geometry": {"coordinates":[8.6556339264,47.239276886],"type":"Point"}
}