{
  "type": "Feature",
  "properties": {
    "iso:country":"CH",
    "sg:address":"Bleicherweg 66",
    "sg:city":"Z\u00fcrich",
    "sg:orig_category":"Elektrizit\u00e4tsversorgung",
    "sg:postcode":"8027",
    "sg:province":"Z\u00fcrich",
    "wof:name":"Aeschlimann Umwelttechnik Gmbh",
    "wof:placetype":"venue"
},
  "geometry": {"coordinates":[7.3774490356,47.0866775513],"type":"Point"}
}