{
  "type": "Feature",
  "properties": {
    "iso:country":"CH",
    "sg:address":"M\u00f4rache Rue De La 8",
    "sg:city":"Nyon",
    "sg:orig_category":"Erbringung von Dienstleistungen f\u00fcr Unternehmen",
    "sg:phone":"+41 22 990 21 41",
    "sg:postcode":"1260",
    "sg:province":"Vaud",
    "wof:name":"Atelier Zuppinger Vincent Sa",
    "wof:placetype":"venue"
},
  "geometry": {"coordinates":[6.2390799522,46.3823661804],"type":"Point"}
}