{
  "type": "Feature",
  "properties": {
    "iso:country":"CH",
    "sg:address":"Gupf 20",
    "sg:city":"Rehetobel",
    "sg:orig_category":"Grosshandel mit B\u00fcromaschinen U einrichtungen",
    "sg:phone":"+41 71 311 20 26",
    "sg:postcode":"9038",
    "sg:province":"Appenzell Ausserrhoden",
    "wof:name":"Sommer Peter, B\u00fcro Und Kindergarteneinrichtungen",
    "wof:placetype":"venue"
},
  "geometry": {"coordinates":[9.3109416962,47.413394928],"type":"Point"}
}