{
  "type": "Feature",
  "properties": {
    "iso:country":"CH",
    "sg:address":"Chemin Du Relais 1958 St-l\u00e9onard. Postfach",
    "sg:city":"St-l\u00e9onard",
    "sg:orig_category":"Herstellung von Metallkonstruktionen",
    "sg:postcode":"1958",
    "sg:province":"Valais",
    "wof:name":"Schwery Camille & Fils Sa",
    "wof:placetype":"venue"
},
  "geometry": {"coordinates":[7.4209852219,46.2528305054],"type":"Point"}
}