{
  "type": "Feature",
  "properties": {
    "iso:country":"CH",
    "sg:address":"Griebengasse 18",
    "sg:city":"Arlesheim",
    "sg:orig_category":"Sanit\u00e4r U Heizungsinstallation Sonstiger Grosshandel",
    "sg:phone":"+41 32 422 28 74",
    "sg:postcode":"4144",
    "sg:province":"Basel-Landschaft",
    "wof:name":"Faivre Henri Sa",
    "wof:placetype":"venue"
},
  "geometry": {"coordinates":[7.3565349579,47.3669662476],"type":"Point"}
}