{
  "type": "Feature",
  "properties": {
    "addr:full":"Allmendstrasse 22 6048 Horw. Postfach 459 Horw Luzern 6048",
    "addr:housenumber":"22;459",
    "addr:postcode":"6048;6048",
    "addr:street":"Allmendstrasse;Postfach",
    "iso:country":"CH",
    "sg:address":"Allmendstrasse 22 6048 Horw. Postfach 459",
    "sg:city":"Horw",
    "sg:orig_category":"Herstellung von Metallkonstruktionen Stahl U Leichtmetallbau",
    "sg:phone":"+41 41 340 51 31",
    "sg:postcode":"6048",
    "sg:province":"Luzern",
    "wof:name":"Wostrag",
    "wof:placetype":"venue"
},
  "geometry": {"coordinates":[8.305931,47.022095],"type":"Point"}
}