{
  "type": "Feature",
  "properties": {
    "iso:country":"CH",
    "sg:address":"Route Principale 2",
    "sg:city":"Courgevaux",
    "sg:orig_category":"Mechanische Werkst\u00e4tten",
    "sg:phone":"+41 26 670 45 85",
    "sg:postcode":"1796",
    "sg:province":"Fribourg",
    "wof:name":"Rudolf Graf Atelier M\u00e9canique",
    "wof:placetype":"venue"
},
  "geometry": {"coordinates":[7.1133999825,46.9134559631],"type":"Point"}
}