{
  "type": "Feature",
  "properties": {
    "addr:full":"Churer Str. 168 Pf\u00e4ffikon Schwyz 8808",
    "addr:housenumber":"168",
    "addr:postcode":"8808",
    "addr:street":"Str.;Schwyz",
    "iso:country":"CH",
    "sg:address":"Churer Str. 168",
    "sg:city":"Pf\u00e4ffikon",
    "sg:classifiers":[
        {
            "category":"Professional",
            "subcategory":"Advertising",
            "type":"Services"
        }
    ],
    "sg:phone":"+41 55 415 68 18",
    "sg:postcode":"8808",
    "sg:province":"Schwyz",
    "sg:tags":[
        "information",
        "medium",
        "communication"
    ],
    "wof:name":"Highlight Communications Ag",
    "wof:placetype":"venue"
},
  "geometry": {"coordinates":[8.802979,47.200981],"type":"Point"}
}