{
  "type": "Feature",
  "properties": {
    "iso:country":"CH",
    "sg:address":"Alsenmattstrasse 7",
    "sg:city":"Thalwil",
    "sg:orig_category":"Allgemeiner Hoch U Tiefbau",
    "sg:phone":"+41 17204265",
    "sg:postcode":"8800",
    "sg:province":"Z\u00fcrich",
    "wof:name":"Sp\u00f6rri Bauunternehmung Ag",
    "wof:placetype":"venue"
},
  "geometry": {"coordinates":[8.552206,47.299263],"type":"Point"}
}