{
  "type": "Feature",
  "properties": {
    "iso:country":"CH",
    "sg:address":"Badenerstrasse 812",
    "sg:city":"Z\u00fcrich",
    "sg:orig_category":"Datenverarbeitungsdienste Fernmeldedienste",
    "sg:phone":"+41 14397031",
    "sg:postcode":"8048",
    "sg:province":"Z\u00fcrich",
    "wof:name":"Gct Ag Global Communication & Technology",
    "wof:placetype":"venue"
},
  "geometry": {"coordinates":[8.474527,47.393215],"type":"Point"}
}