{
  "type": "Feature",
  "properties": {
    "iso:country":"CH",
    "sg:address":"Justice Rue De La 1",
    "sg:city":"Del\u00e9mont",
    "sg:orig_category":"Technische, physikalische U chemische Untersuchung",
    "sg:phone":"+41 21 635 27 31",
    "sg:postcode":"2800",
    "sg:province":"Jura",
    "wof:name":"Sacr Sa, Soci\u00e9t\u00e9 D'analyses Et De Contr\u00f4les Routiers",
    "wof:placetype":"venue"
},
  "geometry": {"coordinates":[7.3439698219,47.3653564453],"type":"Point"}
}