{
  "type": "Feature",
  "properties": {
    "iso:country":"CH",
    "sg:address":"Jakobsbad",
    "sg:city":"Gonten",
    "sg:orig_category":"Zimmerei, Dachdeckerei, Bauspenglerei U Abdichtung",
    "sg:postcode":"9108",
    "sg:province":"Appenzell Innerhoden",
    "wof:name":"Br\u00e4ndle Heinz Bedachungen Ag",
    "wof:placetype":"venue"
},
  "geometry": {"coordinates":[9.1993598938,47.2241897583],"type":"Point"}
}