{
  "type": "Feature",
  "properties": {
    "iso:country":"CH",
    "sg:address":"Chemin Du Publiet 16",
    "sg:city":"Marly",
    "sg:orig_category":"Vermietung U Verpachtung von eigenen Immobilien",
    "sg:phone":"+41 26 436 54 54",
    "sg:postcode":"1723",
    "sg:province":"Fribourg",
    "wof:name":"Maillard Paul-henri",
    "wof:placetype":"venue"
},
  "geometry": {"coordinates":[7.1614470482,46.7787628174],"type":"Point"}
}