{
  "type": "Feature",
  "properties": {
    "iso:country":"CH",
    "sg:address":"Horwerstrasse 41",
    "sg:city":"Kriens",
    "sg:orig_category":"Tierarztpraxis",
    "sg:phone":"+41 41 310 99 22",
    "sg:postcode":"6010",
    "sg:province":"Luzern",
    "wof:name":"Dr. Med. Vet. Anton Burri Tierarzt",
    "wof:placetype":"venue"
},
  "geometry": {"coordinates":[8.287153244,47.0311317444],"type":"Point"}
}