{
  "type": "Feature",
  "properties": {
    "iso:country":"CH",
    "sg:address":"Chemin De La Colline 5",
    "sg:city":"Lausanne",
    "sg:orig_category":"Herstellung von Bereifungen Runderneuerung von Bereifungen",
    "sg:phone":"+41 21 624 13 91",
    "sg:postcode":"1007",
    "sg:province":"Vaud",
    "wof:name":"Silegg Pneus Service Ltd, \u00e0 Londres, Succursale De Lausanne",
    "wof:placetype":"venue"
},
  "geometry": {"coordinates":[6.6120100021,46.5214347839],"type":"Point"}
}