{
  "type": "Feature",
  "properties": {
    "iso:country":"CH",
    "sg:address":"Heubachstrasse 50",
    "sg:city":"Horgen",
    "sg:orig_category":"Unclassifiable Establishments",
    "sg:postcode":"8810",
    "sg:province":"Z\u00fcrich",
    "wof:name":"K\u00fcpfer Consulting Gmbh",
    "wof:placetype":"venue"
},
  "geometry": {"coordinates":[8.6033525467,47.2548866272],"type":"Point"}
}