{
  "type": "Feature",
  "properties": {
    "addr:full":"Ch. De La Gradelle 10 Ch\u00eane Bougeries Gen\u00e8ve 1224",
    "addr:housenumber":"10",
    "addr:postcode":"1224",
    "addr:street":"Ch. De La Gradelle;Bougeries",
    "iso:country":"CH",
    "sg:address":"Ch. De La Gradelle 10",
    "sg:city":"Ch\u00eane Bougeries",
    "sg:classifiers":[
        {
            "category":"Banks & Credit Unions",
            "subcategory":"Bank",
            "type":"Services"
        }
    ],
    "sg:phone":"+41 22 348 06 21",
    "sg:postcode":"1224",
    "sg:province":"Gen\u00e8ve",
    "wof:name":"Union De Banques Suisses, Centre De Loisirs La Gradelle",
    "wof:placetype":"venue"
},
  "geometry": {"coordinates":[6.181594,46.205463],"type":"Point"}
}