{
  "type": "Feature",
  "properties": {
    "iso:country":"CH",
    "sg:address":"Heinrich Stutz-strasse 2",
    "sg:city":"Urdorf",
    "sg:orig_category":"Autogaragen",
    "sg:phone":"+41 17344866",
    "sg:postcode":"8902",
    "sg:province":"Z\u00fcrich",
    "wof:name":"Herbert Cilly Sport-garage",
    "wof:placetype":"venue"
},
  "geometry": {"coordinates":[8.424052,47.371193],"type":"Point"}
}