{
  "type": "Feature",
  "properties": {
    "iso:country":"CH",
    "sg:address":"Dreilindenstrasse 27",
    "sg:city":"Luzern",
    "sg:orig_category":"Fussboden, Fliesen U Plattenlegerei, Tapeziererei",
    "sg:phone":"+41 41 410 86 83",
    "sg:postcode":"6006",
    "sg:province":"Luzern",
    "wof:name":"Durrer Ag Parquet Luzern",
    "wof:placetype":"venue"
},
  "geometry": {"coordinates":[8.3149547577,47.0574111938],"type":"Point"}
}