{
  "type": "Feature",
  "properties": {
    "iso:country":"CH",
    "sg:address":"Aarburgerstrasse 13",
    "sg:city":"Zofingen",
    "sg:orig_category":"Versandhandel",
    "sg:phone":"+41 62 752 22 44",
    "sg:postcode":"4800",
    "sg:province":"Aargau",
    "wof:name":"Philippe Binder Jeans-halle",
    "wof:placetype":"venue"
},
  "geometry": {"coordinates":[7.9414219856,47.2923698425],"type":"Point"}
}