{
  "type": "Feature",
  "properties": {
    "iso:country":"CH",
    "sg:address":"Unterdorfstrasse 7",
    "sg:city":"Sch\u00f6nb\u00fchl-urtenen",
    "sg:orig_category":"Technische B\u00fcros Elektro",
    "sg:phone":"+41 31 859 29 24",
    "sg:postcode":"3322",
    "sg:province":"Bern",
    "wof:name":"Hansj\u00f6rg Scheurmann Elektroplanung",
    "wof:placetype":"venue"
},
  "geometry": {"coordinates":[7.5036587715,47.0269966125],"type":"Point"}
}