{
  "type": "Feature",
  "properties": {
    "iso:country":"CH",
    "sg:address":"T\u00f6ssstrasse 1",
    "sg:city":"Rorbas",
    "sg:orig_category":"Sportvereine Turnen Vereine Damen",
    "sg:phone":"+41 56 442 10 50",
    "sg:postcode":"8427",
    "sg:province":"Z\u00fcrich",
    "wof:name":"Damenriege R\u00fcfenach",
    "wof:placetype":"venue"
},
  "geometry": {"coordinates":[8.2110204697,47.5044708252],"type":"Point"}
}