{
  "type": "Feature",
  "properties": {
    "iso:country":"CH",
    "sg:address":"Oberer Brunnacher 16",
    "sg:city":"Ramlinsburg",
    "sg:orig_category":"Sportvereine Orientierungslauf",
    "sg:phone":"+41 61 931 44 22",
    "sg:postcode":"4433",
    "sg:province":"Basel-Landschaft",
    "wof:name":"Olg Kakowa Liestal",
    "wof:placetype":"venue"
},
  "geometry": {"coordinates":[7.7660031319,47.4508323669],"type":"Point"}
}