{
  "type": "Feature",
  "properties": {
    "iso:country":"CH",
    "sg:address":"7550",
    "sg:city":"Scuol",
    "sg:orig_category":"Sportvereine Ballsport Fussball",
    "sg:phone":"+41 81 864 10 37",
    "sg:postcode":"7550",
    "sg:province":"Graubunden",
    "wof:name":"C.b.scuol",
    "wof:placetype":"venue"
},
  "geometry": {"coordinates":[10.3028278351,46.7987670898],"type":"Point"}
}