{
  "type": "Feature",
  "properties": {
    "iso:country":"CH",
    "sg:address":"Hofstrasse 21",
    "sg:city":"H\u00f6ri",
    "sg:orig_category":"D\u00e4mmung gegen K\u00e4lte, W\u00e4rme, Schall U Ersch\u00fctterung Herstellung von sonstigen Metallwaren",
    "sg:phone":"+41 18608800",
    "sg:postcode":"8181",
    "sg:province":"Z\u00fcrich",
    "wof:name":"Burgmann (schweiz) Ag",
    "wof:placetype":"venue"
},
  "geometry": {"coordinates":[8.518913269,47.512386322],"type":"Point"}
}