{
  "type": "Feature",
  "properties": {
    "iso:country":"CH",
    "sg:address":"Obergrundstrasse 44 6003 Luzern. Postfach",
    "sg:city":"Luzern",
    "sg:orig_category":"Versicherungen Generalagenturen",
    "sg:phone":"+41 41 249 88 88",
    "sg:postcode":"6002",
    "sg:province":"Luzern",
    "wof:name":"Alpina Versicherungen Generalagentur Innerschweiz",
    "wof:placetype":"venue"
},
  "geometry": {"coordinates":[8.3039417267,47.0462837219],"type":"Point"}
}