{
  "type": "Feature",
  "properties": {
    "addr:full":"Klosterstrasse 2 A Zug Zug 6300",
    "addr:housenumber":"2 a",
    "addr:postcode":"6300",
    "addr:street":"Klosterstrasse;Zug",
    "iso:country":"CH",
    "sg:address":"Klosterstrasse 2 A",
    "sg:city":"Zug",
    "sg:orig_category":"Bezirks, Sekundar, Realschulen, Oberstufe der Primarschulen Sprachschulen",
    "sg:phone":"+41 41 711 96 16",
    "sg:postcode":"6300",
    "sg:province":"Zug",
    "wof:name":"Institut Maria Opferung",
    "wof:placetype":"venue"
},
  "geometry": {"coordinates":[8.519945,47.163242],"type":"Point"}
}