{
  "type": "Feature",
  "properties": {
    "iso:country":"CH",
    "sg:address":"Jeandin Avenue Adrien- 8",
    "sg:city":"Th\u00f4nex",
    "sg:orig_category":"Sonstige mit der Informatik verbundene T\u00e4tigkeiten",
    "sg:phone":"+41 22 860 03 81",
    "sg:postcode":"1226",
    "sg:province":"Gen\u00e8ve",
    "wof:name":"Schmid, E D V Design & Consulting",
    "wof:placetype":"venue"
},
  "geometry": {"coordinates":[6.2012910843,46.1914405823],"type":"Point"}
}