{
  "type": "Feature",
  "properties": {
    "iso:country":"CH",
    "sg:address":"Immeuble Cr\u00eates-blanches",
    "sg:city":"Haute-nendaz",
    "sg:orig_category":"Autoelektro and -elektronik Werkst\u00e4tten Autogaragen",
    "sg:phone":"+41 21 903 12 45",
    "sg:postcode":"1997",
    "sg:province":"Valais",
    "wof:name":"Claude Jordan Garage",
    "wof:placetype":"venue"
},
  "geometry": {"coordinates":[6.770595,46.593719],"type":"Point"}
}