{
  "type": "Feature",
  "properties": {
    "iso:country":"CH",
    "sg:address":"Engadinerhof",
    "sg:city":"Pontresina",
    "sg:orig_category":"Detailhandel mit Textilien Fachdetailhandel in Verkaufsr\u00e4umen",
    "sg:phone":"+41 81 842 63 81",
    "sg:postcode":"7504",
    "sg:province":"Graubunden",
    "wof:name":"Sch\u00e4fli-schenk Frau E.",
    "wof:placetype":"venue"
},
  "geometry": {"coordinates":[9.9019098282,46.4935150146],"type":"Point"}
}