{
  "type": "Feature",
  "properties": {
    "iso:country":"CH",
    "sg:address":"Limmatstrasse 195",
    "sg:city":"Z\u00fcrich",
    "sg:orig_category":"Diskotheken, Dancings, Night Clubs",
    "sg:phone":"+41 12712270",
    "sg:postcode":"8005",
    "sg:province":"Z\u00fcrich",
    "wof:name":"Night Club City 5 Caramba",
    "wof:placetype":"venue"
},
  "geometry": {"coordinates":[8.5287132263,47.3865280151],"type":"Point"}
}