{
  "type": "Feature",
  "properties": {
    "iso:country":"CH",
    "sg:address":"Schorenstrasse 17",
    "sg:city":"Wallisellen",
    "sg:classifiers":[
        {
            "category":"Banks & Credit Unions",
            "subcategory":"Bank",
            "type":"Services"
        }
    ],
    "sg:phone":"+41 18307530",
    "sg:postcode":"8304",
    "sg:province":"Z\u00fcrich",
    "wof:name":"Schweiz. Mobiliar",
    "wof:placetype":"venue"
},
  "geometry": {"coordinates":[8.597312,47.423248],"type":"Point"}
}