{
  "type": "Feature",
  "properties": {
    "iso:country":"CH",
    "sg:address":"Br\u00fcnigstrasse 83 3860 Meiringen. Postfach 588",
    "sg:city":"Meiringen",
    "sg:orig_category":"Architektur U Ingenieurb\u00fcros",
    "sg:phone":"+41 33 971 22 33",
    "sg:postcode":"3860",
    "sg:province":"Bern",
    "wof:name":"M\u00e4tzener & Wyss, Bauingenieure Ag",
    "wof:placetype":"venue"
},
  "geometry": {"coordinates":[8.17662,46.731709],"type":"Point"}
}