{
  "type": "Feature",
  "properties": {
    "iso:country":"CH",
    "sg:address":"Freie Strasse 49",
    "sg:city":"Trimbach",
    "sg:classifiers":[
        {
            "category":"Wholesale",
            "subcategory":"Vending Machines",
            "type":"Manufacturing & Wholesale Goods"
        }
    ],
    "sg:phone":"+41 62 293 64 71",
    "sg:postcode":"4632",
    "sg:province":"Solothurn",
    "sg:tags":[
        "packaging",
        "used",
        "machines"
    ],
    "wof:name":"Sabia Verpackungsmaschinen-service",
    "wof:placetype":"venue"
},
  "geometry": {"coordinates":[7.9051351547,47.3578033447],"type":"Point"}
}