{
  "type": "Feature",
  "properties": {
    "iso:country":"CH",
    "sg:address":"Ried",
    "sg:city":"Schwarzenegg",
    "sg:orig_category":"G\u00fcterbef\u00f6rderung im Strassenverkehr",
    "sg:phone":"+41 33 453 16 79",
    "sg:postcode":"3616",
    "sg:province":"Bern",
    "wof:name":"Ren\u00e9 Kropf & Sohn Transporte",
    "wof:placetype":"venue"
},
  "geometry": {"coordinates":[7.7116689682,46.7950744629],"type":"Point"}
}