{
  "type": "Feature",
  "properties": {
    "iso:country":"CH",
    "sg:address":"Schoneggstrasse 5",
    "sg:city":"Spiez",
    "sg:orig_category":"Grosshandel mit B\u00fcromaschinen Grosshandel mit Datenverarbeitungsger\u00e4ten",
    "sg:phone":"+41 33 654 50 55",
    "sg:postcode":"3700",
    "sg:province":"Bern",
    "wof:name":"Kaformatik Ag Informations-& Kommunik'techn.",
    "wof:placetype":"venue"
},
  "geometry": {"coordinates":[7.6820611954,46.6870956421],"type":"Point"}
}