{
  "type": "Feature",
  "properties": {
    "iso:country":"CH",
    "sg:address":"Hangenmoos",
    "sg:city":"W\u00e4denswil",
    "sg:orig_category":"Handelsvermittlung U Grosshandel mit Automobilen Instandhaltung U Reparatur von Automobilen",
    "sg:phone":"+41 17800636",
    "sg:postcode":"8820",
    "sg:province":"Z\u00fcrich",
    "wof:name":"Us Car-connection Ag",
    "wof:placetype":"venue"
},
  "geometry": {"coordinates":[8.6536178589,47.2346496582],"type":"Point"}
}