{
  "type": "Feature",
  "properties": {
    "addr:full":"Dietlikonerstr. 17 Kloten Z\u00fcrich 8302",
    "addr:housenumber":"17",
    "addr:postcode":"8302",
    "addr:street":"Dietlikonerstr.",
    "iso:country":"CH",
    "sg:address":"Dietlikonerstr. 17",
    "sg:city":"Kloten",
    "sg:orig_category":"Allgemeiner Hoch U Tiefbau",
    "sg:phone":"+41 18133465",
    "sg:postcode":"8302",
    "sg:province":"Z\u00fcrich",
    "wof:name":"Figi & Keller",
    "wof:placetype":"venue"
},
  "geometry": {"coordinates":[8.585687,47.447742],"type":"Point"}
}