{
  "type": "Feature",
  "properties": {
    "iso:country":"CH",
    "sg:address":"Freienhofgasse 16 3600 Thun. Postfach 1302",
    "sg:city":"Thun",
    "sg:classifiers":[
        {
            "category":"Restaurant",
            "type":"Food & Drink"
        }
    ],
    "sg:phone":"+41 32 751 34 62",
    "sg:postcode":"3601",
    "sg:province":"Bern",
    "wof:name":"Restaurant-pizzeria Au Tonneau",
    "wof:placetype":"venue"
},
  "geometry": {"coordinates":[7.0920171738,47.0630302429],"type":"Point"}
}