{
  "type": "Feature",
  "properties": {
    "iso:country":"CH",
    "sg:address":"Br\u00fctterstrasse 6a",
    "sg:city":"Winkel",
    "sg:orig_category":"Vereine Frauen Vereine Gemeinn\u00fctzige",
    "sg:phone":"+41 18620000",
    "sg:postcode":"8185",
    "sg:province":"Z\u00fcrich",
    "wof:name":"Frauenverein Winkel-r\u00fcti-seeb",
    "wof:placetype":"venue"
},
  "geometry": {"coordinates":[8.5562820435,47.4940452576],"type":"Point"}
}