{
  "type": "Feature",
  "properties": {
    "iso:country":"CH",
    "sg:address":"1725",
    "sg:city":"Posieux",
    "sg:orig_category":"Vorschulen, Kinderg\u00e4rten",
    "sg:phone":"+41 26 477 30 09",
    "sg:postcode":"1725",
    "sg:province":"Fribourg",
    "wof:name":"Ecole Enfantine",
    "wof:placetype":"venue"
},
  "geometry": {"coordinates":[7.0673398972,46.76612854],"type":"Point"}
}