{
  "type": "Feature",
  "properties": {
    "iso:country":"CH",
    "sg:address":"Oberr\u00fctistrasse 45",
    "sg:city":"Hinterforst",
    "sg:orig_category":"Herstellung von Konstruktionsteilen, Fertigbauteilen U Ausbauelementen aus Holz Zimmerei, Ingenieurh",
    "sg:phone":"+41 71 755 44 06",
    "sg:postcode":"9452",
    "sg:province":"St. Gallen",
    "wof:name":"Ernst Walt Holzbau & Montagen",
    "wof:placetype":"venue"
},
  "geometry": {"coordinates":[9.5259237289,47.3559112549],"type":"Point"}
}