{
  "type": "Feature",
  "properties": {
    "iso:country":"CH",
    "sg:address":"Chemin De-maisonneuve 5",
    "sg:city":"Ch\u00e2telaine",
    "sg:orig_category":"Druck ohne Zeitungsdruck Offsetdruck",
    "sg:phone":"+41 21 635 14 82",
    "sg:postcode":"1219",
    "sg:province":"Gen\u00e8ve",
    "wof:name":"Imprimerie Des Arts Et M\u00e9tiers Sa",
    "wof:placetype":"venue"
},
  "geometry": {"coordinates":[6.5877242088,46.5439491272],"type":"Point"}
}