{
  "type": "Feature",
  "properties": {
    "addr:full":"Niesenweg 8 Bern Bern 3012",
    "addr:housenumber":"8",
    "addr:postcode":"3012",
    "addr:street":"Niesenweg;Bern",
    "iso:country":"CH",
    "sg:address":"Niesenweg 8",
    "sg:city":"Bern",
    "sg:orig_category":"Architektur U Ingenieurb\u00fcros",
    "sg:phone":"+41 31 305 15 80",
    "sg:postcode":"3012",
    "sg:province":"Bern",
    "wof:name":"Kiener Architekten Ag",
    "wof:placetype":"venue"
},
  "geometry": {"coordinates":[7.42891,46.949432],"type":"Point"}
}