{
  "type": "Feature",
  "properties": {
    "iso:country":"CH",
    "sg:address":"St\u00f6cklimattstrasse 13a 4513 Langendorf. Postfach",
    "sg:city":"Langendorf",
    "sg:classifiers":[
        {
            "category":"Restaurant",
            "type":"Food & Drink"
        }
    ],
    "sg:phone":"+41 32 623 88 51",
    "sg:postcode":"4513",
    "sg:province":"Solothurn",
    "wof:name":"Pub Weissenstein",
    "wof:placetype":"venue"
},
  "geometry": {"coordinates":[7.5153450966,47.2193107605],"type":"Point"}
}