{
  "type": "Feature",
  "properties": {
    "iso:country":"CH",
    "sg:address":"Bahnhofstrasse 57",
    "sg:city":"Aarau",
    "sg:classifiers":[
        {
            "category":"Restaurant",
            "type":"Food & Drink"
        }
    ],
    "sg:phone":"+41 62 824 04 04",
    "sg:postcode":"5000",
    "sg:province":"Aargau",
    "sg:tags":[
        "tea-rooms",
        "restaurants"
    ],
    "wof:name":"Thai House Oriental Gmbh",
    "wof:placetype":"venue"
},
  "geometry": {"coordinates":[8.0493707657,47.3917236328],"type":"Point"}
}