{
  "type": "Feature",
  "properties": {
    "addr:full":"Fabrikstrasse Cham Zug 6330",
    "addr:postcode":"6330",
    "addr:street":"Fabrikstrasse;Zug",
    "iso:country":"CH",
    "sg:address":"Fabrikstrasse",
    "sg:city":"Cham",
    "sg:orig_category":"Base Paper For Wallpaper",
    "sg:phone":"+41 41 785 18 88",
    "sg:postcode":"6330",
    "sg:province":"Zug",
    "wof:name":"Industrieholding Cham Ag",
    "wof:placetype":"venue"
},
  "geometry": {"coordinates":[8.45731,47.184299],"type":"Point"}
}