{
  "type": "Feature",
  "properties": {
    "iso:country":"CH",
    "sg:address":"Niesenweg 2",
    "sg:city":"Bern",
    "sg:orig_category":"Grosshandel mit B\u00fcromaschinen Grosshandel mit Datenverarbeitungsger\u00e4ten",
    "sg:phone":"+41 71 747 58 40",
    "sg:postcode":"3012",
    "sg:province":"Bern",
    "wof:name":"Elcode Ag",
    "wof:placetype":"venue"
},
  "geometry": {"coordinates":[9.6477251053,47.449432373],"type":"Point"}
}