{
  "type": "Feature",
  "properties": {
    "iso:country":"CH",
    "sg:address":"Sempacherstrasse 1",
    "sg:city":"Luzern",
    "sg:orig_category":"Armierungen Herstellung Herstellung von Kunststoffwaren",
    "sg:phone":"+41 41 210 40 30",
    "sg:postcode":"6003",
    "sg:province":"Luzern",
    "wof:name":"Stresshead Ag Spannsystem F\u00fcr Cfk-lamellen",
    "wof:placetype":"venue"
},
  "geometry": {"coordinates":[8.307179,47.049194],"type":"Point"}
}