{
  "type": "Feature",
  "properties": {
    "iso:country":"CH",
    "sg:address":"Poststrasse 1",
    "sg:city":"Ilanz",
    "sg:classifiers":[
        {
            "category":"Government",
            "subcategory":"Post Office",
            "type":"Public Place"
        }
    ],
    "sg:phone":"+41 81 925 18 20",
    "sg:postcode":"7130",
    "sg:province":"Graubunden",
    "sg:tags":[
        "caf\u00e9s",
        "tea-rooms"
    ],
    "wof:name":"Caf\u00e9 Odeon",
    "wof:placetype":"venue"
},
  "geometry": {"coordinates":[9.2068948746,46.7744827271],"type":"Point"}
}