{
  "type": "Feature",
  "properties": {
    "iso:country":"CH",
    "sg:address":"Zielmatte 2",
    "sg:city":"Stansstad",
    "sg:orig_category":"Detailhandel mit Waren verschiedener Art, Hauptrichtung Nahrungsmittel Grosshandel mit Nahrungsmitte",
    "sg:phone":"+41 41 610 59 69",
    "sg:postcode":"6362",
    "sg:province":"Nidwalden",
    "wof:name":"Odermatt Denner Satellit Gmbh Lebensmittel, Getr\u00e4nke; Handel, Bes. Denner Satellit In Stansstad",
    "wof:placetype":"venue"
},
  "geometry": {"coordinates":[8.3412494659,46.9774169922],"type":"Point"}
}