{
  "type": "Feature",
  "properties": {
    "iso:country":"CH",
    "sg:address":"Schartenstrasse 44",
    "sg:city":"Wettingen",
    "sg:orig_category":"Unclassifiable Establishments",
    "sg:postcode":"5430",
    "sg:province":"Aargau",
    "wof:name":"D + L Leuchtsysteme Gmbh",
    "wof:placetype":"venue"
},
  "geometry": {"coordinates":[8.3215942383,47.4701423645],"type":"Point"}
}