{
  "type": "Feature",
  "properties": {
    "iso:country":"CH",
    "sg:address":"Dufourstrasse 65 8702 Zollikon. Postfach 115",
    "sg:city":"Zollikon",
    "sg:orig_category":"Grosshandel mit Textilien",
    "sg:phone":"+41 71 222 24 07",
    "sg:postcode":"8702",
    "sg:province":"Z\u00fcrich",
    "wof:name":"Rocco Scasascia Textilien",
    "wof:placetype":"venue"
},
  "geometry": {"coordinates":[9.3788700104,47.4246025085],"type":"Point"}
}