{
  "type": "Feature",
  "properties": {
    "addr:full":"Alleeweg 1 Lotzwil Bern 4932",
    "addr:housenumber":"1",
    "addr:postcode":"4932",
    "addr:street":"Alleeweg",
    "iso:country":"CH",
    "sg:address":"Alleeweg 1",
    "sg:city":"Lotzwil",
    "sg:orig_category":"Architekturb\u00fcros",
    "sg:phone":"+41 62 922 38 05",
    "sg:postcode":"4932",
    "sg:province":"Bern",
    "wof:name":"Gerold Dietrich Architekturb\u00fcro",
    "wof:placetype":"venue"
},
  "geometry": {"coordinates":[7.79271,47.188202],"type":"Point"}
}