{
  "type": "Feature",
  "properties": {
    "iso:country":"CH",
    "sg:address":"Pfannenstilstrasse 37",
    "sg:city":"W\u00e4denswil",
    "sg:orig_category":"Unternehmensberatung",
    "sg:postcode":"8820",
    "sg:province":"Z\u00fcrich",
    "wof:name":"Meiho Consulting Meier-hottinger Max",
    "wof:placetype":"venue"
},
  "geometry": {"coordinates":[8.649274826,47.2348175049],"type":"Point"}
}