{
  "type": "Feature",
  "properties": {
    "iso:country":"CH",
    "sg:address":"Oberm\u00fchle 14",
    "sg:city":"Elgg",
    "sg:orig_category":"Kosmetikinstitute",
    "sg:phone":"+41 52 364 38 48",
    "sg:postcode":"8353",
    "sg:province":"Z\u00fcrich",
    "wof:name":"Brigitte Balbi Coiffure & Kosmetik",
    "wof:placetype":"venue"
},
  "geometry": {"coordinates":[8.8627128601,47.4911499023],"type":"Point"}
}