{
  "type": "Feature",
  "properties": {
    "iso:country":"CH",
    "sg:address":"Boulevard De P\u00e9rolles 5 1700 Freiburg. Postfach",
    "sg:city":"Fribourg",
    "sg:orig_category":"Sonstiger spezialisierter Hoch U Tiefbau",
    "sg:postcode":"1702",
    "sg:province":"Fribourg",
    "wof:name":"Brodard Gilbert Et Fils Sa, Succursale De Fribourg",
    "wof:placetype":"venue"
},
  "geometry": {"coordinates":[7.1515917778,46.8015441895],"type":"Point"}
}