{
  "type": "Feature",
  "properties": {
    "iso:country":"CH",
    "sg:address":"6043 Adligenswil. Postfach 371",
    "sg:city":"Adligenswil",
    "sg:orig_category":"Vermietung von Gebrauchsg\u00fctern Vermietung von Wasserfahrzeugen",
    "sg:postcode":"6043",
    "sg:province":"Luzern",
    "wof:name":"War-bootsvermietungs Ag",
    "wof:placetype":"venue"
},
  "geometry": {"coordinates":[8.3629655838,47.0713844299],"type":"Point"}
}