{
  "type": "Feature",
  "properties": {
    "iso:country":"CH",
    "sg:address":"Dorfweg 25",
    "sg:city":"Uster",
    "sg:orig_category":"Softwareentwicklung U beratung",
    "sg:phone":"+41 19943182",
    "sg:postcode":"8610",
    "sg:province":"Z\u00fcrich",
    "wof:name":"Lory Consulting",
    "wof:placetype":"venue"
},
  "geometry": {"coordinates":[8.7311687469,47.3440742493],"type":"Point"}
}