{
  "type": "Feature",
  "properties": {
    "iso:country":"CH",
    "sg:address":"4463",
    "sg:city":"Buus",
    "sg:orig_category":"Vereine Vogel-& Naturschutz",
    "sg:postcode":"4463",
    "sg:province":"Basel-Landschaft",
    "wof:name":"Vogelschutzverein",
    "wof:placetype":"venue"
},
  "geometry": {"coordinates":[7.8598370552,47.5081520081],"type":"Point"}
}