{
  "type": "Feature",
  "properties": {
    "iso:country":"CH",
    "sg:address":"Via Nizzola 2",
    "sg:city":"Lugano",
    "sg:orig_category":"Dienstleistungen von Beteiligungsgesellschaften Immobilienwesen",
    "sg:phone":"+41 91 913 44 05",
    "sg:postcode":"6900",
    "sg:province":"Ticino",
    "wof:name":"Resta Beteiligungen + Immobilien Ag",
    "wof:placetype":"venue"
},
  "geometry": {"coordinates":[8.9531526566,46.0057067871],"type":"Point"}
}