{
  "type": "Feature",
  "properties": {
    "addr:full":"Route Principale 51 Vicques Jura 2824",
    "addr:housenumber":"51",
    "addr:postcode":"2824",
    "addr:street":"Route Principale;Jura",
    "iso:country":"CH",
    "sg:address":"Route Principale 51",
    "sg:city":"Vicques",
    "sg:classifiers":[
        {
            "category":"Banks & Credit Unions",
            "subcategory":"Bank",
            "type":"Services"
        }
    ],
    "sg:phone":"+41 4166356433",
    "sg:postcode":"2824",
    "sg:province":"Jura",
    "wof:name":"Banque Raiffeisen",
    "wof:placetype":"venue"
},
  "geometry": {"coordinates":[7.416645,47.348988],"type":"Point"}
}