{
  "type": "Feature",
  "properties": {
    "iso:country":"CH",
    "sg:address":"Moosstrasse",
    "sg:city":"Einsiedeln",
    "sg:orig_category":"Zimmerei, Dachdeckerei, Bauspenglerei U Abdichtung",
    "sg:phone":"+41 55 412 37 67",
    "sg:postcode":"8840",
    "sg:province":"Schwyz",
    "wof:name":"K\u00e4lin Pius, Spenglerei",
    "wof:placetype":"venue"
},
  "geometry": {"coordinates":[8.7200784683,47.1013870239],"type":"Point"}
}