{
  "type": "Feature",
  "properties": {
    "iso:country":"CH",
    "sg:address":"H\u00e4rdlistrasse 6",
    "sg:city":"Spreitenbach",
    "sg:orig_category":"Handel mit Automobilen",
    "sg:postcode":"8957",
    "sg:province":"Aargau",
    "wof:name":"Auto Heggli",
    "wof:placetype":"venue"
},
  "geometry": {"coordinates":[8.3704357147,47.4317970276],"type":"Point"}
}