{
  "type": "Feature",
  "properties": {
    "iso:country":"CH",
    "sg:address":"Brunnenwiesenstrasse 31",
    "sg:city":"Dietlikon",
    "sg:orig_category":"Grosshandel mit keramischen Erzeugnissen,Glaswaren U Tapeten Herstellung von Radio U Fernsehger\u00e4ten ",
    "sg:phone":"+41 56 634 32 32",
    "sg:postcode":"8305",
    "sg:province":"Z\u00fcrich",
    "wof:name":"Voegelin K.l. Ag",
    "wof:placetype":"venue"
},
  "geometry": {"coordinates":[8.4385242462,47.3228569031],"type":"Point"}
}