{
  "type": "Feature",
  "properties": {
    "iso:country":"CH",
    "sg:address":"9473",
    "sg:city":"Gams",
    "sg:classifiers":[
        {
            "category":"Social Services",
            "subcategory":"Retirement Home",
            "type":"Services"
        }
    ],
    "sg:phone":"+41 17813386",
    "sg:postcode":"9473",
    "sg:province":"St. Gallen",
    "sg:tags":[
        "pflegeheime",
        "u",
        "alters"
    ],
    "wof:name":"Altersheim Au",
    "wof:placetype":"venue"
},
  "geometry": {"coordinates":[8.65261,47.244629],"type":"Point"}
}