{
  "type": "Feature",
  "properties": {
    "iso:country":"CH",
    "sg:address":"Mittskirchstrasse 27",
    "sg:city":"Zurzach",
    "sg:orig_category":"Sportvereine Velo Rad-& Motorfahrer-Bund SRB",
    "sg:postcode":"5330",
    "sg:province":"Aargau",
    "wof:name":"Srb-mtb-club Aarau",
    "wof:placetype":"venue"
},
  "geometry": {"coordinates":[8.0770435333,47.3848190308],"type":"Point"}
}