{
  "type": "Feature",
  "properties": {
    "iso:country":"CH",
    "sg:address":"Vanoni Via 2",
    "sg:city":"Lugano",
    "sg:orig_category":"Interessenvertretungen",
    "sg:postcode":"6900",
    "sg:province":"Ticino",
    "wof:name":"Fondazione Per I Bambini Del Sakha",
    "wof:placetype":"venue"
},
  "geometry": {"coordinates":[8.9542446136,46.0110206604],"type":"Point"}
}