{
  "type": "Feature",
  "properties": {
    "iso:country":"CH",
    "sg:address":"Hauptstrasse 87",
    "sg:city":"Degersheim",
    "sg:orig_category":"Instandhaltung U Reparatur von Automobilen",
    "sg:phone":"+41 71 371 17 17",
    "sg:postcode":"9113",
    "sg:province":"St. Gallen",
    "wof:name":"Zentrum-garage Kr\u00fcsi B.",
    "wof:placetype":"venue"
},
  "geometry": {"coordinates":[9.1956195831,47.3717498779],"type":"Point"}
}