{
  "type": "Feature",
  "properties": {
    "iso:country":"CH",
    "sg:address":"Neuengasse 17",
    "sg:city":"Bern",
    "sg:orig_category":"Unclassifiable Establishments",
    "sg:phone":"+41 31 312 02 71",
    "sg:postcode":"3011",
    "sg:province":"Bern",
    "wof:name":"Sphinx Erne H. & Co",
    "wof:placetype":"venue"
},
  "geometry": {"coordinates":[7.4425449371,46.9488754272],"type":"Point"}
}