{
  "type": "Feature",
  "properties": {
    "iso:country":"CH",
    "sg:address":"Feldstrasse 80 8180 B\u00fclach. Postfach",
    "sg:city":"B\u00fclach",
    "sg:orig_category":"Werbung",
    "sg:postcode":"8180",
    "sg:province":"Z\u00fcrich",
    "wof:name":"Marsella + Maraga Reklame Ag",
    "wof:placetype":"venue"
},
  "geometry": {"coordinates":[8.5388889313,47.5093765259],"type":"Point"}
}