{
  "type": "Feature",
  "properties": {
    "iso:country":"CH",
    "sg:address":"Museumstrasse 10",
    "sg:city":"Bern",
    "sg:classifiers":[
        {
            "category":"Manufacturing",
            "subcategory":"Jewelry",
            "type":"Manufacturing & Wholesale Goods"
        }
    ],
    "sg:phone":"+41 31 350 13 50",
    "sg:postcode":"3005",
    "sg:province":"Bern",
    "sg:tags":[
        "jewellery",
        "silver",
        "gold",
        "combined"
    ],
    "wof:name":"Montres Trevion Gmbh",
    "wof:placetype":"venue"
},
  "geometry": {"coordinates":[7.4507679939,46.9422225952],"type":"Point"}
}