{
  "type": "Feature",
  "properties": {
    "iso:country":"CH",
    "sg:address":"Rue De La Neuveville 68",
    "sg:city":"Fribourg",
    "sg:orig_category":"Detailhandel mit Waren verschiedener Art, Hauptrichtung Nahrungsmittel",
    "sg:phone":"+41 26 322 93 56",
    "sg:postcode":"1700",
    "sg:province":"Fribourg",
    "wof:name":"March\u00e9 Flag Chez Marie Magasin D'alimentation",
    "wof:placetype":"venue"
},
  "geometry": {"coordinates":[7.1614851952,46.8036575317],"type":"Point"}
}