{
  "type": "Feature",
  "properties": {
    "iso:country":"CH",
    "sg:address":"Rue Du Pr\u00e9-de-la-fontaine 15",
    "sg:city":"Satigny",
    "sg:orig_category":"Fotografisches Gewerbe U fotografische Laboratorien",
    "sg:postcode":"1242",
    "sg:province":"Gen\u00e8ve",
    "wof:name":"N. Welsh Photographe",
    "wof:placetype":"venue"
},
  "geometry": {"coordinates":[6.0531258583,46.2233467102],"type":"Point"}
}