{
  "type": "Feature",
  "properties": {
    "iso:country":"CH",
    "sg:address":"Steckbornerstrasse 14",
    "sg:city":"Pfyn",
    "sg:orig_category":"Verwaltung von Immobilien",
    "sg:phone":"+41 52 765 10 78",
    "sg:postcode":"8505",
    "sg:province":"Thurgau",
    "wof:name":"J\u00f6rg Kollbrunner Treuhandb\u00fcro",
    "wof:placetype":"venue"
},
  "geometry": {"coordinates":[8.9522342682,47.5962867737],"type":"Point"}
}