{
  "type": "Feature",
  "properties": {
    "iso:country":"CH",
    "sg:address":"Rue Du Lac 140",
    "sg:city":"Clarens",
    "sg:orig_category":"Detailhandel mit Teppichen Verlegen von Fussboden",
    "sg:phone":"+41 21 964 56 23",
    "sg:postcode":"1815",
    "sg:province":"Vaud",
    "wof:name":"Charles Jordan Rev\u00eatements De Sols",
    "wof:placetype":"venue"
},
  "geometry": {"coordinates":[6.8853969574,46.4427108765],"type":"Point"}
}