{
  "type": "Feature",
  "properties": {
    "iso:country":"CH",
    "sg:address":"Schaffhauserstrasse 89",
    "sg:city":"Kloten",
    "sg:orig_category":"Betrieb von Taxis",
    "sg:phone":"+41 18138878",
    "sg:postcode":"8302",
    "sg:province":"Z\u00fcrich",
    "wof:name":"Alpine Limousine Travel Gmbh",
    "wof:placetype":"venue"
},
  "geometry": {"coordinates":[8.580311,47.447376],"type":"Point"}
}