{
  "type": "Feature",
  "properties": {
    "iso:country":"CH",
    "sg:address":"Schulstrasse 39/40",
    "sg:city":"Z\u00fcrich",
    "sg:orig_category":"Detailhandel mit Damenbekleidung Grosshandel mit Textilien",
    "sg:phone":"+41 55 210 76 70",
    "sg:postcode":"8050",
    "sg:province":"Z\u00fcrich",
    "wof:name":"Boutique Altstadt Ag",
    "wof:placetype":"venue"
},
  "geometry": {"coordinates":[8.817858696,47.2274703979],"type":"Point"}
}