{
  "type": "Feature",
  "properties": {
    "iso:country":"CH",
    "sg:address":"Othmarsingerstrasse 3",
    "sg:city":"Lenzburg",
    "sg:orig_category":"Wirtschaftspr\u00fcfung, Steuerberatung U Treuhand",
    "sg:phone":"+41 62 891 70 72",
    "sg:postcode":"5600",
    "sg:province":"Aargau",
    "wof:name":"H\u00e4feli & Co, B\u00fcroservice",
    "wof:placetype":"venue"
},
  "geometry": {"coordinates":[8.1848058701,47.3904380798],"type":"Point"}
}