{
  "type": "Feature",
  "properties": {
    "iso:country":"CH",
    "sg:address":"Werner-k\u00e4linstrasse 11 8840 Einsiedeln. Postfach 261",
    "sg:city":"Einsiedeln",
    "sg:orig_category":"Offsetdruck Verlagsgewerbe",
    "sg:phone":"+41 55 418 43 43",
    "sg:postcode":"8840",
    "sg:province":"Schwyz",
    "wof:name":"K\u00fcrzi Ag",
    "wof:placetype":"venue"
},
  "geometry": {"coordinates":[8.746594429,47.1259460449],"type":"Point"}
}