{
  "type": "Feature",
  "properties": {
    "iso:country":"CH",
    "sg:address":"Les Faverges 1 2613 Villeret Case Postale 47",
    "sg:city":"Villeret",
    "sg:orig_category":"Herstellung U Zusammensetzung von Uhren Herstellung von Uhren",
    "sg:phone":"+41 32 942 98 00",
    "sg:postcode":"2613",
    "sg:province":"Bern",
    "wof:name":"Ctl Horlogerie Sa",
    "wof:placetype":"venue"
},
  "geometry": {"coordinates":[7.0138940811,47.1574935913],"type":"Point"}
}