{
  "type": "Feature",
  "properties": {
    "addr:full":"Parkstrasse 2 Steinhausen Zug 6312",
    "addr:housenumber":"2",
    "addr:postcode":"6312",
    "addr:street":"Parkstrasse;Zug",
    "iso:country":"CH",
    "sg:address":"Parkstrasse 2",
    "sg:city":"Steinhausen",
    "sg:orig_category":"Allgemeiner Hoch U Tiefbau Innenausbau",
    "sg:phone":"+41 41 741 71 81",
    "sg:postcode":"6312",
    "sg:province":"Zug",
    "wof:name":"Sw Spezialbau Ag",
    "wof:placetype":"venue"
},
  "geometry": {"coordinates":[8.484903,47.192379],"type":"Point"}
}