{
  "type": "Feature",
  "properties": {
    "iso:country":"CH",
    "sg:address":"Saumackerstrasse 58",
    "sg:city":"Z\u00fcrich",
    "sg:orig_category":"Wirtschaftspr\u00fcfung, Steuerberatung U Treuhand",
    "sg:postcode":"8048",
    "sg:province":"Z\u00fcrich",
    "wof:name":"Zehner Treuhand Z\u00dcrich Gmbh",
    "wof:placetype":"venue"
},
  "geometry": {"coordinates":[8.4878540039,47.3865356445],"type":"Point"}
}