{
  "type": "Feature",
  "properties": {
    "iso:country":"CH",
    "sg:address":"Alte Forchstrasse 42a",
    "sg:city":"Forch",
    "sg:orig_category":"Massagestudios",
    "sg:phone":"+41 19181215",
    "sg:postcode":"8127",
    "sg:province":"Z\u00fcrich",
    "wof:name":"Marianne Berger Meditative Massage",
    "wof:placetype":"venue"
},
  "geometry": {"coordinates":[8.6432943344,47.3252906799],"type":"Point"}
}