{
  "type": "Feature",
  "properties": {
    "iso:country":"CH",
    "sg:address":"Agasse Rue 45 1208 Gen\u00e8ve Case Postale 29",
    "sg:city":"Gen\u00e8ve",
    "sg:orig_category":"Herstellung von Uhren",
    "sg:phone":"+41 32 968 73 29",
    "sg:postcode":"1208",
    "sg:province":"Gen\u00e8ve",
    "wof:name":"B\u00f6gli Emile, D\u00e9cors-laque",
    "wof:placetype":"venue"
},
  "geometry": {"coordinates":[6.8340520859,47.1040534973],"type":"Point"}
}