{
  "type": "Feature",
  "properties": {
    "iso:country":"CH",
    "sg:address":"Rue De Vevey 23 1630 Bulle Case Postale 558",
    "sg:city":"Bulle",
    "sg:orig_category":"Eisengiesserei Herstellung von sonstigen Metallwaren",
    "sg:phone":"+41 26 912 61 58",
    "sg:postcode":"1630",
    "sg:province":"Fribourg",
    "wof:name":"Bulotimbres Ren\u00e9 Rime",
    "wof:placetype":"venue"
},
  "geometry": {"coordinates":[7.0549798012,46.6164398193],"type":"Point"}
}