{
  "type": "Feature",
  "properties": {
    "iso:country":"CH",
    "sg:address":"Scherlihalde 1",
    "sg:city":"Niederscherli",
    "sg:orig_category":"Sportvereine Turnen",
    "sg:phone":"+41 31 849 12 12",
    "sg:postcode":"3145",
    "sg:province":"Bern",
    "wof:name":"Turnverein Stv K\u00f6niz",
    "wof:placetype":"venue"
},
  "geometry": {"coordinates":[7.3933987617,46.8846740723],"type":"Point"}
}