{
  "type": "Feature",
  "properties": {
    "iso:country":"CH",
    "sg:address":"Schaffhauserstrasse 15",
    "sg:city":"Z\u00fcrich",
    "sg:orig_category":"Informatikdienste Softwareentwicklung U beratung",
    "sg:phone":"+41 13506242",
    "sg:postcode":"8006",
    "sg:province":"Z\u00fcrich",
    "wof:name":"Ierax Gmbh",
    "wof:placetype":"venue"
},
  "geometry": {"coordinates":[8.538939476,47.3890228271],"type":"Point"}
}