{
  "type": "Feature",
  "properties": {
    "iso:country":"CH",
    "sg:address":"Engiweg 3",
    "sg:city":"Zuchwil",
    "sg:orig_category":"Vereine Gesang",
    "sg:postcode":"4528",
    "sg:province":"Solothurn",
    "wof:name":"M\u00e4nnerchor Lommiswil",
    "wof:placetype":"venue"
},
  "geometry": {"coordinates":[7.5489501953,47.1969985962],"type":"Point"}
}