{
  "type": "Feature",
  "properties": {
    "iso:country":"CH",
    "sg:address":"1453",
    "sg:city":"Mauborget",
    "sg:orig_category":"RESTAURANTS: TEA-ROOMS",
    "sg:phone":"+41 24 436 13 82",
    "sg:postcode":"1453",
    "sg:province":"Vaud",
    "wof:name":"M\u00fcller Margaretha",
    "wof:placetype":"venue"
},
  "geometry": {"coordinates":[6.615003109,46.8557052612],"type":"Point"}
}