{
  "type": "Feature",
  "properties": {
    "iso:country":"CH",
    "sg:address":"Herrengasse 16",
    "sg:city":"Schwyz",
    "sg:orig_category":"Architektur U Ingenieurb\u00fcros Bauingenieurb\u00fcros Hochbau",
    "sg:phone":"+41 41 813 11 65",
    "sg:postcode":"6430",
    "sg:province":"Schwyz",
    "wof:name":"Hohnen & Hoppe, Hochbauingenieure",
    "wof:placetype":"venue"
},
  "geometry": {"coordinates":[8.65213,47.021885],"type":"Point"}
}