{
  "type": "Feature",
  "properties": {
    "iso:country":"CH",
    "sg:address":"Rue De Gen\u00e8ve 50",
    "sg:city":"Lausanne",
    "sg:orig_category":"Detailhandel mit Musikinstrumenten Detailhandel mit elektrischen Haushalts-,Radio U Fernsehger\u00e4ten s",
    "sg:phone":"+41 21 626 09 52",
    "sg:postcode":"1004",
    "sg:province":"Vaud",
    "wof:name":"Happysound",
    "wof:placetype":"venue"
},
  "geometry": {"coordinates":[6.6195821762,46.5237731934],"type":"Point"}
}