{
  "type": "Feature",
  "properties": {
    "iso:country":"CH",
    "sg:address":"Rue Des Eterpaz 43",
    "sg:city":"Vallorbe",
    "sg:orig_category":"Herstellung von Konstruktionsteilen, Fertigbauteilen U Ausbauelementen aus Holz",
    "sg:phone":"+41 21 843 34 54",
    "sg:postcode":"1337",
    "sg:province":"Vaud",
    "wof:name":"Interfen\u00eatre Gilbert Grandchamp",
    "wof:placetype":"venue"
},
  "geometry": {"coordinates":[6.3874120712,46.716129303],"type":"Point"}
}