{
  "type": "Feature",
  "properties": {
    "addr:full":"Daittet Gr\u00f4ne Valais 3979",
    "addr:postcode":"3979",
    "iso:country":"CH",
    "sg:address":"Daittet",
    "sg:city":"Gr\u00f4ne",
    "sg:orig_category":"Detailhandel mit Boden U Wandbel\u00e4gen ohne Teppiche Verlegen von Fussboden",
    "sg:phone":"+41 22 756 13 06",
    "sg:postcode":"3979",
    "sg:province":"Valais",
    "wof:name":"Michel & Brigitte Bonvin Rev\u00eatements De Sols",
    "wof:placetype":"venue"
},
  "geometry": {"coordinates":[5.99465,46.150669],"type":"Point"}
}