{
  "type": "Feature",
  "properties": {
    "iso:country":"CH",
    "sg:address":"Z\u00fcrcherstrasse 215",
    "sg:city":"Frauenfeld",
    "sg:orig_category":"Detailhandel Reparatur von Gebrauchsg\u00fctern Videotheken",
    "sg:phone":"+41 31 931 44 57",
    "sg:postcode":"8500",
    "sg:province":"Thurgau",
    "wof:name":"Videothek Beverly-hills",
    "wof:placetype":"venue"
},
  "geometry": {"coordinates":[7.4836120605,46.9562110901],"type":"Point"}
}