{
  "type": "Feature",
  "properties": {
    "iso:country":"CH",
    "sg:address":"Treyvaux",
    "sg:city":"Treyvaux",
    "sg:classifiers":[
        {
            "category":"Banks & Credit Unions",
            "subcategory":"Bank",
            "type":"Services"
        }
    ],
    "sg:phone":"+41 37332935",
    "sg:postcode":"1733",
    "sg:province":"Fribourg",
    "wof:name":"Banque Raiffeisen De Treyvaux",
    "wof:placetype":"venue"
},
  "geometry": {"coordinates":[7.136873,46.727631],"type":"Point"}
}