{
  "type": "Feature",
  "properties": {
    "iso:country":"CH",
    "sg:address":"Riedackerstrasse 2",
    "sg:city":"Pfungen",
    "sg:orig_category":"Detailhandel mit Fahrr\u00e4dern Handel mit Motorr\u00e4dern, Teilen U Zubeh\u00f6r Instandhaltung U Reparatur von ",
    "sg:phone":"+41 34 495 53 95",
    "sg:postcode":"8422",
    "sg:province":"Z\u00fcrich",
    "wof:name":"Rosa Bieri Velos-motos",
    "wof:placetype":"venue"
},
  "geometry": {"coordinates":[7.8937020302,46.9029426575],"type":"Point"}
}