{
  "type": "Feature",
  "properties": {
    "iso:country":"CH",
    "sg:address":"Furkastrasse",
    "sg:city":"Ulrichen",
    "sg:orig_category":"Bauingenieurb\u00fcros Hoch- and Tiefbau Ingenieurb\u00fcros Vermessung",
    "sg:phone":"+41 27 973 12 41",
    "sg:postcode":"3988",
    "sg:province":"Valais",
    "wof:name":"Walker-imoberdorf Ag Ingenieurb\u00fcro",
    "wof:placetype":"venue"
},
  "geometry": {"coordinates":[8.298046,46.505024],"type":"Point"}
}