{
  "type": "Feature",
  "properties": {
    "iso:country":"CH",
    "sg:address":"Batterieweg 6",
    "sg:city":"H\u00e4gendorf",
    "sg:classifiers":[
        {
            "category":"Wholesale",
            "subcategory":"Metals & Minerals",
            "type":"Manufacturing & Wholesale Goods"
        }
    ],
    "sg:phone":"+41 62 209 60 70",
    "sg:postcode":"4614",
    "sg:province":"Solothurn",
    "sg:tags":[
        "steel",
        "furnace",
        "plant",
        "non-ferrous",
        "annealing"
    ],
    "wof:name":"Nabertherm Schweiz Ag",
    "wof:placetype":"venue"
},
  "geometry": {"coordinates":[7.83176,47.335964],"type":"Point"}
}