{
  "type": "Feature",
  "properties": {
    "iso:country":"CH",
    "sg:address":"Chemin De Malacor",
    "sg:city":"Venth\u00f4ne",
    "sg:orig_category":"Grosshandel mit elektrischen Haushaltsger\u00e4ten Herstellung von elektrischen Haushaltsger\u00e4ten",
    "sg:phone":"+41 27 456 39 39",
    "sg:postcode":"3973",
    "sg:province":"Valais",
    "wof:name":"Sipa Gastro Sa",
    "wof:placetype":"venue"
},
  "geometry": {"coordinates":[7.5260219574,46.3074607849],"type":"Point"}
}