{
  "type": "Feature",
  "properties": {
    "iso:country":"CH",
    "sg:address":"Chemin Des Combes 68",
    "sg:city":"Fontenais",
    "sg:orig_category":"Schlossereien",
    "sg:phone":"+41 79 250 42 66",
    "sg:postcode":"2902",
    "sg:province":"Jura",
    "wof:name":"Francis Dubey Construction M\u00e9tallique",
    "wof:placetype":"venue"
},
  "geometry": {"coordinates":[7.0774569511,47.3981666565],"type":"Point"}
}