{
  "type": "Feature",
  "properties": {
    "iso:country":"CH",
    "sg:address":"Dubsstrasse 34",
    "sg:city":"Z\u00fcrich",
    "sg:orig_category":"Herstellung von sonstigen elektrischen Ausr\u00fcstungen",
    "sg:phone":"+41 52 763 19 36",
    "sg:postcode":"8003",
    "sg:province":"Z\u00fcrich",
    "wof:name":"Krenmayr Josef Ing",
    "wof:placetype":"venue"
},
  "geometry": {"coordinates":[9.0059299469,47.6034622192],"type":"Point"}
}