{
  "type": "Feature",
  "properties": {
    "iso:country":"CH",
    "sg:address":"Place De L'h\u00f4tel De Ville 8",
    "sg:city":"Echallens",
    "sg:orig_category":"Notariate",
    "sg:phone":"+41 26 912 20 02",
    "sg:postcode":"1040",
    "sg:province":"Vaud",
    "wof:name":"Pierre Rime Etude De Notaire",
    "wof:placetype":"venue"
},
  "geometry": {"coordinates":[7.0559711456,46.6167640686],"type":"Point"}
}