{
  "type": "Feature",
  "properties": {
    "iso:country":"CH",
    "sg:address":"R\u00f6telstrasse 28",
    "sg:city":"Z\u00fcrich",
    "sg:orig_category":"Herstellung von Radio U Fernsehger\u00e4ten sowie phono U videotechnischen Ger\u00e4ten",
    "sg:postcode":"8006",
    "sg:province":"Z\u00fcrich",
    "wof:name":"R/tv Burkhardt Ag",
    "wof:placetype":"venue"
},
  "geometry": {"coordinates":[8.5368919373,47.3910484314],"type":"Point"}
}