{
  "type": "Feature",
  "properties": {
    "iso:country":"CH",
    "sg:address":"Hauptstrasse 64/66 4450 Sissach. Postfach 211",
    "sg:city":"Sissach",
    "sg:orig_category":"Bauschreinerei Innenausbau",
    "sg:phone":"+41 61 971 39 21",
    "sg:postcode":"4450",
    "sg:province":"Basel-Landschaft",
    "wof:name":"G. & H. Grieder Ag",
    "wof:placetype":"venue"
},
  "geometry": {"coordinates":[7.811373,47.464363],"type":"Point"}
}