{
  "type": "Feature",
  "properties": {
    "iso:country":"CH",
    "sg:address":"J\u00f6riacherstrasse 5242 Birr. Postfach 232",
    "sg:city":"Birr",
    "sg:orig_category":"Herstellung von Metallkonstruktionen Mechanik",
    "sg:phone":"+41 56 450 05 50",
    "sg:postcode":"5242",
    "sg:province":"Aargau",
    "wof:name":"Schlosserei & Metallbau Martin Renold",
    "wof:placetype":"venue"
},
  "geometry": {"coordinates":[8.2165050507,47.4291915894],"type":"Point"}
}