{
  "type": "Feature",
  "properties": {
    "iso:country":"CH",
    "sg:address":"Wilimattweg 9",
    "sg:city":"Sissach",
    "sg:orig_category":"Bau U Wohngenossenschaften",
    "sg:phone":"+41 19504766",
    "sg:postcode":"4450",
    "sg:province":"Basel-Landschaft",
    "wof:name":"Baugen.pf\u00e4ffikon Zh Gbp",
    "wof:placetype":"venue"
},
  "geometry": {"coordinates":[8.781544,47.367447],"type":"Point"}
}