{
  "type": "Feature",
  "properties": {
    "iso:country":"CH",
    "sg:address":"Ahornweg 1",
    "sg:city":"Killwangen",
    "sg:orig_category":"Unclassifiable Establishments",
    "sg:postcode":"8956",
    "sg:province":"Aargau",
    "wof:name":"Euro Plaza Day-trading Gmbh",
    "wof:placetype":"venue"
},
  "geometry": {"coordinates":[8.3501243591,47.4327774048],"type":"Point"}
}