{
  "type": "Feature",
  "properties": {
    "iso:country":"CH",
    "sg:address":"Eymatt",
    "sg:city":"Seftigen",
    "sg:orig_category":"Sonstiger spezialisierter Hoch U Tiefbau",
    "sg:postcode":"3662",
    "sg:province":"Bern",
    "wof:name":"Rohrbach Pfl\u00e4sterungen Gmbh",
    "wof:placetype":"venue"
},
  "geometry": {"coordinates":[7.5298070908,46.7882919312],"type":"Point"}
}