{
  "type": "Feature",
  "properties": {
    "iso:country":"CH",
    "sg:address":"Hafenstrasse 32",
    "sg:city":"Romanshorn",
    "sg:classifiers":[
        {
            "category":"Restaurant",
            "type":"Food & Drink"
        }
    ],
    "sg:phone":"+41 71 463 10 31",
    "sg:postcode":"8590",
    "sg:province":"Thurgau",
    "wof:name":"Restaurant Sch\u00e4fli B.bahnhof",
    "wof:placetype":"venue"
},
  "geometry": {"coordinates":[9.3787145615,47.5678024292],"type":"Point"}
}