{
  "type": "Feature",
  "properties": {
    "iso:country":"CH",
    "sg:address":"Alte Rudolfingerstr. 649. 8460 Marthalen. Postfach",
    "sg:city":"Dachsen",
    "sg:orig_category":"Fleischverarbeitung",
    "sg:postcode":"8447",
    "sg:province":"Z\u00fcrich",
    "wof:name":"Rubli, Marthalen",
    "wof:placetype":"venue"
},
  "geometry": {"coordinates":[8.6494474411,47.6258430481],"type":"Point"}
}