{
  "type": "Feature",
  "properties": {
    "iso:country":"CH",
    "sg:address":"Meylan Rue P\u00e9dro- 1 1208 Gen\u00e8ve. Postfach",
    "sg:city":"Gen\u00e8ve",
    "sg:orig_category":"Interessenvertretungen",
    "sg:postcode":"1201",
    "sg:province":"Gen\u00e8ve",
    "wof:name":"Fondation Berma",
    "wof:placetype":"venue"
},
  "geometry": {"coordinates":[6.1635107994,46.1954917908],"type":"Point"}
}