{
  "type": "Feature",
  "properties": {
    "iso:country":"CH",
    "sg:address":"Unterwilrain 42",
    "sg:city":"Littau",
    "sg:orig_category":"Erschliessung von Grundst\u00fccken",
    "sg:postcode":"6014",
    "sg:province":"Luzern",
    "wof:name":"Wohnbaugenossenschaft Stadt B\u00e4ren",
    "wof:placetype":"venue"
},
  "geometry": {"coordinates":[9.3920269012,47.4400558472],"type":"Point"}
}