{
  "type": "Feature",
  "properties": {
    "iso:country":"CH",
    "sg:address":"Dufourstrasse 30",
    "sg:city":"Zollikon",
    "sg:orig_category":"K\u00fcnstlerische U schriftstellerische T\u00e4tigkeiten U Darbietungen",
    "sg:phone":"+41 13918484",
    "sg:postcode":"8702",
    "sg:province":"Z\u00fcrich",
    "wof:name":"Zora, Bosch-gwalter Dr. Hans Rudolf",
    "wof:placetype":"venue"
},
  "geometry": {"coordinates":[8.568523407,47.3437728882],"type":"Point"}
}