{
  "type": "Feature",
  "properties": {
    "iso:country":"CH",
    "sg:address":"Kellerstrasse 25",
    "sg:city":"Luzern",
    "sg:orig_category":"Fahrschulen, Flugschulen",
    "sg:phone":"+41 41 360 21 66",
    "sg:postcode":"6005",
    "sg:province":"Luzern",
    "wof:name":"Luciano & Irene Piacentini Fahrschule",
    "wof:placetype":"venue"
},
  "geometry": {"coordinates":[8.3123979568,47.042350769],"type":"Point"}
}