{
  "type": "Feature",
  "properties": {
    "iso:country":"CH",
    "sg:address":"Dorfstrasse 59",
    "sg:city":"Zumikon",
    "sg:orig_category":"Erschliessung von Grundst\u00fccken",
    "sg:postcode":"8126",
    "sg:province":"Z\u00fcrich",
    "wof:name":"Baugenossenschaft Gewerbe Zumikon Bgz",
    "wof:placetype":"venue"
},
  "geometry": {"coordinates":[8.6248426437,47.3312492371],"type":"Point"}
}