{
  "type": "Feature",
  "properties": {
    "iso:country":"CH",
    "sg:address":"Rebbergstrasse 26",
    "sg:city":"Thayngen",
    "sg:orig_category":"Grosshandel mit B\u00fcromaschinen Grosshandel mit Datenverarbeitungsger\u00e4ten",
    "sg:phone":"+41 52 649 26 51",
    "sg:postcode":"8240",
    "sg:province":"Schaffhausen",
    "wof:name":"Cut-computing Ag",
    "wof:placetype":"venue"
},
  "geometry": {"coordinates":[8.7165460587,47.7480659485],"type":"Point"}
}