{
  "type": "Feature",
  "properties": {
    "iso:country":"CH",
    "sg:address":"Curtille Chemin De 5 1071 Chexbres. Postfach",
    "sg:city":"Chexbres",
    "sg:orig_category":"Unternehmensberatung",
    "sg:phone":"+41 32 721 35 21",
    "sg:postcode":"1071",
    "sg:province":"Vaud",
    "wof:name":"Jawer (neuch\u00e2tel) S.a",
    "wof:placetype":"venue"
},
  "geometry": {"coordinates":[6.633687973,46.9273986816],"type":"Point"}
}