{
  "type": "Feature",
  "properties": {
    "iso:country":"CH",
    "sg:address":"Schiben 470",
    "sg:city":"Untereggen",
    "sg:orig_category":"Malerei Tapeziererei",
    "sg:phone":"+41 79 431 87 91",
    "sg:postcode":"9033",
    "sg:province":"St. Gallen",
    "wof:name":"Walter M\u00f6ckli Maler-& Tapezierergesch\u00e4ft",
    "wof:placetype":"venue"
},
  "geometry": {"coordinates":[9.4358892441,47.4462432861],"type":"Point"}
}