{
  "type": "Feature",
  "properties": {
    "iso:country":"CH",
    "sg:address":"Via Torazza",
    "sg:city":"Caslano",
    "sg:classifiers":[
        {
            "category":"Government",
            "subcategory":"Post Office",
            "type":"Public Place"
        }
    ],
    "sg:phone":"+41 91 606 41 80",
    "sg:postcode":"6987",
    "sg:province":"Ticino",
    "sg:tags":[
        "caf\u00e9s",
        "tea-rooms"
    ],
    "wof:name":"Tea-room Laura",
    "wof:placetype":"venue"
},
  "geometry": {"coordinates":[8.8773889542,45.9592666626],"type":"Point"}
}