{
  "type": "Feature",
  "properties": {
    "iso:country":"CH",
    "sg:address":"Klingenberg",
    "sg:city":"Homburg",
    "sg:orig_category":"Ger\u00fcstbau Oberfl\u00e4chenveredlung U W\u00e4rmebehandlung",
    "sg:phone":"+41 52 763 35 58",
    "sg:postcode":"8508",
    "sg:province":"Thurgau",
    "wof:name":"Kurt Pleithner Malerei & Ger\u00fcstbau",
    "wof:placetype":"venue"
},
  "geometry": {"coordinates":[9.0027303696,47.6224594116],"type":"Point"}
}