{
  "type": "Feature",
  "properties": {
    "iso:country":"CH",
    "sg:address":"Aspweg 12",
    "sg:city":"Gelterkinden",
    "sg:classifiers":[
        {
            "category":"Professional",
            "subcategory":"Computer Services",
            "type":"Services"
        }
    ],
    "sg:postcode":"4460",
    "sg:tags":[
        "joomla",
        "virtual-hosts"
    ],
    "sg:website":"http://www.virtualpower.ch",
    "wof:name":"Hasware",
    "wof:placetype":"venue"
},
  "geometry": {"coordinates":[7.8507039,47.4728863],"type":"Point"}
}