{
  "type": "Feature",
  "properties": {
    "iso:country":"CH",
    "sg:address":"Jeizinen 3945 Gampel. Postfach",
    "sg:city":"Gampel",
    "sg:orig_category":"Detailhandel mit Waren verschiedener Art, Hauptrichtung Nahrungsmittel Grosshandel mit Nahrungsmitte",
    "sg:phone":"+41 27 932 15 83",
    "sg:postcode":"3945",
    "sg:province":"Valais",
    "wof:name":"Nelly Hildbrand Handlung",
    "wof:placetype":"venue"
},
  "geometry": {"coordinates":[7.7216157913,46.3285102844],"type":"Point"}
}