{
  "type": "Feature",
  "properties": {
    "iso:country":"CH",
    "sg:address":"Chatzet\u00f6beli 1",
    "sg:city":"Adetswil",
    "sg:orig_category":"Detailhandel mit Blumen U Pflanzen",
    "sg:phone":"+41 19392568",
    "sg:postcode":"8345",
    "sg:province":"Z\u00fcrich",
    "wof:name":"Ruth R\u00e4ss Blumenatelier",
    "wof:placetype":"venue"
},
  "geometry": {"coordinates":[8.840817,47.340752],"type":"Point"}
}