{
  "type": "Feature",
  "properties": {
    "iso:country":"CH",
    "sg:address":"Hammerstrasse 71",
    "sg:city":"Basel",
    "sg:orig_category":"Detailhandel mit Waren verschiedener Art, Hauptrichtung Nahrungsmittel Reiseb\u00fcros",
    "sg:phone":"+41 61 691 11 35",
    "sg:postcode":"4057",
    "sg:province":"Basel-Stadt",
    "wof:name":"Fikriye Sahin Sahin Bazar",
    "wof:placetype":"venue"
},
  "geometry": {"coordinates":[7.596186161,47.5631752014],"type":"Point"}
}