{
  "type": "Feature",
  "properties": {
    "iso:country":"CH",
    "sg:address":"Hofackerstrasse 79",
    "sg:city":"Muttenz",
    "sg:orig_category":"Fresh Vegetables, Lettuces, And Potatoes",
    "sg:phone":"+41 61 461 28 55",
    "sg:postcode":"4132",
    "sg:province":"Basel-Landschaft",
    "wof:name":"Fritz M\u00fcller-hartmann Ag",
    "wof:placetype":"venue"
},
  "geometry": {"coordinates":[7.6361918449,47.5367202759],"type":"Point"}
}