{
  "type": "Feature",
  "properties": {
    "iso:country":"CH",
    "sg:address":"Schor\u00fctistrasse 546",
    "sg:city":"Uerkheim",
    "sg:orig_category":"Softwareentwicklung U beratung",
    "sg:phone":"+41 62 721 39 22",
    "sg:postcode":"4813",
    "sg:province":"Aargau",
    "wof:name":"Franzi Ag Software-entwicklung & Treuhand",
    "wof:placetype":"venue"
},
  "geometry": {"coordinates":[8.0245800018,47.308177948],"type":"Point"}
}