{
  "type": "Feature",
  "properties": {
    "iso:country":"CH",
    "sg:address":"Vinet Avenue 7 1004 Lausanne. Postfach",
    "sg:city":"Lausanne",
    "sg:classifiers":[
        {
            "category":"Professional",
            "subcategory":"Employment Agencies",
            "type":"Services"
        }
    ],
    "sg:phone":"+41 21 312 09 11",
    "sg:postcode":"1003",
    "sg:province":"Vaud",
    "sg:tags":[
        "personal",
        "u",
        "stellenvermittlung"
    ],
    "wof:name":"Chic Models Agency Barro Jos\u00e9 Ecole Et Agence De Mannequins",
    "wof:placetype":"venue"
},
  "geometry": {"coordinates":[6.6302142143,46.5250358582],"type":"Point"}
}