{
  "type": "Feature",
  "properties": {
    "iso:country":"CH",
    "sg:address":"Poststrasse 2 4410 Liestal. Postfach",
    "sg:city":"Liestal",
    "sg:orig_category":"Konditoreien RESTAURANTS: TEA-ROOMS",
    "sg:phone":"+41 61 922 02 53",
    "sg:postcode":"4410",
    "sg:province":"Basel-Landschaft",
    "wof:name":"Pasticceria L'angolo Dolce, Napoli Grazia Caf\u00e9 Mit Konditorei",
    "wof:placetype":"venue"
},
  "geometry": {"coordinates":[7.7321739197,47.4841003418],"type":"Point"}
}