{
  "type": "Feature",
  "properties": {
    "iso:country":"CH",
    "sg:address":"Vogesenstrasse 47 4056 Basel. Postfach",
    "sg:city":"Basel",
    "sg:orig_category":"Finanzierungsinstitutionen",
    "sg:phone":"+41 61 321 63 32",
    "sg:postcode":"4051",
    "sg:province":"Basel-Stadt",
    "wof:name":"Frei Basil Finanz Finanzgesch\u00e4fte Usw",
    "wof:placetype":"venue"
},
  "geometry": {"coordinates":[7.5773720741,47.5663032532],"type":"Point"}
}