{
  "type": "Feature",
  "properties": {
    "iso:country":"CH",
    "sg:address":"Savoie Avenue Pierre De 48 1400 Yverdon-les-bains. Postfach",
    "sg:city":"Cheseaux-nor\u00e9az",
    "sg:orig_category":"Interessenvertretungen",
    "sg:phone":"+41 24 426 08 09",
    "sg:postcode":"1400",
    "sg:province":"Vaud",
    "wof:name":"Tzaud Alain S\u00e0rl Diriger L'organisation R\u00e9gionale De La Protection Civile, Dans Le Mesures Prescrites Par La Conf\u00e9d\u00e9ration Etc",
    "wof:placetype":"venue"
},
  "geometry": {"coordinates":[6.6395058632,46.7682113647],"type":"Point"}
}