{
  "type": "Feature",
  "properties": {
    "iso:country":"CH",
    "sg:address":"Elfenaustrasse 16 2500 Biel/bienne. Postfach",
    "sg:city":"Biel/bienne",
    "sg:orig_category":"Erwachsenenbildung U Unterricht",
    "sg:phone":"+41 32 322 17 06",
    "sg:postcode":"2502",
    "sg:province":"Bern",
    "wof:name":"Hudritsch Josef Qualit\u00e4ts Management",
    "wof:placetype":"venue"
},
  "geometry": {"coordinates":[7.2403011322,47.135925293],"type":"Point"}
}