{
  "type": "Feature",
  "properties": {
    "iso:country":"CH",
    "sg:address":"Dorf 34a",
    "sg:city":"Etzelkofen",
    "sg:orig_category":"Schreib U \u00dcbersetzungsb\u00fcros",
    "sg:phone":"+41 79 651 50 73",
    "sg:postcode":"3306",
    "sg:province":"Bern",
    "wof:name":"B\u00fcro-service Frau H. Ruch.",
    "wof:placetype":"venue"
},
  "geometry": {"coordinates":[7.4788899422,47.0839233398],"type":"Point"}
}