{
  "type": "Feature",
  "properties": {
    "addr:full":"Sandacker 2 Z\u00fcrich Z\u00fcrich 8052",
    "addr:housenumber":"2",
    "addr:postcode":"8052",
    "addr:street":"Sandacker",
    "iso:country":"CH",
    "sg:address":"Sandacker 2",
    "sg:city":"Z\u00fcrich",
    "sg:orig_category":"Chemische Reinigung",
    "sg:phone":"+41 13013810",
    "sg:postcode":"8052",
    "sg:province":"Z\u00fcrich",
    "wof:name":"Fm Textilreinigung Topservice Gmbh",
    "wof:placetype":"venue"
},
  "geometry": {"coordinates":[8.551641,47.422852],"type":"Point"}
}