{
  "type": "Feature",
  "properties": {
    "iso:country":"CH",
    "sg:address":"D\u00e4ttlikonerstrasse 5 8422 Pfungen. Postfach",
    "sg:city":"Pfungen",
    "sg:orig_category":"G\u00fcterbef\u00f6rderung im Strassenverkehr Sonstige Verkehrsvermittlung",
    "sg:phone":"+41 52 305 04 04",
    "sg:postcode":"8422",
    "sg:province":"Z\u00fcrich",
    "wof:name":"Bps Speditions-service Ag",
    "wof:placetype":"venue"
},
  "geometry": {"coordinates":[8.6380357742,47.5181159973],"type":"Point"}
}