{
  "type": "Feature",
  "properties": {
    "iso:country":"CH",
    "sg:address":"Rue De La Serre 5 2000 Neuenburg. Postfach",
    "sg:city":"Neuenburg",
    "sg:orig_category":"Architektur U Ingenieurb\u00fcros",
    "sg:phone":"+41 32 731 17 37",
    "sg:postcode":"2000",
    "sg:province":"Neuch\u00e2tel",
    "wof:name":"Bureau D'\u00e9tudes, Schneider Olivier",
    "wof:placetype":"venue"
},
  "geometry": {"coordinates":[6.875952,46.985275],"type":"Point"}
}