{
  "type": "Feature",
  "properties": {
    "addr:full":"Seefeldstrasse 55 Z\u00fcrich Z\u00fcrich 8008",
    "addr:housenumber":"55",
    "addr:postcode":"8008",
    "addr:street":"Seefeldstrasse",
    "iso:country":"CH",
    "sg:address":"Seefeldstrasse 55",
    "sg:city":"Z\u00fcrich",
    "sg:orig_category":"Arztpraxen",
    "sg:phone":"+41 71 912 12 33",
    "sg:postcode":"8008",
    "sg:province":"Z\u00fcrich",
    "wof:name":"Dr.med.eugen H\u00e4lg Arzt F\u00fcr Allgemeine Medizin",
    "wof:placetype":"venue"
},
  "geometry": {"coordinates":[9.047717,47.46109],"type":"Point"}
}