{
  "type": "Feature",
  "properties": {
    "iso:country":"CH",
    "sg:address":"Avenue De France 15",
    "sg:city":"Sion",
    "sg:orig_category":"RESTAURANTS: TEA-ROOMS",
    "sg:phone":"+41 17861846",
    "sg:postcode":"1950",
    "sg:province":"Valais",
    "wof:name":"Armin B\u00fceler-weber",
    "wof:placetype":"venue"
},
  "geometry": {"coordinates":[8.7245254517,47.2009925842],"type":"Point"}
}