{
  "type": "Feature",
  "properties": {
    "iso:country":"CH",
    "sg:address":"De-candolle Rue 20 1205 Gen\u00e8ve. Postfach",
    "sg:city":"Gen\u00e8ve",
    "sg:orig_category":"Interessenvertretungen",
    "sg:phone":"+41 22 807 18 88",
    "sg:postcode":"1205",
    "sg:province":"Gen\u00e8ve",
    "wof:name":"Fondation De Prevoyance En Faveur Du Personnel De L'etude Oberson",
    "wof:placetype":"venue"
},
  "geometry": {"coordinates":[6.145154953,46.197845459],"type":"Point"}
}