{
  "type": "Feature",
  "properties": {
    "iso:country":"CH",
    "sg:address":"Massholderenstrasse 7 8143 Stallikon. Postfach",
    "sg:city":"Stallikon",
    "sg:orig_category":"Unternehmensberatung",
    "sg:postcode":"8143",
    "sg:province":"Z\u00fcrich",
    "wof:name":"Comm-flow Ouwerkerk Dr. Pharmaconsulting & Marketing Management Und Marketingconsulting F\u00fcr Die Pharmazeutische Industrie",
    "wof:placetype":"venue"
},
  "geometry": {"coordinates":[8.4886312485,47.3390693665],"type":"Point"}
}