{
  "type": "Feature",
  "properties": {
    "iso:country":"CH",
    "sg:address":"Asylstrasse 16",
    "sg:city":"Aarau",
    "sg:orig_category":"Detailhandel mit Uhren U Schmuck",
    "sg:phone":"+41 62 212 36 16",
    "sg:postcode":"5000",
    "sg:province":"Aargau",
    "wof:name":"Seppo M\u00e4kel\u00e4inen Goldschmied-atelier",
    "wof:placetype":"venue"
},
  "geometry": {"coordinates":[7.8706421852,47.3428497314],"type":"Point"}
}