{
  "type": "Feature",
  "properties": {
    "iso:country":"CH",
    "sg:address":"Im Heumoos 23",
    "sg:city":"Bonstetten",
    "sg:classifiers":[
        {
            "category":"Restaurant",
            "type":"Food & Drink"
        }
    ],
    "sg:phone":"+41 17002121",
    "sg:postcode":"8906",
    "sg:province":"Z\u00fcrich",
    "wof:name":"Kafi Heumoos",
    "wof:placetype":"venue"
},
  "geometry": {"coordinates":[8.4691114426,47.3250999451],"type":"Point"}
}