{
  "type": "Feature",
  "properties": {
    "iso:country":"CH",
    "sg:address":"Hintergasse 1",
    "sg:city":"M\u00fcnsingen",
    "sg:orig_category":"Detailhandel mit Waren verschiedener Art, Hauptrichtung Nahrungsmittel Fachdetailhandel mit Nahrungs",
    "sg:phone":"+41 31 721 95 94",
    "sg:postcode":"3110",
    "sg:province":"Bern",
    "wof:name":"Boccalino Beatrice Stettler",
    "wof:placetype":"venue"
},
  "geometry": {"coordinates":[7.5635461807,46.8749389648],"type":"Point"}
}