{
  "type": "Feature",
  "properties": {
    "iso:country":"CH",
    "sg:address":"Via Gionda 2",
    "sg:city":"Sedrun",
    "sg:orig_category":"Detailhandel mit Zeitungen U Zeitschriften Kioske",
    "sg:phone":"+41 81 949 12 35",
    "sg:postcode":"7188",
    "sg:province":"Graubunden",
    "wof:name":"Giusep Schmid Kiosk",
    "wof:placetype":"venue"
},
  "geometry": {"coordinates":[8.7733888626,46.6797103882],"type":"Point"}
}