{
  "type": "Feature",
  "properties": {
    "iso:country":"CH",
    "sg:address":"Schwertstrasse 9",
    "sg:city":"Schaffhausen",
    "sg:orig_category":"Unclassifiable Establishments",
    "sg:postcode":"8200",
    "sg:province":"Schaffhausen",
    "wof:name":"Tyco International Holding Ag",
    "wof:placetype":"venue"
},
  "geometry": {"coordinates":[8.6325616837,47.6972923279],"type":"Point"}
}