{
  "type": "Feature",
  "properties": {
    "iso:country":"CH",
    "sg:address":"Rue Du Vieux-coll\u00e8ge 10 1200 Genf. Postfach",
    "sg:city":"Gen\u00e8ve",
    "sg:orig_category":"Unclassifiable Establishments",
    "sg:postcode":"1204",
    "sg:province":"Gen\u00e8ve",
    "wof:name":"Monbleu Sa",
    "wof:placetype":"venue"
},
  "geometry": {"coordinates":[6.1512579918,46.2014350891],"type":"Point"}
}