{
  "type": "Feature",
  "properties": {
    "iso:country":"CH",
    "sg:address":"Riedstrasse 1",
    "sg:city":"Rotkreuz",
    "sg:classifiers":[
        {
            "category":"Building & Trades",
            "subcategory":"Electrical",
            "type":"Services"
        }
    ],
    "sg:phone":"+41 41 799 07 99",
    "sg:postcode":"6343",
    "sg:province":"Zug",
    "sg:tags":[
        "engineering",
        "construction",
        "architectural",
        "software"
    ],
    "wof:name":"Wibeag Informatik Ag",
    "wof:placetype":"venue"
},
  "geometry": {"coordinates":[8.42877,47.147362],"type":"Point"}
}