{
  "type": "Feature",
  "properties": {
    "iso:country":"CH",
    "sg:address":"F\u00f6rrlibuckstr. 178",
    "sg:city":"Z\u00fcrich",
    "sg:classifiers":[
        {
            "category":"Food Court",
            "type":"Food & Drink"
        }
    ],
    "sg:phone":"+41 4112727122",
    "sg:postcode":"8005",
    "sg:province":"Z\u00fcrich",
    "sg:tags":[
        "product",
        "related"
    ],
    "wof:name":"Bier-import Ag",
    "wof:placetype":"venue"
},
  "geometry": {"coordinates":[8.5108366013,47.3922920227],"type":"Point"}
}