{
  "type": "Feature",
  "properties": {
    "iso:country":"CH",
    "sg:address":"Steinhofrain 18",
    "sg:city":"Luzern",
    "sg:orig_category":"Fussreflexzonenmassage Naturheil\u00e4rzte and Heilpraktiker",
    "sg:postcode":"6005",
    "sg:province":"Luzern",
    "wof:name":"Christine Brudermann Gesundheitspraxis Dynamis",
    "wof:placetype":"venue"
},
  "geometry": {"coordinates":[8.2952299118,47.0416908264],"type":"Point"}
}