{
  "type": "Feature",
  "properties": {
    "addr:full":"Rue Ch.-bovy-lysberg 2 Gen\u00e8ve Gen\u00e8ve 1204",
    "addr:housenumber":"2",
    "addr:postcode":"1204",
    "addr:street":"Rue Ch.-Bovy-Lysberg",
    "iso:country":"CH",
    "sg:address":"Rue Ch.-bovy-lysberg 2",
    "sg:city":"Gen\u00e8ve",
    "sg:orig_category":"Architektur U Ingenieurb\u00fcros Architekturb\u00fcros",
    "sg:phone":"+41 22 328 05 35",
    "sg:postcode":"1204",
    "sg:province":"Gen\u00e8ve",
    "wof:name":"Atelier D'architectes Grivel Et Cie Sa",
    "wof:placetype":"venue"
},
  "geometry": {"coordinates":[6.140966,46.201443],"type":"Point"}
}