{
  "type": "Feature",
  "properties": {
    "iso:country":"CH",
    "sg:address":"R\u00fcchligstrasse 1",
    "sg:city":"Ottenbach",
    "sg:orig_category":"Detailhandel mit elektrischen Haushalts, Radio U Fernsehger\u00e4ten ohne ausgepr\u00e4gten Schwerpunkt",
    "sg:phone":"+41 62 771 25 75",
    "sg:postcode":"8913",
    "sg:province":"Z\u00fcrich",
    "wof:name":"Otto Steiner Ag Elektrofachgesch\u00e4ft",
    "wof:placetype":"venue"
},
  "geometry": {"coordinates":[8.1826505661,47.2566261292],"type":"Point"}
}