{
  "type": "Feature",
  "properties": {
    "iso:country":"CH",
    "sg:address":"Ifangweg 11",
    "sg:city":"Uster",
    "sg:orig_category":"Gartenbau",
    "sg:phone":"+41 19410224",
    "sg:postcode":"8610",
    "sg:province":"Z\u00fcrich",
    "wof:name":"Urs Weyermann Gartenbau & Gartenpflege",
    "wof:placetype":"venue"
},
  "geometry": {"coordinates":[8.7149267197,47.3581008911],"type":"Point"}
}