{
  "type": "Feature",
  "properties": {
    "iso:country":"CH",
    "sg:address":"Riveta Da La Tor",
    "sg:city":"Morcote",
    "sg:orig_category":"Non-Classified Establishments",
    "sg:postcode":"6922",
    "sg:province":"Ticino",
    "wof:name":"Ristorante Della Torre Sa",
    "wof:placetype":"venue"
},
  "geometry": {"coordinates":[8.9177646637,45.9232559204],"type":"Point"}
}