{
  "type": "Feature",
  "properties": {
    "iso:country":"CH",
    "sg:address":"Rue D'airmont 7",
    "sg:city":"Porrentruy",
    "sg:orig_category":"Verwaltung der Volkswirtschaft Wirtschafts U Arbeitgeberverb\u00e4nde",
    "sg:phone":"+41 32 466 46 42",
    "sg:postcode":"2900",
    "sg:province":"Jura",
    "wof:name":"Association Pour Le D\u00e9veloppement \u00e9conomique Du District De Porrentruy (adep)",
    "wof:placetype":"venue"
},
  "geometry": {"coordinates":[7.0920119286,47.4178848267],"type":"Point"}
}