{
  "type": "Feature",
  "properties": {
    "addr:full":"Jurastrasse 4 M\u00f6hlin Aargau 4313",
    "addr:housenumber":"4",
    "addr:postcode":"4313",
    "addr:street":"Jurastrasse",
    "iso:country":"CH",
    "sg:address":"Jurastrasse 4",
    "sg:city":"M\u00f6hlin",
    "sg:orig_category":"Bau U Wohngenossenschaften",
    "sg:postcode":"4313",
    "sg:province":"Aargau",
    "wof:name":"Wohnbaugen.st\u00e4ghold",
    "wof:placetype":"venue"
},
  "geometry": {"coordinates":[7.84226,47.555126],"type":"Point"}
}