{
  "type": "Feature",
  "properties": {
    "iso:country":"CH",
    "sg:address":"R\u00fctihubelstr. 545 3076 Bangerten B. Worb. Postfach",
    "sg:city":"Enggistein",
    "sg:orig_category":"Zimmerei, Dachdeckerei, Bauspenglerei U Abdichtung",
    "sg:phone":"+41 31 839 43 20",
    "sg:postcode":"3077",
    "sg:province":"Bern",
    "wof:name":"Herrmann Holzbau",
    "wof:placetype":"venue"
},
  "geometry": {"coordinates":[7.597055912,46.9340438843],"type":"Point"}
}