{
  "type": "Feature",
  "properties": {
    "iso:country":"CH",
    "sg:address":"Dienerstrasse 16/18",
    "sg:city":"Z\u00fcrich",
    "sg:orig_category":"Non-Classified Establishments",
    "sg:phone":"+41 56 670 19 70",
    "sg:postcode":"8004",
    "sg:province":"Z\u00fcrich",
    "wof:name":"Safenet Ag",
    "wof:placetype":"venue"
},
  "geometry": {"coordinates":[8.5284767151,47.3778038025],"type":"Point"}
}