{
  "type": "Feature",
  "properties": {
    "iso:country":"CH",
    "sg:address":"Dorfstrasse 1",
    "sg:city":"Fislisbach",
    "sg:orig_category":"Herstellung von k\u00e4lte U lufttechnischen Erzeugnissen f\u00fcr gewerbliche Zwecke Sanit\u00e4r U Heizungsinstal",
    "sg:phone":"+41 56 470 20 10",
    "sg:postcode":"5442",
    "sg:province":"Aargau",
    "wof:name":"Schmidlin Brennertechnik",
    "wof:placetype":"venue"
},
  "geometry": {"coordinates":[8.2918481827,47.4367370605],"type":"Point"}
}