{
  "type": "Feature",
  "properties": {
    "iso:country":"CH",
    "sg:address":"Hauptstrasse 49 4435 Niederdorf. Postfach",
    "sg:city":"Niederdorf",
    "sg:orig_category":"Arztpraxen",
    "sg:phone":"+41 61 961 87 87",
    "sg:postcode":"4435",
    "sg:province":"Basel-Landschaft",
    "wof:name":"Dr.med.andreas Althaus Arzt F.allgemeine Medizin Fmh",
    "wof:placetype":"venue"
},
  "geometry": {"coordinates":[7.75189,47.405022],"type":"Point"}
}