{
  "type": "Feature",
  "properties": {
    "iso:country":"CH",
    "sg:address":"Riehenstrasse 24 4058 Basel. Postfach",
    "sg:city":"Basel",
    "sg:orig_category":"Detailhandel mit Haustieren U zoologischem Bedarf",
    "sg:phone":"+41 61 691 10 51",
    "sg:postcode":"4005",
    "sg:province":"Basel-Stadt",
    "wof:name":"August Bucher Zollilaade",
    "wof:placetype":"venue"
},
  "geometry": {"coordinates":[7.5983500481,47.5607223511],"type":"Point"}
}