{
  "type": "Feature",
  "properties": {
    "iso:country":"CH",
    "sg:address":"Gewerbestrasse 6",
    "sg:city":"Visp",
    "sg:orig_category":"Detailhandel mit Beleuchtungs U Haushaltsgegenst\u00e4nden Herstellung von sonstigen elektrischen Ausr\u00fcst",
    "sg:phone":"+41 33 951 12 40",
    "sg:postcode":"3930",
    "sg:province":"Valais",
    "wof:name":"Zumstein Elektroapparate Ag",
    "wof:placetype":"venue"
},
  "geometry": {"coordinates":[8.055438,46.752586],"type":"Point"}
}