{
  "type": "Feature",
  "properties": {
    "iso:country":"CH",
    "sg:address":"Forenackerstrasse 6",
    "sg:city":"Langwiesen",
    "sg:orig_category":"P\u00e9dicure",
    "sg:phone":"+41 55 410 27 85",
    "sg:postcode":"8246",
    "sg:province":"Z\u00fcrich",
    "wof:name":"Margrit Oudermans P\u00e9dicure",
    "wof:placetype":"venue"
},
  "geometry": {"coordinates":[8.7813034058,47.1997032166],"type":"Point"}
}