{
  "type": "Feature",
  "properties": {
    "iso:country":"CH",
    "sg:address":"In Der Ey 29",
    "sg:city":"Z\u00fcrich",
    "sg:classifiers":[
        {
            "category":"Restaurant",
            "type":"Food & Drink"
        }
    ],
    "sg:phone":"+41 14916548",
    "sg:postcode":"8047",
    "sg:province":"Z\u00fcrich",
    "wof:name":"Restaurant Nuovum Ey",
    "wof:placetype":"venue"
},
  "geometry": {"coordinates":[8.4894046783,47.3739318848],"type":"Point"}
}