{
  "type": "Feature",
  "properties": {
    "iso:country":"CH",
    "sg:address":"Via Papio",
    "sg:city":"Ascona",
    "sg:orig_category":"Parkh\u00e4user",
    "sg:phone":"+41 71 222 11 14",
    "sg:postcode":"6612",
    "sg:province":"Ticino",
    "wof:name":"Neumarkt-parkgarage City-garage Ag",
    "wof:placetype":"venue"
},
  "geometry": {"coordinates":[9.3705272675,47.4222297668],"type":"Point"}
}