{
  "type": "Feature",
  "properties": {
    "iso:country":"CH",
    "sg:address":"Avenue Viollier 9 1260 Nyon Case Postale 182",
    "sg:city":"Nyon",
    "sg:orig_category":"Wirtschaftspr\u00fcfung, Steuerberatung U Treuhand",
    "sg:phone":"+41 22 362 22 08",
    "sg:postcode":"1260",
    "sg:province":"Vaud",
    "wof:name":"Y. Cherpillod & C. Grosjean Bureau D'assistance Fiscale",
    "wof:placetype":"venue"
},
  "geometry": {"coordinates":[6.2374258041,46.3844223022],"type":"Point"}
}