{
  "type": "Feature",
  "properties": {
    "iso:country":"CH",
    "sg:address":"7206",
    "sg:city":"Igis",
    "sg:orig_category":"Instandhaltung U Reparatur von Automobilen",
    "sg:phone":"+41 81 322 18 27",
    "sg:postcode":"7206",
    "sg:province":"Graubunden",
    "wof:name":"Amb\u00fchl G. Ag",
    "wof:placetype":"venue"
},
  "geometry": {"coordinates":[9.5744199753,46.9440612793],"type":"Point"}
}