{
  "type": "Feature",
  "properties": {
    "iso:country":"CH",
    "sg:address":"B\u00f6sch 81 6331 H\u00fcnenberg. Postfach 42",
    "sg:city":"H\u00fcnenberg",
    "sg:orig_category":"Herstellung von Metallerzeugnissen ohne Maschinenbau Mechanik",
    "sg:phone":"+41 79 434 35 31",
    "sg:postcode":"6331",
    "sg:province":"Zug",
    "wof:name":"Breschan Helmut Ag",
    "wof:placetype":"venue"
},
  "geometry": {"coordinates":[8.435297966,47.1623764038],"type":"Point"}
}