{
  "type": "Feature",
  "properties": {
    "iso:country":"CH",
    "sg:address":"Route Du Canard",
    "sg:city":"Granges-marnand",
    "sg:orig_category":"Landwirtschaftliche Genossenschaften",
    "sg:phone":"+41 26 668 11 30",
    "sg:postcode":"1523",
    "sg:province":"Vaud",
    "wof:name":"Soci\u00e9t\u00e9 D'agriculture De Granges",
    "wof:placetype":"venue"
},
  "geometry": {"coordinates":[6.8920850754,46.7602348328],"type":"Point"}
}