{
  "type": "Feature",
  "properties": {
    "iso:country":"CH",
    "sg:address":"Z\u00fcrichstrasse 8",
    "sg:city":"D\u00fcbendorf",
    "sg:orig_category":"Datenverarbeitungsdienste Softwareentwicklung U beratung",
    "sg:phone":"+41 18216633",
    "sg:postcode":"8600",
    "sg:province":"Z\u00fcrich",
    "wof:name":"Inetconsult Ag Internettechnologien; Vermittlung, Entwicklung. Dienstleistungen Im Informatik, Internetbereich",
    "wof:placetype":"venue"
},
  "geometry": {"coordinates":[8.616787,47.397167],"type":"Point"}
}