{
  "type": "Feature",
  "properties": {
    "iso:country":"CH",
    "sg:address":"Im R\u00f6tel 24b",
    "sg:city":"Zug",
    "sg:orig_category":"Detailhandel mit B\u00fcchern, Zeitungen, Schreib U Papeteriewaren Detailhandel mit Ton U Bildtr\u00e4gern",
    "sg:phone":"+41 41 712 19 50",
    "sg:postcode":"6300",
    "sg:province":"Zug",
    "wof:name":"Golfiana Jean-pierre Bertschi",
    "wof:placetype":"venue"
},
  "geometry": {"coordinates":[8.52753,47.167618],"type":"Point"}
}