{
  "type": "Feature",
  "properties": {
    "iso:country":"CH",
    "sg:address":"Baarerstrasse 8",
    "sg:city":"Zug",
    "sg:orig_category":"Unclassifiable Establishments",
    "sg:postcode":"6300",
    "sg:province":"Zug",
    "wof:name":"Divernois S. \u00e0 R.l.",
    "wof:placetype":"venue"
},
  "geometry": {"coordinates":[7.0057091713,47.2100753784],"type":"Point"}
}