{
  "type": "Feature",
  "properties": {
    "iso:country":"CH",
    "sg:address":"Hochtanne.",
    "sg:city":"Russikon",
    "sg:orig_category":"Unclassifiable Establishments",
    "sg:postcode":"8332",
    "sg:province":"Z\u00fcrich",
    "wof:name":"Christian Tritten",
    "wof:placetype":"venue"
},
  "geometry": {"coordinates":[8.7759141922,47.3938407898],"type":"Point"}
}