{
  "type": "Feature",
  "properties": {
    "iso:country":"CH",
    "sg:address":"Rue Jean-ant.-gautier 9",
    "sg:city":"Gen\u00e8ve",
    "sg:orig_category":"Reiseb\u00fcros",
    "sg:phone":"+41 32 913 53 13",
    "sg:postcode":"1201",
    "sg:province":"Gen\u00e8ve",
    "wof:name":"Top-tours Autocars Bailly Michel",
    "wof:placetype":"venue"
},
  "geometry": {"coordinates":[6.8212461472,47.1028900146],"type":"Point"}
}