{
  "type": "Feature",
  "properties": {
    "iso:country":"CH",
    "sg:address":"Rue Du Mont-terri 13",
    "sg:city":"Porrentruy",
    "sg:orig_category":"Vereine Briefmarkensammler",
    "sg:postcode":"2900",
    "sg:province":"Jura",
    "wof:name":"St\u00e9 Philat\u00e9lique Porrentruy",
    "wof:placetype":"venue"
},
  "geometry": {"coordinates":[7.066467762,47.4101142883],"type":"Point"}
}