{
  "type": "Feature",
  "properties": {
    "iso:country":"CH",
    "sg:address":"Pilgerstegstrasse 9",
    "sg:city":"D\u00fcrnten",
    "sg:orig_category":"Non-Classified Establishments",
    "sg:postcode":"8635",
    "sg:province":"Z\u00fcrich",
    "wof:name":"Familienstiftung Fritz Liechti",
    "wof:placetype":"venue"
},
  "geometry": {"coordinates":[8.8676748276,47.2748336792],"type":"Point"}
}