{
  "type": "Feature",
  "properties": {
    "iso:country":"CH",
    "sg:address":"P\u00e9rolles Boulevard De 7",
    "sg:city":"Fribourg",
    "sg:orig_category":"Unclassifiable Establishments",
    "sg:postcode":"1700",
    "sg:province":"Fribourg",
    "wof:name":"Dischinger Andr\u00e9",
    "wof:placetype":"venue"
},
  "geometry": {"coordinates":[7.603741169,46.1775054932],"type":"Point"}
}