{
  "type": "Feature",
  "properties": {
    "addr:full":"Grenzstrasse 31 Lyss Bern 3250",
    "addr:housenumber":"31",
    "addr:postcode":"3250",
    "addr:street":"Grenzstrasse;Bern",
    "iso:country":"CH",
    "sg:address":"Grenzstrasse 31",
    "sg:city":"Lyss",
    "sg:orig_category":"Ausbaugewerbe Installation von Heizungs, L\u00fcftungs U Klimaanlagen",
    "sg:phone":"+41 32 384 80 36",
    "sg:postcode":"3250",
    "sg:province":"Bern",
    "wof:name":"Munters Ag",
    "wof:placetype":"venue"
},
  "geometry": {"coordinates":[7.29079,47.06731],"type":"Point"}
}