{
  "type": "Feature",
  "properties": {
    "iso:country":"CH",
    "sg:address":"Bahnhofstrasse 54",
    "sg:city":"Koblenz",
    "sg:orig_category":"RESTAURANTS: TEA-ROOMS",
    "sg:phone":"+41 81 413 51 78",
    "sg:postcode":"5322",
    "sg:province":"Aargau",
    "wof:name":"Mikuma Ag",
    "wof:placetype":"venue"
},
  "geometry": {"coordinates":[9.8251085281,46.7960891724],"type":"Point"}
}