{
  "type": "Feature",
  "properties": {
    "iso:country":"CH",
    "sg:address":"8753 Mollis. Postfach 107",
    "sg:city":"Mollis",
    "sg:orig_category":"Vereine Musik/Blasmusik",
    "sg:phone":"+41 55 612 34 65",
    "sg:postcode":"8753",
    "sg:province":"Glarus",
    "wof:name":"Musikgesellschaft Harmonie",
    "wof:placetype":"venue"
},
  "geometry": {"coordinates":[9.0745248795,47.0914382935],"type":"Point"}
}