{
  "type": "Feature",
  "properties": {
    "iso:country":"CH",
    "sg:address":"Burgstrasse 7",
    "sg:city":"W\u00e4denswil",
    "sg:orig_category":"Vereine Wissenschaftliche",
    "sg:phone":"+41 17803540",
    "sg:postcode":"8820",
    "sg:province":"Z\u00fcrich",
    "wof:name":"Entomologia Z\u00fcrich",
    "wof:placetype":"venue"
},
  "geometry": {"coordinates":[8.6762361526,47.2191047668],"type":"Point"}
}