{
  "type": "Feature",
  "properties": {
    "iso:country":"CH",
    "sg:address":"Les Bouleaux A/20",
    "sg:city":"Montana-vermala",
    "sg:orig_category":"G\u00fcterbef\u00f6rderung im Strassenverkehr",
    "sg:phone":"+41 27 481 40 86",
    "sg:postcode":"3962",
    "wof:name":"Aderald Savioz Transports",
    "wof:placetype":"venue"
},
  "geometry": {"coordinates":[7.4924340248,46.3144187927],"type":"Point"}
}