{
  "type": "Feature",
  "properties": {
    "iso:country":"CH",
    "sg:address":"K\u00e4nelmattstrasse 60",
    "sg:city":"Arisdorf",
    "sg:orig_category":"Abbruch U Sprenggewerbe Abbruch U Sprenggewerbe, Erdbewegungsarbeiten",
    "sg:phone":"+41 17881767",
    "sg:postcode":"4422",
    "sg:province":"Basel-Landschaft",
    "wof:name":"Staub Julius Geb\u00e4udeabbruch Und Bedachungen",
    "wof:placetype":"venue"
},
  "geometry": {"coordinates":[8.628126,47.190903],"type":"Point"}
}