{
  "type": "Feature",
  "properties": {
    "iso:country":"CH",
    "sg:address":"Schulhausstrasse 1",
    "sg:city":"G\u00fcmligen",
    "sg:orig_category":"Detailhandel mit M\u00f6beln Detailhandel mit M\u00f6beln U Haushaltsgegenst\u00e4nden",
    "sg:phone":"+41 71 388 18 58",
    "sg:postcode":"3073",
    "sg:province":"Bern",
    "wof:name":"Toni M\u00f6bel Ag",
    "wof:placetype":"venue"
},
  "geometry": {"coordinates":[9.2853384018,47.4092788696],"type":"Point"}
}