{
  "type": "Feature",
  "properties": {
    "iso:country":"CH",
    "sg:address":"Rue De L'or\u00e9e 2",
    "sg:city":"Ch\u00e9zard-st-martin",
    "sg:orig_category":"Vermietung U Verpachtung von eigenen Immobilien",
    "sg:postcode":"2054",
    "sg:province":"Neuch\u00e2tel",
    "wof:name":"Arpic Sa",
    "wof:placetype":"venue"
},
  "geometry": {"coordinates":[6.9135141373,47.065410614],"type":"Point"}
}