{
  "type": "Feature",
  "properties": {
    "iso:country":"CH",
    "sg:address":"Reichenbach Willigen",
    "sg:city":"Meiringen",
    "sg:orig_category":"Unclassifiable Establishments",
    "sg:phone":"+41 33 972 81 11",
    "sg:postcode":"3860",
    "sg:province":"Bern",
    "wof:name":"Michel Beteiligungen Im Reichenbach Ag",
    "wof:placetype":"venue"
},
  "geometry": {"coordinates":[8.186214447,46.7278556824],"type":"Point"}
}