{
  "type": "Feature",
  "properties": {
    "iso:country":"CH",
    "sg:address":"Arbonerstrasse 2",
    "sg:city":"Kronb\u00fchl",
    "sg:orig_category":"Detailhandel mit Uhren U Schmuck Reparatur von Uhren U Schmuck",
    "sg:phone":"+41 71 298 42 88",
    "sg:postcode":"9302",
    "wof:name":"Heinrich Bader Uhren & Bijouterie",
    "wof:placetype":"venue"
},
  "geometry": {"coordinates":[9.3952817917,47.459236145],"type":"Point"}
}