{
  "type": "Feature",
  "properties": {
    "iso:country":"CH",
    "sg:address":"Libert\u00e9 Place De La 5",
    "sg:city":"Alle",
    "sg:orig_category":"RESTAURANTS: TEA-ROOMS",
    "sg:phone":"+41 32 471 11 81",
    "sg:postcode":"2942",
    "sg:province":"Jura",
    "wof:name":"Restaurant De L'helvetia, Mazzilli Salvatore",
    "wof:placetype":"venue"
},
  "geometry": {"coordinates":[7.1273069382,47.4245681763],"type":"Point"}
}