{
  "type": "Feature",
  "properties": {
    "addr:full":"Po Box 4623 Gl\u00e4rnischstrasse 36 Z\u00fcrich Z\u00fcrich 8022",
    "addr:housenumber":"po;36",
    "addr:postcode":"8022",
    "addr:street":"Box 4623 Glaernischstrasse",
    "iso:country":"CH",
    "sg:address":"Po Box 4623 Gl\u00e4rnischstrasse 36",
    "sg:city":"Z\u00fcrich",
    "sg:classifiers":[
        {
            "category":"Banks & Credit Unions",
            "subcategory":"Bank",
            "type":"Services"
        }
    ],
    "sg:postcode":"8022",
    "sg:province":"Z\u00fcrich",
    "wof:name":"Ing Baring Private Bank (schweiz) Ag",
    "wof:placetype":"venue"
},
  "geometry": {"coordinates":[8.53801,47.369091],"type":"Point"}
}