{
  "type": "Feature",
  "properties": {
    "iso:country":"CH",
    "sg:address":"Sch\u00fctzenstrasse 2-6 4410 Liestal. Postfach",
    "sg:city":"Liestal",
    "sg:orig_category":"Druck ohne Zeitungsdruck Verlagsgewerbe",
    "sg:phone":"+41 61 927 27 27",
    "sg:postcode":"4410",
    "sg:province":"Basel-Landschaft",
    "wof:name":"L\u00fcdin Ag Druckerei",
    "wof:placetype":"venue"
},
  "geometry": {"coordinates":[7.7333798409,47.4852218628],"type":"Point"}
}