{
  "type": "Feature",
  "properties": {
    "iso:country":"CH",
    "sg:address":"Chemin De Closalet 12",
    "sg:city":"Crissier",
    "sg:orig_category":"Arbeitnehmerverb\u00e4nde",
    "sg:phone":"+41 21 784 35 43",
    "sg:postcode":"1023",
    "sg:province":"Vaud",
    "wof:name":"Association Suisse Des Golfeurs Ind\u00e9pendants Asgi",
    "wof:placetype":"venue"
},
  "geometry": {"coordinates":[6.571396,46.55394],"type":"Point"}
}