{
  "type": "Feature",
  "properties": {
    "iso:country":"CH",
    "sg:address":"Fabrikstrasse 10",
    "sg:city":"Buchs",
    "sg:classifiers":[
        {
            "category":"Personal",
            "subcategory":"Hair Removal",
            "type":"Services"
        }
    ],
    "sg:phone":"+41 81 750 50 30",
    "sg:postcode":"9470",
    "sg:province":"St. Gallen",
    "sg:tags":[
        "piece"
    ],
    "wof:name":"Atelier Bassi Gmbh",
    "wof:placetype":"venue"
},
  "geometry": {"coordinates":[9.4816579819,47.1725120544],"type":"Point"}
}