{
  "type": "Feature",
  "properties": {
    "iso:country":"CH",
    "sg:address":"In Den Hasen 55",
    "sg:city":"Lauerz",
    "sg:orig_category":"Erschliessung von Grundst\u00fccken",
    "sg:postcode":"6424",
    "sg:province":"Schwyz",
    "wof:name":"Genossenschaft Erschliessung Hasen",
    "wof:placetype":"venue"
},
  "geometry": {"coordinates":[8.5827550888,47.0338363647],"type":"Point"}
}