{
  "type": "Feature",
  "properties": {
    "iso:country":"CH",
    "sg:address":"Neubadstrasse 7 4054 Basel. Postfach",
    "sg:city":"Basel",
    "sg:orig_category":"Grosshandel mit chemischen Erzeugnissen",
    "sg:phone":"+41 56 225 26 80",
    "sg:postcode":"4015",
    "sg:province":"Basel-Stadt",
    "wof:name":"Cemag Handels Ag",
    "wof:placetype":"venue"
},
  "geometry": {"coordinates":[8.2446603775,47.4611587524],"type":"Point"}
}