{
  "type": "Feature",
  "properties": {
    "iso:country":"CH",
    "sg:address":"Baslerstrasse 96",
    "sg:city":"Trimbach",
    "sg:orig_category":"Physiotherapie",
    "sg:phone":"+41 62 293 38 78",
    "sg:postcode":"4632",
    "sg:province":"Solothurn",
    "wof:name":"Katharina Sch\u00fcpbach Physiotherapie",
    "wof:placetype":"venue"
},
  "geometry": {"coordinates":[7.897687912,47.3623466492],"type":"Point"}
}