{
  "type": "Feature",
  "properties": {
    "iso:country":"CH",
    "sg:address":"Heimlisbergstrasse 17",
    "sg:city":"Langendorf",
    "sg:orig_category":"Maler U Glasergewerbe Malerei",
    "sg:phone":"+41 32 622 37 66",
    "sg:postcode":"4513",
    "sg:province":"Solothurn",
    "wof:name":"Georges Wyniger Malergesch\u00e4ft",
    "wof:placetype":"venue"
},
  "geometry": {"coordinates":[7.5123581886,47.2200775146],"type":"Point"}
}