{
  "type": "Feature",
  "properties": {
    "iso:country":"CH",
    "sg:address":"Hauptstrasse 26",
    "sg:city":"Bretzwil",
    "sg:orig_category":"Detailhandel mit Milcherzeugnissen U Eiern",
    "sg:phone":"+41 61 941 17 19",
    "sg:postcode":"4207",
    "sg:province":"Basel-Landschaft",
    "wof:name":"Chesi Bretzwil",
    "wof:placetype":"venue"
},
  "geometry": {"coordinates":[7.65376091,47.3997154236],"type":"Point"}
}