{
  "type": "Feature",
  "properties": {
    "iso:country":"CH",
    "sg:address":"Uetlibergstrasse 341",
    "sg:city":"Z\u00fcrich",
    "sg:classifiers":[
        {
            "category":"Restaurant",
            "type":"Food & Drink"
        }
    ],
    "sg:phone":"+41 14620522",
    "sg:postcode":"8045",
    "sg:province":"Z\u00fcrich",
    "wof:name":"Sch\u00fctzenhaus Albisg\u00fcetli Schloss Taverne",
    "wof:placetype":"venue"
},
  "geometry": {"coordinates":[8.5074110031,47.3522491455],"type":"Point"}
}