{
  "type": "Feature",
  "properties": {
    "iso:country":"CH",
    "sg:address":"Hof",
    "sg:city":"Herrliberg",
    "sg:orig_category":"Grosshandel mit chemischen Erzeugnissen Herstellung von sonstigen Maschinen f\u00fcr bestimmte Verwendung",
    "sg:phone":"+41 71 393 58 60",
    "sg:postcode":"8704",
    "sg:province":"Z\u00fcrich",
    "wof:name":"Berger Klebe-systeme",
    "wof:placetype":"venue"
},
  "geometry": {"coordinates":[9.2496490479,47.4107437134],"type":"Point"}
}