{
  "type": "Feature",
  "properties": {
    "iso:country":"CH",
    "sg:address":"Hirschmattstrasse 13",
    "sg:city":"Luzern",
    "sg:orig_category":"Detailhandel mit Damenbekleidung Herstellung von Oberbekleidung",
    "sg:phone":"+41 41 210 76 13",
    "sg:postcode":"6003",
    "sg:province":"Luzern",
    "wof:name":"Maison Steffy Ag",
    "wof:placetype":"venue"
},
  "geometry": {"coordinates":[8.3065052032,47.0488014221],"type":"Point"}
}