{
  "type": "Feature",
  "properties": {
    "iso:country":"CH",
    "sg:address":"4952",
    "sg:city":"Eriswil",
    "sg:orig_category":"Vereine Gesang",
    "sg:postcode":"4952",
    "sg:province":"Bern",
    "wof:name":"M\u00e4nnerchor Eriswil",
    "wof:placetype":"venue"
},
  "geometry": {"coordinates":[7.8506450653,47.0790901184],"type":"Point"}
}