{
  "type": "Feature",
  "properties": {
    "iso:country":"CH",
    "sg:address":"Rue St-randoald 7",
    "sg:city":"Court\u00e9telle",
    "sg:orig_category":"Arztpraxen",
    "sg:phone":"+41 32 422 58 07",
    "sg:postcode":"2852",
    "sg:province":"Jura",
    "wof:name":"Dr M\u00e9d. Fernando Fiori M\u00e9decin G\u00e9n\u00e9raliste",
    "wof:placetype":"venue"
},
  "geometry": {"coordinates":[7.317921,47.343811],"type":"Point"}
}