{
  "type": "Feature",
  "properties": {
    "iso:country":"CH",
    "sg:address":"Chrumbacherweg 10a 5612 Villmergen. Postfach",
    "sg:city":"Villmergen",
    "sg:orig_category":"Herstellung von keramischen Wand U Bodenfliesen U platten",
    "sg:postcode":"5612",
    "sg:province":"Aargau",
    "wof:name":"H\u00fcmbeli M. Plattenbel\u00e4ge Gmbh",
    "wof:placetype":"venue"
},
  "geometry": {"coordinates":[8.240064621,47.3514823914],"type":"Point"}
}