{
  "type": "Feature",
  "properties": {
    "iso:country":"CH",
    "sg:address":"Chemin De La Perroude",
    "sg:city":"Gland",
    "sg:orig_category":"Primarschulen",
    "sg:phone":"+41 22 364 23 05",
    "sg:postcode":"1196",
    "sg:province":"Vaud",
    "wof:name":"Ecole Primaire Centre Scolaire Aux Perrerets",
    "wof:placetype":"venue"
},
  "geometry": {"coordinates":[6.2618851662,46.4246749878],"type":"Point"}
}