{
  "type": "Feature",
  "properties": {
    "iso:country":"CH",
    "sg:address":"Langweidstrasse 1",
    "sg:city":"Obfelden",
    "sg:orig_category":"Caterer Detailhandel mit Fleisch U Fleischwaren",
    "sg:phone":"+41 17612961",
    "sg:postcode":"8912",
    "sg:province":"Z\u00fcrich",
    "wof:name":"Urs Koffel Catering",
    "wof:placetype":"venue"
},
  "geometry": {"coordinates":[8.421502,47.269188],"type":"Point"}
}