{
  "type": "Feature",
  "properties": {
    "iso:country":"CH",
    "sg:address":"Bodenmattstrasse 351",
    "sg:city":"Wallbach",
    "sg:orig_category":"Herstellung von Kunststoffwaren Herstellung von Platten, Folien, Schl\u00e4uchen U Profilen aus Kunststof",
    "sg:phone":"+41 61 861 12 83",
    "sg:postcode":"4323",
    "sg:province":"Aargau",
    "wof:name":"Werkzeug - Formenbau E. Probst Wallbach",
    "wof:placetype":"venue"
},
  "geometry": {"coordinates":[7.9006099701,47.5590515137],"type":"Point"}
}