{
  "type": "Feature",
  "properties": {
    "iso:country":"CH",
    "sg:address":"Route Du Simplon 7 1907 Mayens-de-saxon. Postfach",
    "sg:city":"Mayens-de-saxon",
    "sg:orig_category":"Einzelhandel mit Automobilen Instandhaltung U Reparatur von Automobilen",
    "sg:phone":"+41 27 744 28 95",
    "sg:postcode":"1907",
    "sg:province":"Valais",
    "wof:name":"Garage De La Pierre-\u00e0-voir, Vouillamoz Cyrano Garage-atelier De R\u00e9parations De V\u00e9hicules \u00e0 Moteur Etc.",
    "wof:placetype":"venue"
},
  "geometry": {"coordinates":[7.1794571877,46.15184021],"type":"Point"}
}