{
  "type": "Feature",
  "properties": {
    "iso:country":"CH",
    "sg:address":"Torggelhalde Abt-beda-strasse",
    "sg:city":"Oberb\u00fcren",
    "sg:orig_category":"Herstellung von B\u00fcro U Ladenm\u00f6beln Herstellung von Erzeugnissen aus Beton, Gips U Zement",
    "sg:phone":"+41 71 951 73 08",
    "sg:postcode":"9245",
    "sg:province":"St. Gallen",
    "wof:name":"Contec Fabrikations-& Handels Ag",
    "wof:placetype":"venue"
},
  "geometry": {"coordinates":[9.1631736755,47.4511528015],"type":"Point"}
}