{
  "type": "Feature",
  "properties": {
    "iso:country":"CH",
    "sg:address":"Waaghaus-passage 8",
    "sg:city":"Bern",
    "sg:orig_category":"Detailhandel mit Schreib U Papeteriewaren",
    "sg:phone":"+41 56 441 46 16",
    "sg:postcode":"3011",
    "sg:province":"Bern",
    "wof:name":"Renate Amsler B\u00fcromax",
    "wof:placetype":"venue"
},
  "geometry": {"coordinates":[8.2081766129,47.4812736511],"type":"Point"}
}