{
  "type": "Feature",
  "properties": {
    "addr:full":"Schmiede Oberthal Bern 3531",
    "addr:postcode":"3531",
    "addr:street":"Oberthal",
    "iso:country":"CH",
    "sg:address":"Schmiede",
    "sg:city":"Oberthal",
    "sg:classifiers":[
        {
            "category":"Banks & Credit Unions",
            "subcategory":"Bank",
            "type":"Services"
        }
    ],
    "sg:phone":"+41 31 711 19 42",
    "sg:postcode":"3531",
    "sg:province":"Bern",
    "wof:name":"Raiffeisenbank",
    "wof:placetype":"venue"
},
  "geometry": {"coordinates":[7.659327,46.911381],"type":"Point"}
}