{
  "type": "Feature",
  "properties": {
    "iso:country":"CH",
    "sg:address":"Gare Rue De La 8",
    "sg:city":"Pully",
    "sg:orig_category":"Herstellung von Kakao, Schokoladeerzeugnissen U Zuckerwaren",
    "sg:postcode":"1009",
    "sg:province":"Vaud",
    "wof:name":"Bonbonmania, Colacillo Palmerina",
    "wof:placetype":"venue"
},
  "geometry": {"coordinates":[6.6598000526,46.5102577209],"type":"Point"}
}