{
  "type": "Feature",
  "properties": {
    "iso:country":"CH",
    "sg:address":"Avenue Du Petit-senn 32",
    "sg:city":"Ch\u00eane-bourg",
    "sg:orig_category":"Detailhandel mit B\u00fcchern Interessenvertretungen",
    "sg:phone":"+41 22 869 06 26",
    "sg:postcode":"1225",
    "sg:province":"Gen\u00e8ve",
    "wof:name":"Carrefour Sant\u00e9",
    "wof:placetype":"venue"
},
  "geometry": {"coordinates":[6.194273,46.193073],"type":"Point"}
}