{
  "type": "Feature",
  "properties": {
    "iso:country":"CH",
    "sg:address":"Pfirtergasse 28",
    "sg:city":"Basel",
    "sg:orig_category":"Arztpraxen",
    "sg:phone":"+41 61 281 30 00",
    "sg:postcode":"4054",
    "sg:province":"Basel-Stadt",
    "wof:name":"Dr.med.catherine Aeschlimann Spezial\u00e4rztin Fmh",
    "wof:placetype":"venue"
},
  "geometry": {"coordinates":[7.578189,47.54903],"type":"Point"}
}