{
  "type": "Feature",
  "properties": {
    "iso:country":"CH",
    "sg:address":"Vorderdorfstrasse 40",
    "sg:city":"Otelfingen",
    "sg:orig_category":"Landesverteidigung, Sozialversicherung \u00d6ffentliche Verwaltung",
    "sg:phone":"+41 18442271",
    "sg:postcode":"8112",
    "sg:province":"Z\u00fcrich",
    "wof:name":"Zivilschutzstelle Otelfingen",
    "wof:placetype":"venue"
},
  "geometry": {"coordinates":[8.3878726959,47.4628982544],"type":"Point"}
}