{
  "type": "Feature",
  "properties": {
    "addr:full":"Via Della Posta 29 Locarno Ticino 6600",
    "addr:housenumber":"29",
    "addr:postcode":"6600",
    "addr:street":"Via Della Posta;Ticino",
    "iso:country":"CH",
    "sg:address":"Via Della Posta 29",
    "sg:city":"Locarno",
    "sg:orig_category":"Autogaragen Instandhaltung U Reparatur von Automobilen",
    "sg:phone":"+41 22 785 50 85",
    "sg:postcode":"6600",
    "sg:province":"Ticino",
    "wof:name":"Garage Carrosserie Grande Vitesse, Galatola D. Et N.",
    "wof:placetype":"venue"
},
  "geometry": {"coordinates":[6.082297,46.222828],"type":"Point"}
}