{
  "type": "Feature",
  "properties": {
    "iso:country":"CH",
    "sg:address":"Hauptstrasse 26",
    "sg:city":"Kreuzlingen",
    "sg:orig_category":"Softwareentwicklung U beratung",
    "sg:postcode":"8280",
    "sg:province":"Thurgau",
    "wof:name":"Ingenieurb\u00fcro Ejem",
    "wof:placetype":"venue"
},
  "geometry": {"coordinates":[9.1737251282,47.6520957947],"type":"Point"}
}