{
  "type": "Feature",
  "properties": {
    "iso:country":"CH",
    "sg:address":"Avenue De La Gare 33",
    "sg:city":"Del\u00e9mont",
    "sg:orig_category":"Detailhandel mit Sportartikeln",
    "sg:phone":"+41 32 422 54 22",
    "sg:postcode":"2800",
    "sg:province":"Jura",
    "wof:name":"Rudi Schribertschnig Sporting-sports",
    "wof:placetype":"venue"
},
  "geometry": {"coordinates":[7.3495879173,47.3639717102],"type":"Point"}
}