{
  "type": "Feature",
  "properties": {
    "iso:country":"CH",
    "sg:address":"B\u00fcrglenweg 9",
    "sg:city":"Uetendorf",
    "sg:orig_category":"Sportvereine Ski",
    "sg:phone":"+41 33 345 44 50",
    "sg:postcode":"3661",
    "sg:province":"Bern",
    "wof:name":"Skicl.h'fingen Ski-racing-team",
    "wof:placetype":"venue"
},
  "geometry": {"coordinates":[7.5948910713,46.7768859863],"type":"Point"}
}