{
  "type": "Feature",
  "properties": {
    "iso:country":"CH",
    "sg:address":"Schinerstrasse 3",
    "sg:city":"Brig",
    "sg:orig_category":"Politische Parteien CVP Vereine Damen",
    "sg:phone":"+41 71 222 33 84",
    "sg:postcode":"3900",
    "sg:province":"Valais",
    "wof:name":"Cvp-frauengruppe",
    "wof:placetype":"venue"
},
  "geometry": {"coordinates":[9.3780097961,47.4236297607],"type":"Point"}
}