{
  "type": "Feature",
  "properties": {
    "iso:country":"CH",
    "sg:address":"Route Du Chasseur 30bis",
    "sg:city":"Prilly",
    "sg:orig_category":"Innendekorationsateliers",
    "sg:phone":"+41 21 624 95 72",
    "sg:postcode":"1008",
    "sg:province":"Vaud",
    "wof:name":"Efrem Cornolti Tapissier-d\u00e9corateur",
    "wof:placetype":"venue"
},
  "geometry": {"coordinates":[6.6066460609,46.5385131836],"type":"Point"}
}