{
  "type": "Feature",
  "properties": {
    "iso:country":"CH",
    "sg:address":"Frauenfelderstrasse 19",
    "sg:city":"W\u00e4ngi",
    "sg:orig_category":"Herstellung von Ger\u00e4ten der Elektrizit\u00e4tserzeugung, -verteilung u.\u00e4. -Herstellung von elektronischen",
    "sg:phone":"+41 52 378 21 61",
    "sg:postcode":"9545",
    "sg:province":"Thurgau",
    "wof:name":"Blunier-service Elektroanlagen",
    "wof:placetype":"venue"
},
  "geometry": {"coordinates":[8.9513320923,47.4983711243],"type":"Point"}
}