{
  "type": "Feature",
  "properties": {
    "iso:country":"CH",
    "sg:address":"Hasenmoosstrasse 33",
    "sg:city":"Rothenburg",
    "sg:orig_category":"Grosshandel mit Getr\u00e4nken",
    "sg:phone":"+41 41 289 61 98",
    "sg:postcode":"6023",
    "sg:province":"Luzern",
    "wof:name":"A. & C. Pochon Sa",
    "wof:placetype":"venue"
},
  "geometry": {"coordinates":[8.240146637,47.1009140015],"type":"Point"}
}