{
  "type": "Feature",
  "properties": {
    "addr:full":"H\u00f6lderlinstrasse 10 Z\u00fcrich Z\u00fcrich 8032",
    "addr:housenumber":"10",
    "addr:postcode":"8032",
    "addr:street":"Hoelderlinstrasse",
    "iso:country":"CH",
    "sg:address":"H\u00f6lderlinstrasse 10",
    "sg:city":"Z\u00fcrich",
    "sg:orig_category":"Berufsberatungen",
    "sg:phone":"+41 12525543",
    "sg:postcode":"8032",
    "sg:province":"Z\u00fcrich",
    "wof:name":"Verena Flubacher Berufsberatung",
    "wof:placetype":"venue"
},
  "geometry": {"coordinates":[8.564041,47.366344],"type":"Point"}
}