{
  "type": "Feature",
  "properties": {
    "iso:country":"CH",
    "sg:address":"Postgasse 26",
    "sg:city":"Pieterlen",
    "sg:classifiers":[
        {
            "category":"Manufacturing",
            "subcategory":"Glass & Minerals",
            "type":"Manufacturing & Wholesale Goods"
        }
    ],
    "sg:phone":"+41 71 223 56 66",
    "sg:postcode":"2542",
    "sg:province":"Bern",
    "sg:tags":[
        "frame"
    ],
    "wof:name":"Grasso Optik Ag",
    "wof:placetype":"venue"
},
  "geometry": {"coordinates":[9.3724441528,47.4236679077],"type":"Point"}
}