{
  "type": "Feature",
  "properties": {
    "iso:country":"CH",
    "sg:address":"Mittelg\u00e4ustrasse 30",
    "sg:city":"Gunzgen",
    "sg:classifiers":[
        {
            "category":"Government",
            "subcategory":"Post Office",
            "type":"Public Place"
        }
    ],
    "sg:phone":"+41 62 216 51 16",
    "sg:postcode":"4617",
    "sg:province":"Solothurn",
    "sg:tags":[
        "caf\u00e9s",
        "tea-rooms"
    ],
    "wof:name":"Caf\u00e9 Eintracht",
    "wof:placetype":"venue"
},
  "geometry": {"coordinates":[7.8301482201,47.3183784485],"type":"Point"}
}