{
  "type": "Feature",
  "properties": {
    "iso:country":"CH",
    "sg:address":"Sch\u00fcracherstrasse 7a",
    "sg:city":"Br\u00fcttisellen",
    "sg:orig_category":"Allgemeiner Hoch U Tiefbau Allgemeiner Hochbau",
    "sg:phone":"+41 18333141",
    "sg:postcode":"8306",
    "sg:province":"Z\u00fcrich",
    "wof:name":"Schumacher & Wegmann",
    "wof:placetype":"venue"
},
  "geometry": {"coordinates":[8.631428,47.422329],"type":"Point"}
}