{
  "type": "Feature",
  "properties": {
    "iso:country":"CH",
    "sg:address":"Obergass 49",
    "sg:city":"Eglisau",
    "sg:orig_category":"Detailhandel mit Blumen U Pflanzen",
    "sg:phone":"+41 18675005",
    "sg:postcode":"8193",
    "sg:province":"Z\u00fcrich",
    "wof:name":"Verena Br\u00fcgger Blumenboutique Alte Wagnerei",
    "wof:placetype":"venue"
},
  "geometry": {"coordinates":[8.525493,47.575665],"type":"Point"}
}