{
  "type": "Feature",
  "properties": {
    "iso:country":"CH",
    "sg:address":"Bahnhofstrasse 14 6340 Baar. Postfach 8045 Z\u00fcrich",
    "sg:city":"Zust",
    "sg:orig_category":"Werbung",
    "sg:phone":"+41 14575757",
    "sg:postcode":"45",
    "wof:name":"Wirz Werbung Ag",
    "wof:placetype":"venue"
},
  "geometry": {"coordinates":[8.5234766006,47.1950645447],"type":"Point"}
}