{
  "type": "Feature",
  "properties": {
    "iso:country":"CH",
    "sg:address":"Kirchgasse 13",
    "sg:city":"K\u00f6lliken",
    "sg:orig_category":"Blumen U Zierpflanzenbau Detailhandel mit Blumen U Pflanzen",
    "sg:phone":"+41 62 723 22 40",
    "sg:postcode":"5742",
    "sg:province":"Aargau",
    "wof:name":"Blumen Jost",
    "wof:placetype":"venue"
},
  "geometry": {"coordinates":[8.027188,47.335747],"type":"Point"}
}