{
  "type": "Feature",
  "properties": {
    "iso:country":"CH",
    "sg:address":"Saint-jean Rue De 67 1201 Gen\u00e8ve. Postfach",
    "sg:city":"Gen\u00e8ve",
    "sg:orig_category":"Interessenvertretungen",
    "sg:postcode":"1201",
    "sg:province":"Gen\u00e8ve",
    "wof:name":"Institut D'etudes Immobili\u00e8res",
    "wof:placetype":"venue"
},
  "geometry": {"coordinates":[6.13813591,46.2065467834],"type":"Point"}
}