{
  "type": "Feature",
  "properties": {
    "iso:country":"CH",
    "sg:address":"Z\u00fcrcherstrasse 64",
    "sg:city":"Dietikon",
    "sg:orig_category":"Druckgewerbe",
    "sg:phone":"+41 17403202",
    "sg:postcode":"8953",
    "sg:province":"Z\u00fcrich",
    "wof:name":"Druckerei Markus Hummel + Co.",
    "wof:placetype":"venue"
},
  "geometry": {"coordinates":[8.4049091339,47.4029502869],"type":"Point"}
}