{
  "type": "Feature",
  "properties": {
    "iso:country":"CH",
    "sg:address":"M\u00fchlegasse 18 4410 Liestal. Postfach",
    "sg:city":"Liestal",
    "sg:orig_category":"Detailhandel mit Radio U Fernsehger\u00e4ten Elektroinstallation",
    "sg:phone":"+41 61 921 22 44",
    "sg:postcode":"4410",
    "sg:province":"Basel-Landschaft",
    "wof:name":"Rechsteiner Ag",
    "wof:placetype":"venue"
},
  "geometry": {"coordinates":[7.7339949608,47.4842529297],"type":"Point"}
}