{
  "type": "Feature",
  "properties": {
    "iso:country":"CH",
    "sg:address":"Bahnhofstr. 5 2500 Biel/bienne. Postfach",
    "sg:city":"Biel/bienne",
    "sg:orig_category":"Pensionskassen",
    "sg:postcode":"2501",
    "sg:province":"Bern",
    "wof:name":"Personal-f\u00fcrsorgestiftung Von Bolliger Hans",
    "wof:placetype":"venue"
},
  "geometry": {"coordinates":[8.6053848267,47.3045959473],"type":"Point"}
}