{
  "type": "Feature",
  "properties": {
    "iso:country":"CH",
    "sg:address":"Arnold B\u00f6cklin-strasse 15",
    "sg:city":"Basel",
    "sg:orig_category":"Herstellung von medizinischen U chirurgischen Ger\u00e4ten sowie orthop\u00e4dischen Vorrichtungen",
    "sg:postcode":"4051",
    "sg:province":"Basel-Stadt",
    "wof:name":"Verein F\u00fcr Orthop\u00e4die-traumatologie Im Laniado Hospital In Nethanya",
    "wof:placetype":"venue"
},
  "geometry": {"coordinates":[7.5784850121,47.5512161255],"type":"Point"}
}