{
  "type": "Feature",
  "properties": {
    "addr:full":"Rue Hoffmann 5 Gen\u00e8ve Gen\u00e8ve 1202",
    "addr:housenumber":"5",
    "addr:postcode":"1202",
    "addr:street":"Rue Hoffmann",
    "iso:country":"CH",
    "sg:address":"Rue Hoffmann 5",
    "sg:city":"Gen\u00e8ve",
    "sg:orig_category":"Datenverarbeitungsdienste",
    "sg:phone":"+41 22 733 59 18",
    "sg:postcode":"1202",
    "sg:province":"Gen\u00e8ve",
    "wof:name":"Pascal Barre Informatique",
    "wof:placetype":"venue"
},
  "geometry": {"coordinates":[6.12973,46.214539],"type":"Point"}
}