{
  "type": "Feature",
  "properties": {
    "iso:country":"CH",
    "sg:address":"Bahnhofstrasse 23",
    "sg:city":"Romanshorn",
    "sg:orig_category":"Markt U Meinungsforschung",
    "sg:postcode":"8590",
    "sg:province":"Thurgau",
    "wof:name":"Haris Marketing Schmollinger",
    "wof:placetype":"venue"
},
  "geometry": {"coordinates":[9.3731603622,47.5657958984],"type":"Point"}
}