{
  "type": "Feature",
  "properties": {
    "iso:country":"CH",
    "sg:address":"Neuhor\u00fcti 7",
    "sg:city":"Wolhusen",
    "sg:orig_category":"Bauschreinerei",
    "sg:phone":"+41 62 726 22 52",
    "sg:postcode":"6110",
    "sg:province":"Luzern",
    "wof:name":"Josef Brunner Schreinerei",
    "wof:placetype":"venue"
},
  "geometry": {"coordinates":[8.107488,47.263016],"type":"Point"}
}