{
  "type": "Feature",
  "properties": {
    "iso:country":"CH",
    "sg:address":"Buchenweg 12",
    "sg:city":"Sarmenstorf",
    "sg:orig_category":"Herstellung von Konstruktionsteilen, Fertigbauteilen U Ausbauelementen aus Holz",
    "sg:phone":"+41 56 667 46 40",
    "sg:postcode":"5614",
    "sg:province":"Aargau",
    "wof:name":"Saxer Guido Ag",
    "wof:placetype":"venue"
},
  "geometry": {"coordinates":[8.253534317,47.3157577515],"type":"Point"}
}