{
  "type": "Feature",
  "properties": {
    "iso:country":"CH",
    "sg:address":"Industriestrasse 16 4222 Zwingen. Postfach 512",
    "sg:city":"Laufen",
    "sg:orig_category":"Fachdetailhandel in Verkaufsr\u00e4umen Sonstiger Fachdetailhandel in Verkaufsr\u00e4umen",
    "sg:phone":"+41 61 761 14 14",
    "sg:postcode":"4242",
    "sg:province":"Basel-Landschaft",
    "wof:name":"Marken-m\u00fcller Ag",
    "wof:placetype":"venue"
},
  "geometry": {"coordinates":[7.5129108429,47.4294891357],"type":"Point"}
}