{
  "type": "Feature",
  "properties": {
    "iso:country":"CH",
    "sg:address":"Chamerstrasse 172 6300 Zug. Postfach",
    "sg:city":"Cham",
    "sg:orig_category":"Markt U Meinungsforschung",
    "sg:postcode":"6330",
    "sg:province":"Zug",
    "wof:name":"Felder Marketingberatung",
    "wof:placetype":"venue"
},
  "geometry": {"coordinates":[8.4854402542,47.1810264587],"type":"Point"}
}