{
  "type": "Feature",
  "properties": {
    "iso:country":"CH",
    "sg:address":"Rue Du Pont 12",
    "sg:city":"Montreux",
    "sg:orig_category":"Herstellung von Dauerbackwaren",
    "sg:postcode":"1820",
    "sg:province":"Vaud",
    "wof:name":"Amez-droz A.",
    "wof:placetype":"venue"
},
  "geometry": {"coordinates":[6.9166312218,46.4338188171],"type":"Point"}
}