{
  "type": "Feature",
  "properties": {
    "iso:country":"CH",
    "sg:address":"Rainstrasse 48",
    "sg:city":"Safnern",
    "sg:orig_category":"Fussreflexzonenmassage",
    "sg:phone":"+41 32 355 31 73",
    "sg:postcode":"2553",
    "sg:province":"Bern",
    "wof:name":"Ilka Nopper Fussreflexzonen-massage",
    "wof:placetype":"venue"
},
  "geometry": {"coordinates":[7.3163790703,47.1467208862],"type":"Point"}
}