{
  "type": "Feature",
  "properties": {
    "iso:country":"CH",
    "sg:address":"Frutigenstrasse 25",
    "sg:city":"Thun",
    "sg:orig_category":"RESTAURANTS: TEA-ROOMS",
    "sg:phone":"+41 33 222 31 37",
    "sg:postcode":"3600",
    "sg:province":"Bern",
    "wof:name":"Seefeld Gastro Thun Gmbh",
    "wof:placetype":"venue"
},
  "geometry": {"coordinates":[7.62733078,46.7525291443],"type":"Point"}
}