{
  "type": "Feature",
  "properties": {
    "addr:full":"Artherstrasse 1a 6318 Walchwil. Postfach 125 Walchwil Zug 6318",
    "addr:housenumber":"1a;125",
    "addr:postcode":"6318 walchwil.;6318",
    "addr:street":"Artherstrasse;Postfach;Zug",
    "iso:country":"CH",
    "sg:address":"Artherstrasse 1a 6318 Walchwil. Postfach 125",
    "sg:city":"Walchwil",
    "sg:orig_category":"Detailhandel mit Blumen U Pflanzen",
    "sg:phone":"+41 41 758 00 50",
    "sg:postcode":"6318",
    "sg:province":"Zug",
    "wof:name":"Silvia Camenzind Blumen La Luna",
    "wof:placetype":"venue"
},
  "geometry": {"coordinates":[8.513656,47.099339],"type":"Point"}
}