{
  "type": "Feature",
  "properties": {
    "iso:country":"CH",
    "sg:address":"M\u00e4rtmattenstrasse 3 3930 Visp. Postfach",
    "sg:city":"Visp",
    "sg:orig_category":"Architekturb\u00fcros",
    "sg:phone":"+41 71 223 49 76",
    "sg:postcode":"3930",
    "sg:province":"Valais",
    "wof:name":"P. & J. Diethelm-grauer Architekturb\u00fcro",
    "wof:placetype":"venue"
},
  "geometry": {"coordinates":[9.369556,47.420574],"type":"Point"}
}