{
  "type": "Feature",
  "properties": {
    "iso:country":"CH",
    "sg:address":"Weissensteinstrasse 20",
    "sg:city":"Burgdorf",
    "sg:orig_category":"Interessenvertretungen",
    "sg:postcode":"3400",
    "sg:province":"Bern",
    "wof:name":"Prediger-witwen Und Waisenkasse Von Burgdorf",
    "wof:placetype":"venue"
},
  "geometry": {"coordinates":[7.6150250435,47.0571022034],"type":"Point"}
}