{
  "type": "Feature",
  "properties": {
    "iso:country":"CH",
    "sg:address":"Zameia",
    "sg:city":"Vals",
    "sg:orig_category":"Grosshandel mit lebenden Tieren Herstellung von Bereifungen",
    "sg:phone":"+41 81 935 12 50",
    "sg:postcode":"7132",
    "sg:province":"Graubunden",
    "wof:name":"Anton T\u00f6nz Viehhandel",
    "wof:placetype":"venue"
},
  "geometry": {"coordinates":[9.1819067001,46.6187324524],"type":"Point"}
}