{
  "type": "Feature",
  "properties": {
    "addr:full":"4242 Laufen Basel-Landschaft 4242",
    "addr:housenumber":"4242",
    "addr:postcode":"4242",
    "addr:street":"Laufen Basel-Landschaft",
    "iso:country":"CH",
    "sg:address":"4242",
    "sg:city":"Laufen",
    "sg:orig_category":"Bauspenglerei Sanit\u00e4rinstallation",
    "sg:phone":"+41 31 331 36 56",
    "sg:postcode":"4242",
    "sg:province":"Basel-Landschaft",
    "wof:name":"Werner Soltermann Sanit\u00e4r-heizung-spenglerei",
    "wof:placetype":"venue"
},
  "geometry": {"coordinates":[7.453917,46.963104],"type":"Point"}
}