{
  "type": "Feature",
  "properties": {
    "iso:country":"CH",
    "sg:address":"Alfred Escher-strasse 17",
    "sg:city":"Z\u00fcrich",
    "sg:classifiers":[
        {
            "category":"Professional",
            "subcategory":"Employment Agencies",
            "type":"Services"
        }
    ],
    "sg:phone":"+41 12116173",
    "sg:postcode":"8001",
    "sg:province":"Z\u00fcrich",
    "sg:tags":[
        "personal",
        "u",
        "stellenvermittlung"
    ],
    "wof:name":"A. Hagmann & P. Butti Stellenvermittll. Rio-select",
    "wof:placetype":"venue"
},
  "geometry": {"coordinates":[8.5395498276,47.3770599365],"type":"Point"}
}