{
  "type": "Feature",
  "properties": {
    "iso:country":"CH",
    "sg:address":"Hardturmstrasse 169 8005 Z\u00fcrich. Postfach",
    "sg:city":"Z\u00fcrich",
    "sg:orig_category":"Erbringung von Dienstleistungen f\u00fcr Unternehmen",
    "sg:phone":"+41 71 744 20 44",
    "sg:postcode":"8001",
    "sg:province":"Z\u00fcrich",
    "wof:name":"Karriere Expo (schweiz) Ag",
    "wof:placetype":"venue"
},
  "geometry": {"coordinates":[9.6351919174,47.4310073853],"type":"Point"}
}