{
  "type": "Feature",
  "properties": {
    "iso:country":"CH",
    "sg:address":"Haldenstrasse 5 6340 Baar. Postfach",
    "sg:city":"Baar",
    "sg:orig_category":"Sonstiges Verlagsgewerbe",
    "sg:postcode":"6340",
    "sg:province":"Zug",
    "wof:name":"Creative Verlag Brigitte Umberg",
    "wof:placetype":"venue"
},
  "geometry": {"coordinates":[8.8205776215,47.1895294189],"type":"Point"}
}