{
  "type": "Feature",
  "properties": {
    "iso:country":"CH",
    "sg:address":"Crespera Via 78",
    "sg:city":"Breganzona",
    "sg:orig_category":"Handel mit Automobilen",
    "sg:postcode":"6932",
    "sg:province":"Ticino",
    "wof:name":"M\u00fcwi Autohandel M\u00fcller & Widmer",
    "wof:placetype":"venue"
},
  "geometry": {"coordinates":[8.9731235504,47.4651374817],"type":"Point"}
}