{
  "type": "Feature",
  "properties": {
    "iso:country":"CH",
    "sg:address":"Bahnhofstrasse 20",
    "sg:city":"Burgdorf",
    "sg:orig_category":"Detailhandel mit Uhren U Schmuck Fachdetailhandel in Verkaufsr\u00e4umen",
    "sg:phone":"+41 34 422 53 84",
    "sg:postcode":"3400",
    "sg:province":"Bern",
    "wof:name":"Max Lauener Uhren Schmuck",
    "wof:placetype":"venue"
},
  "geometry": {"coordinates":[7.6224370003,47.0605201721],"type":"Point"}
}