{
  "type": "Feature",
  "properties": {
    "iso:country":"CH",
    "sg:address":"Le Bugnonet",
    "sg:city":"Cr\u00e9suz",
    "sg:orig_category":"Markt U Meinungsforschung",
    "sg:phone":"+41 26 927 26 16",
    "sg:postcode":"1653",
    "sg:province":"Fribourg",
    "wof:name":"Flexxe Consultancy, Bruyneel Nancy",
    "wof:placetype":"venue"
},
  "geometry": {"coordinates":[7.1416501999,46.6203956604],"type":"Point"}
}