{
  "type": "Feature",
  "properties": {
    "iso:country":"CH",
    "sg:address":"Im Hof 11",
    "sg:city":"Gipf-oberfrick",
    "sg:orig_category":"RESTAURANTS: TEA-ROOMS",
    "sg:postcode":"5073",
    "sg:province":"Aargau",
    "wof:name":"Maurer Gastronomie",
    "wof:placetype":"venue"
},
  "geometry": {"coordinates":[7.9960107803,47.4938850403],"type":"Point"}
}