{
  "type": "Feature",
  "properties": {
    "iso:country":"CH",
    "sg:address":"Ohne Dom.",
    "sg:city":"Glarus",
    "sg:orig_category":"Non-Classified Establishments",
    "sg:postcode":"8750",
    "sg:province":"Glarus",
    "wof:name":"Teamco-invest Ag",
    "wof:placetype":"venue"
},
  "geometry": {"coordinates":[9.0680904388,47.0399703979],"type":"Point"}
}