{
  "type": "Feature",
  "properties": {
    "iso:country":"CH",
    "sg:address":"Mattenstrasse 137",
    "sg:city":"Biel/bienne",
    "sg:orig_category":"Herstellung von Ger\u00e4ten der Elektrizit\u00e4tserzeugung, -verteilung u.\u00e4. -Herstellung von Mess U Kontrol",
    "sg:phone":"+41 55 246 47 47",
    "sg:postcode":"2503",
    "sg:province":"Bern",
    "wof:name":"Flexum Messtechnik Ag",
    "wof:placetype":"venue"
},
  "geometry": {"coordinates":[8.9338798523,47.278301239],"type":"Point"}
}