{
  "type": "Feature",
  "properties": {
    "iso:country":"CH",
    "sg:address":"Reutenenstrasse 32",
    "sg:city":"Frauenfeld",
    "sg:orig_category":"Mit dem Versicherungsgewerbe verbundene T\u00e4tigkeiten",
    "sg:postcode":"8500",
    "sg:province":"Thurgau",
    "wof:name":"Dynamis Versicherungs Und Anlageberatungs Ag",
    "wof:placetype":"venue"
},
  "geometry": {"coordinates":[8.9023513794,47.5522499084],"type":"Point"}
}