{
  "type": "Feature",
  "properties": {
    "iso:country":"CH",
    "sg:address":"Freiburgstrasse 384",
    "sg:city":"Bern",
    "sg:orig_category":"Herstellung von Verbrennungsmotoren U Turbinen ohne Motoren f\u00fcr Luft U Strassenfahrzeuge Herstellung",
    "sg:phone":"+41 21 635 63 41",
    "sg:postcode":"3018",
    "sg:province":"Bern",
    "wof:name":"Sauter Building Control Schweiz Sa",
    "wof:placetype":"venue"
},
  "geometry": {"coordinates":[6.5861711502,46.5446662903],"type":"Point"}
}