{
  "type": "Feature",
  "properties": {
    "iso:country":"CH",
    "sg:address":"General-guisanstrasse 39",
    "sg:city":"Interlaken",
    "sg:orig_category":"Sportvereine Wassersport Segeln",
    "sg:phone":"+41 19106454",
    "sg:postcode":"3800",
    "sg:province":"Bern",
    "wof:name":"See-club K\u00fcsnacht",
    "wof:placetype":"venue"
},
  "geometry": {"coordinates":[8.5791940689,47.3153839111],"type":"Point"}
}