{
  "type": "Feature",
  "properties": {
    "iso:country":"CH",
    "sg:address":"Dorfstrasse 12",
    "sg:city":"Selzach",
    "sg:orig_category":"Detailhandel mit Brot, Back U S\u00fcsswaren Detailhandel mit Waren verschiedener Art, Hauptrichtung Nahr",
    "sg:phone":"+41 32 641 10 49",
    "sg:postcode":"2545",
    "sg:province":"Solothurn",
    "wof:name":"Kolb-kocher, Fritz.",
    "wof:placetype":"venue"
},
  "geometry": {"coordinates":[7.455439,47.20451],"type":"Point"}
}