{
  "type": "Feature",
  "properties": {
    "iso:country":"CH",
    "sg:address":"Hauptgasse 25",
    "sg:city":"Morat",
    "sg:orig_category":"Interessenvertretungen Sonstige Institutionen des Sozialwesens ohne Beherbergung",
    "sg:phone":"+41 26 672 11 77",
    "sg:postcode":"3280",
    "sg:province":"Fribourg",
    "wof:name":"Impuls Seebezirk",
    "wof:placetype":"venue"
},
  "geometry": {"coordinates":[7.1170959473,46.9283103943],"type":"Point"}
}