{
  "type": "Feature",
  "properties": {
    "iso:country":"CH",
    "sg:address":"Zentrum Fangh\u00f6fli 4 6014 Littau. Postfach 10",
    "sg:city":"Littau",
    "sg:orig_category":"Grosshandel mit M\u00f6beln, Wohnbedarf, Teppichen U Bodenbel\u00e4gen Grosshandel mit Textilien",
    "sg:phone":"+41 41 250 83 83",
    "sg:postcode":"6014",
    "sg:province":"Luzern",
    "wof:name":"Glm Novitas Gmbh",
    "wof:placetype":"venue"
},
  "geometry": {"coordinates":[8.2610559464,47.0491065979],"type":"Point"}
}