{
  "type": "Feature",
  "properties": {
    "iso:country":"CH",
    "sg:address":"Eaux-vives Rue Des 8 1207 Gen\u00e8ve. Postfach",
    "sg:city":"Gen\u00e8ve",
    "sg:orig_category":"RESTAURANTS: TEA-ROOMS",
    "sg:postcode":"1207",
    "sg:province":"Gen\u00e8ve",
    "wof:name":"Sengul Hasan",
    "wof:placetype":"venue"
},
  "geometry": {"coordinates":[6.1665759087,46.2005958557],"type":"Point"}
}