{
  "type": "Feature",
  "properties": {
    "iso:country":"CH",
    "sg:address":"Via Battaglini",
    "sg:city":"Tesserete",
    "sg:orig_category":"Grosshandel mit Eisenwaren sowie Installationsbedarf f\u00fcr Gas, Wasser U Heizung",
    "sg:postcode":"6950",
    "sg:province":"Ticino",
    "wof:name":"So-va-bad Di Zoppellari D.",
    "wof:placetype":"venue"
},
  "geometry": {"coordinates":[8.9695138931,46.0674934387],"type":"Point"}
}