{
  "type": "Feature",
  "properties": {
    "addr:full":"Unterdorfstrasse 37 D\u00e4niken Solothurn 4658",
    "addr:housenumber":"37",
    "addr:postcode":"4658",
    "addr:street":"Unterdorfstrasse;Solothurn",
    "iso:country":"CH",
    "sg:address":"Unterdorfstrasse 37",
    "sg:city":"D\u00e4niken",
    "sg:orig_category":"Cleaning, Disinfecting And Degreasing Agents",
    "sg:phone":"+41 62 288 11 11",
    "sg:postcode":"4658",
    "sg:province":"Solothurn",
    "wof:name":"Winoil Ag",
    "wof:placetype":"venue"
},
  "geometry": {"coordinates":[7.973185,47.355438],"type":"Point"}
}