{
  "type": "Feature",
  "properties": {
    "iso:country":"CH",
    "sg:address":"Baarerstrasse 14",
    "sg:city":"Zug",
    "sg:orig_category":"Softwareentwicklung U beratung",
    "sg:postcode":"6300",
    "sg:province":"Zug",
    "wof:name":"Financial Software House Zug Ag",
    "wof:placetype":"venue"
},
  "geometry": {"coordinates":[8.5166511536,47.1720809937],"type":"Point"}
}