{
  "type": "Feature",
  "properties": {
    "iso:country":"CH",
    "sg:address":"Bruggstrasse 8",
    "sg:city":"Thalwil",
    "sg:orig_category":"Detailhandel mit Textilien Grosshandel mit Textilien",
    "sg:postcode":"8800",
    "sg:province":"Z\u00fcrich",
    "wof:name":"Korber Franz Textilien",
    "wof:placetype":"venue"
},
  "geometry": {"coordinates":[8.5761241913,47.2819900513],"type":"Point"}
}