{
  "type": "Feature",
  "properties": {
    "iso:country":"CH",
    "sg:address":"Buchholzstrasse 61a",
    "sg:city":"Thun",
    "sg:orig_category":"Erwachsenenbildung U Unterricht",
    "sg:phone":"+41 33 336 58 10",
    "sg:postcode":"3604",
    "sg:province":"Bern",
    "wof:name":"Beat Zimmermann",
    "wof:placetype":"venue"
},
  "geometry": {"coordinates":[7.6130051613,46.7371673584],"type":"Point"}
}