{
  "type": "Feature",
  "properties": {
    "iso:country":"CH",
    "sg:address":"Chili Route Du 2 1870 Monthey. Postfach",
    "sg:city":"Monthey",
    "sg:orig_category":"Mineralquellen, Herstellung von alkoholfreien Getr\u00e4nken",
    "sg:postcode":"1870",
    "sg:province":"Valais",
    "wof:name":"Fgo Saporis, Mouthon & Cie Boissons Alcoolis\u00e9es, Notamm. \u00e0 Base D'agrumes; Production, Diffusion",
    "wof:placetype":"venue"
},
  "geometry": {"coordinates":[6.9471468925,46.2516288757],"type":"Point"}
}