{
  "type": "Feature",
  "properties": {
    "addr:full":"Rue Neuve 1 Ste-croix Vaud 1450",
    "addr:housenumber":"1",
    "addr:postcode":"1450",
    "addr:street":"Rue Neuve",
    "iso:country":"CH",
    "sg:address":"Rue Neuve 1",
    "sg:city":"Ste-croix",
    "sg:classifiers":[
        {
            "category":"Bars & Pubs",
            "type":"Food & Drink"
        }
    ],
    "sg:postcode":"1450",
    "sg:province":"Vaud",
    "wof:name":"Lombardo Paolo Et Maryse",
    "wof:placetype":"venue"
},
  "geometry": {"coordinates":[6.501463,46.82325],"type":"Point"}
}