{
  "type": "Feature",
  "properties": {
    "iso:country":"CH",
    "sg:address":"Chemin De Platton 17",
    "sg:city":"Troinex",
    "sg:orig_category":"Unclassifiable Establishments",
    "sg:phone":"+41 41 850 48 78",
    "sg:postcode":"1256",
    "sg:province":"Gen\u00e8ve",
    "wof:name":"Widmer Louis Holding Ag",
    "wof:placetype":"venue"
},
  "geometry": {"coordinates":[8.4368066788,47.0692977905],"type":"Point"}
}