{
  "type": "Feature",
  "properties": {
    "iso:country":"CH",
    "sg:address":"Florenz-strasse 7",
    "sg:city":"Basel",
    "sg:classifiers":[
        {
            "category":"Airport",
            "subcategory":"International",
            "type":"Transportation"
        }
    ],
    "sg:phone":"+41 61 333 03 30",
    "sg:postcode":"4053",
    "sg:province":"Basel-Stadt",
    "sg:tags":[
        "transport"
    ],
    "wof:name":"Celtra Ag",
    "wof:placetype":"venue"
},
  "geometry": {"coordinates":[7.6084570885,47.5363883972],"type":"Point"}
}