{
  "type": "Feature",
  "properties": {
    "iso:country":"CH",
    "sg:address":"4124",
    "sg:city":"Sch\u00f6nenbuch",
    "sg:orig_category":"Verwertung von Milch",
    "sg:postcode":"4124",
    "sg:province":"Basel-Landschaft",
    "wof:name":"Milch Und Landwirtschaftliche Konsumgenossenschaft 4347 Wil Ag",
    "wof:placetype":"venue"
},
  "geometry": {"coordinates":[8.1511602402,47.5611495972],"type":"Point"}
}