{
  "type": "Feature",
  "properties": {
    "iso:country":"CH",
    "sg:address":"Route De La Gl\u00e2ne 9b",
    "sg:city":"Fribourg",
    "sg:orig_category":"Verlegen von Fliesen U Platten",
    "sg:phone":"+41 26 322 35 68",
    "sg:postcode":"1700",
    "sg:province":"Fribourg",
    "wof:name":"Pascal Aebischer A.p. Carrelages",
    "wof:placetype":"venue"
},
  "geometry": {"coordinates":[7.1457409859,46.7963676453],"type":"Point"}
}