{
  "type": "Feature",
  "properties": {
    "iso:country":"CH",
    "sg:address":"Marktgasse 12",
    "sg:city":"Baar",
    "sg:orig_category":"Detailhandel mit Spielwaren Herstellung von Spielwaren",
    "sg:phone":"+41 71 277 41 39",
    "sg:postcode":"6340",
    "sg:province":"Zug",
    "wof:name":"Neule Grossbahn Neuweiler",
    "wof:placetype":"venue"
},
  "geometry": {"coordinates":[9.3191003799,47.4219245911],"type":"Point"}
}