{
  "type": "Feature",
  "properties": {
    "iso:country":"CH",
    "sg:address":"Unterdorfstrasse 23",
    "sg:city":"Dornach",
    "sg:classifiers":[
        {
            "category":"Structure",
            "subcategory":"Warehouse",
            "type":"Public Place"
        }
    ],
    "sg:phone":"+41 34 461 57 28",
    "sg:postcode":"4143",
    "sg:province":"Solothurn",
    "sg:tags":[
        "chiller",
        "air-conditioning",
        "system"
    ],
    "wof:name":"Adrian Leu Klimaanlagen-service",
    "wof:placetype":"venue"
},
  "geometry": {"coordinates":[7.628309,47.002251],"type":"Point"}
}