{
  "type": "Feature",
  "properties": {
    "iso:country":"CH",
    "sg:address":"S\u00fcdbahnhofstrasse 14c",
    "sg:city":"Bern",
    "sg:orig_category":"Organisationen des Gesundheitswesen",
    "sg:phone":"+41 34 402 12 60",
    "sg:postcode":"3007",
    "sg:province":"Bern",
    "wof:name":"Lungenliga Bern,beratungsst. F\u00fcr Lungen-& Langzeitkranke",
    "wof:placetype":"venue"
},
  "geometry": {"coordinates":[7.757589817,46.9491271973],"type":"Point"}
}