{
  "type": "Feature",
  "properties": {
    "iso:country":"CH",
    "sg:address":"Rubigenstrasse 35",
    "sg:city":"Belp",
    "sg:orig_category":"RESTAURANTS: TEA-ROOMS Vermittlung von Immobilien",
    "sg:phone":"+41 31 961 30 74",
    "sg:postcode":"3123",
    "sg:province":"Bern",
    "wof:name":"M\u00fcller & M\u00fcller",
    "wof:placetype":"venue"
},
  "geometry": {"coordinates":[7.501955986,46.8926811218],"type":"Point"}
}