{
  "type": "Feature",
  "properties": {
    "iso:country":"CH",
    "sg:address":"T\u00fcrrmatt 320",
    "sg:city":"Oeschgen",
    "sg:orig_category":"Grosshandel mit Eisenwaren sowie Installationsbedarf f\u00fcr Gas, Wasser U Heizung Grosshandel mit Getr\u00e4",
    "sg:phone":"+41 62 871 20 00",
    "sg:postcode":"5072",
    "sg:province":"Aargau",
    "wof:name":"Jolicave-frigolux Weinlagerspezialisten",
    "wof:placetype":"venue"
},
  "geometry": {"coordinates":[8.0196313858,47.5169334412],"type":"Point"}
}