{
  "type": "Feature",
  "properties": {
    "iso:country":"CH",
    "sg:address":"Kanonengasse 37",
    "sg:city":"Basel",
    "sg:orig_category":"Massagestudios",
    "sg:phone":"+41 61 271 15 72",
    "sg:postcode":"4051",
    "sg:province":"Basel-Stadt",
    "wof:name":"Yves Greder Sportmassagen",
    "wof:placetype":"venue"
},
  "geometry": {"coordinates":[7.5849509239,47.5529823303],"type":"Point"}
}