{
  "type": "Feature",
  "properties": {
    "iso:country":"CH",
    "sg:address":"Stockackerstrasse 1",
    "sg:city":"Kehrsatz",
    "sg:orig_category":"Fussreflexzonenmassage",
    "sg:phone":"+41 31 961 18 66",
    "sg:postcode":"3122",
    "sg:province":"Bern",
    "wof:name":"Silvia Kleiner Fussreflexzonen-massage",
    "wof:placetype":"venue"
},
  "geometry": {"coordinates":[7.4692311287,46.9169807434],"type":"Point"}
}