{
  "type": "Feature",
  "properties": {
    "iso:country":"CH",
    "sg:address":"Rue Port-roulant 6",
    "sg:city":"Neuch\u00e2tel",
    "sg:orig_category":"Schulpflegen",
    "sg:phone":"+41 32 730 48 46",
    "sg:postcode":"2000",
    "sg:province":"Neuch\u00e2tel",
    "wof:name":"Commission Scolaire De L'\u00e9cole Second.r\u00e9gion.m.henri Rivier",
    "wof:placetype":"venue"
},
  "geometry": {"coordinates":[6.9121890068,46.9857063293],"type":"Point"}
}