{
  "type": "Feature",
  "properties": {
    "iso:country":"CH",
    "sg:address":"Moosmattstrasse 6 8953 Dietikon. Postfach 762",
    "sg:city":"Dietikon",
    "sg:orig_category":"Handelsvermittlung U Grosshandel Herstellung von Hebezeugen U F\u00f6rdermitteln",
    "sg:phone":"+41 19327017",
    "sg:postcode":"8953",
    "sg:province":"Z\u00fcrich",
    "wof:name":"Intratrade Ag",
    "wof:placetype":"venue"
},
  "geometry": {"coordinates":[8.7789669037,47.3110771179],"type":"Point"}
}