{
  "type": "Feature",
  "properties": {
    "iso:country":"CH",
    "sg:address":"Spilchb\u00fchl 1 8342 Wernetshausen. Postfach",
    "sg:city":"Wernetshausen",
    "sg:orig_category":"Softwareentwicklung U beratung",
    "sg:postcode":"8342",
    "sg:province":"Z\u00fcrich",
    "wof:name":"Ingenieurb\u00fcro Brand Ibb",
    "wof:placetype":"venue"
},
  "geometry": {"coordinates":[7.4303832054,46.924156189],"type":"Point"}
}