{
  "type": "Feature",
  "properties": {
    "iso:country":"CH",
    "sg:address":"Finkernweg 4",
    "sg:city":"Kreuzlingen",
    "sg:orig_category":"Betrieb von Taxis",
    "sg:phone":"+41 800 822 777",
    "sg:postcode":"8280",
    "sg:province":"Thurgau",
    "wof:name":"Taxi-zentrale St.gallen 111 Gmbh",
    "wof:placetype":"venue"
},
  "geometry": {"coordinates":[9.37301,47.424591],"type":"Point"}
}