{
  "type": "Feature",
  "properties": {
    "iso:country":"CH",
    "sg:address":"Bahnhofstrasse 64",
    "sg:city":"Berikon",
    "sg:orig_category":"Schreib U \u00dcbersetzungsb\u00fcros",
    "sg:postcode":"8965",
    "sg:province":"Aargau",
    "wof:name":"Translavia Ivan Vanek Dipl. Ing.",
    "wof:placetype":"venue"
},
  "geometry": {"coordinates":[8.3699417114,47.3520698547],"type":"Point"}
}