{
  "type": "Feature",
  "properties": {
    "iso:country":"CH",
    "sg:address":"Rue Baudit 6",
    "sg:city":"Gen\u00e8ve",
    "sg:orig_category":"Arztpraxen",
    "sg:phone":"+41 22 734 18 28",
    "sg:postcode":"1201",
    "sg:province":"Gen\u00e8ve",
    "wof:name":"Dr M\u00e9d. Boris Radeff M\u00e9decin Sp\u00e9cialiste Fmh",
    "wof:placetype":"venue"
},
  "geometry": {"coordinates":[6.138545,46.210197],"type":"Point"}
}