{
  "type": "Feature",
  "properties": {
    "iso:country":"CH",
    "sg:address":"Aabachstrasse 5 6300 Zug. Postfach 857",
    "sg:city":"Zug",
    "sg:orig_category":"Arbeits\u00e4mter",
    "sg:phone":"+41 41 728 34 77",
    "sg:postcode":"6301",
    "sg:province":"Zug",
    "wof:name":"Kantonales Arbeitsamt",
    "wof:placetype":"venue"
},
  "geometry": {"coordinates":[8.511155,47.174458],"type":"Point"}
}