{
  "type": "Feature",
  "properties": {
    "iso:country":"CH",
    "sg:address":"Lacuez Chemin Du 43 1807 Blonay. Postfach",
    "sg:city":"Blonay",
    "sg:orig_category":"Allgemeiner Hoch U Tiefbau",
    "sg:postcode":"1807",
    "sg:province":"Vaud",
    "wof:name":"Longa Gebr\u00fcder",
    "wof:placetype":"venue"
},
  "geometry": {"coordinates":[9.816458,46.783833],"type":"Point"}
}