{
  "type": "Feature",
  "properties": {
    "iso:country":"CH",
    "sg:address":"Schwarzenbacherstrasse",
    "sg:city":"Mosen",
    "sg:classifiers":[
        {
            "category":"Restaurant",
            "type":"Food & Drink"
        }
    ],
    "sg:phone":"+41 41 917 14 02",
    "sg:postcode":"6295",
    "sg:province":"Luzern",
    "wof:name":"Restaurant Kreuz",
    "wof:placetype":"venue"
},
  "geometry": {"coordinates":[8.2237701416,47.2440452576],"type":"Point"}
}