{
  "type": "Feature",
  "properties": {
    "addr:full":"Rue Pierre Sciob\u00e9ret 43 Bulle Fribourg 1630",
    "addr:housenumber":"43",
    "addr:postcode":"1630",
    "addr:street":"Rue Pierre Sciobe\u0301Ret",
    "iso:country":"CH",
    "sg:address":"Rue Pierre Sciob\u00e9ret 43",
    "sg:city":"Bulle",
    "sg:orig_category":"Detailhandel mit Brot, Back U S\u00fcsswaren",
    "sg:phone":"+41 26 912 74 50",
    "sg:postcode":"1630",
    "sg:province":"Fribourg",
    "wof:name":"Claude Jolliet Boulangerie & P\u00e2tisserie",
    "wof:placetype":"venue"
},
  "geometry": {"coordinates":[7.054891,46.613144],"type":"Point"}
}