{
  "type": "Feature",
  "properties": {
    "iso:country":"CH",
    "sg:address":"1536",
    "sg:city":"Combremont-petit",
    "sg:orig_category":"RESTAURANTS: TEA-ROOMS",
    "sg:phone":"+41 27 207 12 43",
    "sg:postcode":"1536",
    "sg:province":"Vaud",
    "wof:name":"D\u00e9l\u00e8ze Jean-maurice.",
    "wof:placetype":"venue"
},
  "geometry": {"coordinates":[7.3364601135,46.1857681274],"type":"Point"}
}