{
  "type": "Feature",
  "properties": {
    "iso:country":"CH",
    "sg:address":"Rue Du Rafour 1",
    "sg:city":"St-aubin-sauges",
    "sg:orig_category":"Mechanik Schlossereien",
    "sg:phone":"+41 32 835 25 23",
    "sg:postcode":"2024",
    "sg:province":"Neuch\u00e2tel",
    "wof:name":"Willy Baud Serrurerie",
    "wof:placetype":"venue"
},
  "geometry": {"coordinates":[6.7778692245,46.8939704895],"type":"Point"}
}