{
  "type": "Feature",
  "properties": {
    "iso:country":"CH",
    "sg:address":"Gare Avenue De La 29 1003 Lausanne. Postfach",
    "sg:city":"Lausanne",
    "sg:orig_category":"Unclassifiable Establishments",
    "sg:postcode":"1003",
    "sg:province":"Vaud",
    "wof:name":"Verdoro Gmbh",
    "wof:placetype":"venue"
},
  "geometry": {"coordinates":[8.7298908234,47.2009048462],"type":"Point"}
}