{
  "type": "Feature",
  "properties": {
    "iso:country":"CH",
    "sg:address":"Eierbrechtstrasse 66 8053 Z\u00fcrich. Postfach",
    "sg:city":"Z\u00fcrich",
    "sg:orig_category":"Advokaturb\u00fcros",
    "sg:phone":"+41 13833000",
    "sg:postcode":"8053",
    "sg:province":"Z\u00fcrich",
    "wof:name":"Dr.walter Eigenmann Advokaturb\u00fcro",
    "wof:placetype":"venue"
},
  "geometry": {"coordinates":[8.578863,47.357216],"type":"Point"}
}