{
  "type": "Feature",
  "properties": {
    "iso:country":"CH",
    "sg:address":"Rue H.-f. Sandoz 62 Case Postale 84",
    "sg:city":"Tavannes",
    "sg:classifiers":[
        {
            "category":"Wholesale",
            "subcategory":"Machinery & Supplies",
            "type":"Manufacturing & Wholesale Goods"
        }
    ],
    "sg:phone":"+41 32 351 24 51",
    "sg:postcode":"2710",
    "sg:province":"Bern",
    "sg:tags":[
        "equipment",
        "equipement",
        "precision",
        "timekeeping"
    ],
    "wof:name":"Schwab-feller Ag",
    "wof:placetype":"venue"
},
  "geometry": {"coordinates":[7.3756260872,47.1376609802],"type":"Point"}
}