{
  "type": "Feature",
  "properties": {
    "iso:country":"CH",
    "sg:address":"Suhrenmatteng\u00e4ssli 8 5036 Oberentfelden. Postfach",
    "sg:city":"Oberentfelden",
    "sg:orig_category":"Verlagsgewerbe",
    "sg:phone":"+41 61 711 77 56",
    "sg:postcode":"5036",
    "sg:province":"Aargau",
    "wof:name":"Sonnseitig Leben",
    "wof:placetype":"venue"
},
  "geometry": {"coordinates":[7.5876030922,47.4912223816],"type":"Point"}
}