{
  "type": "Feature",
  "properties": {
    "iso:country":"CH",
    "sg:address":"Spitzwaldstrasse 215",
    "sg:city":"Allschwil",
    "sg:orig_category":"Detailhandel mit Schuhen",
    "sg:phone":"+41 61 481 16 17",
    "sg:postcode":"4123",
    "sg:province":"Basel-Landschaft",
    "wof:name":"Schuh-bazar Fricker Schuhe & Co",
    "wof:placetype":"venue"
},
  "geometry": {"coordinates":[7.5529527664,47.5470352173],"type":"Point"}
}