{
  "type": "Feature",
  "properties": {
    "iso:country":"CH",
    "sg:address":"Bernstrasse 38 4922 B\u00fctzberg. Postfach",
    "sg:city":"B\u00fctzberg",
    "sg:orig_category":"Unternehmensberatung",
    "sg:phone":"+41 62 963 04 91",
    "sg:postcode":"4922",
    "sg:province":"Bern",
    "wof:name":"Wyler Markus Wirtschaftsberatung",
    "wof:placetype":"venue"
},
  "geometry": {"coordinates":[7.7433300018,47.2141799927],"type":"Point"}
}