{
  "type": "Feature",
  "properties": {
    "iso:country":"CH",
    "sg:address":"M\u00e4ritgasse 4 3052 Zollikofen. Postfach",
    "sg:city":"Zollikofen",
    "sg:orig_category":"Sonstige mit der Informatik verbundene T\u00e4tigkeiten",
    "sg:postcode":"3052",
    "sg:province":"Bern",
    "wof:name":"Maricom Gmbh Edv; Dienstleistungen, Handel Usw.",
    "wof:placetype":"venue"
},
  "geometry": {"coordinates":[7.458717823,46.9967384338],"type":"Point"}
}