{
  "type": "Feature",
  "properties": {
    "iso:country":"CH",
    "sg:address":"Schulgasse 17",
    "sg:city":"Nidau",
    "sg:orig_category":"RESTAURANTS: TEA-ROOMS",
    "sg:phone":"+41 32 331 86 48",
    "sg:postcode":"2560",
    "sg:province":"Bern",
    "wof:name":"Bussolo B.",
    "wof:placetype":"venue"
},
  "geometry": {"coordinates":[7.2400212288,47.1244544983],"type":"Point"}
}