{
  "type": "Feature",
  "properties": {
    "iso:country":"CH",
    "sg:address":"Rue Du Ch\u00e2telard 28",
    "sg:city":"Peseux",
    "sg:orig_category":"Institutionen des Sozialwesens ohne Beherbergung Internationale Organisationen mit Beh\u00f6rdecharakter",
    "sg:phone":"+41 22 849 84 00",
    "sg:postcode":"2034",
    "sg:province":"Neuch\u00e2tel",
    "wof:name":"M\u00e9decins Sans Fronti\u00e8res",
    "wof:placetype":"venue"
},
  "geometry": {"coordinates":[6.1574859619,46.2039604187],"type":"Point"}
}