{
  "type": "Feature",
  "properties": {
    "iso:country":"CH",
    "sg:address":"Uhwieserstrasse 8",
    "sg:city":"Flurlingen",
    "sg:orig_category":"Bau von Strassen, Sportanlagen U Bahnverkehrsstrecken",
    "sg:postcode":"8247",
    "sg:province":"Z\u00fcrich",
    "wof:name":"Strabus Strassenbau-unternehmung Schaffhausen Ag, Zweigniederlassung Flurlingen",
    "wof:placetype":"venue"
},
  "geometry": {"coordinates":[8.630166,47.68214],"type":"Point"}
}