{
  "type": "Feature",
  "properties": {
    "iso:country":"CH",
    "sg:address":"Freiburgstrasse 38",
    "sg:city":"Courlevon",
    "sg:orig_category":"Non-Classified Establishments",
    "sg:postcode":"1795",
    "sg:province":"Fribourg",
    "wof:name":"China Restaurant Goldener Adler Gmbh",
    "wof:placetype":"venue"
},
  "geometry": {"coordinates":[7.1116948128,46.8910217285],"type":"Point"}
}