{
  "type": "Feature",
  "properties": {
    "iso:country":"CH",
    "sg:address":"Ausserdorfstrasse 9",
    "sg:city":"Seon",
    "sg:classifiers":[
        {
            "category":"Professional",
            "subcategory":"Employment Agencies",
            "type":"Services"
        }
    ],
    "sg:postcode":"5703",
    "sg:province":"Aargau",
    "sg:tags":[
        "personal",
        "u",
        "stellenvermittlung"
    ],
    "wof:name":"Schlegel + Meier",
    "wof:placetype":"venue"
},
  "geometry": {"coordinates":[8.1610908508,47.3419914246],"type":"Point"}
}