{
  "type": "Feature",
  "properties": {
    "iso:country":"CH",
    "sg:address":"Heimatstrasse 30 8645 Jona. Postfach",
    "sg:city":"Jona",
    "sg:orig_category":"Unclassifiable Establishments",
    "sg:postcode":"8645",
    "sg:province":"St. Gallen",
    "wof:name":"Mohn Kommunikation Netzwerkagentur F\u00fcr Integrierte Kommunikation. Public Relations, Marketing- U. Werbeberatung",
    "wof:placetype":"venue"
},
  "geometry": {"coordinates":[8.8349399567,47.2227592468],"type":"Point"}
}