{
  "type": "Feature",
  "properties": {
    "iso:country":"CH",
    "sg:address":"Olivenweg 38",
    "sg:city":"Bern",
    "sg:orig_category":"Sanit\u00e4r U Heizungsinstallation",
    "sg:phone":"+41 31 991 01 91",
    "sg:postcode":"3018",
    "sg:province":"Bern",
    "wof:name":"Wt Service Gmbh W\u00e4rmetauscherservice",
    "wof:placetype":"venue"
},
  "geometry": {"coordinates":[7.3878488541,46.9411735535],"type":"Point"}
}