{
  "type": "Feature",
  "properties": {
    "iso:country":"CH",
    "sg:address":"M\u00fclhauserstrasse 111",
    "sg:city":"Basel",
    "sg:orig_category":"Erbringung von Dienstleistungen f\u00fcr Unternehmen",
    "sg:phone":"+41 61 383 80 85",
    "sg:postcode":"4056",
    "sg:province":"Basel-Stadt",
    "wof:name":"Astro Life Astrologie Und Beratung",
    "wof:placetype":"venue"
},
  "geometry": {"coordinates":[7.57685709,47.5668792725],"type":"Point"}
}