{
  "type": "Feature",
  "properties": {
    "iso:country":"CH",
    "sg:address":"Wasserwerkgasse 2 3011 Bern. Postfach",
    "sg:city":"Bern",
    "sg:orig_category":"Architektur U Ingenieurb\u00fcros",
    "sg:phone":"+41 31 328 33 00",
    "sg:postcode":"3013",
    "sg:province":"Bern",
    "wof:name":"Ingenieurb\u00fcro Moser Beratung & Planung",
    "wof:placetype":"venue"
},
  "geometry": {"coordinates":[7.45796,46.947815],"type":"Point"}
}