{
  "type": "Feature",
  "properties": {
    "iso:country":"CH",
    "sg:address":"Schloss Sargans",
    "sg:city":"Sargans",
    "sg:orig_category":"Museen",
    "sg:phone":"+41 81 723 65 69",
    "sg:postcode":"7320",
    "sg:province":"St. Gallen",
    "wof:name":"Museum Sarganserland",
    "wof:placetype":"venue"
},
  "geometry": {"coordinates":[9.4374399185,47.0502510071],"type":"Point"}
}