{
  "type": "Feature",
  "properties": {
    "iso:country":"CH",
    "sg:address":"W\u00fclflingerstrasse 247 8408 Winterthur. Postfach 307",
    "sg:city":"Winterthur",
    "sg:orig_category":"Kantonalbanken",
    "sg:phone":"+41 19366767",
    "sg:postcode":"8408",
    "sg:province":"Z\u00fcrich",
    "wof:name":"Z\u00fcrcher Kantonalbank",
    "wof:placetype":"venue"
},
  "geometry": {"coordinates":[8.7609901428,47.3074913025],"type":"Point"}
}