{
  "type": "Feature",
  "properties": {
    "iso:country":"CH",
    "sg:address":"Safrangasse 2",
    "sg:city":"Schaffhausen",
    "sg:classifiers":[
        {
            "category":"Restaurant",
            "type":"Food & Drink"
        }
    ],
    "sg:phone":"+41 52 625 34 98",
    "sg:postcode":"8200",
    "sg:province":"Schaffhausen",
    "wof:name":"Restaurant Cuba Club",
    "wof:placetype":"venue"
},
  "geometry": {"coordinates":[8.6352701187,47.697101593],"type":"Point"}
}