{
  "type": "Feature",
  "properties": {
    "iso:country":"CH",
    "sg:address":"Chemin Du Basse Fin 190",
    "sg:city":"Courtema\u00eeche",
    "sg:orig_category":"Fachdetailhandel in Verkaufsr\u00e4umen Herstellung U Zusammensetzung von Uhren",
    "sg:phone":"+41 32 968 89 90",
    "sg:postcode":"2923",
    "sg:province":"Jura",
    "wof:name":"Montres Mirvaine S\u00e0rl",
    "wof:placetype":"venue"
},
  "geometry": {"coordinates":[6.83314991,47.1057701111],"type":"Point"}
}