{
  "type": "Feature",
  "properties": {
    "iso:country":"CH",
    "sg:address":"Haltingerstrasse 12",
    "sg:city":"Basel",
    "sg:orig_category":"Reiseb\u00fcros",
    "sg:phone":"+41 61 693 47 10",
    "sg:postcode":"4057",
    "sg:province":"Basel-Stadt",
    "wof:name":"Arabella Reiseb\u00fcro",
    "wof:placetype":"venue"
},
  "geometry": {"coordinates":[7.592373848,47.5654449463],"type":"Point"}
}