{
  "type": "Feature",
  "properties": {
    "iso:country":"CH",
    "sg:address":"Via Stazione 4",
    "sg:city":"Muralto",
    "sg:orig_category":"Detailhandel mit Uhren U Schmuck Reparatur von Uhren U Schmuck",
    "sg:phone":"+41 81 911 15 17",
    "sg:postcode":"6600",
    "sg:province":"Ticino",
    "wof:name":"Zoppi Inh.zoppi & Co Uhren & Juwelen",
    "wof:placetype":"venue"
},
  "geometry": {"coordinates":[9.2883176804,46.8262405396],"type":"Point"}
}