{
  "type": "Feature",
  "properties": {
    "iso:country":"CH",
    "sg:address":"Hofmattweg 29",
    "sg:city":"Balsthal",
    "sg:orig_category":"Sportvereine Velo Rad-& Motorfahrer-Bund SRB",
    "sg:phone":"+41 62 391 51 30",
    "sg:postcode":"4710",
    "sg:province":"Solothurn",
    "wof:name":"Vc Balsthal-klus Falkenstein",
    "wof:placetype":"venue"
},
  "geometry": {"coordinates":[7.7038068771,47.3190765381],"type":"Point"}
}