{
  "type": "Feature",
  "properties": {
    "iso:country":"CH",
    "sg:address":"Gotthardstrasse 104 6472 Erstfeld. Postfach 52",
    "sg:city":"Erstfeld",
    "sg:orig_category":"Non-Classified Establishments",
    "sg:phone":"+41 41 880 25 55",
    "sg:postcode":"6472",
    "sg:province":"Uri",
    "wof:name":"Spar-supermarkt, Niederberger Und Gisler",
    "wof:placetype":"venue"
},
  "geometry": {"coordinates":[8.6506071091,46.8213272095],"type":"Point"}
}