{
  "type": "Feature",
  "properties": {
    "iso:country":"CH",
    "sg:address":"Im Eich 13 5742 K\u00f6lliken. Postfach",
    "sg:city":"K\u00f6lliken",
    "sg:orig_category":"Reinigungsgewerbe",
    "sg:postcode":"5742",
    "sg:province":"Aargau",
    "wof:name":"Segessenmann R. Kaminfegermeister Und Feuerschauer",
    "wof:placetype":"venue"
},
  "geometry": {"coordinates":[8.0212869644,47.3262672424],"type":"Point"}
}