{
  "type": "Feature",
  "properties": {
    "iso:country":"CH",
    "sg:address":"Postplatz 2 3930 Visp. Postfach",
    "sg:city":"Visp",
    "sg:orig_category":"RESTAURANTS: TEA-ROOMS",
    "sg:postcode":"3930",
    "sg:province":"Valais",
    "wof:name":"Restaurant La Potini\u00e8re, Sevic Z.",
    "wof:placetype":"venue"
},
  "geometry": {"coordinates":[7.1454091072,46.3468284607],"type":"Point"}
}