{
  "type": "Feature",
  "properties": {
    "iso:country":"CH",
    "sg:address":"Hofstrasse 1 6004 Luzern. Postfach",
    "sg:city":"Luzern",
    "sg:orig_category":"Schreib U \u00dcbersetzungsb\u00fcros",
    "sg:postcode":"6003",
    "sg:province":"Luzern",
    "wof:name":"Apostroph Ag",
    "wof:placetype":"venue"
},
  "geometry": {"coordinates":[8.3107995987,47.0560760498],"type":"Point"}
}