{
  "type": "Feature",
  "properties": {
    "iso:country":"CH",
    "sg:address":"M\u00fcllerstrasse 23",
    "sg:city":"Z\u00fcrich",
    "sg:orig_category":"Unternehmensberatung",
    "sg:phone":"+41 19843844",
    "sg:postcode":"8004",
    "sg:province":"Z\u00fcrich",
    "wof:name":"Rohner It Consulting & Engineering",
    "wof:placetype":"venue"
},
  "geometry": {"coordinates":[8.5305833817,47.3743629456],"type":"Point"}
}