{
  "type": "Feature",
  "properties": {
    "iso:country":"CH",
    "sg:address":"St\u00e4dtlistrasse 14",
    "sg:city":"Ilanz",
    "sg:orig_category":"Grosshandel mit sonstigen Nahrungsmitteln Sonstiger Fachdetailhandel mit Nahrungsmitteln, Getr\u00e4nken ",
    "sg:phone":"+41 81 925 43 27",
    "sg:postcode":"7130",
    "sg:province":"Graubunden",
    "wof:name":"Reformhaus Itulanda",
    "wof:placetype":"venue"
},
  "geometry": {"coordinates":[9.2036924362,46.7733459473],"type":"Point"}
}