{
  "type": "Feature",
  "properties": {
    "iso:country":"CH",
    "sg:address":"Mon-repos Avenue 10 1005 Lausanne. Postfach",
    "sg:city":"Lausanne",
    "sg:orig_category":"Vermietung U Verpachtung von eigenen Immobilien",
    "sg:postcode":"1005",
    "sg:province":"Vaud",
    "wof:name":"Gexim, Martinet Gilbert Xavier Immeubles Etc",
    "wof:placetype":"venue"
},
  "geometry": {"coordinates":[6.6397280693,46.5192260742],"type":"Point"}
}