{
  "type": "Feature",
  "properties": {
    "iso:country":"CH",
    "sg:address":"St\u00e4pfetlistrasse 5",
    "sg:city":"Werrikon",
    "sg:classifiers":[
        {
            "category":"Transit Center",
            "subcategory":"Freight",
            "type":"Transportation"
        }
    ],
    "sg:phone":"+41 19057788",
    "sg:postcode":"8606",
    "sg:province":"Z\u00fcrich",
    "sg:tags":[
        "box",
        "stacking",
        "containers",
        "cleaning",
        "transport"
    ],
    "wof:name":"Contreag Ag",
    "wof:placetype":"venue"
},
  "geometry": {"coordinates":[8.700586,47.363167],"type":"Point"}
}