{
  "type": "Feature",
  "properties": {
    "iso:country":"CH",
    "sg:address":"Chemin Des Grands Champs 2 1033 Cheseaux-lausanne Case Postale 124",
    "sg:city":"Cheseaux-lausanne",
    "sg:orig_category":"Herstellung von Kunststoffwaren Sonstige Herstellung von Maschinen f\u00fcr bestimmte Verwendung",
    "sg:phone":"+41 26 495 94 70",
    "sg:postcode":"1033",
    "sg:province":"Vaud",
    "wof:name":"Kbs-spritztechnik Ch Gmbh Kunststoffverarbeitung",
    "wof:placetype":"venue"
},
  "geometry": {"coordinates":[7.2594342232,46.821472168],"type":"Point"}
}