{
  "type": "Feature",
  "properties": {
    "iso:country":"CH",
    "sg:address":"Mitteldorfstrasse 1",
    "sg:city":"Diepoldsau",
    "sg:orig_category":"Mechanische Werkst\u00e4tten",
    "sg:phone":"+41 71 733 11 06",
    "sg:postcode":"9444",
    "sg:province":"St. Gallen",
    "wof:name":"Jakob Weder Mechanische Werkst\u00e4tte",
    "wof:placetype":"venue"
},
  "geometry": {"coordinates":[9.6534099579,47.3845100403],"type":"Point"}
}