{
  "type": "Feature",
  "properties": {
    "iso:country":"CH",
    "sg:address":"B\u00fcndte 1",
    "sg:city":"Tamins",
    "sg:orig_category":"Sonstiger Fachdetailhandel in Verkaufsr\u00e4umen",
    "sg:phone":"+41 81 641 22 47",
    "sg:postcode":"7015",
    "sg:province":"Graubunden",
    "wof:name":"Peter E. Ryser Lady M Modeschmuck",
    "wof:placetype":"venue"
},
  "geometry": {"coordinates":[9.4058904648,46.8297119141],"type":"Point"}
}