{
  "type": "Feature",
  "properties": {
    "iso:country":"CH",
    "sg:address":"Jupiterstrasse 26",
    "sg:city":"Z\u00fcrich",
    "sg:orig_category":"Sanit\u00e4r, Heizungs U L\u00fcftungsinstallation",
    "sg:phone":"+41 32 968 13 13",
    "sg:postcode":"8032",
    "sg:province":"Z\u00fcrich",
    "wof:name":"Andr\u00e9 Charmillot",
    "wof:placetype":"venue"
},
  "geometry": {"coordinates":[6.8299927711,47.1059913635],"type":"Point"}
}