{
  "type": "Feature",
  "properties": {
    "iso:country":"CH",
    "sg:address":"Klusstrasse 36",
    "sg:city":"Oensingen",
    "sg:orig_category":"Sonstiger spezialisierter Hoch U Tiefbau",
    "sg:phone":"+41 79 356 44 88",
    "sg:postcode":"4702",
    "sg:province":"Solothurn",
    "wof:name":"M\u00fcller Kamine Ag",
    "wof:placetype":"venue"
},
  "geometry": {"coordinates":[7.7111668587,47.2919769287],"type":"Point"}
}