{
  "type": "Feature",
  "properties": {
    "iso:country":"CH",
    "sg:address":"Dorfstrasse 3792 Saanen. Postfach 78",
    "sg:city":"Saanen",
    "sg:orig_category":"Grafikateliers, Design",
    "sg:phone":"+41 33 744 44 43",
    "sg:postcode":"3792",
    "sg:province":"Bern",
    "wof:name":"Ruth Knutti Grafik Center",
    "wof:placetype":"venue"
},
  "geometry": {"coordinates":[7.2619848251,46.4898033142],"type":"Point"}
}