{
  "type": "Feature",
  "properties": {
    "iso:country":"CH",
    "sg:address":"Holenackerstrasse 9",
    "sg:city":"Bern",
    "sg:orig_category":"Grosshandel mit elektrischen Haushaltsger\u00e4ten, Radio U Fernsehger\u00e4ten",
    "sg:phone":"+41 31 994 14 10",
    "sg:postcode":"3027",
    "sg:province":"Bern",
    "wof:name":"Duchilio Peter",
    "wof:placetype":"venue"
},
  "geometry": {"coordinates":[7.380628109,46.9492111206],"type":"Point"}
}