{
  "type": "Feature",
  "properties": {
    "iso:country":"CH",
    "sg:address":"R\u00e4mistrasse 50",
    "sg:city":"Z\u00fcrich",
    "sg:orig_category":"Verm\u00f6gensverwaltung",
    "sg:phone":"+41 12613132",
    "sg:postcode":"8001",
    "sg:province":"Z\u00fcrich",
    "wof:name":"Incentive Investment Ag",
    "wof:placetype":"venue"
},
  "geometry": {"coordinates":[8.5501689911,47.3712348938],"type":"Point"}
}