{
  "type": "Feature",
  "properties": {
    "iso:country":"CH",
    "sg:address":"Im Schnegg 4",
    "sg:city":"Horgen",
    "sg:orig_category":"Unclassifiable Establishments",
    "sg:postcode":"8810",
    "sg:province":"Z\u00fcrich",
    "wof:name":"Transport Darko Terzic",
    "wof:placetype":"venue"
},
  "geometry": {"coordinates":[8.6042785645,47.2480964661],"type":"Point"}
}