{
  "type": "Feature",
  "properties": {
    "iso:country":"CH",
    "sg:address":"St\u00e4glistrasse 2",
    "sg:city":"Stadel",
    "sg:orig_category":"Architekturb\u00fcros",
    "sg:phone":"+41 18581151",
    "sg:postcode":"8174",
    "sg:province":"Z\u00fcrich",
    "wof:name":"Rolf Naegeli Architekturb\u00fcro",
    "wof:placetype":"venue"
},
  "geometry": {"coordinates":[8.466479,47.534016],"type":"Point"}
}