{
  "type": "Feature",
  "properties": {
    "iso:country":"CH",
    "sg:address":"Quellenstrasse 10",
    "sg:city":"Rheinfelden",
    "sg:orig_category":"Non-Classified Establishments",
    "sg:postcode":"4310",
    "sg:province":"Aargau",
    "wof:name":"Reineke Schweiz Gmbh",
    "wof:placetype":"venue"
},
  "geometry": {"coordinates":[7.7898387909,47.5511856079],"type":"Point"}
}