{
  "type": "Feature",
  "properties": {
    "iso:country":"CH",
    "sg:address":"Lindenquai 10 7000 Chur. Postfach",
    "sg:city":"Chur",
    "sg:orig_category":"Unclassifiable Establishments",
    "sg:postcode":"7000",
    "sg:province":"Graubunden",
    "wof:name":"Kumares Ag",
    "wof:placetype":"venue"
},
  "geometry": {"coordinates":[9.5302476883,46.8472480774],"type":"Point"}
}