{
  "type": "Feature",
  "properties": {
    "iso:country":"CH",
    "sg:address":"Place Isaac-mercier 3",
    "sg:city":"Gen\u00e8ve",
    "sg:orig_category":"Unternehmensberatung",
    "sg:phone":"+41 22 732 72 80",
    "sg:postcode":"1201",
    "sg:province":"Gen\u00e8ve",
    "wof:name":"Synergers Sa",
    "wof:placetype":"venue"
},
  "geometry": {"coordinates":[6.1393389702,46.2066383362],"type":"Point"}
}