{
  "type": "Feature",
  "properties": {
    "iso:country":"CH",
    "sg:address":"1884",
    "sg:city":"Arveyes",
    "sg:orig_category":"Sportvereine Flug Aero-Club",
    "sg:postcode":"1884",
    "sg:province":"Vaud",
    "wof:name":"Gpe De Mod\u00e8les R\u00e9duits Aecs",
    "wof:placetype":"venue"
},
  "geometry": {"coordinates":[7.0609898567,46.2908287048],"type":"Point"}
}