{
  "type": "Feature",
  "properties": {
    "iso:country":"CH",
    "sg:address":"Via Gismonda 2",
    "sg:city":"Mendrisio",
    "sg:orig_category":"Detailhandel mit Bekleidung Detailhandel mit Damenbekleidung",
    "sg:phone":"+41 91 646 70 74",
    "sg:postcode":"6850",
    "sg:province":"Ticino",
    "wof:name":"Iris Magatti Boutique Valessia Mode",
    "wof:placetype":"venue"
},
  "geometry": {"coordinates":[8.9852,45.867992],"type":"Point"}
}