{
  "type": "Feature",
  "properties": {
    "iso:country":"CH",
    "sg:address":"Am Iberghang 3 8400 Winterthur. Postfach",
    "sg:city":"Winterthur",
    "sg:orig_category":"Technische, physikalische U chemische Untersuchung",
    "sg:phone":"+41 52 232 43 67",
    "sg:postcode":"8405",
    "sg:province":"Z\u00fcrich",
    "wof:name":"Fl\u00fcckiger F., Systems Engineering",
    "wof:placetype":"venue"
},
  "geometry": {"coordinates":[8.7800416946,47.4644088745],"type":"Point"}
}