{
  "type": "Feature",
  "properties": {
    "iso:country":"CH",
    "sg:address":"Hofmattstrasse 12",
    "sg:city":"Gossau",
    "sg:classifiers":[
        {
            "category":"Health Services",
            "subcategory":"Doctor",
            "type":"Services"
        }
    ],
    "sg:phone":"+41 71 388 11 66",
    "sg:postcode":"9200",
    "sg:province":"St. Gallen",
    "sg:tags":[
        "lamps",
        "lamp",
        "physical",
        "examination",
        "doctor's"
    ],
    "wof:name":"Derungs Licht Ag",
    "wof:placetype":"venue"
},
  "geometry": {"coordinates":[9.2647209167,47.4143943787],"type":"Point"}
}