{
  "type": "Feature",
  "properties": {
    "addr:full":"Bleicheweg 5 Goldach St. Gallen 9403",
    "addr:housenumber":"5",
    "addr:postcode":"9403",
    "addr:street":"Bleicheweg",
    "iso:country":"CH",
    "sg:address":"Bleicheweg 5",
    "sg:city":"Goldach",
    "sg:orig_category":"Bauschreinerei Herstellung von Konstruktionsteilen, Fertigbauteilen U Ausbauelementen aus Holz",
    "sg:phone":"+41 81 413 16 05",
    "sg:postcode":"9403",
    "sg:province":"St. Gallen",
    "wof:name":"Amb\u00fchl Conradin",
    "wof:placetype":"venue"
},
  "geometry": {"coordinates":[9.818463,46.788349],"type":"Point"}
}