{
  "type": "Feature",
  "properties": {
    "iso:country":"CH",
    "sg:address":"9642",
    "sg:city":"Ebnat",
    "sg:orig_category":"Sportvereine Sch\u00fctzen",
    "sg:postcode":"9642",
    "sg:province":"St. Gallen",
    "wof:name":"Sch\u00fctzenverein",
    "wof:placetype":"venue"
},
  "geometry": {"coordinates":[9.1167001724,47.25],"type":"Point"}
}