{
  "type": "Feature",
  "properties": {
    "iso:country":"CH",
    "sg:address":"Meyrin Route De 267",
    "sg:city":"Meyrin",
    "sg:orig_category":"Finanzierungsinstitutionen",
    "sg:phone":"+41 22 719 35 00",
    "sg:postcode":"1217",
    "sg:province":"Gen\u00e8ve",
    "wof:name":"G.b.o.-general Beverage Overseas Sa, Luxembourg, Succursale De Meyrin",
    "wof:placetype":"venue"
},
  "geometry": {"coordinates":[6.0722160339,46.2284431458],"type":"Point"}
}