{
  "type": "Feature",
  "properties": {
    "iso:country":"CH",
    "sg:address":"Eichenweg 61",
    "sg:city":"Embrach",
    "sg:orig_category":"Sonstige Verkehrsvermittlung",
    "sg:postcode":"8424",
    "sg:province":"Z\u00fcrich",
    "wof:name":"Von Allmen Internationale Transporte Ag",
    "wof:placetype":"venue"
},
  "geometry": {"coordinates":[8.5946388245,47.5122413635],"type":"Point"}
}