{
  "type": "Feature",
  "properties": {
    "iso:country":"CH",
    "sg:address":"Route Lanche",
    "sg:city":"Bouveret",
    "sg:orig_category":"Betrieb von Taxis",
    "sg:phone":"+41 24 481 21 20",
    "sg:postcode":"1897",
    "sg:province":"Valais",
    "wof:name":"Gaston Rogivue Taxi Port-valais",
    "wof:placetype":"venue"
},
  "geometry": {"coordinates":[6.85915,46.38237],"type":"Point"}
}