{
  "type": "Feature",
  "properties": {
    "iso:country":"CH",
    "sg:address":"Alleeweg 11",
    "sg:city":"Kreuzlingen",
    "sg:orig_category":"Detektivb\u00fcros U \u00dcberwachung",
    "sg:postcode":"8280",
    "sg:province":"Thurgau",
    "wof:name":"Luchs Sicherheitsdienstleistungen Inhaber Schwager Ph",
    "wof:placetype":"venue"
},
  "geometry": {"coordinates":[9.1707935333,47.6478042603],"type":"Point"}
}