{
  "type": "Feature",
  "properties": {
    "iso:country":"CH",
    "sg:address":"Buchholzstrasse 45",
    "sg:city":"Thun",
    "sg:orig_category":"Detailhandel mit Fleisch U Fleischwaren",
    "sg:phone":"+41 33 222 58 26",
    "sg:postcode":"3600",
    "sg:province":"Bern",
    "wof:name":"Max Aeberhard",
    "wof:placetype":"venue"
},
  "geometry": {"coordinates":[7.6097898483,46.7300643921],"type":"Point"}
}