{
  "type": "Feature",
  "properties": {
    "iso:country":"CH",
    "sg:address":"Via Cantonale 24 6900 Lugano. Postfach",
    "sg:city":"Lugano",
    "sg:orig_category":"Handels-H\u00e4user U Gesellschaften",
    "sg:postcode":"6900",
    "sg:province":"Ticino",
    "wof:name":"Casalp Trading Ltd, \u00e0 Londres, Succursale De Corcelles-cormondr\u00e8che",
    "wof:placetype":"venue"
},
  "geometry": {"coordinates":[6.8677778244,46.987033844],"type":"Point"}
}