{
  "type": "Feature",
  "properties": {
    "addr:full":"Wiedenhubstrasse 35 4410 Liestal. Postfach Liestal Basel-Landschaft 4410",
    "addr:housenumber":"35",
    "addr:postcode":"4410 liestal. postfach;4410",
    "addr:street":"Wiedenhubstrasse",
    "iso:country":"CH",
    "sg:address":"Wiedenhubstrasse 35 4410 Liestal. Postfach",
    "sg:city":"Liestal",
    "sg:orig_category":"Bibliotheken U Archive Sonstige mit der \u00f6ffentlichen Verwaltung verbundene T\u00e4tigkeiten",
    "sg:phone":"+41 61 921 44 40",
    "sg:postcode":"4410",
    "sg:province":"Basel-Landschaft",
    "wof:name":"Staatsarchiv Baselland",
    "wof:placetype":"venue"
},
  "geometry": {"coordinates":[7.726491,47.487259],"type":"Point"}
}