{
  "type": "Feature",
  "properties": {
    "iso:country":"CH",
    "sg:address":"Place Centrale 3967 Vercorin. Postfach",
    "sg:city":"Vercorin",
    "sg:orig_category":"RESTAURANTS: TEA-ROOMS",
    "sg:postcode":"3967",
    "sg:province":"Valais",
    "wof:name":"Caf\u00e9-restaurant La Brentaz, Tissi\u00e8res",
    "wof:placetype":"venue"
},
  "geometry": {"coordinates":[7.5309901237,46.2572250366],"type":"Point"}
}