{
  "type": "Feature",
  "properties": {
    "iso:country":"CH",
    "sg:address":"Sonnhaldestrasse 55",
    "sg:city":"Aarwangen",
    "sg:orig_category":"Herstellung von Metallerzeugnissen ohne Maschinenbau",
    "sg:phone":"+41 79 356 07 58",
    "sg:postcode":"4912",
    "sg:province":"Bern",
    "wof:name":"Roger S\u00e4gesser Anlage-& Apparatebau",
    "wof:placetype":"venue"
},
  "geometry": {"coordinates":[7.7674489021,47.2318992615],"type":"Point"}
}