{
  "type": "Feature",
  "properties": {
    "iso:country":"CH",
    "sg:address":"Via Rusca 8",
    "sg:city":"Chiasso",
    "sg:orig_category":"Druck ohne Zeitungsdruck Offsetdruck",
    "sg:phone":"+41 91 682 93 40",
    "sg:postcode":"6830",
    "sg:province":"Ticino",
    "wof:name":"Puntografico Sagl",
    "wof:placetype":"venue"
},
  "geometry": {"coordinates":[9.0191907883,45.8389320374],"type":"Point"}
}