{
  "type": "Feature",
  "properties": {
    "iso:country":"CH",
    "sg:address":"Bahnhofstrasse 1",
    "sg:city":"Erlen",
    "sg:orig_category":"RESTAURANTS: TEA-ROOMS",
    "sg:postcode":"8586",
    "sg:province":"Thurgau",
    "wof:name":"Reitter Gmbh",
    "wof:placetype":"venue"
},
  "geometry": {"coordinates":[9.2267589569,47.5512695312],"type":"Point"}
}