{
  "type": "Feature",
  "properties": {
    "addr:full":"Av. Mayor-vautier 32 1820 Montreux Case Postale Montreux Vaud 1820",
    "addr:housenumber":"32",
    "addr:postcode":"1820;postale montreux;1820",
    "addr:street":"Av. Mayor-Vautier",
    "iso:country":"CH",
    "sg:address":"Av. Mayor-vautier 32 1820 Montreux Case Postale",
    "sg:city":"Montreux",
    "sg:orig_category":"Detailhandel mit Bekleidung",
    "sg:postcode":"1820",
    "sg:province":"Vaud",
    "wof:name":"Savary E. V\u00eatements Et Appareils M\u00e9nagers; Comm, Repr\u00e9s",
    "wof:placetype":"venue"
},
  "geometry": {"coordinates":[6.893937,46.442471],"type":"Point"}
}