{
  "type": "Feature",
  "properties": {
    "iso:country":"CH",
    "sg:address":"Bl\u00fcmlisalpstrasse 22",
    "sg:city":"Worb",
    "sg:orig_category":"Gartenbau Reinigungsgewerbe",
    "sg:phone":"+41 31 839 49 27",
    "sg:postcode":"3076",
    "sg:province":"Bern",
    "wof:name":"Lirep Liegenschaftsdienst Hauswartungen Und Umgebungsarbeiten",
    "wof:placetype":"venue"
},
  "geometry": {"coordinates":[7.5752420425,46.9254493713],"type":"Point"}
}