{
  "type": "Feature",
  "properties": {
    "iso:country":"CH",
    "sg:address":"Kornhausgasse 16 3400 Burgdorf. Postfach 810",
    "sg:city":"Burgdorf",
    "sg:orig_category":"Museen",
    "sg:phone":"+41 34 423 10 10",
    "sg:postcode":"3401",
    "sg:province":"Bern",
    "wof:name":"Kornhaus Burgdorf Museum",
    "wof:placetype":"venue"
},
  "geometry": {"coordinates":[7.6268968582,47.0582084656],"type":"Point"}
}