{
  "type": "Feature",
  "properties": {
    "iso:country":"CH",
    "sg:address":"Allmendstrasse 1",
    "sg:city":"R\u00fcttenen",
    "sg:orig_category":"Handelsvermittlung U Grosshandel Handelsvermittlung von Brennstoffen, Erzen, Metallen U Chemikalien",
    "sg:phone":"+41 32 622 62 63",
    "sg:postcode":"4522",
    "sg:province":"Solothurn",
    "wof:name":"Drevico Handels-gmbh",
    "wof:placetype":"venue"
},
  "geometry": {"coordinates":[7.5261001587,47.2297096252],"type":"Point"}
}