{
  "type": "Feature",
  "properties": {
    "iso:country":"CH",
    "sg:address":"Ogoz Chemin D' 3",
    "sg:city":"Bulle",
    "sg:orig_category":"Unclassifiable Establishments",
    "sg:phone":"+41 26 912 69 69",
    "sg:postcode":"1630",
    "sg:province":"Fribourg",
    "wof:name":"Entreprise Ren\u00e9 Mauroux Sa",
    "wof:placetype":"venue"
},
  "geometry": {"coordinates":[7.0232000351,46.6070785522],"type":"Point"}
}