{
  "type": "Feature",
  "properties": {
    "addr:full":"Auf Der Lyss 16 Basel Basel-Stadt 4051",
    "addr:housenumber":"16",
    "addr:postcode":"4051",
    "addr:street":"Auf Der Lyss",
    "iso:country":"CH",
    "sg:address":"Auf Der Lyss 16",
    "sg:city":"Basel",
    "sg:orig_category":"Detailhandel mit Bekleidung",
    "sg:phone":"+41 61 262 10 08",
    "sg:postcode":"4051",
    "sg:province":"Basel-Stadt",
    "wof:name":"Guskin Beatrice",
    "wof:placetype":"venue"
},
  "geometry": {"coordinates":[7.584242,47.556198],"type":"Point"}
}