{
  "type": "Feature",
  "properties": {
    "iso:country":"CH",
    "sg:address":"Av. Des 4 Maronniers 28",
    "sg:city":"Yverdon-les-bains",
    "sg:orig_category":"Pensionskassen",
    "sg:postcode":"1400",
    "sg:province":"Vaud",
    "wof:name":"Fonds De Secours Du Centre Hospitalier Yverdon-chamblon (chyc)",
    "wof:placetype":"venue"
},
  "geometry": {"coordinates":[6.6527061462,46.777507782],"type":"Point"}
}