{
  "type": "Feature",
  "properties": {
    "iso:country":"CH",
    "sg:address":"Le Village",
    "sg:city":"Morgins",
    "sg:classifiers":[
        {
            "category":"Bars & Pubs",
            "type":"Food & Drink"
        }
    ],
    "sg:phone":"+41 24 477 41 98",
    "sg:postcode":"1875",
    "sg:province":"Valais",
    "wof:name":"Crystal Pub",
    "wof:placetype":"venue"
},
  "geometry": {"coordinates":[6.857069,46.237328],"type":"Point"}
}