{
  "type": "Feature",
  "properties": {
    "iso:country":"CH",
    "sg:address":"Gewerbestrasse 1",
    "sg:city":"Honau",
    "sg:orig_category":"Grosshandel mit sonstigen Halbwaren",
    "sg:phone":"+41 18699111",
    "sg:postcode":"6038",
    "sg:province":"Luzern",
    "wof:name":"Brangs & Heinrich Papiere",
    "wof:placetype":"venue"
},
  "geometry": {"coordinates":[8.5068302155,47.5976371765],"type":"Point"}
}