{
  "type": "Feature",
  "properties": {
    "iso:country":"CH",
    "sg:address":"Kalchrainstrasse 10",
    "sg:city":"Ober\u00e4geri",
    "sg:orig_category":"Vermietung U Verpachtung von eigenen Immobilien",
    "sg:postcode":"6315",
    "sg:province":"Zug",
    "wof:name":"W.u.h. Finanz Ag",
    "wof:placetype":"venue"
},
  "geometry": {"coordinates":[8.6214771271,47.1334152222],"type":"Point"}
}