{
  "type": "Feature",
  "properties": {
    "iso:country":"CH",
    "sg:address":"Rue Principale 14",
    "sg:city":"Pleigne",
    "sg:orig_category":"Detailhandel mit Waren verschiedener Art, Hauptrichtung Nahrungsmittel",
    "sg:phone":"+41 32 431 12 32",
    "sg:postcode":"2807",
    "sg:province":"Jura",
    "wof:name":"Claudine Crevoiserat Alimentation Chez Claudine",
    "wof:placetype":"venue"
},
  "geometry": {"coordinates":[7.2922067642,47.4076347351],"type":"Point"}
}