{
  "type": "Feature",
  "properties": {
    "iso:country":"CH",
    "sg:address":"Rue Des Moulins 21",
    "sg:city":"Del\u00e9mont",
    "sg:orig_category":"Pensionskassen",
    "sg:postcode":"2800",
    "sg:province":"Jura",
    "wof:name":"Fondation Patronale Pour Le Personnel Du D\u00e9mocrate Sa",
    "wof:placetype":"venue"
},
  "geometry": {"coordinates":[7.3453588486,47.3641624451],"type":"Point"}
}