{
  "type": "Feature",
  "properties": {
    "iso:country":"CH",
    "sg:address":"Via Santo Stefano 4",
    "sg:city":"Muralto",
    "sg:orig_category":"Ger\u00fcstbau Sonstiger spezialisierter Hoch U Tiefbau",
    "sg:phone":"+41 79 621 63 83",
    "sg:postcode":"6600",
    "sg:province":"Ticino",
    "wof:name":"Moponta Sa",
    "wof:placetype":"venue"
},
  "geometry": {"coordinates":[8.8046979904,46.1736831665],"type":"Point"}
}