{
  "type": "Feature",
  "properties": {
    "iso:country":"CH",
    "sg:address":"In Der H\u00e4rti 13",
    "sg:city":"Winterthur",
    "sg:orig_category":"Unclassifiable Establishments",
    "sg:postcode":"8408",
    "sg:province":"Z\u00fcrich",
    "wof:name":"Garic & Partner Kredit",
    "wof:placetype":"venue"
},
  "geometry": {"coordinates":[8.6857013702,47.5149497986],"type":"Point"}
}