{
  "type": "Feature",
  "properties": {
    "iso:country":"CH",
    "sg:address":"Oberdorfstrasse 26",
    "sg:city":"Stettlen",
    "sg:orig_category":"Bauschreinerei Innenausbau",
    "sg:phone":"+41 31 931 41 18",
    "sg:postcode":"3066",
    "sg:province":"Bern",
    "wof:name":"Ulrich Utiger M\u00f6belschreinerei-innenausbau",
    "wof:placetype":"venue"
},
  "geometry": {"coordinates":[7.52592,46.960068],"type":"Point"}
}