{
  "type": "Feature",
  "properties": {
    "iso:country":"CH",
    "sg:address":"Schulhausgasse 6",
    "sg:city":"B\u00f6nigen",
    "sg:orig_category":"Reparatur von Schuhen U Lederwaren",
    "sg:phone":"+41 33 822 50 54",
    "sg:postcode":"3806",
    "sg:province":"Bern",
    "wof:name":"Silvio Gadenz Schuhmacherei",
    "wof:placetype":"venue"
},
  "geometry": {"coordinates":[7.8950328827,46.6854133606],"type":"Point"}
}