{
  "type": "Feature",
  "properties": {
    "iso:country":"CH",
    "sg:address":"R\u00f6hrli 21",
    "sg:city":"Beckenried",
    "sg:orig_category":"Detailhandel mit Damenbekleidung Detailhandel mit Herrenbekleidung",
    "sg:phone":"+41 41 620 03 02",
    "sg:postcode":"6375",
    "sg:province":"Nidwalden",
    "wof:name":"Gallery D.c. Modische Sportswear",
    "wof:placetype":"venue"
},
  "geometry": {"coordinates":[8.4745855331,46.9649887085],"type":"Point"}
}