{
  "type": "Feature",
  "properties": {
    "iso:country":"CH",
    "sg:address":"Wespiwiese 8",
    "sg:city":"Niederuzwil",
    "sg:classifiers":[
        {
            "category":"Insurance",
            "subcategory":"Insurance Agent",
            "type":"Services"
        }
    ],
    "sg:phone":"+41 22 343 75 16",
    "sg:postcode":"9244",
    "sg:province":"St. Gallen",
    "sg:tags":[
        "versicherungsagenturen",
        "-broker"
    ],
    "wof:name":"Rls Office Courtage Gestion D'assurances",
    "wof:placetype":"venue"
},
  "geometry": {"coordinates":[6.1379151344,46.1882781982],"type":"Point"}
}