{
  "type": "Feature",
  "properties": {
    "iso:country":"CH",
    "sg:address":"Fr\u00f6schweid 14",
    "sg:city":"Rheinfelden",
    "sg:orig_category":"Non-Classified Establishments",
    "sg:postcode":"4310",
    "sg:province":"Aargau",
    "wof:name":"Confiserie Minerva Henauer S.a.",
    "wof:placetype":"venue"
},
  "geometry": {"coordinates":[6.8241219521,47.0995979309],"type":"Point"}
}