{
  "type": "Feature",
  "properties": {
    "iso:country":"CH",
    "sg:address":"Vieux-coll\u00e8ge Rue Du 8 1204 Gen\u00e8ve. Postfach",
    "sg:city":"Gen\u00e8ve",
    "sg:orig_category":"Non-Classified Establishments",
    "sg:postcode":"1204",
    "sg:province":"Gen\u00e8ve",
    "wof:name":"Si Tierdzon Sa",
    "wof:placetype":"venue"
},
  "geometry": {"coordinates":[6.8680329323,46.8162384033],"type":"Point"}
}