{
  "type": "Feature",
  "properties": {
    "iso:country":"CH",
    "sg:address":"Lohstampfestrasse 11",
    "sg:city":"T\u00e4gerwilen",
    "sg:classifiers":[
        {
            "category":"Utilities",
            "subcategory":"Sewage",
            "type":"Services"
        }
    ],
    "sg:phone":"+41 71 666 72 05",
    "sg:postcode":"8274",
    "sg:province":"Thurgau",
    "sg:tags":[
        "sludge",
        "plant",
        "drying"
    ],
    "wof:name":"Innoplana Umweltechnik Ag",
    "wof:placetype":"venue"
},
  "geometry": {"coordinates":[9.1292333603,47.659740448],"type":"Point"}
}