{
  "type": "Feature",
  "properties": {
    "iso:country":"CH",
    "sg:address":"R\u00fcdenweg 30",
    "sg:city":"Boll",
    "sg:orig_category":"Unternehmensberatung",
    "sg:phone":"+41 31 839 81 39",
    "sg:postcode":"3067",
    "sg:province":"Bern",
    "wof:name":"Msb Unternehmensberatung",
    "wof:placetype":"venue"
},
  "geometry": {"coordinates":[7.5484848022,46.9599494934],"type":"Point"}
}