{
  "type": "Feature",
  "properties": {
    "iso:country":"CH",
    "sg:address":"Schleufenbergstrasse 9",
    "sg:city":"B\u00fclach",
    "sg:orig_category":"Unternehmensberatung",
    "sg:postcode":"8180",
    "sg:province":"Z\u00fcrich",
    "wof:name":"Bulleri Consulting",
    "wof:placetype":"venue"
},
  "geometry": {"coordinates":[8.545419693,47.5106163025],"type":"Point"}
}