{
  "type": "Feature",
  "properties": {
    "iso:country":"CH",
    "sg:address":"Trottenweg 25",
    "sg:city":"B\u00f6ttstein",
    "sg:orig_category":"Elektrizit\u00e4tsversorgung",
    "sg:phone":"+41 56 245 53 79",
    "sg:postcode":"5315",
    "sg:province":"Aargau",
    "wof:name":"Elektra B\u00f6ttstein",
    "wof:placetype":"venue"
},
  "geometry": {"coordinates":[8.2220802307,47.5545501709],"type":"Point"}
}