{
  "type": "Feature",
  "properties": {
    "iso:country":"CH",
    "sg:address":"Adlikerstrasse 297",
    "sg:city":"Regensdorf",
    "sg:orig_category":"Detailhandel mit Radio U Fernsehger\u00e4ten Detailhandel mit fotografischen Artikeln",
    "sg:phone":"+41 18841531",
    "sg:postcode":"8105",
    "sg:province":"Z\u00fcrich",
    "wof:name":"Interdiscount Ag Hi-fi Video Photo Radio",
    "wof:placetype":"venue"
},
  "geometry": {"coordinates":[8.4658508301,47.4440193176],"type":"Point"}
}