{
  "type": "Feature",
  "properties": {
    "iso:country":"CH",
    "sg:address":"Bl\u00e4siring 133 4057 Basel. Postfach",
    "sg:city":"Basel",
    "sg:orig_category":"Non-Classified Establishments",
    "sg:postcode":"4051",
    "sg:province":"Basel-Stadt",
    "wof:name":"Streiffschuss Films Ag",
    "wof:placetype":"venue"
},
  "geometry": {"coordinates":[7.5941419601,47.5687255859],"type":"Point"}
}