{
  "type": "Feature",
  "properties": {
    "iso:country":"CH",
    "sg:address":"Schlettstadtstrasse 4 2540 Grenchen. Postfach 1340",
    "sg:city":"Grenchen",
    "sg:orig_category":"Architektur U Ingenieurb\u00fcros",
    "sg:phone":"+41 32 645 04 44",
    "sg:postcode":"2540",
    "sg:province":"Solothurn",
    "wof:name":"H & W Engineering Hugi B. + W\u00fcrth R.",
    "wof:placetype":"venue"
},
  "geometry": {"coordinates":[7.4096231461,47.1917495728],"type":"Point"}
}