{
  "type": "Feature",
  "properties": {
    "iso:country":"CH",
    "sg:address":"Scheihagweg 13",
    "sg:city":"Itingen",
    "sg:orig_category":"Fachdetailhandel in Verkaufsr\u00e4umen",
    "sg:postcode":"4452",
    "sg:province":"Basel-Landschaft",
    "wof:name":"Hiberna Ag",
    "wof:placetype":"venue"
},
  "geometry": {"coordinates":[7.7884140015,47.4714241028],"type":"Point"}
}