{
  "type": "Feature",
  "properties": {
    "iso:country":"CH",
    "sg:address":"6300",
    "sg:city":"Zug",
    "sg:orig_category":"Kinos",
    "sg:postcode":"6300",
    "sg:province":"Zug",
    "wof:name":"H\u00fcrlimann Frau Cin\u00e9ma",
    "wof:placetype":"venue"
},
  "geometry": {"coordinates":[8.5168199539,47.1568984985],"type":"Point"}
}