{
  "type": "Feature",
  "properties": {
    "iso:country":"CH",
    "sg:address":"Bahnhofstrasse 28 6300 Zug. Postfach 4516",
    "sg:city":"Zug",
    "sg:orig_category":"Personal U Stellenvermittlung Unternehmensberatung",
    "sg:phone":"+41 41 729 80 47",
    "sg:postcode":"6304",
    "sg:province":"Zug",
    "wof:name":"Top Fifty Management",
    "wof:placetype":"venue"
},
  "geometry": {"coordinates":[8.5159921646,47.1701126099],"type":"Point"}
}