{
  "type": "Feature",
  "properties": {
    "iso:country":"CH",
    "sg:address":"Bernstr. 78",
    "sg:city":"B\u00fctzberg",
    "sg:classifiers":[
        {
            "category":"Manufacturing",
            "subcategory":"Wood Products",
            "type":"Manufacturing & Wholesale Goods"
        }
    ],
    "sg:phone":"+41 62 958 58 58",
    "sg:postcode":"4922",
    "sg:province":"Bern",
    "sg:tags":[
        "professional",
        "furniture"
    ],
    "wof:name":"Girsberger Ag",
    "wof:placetype":"venue"
},
  "geometry": {"coordinates":[7.7389397621,47.211555481],"type":"Point"}
}