{
  "type": "Feature",
  "properties": {
    "iso:country":"CH",
    "sg:address":"Insstrasse 7",
    "sg:city":"Br\u00fcttelen",
    "sg:orig_category":"Gem\u00fcsebau",
    "sg:phone":"+41 32 392 39 65",
    "sg:postcode":"2578",
    "wof:name":"Andreas Ramseier Gem\u00fcsebau",
    "wof:placetype":"venue"
},
  "geometry": {"coordinates":[7.2566080093,47.0363006592],"type":"Point"}
}