{
  "type": "Feature",
  "properties": {
    "iso:country":"CH",
    "sg:address":"Hauptstrasse 15",
    "sg:city":"Bichelsee",
    "sg:orig_category":"Massagestudios",
    "sg:phone":"+41 56 633 86 88",
    "sg:postcode":"8363",
    "sg:province":"Thurgau",
    "wof:name":"Sonja Gut Massagen",
    "wof:placetype":"venue"
},
  "geometry": {"coordinates":[8.3409547806,47.3514556885],"type":"Point"}
}