{
  "type": "Feature",
  "properties": {
    "iso:country":"CH",
    "sg:address":"Via Ludovico Ariosto 4",
    "sg:city":"Lugano",
    "sg:orig_category":"Detailhandel mit elektrischen Haushalts-,Radio U Fernsehger\u00e4ten sowie Musikinstrumenten",
    "sg:postcode":"6900",
    "sg:province":"Ticino",
    "wof:name":"Dorier Roland",
    "wof:placetype":"venue"
},
  "geometry": {"coordinates":[6.9876022339,46.2100830078],"type":"Point"}
}