{
  "type": "Feature",
  "properties": {
    "iso:country":"CH",
    "sg:address":"Lettenweg 50",
    "sg:city":"Allschwil",
    "sg:orig_category":"Herstellung von Anstrichmitteln, Druckfarben U Kitten Herstellung von sonstigen chemischen Erzeugnis",
    "sg:phone":"+41 62 837 93 00",
    "sg:postcode":"4123",
    "sg:province":"Basel-Landschaft",
    "wof:name":"Basler Lacke Ag",
    "wof:placetype":"venue"
},
  "geometry": {"coordinates":[8.0892295837,47.385848999],"type":"Point"}
}