{
  "type": "Feature",
  "properties": {
    "iso:country":"CH",
    "sg:address":"Mazzetti Contrada 1",
    "sg:city":"Bissone",
    "sg:orig_category":"RESTAURANTS: TEA-ROOMS",
    "sg:phone":"+41 91 649 63 95",
    "sg:postcode":"6816",
    "sg:province":"Ticino",
    "wof:name":"Ugam Sagl",
    "wof:placetype":"venue"
},
  "geometry": {"coordinates":[8.9647436142,45.9502105713],"type":"Point"}
}