{
  "type": "Feature",
  "properties": {
    "iso:country":"CH",
    "sg:address":"M\u00fclibachstrasse 15",
    "sg:city":"Winkel",
    "sg:orig_category":"Non-Classified Establishments",
    "sg:postcode":"8185",
    "sg:province":"Z\u00fcrich",
    "wof:name":"Dr. Donato Scognamiglio Finanz- & Immobilienberatung",
    "wof:placetype":"venue"
},
  "geometry": {"coordinates":[8.56179142,47.481086731],"type":"Point"}
}