{
  "type": "Feature",
  "properties": {
    "iso:country":"CH",
    "sg:address":"Freiestrasse 18 2502 Biel/bienne. Postfach",
    "sg:city":"Biel/bienne",
    "sg:orig_category":"Softwareentwicklung U beratung",
    "sg:phone":"+41 32 342 62 65",
    "sg:postcode":"2502",
    "sg:province":"Bern",
    "wof:name":"Click Twice, D\u00f6me Patrick Pc-systeme U. Software; Verkauf",
    "wof:placetype":"venue"
},
  "geometry": {"coordinates":[7.2493457794,47.1419334412],"type":"Point"}
}