{
  "type": "Feature",
  "properties": {
    "addr:full":"Wydenmattstrasse 299 Erschwil Solothurn 4228",
    "addr:housenumber":"299",
    "addr:postcode":"4228",
    "addr:street":"Wydenmattstrasse",
    "iso:country":"CH",
    "sg:address":"Wydenmattstrasse 299",
    "sg:city":"Erschwil",
    "sg:orig_category":"Allgemeiner Hoch U Tiefbau Allgemeiner Hochbau",
    "sg:phone":"+41 61 781 20 33",
    "sg:postcode":"4228",
    "sg:province":"Solothurn",
    "wof:name":"Albin Borer Ag",
    "wof:placetype":"venue"
},
  "geometry": {"coordinates":[7.538863,47.379356],"type":"Point"}
}