{
  "type": "Feature",
  "properties": {
    "iso:country":"CH",
    "sg:address":"Denkmalstrasse 5",
    "sg:city":"Luzern",
    "sg:orig_category":"Physiotherapie",
    "sg:phone":"+41 79 213 14 05",
    "sg:postcode":"6006",
    "sg:province":"Luzern",
    "wof:name":"Jean-pierre Schnyder Naturheilpraxis",
    "wof:placetype":"venue"
},
  "geometry": {"coordinates":[8.3105621338,47.0575561523],"type":"Point"}
}