{
  "type": "Feature",
  "properties": {
    "iso:country":"CH",
    "sg:address":"Rue De La Promenade 19",
    "sg:city":"Bulle",
    "sg:orig_category":"Warenh\u00e4user",
    "sg:phone":"+41 56 618 86 99",
    "sg:postcode":"1630",
    "sg:province":"Fribourg",
    "wof:name":"Manor Ag",
    "wof:placetype":"venue"
},
  "geometry": {"coordinates":[8.2776937485,47.3499336243],"type":"Point"}
}