{
  "type": "Feature",
  "properties": {
    "iso:country":"CH",
    "sg:address":"Romanshornerstrasse 57",
    "sg:city":"Wittenbach",
    "sg:orig_category":"Interessenvertretungen",
    "sg:postcode":"9303",
    "wof:name":"Verband Schweizerischer Holzbeizmeister (vshb)",
    "wof:placetype":"venue"
},
  "geometry": {"coordinates":[9.3827371597,47.4604110718],"type":"Point"}
}