{
  "type": "Feature",
  "properties": {
    "iso:country":"CH",
    "sg:address":"Route De La Gare 107",
    "sg:city":"Ch\u00e9nens",
    "sg:orig_category":"Detailhandel mit Waren verschiedener Art, Hauptrichtung Nahrungsmittel",
    "sg:phone":"+41 26 477 10 44",
    "sg:postcode":"1744",
    "sg:province":"Fribourg",
    "wof:name":"Soci\u00e9t\u00e9 D'agriculture De Ch\u00e9nens",
    "wof:placetype":"venue"
},
  "geometry": {"coordinates":[7.0015830994,46.7488441467],"type":"Point"}
}