{
  "type": "Feature",
  "properties": {
    "iso:country":"CH",
    "sg:address":"6717",
    "sg:city":"Torre",
    "sg:orig_category":"Sanit\u00e4r U Heizungsinstallation Sanit\u00e4rinstallation",
    "sg:phone":"+41 41 870 22 86",
    "sg:postcode":"6717",
    "sg:province":"Ticino",
    "wof:name":"Aschwanden Beat Ag",
    "wof:placetype":"venue"
},
  "geometry": {"coordinates":[8.6413536072,46.8794403076],"type":"Point"}
}