{
  "type": "Feature",
  "properties": {
    "iso:country":"CH",
    "sg:address":"Chemin Du Signal 5",
    "sg:city":"Coppet",
    "sg:orig_category":"Wirtschaftspr\u00fcfung, Steuerberatung U Treuhand",
    "sg:postcode":"1296",
    "sg:province":"Vaud",
    "wof:name":"Accist Sa",
    "wof:placetype":"venue"
},
  "geometry": {"coordinates":[6.1852469444,46.3131256104],"type":"Point"}
}