{
  "type": "Feature",
  "properties": {
    "iso:country":"CH",
    "sg:address":"Le Martinet K",
    "sg:city":"Gingins",
    "sg:orig_category":"Herstellung von Kakao, Schokoladeerzeugnissen U Zuckerwaren",
    "sg:phone":"+41 22 369 22 26",
    "sg:postcode":"1276",
    "sg:province":"Vaud",
    "wof:name":"Caf\u00e9 Pr\u00e9d\u00e9r\u00e8s",
    "wof:placetype":"venue"
},
  "geometry": {"coordinates":[6.183426857,46.403717041],"type":"Point"}
}