{
  "type": "Feature",
  "properties": {
    "iso:country":"CH",
    "sg:address":"Scheuchzerstrasse 18 8006 Z\u00fcrich. Postfach",
    "sg:city":"Z\u00fcrich",
    "sg:orig_category":"Fotografische Ateliers Fotografische Laboratorien",
    "sg:phone":"+41 13502790",
    "sg:postcode":"8023",
    "sg:province":"Z\u00fcrich",
    "wof:name":"Comet Photoshopping Gmbh Presse-photoagentur F. Fach, Luftbildfotografie, Fachlabor Usw",
    "wof:placetype":"venue"
},
  "geometry": {"coordinates":[8.545507431,47.38331604],"type":"Point"}
}