{
  "type": "Feature",
  "properties": {
    "iso:country":"CH",
    "sg:address":"Furttalstrasse 11",
    "sg:city":"Z\u00fcrich",
    "sg:orig_category":"Allgemeiner Hoch U Tiefbau",
    "sg:phone":"+41 13713666",
    "sg:postcode":"8046",
    "sg:province":"Z\u00fcrich",
    "wof:name":"Frito Ag, Z\u00fcrich Hoch- U. Tiefbauarbeiten",
    "wof:placetype":"venue"
},
  "geometry": {"coordinates":[8.501691,47.4207],"type":"Point"}
}