{
  "type": "Feature",
  "properties": {
    "iso:country":"CH",
    "sg:address":"Hauptstrasse 18",
    "sg:city":"Koppigen",
    "sg:orig_category":"Herstellung von Hebezeugen U F\u00f6rdermitteln Mechanische Werkst\u00e4tten",
    "sg:phone":"+41 34 413 03 35",
    "sg:postcode":"3425",
    "sg:province":"Bern",
    "wof:name":"Baumgartner",
    "wof:placetype":"venue"
},
  "geometry": {"coordinates":[7.6040787697,47.1326942444],"type":"Point"}
}