{
  "type": "Feature",
  "properties": {
    "iso:country":"CH",
    "sg:address":"Bahnhofzentrum",
    "sg:city":"D\u00fcdingen",
    "sg:orig_category":"Unclassifiable Establishments",
    "sg:phone":"+41 26 493 35 55",
    "sg:postcode":"3186",
    "sg:province":"Fribourg",
    "wof:name":"Elvia Versicherungen B\u00fcro D\u00fcdingen",
    "wof:placetype":"venue"
},
  "geometry": {"coordinates":[7.1900749207,46.8504104614],"type":"Point"}
}