{
  "type": "Feature",
  "properties": {
    "iso:country":"CH",
    "sg:address":"Fabrikstrasse Im Bifang 4",
    "sg:city":"Haegendorf",
    "sg:classifiers":[
        {
            "category":"Professional",
            "subcategory":"Engineering",
            "type":"Services"
        }
    ],
    "sg:phone":"+41 62 216 33 88",
    "sg:postcode":"4614",
    "sg:province":"Solothurn",
    "sg:tags":[
        "machine",
        "-",
        "mechanical"
    ],
    "wof:name":"U. Dolder",
    "wof:placetype":"venue"
},
  "geometry": {"coordinates":[7.8448348045,47.3368263245],"type":"Point"}
}