{
  "type": "Feature",
  "properties": {
    "iso:country":"CH",
    "sg:address":"3752",
    "sg:city":"Wimmis",
    "sg:classifiers":[
        {
            "category":"Utilities",
            "subcategory":"Electric",
            "type":"Services"
        }
    ],
    "sg:phone":"+41 32 732 41 11",
    "sg:postcode":"3752",
    "sg:province":"Bern",
    "sg:tags":[
        "electricity",
        "raw",
        "energy",
        "material"
    ],
    "wof:name":"Electricite Neuchateloise Sa",
    "wof:placetype":"venue"
},
  "geometry": {"coordinates":[6.8677778244,46.987033844],"type":"Point"}
}