{
  "type": "Feature",
  "properties": {
    "iso:country":"CH",
    "sg:address":"Schulstrasse 152 8413 Neftenbach. Postfach 358",
    "sg:city":"Neftenbach",
    "sg:orig_category":"Verwaltung von Immobilien Wirtschaftspr\u00fcfung, Steuerberatung U Treuhand",
    "sg:phone":"+41 52 301 05 05",
    "sg:postcode":"8413",
    "sg:province":"Z\u00fcrich",
    "wof:name":"Boga Treuhand + Verwaltungen, B\u00f6sch H.r.",
    "wof:placetype":"venue"
},
  "geometry": {"coordinates":[8.6599626541,47.523639679],"type":"Point"}
}