{
  "type": "Feature",
  "properties": {
    "iso:country":"CH",
    "sg:address":"Via Dal Crot",
    "sg:city":"Poschiavo",
    "sg:orig_category":"Detailhandel mit Waren verschiedener Art, Hauptrichtung Nahrungsmittel",
    "sg:phone":"+41 81 844 01 36",
    "sg:postcode":"7742",
    "sg:province":"Graubunden",
    "wof:name":"Coop Centro",
    "wof:placetype":"venue"
},
  "geometry": {"coordinates":[10.0542373657,46.3232040405],"type":"Point"}
}