{
  "type": "Feature",
  "properties": {
    "iso:country":"CH",
    "sg:address":"Lettenstrasse 6",
    "sg:city":"Zweidlen",
    "sg:orig_category":"Malerei-Gipserei Stukkateurgewerbe, Gipserei U Verputzerei",
    "sg:phone":"+41 18672074",
    "sg:postcode":"8192",
    "sg:province":"Z\u00fcrich",
    "wof:name":"Roberto Walder Gipsergesch\u00e4ft",
    "wof:placetype":"venue"
},
  "geometry": {"coordinates":[8.5024900436,47.55884552],"type":"Point"}
}