{
  "type": "Feature",
  "properties": {
    "iso:country":"CH",
    "sg:address":"5035",
    "sg:city":"Unterentfelden",
    "sg:orig_category":"Wasserversorgung",
    "sg:phone":"+41 62 723 45 07",
    "sg:postcode":"5035",
    "sg:province":"Aargau",
    "wof:name":"Wasserversorgung Der Gemeinde Unterfelden",
    "wof:placetype":"venue"
},
  "geometry": {"coordinates":[8.0446243286,47.3672866821],"type":"Point"}
}