{
  "type": "Feature",
  "properties": {
    "addr:full":"Chemin Du Talent 5 Echallens Vaud 1040",
    "addr:housenumber":"5",
    "addr:postcode":"1040",
    "addr:street":"Chemin Du Talent",
    "iso:country":"CH",
    "sg:address":"Chemin Du Talent 5",
    "sg:city":"Echallens",
    "sg:orig_category":"Detailhandel mit Antiquit\u00e4ten U Gebrauchtwaren in Verkaufsr\u00e4umen",
    "sg:phone":"+41 21 881 40 02",
    "sg:postcode":"1040",
    "sg:province":"Vaud",
    "wof:name":"Expo-occasions, Pittet Daniel",
    "wof:placetype":"venue"
},
  "geometry": {"coordinates":[6.632302,46.642265],"type":"Point"}
}