{
  "type": "Feature",
  "properties": {
    "addr:full":"Albert Rey Immeuble 1er Montana-vermala 3962",
    "addr:housenumber":"3962",
    "addr:street":"Albert Rey Immeuble 1Er Montana-Vermala",
    "iso:country":"CH",
    "sg:address":"Albert Rey Immeuble 1er",
    "sg:city":"Montana-vermala",
    "sg:classifiers":[
        {
            "category":"Bars & Pubs",
            "type":"Food & Drink"
        }
    ],
    "sg:phone":"+41 27 481 24 68",
    "sg:postcode":"3962",
    "wof:name":"Lonfat Patrice",
    "wof:placetype":"venue"
},
  "geometry": {"coordinates":[7.492434,46.314419],"type":"Point"}
}