{
  "type": "Feature",
  "properties": {
    "iso:country":"CH",
    "sg:address":"Z\u00fcrichbergstrasse 107",
    "sg:city":"Z\u00fcrich",
    "sg:orig_category":"Wohnheime",
    "sg:phone":"+41 12515120",
    "sg:postcode":"8044",
    "sg:province":"Z\u00fcrich",
    "wof:name":"Mil-stiftung Adolf Und Mary.",
    "wof:placetype":"venue"
},
  "geometry": {"coordinates":[8.5631513596,47.3784675598],"type":"Point"}
}