{
  "type": "Feature",
  "properties": {
    "iso:country":"CH",
    "sg:address":"Lisighaus 9658 Wildhaus. Postfach",
    "sg:city":"Wildhaus",
    "sg:orig_category":"Wohnheime",
    "sg:phone":"+41 71 999 12 43",
    "sg:postcode":"9658",
    "sg:province":"St. Gallen",
    "wof:name":"Galluszentrum Ferienheim",
    "wof:placetype":"venue"
},
  "geometry": {"coordinates":[9.3415641785,47.2017974854],"type":"Point"}
}