{
  "type": "Feature",
  "properties": {
    "iso:country":"CH",
    "sg:address":"1742",
    "sg:city":"Autigny",
    "sg:classifiers":[
        {
            "category":"Travel",
            "subcategory":"Hotels & Motels",
            "type":"Entertainment"
        }
    ],
    "sg:postcode":"1742",
    "sg:province":"Fribourg",
    "sg:tags":[
        "hotels",
        "mit",
        "restaurant"
    ],
    "wof:name":"Chautems Patricia, Auberge De L'ecu",
    "wof:placetype":"venue"
},
  "geometry": {"coordinates":[7.0183601379,46.7365837097],"type":"Point"}
}