{
  "type": "Feature",
  "properties": {
    "iso:country":"CH",
    "sg:address":"Chileholzstrasse 7",
    "sg:city":"Sulzbach",
    "sg:orig_category":"Sportvereine Behindertensport",
    "sg:phone":"+41 19150945",
    "sg:postcode":"8614",
    "sg:province":"Z\u00fcrich",
    "wof:name":"Svbs Z\u00fcrichsee",
    "wof:placetype":"venue"
},
  "geometry": {"coordinates":[8.5996904373,47.2966651917],"type":"Point"}
}