{
  "type": "Feature",
  "properties": {
    "iso:country":"CH",
    "sg:address":"Langenthalstrasse 75a",
    "sg:city":"Lotzwil",
    "sg:orig_category":"Bauschreinerei Herstellung von M\u00f6beln verschiedener Art",
    "sg:phone":"+41 62 922 20 33",
    "sg:postcode":"4932",
    "sg:province":"Bern",
    "wof:name":"Ernst Zimmerli Bau-& M\u00f6belschreinerei",
    "wof:placetype":"venue"
},
  "geometry": {"coordinates":[7.787157,47.197449],"type":"Point"}
}