{
  "type": "Feature",
  "properties": {
    "iso:country":"CH",
    "sg:address":"Keltenstrasse 33 3018 Bern. Postfach",
    "sg:city":"Bern",
    "sg:orig_category":"Softwareentwicklung U beratung",
    "sg:postcode":"3018",
    "sg:province":"Bern",
    "wof:name":"Huber Philippe Ausf\u00fchrung V Edv-grafik U Handel M Entsprechender Software",
    "wof:placetype":"venue"
},
  "geometry": {"coordinates":[7.3974890709,46.9453887939],"type":"Point"}
}