{
  "type": "Feature",
  "properties": {
    "iso:country":"CH",
    "sg:address":"Dohlenzelgstrasse",
    "sg:city":"Windisch",
    "sg:orig_category":"Bezirks, Sekundar, Realschulen, Oberstufe der Primarschulen",
    "sg:phone":"+41 56 441 66 76",
    "sg:postcode":"5210",
    "sg:province":"Aargau",
    "wof:name":"Bezirksschule",
    "wof:placetype":"venue"
},
  "geometry": {"coordinates":[8.216715,47.477299],"type":"Point"}
}