{
  "type": "Feature",
  "properties": {
    "iso:country":"CH",
    "sg:address":"1642",
    "sg:city":"Sorens",
    "sg:orig_category":"Verarbeitung von Milch Verwertung von Milch",
    "sg:postcode":"1642",
    "sg:province":"Fribourg",
    "wof:name":"Soci\u00e9t\u00e9 De Laiterie De Malessert",
    "wof:placetype":"venue"
},
  "geometry": {"coordinates":[7.0537500381,46.6693954468],"type":"Point"}
}