{
  "type": "Feature",
  "properties": {
    "iso:country":"CH",
    "sg:address":"Vers-chez-carrard",
    "sg:city":"Font",
    "sg:orig_category":"Herstellung von sonstigen M\u00f6beln Innendekorationsateliers",
    "sg:phone":"+41 26 663 34 81",
    "sg:postcode":"1473",
    "sg:province":"Fribourg",
    "wof:name":"Joseph Frioud D\u00e9coration D'int\u00e9rieur",
    "wof:placetype":"venue"
},
  "geometry": {"coordinates":[6.8229799271,46.8351402283],"type":"Point"}
}