{
  "type": "Feature",
  "properties": {
    "iso:country":"CH",
    "sg:address":"Alte Gasse 4",
    "sg:city":"Oberiberg",
    "sg:orig_category":"Malerei",
    "sg:phone":"+41 55 414 18 75",
    "sg:postcode":"8843",
    "sg:province":"Schwyz",
    "wof:name":"Franz Holdener Malergesch\u00e4ft Eldorado",
    "wof:placetype":"venue"
},
  "geometry": {"coordinates":[8.775472641,47.0364608765],"type":"Point"}
}