{
  "type": "Feature",
  "properties": {
    "iso:country":"CH",
    "sg:address":"Tierparkweg 4",
    "sg:city":"Waltenschwil",
    "sg:orig_category":"Softwareentwicklung U beratung",
    "sg:phone":"+41 56 611 08 35",
    "sg:postcode":"5622",
    "sg:province":"Aargau",
    "wof:name":"Unilink Ag",
    "wof:placetype":"venue"
},
  "geometry": {"coordinates":[8.3081636429,47.3347816467],"type":"Point"}
}