{
  "type": "Feature",
  "properties": {
    "iso:country":"CH",
    "sg:address":"Pr\u00e9s Jeannette 36",
    "sg:city":"Courchavon",
    "sg:orig_category":"Maurerarbeiten Sonstiger spezialisierter Hoch U Tiefbau",
    "sg:postcode":"2922",
    "sg:province":"Jura",
    "wof:name":"Dominique Meyer",
    "wof:placetype":"venue"
},
  "geometry": {"coordinates":[7.0538949966,47.4415168762],"type":"Point"}
}