{
  "type": "Feature",
  "properties": {
    "iso:country":"CH",
    "sg:address":"Horwerstrasse 81",
    "sg:city":"Luzern",
    "sg:orig_category":"Reiseb\u00fcros U Reiseveranstalter",
    "sg:postcode":"6005",
    "sg:province":"Luzern",
    "wof:name":"T&t, Tickets & Tourismus Gmbh",
    "wof:placetype":"venue"
},
  "geometry": {"coordinates":[8.3029003143,47.0356674194],"type":"Point"}
}