{
  "type": "Feature",
  "properties": {
    "iso:country":"CH",
    "sg:address":"Baslerstrasse 27",
    "sg:city":"Oftringen",
    "sg:orig_category":"Detailhandel mit Musikinstrumenten K\u00fcnstlerische Schulen",
    "sg:phone":"+41 32 351 40 04",
    "sg:postcode":"4665",
    "sg:province":"Aargau",
    "wof:name":"Martin Sch\u00fctz",
    "wof:placetype":"venue"
},
  "geometry": {"coordinates":[7.358880043,47.1080741882],"type":"Point"}
}