{
  "type": "Feature",
  "properties": {
    "iso:country":"CH",
    "sg:address":"M\u00fchlegasse 30",
    "sg:city":"Baar",
    "sg:classifiers":[
        {
            "category":"Professional",
            "subcategory":"Engineering",
            "type":"Services"
        }
    ],
    "sg:phone":"+41 41 760 82 83",
    "sg:postcode":"6340",
    "sg:province":"Zug",
    "wof:name":"Marty - Engineering",
    "wof:placetype":"venue"
},
  "geometry": {"coordinates":[8.5252084732,47.1997871399],"type":"Point"}
}