{
  "type": "Feature",
  "properties": {
    "iso:country":"CH",
    "sg:address":"Kapellenweg 24",
    "sg:city":"Steffisburg",
    "sg:orig_category":"Sportvereine Ski",
    "sg:phone":"+41 33 442 22 55",
    "sg:postcode":"3612",
    "sg:province":"Bern",
    "wof:name":"Skiclub Homberg",
    "wof:placetype":"venue"
},
  "geometry": {"coordinates":[7.6289730072,46.7828140259],"type":"Point"}
}