{
  "type": "Feature",
  "properties": {
    "iso:country":"CH",
    "sg:address":"Sophie Taeuber-strasse 4",
    "sg:city":"Z\u00fcrich",
    "sg:orig_category":"Arztpraxen",
    "sg:phone":"+41 13151848",
    "sg:postcode":"8050",
    "sg:province":"Z\u00fcrich",
    "wof:name":"Dres Med. Fankhauser & Schultz \u00c4rztinnen F.allgem.medizin Fmh",
    "wof:placetype":"venue"
},
  "geometry": {"coordinates":[8.54031,47.41288],"type":"Point"}
}