{
  "type": "Feature",
  "properties": {
    "iso:country":"CH",
    "sg:address":"Gutenbergstrasse 20 3011 Bern. Postfach",
    "sg:city":"Bern",
    "sg:orig_category":"Film U Videofilmherstellung Sonstige Hilfsdienste des Kultur U Unterhaltungswesens",
    "sg:phone":"+41 17718022",
    "sg:postcode":"3001",
    "sg:province":"Bern",
    "wof:name":"Cd Mailing Michel",
    "wof:placetype":"venue"
},
  "geometry": {"coordinates":[8.5245218277,47.2925567627],"type":"Point"}
}