{
  "type": "Feature",
  "properties": {
    "iso:country":"CH",
    "sg:address":"Raithard",
    "sg:city":"Willisdorf",
    "sg:orig_category":"Grosshandel mit elektrischen Haushaltsger\u00e4ten, Radio U Fernsehger\u00e4ten",
    "sg:phone":"+41 52 654 16 88",
    "sg:postcode":"8253",
    "sg:province":"Thurgau",
    "wof:name":"Eph Electronic-print- Handels Ag",
    "wof:placetype":"venue"
},
  "geometry": {"coordinates":[8.750254631,47.689491272],"type":"Point"}
}