{
  "type": "Feature",
  "properties": {
    "iso:country":"CH",
    "sg:address":"Thalmatt 1 3038 Kirchlindach. Postfach",
    "sg:city":"Herrenschwanden",
    "sg:orig_category":"Sonstiger Grosshandel",
    "sg:postcode":"3037",
    "sg:province":"Bern",
    "wof:name":"Cafetina Pl\u00fcss M. & Co",
    "wof:placetype":"venue"
},
  "geometry": {"coordinates":[7.4103879929,46.9759407043],"type":"Point"}
}