{
  "type": "Feature",
  "properties": {
    "iso:country":"CH",
    "sg:address":"Schloss Regensberg 8158 Regensberg. Postfach",
    "sg:city":"Regensberg",
    "sg:orig_category":"Pensionskassen",
    "sg:postcode":"8158",
    "sg:province":"Z\u00fcrich",
    "wof:name":"Angestellten-f\u00fcrsorge-stiftung Der Stiftung Schloss Regensberg",
    "wof:placetype":"venue"
},
  "geometry": {"coordinates":[8.4363718033,47.4825248718],"type":"Point"}
}