{
  "type": "Feature",
  "properties": {
    "iso:country":"CH",
    "sg:address":"Vorstatt 2",
    "sg:city":"Lauwil",
    "sg:orig_category":"Futtermittel, Heu and Stroh Grosshandel",
    "sg:phone":"+41 61 943 01 00",
    "sg:postcode":"4426",
    "sg:province":"Basel-Landschaft",
    "wof:name":"Ulrich E. Bernhard Martin Horse Feed",
    "wof:placetype":"venue"
},
  "geometry": {"coordinates":[7.6756000519,47.390007019],"type":"Point"}
}