{
  "type": "Feature",
  "properties": {
    "iso:country":"CH",
    "sg:address":"Kraftstrasse 4",
    "sg:city":"Z\u00fcrich",
    "sg:orig_category":"Elektroinstallation",
    "sg:postcode":"8044",
    "sg:province":"Z\u00fcrich",
    "wof:name":"Stalder Ferd., Inh. Dudli Chr. Elektrische Installationen.",
    "wof:placetype":"venue"
},
  "geometry": {"coordinates":[8.5597400665,47.3771095276],"type":"Point"}
}