{
  "type": "Feature",
  "properties": {
    "iso:country":"CH",
    "sg:address":"Industriestrasse 8",
    "sg:city":"Dietlikon",
    "sg:orig_category":"Non-Classified Establishments",
    "sg:postcode":"8305",
    "sg:province":"Z\u00fcrich",
    "wof:name":"Derendinger-web Ag",
    "wof:placetype":"venue"
},
  "geometry": {"coordinates":[8.6246013641,47.415813446],"type":"Point"}
}