{
  "type": "Feature",
  "properties": {
    "iso:country":"CH",
    "sg:address":"Champs-montants 4",
    "sg:city":"Marin-centre",
    "sg:orig_category":"Sonstiger Detailhandel mit Metallwaren, Anstrichmitteln, Glaswaren, Bau U Heimwerkerbedarf",
    "sg:phone":"+41 32 731 73 01",
    "sg:postcode":"2074",
    "sg:province":"Neuch\u00e2tel",
    "wof:name":"Jumbo Brico & Loisirs",
    "wof:placetype":"venue"
},
  "geometry": {"coordinates":[6.9969191551,47.0127105713],"type":"Point"}
}