{
  "type": "Feature",
  "properties": {
    "iso:country":"CH",
    "sg:address":"Chemin Des Sapins 21",
    "sg:city":"Cointrin",
    "sg:orig_category":"Bauspenglerei Dachdeckerei",
    "sg:phone":"+41 22 798 06 30",
    "sg:postcode":"1216",
    "sg:province":"Gen\u00e8ve",
    "wof:name":"Jean-michel Piroia Ferblanterie & Couverture",
    "wof:placetype":"venue"
},
  "geometry": {"coordinates":[6.107499,46.226315],"type":"Point"}
}