{
  "type": "Feature",
  "properties": {
    "iso:country":"CH",
    "sg:address":"Petersgraben 27",
    "sg:city":"Basel",
    "sg:orig_category":"Interessenvertretungen",
    "sg:postcode":"4051",
    "sg:province":"Basel-Stadt",
    "wof:name":"Strobel-stiftung",
    "wof:placetype":"venue"
},
  "geometry": {"coordinates":[7.5846509933,47.5593833923],"type":"Point"}
}