{
  "type": "Feature",
  "properties": {
    "iso:country":"CH",
    "sg:address":"Chemin Des Perdrix 10",
    "sg:city":"Plan-les-ouates",
    "sg:orig_category":"Wirtschaftspr\u00fcfung, Steuerberatung U Treuhand",
    "sg:postcode":"1228",
    "sg:province":"Gen\u00e8ve",
    "wof:name":"Bureau De Secr\u00e9tariat Et De Comptabilit\u00e9, Marianne Perret N\u00e9e W\u00e4lti",
    "wof:placetype":"venue"
},
  "geometry": {"coordinates":[7.0020017624,47.1207389832],"type":"Point"}
}