{
  "type": "Feature",
  "properties": {
    "iso:country":"CH",
    "sg:address":"Schulhausstrasse",
    "sg:city":"Gampel",
    "sg:orig_category":"Herstellung von Arbeits U Berufsbekleidung Textilgewerbe",
    "sg:phone":"+41 31 839 77 59",
    "sg:postcode":"3945",
    "sg:province":"Valais",
    "wof:name":"Karl Moser Schneiderei Ag",
    "wof:placetype":"venue"
},
  "geometry": {"coordinates":[7.5298790932,46.9306221008],"type":"Point"}
}