{
  "type": "Feature",
  "properties": {
    "iso:country":"CH",
    "sg:address":"Bauelenzelgstrasse 20 8193 Eglisau. Postfach",
    "sg:city":"Eglisau",
    "sg:orig_category":"Herstellung von Teppichen Herstellung von sonstigen konfektionierten Textilwaren ohne Bekleidung",
    "sg:phone":"+41 18682626",
    "sg:postcode":"8193",
    "sg:province":"Z\u00fcrich",
    "wof:name":"Stamoid Ag",
    "wof:placetype":"venue"
},
  "geometry": {"coordinates":[8.5156869888,47.5806617737],"type":"Point"}
}