{
  "type": "Feature",
  "properties": {
    "iso:country":"CH",
    "sg:address":"Weggisgasse 25-27",
    "sg:city":"Luzern",
    "sg:orig_category":"Detailhandel mit Uhren U Schmuck Herstellung von Uhren",
    "sg:phone":"+41 12253434",
    "sg:postcode":"6004",
    "sg:province":"Luzern",
    "wof:name":"Juwelier Kurz Ag",
    "wof:placetype":"venue"
},
  "geometry": {"coordinates":[8.3058719635,47.0527915955],"type":"Point"}
}