{
  "type": "Feature",
  "properties": {
    "addr:full":"Schachenstrasse 10a/14a Emmenbr\u00fccke Luzern 6020",
    "addr:housenumber":"10a / 14a",
    "addr:postcode":"6020",
    "addr:street":"Schachenstrasse;Emmenbruecke",
    "iso:country":"CH",
    "sg:address":"Schachenstrasse 10a/14a",
    "sg:city":"Emmenbr\u00fccke",
    "sg:classifiers":[
        {
            "category":"Autos & Motor Vehicles",
            "subcategory":"Recreational Vehicle Sales",
            "type":"Retail Goods"
        }
    ],
    "sg:phone":"+41 41 260 48 88",
    "sg:postcode":"6020",
    "sg:province":"Luzern",
    "sg:tags":[
        "car",
        "racing",
        "tuning",
        "accessory"
    ],
    "wof:name":"Rudolf Glauser Ag",
    "wof:placetype":"venue"
},
  "geometry": {"coordinates":[8.287912,47.068455],"type":"Point"}
}