{
  "type": "Feature",
  "properties": {
    "iso:country":"CH",
    "sg:address":"Industrieneuhof 31",
    "sg:city":"Kirchberg",
    "sg:classifiers":[
        {
            "category":"Wholesale",
            "subcategory":"Medical Equipment & Supplies",
            "type":"Manufacturing & Wholesale Goods"
        }
    ],
    "sg:phone":"+41 34 448 14 14",
    "sg:postcode":"3422",
    "sg:province":"Bern",
    "sg:tags":[
        "instrument",
        "health",
        "-",
        "precision"
    ],
    "wof:name":"Mcm Medsys Ag",
    "wof:placetype":"venue"
},
  "geometry": {"coordinates":[7.568109,47.096146],"type":"Point"}
}