{
  "type": "Feature",
  "properties": {
    "iso:country":"CH",
    "sg:address":"Thorenbergmatte 27",
    "sg:city":"Littau",
    "sg:orig_category":"Grosshandel mit sonstigen Gebrauchs U Verbrauchsg\u00fctern",
    "sg:phone":"+41 41 250 80 20",
    "sg:postcode":"6014",
    "sg:province":"Luzern",
    "wof:name":"Collectors Firearms Koller Kurt",
    "wof:placetype":"venue"
},
  "geometry": {"coordinates":[8.2511053085,47.0539321899],"type":"Point"}
}