{
  "type": "Feature",
  "properties": {
    "iso:country":"CH",
    "sg:address":"6345 Neuheim. Postfach 24",
    "sg:city":"Neuheim",
    "sg:orig_category":"Sportvereine Ballsport Badminton",
    "sg:phone":"+41 41 757 02 42",
    "sg:postcode":"6345",
    "sg:province":"Zug",
    "wof:name":"Badminton-club Neuheim",
    "wof:placetype":"venue"
},
  "geometry": {"coordinates":[8.5765800476,47.2029075623],"type":"Point"}
}