{
  "type": "Feature",
  "properties": {
    "addr:full":"Cadras 134 Tinizong Graubunden 7453",
    "addr:housenumber":"134",
    "addr:postcode":"7453",
    "addr:street":"Tinizong Graubunden",
    "iso:country":"CH",
    "sg:address":"Cadras 134",
    "sg:city":"Tinizong",
    "sg:orig_category":"Architektur U Ingenieurb\u00fcros",
    "sg:postcode":"7453",
    "sg:province":"Graubunden",
    "wof:name":"Jegher Bau-engineering",
    "wof:placetype":"venue"
},
  "geometry": {"coordinates":[9.61316,46.585918],"type":"Point"}
}