{
  "type": "Feature",
  "properties": {
    "iso:country":"CH",
    "sg:address":"Grand-rue 19",
    "sg:city":"Payerne",
    "sg:orig_category":"Zahntechnische Laboratorien",
    "sg:phone":"+41 26 660 31 44",
    "sg:postcode":"1530",
    "sg:province":"Vaud",
    "wof:name":"Roger Zahno Sa Labor.de Proth\u00e8ses Dentaires",
    "wof:placetype":"venue"
},
  "geometry": {"coordinates":[6.9382781982,46.8212738037],"type":"Point"}
}