{
  "type": "Feature",
  "properties": {
    "addr:full":"Schlyffistrasse 8 B\u00e4ch Schwyz 8806",
    "addr:housenumber":"8",
    "addr:postcode":"8806",
    "addr:street":"Schlyffistrasse;Schwyz",
    "iso:country":"CH",
    "sg:address":"Schlyffistrasse 8",
    "sg:city":"B\u00e4ch",
    "sg:classifiers":[
        {
            "category":"Structure",
            "subcategory":"Building",
            "type":"Public Place"
        }
    ],
    "sg:phone":"+41 17849694",
    "sg:postcode":"8806",
    "sg:province":"Schwyz",
    "sg:tags":[
        "calibrating",
        "system",
        "equipment"
    ],
    "wof:name":"Negele Industrieelektronik Ag",
    "wof:placetype":"venue"
},
  "geometry": {"coordinates":[8.728983,47.200966],"type":"Point"}
}