{
  "type": "Feature",
  "properties": {
    "iso:country":"CH",
    "sg:address":"Cantonale Via 15",
    "sg:city":"Melide",
    "sg:orig_category":"W\u00e4scherei U chemische Reinigung",
    "sg:postcode":"6815",
    "sg:province":"Ticino",
    "wof:name":"Pulirecord Di Sica Gerardo Sagl",
    "wof:placetype":"venue"
},
  "geometry": {"coordinates":[8.9496097565,45.9547386169],"type":"Point"}
}