{
  "type": "Feature",
  "properties": {
    "iso:country":"CH",
    "sg:address":"Via Cantonale",
    "sg:city":"Mezzovico",
    "sg:orig_category":"Automaten Herstellung Herstellung von medizinischen U chirurgischen Ger\u00e4ten sowie orthop\u00e4dischen Vor",
    "sg:phone":"+41 91 935 91 60",
    "sg:postcode":"6805",
    "sg:province":"Ticino",
    "wof:name":"Medway Sa",
    "wof:placetype":"venue"
},
  "geometry": {"coordinates":[8.919883,46.087986],"type":"Point"}
}