{
  "type": "Feature",
  "properties": {
    "iso:country":"CH",
    "sg:address":"Badenerstrasse 799",
    "sg:city":"Z\u00fcrich",
    "sg:orig_category":"Mineral\u00f6lverarbeitung Tankstellen",
    "sg:phone":"+41 13410870",
    "sg:postcode":"8048",
    "sg:province":"Z\u00fcrich",
    "wof:name":"Migrol-genossenschaft Tankstelle",
    "wof:placetype":"venue"
},
  "geometry": {"coordinates":[8.4753723145,47.3925285339],"type":"Point"}
}