{
  "type": "Feature",
  "properties": {
    "iso:country":"CH",
    "sg:address":"Creux-\u00e0-la-reine",
    "sg:city":"Villars-tiercelin",
    "sg:orig_category":"Herstellung von Elektromotoren, Generatoren U Transformatoren",
    "sg:postcode":"1058",
    "sg:province":"Vaud",
    "wof:name":"Jps/rlc S\u00e0rl",
    "wof:placetype":"venue"
},
  "geometry": {"coordinates":[6.8308701515,46.6445655823],"type":"Point"}
}