{
  "type": "Feature",
  "properties": {
    "iso:country":"CH",
    "sg:address":"Fischenh\u00f6lzlistrasse 31 8580 Amriswil. Postfach 1228",
    "sg:city":"Amriswil",
    "sg:orig_category":"Personal U Stellenvermittlung Unternehmensberatung",
    "sg:phone":"+41 71 411 80 76",
    "sg:postcode":"8580",
    "sg:province":"Thurgau",
    "wof:name":"Gpw Consulting & Kaderselektion Gmbh",
    "wof:placetype":"venue"
},
  "geometry": {"coordinates":[9.2975301743,47.5528564453],"type":"Point"}
}