{
  "type": "Feature",
  "properties": {
    "iso:country":"CH",
    "sg:address":"Petersburg 310",
    "sg:city":"Ramsen",
    "sg:orig_category":"Gartenbau",
    "sg:phone":"+41 52 743 11 25",
    "sg:postcode":"8262",
    "sg:province":"Schaffhausen",
    "wof:name":"Bruno Koll\u00f6ffel G\u00e4rtnerei & Gartenbau",
    "wof:placetype":"venue"
},
  "geometry": {"coordinates":[8.8203639984,47.7054290771],"type":"Point"}
}