{
  "type": "Feature",
  "properties": {
    "iso:country":"CH",
    "sg:address":"Lyon-strasse 18",
    "sg:city":"Basel",
    "sg:orig_category":"Detailhandel mit Getreide, Futtermitteln U Landesprodukten Sonstiger Detailhandel mit Metallwaren, A",
    "sg:phone":"+41 61 338 40 40",
    "sg:postcode":"4053",
    "sg:province":"Basel-Stadt",
    "wof:name":"Landi Reba Ag",
    "wof:placetype":"venue"
},
  "geometry": {"coordinates":[7.6073489189,47.5352897644],"type":"Point"}
}