{
  "type": "Feature",
  "properties": {
    "iso:country":"CH",
    "sg:address":"Br\u00fcnneliacker 6",
    "sg:city":"Z\u00fcrich",
    "sg:orig_category":"Reiseb\u00fcros U Reiseveranstalter",
    "sg:postcode":"8047",
    "sg:province":"Z\u00fcrich",
    "wof:name":"Argo-reisen",
    "wof:placetype":"venue"
},
  "geometry": {"coordinates":[-0.6475300193,39.0191192627],"type":"Point"}
}