{
  "type": "Feature",
  "properties": {
    "iso:country":"CH",
    "sg:address":"Buzibachstrasse 43",
    "sg:city":"Rothenburg",
    "sg:classifiers":[
        {
            "category":"Professional",
            "subcategory":"Computer Services",
            "type":"Services"
        }
    ],
    "sg:phone":"+41 41 289 22 22",
    "sg:postcode":"6023",
    "sg:province":"Luzern",
    "sg:tags":[
        "development",
        "software"
    ],
    "wof:name":"Dialog Verwaltungs-data Ag",
    "wof:placetype":"venue"
},
  "geometry": {"coordinates":[8.2555580139,47.0904579163],"type":"Point"}
}