{
  "type": "Feature",
  "properties": {
    "iso:country":"CH",
    "sg:address":"H\u00f6fliweg 36",
    "sg:city":"Lotzwil",
    "sg:orig_category":"Detailhandel mit Bekleidung",
    "sg:phone":"+41 62 922 37 09",
    "sg:postcode":"4932",
    "sg:province":"Bern",
    "wof:name":"De Lini Gmbh",
    "wof:placetype":"venue"
},
  "geometry": {"coordinates":[7.792935,47.189701],"type":"Point"}
}