{
  "type": "Feature",
  "properties": {
    "iso:country":"CH",
    "sg:address":"Chamerstrasse 79 6300 Zug. Postfach",
    "sg:city":"Zug",
    "sg:orig_category":"Softwareentwicklung U beratung",
    "sg:phone":"+41 22 300 22 89",
    "sg:postcode":"6300",
    "sg:province":"Zug",
    "wof:name":"Info-quest, Ciciulla Alfredo",
    "wof:placetype":"venue"
},
  "geometry": {"coordinates":[6.1295170784,46.183971405],"type":"Point"}
}