{
  "type": "Feature",
  "properties": {
    "iso:country":"CH",
    "sg:address":"Clos Des Ecornaches 36",
    "sg:city":"Th\u00f4nex",
    "sg:orig_category":"Fahrschulen, Flugschulen",
    "sg:phone":"+41 22 349 86 58",
    "sg:postcode":"1226",
    "sg:province":"Gen\u00e8ve",
    "wof:name":"Jean-marc Etienne Auto-\u00e9cole",
    "wof:placetype":"venue"
},
  "geometry": {"coordinates":[6.1942601204,46.1849708557],"type":"Point"}
}