{
  "type": "Feature",
  "properties": {
    "iso:country":"CH",
    "sg:address":"B\u00e4renfelserstrasse 20",
    "sg:city":"Basel",
    "sg:orig_category":"Bauschreinerei Herstellung von Fenstern U T\u00fcren aus Holz",
    "sg:phone":"+41 61 691 05 05",
    "sg:postcode":"4057",
    "sg:province":"Basel-Stadt",
    "wof:name":"Gutzwiller Gmbh Bau-& M\u00f6belschreinerei",
    "wof:placetype":"venue"
},
  "geometry": {"coordinates":[7.588036,47.566944],"type":"Point"}
}