{
  "type": "Feature",
  "properties": {
    "iso:country":"CH",
    "sg:address":"Kreuzstrasse 26",
    "sg:city":"Z\u00fcrich",
    "sg:orig_category":"Fernmeldedienste",
    "sg:phone":"+41 12697171",
    "sg:postcode":"8008",
    "sg:province":"Z\u00fcrich",
    "wof:name":"Rtl (schweiz) Fernseh Ag",
    "wof:placetype":"venue"
},
  "geometry": {"coordinates":[8.5491008759,47.3628196716],"type":"Point"}
}