{
  "type": "Feature",
  "properties": {
    "iso:country":"CH",
    "sg:address":"Kornweg 8",
    "sg:city":"Vaduz",
    "sg:orig_category":"Detailhandel mit Teppichen Verlegen von Fussboden",
    "sg:phone":"+41 79 600 29 89",
    "sg:postcode":"9490",
    "wof:name":"Richard Biedermann Tebiva Inneneinrichtungen",
    "wof:placetype":"venue"
},
  "geometry": {"coordinates":[9.516579628,47.1358413696],"type":"Point"}
}