{
  "type": "Feature",
  "properties": {
    "iso:country":"CH",
    "sg:address":"Hohenemserstr.3",
    "sg:city":"Diepoldsau",
    "sg:orig_category":"Erbringung von Dienstleistungen f\u00fcr Unternehmen Herstellung von elektrischen Ausr\u00fcstungen",
    "sg:phone":"+41 71 733 24 58",
    "sg:postcode":"9444",
    "sg:province":"St. Gallen",
    "wof:name":"Keller Electronic Elektronikfertigung",
    "wof:placetype":"venue"
},
  "geometry": {"coordinates":[9.6566734314,47.3849029541],"type":"Point"}
}