{
  "type": "Feature",
  "properties": {
    "addr:full":"Chemin Des Epinettes 8 Marly Fribourg 1723",
    "addr:housenumber":"8",
    "addr:postcode":"1723",
    "addr:street":"Chemin Des Epinettes",
    "iso:country":"CH",
    "sg:address":"Chemin Des Epinettes 8",
    "sg:city":"Marly",
    "sg:orig_category":"Alters U Pflegeheime Wohnheime",
    "sg:phone":"+41 26 436 27 22",
    "sg:postcode":"1723",
    "sg:province":"Fribourg",
    "wof:name":"R\u00e9sidence Pour Personne \u00e2g\u00e9es \u00ables Epinettes\u00bb",
    "wof:placetype":"venue"
},
  "geometry": {"coordinates":[7.157958,46.776272],"type":"Point"}
}