{
  "type": "Feature",
  "properties": {
    "addr:full":"Rebgarten 19 Romanshorn Thurgau 8590",
    "addr:housenumber":"19",
    "addr:postcode":"8590",
    "addr:street":"Rebgarten",
    "iso:country":"CH",
    "sg:address":"Rebgarten 19",
    "sg:city":"Romanshorn",
    "sg:orig_category":"Detailhandel mit Brennstoffen U Heizmaterial Grosshandel mit festen Brennstoffen U Mineral\u00f6lerzeugni",
    "sg:phone":"+41 71 463 16 63",
    "sg:postcode":"8590",
    "sg:province":"Thurgau",
    "wof:name":"Heutschi Paul",
    "wof:placetype":"venue"
},
  "geometry": {"coordinates":[9.369622,47.562618],"type":"Point"}
}