{
  "type": "Feature",
  "properties": {
    "addr:full":"M\u00fchlegasse 1 Zweisimmen Bern 3770",
    "addr:housenumber":"1",
    "addr:postcode":"3770",
    "addr:street":"Muehlegasse",
    "iso:country":"CH",
    "sg:address":"M\u00fchlegasse 1",
    "sg:city":"Zweisimmen",
    "sg:orig_category":"Advokaturb\u00fcros Notariate",
    "sg:phone":"+41 33 722 20 64",
    "sg:postcode":"3770",
    "sg:province":"Bern",
    "wof:name":"P. Schl\u00e4ppi & B. Balmer Advokatur- & Notariatsb\u00fcro",
    "wof:placetype":"venue"
},
  "geometry": {"coordinates":[7.372056,46.552883],"type":"Point"}
}