{
  "type": "Feature",
  "properties": {
    "iso:country":"CH",
    "sg:address":"Schaffhauserstrasse 5 8500 Frauenfeld. Postfach 3065",
    "sg:city":"Frauenfeld",
    "sg:orig_category":"Grosshandel mit Maschinen U Ausr\u00fcstungen Grosshandel mit sonstigen Maschinen U Ausr\u00fcstungen f\u00fcr Indu",
    "sg:phone":"+41 79 672 53 76",
    "sg:postcode":"8503",
    "sg:province":"Thurgau",
    "wof:name":"Masson Kommunaltechnik",
    "wof:placetype":"venue"
},
  "geometry": {"coordinates":[8.8892498016,47.5610313416],"type":"Point"}
}