{
  "type": "Feature",
  "properties": {
    "iso:country":"CH",
    "sg:address":"Hardstrasse 12",
    "sg:city":"Volketswil",
    "sg:orig_category":"Detailhandel mit M\u00f6beln Mechanische Werkst\u00e4tten",
    "sg:phone":"+41 19082626",
    "sg:postcode":"8604",
    "sg:province":"Z\u00fcrich",
    "wof:name":"Zulliger Ag",
    "wof:placetype":"venue"
},
  "geometry": {"coordinates":[8.6922254562,47.3872795105],"type":"Point"}
}