{
  "type": "Feature",
  "properties": {
    "iso:country":"CH",
    "sg:address":"Blumensteinstrasse 4",
    "sg:city":"Bern",
    "sg:orig_category":"Druck ohne Zeitungsdruck",
    "sg:postcode":"3012",
    "sg:province":"Bern",
    "wof:name":"Gito Ag",
    "wof:placetype":"venue"
},
  "geometry": {"coordinates":[7.4272022247,46.9550857544],"type":"Point"}
}