{
  "type": "Feature",
  "properties": {
    "iso:country":"CH",
    "sg:address":"Neuhofstr. 6",
    "sg:city":"Baar",
    "sg:classifiers":[
        {
            "category":"Health Services",
            "subcategory":"Medical Lab",
            "type":"Services"
        }
    ],
    "sg:phone":"+41 41 767 72 00",
    "sg:postcode":"6341",
    "sg:province":"Zug",
    "sg:tags":[
        "chemical",
        "pharmaceutical",
        "pharmacy"
    ],
    "wof:name":"Bristol-myers Squibb Gmbh",
    "wof:placetype":"venue"
},
  "geometry": {"coordinates":[8.513106,47.189991],"type":"Point"}
}