{
  "type": "Feature",
  "properties": {
    "iso:country":"CH",
    "sg:address":"1618",
    "sg:city":"Ch\u00e2tel-st-denis",
    "sg:orig_category":"Herstellung von Transportbeton",
    "sg:postcode":"1618",
    "sg:province":"Fribourg",
    "wof:name":"B\u00e9tonfrais Bulle Sa",
    "wof:placetype":"venue"
},
  "geometry": {"coordinates":[7.0834698677,46.7041091919],"type":"Point"}
}