{
  "type": "Feature",
  "properties": {
    "iso:country":"CH",
    "sg:address":"Cit\u00e9 Villars 6 1201 Gen\u00e8ve. Postfach",
    "sg:city":"Gen\u00e8ve",
    "sg:orig_category":"Interessenvertretungen",
    "sg:postcode":"1201",
    "sg:province":"Gen\u00e8ve",
    "wof:name":"Association Pro-krzysztofory",
    "wof:placetype":"venue"
},
  "geometry": {"coordinates":[6.123295784,46.2149009705],"type":"Point"}
}