{
  "type": "Feature",
  "properties": {
    "iso:country":"CH",
    "sg:address":"Via Cantonale 80",
    "sg:city":"Cugnasco",
    "sg:orig_category":"Mechanische Werkst\u00e4tten",
    "sg:phone":"+41 91 859 21 57",
    "sg:postcode":"6516",
    "sg:province":"Ticino",
    "wof:name":"Daniele Carrara Officina Meccanica",
    "wof:placetype":"venue"
},
  "geometry": {"coordinates":[8.9072704315,46.1733932495],"type":"Point"}
}