{
  "type": "Feature",
  "properties": {
    "iso:country":"CH",
    "sg:address":"Sch\u00f6nenwaldstrasse 5",
    "sg:city":"Biberist",
    "sg:orig_category":"Detailhandel mit Blumen U Pflanzen",
    "sg:phone":"+41 32 672 46 09",
    "sg:postcode":"4562",
    "sg:province":"Solothurn",
    "wof:name":"Eva Minder B\u00fchlmann Bl\u00dctenzauber",
    "wof:placetype":"venue"
},
  "geometry": {"coordinates":[7.561959,47.191414],"type":"Point"}
}