{
  "type": "Feature",
  "properties": {
    "addr:full":"R\u00f6ssligasse 20 Riehen Basel-Stadt 4125",
    "addr:housenumber":"20",
    "addr:postcode":"4125",
    "addr:street":"Roessligasse",
    "iso:country":"CH",
    "sg:address":"R\u00f6ssligasse 20",
    "sg:city":"Riehen",
    "sg:classifiers":[
        {
            "category":"Banks & Credit Unions",
            "subcategory":"Bank",
            "type":"Services"
        }
    ],
    "sg:phone":"+41 61 641 33 33",
    "sg:postcode":"4125",
    "sg:province":"Basel-Stadt",
    "wof:name":"Schweiz. Bankgesellschaft",
    "wof:placetype":"venue"
},
  "geometry": {"coordinates":[7.651324,47.585453],"type":"Point"}
}