{
  "type": "Feature",
  "properties": {
    "iso:country":"CH",
    "sg:address":"Haldenstrasse 1 6340 Baar. Postfach 2354",
    "sg:city":"Baar",
    "sg:orig_category":"Grosshandel mit B\u00fcromaschinen U einrichtungen Innenarchitekturb\u00fcros",
    "sg:phone":"+41 41 760 27 32",
    "sg:postcode":"6342",
    "sg:province":"Zug",
    "wof:name":"Heimgartner F. Ag",
    "wof:placetype":"venue"
},
  "geometry": {"coordinates":[8.5362234116,47.1954154968],"type":"Point"}
}