{
  "type": "Feature",
  "properties": {
    "iso:country":"CH",
    "sg:address":"Industriestrasse 22",
    "sg:city":"Selzach",
    "sg:classifiers":[
        {
            "category":"Professional",
            "subcategory":"Advertising",
            "type":"Services"
        }
    ],
    "sg:phone":"+41 32 641 65 50",
    "sg:postcode":"2545",
    "sg:province":"Solothurn",
    "sg:tags":[
        "article",
        "plexiglas"
    ],
    "wof:name":"Eurocryl Ag",
    "wof:placetype":"venue"
},
  "geometry": {"coordinates":[7.453928,47.198547],"type":"Point"}
}