{
  "type": "Feature",
  "properties": {
    "iso:country":"CH",
    "sg:address":"M\u00fchlenthalstrasse",
    "sg:city":"Schaffhausen",
    "sg:orig_category":"Grosshandel mit Eisenwaren sowie Installationsbedarf f\u00fcr Gas, Wasser U Heizung Herstellung von Hebez",
    "sg:postcode":"8200",
    "sg:province":"Schaffhausen",
    "wof:name":"Schmid & B\u00fchrer Ag",
    "wof:placetype":"venue"
},
  "geometry": {"coordinates":[8.6306409836,47.7000007629],"type":"Point"}
}