{
  "type": "Feature",
  "properties": {
    "iso:country":"CH",
    "sg:address":"En Bovery 1868 Collombey Case Postale 113",
    "sg:city":"Collombey",
    "sg:orig_category":"Herstellung von Metallkonstruktionen",
    "sg:phone":"+41 24 472 83 13",
    "sg:postcode":"1868",
    "sg:province":"Valais",
    "wof:name":"Meda Et Cie",
    "wof:placetype":"venue"
},
  "geometry": {"coordinates":[6.9432849884,46.2826385498],"type":"Point"}
}