{
  "type": "Feature",
  "properties": {
    "addr:full":"Jonas-furrer-strasse 20 Z\u00fcrich Z\u00fcrich 8046",
    "addr:housenumber":"20",
    "addr:postcode":"8046",
    "addr:street":"Jonas-Furrer-Strasse",
    "iso:country":"CH",
    "sg:address":"Jonas-furrer-strasse 20",
    "sg:city":"Z\u00fcrich",
    "sg:orig_category":"Arztpraxen",
    "sg:phone":"+41 19302292",
    "sg:postcode":"8046",
    "sg:province":"Z\u00fcrich",
    "wof:name":"Dr.med.georg Elsayan Spezialarzt Fmh",
    "wof:placetype":"venue"
},
  "geometry": {"coordinates":[8.804759,47.327957],"type":"Point"}
}