{
  "type": "Feature",
  "properties": {
    "iso:country":"CH",
    "sg:address":"Route D'anz\u00e8re 1974 Arbaz Case Postale 430",
    "sg:city":"Arbaz",
    "sg:orig_category":"Herstellung von Duft U K\u00f6rperpflegemitteln Herstellung von Seifen, Wasch U Reinigungsmitteln",
    "sg:phone":"+41 79 220 40 60",
    "sg:postcode":"1974",
    "sg:province":"Valais",
    "wof:name":"Foodclean Sa",
    "wof:placetype":"venue"
},
  "geometry": {"coordinates":[7.385187149,46.2734489441],"type":"Point"}
}