{
  "type": "Feature",
  "properties": {
    "iso:country":"CH",
    "sg:address":"Centralstrasse 10",
    "sg:city":"Diepoldsau",
    "sg:orig_category":"Werbeagenturen",
    "sg:phone":"+41 71 727 96 11",
    "sg:postcode":"9444",
    "sg:province":"St. Gallen",
    "wof:name":"Daniel Waibel Werbeatelier",
    "wof:placetype":"venue"
},
  "geometry": {"coordinates":[9.6572189331,47.3865203857],"type":"Point"}
}