{
  "type": "Feature",
  "properties": {
    "addr:full":"Im Veltlin 34 8706 Meilen. Postfach Meilen Z\u00fcrich 8706",
    "addr:housenumber":"34",
    "addr:postcode":"8706 meilen. postfach;8706",
    "addr:street":"Im Veltlin",
    "iso:country":"CH",
    "sg:address":"Im Veltlin 34 8706 Meilen. Postfach",
    "sg:city":"Meilen",
    "sg:orig_category":"Allgemeiner Hoch U Tiefbau",
    "sg:postcode":"8706",
    "sg:province":"Z\u00fcrich",
    "wof:name":"Arnold Andy Bauunternehmung",
    "wof:placetype":"venue"
},
  "geometry": {"coordinates":[8.644297,47.275429],"type":"Point"}
}