{
  "type": "Feature",
  "properties": {
    "iso:country":"CH",
    "sg:address":"Arbonerstrasse 13",
    "sg:city":"Wittenbach",
    "sg:orig_category":"G\u00fcterbef\u00f6rderung im Strassenverkehr",
    "sg:postcode":"9303",
    "wof:name":"Walter Ackermann Transporte",
    "wof:placetype":"venue"
},
  "geometry": {"coordinates":[9.3944997787,47.4631614685],"type":"Point"}
}