{
  "type": "Feature",
  "properties": {
    "iso:country":"CH",
    "sg:address":"Rheinstrasse 10",
    "sg:city":"Frauenfeld",
    "sg:orig_category":"Allgemeiner Hoch U Tiefbau",
    "sg:phone":"+41 52 722 42 02",
    "sg:postcode":"8500",
    "sg:province":"Thurgau",
    "wof:name":"Zani Ag Frauenfeld",
    "wof:placetype":"venue"
},
  "geometry": {"coordinates":[8.895958,47.556274],"type":"Point"}
}