{
  "type": "Feature",
  "properties": {
    "iso:country":"CH",
    "sg:address":"Kleinh\u00fcningerstrasse 96 4057 Basel. Postfach",
    "sg:city":"Basel",
    "sg:orig_category":"Sonstiger spezialisierter Hoch U Tiefbau",
    "sg:phone":"+41 61 631 60 86",
    "sg:postcode":"4057",
    "sg:province":"Basel-Stadt",
    "wof:name":"Md Ger\u00fcste + Rollladenbau Gmbh Ger\u00fcst- U. Rollladenbauarbeiten Usw",
    "wof:placetype":"venue"
},
  "geometry": {"coordinates":[7.5896701813,47.5769767761],"type":"Point"}
}