{
  "type": "Feature",
  "properties": {
    "iso:country":"CH",
    "sg:address":"Inselstrasse 76 4057 Basel. Postfach",
    "sg:city":"Basel",
    "sg:orig_category":"Grosshandel mit Eisenwaren sowie Installationsbedarf f\u00fcr Gas, Wasser U Heizung",
    "sg:postcode":"4051",
    "sg:province":"Basel-Stadt",
    "wof:name":"Kingshop-center Sagl",
    "wof:placetype":"venue"
},
  "geometry": {"coordinates":[9.1283597946,46.2375984192],"type":"Point"}
}