{
  "type": "Feature",
  "properties": {
    "addr:full":"Kreuzgasse Latterbach Bern 3758",
    "addr:postcode":"3758",
    "addr:street":"Kreuzgasse",
    "iso:country":"CH",
    "sg:address":"Kreuzgasse",
    "sg:city":"Latterbach",
    "sg:orig_category":"Autospenglereien",
    "sg:phone":"+41 33 681 17 12",
    "sg:postcode":"3758",
    "sg:province":"Bern",
    "wof:name":"Eugen Marschall Carrosserie",
    "wof:placetype":"venue"
},
  "geometry": {"coordinates":[7.57805,46.663994],"type":"Point"}
}