{
  "type": "Feature",
  "properties": {
    "iso:country":"CH",
    "sg:address":"Frohburgstrasse 3",
    "sg:city":"Luzern",
    "sg:orig_category":"Nationale Postdienste",
    "sg:phone":"+41 61 411 46 39",
    "sg:postcode":"6002",
    "sg:province":"Luzern",
    "wof:name":"Die Schweizerische Post M\u00fcnchenstein 3 Zollweiden",
    "wof:placetype":"venue"
},
  "geometry": {"coordinates":[7.6167430878,47.5231018066],"type":"Point"}
}