{
  "type": "Feature",
  "properties": {
    "iso:country":"CH",
    "sg:address":"Tann\u00e4gertenstrasse 33",
    "sg:city":"D\u00fcrnten",
    "sg:orig_category":"Blumen U Zierpflanzenbau Detailhandel mit Blumen U Pflanzen",
    "sg:phone":"+41 55 240 18 15",
    "sg:postcode":"8635",
    "sg:province":"Z\u00fcrich",
    "wof:name":"Schoch",
    "wof:placetype":"venue"
},
  "geometry": {"coordinates":[8.835864,47.267132],"type":"Point"}
}