{
  "type": "Feature",
  "properties": {
    "iso:country":"CH",
    "sg:address":"Br\u00fcggli",
    "sg:city":"Wildhaus",
    "sg:orig_category":"Sportvereine Turnen Vereine Damen",
    "sg:postcode":"9658",
    "sg:province":"St. Gallen",
    "wof:name":"Damenturnverein Stv Wohlen",
    "wof:placetype":"venue"
},
  "geometry": {"coordinates":[8.2859992981,47.3463096619],"type":"Point"}
}