{
  "type": "Feature",
  "properties": {
    "iso:country":"CH",
    "sg:address":"Zentralstrasse 9 6003 Luzern. Postfach",
    "sg:city":"Luzern",
    "sg:orig_category":"Informatikschulen",
    "sg:phone":"+41 21 652 77 11",
    "sg:postcode":"6002",
    "sg:province":"Luzern",
    "wof:name":"Institut Suisse D'enseignement De L'informatique De Gestion",
    "wof:placetype":"venue"
},
  "geometry": {"coordinates":[6.6671361923,46.5355529785],"type":"Point"}
}