{
  "type": "Feature",
  "properties": {
    "iso:country":"CH",
    "sg:address":"Bernrainstrasse 3",
    "sg:city":"Kreuzlingen",
    "sg:orig_category":"Detailhandel mit Brot, Back U S\u00fcsswaren",
    "sg:phone":"+41 79 605 21 33",
    "sg:postcode":"8280",
    "sg:province":"Thurgau",
    "wof:name":"N\u00fcesch's B\u00e4ckerei, N\u00fcesch Gustav",
    "wof:placetype":"venue"
},
  "geometry": {"coordinates":[9.161899,47.647652],"type":"Point"}
}