{
  "type": "Feature",
  "properties": {
    "iso:country":"CH",
    "sg:address":"Buchbergstrasse 51 9425 Thal. Postfach",
    "sg:city":"Thal",
    "sg:orig_category":"Erbringung von Dienstleistungen f\u00fcr Unternehmen",
    "sg:postcode":"9425",
    "sg:province":"St. Gallen",
    "wof:name":"Eyelies Gmbh",
    "wof:placetype":"venue"
},
  "geometry": {"coordinates":[9.5668134689,47.475025177],"type":"Point"}
}