{
  "type": "Feature",
  "properties": {
    "iso:country":"CH",
    "sg:address":"Via Ciseri 23",
    "sg:city":"Locarno",
    "sg:orig_category":"Grosshandel mit Getr\u00e4nken Grosshandel mit Wein U Spirituosen",
    "sg:phone":"+41 91 751 39 81",
    "sg:postcode":"6600",
    "sg:province":"Ticino",
    "wof:name":"Marchesi Di Barolo International Sa, Lussemburgo, Succursale Di Locarno",
    "wof:placetype":"venue"
},
  "geometry": {"coordinates":[8.7961130142,46.1684074402],"type":"Point"}
}