{
  "type": "Feature",
  "properties": {
    "iso:country":"CH",
    "sg:address":"Schwantlern 49 9056 Gais. Postfach",
    "sg:city":"Gais",
    "sg:orig_category":"Wohnheime",
    "sg:phone":"+41 71 793 11 53",
    "sg:postcode":"9056",
    "sg:province":"Appenzell Ausserrhoden",
    "wof:name":"Wohnheim F\u00fcr Asylbewerber",
    "wof:placetype":"venue"
},
  "geometry": {"coordinates":[9.4577045441,47.3640975952],"type":"Point"}
}