{
  "type": "Feature",
  "properties": {
    "iso:country":"CH",
    "sg:address":"Wissmannstrasse 9 8057 Z\u00fcrich. Postfach",
    "sg:city":"Z\u00fcrich",
    "sg:orig_category":"Gesundheitswesen",
    "sg:postcode":"8057",
    "sg:province":"Z\u00fcrich",
    "wof:name":"Kispex Kinder-spitex Kanton Z\u00fcrich",
    "wof:placetype":"venue"
},
  "geometry": {"coordinates":[8.5362682343,47.3938293457],"type":"Point"}
}