{
  "type": "Feature",
  "properties": {
    "iso:country":"CH",
    "sg:address":"Coteau Chemin Du 15",
    "sg:city":"Aclens",
    "sg:orig_category":"Grosshandel mit Erzen U Metallen",
    "sg:phone":"+41 52 742 02 27",
    "sg:postcode":"1123",
    "sg:province":"Vaud",
    "wof:name":"Trigo Ag",
    "wof:placetype":"venue"
},
  "geometry": {"coordinates":[9.0263586044,47.6082954407],"type":"Point"}
}