{
  "type": "Feature",
  "properties": {
    "iso:country":"CH",
    "sg:address":"Heidenlochstrasse 46",
    "sg:city":"Liestal",
    "sg:orig_category":"Herstellung von elektrischen Haushaltsger\u00e4ten",
    "sg:phone":"+41 61 922 18 66",
    "sg:postcode":"4410",
    "sg:province":"Basel-Landschaft",
    "wof:name":"Dettwiler Gmbh Kaffeemaschinen",
    "wof:placetype":"venue"
},
  "geometry": {"coordinates":[7.7468519211,47.4833106995],"type":"Point"}
}