{
  "type": "Feature",
  "properties": {
    "iso:country":"CH",
    "sg:address":"Socinstrasse 3 4051 Basel. Postfach",
    "sg:city":"Basel",
    "sg:orig_category":"Dienstleistungen von Beteiligungsgesellschaften Sonstige Finanzierungsinstitutionen",
    "sg:phone":"+41 61 263 30 70",
    "sg:postcode":"4051",
    "sg:province":"Basel-Stadt",
    "wof:name":"Berg Industrie Holding Ag",
    "wof:placetype":"venue"
},
  "geometry": {"coordinates":[7.5795388222,47.5580635071],"type":"Point"}
}