{
  "type": "Feature",
  "properties": {
    "iso:country":"CH",
    "sg:address":"Br\u00fchlstrasse 3",
    "sg:city":"Oberkulm",
    "sg:orig_category":"Kinderkrippen U horte",
    "sg:phone":"+41 62 776 22 81",
    "sg:postcode":"5727",
    "sg:province":"Aargau",
    "wof:name":"Spielgruppe Pingu",
    "wof:placetype":"venue"
},
  "geometry": {"coordinates":[8.112244606,47.3024711609],"type":"Point"}
}