{
  "type": "Feature",
  "properties": {
    "iso:country":"CH",
    "sg:address":"Vordere Vorstadt 16",
    "sg:city":"Aarau",
    "sg:orig_category":"Sonstige Institutionen des Sozialwesens ohne Beherbergung",
    "sg:phone":"+41 55 410 28 55",
    "sg:postcode":"5000",
    "sg:province":"Aargau",
    "wof:name":"Agbas Ausl\u00e4nderberatungs- Stelle Im Kanton Schwyz",
    "wof:placetype":"venue"
},
  "geometry": {"coordinates":[8.7776603699,47.200843811],"type":"Point"}
}