{
  "type": "Feature",
  "properties": {
    "addr:full":"Ch\u00e4lenrain 6053 Alpnachstad. Postfach Alpnachstad Obwalden 6053",
    "addr:housenumber":"6053",
    "addr:postcode":"6053",
    "addr:street":"Alpnachstad. Postfach",
    "iso:country":"CH",
    "sg:address":"Ch\u00e4lenrain 6053 Alpnachstad. Postfach",
    "sg:city":"Alpnachstad",
    "sg:orig_category":"Architektur U Ingenieurb\u00fcros",
    "sg:phone":"+41 14318288",
    "sg:postcode":"6053",
    "sg:province":"Obwalden",
    "wof:name":"A O Technischer-dienst Gmbh",
    "wof:placetype":"venue"
},
  "geometry": {"coordinates":[8.272536,46.952061],"type":"Point"}
}