{
  "type": "Feature",
  "properties": {
    "iso:country":"CH",
    "sg:address":"Dorfstrasse 21",
    "sg:city":"Sch\u00fcpfen",
    "sg:classifiers":[
        {
            "category":"Travel",
            "subcategory":"Hotels & Motels",
            "type":"Entertainment"
        }
    ],
    "sg:phone":"+41 31790392",
    "sg:postcode":"3054",
    "sg:province":"Bern",
    "sg:tags":[
        "hotels",
        "mit",
        "restaurant"
    ],
    "wof:name":"Meier-etter Fritz",
    "wof:placetype":"venue"
},
  "geometry": {"coordinates":[7.3764028549,47.0370407104],"type":"Point"}
}