{
  "type": "Feature",
  "properties": {
    "iso:country":"CH",
    "sg:address":"Kirchstrasse 25",
    "sg:city":"Sulgen",
    "sg:orig_category":"Detailhandel mit Geschenkartikeln U Souvenirs",
    "sg:phone":"+41 71 642 17 64",
    "sg:postcode":"8583",
    "sg:province":"Thurgau",
    "wof:name":"Lotti Frei Geschenkladen",
    "wof:placetype":"venue"
},
  "geometry": {"coordinates":[9.1842975616,47.5433235168],"type":"Point"}
}