{
  "type": "Feature",
  "properties": {
    "iso:country":"CH",
    "sg:address":"Ebnetstrasse 48",
    "sg:city":"Dinhard",
    "sg:orig_category":"Softwareentwicklung U beratung",
    "sg:phone":"+41 52 336 16 36",
    "sg:postcode":"8474",
    "sg:province":"Z\u00fcrich",
    "wof:name":"Unikis Richard Schmalz Softwareentwicklung",
    "wof:placetype":"venue"
},
  "geometry": {"coordinates":[8.7640628815,47.5576248169],"type":"Point"}
}