{
  "type": "Feature",
  "properties": {
    "iso:country":"CH",
    "sg:address":"Flugplatzstrasse 70",
    "sg:city":"Kehrsatz",
    "sg:orig_category":"Malerei-Gipserei Stukkateurgewerbe, Gipserei U Verputzerei",
    "sg:phone":"+41 31 961 08 24",
    "sg:postcode":"3122",
    "sg:province":"Bern",
    "wof:name":"Ernst & Golda Hasler Gipsergesch\u00e4ft",
    "wof:placetype":"venue"
},
  "geometry": {"coordinates":[7.479434967,46.9121856689],"type":"Point"}
}