{
  "type": "Feature",
  "properties": {
    "iso:country":"CH",
    "sg:address":"Maladi\u00e8re Route De La 22",
    "sg:city":"Chavannes-renens",
    "sg:orig_category":"Non-Classified Establishments",
    "sg:postcode":"1022",
    "sg:province":"Vaud",
    "wof:name":"Alcom Services, Rinaldo Vicinanza",
    "wof:placetype":"venue"
},
  "geometry": {"coordinates":[6.5755262375,46.5277023315],"type":"Point"}
}