{
  "type": "Feature",
  "properties": {
    "iso:country":"CH",
    "sg:address":"Giebelstrasse",
    "sg:city":"Root",
    "sg:orig_category":"Elektroinstallation",
    "sg:phone":"+41 41 450 14 42",
    "sg:postcode":"6037",
    "sg:province":"Luzern",
    "wof:name":"Chrimo Temp Gunz Christian",
    "wof:placetype":"venue"
},
  "geometry": {"coordinates":[8.3810300827,47.1121368408],"type":"Point"}
}