{
  "type": "Feature",
  "properties": {
    "iso:country":"CH",
    "sg:address":"Denkmalstrasse 2 6006 Luzern. Postfach",
    "sg:city":"Luzern",
    "sg:orig_category":"Softwareentwicklung U beratung",
    "sg:phone":"+41 41 410 37 03",
    "sg:postcode":"6006",
    "sg:province":"Luzern",
    "wof:name":"Npt Ag Software; Beratung, Erstellung, Vertrieb. Hardwarehandel Usw",
    "wof:placetype":"venue"
},
  "geometry": {"coordinates":[8.3109292984,47.0576553345],"type":"Point"}
}