{
  "type": "Feature",
  "properties": {
    "iso:country":"CH",
    "sg:address":"Lettenstrasse 9",
    "sg:city":"Rotkreuz",
    "sg:orig_category":"Unternehmensberatung",
    "sg:postcode":"6343",
    "sg:province":"Zug",
    "wof:name":"Linus Oehen",
    "wof:placetype":"venue"
},
  "geometry": {"coordinates":[8.4327220917,47.1469917297],"type":"Point"}
}