{
  "type": "Feature",
  "properties": {
    "iso:country":"CH",
    "sg:address":"Route De Rolle 20",
    "sg:city":"St-prex",
    "sg:orig_category":"Grosshandel mit Eisenwaren sowie Installationsbedarf f\u00fcr Gas, Wasser U Heizung Grosshandel mit Werkz",
    "sg:phone":"+41 21 806 43 33",
    "sg:postcode":"1162",
    "sg:province":"Vaud",
    "wof:name":"Manatec Sa",
    "wof:placetype":"venue"
},
  "geometry": {"coordinates":[6.4542880058,46.480052948],"type":"Point"}
}