{
  "type": "Feature",
  "properties": {
    "iso:country":"CH",
    "sg:address":"Mellingerstrasse 15",
    "sg:city":"H\u00e4gglingen",
    "sg:orig_category":"Haltung von Gefl\u00fcgel",
    "sg:phone":"+41 56 443 15 35",
    "sg:postcode":"5607",
    "sg:province":"Aargau",
    "wof:name":"Hans Pfander Gefl\u00fcgelfarm",
    "wof:placetype":"venue"
},
  "geometry": {"coordinates":[8.1511306763,47.4290733337],"type":"Point"}
}