{
  "type": "Feature",
  "properties": {
    "iso:country":"CH",
    "sg:address":"Dorf",
    "sg:city":"Br\u00fcnisried",
    "sg:orig_category":"RESTAURANTS: TEA-ROOMS",
    "sg:phone":"+41 26 419 12 12",
    "sg:postcode":"1719",
    "sg:province":"Fribourg",
    "wof:name":"Restaurant Zur Linde Br\u00fcnisried, Rappo Margrit",
    "wof:placetype":"venue"
},
  "geometry": {"coordinates":[7.2786340714,46.7587509155],"type":"Point"}
}