{
  "type": "Feature",
  "properties": {
    "iso:country":"CH",
    "sg:address":"Im Lindenacher 20",
    "sg:city":"Bassersdorf",
    "sg:orig_category":"Sonstiger Grosshandel",
    "sg:postcode":"8303",
    "sg:province":"Z\u00fcrich",
    "wof:name":"San Import, Export, G\u00f6kcay Ahmet",
    "wof:placetype":"venue"
},
  "geometry": {"coordinates":[8.6331157684,47.4418640137],"type":"Point"}
}