{
  "type": "Feature",
  "properties": {
    "addr:full":"R\u00fcnenbergerstrasse 28 Gelterkinden Basel-Landschaft 4460",
    "addr:housenumber":"28",
    "addr:postcode":"4460",
    "addr:street":"Ruenenbergerstrasse",
    "iso:country":"CH",
    "sg:address":"R\u00fcnenbergerstrasse 28",
    "sg:city":"Gelterkinden",
    "sg:orig_category":"Allgemeiner Hoch U Tiefbau Allgemeiner Hochbau",
    "sg:phone":"+41 62 299 00 72",
    "sg:postcode":"4460",
    "sg:province":"Basel-Landschaft",
    "wof:name":"Tettoni Ag",
    "wof:placetype":"venue"
},
  "geometry": {"coordinates":[7.860164,47.46043],"type":"Point"}
}