{
  "type": "Feature",
  "properties": {
    "iso:country":"CH",
    "sg:address":"Bienenweg 420",
    "sg:city":"Wohlenschwil",
    "sg:orig_category":"Architekturb\u00fcros",
    "sg:phone":"+41 56 470 22 11",
    "sg:postcode":"5512",
    "sg:province":"Aargau",
    "wof:name":"Rolf Schoch Architekturb\u00fcro",
    "wof:placetype":"venue"
},
  "geometry": {"coordinates":[8.292766,47.449081],"type":"Point"}
}