{
  "type": "Feature",
  "properties": {
    "iso:country":"CH",
    "sg:address":"Rigiweg 7",
    "sg:city":"Udligenswil",
    "sg:orig_category":"Wirtschaftspr\u00fcfung, Steuerberatung U Treuhand",
    "sg:phone":"+41 41 372 05 51",
    "sg:postcode":"6044",
    "sg:province":"Luzern",
    "wof:name":"Dutch-swiss Financial, Advising & Investment Ag",
    "wof:placetype":"venue"
},
  "geometry": {"coordinates":[8.4044084549,47.0902862549],"type":"Point"}
}