{
  "type": "Feature",
  "properties": {
    "iso:country":"CH",
    "sg:address":"Alte D\u00fcbendorfer Str. 20 Pf 274",
    "sg:city":"Dietlikon",
    "sg:classifiers":[
        {
            "category":"Wholesale",
            "subcategory":"Machinery & Supplies",
            "type":"Manufacturing & Wholesale Goods"
        }
    ],
    "sg:phone":"+41 4118352300",
    "sg:postcode":"8305",
    "sg:province":"Z\u00fcrich",
    "sg:tags":[
        "handling",
        "material",
        "-",
        "machine",
        "equipment",
        "engineering",
        "mechanical"
    ],
    "wof:name":"Linde Lansing F\u00d6rdertechnik Ag",
    "wof:placetype":"venue"
},
  "geometry": {"coordinates":[8.6181192398,47.423160553],"type":"Point"}
}