{
  "type": "Feature",
  "properties": {
    "iso:country":"CH",
    "sg:address":"6939",
    "sg:city":"Arosio",
    "sg:orig_category":"Grosshandel mit Eisenwaren sowie Installationsbedarf f\u00fcr Gas, Wasser U Heizung Handelsvermittlung U ",
    "sg:phone":"+41 91 609 12 59",
    "sg:postcode":"6939",
    "sg:province":"Ticino",
    "wof:name":"Tegro Ag Succursale Ticino",
    "wof:placetype":"venue"
},
  "geometry": {"coordinates":[8.9027500153,46.0467605591],"type":"Point"}
}