{
  "type": "Feature",
  "properties": {
    "iso:country":"CH",
    "sg:address":"Rue Eug\u00e8ne-marziano 19",
    "sg:city":"Gen\u00e8ve",
    "sg:orig_category":"Handel mit Automobilen",
    "sg:phone":"+41 81 413 55 00",
    "sg:postcode":"1200",
    "sg:province":"Gen\u00e8ve",
    "wof:name":"Talgarage Davos Ag",
    "wof:placetype":"venue"
},
  "geometry": {"coordinates":[9.8360786438,46.8007774353],"type":"Point"}
}