{
  "type": "Feature",
  "properties": {
    "iso:country":"CH",
    "sg:address":"R\u00fcteliweg",
    "sg:city":"Mettmenstetten",
    "sg:orig_category":"Mit Sport verbundene T\u00e4tigkeiten",
    "sg:phone":"+41 17670961",
    "sg:postcode":"8932",
    "sg:province":"Z\u00fcrich",
    "wof:name":"Pony-hof Reitschule",
    "wof:placetype":"venue"
},
  "geometry": {"coordinates":[8.4567127228,47.2418289185],"type":"Point"}
}