{
  "type": "Feature",
  "properties": {
    "iso:country":"CH",
    "sg:address":"Chemin De Garmaise 3a 1251 Gy. Postfach",
    "sg:city":"Gy",
    "sg:orig_category":"Maler U Glasergewerbe",
    "sg:postcode":"1251",
    "sg:province":"Gen\u00e8ve",
    "wof:name":"Grob Mayer Malergesch\u00e4ft",
    "wof:placetype":"venue"
},
  "geometry": {"coordinates":[8.8641748428,47.1955375671],"type":"Point"}
}