{
  "type": "Feature",
  "properties": {
    "iso:country":"CH",
    "sg:address":"Via Acquedotto 1 6814 Cadempino. Postfach",
    "sg:city":"Cadempino",
    "sg:orig_category":"Herstellung von medizinischen U chirurgischen Ger\u00e4ten sowie orthop\u00e4dischen Vorrichtungen",
    "sg:postcode":"6814",
    "sg:province":"Ticino",
    "wof:name":"Radio Invest Sa Apparecchiature Mediche; Compravendita, Gestione. Investimenti Nel Campo Medico Ecc",
    "wof:placetype":"venue"
},
  "geometry": {"coordinates":[8.9316387177,46.0365028381],"type":"Point"}
}