{
  "type": "Feature",
  "properties": {
    "iso:country":"CH",
    "sg:address":"Ifangstrasse 12a 8603 Schwerzenbach. Postfach",
    "sg:city":"Schwerzenbach",
    "sg:orig_category":"Allgemeinbildende weiterf\u00fchrende Schulen",
    "sg:postcode":"8609",
    "sg:province":"Z\u00fcrich",
    "wof:name":"Kuk, Tagesschule & Kurse Kaufmann Urs & Co",
    "wof:placetype":"venue"
},
  "geometry": {"coordinates":[8.663134,47.383125],"type":"Point"}
}