{
  "type": "Feature",
  "properties": {
    "iso:country":"CH",
    "sg:address":"Rond-point De La Jonction 8",
    "sg:city":"Gen\u00e8ve",
    "sg:classifiers":[
        {
            "category":"Restaurant",
            "type":"Food & Drink"
        }
    ],
    "sg:phone":"+41 22 321 54 98",
    "sg:postcode":"1205",
    "sg:province":"Gen\u00e8ve",
    "wof:name":"Caf\u00e9-restaurant Le Motelon",
    "wof:placetype":"venue"
},
  "geometry": {"coordinates":[6.1279888153,46.2011451721],"type":"Point"}
}