{
  "type": "Feature",
  "properties": {
    "iso:country":"CH",
    "sg:address":"Davidsbodenstrasse 39",
    "sg:city":"Basel",
    "sg:orig_category":"Interessenvertretungen",
    "sg:phone":"+41 61 321 28 12",
    "sg:postcode":"4056",
    "sg:province":"Basel-Stadt",
    "wof:name":"Esquina Caliente Spaniol & Tosin",
    "wof:placetype":"venue"
},
  "geometry": {"coordinates":[7.5760979652,47.566078186],"type":"Point"}
}