{
  "type": "Feature",
  "properties": {
    "iso:country":"CH",
    "sg:address":"1421",
    "sg:city":"Grandevent",
    "sg:orig_category":"Detailhandel mit Antiquit\u00e4ten Innendekorationsateliers",
    "sg:phone":"+41 24 436 11 42",
    "sg:postcode":"1421",
    "sg:province":"Vaud",
    "wof:name":"Claude Ponzio Tapiss.-d\u00e9corateur Antiquit\u00e9s",
    "wof:placetype":"venue"
},
  "geometry": {"coordinates":[6.59886,46.844872],"type":"Point"}
}