{
  "type": "Feature",
  "properties": {
    "iso:country":"CH",
    "sg:address":"Guschastrasse 13",
    "sg:city":"Sevelen",
    "sg:orig_category":"Grosshandel mit Parf\u00fcmerieartikeln U K\u00f6rperpflegemitteln Herstellung von Duft U K\u00f6rperpflegemitteln",
    "sg:phone":"+41 81 740 13 50",
    "sg:postcode":"9475",
    "sg:province":"St. Gallen",
    "wof:name":"Gerhard Klapp Cosmetics, Hessisch Lichtenau (d), Zweigniederlassung Sevelen",
    "wof:placetype":"venue"
},
  "geometry": {"coordinates":[9.4925508499,47.1252250671],"type":"Point"}
}