{
  "type": "Feature",
  "properties": {
    "iso:country":"CH",
    "sg:address":"Fichtenweg 1",
    "sg:city":"Lommiswil",
    "sg:orig_category":"Fachdetailhandel in Verkaufsr\u00e4umen",
    "sg:postcode":"4514",
    "sg:province":"Solothurn",
    "wof:name":"Power Sports-trading Gmbh",
    "wof:placetype":"venue"
},
  "geometry": {"coordinates":[7.4722709656,47.2279472351],"type":"Point"}
}