{
  "type": "Feature",
  "properties": {
    "iso:country":"CH",
    "sg:address":"Dorfstrasse 38",
    "sg:city":"Baar",
    "sg:orig_category":"Non-Classified Establishments",
    "sg:phone":"+41 71 311 31 40",
    "sg:postcode":"6340",
    "sg:province":"Zug",
    "wof:name":"Reber Ag Transport Und Handelsgesellschaft",
    "wof:placetype":"venue"
},
  "geometry": {"coordinates":[9.3080587387,47.4074172974],"type":"Point"}
}