{
  "type": "Feature",
  "properties": {
    "iso:country":"CH",
    "sg:address":"Nidaugasse 8",
    "sg:city":"Biel/bienne",
    "sg:orig_category":"Zahnarztpraxen",
    "sg:phone":"+41 32 323 16 60",
    "sg:postcode":"2502",
    "sg:province":"Bern",
    "wof:name":"Dr.med.dent.roland Fr\u00f6hlicher Zahnarzt",
    "wof:placetype":"venue"
},
  "geometry": {"coordinates":[7.2454848289,47.1402053833],"type":"Point"}
}