{
  "type": "Feature",
  "properties": {
    "iso:country":"CH",
    "sg:address":"Rue De Chantepoulet 1-3",
    "sg:city":"Gen\u00e8ve",
    "sg:orig_category":"Grosshandel mit B\u00fcromaschinen Grosshandel mit Datenverarbeitungsger\u00e4ten",
    "sg:phone":"+41 22 732 49 39",
    "sg:postcode":"1201",
    "sg:province":"Gen\u00e8ve",
    "wof:name":"S-quell Software Sa",
    "wof:placetype":"venue"
},
  "geometry": {"coordinates":[6.1454720497,46.2079353333],"type":"Point"}
}