{
  "type": "Feature",
  "properties": {
    "iso:country":"CH",
    "sg:address":"St. Gallerstrasse 161",
    "sg:city":"Jona",
    "sg:orig_category":"Versicherungen Hauptagenturen",
    "sg:phone":"+41 56 622 61 12",
    "sg:postcode":"8645",
    "sg:province":"St. Gallen",
    "wof:name":"Alpina Versicherungen Hauptagentur",
    "wof:placetype":"venue"
},
  "geometry": {"coordinates":[8.2719163895,47.348072052],"type":"Point"}
}