{
  "type": "Feature",
  "properties": {
    "iso:country":"CH",
    "sg:address":"Felsenweg 28",
    "sg:city":"D\u00f6ttingen",
    "sg:orig_category":"G\u00fcterbef\u00f6rderung im Strassenverkehr",
    "sg:phone":"+41 56 245 14 83",
    "sg:postcode":"5312",
    "sg:province":"Aargau",
    "wof:name":"Keller Johann Transporte",
    "wof:placetype":"venue"
},
  "geometry": {"coordinates":[8.2594852448,47.5740432739],"type":"Point"}
}