{
  "type": "Feature",
  "properties": {
    "iso:country":"CH",
    "sg:address":"Pr\u00e9 D'emoz Chemin De 14",
    "sg:city":"Aigle",
    "sg:orig_category":"Unclassifiable Establishments",
    "sg:phone":"+41 24 466 91 22",
    "sg:postcode":"1860",
    "sg:province":"Vaud",
    "wof:name":"Vnet S\u00e0rl",
    "wof:placetype":"venue"
},
  "geometry": {"coordinates":[6.9233641624,46.3436775208],"type":"Point"}
}