{
  "type": "Feature",
  "properties": {
    "iso:country":"CH",
    "sg:address":"M\u00f6\u00f6sliweg 13.",
    "sg:city":"Biel/bienne",
    "sg:orig_category":"Grosshandel mit Erzen U Metallen",
    "sg:postcode":"2500",
    "sg:province":"Bern",
    "wof:name":"Omni Internet Auktionen Gmbh",
    "wof:placetype":"venue"
},
  "geometry": {"coordinates":[9.3786430359,47.3904953003],"type":"Point"}
}