{
  "type": "Feature",
  "properties": {
    "iso:country":"CH",
    "sg:address":"Weissbadstrasse 8 B",
    "sg:city":"Appenzell",
    "sg:orig_category":"Non-Classified Establishments",
    "sg:postcode":"9050",
    "sg:province":"Appenzell Innerhoden",
    "wof:name":"Swiss Dental Export Gmbh",
    "wof:placetype":"venue"
},
  "geometry": {"coordinates":[9.5567455292,47.3799743652],"type":"Point"}
}