{
  "type": "Feature",
  "properties": {
    "iso:country":"CH",
    "sg:address":"Entlebucherstrasse 4",
    "sg:city":"Wolhusen",
    "sg:orig_category":"Fachdetailhandel mit pharmazeutischen Produkten",
    "sg:phone":"+41 41 490 12 17",
    "sg:postcode":"6110",
    "sg:province":"Luzern",
    "wof:name":"Central-apotheke Wolhusen, Dr. F. Schnyder",
    "wof:placetype":"venue"
},
  "geometry": {"coordinates":[8.0727529526,47.0586471558],"type":"Point"}
}