{
  "type": "Feature",
  "properties": {
    "iso:country":"CH",
    "sg:address":"Pumpwerkstatt 40 8105 Regensdorf. Postfach",
    "sg:city":"Z\u00fcrich",
    "sg:orig_category":"Hardwareberatung Herstellung von sonstigen elektrischen Ausr\u00fcstungen",
    "sg:phone":"+41 13083666",
    "sg:postcode":"8000",
    "sg:province":"Z\u00fcrich",
    "wof:name":"Issx Internet Security Systems Ag Internet-sicherheitssysteme, Hard, Software; Handel, Marketing, Beratung",
    "wof:placetype":"venue"
},
  "geometry": {"coordinates":[8.4608869553,47.4449310303],"type":"Point"}
}