{
  "type": "Feature",
  "properties": {
    "iso:country":"CH",
    "sg:address":"Altwingerten 1",
    "sg:city":"Dinhard",
    "sg:orig_category":"Softwareentwicklung U beratung",
    "sg:phone":"+41 61 713 80 90",
    "sg:postcode":"8474",
    "sg:province":"Z\u00fcrich",
    "wof:name":"Haberth\u00fcr Benjamin Informatikberatung",
    "wof:placetype":"venue"
},
  "geometry": {"coordinates":[7.5876002312,47.4954681396],"type":"Point"}
}