{
  "type": "Feature",
  "properties": {
    "iso:country":"CH",
    "sg:address":"Guisan Av. Du G\u00e9n\u00e9ral 29",
    "sg:city":"Sierre",
    "sg:orig_category":"Finanzierungsinstitutionen",
    "sg:postcode":"3960",
    "sg:province":"Valais",
    "wof:name":"Aryeh Dariush, Conseil Financier",
    "wof:placetype":"venue"
},
  "geometry": {"coordinates":[7.5288448334,46.2917785645],"type":"Point"}
}