{
  "type": "Feature",
  "properties": {
    "iso:country":"CH",
    "sg:address":"Jurastrasse 28",
    "sg:city":"Arch",
    "sg:orig_category":"Sanit\u00e4rinstallation",
    "sg:phone":"+41 32 679 38 35",
    "sg:postcode":"3296",
    "sg:province":"Bern",
    "wof:name":"Fredy Walther Sanit\u00e4re Anlagen",
    "wof:placetype":"venue"
},
  "geometry": {"coordinates":[7.4343647957,47.1688919067],"type":"Point"}
}