{
  "type": "Feature",
  "properties": {
    "iso:country":"CH",
    "sg:address":"G\u00fcetlistrasse 1",
    "sg:city":"Appenzell",
    "sg:orig_category":"Vereine Haus- and Grundeigent\u00fcmer",
    "sg:phone":"+41 32 352 06 06",
    "sg:postcode":"9050",
    "sg:province":"Appenzell Innerhoden",
    "wof:name":"Hauseigent\u00fcmerverband Amt B\u00fcren",
    "wof:placetype":"venue"
},
  "geometry": {"coordinates":[7.370882988,47.140007019],"type":"Point"}
}