{
  "type": "Feature",
  "properties": {
    "iso:country":"CH",
    "sg:address":"Avenue Louis-ruchonnet 33",
    "sg:city":"Lausanne",
    "sg:orig_category":"Detailhandel mit Tabakwaren Grosshandel mit Tabakwaren",
    "sg:phone":"+41 21 312 41 04",
    "sg:postcode":"1003",
    "sg:province":"Vaud",
    "wof:name":"Osvalt Presse",
    "wof:placetype":"venue"
},
  "geometry": {"coordinates":[6.6245379448,46.5190544128],"type":"Point"}
}