{
  "type": "Feature",
  "properties": {
    "iso:country":"CH",
    "sg:address":"Rue De La Tour 2",
    "sg:city":"St-prex",
    "sg:orig_category":"Detailhandel mit B\u00fcchern Detailhandel mit B\u00fcchern, Zeitungen, Schreib U Papeteriewaren",
    "sg:phone":"+41 21 329 09 06",
    "sg:postcode":"1162",
    "sg:province":"Vaud",
    "wof:name":"Librairie Oh 7\u00e8me Ciel Livres Rares Du Xx\u00e8me Si\u00e8gle",
    "wof:placetype":"venue"
},
  "geometry": {"coordinates":[6.635532,46.523392],"type":"Point"}
}