{
  "type": "Feature",
  "properties": {
    "iso:country":"CH",
    "sg:address":"1874",
    "sg:city":"Champ\u00e9ry",
    "sg:orig_category":"Finanzierungsinstitutionen",
    "sg:postcode":"1874",
    "sg:province":"Valais",
    "wof:name":"Lan Sa",
    "wof:placetype":"venue"
},
  "geometry": {"coordinates":[6.8706860542,46.1794052124],"type":"Point"}
}