{
  "type": "Feature",
  "properties": {
    "addr:full":"Hauptstrasse 14 M\u00e4genwil Aargau 5506",
    "addr:housenumber":"14",
    "addr:postcode":"5506",
    "addr:street":"Hauptstrasse",
    "iso:country":"CH",
    "sg:address":"Hauptstrasse 14",
    "sg:city":"M\u00e4genwil",
    "sg:orig_category":"Biotopes",
    "sg:phone":"+41 62 889 83 83",
    "sg:postcode":"5506",
    "sg:province":"Aargau",
    "wof:name":"Wiederkehr Hauswartungen Ag",
    "wof:placetype":"venue"
},
  "geometry": {"coordinates":[8.228605,47.4109],"type":"Point"}
}