{
  "type": "Feature",
  "properties": {
    "iso:country":"CH",
    "sg:address":"Hauptstrasse 81",
    "sg:city":"Einsiedeln",
    "sg:orig_category":"Arztpraxen",
    "sg:phone":"+41 71 911 50 40",
    "sg:postcode":"8840",
    "sg:province":"Schwyz",
    "wof:name":"Dr.med.beat Lenzin Spezialarzt Fmh",
    "wof:placetype":"venue"
},
  "geometry": {"coordinates":[9.05075,47.46595],"type":"Point"}
}