{
  "type": "Feature",
  "properties": {
    "iso:country":"CH",
    "sg:address":"G\u00fcterstrasse 12 3360 Herzogenbuchsee. Postfach",
    "sg:city":"Herzogenbuchsee",
    "sg:orig_category":"Herstellung von sonstigen elektrischen Ausr\u00fcstungen",
    "sg:postcode":"3360",
    "sg:province":"Bern",
    "wof:name":"Grobplanung Gmbh",
    "wof:placetype":"venue"
},
  "geometry": {"coordinates":[7.7003002167,47.1881103516],"type":"Point"}
}