{
  "type": "Feature",
  "properties": {
    "iso:country":"CH",
    "sg:address":"Dittingerstrasse 30 4053 Basel. Postfach",
    "sg:city":"Basel",
    "sg:orig_category":"Handel mit Automobilen",
    "sg:postcode":"4051",
    "sg:province":"Basel-Stadt",
    "wof:name":"Knobloch Christian Auto Usw; An, U. Verkauf",
    "wof:placetype":"venue"
},
  "geometry": {"coordinates":[7.58852005,47.5404663086],"type":"Point"}
}