{
  "type": "Feature",
  "properties": {
    "iso:country":"CH",
    "sg:address":"Kantonsstrasse 20",
    "sg:city":"Visp",
    "sg:orig_category":"Detailhandel mit Teppichen",
    "sg:phone":"+41 79 449 29 54",
    "sg:postcode":"3930",
    "sg:province":"Valais",
    "wof:name":"Rudolf Sarbach Teppich-center Sarbach",
    "wof:placetype":"venue"
},
  "geometry": {"coordinates":[7.8847441673,46.2920227051],"type":"Point"}
}