{
  "type": "Feature",
  "properties": {
    "addr:full":"Birmensdorferstrasse 188 8003 Z\u00fcrich. Postfach Z\u00fcrich Z\u00fcrich 8036",
    "addr:housenumber":"188",
    "addr:postcode":"8003 zuerich. postfach;8036",
    "addr:street":"Birmensdorferstrasse",
    "iso:country":"CH",
    "sg:address":"Birmensdorferstrasse 188 8003 Z\u00fcrich. Postfach",
    "sg:city":"Z\u00fcrich",
    "sg:orig_category":"Detailhandel mit Brillen U anderen Sehhilfen Fachdetailhandel in Verkaufsr\u00e4umen",
    "sg:phone":"+41 14637987",
    "sg:postcode":"8036",
    "sg:province":"Z\u00fcrich",
    "wof:name":"Vohdin Optik Ag",
    "wof:placetype":"venue"
},
  "geometry": {"coordinates":[8.517457,47.370747],"type":"Point"}
}