{
  "type": "Feature",
  "properties": {
    "iso:country":"CH",
    "sg:address":"Kerzersstrasse 3225 M\u00fcntschemier. Postfach",
    "sg:city":"M\u00fcntschemier",
    "sg:orig_category":"Instandhaltung U Reparatur von Automobilen",
    "sg:postcode":"3225",
    "sg:province":"Bern",
    "wof:name":"Moosgarage Ag, M\u00fcntschemier",
    "wof:placetype":"venue"
},
  "geometry": {"coordinates":[7.1530308723,46.9946975708],"type":"Point"}
}