{
  "type": "Feature",
  "properties": {
    "iso:country":"CH",
    "sg:address":"Bernoullistrasse 8",
    "sg:city":"Basel",
    "sg:orig_category":"Zahnarztpraxen",
    "sg:phone":"+41 61 261 10 00",
    "sg:postcode":"4056",
    "sg:province":"Basel-Stadt",
    "wof:name":"Dr. Med. Dent. Mustafa Bacca Zahnarzt",
    "wof:placetype":"venue"
},
  "geometry": {"coordinates":[7.5823311806,47.559803009],"type":"Point"}
}