{
  "type": "Feature",
  "properties": {
    "iso:country":"CH",
    "sg:address":"Im Kleinholz 3",
    "sg:city":"Olten",
    "sg:orig_category":"Unclassifiable Establishments",
    "sg:postcode":"4600",
    "sg:province":"Solothurn",
    "wof:name":"Kleinkraftwerk Axalp Ag",
    "wof:placetype":"venue"
},
  "geometry": {"coordinates":[8.0380096436,46.7220306396],"type":"Point"}
}