{
  "type": "Feature",
  "properties": {
    "iso:country":"CH",
    "sg:address":"Bondastrasse 112",
    "sg:city":"Chur",
    "sg:orig_category":"Vereine Wissenschaftliche",
    "sg:phone":"+41 81 353 28 53",
    "sg:postcode":"7000",
    "sg:province":"Graubunden",
    "wof:name":"Schweiz.ges.f.gyn./geb.sggg",
    "wof:placetype":"venue"
},
  "geometry": {"coordinates":[9.5468225479,46.8613777161],"type":"Point"}
}