{
  "type": "Feature",
  "properties": {
    "iso:country":"CH",
    "sg:address":"Bahnhofstr. 9",
    "sg:city":"Busswil",
    "sg:classifiers":[
        {
            "category":"Banks & Credit Unions",
            "subcategory":"Bank",
            "type":"Services"
        }
    ],
    "sg:phone":"+41 32 385 35 35",
    "sg:postcode":"3292",
    "sg:province":"Bern",
    "wof:name":"Raiffeisenbank Busswil",
    "wof:placetype":"venue"
},
  "geometry": {"coordinates":[7.321393,47.099594],"type":"Point"}
}