{
  "type": "Feature",
  "properties": {
    "iso:country":"CH",
    "sg:address":"Balierestrasse 27 8500 Frauenfeld. Postfach",
    "sg:city":"Frauenfeld",
    "sg:orig_category":"Detailhandel mit M\u00f6beln U Haushaltsgegenst\u00e4nden",
    "sg:postcode":"8503",
    "sg:province":"Thurgau",
    "wof:name":"Stockwerk3 Gmbh",
    "wof:placetype":"venue"
},
  "geometry": {"coordinates":[8.894452095,47.5550003052],"type":"Point"}
}