{
  "type": "Feature",
  "properties": {
    "iso:country":"CH",
    "sg:address":"Chemin Du Lussex 15",
    "sg:city":"Jouxtens-m\u00e9zery",
    "sg:orig_category":"Sportvereine Turnen Vereine Damen",
    "sg:phone":"+41 21 634 92 28",
    "sg:postcode":"1008",
    "sg:province":"Vaud",
    "wof:name":"St\u00e9 De Gym.fem.jouxtens-m\u00e9zery",
    "wof:placetype":"venue"
},
  "geometry": {"coordinates":[6.5970082283,46.5601348877],"type":"Point"}
}