{
  "type": "Feature",
  "properties": {
    "iso:country":"CH",
    "sg:address":"Chemin Antoine-verch\u00e8re 1",
    "sg:city":"Meyrin",
    "sg:orig_category":"RESTAURANTS: TEA-ROOMS",
    "sg:postcode":"1217",
    "sg:province":"Gen\u00e8ve",
    "wof:name":"Caldogneto Gianni",
    "wof:placetype":"venue"
},
  "geometry": {"coordinates":[6.0724720955,46.2284965515],"type":"Point"}
}