{
  "type": "Feature",
  "properties": {
    "iso:country":"CH",
    "sg:address":"Zone Industrielle Mont De Faux 3",
    "sg:city":"Villars-ste-croix",
    "sg:orig_category":"Schiffsbau ohne Boots U Yachtbau",
    "sg:postcode":"1029",
    "sg:province":"Vaud",
    "wof:name":"Ventilo Catamarans & Profils Carbone S\u00e0rl",
    "wof:placetype":"venue"
},
  "geometry": {"coordinates":[6.5673518181,46.5627365112],"type":"Point"}
}