{
  "type": "Feature",
  "properties": {
    "iso:country":"CH",
    "sg:address":"Z\u00fcrcherstrasse 95",
    "sg:city":"Frauenfeld",
    "sg:orig_category":"Softwareentwicklung U beratung",
    "sg:postcode":"8500",
    "sg:province":"Thurgau",
    "wof:name":"Pc Discount Computervertriebs Gmbh",
    "wof:placetype":"venue"
},
  "geometry": {"coordinates":[8.8906879425,47.5530433655],"type":"Point"}
}