{
  "type": "Feature",
  "properties": {
    "iso:country":"CH",
    "sg:address":"Brauereiweg 1",
    "sg:city":"Balsthal",
    "sg:orig_category":"Verwertung von Milch",
    "sg:phone":"+41 62 391 43 21",
    "sg:postcode":"4710",
    "sg:province":"Solothurn",
    "wof:name":"Milchgenossenschaft Balsthal-klus",
    "wof:placetype":"venue"
},
  "geometry": {"coordinates":[7.6967477798,47.3181266785],"type":"Point"}
}