{
  "type": "Feature",
  "properties": {
    "iso:country":"CH",
    "sg:address":"7149",
    "sg:city":"Vrin",
    "sg:orig_category":"Primarschulen",
    "sg:phone":"+41 81 931 34 89",
    "sg:postcode":"7149",
    "sg:province":"Graubunden",
    "wof:name":"Primarschule",
    "wof:placetype":"venue"
},
  "geometry": {"coordinates":[9.0988416672,46.6555213928],"type":"Point"}
}