{
  "type": "Feature",
  "properties": {
    "iso:country":"CH",
    "sg:address":"Staffelbacherstr. 189",
    "sg:city":"Kirchleerau",
    "sg:classifiers":[
        {
            "category":"Manufacturing",
            "subcategory":"Metals",
            "type":"Manufacturing & Wholesale Goods"
        }
    ],
    "sg:phone":"+41 62 738 55 00",
    "sg:postcode":"5054",
    "sg:province":"Aargau",
    "sg:tags":[
        "-",
        "machine",
        "equipment",
        "engineering",
        "machinery",
        "mechanical"
    ],
    "wof:name":"R\u00d6sler Schweiz Ag",
    "wof:placetype":"venue"
},
  "geometry": {"coordinates":[8.060202,47.280106],"type":"Point"}
}