{
  "type": "Feature",
  "properties": {
    "iso:country":"CH",
    "sg:address":"Wilstrasse 55",
    "sg:city":"D\u00fcbendorf",
    "sg:orig_category":"Organisationen des Gesundheitswesen",
    "sg:phone":"+41 81 302 29 13",
    "sg:postcode":"8600",
    "sg:province":"Z\u00fcrich",
    "wof:name":"Samariterverein",
    "wof:placetype":"venue"
},
  "geometry": {"coordinates":[9.517572403,46.9916305542],"type":"Point"}
}