{
  "type": "Feature",
  "properties": {
    "iso:country":"CH",
    "sg:address":"Bleienbachstrasse 6 4932 Lotzwil. Postfach 189",
    "sg:city":"Lotzwil",
    "sg:orig_category":"Herstellung von Strumpfwaren Spinnstoffaufbereitung U Spinnerei",
    "sg:phone":"+41 62 923 23 61",
    "sg:postcode":"4932",
    "sg:province":"Bern",
    "wof:name":"Jacques Sommer Ag",
    "wof:placetype":"venue"
},
  "geometry": {"coordinates":[7.7878870964,47.1890449524],"type":"Point"}
}