{
  "type": "Feature",
  "properties": {
    "iso:country":"CH",
    "sg:address":"Im Maas 19",
    "sg:city":"Z\u00fcrich",
    "sg:orig_category":"Detailhandel mit Metallwaren, Anstrichmitteln, Glaswaren, Bau U Heimwerkerbedarf",
    "sg:phone":"+41 13715368",
    "sg:postcode":"8049",
    "sg:province":"Z\u00fcrich",
    "wof:name":"Elevenparts Ag Techn. Produkte (fertigfabrikate, Halbfabrikate, Bestandteile); Handel Usw",
    "wof:placetype":"venue"
},
  "geometry": {"coordinates":[8.5051612854,47.4019241333],"type":"Point"}
}