{
  "type": "Feature",
  "properties": {
    "iso:country":"CH",
    "sg:address":"Im Baumgarten 1",
    "sg:city":"Dietwil",
    "sg:orig_category":"Grafikateliers, Design",
    "sg:phone":"+41 41 788 02 05",
    "sg:postcode":"6042",
    "sg:province":"Aargau",
    "wof:name":"Monika Galliker Dekorationen",
    "wof:placetype":"venue"
},
  "geometry": {"coordinates":[8.393237114,47.1501426697],"type":"Point"}
}