{
  "type": "Feature",
  "properties": {
    "iso:country":"CH",
    "sg:address":"Oberfeld 21 6037 Root. Postfach",
    "sg:city":"Root",
    "sg:orig_category":"Autogaragen",
    "sg:phone":"+41 41 377 23 42",
    "sg:postcode":"6037",
    "sg:province":"Luzern",
    "wof:name":"Toni Patt Tell Garage",
    "wof:placetype":"venue"
},
  "geometry": {"coordinates":[8.38529,47.109222],"type":"Point"}
}