{
  "type": "Feature",
  "properties": {
    "iso:country":"CH",
    "sg:address":"Kobelstrasse 13 9442 Berneck. Postfach",
    "sg:city":"Berneck",
    "sg:orig_category":"Zimmerei, Dachdeckerei, Bauspenglerei U Abdichtung",
    "sg:postcode":"9442",
    "sg:province":"St. Gallen",
    "wof:name":"Bhb Hausbau Gmbh",
    "wof:placetype":"venue"
},
  "geometry": {"coordinates":[9.625087738,47.4325637817],"type":"Point"}
}