{
  "type": "Feature",
  "properties": {
    "iso:country":"CH",
    "sg:address":"Akazienweg 41",
    "sg:city":"Trimbach",
    "sg:orig_category":"Herstellung von Ausbauelementen aus Metall",
    "sg:phone":"+41 62 293 48 88",
    "sg:postcode":"4632",
    "sg:province":"Solothurn",
    "wof:name":"Leuenberger Ag",
    "wof:placetype":"venue"
},
  "geometry": {"coordinates":[7.9114618301,47.3687591553],"type":"Point"}
}