{
  "type": "Feature",
  "properties": {
    "iso:country":"CH",
    "sg:address":"Faucigny Rue P.-a.-de- 5",
    "sg:city":"Fribourg",
    "sg:orig_category":"Non-Classified Establishments",
    "sg:postcode":"1700",
    "sg:province":"Fribourg",
    "wof:name":"Letitia Holding Sa",
    "wof:placetype":"venue"
},
  "geometry": {"coordinates":[7.1536831856,46.8037452698],"type":"Point"}
}