{
  "type": "Feature",
  "properties": {
    "iso:country":"CH",
    "sg:address":"Heckenweg 15",
    "sg:city":"Aarberg",
    "sg:orig_category":"Herstellung von Mess U Kontrollinstrumenten U vorrichtungen Herstellung von Werkzeugen",
    "sg:phone":"+41 32 392 22 77",
    "sg:postcode":"3270",
    "sg:province":"Bern",
    "wof:name":"Sambro Ag",
    "wof:placetype":"venue"
},
  "geometry": {"coordinates":[7.2846670151,47.0497817993],"type":"Point"}
}