{
  "type": "Feature",
  "properties": {
    "iso:country":"CH",
    "sg:address":"Hauptstrasse",
    "sg:city":"Fr\u00e4schels",
    "sg:orig_category":"Handel mit Automobilen",
    "sg:phone":"+41 31556969",
    "sg:postcode":"3284",
    "sg:province":"Fribourg",
    "wof:name":"Elite Diffusion A. Zenari",
    "wof:placetype":"venue"
},
  "geometry": {"coordinates":[7.2095150948,46.9998283386],"type":"Point"}
}