{
  "type": "Feature",
  "properties": {
    "iso:country":"CH",
    "sg:address":"Clos Du Moulin",
    "sg:city":"Cuarny",
    "sg:classifiers":[
        {
            "category":"Professional",
            "subcategory":"Computer Services",
            "type":"Services"
        }
    ],
    "sg:phone":"+41 24 425 80 87",
    "sg:postcode":"1404",
    "sg:province":"Vaud",
    "sg:tags":[
        "informatics",
        "consulting"
    ],
    "wof:name":"Neurom S.\u00e0.r.l.",
    "wof:placetype":"venue"
},
  "geometry": {"coordinates":[6.6904888153,46.766368866],"type":"Point"}
}