{
  "type": "Feature",
  "properties": {
    "iso:country":"CH",
    "sg:address":"Flanthey",
    "sg:city":"Lens",
    "sg:orig_category":"Fachdetailhandel in Verkaufsr\u00e4umen",
    "sg:postcode":"1978",
    "sg:province":"Valais",
    "wof:name":"Biel Michel, Cycles Et Motos",
    "wof:placetype":"venue"
},
  "geometry": {"coordinates":[7.4469671249,46.2792243958],"type":"Point"}
}