{
  "type": "Feature",
  "properties": {
    "iso:country":"CH",
    "sg:address":"Rosengartenstrasse 7 8037 Z\u00fcrich. Postfach 192",
    "sg:city":"Z\u00fcrich",
    "sg:orig_category":"Druck ohne Zeitungsdruck Offsetdruck",
    "sg:phone":"+41 12711923",
    "sg:postcode":"8037",
    "sg:province":"Z\u00fcrich",
    "wof:name":"J\u00e4ggi & Roffler Ag",
    "wof:placetype":"venue"
},
  "geometry": {"coordinates":[8.5248718262,47.3939819336],"type":"Point"}
}