{
  "type": "Feature",
  "properties": {
    "iso:country":"CH",
    "sg:address":"Schartenstrasse 22",
    "sg:city":"Rebstein",
    "sg:orig_category":"Saunas Saunas, Solarien, Fitnesszentren U \u00e4hnliches",
    "sg:phone":"+41 71 777 20 82",
    "sg:postcode":"9445",
    "sg:province":"St. Gallen",
    "wof:name":"Fitness 2000 Rubin + Co",
    "wof:placetype":"venue"
},
  "geometry": {"coordinates":[9.5878038406,47.4016151428],"type":"Point"}
}