{
  "type": "Feature",
  "properties": {
    "iso:country":"CH",
    "sg:address":"Parkstrasse 9",
    "sg:city":"F\u00fcllinsdorf",
    "sg:orig_category":"Detailhandel mit Beleuchtungs U Haushaltsgegenst\u00e4nden Innendekorationsateliers",
    "sg:phone":"+41 61 901 60 50",
    "sg:postcode":"4414",
    "sg:province":"Basel-Landschaft",
    "wof:name":"Nelly Mohler Vorh\u00e4nge",
    "wof:placetype":"venue"
},
  "geometry": {"coordinates":[7.72334,47.503197],"type":"Point"}
}