{
  "type": "Feature",
  "properties": {
    "iso:country":"CH",
    "sg:address":"Badstrasse 17 5400 Baden. Postfach",
    "sg:city":"Baden",
    "sg:orig_category":"Eisenbahnverkehr",
    "sg:postcode":"5400",
    "sg:province":"Aargau",
    "wof:name":"Vereinigung Schweizerischer Bahntechnik Unternehmen Vsbtu",
    "wof:placetype":"venue"
},
  "geometry": {"coordinates":[8.3081865311,47.4749450684],"type":"Point"}
}