{
  "type": "Feature",
  "properties": {
    "iso:country":"CH",
    "sg:address":"Rebweg 6 9534 G\u00e4hwil. Postfach",
    "sg:city":"G\u00e4hwil",
    "sg:orig_category":"Allgemeiner Hoch U Tiefbau",
    "sg:postcode":"9534",
    "sg:province":"St. Gallen",
    "wof:name":"Spezial-reinigungen Strang",
    "wof:placetype":"venue"
},
  "geometry": {"coordinates":[8.999369,47.396591],"type":"Point"}
}