{
  "type": "Feature",
  "properties": {
    "iso:country":"CH",
    "sg:address":"D\u00e9lices Chemin Des 9 1006 Lausanne. Postfach",
    "sg:city":"Basel",
    "sg:orig_category":"Unclassifiable Establishments",
    "sg:phone":"+41 61 695 81 11",
    "sg:postcode":"4051",
    "sg:province":"Basel-Stadt",
    "wof:name":"Transline Sa Transporte U. Speditionen Zu Lande, Zu Wasser Und In Der Luft Usw",
    "wof:placetype":"venue"
},
  "geometry": {"coordinates":[6.632335186,46.5195960999],"type":"Point"}
}