{
  "type": "Feature",
  "properties": {
    "iso:country":"CH",
    "sg:address":"Chemin De La Gottrause 13",
    "sg:city":"Crissier",
    "sg:orig_category":"Bauschreinerei",
    "sg:phone":"+41 21 634 10 77",
    "sg:postcode":"1023",
    "sg:province":"Vaud",
    "wof:name":"Pierre-alain Visinand Menuiserie",
    "wof:placetype":"venue"
},
  "geometry": {"coordinates":[6.571102,46.547325],"type":"Point"}
}