{
  "type": "Feature",
  "properties": {
    "addr:full":"Chatzer\u00fcti Hefenhofen Thurgau 8580",
    "addr:postcode":"8580",
    "iso:country":"CH",
    "sg:address":"Chatzer\u00fcti",
    "sg:city":"Hefenhofen",
    "sg:orig_category":"Architekturb\u00fcros",
    "sg:phone":"+41 34 447 48 48",
    "sg:postcode":"8580",
    "sg:province":"Thurgau",
    "wof:name":"Hpag Peter Fl\u00fcckiger Architekturb\u00fcro",
    "wof:placetype":"venue"
},
  "geometry": {"coordinates":[7.585186,47.082859],"type":"Point"}
}