{
  "type": "Feature",
  "properties": {
    "iso:country":"CH",
    "sg:address":"Gotthardstrasse 21 6353 Weggis. Postfach 144",
    "sg:city":"Weggis",
    "sg:orig_category":"Sanit\u00e4r, Heizungs U L\u00fcftungsinstallation Sanit\u00e4rinstallation",
    "sg:phone":"+41 41 390 11 08",
    "sg:postcode":"6353",
    "sg:province":"Luzern",
    "wof:name":"Kaufmann Rolf",
    "wof:placetype":"venue"
},
  "geometry": {"coordinates":[8.4379768372,47.0315361023],"type":"Point"}
}