{
  "type": "Feature",
  "properties": {
    "addr:full":"Bahnhofplatz 13 Dietikon Z\u00fcrich 8953",
    "addr:housenumber":"13",
    "addr:postcode":"8953",
    "addr:street":"Bahnhofplatz",
    "iso:country":"CH",
    "sg:address":"Bahnhofplatz 13",
    "sg:city":"Dietikon",
    "sg:classifiers":[
        {
            "category":"Banks & Credit Unions",
            "subcategory":"Bank",
            "type":"Services"
        }
    ],
    "sg:phone":"+41 17438686",
    "sg:postcode":"8953",
    "sg:province":"Z\u00fcrich",
    "wof:name":"Swiss Bank Corp., Branch Dietlikon",
    "wof:placetype":"venue"
},
  "geometry": {"coordinates":[8.403621,47.405788],"type":"Point"}
}