{
  "type": "Feature",
  "properties": {
    "iso:country":"CH",
    "sg:address":"Leberngasse 7",
    "sg:city":"Olten",
    "sg:orig_category":"Rechtsberatung",
    "sg:postcode":"4600",
    "sg:province":"Solothurn",
    "wof:name":"Patin Ag Pag Patente, Lizenzen; Verwertung",
    "wof:placetype":"venue"
},
  "geometry": {"coordinates":[7.9006929398,47.3490104675],"type":"Point"}
}