{
  "type": "Feature",
  "properties": {
    "iso:country":"CH",
    "sg:address":"Grand-rue 21",
    "sg:city":"Morges",
    "sg:orig_category":"Detailhandel mit Bekleidung Detailhandel mit Herrenbekleidung",
    "sg:phone":"+41 21 801 38 80",
    "sg:postcode":"1110",
    "sg:province":"Vaud",
    "wof:name":"Tille Fabienne",
    "wof:placetype":"venue"
},
  "geometry": {"coordinates":[6.499495,46.510014],"type":"Point"}
}