{
  "type": "Feature",
  "properties": {
    "iso:country":"CH",
    "sg:address":"Sempacherstrasse 2",
    "sg:city":"Basel",
    "sg:orig_category":"Fotografische Ateliers",
    "sg:phone":"+41 61 361 79 55",
    "sg:postcode":"4053",
    "sg:province":"Basel-Stadt",
    "wof:name":"Photograph Andrei-lucian Dinu",
    "wof:placetype":"venue"
},
  "geometry": {"coordinates":[7.5885891914,47.544921875],"type":"Point"}
}