{
  "type": "Feature",
  "properties": {
    "iso:country":"CH",
    "sg:address":"Nordstrasse 118",
    "sg:city":"Schaffhausen",
    "sg:orig_category":"Kosmetikinstitute",
    "sg:phone":"+41 52 624 34 08",
    "sg:postcode":"8200",
    "sg:province":"Schaffhausen",
    "wof:name":"Coiffure Hanspeter Gruber Damen Und Herren",
    "wof:placetype":"venue"
},
  "geometry": {"coordinates":[8.6276855469,47.707118988],"type":"Point"}
}