{
  "type": "Feature",
  "properties": {
    "iso:country":"CH",
    "sg:address":"6597",
    "sg:city":"Agarone",
    "sg:orig_category":"Allgemeiner Hoch U Tiefbau Strassenbau",
    "sg:phone":"+41 91 859 12 74",
    "sg:postcode":"6597",
    "sg:province":"Ticino",
    "wof:name":"Fratelli Tenconi Impresa Edile Sa",
    "wof:placetype":"venue"
},
  "geometry": {"coordinates":[8.90636,46.17844],"type":"Point"}
}