{
  "type": "Feature",
  "properties": {
    "iso:country":"CH",
    "sg:address":"Passwangstrasse 37",
    "sg:city":"Breitenbach",
    "sg:orig_category":"Herstellung von Maschinen f\u00fcr die Textil, Bekleidungsherstellung U die Lederverarbeitung Herstellung",
    "sg:phone":"+41 61 789 16 70",
    "sg:postcode":"4226",
    "sg:province":"Solothurn",
    "wof:name":"Sb Breitenbach Maschinen Ag",
    "wof:placetype":"venue"
},
  "geometry": {"coordinates":[7.5426898003,47.4031944275],"type":"Point"}
}