{
  "type": "Feature",
  "properties": {
    "iso:country":"CH",
    "sg:address":"Achenbergweg 3",
    "sg:city":"Klingnau",
    "sg:orig_category":"Detailhandel mit Fahrr\u00e4dern Handel mit Motorr\u00e4dern, Teilen U Zubeh\u00f6r Instandhaltung U Reparatur von ",
    "sg:phone":"+41 19323397",
    "sg:postcode":"5313",
    "sg:province":"Aargau",
    "wof:name":"Thomas Niessl Tom's Bike Center",
    "wof:placetype":"venue"
},
  "geometry": {"coordinates":[8.7951393127,47.3207168579],"type":"Point"}
}