{
  "type": "Feature",
  "properties": {
    "iso:country":"CH",
    "sg:address":"Kolbenacker 14/35",
    "sg:city":"Seebach",
    "sg:orig_category":"Unclassifiable Establishments",
    "sg:postcode":"8052",
    "sg:province":"Z\u00fcrich",
    "wof:name":"Schule F\u00fcr Nat\u00fcrliches Heilen Gmbh",
    "wof:placetype":"venue"
},
  "geometry": {"coordinates":[9.576338768,46.982383728],"type":"Point"}
}