{
  "type": "Feature",
  "properties": {
    "iso:country":"CH",
    "sg:address":"Dorfstrasse 11",
    "sg:city":"Oberhelfenschwil",
    "sg:orig_category":"Detailhandel mit Fleisch U Fleischwaren",
    "sg:phone":"+41 71 374 11 66",
    "sg:postcode":"9621",
    "sg:province":"St. Gallen",
    "wof:name":"Gebr.jakob & Leo Thaler Metzgerei",
    "wof:placetype":"venue"
},
  "geometry": {"coordinates":[9.1126785278,47.3548545837],"type":"Point"}
}