{
  "type": "Feature",
  "properties": {
    "iso:country":"CH",
    "sg:address":"2944",
    "sg:city":"Bonfol",
    "sg:classifiers":[
        {
            "category":"Education",
            "subcategory":"Vocational School",
            "type":"Public Place"
        }
    ],
    "sg:postcode":"2944",
    "sg:province":"Jura",
    "sg:tags":[
        "koch-",
        "haushaltschulen"
    ],
    "wof:name":"Ecole M\u00e9nag\u00e8re",
    "wof:placetype":"venue"
},
  "geometry": {"coordinates":[7.1496939659,47.4781341553],"type":"Point"}
}