{
  "type": "Feature",
  "properties": {
    "iso:country":"CH",
    "sg:address":"S\u00fcdstrasse 22",
    "sg:city":"Biel/bienne",
    "sg:orig_category":"Kaminfeger Reinigungsgewerbe",
    "sg:phone":"+41 32 341 62 19",
    "sg:postcode":"2504",
    "sg:province":"Bern",
    "wof:name":"Dietrich Peter",
    "wof:placetype":"venue"
},
  "geometry": {"coordinates":[7.2711510658,47.1419944763],"type":"Point"}
}