{
  "type": "Feature",
  "properties": {
    "iso:country":"CH",
    "sg:address":"R\u00f4tisserie Rue De La 4 1204 Gen\u00e8ve. Postfach",
    "sg:city":"Gen\u00e8ve",
    "sg:orig_category":"Non-Classified Establishments",
    "sg:postcode":"1204",
    "sg:province":"Gen\u00e8ve",
    "wof:name":"Soci\u00e9t\u00e9 Holding De Participations H\u00f4teli\u00e8res, Financi\u00e8res Et Immobili\u00e8res Sa",
    "wof:placetype":"venue"
},
  "geometry": {"coordinates":[6.1457848549,46.202922821],"type":"Point"}
}