{
  "type": "Feature",
  "properties": {
    "iso:country":"CH",
    "sg:address":"Bachlettenstrasse 62 4054 Basel. Postfach",
    "sg:city":"Basel",
    "sg:orig_category":"Detailhandel mit B\u00fcromaschinen U einrichtungen",
    "sg:phone":"+41 61 281 70 81",
    "sg:postcode":"4011",
    "sg:province":"Basel-Stadt",
    "wof:name":"Romeo Cassani B\u00fcromaschinen",
    "wof:placetype":"venue"
},
  "geometry": {"coordinates":[7.578269,47.548447],"type":"Point"}
}