{
  "type": "Feature",
  "properties": {
    "iso:country":"CH",
    "sg:address":"Breitr\u00fctti 12",
    "sg:city":"Schattdorf",
    "sg:orig_category":"Herstellung von Bereifungen",
    "sg:phone":"+41 41 870 83 02",
    "sg:postcode":"6467",
    "sg:province":"Uri",
    "wof:name":"Pneuhaus Welti, Inhaber Karl Jauch",
    "wof:placetype":"venue"
},
  "geometry": {"coordinates":[8.6431589127,46.8587760925],"type":"Point"}
}