{
  "type": "Feature",
  "properties": {
    "iso:country":"CH",
    "sg:address":"Wartstrasse 31 8400 Winterthur. Postfach",
    "sg:city":"Winterthur",
    "sg:orig_category":"Non-Classified Establishments",
    "sg:postcode":"8400",
    "sg:province":"Z\u00fcrich",
    "wof:name":"4tm Holding Ag",
    "wof:placetype":"venue"
},
  "geometry": {"coordinates":[8.719250679,47.5017204285],"type":"Point"}
}