{
  "type": "Feature",
  "properties": {
    "iso:country":"CH",
    "sg:address":"Chemin De Bethl\u00e9em 9 1700 Fribourg. Postfach",
    "sg:city":"Fribourg",
    "sg:orig_category":"Farben and Lacke Detailhandel Glaserei",
    "sg:phone":"+41 27 722 21 45",
    "sg:postcode":"1703",
    "wof:name":"Gualino Vitrerie-couleurs",
    "wof:placetype":"venue"
},
  "geometry": {"coordinates":[7.0754008293,46.1029968262],"type":"Point"}
}