{
  "type": "Feature",
  "properties": {
    "iso:country":"CH",
    "sg:address":"Hohrain 33",
    "sg:city":"Obererlinsbach",
    "sg:orig_category":"Herstellung von Metallkonstruktionen Schlossereien",
    "sg:phone":"+41 62 844 29 82",
    "sg:postcode":"5016",
    "wof:name":"Hermann Von D\u00e4niken Schlosserei Konstr'werkstatt",
    "wof:placetype":"venue"
},
  "geometry": {"coordinates":[8.0046072006,47.4053840637],"type":"Point"}
}