{
  "type": "Feature",
  "properties": {
    "iso:country":"CH",
    "sg:address":"Lettenstrasse 2",
    "sg:city":"Rotkreuz",
    "sg:orig_category":"Finanzierungsinstitutionen",
    "sg:phone":"+41 41 790 36 48",
    "sg:postcode":"6343",
    "sg:province":"Zug",
    "wof:name":"Blue Circle Luxembourg Sa, Luxembourg, Zweigniederlassung Rotkreuz",
    "wof:placetype":"venue"
},
  "geometry": {"coordinates":[8.432220459,47.1485290527],"type":"Point"}
}