{
  "type": "Feature",
  "properties": {
    "iso:country":"CH",
    "sg:address":"Fuchsb\u00fchlstrasse 11",
    "sg:city":"Amriswil",
    "sg:orig_category":"Handels-H\u00e4user U Gesellschaften",
    "sg:phone":"+41 28244764",
    "sg:postcode":"8580",
    "sg:province":"Thurgau",
    "wof:name":"Agentur Globe, Dopp Ilse-maria",
    "wof:placetype":"venue"
},
  "geometry": {"coordinates":[9.2732515335,47.5457382202],"type":"Point"}
}