{
  "type": "Feature",
  "properties": {
    "iso:country":"CH",
    "sg:address":"Via General Guisan 20",
    "sg:city":"Balerna",
    "sg:orig_category":"Kosmetikinstitute",
    "sg:phone":"+41 91 683 21 49",
    "sg:postcode":"6828",
    "sg:province":"Ticino",
    "wof:name":"Brunella Probst Istituto Di Bellezza",
    "wof:placetype":"venue"
},
  "geometry": {"coordinates":[9.009806633,45.8470802307],"type":"Point"}
}