{
  "type": "Feature",
  "properties": {
    "iso:country":"CH",
    "sg:address":"S\u00e4ntisstrasse 12 9230 Flawil. Postfach",
    "sg:city":"Flawil",
    "sg:orig_category":"Herstellung von sonstigen keramischen Erzeugnissen",
    "sg:postcode":"9230",
    "sg:province":"St. Gallen",
    "wof:name":"Kapp Frau G.",
    "wof:placetype":"venue"
},
  "geometry": {"coordinates":[7.850689888,47.344997406],"type":"Point"}
}