{
  "type": "Feature",
  "properties": {
    "iso:country":"CH",
    "sg:address":"Hauptgasse 37 4500 Solothurn. Postfach",
    "sg:city":"Solothurn",
    "sg:orig_category":"Unternehmensberatung",
    "sg:phone":"+41 32 621 39 71",
    "sg:postcode":"4500",
    "sg:province":"Solothurn",
    "wof:name":"Zero Concept Tschopp Roby Unternehmensberatung Und Projektabwicklung",
    "wof:placetype":"venue"
},
  "geometry": {"coordinates":[7.5368938446,47.2074012756],"type":"Point"}
}