{
  "type": "Feature",
  "properties": {
    "iso:country":"CH",
    "sg:address":"Unneri Strass 21 3902 Glis. Postfach",
    "sg:city":"Glis",
    "sg:orig_category":"Detailhandel mit Metallwaren, Anstrichmitteln, Glaswaren, Bau U Heimwerkerbedarf",
    "sg:phone":"+41 27 924 84 84",
    "sg:postcode":"3902",
    "sg:province":"Valais",
    "wof:name":"Seiler Alu-tech Ag",
    "wof:placetype":"venue"
},
  "geometry": {"coordinates":[7.9776821136,46.3108596802],"type":"Point"}
}