{
  "type": "Feature",
  "properties": {
    "iso:country":"CH",
    "sg:address":"Asylstrasse 15",
    "sg:city":"Baar",
    "sg:orig_category":"Primarschulen Vorschulen, Kinderg\u00e4rten",
    "sg:phone":"+41 41 761 30 77",
    "sg:postcode":"6340",
    "sg:province":"Zug",
    "wof:name":"Rudolf Steiner-schule",
    "wof:placetype":"venue"
},
  "geometry": {"coordinates":[8.5204153061,47.1941947937],"type":"Point"}
}