{
  "type": "Feature",
  "properties": {
    "addr:full":"Eschenbachstrasse 78 Rothenburg Luzern 6023",
    "addr:housenumber":"78",
    "addr:postcode":"6023",
    "addr:street":"Eschenbachstrasse",
    "iso:country":"CH",
    "sg:address":"Eschenbachstrasse 78",
    "sg:city":"Rothenburg",
    "sg:orig_category":"Allgemeiner Gartenbau Gartenbau",
    "sg:phone":"+41 41 280 83 22",
    "sg:postcode":"6023",
    "sg:province":"Luzern",
    "wof:name":"Ottiger Baumschule",
    "wof:placetype":"venue"
},
  "geometry": {"coordinates":[8.28345,47.100861],"type":"Point"}
}