{
  "type": "Feature",
  "properties": {
    "iso:country":"CH",
    "sg:address":"6850",
    "sg:city":"Mendrisio",
    "sg:orig_category":"Kinderg\u00e4rten, Vor U Grundschulen",
    "sg:phone":"+41 91 646 29 71",
    "sg:postcode":"6850",
    "sg:province":"Ticino",
    "wof:name":"Asilo Infantile Famiglia Bernasconi Giovanni",
    "wof:placetype":"venue"
},
  "geometry": {"coordinates":[8.9789495468,45.876991272],"type":"Point"}
}