{
  "type": "Feature",
  "properties": {
    "iso:country":"CH",
    "sg:address":"Laurenzenvorstadt 11 5000 Aarau. Postfach",
    "sg:city":"Aarau",
    "sg:orig_category":"Unclassifiable Establishments",
    "sg:phone":"+41 62 823 00 10",
    "sg:postcode":"5001",
    "sg:province":"Aargau",
    "wof:name":"Colliers Csl Ag Immobilien-dienstleistungen",
    "wof:placetype":"venue"
},
  "geometry": {"coordinates":[8.0477695465,47.3939208984],"type":"Point"}
}