{
  "type": "Feature",
  "properties": {
    "iso:country":"CH",
    "sg:address":"Birkenweg 13 6340 Baar. Postfach",
    "sg:city":"Baar",
    "sg:orig_category":"Religi\u00f6se Vereinigungen",
    "sg:phone":"+41 22 342 62 32",
    "sg:postcode":"6340",
    "sg:province":"Zug",
    "wof:name":"Oratoire St. Joseph",
    "wof:placetype":"venue"
},
  "geometry": {"coordinates":[6.1429510117,46.1859970093],"type":"Point"}
}