{
  "type": "Feature",
  "properties": {
    "iso:country":"CH",
    "sg:address":"Rte De Buix 45",
    "sg:city":"Montignez",
    "sg:orig_category":"Herstellung von Konstruktionsteilen, Fertigbauteilen U Ausbauelementen aus Holz",
    "sg:phone":"+41 79 233 70 70",
    "sg:postcode":"2924",
    "sg:province":"Jura",
    "wof:name":"B\u00e9let Jean-marc",
    "wof:placetype":"venue"
},
  "geometry": {"coordinates":[7.056060791,47.4869499207],"type":"Point"}
}