{
  "type": "Feature",
  "properties": {
    "iso:country":"CH",
    "sg:address":"Avenue De La Gare 4 2114 Fleurier Case Postale 286",
    "sg:city":"Fleurier",
    "sg:orig_category":"Detailhandel mit Schreib U Papeteriewaren",
    "sg:phone":"+41 32 861 15 58",
    "sg:postcode":"2114",
    "sg:province":"Neuch\u00e2tel",
    "wof:name":"Martin-gilg Mme Josiane",
    "wof:placetype":"venue"
},
  "geometry": {"coordinates":[6.5819311142,46.9025344849],"type":"Point"}
}