{
  "type": "Feature",
  "properties": {
    "iso:country":"CH",
    "sg:address":"Via S. Stefano",
    "sg:city":"Chiasso",
    "sg:orig_category":"Sonstiges Versicherungsgewerbe",
    "sg:postcode":"6830",
    "sg:province":"Ticino",
    "wof:name":"Coassa Sa",
    "wof:placetype":"venue"
},
  "geometry": {"coordinates":[9.0103349686,45.8280448914],"type":"Point"}
}