{
  "type": "Feature",
  "properties": {
    "iso:country":"CH",
    "sg:address":"Platz 8",
    "sg:city":"Schaffhausen",
    "sg:orig_category":"Pensionskassen",
    "sg:postcode":"8200",
    "sg:province":"Schaffhausen",
    "wof:name":"Personalf\u00fcrsorgestiftung Unionsdruckerei Ag/schaffhauser Az",
    "wof:placetype":"venue"
},
  "geometry": {"coordinates":[8.635055542,47.6978988647],"type":"Point"}
}