{
  "type": "Feature",
  "properties": {
    "iso:country":"CH",
    "sg:address":"Avenue Du Casino 28",
    "sg:city":"Montreux",
    "sg:orig_category":"Detailhandel mit Beleuchtungs U Haushaltsgegenst\u00e4nden Detailhandel mit Uhren U Schmuck",
    "sg:phone":"+41 22 312 36 70",
    "sg:postcode":"1820",
    "sg:province":"Vaud",
    "wof:name":"Touzeau Arts De La Table Sa",
    "wof:placetype":"venue"
},
  "geometry": {"coordinates":[6.912736,46.43042],"type":"Point"}
}