{
  "type": "Feature",
  "properties": {
    "iso:country":"CH",
    "sg:address":"H\u00f6heweg 45",
    "sg:city":"Interlaken",
    "sg:orig_category":"Detailhandel mit Bekleidung Detailhandel mit Damenbekleidung",
    "sg:phone":"+41 33 823 23 32",
    "sg:postcode":"3800",
    "sg:province":"Bern",
    "wof:name":"King's Fashion Ag",
    "wof:placetype":"venue"
},
  "geometry": {"coordinates":[7.857417,46.686424],"type":"Point"}
}