{
  "type": "Feature",
  "properties": {
    "iso:country":"CH",
    "sg:address":"Weissensteinstrasse 6",
    "sg:city":"Nieder\u00f6nz",
    "sg:orig_category":"Sportvereine Turnen Vereine Damen",
    "sg:phone":"+41 62 961 49 10",
    "sg:postcode":"3362",
    "sg:province":"Bern",
    "wof:name":"Satus-turnerinnenverein",
    "wof:placetype":"venue"
},
  "geometry": {"coordinates":[7.694852829,47.1886787415],"type":"Point"}
}