{
  "type": "Feature",
  "properties": {
    "iso:country":"CH",
    "sg:address":"M\u00f6venweg 8597 Landschlacht. Postfach",
    "sg:city":"Landschlacht",
    "sg:orig_category":"Kauf U Verkauf von Immobilien auf eigene Rechnung",
    "sg:postcode":"8597",
    "sg:province":"Thurgau",
    "wof:name":"Biag, Bodensee Gmbh Liegenschaften Usw",
    "wof:placetype":"venue"
},
  "geometry": {"coordinates":[9.2487401962,47.6284866333],"type":"Point"}
}