{
  "type": "Feature",
  "properties": {
    "iso:country":"CH",
    "sg:address":"Loye",
    "sg:city":"Gr\u00f4ne",
    "sg:orig_category":"Elektroinstallation",
    "sg:phone":"+41 81 353 53 53",
    "sg:postcode":"3979",
    "sg:province":"Valais",
    "wof:name":"Morelisse Elektro Ag",
    "wof:placetype":"venue"
},
  "geometry": {"coordinates":[9.520652771,46.9897613525],"type":"Point"}
}