{
  "type": "Feature",
  "properties": {
    "iso:country":"CH",
    "sg:address":"Les Grandes-planches 9",
    "sg:city":"Geneveys-coffrane",
    "sg:orig_category":"Politische Parteien SP",
    "sg:phone":"+41 32 857 12 20",
    "sg:postcode":"2206",
    "sg:province":"Neuch\u00e2tel",
    "wof:name":"Ps Les Geneveys-sur-coffrane",
    "wof:placetype":"venue"
},
  "geometry": {"coordinates":[6.8458170891,47.0120315552],"type":"Point"}
}