{
  "type": "Feature",
  "properties": {
    "addr:full":"Neuhofstrasse 23 D\u00fcbendorf Z\u00fcrich 8600",
    "addr:housenumber":"23",
    "addr:postcode":"8600",
    "addr:street":"Neuhofstrasse;Zuerich",
    "iso:country":"CH",
    "sg:address":"Neuhofstrasse 23",
    "sg:city":"D\u00fcbendorf",
    "sg:orig_category":"Bauspenglerei Dachdeckerei",
    "sg:phone":"+41 18200177",
    "sg:postcode":"8600",
    "sg:province":"Z\u00fcrich",
    "wof:name":"Jung & Partner Bauspenglerei Ag",
    "wof:placetype":"venue"
},
  "geometry": {"coordinates":[8.622261,47.399406],"type":"Point"}
}