{
  "type": "Feature",
  "properties": {
    "iso:country":"CH",
    "sg:address":"Villettemattstrasse 13 3007 Bern. Postfach",
    "sg:city":"Hinterkappelen",
    "sg:orig_category":"Unternehmensberatung",
    "sg:postcode":"3032",
    "sg:province":"Bern",
    "wof:name":"Marketing Und Unternehmensberatung Christian Meyer",
    "wof:placetype":"venue"
},
  "geometry": {"coordinates":[7.4303340912,46.944103241],"type":"Point"}
}