{
  "type": "Feature",
  "properties": {
    "iso:country":"CH",
    "sg:address":"Rue De Livron 31",
    "sg:city":"Meyrin",
    "sg:orig_category":"Handels-H\u00e4user U Gesellschaften",
    "sg:postcode":"1217",
    "sg:province":"Gen\u00e8ve",
    "wof:name":"Ist Soft-trading Sa",
    "wof:placetype":"venue"
},
  "geometry": {"coordinates":[7.0326981544,46.7506790161],"type":"Point"}
}