{
  "type": "Feature",
  "properties": {
    "iso:country":"CH",
    "sg:address":"Rue De La Mor\u00e2che 6",
    "sg:city":"Nyon",
    "sg:orig_category":"Detailhandel mit Brillen U anderen Sehhilfen Fachdetailhandel in Verkaufsr\u00e4umen",
    "sg:phone":"+41 32 725 11 38",
    "sg:postcode":"1260",
    "sg:province":"Vaud",
    "wof:name":"Optique Des Arcades Lamboley P. Et M.-a. Sa",
    "wof:placetype":"venue"
},
  "geometry": {"coordinates":[6.936381,46.994297],"type":"Point"}
}