{
  "type": "Feature",
  "properties": {
    "addr:full":"Zuchwilerstrasse 43 4500 Solothurn. Postfach Solothurn Solothurn 4501",
    "addr:housenumber":"43",
    "addr:postcode":"4500 solothurn. postfach;4501",
    "addr:street":"Zuchwilerstrasse",
    "iso:country":"CH",
    "sg:address":"Zuchwilerstrasse 43 4500 Solothurn. Postfach",
    "sg:city":"Solothurn",
    "sg:orig_category":"Arztpraxen",
    "sg:phone":"+41 32 623 38 91",
    "sg:postcode":"4501",
    "sg:province":"Solothurn",
    "wof:name":"Dr.med.claudia Daum\u00fcller Spezial\u00e4rztin Fmh",
    "wof:placetype":"venue"
},
  "geometry": {"coordinates":[7.543839,47.202946],"type":"Point"}
}