{
  "type": "Feature",
  "properties": {
    "iso:country":"CH",
    "sg:address":"Birsigstrasse 45",
    "sg:city":"Basel",
    "sg:orig_category":"Schulpflegen",
    "sg:phone":"+41 56 243 14 24",
    "sg:postcode":"4054",
    "sg:province":"Basel-Stadt",
    "wof:name":"Primarschulflege Der Gemeinde R\u00fcmikon",
    "wof:placetype":"venue"
},
  "geometry": {"coordinates":[8.378780365,47.5648117065],"type":"Point"}
}