{
  "type": "Feature",
  "properties": {
    "iso:country":"CH",
    "sg:address":"Winkelgasse 6",
    "sg:city":"Brig",
    "sg:orig_category":"Detailhandel mit Radio U Fernsehger\u00e4ten Detailhandel mit fotografischen Artikeln",
    "sg:phone":"+41 27 924 14 64",
    "sg:postcode":"3900",
    "sg:province":"Valais",
    "wof:name":"Foto Weis",
    "wof:placetype":"venue"
},
  "geometry": {"coordinates":[7.9877119064,46.3173675537],"type":"Point"}
}