{
  "type": "Feature",
  "properties": {
    "iso:country":"CH",
    "sg:address":"Uitikonerstrasse 29",
    "sg:city":"Urdorf",
    "sg:orig_category":"Instandhaltung U Reparatur von Automobilen",
    "sg:phone":"+41 77642664",
    "sg:postcode":"8902",
    "sg:province":"Z\u00fcrich",
    "wof:name":"Bristol Ag",
    "wof:placetype":"venue"
},
  "geometry": {"coordinates":[8.4277076721,47.3812179565],"type":"Point"}
}