{
  "type": "Feature",
  "properties": {
    "iso:country":"CH",
    "sg:address":"Mitteldorfstrasse 85",
    "sg:city":"Ebnat",
    "sg:orig_category":"Herstellung von Metallkonstruktionen Stahl U Leichtmetallbau",
    "sg:phone":"+41 71 993 18 02",
    "sg:postcode":"9642",
    "sg:province":"St. Gallen",
    "wof:name":"Koller A. + H. Ag",
    "wof:placetype":"venue"
},
  "geometry": {"coordinates":[9.1191139221,47.2677345276],"type":"Point"}
}