{
  "type": "Feature",
  "properties": {
    "iso:country":"CH",
    "sg:address":"Luzernerstrasse 29",
    "sg:city":"Oftringen",
    "sg:orig_category":"Detailhandel mit Bekleidung Detailhandel mit Textilien",
    "sg:phone":"+41 62 797 10 02",
    "sg:postcode":"4665",
    "sg:province":"Aargau",
    "wof:name":"Gertrud Zimmerli Wolle & Textilien",
    "wof:placetype":"venue"
},
  "geometry": {"coordinates":[7.925089,47.309654],"type":"Point"}
}