{
  "type": "Feature",
  "properties": {
    "iso:country":"CH",
    "sg:address":"Rehhagstrasse 5",
    "sg:city":"H\u00f6lstein",
    "sg:orig_category":"Handel mit Automobilteilen U Zubeh\u00f6r",
    "sg:phone":"+41 61 951 20 90",
    "sg:postcode":"4434",
    "sg:province":"Basel-Landschaft",
    "wof:name":"Werner Theiler Autozubeh\u00f6r",
    "wof:placetype":"venue"
},
  "geometry": {"coordinates":[7.7731871605,47.4223213196],"type":"Point"}
}