{
  "type": "Feature",
  "properties": {
    "addr:full":"Merkurstrasse 45 Z\u00fcrich Z\u00fcrich 8032",
    "addr:housenumber":"45",
    "addr:postcode":"8032",
    "addr:street":"Merkurstrasse",
    "iso:country":"CH",
    "sg:address":"Merkurstrasse 45",
    "sg:city":"Z\u00fcrich",
    "sg:classifiers":[
        {
            "category":"Manufacturing",
            "subcategory":"Paper Products",
            "type":"Manufacturing & Wholesale Goods"
        }
    ],
    "sg:phone":"+41 19916688",
    "sg:postcode":"8032",
    "sg:province":"Z\u00fcrich",
    "sg:tags":[
        "cardboard",
        "package"
    ],
    "wof:name":"Ankersmit Verpackung + Werbung",
    "wof:placetype":"venue"
},
  "geometry": {"coordinates":[8.554873,47.367584],"type":"Point"}
}