{
  "type": "Feature",
  "properties": {
    "iso:country":"CH",
    "sg:address":"Baslerstrasse 252",
    "sg:city":"Allschwil",
    "sg:orig_category":"Fahrschulen, Flugschulen",
    "sg:phone":"+41 61 272 30 30",
    "sg:postcode":"4123",
    "sg:province":"Basel-Landschaft",
    "wof:name":"Gion Egli Autofahrschule",
    "wof:placetype":"venue"
},
  "geometry": {"coordinates":[7.5566821098,47.5551757812],"type":"Point"}
}