{
  "type": "Feature",
  "properties": {
    "iso:country":"CH",
    "sg:address":"Friedenstrasse 15",
    "sg:city":"Wallisellen",
    "sg:orig_category":"Softwareentwicklung U beratung",
    "sg:phone":"+41 18832151",
    "sg:postcode":"8304",
    "sg:province":"Z\u00fcrich",
    "wof:name":"Wings Software Developments Vontobel M.",
    "wof:placetype":"venue"
},
  "geometry": {"coordinates":[8.5858030319,47.4150466919],"type":"Point"}
}