{
  "type": "Feature",
  "properties": {
    "iso:country":"CH",
    "sg:address":"1804",
    "sg:city":"Corsier-sur-vevey",
    "sg:orig_category":"Herstellung von \u00d6fen U Brennern",
    "sg:postcode":"1804",
    "sg:province":"Vaud",
    "wof:name":"Battistella Amos Kafu Diffusion",
    "wof:placetype":"venue"
},
  "geometry": {"coordinates":[6.8515601158,46.4769706726],"type":"Point"}
}