{
  "type": "Feature",
  "properties": {
    "iso:country":"CH",
    "sg:address":"Chemin Des Vignes 14",
    "sg:city":"Pr\u00e9verenges",
    "sg:orig_category":"Architektur U Ingenieurb\u00fcros",
    "sg:phone":"+41 24 472 77 81",
    "sg:postcode":"1028",
    "sg:province":"Vaud",
    "wof:name":"Pierre-andr\u00e9 Lathion Bureau D'ing\u00e9nieur",
    "wof:placetype":"venue"
},
  "geometry": {"coordinates":[6.926319,46.279118],"type":"Point"}
}