{
  "type": "Feature",
  "properties": {
    "iso:country":"CH",
    "sg:address":"Bahnhofstrasse 12 3900 Brig. Postfach",
    "sg:city":"Brig",
    "sg:orig_category":"Detailhandel mit Zeitungen U Zeitschriften Kioske",
    "sg:phone":"+41 32 373 14 20",
    "sg:postcode":"3900",
    "sg:province":"Valais",
    "wof:name":"Monika R\u00fcegger Lotto-kiosk",
    "wof:placetype":"venue"
},
  "geometry": {"coordinates":[7.2785029411,47.1245613098],"type":"Point"}
}