{
  "type": "Feature",
  "properties": {
    "addr:full":"Hauptgasse 2 & 12 6130 Willisau. Postfach Willisau Luzern 6130",
    "addr:housenumber":"2 & 12",
    "addr:postcode":"6130 willisau. postfach;6130",
    "addr:street":"Hauptgasse",
    "iso:country":"CH",
    "sg:address":"Hauptgasse 2 & 12 6130 Willisau. Postfach",
    "sg:city":"Willisau",
    "sg:orig_category":"Detailhandel mit Brillen U anderen Sehhilfen Detailhandel mit Uhren U Schmuck",
    "sg:phone":"+41 41 970 17 80",
    "sg:postcode":"6130",
    "sg:province":"Luzern",
    "wof:name":"Peter Uhren Optik Ag",
    "wof:placetype":"venue"
},
  "geometry": {"coordinates":[7.992142,47.121059],"type":"Point"}
}