{
  "type": "Feature",
  "properties": {
    "iso:country":"CH",
    "sg:address":"Industriestrasse 19",
    "sg:city":"Volketswil",
    "sg:orig_category":"Detailhandel mit M\u00f6beln U Haushaltsgegenst\u00e4nden",
    "sg:postcode":"8604",
    "sg:province":"Z\u00fcrich",
    "wof:name":"Teppich Center Costa Ag",
    "wof:placetype":"venue"
},
  "geometry": {"coordinates":[8.6740636826,47.381187439],"type":"Point"}
}