{
  "type": "Feature",
  "properties": {
    "iso:country":"CH",
    "sg:address":"Plattenstrasse 33",
    "sg:city":"Gr\u00fcningen",
    "sg:orig_category":"Sonstiger Grosshandel",
    "sg:phone":"+41 71 311 25 15",
    "sg:postcode":"8627",
    "sg:province":"Z\u00fcrich",
    "wof:name":"Meitz Ag Waren Aller Art, Bes Baustoffe; Handel",
    "wof:placetype":"venue"
},
  "geometry": {"coordinates":[9.2955293655,47.4017486572],"type":"Point"}
}