{
  "type": "Feature",
  "properties": {
    "iso:country":"CH",
    "sg:address":"Grund.",
    "sg:city":"Saanen",
    "sg:orig_category":"Interessenvertretungen",
    "sg:postcode":"3792",
    "sg:province":"Bern",
    "wof:name":"Weggenossenschaft Baumerli",
    "wof:placetype":"venue"
},
  "geometry": {"coordinates":[7.2749638557,46.4418296814],"type":"Point"}
}