{
  "type": "Feature",
  "properties": {
    "iso:country":"CH",
    "sg:address":"Freilagerstrasse 29 8047 Z\u00fcrich. Postfach",
    "sg:city":"Z\u00fcrich",
    "sg:orig_category":"Instandhaltung U Reparatur von Automobilen",
    "sg:postcode":"8047",
    "sg:province":"Z\u00fcrich",
    "wof:name":"Frekorep Frei U., Autogarage & Reparaturservice",
    "wof:placetype":"venue"
},
  "geometry": {"coordinates":[8.4912910461,47.3789100647],"type":"Point"}
}