{
  "type": "Feature",
  "properties": {
    "iso:country":"CH",
    "sg:address":"Freiburgstrasse 435",
    "sg:city":"Bern",
    "sg:orig_category":"Non-Classified Establishments",
    "sg:postcode":"3018",
    "sg:province":"Bern",
    "wof:name":"Groba Bern Ag",
    "wof:placetype":"venue"
},
  "geometry": {"coordinates":[7.3944039345,46.9344406128],"type":"Point"}
}