{
  "type": "Feature",
  "properties": {
    "iso:country":"CH",
    "sg:address":"Kretzenboden",
    "sg:city":"Pany",
    "sg:orig_category":"Detailhandel mit Sportartikeln Zimmerei, Ingenieurholzbau",
    "sg:phone":"+41 81 332 23 68",
    "sg:postcode":"7243",
    "sg:province":"Graubunden",
    "wof:name":"Andres Hartmann",
    "wof:placetype":"venue"
},
  "geometry": {"coordinates":[9.7629184723,46.9277267456],"type":"Point"}
}