{
  "type": "Feature",
  "properties": {
    "iso:country":"CH",
    "sg:address":"Badstubenstrasse 15 8880 Walenstadt. Postfach 28",
    "sg:city":"Walenstadt",
    "sg:orig_category":"Bauschreinerei Zimmerei, Ingenieurholzbau",
    "sg:phone":"+41 81 735 22 45",
    "sg:postcode":"8880",
    "sg:province":"St. Gallen",
    "wof:name":"Max Beglinger Schreinerei & Zimmerei",
    "wof:placetype":"venue"
},
  "geometry": {"coordinates":[9.313039,47.123096],"type":"Point"}
}