{
  "type": "Feature",
  "properties": {
    "iso:country":"CH",
    "sg:address":"Bluemwis 4",
    "sg:city":"Schleinikon",
    "sg:orig_category":"Vorschulen, Kinderg\u00e4rten",
    "sg:phone":"+41 18560896",
    "sg:postcode":"8165",
    "sg:province":"Z\u00fcrich",
    "wof:name":"Kindergarten",
    "wof:placetype":"venue"
},
  "geometry": {"coordinates":[8.4170503616,47.4997406006],"type":"Point"}
}