{
  "type": "Feature",
  "properties": {
    "iso:country":"CH",
    "sg:address":"Drahtzugstrasse 69 4057 Basel. Postfach",
    "sg:city":"Basel",
    "sg:orig_category":"Handel mit Automobilen",
    "sg:phone":"+41 61 681 97 08",
    "sg:postcode":"4051",
    "sg:province":"Basel-Stadt",
    "wof:name":"B\u00fctler P. Autohandel",
    "wof:placetype":"venue"
},
  "geometry": {"coordinates":[7.5982961655,47.5643005371],"type":"Point"}
}