{
  "type": "Feature",
  "properties": {
    "iso:country":"CH",
    "sg:address":"Vela Riva 12",
    "sg:city":"Lugano",
    "sg:orig_category":"Vermietung U Verpachtung von eigenen Immobilien",
    "sg:postcode":"6900",
    "sg:province":"Ticino",
    "wof:name":"Greha Sa",
    "wof:placetype":"venue"
},
  "geometry": {"coordinates":[5.1808700562,45.8973388672],"type":"Point"}
}