{
  "type": "Feature",
  "properties": {
    "iso:country":"CH",
    "sg:address":"Via Cantonale",
    "sg:city":"Agno",
    "sg:classifiers":[
        {
            "category":"Internet Cafe",
            "subcategory":"None",
            "type":"Food & Drink"
        }
    ],
    "sg:postcode":"6982",
    "sg:province":"Ticino",
    "sg:tags":[
        "informatikdienste",
        "provider"
    ],
    "wof:name":"Victor-liviu Dumitrescu Web Solutions",
    "wof:placetype":"venue"
},
  "geometry": {"coordinates":[6.0990548134,46.2041282654],"type":"Point"}
}