{
  "type": "Feature",
  "properties": {
    "iso:country":"CH",
    "sg:address":"1682",
    "sg:city":"Lovatens",
    "sg:orig_category":"Schulpflegen",
    "sg:postcode":"1682",
    "sg:province":"Vaud",
    "wof:name":"Commission Scolaire De L'\u00e9cole Secondaire",
    "wof:placetype":"venue"
},
  "geometry": {"coordinates":[7.1607999802,46.7766113281],"type":"Point"}
}