{
  "type": "Feature",
  "properties": {
    "iso:country":"CH",
    "sg:address":"Kasernenstrasse 95 7000 Chur. Postfach",
    "sg:city":"Chur",
    "sg:orig_category":"Nationale Postdienste",
    "sg:phone":"+41 81 416 54 69",
    "sg:postcode":"7007",
    "sg:province":"Graubunden",
    "wof:name":"Die Schweizerische Post Davos 2 Horlauben",
    "wof:placetype":"venue"
},
  "geometry": {"coordinates":[9.8327703476,46.8014831543],"type":"Point"}
}