{
  "type": "Feature",
  "properties": {
    "iso:country":"CH",
    "sg:address":"Bruchstrasse 34",
    "sg:city":"Luzern",
    "sg:orig_category":"Schlossereien",
    "sg:phone":"+41 41 630 12 31",
    "sg:postcode":"6003",
    "sg:province":"Luzern",
    "wof:name":"Edi Lussi Schlosserei & Storen",
    "wof:placetype":"venue"
},
  "geometry": {"coordinates":[8.303850174,46.9898033142],"type":"Point"}
}