{
  "type": "Feature",
  "properties": {
    "iso:country":"CH",
    "sg:address":"Kirchgasse 10",
    "sg:city":"Herzogenbuchsee",
    "sg:orig_category":"Detailhandel mit Fleisch U Fleischwaren Detailhandel mit Waren verschiedener Art, Hauptrichtung Nahr",
    "sg:phone":"+41 71 923 14 79",
    "sg:postcode":"3360",
    "sg:province":"Bern",
    "wof:name":"Marianne Fritzsche Metzgerei Lebensmittel",
    "wof:placetype":"venue"
},
  "geometry": {"coordinates":[9.0749568939,47.4424171448],"type":"Point"}
}