{
  "type": "Feature",
  "properties": {
    "iso:country":"CH",
    "sg:address":"Avenue De L'avant-poste 4 1005 Lausanne. Postfach",
    "sg:city":"Lausanne",
    "sg:orig_category":"Effektenvermittlung Broker Finanzierungsinstitutionen",
    "sg:phone":"+41 21 311 72 33",
    "sg:postcode":"1002",
    "sg:province":"Vaud",
    "wof:name":"Libra Financi\u00e8re Sa",
    "wof:placetype":"venue"
},
  "geometry": {"coordinates":[6.6415610313,46.5171127319],"type":"Point"}
}