{
  "type": "Feature",
  "properties": {
    "iso:country":"CH",
    "sg:address":"Via L. Pasteur 1",
    "sg:city":"Chiasso",
    "sg:orig_category":"Non-Classified Establishments",
    "sg:postcode":"6830",
    "sg:province":"Ticino",
    "wof:name":"Edge Consulting Sa",
    "wof:placetype":"venue"
},
  "geometry": {"coordinates":[9.0241270065,45.8334274292],"type":"Point"}
}