{
  "type": "Feature",
  "properties": {
    "iso:country":"CH",
    "sg:address":"Gurzelenstrasse 37",
    "sg:city":"Biel/bienne",
    "sg:orig_category":"Detailhandel mit Fleisch U Fleischwaren",
    "sg:phone":"+41 32 341 37 55",
    "sg:postcode":"2500",
    "sg:province":"Bern",
    "wof:name":"Luginb\u00fchl Kurt Traiteur /partyservice",
    "wof:placetype":"venue"
},
  "geometry": {"coordinates":[7.2576289177,47.1445922852],"type":"Point"}
}