{
  "type": "Feature",
  "properties": {
    "iso:country":"CH",
    "sg:address":"Halte",
    "sg:city":"Schwanden-brienz",
    "sg:orig_category":"Architektur U Ingenieurb\u00fcros",
    "sg:phone":"+41 33 951 10 56",
    "sg:postcode":"3855",
    "sg:province":"Bern",
    "wof:name":"Schild & Partner Architekten Ag",
    "wof:placetype":"venue"
},
  "geometry": {"coordinates":[8.061285,46.759933],"type":"Point"}
}