{
  "type": "Feature",
  "properties": {
    "iso:country":"CH",
    "sg:address":"Ahornweg 13",
    "sg:city":"Weggis",
    "sg:orig_category":"G\u00fcterbef\u00f6rderung im Strassenverkehr",
    "sg:postcode":"6353",
    "sg:province":"Luzern",
    "wof:name":"Villa Transporte",
    "wof:placetype":"venue"
},
  "geometry": {"coordinates":[8.4541969299,47.0294265747],"type":"Point"}
}