{
  "type": "Feature",
  "properties": {
    "iso:country":"CH",
    "sg:address":"Hinterbergstrasse 26 6330 Cham. Postfach",
    "sg:city":"Cham",
    "sg:orig_category":"Fachdetailhandel mit pharmazeutischen Produkten",
    "sg:postcode":"6330",
    "sg:province":"Zug",
    "wof:name":"Mina Ag",
    "wof:placetype":"venue"
},
  "geometry": {"coordinates":[8.4762506485,47.1866188049],"type":"Point"}
}