{
  "type": "Feature",
  "properties": {
    "iso:country":"CH",
    "sg:address":"Route De Boudry",
    "sg:city":"Cortaillod",
    "sg:orig_category":"Pensionskassen",
    "sg:postcode":"2016",
    "sg:province":"Neuch\u00e2tel",
    "wof:name":"Fonds De Pr\u00e9voyance En Faveur Du Personnel De Stila Sa",
    "wof:placetype":"venue"
},
  "geometry": {"coordinates":[6.826736927,47.1077880859],"type":"Point"}
}