{
  "type": "Feature",
  "properties": {
    "addr:full":"Casa Torchio Vicolo Al Burio Gordola Ticino 6596",
    "addr:postcode":"6596",
    "addr:street":"Vicolo Al Burio",
    "iso:country":"CH",
    "sg:address":"Casa Torchio Vicolo Al Burio",
    "sg:city":"Gordola",
    "sg:orig_category":"Architekturb\u00fcros Vermittlung von Immobilien",
    "sg:phone":"+41 91 745 28 91",
    "sg:postcode":"6596",
    "sg:province":"Ticino",
    "wof:name":"Hugo Fahrner Hf Consulting + Management",
    "wof:placetype":"venue"
},
  "geometry": {"coordinates":[8.86042,46.180935],"type":"Point"}
}