{
  "type": "Feature",
  "properties": {
    "iso:country":"CH",
    "sg:address":"Romanshornerstrasse 81",
    "sg:city":"Wittenbach",
    "sg:orig_category":"Erschliessung von Grundst\u00fccken",
    "sg:postcode":"9303",
    "wof:name":"Baugarantie Pr\u00e4ttigau",
    "wof:placetype":"venue"
},
  "geometry": {"coordinates":[9.8787593842,46.8823013306],"type":"Point"}
}