{
  "type": "Feature",
  "properties": {
    "iso:country":"CH",
    "sg:address":"Schlossstrasse 1",
    "sg:city":"Luzern",
    "sg:orig_category":"Organisationen des Gesundheitswesen",
    "sg:phone":"+41 41 310 17 01",
    "sg:postcode":"6005",
    "sg:province":"Luzern",
    "wof:name":"Hilfsverein F.psychischkranke Des Kantons Luzern",
    "wof:placetype":"venue"
},
  "geometry": {"coordinates":[8.3025655746,47.04246521],"type":"Point"}
}