{
  "type": "Feature",
  "properties": {
    "iso:country":"CH",
    "sg:address":"Via Centrale 2",
    "sg:city":"Bellinzona",
    "sg:orig_category":"Primarschulen",
    "sg:postcode":"6500",
    "sg:province":"Ticino",
    "wof:name":"Scuola Elementare Daro",
    "wof:placetype":"venue"
},
  "geometry": {"coordinates":[9.0300550461,46.1942329407],"type":"Point"}
}