{
  "type": "Feature",
  "properties": {
    "iso:country":"CH",
    "sg:address":"Oberdorfstr. 28",
    "sg:city":"Nuglar",
    "sg:orig_category":"RESTAURANTS: TEA-ROOMS",
    "sg:phone":"+41 61 911 00 15",
    "sg:postcode":"4412",
    "sg:province":"Solothurn",
    "wof:name":"Leitner Christine & Co",
    "wof:placetype":"venue"
},
  "geometry": {"coordinates":[7.6914830208,47.4722442627],"type":"Point"}
}