{
  "type": "Feature",
  "properties": {
    "iso:country":"CH",
    "sg:address":"Stadtturmstrasse 19",
    "sg:city":"Baden",
    "sg:orig_category":"Unclassifiable Establishments",
    "sg:phone":"+41 56 222 45 85",
    "sg:postcode":"5400",
    "sg:province":"Aargau",
    "wof:name":"H\u00e4chler Hans Holding Ag",
    "wof:placetype":"venue"
},
  "geometry": {"coordinates":[8.3055353165,47.4757881165],"type":"Point"}
}