{
  "type": "Feature",
  "properties": {
    "addr:full":"Heldstrasse 12a Widnau St. Gallen 9443",
    "addr:housenumber":"12a",
    "addr:postcode":"9443",
    "addr:street":"Heldstrasse",
    "iso:country":"CH",
    "sg:address":"Heldstrasse 12a",
    "sg:city":"Widnau",
    "sg:orig_category":"Mechanik Stahl U Leichtmetallbau",
    "sg:phone":"+41 71 722 59 64",
    "sg:postcode":"9443",
    "sg:province":"St. Gallen",
    "wof:name":"Hutter Ag, Kunstschlosserei + Metallbau",
    "wof:placetype":"venue"
},
  "geometry": {"coordinates":[9.636984,47.399536],"type":"Point"}
}