{
  "type": "Feature",
  "properties": {
    "iso:country":"CH",
    "sg:address":"Hauptstrasse 38",
    "sg:city":"Rorschach",
    "sg:orig_category":"Non-Classified Establishments",
    "sg:postcode":"9400",
    "sg:province":"St. Gallen",
    "wof:name":"K-w-sport Karin W\u00e4chtler",
    "wof:placetype":"venue"
},
  "geometry": {"coordinates":[9.4944410324,47.4781646729],"type":"Point"}
}