{
  "type": "Feature",
  "properties": {
    "iso:country":"CH",
    "sg:address":"Marterey Rue 19 1005 Lausanne. Postfach",
    "sg:city":"Lausanne",
    "sg:orig_category":"Reparatur von Schuhen U Lederwaren",
    "sg:phone":"+41 21 323 90 93",
    "sg:postcode":"1003",
    "sg:province":"Vaud",
    "wof:name":"Malizia Leonardo. Cordonnerie.",
    "wof:placetype":"venue"
},
  "geometry": {"coordinates":[6.6392760277,46.5212478638],"type":"Point"}
}