{
  "type": "Feature",
  "properties": {
    "iso:country":"CH",
    "sg:address":"Schulhausstrasse 12",
    "sg:city":"Langenthal",
    "sg:orig_category":"Advokaturb\u00fcros",
    "sg:phone":"+41 71 228 07 77",
    "sg:postcode":"4900",
    "sg:province":"Bern",
    "wof:name":"Kaufmann David & Partner Advokaturb\u00fcro",
    "wof:placetype":"venue"
},
  "geometry": {"coordinates":[9.376334,47.425095],"type":"Point"}
}