{
  "type": "Feature",
  "properties": {
    "iso:country":"CH",
    "sg:address":"Wiesenstrasse 1",
    "sg:city":"Winterthur",
    "sg:orig_category":"Herstellung von Konstruktionsteilen, Fertigbauteilen U Ausbauelementen aus Holz",
    "sg:postcode":"8400",
    "sg:province":"Z\u00fcrich",
    "wof:name":"Ita Schreinerei Und Innenausbau Gmbh",
    "wof:placetype":"venue"
},
  "geometry": {"coordinates":[8.7176837921,47.5077400208],"type":"Point"}
}