{
  "type": "Feature",
  "properties": {
    "iso:country":"CH",
    "sg:address":"Hauptstrasse 41 8750 Glarus. Postfach",
    "sg:city":"Glarus",
    "sg:orig_category":"Architektur U Ingenieurb\u00fcros Architekturb\u00fcros",
    "sg:phone":"+41 79 216 70 47",
    "sg:postcode":"8750",
    "sg:province":"Glarus",
    "wof:name":"Conte Claudio, Architekturb\u00fcro",
    "wof:placetype":"venue"
},
  "geometry": {"coordinates":[9.067325,47.040531],"type":"Point"}
}