{
  "type": "Feature",
  "properties": {
    "iso:country":"CH",
    "sg:address":"1409",
    "sg:city":"Chan\u00e9az",
    "sg:orig_category":"Non-Classified Establishments",
    "sg:phone":"+41 62 866 11 77",
    "sg:postcode":"1409",
    "sg:province":"Vaud",
    "wof:name":"Hek Stein Ag",
    "wof:placetype":"venue"
},
  "geometry": {"coordinates":[7.9498701096,47.5454216003],"type":"Point"}
}