{
  "type": "Feature",
  "properties": {
    "iso:country":"CH",
    "sg:address":"Langgasse 30",
    "sg:city":"Gais",
    "sg:orig_category":"Reiseb\u00fcros U Reiseveranstalter",
    "sg:phone":"+41 71 790 00 79",
    "sg:postcode":"9056",
    "sg:province":"Appenzell Ausserrhoden",
    "wof:name":"Portimar Gmbh Reiseb\u00fcro",
    "wof:placetype":"venue"
},
  "geometry": {"coordinates":[9.4496688843,47.3609733582],"type":"Point"}
}