{
  "type": "Feature",
  "properties": {
    "iso:country":"CH",
    "sg:address":"6562",
    "sg:city":"Soazza",
    "sg:orig_category":"Architektur U Ingenieurb\u00fcros",
    "sg:phone":"+41 81 252 85 25",
    "sg:postcode":"6562",
    "sg:province":"Graubunden",
    "wof:name":"Renova, Manfred Toschini Arch. Htl.",
    "wof:placetype":"venue"
},
  "geometry": {"coordinates":[9.22181,46.365547],"type":"Point"}
}