{
  "type": "Feature",
  "properties": {
    "iso:country":"CH",
    "sg:address":"Predigerplatz 22",
    "sg:city":"Z\u00fcrich",
    "sg:orig_category":"Detailhandel mit M\u00f6beln U Haushaltsgegenst\u00e4nden",
    "sg:phone":"+41 12606035",
    "sg:postcode":"8001",
    "sg:province":"Z\u00fcrich",
    "wof:name":"Casa Smeralda Ag",
    "wof:placetype":"venue"
},
  "geometry": {"coordinates":[8.5455913544,47.3735389709],"type":"Point"}
}