{
  "type": "Feature",
  "properties": {
    "iso:country":"CH",
    "sg:address":"4934",
    "sg:city":"Madiswil",
    "sg:orig_category":"Vereine Abstinenten",
    "sg:postcode":"4934",
    "sg:province":"Bern",
    "wof:name":"Blaues Kreuz",
    "wof:placetype":"venue"
},
  "geometry": {"coordinates":[7.798514843,47.1655158997],"type":"Point"}
}