{
  "type": "Feature",
  "properties": {
    "iso:country":"CH",
    "sg:address":"Salina 65",
    "sg:city":"Ramosch",
    "sg:orig_category":"G\u00fcterbef\u00f6rderung im Strassenverkehr",
    "sg:phone":"+41 81 866 31 93",
    "sg:postcode":"7556",
    "sg:province":"Graubunden",
    "wof:name":"Not Denoth Transporte",
    "wof:placetype":"venue"
},
  "geometry": {"coordinates":[10.3812198639,46.8351821899],"type":"Point"}
}