{
  "type": "Feature",
  "properties": {
    "iso:country":"CH",
    "sg:address":"Colombaires Rue Des 7",
    "sg:city":"Grandson",
    "sg:orig_category":"Erbringung von Dienstleistungen f\u00fcr Unternehmen",
    "sg:postcode":"1422",
    "sg:province":"Vaud",
    "wof:name":"Cavin Florence",
    "wof:placetype":"venue"
},
  "geometry": {"coordinates":[6.6473031044,46.8110160828],"type":"Point"}
}