{
  "type": "Feature",
  "properties": {
    "iso:country":"CH",
    "sg:address":"Burggrabenstrasse 31",
    "sg:city":"Steckborn",
    "sg:orig_category":"Erschliessung von Grundst\u00fccken",
    "sg:postcode":"8266",
    "sg:province":"Thurgau",
    "wof:name":"Wohnbau-genossenschaft Steckborn.",
    "wof:placetype":"venue"
},
  "geometry": {"coordinates":[8.9899320602,47.6619415283],"type":"Point"}
}