{
  "type": "Feature",
  "properties": {
    "iso:country":"CH",
    "sg:address":"Casa Edera",
    "sg:city":"Castelrotto",
    "sg:orig_category":"Herstellung von sonstigen Fahrzeugen",
    "sg:postcode":"6980",
    "sg:province":"Ticino",
    "wof:name":"Evvli Techno Project Sagl",
    "wof:placetype":"venue"
},
  "geometry": {"coordinates":[8.8413286209,45.988571167],"type":"Point"}
}