{
  "type": "Feature",
  "properties": {
    "iso:country":"CH",
    "sg:address":"R\u00e9sidences De La C\u00f4te 30",
    "sg:city":"Morges",
    "sg:orig_category":"Grosshandel mit sonstigen Gebrauchs U Verbrauchsg\u00fctern",
    "sg:phone":"+41 19233905",
    "sg:postcode":"1110",
    "sg:province":"Vaud",
    "wof:name":"Well-communications Sa",
    "wof:placetype":"venue"
},
  "geometry": {"coordinates":[6.4970970154,46.518321991],"type":"Point"}
}