{
  "type": "Feature",
  "properties": {
    "iso:country":"CH",
    "sg:address":"Cassinelle Zona 6986 Miglieglia. Postfach",
    "sg:city":"Miglieglia",
    "sg:orig_category":"Fachdetailhandel in Verkaufsr\u00e4umen",
    "sg:postcode":"6986",
    "sg:province":"Ticino",
    "wof:name":"Haeuselmann Marcel",
    "wof:placetype":"venue"
},
  "geometry": {"coordinates":[8.8630552292,46.0335426331],"type":"Point"}
}