{
  "type": "Feature",
  "properties": {
    "iso:country":"CH",
    "sg:address":"8767",
    "sg:city":"Elm",
    "sg:classifiers":[
        {
            "category":"Education",
            "subcategory":"Library",
            "type":"Public Place"
        }
    ],
    "sg:postcode":"8767",
    "sg:province":"Glarus",
    "sg:tags":[
        "u",
        "bibliotheken",
        "archive"
    ],
    "wof:name":"Schul-& Gemeindebibliothek",
    "wof:placetype":"venue"
},
  "geometry": {"coordinates":[9.172847,46.921394],"type":"Point"}
}