{
  "type": "Feature",
  "properties": {
    "iso:country":"CH",
    "sg:address":"Wasserwerkgasse 3.1",
    "sg:city":"Bern",
    "sg:orig_category":"Reiseb\u00fcros U Reiseveranstalter",
    "sg:postcode":"3011",
    "sg:province":"Bern",
    "wof:name":"See You Highlights On Tour, Peter K\u00e4stli",
    "wof:placetype":"venue"
},
  "geometry": {"coordinates":[7.4581069946,46.9471969604],"type":"Point"}
}