{
  "type": "Feature",
  "properties": {
    "iso:country":"CH",
    "sg:address":"6707",
    "sg:city":"Iragna",
    "sg:orig_category":"Primarschulen",
    "sg:phone":"+41 91 865 15 12",
    "sg:postcode":"6707",
    "sg:province":"Ticino",
    "wof:name":"Scuola Elementare",
    "wof:placetype":"venue"
},
  "geometry": {"coordinates":[8.9680175781,46.330280304],"type":"Point"}
}