{
  "type": "Feature",
  "properties": {
    "iso:country":"CH",
    "sg:address":"Chemin Des Pr\u00e9s 2",
    "sg:city":"Corg\u00e9mont",
    "sg:classifiers":[
        {
            "category":"Insurance",
            "subcategory":"Insurance Agent",
            "type":"Services"
        }
    ],
    "sg:phone":"+41 32 482 64 11",
    "sg:postcode":"2606",
    "sg:province":"Bern",
    "sg:tags":[
        "versicherungsagenturen",
        "-broker"
    ],
    "wof:name":"Erwin Dornbierer Assurances",
    "wof:placetype":"venue"
},
  "geometry": {"coordinates":[7.1449160576,47.1900177002],"type":"Point"}
}