{
  "type": "Feature",
  "properties": {
    "iso:country":"CH",
    "sg:address":"Kirchgasse 9",
    "sg:city":"Seuzach",
    "sg:orig_category":"Institutionen f\u00fcr psychosoziale F\u00e4lle Organisationen der Wohlfahrtspflege",
    "sg:phone":"+41 52 335 14 21",
    "sg:postcode":"8472",
    "sg:province":"Z\u00fcrich",
    "wof:name":"Beatus-heim F\u00fcr Seelenpflege- Bed\u00fcrftige Erwachsene",
    "wof:placetype":"venue"
},
  "geometry": {"coordinates":[8.7283697128,47.534072876],"type":"Point"}
}