{
  "type": "Feature",
  "properties": {
    "iso:country":"CH",
    "sg:address":"Industriestrasse 42",
    "sg:city":"Oberentfelden",
    "sg:classifiers":[
        {
            "category":"Shopping",
            "subcategory":"Crafts & Fabrics",
            "type":"Retail Goods"
        }
    ],
    "sg:phone":"+41 62 737 87 87",
    "sg:postcode":"5036",
    "sg:province":"Aargau",
    "sg:tags":[
        "brush"
    ],
    "wof:name":"Wasag Ag",
    "wof:placetype":"venue"
},
  "geometry": {"coordinates":[8.056525,47.354191],"type":"Point"}
}