{
  "type": "Feature",
  "properties": {
    "iso:country":"CH",
    "sg:address":"Auberg 15 4051 Basel. Postfach",
    "sg:city":"Basel",
    "sg:orig_category":"Unclassifiable Establishments",
    "sg:phone":"+41 61 272 92 95",
    "sg:postcode":"4051",
    "sg:province":"Basel-Stadt",
    "wof:name":"R. Maggiorini & Co. Ag B\u00fcromaschinen, B\u00fcrom\u00f6bel; Kauf, Verkauf",
    "wof:placetype":"venue"
},
  "geometry": {"coordinates":[7.5844287872,47.5522346497],"type":"Point"}
}