{
  "type": "Feature",
  "properties": {
    "iso:country":"CH",
    "sg:address":"San Gottardo Corso 105",
    "sg:city":"Chiasso",
    "sg:orig_category":"Herstellung von sonstigen Nahrungsmitteln",
    "sg:phone":"+41 91 682 14 83",
    "sg:postcode":"6830",
    "sg:province":"Ticino",
    "wof:name":"Green Spirit Sagl",
    "wof:placetype":"venue"
},
  "geometry": {"coordinates":[9.0242376328,45.8367805481],"type":"Point"}
}