{
  "type": "Feature",
  "properties": {
    "iso:country":"CH",
    "sg:address":"Sur Le Cr\u00eat 11",
    "sg:city":"Lamboing",
    "sg:orig_category":"Herstellung von Tanks U Sammelbeh\u00e4ltern aus Metall Reinigungsgewerbe",
    "sg:phone":"+41 32 315 17 53",
    "sg:postcode":"2516",
    "sg:province":"Bern",
    "wof:name":"Richard Gilbert",
    "wof:placetype":"venue"
},
  "geometry": {"coordinates":[7.1357989311,47.1179046631],"type":"Point"}
}