{
  "type": "Feature",
  "properties": {
    "iso:country":"CH",
    "sg:address":"Ennetgiessen 5 8752 N\u00e4fels. Postfach",
    "sg:city":"N\u00e4fels",
    "sg:orig_category":"Dienstleistungen von Beteiligungsgesellschaften",
    "sg:postcode":"8752",
    "sg:province":"Glarus",
    "wof:name":"V+m Services, Landolt-fischli Peter",
    "wof:placetype":"venue"
},
  "geometry": {"coordinates":[9.0641641617,47.0979232788],"type":"Point"}
}