{
  "type": "Feature",
  "properties": {
    "iso:country":"CH",
    "sg:address":"Seerosenstrasse 3 8008 Z\u00fcrich. Postfach",
    "sg:city":"Z\u00fcrich",
    "sg:orig_category":"Non-Classified Establishments",
    "sg:postcode":"8001",
    "sg:province":"Z\u00fcrich",
    "wof:name":"B.i.t. Burkhard Informatik Technologien Software; Entw. Informatik; Beratung",
    "wof:placetype":"venue"
},
  "geometry": {"coordinates":[8.5473213196,47.3632278442],"type":"Point"}
}