{
  "type": "Feature",
  "properties": {
    "iso:country":"CH",
    "sg:address":"Libernstrasse 16",
    "sg:city":"Otelfingen",
    "sg:orig_category":"R\u00fcckgewinnung U Vorbereitung f\u00fcr die Wiederverwertung Recycling",
    "sg:phone":"+41 26 673 25 00",
    "sg:postcode":"8112",
    "sg:province":"Z\u00fcrich",
    "wof:name":"Kompostieranlage Seeland Ag",
    "wof:placetype":"venue"
},
  "geometry": {"coordinates":[7.1449990273,46.9494552612],"type":"Point"}
}