{
  "type": "Feature",
  "properties": {
    "iso:country":"CH",
    "sg:address":"La Renardi\u00e8re E",
    "sg:city":"Ch\u00e2tel-st-denis",
    "sg:orig_category":"Herstellung von keramischen Haushaltswaren U Ziergegenst\u00e4nden",
    "sg:phone":"+41 21 948 00 75",
    "sg:postcode":"1618",
    "sg:province":"Fribourg",
    "wof:name":"Silvabela Da Silva Henrique Adriano",
    "wof:placetype":"venue"
},
  "geometry": {"coordinates":[6.9015398026,46.5275344849],"type":"Point"}
}