{
  "type": "Feature",
  "properties": {
    "iso:country":"CH",
    "sg:address":"Hinterdorf 104e",
    "sg:city":"Schiers",
    "sg:orig_category":"Detailhandel mit Waren verschiedener Art, Hauptrichtung Nahrungsmittel",
    "sg:phone":"+41 81 328 11 17",
    "sg:postcode":"7220",
    "sg:province":"Graubunden",
    "wof:name":"Coop Ostschweiz",
    "wof:placetype":"venue"
},
  "geometry": {"coordinates":[9.6913909912,46.9687194824],"type":"Point"}
}