{
  "type": "Feature",
  "properties": {
    "iso:country":"CH",
    "sg:address":"Sur Les Pins 10",
    "sg:city":"Courgenay",
    "sg:orig_category":"Grosshandel mit sonstigen Maschinen U Ausr\u00fcstungen f\u00fcr Industrie, Handel U Schiffahrt",
    "sg:phone":"+41 32 471 22 77",
    "sg:postcode":"2950",
    "sg:province":"Jura",
    "wof:name":"M.i.f.o. S\u00e0rl",
    "wof:placetype":"venue"
},
  "geometry": {"coordinates":[7.1122908592,47.4078903198],"type":"Point"}
}