{
  "type": "Feature",
  "properties": {
    "iso:country":"CH",
    "sg:address":"Casa Sogno Mio",
    "sg:city":"Carona",
    "sg:orig_category":"Unclassifiable Establishments",
    "sg:phone":"+41 61 331 35 89",
    "sg:postcode":"6914",
    "sg:province":"Ticino",
    "wof:name":"Scibile Software Di Bumbacher Karin",
    "wof:placetype":"venue"
},
  "geometry": {"coordinates":[8.9357252121,45.9573364258],"type":"Point"}
}