{
  "type": "Feature",
  "properties": {
    "iso:country":"CH",
    "sg:address":"Bubenbergplatz 4 3011 Bern. Postfach",
    "sg:city":"Bern",
    "sg:classifiers":[
        {
            "category":"Education",
            "subcategory":"Library",
            "type":"Public Place"
        }
    ],
    "sg:phone":"+41 27 473 13 61",
    "sg:postcode":"3001",
    "sg:province":"Bern",
    "sg:tags":[
        "u",
        "bibliotheken",
        "archive"
    ],
    "wof:name":"Burgerspital Leuk",
    "wof:placetype":"venue"
},
  "geometry": {"coordinates":[7.63466,46.31633],"type":"Point"}
}