{
  "type": "Feature",
  "properties": {
    "iso:country":"CH",
    "sg:address":"Langhagstrasse 15",
    "sg:city":"Liestal",
    "sg:orig_category":"Pensionskassen",
    "sg:postcode":"4410",
    "sg:province":"Basel-Landschaft",
    "wof:name":"Personalvorsorgestiftung Cheddite",
    "wof:placetype":"venue"
},
  "geometry": {"coordinates":[7.7372188568,47.4786643982],"type":"Point"}
}