{
  "type": "Feature",
  "properties": {
    "iso:country":"CH",
    "sg:address":"St.gallerstrasse 87",
    "sg:city":"Jona",
    "sg:orig_category":"Geb\u00e4ude, Wohnungsreinigung",
    "sg:phone":"+41 55 212 15 10",
    "sg:postcode":"8645",
    "sg:province":"St. Gallen",
    "wof:name":"Fredi Kistler Geb\u00e4udereinigung",
    "wof:placetype":"venue"
},
  "geometry": {"coordinates":[8.844584465,47.2299957275],"type":"Point"}
}