{
  "type": "Feature",
  "properties": {
    "iso:country":"CH",
    "sg:address":"Bernstrasse 358",
    "sg:city":"Dietikon",
    "sg:orig_category":"Instandhaltung U Reparatur von Automobilen",
    "sg:phone":"+41 17410405",
    "sg:postcode":"8953",
    "sg:province":"Z\u00fcrich",
    "wof:name":"S&r Automobile Dietikon Ag",
    "wof:placetype":"venue"
},
  "geometry": {"coordinates":[8.4018640518,47.3929100037],"type":"Point"}
}