{
  "type": "Feature",
  "properties": {
    "iso:country":"CH",
    "sg:address":"Coll\u00e8ge Chemin Du 3 1092 Belmont-lausanne. Postfach",
    "sg:city":"Belmont-lausanne",
    "sg:orig_category":"Architektur U Ingenieurb\u00fcros",
    "sg:postcode":"1092",
    "sg:province":"Vaud",
    "wof:name":"Lecouturier Architectes S\u00e0rl Fournir Toute Prestation Dans Le Domaine De La Construction, De L'architecture Etc",
    "wof:placetype":"venue"
},
  "geometry": {"coordinates":[6.678242,46.519859],"type":"Point"}
}