{
  "type": "Feature",
  "properties": {
    "iso:country":"CH",
    "sg:address":"Talwiesenstrasse 1",
    "sg:city":"N\u00fcrensdorf",
    "sg:orig_category":"Softwareentwicklung U beratung",
    "sg:phone":"+41 79 213 20 30",
    "sg:postcode":"8309",
    "sg:province":"Z\u00fcrich",
    "wof:name":"Burelec, Burtscher Elektronik",
    "wof:placetype":"venue"
},
  "geometry": {"coordinates":[8.6537857056,47.4444770813],"type":"Point"}
}