{
  "type": "Feature",
  "properties": {
    "iso:country":"CH",
    "sg:address":"Rue Dizerens 7 1200 Genf. Postfach",
    "sg:city":"Gen\u00e8ve",
    "sg:orig_category":"Finanzierungsinstitutionen",
    "sg:postcode":"1201",
    "sg:province":"Gen\u00e8ve",
    "wof:name":"Fund Advisory And Management Company (famco) Sa",
    "wof:placetype":"venue"
},
  "geometry": {"coordinates":[6.1433701515,46.1927070618],"type":"Point"}
}