{
  "type": "Feature",
  "properties": {
    "iso:country":"CH",
    "sg:address":"Via San Gottardo",
    "sg:city":"Arbedo",
    "sg:orig_category":"Einbau von Schreinerwaren Sonstiger Grosshandel",
    "sg:phone":"+41 91 829 35 15",
    "sg:postcode":"6517",
    "sg:province":"Ticino",
    "wof:name":"Elnorm Sa",
    "wof:placetype":"venue"
},
  "geometry": {"coordinates":[9.0392827988,46.2110748291],"type":"Point"}
}