{
  "type": "Feature",
  "properties": {
    "iso:country":"CH",
    "sg:address":"Okenstrasse 6",
    "sg:city":"Z\u00fcrich",
    "sg:orig_category":"Architektur U Ingenieurb\u00fcros Architekturb\u00fcros",
    "sg:phone":"+41 13664066",
    "sg:postcode":"8037",
    "sg:province":"Z\u00fcrich",
    "wof:name":"Ackermann Architekten Ag",
    "wof:placetype":"venue"
},
  "geometry": {"coordinates":[8.53481,47.387699],"type":"Point"}
}