{
  "type": "Feature",
  "properties": {
    "iso:country":"CH",
    "sg:address":"M\u00fchlegasse 13",
    "sg:city":"Z\u00fcrich",
    "sg:orig_category":"Schreib U \u00dcbersetzungsb\u00fcros \u00dcbersetzungsb\u00fcros",
    "sg:phone":"+41 31 951 84 70",
    "sg:postcode":"8025",
    "wof:name":"Alltext Gmbh",
    "wof:placetype":"venue"
},
  "geometry": {"coordinates":[7.5245838165,46.9141731262],"type":"Point"}
}