{
  "type": "Feature",
  "properties": {
    "iso:country":"CH",
    "sg:address":"Riasco Via 42",
    "sg:city":"Brissago",
    "sg:orig_category":"Architektur U Ingenieurb\u00fcros",
    "sg:phone":"+41 91 793 23 65",
    "sg:postcode":"6614",
    "sg:province":"Ticino",
    "wof:name":"At - Architettura E Tecnica Massimo E Luigi Biffi Sagl",
    "wof:placetype":"venue"
},
  "geometry": {"coordinates":[8.710298,46.118977],"type":"Point"}
}