{
  "type": "Feature",
  "properties": {
    "iso:country":"CH",
    "sg:address":"Bahnhofstrasse 32",
    "sg:city":"M\u00e4rstetten",
    "sg:orig_category":"Nationale Postdienste",
    "sg:phone":"+41 71 659 06 60",
    "sg:postcode":"8560",
    "sg:province":"Thurgau",
    "wof:name":"Die Schweizerische Post",
    "wof:placetype":"venue"
},
  "geometry": {"coordinates":[9.0652971268,47.5903282166],"type":"Point"}
}