{
  "type": "Feature",
  "properties": {
    "addr:full":"Place Du Mai 1 St-ursanne Jura 2882",
    "addr:housenumber":"1",
    "addr:postcode":"2882",
    "addr:street":"Place Du Mai;Jura",
    "iso:country":"CH",
    "sg:address":"Place Du Mai 1",
    "sg:city":"St-ursanne",
    "sg:orig_category":"Architektur U Ingenieurb\u00fcros",
    "sg:phone":"+41 52 672 59 23",
    "sg:postcode":"2882",
    "sg:province":"Jura",
    "wof:name":"P. B\u00fchrer Gmbh, Architekturb\u00fcro",
    "wof:placetype":"venue"
},
  "geometry": {"coordinates":[8.62304,47.682442],"type":"Point"}
}