{
  "type": "Feature",
  "properties": {
    "iso:country":"CH",
    "sg:address":"Freiburgstrasse 14 3178 B\u00f6singen. Postfach",
    "sg:city":"B\u00f6singen",
    "sg:orig_category":"Maler U Glasergewerbe Malerei",
    "sg:phone":"+41 31 747 79 91",
    "sg:postcode":"3178",
    "sg:province":"Fribourg",
    "wof:name":"Schmutz Armin",
    "wof:placetype":"venue"
},
  "geometry": {"coordinates":[7.2267751694,46.8914833069],"type":"Point"}
}