{
  "type": "Feature",
  "properties": {
    "iso:country":"CH",
    "sg:address":"Laupenstrasse 12",
    "sg:city":"Neuenegg",
    "sg:orig_category":"Landwirtschaftliche Genossenschaften",
    "sg:phone":"+41 31 741 04 32",
    "sg:postcode":"3176",
    "sg:province":"Bern",
    "wof:name":"Landi Landw. Genossenschaft Neuenegg",
    "wof:placetype":"venue"
},
  "geometry": {"coordinates":[7.2990198135,46.8941116333],"type":"Point"}
}