{
  "type": "Feature",
  "properties": {
    "iso:country":"CH",
    "sg:address":"Cit\u00e9-derri\u00e8re Rue 8 1005 Lausanne. Postfach",
    "sg:city":"Lausanne",
    "sg:orig_category":"Gesundheitswesen",
    "sg:phone":"+41 21 323 15 01",
    "sg:postcode":"1003",
    "sg:province":"Vaud",
    "wof:name":"L'atelier Du Dialogue Int\u00e9rieur, Oesch Adelheid Enseignement D. Le Dom. D D\u00e9velopp. Personnel",
    "wof:placetype":"venue"
},
  "geometry": {"coordinates":[6.6361041069,46.5231666565],"type":"Point"}
}