{
  "type": "Feature",
  "properties": {
    "iso:country":"CH",
    "sg:address":"D\u00f6rflistrasse 20",
    "sg:city":"K\u00f6lliken",
    "sg:orig_category":"K\u00fcnstlerische Schulen",
    "sg:phone":"+41 62 723 13 76",
    "sg:postcode":"5742",
    "sg:province":"Aargau",
    "wof:name":"Werner Bossard Handharmonikaschule",
    "wof:placetype":"venue"
},
  "geometry": {"coordinates":[8.0199604034,47.3408546448],"type":"Point"}
}