{
  "type": "Feature",
  "properties": {
    "iso:country":"CH",
    "sg:address":"Via Pini 11 6710 Biasca. Postfach",
    "sg:city":"Biasca",
    "sg:orig_category":"Detailhandel mit Herrenbekleidung Grosshandel mit sonstigen Gebrauchs U Verbrauchsg\u00fctern",
    "sg:phone":"+41 91 880 03 40",
    "sg:postcode":"6710",
    "sg:province":"Ticino",
    "wof:name":"Passionsport Sagl Articoli Per La Caccia E Tiro Ecc.; Vendita, Acquisto, Comm.",
    "wof:placetype":"venue"
},
  "geometry": {"coordinates":[8.9700622559,46.3598556519],"type":"Point"}
}