{
  "type": "Feature",
  "properties": {
    "iso:country":"CH",
    "sg:address":"Ringstrasse 53",
    "sg:city":"Vilters",
    "sg:orig_category":"Innenausbau Sonstige Herstellung von Konstruktionsteilen, Fertigbauteilen U Ausbauelementen aus Holz",
    "sg:phone":"+41 81 723 42 31",
    "sg:postcode":"7324",
    "sg:province":"St. Gallen",
    "wof:name":"Vils Bruno Holzbau Ag",
    "wof:placetype":"venue"
},
  "geometry": {"coordinates":[9.4523200989,47.0284843445],"type":"Point"}
}