{
  "type": "Feature",
  "properties": {
    "iso:country":"CH",
    "sg:address":"Glattalstrasse 507",
    "sg:city":"R\u00fcmlang",
    "sg:orig_category":"Autospenglereien",
    "sg:phone":"+41 31 747 82 15",
    "sg:postcode":"8153",
    "sg:province":"Z\u00fcrich",
    "wof:name":"Martin Nydegger Carrosserie",
    "wof:placetype":"venue"
},
  "geometry": {"coordinates":[7.242225,46.898975],"type":"Point"}
}