{
  "type": "Feature",
  "properties": {
    "iso:country":"CH",
    "sg:address":"Bernstr. 48 G",
    "sg:city":"Grafenried",
    "sg:orig_category":"Nahrungsmittel-Industrie: Rohstoffe",
    "sg:phone":"+41 31677744",
    "sg:postcode":"3308",
    "sg:province":"Bern",
    "wof:name":"Biva Vardi & Co",
    "wof:placetype":"venue"
},
  "geometry": {"coordinates":[7.5111999512,47.0768051147],"type":"Point"}
}