{
  "type": "Feature",
  "properties": {
    "iso:country":"CH",
    "sg:address":"Staatsstrasse 65",
    "sg:city":"Rebstein",
    "sg:orig_category":"Bau U Wohngenossenschaften",
    "sg:postcode":"9445",
    "sg:province":"St. Gallen",
    "wof:name":"Liberale Baugen.zell",
    "wof:placetype":"venue"
},
  "geometry": {"coordinates":[7.922749,47.139156],"type":"Point"}
}