{
  "type": "Feature",
  "properties": {
    "iso:country":"CH",
    "sg:address":"Chemin Des Perchettes",
    "sg:city":"Founex",
    "sg:orig_category":"Herstellung von sonstigen M\u00f6beln",
    "sg:postcode":"1297",
    "sg:province":"Vaud",
    "wof:name":"Baldino Giuseppe.",
    "wof:placetype":"venue"
},
  "geometry": {"coordinates":[6.2015948296,46.3314857483],"type":"Point"}
}