{
  "type": "Feature",
  "properties": {
    "iso:country":"CH",
    "sg:address":"B\u00fcndte 5",
    "sg:city":"Tamins",
    "sg:orig_category":"Grosshandel mit sonstigen Maschinen U Ausr\u00fcstungen f\u00fcr Industrie, Handel U Schiffahrt",
    "sg:postcode":"7015",
    "sg:province":"Graubunden",
    "wof:name":"Obchodni-technik, H. Plump",
    "wof:placetype":"venue"
},
  "geometry": {"coordinates":[9.4057245255,46.8296470642],"type":"Point"}
}