{
  "type": "Feature",
  "properties": {
    "iso:country":"CH",
    "sg:address":"Kirchgemeindehaus 3700 Spiez. Postfach 243",
    "sg:city":"Spiez",
    "sg:orig_category":"Sonstige Institutionen des Sozialwesens ohne Beherbergung",
    "sg:phone":"+41 33 654 40 04",
    "sg:postcode":"3700",
    "sg:province":"Bern",
    "wof:name":"Jugendberatungsstelle Der Evangelischen Kirchgemeinde",
    "wof:placetype":"venue"
},
  "geometry": {"coordinates":[7.6748552322,46.6898498535],"type":"Point"}
}