{
  "type": "Feature",
  "properties": {
    "iso:country":"CH",
    "sg:address":"Route Molliau",
    "sg:city":"Tolochenaz",
    "sg:orig_category":"Naturheil\u00e4rzte and Heilpraktiker",
    "sg:phone":"+41 21 801 39 35",
    "sg:postcode":"1131",
    "sg:province":"Vaud",
    "wof:name":"Marie-c. Rulence Naturopathe",
    "wof:placetype":"venue"
},
  "geometry": {"coordinates":[6.4755210876,46.5056877136],"type":"Point"}
}