{
  "type": "Feature",
  "properties": {
    "iso:country":"CH",
    "sg:address":"Via Canonica 5 6950 Tesserete. Postfach",
    "sg:city":"Tesserete",
    "sg:orig_category":"Non-Classified Establishments",
    "sg:postcode":"6950",
    "sg:province":"Ticino",
    "wof:name":"Nordex Sagl Partecipazioni Ecc",
    "wof:placetype":"venue"
},
  "geometry": {"coordinates":[8.9668922424,46.0670509338],"type":"Point"}
}