{
  "type": "Feature",
  "properties": {
    "iso:country":"CH",
    "sg:address":"Kauffmannweg 29",
    "sg:city":"Luzern",
    "sg:orig_category":"Naturheil\u00e4rzte and Heilpraktiker",
    "sg:phone":"+41 41 670 20 88",
    "sg:postcode":"6003",
    "sg:province":"Luzern",
    "wof:name":"Paul Bienefeld Naturarzt",
    "wof:placetype":"venue"
},
  "geometry": {"coordinates":[8.2936210632,46.9641838074],"type":"Point"}
}