{
  "type": "Feature",
  "properties": {
    "iso:country":"CH",
    "sg:address":"Alle Brughette A3",
    "sg:city":"Figino",
    "sg:orig_category":"Grosshandel mit Geschenkartikeln U Souvenirs",
    "sg:phone":"+41 91 995 22 55",
    "sg:postcode":"6918",
    "sg:province":"Ticino",
    "wof:name":"Medri Trading Di Daniela Medri Importaz.-esportaz.& Commercio",
    "wof:placetype":"venue"
},
  "geometry": {"coordinates":[8.9069690704,45.9528579712],"type":"Point"}
}