{
  "type": "Feature",
  "properties": {
    "iso:country":"CH",
    "sg:address":"Route Du Centre 13",
    "sg:city":"Corminboeuf",
    "sg:orig_category":"Nationale Postdienste",
    "sg:phone":"+41 26 677 11 25",
    "sg:postcode":"1720",
    "sg:province":"Fribourg",
    "wof:name":"La Poste Suisse",
    "wof:placetype":"venue"
},
  "geometry": {"coordinates":[6.9818091393,46.8876266479],"type":"Point"}
}