{
  "type": "Feature",
  "properties": {
    "iso:country":"CH",
    "sg:address":"Grossfeldstrasse 18",
    "sg:city":"Sargans",
    "sg:orig_category":"Zahnarztpraxen",
    "sg:phone":"+41 81 723 36 95",
    "sg:postcode":"7320",
    "sg:province":"St. Gallen",
    "wof:name":"Dres Med.dent. Stauffacher Zahn\u00e4rzte",
    "wof:placetype":"venue"
},
  "geometry": {"coordinates":[9.43983078,47.0457382202],"type":"Point"}
}