{
  "type": "Feature",
  "properties": {
    "iso:country":"CH",
    "sg:address":"Arcas 12",
    "sg:city":"Chur",
    "sg:orig_category":"Detailhandel mit S\u00e4uglings U Kinderbekleidung Sonstiger Fachdetailhandel in Verkaufsr\u00e4umen",
    "sg:phone":"+41 81 252 60 29",
    "sg:postcode":"7000",
    "sg:province":"Graubunden",
    "wof:name":"Marianne Rehli Marianne's Kinderboutique",
    "wof:placetype":"venue"
},
  "geometry": {"coordinates":[9.5314655304,46.847984314],"type":"Point"}
}