{
  "type": "Feature",
  "properties": {
    "iso:country":"CH",
    "sg:address":"Dorfstrasse 44",
    "sg:city":"Uetendorf",
    "sg:classifiers":[
        {
            "category":"Government",
            "subcategory":"Post Office",
            "type":"Public Place"
        }
    ],
    "sg:phone":"+41 33 345 45 23",
    "sg:postcode":"3661",
    "sg:province":"Bern",
    "sg:tags":[
        "caf\u00e9s",
        "tea-rooms"
    ],
    "wof:name":"Kafi Haustock",
    "wof:placetype":"venue"
},
  "geometry": {"coordinates":[7.574092865,46.7735786438],"type":"Point"}
}