{
  "type": "Feature",
  "properties": {
    "addr:full":"Thalwiesenstr 1 Kloten Z\u00fcrich 8302",
    "addr:housenumber":"1",
    "addr:postcode":"8302",
    "addr:street":"Thalwiesenstr",
    "iso:country":"CH",
    "sg:address":"Thalwiesenstr 1",
    "sg:city":"Kloten",
    "sg:classifiers":[
        {
            "category":"Banks & Credit Unions",
            "subcategory":"Investment Brokerage",
            "type":"Services"
        }
    ],
    "sg:phone":"+41 4118169030",
    "sg:postcode":"8302",
    "sg:province":"Z\u00fcrich",
    "sg:tags":[
        "sea",
        "transport",
        "road",
        "air"
    ],
    "wof:name":"Tpa Transporte Panatlantic Ag",
    "wof:placetype":"venue"
},
  "geometry": {"coordinates":[8.583049,47.457268],"type":"Point"}
}