{
  "type": "Feature",
  "properties": {
    "iso:country":"CH",
    "sg:address":"Oberhilti",
    "sg:city":"Hohenrain",
    "sg:orig_category":"Verarbeitung von Milch Verwertung von Milch",
    "sg:postcode":"6276",
    "sg:province":"Luzern",
    "wof:name":"K\u00e4sereigenossenschaft Halden",
    "wof:placetype":"venue"
},
  "geometry": {"coordinates":[9.0054197311,47.19764328],"type":"Point"}
}