{
  "type": "Feature",
  "properties": {
    "iso:country":"CH",
    "sg:address":"Kantonsstrasse 111",
    "sg:city":"Horw",
    "sg:orig_category":"Innenausbau M\u00f6belschreinerei",
    "sg:phone":"+41 41 340 23 42",
    "sg:postcode":"6048",
    "sg:province":"Luzern",
    "wof:name":"K\u00e4lin & Co",
    "wof:placetype":"venue"
},
  "geometry": {"coordinates":[8.3107786179,47.0138702393],"type":"Point"}
}