{
  "type": "Feature",
  "properties": {
    "iso:country":"CH",
    "sg:address":"Hohlstrasse 169",
    "sg:city":"Z\u00fcrich",
    "sg:orig_category":"Sonstige Verkehrsvermittlung",
    "sg:phone":"+41 71 744 08 25",
    "sg:postcode":"8004",
    "sg:province":"Z\u00fcrich",
    "wof:name":"Verzollungsagentur Ferrer Gmbh Zollabfertigung. Waren; Import, Export Usw.",
    "wof:placetype":"venue"
},
  "geometry": {"coordinates":[9.6429071426,47.4530143738],"type":"Point"}
}