{
  "type": "Feature",
  "properties": {
    "iso:country":"CH",
    "sg:address":"Guggistrasse 27",
    "sg:city":"Luzern",
    "sg:classifiers":[
        {
            "category":"Personal",
            "subcategory":"Hair Removal",
            "type":"Services"
        }
    ],
    "sg:phone":"+41 41 311 24 66",
    "sg:postcode":"6005",
    "sg:province":"Luzern",
    "sg:tags":[
        "cap",
        "hat"
    ],
    "wof:name":"Bafix Ag",
    "wof:placetype":"venue"
},
  "geometry": {"coordinates":[8.299215,47.044094],"type":"Point"}
}