{
  "type": "Feature",
  "properties": {
    "iso:country":"CH",
    "sg:address":"Plambuit",
    "sg:city":"Panex",
    "sg:classifiers":[
        {
            "category":"Restaurant",
            "type":"Food & Drink"
        }
    ],
    "sg:phone":"+41 24 499 13 56",
    "sg:postcode":"1858",
    "wof:name":"Caf\u00e9 De Plambuit",
    "wof:placetype":"venue"
},
  "geometry": {"coordinates":[7.0141601562,46.3112297058],"type":"Point"}
}