{
  "type": "Feature",
  "properties": {
    "iso:country":"CH",
    "sg:address":"Rue Du Grand-pont 21",
    "sg:city":"Sion",
    "sg:classifiers":[
        {
            "category":"Restaurant",
            "type":"Food & Drink"
        }
    ],
    "sg:phone":"+41 27 323 83 77",
    "sg:postcode":"1950",
    "sg:province":"Valais",
    "wof:name":"Grotto De La Fontaine",
    "wof:placetype":"venue"
},
  "geometry": {"coordinates":[7.3603811264,46.2345085144],"type":"Point"}
}