{
  "type": "Feature",
  "properties": {
    "iso:country":"CH",
    "sg:address":"St. Gallerstrasse 54",
    "sg:city":"Matzingen",
    "sg:orig_category":"Herstellung von Platten, Folien, Schl\u00e4uchen U Profilen aus Kunststoff Herstellung von sonstigen Masc",
    "sg:phone":"+41 19101924",
    "sg:postcode":"9548",
    "sg:province":"Thurgau",
    "wof:name":"Ernst Rudolf Ag, Maschinenfabrik",
    "wof:placetype":"venue"
},
  "geometry": {"coordinates":[8.5907516479,47.3147506714],"type":"Point"}
}