{
  "type": "Feature",
  "properties": {
    "iso:country":"CH",
    "sg:address":"Wilerstrasse 19",
    "sg:city":"Wattwil",
    "sg:orig_category":"Detailhandel mit Fahrr\u00e4dern Handel mit Motorr\u00e4dern, Teilen U Zubeh\u00f6r Instandhaltung U Reparatur von ",
    "sg:phone":"+41 71 988 78 48",
    "sg:postcode":"9630",
    "sg:province":"St. Gallen",
    "wof:name":"Velos & Motos Gabathuler",
    "wof:placetype":"venue"
},
  "geometry": {"coordinates":[9.0877323151,47.3045043945],"type":"Point"}
}