{
  "type": "Feature",
  "properties": {
    "iso:country":"CH",
    "sg:address":"Grindelstrasse 11",
    "sg:city":"Bassersdorf",
    "sg:orig_category":"Einbau von Schreinerwaren",
    "sg:phone":"+41 71 278 40 21",
    "sg:postcode":"8303",
    "sg:province":"Z\u00fcrich",
    "wof:name":"Erwin Sprenger Einbauk\u00fcchen",
    "wof:placetype":"venue"
},
  "geometry": {"coordinates":[9.3609333038,47.415473938],"type":"Point"}
}