{
  "type": "Feature",
  "properties": {
    "iso:country":"CH",
    "sg:address":"Schaffhauserstrasse 193a",
    "sg:city":"Frauenfeld",
    "sg:orig_category":"Wirtschaftspr\u00fcfung, Steuerberatung U Treuhand",
    "sg:phone":"+41 52 721 89 28",
    "sg:postcode":"8500",
    "sg:province":"Thurgau",
    "wof:name":"Zefimo Verwaltungen Ag",
    "wof:placetype":"venue"
},
  "geometry": {"coordinates":[8.8792495728,47.5628509521],"type":"Point"}
}