{
  "type": "Feature",
  "properties": {
    "iso:country":"CH",
    "sg:address":"Brunnenwisstrasse 11",
    "sg:city":"Gr\u00fcningen",
    "sg:orig_category":"Unclassifiable Establishments",
    "sg:phone":"+41 19354575",
    "sg:postcode":"8627",
    "sg:province":"Z\u00fcrich",
    "wof:name":"Fg Unternehmensberatungen Gmbh",
    "wof:placetype":"venue"
},
  "geometry": {"coordinates":[8.7569885254,47.2847709656],"type":"Point"}
}