{
  "type": "Feature",
  "properties": {
    "iso:country":"CH",
    "sg:address":"Grundstrasse 4",
    "sg:city":"Rotkreuz",
    "sg:orig_category":"Herstellung von sonstigen Metallwaren",
    "sg:phone":"+41 79 218 50 90",
    "sg:postcode":"6343",
    "sg:province":"Zug",
    "wof:name":"Technikplan Gmbh",
    "wof:placetype":"venue"
},
  "geometry": {"coordinates":[8.4297704697,47.1448402405],"type":"Point"}
}