{
  "type": "Feature",
  "properties": {
    "iso:country":"CH",
    "sg:address":"Altwingerten 15",
    "sg:city":"Dinhard",
    "sg:orig_category":"Elektroinstallation",
    "sg:phone":"+41 52 336 14 53",
    "sg:postcode":"8474",
    "sg:province":"Z\u00fcrich",
    "wof:name":"Hansruedi Gretener Elektro-anlagen",
    "wof:placetype":"venue"
},
  "geometry": {"coordinates":[8.7488327026,47.5538902283],"type":"Point"}
}