{
  "type": "Feature",
  "properties": {
    "iso:country":"CH",
    "sg:address":"Rathausgasse 23",
    "sg:city":"Glarus",
    "sg:orig_category":"Detailhandel mit Brot, Back U S\u00fcsswaren",
    "sg:postcode":"8750",
    "sg:province":"Glarus",
    "wof:name":"Aebli-hartmann Hch., B\u00e4ckerei-konditorei",
    "wof:placetype":"venue"
},
  "geometry": {"coordinates":[9.06627,47.040901],"type":"Point"}
}