{
  "type": "Feature",
  "properties": {
    "iso:country":"CH",
    "sg:address":"Speicherstrasse 11 8500 Frauenfeld. Postfach",
    "sg:city":"Matzingen",
    "sg:orig_category":"Forschung U Entwicklung im Bereich der Naturwissenschaften",
    "sg:postcode":"9548",
    "sg:province":"Thurgau",
    "wof:name":"Stiftung F\u00fcr Biomedizinische Forschung",
    "wof:placetype":"venue"
},
  "geometry": {"coordinates":[8.9045982361,47.5575447083],"type":"Point"}
}