{
  "type": "Feature",
  "properties": {
    "iso:country":"CH",
    "sg:address":"Via Al Mulino 21",
    "sg:city":"Cadempino",
    "sg:orig_category":"Grosshandel mit Flachglas, Sanit\u00e4rkeramik U Anstrichmitteln Herstellung von Anstrichmitteln, Druckfa",
    "sg:phone":"+41 91 968 21 69",
    "sg:postcode":"6814",
    "sg:province":"Ticino",
    "wof:name":"Iolca Sa Commercio Di Vernici",
    "wof:placetype":"venue"
},
  "geometry": {"coordinates":[8.9314403534,46.0353088379],"type":"Point"}
}