{
  "type": "Feature",
  "properties": {
    "iso:country":"CH",
    "sg:address":"Hintere Gasse 3",
    "sg:city":"Kerzers",
    "sg:orig_category":"Herstellung von Metallerzeugnissen ohne Maschinenbau Maschinenbau",
    "sg:phone":"+41 32 913 85 82",
    "sg:postcode":"3210",
    "sg:province":"Fribourg",
    "wof:name":"Rewitech Sa",
    "wof:placetype":"venue"
},
  "geometry": {"coordinates":[6.8209791183,47.1025505066],"type":"Point"}
}