{
  "type": "Feature",
  "properties": {
    "iso:country":"CH",
    "sg:address":"Subergstrasse 45",
    "sg:city":"Grossaffoltern",
    "sg:orig_category":"Maler U Glasergewerbe",
    "sg:phone":"+41 71 333 13 91",
    "sg:postcode":"3257",
    "sg:province":"Bern",
    "wof:name":"Christian Cadosch",
    "wof:placetype":"venue"
},
  "geometry": {"coordinates":[9.3821697235,47.3912200928],"type":"Point"}
}