{
  "type": "Feature",
  "properties": {
    "iso:country":"CH",
    "sg:address":"Rotwegstrasse 4",
    "sg:city":"Horgen",
    "sg:orig_category":"Detailhandel mit Waren verschiedener Art, Hauptrichtung Nahrungsmittel Fachdetailhandel mit Nahrungs",
    "sg:phone":"+41 17200654",
    "sg:postcode":"8810",
    "sg:province":"Z\u00fcrich",
    "wof:name":"Reto Studer",
    "wof:placetype":"venue"
},
  "geometry": {"coordinates":[8.6083898544,47.2562599182],"type":"Point"}
}