{
  "type": "Feature",
  "properties": {
    "iso:country":"CH",
    "sg:address":"Kunoweg 23",
    "sg:city":"Bremgarten",
    "sg:classifiers":[
        {
            "category":"Professional",
            "subcategory":"Art Services",
            "type":"Services"
        }
    ],
    "sg:phone":"+41 31 302 43 34",
    "sg:postcode":"3047",
    "sg:province":"Bern",
    "sg:tags":[
        "homepage",
        "designing"
    ],
    "wof:name":"Webcare",
    "wof:placetype":"venue"
},
  "geometry": {"coordinates":[7.43516922,46.9744033813],"type":"Point"}
}