{
  "type": "Feature",
  "properties": {
    "iso:country":"CH",
    "sg:address":"Via Maggio 1",
    "sg:city":"Cassarate",
    "sg:classifiers":[
        {
            "category":"Banks & Credit Unions",
            "subcategory":"Bank",
            "type":"Services"
        }
    ],
    "sg:phone":"+41 4191210110",
    "sg:postcode":"6900",
    "sg:province":"Ticino",
    "wof:name":"Banque De Participations, Et De Placements Sa",
    "wof:placetype":"venue"
},
  "geometry": {"coordinates":[8.961099,46.008034],"type":"Point"}
}