{
  "type": "Feature",
  "properties": {
    "iso:country":"CH",
    "sg:address":"Chemin Monplaisir 9",
    "sg:city":"Ch\u00eane-bougeries",
    "sg:orig_category":"Gesundheitswesen",
    "sg:phone":"+41 22 869 11 03",
    "sg:postcode":"1224",
    "sg:province":"Gen\u00e8ve",
    "wof:name":"Savoyat Bruno",
    "wof:placetype":"venue"
},
  "geometry": {"coordinates":[6.1837911606,46.1996116638],"type":"Point"}
}