{
  "type": "Feature",
  "properties": {
    "iso:country":"CH",
    "sg:address":"Neuhofstrasse 9",
    "sg:city":"Lindau",
    "sg:orig_category":"Allgemeiner Hoch U Tiefbau",
    "sg:postcode":"8315",
    "sg:province":"Z\u00fcrich",
    "wof:name":"Tri Renova Lerch, Weiss + Mastrodomenico",
    "wof:placetype":"venue"
},
  "geometry": {"coordinates":[8.672724,47.441757],"type":"Point"}
}