{
  "type": "Feature",
  "properties": {
    "iso:country":"CH",
    "sg:address":"Schlossm\u00fchlestrasse 1",
    "sg:city":"Frauenfeld",
    "sg:orig_category":"Kosmetikinstitute",
    "sg:phone":"+41 52 721 60 49",
    "sg:postcode":"8500",
    "sg:province":"Thurgau",
    "wof:name":"Carmen Moretti Kosmetisches Institut",
    "wof:placetype":"venue"
},
  "geometry": {"coordinates":[8.8967628479,47.5551719666],"type":"Point"}
}