{
  "type": "Feature",
  "properties": {
    "iso:country":"CH",
    "sg:address":"Rue De Pr\u00e9-fleuri 2b",
    "sg:city":"Sion",
    "sg:orig_category":"Detailhandel mit Damenbekleidung Detailhandel mit Herrenbekleidung",
    "sg:postcode":"1950",
    "sg:province":"Valais",
    "wof:name":"Yvonne Schmid-h\u00fcrlimann Boutique Laura",
    "wof:placetype":"venue"
},
  "geometry": {"coordinates":[8.7988815308,47.3261222839],"type":"Point"}
}