{
  "type": "Feature",
  "properties": {
    "iso:country":"CH",
    "sg:address":"Thunstr. 113",
    "sg:city":"Bern",
    "sg:classifiers":[
        {
            "category":"Manufacturing",
            "subcategory":"Tools & Machinery",
            "type":"Manufacturing & Wholesale Goods"
        }
    ],
    "sg:phone":"+41 31 352 85 85",
    "sg:postcode":"3006",
    "sg:province":"Bern",
    "sg:tags":[
        "equipment",
        "measurement",
        "-",
        "precision",
        "instrument"
    ],
    "wof:name":"Ingentra Ag",
    "wof:placetype":"venue"
},
  "geometry": {"coordinates":[7.4658460617,46.9417114258],"type":"Point"}
}