{
  "type": "Feature",
  "properties": {
    "iso:country":"CH",
    "sg:address":"Gutenbergstrasse 24 3011 Bern. Postfach",
    "sg:city":"Bern",
    "sg:orig_category":"Sonstiger Grosshandel",
    "sg:phone":"+41 71 385 95 46",
    "sg:postcode":"3005",
    "sg:province":"Bern",
    "wof:name":"Specht Petura Ag",
    "wof:placetype":"venue"
},
  "geometry": {"coordinates":[9.2435712814,47.4140853882],"type":"Point"}
}