{
  "type": "Feature",
  "properties": {
    "iso:country":"CH",
    "sg:address":"Hinterer Engelstein 8",
    "sg:city":"B\u00e4retswil",
    "sg:orig_category":"Detektivb\u00fcros U \u00dcberwachung Sicherheitsdienste",
    "sg:phone":"+41 19393141",
    "sg:postcode":"8344",
    "sg:province":"Z\u00fcrich",
    "wof:name":"She Service + Consulting, Maschek Wolfgang",
    "wof:placetype":"venue"
},
  "geometry": {"coordinates":[8.8521490097,47.3423614502],"type":"Point"}
}