{
  "type": "Feature",
  "properties": {
    "iso:country":"CH",
    "sg:address":"Holdenweg 27 4455 Zunzgen. Postfach",
    "sg:city":"Zunzgen",
    "sg:orig_category":"Architektur U Ingenieurb\u00fcros",
    "sg:postcode":"4455",
    "sg:province":"Basel-Landschaft",
    "wof:name":"Schaffner W. Baudienstleistungen",
    "wof:placetype":"venue"
},
  "geometry": {"coordinates":[7.809046,47.451035],"type":"Point"}
}