{
  "type": "Feature",
  "properties": {
    "iso:country":"CH",
    "sg:address":"Ch\u00fceferistrasse 16",
    "sg:city":"Fehraltorf",
    "sg:orig_category":"Sonstige Herstellung von Konstruktionsteilen, Fertigbauteilen U Ausbauelementen aus Holz",
    "sg:phone":"+41 19541285",
    "sg:postcode":"8320",
    "sg:province":"Z\u00fcrich",
    "wof:name":"Naef Saunabau",
    "wof:placetype":"venue"
},
  "geometry": {"coordinates":[8.754442215,47.3840522766],"type":"Point"}
}