{
  "type": "Feature",
  "properties": {
    "iso:country":"CH",
    "sg:address":"Rue De La Boverie 19",
    "sg:city":"Payerne",
    "sg:orig_category":"RESTAURANTS: TEA-ROOMS",
    "sg:postcode":"1530",
    "sg:province":"Vaud",
    "wof:name":"Donzallaz Mme Verena Caf\u00e9-restaurant L'a\u00e9rodrome",
    "wof:placetype":"venue"
},
  "geometry": {"coordinates":[7.0892109871,46.7579231262],"type":"Point"}
}