{
  "type": "Feature",
  "properties": {
    "iso:country":"CH",
    "sg:address":"Neuenburgstrasse 27",
    "sg:city":"T\u00fcscherz-alferm\u00e9e",
    "sg:classifiers":[
        {
            "category":"Restaurant",
            "type":"Food & Drink"
        }
    ],
    "sg:phone":"+41 71 455 10 58",
    "sg:postcode":"2512",
    "sg:province":"Bern",
    "wof:name":"Restaurant Sternen",
    "wof:placetype":"venue"
},
  "geometry": {"coordinates":[9.3995685577,47.5031776428],"type":"Point"}
}