{
  "type": "Feature",
  "properties": {
    "iso:country":"CH",
    "sg:address":"Spinnlerstrasse 12",
    "sg:city":"Liestal",
    "sg:orig_category":"Instandhaltung U Reparatur von Automobilen",
    "sg:phone":"+41 61 921 44 45",
    "sg:postcode":"4410",
    "sg:province":"Basel-Landschaft",
    "wof:name":"Garage + Carrosserie Oristal, Bl\u00f6chliger-krystynek Zdenek",
    "wof:placetype":"venue"
},
  "geometry": {"coordinates":[7.7258081436,47.4763832092],"type":"Point"}
}