{
  "type": "Feature",
  "properties": {
    "iso:country":"CH",
    "sg:address":"Entre-deux-rivi\u00e8res",
    "sg:city":"Fleurier",
    "sg:orig_category":"Herstellung von Duft U K\u00f6rperpflegemitteln",
    "sg:phone":"+41 22 810 09 80",
    "sg:postcode":"2114",
    "sg:province":"Neuch\u00e2tel",
    "wof:name":"Phyto Distribution Sa",
    "wof:placetype":"venue"
},
  "geometry": {"coordinates":[6.585474968,46.9066162109],"type":"Point"}
}