{
  "type": "Feature",
  "properties": {
    "iso:country":"CH",
    "sg:address":"Im Feld",
    "sg:city":"Leissigen",
    "sg:orig_category":"Wirtschaftspr\u00fcfung, Steuerberatung U Treuhand",
    "sg:phone":"+41 33 847 00 00",
    "sg:postcode":"3706",
    "sg:province":"Bern",
    "wof:name":"Bsr Treuhand, M\u00fchlheim Franziska",
    "wof:placetype":"venue"
},
  "geometry": {"coordinates":[7.7740898132,46.6546554565],"type":"Point"}
}