{
  "type": "Feature",
  "properties": {
    "iso:country":"CH",
    "sg:address":"En Pallatex 5 1163 Etoy. Postfach",
    "sg:city":"Etoy",
    "sg:orig_category":"Blumen U Zierpflanzenbau Grosshandel mit Obst U Gem\u00fcse",
    "sg:phone":"+41 21 807 39 69",
    "sg:postcode":"1163",
    "sg:province":"Vaud",
    "wof:name":"Thury Fruits Sa Gestion De Domaines De Cultures Fruiti\u00e8res Et Mara\u00eech\u00e8res Etc",
    "wof:placetype":"venue"
},
  "geometry": {"coordinates":[6.428012,46.477425],"type":"Point"}
}