{
  "type": "Feature",
  "properties": {
    "iso:country":"CH",
    "sg:address":"Moserstrasse 24 3005 Bern. Postfach",
    "sg:city":"Bern",
    "sg:classifiers":[
        {
            "category":"Communications",
            "subcategory":"Radio Station",
            "type":"Services"
        }
    ],
    "sg:phone":"+41 19333298",
    "sg:postcode":"3005",
    "sg:province":"Bern",
    "sg:tags":[
        "fernsehanstalten",
        "u"
    ],
    "wof:name":"Regionalfernseh.z\u00fcrcher Ober- Land Ag,c/o Druckerei Wetzikon",
    "wof:placetype":"venue"
},
  "geometry": {"coordinates":[8.7933101654,47.3177604675],"type":"Point"}
}