{
  "type": "Feature",
  "properties": {
    "iso:country":"CH",
    "sg:address":"Viale Giuseppe Motta 7",
    "sg:city":"Bellinzona",
    "sg:orig_category":"Detailhandel Reparatur von Gebrauchsg\u00fctern Vermietung von Gebrauchsg\u00fctern",
    "sg:phone":"+41 41 850 68 59",
    "sg:postcode":"6500",
    "sg:province":"Ticino",
    "wof:name":"Videothek Atlantis",
    "wof:placetype":"venue"
},
  "geometry": {"coordinates":[8.440079689,47.0829467773],"type":"Point"}
}