{
  "type": "Feature",
  "properties": {
    "iso:country":"CH",
    "sg:address":"Gmeindstrasse 4",
    "sg:city":"Diepoldsau",
    "sg:orig_category":"Grosshandel mit Textilien Herstellung von konfektionierten Textilwaren ohne Bekleidung",
    "sg:phone":"+41 71 733 22 77",
    "sg:postcode":"9444",
    "sg:province":"St. Gallen",
    "wof:name":"Biasi E. Gmbh",
    "wof:placetype":"venue"
},
  "geometry": {"coordinates":[9.6567621231,47.3810691833],"type":"Point"}
}