{
  "type": "Feature",
  "properties": {
    "iso:country":"CH",
    "sg:address":"Baarerstrasse 43 6300 Zug. Postfach",
    "sg:city":"Zug",
    "sg:orig_category":"Pensionskassen",
    "sg:phone":"+41 41 710 32 39",
    "sg:postcode":"6300",
    "sg:province":"Zug",
    "wof:name":"F\u00fcrsorgefonds Der Firma Stralfors Th. Ag",
    "wof:placetype":"venue"
},
  "geometry": {"coordinates":[8.516579628,47.1738433838],"type":"Point"}
}