{
  "type": "Feature",
  "properties": {
    "iso:country":"CH",
    "sg:address":"Route De Belfort 77",
    "sg:city":"Porrentruy",
    "sg:orig_category":"Dienstleistungen in der Forstwirtschaft Herstellung von Elektromotoren, Generatoren U Transformatore",
    "sg:phone":"+41 32 466 29 44",
    "sg:postcode":"2900",
    "sg:province":"Jura",
    "wof:name":"Thermor\u00e9seau - Porrentruy Sa",
    "wof:placetype":"venue"
},
  "geometry": {"coordinates":[7.077559948,47.4244194031],"type":"Point"}
}