{
  "type": "Feature",
  "properties": {
    "iso:country":"CH",
    "sg:address":"Auriedstrasse 20",
    "sg:city":"B\u00f6singen",
    "sg:orig_category":"Grosshandel mit B\u00fcromaschinen Herstellung von sonstigen elektrischen Ausr\u00fcstungen",
    "sg:phone":"+41 31 378 70 70",
    "sg:postcode":"3178",
    "sg:province":"Fribourg",
    "wof:name":"Comdirect Ag",
    "wof:placetype":"venue"
},
  "geometry": {"coordinates":[7.2291150093,46.9020690918],"type":"Point"}
}