{
  "type": "Feature",
  "properties": {
    "iso:country":"CH",
    "sg:address":"4814",
    "sg:city":"Bottenwil",
    "sg:orig_category":"Vereine Musik/Blasmusik",
    "sg:postcode":"4814",
    "sg:province":"Aargau",
    "wof:name":"Posaunenchor",
    "wof:placetype":"venue"
},
  "geometry": {"coordinates":[7.9994702339,47.2817802429],"type":"Point"}
}