{
  "type": "Feature",
  "properties": {
    "iso:country":"CH",
    "sg:address":"Kugelmoos",
    "sg:city":"Sch\u00f6nengrund",
    "sg:orig_category":"Vorschulen, Kinderg\u00e4rten",
    "sg:phone":"+41 71 361 10 15",
    "sg:postcode":"9105",
    "sg:province":"Appenzell Ausserrhoden",
    "wof:name":"Kindergarten",
    "wof:placetype":"venue"
},
  "geometry": {"coordinates":[9.2274198532,47.3283348083],"type":"Point"}
}