{
  "type": "Feature",
  "properties": {
    "iso:country":"CH",
    "sg:address":"Hauptstr. 96",
    "sg:city":"Merenschwand",
    "sg:orig_category":"Herstellung von Mess U Kontrollinstrumenten U vorrichtungen",
    "sg:phone":"+41 56 675 57 57",
    "sg:postcode":"5634",
    "sg:province":"Aargau",
    "wof:name":"Plantech Ag",
    "wof:placetype":"venue"
},
  "geometry": {"coordinates":[8.3721055984,47.2608451843],"type":"Point"}
}