{
  "type": "Feature",
  "properties": {
    "addr:full":"Chalet Alpina Verbier Valais 1936",
    "addr:postcode":"1936",
    "iso:country":"CH",
    "sg:address":"Chalet Alpina",
    "sg:city":"Verbier",
    "sg:orig_category":"Chemische Reinigung Teppichreinigung",
    "sg:phone":"+41 27 771 73 17",
    "sg:postcode":"1936",
    "sg:province":"Valais",
    "wof:name":"Egm Sa Nettoyage & Maintenance",
    "wof:placetype":"venue"
},
  "geometry": {"coordinates":[7.222962,46.096729],"type":"Point"}
}