{
  "type": "Feature",
  "properties": {
    "iso:country":"CH",
    "sg:address":"G\u00fcrtelstrasse 8",
    "sg:city":"Chur",
    "sg:orig_category":"Grosshandel mit Geschenkartikeln U Souvenirs Herstellung von sonstigen Erzeugnissen",
    "sg:phone":"+41 81 253 56 55",
    "sg:postcode":"7000",
    "sg:province":"Graubunden",
    "wof:name":"Ballon-service, Kollegger & M\u00fcller",
    "wof:placetype":"venue"
},
  "geometry": {"coordinates":[9.5278568268,46.851940155],"type":"Point"}
}