{
  "type": "Feature",
  "properties": {
    "iso:country":"CH",
    "sg:address":"1875",
    "sg:city":"Morgins",
    "sg:orig_category":"G\u00fcterbef\u00f6rderung im Strassenverkehr",
    "sg:phone":"+41 32 841 19 06",
    "sg:postcode":"1875",
    "sg:province":"Valais",
    "wof:name":"Raymond Ducommun Transports",
    "wof:placetype":"venue"
},
  "geometry": {"coordinates":[6.8509349823,46.9669876099],"type":"Point"}
}