{
  "type": "Feature",
  "properties": {
    "iso:country":"CH",
    "sg:address":"Marienstrasse 16",
    "sg:city":"Z\u00fcrich",
    "sg:classifiers":[
        {
            "category":"Restaurant",
            "type":"Food & Drink"
        }
    ],
    "sg:phone":"+41 14626532",
    "sg:postcode":"8003",
    "sg:province":"Z\u00fcrich",
    "wof:name":"Restaurant Boccalino",
    "wof:placetype":"venue"
},
  "geometry": {"coordinates":[8.5180807114,47.374584198],"type":"Point"}
}