{
  "type": "Feature",
  "properties": {
    "iso:country":"CH",
    "sg:address":"Scuole Via Delle",
    "sg:city":"Cadempino",
    "sg:orig_category":"RESTAURANTS: TEA-ROOMS",
    "sg:phone":"+41 91 967 18 54",
    "sg:postcode":"6814",
    "sg:province":"Ticino",
    "wof:name":"Giacosa Giovanni",
    "wof:placetype":"venue"
},
  "geometry": {"coordinates":[8.93151474,46.0453643799],"type":"Point"}
}