{
  "type": "Feature",
  "properties": {
    "iso:country":"CH",
    "sg:address":"Seeblick 1",
    "sg:city":"Cham",
    "sg:orig_category":"Markt U Meinungsforschung Public-Relations-Agenturen",
    "sg:phone":"+41 41 785 21 45",
    "sg:postcode":"6330",
    "sg:province":"Zug",
    "wof:name":"West'n Forest Ag",
    "wof:placetype":"venue"
},
  "geometry": {"coordinates":[8.4589233398,47.1807899475],"type":"Point"}
}