{
  "type": "Feature",
  "properties": {
    "iso:country":"CH",
    "sg:address":"Meierhofstrasse 15",
    "sg:city":"Triesen",
    "sg:orig_category":"HOTELS: MIT RESTAURANT Kongress- and Tagungshotels mit Restaurant",
    "sg:phone":"+423 399 00 11",
    "sg:postcode":"9495",
    "wof:name":"Hotel Meierhof Ag",
    "wof:placetype":"venue"
},
  "geometry": {"coordinates":[9.5289125443,47.1222038269],"type":"Point"}
}