{
  "type": "Feature",
  "properties": {
    "iso:country":"CH",
    "sg:address":"M\u00fchlentalstrasse 5 8200 Schaffhausen. Postfach",
    "sg:city":"Schaffhausen",
    "sg:orig_category":"Fotografische Ateliers",
    "sg:phone":"+41 52 624 68 54",
    "sg:postcode":"8201",
    "sg:province":"Schaffhausen",
    "wof:name":"Heinz Hasler Gmbh Fotografisches Atelier",
    "wof:placetype":"venue"
},
  "geometry": {"coordinates":[8.6314573288,47.6995353699],"type":"Point"}
}