{
  "type": "Feature",
  "properties": {
    "iso:country":"CH",
    "sg:address":"Route De Courgenay 7",
    "sg:city":"Cornol",
    "sg:orig_category":"Instandhaltung U Reparatur von Automobilen",
    "sg:phone":"+41 32 462 29 22",
    "sg:postcode":"2952",
    "sg:province":"Jura",
    "wof:name":"Andr\u00e9 H\u00eache Garage Des Rangiers",
    "wof:placetype":"venue"
},
  "geometry": {"coordinates":[7.1584382057,47.4088058472],"type":"Point"}
}