{
  "type": "Feature",
  "properties": {
    "iso:country":"CH",
    "sg:address":"Ottoplatz 19 7000 Chur. Postfach",
    "sg:city":"Chur",
    "sg:orig_category":"Advokaturb\u00fcros Notariate",
    "sg:phone":"+41 81 253 53 54",
    "sg:postcode":"7001",
    "sg:province":"Graubunden",
    "wof:name":"Reto Mengiardi Advokatur- & Notariatsb\u00fcro",
    "wof:placetype":"venue"
},
  "geometry": {"coordinates":[9.531838,46.853642],"type":"Point"}
}