{
  "type": "Feature",
  "properties": {
    "iso:country":"CH",
    "sg:address":"Oberdorf 7",
    "sg:city":"Rafz",
    "sg:orig_category":"Fachdetailhandel in Verkaufsr\u00e4umen",
    "sg:phone":"+41 18690926",
    "sg:postcode":"8197",
    "sg:province":"Z\u00fcrich",
    "wof:name":"Plantissimo Nieuwesteeg",
    "wof:placetype":"venue"
},
  "geometry": {"coordinates":[8.5358276367,47.6147956848],"type":"Point"}
}