{
  "type": "Feature",
  "properties": {
    "iso:country":"CH",
    "sg:address":"Dammweg 8",
    "sg:city":"Gelterkinden",
    "sg:orig_category":"Sportvereine Velo Rad-& Motorfahrer-Bund SRB",
    "sg:phone":"+41 61 981 42 57",
    "sg:postcode":"4460",
    "sg:province":"Basel-Landschaft",
    "wof:name":"Velo-moto-club Liestal",
    "wof:placetype":"venue"
},
  "geometry": {"coordinates":[7.8616948128,47.4625473022],"type":"Point"}
}