{
  "type": "Feature",
  "properties": {
    "iso:country":"CH",
    "sg:address":"Route De St-julien 145",
    "sg:city":"Plan-les-ouates",
    "sg:orig_category":"Darlehenskassen U Raiffeisenbanken",
    "sg:phone":"+41 22 794 91 04",
    "sg:postcode":"1228",
    "sg:province":"Gen\u00e8ve",
    "wof:name":"Banque Raiffeisen Des Communes R\u00e9unies",
    "wof:placetype":"venue"
},
  "geometry": {"coordinates":[6.117378,46.168034],"type":"Point"}
}