{
  "type": "Feature",
  "properties": {
    "iso:country":"CH",
    "sg:address":"R\u00e4mistrasse 101 8006 Z\u00fcrich. Postfach",
    "sg:city":"Z\u00fcrich",
    "sg:orig_category":"Interessenvertretungen",
    "sg:phone":"+41 16324035",
    "sg:postcode":"8006",
    "sg:province":"Z\u00fcrich",
    "wof:name":"Frisch Max-stiftung",
    "wof:placetype":"venue"
},
  "geometry": {"coordinates":[8.5487222672,47.3760719299],"type":"Point"}
}