{
  "type": "Feature",
  "properties": {
    "addr:full":"Hauptstrasse 41 Sch\u00f6nengrund Appenzell Ausserrhoden 9105",
    "addr:housenumber":"41",
    "addr:postcode":"9105",
    "addr:street":"Hauptstrasse;Schoenengrund Appenzell Ausserrhoden",
    "iso:country":"CH",
    "sg:address":"Hauptstrasse 41",
    "sg:city":"Sch\u00f6nengrund",
    "sg:orig_category":"Detailhandel mit Brot, Back U S\u00fcsswaren",
    "sg:phone":"+41 71 361 15 66",
    "sg:postcode":"9105",
    "sg:province":"Appenzell Ausserrhoden",
    "wof:name":"Werner Kuhn B\u00e4ckerei-konditorei",
    "wof:placetype":"venue"
},
  "geometry": {"coordinates":[9.224681,47.328339],"type":"Point"}
}