{
  "type": "Feature",
  "properties": {
    "iso:country":"CH",
    "sg:address":"Fuchsweg 10",
    "sg:city":"Bellach",
    "sg:orig_category":"Sportvereine Ballsport Volleyball",
    "sg:postcode":"4512",
    "sg:province":"Solothurn",
    "wof:name":"Volleyball-club Kanti Soloth.",
    "wof:placetype":"venue"
},
  "geometry": {"coordinates":[7.4982447624,47.2148323059],"type":"Point"}
}