{
  "type": "Feature",
  "properties": {
    "iso:country":"CH",
    "sg:address":"Weriweg 29 3900 Brig. Postfach",
    "sg:city":"Glis",
    "sg:orig_category":"Reiseb\u00fcros U Reiseveranstalter",
    "sg:postcode":"3902",
    "sg:province":"Valais",
    "wof:name":"Marketing Und Reisen, Moser Beat",
    "wof:placetype":"venue"
},
  "geometry": {"coordinates":[7.9909348488,46.3132133484],"type":"Point"}
}