{
  "type": "Feature",
  "properties": {
    "iso:country":"CH",
    "sg:address":"Hofstrasse 13a",
    "sg:city":"Weesen",
    "sg:orig_category":"Unternehmensberatung",
    "sg:phone":"+41 55 615 31 20",
    "sg:postcode":"8872",
    "sg:province":"St. Gallen",
    "wof:name":"Win Consulting Network, Ochsner Erwin",
    "wof:placetype":"venue"
},
  "geometry": {"coordinates":[9.1023597717,47.1347351074],"type":"Point"}
}