{
  "type": "Feature",
  "properties": {
    "iso:country":"CH",
    "sg:address":"Talackerstrasse 34",
    "sg:city":"Frauenfeld",
    "sg:orig_category":"Architektur U Ingenieurb\u00fcros",
    "sg:postcode":"8500",
    "sg:province":"Thurgau",
    "wof:name":"Kuster + Hager Architekturb\u00fcro Ag",
    "wof:placetype":"venue"
},
  "geometry": {"coordinates":[8.78544,47.201256],"type":"Point"}
}