{
  "type": "Feature",
  "properties": {
    "iso:country":"CH",
    "sg:address":"Place Des Halles 3",
    "sg:city":"Lutry",
    "sg:orig_category":"Detailhandel mit Blumen U Pflanzen",
    "sg:phone":"+41 21 791 14 65",
    "sg:postcode":"1095",
    "sg:province":"Vaud",
    "wof:name":"Iris Aebi Iris Fleurs",
    "wof:placetype":"venue"
},
  "geometry": {"coordinates":[6.684853,46.502121],"type":"Point"}
}