{
  "type": "Feature",
  "properties": {
    "iso:country":"CH",
    "sg:address":"L\u00f6wenstrasse 24",
    "sg:city":"Rorschach",
    "sg:classifiers":[
        {
            "category":"Restaurant",
            "type":"Food & Drink"
        }
    ],
    "sg:phone":"+41 71 841 11 27",
    "sg:postcode":"9400",
    "sg:province":"St. Gallen",
    "wof:name":"Restaurant Habsburg",
    "wof:placetype":"venue"
},
  "geometry": {"coordinates":[9.4873542786,47.4768104553],"type":"Point"}
}