{
  "type": "Feature",
  "properties": {
    "iso:country":"CH",
    "sg:address":"Elvezia Corso 14",
    "sg:city":"Lugano",
    "sg:orig_category":"Unclassifiable Establishments",
    "sg:postcode":"6900",
    "sg:province":"Ticino",
    "wof:name":"Vhcm Ventura Human Capital Management Di Ketty Ventura",
    "wof:placetype":"venue"
},
  "geometry": {"coordinates":[8.9558019638,46.0073852539],"type":"Point"}
}