{
  "type": "Feature",
  "properties": {
    "iso:country":"CH",
    "sg:address":"Schmiedengasse 17",
    "sg:city":"Solothurn",
    "sg:orig_category":"Detailhandel mit Schuhen",
    "sg:phone":"+41 32 621 44 21",
    "sg:postcode":"4500",
    "sg:province":"Solothurn",
    "wof:name":"Chaussures Yvonne Leibundgut & Cie",
    "wof:placetype":"venue"
},
  "geometry": {"coordinates":[7.5350871086,47.2075576782],"type":"Point"}
}