{
  "type": "Feature",
  "properties": {
    "iso:country":"CH",
    "sg:address":"Aarauerstrasse 2",
    "sg:city":"Lenzburg",
    "sg:orig_category":"Herstellung von K\u00fcchenm\u00f6beln",
    "sg:postcode":"5600",
    "sg:province":"Aargau",
    "wof:name":"Meier & Mathis Schreinerei Gmbh",
    "wof:placetype":"venue"
},
  "geometry": {"coordinates":[8.1730308533,47.3868522644],"type":"Point"}
}