{
  "type": "Feature",
  "properties": {
    "iso:country":"CH",
    "sg:address":"7535",
    "sg:city":"Valchava",
    "sg:orig_category":"Sportvereine Sch\u00fctzen",
    "sg:postcode":"7535",
    "sg:province":"Graubunden",
    "wof:name":"Societ\u00e0 Da Tregants",
    "wof:placetype":"venue"
},
  "geometry": {"coordinates":[10.423620224,46.6011390686],"type":"Point"}
}