{
  "type": "Feature",
  "properties": {
    "iso:country":"CH",
    "sg:address":"Sch\u00fctzengraben 9",
    "sg:city":"Basel",
    "sg:orig_category":"Vorschulen, Kinderg\u00e4rten",
    "sg:phone":"+41 61 261 28 87",
    "sg:postcode":"4051",
    "sg:province":"Basel-Stadt",
    "wof:name":"Basler Bastelschule Kindergarten",
    "wof:placetype":"venue"
},
  "geometry": {"coordinates":[7.5827980042,47.5556602478],"type":"Point"}
}