{
  "type": "Feature",
  "properties": {
    "iso:country":"CH",
    "sg:address":"Bahnhofstrasse 2",
    "sg:city":"Naters",
    "sg:orig_category":"RESTAURANTS: TEA-ROOMS",
    "sg:phone":"+41 27 923 82 95",
    "sg:postcode":"3904",
    "sg:province":"Valais",
    "wof:name":"Hotel-restaurant Du Rh\u00f4ne, Schmid Ren\u00e9",
    "wof:placetype":"venue"
},
  "geometry": {"coordinates":[7.9864478111,46.3211593628],"type":"Point"}
}