{
  "type": "Feature",
  "properties": {
    "iso:country":"CH",
    "sg:address":"8750",
    "sg:city":"Glarus",
    "sg:orig_category":"Sportvereine Turnen Vereine Damen",
    "sg:phone":"+41 55 640 91 38",
    "sg:postcode":"8750",
    "sg:province":"Glarus",
    "wof:name":"Frauenturnclub Glarus",
    "wof:placetype":"venue"
},
  "geometry": {"coordinates":[9.0680904388,47.0399703979],"type":"Point"}
}