{
  "type": "Feature",
  "properties": {
    "iso:country":"CH",
    "sg:address":"Hochwangstrasse",
    "sg:city":"Zizers",
    "sg:orig_category":"Erwachsenenbildung U Unterricht",
    "sg:postcode":"7205",
    "sg:province":"Graubunden",
    "wof:name":"Institut F\u00fcr Pe + Oe, Esther Carisch Schuhmacher",
    "wof:placetype":"venue"
},
  "geometry": {"coordinates":[9.5692186356,46.9380302429],"type":"Point"}
}