{
  "type": "Feature",
  "properties": {
    "iso:country":"CH",
    "sg:address":"Grand'rue 90",
    "sg:city":"Rolle",
    "sg:orig_category":"Handel mit Motorr\u00e4dern, Teilen U Zubeh\u00f6r Instandhaltung U Reparatur von Motorr\u00e4dern",
    "sg:phone":"+41 61 711 00 51",
    "sg:postcode":"1180",
    "sg:province":"Vaud",
    "wof:name":"Rollerzentrale Amstutz Daniel",
    "wof:placetype":"venue"
},
  "geometry": {"coordinates":[7.5994501114,47.4885902405],"type":"Point"}
}