{
  "type": "Feature",
  "properties": {
    "iso:country":"CH",
    "sg:address":"Schlossplatz 23",
    "sg:city":"Aarau",
    "sg:orig_category":"Museen",
    "sg:phone":"+41 56 631 17 50",
    "sg:postcode":"5000",
    "sg:province":"Aargau",
    "wof:name":"Stadtmuseum",
    "wof:placetype":"venue"
},
  "geometry": {"coordinates":[8.3394117355,47.3508720398],"type":"Point"}
}