{
  "type": "Feature",
  "properties": {
    "iso:country":"CH",
    "sg:address":"Eaux-vives Rue Des 61 1207 Gen\u00e8ve. Postfach",
    "sg:city":"Gen\u00e8ve",
    "sg:orig_category":"Fachdetailhandel in Verkaufsr\u00e4umen",
    "sg:postcode":"1207",
    "sg:province":"Gen\u00e8ve",
    "wof:name":"Rieben Zofia",
    "wof:placetype":"venue"
},
  "geometry": {"coordinates":[6.1599121094,46.2050971985],"type":"Point"}
}