{
  "type": "Feature",
  "properties": {
    "iso:country":"CH",
    "sg:address":"Rue Gambetta 25",
    "sg:city":"Clarens",
    "sg:orig_category":"Detailhandel mit Damenbekleidung",
    "sg:phone":"+41 21 964 20 37",
    "sg:postcode":"1815",
    "sg:province":"Vaud",
    "wof:name":"Laura Truscello Couture Laura",
    "wof:placetype":"venue"
},
  "geometry": {"coordinates":[6.896241,46.44202],"type":"Point"}
}