{
  "type": "Feature",
  "properties": {
    "iso:country":"CH",
    "sg:address":"M\u00fclhauserstrasse 17",
    "sg:city":"Basel",
    "sg:orig_category":"Grosshandel mit Getr\u00e4nken",
    "sg:postcode":"4056",
    "sg:province":"Basel-Stadt",
    "wof:name":"Mangold Weine",
    "wof:placetype":"venue"
},
  "geometry": {"coordinates":[7.5819811821,47.570148468],"type":"Point"}
}