{
  "type": "Feature",
  "properties": {
    "iso:country":"CH",
    "sg:address":"Weissenb\u00fchlweg 6",
    "sg:city":"Bern",
    "sg:orig_category":"Architektur U Ingenieurb\u00fcros Architekturb\u00fcros",
    "sg:phone":"+41 31 372 40 48",
    "sg:postcode":"3007",
    "sg:province":"Bern",
    "wof:name":"Architektur, Design- & Planungswerkstatt Schihin Karl & Partner Ag, Bern",
    "wof:placetype":"venue"
},
  "geometry": {"coordinates":[7.432824,46.93792],"type":"Point"}
}