{
  "type": "Feature",
  "properties": {
    "iso:country":"CH",
    "sg:address":"Route Torny-le-petit",
    "sg:city":"Middes",
    "sg:orig_category":"Wirtschaftsverb\u00e4nde Industrie, Handel and Gewerbe",
    "sg:phone":"+41 26 658 14 41",
    "sg:postcode":"1749",
    "sg:province":"Fribourg",
    "wof:name":"Assoc.suisse Du N\u00e9goce De L'ammeublement,m.walter Blank",
    "wof:placetype":"venue"
},
  "geometry": {"coordinates":[6.9493360519,46.7676544189],"type":"Point"}
}