{
  "type": "Feature",
  "properties": {
    "iso:country":"CH",
    "sg:address":"Strehlgasse 8 8353 Elgg. Postfach",
    "sg:city":"Elgg",
    "sg:orig_category":"Interessenvertretungen",
    "sg:postcode":"8353",
    "sg:province":"Z\u00fcrich",
    "wof:name":"Genossenschaft Wohnen Arbeit Und Kultur Elgg Und Umgebung",
    "wof:placetype":"venue"
},
  "geometry": {"coordinates":[8.8661346436,47.4900436401],"type":"Point"}
}