{
  "type": "Feature",
  "properties": {
    "iso:country":"CH",
    "sg:address":"Thunstrasse 24",
    "sg:city":"Bern",
    "sg:orig_category":"Finanzierungsinstitutionen",
    "sg:phone":"+41 31 952 62 61",
    "sg:postcode":"3005",
    "sg:province":"Bern",
    "wof:name":"Elton Energy Ag",
    "wof:placetype":"venue"
},
  "geometry": {"coordinates":[7.4541859627,46.9419364929],"type":"Point"}
}