{
  "type": "Feature",
  "properties": {
    "iso:country":"CH",
    "sg:address":"Schwendi 8494 Bauma. Postfach",
    "sg:city":"Bauma",
    "sg:orig_category":"Betrieb von Taxis",
    "sg:phone":"+41 52 386 31 30",
    "sg:postcode":"8494",
    "sg:province":"Z\u00fcrich",
    "wof:name":"Leutenegger Peter Gmbh Personen-transporte, Waschanlagen, Tankstellen. Liegenschaften; Verwaltung",
    "wof:placetype":"venue"
},
  "geometry": {"coordinates":[8.876505,47.367821],"type":"Point"}
}