{
  "type": "Feature",
  "properties": {
    "iso:country":"CH",
    "sg:address":"Poststrasse 20 6300 Zug. Postfach",
    "sg:city":"Zug",
    "sg:orig_category":"Werbung",
    "sg:postcode":"6300",
    "sg:province":"Zug",
    "wof:name":"Mw Design Gmbh",
    "wof:placetype":"venue"
},
  "geometry": {"coordinates":[8.5168733597,47.1705207825],"type":"Point"}
}