{
  "type": "Feature",
  "properties": {
    "iso:country":"CH",
    "sg:address":"Gempenstrasse 46",
    "sg:city":"Basel",
    "sg:orig_category":"Unternehmensberatung",
    "sg:postcode":"4053",
    "sg:province":"Basel-Stadt",
    "wof:name":"Questor Systems Gmbh",
    "wof:placetype":"venue"
},
  "geometry": {"coordinates":[7.5866260529,47.5437583923],"type":"Point"}
}