{
  "type": "Feature",
  "properties": {
    "iso:country":"CH",
    "sg:address":"Via San Materno",
    "sg:city":"Ascona",
    "sg:orig_category":"Detailhandel mit Brot, Back U S\u00fcsswaren",
    "sg:postcode":"6612",
    "sg:province":"Ticino",
    "wof:name":"Sieber Ernst",
    "wof:placetype":"venue"
},
  "geometry": {"coordinates":[8.76894,46.161991],"type":"Point"}
}