{
  "type": "Feature",
  "properties": {
    "iso:country":"CH",
    "sg:address":"Weissbadstrasse 14",
    "sg:city":"Schwende",
    "sg:orig_category":"Non-Classified Establishments",
    "sg:phone":"+41 41 632 53 53",
    "sg:postcode":"9057",
    "sg:province":"Appenzell Innerhoden",
    "wof:name":"Swiss\u00f4tel Holding Ag",
    "wof:placetype":"venue"
},
  "geometry": {"coordinates":[8.3105077744,46.9956893921],"type":"Point"}
}