{
  "type": "Feature",
  "properties": {
    "iso:country":"CH",
    "sg:address":"Route De Ch\u00e2tel 43",
    "sg:city":"Bex",
    "sg:orig_category":"Detailhandel mit Brot, Back U S\u00fcsswaren",
    "sg:phone":"+41 24 463 13 07",
    "sg:postcode":"1880",
    "sg:province":"Vaud",
    "wof:name":"Christian Schmid Boulangerie & P\u00e2tisserie",
    "wof:placetype":"venue"
},
  "geometry": {"coordinates":[7.024115,46.238754],"type":"Point"}
}