{
  "type": "Feature",
  "properties": {
    "iso:country":"CH",
    "sg:address":"Chemin Le Tr\u00e9si 7",
    "sg:city":"Pr\u00e9verenges",
    "sg:orig_category":"Instandhaltung U Reparatur von Automobilen",
    "sg:phone":"+41 21 803 04 69",
    "sg:postcode":"1028",
    "sg:province":"Vaud",
    "wof:name":"Carrosserie Le Tr\u00e8fle Sensi A.",
    "wof:placetype":"venue"
},
  "geometry": {"coordinates":[6.5295901299,46.5226173401],"type":"Point"}
}