{
  "type": "Feature",
  "properties": {
    "iso:country":"CH",
    "sg:address":"Route De St-cergue 305",
    "sg:city":"Nyon",
    "sg:orig_category":"Grosshandel mit B\u00fcromaschinen Grosshandel mit Datenverarbeitungsger\u00e4ten",
    "sg:phone":"+41 55 450 20 60",
    "sg:postcode":"1260",
    "sg:province":"Vaud",
    "wof:name":"Procom Technology Ag",
    "wof:placetype":"venue"
},
  "geometry": {"coordinates":[8.7781352997,47.2013778687],"type":"Point"}
}