{
  "type": "Feature",
  "properties": {
    "iso:country":"CH",
    "sg:address":"Bucheggstrasse 40 8000 Z\u00fcrich. Postfach",
    "sg:city":"Z\u00fcrich",
    "sg:orig_category":"RESTAURANTS: TEA-ROOMS",
    "sg:postcode":"8037",
    "sg:province":"Z\u00fcrich",
    "wof:name":"Keel-sieber Alois",
    "wof:placetype":"venue"
},
  "geometry": {"coordinates":[9.5506801605,47.3855934143],"type":"Point"}
}