{
  "type": "Feature",
  "properties": {
    "iso:country":"CH",
    "sg:address":"Moosstrasse 11",
    "sg:city":"Kernenried",
    "sg:orig_category":"Grosshandel mit Getr\u00e4nken",
    "sg:postcode":"3309",
    "sg:province":"Bern",
    "wof:name":"Wy Vom Moosch\u00e4uer, Sollberger Peter",
    "wof:placetype":"venue"
},
  "geometry": {"coordinates":[7.550219059,47.0780944824],"type":"Point"}
}