{
  "type": "Feature",
  "properties": {
    "iso:country":"CH",
    "sg:address":"Rue De La Combettaz",
    "sg:city":"Chandolin-savi\u00e8se",
    "sg:orig_category":"Grosshandel mit Wein U Spirituosen",
    "sg:phone":"+41 27 744 32 72",
    "sg:postcode":"1965",
    "sg:province":"Valais",
    "wof:name":"Fran\u00e7oise Bruchez",
    "wof:placetype":"venue"
},
  "geometry": {"coordinates":[7.3673171997,46.2633361816],"type":"Point"}
}