{
  "type": "Feature",
  "properties": {
    "iso:country":"CH",
    "sg:address":"Route De Babolles",
    "sg:city":"Semsales",
    "sg:orig_category":"Maurerarbeiten Sonstiger spezialisierter Hoch U Tiefbau",
    "sg:phone":"+41 26 918 55 22",
    "sg:postcode":"1623",
    "sg:province":"Fribourg",
    "wof:name":"Entreprise De Ma\u00e7onnerie Savary Et Fils Sa",
    "wof:placetype":"venue"
},
  "geometry": {"coordinates":[6.9310269356,46.5761756897],"type":"Point"}
}