{
  "type": "Feature",
  "properties": {
    "iso:country":"CH",
    "sg:address":"Planche Sup\u00e9rieure 16 1700 Fribourg Case Postale 15",
    "sg:city":"Fribourg",
    "sg:orig_category":"WIRTSCHAFTSVERB\u00c4NDE WIRTSCHAFTS-& HANDELSF\u00d6RDER",
    "sg:phone":"+41 26 322 26 55",
    "sg:postcode":"1704",
    "sg:province":"Fribourg",
    "wof:name":"Swiss Label St\u00e9 Promotion Produits & Services Suisses",
    "wof:placetype":"venue"
},
  "geometry": {"coordinates":[7.1625490189,46.8028755188],"type":"Point"}
}