{
  "type": "Feature",
  "properties": {
    "iso:country":"CH",
    "sg:address":"3792 Saanen. Postfach",
    "sg:city":"Gstaad",
    "sg:orig_category":"Detailhandel an Verkaufsst\u00e4nden U auf M\u00e4rkten",
    "sg:postcode":"3780",
    "sg:province":"Bern",
    "wof:name":"Frau Ruth Ryf",
    "wof:placetype":"venue"
},
  "geometry": {"coordinates":[7.23614,46.463219],"type":"Point"}
}