{
  "type": "Feature",
  "properties": {
    "iso:country":"CH",
    "sg:address":"Chemin Cr\u00eat",
    "sg:city":"St-george",
    "sg:orig_category":"Architekturb\u00fcros",
    "sg:phone":"+41 32 968 22 84",
    "sg:postcode":"1261",
    "sg:province":"Vaud",
    "wof:name":"St\u00e9phane Horni Bureau D'architecture",
    "wof:placetype":"venue"
},
  "geometry": {"coordinates":[6.818907,47.108051],"type":"Point"}
}