{
  "type": "Feature",
  "properties": {
    "iso:country":"CH",
    "sg:address":"Rue De L'eglise 20",
    "sg:city":"Chamoson",
    "sg:classifiers":[
        {
            "category":"Restaurant",
            "type":"Food & Drink"
        }
    ],
    "sg:phone":"+41 27 306 25 04",
    "sg:postcode":"1955",
    "sg:province":"Valais",
    "wof:name":"Restaurant Pinte",
    "wof:placetype":"venue"
},
  "geometry": {"coordinates":[7.2374329567,46.1927375793],"type":"Point"}
}