{
  "type": "Feature",
  "properties": {
    "iso:country":"CH",
    "sg:address":"Aneter Strasse 7",
    "sg:city":"Bettwiesen",
    "sg:orig_category":"Bauschreinerei Herstellung von M\u00f6beln verschiedener Art",
    "sg:phone":"+41 71 911 09 80",
    "sg:postcode":"9553",
    "sg:province":"Thurgau",
    "wof:name":"Albert Bommer Bau-& M\u00f6belschreinerei",
    "wof:placetype":"venue"
},
  "geometry": {"coordinates":[9.022343,47.495388],"type":"Point"}
}