{
  "type": "Feature",
  "properties": {
    "iso:country":"CH",
    "sg:address":"Dreik\u00f6nigstrasse 31a 8002 Z\u00fcrich. Postfach",
    "sg:city":"Z\u00fcrich",
    "sg:orig_category":"Erwachsenenbildung U Unterricht",
    "sg:postcode":"8001",
    "sg:province":"Z\u00fcrich",
    "wof:name":"Transm Erny Rolf Entwicklung, Coaching Von F\u00fchrungskr\u00e4ften U. Unternehmen; Unterst\u00fctzung. Interims-management Usw",
    "wof:placetype":"venue"
},
  "geometry": {"coordinates":[8.5351734161,47.3664855957],"type":"Point"}
}