{
  "type": "Feature",
  "properties": {
    "iso:country":"CH",
    "sg:address":"Rue De Flandres 2",
    "sg:city":"Neuch\u00e2tel",
    "sg:orig_category":"Detailhandel mit Schuhen Detailhandel mit Schuhen U Lederwaren",
    "sg:phone":"+41 21 801 98 84",
    "sg:postcode":"2000",
    "sg:province":"Neuch\u00e2tel",
    "wof:name":"Boutique Via Veneto M.chappuis Chaussures Petite Mode",
    "wof:placetype":"venue"
},
  "geometry": {"coordinates":[6.4956989288,46.5090408325],"type":"Point"}
}