{
  "type": "Feature",
  "properties": {
    "addr:full":"Via Lugano 14 Bellinzona Ticino 6500",
    "addr:housenumber":"14",
    "addr:postcode":"6500",
    "addr:street":"Via Lugano",
    "iso:country":"CH",
    "sg:address":"Via Lugano 14",
    "sg:city":"Bellinzona",
    "sg:orig_category":"Architekturb\u00fcros",
    "sg:phone":"+41 91 826 26 01",
    "sg:postcode":"6500",
    "sg:province":"Ticino",
    "wof:name":"Giovanni Battista Balestra Studio D'architettura",
    "wof:placetype":"venue"
},
  "geometry": {"coordinates":[9.020811,46.187229],"type":"Point"}
}