{
  "type": "Feature",
  "properties": {
    "iso:country":"CH",
    "sg:address":"Kleintwann 17",
    "sg:city":"Twann",
    "sg:orig_category":"Datenverarbeitungsdienste Softwareentwicklung U beratung",
    "sg:phone":"+41 32 315 26 18",
    "sg:postcode":"2513",
    "sg:province":"Bern",
    "wof:name":"Pace Informatik Gmbh",
    "wof:placetype":"venue"
},
  "geometry": {"coordinates":[7.15632,47.09433],"type":"Point"}
}