{
  "type": "Feature",
  "properties": {
    "iso:country":"CH",
    "sg:address":"A La Gare 86",
    "sg:city":"Ch\u00e9nens",
    "sg:classifiers":[
        {
            "category":"Restaurant",
            "type":"Food & Drink"
        }
    ],
    "sg:phone":"+41 79 287 82 31",
    "sg:postcode":"1744",
    "sg:province":"Fribourg",
    "wof:name":"Restaurant Gare",
    "wof:placetype":"venue"
},
  "geometry": {"coordinates":[7.0003418922,46.7490005493],"type":"Point"}
}