{
  "type": "Feature",
  "properties": {
    "iso:country":"CH",
    "sg:address":"Rue De Fin De Forel 11",
    "sg:city":"Ligni\u00e8res",
    "sg:orig_category":"Maurerarbeiten Unterhalt U Reparatur im Hoch U Tiefbau",
    "sg:phone":"+41 79 624 76 74",
    "sg:postcode":"2523",
    "sg:province":"Neuch\u00e2tel",
    "wof:name":"Decobat S\u00e0rl Travaux De Construction",
    "wof:placetype":"venue"
},
  "geometry": {"coordinates":[6.1339879036,46.1868667603],"type":"Point"}
}