{
  "type": "Feature",
  "properties": {
    "iso:country":"CH",
    "sg:address":"Hinterdorfstrasse 72",
    "sg:city":"Mollis",
    "sg:orig_category":"Maurerarbeiten",
    "sg:phone":"+41 79 350 54 47",
    "sg:postcode":"8753",
    "sg:province":"Glarus",
    "wof:name":"Beat Von Rotz Kundenmaurerei",
    "wof:placetype":"venue"
},
  "geometry": {"coordinates":[9.0723581314,47.1014518738],"type":"Point"}
}