{
  "type": "Feature",
  "properties": {
    "iso:country":"CH",
    "sg:address":"Lotzwilstrasse 70",
    "sg:city":"Langenthal",
    "sg:orig_category":"Instandhaltung U Reparatur von Automobilen",
    "sg:phone":"+41 79 407 04 91",
    "sg:postcode":"4900",
    "sg:province":"Bern",
    "wof:name":"B\u00fcrgin Urs",
    "wof:placetype":"venue"
},
  "geometry": {"coordinates":[7.7842950821,47.2017707825],"type":"Point"}
}