{
  "type": "Feature",
  "properties": {
    "iso:country":"CH",
    "sg:address":"Br\u00eat Chemin Du 11",
    "sg:city":"Orbe",
    "sg:orig_category":"Vermietung U Verpachtung von eigenen Immobilien",
    "sg:phone":"+41 24 441 81 18",
    "sg:postcode":"1350",
    "sg:province":"Vaud",
    "wof:name":"Les R\u00e9sidences Emma Sa",
    "wof:placetype":"venue"
},
  "geometry": {"coordinates":[6.5309619904,46.7247772217],"type":"Point"}
}