{
  "type": "Feature",
  "properties": {
    "iso:country":"CH",
    "sg:address":"Stradun",
    "sg:city":"Scuol",
    "sg:classifiers":[
        {
            "category":"Banks & Credit Unions",
            "subcategory":"Bank",
            "type":"Services"
        }
    ],
    "sg:phone":"+41 81 943 11 81",
    "sg:postcode":"7550",
    "sg:province":"Graubunden",
    "wof:name":"Banca Raiffeisen Trun-schlans",
    "wof:placetype":"venue"
},
  "geometry": {"coordinates":[8.990615,46.743107],"type":"Point"}
}