{
  "type": "Feature",
  "properties": {
    "iso:country":"CH",
    "sg:address":"R\u00fctistrasse 1 8633 Wolfhausen. Postfach",
    "sg:city":"Wolfhausen",
    "sg:orig_category":"Autogaragen",
    "sg:phone":"+41 55 243 14 55",
    "sg:postcode":"8633",
    "sg:province":"Z\u00fcrich",
    "wof:name":"Auto-b\u00fchler Garage",
    "wof:placetype":"venue"
},
  "geometry": {"coordinates":[8.808843,47.258457],"type":"Point"}
}