{
  "type": "Feature",
  "properties": {
    "iso:country":"CH",
    "sg:address":"Rue De La Dixence 17",
    "sg:city":"Sion",
    "sg:orig_category":"Herstellung von Anstrichmitteln, Druckfarben U Kitten Sonstiger Detailhandel mit Metallwaren, Anstri",
    "sg:phone":"+41 27 322 42 24",
    "sg:postcode":"1950",
    "sg:province":"Valais",
    "wof:name":"Ev\u00e9quoz Peinture Sa",
    "wof:placetype":"venue"
},
  "geometry": {"coordinates":[7.363366127,46.2308769226],"type":"Point"}
}