{
  "type": "Feature",
  "properties": {
    "iso:country":"CH",
    "sg:address":"Sarmenstorferstrasse 5",
    "sg:city":"Fahrwangen",
    "sg:orig_category":"Detailhandel mit Sportartikeln Hobel U Holzimpr\u00e4gnierwerke",
    "sg:phone":"+41 56 667 13 69",
    "sg:postcode":"5615",
    "sg:province":"Aargau",
    "wof:name":"Walter Rodel",
    "wof:placetype":"venue"
},
  "geometry": {"coordinates":[8.2428178787,47.2956161499],"type":"Point"}
}