{
  "type": "Feature",
  "properties": {
    "iso:country":"CH",
    "sg:address":"Lehenmattstrasse 344 4052 Basel. Postfach",
    "sg:city":"Basel",
    "sg:orig_category":"Detailhandel mit B\u00fcromaschinen U einrichtungen",
    "sg:phone":"+41 79 422 68 93",
    "sg:postcode":"4028",
    "wof:name":"Siegfried Streit B\u00fcroeinrichtungen; Handel",
    "wof:placetype":"venue"
},
  "geometry": {"coordinates":[7.620002,47.543896],"type":"Point"}
}