{
  "type": "Feature",
  "properties": {
    "iso:country":"CH",
    "sg:address":"Buchenstrasse 6 4127 Birsfelden. Postfach 728",
    "sg:city":"Birsfelden",
    "sg:orig_category":"Baugewerbe Herstellung von Metallkonstruktionen",
    "sg:phone":"+41 61 313 18 48",
    "sg:postcode":"4127",
    "sg:province":"Basel-Landschaft",
    "wof:name":"T. Stetter, Montage-unternehmen",
    "wof:placetype":"venue"
},
  "geometry": {"coordinates":[7.626892,47.549511],"type":"Point"}
}