{
  "type": "Feature",
  "properties": {
    "iso:country":"CH",
    "sg:address":"In Der Appenhalten 6 8706 Meilen. Postfach 381",
    "sg:city":"Meilen",
    "sg:orig_category":"Werbeagenturen Werbegrafikateliers",
    "sg:phone":"+41 19232133",
    "sg:postcode":"8706",
    "sg:province":"Z\u00fcrich",
    "wof:name":"Rup R\u00e9e Werbeagentur",
    "wof:placetype":"venue"
},
  "geometry": {"coordinates":[8.6605854034,47.2689628601],"type":"Point"}
}