{
  "type": "Feature",
  "properties": {
    "iso:country":"CH",
    "sg:address":"General Wille-strasse 8",
    "sg:city":"Z\u00fcrich",
    "sg:orig_category":"Fachdetailhandel in Verkaufsr\u00e4umen Kunsthandel",
    "sg:phone":"+41 22014393",
    "sg:postcode":"8002",
    "sg:province":"Z\u00fcrich",
    "wof:name":"Acf Art Collector's Fund Ltd",
    "wof:placetype":"venue"
},
  "geometry": {"coordinates":[8.533911705,47.3635520935],"type":"Point"}
}