{
  "type": "Feature",
  "properties": {
    "iso:country":"CH",
    "sg:address":"5704 Egliswil. Postfach 7",
    "sg:city":"Egliswil",
    "sg:orig_category":"Technische, physikalische U chemische Untersuchung",
    "sg:phone":"+41 62 775 00 26",
    "sg:postcode":"5704",
    "sg:province":"Aargau",
    "wof:name":"Terre Ag",
    "wof:placetype":"venue"
},
  "geometry": {"coordinates":[8.1889467239,47.3499946594],"type":"Point"}
}