{
  "type": "Feature",
  "properties": {
    "iso:country":"CH",
    "sg:address":"1627",
    "sg:city":"Vaulruz",
    "sg:orig_category":"Wasserversorgung",
    "sg:postcode":"1627",
    "sg:province":"Fribourg",
    "wof:name":"Service Des Eaux De La Commune De Vaulruz",
    "wof:placetype":"venue"
},
  "geometry": {"coordinates":[6.9905180931,46.6209640503],"type":"Point"}
}