{
  "type": "Feature",
  "properties": {
    "iso:country":"CH",
    "sg:address":"1854",
    "sg:city":"Leysin",
    "sg:orig_category":"Campingpl\u00e4tze Detailhandel mit Zeitungen U Zeitschriften Kioske",
    "sg:phone":"+41 33 336 40 67",
    "sg:postcode":"1854",
    "sg:province":"Vaud",
    "wof:name":"Camping Tcs Gwatt",
    "wof:placetype":"venue"
},
  "geometry": {"coordinates":[7.62784,46.727444],"type":"Point"}
}