{
  "type": "Feature",
  "properties": {
    "iso:country":"CH",
    "sg:address":"Kantonsstrasse",
    "sg:city":"Eyholz",
    "sg:orig_category":"Detailhandel mit Fleisch U Fleischwaren",
    "sg:phone":"+41 27 946 40 68",
    "sg:postcode":"3931",
    "sg:province":"Valais",
    "wof:name":"Metzgerei Souvel Sa",
    "wof:placetype":"venue"
},
  "geometry": {"coordinates":[7.9069499969,46.2946052551],"type":"Point"}
}