{
  "type": "Feature",
  "properties": {
    "iso:country":"CH",
    "sg:address":"H\u00fcttenackerstrasse",
    "sg:city":"B\u00e4retswil",
    "sg:orig_category":"Handels-H\u00e4user U Gesellschaften",
    "sg:phone":"+41 19392803",
    "sg:postcode":"8344",
    "sg:province":"Z\u00fcrich",
    "wof:name":"Guyer R.",
    "wof:placetype":"venue"
},
  "geometry": {"coordinates":[8.8592653275,47.3370513916],"type":"Point"}
}