{
  "type": "Feature",
  "properties": {
    "iso:country":"CH",
    "sg:address":"Le Pressoir 1813 St-saphorin-lavaux. Postfach",
    "sg:city":"St-saphorin-lavaux",
    "sg:orig_category":"Finanzierungsinstitutionen",
    "sg:postcode":"1813",
    "wof:name":"Cogica, G\u00e9rard Grangier",
    "wof:placetype":"venue"
},
  "geometry": {"coordinates":[1.1983300447,47.9225616455],"type":"Point"}
}