{
  "type": "Feature",
  "properties": {
    "iso:country":"CH",
    "sg:address":"Zieglerstrasse 34",
    "sg:city":"Bern",
    "sg:orig_category":"Softwareentwicklung U beratung",
    "sg:phone":"+41 31 385 30 11",
    "sg:postcode":"3007",
    "sg:province":"Bern",
    "wof:name":"Glue Software Engineering Ag",
    "wof:placetype":"venue"
},
  "geometry": {"coordinates":[7.4296989441,46.9443740845],"type":"Point"}
}