{
  "type": "Feature",
  "properties": {
    "iso:country":"CH",
    "sg:address":"Weissbadstrasse 2",
    "sg:city":"Appenzell",
    "sg:classifiers":[
        {
            "category":"Travel",
            "subcategory":"Hotels & Motels",
            "type":"Entertainment"
        }
    ],
    "sg:phone":"+41 79 414 13 27",
    "sg:postcode":"9050",
    "sg:province":"Appenzell Innerhoden",
    "sg:tags":[
        "hotels",
        "mit",
        "restaurant"
    ],
    "wof:name":"Hotel Adler-glasi",
    "wof:placetype":"venue"
},
  "geometry": {"coordinates":[8.3113203049,46.9813232422],"type":"Point"}
}