{
  "type": "Feature",
  "properties": {
    "iso:country":"CH",
    "sg:address":"Stegr\u00fcteli",
    "sg:city":"Galgenen",
    "sg:orig_category":"Allgemeiner Hoch U Tiefbau",
    "sg:postcode":"8854",
    "sg:province":"Schwyz",
    "wof:name":"Wogebag B\u00e4ch Ag",
    "wof:placetype":"venue"
},
  "geometry": {"coordinates":[8.734148,47.197395],"type":"Point"}
}