{
  "type": "Feature",
  "properties": {
    "iso:country":"CH",
    "sg:address":"Eschikon 21r",
    "sg:city":"Lindau",
    "sg:orig_category":"Grosshandel mit Getreide, Saatgut U Futtermitteln",
    "sg:phone":"+41 17881258",
    "sg:postcode":"8315",
    "sg:province":"Z\u00fcrich",
    "wof:name":"Z\u00fcrrer Alfred, Landesprodukte & Transporte",
    "wof:placetype":"venue"
},
  "geometry": {"coordinates":[8.6605319977,47.1924514771],"type":"Point"}
}