{
  "type": "Feature",
  "properties": {
    "iso:country":"CH",
    "sg:address":"Z\u00fcrichstrasse 7-9",
    "sg:city":"Herzogenbuchsee",
    "sg:orig_category":"Detailhandel mit Radio U Fernsehger\u00e4ten Elektroinstallation",
    "sg:postcode":"3360",
    "sg:province":"Bern",
    "wof:name":"Stalder, Heinz",
    "wof:placetype":"venue"
},
  "geometry": {"coordinates":[7.7063961029,47.1885185242],"type":"Point"}
}