{
  "type": "Feature",
  "properties": {
    "iso:country":"CH",
    "sg:address":"Impasse Beaus\u00e9jour 27",
    "sg:city":"Givisiez",
    "sg:orig_category":"Handels-H\u00e4user U Gesellschaften",
    "sg:phone":"+41 26 466 43 16",
    "sg:postcode":"1762",
    "sg:province":"Fribourg",
    "wof:name":"Moullet Christian",
    "wof:placetype":"venue"
},
  "geometry": {"coordinates":[7.1321940422,46.8106575012],"type":"Point"}
}