{
  "type": "Feature",
  "properties": {
    "iso:country":"CH",
    "sg:address":"Schwanenstrasse 7",
    "sg:city":"Einsiedeln",
    "sg:orig_category":"Sportvereine Ballsport Handball",
    "sg:phone":"+41 55 412 25 48",
    "sg:postcode":"8840",
    "sg:province":"Schwyz",
    "wof:name":"Hc Einsiedeln",
    "wof:placetype":"venue"
},
  "geometry": {"coordinates":[8.7465524673,47.1269569397],"type":"Point"}
}