{
  "type": "Feature",
  "properties": {
    "iso:country":"CH",
    "sg:address":"Buchzelgstrasse 112",
    "sg:city":"Z\u00fcrich",
    "sg:orig_category":"Grosshandel mit sonstigen Gebrauchs U Verbrauchsg\u00fctern",
    "sg:postcode":"8053",
    "sg:province":"Z\u00fcrich",
    "wof:name":"Alma-vision, Dr. Altmann A. Elektronische Werbedisplay; Handel, Vermietung",
    "wof:placetype":"venue"
},
  "geometry": {"coordinates":[8.5923633575,47.3596725464],"type":"Point"}
}