{
  "type": "Feature",
  "properties": {
    "iso:country":"CH",
    "sg:address":"3770",
    "sg:city":"Zweisimmen",
    "sg:orig_category":"Grosshandel mit Erzen U Metallen",
    "sg:postcode":"3770",
    "sg:province":"Bern",
    "wof:name":"E. Matti",
    "wof:placetype":"venue"
},
  "geometry": {"coordinates":[7.3726348877,46.5528755188],"type":"Point"}
}