{
  "type": "Feature",
  "properties": {
    "iso:country":"CH",
    "sg:address":"Rue Neuve",
    "sg:city":"Ste-croix",
    "sg:classifiers":[
        {
            "category":"Government",
            "subcategory":"Post Office",
            "type":"Public Place"
        }
    ],
    "sg:phone":"+41 24 454 35 37",
    "sg:postcode":"1450",
    "sg:province":"Vaud",
    "sg:tags":[
        "caf\u00e9s",
        "tea-rooms"
    ],
    "wof:name":"Bar \u00e0 Caf\u00e9 Le Sporting",
    "wof:placetype":"venue"
},
  "geometry": {"coordinates":[6.5018129349,46.8219451904],"type":"Point"}
}