{
  "type": "Feature",
  "properties": {
    "iso:country":"CH",
    "sg:address":"Meienbreitenstrasse 13 8153 R\u00fcmlang. Postfach",
    "sg:city":"R\u00fcmlang",
    "sg:orig_category":"Herstellung von Metallkonstruktionen Stahl U Leichtmetallbau",
    "sg:phone":"+41 18181222",
    "sg:postcode":"8153",
    "sg:province":"Z\u00fcrich",
    "wof:name":"Bama Metallbau Gmbh",
    "wof:placetype":"venue"
},
  "geometry": {"coordinates":[8.5274877548,47.4588546753],"type":"Point"}
}