{
  "type": "Feature",
  "properties": {
    "iso:country":"CH",
    "sg:address":"Navigation Rue De La 25 1201 Gen\u00e8ve. Postfach",
    "sg:city":"Gen\u00e8ve",
    "sg:orig_category":"Personenbef\u00f6rderung im Linienverkehr zu Land",
    "sg:postcode":"1201",
    "sg:province":"Gen\u00e8ve",
    "wof:name":"Cb City Bus Sa",
    "wof:placetype":"venue"
},
  "geometry": {"coordinates":[6.1460108757,46.2125205994],"type":"Point"}
}