{
  "type": "Feature",
  "properties": {
    "iso:country":"CH",
    "sg:address":"3929",
    "sg:city":"T\u00e4sch",
    "sg:orig_category":"Sportvereine Sch\u00fctzen",
    "sg:postcode":"3929",
    "sg:province":"Valais",
    "wof:name":"Milit\u00e4rschiessverein Alphubel",
    "wof:placetype":"venue"
},
  "geometry": {"coordinates":[7.7763252258,46.069694519],"type":"Point"}
}