{
  "type": "Feature",
  "properties": {
    "iso:country":"CH",
    "sg:address":"Alpes Avenue Des 2",
    "sg:city":"Sierre",
    "sg:orig_category":"Bestattungswesen",
    "sg:phone":"+41 27 455 10 16",
    "sg:postcode":"3960",
    "sg:province":"Valais",
    "wof:name":"Pompes Fun\u00e8bres Moeri Et Voeffray Sa",
    "wof:placetype":"venue"
},
  "geometry": {"coordinates":[7.530655,46.292404],"type":"Point"}
}