{
  "type": "Feature",
  "properties": {
    "iso:country":"CH",
    "sg:address":"Via Salvioni 6b",
    "sg:city":"Bellinzona",
    "sg:orig_category":"Zahnarztpraxen",
    "sg:phone":"+41 91 825 57 02",
    "sg:postcode":"6500",
    "sg:province":"Ticino",
    "wof:name":"Dott.med.dent.matteo Cassina Dentista",
    "wof:placetype":"venue"
},
  "geometry": {"coordinates":[9.016494751,46.1921768188],"type":"Point"}
}