{
  "type": "Feature",
  "properties": {
    "iso:country":"CH",
    "sg:address":"Z\u00fcrcherstrasse 137 8952 Schlieren. Postfach 471",
    "sg:city":"Schlieren",
    "sg:orig_category":"Fotografische Ateliers Fotografisches Gewerbe U fotografische Laboratorien",
    "sg:phone":"+41 79 356 65 94",
    "sg:postcode":"8952",
    "sg:province":"Z\u00fcrich",
    "wof:name":"Foto Cherry, Niederer Gerhard",
    "wof:placetype":"venue"
},
  "geometry": {"coordinates":[8.4659824371,47.3965187073],"type":"Point"}
}