{
  "type": "Feature",
  "properties": {
    "iso:country":"CH",
    "sg:address":"Sch\u00f6ntal",
    "sg:city":"H\u00fctten",
    "sg:orig_category":"Abwasserreinigung, Abfallbeseitigung U sonstige Entsorgung",
    "sg:postcode":"8825",
    "sg:province":"Z\u00fcrich",
    "wof:name":"Pfister Arnold, Kanalreinigung, Transport, Entsorgung",
    "wof:placetype":"venue"
},
  "geometry": {"coordinates":[8.665453,47.167603],"type":"Point"}
}