{
  "type": "Feature",
  "properties": {
    "iso:country":"CH",
    "sg:address":"Eschmatt",
    "sg:city":"Gibswil-ried",
    "sg:orig_category":"Grosshandel mit Holz U Baustoffen",
    "sg:phone":"+41 55 265 61 30",
    "sg:postcode":"8498",
    "sg:province":"Z\u00fcrich",
    "wof:name":"Real-stein Ag",
    "wof:placetype":"venue"
},
  "geometry": {"coordinates":[8.9219198227,47.3058509827],"type":"Point"}
}