{
  "type": "Feature",
  "properties": {
    "iso:country":"CH",
    "sg:address":"Yerly Rue Pierre 10",
    "sg:city":"Givisiez",
    "sg:orig_category":"Handels-H\u00e4user U Gesellschaften",
    "sg:phone":"+41 26 466 70 22",
    "sg:postcode":"1762",
    "sg:province":"Fribourg",
    "wof:name":"Dimenziya Publishing Sa",
    "wof:placetype":"venue"
},
  "geometry": {"coordinates":[7.1362071037,46.8153610229],"type":"Point"}
}