{
  "type": "Feature",
  "properties": {
    "iso:country":"CH",
    "sg:address":"Route D'echallens 2",
    "sg:city":"Romanel-s-lausanne",
    "sg:orig_category":"Wirtschaftspr\u00fcfung, Steuerberatung U Treuhand",
    "sg:phone":"+41 22 301 40 50",
    "sg:postcode":"1032",
    "sg:province":"Vaud",
    "wof:name":"Fiduciaire Suchet Sa",
    "wof:placetype":"venue"
},
  "geometry": {"coordinates":[6.12774086,46.1870918274],"type":"Point"}
}