{
  "type": "Feature",
  "properties": {
    "iso:country":"CH",
    "sg:address":"Zumhofhalde 10",
    "sg:city":"Kriens",
    "sg:orig_category":"Grosshandel mit Foto U Kinoger\u00e4ten, feinmechanischen U optischen Erzeugnissen Grosshandel mit elektr",
    "sg:phone":"+41 41 320 44 60",
    "sg:postcode":"6010",
    "sg:province":"Luzern",
    "wof:name":"Ms Spotlight Diskothekenbedarf",
    "wof:placetype":"venue"
},
  "geometry": {"coordinates":[8.2713804245,47.037815094],"type":"Point"}
}