{
  "type": "Feature",
  "properties": {
    "addr:full":"Via Cantonale 1 Stabio Ticino 6855",
    "addr:housenumber":"1",
    "addr:postcode":"6855",
    "addr:street":"Via Cantonale",
    "iso:country":"CH",
    "sg:address":"Via Cantonale 1",
    "sg:city":"Stabio",
    "sg:classifiers":[
        {
            "category":"Wholesale",
            "subcategory":"Wine & Distilled Alcoholic Beverages",
            "type":"Manufacturing & Wholesale Goods"
        }
    ],
    "sg:phone":"+41 91 647 32 81",
    "sg:postcode":"6855",
    "sg:province":"Ticino",
    "sg:tags":[
        "german"
    ],
    "wof:name":"Vini B\u00e9e S.a.",
    "wof:placetype":"venue"
},
  "geometry": {"coordinates":[8.945748,45.851856],"type":"Point"}
}