{
  "type": "Feature",
  "properties": {
    "iso:country":"CH",
    "sg:address":"8310 Kemptthal. Postfach 3",
    "sg:city":"Kemptthal",
    "sg:orig_category":"Sportvereine Ballsport Fussball",
    "sg:phone":"+41 52 203 83 03",
    "sg:postcode":"8310",
    "sg:province":"Z\u00fcrich",
    "wof:name":"Fc Kemptthal",
    "wof:placetype":"venue"
},
  "geometry": {"coordinates":[8.7117395401,47.4551887512],"type":"Point"}
}