{
  "type": "Feature",
  "properties": {
    "iso:country":"CH",
    "sg:address":"Schmidholzstrasse 56",
    "sg:city":"M\u00fcnchenstein",
    "sg:orig_category":"Architektur U Ingenieurb\u00fcros",
    "sg:postcode":"4142",
    "sg:province":"Basel-Landschaft",
    "wof:name":"Industinum Gmbh",
    "wof:placetype":"venue"
},
  "geometry": {"coordinates":[7.604845,47.519497],"type":"Point"}
}