{
  "type": "Feature",
  "properties": {
    "iso:country":"CH",
    "sg:address":"St. Alban-anlage 25",
    "sg:city":"Basel",
    "sg:orig_category":"Physiotherapie",
    "sg:phone":"+41 61 272 36 95",
    "sg:postcode":"4052",
    "sg:province":"Basel-Stadt",
    "wof:name":"Waltraut E. Rodes Physiotherapie",
    "wof:placetype":"venue"
},
  "geometry": {"coordinates":[7.598277092,47.5523071289],"type":"Point"}
}