{
  "type": "Feature",
  "properties": {
    "iso:country":"CH",
    "sg:address":"Espace De L'europe 10",
    "sg:city":"Neuch\u00e2tel",
    "sg:orig_category":"Verwaltung der Volkswirtschaft",
    "sg:phone":"+41 32 713 60 11",
    "sg:postcode":"2000",
    "sg:province":"Neuch\u00e2tel",
    "wof:name":"Office F\u00e9d.de La Statistique",
    "wof:placetype":"venue"
},
  "geometry": {"coordinates":[6.941450119,46.9826812744],"type":"Point"}
}