{
  "type": "Feature",
  "properties": {
    "iso:country":"CH",
    "sg:address":"Stadtbr\u00fccke 3 9620 Lichtensteig. Postfach 63",
    "sg:city":"Lichtensteig",
    "sg:orig_category":"Herstellung von chemischen Grundstoffen",
    "sg:phone":"+41 91 829 00 29",
    "sg:postcode":"9620",
    "sg:province":"St. Gallen",
    "wof:name":"At Compound Sa Advanced Technology",
    "wof:placetype":"venue"
},
  "geometry": {"coordinates":[9.1105241776,46.237323761],"type":"Point"}
}