{
  "type": "Feature",
  "properties": {
    "iso:country":"CH",
    "sg:address":"Kantonsstrasse 160",
    "sg:city":"Horw",
    "sg:orig_category":"Allgemeiner Hoch U Tiefbau Hoch U Tiefbau",
    "sg:phone":"+41 41 310 90 67",
    "sg:postcode":"6048",
    "sg:province":"Luzern",
    "wof:name":"Bossart Spezialsanierungen",
    "wof:placetype":"venue"
},
  "geometry": {"coordinates":[8.308082,47.011864],"type":"Point"}
}