{
  "type": "Feature",
  "properties": {
    "iso:country":"CH",
    "sg:address":"Bahnstrasse 1",
    "sg:city":"Sch\u00f6nenwerd",
    "sg:classifiers":[
        {
            "category":"Restaurant",
            "type":"Food & Drink"
        }
    ],
    "sg:phone":"+41 19371212",
    "sg:postcode":"5012",
    "sg:province":"Solothurn",
    "wof:name":"Restaurant Feldegg",
    "wof:placetype":"venue"
},
  "geometry": {"coordinates":[8.8404378891,47.2999458313],"type":"Point"}
}