{
  "type": "Feature",
  "properties": {
    "iso:country":"CH",
    "sg:address":"M\u00fcllerh\u00f6lzlistrasse 16",
    "sg:city":"Volketswil",
    "sg:orig_category":"Herstellung von keramischen Wand U Bodenfliesen U platten",
    "sg:phone":"+41 71 222 33 12",
    "sg:postcode":"8604",
    "sg:province":"Z\u00fcrich",
    "wof:name":"Tomasini Giovanni Ag",
    "wof:placetype":"venue"
},
  "geometry": {"coordinates":[9.3661384583,47.4180526733],"type":"Point"}
}