{
  "type": "Feature",
  "properties": {
    "iso:country":"CH",
    "sg:address":"Taillepied Route De 125",
    "sg:city":"Ch\u00e2telard-lutry",
    "sg:orig_category":"Wohnheime",
    "sg:phone":"+41 32 752 12 12",
    "sg:postcode":"1095",
    "sg:province":"Vaud",
    "wof:name":"Home M\u00e9dicalis\u00e9 Bellevue, Fondation Russ Hermann",
    "wof:placetype":"venue"
},
  "geometry": {"coordinates":[7.0641651154,47.0518341064],"type":"Point"}
}