{
  "type": "Feature",
  "properties": {
    "iso:country":"CH",
    "sg:address":"Zelgenweg 6",
    "sg:city":"Embrach",
    "sg:orig_category":"Wirtschaftspr\u00fcfung, Steuerberatung U Treuhand",
    "sg:postcode":"8424",
    "sg:province":"Z\u00fcrich",
    "wof:name":"Key - Consulting - De Feo",
    "wof:placetype":"venue"
},
  "geometry": {"coordinates":[8.5911846161,47.5016365051],"type":"Point"}
}