{
  "type": "Feature",
  "properties": {
    "iso:country":"CH",
    "sg:address":"Riedbachstrasse 22",
    "sg:city":"Frauenkappelen",
    "sg:orig_category":"Architektur U Ingenieurb\u00fcros",
    "sg:phone":"+41 31 920 10 10",
    "sg:postcode":"3202",
    "sg:province":"Bern",
    "wof:name":"Lehmann Bauberatung",
    "wof:placetype":"venue"
},
  "geometry": {"coordinates":[7.337607,46.950714],"type":"Point"}
}