{
  "type": "Feature",
  "properties": {
    "iso:country":"CH",
    "sg:address":"Ettenbergstrasse 86",
    "sg:city":"Wettswil",
    "sg:orig_category":"Sportvereine Fischerei",
    "sg:phone":"+41 17000848",
    "sg:postcode":"8907",
    "sg:province":"Z\u00fcrich",
    "wof:name":"Fischereiverein",
    "wof:placetype":"venue"
},
  "geometry": {"coordinates":[8.4634437561,47.3472290039],"type":"Point"}
}