{
  "type": "Feature",
  "properties": {
    "iso:country":"CH",
    "sg:address":"Rue St-maurice 7d",
    "sg:city":"Del\u00e9mont",
    "sg:orig_category":"HERSTELLUNG VON GER\u00c4TEN DER ELEKTRIZIT\u00c4TSERZEUGUNG, -VERTEILUNG U.\u00c4 Mechanische Werkst\u00e4tten",
    "sg:phone":"+41 32 422 95 16",
    "sg:postcode":"2800",
    "sg:province":"Jura",
    "wof:name":"Overland Bolling Sa",
    "wof:placetype":"venue"
},
  "geometry": {"coordinates":[7.3419780731,47.3525428772],"type":"Point"}
}