{
  "type": "Feature",
  "properties": {
    "addr:full":"Wangenerstrasse 1 Tagelswangen Z\u00fcrich 8317",
    "addr:housenumber":"1",
    "addr:postcode":"8317",
    "addr:street":"Wangenerstrasse",
    "iso:country":"CH",
    "sg:address":"Wangenerstrasse 1",
    "sg:city":"Tagelswangen",
    "sg:orig_category":"Autogaragen",
    "sg:phone":"+41 52 343 16 62",
    "sg:postcode":"8317",
    "sg:province":"Z\u00fcrich",
    "wof:name":"Kurt Steiner Garage",
    "wof:placetype":"venue"
},
  "geometry": {"coordinates":[8.672056,47.430328],"type":"Point"}
}