{
  "type": "Feature",
  "properties": {
    "iso:country":"CH",
    "sg:address":"Friedheimstrasse 17",
    "sg:city":"Z\u00fcrich",
    "sg:orig_category":"Berufliche Weiterbildung, Erwachsenenbildung",
    "sg:phone":"+41 18011717",
    "sg:postcode":"8050",
    "sg:province":"Z\u00fcrich",
    "wof:name":"Hochschule F\u00fcr Soziale Arbeit Weiter Und Fortbildung",
    "wof:placetype":"venue"
},
  "geometry": {"coordinates":[8.598921,47.395294],"type":"Point"}
}