{
  "type": "Feature",
  "properties": {
    "iso:country":"CH",
    "sg:address":"Rue Caroline 17",
    "sg:city":"Gen\u00e8ve",
    "sg:orig_category":"RESTAURANTS: TEA-ROOMS",
    "sg:phone":"+41 61 771 06 42",
    "sg:postcode":"1200",
    "sg:province":"Gen\u00e8ve",
    "wof:name":"Steiner-steiner Anna, Restaurant Kreuz",
    "wof:placetype":"venue"
},
  "geometry": {"coordinates":[7.4295911789,47.4036254883],"type":"Point"}
}