{
  "type": "Feature",
  "properties": {
    "iso:country":"CH",
    "sg:address":"3615",
    "sg:city":"Heimenschwand",
    "sg:orig_category":"Landesverteidigung, Sozialversicherung \u00d6ffentliche Verwaltung",
    "sg:phone":"+41 62 834 74 01",
    "sg:postcode":"3615",
    "sg:province":"Bern",
    "wof:name":"Zivilschutzstelle Buchs",
    "wof:placetype":"venue"
},
  "geometry": {"coordinates":[8.075630188,47.3880691528],"type":"Point"}
}