{
  "type": "Feature",
  "properties": {
    "iso:country":"CH",
    "sg:address":"S\u00e4gereistrasse 4",
    "sg:city":"Schindellegi",
    "sg:orig_category":"S\u00e4ge, Hobel U Holzimpr\u00e4gnierwerke S\u00e4gewerke",
    "sg:phone":"+41 17841642",
    "sg:postcode":"8834",
    "sg:province":"Schwyz",
    "wof:name":"Schatt Gebr. Ag",
    "wof:placetype":"venue"
},
  "geometry": {"coordinates":[8.7123813629,47.1733360291],"type":"Point"}
}