{
  "type": "Feature",
  "properties": {
    "iso:country":"CH",
    "sg:address":"Gotthardstrasse 55 8800 Thalwil. Postfach",
    "sg:city":"Thalwil",
    "sg:orig_category":"Architektur U Ingenieurb\u00fcros Architekturb\u00fcros",
    "sg:phone":"+41 17200815",
    "sg:postcode":"8800",
    "sg:province":"Z\u00fcrich",
    "wof:name":"Angst Architekten Ag Architekturb\u00fcro",
    "wof:placetype":"venue"
},
  "geometry": {"coordinates":[8.561955,47.297775],"type":"Point"}
}