{
  "type": "Feature",
  "properties": {
    "iso:country":"CH",
    "sg:address":"Landorfstrasse 48a 3098 K\u00f6niz. Postfach 676",
    "sg:city":"K\u00f6niz",
    "sg:orig_category":"Advokaturb\u00fcros",
    "sg:phone":"+41 31 971 72 61",
    "sg:postcode":"3098",
    "sg:province":"Bern",
    "wof:name":"Gerhard Jakob Advokaturb\u00fcro",
    "wof:placetype":"venue"
},
  "geometry": {"coordinates":[7.410194,46.921551],"type":"Point"}
}