{
  "type": "Feature",
  "properties": {
    "iso:country":"CH",
    "sg:address":"Regensdorferstrasse 22",
    "sg:city":"D\u00e4llikon",
    "sg:orig_category":"Nationale Postdienste",
    "sg:phone":"+41 18440500",
    "sg:postcode":"8108",
    "sg:province":"Z\u00fcrich",
    "wof:name":"Die Schweizerische Post",
    "wof:placetype":"venue"
},
  "geometry": {"coordinates":[8.4408140182,47.4394721985],"type":"Point"}
}