{
  "type": "Feature",
  "properties": {
    "addr:full":"Zeltweg 50 Z\u00fcrich Z\u00fcrich 8032",
    "addr:housenumber":"50",
    "addr:postcode":"8032",
    "addr:street":"Zeltweg",
    "iso:country":"CH",
    "sg:address":"Zeltweg 50",
    "sg:city":"Z\u00fcrich",
    "sg:orig_category":"Berufsberatungen",
    "sg:phone":"+41 12616010",
    "sg:postcode":"8032",
    "sg:province":"Z\u00fcrich",
    "wof:name":"Ursina Ricklin Schul-& Laufbahnberatung",
    "wof:placetype":"venue"
},
  "geometry": {"coordinates":[8.552059,47.367599],"type":"Point"}
}