{
  "type": "Feature",
  "properties": {
    "iso:country":"CH",
    "sg:address":"Breitenrainstrasse 25 3013 Bern. Postfach",
    "sg:city":"Bern",
    "sg:orig_category":"Grosshandel mit Nahrungsmitteln, Getr\u00e4nken U Tabakwaren ohne ausgepr\u00e4gten Schwerpunkt",
    "sg:postcode":"3005",
    "sg:province":"Bern",
    "wof:name":"Oberson Mme S. March\u00e9 St-andr\u00e9",
    "wof:placetype":"venue"
},
  "geometry": {"coordinates":[7.0224370956,46.7736816406],"type":"Point"}
}