{
  "type": "Feature",
  "properties": {
    "iso:country":"CH",
    "sg:address":"St\u00e4dtlistrasse 11",
    "sg:city":"Dallenwil",
    "sg:orig_category":"Non-Classified Establishments",
    "sg:phone":"+41 41 628 00 28",
    "sg:postcode":"6383",
    "sg:province":"Nidwalden",
    "wof:name":"Gasthaus Schl\u00fcssel",
    "wof:placetype":"venue"
},
  "geometry": {"coordinates":[8.3905954361,46.9325180054],"type":"Point"}
}