{
  "type": "Feature",
  "properties": {
    "iso:country":"CH",
    "sg:address":"Fontaine Place De La 4",
    "sg:city":"Peseux",
    "sg:orig_category":"Interessenvertretungen",
    "sg:postcode":"2034",
    "sg:province":"Neuch\u00e2tel",
    "wof:name":"International Ambassadors Fellowship Guild",
    "wof:placetype":"venue"
},
  "geometry": {"coordinates":[6.8898267746,46.9876365662],"type":"Point"}
}