{
  "type": "Feature",
  "properties": {
    "iso:country":"CH",
    "sg:address":"Oberallmendstrasse 16 6300 Zug. Postfach 2062",
    "sg:city":"Zug",
    "sg:orig_category":"Wirtschaftspr\u00fcfung, Steuerberatung U Treuhand",
    "sg:phone":"+41 41 760 14 15",
    "sg:postcode":"6302",
    "sg:province":"Zug",
    "wof:name":"Waller Treuhand Ag",
    "wof:placetype":"venue"
},
  "geometry": {"coordinates":[8.5234107971,47.180973053],"type":"Point"}
}