{
  "type": "Feature",
  "properties": {
    "iso:country":"CH",
    "sg:address":"Bahnhofstrasse 3",
    "sg:city":"Langenthal",
    "sg:orig_category":"Reiseb\u00fcros",
    "sg:phone":"+41 62 916 70 70",
    "sg:postcode":"4900",
    "sg:province":"Bern",
    "wof:name":"Kuoni Reisen Ag",
    "wof:placetype":"venue"
},
  "geometry": {"coordinates":[7.788836956,47.2122192383],"type":"Point"}
}