{
  "type": "Feature",
  "properties": {
    "iso:country":"CH",
    "sg:address":"Tuma Cast\u00e9 Via 33",
    "sg:city":"Domat/ems",
    "sg:orig_category":"Finanzierungsinstitutionen",
    "sg:phone":"+41 81 633 51 78",
    "sg:postcode":"7013",
    "sg:province":"Graubunden",
    "wof:name":"Lazic Marija",
    "wof:placetype":"venue"
},
  "geometry": {"coordinates":[9.4473543167,46.8362007141],"type":"Point"}
}