{
  "type": "Feature",
  "properties": {
    "iso:country":"CH",
    "sg:address":"Bahnhofstrasse 25",
    "sg:city":"Dottikon",
    "sg:orig_category":"RESTAURANTS: TEA-ROOMS",
    "sg:phone":"+41 79 297 87 26",
    "sg:postcode":"5605",
    "sg:province":"Aargau",
    "wof:name":"Caf\u00e9 Restaurant De L'univers Ben Hamida Adel & Cie.",
    "wof:placetype":"venue"
},
  "geometry": {"coordinates":[6.8400359154,47.107673645],"type":"Point"}
}