{
  "type": "Feature",
  "properties": {
    "iso:country":"CH",
    "sg:address":"Th\u00e9\u00e2tre Rue Du 20 1820 Montreux. Postfach",
    "sg:city":"Montreux",
    "sg:orig_category":"Architektur U Ingenieurb\u00fcros",
    "sg:postcode":"1820",
    "sg:province":"Vaud",
    "wof:name":"Ben Business Executive Network Sa",
    "wof:placetype":"venue"
},
  "geometry": {"coordinates":[6.909442,46.431095],"type":"Point"}
}