{
  "type": "Feature",
  "properties": {
    "iso:country":"CH",
    "sg:address":"Thunstrasse 38",
    "sg:city":"Rubigen",
    "sg:orig_category":"Zimmerei, Dachdeckerei, Bauspenglerei U Abdichtung",
    "sg:postcode":"3113",
    "sg:province":"Bern",
    "wof:name":"Schmid Emil",
    "wof:placetype":"venue"
},
  "geometry": {"coordinates":[9.2819824219,46.8325805664],"type":"Point"}
}