{
  "type": "Feature",
  "properties": {
    "addr:full":"Gzs-strahlholz Gais Appenzell Ausserrhoden 9056",
    "addr:postcode":"9056",
    "addr:street":"Gzs-Strahlholz;Appenzell Ausserrhoden",
    "iso:country":"CH",
    "sg:address":"Gzs-strahlholz",
    "sg:city":"Gais",
    "sg:classifiers":[
        {
            "category":"Utilities",
            "subcategory":"Electric",
            "type":"Services"
        }
    ],
    "sg:phone":"+41 21 694 41 11",
    "sg:postcode":"9056",
    "sg:province":"Appenzell Ausserrhoden",
    "sg:tags":[
        "electricity",
        "electronic",
        "electrical",
        "equipment"
    ],
    "wof:name":"Mailleser Sa",
    "wof:placetype":"venue"
},
  "geometry": {"coordinates":[6.567451,46.534832],"type":"Point"}
}