{
  "type": "Feature",
  "properties": {
    "addr:full":"Rue Pestalozzoi 17 Gen\u00e8ve Gen\u00e8ve 1202",
    "addr:housenumber":"17",
    "addr:postcode":"1202",
    "addr:street":"Rue Pestalozzoi",
    "iso:country":"CH",
    "sg:address":"Rue Pestalozzoi 17",
    "sg:city":"Gen\u00e8ve",
    "sg:orig_category":"Autogaragen",
    "sg:phone":"+41 22 733 33 33",
    "sg:postcode":"1202",
    "sg:province":"Gen\u00e8ve",
    "wof:name":"Garage De L'etoile Automobiles Sa",
    "wof:placetype":"venue"
},
  "geometry": {"coordinates":[6.128041,46.216816],"type":"Point"}
}