{
  "type": "Feature",
  "properties": {
    "iso:country":"CH",
    "sg:address":"Weinfelderstrasse 15 8580 Amriswil. Postfach",
    "sg:city":"Amriswil",
    "sg:orig_category":"Detailhandel mit Metallwaren, Anstrichmitteln, Glaswaren, Bau U Heimwerkerbedarf",
    "sg:postcode":"8580",
    "sg:province":"Thurgau",
    "wof:name":"Atecno Gmbh Technische Ger\u00e4te; Entwicklung, Produktion, Verkauf Usw",
    "wof:placetype":"venue"
},
  "geometry": {"coordinates":[9.2956752777,47.5452346802],"type":"Point"}
}