{
  "type": "Feature",
  "properties": {
    "iso:country":"CH",
    "sg:address":"Bahnhofstrasse 49 9320 Arbon. Postfach 437",
    "sg:city":"Arbon",
    "sg:orig_category":"HOTELS: MIT RESTAURANT Kongress- and Tagungshotels mit Restaurant",
    "sg:phone":"+41 71 447 82 82",
    "sg:postcode":"9320",
    "sg:province":"Thurgau",
    "wof:name":"Hotel Metropol",
    "wof:placetype":"venue"
},
  "geometry": {"coordinates":[9.4338340759,47.5113601685],"type":"Point"}
}