{
  "type": "Feature",
  "properties": {
    "addr:full":"Aarauerstrasse 69 Brugg Aargau 5200",
    "addr:housenumber":"69",
    "addr:postcode":"5200",
    "addr:street":"Aarauerstrasse",
    "iso:country":"CH",
    "sg:address":"Aarauerstrasse 69",
    "sg:city":"Brugg",
    "sg:classifiers":[
        {
            "category":"Banks & Credit Unions",
            "subcategory":"Investment Brokerage",
            "type":"Services"
        }
    ],
    "sg:phone":"+41 56 460 74 74",
    "sg:postcode":"5200",
    "sg:province":"Aargau",
    "sg:tags":[
        "machine",
        "ticket",
        "automatic",
        "machines",
        "parking"
    ],
    "wof:name":"Hectronic Ag",
    "wof:placetype":"venue"
},
  "geometry": {"coordinates":[8.200164,47.474621],"type":"Point"}
}