{
  "type": "Feature",
  "properties": {
    "addr:full":"1724 Mont\u00e9vraz Fribourg 1724",
    "addr:housenumber":"1724",
    "addr:postcode":"1724",
    "addr:street":"Monte\u0301Vraz Fribourg",
    "iso:country":"CH",
    "sg:address":"1724",
    "sg:city":"Mont\u00e9vraz",
    "sg:orig_category":"Bauschreinerei Herstellung von Konstruktionsteilen, Fertigbauteilen U Ausbauelementen aus Holz",
    "sg:phone":"+41 26 413 30 12",
    "sg:postcode":"1724",
    "sg:province":"Fribourg",
    "wof:name":"Sturny Jacques",
    "wof:placetype":"venue"
},
  "geometry": {"coordinates":[7.177688,46.728645],"type":"Point"}
}