{
  "type": "Feature",
  "properties": {
    "iso:country":"CH",
    "sg:address":"Bahnhofstrasse",
    "sg:city":"Fl\u00fcelen",
    "sg:orig_category":"Interessenvertretungen",
    "sg:phone":"+41 41 870 25 58",
    "sg:postcode":"6454",
    "sg:province":"Uri",
    "wof:name":"Personalf\u00fcrsorgestiftung Der Firma Bika-holzverarbeitung Gebr. Alois & Anton Bissig.",
    "wof:placetype":"venue"
},
  "geometry": {"coordinates":[8.6240520477,46.8979530334],"type":"Point"}
}