{
  "type": "Feature",
  "properties": {
    "iso:country":"CH",
    "sg:address":"Sternhalde 5. 6000 Luzern. Postfach",
    "sg:city":"Luzern",
    "sg:orig_category":"Pensionskassen",
    "sg:postcode":"6005",
    "sg:province":"Luzern",
    "wof:name":"Personalf\u00fcrsorgestiftung Der Niederberger & Co.",
    "wof:placetype":"venue"
},
  "geometry": {"coordinates":[8.3096961975,47.0385894775],"type":"Point"}
}