{
  "type": "Feature",
  "properties": {
    "iso:country":"CH",
    "sg:address":"Birchstrasse 24",
    "sg:city":"Tagelswangen",
    "sg:orig_category":"Handelsvermittlung U Grosshandel Herstellung von feuerfester Keramik",
    "sg:phone":"+41 52 343 31 18",
    "sg:postcode":"8317",
    "sg:province":"Z\u00fcrich",
    "wof:name":"Hug Georges",
    "wof:placetype":"venue"
},
  "geometry": {"coordinates":[8.675160408,47.4290428162],"type":"Point"}
}