{
  "type": "Feature",
  "properties": {
    "iso:country":"CH",
    "sg:address":"Florastrasse 3",
    "sg:city":"Bern",
    "sg:classifiers":[
        {
            "category":"Professional",
            "subcategory":"Advertising",
            "type":"Services"
        }
    ],
    "sg:phone":"+41 31 357 20 20",
    "sg:postcode":"3005",
    "sg:province":"Bern",
    "sg:tags":[
        "textile",
        "articles"
    ],
    "wof:name":"Fahnenfabrik Bern Hutmacher-schalch Ag",
    "wof:placetype":"venue"
},
  "geometry": {"coordinates":[7.452982,46.943146],"type":"Point"}
}