{
  "type": "Feature",
  "properties": {
    "iso:country":"CH",
    "sg:address":"M\u00fchlemattstrasse 10",
    "sg:city":"Luzern",
    "sg:orig_category":"Wirtschafts U Arbeitgeberverb\u00e4nde",
    "sg:postcode":"6004",
    "sg:province":"Luzern",
    "wof:name":"Zimmermeister-verband Luzern & Umgebung",
    "wof:placetype":"venue"
},
  "geometry": {"coordinates":[8.3010463715,47.0555114746],"type":"Point"}
}