{
  "type": "Feature",
  "properties": {
    "iso:country":"CH",
    "sg:address":"Im Schachenhof 2",
    "sg:city":"Bonstetten",
    "sg:orig_category":"Grosshandel mit Eisenwaren sowie Installationsbedarf f\u00fcr Gas, Wasser U Heizung Sanit\u00e4r, Heizungs U L",
    "sg:phone":"+41 17003870",
    "sg:postcode":"8906",
    "sg:province":"Z\u00fcrich",
    "wof:name":"Josef Sgier Neutherm-heiztechnik",
    "wof:placetype":"venue"
},
  "geometry": {"coordinates":[8.4684276581,47.3150024414],"type":"Point"}
}