{
  "type": "Feature",
  "properties": {
    "addr:full":"Mattenstrasse 3 Pf\u00e4ffikon Z\u00fcrich 8330",
    "addr:housenumber":"3",
    "addr:postcode":"8330",
    "addr:street":"Mattenstrasse",
    "iso:country":"CH",
    "sg:address":"Mattenstrasse 3",
    "sg:city":"Pf\u00e4ffikon",
    "sg:orig_category":"Cylinder Head Processing Machines",
    "sg:phone":"+41 19501720",
    "sg:postcode":"8330",
    "sg:province":"Z\u00fcrich",
    "wof:name":"Minelli Ag",
    "wof:placetype":"venue"
},
  "geometry": {"coordinates":[8.776035,47.370316],"type":"Point"}
}