{
  "type": "Feature",
  "properties": {
    "iso:country":"CH",
    "sg:address":"Bechtenreute 808",
    "sg:city":"Oberegg",
    "sg:orig_category":"Sonstiger spezialisierter Hoch U Tiefbau",
    "sg:postcode":"9413",
    "sg:province":"Appenzell Innerhoden",
    "wof:name":"Andreas Ulmann, Maurergesch\u00e4ft",
    "wof:placetype":"venue"
},
  "geometry": {"coordinates":[9.5503931046,47.4226455688],"type":"Point"}
}