{
  "type": "Feature",
  "properties": {
    "iso:country":"CH",
    "sg:address":"Haldenstrasse 12",
    "sg:city":"Safenwil",
    "sg:orig_category":"Textilveredlung",
    "sg:phone":"+41 62 797 94 90",
    "sg:postcode":"5745",
    "sg:province":"Aargau",
    "wof:name":"Texprint Gmbh Textile Werbung",
    "wof:placetype":"venue"
},
  "geometry": {"coordinates":[7.970911026,47.3199501038],"type":"Point"}
}