{
  "type": "Feature",
  "properties": {
    "iso:country":"CH",
    "sg:address":"Avenue Du L\u00e9man 21",
    "sg:city":"Lausanne",
    "sg:orig_category":"Vermietung U Verpachtung von eigenen Immobilien Vermittlung von Immobilien",
    "sg:phone":"+41 21 966 11 22",
    "sg:postcode":"1005",
    "sg:province":"Vaud",
    "wof:name":"R\u00e9gie De La Riviera Sa",
    "wof:placetype":"venue"
},
  "geometry": {"coordinates":[6.6447248459,46.5165176392],"type":"Point"}
}