{
  "type": "Feature",
  "properties": {
    "iso:country":"CH",
    "sg:address":"Horloge Rue De L'",
    "sg:city":"Buchillon",
    "sg:orig_category":"Wirtschaftspr\u00fcfung, Steuerberatung U Treuhand",
    "sg:phone":"+41 21 807 38 53",
    "sg:postcode":"1164",
    "sg:province":"Vaud",
    "wof:name":"Perlini Paul, Expert-comptable",
    "wof:placetype":"venue"
},
  "geometry": {"coordinates":[6.4212498665,46.4699783325],"type":"Point"}
}