{
  "type": "Feature",
  "properties": {
    "iso:country":"CH",
    "sg:address":"Someo 6674 Someo. Postfach",
    "sg:city":"Someo",
    "sg:orig_category":"RESTAURANTS: TEA-ROOMS",
    "sg:phone":"+41 91 753 32 34",
    "sg:postcode":"6674",
    "sg:province":"Ticino",
    "wof:name":"Morandi Valeria Ristorante Bar Pizzeria Soladino",
    "wof:placetype":"venue"
},
  "geometry": {"coordinates":[8.6570596695,46.2887153625],"type":"Point"}
}