{
  "type": "Feature",
  "properties": {
    "iso:country":"CH",
    "sg:address":"Brandschenkestrasse 60",
    "sg:city":"Z\u00fcrich",
    "sg:orig_category":"Dienstleistungen von Beteiligungsgesellschaften",
    "sg:phone":"+41 12013852",
    "sg:postcode":"8002",
    "sg:province":"Z\u00fcrich",
    "wof:name":"Data Partner Ag",
    "wof:placetype":"venue"
},
  "geometry": {"coordinates":[8.5294628143,47.3678359985],"type":"Point"}
}