{
  "type": "Feature",
  "properties": {
    "iso:country":"CH",
    "sg:address":"Hauptstrasse 8",
    "sg:city":"Mammern",
    "sg:orig_category":"Campingpl\u00e4tze Detailhandel mit Zeitungen U Zeitschriften Kioske",
    "sg:phone":"+41 52 741 12 89",
    "sg:postcode":"8265",
    "sg:province":"Thurgau",
    "wof:name":"Camping Seewiese",
    "wof:placetype":"venue"
},
  "geometry": {"coordinates":[8.914601,47.6455],"type":"Point"}
}