{
  "type": "Feature",
  "properties": {
    "iso:country":"CH",
    "sg:address":"Minervastrasse 99 8032 Z\u00fcrich. Postfach",
    "sg:city":"Z\u00fcrich",
    "sg:orig_category":"Hochschulen U h\u00f6here Ausbildung",
    "sg:phone":"+41 13832083",
    "sg:postcode":"8032",
    "sg:province":"Z\u00fcrich",
    "wof:name":"Dentalhygiene-schule Z\u00fcrich",
    "wof:placetype":"venue"
},
  "geometry": {"coordinates":[8.5576753616,47.3645210266],"type":"Point"}
}