{
  "type": "Feature",
  "properties": {
    "iso:country":"CH",
    "sg:address":"Walzm\u00fchlestrasse 60",
    "sg:city":"Frauenfeld",
    "sg:orig_category":"Unternehmensberatung",
    "sg:postcode":"8500",
    "sg:province":"Thurgau",
    "wof:name":"Werugi Gmbh",
    "wof:placetype":"venue"
},
  "geometry": {"coordinates":[8.8929262161,47.5465087891],"type":"Point"}
}