{
  "type": "Feature",
  "properties": {
    "iso:country":"CH",
    "sg:address":"Marktgasse 20 4310 Rheinfelden. Postfach",
    "sg:city":"Rheinfelden",
    "sg:orig_category":"Detailhandel mit Brillen U anderen Sehhilfen Fachdetailhandel in Verkaufsr\u00e4umen",
    "sg:phone":"+41 61 831 14 28",
    "sg:postcode":"4310",
    "sg:province":"Aargau",
    "wof:name":"Veronesi Optik",
    "wof:placetype":"venue"
},
  "geometry": {"coordinates":[7.793019,47.555389],"type":"Point"}
}