{
  "type": "Feature",
  "properties": {
    "iso:country":"CH",
    "sg:address":"Ackerstrasse 37",
    "sg:city":"Uster",
    "sg:orig_category":"Non-Classified Establishments",
    "sg:postcode":"8610",
    "sg:province":"Z\u00fcrich",
    "wof:name":"Maler Simoes Peixoto",
    "wof:placetype":"venue"
},
  "geometry": {"coordinates":[8.7079353333,47.355758667],"type":"Point"}
}