{
  "type": "Feature",
  "properties": {
    "iso:country":"CH",
    "sg:address":"Via Alle Semine 6 6500 Bellinzona. Postfach",
    "sg:city":"Camorino",
    "sg:orig_category":"Werbeagenturen Werbung",
    "sg:phone":"+41 91 826 38 39",
    "sg:postcode":"6528",
    "sg:province":"Ticino",
    "wof:name":"Dama Communication Sa Contratti Pubblicitari, Consulenza Pubblicitaria E Commerciale Ecc",
    "wof:placetype":"venue"
},
  "geometry": {"coordinates":[9.0159778595,46.1844520569],"type":"Point"}
}