{
  "type": "Feature",
  "properties": {
    "iso:country":"CH",
    "sg:address":"Bahnhofplatz 7",
    "sg:city":"Z\u00fcrich",
    "sg:orig_category":"Detailhandel mit Schuhen U Lederwaren",
    "sg:phone":"+41 12211919",
    "sg:postcode":"8001",
    "sg:province":"Z\u00fcrich",
    "wof:name":"Artisti Schuhe + Lederwaren, Anagnostopoulos Schuhe, Accessoires Usw; Handel",
    "wof:placetype":"venue"
},
  "geometry": {"coordinates":[8.53947258,47.3769378662],"type":"Point"}
}