{
  "type": "Feature",
  "properties": {
    "iso:country":"CH",
    "sg:address":"Via Gr\u00fctli 10",
    "sg:city":"Chiasso",
    "sg:orig_category":"Detailhandel mit Waren verschiedener Art, Hauptrichtung Nahrungsmittel",
    "sg:phone":"+41 71 245 24 34",
    "sg:postcode":"6830",
    "sg:province":"Ticino",
    "wof:name":"Renate Hunkeler Lebensmittel Fr\u00fcchte",
    "wof:placetype":"venue"
},
  "geometry": {"coordinates":[9.3916463852,47.430393219],"type":"Point"}
}