{
  "type": "Feature",
  "properties": {
    "iso:country":"CH",
    "sg:address":"Sagenboden",
    "sg:city":"Plasselb",
    "sg:orig_category":"Herstellung von sonstigen landwirtschaftlichen Maschinen",
    "sg:postcode":"1737",
    "sg:province":"Fribourg",
    "wof:name":"J.cl. Ruffieux-landmaschinen & Trax Ag",
    "wof:placetype":"venue"
},
  "geometry": {"coordinates":[7.2509431839,46.7351074219],"type":"Point"}
}