{
  "type": "Feature",
  "properties": {
    "iso:country":"CH",
    "sg:address":"Maulbeerweg 2 4512 Bellach. Postfach 104",
    "sg:city":"Bellach",
    "sg:orig_category":"Stukkateurgewerbe, Gipserei U Verputzerei",
    "sg:postcode":"4512",
    "sg:province":"Solothurn",
    "wof:name":"Gipserei Gehriger",
    "wof:placetype":"venue"
},
  "geometry": {"coordinates":[7.5999817848,47.4726142883],"type":"Point"}
}