{
  "type": "Feature",
  "properties": {
    "iso:country":"CH",
    "sg:address":"Rue Du Temple 12",
    "sg:city":"Porrentruy",
    "sg:orig_category":"Schwimmb\u00e4der",
    "sg:phone":"+41 32 466 71 13",
    "sg:postcode":"2900",
    "sg:province":"Jura",
    "wof:name":"Piscine Couverte Les Tilleuls",
    "wof:placetype":"venue"
},
  "geometry": {"coordinates":[7.0742712021,47.4147834778],"type":"Point"}
}