{
  "type": "Feature",
  "properties": {
    "iso:country":"CH",
    "sg:address":"Halbrain 1",
    "sg:city":"Wangen",
    "sg:classifiers":[
        {
            "category":"Home & Garden",
            "subcategory":"Building Materials",
            "type":"Retail Goods"
        }
    ],
    "sg:phone":"+41 62 212 47 32",
    "sg:postcode":"4612",
    "sg:province":"Solothurn",
    "sg:tags":[
        "hinge"
    ],
    "wof:name":"H. Briner Ag",
    "wof:placetype":"venue"
},
  "geometry": {"coordinates":[7.8697991371,47.3450698853],"type":"Point"}
}