{
  "type": "Feature",
  "properties": {
    "iso:country":"CH",
    "sg:address":"Rue De Carouge 104",
    "sg:city":"Gen\u00e8ve",
    "sg:orig_category":"Detailhandel mit M\u00f6beln U Haushaltsgegenst\u00e4nden Detailhandel mit Teppichen",
    "sg:phone":"+41 79 202 37 70",
    "sg:postcode":"1205",
    "sg:province":"Gen\u00e8ve",
    "wof:name":"Atelier Du Tapis Rasti Mehri",
    "wof:placetype":"venue"
},
  "geometry": {"coordinates":[6.143237114,46.1900253296],"type":"Point"}
}