{
  "type": "Feature",
  "properties": {
    "iso:country":"CH",
    "sg:address":"Benziwilstrasse 14a",
    "sg:city":"Emmenbr\u00fccke",
    "sg:orig_category":"Vorschulen, Kinderg\u00e4rten",
    "sg:phone":"+41 52 375 16 49",
    "sg:postcode":"6020",
    "sg:province":"Luzern",
    "wof:name":"Kindergarten",
    "wof:placetype":"venue"
},
  "geometry": {"coordinates":[8.8259296417,47.5615615845],"type":"Point"}
}