{
  "type": "Feature",
  "properties": {
    "iso:country":"CH",
    "sg:address":"1376",
    "sg:city":"Goumoens-la-ville",
    "sg:orig_category":"Allgemeiner Hoch U Tiefbau",
    "sg:postcode":"1376",
    "sg:province":"Vaud",
    "wof:name":"Polyartis Sa, \u00e0 Port-louis (ile Maurice), Succursale De Goumoens-la-ville",
    "wof:placetype":"venue"
},
  "geometry": {"coordinates":[6.604554,46.657974],"type":"Point"}
}