{
  "type": "Feature",
  "properties": {
    "iso:country":"CH",
    "sg:address":"Leonhardstrasse 15",
    "sg:city":"Z\u00fcrich",
    "sg:orig_category":"Wohnheime",
    "sg:phone":"+41 16324290",
    "sg:postcode":"8001",
    "sg:province":"Z\u00fcrich",
    "wof:name":"Studentische Wohn-genossenschaft Z\u00fcrich (woko)",
    "wof:placetype":"venue"
},
  "geometry": {"coordinates":[8.5457458496,47.37840271],"type":"Point"}
}