{
  "type": "Feature",
  "properties": {
    "iso:country":"CH",
    "sg:address":"Signalstrasse 8",
    "sg:city":"Aarau",
    "sg:orig_category":"Vermietung U Verpachtung von eigenen Immobilien",
    "sg:phone":"+41 62 824 17 14",
    "sg:postcode":"5000",
    "sg:province":"Aargau",
    "wof:name":"Hans Baumgartner Immobilien Ag",
    "wof:placetype":"venue"
},
  "geometry": {"coordinates":[8.0446968079,47.3814201355],"type":"Point"}
}