{
  "type": "Feature",
  "properties": {
    "iso:country":"CH",
    "sg:address":"Bergstrasse 114 8032 Z\u00fcrich 32 Zust. Postfach",
    "sg:city":"Z\u00fcrich",
    "sg:orig_category":"Herstellung von W\u00e4sche",
    "sg:phone":"+41 56 441 11 64",
    "sg:postcode":"8008",
    "sg:province":"Z\u00fcrich",
    "wof:name":"Seiler Elisabeth, Damenmode",
    "wof:placetype":"venue"
},
  "geometry": {"coordinates":[8.2073869705,47.4840774536],"type":"Point"}
}