{
  "type": "Feature",
  "properties": {
    "iso:country":"CH",
    "sg:address":"Auberge Communale 1149 Berolle. Postfach",
    "sg:city":"Berolle",
    "sg:orig_category":"RESTAURANTS: TEA-ROOMS",
    "sg:postcode":"1149",
    "sg:province":"Vaud",
    "wof:name":"Feuillade Anne Caf\u00e9-restaurant Auberge Communale",
    "wof:placetype":"venue"
},
  "geometry": {"coordinates":[6.3381319046,46.5589561462],"type":"Point"}
}