{
  "type": "Feature",
  "properties": {
    "iso:country":"CH",
    "sg:address":"Route Du Lac",
    "sg:city":"St-saphorin-lavaux",
    "sg:orig_category":"RESTAURANTS: TEA-ROOMS",
    "sg:phone":"+41 21 921 13 27",
    "sg:postcode":"1813",
    "wof:name":"Lambert Norbert.",
    "wof:placetype":"venue"
},
  "geometry": {"coordinates":[6.7959570885,46.4733009338],"type":"Point"}
}