{
  "type": "Feature",
  "properties": {
    "iso:country":"CH",
    "sg:address":"Cond.bosco Grande",
    "sg:city":"Faido",
    "sg:orig_category":"Fachdetailhandel mit pharmazeutischen Produkten",
    "sg:phone":"+41 31 301 21 02",
    "sg:postcode":"6760",
    "sg:province":"Ticino",
    "wof:name":"Br\u00fcckfeld-apotheke, W. M\u00fcller",
    "wof:placetype":"venue"
},
  "geometry": {"coordinates":[7.4368700981,46.9576416016],"type":"Point"}
}