{
  "type": "Feature",
  "properties": {
    "iso:country":"CH",
    "sg:address":"3935",
    "sg:city":"B\u00fcrchen",
    "sg:orig_category":"Primarschulen",
    "sg:postcode":"3935",
    "sg:province":"Valais",
    "wof:name":"Primarschule",
    "wof:placetype":"venue"
},
  "geometry": {"coordinates":[7.8274497986,46.3500709534],"type":"Point"}
}