{
  "type": "Feature",
  "properties": {
    "iso:country":"CH",
    "sg:address":"Seftigenstrasse 21 3007 Bern. Postfach 6",
    "sg:city":"Bern",
    "sg:orig_category":"Herstellung von Anstrichmitteln, Druckfarben U Kitten",
    "sg:phone":"+41 21 634 75 85",
    "sg:postcode":"3007",
    "sg:province":"Bern",
    "wof:name":"Pirrello E.",
    "wof:placetype":"venue"
},
  "geometry": {"coordinates":[6.5881829262,46.5427818298],"type":"Point"}
}