{
  "type": "Feature",
  "properties": {
    "iso:country":"CH",
    "sg:address":"6207",
    "sg:city":"Nottwil",
    "sg:orig_category":"Verwertung von Milch",
    "sg:postcode":"6207",
    "sg:province":"Luzern",
    "wof:name":"K\u00e4sereigenossenschaft B\u00fcren A/a",
    "wof:placetype":"venue"
},
  "geometry": {"coordinates":[7.3718671799,47.1398963928],"type":"Point"}
}