{
  "type": "Feature",
  "properties": {
    "iso:country":"CH",
    "sg:address":"Waisenhausstrasse 6",
    "sg:city":"Herisau",
    "sg:orig_category":"Kaufm\u00e4nnische Berufsschulen",
    "sg:phone":"+41 61 711 96 11",
    "sg:postcode":"9100",
    "sg:province":"Appenzell Ausserrhoden",
    "wof:name":"Kv Reinach",
    "wof:placetype":"venue"
},
  "geometry": {"coordinates":[7.5916571617,47.49659729],"type":"Point"}
}