{
  "type": "Feature",
  "properties": {
    "iso:country":"CH",
    "sg:address":"Via Violino 1",
    "sg:city":"Manno",
    "sg:orig_category":"Herstellung von sonstigen elektrischen Ausr\u00fcstungen",
    "sg:postcode":"6928",
    "sg:province":"Ticino",
    "wof:name":"Dario Pianezze Sam's Pc-shop",
    "wof:placetype":"venue"
},
  "geometry": {"coordinates":[9.2010498047,47.5218238831],"type":"Point"}
}