{
  "type": "Feature",
  "properties": {
    "iso:country":"CH",
    "sg:address":"Schachenallee 29",
    "sg:city":"Aarau",
    "sg:orig_category":"Architektur U Ingenieurb\u00fcros",
    "sg:phone":"+41 62 834 44 00",
    "sg:postcode":"5000",
    "sg:province":"Aargau",
    "wof:name":"Csd Ingenieure Und Geologen Ag",
    "wof:placetype":"venue"
},
  "geometry": {"coordinates":[8.04062,47.39027],"type":"Point"}
}