{
  "type": "Feature",
  "properties": {
    "iso:country":"CH",
    "sg:address":"Bahnhofstrasse 5 8570 Weinfelden. Postfach 14",
    "sg:city":"Weinfelden",
    "sg:orig_category":"Organisationen der Wohlfahrtspflege Religi\u00f6se Vereinigungen",
    "sg:phone":"+41 71 622 44 21",
    "sg:postcode":"8570",
    "sg:province":"Thurgau",
    "wof:name":"Amt F\u00fcr Gemeinde-jugendarbeit",
    "wof:placetype":"venue"
},
  "geometry": {"coordinates":[9.1062488556,47.5674972534],"type":"Point"}
}