{
  "type": "Feature",
  "properties": {
    "iso:country":"CH",
    "sg:address":"Laupenstrasse 49",
    "sg:city":"Bern",
    "sg:orig_category":"Psychiatrische Kliniken",
    "sg:phone":"+41 31 930 91 11",
    "sg:postcode":"3010",
    "sg:province":"Bern",
    "wof:name":"Universit\u00e4re Psychiatrische Dienste Upd",
    "wof:placetype":"venue"
},
  "geometry": {"coordinates":[7.4301328659,46.9474716187],"type":"Point"}
}