{
  "type": "Feature",
  "properties": {
    "iso:country":"CH",
    "sg:address":"Limmattalstrasse 154",
    "sg:city":"Z\u00fcrich",
    "sg:orig_category":"Schwimmb\u00e4der",
    "sg:phone":"+41 13419368",
    "sg:postcode":"8049",
    "sg:province":"Z\u00fcrich",
    "wof:name":"Hallenbad Bl\u00e4si",
    "wof:placetype":"venue"
},
  "geometry": {"coordinates":[8.5014705658,47.4014205933],"type":"Point"}
}