{
  "type": "Feature",
  "properties": {
    "iso:country":"CH",
    "sg:address":"Rheinstrasse 2 4127 Birsfelden. Postfach",
    "sg:city":"Birsfelden",
    "sg:orig_category":"Herstellung von Kakao, Schokoladeerzeugnissen U Zuckerwaren",
    "sg:postcode":"4127",
    "sg:province":"Basel-Landschaft",
    "wof:name":"Chocolat Bernrain Birsfelden Ag",
    "wof:placetype":"venue"
},
  "geometry": {"coordinates":[7.6196990013,47.554473877],"type":"Point"}
}