{
  "type": "Feature",
  "properties": {
    "iso:country":"CH",
    "sg:address":"Zimmelhofweg 5 6314 Unter\u00e4geri. Postfach",
    "sg:city":"Unter\u00e4geri",
    "sg:orig_category":"Unclassifiable Establishments",
    "sg:postcode":"6314",
    "sg:province":"Zug",
    "wof:name":"L\u00f6hri Gartenbau Ag",
    "wof:placetype":"venue"
},
  "geometry": {"coordinates":[8.5760965347,47.1370697021],"type":"Point"}
}