{
  "type": "Feature",
  "properties": {
    "iso:country":"CH",
    "sg:address":"Luzernerstr. 14",
    "sg:city":"Kriens",
    "sg:classifiers":[
        {
            "category":"Banks & Credit Unions",
            "subcategory":"Bank",
            "type":"Services"
        }
    ],
    "sg:phone":"+41 41 208 17 77",
    "sg:postcode":"6010",
    "sg:province":"Luzern",
    "wof:name":"Schweiz. Bankgesellschaft",
    "wof:placetype":"venue"
},
  "geometry": {"coordinates":[8.279838,47.033737],"type":"Point"}
}