{
  "type": "Feature",
  "properties": {
    "iso:country":"CH",
    "sg:address":"Dornacherstrasse 158",
    "sg:city":"Basel",
    "sg:orig_category":"Arztpraxen",
    "sg:phone":"+41 61 361 01 01",
    "sg:postcode":"4053",
    "sg:province":"Basel-Stadt",
    "wof:name":"Dr.med. Mirjam Kummerer \u00c4rztin F\u00fcr Allg.medizin Fmh",
    "wof:placetype":"venue"
},
  "geometry": {"coordinates":[7.592009,47.542194],"type":"Point"}
}