{
  "type": "Feature",
  "properties": {
    "iso:country":"CH",
    "sg:address":"Frauenfelderstrasse 19a",
    "sg:city":"Steckborn",
    "sg:orig_category":"Baugewerbe",
    "sg:phone":"+41 52 761 17 51",
    "sg:postcode":"8266",
    "sg:province":"Thurgau",
    "wof:name":"Pernet Ofen Und Chemin\u00e9ebau/plattenbel\u00e4ge Gmbh",
    "wof:placetype":"venue"
},
  "geometry": {"coordinates":[8.985036,47.664261],"type":"Point"}
}