{
  "type": "Feature",
  "properties": {
    "iso:country":"CH",
    "sg:address":"Maison Rouge Rue De La 15",
    "sg:city":"Yverdon-les-bains",
    "sg:orig_category":"Sanit\u00e4r, Heizungs U L\u00fcftungsinstallation",
    "sg:phone":"+41 21 960 36 42",
    "sg:postcode":"1400",
    "sg:province":"Vaud",
    "wof:name":"Ecuyer Jean-marc",
    "wof:placetype":"venue"
},
  "geometry": {"coordinates":[6.9286928177,46.3625984192],"type":"Point"}
}