{
  "type": "Feature",
  "properties": {
    "iso:country":"CH",
    "sg:address":"Breisacherstrasse 69",
    "sg:city":"Basel",
    "sg:orig_category":"Softwareentwicklung U beratung",
    "sg:phone":"+41 61 692 24 32",
    "sg:postcode":"4057",
    "sg:province":"Basel-Stadt",
    "wof:name":"Bidule Applications, Peter C.",
    "wof:placetype":"venue"
},
  "geometry": {"coordinates":[7.5886178017,47.5671424866],"type":"Point"}
}