{
  "type": "Feature",
  "properties": {
    "iso:country":"CH",
    "sg:address":"Bahnhofplatz 1 Postfach 633",
    "sg:city":"Stans",
    "sg:classifiers":[
        {
            "category":"Farming",
            "subcategory":"Farm",
            "type":"Manufacturing & Wholesale Goods"
        }
    ],
    "sg:phone":"+41 81 307 21 31",
    "sg:postcode":"6371",
    "sg:province":"Nidwalden",
    "sg:tags":[
        "horticulture",
        "agriculture",
        "livestock"
    ],
    "wof:name":"Gensetter Topfpflanzen Ag",
    "wof:placetype":"venue"
},
  "geometry": {"coordinates":[9.56942,46.955429],"type":"Point"}
}