{
  "type": "Feature",
  "properties": {
    "iso:country":"CH",
    "sg:address":"Hodlerstrasse 8",
    "sg:city":"Bern",
    "sg:orig_category":"Internationale Organisationen mit Beh\u00f6rdecharakter",
    "sg:phone":"+41 2242169",
    "sg:postcode":"3012",
    "sg:province":"Bern",
    "wof:name":"Intern.vereinigung Wissensch. Fremdenverkehrsexperten Aiest",
    "wof:placetype":"venue"
},
  "geometry": {"coordinates":[9.3733510971,47.431438446],"type":"Point"}
}