{
  "type": "Feature",
  "properties": {
    "iso:country":"CH",
    "sg:address":"Dorfstrasse 41",
    "sg:city":"Bettlach",
    "sg:orig_category":"Physiotherapie",
    "sg:phone":"+41 32 645 38 28",
    "sg:postcode":"2544",
    "sg:province":"Solothurn",
    "wof:name":"Dirk Ketels Physiotherapie",
    "wof:placetype":"venue"
},
  "geometry": {"coordinates":[7.4236698151,47.2028846741],"type":"Point"}
}