{
  "type": "Feature",
  "properties": {
    "iso:country":"CH",
    "sg:address":"Schibiweg 9",
    "sg:city":"Luzern",
    "sg:orig_category":"Sonstige Kultur U Unterhaltungseinrichtungen Tanzschulen, Tanzlehrer",
    "sg:phone":"+41 41 420 50 20",
    "sg:postcode":"6006",
    "sg:province":"Luzern",
    "wof:name":"Moving Art Claudia C. Steiner Von Arx Dipl. Gymnastikp\u00e4dagogin Sbtg/sfg",
    "wof:placetype":"venue"
},
  "geometry": {"coordinates":[8.31960392,47.0634269714],"type":"Point"}
}