{
  "type": "Feature",
  "properties": {
    "iso:country":"CH",
    "sg:address":"6594",
    "sg:city":"Contone",
    "sg:orig_category":"Grafikateliers, Design",
    "sg:phone":"+41 91 858 26 80",
    "sg:postcode":"6594",
    "sg:province":"Ticino",
    "wof:name":"Franco Weit Pittura D'insegne",
    "wof:placetype":"venue"
},
  "geometry": {"coordinates":[8.9264097214,46.1555290222],"type":"Point"}
}