{
  "type": "Feature",
  "properties": {
    "iso:country":"CH",
    "sg:address":"Birkenweg 28",
    "sg:city":"Belp",
    "sg:orig_category":"Vermittlung U Verwaltung von Immobilien Wirtschaftspr\u00fcfung, Steuerberatung U Treuhand",
    "sg:phone":"+41 55 240 86 54",
    "sg:postcode":"3123",
    "sg:province":"Bern",
    "wof:name":"Ernst Spitzer Immobilien Treuhand",
    "wof:placetype":"venue"
},
  "geometry": {"coordinates":[8.8392601013,47.2569160461],"type":"Point"}
}