{
  "type": "Feature",
  "properties": {
    "iso:country":"CH",
    "sg:address":"Rheinweg 1",
    "sg:city":"Neuhausen",
    "sg:orig_category":"Fachdetailhandel in Verkaufsr\u00e4umen",
    "sg:phone":"+41 52 634 05 71",
    "sg:postcode":"8212",
    "sg:province":"Schaffhausen",
    "wof:name":"Mt Handels Ag",
    "wof:placetype":"venue"
},
  "geometry": {"coordinates":[8.6236944199,47.6923599243],"type":"Point"}
}