{
  "type": "Feature",
  "properties": {
    "iso:country":"CH",
    "sg:address":"Via San Pietro Pambio 23",
    "sg:city":"Paradiso",
    "sg:orig_category":"Maler U Glasergewerbe Malerei",
    "sg:phone":"+41 91 994 49 94",
    "sg:postcode":"6900",
    "sg:province":"Ticino",
    "wof:name":"Dario Sarinelli Impresa Di Pittura",
    "wof:placetype":"venue"
},
  "geometry": {"coordinates":[8.9398202896,45.9889221191],"type":"Point"}
}