{
  "type": "Feature",
  "properties": {
    "iso:country":"CH",
    "sg:address":"Schulweg 6",
    "sg:city":"Boniswil",
    "sg:orig_category":"Sportvereine Eissport Curling",
    "sg:phone":"+41 62 777 19 83",
    "sg:postcode":"5706",
    "sg:province":"Aargau",
    "wof:name":"Curling-club Baden-lake Valley",
    "wof:placetype":"venue"
},
  "geometry": {"coordinates":[8.1873502731,47.3147163391],"type":"Point"}
}