{
  "type": "Feature",
  "properties": {
    "iso:country":"CH",
    "sg:address":"Sch\u00fctzenstrasse 2b",
    "sg:city":"Rorschach",
    "sg:orig_category":"Interessenvertretungen",
    "sg:postcode":"9400",
    "sg:province":"St. Gallen",
    "wof:name":"Kulturstiftung Klaeger Robert",
    "wof:placetype":"venue"
},
  "geometry": {"coordinates":[9.4932060242,47.4703712463],"type":"Point"}
}