{
  "type": "Feature",
  "properties": {
    "iso:country":"CH",
    "sg:address":"Obere Vorstadt 40 5000 Aarau. Postfach",
    "sg:city":"Aarau",
    "sg:orig_category":"Advokaturb\u00fcros Rechtsberatung",
    "sg:phone":"+41 62 832 77 33",
    "sg:postcode":"5000",
    "sg:province":"Aargau",
    "wof:name":"Anwaltskanzlei Weltert Dr.",
    "wof:placetype":"venue"
},
  "geometry": {"coordinates":[8.047606,47.389233],"type":"Point"}
}