{
  "type": "Feature",
  "properties": {
    "iso:country":"CH",
    "sg:address":"Birchlenstrasse 38",
    "sg:city":"D\u00fcbendorf",
    "sg:orig_category":"Einzelhandel mit Automobilen Herstellung von Bereifungen",
    "sg:phone":"+41 18821531",
    "sg:postcode":"8600",
    "sg:province":"Z\u00fcrich",
    "wof:name":"Carstop Pfister & Steinlin",
    "wof:placetype":"venue"
},
  "geometry": {"coordinates":[8.6102390289,47.3992576599],"type":"Point"}
}