{
  "type": "Feature",
  "properties": {
    "iso:country":"CH",
    "sg:address":"Hornbach",
    "sg:city":"Sumiswald",
    "sg:orig_category":"RESTAURANTS: TEA-ROOMS",
    "sg:postcode":"3454",
    "sg:province":"Bern",
    "wof:name":"Gastwirtschaft Hornbach R. + Sch\u00fcpbach-fasel R.",
    "wof:placetype":"venue"
},
  "geometry": {"coordinates":[7.8252100945,47.0478897095],"type":"Point"}
}