{
  "type": "Feature",
  "properties": {
    "addr:full":"Belle-roche Fleurier Neuch\u00e2tel 2114",
    "addr:postcode":"2114",
    "addr:street":"Neucha\u0302Tel",
    "iso:country":"CH",
    "sg:address":"Belle-roche",
    "sg:city":"Fleurier",
    "sg:orig_category":"Campingpl\u00e4tze",
    "sg:phone":"+41 32 861 38 17",
    "sg:postcode":"2114",
    "sg:province":"Neuch\u00e2tel",
    "wof:name":"Camping Tcs",
    "wof:placetype":"venue"
},
  "geometry": {"coordinates":[6.579514,46.906502],"type":"Point"}
}