{
  "type": "Feature",
  "properties": {
    "iso:country":"CH",
    "sg:address":"Dahlienweg 4",
    "sg:city":"Grenchen",
    "sg:orig_category":"Vereine Briefmarkensammler",
    "sg:phone":"+41 78 647 19 70",
    "sg:postcode":"2540",
    "sg:province":"Solothurn",
    "wof:name":"Philatelistenverein Grenchen",
    "wof:placetype":"venue"
},
  "geometry": {"coordinates":[7.3856220245,47.1970062256],"type":"Point"}
}