{
  "type": "Feature",
  "properties": {
    "iso:country":"CH",
    "sg:address":"Feldeggstrasse 69 8008 Z\u00fcrich. Postfach",
    "sg:city":"Z\u00fcrich",
    "sg:orig_category":"Berufsbildende weiterf\u00fchrende Schulen",
    "sg:phone":"+41 14214030",
    "sg:postcode":"8001",
    "sg:province":"Z\u00fcrich",
    "wof:name":"Nbw Netzwerk F\u00fcr Betriebswirtschaftliche Weiterbildung Ag",
    "wof:placetype":"venue"
},
  "geometry": {"coordinates":[8.553953,47.361343],"type":"Point"}
}