{
  "type": "Feature",
  "properties": {
    "iso:country":"CH",
    "sg:address":"Langacherweg 13",
    "sg:city":"Gelterkinden",
    "sg:orig_category":"G\u00fcterbef\u00f6rderung im Strassenverkehr Sonstige Kurierdienste",
    "sg:phone":"+41 61 983 93 00",
    "sg:postcode":"4460",
    "sg:province":"Basel-Landschaft",
    "wof:name":"Gebr. Buser Transporte Express-kurierdienste",
    "wof:placetype":"venue"
},
  "geometry": {"coordinates":[7.8684139252,47.4601821899],"type":"Point"}
}