{
  "type": "Feature",
  "properties": {
    "iso:country":"CH",
    "sg:address":"1822",
    "sg:city":"Chernex",
    "sg:orig_category":"Vorschulen, Kinderg\u00e4rten",
    "sg:postcode":"1822",
    "sg:province":"Vaud",
    "wof:name":"Ecole Enfantine",
    "wof:placetype":"venue"
},
  "geometry": {"coordinates":[6.9113698006,46.4435386658],"type":"Point"}
}