{
  "type": "Feature",
  "properties": {
    "iso:country":"CH",
    "sg:address":"Fatiostrasse 8",
    "sg:city":"Basel",
    "sg:orig_category":"Detailhandel mit Beleuchtungs U Haushaltsgegenst\u00e4nden",
    "sg:phone":"+41 61 321 31 37",
    "sg:postcode":"4056",
    "sg:province":"Basel-Stadt",
    "wof:name":"Walter Lenggenhager Haushaltartikel",
    "wof:placetype":"venue"
},
  "geometry": {"coordinates":[7.579826,47.567307],"type":"Point"}
}