{
  "type": "Feature",
  "properties": {
    "iso:country":"CH",
    "sg:address":"Vogelsang",
    "sg:city":"Rizenbach",
    "sg:orig_category":"Handelsvermittlung U Grosshandel R\u00fcckgewinnung U Vorbereitung f\u00fcr die Wiederverwertung Recycling",
    "sg:phone":"+41 31 751 00 87",
    "sg:postcode":"3206",
    "sg:province":"Bern",
    "wof:name":"Albert Rudolf Alteisen & Metalle",
    "wof:placetype":"venue"
},
  "geometry": {"coordinates":[7.2266149521,46.9413261414],"type":"Point"}
}