{
  "type": "Feature",
  "properties": {
    "iso:country":"CH",
    "sg:address":"Grimselstrasse 12",
    "sg:city":"Z\u00fcrich",
    "sg:orig_category":"Grosshandel mit Nahrungsmitteln, Getr\u00e4nken U Tabakwaren ohne ausgepr\u00e4gten Schwerpunkt",
    "sg:postcode":"8048",
    "sg:province":"Z\u00fcrich",
    "wof:name":"Kandil Gmbh Lebensmittel, Waren; Einkauf, Verkauf Usw",
    "wof:placetype":"venue"
},
  "geometry": {"coordinates":[8.7341480255,47.1973953247],"type":"Point"}
}