{
  "type": "Feature",
  "properties": {
    "iso:country":"CH",
    "sg:address":"Guisan Av. Du G\u00e9n\u00e9ral 9",
    "sg:city":"Sierre",
    "sg:orig_category":"Mechanik",
    "sg:postcode":"3960",
    "sg:province":"Valais",
    "wof:name":"Serrurerie Smef S\u00e0rl",
    "wof:placetype":"venue"
},
  "geometry": {"coordinates":[7.5311450958,46.2924804688],"type":"Point"}
}