{
  "type": "Feature",
  "properties": {
    "iso:country":"CH",
    "sg:address":"Rue De Neuch\u00e2tel 42",
    "sg:city":"Yverdon-les-bains",
    "sg:orig_category":"Zahnarztpraxen",
    "sg:phone":"+41 24 425 76 76",
    "sg:postcode":"1400",
    "sg:province":"Vaud",
    "wof:name":"Dr M\u00e9d. Dent. Vanni Pisa M\u00e9decin-dentiste",
    "wof:placetype":"venue"
},
  "geometry": {"coordinates":[6.6348800659,46.7831764221],"type":"Point"}
}