{
  "type": "Feature",
  "properties": {
    "iso:country":"CH",
    "sg:address":"B\u00fcndtenackerweg 13b",
    "sg:city":"Hochwald",
    "sg:orig_category":"Bauingenieurb\u00fcros Heizung L\u00fcftung Klima",
    "sg:phone":"+41 61 366 86 96",
    "sg:postcode":"4146",
    "sg:province":"Solothurn",
    "wof:name":"Thomas Juhasz Ingenieurb\u00fcro",
    "wof:placetype":"venue"
},
  "geometry": {"coordinates":[7.645513,47.459633],"type":"Point"}
}