{
  "type": "Feature",
  "properties": {
    "iso:country":"CH",
    "sg:address":"Via Della Salina",
    "sg:city":"Muralto",
    "sg:orig_category":"Detailhandel mit M\u00f6beln U Haushaltsgegenst\u00e4nden Verlegen von Fussboden",
    "sg:phone":"+41 91 743 61 69",
    "sg:postcode":"6600",
    "sg:province":"Ticino",
    "wof:name":"Bianda Oliviero",
    "wof:placetype":"venue"
},
  "geometry": {"coordinates":[8.8007802963,46.1715660095],"type":"Point"}
}