{
  "type": "Feature",
  "properties": {
    "iso:country":"CH",
    "sg:address":"Loco Coste Via 11",
    "sg:city":"Gordola",
    "sg:orig_category":"Architektur U Ingenieurb\u00fcros",
    "sg:postcode":"6596",
    "sg:province":"Ticino",
    "wof:name":"Nc Kiln Engineering Sagl",
    "wof:placetype":"venue"
},
  "geometry": {"coordinates":[8.86042,46.180935],"type":"Point"}
}