{
  "type": "Feature",
  "properties": {
    "iso:country":"CH",
    "sg:address":"Balmfluhstrasse 406",
    "sg:city":"G\u00fcnsberg",
    "sg:orig_category":"Bauspenglerei Sanit\u00e4rinstallation",
    "sg:phone":"+41 32 637 24 35",
    "sg:postcode":"4524",
    "sg:province":"Solothurn",
    "wof:name":"Wolfgang Sp\u00f6hrle Sanit\u00e4r Bauspenglerei Heizung",
    "wof:placetype":"venue"
},
  "geometry": {"coordinates":[7.57399,47.254238],"type":"Point"}
}