{
  "type": "Feature",
  "properties": {
    "iso:country":"CH",
    "sg:address":"Schmiedgasse 18 9100 Herisau. Postfach",
    "sg:city":"Herisau",
    "sg:orig_category":"Detailhandel mit B\u00fcchern Sonstiger Detailhandel mit Waren verschiedener Art, Hauptrichtung Nichtnahr",
    "sg:phone":"+41 71 352 16 76",
    "sg:postcode":"9102",
    "sg:province":"Appenzell Ausserrhoden",
    "wof:name":"Kaleidos D\u00fcfte/steine/b\u00fccher/kurse",
    "wof:placetype":"venue"
},
  "geometry": {"coordinates":[9.276844,47.385319],"type":"Point"}
}