{
  "type": "Feature",
  "properties": {
    "iso:country":"CH",
    "sg:address":"Klegi 5 9215 Buhwil. Postfach",
    "sg:city":"Buhwil",
    "sg:orig_category":"Sonstige pers\u00f6nliche Dienstleistungen",
    "sg:postcode":"9215",
    "sg:province":"Thurgau",
    "wof:name":"B\u00fchler Walter A. Dienstleistungen",
    "wof:placetype":"venue"
},
  "geometry": {"coordinates":[9.166519165,47.5265007019],"type":"Point"}
}