{
  "type": "Feature",
  "properties": {
    "iso:country":"CH",
    "sg:address":"Seestrasse 367",
    "sg:city":"Z\u00fcrich",
    "sg:orig_category":"Werbegrafikateliers",
    "sg:phone":"+41 31 971 65 56",
    "sg:postcode":"8038",
    "sg:province":"Z\u00fcrich",
    "wof:name":"Marcus Pfister Grafiker Asg",
    "wof:placetype":"venue"
},
  "geometry": {"coordinates":[7.4375500679,46.926486969],"type":"Point"}
}