{
  "type": "Feature",
  "properties": {
    "iso:country":"CH",
    "sg:address":"B\u00fcrglipark 26",
    "sg:city":"W\u00e4denswil",
    "sg:orig_category":"Informatikdienste Pers\u00f6nliche Dienstleistungen",
    "sg:phone":"+41 17800087",
    "sg:postcode":"8820",
    "sg:province":"Z\u00fcrich",
    "wof:name":"Infacom Gmbh",
    "wof:placetype":"venue"
},
  "geometry": {"coordinates":[8.6652231216,47.2334671021],"type":"Point"}
}