{
  "type": "Feature",
  "properties": {
    "iso:country":"CH",
    "sg:address":"Chrummacherstrasse",
    "sg:city":"Geroldswil",
    "sg:orig_category":"Grosshandel mit Holz U Baustoffen Herstellung von konfektionierten Textilwaren ohne Bekleidung",
    "sg:phone":"+41 17483777",
    "sg:postcode":"8954",
    "sg:province":"Z\u00fcrich",
    "wof:name":"Storenmaterial Ag",
    "wof:placetype":"venue"
},
  "geometry": {"coordinates":[8.4172563553,47.4180412292],"type":"Point"}
}