{
  "type": "Feature",
  "properties": {
    "iso:country":"CH",
    "sg:address":"Dornacherstrasse 258",
    "sg:city":"Basel",
    "sg:orig_category":"Detailhandel mit Waren verschiedener Art, Hauptrichtung Nahrungsmittel",
    "sg:phone":"+41 61 337 90 10",
    "sg:postcode":"4053",
    "sg:province":"Basel-Stadt",
    "wof:name":"Migros-markt Thiersteinerallee",
    "wof:placetype":"venue"
},
  "geometry": {"coordinates":[7.5974187851,47.5404701233],"type":"Point"}
}