{
  "type": "Feature",
  "properties": {
    "iso:country":"CH",
    "sg:address":"Schmidgasse 1 8400 Winterthur. Postfach 947",
    "sg:city":"Winterthur",
    "sg:orig_category":"Detailhandel mit Ton U Bildtr\u00e4gern Detailhandel mit elektrischen Haushalts-,Radio U Fernsehger\u00e4ten s",
    "sg:phone":"+41 52 213 25 25",
    "sg:postcode":"8401",
    "sg:province":"Z\u00fcrich",
    "wof:name":"Musik Hug Ag",
    "wof:placetype":"venue"
},
  "geometry": {"coordinates":[8.7273197174,47.4995613098],"type":"Point"}
}