{
  "type": "Feature",
  "properties": {
    "iso:country":"CH",
    "sg:address":"Riehentorstrasse 15",
    "sg:city":"Basel",
    "sg:orig_category":"Wirtschaftspr\u00fcfung, Steuerberatung U Treuhand",
    "sg:postcode":"4058",
    "sg:province":"Basel-Stadt",
    "wof:name":"Tsc Treuhand Service & Consult Gmbh",
    "wof:placetype":"venue"
},
  "geometry": {"coordinates":[7.595582962,47.5593833923],"type":"Point"}
}