{
  "type": "Feature",
  "properties": {
    "addr:full":"Avenue Jean-marie-musy 8 1700 Freiburg. Postfach Fribourg Fribourg 1702",
    "addr:housenumber":"8",
    "addr:postcode":"1700;postfach;1702",
    "addr:street":"Avenue Jean-Marie-Musy",
    "iso:country":"CH",
    "sg:address":"Avenue Jean-marie-musy 8 1700 Freiburg. Postfach",
    "sg:city":"Fribourg",
    "sg:orig_category":"Detailhandel mit Bekleidung",
    "sg:postcode":"1702",
    "sg:province":"Fribourg",
    "wof:name":"Akajeans - Lumeka Longi-yves",
    "wof:placetype":"venue"
},
  "geometry": {"coordinates":[7.176304,46.806824],"type":"Point"}
}