{
  "type": "Feature",
  "properties": {
    "iso:country":"CH",
    "sg:address":"Mattenweg 80",
    "sg:city":"Vinelz",
    "sg:orig_category":"Sportvereine Turnen",
    "sg:phone":"+41 32 338 33 41",
    "sg:postcode":"3234",
    "sg:province":"Bern",
    "wof:name":"Turnverein Stv Vinelz",
    "wof:placetype":"venue"
},
  "geometry": {"coordinates":[7.1218118668,47.0338554382],"type":"Point"}
}