{
  "type": "Feature",
  "properties": {
    "iso:country":"CH",
    "sg:address":"Lindenberg 5 4000 Basel. Postfach",
    "sg:city":"Basel",
    "sg:orig_category":"Unternehmensberatung",
    "sg:postcode":"4058",
    "sg:province":"Basel-Stadt",
    "wof:name":"Merkur Invest Ag",
    "wof:placetype":"venue"
},
  "geometry": {"coordinates":[7.5944371223,47.5590858459],"type":"Point"}
}