{
  "type": "Feature",
  "properties": {
    "iso:country":"CH",
    "sg:address":"Engelmattstrasse 7",
    "sg:city":"Walchwil",
    "sg:orig_category":"Herstellung von Zahnr\u00e4dern U Antriebselementen Herstellung von sonstigen Maschinen f\u00fcr unspezifische",
    "sg:phone":"+41 41 759 00 66",
    "sg:postcode":"6318",
    "sg:province":"Zug",
    "wof:name":"Kavent Ag",
    "wof:placetype":"venue"
},
  "geometry": {"coordinates":[8.5137968063,47.099521637],"type":"Point"}
}