{
  "type": "Feature",
  "properties": {
    "iso:country":"CH",
    "sg:address":"Waisenhausstrasse 15",
    "sg:city":"W\u00e4denswil",
    "sg:orig_category":"Unternehmensberatung Wirtschaftspr\u00fcfung, Steuerberatung U Treuhand",
    "sg:phone":"+41 17806882",
    "sg:postcode":"8820",
    "sg:province":"Z\u00fcrich",
    "wof:name":"Damowa Gmbh Treuhandb\u00fcro",
    "wof:placetype":"venue"
},
  "geometry": {"coordinates":[8.6741523743,47.2176132202],"type":"Point"}
}