{
  "type": "Feature",
  "properties": {
    "iso:country":"CH",
    "sg:address":"Aarwangenstrasse 12",
    "sg:city":"Wynau",
    "sg:orig_category":"Schmieden",
    "sg:phone":"+41 62 929 24 18",
    "sg:postcode":"4923",
    "sg:province":"Bern",
    "wof:name":"Otto Kohler Schmiede",
    "wof:placetype":"venue"
},
  "geometry": {"coordinates":[7.8058729172,47.261013031],"type":"Point"}
}