{
  "type": "Feature",
  "properties": {
    "iso:country":"CH",
    "sg:address":"Zopfstrasse 15",
    "sg:city":"Remetschwil",
    "sg:orig_category":"Religi\u00f6se Vereinigungen divers Vereine Gemeinn\u00fctzige",
    "sg:phone":"+41 56 496 29 37",
    "sg:postcode":"5453",
    "sg:province":"Aargau",
    "wof:name":"Kath.frauenbund Bellikon",
    "wof:placetype":"venue"
},
  "geometry": {"coordinates":[8.3272123337,47.4057655334],"type":"Point"}
}