{
  "type": "Feature",
  "properties": {
    "iso:country":"CH",
    "sg:address":"Allmendmarkt",
    "sg:city":"Gelterkinden",
    "sg:orig_category":"Drogerien Sonstiger Fachdetailhandel mit Nahrungsmitteln, Getr\u00e4nken U Tabak in Verkaufsr\u00e4umen",
    "sg:phone":"+41 71 245 00 16",
    "sg:postcode":"4460",
    "sg:province":"Basel-Landschaft",
    "wof:name":"Rotmonten-drogerie Vontobel Roland",
    "wof:placetype":"venue"
},
  "geometry": {"coordinates":[9.3793554306,47.4387245178],"type":"Point"}
}