{
  "type": "Feature",
  "properties": {
    "iso:country":"CH",
    "sg:address":"Route Colondalles 61",
    "sg:city":"Montreux",
    "sg:orig_category":"Gartenbau Landschaftsplanungsb\u00fcros U Gartenarchitekturb\u00fcros",
    "sg:phone":"+41 21 691 63 05",
    "sg:postcode":"1820",
    "sg:province":"Vaud",
    "wof:name":"Lohner Denis Cr\u00e9ations De Jardins",
    "wof:placetype":"venue"
},
  "geometry": {"coordinates":[6.9055352211,46.4427452087],"type":"Point"}
}