{
  "type": "Feature",
  "properties": {
    "iso:country":"CH",
    "sg:address":"9052",
    "sg:city":"Niederteufen",
    "sg:orig_category":"Verwaltung der Strafvollzuganstalten Wohnheime",
    "sg:phone":"+41 18711711",
    "sg:postcode":"9052",
    "sg:province":"Appenzell Ausserrhoden",
    "wof:name":"Kant. Strafanstalt P\u00f6schwies",
    "wof:placetype":"venue"
},
  "geometry": {"coordinates":[8.4722661972,47.4315071106],"type":"Point"}
}