{
  "type": "Feature",
  "properties": {
    "addr:full":"Hauptstrasse 22 Frick Aargau 5070",
    "addr:housenumber":"22",
    "addr:postcode":"5070",
    "addr:street":"Hauptstrasse",
    "iso:country":"CH",
    "sg:address":"Hauptstrasse 22",
    "sg:city":"Frick",
    "sg:orig_category":"Architektur U Ingenieurb\u00fcros",
    "sg:phone":"+41 62 824 28 66",
    "sg:postcode":"5070",
    "sg:province":"Aargau",
    "wof:name":"St\u00e4uble + Partner Ag",
    "wof:placetype":"venue"
},
  "geometry": {"coordinates":[8.017159,47.510361],"type":"Point"}
}