{
  "type": "Feature",
  "properties": {
    "addr:full":"Stadthausquai 1 Z\u00fcrich Z\u00fcrich 8001",
    "addr:housenumber":"1",
    "addr:postcode":"8001",
    "addr:street":"Stadthausquai",
    "iso:country":"CH",
    "sg:address":"Stadthausquai 1",
    "sg:city":"Z\u00fcrich",
    "sg:orig_category":"Advokaturb\u00fcros",
    "sg:phone":"+41 12110375",
    "sg:postcode":"8001",
    "sg:province":"Z\u00fcrich",
    "wof:name":"Vogel Rohner Helfenstein & Crameri",
    "wof:placetype":"venue"
},
  "geometry": {"coordinates":[8.541627,47.367474],"type":"Point"}
}