{
  "type": "Feature",
  "properties": {
    "iso:country":"CH",
    "sg:address":"Solenberg 51",
    "sg:city":"Rufi",
    "sg:orig_category":"Unternehmensberatung",
    "sg:postcode":"8723",
    "sg:province":"St. Gallen",
    "wof:name":"Elitea Ag",
    "wof:placetype":"venue"
},
  "geometry": {"coordinates":[8.7323045731,47.2033233643],"type":"Point"}
}