{
  "type": "Feature",
  "properties": {
    "iso:country":"CH",
    "sg:address":"Rue Du Simplon 14",
    "sg:city":"Gen\u00e8ve",
    "sg:orig_category":"Herstellung von konfektionierten Textilwaren ohne Bekleidung Herstellung von sonstigen konfektionier",
    "sg:phone":"+41 71 923 61 41",
    "sg:postcode":"1207",
    "sg:province":"Gen\u00e8ve",
    "wof:name":"Curatolo Blachen U. Verdecke",
    "wof:placetype":"venue"
},
  "geometry": {"coordinates":[9.0477685928,47.4584350586],"type":"Point"}
}