{
  "type": "Feature",
  "properties": {
    "iso:country":"CH",
    "sg:address":"Via Cantonale 45",
    "sg:city":"Comano",
    "sg:orig_category":"HOTELS: MIT RESTAURANT Kongress- and Tagungshotels mit Restaurant",
    "sg:phone":"+41 91 743 01 21",
    "sg:postcode":"6949",
    "sg:province":"Ticino",
    "wof:name":"Albergo Dellavalle",
    "wof:placetype":"venue"
},
  "geometry": {"coordinates":[8.8183546066,46.1844978333],"type":"Point"}
}