{
  "type": "Feature",
  "properties": {
    "iso:country":"CH",
    "sg:address":"Route De Jussy 39 1226 Th\u00f4nex. Postfach",
    "sg:city":"Th\u00f4nex",
    "sg:orig_category":"Sonstige Kultur U Unterhaltungseinrichtungen",
    "sg:phone":"+41 22 796 24 80",
    "sg:postcode":"1226",
    "sg:province":"Gen\u00e8ve",
    "wof:name":"Centre De Loisirs Avanchet-parc",
    "wof:placetype":"venue"
},
  "geometry": {"coordinates":[6.1082777977,46.2217712402],"type":"Point"}
}