{
  "type": "Feature",
  "properties": {
    "iso:country":"CH",
    "sg:address":"Etzwilerstrasse 4",
    "sg:city":"Schlattingen",
    "sg:orig_category":"Schmieden",
    "sg:phone":"+41 61 911 04 65",
    "sg:postcode":"8255",
    "sg:province":"Thurgau",
    "wof:name":"Heiner B\u00fcrgin Hufschmiede",
    "wof:placetype":"venue"
},
  "geometry": {"coordinates":[7.6586809158,47.43334198],"type":"Point"}
}