{
  "type": "Feature",
  "properties": {
    "iso:country":"CH",
    "sg:address":"Sternmatt 9 6010 Kriens. Postfach",
    "sg:city":"Kriens",
    "sg:orig_category":"Herstellung von Teilen U Zubeh\u00f6r f\u00fcr Automobile",
    "sg:postcode":"6010",
    "sg:province":"Luzern",
    "wof:name":"Weitec Schweiz Ag Fahrzeugteile; Handel, Im- U. Export. Liegenschaften Usw",
    "wof:placetype":"venue"
},
  "geometry": {"coordinates":[8.2976646423,47.0295143127],"type":"Point"}
}