{
  "type": "Feature",
  "properties": {
    "iso:country":"CH",
    "sg:address":"Unterdorfstrasse 7",
    "sg:city":"T\u00e4gerwilen",
    "sg:orig_category":"Grosshandel mit Getr\u00e4nken",
    "sg:phone":"+41 71 669 15 87",
    "sg:postcode":"8274",
    "sg:province":"Thurgau",
    "wof:name":"Wolf Getr\u00e4nke Gmbh",
    "wof:placetype":"venue"
},
  "geometry": {"coordinates":[9.1349802017,47.656337738],"type":"Point"}
}