{
  "type": "Feature",
  "properties": {
    "iso:country":"CH",
    "sg:address":"Untere Hauptgasse 32",
    "sg:city":"Thun",
    "sg:orig_category":"RESTAURANTS: TEA-ROOMS",
    "sg:phone":"+41 56 282 58 49",
    "sg:postcode":"3600",
    "sg:province":"Bern",
    "wof:name":"E + R Paradies-betriebe Gmbh",
    "wof:placetype":"venue"
},
  "geometry": {"coordinates":[8.2726507187,47.4952812195],"type":"Point"}
}