{
  "type": "Feature",
  "properties": {
    "iso:country":"CH",
    "sg:address":"8767",
    "sg:city":"Elm",
    "sg:classifiers":[
        {
            "category":"Restaurant",
            "type":"Food & Drink"
        }
    ],
    "sg:phone":"+41 71 995 52 73",
    "sg:postcode":"8767",
    "sg:province":"Glarus",
    "wof:name":"Restaurant Sonne",
    "wof:placetype":"venue"
},
  "geometry": {"coordinates":[9.1889600754,47.2384796143],"type":"Point"}
}