{
  "type": "Feature",
  "properties": {
    "iso:country":"CH",
    "sg:address":"Dammstrasse 32",
    "sg:city":"Windisch",
    "sg:orig_category":"Herstellung von sonstigen keramischen Erzeugnissen f\u00fcr technische Zwecke",
    "sg:phone":"+41 79 205 61 33",
    "sg:postcode":"5210",
    "sg:province":"Aargau",
    "wof:name":"Sahli + Jordi Plattenbel\u00e4ge Gmbh",
    "wof:placetype":"venue"
},
  "geometry": {"coordinates":[8.2284584045,47.4841041565],"type":"Point"}
}