{
  "type": "Feature",
  "properties": {
    "iso:country":"CH",
    "sg:address":"Buzibachstrasse 31",
    "sg:city":"Rothenburg",
    "sg:orig_category":"Event Arrangements, Vip Villages",
    "sg:phone":"+41 41 280 50 10",
    "sg:postcode":"6023",
    "sg:province":"Luzern",
    "wof:name":"India Zelt Luzern",
    "wof:placetype":"venue"
},
  "geometry": {"coordinates":[8.2572145462,47.0911903381],"type":"Point"}
}