{
  "type": "Feature",
  "properties": {
    "iso:country":"CH",
    "sg:address":"Aegeristrasse 52",
    "sg:city":"Zug",
    "sg:orig_category":"Unclassifiable Establishments",
    "sg:postcode":"6300",
    "sg:province":"Zug",
    "wof:name":"Stena Maritime Ag",
    "wof:placetype":"venue"
},
  "geometry": {"coordinates":[8.5194892883,47.1668052673],"type":"Point"}
}