{
  "type": "Feature",
  "properties": {
    "iso:country":"CH",
    "sg:address":"6405",
    "sg:city":"Immensee",
    "sg:orig_category":"Vereine Musik/Blasmusik",
    "sg:phone":"+41 41 855 33 77",
    "sg:postcode":"6405",
    "sg:province":"Schwyz",
    "wof:name":"Musikgesellschaft",
    "wof:placetype":"venue"
},
  "geometry": {"coordinates":[8.4635696411,47.0969085693],"type":"Point"}
}