{
  "type": "Feature",
  "properties": {
    "iso:country":"CH",
    "sg:address":"Route Des Fournaises",
    "sg:city":"Sion",
    "sg:orig_category":"Grosshandel mit landwirtschaftlichen Maschinen U Ger\u00e4ten Grosshandel mit sonstigen Maschinen U Ausr\u00fc",
    "sg:phone":"+41 27 203 34 24",
    "sg:postcode":"1950",
    "sg:province":"Valais",
    "wof:name":"Maurice Jaquet Mat\u00e9riel Forestier Sa",
    "wof:placetype":"venue"
},
  "geometry": {"coordinates":[7.3718547821,46.2235946655],"type":"Point"}
}