{
  "type": "Feature",
  "properties": {
    "iso:country":"CH",
    "sg:address":"Theaterweg 11 7000 Chur. Postfach",
    "sg:city":"Chur",
    "sg:orig_category":"Vermietung U Verpachtung von eigenen Immobilien",
    "sg:postcode":"7000",
    "sg:province":"Graubunden",
    "wof:name":"Immobilien Ramp Ag Pf\u00e4ffikon - Zh",
    "wof:placetype":"venue"
},
  "geometry": {"coordinates":[8.7820320129,47.3670082092],"type":"Point"}
}