{
  "type": "Feature",
  "properties": {
    "iso:country":"CH",
    "sg:address":"August M\u00fcllerstrasse 17",
    "sg:city":"Adliswil",
    "sg:orig_category":"Handelsvermittlung U Grosshandel mit Automobilen Instandhaltung U Reparatur von Automobilen",
    "sg:phone":"+41 61 401 13 03",
    "sg:postcode":"8134",
    "sg:province":"Z\u00fcrich",
    "wof:name":"Buss + Co Fahrzeuge-maschinen",
    "wof:placetype":"venue"
},
  "geometry": {"coordinates":[7.5592570305,47.5188331604],"type":"Point"}
}