{
  "type": "Feature",
  "properties": {
    "iso:country":"CH",
    "sg:address":"Staubishub",
    "sg:city":"Winden",
    "sg:classifiers":[
        {
            "category":"Social Services",
            "subcategory":"Retirement Home",
            "type":"Services"
        }
    ],
    "sg:phone":"+41 71 477 13 26",
    "sg:postcode":"9315",
    "sg:province":"Thurgau",
    "sg:tags":[
        "pflegeheime",
        "u",
        "alters"
    ],
    "wof:name":"Privataltersheim Jean-claude & Sonja Steib",
    "wof:placetype":"venue"
},
  "geometry": {"coordinates":[9.369273,47.528889],"type":"Point"}
}