{
  "type": "Feature",
  "properties": {
    "iso:country":"CH",
    "sg:address":"Hirschg\u00e4sslein 44",
    "sg:city":"Basel",
    "sg:orig_category":"Kosmetikinstitute",
    "sg:phone":"+41 79 218 73 32",
    "sg:postcode":"4051",
    "sg:province":"Basel-Stadt",
    "wof:name":"Joane Martin Institut De Beaut\u00e9 Joane",
    "wof:placetype":"venue"
},
  "geometry": {"coordinates":[6.5743689537,46.5368499756],"type":"Point"}
}