{
  "type": "Feature",
  "properties": {
    "iso:country":"CH",
    "sg:address":"2802",
    "sg:city":"Develier",
    "sg:classifiers":[
        {
            "category":"Restaurant",
            "type":"Food & Drink"
        }
    ],
    "sg:phone":"+41 81 413 69 42",
    "sg:postcode":"2802",
    "sg:province":"Jura",
    "wof:name":"Restaurant Clavadeleralp",
    "wof:placetype":"venue"
},
  "geometry": {"coordinates":[9.8209161758,46.7938766479],"type":"Point"}
}