{
  "type": "Feature",
  "properties": {
    "iso:country":"CH",
    "sg:address":"K\u00f6nizstrasse 21",
    "sg:city":"Bern",
    "sg:orig_category":"Unclassifiable Establishments",
    "sg:postcode":"3008",
    "sg:province":"Bern",
    "wof:name":"Factor7 Marti & Oesch Internet Solutions",
    "wof:placetype":"venue"
},
  "geometry": {"coordinates":[7.4202637672,46.942691803],"type":"Point"}
}