{
  "type": "Feature",
  "properties": {
    "iso:country":"CH",
    "sg:address":"Gemeindehaus",
    "sg:city":"Netstal",
    "sg:orig_category":"Wohnheime",
    "sg:postcode":"8754",
    "sg:province":"Glarus",
    "wof:name":"Zbinden Steinmann Anna-stiftung",
    "wof:placetype":"venue"
},
  "geometry": {"coordinates":[9.057393074,47.0656394958],"type":"Point"}
}