{
  "type": "Feature",
  "properties": {
    "iso:country":"CH",
    "sg:address":"Kempttalstrasse 75",
    "sg:city":"Fehraltorf",
    "sg:orig_category":"Schlossereien",
    "sg:phone":"+41 19541758",
    "sg:postcode":"8320",
    "sg:province":"Z\u00fcrich",
    "wof:name":"Peter Von K\u00e4nel Kunstschlosserei",
    "wof:placetype":"venue"
},
  "geometry": {"coordinates":[8.7531509399,47.3874778748],"type":"Point"}
}