{
  "type": "Feature",
  "properties": {
    "iso:country":"CH",
    "sg:address":"Obere Breiten 6",
    "sg:city":"D\u00e4llikon",
    "sg:orig_category":"Softwareentwicklung U beratung",
    "sg:phone":"+41 18443230",
    "sg:postcode":"8108",
    "sg:province":"Z\u00fcrich",
    "wof:name":"Karin Facchinetti Software-support",
    "wof:placetype":"venue"
},
  "geometry": {"coordinates":[8.4464073181,47.4373054504],"type":"Point"}
}