{
  "type": "Feature",
  "properties": {
    "iso:country":"CH",
    "sg:address":"Lerchenb\u00fchlstrasse 26",
    "sg:city":"Meggen",
    "sg:orig_category":"Unclassifiable Establishments",
    "sg:postcode":"6045",
    "sg:province":"Luzern",
    "wof:name":"Csp Consulting Peyer Stephan / Coaching Und Beratung F\u00fcr Personal- & Organsisationsentwicklung",
    "wof:placetype":"venue"
},
  "geometry": {"coordinates":[8.3627433777,47.040397644],"type":"Point"}
}