{
  "type": "Feature",
  "properties": {
    "iso:country":"CH",
    "sg:address":"Trachslauerstrasse 2",
    "sg:city":"Trachslau",
    "sg:orig_category":"Malerei Tapeziererei",
    "sg:phone":"+41 55 412 86 49",
    "sg:postcode":"8840",
    "sg:province":"Schwyz",
    "wof:name":"Erwin K\u00e4lin Maler-& Tapeziererarbeiten",
    "wof:placetype":"venue"
},
  "geometry": {"coordinates":[8.7268104553,47.0992584229],"type":"Point"}
}