{
  "type": "Feature",
  "properties": {
    "iso:country":"CH",
    "sg:address":"Kapfweg 6",
    "sg:city":"Bubikon",
    "sg:orig_category":"Physiotherapie",
    "sg:phone":"+41 55 243 19 29",
    "sg:postcode":"8608",
    "sg:province":"Z\u00fcrich",
    "wof:name":"Jacob Band Physiotherapie",
    "wof:placetype":"venue"
},
  "geometry": {"coordinates":[8.8192586899,47.2669830322],"type":"Point"}
}