{
  "type": "Feature",
  "properties": {
    "iso:country":"CH",
    "sg:address":"Chemin Des Vignes",
    "sg:city":"Lonay",
    "sg:orig_category":"Vermietung U Verpachtung von eigenen Immobilien",
    "sg:postcode":"1027",
    "sg:province":"Vaud",
    "wof:name":"Parasole Sa",
    "wof:placetype":"venue"
},
  "geometry": {"coordinates":[9.8206882477,46.7937698364],"type":"Point"}
}