{
  "type": "Feature",
  "properties": {
    "iso:country":"CH",
    "sg:address":"W\u00fcrzenbachstrasse 54",
    "sg:city":"Luzern",
    "sg:orig_category":"Sportschulen Wassersport",
    "sg:phone":"+41 41 370 17 33",
    "sg:postcode":"6006",
    "sg:province":"Luzern",
    "wof:name":"Gr\u00e9 Schwitter Segelschule",
    "wof:placetype":"venue"
},
  "geometry": {"coordinates":[8.350892067,47.056968689],"type":"Point"}
}