{
  "type": "Feature",
  "properties": {
    "iso:country":"CH",
    "sg:address":"Fluh 73 Juchlishaus Rossh\u00e4usern",
    "sg:city":"M\u00fchleberg",
    "sg:orig_category":"Detailhandel mit M\u00f6beln Innendekorationsateliers",
    "sg:phone":"+41 21 944 21 24",
    "sg:postcode":"3203",
    "sg:province":"Bern",
    "wof:name":"Antoinette Barbey La Maison Du Dos",
    "wof:placetype":"venue"
},
  "geometry": {"coordinates":[6.864798069,46.4554214478],"type":"Point"}
}