{
  "type": "Feature",
  "properties": {
    "iso:country":"CH",
    "sg:address":"Althardstrasse 5/9",
    "sg:city":"Regensdorf",
    "sg:orig_category":"Herstellung von Ziegeln U sonstiger Baukeramik",
    "sg:postcode":"8105",
    "sg:province":"Z\u00fcrich",
    "wof:name":"Zz Ziegeleien",
    "wof:placetype":"venue"
},
  "geometry": {"coordinates":[8.4743442535,47.4363365173],"type":"Point"}
}