{
  "type": "Feature",
  "properties": {
    "iso:country":"CH",
    "sg:address":"Pflanzschulstrasse 36",
    "sg:city":"Z\u00fcrich",
    "sg:orig_category":"Detailhandel mit Getr\u00e4nken Grosshandel mit Getr\u00e4nken",
    "sg:phone":"+41 56 450 10 80",
    "sg:postcode":"8004",
    "sg:province":"Z\u00fcrich",
    "wof:name":"Weinhaus Blumer",
    "wof:placetype":"venue"
},
  "geometry": {"coordinates":[8.1469917297,47.4370079041],"type":"Point"}
}