{
  "type": "Feature",
  "properties": {
    "iso:country":"CH",
    "sg:address":"Alte Landstrasse 30 8942 Oberrieden. Postfach",
    "sg:city":"Oberrieden",
    "sg:orig_category":"Regionalbanken U Sparkassen",
    "sg:phone":"+41 17132224",
    "sg:postcode":"8942",
    "sg:province":"Z\u00fcrich",
    "wof:name":"Sparkasse Thalwil",
    "wof:placetype":"venue"
},
  "geometry": {"coordinates":[8.5421829224,47.2883377075],"type":"Point"}
}