{
  "type": "Feature",
  "properties": {
    "iso:country":"CH",
    "sg:address":"Schlossstrasse 2 8353 Elgg. Postfach 116",
    "sg:city":"Elgg",
    "sg:orig_category":"Druck ohne Zeitungsdruck Offsetdruck",
    "sg:phone":"+41 52 364 32 44",
    "sg:postcode":"8353",
    "sg:province":"Z\u00fcrich",
    "wof:name":"Druckerei Kunz, Vormals Schollenberger & Kunz",
    "wof:placetype":"venue"
},
  "geometry": {"coordinates":[8.8669843674,47.488445282],"type":"Point"}
}