{
  "type": "Feature",
  "properties": {
    "iso:country":"CH",
    "sg:address":"Postplatz 7078 Lenzerheide/lai. Postfach",
    "sg:city":"Lenzerheide/lai",
    "sg:orig_category":"Detailhandel an Verkaufsst\u00e4nden U auf M\u00e4rkten",
    "sg:phone":"+41 81 384 11 64",
    "sg:postcode":"7078",
    "sg:province":"Graubunden",
    "wof:name":"Bazar Hartmann Ag",
    "wof:placetype":"venue"
},
  "geometry": {"coordinates":[9.557853,46.724579],"type":"Point"}
}