{
  "type": "Feature",
  "properties": {
    "iso:country":"CH",
    "sg:address":"Thurstrasse 9 8500 Frauenfeld. Postfach",
    "sg:city":"Frauenfeld",
    "sg:orig_category":"Nationale Postdienste",
    "sg:phone":"+41 52 720 66 11",
    "sg:postcode":"8503",
    "sg:province":"Thurgau",
    "wof:name":"Die Schweizerische Post Frauenfeld 3 Kurzdorf",
    "wof:placetype":"venue"
},
  "geometry": {"coordinates":[8.8909378052,47.5620727539],"type":"Point"}
}