{
  "type": "Feature",
  "properties": {
    "iso:country":"CH",
    "sg:address":"Rotboden 1",
    "sg:city":"Niederbipp",
    "sg:orig_category":"Herstellung von Papier, Karton U Pappe",
    "sg:phone":"+41 32 633 51 11",
    "sg:postcode":"4704",
    "sg:province":"Bern",
    "wof:name":"Tela-kimberly Switzerland Gmbh",
    "wof:placetype":"venue"
},
  "geometry": {"coordinates":[7.6922550201,47.2706947327],"type":"Point"}
}