{
  "type": "Feature",
  "properties": {
    "iso:country":"CH",
    "sg:address":"Margritstrasse 13",
    "sg:city":"Wallisellen",
    "sg:orig_category":"Grosshandel mit Schuhen",
    "sg:phone":"+41 18300723",
    "sg:postcode":"8304",
    "sg:province":"Z\u00fcrich",
    "wof:name":"Kony Leonhard Schuhvertretungen",
    "wof:placetype":"venue"
},
  "geometry": {"coordinates":[8.5990104675,47.4230804443],"type":"Point"}
}