{
  "type": "Feature",
  "properties": {
    "iso:country":"CH",
    "sg:address":"5054",
    "sg:city":"Moosleerau",
    "sg:orig_category":"Sportvereine Sch\u00fctzen",
    "sg:phone":"+41 62 726 27 33",
    "sg:postcode":"5054",
    "sg:province":"Aargau",
    "wof:name":"Feldsch\u00fctzengesellschaft",
    "wof:placetype":"venue"
},
  "geometry": {"coordinates":[8.0646743774,47.2692070007],"type":"Point"}
}