{
  "type": "Feature",
  "properties": {
    "iso:country":"CH",
    "sg:address":"K\u00fcngoltstrasse 14",
    "sg:city":"Solothurn",
    "sg:orig_category":"Softwareentwicklung U beratung",
    "sg:postcode":"4500",
    "sg:province":"Solothurn",
    "wof:name":"Menth Ag",
    "wof:placetype":"venue"
},
  "geometry": {"coordinates":[7.5251250267,47.2104072571],"type":"Point"}
}