{
  "type": "Feature",
  "properties": {
    "iso:country":"CH",
    "sg:address":"T\u00f6sstalstrasse 69",
    "sg:city":"Turbenthal",
    "sg:orig_category":"Betrieb U technische Hilfsdienste des Kultur U Unterhaltungswesens",
    "sg:phone":"+41 19391437",
    "sg:postcode":"8488",
    "sg:province":"Z\u00fcrich",
    "wof:name":"Oxyd Organisation Sascha Legenstein",
    "wof:placetype":"venue"
},
  "geometry": {"coordinates":[8.843449,47.440617],"type":"Point"}
}