{
  "type": "Feature",
  "properties": {
    "iso:country":"CH",
    "sg:address":"Villarets Chemin Des 16 A 2036 Cormondr\u00e8che. Postfach",
    "sg:city":"Cormondr\u00e8che",
    "sg:orig_category":"Vermietung U Verpachtung von eigenen Immobilien",
    "sg:phone":"+41 32 730 38 57",
    "sg:postcode":"2036",
    "sg:province":"Neuch\u00e2tel",
    "wof:name":"Meseltron",
    "wof:placetype":"venue"
},
  "geometry": {"coordinates":[6.869562149,46.9805488586],"type":"Point"}
}