{
  "type": "Feature",
  "properties": {
    "iso:country":"CH",
    "sg:address":"Schlosshaldenweg 2",
    "sg:city":"Felsberg",
    "sg:orig_category":"Zimmerei, Dachdeckerei, Bauspenglerei U Abdichtung",
    "sg:postcode":"7012",
    "sg:province":"Graubunden",
    "wof:name":"Rieder Erwin",
    "wof:placetype":"venue"
},
  "geometry": {"coordinates":[9.4755487442,46.8467407227],"type":"Point"}
}