{
  "type": "Feature",
  "properties": {
    "iso:country":"CH",
    "sg:address":"M\u00fchlebachstrasse 3 6370 Stans. Postfach 763",
    "sg:city":"Stans",
    "sg:orig_category":"Grosshandel mit Sportartikeln Herstellung von Sportger\u00e4ten",
    "sg:phone":"+41 41 619 16 66",
    "sg:postcode":"6371",
    "sg:province":"Nidwalden",
    "wof:name":"Montana Sport Ag",
    "wof:placetype":"venue"
},
  "geometry": {"coordinates":[8.3584852219,46.9673919678],"type":"Point"}
}