{
  "type": "Feature",
  "properties": {
    "iso:country":"CH",
    "sg:address":"Bachtobelstrasse 50",
    "sg:city":"Z\u00fcrich",
    "sg:orig_category":"Detailhandel mit M\u00f6beln Innendekorationsateliers",
    "sg:phone":"+41 14635945",
    "sg:postcode":"8045",
    "sg:province":"Z\u00fcrich",
    "wof:name":"Reinhard Leuthold Polsterm\u00f6bel Innendekoration",
    "wof:placetype":"venue"
},
  "geometry": {"coordinates":[8.5149869919,47.3608207703],"type":"Point"}
}