{
  "type": "Feature",
  "properties": {
    "addr:full":"Langstrasse 210 Z\u00fcrich Z\u00fcrich 8005",
    "addr:housenumber":"210",
    "addr:postcode":"8005",
    "addr:street":"Langstrasse",
    "iso:country":"CH",
    "sg:address":"Langstrasse 210",
    "sg:city":"Z\u00fcrich",
    "sg:classifiers":[
        {
            "category":"Bars & Pubs",
            "type":"Food & Drink"
        }
    ],
    "sg:phone":"+41 12713856",
    "sg:postcode":"8005",
    "sg:province":"Z\u00fcrich",
    "sg:tags":[
        "restaurant"
    ],
    "wof:name":"Restaurant & Bar Bodega",
    "wof:placetype":"venue"
},
  "geometry": {"coordinates":[8.530109,47.382801],"type":"Point"}
}