{
  "type": "Feature",
  "properties": {
    "iso:country":"CH",
    "sg:address":"En Budron A 15",
    "sg:city":"Mont-sur-lausanne",
    "sg:orig_category":"D\u00e4mmung gegen K\u00e4lte, W\u00e4rme, Schall U Ersch\u00fctterung Herstellung von Bettwaren",
    "sg:phone":"+41 21 653 55 33",
    "sg:postcode":"1052",
    "sg:province":"Vaud",
    "wof:name":"Plafonmetal Sa Fabrication & Pose De Plafonds",
    "wof:placetype":"venue"
},
  "geometry": {"coordinates":[6.6297330856,46.5709915161],"type":"Point"}
}