{
  "type": "Feature",
  "properties": {
    "iso:country":"CH",
    "sg:address":"Hauptstrasse 67",
    "sg:city":"Muntelier",
    "sg:orig_category":"Landesverteidigung, Sozialversicherung \u00d6ffentliche Verwaltung",
    "sg:phone":"+41 26 670 41 50",
    "sg:postcode":"3286",
    "sg:province":"Fribourg",
    "wof:name":"Zivilschutzstelle Muntelier",
    "wof:placetype":"venue"
},
  "geometry": {"coordinates":[7.1250209808,46.9361839294],"type":"Point"}
}