{
  "type": "Feature",
  "properties": {
    "iso:country":"CH",
    "sg:address":"Trevano Via 77",
    "sg:city":"Lugano",
    "sg:orig_category":"RESTAURANTS: TEA-ROOMS",
    "sg:postcode":"6900",
    "sg:province":"Ticino",
    "wof:name":"New Match Sa",
    "wof:placetype":"venue"
},
  "geometry": {"coordinates":[8.9573402405,46.0196266174],"type":"Point"}
}