{
  "type": "Feature",
  "properties": {
    "iso:country":"CH",
    "sg:address":"Chesa Wieser",
    "sg:city":"Zuoz",
    "sg:orig_category":"Non-Classified Establishments",
    "sg:postcode":"7524",
    "sg:province":"Graubunden",
    "wof:name":"Karos Ag",
    "wof:placetype":"venue"
},
  "geometry": {"coordinates":[9.9598398209,46.6027832031],"type":"Point"}
}