{
  "type": "Feature",
  "properties": {
    "iso:country":"CH",
    "sg:address":"Birkenstrasse 105 9443 Widnau. Postfach",
    "sg:city":"Widnau",
    "sg:orig_category":"Finanzierungsinstitutionen",
    "sg:phone":"+41 71 722 51 11",
    "sg:postcode":"9443",
    "sg:province":"St. Gallen",
    "wof:name":"Frei Ag, Finanzierungen",
    "wof:placetype":"venue"
},
  "geometry": {"coordinates":[9.6402168274,47.4136428833],"type":"Point"}
}