{
  "type": "Feature",
  "properties": {
    "addr:full":"Werner Abeggstrasse 54 Riggisberg Bern 3132",
    "addr:housenumber":"54",
    "addr:postcode":"3132",
    "addr:street":"Abeggstrasse",
    "iso:country":"CH",
    "sg:address":"Werner Abeggstrasse 54",
    "sg:city":"Riggisberg",
    "sg:classifiers":[
        {
            "category":"Insurance",
            "subcategory":"Insurance Agent",
            "type":"Services"
        }
    ],
    "sg:phone":"+41 31 809 14 32",
    "sg:postcode":"3132",
    "sg:province":"Bern",
    "sg:tags":[
        "versicherungsagenturen",
        "-broker"
    ],
    "wof:name":"Die Mobiliar Versicherungen & Vorsorge",
    "wof:placetype":"venue"
},
  "geometry": {"coordinates":[7.488482,46.813759],"type":"Point"}
}