{
  "type": "Feature",
  "properties": {
    "addr:full":"Marktgasse 63/65 3011 Bern. Postfach 5325 Bern Bern 3001",
    "addr:housenumber":"63 / 65",
    "addr:postcode":"3011;postfach 5325 bern;3001",
    "addr:street":"Marktgasse",
    "iso:country":"CH",
    "sg:address":"Marktgasse 63/65 3011 Bern. Postfach 5325",
    "sg:city":"Bern",
    "sg:orig_category":"Aktivit\u00e4t der Bankinstitute",
    "sg:phone":"+41 22 908 16 11",
    "sg:postcode":"3001",
    "sg:province":"Bern",
    "wof:name":"Banque Clariden",
    "wof:placetype":"venue"
},
  "geometry": {"coordinates":[6.147694,46.207092],"type":"Point"}
}