{
  "type": "Feature",
  "properties": {
    "iso:country":"CH",
    "sg:address":"Alberich Zwissigstrasse 49",
    "sg:city":"Wettingen",
    "sg:orig_category":"Datenverarbeitungsdienste",
    "sg:phone":"+41 14226523",
    "sg:postcode":"5430",
    "sg:province":"Aargau",
    "wof:name":"Beg Logistik Ag",
    "wof:placetype":"venue"
},
  "geometry": {"coordinates":[8.323583,47.463802],"type":"Point"}
}