{
  "type": "Feature",
  "properties": {
    "iso:country":"CH",
    "sg:address":"Unterdorfstrasse 5",
    "sg:city":"Mels",
    "sg:orig_category":"Detailhandel mit Beleuchtungs U Haushaltsgegenst\u00e4nden Herstellung von sonstigen Maschinen f\u00fcr unspez",
    "sg:phone":"+41 81 723 60 70",
    "sg:postcode":"8887",
    "sg:province":"St. Gallen",
    "wof:name":"Gonzen Apparate Ag, Mels",
    "wof:placetype":"venue"
},
  "geometry": {"coordinates":[9.419947,47.047626],"type":"Point"}
}