{
  "type": "Feature",
  "properties": {
    "iso:country":"CH",
    "sg:address":"Ankerstrasse 53 8004 Z\u00fcrich. Postfach",
    "sg:city":"Z\u00fcrich",
    "sg:orig_category":"Sonstiges Versicherungsgewerbe",
    "sg:postcode":"8001",
    "sg:province":"Z\u00fcrich",
    "wof:name":"Generalagentur Egger Walter A. Generalagentur D Nieuw Rotterdam Versicherungsges",
    "wof:placetype":"venue"
},
  "geometry": {"coordinates":[8.524977684,47.3743743896],"type":"Point"}
}