{
  "type": "Feature",
  "properties": {
    "iso:country":"CH",
    "sg:address":"Neugasse 8 9620 Lichtensteig. Postfach 253",
    "sg:city":"Lichtensteig",
    "sg:orig_category":"Fachdetailhandel in Verkaufsr\u00e4umen Grosshandel mit Sportartikeln",
    "sg:phone":"+41 71 988 14 06",
    "sg:postcode":"9620",
    "sg:province":"St. Gallen",
    "wof:name":"K\u00fcndig Sport Ag",
    "wof:placetype":"venue"
},
  "geometry": {"coordinates":[9.08751297,47.3219909668],"type":"Point"}
}