{
  "type": "Feature",
  "properties": {
    "iso:country":"CH",
    "sg:address":"Herbstackerstrasse 7 B",
    "sg:city":"Seuzach",
    "sg:orig_category":"Non-Classified Establishments",
    "sg:postcode":"8472",
    "sg:province":"Z\u00fcrich",
    "wof:name":"Vogt Baumanagement Ag",
    "wof:placetype":"venue"
},
  "geometry": {"coordinates":[8.7420492172,47.5356025696],"type":"Point"}
}