{
  "type": "Feature",
  "properties": {
    "iso:country":"CH",
    "sg:address":"Av. De Mategnin 71. 1217 Meyrin Case Postale 287",
    "sg:city":"Meyrin",
    "sg:orig_category":"Fachdetailhandel in Verkaufsr\u00e4umen",
    "sg:phone":"+41 71 620 07 15",
    "sg:postcode":"1217",
    "sg:province":"Gen\u00e8ve",
    "wof:name":"Animal-house Ag Tierprodukte Usw.; Handel",
    "wof:placetype":"venue"
},
  "geometry": {"coordinates":[9.1381845474,47.5666694641],"type":"Point"}
}