{
  "type": "Feature",
  "properties": {
    "iso:country":"CH",
    "sg:address":"Cit\u00e9 Vieusseux 9",
    "sg:city":"Gen\u00e8ve",
    "sg:orig_category":"Aktivit\u00e4ten der Generalunternehmen im Baugewerbe Architektur U Ingenieurb\u00fcros",
    "sg:phone":"+41 22 340 15 53",
    "sg:postcode":"1203",
    "sg:province":"Gen\u00e8ve",
    "wof:name":"Artisans Associ\u00e9s S\u00e0rl",
    "wof:placetype":"venue"
},
  "geometry": {"coordinates":[6.120408,46.213131],"type":"Point"}
}