{
  "type": "Feature",
  "properties": {
    "iso:country":"CH",
    "sg:address":"D\u00fcbendorfstrasse 153",
    "sg:city":"Z\u00fcrich",
    "sg:classifiers":[
        {
            "category":"Restaurant",
            "type":"Food & Drink"
        }
    ],
    "sg:phone":"+41 13224843",
    "sg:postcode":"8051",
    "sg:province":"Z\u00fcrich",
    "wof:name":"Restaurant Glattwies",
    "wof:placetype":"venue"
},
  "geometry": {"coordinates":[8.5816402435,47.4017372131],"type":"Point"}
}