{
  "type": "Feature",
  "properties": {
    "iso:country":"CH",
    "sg:address":"Breitestrasse 17b",
    "sg:city":"Seuzach",
    "sg:orig_category":"Mit dem Versicherungsgewerbe verbundene T\u00e4tigkeiten",
    "sg:phone":"+41 52 338 03 65",
    "sg:postcode":"8472",
    "sg:province":"Z\u00fcrich",
    "wof:name":"Ivrem Institut F\u00fcr Banken- & Versicherungsrecht Gmbh",
    "wof:placetype":"venue"
},
  "geometry": {"coordinates":[8.7322769165,47.5352554321],"type":"Point"}
}