{
  "type": "Feature",
  "properties": {
    "iso:country":"CH",
    "sg:address":"Riesbachstrasse 57 8008 Z\u00fcrich. Postfach",
    "sg:city":"Z\u00fcrich",
    "sg:orig_category":"Datenverarbeitungsdienste Unternehmensberatung",
    "sg:phone":"+41 13896989",
    "sg:postcode":"8034",
    "sg:province":"Z\u00fcrich",
    "wof:name":"Fischer Global Services Ltd",
    "wof:placetype":"venue"
},
  "geometry": {"coordinates":[8.555426,47.358334],"type":"Point"}
}