{
  "type": "Feature",
  "properties": {
    "addr:full":"Unterer Quai 35 Biel/bienne Bern 2502",
    "addr:housenumber":"35",
    "addr:postcode":"2502",
    "addr:street":"Unterer Quai",
    "iso:country":"CH",
    "sg:address":"Unterer Quai 35",
    "sg:city":"Biel/bienne",
    "sg:orig_category":"Arztpraxen",
    "sg:phone":"+41 32 323 45 20",
    "sg:postcode":"2502",
    "sg:province":"Bern",
    "wof:name":"Dr.med.fran\u00e7oise Verrey Bass Spezial\u00e4rztin Fmh",
    "wof:placetype":"venue"
},
  "geometry": {"coordinates":[7.244854,47.136532],"type":"Point"}
}