{
  "type": "Feature",
  "properties": {
    "iso:country":"CH",
    "sg:address":"6925",
    "sg:city":"Gentilino",
    "sg:orig_category":"Non-Classified Establishments",
    "sg:phone":"+41 91 994 67 76",
    "sg:postcode":"6925",
    "sg:province":"Ticino",
    "wof:name":"Ristorante Al Bosco",
    "wof:placetype":"venue"
},
  "geometry": {"coordinates":[8.925740242,45.9940795898],"type":"Point"}
}