{
  "type": "Feature",
  "properties": {
    "iso:country":"CH",
    "sg:address":"Chemin Des Verdiers 12",
    "sg:city":"Th\u00f4nex",
    "sg:orig_category":"Physiotherapie",
    "sg:phone":"+41 22 349 40 90",
    "sg:postcode":"1226",
    "sg:province":"Gen\u00e8ve",
    "wof:name":"Physioth\u00e9rapie Verdiers",
    "wof:placetype":"venue"
},
  "geometry": {"coordinates":[6.2159948349,46.2025756836],"type":"Point"}
}