{
  "type": "Feature",
  "properties": {
    "iso:country":"CH",
    "sg:address":"Rue Robert-c\u00e9ard 6",
    "sg:city":"Gen\u00e8ve",
    "sg:orig_category":"Kosmetikinstitute",
    "sg:phone":"+41 21 946 30 50",
    "sg:postcode":"1204",
    "sg:province":"Gen\u00e8ve",
    "wof:name":"Denise Rod Institut De Beaut\u00e9 Denise",
    "wof:placetype":"venue"
},
  "geometry": {"coordinates":[1.8562330008,50.328994751],"type":"Point"}
}