{
  "type": "Feature",
  "properties": {
    "iso:country":"CH",
    "sg:address":"Pfisternweg 11",
    "sg:city":"Baar",
    "sg:orig_category":"RESTAURANTS: TEA-ROOMS",
    "sg:phone":"+41 41 763 02 95",
    "sg:postcode":"6340",
    "sg:province":"Zug",
    "wof:name":"T + T & Osaka Gmbh",
    "wof:placetype":"venue"
},
  "geometry": {"coordinates":[8.5348882675,47.1956329346],"type":"Point"}
}