{
  "type": "Feature",
  "properties": {
    "iso:country":"CH",
    "sg:address":"Saumhalde 5 9100 Herisau. Postfach 1556",
    "sg:city":"Herisau",
    "sg:orig_category":"Wirtschaftspr\u00fcfung, Steuerberatung U Treuhand",
    "sg:phone":"+41 71 354 84 54",
    "sg:postcode":"9102",
    "sg:province":"Appenzell Ausserrhoden",
    "wof:name":"Zellweger Treuhand Und Verwaltungs Ag",
    "wof:placetype":"venue"
},
  "geometry": {"coordinates":[9.3044662476,47.385887146],"type":"Point"}
}