{
  "type": "Feature",
  "properties": {
    "iso:country":"CH",
    "sg:address":"Steinweg 19",
    "sg:city":"Arlesheim",
    "sg:orig_category":"Handelsvermittlung Sonstiger Grosshandel",
    "sg:phone":"+41 61 703 12 21",
    "sg:postcode":"4144",
    "sg:province":"Basel-Landschaft",
    "wof:name":"Frei Trading",
    "wof:placetype":"venue"
},
  "geometry": {"coordinates":[7.6092329025,47.4899291992],"type":"Point"}
}