{
  "type": "Feature",
  "properties": {
    "iso:country":"CH",
    "sg:address":"Route De Coeuve 46",
    "sg:city":"Porrentruy",
    "sg:orig_category":"Herstellung U Zusammensetzung von Uhren",
    "sg:phone":"+41 79 455 29 41",
    "sg:postcode":"2900",
    "sg:province":"Jura",
    "wof:name":"Nelly Bonvallat D\u00e9coration De Boites Montres",
    "wof:placetype":"venue"
},
  "geometry": {"coordinates":[7.086151123,47.4224700928],"type":"Point"}
}