{
  "type": "Feature",
  "properties": {
    "iso:country":"CH",
    "sg:address":"Neustadtgasse 5",
    "sg:city":"Z\u00fcrich",
    "sg:orig_category":"Architektur U Ingenieurb\u00fcros",
    "sg:postcode":"8001",
    "sg:province":"Z\u00fcrich",
    "wof:name":"Grossen-andor Philip, Architekt",
    "wof:placetype":"venue"
},
  "geometry": {"coordinates":[8.545304,47.369732],"type":"Point"}
}