{
  "type": "Feature",
  "properties": {
    "iso:country":"CH",
    "sg:address":"Route Mon-repos 5",
    "sg:city":"Fribourg",
    "sg:orig_category":"Grosshandel mit sonstigen Gebrauchs U Verbrauchsg\u00fctern Spielsalons",
    "sg:phone":"+41 26 481 50 58",
    "sg:postcode":"1700",
    "sg:province":"Fribourg",
    "wof:name":"Automates Et Jeux Proms Sa",
    "wof:placetype":"venue"
},
  "geometry": {"coordinates":[7.1734428406,46.8089256287],"type":"Point"}
}