{
  "type": "Feature",
  "properties": {
    "iso:country":"CH",
    "sg:address":"Bartenheimerstrasse 15",
    "sg:city":"Basel",
    "sg:orig_category":"Architektur U Ingenieurb\u00fcros Architekturb\u00fcros",
    "sg:phone":"+41 61 382 82 03",
    "sg:postcode":"4055",
    "sg:province":"Basel-Stadt",
    "wof:name":"Studer Daniel Architekturb\u00fcro Gmbh",
    "wof:placetype":"venue"
},
  "geometry": {"coordinates":[7.570744,47.560051],"type":"Point"}
}