{
  "type": "Feature",
  "properties": {
    "iso:country":"CH",
    "sg:address":"6745",
    "sg:city":"Giornico",
    "sg:classifiers":[
        {
            "category":"Restaurant",
            "type":"Food & Drink"
        }
    ],
    "sg:phone":"+41 91 864 22 15",
    "sg:postcode":"6745",
    "sg:province":"Ticino",
    "wof:name":"Ristorante Giornico",
    "wof:placetype":"venue"
},
  "geometry": {"coordinates":[8.8754682541,46.4028129578],"type":"Point"}
}