{
  "type": "Feature",
  "properties": {
    "addr:full":"Z.i. Le Tr\u00e9si 6 Pr\u00e9verenges Vaud 1028",
    "addr:housenumber":"6",
    "addr:postcode":"1028",
    "addr:street":"Z.I. Le Tre\u0301Si",
    "iso:country":"CH",
    "sg:address":"Z.i. Le Tr\u00e9si 6",
    "sg:city":"Pr\u00e9verenges",
    "sg:orig_category":"Detailhandel mit B\u00fcchern",
    "sg:phone":"+41 21 811 40 40",
    "sg:postcode":"1028",
    "sg:province":"Vaud",
    "wof:name":"Maison De La Bible Librairie",
    "wof:placetype":"venue"
},
  "geometry": {"coordinates":[6.527225,46.517151],"type":"Point"}
}