{
  "type": "Feature",
  "properties": {
    "iso:country":"CH",
    "sg:address":"Belles Fontaines",
    "sg:city":"L'isle",
    "sg:orig_category":"Detailhandel mit Fleisch U Fleischwaren",
    "sg:postcode":"1148",
    "sg:province":"Vaud",
    "wof:name":"Hohl David",
    "wof:placetype":"venue"
},
  "geometry": {"coordinates":[-93.47286224370001,46.1380386353],"type":"Point"}
}