{
  "type": "Feature",
  "properties": {
    "iso:country":"CH",
    "sg:address":"Breitingerstrasse 35 8002 Z\u00fcrich. Postfach",
    "sg:city":"Z\u00fcrich",
    "sg:orig_category":"Wirtschaftsverb\u00e4nde Industrie, Handel and Gewerbe",
    "sg:phone":"+41 12023386",
    "sg:postcode":"8027",
    "sg:province":"Z\u00fcrich",
    "wof:name":"Verband D.schweiz.lieferanten Kosmet.& Verw.prod.,dr.k.gehri",
    "wof:placetype":"venue"
},
  "geometry": {"coordinates":[8.5316362381,47.3620185852],"type":"Point"}
}