{
  "type": "Feature",
  "properties": {
    "iso:country":"CH",
    "sg:address":"Falknerstrasse 35",
    "sg:city":"Basel",
    "sg:orig_category":"Erbringung von sonstigen Dienstleistungen f\u00fcr Unterhaltung, Erholung U Freizeit",
    "sg:postcode":"4001",
    "sg:province":"Basel-Stadt",
    "wof:name":"Interstate Schmid",
    "wof:placetype":"venue"
},
  "geometry": {"coordinates":[7.5894532204,47.5552520752],"type":"Point"}
}