{
  "type": "Feature",
  "properties": {
    "iso:country":"CH",
    "sg:address":"Schl\u00f6sslistrasse 15 3001 Bern. Postfach 7864",
    "sg:city":"Bern",
    "sg:orig_category":"Interessenvertretungen U sonstige Vereinigungen",
    "sg:phone":"+41 31 381 86 86",
    "sg:postcode":"3001",
    "sg:province":"Bern",
    "wof:name":"Satus Der Sportverband",
    "wof:placetype":"venue"
},
  "geometry": {"coordinates":[7.4309468269,46.9467506409],"type":"Point"}
}