{
  "type": "Feature",
  "properties": {
    "addr:full":"M\u00e4rtplatz 29 Effretikon Z\u00fcrich 8307",
    "addr:housenumber":"29",
    "addr:postcode":"8307",
    "addr:street":"Maertplatz",
    "iso:country":"CH",
    "sg:address":"M\u00e4rtplatz 29",
    "sg:city":"Effretikon",
    "sg:orig_category":"Aktivit\u00e4ten der Krankenschwestern U Hebammen, Hauspflege Organisationen des Gesundheitswesen",
    "sg:phone":"+41 81 413 22 43",
    "sg:postcode":"8307",
    "sg:province":"Z\u00fcrich",
    "wof:name":"Spitex Zentrum Gemeindekrankenpflege",
    "wof:placetype":"venue"
},
  "geometry": {"coordinates":[9.819683,46.794876],"type":"Point"}
}