{
  "type": "Feature",
  "properties": {
    "iso:country":"CH",
    "sg:address":"Hauptstrasse 84",
    "sg:city":"Derendingen",
    "sg:classifiers":[
        {
            "category":"Restaurant",
            "type":"Food & Drink"
        }
    ],
    "sg:phone":"+41 32 681 03 55",
    "sg:postcode":"4552",
    "sg:province":"Solothurn",
    "wof:name":"Restaurant Linde",
    "wof:placetype":"venue"
},
  "geometry": {"coordinates":[7.5863609314,47.1912269592],"type":"Point"}
}