{
  "type": "Feature",
  "properties": {
    "addr:full":"Krankenhausstrasse 7 Oberdiessbach Bern 3672",
    "addr:housenumber":"7",
    "addr:postcode":"3672",
    "addr:street":"Krankenhausstrasse",
    "iso:country":"CH",
    "sg:address":"Krankenhausstrasse 7",
    "sg:city":"Oberdiessbach",
    "sg:classifiers":[
        {
            "category":"Social Services",
            "subcategory":"Retirement Home",
            "type":"Services"
        }
    ],
    "sg:phone":"+41 31 771 03 43",
    "sg:postcode":"3672",
    "sg:province":"Bern",
    "sg:tags":[
        "pflegeheime",
        "u",
        "alters"
    ],
    "wof:name":"Altersheim Oberdiessbach",
    "wof:placetype":"venue"
},
  "geometry": {"coordinates":[7.621241,46.837311],"type":"Point"}
}