{
  "type": "Feature",
  "properties": {
    "iso:country":"CH",
    "sg:address":"Neugasse 12",
    "sg:city":"Mattwil",
    "sg:orig_category":"Einbau von Schreinerwaren",
    "sg:phone":"+41 71 463 22 39",
    "sg:postcode":"8585",
    "sg:province":"Thurgau",
    "wof:name":"Luminati Gastrotechnik",
    "wof:placetype":"venue"
},
  "geometry": {"coordinates":[9.2051029205,47.5796051025],"type":"Point"}
}