{
  "type": "Feature",
  "properties": {
    "iso:country":"CH",
    "sg:address":"St. Jakobs-strasse 11 4052 Basel. Postfach",
    "sg:city":"Basel",
    "sg:orig_category":"Wirtschaftspr\u00fcfung, Steuerberatung U Treuhand",
    "sg:postcode":"4052",
    "sg:province":"Basel-Stadt",
    "wof:name":"Ace Treuhand E. Achermann",
    "wof:placetype":"venue"
},
  "geometry": {"coordinates":[7.5960707664,47.550655365],"type":"Point"}
}