{
  "type": "Feature",
  "properties": {
    "iso:country":"CH",
    "sg:address":"Steinacker Str. 47",
    "sg:city":"Urdorf",
    "sg:classifiers":[
        {
            "category":"Professional",
            "subcategory":"Business Services",
            "type":"Services"
        }
    ],
    "sg:phone":"+41 4117348000",
    "sg:postcode":"8902",
    "sg:province":"Z\u00fcrich",
    "sg:tags":[
        "information",
        "advice",
        "technology",
        "software"
    ],
    "wof:name":"Steria Schweiz Ag",
    "wof:placetype":"venue"
},
  "geometry": {"coordinates":[8.422353,47.395096],"type":"Point"}
}