{
  "type": "Feature",
  "properties": {
    "iso:country":"CH",
    "sg:address":"Heuberg 16 4000 Basel. Postfach",
    "sg:city":"Basel",
    "sg:orig_category":"Allgemeiner Hoch U Tiefbau",
    "sg:postcode":"4051",
    "sg:province":"Basel-Stadt",
    "wof:name":"Borer Albin Ag",
    "wof:placetype":"venue"
},
  "geometry": {"coordinates":[7.58552,47.556274],"type":"Point"}
}