{
  "type": "Feature",
  "properties": {
    "iso:country":"CH",
    "sg:address":"Chemin De Mongevon 6 1023 Crissier Case Postale 29",
    "sg:city":"Crissier",
    "sg:orig_category":"Vermittlung von Immobilien Verwaltung von Immobilien",
    "sg:phone":"+41 21 634 94 84",
    "sg:postcode":"1023",
    "sg:province":"Vaud",
    "wof:name":"Dic D\u00e9veloppement Industriel Et Commercial S.a.",
    "wof:placetype":"venue"
},
  "geometry": {"coordinates":[6.5746688843,46.5478439331],"type":"Point"}
}