{
  "type": "Feature",
  "properties": {
    "iso:country":"CH",
    "sg:address":"Oberkulmerstrasse 5728 Gontenschwil. Postfach 32",
    "sg:city":"Gontenschwil",
    "sg:orig_category":"Grosshandel mit sonstigen Konsumg\u00fctern",
    "sg:phone":"+41 62 767 00 50",
    "sg:postcode":"5728",
    "sg:province":"Aargau",
    "wof:name":"Neogard Ag Garten- & Do It Yourself-artikel / Solar",
    "wof:placetype":"venue"
},
  "geometry": {"coordinates":[8.1441307068,47.2810287476],"type":"Point"}
}