{
  "type": "Feature",
  "properties": {
    "iso:country":"CH",
    "sg:address":"Pfistergasse 25",
    "sg:city":"Winikon",
    "sg:orig_category":"Erschliessung von Grundst\u00fccken",
    "sg:phone":"+41 41 933 09 01",
    "sg:postcode":"6235",
    "sg:province":"Luzern",
    "wof:name":"Baugen.unterdorf Winikon",
    "wof:placetype":"venue"
},
  "geometry": {"coordinates":[8.0469465256,47.2367248535],"type":"Point"}
}