{
  "type": "Feature",
  "properties": {
    "iso:country":"CH",
    "sg:address":"Vordere Hauptgasse 20",
    "sg:city":"Zofingen",
    "sg:orig_category":"Detailhandel mit Uhren U Schmuck",
    "sg:phone":"+41 62 751 25 45",
    "sg:postcode":"4800",
    "sg:province":"Aargau",
    "wof:name":"Daniel Jegge Goldschmiede",
    "wof:placetype":"venue"
},
  "geometry": {"coordinates":[7.9441680908,47.2898712158],"type":"Point"}
}