{
  "type": "Feature",
  "properties": {
    "iso:country":"CH",
    "sg:address":"Montmelley",
    "sg:city":"Echarlens",
    "sg:orig_category":"Unclassifiable Establishments",
    "sg:phone":"+41 79 250 87 23",
    "sg:postcode":"1646",
    "sg:province":"Fribourg",
    "wof:name":"Haymoz Jardin",
    "wof:placetype":"venue"
},
  "geometry": {"coordinates":[7.0758051872,46.6438941956],"type":"Point"}
}