{
  "type": "Feature",
  "properties": {
    "iso:country":"CH",
    "sg:address":"Johannisbergstrasse 10",
    "sg:city":"Jona",
    "sg:orig_category":"Physiotherapie",
    "sg:phone":"+41 55 212 61 17",
    "sg:postcode":"8645",
    "sg:province":"St. Gallen",
    "wof:name":"Patricia Dobes Physiotherapie",
    "wof:placetype":"venue"
},
  "geometry": {"coordinates":[8.8398799896,47.232131958],"type":"Point"}
}