{
  "type": "Feature",
  "properties": {
    "iso:country":"CH",
    "sg:address":"Linthescherstrasse 27 8865 Bilten. Postfach",
    "sg:city":"Bilten",
    "sg:orig_category":"Kalb U Schweine-M\u00e4sterei U Zucht",
    "sg:postcode":"8865",
    "sg:province":"Glarus",
    "wof:name":"Bilta-stern-fleischschwein-genossenschaft",
    "wof:placetype":"venue"
},
  "geometry": {"coordinates":[9.0311899185,47.1502037048],"type":"Point"}
}