{
  "type": "Feature",
  "properties": {
    "iso:country":"CH",
    "sg:address":"Offenburgerstrasse 49",
    "sg:city":"Basel",
    "sg:orig_category":"Malerei",
    "sg:phone":"+41 41 630 46 56",
    "sg:postcode":"4057",
    "sg:province":"Basel-Stadt",
    "wof:name":"Alfons Niederberger Malergesch\u00e4ft",
    "wof:placetype":"venue"
},
  "geometry": {"coordinates":[8.3117179871,46.9954071045],"type":"Point"}
}