{
  "type": "Feature",
  "properties": {
    "iso:country":"CH",
    "sg:address":"Feldstrasse 12",
    "sg:city":"Niederurnen",
    "sg:orig_category":"Fussreflexzonenmassage",
    "sg:phone":"+41 55 610 21 16",
    "sg:postcode":"8867",
    "sg:province":"Glarus",
    "wof:name":"Elisabeth Landolt Relax St\u00fcbli",
    "wof:placetype":"venue"
},
  "geometry": {"coordinates":[9.0503921509,47.1241645813],"type":"Point"}
}