{
  "type": "Feature",
  "properties": {
    "iso:country":"CH",
    "sg:address":"Heinrich Bosshardstrasse 18 8400 Winterthur. Postfach",
    "sg:city":"Winterthur",
    "sg:orig_category":"Grosshandel mit Getr\u00e4nken",
    "sg:postcode":"8400",
    "sg:province":"Z\u00fcrich",
    "wof:name":"Wain.ch Gmbh Wein U. Andere Handelsg\u00fcter; Handel",
    "wof:placetype":"venue"
},
  "geometry": {"coordinates":[8.7555885315,47.4857902527],"type":"Point"}
}