{
  "type": "Feature",
  "properties": {
    "iso:country":"CH",
    "sg:address":"R\u00f6merstrasse 140 8404 Oberwinterthur. Postfach",
    "sg:city":"Winterthur",
    "sg:orig_category":"Softwareentwicklung U beratung",
    "sg:postcode":"8404",
    "sg:province":"Z\u00fcrich",
    "wof:name":"Pc-pro P. Frischknecht",
    "wof:placetype":"venue"
},
  "geometry": {"coordinates":[8.7530727386,47.5065307617],"type":"Point"}
}