{
  "type": "Feature",
  "properties": {
    "iso:country":"CH",
    "sg:address":"Hauptstrasse 22",
    "sg:city":"Muttenz",
    "sg:orig_category":"Detailhandel mit Brillen U anderen Sehhilfen",
    "sg:phone":"+41 31 311 20 40",
    "sg:postcode":"4132",
    "sg:province":"Basel-Landschaft",
    "wof:name":"B\u00f6tschi-optik",
    "wof:placetype":"venue"
},
  "geometry": {"coordinates":[7.4530520439,46.9479560852],"type":"Point"}
}