{
  "type": "Feature",
  "properties": {
    "iso:country":"CH",
    "sg:address":"Cossonay Route De 18 1040 Echallens Case Postale 66",
    "sg:city":"Echallens",
    "sg:orig_category":"Herstellung von sonstigen landwirtschaftlichen Maschinen",
    "sg:phone":"+41 21 881 11 80",
    "sg:postcode":"1040",
    "sg:province":"Vaud",
    "wof:name":"Joseph Cherpit Sa",
    "wof:placetype":"venue"
},
  "geometry": {"coordinates":[6.6246881485,46.6406478882],"type":"Point"}
}