{
  "type": "Feature",
  "properties": {
    "iso:country":"CH",
    "sg:address":"Horwerstrasse 24a 6005 Luzern. Postfach",
    "sg:city":"Luzern",
    "sg:orig_category":"Abdichtung Herstellung von sonstigen Metallwaren",
    "sg:phone":"+41 41 311 11 01",
    "sg:postcode":"6003",
    "sg:province":"Luzern",
    "wof:name":"Abdichtungsbau Durrer Gmbh, Zweigniederlassung Luzern Baubdichtungen; Planung, Ausf\u00fchrung. Dichtungsprodukte; Handel Usw",
    "wof:placetype":"venue"
},
  "geometry": {"coordinates":[8.301601,47.037933],"type":"Point"}
}