{
  "type": "Feature",
  "properties": {
    "iso:country":"CH",
    "sg:address":"Gerichtsstrasse 8",
    "sg:city":"Uster",
    "sg:orig_category":"Detailhandel mit S\u00e4uglings U Kinderbekleidung Herstellung von sonstiger Bekleidung U Bekleidungszube",
    "sg:phone":"+41 19416184",
    "sg:postcode":"8610",
    "sg:province":"Z\u00fcrich",
    "wof:name":"Pinocchio Kindermode Mundwiler Hannelore",
    "wof:placetype":"venue"
},
  "geometry": {"coordinates":[8.7158622742,47.3504676819],"type":"Point"}
}