{
  "type": "Feature",
  "properties": {
    "iso:country":"CH",
    "sg:address":"Oberdorfstrasse.",
    "sg:city":"Flond",
    "sg:orig_category":"Sanit\u00e4r, Heizungs U L\u00fcftungsinstallation Sanit\u00e4rinstallation",
    "sg:phone":"+41 81 925 31 77",
    "sg:postcode":"7137",
    "sg:province":"Graubunden",
    "wof:name":"Saxer Hans.",
    "wof:placetype":"venue"
},
  "geometry": {"coordinates":[9.1650514603,46.7671928406],"type":"Point"}
}