{
  "type": "Feature",
  "properties": {
    "addr:full":"Rue Du Seyon 20 Neuenburg Neuch\u00e2tel 2000",
    "addr:housenumber":"20",
    "addr:postcode":"2000",
    "addr:street":"Rue Du Seyon",
    "iso:country":"CH",
    "sg:address":"Rue Du Seyon 20",
    "sg:city":"Neuenburg",
    "sg:orig_category":"Detailhandel mit B\u00fcchern, Zeitungen, Schreib U Papeteriewaren Detailhandel mit Zeitungen U Zeitschri",
    "sg:phone":"+41 32 725 28 30",
    "sg:postcode":"2000",
    "sg:province":"Neuch\u00e2tel",
    "wof:name":"Kiosque Du Seyon, Schembari Giorgio",
    "wof:placetype":"venue"
},
  "geometry": {"coordinates":[6.928753,46.99231],"type":"Point"}
}