{
  "type": "Feature",
  "properties": {
    "iso:country":"CH",
    "sg:address":"Pflugstrasse 22",
    "sg:city":"Vaduz",
    "sg:orig_category":"Unternehmensberatung Werbeberatung",
    "sg:phone":"+41 75 233 33 26",
    "sg:postcode":"9490",
    "wof:name":"Larona Livers Associates Ltd",
    "wof:placetype":"venue"
},
  "geometry": {"coordinates":[9.5244894028,47.1253585815],"type":"Point"}
}