{
  "type": "Feature",
  "properties": {
    "iso:country":"CH",
    "sg:address":"Aegeristrasse 5",
    "sg:city":"Sattel",
    "sg:orig_category":"Betrieb von Taxis",
    "sg:phone":"+41 26 411 27 10",
    "sg:postcode":"6417",
    "sg:province":"Schwyz",
    "wof:name":"Voyages 2000, J. Sauteur",
    "wof:placetype":"venue"
},
  "geometry": {"coordinates":[7.08347,46.704109],"type":"Point"}
}