{
  "type": "Feature",
  "properties": {
    "iso:country":"CH",
    "sg:address":"Gundeldingerstrasse 468",
    "sg:city":"Basel",
    "sg:orig_category":"Sportvereine Velo Rad-& Motorfahrer-Bund SRB",
    "sg:postcode":"4053",
    "sg:province":"Basel-Stadt",
    "wof:name":"Veloclub Landesgrenze Basel",
    "wof:placetype":"venue"
},
  "geometry": {"coordinates":[7.6013360023,47.5375175476],"type":"Point"}
}