{
  "type": "Feature",
  "properties": {
    "iso:country":"CH",
    "sg:address":"Schulhausstrasse 46",
    "sg:city":"Oberwichtrach",
    "sg:orig_category":"Sportvereine Ski",
    "sg:phone":"+41 31 781 03 74",
    "sg:postcode":"3114",
    "sg:province":"Bern",
    "wof:name":"Skiclub M\u00fcnsingen",
    "wof:placetype":"venue"
},
  "geometry": {"coordinates":[7.5781888962,46.8442955017],"type":"Point"}
}