{
  "type": "Feature",
  "properties": {
    "iso:country":"CH",
    "sg:address":"Oristalstrasse 2",
    "sg:city":"Nuglar",
    "sg:orig_category":"Gasth\u00f6fe/Gasth\u00e4user mit Restaurant",
    "sg:phone":"+41 61 911 09 68",
    "sg:postcode":"4412",
    "sg:province":"Solothurn",
    "wof:name":"Gasthof Waldeck Curry-hus",
    "wof:placetype":"venue"
},
  "geometry": {"coordinates":[7.7080321312,47.4698028564],"type":"Point"}
}