{
  "type": "Feature",
  "properties": {
    "iso:country":"CH",
    "sg:address":"Ziegelmattstrasse 1",
    "sg:city":"Solothurn",
    "sg:classifiers":[
        {
            "category":"Utilities",
            "subcategory":"Telephone",
            "type":"Services"
        }
    ],
    "sg:phone":"+41 32 624 21 11",
    "sg:postcode":"4500",
    "sg:province":"Solothurn",
    "sg:tags":[
        "telecommunication"
    ],
    "wof:name":"Ascom Enterprises Communication Ag",
    "wof:placetype":"venue"
},
  "geometry": {"coordinates":[7.528051,47.213329],"type":"Point"}
}