{
  "type": "Feature",
  "properties": {
    "iso:country":"CH",
    "sg:address":"Bernstrasse 15 3270 Aarberg. Postfach 42",
    "sg:city":"Aarberg",
    "sg:orig_category":"Elektroinstallation",
    "sg:phone":"+41 32 392 37 37",
    "sg:postcode":"3270",
    "sg:province":"Bern",
    "wof:name":"Elektro-glanzmann Ag",
    "wof:placetype":"venue"
},
  "geometry": {"coordinates":[7.2829117775,47.044128418],"type":"Point"}
}