{
  "type": "Feature",
  "properties": {
    "iso:country":"CH",
    "sg:address":"Bahnhofstrasse 92",
    "sg:city":"Uzwil",
    "sg:orig_category":"Detailhandel mit Textilien Detailhandel mit elektrischen Haushaltsger\u00e4ten",
    "sg:phone":"+41 71 911 54 62",
    "sg:postcode":"9240",
    "sg:province":"St. Gallen",
    "wof:name":"Niedermann Bernina-n\u00e4hcenter",
    "wof:placetype":"venue"
},
  "geometry": {"coordinates":[9.0477561951,47.4660110474],"type":"Point"}
}