{
  "type": "Feature",
  "properties": {
    "iso:country":"CH",
    "sg:address":"Bolstelmatte 5",
    "sg:city":"Reigoldswil",
    "sg:orig_category":"Kaminfeger",
    "sg:phone":"+41 61 941 19 77",
    "sg:postcode":"4418",
    "sg:province":"Basel-Landschaft",
    "wof:name":"Kurt Nef Kaminfegergesch\u00e4ft",
    "wof:placetype":"venue"
},
  "geometry": {"coordinates":[7.6939888,47.3997573853],"type":"Point"}
}