{
  "type": "Feature",
  "properties": {
    "iso:country":"CH",
    "sg:address":"Chemin De Sous-le-cr\u00eat 44",
    "sg:city":"Troinex",
    "sg:orig_category":"Herstellung von Oberbekleidung Unternehmensberatung",
    "sg:phone":"+41 22 736 79 36",
    "sg:postcode":"1256",
    "sg:province":"Gen\u00e8ve",
    "wof:name":"B. Entreprises Sa",
    "wof:placetype":"venue"
},
  "geometry": {"coordinates":[6.1517920494,46.1666564941],"type":"Point"}
}