{
  "type": "Feature",
  "properties": {
    "iso:country":"CH",
    "sg:address":"Hardstrasse 34",
    "sg:city":"Wettingen",
    "sg:orig_category":"Herstellung von Elektrizit\u00e4tsverteilungs U schalteinrichtungen",
    "sg:postcode":"5430",
    "sg:province":"Aargau",
    "wof:name":"Indal Ag",
    "wof:placetype":"venue"
},
  "geometry": {"coordinates":[8.3302774429,47.4601974487],"type":"Point"}
}