{
  "type": "Feature",
  "properties": {
    "iso:country":"CH",
    "sg:address":"Dorfstrasse 17",
    "sg:city":"B\u00fcnzen",
    "sg:classifiers":[
        {
            "category":"Restaurant",
            "type":"Food & Drink"
        }
    ],
    "sg:phone":"+41 71 966 41 66",
    "sg:postcode":"5624",
    "sg:province":"Aargau",
    "wof:name":"Restaurant Hirschen",
    "wof:placetype":"venue"
},
  "geometry": {"coordinates":[8.9863128662,47.4497489929],"type":"Point"}
}