{
  "type": "Feature",
  "properties": {
    "iso:country":"CH",
    "sg:address":"Piazza G. Motta 57",
    "sg:city":"Ascona",
    "sg:orig_category":"Detailhandel mit Bekleidung",
    "sg:phone":"+41 52 222 48 30",
    "sg:postcode":"6612",
    "sg:province":"Ticino",
    "wof:name":"Errebi Sa Merci, In Part. Nel Sett. Dell'abbigliamento Ecc.; Produzione, Vendita, Comm.",
    "wof:placetype":"venue"
},
  "geometry": {"coordinates":[8.770656,46.153057],"type":"Point"}
}