{
  "type": "Feature",
  "properties": {
    "iso:country":"CH",
    "sg:address":"Bremgartenstrasse 31 8967 Widen. Postfach",
    "sg:city":"Widen",
    "sg:orig_category":"Interessenvertretungen",
    "sg:postcode":"8967",
    "sg:province":"Aargau",
    "wof:name":"Stiftung Jauch Karl",
    "wof:placetype":"venue"
},
  "geometry": {"coordinates":[8.6441907883,46.8816986084],"type":"Point"}
}