{
  "type": "Feature",
  "properties": {
    "iso:country":"CH",
    "sg:address":"Hochalp",
    "sg:city":"Urn\u00e4sch",
    "sg:classifiers":[
        {
            "category":"Restaurant",
            "type":"Food & Drink"
        }
    ],
    "sg:phone":"+41 55 442 12 09",
    "sg:postcode":"9107",
    "sg:province":"Appenzell Ausserrhoden",
    "wof:name":"Gasthaus Kapelle",
    "wof:placetype":"venue"
},
  "geometry": {"coordinates":[8.8576946259,47.1942138672],"type":"Point"}
}