{
  "type": "Feature",
  "properties": {
    "iso:country":"CH",
    "sg:address":"Stampfenbachstrasse 38 8006 Z\u00fcrich. Postfach",
    "sg:city":"Z\u00fcrich",
    "sg:orig_category":"Grosshandel mit Getreide, Saatgut U Futtermitteln Grosshandel mit Nahrungsmitteln, Getr\u00e4nken U Tabak",
    "sg:phone":"+41 13682580",
    "sg:postcode":"8023",
    "sg:province":"Z\u00fcrich",
    "wof:name":"Comagra Commerz & Agrar-handel Ag",
    "wof:placetype":"venue"
},
  "geometry": {"coordinates":[8.543135643,47.3800926208],"type":"Point"}
}