{
  "type": "Feature",
  "properties": {
    "addr:full":"Chemin De Montolivet 19 Lausanne Vaud 1006",
    "addr:housenumber":"19",
    "addr:postcode":"1006",
    "addr:street":"Chemin De Montolivet",
    "iso:country":"CH",
    "sg:address":"Chemin De Montolivet 19",
    "sg:city":"Lausanne",
    "sg:orig_category":"Arztpraxen",
    "sg:phone":"+41 21 601 15 38",
    "sg:postcode":"1006",
    "sg:province":"Vaud",
    "wof:name":"Dr M\u00e9d. Nicolas Guberan M\u00e9decin Sp\u00e9cialiste",
    "wof:placetype":"venue"
},
  "geometry": {"coordinates":[6.638899,46.511963],"type":"Point"}
}