{
  "type": "Feature",
  "properties": {
    "iso:country":"CH",
    "sg:address":"Im Sch\u00e4fer 2",
    "sg:city":"Dulliken",
    "sg:orig_category":"Instandhaltung U Reparatur von Automobilen",
    "sg:phone":"+41 62 295 30 07",
    "sg:postcode":"4657",
    "sg:province":"Solothurn",
    "wof:name":"Urs Bloch Garage Langfeld",
    "wof:placetype":"venue"
},
  "geometry": {"coordinates":[7.9326200485,47.3538703918],"type":"Point"}
}