{
  "type": "Feature",
  "properties": {
    "iso:country":"CH",
    "sg:address":"Hartbertstrasse 11",
    "sg:city":"Chur",
    "sg:orig_category":"Unclassifiable Establishments",
    "sg:postcode":"7000",
    "sg:province":"Graubunden",
    "wof:name":"Von Arnim Holding Ag",
    "wof:placetype":"venue"
},
  "geometry": {"coordinates":[9.5321893692,46.8534011841],"type":"Point"}
}