{
  "type": "Feature",
  "properties": {
    "iso:country":"CH",
    "sg:address":"Klosbachstrasse 111 8032 Z\u00fcrich. Postfach",
    "sg:city":"Z\u00fcrich",
    "sg:orig_category":"Grosshandel mit Werkzeugmaschinen Grosshandel mit sonstigen Maschinen U Ausr\u00fcstungen f\u00fcr Industrie, ",
    "sg:phone":"+41 56 470 40 30",
    "sg:postcode":"8030",
    "wof:name":"Kaltenbach (schweiz) Gmbh Maschinen, Maschinenanlagen Ger\u00e4te Usw.; Handel",
    "wof:placetype":"venue"
},
  "geometry": {"coordinates":[8.285349,47.456463],"type":"Point"}
}