{
  "type": "Feature",
  "properties": {
    "iso:country":"CH",
    "sg:address":"Schartenstrasse 39 5400 Baden. Postfach 751",
    "sg:city":"Baden",
    "sg:orig_category":"Herstellung von sonstigen Nahrungsmitteln",
    "sg:phone":"+41 56 282 27 28",
    "sg:postcode":"5400",
    "sg:province":"Aargau",
    "wof:name":"Miel De Provence B\u00e9atrice Stocker",
    "wof:placetype":"venue"
},
  "geometry": {"coordinates":[8.317193985,47.4723205566],"type":"Point"}
}