{
  "type": "Feature",
  "properties": {
    "iso:country":"CH",
    "sg:address":"Cantonale Via 36",
    "sg:city":"Pregassona",
    "sg:orig_category":"Non-Classified Establishments",
    "sg:postcode":"6963",
    "sg:province":"Ticino",
    "wof:name":"Dimensione Habitat Di Manzulli Angelica",
    "wof:placetype":"venue"
},
  "geometry": {"coordinates":[8.9760942459,46.0212974548],"type":"Point"}
}