{
  "type": "Feature",
  "properties": {
    "iso:country":"CH",
    "sg:address":"Lyss-strasse 11",
    "sg:city":"Aarberg",
    "sg:orig_category":"Detailhandel mit medizinischen U orthop\u00e4dischen Artikeln",
    "sg:phone":"+41 32 392 56 80",
    "sg:postcode":"3270",
    "sg:province":"Bern",
    "wof:name":"Rehabil, Bilat Paul",
    "wof:placetype":"venue"
},
  "geometry": {"coordinates":[7.2779340744,47.0462799072],"type":"Point"}
}