{
  "type": "Feature",
  "properties": {
    "iso:country":"CH",
    "sg:address":"Au Sablion 8",
    "sg:city":"Grolley",
    "sg:orig_category":"Sportvereine Flug Aero-Club",
    "sg:phone":"+41 26 475 23 00",
    "sg:postcode":"1772",
    "sg:province":"Fribourg",
    "wof:name":"Gpe De Mod\u00e8les R\u00e9duits Aecs",
    "wof:placetype":"venue"
},
  "geometry": {"coordinates":[7.0630421638,46.8325653076],"type":"Point"}
}