{
  "type": "Feature",
  "properties": {
    "iso:country":"CH",
    "sg:address":"G\u00fcterstrasse 125 4053 Basel. Postfach",
    "sg:city":"Basel",
    "sg:orig_category":"Herstellung von K\u00fcchenm\u00f6beln",
    "sg:postcode":"4051",
    "sg:province":"Basel-Stadt",
    "wof:name":"Ferdinand Catering Vermietung Gmbh Cateringmaterial Wie K\u00fcchenauto, Zelte, K\u00fcchenmaschinen Usw.; Vermietung",
    "wof:placetype":"venue"
},
  "geometry": {"coordinates":[8.5799741745,47.3181686401],"type":"Point"}
}