{
  "type": "Feature",
  "properties": {
    "iso:country":"CH",
    "sg:address":"Chemin De La Planchette 3-5",
    "sg:city":"Aigle",
    "sg:orig_category":"Fachdetailhandel mit pharmazeutischen Produkten",
    "sg:phone":"+41 24 467 04 04",
    "sg:postcode":"1860",
    "sg:province":"Vaud",
    "wof:name":"Pharmacie De La Planchette",
    "wof:placetype":"venue"
},
  "geometry": {"coordinates":[6.9596939087,46.3198661804],"type":"Point"}
}