{
  "type": "Feature",
  "properties": {
    "iso:country":"CH",
    "sg:address":"M\u00f6hlinstrasse 3",
    "sg:city":"Maisprach",
    "sg:orig_category":"Wasserversorgung",
    "sg:phone":"+41 61 841 26 66",
    "sg:postcode":"4464",
    "sg:province":"Basel-Landschaft",
    "wof:name":"Grob Kalkschutz Ag Elektronik-kalkschutzanlagen",
    "wof:placetype":"venue"
},
  "geometry": {"coordinates":[7.8467020988,47.5248680115],"type":"Point"}
}