{
  "type": "Feature",
  "properties": {
    "iso:country":"CH",
    "sg:address":"Talackerstrasse 13 8152 Opfikon. Postfach",
    "sg:city":"Opfikon",
    "sg:orig_category":"Sonstiges Textilgewerbe",
    "sg:phone":"+41 18281616",
    "sg:postcode":"8152",
    "sg:province":"Z\u00fcrich",
    "wof:name":"Bollag-guggenheim & Co Ag",
    "wof:placetype":"venue"
},
  "geometry": {"coordinates":[8.5612001419,47.4258499146],"type":"Point"}
}