{
  "type": "Feature",
  "properties": {
    "addr:full":"Am Stausee 23 Birsfelden Basel-Landschaft 4127",
    "addr:housenumber":"23",
    "addr:postcode":"4127",
    "addr:street":"Am Stausee",
    "iso:country":"CH",
    "sg:address":"Am Stausee 23",
    "sg:city":"Birsfelden",
    "sg:orig_category":"Buchf\u00fchrung Wirtschaftspr\u00fcfung, Steuerberatung U Treuhand",
    "sg:phone":"+41 61 373 89 30",
    "sg:postcode":"4127",
    "sg:province":"Basel-Landschaft",
    "wof:name":"Inova Treuhand Gmbh",
    "wof:placetype":"venue"
},
  "geometry": {"coordinates":[7.631329,47.557182],"type":"Point"}
}