{
  "type": "Feature",
  "properties": {
    "iso:country":"CH",
    "sg:address":"Teatro Piazza 4",
    "sg:city":"Bellinzona",
    "sg:orig_category":"Detailhandel mit medizinischen U orthop\u00e4dischen Artikeln",
    "sg:phone":"+41 91 825 81 83",
    "sg:postcode":"6500",
    "sg:province":"Ticino",
    "wof:name":"Sonora Sa",
    "wof:placetype":"venue"
},
  "geometry": {"coordinates":[9.0241193771,46.1944618225],"type":"Point"}
}