{
  "type": "Feature",
  "properties": {
    "iso:country":"CH",
    "sg:address":"Grotweg 30",
    "sg:city":"Lengnau",
    "sg:orig_category":"Stamping Foils",
    "sg:phone":"+41 32 653 37 37",
    "sg:postcode":"2543",
    "sg:province":"Bern",
    "wof:name":"Star-foil Heisspr\u00e4gefolien",
    "wof:placetype":"venue"
},
  "geometry": {"coordinates":[7.3749260902,47.1880645752],"type":"Point"}
}