{
  "type": "Feature",
  "properties": {
    "iso:country":"CH",
    "sg:address":"Rue De La Servette 43",
    "sg:city":"Gen\u00e8ve",
    "sg:orig_category":"Detailhandel mit Fahrr\u00e4dern",
    "sg:phone":"+41 22 733 17 92",
    "sg:postcode":"1202",
    "sg:province":"Gen\u00e8ve",
    "wof:name":"Fran\u00e7ois Monnoyeur Cycles",
    "wof:placetype":"venue"
},
  "geometry": {"coordinates":[6.1357150078,46.2107009888],"type":"Point"}
}