{
  "type": "Feature",
  "properties": {
    "iso:country":"CH",
    "sg:address":"Baselmattweg 68",
    "sg:city":"Allschwil",
    "sg:orig_category":"Innendekorationsateliers",
    "sg:phone":"+41 79 358 24 16",
    "sg:postcode":"4123",
    "sg:province":"Basel-Landschaft",
    "wof:name":"Xaver Heinzer Tapezierergesch\u00e4ft",
    "wof:placetype":"venue"
},
  "geometry": {"coordinates":[7.5490889549,47.554889679],"type":"Point"}
}