{
  "type": "Feature",
  "properties": {
    "addr:full":"Im Winkel 6 8240 Thayngen. Postfach Thayngen Schaffhausen 8240",
    "addr:housenumber":"6",
    "addr:postcode":"8240 thayngen. postfach;8240",
    "addr:street":"Im Winkel",
    "iso:country":"CH",
    "sg:address":"Im Winkel 6 8240 Thayngen. Postfach",
    "sg:city":"Thayngen",
    "sg:orig_category":"Lagerh\u00e4user, G\u00fcterumschlag, Verteilzentren",
    "sg:phone":"+41 52 649 31 51",
    "sg:postcode":"8240",
    "sg:province":"Schaffhausen",
    "wof:name":"Lagerhaus Gmbh Thayngen",
    "wof:placetype":"venue"
},
  "geometry": {"coordinates":[8.711932,47.746979],"type":"Point"}
}