{
  "type": "Feature",
  "properties": {
    "iso:country":"CH",
    "sg:address":"Waffenplatzstrasse 47",
    "sg:city":"Z\u00fcrich",
    "sg:orig_category":"Detailhandel mit Fahrr\u00e4dern Handel mit Motorr\u00e4dern, Teilen U Zubeh\u00f6r Instandhaltung U Reparatur von ",
    "sg:phone":"+41 12014650",
    "sg:postcode":"8002",
    "sg:province":"Z\u00fcrich",
    "wof:name":"Fritz Grob 2-rad-shop",
    "wof:placetype":"venue"
},
  "geometry": {"coordinates":[8.5270223618,47.3592720032],"type":"Point"}
}