{
  "type": "Feature",
  "properties": {
    "iso:country":"CH",
    "sg:address":"Ringstrasse 30",
    "sg:city":"Olten",
    "sg:classifiers":[
        {
            "category":"Professional",
            "subcategory":"Management & Consulting",
            "type":"Services"
        }
    ],
    "sg:phone":"+41 62 205 20 40",
    "sg:postcode":"4600",
    "sg:province":"Solothurn",
    "sg:tags":[
        "hr",
        "resource",
        "consultancy",
        "human"
    ],
    "wof:name":"Job And Jobs Ag",
    "wof:placetype":"venue"
},
  "geometry": {"coordinates":[7.8992400169,47.351184845],"type":"Point"}
}