{
  "type": "Feature",
  "properties": {
    "iso:country":"CH",
    "sg:address":"Industriestrasse 5",
    "sg:city":"Gossau",
    "sg:classifiers":[
        {
            "category":"Bars & Pubs",
            "subcategory":"Lounge",
            "type":"Food & Drink"
        }
    ],
    "sg:phone":"+41 19365100",
    "sg:postcode":"8625",
    "sg:province":"Z\u00fcrich",
    "sg:tags":[
        "shelf",
        "all-purpose"
    ],
    "wof:name":"Pendt Ag",
    "wof:placetype":"venue"
},
  "geometry": {"coordinates":[8.751088,47.305134],"type":"Point"}
}