{
  "type": "Feature",
  "properties": {
    "iso:country":"CH",
    "sg:address":"Bahnhofplatz 3",
    "sg:city":"Stans",
    "sg:orig_category":"Nationale Postdienste",
    "sg:phone":"+41 41 618 31 11",
    "sg:postcode":"6370",
    "sg:province":"Nidwalden",
    "wof:name":"Die Schweizerische Post",
    "wof:placetype":"venue"
},
  "geometry": {"coordinates":[8.3670463562,46.9586791992],"type":"Point"}
}