{
  "type": "Feature",
  "properties": {
    "iso:country":"CH",
    "sg:address":"Constant Place Benjamin- 2",
    "sg:city":"Lausanne",
    "sg:orig_category":"Non-Classified Establishments",
    "sg:phone":"+41 41 872 08 72",
    "sg:postcode":"1003",
    "sg:province":"Vaud",
    "wof:name":"Gamma Reto, Office F\u00fcr Kommunikation",
    "wof:placetype":"venue"
},
  "geometry": {"coordinates":[8.6441907883,46.8816986084],"type":"Point"}
}