{
  "type": "Feature",
  "properties": {
    "iso:country":"CH",
    "sg:address":"Webergasse 35",
    "sg:city":"Schaffhausen",
    "sg:orig_category":"Detailhandel mit Lederwaren U Reiseartikeln Detailhandel mit Schuhen U Lederwaren",
    "sg:phone":"+41 56 633 12 32",
    "sg:postcode":"8200",
    "sg:province":"Schaffhausen",
    "wof:name":"Modes Silvia Lederwaren Silvia K\u00fcttel",
    "wof:placetype":"venue"
},
  "geometry": {"coordinates":[8.3426809311,47.3510169983],"type":"Point"}
}