{
  "type": "Feature",
  "properties": {
    "iso:country":"CH",
    "sg:address":"Axenstrasse 3 6440 Brunnen. Postfach",
    "sg:city":"Brunnen",
    "sg:orig_category":"Softwareentwicklung U beratung",
    "sg:postcode":"6440",
    "sg:province":"Schwyz",
    "wof:name":"Causa Net Ag Evidenzbasierte Informations- U. Kommunikationsl\u00f6sungen, Internetportale Im Gesundheitswesen, Behandlungsmethoden, Heilmittel, Pflegeprodukte; Entwicklung, Vertrieb Usw",
    "wof:placetype":"venue"
},
  "geometry": {"coordinates":[8.6063709259,46.9937210083],"type":"Point"}
}