{
  "type": "Feature",
  "properties": {
    "iso:country":"CH",
    "sg:address":"Landstrasse 33 8450 Andelfingen. Postfach 374",
    "sg:city":"Andelfingen",
    "sg:classifiers":[
        {
            "category":"Insurance",
            "subcategory":"Insurance Agent",
            "type":"Services"
        }
    ],
    "sg:phone":"+41 52 317 16 17",
    "sg:postcode":"8450",
    "sg:province":"Z\u00fcrich",
    "sg:tags":[
        "versicherungsagenturen",
        "-broker"
    ],
    "wof:name":"Z\u00fcrich-versicherungen Agentur Wyland",
    "wof:placetype":"venue"
},
  "geometry": {"coordinates":[8.6789178848,47.5924797058],"type":"Point"}
}