{
  "type": "Feature",
  "properties": {
    "iso:country":"CH",
    "sg:address":"Rue De La Gare 28",
    "sg:city":"Chez-le-bart",
    "sg:orig_category":"D\u00e9colletagen and Schrauben Herstellung",
    "sg:phone":"+41 32 968 70 22",
    "sg:postcode":"2025",
    "sg:province":"Neuch\u00e2tel",
    "wof:name":"Roland Egger Atelier De D\u00e9colletages",
    "wof:placetype":"venue"
},
  "geometry": {"coordinates":[6.8305921555,47.1087875366],"type":"Point"}
}