{
  "type": "Feature",
  "properties": {
    "iso:country":"CH",
    "sg:address":"Ch. Du Lizet 8",
    "sg:city":"Echandens",
    "sg:orig_category":"Fachdetailhandel in Verkaufsr\u00e4umen",
    "sg:postcode":"1026",
    "sg:province":"Vaud",
    "wof:name":"Widmer Uhren Und Schmuck Uhren, Schmuck, Zinn, Silberwaren; Handel",
    "wof:placetype":"venue"
},
  "geometry": {"coordinates":[9.2496547699,47.415977478],"type":"Point"}
}