{
  "type": "Feature",
  "properties": {
    "iso:country":"CH",
    "sg:address":"1856",
    "sg:city":"Corbeyrier",
    "sg:orig_category":"Vorschulen, Kinderg\u00e4rten",
    "sg:phone":"+41 26 470 24 70",
    "sg:postcode":"1856",
    "sg:province":"Vaud",
    "wof:name":"Ecole Enfantine Coll\u00e8ge Communal",
    "wof:placetype":"venue"
},
  "geometry": {"coordinates":[6.9581289291,46.3499412537],"type":"Point"}
}