{
  "type": "Feature",
  "properties": {
    "iso:country":"CH",
    "sg:address":"R\u00e9chy Route De",
    "sg:city":"R\u00e9chy",
    "sg:orig_category":"Bauspenglerei Zimmerei, Dachdeckerei, Bauspenglerei U Abdichtung",
    "sg:phone":"+41 27 458 22 49",
    "sg:postcode":"3966",
    "sg:province":"Valais",
    "wof:name":"Perruchoud Lucien",
    "wof:placetype":"venue"
},
  "geometry": {"coordinates":[7.505455,46.265469],"type":"Point"}
}