{
  "type": "Feature",
  "properties": {
    "iso:country":"CH",
    "sg:address":"Reidholzstr. 1",
    "sg:city":"Richterswil",
    "sg:orig_category":"Wirtschaft U Handel, Landwirtschaft",
    "sg:phone":"+41 17867236",
    "sg:postcode":"8805",
    "sg:province":"Z\u00fcrich",
    "wof:name":"Tr\u00fcb Ag Horgen Gartenbau",
    "wof:placetype":"venue"
},
  "geometry": {"coordinates":[8.691466,47.211697],"type":"Point"}
}