{
  "type": "Feature",
  "properties": {
    "iso:country":"CH",
    "sg:address":"General-wille-str. 201",
    "sg:city":"Feldmeilen",
    "sg:classifiers":[
        {
            "category":"Manufacturing",
            "subcategory":"Metals",
            "type":"Manufacturing & Wholesale Goods"
        }
    ],
    "sg:phone":"+41 22 794 77 66",
    "sg:postcode":"8706",
    "sg:province":"Z\u00fcrich",
    "sg:tags":[
        "metallurgy",
        "-",
        "metalworking",
        "metallic",
        "machine",
        "engineering",
        "finished",
        "mechanical"
    ],
    "wof:name":"Jean Gallay Sa",
    "wof:placetype":"venue"
},
  "geometry": {"coordinates":[6.1080188751,46.1700782776],"type":"Point"}
}