{
  "type": "Feature",
  "properties": {
    "iso:country":"CH",
    "sg:address":"Mattenweg 3",
    "sg:city":"K\u00f6niz",
    "sg:orig_category":"Betrieb U technische Hilfsdienste des Kultur U Unterhaltungswesens",
    "sg:phone":"+41 12559987",
    "sg:postcode":"3098",
    "sg:province":"Bern",
    "wof:name":"Bloch Werner Video-technik Und Studio.",
    "wof:placetype":"venue"
},
  "geometry": {"coordinates":[8.545028,47.323189],"type":"Point"}
}