{
  "type": "Feature",
  "properties": {
    "iso:country":"CH",
    "sg:address":"Habsburgerstrasse 2",
    "sg:city":"Rheinfelden",
    "sg:orig_category":"Unclassifiable Establishments",
    "sg:postcode":"4310",
    "sg:province":"Aargau",
    "wof:name":"Niederberger Internet Services N.i.s",
    "wof:placetype":"venue"
},
  "geometry": {"coordinates":[7.7678189278,47.5468177795],"type":"Point"}
}