{
  "type": "Feature",
  "properties": {
    "iso:country":"CH",
    "sg:address":"Achereggstrasse 2",
    "sg:city":"Stansstad",
    "sg:orig_category":"Softwareentwicklung U beratung",
    "sg:phone":"+41 71 385 46 66",
    "sg:postcode":"6362",
    "sg:province":"Nidwalden",
    "wof:name":"S & S Cad Systeme, Sch\u00f6nenberger",
    "wof:placetype":"venue"
},
  "geometry": {"coordinates":[9.2549133301,47.4134712219],"type":"Point"}
}