{
  "type": "Feature",
  "properties": {
    "iso:country":"CH",
    "sg:address":"3618",
    "sg:city":"S\u00fcderen",
    "sg:orig_category":"Schulpflegen",
    "sg:postcode":"3618",
    "sg:province":"Bern",
    "wof:name":"Primarschulkommission Der Gemeinde Waldegg",
    "wof:placetype":"venue"
},
  "geometry": {"coordinates":[7.8132300377,46.7012710571],"type":"Point"}
}