{
  "type": "Feature",
  "properties": {
    "iso:country":"CH",
    "sg:address":"Limmatquai 32",
    "sg:city":"Z\u00fcrich",
    "sg:orig_category":"Fachdetailhandel in Verkaufsr\u00e4umen",
    "sg:phone":"+41 81 413 24 44",
    "sg:postcode":"8001",
    "sg:province":"Z\u00fcrich",
    "wof:name":"Augenoptik Schneider",
    "wof:placetype":"venue"
},
  "geometry": {"coordinates":[9.8225479126,46.7978477478],"type":"Point"}
}