{
  "type": "Feature",
  "properties": {
    "iso:country":"CH",
    "sg:address":"Winterhalde",
    "sg:city":"Wintersingen",
    "sg:orig_category":"Sportvereine Sch\u00fctzen Pistolen-& Gewehr",
    "sg:phone":"+41 61 971 80 48",
    "sg:postcode":"4451",
    "sg:province":"Basel-Landschaft",
    "wof:name":"Felsch\u00fctzenges.wintersingen",
    "wof:placetype":"venue"
},
  "geometry": {"coordinates":[7.8255090714,47.4990081787],"type":"Point"}
}