{
  "type": "Feature",
  "properties": {
    "addr:full":"2517 Diesse Bern 2517",
    "addr:housenumber":"2517",
    "addr:postcode":"2517",
    "iso:country":"CH",
    "sg:address":"2517",
    "sg:city":"Diesse",
    "sg:orig_category":"Darlehenskassen U Raiffeisenbanken",
    "sg:phone":"+41 32 315 15 46",
    "sg:postcode":"2517",
    "sg:province":"Bern",
    "wof:name":"Banque Raiffeisen",
    "wof:placetype":"venue"
},
  "geometry": {"coordinates":[7.116241,47.113258],"type":"Point"}
}