{
  "type": "Feature",
  "properties": {
    "iso:country":"CH",
    "sg:address":"6314 Unter\u00e4geri. Postfach 561",
    "sg:city":"Unter\u00e4geri",
    "sg:orig_category":"Bezirks, Sekundar, Realschulen, Oberstufe der Primarschulen",
    "sg:phone":"+41 31 781 11 78",
    "sg:postcode":"6314",
    "sg:province":"Zug",
    "wof:name":"Sekundarschule",
    "wof:placetype":"venue"
},
  "geometry": {"coordinates":[8.583835,47.137405],"type":"Point"}
}