{
  "type": "Feature",
  "properties": {
    "iso:country":"CH",
    "sg:address":"1261",
    "sg:city":"Marchissy",
    "sg:orig_category":"Schulpflegen",
    "sg:postcode":"1261",
    "sg:province":"Vaud",
    "wof:name":"Commission Scolaire Des \u00e9coles Prim.de Noville-chessel-rennaz",
    "wof:placetype":"venue"
},
  "geometry": {"coordinates":[6.926129818,46.3981781006],"type":"Point"}
}