{
  "type": "Feature",
  "properties": {
    "iso:country":"CH",
    "sg:address":"Klosbachstrasse 2 8032 Z\u00fcrich. Postfach",
    "sg:city":"Z\u00fcrich",
    "sg:orig_category":"Interessenvertretungen Organisationen der Wohlfahrtspflege",
    "sg:phone":"+41 13830507",
    "sg:postcode":"8032",
    "sg:province":"Z\u00fcrich",
    "wof:name":"Krebsliga Des Kantons Z\u00fcrich",
    "wof:placetype":"venue"
},
  "geometry": {"coordinates":[8.5548429489,47.3647651672],"type":"Point"}
}