{
  "type": "Feature",
  "properties": {
    "addr:full":"Spitalstrasse 72 R\u00fcti Z\u00fcrich 8630",
    "addr:housenumber":"72",
    "addr:postcode":"8630",
    "addr:street":"Spitalstrasse",
    "iso:country":"CH",
    "sg:address":"Spitalstrasse 72",
    "sg:city":"R\u00fcti",
    "sg:orig_category":"Biodiesel",
    "sg:phone":"+41 34 435 88 88",
    "sg:postcode":"8630",
    "sg:province":"Z\u00fcrich",
    "wof:name":"Bichsel Ag",
    "wof:placetype":"venue"
},
  "geometry": {"coordinates":[7.751251,47.06176],"type":"Point"}
}