{
  "type": "Feature",
  "properties": {
    "iso:country":"CH",
    "sg:address":"Via Belvedere 15",
    "sg:city":"Canobbio",
    "sg:orig_category":"Instandhaltung U Reparatur von Automobilen",
    "sg:phone":"+41 91 942 71 71",
    "sg:postcode":"6952",
    "sg:province":"Ticino",
    "wof:name":"Pietro Steger Carrozzeria & Garage",
    "wof:placetype":"venue"
},
  "geometry": {"coordinates":[8.9678087234,46.0308456421],"type":"Point"}
}