{
  "type": "Feature",
  "properties": {
    "iso:country":"CH",
    "sg:address":"Industriestrasse 32 9495 Triesen. Postfach 568",
    "sg:city":"Triesen",
    "sg:orig_category":"Grosshandel mit festen Brennstoffen U Mineral\u00f6lerzeugnissen G\u00fcterbef\u00f6rderung im Strassenverkehr",
    "sg:phone":"+423 392 37 37",
    "sg:postcode":"9495",
    "wof:name":"Tz Aktiengesellschaft",
    "wof:placetype":"venue"
},
  "geometry": {"coordinates":[9.5180988312,47.1191711426],"type":"Point"}
}