{
  "type": "Feature",
  "properties": {
    "iso:country":"CH",
    "sg:address":"5063",
    "sg:city":"W\u00f6lflinswil",
    "sg:orig_category":"Primarschulen",
    "sg:postcode":"5063",
    "sg:province":"Aargau",
    "wof:name":"Primarschule Huebmet",
    "wof:placetype":"venue"
},
  "geometry": {"coordinates":[7.997399807,47.4621200562],"type":"Point"}
}