{
  "type": "Feature",
  "properties": {
    "iso:country":"CH",
    "sg:address":"Village 8",
    "sg:city":"Cerneux-p\u00e9quignot",
    "sg:orig_category":"Unclassifiable Establishments",
    "sg:postcode":"2414",
    "sg:province":"Neuch\u00e2tel",
    "wof:name":"Roger Vogt",
    "wof:placetype":"venue"
},
  "geometry": {"coordinates":[8.5974979401,47.2994155884],"type":"Point"}
}