{
  "type": "Feature",
  "properties": {
    "iso:country":"CH",
    "sg:address":"Winggel 9475 Sevelen. Postfach",
    "sg:city":"Sevelen",
    "sg:orig_category":"Herstellung von keramischen Wand U Bodenfliesen U platten",
    "sg:postcode":"9475",
    "sg:province":"St. Gallen",
    "wof:name":"Kaiser Pl\u00e4ttliausstellung",
    "wof:placetype":"venue"
},
  "geometry": {"coordinates":[9.483921051,47.1204109192],"type":"Point"}
}