{
  "type": "Feature",
  "properties": {
    "iso:country":"CH",
    "sg:address":"R\u00fctistrasse 21",
    "sg:city":"Widnau",
    "sg:classifiers":[
        {
            "category":"Home & Garden",
            "subcategory":"Household Appliances",
            "type":"Retail Goods"
        }
    ],
    "sg:phone":"+41 71 722 45 45",
    "sg:postcode":"9443",
    "sg:province":"St. Gallen",
    "sg:tags":[
        "stove",
        "chimney"
    ],
    "wof:name":"Asko Handels Ag",
    "wof:placetype":"venue"
},
  "geometry": {"coordinates":[9.638941,47.403725],"type":"Point"}
}