{
  "type": "Feature",
  "properties": {
    "iso:country":"CH",
    "sg:address":"Im Stutz 3",
    "sg:city":"Elgg",
    "sg:orig_category":"Hardwareberatung",
    "sg:postcode":"8353",
    "sg:province":"Z\u00fcrich",
    "wof:name":"Pb Handel Und Dienstleistungen Blaser Dieter",
    "wof:placetype":"venue"
},
  "geometry": {"coordinates":[8.864897728,47.4986724854],"type":"Point"}
}