{
  "type": "Feature",
  "properties": {
    "iso:country":"CH",
    "sg:address":"Erlenweg 5",
    "sg:city":"Zofingen",
    "sg:orig_category":"Unternehmensberatung Wirtschaftspr\u00fcfung, Steuerberatung U Treuhand",
    "sg:phone":"+41 62 751 32 11",
    "sg:postcode":"4800",
    "sg:province":"Aargau",
    "wof:name":"P. Zimmermann, Unternehmensberatung & Treuhand",
    "wof:placetype":"venue"
},
  "geometry": {"coordinates":[7.9455299377,47.2770271301],"type":"Point"}
}