{
  "type": "Feature",
  "properties": {
    "iso:country":"CH",
    "sg:address":"Via Pradello",
    "sg:city":"Bioggio",
    "sg:orig_category":"Architektur U Ingenieurb\u00fcros Innenarchitekturb\u00fcros",
    "sg:phone":"+41 91 605 66 40",
    "sg:postcode":"6934",
    "sg:province":"Ticino",
    "wof:name":"Neo-design Stefania Cavalleri Architettura D'interni",
    "wof:placetype":"venue"
},
  "geometry": {"coordinates":[8.909975,46.013439],"type":"Point"}
}