{
  "type": "Feature",
  "properties": {
    "iso:country":"CH",
    "sg:address":"Oberdorfstrasse 1",
    "sg:city":"Seengen",
    "sg:orig_category":"Detailhandel mit Fleisch U Fleischwaren",
    "sg:phone":"+41 62 777 12 40",
    "sg:postcode":"5707",
    "sg:province":"Aargau",
    "wof:name":"Hansrudolf Hechler Metzgerei B\u00e4ren",
    "wof:placetype":"venue"
},
  "geometry": {"coordinates":[8.2056427002,47.3270988464],"type":"Point"}
}