{
  "type": "Feature",
  "properties": {
    "iso:country":"CH",
    "sg:address":"Buckstrasse 1",
    "sg:city":"Neerach",
    "sg:orig_category":"Non-Classified Establishments",
    "sg:phone":"+41 18584004",
    "sg:postcode":"8173",
    "sg:province":"Z\u00fcrich",
    "wof:name":"Quastra Consulting Gmbh",
    "wof:placetype":"venue"
},
  "geometry": {"coordinates":[8.4725809097,47.5023803711],"type":"Point"}
}