{
  "type": "Feature",
  "properties": {
    "iso:country":"CH",
    "sg:address":"Ahornweg 11",
    "sg:city":"Belp",
    "sg:orig_category":"Allgemeiner Hoch U Tiefbau",
    "sg:phone":"+41 31 985 23 23",
    "sg:postcode":"3123",
    "sg:province":"Bern",
    "wof:name":"Weiss + Appetito Ag Belp",
    "wof:placetype":"venue"
},
  "geometry": {"coordinates":[7.50051,46.886086],"type":"Point"}
}