{
  "type": "Feature",
  "properties": {
    "iso:country":"CH",
    "sg:address":"Landstrasse 24 8865 Bilten. Postfach",
    "sg:city":"Bilten",
    "sg:orig_category":"Erbringung von Dienstleistungen f\u00fcr Unternehmen",
    "sg:postcode":"8865",
    "sg:province":"Glarus",
    "wof:name":"Deejay, Gastro Und Fun Management Gmbh Gastro- U. Unterhaltungskonzepten; Erarbeitung, Vermarktung Usw.",
    "wof:placetype":"venue"
},
  "geometry": {"coordinates":[9.0186767578,47.1529121399],"type":"Point"}
}