{
  "type": "Feature",
  "properties": {
    "iso:country":"CH",
    "sg:address":"Bahnhofstrasse 47",
    "sg:city":"Maienfeld",
    "sg:orig_category":"Detailhandel mit Fleisch U Fleischwaren",
    "sg:phone":"+41 81 302 13 31",
    "sg:postcode":"7304",
    "sg:province":"Graubunden",
    "wof:name":"Hansjakob M\u00f6hr Metzgerei & Wursterei",
    "wof:placetype":"venue"
},
  "geometry": {"coordinates":[9.528719902,47.0042190552],"type":"Point"}
}