{
  "type": "Feature",
  "properties": {
    "iso:country":"CH",
    "sg:address":"Chemin Des Crues 15",
    "sg:city":"Perly",
    "sg:orig_category":"Grosshandel mit Getr\u00e4nken Handelsvermittlung U Grosshandel",
    "sg:phone":"+41 22 958 01 63",
    "sg:postcode":"1258",
    "sg:province":"Gen\u00e8ve",
    "wof:name":"Dav Sa",
    "wof:placetype":"venue"
},
  "geometry": {"coordinates":[6.0986218452,46.1618347168],"type":"Point"}
}