{
  "type": "Feature",
  "properties": {
    "iso:country":"CH",
    "sg:address":"Ceresio Via 43 6963 Pregassona. Postfach",
    "sg:city":"Pregassona",
    "sg:orig_category":"Grosshandel mit Getr\u00e4nken",
    "sg:postcode":"6963",
    "sg:province":"Ticino",
    "wof:name":"Idro Space Sa Acque Minerali; Compravendita, Comm. Ecc",
    "wof:placetype":"venue"
},
  "geometry": {"coordinates":[8.9664268494,46.0221214294],"type":"Point"}
}