{
  "type": "Feature",
  "properties": {
    "iso:country":"CH",
    "sg:address":"Baslerstrasse 183",
    "sg:city":"Allschwil",
    "sg:orig_category":"Detailhandel mit Sportartikeln",
    "sg:phone":"+41 61 481 41 91",
    "sg:postcode":"4123",
    "sg:province":"Basel-Landschaft",
    "wof:name":"Hans Bohnenblust Treboh Bike-& Ski Shop",
    "wof:placetype":"venue"
},
  "geometry": {"coordinates":[7.549888134,47.55286026],"type":"Point"}
}