{
  "type": "Feature",
  "properties": {
    "iso:country":"CH",
    "sg:address":"Lindenweg 23",
    "sg:city":"Buchrain",
    "sg:orig_category":"Softwareentwicklung U beratung",
    "sg:phone":"+41 79 353 04 86",
    "sg:postcode":"6033",
    "sg:province":"Luzern",
    "wof:name":"Corda Ag",
    "wof:placetype":"venue"
},
  "geometry": {"coordinates":[8.3492212296,47.0989074707],"type":"Point"}
}