{
  "type": "Feature",
  "properties": {
    "addr:full":"Bad.bahnhofstrasse 5 Neuhausen Schaffhausen 8212",
    "addr:housenumber":"5",
    "addr:postcode":"8212",
    "addr:street":"Bad.Bahnhofstrasse",
    "iso:country":"CH",
    "sg:address":"Bad.bahnhofstrasse 5",
    "sg:city":"Neuhausen",
    "sg:orig_category":"Bauschreinerei Herstellung von Konstruktionsteilen, Fertigbauteilen U Ausbauelementen aus Holz",
    "sg:phone":"+41 52 763 43 50",
    "sg:postcode":"8212",
    "sg:province":"Schaffhausen",
    "wof:name":"Schreinerei Fehlmann",
    "wof:placetype":"venue"
},
  "geometry": {"coordinates":[8.994883,47.598305],"type":"Point"}
}