{
  "type": "Feature",
  "properties": {
    "addr:full":"Chillon Avenue De 70 Territet-veytaux Vaud 1820",
    "addr:housenumber":"70",
    "addr:postcode":"1820",
    "addr:street":"Chillon Avenue De",
    "iso:country":"CH",
    "sg:address":"Chillon Avenue De 70",
    "sg:city":"Territet-veytaux",
    "sg:orig_category":"Betrieb U technische Hilfsdienste des Kultur U Unterhaltungswesens",
    "sg:postcode":"1820",
    "sg:province":"Vaud",
    "wof:name":"Top Events Of Switzerland",
    "wof:placetype":"venue"
},
  "geometry": {"coordinates":[6.910506,46.431694],"type":"Point"}
}