{
  "type": "Feature",
  "properties": {
    "iso:country":"CH",
    "sg:address":"Simplon Rue Du 34 1920 Martigny Case Postale 502",
    "sg:city":"Martigny",
    "sg:orig_category":"Instandhaltung U Reparatur von Automobilen",
    "sg:phone":"+41 27 722 63 33",
    "sg:postcode":"1920",
    "sg:province":"Valais",
    "wof:name":"Garage Kaspar Sa Martigny",
    "wof:placetype":"venue"
},
  "geometry": {"coordinates":[7.0801568031,46.1037063599],"type":"Point"}
}