{
  "type": "Feature",
  "properties": {
    "iso:country":"CH",
    "sg:address":"S\u00fcdstrasse 1",
    "sg:city":"Schlieren",
    "sg:orig_category":"Non-Classified Establishments",
    "sg:phone":"+41 18450343",
    "sg:postcode":"8952",
    "sg:province":"Z\u00fcrich",
    "wof:name":"Stalder Hydraulik Service - Center",
    "wof:placetype":"venue"
},
  "geometry": {"coordinates":[8.4634246826,47.399974823],"type":"Point"}
}