{
  "type": "Feature",
  "properties": {
    "iso:country":"CH",
    "sg:address":"Ferme Rue De La 9 1205 Gen\u00e8ve. Postfach",
    "sg:city":"Gen\u00e8ve",
    "sg:orig_category":"Elektroinstallation",
    "sg:phone":"+41 21 697 67 67",
    "sg:postcode":"1205",
    "sg:province":"Gen\u00e8ve",
    "wof:name":"Batiwatt Sa",
    "wof:placetype":"venue"
},
  "geometry": {"coordinates":[6.5532917976,46.5139274597],"type":"Point"}
}