{
  "type": "Feature",
  "properties": {
    "iso:country":"CH",
    "sg:address":"Eichenweg 33",
    "sg:city":"Embrach",
    "sg:orig_category":"Sportvereine Sch\u00fctzen",
    "sg:postcode":"8424",
    "sg:province":"Z\u00fcrich",
    "wof:name":"Milit\u00e4rsch\u00fctzen B\u00fclach",
    "wof:placetype":"venue"
},
  "geometry": {"coordinates":[8.5944213867,47.5096244812],"type":"Point"}
}