{
  "type": "Feature",
  "properties": {
    "addr:full":"Unterdorfstrasse 38 Lausen Basel-Landschaft 4415",
    "addr:housenumber":"38",
    "addr:postcode":"4415",
    "addr:street":"Unterdorfstrasse",
    "iso:country":"CH",
    "sg:address":"Unterdorfstrasse 38",
    "sg:city":"Lausen",
    "sg:orig_category":"Architektur U Ingenieurb\u00fcros",
    "sg:phone":"+41 61 921 20 11",
    "sg:postcode":"4415",
    "sg:province":"Basel-Landschaft",
    "wof:name":"Stierli + Ruggli Ingenieure Und Raumplaner",
    "wof:placetype":"venue"
},
  "geometry": {"coordinates":[7.761361,47.472057],"type":"Point"}
}