{
  "type": "Feature",
  "properties": {
    "iso:country":"CH",
    "sg:address":"Chemin Des Cerisiers 30 1462 Yvonand Case Postale 36",
    "sg:city":"Yvonand",
    "sg:orig_category":"Grosshandel mit Geschenkartikeln U Souvenirs Grosshandel mit sonstigen Gebrauchs U Verbrauchsg\u00fctern",
    "sg:phone":"+41 41 666 29 20",
    "sg:postcode":"1462",
    "sg:province":"Vaud",
    "wof:name":"Innovation By Teb * Tebswiss Werbeartikel - Werbegeschenke",
    "wof:placetype":"venue"
},
  "geometry": {"coordinates":[8.2495098114,46.9012107849],"type":"Point"}
}