{
  "type": "Feature",
  "properties": {
    "addr:full":"Hintere St\u00fctlistrasse 9472 Grabs. Postfach Grabs St. Gallen 9472",
    "addr:postcode":"9472 grabs. postfach;9472",
    "addr:street":"Hintere Stuetlistrasse",
    "iso:country":"CH",
    "sg:address":"Hintere St\u00fctlistrasse 9472 Grabs. Postfach",
    "sg:city":"Grabs",
    "sg:orig_category":"Ausbaugewerbe Verlegen von Fliesen U Platten",
    "sg:phone":"+41 81 771 26 31",
    "sg:postcode":"9472",
    "sg:province":"St. Gallen",
    "wof:name":"Ammann Christof.",
    "wof:placetype":"venue"
},
  "geometry": {"coordinates":[9.44353,47.185104],"type":"Point"}
}