{
  "type": "Feature",
  "properties": {
    "iso:country":"CH",
    "sg:address":"Kantonsstrasse 115",
    "sg:city":"Horw",
    "sg:orig_category":"G\u00fcterbef\u00f6rderung im Strassenverkehr",
    "sg:phone":"+41 19841580",
    "sg:postcode":"6048",
    "sg:province":"Luzern",
    "wof:name":"Kunz Transport Ag, Egg",
    "wof:placetype":"venue"
},
  "geometry": {"coordinates":[8.6900548935,47.3005561829],"type":"Point"}
}