{
  "type": "Feature",
  "properties": {
    "iso:country":"CH",
    "sg:address":"Saint-fran\u00e7ois Place 16",
    "sg:city":"Lausanne",
    "sg:orig_category":"Unclassifiable Establishments",
    "sg:postcode":"1003",
    "sg:province":"Vaud",
    "wof:name":"Si Lapro Sa Lausanne",
    "wof:placetype":"venue"
},
  "geometry": {"coordinates":[6.6326618195,46.5194625854],"type":"Point"}
}