{
  "type": "Feature",
  "properties": {
    "iso:country":"CH",
    "sg:address":"Kirchbergstrasse 5",
    "sg:city":"Hindelbank",
    "sg:orig_category":"Detailhandel mit Zeitungen U Zeitschriften Kioske",
    "sg:phone":"+41 34 411 11 13",
    "sg:postcode":"3324",
    "sg:province":"Bern",
    "wof:name":"Beat J\u00f6rg Kiosk",
    "wof:placetype":"venue"
},
  "geometry": {"coordinates":[7.5440740585,47.0494766235],"type":"Point"}
}