{
  "type": "Feature",
  "properties": {
    "iso:country":"CH",
    "sg:address":"Chemin Du Village 19",
    "sg:city":"Romanel-s-lausanne",
    "sg:classifiers":[
        {
            "category":"Travel",
            "subcategory":"Hotels & Motels",
            "type":"Entertainment"
        }
    ],
    "sg:phone":"+41 21 646 10 12",
    "sg:postcode":"1032",
    "sg:province":"Vaud",
    "sg:tags":[
        "hotels",
        "mit",
        "restaurant"
    ],
    "wof:name":"La Chotte S\u00e0rl",
    "wof:placetype":"venue"
},
  "geometry": {"coordinates":[6.6062197685,46.5634307861],"type":"Point"}
}