{
  "type": "Feature",
  "properties": {
    "iso:country":"CH",
    "sg:address":"Schlossweg 29",
    "sg:city":"H\u00fcnibach",
    "sg:orig_category":"Immobilienwesen Kauf U Verkauf von Immobilien auf eigene Rechnung",
    "sg:phone":"+41 33 243 53 58",
    "sg:postcode":"3626",
    "sg:province":"Bern",
    "wof:name":"Makar Immobilien Ag",
    "wof:placetype":"venue"
},
  "geometry": {"coordinates":[7.6428198814,46.7477836609],"type":"Point"}
}