{
  "type": "Feature",
  "properties": {
    "iso:country":"CH",
    "sg:address":"Binningerstrasse 112",
    "sg:city":"Allschwil",
    "sg:orig_category":"Instandhaltung U Reparatur von Automobilen",
    "sg:phone":"+41 61 406 91 90",
    "sg:postcode":"4123",
    "sg:province":"Basel-Landschaft",
    "wof:name":"Mundwiler & Co.",
    "wof:placetype":"venue"
},
  "geometry": {"coordinates":[7.5559267998,47.5116920471],"type":"Point"}
}