{
  "type": "Feature",
  "properties": {
    "iso:country":"CH",
    "sg:address":"Serre Rue De La 4",
    "sg:city":"Neuch\u00e2tel",
    "sg:orig_category":"Grosshandel mit Zucker, Schokolade U S\u00fcsswaren",
    "sg:phone":"+41 61 731 33 31",
    "sg:postcode":"2000",
    "sg:province":"Neuch\u00e2tel",
    "wof:name":"Chocolat Nogal Sa",
    "wof:placetype":"venue"
},
  "geometry": {"coordinates":[7.5978589058,47.4669914246],"type":"Point"}
}