{
  "type": "Feature",
  "properties": {
    "iso:country":"CH",
    "sg:address":"Kirchb\u00fchl 19",
    "sg:city":"Burgdorf",
    "sg:orig_category":"Beherbergungsgewerbe",
    "sg:postcode":"3400",
    "sg:province":"Bern",
    "wof:name":"Stiftung F\u00fcr Die Schuljugend Der Stadt Burgdorf",
    "wof:placetype":"venue"
},
  "geometry": {"coordinates":[7.625717,47.056168],"type":"Point"}
}