{
  "type": "Feature",
  "properties": {
    "iso:country":"CH",
    "sg:address":"Obergrundstrasse 70",
    "sg:city":"Luzern",
    "sg:orig_category":"Physiotherapie",
    "sg:phone":"+41 55 210 09 08",
    "sg:postcode":"6003",
    "sg:province":"Luzern",
    "wof:name":"Reinaud Fokker Koen Physiotherapie",
    "wof:placetype":"venue"
},
  "geometry": {"coordinates":[8.8255090714,47.2289085388],"type":"Point"}
}