{
  "type": "Feature",
  "properties": {
    "iso:country":"CH",
    "sg:address":"Via Cattori 4",
    "sg:city":"Lugano",
    "sg:orig_category":"Handel mit Motorr\u00e4dern, Teilen U Zubeh\u00f6r Instandhaltung U Reparatur von Motorr\u00e4dern",
    "sg:phone":"+41 91 993 07 77",
    "sg:postcode":"6900",
    "sg:province":"Ticino",
    "wof:name":"Hobby Moto Di Schiesari Renzo",
    "wof:placetype":"venue"
},
  "geometry": {"coordinates":[8.9459562302,45.9932441711],"type":"Point"}
}