{
  "type": "Feature",
  "properties": {
    "iso:country":"CH",
    "sg:address":"Herrenschwandenstrasse 5",
    "sg:city":"Herrenschwanden",
    "sg:orig_category":"Reiseb\u00fcros U Reiseveranstalter",
    "sg:phone":"+41 31 302 88 77",
    "sg:postcode":"3037",
    "sg:province":"Bern",
    "wof:name":"Berger Aktiv-reisen",
    "wof:placetype":"venue"
},
  "geometry": {"coordinates":[7.4173212051,46.9775238037],"type":"Point"}
}