{
  "type": "Feature",
  "properties": {
    "iso:country":"CH",
    "sg:address":"Chemin Du Levant 3",
    "sg:city":"Payerne",
    "sg:orig_category":"Sportvereine Sch\u00fctzen",
    "sg:phone":"+41 26 660 11 86",
    "sg:postcode":"1530",
    "sg:province":"Vaud",
    "wof:name":"St\u00e9 De Tir Le Grutli",
    "wof:placetype":"venue"
},
  "geometry": {"coordinates":[6.9440059662,46.816696167],"type":"Point"}
}