{
  "type": "Feature",
  "properties": {
    "iso:country":"CH",
    "sg:address":"Fuchsweg 14 4704 Niederbipp. Postfach",
    "sg:city":"Niederbipp",
    "sg:orig_category":"Sonstige pers\u00f6nliche Dienstleistungen",
    "sg:postcode":"4704",
    "sg:province":"Bern",
    "wof:name":"X&x Gmbh",
    "wof:placetype":"venue"
},
  "geometry": {"coordinates":[7.6979050636,47.2700157166],"type":"Point"}
}