{
  "type": "Feature",
  "properties": {
    "addr:full":"Baslerstrasse 9 Olten Solothurn 4600",
    "addr:housenumber":"9",
    "addr:postcode":"4600",
    "addr:street":"Baslerstrasse",
    "iso:country":"CH",
    "sg:address":"Baslerstrasse 9",
    "sg:city":"Olten",
    "sg:orig_category":"Detailhandel mit B\u00fcchern, Zeitungen, Schreib U Papeteriewaren Detailhandel mit Ton U Bildtr\u00e4gern",
    "sg:phone":"+41 62 212 93 03",
    "sg:postcode":"4600",
    "sg:province":"Solothurn",
    "wof:name":"Weltbildplus Olten",
    "wof:placetype":"venue"
},
  "geometry": {"coordinates":[7.902548,47.350956],"type":"Point"}
}