{
  "type": "Feature",
  "properties": {
    "iso:country":"CH",
    "sg:address":"Place De Savoie 2",
    "sg:city":"Nyon",
    "sg:orig_category":"Detailhandel mit M\u00f6beln Kunsthandel",
    "sg:phone":"+41 22 362 70 02",
    "sg:postcode":"1260",
    "sg:province":"Vaud",
    "wof:name":"Esther Giger Galeries Du Lac",
    "wof:placetype":"venue"
},
  "geometry": {"coordinates":[6.2409029007,46.3804283142],"type":"Point"}
}