{
  "type": "Feature",
  "properties": {
    "iso:country":"CH",
    "sg:address":"6023 Rothenburg. Postfach 206",
    "sg:city":"Rothenburg",
    "sg:orig_category":"Sportvereine Ballsport Fussball",
    "sg:phone":"+41 33 951 27 06",
    "sg:postcode":"6023",
    "sg:province":"Luzern",
    "wof:name":"Fc Rothorn",
    "wof:placetype":"venue"
},
  "geometry": {"coordinates":[8.0554924011,46.7590522766],"type":"Point"}
}