{
  "type": "Feature",
  "properties": {
    "iso:country":"CH",
    "sg:address":"Grand'rue 11 1200 Genf. Postfach",
    "sg:city":"Gen\u00e8ve",
    "sg:orig_category":"K\u00fcnstlerische U schriftstellerische T\u00e4tigkeiten U Darbietungen",
    "sg:postcode":"1204",
    "sg:province":"Gen\u00e8ve",
    "wof:name":"Fondation Soci\u00e9t\u00e9 De Lecture",
    "wof:placetype":"venue"
},
  "geometry": {"coordinates":[6.1470108032,46.2012367249],"type":"Point"}
}