{
  "type": "Feature",
  "properties": {
    "iso:country":"CH",
    "sg:address":"Rosemont Avenue 9",
    "sg:city":"Gen\u00e8ve",
    "sg:orig_category":"K\u00fcnstlerische U schriftstellerische T\u00e4tigkeiten U Darbietungen",
    "sg:postcode":"1208",
    "sg:province":"Gen\u00e8ve",
    "wof:name":"Beranek Petr",
    "wof:placetype":"venue"
},
  "geometry": {"coordinates":[6.1721348763,46.2022323608],"type":"Point"}
}