{
  "type": "Feature",
  "properties": {
    "iso:country":"CH",
    "sg:address":"Bahnhofstrasse",
    "sg:city":"Berikon",
    "sg:orig_category":"Detailhandel mit B\u00fcchern, Zeitungen, Schreib U Papeteriewaren",
    "sg:phone":"+41 22 342 05 46",
    "sg:postcode":"8965",
    "sg:province":"Aargau",
    "wof:name":"Papeterie De Carouge, Daniel Lovato",
    "wof:placetype":"venue"
},
  "geometry": {"coordinates":[6.137363,46.183529],"type":"Point"}
}