{
  "type": "Feature",
  "properties": {
    "iso:country":"CH",
    "sg:address":"Boulevard De P\u00e9rolles 55",
    "sg:city":"Fribourg",
    "sg:orig_category":"Unclassifiable Establishments",
    "sg:postcode":"1700",
    "sg:province":"Fribourg",
    "wof:name":"Nour Holding Sa",
    "wof:placetype":"venue"
},
  "geometry": {"coordinates":[7.1547498703,46.796661377],"type":"Point"}
}