{
  "type": "Feature",
  "properties": {
    "iso:country":"CH",
    "sg:address":"Avenue De Chailly 7",
    "sg:city":"Lausanne",
    "sg:orig_category":"Nationale Postdienste",
    "sg:phone":"+41 21 318 94 00",
    "sg:postcode":"1012",
    "sg:province":"Vaud",
    "wof:name":"La Poste Suisse Lausanne 14 Tribunal F\u00e9d\u00e9ral",
    "wof:placetype":"venue"
},
  "geometry": {"coordinates":[6.6434879303,46.5195198059],"type":"Point"}
}