{
  "type": "Feature",
  "properties": {
    "iso:country":"CH",
    "sg:address":"Brunngasse 6",
    "sg:city":"Winterthur",
    "sg:orig_category":"Arztpraxen",
    "sg:phone":"+41 52 269 16 20",
    "sg:postcode":"8400",
    "sg:province":"Z\u00fcrich",
    "wof:name":"Dr.med.b\u00e9atrice Spiess Spezial\u00e4rztin Fmh",
    "wof:placetype":"venue"
},
  "geometry": {"coordinates":[8.725231,47.505371],"type":"Point"}
}