{
  "type": "Feature",
  "properties": {
    "iso:country":"CH",
    "sg:address":"Hochstrasse 59 4053 Basel. Postfach",
    "sg:city":"Basel",
    "sg:orig_category":"RESTAURANTS: TEA-ROOMS",
    "sg:phone":"+41 19100715",
    "sg:postcode":"4051",
    "sg:province":"Basel-Stadt",
    "wof:name":"Petermann's Restaurant Kunststuben",
    "wof:placetype":"venue"
},
  "geometry": {"coordinates":[8.5799207687,47.3156394958],"type":"Point"}
}