{
  "type": "Feature",
  "properties": {
    "iso:country":"CH",
    "sg:address":"Avenue Des Communes-r\u00e9unies 62",
    "sg:city":"Grand-lancy",
    "sg:orig_category":"Malerei-Gipserei",
    "sg:phone":"+41 71 923 88 60",
    "sg:postcode":"1212",
    "sg:province":"Gen\u00e8ve",
    "wof:name":"Felix Karg Malergesch\u00e4ft",
    "wof:placetype":"venue"
},
  "geometry": {"coordinates":[9.0391159058,47.4590873718],"type":"Point"}
}