{
  "type": "Feature",
  "properties": {
    "iso:country":"CH",
    "sg:address":"Hauptstrasse 92a",
    "sg:city":"Kreuzlingen",
    "sg:orig_category":"Detailhandel mit Blumen U Pflanzen Fachdetailhandel in Verkaufsr\u00e4umen",
    "sg:phone":"+41 71 672 44 33",
    "sg:postcode":"8280",
    "sg:province":"Thurgau",
    "wof:name":"B\u00fcrgi Franziska Blumen-raum-gestaltung",
    "wof:placetype":"venue"
},
  "geometry": {"coordinates":[9.177409,47.645733],"type":"Point"}
}