{
  "type": "Feature",
  "properties": {
    "iso:country":"CH",
    "sg:address":"Hohlweg 1",
    "sg:city":"Rapperswil",
    "sg:classifiers":[
        {
            "category":"Professional",
            "subcategory":"Computer Services",
            "type":"Services"
        }
    ],
    "sg:phone":"+41 55 222 69 00",
    "sg:postcode":"8640",
    "sg:province":"Schwyz",
    "sg:tags":[
        "data-loggers"
    ],
    "wof:name":"Dipl. Ing. Ernest Spirig",
    "wof:placetype":"venue"
},
  "geometry": {"coordinates":[8.831034,47.222172],"type":"Point"}
}