{
  "type": "Feature",
  "properties": {
    "iso:country":"CH",
    "sg:address":"Neufeldstrasse 36i",
    "sg:city":"Thun",
    "sg:orig_category":"Einbau von Schreinerwaren Elektroinstallation",
    "sg:postcode":"3604",
    "sg:province":"Bern",
    "wof:name":"Bms B\u00fcromontageservice",
    "wof:placetype":"venue"
},
  "geometry": {"coordinates":[7.6099529266,46.7401237488],"type":"Point"}
}