{
  "type": "Feature",
  "properties": {
    "addr:full":"Via Franchini 2 Mendrisio Ticino 6850",
    "addr:housenumber":"2",
    "addr:postcode":"6850",
    "addr:street":"Via Franchini",
    "iso:country":"CH",
    "sg:address":"Via Franchini 2",
    "sg:city":"Mendrisio",
    "sg:orig_category":"Arztpraxen",
    "sg:phone":"+41 91 646 39 22",
    "sg:postcode":"6850",
    "sg:province":"Ticino",
    "wof:name":"Dottori D'apuzzo & Ferrazzini Specialisti Fmh",
    "wof:placetype":"venue"
},
  "geometry": {"coordinates":[8.98148,45.864456],"type":"Point"}
}