{
  "type": "Feature",
  "properties": {
    "iso:country":"CH",
    "sg:address":"Obertannberg 13",
    "sg:city":"Schenkon",
    "sg:orig_category":"Architektur U Ingenieurb\u00fcros",
    "sg:phone":"+41 41 926 70 60",
    "sg:postcode":"6214",
    "sg:province":"Luzern",
    "wof:name":"Hansj\u00f6rg Bosshard Bauingenieurb\u00fcro Gmbh",
    "wof:placetype":"venue"
},
  "geometry": {"coordinates":[8.136209,47.183754],"type":"Point"}
}