{
  "type": "Feature",
  "properties": {
    "iso:country":"CH",
    "sg:address":"Gibraltarstrasse 548",
    "sg:city":"Luzern",
    "sg:orig_category":"Pensionskassen",
    "sg:postcode":"6000",
    "sg:province":"Luzern",
    "wof:name":"F\u00fcrsorgestiftung Der Meyer Josef Holding Ag, Luzern",
    "wof:placetype":"venue"
},
  "geometry": {"coordinates":[8.2979602814,47.0519599915],"type":"Point"}
}