{
  "type": "Feature",
  "properties": {
    "iso:country":"CH",
    "sg:address":"Bahnhofstrasse 102",
    "sg:city":"Frauenfeld",
    "sg:orig_category":"Detailhandel mit Waren verschiedener Art, Hauptrichtung Nahrungsmittel",
    "sg:phone":"+41 52 721 67 47",
    "sg:postcode":"8500",
    "sg:province":"Thurgau",
    "wof:name":"Denner Top Superdiscount",
    "wof:placetype":"venue"
},
  "geometry": {"coordinates":[8.9039611816,47.5611495972],"type":"Point"}
}