{
  "type": "Feature",
  "properties": {
    "iso:country":"CH",
    "sg:address":"3504",
    "sg:city":"Oberh\u00fcnigen",
    "sg:orig_category":"Primarschulen",
    "sg:phone":"+41 31 711 39 25",
    "sg:postcode":"3504",
    "sg:province":"Bern",
    "wof:name":"Primarschule",
    "wof:placetype":"venue"
},
  "geometry": {"coordinates":[7.6671600342,46.9350700378],"type":"Point"}
}