{
  "type": "Feature",
  "properties": {
    "iso:country":"CH",
    "sg:address":"Bernstrasse 114",
    "sg:city":"Ostermundigen",
    "sg:orig_category":"Gesundheitswesen",
    "sg:postcode":"3072",
    "sg:province":"Bern",
    "wof:name":"Fmh Business Services Sa",
    "wof:placetype":"venue"
},
  "geometry": {"coordinates":[8.1118364334,47.1541862488],"type":"Point"}
}