{
  "type": "Feature",
  "properties": {
    "iso:country":"CH",
    "sg:address":"Bachlettenstrasse 62",
    "sg:city":"Basel",
    "sg:orig_category":"Betrieb von Taxis",
    "sg:phone":"+41 18500707",
    "sg:postcode":"4054",
    "sg:province":"Basel-Stadt",
    "wof:name":"Carmine Ambrosio Funk Taxi Oberglatt",
    "wof:placetype":"venue"
},
  "geometry": {"coordinates":[8.505085,47.478802],"type":"Point"}
}