{
  "type": "Feature",
  "properties": {
    "iso:country":"CH",
    "sg:address":"3999",
    "sg:city":"Oberwald",
    "sg:orig_category":"Schulpflegen",
    "sg:postcode":"3999",
    "sg:province":"Valais",
    "wof:name":"Schulkommission Der Gemeinde Oberwald",
    "wof:placetype":"venue"
},
  "geometry": {"coordinates":[8.3459253311,46.5333633423],"type":"Point"}
}