{
  "type": "Feature",
  "properties": {
    "iso:country":"CH",
    "sg:address":"T\u00f6sstalstrasse 224a",
    "sg:city":"Winterthur",
    "sg:orig_category":"Detailhandel mit Fahrr\u00e4dern Handel mit Motorr\u00e4dern, Teilen U Zubeh\u00f6r Instandhaltung U Reparatur von ",
    "sg:phone":"+41 22 796 49 82",
    "sg:postcode":"8405",
    "sg:province":"Z\u00fcrich",
    "wof:name":"Motomure Motos Harley-davidson",
    "wof:placetype":"venue"
},
  "geometry": {"coordinates":[6.1002898216,46.2071914673],"type":"Point"}
}