{
  "type": "Feature",
  "properties": {
    "iso:country":"CH",
    "sg:address":"L\u00e4nggassstrasse 7 3012 Bern. Postfach 5916",
    "sg:city":"Bern",
    "sg:orig_category":"Rechtsberatung Unternehmensberatung",
    "sg:phone":"+41 31 301 93 93",
    "sg:postcode":"3001",
    "sg:province":"Bern",
    "wof:name":"Pd-consulting Gmbh",
    "wof:placetype":"venue"
},
  "geometry": {"coordinates":[7.4345221519,46.9515609741],"type":"Point"}
}