{
  "type": "Feature",
  "properties": {
    "iso:country":"CH",
    "sg:address":"Grand-rue 4",
    "sg:city":"Thielle-wavre",
    "sg:orig_category":"Gemeindeverwaltungen",
    "sg:phone":"+41 32 753 55 10",
    "sg:postcode":"2075",
    "sg:province":"Neuch\u00e2tel",
    "wof:name":"Administration Communale De Thielle-wavre",
    "wof:placetype":"venue"
},
  "geometry": {"coordinates":[7.0212807655,47.0256309509],"type":"Point"}
}