{
  "type": "Feature",
  "properties": {
    "addr:full":"Route Du Village 30 Blonay Vaud 1807",
    "addr:housenumber":"30",
    "addr:postcode":"1807",
    "addr:street":"Route Du Village",
    "iso:country":"CH",
    "sg:address":"Route Du Village 30",
    "sg:city":"Blonay",
    "sg:classifiers":[
        {
            "category":"Banks & Credit Unions",
            "subcategory":"Bank",
            "type":"Services"
        }
    ],
    "sg:phone":"+41 21 943 25 62",
    "sg:postcode":"1807",
    "sg:province":"Vaud",
    "wof:name":"Banque Raiffeisen",
    "wof:placetype":"venue"
},
  "geometry": {"coordinates":[6.893904,46.466209],"type":"Point"}
}