{
  "type": "Feature",
  "properties": {
    "iso:country":"CH",
    "sg:address":"Zeughausstrasse 9",
    "sg:city":"Lenzburg",
    "sg:orig_category":"Pensionskassen",
    "sg:postcode":"5600",
    "sg:province":"Aargau",
    "wof:name":"Gloor-h\u00e4usermann-stiftung Marty Lenzburg",
    "wof:placetype":"venue"
},
  "geometry": {"coordinates":[8.1696014404,47.3896408081],"type":"Point"}
}