{
  "type": "Feature",
  "properties": {
    "iso:country":"CH",
    "sg:address":"Obere Zollgasse 71",
    "sg:city":"Ostermundigen",
    "sg:orig_category":"Herstellung von Metallerzeugnissen ohne Maschinenbau Herstellung von sonstigen Maschinen f\u00fcr unspezi",
    "sg:phone":"+41 31 931 21 11",
    "sg:postcode":"3072",
    "sg:province":"Bern",
    "wof:name":"Maschinenfabrik Bern Ag",
    "wof:placetype":"venue"
},
  "geometry": {"coordinates":[7.48498106,46.950050354],"type":"Point"}
}