{
  "type": "Feature",
  "properties": {
    "iso:country":"CH",
    "sg:address":"Route De Saint-julien 285 Perly 1258 Certoux. Postfach",
    "sg:city":"Perly",
    "sg:orig_category":"Herstellung von Schl\u00f6ssern U Beschl\u00e4gen",
    "sg:postcode":"1258",
    "sg:province":"Gen\u00e8ve",
    "wof:name":"Clefs Drac Sa",
    "wof:placetype":"venue"
},
  "geometry": {"coordinates":[6.0969948769,46.1573181152],"type":"Point"}
}