{
  "type": "Feature",
  "properties": {
    "iso:country":"CH",
    "sg:address":"Pr\u00e9-lauret Route De 5",
    "sg:city":"Bernex",
    "sg:orig_category":"Gesundheitswesen",
    "sg:phone":"+41 22 757 68 40",
    "sg:postcode":"1233",
    "sg:province":"Gen\u00e8ve",
    "wof:name":"Association Thais",
    "wof:placetype":"venue"
},
  "geometry": {"coordinates":[6.0555667877,46.1590156555],"type":"Point"}
}