{
  "type": "Feature",
  "properties": {
    "iso:country":"CH",
    "sg:address":"Moosmattstrasse 47",
    "sg:city":"Luzern",
    "sg:orig_category":"Arbeitnehmerverb\u00e4nde",
    "sg:phone":"+41 41 310 30 07",
    "sg:postcode":"6005",
    "sg:province":"Luzern",
    "wof:name":"Verein.eidg.dipl.buchhalter Reg.innerschweiz,hans Hafner",
    "wof:placetype":"venue"
},
  "geometry": {"coordinates":[8.30359,47.036629],"type":"Point"}
}