{
  "type": "Feature",
  "properties": {
    "iso:country":"CH",
    "sg:address":"Fehrenstrasse 13",
    "sg:city":"Breitenbach",
    "sg:orig_category":"Kosmetikinstitute",
    "sg:phone":"+41 61 781 20 90",
    "sg:postcode":"4226",
    "sg:province":"Solothurn",
    "wof:name":"Sie + Er Kosmetik + P\u00e9dicure",
    "wof:placetype":"venue"
},
  "geometry": {"coordinates":[7.5459041595,47.4079933167],"type":"Point"}
}