{
  "type": "Feature",
  "properties": {
    "iso:country":"CH",
    "sg:address":"Hopfenweg 19",
    "sg:city":"Bern",
    "sg:orig_category":"Zahnarztpraxen",
    "sg:phone":"+41 31 371 75 55",
    "sg:postcode":"3007",
    "sg:province":"Bern",
    "wof:name":"Dr. Med. Dent. Marco Panzera Zahnarzt",
    "wof:placetype":"venue"
},
  "geometry": {"coordinates":[7.4274921417,46.9417686462],"type":"Point"}
}