{
  "type": "Feature",
  "properties": {
    "iso:country":"CH",
    "sg:address":"Artherstrasse 6",
    "sg:city":"Zug",
    "sg:orig_category":"Unclassifiable Establishments",
    "sg:postcode":"6300",
    "sg:province":"Zug",
    "wof:name":"Ora Ag",
    "wof:placetype":"venue"
},
  "geometry": {"coordinates":[8.5139198303,47.1637001038],"type":"Point"}
}