{
  "type": "Feature",
  "properties": {
    "iso:country":"CH",
    "sg:address":"Bergstrasse 32",
    "sg:city":"Geroldswil",
    "sg:orig_category":"Unternehmensberatung",
    "sg:phone":"+41 17483166",
    "sg:postcode":"8954",
    "sg:province":"Z\u00fcrich",
    "wof:name":"Wehrli Unternehmensberatung",
    "wof:placetype":"venue"
},
  "geometry": {"coordinates":[8.4122142792,47.4255714417],"type":"Point"}
}