{
  "type": "Feature",
  "properties": {
    "iso:country":"CH",
    "sg:address":"Poststrasse 11",
    "sg:city":"Chur",
    "sg:orig_category":"Fachdetailhandel in Verkaufsr\u00e4umen",
    "sg:phone":"+41 81 252 55 15",
    "sg:postcode":"7000",
    "sg:province":"Graubunden",
    "wof:name":"Qpo-philatelic-trading Ag, Chur",
    "wof:placetype":"venue"
},
  "geometry": {"coordinates":[9.5323696136,46.8498687744],"type":"Point"}
}