{
  "type": "Feature",
  "properties": {
    "iso:country":"CH",
    "sg:address":"Sempacherstrasse 19 6003 Luzern. Postfach",
    "sg:city":"Luzern",
    "sg:orig_category":"Sonstige pers\u00f6nliche Dienstleistungen Werbevermittlung",
    "sg:phone":"+41 41 310 74 00",
    "sg:postcode":"6002",
    "sg:province":"Luzern",
    "wof:name":"Kreag Ag",
    "wof:placetype":"venue"
},
  "geometry": {"coordinates":[8.3030509949,47.0403900146],"type":"Point"}
}