{
  "type": "Feature",
  "properties": {
    "iso:country":"CH",
    "sg:address":"W\u00f6schnauring 47",
    "sg:city":"Aarau",
    "sg:orig_category":"Non-Classified Establishments",
    "sg:postcode":"5000",
    "sg:province":"Aargau",
    "wof:name":"Ad Vitam Peter Blanc Gmbh Allfinanz-planung",
    "wof:placetype":"venue"
},
  "geometry": {"coordinates":[7.2659540176,46.7959709167],"type":"Point"}
}