{
  "type": "Feature",
  "properties": {
    "iso:country":"CH",
    "sg:address":"Dorfstrasse 26",
    "sg:city":"Engelberg",
    "sg:orig_category":"Detailhandel mit Brillen U anderen Sehhilfen Fachdetailhandel in Verkaufsr\u00e4umen",
    "sg:phone":"+41 22 792 01 37",
    "sg:postcode":"6390",
    "sg:province":"Obwalden",
    "wof:name":"Philippe Dutoit Opticien Sa",
    "wof:placetype":"venue"
},
  "geometry": {"coordinates":[6.112469,46.188328],"type":"Point"}
}