{
  "type": "Feature",
  "properties": {
    "iso:country":"CH",
    "sg:address":"L\u00fctzelfl\u00fchstrasse 4",
    "sg:city":"R\u00fcegsauschachen",
    "sg:orig_category":"Detailhandel mit Lederwaren U Reiseartikeln",
    "sg:phone":"+41 34 461 13 08",
    "sg:postcode":"3415",
    "sg:province":"Bern",
    "wof:name":"Anna Sch\u00f6ni Lederwaren",
    "wof:placetype":"venue"
},
  "geometry": {"coordinates":[7.6580457687,47.0167884827],"type":"Point"}
}