{
  "type": "Feature",
  "properties": {
    "iso:country":"CH",
    "sg:address":"Grundstrasse 16 6343 Risch. Postfach",
    "sg:city":"Risch",
    "sg:orig_category":"Sonstige mit der Informatik verbundene T\u00e4tigkeiten",
    "sg:postcode":"6343",
    "sg:province":"Zug",
    "wof:name":"Schumacher Informatik",
    "wof:placetype":"venue"
},
  "geometry": {"coordinates":[8.4307823181,47.1460037231],"type":"Point"}
}