{
  "type": "Feature",
  "properties": {
    "iso:country":"CH",
    "sg:address":"Maiacherstrasse 38 8604 Volketswil. Postfach",
    "sg:city":"Volketswil",
    "sg:orig_category":"Reinigungsgewerbe",
    "sg:phone":"+41 19451644",
    "sg:postcode":"8604",
    "sg:province":"Z\u00fcrich",
    "wof:name":"Lise Gmbh Geb\u00e4ude, Liegenschaften; Reparatur Und Unterhalt, Serviceleistungen, Bes. Hauswartungen Usw",
    "wof:placetype":"venue"
},
  "geometry": {"coordinates":[8.6619882584,47.3916053772],"type":"Point"}
}