{
  "type": "Feature",
  "properties": {
    "iso:country":"CH",
    "sg:address":"Kreuzplatz",
    "sg:city":"Wildegg",
    "sg:classifiers":[
        {
            "category":"Banks & Credit Unions",
            "subcategory":"Bank",
            "type":"Services"
        }
    ],
    "sg:phone":"+41 4164532155",
    "sg:postcode":"5103",
    "sg:province":"Aargau",
    "wof:name":"Hypothekarbank, Lenzburg",
    "wof:placetype":"venue"
},
  "geometry": {"coordinates":[8.165375,47.415291],"type":"Point"}
}