{
  "type": "Feature",
  "properties": {
    "iso:country":"CH",
    "sg:address":"Route De Sion 91a",
    "sg:city":"Sierre",
    "sg:orig_category":"Detailhandel mit Fleisch U Fleischwaren",
    "sg:phone":"+41 27 456 31 71",
    "sg:postcode":"3960",
    "sg:province":"Valais",
    "wof:name":"Marcelline Hermann D\u00e9lice De Ch\u00e2teaubriand",
    "wof:placetype":"venue"
},
  "geometry": {"coordinates":[7.5154628754,46.2842102051],"type":"Point"}
}