{
  "type": "Feature",
  "properties": {
    "iso:country":"CH",
    "sg:address":"Hasenmattstrasse 23",
    "sg:city":"Lommiswil",
    "sg:orig_category":"Innenarchitekturb\u00fcros",
    "sg:phone":"+41 32 641 11 51",
    "sg:postcode":"4514",
    "sg:province":"Solothurn",
    "wof:name":"Karl Bl\u00fclle Innenarchitektur",
    "wof:placetype":"venue"
},
  "geometry": {"coordinates":[7.4658489227,47.2220573425],"type":"Point"}
}