{
  "type": "Feature",
  "properties": {
    "iso:country":"CH",
    "sg:address":"Bahnhofstrasse 8",
    "sg:city":"Malters",
    "sg:orig_category":"Detailhandel mit Radio U Fernsehger\u00e4ten Elektroinstallation",
    "sg:phone":"+41 41 497 19 66",
    "sg:postcode":"6102",
    "sg:province":"Luzern",
    "wof:name":"Antennen Ag Malters Radio Burri Ag",
    "wof:placetype":"venue"
},
  "geometry": {"coordinates":[8.1820745468,47.0378684998],"type":"Point"}
}