{
  "type": "Feature",
  "properties": {
    "iso:country":"CH",
    "sg:address":"St. Alban-anlage 19",
    "sg:city":"Basel",
    "sg:orig_category":"Handelsvermittlung U Grosshandel Sonstiger Grosshandel",
    "sg:phone":"+41 61 271 11 77",
    "sg:postcode":"4052",
    "sg:province":"Basel-Stadt",
    "wof:name":"Altum Gmbh",
    "wof:placetype":"venue"
},
  "geometry": {"coordinates":[7.5967378616,47.5520057678],"type":"Point"}
}