{
  "type": "Feature",
  "properties": {
    "iso:country":"CH",
    "sg:address":"Ch. De Sous La Ferme 6 Villa Le Catalpa",
    "sg:city":"Mies",
    "sg:orig_category":"Finanzierungsinstitutionen",
    "sg:phone":"+41 22 776 35 40",
    "sg:postcode":"1295",
    "sg:province":"Vaud",
    "wof:name":"Haller Mario E.",
    "wof:placetype":"venue"
},
  "geometry": {"coordinates":[6.1760988235,46.3089599609],"type":"Point"}
}