{
  "type": "Feature",
  "properties": {
    "iso:country":"CH",
    "sg:address":"Shopping Center 9/104 8957 Spreitenbach. Postfach",
    "sg:city":"Spreitenbach",
    "sg:orig_category":"Sonstiger Grosshandel",
    "sg:phone":"+41 71 244 33 11",
    "sg:postcode":"8957",
    "sg:province":"Aargau",
    "wof:name":"Tipco Asesor Gmbh",
    "wof:placetype":"venue"
},
  "geometry": {"coordinates":[9.3798360825,47.4371337891],"type":"Point"}
}