{
  "type": "Feature",
  "properties": {
    "iso:country":"CH",
    "sg:address":"4900",
    "sg:city":"Langenthal",
    "sg:orig_category":"Vereine Gesang",
    "sg:postcode":"4900",
    "sg:province":"Bern",
    "wof:name":"Gemischter Chor Langenthal",
    "wof:placetype":"venue"
},
  "geometry": {"coordinates":[7.7974300385,47.2173309326],"type":"Point"}
}