{
  "type": "Feature",
  "properties": {
    "iso:country":"CH",
    "sg:address":"Alte Poststrasse 5",
    "sg:city":"T\u00e4gerig",
    "sg:classifiers":[
        {
            "category":"Travel",
            "subcategory":"Hotels & Motels",
            "type":"Entertainment"
        }
    ],
    "sg:phone":"+41 61 761 50 02",
    "sg:postcode":"5522",
    "sg:province":"Aargau",
    "sg:tags":[
        "hotels",
        "mit",
        "restaurant"
    ],
    "wof:name":"Gasthaus Oberfringeli",
    "wof:placetype":"venue"
},
  "geometry": {"coordinates":[7.480837822,47.3730163574],"type":"Point"}
}