{
  "type": "Feature",
  "properties": {
    "iso:country":"CH",
    "sg:address":"St\u00e4ffiserweg 8",
    "sg:city":"Solothurn",
    "sg:orig_category":"Schlossereien",
    "sg:phone":"+41 32 622 80 42",
    "sg:postcode":"4500",
    "sg:province":"Solothurn",
    "wof:name":"Patrick Beetschen Antikschlosserei",
    "wof:placetype":"venue"
},
  "geometry": {"coordinates":[7.5186729431,47.2134742737],"type":"Point"}
}