{
  "type": "Feature",
  "properties": {
    "iso:country":"CH",
    "sg:address":"Daillettes Route Des 21",
    "sg:city":"Fribourg",
    "sg:orig_category":"Unclassifiable Establishments",
    "sg:phone":"+41 26 424 51 51",
    "sg:postcode":"1700",
    "sg:province":"Fribourg",
    "wof:name":"Redasan Sa",
    "wof:placetype":"venue"
},
  "geometry": {"coordinates":[7.1462688446,46.7925186157],"type":"Point"}
}