{
  "type": "Feature",
  "properties": {
    "iso:country":"CH",
    "sg:address":"Unterwaldstatt 708",
    "sg:city":"Waldstatt",
    "sg:orig_category":"RESTAURANTS: TEA-ROOMS",
    "sg:postcode":"9104",
    "sg:province":"Appenzell Ausserrhoden",
    "wof:name":"Troxler-biser Theodor",
    "wof:placetype":"venue"
},
  "geometry": {"coordinates":[9.2923707962,47.3529434204],"type":"Point"}
}