{
  "type": "Feature",
  "properties": {
    "iso:country":"CH",
    "sg:address":"Hohlstrasse 169",
    "sg:city":"Z\u00fcrich",
    "sg:orig_category":"Sonstige Verkehrsvermittlung",
    "sg:phone":"+41 12911648",
    "sg:postcode":"8004",
    "sg:province":"Z\u00fcrich",
    "wof:name":"Verzollungsagentur D\u00f6rig Leo Ag",
    "wof:placetype":"venue"
},
  "geometry": {"coordinates":[8.5190382004,47.3804588318],"type":"Point"}
}