{
  "type": "Feature",
  "properties": {
    "iso:country":"CH",
    "sg:address":"Av. Du Bois-de-la-chapelle 57.",
    "sg:city":"Petit-lancy",
    "sg:orig_category":"Herstellung von Armaturen",
    "sg:postcode":"1213",
    "sg:province":"Gen\u00e8ve",
    "wof:name":"Negro Tommaso",
    "wof:placetype":"venue"
},
  "geometry": {"coordinates":[6.1074099541,46.1909790039],"type":"Point"}
}