{
  "type": "Feature",
  "properties": {
    "addr:full":"Verenam\u00f6\u00f6sli 1 Subingen Solothurn 4553",
    "addr:housenumber":"1",
    "addr:postcode":"4553",
    "addr:street":"Verenamoeoesli",
    "iso:country":"CH",
    "sg:address":"Verenam\u00f6\u00f6sli 1",
    "sg:city":"Subingen",
    "sg:orig_category":"Allgemeiner Hoch U Tiefbau",
    "sg:phone":"+41 32 614 24 79",
    "sg:postcode":"4553",
    "sg:province":"Solothurn",
    "wof:name":"Glutz Alois, Baugesch\u00e4ft",
    "wof:placetype":"venue"
},
  "geometry": {"coordinates":[7.622682,47.193935],"type":"Point"}
}