{
  "type": "Feature",
  "properties": {
    "iso:country":"CH",
    "sg:address":"Winistorfstrasse 56",
    "sg:city":"Hersiwil",
    "sg:orig_category":"Unclassifiable Establishments",
    "sg:postcode":"4558",
    "sg:province":"Solothurn",
    "wof:name":"Baukeramik Steiner Gmbh",
    "wof:placetype":"venue"
},
  "geometry": {"coordinates":[7.6367812157,47.1671066284],"type":"Point"}
}