{
  "type": "Feature",
  "properties": {
    "iso:country":"CH",
    "sg:address":"Bollwerk 19 3011 Bern. Postfach",
    "sg:city":"Bern",
    "sg:orig_category":"W\u00e4scherei U chemische Reinigung",
    "sg:postcode":"3005",
    "sg:province":"Bern",
    "wof:name":"Teppich-reinigung-tempo Graf Teppichreinigungen, Verlegearbeiten. Textilbodenbel\u00e4ge; Verkauf",
    "wof:placetype":"venue"
},
  "geometry": {"coordinates":[7.4407339096,46.9498252869],"type":"Point"}
}