{
  "type": "Feature",
  "properties": {
    "iso:country":"CH",
    "sg:address":"Herrenweg 60",
    "sg:city":"Allschwil",
    "sg:orig_category":"Grosshandel mit B\u00fcromaschinen Grosshandel mit Datenverarbeitungsger\u00e4ten",
    "sg:phone":"+41 61 303 30 00",
    "sg:postcode":"4123",
    "sg:province":"Basel-Landschaft",
    "wof:name":"Unitrade Informatik Impex Gmbh",
    "wof:placetype":"venue"
},
  "geometry": {"coordinates":[7.5521059036,47.5443534851],"type":"Point"}
}