{
  "type": "Feature",
  "properties": {
    "iso:country":"CH",
    "sg:address":"Wilerstrasse 69",
    "sg:city":"Bazenheid",
    "sg:orig_category":"Museen",
    "sg:phone":"+41 19101649",
    "sg:postcode":"9602",
    "sg:province":"St. Gallen",
    "wof:name":"Schmuck-galerie Bektas Rima",
    "wof:placetype":"venue"
},
  "geometry": {"coordinates":[8.6057395935,47.3268127441],"type":"Point"}
}