{
  "type": "Feature",
  "properties": {
    "iso:country":"CH",
    "sg:address":"Zimmerlistrasse 21",
    "sg:city":"Aarburg",
    "sg:orig_category":"Detailhandel mit Metallwaren, Anstrichmitteln, Glaswaren, Bau U Heimwerkerbedarf Grosshandel mit Spo",
    "sg:phone":"+41 62 791 13 50",
    "sg:postcode":"4663",
    "sg:province":"Aargau",
    "wof:name":"Technoswap Ag",
    "wof:placetype":"venue"
},
  "geometry": {"coordinates":[7.9076337814,47.3175926208],"type":"Point"}
}