{
  "type": "Feature",
  "properties": {
    "iso:country":"CH",
    "sg:address":"Reinhold Frei-strasse 58",
    "sg:city":"Z\u00fcrich",
    "sg:orig_category":"Tanzschulen, Tanzlehrer",
    "sg:phone":"+41 13413366",
    "sg:postcode":"8049",
    "sg:province":"Z\u00fcrich",
    "wof:name":"Carmen Betschart Jazzgymnastik Jazztanz",
    "wof:placetype":"venue"
},
  "geometry": {"coordinates":[8.4861383438,47.4089241028],"type":"Point"}
}