{
  "type": "Feature",
  "properties": {
    "iso:country":"CH",
    "sg:address":"Badenerstrasse 760",
    "sg:city":"Z\u00fcrich",
    "sg:orig_category":"Non-Classified Establishments",
    "sg:postcode":"8048",
    "sg:province":"Z\u00fcrich",
    "wof:name":"Duyair Gmbh",
    "wof:placetype":"venue"
},
  "geometry": {"coordinates":[8.4781293869,47.3918800354],"type":"Point"}
}