{
  "type": "Feature",
  "properties": {
    "iso:country":"CH",
    "sg:address":"Lettenstrasse 2",
    "sg:city":"Rotkreuz",
    "sg:orig_category":"Herstellung von Maschinen f\u00fcr das Papiergewerbe",
    "sg:phone":"+41 41 790 46 22",
    "sg:postcode":"6343",
    "sg:province":"Zug",
    "wof:name":"Papierprogr\u00e8s Bielomatik Gmbh",
    "wof:placetype":"venue"
},
  "geometry": {"coordinates":[8.432220459,47.1485290527],"type":"Point"}
}