{
  "type": "Feature",
  "properties": {
    "iso:country":"CH",
    "sg:address":"Hauptgasse 29",
    "sg:city":"Lichtensteig",
    "sg:orig_category":"Reiseb\u00fcros",
    "sg:phone":"+41 71 988 43 33",
    "sg:postcode":"9620",
    "sg:province":"St. Gallen",
    "wof:name":"Reiseb\u00fcro Lichtensteig Diethelm & Storchenegger",
    "wof:placetype":"venue"
},
  "geometry": {"coordinates":[9.087635994,47.3226089478],"type":"Point"}
}