{
  "type": "Feature",
  "properties": {
    "iso:country":"CH",
    "sg:address":"Freiburgstrasse 20 2500 Biel/bienne. Postfach",
    "sg:city":"Biel/bienne",
    "sg:orig_category":"Sonstiger Grosshandel",
    "sg:postcode":"2503",
    "sg:province":"Bern",
    "wof:name":"Spring & Partner",
    "wof:placetype":"venue"
},
  "geometry": {"coordinates":[7.2481408119,47.1318054199],"type":"Point"}
}