{
  "type": "Feature",
  "properties": {
    "iso:country":"CH",
    "sg:address":"Versoix Quai De 17",
    "sg:city":"Versoix",
    "sg:orig_category":"Herstellung von Elektromotoren, Generatoren U Transformatoren",
    "sg:phone":"+41 56 483 11 11",
    "sg:postcode":"1290",
    "sg:province":"Gen\u00e8ve",
    "wof:name":"Colenco Power Engineering Ag Ingenieurunternehmung",
    "wof:placetype":"venue"
},
  "geometry": {"coordinates":[8.291217804,47.4502792358],"type":"Point"}
}