{
  "type": "Feature",
  "properties": {
    "iso:country":"CH",
    "sg:address":"Route D'ambilly 1",
    "sg:city":"Th\u00f4nex",
    "sg:orig_category":"Tankstellen",
    "sg:phone":"+41 22 348 80 93",
    "sg:postcode":"1226",
    "sg:province":"Gen\u00e8ve",
    "wof:name":"Shell Switzerland Station-service",
    "wof:placetype":"venue"
},
  "geometry": {"coordinates":[6.2208299637,46.1991157532],"type":"Point"}
}