{
  "type": "Feature",
  "properties": {
    "iso:country":"CH",
    "sg:address":"Feldeggstrasse 42",
    "sg:city":"Z\u00fcrich",
    "sg:classifiers":[
        {
            "category":"Manufacturing",
            "subcategory":"Printing",
            "type":"Manufacturing & Wholesale Goods"
        }
    ],
    "sg:phone":"+41 13831610",
    "sg:postcode":"8008",
    "sg:province":"Z\u00fcrich",
    "sg:tags":[
        "house",
        "book"
    ],
    "wof:name":"Eichholzer Druck + Kopie Ag",
    "wof:placetype":"venue"
},
  "geometry": {"coordinates":[8.551581,47.360111],"type":"Point"}
}