{
  "type": "Feature",
  "properties": {
    "iso:country":"CH",
    "sg:address":"Via Al Ronchetto 7",
    "sg:city":"Lugano",
    "sg:orig_category":"Grosshandel mit Sportartikeln Sonstige mit Sport verbundene T\u00e4tigkeiten",
    "sg:phone":"+41 91 971 10 40",
    "sg:postcode":"6900",
    "sg:province":"Ticino",
    "wof:name":"Bolle Blu Sagl",
    "wof:placetype":"venue"
},
  "geometry": {"coordinates":[8.9579963684,46.0215606689],"type":"Point"}
}