{
  "type": "Feature",
  "properties": {
    "iso:country":"CH",
    "sg:address":"7436",
    "sg:city":"Medels",
    "sg:orig_category":"Landesverteidigung, Sozialversicherung \u00d6ffentliche Verwaltung",
    "sg:phone":"+41 81 664 14 44",
    "sg:postcode":"7436",
    "sg:province":"Graubunden",
    "wof:name":"Zivilschutzstelle Medels Im Rheinwald",
    "wof:placetype":"venue"
},
  "geometry": {"coordinates":[9.2958803177,46.5483093262],"type":"Point"}
}