{
  "type": "Feature",
  "properties": {
    "iso:country":"CH",
    "sg:address":"Unterm\u00fchlestrasse 12 6330 Cham. Postfach",
    "sg:city":"Baar",
    "sg:orig_category":"Non-Classified Establishments",
    "sg:postcode":"6340",
    "sg:province":"Zug",
    "wof:name":"Staubli Oliver Public Relations Kommunikations-dienstleistungen, Bes. Durch Public Relations, Medienarbeit, Marketing, Werbung Usw",
    "wof:placetype":"venue"
},
  "geometry": {"coordinates":[8.445854187,47.196231842],"type":"Point"}
}