{
  "type": "Feature",
  "properties": {
    "iso:country":"CH",
    "sg:address":"Kirchstrasse 11",
    "sg:city":"Glarus",
    "sg:orig_category":"Detailhandel mit Damenbekleidung Detailhandel mit Herrenbekleidung",
    "sg:phone":"+41 55 241 19 56",
    "sg:postcode":"8750",
    "sg:province":"Glarus",
    "wof:name":"Harry's Biker Store",
    "wof:placetype":"venue"
},
  "geometry": {"coordinates":[8.860830307,47.2597427368],"type":"Point"}
}