{
  "type": "Feature",
  "properties": {
    "iso:country":"CH",
    "sg:address":"Ernetschwilerstrasse 20",
    "sg:city":"Gommiswald",
    "sg:orig_category":"Sonstiger Grosshandel",
    "sg:phone":"+41 55 280 22 05",
    "sg:postcode":"8737",
    "sg:province":"St. Gallen",
    "wof:name":"Udo R\u00fcegg Ag Schwimmb\u00e4der & Zubeh\u00f6r",
    "wof:placetype":"venue"
},
  "geometry": {"coordinates":[9.0190420151,47.2359962463],"type":"Point"}
}