{
  "type": "Feature",
  "properties": {
    "iso:country":"CH",
    "sg:address":"Rue De La Treille 9",
    "sg:city":"Neuch\u00e2tel",
    "sg:classifiers":[
        {
            "category":"Government",
            "subcategory":"Post Office",
            "type":"Public Place"
        }
    ],
    "sg:phone":"+41 32 725 14 44",
    "sg:postcode":"2000",
    "sg:province":"Neuch\u00e2tel",
    "sg:tags":[
        "caf\u00e9s",
        "tea-rooms"
    ],
    "wof:name":"Tea-room Schmid Sa",
    "wof:placetype":"venue"
},
  "geometry": {"coordinates":[6.9294819832,46.9904098511],"type":"Point"}
}