{
  "type": "Feature",
  "properties": {
    "iso:country":"CH",
    "sg:address":"Neugutweg 9",
    "sg:city":"Vaduz",
    "sg:orig_category":"Gartencenter",
    "sg:postcode":"9490",
    "wof:name":"Gartencenter Elsensohn",
    "wof:placetype":"venue"
},
  "geometry": {"coordinates":[9.5204753876,47.1263694763],"type":"Point"}
}