{
  "type": "Feature",
  "properties": {
    "addr:full":"Av. Du G\u00e9n\u00e9ral Guisan 3 Sierre Valais 3960",
    "addr:housenumber":"3",
    "addr:postcode":"3960",
    "addr:street":"Av. Du Ge\u0301Ne\u0301Ral Guisan",
    "iso:country":"CH",
    "sg:address":"Av. Du G\u00e9n\u00e9ral Guisan 3",
    "sg:city":"Sierre",
    "sg:orig_category":"Architektur U Ingenieurb\u00fcros",
    "sg:postcode":"3960",
    "sg:province":"Valais",
    "wof:name":"G\u00e9oconseils Valentini Bruno",
    "wof:placetype":"venue"
},
  "geometry": {"coordinates":[7.532085,46.292866],"type":"Point"}
}