{
  "type": "Feature",
  "properties": {
    "iso:country":"CH",
    "sg:address":"Avenue Mercier De Molin 2",
    "sg:city":"Sierre",
    "sg:orig_category":"Physiotherapie",
    "sg:phone":"+41 27 456 56 00",
    "sg:postcode":"3960",
    "sg:province":"Valais",
    "wof:name":"Heidi Volken Physioth\u00e9rapie",
    "wof:placetype":"venue"
},
  "geometry": {"coordinates":[7.5285801888,46.2921409607],"type":"Point"}
}