{
  "type": "Feature",
  "properties": {
    "iso:country":"CH",
    "sg:address":"Werkstrasse 10",
    "sg:city":"Diepoldsau",
    "sg:orig_category":"Herstellung von Medikamenten U sonstigen pharmazeutischen Erzeugnissen Herstellung von pharmazeutisc",
    "sg:phone":"+41 71 455 14 90",
    "sg:postcode":"9444",
    "sg:province":"St. Gallen",
    "wof:name":"Sano-pharm E.zehentmayer Ag",
    "wof:placetype":"venue"
},
  "geometry": {"coordinates":[9.4112644196,47.487991333],"type":"Point"}
}