{
  "type": "Feature",
  "properties": {
    "iso:country":"CH",
    "sg:address":"Grabenmattstrasse 32",
    "sg:city":"Oberrohrdorf",
    "sg:orig_category":"Sportvereine Ballsport Handball",
    "sg:phone":"+41 56 496 61 55",
    "sg:postcode":"5452",
    "sg:province":"Aargau",
    "wof:name":"Handballclub Tv Stetten",
    "wof:placetype":"venue"
},
  "geometry": {"coordinates":[8.310956955,47.4215164185],"type":"Point"}
}