{
  "type": "Feature",
  "properties": {
    "addr:full":"St\u00f6renbergstrasse 16 Mammern Thurgau 8265",
    "addr:housenumber":"16",
    "addr:postcode":"8265",
    "addr:street":"Stoerenbergstrasse;Thurgau",
    "iso:country":"CH",
    "sg:address":"St\u00f6renbergstrasse 16",
    "sg:city":"Mammern",
    "sg:orig_category":"Allgemeiner Hochbau Strassenbau",
    "sg:phone":"+41 52 741 50 57",
    "sg:postcode":"8265",
    "sg:province":"Thurgau",
    "wof:name":"H\u00e4ni-bau Ag",
    "wof:placetype":"venue"
},
  "geometry": {"coordinates":[8.913449,47.642815],"type":"Point"}
}