{
  "type": "Feature",
  "properties": {
    "iso:country":"CH",
    "sg:address":"C\u00e4cilienstrasse 3 8032 Z\u00fcrich",
    "sg:city":"Zust",
    "sg:orig_category":"Unclassifiable Establishments",
    "sg:phone":"+41 55 240 89 89",
    "sg:postcode":"32",
    "wof:name":"Inrel Ag",
    "wof:placetype":"venue"
},
  "geometry": {"coordinates":[8.8452653885,47.2538757324],"type":"Point"}
}