{
  "type": "Feature",
  "properties": {
    "iso:country":"CH",
    "sg:address":"Rue De Saint-maurice 9",
    "sg:city":"Court\u00e9telle",
    "sg:orig_category":"Sanit\u00e4r, Heizungs U L\u00fcftungsinstallation Sanit\u00e4rinstallation",
    "sg:phone":"+41 32 422 58 46",
    "sg:postcode":"2852",
    "sg:province":"Jura",
    "wof:name":"Migliano Vincent",
    "wof:placetype":"venue"
},
  "geometry": {"coordinates":[7.317070961,47.3442420959],"type":"Point"}
}