{
  "type": "Feature",
  "properties": {
    "iso:country":"CH",
    "sg:address":"Weiningerstrasse 77",
    "sg:city":"Regensdorf",
    "sg:orig_category":"Fahrschulen, Flugschulen",
    "sg:phone":"+41 79 635 90 90",
    "sg:postcode":"8105",
    "sg:province":"Z\u00fcrich",
    "wof:name":"Markus K\u00fcenzi Autofahrschule",
    "wof:placetype":"venue"
},
  "geometry": {"coordinates":[7.690926075,46.6257705688],"type":"Point"}
}