{
  "type": "Feature",
  "properties": {
    "iso:country":"CH",
    "sg:address":"Hembrunnstrasse 17",
    "sg:city":"Dottikon",
    "sg:orig_category":"Instandhaltung U Reparatur von Automobilen",
    "sg:phone":"+41 26 494 12 37",
    "sg:postcode":"5605",
    "sg:province":"Aargau",
    "wof:name":"A. & O. Piller Hofmatt-garage Mitsubishi",
    "wof:placetype":"venue"
},
  "geometry": {"coordinates":[7.2762241364,46.7829971313],"type":"Point"}
}