{
  "type": "Feature",
  "properties": {
    "addr:full":"B\u00fcelenstrasse 4 W\u00e4denswil Z\u00fcrich 8820",
    "addr:housenumber":"4",
    "addr:postcode":"8820",
    "addr:street":"Bueelenstrasse;Zuerich",
    "iso:country":"CH",
    "sg:address":"B\u00fcelenstrasse 4",
    "sg:city":"W\u00e4denswil",
    "sg:classifiers":[
        {
            "category":"Arts & Performance",
            "subcategory":"Music",
            "type":"Entertainment"
        }
    ],
    "sg:phone":"+41 17802727",
    "sg:postcode":"8820",
    "sg:province":"Z\u00fcrich",
    "sg:tags":[
        "system",
        "background"
    ],
    "wof:name":"007.ch/karaoke-entertainment Gmbh",
    "wof:placetype":"venue"
},
  "geometry": {"coordinates":[8.663506,47.231777],"type":"Point"}
}