{
  "type": "Feature",
  "properties": {
    "iso:country":"CH",
    "sg:address":"Burgmattstrasse 16",
    "sg:city":"Waldenburg",
    "sg:orig_category":"Kaminfeger Reinigungsgewerbe",
    "sg:phone":"+41 61 961 91 65",
    "sg:postcode":"4437",
    "sg:province":"Basel-Landschaft",
    "wof:name":"Ramseier Simon",
    "wof:placetype":"venue"
},
  "geometry": {"coordinates":[7.7509031296,47.3849906921],"type":"Point"}
}