{
  "type": "Feature",
  "properties": {
    "iso:country":"CH",
    "sg:address":"Oberwiler Kirchweg 9a",
    "sg:city":"Zug",
    "sg:orig_category":"Forschung U Entwicklung im Bereich der Naturwissenschaften",
    "sg:phone":"+41 62 842 33 41",
    "sg:postcode":"6300",
    "sg:province":"Zug",
    "wof:name":"Servichem Ag",
    "wof:placetype":"venue"
},
  "geometry": {"coordinates":[8.5163402557,47.1587982178],"type":"Point"}
}