{
  "type": "Feature",
  "properties": {
    "iso:country":"CH",
    "sg:address":"Via Suot Mulin",
    "sg:city":"Celerina",
    "sg:orig_category":"Unternehmensberatung",
    "sg:postcode":"7505",
    "sg:province":"Graubunden",
    "wof:name":"Huber Hans J., Dipl. Wirtschaftspr\u00fcfer",
    "wof:placetype":"venue"
},
  "geometry": {"coordinates":[8.4621114731,47.3601722717],"type":"Point"}
}