{
  "type": "Feature",
  "properties": {
    "iso:country":"CH",
    "sg:address":"Route De Saint-julien 119",
    "sg:city":"Plan-les-ouates",
    "sg:orig_category":"Elektroinstallation",
    "sg:phone":"+41 22 794 96 66",
    "sg:postcode":"1228",
    "sg:province":"Gen\u00e8ve",
    "wof:name":"Puchat Paul Sa",
    "wof:placetype":"venue"
},
  "geometry": {"coordinates":[6.1204991341,46.1696243286],"type":"Point"}
}