{
  "type": "Feature",
  "properties": {
    "iso:country":"CH",
    "sg:address":"Unterdorfstrasse 35",
    "sg:city":"Buchrain",
    "sg:orig_category":"Sonstige mit der Informatik verbundene T\u00e4tigkeiten",
    "sg:postcode":"6033",
    "sg:province":"Luzern",
    "wof:name":"Data-case Ammann",
    "wof:placetype":"venue"
},
  "geometry": {"coordinates":[8.3535442352,47.0967674255],"type":"Point"}
}