{
  "type": "Feature",
  "properties": {
    "iso:country":"CH",
    "sg:address":"Rue Du Vingt-trois Juin",
    "sg:city":"Courroux",
    "sg:orig_category":"S\u00e4gewerke",
    "sg:phone":"+41 32 422 20 25",
    "sg:postcode":"2822",
    "sg:province":"Jura",
    "wof:name":"Scierie Studer Sa",
    "wof:placetype":"venue"
},
  "geometry": {"coordinates":[7.3671998978,47.3620910645],"type":"Point"}
}