{
  "type": "Feature",
  "properties": {
    "iso:country":"CH",
    "sg:address":"Nauenstrasse 55",
    "sg:city":"Basel",
    "sg:orig_category":"Zahnarztpraxen",
    "sg:phone":"+41 61 271 00 92",
    "sg:postcode":"4052",
    "sg:province":"Basel-Stadt",
    "wof:name":"Dr.med.dent.hansj. Gensheimer Zahnarzt",
    "wof:placetype":"venue"
},
  "geometry": {"coordinates":[7.5939230919,47.547077179],"type":"Point"}
}