{
  "type": "Feature",
  "properties": {
    "iso:country":"CH",
    "sg:address":"Kreuzgasse 4",
    "sg:city":"Morat",
    "sg:orig_category":"RESTAURANTS: TEA-ROOMS",
    "sg:phone":"+41 26 670 21 22",
    "sg:postcode":"3280",
    "sg:province":"Fribourg",
    "wof:name":"Pizzeria Taverna Italiana Paszti Istvan Und Klara",
    "wof:placetype":"venue"
},
  "geometry": {"coordinates":[7.1167321205,46.9283561707],"type":"Point"}
}