{
  "type": "Feature",
  "properties": {
    "iso:country":"CH",
    "sg:address":"Levron",
    "sg:city":"Levron",
    "sg:classifiers":[
        {
            "category":"Banks & Credit Unions",
            "subcategory":"Bank",
            "type":"Services"
        }
    ],
    "sg:phone":"+41 27 785 18 14",
    "sg:postcode":"1942",
    "sg:province":"Valais",
    "wof:name":"Raiffeisen",
    "wof:placetype":"venue"
},
  "geometry": {"coordinates":[7.16049,46.095032],"type":"Point"}
}