{
  "type": "Feature",
  "properties": {
    "iso:country":"CH",
    "sg:address":"Chemin Des Clochetons 33",
    "sg:city":"Lausanne",
    "sg:orig_category":"Werbung",
    "sg:phone":"+41 21 625 25 35",
    "sg:postcode":"1004",
    "sg:province":"Vaud",
    "wof:name":"Publirahm, Rahm Jean-pierre",
    "wof:placetype":"venue"
},
  "geometry": {"coordinates":[6.6174287796,46.5262107849],"type":"Point"}
}