{
  "type": "Feature",
  "properties": {
    "iso:country":"CH",
    "sg:address":"Chemin De Bouleyres 71",
    "sg:city":"Bulle",
    "sg:orig_category":"Organisationen der Wohlfahrtspflege",
    "sg:phone":"+41 26 912 99 29",
    "sg:postcode":"1630",
    "sg:province":"Fribourg",
    "wof:name":"Pro Juventute",
    "wof:placetype":"venue"
},
  "geometry": {"coordinates":[7.0650858879,46.6157264709],"type":"Point"}
}