{
  "type": "Feature",
  "properties": {
    "iso:country":"CH",
    "sg:address":"H\u00fcnenbergerstrasse 3",
    "sg:city":"Cham",
    "sg:orig_category":"Arztpraxen",
    "sg:phone":"+41 41 780 39 88",
    "sg:postcode":"6330",
    "sg:province":"Zug",
    "wof:name":"Dr.med.valerie Meier Spezial\u00e4rztin Fmh",
    "wof:placetype":"venue"
},
  "geometry": {"coordinates":[8.45721,47.179588],"type":"Point"}
}