{
  "type": "Feature",
  "properties": {
    "addr:full":"Route De L'a\u00e9roport 10 1217 Meyrin. Postfach Meyrin Gen\u00e8ve 1217",
    "addr:housenumber":"10",
    "addr:postcode":"1217;postfach;1217",
    "addr:street":"Route De L'Ae \u0301Roport",
    "iso:country":"CH",
    "sg:address":"Route De L'a\u00e9roport 10 1217 Meyrin. Postfach",
    "sg:city":"Meyrin",
    "sg:orig_category":"Binnenschiffahrt",
    "sg:postcode":"1217",
    "sg:province":"Gen\u00e8ve",
    "wof:name":"Cssa Chartering And Shipping Services Sa Affr\u00e9ter Et Fr\u00e9ter \u00e0 Terme Ou Au Voyage Des Navires Pour Le Transport D'hydrocarbures, De Produits Chimiques Ou De Marchandises Appartenant \u00e0 Des Soci\u00e9t\u00e9s Etc",
    "wof:placetype":"venue"
},
  "geometry": {"coordinates":[6.105718,46.229107],"type":"Point"}
}