{
  "type": "Feature",
  "properties": {
    "iso:country":"CH",
    "sg:address":"2802",
    "sg:city":"Develier",
    "sg:orig_category":"Unclassifiable Establishments",
    "sg:postcode":"2802",
    "sg:province":"Jura",
    "wof:name":"Si La Communance Sa",
    "wof:placetype":"venue"
},
  "geometry": {"coordinates":[7.2934741974,47.355556488],"type":"Point"}
}