{
  "type": "Feature",
  "properties": {
    "iso:country":"CH",
    "sg:address":"Schw\u00e4rzistr. 6",
    "sg:city":"Freienbach",
    "sg:classifiers":[
        {
            "category":"Shopping",
            "subcategory":"Gifts & Souvenirs",
            "type":"Retail Goods"
        }
    ],
    "sg:phone":"+41 55 415 41 41",
    "sg:postcode":"8807",
    "sg:province":"Schwyz",
    "sg:tags":[
        "product",
        "miscellaneous"
    ],
    "wof:name":"Lombbard Ag",
    "wof:placetype":"venue"
},
  "geometry": {"coordinates":[8.7587518692,47.2014312744],"type":"Point"}
}