{
  "type": "Feature",
  "properties": {
    "iso:country":"CH",
    "sg:address":"Ifangstrasse 12a 8603 Schwerzenbach. Postfach",
    "sg:city":"Schwerzenbach",
    "sg:orig_category":"Vermietung U Verpachtung von eigenen Immobilien",
    "sg:postcode":"8609",
    "sg:province":"Z\u00fcrich",
    "wof:name":"Ifang Gewerbezentrum Ag",
    "wof:placetype":"venue"
},
  "geometry": {"coordinates":[8.6631336212,47.3831253052],"type":"Point"}
}