{
  "type": "Feature",
  "properties": {
    "iso:country":"CH",
    "sg:address":"Hofstattstrasse 2",
    "sg:city":"Recherswil",
    "sg:orig_category":"Arztpraxen",
    "sg:phone":"+41 32 675 44 64",
    "sg:postcode":"4565",
    "sg:province":"Solothurn",
    "wof:name":"Dr.med.j\u00f6rg L\u00fcthy Arzt F.allgemeine Medizin Fmh",
    "wof:placetype":"venue"
},
  "geometry": {"coordinates":[7.593557,47.164494],"type":"Point"}
}