{
  "type": "Feature",
  "properties": {
    "iso:country":"CH",
    "sg:address":"Sarments Chemin Des 4",
    "sg:city":"Mies-tannay",
    "sg:orig_category":"Non-Classified Establishments",
    "sg:postcode":"1295",
    "sg:province":"Vaud",
    "wof:name":"L'immobiliere, Christian Naudin",
    "wof:placetype":"venue"
},
  "geometry": {"coordinates":[6.1724500656,46.3060684204],"type":"Point"}
}