{
  "type": "Feature",
  "properties": {
    "iso:country":"CH",
    "sg:address":"Sandstrasse",
    "sg:city":"Sch\u00f6nb\u00fchl-urtenen",
    "sg:orig_category":"Drogerien Sonstiger Fachdetailhandel mit Nahrungsmitteln, Getr\u00e4nken U Tabak in Verkaufsr\u00e4umen",
    "sg:phone":"+41 31 859 13 95",
    "sg:postcode":"3322",
    "sg:province":"Bern",
    "wof:name":"Pedro-drogerie Ag Durtschi",
    "wof:placetype":"venue"
},
  "geometry": {"coordinates":[7.5026202202,47.0184593201],"type":"Point"}
}