{
  "type": "Feature",
  "properties": {
    "iso:country":"CH",
    "sg:address":"Adam Zeltner-weg 5",
    "sg:city":"Olten",
    "sg:orig_category":"Advokaturb\u00fcros Notariate",
    "sg:phone":"+41 62 212 40 44",
    "sg:postcode":"4600",
    "sg:province":"Solothurn",
    "wof:name":"Dr.gaston Kupper Advokatur-& Notariatsb\u00fcro",
    "wof:placetype":"venue"
},
  "geometry": {"coordinates":[7.8935,47.355427],"type":"Point"}
}