{
  "type": "Feature",
  "properties": {
    "iso:country":"CH",
    "sg:address":"L\u00fctschinenstrasse 15",
    "sg:city":"B\u00f6nigen",
    "sg:orig_category":"K\u00fcnstlerische U schriftstellerische T\u00e4tigkeiten U Darbietungen",
    "sg:phone":"+41 33 822 42 14",
    "sg:postcode":"3806",
    "sg:province":"Bern",
    "wof:name":"St\u00e4hli Natursteine Ag",
    "wof:placetype":"venue"
},
  "geometry": {"coordinates":[7.8944678307,46.6898918152],"type":"Point"}
}