{
  "type": "Feature",
  "properties": {
    "iso:country":"CH",
    "sg:address":"Pflanzschulstrasse 43 8400 Winterthur. Postfach",
    "sg:city":"Winterthur",
    "sg:orig_category":"Softwareentwicklung U beratung",
    "sg:postcode":"8400",
    "sg:province":"Z\u00fcrich",
    "wof:name":"Hc.solution Ag Informatik-l\u00f6sungen; Entwicklung. Informatik-produkte; Vertrieb Usw",
    "wof:placetype":"venue"
},
  "geometry": {"coordinates":[8.7390575409,47.4998664856],"type":"Point"}
}