{
  "type": "Feature",
  "properties": {
    "iso:country":"CH",
    "sg:address":"Rh\u00f4ne Rue Du 29 1204 Gen\u00e8ve. Postfach",
    "sg:city":"Gen\u00e8ve",
    "sg:orig_category":"Pensionskassen",
    "sg:phone":"+41 32 751 35 35",
    "sg:postcode":"1204",
    "sg:province":"Gen\u00e8ve",
    "wof:name":"Caisse De Pensions Des Lamineries Matthey Sa",
    "wof:placetype":"venue"
},
  "geometry": {"coordinates":[7.0901761055,47.0630378723],"type":"Point"}
}