{
  "type": "Feature",
  "properties": {
    "iso:country":"CH",
    "sg:address":"Industriestrasse 23 4922 B\u00fctzberg. Postfach",
    "sg:city":"B\u00fctzberg",
    "sg:orig_category":"Bau U Wohngenossenschaften",
    "sg:postcode":"4922",
    "sg:province":"Bern",
    "wof:name":"Baugen.buchiacker B\u00fctzberg Coop Regionallager-gen.",
    "wof:placetype":"venue"
},
  "geometry": {"coordinates":[7.754183,47.21386],"type":"Point"}
}