{
  "type": "Feature",
  "properties": {
    "iso:country":"CH",
    "sg:address":"Kirschgarten 18 4124 Sch\u00f6nenbuch. Postfach",
    "sg:city":"Basel",
    "sg:orig_category":"Non-Classified Establishments",
    "sg:postcode":"4051",
    "sg:province":"Basel-Stadt",
    "wof:name":"Import Und Export Pavkovic-m\u00e4rki Frau Heidi",
    "wof:placetype":"venue"
},
  "geometry": {"coordinates":[8.4525680542,47.2761726379],"type":"Point"}
}