{
  "type": "Feature",
  "properties": {
    "iso:country":"CH",
    "sg:address":"Zunzgerstrasse 2",
    "sg:city":"Sissach",
    "sg:orig_category":"Museen",
    "sg:phone":"+41 61 971 32 12",
    "sg:postcode":"4450",
    "sg:province":"Basel-Landschaft",
    "wof:name":"Heimatmuseum",
    "wof:placetype":"venue"
},
  "geometry": {"coordinates":[7.8100218773,47.4637985229],"type":"Point"}
}