{
  "type": "Feature",
  "properties": {
    "iso:country":"CH",
    "sg:address":"Mariahilfgasse 7",
    "sg:city":"Luzern",
    "sg:orig_category":"Fussreflexzonenmassage Naturheil\u00e4rzte and Heilpraktiker",
    "sg:postcode":"6004",
    "sg:province":"Luzern",
    "wof:name":"Marcella Gottsponer Fussreflexzonenmassage",
    "wof:placetype":"venue"
},
  "geometry": {"coordinates":[8.3052978516,47.0535736084],"type":"Point"}
}