{
  "type": "Feature",
  "properties": {
    "iso:country":"CH",
    "sg:address":"Dreilindenstrasse 13",
    "sg:city":"Luzern",
    "sg:orig_category":"Religi\u00f6se Vereinigungen divers",
    "sg:phone":"+41 41 410 04 39",
    "sg:postcode":"6006",
    "sg:province":"Luzern",
    "wof:name":"Corporis-christi-bruderschaft",
    "wof:placetype":"venue"
},
  "geometry": {"coordinates":[8.3133792877,47.0566291809],"type":"Point"}
}