{
  "type": "Feature",
  "properties": {
    "iso:country":"CH",
    "sg:address":"Ottostrasse 29",
    "sg:city":"Chur",
    "sg:orig_category":"Wirtschaftspr\u00fcfung, Steuerberatung U Treuhand",
    "sg:phone":"+41 81 252 22 12",
    "sg:postcode":"7000",
    "sg:province":"Graubunden",
    "wof:name":"Allemann + Gredig Treuhand Und Revisions Ag",
    "wof:placetype":"venue"
},
  "geometry": {"coordinates":[9.5336322784,46.8536605835],"type":"Point"}
}