{
  "type": "Feature",
  "properties": {
    "iso:country":"CH",
    "sg:address":"Ackerstrasse 1",
    "sg:city":"Herrliberg",
    "sg:orig_category":"Technische B\u00fcros Hoch-& Tiefbau",
    "sg:phone":"+41 19916235",
    "sg:postcode":"8704",
    "sg:province":"Z\u00fcrich",
    "wof:name":"Peter Hirsiger Bautechnisches B\u00fcro",
    "wof:placetype":"venue"
},
  "geometry": {"coordinates":[8.6109323502,47.2938461304],"type":"Point"}
}