{
  "type": "Feature",
  "properties": {
    "iso:country":"CH",
    "sg:address":"Via F. Borromini 1",
    "sg:city":"Chiasso",
    "sg:orig_category":"Unclassifiable Establishments",
    "sg:postcode":"6830",
    "sg:province":"Ticino",
    "wof:name":"Maurizio Verga",
    "wof:placetype":"venue"
},
  "geometry": {"coordinates":[9.0254020691,45.8334655762],"type":"Point"}
}