{
  "type": "Feature",
  "properties": {
    "addr:full":"Rue Communaux 2 Vevey Vaud 1800",
    "addr:housenumber":"2",
    "addr:postcode":"1800",
    "addr:street":"Rue Communaux",
    "iso:country":"CH",
    "sg:address":"Rue Communaux 2",
    "sg:city":"Vevey",
    "sg:classifiers":[
        {
            "category":"Social Services",
            "subcategory":"Retirement Home",
            "type":"Services"
        }
    ],
    "sg:phone":"+41 21 922 68 71",
    "sg:postcode":"1800",
    "sg:province":"Vaud",
    "sg:tags":[
        "pflegeheime",
        "u",
        "alters"
    ],
    "wof:name":"Etablissement M\u00e9dico-social Beau-s\u00e9jour",
    "wof:placetype":"venue"
},
  "geometry": {"coordinates":[6.849015,46.460751],"type":"Point"}
}