{
  "type": "Feature",
  "properties": {
    "iso:country":"CH",
    "sg:address":"Platten 4",
    "sg:city":"B\u00fctschwil",
    "sg:orig_category":"Elektroinstallation",
    "sg:postcode":"9606",
    "sg:province":"St. Gallen",
    "wof:name":"F\u00e4ssler K., Elektro-anlagen",
    "wof:placetype":"venue"
},
  "geometry": {"coordinates":[8.8226995468,47.446521759],"type":"Point"}
}