{
  "type": "Feature",
  "properties": {
    "iso:country":"CH",
    "sg:address":"Maispracherstrasse 34",
    "sg:city":"Magden",
    "sg:orig_category":"Grosshandel mit sonstigen Maschinen U Ausr\u00fcstungen f\u00fcr Industrie, Handel U Schiffahrt Herstellung vo",
    "sg:phone":"+41 61 843 94 30",
    "sg:postcode":"4312",
    "sg:province":"Aargau",
    "wof:name":"Pc-laborsystem Gmbh",
    "wof:placetype":"venue"
},
  "geometry": {"coordinates":[7.8183960915,47.5273704529],"type":"Point"}
}