{
  "type": "Feature",
  "properties": {
    "iso:country":"CH",
    "sg:address":"Talacker 41 8001 Z\u00fcrich. Postfach",
    "sg:city":"Z\u00fcrich",
    "sg:orig_category":"Kauf U Verkauf von Immobilien auf eigene Rechnung",
    "sg:postcode":"8001",
    "sg:province":"Z\u00fcrich",
    "wof:name":"Haus Zum Sihlgarten, Schnyder Von Wartensee & Co Liegenschaftenverwaltung, -nutzung Usw",
    "wof:placetype":"venue"
},
  "geometry": {"coordinates":[8.5345478058,47.3723602295],"type":"Point"}
}