{
  "type": "Feature",
  "properties": {
    "iso:country":"CH",
    "sg:address":"Bahnhofstrasse 8",
    "sg:city":"Dulliken",
    "sg:orig_category":"Detailhandel mit Getr\u00e4nken",
    "sg:phone":"+41 62 295 12 44",
    "sg:postcode":"4657",
    "sg:province":"Solothurn",
    "wof:name":"Getr\u00e4nke Joller Gmbh",
    "wof:placetype":"venue"
},
  "geometry": {"coordinates":[7.9462490082,47.3528442383],"type":"Point"}
}