{
  "type": "Feature",
  "properties": {
    "iso:country":"CH",
    "sg:address":"Dennliweg 70b",
    "sg:city":"Langenthal",
    "sg:orig_category":"Sanit\u00e4r, Heizungs U L\u00fcftungsinstallation Sanit\u00e4rinstallation U Spenglerei",
    "sg:phone":"+41 62 922 80 38",
    "sg:postcode":"4900",
    "sg:province":"Bern",
    "wof:name":"S\u00e4gesser + B\u00fcrki + Cie.",
    "wof:placetype":"venue"
},
  "geometry": {"coordinates":[7.7767829895,47.2016525269],"type":"Point"}
}