{
  "type": "Feature",
  "properties": {
    "iso:country":"CH",
    "sg:address":"Rue De Lausanne 64",
    "sg:city":"Sion",
    "sg:classifiers":[
        {
            "category":"Bars & Pubs",
            "type":"Food & Drink"
        }
    ],
    "sg:phone":"+41 27 322 49 77",
    "sg:postcode":"1950",
    "sg:province":"Valais",
    "wof:name":"Britannia Pub",
    "wof:placetype":"venue"
},
  "geometry": {"coordinates":[7.350407,46.230545],"type":"Point"}
}