{
  "type": "Feature",
  "properties": {
    "iso:country":"CH",
    "sg:address":"Gewerbestrasse 11",
    "sg:city":"Zuchwil",
    "sg:orig_category":"Pensionskassen",
    "sg:phone":"+41 32 685 45 35",
    "sg:postcode":"4528",
    "sg:province":"Solothurn",
    "wof:name":"Wohlfahrtsstiftung Der Hediger Felix Ag",
    "wof:placetype":"venue"
},
  "geometry": {"coordinates":[7.5743589401,47.2004508972],"type":"Point"}
}