{
  "type": "Feature",
  "properties": {
    "iso:country":"CH",
    "sg:address":"Leimbachstrasse 51 8041 Z\u00fcrich. Postfach",
    "sg:city":"Z\u00fcrich",
    "sg:orig_category":"Elektroinstallation",
    "sg:phone":"+41 14821382",
    "sg:postcode":"8041",
    "sg:province":"Z\u00fcrich",
    "wof:name":"Elektro Team Ag",
    "wof:placetype":"venue"
},
  "geometry": {"coordinates":[8.5186862946,47.3335533142],"type":"Point"}
}