{
  "type": "Feature",
  "properties": {
    "iso:country":"CH",
    "sg:address":"Laupenstrasse 35",
    "sg:city":"Rossh\u00e4usern",
    "sg:orig_category":"Detailhandel mit Milcherzeugnissen U Eiern Verarbeitung von Milch",
    "sg:phone":"+41 31 751 01 95",
    "sg:postcode":"3204",
    "sg:province":"Bern",
    "wof:name":"Hans St\u00e4mpfli K\u00e4serei",
    "wof:placetype":"venue"
},
  "geometry": {"coordinates":[7.276966095,46.9344558716],"type":"Point"}
}