{
  "type": "Feature",
  "properties": {
    "iso:country":"CH",
    "sg:address":"1892",
    "sg:city":"Lavey-village",
    "sg:orig_category":"Unclassifiable Establishments",
    "sg:postcode":"1892",
    "sg:province":"Vaud",
    "wof:name":"Si Le Courset Sa",
    "wof:placetype":"venue"
},
  "geometry": {"coordinates":[7.017250061,46.219909668],"type":"Point"}
}