{
  "type": "Feature",
  "properties": {
    "iso:country":"CH",
    "sg:address":"B\u00e4lliz 54 3600 Thun. Postfach 1001",
    "sg:city":"Thun",
    "sg:orig_category":"Detailhandel mit Schuhen",
    "sg:phone":"+41 33 222 26 77",
    "sg:postcode":"3601",
    "sg:province":"Bern",
    "wof:name":"Eugen Fine Shoe Selection",
    "wof:placetype":"venue"
},
  "geometry": {"coordinates":[7.6281700134,46.7576980591],"type":"Point"}
}