{
  "type": "Feature",
  "properties": {
    "iso:country":"CH",
    "sg:address":"Avenue De La Prairie 22",
    "sg:city":"Vevey",
    "sg:orig_category":"Arztpraxen",
    "sg:phone":"+41 21 944 33 37",
    "sg:postcode":"1800",
    "sg:province":"Vaud",
    "wof:name":"Dr M\u00e9d. Daniel Bron M\u00e9decin Sp\u00e9cialiste Fmh",
    "wof:placetype":"venue"
},
  "geometry": {"coordinates":[6.853774,46.458736],"type":"Point"}
}