{
  "type": "Feature",
  "properties": {
    "iso:country":"CH",
    "sg:address":"Rue De La Poste 24",
    "sg:city":"Fully",
    "sg:orig_category":"Zahnarztpraxen",
    "sg:phone":"+41 27 746 39 93",
    "sg:postcode":"1926",
    "sg:province":"Valais",
    "wof:name":"Dr M\u00e9d.dent. Pierre-o. Ducrest M\u00e9decin-dentiste",
    "wof:placetype":"venue"
},
  "geometry": {"coordinates":[7.1143989563,46.1376953125],"type":"Point"}
}