{
  "type": "Feature",
  "properties": {
    "iso:country":"CH",
    "sg:address":"Weidstrasse 18a",
    "sg:city":"Zug",
    "sg:orig_category":"Elektrizit\u00e4tsversorgung Grosshandel mit sonstigen Maschinen U Ausr\u00fcstungen f\u00fcr Industrie, Handel U S",
    "sg:phone":"+41 41 910 47 85",
    "sg:postcode":"6300",
    "sg:province":"Zug",
    "wof:name":"Biolet Gmbh",
    "wof:placetype":"venue"
},
  "geometry": {"coordinates":[8.5274648666,47.1686935425],"type":"Point"}
}