{
  "type": "Feature",
  "properties": {
    "iso:country":"CH",
    "sg:address":"Gertrudstrasse 69 8000 Z\u00fcrich. Postfach",
    "sg:city":"Z\u00fcrich",
    "sg:orig_category":"Grosshandel mit Nahrungsmitteln, Getr\u00e4nken U Tabakwaren ohne ausgepr\u00e4gten Schwerpunkt",
    "sg:postcode":"8001",
    "sg:province":"Z\u00fcrich",
    "wof:name":"Meier & Hauri Lebensmittel Gmbh",
    "wof:placetype":"venue"
},
  "geometry": {"coordinates":[8.5130872726,47.3721008301],"type":"Point"}
}