{
  "type": "Feature",
  "properties": {
    "iso:country":"CH",
    "sg:address":"Avenue De Cour 6a",
    "sg:city":"Lausanne",
    "sg:orig_category":"Handelsvermittlung U Grosshandel",
    "sg:phone":"+41 21 624 00 66",
    "sg:postcode":"1007",
    "sg:province":"Vaud",
    "wof:name":"Bar Au M\u00e8tre S\u00e0rl Achats Vente Courtage",
    "wof:placetype":"venue"
},
  "geometry": {"coordinates":[6.6262578964,46.512260437],"type":"Point"}
}