{
  "type": "Feature",
  "properties": {
    "iso:country":"CH",
    "sg:address":"Neuweilerstrasse",
    "sg:city":"Allschwil",
    "sg:orig_category":"Zoll- and Grenzb\u00fcros",
    "sg:phone":"+41 52 653 14 21",
    "sg:postcode":"4123",
    "sg:province":"Basel-Landschaft",
    "wof:name":"Zollamt Bargen",
    "wof:placetype":"venue"
},
  "geometry": {"coordinates":[8.6124200821,47.7928199768],"type":"Point"}
}