{
  "type": "Feature",
  "properties": {
    "iso:country":"CH",
    "sg:address":"Alpsteinstrasse 16c",
    "sg:city":"Herisau",
    "sg:orig_category":"Vorschulen, Kinderg\u00e4rten",
    "sg:phone":"+41 71 352 17 25",
    "sg:postcode":"9100",
    "sg:province":"Appenzell Ausserrhoden",
    "wof:name":"Kindergartenpavillon Wilen",
    "wof:placetype":"venue"
},
  "geometry": {"coordinates":[9.2790699005,47.3781700134],"type":"Point"}
}