{
  "type": "Feature",
  "properties": {
    "iso:country":"CH",
    "sg:address":"Chandoline Route De 1950 Sion Case Postale 4117",
    "sg:city":"Sitten",
    "sg:orig_category":"Zimmerei, Dachdeckerei, Bauspenglerei U Abdichtung",
    "sg:phone":"+41 27 203 31 34",
    "sg:postcode":"1950",
    "sg:province":"Valais",
    "wof:name":"Fournier Andr\u00e9 & Cie Sa",
    "wof:placetype":"venue"
},
  "geometry": {"coordinates":[7.3641381264,46.2191581726],"type":"Point"}
}