{
  "type": "Feature",
  "properties": {
    "iso:country":"CH",
    "sg:address":"Via Cantonale",
    "sg:city":"Mezzovico",
    "sg:orig_category":"Druckweiterverarbeitung Offsetdruck",
    "sg:phone":"+41 91 946 16 76",
    "sg:postcode":"6805",
    "sg:province":"Ticino",
    "wof:name":"Silvano Rovelli Print Color Tipografia",
    "wof:placetype":"venue"
},
  "geometry": {"coordinates":[8.9198827744,46.0879859924],"type":"Point"}
}