{
  "type": "Feature",
  "properties": {
    "iso:country":"CH",
    "sg:address":"Route De Courfaivre 61 D",
    "sg:city":"Soulce",
    "sg:orig_category":"Non-Classified Establishments",
    "sg:postcode":"2864",
    "sg:province":"Jura",
    "wof:name":"Domon Charles",
    "wof:placetype":"venue"
},
  "geometry": {"coordinates":[7.2648868561,47.3057289124],"type":"Point"}
}