{
  "type": "Feature",
  "properties": {
    "iso:country":"CH",
    "sg:address":"Rue Du Ch\u00e2teau 3 1804 Corsier-sur-vevey Case Postale 33",
    "sg:city":"Corsier-sur-vevey",
    "sg:orig_category":"Grosshandel mit sonstigen Gebrauchs U Verbrauchsg\u00fctern Herstellung von elektrischen Lampen U Leuchte",
    "sg:phone":"+41 79 401 51 31",
    "sg:postcode":"1804",
    "sg:province":"Vaud",
    "wof:name":"Th\u00e9ad\u00e9c Sa",
    "wof:placetype":"venue"
},
  "geometry": {"coordinates":[6.8430261612,46.4703140259],"type":"Point"}
}