{
  "type": "Feature",
  "properties": {
    "iso:country":"CH",
    "sg:address":"Schadaustrasse 31b",
    "sg:city":"Thun",
    "sg:orig_category":"Sportvereine Ski",
    "sg:phone":"+41 41 833 17 38",
    "sg:postcode":"3604",
    "sg:province":"Bern",
    "wof:name":"Skiclub Amsteg",
    "wof:placetype":"venue"
},
  "geometry": {"coordinates":[8.6581697464,46.8750228882],"type":"Point"}
}