{
  "type": "Feature",
  "properties": {
    "iso:country":"CH",
    "sg:address":"La Rosaire 5",
    "sg:city":"Aclens",
    "sg:orig_category":"Herstellung von Waren aus Papier, Karton U Pappe Informatikdienste",
    "sg:phone":"+41 21 869 97 70",
    "sg:postcode":"1123",
    "sg:province":"Vaud",
    "wof:name":"Gomaro Sa Codes Barres Barcodes \u00e9tiquettes Etiketten",
    "wof:placetype":"venue"
},
  "geometry": {"coordinates":[6.5228309631,46.5710334778],"type":"Point"}
}