{
  "type": "Feature",
  "properties": {
    "iso:country":"CH",
    "sg:address":"Holdernstrasse 12 8865 Bilten. Postfach",
    "sg:city":"Bilten",
    "sg:orig_category":"Unternehmensberatung",
    "sg:phone":"+41 55 615 37 55",
    "sg:postcode":"8865",
    "sg:province":"Glarus",
    "wof:name":"Steiner-lang & Partner Gmbh Unternehmensaufbau U. Vertriebsf\u00f6rderung. Ganzheitliche Pers\u00f6nlichkeits- U. Management-seminare Usw",
    "wof:placetype":"venue"
},
  "geometry": {"coordinates":[9.0173158646,47.1529884338],"type":"Point"}
}