{
  "type": "Feature",
  "properties": {
    "iso:country":"CH",
    "sg:address":"Bierigut-strasse 1",
    "sg:city":"Thun",
    "sg:orig_category":"Grosshandel mit B\u00fcromaschinen Grosshandel mit Datenverarbeitungsger\u00e4ten",
    "sg:phone":"+41 33 334 10 20",
    "sg:postcode":"3608",
    "sg:province":"Bern",
    "wof:name":"Orgatime Ag Betriebsdatenerfassung",
    "wof:placetype":"venue"
},
  "geometry": {"coordinates":[7.6000819206,46.7398262024],"type":"Point"}
}