{
  "type": "Feature",
  "properties": {
    "iso:country":"CH",
    "sg:address":"Altackerstrasse 228",
    "sg:city":"Seengen",
    "sg:orig_category":"Herstellung von Bergwerks U Baumaschinen",
    "sg:postcode":"5707",
    "sg:province":"Aargau",
    "wof:name":"Sedimec Ag",
    "wof:placetype":"venue"
},
  "geometry": {"coordinates":[8.2134599686,47.3235206604],"type":"Point"}
}