{
  "type": "Feature",
  "properties": {
    "iso:country":"CH",
    "sg:address":"Champ De Chin 17",
    "sg:city":"Malleray-b\u00e9vilard",
    "sg:classifiers":[
        {
            "category":"Government",
            "subcategory":"Fire Station",
            "type":"Public Place"
        }
    ],
    "sg:phone":"+41 32 492 13 65",
    "sg:postcode":"2735",
    "sg:province":"Bern",
    "sg:tags":[
        "component",
        "watch",
        "clock"
    ],
    "wof:name":"D\u00e9colletage Andr\u00e9 Broquet Succ. P.-a. Broquet",
    "wof:placetype":"venue"
},
  "geometry": {"coordinates":[7.298216,47.255253],"type":"Point"}
}