{
  "type": "Feature",
  "properties": {
    "iso:country":"CH",
    "sg:address":"Rue De Gen\u00e8ve 92",
    "sg:city":"Th\u00f4nex",
    "sg:orig_category":"Sportvereine Kegeln",
    "sg:phone":"+41 22 349 84 84",
    "sg:postcode":"1226",
    "sg:province":"Gen\u00e8ve",
    "wof:name":"Amf Bowling Centers Switzer. Inc.,wilmington",
    "wof:placetype":"venue"
},
  "geometry": {"coordinates":[6.1999201775,46.1931762695],"type":"Point"}
}