{
  "type": "Feature",
  "properties": {
    "iso:country":"CH",
    "sg:address":"Schreinerweg 6",
    "sg:city":"Steffisburg",
    "sg:orig_category":"Instandhaltung U Reparatur von Automobilen",
    "sg:phone":"+41 33 437 32 03",
    "sg:postcode":"3612",
    "sg:province":"Bern",
    "wof:name":"Garage Markus Zaugg",
    "wof:placetype":"venue"
},
  "geometry": {"coordinates":[7.6329441071,46.776134491],"type":"Point"}
}