{
  "type": "Feature",
  "properties": {
    "iso:country":"CH",
    "sg:address":"Bl\u00e4ienstrasse 1",
    "sg:city":"Gr\u00e4nichen",
    "sg:classifiers":[
        {
            "category":"Restaurant",
            "type":"Food & Drink"
        }
    ],
    "sg:phone":"+41 62 842 14 01",
    "sg:postcode":"5722",
    "sg:province":"Aargau",
    "wof:name":"Restaurant Bleien",
    "wof:placetype":"venue"
},
  "geometry": {"coordinates":[8.1133050919,47.3448829651],"type":"Point"}
}