{
  "type": "Feature",
  "properties": {
    "iso:country":"CH",
    "sg:address":"Steinentorstrasse 8 4051 Basel. Postfach",
    "sg:city":"Basel",
    "sg:orig_category":"Vermietung U Verpachtung von eigenen Immobilien",
    "sg:postcode":"4051",
    "sg:province":"Basel-Stadt",
    "wof:name":"Immobiliengesellschaft Priva Ag",
    "wof:placetype":"venue"
},
  "geometry": {"coordinates":[8.185174942,47.2475776672],"type":"Point"}
}