{
  "type": "Feature",
  "properties": {
    "iso:country":"CH",
    "sg:address":"R\u00fcfe In Der 7304 Maienfeld. Postfach",
    "sg:city":"Maienfeld",
    "sg:orig_category":"Handel mit Automobilteilen U Zubeh\u00f6r",
    "sg:postcode":"7304",
    "sg:province":"Graubunden",
    "wof:name":"Power Speed Autozubeh\u00f6r Komminoth",
    "wof:placetype":"venue"
},
  "geometry": {"coordinates":[9.5293388367,47.0131835938],"type":"Point"}
}