{
  "type": "Feature",
  "properties": {
    "iso:country":"CH",
    "sg:address":"Stiglenstrasse 71",
    "sg:city":"Seebach",
    "sg:orig_category":"D\u00e4mmung gegen K\u00e4lte, W\u00e4rme, Schall U Ersch\u00fctterung",
    "sg:phone":"+41 13023644",
    "sg:postcode":"8052",
    "sg:province":"Z\u00fcrich",
    "wof:name":"Egger + Widmer Ag",
    "wof:placetype":"venue"
},
  "geometry": {"coordinates":[8.5402402878,47.4224815369],"type":"Point"}
}