{
  "type": "Feature",
  "properties": {
    "iso:country":"CH",
    "sg:address":"Bundesplatz 2a",
    "sg:city":"Luzern",
    "sg:orig_category":"Gymnastik U Fitnesszentren",
    "sg:phone":"+41 32 751 33 89",
    "sg:postcode":"6003",
    "sg:province":"Luzern",
    "wof:name":"Claude Beyeler Fitness-center,ecole De Sport",
    "wof:placetype":"venue"
},
  "geometry": {"coordinates":[7.0634670258,47.0580673218],"type":"Point"}
}