{
  "type": "Feature",
  "properties": {
    "iso:country":"CH",
    "sg:address":"Route De France",
    "sg:city":"Morgins",
    "sg:orig_category":"HOTELS: MIT RESTAURANT Kongress- and Tagungshotels mit Restaurant",
    "sg:phone":"+41 41 397 16 16",
    "sg:postcode":"1875",
    "sg:province":"Valais",
    "wof:name":"Hostellerie Rigi",
    "wof:placetype":"venue"
},
  "geometry": {"coordinates":[8.4673700333,47.0442008972],"type":"Point"}
}