{
  "type": "Feature",
  "properties": {
    "iso:country":"CH",
    "sg:address":"Niderwisstrasse 1/3",
    "sg:city":"Gr\u00fcningen",
    "sg:orig_category":"Non-Classified Establishments",
    "sg:postcode":"8627",
    "sg:province":"Z\u00fcrich",
    "wof:name":"Z\u00fcriwerk Gr\u00fcningen",
    "wof:placetype":"venue"
},
  "geometry": {"coordinates":[8.7590799332,47.2798614502],"type":"Point"}
}