{
  "type": "Feature",
  "properties": {
    "iso:country":"CH",
    "sg:address":"General-dufour-strasse 143",
    "sg:city":"Biel/bienne",
    "sg:classifiers":[
        {
            "category":"Restaurant",
            "type":"Food & Drink"
        }
    ],
    "sg:phone":"+41 32 341 57 31",
    "sg:postcode":"2502",
    "sg:province":"Bern",
    "wof:name":"Restaurant Merkur",
    "wof:placetype":"venue"
},
  "geometry": {"coordinates":[7.2572379112,47.1444549561],"type":"Point"}
}