{
  "type": "Feature",
  "properties": {
    "iso:country":"CH",
    "sg:address":"R\u00f6tistrasse 22",
    "sg:city":"Langendorf",
    "sg:orig_category":"Erschliessung von Grundst\u00fccken",
    "sg:postcode":"4513",
    "sg:province":"Solothurn",
    "wof:name":"Wohnbau-genossenschaft Langendorf",
    "wof:placetype":"venue"
},
  "geometry": {"coordinates":[7.5170850754,47.224029541],"type":"Point"}
}