{
  "type": "Feature",
  "properties": {
    "iso:country":"CH",
    "sg:address":"Adam-g\u00f6uffi-strasse 18",
    "sg:city":"Biel/bienne",
    "sg:orig_category":"Non-Classified Establishments",
    "sg:postcode":"2502",
    "sg:province":"Bern",
    "wof:name":"A + W Architekten Gmbh",
    "wof:placetype":"venue"
},
  "geometry": {"coordinates":[7.5900669098,47.0785751343],"type":"Point"}
}