{
  "type": "Feature",
  "properties": {
    "iso:country":"CH",
    "sg:address":"Alpenstrasse 14",
    "sg:city":"Zug",
    "sg:orig_category":"Unclassifiable Establishments",
    "sg:postcode":"6300",
    "sg:province":"Zug",
    "wof:name":"Knobel Gartenpflege Gmbh Gartenanlagen U. Holzbauten; Planung Usw",
    "wof:placetype":"venue"
},
  "geometry": {"coordinates":[7.8204698563,47.2413673401],"type":"Point"}
}