{
  "type": "Feature",
  "properties": {
    "iso:country":"CH",
    "sg:address":"Peillonex Rue 10",
    "sg:city":"Ch\u00eane-bourg",
    "sg:orig_category":"Sonstige mit der Informatik verbundene T\u00e4tigkeiten",
    "sg:phone":"+41 22 348 84 63",
    "sg:postcode":"1225",
    "sg:province":"Gen\u00e8ve",
    "wof:name":"Tonoli Sarl",
    "wof:placetype":"venue"
},
  "geometry": {"coordinates":[6.1960601807,46.1944694519],"type":"Point"}
}