{
  "type": "Feature",
  "properties": {
    "iso:country":"CH",
    "sg:address":"G\u00fcterstrasse 136 4053 Basel. Postfach",
    "sg:city":"Basel",
    "sg:orig_category":"Herstellung von elektrischen Lampen U Leuchten",
    "sg:phone":"+41 61 363 31 13",
    "sg:postcode":"4053",
    "sg:province":"Basel-Stadt",
    "wof:name":"Basilicht H\u00e4nggi Rolf Beleuchtungsprojekte Im Bereich Der Architektur- U. Theaterbeleuchtung",
    "wof:placetype":"venue"
},
  "geometry": {"coordinates":[7.5891098976,47.5447616577],"type":"Point"}
}