{
  "type": "Feature",
  "properties": {
    "iso:country":"CH",
    "sg:address":"6197",
    "sg:city":"Bumbach",
    "sg:orig_category":"Detailhandel mit Waren verschiedener Art, Hauptrichtung Nahrungsmittel",
    "sg:phone":"+41 34 493 38 59",
    "sg:postcode":"6197",
    "sg:province":"Bern",
    "wof:name":"Hermann Brunner Handlung",
    "wof:placetype":"venue"
},
  "geometry": {"coordinates":[7.900949955,46.8138504028],"type":"Point"}
}