{
  "type": "Feature",
  "properties": {
    "iso:country":"CH",
    "sg:address":"St. Wolfgangstrasse 18a",
    "sg:city":"Balsthal",
    "sg:orig_category":"Bauschreinerei Innenausbau",
    "sg:phone":"+41 79 425 43 71",
    "sg:postcode":"4710",
    "sg:province":"Solothurn",
    "wof:name":"Haefeli Ag Schreinerei-innenausbau",
    "wof:placetype":"venue"
},
  "geometry": {"coordinates":[7.700609,47.31979],"type":"Point"}
}