{
  "type": "Feature",
  "properties": {
    "iso:country":"CH",
    "sg:address":"Chemin Riant-mont 4",
    "sg:city":"Corsier-sur-vevey",
    "sg:orig_category":"Malerei Stukkateurgewerbe, Gipserei U Verputzerei",
    "sg:phone":"+41 21 921 98 81",
    "sg:postcode":"1804",
    "sg:province":"Vaud",
    "wof:name":"Maurice Jaques Gypserie & Peinture",
    "wof:placetype":"venue"
},
  "geometry": {"coordinates":[6.8485169411,46.4718284607],"type":"Point"}
}