{
  "type": "Feature",
  "properties": {
    "iso:country":"CH",
    "sg:address":"Chrotteg\u00e4ssli 2 3065 Bolligen. Postfach",
    "sg:city":"Bern",
    "sg:orig_category":"Erwachsenenbildung U Unterricht",
    "sg:postcode":"3005",
    "sg:province":"Bern",
    "wof:name":"Musikschule De La Poza",
    "wof:placetype":"venue"
},
  "geometry": {"coordinates":[9.5429334641,47.4775428772],"type":"Point"}
}