{
  "type": "Feature",
  "properties": {
    "iso:country":"CH",
    "sg:address":"Sonneckstrasse 16",
    "sg:city":"Jona",
    "sg:orig_category":"Unternehmensberatung",
    "sg:phone":"+41 55 210 17 02",
    "sg:postcode":"8645",
    "sg:province":"St. Gallen",
    "wof:name":"Egger Consulting",
    "wof:placetype":"venue"
},
  "geometry": {"coordinates":[8.8235692978,47.2421112061],"type":"Point"}
}