{
  "type": "Feature",
  "properties": {
    "iso:country":"CH",
    "sg:address":"Bd De La For\u00eat 36",
    "sg:city":"Pully",
    "sg:orig_category":"Detailhandel mit Waren verschiedener Art, Hauptrichtung Nahrungsmittel",
    "sg:phone":"+41 21 652 24 15",
    "sg:postcode":"1009",
    "sg:province":"Vaud",
    "wof:name":"Delarive Philippe",
    "wof:placetype":"venue"
},
  "geometry": {"coordinates":[6.6682229042,46.522644043],"type":"Point"}
}