{
  "type": "Feature",
  "properties": {
    "iso:country":"CH",
    "sg:address":"Thurfeldstrasse 16",
    "sg:city":"Schweizersholz",
    "sg:classifiers":[
        {
            "category":"Restaurant",
            "type":"Food & Drink"
        }
    ],
    "sg:phone":"+41 71 422 12 47",
    "sg:postcode":"9223",
    "sg:province":"Thurgau",
    "wof:name":"Restaurant Muggensturm",
    "wof:placetype":"venue"
},
  "geometry": {"coordinates":[9.2093801498,47.5044059753],"type":"Point"}
}