{
  "type": "Feature",
  "properties": {
    "iso:country":"CH",
    "sg:address":"Baarerstrasse 112",
    "sg:city":"Zug",
    "sg:orig_category":"Unclassifiable Establishments",
    "sg:postcode":"6300",
    "sg:province":"Zug",
    "wof:name":"Y\u00e0mama Gmbh",
    "wof:placetype":"venue"
},
  "geometry": {"coordinates":[8.5190229416,47.1802215576],"type":"Point"}
}