{
  "type": "Feature",
  "properties": {
    "addr:full":"Chemin De Paudille 3 Chardonne Vaud 1803",
    "addr:housenumber":"3",
    "addr:postcode":"1803",
    "addr:street":"Chemin De Paudille",
    "iso:country":"CH",
    "sg:address":"Chemin De Paudille 3",
    "sg:city":"Chardonne",
    "sg:orig_category":"Datenverarbeitungsdienste Sonstige mit der Informatik verbundene T\u00e4tigkeiten",
    "sg:phone":"+41 21 922 27 02",
    "sg:postcode":"1803",
    "sg:province":"Vaud",
    "wof:name":"Schroffartis S\u00e0rl Informatique, T\u00e9l\u00e9communications Etc.; Conseils, R\u00e9alisation, Services",
    "wof:placetype":"venue"
},
  "geometry": {"coordinates":[6.831903,46.479298],"type":"Point"}
}