{
  "type": "Feature",
  "properties": {
    "iso:country":"CH",
    "sg:address":"R\u00fctistrasse 8",
    "sg:city":"D\u00fcrnten",
    "sg:orig_category":"Elektroinstallation Mechanische Werkst\u00e4tten",
    "sg:phone":"+41 55 240 11 48",
    "sg:postcode":"8635",
    "sg:province":"Z\u00fcrich",
    "wof:name":"Albert B\u00f6singer Elektroinst.& Mech.werkstatt",
    "wof:placetype":"venue"
},
  "geometry": {"coordinates":[8.8431282043,47.276927948],"type":"Point"}
}