{
  "type": "Feature",
  "properties": {
    "iso:country":"CH",
    "sg:address":"Farel Rue 6 1860 Aigle. Postfach",
    "sg:city":"Aigle",
    "sg:orig_category":"Detailhandel mit Waren verschiedener Art, Hauptrichtung Nahrungsmittel",
    "sg:postcode":"1860",
    "sg:province":"Vaud",
    "wof:name":"Galimentar, Salgueiro Galinha Antonio",
    "wof:placetype":"venue"
},
  "geometry": {"coordinates":[6.9686541557,46.3178787231],"type":"Point"}
}