{
  "type": "Feature",
  "properties": {
    "iso:country":"CH",
    "sg:address":"Via Nouva 1",
    "sg:city":"Samedan",
    "sg:orig_category":"Organisationen der Wohlfahrtspflege Organisationen des Gesundheitswesen",
    "sg:phone":"+41 32 323 10 02",
    "sg:postcode":"7503",
    "sg:province":"Graubunden",
    "wof:name":"Pro Infirmis & Rheumaberatung",
    "wof:placetype":"venue"
},
  "geometry": {"coordinates":[7.2458848953,47.1379508972],"type":"Point"}
}