{
  "type": "Feature",
  "properties": {
    "iso:country":"CH",
    "sg:address":"1081",
    "sg:city":"Montpreveyres",
    "sg:orig_category":"Instandhaltung U Reparatur von Automobilen",
    "sg:phone":"+41 27 932 35 46",
    "sg:postcode":"1081",
    "sg:province":"Vaud",
    "wof:name":"Mesrew Ag",
    "wof:placetype":"venue"
},
  "geometry": {"coordinates":[7.7549748421,46.3116264343],"type":"Point"}
}