{
  "type": "Feature",
  "properties": {
    "iso:country":"CH",
    "sg:address":"Am Balsberg 30 8302 Kloten. Postfach",
    "sg:city":"Kloten",
    "sg:orig_category":"Maler U Glasergewerbe Malerei",
    "sg:phone":"+41 55 445 20 14",
    "sg:postcode":"8302",
    "sg:province":"Z\u00fcrich",
    "wof:name":"Sergio Chenet Malergesch\u00e4ft",
    "wof:placetype":"venue"
},
  "geometry": {"coordinates":[8.8990850449,47.1829605103],"type":"Point"}
}