{
  "type": "Feature",
  "properties": {
    "iso:country":"CH",
    "sg:address":"Rue De L'ouriettaz",
    "sg:city":"Aubonne",
    "sg:orig_category":"Instandhaltung U Reparatur von Automobilen",
    "sg:phone":"+41 79 434 73 33",
    "sg:postcode":"1170",
    "sg:province":"Vaud",
    "wof:name":"Jean-paul Morel Sports S\u00e0rl Garage",
    "wof:placetype":"venue"
},
  "geometry": {"coordinates":[6.3076310158,46.508731842],"type":"Point"}
}