{
  "type": "Feature",
  "properties": {
    "iso:country":"CH",
    "sg:address":"Via Stazione 13 6828 Balerna. Postfach",
    "sg:city":"Balerna",
    "sg:orig_category":"K\u00fcnstlerische U schriftstellerische T\u00e4tigkeiten U Darbietungen Weiterbildungskurse and Seminar Anbie",
    "sg:phone":"+41 91 690 00 60",
    "sg:postcode":"6828",
    "sg:province":"Ticino",
    "wof:name":"Artynja Sa Attivit\u00e0 Artistiche N. Ambito D. Pittura, D. Grafica Ecc",
    "wof:placetype":"venue"
},
  "geometry": {"coordinates":[9.0060825348,45.8486595154],"type":"Point"}
}