{
  "type": "Feature",
  "properties": {
    "iso:country":"CH",
    "sg:address":"Kirchplatz 4",
    "sg:city":"Winterthur",
    "sg:orig_category":"Arztpraxen",
    "sg:phone":"+41 56 241 11 30",
    "sg:postcode":"8400",
    "sg:province":"Z\u00fcrich",
    "wof:name":"Dr.med.alex Peter Reimann Arzt F.allgemeine Medizin",
    "wof:placetype":"venue"
},
  "geometry": {"coordinates":[8.331857,47.521202],"type":"Point"}
}