{
  "type": "Feature",
  "properties": {
    "iso:country":"CH",
    "sg:address":"Heinrich Federer-strasse 10",
    "sg:city":"Z\u00fcrich",
    "sg:orig_category":"Sportvereine Triathlon Laufen, Schwimmen, Velo",
    "sg:phone":"+41 17210317",
    "sg:postcode":"8038",
    "sg:province":"Z\u00fcrich",
    "wof:name":"Triathlon Club Z\u00fcrich",
    "wof:placetype":"venue"
},
  "geometry": {"coordinates":[8.5312633514,47.3363456726],"type":"Point"}
}