{
  "type": "Feature",
  "properties": {
    "iso:country":"CH",
    "sg:address":"Sch\u00fctzenstrasse 43",
    "sg:city":"Zollikon",
    "sg:orig_category":"Sonstige mit Sport verbundene T\u00e4tigkeiten",
    "sg:phone":"+41 32 931 15 88",
    "sg:postcode":"8702",
    "sg:province":"Z\u00fcrich",
    "wof:name":"Vonlanthen, Claude",
    "wof:placetype":"venue"
},
  "geometry": {"coordinates":[6.7499389648,47.0587768555],"type":"Point"}
}