{
  "type": "Feature",
  "properties": {
    "iso:country":"CH",
    "sg:address":"Kolinplatz 1",
    "sg:city":"Zug",
    "sg:orig_category":"Handelsvermittlung von Textilien, Bekleidung, Schuhen U Lederwaren",
    "sg:postcode":"6300",
    "sg:province":"Zug",
    "wof:name":"Alpencommerz Ag",
    "wof:placetype":"venue"
},
  "geometry": {"coordinates":[8.5155277252,47.1661834717],"type":"Point"}
}