{
  "type": "Feature",
  "properties": {
    "iso:country":"CH",
    "sg:address":"Steinengraben 5",
    "sg:city":"Basel",
    "sg:orig_category":"Unclassifiable Establishments",
    "sg:postcode":"4051",
    "sg:province":"Basel-Stadt",
    "wof:name":"Aubena Sa",
    "wof:placetype":"venue"
},
  "geometry": {"coordinates":[7.0576848984,46.5961875916],"type":"Point"}
}