{
  "type": "Feature",
  "properties": {
    "iso:country":"CH",
    "sg:address":"Studbachstrasse 13b",
    "sg:city":"Hinwil",
    "sg:classifiers":[
        {
            "category":"Banks & Credit Unions",
            "subcategory":"Bureau De Change",
            "type":"Services"
        }
    ],
    "sg:phone":"+41 19388040",
    "sg:postcode":"8340",
    "sg:province":"Z\u00fcrich",
    "sg:tags":[
        "image",
        "processing",
        "system",
        "digital"
    ],
    "wof:name":"Luminus Systeme Ag",
    "wof:placetype":"venue"
},
  "geometry": {"coordinates":[8.8190374374,47.3039855957],"type":"Point"}
}