{
  "type": "Feature",
  "properties": {
    "iso:country":"CH",
    "sg:address":"Seetalstrasse 1",
    "sg:city":"Seon",
    "sg:orig_category":"Reiseb\u00fcros Reiseb\u00fcros U Reiseveranstalter",
    "sg:phone":"+41 62 775 43 65",
    "sg:postcode":"5703",
    "sg:province":"Aargau",
    "wof:name":"Prp Plaz Reiseplanung Gmbh",
    "wof:placetype":"venue"
},
  "geometry": {"coordinates":[8.1606798172,47.3534812927],"type":"Point"}
}