{
  "type": "Feature",
  "properties": {
    "iso:country":"CH",
    "sg:address":"Via Balestra 40",
    "sg:city":"Locarno",
    "sg:orig_category":"Erwachsenenbildung U Unterricht K\u00fcnstlerische Schulen",
    "sg:phone":"+41 91 751 84 40",
    "sg:postcode":"6600",
    "sg:province":"Ticino",
    "wof:name":"Conservatorio Della Svizzera Italiana",
    "wof:placetype":"venue"
},
  "geometry": {"coordinates":[8.7980575562,46.162273407],"type":"Point"}
}