{
  "type": "Feature",
  "properties": {
    "iso:country":"CH",
    "sg:address":"Reichsgasse 54",
    "sg:city":"Chur",
    "sg:orig_category":"Innendekorationsateliers Sonstiges Textilgewerbe",
    "sg:phone":"+41 81 252 58 57",
    "sg:postcode":"7000",
    "sg:province":"Graubunden",
    "wof:name":"Tessuti R54 Gmbh",
    "wof:placetype":"venue"
},
  "geometry": {"coordinates":[9.5328388214,46.8494224548],"type":"Point"}
}