{
  "type": "Feature",
  "properties": {
    "iso:country":"CH",
    "sg:address":"6244",
    "sg:city":"Nebikon",
    "sg:orig_category":"Primarschulen",
    "sg:phone":"+41 62 756 20 14",
    "sg:postcode":"6244",
    "sg:province":"Luzern",
    "wof:name":"Primarschule",
    "wof:placetype":"venue"
},
  "geometry": {"coordinates":[7.978700161,47.1917686462],"type":"Point"}
}