{
  "type": "Feature",
  "properties": {
    "iso:country":"CH",
    "sg:address":"Bodenackerweg 18 5612 Villmergen. Postfach 122",
    "sg:city":"Villmergen",
    "sg:orig_category":"Elektroinstallation",
    "sg:phone":"+41 56 610 05 11",
    "sg:postcode":"5612",
    "sg:province":"Aargau",
    "wof:name":"Reke-elektro Ag Villmergen",
    "wof:placetype":"venue"
},
  "geometry": {"coordinates":[8.2581195831,47.3486061096],"type":"Point"}
}