{
  "type": "Feature",
  "properties": {
    "iso:country":"CH",
    "sg:address":"Haldengasse 31",
    "sg:city":"Zeiningen",
    "sg:orig_category":"Sonstige mit der Informatik verbundene T\u00e4tigkeiten",
    "sg:phone":"+41 13500860",
    "sg:postcode":"4314",
    "sg:province":"Aargau",
    "wof:name":"Miaute Consulting",
    "wof:placetype":"venue"
},
  "geometry": {"coordinates":[7.8700551987,47.5451622009],"type":"Point"}
}