{
  "type": "Feature",
  "properties": {
    "addr:full":"Zulgstrasse 59 3612 Steffisburg. Postfach 71 Steffisburg Bern 3612",
    "addr:housenumber":"59;71",
    "addr:postcode":"3612 steffisburg.;3612",
    "addr:street":"Zulgstrasse;Postfach;Bern",
    "iso:country":"CH",
    "sg:address":"Zulgstrasse 59 3612 Steffisburg. Postfach 71",
    "sg:city":"Steffisburg",
    "sg:orig_category":"Architektur U Ingenieurb\u00fcros Architekturb\u00fcros",
    "sg:phone":"+41 33 437 70 41",
    "sg:postcode":"3612",
    "sg:province":"Bern",
    "wof:name":"Intarch Steffisburg Gmbh",
    "wof:placetype":"venue"
},
  "geometry": {"coordinates":[7.626798,46.77515],"type":"Point"}
}