{
  "type": "Feature",
  "properties": {
    "iso:country":"CH",
    "sg:address":"Hasental 16",
    "sg:city":"Knonau",
    "sg:orig_category":"Unclassifiable Establishments",
    "sg:phone":"+41 41 711 42 87",
    "sg:postcode":"8934",
    "sg:province":"Z\u00fcrich",
    "wof:name":"Frei & Hunkeler Ag Ladenbau, Innenausbau, Dekorationssysteme; Fabrikation, Handel Usw",
    "wof:placetype":"venue"
},
  "geometry": {"coordinates":[8.4689073563,47.2151222229],"type":"Point"}
}