{
  "type": "Feature",
  "properties": {
    "iso:country":"CH",
    "sg:address":"Hauptstrasse 26",
    "sg:city":"Tenniken",
    "sg:orig_category":"Herstellung von Metallerzeugnissen ohne Maschinenbau Herstellung von Werkzeugmaschinen",
    "sg:phone":"+41 61 971 34 84",
    "sg:postcode":"4456",
    "sg:province":"Basel-Landschaft",
    "wof:name":"Hans Heid Ag",
    "wof:placetype":"venue"
},
  "geometry": {"coordinates":[7.8100438118,47.4368934631],"type":"Point"}
}