{
  "type": "Feature",
  "properties": {
    "iso:country":"CH",
    "sg:address":"Avenue Mon-loisir 16",
    "sg:city":"Lausanne",
    "sg:classifiers":[
        {
            "category":"Government",
            "subcategory":"Post Office",
            "type":"Public Place"
        }
    ],
    "sg:phone":"+41 21 616 32 98",
    "sg:postcode":"1006",
    "sg:province":"Vaud",
    "sg:tags":[
        "caf\u00e9s",
        "tea-rooms"
    ],
    "wof:name":"Tea-room Mon-loisir",
    "wof:placetype":"venue"
},
  "geometry": {"coordinates":[6.6311178207,46.5114097595],"type":"Point"}
}