{
  "type": "Feature",
  "properties": {
    "iso:country":"CH",
    "sg:address":"Rte Cantonale",
    "sg:city":"Courtema\u00eeche",
    "sg:orig_category":"Herstellung von Konstruktionsteilen, Fertigbauteilen U Ausbauelementen aus Holz",
    "sg:postcode":"2923",
    "sg:province":"Jura",
    "wof:name":"Reber G\u00e9rard",
    "wof:placetype":"venue"
},
  "geometry": {"coordinates":[7.0477051735,47.4579048157],"type":"Point"}
}