{
  "type": "Feature",
  "properties": {
    "iso:country":"CH",
    "sg:address":"6992",
    "sg:city":"Vernate",
    "sg:orig_category":"Malerei Tapeziererei",
    "sg:phone":"+41 91 605 17 50",
    "sg:postcode":"6992",
    "sg:province":"Ticino",
    "wof:name":"Sandro Soldati & Figli Impresa Di Pittura",
    "wof:placetype":"venue"
},
  "geometry": {"coordinates":[8.8890895844,46.0018806458],"type":"Point"}
}