{
  "type": "Feature",
  "properties": {
    "iso:country":"CH",
    "sg:address":"Le Ch\u00e2telard",
    "sg:city":"Treycovagnes",
    "sg:classifiers":[
        {
            "category":"Restaurant",
            "type":"Food & Drink"
        }
    ],
    "sg:phone":"+41 32 731 34 98",
    "sg:postcode":"1436",
    "sg:province":"Vaud",
    "wof:name":"Caf\u00e9 Du Clos-de-serri\u00e8res",
    "wof:placetype":"venue"
},
  "geometry": {"coordinates":[6.9025950432,46.9826049805],"type":"Point"}
}