{
  "type": "Feature",
  "properties": {
    "iso:country":"CH",
    "sg:address":"T\u00e8ra D'sott 85",
    "sg:city":"Comano",
    "sg:orig_category":"Detailhandel mit Fleisch U Fleischwaren",
    "sg:phone":"+41 91 940 62 89",
    "sg:postcode":"6949",
    "sg:province":"Ticino",
    "wof:name":"Michele Ballerini Macelleria & Salumeria",
    "wof:placetype":"venue"
},
  "geometry": {"coordinates":[8.9570102692,46.0399208069],"type":"Point"}
}