{
  "type": "Feature",
  "properties": {
    "iso:country":"CH",
    "sg:address":"1468",
    "sg:city":"Cheyres",
    "sg:orig_category":"Erbringung von Dienstleistungen f\u00fcr Unternehmen",
    "sg:postcode":"1468",
    "sg:province":"Fribourg",
    "wof:name":"Schafer-duc",
    "wof:placetype":"venue"
},
  "geometry": {"coordinates":[6.7879991531,46.8158111572],"type":"Point"}
}