{
  "type": "Feature",
  "properties": {
    "iso:country":"CH",
    "sg:address":"Rasch\u00e4renstrasse 35 7000 Chur. Postfach 659",
    "sg:city":"Chur",
    "sg:orig_category":"Allgemeiner Hoch U Tiefbau Strassenbau",
    "sg:phone":"+41 81 257 03 30",
    "sg:postcode":"7002",
    "sg:province":"Graubunden",
    "wof:name":"Schlub Ag",
    "wof:placetype":"venue"
},
  "geometry": {"coordinates":[9.508626,46.847599],"type":"Point"}
}