{
  "type": "Feature",
  "properties": {
    "iso:country":"CH",
    "sg:address":"1987",
    "sg:city":"H\u00e9r\u00e9mence",
    "sg:orig_category":"G\u00fcterbef\u00f6rderung im Strassenverkehr",
    "sg:phone":"+41 27 281 12 30",
    "sg:postcode":"1987",
    "sg:province":"Valais",
    "wof:name":"Firmin Mayoraz Transports",
    "wof:placetype":"venue"
},
  "geometry": {"coordinates":[7.404665947,46.1833267212],"type":"Point"}
}