{
  "type": "Feature",
  "properties": {
    "iso:country":"CH",
    "sg:address":"Gr\u00fctstrasse 26",
    "sg:city":"Herrliberg",
    "sg:orig_category":"Vereine Diverse",
    "sg:phone":"+41 19151802",
    "sg:postcode":"8704",
    "sg:province":"Z\u00fcrich",
    "wof:name":"Waffensammler-club",
    "wof:placetype":"venue"
},
  "geometry": {"coordinates":[8.6100740433,47.2869682312],"type":"Point"}
}