{
  "type": "Feature",
  "properties": {
    "iso:country":"CH",
    "sg:address":"Eckwilerstrasse 5",
    "sg:city":"M\u00e4genwil",
    "sg:orig_category":"Tierarztpraxis",
    "sg:phone":"+41 62 896 25 55",
    "sg:postcode":"5506",
    "sg:province":"Aargau",
    "wof:name":"Dr. Med. Vet. Rolf K\u00fcnzler Tierarzt",
    "wof:placetype":"venue"
},
  "geometry": {"coordinates":[8.2431983948,47.4100151062],"type":"Point"}
}