{
  "type": "Feature",
  "properties": {
    "iso:country":"CH",
    "sg:address":"Lettenweg 129",
    "sg:city":"Allschwil",
    "sg:orig_category":"Interessenvertretungen",
    "sg:postcode":"4123",
    "sg:province":"Basel-Landschaft",
    "wof:name":"Schweizer Muskel-stiftung",
    "wof:placetype":"venue"
},
  "geometry": {"coordinates":[7.552336216,47.5478401184],"type":"Point"}
}