{
  "type": "Feature",
  "properties": {
    "iso:country":"CH",
    "sg:address":"Im Gr\u00e4fler 3",
    "sg:city":"Schaffhausen",
    "sg:orig_category":"Physiotherapie",
    "sg:phone":"+41 61 751 34 54",
    "sg:postcode":"8207",
    "sg:province":"Schaffhausen",
    "wof:name":"Institut F.physiotherapie",
    "wof:placetype":"venue"
},
  "geometry": {"coordinates":[7.5969638824,47.4690475464],"type":"Point"}
}