{
  "type": "Feature",
  "properties": {
    "iso:country":"CH",
    "sg:address":"Baselstrasse 74",
    "sg:city":"Luzern",
    "sg:orig_category":"Detailhandel mit Bekleidungszubeh\u00f6r U Bekleidung ohne ausgepr\u00e4gten Schwerpunkt Sonstiger Detailhande",
    "sg:postcode":"6003",
    "sg:province":"Luzern",
    "wof:name":"Freak-inn Gmbh Hanfprodukte",
    "wof:placetype":"venue"
},
  "geometry": {"coordinates":[8.29273,47.053825],"type":"Point"}
}