{
  "type": "Feature",
  "properties": {
    "iso:country":"CH",
    "sg:address":"Riedm\u00fchle",
    "sg:city":"Sarmenstorf",
    "sg:orig_category":"Verarbeitung von Milch Verwertung von Milch",
    "sg:postcode":"5614",
    "sg:province":"Aargau",
    "wof:name":"K\u00e4sereigesellschaft Sarmenstorf",
    "wof:placetype":"venue"
},
  "geometry": {"coordinates":[8.2469654083,47.3096160889],"type":"Point"}
}