{
  "type": "Feature",
  "properties": {
    "iso:country":"CH",
    "sg:address":"7250",
    "sg:city":"Klosters",
    "sg:orig_category":"Herstellung von Konstruktionsteilen, Fertigbauteilen U Ausbauelementen aus Holz",
    "sg:phone":"+41 62 291 42 17",
    "sg:postcode":"7250",
    "sg:province":"Graubunden",
    "wof:name":"M\u00fcller Bautechnik",
    "wof:placetype":"venue"
},
  "geometry": {"coordinates":[7.9765357971,47.3561897278],"type":"Point"}
}