{
  "type": "Feature",
  "properties": {
    "iso:country":"CH",
    "sg:address":"Clochetons Chemin Des 31",
    "sg:city":"Lausanne",
    "sg:orig_category":"Interessenvertretungen",
    "sg:phone":"+41 21 625 24 90",
    "sg:postcode":"1004",
    "sg:province":"Vaud",
    "wof:name":"Fondation Bataillard Pierre Et Nouky",
    "wof:placetype":"venue"
},
  "geometry": {"coordinates":[6.6176161766,46.5261573792],"type":"Point"}
}