{
  "type": "Feature",
  "properties": {
    "iso:country":"CH",
    "sg:address":"Chemin Du Petit-bois 3",
    "sg:city":"Ch\u00e2telaine",
    "sg:orig_category":"Mechanik",
    "sg:phone":"+41 55 283 40 22",
    "sg:postcode":"1219",
    "sg:province":"Gen\u00e8ve",
    "wof:name":"Garage Matosevic",
    "wof:placetype":"venue"
},
  "geometry": {"coordinates":[9.0061979294,47.2013320923],"type":"Point"}
}