{
  "type": "Feature",
  "properties": {
    "iso:country":"CH",
    "sg:address":"Rue Du 1-er Mars 29",
    "sg:city":"Les Geneveys",
    "sg:classifiers":[
        {
            "category":"Banks & Credit Unions",
            "subcategory":"Bank",
            "type":"Services"
        }
    ],
    "sg:phone":"+41 38571566",
    "sg:postcode":"2206",
    "sg:province":"Neuch\u00e2tel",
    "wof:name":"Banque Cantonale, Neuchateloise",
    "wof:placetype":"venue"
},
  "geometry": {"coordinates":[6.850151,47.014652],"type":"Point"}
}