{
  "type": "Feature",
  "properties": {
    "addr:full":"Sch\u00f6neckstrasse 19 Emmetten Nidwalden 6376",
    "addr:housenumber":"19",
    "addr:postcode":"6376",
    "addr:street":"Schoeneckstrasse",
    "iso:country":"CH",
    "sg:address":"Sch\u00f6neckstrasse 19",
    "sg:city":"Emmetten",
    "sg:orig_category":"Architektur U Ingenieurb\u00fcros",
    "sg:phone":"+41 41 620 44 31",
    "sg:postcode":"6376",
    "sg:province":"Nidwalden",
    "wof:name":"Hansruedi Hagmann Planungsb\u00fcro",
    "wof:placetype":"venue"
},
  "geometry": {"coordinates":[8.507323,46.958961],"type":"Point"}
}