{
  "type": "Feature",
  "properties": {
    "iso:country":"CH",
    "sg:address":"Avenue Louis-casa\u00ef 27",
    "sg:city":"Gen\u00e8ve",
    "sg:orig_category":"Unclassifiable Establishments",
    "sg:postcode":"1209",
    "sg:province":"Gen\u00e8ve",
    "wof:name":"Visilab Sa Optique Magasins Balexert",
    "wof:placetype":"venue"
},
  "geometry": {"coordinates":[6.1146712303,46.2194747925],"type":"Point"}
}