{
  "type": "Feature",
  "properties": {
    "iso:country":"CH",
    "sg:address":"Thunstr. 15 3612 Steffisburg. Postfach 237",
    "sg:city":"Steffisburg",
    "sg:orig_category":"Elektrizit\u00e4tsversorgung",
    "sg:phone":"+41 33 439 15 35",
    "sg:postcode":"3612",
    "sg:province":"Bern",
    "wof:name":"Zut Zentrum F\u00fcr Umwelttechnologie",
    "wof:placetype":"venue"
},
  "geometry": {"coordinates":[7.6310558319,46.770614624],"type":"Point"}
}