{
  "type": "Feature",
  "properties": {
    "iso:country":"CH",
    "sg:address":"Z\u00fcrcherstrasse 30 8854 Siebnen. Postfach 248",
    "sg:city":"Siebnen",
    "sg:orig_category":"Herstellung von M\u00f6beln",
    "sg:phone":"+41 55 440 22 64",
    "sg:postcode":"8854",
    "sg:province":"Schwyz",
    "wof:name":"R\u00fcttimann Ag",
    "wof:placetype":"venue"
},
  "geometry": {"coordinates":[8.8935775757,47.1761512756],"type":"Point"}
}