{
  "type": "Feature",
  "properties": {
    "iso:country":"CH",
    "sg:address":"Neumarkt 28 8001 Z\u00fcrich. Postfach 742",
    "sg:city":"Z\u00fcrich",
    "sg:orig_category":"Architektur U Ingenieurb\u00fcros",
    "sg:phone":"+41 12623646",
    "sg:postcode":"8001",
    "sg:province":"Z\u00fcrich",
    "wof:name":"Burckhardt + Partner Ag, Architekten Generalplaner Architekten Generalplaner",
    "wof:placetype":"venue"
},
  "geometry": {"coordinates":[8.54665,47.372852],"type":"Point"}
}