{
  "type": "Feature",
  "properties": {
    "iso:country":"CH",
    "sg:address":"Berglistrasse 34",
    "sg:city":"Arbon",
    "sg:orig_category":"RESTAURANTS: TEA-ROOMS",
    "sg:postcode":"9320",
    "sg:province":"Thurgau",
    "wof:name":"Sch\u00e4rer Jakob",
    "wof:placetype":"venue"
},
  "geometry": {"coordinates":[9.4268550873,47.5162353516],"type":"Point"}
}