{
  "type": "Feature",
  "properties": {
    "iso:country":"CH",
    "sg:address":"Chemin Des Ch\u00eanes 12",
    "sg:city":"St-blaise",
    "sg:orig_category":"Clock Pendulums",
    "sg:phone":"+41 32 753 16 16",
    "sg:postcode":"2072",
    "sg:province":"Neuch\u00e2tel",
    "wof:name":"Cadenzia S.a.",
    "wof:placetype":"venue"
},
  "geometry": {"coordinates":[6.989527,47.021446],"type":"Point"}
}