{
  "type": "Feature",
  "properties": {
    "iso:country":"CH",
    "sg:address":"Vignoble Avenue Du 2",
    "sg:city":"Neuenburg",
    "sg:orig_category":"Herstellung von medizinischen U chirurgischen Ger\u00e4ten sowie orthop\u00e4dischen Vorrichtungen",
    "sg:postcode":"2000",
    "sg:province":"Neuch\u00e2tel",
    "wof:name":"Metalor Technologies Sa",
    "wof:placetype":"venue"
},
  "geometry": {"coordinates":[6.9310851097,46.9903335571],"type":"Point"}
}