{
  "type": "Feature",
  "properties": {
    "iso:country":"CH",
    "sg:address":"Grabenackerweg 5. 5102 Rupperswil. Postfach",
    "sg:city":"Rupperswil",
    "sg:orig_category":"Pensionskassen",
    "sg:phone":"+41 41 871 00 23",
    "sg:postcode":"5102",
    "sg:province":"Aargau",
    "wof:name":"Personalf\u00fcrsorge Des Schweiz. Grosshandelsverbandes Der Sanit\u00e4ren Branche, Altdorf Ur",
    "wof:placetype":"venue"
},
  "geometry": {"coordinates":[8.6435632706,46.8808326721],"type":"Point"}
}