{
  "type": "Feature",
  "properties": {
    "addr:full":"P. Grande 99 Giubiasco Ticino 6512",
    "addr:housenumber":"99",
    "addr:postcode":"6512",
    "addr:street":"P. Grande",
    "iso:country":"CH",
    "sg:address":"P. Grande 99",
    "sg:city":"Giubiasco",
    "sg:orig_category":"Darlehenskassen U Raiffeisenbanken",
    "sg:phone":"+41 91 857 35 69",
    "sg:postcode":"6512",
    "sg:province":"Ticino",
    "wof:name":"Banca Raiffeisen",
    "wof:placetype":"venue"
},
  "geometry": {"coordinates":[9.0127,46.172649],"type":"Point"}
}