{
  "type": "Feature",
  "properties": {
    "iso:country":"CH",
    "sg:address":"Am Gottesgraben 4",
    "sg:city":"Wettingen",
    "sg:orig_category":"Kunsthandel",
    "sg:phone":"+41 56 427 16 38",
    "sg:postcode":"5430",
    "sg:province":"Aargau",
    "wof:name":"Galerie Fao",
    "wof:placetype":"venue"
},
  "geometry": {"coordinates":[8.3121051788,47.4645042419],"type":"Point"}
}