{
  "type": "Feature",
  "properties": {
    "iso:country":"CH",
    "sg:address":"Route De Cossonay 26",
    "sg:city":"Prilly",
    "sg:orig_category":"RESTAURANTS: TEA-ROOMS",
    "sg:phone":"+41 56 426 44 62",
    "sg:postcode":"1008",
    "sg:province":"Vaud",
    "wof:name":"Friends And Partners Gmbh",
    "wof:placetype":"venue"
},
  "geometry": {"coordinates":[8.0295629501,46.754283905],"type":"Point"}
}