{
  "type": "Feature",
  "properties": {
    "iso:country":"CH",
    "sg:address":"Bordeaux-strasse 5",
    "sg:city":"Basel",
    "sg:orig_category":"Grosshandel mit Wasch U Reinigungsmitteln Unternehmensberatung",
    "sg:phone":"+41 55 410 68 30",
    "sg:postcode":"4053",
    "sg:province":"Basel-Stadt",
    "wof:name":"Star Line Service Gmbh Finanz- U. Verm\u00f6gen, Bes. Vorsorgeoptimierung; Beratung Usw",
    "wof:placetype":"venue"
},
  "geometry": {"coordinates":[8.7701854706,47.1988258362],"type":"Point"}
}