{
  "type": "Feature",
  "properties": {
    "iso:country":"CH",
    "sg:address":"Grand-rue 46",
    "sg:city":"Dombresson",
    "sg:orig_category":"Detailhandel mit Milcherzeugnissen U Eiern",
    "sg:phone":"+41 31 311 37 16",
    "sg:postcode":"2056",
    "sg:province":"Neuch\u00e2tel",
    "wof:name":"Dieter Heugel Milchprodukte Z.ch\u00e4sh\u00fctte",
    "wof:placetype":"venue"
},
  "geometry": {"coordinates":[7.4481449127,46.9486427307],"type":"Point"}
}