{
  "type": "Feature",
  "properties": {
    "iso:country":"CH",
    "sg:address":"Schlachthofstrasse 19",
    "sg:city":"Winterthur",
    "sg:orig_category":"Herstellung von Metallerzeugnissen ohne Maschinenbau Maschinenbau",
    "sg:phone":"+41 56 633 28 25",
    "sg:postcode":"8406",
    "sg:province":"Z\u00fcrich",
    "wof:name":"Fuchs Heinrich, Maschinenbau",
    "wof:placetype":"venue"
},
  "geometry": {"coordinates":[8.3359479904,47.3445854187],"type":"Point"}
}