{
  "type": "Feature",
  "properties": {
    "addr:full":"B\u00e4raustrasse 43c B\u00e4rau Bern 3552",
    "addr:housenumber":"43c",
    "addr:postcode":"3552",
    "addr:street":"Baeraustrasse",
    "iso:country":"CH",
    "sg:address":"B\u00e4raustrasse 43c",
    "sg:city":"B\u00e4rau",
    "sg:orig_category":"Allgemeiner Hoch U Tiefbau Allgemeiner Hochbau",
    "sg:phone":"+41 34 402 40 60",
    "sg:postcode":"3552",
    "sg:province":"Bern",
    "wof:name":"Lehmann Bau + Kran Ag",
    "wof:placetype":"venue"
},
  "geometry": {"coordinates":[7.811132,46.933083],"type":"Point"}
}