{
  "type": "Feature",
  "properties": {
    "iso:country":"CH",
    "sg:address":"Brignon 1994 Baar (nendaz). Postfach",
    "sg:city":"Vernami\u00e8ge",
    "sg:orig_category":"RESTAURANTS: TEA-ROOMS",
    "sg:postcode":"1961",
    "sg:province":"Valais",
    "wof:name":"Schnyder Sandra, Caf\u00e9-restaurant Du Ch\u00e2teau De Brignon",
    "wof:placetype":"venue"
},
  "geometry": {"coordinates":[7.3247652054,46.1818466187],"type":"Point"}
}