{
  "type": "Feature",
  "properties": {
    "iso:country":"CH",
    "sg:address":"Sandhofstrasse 3",
    "sg:city":"W\u00e4denswil",
    "sg:orig_category":"Erschliessung von Grundst\u00fccken",
    "sg:postcode":"8820",
    "sg:province":"Z\u00fcrich",
    "wof:name":"Bau Und Wohngenossenschaft Habito",
    "wof:placetype":"venue"
},
  "geometry": {"coordinates":[8.6719198227,47.2199745178],"type":"Point"}
}