{
  "type": "Feature",
  "properties": {
    "iso:country":"CH",
    "sg:address":"Zugerstrasse 15/17",
    "sg:city":"Cham",
    "sg:classifiers":[
        {
            "category":"Government",
            "subcategory":"Post Office",
            "type":"Public Place"
        }
    ],
    "sg:phone":"+41 41 780 53 20",
    "sg:postcode":"6330",
    "sg:province":"Zug",
    "sg:tags":[
        "caf\u00e9s",
        "tea-rooms"
    ],
    "wof:name":"Caf\u00e9 Neudorf",
    "wof:placetype":"venue"
},
  "geometry": {"coordinates":[8.4615259171,47.1817016602],"type":"Point"}
}