{
  "type": "Feature",
  "properties": {
    "iso:country":"CH",
    "sg:address":"Route Des Sauges 20",
    "sg:city":"Montagne-sonvilier",
    "sg:orig_category":"Wirtschaftspr\u00fcfung, Steuerberatung U Treuhand",
    "sg:phone":"+41 32 940 12 68",
    "sg:postcode":"2615",
    "sg:province":"Bern",
    "wof:name":"P. Gilomen & A. Rodrigue",
    "wof:placetype":"venue"
},
  "geometry": {"coordinates":[6.9694709778,47.1391868591],"type":"Point"}
}