{
  "type": "Feature",
  "properties": {
    "addr:full":"Eugen Huber-strasse 117 Z\u00fcrich Z\u00fcrich 8048",
    "addr:housenumber":"117",
    "addr:postcode":"8048",
    "addr:street":"Huber-Strasse",
    "iso:country":"CH",
    "sg:address":"Eugen Huber-strasse 117",
    "sg:city":"Z\u00fcrich",
    "sg:orig_category":"Detailhandel mit B\u00fcchern, Zeitungen, Schreib U Papeteriewaren",
    "sg:postcode":"8048",
    "sg:province":"Z\u00fcrich",
    "wof:name":"Quartierkiosk Milic",
    "wof:placetype":"venue"
},
  "geometry": {"coordinates":[8.475358,47.387814],"type":"Point"}
}