{
  "type": "Feature",
  "properties": {
    "iso:country":"CH",
    "sg:address":"Grenchenstr. 16",
    "sg:city":"Arch",
    "sg:orig_category":"Wohnheime",
    "sg:phone":"+41 32 679 38 74",
    "sg:postcode":"3296",
    "sg:province":"Bern",
    "wof:name":"Stucki Irma",
    "wof:placetype":"venue"
},
  "geometry": {"coordinates":[7.4254398346,47.1698226929],"type":"Point"}
}