{
  "type": "Feature",
  "properties": {
    "iso:country":"CH",
    "sg:address":"12 Rue De La Vernie",
    "sg:city":"Crissier",
    "sg:classifiers":[
        {
            "category":"Manufacturing",
            "subcategory":"Building Materials",
            "type":"Manufacturing & Wholesale Goods"
        }
    ],
    "sg:phone":"+41 21 635 15 11",
    "sg:postcode":"1023",
    "sg:province":"Vaud",
    "sg:tags":[
        "raw",
        "finished",
        "paper",
        "-",
        "cardboard"
    ],
    "wof:name":"Baumgartner Papiers Sa",
    "wof:placetype":"venue"
},
  "geometry": {"coordinates":[6.5743789673,46.5460662842],"type":"Point"}
}