{
  "type": "Feature",
  "properties": {
    "iso:country":"CH",
    "sg:address":"Waldburg",
    "sg:city":"Unter\u00e4geri",
    "sg:orig_category":"Herstellung von sonstigen elektrischen Ausr\u00fcstungen",
    "sg:phone":"+41 41 750 40 05",
    "sg:postcode":"6314",
    "sg:province":"Zug",
    "wof:name":"Bypass Fes Frischknecht Elektronik Service",
    "wof:placetype":"venue"
},
  "geometry": {"coordinates":[8.5750551224,47.1415214539],"type":"Point"}
}