{
  "type": "Feature",
  "properties": {
    "iso:country":"CH",
    "sg:address":"Industriestr. 20",
    "sg:city":"F\u00e4llanden",
    "sg:classifiers":[
        {
            "category":"Manufacturing",
            "subcategory":"Rubber & Plastics",
            "type":"Manufacturing & Wholesale Goods"
        }
    ],
    "sg:phone":"+41 4118250635",
    "sg:postcode":"8117",
    "sg:province":"Z\u00fcrich",
    "wof:name":"Renato Ventura Ag",
    "wof:placetype":"venue"
},
  "geometry": {"coordinates":[8.6433486938,47.3775444031],"type":"Point"}
}