{
  "type": "Feature",
  "properties": {
    "iso:country":"CH",
    "sg:address":"Feldhofstrasse 26a",
    "sg:city":"D\u00fcbendorf",
    "sg:classifiers":[
        {
            "category":"Professional",
            "subcategory":"Art Services",
            "type":"Services"
        }
    ],
    "sg:phone":"+41 71 282 44 74",
    "sg:postcode":"8600",
    "sg:province":"Z\u00fcrich",
    "sg:tags":[
        "graphic",
        "designer"
    ],
    "wof:name":"John Diener Communication Design Ag",
    "wof:placetype":"venue"
},
  "geometry": {"coordinates":[9.4193134308,47.4383659363],"type":"Point"}
}