{
  "type": "Feature",
  "properties": {
    "iso:country":"CH",
    "sg:address":"Rychenbergstrasse 208 8404 Oberwinterthur. Postfach",
    "sg:city":"Winterthur",
    "sg:orig_category":"Softwareentwicklung U beratung",
    "sg:phone":"+41 52 246 06 20",
    "sg:postcode":"8404",
    "sg:province":"Z\u00fcrich",
    "wof:name":"Frontened Software & Beratung J. Kuriger",
    "wof:placetype":"venue"
},
  "geometry": {"coordinates":[8.7466859818,47.5028648376],"type":"Point"}
}