{
  "type": "Feature",
  "properties": {
    "iso:country":"CH",
    "sg:address":"Hauptstrasse 25",
    "sg:city":"Diessenhofen",
    "sg:orig_category":"Detailhandel mit Brot, Back U S\u00fcsswaren",
    "sg:phone":"+41 52 657 10 81",
    "sg:postcode":"8253",
    "sg:province":"Thurgau",
    "wof:name":"Werner Strasser B\u00e4ckerei-konditorei",
    "wof:placetype":"venue"
},
  "geometry": {"coordinates":[8.750922,47.689499],"type":"Point"}
}