{
  "type": "Feature",
  "properties": {
    "addr:full":"Rue D'italie 8-10 Gen\u00e8ve Gen\u00e8ve 1211",
    "addr:housenumber":"8-10",
    "addr:postcode":"1211",
    "addr:street":"Rue D'Italie",
    "iso:country":"CH",
    "sg:address":"Rue D'italie 8-10",
    "sg:city":"Gen\u00e8ve",
    "sg:classifiers":[
        {
            "category":"Banks & Credit Unions",
            "subcategory":"Bank",
            "type":"Services"
        }
    ],
    "sg:phone":"+41 22 819 51 11",
    "sg:postcode":"1211",
    "sg:province":"Gen\u00e8ve",
    "wof:name":"Barclays Bank Suisse Sa",
    "wof:placetype":"venue"
},
  "geometry": {"coordinates":[6.13993,46.203819],"type":"Point"}
}