{
  "type": "Feature",
  "properties": {
    "iso:country":"CH",
    "sg:address":"Bahnhofstrasse 1 8583 Sulgen. Postfach 84",
    "sg:city":"Sulgen",
    "sg:orig_category":"Kantonalbanken",
    "sg:phone":"+41 71 971 27 27",
    "sg:postcode":"8583",
    "sg:province":"Thurgau",
    "wof:name":"Thurgauer Kantonalbank",
    "wof:placetype":"venue"
},
  "geometry": {"coordinates":[8.9692316055,47.4648208618],"type":"Point"}
}