{
  "type": "Feature",
  "properties": {
    "iso:country":"CH",
    "sg:address":"Gehrenstrasse 26",
    "sg:city":"Erlinsbach",
    "sg:orig_category":"Sportvereine Ballsport Tischtennis",
    "sg:phone":"+41 52 365 38 85",
    "sg:postcode":"5018",
    "sg:province":"Solothurn",
    "wof:name":"Ttc Ettenhausen",
    "wof:placetype":"venue"
},
  "geometry": {"coordinates":[8.8944816589,47.4775810242],"type":"Point"}
}