{
  "type": "Feature",
  "properties": {
    "iso:country":"CH",
    "sg:address":"P\u00e9colat Rue 1201 Gen\u00e8ve Case Postale 1406",
    "sg:city":"Gen\u00e8ve",
    "sg:orig_category":"Detailhandel mit Bekleidung",
    "sg:phone":"+41 22 732 24 42",
    "sg:postcode":"1201",
    "sg:province":"Gen\u00e8ve",
    "wof:name":"Peter Saxer & Cie Sa",
    "wof:placetype":"venue"
},
  "geometry": {"coordinates":[6.14632,46.20892],"type":"Point"}
}