{
  "type": "Feature",
  "properties": {
    "iso:country":"CH",
    "sg:address":"Rue Gustave-amweg 43",
    "sg:city":"Porrentruy",
    "sg:orig_category":"Kinderkrippen U horte",
    "sg:phone":"+41 32 466 75 33",
    "sg:postcode":"2900",
    "sg:province":"Jura",
    "wof:name":"Cr\u00e8che \u00e0 Domicile D'ajoie",
    "wof:placetype":"venue"
},
  "geometry": {"coordinates":[7.0788421631,47.4202957153],"type":"Point"}
}