{
  "type": "Feature",
  "properties": {
    "iso:country":"CH",
    "sg:address":"Industriestrasse 14 5036 Oberentfelden. Postfach",
    "sg:city":"Oberentfelden",
    "sg:orig_category":"Architektur U Ingenieurb\u00fcros",
    "sg:phone":"+41 62 737 20 60",
    "sg:postcode":"5036",
    "sg:province":"Aargau",
    "wof:name":"B\u00e4rtsch Messerli Ag",
    "wof:placetype":"venue"
},
  "geometry": {"coordinates":[8.053616,47.35667],"type":"Point"}
}