{
  "type": "Feature",
  "properties": {
    "iso:country":"CH",
    "sg:address":"Battenhaus",
    "sg:city":"Niederteufen",
    "sg:orig_category":"Bau von Strassen, Sportanlagen U Bahnverkehrsstrecken Erdbewegungsarbeiten",
    "sg:phone":"+41 81 325 23 37",
    "sg:postcode":"9052",
    "sg:province":"Appenzell Ausserrhoden",
    "wof:name":"R\u00e4umdienst Seewis, Fausch Urs Schneer\u00e4umung U. Erdarbeiten",
    "wof:placetype":"venue"
},
  "geometry": {"coordinates":[9.607912,46.989738],"type":"Point"}
}