{
  "type": "Feature",
  "properties": {
    "iso:country":"CH",
    "sg:address":"Stotz 11",
    "sg:city":"Untervaz",
    "sg:orig_category":"Sonstige Herstellung von Konstruktionsteilen, Fertigbauteilen U Ausbauelementen aus Holz",
    "sg:phone":"+41 81 322 15 35",
    "sg:postcode":"7204",
    "sg:province":"Graubunden",
    "wof:name":"Patrik St\u00e4ger Schindelmacherei",
    "wof:placetype":"venue"
},
  "geometry": {"coordinates":[9.5343103409,46.9292755127],"type":"Point"}
}