{
  "type": "Feature",
  "properties": {
    "iso:country":"CH",
    "sg:address":"Route De Boudry 22",
    "sg:city":"Cortaillod",
    "sg:orig_category":"Herstellung von Elektromotoren, Generatoren U Transformatoren",
    "sg:phone":"+41 32 842 12 66",
    "sg:postcode":"2016",
    "sg:province":"Neuch\u00e2tel",
    "wof:name":"Sieber P.-f. S\u00e0rl Bobinage De Moteurs \u00e9lectr.",
    "wof:placetype":"venue"
},
  "geometry": {"coordinates":[6.8432278633,46.9449195862],"type":"Point"}
}