{
  "type": "Feature",
  "properties": {
    "iso:country":"CH",
    "sg:address":"Ackersteinstrasse 17",
    "sg:city":"Z\u00fcrich",
    "sg:orig_category":"Fleischverarbeitung",
    "sg:phone":"+41 41 818 31 61",
    "sg:postcode":"8049",
    "sg:province":"Z\u00fcrich",
    "wof:name":"Hans Felder Ag Fleischwaren Produktion",
    "wof:placetype":"venue"
},
  "geometry": {"coordinates":[8.6306648254,47.0190849304],"type":"Point"}
}