{
  "type": "Feature",
  "properties": {
    "iso:country":"CH",
    "sg:address":"Hohlstrasse 188",
    "sg:city":"Z\u00fcrich",
    "sg:classifiers":[
        {
            "category":"Autos & Motor Vehicles",
            "subcategory":"Auto Supplies",
            "type":"Retail Goods"
        }
    ],
    "sg:phone":"+41 12999898",
    "sg:postcode":"8004",
    "sg:province":"Z\u00fcrich",
    "sg:tags":[
        "automobile",
        "accessory"
    ],
    "wof:name":"Dezag",
    "wof:placetype":"venue"
},
  "geometry": {"coordinates":[8.518249,47.381172],"type":"Point"}
}