{
  "type": "Feature",
  "properties": {
    "addr:full":"Feldgasse 28 Triengen Luzern 6234",
    "addr:housenumber":"28",
    "addr:postcode":"6234",
    "addr:street":"Feldgasse",
    "iso:country":"CH",
    "sg:address":"Feldgasse 28",
    "sg:city":"Triengen",
    "sg:orig_category":"Arbeitnehmerverb\u00e4nde",
    "sg:phone":"+41 41 933 17 30",
    "sg:postcode":"6234",
    "sg:province":"Luzern",
    "wof:name":"Schw.verb.evang.arbeitnehmer Herrn Hans Peter Erb",
    "wof:placetype":"venue"
},
  "geometry": {"coordinates":[8.075193,47.240429],"type":"Point"}
}