{
  "type": "Feature",
  "properties": {
    "iso:country":"CH",
    "sg:address":"Steigstrasse 26 8200 Schaffhausen. Postfach",
    "sg:city":"Schaffhausen",
    "sg:orig_category":"RESTAURANTS: TEA-ROOMS",
    "sg:phone":"+41 52 625 43 58",
    "sg:postcode":"8200",
    "sg:province":"Schaffhausen",
    "wof:name":"Grubenmann Casino Ag Restaurant Casino. Gesellschaftliche U. Kulturelle Anl\u00e4sse. Party-service Usw",
    "wof:placetype":"venue"
},
  "geometry": {"coordinates":[8.6299409866,47.6956787109],"type":"Point"}
}