{
  "type": "Feature",
  "properties": {
    "iso:country":"CH",
    "sg:address":"Schwertgasse 2",
    "sg:city":"Zurzach",
    "sg:orig_category":"Detailhandel mit Fleisch U Fleischwaren",
    "sg:phone":"+41 56 249 21 40",
    "sg:postcode":"5330",
    "sg:province":"Aargau",
    "wof:name":"Joseph St\u00e4dler Metzgerei-wursterei",
    "wof:placetype":"venue"
},
  "geometry": {"coordinates":[8.2939157486,47.5873603821],"type":"Point"}
}