{
  "type": "Feature",
  "properties": {
    "iso:country":"CH",
    "sg:address":"Alte Winterthurerstrasse 23 8304 Wallisellen. Postfach",
    "sg:city":"Wallisellen",
    "sg:classifiers":[
        {
            "category":"Professional",
            "subcategory":"Employment Agencies",
            "type":"Services"
        }
    ],
    "sg:postcode":"8304",
    "sg:province":"Z\u00fcrich",
    "sg:tags":[
        "personal",
        "u",
        "stellenvermittlung"
    ],
    "wof:name":"P.c. Prisco Consulting Personal- U. Kaderentwicklung. F\u00fchrungskr\u00e4fte; Beratung, Coaching. Ausbildungs, Entwicklungskonzepte; Erstellung Usw",
    "wof:placetype":"venue"
},
  "geometry": {"coordinates":[8.5873212814,47.4151496887],"type":"Point"}
}