{
  "type": "Feature",
  "properties": {
    "iso:country":"CH",
    "sg:address":"Buholzstr. 36",
    "sg:city":"Emmen",
    "sg:classifiers":[
        {
            "category":"Wholesale",
            "subcategory":"Machinery & Supplies",
            "type":"Manufacturing & Wholesale Goods"
        }
    ],
    "sg:phone":"+41 41 260 43 43",
    "sg:postcode":"6032",
    "sg:province":"Luzern",
    "sg:tags":[
        "equipment",
        "precision"
    ],
    "wof:name":"Manitec Ag",
    "wof:placetype":"venue"
},
  "geometry": {"coordinates":[8.3184213638,47.092918396],"type":"Point"}
}