{
  "type": "Feature",
  "properties": {
    "iso:country":"CH",
    "sg:address":"Centrale Rue 76 2740 Montagne-moutier. Postfach",
    "sg:city":"Montagne-moutier",
    "sg:orig_category":"Detailhandel mit Brot, Back U S\u00fcsswaren",
    "sg:postcode":"2740",
    "sg:province":"Bern",
    "wof:name":"Schuppisser Yves Boulangerie-p\u00e2tisserie-confiserie, Traiteur, Tea-room",
    "wof:placetype":"venue"
},
  "geometry": {"coordinates":[7.372463,47.278725],"type":"Point"}
}