{
  "type": "Feature",
  "properties": {
    "iso:country":"CH",
    "sg:address":"Moos",
    "sg:city":"Neudorf",
    "sg:orig_category":"Indoor Fireworks",
    "sg:phone":"+41 41 932 18 18",
    "sg:postcode":"6025",
    "sg:province":"Luzern",
    "wof:name":"Bugano Ag",
    "wof:placetype":"venue"
},
  "geometry": {"coordinates":[8.2055597305,47.1926460266],"type":"Point"}
}