{
  "type": "Feature",
  "properties": {
    "addr:full":"Oberg\u00fctschrain 2 Luzern Luzern 6003",
    "addr:housenumber":"2",
    "addr:postcode":"6003",
    "addr:street":"Oberguetschrain",
    "iso:country":"CH",
    "sg:address":"Oberg\u00fctschrain 2",
    "sg:city":"Luzern",
    "sg:orig_category":"Aktivit\u00e4ten der Generalunternehmen im Baugewerbe Bau von Strassen, Sportanlagen U Bahnverkehrsstreck",
    "sg:phone":"+41 41 311 25 25",
    "sg:postcode":"6003",
    "sg:province":"Luzern",
    "wof:name":"Batigroup Ag",
    "wof:placetype":"venue"
},
  "geometry": {"coordinates":[8.287842,47.04615],"type":"Point"}
}