{
  "type": "Feature",
  "properties": {
    "iso:country":"CH",
    "sg:address":"Lausanne Rue De 46",
    "sg:city":"Fribourg",
    "sg:orig_category":"Detailhandel mit Bekleidung",
    "sg:phone":"+41 31 311 59 74",
    "sg:postcode":"1700",
    "sg:province":"Fribourg",
    "wof:name":"Item Bekleidung",
    "wof:placetype":"venue"
},
  "geometry": {"coordinates":[7.456076,46.947327],"type":"Point"}
}