{
  "type": "Feature",
  "properties": {
    "iso:country":"CH",
    "sg:address":"In Der Luberzen 17 8902 Urdorf. Postfach",
    "sg:city":"Urdorf",
    "sg:orig_category":"Herstellung von sonstigen Maschinen f\u00fcr bestimmte Verwendung",
    "sg:phone":"+41 17344616",
    "sg:postcode":"8902",
    "sg:province":"Z\u00fcrich",
    "wof:name":"Bigraph Ag",
    "wof:placetype":"venue"
},
  "geometry": {"coordinates":[8.4212150574,47.3936004639],"type":"Point"}
}