{
  "type": "Feature",
  "properties": {
    "iso:country":"CH",
    "sg:address":"Rue Du Pont-levis 2",
    "sg:city":"St-prex",
    "sg:orig_category":"Fachdetailhandel mit pharmazeutischen Produkten",
    "sg:phone":"+41 21 806 26 26",
    "sg:postcode":"1162",
    "sg:province":"Vaud",
    "wof:name":"Polla Dominique",
    "wof:placetype":"venue"
},
  "geometry": {"coordinates":[6.4603629112,46.4804039001],"type":"Point"}
}