{
  "type": "Feature",
  "properties": {
    "iso:country":"CH",
    "sg:address":"Via Zurigo 46",
    "sg:city":"Lugano",
    "sg:orig_category":"Vermietung U Verpachtung von eigenen Immobilien",
    "sg:postcode":"6900",
    "sg:province":"Ticino",
    "wof:name":"Immobiliare Finigea Sa",
    "wof:placetype":"venue"
},
  "geometry": {"coordinates":[8.9503822327,46.0101547241],"type":"Point"}
}