{
  "type": "Feature",
  "properties": {
    "iso:country":"CH",
    "sg:address":"Chemin Des B\u00e2ches 7 1030 Bussigny-lausanne Case Postale 118",
    "sg:city":"Bussigny-lausanne",
    "sg:orig_category":"Mineralwasser Detailhandel Wein Detailhandel",
    "sg:phone":"+41 21 701 14 82",
    "sg:postcode":"1030",
    "sg:province":"Vaud",
    "wof:name":"Claude Crottaz",
    "wof:placetype":"venue"
},
  "geometry": {"coordinates":[6.5520720482,46.5458526611],"type":"Point"}
}