{
  "type": "Feature",
  "properties": {
    "iso:country":"CH",
    "sg:address":"H\u00f6hnenstrasse 8a",
    "sg:city":"Ramlinsburg",
    "sg:orig_category":"Grosshandel mit B\u00fcromaschinen Herstellung von sonstigen elektrischen Ausr\u00fcstungen",
    "sg:phone":"+41 61 633 02 21",
    "sg:postcode":"4433",
    "sg:province":"Basel-Landschaft",
    "wof:name":"Kuetten Elektronik",
    "wof:placetype":"venue"
},
  "geometry": {"coordinates":[7.767059803,47.4497184753],"type":"Point"}
}