{
  "type": "Feature",
  "properties": {
    "iso:country":"CH",
    "sg:address":"Rue Louis-favre 14",
    "sg:city":"Gen\u00e8ve",
    "sg:orig_category":"Autogaragen",
    "sg:phone":"+41 21 691 71 03",
    "sg:postcode":"1201",
    "sg:province":"Gen\u00e8ve",
    "wof:name":"Garage Des Routiers Andr\u00e9 Schwendimann",
    "wof:placetype":"venue"
},
  "geometry": {"coordinates":[6.550828,46.512257],"type":"Point"}
}