{
  "type": "Feature",
  "properties": {
    "iso:country":"CH",
    "sg:address":"Alte Badenerstrasse 37",
    "sg:city":"Eggenwil",
    "sg:orig_category":"Erbringung von Dienstleistungen f\u00fcr Unternehmen",
    "sg:phone":"+41 56 631 66 43",
    "sg:postcode":"5445",
    "sg:province":"Aargau",
    "wof:name":"Wertli Paul Werkstatt F\u00fcr Design",
    "wof:placetype":"venue"
},
  "geometry": {"coordinates":[8.3421497345,47.3721008301],"type":"Point"}
}