{
  "type": "Feature",
  "properties": {
    "iso:country":"CH",
    "sg:address":"Hammerstrasse 108 4057 Basel. Postfach",
    "sg:city":"Basel",
    "sg:orig_category":"Fachdetailhandel in Verkaufsr\u00e4umen",
    "sg:phone":"+41 61 691 91 89",
    "sg:postcode":"4051",
    "sg:province":"Basel-Stadt",
    "wof:name":"Rusterholtz Thomas Fine Art Werke D. Bildenden Kunst; An, Verkauf. Kunstauktionen",
    "wof:placetype":"venue"
},
  "geometry": {"coordinates":[7.5956120491,47.5656585693],"type":"Point"}
}