{
  "type": "Feature",
  "properties": {
    "iso:country":"CH",
    "sg:address":"H\u00f6heweg",
    "sg:city":"Interlaken",
    "sg:classifiers":[
        {
            "category":"Travel",
            "subcategory":"Hotels & Motels",
            "type":"Entertainment"
        }
    ],
    "sg:phone":"+41 33 828 28 28",
    "sg:postcode":"3800",
    "sg:province":"Bern",
    "sg:tags":[
        "hotels",
        "business",
        "restaurant"
    ],
    "wof:name":"Victoria Jungfrau Grand Hotel & Spa",
    "wof:placetype":"venue"
},
  "geometry": {"coordinates":[7.859302,46.687134],"type":"Point"}
}