{
  "type": "Feature",
  "properties": {
    "iso:country":"CH",
    "sg:address":"Neubruchstrasse 15 8400 Winterthur. Postfach",
    "sg:city":"Winterthur",
    "sg:orig_category":"Hardwareberatung",
    "sg:postcode":"8406",
    "sg:province":"Z\u00fcrich",
    "wof:name":"Comassist Consulting Leuenberger",
    "wof:placetype":"venue"
},
  "geometry": {"coordinates":[8.6977043152,47.4839515686],"type":"Point"}
}