{
  "type": "Feature",
  "properties": {
    "iso:country":"CH",
    "sg:address":"Immeuble Genziana A",
    "sg:city":"Montana",
    "sg:orig_category":"Wirtschaftspr\u00fcfung, Steuerberatung U Treuhand",
    "sg:postcode":"3962",
    "wof:name":"Fiduciaire De Crans-montana (fcm) Sa",
    "wof:placetype":"venue"
},
  "geometry": {"coordinates":[7.4833321571,46.3119773865],"type":"Point"}
}