{
  "type": "Feature",
  "properties": {
    "iso:country":"CH",
    "sg:address":"Baarermatte",
    "sg:city":"Baar",
    "sg:orig_category":"Datenverarbeitungsdienste Softwareentwicklung U beratung",
    "sg:phone":"+41 22 717 44 19",
    "sg:postcode":"6340",
    "sg:province":"Zug",
    "wof:name":"Csc Switzerland Ag",
    "wof:placetype":"venue"
},
  "geometry": {"coordinates":[6.122862,46.238377],"type":"Point"}
}