{
  "type": "Feature",
  "properties": {
    "iso:country":"CH",
    "sg:address":"H\u00f6lzlistrasse 10",
    "sg:city":"Inkwil",
    "sg:orig_category":"Wirtschaftspr\u00fcfung, Steuerberatung U Treuhand",
    "sg:postcode":"3375",
    "sg:province":"Bern",
    "wof:name":"Habegger Treuhand",
    "wof:placetype":"venue"
},
  "geometry": {"coordinates":[7.6707530022,47.1980400085],"type":"Point"}
}