{
  "type": "Feature",
  "properties": {
    "addr:full":"Kirchstrasse 4 8807 Freienbach. Postfach Freienbach Schwyz 8807",
    "addr:housenumber":"4",
    "addr:postcode":"8807;8807",
    "addr:street":"Kirchstrasse;Postfach;Schwyz",
    "iso:country":"CH",
    "sg:address":"Kirchstrasse 4 8807 Freienbach. Postfach",
    "sg:city":"Freienbach",
    "sg:orig_category":"Allgemeiner Hochbau Herstellung von Metallkonstruktionen",
    "sg:phone":"+41 61 461 29 30",
    "sg:postcode":"8807",
    "sg:province":"Schwyz",
    "wof:name":"Jauslin Fassadenbau Ag",
    "wof:placetype":"venue"
},
  "geometry": {"coordinates":[7.650264,47.52961],"type":"Point"}
}