{
  "type": "Feature",
  "properties": {
    "iso:country":"CH",
    "sg:address":"Luzernstrasse 6",
    "sg:city":"Ballwil",
    "sg:orig_category":"G\u00fcterbef\u00f6rderung im Strassenverkehr",
    "sg:postcode":"6275",
    "sg:province":"Luzern",
    "wof:name":"Infanger Eurotrans Gmbh",
    "wof:placetype":"venue"
},
  "geometry": {"coordinates":[8.3169574738,47.1518516541],"type":"Point"}
}