{
  "type": "Feature",
  "properties": {
    "iso:country":"CH",
    "sg:address":"Dent-blanche Rue De La 10",
    "sg:city":"Sion",
    "sg:orig_category":"Non-Classified Establishments",
    "sg:postcode":"1950",
    "sg:province":"Valais",
    "wof:name":"Godissa Sa",
    "wof:placetype":"venue"
},
  "geometry": {"coordinates":[7.3590807915,46.2312812805],"type":"Point"}
}