{
  "type": "Feature",
  "properties": {
    "iso:country":"CH",
    "sg:address":"Oberer Saltinadamm 30 3902 Glis. Postfach",
    "sg:city":"Glis",
    "sg:orig_category":"Reiseb\u00fcros U Reiseveranstalter",
    "sg:postcode":"3902",
    "sg:province":"Valais",
    "wof:name":"Hrt Management Group Gmbh",
    "wof:placetype":"venue"
},
  "geometry": {"coordinates":[7.9889111519,46.3145484924],"type":"Point"}
}