{
  "type": "Feature",
  "properties": {
    "iso:country":"CH",
    "sg:address":"Baselstrasse 26",
    "sg:city":"Luzern",
    "sg:orig_category":"RESTAURANTS: TEA-ROOMS",
    "sg:phone":"+41 41 240 26 42",
    "sg:postcode":"6003",
    "sg:province":"Luzern",
    "wof:name":"W\u00fclser & W\u00fclser Gmbh",
    "wof:placetype":"venue"
},
  "geometry": {"coordinates":[8.2961835861,47.0528068542],"type":"Point"}
}