{
  "type": "Feature",
  "properties": {
    "iso:country":"CH",
    "sg:address":"Avenue De La Gare 18",
    "sg:city":"Sion",
    "sg:orig_category":"Detailhandel mit Damenbekleidung Detailhandel mit Herrenbekleidung",
    "sg:phone":"+41 27 323 26 56",
    "sg:postcode":"1950",
    "sg:province":"Valais",
    "wof:name":"Boutique Le Bateau Ivre Pr\u00eat-\u00e0-porter",
    "wof:placetype":"venue"
},
  "geometry": {"coordinates":[7.358678,46.229713],"type":"Point"}
}