{
  "type": "Feature",
  "properties": {
    "iso:country":"CH",
    "sg:address":"H\u00f4pital Rue De L' 18",
    "sg:city":"Neuch\u00e2tel",
    "sg:orig_category":"Technische, physikalische U chemische Untersuchung",
    "sg:phone":"+41 22 930 80 00",
    "sg:postcode":"2000",
    "sg:province":"Neuch\u00e2tel",
    "wof:name":"Laboratoire D'analyses Mat\u00e9riaux Ertec Sa",
    "wof:placetype":"venue"
},
  "geometry": {"coordinates":[6.0691370964,46.2185974121],"type":"Point"}
}