{
  "type": "Feature",
  "properties": {
    "iso:country":"CH",
    "sg:address":"Reusstrasse 6",
    "sg:city":"Attinghausen",
    "sg:orig_category":"Vermittlung von Immobilien",
    "sg:phone":"+41 41 870 88 72",
    "sg:postcode":"6468",
    "sg:province":"Uri",
    "wof:name":"Augusto Moretti Immobilien Promotion",
    "wof:placetype":"venue"
},
  "geometry": {"coordinates":[8.6310033798,46.8637657166],"type":"Point"}
}