{
  "type": "Feature",
  "properties": {
    "iso:country":"CH",
    "sg:address":"Freiestrasse 55",
    "sg:city":"Uster",
    "sg:orig_category":"Bauschreinerei",
    "sg:phone":"+41 19409870",
    "sg:postcode":"8610",
    "sg:province":"Z\u00fcrich",
    "wof:name":"Markus Zweifel Schreinerei",
    "wof:placetype":"venue"
},
  "geometry": {"coordinates":[8.725997,47.346947],"type":"Point"}
}