{
  "type": "Feature",
  "properties": {
    "iso:country":"CH",
    "sg:address":"Suisse Route De 11",
    "sg:city":"Versoix",
    "sg:orig_category":"M\u00f6belschreinereien",
    "sg:postcode":"1290",
    "sg:province":"Gen\u00e8ve",
    "wof:name":"Menuiserie - Agencement, Jan Kotecki",
    "wof:placetype":"venue"
},
  "geometry": {"coordinates":[6.1671500206,46.280292511],"type":"Point"}
}