{
  "type": "Feature",
  "properties": {
    "iso:country":"CH",
    "sg:address":"R\u00fcschlistrasse 5",
    "sg:city":"Biel/bienne",
    "sg:orig_category":"Kosmetikinstitute",
    "sg:phone":"+41 32 322 23 63",
    "sg:postcode":"2502",
    "sg:province":"Bern",
    "wof:name":"Nicole Meier Kosmetikinstitut",
    "wof:placetype":"venue"
},
  "geometry": {"coordinates":[7.2434191704,47.1390686035],"type":"Point"}
}