{
  "type": "Feature",
  "properties": {
    "iso:country":"CH",
    "sg:address":"Rue D'orzival 4 3960 Sierre Case Postale",
    "sg:city":"Siders",
    "sg:orig_category":"Reiseb\u00fcros U Reiseveranstalter",
    "sg:postcode":"3960",
    "sg:province":"Valais",
    "wof:name":"Soci\u00e9t\u00e9 De D\u00e9veloppement De Sierre Salgesch Et Environs Promouvoir L'essor Du Tourisme, Etc",
    "wof:placetype":"venue"
},
  "geometry": {"coordinates":[7.5315351486,46.29920578],"type":"Point"}
}