{
  "type": "Feature",
  "properties": {
    "iso:country":"CH",
    "sg:address":"De-senger Rue Hugo- 10 1200 Genf. Postfach",
    "sg:city":"Gen\u00e8ve",
    "sg:orig_category":"Herstellung von konfektionierten Textilwaren ohne Bekleidung",
    "sg:postcode":"1205",
    "sg:province":"Gen\u00e8ve",
    "wof:name":"Aeschlimann Storen & Rolladen",
    "wof:placetype":"venue"
},
  "geometry": {"coordinates":[7.9110617638,47.1511993408],"type":"Point"}
}