{
  "type": "Feature",
  "properties": {
    "iso:country":"CH",
    "sg:address":"Hauptstrasse 12",
    "sg:city":"Tobel",
    "sg:orig_category":"Detailhandel mit Haustieren U zoologischem Bedarf",
    "sg:phone":"+41 71 917 20 85",
    "sg:postcode":"9555",
    "sg:province":"Thurgau",
    "wof:name":"Susanne Heusser Dog Dog Ch-katzen&hundefutter",
    "wof:placetype":"venue"
},
  "geometry": {"coordinates":[9.0318603516,47.5142402649],"type":"Point"}
}