{
  "type": "Feature",
  "properties": {
    "addr:full":"Limmatstrasse 43 Turgi Aargau 5300",
    "addr:housenumber":"43",
    "addr:postcode":"5300",
    "addr:street":"Limmatstrasse",
    "iso:country":"CH",
    "sg:address":"Limmatstrasse 43",
    "sg:city":"Turgi",
    "sg:orig_category":"Bauschreinerei",
    "sg:phone":"+41 56 223 23 63",
    "sg:postcode":"5300",
    "sg:province":"Aargau",
    "wof:name":"Ren\u00e9 Vogelsang Schreinerei",
    "wof:placetype":"venue"
},
  "geometry": {"coordinates":[8.25119,47.494598],"type":"Point"}
}