{
  "type": "Feature",
  "properties": {
    "iso:country":"CH",
    "sg:address":"Unterdorfstrasse 8",
    "sg:city":"Oberegg",
    "sg:orig_category":"Herstellung von Metallkonstruktionen Stahl U Leichtmetallbau",
    "sg:phone":"+41 79 429 43 40",
    "sg:postcode":"9413",
    "sg:province":"Appenzell Innerhoden",
    "wof:name":"Geiger Kurt Ag",
    "wof:placetype":"venue"
},
  "geometry": {"coordinates":[9.5539598465,47.4228515625],"type":"Point"}
}