{
  "type": "Feature",
  "properties": {
    "iso:country":"CH",
    "sg:address":"Wehntalerstrasse 559",
    "sg:city":"Z\u00fcrich",
    "sg:orig_category":"Vermietung U Verpachtung von eigenen Immobilien",
    "sg:phone":"+41 13710444",
    "sg:postcode":"8046",
    "sg:province":"Z\u00fcrich",
    "wof:name":"Ita Gebr. Ag",
    "wof:placetype":"venue"
},
  "geometry": {"coordinates":[8.5048246384,47.4195632935],"type":"Point"}
}