{
  "type": "Feature",
  "properties": {
    "iso:country":"CH",
    "sg:address":"Regensdorferstrasse 140",
    "sg:city":"Z\u00fcrich",
    "sg:orig_category":"Erschliessung von Grundst\u00fccken",
    "sg:postcode":"8049",
    "sg:province":"Z\u00fcrich",
    "wof:name":"Siedlungsgenossenschaft Hinterberg, St. Gallen",
    "wof:placetype":"venue"
},
  "geometry": {"coordinates":[9.3363304138,47.4099197388],"type":"Point"}
}