{
  "type": "Feature",
  "properties": {
    "iso:country":"CH",
    "sg:address":"H\u00fceblistrasse 61",
    "sg:city":"Oberweningen",
    "sg:orig_category":"Detailhandel mit Radio U Fernsehger\u00e4ten",
    "sg:phone":"+41 18561200",
    "sg:postcode":"8165",
    "sg:province":"Z\u00fcrich",
    "wof:name":"Viktor Arm Hi-fi Studio",
    "wof:placetype":"venue"
},
  "geometry": {"coordinates":[8.4006538391,47.5012512207],"type":"Point"}
}