{
  "type": "Feature",
  "properties": {
    "iso:country":"CH",
    "sg:address":"Hauptstrasse 27",
    "sg:city":"Frick",
    "sg:orig_category":"Organisationen der Wohlfahrtspflege",
    "sg:phone":"+41 62 871 37 14",
    "sg:postcode":"5070",
    "sg:province":"Aargau",
    "wof:name":"Pro Senectute",
    "wof:placetype":"venue"
},
  "geometry": {"coordinates":[8.0178003311,47.5097503662],"type":"Point"}
}