{
  "type": "Feature",
  "properties": {
    "iso:country":"CH",
    "sg:address":"Centre La Placette",
    "sg:city":"No\u00ebs",
    "sg:orig_category":"Detailhandel mit Schuhen",
    "sg:phone":"+41 27 456 91 00",
    "sg:postcode":"3976",
    "sg:province":"Valais",
    "wof:name":"Karl V\u00f6gele Sa",
    "wof:placetype":"venue"
},
  "geometry": {"coordinates":[7.5055451393,46.2809448242],"type":"Point"}
}