{
  "type": "Feature",
  "properties": {
    "iso:country":"CH",
    "sg:address":"Wehntalerstrasse 3",
    "sg:city":"Oberweningen",
    "sg:orig_category":"Detailhandel mit Fahrr\u00e4dern",
    "sg:phone":"+41 18560268",
    "sg:postcode":"8165",
    "sg:province":"Z\u00fcrich",
    "wof:name":"Ren\u00e9 Hurler Velohandlung",
    "wof:placetype":"venue"
},
  "geometry": {"coordinates":[8.4110450745,47.4994544983],"type":"Point"}
}