{
  "type": "Feature",
  "properties": {
    "iso:country":"CH",
    "sg:address":"Industriestrasse 26 8404 Oberwinterthur. Postfach",
    "sg:city":"Oberwinterthur",
    "sg:orig_category":"Herstellung von Radio U Fernsehger\u00e4ten sowie phono U videotechnischen Ger\u00e4ten",
    "sg:phone":"+41 52 234 03 03",
    "sg:postcode":"8404",
    "sg:province":"Z\u00fcrich",
    "wof:name":"Mobiletouch Ag Dienstleistungen U. Handel Auf Dem Gebiet Der Unterhaltungselektronik, Informatik, Mobilkommunikation",
    "wof:placetype":"venue"
},
  "geometry": {"coordinates":[8.7551822662,47.4964370728],"type":"Point"}
}