{
  "type": "Feature",
  "properties": {
    "iso:country":"CH",
    "sg:address":"Dahlienweg 11",
    "sg:city":"W\u00fcrenlingen",
    "sg:orig_category":"Kosmetikinstitute",
    "sg:phone":"+41 56 281 26 21",
    "sg:postcode":"5303",
    "sg:province":"Aargau",
    "wof:name":"Judith Keller Kosmetikinstitut",
    "wof:placetype":"venue"
},
  "geometry": {"coordinates":[8.2526741028,47.529750824],"type":"Point"}
}