{
  "type": "Feature",
  "properties": {
    "iso:country":"CH",
    "sg:address":"Tschudistrasse 4",
    "sg:city":"St.gallen",
    "sg:orig_category":"Architektur U Ingenieurb\u00fcros Architekturb\u00fcros",
    "sg:phone":"+41 71 230 05 68",
    "sg:postcode":"9000",
    "sg:province":"St. Gallen",
    "wof:name":"L\u00fcchinger Roland",
    "wof:placetype":"venue"
},
  "geometry": {"coordinates":[9.367166,47.417904],"type":"Point"}
}