{
  "type": "Feature",
  "properties": {
    "iso:country":"CH",
    "sg:address":"Croix-d'or Rue De La 17 1204 Gen\u00e8ve. Postfach",
    "sg:city":"Gen\u00e8ve",
    "sg:orig_category":"Non-Classified Establishments",
    "sg:postcode":"1204",
    "sg:province":"Gen\u00e8ve",
    "wof:name":"Mudia Sa.",
    "wof:placetype":"venue"
},
  "geometry": {"coordinates":[3.5555009842,49.5370674133],"type":"Point"}
}