{
  "type": "Feature",
  "properties": {
    "iso:country":"CH",
    "sg:address":"Brunnenstrasse 3",
    "sg:city":"Horn",
    "sg:orig_category":"Wirtschaftspr\u00fcfung, Steuerberatung U Treuhand",
    "sg:phone":"+41 71 841 23 25",
    "sg:postcode":"9326",
    "sg:province":"Thurgau",
    "wof:name":"Kurt Stecher Treuhand",
    "wof:placetype":"venue"
},
  "geometry": {"coordinates":[9.4602661133,47.4895210266],"type":"Point"}
}