{
  "type": "Feature",
  "properties": {
    "iso:country":"CH",
    "sg:address":"Plaz",
    "sg:city":"Salouf",
    "sg:orig_category":"Primarschulen",
    "sg:phone":"+41 81 684 32 02",
    "sg:postcode":"7462",
    "sg:province":"Graubunden",
    "wof:name":"Primarschule Salouf Mon Stierva",
    "wof:placetype":"venue"
},
  "geometry": {"coordinates":[9.5759849548,46.6243095398],"type":"Point"}
}