{
  "type": "Feature",
  "properties": {
    "addr:full":"Herzogstrasse 6 Z\u00fcrich Z\u00fcrich 8044",
    "addr:housenumber":"6",
    "addr:postcode":"8044",
    "addr:street":"Herzogstrasse",
    "iso:country":"CH",
    "sg:address":"Herzogstrasse 6",
    "sg:city":"Z\u00fcrich",
    "sg:orig_category":"Datenverarbeitungsdienste",
    "sg:postcode":"8044",
    "sg:province":"Z\u00fcrich",
    "wof:name":"Barman Jean-yves",
    "wof:placetype":"venue"
},
  "geometry": {"coordinates":[7.208645,46.186459],"type":"Point"}
}