{
  "type": "Feature",
  "properties": {
    "iso:country":"CH",
    "sg:address":"Kr\u00e4hb\u00fchlstrasse 90",
    "sg:city":"Z\u00fcrich",
    "sg:orig_category":"Saunas Solarien",
    "sg:phone":"+41 17133313",
    "sg:postcode":"8044",
    "sg:province":"Z\u00fcrich",
    "wof:name":"Sauna-sihlmatte Massagen",
    "wof:placetype":"venue"
},
  "geometry": {"coordinates":[8.5419845581,47.2924766541],"type":"Point"}
}