{
  "type": "Feature",
  "properties": {
    "iso:country":"CH",
    "sg:address":"Flurstrasse 8",
    "sg:city":"Hagendorn",
    "sg:orig_category":"Oberfl\u00e4chenreinigung Sandstrahlen Verarbeitung U Veredlung von Flachglas",
    "sg:phone":"+41 41 280 58 03",
    "sg:postcode":"6332",
    "sg:province":"Zug",
    "wof:name":"Efotech Gmbh Glas-& Sandstrahltechnik",
    "wof:placetype":"venue"
},
  "geometry": {"coordinates":[8.4297609329,47.2022094727],"type":"Point"}
}