{
  "type": "Feature",
  "properties": {
    "iso:country":"CH",
    "sg:address":"Oberes Zelgli 2 5313 Klingnau. Postfach",
    "sg:city":"Klingnau",
    "sg:orig_category":"Pensionskassen",
    "sg:postcode":"5313",
    "sg:province":"Aargau",
    "wof:name":"Personalvorsorgekasse Der De Sede Ag",
    "wof:placetype":"venue"
},
  "geometry": {"coordinates":[8.2403106689,47.5919189453],"type":"Point"}
}