{
  "type": "Feature",
  "properties": {
    "iso:country":"CH",
    "sg:address":"Untergassen B. D. Stifterfirma",
    "sg:city":"Escholzmatt",
    "sg:orig_category":"Pensionskassen",
    "sg:postcode":"6182",
    "sg:province":"Luzern",
    "wof:name":"Wohlfahrtsstiftung Der Elektro-feindraht Ag.",
    "wof:placetype":"venue"
},
  "geometry": {"coordinates":[7.9358839989,46.9165306091],"type":"Point"}
}