{
  "type": "Feature",
  "properties": {
    "iso:country":"CH",
    "sg:address":"Vorhaldenstrasse 7",
    "sg:city":"Z\u00fcrich",
    "sg:orig_category":"Vereine Gartenbau",
    "sg:postcode":"8049",
    "sg:province":"Z\u00fcrich",
    "wof:name":"Verein F.familieng\u00e4rten Albi.",
    "wof:placetype":"venue"
},
  "geometry": {"coordinates":[8.4941005707,47.4007835388],"type":"Point"}
}