{
  "type": "Feature",
  "properties": {
    "iso:country":"CH",
    "sg:address":"Dorfstrasse 89",
    "sg:city":"Watt",
    "sg:orig_category":"Assembling, Disassembling",
    "sg:phone":"+41 18406382",
    "sg:postcode":"8105",
    "sg:province":"Z\u00fcrich",
    "wof:name":"Jakob Bader Tore Und Antriebe",
    "wof:placetype":"venue"
},
  "geometry": {"coordinates":[8.479043,47.44072],"type":"Point"}
}