{
  "type": "Feature",
  "properties": {
    "iso:country":"CH",
    "sg:address":"Blumenrain 30",
    "sg:city":"Basel",
    "sg:orig_category":"Detailhandel mit Geschenkartikeln U Souvenirs",
    "sg:phone":"+41 61 261 47 03",
    "sg:postcode":"4051",
    "sg:province":"Basel-Stadt",
    "wof:name":"Hilde Mundwiler Boutique Iris",
    "wof:placetype":"venue"
},
  "geometry": {"coordinates":[7.5865368843,47.5613288879],"type":"Point"}
}