{
  "type": "Feature",
  "properties": {
    "iso:country":"CH",
    "sg:address":"Z\u00fcrcherstrasse 149",
    "sg:city":"Oberengstringen",
    "sg:orig_category":"Non-Classified Establishments",
    "sg:postcode":"8102",
    "sg:province":"Z\u00fcrich",
    "wof:name":"Qualisuisse Gmbh",
    "wof:placetype":"venue"
},
  "geometry": {"coordinates":[8.4581851959,47.4105567932],"type":"Point"}
}