{
  "type": "Feature",
  "properties": {
    "iso:country":"CH",
    "sg:address":"Mont-blanc Avenue Du",
    "sg:city":"Gland",
    "sg:orig_category":"Interessenvertretungen",
    "sg:phone":"+41 22 364 91 11",
    "sg:postcode":"1196",
    "sg:province":"Vaud",
    "wof:name":"Wwf-world Wide Fund For Nature (formerly World Wildlife Fund)",
    "wof:placetype":"venue"
},
  "geometry": {"coordinates":[6.2616271973,46.4224128723],"type":"Point"}
}