{
  "type": "Feature",
  "properties": {
    "iso:country":"CH",
    "sg:address":"Vela Via Vincenzo 3",
    "sg:city":"Chiasso",
    "sg:orig_category":"Verwaltung von Immobilien",
    "sg:phone":"+41 71 930 05 55",
    "sg:postcode":"6830",
    "sg:province":"Ticino",
    "wof:name":"Finara Ag Grundst\u00fccke; Kauf, Verkauf, Vermittlung, Verwaltung Usw.",
    "wof:placetype":"venue"
},
  "geometry": {"coordinates":[9.0409908295,47.4100990295],"type":"Point"}
}