{
  "type": "Feature",
  "properties": {
    "iso:country":"CH",
    "sg:address":"Obereggerstrasse",
    "sg:city":"Heiden",
    "sg:orig_category":"Handel mit Automobilen",
    "sg:postcode":"9410",
    "sg:province":"Appenzell Ausserrhoden",
    "wof:name":"Oliva Autohandel & Tuning",
    "wof:placetype":"venue"
},
  "geometry": {"coordinates":[8.1431903839,47.4373092651],"type":"Point"}
}