{
  "type": "Feature",
  "properties": {
    "iso:country":"CH",
    "sg:address":"Strassburgstrasse 11",
    "sg:city":"Z\u00fcrich",
    "sg:orig_category":"Berufsorganisationen",
    "sg:postcode":"8004",
    "sg:province":"Z\u00fcrich",
    "wof:name":"Gewerkschaftshaus",
    "wof:placetype":"venue"
},
  "geometry": {"coordinates":[8.528771,47.372543],"type":"Point"}
}