{
  "type": "Feature",
  "properties": {
    "addr:full":"Varis 12 Freiburg Fribourg 1700",
    "addr:housenumber":"12",
    "addr:postcode":"1700",
    "iso:country":"CH",
    "sg:address":"Varis 12",
    "sg:city":"Freiburg",
    "sg:orig_category":"Detailhandel mit Antiquit\u00e4ten U Gebrauchtwaren in Verkaufsr\u00e4umen",
    "sg:phone":"+41 71 245 00 30",
    "sg:postcode":"1700",
    "sg:province":"Fribourg",
    "wof:name":"Bravo V.a.v. Gmbh",
    "wof:placetype":"venue"
},
  "geometry": {"coordinates":[9.384803,47.433495],"type":"Point"}
}