{
  "type": "Feature",
  "properties": {
    "iso:country":"CH",
    "sg:address":"Mattenweg 11",
    "sg:city":"Sch\u00f6nb\u00fchl-urtenen",
    "sg:classifiers":[
        {
            "category":"Insurance",
            "subcategory":"Insurance Agent",
            "type":"Services"
        }
    ],
    "sg:phone":"+41 31 859 38 92",
    "sg:postcode":"3322",
    "sg:province":"Bern",
    "sg:tags":[
        "versicherungsagenturen",
        "-broker"
    ],
    "wof:name":"Winterthur-leben Agentur",
    "wof:placetype":"venue"
},
  "geometry": {"coordinates":[7.4956221581,47.021648407],"type":"Point"}
}