{
  "type": "Feature",
  "properties": {
    "iso:country":"CH",
    "sg:address":"H\u00fcnenbergerstrasse 5",
    "sg:city":"Cham",
    "sg:orig_category":"Grosshandel mit Erzen U Metallen Sonstiger Grosshandel",
    "sg:phone":"+41 41 785 82 33",
    "sg:postcode":"6330",
    "sg:province":"Zug",
    "wof:name":"Brand Metal Trading Ltd",
    "wof:placetype":"venue"
},
  "geometry": {"coordinates":[8.4567241669,47.1795349121],"type":"Point"}
}