{
  "type": "Feature",
  "properties": {
    "iso:country":"CH",
    "sg:address":"Herracherweg 18 8610 Uster. Postfach 88",
    "sg:city":"Uster",
    "sg:orig_category":"Sonstige Kurierdienste",
    "sg:postcode":"8610",
    "sg:province":"Z\u00fcrich",
    "wof:name":"Baumann R. Kurierdienste Und Kleintransporte",
    "wof:placetype":"venue"
},
  "geometry": {"coordinates":[8.7151899338,47.3495101929],"type":"Point"}
}