{
  "type": "Feature",
  "properties": {
    "iso:country":"CH",
    "sg:address":"Rue De Lausanne 65 -",
    "sg:city":"Geneva",
    "sg:classifiers":[
        {
            "category":"Professional",
            "subcategory":"Art Services",
            "type":"Services"
        }
    ],
    "sg:phone":"+41 22 740 49 40",
    "sg:postcode":"1202",
    "sg:province":"Gen\u00e8ve",
    "sg:tags":[
        "export-import"
    ],
    "wof:name":"Eritrea Consulate",
    "wof:placetype":"venue"
},
  "geometry": {"coordinates":[6.133918,46.215908],"type":"Point"}
}