{
  "type": "Feature",
  "properties": {
    "iso:country":"CH",
    "sg:address":"Rue Verdaine 9",
    "sg:city":"Genf",
    "sg:orig_category":"Detailhandel mit Bekleidung",
    "sg:phone":"+41 22 310 01 28",
    "sg:postcode":"1200",
    "sg:province":"Gen\u00e8ve",
    "wof:name":"Boutique Kalinka, Goux De Olivera Bernadette",
    "wof:placetype":"venue"
},
  "geometry": {"coordinates":[6.150375,46.201286],"type":"Point"}
}