{
  "type": "Feature",
  "properties": {
    "iso:country":"CH",
    "sg:address":"Staudengasse 636",
    "sg:city":"Eschen",
    "sg:orig_category":"Sportvereine Velo Rad-& Motorfahrer-Bund SRB",
    "sg:phone":"+41 62 824 64 14",
    "sg:postcode":"9492",
    "wof:name":"Veloclub Rohr",
    "wof:placetype":"venue"
},
  "geometry": {"coordinates":[8.0888996124,47.40391922],"type":"Point"}
}