{
  "type": "Feature",
  "properties": {
    "iso:country":"CH",
    "sg:address":"Auberg 4 4051 Basel. Postfach",
    "sg:city":"Basel",
    "sg:orig_category":"Grosshandel mit Maschinen U Ausr\u00fcstungen Grosshandel mit sonstigen Maschinen U Ausr\u00fcstungen f\u00fcr Indu",
    "sg:phone":"+41 61 272 32 52",
    "sg:postcode":"4001",
    "sg:province":"Basel-Stadt",
    "wof:name":"Spamak Aktiengesellschaft",
    "wof:placetype":"venue"
},
  "geometry": {"coordinates":[7.5852270126,47.5524215698],"type":"Point"}
}