{
  "type": "Feature",
  "properties": {
    "iso:country":"CH",
    "sg:address":"R\u00e9sidence Bellevue",
    "sg:city":"F\u00fcrigen",
    "sg:orig_category":"Finanzierungsinstitutionen",
    "sg:phone":"+41 41 610 79 60",
    "sg:postcode":"6363",
    "sg:province":"Nidwalden",
    "wof:name":"Abri Investments Bringolf Astrid",
    "wof:placetype":"venue"
},
  "geometry": {"coordinates":[8.3511486053,46.9822006226],"type":"Point"}
}