{
  "type": "Feature",
  "properties": {
    "iso:country":"CH",
    "sg:address":"Rebmattweg 1",
    "sg:city":"Villigen",
    "sg:orig_category":"Zimmerei, Dachdeckerei, Bauspenglerei U Abdichtung",
    "sg:phone":"+41 56 284 17 61",
    "sg:postcode":"5234",
    "sg:province":"Aargau",
    "wof:name":"Baumann Willi Gmbh",
    "wof:placetype":"venue"
},
  "geometry": {"coordinates":[8.2146549225,47.529209137],"type":"Point"}
}