{
  "type": "Feature",
  "properties": {
    "iso:country":"CH",
    "sg:address":"Burgdorfstrasse 37",
    "sg:city":"Lyssach",
    "sg:orig_category":"Naturheil\u00e4rzte and Heilpraktiker",
    "sg:phone":"+41 34 445 25 30",
    "sg:postcode":"3421",
    "sg:province":"Bern",
    "wof:name":"Adelheid Christ Hom\u00f6opathie",
    "wof:placetype":"venue"
},
  "geometry": {"coordinates":[7.5852398872,47.0656166077],"type":"Point"}
}