{
  "type": "Feature",
  "properties": {
    "addr:full":"Wehntalerstrasse 82 8157 Dielsdorf. Postfach 257 Dielsdorf Z\u00fcrich 8157",
    "addr:housenumber":"82;257",
    "addr:postcode":"8157 dielsdorf.;8157",
    "addr:street":"Wehntalerstrasse;Postfach",
    "iso:country":"CH",
    "sg:address":"Wehntalerstrasse 82 8157 Dielsdorf. Postfach 257",
    "sg:city":"Dielsdorf",
    "sg:orig_category":"Autogaragen",
    "sg:phone":"+41 56 622 40 44",
    "sg:postcode":"8157",
    "sg:province":"Z\u00fcrich",
    "wof:name":"Bruno & Andr\u00e9 Renner Garage",
    "wof:placetype":"venue"
},
  "geometry": {"coordinates":[8.269144,47.326401],"type":"Point"}
}