{
  "type": "Feature",
  "properties": {
    "addr:full":"Bahnhofstrasse 39 Kreuzlingen Thurgau 8280",
    "addr:housenumber":"39",
    "addr:postcode":"8280",
    "addr:street":"Bahnhofstrasse",
    "iso:country":"CH",
    "sg:address":"Bahnhofstrasse 39",
    "sg:city":"Kreuzlingen",
    "sg:orig_category":"Arbeitnehmerverb\u00e4nde",
    "sg:phone":"+41 71 672 67 72",
    "sg:postcode":"8280",
    "sg:province":"Thurgau",
    "wof:name":"Gewerkschaft Smuv-unia Sekretariat Kreuzlingen",
    "wof:placetype":"venue"
},
  "geometry": {"coordinates":[9.167055,47.652786],"type":"Point"}
}