{
  "type": "Feature",
  "properties": {
    "iso:country":"CH",
    "sg:address":"Via Vira 9",
    "sg:city":"Porza",
    "sg:orig_category":"Allgemeiner Hoch U Tiefbau Architektur U Ingenieurb\u00fcros",
    "sg:phone":"+41 91 942 69 68",
    "sg:postcode":"6948",
    "sg:province":"Ticino",
    "wof:name":"Bonetti & Dosso Sa Ufficio Tecnico",
    "wof:placetype":"venue"
},
  "geometry": {"coordinates":[8.954649,46.023819],"type":"Point"}
}