{
  "type": "Feature",
  "properties": {
    "iso:country":"CH",
    "sg:address":"W\u00fchrestrasse 24b 8610 Uster. Postfach",
    "sg:city":"Z\u00fcrich",
    "sg:orig_category":"Grosshandel mit Datenverarbeitungsger\u00e4ten Softwareentwicklung U beratung",
    "sg:phone":"+41 14501271",
    "sg:postcode":"8036",
    "sg:province":"Z\u00fcrich",
    "wof:name":"Db Data Gmbh",
    "wof:placetype":"venue"
},
  "geometry": {"coordinates":[8.7189216614,47.3374252319],"type":"Point"}
}