{
  "type": "Feature",
  "properties": {
    "addr:full":"Grenzstrasse 88a 4057 Basel. Postfach Basel Basel-Stadt 4019",
    "addr:housenumber":"88a",
    "addr:postcode":"4057;4019",
    "addr:street":"Grenzstrasse;Postfach",
    "iso:country":"CH",
    "sg:address":"Grenzstrasse 88a 4057 Basel. Postfach",
    "sg:city":"Basel",
    "sg:orig_category":"Bauschreinerei",
    "sg:phone":"+41 61 631 11 50",
    "sg:postcode":"4019",
    "sg:province":"Basel-Stadt",
    "wof:name":"Meier-l\u00f6liger Ag Mechan. Schreinerei, Schreibarbeiten Usw",
    "wof:placetype":"venue"
},
  "geometry": {"coordinates":[7.601836,47.58564],"type":"Point"}
}