{
  "type": "Feature",
  "properties": {
    "addr:full":"St. Gallerstr. 180 Winterthur Z\u00fcrich 8411",
    "addr:housenumber":"180",
    "addr:postcode":"8411",
    "iso:country":"CH",
    "sg:address":"St. Gallerstr. 180",
    "sg:city":"Winterthur",
    "sg:classifiers":[
        {
            "category":"Manufacturing",
            "subcategory":"Chemicals & Compounds",
            "type":"Manufacturing & Wholesale Goods"
        }
    ],
    "sg:phone":"+41 52 234 44 44",
    "sg:postcode":"8411",
    "sg:province":"Z\u00fcrich",
    "sg:tags":[
        "pharmaceutical",
        "chemistry",
        "-",
        "by-product"
    ],
    "wof:name":"Cwk Ag",
    "wof:placetype":"venue"
},
  "geometry": {"coordinates":[8.72616,47.499882],"type":"Point"}
}