{
  "type": "Feature",
  "properties": {
    "addr:full":"Bielstrasse 83 4500 Solothurn. Postfach 262 Solothurn Solothurn 4503",
    "addr:housenumber":"83;262",
    "addr:postcode":"4500 solothurn.;4503",
    "addr:street":"Bielstrasse;Postfach",
    "iso:country":"CH",
    "sg:address":"Bielstrasse 83 4500 Solothurn. Postfach 262",
    "sg:city":"Solothurn",
    "sg:orig_category":"Allgemeiner Hoch U Tiefbau",
    "sg:phone":"+41 32 623 10 82",
    "sg:postcode":"4503",
    "sg:province":"Solothurn",
    "wof:name":"Jakob Bau Ag",
    "wof:placetype":"venue"
},
  "geometry": {"coordinates":[7.524514,47.211346],"type":"Point"}
}