{
  "type": "Feature",
  "properties": {
    "iso:country":"CH",
    "sg:address":"Hofstattstrasse 19",
    "sg:city":"Derendingen",
    "sg:orig_category":"Sonstiger Grosshandel",
    "sg:phone":"+41 32 682 34 17",
    "sg:postcode":"4552",
    "sg:province":"Solothurn",
    "wof:name":"Gloor-k\u00f6hli Ruth",
    "wof:placetype":"venue"
},
  "geometry": {"coordinates":[7.5885839462,47.1877861023],"type":"Point"}
}