{
  "type": "Feature",
  "properties": {
    "iso:country":"CH",
    "sg:address":"Chiasso Via",
    "sg:city":"Biasca",
    "sg:orig_category":"Vermietung U Verpachtung von eigenen Immobilien",
    "sg:postcode":"6710",
    "sg:province":"Ticino",
    "wof:name":"Valscura Sa",
    "wof:placetype":"venue"
},
  "geometry": {"coordinates":[8.9766597748,46.3404998779],"type":"Point"}
}