{
  "type": "Feature",
  "properties": {
    "iso:country":"CH",
    "sg:address":"Schorenweg 1",
    "sg:city":"Basel",
    "sg:orig_category":"Herstellung von Schl\u00f6ssern U Beschl\u00e4gen",
    "sg:phone":"+41 79 333 57 56",
    "sg:postcode":"4058",
    "sg:province":"Basel-Stadt",
    "wof:name":"Speedy Schl\u00fcssel-dienst Tumminelli V.",
    "wof:placetype":"venue"
},
  "geometry": {"coordinates":[7.6097187996,47.5699424744],"type":"Point"}
}