{
  "type": "Feature",
  "properties": {
    "iso:country":"CH",
    "sg:address":"Lischweg 15",
    "sg:city":"Vordemwald",
    "sg:orig_category":"Strassenbau",
    "sg:phone":"+41 62 751 72 56",
    "sg:postcode":"4803",
    "sg:province":"Aargau",
    "wof:name":"Walter Ebinger Strassenbau",
    "wof:placetype":"venue"
},
  "geometry": {"coordinates":[7.8993501663,47.2756385803],"type":"Point"}
}