{
  "type": "Feature",
  "properties": {
    "iso:country":"CH",
    "sg:address":"Talstrasse 2",
    "sg:city":"Auenstein",
    "sg:orig_category":"Grosshandel mit Baumaterialien Grosshandel mit Holz U Baustoffen",
    "sg:phone":"+41 56 443 37 77",
    "sg:postcode":"5105",
    "sg:province":"Aargau",
    "wof:name":"Kbs, Kirchhofer-boden-systeme Ag",
    "wof:placetype":"venue"
},
  "geometry": {"coordinates":[8.1097135544,47.4402351379],"type":"Point"}
}