{
  "type": "Feature",
  "properties": {
    "iso:country":"CH",
    "sg:address":"Farinet",
    "sg:city":"Montana-vermala",
    "sg:orig_category":"Detailhandel mit B\u00fcchern Detailhandel mit Schreib U Papeteriewaren",
    "sg:phone":"+41 27 481 79 34",
    "sg:postcode":"3962",
    "wof:name":"Librairie-papeterie Du Haut-plateau",
    "wof:placetype":"venue"
},
  "geometry": {"coordinates":[7.492434,46.314419],"type":"Point"}
}