{
  "type": "Feature",
  "properties": {
    "iso:country":"CH",
    "sg:address":"L\u00e9man Route Du 33 1895 Vionnaz. Postfach",
    "sg:city":"Vionnaz",
    "sg:orig_category":"Detailhandel mit M\u00f6beln U Haushaltsgegenst\u00e4nden",
    "sg:postcode":"1895",
    "sg:province":"Valais",
    "wof:name":"Trisconi V. Sa Commerce De Meubles Etc",
    "wof:placetype":"venue"
},
  "geometry": {"coordinates":[6.8994240761,46.3116989136],"type":"Point"}
}