{
  "type": "Feature",
  "properties": {
    "iso:country":"CH",
    "sg:address":"Route De Sonvilier 31 2610 St-imier Case Postale 64",
    "sg:city":"St-imier",
    "sg:orig_category":"Offsetdruck",
    "sg:phone":"+41 32 941 22 96",
    "sg:postcode":"2610",
    "sg:province":"Bern",
    "wof:name":"Favre Sa Imprimerie",
    "wof:placetype":"venue"
},
  "geometry": {"coordinates":[6.9885149002,47.1489372253],"type":"Point"}
}