{
  "type": "Feature",
  "properties": {
    "iso:country":"CH",
    "sg:address":"Schartenstrasse 24",
    "sg:city":"Rebstein",
    "sg:orig_category":"Sonstige Kultur U Unterhaltungseinrichtungen",
    "sg:postcode":"9445",
    "sg:province":"St. Gallen",
    "wof:name":"Pel\u00dc Gmbh",
    "wof:placetype":"venue"
},
  "geometry": {"coordinates":[8.3117341995,46.9878578186],"type":"Point"}
}