{
  "type": "Feature",
  "properties": {
    "iso:country":"CH",
    "sg:address":"Rue Des Alpes 53",
    "sg:city":"Crissier",
    "sg:orig_category":"Detailhandel mit Spielwaren Detailhandel mit S\u00e4uglings U Kinderbekleidung",
    "sg:phone":"+41 21 636 40 88",
    "sg:postcode":"1023",
    "sg:province":"Vaud",
    "wof:name":"Boutique Aux Enfants",
    "wof:placetype":"venue"
},
  "geometry": {"coordinates":[6.5799679756,46.5412635803],"type":"Point"}
}