{
  "type": "Feature",
  "properties": {
    "iso:country":"CH",
    "sg:address":"Weidenweg 17",
    "sg:city":"Frenkendorf",
    "sg:orig_category":"Sportschulen Fern\u00f6stliche Kampfsportarten Sportvereine Judo and Karate",
    "sg:postcode":"4402",
    "sg:province":"Basel-Landschaft",
    "wof:name":"Js Kun-tai-ko F\u00fcllinsdorf",
    "wof:placetype":"venue"
},
  "geometry": {"coordinates":[7.7145199776,47.5000305176],"type":"Point"}
}