{
  "type": "Feature",
  "properties": {
    "addr:full":"Solothurnstr. 26 Jegenstorf Bern 3303",
    "addr:housenumber":"26",
    "addr:postcode":"3303",
    "addr:street":"Solothurnstr.",
    "iso:country":"CH",
    "sg:address":"Solothurnstr. 26",
    "sg:city":"Jegenstorf",
    "sg:classifiers":[
        {
            "category":"Banks & Credit Unions",
            "subcategory":"Bank",
            "type":"Services"
        }
    ],
    "sg:postcode":"3303",
    "sg:province":"Bern",
    "wof:name":"Amtsersparniskasse Obersimmental",
    "wof:placetype":"venue"
},
  "geometry": {"coordinates":[7.372635,46.552876],"type":"Point"}
}