{
  "type": "Feature",
  "properties": {
    "iso:country":"CH",
    "sg:address":"Postgasse 14",
    "sg:city":"Binningen",
    "sg:orig_category":"Bauspenglerei Sanit\u00e4rinstallation",
    "sg:phone":"+41 61 421 61 80",
    "sg:postcode":"4102",
    "sg:province":"Basel-Landschaft",
    "wof:name":"Urs Schaub Sanit\u00e4re Anlagen & Spenglerei",
    "wof:placetype":"venue"
},
  "geometry": {"coordinates":[7.57492,47.540634],"type":"Point"}
}