{
  "type": "Feature",
  "properties": {
    "iso:country":"CH",
    "sg:address":"Schaffhauserstrasse 335 8000 Z\u00fcrich. Postfach 8050 Z\u00fcrich",
    "sg:city":"Zust",
    "sg:orig_category":"Interessenvertretungen",
    "sg:postcode":"50",
    "wof:name":"Stiftung Des Rotary Clubs Oerlikon",
    "wof:placetype":"venue"
},
  "geometry": {"coordinates":[8.546462059,47.4084510803],"type":"Point"}
}