{
  "type": "Feature",
  "properties": {
    "iso:country":"CH",
    "sg:address":"Conters Im Pr\u00e4ttigau",
    "sg:city":"K\u00fcblis",
    "sg:orig_category":"Gemeindeverwaltungen",
    "sg:phone":"+41 79 330 53 17",
    "sg:postcode":"7240",
    "sg:province":"Graubunden",
    "wof:name":"Gemeindeverwaltung Conters Im Pr\u00e4ttigau",
    "wof:placetype":"venue"
},
  "geometry": {"coordinates":[9.7779302597,46.9144554138],"type":"Point"}
}