{
  "type": "Feature",
  "properties": {
    "iso:country":"CH",
    "sg:address":"Falknerstrasse 36 4001 Basel. Postfach",
    "sg:city":"Basel",
    "sg:orig_category":"Ausgleichskassen AHV/IV",
    "sg:phone":"+41 61 264 97 55",
    "sg:postcode":"4001",
    "sg:province":"Basel-Stadt",
    "wof:name":"Ausgleichskasse Der Brauereien",
    "wof:placetype":"venue"
},
  "geometry": {"coordinates":[7.58894,47.555595],"type":"Point"}
}