{
  "type": "Feature",
  "properties": {
    "addr:full":"Rue Du Mont-blanc 30 Gen\u00e8ve Gen\u00e8ve 1201",
    "addr:housenumber":"30",
    "addr:postcode":"1201",
    "addr:street":"Rue Du Mont-Blanc",
    "iso:country":"CH",
    "sg:address":"Rue Du Mont-blanc 30",
    "sg:city":"Gen\u00e8ve",
    "sg:orig_category":"Detailhandel mit Bekleidung",
    "sg:phone":"+41 22 732 88 62",
    "sg:postcode":"1201",
    "sg:province":"Gen\u00e8ve",
    "wof:name":"Bella K\u00f6stenbaum Chemiserie Elys\u00e9e",
    "wof:placetype":"venue"
},
  "geometry": {"coordinates":[6.143337,46.209438],"type":"Point"}
}