{
  "type": "Feature",
  "properties": {
    "addr:full":"Chuematt 3 Sachseln Obwalden 6072",
    "addr:housenumber":"3",
    "addr:postcode":"6072",
    "addr:street":"Chuematt",
    "iso:country":"CH",
    "sg:address":"Chuematt 3",
    "sg:city":"Sachseln",
    "sg:orig_category":"Detailhandel mit Bekleidung",
    "sg:phone":"+41 19301067",
    "sg:postcode":"6072",
    "sg:province":"Obwalden",
    "wof:name":"Petit Paris Gmbh",
    "wof:placetype":"venue"
},
  "geometry": {"coordinates":[8.798246,47.323322],"type":"Point"}
}