{
  "type": "Feature",
  "properties": {
    "iso:country":"CH",
    "sg:address":"Bielstrasse 26",
    "sg:city":"Br\u00fcgg",
    "sg:orig_category":"Precision Adjusting Nuts",
    "sg:phone":"+41 32 372 17 88",
    "sg:postcode":"2555",
    "sg:province":"Bern",
    "wof:name":"Kuso Gmbh",
    "wof:placetype":"venue"
},
  "geometry": {"coordinates":[7.2737689018,47.1253089905],"type":"Point"}
}