{
  "type": "Feature",
  "properties": {
    "iso:country":"CH",
    "sg:address":"Falknerstrasse 5",
    "sg:city":"Basel",
    "sg:orig_category":"Kauf U Verkauf von Immobilien auf eigene Rechnung",
    "sg:postcode":"4001",
    "sg:province":"Basel-Stadt",
    "wof:name":"Armand Goetschel, Aktiengesellschaft",
    "wof:placetype":"venue"
},
  "geometry": {"coordinates":[7.589017868,47.5563926697],"type":"Point"}
}