{
  "type": "Feature",
  "properties": {
    "iso:country":"CH",
    "sg:address":"Rue Du Roveray 13",
    "sg:city":"Gen\u00e8ve",
    "sg:orig_category":"Architekturb\u00fcros",
    "sg:phone":"+41 22 700 51 35",
    "sg:postcode":"1207",
    "sg:province":"Gen\u00e8ve",
    "wof:name":"Fran\u00e7ois Frey & Charles Pictet Bureau D'architecte",
    "wof:placetype":"venue"
},
  "geometry": {"coordinates":[6.15959,46.204948],"type":"Point"}
}