{
  "type": "Feature",
  "properties": {
    "iso:country":"CH",
    "sg:address":"Bahnhofstrasse 182 6654 Cavigliano Casella Postale 5",
    "sg:city":"Cavigliano",
    "sg:classifiers":[
        {
            "category":"Restaurant",
            "type":"Food & Drink"
        }
    ],
    "sg:phone":"+41 91 780 71 70",
    "sg:postcode":"6654",
    "sg:province":"Ticino",
    "sg:tags":[
        "tea-rooms",
        "restaurants"
    ],
    "wof:name":"Bar Ristorante El Centro Casagrande Claudio",
    "wof:placetype":"venue"
},
  "geometry": {"coordinates":[8.719209671,46.184879303],"type":"Point"}
}