{
  "type": "Feature",
  "properties": {
    "iso:country":"CH",
    "sg:address":"Haus Fleckstein",
    "sg:city":"Randa",
    "sg:orig_category":"Stukkateurgewerbe, Gipserei U Verputzerei",
    "sg:phone":"+41 27 967 59 49",
    "sg:postcode":"3928",
    "sg:province":"Valais",
    "wof:name":"Urban Brantschen Gipsergesch\u00e4ft",
    "wof:placetype":"venue"
},
  "geometry": {"coordinates":[7.7803549767,46.0985984802],"type":"Point"}
}