{
  "type": "Feature",
  "properties": {
    "iso:country":"CH",
    "sg:address":"Rue De L'avenir 23",
    "sg:city":"Del\u00e9mont",
    "sg:orig_category":"Wirtschaftspr\u00fcfung, Steuerberatung U Treuhand",
    "sg:phone":"+41 32 423 47 47",
    "sg:postcode":"2800",
    "sg:province":"Jura",
    "wof:name":"Fiduciaire Juravenir Sa",
    "wof:placetype":"venue"
},
  "geometry": {"coordinates":[7.350897789,47.3648757935],"type":"Point"}
}