{
  "type": "Feature",
  "properties": {
    "iso:country":"CH",
    "sg:address":"Rue Louis-favre 39",
    "sg:city":"Boudry",
    "sg:orig_category":"Konkurs- and Betreibungs\u00e4mter",
    "sg:phone":"+41 32 842 19 22",
    "sg:postcode":"2017",
    "sg:province":"Neuch\u00e2tel",
    "wof:name":"Office Des Poursuites & Faillites",
    "wof:placetype":"venue"
},
  "geometry": {"coordinates":[6.8355870247,46.9486160278],"type":"Point"}
}