{
  "type": "Feature",
  "properties": {
    "iso:country":"CH",
    "sg:address":"M\u00fchlestrasse 6",
    "sg:city":"Grenchen",
    "sg:orig_category":"Detailhandel mit Brot, Back U S\u00fcsswaren",
    "sg:postcode":"2540",
    "sg:province":"Solothurn",
    "wof:name":"B\u00e4ckerei-konditorei Alte M\u00fchle, Sprenger",
    "wof:placetype":"venue"
},
  "geometry": {"coordinates":[7.394345,47.197231],"type":"Point"}
}