{
  "type": "Feature",
  "properties": {
    "iso:country":"CH",
    "sg:address":"Fl\u00fcckenstrasse 127",
    "sg:city":"Meisterschwanden",
    "sg:orig_category":"Mechanik Mechanische Werkst\u00e4tten",
    "sg:phone":"+41 79 657 63 82",
    "sg:postcode":"5616",
    "sg:province":"Aargau",
    "wof:name":"Amsco Elektro Schweisstechnik Ag",
    "wof:placetype":"venue"
},
  "geometry": {"coordinates":[8.2322626114,47.2931556702],"type":"Point"}
}