{
  "type": "Feature",
  "properties": {
    "iso:country":"CH",
    "sg:address":"Harzachstrasse 5",
    "sg:city":"Winterthur",
    "sg:orig_category":"Architektur U Ingenieurb\u00fcros",
    "sg:phone":"+41 52 235 10 80",
    "sg:postcode":"8404",
    "sg:province":"Z\u00fcrich",
    "wof:name":"Leicom Ag",
    "wof:placetype":"venue"
},
  "geometry": {"coordinates":[8.763846,47.495396],"type":"Point"}
}