{
  "type": "Feature",
  "properties": {
    "addr:full":"Via Mappo 8 Tenero Ticino 6598",
    "addr:housenumber":"8",
    "addr:postcode":"6598",
    "addr:street":"Via Mappo",
    "iso:country":"CH",
    "sg:address":"Via Mappo 8",
    "sg:city":"Tenero",
    "sg:orig_category":"Architektur U Ingenieurb\u00fcros",
    "sg:phone":"+41 91 745 05 44",
    "sg:postcode":"6598",
    "sg:province":"Ticino",
    "wof:name":"T 21 Gmbh Dienstleistungen Im Technischen Bereich. Warenhandel",
    "wof:placetype":"venue"
},
  "geometry": {"coordinates":[8.84986,46.180897],"type":"Point"}
}