{
  "type": "Feature",
  "properties": {
    "iso:country":"CH",
    "sg:address":"Rue De La Grand'vigne 5",
    "sg:city":"Vouvry",
    "sg:orig_category":"Datenverarbeitungsdienste Sonstige mit der Informatik verbundene T\u00e4tigkeiten",
    "sg:phone":"+41 24 481 44 33",
    "sg:postcode":"1896",
    "sg:province":"Valais",
    "wof:name":"Rinaldi James",
    "wof:placetype":"venue"
},
  "geometry": {"coordinates":[6.887451,46.33408],"type":"Point"}
}