{
  "type": "Feature",
  "properties": {
    "iso:country":"CH",
    "sg:address":"Neugutstrasse 58",
    "sg:city":"D\u00fcbendorf",
    "sg:orig_category":"Pensionskassen",
    "sg:postcode":"8600",
    "sg:province":"Z\u00fcrich",
    "wof:name":"Wohlfahrtsfonds Der Injecta Ag",
    "wof:placetype":"venue"
},
  "geometry": {"coordinates":[8.1137800217,47.3318786621],"type":"Point"}
}