{
  "type": "Feature",
  "properties": {
    "iso:country":"CH",
    "sg:address":"Schaffhauserstrasse 550",
    "sg:city":"Z\u00fcrich",
    "sg:orig_category":"Non-Classified Establishments",
    "sg:phone":"+41 56 442 63 13",
    "sg:postcode":"8052",
    "sg:province":"Z\u00fcrich",
    "wof:name":"Zst Haustechnik Gmbh",
    "wof:placetype":"venue"
},
  "geometry": {"coordinates":[8.205532074,47.4626426697],"type":"Point"}
}