{
  "type": "Feature",
  "properties": {
    "addr:full":"Spelterinistrasse 7 Bazenheid St. Gallen 9602",
    "addr:housenumber":"7;st.",
    "addr:postcode":"9602",
    "addr:street":"Spelterinistrasse",
    "iso:country":"CH",
    "sg:address":"Spelterinistrasse 7",
    "sg:city":"Bazenheid",
    "sg:orig_category":"Architekturb\u00fcros",
    "sg:phone":"+41 71 931 22 77",
    "sg:postcode":"9602",
    "sg:province":"St. Gallen",
    "wof:name":"Guido Sch\u00f6nenberger Architekturb\u00fcro",
    "wof:placetype":"venue"
},
  "geometry": {"coordinates":[9.066092,47.412697],"type":"Point"}
}