{
  "type": "Feature",
  "properties": {
    "iso:country":"CH",
    "sg:address":"Avenue Des Amazones 16",
    "sg:city":"Ch\u00eane-bougeries",
    "sg:orig_category":"Innenarchitekturb\u00fcros",
    "sg:phone":"+41 22 348 22 01",
    "sg:postcode":"1224",
    "sg:province":"Gen\u00e8ve",
    "wof:name":"Christine Othenin-girard Architecture D'int\u00e9rieur",
    "wof:placetype":"venue"
},
  "geometry": {"coordinates":[6.1859788895,46.2021827698],"type":"Point"}
}