{
  "type": "Feature",
  "properties": {
    "iso:country":"CH",
    "sg:address":"Bleicheli 89",
    "sg:city":"B\u00fchler",
    "sg:orig_category":"Sonstige pers\u00f6nliche Dienstleistungen",
    "sg:postcode":"9055",
    "sg:province":"Appenzell Ausserrhoden",
    "wof:name":"Romer-consult",
    "wof:placetype":"venue"
},
  "geometry": {"coordinates":[9.422036171,47.3704071045],"type":"Point"}
}