{
  "type": "Feature",
  "properties": {
    "iso:country":"CH",
    "sg:address":"Moosb\u00fchlweg 2 3673 Linden. Postfach 11",
    "sg:city":"Linden",
    "sg:orig_category":"Handelsvermittlung U Grosshandel Herstellung von Metallkonstruktionen",
    "sg:phone":"+41 32 925 09 09",
    "sg:postcode":"3673",
    "sg:province":"Bern",
    "wof:name":"Setco La Chaux-de-fonds Sa",
    "wof:placetype":"venue"
},
  "geometry": {"coordinates":[6.8154511452,47.0963630676],"type":"Point"}
}