{
  "type": "Feature",
  "properties": {
    "iso:country":"CH",
    "sg:address":"Werkstrasse 10",
    "sg:city":"Diepoldsau",
    "sg:orig_category":"Handelsvermittlung U Grosshandel mit Automobilteilen U Zubeh\u00f6r Herstellung von Teilen U Zubeh\u00f6r f\u00fcr ",
    "sg:phone":"+41 19352704",
    "sg:postcode":"9444",
    "sg:province":"St. Gallen",
    "wof:name":"Wepla Ag",
    "wof:placetype":"venue"
},
  "geometry": {"coordinates":[8.7521724701,47.3063316345],"type":"Point"}
}