{
  "type": "Feature",
  "properties": {
    "iso:country":"CH",
    "sg:address":"Spitalgasse 4",
    "sg:city":"Bern",
    "sg:orig_category":"Unternehmensberatung",
    "sg:phone":"+41 78 632 39 30",
    "sg:postcode":"3011",
    "sg:province":"Bern",
    "wof:name":"Clivaz Roger-pierre Courtage En Transmission D'entreprises, Immobiliers Etc",
    "wof:placetype":"venue"
},
  "geometry": {"coordinates":[7.4068250656,46.2767829895],"type":"Point"}
}