{
  "type": "Feature",
  "properties": {
    "iso:country":"CH",
    "sg:address":"Niedersurenen",
    "sg:city":"Engelberg",
    "sg:classifiers":[
        {
            "category":"Restaurant",
            "type":"Food & Drink"
        }
    ],
    "sg:phone":"+41 41 637 44 24",
    "sg:postcode":"6390",
    "sg:province":"Obwalden",
    "wof:name":"Restaurant Alpenr\u00f6sli",
    "wof:placetype":"venue"
},
  "geometry": {"coordinates":[8.4043922424,46.8209877014],"type":"Point"}
}