{
  "type": "Feature",
  "properties": {
    "iso:country":"CH",
    "sg:address":"Sonnhaldestrasse 14",
    "sg:city":"B\u00fctzberg",
    "sg:orig_category":"Schwimmb\u00e4der",
    "sg:postcode":"4922",
    "sg:province":"Bern",
    "wof:name":"Primarschulanlage Byfang Betriebsleitung Hallenbad",
    "wof:placetype":"venue"
},
  "geometry": {"coordinates":[7.75395298,47.2041740417],"type":"Point"}
}