{
  "type": "Feature",
  "properties": {
    "iso:country":"CH",
    "sg:address":"Herrengasse 37",
    "sg:city":"Schwyz",
    "sg:orig_category":"K\u00fcnstlerische Schulen",
    "sg:phone":"+41 61 401 25 98",
    "sg:postcode":"6430",
    "sg:province":"Schwyz",
    "wof:name":"Jugendmusikschule",
    "wof:placetype":"venue"
},
  "geometry": {"coordinates":[7.5549578667,47.5137214661],"type":"Point"}
}