{
  "type": "Feature",
  "properties": {
    "iso:country":"CH",
    "sg:address":"Wildensteinerstrasse 12",
    "sg:city":"Bubendorf",
    "sg:orig_category":"Detailhandel mit Teppichen Verlegen von Fussboden",
    "sg:phone":"+41 71 385 42 52",
    "sg:postcode":"4416",
    "sg:province":"Basel-Landschaft",
    "wof:name":"Xaver Benz Teppiche & Bodenbel\u00e4ge",
    "wof:placetype":"venue"
},
  "geometry": {"coordinates":[9.2740983963,47.4164390564],"type":"Point"}
}