{
  "type": "Feature",
  "properties": {
    "iso:country":"CH",
    "sg:address":"Aarestrasse 2",
    "sg:city":"Thun",
    "sg:classifiers":[
        {
            "category":"Professional",
            "subcategory":"Employment Agencies",
            "type":"Services"
        }
    ],
    "sg:phone":"+41 33 227 20 00",
    "sg:postcode":"3600",
    "sg:province":"Bern",
    "sg:tags":[
        "personal",
        "u",
        "stellenvermittlung"
    ],
    "wof:name":"A-eins Personal Ag",
    "wof:placetype":"venue"
},
  "geometry": {"coordinates":[7.6257109642,46.7591133118],"type":"Point"}
}