{
  "type": "Feature",
  "properties": {
    "iso:country":"CH",
    "sg:address":"Nordring 2 8854 Siebnen. Postfach 110",
    "sg:city":"Siebnen",
    "sg:orig_category":"Herstellung von Baubedarfsartikeln aus Kunststoff",
    "sg:phone":"+41 55 440 28 82",
    "sg:postcode":"8854",
    "sg:province":"Schwyz",
    "wof:name":"Hermann Kessler Ag Kunststoff-fenster",
    "wof:placetype":"venue"
},
  "geometry": {"coordinates":[8.9090356827,47.1766242981],"type":"Point"}
}