{
  "type": "Feature",
  "properties": {
    "iso:country":"CH",
    "sg:address":"Kempttalstrasse 48",
    "sg:city":"Fehraltorf",
    "sg:orig_category":"Regionalbanken U Sparkassen",
    "sg:phone":"+41 19541888",
    "sg:postcode":"8320",
    "sg:province":"Z\u00fcrich",
    "wof:name":"Sparkasse Z\u00fcrcher Oberland",
    "wof:placetype":"venue"
},
  "geometry": {"coordinates":[8.7519311905,47.3878974915],"type":"Point"}
}