{
  "type": "Feature",
  "properties": {
    "iso:country":"CH",
    "sg:address":"Route De Gilly",
    "sg:city":"Bursins",
    "sg:orig_category":"Grosshandel mit Parf\u00fcmerieartikeln U K\u00f6rperpflegemitteln Grosshandel mit pharmazeutischen Erzeugniss",
    "sg:phone":"+41 22 782 10 00",
    "sg:postcode":"1183",
    "sg:province":"Vaud",
    "wof:name":"Horn C. & Cie.",
    "wof:placetype":"venue"
},
  "geometry": {"coordinates":[6.0753221512,46.2311172485],"type":"Point"}
}