{
  "type": "Feature",
  "properties": {
    "iso:country":"CH",
    "sg:address":"Grossacker",
    "sg:city":"Hersberg",
    "sg:orig_category":"Sportvereine Schwingen",
    "sg:phone":"+41 61 921 27 62",
    "sg:postcode":"4423",
    "sg:province":"Basel-Landschaft",
    "wof:name":"Schwingklub Liestal",
    "wof:placetype":"venue"
},
  "geometry": {"coordinates":[7.7827968597,47.4921455383],"type":"Point"}
}