{
  "type": "Feature",
  "properties": {
    "addr:full":"Dienerstrasse 28 Z\u00fcrich Z\u00fcrich 8004",
    "addr:housenumber":"28",
    "addr:postcode":"8004",
    "addr:street":"Dienerstrasse",
    "iso:country":"CH",
    "sg:address":"Dienerstrasse 28",
    "sg:city":"Z\u00fcrich",
    "sg:classifiers":[
        {
            "category":"Bars & Pubs",
            "type":"Food & Drink"
        }
    ],
    "sg:phone":"+41 12911414",
    "sg:postcode":"8004",
    "sg:province":"Z\u00fcrich",
    "wof:name":"Bikini Bar",
    "wof:placetype":"venue"
},
  "geometry": {"coordinates":[8.527903,47.378197],"type":"Point"}
}