{
  "type": "Feature",
  "properties": {
    "iso:country":"CH",
    "sg:address":"Avenue Parc-de-la-rouvraie 3",
    "sg:city":"Lausanne",
    "sg:orig_category":"Detailhandel mit Waren verschiedener Art, Hauptrichtung Nahrungsmittel",
    "sg:phone":"+41 21 601 31 61",
    "sg:postcode":"1018",
    "sg:province":"Vaud",
    "wof:name":"Pick Pay Partenaire Olivier Jaques",
    "wof:placetype":"venue"
},
  "geometry": {"coordinates":[6.6335749626,46.5319099426],"type":"Point"}
}