{
  "type": "Feature",
  "properties": {
    "addr:full":"Spalenring 138 4055 Basel. Postfach 399 Basel Basel-Stadt 4009",
    "addr:housenumber":"138;399",
    "addr:postcode":"4055;4009",
    "addr:street":"Spalenring;Postfach",
    "iso:country":"CH",
    "sg:address":"Spalenring 138 4055 Basel. Postfach 399",
    "sg:city":"Basel",
    "sg:orig_category":"Detailhandel mit M\u00f6beln",
    "sg:phone":"+41 61 301 55 15",
    "sg:postcode":"4009",
    "sg:province":"Basel-Stadt",
    "wof:name":"Trachtner M\u00f6bel M\u00f6bel, Bett, Polster-waren, Teppiche Usw; Handel",
    "wof:placetype":"venue"
},
  "geometry": {"coordinates":[7.575668,47.555313],"type":"Point"}
}