{
  "type": "Feature",
  "properties": {
    "iso:country":"CH",
    "sg:address":"Im F\u00fcchsli 4 8180 B\u00fclach. Postfach",
    "sg:city":"B\u00fclach",
    "sg:orig_category":"Grosshandel mit Getr\u00e4nken Wein Detailhandel",
    "sg:phone":"+41 18602025",
    "sg:postcode":"8180",
    "sg:province":"Z\u00fcrich",
    "wof:name":"Al Mercato Wanner & Azzoni",
    "wof:placetype":"venue"
},
  "geometry": {"coordinates":[8.5441856384,47.5233764648],"type":"Point"}
}