{
  "type": "Feature",
  "properties": {
    "iso:country":"CH",
    "sg:address":"Rebackerstrasse 21 8955 Oetwil. Postfach",
    "sg:city":"Oetwil",
    "sg:orig_category":"Reiseb\u00fcros U Reiseveranstalter",
    "sg:phone":"+41 17757481",
    "sg:postcode":"8955",
    "sg:province":"Z\u00fcrich",
    "wof:name":"Topkatours Chennani Reiseb\u00fcro",
    "wof:placetype":"venue"
},
  "geometry": {"coordinates":[8.3956127167,47.4269256592],"type":"Point"}
}