{
  "type": "Feature",
  "properties": {
    "iso:country":"CH",
    "sg:address":"Herrengasse 6430 Schwyz. Postfach",
    "sg:city":"Schwyz",
    "sg:orig_category":"Handel mit Automobilen",
    "sg:postcode":"6431",
    "sg:province":"Schwyz",
    "wof:name":"Garage Seeholzer",
    "wof:placetype":"venue"
},
  "geometry": {"coordinates":[8.6471700668,47.0240211487],"type":"Point"}
}