{
  "type": "Feature",
  "properties": {
    "iso:country":"CH",
    "sg:address":"Rue Des Granges 2",
    "sg:city":"Monthey",
    "sg:classifiers":[
        {
            "category":"Banks & Credit Unions",
            "subcategory":"Bank",
            "type":"Services"
        }
    ],
    "sg:phone":"+41 25719237",
    "sg:postcode":"1870",
    "sg:province":"Valais",
    "wof:name":"Nationale Suisse",
    "wof:placetype":"venue"
},
  "geometry": {"coordinates":[6.94627,46.250751],"type":"Point"}
}