{
  "type": "Feature",
  "properties": {
    "iso:country":"CH",
    "sg:address":"Willigen",
    "sg:city":"Meiringen",
    "sg:orig_category":"Hoch U Tiefbau Strassenbau",
    "sg:phone":"+41 33 971 14 71",
    "sg:postcode":"3860",
    "sg:province":"Bern",
    "wof:name":"Kohler Bau Ag",
    "wof:placetype":"venue"
},
  "geometry": {"coordinates":[8.190580368,46.7192382812],"type":"Point"}
}