{
  "type": "Feature",
  "properties": {
    "iso:country":"CH",
    "sg:address":"B\u00fcndtenweg 62",
    "sg:city":"Binningen",
    "sg:orig_category":"Detailhandel mit Musikinstrumenten",
    "sg:phone":"+41 61 421 83 63",
    "sg:postcode":"4102",
    "sg:province":"Basel-Landschaft",
    "wof:name":"Georg F. Senn Historische Tasteninstrumente",
    "wof:placetype":"venue"
},
  "geometry": {"coordinates":[7.5677161217,47.5426025391],"type":"Point"}
}