{
  "type": "Feature",
  "properties": {
    "iso:country":"CH",
    "sg:address":"Marktgasse 11",
    "sg:city":"Gelterkinden",
    "sg:orig_category":"Detailhandel mit S\u00e4uglings U Kinderbekleidung",
    "sg:phone":"+41 61 981 47 87",
    "sg:postcode":"4460",
    "sg:province":"Basel-Landschaft",
    "wof:name":"Zum Rasende Schn\u00e4gg C.wenger Kinderartikelb\u00f6rse",
    "wof:placetype":"venue"
},
  "geometry": {"coordinates":[7.8569149971,47.4640388489],"type":"Point"}
}