{
  "type": "Feature",
  "properties": {
    "iso:country":"CH",
    "sg:address":"Route De Lausanne 33",
    "sg:city":"Echallens",
    "sg:orig_category":"Detailhandel mit Ton U Bildtr\u00e4gern Vermietung von Gebrauchsg\u00fctern",
    "sg:phone":"+41 79 310 04 62",
    "sg:postcode":"1040",
    "sg:province":"Vaud",
    "wof:name":"Tara M\u00e9lodie Vente Cd Vid\u00e9o",
    "wof:placetype":"venue"
},
  "geometry": {"coordinates":[6.6357851028,46.6374473572],"type":"Point"}
}