{
  "type": "Feature",
  "properties": {
    "iso:country":"CH",
    "sg:address":"Remisbergstrasse 20",
    "sg:city":"Kreuzlingen",
    "sg:orig_category":"Arztpraxen",
    "sg:phone":"+41 71 688 25 75",
    "sg:postcode":"8280",
    "sg:province":"Thurgau",
    "wof:name":"Dres Med. A. Fuchs & D. Wolf Spezial\u00e4rzte Fmh",
    "wof:placetype":"venue"
},
  "geometry": {"coordinates":[9.1806030273,47.6432151794],"type":"Point"}
}