{
  "type": "Feature",
  "properties": {
    "iso:country":"CH",
    "sg:address":"B\u00fctzenenweg 94",
    "sg:city":"Sissach",
    "sg:orig_category":"Detailhandel mit Damenbekleidung",
    "sg:phone":"+41 61 971 36 17",
    "sg:postcode":"4450",
    "sg:province":"Basel-Landschaft",
    "wof:name":"Couture Modesta",
    "wof:placetype":"venue"
},
  "geometry": {"coordinates":[7.821232,47.4632],"type":"Point"}
}