{
  "type": "Feature",
  "properties": {
    "iso:country":"CH",
    "sg:address":"Eiweg 2 4460 Gelterkinden. Postfach",
    "sg:city":"Gelterkinden",
    "sg:orig_category":"Herstellung von Dauerbackwaren Herstellung von Verpackungsmitteln aus Holz",
    "sg:phone":"+41 21 634 47 67",
    "sg:postcode":"4460",
    "sg:province":"Basel-Landschaft",
    "wof:name":"Afiro",
    "wof:placetype":"venue"
},
  "geometry": {"coordinates":[6.5727257729,46.5379867554],"type":"Point"}
}