{
  "type": "Feature",
  "properties": {
    "addr:full":"Wiestistrasse 19 Zermatt Valais 3920",
    "addr:housenumber":"19",
    "addr:postcode":"3920",
    "addr:street":"Wiestistrasse",
    "iso:country":"CH",
    "sg:address":"Wiestistrasse 19",
    "sg:city":"Zermatt",
    "sg:classifiers":[
        {
            "category":"Bars & Pubs",
            "type":"Food & Drink"
        }
    ],
    "sg:phone":"+41 27 967 65 95",
    "sg:postcode":"3920",
    "sg:province":"Valais",
    "sg:tags":[
        "restaurant"
    ],
    "wof:name":"Restaurant & Bar La Cachette",
    "wof:placetype":"venue"
},
  "geometry": {"coordinates":[7.752579,46.023293],"type":"Point"}
}