{
  "type": "Feature",
  "properties": {
    "iso:country":"CH",
    "sg:address":"Neugasse 7",
    "sg:city":"Diepoldsau",
    "sg:orig_category":"Sanit\u00e4r U Heizungsinstallation Sanit\u00e4rinstallation",
    "sg:phone":"+41 71 733 20 43",
    "sg:postcode":"9444",
    "sg:province":"St. Gallen",
    "wof:name":"H.r. Zellweger Ag Sanit\u00e4re Anlagen & Heizungen",
    "wof:placetype":"venue"
},
  "geometry": {"coordinates":[9.6543292999,47.3882827759],"type":"Point"}
}