{
  "type": "Feature",
  "properties": {
    "iso:country":"CH",
    "sg:address":"Zentralstrasse 4",
    "sg:city":"Besenb\u00fcren",
    "sg:orig_category":"Bauschreinerei Herstellung von Konstruktionsteilen, Fertigbauteilen U Ausbauelementen aus Holz",
    "sg:phone":"+41 56 666 10 76",
    "sg:postcode":"5627",
    "sg:province":"Aargau",
    "wof:name":"Schreinerei Moser Gmbh",
    "wof:placetype":"venue"
},
  "geometry": {"coordinates":[8.342969,47.312988],"type":"Point"}
}