{
  "type": "Feature",
  "properties": {
    "iso:country":"CH",
    "sg:address":"Avenue De La Gare 13",
    "sg:city":"Monthey",
    "sg:orig_category":"Fast-Foodrestaurants",
    "sg:phone":"+41 24 471 16 47",
    "sg:postcode":"1870",
    "sg:province":"Valais",
    "wof:name":"Mega Pizza",
    "wof:placetype":"venue"
},
  "geometry": {"coordinates":[6.9492049217,46.2532730103],"type":"Point"}
}