{
  "type": "Feature",
  "properties": {
    "iso:country":"CH",
    "sg:address":"Pargherastrasse 1/3",
    "sg:city":"Chur",
    "sg:classifiers":[
        {
            "category":"Restaurant",
            "type":"Food & Drink"
        }
    ],
    "sg:phone":"+41 81 253 16 00",
    "sg:postcode":"7000",
    "sg:province":"Graubunden",
    "wof:name":"Pizzeria Triangolo",
    "wof:placetype":"venue"
},
  "geometry": {"coordinates":[9.5130853653,46.8461036682],"type":"Point"}
}