{
  "type": "Feature",
  "properties": {
    "iso:country":"CH",
    "sg:address":"9042",
    "sg:city":"Speicher",
    "sg:orig_category":"Sportvereine Turnen",
    "sg:postcode":"9042",
    "sg:province":"Appenzell Ausserrhoden",
    "wof:name":"Turnverein",
    "wof:placetype":"venue"
},
  "geometry": {"coordinates":[9.4437513351,47.4104042053],"type":"Point"}
}