{
  "type": "Feature",
  "properties": {
    "iso:country":"CH",
    "sg:address":"Wannenholzstrasse 14",
    "sg:city":"Z\u00fcrich",
    "sg:orig_category":"Hardwareberatung",
    "sg:postcode":"8046",
    "sg:province":"Z\u00fcrich",
    "wof:name":"Blue Trade And Service Gmbh",
    "wof:placetype":"venue"
},
  "geometry": {"coordinates":[8.5203561783,47.4118995667],"type":"Point"}
}