{
  "type": "Feature",
  "properties": {
    "iso:country":"CH",
    "sg:address":"Hardstrasse 35",
    "sg:city":"M\u00fcnchenstein",
    "sg:orig_category":"Primarschulen",
    "sg:phone":"+41 61 411 60 60",
    "sg:postcode":"4142",
    "sg:province":"Basel-Landschaft",
    "wof:name":"Primarschule Neuewelt",
    "wof:placetype":"venue"
},
  "geometry": {"coordinates":[7.6183028221,47.5265731812],"type":"Point"}
}