{
  "type": "Feature",
  "properties": {
    "addr:full":"Dorf Gommiswald St. Gallen 8737",
    "addr:postcode":"8737",
    "addr:street":"Dorf Gommiswald",
    "iso:country":"CH",
    "sg:address":"Dorf",
    "sg:city":"Gommiswald",
    "sg:orig_category":"Darlehenskassen U Raiffeisenbanken",
    "sg:phone":"+41 34 402 80 66",
    "sg:postcode":"8737",
    "sg:province":"St. Gallen",
    "wof:name":"Raiffeisenbank",
    "wof:placetype":"venue"
},
  "geometry": {"coordinates":[7.75759,46.949127],"type":"Point"}
}