{
  "type": "Feature",
  "properties": {
    "iso:country":"CH",
    "sg:address":"Avenue De Miremont 42 1200 Genf. Postfach",
    "sg:city":"Gen\u00e8ve",
    "sg:orig_category":"Sonstige mit der Informatik verbundene T\u00e4tigkeiten",
    "sg:postcode":"1201",
    "sg:province":"Gen\u00e8ve",
    "wof:name":"Intermed Webdesign & Consulting, Arcidiacono Et Khouja",
    "wof:placetype":"venue"
},
  "geometry": {"coordinates":[6.158493042,46.1875915527],"type":"Point"}
}