{
  "type": "Feature",
  "properties": {
    "iso:country":"CH",
    "sg:address":"Br\u00fcgistrasse 6",
    "sg:city":"Anglikon",
    "sg:orig_category":"Werbung",
    "sg:phone":"+41 56 621 95 21",
    "sg:postcode":"5611",
    "sg:province":"Aargau",
    "wof:name":"Atw Werbe Ag",
    "wof:placetype":"venue"
},
  "geometry": {"coordinates":[8.2628612518,47.3663978577],"type":"Point"}
}