{
  "type": "Feature",
  "properties": {
    "iso:country":"CH",
    "sg:address":"Gesellschaftsstrasse 80",
    "sg:city":"Bern",
    "sg:orig_category":"Physiotherapie",
    "sg:phone":"+41 31 302 15 66",
    "sg:postcode":"3012",
    "sg:province":"Bern",
    "wof:name":"Beat Studer Physiotherapie",
    "wof:placetype":"venue"
},
  "geometry": {"coordinates":[7.4314570427,46.9551010132],"type":"Point"}
}