{
  "type": "Feature",
  "properties": {
    "iso:country":"CH",
    "sg:address":"Quartierstrasse 1 8867 Niederurnen. Postfach 224",
    "sg:city":"Niederurnen",
    "sg:orig_category":"Verwaltung von Immobilien Wirtschaftspr\u00fcfung, Steuerberatung U Treuhand",
    "sg:phone":"+41 55 617 20 00",
    "sg:postcode":"8867",
    "sg:province":"Glarus",
    "wof:name":"Franco Antoniazzi Treuhandb\u00fcro",
    "wof:placetype":"venue"
},
  "geometry": {"coordinates":[9.0562458038,47.1280021667],"type":"Point"}
}