{
  "type": "Feature",
  "properties": {
    "iso:country":"CH",
    "sg:address":"Keistenweg 9 4310 Rheinfelden. Postfach",
    "sg:city":"Rheinfelden",
    "sg:orig_category":"Pensionskassen",
    "sg:postcode":"4310",
    "sg:province":"Aargau",
    "wof:name":"Stiftung 500 Jahre Sch\u00fctzengesellschaft Rheinfelden",
    "wof:placetype":"venue"
},
  "geometry": {"coordinates":[7.8000001907,47.5509300232],"type":"Point"}
}