{
  "type": "Feature",
  "properties": {
    "iso:country":"CH",
    "sg:address":"Gewerbestrasse 1",
    "sg:city":"Zuchwil",
    "sg:orig_category":"Instandhaltung U Reparatur von Automobilen",
    "sg:phone":"+41 32 685 62 18",
    "sg:postcode":"4528",
    "sg:province":"Solothurn",
    "wof:name":"B\u00f6gli Peter Ag",
    "wof:placetype":"venue"
},
  "geometry": {"coordinates":[7.572491169,47.2010574341],"type":"Point"}
}