{
  "type": "Feature",
  "properties": {
    "iso:country":"CH",
    "sg:address":"Schuermattstrasse 2a",
    "sg:city":"H\u00fcnenberg",
    "sg:orig_category":"Erdbewegungsarbeiten Spezieller Tiefbau",
    "sg:phone":"+41 41 741 52 45",
    "sg:postcode":"6331",
    "sg:province":"Zug",
    "wof:name":"Josef Wyss Tiefbau & Muldenservice",
    "wof:placetype":"venue"
},
  "geometry": {"coordinates":[8.4302463531,47.177936554],"type":"Point"}
}