{
  "type": "Feature",
  "properties": {
    "iso:country":"CH",
    "sg:address":"G\u00fcterstrasse 144",
    "sg:city":"Basel",
    "sg:orig_category":"Non-Classified Establishments",
    "sg:postcode":"4053",
    "sg:province":"Basel-Stadt",
    "wof:name":"Phoenix Projektsteuerung Ag",
    "wof:placetype":"venue"
},
  "geometry": {"coordinates":[8.7755222321,47.2052307129],"type":"Point"}
}