{
  "type": "Feature",
  "properties": {
    "iso:country":"CH",
    "sg:address":"Rheinstrasse 1 9443 Widnau. Postfach",
    "sg:city":"Widnau",
    "sg:orig_category":"Detailhandel mit elektrischen Haushalts-,Radio U Fernsehger\u00e4ten sowie Musikinstrumenten",
    "sg:postcode":"9443",
    "sg:province":"St. Gallen",
    "wof:name":"Hifi-tv Kirchhofer Hifi- U. Tv-ger\u00e4te; Verkauf U. Reparatur",
    "wof:placetype":"venue"
},
  "geometry": {"coordinates":[9.647395134,47.4071235657],"type":"Point"}
}