{
  "type": "Feature",
  "properties": {
    "iso:country":"CH",
    "sg:address":"Hauptstrasse 119 8274 T\u00e4gerwilen. Postfach",
    "sg:city":"Salenstein",
    "sg:orig_category":"Handel mit Automobilen",
    "sg:postcode":"8268",
    "sg:province":"Thurgau",
    "wof:name":"Rw Automobile, Wolfensberger Remo",
    "wof:placetype":"venue"
},
  "geometry": {"coordinates":[8.847741127,47.2520332336],"type":"Point"}
}