{
  "type": "Feature",
  "properties": {
    "iso:country":"CH",
    "sg:address":"Klosterzelgstrasse 28",
    "sg:city":"Brugg",
    "sg:orig_category":"Fibre Optic Cable And Optical Fibre Plug Connectors",
    "sg:phone":"+41 56 460 31 00",
    "sg:postcode":"5200",
    "sg:province":"Aargau",
    "wof:name":"Brugg Cables Ag",
    "wof:placetype":"venue"
},
  "geometry": {"coordinates":[8.2113075256,47.4798126221],"type":"Point"}
}