{
  "type": "Feature",
  "properties": {
    "iso:country":"CH",
    "sg:address":"Claragraben 50",
    "sg:city":"Basel",
    "sg:orig_category":"Bezirks, Sekundar, Realschulen, Oberstufe der Primarschulen Sonstiger Fachdetailhandel mit Nahrungsm",
    "sg:phone":"+41 61 681 00 02",
    "sg:postcode":"4058",
    "sg:province":"Basel-Stadt",
    "wof:name":"Platter Sa",
    "wof:placetype":"venue"
},
  "geometry": {"coordinates":[7.595926,47.560944],"type":"Point"}
}