{
  "type": "Feature",
  "properties": {
    "iso:country":"CH",
    "sg:address":"Seeli",
    "sg:city":"Richterswil",
    "sg:orig_category":"Herstellung von Konstruktionsteilen, Fertigbauteilen U Ausbauelementen aus Holz",
    "sg:phone":"+41 19322665",
    "sg:postcode":"8805",
    "sg:province":"Z\u00fcrich",
    "wof:name":"K\u00e4mpf A. Schreinerarbeiten",
    "wof:placetype":"venue"
},
  "geometry": {"coordinates":[8.7804870605,47.3103752136],"type":"Point"}
}