{
  "type": "Feature",
  "properties": {
    "iso:country":"CH",
    "sg:address":"Via Giovan Battist Pioda 12",
    "sg:city":"Lugano",
    "sg:orig_category":"Sonstige pers\u00f6nliche Dienstleistungen",
    "sg:phone":"+41 31 869 44 03",
    "sg:postcode":"6900",
    "sg:province":"Ticino",
    "wof:name":"Lwd Zimmermann Ag",
    "wof:placetype":"venue"
},
  "geometry": {"coordinates":[7.4566159248,47.0306739807],"type":"Point"}
}