{
  "type": "Feature",
  "properties": {
    "iso:country":"CH",
    "sg:address":"Steinstrasse 16 8105 Regensdorf. Postfach",
    "sg:city":"Regensdorf",
    "sg:orig_category":"Herstellung von Konstruktionsteilen, Fertigbauteilen U Ausbauelementen aus Holz",
    "sg:postcode":"8105",
    "sg:province":"Z\u00fcrich",
    "wof:name":"Barlow Equipment And Service Techniques Windschutzscheiben; Reparatur Und Politur",
    "wof:placetype":"venue"
},
  "geometry": {"coordinates":[8.4620685577,47.4522094727],"type":"Point"}
}