{
  "type": "Feature",
  "properties": {
    "iso:country":"CH",
    "sg:address":"Hasli 265b",
    "sg:city":"Signau",
    "sg:orig_category":"Haltung von Gefl\u00fcgel",
    "sg:phone":"+41 32 396 27 40",
    "sg:postcode":"3534",
    "sg:province":"Bern",
    "wof:name":"Peter R\u00f6thlisberger Gefl\u00fcgelzucht",
    "wof:placetype":"venue"
},
  "geometry": {"coordinates":[7.195412159,47.0255126953],"type":"Point"}
}