{
  "type": "Feature",
  "properties": {
    "iso:country":"CH",
    "sg:address":"Avenue De Champel 28",
    "sg:city":"Gen\u00e8ve",
    "sg:classifiers":[
        {
            "category":"Restaurant",
            "type":"Food & Drink"
        }
    ],
    "sg:phone":"+41 22 346 33 56",
    "sg:postcode":"1206",
    "sg:province":"Gen\u00e8ve",
    "wof:name":"Caf\u00e9 Grand-bleu",
    "wof:placetype":"venue"
},
  "geometry": {"coordinates":[6.1528611183,46.1905822754],"type":"Point"}
}