{
  "type": "Feature",
  "properties": {
    "iso:country":"CH",
    "sg:address":"Bahnhofstrasse 134 Seewen Sz",
    "sg:city":"Schwyz",
    "sg:orig_category":"Detailhandel mit Computern U Software Reparatur von sonstigen Gebrauchsg\u00fctern",
    "sg:phone":"+41 41 811 00 40",
    "sg:postcode":"6430",
    "sg:province":"Schwyz",
    "wof:name":"It Support Gmbh Beratung - Verkauf - Support",
    "wof:placetype":"venue"
},
  "geometry": {"coordinates":[8.652429,47.021667],"type":"Point"}
}