{
  "type": "Feature",
  "properties": {
    "iso:country":"CH",
    "sg:address":"Sagiweg 218",
    "sg:city":"Moosleerau",
    "sg:orig_category":"Erschliessung von Grundst\u00fccken",
    "sg:postcode":"5054",
    "sg:province":"Aargau",
    "wof:name":"Hubag Immobiliengenossenschaft",
    "wof:placetype":"venue"
},
  "geometry": {"coordinates":[8.0651884079,47.2712249756],"type":"Point"}
}