{
  "type": "Feature",
  "properties": {
    "iso:country":"CH",
    "sg:address":"Bahnhofstrasse 11 6300 Zug. Postfach",
    "sg:city":"Zug",
    "sg:orig_category":"Mineral\u00f6lverarbeitung",
    "sg:postcode":"6300",
    "sg:province":"Zug",
    "wof:name":"Corund Trading Ltd Mineral\u00f6le U. -produkte; Handel, Vermittlung. Beratung Usw",
    "wof:placetype":"venue"
},
  "geometry": {"coordinates":[8.5155363083,47.1688194275],"type":"Point"}
}