{
  "type": "Feature",
  "properties": {
    "iso:country":"CH",
    "sg:address":"Speerstrasse 7 8942 Oberrieden. Postfach",
    "sg:city":"Oberrieden",
    "sg:orig_category":"Mit dem Versicherungsgewerbe verbundene T\u00e4tigkeiten Versicherungsagenturen and -broker",
    "sg:phone":"+41 56 619 71 11",
    "sg:postcode":"8942",
    "sg:province":"Z\u00fcrich",
    "wof:name":"Baumgartner + Co Gmbh Versicherungen + Finanzen",
    "wof:placetype":"venue"
},
  "geometry": {"coordinates":[8.2953624725,47.377532959],"type":"Point"}
}