{
  "type": "Feature",
  "properties": {
    "iso:country":"CH",
    "sg:address":"Riedm\u00fchlestrasse 1 8305 Dietlikon. Postfach",
    "sg:city":"Dietlikon",
    "sg:orig_category":"Reiseb\u00fcros U Reiseveranstalter",
    "sg:postcode":"8305",
    "sg:province":"Z\u00fcrich",
    "wof:name":"Travelsupport Keller & Partner",
    "wof:placetype":"venue"
},
  "geometry": {"coordinates":[8.6192922592,47.4270210266],"type":"Point"}
}