{
  "type": "Feature",
  "properties": {
    "iso:country":"CH",
    "sg:address":"Hauptstr.",
    "sg:city":"Reichenburg",
    "sg:orig_category":"Instandhaltung U Reparatur von Automobilen",
    "sg:postcode":"8864",
    "sg:province":"Schwyz",
    "wof:name":"M\u00fcller Albert Garage.",
    "wof:placetype":"venue"
},
  "geometry": {"coordinates":[8.974697113,47.1703109741],"type":"Point"}
}