{
  "type": "Feature",
  "properties": {
    "addr:full":"Pfrundmatte Lauterbrunnen Bern 3822",
    "addr:postcode":"3822",
    "addr:street":"Lauterbrunnen",
    "iso:country":"CH",
    "sg:address":"Pfrundmatte",
    "sg:city":"Lauterbrunnen",
    "sg:orig_category":"Bauspenglerei Sanit\u00e4rinstallation U Spenglerei",
    "sg:phone":"+41 33 855 14 88",
    "sg:postcode":"3822",
    "sg:province":"Bern",
    "wof:name":"Karl Sigrist Spenglerei & Heizungen",
    "wof:placetype":"venue"
},
  "geometry": {"coordinates":[7.907424,46.591595],"type":"Point"}
}