{
  "type": "Feature",
  "properties": {
    "iso:country":"CH",
    "sg:address":"Friedmattstrasse 25",
    "sg:city":"Reiden",
    "sg:orig_category":"Zahnarztpraxen",
    "sg:phone":"+41 62 758 11 88",
    "sg:postcode":"6260",
    "sg:province":"Luzern",
    "wof:name":"Dres Med.dent.t.& W. Denninger Zahn\u00e4rzte",
    "wof:placetype":"venue"
},
  "geometry": {"coordinates":[7.9677381516,47.2457199097],"type":"Point"}
}