{
  "type": "Feature",
  "properties": {
    "iso:country":"CH",
    "sg:address":"Seetalstrasse 7",
    "sg:city":"Boniswil",
    "sg:orig_category":"RESTAURANTS: TEA-ROOMS",
    "sg:phone":"+41 62 777 11 24",
    "sg:postcode":"5706",
    "sg:province":"Aargau",
    "wof:name":"Rest. Bahnhof Wettstein P.",
    "wof:placetype":"venue"
},
  "geometry": {"coordinates":[8.1843929291,47.3173027039],"type":"Point"}
}