{
  "type": "Feature",
  "properties": {
    "iso:country":"CH",
    "sg:address":"1874",
    "sg:city":"Champ\u00e9ry",
    "sg:orig_category":"D\u00e4mmung gegen K\u00e4lte, W\u00e4rme, Schall U Ersch\u00fctterung Stukkateurgewerbe, Gipserei U Verputzerei",
    "sg:phone":"+41 24 479 30 30",
    "sg:postcode":"1874",
    "sg:province":"Valais",
    "wof:name":"Aqua Airsec Sa Ass\u00e8chement De B\u00e2timents",
    "wof:placetype":"venue"
},
  "geometry": {"coordinates":[6.8706860542,46.1794052124],"type":"Point"}
}