{
  "type": "Feature",
  "properties": {
    "addr:full":"Wangenstrasse 50 Bern Bern 3018",
    "addr:housenumber":"50",
    "addr:postcode":"3018",
    "addr:street":"Wangenstrasse",
    "iso:country":"CH",
    "sg:address":"Wangenstrasse 50",
    "sg:city":"Bern",
    "sg:classifiers":[
        {
            "category":"Banks & Credit Unions",
            "subcategory":"Investment Brokerage",
            "type":"Services"
        }
    ],
    "sg:phone":"+41 31 981 23 77",
    "sg:postcode":"3018",
    "sg:province":"Bern",
    "sg:tags":[
        "alarm",
        "ammonia",
        "system"
    ],
    "wof:name":"Mas Consulting Gmbh",
    "wof:placetype":"venue"
},
  "geometry": {"coordinates":[7.388529,46.935497],"type":"Point"}
}