{
  "type": "Feature",
  "properties": {
    "iso:country":"CH",
    "sg:address":"Eigerstrasse 12",
    "sg:city":"Bern",
    "sg:orig_category":"Organisationen der Wohlfahrtspflege",
    "sg:phone":"+41 31 302 02 55",
    "sg:postcode":"3007",
    "sg:province":"Bern",
    "wof:name":"Rehaswiss",
    "wof:placetype":"venue"
},
  "geometry": {"coordinates":[7.4324798584,46.9408035278],"type":"Point"}
}