{
  "type": "Feature",
  "properties": {
    "iso:country":"CH",
    "sg:address":"Via Lucomagno",
    "sg:city":"Dongio",
    "sg:classifiers":[
        {
            "category":"Restaurant",
            "type":"Food & Drink"
        }
    ],
    "sg:phone":"+41 91 795 15 82",
    "sg:postcode":"6715",
    "sg:province":"Ticino",
    "wof:name":"Ristorante Rodolfo",
    "wof:placetype":"venue"
},
  "geometry": {"coordinates":[8.8414697647,46.1437950134],"type":"Point"}
}