{
  "type": "Feature",
  "properties": {
    "iso:country":"CH",
    "sg:address":"Gerichtshausstrasse",
    "sg:city":"Glarus",
    "sg:orig_category":"Interessenvertretungen",
    "sg:phone":"+41 55 645 60 20",
    "sg:postcode":"8750",
    "sg:province":"Glarus",
    "wof:name":"Pro Senectute Glarus/f\u00fcr Das Alter",
    "wof:placetype":"venue"
},
  "geometry": {"coordinates":[9.0652999878,47.0410766602],"type":"Point"}
}