{
  "type": "Feature",
  "properties": {
    "iso:country":"CH",
    "sg:address":"Rishaldenweg 12a",
    "sg:city":"Rothrist",
    "sg:orig_category":"Zimmerei, Ingenieurholzbau",
    "sg:phone":"+41 62 794 44 43",
    "sg:postcode":"4852",
    "sg:province":"Aargau",
    "wof:name":"Kennag Holz & Furnier",
    "wof:placetype":"venue"
},
  "geometry": {"coordinates":[7.892334938,47.3118057251],"type":"Point"}
}