{
  "type": "Feature",
  "properties": {
    "iso:country":"CH",
    "sg:address":"Hochbergerstrasse 15",
    "sg:city":"Basel",
    "sg:orig_category":"Werbung",
    "sg:postcode":"4057",
    "sg:province":"Basel-Stadt",
    "wof:name":"Move Consultant Mosimann V\u00e9ronique",
    "wof:placetype":"venue"
},
  "geometry": {"coordinates":[6.9953799248,46.2966117859],"type":"Point"}
}