{
  "type": "Feature",
  "properties": {
    "iso:country":"CH",
    "sg:address":"Bibliothekg\u00e4sschen 3",
    "sg:city":"Bern",
    "sg:orig_category":"Detailhandel mit B\u00fcchern",
    "sg:phone":"+41 31 311 19 37",
    "sg:postcode":"3011",
    "sg:province":"Bern",
    "wof:name":"Erotica Ag Buchhandlung",
    "wof:placetype":"venue"
},
  "geometry": {"coordinates":[7.449332,46.947277],"type":"Point"}
}