{
  "type": "Feature",
  "properties": {
    "iso:country":"CH",
    "sg:address":"Rengglochstrasse 19 6012 Obernau. Postfach",
    "sg:city":"Obernau",
    "sg:orig_category":"Herstellung von M\u00f6beln verschiedener Art Sonstiger Grosshandel",
    "sg:phone":"+41 41 322 06 66",
    "sg:postcode":"6012",
    "sg:province":"Luzern",
    "wof:name":"Moebelle Gmbh",
    "wof:placetype":"venue"
},
  "geometry": {"coordinates":[8.255030632,47.0333824158],"type":"Point"}
}