{
  "type": "Feature",
  "properties": {
    "iso:country":"CH",
    "sg:address":"Rue Des Foug\u00e8res 21",
    "sg:city":"Conthey",
    "sg:orig_category":"Maler U Glasergewerbe Stukkateurgewerbe, Gipserei U Verputzerei",
    "sg:phone":"+41 79 232 08 78",
    "sg:postcode":"1964",
    "sg:province":"Valais",
    "wof:name":"Monnet Martial",
    "wof:placetype":"venue"
},
  "geometry": {"coordinates":[7.3020191193,46.2180786133],"type":"Point"}
}