{
  "type": "Feature",
  "properties": {
    "iso:country":"CH",
    "sg:address":"Gerbergasse 81",
    "sg:city":"Basel",
    "sg:orig_category":"RESTAURANTS: TEA-ROOMS",
    "sg:postcode":"4001",
    "sg:province":"Basel-Stadt",
    "wof:name":"Mangiantini Renzo.",
    "wof:placetype":"venue"
},
  "geometry": {"coordinates":[7.5160098076,46.9326095581],"type":"Point"}
}