{
  "type": "Feature",
  "properties": {
    "iso:country":"CH",
    "sg:address":"Terrassi\u00e8re Rue De La 48 1207 Gen\u00e8ve. Postfach",
    "sg:city":"Gen\u00e8ve",
    "sg:orig_category":"RESTAURANTS: TEA-ROOMS",
    "sg:postcode":"1207",
    "sg:province":"Gen\u00e8ve",
    "wof:name":"Negaty Hindi Guy Et Martine Caf\u00e9-restaurant Aux Trois Chaudrons",
    "wof:placetype":"venue"
},
  "geometry": {"coordinates":[6.1590099335,46.2005004883],"type":"Point"}
}