{
  "type": "Feature",
  "properties": {
    "iso:country":"CH",
    "sg:address":"Haldenweg 5",
    "sg:city":"L\u00f6hningen",
    "sg:orig_category":"Detailhandel mit elektrischen Haushalts-,Radio U Fernsehger\u00e4ten sowie Musikinstrumenten Elektroinsta",
    "sg:phone":"+41 52 685 35 55",
    "sg:postcode":"8224",
    "sg:province":"Schaffhausen",
    "wof:name":"W\u00e4ckerlin Hans",
    "wof:placetype":"venue"
},
  "geometry": {"coordinates":[8.5540781021,47.7040901184],"type":"Point"}
}