{
  "type": "Feature",
  "properties": {
    "iso:country":"CH",
    "sg:address":"Bruy\u00e8re Chemin De La 32",
    "sg:city":"Prangins",
    "sg:orig_category":"Hardwareberatung",
    "sg:phone":"+41 19408359",
    "sg:postcode":"1197",
    "sg:province":"Vaud",
    "wof:name":"Vanek Miroslav",
    "wof:placetype":"venue"
},
  "geometry": {"coordinates":[8.7395153046,47.2749900818],"type":"Point"}
}