{
  "type": "Feature",
  "properties": {
    "iso:country":"CH",
    "sg:address":"Nidaustrasse 47",
    "sg:city":"Biel/bienne",
    "sg:orig_category":"Detailhandel mit Haustieren U zoologischem Bedarf",
    "sg:phone":"+41 32 327 31 80",
    "sg:postcode":"2502",
    "sg:province":"Bern",
    "wof:name":"Qualipet Ag Haustierbedarfs-center Zoo Loeb",
    "wof:placetype":"venue"
},
  "geometry": {"coordinates":[7.2468338013,47.1375961304],"type":"Point"}
}