{
  "type": "Feature",
  "properties": {
    "iso:country":"CH",
    "sg:address":"Oeleweg 5",
    "sg:city":"Attiswil",
    "sg:orig_category":"Gartenbau",
    "sg:phone":"+41 32 637 16 82",
    "sg:postcode":"4536",
    "sg:province":"Bern",
    "wof:name":"Gebr.jonny & Ernst Gehriger G\u00e4rtnerei",
    "wof:placetype":"venue"
},
  "geometry": {"coordinates":[7.6131691933,47.2486915588],"type":"Point"}
}