{
  "type": "Feature",
  "properties": {
    "iso:country":"CH",
    "sg:address":"Wallisellenstrasse 9",
    "sg:city":"D\u00fcbendorf",
    "sg:classifiers":[
        {
            "category":"Restaurant",
            "type":"Food & Drink"
        }
    ],
    "sg:phone":"+41 41 610 26 25",
    "sg:postcode":"8600",
    "sg:province":"Z\u00fcrich",
    "wof:name":"Restaurant Zur Trotte",
    "wof:placetype":"venue"
},
  "geometry": {"coordinates":[8.3967208862,46.938583374],"type":"Point"}
}