{
  "type": "Feature",
  "properties": {
    "iso:country":"CH",
    "sg:address":"Kradolfstrasse 78",
    "sg:city":"Sulgen",
    "sg:orig_category":"Wirtschafts- and Arbeitgeberverb\u00e4nde",
    "sg:postcode":"8583",
    "sg:province":"Thurgau",
    "wof:name":"Schweizerischer Drechslermeisterverband",
    "wof:placetype":"venue"
},
  "geometry": {"coordinates":[9.1863622665,47.5357017517],"type":"Point"}
}