{
  "type": "Feature",
  "properties": {
    "iso:country":"CH",
    "sg:address":"Oberer Deutweg 26",
    "sg:city":"Winterthur",
    "sg:orig_category":"Blumen U Zierpflanzenbau",
    "sg:phone":"+41 56 622 12 02",
    "sg:postcode":"8400",
    "sg:province":"Z\u00fcrich",
    "wof:name":"Walter Gysin Ag",
    "wof:placetype":"venue"
},
  "geometry": {"coordinates":[8.274864,47.35289],"type":"Point"}
}