{
  "type": "Feature",
  "properties": {
    "iso:country":"CH",
    "sg:address":"Beim Bahnhof",
    "sg:city":"Nidfurn",
    "sg:classifiers":[
        {
            "category":"Home & Garden",
            "subcategory":"Home Furnishings",
            "type":"Retail Goods"
        }
    ],
    "sg:phone":"+41 55 644 40 80",
    "sg:postcode":"8772",
    "sg:province":"Glarus",
    "sg:tags":[
        "candle",
        "holder"
    ],
    "wof:name":"T\u00f6diplast Ag",
    "wof:placetype":"venue"
},
  "geometry": {"coordinates":[9.051894,46.984081],"type":"Point"}
}