{
  "type": "Feature",
  "properties": {
    "iso:country":"CH",
    "sg:address":"Rte De Xir\u00e8s 3971 Chermignon. Postfach",
    "sg:city":"Crans-sur-sierre",
    "sg:classifiers":[
        {
            "category":"Travel",
            "subcategory":"Hotels & Motels",
            "type":"Entertainment"
        }
    ],
    "sg:postcode":"3963",
    "sg:province":"Valais",
    "sg:tags":[
        "hotels",
        "mit",
        "restaurant"
    ],
    "wof:name":"Barras Ren\u00e9",
    "wof:placetype":"venue"
},
  "geometry": {"coordinates":[7.473965168,46.2884407043],"type":"Point"}
}