{
  "type": "Feature",
  "properties": {
    "iso:country":"CH",
    "sg:address":"Neugutstrasse 1",
    "sg:city":"Wallisellen",
    "sg:orig_category":"Zahnarztpraxen",
    "sg:phone":"+41 18300188",
    "sg:postcode":"8304",
    "sg:province":"Z\u00fcrich",
    "wof:name":"Dr. Med. Dent. Hans Gut Zahnarzt",
    "wof:placetype":"venue"
},
  "geometry": {"coordinates":[8.5928459167,47.4134368896],"type":"Point"}
}