{
  "type": "Feature",
  "properties": {
    "iso:country":"CH",
    "sg:address":"Eggstrasse 88",
    "sg:city":"R\u00fcschlikon",
    "sg:orig_category":"Grosshandel mit festen Brennstoffen U Mineral\u00f6lerzeugnissen",
    "sg:postcode":"8803",
    "sg:province":"Z\u00fcrich",
    "wof:name":"Oel-hunziker Ag",
    "wof:placetype":"venue"
},
  "geometry": {"coordinates":[8.5448608398,47.3027305603],"type":"Point"}
}