{
  "type": "Feature",
  "properties": {
    "addr:full":"Beauregard Avenue 12 Fribourg Fribourg 1700",
    "addr:housenumber":"12",
    "addr:postcode":"1700",
    "addr:street":"Beauregard Avenue",
    "iso:country":"CH",
    "sg:address":"Beauregard Avenue 12",
    "sg:city":"Fribourg",
    "sg:orig_category":"Binnenschiffahrt",
    "sg:postcode":"1700",
    "sg:province":"Fribourg",
    "wof:name":"Dca Services Sa",
    "wof:placetype":"venue"
},
  "geometry": {"coordinates":[7.147583,46.802029],"type":"Point"}
}