{
  "type": "Feature",
  "properties": {
    "iso:country":"CH",
    "sg:address":"Trischlistrasse 10 9400 Rorschach. Postfach",
    "sg:city":"Rorschach",
    "sg:orig_category":"Antennenbau Detailhandel mit Radio U Fernsehger\u00e4ten",
    "sg:phone":"+41 71 844 60 60",
    "sg:postcode":"9401",
    "sg:province":"St. Gallen",
    "wof:name":"Schefer Radio Ag Fernsehen & Antennenbau",
    "wof:placetype":"venue"
},
  "geometry": {"coordinates":[9.488722,47.478138],"type":"Point"}
}