{
  "type": "Feature",
  "properties": {
    "addr:full":"In Der Luberzen 1 Urdorf Z\u00fcrich 8902",
    "addr:housenumber":"1",
    "addr:postcode":"8902",
    "addr:street":"In Der Luberzen",
    "iso:country":"CH",
    "sg:address":"In Der Luberzen 1",
    "sg:city":"Urdorf",
    "sg:orig_category":"Buchf\u00fchrung Unternehmensberatung",
    "sg:phone":"+41 17358100",
    "sg:postcode":"8902",
    "sg:province":"Z\u00fcrich",
    "wof:name":"Bt&t Asset Management Ag",
    "wof:placetype":"venue"
},
  "geometry": {"coordinates":[8.418407,47.393238],"type":"Point"}
}