{
  "type": "Feature",
  "properties": {
    "iso:country":"CH",
    "sg:address":"Chemin Praz-buchilly 4",
    "sg:city":"Epalinges",
    "sg:orig_category":"Bauspenglerei Dachdeckerei",
    "sg:phone":"+41 21 784 19 33",
    "sg:postcode":"1066",
    "sg:province":"Vaud",
    "wof:name":"Roland Steindl Ferblanterie & Couverture",
    "wof:placetype":"venue"
},
  "geometry": {"coordinates":[6.670968,46.555347],"type":"Point"}
}