{
  "type": "Feature",
  "properties": {
    "iso:country":"CH",
    "sg:address":"Avenir Rue De L' 23",
    "sg:city":"Del\u00e9mont",
    "sg:orig_category":"Unclassifiable Establishments",
    "sg:postcode":"2800",
    "sg:province":"Jura",
    "wof:name":"Vinzgarden Paysagiste, Jungo V.",
    "wof:placetype":"venue"
},
  "geometry": {"coordinates":[6.6091198921,46.7431411743],"type":"Point"}
}