{
  "type": "Feature",
  "properties": {
    "iso:country":"CH",
    "sg:address":"Piazza Municipio",
    "sg:city":"Brissago",
    "sg:orig_category":"Reinigungsgewerbe",
    "sg:phone":"+41 27 722 00 23",
    "sg:postcode":"6614",
    "sg:province":"Ticino",
    "wof:name":"Besse R\u00e9my Et Florian Propri\u00e9taires-encaveurs",
    "wof:placetype":"venue"
},
  "geometry": {"coordinates":[7.0525197983,46.0899276733],"type":"Point"}
}