{
  "type": "Feature",
  "properties": {
    "iso:country":"CH",
    "sg:address":"Dorfstrasse 15",
    "sg:city":"Kappelen",
    "sg:orig_category":"Sonstige k\u00fcnstlerische U schriftstellerische T\u00e4tigkeiten U Darbietungen",
    "sg:phone":"+41 32 392 45 54",
    "sg:postcode":"3273",
    "sg:province":"Bern",
    "wof:name":"Willy Arn Ag Restaurierungen",
    "wof:placetype":"venue"
},
  "geometry": {"coordinates":[7.2629480362,47.0572814941],"type":"Point"}
}