{
  "type": "Feature",
  "properties": {
    "addr:full":"3954 Leukerbad Valais 3954",
    "addr:postcode":"3954;3954",
    "iso:country":"CH",
    "sg:address":"3954",
    "sg:city":"Leukerbad",
    "sg:orig_category":"Detailhandel an Verkaufsst\u00e4nden U auf M\u00e4rkten",
    "sg:postcode":"3954",
    "sg:province":"Valais",
    "wof:name":"Bazar, Bovet Marlis",
    "wof:placetype":"venue"
},
  "geometry": {"coordinates":[7.625326,46.375931],"type":"Point"}
}