{
  "type": "Feature",
  "properties": {
    "iso:country":"CH",
    "sg:address":"Aem\u00e4ttlistrasse 2",
    "sg:city":"Stans",
    "sg:orig_category":"Softwareentwicklung U beratung",
    "sg:phone":"+41 41 618 61 11",
    "sg:postcode":"6370",
    "sg:province":"Nidwalden",
    "wof:name":"Lis Nidwalden Ag",
    "wof:placetype":"venue"
},
  "geometry": {"coordinates":[8.3585557938,46.9624328613],"type":"Point"}
}