{
  "type": "Feature",
  "properties": {
    "iso:country":"CH",
    "sg:address":"Ischlagweg 19",
    "sg:city":"Reigoldswil",
    "sg:orig_category":"Erschliessung von Grundst\u00fccken",
    "sg:postcode":"4418",
    "sg:province":"Basel-Landschaft",
    "wof:name":"Wohnbaugenossenschaft Reigoldswil Und Umgebung",
    "wof:placetype":"venue"
},
  "geometry": {"coordinates":[7.6849122047,47.3977279663],"type":"Point"}
}