{
  "type": "Feature",
  "properties": {
    "addr:full":"Beundenfeldstrasse 51 Bern Bern 3013",
    "addr:housenumber":"51",
    "addr:postcode":"3013",
    "addr:street":"Beundenfeldstrasse",
    "iso:country":"CH",
    "sg:address":"Beundenfeldstrasse 51",
    "sg:city":"Bern",
    "sg:orig_category":"Arztpraxen",
    "sg:phone":"+41 31 331 00 92",
    "sg:postcode":"3013",
    "sg:province":"Bern",
    "wof:name":"Dr.med.guido P. Brun Del Re Spezialarzt Fmh",
    "wof:placetype":"venue"
},
  "geometry": {"coordinates":[7.4561,46.957771],"type":"Point"}
}