{
  "type": "Feature",
  "properties": {
    "iso:country":"CH",
    "sg:address":"Grundstrasse 18",
    "sg:city":"Rotkreuz",
    "sg:orig_category":"Detailhandel mit M\u00f6beln U Haushaltsgegenst\u00e4nden Detailhandel mit Textilien",
    "sg:postcode":"6343",
    "sg:province":"Zug",
    "wof:name":"Ab\u00e4cherli Teppiche, M\u00f6bel, Vorh\u00e4nge Ag",
    "wof:placetype":"venue"
},
  "geometry": {"coordinates":[8.4306993484,47.14610672],"type":"Point"}
}