{
  "type": "Feature",
  "properties": {
    "iso:country":"CH",
    "sg:address":"Z\u00fcrcherstrasse 11 4310 Rheinfelden. Postfach",
    "sg:city":"Rheinfelden",
    "sg:orig_category":"Herstellung von Drahtwaren",
    "sg:phone":"+41 55 442 24 82",
    "sg:postcode":"4310",
    "sg:province":"Aargau",
    "wof:name":"Josef Steiner Armierungen",
    "wof:placetype":"venue"
},
  "geometry": {"coordinates":[8.85297966,47.1889228821],"type":"Point"}
}