{
  "type": "Feature",
  "properties": {
    "iso:country":"CH",
    "sg:address":"Rue Saint-georges 3",
    "sg:city":"Sierre",
    "sg:orig_category":"Grosshandel mit chemischen Erzeugnissen",
    "sg:phone":"+41 27 455 66 93",
    "sg:postcode":"3960",
    "sg:province":"Valais",
    "wof:name":"Pronet Produits De Nettoyage",
    "wof:placetype":"venue"
},
  "geometry": {"coordinates":[7.5231847763,46.2913589478],"type":"Point"}
}