{
  "type": "Feature",
  "properties": {
    "iso:country":"CH",
    "sg:address":"Piazza Mesolcina 12",
    "sg:city":"Bellinzona",
    "sg:orig_category":"Zahnarztpraxen",
    "sg:phone":"+41 91 825 81 35",
    "sg:postcode":"6500",
    "sg:province":"Ticino",
    "wof:name":"Dott. Med. Dent. Reto Reali Dentista",
    "wof:placetype":"venue"
},
  "geometry": {"coordinates":[9.0270309448,46.1992340088],"type":"Point"}
}