{
  "type": "Feature",
  "properties": {
    "iso:country":"CH",
    "sg:address":"6340",
    "sg:city":"Sihlbrugg",
    "sg:orig_category":"Detailhandel mit Metallwaren, Anstrichmitteln, Glaswaren, Bau U Heimwerkerbedarf",
    "sg:phone":"+41 41 761 35 35",
    "sg:postcode":"6340",
    "sg:province":"Zug",
    "wof:name":"Mlten Management Ag",
    "wof:placetype":"venue"
},
  "geometry": {"coordinates":[8.5773696899,47.2177505493],"type":"Point"}
}