{
  "type": "Feature",
  "properties": {
    "iso:country":"CH",
    "sg:address":"Haus 674",
    "sg:city":"B\u00fclach",
    "sg:orig_category":"Druck ohne Zeitungsdruck Offsetdruck",
    "sg:phone":"+41 18610146",
    "sg:postcode":"8180",
    "sg:province":"Z\u00fcrich",
    "wof:name":"Markus Wobmann Color Service",
    "wof:placetype":"venue"
},
  "geometry": {"coordinates":[8.5410089493,47.5176849365],"type":"Point"}
}