{
  "type": "Feature",
  "properties": {
    "iso:country":"CH",
    "sg:address":"Bernetstrasse 9",
    "sg:city":"Bergdietikon",
    "sg:orig_category":"Sonstiger Fachdetailhandel mit Nahrungsmitteln, Getr\u00e4nken U Tabak in Verkaufsr\u00e4umen",
    "sg:phone":"+41 17434020",
    "sg:postcode":"8962",
    "sg:province":"Aargau",
    "wof:name":"Madal Bal Ag",
    "wof:placetype":"venue"
},
  "geometry": {"coordinates":[8.3866462708,47.3893852234],"type":"Point"}
}