{
  "type": "Feature",
  "properties": {
    "iso:country":"CH",
    "sg:address":"3280",
    "sg:city":"Meyriez",
    "sg:orig_category":"Interessenvertretungen",
    "sg:phone":"+41 26 672 51 39",
    "sg:postcode":"3280",
    "sg:province":"Fribourg",
    "wof:name":"Stiftung F\u00fcr Das Spital Des Seebezirks",
    "wof:placetype":"venue"
},
  "geometry": {"coordinates":[7.1084527969,46.9252319336],"type":"Point"}
}