{
  "type": "Feature",
  "properties": {
    "iso:country":"CH",
    "sg:address":"Bandwiesstrasse 4",
    "sg:city":"R\u00fcti",
    "sg:classifiers":[
        {
            "category":"Professional",
            "subcategory":"Advertising",
            "type":"Services"
        }
    ],
    "sg:phone":"+41 55 260 13 05",
    "sg:postcode":"8630",
    "sg:province":"Z\u00fcrich",
    "sg:tags":[
        "agency"
    ],
    "wof:name":"Ipb Gmbh",
    "wof:placetype":"venue"
},
  "geometry": {"coordinates":[8.84914,47.258751],"type":"Point"}
}