{
  "type": "Feature",
  "properties": {
    "iso:country":"CH",
    "sg:address":"Kappelestrasse 634",
    "sg:city":"Eschen",
    "sg:orig_category":"Patentverwertung",
    "sg:phone":"+41 75 373 83 93",
    "sg:postcode":"9492",
    "wof:name":"Riederer Hasler & Partner Patentanw\u00e4lte Ag",
    "wof:placetype":"venue"
},
  "geometry": {"coordinates":[9.5177497864,47.2124099731],"type":"Point"}
}