{
  "type": "Feature",
  "properties": {
    "iso:country":"CH",
    "sg:address":"Hofstatt",
    "sg:city":"Morschach",
    "sg:orig_category":"Kauf U Verkauf von Immobilien auf eigene Rechnung",
    "sg:postcode":"6443",
    "sg:province":"Schwyz",
    "wof:name":"R\u00fctliblick Ag",
    "wof:placetype":"venue"
},
  "geometry": {"coordinates":[8.6183691025,46.9815864563],"type":"Point"}
}