{
  "type": "Feature",
  "properties": {
    "iso:country":"CH",
    "sg:address":"Emmenweg 12",
    "sg:city":"Blauen",
    "sg:orig_category":"Bauschreinerei Herstellung von Konstruktionsteilen, Fertigbauteilen U Ausbauelementen aus Holz",
    "sg:phone":"+41 61 761 17 81",
    "sg:postcode":"4223",
    "sg:province":"Basel-Landschaft",
    "wof:name":"Franz Gebhardt Schreinerei",
    "wof:placetype":"venue"
},
  "geometry": {"coordinates":[7.515558,47.451363],"type":"Point"}
}