{
  "type": "Feature",
  "properties": {
    "iso:country":"CH",
    "sg:address":"Burstwiesenstr. 67",
    "sg:city":"N\u00e4nikon",
    "sg:orig_category":"Herstellung von sonstigen elektrischen Ausr\u00fcstungen",
    "sg:phone":"+41 79 443 00 40",
    "sg:postcode":"8606",
    "sg:province":"Z\u00fcrich",
    "wof:name":"Pa Systems Gmbh",
    "wof:placetype":"venue"
},
  "geometry": {"coordinates":[8.677529335,47.365234375],"type":"Point"}
}