{
  "type": "Feature",
  "properties": {
    "addr:full":"Boulevard De Saint-georges 6 Gen\u00e8ve Gen\u00e8ve 1205",
    "addr:housenumber":"6",
    "addr:postcode":"1205",
    "addr:street":"Boulevard De Saint-Georges",
    "iso:country":"CH",
    "sg:address":"Boulevard De Saint-georges 6",
    "sg:city":"Gen\u00e8ve",
    "sg:orig_category":"Allgemeiner Hoch U Tiefbau Stukkateurgewerbe, Gipserei U Verputzerei",
    "sg:phone":"+41 22 329 12 36",
    "sg:postcode":"1205",
    "sg:province":"Gen\u00e8ve",
    "wof:name":"J. Hell\u00e9 Soci\u00e9t\u00e9 Anonyme",
    "wof:placetype":"venue"
},
  "geometry": {"coordinates":[6.131152,46.201168],"type":"Point"}
}