{
  "type": "Feature",
  "properties": {
    "iso:country":"CH",
    "sg:address":"3215",
    "sg:city":"Lurtigen",
    "sg:orig_category":"Maler U Glasergewerbe Malerei",
    "sg:phone":"+41 79 208 19 31",
    "sg:postcode":"3215",
    "sg:province":"Fribourg",
    "wof:name":"Morgenegg Fritz, Malergesch\u00e4ft",
    "wof:placetype":"venue"
},
  "geometry": {"coordinates":[7.181789875,46.934879303],"type":"Point"}
}