{
  "type": "Feature",
  "properties": {
    "iso:country":"CH",
    "sg:address":"Avenue Des Sports 11",
    "sg:city":"Yverdon",
    "sg:orig_category":"Chemicals and Pharmaceuticals Chemistry Health - equipments and instruments Precision Equipment",
    "sg:phone":"+41 21 921 26 31",
    "sg:postcode":"1400",
    "sg:province":"Vaud",
    "wof:name":"Produits Dentaires Sa",
    "wof:placetype":"venue"
},
  "geometry": {"coordinates":[6.84562,46.465191],"type":"Point"}
}