{
  "type": "Feature",
  "properties": {
    "iso:country":"CH",
    "sg:address":"Baselstrasse 74",
    "sg:city":"Solothurn",
    "sg:orig_category":"Non-Classified Establishments",
    "sg:phone":"+41 32 622 66 66",
    "sg:postcode":"4500",
    "sg:province":"Solothurn",
    "wof:name":"Christine Stucki, Taxibetrieb",
    "wof:placetype":"venue"
},
  "geometry": {"coordinates":[7.5477747917,47.2139167786],"type":"Point"}
}