{
  "type": "Feature",
  "properties": {
    "addr:full":"3763 D\u00e4rstetten Bern 3763",
    "addr:housenumber":"3763",
    "addr:postcode":"3763",
    "addr:street":"Daerstetten Bern",
    "iso:country":"CH",
    "sg:address":"3763",
    "sg:city":"D\u00e4rstetten",
    "sg:orig_category":"Bau U Wohngenossenschaften",
    "sg:phone":"+41 33 733 10 34",
    "sg:postcode":"3763",
    "sg:province":"Bern",
    "wof:name":"Gen.f\u00fcr Landwirtschaftl.bauen",
    "wof:placetype":"venue"
},
  "geometry": {"coordinates":[7.44685,46.44915],"type":"Point"}
}