{
  "type": "Feature",
  "properties": {
    "iso:country":"CH",
    "sg:address":"V. Cantonale 18",
    "sg:city":"Stabio",
    "sg:classifiers":[
        {
            "category":"Wholesale",
            "subcategory":"Machinery & Supplies",
            "type":"Manufacturing & Wholesale Goods"
        }
    ],
    "sg:phone":"+41 91 647 44 45",
    "sg:postcode":"6855",
    "sg:province":"Ticino",
    "sg:tags":[
        "equipment",
        "equipement",
        "precision",
        "timekeeping"
    ],
    "wof:name":"Farone Sa",
    "wof:placetype":"venue"
},
  "geometry": {"coordinates":[8.9411401749,45.8490600586],"type":"Point"}
}