{
  "type": "Feature",
  "properties": {
    "addr:full":"L\u00e9cheretta Rue De La 17 Bulle Fribourg 1630",
    "addr:housenumber":"17",
    "addr:postcode":"1630",
    "addr:street":"Rue De La",
    "iso:country":"CH",
    "sg:address":"L\u00e9cheretta Rue De La 17",
    "sg:city":"Bulle",
    "sg:orig_category":"Bestattungswesen",
    "sg:phone":"+41 26 919 86 20",
    "sg:postcode":"1630",
    "sg:province":"Fribourg",
    "wof:name":"Pompes Fun\u00e8bres Ruffieux",
    "wof:placetype":"venue"
},
  "geometry": {"coordinates":[7.055756,46.619762],"type":"Point"}
}