{
  "type": "Feature",
  "properties": {
    "iso:country":"CH",
    "sg:address":"P\u00eacheurs Rue Des 8",
    "sg:city":"Yverdon-les-bains",
    "sg:orig_category":"Non-Classified Establishments",
    "sg:postcode":"1400",
    "sg:province":"Vaud",
    "wof:name":"Cabinet Infirmier En Psychiatrie Fabrizio Bagatella",
    "wof:placetype":"venue"
},
  "geometry": {"coordinates":[6.6447529793,46.7814865112],"type":"Point"}
}