{
  "type": "Feature",
  "properties": {
    "iso:country":"CH",
    "sg:address":"Feldeggstrasse 47",
    "sg:city":"K\u00f6niz",
    "sg:orig_category":"Grosshandel mit Getr\u00e4nken Grosshandel mit Wein U Spirituosen",
    "sg:phone":"+41 22 707 61 11",
    "sg:postcode":"3098",
    "sg:province":"Bern",
    "wof:name":"Sanamex Sa",
    "wof:placetype":"venue"
},
  "geometry": {"coordinates":[6.162735939,46.2028083801],"type":"Point"}
}