{
  "type": "Feature",
  "properties": {
    "iso:country":"CH",
    "sg:address":"Staz",
    "sg:city":"Schlarigna",
    "sg:orig_category":"Abwasserreinigung",
    "sg:phone":"+41 81 833 83 33",
    "sg:postcode":"7505",
    "sg:province":"Graubunden",
    "wof:name":"Kl\u00e4ranlage",
    "wof:placetype":"venue"
},
  "geometry": {"coordinates":[9.871455,46.49733],"type":"Point"}
}