{
  "type": "Feature",
  "properties": {
    "addr:full":"Vison Charrat Valais 1906",
    "addr:housenumber":"1906",
    "iso:country":"CH",
    "sg:address":"Vison",
    "sg:city":"Charrat",
    "sg:orig_category":"Allgemeiner Gartenbau Detailhandel mit Getr\u00e4nken",
    "sg:phone":"+41 79 301 36 22",
    "sg:postcode":"1906",
    "sg:province":"Valais",
    "wof:name":"Laccomoff",
    "wof:placetype":"venue"
},
  "geometry": {"coordinates":[7.13825,46.12508],"type":"Point"}
}