{
  "type": "Feature",
  "properties": {
    "iso:country":"CH",
    "sg:address":"Freilagerstrasse 1",
    "sg:city":"Z\u00fcrich",
    "sg:orig_category":"Chemische Reinigung Teppichreinigung",
    "sg:phone":"+41 71 923 12 12",
    "sg:postcode":"8047",
    "sg:province":"Z\u00fcrich",
    "wof:name":"Ag F\u00fcr Chemischreinigung",
    "wof:placetype":"venue"
},
  "geometry": {"coordinates":[9.037396,47.452118],"type":"Point"}
}