{
  "type": "Feature",
  "properties": {
    "iso:country":"CH",
    "sg:address":"Roggenfarstrasse 33",
    "sg:city":"Eglisau",
    "sg:orig_category":"Non-Classified Establishments",
    "sg:phone":"+41 18674603",
    "sg:postcode":"8193",
    "sg:province":"Z\u00fcrich",
    "wof:name":"Electronic Publishing Rieser Robert",
    "wof:placetype":"venue"
},
  "geometry": {"coordinates":[8.528380394,47.5709495544],"type":"Point"}
}