{
  "type": "Feature",
  "properties": {
    "iso:country":"CH",
    "sg:address":"Loretostrasse 19",
    "sg:city":"Lichtensteig",
    "sg:orig_category":"RESTAURANTS: TEA-ROOMS",
    "sg:phone":"+41 71 988 46 46",
    "sg:postcode":"9620",
    "sg:province":"St. Gallen",
    "wof:name":"Restaurant Braustube, Burth Annelore",
    "wof:placetype":"venue"
},
  "geometry": {"coordinates":[9.0855846405,47.3255844116],"type":"Point"}
}