{
  "type": "Feature",
  "properties": {
    "iso:country":"CH",
    "sg:address":"Avenue Juste-olivier 16",
    "sg:city":"Lausanne",
    "sg:orig_category":"Grosshandel mit pharmazeutischen Erzeugnissen Herstellung von medizinischen U chirurgischen Ger\u00e4ten ",
    "sg:phone":"+41 21 323 70 21",
    "sg:postcode":"1006",
    "sg:province":"Vaud",
    "wof:name":"Medical Concepts Reall Ys S\u00e0rl",
    "wof:placetype":"venue"
},
  "geometry": {"coordinates":[6.6366758347,46.515296936],"type":"Point"}
}