{
  "type": "Feature",
  "properties": {
    "iso:country":"CH",
    "sg:address":"Le Sasselet",
    "sg:city":"Ligni\u00e8res",
    "sg:orig_category":"Grosshandel mit Textilien",
    "sg:phone":"+41 32 751 25 15",
    "sg:postcode":"2523",
    "sg:province":"Neuch\u00e2tel",
    "wof:name":"Valec Sa",
    "wof:placetype":"venue"
},
  "geometry": {"coordinates":[7.060090065,47.0870552063],"type":"Point"}
}