{
  "type": "Feature",
  "properties": {
    "iso:country":"CH",
    "sg:address":"3984",
    "sg:city":"Fiesch",
    "sg:orig_category":"Gewinnung von Kies U Sand",
    "sg:postcode":"3984",
    "sg:province":"Valais",
    "wof:name":"Imhasly Bodenmann & Wyden",
    "wof:placetype":"venue"
},
  "geometry": {"coordinates":[8.0610904694,46.4772415161],"type":"Point"}
}