{
  "type": "Feature",
  "properties": {
    "iso:country":"CH",
    "sg:address":"Greussweg 7",
    "sg:city":"M\u00f6rigen",
    "sg:orig_category":"Aktivit\u00e4ten der Generalunternehmen im Baugewerbe Vermietung U Verpachtung von eigenen Immobilien",
    "sg:phone":"+41 32 397 17 85",
    "sg:postcode":"2572",
    "sg:province":"Bern",
    "wof:name":"Euramas Ag",
    "wof:placetype":"venue"
},
  "geometry": {"coordinates":[7.206383,47.090736],"type":"Point"}
}