{
  "type": "Feature",
  "properties": {
    "iso:country":"CH",
    "sg:address":"Gerbergasse 66 4001 Basel. Postfach",
    "sg:city":"Basel",
    "sg:orig_category":"Detailhandel mit Lederwaren U Reiseartikeln Herstellung von Reiseartikeln, Leder U Sattlerwaren",
    "sg:phone":"+41 61 261 39 33",
    "sg:postcode":"4001",
    "sg:province":"Basel-Stadt",
    "wof:name":"Leder Locher Ag Basel Lederwaren Usw; Handel, Fabrikation",
    "wof:placetype":"venue"
},
  "geometry": {"coordinates":[7.5886378288,47.5553245544],"type":"Point"}
}