{
  "type": "Feature",
  "properties": {
    "addr:full":"Rue G. De Vergy 3 Cernier Neuch\u00e2tel 2053",
    "addr:housenumber":"3",
    "addr:postcode":"2053",
    "addr:street":"Rue G. De Vergy;Neucha\u0302Tel",
    "iso:country":"CH",
    "sg:address":"Rue G. De Vergy 3",
    "sg:city":"Cernier",
    "sg:orig_category":"Blumen U Zierpflanzenbau",
    "sg:phone":"+41 32 853 18 70",
    "sg:postcode":"2053",
    "sg:province":"Neuch\u00e2tel",
    "wof:name":"Francois Favre Jardinier-horticulteur",
    "wof:placetype":"venue"
},
  "geometry": {"coordinates":[6.899137,47.057571],"type":"Point"}
}