{
  "type": "Feature",
  "properties": {
    "iso:country":"CH",
    "sg:address":"Tonishofstrasse 21 6318 Walchwil. Postfach 16",
    "sg:city":"Walchwil",
    "sg:orig_category":"Torfgewinnung U brikettherstellung",
    "sg:phone":"+41 41 758 18 76",
    "sg:postcode":"6318",
    "sg:province":"Zug",
    "wof:name":"Nieth Robert Ag",
    "wof:placetype":"venue"
},
  "geometry": {"coordinates":[8.5182056427,47.1010169983],"type":"Point"}
}