{
  "type": "Feature",
  "properties": {
    "iso:country":"CH",
    "sg:address":"Rue Des Terreaux 13 1003 Lausanne Case Postale 2791",
    "sg:city":"Lausanne",
    "sg:orig_category":"Vermittlung von Immobilien Verwaltung von Immobilien",
    "sg:phone":"+41 21 321 26 10",
    "sg:postcode":"1002",
    "sg:province":"Vaud",
    "wof:name":"Fiduciaire Pragma Sa",
    "wof:placetype":"venue"
},
  "geometry": {"coordinates":[6.6282057762,46.5224723816],"type":"Point"}
}