{
  "type": "Feature",
  "properties": {
    "iso:country":"CH",
    "sg:address":"Dachlissen",
    "sg:city":"Mettmenstetten",
    "sg:orig_category":"Hoch U Tiefbau",
    "sg:phone":"+41 17617765",
    "sg:postcode":"8932",
    "sg:province":"Z\u00fcrich",
    "wof:name":"Hansulrich Spahr Baugesch\u00e4ft",
    "wof:placetype":"venue"
},
  "geometry": {"coordinates":[8.4681768417,47.2774810791],"type":"Point"}
}