{
  "type": "Feature",
  "properties": {
    "iso:country":"CH",
    "sg:address":"Kirchweg 64",
    "sg:city":"Glarus",
    "sg:classifiers":[
        {
            "category":"Restaurant",
            "type":"Food & Drink"
        }
    ],
    "sg:phone":"+41 55 640 11 56",
    "sg:postcode":"8750",
    "sg:province":"Glarus",
    "wof:name":"Restaurant National-saloon",
    "wof:placetype":"venue"
},
  "geometry": {"coordinates":[9.071387291,47.03723526],"type":"Point"}
}