{
  "type": "Feature",
  "properties": {
    "iso:country":"CH",
    "sg:address":"Cornat Rue Du 34a 2852 Court\u00e9telle. Postfach",
    "sg:city":"Court\u00e9telle",
    "sg:orig_category":"Herstellung von Konstruktionsteilen, Fertigbauteilen U Ausbauelementen aus Holz",
    "sg:postcode":"2852",
    "sg:province":"Jura",
    "wof:name":"Brunovska-fr\u00e9sard S\u00e0rl Menuiserie, \u00e9b\u00e9nisterie Et Agencements Etc",
    "wof:placetype":"venue"
},
  "geometry": {"coordinates":[7.3227081299,47.3392562866],"type":"Point"}
}