{
  "type": "Feature",
  "properties": {
    "iso:country":"CH",
    "sg:address":"Flurweg 2",
    "sg:city":"Uttigen",
    "sg:orig_category":"Sportvereine Eissport Eishockey",
    "sg:phone":"+41 31 781 10 41",
    "sg:postcode":"3628",
    "sg:province":"Bern",
    "wof:name":"Eishockey-club Uttigen",
    "wof:placetype":"venue"
},
  "geometry": {"coordinates":[7.5776200294,46.7928848267],"type":"Point"}
}