{
  "type": "Feature",
  "properties": {
    "iso:country":"CH",
    "sg:address":"Kirchgasse 49",
    "sg:city":"Flumenthal",
    "sg:orig_category":"Malerei",
    "sg:phone":"+41 79 632 16 92",
    "sg:postcode":"4534",
    "sg:province":"Solothurn",
    "wof:name":"Hans Wirth Malergesch\u00e4ft",
    "wof:placetype":"venue"
},
  "geometry": {"coordinates":[7.5991048813,47.2343177795],"type":"Point"}
}