{
  "type": "Feature",
  "properties": {
    "addr:full":"Calendariaweg 2 6405 Immensee. Postfach Immensee Schwyz 6405",
    "addr:housenumber":"2",
    "addr:postcode":"6405 immensee. postfach;6405",
    "addr:street":"Calendariaweg",
    "iso:country":"CH",
    "sg:address":"Calendariaweg 2 6405 Immensee. Postfach",
    "sg:city":"Immensee",
    "sg:orig_category":"Architektur U Ingenieurb\u00fcros",
    "sg:phone":"+41 31 370 30 30",
    "sg:postcode":"6405",
    "sg:province":"Schwyz",
    "wof:name":"Holinger Ag Ingenieurb\u00fcro",
    "wof:placetype":"venue"
},
  "geometry": {"coordinates":[7.426752,46.942924],"type":"Point"}
}