{
  "type": "Feature",
  "properties": {
    "iso:country":"CH",
    "sg:address":"Carrels 11g",
    "sg:city":"Peseux",
    "sg:orig_category":"Fachdetailhandel in Verkaufsr\u00e4umen",
    "sg:phone":"+41 32 731 19 78",
    "sg:postcode":"2034",
    "sg:province":"Neuch\u00e2tel",
    "wof:name":"La Plan\u00e8te Des Timbres, Yves Genoud",
    "wof:placetype":"venue"
},
  "geometry": {"coordinates":[6.8981790543,46.9893112183],"type":"Point"}
}