{
  "type": "Feature",
  "properties": {
    "iso:country":"CH",
    "sg:address":"Feldhofstrasse 2",
    "sg:city":"Uster",
    "sg:orig_category":"Tankstellen",
    "sg:phone":"+41 56 621 01 00",
    "sg:postcode":"8610",
    "sg:province":"Z\u00fcrich",
    "wof:name":"Fs-tankstelle H\u00fcbscher D.",
    "wof:placetype":"venue"
},
  "geometry": {"coordinates":[8.2703018188,47.3499259949],"type":"Point"}
}