{
  "type": "Feature",
  "properties": {
    "addr:full":"Wolfsb\u00f6hlstrasse 1 9050 Appenzell. Postfach Appenzell Appenzell Innerhoden 9050",
    "addr:housenumber":"1",
    "addr:postcode":"9050;9050",
    "addr:street":"Wolfsboehlstrasse",
    "iso:country":"CH",
    "sg:address":"Wolfsb\u00f6hlstrasse 1 9050 Appenzell. Postfach",
    "sg:city":"Appenzell",
    "sg:orig_category":"Ausbaugewerbe",
    "sg:phone":"+41 32 731 20 03",
    "sg:postcode":"9050",
    "sg:province":"Appenzell Innerhoden",
    "wof:name":"Marbrerie Des Deurres, Aldo Caldara",
    "wof:placetype":"venue"
},
  "geometry": {"coordinates":[6.898659,46.98711],"type":"Point"}
}