{
  "type": "Feature",
  "properties": {
    "iso:country":"CH",
    "sg:address":"Bleichistrasse 3a",
    "sg:city":"Rorschacherberg",
    "sg:orig_category":"Bauschreinerei Herstellung von M\u00f6beln verschiedener Art",
    "sg:phone":"+41 71 855 74 42",
    "sg:postcode":"9404",
    "sg:province":"St. Gallen",
    "wof:name":"Bruno B\u00fcttel",
    "wof:placetype":"venue"
},
  "geometry": {"coordinates":[9.490129,47.469383],"type":"Point"}
}