{
  "type": "Feature",
  "properties": {
    "iso:country":"CH",
    "sg:address":"Martinsbergstrasse 10 5400 Baden. Postfach",
    "sg:city":"Baden",
    "sg:orig_category":"Architektur U Ingenieurb\u00fcros",
    "sg:postcode":"5400",
    "sg:province":"Aargau",
    "wof:name":"Araseki Architekten Ag",
    "wof:placetype":"venue"
},
  "geometry": {"coordinates":[8.304262,47.474735],"type":"Point"}
}