{
  "type": "Feature",
  "properties": {
    "iso:country":"CH",
    "sg:address":"Chemin Du Pr\u00e9-salomon 25",
    "sg:city":"Satigny",
    "sg:orig_category":"G\u00fcterbef\u00f6rderung im Strassenverkehr",
    "sg:phone":"+41 22 341 58 00",
    "sg:postcode":"1242",
    "sg:province":"Gen\u00e8ve",
    "wof:name":"Tmc Transports-multibennes-camions",
    "wof:placetype":"venue"
},
  "geometry": {"coordinates":[6.062939167,46.1960639954],"type":"Point"}
}