{
  "type": "Feature",
  "properties": {
    "iso:country":"CH",
    "sg:address":"Hauptstrasse 21",
    "sg:city":"Muttenz",
    "sg:orig_category":"RESTAURANTS: TEA-ROOMS",
    "sg:phone":"+41 61 461 10 27",
    "sg:postcode":"4132",
    "sg:province":"Basel-Landschaft",
    "wof:name":"Restaurant Salmen C\u00f6l + Co",
    "wof:placetype":"venue"
},
  "geometry": {"coordinates":[7.6453680992,47.5235443115],"type":"Point"}
}