{
  "type": "Feature",
  "properties": {
    "iso:country":"CH",
    "sg:address":"Chemin De L'islettaz",
    "sg:city":"Penthalaz",
    "sg:orig_category":"Herstellung von Papier, Karton U Pappe Papier U Kartongewerbe",
    "sg:phone":"+41 21 863 10 63",
    "sg:postcode":"1305",
    "sg:province":"Vaud",
    "wof:name":"B & T Papiers Sa",
    "wof:placetype":"venue"
},
  "geometry": {"coordinates":[6.5224580765,46.6078414917],"type":"Point"}
}