{
  "type": "Feature",
  "properties": {
    "iso:country":"CH",
    "sg:address":"Moserstrasse 14",
    "sg:city":"Bern",
    "sg:orig_category":"Detailhandel mit M\u00f6beln Detailhandel mit Textilien",
    "sg:phone":"+41 71 333 23 72",
    "sg:postcode":"3014",
    "sg:province":"Bern",
    "wof:name":"Ernst Rechsteiner Innendekorationen",
    "wof:placetype":"venue"
},
  "geometry": {"coordinates":[9.3621683121,47.3862419128],"type":"Point"}
}