{
  "type": "Feature",
  "properties": {
    "iso:country":"CH",
    "sg:address":"Spisergasse 3",
    "sg:city":"St.gallen",
    "sg:orig_category":"Kauf U Verkauf von Immobilien auf eigene Rechnung",
    "sg:postcode":"9000",
    "sg:province":"St. Gallen",
    "wof:name":"Immobilien Ag Zum Weissen Widder",
    "wof:placetype":"venue"
},
  "geometry": {"coordinates":[7.5955381393,47.470413208],"type":"Point"}
}