{
  "type": "Feature",
  "properties": {
    "iso:country":"CH",
    "sg:address":"Chemin Des Pr\u00e9s-seigneurs 29",
    "sg:city":"Jussy",
    "sg:orig_category":"Nationale Postdienste",
    "sg:phone":"+41 22 759 14 91",
    "sg:postcode":"1254",
    "sg:province":"Gen\u00e8ve",
    "wof:name":"La Poste Suisse",
    "wof:placetype":"venue"
},
  "geometry": {"coordinates":[6.2669329643,46.2349510193],"type":"Point"}
}