{
  "type": "Feature",
  "properties": {
    "addr:full":"Vordere Hauptgasse 44 Zofingen Aargau 4800",
    "addr:housenumber":"44",
    "addr:postcode":"4800",
    "addr:street":"Vordere Hauptgasse",
    "iso:country":"CH",
    "sg:address":"Vordere Hauptgasse 44",
    "sg:city":"Zofingen",
    "sg:orig_category":"Detailhandel mit Bekleidung",
    "sg:phone":"+41 62 751 66 33",
    "sg:postcode":"4800",
    "sg:province":"Aargau",
    "wof:name":"Von D\u00e4niken Mode",
    "wof:placetype":"venue"
},
  "geometry": {"coordinates":[7.94428,47.289211],"type":"Point"}
}