{
  "type": "Feature",
  "properties": {
    "iso:country":"CH",
    "sg:address":"6916 Grancia Casella Postale 648",
    "sg:city":"Grancia",
    "sg:orig_category":"Grosshandel mit Holz U Baustoffen Verlegen von Fliesen U Platten",
    "sg:phone":"+41 91 994 81 21",
    "sg:postcode":"6916",
    "sg:province":"Ticino",
    "wof:name":"Valli P.l. Sa",
    "wof:placetype":"venue"
},
  "geometry": {"coordinates":[8.9250659943,45.9669761658],"type":"Point"}
}