{
  "type": "Feature",
  "properties": {
    "addr:full":"Wasenstrasse 39 Kreuzlingen Thurgau 8280",
    "addr:housenumber":"39",
    "addr:postcode":"8280",
    "addr:street":"Wasenstrasse",
    "iso:country":"CH",
    "sg:address":"Wasenstrasse 39",
    "sg:city":"Kreuzlingen",
    "sg:orig_category":"Blumen U Zierpflanzenbau",
    "sg:phone":"+41 71 688 17 75",
    "sg:postcode":"8280",
    "sg:province":"Thurgau",
    "wof:name":"G\u00e4rtnerei Maier Ag",
    "wof:placetype":"venue"
},
  "geometry": {"coordinates":[9.184288,47.646297],"type":"Point"}
}