{
  "type": "Feature",
  "properties": {
    "iso:country":"CH",
    "sg:address":"Via Cantonale 19 6900 Lugano. Postfach Caselle Postale 2913",
    "sg:city":"Lugano",
    "sg:orig_category":"Grosshandel mit Werkzeugmaschinen Herstellung von Werkzeugmaschinen",
    "sg:phone":"+41 91 922 25 22",
    "sg:postcode":"6901",
    "sg:province":"Ticino",
    "wof:name":"Scm Sa",
    "wof:placetype":"venue"
},
  "geometry": {"coordinates":[8.9502239227,46.0093307495],"type":"Point"}
}