{
  "type": "Feature",
  "properties": {
    "iso:country":"CH",
    "sg:address":"Poststrasse 9 9443 Widnau. Postfach",
    "sg:city":"Widnau",
    "sg:classifiers":[
        {
            "category":"Professional",
            "subcategory":"Employment Agencies",
            "type":"Services"
        }
    ],
    "sg:phone":"+41 71 913 99 99",
    "sg:postcode":"9443",
    "sg:province":"St. Gallen",
    "sg:tags":[
        "personal",
        "u",
        "stellenvermittlung"
    ],
    "wof:name":"Eupro Wil Ag",
    "wof:placetype":"venue"
},
  "geometry": {"coordinates":[9.0435724258,47.4622612],"type":"Point"}
}