{
  "type": "Feature",
  "properties": {
    "iso:country":"CH",
    "sg:address":"Poststrasse 1",
    "sg:city":"Killwangen",
    "sg:orig_category":"Mechanik",
    "sg:phone":"+41 56 401 19 19",
    "sg:postcode":"8956",
    "sg:province":"Aargau",
    "wof:name":"Ernst Suhner Ag",
    "wof:placetype":"venue"
},
  "geometry": {"coordinates":[8.354839325,47.4307899475],"type":"Point"}
}