{
  "type": "Feature",
  "properties": {
    "iso:country":"CH",
    "sg:address":"Gr\u00fcnau 4",
    "sg:city":"Lyss",
    "sg:orig_category":"Maurerarbeiten",
    "sg:phone":"+41 32 384 37 30",
    "sg:postcode":"3250",
    "sg:province":"Bern",
    "wof:name":"Bruno Burlet Maurergesch\u00e4ft",
    "wof:placetype":"venue"
},
  "geometry": {"coordinates":[7.3034858704,47.0769920349],"type":"Point"}
}