{
  "type": "Feature",
  "properties": {
    "addr:full":"Lindenweg 8 Schwadernau Bern 2556",
    "addr:housenumber":"8",
    "addr:postcode":"2556",
    "addr:street":"Lindenweg",
    "iso:country":"CH",
    "sg:address":"Lindenweg 8",
    "sg:city":"Schwadernau",
    "sg:orig_category":"Autogaragen",
    "sg:phone":"+41 32 373 48 40",
    "sg:postcode":"2556",
    "sg:province":"Bern",
    "wof:name":"Affolter Peter",
    "wof:placetype":"venue"
},
  "geometry": {"coordinates":[7.306458,47.128273],"type":"Point"}
}