{
  "type": "Feature",
  "properties": {
    "iso:country":"CH",
    "sg:address":"Taubenloch Chemin Du 4 Et 4a 2504 Biel/bienne. Postfach",
    "sg:city":"Biel/bienne",
    "sg:orig_category":"RESTAURANTS: TEA-ROOMS",
    "sg:postcode":"2504",
    "sg:province":"Bern",
    "wof:name":"Muths Ernest",
    "wof:placetype":"venue"
},
  "geometry": {"coordinates":[7.2761301994,47.1589012146],"type":"Point"}
}