{
  "type": "Feature",
  "properties": {
    "iso:country":"CH",
    "sg:address":"2027",
    "sg:city":"Fresens",
    "sg:orig_category":"Gemeindeverwaltungen",
    "sg:phone":"+41 32 835 18 00",
    "sg:postcode":"2027",
    "sg:province":"Neuch\u00e2tel",
    "wof:name":"Administration Communale De Fresens",
    "wof:placetype":"venue"
},
  "geometry": {"coordinates":[6.7465348244,46.8887023926],"type":"Point"}
}