{
  "type": "Feature",
  "properties": {
    "iso:country":"CH",
    "sg:address":"Eschenstrasse 3 6312 Steinhausen. Postfach",
    "sg:city":"Steinhausen",
    "sg:orig_category":"Kauf U Verkauf von Immobilien auf eigene Rechnung",
    "sg:postcode":"6312",
    "sg:province":"Zug",
    "wof:name":"Eupo Ag",
    "wof:placetype":"venue"
},
  "geometry": {"coordinates":[8.4906635284,47.196723938],"type":"Point"}
}