{
  "type": "Feature",
  "properties": {
    "iso:country":"CH",
    "sg:address":"M\u00e4rwiler Strasse 14",
    "sg:city":"Affeltrangen",
    "sg:orig_category":"Architektur U Ingenieurb\u00fcros",
    "sg:phone":"+41 71 919 00 55",
    "sg:postcode":"9556",
    "sg:province":"Thurgau",
    "wof:name":"Itk Planungen Acanski Notter & Partner",
    "wof:placetype":"venue"
},
  "geometry": {"coordinates":[9.032356,47.526714],"type":"Point"}
}