{
  "type": "Feature",
  "properties": {
    "addr:full":"Zinggentorstrasse 8 Luzern Luzern 6006",
    "addr:housenumber":"8",
    "addr:postcode":"6006",
    "addr:street":"Zinggentorstrasse",
    "iso:country":"CH",
    "sg:address":"Zinggentorstrasse 8",
    "sg:city":"Luzern",
    "sg:orig_category":"Advokaturb\u00fcros Notariate",
    "sg:phone":"+41 41 410 41 37",
    "sg:postcode":"6006",
    "sg:province":"Luzern",
    "wof:name":"Dr.walter Stutz Advokatur-& Notariatsb\u00fcro",
    "wof:placetype":"venue"
},
  "geometry": {"coordinates":[8.317879,47.055386],"type":"Point"}
}