{
  "type": "Feature",
  "properties": {
    "addr:full":"Rue Pierre-jolissaint 37 St-imier Bern 2610",
    "addr:housenumber":"37",
    "addr:postcode":"2610",
    "addr:street":"Rue Pierre-Jolissaint",
    "iso:country":"CH",
    "sg:address":"Rue Pierre-jolissaint 37",
    "sg:city":"St-imier",
    "sg:orig_category":"Bauingenieurb\u00fcros allgemein",
    "sg:phone":"+41 32 941 60 22",
    "sg:postcode":"2610",
    "sg:province":"Bern",
    "wof:name":"Gvh St-imier Sa Bureau D'ing\u00e9nieurs",
    "wof:placetype":"venue"
},
  "geometry": {"coordinates":[6.994483,47.152199],"type":"Point"}
}