{
  "type": "Feature",
  "properties": {
    "iso:country":"CH",
    "sg:address":"8598 Bottighofen. Postfach",
    "sg:city":"Bottighofen",
    "sg:orig_category":"Kauf U Verkauf von Immobilien auf eigene Rechnung",
    "sg:phone":"+41 71 680 01 11",
    "sg:postcode":"8598",
    "sg:province":"Thurgau",
    "wof:name":"Umb Untere M\u00fchle Bottighofen Ag",
    "wof:placetype":"venue"
},
  "geometry": {"coordinates":[9.2109098434,47.638420105],"type":"Point"}
}