{
  "type": "Feature",
  "properties": {
    "iso:country":"CH",
    "sg:address":"Grabenstrasse 2a 4805 Brittnau. Postfach 128",
    "sg:city":"Brittnau",
    "sg:orig_category":"Grosshandel mit Erzen U Metallen Herstellung von Konstruktionsteilen, Fertigbauteilen U Ausbauelemen",
    "sg:phone":"+41 79 211 55 01",
    "sg:postcode":"4805",
    "sg:province":"Aargau",
    "wof:name":"Meier Z\u00e4une",
    "wof:placetype":"venue"
},
  "geometry": {"coordinates":[7.9422941208,47.2586135864],"type":"Point"}
}