{
  "type": "Feature",
  "properties": {
    "iso:country":"CH",
    "sg:address":"Avenue Bergi\u00e8res 11-13",
    "sg:city":"Lausanne",
    "sg:orig_category":"Museen",
    "sg:phone":"+41 21 647 54 35",
    "sg:postcode":"1004",
    "sg:province":"Vaud",
    "wof:name":"Collection De L'art Brut Mus\u00e9e Du Ch\u00e2teau De Beaulieu",
    "wof:placetype":"venue"
},
  "geometry": {"coordinates":[6.6251029968,46.5273895264],"type":"Point"}
}