{
  "type": "Feature",
  "properties": {
    "iso:country":"CH",
    "sg:address":"Alte Bernstrasse 23",
    "sg:city":"Oberentfelden",
    "sg:orig_category":"G\u00fcterbef\u00f6rderung im Strassenverkehr",
    "sg:postcode":"5036",
    "sg:province":"Aargau",
    "wof:name":"Mto Metzger Transporte",
    "wof:placetype":"venue"
},
  "geometry": {"coordinates":[8.0433731079,47.3540611267],"type":"Point"}
}