{
  "type": "Feature",
  "properties": {
    "addr:full":"Chamerstrasse 79 6300 Zug. Postfach 3361 Zug Zug 6303",
    "addr:housenumber":"79",
    "addr:postcode":"6300;3361;6303",
    "addr:street":"Chamerstrasse;Postfach;Zug",
    "iso:country":"CH",
    "sg:address":"Chamerstrasse 79 6300 Zug. Postfach 3361",
    "sg:city":"Zug",
    "sg:orig_category":"Advokaturb\u00fcros Notariate",
    "sg:phone":"+41 41 711 78 36",
    "sg:postcode":"6303",
    "sg:province":"Zug",
    "wof:name":"Dr.erwin Lustenberger Advokatur-& Notariatsb\u00fcro",
    "wof:placetype":"venue"
},
  "geometry": {"coordinates":[8.499133,47.176517],"type":"Point"}
}