{
  "type": "Feature",
  "properties": {
    "iso:country":"CH",
    "sg:address":"Einkaufszentrum Tychboden",
    "sg:city":"Oftringen",
    "sg:orig_category":"RESTAURANTS: TEA-ROOMS",
    "sg:postcode":"4665",
    "sg:province":"Aargau",
    "wof:name":"Massimo Gastro Gmbh",
    "wof:placetype":"venue"
},
  "geometry": {"coordinates":[7.9209251404,47.3165397644],"type":"Point"}
}