{
  "type": "Feature",
  "properties": {
    "iso:country":"CH",
    "sg:address":"Appenzellerstrasse 44 9424 Rheineck. Postfach",
    "sg:city":"Rheineck",
    "sg:orig_category":"Elektroinstallation",
    "sg:postcode":"9424",
    "sg:province":"St. Gallen",
    "wof:name":"Elektro Br\u00fclisauer",
    "wof:placetype":"venue"
},
  "geometry": {"coordinates":[9.5870676041,47.4635887146],"type":"Point"}
}