{
  "type": "Feature",
  "properties": {
    "iso:country":"CH",
    "sg:address":"Bahnhofstrasse 38",
    "sg:city":"Kaiseraugst",
    "sg:classifiers":[
        {
            "category":"Travel",
            "subcategory":"Hotels & Motels",
            "type":"Entertainment"
        }
    ],
    "sg:phone":"+41 61 811 10 01",
    "sg:postcode":"4303",
    "sg:province":"Aargau",
    "sg:tags":[
        "hotels",
        "mit",
        "restaurant"
    ],
    "wof:name":"Hotel Bahnhof",
    "wof:placetype":"venue"
},
  "geometry": {"coordinates":[7.7246170044,47.5383605957],"type":"Point"}
}