{
  "type": "Feature",
  "properties": {
    "iso:country":"CH",
    "sg:address":"Gysnauweg 12 3400 Burgdorf. Postfach",
    "sg:city":"Burgdorf",
    "sg:orig_category":"Notariate",
    "sg:phone":"+41 34 422 20 66",
    "sg:postcode":"3401",
    "sg:province":"Bern",
    "wof:name":"Hans M\u00fchlethaler Notariatsb\u00fcro",
    "wof:placetype":"venue"
},
  "geometry": {"coordinates":[7.628464222,47.0597801208],"type":"Point"}
}