{
  "type": "Feature",
  "properties": {
    "iso:country":"CH",
    "sg:address":"Hofstettenstrasse 30 4112 B\u00e4ttwil-fl\u00fch. Postfach",
    "sg:city":"Fl\u00fch",
    "sg:orig_category":"Erschliessung von Grundst\u00fccken",
    "sg:postcode":"4112",
    "sg:province":"Solothurn",
    "wof:name":"Wohnbaugenossenschaft M\u00fchleweg Hofstetten-fl\u00fch",
    "wof:placetype":"venue"
},
  "geometry": {"coordinates":[7.5003180504,47.4832649231],"type":"Point"}
}