{
  "type": "Feature",
  "properties": {
    "iso:country":"CH",
    "sg:address":"Heitligstrasse 19",
    "sg:city":"Neerach",
    "sg:orig_category":"Kauf U Verkauf von Immobilien auf eigene Rechnung",
    "sg:postcode":"8173",
    "sg:province":"Z\u00fcrich",
    "wof:name":"West Ag",
    "wof:placetype":"venue"
},
  "geometry": {"coordinates":[8.4678287506,47.5117416382],"type":"Point"}
}