{
  "type": "Feature",
  "properties": {
    "iso:country":"CH",
    "sg:address":"Industriestrasse 42",
    "sg:city":"F\u00e4llanden",
    "sg:orig_category":"RESTAURANTS: TEA-ROOMS",
    "sg:postcode":"8117",
    "sg:province":"Z\u00fcrich",
    "wof:name":"Food Services Et Traiteurs Sa",
    "wof:placetype":"venue"
},
  "geometry": {"coordinates":[0.6580870152,46.1205368042],"type":"Point"}
}