{
  "type": "Feature",
  "properties": {
    "iso:country":"CH",
    "sg:address":"Haldimand Avenue 97",
    "sg:city":"Yverdon-les-bains",
    "sg:orig_category":"Unclassifiable Establishments",
    "sg:postcode":"1400",
    "sg:province":"Vaud",
    "wof:name":"Cari Syst\u00e8mes S\u00e0rl",
    "wof:placetype":"venue"
},
  "geometry": {"coordinates":[6.651157856,46.7780570984],"type":"Point"}
}