{
  "type": "Feature",
  "properties": {
    "iso:country":"CH",
    "sg:address":"March\u00e9 Place Du 6 1820 Montreux. Postfach",
    "sg:city":"Montreux",
    "sg:orig_category":"Detailhandel mit Bekleidung",
    "sg:postcode":"1820",
    "sg:province":"Vaud",
    "wof:name":"Montex S\u00e0rl Produits, Notamm. Dans Le Dom. De L'habillement, Des Bijoux, Etc.; Commerce, Distribution, Repr\u00e9sentation",
    "wof:placetype":"venue"
},
  "geometry": {"coordinates":[6.910506,46.431694],"type":"Point"}
}