{
  "type": "Feature",
  "properties": {
    "iso:country":"CH",
    "sg:address":"Route De La Gl\u00e2ne 7",
    "sg:city":"Fribourg",
    "sg:orig_category":"Vermietung U Verpachtung von eigenen Immobilien",
    "sg:postcode":"1700",
    "sg:province":"Fribourg",
    "wof:name":"Immocost Ag",
    "wof:placetype":"venue"
},
  "geometry": {"coordinates":[7.1459121704,46.7968826294],"type":"Point"}
}