{
  "type": "Feature",
  "properties": {
    "iso:country":"CH",
    "sg:address":"Corso San Gottardo 32",
    "sg:city":"Chiasso",
    "sg:orig_category":"Herstellung von Maschinen f\u00fcr die Nahrungsmittel, Getr\u00e4nkeherstellung U die Tabakverarbeitung",
    "sg:postcode":"6830",
    "sg:province":"Ticino",
    "wof:name":"Travinter Sa, Lussemburgo, Succursale Di Chiasso",
    "wof:placetype":"venue"
},
  "geometry": {"coordinates":[9.0298786163,45.8341331482],"type":"Point"}
}