{
  "type": "Feature",
  "properties": {
    "iso:country":"CH",
    "sg:address":"Hauptstrasse 21 4242 Laufen. Postfach 216",
    "sg:city":"Laufen",
    "sg:orig_category":"Detailhandel mit Uhren U Schmuck Reparatur von Uhren U Schmuck",
    "sg:phone":"+41 61 761 11 51",
    "sg:postcode":"4242",
    "sg:province":"Basel-Landschaft",
    "wof:name":"Roger Chalon Uhren/bijouterie",
    "wof:placetype":"venue"
},
  "geometry": {"coordinates":[7.5003662109,47.4219665527],"type":"Point"}
}