{
  "type": "Feature",
  "properties": {
    "iso:country":"CH",
    "sg:address":"Ob.binzberg",
    "sg:city":"R\u00fcegsau",
    "sg:orig_category":"Landw. Genossenschaften Dresch",
    "sg:phone":"+41 34 461 19 10",
    "sg:postcode":"3417",
    "sg:province":"Bern",
    "wof:name":"Ueli Stalder M\u00e4hdrescherei",
    "wof:placetype":"venue"
},
  "geometry": {"coordinates":[7.6760349274,47.0338134766],"type":"Point"}
}