{
  "type": "Feature",
  "properties": {
    "iso:country":"CH",
    "sg:address":"Martinsstrasse 13",
    "sg:city":"Galgenen",
    "sg:classifiers":[
        {
            "category":"Restaurant",
            "type":"Food & Drink"
        }
    ],
    "sg:phone":"+41 55 440 52 52",
    "sg:postcode":"8854",
    "sg:province":"Schwyz",
    "wof:name":"Restaurant Sternen",
    "wof:placetype":"venue"
},
  "geometry": {"coordinates":[8.8751811981,47.1810073853],"type":"Point"}
}