{
  "type": "Feature",
  "properties": {
    "iso:country":"CH",
    "sg:address":"Guschstrasse 60",
    "sg:city":"Uster",
    "sg:orig_category":"Herstellung von sonstigen Nahrungsmitteln Sonstiger Detailhandel mit Waren verschiedener Art, Hauptr",
    "sg:phone":"+41 19421220",
    "sg:postcode":"8610",
    "sg:province":"Z\u00fcrich",
    "wof:name":"Liechtboge-l\u00e4deli, Juon-moll Barbara",
    "wof:placetype":"venue"
},
  "geometry": {"coordinates":[8.7229747772,47.3454856873],"type":"Point"}
}