{
  "type": "Feature",
  "properties": {
    "iso:country":"CH",
    "sg:address":"Kirchstr. 6",
    "sg:city":"Attiswil",
    "sg:orig_category":"Mechanik",
    "sg:postcode":"4536",
    "sg:province":"Bern",
    "wof:name":"Oswald, Schlosserei / Metallbau",
    "wof:placetype":"venue"
},
  "geometry": {"coordinates":[9.0630140305,47.4692077637],"type":"Point"}
}