{
  "type": "Feature",
  "properties": {
    "iso:country":"CH",
    "sg:address":"Chemin De Bois-genoud 36",
    "sg:city":"Crissier",
    "sg:classifiers":[
        {
            "category":"Restaurant",
            "type":"Food & Drink"
        }
    ],
    "sg:phone":"+41 32 963 11 13",
    "sg:postcode":"1023",
    "sg:province":"Vaud",
    "wof:name":"Caf\u00e9 De Campagne",
    "wof:placetype":"venue"
},
  "geometry": {"coordinates":[6.926047802,47.12525177],"type":"Point"}
}