{
  "type": "Feature",
  "properties": {
    "iso:country":"CH",
    "sg:address":"M\u00fchlestrasse 1 5702 Niederlenz. Postfach 51",
    "sg:city":"Niederlenz",
    "sg:orig_category":"Fachdetailhandel mit pharmazeutischen Produkten",
    "sg:phone":"+41 800 300 001",
    "sg:postcode":"5702",
    "sg:province":"Aargau",
    "wof:name":"M\u00fcli Apotheke Ag",
    "wof:placetype":"venue"
},
  "geometry": {"coordinates":[8.175321579,47.4021148682],"type":"Point"}
}