{
  "type": "Feature",
  "properties": {
    "iso:country":"CH",
    "sg:address":"Br\u00fcnigstrasse 151",
    "sg:city":"Sarnen",
    "sg:classifiers":[
        {
            "category":"Travel",
            "subcategory":"Hotels & Motels",
            "type":"Entertainment"
        }
    ],
    "sg:phone":"+41 41 660 18 17",
    "sg:postcode":"6060",
    "sg:province":"Obwalden",
    "sg:tags":[
        "hotels",
        "mit",
        "restaurant"
    ],
    "wof:name":"Hotel Obwaldnerhof",
    "wof:placetype":"venue"
},
  "geometry": {"coordinates":[8.2461004257,46.8966789246],"type":"Point"}
}