{
  "type": "Feature",
  "properties": {
    "iso:country":"CH",
    "sg:address":"1936 Verbier Case Postale 419",
    "sg:city":"Verbier",
    "sg:orig_category":"Reiseb\u00fcros U Reiseveranstalter",
    "sg:phone":"+41 27 283 19 16",
    "sg:postcode":"1936",
    "sg:province":"Valais",
    "wof:name":"T\u00e9l\u00e9ski Du Tsat\u00e9 Blanchalpe Sa",
    "wof:placetype":"venue"
},
  "geometry": {"coordinates":[7.5164909363,46.0975532532],"type":"Point"}
}