{
  "type": "Feature",
  "properties": {
    "iso:country":"CH",
    "sg:address":"Oberer Aareweg 4",
    "sg:city":"Lyss",
    "sg:orig_category":"Electroformed Parts",
    "sg:phone":"+41 32 384 23 24",
    "sg:postcode":"3250",
    "sg:province":"Bern",
    "wof:name":"J\u00fcrg Nyfeler",
    "wof:placetype":"venue"
},
  "geometry": {"coordinates":[7.2980709076,47.0799407959],"type":"Point"}
}