{
  "type": "Feature",
  "properties": {
    "iso:country":"CH",
    "sg:address":"Via Sociale 4",
    "sg:city":"Losone",
    "sg:orig_category":"Non-Classified Establishments",
    "sg:postcode":"6616",
    "sg:province":"Ticino",
    "wof:name":"Famagra G. Fa\u00e8",
    "wof:placetype":"venue"
},
  "geometry": {"coordinates":[8.758102417,46.1681365967],"type":"Point"}
}