{
  "type": "Feature",
  "properties": {
    "iso:country":"CH",
    "sg:address":"Biberiststrasse 35",
    "sg:city":"Derendingen",
    "sg:orig_category":"Herstellung von sonstigen Maschinen f\u00fcr bestimmte Verwendung",
    "sg:phone":"+41 79 251 00 84",
    "sg:postcode":"4552",
    "sg:province":"Solothurn",
    "wof:name":"Fretz E. Ag",
    "wof:placetype":"venue"
},
  "geometry": {"coordinates":[7.5812039375,47.1865882874],"type":"Point"}
}