{
  "type": "Feature",
  "properties": {
    "iso:country":"CH",
    "sg:address":"4532",
    "sg:city":"Feldbrunnen",
    "sg:orig_category":"Unclassifiable Establishments",
    "sg:postcode":"4532",
    "sg:province":"Solothurn",
    "wof:name":"Legatax Holding Ag",
    "wof:placetype":"venue"
},
  "geometry": {"coordinates":[7.5509500504,47.2254295349],"type":"Point"}
}