{
  "type": "Feature",
  "properties": {
    "iso:country":"CH",
    "sg:address":"Mittelstrasse 38",
    "sg:city":"Langenthal",
    "sg:orig_category":"Instandhaltung U Reparatur von Automobilen",
    "sg:phone":"+41 62 922 75 55",
    "sg:postcode":"4900",
    "sg:province":"Bern",
    "wof:name":"Peter Bonani Garage",
    "wof:placetype":"venue"
},
  "geometry": {"coordinates":[7.7848038673,47.2058372498],"type":"Point"}
}