{
  "type": "Feature",
  "properties": {
    "iso:country":"CH",
    "sg:address":"Lehmattstrasse",
    "sg:city":"Zeglingen",
    "sg:orig_category":"S\u00e4gewerke",
    "sg:phone":"+41 61 981 21 36",
    "sg:postcode":"4495",
    "sg:province":"Basel-Landschaft",
    "wof:name":"Rickenbacher S\u00e4gerei Ag",
    "wof:placetype":"venue"
},
  "geometry": {"coordinates":[7.9075198174,47.4165534973],"type":"Point"}
}