{
  "type": "Feature",
  "properties": {
    "addr:full":"M\u00fchlegasse 15 8001 Z\u00fcrich. Postfach Z\u00fcrich Z\u00fcrich 8001",
    "addr:housenumber":"15",
    "addr:postcode":"8001 zuerich. postfach;8001",
    "addr:street":"Muehlegasse",
    "iso:country":"CH",
    "sg:address":"M\u00fchlegasse 15 8001 Z\u00fcrich. Postfach",
    "sg:city":"Z\u00fcrich",
    "sg:orig_category":"Detailhandel mit Bekleidung",
    "sg:phone":"+41 12513333",
    "sg:postcode":"8001",
    "sg:province":"Z\u00fcrich",
    "wof:name":"Just Call Me Susie, Inhaber Fehlmann D.",
    "wof:placetype":"venue"
},
  "geometry": {"coordinates":[8.544325,47.37429],"type":"Point"}
}