{
  "type": "Feature",
  "properties": {
    "iso:country":"CH",
    "sg:address":"Hauptstr. 90",
    "sg:city":"Reinach",
    "sg:classifiers":[
        {
            "category":"Transit Center",
            "subcategory":"Freight",
            "type":"Transportation"
        }
    ],
    "sg:phone":"+41 62 771 15 55",
    "sg:postcode":"5734",
    "sg:province":"Aargau",
    "sg:tags":[
        "metallurgy",
        "pipe",
        "metalworking",
        "sheet"
    ],
    "wof:name":"Fischer Reinach Ag",
    "wof:placetype":"venue"
},
  "geometry": {"coordinates":[8.1848106384,47.2477684021],"type":"Point"}
}