{
  "type": "Feature",
  "properties": {
    "iso:country":"CH",
    "sg:address":"Chesa Grusaida",
    "sg:city":"Zernez",
    "sg:orig_category":"Landesverteidigung, Zivilschutz",
    "sg:postcode":"7530",
    "sg:province":"Graubunden",
    "wof:name":"Foppa Ag",
    "wof:placetype":"venue"
},
  "geometry": {"coordinates":[10.0946302414,46.7002983093],"type":"Point"}
}