{
  "type": "Feature",
  "properties": {
    "iso:country":"CH",
    "sg:address":"Piazza C.stoppa",
    "sg:city":"Pedrinate",
    "sg:orig_category":"Detailhandel mit Waren verschiedener Art, Hauptrichtung Nahrungsmittel",
    "sg:phone":"+41 91 683 82 27",
    "sg:postcode":"6832",
    "sg:province":"Ticino",
    "wof:name":"Teresa Cairoli Coloniali",
    "wof:placetype":"venue"
},
  "geometry": {"coordinates":[9.0123806,45.8266983032],"type":"Point"}
}