{
  "type": "Feature",
  "properties": {
    "iso:country":"CH",
    "sg:address":"Dorfstrasse 10",
    "sg:city":"Waltenschwil",
    "sg:orig_category":"Maschinenbau Mechanische Werkst\u00e4tten",
    "sg:phone":"+41 79 404 88 85",
    "sg:postcode":"5622",
    "sg:province":"Aargau",
    "wof:name":"Peyer Fertigungstechnik Ag",
    "wof:placetype":"venue"
},
  "geometry": {"coordinates":[8.2792901993,47.3339195251],"type":"Point"}
}