{
  "type": "Feature",
  "properties": {
    "iso:country":"CH",
    "sg:address":"Schoosstrasse 7",
    "sg:city":"Rothenthurm",
    "sg:orig_category":"Unclassifiable Establishments",
    "sg:postcode":"6418",
    "sg:province":"Schwyz",
    "wof:name":"Swissflight - The Club",
    "wof:placetype":"venue"
},
  "geometry": {"coordinates":[8.6727619171,47.1016578674],"type":"Point"}
}