{
  "type": "Feature",
  "properties": {
    "iso:country":"CH",
    "sg:address":"T\u00f6ssfeldstrasse 2 8406 Winterthur. Postfach",
    "sg:city":"Winterthur",
    "sg:orig_category":"RESTAURANTS: TEA-ROOMS",
    "sg:postcode":"8406",
    "sg:province":"Z\u00fcrich",
    "wof:name":"Gastronomie Betriebe L\u00f6wen Gmbh",
    "wof:placetype":"venue"
},
  "geometry": {"coordinates":[9.6351919174,47.4310073853],"type":"Point"}
}