{
  "type": "Feature",
  "properties": {
    "iso:country":"CH",
    "sg:address":"Hirtenhofweg 2",
    "sg:city":"Luzern",
    "sg:orig_category":"Interessenvertretungen",
    "sg:postcode":"6005",
    "sg:province":"Luzern",
    "wof:name":"Stiftung Chorschule Des M\u00e4nnerchors Luzern",
    "wof:placetype":"venue"
},
  "geometry": {"coordinates":[8.3211927414,47.0368881226],"type":"Point"}
}