{
  "type": "Feature",
  "properties": {
    "iso:country":"CH",
    "sg:address":"Bachgraben",
    "sg:city":"Unterlangenegg",
    "sg:orig_category":"Gartenbau",
    "sg:phone":"+41 33 453 21 65",
    "sg:postcode":"3614",
    "sg:province":"Bern",
    "wof:name":"Stefan Kammermann G\u00e4rtnerei",
    "wof:placetype":"venue"
},
  "geometry": {"coordinates":[7.7005491257,46.8010292053],"type":"Point"}
}