{
  "type": "Feature",
  "properties": {
    "iso:country":"CH",
    "sg:address":"Grabenstrasse 14",
    "sg:city":"Zug",
    "sg:orig_category":"Unclassifiable Establishments",
    "sg:postcode":"6300",
    "sg:province":"Zug",
    "wof:name":"Monapax Ag",
    "wof:placetype":"venue"
},
  "geometry": {"coordinates":[8.5151357651,47.1657447815],"type":"Point"}
}