{
  "type": "Feature",
  "properties": {
    "iso:country":"CH",
    "sg:address":"Bahnhofstrasse 15 4552 Derendingen. Postfach",
    "sg:city":"Derendingen",
    "sg:orig_category":"Grosshandel mit elektrischen Haushaltsger\u00e4ten Herstellung von elektrischen Lampen U Leuchten",
    "sg:phone":"+41 22 301 03 60",
    "sg:postcode":"4552",
    "sg:province":"Solothurn",
    "wof:name":"Lumitech Sa",
    "wof:placetype":"venue"
},
  "geometry": {"coordinates":[6.1434750557,46.1856079102],"type":"Point"}
}