{
  "type": "Feature",
  "properties": {
    "iso:country":"CH",
    "sg:address":"Im Wyl 48",
    "sg:city":"Z\u00fcrich",
    "sg:orig_category":"Detailhandel mit M\u00f6beln U Haushaltsgegenst\u00e4nden Grosshandel mit M\u00f6beln, Wohnbedarf, Teppichen U Bode",
    "sg:phone":"+41 62 797 06 18",
    "sg:postcode":"8055",
    "sg:province":"Z\u00fcrich",
    "wof:name":"Handelsagentur Wullschleger Ren\u00e9",
    "wof:placetype":"venue"
},
  "geometry": {"coordinates":[8.5126399994,47.3681564331],"type":"Point"}
}