{
  "type": "Feature",
  "properties": {
    "addr:full":"Piazza Tarchini 67 Balerna Ticino 6828",
    "addr:housenumber":"67",
    "addr:postcode":"6828",
    "addr:street":"Piazza Tarchini",
    "iso:country":"CH",
    "sg:address":"Piazza Tarchini 67",
    "sg:city":"Balerna",
    "sg:orig_category":"Detailhandel mit B\u00fcchern Detailhandel mit B\u00fcchern, Zeitungen, Schreib U Papeteriewaren",
    "sg:phone":"+41 91 682 04 84",
    "sg:postcode":"6828",
    "sg:province":"Ticino",
    "wof:name":"Fant\u00e0sia Libreria Dei Bambini Maura & Christian Pagani",
    "wof:placetype":"venue"
},
  "geometry": {"coordinates":[8.99933,45.845619],"type":"Point"}
}