{
  "type": "Feature",
  "properties": {
    "iso:country":"CH",
    "sg:address":"Sihlbruggstrasse 109",
    "sg:city":"Baar",
    "sg:orig_category":"Unternehmensberatung",
    "sg:phone":"+41 79 400 38 92",
    "sg:postcode":"6340",
    "sg:province":"Zug",
    "wof:name":"Oec Oertli Consulting",
    "wof:placetype":"venue"
},
  "geometry": {"coordinates":[8.4524383545,47.3732681274],"type":"Point"}
}