{
  "type": "Feature",
  "properties": {
    "iso:country":"CH",
    "sg:address":"Schluchtbachstrasse 1",
    "sg:city":"Derendingen",
    "sg:orig_category":"Detailhandel mit Bekleidung Detailhandel mit Damenbekleidung",
    "sg:phone":"+41 62 824 83 55",
    "sg:postcode":"4552",
    "sg:province":"Solothurn",
    "wof:name":"Mode Figura Ag",
    "wof:placetype":"venue"
},
  "geometry": {"coordinates":[8.080012,47.401745],"type":"Point"}
}