{
  "type": "Feature",
  "properties": {
    "iso:country":"CH",
    "sg:address":"Aarauerstrasse 101 5015 Niedererlinsbach. Postfach 183",
    "sg:city":"Niedererlinsbach",
    "sg:orig_category":"Architektur U Ingenieurb\u00fcros",
    "sg:phone":"+41 62 844 35 62",
    "sg:postcode":"5015",
    "sg:province":"Solothurn",
    "wof:name":"Urs Moser Technisches B\u00fcro",
    "wof:placetype":"venue"
},
  "geometry": {"coordinates":[8.008854,47.397125],"type":"Point"}
}