{
  "type": "Feature",
  "properties": {
    "addr:full":"Forchstrasse 150 Zollikerberg Z\u00fcrich 8125",
    "addr:housenumber":"150",
    "addr:postcode":"8125",
    "addr:street":"Forchstrasse",
    "iso:country":"CH",
    "sg:address":"Forchstrasse 150",
    "sg:city":"Zollikerberg",
    "sg:orig_category":"Detailhandel mit Bekleidung",
    "sg:phone":"+41 13917677",
    "sg:postcode":"8125",
    "sg:province":"Z\u00fcrich",
    "wof:name":"Top-chic-shop M\u00e4rt Franz Feierabend",
    "wof:placetype":"venue"
},
  "geometry": {"coordinates":[8.598397,47.346893],"type":"Point"}
}