{
  "type": "Feature",
  "properties": {
    "addr:full":"Rue Des Creusets 21 Sion Valais 1950",
    "addr:housenumber":"21",
    "addr:postcode":"1950",
    "addr:street":"Rue Des Creusets",
    "iso:country":"CH",
    "sg:address":"Rue Des Creusets 21",
    "sg:city":"Sion",
    "sg:classifiers":[
        {
            "category":"Manufacturing",
            "subcategory":"Glass & Minerals",
            "type":"Manufacturing & Wholesale Goods"
        }
    ],
    "sg:phone":"+41 32 912 56 56",
    "sg:postcode":"1950",
    "sg:province":"Valais",
    "sg:tags":[
        "cleaning",
        "agent"
    ],
    "wof:name":"Stehlin Opticiens",
    "wof:placetype":"venue"
},
  "geometry": {"coordinates":[6.830017,47.102558],"type":"Point"}
}