{
  "type": "Feature",
  "properties": {
    "iso:country":"CH",
    "sg:address":"Bergstrasse 36",
    "sg:city":"Z\u00fcrich",
    "sg:classifiers":[
        {
            "category":"Professional",
            "subcategory":"Employment Agencies",
            "type":"Services"
        }
    ],
    "sg:postcode":"8044",
    "sg:province":"Z\u00fcrich",
    "sg:tags":[
        "personal",
        "u",
        "stellenvermittlung"
    ],
    "wof:name":"Bb Bau Und Bohr Ag Bau, Bohrarbeiten Im Hoch, Tiefbau Usw",
    "wof:placetype":"venue"
},
  "geometry": {"coordinates":[8.5610589981,47.3739242554],"type":"Point"}
}