{
  "type": "Feature",
  "properties": {
    "iso:country":"CH",
    "sg:address":"Selzachstrasse 1",
    "sg:city":"Lommiswil",
    "sg:classifiers":[
        {
            "category":"Banks & Credit Unions",
            "subcategory":"Bank",
            "type":"Services"
        }
    ],
    "sg:phone":"+41 4165612226",
    "sg:postcode":"4514",
    "sg:province":"Solothurn",
    "wof:name":"Raiffeisenbank Lommiswil",
    "wof:placetype":"venue"
},
  "geometry": {"coordinates":[7.471171,47.220676],"type":"Point"}
}