{
  "type": "Feature",
  "properties": {
    "iso:country":"CH",
    "sg:address":"Via Balestra 27 6900 Lugano Casella Postale",
    "sg:city":"Lugano",
    "sg:orig_category":"Mit dem Versicherungsgewerbe verbundene T\u00e4tigkeiten",
    "sg:phone":"+41 32 955 14 55",
    "sg:postcode":"6901",
    "sg:province":"Ticino",
    "wof:name":"Assidu Sa",
    "wof:placetype":"venue"
},
  "geometry": {"coordinates":[7.0464949608,47.2872161865],"type":"Point"}
}