{
  "type": "Feature",
  "properties": {
    "iso:country":"CH",
    "sg:address":"Fuchsronstrasse 36",
    "sg:city":"Galgenen",
    "sg:orig_category":"Sportvereine Ballsport Handball",
    "sg:phone":"+41 55 440 17 67",
    "sg:postcode":"8854",
    "sg:province":"Schwyz",
    "wof:name":"Sport Club Usw C/o Usw Beschl.",
    "wof:placetype":"venue"
},
  "geometry": {"coordinates":[8.8637485504,47.1771125793],"type":"Point"}
}