{
  "type": "Feature",
  "properties": {
    "iso:country":"CH",
    "sg:address":"Bergweg 5 3283 Kallnach. Postfach",
    "sg:city":"Kallnach",
    "sg:orig_category":"Erwachsenenbildung U Unterricht",
    "sg:phone":"+41 32 392 46 05",
    "sg:postcode":"3283",
    "sg:province":"Bern",
    "wof:name":"Abderhalden Vermittlung V. Sprachschulen Im Ausland.",
    "wof:placetype":"venue"
},
  "geometry": {"coordinates":[7.2344961166,47.0224609375],"type":"Point"}
}