{
  "type": "Feature",
  "properties": {
    "iso:country":"CH",
    "sg:address":"Dorfstrasse 128 5012 W\u00f6schnau. Postfach",
    "sg:city":"Eppenberg",
    "sg:orig_category":"Herstellung von Konstruktionsteilen, Fertigbauteilen U Ausbauelementen aus Holz",
    "sg:postcode":"5012",
    "sg:province":"Solothurn",
    "wof:name":"Rohner & Bas Servicetechnik Fenster, T\u00fcren, Zargen, Garagentore; Im, Export Und Handel",
    "wof:placetype":"venue"
},
  "geometry": {"coordinates":[8.0026493073,47.3721618652],"type":"Point"}
}