{
  "type": "Feature",
  "properties": {
    "iso:country":"CH",
    "sg:address":"Krebsweg 14",
    "sg:city":"Nidau",
    "sg:orig_category":"Non-Classified Establishments",
    "sg:postcode":"2560",
    "sg:province":"Bern",
    "wof:name":"Roni Data Gmbh.",
    "wof:placetype":"venue"
},
  "geometry": {"coordinates":[7.2464132309,47.1230010986],"type":"Point"}
}