{
  "type": "Feature",
  "properties": {
    "iso:country":"CH",
    "sg:address":"M\u00fchleweg 1",
    "sg:city":"Solothurn",
    "sg:classifiers":[
        {
            "category":"Social Services",
            "subcategory":"Retirement Home",
            "type":"Services"
        }
    ],
    "sg:phone":"+41 32 622 18 17",
    "sg:postcode":"4500",
    "sg:province":"Solothurn",
    "sg:tags":[
        "pflegeheime",
        "u",
        "alters"
    ],
    "wof:name":"Altersheim Riant-mont",
    "wof:placetype":"venue"
},
  "geometry": {"coordinates":[7.530574,47.215752],"type":"Point"}
}