{
  "type": "Feature",
  "properties": {
    "addr:full":"Wickenweg 19 Z\u00fcrich Z\u00fcrich 8048",
    "addr:housenumber":"19",
    "addr:postcode":"8048",
    "addr:street":"Wickenweg",
    "iso:country":"CH",
    "sg:address":"Wickenweg 19",
    "sg:city":"Z\u00fcrich",
    "sg:orig_category":"Architektur U Ingenieurb\u00fcros",
    "sg:phone":"+41 14314863",
    "sg:postcode":"8048",
    "sg:province":"Z\u00fcrich",
    "wof:name":"Ing.-b\u00fcro Rossi Guido Ingenieurb\u00fcro F\u00fcr Verfahrenstechnik",
    "wof:placetype":"venue"
},
  "geometry": {"coordinates":[8.481143,47.381599],"type":"Point"}
}