{
  "type": "Feature",
  "properties": {
    "iso:country":"CH",
    "sg:address":"Stadlerstrasse 181",
    "sg:city":"Stadel(winterthur)",
    "sg:orig_category":"Elektro- and elektronische Maschinen Grosshandel Sonstige mit der Informatik verbundene T\u00e4tigkeiten",
    "sg:postcode":"8404",
    "sg:province":"Z\u00fcrich",
    "wof:name":"Nahi Ag Elektrotechnische Beratung",
    "wof:placetype":"venue"
},
  "geometry": {"coordinates":[8.7608194351,47.5338439941],"type":"Point"}
}