{
  "type": "Feature",
  "properties": {
    "iso:country":"CH",
    "sg:address":"Zwillikerstrasse 9",
    "sg:city":"Hedingen",
    "sg:orig_category":"RESTAURANTS: TEA-ROOMS",
    "sg:phone":"+41 17616356",
    "sg:postcode":"8908",
    "sg:province":"Z\u00fcrich",
    "wof:name":"Restaurant Post, Hedingen, Arnold Peter + B\u00fchrer Yvonne",
    "wof:placetype":"venue"
},
  "geometry": {"coordinates":[8.4469041824,47.2976570129],"type":"Point"}
}