{
  "type": "Feature",
  "properties": {
    "iso:country":"CH",
    "sg:address":"Les Planches 1041 Bottens Case Postale 38",
    "sg:city":"Bottens",
    "sg:orig_category":"Maurerarbeiten Sonstiger spezialisierter Hoch U Tiefbau",
    "sg:phone":"+41 21 881 29 70",
    "sg:postcode":"1041",
    "sg:province":"Vaud",
    "wof:name":"Schmalz Patrick",
    "wof:placetype":"venue"
},
  "geometry": {"coordinates":[6.6633448601,46.6148605347],"type":"Point"}
}