{
  "type": "Feature",
  "properties": {
    "iso:country":"CH",
    "sg:address":"G\u00fcterstrasse 144",
    "sg:city":"Basel",
    "sg:orig_category":"Einbau von Schreinerwaren Grosshandel mit M\u00f6beln, Wohnbedarf, Teppichen U Bodenbel\u00e4gen",
    "sg:phone":"+41 61 366 90 90",
    "sg:postcode":"4053",
    "sg:province":"Basel-Stadt",
    "wof:name":"Bruno Piatti Ag K\u00fcchenbau",
    "wof:placetype":"venue"
},
  "geometry": {"coordinates":[7.5895190239,47.5446014404],"type":"Point"}
}