{
  "type": "Feature",
  "properties": {
    "iso:country":"CH",
    "sg:address":"3954",
    "sg:city":"Leukerbad",
    "sg:orig_category":"Vorschulen, Kinderg\u00e4rten",
    "sg:phone":"+41 27 473 31 02",
    "sg:postcode":"3954",
    "sg:province":"Valais",
    "wof:name":"Kindergarten",
    "wof:placetype":"venue"
},
  "geometry": {"coordinates":[7.6253261566,46.3759307861],"type":"Point"}
}