{
  "type": "Feature",
  "properties": {
    "iso:country":"CH",
    "sg:address":"Hessstrasse 27a 3097 Liebefeld. Postfach",
    "sg:city":"Liebefeld",
    "sg:orig_category":"Detailhandel mit Musikinstrumenten Erwachsenenbildung U Unterricht",
    "sg:phone":"+41 31 971 26 24",
    "sg:postcode":"3097",
    "sg:province":"Bern",
    "wof:name":"Drum & Percussion-studio, Ren\u00e9 Diggelmann & Doris Jossen",
    "wof:placetype":"venue"
},
  "geometry": {"coordinates":[7.4255328178,46.9313735962],"type":"Point"}
}