{
  "type": "Feature",
  "properties": {
    "iso:country":"CH",
    "sg:address":"6466",
    "sg:city":"Bauen",
    "sg:classifiers":[
        {
            "category":"Travel",
            "subcategory":"Hotels & Motels",
            "type":"Entertainment"
        }
    ],
    "sg:phone":"+41 41 878 11 55",
    "sg:postcode":"6466",
    "sg:province":"Uri",
    "sg:tags":[
        "hotels",
        "mit",
        "restaurant"
    ],
    "wof:name":"Hotel Schiller",
    "wof:placetype":"venue"
},
  "geometry": {"coordinates":[8.5792150497,46.934551239],"type":"Point"}
}