{
  "type": "Feature",
  "properties": {
    "iso:country":"CH",
    "sg:address":"Neuensteigstrasse 9 9424 Rheineck. Postfach",
    "sg:city":"Rheineck",
    "sg:orig_category":"Grosshandel mit pharmazeutischen Erzeugnissen, medizinischen U orthop\u00e4dischen Artikeln Grosshandel m",
    "sg:phone":"+41 71 888 33 44",
    "sg:postcode":"9424",
    "sg:province":"St. Gallen",
    "wof:name":"Veronika Liebherr Spital-& Industriebedarf",
    "wof:placetype":"venue"
},
  "geometry": {"coordinates":[9.589802742,47.4621772766],"type":"Point"}
}