{
  "type": "Feature",
  "properties": {
    "iso:country":"CH",
    "sg:address":"Via Alla Chiesa 1",
    "sg:city":"Viganello",
    "sg:orig_category":"Detailhandel mit Uhren U Schmuck Reparatur von Uhren U Schmuck",
    "sg:phone":"+41 32 322 32 66",
    "sg:postcode":"6962",
    "sg:province":"Ticino",
    "wof:name":"J.-b. Ryser Bijouterie Uhren",
    "wof:placetype":"venue"
},
  "geometry": {"coordinates":[7.2459359169,47.1404190063],"type":"Point"}
}