{
  "type": "Feature",
  "properties": {
    "iso:country":"CH",
    "sg:address":"Rue Saint-henri 10",
    "sg:city":"Del\u00e9mont",
    "sg:orig_category":"Giessereiindustrie Herstellung von Metallerzeugnissen ohne Maschinenbau",
    "sg:phone":"+41 32 422 50 71",
    "sg:postcode":"2800",
    "sg:province":"Jura",
    "wof:name":"Imhof Henri Et Fils Sa",
    "wof:placetype":"venue"
},
  "geometry": {"coordinates":[7.339381218,47.351940155],"type":"Point"}
}