{
  "type": "Feature",
  "properties": {
    "iso:country":"CH",
    "sg:address":"Baarerstrasse 16 6300 Zug. Postfach 4539",
    "sg:city":"Zug",
    "sg:orig_category":"Herstellung von Automobilen Herstellung von elektronischen Bauelementen",
    "sg:phone":"+41 41 725 27 40",
    "sg:postcode":"6304",
    "sg:province":"Zug",
    "wof:name":"Latco Ag",
    "wof:placetype":"venue"
},
  "geometry": {"coordinates":[8.5167160034,47.1723556519],"type":"Point"}
}