{
  "type": "Feature",
  "properties": {
    "iso:country":"CH",
    "sg:address":"6964",
    "sg:city":"Davesco-soragno",
    "sg:orig_category":"Sportvereine Eissport Eishockey",
    "sg:phone":"+41 81 833 07 92",
    "sg:postcode":"6964",
    "sg:province":"Ticino",
    "wof:name":"Hockey-club Poschiavo",
    "wof:placetype":"venue"
},
  "geometry": {"coordinates":[9.8361949921,46.4871101379],"type":"Point"}
}