{
  "type": "Feature",
  "properties": {
    "iso:country":"CH",
    "sg:address":"Spalenring 72 4055 Basel. Postfach 379",
    "sg:city":"Basel",
    "sg:orig_category":"Personal U Stellenvermittlung Unternehmensberatung",
    "sg:phone":"+41 52 318 19 29",
    "sg:postcode":"4009",
    "sg:province":"Basel-Stadt",
    "wof:name":"Scheidegger & Partner Personal Und Unternehmensberatung",
    "wof:placetype":"venue"
},
  "geometry": {"coordinates":[8.6215896606,47.5495223999],"type":"Point"}
}