{
  "type": "Feature",
  "properties": {
    "iso:country":"CH",
    "sg:address":"Salzhausstrasse 5 - 7",
    "sg:city":"Biel/bienne",
    "sg:orig_category":"Dienstleistungen, Sonstige Dienstleistungen",
    "sg:phone":"+41 32 322 01 88",
    "sg:postcode":"2503",
    "sg:province":"Bern",
    "wof:name":"Teutschmann Rene",
    "wof:placetype":"venue"
},
  "geometry": {"coordinates":[7.241589,47.128628],"type":"Point"}
}