{
  "type": "Feature",
  "properties": {
    "iso:country":"CH",
    "sg:address":"Gumpenwiesenstrasse 25",
    "sg:city":"Dielsdorf",
    "sg:orig_category":"Markt U Meinungsforschung",
    "sg:phone":"+41 18531717",
    "sg:postcode":"8157",
    "sg:province":"Z\u00fcrich",
    "wof:name":"Zimmermann Consulting",
    "wof:placetype":"venue"
},
  "geometry": {"coordinates":[8.4569349289,47.4766654968],"type":"Point"}
}