{
  "type": "Feature",
  "properties": {
    "iso:country":"CH",
    "sg:address":"Av. Eug\u00e8ne-lance 72",
    "sg:city":"Grand-lancy",
    "sg:orig_category":"Interessenvertretungen",
    "sg:postcode":"1212",
    "sg:province":"Gen\u00e8ve",
    "wof:name":"Acquanav Organisation",
    "wof:placetype":"venue"
},
  "geometry": {"coordinates":[6.1268029213,46.1746864319],"type":"Point"}
}