{
  "type": "Feature",
  "properties": {
    "iso:country":"CH",
    "sg:address":"Ponte Cremenaga 6998 Termine. Postfach",
    "sg:city":"Termine",
    "sg:orig_category":"Fachdetailhandel in Verkaufsr\u00e4umen",
    "sg:postcode":"6998",
    "sg:province":"Ticino",
    "wof:name":"Golden B Sa",
    "wof:placetype":"venue"
},
  "geometry": {"coordinates":[8.8026599884,45.9980583191],"type":"Point"}
}