{
  "type": "Feature",
  "properties": {
    "iso:country":"CH",
    "sg:address":"Talmoosstrasse 11",
    "sg:city":"Ittigen",
    "sg:orig_category":"Detailhandel mit M\u00f6beln U Haushaltsgegenst\u00e4nden",
    "sg:postcode":"3063",
    "sg:province":"Bern",
    "wof:name":"Mema Meng & Co",
    "wof:placetype":"venue"
},
  "geometry": {"coordinates":[7.4816331863,46.9790115356],"type":"Point"}
}