{
  "type": "Feature",
  "properties": {
    "addr:full":"Oltnerstrasse 14 Sch\u00f6nenwerd Solothurn 5012",
    "addr:housenumber":"14",
    "addr:postcode":"5012",
    "addr:street":"Oltnerstrasse;Schoenenwerd Solothurn",
    "iso:country":"CH",
    "sg:address":"Oltnerstrasse 14",
    "sg:city":"Sch\u00f6nenwerd",
    "sg:orig_category":"Datenverarbeitungsdienste",
    "sg:phone":"+41 62 849 59 55",
    "sg:postcode":"5012",
    "sg:province":"Solothurn",
    "wof:name":"Kurt Zulauf Edv-beratung",
    "wof:placetype":"venue"
},
  "geometry": {"coordinates":[8.002089,47.371529],"type":"Point"}
}