{
  "type": "Feature",
  "properties": {
    "iso:country":"CH",
    "sg:address":"Borzuat.",
    "sg:city":"Sierre",
    "sg:orig_category":"Herstellung von Maschinen f\u00fcr die Nahrungsmittel, Getr\u00e4nkeherstellung U die Tabakverarbeitung",
    "sg:postcode":"3960",
    "sg:province":"Valais",
    "wof:name":"Berclaz & Cie, Bondes Id\u00e9ales.",
    "wof:placetype":"venue"
},
  "geometry": {"coordinates":[7.5370020866,46.2945976257],"type":"Point"}
}