{
  "type": "Feature",
  "properties": {
    "iso:country":"CH",
    "sg:address":"Luchten 75",
    "sg:city":"Wolfhalden",
    "sg:orig_category":"Herstellung von Kunststoffwaren Herstellung von Platten, Folien, Schl\u00e4uchen U Profilen aus Kunststof",
    "sg:phone":"+41 55 444 22 49",
    "sg:postcode":"9427",
    "sg:province":"Appenzell Ausserrhoden",
    "wof:name":"Produ-plast, Langenscheid J.",
    "wof:placetype":"venue"
},
  "geometry": {"coordinates":[8.9527902603,47.1751785278],"type":"Point"}
}