{
  "type": "Feature",
  "properties": {
    "iso:country":"CH",
    "sg:address":"Gupfstrasse 11",
    "sg:city":"B\u00e4retswil",
    "sg:orig_category":"Detailhandel mit B\u00fcchern, Zeitungen, Schreib U Papeteriewaren Detailhandel mit Schreib U Papeteriewa",
    "sg:phone":"+41 19791919",
    "sg:postcode":"8344",
    "sg:province":"Z\u00fcrich",
    "wof:name":"B\u00e4relade Helen Lieb Papeterie Geschenkartikel",
    "wof:placetype":"venue"
},
  "geometry": {"coordinates":[8.855384,47.33503],"type":"Point"}
}