{
  "type": "Feature",
  "properties": {
    "iso:country":"CH",
    "sg:address":"Varenna Via Bartolomeo 59",
    "sg:city":"Locarno",
    "sg:orig_category":"Handel mit Automobilen",
    "sg:postcode":"6600",
    "sg:province":"Ticino",
    "wof:name":"Mohsen Autoexport",
    "wof:placetype":"venue"
},
  "geometry": {"coordinates":[8.7891998291,46.1678085327],"type":"Point"}
}