{
  "type": "Feature",
  "properties": {
    "iso:country":"CH",
    "sg:address":"Hofackerstrasse 26 8953 Dietikon. Postfach",
    "sg:city":"Dietikon",
    "sg:orig_category":"Herstellung von Mess U Kontrollinstrumenten U vorrichtungen Mechanische Werkst\u00e4tten",
    "sg:phone":"+41 17402777",
    "sg:postcode":"8953",
    "sg:province":"Z\u00fcrich",
    "wof:name":"Mafag Ag F\u00fcr Feinmechanik",
    "wof:placetype":"venue"
},
  "geometry": {"coordinates":[8.4134311676,47.3963165283],"type":"Point"}
}