{
  "type": "Feature",
  "properties": {
    "iso:country":"CH",
    "sg:address":"Hauptstrasse 10",
    "sg:city":"Meltingen",
    "sg:classifiers":[
        {
            "category":"Restaurant",
            "type":"Food & Drink"
        }
    ],
    "sg:phone":"+41 61 791 03 26",
    "sg:postcode":"4233",
    "sg:province":"Solothurn",
    "wof:name":"Restaurant Kreuz",
    "wof:placetype":"venue"
},
  "geometry": {"coordinates":[7.5901141167,47.3879623413],"type":"Point"}
}