{
  "type": "Feature",
  "properties": {
    "iso:country":"CH",
    "sg:address":"Post 1",
    "sg:city":"Murg",
    "sg:classifiers":[
        {
            "category":"Government",
            "subcategory":"Post Office",
            "type":"Public Place"
        }
    ],
    "sg:phone":"+41 81 738 11 13",
    "sg:postcode":"8877",
    "sg:province":"St. Gallen",
    "sg:tags":[
        "die",
        "poststellen"
    ],
    "wof:name":"Die Schweizerische Post",
    "wof:placetype":"venue"
},
  "geometry": {"coordinates":[9.2161121368,47.1130218506],"type":"Point"}
}