{
  "type": "Feature",
  "properties": {
    "iso:country":"CH",
    "sg:address":"Oberalpstrasse 31",
    "sg:city":"Basel",
    "sg:orig_category":"Softwareentwicklung U beratung",
    "sg:phone":"+41 71 770 00 34",
    "sg:postcode":"4054",
    "sg:province":"Basel-Stadt",
    "wof:name":"Cbis Comko Ag",
    "wof:placetype":"venue"
},
  "geometry": {"coordinates":[9.5684919357,47.3893165588],"type":"Point"}
}