{
  "type": "Feature",
  "properties": {
    "iso:country":"CH",
    "sg:address":"Bahnhofstrasse 3",
    "sg:city":"Huttwil",
    "sg:orig_category":"Detailhandel mit Waren verschiedener Art, Hauptrichtung Nahrungsmittel",
    "sg:phone":"+41 62 962 35 50",
    "sg:postcode":"4950",
    "sg:province":"Bern",
    "wof:name":"Denner Top Superdiscount",
    "wof:placetype":"venue"
},
  "geometry": {"coordinates":[7.8478097916,47.1138801575],"type":"Point"}
}