{
  "type": "Feature",
  "properties": {
    "iso:country":"CH",
    "sg:address":"Gen\u00e8ve Rue De 82",
    "sg:city":"Lausanne",
    "sg:orig_category":"Herstellung von k\u00e4lte U lufttechnischen Erzeugnissen f\u00fcr gewerbliche Zwecke",
    "sg:phone":"+41 33 243 10 77",
    "sg:postcode":"1004",
    "sg:province":"Vaud",
    "wof:name":"Feierabend Heinrich",
    "wof:placetype":"venue"
},
  "geometry": {"coordinates":[7.6794238091,46.7268218994],"type":"Point"}
}