{
  "type": "Feature",
  "properties": {
    "addr:full":"Klybeckstrasse 70 Basel Basel-Stadt 4057",
    "addr:housenumber":"70",
    "addr:postcode":"4057",
    "addr:street":"Klybeckstrasse",
    "iso:country":"CH",
    "sg:address":"Klybeckstrasse 70",
    "sg:city":"Basel",
    "sg:classifiers":[
        {
            "category":"Banks & Credit Unions",
            "subcategory":"Bank",
            "type":"Services"
        }
    ],
    "sg:phone":"+41 61 266 26 44",
    "sg:postcode":"4057",
    "sg:province":"Basel-Stadt",
    "wof:name":"Basler Kantonalbank",
    "wof:placetype":"venue"
},
  "geometry": {"coordinates":[7.59127,47.566048],"type":"Point"}
}