{
  "type": "Feature",
  "properties": {
    "iso:country":"CH",
    "sg:address":"Dorfstrasse 11",
    "sg:city":"Kloten",
    "sg:orig_category":"Sonstiger spezialisierter Hoch U Tiefbau",
    "sg:phone":"+41 18142523",
    "sg:postcode":"8302",
    "sg:province":"Z\u00fcrich",
    "wof:name":"Kundenmaurer-service Gmbh",
    "wof:placetype":"venue"
},
  "geometry": {"coordinates":[8.5819396973,47.4534797668],"type":"Point"}
}