{
  "type": "Feature",
  "properties": {
    "iso:country":"CH",
    "sg:address":"Zugerstrasse 37",
    "sg:city":"Steinhausen",
    "sg:orig_category":"Maurerarbeiten Sonstiger spezialisierter Hoch U Tiefbau",
    "sg:phone":"+41 41 741 26 10",
    "sg:postcode":"6312",
    "sg:province":"Zug",
    "wof:name":"Sattlegger G\u00fcnther",
    "wof:placetype":"venue"
},
  "geometry": {"coordinates":[8.4867658615,47.1934165955],"type":"Point"}
}