{
  "type": "Feature",
  "properties": {
    "iso:country":"CH",
    "sg:address":"Kapuzinerstrasse 1",
    "sg:city":"Glis",
    "sg:orig_category":"Fahrschulen, Flugschulen",
    "sg:phone":"+41 27 923 21 35",
    "sg:postcode":"3902",
    "sg:province":"Valais",
    "wof:name":"Johann Minnig Autofahrschule",
    "wof:placetype":"venue"
},
  "geometry": {"coordinates":[7.9876217842,46.3157196045],"type":"Point"}
}