{
  "type": "Feature",
  "properties": {
    "iso:country":"CH",
    "sg:address":"Haldenstrasse 25a 2502 Biel/bienne. Postfach",
    "sg:city":"Biel/bienne",
    "sg:orig_category":"Sonstige mit der Informatik verbundene T\u00e4tigkeiten",
    "sg:postcode":"2502",
    "sg:province":"Bern",
    "wof:name":"Tipr Gmbh",
    "wof:placetype":"venue"
},
  "geometry": {"coordinates":[7.2578120232,47.1493721008],"type":"Point"}
}