{
  "type": "Feature",
  "properties": {
    "iso:country":"CH",
    "sg:address":"Bahnhofstrasse 42",
    "sg:city":"Sursee",
    "sg:orig_category":"Detailhandel mit Musikinstrumenten Detailhandel mit Ton U Bildtr\u00e4gern",
    "sg:phone":"+41 41 920 14 84",
    "sg:postcode":"6210",
    "sg:province":"Luzern",
    "wof:name":"Ml Music Land Herbert Limacher Cd & Instrumentenshop",
    "wof:placetype":"venue"
},
  "geometry": {"coordinates":[8.0992889404,47.1715278625],"type":"Point"}
}