{
  "type": "Feature",
  "properties": {
    "iso:country":"CH",
    "sg:address":"Zollrain 2",
    "sg:city":"Aarau",
    "sg:orig_category":"Allgemeiner Hoch U Tiefbau Architekturb\u00fcros",
    "sg:phone":"+41 55 644 28 80",
    "sg:postcode":"5000",
    "sg:province":"Aargau",
    "wof:name":"Vitali Anton Ag",
    "wof:placetype":"venue"
},
  "geometry": {"coordinates":[9.078759,46.995136],"type":"Point"}
}