{
  "type": "Feature",
  "properties": {
    "iso:country":"CH",
    "sg:address":"Route Aloys-fauquez 91 1018 Lausanne Case Postale",
    "sg:city":"Lausanne",
    "sg:orig_category":"Autogaragen",
    "sg:phone":"+41 21 648 01 01",
    "sg:postcode":"1018",
    "sg:province":"Vaud",
    "wof:name":"Garage De Bellevaux Sa Honda Automobiles Succursale De Lausanne",
    "wof:placetype":"venue"
},
  "geometry": {"coordinates":[6.633327,46.536659],"type":"Point"}
}