{
  "type": "Feature",
  "properties": {
    "iso:country":"CH",
    "sg:address":"Weberstrasse 7",
    "sg:city":"Z\u00fcrich",
    "sg:orig_category":"Non-Classified Establishments",
    "sg:phone":"+41 12414833",
    "sg:postcode":"8004",
    "sg:province":"Z\u00fcrich",
    "wof:name":"G\u00fcnter Kathrein Fotostudio",
    "wof:placetype":"venue"
},
  "geometry": {"coordinates":[8.5284690857,47.3703193665],"type":"Point"}
}