{
  "type": "Feature",
  "properties": {
    "iso:country":"CH",
    "sg:address":"Rue De L'ancienne Poste",
    "sg:city":"Savi\u00e8se",
    "sg:orig_category":"Sanit\u00e4r U Heizungsinstallation",
    "sg:phone":"+41 27 395 14 24",
    "sg:postcode":"1965",
    "sg:province":"Valais",
    "wof:name":"Gilbert H\u00e9ritier Chauffages Centraux",
    "wof:placetype":"venue"
},
  "geometry": {"coordinates":[7.3476800919,46.2518692017],"type":"Point"}
}