{
  "type": "Feature",
  "properties": {
    "iso:country":"CH",
    "sg:address":"Solenbergstrasse 33 8207 Schaffhausen. Postfach",
    "sg:city":"Schaffhausen",
    "sg:orig_category":"Grosshandel mit Maschinen U Ausr\u00fcstungen Grosshandel mit sonstigen Maschinen U Ausr\u00fcstungen f\u00fcr Indu",
    "sg:phone":"+41 52 644 05 50",
    "sg:postcode":"8207",
    "sg:province":"Schaffhausen",
    "wof:name":"Bm Schaffhausen Ag Maschinenhandel",
    "wof:placetype":"venue"
},
  "geometry": {"coordinates":[8.6715307236,47.7187843323],"type":"Point"}
}