{
  "type": "Feature",
  "properties": {
    "iso:country":"CH",
    "sg:address":"Solothurnstrasse 15",
    "sg:city":"Oensingen",
    "sg:orig_category":"Sonstiges Versicherungsgewerbe",
    "sg:postcode":"4702",
    "sg:province":"Solothurn",
    "wof:name":"H\u00e4ner Kurt",
    "wof:placetype":"venue"
},
  "geometry": {"coordinates":[7.7056980133,47.2857971191],"type":"Point"}
}