{
  "type": "Feature",
  "properties": {
    "iso:country":"CH",
    "sg:address":"Via San Gottardo 60 6500 Bellinzona. Postfach",
    "sg:city":"Bellinzona",
    "sg:orig_category":"Fachdetailhandel in Verkaufsr\u00e4umen",
    "sg:postcode":"6500",
    "sg:province":"Ticino",
    "wof:name":"L'idea Di De Carli Katharina",
    "wof:placetype":"venue"
},
  "geometry": {"coordinates":[9.0337762833,46.2018318176],"type":"Point"}
}