{
  "type": "Feature",
  "properties": {
    "iso:country":"CH",
    "sg:address":"Reusseggstrasse 10",
    "sg:city":"Emmenbr\u00fccke",
    "sg:orig_category":"Abfallbeseitigung",
    "sg:phone":"+41 41 208 86 90",
    "sg:postcode":"6020",
    "sg:province":"Luzern",
    "wof:name":"St\u00e4dtische Kehrichtabfuhr",
    "wof:placetype":"venue"
},
  "geometry": {"coordinates":[8.28276,47.068417],"type":"Point"}
}