{
  "type": "Feature",
  "properties": {
    "iso:country":"CH",
    "sg:address":"Seestrasse 2 3700 Spiez. Postfach 276",
    "sg:city":"Spiez",
    "sg:orig_category":"Allgemeiner Hochbau Strassenbau",
    "sg:phone":"+41 41 811 18 06",
    "sg:postcode":"3700",
    "sg:province":"Bern",
    "wof:name":"Steiner\u00b4s Xaver S\u00f6hne, Bauunternehmung",
    "wof:placetype":"venue"
},
  "geometry": {"coordinates":[8.670334,47.01458],"type":"Point"}
}