{
  "type": "Feature",
  "properties": {
    "iso:country":"CH",
    "sg:address":"Rue Mercier 2",
    "sg:city":"Moutier",
    "sg:orig_category":"Vorschulen, Kinderg\u00e4rten",
    "sg:phone":"+41 32 493 53 25",
    "sg:postcode":"2740",
    "sg:province":"Bern",
    "wof:name":"Ecole Enfantine",
    "wof:placetype":"venue"
},
  "geometry": {"coordinates":[7.3860697746,47.282081604],"type":"Point"}
}