{
  "type": "Feature",
  "properties": {
    "iso:country":"CH",
    "sg:address":"Dorfring 12",
    "sg:city":"Allenwinden",
    "sg:orig_category":"Herstellung von Medikamenten U sonstigen pharmazeutischen Erzeugnissen Herstellung von pharmazeutisc",
    "sg:phone":"+41 41 720 42 25",
    "sg:postcode":"6319",
    "sg:province":"Zug",
    "wof:name":"Erbavita Pharma Gmbh",
    "wof:placetype":"venue"
},
  "geometry": {"coordinates":[8.5546703339,47.1657409668],"type":"Point"}
}