{
  "type": "Feature",
  "properties": {
    "iso:country":"CH",
    "sg:address":"Rue De La Justice 2",
    "sg:city":"Cully",
    "sg:orig_category":"Grafikateliers, Design",
    "sg:phone":"+41 21 799 16 63",
    "sg:postcode":"1096",
    "sg:province":"Vaud",
    "wof:name":"Marcel Treboud Peinture D'enseignes",
    "wof:placetype":"venue"
},
  "geometry": {"coordinates":[6.7303819656,46.4888916016],"type":"Point"}
}