{
  "type": "Feature",
  "properties": {
    "iso:country":"CH",
    "sg:address":"Via Alla Rossa",
    "sg:city":"Rancate",
    "sg:orig_category":"Herstellung von medizinischen U chirurgischen Ger\u00e4ten sowie orthop\u00e4dischen Vorrichtungen Medizinisch",
    "sg:phone":"+41 91 640 60 40",
    "sg:postcode":"6862",
    "sg:province":"Ticino",
    "wof:name":"Helbio Sa",
    "wof:placetype":"venue"
},
  "geometry": {"coordinates":[8.9721879959,45.8865013123],"type":"Point"}
}