{
  "type": "Feature",
  "properties": {
    "iso:country":"CH",
    "sg:address":"Hirtenb\u00fcndtenweg 2",
    "sg:city":"Binningen",
    "sg:orig_category":"Rolladen- and Storenmontage",
    "sg:phone":"+41 61 421 68 30",
    "sg:postcode":"4102",
    "sg:province":"Basel-Landschaft",
    "wof:name":"Felix Karrer Storen & Rolladen",
    "wof:placetype":"venue"
},
  "geometry": {"coordinates":[7.5688691139,47.5306510925],"type":"Point"}
}