{
  "type": "Feature",
  "properties": {
    "iso:country":"CH",
    "sg:address":"Rue Sainte-beuve 1",
    "sg:city":"Lausanne",
    "sg:orig_category":"Reiseb\u00fcros",
    "sg:phone":"+41 21 320 60 71",
    "sg:postcode":"1005",
    "sg:province":"Vaud",
    "wof:name":"Universal Air Tours",
    "wof:placetype":"venue"
},
  "geometry": {"coordinates":[6.6393070221,46.5208854675],"type":"Point"}
}