{
  "type": "Feature",
  "properties": {
    "iso:country":"CH",
    "sg:address":"Poststrasse 14",
    "sg:city":"Zug",
    "sg:orig_category":"Unclassifiable Establishments",
    "sg:phone":"+41 41 727 81 47",
    "sg:postcode":"6300",
    "sg:province":"Zug",
    "wof:name":"Vkg Holding Ag",
    "wof:placetype":"venue"
},
  "geometry": {"coordinates":[8.5165987015,47.1694488525],"type":"Point"}
}