{
  "type": "Feature",
  "properties": {
    "iso:country":"CH",
    "sg:address":"Rue Du Torrent 6",
    "sg:city":"Vevey",
    "sg:orig_category":"Druckweiterverarbeitung",
    "sg:phone":"+41 21 921 18 44",
    "sg:postcode":"1800",
    "sg:province":"Vaud",
    "wof:name":"Daniel Boulenaz Atelier De Reliure",
    "wof:placetype":"venue"
},
  "geometry": {"coordinates":[6.8408470154,46.460559845],"type":"Point"}
}