{
  "type": "Feature",
  "properties": {
    "iso:country":"CH",
    "sg:address":"Alpenstrasse 5",
    "sg:city":"Switzerland",
    "sg:classifiers":[
        {
            "category":"Industrial Area",
            "type":"Public Place"
        }
    ],
    "sg:phone":"+41 4119210000",
    "sg:postcode":"6",
    "sg:tags":[
        "large",
        "private"
    ],
    "wof:name":"Ems-chemie Holding Ag",
    "wof:placetype":"venue"
},
  "geometry": {"coordinates":[8.69140625,47.2544021606],"type":"Point"}
}