{
  "type": "Feature",
  "properties": {
    "iso:country":"CH",
    "sg:address":"Br\u00fcgglisackerweg 20",
    "sg:city":"Niederbipp",
    "sg:orig_category":"Unclassifiable Establishments",
    "sg:phone":"+41 32 633 19 91",
    "sg:postcode":"4704",
    "sg:province":"Bern",
    "wof:name":"L\u00fcthi Erich Gartenbau",
    "wof:placetype":"venue"
},
  "geometry": {"coordinates":[7.6839089394,47.2688674927],"type":"Point"}
}