{
  "type": "Feature",
  "properties": {
    "iso:country":"CH",
    "sg:address":"Rue Du 31-d\u00e9cembre 63",
    "sg:city":"Gen\u00e8ve",
    "sg:orig_category":"Primarschulen",
    "sg:phone":"+41 22 736 62 21",
    "sg:postcode":"1207",
    "sg:province":"Gen\u00e8ve",
    "wof:name":"Ecole Primaire Trente-et-un-d\u00e9cembre",
    "wof:placetype":"venue"
},
  "geometry": {"coordinates":[6.1620159149,46.2013511658],"type":"Point"}
}