{
  "type": "Feature",
  "properties": {
    "iso:country":"CH",
    "sg:address":"Tatroz R\u00e9sidence Le Tatrel",
    "sg:city":"Remaufens",
    "sg:orig_category":"Herstellung von Konstruktionsteilen, Fertigbauteilen U Ausbauelementen aus Holz",
    "sg:postcode":"1617",
    "sg:province":"Fribourg",
    "wof:name":"M & S Montage Maillard Et Sterckx",
    "wof:placetype":"venue"
},
  "geometry": {"coordinates":[6.8788499832,46.5283584595],"type":"Point"}
}