{
  "type": "Feature",
  "properties": {
    "iso:country":"CH",
    "sg:address":"S\u00e4gereistr. 28",
    "sg:city":"Glattbrugg",
    "sg:classifiers":[
        {
            "category":"Building & Trades",
            "subcategory":"Electrical",
            "type":"Services"
        }
    ],
    "sg:phone":"+41 71 388 11 66",
    "sg:postcode":"8152",
    "sg:province":"Z\u00fcrich",
    "sg:tags":[
        "electronic",
        "lighting",
        "equipment"
    ],
    "wof:name":"Derungs Licht Ag",
    "wof:placetype":"venue"
},
  "geometry": {"coordinates":[9.2647209167,47.4143943787],"type":"Point"}
}