{
  "type": "Feature",
  "properties": {
    "iso:country":"CH",
    "sg:address":"Rue Du Bourg 16",
    "sg:city":"Martigny",
    "sg:orig_category":"Detailhandel mit Damenbekleidung Detailhandel mit Textilien",
    "sg:phone":"+41 27 722 28 20",
    "sg:postcode":"1920",
    "sg:province":"Valais",
    "wof:name":"Friberg-carron Anne-marie",
    "wof:placetype":"venue"
},
  "geometry": {"coordinates":[7.0645418167,46.0910377502],"type":"Point"}
}