{
  "type": "Feature",
  "properties": {
    "iso:country":"CH",
    "sg:address":"Leuberg",
    "sg:city":"Hosenruck",
    "sg:orig_category":"Allgemeiner Gartenbau Gartenbau",
    "sg:phone":"+41 41 711 11 45",
    "sg:postcode":"9515",
    "sg:province":"Thurgau",
    "wof:name":"Stocklin Josef, Baumschule",
    "wof:placetype":"venue"
},
  "geometry": {"coordinates":[8.509585,47.147411],"type":"Point"}
}