{
  "type": "Feature",
  "properties": {
    "iso:country":"CH",
    "sg:address":"Rue De La Tour 1",
    "sg:city":"Avenches",
    "sg:orig_category":"Verlegen von Fliesen U Platten",
    "sg:phone":"+41 26 675 32 68",
    "sg:postcode":"1580",
    "sg:province":"Vaud",
    "wof:name":"Ada Rev\u00eatements-tapis- Parquets-carrelages",
    "wof:placetype":"venue"
},
  "geometry": {"coordinates":[7.0391130447,46.8791389465],"type":"Point"}
}