{
  "type": "Feature",
  "properties": {
    "iso:country":"CH",
    "sg:address":"Dietschenen 5",
    "sg:city":"Trachslau",
    "sg:orig_category":"Sonstiger Grosshandel",
    "sg:phone":"+41 55 412 51 14",
    "sg:postcode":"8840",
    "sg:province":"Schwyz",
    "wof:name":"Erich Sch\u00e4dler Muldenverkauf",
    "wof:placetype":"venue"
},
  "geometry": {"coordinates":[8.7233524323,47.0976982117],"type":"Point"}
}