{
  "type": "Feature",
  "properties": {
    "iso:country":"CH",
    "sg:address":"Neufeldstrasse 12",
    "sg:city":"Wettingen",
    "sg:orig_category":"Non-Classified Establishments",
    "sg:phone":"+41 56 426 39 73",
    "sg:postcode":"5430",
    "sg:province":"Aargau",
    "wof:name":"Fritschi Ren\u00e9 Consulting",
    "wof:placetype":"venue"
},
  "geometry": {"coordinates":[8.3370265961,47.460319519],"type":"Point"}
}