{
  "type": "Feature",
  "properties": {
    "iso:country":"CH",
    "sg:address":"Immeuble Le Postillon",
    "sg:city":"Crans-sur-sierre",
    "sg:orig_category":"Detailhandel mit Antiquit\u00e4ten Kunsthandel",
    "sg:phone":"+41 81 833 00 06",
    "sg:postcode":"3963",
    "sg:province":"Valais",
    "wof:name":"Antique Collector A.& L.ziegler-ardessi",
    "wof:placetype":"venue"
},
  "geometry": {"coordinates":[9.840252,46.497379],"type":"Point"}
}