{
  "type": "Feature",
  "properties": {
    "iso:country":"CH",
    "sg:address":"Wiesstrasse 7",
    "sg:city":"Heiden",
    "sg:orig_category":"Softwareentwicklung U beratung",
    "sg:phone":"+41 71 891 20 67",
    "sg:postcode":"9410",
    "sg:province":"Appenzell Ausserrhoden",
    "wof:name":"Computer System Hans Fritsche",
    "wof:placetype":"venue"
},
  "geometry": {"coordinates":[9.5391311646,47.4377250671],"type":"Point"}
}