{
  "type": "Feature",
  "properties": {
    "iso:country":"CH",
    "sg:address":"Ch. Des Cr\u00eats-de-champel 24 1206 Gen\u00e8ve. Postfach",
    "sg:city":"Gen\u00e8ve",
    "sg:orig_category":"Sonstige mit der Informatik verbundene T\u00e4tigkeiten",
    "sg:postcode":"1206",
    "sg:province":"Gen\u00e8ve",
    "wof:name":"Epilog Weibel",
    "wof:placetype":"venue"
},
  "geometry": {"coordinates":[6.1554880142,46.1873321533],"type":"Point"}
}