{
  "type": "Feature",
  "properties": {
    "iso:country":"CH",
    "sg:address":"Hauptstrasse 2",
    "sg:city":"F\u00fcllinsdorf",
    "sg:orig_category":"Grosshandel mit Holz U Baustoffen Herstellung von Konstruktionsteilen, Fertigbauteilen U Ausbaueleme",
    "sg:postcode":"4414",
    "sg:province":"Basel-Landschaft",
    "wof:name":"Ganba Bauelemente Ag",
    "wof:placetype":"venue"
},
  "geometry": {"coordinates":[7.7271342278,47.5025482178],"type":"Point"}
}