{
  "type": "Feature",
  "properties": {
    "iso:country":"CH",
    "sg:address":"Bodanstrasse 7a",
    "sg:city":"Kreuzlingen",
    "sg:orig_category":"Architekturb\u00fcros",
    "sg:phone":"+41 71 677 10 37",
    "sg:postcode":"8280",
    "sg:province":"Thurgau",
    "wof:name":"Walter Metzger Architekturplanungen",
    "wof:placetype":"venue"
},
  "geometry": {"coordinates":[9.175279,47.651138],"type":"Point"}
}