{
  "type": "Feature",
  "properties": {
    "iso:country":"CH",
    "sg:address":"Gewerbestrasse 11",
    "sg:city":"Cham",
    "sg:orig_category":"Detektivb\u00fcros U \u00dcberwachung",
    "sg:phone":"+41 41 743 13 00",
    "sg:postcode":"6330",
    "sg:province":"Zug",
    "wof:name":"Scotti School Ltd For Security",
    "wof:placetype":"venue"
},
  "geometry": {"coordinates":[8.4720430374,47.1886940002],"type":"Point"}
}