{
  "type": "Feature",
  "properties": {
    "iso:country":"CH",
    "sg:address":"Sch\u00f6nenbergstrasse 33 8820 W\u00e4denswil. Postfach 170",
    "sg:city":"W\u00e4denswil",
    "sg:orig_category":"Elektrizit\u00e4tsversorgung",
    "sg:phone":"+41 17831111",
    "sg:postcode":"8820",
    "sg:province":"Z\u00fcrich",
    "wof:name":"Elektrizit\u00e4tswerke Des Kantons Z\u00fcrich (ekz) Eltop",
    "wof:placetype":"venue"
},
  "geometry": {"coordinates":[8.6708402634,47.2266311646],"type":"Point"}
}