{
  "type": "Feature",
  "properties": {
    "iso:country":"CH",
    "sg:address":"Rombacht\u00e4li 11 5024 K\u00fcttigen. Postfach",
    "sg:city":"Rombach",
    "sg:orig_category":"Sonstiger spezialisierter Hoch U Tiefbau",
    "sg:postcode":"5022",
    "sg:province":"Aargau",
    "wof:name":"Andy Fugenabdichtungen, Metallbau, Montage, Isolierglas, V. Andjelkovic",
    "wof:placetype":"venue"
},
  "geometry": {"coordinates":[8.0342721939,47.4038772583],"type":"Point"}
}