{
  "type": "Feature",
  "properties": {
    "iso:country":"CH",
    "sg:address":"M\u00fcrtschenstrasse 3",
    "sg:city":"Uznach",
    "sg:orig_category":"Architektur U Ingenieurb\u00fcros",
    "sg:phone":"+41 55 280 36 44",
    "sg:postcode":"8730",
    "sg:province":"St. Gallen",
    "wof:name":"Hug Ingenieurb\u00fcro",
    "wof:placetype":"venue"
},
  "geometry": {"coordinates":[8.995098,47.22467],"type":"Point"}
}