{
  "type": "Feature",
  "properties": {
    "iso:country":"CH",
    "sg:address":"Althardstrasse 160",
    "sg:city":"Regensdorf",
    "sg:orig_category":"Herstellung von k\u00e4lte U lufttechnischen Erzeugnissen f\u00fcr gewerbliche Zwecke Installation von Heizung",
    "sg:phone":"+41 19951785",
    "sg:postcode":"8105",
    "sg:province":"Z\u00fcrich",
    "wof:name":"Rietmann Thomas, Inbetriebsetzen Von Klimaanlagen",
    "wof:placetype":"venue"
},
  "geometry": {"coordinates":[8.7815437317,47.3674468994],"type":"Point"}
}