{
  "type": "Feature",
  "properties": {
    "iso:country":"CH",
    "sg:address":"H\u00f6hena 59",
    "sg:city":"Br\u00fcnisried",
    "sg:orig_category":"Detailhandel mit Milcherzeugnissen U Eiern Verarbeitung von Milch",
    "sg:phone":"+41 26 419 23 64",
    "sg:postcode":"1719",
    "sg:province":"Fribourg",
    "wof:name":"Hans-rudolf Dennler K\u00e4sermeister",
    "wof:placetype":"venue"
},
  "geometry": {"coordinates":[7.2841300964,46.7497215271],"type":"Point"}
}