{
  "type": "Feature",
  "properties": {
    "iso:country":"CH",
    "sg:address":"Sagenbachmatt 11",
    "sg:city":"Hochdorf",
    "sg:orig_category":"Unclassifiable Establishments",
    "sg:postcode":"6280",
    "sg:province":"Luzern",
    "wof:name":"Riedweg Malergesch\u00e4ft Gmbh",
    "wof:placetype":"venue"
},
  "geometry": {"coordinates":[8.295750618,47.1674804688],"type":"Point"}
}