{
  "type": "Feature",
  "properties": {
    "iso:country":"CH",
    "sg:address":"Rue Des Ch\u00e2teaux 12",
    "sg:city":"Sion",
    "sg:orig_category":"Museen",
    "sg:phone":"+41 22 418 26 00",
    "sg:postcode":"1950",
    "sg:province":"Valais",
    "wof:name":"Mus\u00e9e D'art & D'histoire",
    "wof:placetype":"venue"
},
  "geometry": {"coordinates":[6.1530170441,46.198764801],"type":"Point"}
}