{
  "type": "Feature",
  "properties": {
    "iso:country":"CH",
    "sg:address":"Zentralstrasse 4",
    "sg:city":"Wallisellen",
    "sg:orig_category":"D\u00e4mmung gegen K\u00e4lte, W\u00e4rme, Schall U Ersch\u00fctterung",
    "sg:phone":"+41 18304664",
    "sg:postcode":"8304",
    "sg:province":"Z\u00fcrich",
    "wof:name":"Hotz Isolationen Ag",
    "wof:placetype":"venue"
},
  "geometry": {"coordinates":[8.5921058655,47.4161224365],"type":"Point"}
}