{
  "type": "Feature",
  "properties": {
    "iso:country":"CH",
    "sg:address":"1897 Bouveret Case Postale 30",
    "sg:city":"Bouveret",
    "sg:orig_category":"Detailhandel mit Getr\u00e4nken Grosshandel mit Getr\u00e4nken",
    "sg:phone":"+41 52 242 44 74",
    "sg:postcode":"1897",
    "sg:province":"Valais",
    "wof:name":"Cave Du Moulin Graff",
    "wof:placetype":"venue"
},
  "geometry": {"coordinates":[8.7712812424,47.5076637268],"type":"Point"}
}