{
  "type": "Feature",
  "properties": {
    "iso:country":"CH",
    "sg:address":"Sihlbruggstrasse 105",
    "sg:city":"Baar",
    "sg:orig_category":"Unclassifiable Establishments",
    "sg:postcode":"6340",
    "sg:province":"Zug",
    "wof:name":"Dimitrios Und Regina Deletaris",
    "wof:placetype":"venue"
},
  "geometry": {"coordinates":[7.3618221283,47.182144165],"type":"Point"}
}