{
  "type": "Feature",
  "properties": {
    "iso:country":"CH",
    "sg:address":"Weyerstrasse 15",
    "sg:city":"Wabern",
    "sg:orig_category":"Fahrschulen, Flugschulen",
    "sg:phone":"+41 31 961 17 24",
    "sg:postcode":"3084",
    "sg:province":"Bern",
    "wof:name":"Beat Waller Autofahrschule",
    "wof:placetype":"venue"
},
  "geometry": {"coordinates":[7.4558730125,46.9279212952],"type":"Point"}
}