{
  "type": "Feature",
  "properties": {
    "iso:country":"CH",
    "sg:address":"Rue De Couvaloup 13",
    "sg:city":"Morges",
    "sg:orig_category":"Diskotheken, Dancings, Night Clubs",
    "sg:phone":"+41 21 801 10 13",
    "sg:postcode":"1110",
    "sg:province":"Vaud",
    "wof:name":"Dancing Le Jockey-club",
    "wof:placetype":"venue"
},
  "geometry": {"coordinates":[6.4988470078,46.5101623535],"type":"Point"}
}