{
  "type": "Feature",
  "properties": {
    "iso:country":"CH",
    "sg:address":"Klybeckstrasse 40",
    "sg:city":"Basel",
    "sg:orig_category":"Arztpraxen",
    "sg:phone":"+41 61 681 81 40",
    "sg:postcode":"4057",
    "sg:province":"Basel-Stadt",
    "wof:name":"Dr.med.franz M\u00fcck Spezialarzt",
    "wof:placetype":"venue"
},
  "geometry": {"coordinates":[7.59154,47.564613],"type":"Point"}
}