{
  "type": "Feature",
  "properties": {
    "iso:country":"CH",
    "sg:address":"Froideville Chemin De 3 1422 Grandson Case Postale 60",
    "sg:city":"Grandson",
    "sg:orig_category":"Herstellung von sonstigen elektrischen Ausr\u00fcstungen",
    "sg:phone":"+41 24 445 25 19",
    "sg:postcode":"1422",
    "sg:province":"Vaud",
    "wof:name":"Roth Paul Sa",
    "wof:placetype":"venue"
},
  "geometry": {"coordinates":[6.6459851265,46.8093681335],"type":"Point"}
}