{
  "type": "Feature",
  "properties": {
    "iso:country":"CH",
    "sg:address":"L\u00f6wenstrasse 6",
    "sg:city":"Luzern",
    "sg:orig_category":"Detailhandel mit Beleuchtungs U Haushaltsgegenst\u00e4nden Detailhandel mit M\u00f6beln",
    "sg:phone":"+41 41 410 52 93",
    "sg:postcode":"6004",
    "sg:province":"Luzern",
    "wof:name":"Stolz & Co Souvenir, Geschenkartikel. Wohnbedarf, Beleuchtung Usw",
    "wof:placetype":"venue"
},
  "geometry": {"coordinates":[8.312169,47.055599],"type":"Point"}
}