{
  "type": "Feature",
  "properties": {
    "iso:country":"CH",
    "sg:address":"Vernier Route De 190",
    "sg:city":"Vernier",
    "sg:orig_category":"Saunas, Solarien, Fitnesszentren U \u00e4hnliches",
    "sg:phone":"+41 22 341 10 20",
    "sg:postcode":"1214",
    "sg:province":"Gen\u00e8ve",
    "wof:name":"Association Yoga De L'energie Universelle Et Humaine - Suisse Romande",
    "wof:placetype":"venue"
},
  "geometry": {"coordinates":[6.0804748535,46.2123451233],"type":"Point"}
}