{
  "type": "Feature",
  "properties": {
    "iso:country":"CH",
    "sg:address":"Werdstrasse 21 8021 Z\u00fcrich. Postfach 8895",
    "sg:city":"Z\u00fcrich",
    "sg:classifiers":[
        {
            "category":"Internet Cafe",
            "subcategory":"None",
            "type":"Food & Drink"
        }
    ],
    "sg:phone":"+41 13065757",
    "sg:postcode":"8004",
    "sg:province":"Z\u00fcrich",
    "sg:tags":[
        "provider"
    ],
    "wof:name":"Winner Market Ag",
    "wof:placetype":"venue"
},
  "geometry": {"coordinates":[8.5297670364,47.3725471497],"type":"Point"}
}