{
  "type": "Feature",
  "properties": {
    "iso:country":"CH",
    "sg:address":"Gare Rue De La 9",
    "sg:city":"Glovelier",
    "sg:orig_category":"RESTAURANTS: TEA-ROOMS",
    "sg:postcode":"2855",
    "sg:province":"Jura",
    "wof:name":"Lachat Ad\u00e8le",
    "wof:placetype":"venue"
},
  "geometry": {"coordinates":[7.1992797852,47.3326377869],"type":"Point"}
}