{
  "type": "Feature",
  "properties": {
    "iso:country":"CH",
    "sg:address":"Bd Perolles 25 Bp 1044",
    "sg:city":"Fribourg",
    "sg:classifiers":[
        {
            "category":"Utilities",
            "subcategory":"Electric",
            "type":"Services"
        }
    ],
    "sg:phone":"+41 26 352 52 52",
    "sg:postcode":"1701",
    "sg:province":"Fribourg",
    "sg:tags":[
        "electricity",
        "raw",
        "energy",
        "material"
    ],
    "wof:name":"Entreprises Electriques Fribourgeoises",
    "wof:placetype":"venue"
},
  "geometry": {"coordinates":[7.1526122093,46.7992172241],"type":"Point"}
}