{
  "type": "Feature",
  "properties": {
    "iso:country":"CH",
    "sg:address":"Hauptstrasse 10",
    "sg:city":"Ederswiler",
    "sg:orig_category":"RESTAURANTS: TEA-ROOMS",
    "sg:phone":"+41 32 431 17 50",
    "sg:postcode":"2813",
    "sg:province":"Jura",
    "wof:name":"Buchacher Josef",
    "wof:placetype":"venue"
},
  "geometry": {"coordinates":[7.3355870247,47.4257354736],"type":"Point"}
}