{
  "type": "Feature",
  "properties": {
    "iso:country":"CH",
    "sg:address":"Waagtalstrasse 8",
    "sg:city":"Unteriberg",
    "sg:orig_category":"Malerei",
    "sg:phone":"+41 71 755 39 11",
    "sg:postcode":"8842",
    "sg:province":"Schwyz",
    "wof:name":"Hans-rudolf Keller Malergesch\u00e4ft",
    "wof:placetype":"venue"
},
  "geometry": {"coordinates":[9.5355577469,47.3810882568],"type":"Point"}
}