{
  "type": "Feature",
  "properties": {
    "iso:country":"CH",
    "sg:address":"R\u00e9sidence De La C\u00f4te 10",
    "sg:city":"Morges",
    "sg:orig_category":"Kinesiologie",
    "sg:phone":"+41 52 242 52 02",
    "sg:postcode":"1110",
    "sg:province":"Vaud",
    "wof:name":"Brigitte Wiesendanger Kinesiologie",
    "wof:placetype":"venue"
},
  "geometry": {"coordinates":[8.7785263062,47.5058746338],"type":"Point"}
}