{
  "type": "Feature",
  "properties": {
    "iso:country":"CH",
    "sg:address":"Sch\u00fctzenstrasse 1",
    "sg:city":"Triengen",
    "sg:orig_category":"Handelsvermittlung U Grosshandel R\u00fcckgewinnung U Vorbereitung f\u00fcr die Wiederverwertung Recycling",
    "sg:phone":"+41 41 933 16 22",
    "sg:postcode":"6234",
    "sg:province":"Luzern",
    "wof:name":"Moritz B\u00fchlmann Alteisen & Metalle",
    "wof:placetype":"venue"
},
  "geometry": {"coordinates":[8.0726804733,47.2352638245],"type":"Point"}
}