{
  "type": "Feature",
  "properties": {
    "iso:country":"CH",
    "sg:address":"Voa Sporz 7082 Vaz/obervaz. Postfach",
    "sg:city":"Vaz/obervaz",
    "sg:orig_category":"RESTAURANTS: TEA-ROOMS",
    "sg:postcode":"7082",
    "sg:province":"Graubunden",
    "wof:name":"Grotto Pizzeria Da Elio, Marcel Caluori",
    "wof:placetype":"venue"
},
  "geometry": {"coordinates":[9.5434093475,46.7219467163],"type":"Point"}
}