{
  "type": "Feature",
  "properties": {
    "iso:country":"CH",
    "sg:address":"Bahnhofstrasse 3860 Meiringen. Postfach",
    "sg:city":"Meiringen",
    "sg:orig_category":"Wirtschafts- and Arbeitgeberverb\u00e4nde",
    "sg:phone":"+41 33 972 50 50",
    "sg:postcode":"3860",
    "sg:province":"Bern",
    "wof:name":"Hotelier-verein Meiringen Verkehrsb\u00fcro",
    "wof:placetype":"venue"
},
  "geometry": {"coordinates":[8.1877098083,46.7271766663],"type":"Point"}
}