{
  "type": "Feature",
  "properties": {
    "iso:country":"CH",
    "sg:address":"1656",
    "sg:city":"Jaun",
    "sg:orig_category":"Interessenvertretungen",
    "sg:postcode":"1656",
    "sg:province":"Fribourg",
    "wof:name":"Stiftung Alte M\u00fchle Oberbann Erwerb, Umbau, Betrieb Der Alten M\u00fchle, Historische Objekte Usw",
    "wof:placetype":"venue"
},
  "geometry": {"coordinates":[7.6346611977,46.3163337708],"type":"Point"}
}