{
  "type": "Feature",
  "properties": {
    "iso:country":"CH",
    "sg:address":"Felsenaustrasse 30 8200 Schaffhausen. Postfach",
    "sg:city":"Schaffhausen",
    "sg:orig_category":"Fussboden, Fliesen U Plattenlegerei, Tapeziererei",
    "sg:phone":"+41 52 625 12 54",
    "sg:postcode":"8202",
    "sg:province":"Schaffhausen",
    "wof:name":"Kunz Dominik Gmbh Plattenlegerbetrieb. Waren; An, Verkauf",
    "wof:placetype":"venue"
},
  "geometry": {"coordinates":[8.630613327,47.7115478516],"type":"Point"}
}