{
  "type": "Feature",
  "properties": {
    "iso:country":"CH",
    "sg:address":"Mouson Rue Du 5",
    "sg:city":"Marin-centre",
    "sg:orig_category":"Mit dem Versicherungsgewerbe verbundene T\u00e4tigkeiten",
    "sg:phone":"+41 41 630 01 55",
    "sg:postcode":"2074",
    "sg:province":"Neuch\u00e2tel",
    "wof:name":"Jowe Versicherungsbroker Ag Immobilien Usw",
    "wof:placetype":"venue"
},
  "geometry": {"coordinates":[8.3023681641,46.9898109436],"type":"Point"}
}