{
  "type": "Feature",
  "properties": {
    "iso:country":"CH",
    "sg:address":"Poststrasse 133",
    "sg:city":"Hilfikon",
    "sg:orig_category":"Politische Parteien CVP",
    "sg:phone":"+41 56 222 97 97",
    "sg:postcode":"5613",
    "sg:province":"Aargau",
    "wof:name":"Cvp Ortspartei Hilfikon",
    "wof:placetype":"venue"
},
  "geometry": {"coordinates":[8.247636795,47.3315315247],"type":"Point"}
}