{
  "type": "Feature",
  "properties": {
    "iso:country":"CH",
    "sg:address":"Hauptstrasse 171",
    "sg:city":"Arisdorf",
    "sg:orig_category":"Personenbef\u00f6rderung im Linienverkehr zu Land Personenbef\u00f6rderung im Nahverkehr",
    "sg:phone":"+41 61 811 22 54",
    "sg:postcode":"4422",
    "sg:province":"Basel-Landschaft",
    "wof:name":"Pa Autobus Gmbh",
    "wof:placetype":"venue"
},
  "geometry": {"coordinates":[7.76583004,47.4987030029],"type":"Point"}
}