{
  "type": "Feature",
  "properties": {
    "iso:country":"CH",
    "sg:address":"Buecheneggstrasse 15 8906 Bonstetten. Postfach",
    "sg:city":"Bonstetten",
    "sg:orig_category":"Spezialkreditinstitute",
    "sg:postcode":"8906",
    "sg:province":"Z\u00fcrich",
    "wof:name":"Z\u00fcrcher Amtsb\u00fcrgschaftsgenossenschaft",
    "wof:placetype":"venue"
},
  "geometry": {"coordinates":[8.4741868973,47.3132820129],"type":"Point"}
}