{
  "type": "Feature",
  "properties": {
    "iso:country":"CH",
    "sg:address":"Rue De L'eau 29 2500 Biel/bienne. Postfach",
    "sg:city":"Biel/bienne",
    "sg:orig_category":"Grosshandel mit Nahrungsmitteln, Getr\u00e4nken U Tabakwaren ohne ausgepr\u00e4gten Schwerpunkt",
    "sg:phone":"+41 32 342 38 19",
    "sg:postcode":"2502",
    "sg:province":"Bern",
    "wof:name":"Pennisi Camillo.",
    "wof:placetype":"venue"
},
  "geometry": {"coordinates":[7.2486801147,47.1438102722],"type":"Point"}
}