{
  "type": "Feature",
  "properties": {
    "iso:country":"CH",
    "sg:address":"Industriering 7",
    "sg:city":"Utzenstorf",
    "sg:orig_category":"G\u00fcterbef\u00f6rderung im Strassenverkehr R\u00fcckgewinnung U Vorbereitung f\u00fcr die Wiederverwertung Recycling",
    "sg:phone":"+41 32 666 40 80",
    "sg:postcode":"3427",
    "sg:province":"Bern",
    "wof:name":"Hans Gast",
    "wof:placetype":"venue"
},
  "geometry": {"coordinates":[7.5499949455,47.1428527832],"type":"Point"}
}