{
  "type": "Feature",
  "properties": {
    "iso:country":"CH",
    "sg:address":"Bernstrasse 306",
    "sg:city":"Heimberg",
    "sg:orig_category":"Detailhandel mit Haustieren U zoologischem Bedarf Veterin\u00e4rwesen",
    "sg:phone":"+41 33 437 05 00",
    "sg:postcode":"3627",
    "sg:province":"Bern",
    "wof:name":"Tierpflege Winter & Hofstetter",
    "wof:placetype":"venue"
},
  "geometry": {"coordinates":[7.6071147919,46.7912483215],"type":"Point"}
}