{
  "type": "Feature",
  "properties": {
    "iso:country":"CH",
    "sg:address":"Quaderstrasse 19",
    "sg:city":"Chur",
    "sg:orig_category":"Gemischte Landwirtschaft",
    "sg:postcode":"7000",
    "sg:province":"Graubunden",
    "wof:name":"Anton Frei Lohnunternehmung Gmbh",
    "wof:placetype":"venue"
},
  "geometry": {"coordinates":[7.9244251251,47.1359481812],"type":"Point"}
}