{
  "type": "Feature",
  "properties": {
    "iso:country":"CH",
    "sg:address":"Passage De L'industrie 8",
    "sg:city":"St-imier",
    "sg:orig_category":"Herstellung von Uhren",
    "sg:phone":"+41 32 963 15 58",
    "sg:postcode":"2610",
    "sg:province":"Bern",
    "wof:name":"Miserez A. & Fils Sa.",
    "wof:placetype":"venue"
},
  "geometry": {"coordinates":[6.9292798042,47.1269111633],"type":"Point"}
}