{
  "type": "Feature",
  "properties": {
    "iso:country":"CH",
    "sg:address":"Magoria Piazza 8",
    "sg:city":"Bellinzona",
    "sg:orig_category":"Herstellung von W\u00e4sche",
    "sg:phone":"+41 91 826 14 41",
    "sg:postcode":"6500",
    "sg:province":"Ticino",
    "wof:name":"Nora Bimbi Sa",
    "wof:placetype":"venue"
},
  "geometry": {"coordinates":[9.0241346359,46.1910743713],"type":"Point"}
}