{
  "type": "Feature",
  "properties": {
    "iso:country":"CH",
    "sg:address":"Oberkirchstrasse 27",
    "sg:city":"Frauenfeld",
    "sg:orig_category":"Wirtschafts- and Arbeitgeberverb\u00e4nde",
    "sg:postcode":"8500",
    "sg:province":"Thurgau",
    "wof:name":"Verband Schweiz.g\u00e4rtner- Meister,hrn Aug.sch\u00f6nenberger",
    "wof:placetype":"venue"
},
  "geometry": {"coordinates":[8.5074367523,47.1491966248],"type":"Point"}
}