{
  "type": "Feature",
  "properties": {
    "iso:country":"CH",
    "sg:address":"1523",
    "sg:city":"Granges-marnand",
    "sg:orig_category":"Detailhandel mit Waren verschiedener Art, Hauptrichtung Nahrungsmittel",
    "sg:phone":"+41 26 927 11 35",
    "sg:postcode":"1523",
    "sg:province":"Vaud",
    "wof:name":"Coop Centre",
    "wof:placetype":"venue"
},
  "geometry": {"coordinates":[7.1641640663,46.6192207336],"type":"Point"}
}