{
  "type": "Feature",
  "properties": {
    "iso:country":"CH",
    "sg:address":"Fahracker",
    "sg:city":"Murgenthal",
    "sg:orig_category":"Detailhandel mit Waren verschiedener Art, Hauptrichtung Nahrungsmittel",
    "sg:phone":"+41 62 926 39 46",
    "sg:postcode":"4853",
    "sg:province":"Aargau",
    "wof:name":"Migros Aare",
    "wof:placetype":"venue"
},
  "geometry": {"coordinates":[7.8285050392,47.2650756836],"type":"Point"}
}