{
  "type": "Feature",
  "properties": {
    "iso:country":"CH",
    "sg:address":"Haldenweg 1",
    "sg:city":"Jegenstorf",
    "sg:orig_category":"Handelsvermittlung U Grosshandel",
    "sg:phone":"+41 31 761 25 29",
    "sg:postcode":"3303",
    "sg:province":"Bern",
    "wof:name":"Susanna Neuenschwander Mini-mundus Gen'vertr.schweiz",
    "wof:placetype":"venue"
},
  "geometry": {"coordinates":[7.5067739487,47.0534553528],"type":"Point"}
}