{
  "type": "Feature",
  "properties": {
    "iso:country":"CH",
    "sg:address":"Helblingstrasse 10",
    "sg:city":"Rothrist",
    "sg:orig_category":"Sonstige technische Beratung U Planung",
    "sg:phone":"+41 71 311 20 40",
    "sg:postcode":"4852",
    "sg:province":"Aargau",
    "wof:name":"Gantag Ag Bauberatungs-praxis",
    "wof:placetype":"venue"
},
  "geometry": {"coordinates":[9.3153038025,47.4208641052],"type":"Point"}
}