{
  "type": "Feature",
  "properties": {
    "iso:country":"CH",
    "sg:address":"3555",
    "sg:city":"Trubschachen",
    "sg:orig_category":"Erschliessung von Grundst\u00fccken",
    "sg:postcode":"3555",
    "sg:province":"Bern",
    "wof:name":"Wohnbaugenossenschaft Wbg Trubschachen",
    "wof:placetype":"venue"
},
  "geometry": {"coordinates":[7.844203949,46.9230995178],"type":"Point"}
}