{
  "type": "Feature",
  "properties": {
    "iso:country":"CH",
    "sg:address":"Jurastrasse 39",
    "sg:city":"Seltisberg",
    "sg:orig_category":"Filmverleih U Videoprogrammanbieter",
    "sg:phone":"+41 61 911 99 39",
    "sg:postcode":"4411",
    "sg:province":"Basel-Landschaft",
    "wof:name":"Hedy Wehrli Film-& Videoarchiv",
    "wof:placetype":"venue"
},
  "geometry": {"coordinates":[7.7257938385,47.4657020569],"type":"Point"}
}