{
  "type": "Feature",
  "properties": {
    "iso:country":"CH",
    "sg:address":"Segger",
    "sg:city":"Walkringen",
    "sg:orig_category":"Sportvereine Hornussen",
    "sg:phone":"+41 31 701 15 34",
    "sg:postcode":"3512",
    "sg:province":"Bern",
    "wof:name":"Hornusserges.bigenthal",
    "wof:placetype":"venue"
},
  "geometry": {"coordinates":[7.6282448769,46.9553260803],"type":"Point"}
}