{
  "type": "Feature",
  "properties": {
    "addr:full":"Route De Riddes 77 Sion Valais 1950",
    "addr:housenumber":"77",
    "addr:postcode":"1950",
    "addr:street":"Route De Riddes",
    "iso:country":"CH",
    "sg:address":"Route De Riddes 77",
    "sg:city":"Sion",
    "sg:orig_category":"Dachdeckerei Zimmerei, Dachdeckerei, Bauspenglerei U Abdichtung",
    "sg:phone":"+41 27 203 33 56",
    "sg:postcode":"1950",
    "sg:province":"Valais",
    "wof:name":"Geneux Dancet Sa",
    "wof:placetype":"venue"
},
  "geometry": {"coordinates":[7.368485,46.222786],"type":"Point"}
}