{
  "type": "Feature",
  "properties": {
    "iso:country":"CH",
    "sg:address":"Hinterm\u00fchlenstrasse 6",
    "sg:city":"Winterthur",
    "sg:orig_category":"Herstellung von sonstigen Maschinen f\u00fcr unspezifische Verwendung",
    "sg:phone":"+41 52 242 51 11",
    "sg:postcode":"8409",
    "sg:province":"Z\u00fcrich",
    "wof:name":"Entso Tech Ag Gesellschaft F\u00fcr Entsorgungstechnik",
    "wof:placetype":"venue"
},
  "geometry": {"coordinates":[8.7736988068,47.5038948059],"type":"Point"}
}