{
  "type": "Feature",
  "properties": {
    "iso:country":"CH",
    "sg:address":"Balsingenstrasse 8",
    "sg:city":"W\u00fcnnewil",
    "sg:orig_category":"Bauschreinerei Einbau von Schreinerwaren",
    "sg:phone":"+41 26 496 14 31",
    "sg:postcode":"3184",
    "sg:province":"Fribourg",
    "wof:name":"Emil M\u00fclhauser Schreinerei & K\u00fcchenbau",
    "wof:placetype":"venue"
},
  "geometry": {"coordinates":[7.287797,46.876019],"type":"Point"}
}