{
  "type": "Feature",
  "properties": {
    "addr:full":"Rue Du Rh\u00f4ne 40 Gen\u00e8ve Gen\u00e8ve 1204",
    "addr:housenumber":"40",
    "addr:postcode":"1204",
    "addr:street":"Rue Du Rho\u0302Ne",
    "iso:country":"CH",
    "sg:address":"Rue Du Rh\u00f4ne 40",
    "sg:city":"Gen\u00e8ve",
    "sg:orig_category":"Detailhandel mit Damenbekleidung",
    "sg:phone":"+41 22 310 83 83",
    "sg:postcode":"1204",
    "sg:province":"Gen\u00e8ve",
    "wof:name":"Boutique Gaia Pr\u00eat-\u00e0-porter F\u00e9minin",
    "wof:placetype":"venue"
},
  "geometry": {"coordinates":[6.146813,46.204197],"type":"Point"}
}