{
  "type": "Feature",
  "properties": {
    "iso:country":"CH",
    "sg:address":"Industrie Rue De L' 8a",
    "sg:city":"Chavornay",
    "sg:orig_category":"Herstellung von Konstruktionsteilen, Fertigbauteilen U Ausbauelementen aus Holz",
    "sg:phone":"+41 61 302 81 03",
    "sg:postcode":"1373",
    "sg:province":"Vaud",
    "wof:name":"Scire'banchitta Giuseppe Kunden-schreiner",
    "wof:placetype":"venue"
},
  "geometry": {"coordinates":[7.563574791,47.5225524902],"type":"Point"}
}