{
  "type": "Feature",
  "properties": {
    "iso:country":"CH",
    "sg:address":"Becklimattweg 6",
    "sg:city":"Strengelbach",
    "sg:orig_category":"Hardwareberatung",
    "sg:phone":"+41 17152777",
    "sg:postcode":"4802",
    "sg:province":"Aargau",
    "wof:name":"Solutions Multimedia R. Koch",
    "wof:placetype":"venue"
},
  "geometry": {"coordinates":[8.5427427292,47.3339195251],"type":"Point"}
}