{
  "type": "Feature",
  "properties": {
    "iso:country":"CH",
    "sg:address":"Im L\u00f6ntsch",
    "sg:city":"Rheineck",
    "sg:orig_category":"K\u00fcnstlerische Schulen",
    "sg:phone":"+41 71 888 52 66",
    "sg:postcode":"9424",
    "sg:province":"St. Gallen",
    "wof:name":"Musikschule Am Alten Rhein Sekretariat",
    "wof:placetype":"venue"
},
  "geometry": {"coordinates":[9.5887203217,47.4664802551],"type":"Point"}
}