{
  "type": "Feature",
  "properties": {
    "iso:country":"CH",
    "sg:address":"Reiterstrasse 4",
    "sg:city":"Basel",
    "sg:orig_category":"Gesundheitswesen",
    "sg:phone":"+41 61 302 12 50",
    "sg:postcode":"4054",
    "sg:province":"Basel-Stadt",
    "wof:name":"Kreative Lebenswerkstatt, Jakober Franz",
    "wof:placetype":"venue"
},
  "geometry": {"coordinates":[7.56559515,47.5495910645],"type":"Point"}
}