{
  "type": "Feature",
  "properties": {
    "iso:country":"CH",
    "sg:address":"Rue Du Nant 15",
    "sg:city":"Gen\u00e8ve",
    "sg:orig_category":"Detailhandel mit Tabakwaren Detailhandel mit Zeitungen U Zeitschriften Kioske",
    "sg:phone":"+41 22 735 24 41",
    "sg:postcode":"1207",
    "sg:province":"Gen\u00e8ve",
    "wof:name":"Nicole Mauron Tabacs-journaux",
    "wof:placetype":"venue"
},
  "geometry": {"coordinates":[6.1603679657,46.2024040222],"type":"Point"}
}