{
  "type": "Feature",
  "properties": {
    "iso:country":"CH",
    "sg:address":"5707 Seengen. Postfach 1",
    "sg:city":"Seengen",
    "sg:orig_category":"Sportvereine Ballsport Fussball Vereine Damen",
    "sg:phone":"+41 56 462 55 31",
    "sg:postcode":"5707",
    "sg:province":"Aargau",
    "wof:name":"Sc Seengen Abt.damen",
    "wof:placetype":"venue"
},
  "geometry": {"coordinates":[8.2041797638,47.3263511658],"type":"Point"}
}