{
  "type": "Feature",
  "properties": {
    "iso:country":"CH",
    "sg:address":"Rue De La Poterie 4",
    "sg:city":"Gen\u00e8ve",
    "sg:orig_category":"Sportvereine Ski",
    "sg:postcode":"1202",
    "sg:province":"Gen\u00e8ve",
    "wof:name":"Ski-club De Gen\u00e8ve",
    "wof:placetype":"venue"
},
  "geometry": {"coordinates":[6.1326332092,46.2090492249],"type":"Point"}
}