{
  "type": "Feature",
  "properties": {
    "iso:country":"CH",
    "sg:address":"Bahnhofstrasse 23",
    "sg:city":"Kreuzlingen",
    "sg:orig_category":"Non-Classified Establishments",
    "sg:postcode":"8280",
    "sg:province":"Thurgau",
    "wof:name":"Martin Hafner M.d. Hafner Schreinerarbeiten",
    "wof:placetype":"venue"
},
  "geometry": {"coordinates":[9.1704063416,47.6515884399],"type":"Point"}
}