{
  "type": "Feature",
  "properties": {
    "iso:country":"CH",
    "sg:address":"Jurastr. 29",
    "sg:city":"Langenthal",
    "sg:classifiers":[
        {
            "category":"Banks & Credit Unions",
            "subcategory":"Bank",
            "type":"Services"
        }
    ],
    "sg:phone":"+41 62 916 16 16",
    "sg:postcode":"4900",
    "sg:province":"Bern",
    "wof:name":"Schweiz. Bankgesellschaft",
    "wof:placetype":"venue"
},
  "geometry": {"coordinates":[7.787083,47.214611],"type":"Point"}
}