{
  "type": "Feature",
  "properties": {
    "iso:country":"CH",
    "sg:address":"Dorfstrasse 27",
    "sg:city":"M\u00fchlethurnen",
    "sg:orig_category":"Instandhaltung U Reparatur von Automobilen Regelm\u00e4ssige Personenbef\u00f6rderung im Fernverkehr",
    "sg:phone":"+41 31 809 02 02",
    "sg:postcode":"3127",
    "sg:province":"Bern",
    "wof:name":"Lengacher Ag",
    "wof:placetype":"venue"
},
  "geometry": {"coordinates":[7.5068101883,46.8154373169],"type":"Point"}
}