{
  "type": "Feature",
  "properties": {
    "iso:country":"CH",
    "sg:address":"Vordere Hauptgasse 11 4800 Zofingen. Postfach",
    "sg:city":"Zofingen",
    "sg:orig_category":"RESTAURANTS: TEA-ROOMS",
    "sg:phone":"+41 62 751 10 08",
    "sg:postcode":"4800",
    "sg:province":"Aargau",
    "wof:name":"Cafe Kern",
    "wof:placetype":"venue"
},
  "geometry": {"coordinates":[7.9443039894,47.2900848389],"type":"Point"}
}