{
  "type": "Feature",
  "properties": {
    "addr:full":"Route De Vidy 10 Lausanne Vaud 1007",
    "addr:housenumber":"10",
    "addr:postcode":"1007",
    "addr:street":"Route De Vidy",
    "iso:country":"CH",
    "sg:address":"Route De Vidy 10",
    "sg:city":"Lausanne",
    "sg:orig_category":"Abwasserreinigung",
    "sg:phone":"+41 21 623 32 00",
    "sg:postcode":"1007",
    "sg:province":"Vaud",
    "wof:name":"Stat.d'\u00e9puration Des Eaux Step",
    "wof:placetype":"venue"
},
  "geometry": {"coordinates":[6.59964,46.51432],"type":"Point"}
}