{
  "type": "Feature",
  "properties": {
    "iso:country":"CH",
    "sg:address":"Bienenstrasse 2",
    "sg:city":"Chur",
    "sg:orig_category":"Unternehmensberatung",
    "sg:phone":"+41 22 798 45 95",
    "sg:postcode":"7000",
    "sg:province":"Graubunden",
    "wof:name":"Saenger Olivier",
    "wof:placetype":"venue"
},
  "geometry": {"coordinates":[6.1188178062,46.2307395935],"type":"Point"}
}