{
  "type": "Feature",
  "properties": {
    "iso:country":"CH",
    "sg:address":"Kreuzbuchstrasse 89 6006 Luzern. Postfach",
    "sg:city":"Luzern",
    "sg:orig_category":"Unclassifiable Establishments",
    "sg:postcode":"6006",
    "sg:province":"Luzern",
    "wof:name":"Gpl Trennw\u00e4nde Ag Beteiligungen, Bes. Im Inneneinrichtungs- U. Trennwandsektor Usw",
    "wof:placetype":"venue"
},
  "geometry": {"coordinates":[8.3437261581,47.0517616272],"type":"Point"}
}