{
  "type": "Feature",
  "properties": {
    "iso:country":"CH",
    "sg:address":"Friedenstrasse 2 6373 Ennetb\u00fcrgen. Postfach 46",
    "sg:city":"Ennetb\u00fcrgen",
    "sg:orig_category":"Herstellung von sonstigen organischen Grundstoffen U Chemikalien",
    "sg:phone":"+41 41 620 26 22",
    "sg:postcode":"6373",
    "sg:province":"Nidwalden",
    "wof:name":"Riag Oberfl\u00e4chentechnik Ag",
    "wof:placetype":"venue"
},
  "geometry": {"coordinates":[8.4140148163,46.9843826294],"type":"Point"}
}