{
  "type": "Feature",
  "properties": {
    "iso:country":"CH",
    "sg:address":"Rathausbogen 4",
    "sg:city":"Schaffhausen",
    "sg:orig_category":"Bibliotheken U Archive Sonstige mit der \u00f6ffentlichen Verwaltung verbundene T\u00e4tigkeiten",
    "sg:phone":"+41 52 632 73 68",
    "sg:postcode":"8200",
    "sg:province":"Schaffhausen",
    "wof:name":"Kantonales Staatsarchiv",
    "wof:placetype":"venue"
},
  "geometry": {"coordinates":[8.634262,47.69582],"type":"Point"}
}