{
  "type": "Feature",
  "properties": {
    "iso:country":"CH",
    "sg:address":"Jacob Burckhardt-strasse 30",
    "sg:city":"Z\u00fcrich",
    "sg:orig_category":"Markt U Meinungsforschung",
    "sg:postcode":"8049",
    "sg:province":"Z\u00fcrich",
    "wof:name":"Sales Up, Huber Godi Verkaufsschulung, -beratung",
    "wof:placetype":"venue"
},
  "geometry": {"coordinates":[8.5058403015,47.4013061523],"type":"Point"}
}