{
  "type": "Feature",
  "properties": {
    "iso:country":"CH",
    "sg:address":"Les Vouanguyes Bluche",
    "sg:city":"Randogne",
    "sg:orig_category":"Architekturb\u00fcros",
    "sg:phone":"+41 27 481 66 66",
    "sg:postcode":"3975",
    "sg:province":"Valais",
    "wof:name":"Fr\u00e9d\u00e9ric Elzingre Bureau D'architecture",
    "wof:placetype":"venue"
},
  "geometry": {"coordinates":[7.510419,46.31184],"type":"Point"}
}