{
  "type": "Feature",
  "properties": {
    "iso:country":"CH",
    "sg:address":"Im Fink 18",
    "sg:city":"Thalwil",
    "sg:orig_category":"Mit dem Versicherungsgewerbe verbundene T\u00e4tigkeiten",
    "sg:postcode":"8800",
    "sg:province":"Z\u00fcrich",
    "wof:name":"Limmat Capital Asset Management Pauchard Albert",
    "wof:placetype":"venue"
},
  "geometry": {"coordinates":[8.5757446289,47.2829284668],"type":"Point"}
}