{
  "type": "Feature",
  "properties": {
    "iso:country":"CH",
    "sg:address":"Bergstrasse 7",
    "sg:city":"Meggen",
    "sg:classifiers":[
        {
            "category":"Professional",
            "subcategory":"Employment Agencies",
            "type":"Services"
        }
    ],
    "sg:phone":"+41 41 377 51 51",
    "sg:postcode":"6045",
    "sg:province":"Luzern",
    "sg:tags":[
        "personal",
        "u",
        "stellenvermittlung"
    ],
    "wof:name":"Personal Data Weber Ruth",
    "wof:placetype":"venue"
},
  "geometry": {"coordinates":[8.3853368759,47.0613174438],"type":"Point"}
}