{
  "type": "Feature",
  "properties": {
    "iso:country":"CH",
    "sg:address":"Pestalozzistrasse 2",
    "sg:city":"Schaffhausen",
    "sg:orig_category":"Geb\u00e4ude, Wohnungsreinigung Reinigungsgewerbe",
    "sg:phone":"+41 22 782 54 55",
    "sg:postcode":"8200",
    "sg:province":"Schaffhausen",
    "wof:name":"Iss Facility Services Ag",
    "wof:placetype":"venue"
},
  "geometry": {"coordinates":[6.0815730095,46.2250823975],"type":"Point"}
}