{
  "type": "Feature",
  "properties": {
    "iso:country":"CH",
    "sg:address":"Avenue De L'industrie 23 1870 Monthey. Postfach",
    "sg:city":"Monthey",
    "sg:orig_category":"Softwareentwicklung U beratung",
    "sg:postcode":"1870",
    "sg:province":"Valais",
    "wof:name":"Fmd, Le Caret, G. Schumacher Et Cie",
    "wof:placetype":"venue"
},
  "geometry": {"coordinates":[6.9530711174,46.2523193359],"type":"Point"}
}