{
  "type": "Feature",
  "properties": {
    "iso:country":"CH",
    "sg:address":"Hagartenstrasse 12",
    "sg:city":"Biberist",
    "sg:orig_category":"Nahrungsmittel-Industrie: Rohstoffe",
    "sg:postcode":"4562",
    "sg:province":"Solothurn",
    "wof:name":"Casa Vera Gmbh",
    "wof:placetype":"venue"
},
  "geometry": {"coordinates":[8.4414148331,47.0817146301],"type":"Point"}
}