{
  "type": "Feature",
  "properties": {
    "iso:country":"CH",
    "sg:address":"Br\u00fcckenstrasse 6",
    "sg:city":"Kreuzlingen",
    "sg:orig_category":"Wohnheime",
    "sg:phone":"+41 71 672 84 65",
    "sg:postcode":"8280",
    "sg:province":"Thurgau",
    "wof:name":"Verein Haus Br\u00fccke",
    "wof:placetype":"venue"
},
  "geometry": {"coordinates":[9.1730213165,47.6546974182],"type":"Point"}
}