{
  "type": "Feature",
  "properties": {
    "iso:country":"CH",
    "sg:address":"Dorfstrasse 10",
    "sg:city":"Thalwil",
    "sg:orig_category":"Gasversorgung Wasserversorgung",
    "sg:phone":"+41 17232292",
    "sg:postcode":"8800",
    "sg:province":"Z\u00fcrich",
    "wof:name":"Gemeindewerke Gas-& Wasserversorgung",
    "wof:placetype":"venue"
},
  "geometry": {"coordinates":[8.5680627823,47.289768219],"type":"Point"}
}