{
  "type": "Feature",
  "properties": {
    "iso:country":"CH",
    "sg:address":"Rue De Saladey 5",
    "sg:city":"Erde",
    "sg:classifiers":[
        {
            "category":"Insurance",
            "subcategory":"Insurance Agent",
            "type":"Services"
        }
    ],
    "sg:phone":"+41 79 212 35 31",
    "sg:postcode":"1976",
    "sg:province":"Valais",
    "sg:tags":[
        "versicherungsagenturen",
        "-broker"
    ],
    "wof:name":"Helvetia Patria Assurances Agence",
    "wof:placetype":"venue"
},
  "geometry": {"coordinates":[7.2959799767,46.2425804138],"type":"Point"}
}