{
  "type": "Feature",
  "properties": {
    "iso:country":"CH",
    "sg:address":"5707",
    "sg:city":"Seengen",
    "sg:classifiers":[
        {
            "category":"Education",
            "subcategory":"Vocational School",
            "type":"Public Place"
        }
    ],
    "sg:phone":"+41 81 384 21 07",
    "sg:postcode":"5707",
    "sg:province":"Aargau",
    "sg:tags":[
        "koch-",
        "haushaltschulen"
    ],
    "wof:name":"Haushaltungsschule",
    "wof:placetype":"venue"
},
  "geometry": {"coordinates":[8.2041797638,47.3263511658],"type":"Point"}
}