{
  "type": "Feature",
  "properties": {
    "iso:country":"CH",
    "sg:address":"Piazza Grande 22 Palazzo Piotti",
    "sg:city":"Locarno",
    "sg:orig_category":"Finanzierungsinstitutionen",
    "sg:postcode":"6600",
    "sg:province":"Ticino",
    "wof:name":"Ag F\u00fcr Hypothekaranlagen",
    "wof:placetype":"venue"
},
  "geometry": {"coordinates":[8.8003940582,46.1705741882],"type":"Point"}
}