{
  "type": "Feature",
  "properties": {
    "iso:country":"CH",
    "sg:address":"Chemin Du Coteau 5",
    "sg:city":"Aclens",
    "sg:orig_category":"Tankstellen",
    "sg:phone":"+41 21 869 96 26",
    "sg:postcode":"1123",
    "sg:province":"Vaud",
    "wof:name":"Carrosserie De La Plaine Lorenzo Loverde S\u00e0rl",
    "wof:placetype":"venue"
},
  "geometry": {"coordinates":[6.5209059715,46.5642967224],"type":"Point"}
}