{
  "type": "Feature",
  "properties": {
    "iso:country":"CH",
    "sg:address":"Gottret Ch.jules-eduard- 5",
    "sg:city":"Veyrier",
    "sg:orig_category":"Unclassifiable Establishments",
    "sg:phone":"+41 22 890 04 29",
    "sg:postcode":"1255",
    "sg:province":"Gen\u00e8ve",
    "wof:name":"Quinton Distribution S\u00e0rl",
    "wof:placetype":"venue"
},
  "geometry": {"coordinates":[6.1856799126,46.1664657593],"type":"Point"}
}