{
  "type": "Feature",
  "properties": {
    "iso:country":"CH",
    "sg:address":"Rinkenbach 10",
    "sg:city":"Appenzell",
    "sg:orig_category":"Sanit\u00e4r U Heizungsinstallation Sanit\u00e4r, Heizungs U L\u00fcftungsinstallation",
    "sg:phone":"+41 71 787 21 61",
    "sg:postcode":"9050",
    "sg:province":"Appenzell Innerhoden",
    "wof:name":"Ulmann Franz Ag",
    "wof:placetype":"venue"
},
  "geometry": {"coordinates":[9.4019546509,47.3319664001],"type":"Point"}
}