{
  "type": "Feature",
  "properties": {
    "iso:country":"CH",
    "sg:address":"Route Aloys-fauquez 6 1018 Lausanne Case Postale 217",
    "sg:city":"Lausanne",
    "sg:orig_category":"Instandhaltung U Reparatur von Automobilen",
    "sg:phone":"+41 62 873 22 27",
    "sg:postcode":"1018",
    "sg:province":"Vaud",
    "wof:name":"Garage Stichmatt Ag",
    "wof:placetype":"venue"
},
  "geometry": {"coordinates":[7.9878330231,47.5527458191],"type":"Point"}
}