{
  "type": "Feature",
  "properties": {
    "iso:country":"CH",
    "sg:address":"Weggengasse 3",
    "sg:city":"Z\u00fcrich",
    "sg:orig_category":"Bauschreinerei Herstellung von M\u00f6beln verschiedener Art",
    "sg:phone":"+41 12115925",
    "sg:postcode":"8001",
    "sg:province":"Z\u00fcrich",
    "wof:name":"Markus Sturzenegger Restauration Antiker M\u00f6bel",
    "wof:placetype":"venue"
},
  "geometry": {"coordinates":[8.54112,47.371414],"type":"Point"}
}