{
  "type": "Feature",
  "properties": {
    "iso:country":"CH",
    "sg:address":"Beaux-arts Rue Des 15",
    "sg:city":"Neuch\u00e2tel",
    "sg:orig_category":"Detailhandel mit elektrischen Haushalts-,Radio U Fernsehger\u00e4ten sowie Musikinstrumenten",
    "sg:postcode":"2000",
    "sg:province":"Neuch\u00e2tel",
    "wof:name":"Huguenin-dumittan",
    "wof:placetype":"venue"
},
  "geometry": {"coordinates":[6.9375338554,46.9929199219],"type":"Point"}
}