{
  "type": "Feature",
  "properties": {
    "iso:country":"CH",
    "sg:address":"1470 Estavayer-le-lac. Postfach",
    "sg:city":"Estavayer-le-lac",
    "sg:orig_category":"Unternehmensberatung",
    "sg:postcode":"1470",
    "sg:province":"Fribourg",
    "wof:name":"Keb Consulting, Emmanuelle Bussard",
    "wof:placetype":"venue"
},
  "geometry": {"coordinates":[6.8482789993,46.8487930298],"type":"Point"}
}