{
  "type": "Feature",
  "properties": {
    "iso:country":"CH",
    "sg:address":"Churfirstenstrasse 25",
    "sg:city":"Horgen",
    "sg:orig_category":"Sportvereine Wassersport Segeln",
    "sg:phone":"+41 17250884",
    "sg:postcode":"8810",
    "sg:province":"Z\u00fcrich",
    "wof:name":"Yachtclub Horgen Ych",
    "wof:placetype":"venue"
},
  "geometry": {"coordinates":[8.6056137085,47.2530593872],"type":"Point"}
}