{
  "type": "Feature",
  "properties": {
    "iso:country":"CH",
    "sg:address":"Im Steinenm\u00fcller 11",
    "sg:city":"M\u00fcnchenstein",
    "sg:orig_category":"Unternehmensberatung",
    "sg:phone":"+41 79 404 59 06",
    "sg:postcode":"4142",
    "sg:province":"Basel-Landschaft",
    "wof:name":"Qsb-consulting Frey",
    "wof:placetype":"venue"
},
  "geometry": {"coordinates":[8.3174819946,47.2825775146],"type":"Point"}
}