{
  "type": "Feature",
  "properties": {
    "iso:country":"CH",
    "sg:address":"Industriestrasse 10",
    "sg:city":"Safnern",
    "sg:orig_category":"Herstellung von Metallerzeugnissen ohne Maschinenbau",
    "sg:phone":"+41 32 322 63 32",
    "sg:postcode":"2553",
    "sg:province":"Bern",
    "wof:name":"Wels Kunststoffveredelung Ag",
    "wof:placetype":"venue"
},
  "geometry": {"coordinates":[7.3303461075,47.1548042297],"type":"Point"}
}