{
  "type": "Feature",
  "properties": {
    "iso:country":"CH",
    "sg:address":"Aachstrasse 2 9326 Horn. Postfach 103",
    "sg:city":"Horn",
    "sg:orig_category":"Handelsvermittlung U Grosshandel Sonstiger Grosshandel",
    "sg:phone":"+41 71 844 40 40",
    "sg:postcode":"9326",
    "sg:province":"Thurgau",
    "wof:name":"Thumag Ag",
    "wof:placetype":"venue"
},
  "geometry": {"coordinates":[9.4647865295,47.4925765991],"type":"Point"}
}