{
  "type": "Feature",
  "properties": {
    "addr:full":"Oberwilen 21 Speicher Appenzell Ausserrhoden 9042",
    "addr:housenumber":"21",
    "addr:postcode":"9042",
    "addr:street":"Oberwilen;Ausserrhoden",
    "iso:country":"CH",
    "sg:address":"Oberwilen 21",
    "sg:city":"Speicher",
    "sg:orig_category":"Bau U Wohngenossenschaften",
    "sg:phone":"+41 79 436 18 13",
    "sg:postcode":"9042",
    "sg:province":"Appenzell Ausserrhoden",
    "wof:name":"Wohnbaugen.oberwilen",
    "wof:placetype":"venue"
},
  "geometry": {"coordinates":[9.441026,47.414856],"type":"Point"}
}