{
  "type": "Feature",
  "properties": {
    "iso:country":"CH",
    "sg:address":"Kaiserstrasse 5a",
    "sg:city":"Rheinfelden",
    "sg:orig_category":"Fast-Foodrestaurants",
    "sg:phone":"+41 61 831 74 83",
    "sg:postcode":"4310",
    "sg:province":"Aargau",
    "wof:name":"Take-away-food Yong Faa",
    "wof:placetype":"venue"
},
  "geometry": {"coordinates":[7.7945370674,47.5524902344],"type":"Point"}
}