{
  "type": "Feature",
  "properties": {
    "iso:country":"CH",
    "sg:address":"R\u00fctistrasse 10",
    "sg:city":"Appenzell",
    "sg:orig_category":"Betrieb von Taxis G\u00fcterbef\u00f6rderung im Strassenverkehr",
    "sg:phone":"+41 71 787 13 44",
    "sg:postcode":"9050",
    "sg:province":"Appenzell Innerhoden",
    "wof:name":"Aeschbacher Ag Transporte & Taxi",
    "wof:placetype":"venue"
},
  "geometry": {"coordinates":[9.398773,47.333027],"type":"Point"}
}