{
  "type": "Feature",
  "properties": {
    "iso:country":"CH",
    "sg:address":"Via Cantonale 53",
    "sg:city":"Porza",
    "sg:orig_category":"Vermietung U Verpachtung von eigenen Immobilien",
    "sg:phone":"+41 91 941 62 45",
    "sg:postcode":"6948",
    "sg:province":"Ticino",
    "wof:name":"Grotto Cacciatori",
    "wof:placetype":"venue"
},
  "geometry": {"coordinates":[8.9559698105,46.029510498],"type":"Point"}
}