{
  "type": "Feature",
  "properties": {
    "iso:country":"CH",
    "sg:address":"Wilstrasse 11 8612 Uster 2. Postfach",
    "sg:city":"Uster",
    "sg:orig_category":"Werbung",
    "sg:postcode":"8610",
    "sg:province":"Z\u00fcrich",
    "wof:name":"Schwarz Auf Weiss, Fekete U. G\u00f6schel",
    "wof:placetype":"venue"
},
  "geometry": {"coordinates":[8.7085075378,47.3449554443],"type":"Point"}
}