{
  "type": "Feature",
  "properties": {
    "iso:country":"CH",
    "sg:address":"Hochrahn 65",
    "sg:city":"Hemmental",
    "sg:orig_category":"Maurerarbeiten Sonstiger spezialisierter Hoch U Tiefbau",
    "sg:phone":"+41 52 685 41 30",
    "sg:postcode":"8231",
    "sg:province":"Schaffhausen",
    "wof:name":"Schlatter Kurt Ag",
    "wof:placetype":"venue"
},
  "geometry": {"coordinates":[8.5872249603,47.7326049805],"type":"Point"}
}