{
  "type": "Feature",
  "properties": {
    "iso:country":"CH",
    "sg:address":"F\u00f6hrenstrasse 9",
    "sg:city":"Hettlingen",
    "sg:orig_category":"Sportvereine Turnen",
    "sg:phone":"+41 52 233 59 49",
    "sg:postcode":"8442",
    "sg:province":"Z\u00fcrich",
    "wof:name":"Turnverein Oberwinterhur",
    "wof:placetype":"venue"
},
  "geometry": {"coordinates":[8.7142953873,47.548374176],"type":"Point"}
}