{
  "type": "Feature",
  "properties": {
    "iso:country":"CH",
    "sg:address":"Jentzer Rue Alcide- 9 1205 Gen\u00e8ve. Postfach",
    "sg:city":"Gen\u00e8ve",
    "sg:orig_category":"RESTAURANTS: TEA-ROOMS",
    "sg:postcode":"1205",
    "sg:province":"Gen\u00e8ve",
    "wof:name":"Ny Unterhaltungsgastronomie Gmbh",
    "wof:placetype":"venue"
},
  "geometry": {"coordinates":[9.2883176804,46.8262405396],"type":"Point"}
}