{
  "type": "Feature",
  "properties": {
    "iso:country":"CH",
    "sg:address":"Corso San Gottardo 35",
    "sg:city":"Lugano",
    "sg:orig_category":"Unclassifiable Establishments",
    "sg:phone":"+41 91 993 01 25",
    "sg:postcode":"6900",
    "sg:province":"Ticino",
    "wof:name":"Qoboqobo Sa",
    "wof:placetype":"venue"
},
  "geometry": {"coordinates":[8.9464731216,46.0083084106],"type":"Point"}
}