{
  "type": "Feature",
  "properties": {
    "iso:country":"CH",
    "sg:address":"Rue St-andr\u00e9 20",
    "sg:city":"Chamoson",
    "sg:orig_category":"Rebbau",
    "sg:phone":"+41 21 801 32 80",
    "sg:postcode":"1955",
    "sg:province":"Valais",
    "wof:name":"Pierre Chabloz Vigneron-encaveur",
    "wof:placetype":"venue"
},
  "geometry": {"coordinates":[6.4640598297,46.5057106018],"type":"Point"}
}