{
  "type": "Feature",
  "properties": {
    "iso:country":"CH",
    "sg:address":"Gillhofstrasse 4",
    "sg:city":"M\u00e4rstetten",
    "sg:orig_category":"Herstellung von \u00d6fen U Brennern Verlegen von Fliesen U Platten",
    "sg:phone":"+41 71 657 18 11",
    "sg:postcode":"8560",
    "sg:province":"Thurgau",
    "wof:name":"Peter Gremlich Ofenbau & Plattenbel\u00e4ge",
    "wof:placetype":"venue"
},
  "geometry": {"coordinates":[9.0598964691,47.5846366882],"type":"Point"}
}