{
  "type": "Feature",
  "properties": {
    "iso:country":"CH",
    "sg:address":"Haldenstrasse 87",
    "sg:city":"Z\u00fcrich",
    "sg:orig_category":"Druckweiterverarbeitung",
    "sg:postcode":"8045",
    "sg:province":"Z\u00fcrich",
    "wof:name":"Buchbinderei Und Einrahmungsatelier, Bayard Hermann",
    "wof:placetype":"venue"
},
  "geometry": {"coordinates":[7.6328001022,46.3084754944],"type":"Point"}
}