{
  "type": "Feature",
  "properties": {
    "iso:country":"CH",
    "sg:address":"R\u00fcttihardstrasse 5",
    "sg:city":"Birsfelden",
    "sg:orig_category":"Sportvereine Ballsport Volleyball",
    "sg:postcode":"4127",
    "sg:province":"Basel-Landschaft",
    "wof:name":"Volleyball-club Ph\u00f6nix",
    "wof:placetype":"venue"
},
  "geometry": {"coordinates":[7.6298317909,47.5522499084],"type":"Point"}
}