{
  "type": "Feature",
  "properties": {
    "iso:country":"CH",
    "sg:address":"Route De Lausanne 18",
    "sg:city":"Yverdon-les-bains",
    "sg:orig_category":"Grafikateliers, Design Siebdruck",
    "sg:phone":"+41 32 926 62 20",
    "sg:postcode":"1400",
    "sg:province":"Vaud",
    "wof:name":"Jean-marc Fallet Peintre En Lettres",
    "wof:placetype":"venue"
},
  "geometry": {"coordinates":[6.8258519173,47.1012001038],"type":"Point"}
}