{
  "type": "Feature",
  "properties": {
    "iso:country":"CH",
    "sg:address":"Hartlisbergstrasse 20",
    "sg:city":"Steffisburg",
    "sg:orig_category":"Herstellung von Tanks U Sammelbeh\u00e4ltern aus Metall Reinigungsgewerbe",
    "sg:phone":"+41 33 437 66 23",
    "sg:postcode":"3612",
    "sg:province":"Bern",
    "wof:name":"Tankreinigung Kr\u00e4henb\u00fchl Ag",
    "wof:placetype":"venue"
},
  "geometry": {"coordinates":[7.6287660599,46.7873802185],"type":"Point"}
}