{
  "type": "Feature",
  "properties": {
    "iso:country":"CH",
    "sg:address":"Seestrasse 10",
    "sg:city":"Horn",
    "sg:orig_category":"Non-Classified Establishments",
    "sg:postcode":"9326",
    "sg:province":"Thurgau",
    "wof:name":"Klingel Robert Verwaltungs Gmbh",
    "wof:placetype":"venue"
},
  "geometry": {"coordinates":[9.4728221893,47.4905548096],"type":"Point"}
}