{
  "type": "Feature",
  "properties": {
    "iso:country":"CH",
    "sg:address":"Artherstrasse 8 6300 Zug. Postfach",
    "sg:city":"Zug",
    "sg:orig_category":"Sonstige pers\u00f6nliche Dienstleistungen",
    "sg:postcode":"6300",
    "sg:province":"Zug",
    "wof:name":"Straub & Co Dienstleistungen In Handel U. Industrie",
    "wof:placetype":"venue"
},
  "geometry": {"coordinates":[8.5138406754,47.1634979248],"type":"Point"}
}