{
  "type": "Feature",
  "properties": {
    "iso:country":"CH",
    "sg:address":"Avenue Du Fosseau 6",
    "sg:city":"Vouvry",
    "sg:orig_category":"Physiotherapie",
    "sg:phone":"+41 24 481 33 20",
    "sg:postcode":"1896",
    "sg:province":"Valais",
    "wof:name":"Fabien Delavy Physioth\u00e9rapie",
    "wof:placetype":"venue"
},
  "geometry": {"coordinates":[6.8886599541,46.3391036987],"type":"Point"}
}