{
  "type": "Feature",
  "properties": {
    "iso:country":"CH",
    "sg:address":"Reussgasse 1",
    "sg:city":"Seon",
    "sg:orig_category":"Herstellung von Automobilen",
    "sg:phone":"+41 62 775 44 80",
    "sg:postcode":"5703",
    "sg:province":"Aargau",
    "wof:name":"Mobilforum (schweiz) Gmbh",
    "wof:placetype":"venue"
},
  "geometry": {"coordinates":[8.1606006622,47.3454971313],"type":"Point"}
}