{
  "type": "Feature",
  "properties": {
    "iso:country":"CH",
    "sg:address":"Vicolo Sacchetti 1",
    "sg:city":"Ascona",
    "sg:orig_category":"Detailhandel mit Geschenkartikeln U Souvenirs",
    "sg:phone":"+41 91 791 80 61",
    "sg:postcode":"6612",
    "sg:province":"Ticino",
    "wof:name":"Gianfranca Bondandini Boutique La Gatta",
    "wof:placetype":"venue"
},
  "geometry": {"coordinates":[8.7679843903,46.1543998718],"type":"Point"}
}