{
  "type": "Feature",
  "properties": {
    "iso:country":"CH",
    "sg:address":"Weyerstrasse 26",
    "sg:city":"Wabern",
    "sg:orig_category":"Maler U Glasergewerbe Malerei",
    "sg:phone":"+41 31 961 34 87",
    "sg:postcode":"3084",
    "sg:province":"Bern",
    "wof:name":"Keiser & Piccioni Malergesch\u00e4ft",
    "wof:placetype":"venue"
},
  "geometry": {"coordinates":[7.4565281868,46.9281387329],"type":"Point"}
}