{
  "type": "Feature",
  "properties": {
    "iso:country":"CH",
    "sg:address":"Kreuzmattring 7",
    "sg:city":"Kastanienbaum",
    "sg:orig_category":"Wirtschaftspr\u00fcfung, Steuerberatung U Treuhand",
    "sg:postcode":"6047",
    "sg:province":"Luzern",
    "wof:name":"Isler-steuerberatung",
    "wof:placetype":"venue"
},
  "geometry": {"coordinates":[8.5495815277,47.4044799805],"type":"Point"}
}