{
  "type": "Feature",
  "properties": {
    "iso:country":"CH",
    "sg:address":"Treize-cantons",
    "sg:city":"Seigneux",
    "sg:orig_category":"Non-Classified Establishments",
    "sg:postcode":"1525",
    "sg:province":"Vaud",
    "wof:name":"Df Doigts De F\u00e9e S\u00e0rl",
    "wof:placetype":"venue"
},
  "geometry": {"coordinates":[6.87018013,46.7275810242],"type":"Point"}
}