{
  "type": "Feature",
  "properties": {
    "iso:country":"CH",
    "sg:address":"Chapfstrasse 50",
    "sg:city":"Zumikon",
    "sg:orig_category":"Fachdetailhandel in Verkaufsr\u00e4umen Grosshandel mit Sportartikeln",
    "sg:phone":"+41 19190071",
    "sg:postcode":"8126",
    "sg:province":"Z\u00fcrich",
    "wof:name":"Fittrade, Daniel H\u00fcsler",
    "wof:placetype":"venue"
},
  "geometry": {"coordinates":[8.6321201324,47.3298149109],"type":"Point"}
}