{
  "type": "Feature",
  "properties": {
    "iso:country":"CH",
    "sg:address":"Puplinge Route De 24",
    "sg:city":"Puplinge",
    "sg:orig_category":"RESTAURANTS: TEA-ROOMS",
    "sg:postcode":"1241",
    "sg:province":"Gen\u00e8ve",
    "wof:name":"Restaurant Mon Id\u00e9e S\u00e0rl",
    "wof:placetype":"venue"
},
  "geometry": {"coordinates":[6.2292609215,46.2074165344],"type":"Point"}
}