{
  "type": "Feature",
  "properties": {
    "iso:country":"CH",
    "sg:address":"Ruedswilstrasse 4",
    "sg:city":"Ersigen",
    "sg:orig_category":"Fussboden, Fliesen U Plattenlegerei, Tapeziererei",
    "sg:postcode":"3423",
    "sg:province":"Bern",
    "wof:name":"Aeschbacher's Pl\u00e4ttliservice",
    "wof:placetype":"venue"
},
  "geometry": {"coordinates":[7.6052131653,47.101524353],"type":"Point"}
}