{
  "type": "Feature",
  "properties": {
    "iso:country":"CH",
    "sg:address":"Girlenstrasse 15",
    "sg:city":"Widnau",
    "sg:orig_category":"Herstellung von Konstruktionsteilen, Fertigbauteilen U Ausbauelementen aus Holz",
    "sg:phone":"+41 71 722 11 06",
    "sg:postcode":"9443",
    "sg:province":"St. Gallen",
    "wof:name":"Schreinermontagen/innenausbau Hanspeter Ritter",
    "wof:placetype":"venue"
},
  "geometry": {"coordinates":[9.6376008987,47.4082374573],"type":"Point"}
}