{
  "type": "Feature",
  "properties": {
    "iso:country":"CH",
    "sg:address":"Schlossbergplatz 7 5400 Baden. Postfach",
    "sg:city":"Baden",
    "sg:orig_category":"Warenh\u00e4user",
    "sg:phone":"+41 56 203 36 49",
    "sg:postcode":"5401",
    "sg:province":"Aargau",
    "wof:name":"Manor",
    "wof:placetype":"venue"
},
  "geometry": {"coordinates":[8.3074436188,47.4735183716],"type":"Point"}
}