{
  "type": "Feature",
  "properties": {
    "iso:country":"CH",
    "sg:address":"Poststr 9",
    "sg:city":"Ermatingen",
    "sg:classifiers":[
        {
            "category":"Manufacturing",
            "subcategory":"Metals",
            "type":"Manufacturing & Wholesale Goods"
        }
    ],
    "sg:phone":"+41 71 664 11 66",
    "sg:postcode":"8272",
    "sg:province":"Thurgau",
    "sg:tags":[
        "metallurgy",
        "metalworking",
        "processing"
    ],
    "wof:name":"Ermatec Ag",
    "wof:placetype":"venue"
},
  "geometry": {"coordinates":[9.0827550888,47.6701469421],"type":"Point"}
}