{
  "type": "Feature",
  "properties": {
    "iso:country":"CH",
    "sg:address":"Rousseau Rue 30 1201 Gen\u00e8ve. Postfach",
    "sg:city":"Gen\u00e8ve",
    "sg:orig_category":"Vermietung U Verpachtung von eigenen Immobilien",
    "sg:phone":"+41 26 413 19 68",
    "sg:postcode":"1201",
    "sg:province":"Gen\u00e8ve",
    "wof:name":"Clerc Jean-marie.",
    "wof:placetype":"venue"
},
  "geometry": {"coordinates":[7.1380701065,46.6968002319],"type":"Point"}
}