{
  "type": "Feature",
  "properties": {
    "iso:country":"CH",
    "sg:address":"Place Du Molard 7 1204 Gen\u00e8ve Case Postale 3806",
    "sg:city":"Gen\u00e8ve",
    "sg:orig_category":"Unternehmensberatung",
    "sg:phone":"+41 22 818 36 36",
    "sg:postcode":"1204",
    "sg:province":"Gen\u00e8ve",
    "wof:name":"Willsearch Partners Sa",
    "wof:placetype":"venue"
},
  "geometry": {"coordinates":[6.1479358673,46.2033576965],"type":"Point"}
}