{
  "type": "Feature",
  "properties": {
    "iso:country":"CH",
    "sg:address":"Rue De Ancien Cimeti\u00e8re 2",
    "sg:city":"Sierre",
    "sg:orig_category":"RESTAURANTS: TEA-ROOMS",
    "sg:phone":"+41 62 772 04 05",
    "sg:postcode":"3960",
    "sg:province":"Valais",
    "wof:name":"Paninoteca Maruzzella Gelsomino Maria",
    "wof:placetype":"venue"
},
  "geometry": {"coordinates":[8.1835489273,47.2527351379],"type":"Point"}
}