{
  "type": "Feature",
  "properties": {
    "iso:country":"CH",
    "sg:address":"Avenue Des Communes-r\u00e9unies 80 1212 Grand-lancy. Postfach",
    "sg:city":"Arare",
    "sg:orig_category":"Softwareentwicklung U beratung",
    "sg:postcode":"1212",
    "sg:province":"Gen\u00e8ve",
    "wof:name":"Multi Mod\u00e8les Informatiques S\u00e0rl Activit\u00e9s Commerciales Etc., Notamm. De Mat\u00e9riel Informatique Et De Produits D\u00e9riv\u00e9s",
    "wof:placetype":"venue"
},
  "geometry": {"coordinates":[6.1222710609,46.1728172302],"type":"Point"}
}