{
  "type": "Feature",
  "properties": {
    "iso:country":"CH",
    "sg:address":"Zugerstrasse 7 6330 Cham. Postfach 360",
    "sg:city":"Cham",
    "sg:classifiers":[
        {
            "category":"Travel",
            "subcategory":"Hotels & Motels",
            "type":"Entertainment"
        }
    ],
    "sg:postcode":"6330",
    "sg:province":"Zug",
    "sg:tags":[
        "hotels",
        "mit",
        "restaurant"
    ],
    "wof:name":"Hotel Krone, Ernst Aebi",
    "wof:placetype":"venue"
},
  "geometry": {"coordinates":[7.6547207832,47.2355384827],"type":"Point"}
}