{
  "type": "Feature",
  "properties": {
    "iso:country":"CH",
    "sg:address":"Fronalpstrasse 12",
    "sg:city":"N\u00e4fels",
    "sg:orig_category":"Sonstige Institutionen des Sozialwesens ohne Beherbergung",
    "sg:phone":"+41 31 371 26 54",
    "sg:postcode":"8752",
    "sg:province":"Glarus",
    "wof:name":"Beratungsstelle F\u00fcr Geh\u00f6rlose",
    "wof:placetype":"venue"
},
  "geometry": {"coordinates":[7.4328241348,46.9417266846],"type":"Point"}
}