{
  "type": "Feature",
  "properties": {
    "iso:country":"CH",
    "sg:address":"Olgiati Viale C. 44 6512 Giubiasco. Postfach",
    "sg:city":"Giubiasco",
    "sg:orig_category":"Sonstige Personenbef\u00f6rderung im Landverkehr",
    "sg:postcode":"6512",
    "sg:province":"Ticino",
    "wof:name":"Simili Bus Service Sagl Viaggi Internazionali Ecc",
    "wof:placetype":"venue"
},
  "geometry": {"coordinates":[9.0108251572,46.1730804443],"type":"Point"}
}