{
  "type": "Feature",
  "properties": {
    "iso:country":"CH",
    "sg:address":"M\u00f4le Rue Du 2-4 2000 Neuch\u00e2tel. Postfach",
    "sg:city":"Neuch\u00e2tel",
    "sg:orig_category":"Non-Classified Establishments",
    "sg:postcode":"2000",
    "sg:province":"Neuch\u00e2tel",
    "wof:name":"E2e Solutions Sa Participations Etc",
    "wof:placetype":"venue"
},
  "geometry": {"coordinates":[6.9310851097,46.9903335571],"type":"Point"}
}