{
  "type": "Feature",
  "properties": {
    "addr:full":"Seeblickstrasse 23 Degersheim St. Gallen 9113",
    "addr:housenumber":"23",
    "addr:postcode":"9113",
    "addr:street":"Seeblickstrasse",
    "iso:country":"CH",
    "sg:address":"Seeblickstrasse 23",
    "sg:city":"Degersheim",
    "sg:orig_category":"Datenverarbeitungsdienste Softwareentwicklung U beratung",
    "sg:phone":"+41 81 833 08 76",
    "sg:postcode":"9113",
    "sg:province":"St. Gallen",
    "wof:name":"Z\u00fcndel & Partner Systems Consultants Ag",
    "wof:placetype":"venue"
},
  "geometry": {"coordinates":[9.833292,46.498161],"type":"Point"}
}