{
  "type": "Feature",
  "properties": {
    "iso:country":"CH",
    "sg:address":"Riedstrasse 56",
    "sg:city":"Appenzell",
    "sg:orig_category":"Finanzierungsinstitutionen",
    "sg:postcode":"9050",
    "sg:province":"Appenzell Innerhoden",
    "wof:name":"Greho-ag",
    "wof:placetype":"venue"
},
  "geometry": {"coordinates":[9.4035263062,47.3281021118],"type":"Point"}
}