{
  "type": "Feature",
  "properties": {
    "addr:full":"Chemin De Chamb\u00e9sy 18 Chamb\u00e9sy Gen\u00e8ve 1292",
    "addr:housenumber":"18",
    "addr:postcode":"1292",
    "addr:street":"Chemin De Chambe\u0301Sy",
    "iso:country":"CH",
    "sg:address":"Chemin De Chamb\u00e9sy 18",
    "sg:city":"Chamb\u00e9sy",
    "sg:orig_category":"Benzin, Heiz\u00f6l and Mineral\u00f6lprodukte Grosshandel Grosshandel mit festen Brennstoffen U Mineral\u00f6lerze",
    "sg:phone":"+41 22 758 90 60",
    "sg:postcode":"1292",
    "sg:province":"Gen\u00e8ve",
    "wof:name":"Quimex Sa",
    "wof:placetype":"venue"
},
  "geometry": {"coordinates":[6.145952,46.243572],"type":"Point"}
}