{
  "type": "Feature",
  "properties": {
    "addr:full":"Bahnhofstrasse 2 Kerzers Fribourg 3210",
    "addr:housenumber":"2",
    "addr:postcode":"3210",
    "addr:street":"Bahnhofstrasse",
    "iso:country":"CH",
    "sg:address":"Bahnhofstrasse 2",
    "sg:city":"Kerzers",
    "sg:classifiers":[
        {
            "category":"Banks & Credit Unions",
            "subcategory":"Bank",
            "type":"Services"
        }
    ],
    "sg:phone":"+41 31 755 51 74",
    "sg:postcode":"3210",
    "sg:province":"Fribourg",
    "wof:name":"Freiburger Staatsbank",
    "wof:placetype":"venue"
},
  "geometry": {"coordinates":[7.194418,46.974995],"type":"Point"}
}