{
  "type": "Feature",
  "properties": {
    "addr:full":"Goutte-d'or Rue De La 13 2014 B\u00f4le. Postfach B\u00f4le Neuch\u00e2tel 2014",
    "addr:housenumber":"13",
    "addr:postcode":"2014;2014",
    "addr:street":"Rue De La",
    "iso:country":"CH",
    "sg:address":"Goutte-d'or Rue De La 13 2014 B\u00f4le. Postfach",
    "sg:city":"B\u00f4le",
    "sg:orig_category":"Architektur U Ingenieurb\u00fcros",
    "sg:phone":"+41 41 610 64 10",
    "sg:postcode":"2014",
    "sg:province":"Neuch\u00e2tel",
    "wof:name":"Mischol Bauingenieure Ag Ingenieurb\u00fcro F. Hoch- U. Tiefbau",
    "wof:placetype":"venue"
},
  "geometry": {"coordinates":[8.311101,46.986439],"type":"Point"}
}