{
  "type": "Feature",
  "properties": {
    "iso:country":"CH",
    "sg:address":"Kirchstrasse 1",
    "sg:city":"Grenchen",
    "sg:orig_category":"Unclassifiable Establishments",
    "sg:postcode":"2540",
    "sg:province":"Solothurn",
    "wof:name":"Vde De-tail Gmbh",
    "wof:placetype":"venue"
},
  "geometry": {"coordinates":[7.3955807686,47.1924247742],"type":"Point"}
}