{
  "type": "Feature",
  "properties": {
    "iso:country":"CH",
    "sg:address":"6000 Luzern. Postfach 4923",
    "sg:city":"Luzern",
    "sg:orig_category":"Grosshandel mit Software Softwareentwicklung U beratung",
    "sg:phone":"+41 41 310 38 81",
    "sg:postcode":"6002",
    "sg:province":"Luzern",
    "wof:name":"Ifob Gmbh",
    "wof:placetype":"venue"
},
  "geometry": {"coordinates":[8.3082399368,47.0456581116],"type":"Point"}
}