{
  "type": "Feature",
  "properties": {
    "iso:country":"CH",
    "sg:address":"Weber Avenue Th\u00e9odore- 15 1208 Gen\u00e8ve. Postfach",
    "sg:city":"Gen\u00e8ve",
    "sg:orig_category":"Forschung U Entwicklung im Bereich der Naturwissenschaften",
    "sg:postcode":"1208",
    "sg:province":"Gen\u00e8ve",
    "wof:name":"Groupe D'\u00e9tudes Spatiales",
    "wof:placetype":"venue"
},
  "geometry": {"coordinates":[6.1636161804,46.1987380981],"type":"Point"}
}