{
  "type": "Feature",
  "properties": {
    "addr:full":"Piazza Molino Nuovo 6 Lugano Ticino 6900",
    "addr:housenumber":"6",
    "addr:postcode":"6900",
    "addr:street":"Piazza Molino Nuovo",
    "iso:country":"CH",
    "sg:address":"Piazza Molino Nuovo 6",
    "sg:city":"Lugano",
    "sg:orig_category":"Ampoules",
    "sg:phone":"+41 91 923 60 68",
    "sg:postcode":"6900",
    "sg:province":"Ticino",
    "wof:name":"Consedil Sa",
    "wof:placetype":"venue"
},
  "geometry": {"coordinates":[8.955129,46.011997],"type":"Point"}
}