{
  "type": "Feature",
  "properties": {
    "iso:country":"CH",
    "sg:address":"Br\u00fchlweg 1",
    "sg:city":"Z\u00fcrich",
    "sg:orig_category":"Saunas, Solarien, Fitnesszentren U \u00e4hnliches Solarien",
    "sg:phone":"+41 13424142",
    "sg:postcode":"8049",
    "sg:province":"Z\u00fcrich",
    "wof:name":"Get Sun Gmbh",
    "wof:placetype":"venue"
},
  "geometry": {"coordinates":[8.4990310669,47.402973175],"type":"Point"}
}