{
  "type": "Feature",
  "properties": {
    "iso:country":"CH",
    "sg:address":"Lautengartenstrasse 8",
    "sg:city":"Basel",
    "sg:orig_category":"Wirtschaftspr\u00fcfung, Steuerberatung U Treuhand",
    "sg:phone":"+41 61 272 11 77",
    "sg:postcode":"4052",
    "sg:province":"Basel-Stadt",
    "wof:name":"Kym Ruedi",
    "wof:placetype":"venue"
},
  "geometry": {"coordinates":[7.5961089134,47.5529785156],"type":"Point"}
}