{
  "type": "Feature",
  "properties": {
    "iso:country":"CH",
    "sg:address":"Avenue De La Gare 36",
    "sg:city":"Monthey",
    "sg:orig_category":"Detailhandel mit Waren verschiedener Art, Hauptrichtung Nahrungsmittel Grosshandel mit Nahrungsmitte",
    "sg:phone":"+41 24 471 82 57",
    "sg:postcode":"1870",
    "sg:province":"Valais",
    "wof:name":"Pick Pay Betriebs Ag",
    "wof:placetype":"venue"
},
  "geometry": {"coordinates":[6.9517960548,46.2540359497],"type":"Point"}
}