{
  "type": "Feature",
  "properties": {
    "iso:country":"CH",
    "sg:address":"Solothurnstrasse 10",
    "sg:city":"Biberist",
    "sg:orig_category":"Detailhandel mit Bekleidung Detailhandel mit Brot, Back U S\u00fcsswaren",
    "sg:phone":"+41 32 672 46 68",
    "sg:postcode":"4562",
    "sg:province":"Solothurn",
    "wof:name":"Balmer Heinz",
    "wof:placetype":"venue"
},
  "geometry": {"coordinates":[7.557816,47.182816],"type":"Point"}
}