{
  "type": "Feature",
  "properties": {
    "iso:country":"CH",
    "sg:address":"Bruggwiesenstrasse 6",
    "sg:city":"Effretikon",
    "sg:orig_category":"D\u00e4mmung gegen K\u00e4lte, W\u00e4rme, Schall U Ersch\u00fctterung Herstellung von k\u00e4lte U lufttechnischen Erzeugnis",
    "sg:phone":"+41 52 343 05 01",
    "sg:postcode":"8307",
    "sg:province":"Z\u00fcrich",
    "wof:name":"Baracchi Isolationen",
    "wof:placetype":"venue"
},
  "geometry": {"coordinates":[8.6857318878,47.4267654419],"type":"Point"}
}