{
  "type": "Feature",
  "properties": {
    "iso:country":"CH",
    "sg:address":"Rheinsprung 16 4051 Basel. Postfach 1532",
    "sg:city":"Basel",
    "sg:orig_category":"Erziehungs\u00e4mter",
    "sg:phone":"+41 61 267 81 81",
    "sg:postcode":"4001",
    "sg:province":"Basel-Stadt",
    "wof:name":"St\u00e4dtisches Jugendamt Basel",
    "wof:placetype":"venue"
},
  "geometry": {"coordinates":[7.589179039,47.5586738586],"type":"Point"}
}