{
  "type": "Feature",
  "properties": {
    "iso:country":"CH",
    "sg:address":"Knobelstrasse 26",
    "sg:city":"Anglikon",
    "sg:orig_category":"Bauschreinerei",
    "sg:phone":"+41 56 622 13 53",
    "sg:postcode":"5611",
    "sg:province":"Aargau",
    "wof:name":"Peter M\u00e4der Schreinerei",
    "wof:placetype":"venue"
},
  "geometry": {"coordinates":[8.266171,47.365292],"type":"Point"}
}