{
  "type": "Feature",
  "properties": {
    "iso:country":"CH",
    "sg:address":"Bahnhofstrasse 12 4553 Subingen. Postfach 244",
    "sg:city":"Subingen",
    "sg:orig_category":"Detailhandel mit Schreib U Papeteriewaren Detailhandel mit Spielwaren",
    "sg:phone":"+41 32 614 32 89",
    "sg:postcode":"4553",
    "sg:province":"Solothurn",
    "wof:name":"Papeterie & Geschenke Flury Ag",
    "wof:placetype":"venue"
},
  "geometry": {"coordinates":[7.6129951477,47.1942329407],"type":"Point"}
}