{
  "type": "Feature",
  "properties": {
    "iso:country":"CH",
    "sg:address":"Pulverm\u00fchlestrasse 20 7000 Chur. Postfach",
    "sg:city":"Chur",
    "sg:orig_category":"Betrieb von Taxis",
    "sg:postcode":"7000",
    "sg:province":"Graubunden",
    "wof:name":"City Taxi, Cilek Baysun",
    "wof:placetype":"venue"
},
  "geometry": {"coordinates":[9.516613,46.852673],"type":"Point"}
}