{
  "type": "Feature",
  "properties": {
    "iso:country":"CH",
    "sg:address":"Allmendstr. 1 Pf 97",
    "sg:city":"Thun",
    "sg:classifiers":[
        {
            "category":"Food & Beverages",
            "subcategory":"Dairy",
            "type":"Retail Goods"
        }
    ],
    "sg:phone":"+41 33 227 55 55",
    "sg:postcode":"3602",
    "sg:province":"Bern",
    "sg:tags":[
        "product",
        "related"
    ],
    "wof:name":"Gerber Fromage Sa",
    "wof:placetype":"venue"
},
  "geometry": {"coordinates":[7.630185,46.756966],"type":"Point"}
}