{
  "type": "Feature",
  "properties": {
    "iso:country":"CH",
    "sg:address":"Baarerstrasse 12",
    "sg:city":"Zug",
    "sg:orig_category":"Non-Classified Establishments",
    "sg:postcode":"6300",
    "sg:province":"Zug",
    "wof:name":"Dr. Oec. Hans Peter Bieri Finanz Ag",
    "wof:placetype":"venue"
},
  "geometry": {"coordinates":[8.5164785385,47.1717300415],"type":"Point"}
}