{
  "type": "Feature",
  "properties": {
    "addr:full":"Lenzhard Schafisheim Aargau 5503",
    "addr:postcode":"5503",
    "addr:street":"Lenzhard",
    "iso:country":"CH",
    "sg:address":"Lenzhard",
    "sg:city":"Schafisheim",
    "sg:orig_category":"Allgemeiner Hoch U Tiefbau ohne ausgepr\u00e4gten Schwerpunkt",
    "sg:phone":"+41 62 886 21 21",
    "sg:postcode":"5503",
    "sg:province":"Aargau",
    "wof:name":"Autobahnwerkhof",
    "wof:placetype":"venue"
},
  "geometry": {"coordinates":[8.142759,47.376923],"type":"Point"}
}