{
  "type": "Feature",
  "properties": {
    "iso:country":"CH",
    "sg:address":"Neugasse 20 6300 Zug. Postfach",
    "sg:city":"Zug",
    "sg:orig_category":"Herstellung von sonstigen keramischen Erzeugnissen",
    "sg:phone":"+41 41 710 48 87",
    "sg:postcode":"6300",
    "sg:province":"Zug",
    "wof:name":"Ceramic Cafe Fl\u00fcckiger Sabrina Keramik-atelier",
    "wof:placetype":"venue"
},
  "geometry": {"coordinates":[8.5153150558,47.1666107178],"type":"Point"}
}