{
  "type": "Feature",
  "properties": {
    "iso:country":"CH",
    "sg:address":"Carri\u00e8res Rue Des 18 2800 Del\u00e9mont Case Postale 2209",
    "sg:city":"Del\u00e9mont",
    "sg:orig_category":"Stukkateurgewerbe, Gipserei U Verputzerei",
    "sg:phone":"+41 32 422 86 64",
    "sg:postcode":"2800",
    "sg:province":"Jura",
    "wof:name":"Macchi Elio & Fils Sa",
    "wof:placetype":"venue"
},
  "geometry": {"coordinates":[7.3585581779,47.3738059998],"type":"Point"}
}