{
  "type": "Feature",
  "properties": {
    "iso:country":"CH",
    "sg:address":"Baarerstrasse 11",
    "sg:city":"Zug",
    "sg:orig_category":"Arztpraxen",
    "sg:phone":"+41 41 711 88 42",
    "sg:postcode":"6300",
    "sg:province":"Zug",
    "wof:name":"Dr.med.beat Wicky Spezialarzt Fmh",
    "wof:placetype":"venue"
},
  "geometry": {"coordinates":[8.516021,47.171532],"type":"Point"}
}