{
  "type": "Feature",
  "properties": {
    "iso:country":"CH",
    "sg:address":"Gasterstrasse 6",
    "sg:city":"Kaltbrunn",
    "sg:orig_category":"Zimmerei, Dachdeckerei, Bauspenglerei U Abdichtung Zimmerei, Ingenieurholzbau",
    "sg:phone":"+41 55 283 29 35",
    "sg:postcode":"8722",
    "sg:province":"St. Gallen",
    "wof:name":"Helbling Peter, Holzbau",
    "wof:placetype":"venue"
},
  "geometry": {"coordinates":[9.0262508392,47.2123985291],"type":"Point"}
}