{
  "type": "Feature",
  "properties": {
    "iso:country":"CH",
    "sg:address":"Solothurnerstrasse 10",
    "sg:city":"H\u00e4gendorf",
    "sg:orig_category":"Detailhandel mit Boden U Wandbel\u00e4gen ohne Teppiche Verlegen von Fussboden",
    "sg:phone":"+41 62 216 21 30",
    "sg:postcode":"4614",
    "sg:province":"Solothurn",
    "wof:name":"Ermano N\u00fcnlist Bodenbel\u00e4ge",
    "wof:placetype":"venue"
},
  "geometry": {"coordinates":[7.841965,47.332661],"type":"Point"}
}