{
  "type": "Feature",
  "properties": {
    "iso:country":"CH",
    "sg:address":"Dorfstrasse 17",
    "sg:city":"Ebikon",
    "sg:orig_category":"Unclassifiable Establishments",
    "sg:phone":"+41 65452448",
    "sg:postcode":"6030",
    "sg:province":"Luzern",
    "wof:name":"Mediaberatung Crescendo, Sommer Heinz",
    "wof:placetype":"venue"
},
  "geometry": {"coordinates":[7.5584158897,47.1529693604],"type":"Point"}
}