{
  "type": "Feature",
  "properties": {
    "iso:country":"CH",
    "sg:address":"Rte De Vaudigny",
    "sg:city":"Lugnorre",
    "sg:orig_category":"Vermietung U Verpachtung von eigenen Immobilien",
    "sg:postcode":"1789",
    "sg:province":"Fribourg",
    "wof:name":"S.i. Chemin Des Cygnes 49 Sa",
    "wof:placetype":"venue"
},
  "geometry": {"coordinates":[7.0823712349,46.947933197],"type":"Point"}
}