{
  "type": "Feature",
  "properties": {
    "iso:country":"CH",
    "sg:address":"Seehaldenstrasse 12",
    "sg:city":"Steckborn",
    "sg:orig_category":"Sportvereine Turnen Vereine Damen",
    "sg:phone":"+41 52 761 12 40",
    "sg:postcode":"8266",
    "sg:province":"Thurgau",
    "wof:name":"Frauenturnverein Steckborn",
    "wof:placetype":"venue"
},
  "geometry": {"coordinates":[8.9916191101,47.6675491333],"type":"Point"}
}