{
  "type": "Feature",
  "properties": {
    "iso:country":"CH",
    "sg:address":"Unterwienacht 451",
    "sg:city":"Wienacht-tobel",
    "sg:classifiers":[
        {
            "category":"Restaurant",
            "type":"Food & Drink"
        }
    ],
    "sg:phone":"+41 71 891 21 61",
    "sg:postcode":"9405",
    "sg:province":"Appenzell Ausserrhoden",
    "wof:name":"Restaurant Treichli",
    "wof:placetype":"venue"
},
  "geometry": {"coordinates":[9.5425100327,47.464756012],"type":"Point"}
}