{
  "type": "Feature",
  "properties": {
    "iso:country":"CH",
    "sg:address":"Johann-renfer-str. 58",
    "sg:city":"Biel/bienne",
    "sg:classifiers":[
        {
            "category":"Professional",
            "subcategory":"Engineering",
            "type":"Services"
        }
    ],
    "sg:phone":"+41 52 646 02 20",
    "sg:postcode":"2504",
    "sg:province":"Bern",
    "sg:tags":[
        "machine",
        "-",
        "mechanical"
    ],
    "wof:name":"Wemo Ger\u00c4te Ag Mobile K\u00c4lte",
    "wof:placetype":"venue"
},
  "geometry": {"coordinates":[8.7044019699,47.6635932922],"type":"Point"}
}