{
  "type": "Feature",
  "properties": {
    "iso:country":"CH",
    "sg:address":"Ennetb\u00fcrgerstrasse 10 6374 Buochs. Postfach 342",
    "sg:city":"Buochs",
    "sg:classifiers":[
        {
            "category":"Restaurant",
            "type":"Food & Drink"
        }
    ],
    "sg:phone":"+41 22 342 11 80",
    "sg:postcode":"6374",
    "sg:province":"Nidwalden",
    "wof:name":"Caf\u00e9-rest. Equinoxe",
    "wof:placetype":"venue"
},
  "geometry": {"coordinates":[6.1402378082,46.1866264343],"type":"Point"}
}