{
  "type": "Feature",
  "properties": {
    "iso:country":"CH",
    "sg:address":"M\u00e4tteli 134",
    "sg:city":"Olsberg",
    "sg:orig_category":"Herstellung von Textilbekleidung Textilveredlung",
    "sg:phone":"+41 61 841 27 25",
    "sg:postcode":"4305",
    "sg:province":"Aargau",
    "wof:name":"Seidenmalatelier Seidenmalkurse",
    "wof:placetype":"venue"
},
  "geometry": {"coordinates":[7.7880330086,47.5224494934],"type":"Point"}
}