{
  "type": "Feature",
  "properties": {
    "iso:country":"CH",
    "sg:address":"Chemin De La Colice 2",
    "sg:city":"Crissier",
    "sg:orig_category":"Sportvereine Billard",
    "sg:phone":"+41 21 635 68 00",
    "sg:postcode":"1023",
    "sg:province":"Vaud",
    "wof:name":"Ma Boule Billard-club",
    "wof:placetype":"venue"
},
  "geometry": {"coordinates":[6.5700201988,46.5602607727],"type":"Point"}
}