{
  "type": "Feature",
  "properties": {
    "iso:country":"CH",
    "sg:address":"Technikumstrasse 3 8400 Winterthur. Postfach 929",
    "sg:city":"Winterthur",
    "sg:orig_category":"Grosshandel mit Eisenwaren sowie Installationsbedarf f\u00fcr Gas, Wasser U Heizung Grosshandel mit sonst",
    "sg:phone":"+41 52 212 90 80",
    "sg:postcode":"8401",
    "sg:province":"Z\u00fcrich",
    "wof:name":"Haus L. Ag",
    "wof:placetype":"venue"
},
  "geometry": {"coordinates":[8.731880188,47.497543335],"type":"Point"}
}