{
  "type": "Feature",
  "properties": {
    "iso:country":"CH",
    "sg:address":"Rosentalstrasse 22",
    "sg:city":"Basel",
    "sg:orig_category":"Detailhandel mit Waren verschiedener Art, Hauptrichtung Nahrungsmittel Grosshandel mit Nahrungsmitte",
    "sg:phone":"+41 81 833 34 50",
    "sg:postcode":"4058",
    "sg:province":"Basel-Stadt",
    "wof:name":"Bornatico Giovanni.",
    "wof:placetype":"venue"
},
  "geometry": {"coordinates":[9.8398723602,46.4989433289],"type":"Point"}
}