{
  "type": "Feature",
  "properties": {
    "iso:country":"CH",
    "sg:address":"Campingstrasse 7",
    "sg:city":"B\u00f6nigen",
    "sg:orig_category":"Sonstige pers\u00f6nliche Dienstleistungen",
    "sg:phone":"+41 33 822 46 25",
    "sg:postcode":"3806",
    "sg:province":"Bern",
    "wof:name":"M\u00fchlemann Daniel, Beratungen",
    "wof:placetype":"venue"
},
  "geometry": {"coordinates":[7.8931708336,46.6902618408],"type":"Point"}
}