{
  "type": "Feature",
  "properties": {
    "iso:country":"CH",
    "sg:address":"Rankstrasse 7",
    "sg:city":"Endingen",
    "sg:orig_category":"Wirtschaftspr\u00fcfung, Steuerberatung U Treuhand",
    "sg:postcode":"5304",
    "sg:province":"Aargau",
    "wof:name":"Controlling & Organisation Lanter",
    "wof:placetype":"venue"
},
  "geometry": {"coordinates":[8.2889060974,47.5384635925],"type":"Point"}
}