{
  "type": "Feature",
  "properties": {
    "iso:country":"CH",
    "sg:address":"Z\u00fcgstrasse 30",
    "sg:city":"Engelberg",
    "sg:orig_category":"Interessenvertretungen",
    "sg:postcode":"6390",
    "sg:province":"Obwalden",
    "wof:name":"Strassen Und Kanalisationsgenossenschaft Fellenr\u00fcti Und Z\u00fcg, Engelberg",
    "wof:placetype":"venue"
},
  "geometry": {"coordinates":[8.3962202072,46.8263702393],"type":"Point"}
}