{
  "type": "Feature",
  "properties": {
    "addr:full":"Rohrmattstrasse 9 G\u00fcmligen Bern 3073",
    "addr:housenumber":"9",
    "addr:postcode":"3073",
    "addr:street":"Rohrmattstrasse",
    "iso:country":"CH",
    "sg:address":"Rohrmattstrasse 9",
    "sg:city":"G\u00fcmligen",
    "sg:orig_category":"Architektur U Ingenieurb\u00fcros",
    "sg:phone":"+41 31 952 72 50",
    "sg:postcode":"3073",
    "sg:province":"Bern",
    "wof:name":"Binder Engineering Ag",
    "wof:placetype":"venue"
},
  "geometry": {"coordinates":[7.506609,46.932003],"type":"Point"}
}