{
  "type": "Feature",
  "properties": {
    "iso:country":"CH",
    "sg:address":"Metzgergasse 21",
    "sg:city":"Burgdorf",
    "sg:orig_category":"Erbringung von Dienstleistungen f\u00fcr Unternehmen",
    "sg:phone":"+41 34 423 36 01",
    "sg:postcode":"3400",
    "sg:province":"Bern",
    "wof:name":"Team Interieur, Bracher Marianna Und Ruch Ursula",
    "wof:placetype":"venue"
},
  "geometry": {"coordinates":[7.6254000664,47.056804657],"type":"Point"}
}