{
  "type": "Feature",
  "properties": {
    "iso:country":"CH",
    "sg:address":"L\u00f6wengasse 15",
    "sg:city":"Solothurn",
    "sg:orig_category":"Erbringung von Dienstleistungen f\u00fcr Unternehmen",
    "sg:postcode":"4500",
    "sg:province":"Solothurn",
    "wof:name":"Ridesign, Rietzler Willi",
    "wof:placetype":"venue"
},
  "geometry": {"coordinates":[9.4882335663,47.1484375],"type":"Point"}
}