{
  "type": "Feature",
  "properties": {
    "iso:country":"CH",
    "sg:address":"R\u00fcderswilschachen 3436 Zollbr\u00fcck. Postfach",
    "sg:city":"Zollbr\u00fcck",
    "sg:orig_category":"Sonstiger spezialisierter Hoch U Tiefbau",
    "sg:phone":"+41 31 711 03 96",
    "sg:postcode":"3436",
    "sg:province":"Bern",
    "wof:name":"Gerag, Ger\u00fcstebau Ag",
    "wof:placetype":"venue"
},
  "geometry": {"coordinates":[7.7382760048,46.9745826721],"type":"Point"}
}