{
  "type": "Feature",
  "properties": {
    "iso:country":"CH",
    "sg:address":"Buchserstrasse 29 8108 D\u00e4llikon. Postfach",
    "sg:city":"D\u00e4llikon",
    "sg:orig_category":"Herstellung von Kunststoff in Prim\u00e4rformen",
    "sg:postcode":"8108",
    "sg:province":"Z\u00fcrich",
    "wof:name":"Frey & S\u00f6hne, K.",
    "wof:placetype":"venue"
},
  "geometry": {"coordinates":[8.4382610321,47.4478187561],"type":"Point"}
}