{
  "type": "Feature",
  "properties": {
    "iso:country":"CH",
    "sg:address":"Spychertenstrasse 41",
    "sg:city":"Hilterfingen",
    "sg:orig_category":"Elektroinstallation",
    "sg:phone":"+41 33 243 07 30",
    "sg:postcode":"3652",
    "sg:province":"Bern",
    "wof:name":"Urfer Montagen",
    "wof:placetype":"venue"
},
  "geometry": {"coordinates":[7.6620287895,46.7378158569],"type":"Point"}
}