{
  "type": "Feature",
  "properties": {
    "iso:country":"CH",
    "sg:address":"Seestrasse 59",
    "sg:city":"St\u00e4fa",
    "sg:orig_category":"Non-Classified Establishments",
    "sg:phone":"+41 19261340",
    "sg:postcode":"8712",
    "sg:province":"Z\u00fcrich",
    "wof:name":"Gasthof Frohsinn",
    "wof:placetype":"venue"
},
  "geometry": {"coordinates":[8.7194519043,47.2391815186],"type":"Point"}
}