{
  "type": "Feature",
  "properties": {
    "iso:country":"CH",
    "sg:address":"Im Sunneb\u00fcel 11",
    "sg:city":"Thalwil",
    "sg:orig_category":"Softwareentwicklung U beratung",
    "sg:phone":"+41 17207668",
    "sg:postcode":"8800",
    "sg:province":"Z\u00fcrich",
    "wof:name":"N\u00f6sberger Marcel",
    "wof:placetype":"venue"
},
  "geometry": {"coordinates":[8.5588283539,47.2951965332],"type":"Point"}
}