{
  "type": "Feature",
  "properties": {
    "iso:country":"CH",
    "sg:address":"Zona Industriale",
    "sg:city":"Bedano",
    "sg:orig_category":"Herstellung von Maschinen f\u00fcr die Textil, Bekleidungsherstellung U die Lederverarbeitung Herstellung",
    "sg:phone":"+41 71 763 80 40",
    "sg:postcode":"6930",
    "sg:province":"Ticino",
    "wof:name":"Textronica Ag",
    "wof:placetype":"venue"
},
  "geometry": {"coordinates":[9.567905426,47.3295936584],"type":"Point"}
}