{
  "type": "Feature",
  "properties": {
    "iso:country":"CH",
    "sg:address":"Rue Centrale 20 1000 Lausanne. Postfach",
    "sg:city":"Lausanne",
    "sg:orig_category":"Versandhandel",
    "sg:postcode":"1003",
    "sg:province":"Vaud",
    "wof:name":"Obsession, Jeantet Eric",
    "wof:placetype":"venue"
},
  "geometry": {"coordinates":[6.6344861984,46.5207290649],"type":"Point"}
}