{
  "type": "Feature",
  "properties": {
    "iso:country":"CH",
    "sg:address":"Oberwiesenstrasse 5 8057 Z\u00fcrich. Postfach 196",
    "sg:city":"Z\u00fcrich",
    "sg:orig_category":"Reiseb\u00fcros U Reiseveranstalter",
    "sg:phone":"+41 13638821",
    "sg:postcode":"8057",
    "sg:province":"Z\u00fcrich",
    "wof:name":"Untra Trade Und Travel Ag",
    "wof:placetype":"venue"
},
  "geometry": {"coordinates":[8.5310344696,47.4079551697],"type":"Point"}
}