{
  "type": "Feature",
  "properties": {
    "iso:country":"CH",
    "sg:address":"Via Giulia 12a",
    "sg:city":"Stabio",
    "sg:orig_category":"Bauspenglerei Dachdeckerei",
    "sg:phone":"+41 91 647 25 18",
    "sg:postcode":"6855",
    "sg:province":"Ticino",
    "wof:name":"Torti Germano.",
    "wof:placetype":"venue"
},
  "geometry": {"coordinates":[8.938644,45.850365],"type":"Point"}
}