{
  "type": "Feature",
  "properties": {
    "iso:country":"CH",
    "sg:address":"Im Hogeracker",
    "sg:city":"B\u00fcttenhardt",
    "sg:orig_category":"Primarschulen",
    "sg:postcode":"8236",
    "sg:province":"Schaffhausen",
    "wof:name":"Primarschule B\u00fctzi",
    "wof:placetype":"venue"
},
  "geometry": {"coordinates":[8.6840496063,47.300491333],"type":"Point"}
}