{
  "type": "Feature",
  "properties": {
    "iso:country":"CH",
    "sg:address":"Schulhausstrasse 314",
    "sg:city":"Rohrbach",
    "sg:orig_category":"Nationale Postdienste",
    "sg:phone":"+41 56 633 13 36",
    "sg:postcode":"4938",
    "sg:province":"Bern",
    "wof:name":"Die Schweizerische Post",
    "wof:placetype":"venue"
},
  "geometry": {"coordinates":[8.3871650696,47.3362808228],"type":"Point"}
}