{
  "type": "Feature",
  "properties": {
    "iso:country":"CH",
    "sg:address":"Hauptstrasse 73",
    "sg:city":"Menziken",
    "sg:orig_category":"Detailhandel mit Bekleidung",
    "sg:postcode":"5737",
    "sg:province":"Aargau",
    "wof:name":"Mode Bas, Import, Export",
    "wof:placetype":"venue"
},
  "geometry": {"coordinates":[8.189396,47.238754],"type":"Point"}
}