{
  "type": "Feature",
  "properties": {
    "iso:country":"CH",
    "sg:address":"Les Hirondelles",
    "sg:city":"Penthaz",
    "sg:orig_category":"Geb\u00e4ude, Wohnungsreinigung",
    "sg:phone":"+41 21 862 73 57",
    "sg:postcode":"1303",
    "sg:province":"Vaud",
    "wof:name":"Ren\u00e9 Dovat Nettoyages Erd\u00e9",
    "wof:placetype":"venue"
},
  "geometry": {"coordinates":[6.5384898186,46.5996818542],"type":"Point"}
}