{
  "type": "Feature",
  "properties": {
    "iso:country":"CH",
    "sg:address":"Bruggerstrasse 117",
    "sg:city":"Baden",
    "sg:orig_category":"Detailhandel mit Antiquit\u00e4ten U Gebrauchtwaren in Verkaufsr\u00e4umen",
    "sg:postcode":"5400",
    "sg:province":"Aargau",
    "wof:name":"Renigreni Gr\u00e4nacher's Chi-ma",
    "wof:placetype":"venue"
},
  "geometry": {"coordinates":[8.292877,47.483238],"type":"Point"}
}