{
  "type": "Feature",
  "properties": {
    "iso:country":"CH",
    "sg:address":"Schmiedgasse 56 9102 Herisau. Postfach",
    "sg:city":"Herisau",
    "sg:orig_category":"Unternehmensberatung",
    "sg:postcode":"9102",
    "sg:province":"Appenzell Ausserrhoden",
    "wof:name":"Steinhauer Mathias, Organisationsberatung, Coaching Und Supervision",
    "wof:placetype":"venue"
},
  "geometry": {"coordinates":[9.2764396667,47.3836631775],"type":"Point"}
}