{
  "type": "Feature",
  "properties": {
    "iso:country":"CH",
    "sg:address":"Seestrasse 3",
    "sg:city":"Zug",
    "sg:classifiers":[
        {
            "category":"Bars & Pubs",
            "type":"Food & Drink"
        }
    ],
    "sg:phone":"+41 71 222 23 65",
    "sg:postcode":"6300",
    "sg:province":"Zug",
    "sg:tags":[
        "restaurant"
    ],
    "wof:name":"Restaurant Hardy's",
    "wof:placetype":"venue"
},
  "geometry": {"coordinates":[9.377757,47.425797],"type":"Point"}
}