{
  "type": "Feature",
  "properties": {
    "iso:country":"CH",
    "sg:address":"9477",
    "sg:city":"Tr\u00fcbbach",
    "sg:orig_category":"Detailhandel mit Waren verschiedener Art, Hauptrichtung Nahrungsmittel",
    "sg:phone":"+41 81 783 11 33",
    "sg:postcode":"9477",
    "sg:province":"St. Gallen",
    "wof:name":"Coop Center",
    "wof:placetype":"venue"
},
  "geometry": {"coordinates":[9.4787502289,47.071018219],"type":"Point"}
}