{
  "type": "Feature",
  "properties": {
    "iso:country":"CH",
    "sg:address":"Musterplatzweg 6",
    "sg:city":"Langenthal",
    "sg:orig_category":"Allgemeiner Gartenbau Gem\u00fcsebau",
    "sg:phone":"+41 62 922 27 73",
    "sg:postcode":"4900",
    "sg:province":"Bern",
    "wof:name":"Erich Kuert",
    "wof:placetype":"venue"
},
  "geometry": {"coordinates":[7.800551,47.213665],"type":"Point"}
}