{
  "type": "Feature",
  "properties": {
    "iso:country":"CH",
    "sg:address":"Bernstrasse 6",
    "sg:city":"Herzogenbuchsee",
    "sg:orig_category":"Elektroinstallation",
    "sg:phone":"+41 62 961 50 51",
    "sg:postcode":"3360",
    "sg:province":"Bern",
    "wof:name":"Elektro Gygax Ag",
    "wof:placetype":"venue"
},
  "geometry": {"coordinates":[7.705160141,47.1878433228],"type":"Point"}
}