{
  "type": "Feature",
  "properties": {
    "addr:full":"Grienbachstrasse 17 6300 Zug. Postfach Zug Zug 6300",
    "addr:housenumber":"17",
    "addr:postcode":"6300;postfach;6300",
    "addr:street":"Grienbachstrasse;Zug",
    "iso:country":"CH",
    "sg:address":"Grienbachstrasse 17 6300 Zug. Postfach",
    "sg:city":"Zug",
    "sg:orig_category":"Architektur U Ingenieurb\u00fcros",
    "sg:postcode":"6300",
    "sg:province":"Zug",
    "wof:name":"Thomann Th., Dipl. Ing. Eth & Sia, Ingenieurbureau",
    "wof:placetype":"venue"
},
  "geometry": {"coordinates":[7.75759,46.949127],"type":"Point"}
}