{
  "type": "Feature",
  "properties": {
    "iso:country":"CH",
    "sg:address":"Kirchbergstrasse 84",
    "sg:city":"Lyssach",
    "sg:orig_category":"Vermittlung von Immobilien",
    "sg:phone":"+41 34 445 72 60",
    "sg:postcode":"3421",
    "sg:province":"Bern",
    "wof:name":"Affolter Immobilien",
    "wof:placetype":"venue"
},
  "geometry": {"coordinates":[7.5828142166,47.0764541626],"type":"Point"}
}