{
  "type": "Feature",
  "properties": {
    "iso:country":"CH",
    "sg:address":"Pfaffenweg 17",
    "sg:city":"Niedererlinsbach",
    "sg:orig_category":"Sportvereine Orientierungslauf",
    "sg:phone":"+41 62 844 15 32",
    "sg:postcode":"5015",
    "sg:province":"Solothurn",
    "wof:name":"Olg Atv Suhr",
    "wof:placetype":"venue"
},
  "geometry": {"coordinates":[8.0029535294,47.3930625916],"type":"Point"}
}