{
  "type": "Feature",
  "properties": {
    "iso:country":"CH",
    "sg:address":"Geerenstrasse 8",
    "sg:city":"Dielsdorf",
    "sg:orig_category":"Sanit\u00e4r U Heizungsinstallation",
    "sg:phone":"+41 18531767",
    "sg:postcode":"8157",
    "sg:province":"Z\u00fcrich",
    "wof:name":"Heinrich Osterwalder Zentralheizungen",
    "wof:placetype":"venue"
},
  "geometry": {"coordinates":[8.4575996399,47.4809074402],"type":"Point"}
}