{
  "type": "Feature",
  "properties": {
    "iso:country":"CH",
    "sg:address":"St\u00e4nzlergasse 7 4051 Basel. Postfach",
    "sg:city":"Basel",
    "sg:orig_category":"Sonstige pers\u00f6nliche Dienstleistungen",
    "sg:postcode":"4051",
    "sg:province":"Basel-Stadt",
    "wof:name":"Executive Search Partners Dietrich & Falbriard Dienstl. Im Personalsektor",
    "wof:placetype":"venue"
},
  "geometry": {"coordinates":[7.5895061493,47.5526351929],"type":"Point"}
}