{
  "type": "Feature",
  "properties": {
    "iso:country":"CH",
    "sg:address":"Rainweg 1",
    "sg:city":"M\u00e4genwil",
    "sg:orig_category":"Bau U Wohngenossenschaften Interessenvertretungen",
    "sg:phone":"+41 62 896 07 77",
    "sg:postcode":"5506",
    "sg:province":"Aargau",
    "wof:name":"Tr\u00e4gerverein F\u00fcr Alterswohnungen M\u00e4genwil",
    "wof:placetype":"venue"
},
  "geometry": {"coordinates":[8.229772,47.409897],"type":"Point"}
}