{
  "type": "Feature",
  "properties": {
    "iso:country":"CH",
    "sg:address":"Hegenheimerstrasse 62",
    "sg:city":"Basel",
    "sg:orig_category":"Lichtpause U Reprografiebetriebe Sonstiges Druckgewerbe",
    "sg:phone":"+41 61 381 66 60",
    "sg:postcode":"4055",
    "sg:province":"Basel-Stadt",
    "wof:name":"Ag Vormals Braun Peter Lichtpausanstalt",
    "wof:placetype":"venue"
},
  "geometry": {"coordinates":[7.5707001686,47.5609321594],"type":"Point"}
}