{
  "type": "Feature",
  "properties": {
    "iso:country":"CH",
    "sg:address":"Sot Baselgia 27",
    "sg:city":"Ramosch",
    "sg:orig_category":"Schlossereien",
    "sg:phone":"+41 81 866 33 82",
    "sg:postcode":"7556",
    "sg:province":"Graubunden",
    "wof:name":"Domenic Tonas Schlosserei",
    "wof:placetype":"venue"
},
  "geometry": {"coordinates":[10.3827981949,46.8339996338],"type":"Point"}
}