{
  "type": "Feature",
  "properties": {
    "iso:country":"CH",
    "sg:address":"Dettenriederstrasse 1",
    "sg:city":"Weisslingen",
    "sg:orig_category":"Hardwareberatung",
    "sg:phone":"+41 52 384 25 57",
    "sg:postcode":"8484",
    "sg:province":"Z\u00fcrich",
    "wof:name":"Comgraf Weisslingen, Bruno K\u00fcndig",
    "wof:placetype":"venue"
},
  "geometry": {"coordinates":[8.7639493942,47.4322280884],"type":"Point"}
}