{
  "type": "Feature",
  "properties": {
    "iso:country":"CH",
    "sg:address":"Zopfstrasse 3",
    "sg:city":"Adliswil",
    "sg:orig_category":"Bau von Strassen, Sportanlagen U Bahnverkehrsstrecken",
    "sg:phone":"+41 17090211",
    "sg:postcode":"8134",
    "sg:province":"Z\u00fcrich",
    "wof:name":"Vonplon R. Ag",
    "wof:placetype":"venue"
},
  "geometry": {"coordinates":[8.516881,47.316631],"type":"Point"}
}