{
  "type": "Feature",
  "properties": {
    "iso:country":"CH",
    "sg:address":"Bernstrasse 27 3052 Zollikofen. Postfach",
    "sg:city":"Zollikofen",
    "sg:orig_category":"Handelsvermittlung U Grosshandel Herstellung von sonstigen Maschinen f\u00fcr unspezifische Verwendung",
    "sg:phone":"+41 31 911 36 26",
    "sg:postcode":"3052",
    "sg:province":"Bern",
    "wof:name":"Schrag Feuerschutz Ag",
    "wof:placetype":"venue"
},
  "geometry": {"coordinates":[7.4569392204,46.9858894348],"type":"Point"}
}