{
  "type": "Feature",
  "properties": {
    "iso:country":"CH",
    "sg:address":"Gassaura 7317 Valens. Postfach",
    "sg:city":"Valens",
    "sg:orig_category":"Allgemeiner Hoch U Tiefbau",
    "sg:phone":"+41 81 302 27 23",
    "sg:postcode":"7317",
    "sg:province":"St. Gallen",
    "wof:name":"David Riederer",
    "wof:placetype":"venue"
},
  "geometry": {"coordinates":[9.478348,46.967976],"type":"Point"}
}