{
  "type": "Feature",
  "properties": {
    "iso:country":"CH",
    "sg:address":"T\u00e4gernstrasse 15",
    "sg:city":"Maur",
    "sg:orig_category":"Grosshandel mit Holz U Baustoffen",
    "sg:phone":"+41 71 911 75 75",
    "sg:postcode":"8124",
    "sg:province":"Z\u00fcrich",
    "wof:name":"Mayer Jakob A. Zedernpark",
    "wof:placetype":"venue"
},
  "geometry": {"coordinates":[9.042429924,47.4672279358],"type":"Point"}
}