{
  "type": "Feature",
  "properties": {
    "iso:country":"CH",
    "sg:address":"8868 Oberurnen. Postfach",
    "sg:city":"Oberurnen",
    "sg:orig_category":"Detailhandel mit Antiquit\u00e4ten U Gebrauchtwaren in Verkaufsr\u00e4umen",
    "sg:phone":"+41 55 610 31 60",
    "sg:postcode":"8868",
    "sg:province":"Glarus",
    "wof:name":"Kieni Otto",
    "wof:placetype":"venue"
},
  "geometry": {"coordinates":[9.05934,47.115208],"type":"Point"}
}