{
  "type": "Feature",
  "properties": {
    "iso:country":"CH",
    "sg:address":"Gubelstrasse 15",
    "sg:city":"Zug",
    "sg:orig_category":"Sonstige Finanzierungsinstitutionen",
    "sg:phone":"+41 41 720 06 55",
    "sg:postcode":"6300",
    "sg:province":"Zug",
    "wof:name":"Gay Freres Holding Sa",
    "wof:placetype":"venue"
},
  "geometry": {"coordinates":[8.5168743134,47.1744041443],"type":"Point"}
}