{
  "type": "Feature",
  "properties": {
    "iso:country":"CH",
    "sg:address":"Mangelegg 121",
    "sg:city":"Schwyz",
    "sg:orig_category":"Detailhandel mit M\u00f6beln U Haushaltsgegenst\u00e4nden Detailhandel mit Teppichen",
    "sg:phone":"+41 41 810 01 84",
    "sg:postcode":"6430",
    "sg:province":"Schwyz",
    "wof:name":"Bruno Ulrich",
    "wof:placetype":"venue"
},
  "geometry": {"coordinates":[8.6542034149,47.0286521912],"type":"Point"}
}