{
  "type": "Feature",
  "properties": {
    "iso:country":"CH",
    "sg:address":"Br\u00fcggli",
    "sg:city":"Sattel",
    "sg:orig_category":"Abwasserreinigung",
    "sg:phone":"+41 41 835 15 12",
    "sg:postcode":"6417",
    "sg:province":"Schwyz",
    "wof:name":"Kl\u00e4ranlage",
    "wof:placetype":"venue"
},
  "geometry": {"coordinates":[8.625316,47.075924],"type":"Point"}
}