{
  "type": "Feature",
  "properties": {
    "iso:country":"CH",
    "sg:address":"6802 Rivera Casella Postale",
    "sg:city":"Rivera",
    "sg:orig_category":"G\u00fcterbef\u00f6rderung im Strassenverkehr Lagerung",
    "sg:phone":"+41 91 946 25 61",
    "sg:postcode":"6802",
    "sg:province":"Ticino",
    "wof:name":"Richina Cargo Sa",
    "wof:placetype":"venue"
},
  "geometry": {"coordinates":[8.9231395721,46.1164894104],"type":"Point"}
}