{
  "type": "Feature",
  "properties": {
    "iso:country":"CH",
    "sg:address":"Pr\u00e9 Rond 22",
    "sg:city":"Malleray",
    "sg:orig_category":"Erdbewegungsarbeiten G\u00fcterbef\u00f6rderung im Strassenverkehr",
    "sg:phone":"+41 27 207 26 33",
    "sg:postcode":"2735",
    "sg:province":"Bern",
    "wof:name":"Pierre Pitteloud Entreprise De Terrassement & Transports Sa",
    "wof:placetype":"venue"
},
  "geometry": {"coordinates":[7.3746399879,46.2108612061],"type":"Point"}
}