{
  "type": "Feature",
  "properties": {
    "addr:full":"Feldblumenstrasse 87 Adliswil Z\u00fcrich 8134",
    "addr:housenumber":"87",
    "addr:postcode":"8134",
    "addr:street":"Feldblumenstrasse",
    "iso:country":"CH",
    "sg:address":"Feldblumenstrasse 87",
    "sg:city":"Adliswil",
    "sg:orig_category":"Allgemeiner Gartenbau",
    "sg:phone":"+41 17106464",
    "sg:postcode":"8134",
    "sg:province":"Z\u00fcrich",
    "wof:name":"Daniel Br\u00fchwiler Gartenbau & Baumpflege",
    "wof:placetype":"venue"
},
  "geometry": {"coordinates":[8.514694,47.317036],"type":"Point"}
}