{
  "type": "Feature",
  "properties": {
    "iso:country":"CH",
    "sg:address":"Waldhofstrasse 74",
    "sg:city":"Langenthal",
    "sg:orig_category":"Wirtschaftspr\u00fcfung, Steuerberatung U Treuhand",
    "sg:phone":"+41 62 923 22 09",
    "sg:postcode":"4900",
    "sg:province":"Bern",
    "wof:name":"M & G Consulting Gmbh",
    "wof:placetype":"venue"
},
  "geometry": {"coordinates":[7.7981557846,47.2170715332],"type":"Point"}
}