{
  "type": "Feature",
  "properties": {
    "iso:country":"CH",
    "sg:address":"Forchstrasse 10",
    "sg:city":"Uster",
    "sg:orig_category":"Druck ohne Zeitungsdruck Werbegrafikateliers",
    "sg:postcode":"8610",
    "sg:province":"Z\u00fcrich",
    "wof:name":"Martin Bolt Bolt Graphix Artwork And Prepress",
    "wof:placetype":"venue"
},
  "geometry": {"coordinates":[8.7124300003,47.3473396301],"type":"Point"}
}