{
  "type": "Feature",
  "properties": {
    "iso:country":"CH",
    "sg:address":"Etzelstrasse 26",
    "sg:city":"Hombrechtikon",
    "sg:classifiers":[
        {
            "category":"Restaurant",
            "type":"Food & Drink"
        }
    ],
    "sg:phone":"+41 55 244 42 12",
    "sg:postcode":"8634",
    "sg:province":"Z\u00fcrich",
    "wof:name":"Restaurant Eichwies",
    "wof:placetype":"venue"
},
  "geometry": {"coordinates":[8.7801799774,47.2492904663],"type":"Point"}
}