{
  "type": "Feature",
  "properties": {
    "iso:country":"CH",
    "sg:address":"Badstrasse 1 6210 Sursee. Postfach 47",
    "sg:city":"Sursee",
    "sg:orig_category":"Detailhandel mit B\u00fcromaschinen U einrichtungen Detailhandel mit elektrischen Haushalts-,Radio U Fern",
    "sg:phone":"+41 41 921 32 52",
    "sg:postcode":"6210",
    "sg:province":"Luzern",
    "wof:name":"Sidler Josef Ag",
    "wof:placetype":"venue"
},
  "geometry": {"coordinates":[8.111856,47.170815],"type":"Point"}
}