{
  "type": "Feature",
  "properties": {
    "iso:country":"CH",
    "sg:address":"Rue Du Midi 11",
    "sg:city":"Aigle",
    "sg:orig_category":"Zahntechnische Laboratorien",
    "sg:phone":"+41 24 466 41 39",
    "sg:postcode":"1860",
    "sg:province":"Vaud",
    "wof:name":"Dominique Page Labor.de Proth\u00e8ses Dentaires",
    "wof:placetype":"venue"
},
  "geometry": {"coordinates":[6.9682359695,46.3171157837],"type":"Point"}
}