{
  "type": "Feature",
  "properties": {
    "iso:country":"CH",
    "sg:address":"Chalet La Corniche",
    "sg:city":"Ravoire",
    "sg:orig_category":"Fahrschulen, Flugschulen",
    "sg:phone":"+41 27 722 47 77",
    "sg:postcode":"1928",
    "sg:province":"Valais",
    "wof:name":"Jean-pierre Grob\u00e9ty Auto-\u00e9cole",
    "wof:placetype":"venue"
},
  "geometry": {"coordinates":[7.0449562073,46.095954895],"type":"Point"}
}