{
  "type": "Feature",
  "properties": {
    "iso:country":"CH",
    "sg:address":"Merlina Via 28",
    "sg:city":"Viganello",
    "sg:orig_category":"Vermietung von Luftfahrzeugen",
    "sg:postcode":"6962",
    "sg:province":"Ticino",
    "wof:name":"Luckyair Sa",
    "wof:placetype":"venue"
},
  "geometry": {"coordinates":[8.9632148743,46.0143356323],"type":"Point"}
}