{
  "type": "Feature",
  "properties": {
    "iso:country":"CH",
    "sg:address":"Via Verbano 29",
    "sg:city":"Minusio",
    "sg:orig_category":"HOTELS: OHNE RESTAURANT",
    "sg:phone":"+41 91 743 10 33",
    "sg:postcode":"6648",
    "sg:province":"Ticino",
    "wof:name":"Albergo Garni Remorino",
    "wof:placetype":"venue"
},
  "geometry": {"coordinates":[8.8183898926,46.1750183105],"type":"Point"}
}