{
  "type": "Feature",
  "properties": {
    "iso:country":"CH",
    "sg:address":"Kaiserstuhlerstrasse 81",
    "sg:city":"Windlach",
    "sg:orig_category":"Unternehmensberatung Wirtschaftspr\u00fcfung, Steuerberatung U Treuhand",
    "sg:phone":"+41 12012323",
    "sg:postcode":"8175",
    "sg:province":"Z\u00fcrich",
    "wof:name":"F\u00fchrer Luigi A. & Partner Ag",
    "wof:placetype":"venue"
},
  "geometry": {"coordinates":[8.3419370651,47.3513870239],"type":"Point"}
}