{
  "type": "Feature",
  "properties": {
    "addr:full":"Gewerbezone L\u00e4tti M\u00fcnchenbuchsee Bern 3053",
    "addr:postcode":"3053",
    "addr:street":"Gewerbezone",
    "iso:country":"CH",
    "sg:address":"Gewerbezone L\u00e4tti",
    "sg:city":"M\u00fcnchenbuchsee",
    "sg:orig_category":"Architektur U Ingenieurb\u00fcros Forschung U Entwicklung",
    "sg:phone":"+41 31 868 44 66",
    "sg:postcode":"3053",
    "sg:province":"Bern",
    "wof:name":"Wavelab Engineering Ag Engineering Fuer Hochfrequenz Und Mikrowellentechnik",
    "wof:placetype":"venue"
},
  "geometry": {"coordinates":[7.450539,47.021427],"type":"Point"}
}