{
  "type": "Feature",
  "properties": {
    "iso:country":"CH",
    "sg:address":"Br\u00fcggmattstr. 9",
    "sg:city":"Lommiswil",
    "sg:orig_category":"Maler U Glasergewerbe",
    "sg:phone":"+41 71 455 13 16",
    "sg:postcode":"4514",
    "sg:province":"Solothurn",
    "wof:name":"K\u00fcnzler Fritz",
    "wof:placetype":"venue"
},
  "geometry": {"coordinates":[9.3967514038,47.4986801147],"type":"Point"}
}