{
  "type": "Feature",
  "properties": {
    "iso:country":"CH",
    "sg:address":"Rue Du Vingt-trois-juin 19",
    "sg:city":"Porrentruy",
    "sg:orig_category":"Detailhandel mit Damenbekleidung Detailhandel mit Herrenbekleidung",
    "sg:phone":"+41 32 466 30 50",
    "sg:postcode":"2900",
    "sg:province":"Jura",
    "wof:name":"Boutique Benetton",
    "wof:placetype":"venue"
},
  "geometry": {"coordinates":[7.073812,47.416039],"type":"Point"}
}