{
  "type": "Feature",
  "properties": {
    "iso:country":"CH",
    "sg:address":"Lavaux Route De 281",
    "sg:city":"Ch\u00e2telard-lutry",
    "sg:orig_category":"Detailhandel mit B\u00fcchern, Zeitungen, Schreib U Papeteriewaren",
    "sg:phone":"+41 21 791 54 91",
    "sg:postcode":"1095",
    "sg:province":"Vaud",
    "wof:name":"Dg Motte",
    "wof:placetype":"venue"
},
  "geometry": {"coordinates":[6.685757,46.503281],"type":"Point"}
}