{
  "type": "Feature",
  "properties": {
    "iso:country":"CH",
    "sg:address":"Untere Gasse 9",
    "sg:city":"Chur",
    "sg:orig_category":"Interessenvertretungen Vereine Kultur",
    "sg:phone":"+41 81 252 20 20",
    "sg:postcode":"7000",
    "sg:province":"Graubunden",
    "wof:name":"Genossenschaft Stattwerk",
    "wof:placetype":"venue"
},
  "geometry": {"coordinates":[9.5306863785,46.8485565186],"type":"Point"}
}