{
  "type": "Feature",
  "properties": {
    "iso:country":"CH",
    "sg:address":"Blumeneggstrasse 23 9403 Goldach. Postfach",
    "sg:city":"Goldach",
    "sg:orig_category":"Unclassifiable Establishments",
    "sg:phone":"+41 71 845 13 66",
    "sg:postcode":"9403",
    "sg:province":"St. Gallen",
    "wof:name":"Eichmann Network Internet Service Provider F\u00fcr Firmen U. Privatkunden, Bes. Hosting Von Websites U. Datenbanken",
    "wof:placetype":"venue"
},
  "geometry": {"coordinates":[9.4596414566,47.4718322754],"type":"Point"}
}