{
  "type": "Feature",
  "properties": {
    "iso:country":"CH",
    "sg:address":"Route De Fribourg 77",
    "sg:city":"Posieux",
    "sg:orig_category":"Unclassifiable Establishments",
    "sg:postcode":"1725",
    "sg:province":"Fribourg",
    "wof:name":"Swiss-pacific Co. S\u00e0rl",
    "wof:placetype":"venue"
},
  "geometry": {"coordinates":[7.095459938,46.7608032227],"type":"Point"}
}