{
  "type": "Feature",
  "properties": {
    "iso:country":"CH",
    "sg:address":"Langackerweg 519",
    "sg:city":"W\u00fcrenlingen",
    "sg:orig_category":"Herstellung von sonstigen elektrischen Ausr\u00fcstungen",
    "sg:postcode":"5303",
    "sg:province":"Aargau",
    "wof:name":"Muhmenthaler Elektronik",
    "wof:placetype":"venue"
},
  "geometry": {"coordinates":[8.2522220612,47.5303573608],"type":"Point"}
}