{
  "type": "Feature",
  "properties": {
    "iso:country":"CH",
    "sg:address":"Dorfstrasse 38",
    "sg:city":"Baar",
    "sg:orig_category":"Unclassifiable Establishments",
    "sg:postcode":"6340",
    "sg:province":"Zug",
    "wof:name":"Schwarb B. Holding Ag",
    "wof:placetype":"venue"
},
  "geometry": {"coordinates":[7.9619460106,47.5386695862],"type":"Point"}
}