{
  "type": "Feature",
  "properties": {
    "iso:country":"CH",
    "sg:address":"Oberfeld 43",
    "sg:city":"Kallnach",
    "sg:orig_category":"Zimmerei, Dachdeckerei, Bauspenglerei U Abdichtung",
    "sg:phone":"+41 32 392 19 02",
    "sg:postcode":"3283",
    "sg:province":"Bern",
    "wof:name":"Willy Marti Holzbau Ag",
    "wof:placetype":"venue"
},
  "geometry": {"coordinates":[7.2292790413,47.0160217285],"type":"Point"}
}