{
  "type": "Feature",
  "properties": {
    "iso:country":"CH",
    "sg:address":"Dorfstrasse 49",
    "sg:city":"Grossaffoltern",
    "sg:classifiers":[
        {
            "category":"Autos & Motor Vehicles",
            "subcategory":"Auto Supplies",
            "type":"Retail Goods"
        }
    ],
    "sg:phone":"+41 32 389 20 45",
    "sg:postcode":"3257",
    "sg:province":"Bern",
    "sg:tags":[
        "part",
        "spare",
        "motorcycle",
        "accessory"
    ],
    "wof:name":"Ernst Uhlmann Ag Triumph",
    "wof:placetype":"venue"
},
  "geometry": {"coordinates":[7.3617129326,47.0666275024],"type":"Point"}
}