{
  "type": "Feature",
  "properties": {
    "iso:country":"CH",
    "sg:address":"Landstrasse 52",
    "sg:city":"Gipf-oberfrick",
    "sg:orig_category":"Metallurgy and Metalworking Miscellaneous Products Sport Tools",
    "sg:phone":"+41 56 424 01 51",
    "sg:postcode":"5073",
    "sg:province":"Aargau",
    "wof:name":"Peterhans Handwerker- Center Ag",
    "wof:placetype":"venue"
},
  "geometry": {"coordinates":[8.3168992996,47.4699935913],"type":"Point"}
}