{
  "type": "Feature",
  "properties": {
    "iso:country":"CH",
    "sg:address":"Bethlehemstrasse 116 3018 Bern. Postfach",
    "sg:city":"Bern",
    "sg:orig_category":"Kauf U Verkauf von Immobilien auf eigene Rechnung Personal U Stellenvermittlung",
    "sg:phone":"+41 31 991 05 95",
    "sg:postcode":"3018",
    "sg:province":"Bern",
    "wof:name":"Interb\u00fcro Gmbh Unternehmung F\u00fcr Verm\u00f6gens- U. Immobilienverwaltung Usw.",
    "wof:placetype":"venue"
},
  "geometry": {"coordinates":[7.4001340866,46.9435882568],"type":"Point"}
}