{
  "type": "Feature",
  "properties": {
    "iso:country":"CH",
    "sg:address":"H\u00f6henweg 21",
    "sg:city":"Uetendorf",
    "sg:orig_category":"Kaminfeger Reinigungsgewerbe",
    "sg:phone":"+41 33 345 19 87",
    "sg:postcode":"3661",
    "sg:province":"Bern",
    "wof:name":"Gr\u00fctter Peter",
    "wof:placetype":"venue"
},
  "geometry": {"coordinates":[7.5728840828,46.7725105286],"type":"Point"}
}