{
  "type": "Feature",
  "properties": {
    "iso:country":"CH",
    "sg:address":"Via Nassa 17",
    "sg:city":"Lugano",
    "sg:orig_category":"Advokaturb\u00fcros Steuerberatung",
    "sg:phone":"+41 91 923 90 91",
    "sg:postcode":"6900",
    "sg:province":"Ticino",
    "wof:name":"Dott.walter Pizzoli Studio Legale & Fiscale",
    "wof:placetype":"venue"
},
  "geometry": {"coordinates":[8.949765,46.001919],"type":"Point"}
}