{
  "type": "Feature",
  "properties": {
    "iso:country":"CH",
    "sg:address":"Kalchb\u00fchlstrasse 40",
    "sg:city":"Chur",
    "sg:orig_category":"Elektroinstallation Herstellung von sonstigen elektrischen Ausr\u00fcstungen",
    "sg:phone":"+41 71 245 45 45",
    "sg:postcode":"7000",
    "sg:province":"Graubunden",
    "wof:name":"Schmid Ag Elektrotechnische Unternehmungen Elektr. Starkstrom, Schwachstrom- U Telefonanlagen Usw",
    "wof:placetype":"venue"
},
  "geometry": {"coordinates":[9.389997,47.438717],"type":"Point"}
}