{
  "type": "Feature",
  "properties": {
    "iso:country":"CH",
    "sg:address":"Othmarstrasse 8 8000 Z\u00fcrich. Postfach",
    "sg:city":"Z\u00fcrich",
    "sg:orig_category":"Finanzierungsinstitutionen",
    "sg:phone":"+41 22 798 80 48",
    "sg:postcode":"8008",
    "sg:province":"Z\u00fcrich",
    "wof:name":"Tc Tous Changes Sa",
    "wof:placetype":"venue"
},
  "geometry": {"coordinates":[6.126830101,46.2368164062],"type":"Point"}
}