{
  "type": "Feature",
  "properties": {
    "iso:country":"CH",
    "sg:address":"Stationsstrasse 4",
    "sg:city":"Aadorf",
    "sg:classifiers":[
        {
            "category":"Restaurant",
            "type":"Food & Drink"
        }
    ],
    "sg:phone":"+41 52 365 11 67",
    "sg:postcode":"8355",
    "sg:province":"Thurgau",
    "wof:name":"Restaurant Gr\u00fctli",
    "wof:placetype":"venue"
},
  "geometry": {"coordinates":[8.8953018188,47.4918861389],"type":"Point"}
}