{
  "type": "Feature",
  "properties": {
    "iso:country":"CH",
    "sg:address":"Missionsstrasse 50",
    "sg:city":"Basel",
    "sg:orig_category":"Grosshandel mit B\u00fcromaschinen Sonstige mit der Informatik verbundene T\u00e4tigkeiten",
    "sg:phone":"+41 61 281 81 50",
    "sg:postcode":"4055",
    "sg:province":"Basel-Stadt",
    "wof:name":"Rhena-data Ag",
    "wof:placetype":"venue"
},
  "geometry": {"coordinates":[7.5760540962,47.5608634949],"type":"Point"}
}