{
  "type": "Feature",
  "properties": {
    "iso:country":"CH",
    "sg:address":"Rathausgasse 72",
    "sg:city":"Bern",
    "sg:orig_category":"Gastgewerbe",
    "sg:phone":"+41 31 311 02 16",
    "sg:postcode":"3011",
    "sg:province":"Bern",
    "wof:name":"Hotel Goldener Schl\u00fcssel",
    "wof:placetype":"venue"
},
  "geometry": {"coordinates":[7.4487128258,46.9486122131],"type":"Point"}
}