{
  "type": "Feature",
  "properties": {
    "iso:country":"CH",
    "sg:address":"Bruggerstrasse 59",
    "sg:city":"Baden",
    "sg:classifiers":[
        {
            "category":"Structure",
            "subcategory":"Warehouse",
            "type":"Public Place"
        }
    ],
    "sg:phone":"+41 56 203 73 73",
    "sg:postcode":"5400",
    "sg:province":"Aargau",
    "sg:tags":[
        "air-conditioning",
        "system"
    ],
    "wof:name":"Klimavent Ag",
    "wof:placetype":"venue"
},
  "geometry": {"coordinates":[8.303652,47.477962],"type":"Point"}
}