{
  "type": "Feature",
  "properties": {
    "iso:country":"CH",
    "sg:address":"Lehmattstrasse",
    "sg:city":"Zeglingen",
    "sg:orig_category":"S\u00e4gewerke",
    "sg:phone":"+41 33 765 32 66",
    "sg:postcode":"4495",
    "sg:province":"Basel-Landschaft",
    "wof:name":"Robert Annen S\u00e4gerei",
    "wof:placetype":"venue"
},
  "geometry": {"coordinates":[7.3235812187,46.4193496704],"type":"Point"}
}