{
  "type": "Feature",
  "properties": {
    "iso:country":"CH",
    "sg:address":"Sickingerstrasse 6",
    "sg:city":"Bern",
    "sg:orig_category":"Architektur U Ingenieurb\u00fcros",
    "sg:postcode":"3005",
    "sg:province":"Bern",
    "wof:name":"Bauhof Architekten Gmbh",
    "wof:placetype":"venue"
},
  "geometry": {"coordinates":[7.451173,46.95673],"type":"Point"}
}