{
  "type": "Feature",
  "properties": {
    "iso:country":"CH",
    "sg:address":"Pierre Rue Saint- 6 1700 Fribourg. Postfach",
    "sg:city":"Freiburg",
    "sg:orig_category":"Non-Classified Establishments",
    "sg:postcode":"1700",
    "sg:province":"Fribourg",
    "wof:name":"Kawasa Sa",
    "wof:placetype":"venue"
},
  "geometry": {"coordinates":[7.1548838615,46.8036270142],"type":"Point"}
}