{
  "type": "Feature",
  "properties": {
    "iso:country":"CH",
    "sg:address":"Sch\u00e4renmoosstrasse 110",
    "sg:city":"Z\u00fcrich",
    "sg:orig_category":"Datenbanken Fernmeldedienste",
    "sg:phone":"+41 13083629",
    "sg:postcode":"8052",
    "sg:province":"Z\u00fcrich",
    "wof:name":"Isc Information Shuttle Corporation Gmbh",
    "wof:placetype":"venue"
},
  "geometry": {"coordinates":[8.559167,47.418346],"type":"Point"}
}