{
  "type": "Feature",
  "properties": {
    "iso:country":"CH",
    "sg:address":"Thujastrasse 57 8000 Z\u00fcrich. Postfach",
    "sg:city":"Z\u00fcrich",
    "sg:orig_category":"Non-Classified Establishments",
    "sg:postcode":"8038",
    "sg:province":"Z\u00fcrich",
    "wof:name":"Manogi Sa",
    "wof:placetype":"venue"
},
  "geometry": {"coordinates":[9.1073904037,46.2385597229],"type":"Point"}
}