{
  "type": "Feature",
  "properties": {
    "iso:country":"CH",
    "sg:address":"Giessenstrasse 11 8952 Schlieren. Postfach",
    "sg:city":"Z\u00fcrich",
    "sg:orig_category":"Herstellung von sonstigen Erzeugnissen",
    "sg:postcode":"8048",
    "sg:province":"Z\u00fcrich",
    "wof:name":"Royalman Gmbh",
    "wof:placetype":"venue"
},
  "geometry": {"coordinates":[8.4514198303,47.3982124329],"type":"Point"}
}