{
  "type": "Feature",
  "properties": {
    "iso:country":"CH",
    "sg:address":"Bahnhofstrasse 26 2502 Biel/bienne Case Postale 920",
    "sg:city":"Biel/bienne",
    "sg:orig_category":"Fachdetailhandel in Verkaufsr\u00e4umen Grosshandel mit Uhren",
    "sg:phone":"+41 32 323 88 51",
    "sg:postcode":"2501",
    "sg:province":"Bern",
    "wof:name":"San Marco Biennne Sa",
    "wof:placetype":"venue"
},
  "geometry": {"coordinates":[7.2449269295,47.1351470947],"type":"Point"}
}