{
  "type": "Feature",
  "properties": {
    "addr:full":"Rohrerstrasse 62 Aarau Aargau 5000",
    "addr:housenumber":"62",
    "addr:postcode":"5000",
    "addr:street":"Rohrerstrasse",
    "iso:country":"CH",
    "sg:address":"Rohrerstrasse 62",
    "sg:city":"Aarau",
    "sg:orig_category":"Allgemeiner Hoch U Tiefbau",
    "sg:phone":"+41 62 824 55 07",
    "sg:postcode":"5000",
    "sg:province":"Aargau",
    "wof:name":"Bamodag",
    "wof:placetype":"venue"
},
  "geometry": {"coordinates":[8.060378,47.395264],"type":"Point"}
}