{
  "type": "Feature",
  "properties": {
    "iso:country":"CH",
    "sg:address":"Grand-rue 45",
    "sg:city":"Buix",
    "sg:classifiers":[
        {
            "category":"Banks & Credit Unions",
            "subcategory":"Bank",
            "type":"Services"
        }
    ],
    "sg:phone":"+41 26 927 11 53",
    "sg:postcode":"2925",
    "sg:province":"Jura",
    "wof:name":"Banque Raiffeisen De Charmey",
    "wof:placetype":"venue"
},
  "geometry": {"coordinates":[7.164164,46.619221],"type":"Point"}
}