{
  "type": "Feature",
  "properties": {
    "iso:country":"CH",
    "sg:address":"Bildfeldstrasse 33",
    "sg:city":"Bronschhofen",
    "sg:orig_category":"Handel mit Automobilteilen U Zubeh\u00f6r",
    "sg:postcode":"9552",
    "sg:province":"St. Gallen",
    "wof:name":"Car-collection Hauf",
    "wof:placetype":"venue"
},
  "geometry": {"coordinates":[9.0352287292,47.472038269],"type":"Point"}
}