{
  "type": "Feature",
  "properties": {
    "iso:country":"CH",
    "sg:address":"Augiessenstrasse 13b",
    "sg:city":"Widnau",
    "sg:orig_category":"Sonstiger Grosshandel",
    "sg:phone":"+41 71 722 41 86",
    "sg:postcode":"9443",
    "sg:province":"St. Gallen",
    "wof:name":"Net Tech Minikus",
    "wof:placetype":"venue"
},
  "geometry": {"coordinates":[9.6418380737,47.4001655579],"type":"Point"}
}