{
  "type": "Feature",
  "properties": {
    "iso:country":"CH",
    "sg:address":"Sch\u00fctzengraben 20",
    "sg:city":"Schaffhausen",
    "sg:orig_category":"Schlankheitsinstitute",
    "sg:phone":"+41 52 624 23 88",
    "sg:postcode":"8200",
    "sg:province":"Schaffhausen",
    "wof:name":"Erika Uehlinger Belle-fit Figurstudio",
    "wof:placetype":"venue"
},
  "geometry": {"coordinates":[8.6357917786,47.6989326477],"type":"Point"}
}