{
  "type": "Feature",
  "properties": {
    "iso:country":"CH",
    "sg:address":"Haumesserstrasse 20 8038 Z\u00fcrich. Postfach",
    "sg:city":"Z\u00fcrich",
    "sg:orig_category":"Verlagsgewerbe",
    "sg:phone":"+41 14815805",
    "sg:postcode":"8038",
    "sg:province":"Z\u00fcrich",
    "wof:name":"Haumesser Verlag",
    "wof:placetype":"venue"
},
  "geometry": {"coordinates":[8.5312852859,47.3482666016],"type":"Point"}
}