{
  "type": "Feature",
  "properties": {
    "iso:country":"CH",
    "sg:address":"Luzernstrasse 13",
    "sg:city":"Derendingen",
    "sg:classifiers":[
        {
            "category":"Banks & Credit Unions",
            "subcategory":"Investment Brokerage",
            "type":"Services"
        }
    ],
    "sg:phone":"+41 32 682 33 66",
    "sg:postcode":"4552",
    "sg:province":"Solothurn",
    "sg:tags":[
        "development",
        "electronics"
    ],
    "wof:name":"Th. Flury & Partner",
    "wof:placetype":"venue"
},
  "geometry": {"coordinates":[7.5830430984,47.2003822327],"type":"Point"}
}