{
  "type": "Feature",
  "properties": {
    "iso:country":"CH",
    "sg:address":"Avenue Des Alpes 6",
    "sg:city":"Lausanne",
    "sg:orig_category":"Innendekorationsateliers",
    "sg:phone":"+41 21 312 87 05",
    "sg:postcode":"1006",
    "sg:province":"Vaud",
    "wof:name":"Ennio Falsarella D\u00e9coration D'int\u00e9rieur",
    "wof:placetype":"venue"
},
  "geometry": {"coordinates":[6.6378731728,46.5144767761],"type":"Point"}
}