{
  "type": "Feature",
  "properties": {
    "iso:country":"CH",
    "sg:address":"St-bonnet",
    "sg:city":"Dully",
    "sg:orig_category":"Vermietung U Verpachtung von eigenen Immobilien",
    "sg:postcode":"1195",
    "sg:province":"Vaud",
    "wof:name":"Toresama Sa",
    "wof:placetype":"venue"
},
  "geometry": {"coordinates":[9.1283597946,46.2375984192],"type":"Point"}
}