{
  "type": "Feature",
  "properties": {
    "iso:country":"CH",
    "sg:address":"Ausserdorf 20 5705 Hallwil. Postfach",
    "sg:city":"Hallwil",
    "sg:orig_category":"Herstellung von sonstigen landwirtschaftlichen Maschinen",
    "sg:phone":"+41 62 777 22 22",
    "sg:postcode":"5705",
    "sg:province":"Aargau",
    "wof:name":"M\u00fchlemann Motorger\u00e4te",
    "wof:placetype":"venue"
},
  "geometry": {"coordinates":[8.1784858704,47.326625824],"type":"Point"}
}