{
  "type": "Feature",
  "properties": {
    "iso:country":"CH",
    "sg:address":"Gemeindehaus 9242 Oberuzwil. Postfach",
    "sg:city":"Oberuzwil",
    "sg:orig_category":"Interessenvertretungen",
    "sg:postcode":"9242",
    "sg:province":"St. Gallen",
    "wof:name":"Stiftung M\u00fcller Ida Und Jakob",
    "wof:placetype":"venue"
},
  "geometry": {"coordinates":[9.1233797073,47.4295463562],"type":"Point"}
}