{
  "type": "Feature",
  "properties": {
    "iso:country":"CH",
    "sg:address":"1001 Lausanne Case Postale 870",
    "sg:city":"Lausanne",
    "sg:classifiers":[
        {
            "category":"Education",
            "subcategory":"Library",
            "type":"Public Place"
        }
    ],
    "sg:phone":"+41 21 692 48 02",
    "sg:postcode":"1001",
    "sg:province":"Vaud",
    "sg:tags":[
        "u",
        "bibliotheken",
        "archive"
    ],
    "wof:name":"Biblioth\u00e8que Du Secr\u00e9tariat Antialcoolique Suisse",
    "wof:placetype":"venue"
},
  "geometry": {"coordinates":[6.63345,46.519428],"type":"Point"}
}