{
  "type": "Feature",
  "properties": {
    "iso:country":"CH",
    "sg:address":"H\u00fcslibachweg 7",
    "sg:city":"W\u00e4ngi",
    "sg:orig_category":"Versicherungsagenturen and -broker -Steuerberatung",
    "sg:phone":"+41 52 378 21 59",
    "sg:postcode":"9545",
    "sg:province":"Thurgau",
    "wof:name":"Walter Soller Alfa Finanzberatung",
    "wof:placetype":"venue"
},
  "geometry": {"coordinates":[8.9542541504,47.502571106],"type":"Point"}
}