{
  "type": "Feature",
  "properties": {
    "addr:full":"Route De Del\u00e9mont Courrendlin Jura 2830",
    "addr:postcode":"2830",
    "addr:street":"Route De Dele\u0301Mont;Jura",
    "iso:country":"CH",
    "sg:address":"Route De Del\u00e9mont",
    "sg:city":"Courrendlin",
    "sg:orig_category":"Autogaragen",
    "sg:phone":"+41 32 435 50 75",
    "sg:postcode":"2830",
    "sg:province":"Jura",
    "wof:name":"Philippe Gu\u00e9lat Garage",
    "wof:placetype":"venue"
},
  "geometry": {"coordinates":[7.36928,47.342072],"type":"Point"}
}