{
  "type": "Feature",
  "properties": {
    "iso:country":"CH",
    "sg:address":"Im Eigen 2",
    "sg:city":"Laufenburg",
    "sg:orig_category":"Energie\u00e4mter and -fachstellen",
    "sg:phone":"+41 62 874 07 30",
    "sg:postcode":"5080",
    "sg:province":"Aargau",
    "wof:name":"Dominique St\u00e4uble Etelcom",
    "wof:placetype":"venue"
},
  "geometry": {"coordinates":[8.0577812195,47.5592880249],"type":"Point"}
}