{
  "type": "Feature",
  "properties": {
    "iso:country":"CH",
    "sg:address":"Burgstrasse 4",
    "sg:city":"Sch\u00f6nenwerd",
    "sg:orig_category":"Sonstiger Grosshandel",
    "sg:phone":"+41 62 849 68 25",
    "sg:postcode":"5012",
    "sg:province":"Solothurn",
    "wof:name":"Nova-ware Cosentino S.",
    "wof:placetype":"venue"
},
  "geometry": {"coordinates":[8.0028705597,47.3701896667],"type":"Point"}
}