{
  "type": "Feature",
  "properties": {
    "iso:country":"CH",
    "sg:address":"Eigerstrasse 6",
    "sg:city":"Unterseen",
    "sg:orig_category":"Erschliessung von Grundst\u00fccken",
    "sg:postcode":"3800",
    "sg:province":"Bern",
    "wof:name":"Wohnbaugenossenschaft Fiechten",
    "wof:placetype":"venue"
},
  "geometry": {"coordinates":[7.5926861763,47.4989929199],"type":"Point"}
}