{
  "type": "Feature",
  "properties": {
    "iso:country":"CH",
    "sg:address":"Weite Gasse 14 5400 Baden. Postfach 2086",
    "sg:city":"Baden",
    "sg:orig_category":"Advokaturb\u00fcros",
    "sg:phone":"+41 56 222 68 78",
    "sg:postcode":"5402",
    "sg:province":"Aargau",
    "wof:name":"Dr.guolf T\u00f6ndury Advokaturb\u00fcro",
    "wof:placetype":"venue"
},
  "geometry": {"coordinates":[8.307307,47.471924],"type":"Point"}
}