{
  "type": "Feature",
  "properties": {
    "iso:country":"CH",
    "sg:address":"Couchant Chemin Du 11",
    "sg:city":"Orbe",
    "sg:orig_category":"Softwareentwicklung U beratung",
    "sg:phone":"+41 24 441 71 38",
    "sg:postcode":"1350",
    "sg:province":"Vaud",
    "wof:name":"Mats Computer Tschumper Marcel",
    "wof:placetype":"venue"
},
  "geometry": {"coordinates":[6.5309619904,46.7247772217],"type":"Point"}
}