{
  "type": "Feature",
  "properties": {
    "iso:country":"CH",
    "sg:address":"General-wille-str. 22 8706 Meilen. Postfach",
    "sg:city":"Meilen",
    "sg:orig_category":"Fachdetailhandel in Verkaufsr\u00e4umen",
    "sg:postcode":"8706",
    "sg:province":"Z\u00fcrich",
    "wof:name":"Paragon Resort Ag",
    "wof:placetype":"venue"
},
  "geometry": {"coordinates":[8.6116724014,47.2821807861],"type":"Point"}
}