{
  "type": "Feature",
  "properties": {
    "iso:country":"CH",
    "sg:address":"Route De St-cergue 38",
    "sg:city":"Nyon",
    "sg:orig_category":"Verwaltung der Rechtspflege, Gerichte",
    "sg:phone":"+41 21 861 01 77",
    "sg:postcode":"1260",
    "sg:province":"Vaud",
    "wof:name":"Tribunal D'arrondissement De La C\u00f4te",
    "wof:placetype":"venue"
},
  "geometry": {"coordinates":[6.2326798439,46.3877983093],"type":"Point"}
}