{
  "type": "Feature",
  "properties": {
    "iso:country":"CH",
    "sg:address":"Feldbergstrasse 28",
    "sg:city":"Basel",
    "sg:orig_category":"Allgemeiner Hoch U Tiefbau",
    "sg:phone":"+41 81 771 22 55",
    "sg:postcode":"4057",
    "sg:province":"Basel-Stadt",
    "wof:name":"Littleton James D. Gmbh",
    "wof:placetype":"venue"
},
  "geometry": {"coordinates":[9.63487,47.451469],"type":"Point"}
}