{
  "type": "Feature",
  "properties": {
    "iso:country":"CH",
    "sg:address":"Seenerstrasse 143",
    "sg:city":"Seen",
    "sg:orig_category":"Herstellung von Kakao, Schokoladeerzeugnissen U Zuckerwaren",
    "sg:phone":"+41 52 316 34 48",
    "sg:postcode":"8405",
    "sg:province":"Z\u00fcrich",
    "wof:name":"Angelic Creative Inh. Schlosser Marco",
    "wof:placetype":"venue"
},
  "geometry": {"coordinates":[8.7613506317,47.4944267273],"type":"Point"}
}