{
  "type": "Feature",
  "properties": {
    "iso:country":"CH",
    "sg:address":"Buochserstrasse 39",
    "sg:city":"Stans",
    "sg:orig_category":"Arbeitnehmerverb\u00e4nde",
    "sg:phone":"+41 41 610 16 40",
    "sg:postcode":"6370",
    "sg:province":"Nidwalden",
    "wof:name":"Unia Die Dienstleistungsgewerkschaft",
    "wof:placetype":"venue"
},
  "geometry": {"coordinates":[8.373182,46.961117],"type":"Point"}
}