{
  "type": "Feature",
  "properties": {
    "iso:country":"CH",
    "sg:address":"F\u00fcrstenlandstrasse 101",
    "sg:city":"St. Gallen",
    "sg:orig_category":"Dienstleistungen, Sonstige Dienstleistungen",
    "sg:phone":"+41 71 274 81 11",
    "sg:postcode":"9014",
    "sg:province":"St. Gallen",
    "wof:name":"Img Ag",
    "wof:placetype":"venue"
},
  "geometry": {"coordinates":[9.344839,47.412556],"type":"Point"}
}