{
  "type": "Feature",
  "properties": {
    "iso:country":"CH",
    "sg:address":"Krattigstrasse 53a",
    "sg:city":"Spiez",
    "sg:orig_category":"Vereine Haus- and Grundeigent\u00fcmer",
    "sg:phone":"+41 33 654 71 54",
    "sg:postcode":"3700",
    "sg:province":"Bern",
    "wof:name":"Hauseigent\u00fcmerverband Spiez",
    "wof:placetype":"venue"
},
  "geometry": {"coordinates":[7.6863899231,46.6788597107],"type":"Point"}
}