{
  "type": "Feature",
  "properties": {
    "iso:country":"CH",
    "sg:address":"Weystrasse 8",
    "sg:city":"Luzern",
    "sg:classifiers":[
        {
            "category":"Insurance",
            "subcategory":"Insurance Agent",
            "type":"Services"
        }
    ],
    "sg:phone":"+41 41 410 55 56",
    "sg:postcode":"6006",
    "sg:province":"Luzern",
    "sg:tags":[
        "versicherungsagenturen",
        "-broker"
    ],
    "wof:name":"Winterthur Versicherungen Stadtagentur",
    "wof:placetype":"venue"
},
  "geometry": {"coordinates":[8.3129072189,47.0562057495],"type":"Point"}
}