{
  "type": "Feature",
  "properties": {
    "iso:country":"CH",
    "sg:address":"6959",
    "sg:city":"Curtina",
    "sg:orig_category":"Betrieb von Taxis",
    "sg:phone":"+41 79 207 25 25",
    "sg:postcode":"6959",
    "sg:province":"Ticino",
    "wof:name":"Luciano Campana Tassi",
    "wof:placetype":"venue"
},
  "geometry": {"coordinates":[9.0237,46.08128],"type":"Point"}
}