{
  "type": "Feature",
  "properties": {
    "iso:country":"CH",
    "sg:address":"Via Sogn Pieder 14 7013 Domat/ems. Postfach 62",
    "sg:city":"Domat/ems",
    "sg:orig_category":"Stukkateurgewerbe, Gipserei U Verputzerei",
    "sg:phone":"+41 81 633 35 73",
    "sg:postcode":"7013",
    "sg:province":"Graubunden",
    "wof:name":"Gebr\u00fcder Candeloro Ag Gipsergesch\u00e4ft",
    "wof:placetype":"venue"
},
  "geometry": {"coordinates":[9.4491405487,46.835647583],"type":"Point"}
}