{
  "type": "Feature",
  "properties": {
    "iso:country":"CH",
    "sg:address":"Via St. Franscini 6",
    "sg:city":"Biasca",
    "sg:orig_category":"Grosshandel mit Datenverarbeitungsger\u00e4ten Softwareentwicklung U beratung",
    "sg:phone":"+41 91 880 09 09",
    "sg:postcode":"6710",
    "sg:province":"Ticino",
    "wof:name":"Jvan Canonica Jkcomputer",
    "wof:placetype":"venue"
},
  "geometry": {"coordinates":[8.9717903137,46.3519592285],"type":"Point"}
}