{
  "type": "Feature",
  "properties": {
    "iso:country":"CH",
    "sg:address":"Grand'rue 37a",
    "sg:city":"Corg\u00e9mont",
    "sg:orig_category":"Mechanische Werkst\u00e4tten",
    "sg:phone":"+41 32 489 31 91",
    "sg:postcode":"2606",
    "sg:province":"Bern",
    "wof:name":"Daniel Schwyzer Atelier De M\u00e9canique De Pr\u00e9c.",
    "wof:placetype":"venue"
},
  "geometry": {"coordinates":[7.1404972076,47.1935539246],"type":"Point"}
}