{
  "type": "Feature",
  "properties": {
    "iso:country":"CH",
    "sg:address":"Altstadtgasse 3 6210 Sursee. Postfach",
    "sg:city":"Sursee",
    "sg:orig_category":"Detailhandel mit Metallwaren, Anstrichmitteln, Glaswaren, Bau U Heimwerkerbedarf",
    "sg:postcode":"6210",
    "sg:province":"Luzern",
    "wof:name":"Altstadt-bastel-boutique Waller Iris",
    "wof:placetype":"venue"
},
  "geometry": {"coordinates":[8.1091003418,47.172290802],"type":"Point"}
}