{
  "type": "Feature",
  "properties": {
    "iso:country":"CH",
    "sg:address":"Via Santeri 7 7130 Ilanz. Postfach",
    "sg:city":"Ilanz",
    "sg:orig_category":"Handel mit Motorr\u00e4dern, Teilen U Zubeh\u00f6r Instandhaltung U Reparatur von Automobilen Instandhaltung U",
    "sg:phone":"+41 79 357 76 76",
    "sg:postcode":"7130",
    "sg:province":"Graubunden",
    "wof:name":"Allenspach Sepp",
    "wof:placetype":"venue"
},
  "geometry": {"coordinates":[9.2005176544,46.7731971741],"type":"Point"}
}