{
  "type": "Feature",
  "properties": {
    "iso:country":"CH",
    "sg:address":"Brunnenstrasse 5 9410 Heiden. Postfach 206",
    "sg:city":"Heiden",
    "sg:orig_category":"Fotografische Ateliers Fotografisches Gewerbe U fotografische Laboratorien",
    "sg:phone":"+41 71 890 04 04",
    "sg:postcode":"9410",
    "sg:province":"Appenzell Ausserrhoden",
    "wof:name":"Fotostudio Schrag",
    "wof:placetype":"venue"
},
  "geometry": {"coordinates":[9.5282611847,47.4420433044],"type":"Point"}
}