{
  "type": "Feature",
  "properties": {
    "iso:country":"CH",
    "sg:address":"Aufdorfstrasse 172",
    "sg:city":"M\u00e4nnedorf",
    "sg:orig_category":"Vermietung von Automobilen",
    "sg:postcode":"8708",
    "sg:province":"Z\u00fcrich",
    "wof:name":"Rentra Ag",
    "wof:placetype":"venue"
},
  "geometry": {"coordinates":[8.6992120743,47.2588348389],"type":"Point"}
}