{
  "type": "Feature",
  "properties": {
    "iso:country":"CH",
    "sg:address":"Magisterweg 1",
    "sg:city":"Balsthal",
    "sg:orig_category":"Sportschulen Fern\u00f6stliche Kampfsportarten Sportvereine Judo and Karate",
    "sg:phone":"+41 62 391 47 11",
    "sg:postcode":"4710",
    "sg:province":"Solothurn",
    "wof:name":"Karate-schule Shin Wa Kan",
    "wof:placetype":"venue"
},
  "geometry": {"coordinates":[7.6817531586,47.3131523132],"type":"Point"}
}