{
  "type": "Feature",
  "properties": {
    "iso:country":"CH",
    "sg:address":"Hammerstrasse 113 4057 Basel. Postfach Postfach",
    "sg:city":"Basel",
    "sg:orig_category":"Informatikdienste Zeitschriftenverlag",
    "sg:phone":"+41 61 683 88 76",
    "sg:postcode":"4005",
    "sg:province":"Basel-Stadt",
    "wof:name":"Fractal Verlag Gmbh Herausgeber Des Fachmagazins It Business",
    "wof:placetype":"venue"
},
  "geometry": {"coordinates":[7.5950760841,47.5663642883],"type":"Point"}
}