{
  "type": "Feature",
  "properties": {
    "iso:country":"CH",
    "sg:address":"Chemin Des Passereaux 3bis",
    "sg:city":"Th\u00f4nex",
    "sg:orig_category":"Grosshandel mit Sportartikeln",
    "sg:phone":"+41 19202779",
    "sg:postcode":"1226",
    "sg:province":"Gen\u00e8ve",
    "wof:name":"Stucki Handels Ag",
    "wof:placetype":"venue"
},
  "geometry": {"coordinates":[8.6928462982,47.2679405212],"type":"Point"}
}