{
  "type": "Feature",
  "properties": {
    "iso:country":"CH",
    "sg:address":"M\u00fchlestrasse 21",
    "sg:city":"Schlosswil",
    "sg:orig_category":"Landw. Genossenschaften Dresch",
    "sg:phone":"+41 31 711 08 07",
    "sg:postcode":"3082",
    "sg:province":"Bern",
    "wof:name":"Ulrich Segessenmann M\u00e4hdrescherei",
    "wof:placetype":"venue"
},
  "geometry": {"coordinates":[7.5988888741,46.913734436],"type":"Point"}
}