{
  "type": "Feature",
  "properties": {
    "iso:country":"CH",
    "sg:address":"Kapellenweg 11",
    "sg:city":"Gelterkinden",
    "sg:orig_category":"Non-Classified Establishments",
    "sg:phone":"+41 61 981 51 61",
    "sg:postcode":"4460",
    "sg:province":"Basel-Landschaft",
    "wof:name":"Balance Gesundheit - Fitness - Ausgeglichenheit Gmbh",
    "wof:placetype":"venue"
},
  "geometry": {"coordinates":[7.8543291092,47.4638748169],"type":"Point"}
}