{
  "type": "Feature",
  "properties": {
    "iso:country":"CH",
    "sg:address":"Widenholzstrasse 7",
    "sg:city":"Wallisellen",
    "sg:orig_category":"Instandhaltung U Reparatur von Automobilen",
    "sg:phone":"+41 21 691 48 70",
    "sg:postcode":"8304",
    "sg:province":"Z\u00fcrich",
    "wof:name":"Estoppey Andr\u00e9-jean",
    "wof:placetype":"venue"
},
  "geometry": {"coordinates":[6.5580701828,46.5100784302],"type":"Point"}
}