{
  "type": "Feature",
  "properties": {
    "iso:country":"CH",
    "sg:address":"H\u00f6lsteinerstrasse 10",
    "sg:city":"Lampenberg",
    "sg:orig_category":"Innenausbau Zimmerei, Dachdeckerei, Bauspenglerei U Abdichtung",
    "sg:phone":"+41 61 951 15 95",
    "sg:postcode":"4432",
    "sg:province":"Basel-Landschaft",
    "wof:name":"Mundschin Holzbau Bedachungen",
    "wof:placetype":"venue"
},
  "geometry": {"coordinates":[7.7606158257,47.4249725342],"type":"Point"}
}