{
  "type": "Feature",
  "properties": {
    "iso:country":"CH",
    "sg:address":"Avenue D'yverdon 2",
    "sg:city":"Lausanne",
    "sg:orig_category":"Detailhandel mit M\u00f6beln M\u00f6belveredelung U restaurierung",
    "sg:phone":"+41 21 625 14 86",
    "sg:postcode":"1004",
    "sg:province":"Vaud",
    "wof:name":"Ferreira .",
    "wof:placetype":"venue"
},
  "geometry": {"coordinates":[6.6176719666,46.5507926941],"type":"Point"}
}