{
  "type": "Feature",
  "properties": {
    "iso:country":"CH",
    "sg:address":"Mellingerstrasse 6",
    "sg:city":"Baden",
    "sg:orig_category":"Elektroinstallation",
    "sg:phone":"+41 56 210 36 01",
    "sg:postcode":"5400",
    "sg:province":"Aargau",
    "wof:name":"Enercon Engineering Und Montage Ag",
    "wof:placetype":"venue"
},
  "geometry": {"coordinates":[8.3054075241,47.4712982178],"type":"Point"}
}