{
  "type": "Feature",
  "properties": {
    "iso:country":"CH",
    "sg:address":"Chemin De Delay 7",
    "sg:city":"Vernier",
    "sg:orig_category":"Antennenbau",
    "sg:phone":"+41 22 930 12 05",
    "sg:postcode":"1214",
    "sg:province":"Gen\u00e8ve",
    "wof:name":"Citeel Suisse S\u00e0rl T\u00e9l\u00e9communication",
    "wof:placetype":"venue"
},
  "geometry": {"coordinates":[6.077771,46.21854],"type":"Point"}
}