{
  "type": "Feature",
  "properties": {
    "iso:country":"CH",
    "sg:address":"Avenue De La Gare 38",
    "sg:city":"Martigny",
    "sg:orig_category":"Sanit\u00e4r, Heizungs U L\u00fcftungsinstallation",
    "sg:postcode":"1920",
    "sg:province":"Valais",
    "wof:name":"Zanotti Tony.",
    "wof:placetype":"venue"
},
  "geometry": {"coordinates":[7.0764451027,46.1037521362],"type":"Point"}
}