{
  "type": "Feature",
  "properties": {
    "iso:country":"CH",
    "sg:address":"Pr\u00e9 De Riva",
    "sg:city":"Gletterens",
    "sg:orig_category":"Interessenvertretungen",
    "sg:phone":"+41 26 667 22 01",
    "sg:postcode":"1544",
    "sg:province":"Fribourg",
    "wof:name":"Fondation Millioud Jeanne",
    "wof:placetype":"venue"
},
  "geometry": {"coordinates":[6.9308547974,46.9045295715],"type":"Point"}
}