{
  "type": "Feature",
  "properties": {
    "iso:country":"CH",
    "sg:address":"Via Lecch",
    "sg:city":"Rancate",
    "sg:orig_category":"Detailhandel mit M\u00f6beln U Haushaltsgegenst\u00e4nden Innendekorationsateliers",
    "sg:phone":"+41 91 646 65 43",
    "sg:postcode":"6862",
    "sg:province":"Ticino",
    "wof:name":"Gerosa Silvano",
    "wof:placetype":"venue"
},
  "geometry": {"coordinates":[8.9668550491,45.8682250977],"type":"Point"}
}