{
  "type": "Feature",
  "properties": {
    "iso:country":"CH",
    "sg:address":"Luzernerstrasse 26 6330 Cham. Postfach 181",
    "sg:city":"Cham",
    "sg:orig_category":"Friedhofs- and Stadtg\u00e4rtnereien",
    "sg:phone":"+41 55 222 65 11",
    "sg:postcode":"6330",
    "sg:province":"Zug",
    "wof:name":"Bauamt Der Stadt Rapperswil",
    "wof:placetype":"venue"
},
  "geometry": {"coordinates":[8.8163518906,47.2262649536],"type":"Point"}
}