{
  "type": "Feature",
  "properties": {
    "iso:country":"CH",
    "sg:address":"Heimplatz 1",
    "sg:city":"Z\u00fcrich",
    "sg:classifiers":[
        {
            "category":"Restaurant",
            "type":"Food & Drink"
        }
    ],
    "sg:phone":"+41 19100715",
    "sg:postcode":"8001",
    "sg:province":"Z\u00fcrich",
    "wof:name":"Restaurant Kunststuben",
    "wof:placetype":"venue"
},
  "geometry": {"coordinates":[8.5799207687,47.3156394958],"type":"Point"}
}