{
  "type": "Feature",
  "properties": {
    "iso:country":"CH",
    "sg:address":"Gartenstrasse 33",
    "sg:city":"W\u00fcrenlingen",
    "sg:orig_category":"Fahrschulen, Flugschulen",
    "sg:phone":"+41 56 281 19 75",
    "sg:postcode":"5303",
    "sg:province":"Aargau",
    "wof:name":"Anton Baumgartner Autofahrschule",
    "wof:placetype":"venue"
},
  "geometry": {"coordinates":[8.2545881271,47.5324440002],"type":"Point"}
}