{
  "type": "Feature",
  "properties": {
    "iso:country":"CH",
    "sg:address":"Breitenfeldstrasse 3",
    "sg:city":"Bellach",
    "sg:orig_category":"Elektroinstallation Herstellung von Elektromotoren, Generatoren U Transformatoren",
    "sg:phone":"+41 32 618 38 14",
    "sg:postcode":"4512",
    "sg:province":"Solothurn",
    "wof:name":"Aek Elektro Ag",
    "wof:placetype":"venue"
},
  "geometry": {"coordinates":[7.4920258522,47.2137184143],"type":"Point"}
}