{
  "type": "Feature",
  "properties": {
    "addr:full":"Weissbadstrasse 59 Appenzell Appenzell Innerhoden 9050",
    "addr:housenumber":"59",
    "addr:postcode":"9050",
    "addr:street":"Weissbadstrasse",
    "iso:country":"CH",
    "sg:address":"Weissbadstrasse 59",
    "sg:city":"Appenzell",
    "sg:orig_category":"Arztpraxen",
    "sg:phone":"+41 71 787 33 66",
    "sg:postcode":"9050",
    "sg:province":"Appenzell Innerhoden",
    "wof:name":"Dr.med.tek Heng Yong Spezialarzt Eeg-station",
    "wof:placetype":"venue"
},
  "geometry": {"coordinates":[9.416609,47.327106],"type":"Point"}
}