{
  "type": "Feature",
  "properties": {
    "iso:country":"CH",
    "sg:address":"Rue Du Midi 33",
    "sg:city":"Vevey",
    "sg:orig_category":"Reinigungsgewerbe",
    "sg:phone":"+41 21 921 55 25",
    "sg:postcode":"1800",
    "sg:province":"Vaud",
    "wof:name":"Texsana-nettoyage Chimique Vevey Sa",
    "wof:placetype":"venue"
},
  "geometry": {"coordinates":[6.8392028809,46.4643058777],"type":"Point"}
}