{
  "type": "Feature",
  "properties": {
    "iso:country":"CH",
    "sg:address":"Burgfeldermattweg 63",
    "sg:city":"Allschwil",
    "sg:orig_category":"Non-Classified Establishments",
    "sg:postcode":"4123",
    "sg:province":"Basel-Landschaft",
    "wof:name":"Sch\u00e4deli's African Commerce Sacom",
    "wof:placetype":"venue"
},
  "geometry": {"coordinates":[7.5407710075,47.5569190979],"type":"Point"}
}