{
  "type": "Feature",
  "properties": {
    "iso:country":"CH",
    "sg:address":"Zentralstrasse 123",
    "sg:city":"Biel/bienne",
    "sg:orig_category":"Herstellung von Ger\u00e4ten der Elektrizit\u00e4tserzeugung, -verteilung u.\u00e4. -K\u00fcnstlerische U schriftsteller",
    "sg:phone":"+41 32 366 61 66",
    "sg:postcode":"2503",
    "sg:province":"Bern",
    "wof:name":"Klangwerk Gmbh",
    "wof:placetype":"venue"
},
  "geometry": {"coordinates":[7.2513589859,47.1329536438],"type":"Point"}
}