{
  "type": "Feature",
  "properties": {
    "iso:country":"CH",
    "sg:address":"Niederdorfstrasse 49",
    "sg:city":"Z\u00fcrich",
    "sg:orig_category":"RESTAURANTS: TEA-ROOMS",
    "sg:phone":"+41 12611208",
    "sg:postcode":"8001",
    "sg:province":"Z\u00fcrich",
    "wof:name":"Imbiss Und Caf\u00e9-bar Nosch, B. Alkan",
    "wof:placetype":"venue"
},
  "geometry": {"coordinates":[8.5437221527,47.3752975464],"type":"Point"}
}