{
  "type": "Feature",
  "properties": {
    "addr:full":"4303 Kaiseraugst Aargau 4303",
    "addr:postcode":"4303;4303",
    "iso:country":"CH",
    "sg:address":"4303",
    "sg:city":"Kaiseraugst",
    "sg:orig_category":"Campingpl\u00e4tze Detailhandel mit Zeitungen U Zeitschriften Kioske",
    "sg:phone":"+41 33 951 18 43",
    "sg:postcode":"4303",
    "sg:province":"Aargau",
    "wof:name":"Camping Aaregg",
    "wof:placetype":"venue"
},
  "geometry": {"coordinates":[8.048863,46.747787],"type":"Point"}
}