{
  "type": "Feature",
  "properties": {
    "iso:country":"CH",
    "sg:address":"Grand Rue 4",
    "sg:city":"Montreux",
    "sg:orig_category":"Unclassifiable Establishments",
    "sg:postcode":"1820",
    "sg:province":"Vaud",
    "wof:name":"Sa Finanziaria E Commerciale Finco",
    "wof:placetype":"venue"
},
  "geometry": {"coordinates":[9.1283597946,46.2375984192],"type":"Point"}
}