{
  "type": "Feature",
  "properties": {
    "iso:country":"CH",
    "sg:address":"Baarerstrasse 100 6345 Neuheim. Postfach",
    "sg:city":"Neuheim",
    "sg:orig_category":"Interessenvertretungen",
    "sg:postcode":"6345",
    "sg:province":"Zug",
    "wof:name":"Stiftung Ferienhaus Valle",
    "wof:placetype":"venue"
},
  "geometry": {"coordinates":[8.5701198578,47.1973381042],"type":"Point"}
}