{
  "type": "Feature",
  "properties": {
    "addr:full":"Lange R\u00fctti 15 M\u00fcnchenstein Basel-Landschaft 4142",
    "addr:housenumber":"15",
    "addr:postcode":"4142",
    "addr:street":"Lange Ruetti",
    "iso:country":"CH",
    "sg:address":"Lange R\u00fctti 15",
    "sg:city":"M\u00fcnchenstein",
    "sg:orig_category":"Datenverarbeitungsdienste Softwareentwicklung U beratung",
    "sg:phone":"+41 61 413 08 58",
    "sg:postcode":"4142",
    "sg:province":"Basel-Landschaft",
    "wof:name":"Wistar Informatik Ag",
    "wof:placetype":"venue"
},
  "geometry": {"coordinates":[7.624961,47.507221],"type":"Point"}
}