{
  "type": "Feature",
  "properties": {
    "iso:country":"CH",
    "sg:address":"Beillon Chemin De",
    "sg:city":"Venth\u00f4ne",
    "sg:orig_category":"Architektur U Ingenieurb\u00fcros",
    "sg:phone":"+41 27 455 93 15",
    "sg:postcode":"3973",
    "sg:province":"Valais",
    "wof:name":"Ed Plus Gmbh, Extrusion Development",
    "wof:placetype":"venue"
},
  "geometry": {"coordinates":[7.531255,46.307953],"type":"Point"}
}