{
  "type": "Feature",
  "properties": {
    "iso:country":"CH",
    "sg:address":"Bucheggstrasse 6",
    "sg:city":"Grenchen",
    "sg:orig_category":"R\u00fcckgewinnung U Vorbereitung f\u00fcr die Wiederverwertung Recycling von nichtmetallischen Altmaterialien",
    "sg:phone":"+41 79 434 48 93",
    "sg:postcode":"2540",
    "sg:province":"Solothurn",
    "wof:name":"Keller",
    "wof:placetype":"venue"
},
  "geometry": {"coordinates":[7.3967690468,47.1871337891],"type":"Point"}
}