{
  "type": "Feature",
  "properties": {
    "iso:country":"CH",
    "sg:address":"Saint-germain",
    "sg:city":"Savi\u00e8se",
    "sg:classifiers":[
        {
            "category":"Insurance",
            "subcategory":"Insurance Agent",
            "type":"Services"
        }
    ],
    "sg:phone":"+41 27 395 25 56",
    "sg:postcode":"1965",
    "sg:province":"Valais",
    "sg:tags":[
        "versicherungsagenturen",
        "-broker"
    ],
    "wof:name":"Raoul Reynard Nationale Suisse Assurance",
    "wof:placetype":"venue"
},
  "geometry": {"coordinates":[7.3478050232,46.2532310486],"type":"Point"}
}