{
  "type": "Feature",
  "properties": {
    "iso:country":"CH",
    "sg:address":"Vogesenstrasse 577",
    "sg:city":"Basel",
    "sg:orig_category":"Non-Classified Establishments",
    "sg:postcode":"4056",
    "sg:province":"Basel-Stadt",
    "wof:name":"Ivan Moresi Impresa Di Pittura",
    "wof:placetype":"venue"
},
  "geometry": {"coordinates":[9.0178461075,45.8541030884],"type":"Point"}
}