{
  "type": "Feature",
  "properties": {
    "iso:country":"CH",
    "sg:address":"Luzernerstrasse 11",
    "sg:city":"Sins",
    "sg:orig_category":"Herstellung von Frucht U Gem\u00fcses\u00e4ften Herstellung von Obst U Fruchtweinen",
    "sg:phone":"+41 41 787 11 64",
    "sg:postcode":"5643",
    "sg:province":"Aargau",
    "wof:name":"Werner Widmer Mosterei Distillerie",
    "wof:placetype":"venue"
},
  "geometry": {"coordinates":[8.3959112167,47.1898727417],"type":"Point"}
}