{
  "type": "Feature",
  "properties": {
    "iso:country":"CH",
    "sg:address":"Bernstrasse 9",
    "sg:city":"Fraubrunnen",
    "sg:classifiers":[
        {
            "category":"Travel",
            "subcategory":"Hotels & Motels",
            "type":"Entertainment"
        }
    ],
    "sg:phone":"+41 31 767 72 19",
    "sg:postcode":"3312",
    "sg:province":"Bern",
    "sg:tags":[
        "hotels",
        "mit",
        "restaurant"
    ],
    "wof:name":"Hotel Zum L\u00f6wen",
    "wof:placetype":"venue"
},
  "geometry": {"coordinates":[7.5250339508,47.084777832],"type":"Point"}
}