{
  "type": "Feature",
  "properties": {
    "iso:country":"CH",
    "sg:address":"Schweizerhofstrasse 17 8750 Glarus. Postfach",
    "sg:city":"Glarus",
    "sg:orig_category":"Wirtschaftspr\u00fcfung, Steuerberatung U Treuhand",
    "sg:postcode":"8750",
    "sg:province":"Glarus",
    "wof:name":"Trebona Treuhand Und Revisionsgesellschaft",
    "wof:placetype":"venue"
},
  "geometry": {"coordinates":[9.069975853,47.0415344238],"type":"Point"}
}