{
  "type": "Feature",
  "properties": {
    "iso:country":"CH",
    "sg:address":"Ursprungstrasse 13",
    "sg:city":"Aarwangen",
    "sg:orig_category":"Sonstige mit der Informatik verbundene T\u00e4tigkeiten",
    "sg:phone":"+41 62 922 06 89",
    "sg:postcode":"4912",
    "sg:province":"Bern",
    "wof:name":"Oegger Birgit + Co., Edv-schulungen Und Beratung",
    "wof:placetype":"venue"
},
  "geometry": {"coordinates":[7.7681798935,47.2364120483],"type":"Point"}
}