{
  "type": "Feature",
  "properties": {
    "iso:country":"CH",
    "sg:address":"Spitalgasse 37",
    "sg:city":"Bern",
    "sg:orig_category":"Arztpraxen",
    "sg:phone":"+41 31 312 15 06",
    "sg:postcode":"3011",
    "sg:province":"Bern",
    "wof:name":"Dr.med.eric Z\u00fcrcher Spezialarzt Fmh",
    "wof:placetype":"venue"
},
  "geometry": {"coordinates":[7.441596,46.947781],"type":"Point"}
}