{
  "type": "Feature",
  "properties": {
    "iso:country":"CH",
    "sg:address":"Libellules Chemin Des 4 1010 Lausanne. Postfach",
    "sg:city":"Lausanne",
    "sg:orig_category":"Allgemeiner Hoch U Tiefbau",
    "sg:postcode":"1010",
    "sg:province":"Vaud",
    "wof:name":"Massard Patrick Travaux De Fa\u00e7ades; Repr\u00e9sent",
    "wof:placetype":"venue"
},
  "geometry": {"coordinates":[6.643366,46.540428],"type":"Point"}
}