{
  "type": "Feature",
  "properties": {
    "iso:country":"CH",
    "sg:address":"Dorfplatz 7",
    "sg:city":"Niederwichtrach",
    "sg:orig_category":"Herstellung von Metallkonstruktionen Mechanik",
    "sg:phone":"+41 31 781 01 52",
    "sg:postcode":"3114",
    "sg:province":"Bern",
    "wof:name":"Beutler, Werner",
    "wof:placetype":"venue"
},
  "geometry": {"coordinates":[7.5758171082,46.8503227234],"type":"Point"}
}