{
  "type": "Feature",
  "properties": {
    "iso:country":"CH",
    "sg:address":"Via San Gottardo 202.",
    "sg:city":"Minusio",
    "sg:orig_category":"Architektur U Ingenieurb\u00fcros",
    "sg:postcode":"6648",
    "sg:province":"Ticino",
    "wof:name":"Elevars Di Laffranchi L.",
    "wof:placetype":"venue"
},
  "geometry": {"coordinates":[8.843461,46.179287],"type":"Point"}
}