{
  "type": "Feature",
  "properties": {
    "iso:country":"CH",
    "sg:address":"Turin",
    "sg:city":"Salins",
    "sg:classifiers":[
        {
            "category":"Restaurant",
            "type":"Food & Drink"
        }
    ],
    "sg:phone":"+41 27 207 27 29",
    "sg:postcode":"1991",
    "sg:province":"Valais",
    "wof:name":"Caf\u00e9 Belv\u00e9d\u00e8re",
    "wof:placetype":"venue"
},
  "geometry": {"coordinates":[7.3550300598,46.2155303955],"type":"Point"}
}