{
  "type": "Feature",
  "properties": {
    "iso:country":"CH",
    "sg:address":"Lindauerstrasse 7",
    "sg:city":"N\u00fcrensdorf",
    "sg:classifiers":[
        {
            "category":"Restaurant",
            "type":"Food & Drink"
        }
    ],
    "sg:phone":"+41 18371888",
    "sg:postcode":"8309",
    "sg:province":"Z\u00fcrich",
    "wof:name":"Restaurant Linde",
    "wof:placetype":"venue"
},
  "geometry": {"coordinates":[8.6495313644,47.4463806152],"type":"Point"}
}