{
  "type": "Feature",
  "properties": {
    "iso:country":"CH",
    "sg:address":"Dufourstrasse 132 8008 Z\u00fcrich. Postfach",
    "sg:city":"Z\u00fcrich",
    "sg:orig_category":"Fachdetailhandel in Verkaufsr\u00e4umen",
    "sg:phone":"+41 13833834",
    "sg:postcode":"8001",
    "sg:province":"Z\u00fcrich",
    "wof:name":"Guhl Regula Blumenobjekte Blumenatelier. Blumenobjekte, Rauminstallationen",
    "wof:placetype":"venue"
},
  "geometry": {"coordinates":[8.553027153,47.3568687439],"type":"Point"}
}