{
  "type": "Feature",
  "properties": {
    "iso:country":"CH",
    "sg:address":"3037",
    "sg:city":"Herrenschwanden",
    "sg:orig_category":"Primarschulen",
    "sg:phone":"+41 31 301 81 41",
    "sg:postcode":"3037",
    "sg:province":"Bern",
    "wof:name":"Primarschule",
    "wof:placetype":"venue"
},
  "geometry": {"coordinates":[7.4149799347,46.9758300781],"type":"Point"}
}