{
  "type": "Feature",
  "properties": {
    "iso:country":"CH",
    "sg:address":"Burghaldenstrasse 19 5600 Lenzburg. Postfach",
    "sg:city":"Lenzburg",
    "sg:orig_category":"Wirtschaftspr\u00fcfung, Steuerberatung U Treuhand",
    "sg:postcode":"5600",
    "sg:province":"Aargau",
    "wof:name":"Realit Revisions Ag",
    "wof:placetype":"venue"
},
  "geometry": {"coordinates":[8.1795711517,47.3857269287],"type":"Point"}
}