{
  "type": "Feature",
  "properties": {
    "iso:country":"CH",
    "sg:address":"Chalet Abendrot 3818 Grindelwald. Postfach",
    "sg:city":"Grindelwald",
    "sg:orig_category":"Fachdetailhandel in Verkaufsr\u00e4umen",
    "sg:postcode":"3818",
    "sg:province":"Bern",
    "wof:name":"Backdoor Gmbh",
    "wof:placetype":"venue"
},
  "geometry": {"coordinates":[8.0346326828,46.624370575],"type":"Point"}
}