{
  "type": "Feature",
  "properties": {
    "iso:country":"CH",
    "sg:address":"Schulstrasse 34",
    "sg:city":"W\u00fcrenlos",
    "sg:orig_category":"Vorschulen, Kinderg\u00e4rten",
    "sg:phone":"+41 56 436 87 76",
    "sg:postcode":"5436",
    "sg:province":"Aargau",
    "wof:name":"Kindergarten L\u00e4ndli",
    "wof:placetype":"venue"
},
  "geometry": {"coordinates":[8.3664722443,47.4433364868],"type":"Point"}
}