{
  "type": "Feature",
  "properties": {
    "iso:country":"CH",
    "sg:address":"Spitalgasse 10a",
    "sg:city":"Langenthal",
    "sg:orig_category":"Softwareentwicklung U beratung",
    "sg:postcode":"4900",
    "sg:province":"Bern",
    "wof:name":"Creawork, R\u00f6thlisberger Christoph",
    "wof:placetype":"venue"
},
  "geometry": {"coordinates":[7.789899826,47.2111473083],"type":"Point"}
}