{
  "type": "Feature",
  "properties": {
    "iso:country":"CH",
    "sg:address":"Mt-crosin.",
    "sg:city":"Cormoret",
    "sg:classifiers":[
        {
            "category":"Travel",
            "subcategory":"Hotels & Motels",
            "type":"Entertainment"
        }
    ],
    "sg:postcode":"2612",
    "sg:province":"Bern",
    "sg:tags":[
        "hotels",
        "mit",
        "restaurant"
    ],
    "wof:name":"Augstburger U. Gasthof Ochsen",
    "wof:placetype":"venue"
},
  "geometry": {"coordinates":[7.689289093,47.0074958801],"type":"Point"}
}