{
  "type": "Feature",
  "properties": {
    "iso:country":"CH",
    "sg:address":"Herrengasse 15",
    "sg:city":"Schwyz",
    "sg:orig_category":"Finanzierungsinstitutionen",
    "sg:postcode":"6430",
    "sg:province":"Schwyz",
    "wof:name":"H.c.i. Ag Schwyz, Holding F\u00fcr Capital Und Immobilienbeteiligungen",
    "wof:placetype":"venue"
},
  "geometry": {"coordinates":[8.6519975662,47.0216827393],"type":"Point"}
}