{
  "type": "Feature",
  "properties": {
    "iso:country":"CH",
    "sg:address":"Ormisstrasse 118",
    "sg:city":"Meilen",
    "sg:orig_category":"Fahrschulen, Flugschulen",
    "sg:phone":"+41 19232423",
    "sg:postcode":"8706",
    "sg:province":"Z\u00fcrich",
    "wof:name":"Herbert Bernet Autofahrschule",
    "wof:placetype":"venue"
},
  "geometry": {"coordinates":[8.6526432037,47.2706184387],"type":"Point"}
}