{
  "type": "Feature",
  "properties": {
    "iso:country":"CH",
    "sg:address":"6374 Buochs. Postfach 347",
    "sg:city":"Buochs",
    "sg:classifiers":[
        {
            "category":"Education",
            "subcategory":"Vocational School",
            "type":"Public Place"
        }
    ],
    "sg:phone":"+41 56 622 66 33",
    "sg:postcode":"6374",
    "sg:province":"Nidwalden",
    "sg:tags":[
        "koch-",
        "haushaltschulen"
    ],
    "wof:name":"Haushaltungsschule B\u00fcnzmatt",
    "wof:placetype":"venue"
},
  "geometry": {"coordinates":[8.2780599594,47.350528717],"type":"Point"}
}