{
  "type": "Feature",
  "properties": {
    "iso:country":"CH",
    "sg:address":"Kleinjoggstrasse 4 8615 Wermatswil. Postfach",
    "sg:city":"Wermatswil",
    "sg:orig_category":"Forstwirtschaft ohne Dienstleistungen in der Forstwirtschaft",
    "sg:phone":"+41 19751939",
    "sg:postcode":"8615",
    "sg:province":"Z\u00fcrich",
    "wof:name":"Regi Holz Gmbh",
    "wof:placetype":"venue"
},
  "geometry": {"coordinates":[8.7470006943,47.3626976013],"type":"Point"}
}