{
  "type": "Feature",
  "properties": {
    "iso:country":"CH",
    "sg:address":"Zugerstrasse 25",
    "sg:city":"Cham",
    "sg:orig_category":"P\u00e9dicure",
    "sg:phone":"+41 41 780 60 68",
    "sg:postcode":"6330",
    "sg:province":"Zug",
    "wof:name":"Margrith Waller P\u00e9dicure",
    "wof:placetype":"venue"
},
  "geometry": {"coordinates":[8.4627370834,47.1814651489],"type":"Point"}
}