{
  "type": "Feature",
  "properties": {
    "iso:country":"CH",
    "sg:address":"Dorfstr. 43 8645 Jona. Postfach",
    "sg:city":"Bollingen",
    "sg:orig_category":"RESTAURANTS: TEA-ROOMS",
    "sg:postcode":"8715",
    "sg:province":"St. Gallen",
    "wof:name":"Restaurant Schiffahrt Klara Artho",
    "wof:placetype":"venue"
},
  "geometry": {"coordinates":[8.8936195374,47.2190895081],"type":"Point"}
}