{
  "type": "Feature",
  "properties": {
    "iso:country":"CH",
    "sg:address":"Chemin Des Courtines 16",
    "sg:city":"Satigny",
    "sg:classifiers":[
        {
            "category":"Professional",
            "subcategory":"Computer Services",
            "type":"Services"
        }
    ],
    "sg:phone":"+41 22 753 25 30",
    "sg:postcode":"1242",
    "sg:province":"Gen\u00e8ve",
    "sg:tags":[
        "software",
        "postprocessor",
        "cad"
    ],
    "wof:name":"Dynabits S\u00e0rl",
    "wof:placetype":"venue"
},
  "geometry": {"coordinates":[6.038393,46.223377],"type":"Point"}
}