{
  "type": "Feature",
  "properties": {
    "iso:country":"CH",
    "sg:address":"Route De La Maladi\u00e8re 40",
    "sg:city":"Chavannes-renens",
    "sg:classifiers":[
        {
            "category":"Restaurant",
            "type":"Food & Drink"
        }
    ],
    "sg:phone":"+41 21 691 22 20",
    "sg:postcode":"1022",
    "sg:province":"Vaud",
    "wof:name":"Caf\u00e9 De Chavannes",
    "wof:placetype":"venue"
},
  "geometry": {"coordinates":[6.5723118782,46.5275497437],"type":"Point"}
}