{
  "type": "Feature",
  "properties": {
    "iso:country":"CH",
    "sg:address":"Birkenweg 2",
    "sg:city":"Adelboden",
    "sg:orig_category":"Fahrschulen, Flugschulen",
    "sg:phone":"+41 79 310 31 33",
    "sg:postcode":"3715",
    "sg:province":"Bern",
    "wof:name":"Karl Allenbach Autofahrschule",
    "wof:placetype":"venue"
},
  "geometry": {"coordinates":[7.5614237785,46.4841117859],"type":"Point"}
}