{
  "type": "Feature",
  "properties": {
    "iso:country":"CH",
    "sg:address":"Oristalstrasse 98",
    "sg:city":"Liestal",
    "sg:orig_category":"Canalisation",
    "sg:phone":"+41 61 921 99 00",
    "sg:postcode":"4410",
    "sg:province":"Basel-Landschaft",
    "wof:name":"Rudolf Wirz Strassen- Und Tiefbau Ag",
    "wof:placetype":"venue"
},
  "geometry": {"coordinates":[7.720655,47.475361],"type":"Point"}
}