{
  "type": "Feature",
  "properties": {
    "iso:country":"CH",
    "sg:address":"Harzb\u00fcchelstrasse 6",
    "sg:city":"St.gallen",
    "sg:orig_category":"Pensionskassen",
    "sg:phone":"+41 81 756 34 20",
    "sg:postcode":"9000",
    "sg:province":"St. Gallen",
    "wof:name":"Personalf\u00fcrsorgestiftung Der Firma Schrybi Papeterie Und B\u00fcrobedarf Ag Buchs Sg",
    "wof:placetype":"venue"
},
  "geometry": {"coordinates":[9.4755601883,47.1664085388],"type":"Point"}
}