{
  "type": "Feature",
  "properties": {
    "iso:country":"CH",
    "sg:address":"Bahnweg 44 8852 Altendorf. Postfach",
    "sg:city":"Schindellegi",
    "sg:orig_category":"Herstellung von nachrichtentechnischen Ger\u00e4ten U Einrichtungen",
    "sg:phone":"+41 55 440 78 75",
    "sg:postcode":"8834",
    "sg:province":"Schwyz",
    "wof:name":"Baumann Telematik",
    "wof:placetype":"venue"
},
  "geometry": {"coordinates":[8.8410282135,47.1899223328],"type":"Point"}
}