{
  "type": "Feature",
  "properties": {
    "iso:country":"CH",
    "sg:address":"Bernhofstrasse 23",
    "sg:city":"Adliswil",
    "sg:orig_category":"Softwareentwicklung U beratung",
    "sg:postcode":"8134",
    "sg:province":"Z\u00fcrich",
    "wof:name":"Evolusoft (schweiz) Ag",
    "wof:placetype":"venue"
},
  "geometry": {"coordinates":[8.5206689835,47.3017425537],"type":"Point"}
}