{
  "type": "Feature",
  "properties": {
    "iso:country":"CH",
    "sg:address":"Lagerstrasse 47 8004 Z\u00fcrich. Postfach",
    "sg:city":"Z\u00fcrich",
    "sg:orig_category":"Detailhandel mit B\u00fcchern, Zeitungen, Schreib U Papeteriewaren",
    "sg:postcode":"8001",
    "sg:province":"Z\u00fcrich",
    "wof:name":"Brunner & Hiltebrand, Buch Und Kunsthandel",
    "wof:placetype":"venue"
},
  "geometry": {"coordinates":[8.532098,47.37796],"type":"Point"}
}