{
  "type": "Feature",
  "properties": {
    "iso:country":"CH",
    "sg:address":"Untere Geerenstrasse 2",
    "sg:city":"D\u00fcbendorf",
    "sg:orig_category":"Detailhandel mit Fleisch U Fleischwaren",
    "sg:phone":"+41 18223635",
    "sg:postcode":"8600",
    "sg:province":"Z\u00fcrich",
    "wof:name":"Cyrill K\u00e4lin Metzgerei",
    "wof:placetype":"venue"
},
  "geometry": {"coordinates":[8.616859436,47.3896636963],"type":"Point"}
}