{
  "type": "Feature",
  "properties": {
    "iso:country":"CH",
    "sg:address":"Seebacherstrasse 77",
    "sg:city":"Z\u00fcrich",
    "sg:classifiers":[
        {
            "category":"Restaurant",
            "type":"Food & Drink"
        }
    ],
    "sg:phone":"+41 13011414",
    "sg:postcode":"8052",
    "sg:province":"Z\u00fcrich",
    "wof:name":"Restaurant Primavera",
    "wof:placetype":"venue"
},
  "geometry": {"coordinates":[8.5403108597,47.422416687],"type":"Point"}
}