{
  "type": "Feature",
  "properties": {
    "iso:country":"CH",
    "sg:address":"M\u00fclisberg 3",
    "sg:city":"Kaltbrunn",
    "sg:orig_category":"Malerei Tapeziererei",
    "sg:phone":"+41 55 283 33 30",
    "sg:postcode":"8722",
    "sg:province":"St. Gallen",
    "wof:name":"Peter Ciresa Ag Malergesch\u00e4ft",
    "wof:placetype":"venue"
},
  "geometry": {"coordinates":[9.031252861,47.2091522217],"type":"Point"}
}