{
  "type": "Feature",
  "properties": {
    "iso:country":"CH",
    "sg:address":"Chemin De Marclay 9 1253 Vandoeuvres. Postfach",
    "sg:city":"Vandoeuvres",
    "sg:orig_category":"Interessenvertretungen",
    "sg:postcode":"1253",
    "sg:province":"Gen\u00e8ve",
    "wof:name":"Fondation La Colombe",
    "wof:placetype":"venue"
},
  "geometry": {"coordinates":[6.2009429932,46.2289428711],"type":"Point"}
}