{
  "type": "Feature",
  "properties": {
    "iso:country":"CH",
    "sg:address":"Badenerstrasse 891",
    "sg:city":"Z\u00fcrich",
    "sg:orig_category":"Fachdetailhandel in Verkaufsr\u00e4umen",
    "sg:phone":"+41 14314152",
    "sg:postcode":"8048",
    "sg:province":"Z\u00fcrich",
    "wof:name":"Fantini",
    "wof:placetype":"venue"
},
  "geometry": {"coordinates":[8.4719934464,47.3938941956],"type":"Point"}
}