{
  "type": "Feature",
  "properties": {
    "iso:country":"CH",
    "sg:address":"Via Franscini 31",
    "sg:city":"Locarno",
    "sg:orig_category":"Non-Classified Establishments",
    "sg:phone":"+41 91 760 06 30",
    "sg:postcode":"6600",
    "sg:province":"Ticino",
    "wof:name":"Beldoro Ag",
    "wof:placetype":"venue"
},
  "geometry": {"coordinates":[8.7966995239,46.1661109924],"type":"Point"}
}