{
  "type": "Feature",
  "properties": {
    "iso:country":"CH",
    "sg:address":"Rue De La Poste 4",
    "sg:city":"Echallens",
    "sg:orig_category":"Architektur U Ingenieurb\u00fcros",
    "sg:phone":"+41 21 881 13 01",
    "sg:postcode":"1040",
    "sg:province":"Vaud",
    "wof:name":"Bornet Pierre Louis",
    "wof:placetype":"venue"
},
  "geometry": {"coordinates":[6.635287,46.640869],"type":"Point"}
}