{
  "type": "Feature",
  "properties": {
    "iso:country":"CH",
    "sg:address":"Gotthardlistrasse 31",
    "sg:city":"Ennetmoos",
    "sg:orig_category":"RESTAURANTS: TEA-ROOMS",
    "sg:postcode":"6372",
    "sg:province":"Nidwalden",
    "wof:name":"Etinel Ag",
    "wof:placetype":"venue"
},
  "geometry": {"coordinates":[8.3472881317,46.9570960999],"type":"Point"}
}