{
  "type": "Feature",
  "properties": {
    "iso:country":"CH",
    "sg:address":"Ziegelh\u00fctte 589",
    "sg:city":"Flaach",
    "sg:orig_category":"RESTAURANTS: TEA-ROOMS",
    "sg:postcode":"8416",
    "sg:province":"Z\u00fcrich",
    "wof:name":"Restaurant Ziegelh\u00fctte Ag",
    "wof:placetype":"venue"
},
  "geometry": {"coordinates":[8.5817422867,47.5751228333],"type":"Point"}
}