{
  "type": "Feature",
  "properties": {
    "addr:full":"Neuhardstrasse 22 Olten Solothurn 4600",
    "addr:housenumber":"22",
    "addr:postcode":"4600",
    "addr:street":"Neuhardstrasse",
    "iso:country":"CH",
    "sg:address":"Neuhardstrasse 22",
    "sg:city":"Olten",
    "sg:classifiers":[
        {
            "category":"Food & Beverages",
            "subcategory":"Specialty",
            "type":"Retail Goods"
        }
    ],
    "sg:phone":"+41 79 656 68 93",
    "sg:postcode":"4600",
    "sg:province":"Solothurn",
    "sg:tags":[
        "caterer"
    ],
    "wof:name":"Party Peter Party-service",
    "wof:placetype":"venue"
},
  "geometry": {"coordinates":[7.910557,46.707184],"type":"Point"}
}