{
  "type": "Feature",
  "properties": {
    "iso:country":"CH",
    "sg:address":"Furkastrasse",
    "sg:city":"Hospental",
    "sg:orig_category":"Restaurants Sessellifte and Skilifte",
    "sg:phone":"+41 79 607 08 46",
    "sg:postcode":"6493",
    "sg:province":"Uri",
    "wof:name":"Sportbahnen Winterhorn",
    "wof:placetype":"venue"
},
  "geometry": {"coordinates":[8.5654888153,46.6179351807],"type":"Point"}
}