{
  "type": "Feature",
  "properties": {
    "iso:country":"CH",
    "sg:address":"Chemin De La Mochettaz 18 1030 Bussigny-lausanne Case Postale 106",
    "sg:city":"Bussigny-lausanne",
    "sg:orig_category":"Installation von Heizungs, L\u00fcftungs U Klimaanlagen Sanit\u00e4r U Heizungsinstallation",
    "sg:phone":"+41 21 701 45 35",
    "sg:postcode":"1030",
    "sg:province":"Vaud",
    "wof:name":"Ei 3 C Sa",
    "wof:placetype":"venue"
},
  "geometry": {"coordinates":[6.5463590622,46.5483894348],"type":"Point"}
}