{
  "type": "Feature",
  "properties": {
    "iso:country":"CH",
    "sg:address":"Oberneuhofstrasse 7 6340 Baar. Postfach 4142",
    "sg:city":"Zug",
    "sg:orig_category":"Malerei",
    "sg:phone":"+41 41 760 38 30",
    "sg:postcode":"6304",
    "sg:province":"Zug",
    "wof:name":"Maler Blaser Team Ag",
    "wof:placetype":"venue"
},
  "geometry": {"coordinates":[8.5168037415,47.1889686584],"type":"Point"}
}