{
  "type": "Feature",
  "properties": {
    "iso:country":"CH",
    "sg:address":"Franklinstrasse 21 8000 Z\u00fcrich. Postfach 8050 Z\u00fcrich",
    "sg:city":"Zust",
    "sg:orig_category":"Wirtschaftspr\u00fcfung, Steuerberatung U Treuhand",
    "sg:postcode":"50",
    "wof:name":"Sprenger S. Steuerberatung",
    "wof:placetype":"venue"
},
  "geometry": {"coordinates":[8.5445842743,47.4092292786],"type":"Point"}
}