{
  "type": "Feature",
  "properties": {
    "iso:country":"CH",
    "sg:address":"Cit\u00e9 Vieusseux 11",
    "sg:city":"Gen\u00e8ve",
    "sg:classifiers":[
        {
            "category":"Restaurant",
            "type":"Food & Drink"
        }
    ],
    "sg:phone":"+41 21 634 02 27",
    "sg:postcode":"1203",
    "sg:province":"Gen\u00e8ve",
    "wof:name":"Brasserie De La Gare Restaurant & Pizzeria",
    "wof:placetype":"venue"
},
  "geometry": {"coordinates":[6.5793418884,46.5363693237],"type":"Point"}
}