{
  "type": "Feature",
  "properties": {
    "addr:full":"Alpenstrasse 6 G\u00fcmligen Bern 3073",
    "addr:housenumber":"6",
    "addr:postcode":"3073",
    "addr:street":"Alpenstrasse",
    "iso:country":"CH",
    "sg:address":"Alpenstrasse 6",
    "sg:city":"G\u00fcmligen",
    "sg:orig_category":"Detailhandel mit Brot, Back U S\u00fcsswaren",
    "sg:phone":"+41 79 300 78 77",
    "sg:postcode":"3073",
    "sg:province":"Bern",
    "wof:name":"B\u00e4ckerei-konditorei Fuhrer J.& U.grossenbacher",
    "wof:placetype":"venue"
},
  "geometry": {"coordinates":[7.498451,46.935356],"type":"Point"}
}