{
  "type": "Feature",
  "properties": {
    "iso:country":"CH",
    "sg:address":"Postplatz 3",
    "sg:city":"Steinen",
    "sg:classifiers":[
        {
            "category":"Banks & Credit Unions",
            "subcategory":"Bank",
            "type":"Services"
        }
    ],
    "sg:phone":"+41 4143411616",
    "sg:postcode":"6422",
    "sg:province":"Schwyz",
    "wof:name":"Schwyzer Kantonalbank",
    "wof:placetype":"venue"
},
  "geometry": {"coordinates":[8.611837,47.049576],"type":"Point"}
}