{
  "type": "Feature",
  "properties": {
    "iso:country":"CH",
    "sg:address":"Industriestrasse 17",
    "sg:city":"Luzern",
    "sg:orig_category":"Sonstiger Grosshandel",
    "sg:phone":"+41 41 360 30 22",
    "sg:postcode":"6005",
    "sg:province":"Luzern",
    "wof:name":"Side Walk Handelsagentur Barmettler",
    "wof:placetype":"venue"
},
  "geometry": {"coordinates":[8.3120136261,47.0407409668],"type":"Point"}
}