{
  "type": "Feature",
  "properties": {
    "iso:country":"CH",
    "sg:address":"Rigistrasse 171b 6340 Baar. Postfach 1040",
    "sg:city":"Baar",
    "sg:orig_category":"Handelsvermittlung U Grosshandel",
    "sg:phone":"+41 79 252 32 79",
    "sg:postcode":"6341",
    "sg:province":"Zug",
    "wof:name":"Tassoco Sa",
    "wof:placetype":"venue"
},
  "geometry": {"coordinates":[6.1670389175,46.2772636414],"type":"Point"}
}