{
  "type": "Feature",
  "properties": {
    "iso:country":"CH",
    "sg:address":"Riedhofstrasse 159 8400 Winterthur. Postfach",
    "sg:city":"Winterthur",
    "sg:orig_category":"Verwertung von Milch",
    "sg:postcode":"8408",
    "sg:province":"Z\u00fcrich",
    "wof:name":"Mg Milchproduzenten-genossenschaft W\u00fclflingen",
    "wof:placetype":"venue"
},
  "geometry": {"coordinates":[8.6917829514,47.5287590027],"type":"Point"}
}