{
  "type": "Feature",
  "properties": {
    "iso:country":"CH",
    "sg:address":"Bahnhofstrasse 34",
    "sg:city":"Aarburg",
    "sg:orig_category":"Grosshandel mit Textilien",
    "sg:phone":"+41 62 791 46 00",
    "sg:postcode":"4663",
    "sg:province":"Aargau",
    "wof:name":"Fashion Field Ag",
    "wof:placetype":"venue"
},
  "geometry": {"coordinates":[7.9049072266,47.3210983276],"type":"Point"}
}