{
  "type": "Feature",
  "properties": {
    "iso:country":"CH",
    "sg:address":"Alpentherme",
    "sg:city":"Leukerbad",
    "sg:classifiers":[
        {
            "category":"Banks & Credit Unions",
            "subcategory":"Bank",
            "type":"Services"
        }
    ],
    "sg:phone":"+41 27 472 78 20",
    "sg:postcode":"3954",
    "sg:province":"Valais",
    "wof:name":"Walliser Kantonalbank",
    "wof:placetype":"venue"
},
  "geometry": {"coordinates":[7.6253261566,46.3759307861],"type":"Point"}
}