{
  "type": "Feature",
  "properties": {
    "iso:country":"CH",
    "sg:address":"Im Baumgarten 20",
    "sg:city":"Zufikon",
    "sg:orig_category":"Sportvereine Turnen Vereine Damen",
    "sg:phone":"+41 56 633 44 73",
    "sg:postcode":"5621",
    "sg:province":"Aargau",
    "wof:name":"Turnerinnen Svkt Zufikon",
    "wof:placetype":"venue"
},
  "geometry": {"coordinates":[8.3547697067,47.3459129333],"type":"Point"}
}