{
  "type": "Feature",
  "properties": {
    "iso:country":"CH",
    "sg:address":"Libert\u00e9 Impasse De La 6 1632 Riaz. Postfach",
    "sg:city":"Riaz",
    "sg:orig_category":"Detailhandel mit elektrischen Haushalts-,Radio U Fernsehger\u00e4ten sowie Musikinstrumenten",
    "sg:postcode":"1632",
    "sg:province":"Fribourg",
    "wof:name":"Sofa Partner Sa Articles De La Maison, De L'habitat; Import., Export., Achat Etc",
    "wof:placetype":"venue"
},
  "geometry": {"coordinates":[7.0612578392,46.6383972168],"type":"Point"}
}