{
  "type": "Feature",
  "properties": {
    "iso:country":"CH",
    "sg:address":"Blattackerstrasse 6/8 9435 Heerbrugg. Postfach",
    "sg:city":"Heerbrugg",
    "sg:orig_category":"Interessenvertretungen",
    "sg:postcode":"9435",
    "sg:province":"St. Gallen",
    "wof:name":"Hausgenossenschaft Blattackerstrasse 6/8",
    "wof:placetype":"venue"
},
  "geometry": {"coordinates":[9.6280164719,47.4141426086],"type":"Point"}
}