{
  "type": "Feature",
  "properties": {
    "iso:country":"CH",
    "sg:address":"Hauptstrasse 78",
    "sg:city":"Birsfelden",
    "sg:orig_category":"Reiseb\u00fcros U Reiseveranstalter",
    "sg:postcode":"4127",
    "sg:province":"Basel-Landschaft",
    "wof:name":"Philair Resources Gmbh",
    "wof:placetype":"venue"
},
  "geometry": {"coordinates":[7.6228718758,47.5527038574],"type":"Point"}
}