{
  "type": "Feature",
  "properties": {
    "iso:country":"CH",
    "sg:address":"1742",
    "sg:city":"Autigny",
    "sg:orig_category":"Bauingenieurb\u00fcros allgemein",
    "sg:phone":"+41 26 477 07 00",
    "sg:postcode":"1742",
    "sg:province":"Fribourg",
    "wof:name":"Jeanneret Etudes Sa Bureau D'ing\u00e9nieurs",
    "wof:placetype":"venue"
},
  "geometry": {"coordinates":[7.01836,46.736584],"type":"Point"}
}