{
  "type": "Feature",
  "properties": {
    "addr:full":"M\u00fchleweg 10 Ebikon Luzern 6030",
    "addr:housenumber":"10",
    "addr:postcode":"6030",
    "addr:street":"Muehleweg",
    "iso:country":"CH",
    "sg:address":"M\u00fchleweg 10",
    "sg:city":"Ebikon",
    "sg:classifiers":[
        {
            "category":"Banks & Credit Unions",
            "subcategory":"Bank",
            "type":"Services"
        }
    ],
    "sg:phone":"+41 4141332628",
    "sg:postcode":"6030",
    "sg:province":"Luzern",
    "wof:name":"Schweiz. National",
    "wof:placetype":"venue"
},
  "geometry": {"coordinates":[8.338023,47.07362],"type":"Point"}
}