{
  "type": "Feature",
  "properties": {
    "iso:country":"CH",
    "sg:address":"B\u00e4renstutz 15",
    "sg:city":"M\u00fcnsingen",
    "sg:orig_category":"Architektur U Ingenieurb\u00fcros",
    "sg:phone":"+41 31 724 30 30",
    "sg:postcode":"3110",
    "sg:province":"Bern",
    "wof:name":"Jordi + Kolb Ag",
    "wof:placetype":"venue"
},
  "geometry": {"coordinates":[7.565128,46.880882],"type":"Point"}
}