{
  "type": "Feature",
  "properties": {
    "iso:country":"CH",
    "sg:address":"Br\u00fcckenstrasse 13",
    "sg:city":"Bern",
    "sg:orig_category":"Kosmetikinstitute",
    "sg:phone":"+41 31 311 36 60",
    "sg:postcode":"3005",
    "sg:province":"Bern",
    "wof:name":"Modern Times Monika Jordi Coiffure & Kosmetik",
    "wof:placetype":"venue"
},
  "geometry": {"coordinates":[7.4434781075,46.9445533752],"type":"Point"}
}