{
  "type": "Feature",
  "properties": {
    "iso:country":"CH",
    "sg:address":"Hauptstrasse",
    "sg:city":"Weesen",
    "sg:orig_category":"Arbeitnehmerverb\u00e4nde",
    "sg:postcode":"8872",
    "sg:province":"St. Gallen",
    "wof:name":"Ptt-union Sektion Rapperswil",
    "wof:placetype":"venue"
},
  "geometry": {"coordinates":[8.799535,47.213333],"type":"Point"}
}