{
  "type": "Feature",
  "properties": {
    "iso:country":"CH",
    "sg:address":"Schlossweg 24 9496 Balzers. Postfach 175",
    "sg:city":"Balzers",
    "sg:orig_category":"Grosshandel mit Foto U Kinoger\u00e4ten, feinmechanischen U optischen Erzeugnissen",
    "sg:phone":"+423 388 11 50",
    "sg:postcode":"9496",
    "wof:name":"Filtrop Ag Handelsunternehmen",
    "wof:placetype":"venue"
},
  "geometry": {"coordinates":[9.496925354,47.0677566528],"type":"Point"}
}