{
  "type": "Feature",
  "properties": {
    "iso:country":"CH",
    "sg:address":"Bremgartenstrasse 44",
    "sg:city":"Waltenschwil",
    "sg:orig_category":"Unclassifiable Establishments",
    "sg:postcode":"5622",
    "sg:province":"Aargau",
    "wof:name":"Wyrsch Cooperation Ag",
    "wof:placetype":"venue"
},
  "geometry": {"coordinates":[8.3087968826,47.3340797424],"type":"Point"}
}