{
  "type": "Feature",
  "properties": {
    "iso:country":"CH",
    "sg:address":"Gr\u00fcndenstrasse 82",
    "sg:city":"Flurlingen",
    "sg:orig_category":"Non-Classified Establishments",
    "sg:phone":"+41 71 622 27 04",
    "sg:postcode":"8247",
    "sg:province":"Z\u00fcrich",
    "wof:name":"Red Power Holding Ag",
    "wof:placetype":"venue"
},
  "geometry": {"coordinates":[8.6259412766,47.6893997192],"type":"Point"}
}