{
  "type": "Feature",
  "properties": {
    "iso:country":"CH",
    "sg:address":"1545",
    "sg:city":"Chevroux",
    "sg:orig_category":"Maurerarbeiten",
    "sg:phone":"+41 21 861 19 37",
    "sg:postcode":"1545",
    "sg:province":"Vaud",
    "wof:name":"Raymond Pache Ma\u00e7onnerie",
    "wof:placetype":"venue"
},
  "geometry": {"coordinates":[6.4716591835,46.5558280945],"type":"Point"}
}