{
  "type": "Feature",
  "properties": {
    "iso:country":"CH",
    "sg:address":"Stichermattstrasse 7",
    "sg:city":"Emmen",
    "sg:orig_category":"Unclassifiable Establishments",
    "sg:postcode":"6032",
    "sg:province":"Luzern",
    "wof:name":"Hans & Walter Stucki Dorflade Lebensmittel",
    "wof:placetype":"venue"
},
  "geometry": {"coordinates":[8.3003921509,47.0772857666],"type":"Point"}
}