{
  "type": "Feature",
  "properties": {
    "iso:country":"CH",
    "sg:address":"Bachtobelstrasse 3",
    "sg:city":"Horgen",
    "sg:orig_category":"Fachdetailhandel in Verkaufsr\u00e4umen Grosshandel mit Schmuck",
    "sg:phone":"+41 17283800",
    "sg:postcode":"8810",
    "sg:province":"Z\u00fcrich",
    "wof:name":"Signity Ag",
    "wof:placetype":"venue"
},
  "geometry": {"coordinates":[8.6176748276,47.2503967285],"type":"Point"}
}