{
  "type": "Feature",
  "properties": {
    "iso:country":"CH",
    "sg:address":"Livio Via 1",
    "sg:city":"Chiasso",
    "sg:orig_category":"Markt U Meinungsforschung",
    "sg:phone":"+41 91430822",
    "sg:postcode":"6830",
    "sg:province":"Ticino",
    "wof:name":"Malibu Limited Liability Company, Palo Alto, California, (usa), Succursale Di Chiasso",
    "wof:placetype":"venue"
},
  "geometry": {"coordinates":[9.029876709,45.8333625793],"type":"Point"}
}