{
  "type": "Feature",
  "properties": {
    "iso:country":"CH",
    "sg:address":"Gen\u00e8ve Rue De 87 1004 Lausanne Case Postale",
    "sg:city":"Lausanne",
    "sg:orig_category":"Sanit\u00e4r, Heizungs U L\u00fcftungsinstallation",
    "sg:postcode":"1003",
    "sg:province":"Vaud",
    "wof:name":"Genicoud Cl. Installations Sanitaires",
    "wof:placetype":"venue"
},
  "geometry": {"coordinates":[6.6132569313,46.524887085],"type":"Point"}
}