{
  "type": "Feature",
  "properties": {
    "iso:country":"CH",
    "sg:address":"Sch\u00fcrrainweg 2",
    "sg:city":"Schlieren",
    "sg:orig_category":"Bezirks, Sekundar, Realschulen, Oberstufe der Primarschulen",
    "sg:phone":"+41 27 474 99 11",
    "sg:postcode":"8952",
    "sg:province":"Z\u00fcrich",
    "wof:name":"Berufswahlschule Oberwallis",
    "wof:placetype":"venue"
},
  "geometry": {"coordinates":[7.63466,46.31633],"type":"Point"}
}