{
  "type": "Feature",
  "properties": {
    "addr:full":"Oetlisbergstrasse 12 Z\u00fcrich Z\u00fcrich 8053",
    "addr:housenumber":"12",
    "addr:postcode":"8053",
    "addr:street":"Oetlisbergstrasse",
    "iso:country":"CH",
    "sg:address":"Oetlisbergstrasse 12",
    "sg:city":"Z\u00fcrich",
    "sg:orig_category":"Architektur U Ingenieurb\u00fcros",
    "sg:phone":"+41 13835961",
    "sg:postcode":"8053",
    "sg:province":"Z\u00fcrich",
    "wof:name":"Vero Consult, Eugen Vernocchi",
    "wof:placetype":"venue"
},
  "geometry": {"coordinates":[8.595925,47.359596],"type":"Point"}
}