{
  "type": "Feature",
  "properties": {
    "iso:country":"CH",
    "sg:address":"Immeuble Les Arcades",
    "sg:city":"Anz\u00e8re",
    "sg:orig_category":"Elektroinstallation",
    "sg:phone":"+41 61 821 47 27",
    "sg:postcode":"1972",
    "sg:province":"Valais",
    "wof:name":"Widrig + Mottarelli Ag",
    "wof:placetype":"venue"
},
  "geometry": {"coordinates":[7.6741800308,47.5207901001],"type":"Point"}
}