{
  "type": "Feature",
  "properties": {
    "iso:country":"CH",
    "sg:address":"Sch\u00fcrmattstrasse 2b 6331 H\u00fcnenberg. Postfach",
    "sg:city":"H\u00fcnenberg",
    "sg:orig_category":"Kauf U Verkauf von Immobilien auf eigene Rechnung",
    "sg:phone":"+41 79 600 56 77",
    "sg:postcode":"6331",
    "sg:province":"Zug",
    "wof:name":"Bkk B\u00fcrger Kontakt Kommunikation Gmbh",
    "wof:placetype":"venue"
},
  "geometry": {"coordinates":[9.6351919174,47.4310073853],"type":"Point"}
}