{
  "type": "Feature",
  "properties": {
    "iso:country":"CH",
    "sg:address":"Schlossstrasse 59",
    "sg:city":"Herisau",
    "sg:orig_category":"Unclassifiable Establishments",
    "sg:postcode":"9100",
    "sg:province":"Appenzell Ausserrhoden",
    "wof:name":"Diemag Beteiligungs Ag",
    "wof:placetype":"venue"
},
  "geometry": {"coordinates":[9.2671356201,47.3772201538],"type":"Point"}
}