{
  "type": "Feature",
  "properties": {
    "iso:country":"CH",
    "sg:address":"Sch\u00fctzenmattstrasse 52",
    "sg:city":"Basel",
    "sg:orig_category":"Physiotherapie Sonstige Aktivit\u00e4ten der nicht-\u00e4rztlichen Medizinalberufe",
    "sg:phone":"+41 61 272 72 75",
    "sg:postcode":"4051",
    "sg:province":"Basel-Stadt",
    "wof:name":"Eleonore Herzig Physiotherapie & Kinesiologie",
    "wof:placetype":"venue"
},
  "geometry": {"coordinates":[7.579064846,47.5545692444],"type":"Point"}
}