{
  "type": "Feature",
  "properties": {
    "iso:country":"CH",
    "sg:address":"Dachslerenstrasse 10",
    "sg:city":"Zollikon",
    "sg:orig_category":"Detailhandel mit M\u00f6beln Innendekorationsateliers",
    "sg:phone":"+41 32 342 30 29",
    "sg:postcode":"8702",
    "sg:province":"Z\u00fcrich",
    "wof:name":"Kauer Trend M\u00f6belmarkt Ag M\u00f6bel, Accessoires, Konsumprodukte Usw.; Handel",
    "wof:placetype":"venue"
},
  "geometry": {"coordinates":[7.275911808,47.1485557556],"type":"Point"}
}