{
  "type": "Feature",
  "properties": {
    "iso:country":"CH",
    "sg:address":"Bondastrasse 117a",
    "sg:city":"Chur",
    "sg:orig_category":"Herstellung von Teppichen Verlegen von Fliesen U Platten",
    "sg:phone":"+41 81 353 70 60",
    "sg:postcode":"7000",
    "sg:province":"Graubunden",
    "wof:name":"Kurt & Gina Kunfermann K\u00fcmpfis B\u00f6den",
    "wof:placetype":"venue"
},
  "geometry": {"coordinates":[9.5464267731,46.8614311218],"type":"Point"}
}