{
  "type": "Feature",
  "properties": {
    "iso:country":"CH",
    "sg:address":"Kirchstrasse 106 6454 Fl\u00fcelen. Postfach 31",
    "sg:city":"Fl\u00fcelen",
    "sg:orig_category":"Detailhandel mit Uhren U Schmuck Herstellung von Schmuck, Gold U Silberschmiedwaren",
    "sg:phone":"+41 41 870 58 45",
    "sg:postcode":"6454",
    "sg:province":"Uri",
    "wof:name":"Werner Epp, Goldschmied",
    "wof:placetype":"venue"
},
  "geometry": {"coordinates":[8.624458313,46.9095840454],"type":"Point"}
}