{
  "type": "Feature",
  "properties": {
    "iso:country":"CH",
    "sg:address":"Abendweg 8c",
    "sg:city":"Frauenfeld",
    "sg:orig_category":"Dachdeckerei",
    "sg:phone":"+41 52 720 80 27",
    "sg:postcode":"8500",
    "sg:province":"Thurgau",
    "wof:name":"Bruno Stadelmann Dachdeckergesch\u00e4ft",
    "wof:placetype":"venue"
},
  "geometry": {"coordinates":[8.880658,47.560749],"type":"Point"}
}