{
  "type": "Feature",
  "properties": {
    "iso:country":"CH",
    "sg:address":"Contrada Cav. Pellanda 16",
    "sg:city":"Biasca",
    "sg:orig_category":"W\u00e4scherei U chemische Reinigung",
    "sg:phone":"+41 79 353 90 84",
    "sg:postcode":"6710",
    "sg:province":"Ticino",
    "wof:name":"De Rosa Sa",
    "wof:placetype":"venue"
},
  "geometry": {"coordinates":[8.9710493088,46.3605995178],"type":"Point"}
}