{
  "type": "Feature",
  "properties": {
    "iso:country":"CH",
    "sg:address":"Schaffhauserstrasse 144",
    "sg:city":"Kloten",
    "sg:orig_category":"Detailhandel mit Waren verschiedener Art, Hauptrichtung Nahrungsmittel",
    "sg:phone":"+41 41 760 10 60",
    "sg:postcode":"8302",
    "sg:province":"Z\u00fcrich",
    "wof:name":"Gidor Coiffure",
    "wof:placetype":"venue"
},
  "geometry": {"coordinates":[8.5805521011,47.4532241821],"type":"Point"}
}