{
  "type": "Feature",
  "properties": {
    "addr:full":"Bahnhofstrasse 10 Dottikon Aargau 5605",
    "addr:housenumber":"10",
    "addr:postcode":"5605",
    "addr:street":"Bahnhofstrasse",
    "iso:country":"CH",
    "sg:address":"Bahnhofstrasse 10",
    "sg:city":"Dottikon",
    "sg:orig_category":"Architektur U Ingenieurb\u00fcros",
    "sg:postcode":"5605",
    "sg:province":"Aargau",
    "wof:name":"Ag Ingenieurb\u00fcro Maggia, Zweigniederlassung Gossau",
    "wof:placetype":"venue"
},
  "geometry": {"coordinates":[9.253502,47.412487],"type":"Point"}
}