{
  "type": "Feature",
  "properties": {
    "iso:country":"CH",
    "sg:address":"Dorfstrasse 35 3073 G\u00fcmligen. Postfach",
    "sg:city":"G\u00fcmligen",
    "sg:orig_category":"Herstellung von sonstigen Nahrungsmitteln",
    "sg:phone":"+41 79 290 15 37",
    "sg:postcode":"3073",
    "sg:province":"Bern",
    "wof:name":"Binex Gmbh",
    "wof:placetype":"venue"
},
  "geometry": {"coordinates":[8.4394645691,47.4571990967],"type":"Point"}
}