{
  "type": "Feature",
  "properties": {
    "iso:country":"CH",
    "sg:address":"Zentralstrasse 32",
    "sg:city":"Biel/bienne",
    "sg:orig_category":"Fachdetailhandel in Verkaufsr\u00e4umen",
    "sg:phone":"+41 32 322 36 36",
    "sg:postcode":"2500",
    "sg:province":"Bern",
    "wof:name":"Silberschmiede Menn, Grossniklaus & Co",
    "wof:placetype":"venue"
},
  "geometry": {"coordinates":[7.2452888489,47.1380157471],"type":"Point"}
}