{
  "type": "Feature",
  "properties": {
    "iso:country":"CH",
    "sg:address":"Kleinh\u00fcningerstrasse 196 4057 Basel. Postfach",
    "sg:city":"Basel",
    "sg:orig_category":"Druck ohne Zeitungsdruck",
    "sg:postcode":"4051",
    "sg:province":"Basel-Stadt",
    "wof:name":"Eduard Rosenzopf Drucksachen Usw",
    "wof:placetype":"venue"
},
  "geometry": {"coordinates":[7.5914969444,47.5805168152],"type":"Point"}
}