{
  "type": "Feature",
  "properties": {
    "iso:country":"CH",
    "sg:address":"Chiossaccio",
    "sg:city":"Cevio",
    "sg:orig_category":"Herstellung U Zusammensetzung von Uhren",
    "sg:phone":"+41 91 754 24 94",
    "sg:postcode":"6675",
    "sg:province":"Ticino",
    "wof:name":"Achor Sa",
    "wof:placetype":"venue"
},
  "geometry": {"coordinates":[8.6014146805,46.3167762756],"type":"Point"}
}