{
  "type": "Feature",
  "properties": {
    "iso:country":"CH",
    "sg:address":"6618",
    "sg:city":"Arcegno",
    "sg:orig_category":"RESTAURANTS: TEA-ROOMS",
    "sg:phone":"+41 91 792 15 14",
    "sg:postcode":"6618",
    "sg:province":"Ticino",
    "wof:name":"Grotto La Risata",
    "wof:placetype":"venue"
},
  "geometry": {"coordinates":[8.7331104279,46.1613082886],"type":"Point"}
}