{
  "type": "Feature",
  "properties": {
    "iso:country":"CH",
    "sg:address":"Lindenweg 1",
    "sg:city":"Birsfelden",
    "sg:orig_category":"Ingenieurb\u00fcros Umwelttechnik and \u00d6kologie Unternehmensberatung",
    "sg:phone":"+41 31 832 10 30",
    "sg:postcode":"4127",
    "sg:province":"Basel-Landschaft",
    "wof:name":"Hofmann + Partner Gmbh",
    "wof:placetype":"venue"
},
  "geometry": {"coordinates":[7.5760140419,46.9278182983],"type":"Point"}
}