{
  "type": "Feature",
  "properties": {
    "iso:country":"CH",
    "sg:address":"Winkelriedstrasse 67",
    "sg:city":"Bern",
    "sg:orig_category":"Sportvereine Ballsport Fussball",
    "sg:phone":"+41 31 331 50 37",
    "sg:postcode":"3014",
    "sg:province":"Bern",
    "wof:name":"Fc Ticino Bern",
    "wof:placetype":"venue"
},
  "geometry": {"coordinates":[7.4553399086,46.9631843567],"type":"Point"}
}