{
  "type": "Feature",
  "properties": {
    "iso:country":"CH",
    "sg:address":"Bahnhofstrasse 17",
    "sg:city":"Lyssach",
    "sg:orig_category":"Tankstellen",
    "sg:phone":"+41 34 445 03 89",
    "sg:postcode":"3421",
    "sg:province":"Bern",
    "wof:name":"Sch\u00e4r Thomas Gmbh",
    "wof:placetype":"venue"
},
  "geometry": {"coordinates":[7.5796232224,47.0644378662],"type":"Point"}
}