{
  "type": "Feature",
  "properties": {
    "iso:country":"CH",
    "sg:address":"Parc Du Martin-p\u00eacheur 1",
    "sg:city":"Th\u00f4nex",
    "sg:orig_category":"Kosmetikinstitute",
    "sg:phone":"+41 22 348 65 32",
    "sg:postcode":"1226",
    "sg:province":"Gen\u00e8ve",
    "wof:name":"Fran\u00e7oise Deage Institut De Beaut\u00e9 Firmousse",
    "wof:placetype":"venue"
},
  "geometry": {"coordinates":[6.2178578377,46.1989173889],"type":"Point"}
}