{
  "type": "Feature",
  "properties": {
    "iso:country":"CH",
    "sg:address":"5064",
    "sg:city":"Wittnau",
    "sg:orig_category":"Vereine Musik/Blasmusik",
    "sg:phone":"+41 62 871 02 07",
    "sg:postcode":"5064",
    "sg:province":"Aargau",
    "wof:name":"Musikgesellschaft",
    "wof:placetype":"venue"
},
  "geometry": {"coordinates":[7.9845299721,47.4830818176],"type":"Point"}
}