{
  "type": "Feature",
  "properties": {
    "addr:full":"Avenue Du Midi 12 Sion Valais 1951",
    "addr:housenumber":"12",
    "addr:postcode":"1951",
    "addr:street":"Avenue Du Midi",
    "iso:country":"CH",
    "sg:address":"Avenue Du Midi 12",
    "sg:city":"Sion",
    "sg:classifiers":[
        {
            "category":"Banks & Credit Unions",
            "subcategory":"Bank",
            "type":"Services"
        }
    ],
    "sg:phone":"+41 27 329 71 11",
    "sg:postcode":"1951",
    "sg:province":"Valais",
    "wof:name":"Cr\u00e9dit Suisse",
    "wof:placetype":"venue"
},
  "geometry": {"coordinates":[7.359337,46.230759],"type":"Point"}
}