{
  "type": "Feature",
  "properties": {
    "addr:full":"Sunnentalstrasse 13 Wolfhausen Z\u00fcrich 8633",
    "addr:housenumber":"13",
    "addr:postcode":"8633",
    "addr:street":"Sunnentalstrasse",
    "iso:country":"CH",
    "sg:address":"Sunnentalstrasse 13",
    "sg:city":"Wolfhausen",
    "sg:orig_category":"Datenverarbeitungsdienste",
    "sg:phone":"+41 55 243 46 50",
    "sg:postcode":"8633",
    "sg:province":"Z\u00fcrich",
    "wof:name":"Freddy Ringier Tcc The True Connection",
    "wof:placetype":"venue"
},
  "geometry": {"coordinates":[8.804744,47.254395],"type":"Point"}
}