{
  "type": "Feature",
  "properties": {
    "iso:country":"CH",
    "sg:address":"Rue Des Rosiers 2a",
    "sg:city":"Ste-croix",
    "sg:orig_category":"Hardwareberatung",
    "sg:phone":"+41 24 454 43 38",
    "sg:postcode":"1450",
    "sg:province":"Vaud",
    "wof:name":"Holland Sylvie, Siltech",
    "wof:placetype":"venue"
},
  "geometry": {"coordinates":[6.4989581108,46.8232803345],"type":"Point"}
}