{
  "type": "Feature",
  "properties": {
    "iso:country":"CH",
    "sg:address":"Le Chaffard",
    "sg:city":"St-livres",
    "sg:orig_category":"Detailhandel mit elektrischen Haushalts-,Radio U Fernsehger\u00e4ten sowie Musikinstrumenten",
    "sg:phone":"+41 21 808 73 21",
    "sg:postcode":"1176",
    "sg:province":"Vaud",
    "wof:name":"Giroud G\u00e9rald, Electrom\u00e9nagers",
    "wof:placetype":"venue"
},
  "geometry": {"coordinates":[6.3874292374,46.5084075928],"type":"Point"}
}