{
  "type": "Feature",
  "properties": {
    "iso:country":"CH",
    "sg:address":"Lehensteig 21",
    "sg:city":"Z\u00fcrich",
    "sg:orig_category":"Softwareentwicklung U beratung",
    "sg:postcode":"8037",
    "sg:province":"Z\u00fcrich",
    "wof:name":"Sch\u00f6ning Consulting",
    "wof:placetype":"venue"
},
  "geometry": {"coordinates":[8.5244903564,47.3946304321],"type":"Point"}
}