{
  "type": "Feature",
  "properties": {
    "iso:country":"CH",
    "sg:address":"Allmendstrasse 13",
    "sg:city":"Oberengstringen",
    "sg:orig_category":"RESTAURANTS: TEA-ROOMS",
    "sg:phone":"+41 55 440 23 22",
    "sg:postcode":"8102",
    "sg:province":"Z\u00fcrich",
    "wof:name":"Restaurant Flugplatz",
    "wof:placetype":"venue"
},
  "geometry": {"coordinates":[8.8646497726,47.2023887634],"type":"Point"}
}