{
  "type": "Feature",
  "properties": {
    "iso:country":"CH",
    "sg:address":"Berggasse 24",
    "sg:city":"K\u00f6lliken",
    "sg:orig_category":"Primarschulen",
    "sg:phone":"+41 62 723 24 80",
    "sg:postcode":"5742",
    "sg:province":"Aargau",
    "wof:name":"Primarschule",
    "wof:placetype":"venue"
},
  "geometry": {"coordinates":[8.0194101334,47.3346786499],"type":"Point"}
}