{
  "type": "Feature",
  "properties": {
    "iso:country":"CH",
    "sg:address":"Alte Strasse 244b",
    "sg:city":"Thusis",
    "sg:orig_category":"Betrieb von Taxis",
    "sg:phone":"+41 81 651 55 77",
    "sg:postcode":"7430",
    "sg:province":"Graubunden",
    "wof:name":"Adrian Fuchs Taxi-service",
    "wof:placetype":"venue"
},
  "geometry": {"coordinates":[9.43952,46.699364],"type":"Point"}
}