{
  "type": "Feature",
  "properties": {
    "iso:country":"CH",
    "sg:address":"Weidweg",
    "sg:city":"Giswil",
    "sg:orig_category":"Sonstige Aktivit\u00e4ten der nicht-\u00e4rztlichen Medizinalberufe",
    "sg:phone":"+41 41 675 21 63",
    "sg:postcode":"6074",
    "sg:province":"Obwalden",
    "wof:name":"Susi Zahner Kinesiologie",
    "wof:placetype":"venue"
},
  "geometry": {"coordinates":[8.1704454422,46.8374786377],"type":"Point"}
}