{
  "type": "Feature",
  "properties": {
    "iso:country":"CH",
    "sg:address":"Oberwiler Kirchweg 9g",
    "sg:city":"Zug",
    "sg:orig_category":"Sonstige pers\u00f6nliche Dienstleistungen",
    "sg:phone":"+41 41 711 61 28",
    "sg:postcode":"6300",
    "sg:province":"Zug",
    "wof:name":"Dr. Bernhard Ruckli",
    "wof:placetype":"venue"
},
  "geometry": {"coordinates":[8.5163402557,47.1587982178],"type":"Point"}
}