{
  "type": "Feature",
  "properties": {
    "iso:country":"CH",
    "sg:address":"Untere B\u00f6nigstrasse 12",
    "sg:city":"Interlaken",
    "sg:orig_category":"Einbau von Schreinerwaren Herstellung von K\u00fcchenm\u00f6beln",
    "sg:phone":"+41 21 866 70 55",
    "sg:postcode":"3800",
    "sg:province":"Bern",
    "wof:name":"Christian Friant Agencement De Cuisines",
    "wof:placetype":"venue"
},
  "geometry": {"coordinates":[6.5069441795,46.6607475281],"type":"Point"}
}