{
  "type": "Feature",
  "properties": {
    "iso:country":"CH",
    "sg:address":"Hauptstr. 112",
    "sg:city":"M\u00f6hlin",
    "sg:orig_category":"Fachdetailhandel mit pharmazeutischen Produkten",
    "sg:phone":"+41 800 300 001",
    "sg:postcode":"4313",
    "sg:province":"Aargau",
    "wof:name":"Oberdorf-apotheke Dr. Markus Kasper",
    "wof:placetype":"venue"
},
  "geometry": {"coordinates":[7.8508348465,47.5536193848],"type":"Point"}
}