{
  "type": "Feature",
  "properties": {
    "iso:country":"CH",
    "sg:address":"Postgasse 21",
    "sg:city":"Glarus",
    "sg:orig_category":"Non-Classified Establishments",
    "sg:phone":"+41 71 388 80 98",
    "sg:postcode":"8750",
    "sg:province":"Glarus",
    "wof:name":"Livum Gmbh",
    "wof:placetype":"venue"
},
  "geometry": {"coordinates":[9.2631521225,47.4129753113],"type":"Point"}
}