{
  "type": "Feature",
  "properties": {
    "iso:country":"CH",
    "sg:address":"Rue De La Treille 2",
    "sg:city":"Neuch\u00e2tel",
    "sg:orig_category":"Zahnarztpraxen",
    "sg:phone":"+41 32 724 22 20",
    "sg:postcode":"2000",
    "sg:province":"Neuch\u00e2tel",
    "wof:name":"Dr M\u00e9d. Dent. Bernard Huguenin M\u00e9decin-dentiste",
    "wof:placetype":"venue"
},
  "geometry": {"coordinates":[6.9299559593,46.9907417297],"type":"Point"}
}