{
  "type": "Feature",
  "properties": {
    "iso:country":"CH",
    "sg:address":"Bifang 78",
    "sg:city":"Brunegg",
    "sg:orig_category":"Instandhaltung U Reparatur von Automobilen",
    "sg:phone":"+41 79 345 19 18",
    "sg:postcode":"5505",
    "sg:province":"Aargau",
    "wof:name":"Schlossgarage Brunegg Ag",
    "wof:placetype":"venue"
},
  "geometry": {"coordinates":[8.217124939,47.4190864563],"type":"Point"}
}