{
  "type": "Feature",
  "properties": {
    "iso:country":"CH",
    "sg:address":"Baarerstrasse 110c",
    "sg:city":"Zug",
    "sg:orig_category":"Unclassifiable Establishments",
    "sg:phone":"+41 41 769 70 70",
    "sg:postcode":"6300",
    "sg:province":"Zug",
    "wof:name":"Pizza-sprintmobil Gmbh",
    "wof:placetype":"venue"
},
  "geometry": {"coordinates":[8.5189380646,47.1798820496],"type":"Point"}
}