{
  "type": "Feature",
  "properties": {
    "iso:country":"CH",
    "sg:address":"Gewerbestrasse 6 5702 Niederlenz. Postfach",
    "sg:city":"Niederlenz",
    "sg:orig_category":"Handel mit Automobilen",
    "sg:postcode":"5702",
    "sg:province":"Aargau",
    "wof:name":"Iba Automobile Ag",
    "wof:placetype":"venue"
},
  "geometry": {"coordinates":[8.1785869598,47.3990592957],"type":"Point"}
}