{
  "type": "Feature",
  "properties": {
    "addr:full":"Stadelstrasse 4 Ennetb\u00fcrgen Nidwalden 6373",
    "addr:housenumber":"4",
    "addr:postcode":"6373",
    "addr:street":"Stadelstrasse",
    "iso:country":"CH",
    "sg:address":"Stadelstrasse 4",
    "sg:city":"Ennetb\u00fcrgen",
    "sg:orig_category":"Architektur U Ingenieurb\u00fcros",
    "sg:postcode":"6373",
    "sg:province":"Nidwalden",
    "wof:name":"Beratungsb\u00fcro K\u00fcffer R.",
    "wof:placetype":"venue"
},
  "geometry": {"coordinates":[8.408978,46.986408],"type":"Point"}
}