{
  "type": "Feature",
  "properties": {
    "addr:full":"Saasermauer 5 Naters Valais 3904",
    "addr:housenumber":"5",
    "addr:postcode":"3904",
    "addr:street":"Saasermauer",
    "iso:country":"CH",
    "sg:address":"Saasermauer 5",
    "sg:city":"Naters",
    "sg:orig_category":"Bauschreinerei Herstellung von M\u00f6beln",
    "sg:phone":"+41 27 203 31 35",
    "sg:postcode":"3904",
    "sg:province":"Valais",
    "wof:name":"Andr\u00e9 Fournier & Cie Sa Menuiserie & Charpenterie",
    "wof:placetype":"venue"
},
  "geometry": {"coordinates":[7.367769,46.223862],"type":"Point"}
}