{
  "type": "Feature",
  "properties": {
    "iso:country":"CH",
    "sg:address":"Kinkelstrasse 60 8006 Z\u00fcrich. Postfach 33",
    "sg:city":"Z\u00fcrich",
    "sg:orig_category":"Non-Classified Establishments",
    "sg:postcode":"8006",
    "sg:province":"Z\u00fcrich",
    "wof:name":"Omlin O.",
    "wof:placetype":"venue"
},
  "geometry": {"coordinates":[9.8209161758,46.7938766479],"type":"Point"}
}