{
  "type": "Feature",
  "properties": {
    "iso:country":"CH",
    "sg:address":"5233",
    "sg:city":"Stilli",
    "sg:orig_category":"Primarschulen",
    "sg:phone":"+41 56 284 04 36",
    "sg:postcode":"5233",
    "sg:province":"Aargau",
    "wof:name":"Primarschule",
    "wof:placetype":"venue"
},
  "geometry": {"coordinates":[8.2110204697,47.5044708252],"type":"Point"}
}