{
  "type": "Feature",
  "properties": {
    "addr:full":"Kreuzlinger Strasse 153a Oberaach Thurgau 8587",
    "addr:housenumber":"153a",
    "addr:postcode":"8587",
    "addr:street":"Kreuzlinger Strasse",
    "iso:country":"CH",
    "sg:address":"Kreuzlinger Strasse 153a",
    "sg:city":"Oberaach",
    "sg:orig_category":"Bauschreinerei S\u00e4gewerke",
    "sg:phone":"+41 26 912 72 21",
    "sg:postcode":"8587",
    "sg:province":"Thurgau",
    "wof:name":"Menuiserie Defferrard Sa",
    "wof:placetype":"venue"
},
  "geometry": {"coordinates":[7.076177,46.599831],"type":"Point"}
}