{
  "type": "Feature",
  "properties": {
    "iso:country":"CH",
    "sg:address":"Obere Dorfstrasse 8",
    "sg:city":"Suhr",
    "sg:orig_category":"Kauf U Verkauf von Immobilien auf eigene Rechnung",
    "sg:phone":"+41 61 411 84 40",
    "sg:postcode":"5034",
    "sg:province":"Aargau",
    "wof:name":"Tereal Gmbh",
    "wof:placetype":"venue"
},
  "geometry": {"coordinates":[7.5998458862,47.5134391785],"type":"Point"}
}