{
  "type": "Feature",
  "properties": {
    "iso:country":"CH",
    "sg:address":"Neuhofstrasse 8/12",
    "sg:city":"Baar",
    "sg:orig_category":"Reiseb\u00fcros U Reiseveranstalter",
    "sg:phone":"+41 41 767 80 00",
    "sg:postcode":"6340",
    "sg:province":"Zug",
    "wof:name":"Hapimag",
    "wof:placetype":"venue"
},
  "geometry": {"coordinates":[8.5122814178,47.1899795532],"type":"Point"}
}