{
  "type": "Feature",
  "properties": {
    "iso:country":"CH",
    "sg:address":"Bernstrasse 18 4950 Huttwil. Postfach 461",
    "sg:city":"Huttwil",
    "sg:orig_category":"Herstellung von Gew\u00fcrzen U Saucen Herstellung von Teigwaren",
    "sg:phone":"+41 62 959 83 83",
    "sg:postcode":"4950",
    "sg:province":"Bern",
    "wof:name":"Walter Leuenberger Ag, Teigwaren Und Senffabrik",
    "wof:placetype":"venue"
},
  "geometry": {"coordinates":[7.8383197784,47.1132202148],"type":"Point"}
}