{
  "type": "Feature",
  "properties": {
    "iso:country":"CH",
    "sg:address":"Industriestrasse 13c 6300 Zug. Postfach 4339",
    "sg:city":"Zug",
    "sg:orig_category":"Architektur U Ingenieurb\u00fcros Sonstige technische Beratung U Planung",
    "sg:phone":"+41 71 911 05 03",
    "sg:postcode":"6304",
    "sg:province":"Zug",
    "wof:name":"Aerokart Ag Bauvermessung",
    "wof:placetype":"venue"
},
  "geometry": {"coordinates":[9.042646,47.471535],"type":"Point"}
}