{
  "type": "Feature",
  "properties": {
    "iso:country":"CH",
    "sg:address":"Hofgraben 11",
    "sg:city":"Chur",
    "sg:orig_category":"Interessenvertretungen",
    "sg:postcode":"7000",
    "sg:province":"Graubunden",
    "wof:name":"Doerenkamp/zbinden Stiftung F\u00fcr Konstruktiven Tierschutz In Der Biomedizinischen Forschung",
    "wof:placetype":"venue"
},
  "geometry": {"coordinates":[9.5348882675,46.8507270813],"type":"Point"}
}