{
  "type": "Feature",
  "properties": {
    "iso:country":"CH",
    "sg:address":"Grangettes Chemin Des 1871 Cho\u00ebx. Postfach",
    "sg:city":"Cho\u00ebx",
    "sg:orig_category":"Interessenvertretungen",
    "sg:postcode":"1871",
    "sg:province":"Valais",
    "wof:name":"Fondation Romande En Faveur Des Personnes Sourdes-aveugles (f.r.s.a.)",
    "wof:placetype":"venue"
},
  "geometry": {"coordinates":[6.9547939301,46.2385025024],"type":"Point"}
}