{
  "type": "Feature",
  "properties": {
    "iso:country":"CH",
    "sg:address":"Union Place De L' 1 1188 Gimel. Postfach",
    "sg:city":"Gimel",
    "sg:classifiers":[
        {
            "category":"Travel",
            "subcategory":"Hotels & Motels",
            "type":"Entertainment"
        }
    ],
    "sg:postcode":"1188",
    "sg:province":"Vaud",
    "sg:tags":[
        "hotels",
        "mit",
        "restaurant"
    ],
    "wof:name":"Cepeline S\u00e0rl H\u00f4tel-restaurant De L'union Et D'autres",
    "wof:placetype":"venue"
},
  "geometry": {"coordinates":[6.3076100349,46.5087203979],"type":"Point"}
}