{
  "type": "Feature",
  "properties": {
    "iso:country":"CH",
    "sg:address":"Ottenbacherstrasse 78b",
    "sg:city":"Zwillikon",
    "sg:orig_category":"Grosshandel mit B\u00fcromaschinen Grosshandel mit Datenverarbeitungsger\u00e4ten",
    "sg:phone":"+41 17617995",
    "sg:postcode":"8909",
    "sg:province":"Z\u00fcrich",
    "wof:name":"Andreas Schwager Informatikberatung",
    "wof:placetype":"venue"
},
  "geometry": {"coordinates":[8.4325056076,47.2874488831],"type":"Point"}
}