{
  "type": "Feature",
  "properties": {
    "iso:country":"CH",
    "sg:address":"Gare Route De La",
    "sg:city":"Genolier",
    "sg:orig_category":"Herstellung von Medikamenten U sonstigen pharmazeutischen Erzeugnissen",
    "sg:postcode":"1272",
    "sg:province":"Vaud",
    "wof:name":"Comphar Consulting Services, Adler A.",
    "wof:placetype":"venue"
},
  "geometry": {"coordinates":[6.2181859016,46.4349212646],"type":"Point"}
}