{
  "type": "Feature",
  "properties": {
    "iso:country":"CH",
    "sg:address":"Quartier Pr\u00e9-fontaine 58",
    "sg:city":"Crissier",
    "sg:orig_category":"RESTAURANTS: TEA-ROOMS",
    "sg:phone":"+41 21 634 48 45",
    "sg:postcode":"1023",
    "sg:province":"Vaud",
    "wof:name":"Pizzeria Il Capriccio",
    "wof:placetype":"venue"
},
  "geometry": {"coordinates":[6.5764698982,46.5457725525],"type":"Point"}
}