{
  "type": "Feature",
  "properties": {
    "iso:country":"CH",
    "sg:address":"Baumastrasse",
    "sg:city":"B\u00e4retswil",
    "sg:orig_category":"Instandhaltung U Reparatur von Automobilen",
    "sg:phone":"+41 55 210 23 23",
    "sg:postcode":"8344",
    "sg:province":"Z\u00fcrich",
    "wof:name":"Garage Helbling Ag Rapperswil",
    "wof:placetype":"venue"
},
  "geometry": {"coordinates":[8.8186664581,47.2350273132],"type":"Point"}
}