{
  "type": "Feature",
  "properties": {
    "addr:full":"7554 Sent Graubunden 7554",
    "addr:housenumber":"7554",
    "addr:postcode":"7554",
    "addr:street":"Sent Graubunden",
    "iso:country":"CH",
    "sg:address":"7554",
    "sg:city":"Sent",
    "sg:classifiers":[
        {
            "category":"Education",
            "subcategory":"Library",
            "type":"Public Place"
        }
    ],
    "sg:postcode":"7554",
    "sg:province":"Graubunden",
    "sg:tags":[
        "u",
        "bibliotheken",
        "archive"
    ],
    "wof:name":"Volksbibliothek",
    "wof:placetype":"venue"
},
  "geometry": {"coordinates":[8.597042,47.569534],"type":"Point"}
}