{
  "type": "Feature",
  "properties": {
    "iso:country":"CH",
    "sg:address":"Badhus 5",
    "sg:city":"Grosswangen",
    "sg:orig_category":"Ger\u00fcstbau Maler U Glasergewerbe",
    "sg:phone":"+41 41 980 11 20",
    "sg:postcode":"6022",
    "sg:province":"Luzern",
    "wof:name":"Arnet Franz Malergesch\u00e4ft",
    "wof:placetype":"venue"
},
  "geometry": {"coordinates":[8.0437965393,47.1342811584],"type":"Point"}
}