{
  "type": "Feature",
  "properties": {
    "iso:country":"CH",
    "sg:address":"Village Route Du",
    "sg:city":"Pr\u00e9vonloup",
    "sg:orig_category":"M\u00f6belschreinereien",
    "sg:phone":"+41 26 652 54 75",
    "sg:postcode":"1682",
    "sg:province":"Vaud",
    "wof:name":"Menuiserie Paccaud G\u00e9rald",
    "wof:placetype":"venue"
},
  "geometry": {"coordinates":[6.8832001686,46.7082748413],"type":"Point"}
}