{
  "type": "Feature",
  "properties": {
    "iso:country":"CH",
    "sg:address":"Hintere Bahnhofstrasse 14",
    "sg:city":"Suhr",
    "sg:orig_category":"Sonstige Verkehrsvermittlung",
    "sg:phone":"+41 32 866 11 63",
    "sg:postcode":"5034",
    "sg:province":"Aargau",
    "wof:name":"Duqu\u00e8ne & Cie S\u00e0rl",
    "wof:placetype":"venue"
},
  "geometry": {"coordinates":[6.4802680016,46.9043159485],"type":"Point"}
}