{
  "type": "Feature",
  "properties": {
    "iso:country":"CH",
    "sg:address":"L\u00e4nggasse 100 3600 Thun. Postfach",
    "sg:city":"Thun",
    "sg:orig_category":"Non-Classified Establishments",
    "sg:postcode":"3600",
    "sg:province":"Bern",
    "wof:name":"Creasoft Tomasetti",
    "wof:placetype":"venue"
},
  "geometry": {"coordinates":[8.9502496719,46.0590286255],"type":"Point"}
}