{
  "type": "Feature",
  "properties": {
    "iso:country":"CH",
    "sg:address":"Eiweg 14",
    "sg:city":"Gelterkinden",
    "sg:orig_category":"Einzelhandel mit Automobilteilen U Zubeh\u00f6r",
    "sg:phone":"+41 71 925 35 04",
    "sg:postcode":"4460",
    "sg:province":"Basel-Landschaft",
    "wof:name":"Giuseppe Stefania Pneu",
    "wof:placetype":"venue"
},
  "geometry": {"coordinates":[-77.13302612299999,40.4769287109],"type":"Point"}
}