{
  "type": "Feature",
  "properties": {
    "iso:country":"CH",
    "sg:address":"Zinkereistrasse 35",
    "sg:city":"Wolfhausen",
    "sg:orig_category":"Herstellung von sonstigen elektrischen Ausr\u00fcstungen Instandhaltung U Reparatur von Automobilen",
    "sg:phone":"+41 21 624 10 44",
    "sg:postcode":"8633",
    "sg:province":"Z\u00fcrich",
    "wof:name":"Westelectro Sa",
    "wof:placetype":"venue"
},
  "geometry": {"coordinates":[6.6011638641,46.5230941772],"type":"Point"}
}