{
  "type": "Feature",
  "properties": {
    "iso:country":"CH",
    "sg:address":"Via Galbisio 16 6503 Bellinzona. Postfach Caselle Postale 47",
    "sg:city":"Bellinzona",
    "sg:orig_category":"Herstellung von Getr\u00e4nken Herstellung von Spirituosen",
    "sg:phone":"+41 91 826 19 18",
    "sg:postcode":"6503",
    "sg:province":"Ticino",
    "wof:name":"Distilleria Rossi Sa",
    "wof:placetype":"venue"
},
  "geometry": {"coordinates":[9.0163316727,46.2042427063],"type":"Point"}
}