{
  "type": "Feature",
  "properties": {
    "iso:country":"CH",
    "sg:address":"Holbachstrasse 38",
    "sg:city":"Erschwil",
    "sg:orig_category":"Handelsvermittlung U Grosshandel Vermietung von Gebrauchsg\u00fctern",
    "sg:phone":"+41 61 781 17 08",
    "sg:postcode":"4228",
    "sg:province":"Solothurn",
    "wof:name":"Karl Saner Festartikel",
    "wof:placetype":"venue"
},
  "geometry": {"coordinates":[7.5415329933,47.3711891174],"type":"Point"}
}