{
  "type": "Feature",
  "properties": {
    "iso:country":"CH",
    "sg:address":"Avenue D'a\u00efre 36-38 1203 Gen\u00e8ve. Postfach",
    "sg:city":"Gen\u00e8ve",
    "sg:orig_category":"Fachdetailhandel mit pharmazeutischen Produkten Grosshandel mit Parf\u00fcmerieartikeln U K\u00f6rperpflegemit",
    "sg:phone":"+41 55 416 10 20",
    "sg:postcode":"1203",
    "sg:province":"Gen\u00e8ve",
    "wof:name":"Walther Georges Ag",
    "wof:placetype":"venue"
},
  "geometry": {"coordinates":[8.7829656601,47.2017173767],"type":"Point"}
}