{
  "type": "Feature",
  "properties": {
    "iso:country":"CH",
    "sg:address":"Altmattstrasse 19",
    "sg:city":"Rothenthurm",
    "sg:orig_category":"Bauschreinerei",
    "sg:phone":"+41 41 870 80 73",
    "sg:postcode":"6418",
    "sg:province":"Schwyz",
    "wof:name":"Martin Arnold Schreinerei",
    "wof:placetype":"venue"
},
  "geometry": {"coordinates":[8.588794,46.898792],"type":"Point"}
}