{
  "type": "Feature",
  "properties": {
    "iso:country":"CH",
    "sg:address":"Cit\u00e9-robinson 17",
    "sg:city":"Epagnier",
    "sg:orig_category":"Non-Classified Establishments",
    "sg:postcode":"2074",
    "sg:province":"Neuch\u00e2tel",
    "wof:name":"Pierre-alain Egger Bureautique",
    "wof:placetype":"venue"
},
  "geometry": {"coordinates":[7.0129070282,47.0067481995],"type":"Point"}
}