{
  "type": "Feature",
  "properties": {
    "iso:country":"CH",
    "sg:address":"M\u00fchlebachstrasse 12",
    "sg:city":"Z\u00fcrich",
    "sg:orig_category":"Institutionen des Sozialwesens ohne Beherbergung",
    "sg:postcode":"8008",
    "sg:province":"Z\u00fcrich",
    "wof:name":"La Loba-stiftung",
    "wof:placetype":"venue"
},
  "geometry": {"coordinates":[8.5495414734,47.3653640747],"type":"Point"}
}