{
  "type": "Feature",
  "properties": {
    "iso:country":"CH",
    "sg:address":"Untere Rebgasse 4 4058 Basel. Postfach",
    "sg:city":"Basel",
    "sg:orig_category":"Grosshandel mit Nahrungsmitteln, Getr\u00e4nken U Tabakwaren ohne ausgepr\u00e4gten Schwerpunkt",
    "sg:phone":"+41 71 311 44 44",
    "sg:postcode":"4051",
    "sg:province":"Basel-Stadt",
    "wof:name":"Pasta3 Gmbh",
    "wof:placetype":"venue"
},
  "geometry": {"coordinates":[9.2996959686,47.405040741],"type":"Point"}
}