{
  "type": "Feature",
  "properties": {
    "iso:country":"CH",
    "sg:address":"R\u00fcmelbachstrasse",
    "sg:city":"R\u00fcmlang",
    "sg:orig_category":"Primarschulen",
    "sg:phone":"+41 18171487",
    "sg:postcode":"8153",
    "sg:province":"Z\u00fcrich",
    "wof:name":"Primarschule R\u00fcmelbach",
    "wof:placetype":"venue"
},
  "geometry": {"coordinates":[8.5352401733,47.4477653503],"type":"Point"}
}