{
  "type": "Feature",
  "properties": {
    "iso:country":"CH",
    "sg:address":"Chollerstrasse 35 6300 Zug. Postfach 248",
    "sg:city":"Zug",
    "sg:orig_category":"Grosshandel mit Erzen U Metallen",
    "sg:phone":"+41 41 748 27 71",
    "sg:postcode":"6301",
    "sg:province":"Zug",
    "wof:name":"Procmet Co Ag Handelsgesellschaft",
    "wof:placetype":"venue"
},
  "geometry": {"coordinates":[8.4913597107,47.1862449646],"type":"Point"}
}