{
  "type": "Feature",
  "properties": {
    "addr:full":"Buristrasse 14 Bern Bern 3006",
    "addr:housenumber":"14",
    "addr:postcode":"3006",
    "addr:street":"Buristrasse",
    "iso:country":"CH",
    "sg:address":"Buristrasse 14",
    "sg:city":"Bern",
    "sg:orig_category":"Berufsbildende weiterf\u00fchrende Schulen Unternehmensberatung",
    "sg:phone":"+41 81 723 63 14",
    "sg:postcode":"3006",
    "sg:province":"Bern",
    "wof:name":"Orcon Schulung + Beratung L\u00e4ng",
    "wof:placetype":"venue"
},
  "geometry": {"coordinates":[7.510607,47.019985],"type":"Point"}
}