{
  "type": "Feature",
  "properties": {
    "iso:country":"CH",
    "sg:address":"Sch\u00e4renmoosstrasse 76 8052 Z\u00fcrich. Postfach",
    "sg:city":"Z\u00fcrich",
    "sg:orig_category":"Herstellung von Verbrennungsmotoren U Turbinen ohne Motoren f\u00fcr Luft U Strassenfahrzeuge Herstellung",
    "sg:phone":"+41 13012400",
    "sg:postcode":"8052",
    "sg:province":"Z\u00fcrich",
    "wof:name":"L. Kissling & Co Ag Maschinenfabrik",
    "wof:placetype":"venue"
},
  "geometry": {"coordinates":[8.5578250885,47.4185714722],"type":"Point"}
}