{
  "type": "Feature",
  "properties": {
    "iso:country":"CH",
    "sg:address":"Allmendstrasse 11",
    "sg:city":"Sursee",
    "sg:orig_category":"Grosshandel mit elektrischen Haushaltsger\u00e4ten",
    "sg:phone":"+41 32 724 20 34",
    "sg:postcode":"6210",
    "sg:province":"Luzern",
    "wof:name":"Aurora-nouvelle Cuisines Prof.machines \u00e0 Caf\u00e9",
    "wof:placetype":"venue"
},
  "geometry": {"coordinates":[6.9255328178,46.9923934937],"type":"Point"}
}