{
  "type": "Feature",
  "properties": {
    "iso:country":"CH",
    "sg:address":"Magnolienstrasse 8",
    "sg:city":"Gerlafingen",
    "sg:orig_category":"Sonstige Verkehrsvermittlung",
    "sg:postcode":"4563",
    "sg:province":"Solothurn",
    "wof:name":"Emch Wolfgang",
    "wof:placetype":"venue"
},
  "geometry": {"coordinates":[7.5733089447,47.1649589539],"type":"Point"}
}