{
  "type": "Feature",
  "properties": {
    "iso:country":"CH",
    "sg:address":"Grabenwiese 67 8484 Weisslingen. Postfach",
    "sg:city":"Weisslingen",
    "sg:orig_category":"Sonstige pers\u00f6nliche Dienstleistungen",
    "sg:postcode":"8484",
    "sg:province":"Z\u00fcrich",
    "wof:name":"Frei Dbs Wislig",
    "wof:placetype":"venue"
},
  "geometry": {"coordinates":[8.7704687119,47.4272727966],"type":"Point"}
}