{
  "type": "Feature",
  "properties": {
    "iso:country":"CH",
    "sg:address":"Im Sonnenhof 4 8753 Mollis. Postfach 9",
    "sg:city":"Mollis",
    "sg:orig_category":"Unternehmensberatung",
    "sg:phone":"+41 55 612 43 51",
    "sg:postcode":"8753",
    "sg:province":"Glarus",
    "wof:name":"St\u00e4hli + Partners Gmbh",
    "wof:placetype":"venue"
},
  "geometry": {"coordinates":[9.071105957,47.092414856],"type":"Point"}
}