{
  "type": "Feature",
  "properties": {
    "iso:country":"CH",
    "sg:address":"Bahnhofringstrasse 3 3113 Rubigen. Postfach",
    "sg:city":"Rubigen",
    "sg:orig_category":"Unclassifiable Establishments",
    "sg:postcode":"3113",
    "sg:province":"Bern",
    "wof:name":"Reiseb\u00fcro Ferie-insle",
    "wof:placetype":"venue"
},
  "geometry": {"coordinates":[11.7894697189,47.7824707031],"type":"Point"}
}