{
  "type": "Feature",
  "properties": {
    "iso:country":"CH",
    "sg:address":"Ansermet Quai Ernest- 20",
    "sg:city":"Genf",
    "sg:classifiers":[
        {
            "category":"Communications",
            "subcategory":"Radio Station",
            "type":"Services"
        }
    ],
    "sg:phone":"+41 32 421 70 40",
    "sg:postcode":"1200",
    "sg:province":"Gen\u00e8ve",
    "sg:tags":[
        "fernsehanstalten",
        "u"
    ],
    "wof:name":"Fr\u00e9quence Jura Sa",
    "wof:placetype":"venue"
},
  "geometry": {"coordinates":[7.3436050415,47.3652763367],"type":"Point"}
}