{
  "type": "Feature",
  "properties": {
    "addr:full":"Bernstrasse 2 Biberist Solothurn 4562",
    "addr:housenumber":"2",
    "addr:postcode":"4562",
    "addr:street":"Bernstrasse",
    "iso:country":"CH",
    "sg:address":"Bernstrasse 2",
    "sg:city":"Biberist",
    "sg:orig_category":"Bezirks, Sekundar, Realschulen, Oberstufe der Primarschulen",
    "sg:phone":"+41 32 672 30 47",
    "sg:postcode":"4562",
    "sg:province":"Solothurn",
    "wof:name":"Bezirksschule",
    "wof:placetype":"venue"
},
  "geometry": {"coordinates":[7.557115,47.181587],"type":"Point"}
}