{
  "type": "Feature",
  "properties": {
    "addr:full":"Rue Du Village Bramois Valais 1967",
    "addr:postcode":"1967",
    "addr:street":"Rue Du Village",
    "iso:country":"CH",
    "sg:address":"Rue Du Village",
    "sg:city":"Bramois",
    "sg:orig_category":"Bauschreinerei Herstellung von Konstruktionsteilen, Fertigbauteilen U Ausbauelementen aus Holz",
    "sg:phone":"+41 27 203 11 30",
    "sg:postcode":"1967",
    "sg:province":"Valais",
    "wof:name":"Menuiserie Bramoisienne, Fellay B.",
    "wof:placetype":"venue"
},
  "geometry": {"coordinates":[7.404965,46.232998],"type":"Point"}
}