{
  "type": "Feature",
  "properties": {
    "iso:country":"CH",
    "sg:address":"Eglise Rue De L' 18",
    "sg:city":"Pruntrut",
    "sg:orig_category":"Non-Classified Establishments",
    "sg:postcode":"2900",
    "sg:province":"Jura",
    "wof:name":"S.i. Loreley S.a.",
    "wof:placetype":"venue"
},
  "geometry": {"coordinates":[6.9953799248,46.2966117859],"type":"Point"}
}