{
  "type": "Feature",
  "properties": {
    "iso:country":"CH",
    "sg:address":"Schmiedgasse 3",
    "sg:city":"N\u00e4fels",
    "sg:orig_category":"Gesundheitswesen",
    "sg:postcode":"8752",
    "sg:province":"Glarus",
    "wof:name":"Kuoni Anna, Klassische Massagenpraxis",
    "wof:placetype":"venue"
},
  "geometry": {"coordinates":[9.0615444183,47.0992965698],"type":"Point"}
}