{
  "type": "Feature",
  "properties": {
    "iso:country":"CH",
    "sg:address":"Kasernenstrasse 10",
    "sg:city":"Chur",
    "sg:classifiers":[
        {
            "category":"Travel",
            "subcategory":"Hotels & Motels",
            "type":"Entertainment"
        }
    ],
    "sg:phone":"+41 81 252 10 96",
    "sg:postcode":"7000",
    "sg:province":"Graubunden",
    "sg:tags":[
        "hotels",
        "mit",
        "restaurant"
    ],
    "wof:name":"Cortolezis Martin, Hotel Schweizerhaus, Chur",
    "wof:placetype":"venue"
},
  "geometry": {"coordinates":[9.5259752274,46.84765625],"type":"Point"}
}