{
  "type": "Feature",
  "properties": {
    "iso:country":"CH",
    "sg:address":"Place Du Tunnel 19",
    "sg:city":"Lausanne",
    "sg:orig_category":"Architekturb\u00fcros",
    "sg:phone":"+41 21 312 22 90",
    "sg:postcode":"1005",
    "sg:province":"Vaud",
    "wof:name":"D. D\u00e9m\u00e9triad\u00e8s & D. Papadaniel Bureau D'architecture",
    "wof:placetype":"venue"
},
  "geometry": {"coordinates":[6.633832,46.525932],"type":"Point"}
}