{
  "type": "Feature",
  "properties": {
    "iso:country":"CH",
    "sg:address":"Augustin Kellerstrasse 31",
    "sg:city":"Lenzburg",
    "sg:orig_category":"Detailhandel mit Waren verschiedener Art, Hauptrichtung Nahrungsmittel",
    "sg:phone":"+41 62 885 38 38",
    "sg:postcode":"5600",
    "sg:province":"Aargau",
    "wof:name":"Coop Super Center",
    "wof:placetype":"venue"
},
  "geometry": {"coordinates":[8.1715011597,47.3899688721],"type":"Point"}
}