{
  "type": "Feature",
  "properties": {
    "iso:country":"CH",
    "sg:address":"Grand-rue 55 1373 Chavornay. Postfach",
    "sg:city":"Chavornay",
    "sg:orig_category":"RESTAURANTS: TEA-ROOMS",
    "sg:postcode":"1373",
    "sg:province":"Vaud",
    "wof:name":"Caf\u00e9-restaurant De L'union, Bovet Fabien",
    "wof:placetype":"venue"
},
  "geometry": {"coordinates":[6.5690479279,46.7057228088],"type":"Point"}
}