{
  "type": "Feature",
  "properties": {
    "iso:country":"CH",
    "sg:address":"Route De Ch\u00eane 1",
    "sg:city":"Gen\u00e8ve",
    "sg:orig_category":"Detailhandel mit Uhren U Schmuck Reparatur von Uhren U Schmuck",
    "sg:phone":"+41 22 736 98 88",
    "sg:postcode":"1207",
    "sg:province":"Gen\u00e8ve",
    "wof:name":"Ennio Cagnato Horlogerie San Marco",
    "wof:placetype":"venue"
},
  "geometry": {"coordinates":[6.1656899452,46.2000694275],"type":"Point"}
}