{
  "type": "Feature",
  "properties": {
    "iso:country":"CH",
    "sg:address":"Glarnerstr. 8 8862 Sch\u00fcbelbach. Postfach",
    "sg:city":"Siebnen",
    "sg:orig_category":"Sonstige mit der Informatik verbundene T\u00e4tigkeiten",
    "sg:postcode":"8854",
    "sg:province":"Schwyz",
    "wof:name":"Kessler Rudolf, Computer Services",
    "wof:placetype":"venue"
},
  "geometry": {"coordinates":[8.9108295441,47.1760253906],"type":"Point"}
}