{
  "type": "Feature",
  "properties": {
    "iso:country":"CH",
    "sg:address":"3900 Brig. Postfach 669",
    "sg:city":"Brig",
    "sg:orig_category":"Vereine WWF-Sektionen",
    "sg:postcode":"3900",
    "sg:province":"Valais",
    "wof:name":"Wwf Sektion Wallis",
    "wof:placetype":"venue"
},
  "geometry": {"coordinates":[7.9952898026,46.275138855],"type":"Point"}
}