{
  "type": "Feature",
  "properties": {
    "iso:country":"CH",
    "sg:address":"Zimmerwaldstrasse 56",
    "sg:city":"Kehrsatz",
    "sg:orig_category":"Fachdetailhandel in Verkaufsr\u00e4umen",
    "sg:postcode":"3122",
    "sg:province":"Bern",
    "wof:name":"Schenk Beatrice Art",
    "wof:placetype":"venue"
},
  "geometry": {"coordinates":[7.4656639099,46.9054756165],"type":"Point"}
}