{
  "type": "Feature",
  "properties": {
    "iso:country":"CH",
    "sg:address":"Luzernerstrasse 54",
    "sg:city":"Littau",
    "sg:orig_category":"Autogaragen",
    "sg:phone":"+41 41 250 57 52",
    "sg:postcode":"6014",
    "sg:province":"Luzern",
    "wof:name":"Luciano Capra Garage",
    "wof:placetype":"venue"
},
  "geometry": {"coordinates":[8.276656,47.051994],"type":"Point"}
}