{
  "type": "Feature",
  "properties": {
    "iso:country":"CH",
    "sg:address":"Grindelstrasse 12 8303 Bassersdorf. Postfach",
    "sg:city":"Bassersdorf",
    "sg:orig_category":"Herstellung von elektronischen Bauelementen",
    "sg:phone":"+41 18384100",
    "sg:postcode":"8303",
    "sg:province":"Z\u00fcrich",
    "wof:name":"Mader Technic Ag Technische Komponenten; Handel, Vertrieb",
    "wof:placetype":"venue"
},
  "geometry": {"coordinates":[8.6093711853,47.4461135864],"type":"Point"}
}