{
  "type": "Feature",
  "properties": {
    "iso:country":"CH",
    "sg:address":"Juch 1",
    "sg:city":"Zumikon",
    "sg:classifiers":[
        {
            "category":"Restaurant",
            "type":"Food & Drink"
        }
    ],
    "sg:phone":"+41 43 288 01 22",
    "sg:postcode":"8126",
    "sg:province":"Z\u00fcrich",
    "wof:name":"Restaurant Badst\u00fcbli",
    "wof:placetype":"venue"
},
  "geometry": {"coordinates":[8.6203184128,47.3324241638],"type":"Point"}
}