{
  "type": "Feature",
  "properties": {
    "iso:country":"CH",
    "sg:address":"Weisslingerstrasse 5",
    "sg:city":"Illnau",
    "sg:orig_category":"Elektrizit\u00e4tsversorgung Wasserversorgung",
    "sg:phone":"+41 52 346 11 55",
    "sg:postcode":"8308",
    "sg:province":"Z\u00fcrich",
    "wof:name":"Elektrizit\u00e4tswerk & Wasserversorgung Illnau",
    "wof:placetype":"venue"
},
  "geometry": {"coordinates":[8.7269706726,47.4080238342],"type":"Point"}
}