{
  "type": "Feature",
  "properties": {
    "iso:country":"CH",
    "sg:address":"Zilistude 99",
    "sg:city":"Mellikon",
    "sg:orig_category":"Grosshandel mit sonstigen Maschinen U Ausr\u00fcstungen f\u00fcr Industrie, Handel U Schiffahrt",
    "sg:phone":"+41 56 243 18 65",
    "sg:postcode":"5465",
    "sg:province":"Aargau",
    "wof:name":"Pct Ag",
    "wof:placetype":"venue"
},
  "geometry": {"coordinates":[8.3515100479,47.5683364868],"type":"Point"}
}