{
  "type": "Feature",
  "properties": {
    "iso:country":"CH",
    "sg:address":"Mempfel 741 9055 B\u00fchler. Postfach",
    "sg:city":"B\u00fchler",
    "sg:orig_category":"Softwareentwicklung U beratung",
    "sg:phone":"+41 71 793 29 82",
    "sg:postcode":"9055",
    "sg:province":"Appenzell Ausserrhoden",
    "wof:name":"Sager Servertechnik",
    "wof:placetype":"venue"
},
  "geometry": {"coordinates":[9.4184494019,47.3740959167],"type":"Point"}
}