{
  "type": "Feature",
  "properties": {
    "iso:country":"CH",
    "sg:address":"Hardp\u00fcntstrasse 10",
    "sg:city":"Kloten",
    "sg:orig_category":"Sonstiges Versicherungsgewerbe",
    "sg:phone":"+41 18141409",
    "sg:postcode":"8302",
    "sg:province":"Z\u00fcrich",
    "wof:name":"G\u00fcnter Schaad Versicherungen",
    "wof:placetype":"venue"
},
  "geometry": {"coordinates":[8.5801801682,47.4441184998],"type":"Point"}
}