{
  "type": "Feature",
  "properties": {
    "iso:country":"CH",
    "sg:address":"Zeughausstrasse 6 6430 Schwyz. Postfach 516",
    "sg:city":"Schwyz",
    "sg:classifiers":[
        {
            "category":"Restaurant",
            "type":"Food & Drink"
        }
    ],
    "sg:phone":"+41 41 811 22 75",
    "sg:postcode":"6431",
    "sg:province":"Schwyz",
    "wof:name":"Pizzeria Sternen",
    "wof:placetype":"venue"
},
  "geometry": {"coordinates":[8.6515436172,47.0217170715],"type":"Point"}
}