{
  "type": "Feature",
  "properties": {
    "iso:country":"CH",
    "sg:address":"Talhofweg 5",
    "sg:city":"Mels",
    "sg:orig_category":"Wirtschaftspr\u00fcfung, Steuerberatung U Treuhand",
    "sg:phone":"+41 81 723 47 85",
    "sg:postcode":"8887",
    "sg:province":"St. Gallen",
    "wof:name":"Vils Treuhand",
    "wof:placetype":"venue"
},
  "geometry": {"coordinates":[9.4248504639,47.0446929932],"type":"Point"}
}