{
  "type": "Feature",
  "properties": {
    "iso:country":"CH",
    "sg:address":"Isengrundstrasse 7",
    "sg:city":"Adliswil",
    "sg:orig_category":"Vorschulen, Kinderg\u00e4rten",
    "sg:phone":"+41 17106880",
    "sg:postcode":"8134",
    "sg:province":"Z\u00fcrich",
    "wof:name":"Kindergarten Isengrund",
    "wof:placetype":"venue"
},
  "geometry": {"coordinates":[8.5283098221,47.3169898987],"type":"Point"}
}