{
  "type": "Feature",
  "properties": {
    "iso:country":"CH",
    "sg:address":"Kastelsstrasse 114",
    "sg:city":"Grenchen",
    "sg:orig_category":"Mechanische Werkst\u00e4tten",
    "sg:phone":"+41 19321230",
    "sg:postcode":"2540",
    "sg:province":"Solothurn",
    "wof:name":"Schuler Dominik, Reparaturwerkst\u00e4tte",
    "wof:placetype":"venue"
},
  "geometry": {"coordinates":[8.7935171127,47.3101768494],"type":"Point"}
}