{
  "type": "Feature",
  "properties": {
    "iso:country":"CH",
    "sg:address":"Schmiedenstrasse 20",
    "sg:city":"Einsiedeln",
    "sg:orig_category":"Eisenwaren Detailhandel Haushaltartikel Detailhandel",
    "sg:phone":"+41 55 418 80 60",
    "sg:postcode":"8840",
    "sg:province":"Schwyz",
    "wof:name":"Theiler Eisenwaren Haushalt & Schliesstechnik",
    "wof:placetype":"venue"
},
  "geometry": {"coordinates":[8.7484827042,47.1278381348],"type":"Point"}
}