{
  "type": "Feature",
  "properties": {
    "iso:country":"CH",
    "sg:address":"Schaffhauserstrasse 152",
    "sg:city":"Winterthur",
    "sg:classifiers":[
        {
            "category":"Restaurant",
            "type":"Food & Drink"
        }
    ],
    "sg:phone":"+41 52 212 28 60",
    "sg:postcode":"8400",
    "sg:province":"Z\u00fcrich",
    "wof:name":"Restaurant Cindy",
    "wof:placetype":"venue"
},
  "geometry": {"coordinates":[8.7199220657,47.5173606873],"type":"Point"}
}