{
  "type": "Feature",
  "properties": {
    "iso:country":"CH",
    "sg:address":"Landstrasse 3",
    "sg:city":"Nesselnbach",
    "sg:classifiers":[
        {
            "category":"Restaurant",
            "type":"Food & Drink"
        }
    ],
    "sg:phone":"+41 32 623 89 15",
    "sg:postcode":"5524",
    "sg:province":"Aargau",
    "wof:name":"Restaurant Zum R\u00f6ssli",
    "wof:placetype":"venue"
},
  "geometry": {"coordinates":[7.5050520897,47.2283554077],"type":"Point"}
}