{
  "type": "Feature",
  "properties": {
    "iso:country":"CH",
    "sg:address":"Bachstrasse 27",
    "sg:city":"Wettingen",
    "sg:orig_category":"Sportvereine Ballsport Handball",
    "sg:postcode":"5430",
    "sg:province":"Aargau",
    "wof:name":"Mkg Baden",
    "wof:placetype":"venue"
},
  "geometry": {"coordinates":[8.3137483597,47.4647521973],"type":"Point"}
}