{
  "type": "Feature",
  "properties": {
    "iso:country":"CH",
    "sg:address":"Faubourg Ph.-suchard 30",
    "sg:city":"Boudry",
    "sg:orig_category":"Grosshandel mit Eisenwaren sowie Installationsbedarf f\u00fcr Gas, Wasser U Heizung Grosshandel mit sonst",
    "sg:phone":"+41 32 842 38 55",
    "sg:postcode":"2017",
    "sg:province":"Neuch\u00e2tel",
    "wof:name":"Freddy Dumont Fourn.garages & Carrosseries",
    "wof:placetype":"venue"
},
  "geometry": {"coordinates":[6.8322138786,46.9549407959],"type":"Point"}
}