{
  "type": "Feature",
  "properties": {
    "iso:country":"CH",
    "sg:address":"Papierm\u00fchlestrasse 166",
    "sg:city":"Ittigen",
    "sg:orig_category":"Herstellung von medizinischen U chirurgischen Ger\u00e4ten sowie orthop\u00e4dischen Vorrichtungen Zahntechnis",
    "sg:phone":"+41 79 653 05 72",
    "sg:postcode":"3063",
    "sg:province":"Bern",
    "wof:name":"Schaer Zahntechnik J\u00fcrg Schaer",
    "wof:placetype":"venue"
},
  "geometry": {"coordinates":[7.4763669968,46.973865509],"type":"Point"}
}