{
  "type": "Feature",
  "properties": {
    "addr:full":"Sonnenhofstrasse 3 Hochfelden Z\u00fcrich 8182",
    "addr:housenumber":"3",
    "addr:postcode":"8182",
    "addr:street":"Sonnenhofstrasse",
    "iso:country":"CH",
    "sg:address":"Sonnenhofstrasse 3",
    "sg:city":"Hochfelden",
    "sg:orig_category":"Dachdeckerei Zimmerei, Dachdeckerei, Bauspenglerei U Abdichtung",
    "sg:postcode":"8182",
    "sg:province":"Z\u00fcrich",
    "wof:name":"Repond Jean-pierre",
    "wof:placetype":"venue"
},
  "geometry": {"coordinates":[7.164164,46.619221],"type":"Point"}
}