{
  "type": "Feature",
  "properties": {
    "iso:country":"CH",
    "sg:address":"Wiggerblock B",
    "sg:city":"Reiden",
    "sg:orig_category":"Sportvereine Ballsport Volleyball",
    "sg:phone":"+41 62 758 20 05",
    "sg:postcode":"6260",
    "sg:province":"Luzern",
    "wof:name":"Volleyball-club Kgv Reiden",
    "wof:placetype":"venue"
},
  "geometry": {"coordinates":[7.9699230194,47.25365448],"type":"Point"}
}