{
  "type": "Feature",
  "properties": {
    "iso:country":"CH",
    "sg:address":"Kindergartenstrasse 3",
    "sg:city":"Romanshorn",
    "sg:orig_category":"Wohnheime",
    "sg:phone":"+41 71 460 02 84",
    "sg:postcode":"8590",
    "sg:province":"Thurgau",
    "wof:name":"Heim Betula Verein Offenes Wohnheim",
    "wof:placetype":"venue"
},
  "geometry": {"coordinates":[9.3738079071,47.5645027161],"type":"Point"}
}