{
  "type": "Feature",
  "properties": {
    "iso:country":"CH",
    "sg:address":"Gerhard Meier-weg 2",
    "sg:city":"Niederbipp",
    "sg:classifiers":[
        {
            "category":"Retail",
            "subcategory":"Repair Shop",
            "type":"Services"
        }
    ],
    "sg:phone":"+41 32 633 17 81",
    "sg:postcode":"4704",
    "sg:province":"Bern",
    "sg:tags":[
        "tool",
        "electric",
        "machinery"
    ],
    "wof:name":"Toolrep Andr\u00e9 Henzmann",
    "wof:placetype":"venue"
},
  "geometry": {"coordinates":[7.6921339035,47.2730979919],"type":"Point"}
}