{
  "type": "Feature",
  "properties": {
    "iso:country":"CH",
    "sg:address":"Birmensdorferstrasse 24",
    "sg:city":"Urdorf",
    "sg:classifiers":[
        {
            "category":"Banks & Credit Unions",
            "subcategory":"Investment Brokerage",
            "type":"Services"
        }
    ],
    "sg:phone":"+41 52 763 27 82",
    "sg:postcode":"8902",
    "sg:province":"Z\u00fcrich",
    "sg:tags":[
        "floor",
        "heated"
    ],
    "wof:name":"Roman H\u00e4ni",
    "wof:placetype":"venue"
},
  "geometry": {"coordinates":[8.9943847656,47.5981941223],"type":"Point"}
}