{
  "type": "Feature",
  "properties": {
    "addr:full":"Gewerbestrasse 18 8155 Niederhasli. Postfach Niederhasli Z\u00fcrich 8155",
    "addr:housenumber":"18",
    "addr:postcode":"8155 niederhasli. postfach;8155",
    "addr:street":"Gewerbestrasse",
    "iso:country":"CH",
    "sg:address":"Gewerbestrasse 18 8155 Niederhasli. Postfach",
    "sg:city":"Niederhasli",
    "sg:orig_category":"Allgemeiner Hoch U Tiefbau",
    "sg:postcode":"8155",
    "sg:province":"Z\u00fcrich",
    "wof:name":"Vago Niederhasli, Zweigniederlassung Der Kibag Strassen Und Tiefbau",
    "wof:placetype":"venue"
},
  "geometry": {"coordinates":[8.49696,47.479103],"type":"Point"}
}