{
  "type": "Feature",
  "properties": {
    "iso:country":"CH",
    "sg:address":"M\u00fchlegasse 22 3210 Kerzers Case Postale 57",
    "sg:city":"Kerzers",
    "sg:orig_category":"Grosshandel mit Getr\u00e4nken",
    "sg:phone":"+41 31 755 70 56",
    "sg:postcode":"3210",
    "sg:province":"Fribourg",
    "wof:name":"Reinhard Dick Valser Heimdienst",
    "wof:placetype":"venue"
},
  "geometry": {"coordinates":[7.1937141418,46.9683609009],"type":"Point"}
}