{
  "type": "Feature",
  "properties": {
    "iso:country":"CH",
    "sg:address":"Bahnhofstrasse 24 8803 R\u00fcschlikon. Postfach",
    "sg:city":"R\u00fcschlikon",
    "sg:orig_category":"Buchverlag Verlagsgewerbe",
    "sg:phone":"+41 17247777",
    "sg:postcode":"8803",
    "sg:province":"Z\u00fcrich",
    "wof:name":"Sch\u00fcck S\u00f6hne Ag Druckerei Und Verlag",
    "wof:placetype":"venue"
},
  "geometry": {"coordinates":[8.553759,47.310974],"type":"Point"}
}