{
  "type": "Feature",
  "properties": {
    "iso:country":"CH",
    "sg:address":"Via Bosciarina",
    "sg:city":"Arbedo",
    "sg:orig_category":"Grosshandel mit Holz U Bauelementen aus Holz S\u00e4gewerke",
    "sg:phone":"+41 27 952 11 79",
    "sg:postcode":"6517",
    "sg:province":"Ticino",
    "wof:name":"Marius Schnidrig Ag",
    "wof:placetype":"venue"
},
  "geometry": {"coordinates":[7.8664298058,46.2315216064],"type":"Point"}
}