{
  "type": "Feature",
  "properties": {
    "iso:country":"CH",
    "sg:address":"Hessstrasse 42 3097 Liebefeld. Postfach",
    "sg:city":"Liebefeld",
    "sg:orig_category":"Detailhandel mit Radio U Fernsehger\u00e4ten Herstellung von Radio U Fernsehger\u00e4ten sowie phono U videote",
    "sg:phone":"+41 79 215 36 55",
    "sg:postcode":"3097",
    "sg:province":"Bern",
    "wof:name":"Hessgut R-tv, Riesen U.",
    "wof:placetype":"venue"
},
  "geometry": {"coordinates":[7.4275097847,46.9304199219],"type":"Point"}
}