{
  "type": "Feature",
  "properties": {
    "iso:country":"CH",
    "sg:address":"Schlierenh\u00f6lzlistrasse 16",
    "sg:city":"K\u00e4giswil",
    "sg:classifiers":[
        {
            "category":"Insurance",
            "subcategory":"Insurance Agent",
            "type":"Services"
        }
    ],
    "sg:phone":"+41 61 751 11 86",
    "sg:postcode":"6056",
    "sg:province":"Obwalden",
    "sg:tags":[
        "versicherungsagenturen",
        "-broker"
    ],
    "wof:name":"Josef G. Kalbermatter Agentur Basler Versicherungen",
    "wof:placetype":"venue"
},
  "geometry": {"coordinates":[7.6010699272,47.4783592224],"type":"Point"}
}