{
  "type": "Feature",
  "properties": {
    "iso:country":"CH",
    "sg:address":"Hauptstrasse 38",
    "sg:city":"Rorschach",
    "sg:orig_category":"Grosshandel mit Eisenwaren sowie Installationsbedarf f\u00fcr Gas, Wasser U Heizung",
    "sg:phone":"+41 71 841 10 40",
    "sg:postcode":"9400",
    "sg:province":"St. Gallen",
    "wof:name":"Badissimo Ag",
    "wof:placetype":"venue"
},
  "geometry": {"coordinates":[9.4944410324,47.4781646729],"type":"Point"}
}