{
  "type": "Feature",
  "properties": {
    "iso:country":"CH",
    "sg:address":"L\u00fctzelrain 14",
    "sg:city":"Bichelsee",
    "sg:orig_category":"Detailhandel mit Brot, Back U S\u00fcsswaren",
    "sg:phone":"+41 71 971 21 33",
    "sg:postcode":"8363",
    "sg:province":"Thurgau",
    "wof:name":"Ernst Honegger B\u00e4ckerei",
    "wof:placetype":"venue"
},
  "geometry": {"coordinates":[8.9224090576,47.447177887],"type":"Point"}
}