{
  "type": "Feature",
  "properties": {
    "iso:country":"CH",
    "sg:address":"Hotzestrasse 38 8006 Z\u00fcrich. Postfach",
    "sg:city":"Z\u00fcrich",
    "sg:orig_category":"Gesundheitswesen",
    "sg:phone":"+41 13636210",
    "sg:postcode":"8001",
    "sg:province":"Z\u00fcrich",
    "wof:name":"Physiognomik-institut Z\u00fcrich Piz, W. Frey Charakteranalysen Anhand V. Physiognomik-verein-lehrmitteln, Partnerschaftsberatung Usw",
    "wof:placetype":"venue"
},
  "geometry": {"coordinates":[8.540851593,47.3910217285],"type":"Point"}
}