{
  "type": "Feature",
  "properties": {
    "iso:country":"CH",
    "sg:address":"Chemin Des Tuilots 10",
    "sg:city":"Bellevue",
    "sg:orig_category":"Arztpraxen",
    "sg:phone":"+41 22 774 25 74",
    "sg:postcode":"1293",
    "sg:province":"Gen\u00e8ve",
    "wof:name":"Dr M\u00e9d. Jean-pierre Olivier M\u00e9decin Sp\u00e9cialiste Fmh",
    "wof:placetype":"venue"
},
  "geometry": {"coordinates":[6.145793,46.251381],"type":"Point"}
}