{
  "type": "Feature",
  "properties": {
    "iso:country":"CH",
    "sg:address":"R\u00fctistrasse 7 8634 Hombrechtikon. Postfach 370",
    "sg:city":"Hombrechtikon",
    "sg:orig_category":"Fernmeldedienste",
    "sg:phone":"+41 55 244 45 45",
    "sg:postcode":"8634",
    "sg:province":"Z\u00fcrich",
    "wof:name":"Freecom Ag",
    "wof:placetype":"venue"
},
  "geometry": {"coordinates":[8.7674837112,47.2516403198],"type":"Point"}
}