{
  "type": "Feature",
  "properties": {
    "iso:country":"CH",
    "sg:address":"Jungholzstrasse 43 8050 Z\u00fcrich",
    "sg:city":"Zust",
    "sg:orig_category":"Non-Classified Establishments",
    "sg:phone":"+41 21 695 23 60",
    "sg:postcode":"50",
    "wof:name":"Compex Sa",
    "wof:placetype":"venue"
},
  "geometry": {"coordinates":[6.5611319542,46.5254325867],"type":"Point"}
}