{
  "type": "Feature",
  "properties": {
    "iso:country":"CH",
    "sg:address":"1041",
    "sg:city":"Poliez-pittet",
    "sg:orig_category":"Primarschulen",
    "sg:phone":"+41 21 881 47 87",
    "sg:postcode":"1041",
    "sg:province":"Vaud",
    "wof:name":"Ecole Primaire",
    "wof:placetype":"venue"
},
  "geometry": {"coordinates":[6.6836800575,46.6280097961],"type":"Point"}
}