{
  "type": "Feature",
  "properties": {
    "iso:country":"CH",
    "sg:address":"Route D'englisberg 17",
    "sg:city":"Granges-paccot",
    "sg:orig_category":"Non-Classified Establishments",
    "sg:phone":"+41 56 618 81 81",
    "sg:postcode":"1763",
    "sg:province":"Fribourg",
    "wof:name":"Sulzer Metco Holding Ag",
    "wof:placetype":"venue"
},
  "geometry": {"coordinates":[8.2662343979,47.3601646423],"type":"Point"}
}