{
  "type": "Feature",
  "properties": {
    "iso:country":"CH",
    "sg:address":"Gorgenstrasse 6 6074 Giswil. Postfach",
    "sg:city":"Giswil",
    "sg:orig_category":"Herstellung von Konstruktionsteilen, Fertigbauteilen U Ausbauelementen aus Holz",
    "sg:postcode":"6074",
    "sg:province":"Obwalden",
    "wof:name":"Spitzm\u00fcller Stefan Schreinerei",
    "wof:placetype":"venue"
},
  "geometry": {"coordinates":[8.1881113052,46.837928772],"type":"Point"}
}