{
  "type": "Feature",
  "properties": {
    "iso:country":"CH",
    "sg:address":"Bergstrasse 3 8712 St\u00e4fa. Postfach 322",
    "sg:city":"St\u00e4fa",
    "sg:orig_category":"Werbevermittlung Werbung",
    "sg:phone":"+41 19263939",
    "sg:postcode":"8712",
    "sg:province":"Z\u00fcrich",
    "wof:name":"Nada",
    "wof:placetype":"venue"
},
  "geometry": {"coordinates":[8.7199573517,47.2410469055],"type":"Point"}
}