{
  "type": "Feature",
  "properties": {
    "addr:full":"B\u00fcntlistrasse 1 5506 M\u00e4genwil. Postfach 16 M\u00e4genwil Aargau 5506",
    "addr:housenumber":"1;16",
    "addr:postcode":"5506;5506",
    "addr:street":"Buentlistrasse;Postfach",
    "iso:country":"CH",
    "sg:address":"B\u00fcntlistrasse 1 5506 M\u00e4genwil. Postfach 16",
    "sg:city":"M\u00e4genwil",
    "sg:orig_category":"Autogaragen",
    "sg:phone":"+41 62 896 29 79",
    "sg:postcode":"5506",
    "sg:province":"Aargau",
    "wof:name":"Auto Marti Gmbh M\u00e4genwil",
    "wof:placetype":"venue"
},
  "geometry": {"coordinates":[8.223136,47.411507],"type":"Point"}
}