{
  "type": "Feature",
  "properties": {
    "iso:country":"CH",
    "sg:address":"Unterdorfstrasse 25c",
    "sg:city":"Utzenstorf",
    "sg:orig_category":"Tapezierer/Dekorateure",
    "sg:phone":"+41 32 665 27 13",
    "sg:postcode":"3427",
    "sg:province":"Bern",
    "wof:name":"Ernst G\u00fcnter Innendekorationen",
    "wof:placetype":"venue"
},
  "geometry": {"coordinates":[7.5567498207,47.1371307373],"type":"Point"}
}