{
  "type": "Feature",
  "properties": {
    "iso:country":"CH",
    "sg:address":"Via Ballerini 14",
    "sg:city":"Locarno",
    "sg:orig_category":"Vermittlung von Immobilien",
    "sg:phone":"+41 91 751 46 66",
    "sg:postcode":"6600",
    "sg:province":"Ticino",
    "wof:name":"Cesare Bozzini Officina",
    "wof:placetype":"venue"
},
  "geometry": {"coordinates":[8.7979640961,46.1658401489],"type":"Point"}
}