{
  "type": "Feature",
  "properties": {
    "iso:country":"CH",
    "sg:address":"Seefeldstrasse 93",
    "sg:city":"Z\u00fcrich",
    "sg:orig_category":"Vorschulen, Kinderg\u00e4rten",
    "sg:phone":"+41 71 277 50 57",
    "sg:postcode":"8008",
    "sg:province":"Z\u00fcrich",
    "wof:name":"St\u00e4dtischer Kindergarten Rieth\u00fcsli",
    "wof:placetype":"venue"
},
  "geometry": {"coordinates":[9.363776207,47.4114723206],"type":"Point"}
}