{
  "type": "Feature",
  "properties": {
    "iso:country":"CH",
    "sg:address":"Buchserstrasse 4",
    "sg:city":"D\u00e4llikon",
    "sg:orig_category":"G\u00fcterbef\u00f6rderung im Strassenverkehr",
    "sg:phone":"+41 77642451",
    "sg:postcode":"8108",
    "sg:province":"Z\u00fcrich",
    "wof:name":"Hans-joachim Jakob Transporte",
    "wof:placetype":"venue"
},
  "geometry": {"coordinates":[8.4392347336,47.4405174255],"type":"Point"}
}