{
  "type": "Feature",
  "properties": {
    "iso:country":"CH",
    "sg:address":"Adelheid-pagestrasse 3",
    "sg:city":"Cham",
    "sg:orig_category":"Detailhandel mit Antiquit\u00e4ten U Gebrauchtwaren in Verkaufsr\u00e4umen",
    "sg:phone":"+41 77431957",
    "sg:postcode":"6330",
    "sg:province":"Zug",
    "wof:name":"Occasions-markt Kiener",
    "wof:placetype":"venue"
},
  "geometry": {"coordinates":[8.465436,47.18121],"type":"Point"}
}