{
  "type": "Feature",
  "properties": {
    "iso:country":"CH",
    "sg:address":"Feldeggstrasse 1 9113 Degersheim. Postfach",
    "sg:city":"Degersheim",
    "sg:orig_category":"Kauf U Verkauf von Immobilien auf eigene Rechnung",
    "sg:phone":"+41 71 371 12 28",
    "sg:postcode":"9113",
    "sg:province":"St. Gallen",
    "wof:name":"Grauer & Co Ag",
    "wof:placetype":"venue"
},
  "geometry": {"coordinates":[9.1934070587,47.3731880188],"type":"Point"}
}