{
  "type": "Feature",
  "properties": {
    "addr:full":"Neudorfstrasse 75 Thusis Graubunden 7430",
    "addr:housenumber":"75",
    "addr:postcode":"7430",
    "addr:street":"Neudorfstrasse",
    "iso:country":"CH",
    "sg:address":"Neudorfstrasse 75",
    "sg:city":"Thusis",
    "sg:orig_category":"Detailhandel mit Blumen U Pflanzen",
    "sg:phone":"+41 81 651 33 09",
    "sg:postcode":"7430",
    "sg:province":"Graubunden",
    "wof:name":"Rico Frigg Blumenladen",
    "wof:placetype":"venue"
},
  "geometry": {"coordinates":[9.439457,46.698975],"type":"Point"}
}