{
  "type": "Feature",
  "properties": {
    "iso:country":"CH",
    "sg:address":"Via Ballerini 21",
    "sg:city":"Locarno",
    "sg:orig_category":"Grosshandel mit Erzen U Metallen Herstellung von Drahtwaren",
    "sg:phone":"+41 91 751 76 76",
    "sg:postcode":"6600",
    "sg:province":"Ticino",
    "wof:name":"Edilfer Sa",
    "wof:placetype":"venue"
},
  "geometry": {"coordinates":[8.8003940582,46.1705741882],"type":"Point"}
}