{
  "type": "Feature",
  "properties": {
    "iso:country":"CH",
    "sg:address":"Via Nassa 46",
    "sg:city":"Lugano",
    "sg:orig_category":"Non-Classified Establishments",
    "sg:postcode":"6900",
    "sg:province":"Ticino",
    "wof:name":"Dott.med.armando Fetz Specialista Fmh",
    "wof:placetype":"venue"
},
  "geometry": {"coordinates":[8.9494447708,46.0017089844],"type":"Point"}
}