{
  "type": "Feature",
  "properties": {
    "iso:country":"CH",
    "sg:address":"Furkastrasse 17",
    "sg:city":"Brig",
    "sg:orig_category":"Detailhandel Reparatur von Gebrauchsg\u00fctern Vermietung von Gebrauchsg\u00fctern",
    "sg:phone":"+41 62 771 61 44",
    "sg:postcode":"3900",
    "sg:province":"Valais",
    "wof:name":"Videothek L\u00f6wen Sp\u00e4ti B.",
    "wof:placetype":"venue"
},
  "geometry": {"coordinates":[8.1825256348,47.2539482117],"type":"Point"}
}