{
  "type": "Feature",
  "properties": {
    "iso:country":"CH",
    "sg:address":"La Cour-de-chaulin",
    "sg:city":"Chamby",
    "sg:orig_category":"Architekturb\u00fcros",
    "sg:phone":"+41 21 964 50 18",
    "sg:postcode":"1832",
    "sg:province":"Vaud",
    "wof:name":"Atelier Wallace M\u00e9rinat Architecte Sa",
    "wof:placetype":"venue"
},
  "geometry": {"coordinates":[6.930481,46.469646],"type":"Point"}
}