{
  "type": "Feature",
  "properties": {
    "iso:country":"CH",
    "sg:address":"Herrengasse 46",
    "sg:city":"Oltingen",
    "sg:orig_category":"Non-Classified Establishments",
    "sg:postcode":"4494",
    "sg:province":"Basel-Landschaft",
    "wof:name":"Peter Michel, Nachfolger Yves Donz\u00e9",
    "wof:placetype":"venue"
},
  "geometry": {"coordinates":[7.6268639565,46.7273178101],"type":"Point"}
}