{
  "type": "Feature",
  "properties": {
    "iso:country":"CH",
    "sg:address":"Zone Industrielle 1617 Remaufens. Postfach",
    "sg:city":"Remaufens",
    "sg:orig_category":"Herstellung von sonstigen Nahrungsmitteln",
    "sg:postcode":"1617",
    "sg:province":"Fribourg",
    "wof:name":"A.m.d. Applicateur Mousse Et Distribution Julio Produits En Mousse; Fabrication, Export.",
    "wof:placetype":"venue"
},
  "geometry": {"coordinates":[6.8788499832,46.5283584595],"type":"Point"}
}