{
  "type": "Feature",
  "properties": {
    "iso:country":"CH",
    "sg:address":"Rue Du Vidollet 5",
    "sg:city":"Gen\u00e8ve",
    "sg:orig_category":"Datenverarbeitungsdienste",
    "sg:phone":"+41 79 434 93 66",
    "sg:postcode":"1202",
    "sg:province":"Gen\u00e8ve",
    "wof:name":"Ami Jacques Gander Informatique",
    "wof:placetype":"venue"
},
  "geometry": {"coordinates":[6.13909,46.216354],"type":"Point"}
}