{
  "type": "Feature",
  "properties": {
    "iso:country":"CH",
    "sg:address":"Limmattalstrasse 10",
    "sg:city":"Geroldswil",
    "sg:orig_category":"Wirtschaftspr\u00fcfung, Steuerberatung U Treuhand",
    "sg:phone":"+41 17493100",
    "sg:postcode":"8954",
    "sg:province":"Z\u00fcrich",
    "wof:name":"Ernst Treuhand Und Unternehmensberatung",
    "wof:placetype":"venue"
},
  "geometry": {"coordinates":[8.4140501022,47.4195709229],"type":"Point"}
}