{
  "type": "Feature",
  "properties": {
    "iso:country":"CH",
    "sg:address":"Tscharandistrasse 2",
    "sg:city":"Solothurn",
    "sg:classifiers":[
        {
            "category":"Manufacturing",
            "subcategory":"Metals",
            "type":"Manufacturing & Wholesale Goods"
        }
    ],
    "sg:phone":"+41 32 682 18 19",
    "sg:postcode":"4500",
    "sg:province":"Solothurn",
    "sg:tags":[
        "processing",
        "component",
        "shaped"
    ],
    "wof:name":"Dreso Ag",
    "wof:placetype":"venue"
},
  "geometry": {"coordinates":[7.5207810402,47.209941864],"type":"Point"}
}