{
  "type": "Feature",
  "properties": {
    "iso:country":"CH",
    "sg:address":"Rebgasse 45",
    "sg:city":"Binningen",
    "sg:orig_category":"Interessenvertretungen",
    "sg:phone":"+41 61 302 18 58",
    "sg:postcode":"4102",
    "sg:province":"Basel-Landschaft",
    "wof:name":"Molinari & Partner",
    "wof:placetype":"venue"
},
  "geometry": {"coordinates":[7.5661239624,47.5417633057],"type":"Point"}
}