{
  "type": "Feature",
  "properties": {
    "iso:country":"CH",
    "sg:address":"Rue De Bourg 11 1000 Lausanne. Postfach",
    "sg:city":"Lausanne",
    "sg:classifiers":[
        {
            "category":"Professional",
            "subcategory":"Employment Agencies",
            "type":"Services"
        }
    ],
    "sg:phone":"+41 71 750 08 20",
    "sg:postcode":"1003",
    "sg:province":"Vaud",
    "sg:tags":[
        "personal",
        "u",
        "stellenvermittlung"
    ],
    "wof:name":"Work-shop Personalberatung Gmbh",
    "wof:placetype":"venue"
},
  "geometry": {"coordinates":[9.5431070328,47.378364563],"type":"Point"}
}