{
  "type": "Feature",
  "properties": {
    "iso:country":"CH",
    "sg:address":"Im Rank 58",
    "sg:city":"Zug",
    "sg:orig_category":"Unternehmensberatung Wirtschaftspr\u00fcfung, Steuerberatung U Treuhand",
    "sg:phone":"+41 41 740 29 49",
    "sg:postcode":"6300",
    "sg:province":"Zug",
    "wof:name":"Summit Capital Gmbh",
    "wof:placetype":"venue"
},
  "geometry": {"coordinates":[8.4906787872,47.1806182861],"type":"Point"}
}