{
  "type": "Feature",
  "properties": {
    "iso:country":"CH",
    "sg:address":"Schaffhauserstrasse 367",
    "sg:city":"Z\u00fcrich",
    "sg:orig_category":"Aktivit\u00e4ten der Generalunternehmen im Baugewerbe Vermietung U Verpachtung von eigenen Immobilien",
    "sg:phone":"+41 13119330",
    "sg:postcode":"8050",
    "sg:province":"Z\u00fcrich",
    "wof:name":"Wibag Bau Ag",
    "wof:placetype":"venue"
},
  "geometry": {"coordinates":[8.546217,47.411694],"type":"Point"}
}