{
  "type": "Feature",
  "properties": {
    "iso:country":"CH",
    "sg:address":"7317",
    "sg:city":"Valens",
    "sg:classifiers":[
        {
            "category":"Restaurant",
            "type":"Food & Drink"
        }
    ],
    "sg:phone":"+41 71 222 03 55",
    "sg:postcode":"7317",
    "sg:province":"St. Gallen",
    "wof:name":"Restaurant Klubhaus",
    "wof:placetype":"venue"
},
  "geometry": {"coordinates":[9.3662223816,47.4223556519],"type":"Point"}
}