{
  "type": "Feature",
  "properties": {
    "iso:country":"CH",
    "sg:address":"Birmensdorferstrasse 95",
    "sg:city":"Z\u00fcrich",
    "sg:orig_category":"Kosmetikinstitute",
    "sg:phone":"+41 14504205",
    "sg:postcode":"8003",
    "sg:province":"Z\u00fcrich",
    "wof:name":"Amazonia Gmbh",
    "wof:placetype":"venue"
},
  "geometry": {"coordinates":[8.5229673386,47.3707084656],"type":"Point"}
}