{
  "type": "Feature",
  "properties": {
    "iso:country":"CH",
    "sg:address":"Murtenstrasse 70",
    "sg:city":"Biel/bienne",
    "sg:orig_category":"Wirtschafts- and Arbeitgeberverb\u00e4nde",
    "sg:postcode":"2503",
    "sg:province":"Bern",
    "wof:name":"Verband Schweiz.kuttlermeister",
    "wof:placetype":"venue"
},
  "geometry": {"coordinates":[7.2460198402,47.1308517456],"type":"Point"}
}