{
  "type": "Feature",
  "properties": {
    "iso:country":"CH",
    "sg:address":"Hunzikenbr\u00fccke",
    "sg:city":"Belp",
    "sg:classifiers":[
        {
            "category":"Restaurant",
            "type":"Food & Drink"
        }
    ],
    "sg:phone":"+41 31 819 15 55",
    "sg:postcode":"3123",
    "sg:province":"Bern",
    "wof:name":"Restaurant Campagna",
    "wof:placetype":"venue"
},
  "geometry": {"coordinates":[7.5366630554,46.8889427185],"type":"Point"}
}