{
  "type": "Feature",
  "properties": {
    "iso:country":"CH",
    "sg:address":"Kehlhofstrasse 9",
    "sg:city":"Egnach",
    "sg:orig_category":"Vermittlung von Immobilien",
    "sg:phone":"+41 71 477 19 20",
    "sg:postcode":"9322",
    "sg:province":"Thurgau",
    "wof:name":"Hans K\u00fcnzler Planungsb\u00fcro",
    "wof:placetype":"venue"
},
  "geometry": {"coordinates":[9.3776950836,47.5450897217],"type":"Point"}
}