{
  "type": "Feature",
  "properties": {
    "addr:full":"Maihofstrasse 68 6006 Luzern. Postfach 103 Luzern Luzern 6006",
    "addr:housenumber":"68;103",
    "addr:postcode":"6006;6006",
    "addr:street":"Maihofstrasse;Postfach",
    "iso:country":"CH",
    "sg:address":"Maihofstrasse 68 6006 Luzern. Postfach 103",
    "sg:city":"Luzern",
    "sg:orig_category":"Architektur U Ingenieurb\u00fcros",
    "sg:phone":"+41 41 420 40 44",
    "sg:postcode":"6006",
    "sg:province":"Luzern",
    "wof:name":"Krell + Brun Bau Und Projektleitungen Ag",
    "wof:placetype":"venue"
},
  "geometry": {"coordinates":[8.311482,47.065125],"type":"Point"}
}