{
  "type": "Feature",
  "properties": {
    "iso:country":"CH",
    "sg:address":"Schmiedengasse 9",
    "sg:city":"Solothurn",
    "sg:orig_category":"Detailhandel mit Damenbekleidung Herstellung von Oberbekleidung",
    "sg:phone":"+41 32 621 90 21",
    "sg:postcode":"4500",
    "sg:province":"Solothurn",
    "wof:name":"Pour Madame Sa",
    "wof:placetype":"venue"
},
  "geometry": {"coordinates":[7.5351572037,47.2073364258],"type":"Point"}
}