{
  "type": "Feature",
  "properties": {
    "iso:country":"CH",
    "sg:address":"Surseestrasse 53 6206 Neuenkirch. Postfach",
    "sg:city":"Ebikon",
    "sg:orig_category":"Sanit\u00e4r, Heizungs U L\u00fcftungsinstallation",
    "sg:phone":"+41 41 440 66 69",
    "sg:postcode":"6030",
    "sg:province":"Luzern",
    "wof:name":"Meyer Haustechnik Ag Neuenkirch",
    "wof:placetype":"venue"
},
  "geometry": {"coordinates":[8.2011356354,47.1034812927],"type":"Point"}
}