{
  "type": "Feature",
  "properties": {
    "iso:country":"CH",
    "sg:address":"Avenue De La Gare 24 1450 Ste-croix Case Postale 111",
    "sg:city":"Ste-croix",
    "sg:orig_category":"Reiseb\u00fcros",
    "sg:phone":"+41 24 454 19 94",
    "sg:postcode":"1450",
    "sg:province":"Vaud",
    "wof:name":"Voyages Yverdon-ste-croix",
    "wof:placetype":"venue"
},
  "geometry": {"coordinates":[6.5009579659,46.8193626404],"type":"Point"}
}