{
  "type": "Feature",
  "properties": {
    "addr:full":"Criblet Rue Du 7 Fribourg Fribourg 1700",
    "addr:postcode":"1700",
    "addr:street":"Rue Du 7",
    "iso:country":"CH",
    "sg:address":"Criblet Rue Du 7",
    "sg:city":"Fribourg",
    "sg:classifiers":[
        {
            "category":"Bars & Pubs",
            "type":"Food & Drink"
        }
    ],
    "sg:postcode":"1700",
    "sg:province":"Fribourg",
    "wof:name":"Iceberg Bar, Peiry Alexandre",
    "wof:placetype":"venue"
},
  "geometry": {"coordinates":[7.153943,46.804985],"type":"Point"}
}