{
  "type": "Feature",
  "properties": {
    "iso:country":"CH",
    "sg:address":"St.gallerstrasse 77",
    "sg:city":"Herisau",
    "sg:classifiers":[
        {
            "category":"Restaurant",
            "type":"Food & Drink"
        }
    ],
    "sg:phone":"+41 71 351 13 84",
    "sg:postcode":"9100",
    "sg:province":"Appenzell Ausserrhoden",
    "wof:name":"Restaurant Alter Zoll",
    "wof:placetype":"venue"
},
  "geometry": {"coordinates":[9.2929525375,47.3961029053],"type":"Point"}
}