{
  "type": "Feature",
  "properties": {
    "iso:country":"CH",
    "sg:address":"Goldgrubenweg 42 2500 Biel/bienne. Postfach",
    "sg:city":"Biel/bienne",
    "sg:orig_category":"Herstellung von k\u00e4lte U lufttechnischen Erzeugnissen f\u00fcr gewerbliche Zwecke",
    "sg:phone":"+41 17612433",
    "sg:postcode":"2504",
    "sg:province":"Bern",
    "wof:name":"Marchionni M. Ag",
    "wof:placetype":"venue"
},
  "geometry": {"coordinates":[8.2788333893,47.3424034119],"type":"Point"}
}