{
  "type": "Feature",
  "properties": {
    "iso:country":"CH",
    "sg:address":"Flurwaldweg 300",
    "sg:city":"T\u00e4gerig",
    "sg:orig_category":"Kauf U Verkauf von Immobilien auf eigene Rechnung",
    "sg:postcode":"5522",
    "sg:province":"Aargau",
    "wof:name":"Josef Meier Liegenschaften & Verwaltungs Ag",
    "wof:placetype":"venue"
},
  "geometry": {"coordinates":[8.2794399261,47.4012336731],"type":"Point"}
}