{
  "type": "Feature",
  "properties": {
    "iso:country":"CH",
    "sg:address":"Insone",
    "sg:city":"Insone",
    "sg:orig_category":"Herstellung von Teppichen",
    "sg:phone":"+41 71241394",
    "sg:postcode":"6951",
    "sg:province":"Ticino",
    "wof:name":"Roten Jean-claude",
    "wof:placetype":"venue"
},
  "geometry": {"coordinates":[5.1808700562,45.8973388672],"type":"Point"}
}