{
  "type": "Feature",
  "properties": {
    "iso:country":"CH",
    "sg:address":"3474",
    "sg:city":"R\u00fcedisbach",
    "sg:orig_category":"Sportvereine Hornussen",
    "sg:phone":"+41 34 415 17 46",
    "sg:postcode":"3474",
    "sg:province":"Bern",
    "wof:name":"Hornussergesellschaft",
    "wof:placetype":"venue"
},
  "geometry": {"coordinates":[7.7029738426,47.1195526123],"type":"Point"}
}