{
  "type": "Feature",
  "properties": {
    "iso:country":"CH",
    "sg:address":"Via S.gottardo 160",
    "sg:city":"Savosa",
    "sg:orig_category":"Stukkateurgewerbe, Gipserei U Verputzerei Tapeziererei",
    "sg:phone":"+41 79 449 47 56",
    "sg:postcode":"6942",
    "sg:province":"Ticino",
    "wof:name":"Maternini Et Fils Sa",
    "wof:placetype":"venue"
},
  "geometry": {"coordinates":[6.9208049774,46.6975975037],"type":"Point"}
}