{
  "type": "Feature",
  "properties": {
    "iso:country":"CH",
    "sg:address":"R\u00f6ssligasse 11",
    "sg:city":"Winterthur",
    "sg:classifiers":[
        {
            "category":"Education",
            "subcategory":"Library",
            "type":"Public Place"
        }
    ],
    "sg:phone":"+41 52 232 05 33",
    "sg:postcode":"8405",
    "sg:province":"Z\u00fcrich",
    "sg:tags":[
        "u",
        "bibliotheken",
        "archive"
    ],
    "wof:name":"Kreisbibliothek Seen",
    "wof:placetype":"venue"
},
  "geometry": {"coordinates":[8.760651,47.482243],"type":"Point"}
}