{
  "type": "Feature",
  "properties": {
    "iso:country":"CH",
    "sg:address":"Gartenstrasse 9",
    "sg:city":"Cham",
    "sg:orig_category":"Detailhandel mit Computern U Software Hardwareberatung",
    "sg:phone":"+41 62 772 27 31",
    "sg:postcode":"6330",
    "sg:province":"Zug",
    "wof:name":"Compu-shop Menziken Gmbh",
    "wof:placetype":"venue"
},
  "geometry": {"coordinates":[8.272834,47.349579],"type":"Point"}
}