{
  "type": "Feature",
  "properties": {
    "iso:country":"CH",
    "sg:address":"Birchi 498",
    "sg:city":"Plasselb",
    "sg:orig_category":"Non-Classified Establishments",
    "sg:postcode":"1737",
    "sg:province":"Fribourg",
    "wof:name":"Kolly Marcel, Grabmalkunst",
    "wof:placetype":"venue"
},
  "geometry": {"coordinates":[7.2558951378,46.7386398315],"type":"Point"}
}