{
  "type": "Feature",
  "properties": {
    "iso:country":"CH",
    "sg:address":"Benknerstrasse 14",
    "sg:city":"Kaltbrunn",
    "sg:orig_category":"Non-Classified Establishments",
    "sg:phone":"+41 55 283 13 94",
    "sg:postcode":"8722",
    "sg:province":"St. Gallen",
    "wof:name":"Heinz Zahner Chemin\u00e9e-& Ofenbau",
    "wof:placetype":"venue"
},
  "geometry": {"coordinates":[9.0244092941,47.2115936279],"type":"Point"}
}