{
  "type": "Feature",
  "properties": {
    "iso:country":"CH",
    "sg:address":"7180",
    "sg:city":"Disentis/must\u00e9r",
    "sg:classifiers":[
        {
            "category":"Sports & Exercise",
            "subcategory":"Tennis Court",
            "type":"Entertainment"
        }
    ],
    "sg:phone":"+41 81 947 44 34",
    "sg:postcode":"7180",
    "sg:province":"Graubunden",
    "sg:tags":[
        "squash-centers",
        "hallen",
        "tennis-"
    ],
    "wof:name":"Umberto Zanin Sportzentrum Disentis",
    "wof:placetype":"venue"
},
  "geometry": {"coordinates":[8.8531293869,46.7046012878],"type":"Point"}
}