{
  "type": "Feature",
  "properties": {
    "iso:country":"CH",
    "sg:address":"Spenglerei 3618 Oberei B. S\u00fcderen. Postfach",
    "sg:city":"S\u00fcderen",
    "sg:orig_category":"Zimmerei, Dachdeckerei, Bauspenglerei U Abdichtung",
    "sg:phone":"+41 33 453 23 00",
    "sg:postcode":"3618",
    "sg:province":"Bern",
    "wof:name":"Wenger Theo, Spenglerei",
    "wof:placetype":"venue"
},
  "geometry": {"coordinates":[7.7245750427,46.8177490234],"type":"Point"}
}