{
  "type": "Feature",
  "properties": {
    "addr:full":"R\u00fcegsaustrasse 15 R\u00fcegsauschachen Bern 3415",
    "addr:housenumber":"15",
    "addr:postcode":"3415",
    "addr:street":"Rueegsaustrasse",
    "iso:country":"CH",
    "sg:address":"R\u00fcegsaustrasse 15",
    "sg:city":"R\u00fcegsauschachen",
    "sg:orig_category":"Detailhandel mit Bekleidung Detailhandel mit Textilien",
    "sg:phone":"+41 34 461 14 48",
    "sg:postcode":"3415",
    "sg:province":"Bern",
    "wof:name":"Stalder Mode Ag",
    "wof:placetype":"venue"
},
  "geometry": {"coordinates":[7.658806,47.017761],"type":"Point"}
}