{
  "type": "Feature",
  "properties": {
    "iso:country":"CH",
    "sg:address":"Rue De La Poste 16",
    "sg:city":"Martigny",
    "sg:orig_category":"Advokaturb\u00fcros Notariate",
    "sg:phone":"+41 32 422 16 50",
    "sg:postcode":"1920",
    "sg:province":"Valais",
    "wof:name":"Jean-marc Christe Etude D'avocat & Notaire",
    "wof:placetype":"venue"
},
  "geometry": {"coordinates":[7.343728,47.367229],"type":"Point"}
}