{
  "type": "Feature",
  "properties": {
    "iso:country":"CH",
    "sg:address":"Hofwiesenstrasse 55",
    "sg:city":"Z\u00fcrich",
    "sg:orig_category":"Reiseb\u00fcros U Reiseveranstalter",
    "sg:phone":"+41 13621144",
    "sg:postcode":"8057",
    "sg:province":"Z\u00fcrich",
    "wof:name":"Mondomaia, Antonio Iacovazzo Erbringung U. Vermittlung V. Dienstleist- Ungen In Tourismus, Freizeit, Abenteuer",
    "wof:placetype":"venue"
},
  "geometry": {"coordinates":[8.5361118317,47.3949394226],"type":"Point"}
}