{
  "type": "Feature",
  "properties": {
    "iso:country":"CH",
    "sg:address":"Ringstrasse 69",
    "sg:city":"Langenthal",
    "sg:orig_category":"Erbringung von Dienstleistungen f\u00fcr Unternehmen",
    "sg:phone":"+41 62 922 86 26",
    "sg:postcode":"4900",
    "sg:province":"Bern",
    "wof:name":"Text & Dokumentation, Schmied Hans-j\u00fcrg",
    "wof:placetype":"venue"
},
  "geometry": {"coordinates":[7.7833981514,47.2066955566],"type":"Point"}
}