{
  "type": "Feature",
  "properties": {
    "iso:country":"CH",
    "sg:address":"Neumattstrasse 5",
    "sg:city":"Bottmingen",
    "sg:orig_category":"Bauingenieurb\u00fcros Hochbau Bauingenieurb\u00fcros allgemein",
    "sg:phone":"+41 79 320 24 41",
    "sg:postcode":"4103",
    "sg:province":"Basel-Landschaft",
    "wof:name":"Shemshon Zloof Ingenieurb\u00fcro",
    "wof:placetype":"venue"
},
  "geometry": {"coordinates":[7.569101,47.525208],"type":"Point"}
}