{
  "type": "Feature",
  "properties": {
    "iso:country":"CH",
    "sg:address":"Via Brione 3",
    "sg:city":"Orselina",
    "sg:orig_category":"Wohnheime",
    "sg:phone":"+41 91 743 35 65",
    "sg:postcode":"6644",
    "sg:province":"Ticino",
    "wof:name":"Monastero S.hildegardis",
    "wof:placetype":"venue"
},
  "geometry": {"coordinates":[8.8029251099,46.1803512573],"type":"Point"}
}