{
  "type": "Feature",
  "properties": {
    "iso:country":"CH",
    "sg:address":"Chemin Du Pr\u00e9-de-la-tour 10",
    "sg:city":"Pully",
    "sg:orig_category":"Architektur U Ingenieurb\u00fcros",
    "sg:postcode":"1009",
    "sg:province":"Vaud",
    "wof:name":"Duvoisin Jean-marc",
    "wof:placetype":"venue"
},
  "geometry": {"coordinates":[6.661031,46.51123],"type":"Point"}
}