{
  "type": "Feature",
  "properties": {
    "iso:country":"CH",
    "sg:address":"Sch\u00f6nenhofstrasse 15 8500 Frauenfeld. Postfach",
    "sg:city":"Frauenfeld",
    "sg:orig_category":"Herstellung von sonstigen elektrischen Ausr\u00fcstungen",
    "sg:phone":"+41 52 720 30 30",
    "sg:postcode":"8500",
    "sg:province":"Thurgau",
    "wof:name":"Gotele Ag",
    "wof:placetype":"venue"
},
  "geometry": {"coordinates":[8.8717775345,47.5528335571],"type":"Point"}
}