{
  "type": "Feature",
  "properties": {
    "iso:country":"CH",
    "sg:address":"Sprensenb\u00fchlstrasse 4 8032 Z\u00fcrich",
    "sg:city":"Zust",
    "sg:orig_category":"Kauf U Verkauf von Immobilien auf eigene Rechnung",
    "sg:postcode":"32",
    "wof:name":"Urifca Ag",
    "wof:placetype":"venue"
},
  "geometry": {"coordinates":[8.639749527,46.8880310059],"type":"Point"}
}