{
  "type": "Feature",
  "properties": {
    "iso:country":"CH",
    "sg:address":"Strehlgasse 2 8001 Z\u00fcrich. Postfach",
    "sg:city":"Z\u00fcrich",
    "sg:orig_category":"Grosshandel mit chemischen Erzeugnissen",
    "sg:phone":"+41 12221750",
    "sg:postcode":"8032",
    "sg:province":"Z\u00fcrich",
    "wof:name":"Acrylan Ag",
    "wof:placetype":"venue"
},
  "geometry": {"coordinates":[8.5415220261,47.3715705872],"type":"Point"}
}