{
  "type": "Feature",
  "properties": {
    "iso:country":"CH",
    "sg:address":"Sporz Val 60 7078 Lenzerheide/lai. Postfach",
    "sg:city":"Lenzerheide/lai",
    "sg:orig_category":"Verwaltung von Immobilien",
    "sg:postcode":"7078",
    "sg:province":"Graubunden",
    "wof:name":"Isard Sa",
    "wof:placetype":"venue"
},
  "geometry": {"coordinates":[9.5578527451,46.7245788574],"type":"Point"}
}