{
  "type": "Feature",
  "properties": {
    "iso:country":"CH",
    "sg:address":"Kugelgasse 11",
    "sg:city":"M\u00e4nnedorf",
    "sg:classifiers":[
        {
            "category":"Restaurant",
            "type":"Food & Drink"
        }
    ],
    "sg:phone":"+41 19211221",
    "sg:postcode":"8708",
    "sg:province":"Z\u00fcrich",
    "wof:name":"Choi's China-restaurant & Caf\u00e9 Messerli",
    "wof:placetype":"venue"
},
  "geometry": {"coordinates":[8.6902990341,47.2539253235],"type":"Point"}
}