{
  "type": "Feature",
  "properties": {
    "iso:country":"CH",
    "sg:address":"Winterthurerstrasse 689 8051 Z\u00fcrich. Postfach",
    "sg:city":"Z\u00fcrich",
    "sg:orig_category":"Herstellung von k\u00e4lte U lufttechnischen Erzeugnissen f\u00fcr gewerbliche Zwecke",
    "sg:postcode":"8051",
    "sg:province":"Z\u00fcrich",
    "wof:name":"Tabo K\u00fchltechnik Kundert Peter K\u00fchltechnik, K\u00fchl- U. Tiefk\u00fchlzellenbau; Engineering, Beratung Usw",
    "wof:placetype":"venue"
},
  "geometry": {"coordinates":[8.5830831528,47.406463623],"type":"Point"}
}