{
  "type": "Feature",
  "properties": {
    "iso:country":"CH",
    "sg:address":"Einsiedlerstrasse 24",
    "sg:city":"W\u00e4denswil",
    "sg:orig_category":"Interessenvertretungen",
    "sg:postcode":"8820",
    "sg:province":"Z\u00fcrich",
    "wof:name":"Stiftung Zur Erhaltung Der Burg Alt-w\u00e4denswil",
    "wof:placetype":"venue"
},
  "geometry": {"coordinates":[8.6842393875,47.2212791443],"type":"Point"}
}