{
  "type": "Feature",
  "properties": {
    "iso:country":"CH",
    "sg:address":"Impasse Des Agges 13",
    "sg:city":"Avry-sur-matran",
    "sg:orig_category":"Physiotherapie",
    "sg:phone":"+41 26 470 25 97",
    "sg:postcode":"1754",
    "sg:province":"Fribourg",
    "wof:name":"Alain Pirlet Physioth\u00e9rapie",
    "wof:placetype":"venue"
},
  "geometry": {"coordinates":[7.0767331123,46.7891616821],"type":"Point"}
}