{
  "type": "Feature",
  "properties": {
    "iso:country":"CH",
    "sg:address":"Bachstrasse 276",
    "sg:city":"Oeschgen",
    "sg:orig_category":"Physiotherapie",
    "sg:phone":"+41 62 871 40 72",
    "sg:postcode":"5072",
    "sg:province":"Aargau",
    "wof:name":"Elisabeth Michel Physiotherapie",
    "wof:placetype":"venue"
},
  "geometry": {"coordinates":[8.0179729462,47.5173721313],"type":"Point"}
}