{
  "type": "Feature",
  "properties": {
    "iso:country":"CH",
    "sg:address":"2950",
    "sg:city":"Courgenay",
    "sg:orig_category":"Herstellung von Strumpfwaren Herstellung von gewirktem U gestricktem Stoff",
    "sg:phone":"+41 32 471 11 52",
    "sg:postcode":"2950",
    "sg:province":"Jura",
    "wof:name":"Girard Charles Fils",
    "wof:placetype":"venue"
},
  "geometry": {"coordinates":[7.1266851425,47.403213501],"type":"Point"}
}