{
  "type": "Feature",
  "properties": {
    "iso:country":"CH",
    "sg:address":"Schmiedeweg 2",
    "sg:city":"Worblaufen",
    "sg:orig_category":"Sportvereine Wassersport Rudern Vereine Milit\u00e4r",
    "sg:phone":"+41 31 921 31 22",
    "sg:postcode":"3048",
    "sg:province":"Bern",
    "wof:name":"Pontonierfahrverein Bern",
    "wof:placetype":"venue"
},
  "geometry": {"coordinates":[7.4636888504,46.97681427],"type":"Point"}
}