{
  "type": "Feature",
  "properties": {
    "iso:country":"CH",
    "sg:address":"Stickereistrasse 6",
    "sg:city":"Arbon",
    "sg:orig_category":"Herstellung von Betonerzeugnissen f\u00fcr den Bau Sonstige Herstellung von Konstruktionsteilen, Fertigba",
    "sg:phone":"+41 71 351 22 42",
    "sg:postcode":"9320",
    "sg:province":"Thurgau",
    "wof:name":"Roth Bautechnik Ag",
    "wof:placetype":"venue"
},
  "geometry": {"coordinates":[9.2996959686,47.405040741],"type":"Point"}
}