{
  "type": "Feature",
  "properties": {
    "iso:country":"CH",
    "sg:address":"Chemin De Pont-c\u00e9ard 14",
    "sg:city":"Versoix",
    "sg:orig_category":"Handelsvermittlung von Brennstoffen, Erzen, Metallen U Chemikalien",
    "sg:phone":"+41 22 755 34 78",
    "sg:postcode":"1290",
    "sg:province":"Gen\u00e8ve",
    "wof:name":"Interproducts Trading Andrey Roland",
    "wof:placetype":"venue"
},
  "geometry": {"coordinates":[6.1620459557,46.2877693176],"type":"Point"}
}