{
  "type": "Feature",
  "properties": {
    "iso:country":"CH",
    "sg:address":"Via Nosetto 4",
    "sg:city":"Bellinzona",
    "sg:orig_category":"Detailhandel mit Uhren U Schmuck Fachdetailhandel in Verkaufsr\u00e4umen",
    "sg:phone":"+41 91 825 23 55",
    "sg:postcode":"6500",
    "sg:province":"Ticino",
    "wof:name":"Borsa Sergio",
    "wof:placetype":"venue"
},
  "geometry": {"coordinates":[9.0226373672,46.1913146973],"type":"Point"}
}