{
  "type": "Feature",
  "properties": {
    "iso:country":"CH",
    "sg:address":"Hauptstrasse 14a",
    "sg:city":"T\u00e4gerwilen",
    "sg:orig_category":"Herstellung von medizinischen U chirurgischen Ger\u00e4ten Herstellung von medizinischen U chirurgischen ",
    "sg:phone":"+41 19702059",
    "sg:postcode":"8274",
    "sg:province":"Thurgau",
    "wof:name":"Medivent Medizintechnik Gerner J.",
    "wof:placetype":"venue"
},
  "geometry": {"coordinates":[8.815178,47.336979],"type":"Point"}
}