{
  "type": "Feature",
  "properties": {
    "iso:country":"CH",
    "sg:address":"4938 Rohrbach. Postfach",
    "sg:city":"Rohrbach",
    "sg:orig_category":"Organisationen des Gesundheitswesen",
    "sg:postcode":"4938",
    "sg:province":"Bern",
    "wof:name":"Samariterverein",
    "wof:placetype":"venue"
},
  "geometry": {"coordinates":[7.8123750687,47.1359062195],"type":"Point"}
}