{
  "type": "Feature",
  "properties": {
    "iso:country":"CH",
    "sg:address":"Breitmattweg 21a 3173 Oberwangen B. Bern. Postfach",
    "sg:city":"K\u00f6niz",
    "sg:orig_category":"Detailhandel mit Beleuchtungs U Haushaltsgegenst\u00e4nden Herstellung von keramischen Haushaltswaren U Z",
    "sg:phone":"+41 31 889 05 59",
    "sg:postcode":"3098",
    "sg:province":"Bern",
    "wof:name":"Porzellanders Kohli Esther Weissporzellan U. Bemahltes Porzellan; Verkauf Usw.",
    "wof:placetype":"venue"
},
  "geometry": {"coordinates":[7.356645,46.908863],"type":"Point"}
}