{
  "type": "Feature",
  "properties": {
    "iso:country":"CH",
    "sg:address":"Compognapark B",
    "sg:city":"Thusis",
    "sg:orig_category":"Sportvereine Boxen",
    "sg:phone":"+41 81 651 38 62",
    "sg:postcode":"7430",
    "sg:province":"Graubunden",
    "wof:name":"Box-club Thusis",
    "wof:placetype":"venue"
},
  "geometry": {"coordinates":[9.4429769516,46.6982650757],"type":"Point"}
}