{
  "type": "Feature",
  "properties": {
    "iso:country":"CH",
    "sg:address":"Oberfeldstrasse 2",
    "sg:city":"Langenthal",
    "sg:orig_category":"Vorschulen, Kinderg\u00e4rten",
    "sg:phone":"+41 62 922 44 53",
    "sg:postcode":"4900",
    "sg:province":"Bern",
    "wof:name":"Kindergarten Kl\u00e4si-kummer",
    "wof:placetype":"venue"
},
  "geometry": {"coordinates":[7.7805428505,47.2066268921],"type":"Point"}
}