{
  "type": "Feature",
  "properties": {
    "iso:country":"CH",
    "sg:address":"Hinterdorfstrasse 19",
    "sg:city":"Schwyz",
    "sg:classifiers":[
        {
            "category":"Bars & Pubs",
            "type":"Food & Drink"
        }
    ],
    "sg:phone":"+41 41 811 54 78",
    "sg:postcode":"6430",
    "sg:province":"Schwyz",
    "wof:name":"Falken Pub",
    "wof:placetype":"venue"
},
  "geometry": {"coordinates":[8.658711,47.02076],"type":"Point"}
}