{
  "type": "Feature",
  "properties": {
    "iso:country":"CH",
    "sg:address":"Voa Tgameltger",
    "sg:city":"Valbella",
    "sg:orig_category":"Detailhandel mit Getr\u00e4nken",
    "sg:phone":"+41 81 384 13 55",
    "sg:postcode":"7077",
    "sg:province":"Graubunden",
    "wof:name":"P. Bergamin Getr\u00e4nke Ag",
    "wof:placetype":"venue"
},
  "geometry": {"coordinates":[9.5569391251,46.7463722229],"type":"Point"}
}