{
  "type": "Feature",
  "properties": {
    "iso:country":"CH",
    "sg:address":"Saladin Rue Ant. 6",
    "sg:city":"Crans-pr\u00e8s-c\u00e9ligny",
    "sg:orig_category":"Fachdetailhandel in Verkaufsr\u00e4umen",
    "sg:phone":"+41 22 361 19 74",
    "sg:postcode":"1299",
    "sg:province":"Vaud",
    "wof:name":"De Boer Philip",
    "wof:placetype":"venue"
},
  "geometry": {"coordinates":[6.2061100006,46.3593864441],"type":"Point"}
}