{
  "type": "Feature",
  "properties": {
    "iso:country":"CH",
    "sg:address":"Casa Robinia",
    "sg:city":"Melano",
    "sg:orig_category":"Vermietung U Verpachtung von eigenen Immobilien",
    "sg:postcode":"6818",
    "sg:province":"Ticino",
    "wof:name":"Valco Sa",
    "wof:placetype":"venue"
},
  "geometry": {"coordinates":[7.1772699356,46.0913352966],"type":"Point"}
}