{
  "type": "Feature",
  "properties": {
    "iso:country":"CH",
    "sg:address":"Klybeckstrasse 20",
    "sg:city":"Basel",
    "sg:orig_category":"P\u00e9dicure",
    "sg:phone":"+41 61 692 46 47",
    "sg:postcode":"4057",
    "sg:province":"Basel-Stadt",
    "wof:name":"A Pied Chantal Clottu Institut F\u00fcr Fusspflege",
    "wof:placetype":"venue"
},
  "geometry": {"coordinates":[7.5917801857,47.5638122559],"type":"Point"}
}