{
  "type": "Feature",
  "properties": {
    "iso:country":"CH",
    "sg:address":"Hauptstrasse 3752 Wimmis. Postfach 48",
    "sg:city":"Wimmis",
    "sg:orig_category":"Gewinnung von Kies U Sand Herstellung von Betonerzeugnissen f\u00fcr den Bau",
    "sg:phone":"+41 33 657 16 25",
    "sg:postcode":"3752",
    "sg:province":"Bern",
    "wof:name":"Kiestag Kieswerk Steinigand Ag",
    "wof:placetype":"venue"
},
  "geometry": {"coordinates":[7.6480197906,46.6789932251],"type":"Point"}
}