{
  "type": "Feature",
  "properties": {
    "iso:country":"CH",
    "sg:address":"Dorfstrasse 14",
    "sg:city":"Sch\u00fcpfen",
    "sg:orig_category":"Vermietung von Gebrauchsg\u00fctern",
    "sg:phone":"+41 31 879 01 53",
    "sg:postcode":"3054",
    "sg:province":"Bern",
    "wof:name":"Kobel Beat",
    "wof:placetype":"venue"
},
  "geometry": {"coordinates":[7.3765320778,47.0390815735],"type":"Point"}
}