{
  "type": "Feature",
  "properties": {
    "iso:country":"CH",
    "sg:address":"Spiegelbergstrasse 4",
    "sg:city":"Walchwil",
    "sg:orig_category":"Handelsvermittlung U Grosshandel Sonstiger Grosshandel",
    "sg:phone":"+41 41 758 24 67",
    "sg:postcode":"6318",
    "sg:province":"Zug",
    "wof:name":"Havexa Susanna B\u00fcrgler Import & Export",
    "wof:placetype":"venue"
},
  "geometry": {"coordinates":[8.5182037354,47.0995674133],"type":"Point"}
}