{
  "type": "Feature",
  "properties": {
    "iso:country":"CH",
    "sg:address":"Chemin Grenet 18 1214 Vernier. Postfach",
    "sg:city":"Vernier",
    "sg:orig_category":"Non-Classified Establishments",
    "sg:postcode":"1214",
    "sg:province":"Gen\u00e8ve",
    "wof:name":"Interdean Sa",
    "wof:placetype":"venue"
},
  "geometry": {"coordinates":[6.0732550621,46.2179718018],"type":"Point"}
}