{
  "type": "Feature",
  "properties": {
    "iso:country":"CH",
    "sg:address":"Seilerstrasse 4 3011 Bern. Postfach",
    "sg:city":"Bern",
    "sg:orig_category":"Verwaltung von Immobilien",
    "sg:postcode":"3011",
    "sg:province":"Bern",
    "wof:name":"K\u00f6nig Beat",
    "wof:placetype":"venue"
},
  "geometry": {"coordinates":[7.9247078896,46.1060218811],"type":"Point"}
}