{
  "type": "Feature",
  "properties": {
    "iso:country":"CH",
    "sg:address":"Mont-blanc Chemin Du",
    "sg:city":"Aubonne",
    "sg:orig_category":"Stukkateurgewerbe, Gipserei U Verputzerei",
    "sg:postcode":"1170",
    "sg:province":"Vaud",
    "wof:name":"Vellotti Id\u00e9es S\u00e0rl",
    "wof:placetype":"venue"
},
  "geometry": {"coordinates":[6.3966598511,46.4943084717],"type":"Point"}
}