{
  "type": "Feature",
  "properties": {
    "iso:country":"CH",
    "sg:address":"Faubourg Du Lac 42 2502 Biel/bienne. Postfach",
    "sg:city":"Biel/bienne",
    "sg:orig_category":"Finanzierungsinstitutionen",
    "sg:postcode":"2502",
    "sg:province":"Bern",
    "wof:name":"Omniconsult, Succursale Bienne De Omnitech Ag Vaduz",
    "wof:placetype":"venue"
},
  "geometry": {"coordinates":[7.2396478653,47.1378440857],"type":"Point"}
}