{
  "type": "Feature",
  "properties": {
    "iso:country":"CH",
    "sg:address":"Rue Des Jardins 10",
    "sg:city":"Gen\u00e8ve",
    "sg:orig_category":"Innendekorationsateliers",
    "sg:phone":"+41 22 329 44 53",
    "sg:postcode":"1205",
    "sg:province":"Gen\u00e8ve",
    "wof:name":"Laurent Pansier Tapissier-d\u00e9corateur",
    "wof:placetype":"venue"
},
  "geometry": {"coordinates":[6.1323552132,46.2017478943],"type":"Point"}
}