{
  "type": "Feature",
  "properties": {
    "iso:country":"CH",
    "sg:address":"Baslerstr. 575.",
    "sg:city":"Leuggern",
    "sg:orig_category":"Pensionskassen",
    "sg:postcode":"5316",
    "sg:province":"Aargau",
    "wof:name":"Personalf\u00fcrsorgestiftung Der Firma Hans Rudolf Meisel.",
    "wof:placetype":"venue"
},
  "geometry": {"coordinates":[8.2014570236,47.5912246704],"type":"Point"}
}