{
  "type": "Feature",
  "properties": {
    "iso:country":"CH",
    "sg:address":"Dorfstrasse 7b",
    "sg:city":"B\u00fcnzen",
    "sg:orig_category":"Grosshandel mit Datenverarbeitungsger\u00e4ten",
    "sg:phone":"+41 61 716 91 22",
    "sg:postcode":"5624",
    "sg:province":"Aargau",
    "wof:name":"Itris Maintenance Ag Edv-ger\u00e4te; Wartung, Reparatur, Instandstellung, Unterhalt Usw",
    "wof:placetype":"venue"
},
  "geometry": {"coordinates":[7.5980730057,47.4854698181],"type":"Point"}
}