{
  "type": "Feature",
  "properties": {
    "iso:country":"CH",
    "sg:address":"Im Emmet 7",
    "sg:city":"Niederwil",
    "sg:classifiers":[
        {
            "category":"Professional",
            "subcategory":"Advertising",
            "type":"Services"
        }
    ],
    "sg:phone":"+41 56 622 03 83",
    "sg:postcode":"5524",
    "sg:province":"Aargau",
    "sg:tags":[
        "agency"
    ],
    "wof:name":"Creative Communication Studio Systems",
    "wof:placetype":"venue"
},
  "geometry": {"coordinates":[8.291371,47.376362],"type":"Point"}
}