{
  "type": "Feature",
  "properties": {
    "iso:country":"CH",
    "sg:address":"Feldstrasse 34",
    "sg:city":"Olten",
    "sg:orig_category":"Grosshandel mit B\u00fcromaschinen Grosshandel mit Datenverarbeitungsger\u00e4ten",
    "sg:phone":"+41 27 952 22 42",
    "sg:postcode":"4600",
    "sg:province":"Solothurn",
    "wof:name":"Siemens Schweiz Ag",
    "wof:placetype":"venue"
},
  "geometry": {"coordinates":[7.8695178032,46.2319335938],"type":"Point"}
}