{
  "type": "Feature",
  "properties": {
    "iso:country":"CH",
    "sg:address":"Oltnerstrasse 25",
    "sg:city":"H\u00e4gendorf",
    "sg:orig_category":"Instandhaltung U Reparatur von Automobilen",
    "sg:postcode":"4614",
    "sg:province":"Solothurn",
    "wof:name":"Garage Borrelli A.",
    "wof:placetype":"venue"
},
  "geometry": {"coordinates":[9.5620765686,47.3892936707],"type":"Point"}
}