{
  "type": "Feature",
  "properties": {
    "iso:country":"CH",
    "sg:address":"D\u00fcrntnerstrasse 6",
    "sg:city":"Hinwil",
    "sg:orig_category":"Reiseb\u00fcros U Reiseveranstalter",
    "sg:phone":"+41 19374084",
    "sg:postcode":"8340",
    "sg:province":"Z\u00fcrich",
    "wof:name":"Dornbierer Reisen Ag",
    "wof:placetype":"venue"
},
  "geometry": {"coordinates":[8.8430843353,47.3018531799],"type":"Point"}
}