{
  "type": "Feature",
  "properties": {
    "iso:country":"CH",
    "sg:address":"Sonnenberg 38",
    "sg:city":"Menzingen",
    "sg:orig_category":"Fernw\u00e4rmeversorgung",
    "sg:phone":"+41 41 755 03 82",
    "sg:postcode":"6313",
    "sg:province":"Zug",
    "wof:name":"Gutsch W\u00e4rme Ag",
    "wof:placetype":"venue"
},
  "geometry": {"coordinates":[8.5992860794,47.1748085022],"type":"Point"}
}