{
  "type": "Feature",
  "properties": {
    "iso:country":"CH",
    "sg:address":"Casa Torre 2",
    "sg:city":"Tenero",
    "sg:classifiers":[
        {
            "category":"Travel",
            "subcategory":"Hotels & Motels",
            "type":"Entertainment"
        }
    ],
    "sg:postcode":"6598",
    "sg:province":"Ticino",
    "sg:tags":[
        "hotels",
        "mit",
        "restaurant"
    ],
    "wof:name":"Albergo Carni Campofelice Di Amelia Balestra-cattori.",
    "wof:placetype":"venue"
},
  "geometry": {"coordinates":[8.8498601913,46.180896759],"type":"Point"}
}