{
  "type": "Feature",
  "properties": {
    "iso:country":"CH",
    "sg:address":"S\u00e4lih\u00fcgel 1",
    "sg:city":"Luzern",
    "sg:orig_category":"Architekturb\u00fcros",
    "sg:phone":"+41 41 242 03 03",
    "sg:postcode":"6005",
    "sg:province":"Luzern",
    "wof:name":"Steiner & Partner Ag Architekturb\u00fcro",
    "wof:placetype":"venue"
},
  "geometry": {"coordinates":[8.303053,47.045006],"type":"Point"}
}