{
  "type": "Feature",
  "properties": {
    "iso:country":"CH",
    "sg:address":"Gartenstrasse 4",
    "sg:city":"Lostorf",
    "sg:orig_category":"Datenverarbeitungsdienste Softwareentwicklung U beratung",
    "sg:phone":"+41 62 298 07 77",
    "sg:postcode":"4654",
    "sg:province":"Solothurn",
    "wof:name":"Topas Informatik Ag",
    "wof:placetype":"venue"
},
  "geometry": {"coordinates":[7.948087,47.381737],"type":"Point"}
}