{
  "type": "Feature",
  "properties": {
    "iso:country":"CH",
    "sg:address":"Rue Des Remparts 25",
    "sg:city":"Sion",
    "sg:orig_category":"Architekturb\u00fcros Unternehmensberatung",
    "sg:phone":"+41 27 322 21 62",
    "sg:postcode":"1950",
    "sg:province":"Valais",
    "wof:name":"Rolf Fuchs Sa Amb Atelier D'architecture",
    "wof:placetype":"venue"
},
  "geometry": {"coordinates":[7.360303,46.231396],"type":"Point"}
}