{
  "type": "Feature",
  "properties": {
    "iso:country":"CH",
    "sg:address":"Hauptstrasse 38",
    "sg:city":"B\u00e4ttwil",
    "sg:orig_category":"Herstellung von Automobilen Herstellung von landwirtschaftlichen Maschinen",
    "sg:phone":"+41 61 731 11 11",
    "sg:postcode":"4112",
    "sg:province":"Solothurn",
    "wof:name":"M\u00fcller Maschinen Ag B\u00e4ttwil",
    "wof:placetype":"venue"
},
  "geometry": {"coordinates":[7.5070638657,47.4902153015],"type":"Point"}
}