{
  "type": "Feature",
  "properties": {
    "iso:country":"CH",
    "sg:address":"Moosweg 60",
    "sg:city":"Hindelbank",
    "sg:orig_category":"Wirtschaftspr\u00fcfung, Steuerberatung U Treuhand",
    "sg:phone":"+41 34 411 06 50",
    "sg:postcode":"3324",
    "sg:province":"Bern",
    "wof:name":"Kindlimann & Partner Ag, Zweigniederlassung 3324 Hindelbank Be",
    "wof:placetype":"venue"
},
  "geometry": {"coordinates":[7.5482368469,47.0444755554],"type":"Point"}
}