{
  "type": "Feature",
  "properties": {
    "iso:country":"CH",
    "sg:address":"Bertiswilstrasse 77",
    "sg:city":"Rothenburg",
    "sg:orig_category":"Tierarztpraxis",
    "sg:phone":"+41 41 280 10 50",
    "sg:postcode":"6023",
    "sg:province":"Luzern",
    "wof:name":"Dr. Med. Vet. Markus St\u00f6ckli Tierarzt",
    "wof:placetype":"venue"
},
  "geometry": {"coordinates":[8.2667102814,47.1010513306],"type":"Point"}
}