{
  "type": "Feature",
  "properties": {
    "iso:country":"CH",
    "sg:address":"Hauptstrasse 76",
    "sg:city":"B\u00f6nigen",
    "sg:orig_category":"Non-Classified Establishments",
    "sg:postcode":"3806",
    "sg:province":"Bern",
    "wof:name":"Caf\u00e9-st\u00fcbli Bl\u00e4si",
    "wof:placetype":"venue"
},
  "geometry": {"coordinates":[7.8954839706,46.6866264343],"type":"Point"}
}