{
  "type": "Feature",
  "properties": {
    "iso:country":"CH",
    "sg:address":"Baselstrasse 113",
    "sg:city":"Arlesheim",
    "sg:orig_category":"Detektivb\u00fcros U \u00dcberwachung",
    "sg:postcode":"4144",
    "sg:province":"Basel-Landschaft",
    "wof:name":"Ed's Begleitschutz Gmbh",
    "wof:placetype":"venue"
},
  "geometry": {"coordinates":[7.6193351746,47.5075569153],"type":"Point"}
}