{
  "type": "Feature",
  "properties": {
    "iso:country":"CH",
    "sg:address":"Im Boge 10",
    "sg:city":"Russikon",
    "sg:orig_category":"Interessenvertretungen",
    "sg:postcode":"8332",
    "sg:province":"Z\u00fcrich",
    "wof:name":"Kreyenb\u00fchl Johannes Stiftung",
    "wof:placetype":"venue"
},
  "geometry": {"coordinates":[8.7729167938,47.3999061584],"type":"Point"}
}