{
  "type": "Feature",
  "properties": {
    "iso:country":"CH",
    "sg:address":"Br\u00fcgg Route De 121",
    "sg:city":"Biel/bienne",
    "sg:orig_category":"Unclassifiable Establishments",
    "sg:phone":"+41 32 365 99 88",
    "sg:postcode":"2503",
    "sg:province":"Bern",
    "wof:name":"Bernard Monbaron",
    "wof:placetype":"venue"
},
  "geometry": {"coordinates":[7.2634902,47.1304397583],"type":"Point"}
}