{
  "type": "Feature",
  "properties": {
    "iso:country":"CH",
    "sg:address":"Rheinstrasse 2 4127 Birsfelden. Postfach",
    "sg:city":"Birsfelden",
    "sg:orig_category":"Herstellung von Kakao, Schokoladeerzeugnissen U Zuckerwaren",
    "sg:phone":"+41 62 836 26 26",
    "sg:postcode":"4127",
    "sg:province":"Basel-Landschaft",
    "wof:name":"Chocolat Frey Ag",
    "wof:placetype":"venue"
},
  "geometry": {"coordinates":[8.0901870728,47.3858909607],"type":"Point"}
}