{
  "type": "Feature",
  "properties": {
    "iso:country":"CH",
    "sg:address":"Thujastrasse 58",
    "sg:city":"Z\u00fcrich",
    "sg:orig_category":"Selbst\u00e4ndige bildende K\u00fcnstler",
    "sg:phone":"+41 14823031",
    "sg:postcode":"8038",
    "sg:province":"Z\u00fcrich",
    "wof:name":"Rauber & Willi Bildhauer-& Grabmalatelier",
    "wof:placetype":"venue"
},
  "geometry": {"coordinates":[8.524017334,47.3477478027],"type":"Point"}
}