{
  "type": "Feature",
  "properties": {
    "iso:country":"CH",
    "sg:address":"Seeblickstrasse 4",
    "sg:city":"Jona",
    "sg:orig_category":"Detailhandel mit M\u00f6beln U Haushaltsgegenst\u00e4nden",
    "sg:postcode":"8645",
    "sg:province":"St. Gallen",
    "wof:name":"Sadegh-vaziri N.",
    "wof:placetype":"venue"
},
  "geometry": {"coordinates":[6.8687620163,46.4609718323],"type":"Point"}
}