{
  "type": "Feature",
  "properties": {
    "iso:country":"CH",
    "sg:address":"M\u00fchlegasse 7",
    "sg:city":"B\u00e4tterkinden",
    "sg:orig_category":"Malerei Stukkateurgewerbe, Gipserei U Verputzerei",
    "sg:phone":"+41 32 665 22 72",
    "sg:postcode":"3315",
    "sg:province":"Bern",
    "wof:name":"Robert Weber Maler-& Gipsergesch\u00e4ft",
    "wof:placetype":"venue"
},
  "geometry": {"coordinates":[7.5421919823,47.129573822],"type":"Point"}
}