{
  "type": "Feature",
  "properties": {
    "iso:country":"CH",
    "sg:address":"Kirchstrasse 2 4856 Glash\u00fctten. Postfach",
    "sg:city":"Glash\u00fctten",
    "sg:orig_category":"Allgemeiner Hoch U Tiefbau",
    "sg:postcode":"4856",
    "sg:province":"Aargau",
    "wof:name":"Ruf Gebr. W. + H. Ag",
    "wof:placetype":"venue"
},
  "geometry": {"coordinates":[7.846071,47.257988],"type":"Point"}
}