{
  "type": "Feature",
  "properties": {
    "iso:country":"CH",
    "sg:address":"Grabenstrasse 32",
    "sg:city":"Zug",
    "sg:orig_category":"Patentverwertung",
    "sg:phone":"+41 14061077",
    "sg:postcode":"6300",
    "sg:province":"Zug",
    "wof:name":"K\u00fcpat Ag Patentverwertung",
    "wof:placetype":"venue"
},
  "geometry": {"coordinates":[8.4635324478,47.3626976013],"type":"Point"}
}