{
  "type": "Feature",
  "properties": {
    "iso:country":"CH",
    "sg:address":"N\u00fcschelerstrasse 30",
    "sg:city":"Z\u00fcrich",
    "sg:orig_category":"Non-Classified Establishments",
    "sg:phone":"+41 12117577",
    "sg:postcode":"8001",
    "sg:province":"Z\u00fcrich",
    "wof:name":"Augencenter",
    "wof:placetype":"venue"
},
  "geometry": {"coordinates":[8.5361013412,47.3723487854],"type":"Point"}
}