{
  "type": "Feature",
  "properties": {
    "addr:full":"Case Postale 68 Le Landeron Neuch\u00e2tel 2525",
    "addr:housenumber":"68",
    "addr:postcode":"2525",
    "addr:street":"Case Postale",
    "iso:country":"CH",
    "sg:address":"Case Postale 68",
    "sg:city":"Le Landeron",
    "sg:classifiers":[
        {
            "category":"Banks & Credit Unions",
            "subcategory":"Bank",
            "type":"Services"
        }
    ],
    "sg:phone":"+41 32 466 79 29",
    "sg:postcode":"2525",
    "sg:province":"Neuch\u00e2tel",
    "wof:name":"Banque Raiffeisen Epis D'ajoie",
    "wof:placetype":"venue"
},
  "geometry": {"coordinates":[7.09926,47.452709],"type":"Point"}
}