{
  "type": "Feature",
  "properties": {
    "iso:country":"CH",
    "sg:address":"Bahnhofstrasse 5",
    "sg:city":"Uster",
    "sg:orig_category":"Gesundheitswesen Physiotherapie",
    "sg:phone":"+41 19405791",
    "sg:postcode":"8610",
    "sg:province":"Z\u00fcrich",
    "wof:name":"Physiotherapie Uschter C. & R. Groll\u00e9-brouwers",
    "wof:placetype":"venue"
},
  "geometry": {"coordinates":[8.7193117142,47.349407196],"type":"Point"}
}