{
  "type": "Feature",
  "properties": {
    "iso:country":"CH",
    "sg:address":"Zunzgerstrasse 8",
    "sg:city":"Sissach",
    "sg:orig_category":"Detailhandel mit Fleisch U Fleischwaren",
    "sg:phone":"+41 61 971 12 56",
    "sg:postcode":"4450",
    "sg:province":"Basel-Landschaft",
    "wof:name":"Metzgerei H\u00e4ring Gmbh",
    "wof:placetype":"venue"
},
  "geometry": {"coordinates":[7.8098049164,47.4635848999],"type":"Point"}
}