{
  "type": "Feature",
  "properties": {
    "iso:country":"CH",
    "sg:address":"L\u00e4nggassstrasse 65 3012 Bern. Postfach",
    "sg:city":"Bern",
    "sg:orig_category":"Saunas, Solarien, Fitnesszentren U \u00e4hnliches",
    "sg:phone":"+41 52 741 45 55",
    "sg:postcode":"3005",
    "sg:province":"Bern",
    "wof:name":"Sun-line Sonnenstudio M. Inglin",
    "wof:placetype":"venue"
},
  "geometry": {"coordinates":[8.8593511581,47.6601371765],"type":"Point"}
}