{
  "type": "Feature",
  "properties": {
    "iso:country":"CH",
    "sg:address":"Klotenerstrasse 1",
    "sg:city":"Bassersdorf",
    "sg:orig_category":"Kinderkrippen U horte",
    "sg:postcode":"8303",
    "sg:province":"Z\u00fcrich",
    "wof:name":"Spielgruppe Des Vereins Chliichind & Eltere",
    "wof:placetype":"venue"
},
  "geometry": {"coordinates":[8.8027982712,47.3271751404],"type":"Point"}
}