{
  "type": "Feature",
  "properties": {
    "addr:full":"Sulgenbachstrasse 51 3007 Bern. Postfach Z\u00fcrich Z\u00fcrich 8001",
    "addr:housenumber":"51",
    "addr:postcode":"3007;8001",
    "addr:street":"Sulgenbachstrasse",
    "iso:country":"CH",
    "sg:address":"Sulgenbachstrasse 51 3007 Bern. Postfach",
    "sg:city":"Z\u00fcrich",
    "sg:orig_category":"Betrieb U technische Hilfsdienste des Kultur U Unterhaltungswesens Erbringung von sonstigen Dienstle",
    "sg:phone":"+41 12410830",
    "sg:postcode":"8001",
    "sg:province":"Z\u00fcrich",
    "wof:name":"Burgerswiss Gmbh",
    "wof:placetype":"venue"
},
  "geometry": {"coordinates":[7.433357,46.940884],"type":"Point"}
}