{
  "type": "Feature",
  "properties": {
    "iso:country":"CH",
    "sg:address":"Dorfstrasse 19 5025 Asp. Postfach",
    "sg:city":"Asp",
    "sg:orig_category":"Softwareentwicklung U beratung",
    "sg:postcode":"5025",
    "sg:province":"Aargau",
    "wof:name":"Senn E. Hard Und Software",
    "wof:placetype":"venue"
},
  "geometry": {"coordinates":[8.0509138107,47.4447402954],"type":"Point"}
}