{
  "type": "Feature",
  "properties": {
    "iso:country":"CH",
    "sg:address":"Grand-rue 26",
    "sg:city":"Rolle",
    "sg:orig_category":"Geb\u00e4ude, Wohnungsreinigung Reinigungsgewerbe",
    "sg:phone":"+41 21 826 04 39",
    "sg:postcode":"1180",
    "sg:province":"Vaud",
    "wof:name":"Serge Ruchonnet Entretien D'habitations",
    "wof:placetype":"venue"
},
  "geometry": {"coordinates":[6.3399238586,46.4594345093],"type":"Point"}
}