{
  "type": "Feature",
  "properties": {
    "iso:country":"CH",
    "sg:address":"Viale Stazione",
    "sg:city":"Airolo",
    "sg:classifiers":[
        {
            "category":"Travel",
            "subcategory":"Hotels & Motels",
            "type":"Entertainment"
        }
    ],
    "sg:phone":"+41 91 869 17 22",
    "sg:postcode":"6780",
    "sg:province":"Ticino",
    "sg:tags":[
        "hotels",
        "mit",
        "restaurant"
    ],
    "wof:name":"Albergo Des Alpes",
    "wof:placetype":"venue"
},
  "geometry": {"coordinates":[8.6040563583,46.5281944275],"type":"Point"}
}