{
  "type": "Feature",
  "properties": {
    "iso:country":"CH",
    "sg:address":"Rue Pichard 20 1003 Lausanne. Postfach",
    "sg:city":"Lausanne",
    "sg:orig_category":"Allgemeinbildende weiterf\u00fchrende Schulen",
    "sg:postcode":"1002",
    "sg:province":"Vaud",
    "wof:name":"Ecole Alpine Pr\u00e9-fleuri S\u00e0rl",
    "wof:placetype":"venue"
},
  "geometry": {"coordinates":[6.99538,46.296612],"type":"Point"}
}