{
  "type": "Feature",
  "properties": {
    "iso:country":"CH",
    "sg:address":"Niesenstrasse 28",
    "sg:city":"Thun",
    "sg:orig_category":"Vereine Trachten",
    "sg:postcode":"3600",
    "sg:province":"Bern",
    "wof:name":"Trachtengruppe Mauensee",
    "wof:placetype":"venue"
},
  "geometry": {"coordinates":[8.0931692123,47.1640319824],"type":"Point"}
}