{
  "type": "Feature",
  "properties": {
    "iso:country":"CH",
    "sg:address":"Dreik\u00f6nigstrasse 34",
    "sg:city":"Z\u00fcrich",
    "sg:orig_category":"Unclassifiable Establishments",
    "sg:postcode":"8002",
    "sg:province":"Z\u00fcrich",
    "wof:name":"Ascot Classic Filmverleih Ag",
    "wof:placetype":"venue"
},
  "geometry": {"coordinates":[8.5346488953,47.366558075],"type":"Point"}
}