{
  "type": "Feature",
  "properties": {
    "iso:country":"CH",
    "sg:address":"Fluestrasse 30",
    "sg:city":"R\u00fcmlang",
    "sg:orig_category":"Allgemeiner Hoch U Tiefbau",
    "sg:phone":"+41 79 665 17 18",
    "sg:postcode":"8153",
    "sg:province":"Z\u00fcrich",
    "wof:name":"Peter Schindler Ag, Bauunternehmung",
    "wof:placetype":"venue"
},
  "geometry": {"coordinates":[8.52569,47.452011],"type":"Point"}
}