{
  "type": "Feature",
  "properties": {
    "iso:country":"CH",
    "sg:address":"Birmannsgasse 48",
    "sg:city":"Basel",
    "sg:orig_category":"Einbau von Schreinerwaren",
    "sg:phone":"+41 14926167",
    "sg:postcode":"4055",
    "sg:province":"Basel-Stadt",
    "wof:name":"G.m. (gastro Management) Gmbh",
    "wof:placetype":"venue"
},
  "geometry": {"coordinates":[8.4567689896,47.3693466187],"type":"Point"}
}