{
  "type": "Feature",
  "properties": {
    "iso:country":"CH",
    "sg:address":"Dorfstrasse 71",
    "sg:city":"Kleinl\u00fctzel",
    "sg:classifiers":[
        {
            "category":"Travel",
            "subcategory":"Hotels & Motels",
            "type":"Entertainment"
        }
    ],
    "sg:phone":"+41 33 822 18 25",
    "sg:postcode":"4245",
    "sg:province":"Solothurn",
    "sg:tags":[
        "hotels",
        "mit",
        "restaurant"
    ],
    "wof:name":"Hotel Tell",
    "wof:placetype":"venue"
},
  "geometry": {"coordinates":[7.8642811775,46.6804656982],"type":"Point"}
}