{
  "type": "Feature",
  "properties": {
    "iso:country":"CH",
    "sg:address":"Reben\u00e4cker",
    "sg:city":"Birwinken",
    "sg:orig_category":"Werbung",
    "sg:phone":"+41 71 648 10 36",
    "sg:postcode":"8585",
    "sg:province":"Thurgau",
    "wof:name":"Progress-werbung, Huber P.",
    "wof:placetype":"venue"
},
  "geometry": {"coordinates":[9.2476558685,47.5929412842],"type":"Point"}
}