{
  "type": "Feature",
  "properties": {
    "iso:country":"CH",
    "sg:address":"Niklaus Wengistrasse 53",
    "sg:city":"Grenchen",
    "sg:orig_category":"Detailhandel mit Waren verschiedener Art, Hauptrichtung Nahrungsmittel",
    "sg:phone":"+41 32 665 33 39",
    "sg:postcode":"2540",
    "sg:province":"Solothurn",
    "wof:name":"Fritz Ellenberger Lebensmittel",
    "wof:placetype":"venue"
},
  "geometry": {"coordinates":[7.5559802055,47.152381897],"type":"Point"}
}