{
  "type": "Feature",
  "properties": {
    "iso:country":"CH",
    "sg:address":"Dufourstrasse 5",
    "sg:city":"Basel",
    "sg:orig_category":"Unclassifiable Establishments",
    "sg:postcode":"4052",
    "sg:province":"Basel-Stadt",
    "wof:name":"Pw Electronic, Wegmann Peter",
    "wof:placetype":"venue"
},
  "geometry": {"coordinates":[8.3864603043,47.3352279663],"type":"Point"}
}