{
  "type": "Feature",
  "properties": {
    "iso:country":"CH",
    "sg:address":"Hauptstrasse 40a",
    "sg:city":"Sch\u00f6nengrund",
    "sg:orig_category":"Detailhandel mit Textilien Innenausbau",
    "sg:phone":"+41 71 361 13 20",
    "sg:postcode":"9105",
    "sg:province":"Appenzell Ausserrhoden",
    "wof:name":"Willi Frischknecht Polsterei Innenausbau",
    "wof:placetype":"venue"
},
  "geometry": {"coordinates":[9.2246809006,47.328338623],"type":"Point"}
}