{
  "type": "Feature",
  "properties": {
    "iso:country":"CH",
    "sg:address":"T\u00fcftelstrasse 51",
    "sg:city":"Koblenz",
    "sg:orig_category":"Elektroinstallation Grosshandel mit elektrischen Haushaltsger\u00e4ten, Radio U Fernsehger\u00e4ten",
    "sg:phone":"+41 56 246 14 22",
    "sg:postcode":"5322",
    "sg:province":"Aargau",
    "wof:name":"M\u00fchlberg Ag",
    "wof:placetype":"venue"
},
  "geometry": {"coordinates":[8.2495555878,47.6116638184],"type":"Point"}
}