{
  "type": "Feature",
  "properties": {
    "iso:country":"CH",
    "sg:address":"Industriestrasse 7",
    "sg:city":"Neuenhof",
    "sg:orig_category":"Mechanik Mechanische Werkst\u00e4tten",
    "sg:phone":"+41 56 406 31 56",
    "sg:postcode":"5432",
    "sg:province":"Aargau",
    "wof:name":"3 S Ag Neuenhof",
    "wof:placetype":"venue"
},
  "geometry": {"coordinates":[8.3262424469,47.4555854797],"type":"Point"}
}