{
  "type": "Feature",
  "properties": {
    "iso:country":"CH",
    "sg:address":"Forelstrasse 46/40",
    "sg:city":"Ostermundigen",
    "sg:classifiers":[
        {
            "category":"Banks & Credit Unions",
            "subcategory":"Bank",
            "type":"Services"
        }
    ],
    "sg:phone":"+41 31 931 92 38",
    "sg:postcode":"3072",
    "sg:province":"Bern",
    "wof:name":"Schweiz. Mobiliar",
    "wof:placetype":"venue"
},
  "geometry": {"coordinates":[7.485439,46.961132],"type":"Point"}
}