{
  "type": "Feature",
  "properties": {
    "iso:country":"CH",
    "sg:address":"Moosgasse 15",
    "sg:city":"Jens",
    "sg:orig_category":"Herstellung von Mess U Kontrollinstrumenten U vorrichtungen Mechanische Werkst\u00e4tten",
    "sg:phone":"+41 71 767 91 11",
    "sg:postcode":"2565",
    "sg:province":"Bern",
    "wof:name":"Siemens Vdo Trading Ag",
    "wof:placetype":"venue"
},
  "geometry": {"coordinates":[9.5506057739,47.2993965149],"type":"Point"}
}