{
  "type": "Feature",
  "properties": {
    "iso:country":"CH",
    "sg:address":"Route Des Planti\u00e8res 30 1817 Brent Case Postale 10",
    "sg:city":"Brent",
    "sg:orig_category":"Sportvereine Wassersport Segeln",
    "sg:phone":"+41 21 964 56 95",
    "sg:postcode":"1817",
    "sg:province":"Vaud",
    "wof:name":"Yachtclub Montreux",
    "wof:placetype":"venue"
},
  "geometry": {"coordinates":[6.9030399323,46.457649231],"type":"Point"}
}