{
  "type": "Feature",
  "properties": {
    "iso:country":"CH",
    "sg:address":"Chemin Des Mollies 33a 1293 Bellevue. Postfach",
    "sg:city":"Bellevue",
    "sg:orig_category":"Maurerarbeiten Sonstiger spezialisierter Hoch U Tiefbau",
    "sg:phone":"+41 27 475 15 04",
    "sg:postcode":"1293",
    "sg:province":"Gen\u00e8ve",
    "wof:name":"Armand Epiney Et Fils Sa",
    "wof:placetype":"venue"
},
  "geometry": {"coordinates":[7.5864248276,46.2146835327],"type":"Point"}
}