{
  "type": "Feature",
  "properties": {
    "iso:country":"CH",
    "sg:address":"Gingins Route De 2-8",
    "sg:city":"Nyon",
    "sg:orig_category":"Handel mit Automobilen",
    "sg:phone":"+41 22 363 89 89",
    "sg:postcode":"1260",
    "sg:province":"Vaud",
    "wof:name":"Ferrari (suisse) Sa",
    "wof:placetype":"venue"
},
  "geometry": {"coordinates":[6.2390799522,46.3823661804],"type":"Point"}
}