{
  "type": "Feature",
  "properties": {
    "iso:country":"CH",
    "sg:address":"Denges Route De 25",
    "sg:city":"Lonay",
    "sg:orig_category":"Herstellung von Konstruktionsteilen, Fertigbauteilen U Ausbauelementen aus Holz",
    "sg:postcode":"1027",
    "sg:province":"Vaud",
    "wof:name":"Rea Juan Jos\u00e9",
    "wof:placetype":"venue"
},
  "geometry": {"coordinates":[6.520678997,46.5264778137],"type":"Point"}
}