{
  "type": "Feature",
  "properties": {
    "iso:country":"CH",
    "sg:address":"Seestrasse 31",
    "sg:city":"M\u00e4nnedorf",
    "sg:orig_category":"Herstellung von Metallkonstruktionen Mechanik",
    "sg:phone":"+41 19201708",
    "sg:postcode":"8708",
    "sg:province":"Z\u00fcrich",
    "wof:name":"Graber Marcel, Metallbau Und Kunstschlosserei",
    "wof:placetype":"venue"
},
  "geometry": {"coordinates":[8.6805992126,47.2580757141],"type":"Point"}
}