{
  "type": "Feature",
  "properties": {
    "iso:country":"CH",
    "sg:address":"Prop\u00e8ses",
    "sg:city":"Collombey",
    "sg:orig_category":"Restaurants Saunas",
    "sg:phone":"+41 19290055",
    "sg:postcode":"1868",
    "sg:province":"Valais",
    "wof:name":"Wellness-house Oetwil",
    "wof:placetype":"venue"
},
  "geometry": {"coordinates":[8.7195224762,47.2763404846],"type":"Point"}
}