{
  "type": "Feature",
  "properties": {
    "iso:country":"CH",
    "sg:address":"Schaiengarten 13",
    "sg:city":"Ettingen",
    "sg:orig_category":"Non-Classified Establishments",
    "sg:phone":"+41 61 722 02 90",
    "sg:postcode":"4107",
    "sg:province":"Basel-Landschaft",
    "wof:name":"Bleichenbacher Rolf",
    "wof:placetype":"venue"
},
  "geometry": {"coordinates":[7.542265892,47.4781532288],"type":"Point"}
}