{
  "type": "Feature",
  "properties": {
    "iso:country":"CH",
    "sg:address":"Tobelhofstrasse 355",
    "sg:city":"Gockhausen",
    "sg:classifiers":[
        {
            "category":"Restaurant",
            "type":"Food & Drink"
        }
    ],
    "sg:phone":"+41 18215265",
    "sg:postcode":"8044",
    "sg:province":"Z\u00fcrich",
    "wof:name":"Restaurant Frohsinn",
    "wof:placetype":"venue"
},
  "geometry": {"coordinates":[8.5983972549,47.3820953369],"type":"Point"}
}