{
  "type": "Feature",
  "properties": {
    "iso:country":"CH",
    "sg:address":"Kirchplatz 3",
    "sg:city":"B\u00fctschwil",
    "sg:orig_category":"Detailhandel mit Fleisch U Fleischwaren",
    "sg:phone":"+41 71 983 15 67",
    "sg:postcode":"9606",
    "sg:province":"St. Gallen",
    "wof:name":"Wohlgensinger",
    "wof:placetype":"venue"
},
  "geometry": {"coordinates":[9.0710268021,47.3598823547],"type":"Point"}
}