{
  "type": "Feature",
  "properties": {
    "iso:country":"CH",
    "sg:address":"B\u00e4lstrasse 37",
    "sg:city":"H\u00fcntwangen",
    "sg:orig_category":"Sonstiger Grosshandel",
    "sg:phone":"+41 22 733 50 20",
    "sg:postcode":"8194",
    "sg:province":"Z\u00fcrich",
    "wof:name":"Omnipex Sa",
    "wof:placetype":"venue"
},
  "geometry": {"coordinates":[6.137966156,46.2188873291],"type":"Point"}
}