{
  "type": "Feature",
  "properties": {
    "iso:country":"CH",
    "sg:address":"Claridenstrasse 43",
    "sg:city":"Z\u00fcrich",
    "sg:orig_category":"Detailhandel mit Bekleidung Detailhandel mit Damenbekleidung",
    "sg:phone":"+41 71 744 59 83",
    "sg:postcode":"8002",
    "sg:province":"Z\u00fcrich",
    "wof:name":"Pelz-& Ledershop Boutique Larissa N.bouloussis",
    "wof:placetype":"venue"
},
  "geometry": {"coordinates":[9.63602,47.453518],"type":"Point"}
}