{
  "type": "Feature",
  "properties": {
    "iso:country":"CH",
    "sg:address":"Heidb\u00fchl 470",
    "sg:city":"Eggiwil",
    "sg:orig_category":"Detailhandel mit Milcherzeugnissen U Eiern Verarbeitung von Milch",
    "sg:phone":"+41 34 491 17 54",
    "sg:postcode":"3537",
    "sg:province":"Bern",
    "wof:name":"Markus Leuenberger K\u00e4serei Dorf",
    "wof:placetype":"venue"
},
  "geometry": {"coordinates":[7.8006391525,46.8722114563],"type":"Point"}
}