{
  "type": "Feature",
  "properties": {
    "iso:country":"CH",
    "sg:address":"Herrenweg 7",
    "sg:city":"Allschwil",
    "sg:orig_category":"Grosshandel mit Nahrungsmitteln, Getr\u00e4nken U Tabakwaren ohne ausgepr\u00e4gten Schwerpunkt",
    "sg:phone":"+41 61 302 03 86",
    "sg:postcode":"4123",
    "sg:province":"Basel-Landschaft",
    "wof:name":"Bioparadies Gmbh Grosshandel Mit Bioprodukten",
    "wof:placetype":"venue"
},
  "geometry": {"coordinates":[7.5562000275,47.5452804565],"type":"Point"}
}