{
  "type": "Feature",
  "properties": {
    "iso:country":"CH",
    "sg:address":"Untere Grabenstrasse 14 4800 Zofingen. Postfach 1110",
    "sg:city":"Zofingen",
    "sg:orig_category":"Detailhandel mit Brillen U anderen Sehhilfen Fachdetailhandel in Verkaufsr\u00e4umen",
    "sg:phone":"+41 62 751 33 19",
    "sg:postcode":"4800",
    "sg:province":"Aargau",
    "wof:name":"G\u00fcnthert Optik Ag",
    "wof:placetype":"venue"
},
  "geometry": {"coordinates":[7.942859,47.289875],"type":"Point"}
}