{
  "type": "Feature",
  "properties": {
    "iso:country":"CH",
    "sg:address":"Viktoriastrasse 25",
    "sg:city":"Brig",
    "sg:orig_category":"Unclassifiable Establishments",
    "sg:postcode":"3900",
    "sg:province":"Valais",
    "wof:name":"Dental-labor Romeo Bircher",
    "wof:placetype":"venue"
},
  "geometry": {"coordinates":[7.9855289459,46.3186454773],"type":"Point"}
}