{
  "type": "Feature",
  "properties": {
    "iso:country":"CH",
    "sg:address":"Rue Du Jura 33",
    "sg:city":"Porrentruy",
    "sg:classifiers":[
        {
            "category":"Insurance",
            "subcategory":"Insurance Agent",
            "type":"Services"
        }
    ],
    "sg:phone":"+41 32 466 81 82",
    "sg:postcode":"2900",
    "sg:province":"Jura",
    "sg:tags":[
        "versicherungsagenturen",
        "-broker"
    ],
    "wof:name":"B\u00e2loise Assurances Agence",
    "wof:placetype":"venue"
},
  "geometry": {"coordinates":[7.0792531967,47.4201889038],"type":"Point"}
}