{
  "type": "Feature",
  "properties": {
    "iso:country":"CH",
    "sg:address":"Hansmatt 32 6370 Stans. Postfach",
    "sg:city":"Stans",
    "sg:orig_category":"Markt U Meinungsforschung Unternehmensberatung",
    "sg:phone":"+41 41 661 08 60",
    "sg:postcode":"6371",
    "sg:province":"Nidwalden",
    "wof:name":"Zumstein Peter Marketing Und Unternehmensberatung",
    "wof:placetype":"venue"
},
  "geometry": {"coordinates":[8.2500658035,46.8991394043],"type":"Point"}
}