{
  "type": "Feature",
  "properties": {
    "iso:country":"CH",
    "sg:address":"B\u00fctz 2",
    "sg:city":"Gams",
    "sg:orig_category":"Softwareentwicklung U beratung",
    "sg:postcode":"9473",
    "sg:province":"St. Gallen",
    "wof:name":"Sch\u00f6nenberger Informatik",
    "wof:placetype":"venue"
},
  "geometry": {"coordinates":[9.4407997131,47.2006492615],"type":"Point"}
}