{
  "type": "Feature",
  "properties": {
    "iso:country":"CH",
    "sg:address":"Riedhofstrasse 45 8408 Winterthur. Postfach 288",
    "sg:city":"Winterthur",
    "sg:orig_category":"Versicherungen Generalagenturen",
    "sg:phone":"+41 52 222 00 25",
    "sg:postcode":"8408",
    "sg:province":"Z\u00fcrich",
    "wof:name":"Winterthur Versicherungen Generalagentur Winterthur-west",
    "wof:placetype":"venue"
},
  "geometry": {"coordinates":[8.6950769424,47.5193557739],"type":"Point"}
}