{
  "type": "Feature",
  "properties": {
    "iso:country":"CH",
    "sg:address":"Hauserstrasse 65",
    "sg:city":"Windisch",
    "sg:orig_category":"Saunas, Solarien, Fitnesszentren U \u00e4hnliches",
    "sg:phone":"+41 56 442 31 30",
    "sg:postcode":"5210",
    "sg:province":"Aargau",
    "wof:name":"Fitnesscenter Windisch Humbel D.",
    "wof:placetype":"venue"
},
  "geometry": {"coordinates":[8.2113218307,47.4680900574],"type":"Point"}
}