{
  "type": "Feature",
  "properties": {
    "iso:country":"CH",
    "sg:address":"R\u00f6merstrasse 169",
    "sg:city":"Winterthur",
    "sg:orig_category":"Detailhandel mit Fleisch U Fleischwaren",
    "sg:phone":"+41 52 242 12 52",
    "sg:postcode":"8404",
    "sg:province":"Z\u00fcrich",
    "wof:name":"Werner Baumann Oberi-metzg",
    "wof:placetype":"venue"
},
  "geometry": {"coordinates":[8.7548027039,47.5074920654],"type":"Point"}
}