{
  "type": "Feature",
  "properties": {
    "addr:full":"Glasacker 18 Dulliken Solothurn 4657",
    "addr:housenumber":"18",
    "addr:postcode":"4657",
    "addr:street":"Glasacker",
    "iso:country":"CH",
    "sg:address":"Glasacker 18",
    "sg:city":"Dulliken",
    "sg:orig_category":"Architektur U Ingenieurb\u00fcros Architekturb\u00fcros",
    "sg:phone":"+41 62 295 54 45",
    "sg:postcode":"4657",
    "sg:province":"Solothurn",
    "wof:name":"Sch\u00e4rer Andr\u00e9 Architekt.",
    "wof:placetype":"venue"
},
  "geometry": {"coordinates":[7.941016,47.351833],"type":"Point"}
}