{
  "type": "Feature",
  "properties": {
    "addr:full":"Wydenplatz Frick 5262",
    "addr:postcode":"5262",
    "addr:street":"Wydenplatz",
    "iso:country":"CH",
    "sg:address":"Wydenplatz",
    "sg:city":"Frick",
    "sg:classifiers":[
        {
            "category":"Banks & Credit Unions",
            "subcategory":"Bank",
            "type":"Services"
        }
    ],
    "sg:phone":"+41 4164613524",
    "sg:postcode":"5262",
    "wof:name":"Aargauische Kantonalbank, Branch Frick",
    "wof:placetype":"venue"
},
  "geometry": {"coordinates":[8.022143,47.506824],"type":"Point"}
}