{
  "type": "Feature",
  "properties": {
    "iso:country":"CH",
    "sg:address":"Kirchplatz 3 9425 Thal. Postfach 160",
    "sg:city":"Thal",
    "sg:orig_category":"Detailhandel mit Brot, Back U S\u00fcsswaren",
    "sg:phone":"+41 71 888 16 24",
    "sg:postcode":"9425",
    "sg:province":"St. Gallen",
    "wof:name":"Karl Lutz Sch\u00e4flibeck & Konditorei",
    "wof:placetype":"venue"
},
  "geometry": {"coordinates":[9.568933,47.464497],"type":"Point"}
}