{
  "type": "Feature",
  "properties": {
    "iso:country":"CH",
    "sg:address":"Bielstrasse 8 4500 Solothurn. Postfach",
    "sg:city":"Solothurn",
    "sg:orig_category":"Interessenvertretungen",
    "sg:postcode":"4500",
    "sg:province":"Solothurn",
    "wof:name":"Stiftung Conchita M. Hartmann",
    "wof:placetype":"venue"
},
  "geometry": {"coordinates":[7.1084527969,46.9252319336],"type":"Point"}
}