{
  "type": "Feature",
  "properties": {
    "iso:country":"CH",
    "sg:address":"1837",
    "sg:city":"Ch\u00e2teau-d'oex",
    "sg:orig_category":"Abwasserreinigung Wasserversorgung",
    "sg:postcode":"1837",
    "wof:name":"Service Des Eaux De La Commune De Ch\u00e2teau-d'oex",
    "wof:placetype":"venue"
},
  "geometry": {"coordinates":[0.68584,45.246052],"type":"Point"}
}