{
  "type": "Feature",
  "properties": {
    "iso:country":"CH",
    "sg:address":"B\u00fcnzerstrasse 3 5626 Hermetschwil-staff. Postfach",
    "sg:city":"Hermetschwil-staff",
    "sg:orig_category":"Handels-H\u00e4user U Gesellschaften",
    "sg:postcode":"5626",
    "sg:province":"Aargau",
    "wof:name":"Mct R\u00fcttimann",
    "wof:placetype":"venue"
},
  "geometry": {"coordinates":[8.3406267166,47.3303642273],"type":"Point"}
}