{
  "type": "Feature",
  "properties": {
    "iso:country":"CH",
    "sg:address":"Bernstr. 253",
    "sg:city":"Berikon",
    "sg:orig_category":"Herstellung von Elektromotoren, Generatoren U Transformatoren",
    "sg:phone":"+41 41 419 01 11",
    "sg:postcode":"8965",
    "sg:province":"Aargau",
    "wof:name":"Elektroplan Ag",
    "wof:placetype":"venue"
},
  "geometry": {"coordinates":[8.3055267334,47.0526390076],"type":"Point"}
}