{
  "type": "Feature",
  "properties": {
    "iso:country":"CH",
    "sg:address":"Ammerswilerstrasse 34",
    "sg:city":"Lenzburg",
    "sg:orig_category":"Fachdetailhandel in Verkaufsr\u00e4umen",
    "sg:phone":"+41 32 751 17 69",
    "sg:postcode":"5600",
    "sg:province":"Aargau",
    "wof:name":"M\u00e9rillat & Cie",
    "wof:placetype":"venue"
},
  "geometry": {"coordinates":[7.0914731026,47.0622749329],"type":"Point"}
}