{
  "type": "Feature",
  "properties": {
    "iso:country":"CH",
    "sg:address":"Bahnhofstrasse 5",
    "sg:city":"Engelberg",
    "sg:orig_category":"Unclassifiable Establishments",
    "sg:postcode":"6390",
    "sg:province":"Obwalden",
    "wof:name":"Elektro Bussmann + Partner Gmbh",
    "wof:placetype":"venue"
},
  "geometry": {"coordinates":[8.4025907516,46.8185768127],"type":"Point"}
}