{
  "type": "Feature",
  "properties": {
    "iso:country":"CH",
    "sg:address":"Chemin De La Ranch\u00e9e 2",
    "sg:city":"Confignon",
    "sg:orig_category":"Einbau von Schreinerwaren Malerei",
    "sg:postcode":"1232",
    "sg:province":"Gen\u00e8ve",
    "wof:name":"Esquisse S\u00e0rl D\u00e9coration Et Peinture",
    "wof:placetype":"venue"
},
  "geometry": {"coordinates":[6.0767798424,46.1725578308],"type":"Point"}
}