{
  "type": "Feature",
  "properties": {
    "addr:full":"Chasseralstrasse 6 Walperswil Bern 3272",
    "addr:housenumber":"6",
    "addr:postcode":"3272",
    "addr:street":"Chasseralstrasse",
    "iso:country":"CH",
    "sg:address":"Chasseralstrasse 6",
    "sg:city":"Walperswil",
    "sg:orig_category":"Architektur U Ingenieurb\u00fcros Architekturb\u00fcros",
    "sg:phone":"+41 79 251 12 30",
    "sg:postcode":"3272",
    "sg:province":"Bern",
    "wof:name":"Mathys Architektur-planung-immobilien Gmbh",
    "wof:placetype":"venue"
},
  "geometry": {"coordinates":[7.21886,47.05957],"type":"Point"}
}