{
  "type": "Feature",
  "properties": {
    "iso:country":"CH",
    "sg:address":"Kyburgstrasse 27",
    "sg:city":"Z\u00fcrich",
    "sg:orig_category":"Sonstiger Grosshandel",
    "sg:postcode":"8037",
    "sg:province":"Z\u00fcrich",
    "wof:name":"Steiner Ag K\u00fcssnacht",
    "wof:placetype":"venue"
},
  "geometry": {"coordinates":[8.4419078827,47.0767593384],"type":"Point"}
}