{
  "type": "Feature",
  "properties": {
    "iso:country":"CH",
    "sg:address":"Route De La Fenette 8",
    "sg:city":"Payerne",
    "sg:orig_category":"Elektroinstallation",
    "sg:postcode":"1530",
    "sg:province":"Vaud",
    "wof:name":"Coucet A. Sa, Succursale De Payerne.",
    "wof:placetype":"venue"
},
  "geometry": {"coordinates":[6.9482250214,46.8199310303],"type":"Point"}
}