{
  "type": "Feature",
  "properties": {
    "iso:country":"CH",
    "sg:address":"General Guisan-quai 40 8002 Z\u00fcrich. Postfach",
    "sg:city":"Z\u00fcrich",
    "sg:orig_category":"Sonstiges Versicherungsgewerbe",
    "sg:postcode":"8001",
    "sg:province":"Z\u00fcrich",
    "wof:name":"Taggeldkasse Bildende K\u00fcnstlerinnen Taggeldversicherung Zugunsten Bildender K\u00fcnstlerinnen Usw",
    "wof:placetype":"venue"
},
  "geometry": {"coordinates":[8.534781456,47.3630027771],"type":"Point"}
}