{
  "type": "Feature",
  "properties": {
    "iso:country":"CH",
    "sg:address":"7214",
    "sg:city":"Gr\u00fcsch",
    "sg:orig_category":"Eisbahnen and Eissportpl\u00e4tze",
    "sg:phone":"+41 81 838 50 67",
    "sg:postcode":"7214",
    "sg:province":"Graubunden",
    "wof:name":"Eislaufplatz Muot-marias",
    "wof:placetype":"venue"
},
  "geometry": {"coordinates":[9.764169693,46.4287605286],"type":"Point"}
}