{
  "type": "Feature",
  "properties": {
    "iso:country":"CH",
    "sg:address":"Hauptstr. 150",
    "sg:city":"Muntelier",
    "sg:classifiers":[
        {
            "category":"Shopping",
            "subcategory":"Computers & Home Electronics",
            "type":"Retail Goods"
        }
    ],
    "sg:phone":"+41 26 678 74 74",
    "sg:postcode":"3286",
    "sg:province":"Fribourg",
    "sg:tags":[
        "electronic",
        "electrical",
        "equipment"
    ],
    "wof:name":"Selecta Ag",
    "wof:placetype":"venue"
},
  "geometry": {"coordinates":[7.1367878914,46.9411697388],"type":"Point"}
}