{
  "type": "Feature",
  "properties": {
    "iso:country":"CH",
    "sg:address":"6595",
    "sg:city":"Riazzino",
    "sg:orig_category":"Alarm- and Sicherheitsanlagen Grosshandel Installation von Heizungs, L\u00fcftungs U Klimaanlagen",
    "sg:postcode":"6595",
    "sg:province":"Ticino",
    "wof:name":"Nisa Prodotti Sa",
    "wof:placetype":"venue"
},
  "geometry": {"coordinates":[8.8976,46.174561],"type":"Point"}
}