{
  "type": "Feature",
  "properties": {
    "iso:country":"CH",
    "sg:address":"Les Champs Fallats",
    "sg:city":"St-ursanne",
    "sg:orig_category":"Laboratorien biologisch Laboratorien chemisch",
    "sg:phone":"+41 22 310 45 34",
    "sg:postcode":"2882",
    "sg:province":"Jura",
    "wof:name":"Laboratoire Dr.e. Homberger Sa Produits Pharmaceutiques",
    "wof:placetype":"venue"
},
  "geometry": {"coordinates":[6.1491928101,46.200717926],"type":"Point"}
}