{
  "type": "Feature",
  "properties": {
    "iso:country":"CH",
    "sg:address":"Rue De La Cure 5",
    "sg:city":"Cortaillod",
    "sg:orig_category":"Verwertung von Milch",
    "sg:phone":"+41 26 912 78 77",
    "sg:postcode":"2016",
    "sg:province":"Neuch\u00e2tel",
    "wof:name":"Association De La Laiterie De Cortaillod.",
    "wof:placetype":"venue"
},
  "geometry": {"coordinates":[6.84354496,46.9410552979],"type":"Point"}
}