{
  "type": "Feature",
  "properties": {
    "iso:country":"CH",
    "sg:address":"L'essert",
    "sg:city":"Courtion",
    "sg:orig_category":"Handelsvermittlung U Grosshandel mit Automobilen Handelsvermittlung U Grosshandel mit Automobilteile",
    "sg:phone":"+41 79 230 69 67",
    "sg:postcode":"1721",
    "sg:province":"Fribourg",
    "wof:name":"Inter Car Technik Gmbh",
    "wof:placetype":"venue"
},
  "geometry": {"coordinates":[7.0684499741,46.8571395874],"type":"Point"}
}