{
  "type": "Feature",
  "properties": {
    "iso:country":"CH",
    "sg:address":"Mal\u00e8 Via G.b. 10 6600 Locarno. Postfach",
    "sg:city":"Locarno",
    "sg:orig_category":"Unclassifiable Establishments",
    "sg:postcode":"6600",
    "sg:province":"Ticino",
    "wof:name":"Helios Di Casola Anna-rita Centro Estetico, Terapie Naturali Ecc",
    "wof:placetype":"venue"
},
  "geometry": {"coordinates":[8.8003940582,46.1705741882],"type":"Point"}
}