{
  "type": "Feature",
  "properties": {
    "iso:country":"CH",
    "sg:address":"Bahnhofstrasse 1",
    "sg:city":"Schwerzenbach",
    "sg:orig_category":"Grosshandel mit Nahrungsmitteln, Getr\u00e4nken U Tabakwaren ohne ausgepr\u00e4gten Schwerpunkt",
    "sg:phone":"+41 18252878",
    "sg:postcode":"8603",
    "sg:province":"Z\u00fcrich",
    "wof:name":"Spar-markt, Grob W.",
    "wof:placetype":"venue"
},
  "geometry": {"coordinates":[8.6524963379,47.3817825317],"type":"Point"}
}