{
  "type": "Feature",
  "properties": {
    "iso:country":"CH",
    "sg:address":"Dorfplatz 4",
    "sg:city":"Glis",
    "sg:orig_category":"B\u00e4ckereien Konditoreien",
    "sg:phone":"+41 27 923 14 18",
    "sg:postcode":"3902",
    "sg:province":"Valais",
    "wof:name":"Studer Ag B\u00e4ckerei-konditorei",
    "wof:placetype":"venue"
},
  "geometry": {"coordinates":[7.977852,46.311066],"type":"Point"}
}