{
  "type": "Feature",
  "properties": {
    "iso:country":"CH",
    "sg:address":"Altmarktstrasse 96 4410 Liestal. Postfach",
    "sg:city":"Liestal",
    "sg:orig_category":"Arbeitnehmerverb\u00e4nde",
    "sg:postcode":"4410",
    "sg:province":"Basel-Landschaft",
    "wof:name":"Arbeitgeber Nordwestschweiz Gesamt-koordination Der Arbeitgeberpolitik In Der Nordwestschweiz Zugunsten Der Kmu Usw",
    "wof:placetype":"venue"
},
  "geometry": {"coordinates":[7.747329,47.47731],"type":"Point"}
}