{
  "type": "Feature",
  "properties": {
    "addr:full":"Schwesterboden Romoos Luzern 6113",
    "addr:postcode":"6113",
    "iso:country":"CH",
    "sg:address":"Schwesterboden",
    "sg:city":"Romoos",
    "sg:orig_category":"Allgemeiner Hoch U Tiefbau Allgemeiner Hochbau",
    "sg:phone":"+41 41 480 13 15",
    "sg:postcode":"6113",
    "sg:province":"Luzern",
    "wof:name":"Roos Bau Ag",
    "wof:placetype":"venue"
},
  "geometry": {"coordinates":[8.004121,46.996441],"type":"Point"}
}