{
  "type": "Feature",
  "properties": {
    "iso:country":"CH",
    "sg:address":"Chalet Schmadri 3825 M\u00fcrren. Postfach",
    "sg:city":"M\u00fcrren",
    "sg:orig_category":"Markt U Meinungsforschung",
    "sg:phone":"+41 19182513",
    "sg:postcode":"3825",
    "sg:province":"Bern",
    "wof:name":"Hyperknowledge Management Services Ag",
    "wof:placetype":"venue"
},
  "geometry": {"coordinates":[7.8951401711,46.560218811],"type":"Point"}
}