{
  "type": "Feature",
  "properties": {
    "iso:country":"CH",
    "sg:address":"Zugerstrasse 16",
    "sg:city":"Walchwil",
    "sg:orig_category":"Sanit\u00e4r, Heizungs U L\u00fcftungsinstallation Schlossereien",
    "sg:phone":"+41 41 758 11 27",
    "sg:postcode":"6318",
    "sg:province":"Zug",
    "wof:name":"H\u00fcrlimann Tobias",
    "wof:placetype":"venue"
},
  "geometry": {"coordinates":[8.5109348297,47.1021995544],"type":"Point"}
}