{
  "type": "Feature",
  "properties": {
    "iso:country":"CH",
    "sg:address":"Z\u00fcrcherstrasse 282",
    "sg:city":"Frauenfeld",
    "sg:orig_category":"Detailhandel mit Textilien Verlegen von Fussboden",
    "sg:phone":"+41 52 721 27 50",
    "sg:postcode":"8500",
    "sg:province":"Thurgau",
    "wof:name":"Bardellini Albin Ag",
    "wof:placetype":"venue"
},
  "geometry": {"coordinates":[8.9070968628,47.5624961853],"type":"Point"}
}