{
  "type": "Feature",
  "properties": {
    "iso:country":"CH",
    "sg:address":"Ch. De Buchaux 34 2022 Bevaix Case Postale",
    "sg:city":"Bevaix",
    "sg:orig_category":"Satzherstellung U Reproduktion",
    "sg:postcode":"2022",
    "sg:province":"Neuch\u00e2tel",
    "wof:name":"Manaplan Del\u00e9mont Ronald Et Petitpierre Fran\u00e7ois Informatique De Gestion",
    "wof:placetype":"venue"
},
  "geometry": {"coordinates":[6.8216471672,46.9339752197],"type":"Point"}
}