{
  "type": "Feature",
  "properties": {
    "iso:country":"CH",
    "sg:address":"Chemin De La Grand-cour 27",
    "sg:city":"Troinex",
    "sg:orig_category":"Sonstige pers\u00f6nliche Dienstleistungen",
    "sg:postcode":"1256",
    "sg:province":"Gen\u00e8ve",
    "wof:name":"Suraksha Pax Sa.",
    "wof:placetype":"venue"
},
  "geometry": {"coordinates":[6.1480932236,46.1595993042],"type":"Point"}
}