{
  "type": "Feature",
  "properties": {
    "iso:country":"CH",
    "sg:address":"Bas Du Ross\u00e9 13",
    "sg:city":"Etoy",
    "sg:orig_category":"Sonstige Aktivit\u00e4ten der nicht-\u00e4rztlichen Medizinalberufe",
    "sg:phone":"+41 21 807 42 84",
    "sg:postcode":"1163",
    "sg:province":"Vaud",
    "wof:name":"Doris Radeck Naturopathe & Massages",
    "wof:placetype":"venue"
},
  "geometry": {"coordinates":[6.4176821709,46.4837913513],"type":"Point"}
}