{
  "type": "Feature",
  "properties": {
    "addr:full":"Avenue Robert 49 Fontainemelon Neuch\u00e2tel 2052",
    "addr:housenumber":"49",
    "addr:postcode":"2052",
    "addr:street":"Avenue Robert;Neucha\u0302Tel",
    "iso:country":"CH",
    "sg:address":"Avenue Robert 49",
    "sg:city":"Fontainemelon",
    "sg:orig_category":"Autogaragen Handel mit Automobilteilen U Zubeh\u00f6r",
    "sg:postcode":"2052",
    "sg:province":"Neuch\u00e2tel",
    "wof:name":"Auto Abegglen Ag",
    "wof:placetype":"venue"
},
  "geometry": {"coordinates":[7.820771,47.248474],"type":"Point"}
}