{
  "type": "Feature",
  "properties": {
    "iso:country":"CH",
    "sg:address":"Centralstrasse 21",
    "sg:city":"Grenchen",
    "sg:orig_category":"RESTAURANTS: TEA-ROOMS",
    "sg:phone":"+41 32 652 10 24",
    "sg:postcode":"2540",
    "sg:province":"Solothurn",
    "wof:name":"Restaurant Schwingerst\u00fcbli",
    "wof:placetype":"venue"
},
  "geometry": {"coordinates":[7.3953881264,47.1937255859],"type":"Point"}
}