{
  "type": "Feature",
  "properties": {
    "addr:full":"Halenweg 5 Hinterkappelen Bern 3032",
    "addr:housenumber":"5",
    "addr:postcode":"3032",
    "addr:street":"Halenweg",
    "iso:country":"CH",
    "sg:address":"Halenweg 5",
    "sg:city":"Hinterkappelen",
    "sg:orig_category":"Bauschreinerei Herstellung von M\u00f6beln verschiedener Art",
    "sg:phone":"+41 31 901 12 44",
    "sg:postcode":"3032",
    "sg:province":"Bern",
    "wof:name":"Urs Sahli M\u00f6belschreinerei",
    "wof:placetype":"venue"
},
  "geometry": {"coordinates":[7.379984,46.96629],"type":"Point"}
}