{
  "type": "Feature",
  "properties": {
    "iso:country":"CH",
    "sg:address":"Zuchwilerstrasse 71",
    "sg:city":"Solothurn",
    "sg:orig_category":"Interessenvertretungen",
    "sg:postcode":"4500",
    "sg:province":"Solothurn",
    "wof:name":"Kollektiv F\u00fcr M\u00f6bel",
    "wof:placetype":"venue"
},
  "geometry": {"coordinates":[7.5454897881,47.2027397156],"type":"Point"}
}