{
  "type": "Feature",
  "properties": {
    "iso:country":"CH",
    "sg:address":"Kirchstrasse 23 9400 Rorschach. Postfach",
    "sg:city":"Rorschach",
    "sg:classifiers":[
        {
            "category":"Personal",
            "subcategory":"Nail Salon",
            "type":"Services"
        }
    ],
    "sg:phone":"+41 71 845 44 54",
    "sg:postcode":"9401",
    "sg:province":"St. Gallen",
    "sg:tags":[
        "manicure"
    ],
    "wof:name":"Ursula Erni Fingernagel-st\u00fcbli Uschy",
    "wof:placetype":"venue"
},
  "geometry": {"coordinates":[9.492978096,47.4769821167],"type":"Point"}
}