{
  "type": "Feature",
  "properties": {
    "iso:country":"CH",
    "sg:address":"Chemin Des Sports",
    "sg:city":"Granges-marnand",
    "sg:classifiers":[
        {
            "category":"Sports & Exercise",
            "subcategory":"Tennis Court",
            "type":"Entertainment"
        }
    ],
    "sg:phone":"+41 26 668 22 98",
    "sg:postcode":"1523",
    "sg:province":"Vaud",
    "sg:tags":[
        "squash-centers",
        "hallen",
        "tennis-"
    ],
    "wof:name":"Centre De Tennis Les Esserts",
    "wof:placetype":"venue"
},
  "geometry": {"coordinates":[6.8925971985,46.7622451782],"type":"Point"}
}