{
  "type": "Feature",
  "properties": {
    "iso:country":"CH",
    "sg:address":"Rue Fr\u00e9d\u00e9ric-soguel 20 2053 Cernier. Postfach",
    "sg:city":"Cernier",
    "sg:orig_category":"Fachdetailhandel in Verkaufsr\u00e4umen",
    "sg:postcode":"2053",
    "sg:province":"Neuch\u00e2tel",
    "wof:name":"Horlowatch S\u00e0rl",
    "wof:placetype":"venue"
},
  "geometry": {"coordinates":[6.8264021873,47.1004753113],"type":"Point"}
}