{
  "type": "Feature",
  "properties": {
    "iso:country":"CH",
    "sg:address":"Knonauerstrasse 1",
    "sg:city":"Cham",
    "sg:orig_category":"Detailhandel mit Radio U Fernsehger\u00e4ten Detailhandel mit elektrischen Haushalts-,Radio U Fernsehger\u00e4",
    "sg:phone":"+41 41 780 16 68",
    "sg:postcode":"6330",
    "sg:province":"Zug",
    "wof:name":"Steiger Urs, Fernsehen Und Video.",
    "wof:placetype":"venue"
},
  "geometry": {"coordinates":[8.4604377747,47.1816635132],"type":"Point"}
}