{
  "type": "Feature",
  "properties": {
    "iso:country":"CH",
    "sg:address":"Furkastrasse 25 3900 Brig. Postfach",
    "sg:city":"Brig",
    "sg:orig_category":"Advokaturb\u00fcros",
    "sg:phone":"+41 27 924 11 33",
    "sg:postcode":"3900",
    "sg:province":"Valais",
    "wof:name":"Amherd Carlen Truffer Advokatur & Notariat",
    "wof:placetype":"venue"
},
  "geometry": {"coordinates":[7.985496,46.318291],"type":"Point"}
}