{
  "type": "Feature",
  "properties": {
    "iso:country":"CH",
    "sg:address":"Pustget",
    "sg:city":"Trun",
    "sg:orig_category":"Bauschreinerei Herstellung von Konstruktionsteilen, Fertigbauteilen U Ausbauelementen aus Holz",
    "sg:phone":"+41 81 943 18 95",
    "sg:postcode":"7166",
    "sg:province":"Graubunden",
    "wof:name":"Cagienard Sa",
    "wof:placetype":"venue"
},
  "geometry": {"coordinates":[8.987692,46.740993],"type":"Point"}
}