{
  "type": "Feature",
  "properties": {
    "iso:country":"CH",
    "sg:address":"Chemin De Primerose 2",
    "sg:city":"Lausanne",
    "sg:orig_category":"Interessenvertretungen U sonstige Vereinigungen",
    "sg:phone":"+41 21 612 66 66",
    "sg:postcode":"1007",
    "sg:province":"Vaud",
    "wof:name":"International Skating Union",
    "wof:placetype":"venue"
},
  "geometry": {"coordinates":[6.6167998314,46.5147476196],"type":"Point"}
}