{
  "type": "Feature",
  "properties": {
    "iso:country":"CH",
    "sg:address":"B\u00fcmplizstrasse 101",
    "sg:city":"Bern",
    "sg:orig_category":"W\u00e4schereien",
    "sg:phone":"+41 21 963 27 71",
    "sg:postcode":"3018",
    "sg:province":"Bern",
    "wof:name":"Madeleine Egger Blanchisserie",
    "wof:placetype":"venue"
},
  "geometry": {"coordinates":[6.929874897,46.4347610474],"type":"Point"}
}