{
  "type": "Feature",
  "properties": {
    "iso:country":"CH",
    "sg:address":"Seestrasse 15",
    "sg:city":"Ipsach",
    "sg:orig_category":"Detailhandel mit elektrischen Haushalts-,Radio U Fernsehger\u00e4ten sowie Musikinstrumenten",
    "sg:phone":"+41 32 331 89 22",
    "sg:postcode":"2563",
    "sg:province":"Bern",
    "wof:name":"Norman David, Audio Consulting",
    "wof:placetype":"venue"
},
  "geometry": {"coordinates":[7.232380867,47.1158256531],"type":"Point"}
}