{
  "type": "Feature",
  "properties": {
    "iso:country":"CH",
    "sg:address":"Engelbergstrasse 6",
    "sg:city":"Stans",
    "sg:orig_category":"Detailhandel mit Brot, Back U S\u00fcsswaren",
    "sg:phone":"+41 41 610 14 64",
    "sg:postcode":"6370",
    "sg:province":"Nidwalden",
    "wof:name":"Kobi & Ursula Barmettler Kreuzb\u00e4ckerei",
    "wof:placetype":"venue"
},
  "geometry": {"coordinates":[8.367201,46.956779],"type":"Point"}
}