{
  "type": "Feature",
  "properties": {
    "iso:country":"CH",
    "sg:address":"Bachstrasse 7",
    "sg:city":"Kloten",
    "sg:orig_category":"Detailhandel mit Geschenkartikeln U Souvenirs",
    "sg:phone":"+41 18132622",
    "sg:postcode":"8302",
    "sg:province":"Z\u00fcrich",
    "wof:name":"C. Zerbini Boutique Le Bouquet",
    "wof:placetype":"venue"
},
  "geometry": {"coordinates":[8.5817222595,47.4517822266],"type":"Point"}
}