{
  "type": "Feature",
  "properties": {
    "iso:country":"CH",
    "sg:address":"Gaissbergstrasse 4",
    "sg:city":"Kreuzlingen",
    "sg:orig_category":"Webdesign",
    "sg:phone":"+41 71 672 29 51",
    "sg:postcode":"8280",
    "sg:province":"Thurgau",
    "wof:name":"Internetmedia Gmbh",
    "wof:placetype":"venue"
},
  "geometry": {"coordinates":[9.1774606705,47.6452713013],"type":"Point"}
}