{
  "type": "Feature",
  "properties": {
    "addr:full":"Alte Strasse 5 Oftringen Aargau 4665",
    "addr:housenumber":"5",
    "addr:postcode":"4665",
    "addr:street":"Alte Strasse",
    "iso:country":"CH",
    "sg:address":"Alte Strasse 5",
    "sg:city":"Oftringen",
    "sg:orig_category":"Detailhandel mit Bekleidung Versandhandel",
    "sg:phone":"+41 62 797 60 69",
    "sg:postcode":"4665",
    "sg:province":"Aargau",
    "wof:name":"Fritz Hallwyler Berufskleiderversand",
    "wof:placetype":"venue"
},
  "geometry": {"coordinates":[7.912116,47.309231],"type":"Point"}
}