{
  "type": "Feature",
  "properties": {
    "iso:country":"CH",
    "sg:address":"Hintere Vorstadt 11",
    "sg:city":"Aarau",
    "sg:orig_category":"Unclassifiable Establishments",
    "sg:postcode":"5000",
    "sg:province":"Aargau",
    "wof:name":"Prs Ag",
    "wof:placetype":"venue"
},
  "geometry": {"coordinates":[8.0456590652,47.3914299011],"type":"Point"}
}