{
  "type": "Feature",
  "properties": {
    "iso:country":"CH",
    "sg:address":"Binningerstrasse 141",
    "sg:city":"Allschwil",
    "sg:orig_category":"Detailhandel mit Metallwaren, Anstrichmitteln, Glaswaren, Bau U Heimwerkerbedarf",
    "sg:postcode":"4123",
    "sg:province":"Basel-Landschaft",
    "wof:name":"Profi-team Fachmarkt Gmbh",
    "wof:placetype":"venue"
},
  "geometry": {"coordinates":[7.551928997,47.5471954346],"type":"Point"}
}