{
  "type": "Feature",
  "properties": {
    "iso:country":"CH",
    "sg:address":"Chesa Muglin",
    "sg:city":"Bever",
    "sg:orig_category":"Detailhandel mit Radio U Fernsehger\u00e4ten Elektroinstallation",
    "sg:phone":"+41 81 852 57 20",
    "sg:postcode":"7502",
    "sg:province":"Graubunden",
    "wof:name":"Koller Elektro Ag",
    "wof:placetype":"venue"
},
  "geometry": {"coordinates":[9.8891563416,46.5519447327],"type":"Point"}
}