{
  "type": "Feature",
  "properties": {
    "iso:country":"CH",
    "sg:address":"Alte Simplonstrasse 10 3900 Brig. Postfach 53",
    "sg:city":"Brig",
    "sg:orig_category":"RESTAURANTS: TEA-ROOMS",
    "sg:phone":"+41 27 924 56 03",
    "sg:postcode":"3900",
    "sg:province":"Valais",
    "wof:name":"Juon-zenh\u00e4usern Anni, Bistro Viva",
    "wof:placetype":"venue"
},
  "geometry": {"coordinates":[7.9889359474,46.316318512],"type":"Point"}
}