{
  "type": "Feature",
  "properties": {
    "iso:country":"CH",
    "sg:address":"Obermattweg 82",
    "sg:city":"H\u00e4felfingen",
    "sg:orig_category":"Architekturb\u00fcros",
    "sg:phone":"+41 17861595",
    "sg:postcode":"4445",
    "sg:province":"Basel-Landschaft",
    "wof:name":"Hanspeter Gr\u00fcninger Dipl. Arch. Eth/sia",
    "wof:placetype":"venue"
},
  "geometry": {"coordinates":[8.731391,47.204144],"type":"Point"}
}