{
  "type": "Feature",
  "properties": {
    "iso:country":"CH",
    "sg:address":"Buchstrasse 6 8112 Otelfingen. Postfach",
    "sg:city":"Otelfingen",
    "sg:orig_category":"Herstellung von sonstigen Metallwaren",
    "sg:phone":"+41 18846868",
    "sg:postcode":"8112",
    "sg:province":"Z\u00fcrich",
    "wof:name":"Halfen-mobatec Ag Handel U. Fabrikation Von Technischen Produkte Der Baubranche, Bes. Von Verankerungen Aus Metall Usw",
    "wof:placetype":"venue"
},
  "geometry": {"coordinates":[8.3990392685,47.4579391479],"type":"Point"}
}