{
  "type": "Feature",
  "properties": {
    "iso:country":"CH",
    "sg:address":"Rebberg 191",
    "sg:city":"Wohlenschwil",
    "sg:orig_category":"Wirtschaftspr\u00fcfung, Steuerberatung U Treuhand",
    "sg:phone":"+41 79 353 30 64",
    "sg:postcode":"5512",
    "sg:province":"Aargau",
    "wof:name":"Sci-treuhand Schibli Erika.",
    "wof:placetype":"venue"
},
  "geometry": {"coordinates":[8.2594003677,47.4262504578],"type":"Point"}
}