{
  "type": "Feature",
  "properties": {
    "iso:country":"CH",
    "sg:address":"Route Du Mandement 466",
    "sg:city":"Dardagny",
    "sg:orig_category":"Rebbau",
    "sg:phone":"+41 24 466 51 45",
    "sg:postcode":"1282",
    "wof:name":"Charly Blanc Viticulteur",
    "wof:placetype":"venue"
},
  "geometry": {"coordinates":[6.935790062,46.3439598083],"type":"Point"}
}