{
  "type": "Feature",
  "properties": {
    "iso:country":"CH",
    "sg:address":"Rue Des Coll\u00e8ges 1",
    "sg:city":"Corg\u00e9mont",
    "sg:orig_category":"Sportschulen Fern\u00f6stliche Kampfsportarten Sportvereine Judo and Karate",
    "sg:phone":"+41 32 489 23 03",
    "sg:postcode":"2606",
    "sg:province":"Bern",
    "wof:name":"Shotokan Kc Corgemont Halle De Spectacle",
    "wof:placetype":"venue"
},
  "geometry": {"coordinates":[7.1482028961,47.195766449],"type":"Point"}
}