{
  "type": "Feature",
  "properties": {
    "iso:country":"CH",
    "sg:address":"Weinbergstrasse 32",
    "sg:city":"Winterthur",
    "sg:orig_category":"Schulpflegen",
    "sg:phone":"+41 52 222 67 66",
    "sg:postcode":"8400",
    "sg:province":"Z\u00fcrich",
    "wof:name":"Schulpflege Veltheim",
    "wof:placetype":"venue"
},
  "geometry": {"coordinates":[8.7113037109,47.5101203918],"type":"Point"}
}