{
  "type": "Feature",
  "properties": {
    "iso:country":"CH",
    "sg:address":"Im Eichen 8268 Mannenbach-salenst. Postfach",
    "sg:city":"Fruthwilen",
    "sg:orig_category":"Fotografisches Gewerbe U fotografische Laboratorien",
    "sg:postcode":"8559",
    "wof:name":"Sport Und Werbe-photography Herdt Monica",
    "wof:placetype":"venue"
},
  "geometry": {"coordinates":[9.0550966263,47.6733970642],"type":"Point"}
}