{
  "type": "Feature",
  "properties": {
    "iso:country":"CH",
    "sg:address":"Bernstrasse 81",
    "sg:city":"Rothrist",
    "sg:orig_category":"Arztpraxen",
    "sg:phone":"+41 62 794 18 55",
    "sg:postcode":"4852",
    "sg:province":"Aargau",
    "wof:name":"Dr.med.rudolf G\u00fcttinger Arzt F.allgemeine Medizin Fmh",
    "wof:placetype":"venue"
},
  "geometry": {"coordinates":[7.894402,47.304688],"type":"Point"}
}