{
  "type": "Feature",
  "properties": {
    "iso:country":"CH",
    "sg:address":"Waldheimstrasse 37",
    "sg:city":"Zug",
    "sg:orig_category":"Innenarchitekturb\u00fcros",
    "sg:phone":"+41 41 760 71 70",
    "sg:postcode":"6300",
    "sg:province":"Zug",
    "wof:name":"Andreas Zwyssig Innenarchitektur Zwyssig",
    "wof:placetype":"venue"
},
  "geometry": {"coordinates":[8.5213985443,47.1591796875],"type":"Point"}
}