{
  "type": "Feature",
  "properties": {
    "iso:country":"CH",
    "sg:address":"Schwertstrasse 4",
    "sg:city":"Schaffhausen",
    "sg:orig_category":"Bijouterien",
    "sg:phone":"+41 21 845 50 22",
    "sg:postcode":"8200",
    "sg:province":"Schaffhausen",
    "wof:name":"C. Golay N. Niggeler Succr Bijouterie",
    "wof:placetype":"venue"
},
  "geometry": {"coordinates":[6.229968,46.607021],"type":"Point"}
}