{
  "type": "Feature",
  "properties": {
    "iso:country":"CH",
    "sg:address":"St.antons-gasse 4a 6300 Zug. Postfach",
    "sg:city":"Zug",
    "sg:orig_category":"Non-Classified Establishments",
    "sg:postcode":"6300",
    "sg:province":"Zug",
    "wof:name":"Tt Holding Gmbh Beteiligungen Usw",
    "wof:placetype":"venue"
},
  "geometry": {"coordinates":[8.5165901184,47.1672706604],"type":"Point"}
}