{
  "type": "Feature",
  "properties": {
    "iso:country":"CH",
    "sg:address":"1304",
    "sg:city":"Senarclens",
    "sg:orig_category":"Detailhandel mit Brot, Back U S\u00fcsswaren",
    "sg:phone":"+41 21 861 07 17",
    "sg:postcode":"1304",
    "sg:province":"Vaud",
    "wof:name":"Mercuri S.",
    "wof:placetype":"venue"
},
  "geometry": {"coordinates":[6.487557,46.600582],"type":"Point"}
}