{
  "type": "Feature",
  "properties": {
    "iso:country":"CH",
    "sg:address":"Bahnhofstrasse 4 8730 Uznach. Postfach 267",
    "sg:city":"Uznach",
    "sg:orig_category":"Kantonalbanken",
    "sg:phone":"+41 55 285 80 70",
    "sg:postcode":"8730",
    "sg:province":"St. Gallen",
    "wof:name":"St.galler Kantonalbank",
    "wof:placetype":"venue"
},
  "geometry": {"coordinates":[8.9825429916,47.2241287231],"type":"Point"}
}