{
  "type": "Feature",
  "properties": {
    "iso:country":"CH",
    "sg:address":"Stampfelistrasse 4",
    "sg:city":"Wolhusen",
    "sg:orig_category":"Sonstiger Grosshandel",
    "sg:phone":"+41 41 490 34 86",
    "sg:postcode":"6110",
    "sg:province":"Luzern",
    "wof:name":"Schnider",
    "wof:placetype":"venue"
},
  "geometry": {"coordinates":[8.0741062164,47.0612716675],"type":"Point"}
}