{
  "type": "Feature",
  "properties": {
    "iso:country":"CH",
    "sg:address":"8775",
    "sg:city":"Luchsingen",
    "sg:orig_category":"Verkehrs- and Tourismusb\u00fcros",
    "sg:phone":"+41 55 643 10 64",
    "sg:postcode":"8775",
    "sg:province":"Glarus",
    "wof:name":"Verkehrsverein Luchsingen- Betschwanden C/o Gemeindeverw.",
    "wof:placetype":"venue"
},
  "geometry": {"coordinates":[9.0372600555,46.967666626],"type":"Point"}
}