{
  "type": "Feature",
  "properties": {
    "iso:country":"CH",
    "sg:address":"Boulevard Du Th\u00e9\u00e2tre 12",
    "sg:city":"Gen\u00e8ve",
    "sg:classifiers":[
        {
            "category":"Restaurant",
            "type":"Food & Drink"
        }
    ],
    "sg:phone":"+41 22 328 00 95",
    "sg:postcode":"1204",
    "sg:province":"Gen\u00e8ve",
    "wof:name":"Caf\u00e9-restaurant Lyrique",
    "wof:placetype":"venue"
},
  "geometry": {"coordinates":[6.142206192,46.2013053894],"type":"Point"}
}