{
  "type": "Feature",
  "properties": {
    "iso:country":"CH",
    "sg:address":"B\u00fchlstrasse 4 6353 Weggis. Postfach",
    "sg:city":"Weggis",
    "sg:orig_category":"Unternehmensberatung",
    "sg:postcode":"6353",
    "sg:province":"Luzern",
    "wof:name":"Von Graffenried Ag Beratungen Und Publikationen",
    "wof:placetype":"venue"
},
  "geometry": {"coordinates":[7.5464158058,46.8056945801],"type":"Point"}
}