{
  "type": "Feature",
  "properties": {
    "iso:country":"CH",
    "sg:address":"Peter Merian-strasse 86 4052 Basel. Postfach",
    "sg:city":"Basel",
    "sg:orig_category":"H\u00f6here Fachschulen Informatikschulen",
    "sg:phone":"+41 61 279 17 17",
    "sg:postcode":"4002",
    "sg:province":"Basel-Stadt",
    "wof:name":"Fachhochschule Beider Basel Departement Wirtschaft",
    "wof:placetype":"venue"
},
  "geometry": {"coordinates":[7.5939397812,47.5469818115],"type":"Point"}
}