{
  "type": "Feature",
  "properties": {
    "iso:country":"CH",
    "sg:address":"Schmiedengasse 11 4500 Solothurn. Postfach",
    "sg:city":"Solothurn",
    "sg:orig_category":"Betrieb U technische Hilfsdienste des Kultur U Unterhaltungswesens",
    "sg:postcode":"4500",
    "sg:province":"Solothurn",
    "wof:name":"Schmiedengasse 11 Ag Solothurn",
    "wof:placetype":"venue"
},
  "geometry": {"coordinates":[7.535135,47.207382],"type":"Point"}
}