{
  "type": "Feature",
  "properties": {
    "addr:full":"Rue De Eglise Catholique 6 Montreux Vaud 1820",
    "addr:housenumber":"6",
    "addr:postcode":"1820",
    "addr:street":"Rue De Eglise Catholique",
    "iso:country":"CH",
    "sg:address":"Rue De Eglise Catholique 6",
    "sg:city":"Montreux",
    "sg:orig_category":"Detailhandel mit B\u00fcchern, Zeitungen, Schreib U Papeteriewaren Detailhandel mit Tabakwaren",
    "sg:phone":"+41 22 300 34 66",
    "sg:postcode":"1820",
    "sg:province":"Vaud",
    "wof:name":"Ana-maria Delgado Tabacs",
    "wof:placetype":"venue"
},
  "geometry": {"coordinates":[6.139245,46.179321],"type":"Point"}
}