{
  "type": "Feature",
  "properties": {
    "iso:country":"CH",
    "sg:address":"Rue De L'eglise 3",
    "sg:city":"P\u00e9ry",
    "sg:classifiers":[
        {
            "category":"Restaurant",
            "type":"Food & Drink"
        }
    ],
    "sg:phone":"+41 24 492 31 29",
    "sg:postcode":"2603",
    "sg:province":"Bern",
    "wof:name":"Restaurant Du Lac Retaud",
    "wof:placetype":"venue"
},
  "geometry": {"coordinates":[7.1587119102,46.3500404358],"type":"Point"}
}