{
  "type": "Feature",
  "properties": {
    "iso:country":"CH",
    "sg:address":"Les Emibois-muriaux 2338 Emibois-muriaux. Postfach",
    "sg:city":"Emibois-muriaux",
    "sg:orig_category":"Softwareentwicklung U beratung",
    "sg:postcode":"2338",
    "sg:province":"Jura",
    "wof:name":"Panipro S\u00e0rl",
    "wof:placetype":"venue"
},
  "geometry": {"coordinates":[6.9861302376,47.2331314087],"type":"Point"}
}