{
  "type": "Feature",
  "properties": {
    "iso:country":"CH",
    "sg:address":"Buchmattstrasse 44",
    "sg:city":"Burgdorf",
    "sg:orig_category":"Maler U Glasergewerbe Stukkateurgewerbe, Gipserei U Verputzerei",
    "sg:phone":"+41 34 423 17 38",
    "sg:postcode":"3400",
    "sg:province":"Bern",
    "wof:name":"Murri Ag Malergesch\u00e4ft",
    "wof:placetype":"venue"
},
  "geometry": {"coordinates":[7.6053481102,47.0639533997],"type":"Point"}
}