{
  "type": "Feature",
  "properties": {
    "iso:country":"CH",
    "sg:address":"Neugasse 136",
    "sg:city":"Z\u00fcrich",
    "sg:orig_category":"Architekturb\u00fcros",
    "sg:phone":"+41 12733202",
    "sg:postcode":"8005",
    "sg:province":"Z\u00fcrich",
    "wof:name":"Marco Graber & Thomas Pulver Architekturb\u00fcro",
    "wof:placetype":"venue"
},
  "geometry": {"coordinates":[8.525441,47.384602],"type":"Point"}
}