{
  "type": "Feature",
  "properties": {
    "iso:country":"CH",
    "sg:address":"Werkstrasse 12 A",
    "sg:city":"Diepoldsau",
    "sg:orig_category":"Unclassifiable Establishments",
    "sg:postcode":"9444",
    "sg:province":"St. Gallen",
    "wof:name":"J\u00f6rg B\u00fcsel Textilvertretungen",
    "wof:placetype":"venue"
},
  "geometry": {"coordinates":[9.6666002274,47.3777008057],"type":"Point"}
}