{
  "type": "Feature",
  "properties": {
    "iso:country":"CH",
    "sg:address":"Steinlen 4",
    "sg:city":"Gretzenbach",
    "sg:orig_category":"Finanzierungsinstitutionen",
    "sg:phone":"+41 62 288 80 32",
    "sg:postcode":"5014",
    "sg:province":"Solothurn",
    "wof:name":"Kabofina Ag",
    "wof:placetype":"venue"
},
  "geometry": {"coordinates":[7.9886369705,47.3595466614],"type":"Point"}
}