{
  "type": "Feature",
  "properties": {
    "iso:country":"CH",
    "sg:address":"Pierre Rue Saint- 18",
    "sg:city":"Fribourg",
    "sg:orig_category":"Non-Classified Establishments",
    "sg:postcode":"1700",
    "sg:province":"Fribourg",
    "wof:name":"P\u00e9rou Sa.",
    "wof:placetype":"venue"
},
  "geometry": {"coordinates":[9.8095407486,46.4907417297],"type":"Point"}
}