{
  "type": "Feature",
  "properties": {
    "iso:country":"CH",
    "sg:address":"Grabenstrasse 52",
    "sg:city":"Frauenfeld",
    "sg:orig_category":"Non-Classified Establishments",
    "sg:postcode":"8500",
    "sg:province":"Thurgau",
    "wof:name":"Hanf-palast R\u00fcti Gmbh",
    "wof:placetype":"venue"
},
  "geometry": {"coordinates":[8.8528108597,47.2601356506],"type":"Point"}
}