{
  "type": "Feature",
  "properties": {
    "iso:country":"CH",
    "sg:address":"Avenue Du Tirage 5",
    "sg:city":"Pully",
    "sg:orig_category":"Sanit\u00e4rinstallation",
    "sg:phone":"+41 21 728 93 90",
    "sg:postcode":"1009",
    "sg:province":"Vaud",
    "wof:name":"Patrick Clot Installations Sanitaires",
    "wof:placetype":"venue"
},
  "geometry": {"coordinates":[6.6583352089,46.5113067627],"type":"Point"}
}