{
  "type": "Feature",
  "properties": {
    "iso:country":"CH",
    "sg:address":"Alemannenstrasse 146",
    "sg:city":"Eschen",
    "sg:orig_category":"Detailhandel mit Milcherzeugnissen U Eiern Verarbeitung von Milch",
    "sg:phone":"+423 373 12 46",
    "sg:postcode":"9492",
    "wof:name":"K\u00e4thi Heeb Sennerei",
    "wof:placetype":"venue"
},
  "geometry": {"coordinates":[9.5198297501,47.2128486633],"type":"Point"}
}