{
  "type": "Feature",
  "properties": {
    "iso:country":"CH",
    "sg:address":"Reiserstrasse 139 4600 Olten. Postfach",
    "sg:city":"Olten",
    "sg:orig_category":"Architektur U Ingenieurb\u00fcros",
    "sg:postcode":"4600",
    "sg:province":"Solothurn",
    "wof:name":"Architekturb\u00fcro Klaus Rolf",
    "wof:placetype":"venue"
},
  "geometry": {"coordinates":[7.916464,47.348606],"type":"Point"}
}