{
  "type": "Feature",
  "properties": {
    "iso:country":"CH",
    "sg:address":"3970",
    "sg:city":"Salgesch",
    "sg:orig_category":"Herstellung von Wein",
    "sg:phone":"+41 27 455 31 21",
    "sg:postcode":"3970",
    "sg:province":"Valais",
    "wof:name":"Wpg Weinproduzenten-genossenschaft Salgesch",
    "wof:placetype":"venue"
},
  "geometry": {"coordinates":[7.5696148872,46.3114013672],"type":"Point"}
}