{
  "type": "Feature",
  "properties": {
    "iso:country":"CH",
    "sg:address":"Am Wasser 55",
    "sg:city":"Z\u00fcrich",
    "sg:orig_category":"Non-Classified Establishments",
    "sg:phone":"+41 13401435",
    "sg:postcode":"8049",
    "sg:province":"Z\u00fcrich",
    "wof:name":"Pavelka Ralph",
    "wof:placetype":"venue"
},
  "geometry": {"coordinates":[8.5057058334,47.3958587646],"type":"Point"}
}