{
  "type": "Feature",
  "properties": {
    "iso:country":"CH",
    "sg:address":"Route Aloys-fauquez 28",
    "sg:city":"Lausanne",
    "sg:classifiers":[
        {
            "category":"Government",
            "subcategory":"Post Office",
            "type":"Public Place"
        }
    ],
    "sg:phone":"+41 21 648 48 08",
    "sg:postcode":"1018",
    "sg:province":"Vaud",
    "sg:tags":[
        "caf\u00e9s",
        "tea-rooms"
    ],
    "wof:name":"Bar \u00e0 Caf\u00e9 R\u00e9tro",
    "wof:placetype":"venue"
},
  "geometry": {"coordinates":[6.6325960159,46.5323295593],"type":"Point"}
}