{
  "type": "Feature",
  "properties": {
    "iso:country":"CH",
    "sg:address":"Alte Simplonstrasse 47",
    "sg:city":"Brig",
    "sg:orig_category":"Herstellung von Schmuck, Gold U Silberschmiedwaren",
    "sg:phone":"+41 56 493 70 70",
    "sg:postcode":"3900",
    "sg:province":"Valais",
    "wof:name":"Diadoro Schmuck Design Ag",
    "wof:placetype":"venue"
},
  "geometry": {"coordinates":[8.2906999588,47.4518051147],"type":"Point"}
}