{
  "type": "Feature",
  "properties": {
    "iso:country":"CH",
    "sg:address":"Quaistrasse 41",
    "sg:city":"Trimbach",
    "sg:orig_category":"Detailhandel mit Metallwaren, Anstrichmitteln, Glaswaren, Bau U Heimwerkerbedarf Handelsvermittlung ",
    "sg:phone":"+41 62 293 44 30",
    "sg:postcode":"4632",
    "sg:province":"Solothurn",
    "wof:name":"Burn Engineering Ag",
    "wof:placetype":"venue"
},
  "geometry": {"coordinates":[7.9060878754,47.3577194214],"type":"Point"}
}