{
  "type": "Feature",
  "properties": {
    "iso:country":"CH",
    "sg:address":"Hauptstrasse 161",
    "sg:city":"Kirchleerau",
    "sg:orig_category":"Herstellung von sonstigen Fahrzeugen",
    "sg:phone":"+41 62 726 13 18",
    "sg:postcode":"5054",
    "sg:province":"Aargau",
    "wof:name":"Fritz Hunziker Wagnerei",
    "wof:placetype":"venue"
},
  "geometry": {"coordinates":[8.0630025864,47.2759742737],"type":"Point"}
}