{
  "type": "Feature",
  "properties": {
    "iso:country":"CH",
    "sg:address":"Kn\u00fcslistrasse 5 8004 Z\u00fcrich. Postfach",
    "sg:city":"Z\u00fcrich",
    "sg:orig_category":"R\u00fcckgewinnung U Vorbereitung f\u00fcr die Wiederverwertung Recycling von Schrott",
    "sg:postcode":"8001",
    "sg:province":"Z\u00fcrich",
    "wof:name":"Altmetall + Transporte Brutschi Altmetall; Entsorgung, Transporte. Altmaterial; Recycling",
    "wof:placetype":"venue"
},
  "geometry": {"coordinates":[8.5090379715,47.3842506409],"type":"Point"}
}