{
  "type": "Feature",
  "properties": {
    "iso:country":"CH",
    "sg:address":"Administration Communale 1897 Bouveret. Postfach",
    "sg:city":"Bouveret",
    "sg:orig_category":"Interessenvertretungen",
    "sg:postcode":"1897",
    "sg:province":"Valais",
    "wof:name":"Porter Vintage Association",
    "wof:placetype":"venue"
},
  "geometry": {"coordinates":[8.4448652267,47.0884056091],"type":"Point"}
}