{
  "type": "Feature",
  "properties": {
    "iso:country":"CH",
    "sg:address":"Wyd\u00e4ckerring 148 8047 Z\u00fcrich. Postfach",
    "sg:city":"Z\u00fcrich",
    "sg:orig_category":"Reinigungsgewerbe",
    "sg:phone":"+41 14931939",
    "sg:postcode":"8048",
    "sg:province":"Z\u00fcrich",
    "wof:name":"Mishelli Handel Gmbh",
    "wof:placetype":"venue"
},
  "geometry": {"coordinates":[8.4924001694,47.3699913025],"type":"Point"}
}