{
  "type": "Feature",
  "properties": {
    "iso:country":"CH",
    "sg:address":"Rue Du Plandodin",
    "sg:city":"Savi\u00e8se",
    "sg:orig_category":"Detailhandel mit M\u00f6beln Verlegen von Fussboden",
    "sg:phone":"+41 81 933 14 56",
    "sg:postcode":"1965",
    "sg:province":"Valais",
    "wof:name":"Ignaz Sax",
    "wof:placetype":"venue"
},
  "geometry": {"coordinates":[9.1031398773,46.7513198853],"type":"Point"}
}