{
  "type": "Feature",
  "properties": {
    "iso:country":"CH",
    "sg:address":"Hauptstrasse 78",
    "sg:city":"Meinisberg",
    "sg:orig_category":"G\u00fcterbef\u00f6rderung im Strassenverkehr",
    "sg:phone":"+41 32 377 19 02",
    "sg:postcode":"2554",
    "sg:province":"Bern",
    "wof:name":"Matimax Motors Kunz M.",
    "wof:placetype":"venue"
},
  "geometry": {"coordinates":[7.3509421349,47.159942627],"type":"Point"}
}