{
  "type": "Feature",
  "properties": {
    "iso:country":"CH",
    "sg:address":"Morgartenring 126",
    "sg:city":"Basel",
    "sg:orig_category":"Erbringung von Dienstleistungen f\u00fcr Unternehmen",
    "sg:phone":"+41 32 841 20 01",
    "sg:postcode":"4054",
    "sg:province":"Basel-Stadt",
    "wof:name":"Decor'art-d\u00e9coration D'int\u00e9rieur, Fagherazzi C\u00e9dric D\u00e9coration D'int\u00e9rieur Etc",
    "wof:placetype":"venue"
},
  "geometry": {"coordinates":[6.857986927,46.9656143188],"type":"Point"}
}