{
  "type": "Feature",
  "properties": {
    "iso:country":"CH",
    "sg:address":"Z\u00fcrichstrasse 215 8122 Binz. Postfach",
    "sg:city":"Binz",
    "sg:classifiers":[
        {
            "category":"Travel",
            "subcategory":"Hotels & Motels",
            "type":"Entertainment"
        }
    ],
    "sg:postcode":"8122",
    "sg:province":"Z\u00fcrich",
    "sg:tags":[
        "hotels",
        "mit",
        "restaurant"
    ],
    "wof:name":"Sch\u00f6nenberger Silvia (wirtschaft Zur Trotte) Gastbetrieb",
    "wof:placetype":"venue"
},
  "geometry": {"coordinates":[8.6286306381,47.3562431335],"type":"Point"}
}