{
  "type": "Feature",
  "properties": {
    "iso:country":"CH",
    "sg:address":"Hardhofstrasse 17",
    "sg:city":"Embrach",
    "sg:orig_category":"Erbringung von Dienstleistungen f\u00fcr Unternehmen Unternehmensberatung",
    "sg:phone":"+41 18817980",
    "sg:postcode":"8424",
    "sg:province":"Z\u00fcrich",
    "wof:name":"Oeconomic All Risk Service Ag",
    "wof:placetype":"venue"
},
  "geometry": {"coordinates":[8.5942964554,47.5181236267],"type":"Point"}
}