{
  "type": "Feature",
  "properties": {
    "iso:country":"CH",
    "sg:address":"B\u00fchlmattweg 4",
    "sg:city":"Baar",
    "sg:orig_category":"Herstellung von Karosserien U Anh\u00e4ngern",
    "sg:phone":"+41 42522952",
    "sg:postcode":"6340",
    "sg:province":"Zug",
    "wof:name":"Carrosserie Marty Ag",
    "wof:placetype":"venue"
},
  "geometry": {"coordinates":[8.5274858475,47.1975250244],"type":"Point"}
}