{
  "type": "Feature",
  "properties": {
    "iso:country":"CH",
    "sg:address":"Bremgartenstr. 12",
    "sg:city":"Sins",
    "sg:classifiers":[
        {
            "category":"Banks & Credit Unions",
            "subcategory":"Bank",
            "type":"Services"
        }
    ],
    "sg:phone":"+41 71 969 69 00",
    "sg:postcode":"5643",
    "sg:province":"Aargau",
    "wof:name":"Raiffeisenbank Sirnach",
    "wof:placetype":"venue"
},
  "geometry": {"coordinates":[8.99709,47.462101],"type":"Point"}
}