{
  "type": "Feature",
  "properties": {
    "iso:country":"CH",
    "sg:address":"Bahnhofstrasse 8",
    "sg:city":"Ins",
    "sg:orig_category":"Detailhandel mit Waren verschiedener Art, Hauptrichtung Nahrungsmittel",
    "sg:phone":"+41 32 312 96 01",
    "sg:postcode":"3232",
    "sg:province":"Bern",
    "wof:name":"Coop Center",
    "wof:placetype":"venue"
},
  "geometry": {"coordinates":[7.1036458015,47.0056037903],"type":"Point"}
}