{
  "type": "Feature",
  "properties": {
    "iso:country":"CH",
    "sg:address":"Untere Hauptgasse 31",
    "sg:city":"Thun",
    "sg:orig_category":"Wirtschafts- and Arbeitgeberverb\u00e4nde",
    "sg:phone":"+41 33 222 27 71",
    "sg:postcode":"3600",
    "sg:province":"Bern",
    "wof:name":"Apothekerverein C/o Berntor-apotheke",
    "wof:placetype":"venue"
},
  "geometry": {"coordinates":[7.6285657883,46.7612075806],"type":"Point"}
}