{
  "type": "Feature",
  "properties": {
    "iso:country":"CH",
    "sg:address":"Br\u00fctschengasse 19",
    "sg:city":"Wallbach",
    "sg:orig_category":"Sportvereine Orientierungslauf",
    "sg:phone":"+41 61 861 15 19",
    "sg:postcode":"4323",
    "sg:province":"Aargau",
    "wof:name":"Olk Fricktal",
    "wof:placetype":"venue"
},
  "geometry": {"coordinates":[7.9057798386,47.5591087341],"type":"Point"}
}