{
  "type": "Feature",
  "properties": {
    "iso:country":"CH",
    "sg:address":"Dorfstrasse 1 3555 Trubschachen. Postfach 31",
    "sg:city":"Trubschachen",
    "sg:orig_category":"Gewinnung von Kies U Sand Herstellung von sonstigen Produkten aus nichtmetallischen Mineralien",
    "sg:phone":"+41 34 495 51 10",
    "sg:postcode":"3555",
    "sg:province":"Bern",
    "wof:name":"Schwitter Bau Ag Trubschachen",
    "wof:placetype":"venue"
},
  "geometry": {"coordinates":[7.8459239006,46.9224052429],"type":"Point"}
}