{
  "type": "Feature",
  "properties": {
    "iso:country":"CH",
    "sg:address":"Gros Clos 40",
    "sg:city":"Loveresse",
    "sg:orig_category":"Sanit\u00e4r, Heizungs U L\u00fcftungsinstallation",
    "sg:phone":"+41 32 481 21 28",
    "sg:postcode":"2732",
    "sg:province":"Bern",
    "wof:name":"Chauffage-sanitaire A Marca S\u00e0rl",
    "wof:placetype":"venue"
},
  "geometry": {"coordinates":[7.2339138985,47.2413787842],"type":"Point"}
}