{
  "type": "Feature",
  "properties": {
    "iso:country":"CH",
    "sg:address":"Corso Fusina 12",
    "sg:city":"Campione",
    "sg:orig_category":"Herstellung von M\u00f6beln",
    "sg:phone":"+41 91 649 73 03",
    "sg:postcode":"6911",
    "sg:province":"Ticino",
    "wof:name":"Fratelli Luigi & Giuseppe Mena Fabbrica Mobili & Serramenti",
    "wof:placetype":"venue"
},
  "geometry": {"coordinates":[10.8212308884,45.0803642273],"type":"Point"}
}