{
  "type": "Feature",
  "properties": {
    "iso:country":"CH",
    "sg:address":"Champlan 1971 Grimisuat. Postfach",
    "sg:city":"Grimisuat",
    "sg:orig_category":"Detailhandel mit Fleisch U Fleischwaren Sonstige Dienstleistungen in der Tierhaltung",
    "sg:phone":"+41 27 398 42 76",
    "sg:postcode":"1971",
    "sg:province":"Valais",
    "wof:name":"Balet Luc, Boucherie Des Landes",
    "wof:placetype":"venue"
},
  "geometry": {"coordinates":[7.3867740631,46.2607192993],"type":"Point"}
}