{
  "type": "Feature",
  "properties": {
    "iso:country":"CH",
    "sg:address":"Im Fallengatter 3",
    "sg:city":"Frauenfeld",
    "sg:orig_category":"Herstellung von sonstigen elektrischen Ausr\u00fcstungen",
    "sg:postcode":"8500",
    "sg:province":"Thurgau",
    "wof:name":"Werner Eberle",
    "wof:placetype":"venue"
},
  "geometry": {"coordinates":[9.0569219589,46.9810371399],"type":"Point"}
}