{
  "type": "Feature",
  "properties": {
    "iso:country":"CH",
    "sg:address":"Bahnhofstrasse 298",
    "sg:city":"Niederbuchsiten",
    "sg:orig_category":"Herstellung von Akkumulatoren U Batterien",
    "sg:phone":"+41 62 389 66 50",
    "sg:postcode":"4626",
    "sg:province":"Solothurn",
    "wof:name":"Deta Akkumulatoren Ag",
    "wof:placetype":"venue"
},
  "geometry": {"coordinates":[7.7740240097,47.3000411987],"type":"Point"}
}