{
  "type": "Feature",
  "properties": {
    "iso:country":"CH",
    "sg:address":"Gewerbestrasse 8",
    "sg:city":"Sissach",
    "sg:orig_category":"Detailhandel mit Waren verschiedener Art in Verkaufsr\u00e4umen",
    "sg:phone":"+41 61 976 96 10",
    "sg:postcode":"4450",
    "sg:province":"Basel-Landschaft",
    "wof:name":"Coop Bau + Hobby",
    "wof:placetype":"venue"
},
  "geometry": {"coordinates":[7.8023748398,47.46717453],"type":"Point"}
}