{
  "type": "Feature",
  "properties": {
    "iso:country":"CH",
    "sg:address":"Seld 72",
    "sg:city":"Pragg-jenaz",
    "sg:classifiers":[
        {
            "category":"Organizations",
            "subcategory":"Political Organization",
            "type":"Services"
        }
    ],
    "sg:phone":"+41 33 676 24 24",
    "sg:postcode":"7231",
    "sg:province":"Graubunden",
    "sg:tags":[
        "cabling",
        "system"
    ],
    "wof:name":"Electrio Ag",
    "wof:placetype":"venue"
},
  "geometry": {"coordinates":[7.692735,46.62553],"type":"Point"}
}