{
  "type": "Feature",
  "properties": {
    "addr:full":"Lautengartenstrasse 7 4052 Basel. Postfach Basel Basel-Stadt 4052",
    "addr:housenumber":"7",
    "addr:postcode":"4052;4052",
    "addr:street":"Lautengartenstrasse;Postfach",
    "iso:country":"CH",
    "sg:address":"Lautengartenstrasse 7 4052 Basel. Postfach",
    "sg:city":"Basel",
    "sg:orig_category":"Architektur U Ingenieurb\u00fcros",
    "sg:postcode":"4052",
    "sg:province":"Basel-Stadt",
    "wof:name":"Wadec Ag Bauberatung",
    "wof:placetype":"venue"
},
  "geometry": {"coordinates":[7.595579,47.553337],"type":"Point"}
}