{
  "type": "Feature",
  "properties": {
    "iso:country":"CH",
    "sg:address":"1522 Lucens Case Postale 24",
    "sg:city":"Lucens",
    "sg:orig_category":"Sportvereine Ballsport Fussball",
    "sg:phone":"+41 21 905 47 08",
    "sg:postcode":"1522",
    "sg:province":"Vaud",
    "wof:name":"Fc Lucens",
    "wof:placetype":"venue"
},
  "geometry": {"coordinates":[6.8418149948,46.7074050903],"type":"Point"}
}