{
  "type": "Feature",
  "properties": {
    "iso:country":"CH",
    "sg:address":"Einsiedlerstrasse 25",
    "sg:city":"W\u00e4denswil",
    "sg:orig_category":"Architekturb\u00fcros",
    "sg:phone":"+41 17806489",
    "sg:postcode":"8820",
    "sg:province":"Z\u00fcrich",
    "wof:name":"Konrad Ottinger Architekturb\u00fcro",
    "wof:placetype":"venue"
},
  "geometry": {"coordinates":[8.685618,47.220589],"type":"Point"}
}