{
  "type": "Feature",
  "properties": {
    "iso:country":"CH",
    "sg:address":"Irgeli",
    "sg:city":"Stallikon",
    "sg:orig_category":"Herstellung von Metallkonstruktionen Schlossereien",
    "sg:phone":"+41 17000577",
    "sg:postcode":"8143",
    "sg:province":"Z\u00fcrich",
    "wof:name":"Grob Andreas Waren; Handel",
    "wof:placetype":"venue"
},
  "geometry": {"coordinates":[8.489988327,47.3257484436],"type":"Point"}
}