{
  "type": "Feature",
  "properties": {
    "iso:country":"CH",
    "sg:address":"Grundstrasse 1",
    "sg:city":"Fehraltorf",
    "sg:orig_category":"Herstellung von sonstiger Bekleidung U Bekleidungszubeh\u00f6r",
    "sg:phone":"+41 19550845",
    "sg:postcode":"8320",
    "sg:province":"Z\u00fcrich",
    "wof:name":"Strubelpeter, Kinderwaren-b\u00f6rse, Francisca Muff",
    "wof:placetype":"venue"
},
  "geometry": {"coordinates":[8.7550420761,47.3867683411],"type":"Point"}
}