{
  "type": "Feature",
  "properties": {
    "iso:country":"CH",
    "sg:address":"2806",
    "sg:city":"Mettembert",
    "sg:orig_category":"Gemeindeverwaltungen",
    "sg:phone":"+41 32 431 16 12",
    "sg:postcode":"2806",
    "sg:province":"Jura",
    "wof:name":"Administration Communale De Mettembert",
    "wof:placetype":"venue"
},
  "geometry": {"coordinates":[7.3198652267,47.3980560303],"type":"Point"}
}