{
  "type": "Feature",
  "properties": {
    "iso:country":"CH",
    "sg:address":"Rigistrasse 6",
    "sg:city":"Zug",
    "sg:orig_category":"Grosshandel mit pharmazeutischen Erzeugnissen, medizinischen U orthop\u00e4dischen Artikeln Herstellung v",
    "sg:phone":"+41 41 710 90 11",
    "sg:postcode":"6300",
    "sg:province":"Zug",
    "wof:name":"Body Sculpt Ag",
    "wof:placetype":"venue"
},
  "geometry": {"coordinates":[8.5147066116,47.1699905396],"type":"Point"}
}