{
  "type": "Feature",
  "properties": {
    "iso:country":"CH",
    "sg:address":"Schulhausstrasse 10",
    "sg:city":"Hochdorf",
    "sg:orig_category":"Mechanik",
    "sg:phone":"+41 41 910 12 66",
    "sg:postcode":"6280",
    "sg:province":"Luzern",
    "wof:name":"Frey Walter Mech. Werkstatt",
    "wof:placetype":"venue"
},
  "geometry": {"coordinates":[8.2888011932,47.1643714905],"type":"Point"}
}