{
  "type": "Feature",
  "properties": {
    "iso:country":"CH",
    "sg:address":"Avenue De La Gare",
    "sg:city":"Granges-pr\u00e8s-marnand",
    "sg:classifiers":[
        {
            "category":"Building & Trades",
            "subcategory":"Construction",
            "type":"Services"
        }
    ],
    "sg:phone":"+41 26 668 01 85",
    "sg:postcode":"1523",
    "sg:province":"Vaud",
    "sg:tags":[
        "front",
        "door"
    ],
    "wof:name":"Menuiserie Cosendai S.\u00e0 R.l.",
    "wof:placetype":"venue"
},
  "geometry": {"coordinates":[6.8917398453,46.7608108521],"type":"Point"}
}