{
  "type": "Feature",
  "properties": {
    "iso:country":"CH",
    "sg:address":"Unterdorfstrasse 14",
    "sg:city":"Arch",
    "sg:orig_category":"Grosshandel mit Uhren",
    "sg:phone":"+41 31 752 08 13",
    "sg:postcode":"3296",
    "sg:province":"Bern",
    "wof:name":"Jan Swiss Watch Gmbh Uhrenhandel",
    "wof:placetype":"venue"
},
  "geometry": {"coordinates":[7.2607297897,46.9533195496],"type":"Point"}
}