{
  "type": "Feature",
  "properties": {
    "addr:full":"Via Gerolamo Vegezzi 4 Lugano Ticino 6900",
    "addr:housenumber":"4",
    "addr:postcode":"6900",
    "addr:street":"Via Gerolamo Vegezzi",
    "iso:country":"CH",
    "sg:address":"Via Gerolamo Vegezzi 4",
    "sg:city":"Lugano",
    "sg:orig_category":"Arztpraxen",
    "sg:phone":"+41 91 922 94 44",
    "sg:postcode":"6900",
    "sg:province":"Ticino",
    "wof:name":"Dott.med.piero Andreoli Specialista Fmh",
    "wof:placetype":"venue"
},
  "geometry": {"coordinates":[8.953248,46.004723],"type":"Point"}
}