{
  "type": "Feature",
  "properties": {
    "addr:full":"Alte Landstrasse 23 Oberrieden Z\u00fcrich 8942",
    "addr:housenumber":"23",
    "addr:postcode":"8942",
    "addr:street":"Alte Landstrasse",
    "iso:country":"CH",
    "sg:address":"Alte Landstrasse 23",
    "sg:city":"Oberrieden",
    "sg:orig_category":"Architektur U Ingenieurb\u00fcros Sonstiger Grosshandel",
    "sg:phone":"+41 17229090",
    "sg:postcode":"8942",
    "sg:province":"Z\u00fcrich",
    "wof:name":"Messerli E. Partner Ag",
    "wof:placetype":"venue"
},
  "geometry": {"coordinates":[8.57546,47.278721],"type":"Point"}
}