{
  "type": "Feature",
  "properties": {
    "iso:country":"CH",
    "sg:address":"Hechtliacker 33 4053 Basel. Postfach",
    "sg:city":"Basel",
    "sg:orig_category":"Zeitschriftenverlag",
    "sg:postcode":"4051",
    "sg:province":"Basel-Stadt",
    "wof:name":"Die Biene Schmutz Zeitschriften; Herausgabe",
    "wof:placetype":"venue"
},
  "geometry": {"coordinates":[7.6015748978,47.5359764099],"type":"Point"}
}