{
  "type": "Feature",
  "properties": {
    "iso:country":"CH",
    "sg:address":"Grabenackerstrasse 46",
    "sg:city":"Steinhausen",
    "sg:orig_category":"Allgemeiner Hoch U Tiefbau",
    "sg:phone":"+41 41 710 22 47",
    "sg:postcode":"6312",
    "sg:province":"Zug",
    "wof:name":"Bkz Baukonsortium Zug, Kienast & Partner",
    "wof:placetype":"venue"
},
  "geometry": {"coordinates":[8.482676,47.200352],"type":"Point"}
}