{
  "type": "Feature",
  "properties": {
    "iso:country":"CH",
    "sg:address":"Gartenstrasse 4",
    "sg:city":"Pratteln",
    "sg:orig_category":"Blumen U Zierpflanzenbau Detailhandel mit Blumen U Pflanzen",
    "sg:phone":"+41 71 855 18 68",
    "sg:postcode":"4133",
    "sg:province":"Basel-Landschaft",
    "wof:name":"Edwin Frehner G\u00e4rtnerei Adler",
    "wof:placetype":"venue"
},
  "geometry": {"coordinates":[9.542933,47.477543],"type":"Point"}
}