{
  "type": "Feature",
  "properties": {
    "iso:country":"CH",
    "sg:address":"Birchen",
    "sg:city":"Leukerbad",
    "sg:orig_category":"RESTAURANTS: TEA-ROOMS",
    "sg:phone":"+41 27 470 46 08",
    "sg:postcode":"3954",
    "sg:province":"Valais",
    "wof:name":"Roten Alexander, Restaurant Birchen",
    "wof:placetype":"venue"
},
  "geometry": {"coordinates":[7.6150641441,46.3647232056],"type":"Point"}
}