{
  "type": "Feature",
  "properties": {
    "iso:country":"CH",
    "sg:address":"Golena Via 1",
    "sg:city":"Giubiasco",
    "sg:orig_category":"RESTAURANTS: TEA-ROOMS",
    "sg:phone":"+41 91 857 79 98",
    "sg:postcode":"6512",
    "sg:province":"Ticino",
    "wof:name":"Jmg Sagl",
    "wof:placetype":"venue"
},
  "geometry": {"coordinates":[9.0120725632,46.1794242859],"type":"Point"}
}