{
  "type": "Feature",
  "properties": {
    "addr:full":"Zugerstr. 26 Unter\u00e4geri Zug 6314",
    "addr:housenumber":"26",
    "addr:postcode":"6314",
    "addr:street":"Zugerstr.;Zug",
    "iso:country":"CH",
    "sg:address":"Zugerstr. 26",
    "sg:city":"Unter\u00e4geri",
    "sg:classifiers":[
        {
            "category":"Banks & Credit Unions",
            "subcategory":"Bank",
            "type":"Services"
        }
    ],
    "sg:phone":"+41 4142724141",
    "sg:postcode":"6314",
    "sg:province":"Zug",
    "wof:name":"Zuger Kantonalbank",
    "wof:placetype":"venue"
},
  "geometry": {"coordinates":[8.580453,47.137836],"type":"Point"}
}