{
  "type": "Feature",
  "properties": {
    "iso:country":"CH",
    "sg:address":"T\u00f6sstalstrasse 21",
    "sg:city":"Hittnau",
    "sg:orig_category":"Handel mit Motorr\u00e4dern, Teilen U Zubeh\u00f6r Instandhaltung U Reparatur von Motorr\u00e4dern",
    "sg:phone":"+41 19511351",
    "sg:postcode":"8335",
    "sg:province":"Z\u00fcrich",
    "wof:name":"Velo-sport Muggler H.",
    "wof:placetype":"venue"
},
  "geometry": {"coordinates":[8.8241491318,47.3711853027],"type":"Point"}
}