{
  "type": "Feature",
  "properties": {
    "iso:country":"CH",
    "sg:address":"Bahnhofstrasse 10 7130 Ilanz. Postfach 50",
    "sg:city":"Ilanz",
    "sg:orig_category":"Fachdetailhandel mit pharmazeutischen Produkten",
    "sg:phone":"+41 81 925 14 68",
    "sg:postcode":"7130",
    "sg:province":"Graubunden",
    "wof:name":"Apoteca Tomaschett Drogheria",
    "wof:placetype":"venue"
},
  "geometry": {"coordinates":[9.2056303024,46.7750892639],"type":"Point"}
}