{
  "type": "Feature",
  "properties": {
    "iso:country":"CH",
    "sg:address":"Rue Du Bourg De L'auge 4 1636 Broc Case Postale 89",
    "sg:city":"Broc",
    "sg:orig_category":"Fachdetailhandel mit pharmazeutischen Produkten",
    "sg:phone":"+41 26 921 26 26",
    "sg:postcode":"1636",
    "sg:province":"Fribourg",
    "wof:name":"Pharmacie St-luc, Denti-spozio Dominique",
    "wof:placetype":"venue"
},
  "geometry": {"coordinates":[5.2456002235,46.191444397],"type":"Point"}
}