{
  "type": "Feature",
  "properties": {
    "iso:country":"CH",
    "sg:address":"Steinacherstrasse 4",
    "sg:city":"Illnau",
    "sg:orig_category":"Ingenieurb\u00fcros Elektro",
    "sg:phone":"+41 52 346 16 80",
    "sg:postcode":"8308",
    "sg:province":"Z\u00fcrich",
    "wof:name":"Josef Peter Ingenieurb\u00fcro",
    "wof:placetype":"venue"
},
  "geometry": {"coordinates":[8.7146091461,47.4127502441],"type":"Point"}
}