{
  "type": "Feature",
  "properties": {
    "addr:full":"Am Stausee 28 Birsfelden Basel-Landschaft 4127",
    "addr:housenumber":"28",
    "addr:postcode":"4127",
    "addr:street":"Am Stausee",
    "iso:country":"CH",
    "sg:address":"Am Stausee 28",
    "sg:city":"Birsfelden",
    "sg:orig_category":"Arbeitnehmerverb\u00e4nde",
    "sg:phone":"+41 61 312 34 10",
    "sg:postcode":"4127",
    "sg:province":"Basel-Landschaft",
    "wof:name":"Ptt-union Sektion Birsfelden Herrn Rudolf Achermann",
    "wof:placetype":"venue"
},
  "geometry": {"coordinates":[7.630572,47.556763],"type":"Point"}
}