{
  "type": "Feature",
  "properties": {
    "iso:country":"CH",
    "sg:address":"Rennweg 52",
    "sg:city":"Z\u00fcrich",
    "sg:orig_category":"Vermietung U Verpachtung von eigenen Immobilien",
    "sg:phone":"+41 12526366",
    "sg:postcode":"8001",
    "sg:province":"Z\u00fcrich",
    "wof:name":"Appartement-haus Oberdorf Ag",
    "wof:placetype":"venue"
},
  "geometry": {"coordinates":[8.5391893387,47.3737754822],"type":"Point"}
}