{
  "type": "Feature",
  "properties": {
    "addr:full":"Hofacher 5 Gr\u00fcningen Z\u00fcrich 8627",
    "addr:housenumber":"5",
    "addr:postcode":"8627",
    "addr:street":"Hofacher;Zuerich",
    "iso:country":"CH",
    "sg:address":"Hofacher 5",
    "sg:city":"Gr\u00fcningen",
    "sg:orig_category":"Allgemeiner Hoch U Tiefbau",
    "sg:phone":"+41 32 351 45 68",
    "sg:postcode":"8627",
    "sg:province":"Z\u00fcrich",
    "wof:name":"Tomasini Gmbh",
    "wof:placetype":"venue"
},
  "geometry": {"coordinates":[7.363415,47.108486],"type":"Point"}
}