{
  "type": "Feature",
  "properties": {
    "iso:country":"CH",
    "sg:address":"Pl Du March\u00e9 19-21",
    "sg:city":"Carouge",
    "sg:classifiers":[
        {
            "category":"Professional",
            "subcategory":"Engineering",
            "type":"Services"
        }
    ],
    "sg:phone":"+41 22 342 62 80",
    "sg:postcode":"1227",
    "sg:province":"Gen\u00e8ve",
    "sg:tags":[
        "machine",
        "-",
        "mechanical"
    ],
    "wof:name":"Stucker Sa",
    "wof:placetype":"venue"
},
  "geometry": {"coordinates":[6.140068,46.183777],"type":"Point"}
}