{
  "type": "Feature",
  "properties": {
    "iso:country":"CH",
    "sg:address":"Quai De La Sorne 4",
    "sg:city":"Del\u00e9mont",
    "sg:orig_category":"Maler U Glasergewerbe Malerei",
    "sg:phone":"+41 32 422 20 24",
    "sg:postcode":"2800",
    "sg:province":"Jura",
    "wof:name":"Leuba Andr\u00e9.",
    "wof:placetype":"venue"
},
  "geometry": {"coordinates":[7.3476939201,47.3626823425],"type":"Point"}
}