{
  "type": "Feature",
  "properties": {
    "iso:country":"CH",
    "sg:address":"Avenue Gaspard-vallette 12",
    "sg:city":"Gen\u00e8ve",
    "sg:orig_category":"Finanzierungsinstitutionen",
    "sg:phone":"+41 22 318 86 70",
    "sg:postcode":"1206",
    "sg:province":"Gen\u00e8ve",
    "wof:name":"Delta Finance Sa",
    "wof:placetype":"venue"
},
  "geometry": {"coordinates":[6.1571002007,46.1955108643],"type":"Point"}
}