{
  "type": "Feature",
  "properties": {
    "addr:full":"Dorfplatz 9 Stans Nidwalden 6370",
    "addr:housenumber":"9",
    "addr:postcode":"6370",
    "addr:street":"Dorfplatz",
    "iso:country":"CH",
    "sg:address":"Dorfplatz 9",
    "sg:city":"Stans",
    "sg:orig_category":"Advokaturb\u00fcros Notariate",
    "sg:phone":"+41 41 610 41 31",
    "sg:postcode":"6370",
    "sg:province":"Nidwalden",
    "wof:name":"Amstutz & St\u00f6ckli Advokatur- & Notariatsb\u00fcro",
    "wof:placetype":"venue"
},
  "geometry": {"coordinates":[8.365739,46.957329],"type":"Point"}
}