{
  "type": "Feature",
  "properties": {
    "iso:country":"CH",
    "sg:address":"Ebnaterstrasse 16",
    "sg:city":"Ebnat",
    "sg:orig_category":"Herstellung von sonstigen Maschinen f\u00fcr bestimmte Verwendung",
    "sg:phone":"+41 79 250 20 25",
    "sg:postcode":"9642",
    "sg:province":"St. Gallen",
    "wof:name":"K\u00e4ser Maschinen-service",
    "wof:placetype":"venue"
},
  "geometry": {"coordinates":[7.322259903,47.101234436],"type":"Point"}
}