{
  "type": "Feature",
  "properties": {
    "addr:full":"Wuhrmattstrasse 13 Bottmingen Basel-Landschaft 4103",
    "addr:housenumber":"13",
    "addr:postcode":"4103",
    "addr:street":"Wuhrmattstrasse",
    "iso:country":"CH",
    "sg:address":"Wuhrmattstrasse 13",
    "sg:city":"Bottmingen",
    "sg:orig_category":"Bauschreinerei Herstellung von Konstruktionsteilen, Fertigbauteilen U Ausbauelementen aus Holz",
    "sg:phone":"+41 61 421 85 89",
    "sg:postcode":"4103",
    "sg:province":"Basel-Landschaft",
    "wof:name":"Nauer Schreinerei Und K\u00fcchenbau Gmbh",
    "wof:placetype":"venue"
},
  "geometry": {"coordinates":[7.571847,47.52729],"type":"Point"}
}