{
  "type": "Feature",
  "properties": {
    "iso:country":"CH",
    "sg:address":"5242",
    "sg:city":"Birr-lupfig",
    "sg:orig_category":"Sportvereine Sch\u00fctzen Pistolen-& Gewehr",
    "sg:postcode":"5242",
    "sg:province":"Aargau",
    "wof:name":"Pistolenklub Eigenamt",
    "wof:placetype":"venue"
},
  "geometry": {"coordinates":[8.2027196884,47.4361686707],"type":"Point"}
}