{
  "type": "Feature",
  "properties": {
    "iso:country":"CH",
    "sg:address":"Brandstrasse 4",
    "sg:city":"Hinwil",
    "sg:orig_category":"Architekturb\u00fcros",
    "sg:phone":"+41 19371542",
    "sg:postcode":"8340",
    "sg:province":"Z\u00fcrich",
    "wof:name":"Hans-peter M\u00f6rgeli Architekturb\u00fcro",
    "wof:placetype":"venue"
},
  "geometry": {"coordinates":[8.839504,47.295856],"type":"Point"}
}