{
  "type": "Feature",
  "properties": {
    "iso:country":"CH",
    "sg:address":"Strandbadstrasse 3",
    "sg:city":"Interlaken",
    "sg:orig_category":"Grosshandel mit B\u00fcromaschinen Grosshandel mit Datenverarbeitungsger\u00e4ten",
    "sg:phone":"+41 33 826 15 15",
    "sg:postcode":"3800",
    "sg:province":"Bern",
    "wof:name":"Computerfuchs Ag",
    "wof:placetype":"venue"
},
  "geometry": {"coordinates":[7.8547120094,46.6870117188],"type":"Point"}
}