{
  "type": "Feature",
  "properties": {
    "iso:country":"CH",
    "sg:address":"R\u00f6merweg 2",
    "sg:city":"Oberkulm",
    "sg:orig_category":"Reparatur von Uhren U Schmuck",
    "sg:phone":"+41 62 776 28 74",
    "sg:postcode":"5727",
    "sg:province":"Aargau",
    "wof:name":"Charles Sandoz Uhren-reparaturen",
    "wof:placetype":"venue"
},
  "geometry": {"coordinates":[8.1297826767,47.2977294922],"type":"Point"}
}