{
  "type": "Feature",
  "properties": {
    "iso:country":"CH",
    "sg:address":"Sonnmattstrasse 9",
    "sg:city":"Hasle-r\u00fcegsau",
    "sg:classifiers":[
        {
            "category":"Shopping Center",
            "type":"Public Place"
        }
    ],
    "sg:phone":"+41 34 461 56 14",
    "sg:postcode":"3415",
    "sg:province":"Bern",
    "sg:tags":[
        "bag",
        "carrier"
    ],
    "wof:name":"Oeko-sack Gmbh",
    "wof:placetype":"venue"
},
  "geometry": {"coordinates":[7.656434,47.015995],"type":"Point"}
}