{
  "type": "Feature",
  "properties": {
    "iso:country":"CH",
    "sg:address":"Industriestrasse 8 C 3210 Kerzers. Postfach",
    "sg:city":"Kerzers",
    "sg:orig_category":"Sonstige Kultur U Unterhaltungseinrichtungen",
    "sg:phone":"+41 31 755 50 03",
    "sg:postcode":"3210",
    "sg:province":"Fribourg",
    "wof:name":"Body Factory Gmbh Tanz Und Fitnessstudio",
    "wof:placetype":"venue"
},
  "geometry": {"coordinates":[7.1857528687,46.9698295593],"type":"Point"}
}