{
  "type": "Feature",
  "properties": {
    "iso:country":"CH",
    "sg:address":"4500",
    "sg:city":"Solothurn",
    "sg:orig_category":"Vereine Harmonika and Akkordeon",
    "sg:phone":"+41 32 624 17 20",
    "sg:postcode":"4500",
    "sg:province":"Solothurn",
    "wof:name":"Vereinigung Solothurner Handharmonika-spieler",
    "wof:placetype":"venue"
},
  "geometry": {"coordinates":[7.5182700157,47.2069892883],"type":"Point"}
}