{
  "type": "Feature",
  "properties": {
    "iso:country":"CH",
    "sg:address":"Via Nassa 1",
    "sg:city":"Lugano",
    "sg:orig_category":"Fachdetailhandel in Verkaufsr\u00e4umen Grosshandel mit Schmuck",
    "sg:phone":"+41 91 922 99 40",
    "sg:postcode":"6900",
    "sg:province":"Ticino",
    "wof:name":"Calderoni Gioielli Sa",
    "wof:placetype":"venue"
},
  "geometry": {"coordinates":[8.9508190155,46.0034713745],"type":"Point"}
}