{
  "type": "Feature",
  "properties": {
    "iso:country":"CH",
    "sg:address":"Marktgasse 16-18 9220 Bischofszell. Postfach 369",
    "sg:city":"Bischofszell",
    "sg:orig_category":"Herstellung von sonstigen Metallwaren Schlossereien",
    "sg:phone":"+41 71 422 18 21",
    "sg:postcode":"9220",
    "sg:province":"Thurgau",
    "wof:name":"Etter & Co Ag",
    "wof:placetype":"venue"
},
  "geometry": {"coordinates":[9.240322113,47.4939537048],"type":"Point"}
}