{
  "type": "Feature",
  "properties": {
    "iso:country":"CH",
    "sg:address":"La Vegnettaz",
    "sg:city":"Combremont-petit",
    "sg:orig_category":"Grosshandel mit Getreide, Saatgut U Futtermitteln",
    "sg:phone":"+41 26 666 13 77",
    "sg:postcode":"1536",
    "sg:province":"Vaud",
    "wof:name":"Gander Lilly.",
    "wof:placetype":"venue"
},
  "geometry": {"coordinates":[6.8077411652,46.7479362488],"type":"Point"}
}