{
  "type": "Feature",
  "properties": {
    "addr:full":"Rue Centrale 22 Biel/bienne Bern 2502",
    "addr:housenumber":"22",
    "addr:postcode":"2502",
    "addr:street":"Rue Centrale",
    "iso:country":"CH",
    "sg:address":"Rue Centrale 22",
    "sg:city":"Biel/bienne",
    "sg:orig_category":"Detailhandel mit Bekleidung",
    "sg:phone":"+41 32 322 71 57",
    "sg:postcode":"2502",
    "sg:province":"Bern",
    "wof:name":"Adryl, Dubois-dit-bonclaude Adrienne Chemiserie",
    "wof:placetype":"venue"
},
  "geometry": {"coordinates":[7.246537,47.137001],"type":"Point"}
}