{
  "type": "Feature",
  "properties": {
    "iso:country":"CH",
    "sg:address":"Schweissberg",
    "sg:city":"Eggiwil",
    "sg:orig_category":"Zimmerei, Ingenieurholzbau",
    "sg:phone":"+41 33 671 10 62",
    "sg:postcode":"3537",
    "sg:province":"Bern",
    "wof:name":"Fritz F\u00e4hndrich Zimmerei & Chaletbau",
    "wof:placetype":"venue"
},
  "geometry": {"coordinates":[7.6707057953,46.6008453369],"type":"Point"}
}