{
  "type": "Feature",
  "properties": {
    "iso:country":"CH",
    "sg:address":"Romanshornerstrasse 38",
    "sg:city":"Arbon",
    "sg:orig_category":"Sonstiger Fachdetailhandel mit Nahrungsmitteln, Getr\u00e4nken U Tabak in Verkaufsr\u00e4umen",
    "sg:postcode":"9320",
    "sg:province":"Thurgau",
    "wof:name":"T\u00fcfer Ag",
    "wof:placetype":"venue"
},
  "geometry": {"coordinates":[9.8222818375,46.7979431152],"type":"Point"}
}