{
  "type": "Feature",
  "properties": {
    "iso:country":"CH",
    "sg:address":"Bettenstrasse 68",
    "sg:city":"Allschwil",
    "sg:orig_category":"Grosshandel mit Holz U Baustoffen Grosshandel mit M\u00f6beln, Wohnbedarf, Teppichen U Bodenbel\u00e4gen",
    "sg:phone":"+41 41 811 20 07",
    "sg:postcode":"4123",
    "sg:province":"Basel-Landschaft",
    "wof:name":"Netto Baumarkt & Partner Gmbh",
    "wof:placetype":"venue"
},
  "geometry": {"coordinates":[8.6295146942,47.0288581848],"type":"Point"}
}