{
  "type": "Feature",
  "properties": {
    "iso:country":"CH",
    "sg:address":"Chemin Des Brisecou 22",
    "sg:city":"Enges",
    "sg:orig_category":"Sportvereine Ballsport Badminton",
    "sg:phone":"+41 32 757 37 78",
    "sg:postcode":"2073",
    "sg:province":"Neuch\u00e2tel",
    "wof:name":"Badminton-club Le Locle",
    "wof:placetype":"venue"
},
  "geometry": {"coordinates":[7.0168271065,47.0557899475],"type":"Point"}
}