{
  "type": "Feature",
  "properties": {
    "iso:country":"CH",
    "sg:address":"Nadelberg 10",
    "sg:city":"Basel",
    "sg:orig_category":"Interessenvertretungen",
    "sg:postcode":"4051",
    "sg:province":"Basel-Stadt",
    "wof:name":"Stiftung F\u00fcr J\u00fcdische Studien An Der Universit\u00e4t Basel",
    "wof:placetype":"venue"
},
  "geometry": {"coordinates":[7.5853199959,47.5582847595],"type":"Point"}
}