{
  "type": "Feature",
  "properties": {
    "iso:country":"CH",
    "sg:address":"Casa Da Scola",
    "sg:city":"Andiast",
    "sg:classifiers":[
        {
            "category":"Banks & Credit Unions",
            "subcategory":"Bank",
            "type":"Services"
        }
    ],
    "sg:phone":"+41 91 682 47 57",
    "sg:postcode":"7159",
    "sg:province":"Graubunden",
    "wof:name":"Banca Raiffeisen Chiasso",
    "wof:placetype":"venue"
},
  "geometry": {"coordinates":[9.02496,45.833],"type":"Point"}
}