{
  "type": "Feature",
  "properties": {
    "iso:country":"CH",
    "sg:address":"Beislerstrasse 10 8634 Hombrechtikon. Postfach",
    "sg:city":"Hombrechtikon",
    "sg:orig_category":"Mechanik",
    "sg:postcode":"8634",
    "sg:province":"Z\u00fcrich",
    "wof:name":"Treichler Hans-ulrich, Mechanische Werkst\u00e4tte.",
    "wof:placetype":"venue"
},
  "geometry": {"coordinates":[8.7623252869,47.2513313293],"type":"Point"}
}