{
  "type": "Feature",
  "properties": {
    "iso:country":"CH",
    "sg:address":"Forchstrasse 59",
    "sg:city":"Z\u00fcrich",
    "sg:orig_category":"Canalisation",
    "sg:phone":"+41 13896080",
    "sg:postcode":"8032",
    "sg:province":"Z\u00fcrich",
    "wof:name":"Wsa Ingenieure Und Planer Ag",
    "wof:placetype":"venue"
},
  "geometry": {"coordinates":[8.558452,47.362862],"type":"Point"}
}