{
  "type": "Feature",
  "properties": {
    "iso:country":"CH",
    "sg:address":"Via Frasca 10",
    "sg:city":"Lugano",
    "sg:orig_category":"Fachdetailhandel in Verkaufsr\u00e4umen Herstellung von sonstigen Kunststoffwaren",
    "sg:phone":"+41 91 922 68 20",
    "sg:postcode":"6900",
    "sg:province":"Ticino",
    "wof:name":"F & M Di Sciottola Franco",
    "wof:placetype":"venue"
},
  "geometry": {"coordinates":[8.954366684,46.006526947],"type":"Point"}
}