{
  "type": "Feature",
  "properties": {
    "iso:country":"CH",
    "sg:address":"Lang\u00e4cker 140",
    "sg:city":"Wettingen",
    "sg:orig_category":"Elektroinstallation Herstellung von nachrichtentechnischen Ger\u00e4ten U Einrichtungen",
    "sg:phone":"+41 56 437 39 39",
    "sg:postcode":"5430",
    "sg:province":"Aargau",
    "wof:name":"Ruosch Telefonie",
    "wof:placetype":"venue"
},
  "geometry": {"coordinates":[8.3362579346,47.4623222351],"type":"Point"}
}