{
  "type": "Feature",
  "properties": {
    "iso:country":"CH",
    "sg:address":"Ch\u00f6renmattweg 6",
    "sg:city":"Berikon",
    "sg:orig_category":"Informatikdienste Sonstige mit der Informatik verbundene T\u00e4tigkeiten",
    "sg:phone":"+41 56 631 62 92",
    "sg:postcode":"8965",
    "sg:province":"Aargau",
    "wof:name":"Information Solution Gmbh",
    "wof:placetype":"venue"
},
  "geometry": {"coordinates":[8.3669500351,47.3564872742],"type":"Point"}
}