{
  "type": "Feature",
  "properties": {
    "iso:country":"CH",
    "sg:address":"Sch\u00e4renmoosstrasse 105",
    "sg:city":"Z\u00fcrich",
    "sg:orig_category":"Werbeberatung",
    "sg:phone":"+41 21 695 23 40",
    "sg:postcode":"8052",
    "sg:province":"Z\u00fcrich",
    "wof:name":"Trans Marketing Services Sa",
    "wof:placetype":"venue"
},
  "geometry": {"coordinates":[6.5527820587,46.513168335],"type":"Point"}
}