{
  "type": "Feature",
  "properties": {
    "iso:country":"CH",
    "sg:address":"Luzernstrasse 35",
    "sg:city":"Hellb\u00fchl",
    "sg:orig_category":"Instandhaltung U Reparatur von Automobilen",
    "sg:phone":"+41 41 467 15 67",
    "sg:postcode":"6016",
    "sg:province":"Luzern",
    "wof:name":"Schaller & Kogler Ag",
    "wof:placetype":"venue"
},
  "geometry": {"coordinates":[8.2036657333,47.0733375549],"type":"Point"}
}