{
  "type": "Feature",
  "properties": {
    "iso:country":"CH",
    "sg:address":"Monbijoustrasse 68",
    "sg:city":"Bern",
    "sg:orig_category":"Verwaltung von Immobilien",
    "sg:postcode":"3007",
    "sg:province":"Bern",
    "wof:name":"Gesch\u00e4ftshaus-immobilien Ag",
    "wof:placetype":"venue"
},
  "geometry": {"coordinates":[7.4355602264,46.9406089783],"type":"Point"}
}