{
  "type": "Feature",
  "properties": {
    "iso:country":"CH",
    "sg:address":"Fischrain 88",
    "sg:city":"Ittigen",
    "sg:orig_category":"Reiseb\u00fcros U Reiseveranstalter",
    "sg:phone":"+41 31 922 08 78",
    "sg:postcode":"3063",
    "sg:province":"Bern",
    "wof:name":"Beldan B Ag",
    "wof:placetype":"venue"
},
  "geometry": {"coordinates":[7.4758119583,46.9774856567],"type":"Point"}
}