{
  "type": "Feature",
  "properties": {
    "iso:country":"CH",
    "sg:address":"Sevogelstrasse 121 4052 Basel. Postfach",
    "sg:city":"Basel",
    "sg:orig_category":"Herstellung von Maschinen f\u00fcr die Nahrungsmittel, Getr\u00e4nkeherstellung U die Tabakverarbeitung",
    "sg:postcode":"4051",
    "sg:province":"Basel-Stadt",
    "wof:name":"Keller H. & Co. Metzgerei-bedarfsartikel; Handel, Service An Metzgereimaschinen",
    "wof:placetype":"venue"
},
  "geometry": {"coordinates":[7.5990781784,47.5478477478],"type":"Point"}
}