{
  "type": "Feature",
  "properties": {
    "iso:country":"CH",
    "sg:address":"Chiss 9 7503 Samedan. Postfach 18",
    "sg:city":"Samedan",
    "sg:orig_category":"Elektroinstallation",
    "sg:phone":"+41 81 851 10 20",
    "sg:postcode":"7503",
    "sg:province":"Graubunden",
    "wof:name":"Elektrofachgesch\u00e4ft Merz Ag",
    "wof:placetype":"venue"
},
  "geometry": {"coordinates":[9.8693256378,46.5350646973],"type":"Point"}
}