{
  "type": "Feature",
  "properties": {
    "iso:country":"CH",
    "sg:address":"Alpbachstrasse 13",
    "sg:city":"Meiringen",
    "sg:orig_category":"RESTAURANTS: TEA-ROOMS",
    "sg:postcode":"3860",
    "sg:province":"Bern",
    "wof:name":"Martalo-salis A., Restaurant Post",
    "wof:placetype":"venue"
},
  "geometry": {"coordinates":[8.4528255463,47.2771987915],"type":"Point"}
}