{
  "type": "Feature",
  "properties": {
    "iso:country":"CH",
    "sg:address":"Almuesenacherstrasse 4",
    "sg:city":"M\u00e4genwil",
    "sg:orig_category":"Grosshandel mit Datenverarbeitungsger\u00e4ten Softwareentwicklung U beratung",
    "sg:phone":"+41 62 887 44 22",
    "sg:postcode":"5506",
    "sg:province":"Aargau",
    "wof:name":"Control Software Ag Rg Cad/cam-systemhaus",
    "wof:placetype":"venue"
},
  "geometry": {"coordinates":[8.2348155975,47.4154663086],"type":"Point"}
}