{
  "type": "Feature",
  "properties": {
    "iso:country":"CH",
    "sg:address":"Sassalstrasse 14",
    "sg:city":"Chur",
    "sg:orig_category":"Unclassifiable Establishments",
    "sg:phone":"+41 81 252 34 30",
    "sg:postcode":"7000",
    "sg:province":"Graubunden",
    "wof:name":"Seraina Collection Meng",
    "wof:placetype":"venue"
},
  "geometry": {"coordinates":[9.5454025269,46.8360366821],"type":"Point"}
}