{
  "type": "Feature",
  "properties": {
    "iso:country":"CH",
    "sg:address":"Unterstadt 22",
    "sg:city":"Sursee",
    "sg:orig_category":"Werbeagenturen Werbegrafikateliers",
    "sg:phone":"+41 41 921 20 03",
    "sg:postcode":"6210",
    "sg:province":"Luzern",
    "wof:name":"Hanspeter Bisig Grafik & Werbung",
    "wof:placetype":"venue"
},
  "geometry": {"coordinates":[8.1082296371,47.1725692749],"type":"Point"}
}