{
  "type": "Feature",
  "properties": {
    "iso:country":"CH",
    "sg:address":"See\u00e4cherstrasse 11",
    "sg:city":"Zurzach",
    "sg:orig_category":"Detailhandel mit M\u00f6beln U Haushaltsgegenst\u00e4nden Grosshandel mit M\u00f6beln, Wohnbedarf, Teppichen U Bode",
    "sg:phone":"+41 22 347 01 75",
    "sg:postcode":"5330",
    "sg:province":"Aargau",
    "wof:name":"Iel Theophanis Liaros.",
    "wof:placetype":"venue"
},
  "geometry": {"coordinates":[6.1530070305,46.188457489],"type":"Point"}
}