{
  "type": "Feature",
  "properties": {
    "addr:full":"Baumgarten Oberb\u00fctschel Bern 3088",
    "addr:postcode":"3088",
    "iso:country":"CH",
    "sg:address":"Baumgarten",
    "sg:city":"Oberb\u00fctschel",
    "sg:orig_category":"Bauschreinerei",
    "sg:phone":"+41 79 206 25 30",
    "sg:postcode":"3088",
    "sg:province":"Bern",
    "wof:name":"Jakob Stoller Schreinerei",
    "wof:placetype":"venue"
},
  "geometry": {"coordinates":[7.438948,46.821507],"type":"Point"}
}