{
  "type": "Feature",
  "properties": {
    "iso:country":"CH",
    "sg:address":"Trichtenhauserstrasse 25 8125 Zollikerberg. Postfach",
    "sg:city":"Zollikerberg",
    "sg:classifiers":[
        {
            "category":"Professional",
            "subcategory":"Employment Agencies",
            "type":"Services"
        }
    ],
    "sg:postcode":"8125",
    "sg:province":"Z\u00fcrich",
    "sg:tags":[
        "personal",
        "u",
        "stellenvermittlung"
    ],
    "wof:name":"Internet Jobs Hersiczky",
    "wof:placetype":"venue"
},
  "geometry": {"coordinates":[8.5959844589,47.3493423462],"type":"Point"}
}