{
  "type": "Feature",
  "properties": {
    "addr:full":"Oberdorfstrasse 57 M\u00fcnchenbuchsee Bern 3053",
    "addr:housenumber":"57",
    "addr:postcode":"3053",
    "addr:street":"Oberdorfstrasse",
    "iso:country":"CH",
    "sg:address":"Oberdorfstrasse 57",
    "sg:city":"M\u00fcnchenbuchsee",
    "sg:orig_category":"Arztpraxen",
    "sg:phone":"+41 31 869 16 11",
    "sg:postcode":"3053",
    "sg:province":"Bern",
    "wof:name":"Dr.med.samuel Kohler Arzt F\u00fcr Allgemeine Medizin",
    "wof:placetype":"venue"
},
  "geometry": {"coordinates":[7.442062,47.019676],"type":"Point"}
}