{
  "type": "Feature",
  "properties": {
    "iso:country":"CH",
    "sg:address":"Centralbahnplatz 8",
    "sg:city":"Basel",
    "sg:orig_category":"Non-Classified Establishments",
    "sg:postcode":"4051",
    "sg:province":"Basel-Stadt",
    "wof:name":"Prs Ag, Zweigniederlassung Basel Centralbahnplatz",
    "wof:placetype":"venue"
},
  "geometry": {"coordinates":[7.5898227692,47.5481834412],"type":"Point"}
}