{
  "type": "Feature",
  "properties": {
    "iso:country":"CH",
    "sg:address":"Breitenbachstrasse 38",
    "sg:city":"B\u00fcsserach",
    "sg:classifiers":[
        {
            "category":"Banks & Credit Unions",
            "subcategory":"Bank",
            "type":"Services"
        }
    ],
    "sg:phone":"+41 61 781 12 52",
    "sg:postcode":"4227",
    "sg:province":"Solothurn",
    "wof:name":"Raiffeisenbank B\u00fcsserach",
    "wof:placetype":"venue"
},
  "geometry": {"coordinates":[7.541777,47.394676],"type":"Point"}
}