{
  "type": "Feature",
  "properties": {
    "iso:country":"CH",
    "sg:address":"Steinackerstrasse 38",
    "sg:city":"Urdorf",
    "sg:orig_category":"Herstellung von medizinischen U chirurgischen Ger\u00e4ten sowie orthop\u00e4dischen Vorrichtungen Zahntechnis",
    "sg:phone":"+41 61 711 00 30",
    "sg:postcode":"8902",
    "sg:province":"Z\u00fcrich",
    "wof:name":"Spalinger Dentalkeramik",
    "wof:placetype":"venue"
},
  "geometry": {"coordinates":[7.5929889679,47.4970932007],"type":"Point"}
}