{
  "type": "Feature",
  "properties": {
    "iso:country":"CH",
    "sg:address":"Altes Schulhaus 9114 Hoffeld. Postfach",
    "sg:city":"Hoffeld",
    "sg:orig_category":"Softwareentwicklung U beratung",
    "sg:phone":"+41 71 244 40 26",
    "sg:postcode":"9114",
    "sg:province":"St. Gallen",
    "wof:name":"Frei Marcel Computer And Support Mfa",
    "wof:placetype":"venue"
},
  "geometry": {"coordinates":[9.1736860275,47.3633041382],"type":"Point"}
}