{
  "type": "Feature",
  "properties": {
    "iso:country":"CH",
    "sg:address":"Steinrain 2 4663 Aarburg. Postfach 120",
    "sg:city":"Aarburg",
    "sg:orig_category":"Herstellung von Baubedarfsartikeln aus Kunststoff",
    "sg:phone":"+41 62 791 56 01",
    "sg:postcode":"4663",
    "sg:province":"Aargau",
    "wof:name":"G. Iseli Tor Und Storenbau",
    "wof:placetype":"venue"
},
  "geometry": {"coordinates":[7.9030818939,47.3213806152],"type":"Point"}
}