{
  "type": "Feature",
  "properties": {
    "iso:country":"CH",
    "sg:address":"Hebelstrasse 81",
    "sg:city":"Basel",
    "sg:classifiers":[
        {
            "category":"Building & Trades",
            "subcategory":"Plumbing",
            "type":"Services"
        }
    ],
    "sg:phone":"+41 71 244 25 01",
    "sg:postcode":"4056",
    "sg:province":"Basel-Stadt",
    "sg:tags":[
        "dehumidification"
    ],
    "wof:name":"Anderegg Mauersanierungen Ag",
    "wof:placetype":"venue"
},
  "geometry": {"coordinates":[9.386346,47.434315],"type":"Point"}
}