{
  "type": "Feature",
  "properties": {
    "iso:country":"CH",
    "sg:address":"Dorfplatz 8 4144 Arlesheim. Postfach 408",
    "sg:city":"Arlesheim",
    "sg:orig_category":"Detailhandel mit B\u00fcchern, Zeitungen, Schreib U Papeteriewaren",
    "sg:phone":"+41 61 701 14 32",
    "sg:postcode":"4144",
    "sg:province":"Basel-Landschaft",
    "wof:name":"Buchhandlung Gysel Ag",
    "wof:placetype":"venue"
},
  "geometry": {"coordinates":[7.62072,47.493412],"type":"Point"}
}