{
  "type": "Feature",
  "properties": {
    "iso:country":"CH",
    "sg:address":"Imhofstrasse 20",
    "sg:city":"Aarau",
    "sg:orig_category":"Grosshandel mit sonstigen Gebrauchs U Verbrauchsg\u00fctern",
    "sg:phone":"+41 62 824 20 09",
    "sg:postcode":"5000",
    "sg:province":"Aargau",
    "wof:name":"Rolf Richner",
    "wof:placetype":"venue"
},
  "geometry": {"coordinates":[8.0566473007,47.3840255737],"type":"Point"}
}