{
  "type": "Feature",
  "properties": {
    "iso:country":"CH",
    "sg:address":"Tschuepis",
    "sg:city":"Zwischenfl\u00fch",
    "sg:orig_category":"Grosshandel mit lebenden Tieren",
    "sg:phone":"+41 33 684 11 20",
    "sg:postcode":"3756",
    "sg:province":"Bern",
    "wof:name":"Hans Wampfler Viehhandel",
    "wof:placetype":"venue"
},
  "geometry": {"coordinates":[7.5133800507,46.6063117981],"type":"Point"}
}