{
  "type": "Feature",
  "properties": {
    "iso:country":"CH",
    "sg:address":"Bodmerweg 82",
    "sg:city":"Freienbach",
    "sg:orig_category":"Gartenbau",
    "sg:phone":"+41 55 410 12 35",
    "sg:postcode":"8807",
    "sg:province":"Schwyz",
    "wof:name":"K\u00fcmin Gartenbau Ag",
    "wof:placetype":"venue"
},
  "geometry": {"coordinates":[8.7675142288,47.204574585],"type":"Point"}
}