{
  "type": "Feature",
  "properties": {
    "iso:country":"CH",
    "sg:address":"Postgasse 21",
    "sg:city":"Glarus",
    "sg:orig_category":"Allgemeiner Hoch U Tiefbau",
    "sg:postcode":"8750",
    "sg:province":"Glarus",
    "wof:name":"Gig Generalunternehmung Immobilien Gesellschaft",
    "wof:placetype":"venue"
},
  "geometry": {"coordinates":[9.067823,47.040886],"type":"Point"}
}