{
  "type": "Feature",
  "properties": {
    "iso:country":"CH",
    "sg:address":"Niederhaslistrasse 10 8105 Watt. Postfach",
    "sg:city":"Baden",
    "sg:orig_category":"Vereine Vogel-& Naturschutz",
    "sg:phone":"+41 18703395",
    "sg:postcode":"5403",
    "wof:name":"Natur-& Vogelschutzverein Baden/ettenbaden",
    "wof:placetype":"venue"
},
  "geometry": {"coordinates":[8.4820365906,47.4440917969],"type":"Point"}
}