{
  "type": "Feature",
  "properties": {
    "iso:country":"CH",
    "sg:address":"Rte De Neuch\u00e2tel 9",
    "sg:city":"Cressier",
    "sg:classifiers":[
        {
            "category":"Banks & Credit Unions",
            "subcategory":"Bank",
            "type":"Services"
        }
    ],
    "sg:phone":"+41 38471770",
    "sg:postcode":"2088",
    "sg:province":"Neuch\u00e2tel",
    "wof:name":"Banque Cantonale, Neuch\u00e2teloise",
    "wof:placetype":"venue"
},
  "geometry": {"coordinates":[7.037546,47.050873],"type":"Point"}
}