{
  "type": "Feature",
  "properties": {
    "iso:country":"CH",
    "sg:address":"Dorfstrasse 10 + 13",
    "sg:city":"Kloten",
    "sg:orig_category":"Instandhaltung U Reparatur von Automobilen",
    "sg:phone":"+41 18131221",
    "sg:postcode":"8302",
    "sg:province":"Z\u00fcrich",
    "wof:name":"Koch Walter-autos Kloten Ag",
    "wof:placetype":"venue"
},
  "geometry": {"coordinates":[8.5818576813,47.4534912109],"type":"Point"}
}