{
  "type": "Feature",
  "properties": {
    "iso:country":"CH",
    "sg:address":"Avenue De France 8",
    "sg:city":"Sion",
    "sg:classifiers":[
        {
            "category":"Restaurant",
            "type":"Food & Drink"
        }
    ],
    "sg:phone":"+41 27 322 20 42",
    "sg:postcode":"1950",
    "sg:province":"Valais",
    "wof:name":"Pizzeria De La Poste",
    "wof:placetype":"venue"
},
  "geometry": {"coordinates":[7.3579192162,46.228225708],"type":"Point"}
}