{
  "type": "Feature",
  "properties": {
    "iso:country":"CH",
    "sg:address":"Sonnenbergstrasse 14",
    "sg:city":"Rorschacherberg",
    "sg:orig_category":"Gartenbau",
    "sg:phone":"+41 71 855 44 47",
    "sg:postcode":"9404",
    "sg:province":"St. Gallen",
    "wof:name":"Lehag Ag",
    "wof:placetype":"venue"
},
  "geometry": {"coordinates":[9.5065965652,47.4685173035],"type":"Point"}
}