{
  "type": "Feature",
  "properties": {
    "iso:country":"CH",
    "sg:address":"Lorraineweg",
    "sg:city":"B\u00e4tterkinden",
    "sg:orig_category":"Kauf U Verkauf von Immobilien auf eigene Rechnung",
    "sg:postcode":"3315",
    "sg:province":"Bern",
    "wof:name":"Wyharu Ag",
    "wof:placetype":"venue"
},
  "geometry": {"coordinates":[7.538438797,47.1399765015],"type":"Point"}
}