{
  "type": "Feature",
  "properties": {
    "iso:country":"CH",
    "sg:address":"Talbachstrasse 49",
    "sg:city":"Altendorf",
    "sg:orig_category":"Elektroinstallation",
    "sg:phone":"+41 79 420 88 58",
    "sg:postcode":"8852",
    "sg:province":"Schwyz",
    "wof:name":"Elektro Walker",
    "wof:placetype":"venue"
},
  "geometry": {"coordinates":[8.808719635,47.194858551],"type":"Point"}
}