{
  "type": "Feature",
  "properties": {
    "iso:country":"CH",
    "sg:address":"Grand'rue 13",
    "sg:city":"Moudon",
    "sg:orig_category":"Drogerien Parf\u00fcmerien U sonstiger Detailhandel mit kosmetischen Artikeln U K\u00f6rperpflegemitteln",
    "sg:phone":"+41 21 905 12 94",
    "sg:postcode":"1510",
    "sg:province":"Vaud",
    "wof:name":"Andr\u00e9 Christen Droguerie-parfumerie",
    "wof:placetype":"venue"
},
  "geometry": {"coordinates":[6.7962222099,46.6697273254],"type":"Point"}
}