{
  "type": "Feature",
  "properties": {
    "iso:country":"CH",
    "sg:address":"H\u00f6rstetten",
    "sg:city":"Unterh\u00f6rstetten",
    "sg:orig_category":"Elektrizit\u00e4tsversorgung",
    "sg:postcode":"8508",
    "sg:province":"Thurgau",
    "wof:name":"Elektra-genossenschaft H\u00f6rstetten Und Umgebung",
    "wof:placetype":"venue"
},
  "geometry": {"coordinates":[9.0095596313,47.6344146729],"type":"Point"}
}