{
  "type": "Feature",
  "properties": {
    "iso:country":"CH",
    "sg:address":"Amselweg 6",
    "sg:city":"Arlesheim",
    "sg:orig_category":"Grosshandel mit chemischen Erzeugnissen",
    "sg:phone":"+41 61 703 19 80",
    "sg:postcode":"4144",
    "sg:province":"Basel-Landschaft",
    "wof:name":"Kern Trade Consult",
    "wof:placetype":"venue"
},
  "geometry": {"coordinates":[7.624973774,47.4872055054],"type":"Point"}
}