{
  "type": "Feature",
  "properties": {
    "iso:country":"CH",
    "sg:address":"Dorf 3439 Ranfl\u00fch. Postfach",
    "sg:city":"Ranfl\u00fch",
    "sg:orig_category":"RESTAURANTS: TEA-ROOMS",
    "sg:postcode":"3439",
    "sg:province":"Bern",
    "wof:name":"Willfratt & Willfratt",
    "wof:placetype":"venue"
},
  "geometry": {"coordinates":[7.7403659821,46.9863319397],"type":"Point"}
}