{
  "type": "Feature",
  "properties": {
    "iso:country":"CH",
    "sg:address":"2615 Montagne-sonvilier Case Postale 39",
    "sg:city":"Montagne-sonvilier",
    "sg:classifiers":[
        {
            "category":"Education",
            "subcategory":"Library",
            "type":"Public Place"
        }
    ],
    "sg:phone":"+41 9411973",
    "sg:postcode":"2615",
    "sg:province":"Bern",
    "sg:tags":[
        "u",
        "bibliotheken",
        "archive"
    ],
    "wof:name":"Biblioth\u00e8que Communale",
    "wof:placetype":"venue"
},
  "geometry": {"coordinates":[6.964344,47.138897],"type":"Point"}
}