{
  "type": "Feature",
  "properties": {
    "iso:country":"CH",
    "sg:address":"Vergi\u00f2 Via 29",
    "sg:city":"Breganzona",
    "sg:orig_category":"Verwaltung von Immobilien",
    "sg:postcode":"6932",
    "sg:province":"Ticino",
    "wof:name":"Cbr Cris Sagl",
    "wof:placetype":"venue"
},
  "geometry": {"coordinates":[8.9328699112,46.0121231079],"type":"Point"}
}