{
  "type": "Feature",
  "properties": {
    "iso:country":"CH",
    "sg:address":"Avenue Du Midi 7 1950 Sion Case Postale 340",
    "sg:city":"Sion",
    "sg:orig_category":"Arbeits\u00e4mter",
    "sg:phone":"+41 21 316 61 04",
    "sg:postcode":"1951",
    "sg:province":"Valais",
    "wof:name":"Office Cantonal Du Travail",
    "wof:placetype":"venue"
},
  "geometry": {"coordinates":[6.63345,46.519428],"type":"Point"}
}