{
  "type": "Feature",
  "properties": {
    "iso:country":"CH",
    "sg:address":"Chemin De Pierrefleur 30",
    "sg:city":"Lausanne",
    "sg:classifiers":[
        {
            "category":"Restaurant",
            "type":"Food & Drink"
        }
    ],
    "sg:phone":"+41 21 646 99 66",
    "sg:postcode":"1004",
    "sg:province":"Vaud",
    "wof:name":"Caf\u00e9 Le Pierrefleur",
    "wof:placetype":"venue"
},
  "geometry": {"coordinates":[6.6167159081,46.5348625183],"type":"Point"}
}