{
  "type": "Feature",
  "properties": {
    "iso:country":"CH",
    "sg:address":"Vazerolgasse 2",
    "sg:city":"Chur",
    "sg:orig_category":"Herstellung von sonstigen Maschinen f\u00fcr unspezifische Verwendung",
    "sg:postcode":"7000",
    "sg:province":"Graubunden",
    "wof:name":"Interplan Ag",
    "wof:placetype":"venue"
},
  "geometry": {"coordinates":[9.5329093933,46.8505897522],"type":"Point"}
}