{
  "type": "Feature",
  "properties": {
    "iso:country":"CH",
    "sg:address":"Route Du P\u00e9age 11",
    "sg:city":"Sugiez",
    "sg:orig_category":"Polizei",
    "sg:phone":"+41 26 673 14 48",
    "sg:postcode":"1786",
    "sg:province":"Fribourg",
    "wof:name":"Police Cantonale",
    "wof:placetype":"venue"
},
  "geometry": {"coordinates":[7.1184878349,46.9650421143],"type":"Point"}
}