{
  "type": "Feature",
  "properties": {
    "iso:country":"CH",
    "sg:address":"Erlenweg 8",
    "sg:city":"Biel/bienne",
    "sg:orig_category":"Fachdetailhandel in Verkaufsr\u00e4umen",
    "sg:postcode":"2500",
    "sg:province":"Bern",
    "wof:name":"Acamar, Blanc Andr\u00e9",
    "wof:placetype":"venue"
},
  "geometry": {"coordinates":[7.2533631325,47.1235580444],"type":"Point"}
}