{
  "type": "Feature",
  "properties": {
    "iso:country":"CH",
    "sg:address":"Altweg",
    "sg:city":"Schwaderloch",
    "sg:orig_category":"Primarschulen",
    "sg:phone":"+41 56 247 15 88",
    "sg:postcode":"5326",
    "sg:province":"Aargau",
    "wof:name":"Primarschule",
    "wof:placetype":"venue"
},
  "geometry": {"coordinates":[8.1471300125,47.5871276855],"type":"Point"}
}