{
  "type": "Feature",
  "properties": {
    "iso:country":"CH",
    "sg:address":"Via Cantonale 35d",
    "sg:city":"Manno",
    "sg:orig_category":"Non-Classified Establishments",
    "sg:postcode":"6928",
    "sg:province":"Ticino",
    "wof:name":"Pippo Sagl",
    "wof:placetype":"venue"
},
  "geometry": {"coordinates":[8.9187498093,46.028137207],"type":"Point"}
}