{
  "type": "Feature",
  "properties": {
    "iso:country":"CH",
    "sg:address":"1512",
    "sg:city":"Chavannes-s-moudon",
    "sg:orig_category":"Vereine Frauen Vereine Gemeinn\u00fctzige",
    "sg:phone":"+41 21 905 21 61",
    "sg:postcode":"1512",
    "sg:province":"Vaud",
    "wof:name":"Assoc.moudonnoise D.paysannes",
    "wof:placetype":"venue"
},
  "geometry": {"coordinates":[6.7937831879,46.6538200378],"type":"Point"}
}