{
  "type": "Feature",
  "properties": {
    "addr:full":"Etzelstrasse 15 Horgen Z\u00fcrich 8810",
    "addr:housenumber":"15",
    "addr:postcode":"8810",
    "addr:street":"Etzelstrasse",
    "iso:country":"CH",
    "sg:address":"Etzelstrasse 15",
    "sg:city":"Horgen",
    "sg:orig_category":"Architektur U Ingenieurb\u00fcros",
    "sg:phone":"+41 17252552",
    "sg:postcode":"8810",
    "sg:province":"Z\u00fcrich",
    "wof:name":"Huber H.-j., Planungsb\u00fcro F\u00fcr Theater Und Lichttechnik",
    "wof:placetype":"venue"
},
  "geometry": {"coordinates":[8.59917,47.252651],"type":"Point"}
}