{
  "type": "Feature",
  "properties": {
    "iso:country":"CH",
    "sg:address":"W\u00fchre 107",
    "sg:city":"D\u00fcrren\u00e4sch",
    "sg:orig_category":"Politische Parteien SVP",
    "sg:phone":"+41 62 777 27 05",
    "sg:postcode":"5724",
    "sg:province":"Aargau",
    "wof:name":"Svp Ortspartei D\u00fcrren\u00e4sch",
    "wof:placetype":"venue"
},
  "geometry": {"coordinates":[8.1551942825,47.3221435547],"type":"Point"}
}