{
  "type": "Feature",
  "properties": {
    "iso:country":"CH",
    "sg:address":"Schwadernaustr 37 2558 Aegerten. Postfach",
    "sg:city":"Aegerten",
    "sg:orig_category":"Herstellung von Mess U Kontrollinstrumenten U vorrichtungen",
    "sg:phone":"+41 31 302 54 18",
    "sg:postcode":"2558",
    "sg:province":"Bern",
    "wof:name":"Pedos Ag",
    "wof:placetype":"venue"
},
  "geometry": {"coordinates":[7.485449791,46.9274940491],"type":"Point"}
}