{
  "type": "Feature",
  "properties": {
    "iso:country":"CH",
    "sg:address":"Schw\u00e4rzistrasse 11",
    "sg:city":"N\u00e4fels",
    "sg:orig_category":"Zimmerei, Dachdeckerei, Bauspenglerei U Abdichtung",
    "sg:phone":"+41 55 612 17 75",
    "sg:postcode":"8752",
    "sg:province":"Glarus",
    "wof:name":"Fischli Bedachungen Ag",
    "wof:placetype":"venue"
},
  "geometry": {"coordinates":[9.0704231262,47.1065292358],"type":"Point"}
}