{
  "type": "Feature",
  "properties": {
    "iso:country":"CH",
    "sg:address":"Kempttalstrasse 79",
    "sg:city":"Fehraltorf",
    "sg:orig_category":"Fachdetailhandel mit pharmazeutischen Produkten",
    "sg:phone":"+41 79 693 11 11",
    "sg:postcode":"8320",
    "sg:province":"Z\u00fcrich",
    "wof:name":"Linden Apotheke Peter + Bonhage Gmbh",
    "wof:placetype":"venue"
},
  "geometry": {"coordinates":[8.7534627914,47.3873519897],"type":"Point"}
}