{
  "type": "Feature",
  "properties": {
    "iso:country":"CH",
    "sg:address":"Lauriedstrasse 1 6300 Zug. Postfach",
    "sg:city":"Zug",
    "sg:orig_category":"Grosshandel mit chemischen Erzeugnissen",
    "sg:phone":"+41 41 710 82 15",
    "sg:postcode":"6301",
    "sg:province":"Zug",
    "wof:name":"Chemicom Export-import Ag",
    "wof:placetype":"venue"
},
  "geometry": {"coordinates":[8.5178022385,47.1739501953],"type":"Point"}
}