{
  "type": "Feature",
  "properties": {
    "iso:country":"CH",
    "sg:address":"Waisenhausstrasse 2",
    "sg:city":"Thun",
    "sg:orig_category":"Wirtschaftspr\u00fcfung, Steuerberatung U Treuhand",
    "sg:phone":"+41 33 222 04 34",
    "sg:postcode":"3600",
    "sg:province":"Bern",
    "wof:name":"Beat Schmid Treuhand Ag",
    "wof:placetype":"venue"
},
  "geometry": {"coordinates":[7.6261138916,46.7549057007],"type":"Point"}
}