{
  "type": "Feature",
  "properties": {
    "iso:country":"CH",
    "sg:address":"Unterdorf 91",
    "sg:city":"Stilli",
    "sg:orig_category":"Elektroinstallation",
    "sg:postcode":"5233",
    "sg:province":"Aargau",
    "wof:name":"R. Bryner Fenstermontage",
    "wof:placetype":"venue"
},
  "geometry": {"coordinates":[8.2320661545,47.5146484375],"type":"Point"}
}