{
  "type": "Feature",
  "properties": {
    "iso:country":"CH",
    "sg:address":"Poststrasse 6",
    "sg:city":"Uster",
    "sg:orig_category":"Non-Classified Establishments",
    "sg:postcode":"8610",
    "sg:province":"Z\u00fcrich",
    "wof:name":"Accresco Holding Ag",
    "wof:placetype":"venue"
},
  "geometry": {"coordinates":[8.7765932083,47.2011795044],"type":"Point"}
}