{
  "type": "Feature",
  "properties": {
    "iso:country":"CH",
    "sg:address":"Chemin Du Rosey 5 1180 Rolle Case Postale 157",
    "sg:city":"Rolle",
    "sg:orig_category":"Bauschreinerei Hobel U Holzimpr\u00e4gnierwerke",
    "sg:phone":"+41 79 417 15 34",
    "sg:postcode":"1180",
    "sg:province":"Vaud",
    "wof:name":"Jotterand Guy",
    "wof:placetype":"venue"
},
  "geometry": {"coordinates":[6.335144,46.456299],"type":"Point"}
}