{
  "type": "Feature",
  "properties": {
    "iso:country":"CH",
    "sg:address":"Ankerstrasse 6",
    "sg:city":"Bern",
    "sg:orig_category":"Interessenvertretungen",
    "sg:postcode":"3006",
    "sg:province":"Bern",
    "wof:name":"Tmb Techniques Multidisciplinaires Du B\u00e2timent, Infrastructures Et \u00e9quipements, Ing\u00e9nieurs Et Techniciens, Conseils Associ\u00e9s",
    "wof:placetype":"venue"
},
  "geometry": {"coordinates":[6.8187499046,47.1026115417],"type":"Point"}
}