{
  "type": "Feature",
  "properties": {
    "iso:country":"CH",
    "sg:address":"Ziegelbr\u00fcckstrasse 22a",
    "sg:city":"Niederurnen",
    "sg:orig_category":"Handels-H\u00e4user U Gesellschaften",
    "sg:postcode":"8867",
    "sg:province":"Glarus",
    "wof:name":"Binnie And Partners Ag",
    "wof:placetype":"venue"
},
  "geometry": {"coordinates":[9.0556774139,47.1275749207],"type":"Point"}
}