{
  "type": "Feature",
  "properties": {
    "iso:country":"CH",
    "sg:address":"Via Maistra 16",
    "sg:city":"Bever",
    "sg:orig_category":"Allgemeiner Hochbau Bauschreinerei",
    "sg:phone":"+41 81 852 40 86",
    "sg:postcode":"7502",
    "sg:province":"Graubunden",
    "wof:name":"P. Lenatti Ag Bauunternehmung",
    "wof:placetype":"venue"
},
  "geometry": {"coordinates":[9.889341,46.551899],"type":"Point"}
}