{
  "type": "Feature",
  "properties": {
    "iso:country":"CH",
    "sg:address":"Ebenaustrasse 10",
    "sg:city":"Horw",
    "sg:orig_category":"Fachdetailhandel in Verkaufsr\u00e4umen",
    "sg:phone":"+41 41 340 81 92",
    "sg:postcode":"6048",
    "sg:province":"Luzern",
    "wof:name":"Koller Audiovision",
    "wof:placetype":"venue"
},
  "geometry": {"coordinates":[8.3079395294,47.0138587952],"type":"Point"}
}