{
  "type": "Feature",
  "properties": {
    "iso:country":"CH",
    "sg:address":"Signaustrasse 9",
    "sg:city":"Z\u00fcrich",
    "sg:orig_category":"Grosshandel mit chemischen Erzeugnissen",
    "sg:postcode":"8008",
    "sg:province":"Z\u00fcrich",
    "wof:name":"Hug & Co. Kunststoff-import",
    "wof:placetype":"venue"
},
  "geometry": {"coordinates":[8.5564956665,47.3631401062],"type":"Point"}
}