{
  "type": "Feature",
  "properties": {
    "iso:country":"CH",
    "sg:address":"Rond-point De Plainpalais 4",
    "sg:city":"Gen\u00e8ve",
    "sg:orig_category":"Detailhandel mit Geschenkartikeln U Souvenirs Detailhandel mit Spielwaren",
    "sg:phone":"+41 22 329 29 21",
    "sg:postcode":"1205",
    "sg:province":"Gen\u00e8ve",
    "wof:name":"Au Coeur De Bois Sarl",
    "wof:placetype":"venue"
},
  "geometry": {"coordinates":[6.1427340508,46.1976585388],"type":"Point"}
}