{
  "type": "Feature",
  "properties": {
    "iso:country":"CH",
    "sg:address":"Gartenweg 1",
    "sg:city":"Unterentfelden",
    "sg:orig_category":"Herstellung von Metallkonstruktionen",
    "sg:phone":"+41 71 911 72 48",
    "sg:postcode":"5035",
    "sg:province":"Aargau",
    "wof:name":"Locher Karl",
    "wof:placetype":"venue"
},
  "geometry": {"coordinates":[9.0567455292,47.4685173035],"type":"Point"}
}