{
  "type": "Feature",
  "properties": {
    "iso:country":"CH",
    "sg:address":"Paradiesgasse 24 7000 Chur. Postfach",
    "sg:city":"Chur",
    "sg:orig_category":"Unclassifiable Establishments",
    "sg:postcode":"7000",
    "sg:province":"Graubunden",
    "wof:name":"Nail Art, Scialdone Daniela Nagelkosmetik Usw",
    "wof:placetype":"venue"
},
  "geometry": {"coordinates":[9.5314674377,46.8480415344],"type":"Point"}
}