{
  "type": "Feature",
  "properties": {
    "iso:country":"CH",
    "sg:address":"Ahornstrasse 15 4055 Basel. Postfach 223",
    "sg:city":"Basel",
    "sg:orig_category":"Elektroinstallation Herstellung von Elektromotoren, Generatoren U Transformatoren",
    "sg:phone":"+41 61 301 43 39",
    "sg:postcode":"4009",
    "sg:province":"Basel-Stadt",
    "wof:name":"Magnani Gianni, Vormals Buchwalder R.",
    "wof:placetype":"venue"
},
  "geometry": {"coordinates":[7.5740399361,47.5572319031],"type":"Point"}
}