{
  "type": "Feature",
  "properties": {
    "iso:country":"CH",
    "sg:address":"Pillonweg 17 3014 Bern. Postfach",
    "sg:city":"Bern",
    "sg:orig_category":"Herstellung von Schmuck, Gold U Silberschmiedwaren",
    "sg:phone":"+41 31 332 69 25",
    "sg:postcode":"3014",
    "sg:province":"Bern",
    "wof:name":"Espagravur Torres Nilda Gravuren, Seriegraphie, Tampodruck; Anfertigungen Usw.",
    "wof:placetype":"venue"
},
  "geometry": {"coordinates":[7.4478211403,46.9671325684],"type":"Point"}
}