{
  "type": "Feature",
  "properties": {
    "iso:country":"CH",
    "sg:address":"Z\u00fcrichstrasse 23c 2504 Biel/bienne. Postfach",
    "sg:city":"Biel/bienne",
    "sg:orig_category":"Sonstiges Versicherungsgewerbe",
    "sg:postcode":"2502",
    "sg:province":"Bern",
    "wof:name":"Axa Versicherungen, Generalagentur, Hirsbrunner R.",
    "wof:placetype":"venue"
},
  "geometry": {"coordinates":[7.291864872,47.16173172],"type":"Point"}
}