{
  "type": "Feature",
  "properties": {
    "iso:country":"CH",
    "sg:address":"Nidaustrasse 47",
    "sg:city":"Biel/bienne",
    "sg:orig_category":"Detailhandel mit Haustieren U zoologischem Bedarf",
    "sg:postcode":"2502",
    "sg:province":"Bern",
    "wof:name":"Qualipet Ag Haustierbedarfs-center Zoo-oberwil",
    "wof:placetype":"venue"
},
  "geometry": {"coordinates":[7.555352211,47.5109443665],"type":"Point"}
}