{
  "type": "Feature",
  "properties": {
    "iso:country":"CH",
    "sg:address":"Bleichestrasse 15",
    "sg:city":"Kreuzlingen",
    "sg:orig_category":"Drogerien Fachdetailhandel mit pharmazeutischen Produkten",
    "sg:phone":"+41 71 688 35 35",
    "sg:postcode":"8280",
    "sg:province":"Thurgau",
    "wof:name":"Apotheke Drogerie Parf\u00fcmerie Strickler Ag",
    "wof:placetype":"venue"
},
  "geometry": {"coordinates":[9.1963224411,47.6417884827],"type":"Point"}
}