{
  "type": "Feature",
  "properties": {
    "iso:country":"CH",
    "sg:address":"Brunaustrasse 184 8951 Fahrweid. Postfach",
    "sg:city":"Fahrweid",
    "sg:orig_category":"Betrieb U technische Hilfsdienste des Kultur U Unterhaltungswesens",
    "sg:postcode":"8951",
    "sg:province":"Z\u00fcrich",
    "wof:name":"D. Rotzinger Tontechnik",
    "wof:placetype":"venue"
},
  "geometry": {"coordinates":[8.638442,47.241497],"type":"Point"}
}