{
  "type": "Feature",
  "properties": {
    "iso:country":"CH",
    "sg:address":"Fr\u00e9d\u00e9ric-ingold-weg 5 U. 5a 2500 Biel/bienne. Postfach",
    "sg:city":"Biel/bienne",
    "sg:orig_category":"Herstellung von Uhren",
    "sg:postcode":"2500",
    "sg:province":"Bern",
    "wof:name":"Golay Spierer Sa",
    "wof:placetype":"venue"
},
  "geometry": {"coordinates":[6.1397509575,46.1864089966],"type":"Point"}
}