{
  "type": "Feature",
  "properties": {
    "iso:country":"CH",
    "sg:address":"Pl. De La Couronne 6",
    "sg:city":"Echallens",
    "sg:orig_category":"Reinigungsgewerbe Sonstiges Reinigungsgewerbe",
    "sg:phone":"+41 21 886 12 50",
    "sg:postcode":"1040",
    "sg:province":"Vaud",
    "wof:name":"Comas - D\u00e9sinfection",
    "wof:placetype":"venue"
},
  "geometry": {"coordinates":[6.6366658211,46.6409912109],"type":"Point"}
}