{
  "type": "Feature",
  "properties": {
    "iso:country":"CH",
    "sg:address":"Freie Strasse 1",
    "sg:city":"Basel",
    "sg:orig_category":"Non-Classified Establishments",
    "sg:phone":"+41 61 261 61 74",
    "sg:postcode":"4001",
    "sg:province":"Basel-Stadt",
    "wof:name":"Sogipar Ag F\u00fcr Verwaltung Und Beteiligungen",
    "wof:placetype":"venue"
},
  "geometry": {"coordinates":[7.5885238647,47.5577507019],"type":"Point"}
}