{
  "type": "Feature",
  "properties": {
    "iso:country":"CH",
    "sg:address":"H\u00fcbeli",
    "sg:city":"Unterlangenegg",
    "sg:orig_category":"Bauschreinerei Herstellung von Konstruktionsteilen, Fertigbauteilen U Ausbauelementen aus Holz",
    "sg:phone":"+41 33 453 24 38",
    "sg:postcode":"3614",
    "sg:province":"Bern",
    "wof:name":"Gerber & Stettler Ag",
    "wof:placetype":"venue"
},
  "geometry": {"coordinates":[7.702569,46.796471],"type":"Point"}
}