{
  "type": "Feature",
  "properties": {
    "iso:country":"CH",
    "sg:address":"Obholzstrasse 1b",
    "sg:city":"Frauenfeld",
    "sg:orig_category":"Sportvereine Ballsport Handball",
    "sg:phone":"+41 52 730 09 99",
    "sg:postcode":"8500",
    "sg:province":"Thurgau",
    "wof:name":"Handballclub Ktv Frauenfeld",
    "wof:placetype":"venue"
},
  "geometry": {"coordinates":[8.9145965576,47.5463256836],"type":"Point"}
}