{
  "type": "Feature",
  "properties": {
    "iso:country":"CH",
    "sg:address":"Sihlquai 282",
    "sg:city":"Z\u00fcrich",
    "sg:orig_category":"Wirtschaftspr\u00fcfung, Steuerberatung U Treuhand",
    "sg:phone":"+41 12730128",
    "sg:postcode":"8005",
    "sg:province":"Z\u00fcrich",
    "wof:name":"Allbilanz, Gwerder Othmar",
    "wof:placetype":"venue"
},
  "geometry": {"coordinates":[8.5275554657,47.3893241882],"type":"Point"}
}