{
  "type": "Feature",
  "properties": {
    "iso:country":"CH",
    "sg:address":"Route Suisse 5",
    "sg:city":"Etoy",
    "sg:classifiers":[
        {
            "category":"Sports & Exercise",
            "subcategory":"Tennis Court",
            "type":"Entertainment"
        }
    ],
    "sg:phone":"+41 22 343 31 63",
    "sg:postcode":"1163",
    "sg:province":"Vaud",
    "sg:tags":[
        "squash-centers",
        "hallen",
        "tennis-"
    ],
    "wof:name":"Tennis Municipal De La Fontenette",
    "wof:placetype":"venue"
},
  "geometry": {"coordinates":[6.1511192322,46.1849403381],"type":"Point"}
}