{
  "type": "Feature",
  "properties": {
    "iso:country":"CH",
    "sg:address":"Mattenbachstrasse 6",
    "sg:city":"Winterthur",
    "sg:orig_category":"Datenverarbeitungsdienste Softwareentwicklung U beratung",
    "sg:phone":"+41 52 233 67 67",
    "sg:postcode":"8400",
    "sg:province":"Z\u00fcrich",
    "wof:name":"Ten Ag",
    "wof:placetype":"venue"
},
  "geometry": {"coordinates":[8.735312,47.494514],"type":"Point"}
}