{
  "type": "Feature",
  "properties": {
    "iso:country":"CH",
    "sg:address":"Buonaserstrasse 28a 6343 Rotkreuz. Postfach",
    "sg:city":"Rotkreuz",
    "sg:orig_category":"Dienstleistungen von Beteiligungsgesellschaften",
    "sg:phone":"+41 41 790 06 56",
    "sg:postcode":"6343",
    "sg:province":"Zug",
    "wof:name":"Pandora Ltd Liab Co Gesch\u00e4ftsfelder, Bes. Der Gruppe; Verwaltung, F\u00fchrung",
    "wof:placetype":"venue"
},
  "geometry": {"coordinates":[8.4349117279,47.1406936646],"type":"Point"}
}