{
  "type": "Feature",
  "properties": {
    "iso:country":"CH",
    "sg:address":"Tschudistrasse 32",
    "sg:city":"St.gallen",
    "sg:orig_category":"Herstellung von Teppichen",
    "sg:postcode":"9000",
    "sg:province":"St. Gallen",
    "wof:name":"Los Pl\u00e4ttlieros, R. Ferrer",
    "wof:placetype":"venue"
},
  "geometry": {"coordinates":[9.3643732071,47.4164543152],"type":"Point"}
}