{
  "type": "Feature",
  "properties": {
    "addr:full":"Ennetb\u00fcrgerstrasse 43 6374 Buochs. Postfach 142 Buochs Nidwalden 6374",
    "addr:housenumber":"43;142",
    "addr:postcode":"6374 buochs.;6374",
    "addr:street":"Ennetbuergerstrasse;Postfach",
    "iso:country":"CH",
    "sg:address":"Ennetb\u00fcrgerstrasse 43 6374 Buochs. Postfach 142",
    "sg:city":"Buochs",
    "sg:orig_category":"Detailhandel mit Brot, Back U S\u00fcsswaren",
    "sg:phone":"+41 56 622 59 25",
    "sg:postcode":"6374",
    "sg:province":"Nidwalden",
    "wof:name":"Beck Brume B\u00e4ckerei-konditorei",
    "wof:placetype":"venue"
},
  "geometry": {"coordinates":[8.268788,47.350464],"type":"Point"}
}