{
  "type": "Feature",
  "properties": {
    "iso:country":"CH",
    "sg:address":"Wil 10",
    "sg:city":"Muotathal",
    "sg:orig_category":"G\u00fcterbef\u00f6rderung im Strassenverkehr",
    "sg:postcode":"6436",
    "sg:province":"Schwyz",
    "wof:name":"Transportgemeinschaft Brugg Und Umgebung",
    "wof:placetype":"venue"
},
  "geometry": {"coordinates":[8.1788911819,47.4681015015],"type":"Point"}
}