{
  "type": "Feature",
  "properties": {
    "iso:country":"CH",
    "sg:address":"Stadthausgasse 6",
    "sg:city":"Schaffhausen",
    "sg:classifiers":[
        {
            "category":"Restaurant",
            "type":"Food & Drink"
        }
    ],
    "sg:phone":"+41 52 625 16 17",
    "sg:postcode":"8200",
    "sg:province":"Schaffhausen",
    "sg:tags":[
        "tea-rooms",
        "restaurants"
    ],
    "wof:name":"El Copero Gmbh",
    "wof:placetype":"venue"
},
  "geometry": {"coordinates":[8.6354131699,47.6970405579],"type":"Point"}
}