{
  "type": "Feature",
  "properties": {
    "iso:country":"CH",
    "sg:address":"Steinstrasse 25",
    "sg:city":"Z\u00fcrich",
    "sg:orig_category":"Non-Classified Establishments",
    "sg:postcode":"8003",
    "sg:province":"Z\u00fcrich",
    "wof:name":"Barbara Gessler Shiatsu",
    "wof:placetype":"venue"
},
  "geometry": {"coordinates":[8.5199728012,47.3675994873],"type":"Point"}
}