{
  "type": "Feature",
  "properties": {
    "iso:country":"CH",
    "sg:address":"Landstrasse 52",
    "sg:city":"Wettingen",
    "sg:orig_category":"Interessenvertretungen",
    "sg:phone":"+41 56 430 16 65",
    "sg:postcode":"5430",
    "sg:province":"Aargau",
    "wof:name":"Verein Neustart",
    "wof:placetype":"venue"
},
  "geometry": {"coordinates":[8.322265625,47.467666626],"type":"Point"}
}