{
  "type": "Feature",
  "properties": {
    "iso:country":"CH",
    "sg:address":"Ecluse Rue De L' 32",
    "sg:city":"Neuch\u00e2tel",
    "sg:orig_category":"Herstellung von sonstigen Holzwaren",
    "sg:phone":"+41 32 725 26 84",
    "sg:postcode":"2000",
    "sg:province":"Neuch\u00e2tel",
    "wof:name":"Au Tallipot Calderara",
    "wof:placetype":"venue"
},
  "geometry": {"coordinates":[6.9272999763,46.9934310913],"type":"Point"}
}