{
  "type": "Feature",
  "properties": {
    "iso:country":"CH",
    "sg:address":"Limmattalstrasse 197",
    "sg:city":"Z\u00fcrich",
    "sg:orig_category":"Unternehmensberatung",
    "sg:phone":"+41 13413118",
    "sg:postcode":"8049",
    "sg:province":"Z\u00fcrich",
    "wof:name":"Risk Consulting Group Gmbh Unternehmensberatung. Edv-software; Herstellung, Verkauf",
    "wof:placetype":"venue"
},
  "geometry": {"coordinates":[8.4979457855,47.4019165039],"type":"Point"}
}