{
  "type": "Feature",
  "properties": {
    "iso:country":"CH",
    "sg:address":"Ostring 12",
    "sg:city":"Regensdorf",
    "sg:orig_category":"Detailhandel mit M\u00f6beln Innenausbau",
    "sg:phone":"+41 61 961 01 48",
    "sg:postcode":"8105",
    "sg:province":"Z\u00fcrich",
    "wof:name":"M\u00fcller Georg M\u00f6bel Innenausbau Ag",
    "wof:placetype":"venue"
},
  "geometry": {"coordinates":[7.7479729652,47.3933410645],"type":"Point"}
}