{
  "type": "Feature",
  "properties": {
    "iso:country":"CH",
    "sg:address":"Mettliweg 5",
    "sg:city":"Uhwiesen",
    "sg:orig_category":"Vorschulen, Kinderg\u00e4rten",
    "sg:phone":"+41 61 717 81 20",
    "sg:postcode":"8248",
    "sg:province":"Z\u00fcrich",
    "wof:name":"Kindergarten",
    "wof:placetype":"venue"
},
  "geometry": {"coordinates":[7.5947918892,47.5021438599],"type":"Point"}
}