{
  "type": "Feature",
  "properties": {
    "iso:country":"CH",
    "sg:address":"Poststrasse 11",
    "sg:city":"Neuhausen",
    "sg:orig_category":"RESTAURANTS: TEA-ROOMS",
    "sg:phone":"+41 52 672 16 13",
    "sg:postcode":"8212",
    "sg:province":"Schaffhausen",
    "wof:name":"Camenisch Erich, Restaurant Hallauerhof",
    "wof:placetype":"venue"
},
  "geometry": {"coordinates":[8.6198511124,47.6829376221],"type":"Point"}
}