{
  "type": "Feature",
  "properties": {
    "iso:country":"CH",
    "sg:address":"Salita Viarno 3",
    "sg:city":"Pregassona",
    "sg:orig_category":"Architekturb\u00fcros",
    "sg:phone":"+41 91 971 55 73",
    "sg:postcode":"6963",
    "sg:province":"Ticino",
    "wof:name":"Walter Eberli Studio D'architettura",
    "wof:placetype":"venue"
},
  "geometry": {"coordinates":[8.96581,46.015938],"type":"Point"}
}