{
  "type": "Feature",
  "properties": {
    "iso:country":"CH",
    "sg:address":"Hauptstrasse 18 4585 Biezwil. Postfach",
    "sg:city":"Biezwil",
    "sg:classifiers":[
        {
            "category":"Travel",
            "subcategory":"Hotels & Motels",
            "type":"Entertainment"
        }
    ],
    "sg:phone":"+41 26 927 15 75",
    "sg:postcode":"4585",
    "sg:province":"Solothurn",
    "sg:tags":[
        "hotels",
        "mit",
        "restaurant"
    ],
    "wof:name":"Mossu Marc",
    "wof:placetype":"venue"
},
  "geometry": {"coordinates":[7.157790184,46.6337089539],"type":"Point"}
}