{
  "type": "Feature",
  "properties": {
    "iso:country":"CH",
    "sg:address":"6371 Stans. Postfach 209",
    "sg:city":"Stans",
    "sg:orig_category":"Sportvereine Flug Delta",
    "sg:phone":"+41 41 610 33 85",
    "sg:postcode":"6371",
    "sg:province":"Nidwalden",
    "wof:name":"Delta Club Stans",
    "wof:placetype":"venue"
},
  "geometry": {"coordinates":[8.3661203384,46.9571418762],"type":"Point"}
}