{
  "type": "Feature",
  "properties": {
    "iso:country":"CH",
    "sg:address":"Avenue De France 67",
    "sg:city":"Sion",
    "sg:orig_category":"Druck ohne Zeitungsdruck",
    "sg:phone":"+41 71 944 25 55",
    "sg:postcode":"1950",
    "sg:province":"Valais",
    "wof:name":"Zum Druckpunkt J\u00f6hl R.",
    "wof:placetype":"venue"
},
  "geometry": {"coordinates":[9.1234006882,47.4656410217],"type":"Point"}
}