{
  "type": "Feature",
  "properties": {
    "iso:country":"CH",
    "sg:address":"7076",
    "sg:city":"Parpan",
    "sg:classifiers":[
        {
            "category":"Bars & Pubs",
            "type":"Food & Drink"
        }
    ],
    "sg:phone":"+41 81 382 21 24",
    "sg:postcode":"7076",
    "sg:province":"Graubunden",
    "wof:name":"Mungga-bar",
    "wof:placetype":"venue"
},
  "geometry": {"coordinates":[9.55742,46.760136],"type":"Point"}
}