{
  "type": "Feature",
  "properties": {
    "iso:country":"CH",
    "sg:address":"Ruelle Dubl\u00e9 3",
    "sg:city":"Neuch\u00e2tel",
    "sg:orig_category":"Grosshandel mit Erzen U Metallen",
    "sg:phone":"+41 32 725 80 90",
    "sg:postcode":"2000",
    "sg:province":"Neuch\u00e2tel",
    "wof:name":"Novosteel Sa",
    "wof:placetype":"venue"
},
  "geometry": {"coordinates":[6.9293298721,46.9909820557],"type":"Point"}
}