{
  "type": "Feature",
  "properties": {
    "iso:country":"CH",
    "sg:address":"Schachenstrasse",
    "sg:city":"Winznau",
    "sg:orig_category":"Oberfl\u00e4chenveredlung U W\u00e4rmebehandlung",
    "sg:phone":"+41 26 674 34 34",
    "sg:postcode":"4652",
    "sg:province":"Solothurn",
    "wof:name":"Sturzenegger Sa",
    "wof:placetype":"venue"
},
  "geometry": {"coordinates":[7.1366200447,46.8959388733],"type":"Point"}
}