{
  "type": "Feature",
  "properties": {
    "iso:country":"CH",
    "sg:address":"Industriestrasse 7 4410 Liestal. Postfach",
    "sg:city":"Liestal",
    "sg:orig_category":"Grosshandel mit pharmazeutischen Erzeugnissen Herstellung von Medikamenten U sonstigen pharmazeutisc",
    "sg:phone":"+41 61 467 55 55",
    "sg:postcode":"4410",
    "sg:province":"Basel-Landschaft",
    "wof:name":"Skyepharma Ag",
    "wof:placetype":"venue"
},
  "geometry": {"coordinates":[7.6546998024,47.5276794434],"type":"Point"}
}