{
  "type": "Feature",
  "properties": {
    "iso:country":"CH",
    "sg:address":"Rue Saint-jean 30",
    "sg:city":"Nyon",
    "sg:orig_category":"W\u00e4scherei U chemische Reinigung",
    "sg:phone":"+41 22 348 55 22",
    "sg:postcode":"1260",
    "sg:province":"Vaud",
    "wof:name":"Baechler Teinturiers Sa",
    "wof:placetype":"venue"
},
  "geometry": {"coordinates":[6.2395200729,46.3830184937],"type":"Point"}
}