{
  "type": "Feature",
  "properties": {
    "iso:country":"CH",
    "sg:address":"Kirchgasse 6",
    "sg:city":"Aarau",
    "sg:orig_category":"Herstellung von sonstiger Bekleidung U Bekleidungszubeh\u00f6r",
    "sg:phone":"+41 56 622 11 44",
    "sg:postcode":"5000",
    "sg:province":"Aargau",
    "wof:name":"Ammann's Babyshop, Inhaberin Frau S. Ammann Family`s First Friend",
    "wof:placetype":"venue"
},
  "geometry": {"coordinates":[8.2768030167,47.3489494324],"type":"Point"}
}