{
  "type": "Feature",
  "properties": {
    "addr:full":"Sichternstrasse 17 Liestal Basel-Landschaft 4410",
    "addr:housenumber":"17",
    "addr:postcode":"4410",
    "addr:street":"Sichternstrasse",
    "iso:country":"CH",
    "sg:address":"Sichternstrasse 17",
    "sg:city":"Liestal",
    "sg:orig_category":"Detailhandel mit Bekleidung",
    "sg:phone":"+41 61 921 35 51",
    "sg:postcode":"4410",
    "sg:province":"Basel-Landschaft",
    "wof:name":"Coconet Ag",
    "wof:placetype":"venue"
},
  "geometry": {"coordinates":[7.725622,47.483978],"type":"Point"}
}