{
  "type": "Feature",
  "properties": {
    "iso:country":"CH",
    "sg:address":"Via Torraccia 14",
    "sg:city":"Novazzano",
    "sg:orig_category":"Herstellung von Spirituosen",
    "sg:postcode":"6883",
    "sg:province":"Ticino",
    "wof:name":"Beretta Luciano, Succ. A Barzaghi Luigi",
    "wof:placetype":"venue"
},
  "geometry": {"coordinates":[8.987909317,45.8422966003],"type":"Point"}
}