{
  "type": "Feature",
  "properties": {
    "iso:country":"CH",
    "sg:address":"Route Henri Stephan 14",
    "sg:city":"Givisiez",
    "sg:orig_category":"Herstellung von sonstigen Produkten aus nichtmetallischen Mineralien Strassenbau",
    "sg:phone":"+41 26 460 80 42",
    "sg:postcode":"1762",
    "sg:province":"Fribourg",
    "wof:name":"Colas Fribourg Sa",
    "wof:placetype":"venue"
},
  "geometry": {"coordinates":[7.1225500107,46.8158912659],"type":"Point"}
}