{
  "type": "Feature",
  "properties": {
    "iso:country":"CH",
    "sg:address":"6780 Airolo. Postfach",
    "sg:city":"Airolo",
    "sg:orig_category":"Grosshandel mit Getr\u00e4nken",
    "sg:postcode":"6780",
    "sg:province":"Ticino",
    "wof:name":"San-vini Sagl",
    "wof:placetype":"venue"
},
  "geometry": {"coordinates":[9.6523456573,47.4473342896],"type":"Point"}
}