{
  "type": "Feature",
  "properties": {
    "iso:country":"CH",
    "sg:address":"Fabrikstrasse 3 8753 Mollis. Postfach",
    "sg:city":"Mollis",
    "sg:orig_category":"Herstellung von Werkzeugen",
    "sg:phone":"+41 55 618 48 00",
    "sg:postcode":"8753",
    "sg:province":"Glarus",
    "wof:name":"Plica Werkzeugfabrik Ag Werkzeuge Usw; Herstellung, Handel",
    "wof:placetype":"venue"
},
  "geometry": {"coordinates":[9.0694322586,47.0904121399],"type":"Point"}
}