{
  "type": "Feature",
  "properties": {
    "iso:country":"CH",
    "sg:address":"3438",
    "sg:city":"Lauperswil",
    "sg:classifiers":[
        {
            "category":"Government",
            "subcategory":"Post Office",
            "type":"Public Place"
        }
    ],
    "sg:phone":"+41 34 496 74 30",
    "sg:postcode":"3438",
    "sg:province":"Bern",
    "sg:tags":[
        "die",
        "poststellen"
    ],
    "wof:name":"Die Post",
    "wof:placetype":"venue"
},
  "geometry": {"coordinates":[7.7411308289,46.9661712646],"type":"Point"}
}