{
  "type": "Feature",
  "properties": {
    "iso:country":"CH",
    "sg:address":"Birmensdorferstrasse 101",
    "sg:city":"Urdorf",
    "sg:orig_category":"Grosshandel mit Datenverarbeitungsger\u00e4ten Grosshandel mit Software",
    "sg:phone":"+41 17365050",
    "sg:postcode":"8902",
    "sg:province":"Z\u00fcrich",
    "wof:name":"Gisler Systems Ag Computersysteme- & Zubeh\u00f6r",
    "wof:placetype":"venue"
},
  "geometry": {"coordinates":[8.4221611023,47.3837203979],"type":"Point"}
}