{
  "type": "Feature",
  "properties": {
    "iso:country":"CH",
    "sg:address":"Jungholzhof 4",
    "sg:city":"Z\u00fcrich",
    "sg:orig_category":"Glasmalereien Verarbeitung U Veredlung von Flachglas",
    "sg:phone":"+41 13120771",
    "sg:postcode":"8050",
    "sg:province":"Z\u00fcrich",
    "wof:name":"Marco Manera Glaserei Manera",
    "wof:placetype":"venue"
},
  "geometry": {"coordinates":[8.5450210571,47.413318634],"type":"Point"}
}