{
  "type": "Feature",
  "properties": {
    "iso:country":"CH",
    "sg:address":"Bahnhofplatz 1",
    "sg:city":"Bern",
    "sg:orig_category":"Physiotherapie",
    "sg:phone":"+41 31 311 61 62",
    "sg:postcode":"3011",
    "sg:province":"Bern",
    "wof:name":"Physiotherapie Beau-site",
    "wof:placetype":"venue"
},
  "geometry": {"coordinates":[7.4411821365,46.9479370117],"type":"Point"}
}