{
  "type": "Feature",
  "properties": {
    "iso:country":"CH",
    "sg:address":"Oberdorfstrasse 8",
    "sg:city":"Riedern",
    "sg:orig_category":"Detailhandel mit Brot, Back U S\u00fcsswaren",
    "sg:phone":"+41 55 640 14 17",
    "sg:postcode":"8750",
    "sg:province":"Glarus",
    "wof:name":"Lotte Akeret B\u00e4ckerei",
    "wof:placetype":"venue"
},
  "geometry": {"coordinates":[9.050974,47.048908],"type":"Point"}
}