{
  "type": "Feature",
  "properties": {
    "iso:country":"CH",
    "sg:address":"Petit-ch\u00eane Rue Du 10 1003 Lausanne. Postfach",
    "sg:city":"Lausanne",
    "sg:orig_category":"Architektur U Ingenieurb\u00fcros",
    "sg:phone":"+41 21 311 13 68",
    "sg:postcode":"1003",
    "sg:province":"Vaud",
    "wof:name":"Beurer Ivo, Ing. Dipl. Epfl Ing\u00e9nierie Dans Le Dom. Du G\u00e9nie Rural",
    "wof:placetype":"venue"
},
  "geometry": {"coordinates":[6.631862,46.519283],"type":"Point"}
}