{
  "type": "Feature",
  "properties": {
    "addr:full":"Verbier Verbier Valais 1936",
    "addr:postcode":"1936",
    "iso:country":"CH",
    "sg:address":"Verbier",
    "sg:city":"Verbier",
    "sg:classifiers":[
        {
            "category":"Banks & Credit Unions",
            "subcategory":"Bank",
            "type":"Services"
        }
    ],
    "sg:phone":"+41 27 771 61 61",
    "sg:postcode":"1936",
    "sg:province":"Valais",
    "wof:name":"Banque Cantonale Du Valais",
    "wof:placetype":"venue"
},
  "geometry": {"coordinates":[7.22296,46.096722],"type":"Point"}
}