{
  "type": "Feature",
  "properties": {
    "iso:country":"CH",
    "sg:address":"Aarestrasse 14 3600 Thun. Postfach",
    "sg:city":"Thun",
    "sg:orig_category":"Reiseb\u00fcros",
    "sg:phone":"+41 33 225 76 76",
    "sg:postcode":"3601",
    "sg:province":"Bern",
    "wof:name":"Touring Club Schweiz Tcs Reiseb\u00fcro",
    "wof:placetype":"venue"
},
  "geometry": {"coordinates":[7.6265358925,46.7579231262],"type":"Point"}
}