{
  "type": "Feature",
  "properties": {
    "iso:country":"CH",
    "sg:address":"Birchstrasse 108 8000 Z\u00fcrich. Postfach 8050 Z\u00fcrich",
    "sg:city":"Zust",
    "sg:orig_category":"RESTAURANTS: TEA-ROOMS",
    "sg:postcode":"50",
    "wof:name":"Fidel Gastro Ag",
    "wof:placetype":"venue"
},
  "geometry": {"coordinates":[8.5374221802,47.4086761475],"type":"Point"}
}