{
  "type": "Feature",
  "properties": {
    "iso:country":"CH",
    "sg:address":"Burgdorfstrasse 11 3510 Konolfingen. Postfach 48",
    "sg:city":"Konolfingen",
    "sg:orig_category":"Zahnarztpraxen",
    "sg:phone":"+41 31 791 05 76",
    "sg:postcode":"3510",
    "sg:province":"Bern",
    "wof:name":"Dres Med.dent.k. & P. Bigler Zahn\u00e4rzte",
    "wof:placetype":"venue"
},
  "geometry": {"coordinates":[7.621846199,46.8821182251],"type":"Point"}
}