{
  "type": "Feature",
  "properties": {
    "iso:country":"CH",
    "sg:address":"Avenue Du Casino 45",
    "sg:city":"Montreux",
    "sg:orig_category":"Detailhandel mit Pelzwaren",
    "sg:phone":"+41 21 963 37 37",
    "sg:postcode":"1820",
    "sg:province":"Vaud",
    "wof:name":"Pandelis Annas Cr\u00e9ateur De Fourrures",
    "wof:placetype":"venue"
},
  "geometry": {"coordinates":[6.9113311768,46.4305458069],"type":"Point"}
}