{
  "type": "Feature",
  "properties": {
    "iso:country":"CH",
    "sg:address":"Bergstrasse 300",
    "sg:city":"D\u00fcbendorf",
    "sg:orig_category":"Instandhaltung U Reparatur von Automobilen",
    "sg:phone":"+41 18218550",
    "sg:postcode":"8600",
    "sg:province":"Z\u00fcrich",
    "wof:name":"Autospritzwerk Auricchio Pasquale",
    "wof:placetype":"venue"
},
  "geometry": {"coordinates":[8.6258802414,47.4028816223],"type":"Point"}
}