{
  "type": "Feature",
  "properties": {
    "iso:country":"CH",
    "sg:address":"Bahnhofstrasse 7",
    "sg:city":"Rheinfelden",
    "sg:orig_category":"Detailhandel mit Brot, Back U S\u00fcsswaren",
    "sg:phone":"+41 61 831 51 88",
    "sg:postcode":"4310",
    "sg:province":"Aargau",
    "wof:name":"Rohrer Feinb\u00e4ckerei Ag",
    "wof:placetype":"venue"
},
  "geometry": {"coordinates":[7.792109,47.554516],"type":"Point"}
}