{
  "type": "Feature",
  "properties": {
    "iso:country":"CH",
    "sg:address":"Weihermattstrasse 36 5000 Aarau. Postfach",
    "sg:city":"Aarau",
    "sg:orig_category":"Sanit\u00e4r U Heizungsinstallation Sanit\u00e4rinstallation",
    "sg:phone":"+41 62 837 64 64",
    "sg:postcode":"5004",
    "sg:province":"Aargau",
    "wof:name":"Boschetti Ag",
    "wof:placetype":"venue"
},
  "geometry": {"coordinates":[8.0585536957,47.3962554932],"type":"Point"}
}