{
  "type": "Feature",
  "properties": {
    "iso:country":"CH",
    "sg:address":"Notre-dame Place De 4",
    "sg:city":"Fribourg",
    "sg:orig_category":"Forschung U Entwicklung im Bereich der Naturwissenschaften",
    "sg:postcode":"1702",
    "sg:province":"Fribourg",
    "wof:name":"Global Foundation For Life Sciences",
    "wof:placetype":"venue"
},
  "geometry": {"coordinates":[7.1536831856,46.8037452698],"type":"Point"}
}