{
  "type": "Feature",
  "properties": {
    "iso:country":"CH",
    "sg:address":"Mungnau Zollbr\u00fcck.",
    "sg:city":"Lauperswil",
    "sg:orig_category":"Mahl U Sch\u00e4lm\u00fchlen",
    "sg:postcode":"3438",
    "sg:province":"Bern",
    "wof:name":"T. Steiner",
    "wof:placetype":"venue"
},
  "geometry": {"coordinates":[7.7411308289,46.9661712646],"type":"Point"}
}