{
  "type": "Feature",
  "properties": {
    "iso:country":"CH",
    "sg:address":"Bordgeais Rue Des 13",
    "sg:city":"Del\u00e9mont",
    "sg:orig_category":"Unternehmensberatung",
    "sg:phone":"+41 32 422 68 75",
    "sg:postcode":"2800",
    "sg:province":"Jura",
    "wof:name":"Hoffer Bernard Conseils",
    "wof:placetype":"venue"
},
  "geometry": {"coordinates":[7.3577299118,47.3733673096],"type":"Point"}
}