{
  "type": "Feature",
  "properties": {
    "iso:country":"CH",
    "sg:address":"M\u00f6slimatte 5",
    "sg:city":"Ettiswil",
    "sg:orig_category":"Herstellung von Hebezeugen U F\u00f6rdermitteln Herstellung von Metallerzeugnissen ohne Maschinenbau",
    "sg:phone":"+41 41 980 27 70",
    "sg:postcode":"6218",
    "sg:province":"Luzern",
    "wof:name":"Buob Kran Und Greifertechnik Gmbh",
    "wof:placetype":"venue"
},
  "geometry": {"coordinates":[8.0212097168,47.1469917297],"type":"Point"}
}