{
  "type": "Feature",
  "properties": {
    "iso:country":"CH",
    "sg:address":"Brunnmattstrasse 51",
    "sg:city":"Bern",
    "sg:orig_category":"Reiseb\u00fcros U Reiseveranstalter",
    "sg:phone":"+41 31 371 13 58",
    "sg:postcode":"3008",
    "sg:province":"Bern",
    "wof:name":"Abbassy Reisen",
    "wof:placetype":"venue"
},
  "geometry": {"coordinates":[7.4264578819,46.9422683716],"type":"Point"}
}