{
  "type": "Feature",
  "properties": {
    "iso:country":"CH",
    "sg:address":"Serneuserstrasse 7250 Klosters. Postfach",
    "sg:city":"Serneus",
    "sg:orig_category":"RESTAURANTS: TEA-ROOMS",
    "sg:phone":"+41 81 422 14 28",
    "sg:postcode":"7249",
    "sg:province":"Graubunden",
    "wof:name":"Gori Esther",
    "wof:placetype":"venue"
},
  "geometry": {"coordinates":[9.8801698685,46.8800468445],"type":"Point"}
}