{
  "type": "Feature",
  "properties": {
    "iso:country":"CH",
    "sg:address":"Hauptstr. 28.",
    "sg:city":"Kleindietwil",
    "sg:orig_category":"Detailhandel mit M\u00f6beln U Haushaltsgegenst\u00e4nden",
    "sg:phone":"+41 62 965 02 11",
    "sg:postcode":"4936",
    "sg:province":"Bern",
    "wof:name":"Nyfeler",
    "wof:placetype":"venue"
},
  "geometry": {"coordinates":[7.7921700478,47.1436347961],"type":"Point"}
}