{
  "type": "Feature",
  "properties": {
    "iso:country":"CH",
    "sg:address":"Chemin Du Talent 4",
    "sg:city":"Echallens",
    "sg:orig_category":"Verkehrs- and Tourismusb\u00fcros",
    "sg:phone":"+41 21 881 23 27",
    "sg:postcode":"1040",
    "sg:province":"Vaud",
    "wof:name":"St\u00e9 De D\u00e9veloppement Monsieur Emile Favre",
    "wof:placetype":"venue"
},
  "geometry": {"coordinates":[6.6333169937,46.6422157288],"type":"Point"}
}