{
  "type": "Feature",
  "properties": {
    "addr:full":"Baumgartenrain 1 W\u00e4denswil Z\u00fcrich 8820",
    "addr:housenumber":"1",
    "addr:postcode":"8820",
    "addr:street":"Baumgartenrain;Zuerich",
    "iso:country":"CH",
    "sg:address":"Baumgartenrain 1",
    "sg:city":"W\u00e4denswil",
    "sg:orig_category":"Architektur U Ingenieurb\u00fcros Unternehmensberatung",
    "sg:phone":"+41 17805347",
    "sg:postcode":"8820",
    "sg:province":"Z\u00fcrich",
    "wof:name":"Pfeifer Controlling & Consulting",
    "wof:placetype":"venue"
},
  "geometry": {"coordinates":[8.671631,47.222473],"type":"Point"}
}