{
  "type": "Feature",
  "properties": {
    "iso:country":"CH",
    "sg:address":"7056",
    "sg:city":"Molinis",
    "sg:classifiers":[
        {
            "category":"Restaurant",
            "type":"Food & Drink"
        }
    ],
    "sg:phone":"+41 81 374 12 48",
    "sg:postcode":"7056",
    "sg:province":"Graubunden",
    "wof:name":"Restaurant Br\u00fcggli",
    "wof:placetype":"venue"
},
  "geometry": {"coordinates":[9.6538000107,46.8281059265],"type":"Point"}
}