{
  "type": "Feature",
  "properties": {
    "iso:country":"CH",
    "sg:address":"Aarauerstrasse 16",
    "sg:city":"Starrkirch-wil",
    "sg:orig_category":"Pensionskassen",
    "sg:phone":"+41 62 285 40 80",
    "sg:postcode":"4656",
    "sg:province":"Solothurn",
    "wof:name":"Wohlfahrtsfonds Pilloud",
    "wof:placetype":"venue"
},
  "geometry": {"coordinates":[7.9247050285,47.3521461487],"type":"Point"}
}