{
  "type": "Feature",
  "properties": {
    "iso:country":"CH",
    "sg:address":"Thundorferstrasse 8",
    "sg:city":"Frauenfeld",
    "sg:orig_category":"Non-Classified Establishments",
    "sg:postcode":"8500",
    "sg:province":"Thurgau",
    "wof:name":"Ums - Neuromed Ag",
    "wof:placetype":"venue"
},
  "geometry": {"coordinates":[8.8989858627,47.5551147461],"type":"Point"}
}