{
  "type": "Feature",
  "properties": {
    "iso:country":"CH",
    "sg:address":"Route De Gen\u00e8ve 58",
    "sg:city":"Nyon",
    "sg:orig_category":"Non-Classified Establishments",
    "sg:postcode":"1260",
    "sg:province":"Vaud",
    "wof:name":"Rive Claire Sa",
    "wof:placetype":"venue"
},
  "geometry": {"coordinates":[6.2290902138,46.3707084656],"type":"Point"}
}