{
  "type": "Feature",
  "properties": {
    "iso:country":"CH",
    "sg:address":"Bachelin Rue Auguste- 1",
    "sg:city":"Marin-centre",
    "sg:orig_category":"Detailhandel mit Fleisch U Fleischwaren",
    "sg:phone":"+41 32 841 22 48",
    "sg:postcode":"2074",
    "sg:province":"Neuch\u00e2tel",
    "wof:name":"Boucherie Frank.",
    "wof:placetype":"venue"
},
  "geometry": {"coordinates":[6.8603429794,46.9663352966],"type":"Point"}
}