{
  "type": "Feature",
  "properties": {
    "addr:full":"Sch\u00fctzenstrasse 33 Dietikon Z\u00fcrich 8953",
    "addr:housenumber":"33",
    "addr:postcode":"8953",
    "addr:street":"Schuetzenstrasse",
    "iso:country":"CH",
    "sg:address":"Sch\u00fctzenstrasse 33",
    "sg:city":"Dietikon",
    "sg:orig_category":"Architektur U Ingenieurb\u00fcros",
    "sg:phone":"+41 17407979",
    "sg:postcode":"8953",
    "sg:province":"Z\u00fcrich",
    "wof:name":"Stettler Hans, Architekturb\u00fcro",
    "wof:placetype":"venue"
},
  "geometry": {"coordinates":[8.391068,47.404758],"type":"Point"}
}