{
  "type": "Feature",
  "properties": {
    "iso:country":"CH",
    "sg:address":"Walalpweg 20 3661 Uetendorf. Postfach 24",
    "sg:city":"Uetendorf",
    "sg:orig_category":"Grosshandel mit Bekleidung U Schuhen",
    "sg:phone":"+41 33 345 02 66",
    "sg:postcode":"3661",
    "sg:province":"Bern",
    "wof:name":"Aspo Sport Gmbh",
    "wof:placetype":"venue"
},
  "geometry": {"coordinates":[7.5974841118,46.7748298645],"type":"Point"}
}