{
  "type": "Feature",
  "properties": {
    "iso:country":"CH",
    "sg:address":"Hirzlistrasse 19",
    "sg:city":"Bilten",
    "sg:orig_category":"Ausbaugewerbe Verlegen von Fliesen U Platten",
    "sg:phone":"+41 55 615 28 41",
    "sg:postcode":"8865",
    "sg:province":"Glarus",
    "wof:name":"Zweifel Anton Plattenbel\u00e4ge Ag",
    "wof:placetype":"venue"
},
  "geometry": {"coordinates":[9.026029,47.149521],"type":"Point"}
}