{
  "type": "Feature",
  "properties": {
    "iso:country":"CH",
    "sg:address":"Kreuzmattstrasse 5",
    "sg:city":"Horw",
    "sg:orig_category":"Grosshandel mit Holz U Baustoffen",
    "sg:phone":"+41 41 210 47 47",
    "sg:postcode":"6048",
    "sg:province":"Luzern",
    "wof:name":"W\u00fcst Ag",
    "wof:placetype":"venue"
},
  "geometry": {"coordinates":[8.3355560303,47.0139961243],"type":"Point"}
}