{
  "type": "Feature",
  "properties": {
    "iso:country":"CH",
    "sg:address":"Rue Du 23-juin 24",
    "sg:city":"Del\u00e9mont",
    "sg:orig_category":"Grosshandel mit Sportartikeln Sonstige mit Sport verbundene T\u00e4tigkeiten",
    "sg:phone":"+41 32 423 13 23",
    "sg:postcode":"2800",
    "sg:province":"Jura",
    "wof:name":"Promo-sport Diffusion S\u00e0rl",
    "wof:placetype":"venue"
},
  "geometry": {"coordinates":[7.343375206,47.3651695251],"type":"Point"}
}