{
  "type": "Feature",
  "properties": {
    "addr:full":"Dienstleistungszentrum 8590 Romanshorn. Postfach Romanshorn Thurgau 8590",
    "addr:postcode":"8590;8590",
    "addr:street":"Romanshorn. Postfach",
    "iso:country":"CH",
    "sg:address":"Dienstleistungszentrum 8590 Romanshorn. Postfach",
    "sg:city":"Romanshorn",
    "sg:classifiers":[
        {
            "category":"Professional",
            "subcategory":"Accounting & Tax Preparation",
            "type":"Services"
        }
    ],
    "sg:phone":"+41 71 463 55 22",
    "sg:postcode":"8590",
    "sg:province":"Thurgau",
    "sg:tags":[
        "u",
        "yachtbau",
        "boot"
    ],
    "wof:name":"Fredy Blust Gmbh Bootswerft",
    "wof:placetype":"venue"
},
  "geometry": {"coordinates":[9.377975,47.56572],"type":"Point"}
}