{
  "type": "Feature",
  "properties": {
    "iso:country":"CH",
    "sg:address":"Terrassi\u00e8re Rue De La 45 1207 Gen\u00e8ve. Postfach",
    "sg:city":"Gen\u00e8ve",
    "sg:orig_category":"Interessenvertretungen",
    "sg:postcode":"1207",
    "sg:province":"Gen\u00e8ve",
    "wof:name":"Le Piqu\u00e9, Association Francophone De Botanique Appliqu\u00e9e Aux Cactus, Aux Plantes Succulentes Et Aux Plantes D'acclimatation",
    "wof:placetype":"venue"
},
  "geometry": {"coordinates":[6.1590099335,46.2005004883],"type":"Point"}
}