{
  "type": "Feature",
  "properties": {
    "addr:full":"Untere Gasse 4 Chur Graubunden 7000",
    "addr:housenumber":"4",
    "addr:postcode":"7000",
    "addr:street":"Untere Gasse",
    "iso:country":"CH",
    "sg:address":"Untere Gasse 4",
    "sg:city":"Chur",
    "sg:classifiers":[
        {
            "category":"Bars & Pubs",
            "type":"Food & Drink"
        }
    ],
    "sg:phone":"+41 81 252 18 47",
    "sg:postcode":"7000",
    "sg:province":"Graubunden",
    "wof:name":"Pub Hexenkessel & John Bull Bar",
    "wof:placetype":"venue"
},
  "geometry": {"coordinates":[9.530657,46.849033],"type":"Point"}
}