{
  "type": "Feature",
  "properties": {
    "iso:country":"CH",
    "sg:address":"Silisegg",
    "sg:city":"Bauma",
    "sg:orig_category":"Softwareentwicklung U beratung",
    "sg:phone":"+41 52 394 11 05",
    "sg:postcode":"8494",
    "sg:province":"Z\u00fcrich",
    "wof:name":"Hekotech Gmbh",
    "wof:placetype":"venue"
},
  "geometry": {"coordinates":[8.8754043579,47.3621749878],"type":"Point"}
}