{
  "type": "Feature",
  "properties": {
    "iso:country":"CH",
    "sg:address":"1417",
    "sg:city":"Essertines-yverdon",
    "sg:orig_category":"Instandhaltung U Reparatur von Automobilen",
    "sg:phone":"+41 24 435 19 62",
    "sg:postcode":"1417",
    "sg:province":"Vaud",
    "wof:name":"Pavillard, Daniel",
    "wof:placetype":"venue"
},
  "geometry": {"coordinates":[6.6399297714,46.7164115906],"type":"Point"}
}