{
  "type": "Feature",
  "properties": {
    "iso:country":"CH",
    "sg:address":"Hertistrasse",
    "sg:city":"Wallisellen",
    "sg:orig_category":"Allgemeiner Hoch U Tiefbau",
    "sg:phone":"+41 18305588",
    "sg:postcode":"8304",
    "sg:province":"Z\u00fcrich",
    "wof:name":"West Immobilien Ag",
    "wof:placetype":"venue"
},
  "geometry": {"coordinates":[8.577043,47.416389],"type":"Point"}
}