{
  "type": "Feature",
  "properties": {
    "iso:country":"CH",
    "sg:address":"Bramantino Via 1",
    "sg:city":"Locarno",
    "sg:orig_category":"Vermietung U Verpachtung von eigenen Immobilien",
    "sg:postcode":"6600",
    "sg:province":"Ticino",
    "wof:name":"Immobiliare Lago Sa",
    "wof:placetype":"venue"
},
  "geometry": {"coordinates":[8.8017988205,46.1675567627],"type":"Point"}
}