{
  "type": "Feature",
  "properties": {
    "iso:country":"CH",
    "sg:address":"Alte Steinhauserstrasse 21",
    "sg:city":"Cham",
    "sg:orig_category":"Softwareentwicklung U beratung",
    "sg:postcode":"6330",
    "sg:province":"Zug",
    "wof:name":"Riniker, Erci Und Kupferschmid, Three Way",
    "wof:placetype":"venue"
},
  "geometry": {"coordinates":[8.1679506302,47.4527931213],"type":"Point"}
}