{
  "type": "Feature",
  "properties": {
    "iso:country":"CH",
    "sg:address":"Lindenhofstrasse 12",
    "sg:city":"Jona",
    "sg:orig_category":"Herstellung von k\u00e4lte U lufttechnischen Erzeugnissen f\u00fcr gewerbliche Zwecke Installation von Heizung",
    "sg:phone":"+41 55 210 98 00",
    "sg:postcode":"8645",
    "sg:province":"St. Gallen",
    "wof:name":"Baumgartner-klimatechnik Ag",
    "wof:placetype":"venue"
},
  "geometry": {"coordinates":[8.8233194351,47.2410583496],"type":"Point"}
}