{
  "type": "Feature",
  "properties": {
    "iso:country":"CH",
    "sg:address":"G\u00fcterstrasse 5",
    "sg:city":"Ostermundigen",
    "sg:orig_category":"Softwareentwicklung U beratung",
    "sg:phone":"+41 31 380 66 66",
    "sg:postcode":"3072",
    "sg:province":"Bern",
    "wof:name":"Inova Solutions Ag",
    "wof:placetype":"venue"
},
  "geometry": {"coordinates":[7.4797158241,46.9536933899],"type":"Point"}
}