{
  "type": "Feature",
  "properties": {
    "iso:country":"CH",
    "sg:address":"Schmidstrasse 2",
    "sg:city":"Weinfelden",
    "sg:orig_category":"Detailhandel mit Bekleidung Herstellung von sonstiger Bekleidung U Bekleidungszubeh\u00f6r",
    "sg:phone":"+41 71 622 58 37",
    "sg:postcode":"8570",
    "sg:province":"Thurgau",
    "wof:name":"Ernst Burkart Schirme & Herrenmode",
    "wof:placetype":"venue"
},
  "geometry": {"coordinates":[9.108008,47.566605],"type":"Point"}
}