{
  "type": "Feature",
  "properties": {
    "iso:country":"CH",
    "sg:address":"Schloss Liebenfels 8506 Lanzenneunforn. Postfach",
    "sg:city":"Lanzenneunforn",
    "sg:orig_category":"Grosshandel mit Getr\u00e4nken",
    "sg:postcode":"8506",
    "sg:province":"Thurgau",
    "wof:name":"Ebert C., Schloss Liebenfels, Import Wein, Schaumwein-import",
    "wof:placetype":"venue"
},
  "geometry": {"coordinates":[8.938949585,47.6226043701],"type":"Point"}
}