{
  "type": "Feature",
  "properties": {
    "iso:country":"CH",
    "sg:address":"Z\u00fcrcherstrasse 9",
    "sg:city":"Oberengstringen",
    "sg:orig_category":"Vermietung U Verpachtung von eigenen Immobilien",
    "sg:postcode":"8102",
    "sg:province":"Z\u00fcrich",
    "wof:name":"Solsano Oberengstringen Immobilien Ag",
    "wof:placetype":"venue"
},
  "geometry": {"coordinates":[8.4762639999,47.4051895142],"type":"Point"}
}