{
  "type": "Feature",
  "properties": {
    "iso:country":"CH",
    "sg:address":"Chemin De Villardiez 12a",
    "sg:city":"Pully",
    "sg:orig_category":"Non-Classified Establishments",
    "sg:postcode":"1009",
    "sg:province":"Vaud",
    "wof:name":"Fun4people, Oliver Paschaweh",
    "wof:placetype":"venue"
},
  "geometry": {"coordinates":[8.4601297379,47.3635101318],"type":"Point"}
}