{
  "type": "Feature",
  "properties": {
    "iso:country":"CH",
    "sg:address":"Bachstrasse 3",
    "sg:city":"Attiswil",
    "sg:orig_category":"Sportvereine Sch\u00fctzen",
    "sg:phone":"+41 32 637 17 23",
    "sg:postcode":"4536",
    "sg:province":"Bern",
    "wof:name":"Standsch\u00fctzen Attiswil",
    "wof:placetype":"venue"
},
  "geometry": {"coordinates":[7.6119718552,47.24584198],"type":"Point"}
}