{
  "type": "Feature",
  "properties": {
    "iso:country":"CH",
    "sg:address":"Erlenweg 10",
    "sg:city":"Schafisheim",
    "sg:orig_category":"Sportvereine Turnen",
    "sg:phone":"+41 62 891 54 06",
    "sg:postcode":"5503",
    "sg:province":"Aargau",
    "wof:name":"M\u00e4nner Tv Oberwil-lieli",
    "wof:placetype":"venue"
},
  "geometry": {"coordinates":[8.1399068832,47.3719978333],"type":"Point"}
}