{
  "type": "Feature",
  "properties": {
    "iso:country":"CH",
    "sg:address":"Bleichestrasse 35",
    "sg:city":"Stettlen",
    "sg:orig_category":"Baugewerbe",
    "sg:phone":"+41 79 341 00 68",
    "sg:postcode":"3066",
    "sg:province":"Bern",
    "wof:name":"Technic-service Rolf In\u00e4bnit Storen & Rolladen",
    "wof:placetype":"venue"
},
  "geometry": {"coordinates":[7.516097,46.960361],"type":"Point"}
}