{
  "type": "Feature",
  "properties": {
    "iso:country":"CH",
    "sg:address":"Juravorstadt 13",
    "sg:city":"Biel/bienne",
    "sg:orig_category":"Werbung",
    "sg:phone":"+41 32 325 29 10",
    "sg:postcode":"2502",
    "sg:province":"Bern",
    "wof:name":"Werbeatelier B\u00f6rlin",
    "wof:placetype":"venue"
},
  "geometry": {"coordinates":[7.2475972176,47.1434211731],"type":"Point"}
}