{
  "type": "Feature",
  "properties": {
    "iso:country":"CH",
    "sg:address":"Bauenstrasse Isleten",
    "sg:city":"Bauen",
    "sg:orig_category":"RESTAURANTS: TEA-ROOMS",
    "sg:phone":"+41 41 878 11 05",
    "sg:postcode":"6466",
    "sg:province":"Uri",
    "wof:name":"Restaurant Seegarten",
    "wof:placetype":"venue"
},
  "geometry": {"coordinates":[8.5792150497,46.934551239],"type":"Point"}
}