{
  "type": "Feature",
  "properties": {
    "iso:country":"CH",
    "sg:address":"3951",
    "sg:city":"Agarn",
    "sg:orig_category":"G\u00fcterbef\u00f6rderung im Strassenverkehr",
    "sg:phone":"+41 26 413 90 09",
    "sg:postcode":"3951",
    "sg:province":"Valais",
    "wof:name":"Wyssm\u00fcller F., Transports Internationaux Sa",
    "wof:placetype":"venue"
},
  "geometry": {"coordinates":[7.1718049049,46.7444610596],"type":"Point"}
}