{
  "type": "Feature",
  "properties": {
    "iso:country":"CH",
    "sg:address":"Blegistrasse 13 6340 Baar. Postfach 2523",
    "sg:city":"Baar",
    "sg:orig_category":"Detailhandel mit elektrischen Haushalts-,Radio U Fernsehger\u00e4ten sowie Musikinstrumenten",
    "sg:postcode":"6340",
    "sg:province":"Zug",
    "wof:name":"Musicvision Gmbh",
    "wof:placetype":"venue"
},
  "geometry": {"coordinates":[8.5997629166,47.327293396],"type":"Point"}
}