{
  "type": "Feature",
  "properties": {
    "iso:country":"CH",
    "sg:address":"St. Gallerstrasse 19",
    "sg:city":"Rorschach",
    "sg:orig_category":"Sportvereine Sch\u00fctzen Pistolen-& Gewehr",
    "sg:phone":"+41 71 841 15 67",
    "sg:postcode":"9400",
    "sg:province":"St. Gallen",
    "wof:name":"Feldsch\u00fctzengesellschaft",
    "wof:placetype":"venue"
},
  "geometry": {"coordinates":[9.4864826202,47.4786338806],"type":"Point"}
}