{
  "type": "Feature",
  "properties": {
    "iso:country":"CH",
    "sg:address":"Hauptstrasse 58",
    "sg:city":"T\u00e4gerwilen",
    "sg:orig_category":"Druck ohne Zeitungsdruck Offsetdruck",
    "sg:phone":"+41 71 669 17 34",
    "sg:postcode":"8274",
    "sg:province":"Thurgau",
    "wof:name":"Z\u00fcrcher Druck Gmbh",
    "wof:placetype":"venue"
},
  "geometry": {"coordinates":[9.1297559738,47.6556968689],"type":"Point"}
}