{
  "type": "Feature",
  "properties": {
    "iso:country":"CH",
    "sg:address":"1757",
    "sg:city":"Nor\u00e9az",
    "sg:orig_category":"Architektur U Ingenieurb\u00fcros",
    "sg:phone":"+41 79 417 70 60",
    "sg:postcode":"1757",
    "sg:province":"Fribourg",
    "wof:name":"Bureau D'ing\u00e9nieurs Sabert, Succursale De Nor\u00e9az",
    "wof:placetype":"venue"
},
  "geometry": {"coordinates":[7.027735,46.801682],"type":"Point"}
}