{
  "type": "Feature",
  "properties": {
    "iso:country":"CH",
    "sg:address":"Rue De L'h\u00f4pital 18",
    "sg:city":"Saignel\u00e9gier",
    "sg:orig_category":"Verlegen von Fliesen U Platten",
    "sg:phone":"+41 32 951 18 85",
    "sg:postcode":"2350",
    "sg:province":"Jura",
    "wof:name":"Alfons Kornmayer Carrelages & Rev\u00eatements",
    "wof:placetype":"venue"
},
  "geometry": {"coordinates":[6.9954299927,47.2558517456],"type":"Point"}
}