{
  "type": "Feature",
  "properties": {
    "iso:country":"CH",
    "sg:address":"M\u00e4rtplatz 21",
    "sg:city":"Effretikon",
    "sg:orig_category":"Betrieb von Theatern, Opern, Schauspielh\u00e4usern U Konzerthallen",
    "sg:phone":"+41 52 343 39 76",
    "sg:postcode":"8307",
    "sg:province":"Z\u00fcrich",
    "wof:name":"Hallauerhus,jugend-& Freizeit- Zentrum,kleintheater Heubode",
    "wof:placetype":"venue"
},
  "geometry": {"coordinates":[8.685726,47.427654],"type":"Point"}
}