{
  "type": "Feature",
  "properties": {
    "iso:country":"CH",
    "sg:address":"Industriestrasse 19 7000 Chur. Postfach",
    "sg:city":"Chur",
    "sg:orig_category":"Elektroinstallation",
    "sg:phone":"+41 81 286 99 44",
    "sg:postcode":"7001",
    "sg:province":"Graubunden",
    "wof:name":"Willi E. Ag",
    "wof:placetype":"venue"
},
  "geometry": {"coordinates":[9.5098667145,46.8570709229],"type":"Point"}
}