{
  "type": "Feature",
  "properties": {
    "iso:country":"CH",
    "sg:address":"Rue Du Prieur\u00e9 38",
    "sg:city":"Broc",
    "sg:orig_category":"Autogaragen",
    "sg:phone":"+41 79 213 54 14",
    "sg:postcode":"1636",
    "sg:province":"Fribourg",
    "wof:name":"Garage Du Ch\u00e2teau D'en Bas",
    "wof:placetype":"venue"
},
  "geometry": {"coordinates":[7.093688,46.603226],"type":"Point"}
}