{
  "type": "Feature",
  "properties": {
    "iso:country":"CH",
    "sg:address":"1837",
    "sg:city":"Ch\u00e2teau-d'oex",
    "sg:orig_category":"Sonstige Hilfs U Nebent\u00e4tigkeiten f\u00fcr die Luftfahrt",
    "sg:phone":"+41 41 852 07 07",
    "sg:postcode":"1837",
    "wof:name":"Caminada & Partner Ag",
    "wof:placetype":"venue"
},
  "geometry": {"coordinates":[8.4448652267,47.0884056091],"type":"Point"}
}