{
  "type": "Feature",
  "properties": {
    "iso:country":"CH",
    "sg:address":"Rotseestrasse 9",
    "sg:city":"Luzern",
    "sg:orig_category":"Psychotherapie Unternehmensberatung",
    "sg:phone":"+41 41 420 30 22",
    "sg:postcode":"6006",
    "sg:province":"Luzern",
    "wof:name":"Daniele Kirchmair Shima-institut",
    "wof:placetype":"venue"
},
  "geometry": {"coordinates":[8.3107156754,47.0662918091],"type":"Point"}
}