{
  "type": "Feature",
  "properties": {
    "iso:country":"CH",
    "sg:address":"1302",
    "sg:city":"Vufflens-la-ville",
    "sg:orig_category":"Detailhandel mit B\u00fcchern, Zeitungen, Schreib U Papeteriewaren",
    "sg:postcode":"1302",
    "sg:province":"Vaud",
    "wof:name":"Cu\u00e9nod Georges, Les Lectures De La Jorane",
    "wof:placetype":"venue"
},
  "geometry": {"coordinates":[6.53757,46.575211],"type":"Point"}
}