{
  "type": "Feature",
  "properties": {
    "iso:country":"CH",
    "sg:address":"Route De Renens 8",
    "sg:city":"Prilly",
    "sg:orig_category":"Tankstellen",
    "sg:phone":"+41 21 624 51 84",
    "sg:postcode":"1008",
    "sg:province":"Vaud",
    "wof:name":"Esso Suisse S\u00e0rl Fabienne Zwahlen",
    "wof:placetype":"venue"
},
  "geometry": {"coordinates":[6.6024389267,46.528881073],"type":"Point"}
}