{
  "type": "Feature",
  "properties": {
    "iso:country":"CH",
    "sg:address":"B\u00f6sch 41",
    "sg:city":"H\u00fcnenberg",
    "sg:orig_category":"Unclassifiable Establishments",
    "sg:postcode":"6331",
    "sg:province":"Zug",
    "wof:name":"Pro Comp Gygax",
    "wof:placetype":"venue"
},
  "geometry": {"coordinates":[8.4363260269,47.1621665955],"type":"Point"}
}