{
  "type": "Feature",
  "properties": {
    "iso:country":"CH",
    "sg:address":"Freiestrasse 18",
    "sg:city":"Z\u00fcrich",
    "sg:orig_category":"Unclassifiable Establishments",
    "sg:postcode":"8032",
    "sg:province":"Z\u00fcrich",
    "wof:name":"Marcel Scheidegger Architektur Gmbh",
    "wof:placetype":"venue"
},
  "geometry": {"coordinates":[8.5526485443,47.3726882935],"type":"Point"}
}