{
  "type": "Feature",
  "properties": {
    "iso:country":"CH",
    "sg:address":"Rotfluhstrasse 52",
    "sg:city":"Zollikon",
    "sg:orig_category":"Herstellung von K\u00fcchenm\u00f6beln",
    "sg:phone":"+41 13922720",
    "sg:postcode":"8702",
    "sg:province":"Z\u00fcrich",
    "wof:name":"Rubertone Gmbh",
    "wof:placetype":"venue"
},
  "geometry": {"coordinates":[8.5768203735,47.3435096741],"type":"Point"}
}