{
  "type": "Feature",
  "properties": {
    "iso:country":"CH",
    "sg:address":"2744",
    "sg:city":"Belprahon",
    "sg:orig_category":"Gemeindeverwaltungen",
    "sg:phone":"+41 32 493 48 27",
    "sg:postcode":"2744",
    "sg:province":"Bern",
    "wof:name":"Administration Communale De Belprahon",
    "wof:placetype":"venue"
},
  "geometry": {"coordinates":[7.4054498672,47.2902488708],"type":"Point"}
}