{
  "type": "Feature",
  "properties": {
    "iso:country":"CH",
    "sg:address":"Netzelen",
    "sg:city":"Roggliswil",
    "sg:orig_category":"Allgemeiner Hoch U Tiefbau Hoch U Tiefbau",
    "sg:phone":"+41 62 754 12 29",
    "sg:postcode":"6265",
    "sg:province":"Luzern",
    "wof:name":"Luternauer Vinzenz.",
    "wof:placetype":"venue"
},
  "geometry": {"coordinates":[7.882835,47.209873],"type":"Point"}
}