{
  "type": "Feature",
  "properties": {
    "iso:country":"CH",
    "sg:address":"B\u00fcrglistrasse 37",
    "sg:city":"Wallisellen",
    "sg:orig_category":"Detailhandel mit Bekleidung",
    "sg:phone":"+41 18307718",
    "sg:postcode":"8304",
    "sg:province":"Z\u00fcrich",
    "wof:name":"Robert Mauch Textilien",
    "wof:placetype":"venue"
},
  "geometry": {"coordinates":[8.601258,47.415676],"type":"Point"}
}