{
  "type": "Feature",
  "properties": {
    "iso:country":"CH",
    "sg:address":"6563",
    "sg:city":"Mesocco",
    "sg:orig_category":"Bau von Strassen, Sportanlagen U Bahnverkehrsstrecken",
    "sg:phone":"+41 91 831 11 44",
    "sg:postcode":"6563",
    "sg:province":"Graubunden",
    "wof:name":"Cereghetti-neve Sa",
    "wof:placetype":"venue"
},
  "geometry": {"coordinates":[9.2329,46.391632],"type":"Point"}
}