{
  "type": "Feature",
  "properties": {
    "iso:country":"CH",
    "sg:address":"Oberemattstrasse 86",
    "sg:city":"Pratteln",
    "sg:orig_category":"G\u00fcterbef\u00f6rderung im Strassenverkehr",
    "sg:phone":"+41 79 320 20 76",
    "sg:postcode":"4133",
    "sg:province":"Basel-Landschaft",
    "wof:name":"Oray Trans Gmbh Internationale Transporte",
    "wof:placetype":"venue"
},
  "geometry": {"coordinates":[7.7031450272,47.5210418701],"type":"Point"}
}