{
  "type": "Feature",
  "properties": {
    "iso:country":"CH",
    "sg:address":"M\u00fchlebachstrasse 23",
    "sg:city":"Z\u00fcrich",
    "sg:orig_category":"Sonstige pers\u00f6nliche Dienstleistungen",
    "sg:postcode":"8008",
    "sg:province":"Z\u00fcrich",
    "wof:name":"Az Consulting Gmbh",
    "wof:placetype":"venue"
},
  "geometry": {"coordinates":[9.4003334045,47.4435272217],"type":"Point"}
}