{
  "type": "Feature",
  "properties": {
    "iso:country":"CH",
    "sg:address":"Laurenzentorgasse 2 5000 Aarau. Postfach",
    "sg:city":"Aarau",
    "sg:orig_category":"Non-Classified Establishments",
    "sg:postcode":"5000",
    "sg:province":"Aargau",
    "wof:name":"Card-holding Ag Beteiligung Usw",
    "wof:placetype":"venue"
},
  "geometry": {"coordinates":[8.044500351,47.3930358887],"type":"Point"}
}