{
  "type": "Feature",
  "properties": {
    "iso:country":"CH",
    "sg:address":"Zimmergasse 17",
    "sg:city":"Z\u00fcrich",
    "sg:orig_category":"Vermietung U Verpachtung von eigenen Immobilien",
    "sg:postcode":"8008",
    "sg:province":"Z\u00fcrich",
    "wof:name":"Kalasahyf Sa",
    "wof:placetype":"venue"
},
  "geometry": {"coordinates":[6.8297801018,47.1029129028],"type":"Point"}
}