{
  "type": "Feature",
  "properties": {
    "iso:country":"CH",
    "sg:address":"Rue Du Simplon 3d",
    "sg:city":"Lausanne",
    "sg:orig_category":"Tierarztpraxis",
    "sg:phone":"+41 21 616 10 66",
    "sg:postcode":"1006",
    "sg:province":"Vaud",
    "wof:name":"Dr M\u00e9d.v\u00e9t.anne-marie Villars M\u00e9decin V\u00e9t\u00e9rinaire",
    "wof:placetype":"venue"
},
  "geometry": {"coordinates":[6.6320428848,46.5153312683],"type":"Point"}
}