{
  "type": "Feature",
  "properties": {
    "addr:full":"Totentanz 5 Basel Basel-Stadt 4051",
    "addr:housenumber":"5",
    "addr:postcode":"4051",
    "addr:street":"Totentanz",
    "iso:country":"CH",
    "sg:address":"Totentanz 5",
    "sg:city":"Basel",
    "sg:orig_category":"Architekturb\u00fcros",
    "sg:phone":"+41 61 261 72 01",
    "sg:postcode":"4051",
    "sg:province":"Basel-Stadt",
    "wof:name":"Max Schnetz Architekturb\u00fcro",
    "wof:placetype":"venue"
},
  "geometry": {"coordinates":[7.586219,47.561771],"type":"Point"}
}