{
  "type": "Feature",
  "properties": {
    "iso:country":"CH",
    "sg:address":"Greifengasse 9",
    "sg:city":"Basel",
    "sg:classifiers":[
        {
            "category":"Professional",
            "subcategory":"Employment Agencies",
            "type":"Services"
        }
    ],
    "sg:phone":"+41 61 695 90 90",
    "sg:postcode":"4058",
    "sg:province":"Basel-Stadt",
    "sg:tags":[
        "personal",
        "u",
        "stellenvermittlung"
    ],
    "wof:name":"Gst Stellendienst Ag Basel Personalverleih U. Stellenvermittlung Usw",
    "wof:placetype":"venue"
},
  "geometry": {"coordinates":[7.5916838646,47.5611534119],"type":"Point"}
}