{
  "type": "Feature",
  "properties": {
    "iso:country":"CH",
    "sg:address":"Rue Pr\u00e9vost-martin 5",
    "sg:city":"Gen\u00e8ve",
    "sg:classifiers":[
        {
            "category":"Restaurant",
            "type":"Food & Drink"
        }
    ],
    "sg:phone":"+41 21 691 31 98",
    "sg:postcode":"1205",
    "sg:province":"Gen\u00e8ve",
    "wof:name":"Restaurant Des P\u00eacheurs",
    "wof:placetype":"venue"
},
  "geometry": {"coordinates":[6.5580701828,46.5100784302],"type":"Point"}
}