{
  "type": "Feature",
  "properties": {
    "iso:country":"CH",
    "sg:address":"Grand-rue 90",
    "sg:city":"Montreux",
    "sg:orig_category":"Detailhandel mit Musikinstrumenten",
    "sg:phone":"+41 21 963 49 66",
    "sg:postcode":"1820",
    "sg:province":"Vaud",
    "wof:name":"Christian Deb\u00e9taz",
    "wof:placetype":"venue"
},
  "geometry": {"coordinates":[6.9085202217,46.437046051],"type":"Point"}
}