{
  "type": "Feature",
  "properties": {
    "iso:country":"CH",
    "sg:address":"Rue Du Temple 10",
    "sg:city":"Gen\u00e8ve",
    "sg:classifiers":[
        {
            "category":"Insurance",
            "subcategory":"Insurance Agent",
            "type":"Services"
        }
    ],
    "sg:phone":"+41 22 731 44 70",
    "sg:postcode":"1201",
    "sg:province":"Gen\u00e8ve",
    "sg:tags":[
        "versicherungsagenturen",
        "-broker"
    ],
    "wof:name":"Commercial-service Henzler Toutes Assurances",
    "wof:placetype":"venue"
},
  "geometry": {"coordinates":[6.1413121223,46.2061691284],"type":"Point"}
}