{
  "type": "Feature",
  "properties": {
    "iso:country":"CH",
    "sg:address":"Reichenauerstrasse 20",
    "sg:city":"Tamins",
    "sg:orig_category":"Fachdetailhandel in Verkaufsr\u00e4umen",
    "sg:postcode":"7015",
    "sg:province":"Graubunden",
    "wof:name":"S'bluem\u00e4gsichtli, M\u00fcller Maja",
    "wof:placetype":"venue"
},
  "geometry": {"coordinates":[9.4070940018,46.8278503418],"type":"Point"}
}