{
  "type": "Feature",
  "properties": {
    "iso:country":"CH",
    "sg:address":"Bahnhofplatz 11 9100 Herisau. Postfach",
    "sg:city":"Herisau",
    "sg:orig_category":"Architektur U Ingenieurb\u00fcros",
    "sg:postcode":"9101",
    "sg:province":"Appenzell Ausserrhoden",
    "wof:name":"Vip Swiss Prozesstechnik Gmbh",
    "wof:placetype":"venue"
},
  "geometry": {"coordinates":[9.279048,47.390812],"type":"Point"}
}