{
  "type": "Feature",
  "properties": {
    "iso:country":"CH",
    "sg:address":"5000 Aarau. Postfach 4155",
    "sg:city":"Aarau",
    "sg:orig_category":"Sportvereine Triathlon Laufen, Schwimmen, Velo",
    "sg:phone":"+41 56 288 35 18",
    "sg:postcode":"5001",
    "sg:province":"Aargau",
    "wof:name":"Triathlon Club Baden",
    "wof:placetype":"venue"
},
  "geometry": {"coordinates":[8.2824935913,47.455078125],"type":"Point"}
}