{
  "type": "Feature",
  "properties": {
    "iso:country":"CH",
    "sg:address":"Route Mon-repos 5a",
    "sg:city":"Fribourg",
    "sg:classifiers":[
        {
            "category":"Restaurant",
            "type":"Food & Drink"
        }
    ],
    "sg:phone":"+41 26 481 56 28",
    "sg:postcode":"1700",
    "sg:province":"Fribourg",
    "wof:name":"Caf\u00e9 De L' Esplanade",
    "wof:placetype":"venue"
},
  "geometry": {"coordinates":[7.1734428406,46.8089256287],"type":"Point"}
}