{
  "type": "Feature",
  "properties": {
    "iso:country":"CH",
    "sg:address":"Grosser Bongert 8",
    "sg:city":"Triesen",
    "sg:orig_category":"Sportvereine Turnen Vereine Damen",
    "sg:phone":"+41 71 911 03 70",
    "sg:postcode":"9495",
    "wof:name":"Frauenriege Des Stv",
    "wof:placetype":"venue"
},
  "geometry": {"coordinates":[9.061217308,47.4663925171],"type":"Point"}
}