{
  "type": "Feature",
  "properties": {
    "addr:full":"Sur Le Cr\u00eat 4 Corg\u00e9mont Bern 2606",
    "addr:housenumber":"4",
    "addr:postcode":"2606",
    "addr:street":"Le Cre\u0302T;Bern",
    "iso:country":"CH",
    "sg:address":"Sur Le Cr\u00eat 4",
    "sg:city":"Corg\u00e9mont",
    "sg:classifiers":[
        {
            "category":"Social Services",
            "subcategory":"Retirement Home",
            "type":"Services"
        }
    ],
    "sg:phone":"+41 26 407 35 33",
    "sg:postcode":"2606",
    "sg:province":"Bern",
    "sg:tags":[
        "pflegeheime",
        "u",
        "alters"
    ],
    "wof:name":"Les Martinets Home Pour Personnes \u00e2g\u00e9es",
    "wof:placetype":"venue"
},
  "geometry": {"coordinates":[7.1289,46.790932],"type":"Point"}
}