{
  "type": "Feature",
  "properties": {
    "iso:country":"CH",
    "sg:address":"6963",
    "sg:city":"Pregassona",
    "sg:orig_category":"RESTAURANTS: TEA-ROOMS",
    "sg:postcode":"6963",
    "sg:province":"Ticino",
    "wof:name":"Cassina Domenica",
    "wof:placetype":"venue"
},
  "geometry": {"coordinates":[8.9781703949,46.0223617554],"type":"Point"}
}