{
  "type": "Feature",
  "properties": {
    "iso:country":"CH",
    "sg:address":"Kosthausstrasse 8",
    "sg:city":"Kriens",
    "sg:orig_category":"Herstellung von K\u00fcchenm\u00f6beln",
    "sg:phone":"+41 79 694 46 93",
    "sg:postcode":"6010",
    "sg:province":"Luzern",
    "wof:name":"Mb Montagen Mario Boselli",
    "wof:placetype":"venue"
},
  "geometry": {"coordinates":[8.2748184204,47.0338096619],"type":"Point"}
}