{
  "type": "Feature",
  "properties": {
    "iso:country":"CH",
    "sg:address":"Einsiedlerstrasse 71c",
    "sg:city":"Horgen",
    "sg:orig_category":"Vereine Orchester",
    "sg:phone":"+41 17251375",
    "sg:postcode":"8810",
    "sg:province":"Z\u00fcrich",
    "wof:name":"Orchesterverein Horgen-thalwil",
    "wof:placetype":"venue"
},
  "geometry": {"coordinates":[8.5868215561,47.2638320923],"type":"Point"}
}