{
  "type": "Feature",
  "properties": {
    "iso:country":"CH",
    "sg:address":"Bahnstrasse 46",
    "sg:city":"Heerbrugg",
    "sg:orig_category":"Grosshandel mit Flachglas, Sanit\u00e4rkeramik U Anstrichmitteln Herstellung von Anstrichmitteln, Druckfa",
    "sg:phone":"+41 71 722 40 25",
    "sg:postcode":"9435",
    "sg:province":"St. Gallen",
    "wof:name":"Keimfarben Ag",
    "wof:placetype":"venue"
},
  "geometry": {"coordinates":[9.6249303818,47.4148712158],"type":"Point"}
}