{
  "type": "Feature",
  "properties": {
    "iso:country":"CH",
    "sg:city":"Muotathal",
    "sg:orig_category":"Reisen, Reiseb\u00fcros",
    "sg:postcode":"6436",
    "sg:province":"Schwyz",
    "wof:name":"Mountain Adventures",
    "wof:placetype":"venue"
},
  "geometry": {"coordinates":[8.7583,46.973976],"type":"Point"}
}