{
  "type": "Feature",
  "properties": {
    "iso:country":"CH",
    "sg:address":"Landstrasse 4",
    "sg:city":"Rafz",
    "sg:orig_category":"Herstellung von Elektrizit\u00e4tsverteilungs U schalteinrichtungen",
    "sg:phone":"+41 19407062",
    "sg:postcode":"8197",
    "sg:province":"Z\u00fcrich",
    "wof:name":"Technoprocur Ag",
    "wof:placetype":"venue"
},
  "geometry": {"coordinates":[8.5390338898,47.6105384827],"type":"Point"}
}