{
  "type": "Feature",
  "properties": {
    "iso:country":"CH",
    "sg:address":"Haselweg 10 5722 Gr\u00e4nichen. Postfach 220",
    "sg:city":"Gr\u00e4nichen",
    "sg:orig_category":"Herstellung von Schrauben, Nieten, Ketten U Federn Maschinenbau",
    "sg:phone":"+41 62 842 14 06",
    "sg:postcode":"5722",
    "sg:province":"Aargau",
    "wof:name":"Gautschi S\u00f6hne Ag",
    "wof:placetype":"venue"
},
  "geometry": {"coordinates":[8.0930328369,47.3610115051],"type":"Point"}
}