{
  "type": "Feature",
  "properties": {
    "iso:country":"CH",
    "sg:address":"Klingental 20",
    "sg:city":"Basel",
    "sg:classifiers":[
        {
            "category":"Travel",
            "subcategory":"Hotels & Motels",
            "type":"Entertainment"
        }
    ],
    "sg:phone":"+41 61 681 62 48",
    "sg:postcode":"4058",
    "sg:province":"Basel-Stadt",
    "sg:tags":[
        "hotels",
        "mit",
        "restaurant"
    ],
    "wof:name":"Hotel Klingental Garni",
    "wof:placetype":"venue"
},
  "geometry": {"coordinates":[7.5909380913,47.5624084473],"type":"Point"}
}