{
  "type": "Feature",
  "properties": {
    "iso:country":"CH",
    "sg:address":"J.c. Heerstrasse 22",
    "sg:city":"D\u00fcrnten",
    "sg:orig_category":"Malerei Tapeziererei",
    "sg:phone":"+41 55 240 62 63",
    "sg:postcode":"8635",
    "sg:province":"Z\u00fcrich",
    "wof:name":"Hermann Loosli Malergesch\u00e4ft",
    "wof:placetype":"venue"
},
  "geometry": {"coordinates":[8.8738479614,47.2757415771],"type":"Point"}
}