{
  "type": "Feature",
  "properties": {
    "iso:country":"CH",
    "sg:address":"H\u00f6henweg 60",
    "sg:city":"St.gallen",
    "sg:orig_category":"Allgemeinbildende weiterf\u00fchrende Schulen",
    "sg:postcode":"9000",
    "sg:province":"St. Gallen",
    "wof:name":"Institut De Beaulieu, Mme Jaccard.",
    "wof:placetype":"venue"
},
  "geometry": {"coordinates":[6.858149,46.458996],"type":"Point"}
}