{
  "type": "Feature",
  "properties": {
    "iso:country":"CH",
    "sg:address":"Dorfstrasse 41",
    "sg:city":"Matzendorf",
    "sg:orig_category":"Detailhandel mit Waren verschiedener Art, Hauptrichtung Nahrungsmittel",
    "sg:phone":"+41 62 394 11 23",
    "sg:postcode":"4713",
    "sg:province":"Solothurn",
    "wof:name":"Coop Oberaargau-thal/g\u00e4u",
    "wof:placetype":"venue"
},
  "geometry": {"coordinates":[7.62940979,47.3062019348],"type":"Point"}
}