{
  "type": "Feature",
  "properties": {
    "iso:country":"CH",
    "sg:address":"Werchlaubeng\u00e4ssli 6",
    "sg:city":"Luzern",
    "sg:orig_category":"Detailhandel mit Uhren U Schmuck Herstellung von Schmuck, Gold U Silberschmiedwaren",
    "sg:phone":"+41 41 410 20 36",
    "sg:postcode":"6004",
    "sg:province":"Luzern",
    "wof:name":"Schmuckwerkstatt Schedler Kurt",
    "wof:placetype":"venue"
},
  "geometry": {"coordinates":[8.3059206009,47.0524330139],"type":"Point"}
}