{
  "type": "Feature",
  "properties": {
    "iso:country":"CH",
    "sg:address":"Fulenbacherstrasse 230",
    "sg:city":"Boningen",
    "sg:orig_category":"Instandhaltung U Reparatur von Automobilen",
    "sg:postcode":"4618",
    "sg:province":"Solothurn",
    "wof:name":"Carrosserie Spritzwerk Schumacher M.",
    "wof:placetype":"venue"
},
  "geometry": {"coordinates":[7.8528618813,47.3025894165],"type":"Point"}
}