{
  "type": "Feature",
  "properties": {
    "iso:country":"CH",
    "sg:address":"Rue Des Finages 3",
    "sg:city":"Court\u00e9telle",
    "sg:orig_category":"Politische Parteien CVP",
    "sg:phone":"+41 56 222 35 23",
    "sg:postcode":"2852",
    "sg:province":"Jura",
    "wof:name":"Junge Cvp Des Kantons Aargau",
    "wof:placetype":"venue"
},
  "geometry": {"coordinates":[8.2921733856,47.4875640869],"type":"Point"}
}