{
  "type": "Feature",
  "properties": {
    "iso:country":"CH",
    "sg:address":"Route Wilhelm-kaiser 9 1700 Fribourg. Postfach",
    "sg:city":"Fribourg",
    "sg:orig_category":"Unclassifiable Establishments",
    "sg:phone":"+41 26 424 47 30",
    "sg:postcode":"1705",
    "sg:province":"Fribourg",
    "wof:name":"Parti D\u00e9mocrate-chr\u00e9tien Fribourgeois",
    "wof:placetype":"venue"
},
  "geometry": {"coordinates":[7.1550841331,46.7948303223],"type":"Point"}
}