{
  "type": "Feature",
  "properties": {
    "iso:country":"CH",
    "sg:address":"Lehenmattstrasse 252 4052 Basel. Postfach",
    "sg:city":"Basel",
    "sg:orig_category":"Unclassifiable Establishments",
    "sg:postcode":"4058",
    "sg:province":"Basel-Stadt",
    "wof:name":"Immobilien-aktiengesellschaft Landhof",
    "wof:placetype":"venue"
},
  "geometry": {"coordinates":[7.6209011078,47.5476646423],"type":"Point"}
}