{
  "type": "Feature",
  "properties": {
    "iso:country":"CH",
    "sg:address":"8926",
    "sg:city":"Hauptikon",
    "sg:orig_category":"Autogaragen",
    "sg:phone":"+41 91 858 15 29",
    "sg:postcode":"8926",
    "sg:province":"Z\u00fcrich",
    "wof:name":"Savio Bettosini Garage",
    "wof:placetype":"venue"
},
  "geometry": {"coordinates":[8.979807,46.154369],"type":"Point"}
}