{
  "type": "Feature",
  "properties": {
    "iso:country":"CH",
    "sg:address":"R\u00fctschigasse 1",
    "sg:city":"Otelfingen",
    "sg:classifiers":[
        {
            "category":"Restaurant",
            "type":"Food & Drink"
        }
    ],
    "sg:phone":"+41 71 931 12 92",
    "sg:postcode":"8112",
    "sg:province":"Z\u00fcrich",
    "wof:name":"Restaurant Frohsinn",
    "wof:placetype":"venue"
},
  "geometry": {"coordinates":[9.0237102509,47.4117889404],"type":"Point"}
}