{
  "type": "Feature",
  "properties": {
    "iso:country":"CH",
    "sg:address":"Lenzburgerstrasse 60",
    "sg:city":"Wildegg",
    "sg:classifiers":[
        {
            "category":"Building & Trades",
            "subcategory":"Plumbing",
            "type":"Services"
        }
    ],
    "sg:phone":"+41 62 887 55 00",
    "sg:postcode":"5103",
    "sg:province":"Aargau",
    "sg:tags":[
        "tub",
        "bath"
    ],
    "wof:name":"Sanit\u00e4re Apparate Hunziker Ag",
    "wof:placetype":"venue"
},
  "geometry": {"coordinates":[8.165059,47.413044],"type":"Point"}
}