{
  "type": "Feature",
  "properties": {
    "iso:country":"CH",
    "sg:address":"Byfangweg 18",
    "sg:city":"Herzogenbuchsee",
    "sg:orig_category":"Herstellung von sonstigen Holzwaren",
    "sg:phone":"+41 62 956 30 70",
    "sg:postcode":"3360",
    "sg:province":"Bern",
    "wof:name":"Aegerter Fritz Ag",
    "wof:placetype":"venue"
},
  "geometry": {"coordinates":[7.6973538399,47.1959953308],"type":"Point"}
}