{
  "type": "Feature",
  "properties": {
    "iso:country":"CH",
    "sg:address":"Gotthardstrasse 22 6410 Goldau. Postfach 44",
    "sg:city":"Goldau",
    "sg:orig_category":"Detailhandel Handel mit Motorr\u00e4dern, Teilen U Zubeh\u00f6r Instandhaltung U Reparatur von Motorr\u00e4dern Rep",
    "sg:phone":"+41 41 855 32 73",
    "sg:postcode":"6410",
    "sg:province":"Schwyz",
    "wof:name":"Alfred L\u00fc\u00f6nd Euro-motos",
    "wof:placetype":"venue"
},
  "geometry": {"coordinates":[8.5483999252,47.0499839783],"type":"Point"}
}