{
  "type": "Feature",
  "properties": {
    "iso:country":"CH",
    "sg:address":"Kantonsstrasse 40 6048 Horw. Postfach 379",
    "sg:city":"Horw",
    "sg:orig_category":"Grossbanken",
    "sg:phone":"+41 41 349 63 63",
    "sg:postcode":"6048",
    "sg:province":"Luzern",
    "wof:name":"Credit Suisse",
    "wof:placetype":"venue"
},
  "geometry": {"coordinates":[8.3085193634,47.0232467651],"type":"Point"}
}