{
  "type": "Feature",
  "properties": {
    "iso:country":"CH",
    "sg:address":"Mellingerstrasse 1",
    "sg:city":"Baden",
    "sg:classifiers":[
        {
            "category":"Manufacturing",
            "subcategory":"Building Materials",
            "type":"Manufacturing & Wholesale Goods"
        }
    ],
    "sg:phone":"+41 56 222 19 55",
    "sg:postcode":"5400",
    "sg:province":"Aargau",
    "sg:tags":[
        "filter",
        "dust",
        "separation",
        "air"
    ],
    "wof:name":"Haprag Ag",
    "wof:placetype":"venue"
},
  "geometry": {"coordinates":[8.305285,47.471012],"type":"Point"}
}