{
  "type": "Feature",
  "properties": {
    "iso:country":"CH",
    "sg:address":"Zwillikerstrasse 18",
    "sg:city":"Hedingen",
    "sg:orig_category":"Geb\u00e4ude, Wohnungsreinigung W\u00e4scherei U chemische Reinigung",
    "sg:phone":"+41 17618680",
    "sg:postcode":"8908",
    "sg:province":"Z\u00fcrich",
    "wof:name":"Margot Hotz B\u00fcgelservice",
    "wof:placetype":"venue"
},
  "geometry": {"coordinates":[8.4465208054,47.2965278625],"type":"Point"}
}