{
  "type": "Feature",
  "properties": {
    "iso:country":"CH",
    "sg:address":"Rue Ecole-de-m\u00e9decine 7",
    "sg:city":"Gen\u00e8ve",
    "sg:classifiers":[
        {
            "category":"Government",
            "subcategory":"Post Office",
            "type":"Public Place"
        }
    ],
    "sg:phone":"+41 22 321 00 13",
    "sg:postcode":"1205",
    "sg:province":"Gen\u00e8ve",
    "sg:tags":[
        "caf\u00e9s",
        "tea-rooms"
    ],
    "wof:name":"Tea-room Epi Dor\u00e9 Ii",
    "wof:placetype":"venue"
},
  "geometry": {"coordinates":[6.1386780739,46.1973762512],"type":"Point"}
}