{
  "type": "Feature",
  "properties": {
    "iso:country":"CH",
    "sg:address":"Hauptstrasse 46",
    "sg:city":"Binningen",
    "sg:orig_category":"Non-Classified Establishments",
    "sg:postcode":"4102",
    "sg:province":"Basel-Landschaft",
    "wof:name":"Efbe Immobilien Ag",
    "wof:placetype":"venue"
},
  "geometry": {"coordinates":[7.5736842155,47.5412216187],"type":"Point"}
}