{
  "type": "Feature",
  "properties": {
    "iso:country":"CH",
    "sg:address":"Manzenweg 2",
    "sg:city":"Fruthwilen",
    "sg:orig_category":"Allgemeiner Hoch U Tiefbau Spezieller Tiefbau",
    "sg:phone":"+41 71 664 21 31",
    "sg:postcode":"8559",
    "wof:name":"Farner Peter",
    "wof:placetype":"venue"
},
  "geometry": {"coordinates":[9.066534,47.662586],"type":"Point"}
}