{
  "type": "Feature",
  "properties": {
    "iso:country":"CH",
    "sg:address":"Route Du Simplon 20",
    "sg:city":"Sierre",
    "sg:orig_category":"RESTAURANTS: TEA-ROOMS",
    "sg:postcode":"3960",
    "sg:province":"Valais",
    "wof:name":"Essellier Pierre",
    "wof:placetype":"venue"
},
  "geometry": {"coordinates":[7.5392951965,46.2959632874],"type":"Point"}
}