{
  "type": "Feature",
  "properties": {
    "iso:country":"CH",
    "sg:address":"1936",
    "sg:city":"Verbier",
    "sg:orig_category":"Vermittlung von Immobilien",
    "sg:phone":"+41 55 410 22 03",
    "sg:postcode":"1936",
    "sg:province":"Valais",
    "wof:name":"Charles Z\u00fcger Immobilien",
    "wof:placetype":"venue"
},
  "geometry": {"coordinates":[8.7833595276,47.2014961243],"type":"Point"}
}