{
  "type": "Feature",
  "properties": {
    "iso:country":"CH",
    "sg:address":"Vall\u00e0 Via 8",
    "sg:city":"Camorino",
    "sg:orig_category":"Fachdetailhandel in Verkaufsr\u00e4umen",
    "sg:phone":"+41 91 858 12 85",
    "sg:postcode":"6528",
    "sg:province":"Ticino",
    "wof:name":"Mognol Luigi",
    "wof:placetype":"venue"
},
  "geometry": {"coordinates":[9.004901886,46.1623497009],"type":"Point"}
}