{
  "type": "Feature",
  "properties": {
    "iso:country":"CH",
    "sg:address":"Au Chevrey",
    "sg:city":"Pont-la-ville",
    "sg:orig_category":"Nahrungsmittel-Industrie: Rohstoffe",
    "sg:phone":"+41 26 413 29 85",
    "sg:postcode":"1649",
    "sg:province":"Fribourg",
    "wof:name":"Schwaller Dr. P. Consulting",
    "wof:placetype":"venue"
},
  "geometry": {"coordinates":[7.1126132011,46.6907653809],"type":"Point"}
}