{
  "type": "Feature",
  "properties": {
    "iso:country":"CH",
    "sg:address":"Roncacci Via",
    "sg:city":"Tenero",
    "sg:orig_category":"RESTAURANTS: TEA-ROOMS",
    "sg:postcode":"6598",
    "sg:province":"Ticino",
    "wof:name":"Auria Sagl",
    "wof:placetype":"venue"
},
  "geometry": {"coordinates":[8.8498601913,46.180896759],"type":"Point"}
}