{
  "type": "Feature",
  "properties": {
    "iso:country":"CH",
    "sg:address":"Hofstr. 70",
    "sg:city":"Z\u00fcrich",
    "sg:classifiers":[
        {
            "category":"Park",
            "type":"Public Place"
        }
    ],
    "sg:phone":"+41 4112512771",
    "sg:postcode":"8032",
    "sg:province":"Z\u00fcrich",
    "sg:tags":[
        "work",
        "construction",
        "sport"
    ],
    "wof:name":"E. Fritz Ag",
    "wof:placetype":"venue"
},
  "geometry": {"coordinates":[8.561094,47.372845],"type":"Point"}
}