{
  "type": "Feature",
  "properties": {
    "iso:country":"CH",
    "sg:address":"Blignoud",
    "sg:city":"Ayent",
    "sg:orig_category":"Autospenglereien",
    "sg:phone":"+41 27 398 16 31",
    "sg:postcode":"1966",
    "sg:province":"Valais",
    "wof:name":"Olivier Constantin Carrosserie Du Chamossaire",
    "wof:placetype":"venue"
},
  "geometry": {"coordinates":[7.39833,46.27219],"type":"Point"}
}