{
  "type": "Feature",
  "properties": {
    "iso:country":"CH",
    "sg:address":"Sandhof",
    "sg:city":"Richterswil",
    "sg:orig_category":"Forschung U Entwicklung im Bereich der Naturwissenschaften",
    "sg:postcode":"8805",
    "sg:province":"Z\u00fcrich",
    "wof:name":"Bitanx (aero), Bircher Thomas",
    "wof:placetype":"venue"
},
  "geometry": {"coordinates":[8.7291297913,47.1972198486],"type":"Point"}
}