{
  "type": "Feature",
  "properties": {
    "iso:country":"CH",
    "sg:address":"Rue Du Pont 5 1003 Lausanne. Postfach",
    "sg:city":"Lausanne",
    "sg:orig_category":"Reiseb\u00fcros",
    "sg:phone":"+41 21 925 09 50",
    "sg:postcode":"1002",
    "sg:province":"Vaud",
    "wof:name":"Imholz Agences Sa",
    "wof:placetype":"venue"
},
  "geometry": {"coordinates":[5.1808700562,45.8973388672],"type":"Point"}
}