{
  "type": "Feature",
  "properties": {
    "iso:country":"CH",
    "sg:address":"1958",
    "sg:city":"Uvrier",
    "sg:orig_category":"Primarschulen",
    "sg:postcode":"1958",
    "sg:province":"Valais",
    "wof:name":"Ecole Primaire",
    "wof:placetype":"venue"
},
  "geometry": {"coordinates":[7.4412097931,46.1751708984],"type":"Point"}
}