{
  "type": "Feature",
  "properties": {
    "iso:country":"CH",
    "sg:address":"4057 Basel. Postfach",
    "sg:city":"Basel",
    "sg:orig_category":"Organisationen des Gesundheitswesen",
    "sg:phone":"+41 79 243 78 30",
    "sg:postcode":"4004",
    "sg:province":"Basel-Stadt",
    "wof:name":"Samariterverein St.niklaus",
    "wof:placetype":"venue"
},
  "geometry": {"coordinates":[7.8021001816,46.1756591797],"type":"Point"}
}