{
  "type": "Feature",
  "properties": {
    "iso:country":"CH",
    "sg:address":"1468",
    "sg:city":"Cheyres",
    "sg:orig_category":"Malerei Stukkateurgewerbe, Gipserei U Verputzerei",
    "sg:phone":"+41 79 205 45 49",
    "sg:postcode":"1468",
    "sg:province":"Fribourg",
    "wof:name":"Jean Thorens Pl\u00e2trerie & Peinture",
    "wof:placetype":"venue"
},
  "geometry": {"coordinates":[6.8548531532,46.4531669617],"type":"Point"}
}