{
  "type": "Feature",
  "properties": {
    "iso:country":"CH",
    "sg:address":"Dorfstrasse 2",
    "sg:city":"Hinterkappelen",
    "sg:orig_category":"Satzherstellung U Reproduktion",
    "sg:phone":"+41 31 901 05 36",
    "sg:postcode":"3032",
    "sg:province":"Bern",
    "wof:name":"Repro Marti Digital Ag Druckvorstufe",
    "wof:placetype":"venue"
},
  "geometry": {"coordinates":[7.3778209686,46.9677619934],"type":"Point"}
}