{
  "type": "Feature",
  "properties": {
    "iso:country":"CH",
    "sg:address":"Hauptstrasse 96",
    "sg:city":"Wittnau",
    "sg:orig_category":"Unclassifiable Establishments",
    "sg:postcode":"5064",
    "sg:province":"Aargau",
    "wof:name":"Gartenbau Urwyler",
    "wof:placetype":"venue"
},
  "geometry": {"coordinates":[7.9710068703,47.4775657654],"type":"Point"}
}