{
  "type": "Feature",
  "properties": {
    "iso:country":"CH",
    "sg:address":"Via Vela 3",
    "sg:city":"Chiasso",
    "sg:orig_category":"Architektur U Ingenieurb\u00fcros Markt U Meinungsforschung",
    "sg:phone":"+41 91 682 40 10",
    "sg:postcode":"6830",
    "sg:province":"Ticino",
    "wof:name":"Future Engineering Sa",
    "wof:placetype":"venue"
},
  "geometry": {"coordinates":[9.027667,45.836025],"type":"Point"}
}