{
  "type": "Feature",
  "properties": {
    "iso:country":"CH",
    "sg:address":"Hauptstrasse 29",
    "sg:city":"Flaach",
    "sg:classifiers":[
        {
            "category":"Restaurant",
            "type":"Food & Drink"
        }
    ],
    "sg:phone":"+41 71 311 18 19",
    "sg:postcode":"8416",
    "sg:province":"Z\u00fcrich",
    "wof:name":"Restaurant Sternen",
    "wof:placetype":"venue"
},
  "geometry": {"coordinates":[9.3180160522,47.4217033386],"type":"Point"}
}