{
  "type": "Feature",
  "properties": {
    "iso:country":"CH",
    "sg:address":"Chavannes Route De 39 1007 Lausanne Case Postale 124",
    "sg:city":"Lausanne",
    "sg:orig_category":"Sonstiger spezialisierter Hoch U Tiefbau",
    "sg:phone":"+41 21 644 20 05",
    "sg:postcode":"1007",
    "sg:province":"Vaud",
    "wof:name":"Jr Carrelages Sa",
    "wof:placetype":"venue"
},
  "geometry": {"coordinates":[6.5949668884,46.5225143433],"type":"Point"}
}