{
  "type": "Feature",
  "properties": {
    "iso:country":"CH",
    "sg:address":"B\u00fcrkiweg 8",
    "sg:city":"Bern",
    "sg:orig_category":"Architektur U Ingenieurb\u00fcros",
    "sg:phone":"+41 31 371 02 52",
    "sg:postcode":"3007",
    "sg:province":"Bern",
    "wof:name":"Schneider Konstruktionen",
    "wof:placetype":"venue"
},
  "geometry": {"coordinates":[7.430401,46.939461],"type":"Point"}
}