{
  "type": "Feature",
  "properties": {
    "iso:country":"CH",
    "sg:address":"Champ-d'anier Chemin Du 8 1209 Gen\u00e8ve. Postfach",
    "sg:city":"Gen\u00e8ve",
    "sg:orig_category":"Non-Classified Establishments",
    "sg:postcode":"1209",
    "sg:province":"Gen\u00e8ve",
    "wof:name":"Si Corsier-parc",
    "wof:placetype":"venue"
},
  "geometry": {"coordinates":[6.1014318466,46.2022628784],"type":"Point"}
}