{
  "type": "Feature",
  "properties": {
    "addr:full":"Bruggerstrasse 37 Baden Aargau 5400",
    "addr:housenumber":"37",
    "addr:postcode":"5400",
    "addr:street":"Bruggerstrasse",
    "iso:country":"CH",
    "sg:address":"Bruggerstrasse 37",
    "sg:city":"Baden",
    "sg:orig_category":"Architekturb\u00fcros",
    "sg:phone":"+41 56 222 42 77",
    "sg:postcode":"5400",
    "sg:province":"Aargau",
    "wof:name":"Zulauf & Schmidlin Architekturb\u00fcro",
    "wof:placetype":"venue"
},
  "geometry": {"coordinates":[8.304784,47.476402],"type":"Point"}
}