{
  "type": "Feature",
  "properties": {
    "iso:country":"CH",
    "sg:address":"Route De Courgenay 37",
    "sg:city":"Alle",
    "sg:classifiers":[
        {
            "category":"Shopping Center",
            "type":"Public Place"
        }
    ],
    "sg:phone":"+41 32 926 26 60",
    "sg:postcode":"2942",
    "sg:province":"Jura",
    "sg:tags":[
        "case",
        "clock"
    ],
    "wof:name":"Neuenschwander Composants Horlogers Sa",
    "wof:placetype":"venue"
},
  "geometry": {"coordinates":[6.816504,47.097462],"type":"Point"}
}