{
  "type": "Feature",
  "properties": {
    "iso:country":"CH",
    "sg:address":"Quellenweg 1",
    "sg:city":"Safnern",
    "sg:orig_category":"Vermietung U Verpachtung von eigenen Immobilien",
    "sg:phone":"+41 32 355 41 31",
    "sg:postcode":"2553",
    "sg:province":"Bern",
    "wof:name":"R\u00e4bli Immo Ag",
    "wof:placetype":"venue"
},
  "geometry": {"coordinates":[7.3211350441,47.151714325],"type":"Point"}
}