{
  "type": "Feature",
  "properties": {
    "iso:country":"CH",
    "sg:address":"Schwalmenackerstrasse 19",
    "sg:city":"Winterthur",
    "sg:orig_category":"RESTAURANTS: TEA-ROOMS",
    "sg:phone":"+41 33 243 13 08",
    "sg:postcode":"8400",
    "sg:province":"Z\u00fcrich",
    "wof:name":"Frautschi, E.",
    "wof:placetype":"venue"
},
  "geometry": {"coordinates":[7.6698408127,46.7306213379],"type":"Point"}
}