{
  "type": "Feature",
  "properties": {
    "iso:country":"CH",
    "sg:address":"Am Brunnenb\u00e4chli 4",
    "sg:city":"Zollikon",
    "sg:orig_category":"Kauf U Verkauf von Immobilien auf eigene Rechnung",
    "sg:postcode":"8702",
    "sg:province":"Z\u00fcrich",
    "wof:name":"Serpico Ag",
    "wof:placetype":"venue"
},
  "geometry": {"coordinates":[9.4033975601,47.4359321594],"type":"Point"}
}