{
  "type": "Feature",
  "properties": {
    "iso:country":"CH",
    "sg:address":"Via Alpsu 323",
    "sg:city":"Rueras",
    "sg:classifiers":[
        {
            "category":"Travel",
            "subcategory":"Hotels & Motels",
            "type":"Entertainment"
        }
    ],
    "sg:phone":"+41 81 949 11 12",
    "sg:postcode":"7189",
    "sg:province":"Graubunden",
    "sg:tags":[
        "hotels",
        "mit",
        "restaurant"
    ],
    "wof:name":"Hotel Rheinquelle",
    "wof:placetype":"venue"
},
  "geometry": {"coordinates":[8.7437648773,46.6696128845],"type":"Point"}
}