{
  "type": "Feature",
  "properties": {
    "iso:country":"CH",
    "sg:address":"Route De La Gribannaz",
    "sg:city":"Bex",
    "sg:orig_category":"Bauschreinerei Zimmerei, Ingenieurholzbau",
    "sg:phone":"+41 32 936 14 06",
    "sg:postcode":"1880",
    "sg:province":"Vaud",
    "wof:name":"Jean-michel Gaberell Menuiserie & Charpente",
    "wof:placetype":"venue"
},
  "geometry": {"coordinates":[6.703417,47.01318],"type":"Point"}
}