{
  "type": "Feature",
  "properties": {
    "iso:country":"CH",
    "sg:address":"Hermenweg 1",
    "sg:city":"Sch\u00f6ftland",
    "sg:orig_category":"Organisationen des Gesundheitswesen",
    "sg:phone":"+41 62 721 32 63",
    "sg:postcode":"5040",
    "sg:province":"Aargau",
    "wof:name":"Samariterverein Sch\u00f6ftland",
    "wof:placetype":"venue"
},
  "geometry": {"coordinates":[8.0581169128,47.3038787842],"type":"Point"}
}