{
  "type": "Feature",
  "properties": {
    "iso:country":"CH",
    "sg:address":"Avenue Fran\u00e7ois-besson 1",
    "sg:city":"Meyrin",
    "sg:orig_category":"Arztpraxen",
    "sg:phone":"+41 22 782 74 54",
    "sg:postcode":"1217",
    "sg:province":"Gen\u00e8ve",
    "wof:name":"Dr M\u00e9d. Dominique Peterschmitt M\u00e9decin G\u00e9n\u00e9raliste",
    "wof:placetype":"venue"
},
  "geometry": {"coordinates":[6.07902,46.233391],"type":"Point"}
}