{
  "type": "Feature",
  "properties": {
    "iso:country":"CH",
    "sg:address":"6110",
    "sg:city":"Fontannen",
    "sg:orig_category":"RESTAURANTS: TEA-ROOMS",
    "sg:phone":"+41 41 490 28 88",
    "sg:postcode":"6110",
    "sg:province":"Luzern",
    "wof:name":"Restaurant Pintli Studer Sandra",
    "wof:placetype":"venue"
},
  "geometry": {"coordinates":[-87.24467468260001,39.5739784241],"type":"Point"}
}