{
  "type": "Feature",
  "properties": {
    "iso:country":"CH",
    "sg:address":"Rue Rothschild 35 1200 Genf. Postfach",
    "sg:city":"Gen\u00e8ve",
    "sg:orig_category":"Softwareentwicklung U beratung",
    "sg:phone":"+41 22 908 27 00",
    "sg:postcode":"1201",
    "sg:province":"Gen\u00e8ve",
    "wof:name":"Finlab Sa",
    "wof:placetype":"venue"
},
  "geometry": {"coordinates":[6.1488008499,46.2148170471],"type":"Point"}
}