{
  "type": "Feature",
  "properties": {
    "iso:country":"CH",
    "sg:address":"Aufhofen 27",
    "sg:city":"Thundorf",
    "sg:orig_category":"Architektur U Ingenieurb\u00fcros",
    "sg:phone":"+41 52 376 33 00",
    "sg:postcode":"8512",
    "sg:province":"Thurgau",
    "wof:name":"Erbag Oekoplan Gmbh",
    "wof:placetype":"venue"
},
  "geometry": {"coordinates":[8.968202,47.54678],"type":"Point"}
}