{
  "type": "Feature",
  "properties": {
    "iso:country":"CH",
    "sg:address":"1695",
    "sg:city":"Rueyres-st-laurent",
    "sg:orig_category":"Gemeindeverwaltungen",
    "sg:phone":"+41 26 411 14 17",
    "sg:postcode":"1695",
    "sg:province":"Fribourg",
    "wof:name":"Administration Communale Villarsel-le-gibloux",
    "wof:placetype":"venue"
},
  "geometry": {"coordinates":[7.033080101,46.715511322],"type":"Point"}
}