{
  "type": "Feature",
  "properties": {
    "iso:country":"CH",
    "sg:address":"Ch\u00e9zard",
    "sg:city":"Ch\u00e9zard-st-martin",
    "sg:orig_category":"Detailhandel mit Metallwaren, Anstrichmitteln, Glaswaren, Bau U Heimwerkerbedarf",
    "sg:postcode":"2054",
    "sg:province":"Neuch\u00e2tel",
    "wof:name":"Cae Sa, Concept Et Application \u00e9lectrotechnique",
    "wof:placetype":"venue"
},
  "geometry": {"coordinates":[6.9623918533,46.2250595093],"type":"Point"}
}