{
  "type": "Feature",
  "properties": {
    "iso:country":"CH",
    "sg:address":"Rue De L'ancienne-poste 24",
    "sg:city":"Vallorbe",
    "sg:orig_category":"Interessenvertretungen",
    "sg:postcode":"1337",
    "sg:province":"Vaud",
    "wof:name":"Fondation Du Foyer De L'ecolier",
    "wof:placetype":"venue"
},
  "geometry": {"coordinates":[6.8282241821,47.1015625],"type":"Point"}
}