{
  "type": "Feature",
  "properties": {
    "addr:full":"Hauptstrasse 41 4435 Niederdorf. Postfach 158 Niederdorf Basel-Landschaft 4435",
    "addr:housenumber":"41;158",
    "addr:postcode":"4435 niederdorf.;4435",
    "addr:street":"Hauptstrasse;Postfach",
    "iso:country":"CH",
    "sg:address":"Hauptstrasse 41 4435 Niederdorf. Postfach 158",
    "sg:city":"Niederdorf",
    "sg:orig_category":"Aktivit\u00e4ten der Krankenschwestern U Hebammen, Hauspflege Organisationen des Gesundheitswesen",
    "sg:phone":"+41 61 961 11 33",
    "sg:postcode":"4435",
    "sg:province":"Basel-Landschaft",
    "wof:name":"Spitex Waldenburgertal",
    "wof:placetype":"venue"
},
  "geometry": {"coordinates":[7.751572,47.404461],"type":"Point"}
}