{
  "type": "Feature",
  "properties": {
    "iso:country":"CH",
    "sg:address":"Justrain 69",
    "sg:city":"Meilen",
    "sg:orig_category":"Grafikateliers, Design",
    "sg:phone":"+41 19232891",
    "sg:postcode":"8706",
    "sg:province":"Z\u00fcrich",
    "wof:name":"Mathias Hoffmann Design",
    "wof:placetype":"venue"
},
  "geometry": {"coordinates":[8.6541366577,47.2693252563],"type":"Point"}
}