{
  "type": "Feature",
  "properties": {
    "iso:country":"CH",
    "sg:address":"Rellikonstrasse 14",
    "sg:city":"Maur",
    "sg:orig_category":"Einzelhandel mit Automobilteilen U Zubeh\u00f6r Elektroinstallation",
    "sg:phone":"+41 79 350 28 68",
    "sg:postcode":"8124",
    "sg:province":"Z\u00fcrich",
    "wof:name":"Grieffe Sound Heinz M\u00f6hr",
    "wof:placetype":"venue"
},
  "geometry": {"coordinates":[8.6727619171,47.3380393982],"type":"Point"}
}