{
  "type": "Feature",
  "properties": {
    "iso:country":"CH",
    "sg:address":"Dychweg 8",
    "sg:city":"Arlesheim",
    "sg:orig_category":"Grosshandel mit Holz U Baustoffen Herstellung von Konstruktionsteilen, Fertigbauteilen U Ausbaueleme",
    "sg:phone":"+41 79 408 08 58",
    "sg:postcode":"4144",
    "sg:province":"Basel-Landschaft",
    "wof:name":"Schwabe Ch., Tor Und Bauelemente",
    "wof:placetype":"venue"
},
  "geometry": {"coordinates":[7.59628582,47.5060958862],"type":"Point"}
}