{
  "type": "Feature",
  "properties": {
    "addr:full":"Ringstrasse 7302 Landquart. Postfach Landquart Graubunden 7302",
    "addr:postcode":"7302 landquart. postfach;7302",
    "addr:street":"Ringstrasse",
    "iso:country":"CH",
    "sg:address":"Ringstrasse 7302 Landquart. Postfach",
    "sg:city":"Landquart",
    "sg:orig_category":"Allgemeiner Hoch U Tiefbau",
    "sg:postcode":"7302",
    "sg:province":"Graubunden",
    "wof:name":"Reparatur Und Sanierungstechnik R\u00e4tia Ag",
    "wof:placetype":"venue"
},
  "geometry": {"coordinates":[9.559494,46.961285],"type":"Point"}
}