{
  "type": "Feature",
  "properties": {
    "iso:country":"CH",
    "sg:address":"Rue Du Jura 12",
    "sg:city":"Gland",
    "sg:orig_category":"Detailhandel mit Radio U Fernsehger\u00e4ten Detailhandel mit elektrischen Haushalts-,Radio U Fernsehger\u00e4",
    "sg:phone":"+41 56 622 56 87",
    "sg:postcode":"1196",
    "sg:province":"Vaud",
    "wof:name":"W. Strebel Audio-video Ag",
    "wof:placetype":"venue"
},
  "geometry": {"coordinates":[8.2716732025,47.3491172791],"type":"Point"}
}