{
  "type": "Feature",
  "properties": {
    "iso:country":"CH",
    "sg:address":"Avenue De La Gare 56",
    "sg:city":"Chavannes-renens",
    "sg:orig_category":"Stukkateurgewerbe, Gipserei U Verputzerei Tapeziererei",
    "sg:phone":"+41 21 636 09 59",
    "sg:postcode":"1022",
    "sg:province":"Vaud",
    "wof:name":"Longo Giuseppe S\u00e0rl",
    "wof:placetype":"venue"
},
  "geometry": {"coordinates":[6.5756130219,46.5319862366],"type":"Point"}
}