{
  "type": "Feature",
  "properties": {
    "addr:full":"Avenue Des Grandes-communes 26 Onex Gen\u00e8ve 1213",
    "addr:housenumber":"26",
    "addr:postcode":"1213",
    "addr:street":"Avenue Des Grandes-Communes",
    "iso:country":"CH",
    "sg:address":"Avenue Des Grandes-communes 26",
    "sg:city":"Onex",
    "sg:orig_category":"Mechanische Werkst\u00e4tten Schlossereien",
    "sg:phone":"+41 22 792 24 14",
    "sg:postcode":"1213",
    "sg:province":"Gen\u00e8ve",
    "wof:name":"Bertec Sa Atelier M\u00e9canique De Pr\u00e9cision",
    "wof:placetype":"venue"
},
  "geometry": {"coordinates":[6.104528,46.192699],"type":"Point"}
}