{
  "type": "Feature",
  "properties": {
    "iso:country":"CH",
    "sg:address":"Tranchepied Route De 30 1277 Borex. Postfach",
    "sg:city":"Borex",
    "sg:orig_category":"Zimmerei, Dachdeckerei, Bauspenglerei U Abdichtung",
    "sg:phone":"+41 22 367 19 08",
    "sg:postcode":"1277",
    "sg:province":"Vaud",
    "wof:name":"Entreprise Melchiorre Claude Toitures, Ferblanterie-sanitaires Etc",
    "wof:placetype":"venue"
},
  "geometry": {"coordinates":[6.1749968529,46.3807525635],"type":"Point"}
}