{
  "type": "Feature",
  "properties": {
    "iso:country":"CH",
    "sg:address":"Marktgasse 23",
    "sg:city":"Olten",
    "sg:orig_category":"Mit dem Versicherungsgewerbe verbundene T\u00e4tigkeiten",
    "sg:phone":"+41 62 212 23 01",
    "sg:postcode":"4600",
    "sg:province":"Solothurn",
    "wof:name":"Huber E., Consultant",
    "wof:placetype":"venue"
},
  "geometry": {"coordinates":[7.9037361145,47.3493804932],"type":"Point"}
}