{
  "type": "Feature",
  "properties": {
    "iso:country":"CH",
    "sg:address":"Milchg\u00e4ssli 1 6056 K\u00e4giswil. Postfach",
    "sg:city":"Goldau",
    "sg:orig_category":"Erschliessung von Grundst\u00fccken",
    "sg:phone":"+41 41 660 51 54",
    "sg:postcode":"6410",
    "sg:province":"Schwyz",
    "wof:name":"Baugenossenschaft Im Z\u00f6pfli",
    "wof:placetype":"venue"
},
  "geometry": {"coordinates":[8.2616882324,46.9218597412],"type":"Point"}
}