{
  "type": "Feature",
  "properties": {
    "iso:country":"CH",
    "sg:address":"Riedstrasse 14",
    "sg:city":"Dietikon",
    "sg:classifiers":[
        {
            "category":"Restaurant",
            "type":"Food & Drink"
        }
    ],
    "sg:phone":"+41 17463020",
    "sg:postcode":"8953",
    "sg:province":"Z\u00fcrich",
    "wof:name":"Walo's Restaurant Riedhof",
    "wof:placetype":"venue"
},
  "geometry": {"coordinates":[8.3954296112,47.4204406738],"type":"Point"}
}