{
  "type": "Feature",
  "properties": {
    "iso:country":"CH",
    "sg:address":"Im Hofacker 23",
    "sg:city":"Winkel",
    "sg:orig_category":"Einbau von Schreinerwaren",
    "sg:postcode":"8185",
    "sg:province":"Z\u00fcrich",
    "wof:name":"Hauser Montagen, Service, Verkauf",
    "wof:placetype":"venue"
},
  "geometry": {"coordinates":[8.557682991,47.4893722534],"type":"Point"}
}