{
  "type": "Feature",
  "properties": {
    "iso:country":"CH",
    "sg:address":"Kloster Einsiedeln",
    "sg:city":"Einsiedeln",
    "sg:orig_category":"Unclassifiable Establishments",
    "sg:postcode":"8840",
    "sg:province":"Schwyz",
    "wof:name":"Marstall Kloster Einsiedeln Gmbh",
    "wof:placetype":"venue"
},
  "geometry": {"coordinates":[8.7396602631,47.1230812073],"type":"Point"}
}