{
  "type": "Feature",
  "properties": {
    "iso:country":"CH",
    "sg:address":"Reichensteinerstrasse 14 4053 Basel. Postfach",
    "sg:city":"Basel",
    "sg:orig_category":"Grosshandel mit chemischen Erzeugnissen Grosshandel mit medizinischen U orthop\u00e4dischen Artikeln",
    "sg:phone":"+41 71 310 11 60",
    "sg:postcode":"4002",
    "sg:province":"Basel-Stadt",
    "wof:name":"Pangas Gas-fachmarkt & Lieferstelle",
    "wof:placetype":"venue"
},
  "geometry": {"coordinates":[9.3123722076,47.4110488892],"type":"Point"}
}