{
  "type": "Feature",
  "properties": {
    "iso:country":"CH",
    "sg:address":"Chemin De Merdisel 13",
    "sg:city":"Satigny",
    "sg:orig_category":"Instandhaltung U Reparatur von Automobilen",
    "sg:phone":"+41 71 636 11 55",
    "sg:postcode":"1242",
    "sg:province":"Gen\u00e8ve",
    "wof:name":"Gerber H., Auto Elektro",
    "wof:placetype":"venue"
},
  "geometry": {"coordinates":[9.1706132889,47.5797767639],"type":"Point"}
}