{
  "type": "Feature",
  "properties": {
    "iso:country":"CH",
    "sg:address":"Oberschiltstrasse 7",
    "sg:city":"F\u00fcrigen",
    "sg:orig_category":"Unternehmensberatung Wirtschaftspr\u00fcfung, Steuerberatung U Treuhand",
    "sg:phone":"+41 19323200",
    "sg:postcode":"6363",
    "sg:province":"Nidwalden",
    "wof:name":"Silvia Marti Treuhandgesellschaft Mbh",
    "wof:placetype":"venue"
},
  "geometry": {"coordinates":[8.7887907028,47.3217964172],"type":"Point"}
}