{
  "type": "Feature",
  "properties": {
    "iso:country":"CH",
    "sg:address":"R\u00fctschelengasse 12",
    "sg:city":"Burgdorf",
    "sg:orig_category":"Unclassifiable Establishments",
    "sg:postcode":"3400",
    "sg:province":"Bern",
    "wof:name":"Jovanovic Transporte",
    "wof:placetype":"venue"
},
  "geometry": {"coordinates":[7.627363205,47.0549659729],"type":"Point"}
}