{
  "type": "Feature",
  "properties": {
    "iso:country":"CH",
    "sg:address":"Binningerstrasse 15",
    "sg:city":"Basel",
    "sg:orig_category":"RESTAURANTS: TEA-ROOMS",
    "sg:postcode":"4051",
    "sg:province":"Basel-Stadt",
    "wof:name":"Restaurant Bistro, Gnos Daniela Und Caso Michele",
    "wof:placetype":"venue"
},
  "geometry": {"coordinates":[8.6431646347,46.8805770874],"type":"Point"}
}