{
  "type": "Feature",
  "properties": {
    "iso:country":"CH",
    "sg:address":"Seminarstrasse 87",
    "sg:city":"Wettingen",
    "sg:orig_category":"Datenverarbeitungsdienste Softwareentwicklung U beratung",
    "sg:phone":"+41 56 438 04 38",
    "sg:postcode":"5430",
    "sg:province":"Aargau",
    "wof:name":"Travico Gmbh Informatik-dienstleistungen",
    "wof:placetype":"venue"
},
  "geometry": {"coordinates":[8.315171,47.46154],"type":"Point"}
}