{
  "type": "Feature",
  "properties": {
    "iso:country":"CH",
    "sg:address":"Schulhausstrasse",
    "sg:city":"Ebikon",
    "sg:orig_category":"Primarschulen",
    "sg:phone":"+41 41 440 65 00",
    "sg:postcode":"6030",
    "sg:province":"Luzern",
    "wof:name":"Primarschule Zentral",
    "wof:placetype":"venue"
},
  "geometry": {"coordinates":[8.3398227692,47.0799102783],"type":"Point"}
}