{
  "type": "Feature",
  "properties": {
    "iso:country":"CH",
    "sg:address":"Herrenackerstrasse 16 8730 Uznach. Postfach 33",
    "sg:city":"Uznach",
    "sg:orig_category":"Herstellung von sonstigen Erzeugnissen Verwaltung von Immobilien",
    "sg:phone":"+41 91 795 35 90",
    "sg:postcode":"8730",
    "sg:province":"St. Gallen",
    "wof:name":"Casafile",
    "wof:placetype":"venue"
},
  "geometry": {"coordinates":[8.8414697647,46.1437950134],"type":"Point"}
}