{
  "type": "Feature",
  "properties": {
    "iso:country":"CH",
    "sg:address":"Hilfikerstrasse 2",
    "sg:city":"Sarmenstorf",
    "sg:orig_category":"Datenverarbeitungsdienste",
    "sg:phone":"+41 55 410 75 55",
    "sg:postcode":"5614",
    "sg:province":"Aargau",
    "wof:name":"Ml Logistik Ag",
    "wof:placetype":"venue"
},
  "geometry": {"coordinates":[8.778135,47.201378],"type":"Point"}
}