{
  "type": "Feature",
  "properties": {
    "iso:country":"CH",
    "sg:address":"Route Du Bois-genoud 1",
    "sg:city":"Crissier",
    "sg:orig_category":"Grosshandel mit B\u00fcromaschinen Grosshandel mit Datenverarbeitungsger\u00e4ten",
    "sg:phone":"+41 41 469 63 90",
    "sg:postcode":"1023",
    "sg:province":"Vaud",
    "wof:name":"Infopark Ag",
    "wof:placetype":"venue"
},
  "geometry": {"coordinates":[8.1935148239,47.1152954102],"type":"Point"}
}