{
  "type": "Feature",
  "properties": {
    "iso:country":"CH",
    "sg:address":"Stand Rue Du 12 1204 Gen\u00e8ve. Postfach",
    "sg:city":"Gen\u00e8ve",
    "sg:orig_category":"Pensionskassen",
    "sg:postcode":"1204",
    "sg:province":"Gen\u00e8ve",
    "wof:name":"Soci\u00e9t\u00e9 De Secours Mutuels D'employ\u00e9s Du Service Des Eaux Gen\u00e8ve",
    "wof:placetype":"venue"
},
  "geometry": {"coordinates":[6.1451339722,46.2020263672],"type":"Point"}
}