{
  "type": "Feature",
  "properties": {
    "iso:country":"CH",
    "sg:address":"Landstrasse 187",
    "sg:city":"Triesen",
    "sg:orig_category":"Betrieb von Taxis Sonstige Kurierdienste",
    "sg:phone":"+41 79 311 12 13",
    "sg:postcode":"9495",
    "wof:name":"Hans Zimmermann Taxi & Kleintransporte",
    "wof:placetype":"venue"
},
  "geometry": {"coordinates":[7.894929,46.701767],"type":"Point"}
}