{
  "type": "Feature",
  "properties": {
    "iso:country":"CH",
    "sg:address":"Schottikerstrasse 21",
    "sg:city":"R\u00e4terschen",
    "sg:orig_category":"Herstellung von k\u00e4lte U lufttechnischen Erzeugnissen f\u00fcr gewerbliche Zwecke Sanit\u00e4r U Heizungsinstal",
    "sg:postcode":"8352",
    "sg:province":"Z\u00fcrich",
    "wof:name":"Climax, Nagel & Rossel Sa",
    "wof:placetype":"venue"
},
  "geometry": {"coordinates":[6.9229569435,46.9985160828],"type":"Point"}
}