{
  "type": "Feature",
  "properties": {
    "iso:country":"CH",
    "sg:address":"Route De Gen\u00e8ve 5",
    "sg:city":"Bussigny-lausanne",
    "sg:orig_category":"Detailhandel mit Schuhen Detailhandel mit Schuhen U Lederwaren",
    "sg:phone":"+41 21 311 75 62",
    "sg:postcode":"1030",
    "sg:province":"Vaud",
    "wof:name":"Hac Sa Halle Aux Chaussures",
    "wof:placetype":"venue"
},
  "geometry": {"coordinates":[6.5575799942,46.543258667],"type":"Point"}
}