{
  "type": "Feature",
  "properties": {
    "iso:country":"CH",
    "sg:address":"Bottigenstrasse 69",
    "sg:city":"Bern",
    "sg:orig_category":"Malerei",
    "sg:phone":"+41 31 991 09 55",
    "sg:postcode":"3018",
    "sg:province":"Bern",
    "wof:name":"Ferdinand Wermuth Malerei",
    "wof:placetype":"venue"
},
  "geometry": {"coordinates":[7.3825521469,46.9382972717],"type":"Point"}
}