{
  "type": "Feature",
  "properties": {
    "iso:country":"CH",
    "sg:address":"Mor\u00e2che Rue De La 8 1260 Nyon. Postfach",
    "sg:city":"Nyon",
    "sg:orig_category":"Unternehmensberatung",
    "sg:postcode":"1260",
    "sg:province":"Vaud",
    "wof:name":"Crucible Sa Aider Les Soci\u00e9t\u00e9s \u00e9trang\u00e8res Souhaitant S'implanter Dans Le March\u00e9 Europ\u00e9en Etc",
    "wof:placetype":"venue"
},
  "geometry": {"coordinates":[6.2390799522,46.3823661804],"type":"Point"}
}