{
  "type": "Feature",
  "properties": {
    "iso:country":"CH",
    "sg:address":"Neuveville Rue De La 25 1700 Fribourg. Postfach",
    "sg:city":"Fribourg",
    "sg:orig_category":"Detailhandel mit Fleisch U Fleischwaren",
    "sg:phone":"+41 26 322 12 86",
    "sg:postcode":"1700",
    "sg:province":"Fribourg",
    "wof:name":"Bertschy Nicolas, Boucherie, Charcuterie, Traiteur",
    "wof:placetype":"venue"
},
  "geometry": {"coordinates":[7.1610760689,46.8042984009],"type":"Point"}
}