{
  "type": "Feature",
  "properties": {
    "iso:country":"CH",
    "sg:address":"Aarbergstrasse 121a 2575 T\u00e4uffelen. Postfach",
    "sg:city":"T\u00e4uffelen",
    "sg:orig_category":"Herstellung von sonstigen M\u00f6beln",
    "sg:phone":"+41 32 323 12 23",
    "sg:postcode":"2575",
    "sg:province":"Bern",
    "wof:name":"Galleria Flury Marianne Und Daniel",
    "wof:placetype":"venue"
},
  "geometry": {"coordinates":[7.2003650665,47.0670814514],"type":"Point"}
}