{
  "type": "Feature",
  "properties": {
    "iso:country":"CH",
    "sg:address":"Fleurs Chemin Des 6",
    "sg:city":"Puplinge",
    "sg:orig_category":"Flachsaufbereitung U spinnerei",
    "sg:postcode":"1241",
    "sg:province":"Gen\u00e8ve",
    "wof:name":"Hemp Farm, Arnold",
    "wof:placetype":"venue"
},
  "geometry": {"coordinates":[6.232375145,46.21118927],"type":"Point"}
}