{
  "type": "Feature",
  "properties": {
    "iso:country":"CH",
    "sg:address":"Schauenbergstrasse 16 8046 Z\u00fcrich. Postfach",
    "sg:city":"Z\u00fcrich",
    "sg:orig_category":"Stukkateurgewerbe, Gipserei U Verputzerei",
    "sg:postcode":"8046",
    "sg:province":"Z\u00fcrich",
    "wof:name":"Gandola & Battaini Ag Gipserarbeiten, Bauleitungen, Handelsgesch\u00e4fte",
    "wof:placetype":"venue"
},
  "geometry": {"coordinates":[8.5060501099,47.4180831909],"type":"Point"}
}