{
  "type": "Feature",
  "properties": {
    "iso:country":"CH",
    "sg:address":"Heckenweg 6",
    "sg:city":"Herrliberg",
    "sg:orig_category":"Unternehmensberatung",
    "sg:postcode":"8704",
    "sg:province":"Z\u00fcrich",
    "wof:name":"Perma Consultants Holding Ag",
    "wof:placetype":"venue"
},
  "geometry": {"coordinates":[8.6252031326,47.2851142883],"type":"Point"}
}