{
  "type": "Feature",
  "properties": {
    "iso:country":"CH",
    "sg:address":"Wagistrasse 7",
    "sg:city":"Schlieren",
    "sg:orig_category":"Fachdetailhandel in Verkaufsr\u00e4umen",
    "sg:postcode":"8952",
    "sg:province":"Z\u00fcrich",
    "wof:name":"Ctc Cycle Trading Gmbh",
    "wof:placetype":"venue"
},
  "geometry": {"coordinates":[8.4554815292,47.3991966248],"type":"Point"}
}