{
  "type": "Feature",
  "properties": {
    "iso:country":"CH",
    "sg:address":"En Clarens 1267 Vich. Postfach",
    "sg:city":"Gland",
    "sg:orig_category":"Gartenbau",
    "sg:phone":"+41 79 449 18 64",
    "sg:postcode":"1196",
    "sg:province":"Vaud",
    "wof:name":"Multiplant, Sinner, Pasche, Masclet",
    "wof:placetype":"venue"
},
  "geometry": {"coordinates":[6.2514748573,46.4177856445],"type":"Point"}
}