{
  "type": "Feature",
  "properties": {
    "iso:country":"CH",
    "sg:address":"Techno-p\u00f4le 3 3960 Sierre. Postfach",
    "sg:city":"Sierre",
    "sg:orig_category":"Softwareentwicklung U beratung",
    "sg:postcode":"3960",
    "sg:province":"Valais",
    "wof:name":"Keyware Technologies (suisse) Sa Solutions Mat\u00e9rielles Et Logicielles Etc.; Conception, D\u00e9veloppement, Maintenance, Vente Et Marketing",
    "wof:placetype":"venue"
},
  "geometry": {"coordinates":[7.5384831429,46.2837677002],"type":"Point"}
}