{
  "type": "Feature",
  "properties": {
    "iso:country":"CH",
    "sg:address":"Br\u00fcelstrasse 14",
    "sg:city":"Dielsdorf",
    "sg:orig_category":"Malerei",
    "sg:phone":"+41 18530458",
    "sg:postcode":"8157",
    "sg:province":"Z\u00fcrich",
    "wof:name":"Erwin Traub Malergesch\u00e4ft",
    "wof:placetype":"venue"
},
  "geometry": {"coordinates":[8.4672002792,47.4820518494],"type":"Point"}
}