{
  "type": "Feature",
  "properties": {
    "addr:full":"Versam Graubunden 7104",
    "addr:housenumber":"7104",
    "iso:country":"CH",
    "sg:city":"Versam",
    "sg:classifiers":[
        {
            "category":"Banks & Credit Unions",
            "subcategory":"Bank",
            "type":"Services"
        }
    ],
    "sg:phone":"+41 4181411279",
    "sg:postcode":"7104",
    "sg:province":"Graubunden",
    "wof:name":"Raiffeisenbank",
    "wof:placetype":"venue"
},
  "geometry": {"coordinates":[9.33649,46.792641],"type":"Point"}
}