{
  "type": "Feature",
  "properties": {
    "iso:country":"CH",
    "sg:address":"Maunoir Rue 7 1207 Gen\u00e8ve. Postfach",
    "sg:city":"Gen\u00e8ve",
    "sg:orig_category":"M\u00f6belschreinereien",
    "sg:phone":"+41 22 735 32 74",
    "sg:postcode":"1207",
    "sg:province":"Gen\u00e8ve",
    "wof:name":"H. Bachelard",
    "wof:placetype":"venue"
},
  "geometry": {"coordinates":[6.1600618362,46.2041854858],"type":"Point"}
}