{
  "type": "Feature",
  "properties": {
    "iso:country":"CH",
    "sg:address":"Chemin Du Nord 6",
    "sg:city":"Corg\u00e9mont",
    "sg:orig_category":"Grafikateliers, Design",
    "sg:phone":"+41 79 312 81 17",
    "sg:postcode":"2606",
    "sg:province":"Bern",
    "wof:name":"Reynald Kr\u00e4henb\u00fchl Swiss Grafik",
    "wof:placetype":"venue"
},
  "geometry": {"coordinates":[7.1316299438,47.1960639954],"type":"Point"}
}