{
  "type": "Feature",
  "properties": {
    "iso:country":"CH",
    "sg:address":"Bernstrasse 23",
    "sg:city":"Flamatt",
    "sg:orig_category":"Handel mit Motorr\u00e4dern, Teilen U Zubeh\u00f6r Instandhaltung U Reparatur von Motorr\u00e4dern",
    "sg:postcode":"3175",
    "sg:province":"Fribourg",
    "wof:name":"Velo-moto Wolf",
    "wof:placetype":"venue"
},
  "geometry": {"coordinates":[7.3157248497,46.8901748657],"type":"Point"}
}