{
  "type": "Feature",
  "properties": {
    "iso:country":"CH",
    "sg:address":"6048",
    "sg:city":"Horw",
    "sg:classifiers":[
        {
            "category":"Restaurant",
            "type":"Food & Drink"
        }
    ],
    "sg:phone":"+41 55 246 44 43",
    "sg:postcode":"6048",
    "sg:province":"Luzern",
    "wof:name":"Gasthaus Schwert",
    "wof:placetype":"venue"
},
  "geometry": {"coordinates":[8.9413003922,47.2884101868],"type":"Point"}
}