{
  "type": "Feature",
  "properties": {
    "iso:country":"CH",
    "sg:address":"Kronengasse 2",
    "sg:city":"Selzach",
    "sg:orig_category":"Sportvereine Sch\u00fctzen",
    "sg:postcode":"2545",
    "sg:province":"Solothurn",
    "wof:name":"Sportsch\u00fctzen Altreu",
    "wof:placetype":"venue"
},
  "geometry": {"coordinates":[7.4531068802,47.2071609497],"type":"Point"}
}