{
  "type": "Feature",
  "properties": {
    "iso:country":"CH",
    "sg:address":"Z\u00fcrcherstrasse 149 8500 Frauenfeld. Postfach",
    "sg:city":"Frauenfeld",
    "sg:orig_category":"Versicherungen Generalagenturen",
    "sg:phone":"+41 52 720 14 40",
    "sg:postcode":"8501",
    "sg:province":"Thurgau",
    "wof:name":"Allianz Continentale Versich. Generalagentur Caruso & Ott",
    "wof:placetype":"venue"
},
  "geometry": {"coordinates":[8.8960161209,47.5551109314],"type":"Point"}
}