{
  "type": "Feature",
  "properties": {
    "iso:country":"CH",
    "sg:address":"Route D'orpond 48 2500 Biel/bienne. Postfach",
    "sg:city":"Biel/bienne",
    "sg:orig_category":"Fachdetailhandel in Verkaufsr\u00e4umen",
    "sg:phone":"+41 32 866 14 70",
    "sg:postcode":"2504",
    "sg:province":"Bern",
    "wof:name":"Garin Alexis",
    "wof:placetype":"venue"
},
  "geometry": {"coordinates":[6.4823880196,46.9084739685],"type":"Point"}
}