{
  "type": "Feature",
  "properties": {
    "iso:country":"CH",
    "sg:address":"Dorfstrasse 14",
    "sg:city":"Sattel",
    "sg:orig_category":"Arztpraxen",
    "sg:phone":"+41 41 835 15 50",
    "sg:postcode":"6417",
    "sg:province":"Schwyz",
    "wof:name":"Dr.med. Hugo Brunner Arzt F.allgemeine Medizin Fmh",
    "wof:placetype":"venue"
},
  "geometry": {"coordinates":[8.633277,47.080967],"type":"Point"}
}