{
  "type": "Feature",
  "properties": {
    "iso:country":"CH",
    "sg:address":"Gottstattstrasse 24",
    "sg:city":"Biel/bienne",
    "sg:classifiers":[
        {
            "category":"Professional",
            "subcategory":"Management & Consulting",
            "type":"Services"
        }
    ],
    "sg:phone":"+41 22 796 25 44",
    "sg:postcode":"2504",
    "sg:province":"Bern",
    "sg:tags":[
        "logistics"
    ],
    "wof:name":"Procosa S.a.",
    "wof:placetype":"venue"
},
  "geometry": {"coordinates":[6.1013131142,46.2066268921],"type":"Point"}
}