{
  "type": "Feature",
  "properties": {
    "iso:country":"CH",
    "sg:address":"1963 V\u00e9troz Case Postale 0",
    "sg:city":"V\u00e9troz",
    "sg:orig_category":"Pensionskassen",
    "sg:postcode":"1963",
    "sg:province":"Valais",
    "wof:name":"Fondation De Pr\u00e9voyance En Faveur Du Personnel De Du Pont De Nemours International Sa",
    "wof:placetype":"venue"
},
  "geometry": {"coordinates":[6.126830101,46.2368164062],"type":"Point"}
}