{
  "type": "Feature",
  "properties": {
    "iso:country":"CH",
    "sg:address":"Dammweg 9",
    "sg:city":"Ostermundigen",
    "sg:orig_category":"Grosshandel mit festen Brennstoffen U Mineral\u00f6lerzeugnissen",
    "sg:postcode":"3072",
    "sg:province":"Bern",
    "wof:name":"K\u00e4ser W., Kohlen, Heiz\u00f6l U. Autotransporte",
    "wof:placetype":"venue"
},
  "geometry": {"coordinates":[7.4830231667,46.9541244507],"type":"Point"}
}