{
  "type": "Feature",
  "properties": {
    "iso:country":"CH",
    "sg:address":"Br\u00fcndlen 77 8722 Kaltbrunn. Postfach",
    "sg:city":"Kaltbrunn",
    "sg:orig_category":"Gesundheitswesen",
    "sg:phone":"+41 55 283 30 45",
    "sg:postcode":"8722",
    "sg:province":"St. Gallen",
    "wof:name":"Gesund, Schirmer Ursula Gesundheitsberatung",
    "wof:placetype":"venue"
},
  "geometry": {"coordinates":[9.028886795,47.2150917053],"type":"Point"}
}