{
  "type": "Feature",
  "properties": {
    "iso:country":"CH",
    "sg:address":"4304",
    "sg:city":"Giebenach",
    "sg:orig_category":"Sportvereine Sch\u00fctzen",
    "sg:phone":"+41 62 293 52 29",
    "sg:postcode":"4304",
    "sg:province":"Basel-Landschaft",
    "wof:name":"Feldsch\u00fctzengesellschaft",
    "wof:placetype":"venue"
},
  "geometry": {"coordinates":[7.7448701859,47.5195999146],"type":"Point"}
}