{
  "type": "Feature",
  "properties": {
    "iso:country":"CH",
    "sg:address":"Bahnhofstrasse 3",
    "sg:city":"D\u00fcdingen",
    "sg:orig_category":"Aktivit\u00e4ten der Generalunternehmen im Baugewerbe Allgemeiner Hoch U Tiefbau",
    "sg:phone":"+41 26 492 03 70",
    "sg:postcode":"3186",
    "sg:province":"Fribourg",
    "wof:name":"Agob Ag",
    "wof:placetype":"venue"
},
  "geometry": {"coordinates":[7.191167,46.850742],"type":"Point"}
}