{
  "type": "Feature",
  "properties": {
    "iso:country":"CH",
    "sg:address":"Gr\u00fcnmattstrasse 11 6032 Emmen. Postfach",
    "sg:city":"Emmen",
    "sg:orig_category":"Grosshandel mit Holz U Baustoffen",
    "sg:phone":"+41 33 971 60 33",
    "sg:postcode":"6032",
    "sg:province":"Luzern",
    "wof:name":"Wahlen Alb. Ag Meiringen",
    "wof:placetype":"venue"
},
  "geometry": {"coordinates":[8.1095075607,46.7373352051],"type":"Point"}
}