{
  "type": "Feature",
  "properties": {
    "iso:country":"CH",
    "sg:address":"Bahnhofstrasse 6 8197 Rafz. Postfach 110",
    "sg:city":"Rafz",
    "sg:orig_category":"Sportvereine Ballsport Fussball",
    "sg:phone":"+41 18692330",
    "sg:postcode":"8197",
    "sg:province":"Z\u00fcrich",
    "wof:name":"Fc Rafz",
    "wof:placetype":"venue"
},
  "geometry": {"coordinates":[8.5408992767,47.6104736328],"type":"Point"}
}