{
  "type": "Feature",
  "properties": {
    "iso:country":"CH",
    "sg:address":"Tellstrasse 15",
    "sg:city":"Basel",
    "sg:orig_category":"Tankstellen",
    "sg:phone":"+41 61 361 62 98",
    "sg:postcode":"4053",
    "sg:province":"Basel-Stadt",
    "wof:name":"T. Inglese Reparaturwerkst\u00e4tte F. Automobile, An- U. Verkauf.",
    "wof:placetype":"venue"
},
  "geometry": {"coordinates":[7.5956912041,47.5431900024],"type":"Point"}
}