{
  "type": "Feature",
  "properties": {
    "iso:country":"CH",
    "sg:address":"Oberdorf 13",
    "sg:city":"Treiten",
    "sg:orig_category":"Grosshandel mit lebenden Tieren",
    "sg:phone":"+41 32 313 13 85",
    "sg:postcode":"3226",
    "sg:province":"Bern",
    "wof:name":"Fritz Schumacher Viehhandel",
    "wof:placetype":"venue"
},
  "geometry": {"coordinates":[7.1628170013,47.0094718933],"type":"Point"}
}