{
  "type": "Feature",
  "properties": {
    "iso:country":"CH",
    "sg:address":"Stapferstrasse 6",
    "sg:city":"Aarau",
    "sg:orig_category":"Vermietung U Verpachtung von eigenen Immobilien",
    "sg:phone":"+41 56 443 23 94",
    "sg:postcode":"5000",
    "sg:province":"Aargau",
    "wof:name":"Woba Immobilien Ag Aarau",
    "wof:placetype":"venue"
},
  "geometry": {"coordinates":[8.0407924652,47.385761261],"type":"Point"}
}