{
  "type": "Feature",
  "properties": {
    "addr:full":"Kasinostrasse 25 5000 Aarau. Postfach Aarau Aargau 5001",
    "addr:housenumber":"25",
    "addr:postcode":"5000 aarau. postfach;5001",
    "addr:street":"Kasinostrasse",
    "iso:country":"CH",
    "sg:address":"Kasinostrasse 25 5000 Aarau. Postfach",
    "sg:city":"Aarau",
    "sg:orig_category":"Detailhandel mit Damenbekleidung Detailhandel mit Herrenbekleidung",
    "sg:phone":"+41 62 837 97 80",
    "sg:postcode":"5001",
    "sg:province":"Aargau",
    "wof:name":"Bernheim & Co Ag Damen-& Herren-bekleidung",
    "wof:placetype":"venue"
},
  "geometry": {"coordinates":[8.046992,47.392426],"type":"Point"}
}