{
  "type": "Feature",
  "properties": {
    "iso:country":"CH",
    "sg:address":"Alte Chamerstrasse 3",
    "sg:city":"Rotkreuz",
    "sg:classifiers":[
        {
            "category":"Travel",
            "subcategory":"Hotels & Motels",
            "type":"Entertainment"
        }
    ],
    "sg:postcode":"6343",
    "sg:province":"Zug",
    "sg:tags":[
        "hotels",
        "mit",
        "restaurant"
    ],
    "wof:name":"Lorehag Ag",
    "wof:placetype":"venue"
},
  "geometry": {"coordinates":[8.4288406372,47.1424560547],"type":"Point"}
}