{
  "type": "Feature",
  "properties": {
    "iso:country":"CH",
    "sg:address":"Zelgstrasse 95 3661 Uetendorf. Postfach",
    "sg:city":"Uetendorf",
    "sg:orig_category":"Grosshandel mit Eisenwaren sowie Installationsbedarf f\u00fcr Gas, Wasser U Heizung",
    "sg:phone":"+41 33 346 61 61",
    "sg:postcode":"3661",
    "sg:province":"Bern",
    "wof:name":"Immer Handels Ag Eisenwaren, Beschl\u00e4gen, Maschinen, Werkzeuge; Engros, Detailhandel",
    "wof:placetype":"venue"
},
  "geometry": {"coordinates":[7.58901,46.77972],"type":"Point"}
}