{
  "type": "Feature",
  "properties": {
    "iso:country":"CH",
    "sg:address":"Rue Du Bourg 49",
    "sg:city":"Sierre",
    "sg:orig_category":"Unclassifiable Establishments",
    "sg:postcode":"3960",
    "sg:province":"Valais",
    "wof:name":"Alpgeo S\u00e0rl",
    "wof:placetype":"venue"
},
  "geometry": {"coordinates":[7.5364661217,46.2939872742],"type":"Point"}
}