{
  "type": "Feature",
  "properties": {
    "iso:country":"CH",
    "sg:address":"Route De Saint-cergue 112",
    "sg:city":"Nyon",
    "sg:orig_category":"Pensionskassen",
    "sg:postcode":"1260",
    "sg:province":"Vaud",
    "wof:name":"Fonds De Pr\u00e9voyance Perrin Fr\u00e8res Sa",
    "wof:placetype":"venue"
},
  "geometry": {"coordinates":[6.2265439034,46.3946380615],"type":"Point"}
}