{
  "type": "Feature",
  "properties": {
    "iso:country":"CH",
    "sg:address":"Ruessenstrasse 5",
    "sg:city":"Baar",
    "sg:orig_category":"Markt U Meinungsforschung",
    "sg:phone":"+41 56 426 06 44",
    "sg:postcode":"6340",
    "sg:province":"Zug",
    "wof:name":"Pdc Consulting Ag",
    "wof:placetype":"venue"
},
  "geometry": {"coordinates":[8.3156042099,47.4590682983],"type":"Point"}
}