{
  "type": "Feature",
  "properties": {
    "iso:country":"CH",
    "sg:address":"Hauptstr. 62",
    "sg:city":"M\u00fcstair",
    "sg:orig_category":"Detailhandel mit Fleisch U Fleischwaren",
    "sg:phone":"+41 71 385 16 69",
    "sg:postcode":"7537",
    "sg:province":"Graubunden",
    "wof:name":"Metzgerei Gr\u00fcebler",
    "wof:placetype":"venue"
},
  "geometry": {"coordinates":[9.2494602203,47.4156990051],"type":"Point"}
}