{
  "type": "Feature",
  "properties": {
    "iso:country":"CH",
    "sg:address":"Albulastr. 55",
    "sg:city":"Z\u00fcrich",
    "sg:classifiers":[
        {
            "category":"Utilities",
            "subcategory":"Telephone",
            "type":"Services"
        }
    ],
    "sg:phone":"+41 4114368888",
    "sg:postcode":"8048",
    "sg:province":"Z\u00fcrich",
    "sg:tags":[
        "telecommunication"
    ],
    "wof:name":"Burkhalter Net Works Ag",
    "wof:placetype":"venue"
},
  "geometry": {"coordinates":[8.4921560287,47.3885154724],"type":"Point"}
}