{
  "type": "Feature",
  "properties": {
    "iso:country":"CH",
    "sg:address":"Piazza Grande 53",
    "sg:city":"Giubiasco",
    "sg:orig_category":"Detailhandel mit medizinischen U orthop\u00e4dischen Artikeln Herstellung von medizinischen U chirurgisch",
    "sg:phone":"+41 91 857 37 28",
    "sg:postcode":"6512",
    "sg:province":"Ticino",
    "wof:name":"Fulvio Cazzoli Laboratorio Ortopedico",
    "wof:placetype":"venue"
},
  "geometry": {"coordinates":[9.0101776123,46.1712379456],"type":"Point"}
}