{
  "type": "Feature",
  "properties": {
    "iso:country":"CH",
    "sg:address":"Neugasse 75",
    "sg:city":"Z\u00fcrich",
    "sg:orig_category":"Detektivb\u00fcros U \u00dcberwachung",
    "sg:phone":"+41 71 277 10 55",
    "sg:postcode":"8005",
    "sg:province":"Z\u00fcrich",
    "wof:name":"St\u00e9rios Vlachos Detektivb\u00fcro",
    "wof:placetype":"venue"
},
  "geometry": {"coordinates":[9.3485441208,47.4179954529],"type":"Point"}
}