{
  "type": "Feature",
  "properties": {
    "iso:country":"CH",
    "sg:address":"Badstrasse 21 5400 Baden. Postfach 545",
    "sg:city":"Baden",
    "sg:orig_category":"Vermietung U Verpachtung von eigenen Immobilien",
    "sg:postcode":"5400",
    "sg:province":"Aargau",
    "wof:name":"Badstrasse-immobilien Ag",
    "wof:placetype":"venue"
},
  "geometry": {"coordinates":[8.3083381653,47.4751815796],"type":"Point"}
}