{
  "type": "Feature",
  "properties": {
    "iso:country":"CH",
    "sg:address":"Campagnola Via 2",
    "sg:city":"Genestrerio",
    "sg:orig_category":"Grosshandel mit Werkzeugmaschinen",
    "sg:phone":"+41 79 301 10 46",
    "sg:postcode":"6852",
    "sg:province":"Ticino",
    "wof:name":"M\u00e9rillat Machines Machines-outils; Comm.",
    "wof:placetype":"venue"
},
  "geometry": {"coordinates":[6.9309201241,46.9920082092],"type":"Point"}
}