{
  "type": "Feature",
  "properties": {
    "iso:country":"CH",
    "sg:address":"M\u00fcllerstrasse 37 8004 Z\u00fcrich. Postfach",
    "sg:city":"Z\u00fcrich",
    "sg:orig_category":"Konzert- and Theateragenturen Sonstige Hilfsdienste des Kultur U Unterhaltungswesens",
    "sg:phone":"+41 12402689",
    "sg:postcode":"8021",
    "sg:province":"Z\u00fcrich",
    "wof:name":"Urs Gfeller Tanamur",
    "wof:placetype":"venue"
},
  "geometry": {"coordinates":[8.5298719406,47.3749732971],"type":"Point"}
}