{
  "type": "Feature",
  "properties": {
    "iso:country":"CH",
    "sg:address":"Peri Via 15",
    "sg:city":"Lugano",
    "sg:orig_category":"Non-Classified Establishments",
    "sg:phone":"+41 91 840 12 10",
    "sg:postcode":"6900",
    "sg:province":"Ticino",
    "wof:name":"C.a.l.-k. Racing Developpement Sagl",
    "wof:placetype":"venue"
},
  "geometry": {"coordinates":[8.9513053894,46.0029754639],"type":"Point"}
}