{
  "type": "Feature",
  "properties": {
    "iso:country":"CH",
    "sg:address":"Schaanerstrasse 39 9490 Vaduz. Postfach 535",
    "sg:city":"Vaduz",
    "sg:orig_category":"Grosshandel mit Eisenwaren sowie Installationsbedarf f\u00fcr Gas, Wasser U Heizung",
    "sg:phone":"+423 232 33 93",
    "sg:postcode":"9490",
    "wof:name":"Saniplan Ag Sanit'grosshandel",
    "wof:placetype":"venue"
},
  "geometry": {"coordinates":[9.507270813,47.150062561],"type":"Point"}
}