{
  "type": "Feature",
  "properties": {
    "iso:country":"CH",
    "sg:address":"Pfeffingerstrasse 16 4053 Basel. Postfach",
    "sg:city":"Basel",
    "sg:orig_category":"Finanzierungsinstitutionen",
    "sg:postcode":"4051",
    "sg:province":"Basel-Stadt",
    "wof:name":"Rewefit Gmbh Finanz Und Treuhanddienstleistungen",
    "wof:placetype":"venue"
},
  "geometry": {"coordinates":[7.5920128822,47.5449943542],"type":"Point"}
}