{
  "type": "Feature",
  "properties": {
    "addr:full":"Rue De La Grotte 1 Lausanne Vaud 1003",
    "addr:housenumber":"1",
    "addr:postcode":"1003",
    "addr:street":"Rue De La Grotte",
    "iso:country":"CH",
    "sg:address":"Rue De La Grotte 1",
    "sg:city":"Lausanne",
    "sg:orig_category":"Detailhandel mit Brot, Back U S\u00fcsswaren",
    "sg:phone":"+41 21 312 68 37",
    "sg:postcode":"1003",
    "sg:province":"Vaud",
    "wof:name":"A. Polli Sa Boulangerie-p\u00e2tisserie",
    "wof:placetype":"venue"
},
  "geometry": {"coordinates":[6.634085,46.51862],"type":"Point"}
}