{
  "type": "Feature",
  "properties": {
    "iso:country":"CH",
    "sg:address":"Weststrasse 15 8400 Winterthur. Postfach 173",
    "sg:city":"Winterthur",
    "sg:orig_category":"Erschliessung von Grundst\u00fccken",
    "sg:phone":"+41 52 223 19 72",
    "sg:postcode":"8407",
    "wof:name":"Allgemeine Baugenossenschaft Winterthur",
    "wof:placetype":"venue"
},
  "geometry": {"coordinates":[8.7161531448,47.5064468384],"type":"Point"}
}