{
  "type": "Feature",
  "properties": {
    "iso:country":"CH",
    "sg:address":"Steinerbr\u00fcggli",
    "sg:city":"Reichenburg",
    "sg:orig_category":"Grosshandel mit Holz U Baustoffen",
    "sg:phone":"+41 55 444 12 61",
    "sg:postcode":"8864",
    "sg:province":"Schwyz",
    "wof:name":"Kistler-aebli Kurt",
    "wof:placetype":"venue"
},
  "geometry": {"coordinates":[8.9805030823,47.1727676392],"type":"Point"}
}