{
  "type": "Feature",
  "properties": {
    "iso:country":"CH",
    "sg:address":"Route Champ-des-fontaines 13",
    "sg:city":"Fribourg",
    "sg:orig_category":"Bauspenglerei Sanit\u00e4rinstallation",
    "sg:phone":"+41 26 466 21 17",
    "sg:postcode":"1700",
    "sg:province":"Fribourg",
    "wof:name":"Roger Meuwly Appareillage & Ferblanterie",
    "wof:placetype":"venue"
},
  "geometry": {"coordinates":[7.143832,46.809139],"type":"Point"}
}