{
  "type": "Feature",
  "properties": {
    "iso:country":"CH",
    "sg:address":"Via Carlo Maderno 17",
    "sg:city":"Mendrisio",
    "sg:orig_category":"Grosshandel mit Getr\u00e4nken Grosshandel mit Wein U Spirituosen",
    "sg:phone":"+41 91 646 76 46",
    "sg:postcode":"6850",
    "sg:province":"Ticino",
    "wof:name":"Marazza Vini Sagl",
    "wof:placetype":"venue"
},
  "geometry": {"coordinates":[8.9861154556,45.8770523071],"type":"Point"}
}