{
  "type": "Feature",
  "properties": {
    "iso:country":"CH",
    "sg:address":"St. Gallerstrasse 72",
    "sg:city":"R\u00e4terschen",
    "sg:classifiers":[
        {
            "category":"Travel",
            "subcategory":"Hotels & Motels",
            "type":"Entertainment"
        }
    ],
    "sg:phone":"+41 52 363 19 13",
    "sg:postcode":"8352",
    "sg:province":"Z\u00fcrich",
    "sg:tags":[
        "hotels",
        "mit",
        "restaurant"
    ],
    "wof:name":"Hotel Sternen",
    "wof:placetype":"venue"
},
  "geometry": {"coordinates":[8.8003816605,47.4980125427],"type":"Point"}
}