{
  "type": "Feature",
  "properties": {
    "iso:country":"CH",
    "sg:address":"Selzacherstrasse 32",
    "sg:city":"Selzach",
    "sg:orig_category":"Herstellung von medizinischen U chirurgischen Ger\u00e4ten sowie orthop\u00e4dischen Vorrichtungen",
    "sg:postcode":"2545",
    "sg:province":"Solothurn",
    "wof:name":"Medix-pharma Gmbh",
    "wof:placetype":"venue"
},
  "geometry": {"coordinates":[7.4847130775,46.9319496155],"type":"Point"}
}