{
  "type": "Feature",
  "properties": {
    "iso:country":"CH",
    "sg:address":"Eichstockstrasse 21",
    "sg:city":"D\u00fcbendorf",
    "sg:orig_category":"Institutionen des Sozialwesens ohne Beherbergung",
    "sg:postcode":"8600",
    "sg:province":"Z\u00fcrich",
    "wof:name":"Gossweiler Edwin Und Lina Stiftung",
    "wof:placetype":"venue"
},
  "geometry": {"coordinates":[8.6230077744,47.3895606995],"type":"Point"}
}