{
  "type": "Feature",
  "properties": {
    "iso:country":"CH",
    "sg:address":"Hungerb\u00fcelstrasse 17",
    "sg:city":"Frauenfeld",
    "sg:classifiers":[
        {
            "category":"Government",
            "subcategory":"Post Office",
            "type":"Public Place"
        }
    ],
    "sg:phone":"+41 52 721 20 21",
    "sg:postcode":"8500",
    "sg:province":"Thurgau",
    "sg:tags":[
        "plastic",
        "part",
        "working",
        "mechanical"
    ],
    "wof:name":"Economos Schweiz Gmbh",
    "wof:placetype":"venue"
},
  "geometry": {"coordinates":[8.8735303879,47.5622406006],"type":"Point"}
}