{
  "type": "Feature",
  "properties": {
    "iso:country":"CH",
    "sg:address":"Biberiststrasse 4",
    "sg:city":"Gerlafingen",
    "sg:orig_category":"Detailhandel mit M\u00f6beln Detailhandel mit M\u00f6beln U Haushaltsgegenst\u00e4nden",
    "sg:phone":"+41 32 675 69 01",
    "sg:postcode":"4563",
    "sg:province":"Solothurn",
    "wof:name":"M\u00f6bel Brechter Ag",
    "wof:placetype":"venue"
},
  "geometry": {"coordinates":[7.5688791275,47.1711006165],"type":"Point"}
}