{
  "type": "Feature",
  "properties": {
    "iso:country":"CH",
    "sg:address":"Sunnematt 5",
    "sg:city":"Hedingen",
    "sg:orig_category":"Erbringung von Dienstleistungen f\u00fcr Unternehmen Immobilienwesen",
    "sg:phone":"+41 17601414",
    "sg:postcode":"8908",
    "sg:province":"Z\u00fcrich",
    "wof:name":"Target B\u00fcro-umbaumanagement",
    "wof:placetype":"venue"
},
  "geometry": {"coordinates":[8.4475622177,47.3026046753],"type":"Point"}
}