{
  "type": "Feature",
  "properties": {
    "iso:country":"CH",
    "sg:address":"Place Des Bennelats",
    "sg:city":"Porrentruy",
    "sg:orig_category":"Herstellung von Schreibwaren U B\u00fcrobedarf aus Papier, Karton U Pappe",
    "sg:phone":"+41 32 466 85 44",
    "sg:postcode":"2900",
    "sg:province":"Jura",
    "wof:name":"Espace Le Pays Sa",
    "wof:placetype":"venue"
},
  "geometry": {"coordinates":[7.0763158798,47.4171867371],"type":"Point"}
}