{
  "type": "Feature",
  "properties": {
    "iso:country":"CH",
    "sg:address":"Alte Oltnerstrasse 23",
    "sg:city":"Winznau",
    "sg:orig_category":"Glaserei Verarbeitung U Veredlung von Flachglas",
    "sg:phone":"+41 21 960 30 31",
    "sg:postcode":"4652",
    "sg:province":"Solothurn",
    "wof:name":"Martin Verre Sa",
    "wof:placetype":"venue"
},
  "geometry": {"coordinates":[6.9354410172,46.3929176331],"type":"Point"}
}