{
  "type": "Feature",
  "properties": {
    "iso:country":"CH",
    "sg:address":"Bernstrasse 4",
    "sg:city":"Toffen",
    "sg:orig_category":"Sportvereine Turnen Vereine Damen",
    "sg:phone":"+41 79 651 57 74",
    "sg:postcode":"3125",
    "sg:province":"Bern",
    "wof:name":"Damenriege Stv Toffen",
    "wof:placetype":"venue"
},
  "geometry": {"coordinates":[7.4909491539,46.859703064],"type":"Point"}
}