{
  "type": "Feature",
  "properties": {
    "iso:country":"CH",
    "sg:address":"Mitteldorfstrasse 105",
    "sg:city":"Habsburg",
    "sg:orig_category":"Hardwareberatung",
    "sg:postcode":"5245",
    "sg:province":"Aargau",
    "wof:name":"Pc World St. Gallen Gmbh Waren, Bes. Elektron. Ger\u00e4te Inkl. F. D. Elektron. Datenverarbeitung; Handel",
    "wof:placetype":"venue"
},
  "geometry": {"coordinates":[9.4041719437,47.4320526123],"type":"Point"}
}