{
  "type": "Feature",
  "properties": {
    "iso:country":"CH",
    "sg:address":"Route D'ambilly 38",
    "sg:city":"Th\u00f4nex",
    "sg:orig_category":"Hardwareberatung",
    "sg:postcode":"1226",
    "sg:province":"Gen\u00e8ve",
    "wof:name":"Nde Network Design & Equipment, Pousaz C\u00e9dric",
    "wof:placetype":"venue"
},
  "geometry": {"coordinates":[6.2055101395,46.1978683472],"type":"Point"}
}