{
  "type": "Feature",
  "properties": {
    "iso:country":"CH",
    "sg:address":"Rundbuckstrasse 12",
    "sg:city":"Neuhausen A. Rhf.",
    "sg:orig_category":"Industrie, Elektronik U Elektrik",
    "sg:phone":"+41 52 674 14 14",
    "sg:postcode":"8212",
    "sg:province":"Schaffhausen",
    "wof:name":"Kebo Formenbau Ag",
    "wof:placetype":"venue"
},
  "geometry": {"coordinates":[8.602323,47.675419],"type":"Point"}
}