{
  "type": "Feature",
  "properties": {
    "iso:country":"CH",
    "sg:address":"Dorfstrasse 50",
    "sg:city":"Obfelden",
    "sg:orig_category":"Verlegen von Fliesen U Platten",
    "sg:phone":"+41 17614300",
    "sg:postcode":"8912",
    "sg:province":"Z\u00fcrich",
    "wof:name":"Willy H\u00e4chler Ofenbau",
    "wof:placetype":"venue"
},
  "geometry": {"coordinates":[8.4280166626,47.2635612488],"type":"Point"}
}