{
  "type": "Feature",
  "properties": {
    "iso:country":"CH",
    "sg:address":"9214",
    "sg:city":"Kradolf",
    "sg:orig_category":"Mechanik",
    "sg:postcode":"9214",
    "sg:province":"Thurgau",
    "wof:name":"Kernen Ag Buhwil",
    "wof:placetype":"venue"
},
  "geometry": {"coordinates":[9.2017002106,47.5242195129],"type":"Point"}
}