{
  "type": "Feature",
  "properties": {
    "iso:country":"CH",
    "sg:address":"Gottstattstrasse 14",
    "sg:city":"Biel/bienne",
    "sg:orig_category":"Wirtschafts U Arbeitgeberverb\u00e4nde",
    "sg:phone":"+41 32 342 22 42",
    "sg:postcode":"2504",
    "sg:province":"Bern",
    "wof:name":"Vereinigung Der Sand Und Kieswerke Von Biel Und Umgebung",
    "wof:placetype":"venue"
},
  "geometry": {"coordinates":[7.2635030746,47.142124176],"type":"Point"}
}