{
  "type": "Feature",
  "properties": {
    "iso:country":"CH",
    "sg:address":"Neuengass-passage 3 3011 Bern. Postfach 209",
    "sg:city":"Bern",
    "sg:orig_category":"Architektur U Ingenieurb\u00fcros",
    "sg:phone":"+41 31 951 15 55",
    "sg:postcode":"3011",
    "sg:province":"Bern",
    "wof:name":"Foring Ag",
    "wof:placetype":"venue"
},
  "geometry": {"coordinates":[7.443317,46.949116],"type":"Point"}
}