{
  "type": "Feature",
  "properties": {
    "iso:country":"CH",
    "sg:address":"St. Ant\u00f6nienweg 14 7000 Chur. Postfach",
    "sg:city":"Chur",
    "sg:orig_category":"Grosshandel mit Geschenkartikeln U Souvenirs Sonstiger Grosshandel",
    "sg:postcode":"7001",
    "sg:province":"Graubunden",
    "wof:name":"Ideecor Ag Nouveaut\u00e9s Engros & Werbeart.",
    "wof:placetype":"venue"
},
  "geometry": {"coordinates":[9.5290870667,46.8450012207],"type":"Point"}
}