{
  "type": "Feature",
  "properties": {
    "iso:country":"CH",
    "sg:address":"B\u00f6hnirainstrasse 14",
    "sg:city":"Thalwil",
    "sg:orig_category":"Datenverarbeitungsdienste",
    "sg:postcode":"8800",
    "sg:province":"Z\u00fcrich",
    "wof:name":"Sysline Consulting Ag",
    "wof:placetype":"venue"
},
  "geometry": {"coordinates":[8.757775,47.206306],"type":"Point"}
}