{
  "type": "Feature",
  "properties": {
    "iso:country":"CH",
    "sg:address":"Dorfstrasse 23",
    "sg:city":"Schindellegi",
    "sg:orig_category":"Detailhandel mit elektrischen Haushalts, Radio U Fernsehger\u00e4ten ohne ausgepr\u00e4gten Schwerpunkt Elektr",
    "sg:phone":"+41 17841702",
    "sg:postcode":"8834",
    "sg:province":"Schwyz",
    "wof:name":"Arthur Fuchs",
    "wof:placetype":"venue"
},
  "geometry": {"coordinates":[8.7105979919,47.1752433777],"type":"Point"}
}