{
  "type": "Feature",
  "properties": {
    "iso:country":"CH",
    "sg:address":"6300",
    "sg:city":"Zugerberg",
    "sg:orig_category":"Bezirks, Sekundar, Realschulen, Oberstufe der Primarschulen Primarschulen",
    "sg:phone":"+41 41 711 17 22",
    "sg:postcode":"6300",
    "sg:province":"Zug",
    "wof:name":"Institut Montana Zugerberg",
    "wof:placetype":"venue"
},
  "geometry": {"coordinates":[8.53313,47.143951],"type":"Point"}
}