{
  "type": "Feature",
  "properties": {
    "iso:country":"CH",
    "sg:address":"Avenue De Cr\u00e9deilles 4",
    "sg:city":"Vevey",
    "sg:orig_category":"Primarschulen",
    "sg:phone":"+41 21 925 59 35",
    "sg:postcode":"1800",
    "sg:province":"Vaud",
    "wof:name":"Ecole Primaire Pavillon De Cr\u00e9deilles",
    "wof:placetype":"venue"
},
  "geometry": {"coordinates":[6.8520579338,46.4616851807],"type":"Point"}
}