{
  "type": "Feature",
  "properties": {
    "iso:country":"CH",
    "sg:address":"1428",
    "sg:city":"Provence",
    "sg:orig_category":"Detailhandel mit Milcherzeugnissen U Eiern Verarbeitung von Milch",
    "sg:phone":"+41 21 845 60 65",
    "sg:postcode":"1428",
    "sg:province":"Vaud",
    "wof:name":"Soci\u00e9t\u00e9 De Fromagerie Des Landes Laurent Meylan",
    "wof:placetype":"venue"
},
  "geometry": {"coordinates":[6.2375588417,46.6198768616],"type":"Point"}
}