{
  "type": "Feature",
  "properties": {
    "iso:country":"CH",
    "sg:address":"Via Vallemaggia 75",
    "sg:city":"Locarno",
    "sg:orig_category":"Architektur U Ingenieurb\u00fcros Architekturb\u00fcros",
    "sg:phone":"+41 91 751 37 35",
    "sg:postcode":"6600",
    "sg:province":"Ticino",
    "wof:name":"Mario Bianchi & Associati Studio D'architettura",
    "wof:placetype":"venue"
},
  "geometry": {"coordinates":[8.78917,46.16972],"type":"Point"}
}