{
  "type": "Feature",
  "properties": {
    "iso:country":"CH",
    "sg:address":"Rue De Vermont 12",
    "sg:city":"Gen\u00e8ve",
    "sg:orig_category":"Detailhandel Reparatur von Gebrauchsg\u00fctern Vermietung von Gebrauchsg\u00fctern",
    "sg:phone":"+41 22 740 39 40",
    "sg:postcode":"1202",
    "sg:province":"Gen\u00e8ve",
    "wof:name":"Vive-vid\u00e9o Vermont",
    "wof:placetype":"venue"
},
  "geometry": {"coordinates":[6.1354761124,46.2163963318],"type":"Point"}
}