{
  "type": "Feature",
  "properties": {
    "iso:country":"CH",
    "sg:address":"Livio Via 8",
    "sg:city":"Chiasso",
    "sg:orig_category":"Non-Classified Establishments",
    "sg:postcode":"6830",
    "sg:province":"Ticino",
    "wof:name":"Minardi Food Import-export Sagl",
    "wof:placetype":"venue"
},
  "geometry": {"coordinates":[9.0291757584,45.8336448669],"type":"Point"}
}