{
  "type": "Feature",
  "properties": {
    "iso:country":"CH",
    "sg:address":"B\u00fctzenenweg 15",
    "sg:city":"Gelterkinden",
    "sg:orig_category":"Maler U Glasergewerbe Malerei",
    "sg:phone":"+41 81 413 28 88",
    "sg:postcode":"4460",
    "sg:province":"Basel-Landschaft",
    "wof:name":"Attenhofer",
    "wof:placetype":"venue"
},
  "geometry": {"coordinates":[9.8279104233,46.798034668],"type":"Point"}
}