{
  "type": "Feature",
  "properties": {
    "iso:country":"CH",
    "sg:address":"Oberstadt 24",
    "sg:city":"Schaffhausen",
    "sg:orig_category":"RESTAURANTS: TEA-ROOMS",
    "sg:phone":"+41 56 664 56 44",
    "sg:postcode":"8200",
    "sg:province":"Schaffhausen",
    "wof:name":"Caf\u00e9 St. Martin, W. Gubser",
    "wof:placetype":"venue"
},
  "geometry": {"coordinates":[8.3174819946,47.2825775146],"type":"Point"}
}