{
  "type": "Feature",
  "properties": {
    "iso:country":"CH",
    "sg:address":"Bahnhofstrasse 8 3507 Biglen. Postfach 145",
    "sg:city":"Biglen",
    "sg:orig_category":"Drogerien",
    "sg:phone":"+41 31 701 10 56",
    "sg:postcode":"3507",
    "sg:province":"Bern",
    "wof:name":"Drogerie Fehr Ag",
    "wof:placetype":"venue"
},
  "geometry": {"coordinates":[7.6285829544,46.9254417419],"type":"Point"}
}