{
  "type": "Feature",
  "properties": {
    "iso:country":"CH",
    "sg:address":"Witikonerstrasse 368",
    "sg:city":"Z\u00fcrich",
    "sg:orig_category":"Handelsvermittlung U Grosshandel",
    "sg:phone":"+41 13816392",
    "sg:postcode":"8053",
    "sg:province":"Z\u00fcrich",
    "wof:name":"Zhi-jie Jia Import & Export",
    "wof:placetype":"venue"
},
  "geometry": {"coordinates":[8.5916023254,47.3588294983],"type":"Point"}
}