{
  "type": "Feature",
  "properties": {
    "iso:country":"CH",
    "sg:address":"Erlinsbacherstrasse 15",
    "sg:city":"St\u00fcsslingen",
    "sg:orig_category":"Politische Parteien FDP",
    "sg:phone":"+41 62 622 31 66",
    "sg:postcode":"4655",
    "sg:province":"Solothurn",
    "wof:name":"Fdp Ortspartei St\u00fcsslingen",
    "wof:placetype":"venue"
},
  "geometry": {"coordinates":[7.9733228683,47.3911743164],"type":"Point"}
}