{
  "type": "Feature",
  "properties": {
    "iso:country":"CH",
    "sg:address":"Solaria Via 9",
    "sg:city":"Minusio",
    "sg:orig_category":"Sonstiger spezialisierter Hoch U Tiefbau",
    "sg:phone":"+41 79 621 09 63",
    "sg:postcode":"6648",
    "sg:province":"Ticino",
    "wof:name":"Aqva Sagl",
    "wof:placetype":"venue"
},
  "geometry": {"coordinates":[8.8086433411,46.1765365601],"type":"Point"}
}