{
  "type": "Feature",
  "properties": {
    "iso:country":"CH",
    "sg:address":"Boulevard Du Pont-d'arve 61",
    "sg:city":"Gen\u00e8ve",
    "sg:orig_category":"Detailhandel mit Fleisch U Fleischwaren",
    "sg:phone":"+41 22 309 43 60",
    "sg:postcode":"1205",
    "sg:province":"Gen\u00e8ve",
    "wof:name":"Andr\u00e9 Vidonne",
    "wof:placetype":"venue"
},
  "geometry": {"coordinates":[6.1349010468,46.182094574],"type":"Point"}
}