{
  "type": "Feature",
  "properties": {
    "iso:country":"CH",
    "sg:address":"Rue Saint-randoald 15",
    "sg:city":"Del\u00e9mont",
    "sg:orig_category":"Non-Classified Establishments",
    "sg:phone":"+41 32 422 42 02",
    "sg:postcode":"2800",
    "sg:province":"Jura",
    "wof:name":"Marbrerie Kaiser Sa",
    "wof:placetype":"venue"
},
  "geometry": {"coordinates":[7.3431200981,47.3542709351],"type":"Point"}
}