{
  "type": "Feature",
  "properties": {
    "iso:country":"CH",
    "sg:address":"Alte Strasse 2",
    "sg:city":"Dittingen",
    "sg:orig_category":"Handelsvermittlung U Grosshandel Unternehmensberatung",
    "sg:phone":"+41 61 761 39 09",
    "sg:postcode":"4243",
    "sg:province":"Basel-Landschaft",
    "wof:name":"Broadwest Ag",
    "wof:placetype":"venue"
},
  "geometry": {"coordinates":[7.4990282059,47.43800354],"type":"Point"}
}