{
  "type": "Feature",
  "properties": {
    "iso:country":"CH",
    "sg:address":"St\u00fcckistrasse 12",
    "sg:city":"Gersau",
    "sg:orig_category":"Vermietung U Verpachtung von eigenen Immobilien",
    "sg:postcode":"6442",
    "sg:province":"Schwyz",
    "wof:name":"Plexihof-immobilien Ag",
    "wof:placetype":"venue"
},
  "geometry": {"coordinates":[8.5247983932,46.9942970276],"type":"Point"}
}