{
  "type": "Feature",
  "properties": {
    "iso:country":"CH",
    "sg:address":"Adelgasse",
    "sg:city":"Buckten",
    "sg:orig_category":"Primarschulen",
    "sg:postcode":"4446",
    "sg:province":"Basel-Landschaft",
    "wof:name":"Primarschule",
    "wof:placetype":"venue"
},
  "geometry": {"coordinates":[7.8473510742,47.4086685181],"type":"Point"}
}