{
  "type": "Feature",
  "properties": {
    "iso:country":"CH",
    "sg:address":"Rue Emile-yung 11",
    "sg:city":"Gen\u00e8ve",
    "sg:orig_category":"Zahntechnische Laboratorien",
    "sg:phone":"+41 22 347 30 61",
    "sg:postcode":"1205",
    "sg:province":"Gen\u00e8ve",
    "wof:name":"Alexandre Rancic Labor.de Proth\u00e8ses Dentaires",
    "wof:placetype":"venue"
},
  "geometry": {"coordinates":[6.1494460106,46.1953697205],"type":"Point"}
}