{
  "type": "Feature",
  "properties": {
    "iso:country":"CH",
    "sg:address":"Burghofstrasse 20",
    "sg:city":"Regensdorf",
    "sg:classifiers":[
        {
            "category":"Military Area",
            "subcategory":"Air Force Base",
            "type":"Public Place"
        }
    ],
    "sg:phone":"+41 18708999",
    "sg:postcode":"8105",
    "sg:province":"Z\u00fcrich",
    "sg:tags":[
        "electrical",
        "component",
        "electronic"
    ],
    "wof:name":"Ce Consumer Electronic Schweiz Ag",
    "wof:placetype":"venue"
},
  "geometry": {"coordinates":[8.4805612564,47.4285964966],"type":"Point"}
}