{
  "type": "Feature",
  "properties": {
    "iso:country":"CH",
    "sg:address":"Westerholz 8 2500 Biel/bienne. Postfach",
    "sg:city":"Biel/bienne",
    "sg:orig_category":"Non-Classified Establishments",
    "sg:postcode":"2504",
    "sg:province":"Bern",
    "wof:name":"Redor Reginelli A.",
    "wof:placetype":"venue"
},
  "geometry": {"coordinates":[7.2723989487,47.1504096985],"type":"Point"}
}