{
  "type": "Feature",
  "properties": {
    "addr:full":"Hertensteinstrasse 12 Luzern Luzern 6004",
    "addr:housenumber":"12",
    "addr:postcode":"6004",
    "addr:street":"Hertensteinstrasse",
    "iso:country":"CH",
    "sg:address":"Hertensteinstrasse 12",
    "sg:city":"Luzern",
    "sg:orig_category":"Detailhandel mit Bekleidung Detailhandel mit Geschenkartikeln U Souvenirs",
    "sg:phone":"+41 41 410 36 60",
    "sg:postcode":"6004",
    "sg:province":"Luzern",
    "wof:name":"Lacbal Sa",
    "wof:placetype":"venue"
},
  "geometry": {"coordinates":[8.31005,47.055447],"type":"Point"}
}