{
  "type": "Feature",
  "properties": {
    "iso:country":"CH",
    "sg:address":"Industriestr. 900",
    "sg:city":"B\u00f6singen",
    "sg:orig_category":"Instandhaltung U Reparatur von Automobilen",
    "sg:phone":"+41 31 747 83 48",
    "sg:postcode":"3178",
    "sg:province":"Fribourg",
    "wof:name":"Straub Ren\u00e9",
    "wof:placetype":"venue"
},
  "geometry": {"coordinates":[7.2196807861,46.8977355957],"type":"Point"}
}