{
  "type": "Feature",
  "properties": {
    "iso:country":"CH",
    "sg:address":"Hauptstrasse 165",
    "sg:city":"Muntelier",
    "sg:orig_category":"Instandhaltung U Reparatur von Automobilen",
    "sg:phone":"+41 26 670 24 22",
    "sg:postcode":"3286",
    "sg:province":"Fribourg",
    "wof:name":"H. & L. Auto-haus Ag Muntelier",
    "wof:placetype":"venue"
},
  "geometry": {"coordinates":[7.1394200325,46.9424247742],"type":"Point"}
}