{
  "type": "Feature",
  "properties": {
    "iso:country":"CH",
    "sg:address":"Austrasse 102a 4051 Basel. Postfach",
    "sg:city":"Basel",
    "sg:orig_category":"Offsetdruck",
    "sg:phone":"+41 91 827 12 91",
    "sg:postcode":"4003",
    "sg:province":"Basel-Stadt",
    "wof:name":"Tipografia Mesolcinese Gian Piero Rovati",
    "wof:placetype":"venue"
},
  "geometry": {"coordinates":[9.1283597946,46.2375984192],"type":"Point"}
}