{
  "type": "Feature",
  "properties": {
    "addr:full":"Rue De La Veraye 24 Territet-veytaux Vaud 1820",
    "addr:housenumber":"24",
    "addr:postcode":"1820",
    "addr:street":"Rue De La Veraye",
    "iso:country":"CH",
    "sg:address":"Rue De La Veraye 24",
    "sg:city":"Territet-veytaux",
    "sg:orig_category":"Autogaragen",
    "sg:phone":"+41 79 212 09 00",
    "sg:postcode":"1820",
    "sg:province":"Vaud",
    "wof:name":"Garage Auto Central",
    "wof:placetype":"venue"
},
  "geometry": {"coordinates":[6.580378,46.537861],"type":"Point"}
}