{
  "type": "Feature",
  "properties": {
    "addr:full":"Burgfelderstrasse 211 4055 Basel. Postfach 328 Basel Basel-Stadt 4055",
    "addr:housenumber":"211;328",
    "addr:postcode":"4055;4055",
    "addr:street":"Burgfelderstrasse;Postfach",
    "iso:country":"CH",
    "sg:address":"Burgfelderstrasse 211 4055 Basel. Postfach 328",
    "sg:city":"Basel",
    "sg:orig_category":"Allgemeiner Hoch U Tiefbau",
    "sg:phone":"+41 81 921 39 63",
    "sg:postcode":"4055",
    "sg:province":"Basel-Stadt",
    "wof:name":"Batigroup Ag",
    "wof:placetype":"venue"
},
  "geometry": {"coordinates":[9.26783,46.815769],"type":"Point"}
}