{
  "type": "Feature",
  "properties": {
    "iso:country":"CH",
    "sg:address":"Rue Du Valentin 34",
    "sg:city":"Lausanne",
    "sg:classifiers":[
        {
            "category":"Manufacturing",
            "subcategory":"Printing",
            "type":"Manufacturing & Wholesale Goods"
        }
    ],
    "sg:phone":"+41 21 312 01 40",
    "sg:postcode":"1004",
    "sg:province":"Vaud",
    "sg:tags":[
        "publishing"
    ],
    "wof:name":"Graph Style Aldo Ciervo",
    "wof:placetype":"venue"
},
  "geometry": {"coordinates":[6.6318998337,46.5241012573],"type":"Point"}
}