{
  "type": "Feature",
  "properties": {
    "iso:country":"CH",
    "sg:address":"Alte Steinhauserstrasse 29 6330 Cham. Postfach 5291",
    "sg:city":"Cham",
    "sg:orig_category":"Datenverarbeitungsdienste Softwareentwicklung U beratung",
    "sg:phone":"+41 77436706",
    "sg:postcode":"6330",
    "sg:province":"Zug",
    "wof:name":"Krebser Alfred, Informatik Beratung",
    "wof:placetype":"venue"
},
  "geometry": {"coordinates":[8.474659,47.190212],"type":"Point"}
}