{
  "type": "Feature",
  "properties": {
    "iso:country":"CH",
    "sg:address":"Austrasse 112",
    "sg:city":"Basel",
    "sg:orig_category":"Vermietung von Automobilen",
    "sg:phone":"+41 61 272 04 43",
    "sg:postcode":"4051",
    "sg:province":"Basel-Stadt",
    "wof:name":"Luna-autovermietung B. Werthm\u00fcller Inhaber J. Beutler",
    "wof:placetype":"venue"
},
  "geometry": {"coordinates":[7.5773777962,47.5554466248],"type":"Point"}
}