{
  "type": "Feature",
  "properties": {
    "iso:country":"CH",
    "sg:address":"L\u00e4rchenstrasse 6 9630 Wattwil. Postfach",
    "sg:city":"Wattwil",
    "sg:orig_category":"Fussboden, Fliesen U Plattenlegerei, Tapeziererei",
    "sg:phone":"+41 71 988 45 30",
    "sg:postcode":"9630",
    "sg:province":"St. Gallen",
    "wof:name":"To Hieu Dinh Plattenleger- U. Parkettbodenarbeiten",
    "wof:placetype":"venue"
},
  "geometry": {"coordinates":[9.0980882645,47.2924385071],"type":"Point"}
}