{
  "type": "Feature",
  "properties": {
    "iso:country":"CH",
    "sg:address":"Tannenwiesenstrasse 4",
    "sg:city":"Weinfelden",
    "sg:orig_category":"Glass Fibres For Reinforcing Thermoplastic And Thermosetting Plastics",
    "sg:phone":"+41 71 626 50 10",
    "sg:postcode":"8570",
    "sg:province":"Thurgau",
    "wof:name":"Compotech Ag",
    "wof:placetype":"venue"
},
  "geometry": {"coordinates":[9.0955200195,47.5699081421],"type":"Point"}
}