{
  "type": "Feature",
  "properties": {
    "iso:country":"CH",
    "sg:address":"6673",
    "sg:city":"Maggia",
    "sg:orig_category":"Vermietung U Verpachtung von eigenen Immobilien",
    "sg:phone":"+41 91 753 18 68",
    "sg:postcode":"6673",
    "sg:province":"Ticino",
    "wof:name":"Goepfert Bernard",
    "wof:placetype":"venue"
},
  "geometry": {"coordinates":[8.7074766159,46.2456703186],"type":"Point"}
}