{
  "type": "Feature",
  "properties": {
    "iso:country":"CH",
    "sg:address":"Grand-rue 37 1095 Ch\u00e2telard-lutry Case Postale 144",
    "sg:city":"Ch\u00e2telard-lutry",
    "sg:classifiers":[
        {
            "category":"Insurance",
            "subcategory":"Insurance Agent",
            "type":"Services"
        }
    ],
    "sg:phone":"+41 21 791 59 22",
    "sg:postcode":"1095",
    "sg:province":"Vaud",
    "sg:tags":[
        "versicherungsagenturen",
        "-broker"
    ],
    "wof:name":"Winterthur Assurances Agence",
    "wof:placetype":"venue"
},
  "geometry": {"coordinates":[6.6856899261,46.5022468567],"type":"Point"}
}