{
  "type": "Feature",
  "properties": {
    "iso:country":"CH",
    "sg:address":"Rue De Carouge 18",
    "sg:city":"Gen\u00e8ve",
    "sg:orig_category":"Zahnarztpraxen",
    "sg:phone":"+41 22 329 77 33",
    "sg:postcode":"1205",
    "sg:province":"Gen\u00e8ve",
    "wof:name":"Dr M\u00e9d. Dent. Anna Stoianov M\u00e9decin-dentiste",
    "wof:placetype":"venue"
},
  "geometry": {"coordinates":[6.1430478096,46.1964073181],"type":"Point"}
}