{
  "type": "Feature",
  "properties": {
    "iso:country":"CH",
    "sg:address":"1993",
    "sg:city":"Veysonnaz",
    "sg:classifiers":[
        {
            "category":"Bars & Pubs",
            "type":"Food & Drink"
        }
    ],
    "sg:phone":"+41 27 207 18 96",
    "sg:postcode":"1993",
    "sg:province":"Valais",
    "wof:name":"Bar Vague \u00e0 L'ame",
    "wof:placetype":"venue"
},
  "geometry": {"coordinates":[7.338803,46.195984],"type":"Point"}
}