{
  "type": "Feature",
  "properties": {
    "iso:country":"CH",
    "sg:address":"B\u00fctzenweg 20 6300 Zug. Postfach",
    "sg:city":"Zug",
    "sg:orig_category":"Detailhandel mit Metallwaren, Anstrichmitteln, Glaswaren, Bau U Heimwerkerbedarf",
    "sg:phone":"+41 32 373 38 44",
    "sg:postcode":"6300",
    "sg:province":"Zug",
    "wof:name":"Leroy-somer Sa",
    "wof:placetype":"venue"
},
  "geometry": {"coordinates":[7.3060708046,47.1093521118],"type":"Point"}
}