{
  "type": "Feature",
  "properties": {
    "iso:country":"CH",
    "sg:address":"Wipkingerplatz 4 8037 Z\u00fcrich. Postfach",
    "sg:city":"Z\u00fcrich",
    "sg:classifiers":[
        {
            "category":"Education",
            "subcategory":"Vocational School",
            "type":"Public Place"
        }
    ],
    "sg:phone":"+41 14464303",
    "sg:postcode":"8037",
    "sg:province":"Z\u00fcrich",
    "sg:tags":[
        "koch-",
        "haushaltschulen"
    ],
    "wof:name":"Schule F\u00fcr Haushalt & Lebensgestaltung Shl",
    "wof:placetype":"venue"
},
  "geometry": {"coordinates":[8.5241823196,47.3920326233],"type":"Point"}
}