{
  "type": "Feature",
  "properties": {
    "iso:country":"CH",
    "sg:address":"Kirchstrasse Postfach 201",
    "sg:city":"Gstaad",
    "sg:classifiers":[
        {
            "category":"Manufacturing",
            "subcategory":"Printing",
            "type":"Manufacturing & Wholesale Goods"
        }
    ],
    "sg:phone":"+41 41 482 62 62",
    "sg:postcode":"3780",
    "sg:province":"Bern",
    "sg:tags":[
        "publishing"
    ],
    "wof:name":"M\u00dcller Martini Maschinen & Anlagen Ag",
    "wof:placetype":"venue"
},
  "geometry": {"coordinates":[8.0461435318,46.979927063],"type":"Point"}
}