{
  "type": "Feature",
  "properties": {
    "iso:country":"CH",
    "sg:address":"Pichard Rue 9 1003 Lausanne. Postfach",
    "sg:city":"Lausanne",
    "sg:orig_category":"Reinigungsgewerbe",
    "sg:phone":"+41 21 320 71 06",
    "sg:postcode":"1003",
    "sg:province":"Vaud",
    "wof:name":"Luk, Bloch Alain",
    "wof:placetype":"venue"
},
  "geometry": {"coordinates":[6.6308732033,46.5218544006],"type":"Point"}
}