{
  "type": "Feature",
  "properties": {
    "iso:country":"CH",
    "sg:address":"Winkeln",
    "sg:city":"Sch\u00e4nis",
    "sg:classifiers":[
        {
            "category":"Restaurant",
            "type":"Food & Drink"
        }
    ],
    "sg:phone":"+41 55 615 11 57",
    "sg:postcode":"8718",
    "sg:province":"St. Gallen",
    "wof:name":"Restaurant Windegg",
    "wof:placetype":"venue"
},
  "geometry": {"coordinates":[9.0511722565,47.1488037109],"type":"Point"}
}