{
  "type": "Feature",
  "properties": {
    "iso:country":"CH",
    "sg:address":"Mitteldorfstrasse 22",
    "sg:city":"Diepoldsau",
    "sg:orig_category":"Zimmerei, Dachdeckerei, Bauspenglerei U Abdichtung",
    "sg:phone":"+41 71 733 18 64",
    "sg:postcode":"9444",
    "sg:province":"St. Gallen",
    "wof:name":"Kuster Jakob Holzbau Gmbh",
    "wof:placetype":"venue"
},
  "geometry": {"coordinates":[9.655705452,47.383140564],"type":"Point"}
}