{
  "type": "Feature",
  "properties": {
    "iso:country":"CH",
    "sg:address":"Chemin De Lallex 33",
    "sg:city":"Aran",
    "sg:orig_category":"Unclassifiable Establishments",
    "sg:postcode":"1091",
    "sg:province":"Vaud",
    "wof:name":"Georges-edouard Vacher, Cave Des St-martin, Producteur-n\u00e9gociant En Vins",
    "wof:placetype":"venue"
},
  "geometry": {"coordinates":[7.0344457626,47.0529136658],"type":"Point"}
}