{
  "type": "Feature",
  "properties": {
    "iso:country":"CH",
    "sg:address":"Untere Rebgasse 8",
    "sg:city":"Basel",
    "sg:classifiers":[
        {
            "category":"Insurance",
            "subcategory":"Insurance Agent",
            "type":"Services"
        }
    ],
    "sg:phone":"+41 61 681 42 66",
    "sg:postcode":"4058",
    "sg:province":"Basel-Stadt",
    "sg:tags":[
        "versicherungsagenturen",
        "-broker"
    ],
    "wof:name":"Secura Versicherungen Beratungsb\u00fcro Kleinbasel",
    "wof:placetype":"venue"
},
  "geometry": {"coordinates":[7.5927867889,47.5621948242],"type":"Point"}
}