{
  "type": "Feature",
  "properties": {
    "iso:country":"CH",
    "sg:address":"K\u00f6rbligen",
    "sg:city":"Inwil",
    "sg:orig_category":"Herstellung von Ziegeln U sonstiger Baukeramik",
    "sg:postcode":"6034",
    "sg:province":"Luzern",
    "wof:name":"Schumacher Kurt, Ziegeleien K\u00f6rbligen",
    "wof:placetype":"venue"
},
  "geometry": {"coordinates":[8.3954715729,47.1324005127],"type":"Point"}
}