{
  "type": "Feature",
  "properties": {
    "iso:country":"CH",
    "sg:address":"3179",
    "sg:city":"Kriechenwil",
    "sg:orig_category":"Sanit\u00e4r, Heizungs U L\u00fcftungsinstallation",
    "sg:phone":"+41 79 422 53 24",
    "sg:postcode":"3179",
    "sg:province":"Bern",
    "wof:name":"Schneiter Klaus",
    "wof:placetype":"venue"
},
  "geometry": {"coordinates":[7.5931491852,47.4693565369],"type":"Point"}
}