{
  "type": "Feature",
  "properties": {
    "iso:country":"CH",
    "sg:address":"Route De Massonnens",
    "sg:city":"Orsonnens",
    "sg:orig_category":"Polizei",
    "sg:phone":"+41 26 653 14 77",
    "sg:postcode":"1693",
    "wof:name":"Police Cantonale",
    "wof:placetype":"venue"
},
  "geometry": {"coordinates":[6.9952511787,46.7164039612],"type":"Point"}
}