{
  "type": "Feature",
  "properties": {
    "iso:country":"CH",
    "sg:address":"Kradolfstrasse 10",
    "sg:city":"Sulgen",
    "sg:orig_category":"Detailhandel mit Spielwaren",
    "sg:phone":"+41 56 442 21 28",
    "sg:postcode":"8583",
    "sg:province":"Thurgau",
    "wof:name":"Hans Rosenberg Rotrain Modelleisenbahnen",
    "wof:placetype":"venue"
},
  "geometry": {"coordinates":[8.2058963776,47.4793663025],"type":"Point"}
}