{
  "type": "Feature",
  "properties": {
    "iso:country":"CH",
    "sg:address":"Platz 13 8200 Schaffhausen. Postfach 670",
    "sg:city":"Schaffhausen",
    "sg:orig_category":"Versicherungen Generalagenturen",
    "sg:phone":"+41 52 635 44 44",
    "sg:postcode":"8201",
    "sg:province":"Schaffhausen",
    "wof:name":"Winterthur-versicherungen Regionaldirektion",
    "wof:placetype":"venue"
},
  "geometry": {"coordinates":[8.6352310181,47.697593689],"type":"Point"}
}