{
  "type": "Feature",
  "properties": {
    "iso:country":"CH",
    "sg:address":"R\u00fctistrasse 1",
    "sg:city":"Emmen",
    "sg:orig_category":"Sanit\u00e4r, Heizungs U L\u00fcftungsinstallation",
    "sg:phone":"+41 61 711 32 55",
    "sg:postcode":"6032",
    "sg:province":"Luzern",
    "wof:name":"St\u00e4bler-tarag Ag",
    "wof:placetype":"venue"
},
  "geometry": {"coordinates":[7.5986208916,47.4976119995],"type":"Point"}
}