{
  "type": "Feature",
  "properties": {
    "iso:country":"CH",
    "sg:address":"Place De Savoie 1 1260 Nyon. Postfach",
    "sg:city":"Nyon",
    "sg:classifiers":[
        {
            "category":"Travel",
            "subcategory":"Hotels & Motels",
            "type":"Entertainment"
        }
    ],
    "sg:postcode":"1260",
    "sg:province":"Vaud",
    "sg:tags":[
        "hotels",
        "mit",
        "restaurant"
    ],
    "wof:name":"Hotel Real, Tracchia Nicola",
    "wof:placetype":"venue"
},
  "geometry": {"coordinates":[6.2409029007,46.3804283142],"type":"Point"}
}