{
  "type": "Feature",
  "properties": {
    "iso:country":"CH",
    "sg:address":"La Sansonnaz",
    "sg:city":"Cheyres",
    "sg:orig_category":"Gartenbau Landschaftsplanungsb\u00fcros U Gartenarchitekturb\u00fcros",
    "sg:phone":"+41 21 691 50 54",
    "sg:postcode":"1468",
    "sg:province":"Fribourg",
    "wof:name":"Andr\u00e9 Aigroz Paysagiste",
    "wof:placetype":"venue"
},
  "geometry": {"coordinates":[6.5559048653,46.5122718811],"type":"Point"}
}