{
  "type": "Feature",
  "properties": {
    "iso:country":"CH",
    "sg:address":"Egliweg 10",
    "sg:city":"Nidau",
    "sg:orig_category":"Unclassifiable Establishments",
    "sg:postcode":"2560",
    "sg:province":"Bern",
    "wof:name":"Grossen Stadtplanmarketing",
    "wof:placetype":"venue"
},
  "geometry": {"coordinates":[7.233716011,47.1244430542],"type":"Point"}
}