{
  "type": "Feature",
  "properties": {
    "addr:full":"Burgmattstrasse 4322 Mumpf. Postfach 12 Mumpf Aargau 4322",
    "addr:housenumber":"12",
    "addr:postcode":"4322;4322",
    "addr:street":"Burgmattstrasse;Postfach",
    "iso:country":"CH",
    "sg:address":"Burgmattstrasse 4322 Mumpf. Postfach 12",
    "sg:city":"Mumpf",
    "sg:orig_category":"Allgemeiner Hoch U Tiefbau Allgemeiner Hochbau",
    "sg:phone":"+41 79 407 58 14",
    "sg:postcode":"4322",
    "sg:province":"Aargau",
    "wof:name":"Paul G\u00fcntert S\u00f6hne Ag",
    "wof:placetype":"venue"
},
  "geometry": {"coordinates":[7.917009,47.54604],"type":"Point"}
}