{
  "type": "Feature",
  "properties": {
    "iso:country":"CH",
    "sg:address":"T\u00f6berstrasse 3a",
    "sg:city":"Thal",
    "sg:orig_category":"Herstellung von sonstigen Produkten aus nichtmetallischen Mineralien",
    "sg:postcode":"9425",
    "sg:province":"St. Gallen",
    "wof:name":"B-bau Beau Bl\u00e4si",
    "wof:placetype":"venue"
},
  "geometry": {"coordinates":[9.574719429,47.4715881348],"type":"Point"}
}