{
  "type": "Feature",
  "properties": {
    "iso:country":"CH",
    "sg:address":"Feldh\u00f6fli 5",
    "sg:city":"Obernau",
    "sg:orig_category":"Vereine Fasnacht",
    "sg:phone":"+41 79 286 93 54",
    "sg:postcode":"6012",
    "sg:province":"Luzern",
    "wof:name":"Guggenmusig Notensch\u00e4nder",
    "wof:placetype":"venue"
},
  "geometry": {"coordinates":[8.0913600922,47.1465682983],"type":"Point"}
}