{
  "type": "Feature",
  "properties": {
    "iso:country":"CH",
    "sg:address":"Eisenbahnweg 7a",
    "sg:city":"Basel",
    "sg:orig_category":"Werbeagenturen",
    "sg:phone":"+41 61 691 30 91",
    "sg:postcode":"4058",
    "sg:province":"Basel-Stadt",
    "wof:name":"Copyright Buser & R\u00f6thenmund Werbeagentur",
    "wof:placetype":"venue"
},
  "geometry": {"coordinates":[7.6161937714,47.559841156],"type":"Point"}
}