{
  "type": "Feature",
  "properties": {
    "iso:country":"CH",
    "sg:address":"Waldhofstrasse 9b",
    "sg:city":"Langenthal",
    "sg:orig_category":"G\u00fcterbef\u00f6rderung im Strassenverkehr Sonstige Kurierdienste",
    "sg:phone":"+41 62 922 64 74",
    "sg:postcode":"4900",
    "sg:province":"Bern",
    "wof:name":"Kleintransporte Walter K\u00e4mpfer",
    "wof:placetype":"venue"
},
  "geometry": {"coordinates":[7.7902917862,47.216506958],"type":"Point"}
}