{
  "type": "Feature",
  "properties": {
    "iso:country":"CH",
    "sg:address":"Alpenstrasse 6 6004 Luzern. Postfach 5165",
    "sg:city":"Luzern",
    "sg:orig_category":"Versicherungen Generalagenturen",
    "sg:phone":"+41 41 210 82 62",
    "sg:postcode":"6002",
    "sg:province":"Luzern",
    "wof:name":"Z\u00fcrich Schweiz General- Agentur Luzern Privatkunden",
    "wof:placetype":"venue"
},
  "geometry": {"coordinates":[8.3111419678,47.0554161072],"type":"Point"}
}