{
  "type": "Feature",
  "properties": {
    "iso:country":"CH",
    "sg:address":"Challstr. 28.",
    "sg:city":"Metzerlen",
    "sg:orig_category":"Grosshandel mit sonstigen Gebrauchs U Verbrauchsg\u00fctern",
    "sg:postcode":"4116",
    "sg:province":"Solothurn",
    "wof:name":"Ares-waffen, Hammel P.",
    "wof:placetype":"venue"
},
  "geometry": {"coordinates":[7.4632349014,47.4614906311],"type":"Point"}
}