{
  "type": "Feature",
  "properties": {
    "iso:country":"CH",
    "sg:address":"Belle-combe 30",
    "sg:city":"Ch\u00e2telard-lutry",
    "sg:orig_category":"Fachdetailhandel in Verkaufsr\u00e4umen",
    "sg:postcode":"1095",
    "sg:province":"Vaud",
    "wof:name":"Md-diffusion, Diggelmann M.",
    "wof:placetype":"venue"
},
  "geometry": {"coordinates":[6.6814398766,46.5102882385],"type":"Point"}
}