{
  "type": "Feature",
  "properties": {
    "iso:country":"CH",
    "sg:address":"Hirschengraben 20",
    "sg:city":"Z\u00fcrich",
    "sg:orig_category":"Museen",
    "sg:phone":"+41 12619652",
    "sg:postcode":"8001",
    "sg:province":"Z\u00fcrich",
    "wof:name":"Haus Zum Kiel D\u00e9p.museum Rietberg",
    "wof:placetype":"venue"
},
  "geometry": {"coordinates":[8.5478935242,47.3696365356],"type":"Point"}
}