{
  "type": "Feature",
  "properties": {
    "iso:country":"CH",
    "sg:address":"Dinkelbergstrasse 21",
    "sg:city":"Riehen",
    "sg:orig_category":"Mit dem Versicherungsgewerbe verbundene T\u00e4tigkeiten",
    "sg:postcode":"4125",
    "sg:province":"Basel-Stadt",
    "wof:name":"Koller Bruno",
    "wof:placetype":"venue"
},
  "geometry": {"coordinates":[7.6569051743,47.5803222656],"type":"Point"}
}