{
  "type": "Feature",
  "properties": {
    "iso:country":"CH",
    "sg:address":"Rue Du Temple 20",
    "sg:city":"Cartigny",
    "sg:orig_category":"Handelsvermittlung U Grosshandel Handelsvermittlung U Grosshandel mit Automobilteilen U Zubeh\u00f6r",
    "sg:phone":"+41 22 756 36 06",
    "sg:postcode":"1236",
    "sg:province":"Gen\u00e8ve",
    "wof:name":"Off Road Accessoires Pi\u00e8ces D\u00e9tach\u00e9es Pr 4x4",
    "wof:placetype":"venue"
},
  "geometry": {"coordinates":[6.0174608231,46.1745071411],"type":"Point"}
}