{
  "type": "Feature",
  "properties": {
    "iso:country":"CH",
    "sg:address":"Gewerbestrasse 4",
    "sg:city":"M\u00e4nnedorf",
    "sg:orig_category":"Tierarztpraxis",
    "sg:phone":"+41 19200303",
    "sg:postcode":"8708",
    "sg:province":"Z\u00fcrich",
    "wof:name":"Dr. Med. Vet. Roger Weiss Tierarzt",
    "wof:placetype":"venue"
},
  "geometry": {"coordinates":[8.7012472153,47.2579040527],"type":"Point"}
}