{
  "type": "Feature",
  "properties": {
    "iso:country":"CH",
    "sg:address":"Erlenstrasse 59",
    "sg:city":"Basel",
    "sg:orig_category":"RESTAURANTS: TEA-ROOMS",
    "sg:phone":"+41 61 692 12 35",
    "sg:postcode":"4058",
    "sg:province":"Basel-Stadt",
    "wof:name":"J\u00e4gerhalle Betriebs Gmbh",
    "wof:placetype":"venue"
},
  "geometry": {"coordinates":[7.601556778,47.5689926147],"type":"Point"}
}