{
  "type": "Feature",
  "properties": {
    "iso:country":"CH",
    "sg:address":"Hauptstrasse 9",
    "sg:city":"Goldach",
    "sg:orig_category":"Detailhandel mit Damenbekleidung Kleiderboutiquen",
    "sg:phone":"+41 71 840 09 07",
    "sg:postcode":"9403",
    "sg:province":"St. Gallen",
    "wof:name":"Irene Tanner Boutique Fashion Point",
    "wof:placetype":"venue"
},
  "geometry": {"coordinates":[9.4659585953,47.4747695923],"type":"Point"}
}