{
  "type": "Feature",
  "properties": {
    "addr:full":"Grundackerweg 75 Berikon Aargau 8965",
    "addr:housenumber":"75",
    "addr:postcode":"8965",
    "addr:street":"Grundackerweg",
    "iso:country":"CH",
    "sg:address":"Grundackerweg 75",
    "sg:city":"Berikon",
    "sg:orig_category":"Ausbaugewerbe Installation von Heizungs, L\u00fcftungs U Klimaanlagen",
    "sg:phone":"+41 56 631 80 55",
    "sg:postcode":"8965",
    "sg:province":"Aargau",
    "wof:name":"Belfor (suisse) Ag",
    "wof:placetype":"venue"
},
  "geometry": {"coordinates":[8.367851,47.358402],"type":"Point"}
}