{
  "type": "Feature",
  "properties": {
    "iso:country":"CH",
    "sg:address":"Lindauerstrasse 11 8307 Effretikon. Postfach",
    "sg:city":"Effretikon",
    "sg:orig_category":"Fachdetailhandel in Verkaufsr\u00e4umen",
    "sg:postcode":"8307",
    "sg:province":"Z\u00fcrich",
    "wof:name":"I E X Ignjatovic S Sport, Geschenk, Und Werbeartikel; Import Und Export",
    "wof:placetype":"venue"
},
  "geometry": {"coordinates":[8.6843633652,47.428653717],"type":"Point"}
}