{
  "type": "Feature",
  "properties": {
    "iso:country":"CH",
    "sg:address":"Le Truel",
    "sg:city":"Nyon",
    "sg:orig_category":"Vermietung U Verpachtung von eigenen Immobilien",
    "sg:postcode":"1260",
    "sg:province":"Vaud",
    "wof:name":"Si Maison De Pr\u00e9laz",
    "wof:placetype":"venue"
},
  "geometry": {"coordinates":[6.212749958,46.3949584961],"type":"Point"}
}