{
  "type": "Feature",
  "properties": {
    "iso:country":"CH",
    "sg:address":"Route Du Grand-lancy 2",
    "sg:city":"Grand-lancy",
    "sg:orig_category":"Handels-H\u00e4user U Gesellschaften",
    "sg:phone":"+41 22 343 44 77",
    "sg:postcode":"1212",
    "sg:province":"Gen\u00e8ve",
    "wof:name":"Micronetics Inc., Ltd, Panama, Succursale De Lancy",
    "wof:placetype":"venue"
},
  "geometry": {"coordinates":[6.1220998764,46.1846008301],"type":"Point"}
}