{
  "type": "Feature",
  "properties": {
    "iso:country":"CH",
    "sg:address":"Holeestrasse 15",
    "sg:city":"Basel",
    "sg:orig_category":"Detailhandel mit M\u00f6beln U Haushaltsgegenst\u00e4nden Grosshandel mit Textilien",
    "sg:phone":"+41 61 421 15 00",
    "sg:postcode":"4054",
    "sg:province":"Basel-Stadt",
    "wof:name":"Ymcollection Yvonne Memmel",
    "wof:placetype":"venue"
},
  "geometry": {"coordinates":[7.5741958618,47.5444068909],"type":"Point"}
}