{
  "type": "Feature",
  "properties": {
    "iso:country":"CH",
    "sg:address":"Seestrasse 21 6353 Weggis. Postfach",
    "sg:city":"Weggis",
    "sg:classifiers":[
        {
            "category":"Travel",
            "subcategory":"Hotels & Motels",
            "type":"Entertainment"
        }
    ],
    "sg:phone":"+41 91 832 11 97",
    "sg:postcode":"6353",
    "sg:province":"Luzern",
    "sg:tags":[
        "hotels",
        "mit",
        "restaurant"
    ],
    "wof:name":"Garni-rist. Suisse",
    "wof:placetype":"venue"
},
  "geometry": {"coordinates":[9.1906404495,46.4630584717],"type":"Point"}
}