{
  "type": "Feature",
  "properties": {
    "iso:country":"CH",
    "sg:address":"Aeschstrasse 151",
    "sg:city":"Ebmatingen",
    "sg:orig_category":"Organisationen der Wohlfahrtspflege",
    "sg:phone":"+41 18221989",
    "sg:postcode":"8123",
    "sg:province":"Z\u00fcrich",
    "wof:name":"Pro Juventute Bezirk Uster C/o Kiebele",
    "wof:placetype":"venue"
},
  "geometry": {"coordinates":[8.643611908,47.3495864868],"type":"Point"}
}