{
  "type": "Feature",
  "properties": {
    "iso:country":"CH",
    "sg:address":"Molard Place Du 5",
    "sg:city":"Gen\u00e8ve",
    "sg:orig_category":"Dienstleistungen von Beteiligungsgesellschaften",
    "sg:postcode":"1204",
    "sg:province":"Gen\u00e8ve",
    "wof:name":"Ge Global (suisse) Sa",
    "wof:placetype":"venue"
},
  "geometry": {"coordinates":[6.1484470367,46.2035598755],"type":"Point"}
}