{
  "type": "Feature",
  "properties": {
    "iso:country":"CH",
    "sg:address":"Avenue Du Mail 14",
    "sg:city":"Gen\u00e8ve",
    "sg:orig_category":"Religi\u00f6se Vereinigungen divers",
    "sg:postcode":"1205",
    "sg:province":"Gen\u00e8ve",
    "wof:name":"Assoc.catholique Romaine De St-boniface",
    "wof:placetype":"venue"
},
  "geometry": {"coordinates":[6.139125824,46.1986236572],"type":"Point"}
}