{
  "type": "Feature",
  "properties": {
    "iso:country":"CH",
    "sg:address":"Seftigenstrasse 24",
    "sg:city":"Belp",
    "sg:classifiers":[
        {
            "category":"Travel",
            "subcategory":"Hotels & Motels",
            "type":"Entertainment"
        }
    ],
    "sg:phone":"+41 31 819 01 58",
    "sg:postcode":"3123",
    "sg:province":"Bern",
    "sg:tags":[
        "hotels",
        "mit",
        "restaurant"
    ],
    "wof:name":"Gasthof Traube, L\u00f6ffel Marianne",
    "wof:placetype":"venue"
},
  "geometry": {"coordinates":[7.487994194,46.8983573914],"type":"Point"}
}