{
  "type": "Feature",
  "properties": {
    "iso:country":"CH",
    "sg:address":"Grienmattweg 18",
    "sg:city":"Sissach",
    "sg:orig_category":"Sportvereine Turnen",
    "sg:phone":"+41 32 622 91 94",
    "sg:postcode":"4450",
    "sg:province":"Basel-Landschaft",
    "wof:name":"Turnverein Oberdorf",
    "wof:placetype":"venue"
},
  "geometry": {"coordinates":[7.5015997887,47.2306404114],"type":"Point"}
}