{
  "type": "Feature",
  "properties": {
    "iso:country":"CH",
    "sg:address":"1890 St-maurice Case Postale 76",
    "sg:city":"St-maurice",
    "sg:orig_category":"Pensionskassen",
    "sg:postcode":"1890",
    "sg:province":"Valais",
    "wof:name":"Fondation Bourg-dessus, Renens",
    "wof:placetype":"venue"
},
  "geometry": {"coordinates":[6.5958070755,46.5387382507],"type":"Point"}
}