{
  "type": "Feature",
  "properties": {
    "iso:country":"CH",
    "sg:address":"Gartenstrasse 5",
    "sg:city":"Sirnach",
    "sg:orig_category":"Detailhandel mit Blumen U Pflanzen",
    "sg:phone":"+41 81 834 90 70",
    "sg:postcode":"8370",
    "sg:province":"Thurgau",
    "wof:name":"Bel Verde Floristik Ambiente",
    "wof:placetype":"venue"
},
  "geometry": {"coordinates":[9.838191,46.497066],"type":"Point"}
}