{
  "type": "Feature",
  "properties": {
    "iso:country":"CH",
    "sg:address":"Rue Du Petit-ch\u00eane 17",
    "sg:city":"Lausanne",
    "sg:orig_category":"Grosshandel mit sonstigen Konsumg\u00fctern",
    "sg:phone":"+41 21 323 82 68",
    "sg:postcode":"1003",
    "sg:province":"Vaud",
    "wof:name":"Charles Caramello Agence Textiles",
    "wof:placetype":"venue"
},
  "geometry": {"coordinates":[6.6300430298,46.5183410645],"type":"Point"}
}