{
  "type": "Feature",
  "properties": {
    "iso:country":"CH",
    "sg:address":"Rue Des Liserons 4",
    "sg:city":"Yverdon-les-bains",
    "sg:orig_category":"Schreibb\u00fcros",
    "sg:phone":"+41 24 425 59 46",
    "sg:postcode":"1400",
    "sg:province":"Vaud",
    "wof:name":"Monique Perriard Bureau De Dactylographie",
    "wof:placetype":"venue"
},
  "geometry": {"coordinates":[6.6547670364,46.7773017883],"type":"Point"}
}