{
  "type": "Feature",
  "properties": {
    "iso:country":"CH",
    "sg:address":"Eichenweg 1",
    "sg:city":"Liestal",
    "sg:orig_category":"Sonstiges Textilgewerbe",
    "sg:phone":"+41 61 906 97 93",
    "sg:postcode":"4410",
    "sg:province":"Basel-Landschaft",
    "wof:name":"Schild Ag Liestal",
    "wof:placetype":"venue"
},
  "geometry": {"coordinates":[7.7274799347,47.4909362793],"type":"Point"}
}