{
  "type": "Feature",
  "properties": {
    "iso:country":"CH",
    "sg:address":"H\u00e4nsigr\u00fct 5",
    "sg:city":"Sachseln",
    "sg:orig_category":"Bauspenglerei Sanit\u00e4rinstallation U Spenglerei",
    "sg:phone":"+41 41 660 83 64",
    "sg:postcode":"6072",
    "sg:province":"Obwalden",
    "wof:name":"Christof Arnold Spenglerei",
    "wof:placetype":"venue"
},
  "geometry": {"coordinates":[8.220238,46.857616],"type":"Point"}
}