{
  "type": "Feature",
  "properties": {
    "iso:country":"CH",
    "sg:address":"Strengenfeldweg 17",
    "sg:city":"Zwingen",
    "sg:orig_category":"Grosshandel mit Erzen U Metallen Grosshandel mit Holz U Baustoffen",
    "sg:phone":"+41 61 763 08 50",
    "sg:postcode":"4222",
    "sg:province":"Basel-Landschaft",
    "wof:name":"Bauteq Dieter W.rohr",
    "wof:placetype":"venue"
},
  "geometry": {"coordinates":[7.5376520157,47.4378738403],"type":"Point"}
}