{
  "type": "Feature",
  "properties": {
    "iso:country":"CH",
    "sg:address":"Steinackerweg 21",
    "sg:city":"Turbenthal",
    "sg:orig_category":"Verkehrs- and Tourismusb\u00fcros",
    "sg:phone":"+41 52 385 26 50",
    "sg:postcode":"8488",
    "sg:province":"Z\u00fcrich",
    "wof:name":"Verkehrsverein Turbenthal Pr\u00e4s.herrn Ernst Buess",
    "wof:placetype":"venue"
},
  "geometry": {"coordinates":[8.8417434692,47.445892334],"type":"Point"}
}