{
  "type": "Feature",
  "properties": {
    "iso:country":"CH",
    "sg:address":"Winterseistrasse",
    "sg:city":"Hasle-r\u00fcegsau",
    "sg:orig_category":"Industrie, Metallindustrie",
    "sg:phone":"+41 34 460 01 01",
    "sg:postcode":"3415",
    "sg:province":"Bern",
    "wof:name":"Blaser Swisslube",
    "wof:placetype":"venue"
},
  "geometry": {"coordinates":[7.656434,47.015995],"type":"Point"}
}