{
  "type": "Feature",
  "properties": {
    "iso:country":"CH",
    "sg:address":"Jurastrasse 33",
    "sg:city":"Alchenfl\u00fch",
    "sg:orig_category":"Non-Classified Establishments",
    "sg:postcode":"3422",
    "sg:province":"Bern",
    "wof:name":"Gartenbau M. Schweizer",
    "wof:placetype":"venue"
},
  "geometry": {"coordinates":[7.5755062103,47.0856285095],"type":"Point"}
}