{
  "type": "Feature",
  "properties": {
    "iso:country":"CH",
    "sg:address":"7143",
    "sg:city":"Morissen",
    "sg:orig_category":"Grosshandel mit Maschinen U Ausr\u00fcstungen Herstellung von sonstigen Maschinen f\u00fcr unspezifische Verwe",
    "sg:phone":"+41 81 931 22 04",
    "sg:postcode":"7143",
    "sg:province":"Graubunden",
    "wof:name":"Klaus Heinz",
    "wof:placetype":"venue"
},
  "geometry": {"coordinates":[9.1711502075,46.7340698242],"type":"Point"}
}