{
  "type": "Feature",
  "properties": {
    "iso:country":"CH",
    "sg:address":"Bellerivestrasse 260 8008 Z\u00fcrich. Postfach",
    "sg:city":"Z\u00fcrich",
    "sg:orig_category":"Schifffahrts\u00e4mter",
    "sg:phone":"+41 71 686 50 20",
    "sg:postcode":"8034",
    "sg:province":"Z\u00fcrich",
    "wof:name":"Schiffahrtskontrolle Des Kantons Thurgau",
    "wof:placetype":"venue"
},
  "geometry": {"coordinates":[9.1967554092,47.6461029053],"type":"Point"}
}