{
  "type": "Feature",
  "properties": {
    "iso:country":"CH",
    "sg:address":"Place Pestalozzi 6",
    "sg:city":"Yverdon-les-bains",
    "sg:orig_category":"Fachdetailhandel mit pharmazeutischen Produkten",
    "sg:phone":"+41 24 425 24 24",
    "sg:postcode":"1400",
    "sg:province":"Vaud",
    "wof:name":"Marie-france Mettraux Pharmacie De La Place",
    "wof:placetype":"venue"
},
  "geometry": {"coordinates":[6.641064167,46.7786178589],"type":"Point"}
}