{
  "type": "Feature",
  "properties": {
    "iso:country":"CH",
    "sg:address":"T\u00fcffenwies 7/12",
    "sg:city":"Z\u00fcrich",
    "sg:orig_category":"Sonstige mit der Informatik verbundene T\u00e4tigkeiten",
    "sg:phone":"+41 14331718",
    "sg:postcode":"8064",
    "sg:province":"Z\u00fcrich",
    "wof:name":"E. Wiederkehr",
    "wof:placetype":"venue"
},
  "geometry": {"coordinates":[8.4926424026,47.3970031738],"type":"Point"}
}