{
  "type": "Feature",
  "properties": {
    "iso:country":"CH",
    "sg:address":"Bahnhofstrasse 1d",
    "sg:city":"Eglisau",
    "sg:orig_category":"Massagestudios",
    "sg:phone":"+41 18674032",
    "sg:postcode":"8193",
    "sg:province":"Z\u00fcrich",
    "wof:name":"Verena D\u00fcssel Rigling Massagen",
    "wof:placetype":"venue"
},
  "geometry": {"coordinates":[8.5163326263,47.5727272034],"type":"Point"}
}