{
  "type": "Feature",
  "properties": {
    "iso:country":"CH",
    "sg:address":"Av. De La Gare 10. 1630 Bulle. Postfach",
    "sg:city":"Bulle",
    "sg:orig_category":"Wirtschaftspr\u00fcfung, Steuerberatung U Treuhand",
    "sg:phone":"+41 26 912 68 50",
    "sg:postcode":"1630",
    "sg:province":"Fribourg",
    "wof:name":"Fiduciaire Meyer Henri, Expertcomptable Dipl\u00f4m\u00e9",
    "wof:placetype":"venue"
},
  "geometry": {"coordinates":[7.055893898,46.6180915833],"type":"Point"}
}