{
  "type": "Feature",
  "properties": {
    "iso:country":"CH",
    "sg:address":"Ligschwilring 12",
    "sg:city":"Urswil",
    "sg:classifiers":[
        {
            "category":"Banks & Credit Unions",
            "subcategory":"Bank",
            "type":"Services"
        }
    ],
    "sg:phone":"+41 4141883166",
    "sg:postcode":"6282",
    "wof:name":"Rentenanstalt Swiss Life",
    "wof:placetype":"venue"
},
  "geometry": {"coordinates":[8.285457,47.156033],"type":"Point"}
}