{
  "type": "Feature",
  "properties": {
    "iso:country":"CH",
    "sg:address":"Hauptstrasse",
    "sg:city":"Unterterzen",
    "sg:classifiers":[
        {
            "category":"Travel",
            "subcategory":"Hotels & Motels",
            "type":"Entertainment"
        }
    ],
    "sg:phone":"+41 81 738 11 52",
    "sg:postcode":"8882",
    "sg:province":"St. Gallen",
    "sg:tags":[
        "hotels",
        "mit",
        "restaurant"
    ],
    "wof:name":"Hotel Freieck",
    "wof:placetype":"venue"
},
  "geometry": {"coordinates":[9.2626037598,47.1147460938],"type":"Point"}
}