{
  "type": "Feature",
  "properties": {
    "iso:country":"CH",
    "sg:address":"Hauptstrasse 58 5502 Hunzenschwil. Postfach 143",
    "sg:city":"Hunzenschwil",
    "sg:orig_category":"Herstellung von Metallerzeugnissen ohne Maschinenbau",
    "sg:phone":"+41 62 897 24 21",
    "sg:postcode":"5502",
    "sg:province":"Aargau",
    "wof:name":"Rosta Ag",
    "wof:placetype":"venue"
},
  "geometry": {"coordinates":[8.1142902374,47.3874168396],"type":"Point"}
}