{
  "type": "Feature",
  "properties": {
    "iso:country":"CH",
    "sg:address":"Pilatusstrasse 13",
    "sg:city":"Kriens",
    "sg:orig_category":"Detailhandel mit Brot, Back U S\u00fcsswaren",
    "sg:phone":"+41 41 310 33 66",
    "sg:postcode":"6010",
    "sg:province":"Luzern",
    "wof:name":"Enzli-b\u00e4ckerei Richiger Max",
    "wof:placetype":"venue"
},
  "geometry": {"coordinates":[8.290319,47.032879],"type":"Point"}
}