{
  "type": "Feature",
  "properties": {
    "iso:country":"CH",
    "sg:address":"Via Ai Ronchi",
    "sg:city":"Bedano",
    "sg:orig_category":"Instandhaltung U Reparatur von Automobilen",
    "sg:phone":"+41 91 945 00 40",
    "sg:postcode":"6930",
    "sg:province":"Ticino",
    "wof:name":"Von B\u00fcren Eugen",
    "wof:placetype":"venue"
},
  "geometry": {"coordinates":[8.9203147888,46.0529594421],"type":"Point"}
}