{
  "type": "Feature",
  "properties": {
    "iso:country":"CH",
    "sg:address":"Kalchtaren 5",
    "sg:city":"Schongau",
    "sg:orig_category":"Grosshandel mit Baumaschinen Herstellung von Bergwerks U Baumaschinen",
    "sg:phone":"+41 41 917 46 27",
    "sg:postcode":"6288",
    "sg:province":"Luzern",
    "wof:name":"J.wenger Bautechnik Gmbh",
    "wof:placetype":"venue"
},
  "geometry": {"coordinates":[8.2786035538,47.2716941833],"type":"Point"}
}