{
  "type": "Feature",
  "properties": {
    "iso:country":"CH",
    "sg:address":"Brunnenwiesenstrasse 12",
    "sg:city":"Uster",
    "sg:orig_category":"Arztpraxen",
    "sg:phone":"+41 19423633",
    "sg:postcode":"8610",
    "sg:province":"Z\u00fcrich",
    "wof:name":"Dr.med.bernhard Thomas Arzt F\u00fcr Allgemeine Medizin",
    "wof:placetype":"venue"
},
  "geometry": {"coordinates":[8.721024,47.35334],"type":"Point"}
}