{
  "type": "Feature",
  "properties": {
    "iso:country":"CH",
    "sg:address":"Via Maderno 9",
    "sg:city":"Lugano",
    "sg:orig_category":"Markt U Meinungsforschung Unternehmensberatung",
    "sg:phone":"+41 91 910 77 11",
    "sg:postcode":"6900",
    "sg:province":"Ticino",
    "wof:name":"Samar Consulting Sa",
    "wof:placetype":"venue"
},
  "geometry": {"coordinates":[8.9549045563,46.0097045898],"type":"Point"}
}