{
  "type": "Feature",
  "properties": {
    "iso:country":"CH",
    "sg:address":"Bollingenstrasse 126 3065 Bolligen. Postfach",
    "sg:city":"Bolligen",
    "sg:classifiers":[
        {
            "category":"Bars & Pubs",
            "type":"Food & Drink"
        }
    ],
    "sg:phone":"+41 31 922 10 11",
    "sg:postcode":"3065",
    "sg:province":"Bern",
    "wof:name":"Sternen-bar-bolligen Gmbh",
    "wof:placetype":"venue"
},
  "geometry": {"coordinates":[7.496399,46.974754],"type":"Point"}
}