{
  "type": "Feature",
  "properties": {
    "iso:country":"CH",
    "sg:address":"Luzernstrasse 2",
    "sg:city":"Ballwil",
    "sg:orig_category":"Grosshandel mit Nahrungsmitteln, Getr\u00e4nken U Tabakwaren ohne ausgepr\u00e4gten Schwerpunkt",
    "sg:postcode":"6275",
    "sg:province":"Luzern",
    "wof:name":"Budmiger Frieda",
    "wof:placetype":"venue"
},
  "geometry": {"coordinates":[8.3171072006,47.1525421143],"type":"Point"}
}