{
  "type": "Feature",
  "properties": {
    "iso:country":"CH",
    "sg:address":"Wydenweg 15 3053 M\u00fcnchenbuchsee. Postfach",
    "sg:city":"M\u00fcnchenbuchsee",
    "sg:orig_category":"Unternehmensberatung",
    "sg:postcode":"3053",
    "sg:province":"Bern",
    "wof:name":"Lavina P. M.a.c.s",
    "wof:placetype":"venue"
},
  "geometry": {"coordinates":[7.4351148605,47.0202102661],"type":"Point"}
}