{
  "type": "Feature",
  "properties": {
    "iso:country":"CH",
    "sg:address":"Bleicherstrasse 20",
    "sg:city":"Luzern",
    "sg:orig_category":"Politische Parteien SP",
    "sg:phone":"+41 71 222 45 85",
    "sg:postcode":"6003",
    "sg:province":"Luzern",
    "wof:name":"Sp Des Kantons & Der Stadt St.gallen",
    "wof:placetype":"venue"
},
  "geometry": {"coordinates":[9.3721475601,47.4247894287],"type":"Point"}
}