{
  "type": "Feature",
  "properties": {
    "iso:country":"CH",
    "sg:address":"Fabrikstrasse",
    "sg:city":"M\u00e4rstetten",
    "sg:orig_category":"Herstellung von Futtermitteln f\u00fcr Nutztiere",
    "sg:phone":"+41 71 657 12 40",
    "sg:postcode":"8560",
    "sg:province":"Thurgau",
    "wof:name":"Grastrocknungs-genossenschaft M\u00e4rstetten Und Umgebung",
    "wof:placetype":"venue"
},
  "geometry": {"coordinates":[9.070602417,47.5872383118],"type":"Point"}
}