{
  "type": "Feature",
  "properties": {
    "iso:country":"CH",
    "sg:address":"Via Peri 18",
    "sg:city":"Lugano",
    "sg:orig_category":"Detailhandel mit Bekleidung Detailhandel mit Herrenbekleidung",
    "sg:phone":"+41 91 921 26 86",
    "sg:postcode":"6900",
    "sg:province":"Ticino",
    "wof:name":"Mister D Sa",
    "wof:placetype":"venue"
},
  "geometry": {"coordinates":[8.950789,46.00629],"type":"Point"}
}