{
  "type": "Feature",
  "properties": {
    "iso:country":"CH",
    "sg:address":"Talmattstrasse 44",
    "sg:city":"Riehen",
    "sg:orig_category":"Erschliessung von Grundst\u00fccken",
    "sg:postcode":"4125",
    "sg:province":"Basel-Stadt",
    "wof:name":"Genossenschaft Talmattstrasse",
    "wof:placetype":"venue"
},
  "geometry": {"coordinates":[7.6588959694,47.5706672668],"type":"Point"}
}