{
  "type": "Feature",
  "properties": {
    "iso:country":"CH",
    "sg:address":"Winterthurerstrasse 58",
    "sg:city":"Z\u00fcrich",
    "sg:orig_category":"Unternehmensberatung",
    "sg:phone":"+41 13613690",
    "sg:postcode":"8006",
    "sg:province":"Z\u00fcrich",
    "wof:name":"C. Starck & Partner Projektmanagement",
    "wof:placetype":"venue"
},
  "geometry": {"coordinates":[8.5466279984,47.3890037537],"type":"Point"}
}