{
  "type": "Feature",
  "properties": {
    "iso:country":"CH",
    "sg:address":"Hauptstrasse 20",
    "sg:city":"D\u00f6ttingen",
    "sg:orig_category":"Herstellung von medizinischen U chirurgischen Ger\u00e4ten sowie orthop\u00e4dischen Vorrichtungen Zahntechnis",
    "sg:phone":"+41 56 245 55 56",
    "sg:postcode":"5312",
    "sg:province":"Aargau",
    "wof:name":"M\u00fcller-sanders Dental-labor.",
    "wof:placetype":"venue"
},
  "geometry": {"coordinates":[8.2551765442,47.5760612488],"type":"Point"}
}