{
  "type": "Feature",
  "properties": {
    "iso:country":"CH",
    "sg:address":"Halden 704",
    "sg:city":"Schwellbrunn",
    "sg:orig_category":"Herstellung von Teppichen",
    "sg:phone":"+41 71 351 50 72",
    "sg:postcode":"9103",
    "sg:province":"Appenzell Ausserrhoden",
    "wof:name":"Raschle Bodenbel\u00e4ge",
    "wof:placetype":"venue"
},
  "geometry": {"coordinates":[9.2513399124,47.3491630554],"type":"Point"}
}