{
  "type": "Feature",
  "properties": {
    "iso:country":"CH",
    "sg:address":"Chemin Des Charmettes 9 1003 Lausanne. Postfach",
    "sg:city":"Lausanne",
    "sg:classifiers":[
        {
            "category":"Insurance",
            "subcategory":"Insurance Agent",
            "type":"Services"
        }
    ],
    "sg:phone":"+41 21 312 14 37",
    "sg:postcode":"1002",
    "sg:province":"Vaud",
    "sg:tags":[
        "versicherungsagenturen",
        "-broker"
    ],
    "wof:name":"Alain & Jacques Fragni\u00e8re Bureau D'assurances",
    "wof:placetype":"venue"
},
  "geometry": {"coordinates":[6.6284508705,46.5191917419],"type":"Point"}
}