{
  "type": "Feature",
  "properties": {
    "iso:country":"CH",
    "sg:address":"Haus 35",
    "sg:city":"Kriegstetten",
    "sg:orig_category":"Unclassifiable Establishments",
    "sg:phone":"+41 32 682 72 12",
    "sg:postcode":"4566",
    "sg:province":"Solothurn",
    "wof:name":"35, Ag F\u00fcr Kommunikation, Gestaltung Und Produktion",
    "wof:placetype":"venue"
},
  "geometry": {"coordinates":[7.5972681046,47.1784172058],"type":"Point"}
}