{
  "type": "Feature",
  "properties": {
    "iso:country":"CH",
    "sg:address":"Eschnerr\u00fcti 87",
    "sg:city":"Schellenberg",
    "sg:orig_category":"Architekturb\u00fcros",
    "sg:phone":"+41 75 373 66 56",
    "sg:postcode":"9488",
    "wof:name":"Manfred Kieber Architekturb\u00fcro",
    "wof:placetype":"venue"
},
  "geometry": {"coordinates":[9.53891,47.227451],"type":"Point"}
}