{
  "type": "Feature",
  "properties": {
    "iso:country":"CH",
    "sg:address":"Neue Winterthurerstrasse 22",
    "sg:city":"Wallisellen",
    "sg:orig_category":"Autogaragen",
    "sg:phone":"+41 18304622",
    "sg:postcode":"8304",
    "sg:province":"Z\u00fcrich",
    "wof:name":"Joachim Stech Autoreparaturwerkst\u00e4tte",
    "wof:placetype":"venue"
},
  "geometry": {"coordinates":[8.610424,47.411076],"type":"Point"}
}