{
  "type": "Feature",
  "properties": {
    "iso:country":"CH",
    "sg:address":"Rue De Vevey 208",
    "sg:city":"Bulle",
    "sg:orig_category":"Sonstige Kultur U Unterhaltungseinrichtungen",
    "sg:phone":"+41 32 721 49 28",
    "sg:postcode":"1630",
    "sg:province":"Fribourg",
    "wof:name":"Centro Portugues De Neuch\u00e2tel Centre Culturel De Loisirs",
    "wof:placetype":"venue"
},
  "geometry": {"coordinates":[6.9605441093,47.0033226013],"type":"Point"}
}