{
  "type": "Feature",
  "properties": {
    "iso:country":"CH",
    "sg:address":"9220",
    "sg:city":"Bischofszell",
    "sg:orig_category":"Campingpl\u00e4tze",
    "sg:phone":"+41 71 422 10 14",
    "sg:postcode":"9220",
    "sg:province":"Thurgau",
    "wof:name":"Campingplatz Leutswil",
    "wof:placetype":"venue"
},
  "geometry": {"coordinates":[9.240825,47.494225],"type":"Point"}
}