{
  "type": "Feature",
  "properties": {
    "iso:country":"CH",
    "sg:address":"M\u00fchlegasse 1",
    "sg:city":"Burgdorf",
    "sg:classifiers":[
        {
            "category":"Cinema",
            "subcategory":"Drive-in Theater",
            "type":"Entertainment"
        }
    ],
    "sg:phone":"+41 34 422 87 15",
    "sg:postcode":"3400",
    "sg:province":"Bern",
    "sg:tags":[
        "u",
        "ballettgruppen"
    ],
    "wof:name":"Musik Agentur, Kaderli M.",
    "wof:placetype":"venue"
},
  "geometry": {"coordinates":[7.6266407967,47.0573883057],"type":"Point"}
}