{
  "type": "Feature",
  "properties": {
    "iso:country":"CH",
    "sg:address":"8758",
    "sg:city":"Obstalden",
    "sg:orig_category":"Sportvereine Sch\u00fctzen",
    "sg:phone":"+41 27 952 29 05",
    "sg:postcode":"8758",
    "sg:province":"Glarus",
    "wof:name":"Feldsch\u00fctzengesellschaft",
    "wof:placetype":"venue"
},
  "geometry": {"coordinates":[9.1505403519,47.1172447205],"type":"Point"}
}