{
  "type": "Feature",
  "properties": {
    "addr:full":"Ch. De La Tuilerie 2 Couvet Neuch\u00e2tel 2108",
    "addr:housenumber":"2",
    "addr:postcode":"2108",
    "addr:street":"Ch. De La Tuilerie;Neucha\u0302Tel",
    "iso:country":"CH",
    "sg:address":"Ch. De La Tuilerie 2",
    "sg:city":"Couvet",
    "sg:classifiers":[
        {
            "category":"Banks & Credit Unions",
            "subcategory":"Bank",
            "type":"Services"
        }
    ],
    "sg:phone":"+41 38631506",
    "sg:postcode":"2108",
    "sg:province":"Neuch\u00e2tel",
    "wof:name":"Rentenanstalt Swiss Life",
    "wof:placetype":"venue"
},
  "geometry": {"coordinates":[6.636407,46.922764],"type":"Point"}
}