{
  "type": "Feature",
  "properties": {
    "iso:country":"CH",
    "sg:address":"Vorstadtstrasse 78",
    "sg:city":"Dietikon",
    "sg:orig_category":"Wirtschaftspr\u00fcfung, Steuerberatung U Treuhand",
    "sg:phone":"+41 17421611",
    "sg:postcode":"8953",
    "sg:province":"Z\u00fcrich",
    "wof:name":"Trima Ag Treuhandb\u00fcro",
    "wof:placetype":"venue"
},
  "geometry": {"coordinates":[8.399515152,47.4056129456],"type":"Point"}
}