{
  "type": "Feature",
  "properties": {
    "iso:country":"CH",
    "sg:address":"Maihofstrasse 76",
    "sg:city":"Luzern",
    "sg:classifiers":[
        {
            "category":"Shopping",
            "subcategory":"Books",
            "type":"Retail Goods"
        }
    ],
    "sg:phone":"+41 41 429 52 52",
    "sg:postcode":"6006",
    "sg:province":"Luzern",
    "wof:name":"Comenius Verlag",
    "wof:placetype":"venue"
},
  "geometry": {"coordinates":[8.312221,47.065666],"type":"Point"}
}