{
  "type": "Feature",
  "properties": {
    "addr:full":"Leimen Eggiwil Bern 3537",
    "addr:postcode":"3537",
    "iso:country":"CH",
    "sg:address":"Leimen",
    "sg:city":"Eggiwil",
    "sg:orig_category":"Detailhandel mit Bekleidung Detailhandel mit Spielwaren",
    "sg:phone":"+41 34 491 11 12",
    "sg:postcode":"3537",
    "sg:province":"Bern",
    "wof:name":"Hans Sch\u00e4r Textilien Spielwaren",
    "wof:placetype":"venue"
},
  "geometry": {"coordinates":[7.792974,46.869434],"type":"Point"}
}