{
  "type": "Feature",
  "properties": {
    "addr:full":"Untere Vogelsangstrasse 123 Winterthur Z\u00fcrich 8400",
    "addr:housenumber":"123",
    "addr:postcode":"8400",
    "addr:street":"Untere Vogelsangstrasse",
    "iso:country":"CH",
    "sg:address":"Untere Vogelsangstrasse 123",
    "sg:city":"Winterthur",
    "sg:orig_category":"Allgemeiner Hoch U Tiefbau Sonstige Bauinstallation",
    "sg:phone":"+41 79 236 72 49",
    "sg:postcode":"8400",
    "sg:province":"Z\u00fcrich",
    "wof:name":"Zumo Ag Bau-dienstleistungen",
    "wof:placetype":"venue"
},
  "geometry": {"coordinates":[8.719118,47.492542],"type":"Point"}
}