{
  "type": "Feature",
  "properties": {
    "iso:country":"CH",
    "sg:address":"Dorfstrasse 44",
    "sg:city":"Tegerfelden",
    "sg:orig_category":"Sportvereine Velo Rad-& Motorfahrer-Bund SRB",
    "sg:phone":"+41 56 245 15 89",
    "sg:postcode":"5306",
    "sg:province":"Aargau",
    "wof:name":"Veloclub Tegerfelden",
    "wof:placetype":"venue"
},
  "geometry": {"coordinates":[8.2899494171,47.5563049316],"type":"Point"}
}