{
  "type": "Feature",
  "properties": {
    "iso:country":"CH",
    "sg:address":"Moosstrasse 56",
    "sg:city":"Koppigen",
    "sg:orig_category":"Obstbau",
    "sg:phone":"+41 34 413 19 67",
    "sg:postcode":"3425",
    "sg:province":"Bern",
    "wof:name":"Walter L\u00fcthi Obstbau",
    "wof:placetype":"venue"
},
  "geometry": {"coordinates":[7.6071691513,47.1256942749],"type":"Point"}
}