{
  "type": "Feature",
  "properties": {
    "iso:country":"CH",
    "sg:address":"Route Du Monterri 14",
    "sg:city":"Courgenay",
    "sg:classifiers":[
        {
            "category":"Shopping",
            "subcategory":"Stationery & Office Supplies",
            "type":"Retail Goods"
        }
    ],
    "sg:phone":"+41 21 841 18 13",
    "sg:postcode":"2950",
    "sg:province":"Jura",
    "sg:tags":[
        "watchmaker's"
    ],
    "wof:name":"Charles-louis Rochat S.a.",
    "wof:placetype":"venue"
},
  "geometry": {"coordinates":[6.2792539597,46.6471328735],"type":"Point"}
}