{
  "type": "Feature",
  "properties": {
    "iso:country":"CH",
    "sg:address":"Baumgartenweg 20",
    "sg:city":"Therwil",
    "sg:orig_category":"Detailhandel mit Waren verschiedener Art, Hauptrichtung Nahrungsmittel Fachdetailhandel mit Nahrungs",
    "sg:phone":"+41 79 691 88 57",
    "sg:postcode":"4106",
    "sg:province":"Basel-Landschaft",
    "wof:name":"Hans Mathys Traiteur",
    "wof:placetype":"venue"
},
  "geometry": {"coordinates":[7.559650898,47.5004005432],"type":"Point"}
}