{
  "type": "Feature",
  "properties": {
    "iso:country":"CH",
    "sg:address":"Burgstrasse 7 8880 Walenstadt. Postfach 3",
    "sg:city":"Walenstadt",
    "sg:orig_category":"Sportvereine Ballsport Fussball",
    "sg:phone":"+41 81 735 13 93",
    "sg:postcode":"8880",
    "sg:province":"St. Gallen",
    "wof:name":"Fc Walenstadt",
    "wof:placetype":"venue"
},
  "geometry": {"coordinates":[9.3160772324,47.1226882935],"type":"Point"}
}