{
  "type": "Feature",
  "properties": {
    "iso:country":"CH",
    "sg:address":"Rue Des Battieux 3",
    "sg:city":"Neuch\u00e2tel",
    "sg:orig_category":"Detailhandel mit Waren verschiedener Art, Hauptrichtung Nahrungsmittel Fachdetailhandel mit pharmaze",
    "sg:phone":"+41 32 914 20 30",
    "sg:postcode":"2000",
    "sg:province":"Neuch\u00e2tel",
    "wof:name":"Pharmacie Coop\u00e9rative",
    "wof:placetype":"venue"
},
  "geometry": {"coordinates":[6.829100132,47.1025810242],"type":"Point"}
}