{
  "type": "Feature",
  "properties": {
    "iso:country":"CH",
    "sg:address":"Homberg",
    "sg:city":"Oschwand",
    "sg:orig_category":"S\u00e4gewerke",
    "sg:phone":"+41 62 961 65 75",
    "sg:postcode":"3476",
    "sg:province":"Bern",
    "wof:name":"Rudolf Zumstein S\u00e4gerei",
    "wof:placetype":"venue"
},
  "geometry": {"coordinates":[7.7128300667,47.1407585144],"type":"Point"}
}