{
  "type": "Feature",
  "properties": {
    "iso:country":"CH",
    "sg:address":"Dorfstrasse 9",
    "sg:city":"Sachseln",
    "sg:orig_category":"Vermietung U Verpachtung von eigenen Immobilien",
    "sg:phone":"+41 41 666 50 66",
    "sg:postcode":"6072",
    "sg:province":"Obwalden",
    "wof:name":"Piazza Immobilien Ag",
    "wof:placetype":"venue"
},
  "geometry": {"coordinates":[8.2397537231,46.8682403564],"type":"Point"}
}