{
  "type": "Feature",
  "properties": {
    "iso:country":"CH",
    "sg:address":"Casa Zappa",
    "sg:city":"Sagno",
    "sg:orig_category":"Gartenbau Landschaftsplanungsb\u00fcros U Gartenarchitekturb\u00fcros",
    "sg:phone":"+41 91 683 17 40",
    "sg:postcode":"6839",
    "sg:province":"Ticino",
    "wof:name":"Paolo Poggiati Paesaggista",
    "wof:placetype":"venue"
},
  "geometry": {"coordinates":[9.0399723053,45.8565864563],"type":"Point"}
}