{
  "type": "Feature",
  "properties": {
    "addr:full":"Bernstrasse 45 Herzogenbuchsee Bern 3360",
    "addr:housenumber":"45",
    "addr:postcode":"3360",
    "addr:street":"Bernstrasse;Bern",
    "iso:country":"CH",
    "sg:address":"Bernstrasse 45",
    "sg:city":"Herzogenbuchsee",
    "sg:classifiers":[
        {
            "category":"Social Services",
            "subcategory":"Retirement Home",
            "type":"Services"
        }
    ],
    "sg:phone":"+41 56 443 28 24",
    "sg:postcode":"3360",
    "sg:province":"Bern",
    "sg:tags":[
        "pflegeheime",
        "u",
        "alters"
    ],
    "wof:name":"Altersheim Schenkenbergertal",
    "wof:placetype":"venue"
},
  "geometry": {"coordinates":[8.145249,47.44767],"type":"Point"}
}