{
  "type": "Feature",
  "properties": {
    "iso:country":"CH",
    "sg:address":"In Der Chalen 4 Ebmatingen 8124 Maur. Postfach",
    "sg:city":"Ebmatingen",
    "sg:orig_category":"Unclassifiable Establishments",
    "sg:postcode":"8123",
    "sg:province":"Z\u00fcrich",
    "wof:name":"Max.films Gmbh",
    "wof:placetype":"venue"
},
  "geometry": {"coordinates":[8.6676130295,47.3403167725],"type":"Point"}
}