{
  "type": "Feature",
  "properties": {
    "iso:country":"CH",
    "sg:address":"St\u00e4dtle 5",
    "sg:city":"Vaduz",
    "sg:orig_category":"Herstellung von Medikamenten U sonstigen pharmazeutischen Erzeugnissen Parf\u00fcmerien U sonstiger Detai",
    "sg:phone":"+41 75 232 72 77",
    "sg:postcode":"9490",
    "wof:name":"Alrodo Ag",
    "wof:placetype":"venue"
},
  "geometry": {"coordinates":[9.5216808319,47.1411437988],"type":"Point"}
}