{
  "type": "Feature",
  "properties": {
    "addr:full":"Arbonerstrasse 45 Kronb\u00fchl 9302",
    "addr:housenumber":"45",
    "addr:postcode":"9302",
    "addr:street":"Arbonerstrasse",
    "iso:country":"CH",
    "sg:address":"Arbonerstrasse 45",
    "sg:city":"Kronb\u00fchl",
    "sg:classifiers":[
        {
            "category":"Building & Trades",
            "subcategory":"Construction",
            "type":"Services"
        }
    ],
    "sg:phone":"+41 71 298 18 18",
    "sg:postcode":"9302",
    "sg:tags":[
        "carpenter's",
        "work",
        "supraregional"
    ],
    "wof:name":"Jegle + Streule Ag",
    "wof:placetype":"venue"
},
  "geometry": {"coordinates":[9.394362,47.462673],"type":"Point"}
}