{
  "type": "Feature",
  "properties": {
    "iso:country":"CH",
    "sg:address":"Vers-chez-les-porchet",
    "sg:city":"Corcelles-le-jorat",
    "sg:orig_category":"Detektivb\u00fcros U \u00dcberwachung Grosshandel mit Tabakwaren",
    "sg:phone":"+41 21 903 32 02",
    "sg:postcode":"1082",
    "sg:province":"Vaud",
    "wof:name":"Dorincourt Sa",
    "wof:placetype":"venue"
},
  "geometry": {"coordinates":[6.733935833,46.6079406738],"type":"Point"}
}