{
  "type": "Feature",
  "properties": {
    "iso:country":"CH",
    "sg:address":"Meisenweg 3",
    "sg:city":"Derendingen",
    "sg:orig_category":"Detailhandel mit M\u00f6beln U Haushaltsgegenst\u00e4nden",
    "sg:phone":"+41 55 442 51 10",
    "sg:postcode":"4552",
    "sg:province":"Solothurn",
    "wof:name":"Omag-m\u00f6bel Ag",
    "wof:placetype":"venue"
},
  "geometry": {"coordinates":[8.851149559,47.1875152588],"type":"Point"}
}