{
  "type": "Feature",
  "properties": {
    "addr:full":"R\u00fctistrasse 17 Euthal Schwyz 8844",
    "addr:housenumber":"17",
    "addr:postcode":"8844",
    "addr:street":"Ruetistrasse;Schwyz",
    "iso:country":"CH",
    "sg:address":"R\u00fctistrasse 17",
    "sg:city":"Euthal",
    "sg:orig_category":"Detailhandel mit Beleuchtungs U Haushaltsgegenst\u00e4nden Detailhandel mit M\u00f6beln",
    "sg:phone":"+41 55 412 12 47",
    "sg:postcode":"8844",
    "sg:province":"Schwyz",
    "wof:name":"Hanspeter Auf Der Maur Wohnbedarf",
    "wof:placetype":"venue"
},
  "geometry": {"coordinates":[8.813115,47.097206],"type":"Point"}
}