{
  "type": "Feature",
  "properties": {
    "iso:country":"CH",
    "sg:address":"Wees 9107 Urn\u00e4sch. Postfach",
    "sg:city":"Urn\u00e4sch",
    "sg:orig_category":"Herstellung von sonstigen landwirtschaftlichen Maschinen",
    "sg:postcode":"9107",
    "sg:province":"Appenzell Ausserrhoden",
    "wof:name":"Kn\u00f6pfel Surge-melkanlagen",
    "wof:placetype":"venue"
},
  "geometry": {"coordinates":[9.2835702896,47.3174514771],"type":"Point"}
}