{
  "type": "Feature",
  "properties": {
    "iso:country":"CH",
    "sg:address":"Metallstrasse 9a 6300 Zug. Postfach",
    "sg:city":"Zug",
    "sg:orig_category":"Fernmeldedienste",
    "sg:postcode":"6300",
    "sg:province":"Zug",
    "wof:name":"Cri (schweiz) Ag Dienstleistungen Auf Dem Gebiet Der Telekommunikation U. Technologie, Bes. Auf Dem Schweizerischen Markt Usw",
    "wof:placetype":"venue"
},
  "geometry": {"coordinates":[8.5183458328,47.1736183167],"type":"Point"}
}