{
  "type": "Feature",
  "properties": {
    "iso:country":"CH",
    "sg:address":"Center Augustin",
    "sg:city":"Scuol",
    "sg:orig_category":"Bastel- and Hobbyartikel Detailhandel Detailhandel mit Geschenkartikeln U Souvenirs",
    "sg:phone":"+41 26 675 30 66",
    "sg:postcode":"7550",
    "sg:province":"Graubunden",
    "wof:name":"Brico Lyon D'or",
    "wof:placetype":"venue"
},
  "geometry": {"coordinates":[6.989671,46.85117],"type":"Point"}
}