{
  "type": "Feature",
  "properties": {
    "iso:country":"CH",
    "sg:address":"Eichlistrasse 1",
    "sg:city":"M\u00e4genwil",
    "sg:orig_category":"Grosshandel mit sonstigen Halbwaren Herstellung von Verpackungen aus Kunststoff",
    "sg:phone":"+41 62 887 40 30",
    "sg:postcode":"5506",
    "sg:province":"Aargau",
    "wof:name":"Storopack Ag",
    "wof:placetype":"venue"
},
  "geometry": {"coordinates":[8.2320699692,47.4149971008],"type":"Point"}
}