{
  "type": "Feature",
  "properties": {
    "iso:country":"CH",
    "sg:address":"Gr\u00fcttmoos",
    "sg:city":"H\u00e4usernmoos",
    "sg:orig_category":"Detailhandel mit Bekleidung Detailhandel mit Waren verschiedener Art, Hauptrichtung Nahrungsmittel",
    "sg:phone":"+41 34 435 01 27",
    "sg:postcode":"3463",
    "sg:province":"Bern",
    "wof:name":"Susanne Leumann Lebensmittel-textilien",
    "wof:placetype":"venue"
},
  "geometry": {"coordinates":[7.749378,47.079517],"type":"Point"}
}