{
  "type": "Feature",
  "properties": {
    "iso:country":"CH",
    "sg:address":"Aeschistrasse 13",
    "sg:city":"Nieder\u00f6nz",
    "sg:classifiers":[
        {
            "category":"Shopping",
            "subcategory":"Discount & Variety Stores",
            "type":"Retail Goods"
        }
    ],
    "sg:phone":"+41 62 961 34 23",
    "sg:postcode":"3362",
    "sg:province":"Bern",
    "sg:tags":[
        "shop",
        "aluminium",
        "welding"
    ],
    "wof:name":"Kurt Baumgartner Schweissexpress",
    "wof:placetype":"venue"
},
  "geometry": {"coordinates":[7.693854,47.185471],"type":"Point"}
}