{
  "type": "Feature",
  "properties": {
    "iso:country":"CH",
    "sg:address":"Bernstrasse 25",
    "sg:city":"Z\u00e4ziwil",
    "sg:orig_category":"Blumen U Zierpflanzenbau Dienstleistungen im Gartenbau",
    "sg:phone":"+41 31 711 04 40",
    "sg:postcode":"3532",
    "sg:province":"Bern",
    "wof:name":"Rudolf Stalder Blumengesch\u00e4ft & Gartenbau",
    "wof:placetype":"venue"
},
  "geometry": {"coordinates":[7.653922,46.903027],"type":"Point"}
}