{
  "type": "Feature",
  "properties": {
    "iso:country":"CH",
    "sg:address":"Aegeristrasse 58",
    "sg:city":"Zug",
    "sg:orig_category":"Unclassifiable Establishments",
    "sg:postcode":"6300",
    "sg:province":"Zug",
    "wof:name":"Epg Expressgips Gmbh",
    "wof:placetype":"venue"
},
  "geometry": {"coordinates":[8.5206766129,47.1674575806],"type":"Point"}
}