{
  "type": "Feature",
  "properties": {
    "iso:country":"CH",
    "sg:address":"Camminata Via 4a",
    "sg:city":"Bellinzona",
    "sg:orig_category":"RESTAURANTS: TEA-ROOMS",
    "sg:postcode":"6500",
    "sg:province":"Ticino",
    "wof:name":"Demm Sagl",
    "wof:placetype":"venue"
},
  "geometry": {"coordinates":[9.0223741531,46.1905403137],"type":"Point"}
}