{
  "type": "Feature",
  "properties": {
    "iso:country":"CH",
    "sg:address":"Hauptstrasse 106 4415 Lausen. Postfach",
    "sg:city":"Lausen",
    "sg:orig_category":"Detailhandel mit M\u00f6beln U Haushaltsgegenst\u00e4nden Einbau von Schreinerwaren",
    "sg:postcode":"4415",
    "sg:province":"Basel-Landschaft",
    "wof:name":"Oskar H\u00e4felfinger",
    "wof:placetype":"venue"
},
  "geometry": {"coordinates":[7.7613859177,47.47108078],"type":"Point"}
}