{
  "type": "Feature",
  "properties": {
    "iso:country":"CH",
    "sg:address":"Breitengasse 6",
    "sg:city":"Grenchen",
    "sg:orig_category":"Unclassifiable Establishments",
    "sg:postcode":"2540",
    "sg:province":"Solothurn",
    "wof:name":"T-rex Werbung Und Beschriftung Gmbh",
    "wof:placetype":"venue"
},
  "geometry": {"coordinates":[7.3956542015,47.1916351318],"type":"Point"}
}