{
  "type": "Feature",
  "properties": {
    "iso:country":"CH",
    "sg:address":"Grundstrasse 3",
    "sg:city":"Fehraltorf",
    "sg:classifiers":[
        {
            "category":"Government",
            "subcategory":"Post Office",
            "type":"Public Place"
        }
    ],
    "sg:phone":"+41 19541833",
    "sg:postcode":"8320",
    "sg:province":"Z\u00fcrich",
    "sg:tags":[
        "caf\u00e9s",
        "tea-rooms"
    ],
    "wof:name":"Caf\u00e9 Findling",
    "wof:placetype":"venue"
},
  "geometry": {"coordinates":[8.7554521561,47.3871002197],"type":"Point"}
}