{
  "type": "Feature",
  "properties": {
    "iso:country":"CH",
    "sg:address":"Ziegelrain 16",
    "sg:city":"Aarau",
    "sg:orig_category":"Detailhandel mit Gebrauchtwaren in Verkaufsr\u00e4umen",
    "sg:phone":"+41 62 824 25 15",
    "sg:postcode":"5000",
    "sg:province":"Aargau",
    "wof:name":"Brockenhaus Des Gemeinn\u00fctzigen Frauenvereins",
    "wof:placetype":"venue"
},
  "geometry": {"coordinates":[8.0432939529,47.3916473389],"type":"Point"}
}