{
  "type": "Feature",
  "properties": {
    "iso:country":"CH",
    "sg:address":"Wohlenschwilerstrasse 20",
    "sg:city":"T\u00e4gerig",
    "sg:orig_category":"Allgemeiner Hochbau",
    "sg:phone":"+41 31 381 00 25",
    "sg:postcode":"5522",
    "sg:province":"Aargau",
    "wof:name":"Gebr. Glauser Baugesch\u00e4ft Renovationen U. Sanierungen",
    "wof:placetype":"venue"
},
  "geometry": {"coordinates":[7.40529,46.942287],"type":"Point"}
}