{
  "type": "Feature",
  "properties": {
    "iso:country":"CH",
    "sg:address":"Colombi\u00e8re Rue De La 14",
    "sg:city":"Nyon",
    "sg:orig_category":"Herstellung von Konstruktionsteilen, Fertigbauteilen U Ausbauelementen aus Holz",
    "sg:postcode":"1260",
    "sg:province":"Vaud",
    "wof:name":"Ferri Eva Concepts & R\u00e9alisations D'int\u00e9rieur",
    "wof:placetype":"venue"
},
  "geometry": {"coordinates":[6.2411551476,46.3825721741],"type":"Point"}
}