{
  "type": "Feature",
  "properties": {
    "iso:country":"CH",
    "sg:address":"Im Brand 8",
    "sg:city":"Heiden",
    "sg:orig_category":"Hardwareberatung",
    "sg:phone":"+41 71 352 61 45",
    "sg:postcode":"9410",
    "sg:province":"Appenzell Ausserrhoden",
    "wof:name":"Net-web-design, Habersaat & Rothenbacher",
    "wof:placetype":"venue"
},
  "geometry": {"coordinates":[9.5362939835,47.4424171448],"type":"Point"}
}