{
  "type": "Feature",
  "properties": {
    "iso:country":"CH",
    "sg:address":"Augustinergasse 3/5",
    "sg:city":"Z\u00fcrich",
    "sg:orig_category":"RESTAURANTS: TEA-ROOMS",
    "sg:phone":"+41 12125457",
    "sg:postcode":"8001",
    "sg:province":"Z\u00fcrich",
    "wof:name":"Down Mexico Way Im Strohhof Ag",
    "wof:placetype":"venue"
},
  "geometry": {"coordinates":[8.540438652,47.3714561462],"type":"Point"}
}