{
  "type": "Feature",
  "properties": {
    "iso:country":"CH",
    "sg:address":"Peillonnex Rue 8 1225 Ch\u00eane-bourg. Postfach",
    "sg:city":"Ch\u00eane-bourg",
    "sg:orig_category":"Architektur U Ingenieurb\u00fcros",
    "sg:phone":"+41 71 223 57 21",
    "sg:postcode":"1225",
    "sg:province":"Gen\u00e8ve",
    "wof:name":"Karin Fritsche Stadelmann Dipl. Arch. Eth",
    "wof:placetype":"venue"
},
  "geometry": {"coordinates":[9.386855,47.418053],"type":"Point"}
}