{
  "type": "Feature",
  "properties": {
    "iso:country":"CH",
    "sg:address":"Dapples Avenue 42 1006 Lausanne. Postfach",
    "sg:city":"Lausanne",
    "sg:orig_category":"Gesundheitswesen",
    "sg:phone":"+41 21 617 86 49",
    "sg:postcode":"1006",
    "sg:province":"Vaud",
    "wof:name":"Bourquin Martine, Consultante, Sp\u00e9cialiste En Gestion Du Stress Gestion Du Stress, Conseils Et Formation Y Relatifs",
    "wof:placetype":"venue"
},
  "geometry": {"coordinates":[6.6272611618,46.5149040222],"type":"Point"}
}