{
  "type": "Feature",
  "properties": {
    "iso:country":"CH",
    "sg:address":"1041",
    "sg:city":"Poliez-pittet",
    "sg:orig_category":"Mechanische Werkst\u00e4tten",
    "sg:phone":"+41 21 881 54 84",
    "sg:postcode":"1041",
    "sg:province":"Vaud",
    "wof:name":"Pierre Ammann Atelier M\u00e9canique",
    "wof:placetype":"venue"
},
  "geometry": {"coordinates":[6.6836800575,46.6280097961],"type":"Point"}
}