{
  "type": "Feature",
  "properties": {
    "iso:country":"CH",
    "sg:address":"Route De Chaumont 90",
    "sg:city":"Chaumont",
    "sg:classifiers":[
        {
            "category":"Travel",
            "subcategory":"Hotels & Motels",
            "type":"Entertainment"
        }
    ],
    "sg:phone":"+41 32 963 11 44",
    "sg:postcode":"2067",
    "sg:province":"Neuch\u00e2tel",
    "sg:tags":[
        "hotels",
        "mit",
        "restaurant"
    ],
    "wof:name":"Auberge La Puce",
    "wof:placetype":"venue"
},
  "geometry": {"coordinates":[6.8929100037,47.1429443359],"type":"Point"}
}