{
  "type": "Feature",
  "properties": {
    "iso:country":"CH",
    "sg:address":"Centro Contone 1 Via Cantonale",
    "sg:city":"Contone",
    "sg:orig_category":"Unclassifiable Establishments",
    "sg:postcode":"6594",
    "sg:province":"Ticino",
    "wof:name":"Peyer Consult Sa",
    "wof:placetype":"venue"
},
  "geometry": {"coordinates":[8.9260749817,46.148525238],"type":"Point"}
}