{
  "type": "Feature",
  "properties": {
    "iso:country":"CH",
    "sg:address":"Holbeinstrasse 56",
    "sg:city":"Basel",
    "sg:orig_category":"Non-Classified Establishments",
    "sg:postcode":"4051",
    "sg:province":"Basel-Stadt",
    "wof:name":"Jundt Und Partner",
    "wof:placetype":"venue"
},
  "geometry": {"coordinates":[7.5836968422,47.5519447327],"type":"Point"}
}