{
  "type": "Feature",
  "properties": {
    "iso:country":"CH",
    "sg:address":"Im St\u00e4dtli",
    "sg:city":"Greifensee",
    "sg:orig_category":"Vermietung von Gebrauchsg\u00fctern Vermietung von Wasserfahrzeugen",
    "sg:phone":"+41 19411275",
    "sg:postcode":"8606",
    "sg:province":"Z\u00fcrich",
    "wof:name":"St\u00e4dtli-caf\u00e9 & Bootsvermietung",
    "wof:placetype":"venue"
},
  "geometry": {"coordinates":[8.6763715744,47.3648948669],"type":"Point"}
}