{
  "type": "Feature",
  "properties": {
    "iso:country":"CH",
    "sg:address":"Hallerstrasse 2",
    "sg:city":"Bern",
    "sg:orig_category":"Detailhandel mit Teppichen Verlegen von Fussboden",
    "sg:phone":"+41 31 301 73 96",
    "sg:postcode":"3012",
    "sg:province":"Bern",
    "wof:name":"Martin Plattner Bodenbel\u00e4ge Teppiche",
    "wof:placetype":"venue"
},
  "geometry": {"coordinates":[7.434800148,46.9516716003],"type":"Point"}
}