{
  "type": "Feature",
  "properties": {
    "iso:country":"CH",
    "sg:address":"Reichsgasse 61",
    "sg:city":"Chur",
    "sg:orig_category":"Sonstiger Detailhandel mit Metallwaren, Anstrichmitteln, Glaswaren, Bau U Heimwerkerbedarf",
    "sg:phone":"+41 81 252 08 85",
    "sg:postcode":"7000",
    "sg:province":"Graubunden",
    "wof:name":"Eugen Mazenauer Bastelshop",
    "wof:placetype":"venue"
},
  "geometry": {"coordinates":[9.5329761505,46.8490409851],"type":"Point"}
}