{
  "type": "Feature",
  "properties": {
    "iso:country":"CH",
    "sg:address":"Sch\u00fctzenmattstrasse 7",
    "sg:city":"Klingnau",
    "sg:orig_category":"Architektur U Ingenieurb\u00fcros Architekturb\u00fcros",
    "sg:phone":"+41 56 245 60 59",
    "sg:postcode":"5313",
    "sg:province":"Aargau",
    "wof:name":"Bau-konzept Kalt Marcel",
    "wof:placetype":"venue"
},
  "geometry": {"coordinates":[8.249767,47.578037],"type":"Point"}
}