{
  "type": "Feature",
  "properties": {
    "iso:country":"CH",
    "sg:address":"Austrasse 17",
    "sg:city":"Z\u00fcrich",
    "sg:orig_category":"Allgemeiner Hoch U Tiefbau Hoch U Tiefbau",
    "sg:phone":"+41 14621538",
    "sg:postcode":"8045",
    "sg:province":"Z\u00fcrich",
    "wof:name":"Renk A., Bauunternehmung",
    "wof:placetype":"venue"
},
  "geometry": {"coordinates":[8.519983,47.365993],"type":"Point"}
}