{
  "type": "Feature",
  "properties": {
    "iso:country":"CH",
    "sg:address":"Aathalstrasse 4",
    "sg:city":"Uster",
    "sg:classifiers":[
        {
            "category":"Shopping",
            "subcategory":"Discount & Variety Stores",
            "type":"Retail Goods"
        }
    ],
    "sg:phone":"+41 19405456",
    "sg:postcode":"8610",
    "sg:province":"Z\u00fcrich",
    "sg:tags":[
        "shop",
        "locksmith's"
    ],
    "wof:name":"De Donno Ag",
    "wof:placetype":"venue"
},
  "geometry": {"coordinates":[8.7394170761,47.345790863],"type":"Point"}
}