{
  "type": "Feature",
  "properties": {
    "iso:country":"CH",
    "sg:address":"St-aubin Route De",
    "sg:city":"Domdidier",
    "sg:orig_category":"Schaustellergewerbe U Vergn\u00fcgungsparks",
    "sg:phone":"+41 26 675 22 52",
    "sg:postcode":"1564",
    "sg:province":"Fribourg",
    "wof:name":"Chez Fred, Chardonnens Fr\u00e9d\u00e9ric",
    "wof:placetype":"venue"
},
  "geometry": {"coordinates":[7.0025000572,46.872303009],"type":"Point"}
}