{
  "type": "Feature",
  "properties": {
    "iso:country":"CH",
    "sg:address":"Route De Lugnez 26b",
    "sg:city":"Montignez",
    "sg:orig_category":"Bauschreinerei Zimmerei, Dachdeckerei, Bauspenglerei U Abdichtung",
    "sg:phone":"+41 71 333 15 84",
    "sg:postcode":"2924",
    "sg:province":"Jura",
    "wof:name":"Rechsteiner Pius Holzbau Ag",
    "wof:placetype":"venue"
},
  "geometry": {"coordinates":[9.365722,47.369015],"type":"Point"}
}