{
  "type": "Feature",
  "properties": {
    "iso:country":"CH",
    "sg:address":"Hauptstrasse 18",
    "sg:city":"Amlikon",
    "sg:orig_category":"Herstellung von Musikinstrumenten",
    "sg:phone":"+41 71 651 15 76",
    "sg:postcode":"8514",
    "sg:province":"Thurgau",
    "wof:name":"Bruno D\u00f6ssekker Atelier F\u00fcr Klarinettenbau",
    "wof:placetype":"venue"
},
  "geometry": {"coordinates":[9.0586919785,47.5704307556],"type":"Point"}
}