{
  "type": "Feature",
  "properties": {
    "iso:country":"CH",
    "sg:address":"B\u00f6sch 73 6331 H\u00fcnenberg. Postfach",
    "sg:city":"Hagendorn",
    "sg:orig_category":"Detailhandel mit B\u00fcromaschinen U einrichtungen Herstellung von sonstigen Maschinen f\u00fcr bestimmte Ver",
    "sg:phone":"+41 41 780 18 18",
    "sg:postcode":"6332",
    "sg:province":"Zug",
    "wof:name":"Easy Trade Ag Kopier, Drucker, Telefaxger\u00e4te, Handelsartikel; Handel, Vertrieb",
    "wof:placetype":"venue"
},
  "geometry": {"coordinates":[8.440962,47.161667],"type":"Point"}
}