{
  "type": "Feature",
  "properties": {
    "iso:country":"CH",
    "sg:address":"Ch. Des Primev\u00e8res 45",
    "sg:city":"Fribourg",
    "sg:orig_category":"Unclassifiable Establishments",
    "sg:postcode":"1700",
    "sg:province":"Fribourg",
    "wof:name":"Griselda Sa",
    "wof:placetype":"venue"
},
  "geometry": {"coordinates":[7.1410579681,46.8052902222],"type":"Point"}
}