{
  "type": "Feature",
  "properties": {
    "iso:country":"CH",
    "sg:address":"Neugasse 7 6300 Zug. Postfach 1051",
    "sg:city":"Zug",
    "sg:orig_category":"Reiseb\u00fcros",
    "sg:phone":"+41 41 729 41 80",
    "sg:postcode":"6301",
    "sg:province":"Zug",
    "wof:name":"Carlson Wagonlit Travel",
    "wof:placetype":"venue"
},
  "geometry": {"coordinates":[8.5157108307,47.1673927307],"type":"Point"}
}