{
  "type": "Feature",
  "properties": {
    "iso:country":"CH",
    "sg:address":"P\u00fcntenweg 5a",
    "sg:city":"Wettswil",
    "sg:orig_category":"Erbringung von Dienstleistungen f\u00fcr Unternehmen",
    "sg:phone":"+41 79 396 66 63",
    "sg:postcode":"8907",
    "sg:province":"Z\u00fcrich",
    "wof:name":"Single Design Gigerl Wohn- U. Bareinrichtungen Usw.; Planung, Herstellung U. Vertrieb",
    "wof:placetype":"venue"
},
  "geometry": {"coordinates":[8.9962530136,47.4793319702],"type":"Point"}
}