{
  "type": "Feature",
  "properties": {
    "iso:country":"CH",
    "sg:address":"Kirchgasse",
    "sg:city":"Leukerbad",
    "sg:orig_category":"Detailhandel mit Fahrr\u00e4dern Detailhandel mit Sportartikeln",
    "sg:phone":"+41 33 822 17 13",
    "sg:postcode":"3954",
    "sg:province":"Valais",
    "wof:name":"Esthemoa Bike & Snowboard",
    "wof:placetype":"venue"
},
  "geometry": {"coordinates":[7.9045820236,46.706161499],"type":"Point"}
}