{
  "type": "Feature",
  "properties": {
    "iso:country":"CH",
    "sg:address":"Chenevi\u00e8res Rue Des 39",
    "sg:city":"Court\u00e9telle",
    "sg:orig_category":"M\u00f6belschreinereien",
    "sg:phone":"+41 32 422 01 67",
    "sg:postcode":"2852",
    "sg:province":"Jura",
    "wof:name":"Glauser, Artisan-\u00e9b\u00e9niste",
    "wof:placetype":"venue"
},
  "geometry": {"coordinates":[7.3167719841,47.3426017761],"type":"Point"}
}