{
  "type": "Feature",
  "properties": {
    "iso:country":"CH",
    "sg:address":"Weirden 3 9062 Lustm\u00fchle. Postfach",
    "sg:city":"Lustm\u00fchle",
    "sg:orig_category":"Kauf U Verkauf von Immobilien auf eigene Rechnung",
    "sg:postcode":"9062",
    "sg:province":"Appenzell Ausserrhoden",
    "wof:name":"Inoba Gmbh",
    "wof:placetype":"venue"
},
  "geometry": {"coordinates":[9.3568115234,47.3980636597],"type":"Point"}
}