{
  "type": "Feature",
  "properties": {
    "iso:country":"CH",
    "sg:address":"5070",
    "sg:city":"Frick",
    "sg:orig_category":"Interessenvertretungen",
    "sg:postcode":"5070",
    "sg:province":"Aargau",
    "wof:name":"Stiftung Gemeindeverband Abfallbeseitigung Oberes Fricktal",
    "wof:placetype":"venue"
},
  "geometry": {"coordinates":[8.0233249664,47.5061149597],"type":"Point"}
}