{
  "type": "Feature",
  "properties": {
    "iso:country":"CH",
    "sg:address":"Grand-rue 45",
    "sg:city":"Grandval",
    "sg:orig_category":"Unclassifiable Establishments",
    "sg:postcode":"2745",
    "sg:province":"Bern",
    "wof:name":"Francis Freudiger Sa",
    "wof:placetype":"venue"
},
  "geometry": {"coordinates":[7.4255981445,47.2837600708],"type":"Point"}
}