{
  "type": "Feature",
  "properties": {
    "iso:country":"CH",
    "sg:address":"Route Des Rangiers 16",
    "sg:city":"Cornol",
    "sg:orig_category":"Grosshandel mit Getr\u00e4nken Grosshandel mit Wein U Spirituosen",
    "sg:phone":"+41 32 462 22 22",
    "sg:postcode":"2952",
    "sg:province":"Jura",
    "wof:name":"Petignat S\u00e0rl Vins Engros",
    "wof:placetype":"venue"
},
  "geometry": {"coordinates":[7.1666731834,47.4045448303],"type":"Point"}
}