{
  "type": "Feature",
  "properties": {
    "iso:country":"CH",
    "sg:address":"Zinnhagweg",
    "sg:city":"Arlesheim",
    "sg:orig_category":"Dienstleistungen im Gartenbau Reinigungsgewerbe",
    "sg:phone":"+41 61 701 54 72",
    "sg:postcode":"4144",
    "sg:province":"Basel-Landschaft",
    "wof:name":"Kink Haus Wartungen Gmbh",
    "wof:placetype":"venue"
},
  "geometry": {"coordinates":[7.6176710129,47.4900627136],"type":"Point"}
}