{
  "type": "Feature",
  "properties": {
    "iso:country":"CH",
    "sg:address":"Goldacherstrasse 10",
    "sg:city":"T\u00fcbach",
    "sg:orig_category":"Instandhaltung U Reparatur von Automobilen",
    "sg:phone":"+41 71 845 33 44",
    "sg:postcode":"9327",
    "sg:province":"St. Gallen",
    "wof:name":"Carrosserie Tuning Roduner Urs",
    "wof:placetype":"venue"
},
  "geometry": {"coordinates":[9.4573440552,47.4854202271],"type":"Point"}
}