{
  "type": "Feature",
  "properties": {
    "iso:country":"CH",
    "sg:address":"1589 Chabrey. Postfach",
    "sg:city":"Chabrey",
    "sg:orig_category":"Sonstige pers\u00f6nliche Dienstleistungen",
    "sg:phone":"+41 14453420",
    "sg:postcode":"1589",
    "sg:province":"Vaud",
    "wof:name":"Meteodat Gmbh",
    "wof:placetype":"venue"
},
  "geometry": {"coordinates":[8.4409780502,47.3507194519],"type":"Point"}
}