{
  "type": "Feature",
  "properties": {
    "iso:country":"CH",
    "sg:address":"Place Neuve 3 1009 Pully Case Postale 383",
    "sg:city":"Pully",
    "sg:classifiers":[
        {
            "category":"Restaurant",
            "type":"Food & Drink"
        }
    ],
    "sg:phone":"+41 21 729 81 88",
    "sg:postcode":"1009",
    "sg:province":"Vaud",
    "wof:name":"Restaurant Le Delta",
    "wof:placetype":"venue"
},
  "geometry": {"coordinates":[6.6595449448,46.5111923218],"type":"Point"}
}