{
  "type": "Feature",
  "properties": {
    "iso:country":"CH",
    "sg:address":"G\u00e4ssli 186",
    "sg:city":"Kleindietwil",
    "sg:orig_category":"Fernmeldedienste",
    "sg:postcode":"4936",
    "sg:province":"Bern",
    "wof:name":"Fernsehgenossenschaft Kleindietwil",
    "wof:placetype":"venue"
},
  "geometry": {"coordinates":[7.7939801216,47.145652771],"type":"Point"}
}