{
  "type": "Feature",
  "properties": {
    "iso:country":"CH",
    "sg:address":"Erlenstrasse 27b",
    "sg:city":"Therwil",
    "sg:orig_category":"Autotransporte international G\u00fcterbef\u00f6rderung im Strassenverkehr",
    "sg:phone":"+41 61 461 45 45",
    "sg:postcode":"4106",
    "sg:province":"Basel-Landschaft",
    "wof:name":"Freight-logistic Ag",
    "wof:placetype":"venue"
},
  "geometry": {"coordinates":[7.557071,47.503323],"type":"Point"}
}