{
  "type": "Feature",
  "properties": {
    "iso:country":"CH",
    "sg:address":"5604",
    "sg:city":"Hendschiken",
    "sg:orig_category":"Primarschulen",
    "sg:phone":"+41 62 891 41 21",
    "sg:postcode":"5604",
    "sg:province":"Aargau",
    "wof:name":"Primarschule",
    "wof:placetype":"venue"
},
  "geometry": {"coordinates":[8.2156896591,47.3865814209],"type":"Point"}
}