{
  "type": "Feature",
  "properties": {
    "iso:country":"CH",
    "sg:address":"Bahnhofstrasse 56 8001 Z\u00fcrich. Postfach",
    "sg:city":"Z\u00fcrich",
    "sg:orig_category":"Detailhandel mit Damenbekleidung Detailhandel mit Herrenbekleidung",
    "sg:phone":"+41 12152121",
    "sg:postcode":"8021",
    "sg:province":"Z\u00fcrich",
    "wof:name":"Och Sport Ag Waren, Bes. Sportartikel, Textilien Usw.; Handel, Kauf, Verkauf",
    "wof:placetype":"venue"
},
  "geometry": {"coordinates":[8.5383682251,47.3730621338],"type":"Point"}
}