{
  "type": "Feature",
  "properties": {
    "iso:country":"CH",
    "sg:address":"Walderstrasse 125",
    "sg:city":"Hinwil",
    "sg:orig_category":"Detailhandel mit Fleisch U Fleischwaren",
    "sg:phone":"+41 81 322 11 86",
    "sg:postcode":"8340",
    "sg:province":"Z\u00fcrich",
    "wof:name":"Hassler Ren\u00e9",
    "wof:placetype":"venue"
},
  "geometry": {"coordinates":[9.5779285431,46.9812812805],"type":"Point"}
}