{
  "type": "Feature",
  "properties": {
    "iso:country":"CH",
    "sg:address":"Wendelinsgasse 1",
    "sg:city":"Riehen",
    "sg:orig_category":"G\u00fcterbef\u00f6rderung im Strassenverkehr",
    "sg:phone":"+41 61 641 29 30",
    "sg:postcode":"4125",
    "sg:province":"Basel-Stadt",
    "wof:name":"Jani Susmani Garage & Transportunternehmung",
    "wof:placetype":"venue"
},
  "geometry": {"coordinates":[7.6520709991,47.5848693848],"type":"Point"}
}