{
  "type": "Feature",
  "properties": {
    "iso:country":"CH",
    "sg:address":"Spitalgasse 18 3011 Bern. Postfach",
    "sg:city":"Bern",
    "sg:orig_category":"Interessenvertretungen",
    "sg:postcode":"3005",
    "sg:province":"Bern",
    "wof:name":"Stiftung Luise M\u00fcller-fonds Stiftung F Arme U Hilfsbed\u00fcrftige Kinder U Erwachsene Im Kanton Bern",
    "wof:placetype":"venue"
},
  "geometry": {"coordinates":[7.4425492287,46.9481430054],"type":"Point"}
}