{
  "type": "Feature",
  "properties": {
    "iso:country":"CH",
    "sg:address":"Loestrasse 54",
    "sg:city":"Chur",
    "sg:orig_category":"Sonstige mit der Informatik verbundene T\u00e4tigkeiten",
    "sg:phone":"+41 81 252 61 90",
    "sg:postcode":"7000",
    "sg:province":"Graubunden",
    "wof:name":"Smallsolution@web",
    "wof:placetype":"venue"
},
  "geometry": {"coordinates":[9.5378370285,46.8573036194],"type":"Point"}
}