{
  "type": "Feature",
  "properties": {
    "iso:country":"CH",
    "sg:address":"Luzernerstrasse 27",
    "sg:city":"Root",
    "sg:classifiers":[
        {
            "category":"Bars & Pubs",
            "type":"Food & Drink"
        }
    ],
    "sg:phone":"+41 41 450 39 37",
    "sg:postcode":"6037",
    "sg:province":"Luzern",
    "wof:name":"Cocktail-pub",
    "wof:placetype":"venue"
},
  "geometry": {"coordinates":[8.386211,47.11097],"type":"Point"}
}