{
  "type": "Feature",
  "properties": {
    "iso:country":"CH",
    "sg:address":"Bahnhofstrasse 1",
    "sg:city":"T\u00e4gerwilen",
    "sg:orig_category":"Detailhandel mit Milcherzeugnissen U Eiern Verwertung von Milch",
    "sg:postcode":"8274",
    "sg:province":"Thurgau",
    "wof:name":"Dumas Andr\u00e9",
    "wof:placetype":"venue"
},
  "geometry": {"coordinates":[6.9318900108,46.6349906921],"type":"Point"}
}