{
  "type": "Feature",
  "properties": {
    "iso:country":"CH",
    "sg:address":"Grand-montfleury 48",
    "sg:city":"Versoix",
    "sg:orig_category":"Forschung U Entwicklung im Bereich der Naturwissenschaften",
    "sg:phone":"+41 22 775 33 00",
    "sg:postcode":"1290",
    "sg:province":"Gen\u00e8ve",
    "wof:name":"International Council On Human Rights Policy",
    "wof:placetype":"venue"
},
  "geometry": {"coordinates":[6.1645441055,46.2927932739],"type":"Point"}
}