{
  "type": "Feature",
  "properties": {
    "iso:country":"CH",
    "sg:address":"G\u00e4uggelistrasse 16",
    "sg:city":"Chur",
    "sg:orig_category":"Herstellung von Schmuck, Gold U Silberschmiedwaren",
    "sg:phone":"+41 81 253 53 45",
    "sg:postcode":"7000",
    "sg:province":"Graubunden",
    "wof:name":"Selin Gold, Sevgili Mehmet",
    "wof:placetype":"venue"
},
  "geometry": {"coordinates":[9.5295782089,46.8513336182],"type":"Point"}
}