{
  "type": "Feature",
  "properties": {
    "iso:country":"CH",
    "sg:address":"2943",
    "sg:city":"Vendlincourt",
    "sg:orig_category":"Pensionskassen",
    "sg:postcode":"2943",
    "sg:province":"Jura",
    "wof:name":"Fondation De Pr\u00e9voyance En Faveur Du Personnel De La Maison Corbat A. Et C.",
    "wof:placetype":"venue"
},
  "geometry": {"coordinates":[7.1505169868,47.4510688782],"type":"Point"}
}