{
  "type": "Feature",
  "properties": {
    "iso:country":"CH",
    "sg:address":"Rietstrasse 1",
    "sg:city":"Unterengstringen",
    "sg:orig_category":"Handel mit Motorr\u00e4dern, Teilen U Zubeh\u00f6r Instandhaltung U Reparatur von Motorr\u00e4dern",
    "sg:phone":"+41 17501916",
    "sg:postcode":"8103",
    "sg:province":"Z\u00fcrich",
    "wof:name":"Alma Motos Motorrad Reparaturen",
    "wof:placetype":"venue"
},
  "geometry": {"coordinates":[8.4490156174,47.4140586853],"type":"Point"}
}