{
  "type": "Feature",
  "properties": {
    "iso:country":"CH",
    "sg:address":"Winklenstrasse 21 3714 Frutigen. Postfach",
    "sg:city":"Frutigen",
    "sg:orig_category":"Wohnheime f\u00fcr Kinder U Jugendliche",
    "sg:phone":"+41 33 671 13 28",
    "sg:postcode":"3714",
    "sg:province":"Bern",
    "wof:name":"Kinderheimat Sunnehus",
    "wof:placetype":"venue"
},
  "geometry": {"coordinates":[7.646944046,46.5966033936],"type":"Point"}
}