{
  "type": "Feature",
  "properties": {
    "iso:country":"CH",
    "sg:address":"Haslenlohweg 20-22 6315 Ober\u00e4geri. Postfach",
    "sg:city":"Ober\u00e4geri",
    "sg:orig_category":"Unclassifiable Establishments",
    "sg:postcode":"6315",
    "sg:province":"Zug",
    "wof:name":"Nutraceutical & Natural Products (nnp) Ag Nat\u00fcrliche U. Naturnahe Produkte; Handel Usw",
    "wof:placetype":"venue"
},
  "geometry": {"coordinates":[8.6083869934,47.1386642456],"type":"Point"}
}