{
  "type": "Feature",
  "properties": {
    "iso:country":"CH",
    "sg:address":"Schulstrasse 13",
    "sg:city":"Schlieren",
    "sg:orig_category":"Erschliessung von Grundst\u00fccken",
    "sg:phone":"+41 17304615",
    "sg:postcode":"8952",
    "sg:province":"Z\u00fcrich",
    "wof:name":"Liberale Baugenossenschaft Schlieren",
    "wof:placetype":"venue"
},
  "geometry": {"coordinates":[8.4511642456,47.3969573975],"type":"Point"}
}