{
  "type": "Feature",
  "properties": {
    "iso:country":"CH",
    "sg:address":"Route Cantonale",
    "sg:city":"Assens",
    "sg:orig_category":"Instandhaltung U Reparatur von Automobilen",
    "sg:postcode":"1042",
    "sg:province":"Vaud",
    "wof:name":"Corsier Automobiles Sa",
    "wof:placetype":"venue"
},
  "geometry": {"coordinates":[6.2300667763,46.2609519958],"type":"Point"}
}