{
  "type": "Feature",
  "properties": {
    "iso:country":"CH",
    "sg:address":"Rishaldenweg 11",
    "sg:city":"Rothrist",
    "sg:orig_category":"Grosshandel mit Nahrungsmitteln, Getr\u00e4nken U Tabakwaren Grosshandel mit pharmazeutischen Erzeugnisse",
    "sg:phone":"+41 62 794 51 51",
    "sg:postcode":"4852",
    "sg:province":"Aargau",
    "wof:name":"Cosmos Intertrade Ag Internationaler Grosshandel",
    "wof:placetype":"venue"
},
  "geometry": {"coordinates":[7.892054081,47.3112640381],"type":"Point"}
}