{
  "type": "Feature",
  "properties": {
    "iso:country":"CH",
    "sg:address":"Gotthardlistrasse 13",
    "sg:city":"Ennetmoos",
    "sg:orig_category":"Fotografische Ateliers",
    "sg:phone":"+41 41 610 53 00",
    "sg:postcode":"6372",
    "sg:province":"Nidwalden",
    "wof:name":"Josef R\u00f6\u00f6sli Fotografisches Atelier",
    "wof:placetype":"venue"
},
  "geometry": {"coordinates":[8.3482198715,46.9582633972],"type":"Point"}
}