{
  "type": "Feature",
  "properties": {
    "addr:full":"Ch\u00e4mletenweg 6 R\u00fcmlang Z\u00fcrich 8153",
    "addr:housenumber":"6",
    "addr:postcode":"8153",
    "addr:street":"Chaemletenweg;Zuerich",
    "iso:country":"CH",
    "sg:address":"Ch\u00e4mletenweg 6",
    "sg:city":"R\u00fcmlang",
    "sg:classifiers":[
        {
            "category":"Building & Trades",
            "subcategory":"Construction",
            "type":"Services"
        }
    ],
    "sg:phone":"+41 18173800",
    "sg:postcode":"8153",
    "sg:province":"Z\u00fcrich",
    "sg:tags":[
        "central",
        "heating",
        "system"
    ],
    "wof:name":"Marcel Keller Brandschutzberatungen",
    "wof:placetype":"venue"
},
  "geometry": {"coordinates":[8.53324,47.450081],"type":"Point"}
}