{
  "type": "Feature",
  "properties": {
    "addr:full":"Zinnenstrasse 4 Hertenstein Luzern 6353",
    "addr:housenumber":"4",
    "addr:postcode":"6353",
    "addr:street":"Zinnenstrasse",
    "iso:country":"CH",
    "sg:address":"Zinnenstrasse 4",
    "sg:city":"Hertenstein",
    "sg:orig_category":"Dauerkulturbau Gem\u00fcsebau",
    "sg:phone":"+41 41 390 21 10",
    "sg:postcode":"6353",
    "sg:province":"Luzern",
    "wof:name":"Zurm\u00fchle Thomas, Gem\u00fcsebau",
    "wof:placetype":"venue"
},
  "geometry": {"coordinates":[8.434394,47.032295],"type":"Point"}
}