{
  "type": "Feature",
  "properties": {
    "iso:country":"CH",
    "sg:address":"Hauptstr. 10",
    "sg:city":"Tobel",
    "sg:classifiers":[
        {
            "category":"Banks & Credit Unions",
            "subcategory":"Bank",
            "type":"Services"
        }
    ],
    "sg:phone":"+41 71 918 70 70",
    "sg:postcode":"9555",
    "sg:province":"Thurgau",
    "wof:name":"Raiffeisenbank",
    "wof:placetype":"venue"
},
  "geometry": {"coordinates":[9.031462,47.514],"type":"Point"}
}