{
  "type": "Feature",
  "properties": {
    "addr:full":"Pro Quarta Surava Graubunden 7472",
    "addr:postcode":"7472",
    "iso:country":"CH",
    "sg:address":"Pro Quarta",
    "sg:city":"Surava",
    "sg:orig_category":"Allgemeiner Gartenbau",
    "sg:phone":"+41 81 404 21 21",
    "sg:postcode":"7472",
    "sg:province":"Graubunden",
    "wof:name":"Schutz Samen & Pflanzen Ag",
    "wof:placetype":"venue"
},
  "geometry": {"coordinates":[9.626892,46.668373],"type":"Point"}
}