{
  "type": "Feature",
  "properties": {
    "iso:country":"CH",
    "sg:address":"Hauptstrasse 175",
    "sg:city":"Bubendorf",
    "sg:orig_category":"Bauschreinerei Herstellung von M\u00f6beln verschiedener Art",
    "sg:phone":"+41 61 931 24 24",
    "sg:postcode":"4416",
    "sg:province":"Basel-Landschaft",
    "wof:name":"Erich Hummel",
    "wof:placetype":"venue"
},
  "geometry": {"coordinates":[7.730403,47.440578],"type":"Point"}
}