{
  "type": "Feature",
  "properties": {
    "iso:country":"CH",
    "sg:address":"Rte Des Bonnesfontaines 3a 1700 Freiburg. Postfach",
    "sg:city":"Fribourg",
    "sg:orig_category":"Interessenvertretungen",
    "sg:postcode":"1702",
    "sg:province":"Fribourg",
    "wof:name":"Association Foyer St-joseph",
    "wof:placetype":"venue"
},
  "geometry": {"coordinates":[7.1447491646,46.8109092712],"type":"Point"}
}