{
  "type": "Feature",
  "properties": {
    "iso:country":"CH",
    "sg:address":"Rue Du Rh\u00f4ne 100",
    "sg:city":"Gen\u00e8ve",
    "sg:orig_category":"Grosshandel mit medizinischen U orthop\u00e4dischen Artikeln Grosshandel mit pharmazeutischen Erzeugnisse",
    "sg:phone":"+41 32 423 16 56",
    "sg:postcode":"1201",
    "sg:province":"Gen\u00e8ve",
    "wof:name":"Varenkor Sa",
    "wof:placetype":"venue"
},
  "geometry": {"coordinates":[7.3494501114,47.3628463745],"type":"Point"}
}