{
  "type": "Feature",
  "properties": {
    "iso:country":"CH",
    "sg:address":"Unterm\u00fchli 9",
    "sg:city":"Zug",
    "sg:orig_category":"Technische, physikalische U chemische Untersuchung Unternehmensberatung",
    "sg:phone":"+41 41 760 22 21",
    "sg:postcode":"6300",
    "sg:province":"Zug",
    "wof:name":"Abp Assessment Ag",
    "wof:placetype":"venue"
},
  "geometry": {"coordinates":[8.5177631378,47.1804656982],"type":"Point"}
}