{
  "type": "Feature",
  "properties": {
    "iso:country":"CH",
    "sg:address":"Rue De La Blancherie 36",
    "sg:city":"Chavannes-renens",
    "sg:orig_category":"Arztpraxen",
    "sg:phone":"+41 21 635 68 68",
    "sg:postcode":"1022",
    "sg:province":"Vaud",
    "wof:name":"Dr M\u00e9d. Pierre Hunziker M\u00e9decin G\u00e9n\u00e9raliste Fmh",
    "wof:placetype":"venue"
},
  "geometry": {"coordinates":[6.579712,46.532619],"type":"Point"}
}