{
  "type": "Feature",
  "properties": {
    "iso:country":"CH",
    "sg:address":"Bahnhofstrasse 28",
    "sg:city":"Nebikon",
    "sg:classifiers":[
        {
            "category":"Banks & Credit Unions",
            "subcategory":"Bank",
            "type":"Services"
        }
    ],
    "sg:phone":"+41 4162862777",
    "sg:postcode":"6244",
    "sg:province":"Luzern",
    "wof:name":"Raiffeisenbank Oberwiggertal",
    "wof:placetype":"venue"
},
  "geometry": {"coordinates":[7.976706,47.190208],"type":"Point"}
}