{
  "type": "Feature",
  "properties": {
    "iso:country":"CH",
    "sg:address":"Hasli 6032 Emmen. Postfach",
    "sg:city":"Emmen",
    "sg:orig_category":"Herstellung von K\u00e4se Sonstige Milchverwertung",
    "sg:phone":"+41 41 269 20 00",
    "sg:postcode":"6032",
    "sg:province":"Luzern",
    "wof:name":"Emmi Schweiz Ag",
    "wof:placetype":"venue"
},
  "geometry": {"coordinates":[8.3140602112,47.0952644348],"type":"Point"}
}