{
  "type": "Feature",
  "properties": {
    "iso:country":"CH",
    "sg:address":"Steinacher 36",
    "sg:city":"Egolzwil",
    "sg:orig_category":"Offsetdruck Verlagsgewerbe",
    "sg:phone":"+41 41 980 35 21",
    "sg:postcode":"6243",
    "sg:province":"Luzern",
    "wof:name":"Magnificat Druck & Verlag",
    "wof:placetype":"venue"
},
  "geometry": {"coordinates":[8.0093412399,47.1853713989],"type":"Point"}
}