{
  "type": "Feature",
  "properties": {
    "iso:country":"CH",
    "sg:address":"Brand",
    "sg:city":"Obstalden",
    "sg:orig_category":"Finanzierungsinstitutionen",
    "sg:postcode":"8758",
    "sg:province":"Glarus",
    "wof:name":"Crusero Gmbh",
    "wof:placetype":"venue"
},
  "geometry": {"coordinates":[9.1505403519,47.1172447205],"type":"Point"}
}