{
  "type": "Feature",
  "properties": {
    "iso:country":"CH",
    "sg:address":"Grand-rue 33",
    "sg:city":"Nyon",
    "sg:orig_category":"Non-Classified Establishments",
    "sg:postcode":"1260",
    "sg:province":"Vaud",
    "wof:name":"Si Grand-rue 33 \u00e0 Nyon",
    "wof:placetype":"venue"
},
  "geometry": {"coordinates":[6.2382688522,46.3810844421],"type":"Point"}
}