{
  "type": "Feature",
  "properties": {
    "iso:country":"CH",
    "sg:address":"Buchserstr. 34",
    "sg:city":"D\u00e4llikon",
    "sg:classifiers":[
        {
            "category":"Manufacturing",
            "subcategory":"Textiles",
            "type":"Manufacturing & Wholesale Goods"
        }
    ],
    "sg:phone":"+41 81 756 17 67",
    "sg:postcode":"8108",
    "sg:province":"Z\u00fcrich",
    "sg:tags":[
        "linen",
        "clothing",
        "fabric"
    ],
    "wof:name":"Texba Ag",
    "wof:placetype":"venue"
},
  "geometry": {"coordinates":[9.4810638428,47.1726875305],"type":"Point"}
}