{
  "type": "Feature",
  "properties": {
    "iso:country":"CH",
    "sg:city":"Brusio",
    "sg:classifiers":[
        {
            "category":"Banks & Credit Unions",
            "subcategory":"Bank",
            "type":"Services"
        }
    ],
    "sg:phone":"+41 41 825 51 22",
    "sg:postcode":"7743",
    "sg:province":"Graubunden",
    "wof:name":"Banca Cantonale Grigione",
    "wof:placetype":"venue"
},
  "geometry": {"coordinates":[10.125009,46.2589],"type":"Point"}
}