{
  "type": "Feature",
  "properties": {
    "iso:country":"CH",
    "sg:address":"Eickackerstrasse 15",
    "sg:city":"D\u00fcbendorf",
    "sg:orig_category":"Sportvereine Turnen",
    "sg:phone":"+41 18219280",
    "sg:postcode":"8600",
    "sg:province":"Z\u00fcrich",
    "wof:name":"M\u00e4nnerriege Des Turnvereins",
    "wof:placetype":"venue"
},
  "geometry": {"coordinates":[8.6285772324,47.3903770447],"type":"Point"}
}