{
  "type": "Feature",
  "properties": {
    "iso:country":"CH",
    "sg:address":"Lobenschwendi 17",
    "sg:city":"Rehetobel",
    "sg:orig_category":"Dienstleistungen von Beteiligungsgesellschaften",
    "sg:postcode":"9038",
    "sg:province":"Appenzell Ausserrhoden",
    "wof:name":"Meier J.j. Verwaltungs Ag",
    "wof:placetype":"venue"
},
  "geometry": {"coordinates":[9.4672212601,47.4204292297],"type":"Point"}
}