{
  "type": "Feature",
  "properties": {
    "iso:country":"CH",
    "sg:address":"1426",
    "sg:city":"Concise",
    "sg:orig_category":"Instandhaltung U Reparatur von Automobilen",
    "sg:phone":"+41 24 434 13 88",
    "sg:postcode":"1426",
    "sg:province":"Vaud",
    "wof:name":"Kl\u00e4ui P.",
    "wof:placetype":"venue"
},
  "geometry": {"coordinates":[6.7186899185,46.8510704041],"type":"Point"}
}