{
  "type": "Feature",
  "properties": {
    "iso:country":"CH",
    "sg:address":"Route De Divonne 48 1260 Nyon Case Postale 2221",
    "sg:city":"Nyon",
    "sg:orig_category":"Softwareentwicklung U beratung",
    "sg:phone":"+41 22 361 35 83",
    "sg:postcode":"1260",
    "sg:province":"Vaud",
    "wof:name":"Computer Software Services Z. Jean Sa",
    "wof:placetype":"venue"
},
  "geometry": {"coordinates":[6.2227759361,46.3829574585],"type":"Point"}
}