{
  "type": "Feature",
  "properties": {
    "iso:country":"CH",
    "sg:address":"Via L. Pasteur 1",
    "sg:city":"Chiasso",
    "sg:orig_category":"Vermietung U Verpachtung von eigenen Immobilien",
    "sg:postcode":"6830",
    "sg:province":"Ticino",
    "wof:name":"La Roggiana Sa",
    "wof:placetype":"venue"
},
  "geometry": {"coordinates":[9.0241270065,45.8334274292],"type":"Point"}
}