{
  "type": "Feature",
  "properties": {
    "iso:country":"CH",
    "sg:address":"Dorfstrasse 89",
    "sg:city":"Amsoldingen",
    "sg:orig_category":"Bauschreinerei Zimmerei, Dachdeckerei, Bauspenglerei U Abdichtung",
    "sg:phone":"+41 33 341 12 66",
    "sg:postcode":"3633",
    "sg:province":"Bern",
    "wof:name":"Bruni Holzbau Ag Zimmerei & Schreinerei",
    "wof:placetype":"venue"
},
  "geometry": {"coordinates":[7.57986,46.727161],"type":"Point"}
}