{
  "type": "Feature",
  "properties": {
    "iso:country":"CH",
    "sg:address":"Allmeindstrasse 13",
    "sg:city":"Schmerikon",
    "sg:orig_category":"Grosshandel mit sonstigen Maschinen U Ausr\u00fcstungen f\u00fcr Industrie, Handel U Schiffahrt Vermietung von",
    "sg:phone":"+41 55 286 12 12",
    "sg:postcode":"8716",
    "sg:province":"St. Gallen",
    "wof:name":"Atrag",
    "wof:placetype":"venue"
},
  "geometry": {"coordinates":[8.9540605545,47.2227096558],"type":"Point"}
}