{
  "type": "Feature",
  "properties": {
    "iso:country":"CH",
    "sg:address":"Hauptstrasse 93",
    "sg:city":"Ipsach",
    "sg:orig_category":"Cnc Cutting, Cnc Chip Removal",
    "sg:phone":"+41 71 744 24 38",
    "sg:postcode":"2563",
    "sg:province":"Bern",
    "wof:name":"Rolf K\u00f6ppel",
    "wof:placetype":"venue"
},
  "geometry": {"coordinates":[9.609972,47.460213],"type":"Point"}
}