{
  "type": "Feature",
  "properties": {
    "iso:country":"CH",
    "sg:address":"En Peny La Tire-au-loup",
    "sg:city":"Mies",
    "sg:orig_category":"Finanzierungsinstitutionen",
    "sg:postcode":"1295",
    "sg:province":"Vaud",
    "wof:name":"Perrot & Cie Consultants",
    "wof:placetype":"venue"
},
  "geometry": {"coordinates":[6.1685490608,46.3010520935],"type":"Point"}
}