{
  "type": "Feature",
  "properties": {
    "iso:country":"CH",
    "sg:address":"Schulweg 65",
    "sg:city":"Jona",
    "sg:orig_category":"Sonstiger Grosshandel",
    "sg:postcode":"8645",
    "sg:province":"St. Gallen",
    "wof:name":"Zartmann A. Gmbh",
    "wof:placetype":"venue"
},
  "geometry": {"coordinates":[8.8371601105,47.2278785706],"type":"Point"}
}