{
  "type": "Feature",
  "properties": {
    "iso:country":"CH",
    "sg:address":"Via Del Torchio 8",
    "sg:city":"Biasca",
    "sg:orig_category":"Detailhandel mit Brot, Back U S\u00fcsswaren",
    "sg:phone":"+41 91 862 16 26",
    "sg:postcode":"6710",
    "sg:province":"Ticino",
    "wof:name":"Clemente Florioli Sa",
    "wof:placetype":"venue"
},
  "geometry": {"coordinates":[8.971593,46.363091],"type":"Point"}
}