{
  "type": "Feature",
  "properties": {
    "iso:country":"CH",
    "sg:address":"Walchepl.neum\u00fchlequai 10/12 8001 Z\u00fcrich. Postfach",
    "sg:city":"Z\u00fcrich",
    "sg:orig_category":"Herstellung von Bettwaren Herstellung von konfektionierten Textilwaren ohne Bekleidung",
    "sg:phone":"+41 41 448 25 55",
    "sg:postcode":"8023",
    "sg:province":"Z\u00fcrich",
    "wof:name":"Arit Ag",
    "wof:placetype":"venue"
},
  "geometry": {"coordinates":[8.3109169006,47.1298675537],"type":"Point"}
}