{
  "type": "Feature",
  "properties": {
    "iso:country":"CH",
    "sg:address":"Wilerstrasse",
    "sg:city":"B\u00fctschwil",
    "sg:orig_category":"Grosshandel mit sonstigen Maschinen U Ausr\u00fcstungen f\u00fcr Industrie, Handel U Schiffahrt",
    "sg:postcode":"9606",
    "sg:province":"St. Gallen",
    "wof:name":"Bachmann Hans Hochdruckanlagen Ag",
    "wof:placetype":"venue"
},
  "geometry": {"coordinates":[9.0759515762,47.3687400818],"type":"Point"}
}