{
  "type": "Feature",
  "properties": {
    "iso:country":"CH",
    "sg:address":"Stockbr\u00fchlweg 1",
    "sg:city":"Sargans",
    "sg:orig_category":"Unternehmensberatung Wirtschaftspr\u00fcfung, Steuerberatung U Treuhand",
    "sg:phone":"+41 81 710 07 70",
    "sg:postcode":"7320",
    "sg:province":"St. Gallen",
    "wof:name":"Tpm Treuhand Mulle Peter",
    "wof:placetype":"venue"
},
  "geometry": {"coordinates":[9.4441385269,47.047744751],"type":"Point"}
}