{
  "type": "Feature",
  "properties": {
    "iso:country":"CH",
    "sg:address":"Rietwiesstrasse 26",
    "sg:city":"Horgen",
    "sg:orig_category":"Architekturb\u00fcros",
    "sg:phone":"+41 17256867",
    "sg:postcode":"8810",
    "sg:province":"Z\u00fcrich",
    "wof:name":"Ueli Rohner Architekturb\u00fcro",
    "wof:placetype":"venue"
},
  "geometry": {"coordinates":[8.618386,47.250065],"type":"Point"}
}