{
  "type": "Feature",
  "properties": {
    "iso:country":"CH",
    "sg:address":"Laufenstrasse 4",
    "sg:city":"Breitenbach",
    "sg:orig_category":"Detailhandel mit Beleuchtungs U Haushaltsgegenst\u00e4nden Detailhandel mit elektrischen Haushalts-,Radio",
    "sg:phone":"+41 61 781 44 61",
    "sg:postcode":"4226",
    "sg:province":"Solothurn",
    "wof:name":"Ambiente Degen A.",
    "wof:placetype":"venue"
},
  "geometry": {"coordinates":[7.542829,47.408154],"type":"Point"}
}