{
  "type": "Feature",
  "properties": {
    "iso:country":"CH",
    "sg:address":"Lauenenstrasse",
    "sg:city":"Gstaad",
    "sg:orig_category":"Grosshandel mit Baumaterialien Grosshandel mit Holz U Bauelementen aus Holz",
    "sg:phone":"+41 33 744 76 76",
    "sg:postcode":"3780",
    "sg:province":"Bern",
    "wof:name":"Glasson Mat\u00e9riaux Sa",
    "wof:placetype":"venue"
},
  "geometry": {"coordinates":[7.2964911461,46.467414856],"type":"Point"}
}