{
  "type": "Feature",
  "properties": {
    "iso:country":"CH",
    "sg:address":"Weinfelderstrasse 75",
    "sg:city":"Amriswil",
    "sg:orig_category":"Sportvereine Schwingen",
    "sg:phone":"+41 71 411 33 35",
    "sg:postcode":"8580",
    "sg:province":"Thurgau",
    "wof:name":"Schwingklub Oberthurgau",
    "wof:placetype":"venue"
},
  "geometry": {"coordinates":[9.2834091187,47.5446243286],"type":"Point"}
}