{
  "type": "Feature",
  "properties": {
    "iso:country":"CH",
    "sg:address":"Weidliweg 2 3122 Kehrsatz. Postfach",
    "sg:city":"Kehrsatz",
    "sg:orig_category":"Interessenvertretungen",
    "sg:postcode":"3122",
    "sg:province":"Bern",
    "wof:name":"Verein Kultur Und \u00d6ffentlichkeit Kehrsatz Vk\u00d6k Kultur Im Weitesten Sinn. Kunst, Begegnung, Gespr\u00e4chskultur, Wohnkultur Usw",
    "wof:placetype":"venue"
},
  "geometry": {"coordinates":[7.4686670303,46.9091644287],"type":"Point"}
}