{
  "type": "Feature",
  "properties": {
    "iso:country":"CH",
    "sg:address":"Avenir Route De L' 11 1950 Sion. Postfach",
    "sg:city":"Sion",
    "sg:orig_category":"Arbeitnehmerverb\u00e4nde",
    "sg:postcode":"1950",
    "sg:province":"Valais",
    "wof:name":"Caisse De Retraite Anticip\u00e9e Du Secteur Principal De La Construction Et Du Carrelage Du Canton Du Valais - Retabat Eviter Le Licenciement Et Le Ch\u00f4mage Des Travailleurs \u00e2ges Etc",
    "wof:placetype":"venue"
},
  "geometry": {"coordinates":[7.3634,46.236698],"type":"Point"}
}