{
  "type": "Feature",
  "properties": {
    "iso:country":"CH",
    "sg:address":"Route Chapelle",
    "sg:city":"Estavayer-le-lac",
    "sg:orig_category":"Detailhandel mit Waren verschiedener Art, Hauptrichtung Nahrungsmittel",
    "sg:phone":"+41 26 663 56 50",
    "sg:postcode":"1470",
    "sg:province":"Fribourg",
    "wof:name":"Migros",
    "wof:placetype":"venue"
},
  "geometry": {"coordinates":[6.8493299484,46.8495445251],"type":"Point"}
}