{
  "type": "Feature",
  "properties": {
    "iso:country":"CH",
    "sg:address":"Hauptstrasse 79",
    "sg:city":"Mitl\u00f6di",
    "sg:orig_category":"Grosshandel mit Parf\u00fcmerieartikeln U K\u00f6rperpflegemitteln Herstellung von Duft U K\u00f6rperpflegemitteln",
    "sg:phone":"+41 17130381",
    "sg:postcode":"8756",
    "sg:province":"Glarus",
    "wof:name":"Frebag Ag",
    "wof:placetype":"venue"
},
  "geometry": {"coordinates":[8.5364551544,47.2859458923],"type":"Point"}
}