{
  "type": "Feature",
  "properties": {
    "iso:country":"CH",
    "sg:address":"Waldr\u00f6sli",
    "sg:city":"Schwendibach",
    "sg:orig_category":"Gesundheitswesen",
    "sg:postcode":"3624",
    "sg:province":"Bern",
    "wof:name":"Stiftung F\u00fcr Ambulante Krankenpflege K\u00fcsnacht",
    "wof:placetype":"venue"
},
  "geometry": {"coordinates":[8.5787334442,47.3212051392],"type":"Point"}
}