{
  "type": "Feature",
  "properties": {
    "iso:country":"CH",
    "sg:address":"Schwandrainweg 11",
    "sg:city":"Steffisburg",
    "sg:orig_category":"Grosshandel mit lebenden Tieren",
    "sg:phone":"+41 33 437 42 89",
    "sg:postcode":"3612",
    "sg:province":"Bern",
    "wof:name":"Walter Schmid Pferdehandel",
    "wof:placetype":"venue"
},
  "geometry": {"coordinates":[7.6426758766,46.7707633972],"type":"Point"}
}