{
  "type": "Feature",
  "properties": {
    "iso:country":"CH",
    "sg:address":"Reform.pfarrhaus Zinggen 109",
    "sg:city":"Wilchingen",
    "sg:orig_category":"Religi\u00f6se Vereinigungen divers",
    "sg:postcode":"8217",
    "sg:province":"Schaffhausen",
    "wof:name":"Cvjm",
    "wof:placetype":"venue"
},
  "geometry": {"coordinates":[8.4684848785,47.6675109863],"type":"Point"}
}