{
  "type": "Feature",
  "properties": {
    "iso:country":"CH",
    "sg:address":"Hubelmatt",
    "sg:city":"Luzern",
    "sg:orig_category":"Sportvereine Boccia",
    "sg:phone":"+41 41 310 08 40",
    "sg:postcode":"6005",
    "sg:province":"Luzern",
    "wof:name":"Luzerner Sportclub Boccia-club",
    "wof:placetype":"venue"
},
  "geometry": {"coordinates":[8.3035202026,47.0316963196],"type":"Point"}
}