{
  "type": "Feature",
  "properties": {
    "iso:country":"CH",
    "sg:address":"Untere Bruech 139 8706 Meilen. Postfach 881",
    "sg:city":"Meilen",
    "sg:orig_category":"Verwaltung der Rechtspflege, Gerichte",
    "sg:phone":"+41 19251191",
    "sg:postcode":"8706",
    "sg:province":"Z\u00fcrich",
    "wof:name":"Bezirksgericht Meilen",
    "wof:placetype":"venue"
},
  "geometry": {"coordinates":[8.6527242661,47.2677764893],"type":"Point"}
}