{
  "type": "Feature",
  "properties": {
    "iso:country":"CH",
    "sg:address":"Hofmatt 365 5064 Wittnau. Postfach 586",
    "sg:city":"Wittnau",
    "sg:orig_category":"Fernmeldedienste",
    "sg:postcode":"5064",
    "sg:province":"Aargau",
    "wof:name":"Fernsehgenossenschaft Wittnau",
    "wof:placetype":"venue"
},
  "geometry": {"coordinates":[7.9817700386,47.4832000732],"type":"Point"}
}