{
  "type": "Feature",
  "properties": {
    "iso:country":"CH",
    "sg:address":"Im Geissacker 43 8400 Winterthur. Postfach",
    "sg:city":"Winterthur",
    "sg:orig_category":"Detailhandel mit elektrischen Haushalts-,Radio U Fernsehger\u00e4ten sowie Musikinstrumenten",
    "sg:postcode":"8404",
    "sg:province":"Z\u00fcrich",
    "wof:name":"Handyman, Ukmar",
    "wof:placetype":"venue"
},
  "geometry": {"coordinates":[8.7552547455,47.5137557983],"type":"Point"}
}