{
  "type": "Feature",
  "properties": {
    "iso:country":"CH",
    "sg:address":"Unter Den Reben 277",
    "sg:city":"B\u00f6zen",
    "sg:orig_category":"Sonstiger Grosshandel",
    "sg:phone":"+41 62 876 20 80",
    "sg:postcode":"5076",
    "sg:province":"Aargau",
    "wof:name":"Bicik M.",
    "wof:placetype":"venue"
},
  "geometry": {"coordinates":[8.0856304169,47.4971656799],"type":"Point"}
}