{
  "type": "Feature",
  "properties": {
    "addr:full":"Au Moulin 10f Courchavon Jura 2922",
    "addr:housenumber":"10f",
    "addr:postcode":"2922",
    "addr:street":"Jura",
    "iso:country":"CH",
    "sg:address":"Au Moulin 10f",
    "sg:city":"Courchavon",
    "sg:orig_category":"Autogaragen",
    "sg:phone":"+41 32 466 19 53",
    "sg:postcode":"2922",
    "sg:province":"Jura",
    "wof:name":"Yvan Adam Garage Du Ch\u00e2teau",
    "wof:placetype":"venue"
},
  "geometry": {"coordinates":[7.057708,47.439312],"type":"Point"}
}