{
  "type": "Feature",
  "properties": {
    "iso:country":"CH",
    "sg:address":"7122",
    "sg:city":"Valendas",
    "sg:orig_category":"Forst\u00e4mter",
    "sg:phone":"+41 81 921 68 88",
    "sg:postcode":"7122",
    "sg:province":"Graubunden",
    "wof:name":"Revierforstamt",
    "wof:placetype":"venue"
},
  "geometry": {"coordinates":[9.2821350098,46.7875747681],"type":"Point"}
}