{
  "type": "Feature",
  "properties": {
    "iso:country":"CH",
    "sg:address":"Belpbergstrasse 4 3125 Toffen. Postfach",
    "sg:city":"Toffen",
    "sg:orig_category":"Softwareentwicklung U beratung",
    "sg:postcode":"3125",
    "sg:province":"Bern",
    "wof:name":"Tools4you Gmbh Dienstleistungen Im Bereich Informatik. Entwicklung U. Vertrieb Usw",
    "wof:placetype":"venue"
},
  "geometry": {"coordinates":[7.4977412224,46.8591995239],"type":"Point"}
}