{
  "type": "Feature",
  "properties": {
    "iso:country":"CH",
    "sg:address":"Hegifeldstrasse 10 8400 Winterthur. Postfach",
    "sg:city":"Stadel(winterthur)",
    "sg:orig_category":"Grosshandel mit Holz U Baustoffen Herstellung von sonstigen keramischen Erzeugnissen f\u00fcr technische ",
    "sg:phone":"+41 52 262 52 86",
    "sg:postcode":"8404",
    "sg:province":"Z\u00fcrich",
    "wof:name":"Portec Ag",
    "wof:placetype":"venue"
},
  "geometry": {"coordinates":[8.7621946335,47.5068817139],"type":"Point"}
}