{
  "type": "Feature",
  "properties": {
    "iso:country":"CH",
    "sg:address":"3996",
    "sg:city":"Binn",
    "sg:orig_category":"Gemeindeverwaltungen",
    "sg:phone":"+41 61 402 01 54",
    "sg:postcode":"3996",
    "sg:province":"Valais",
    "wof:name":"Gemeindeverwaltung Binningen",
    "wof:placetype":"venue"
},
  "geometry": {"coordinates":[7.5746068954,47.5419158936],"type":"Point"}
}