{
  "type": "Feature",
  "properties": {
    "iso:country":"CH",
    "sg:address":"Bodenmattweg 12 5082 Kaisten. Postfach",
    "sg:city":"Kaisten",
    "sg:orig_category":"Erwachsenenbildung U Unterricht",
    "sg:postcode":"5082",
    "sg:province":"Aargau",
    "wof:name":"Mosx Gmbh Dienstl. In Der Art Von Arbeitsunterst\u00fctzung, Beratung U. Schulung In Den Bereichen Unternehmungsf\u00fchrung Usw",
    "wof:placetype":"venue"
},
  "geometry": {"coordinates":[8.0418567657,47.5440711975],"type":"Point"}
}