{
  "type": "Feature",
  "properties": {
    "iso:country":"CH",
    "sg:address":"1925",
    "sg:city":"Finhaut",
    "sg:orig_category":"G\u00fcterbef\u00f6rderung im Strassenverkehr",
    "sg:phone":"+41 79 449 52 60",
    "sg:postcode":"1925",
    "sg:province":"Valais",
    "wof:name":"Philippe Maillard Transports",
    "wof:placetype":"venue"
},
  "geometry": {"coordinates":[6.9785847664,46.8852500916],"type":"Point"}
}