{
  "type": "Feature",
  "properties": {
    "iso:country":"CH",
    "sg:address":"Baselstrasse 67",
    "sg:city":"Laufen",
    "sg:orig_category":"Tankstellen",
    "sg:phone":"+41 61 761 44 09",
    "sg:postcode":"4242",
    "sg:province":"Basel-Landschaft",
    "wof:name":"Hedy Hof Tankstelle",
    "wof:placetype":"venue"
},
  "geometry": {"coordinates":[7.5056819916,47.4239349365],"type":"Point"}
}