{
  "type": "Feature",
  "properties": {
    "iso:country":"CH",
    "sg:address":"Sonneggstrasse 4 4600 Olten. Postfach",
    "sg:city":"Olten",
    "sg:orig_category":"Architektur U Ingenieurb\u00fcros",
    "sg:phone":"+41 62 296 23 45",
    "sg:postcode":"4601",
    "sg:province":"Solothurn",
    "wof:name":"Hanspeter Wullschleger Ingenieurb\u00fcro",
    "wof:placetype":"venue"
},
  "geometry": {"coordinates":[7.908299,47.344761],"type":"Point"}
}