{
  "type": "Feature",
  "properties": {
    "iso:country":"CH",
    "sg:address":"Matten 2",
    "sg:city":"Holziken",
    "sg:orig_category":"Gartenbau",
    "sg:phone":"+41 62 721 14 84",
    "sg:postcode":"5043",
    "sg:province":"Aargau",
    "wof:name":"Bruno Graber G\u00e4rtnerei",
    "wof:placetype":"venue"
},
  "geometry": {"coordinates":[8.0346422195,47.3251113892],"type":"Point"}
}