{
  "type": "Feature",
  "properties": {
    "iso:country":"CH",
    "sg:address":"Adlerweg 22",
    "sg:city":"Langenthal",
    "sg:orig_category":"Fachdetailhandel in Verkaufsr\u00e4umen",
    "sg:phone":"+41 79 647 61 76",
    "sg:postcode":"4900",
    "sg:province":"Bern",
    "wof:name":"Accessoires-blitz, Widmer Toni",
    "wof:placetype":"venue"
},
  "geometry": {"coordinates":[7.7821087837,47.222782135],"type":"Point"}
}