{
  "type": "Feature",
  "properties": {
    "iso:country":"CH",
    "sg:address":"Dennlerstrasse 41",
    "sg:city":"Z\u00fcrich",
    "sg:orig_category":"Bauingenieurb\u00fcros Heizung L\u00fcftung Klima Bauingenieurb\u00fcros Sanit\u00e4r",
    "sg:phone":"+41 71 314 06 30",
    "sg:postcode":"8047",
    "sg:province":"Z\u00fcrich",
    "wof:name":"Tramonti Geb\u00e4udetechnik Ag Ingenieurunternehmung",
    "wof:placetype":"venue"
},
  "geometry": {"coordinates":[9.314217,47.409187],"type":"Point"}
}