{
  "type": "Feature",
  "properties": {
    "iso:country":"CH",
    "sg:address":"Birkenstrasse 25",
    "sg:city":"Neuenhof",
    "sg:orig_category":"Fahrschulen, Flugschulen",
    "sg:phone":"+41 79 402 23 07",
    "sg:postcode":"5432",
    "sg:province":"Aargau",
    "wof:name":"Autofahrschule Lingg",
    "wof:placetype":"venue"
},
  "geometry": {"coordinates":[8.5010156631,47.4973869324],"type":"Point"}
}