{
  "type": "Feature",
  "properties": {
    "iso:country":"CH",
    "sg:address":"Ernetschwilerstrasse 12",
    "sg:city":"Gommiswald",
    "sg:orig_category":"Herstellung von Medikamenten U sonstigen pharmazeutischen Erzeugnissen",
    "sg:phone":"+41 55 280 34 30",
    "sg:postcode":"8737",
    "sg:province":"St. Gallen",
    "wof:name":"Kistler Ag Verbandwattefabrik",
    "wof:placetype":"venue"
},
  "geometry": {"coordinates":[9.020198822,47.235584259],"type":"Point"}
}