{
  "type": "Feature",
  "properties": {
    "iso:country":"CH",
    "sg:address":"Via Cuschas 22 7013 Domat/ems. Postfach",
    "sg:city":"Domat/ems",
    "sg:orig_category":"Herstellung von Tanks U Sammelbeh\u00e4ltern aus Metall Vermietung von sonstigen Landfahrzeugen",
    "sg:phone":"+41 81 633 52 30",
    "sg:postcode":"7013",
    "sg:province":"Graubunden",
    "wof:name":"Swisscontainer Ag Container; Vermietung, An- U. Verkauf",
    "wof:placetype":"venue"
},
  "geometry": {"coordinates":[9.4587726593,46.8320617676],"type":"Point"}
}