{
  "type": "Feature",
  "properties": {
    "iso:country":"CH",
    "sg:address":"8342",
    "sg:city":"Wernetshausen",
    "sg:orig_category":"Primarschulen",
    "sg:phone":"+41 56 282 30 80",
    "sg:postcode":"8342",
    "sg:province":"Z\u00fcrich",
    "wof:name":"Primarschule Unterboden",
    "wof:placetype":"venue"
},
  "geometry": {"coordinates":[8.2896528244,47.4883422852],"type":"Point"}
}