{
  "type": "Feature",
  "properties": {
    "iso:country":"CH",
    "sg:address":"Neubergstrasse 8",
    "sg:city":"Zurzach",
    "sg:orig_category":"Kaufm\u00e4nnische Berufsschulen",
    "sg:phone":"+41 56 249 00 08",
    "sg:postcode":"5330",
    "sg:province":"Aargau",
    "wof:name":"Kaufm\u00e4nnische Berufsschule Rektorat,herrn N.st\u00f6ckli",
    "wof:placetype":"venue"
},
  "geometry": {"coordinates":[8.2947530746,47.5843544006],"type":"Point"}
}