{
  "type": "Feature",
  "properties": {
    "iso:country":"CH",
    "sg:address":"M\u00fchle 62",
    "sg:city":"Krinau",
    "sg:classifiers":[
        {
            "category":"Communications",
            "subcategory":"Film & Video Production",
            "type":"Services"
        }
    ],
    "sg:phone":"+41 71 988 55 14",
    "sg:postcode":"9622",
    "sg:province":"St. Gallen",
    "sg:tags":[
        "videofilmherstellung",
        "u"
    ],
    "wof:name":"Bre-ton Gmbh",
    "wof:placetype":"venue"
},
  "geometry": {"coordinates":[9.0497646332,47.3174209595],"type":"Point"}
}