{
  "type": "Feature",
  "properties": {
    "iso:country":"CH",
    "sg:address":"Centralstrasse 56",
    "sg:city":"Grenchen",
    "sg:orig_category":"RESTAURANTS: TEA-ROOMS",
    "sg:phone":"+41 32 652 11 38",
    "sg:postcode":"2540",
    "sg:province":"Solothurn",
    "wof:name":"Sch\u00e4rz Marcel",
    "wof:placetype":"venue"
},
  "geometry": {"coordinates":[7.3955769539,47.1953735352],"type":"Point"}
}