{
  "type": "Feature",
  "properties": {
    "iso:country":"CH",
    "sg:address":"Bahnhofstrasse 47",
    "sg:city":"Horw",
    "sg:orig_category":"Sportvereine Velo Rad-& Motorfahrer-Bund SRB",
    "sg:phone":"+41 41 340 21 06",
    "sg:postcode":"6048",
    "sg:province":"Luzern",
    "wof:name":"Radsportclub Pilatus Horw",
    "wof:placetype":"venue"
},
  "geometry": {"coordinates":[8.3069839478,47.0178108215],"type":"Point"}
}