{
  "type": "Feature",
  "properties": {
    "iso:country":"CH",
    "sg:address":"Bahnhofstrasse 21",
    "sg:city":"B\u00fctschwil",
    "sg:orig_category":"Arztpraxen",
    "sg:phone":"+41 71 983 29 33",
    "sg:postcode":"9606",
    "sg:province":"St. Gallen",
    "wof:name":"Dr.med.peter Graf Arzt F.allgemeine Medizin Fmh",
    "wof:placetype":"venue"
},
  "geometry": {"coordinates":[9.074755,47.360451],"type":"Point"}
}