{
  "type": "Feature",
  "properties": {
    "iso:country":"CH",
    "sg:address":"Turmgasse 2 9320 Arbon. Postfach",
    "sg:city":"Arbon",
    "sg:orig_category":"Fachdetailhandel mit pharmazeutischen Produkten",
    "sg:postcode":"9320",
    "sg:province":"Thurgau",
    "wof:name":"Adler-apotheke H. Hollihn",
    "wof:placetype":"venue"
},
  "geometry": {"coordinates":[9.4355478287,47.5151367188],"type":"Point"}
}