{
  "type": "Feature",
  "properties": {
    "iso:country":"CH",
    "sg:address":"Unterdorfstrasse 48",
    "sg:city":"Widnau",
    "sg:orig_category":"Grosshandel mit Textilien Stickerei",
    "sg:phone":"+41 71 744 23 32",
    "sg:postcode":"9443",
    "sg:province":"St. Gallen",
    "wof:name":"Neuburger & Co Ag",
    "wof:placetype":"venue"
},
  "geometry": {"coordinates":[9.6320199966,47.4297142029],"type":"Point"}
}