{
  "type": "Feature",
  "properties": {
    "iso:country":"CH",
    "sg:address":"Webergasse 49",
    "sg:city":"Schaffhausen",
    "sg:orig_category":"Unclassifiable Establishments",
    "sg:phone":"+41 52 624 07 87",
    "sg:postcode":"8200",
    "sg:province":"Schaffhausen",
    "wof:name":"Relax Und Gesundheitsoase Body & Soul Ghirotti Sylvia",
    "wof:placetype":"venue"
},
  "geometry": {"coordinates":[8.6345643997,47.6983680725],"type":"Point"}
}