{
  "type": "Feature",
  "properties": {
    "iso:country":"CH",
    "sg:address":"Oberer Graben 22",
    "sg:city":"St.gallen",
    "sg:orig_category":"Unclassifiable Establishments",
    "sg:postcode":"9000",
    "sg:province":"St. Gallen",
    "wof:name":"Hrd Holding Ag",
    "wof:placetype":"venue"
},
  "geometry": {"coordinates":[9.3740577698,47.4232521057],"type":"Point"}
}