{
  "type": "Feature",
  "properties": {
    "iso:country":"CH",
    "sg:address":"Seestrasse 20",
    "sg:city":"Uster",
    "sg:orig_category":"Detailhandel mit Radio U Fernsehger\u00e4ten Detailhandel mit elektrischen Haushalts-,Radio U Fernsehger\u00e4",
    "sg:phone":"+41 19416362",
    "sg:postcode":"8610",
    "sg:province":"Z\u00fcrich",
    "wof:name":"Petrillo Carmine",
    "wof:placetype":"venue"
},
  "geometry": {"coordinates":[8.7123937607,47.3465385437],"type":"Point"}
}