{
  "type": "Feature",
  "properties": {
    "iso:country":"CH",
    "sg:address":"Fin Route De La 10",
    "sg:city":"Collombey",
    "sg:orig_category":"Stukkateurgewerbe, Gipserei U Verputzerei",
    "sg:phone":"+41 24 472 75 09",
    "sg:postcode":"1868",
    "sg:province":"Valais",
    "wof:name":"Romano Peinture Antonio",
    "wof:placetype":"venue"
},
  "geometry": {"coordinates":[6.945827961,46.2704734802],"type":"Point"}
}