{
  "type": "Feature",
  "properties": {
    "iso:country":"CH",
    "sg:address":"Bergstrasse 229",
    "sg:city":"D\u00fcbendorf",
    "sg:orig_category":"Wirtschaftspr\u00fcfung, Steuerberatung U Treuhand",
    "sg:phone":"+41 18200612",
    "sg:postcode":"8600",
    "sg:province":"Z\u00fcrich",
    "wof:name":"Grossenbacher Treuhand",
    "wof:placetype":"venue"
},
  "geometry": {"coordinates":[8.6262979507,47.4024391174],"type":"Point"}
}