{
  "type": "Feature",
  "properties": {
    "addr:full":"Limmattalstrasse 142 8049 Z\u00fcrich. Postfach 1 Z\u00fcrich Z\u00fcrich 8049",
    "addr:housenumber":"142;1",
    "addr:postcode":"8049 zuerich.;8049",
    "addr:street":"Limmattalstrasse;Postfach",
    "iso:country":"CH",
    "sg:address":"Limmattalstrasse 142 8049 Z\u00fcrich. Postfach 1",
    "sg:city":"Z\u00fcrich",
    "sg:orig_category":"Bauschreinerei Innenausbau",
    "sg:phone":"+41 13414978",
    "sg:postcode":"8049",
    "sg:province":"Z\u00fcrich",
    "wof:name":"J\u00fcrg Kropf Zimmerei Schreinerei",
    "wof:placetype":"venue"
},
  "geometry": {"coordinates":[8.503083,47.400677],"type":"Point"}
}