{
  "type": "Feature",
  "properties": {
    "iso:country":"CH",
    "sg:address":"Seeblickstrasse 25",
    "sg:city":"Z\u00fcrich",
    "sg:orig_category":"Reiseb\u00fcros U Reiseveranstalter",
    "sg:phone":"+41 14828959",
    "sg:postcode":"8038",
    "sg:province":"Z\u00fcrich",
    "wof:name":"Fessel Charles Hospitality Consulting Hotellerie, Gastronomie, Freizeit Usw; Beratungsdienstl.",
    "wof:placetype":"venue"
},
  "geometry": {"coordinates":[8.5360813141,47.3363571167],"type":"Point"}
}