{
  "type": "Feature",
  "properties": {
    "iso:country":"CH",
    "sg:address":"Churerstrasse 3 8852 Altendorf. Postfach",
    "sg:city":"Altendorf",
    "sg:orig_category":"Detailhandel mit Brot, Back U S\u00fcsswaren",
    "sg:phone":"+41 55 442 11 38",
    "sg:postcode":"8852",
    "sg:province":"Schwyz",
    "wof:name":"Knobel-henseler Alois",
    "wof:placetype":"venue"
},
  "geometry": {"coordinates":[8.831903,47.192043],"type":"Point"}
}