{
  "type": "Feature",
  "properties": {
    "iso:country":"CH",
    "sg:address":"Seminarstrasse 71",
    "sg:city":"Wettingen",
    "sg:classifiers":[
        {
            "category":"Restaurant",
            "type":"Food & Drink"
        }
    ],
    "sg:phone":"+41 56 426 72 62",
    "sg:postcode":"5430",
    "sg:province":"Aargau",
    "wof:name":"Restaurant Stadion",
    "wof:placetype":"venue"
},
  "geometry": {"coordinates":[8.3135824203,47.4633598328],"type":"Point"}
}