{
  "type": "Feature",
  "properties": {
    "iso:country":"CH",
    "sg:address":"Schaffhauserstrasse 34",
    "sg:city":"Z\u00fcrich",
    "sg:orig_category":"Non-Classified Establishments",
    "sg:phone":"+41 62 758 56 66",
    "sg:postcode":"8006",
    "sg:province":"Z\u00fcrich",
    "wof:name":"The Navigators Ag L\u00f6sungen, Konzepte F\u00fcr Das Mobile Internet",
    "wof:placetype":"venue"
},
  "geometry": {"coordinates":[7.9600768089,47.2318115234],"type":"Point"}
}