{
  "type": "Feature",
  "properties": {
    "iso:country":"CH",
    "sg:address":"Rosenbergstrasse 54 8304 Wallisellen. Postfach",
    "sg:city":"Wallisellen",
    "sg:orig_category":"Non-Classified Establishments",
    "sg:postcode":"8304",
    "sg:province":"Z\u00fcrich",
    "wof:name":"Anka Ag",
    "wof:placetype":"venue"
},
  "geometry": {"coordinates":[8.5980615616,47.4122505188],"type":"Point"}
}