{
  "type": "Feature",
  "properties": {
    "iso:country":"CH",
    "sg:address":"1717 St-ours. Postfach",
    "sg:city":"St-ours",
    "sg:orig_category":"Sportvereine Turnen",
    "sg:phone":"+41 27 952 10 60",
    "sg:postcode":"1717",
    "sg:province":"Fribourg",
    "wof:name":"Turnverein Stv Stalden",
    "wof:placetype":"venue"
},
  "geometry": {"coordinates":[7.8920350075,46.2011413574],"type":"Point"}
}