{
  "type": "Feature",
  "properties": {
    "addr:full":"Rue De Fer 3 2800 Del\u00e9mont Case Postale Delsberg Jura 2800",
    "addr:housenumber":"3",
    "addr:postcode":"2800;2800",
    "addr:street":"Rue De Fer;Jura",
    "iso:country":"CH",
    "sg:address":"Rue De Fer 3 2800 Del\u00e9mont Case Postale",
    "sg:city":"Delsberg",
    "sg:orig_category":"Architektur U Ingenieurb\u00fcros Architekturb\u00fcros",
    "sg:phone":"+41 32 422 90 55",
    "sg:postcode":"2800",
    "sg:province":"Jura",
    "wof:name":"Architrave Sa",
    "wof:placetype":"venue"
},
  "geometry": {"coordinates":[7.343162,47.365108],"type":"Point"}
}