{
  "type": "Feature",
  "properties": {
    "iso:country":"CH",
    "sg:address":"Sarmenstorferstrasse 3",
    "sg:city":"Fahrwangen",
    "sg:orig_category":"Sonstiger Fachdetailhandel in Verkaufsr\u00e4umen Tea-Rooms and Caf\u00e9s",
    "sg:phone":"+41 56 676 63 73",
    "sg:postcode":"5615",
    "sg:province":"Aargau",
    "wof:name":"Meili Huus",
    "wof:placetype":"venue"
},
  "geometry": {"coordinates":[8.241558075,47.2956695557],"type":"Point"}
}