{
  "type": "Feature",
  "properties": {
    "iso:country":"CH",
    "sg:address":"Schweizergasse 35",
    "sg:city":"Basel",
    "sg:orig_category":"Betrieb U technische Hilfsdienste des Kultur U Unterhaltungswesens Sonstige Hilfsdienste des Kultur ",
    "sg:phone":"+41 41 930 00 06",
    "sg:postcode":"4054",
    "sg:province":"Basel-Stadt",
    "wof:name":"Rec & Play Solution Willimann",
    "wof:placetype":"venue"
},
  "geometry": {"coordinates":[8.150257,47.223736],"type":"Point"}
}