{
  "type": "Feature",
  "properties": {
    "iso:country":"CH",
    "sg:address":"K\u00e4serei 3156 Riffenmatt. Postfach",
    "sg:city":"Riffenmatt",
    "sg:orig_category":"Verwertung von Milch",
    "sg:postcode":"3156",
    "sg:province":"Bern",
    "wof:name":"K\u00e4serei Hostettler Riffenmatt",
    "wof:placetype":"venue"
},
  "geometry": {"coordinates":[7.3531298637,46.7652931213],"type":"Point"}
}