{
  "type": "Feature",
  "properties": {
    "iso:country":"CH",
    "sg:address":"Tannlihag 1",
    "sg:city":"Seon",
    "sg:classifiers":[
        {
            "category":"Government",
            "subcategory":"Fire Station",
            "type":"Public Place"
        }
    ],
    "sg:phone":"+41 62 769 70 70",
    "sg:postcode":"5703",
    "sg:province":"Aargau",
    "sg:tags":[
        "development",
        "hardware",
        "soft"
    ],
    "wof:name":"Insoft Ag",
    "wof:placetype":"venue"
},
  "geometry": {"coordinates":[8.1658620834,47.3648872375],"type":"Point"}
}