{
  "type": "Feature",
  "properties": {
    "iso:country":"CH",
    "sg:address":"Muristrasse 93",
    "sg:city":"Bern",
    "sg:orig_category":"Detailhandel mit Bekleidung Detailhandel mit Uhren U Schmuck",
    "sg:phone":"+41 31 311 24 54",
    "sg:postcode":"3006",
    "sg:province":"Bern",
    "wof:name":"Zebra Mode & Schmuck F.tschanz & M.eichenberger",
    "wof:placetype":"venue"
},
  "geometry": {"coordinates":[7.471003,46.939365],"type":"Point"}
}