{
  "type": "Feature",
  "properties": {
    "iso:country":"CH",
    "sg:address":"Fontnas",
    "sg:city":"Azmoos",
    "sg:orig_category":"Interessenvertretungen",
    "sg:postcode":"9478",
    "sg:province":"St. Gallen",
    "wof:name":"Stiftung Burgruine Wartau",
    "wof:placetype":"venue"
},
  "geometry": {"coordinates":[9.4766893387,47.0802955627],"type":"Point"}
}