{
  "type": "Feature",
  "properties": {
    "addr:full":"Kurvenstrasse 15 D\u00fcbendorf Z\u00fcrich 8600",
    "addr:housenumber":"15",
    "addr:postcode":"8600",
    "addr:street":"Kurvenstrasse;Zuerich",
    "iso:country":"CH",
    "sg:address":"Kurvenstrasse 15",
    "sg:city":"D\u00fcbendorf",
    "sg:orig_category":"Detailhandel mit Computern U Software Elektroinstallation",
    "sg:phone":"+41 18202254",
    "sg:postcode":"8600",
    "sg:province":"Z\u00fcrich",
    "wof:name":"Internet24 Gmbh Online Publisher",
    "wof:placetype":"venue"
},
  "geometry": {"coordinates":[8.614414,47.397137],"type":"Point"}
}