{
  "type": "Feature",
  "properties": {
    "iso:country":"CH",
    "sg:address":"Wolfwilerstrasse 5",
    "sg:city":"Fulenbach",
    "sg:orig_category":"Detailhandel mit Getr\u00e4nken G\u00fcterbef\u00f6rderung im Strassenverkehr",
    "sg:phone":"+41 79 415 14 15",
    "sg:postcode":"4629",
    "sg:province":"Solothurn",
    "wof:name":"Charles Leclerc",
    "wof:placetype":"venue"
},
  "geometry": {"coordinates":[7.828001976,47.2735671997],"type":"Point"}
}