{
  "type": "Feature",
  "properties": {
    "iso:country":"CH",
    "sg:address":"Simmentalstrasse 40",
    "sg:city":"Spiez",
    "sg:orig_category":"Detailhandel mit Sportartikeln",
    "sg:phone":"+41 33 654 79 35",
    "sg:postcode":"3700",
    "sg:province":"Bern",
    "wof:name":"Martin Schranz Billard-& Dart-sport",
    "wof:placetype":"venue"
},
  "geometry": {"coordinates":[7.6673378944,46.6858482361],"type":"Point"}
}