{
  "type": "Feature",
  "properties": {
    "addr:full":"Buckhauserstrasse 24 Zuerich Z\u00fcrich 8048",
    "addr:housenumber":"24",
    "addr:postcode":"8048",
    "addr:street":"Buckhauserstrasse",
    "iso:country":"CH",
    "sg:address":"Buckhauserstrasse 24",
    "sg:city":"Zuerich",
    "sg:orig_category":"Wirtschaft U Handel, Arbeit, Allgemeines zum Thema Arbeit",
    "sg:phone":"+41 14057272",
    "sg:postcode":"8048",
    "sg:province":"Z\u00fcrich",
    "wof:name":"Ifb",
    "wof:placetype":"venue"
},
  "geometry": {"coordinates":[8.492726,47.384586],"type":"Point"}
}