{
  "type": "Feature",
  "properties": {
    "addr:full":"Sonneggweg 10 Stettlen Bern 3066",
    "addr:housenumber":"10",
    "addr:postcode":"3066",
    "addr:street":"Sonneggweg;Bern",
    "iso:country":"CH",
    "sg:address":"Sonneggweg 10",
    "sg:city":"Stettlen",
    "sg:classifiers":[
        {
            "category":"Shopping",
            "subcategory":"Computers & Home Electronics",
            "type":"Retail Goods"
        }
    ],
    "sg:phone":"+41 31 938 12 33",
    "sg:postcode":"3066",
    "sg:province":"Bern",
    "sg:tags":[
        "client-server",
        "software"
    ],
    "wof:name":"Asp Informatik Ag",
    "wof:placetype":"venue"
},
  "geometry": {"coordinates":[7.532153,46.960266],"type":"Point"}
}