{
  "type": "Feature",
  "properties": {
    "iso:country":"CH",
    "sg:address":"Vorderbergstrasse 26 6318 Walchwil. Postfach 89",
    "sg:city":"Walchwil",
    "sg:orig_category":"Gartenbau",
    "sg:phone":"+41 41 758 17 20",
    "sg:postcode":"6318",
    "sg:province":"Zug",
    "wof:name":"Roth Gartenbau Ag",
    "wof:placetype":"venue"
},
  "geometry": {"coordinates":[8.5126581192,47.1074447632],"type":"Point"}
}