{
  "type": "Feature",
  "properties": {
    "iso:country":"CH",
    "sg:address":"L\u00e4nggasse 32",
    "sg:city":"Zollikofen",
    "sg:classifiers":[
        {
            "category":"Professional",
            "subcategory":"Engineering",
            "type":"Services"
        }
    ],
    "sg:phone":"+41 31 911 20 80",
    "sg:postcode":"3052",
    "sg:province":"Bern",
    "sg:tags":[
        "crane"
    ],
    "wof:name":"Erwin Wyss Ag",
    "wof:placetype":"venue"
},
  "geometry": {"coordinates":[7.465545,46.992622],"type":"Point"}
}