{
  "type": "Feature",
  "properties": {
    "iso:country":"CH",
    "sg:address":"Hohlegasse 34a 4102 Binningen. Postfach",
    "sg:city":"Binningen",
    "sg:orig_category":"Rechtsberatung",
    "sg:phone":"+41 61 421 27 47",
    "sg:postcode":"4102",
    "sg:province":"Basel-Landschaft",
    "wof:name":"Smg Legal Consulting Gmbh Beratung U. Dienstleistungen, Speziell F\u00fcr Nonprofit-organisationen Im Bereich Der Justizgesetzgebung, Justizverwaltung U. Der Richterausbildung",
    "wof:placetype":"venue"
},
  "geometry": {"coordinates":[7.5704760551,47.5389251709],"type":"Point"}
}