{
  "type": "Feature",
  "properties": {
    "iso:country":"CH",
    "sg:address":"St.galler Strasse 3",
    "sg:city":"Sitterdorf",
    "sg:orig_category":"Verlegen von Fussboden",
    "sg:phone":"+41 71 422 34 64",
    "sg:postcode":"8589",
    "sg:province":"Thurgau",
    "wof:name":"Lengwiler Unterlagsb\u00f6den Ag",
    "wof:placetype":"venue"
},
  "geometry": {"coordinates":[9.2522563934,47.5062789917],"type":"Point"}
}