{
  "type": "Feature",
  "properties": {
    "iso:country":"CH",
    "sg:address":"Maiholzstrasse 26",
    "sg:city":"Frauenfeld",
    "sg:orig_category":"Non-Classified Establishments",
    "sg:postcode":"8500",
    "sg:province":"Thurgau",
    "wof:name":"Sansotech Frei",
    "wof:placetype":"venue"
},
  "geometry": {"coordinates":[8.8862257004,47.5593338013],"type":"Point"}
}