{
  "type": "Feature",
  "properties": {
    "iso:country":"CH",
    "sg:address":"Stettemerstrasse 50 8200 Schaffhausen. Postfach",
    "sg:city":"Schaffhausen",
    "sg:orig_category":"Erbringung von Dienstleistungen f\u00fcr Unternehmen Inkassob\u00fcros",
    "sg:phone":"+41 16876820",
    "sg:postcode":"8205",
    "sg:province":"Schaffhausen",
    "wof:name":"Is Inkasso Service Gmbh Inkasso Fremder Forderungen",
    "wof:placetype":"venue"
},
  "geometry": {"coordinates":[8.7341480255,47.1973953247],"type":"Point"}
}