{
  "type": "Feature",
  "properties": {
    "iso:country":"CH",
    "sg:city":"Basel",
    "sg:classifiers":[
        {
            "category":"Utilities",
            "subcategory":"Cable",
            "type":"Services"
        }
    ],
    "sg:postcode":"4000",
    "sg:province":"Basel-Stadt",
    "sg:tags":[
        "tv",
        "medien",
        "u",
        "radio"
    ],
    "wof:name":"Zumstein - Zumi.ch",
    "wof:placetype":"venue"
},
  "geometry": {"coordinates":[7.58053,47.559662],"type":"Point"}
}