{
  "type": "Feature",
  "properties": {
    "addr:full":"Heiligholzstrasse 59 M\u00fcnchenstein Basel-Landschaft 4142",
    "addr:housenumber":"59",
    "addr:postcode":"4142",
    "addr:street":"Heiligholzstrasse",
    "iso:country":"CH",
    "sg:address":"Heiligholzstrasse 59",
    "sg:city":"M\u00fcnchenstein",
    "sg:orig_category":"Bauschreinerei Herstellung von Konstruktionsteilen, Fertigbauteilen U Ausbauelementen aus Holz",
    "sg:phone":"+41 61 411 60 80",
    "sg:postcode":"4142",
    "sg:province":"Basel-Landschaft",
    "wof:name":"Schreinerei Weber",
    "wof:placetype":"venue"
},
  "geometry": {"coordinates":[7.603646,47.515945],"type":"Point"}
}