{
  "type": "Feature",
  "properties": {
    "iso:country":"CH",
    "sg:address":"Sunnehof-center Sternenweg 1",
    "sg:city":"Oensingen",
    "sg:orig_category":"Fachdetailhandel in Verkaufsr\u00e4umen",
    "sg:phone":"+41 17615045",
    "sg:postcode":"4702",
    "sg:province":"Solothurn",
    "wof:name":"Spiess Frau Maya, Bambi-tierbedarf",
    "wof:placetype":"venue"
},
  "geometry": {"coordinates":[8.4472856522,47.2764587402],"type":"Point"}
}