{
  "type": "Feature",
  "properties": {
    "iso:country":"CH",
    "sg:address":"Bahnhofstrasse 6",
    "sg:city":"St.gallen",
    "sg:orig_category":"Betrieb U technische Hilfsdienste des Kultur U Unterhaltungswesens",
    "sg:phone":"+41 71 223 41 01",
    "sg:postcode":"9000",
    "sg:province":"St. Gallen",
    "wof:name":"Open Air St. Gallen",
    "wof:placetype":"venue"
},
  "geometry": {"coordinates":[9.373101,47.425865],"type":"Point"}
}