{
  "type": "Feature",
  "properties": {
    "iso:country":"CH",
    "sg:address":"5053",
    "sg:city":"Staffelbach",
    "sg:orig_category":"Primarschulen",
    "sg:postcode":"5053",
    "sg:province":"Aargau",
    "wof:name":"Primarschule",
    "wof:placetype":"venue"
},
  "geometry": {"coordinates":[8.0423364639,47.2841835022],"type":"Point"}
}