{
  "type": "Feature",
  "properties": {
    "iso:country":"CH",
    "sg:address":"Noflerstrasse 77",
    "sg:city":"Ruggell",
    "sg:orig_category":"Handelsvermittlung U Grosshandel Herstellung von sonstigen Maschinen f\u00fcr unspezifische Verwendung",
    "sg:phone":"+41 34 445 10 35",
    "sg:postcode":"9491",
    "wof:name":"Zumstein & Cie",
    "wof:placetype":"venue"
},
  "geometry": {"coordinates":[7.5823397636,47.0854721069],"type":"Point"}
}