{
  "type": "Feature",
  "properties": {
    "iso:country":"CH",
    "sg:address":"Schl\u00fcssel 336",
    "sg:city":"Brienzwiler",
    "sg:orig_category":"Grosshandel mit Textilien",
    "sg:postcode":"3856",
    "sg:province":"Bern",
    "wof:name":"Swiss Bangla Textil Vertriebs Gmbh",
    "wof:placetype":"venue"
},
  "geometry": {"coordinates":[8.1039848328,46.7525100708],"type":"Point"}
}