{
  "type": "Feature",
  "properties": {
    "iso:country":"CH",
    "sg:address":"1535",
    "sg:city":"Combremont-grand",
    "sg:orig_category":"Zimmerei, Dachdeckerei, Bauspenglerei U Abdichtung",
    "sg:postcode":"1535",
    "sg:province":"Vaud",
    "wof:name":"Pierre-andr\u00e9 Richard",
    "wof:placetype":"venue"
},
  "geometry": {"coordinates":[7.0369849205,47.0522041321],"type":"Point"}
}