{
  "type": "Feature",
  "properties": {
    "iso:country":"CH",
    "sg:address":"6573",
    "sg:city":"Magadino",
    "sg:orig_category":"Unclassifiable Establishments",
    "sg:phone":"+41 91 795 10 76",
    "sg:postcode":"6573",
    "sg:province":"Ticino",
    "wof:name":"Ristorante S.gottardo",
    "wof:placetype":"venue"
},
  "geometry": {"coordinates":[8.8637800217,46.145778656],"type":"Point"}
}