{
  "type": "Feature",
  "properties": {
    "iso:country":"CH",
    "sg:address":"Via Panoramica",
    "sg:city":"Tenero",
    "sg:orig_category":"Herstellung von Elektrizit\u00e4tsverteilungs U schalteinrichtungen",
    "sg:phone":"+41 91 745 16 58",
    "sg:postcode":"6598",
    "sg:province":"Ticino",
    "wof:name":"R. Lenhart - Regeltechnik",
    "wof:placetype":"venue"
},
  "geometry": {"coordinates":[8.8498601913,46.180896759],"type":"Point"}
}