{
  "type": "Feature",
  "properties": {
    "iso:country":"CH",
    "sg:address":"Pilatusstrasse 3",
    "sg:city":"Luzern",
    "sg:orig_category":"Detailhandel mit Bekleidung Detailhandel mit Damenbekleidung",
    "sg:phone":"+41 41 210 70 50",
    "sg:postcode":"6003",
    "sg:province":"Luzern",
    "wof:name":"Kofler Ag",
    "wof:placetype":"venue"
},
  "geometry": {"coordinates":[8.3086452484,47.0498085022],"type":"Point"}
}