{
  "type": "Feature",
  "properties": {
    "iso:country":"CH",
    "sg:address":"Beim Restaurant Rossberghof",
    "sg:city":"Wilchingen",
    "sg:orig_category":"Unclassifiable Establishments",
    "sg:postcode":"8217",
    "sg:province":"Schaffhausen",
    "wof:name":"Obrist-tanner Ag",
    "wof:placetype":"venue"
},
  "geometry": {"coordinates":[8.4684848785,47.6675109863],"type":"Point"}
}