{
  "type": "Feature",
  "properties": {
    "iso:country":"CH",
    "sg:address":"Blegistrasse 13 6340 Baar. Postfach",
    "sg:city":"Baar",
    "sg:orig_category":"Pensionskassen",
    "sg:phone":"+41 41 760 25 45",
    "sg:postcode":"6340",
    "sg:province":"Zug",
    "wof:name":"Pensionskasse Der Sapt Ag",
    "wof:placetype":"venue"
},
  "geometry": {"coordinates":[8.5692443848,47.2156867981],"type":"Point"}
}