{
  "type": "Feature",
  "properties": {
    "iso:country":"CH",
    "sg:address":"Eggweg 11",
    "sg:city":"Eglisau",
    "sg:orig_category":"Jugendorganisationen",
    "sg:phone":"+41 19100906",
    "sg:postcode":"8193",
    "sg:province":"Z\u00fcrich",
    "wof:name":"R\u00f6misch-katholisches Pfarramt",
    "wof:placetype":"venue"
},
  "geometry": {"coordinates":[8.5812625885,47.3168563843],"type":"Point"}
}