{
  "type": "Feature",
  "properties": {
    "iso:country":"CH",
    "sg:address":"Angensteinerstrasse 6",
    "sg:city":"Reinach",
    "sg:classifiers":[
        {
            "category":"Professional",
            "subcategory":"Accounting & Tax Preparation",
            "type":"Services"
        }
    ],
    "sg:phone":"+41 61 717 94 84",
    "sg:postcode":"4153",
    "sg:province":"Basel-Landschaft",
    "sg:tags":[
        "financial",
        "software"
    ],
    "wof:name":"Openline Ag",
    "wof:placetype":"venue"
},
  "geometry": {"coordinates":[7.5929059982,47.4923210144],"type":"Point"}
}