{
  "type": "Feature",
  "properties": {
    "iso:country":"CH",
    "sg:address":"Avenue De Morges 44",
    "sg:city":"Lausanne",
    "sg:classifiers":[
        {
            "category":"Restaurant",
            "type":"Food & Drink"
        }
    ],
    "sg:phone":"+41 21 944 51 22",
    "sg:postcode":"1004",
    "sg:province":"Vaud",
    "wof:name":"Buvette L'oubliette",
    "wof:placetype":"venue"
},
  "geometry": {"coordinates":[6.8550820351,46.4529418945],"type":"Point"}
}