{
  "type": "Feature",
  "properties": {
    "iso:country":"CH",
    "sg:address":"Route Du Mandement 15",
    "sg:city":"Meyrin",
    "sg:orig_category":"Herstellung von sonstigen landwirtschaftlichen Maschinen Stahl U Leichtmetallbau",
    "sg:postcode":"1217",
    "sg:province":"Gen\u00e8ve",
    "wof:name":"Kunz Georges Sa",
    "wof:placetype":"venue"
},
  "geometry": {"coordinates":[6.0623941422,46.2300071716],"type":"Point"}
}