{
  "type": "Feature",
  "properties": {
    "iso:country":"CH",
    "sg:address":"Chamerstrasse 14 6300 Zug. Postfach",
    "sg:city":"Zug",
    "sg:orig_category":"Sonstige mit der Informatik verbundene T\u00e4tigkeiten",
    "sg:phone":"+41 71 385 52 85",
    "sg:postcode":"6300",
    "sg:province":"Zug",
    "wof:name":"Brumut, Roland Bruhin",
    "wof:placetype":"venue"
},
  "geometry": {"coordinates":[9.2447805405,47.4174118042],"type":"Point"}
}