{
  "type": "Feature",
  "properties": {
    "iso:country":"CH",
    "sg:address":"2605 Sonceboz-sombeval Case Postale",
    "sg:city":"Sonceboz-sombeval",
    "sg:orig_category":"Detailhandel mit Schuhen U Lederwaren",
    "sg:phone":"+41 32 489 32 22",
    "sg:postcode":"2605",
    "sg:province":"Bern",
    "wof:name":"Hirschy Francis Et Fernand",
    "wof:placetype":"venue"
},
  "geometry": {"coordinates":[7.1722898483,47.1979064941],"type":"Point"}
}