{
  "type": "Feature",
  "properties": {
    "iso:country":"CH",
    "sg:address":"Via Motta 2",
    "sg:city":"Mendrisio",
    "sg:orig_category":"Medizinische Labors Technische, physikalische U chemische Untersuchung",
    "sg:phone":"+41 91 641 63 63",
    "sg:postcode":"6850",
    "sg:province":"Ticino",
    "wof:name":"Las Laboratorio Analisi Speciali Chimico-cliniche Sa",
    "wof:placetype":"venue"
},
  "geometry": {"coordinates":[8.9797563553,45.8682289124],"type":"Point"}
}