{
  "type": "Feature",
  "properties": {
    "iso:country":"CH",
    "sg:address":"Sangernweg 3",
    "sg:city":"Boll",
    "sg:orig_category":"Herstellung von keramischen Haushaltswaren U Ziergegenst\u00e4nden",
    "sg:phone":"+41 71 622 42 90",
    "sg:postcode":"3067",
    "sg:province":"Bern",
    "wof:name":"Ernst Ringli T\u00f6pferei",
    "wof:placetype":"venue"
},
  "geometry": {"coordinates":[9.1381845474,47.5666694641],"type":"Point"}
}