{
  "type": "Feature",
  "properties": {
    "iso:country":"CH",
    "sg:address":"Weinfelderstrasse 38",
    "sg:city":"Amriswil",
    "sg:orig_category":"Handel mit Motorr\u00e4dern, Teilen U Zubeh\u00f6r Instandhaltung U Reparatur von Motorr\u00e4dern",
    "sg:postcode":"8580",
    "sg:province":"Thurgau",
    "wof:name":"Keller R.",
    "wof:placetype":"venue"
},
  "geometry": {"coordinates":[8.8021802902,46.1322402954],"type":"Point"}
}