{
  "type": "Feature",
  "properties": {
    "iso:country":"CH",
    "sg:address":"Fola Via 13 6963 Pregassona. Postfach",
    "sg:city":"Pregassona",
    "sg:orig_category":"Herstellung von Bereifungen",
    "sg:postcode":"6963",
    "sg:province":"Ticino",
    "wof:name":"Centro Servizio Pneumatici Di Derungs Ren\u00e9",
    "wof:placetype":"venue"
},
  "geometry": {"coordinates":[8.9726028442,45.8901138306],"type":"Point"}
}