{
  "type": "Feature",
  "properties": {
    "iso:country":"CH",
    "sg:address":"Av. De La Gare 42",
    "sg:city":"Del\u00e9mont",
    "sg:orig_category":"RESTAURANTS: TEA-ROOMS",
    "sg:postcode":"2800",
    "sg:province":"Jura",
    "wof:name":"Chapuis-koller Myriame Et Michel",
    "wof:placetype":"venue"
},
  "geometry": {"coordinates":[7.3492779732,47.3639602661],"type":"Point"}
}