{
  "type": "Feature",
  "properties": {
    "iso:country":"CH",
    "sg:address":"Dorf 21",
    "sg:city":"Herrliberg",
    "sg:orig_category":"Detailhandel mit Schreib U Papeteriewaren",
    "sg:phone":"+41 19152566",
    "sg:postcode":"8704",
    "sg:province":"Z\u00fcrich",
    "wof:name":"Papeterie Im Dorf Gmbh Bastel Spiel-& B\u00fcroartikel",
    "wof:placetype":"venue"
},
  "geometry": {"coordinates":[8.6161842346,47.2863388062],"type":"Point"}
}