{
  "type": "Feature",
  "properties": {
    "iso:country":"CH",
    "sg:address":"Schlattingen 8254 Basadingen. Postfach",
    "sg:city":"Schlattingen",
    "sg:orig_category":"Fachdetailhandel in Verkaufsr\u00e4umen",
    "sg:phone":"+41 52 657 14 67",
    "sg:postcode":"8255",
    "sg:province":"Thurgau",
    "wof:name":"Gamp E.",
    "wof:placetype":"venue"
},
  "geometry": {"coordinates":[8.7509899139,47.6710968018],"type":"Point"}
}