{
  "type": "Feature",
  "properties": {
    "iso:country":"CH",
    "sg:address":"Beustweg 8",
    "sg:city":"Z\u00fcrich",
    "sg:orig_category":"Arztpraxen",
    "sg:phone":"+41 12614844",
    "sg:postcode":"8032",
    "sg:province":"Z\u00fcrich",
    "wof:name":"Dr. Med. Elisabeth Huber Aerztin F\u00fcr Allg. Medizin Fmh Und H\u00f6m\u00f6opathie",
    "wof:placetype":"venue"
},
  "geometry": {"coordinates":[8.553311,47.367584],"type":"Point"}
}