{
  "type": "Feature",
  "properties": {
    "addr:full":"Bundesrain 8 3005 Bern. Postfach Bern Bern 3001",
    "addr:housenumber":"8",
    "addr:postcode":"3005;postfach;3001",
    "addr:street":"Bundesrain",
    "iso:country":"CH",
    "sg:address":"Bundesrain 8 3005 Bern. Postfach",
    "sg:city":"Bern",
    "sg:orig_category":"Architekturb\u00fcros",
    "sg:phone":"+41 31 312 06 10",
    "sg:postcode":"3001",
    "sg:province":"Bern",
    "wof:name":"Gisela Vollmer Architekturb\u00fcro",
    "wof:placetype":"venue"
},
  "geometry": {"coordinates":[7.442484,46.945312],"type":"Point"}
}