{
  "type": "Feature",
  "properties": {
    "iso:country":"CH",
    "sg:address":"Z\u00fcrcherstrasse 149",
    "sg:city":"Oberengstringen",
    "sg:orig_category":"Arztpraxen",
    "sg:phone":"+41 17505043",
    "sg:postcode":"8102",
    "sg:province":"Z\u00fcrich",
    "wof:name":"Dr.med.walter Schweizer Arzt F\u00fcr Allgemeine Medizin",
    "wof:placetype":"venue"
},
  "geometry": {"coordinates":[8.458185,47.410557],"type":"Point"}
}