{
  "type": "Feature",
  "properties": {
    "iso:country":"CH",
    "sg:address":"Gulmstrasse 62",
    "sg:city":"Ober\u00e4geri",
    "sg:orig_category":"Non-Classified Establishments",
    "sg:postcode":"6315",
    "sg:province":"Zug",
    "wof:name":"Gulm Verwaltungs Ag",
    "wof:placetype":"venue"
},
  "geometry": {"coordinates":[8.7771053314,47.2004928589],"type":"Point"}
}