{
  "type": "Feature",
  "properties": {
    "iso:country":"CH",
    "sg:address":"Chemin De La Possession 11",
    "sg:city":"Prilly",
    "sg:orig_category":"Verlegen von Fliesen U Platten",
    "sg:phone":"+41 21 634 33 63",
    "sg:postcode":"1008",
    "sg:province":"Vaud",
    "wof:name":"Nilo Albricci Carrelage & Rev\u00eatement De Sols",
    "wof:placetype":"venue"
},
  "geometry": {"coordinates":[6.6053991318,46.5389633179],"type":"Point"}
}