{
  "type": "Feature",
  "properties": {
    "iso:country":"CH",
    "sg:address":"Zwillikerstrasse 4",
    "sg:city":"Hedingen",
    "sg:orig_category":"Landwirtschaftliche Genossenschaften",
    "sg:phone":"+41 17616275",
    "sg:postcode":"8908",
    "sg:province":"Z\u00fcrich",
    "wof:name":"Landw.genossenschaft Hedingen",
    "wof:placetype":"venue"
},
  "geometry": {"coordinates":[8.4476175308,47.2983055115],"type":"Point"}
}