{
  "type": "Feature",
  "properties": {
    "iso:country":"CH",
    "sg:address":"Untere Z\u00e4une 19",
    "sg:city":"Z\u00fcrich",
    "sg:orig_category":"Religi\u00f6se Vereinigungen divers",
    "sg:phone":"+41 12515925",
    "sg:postcode":"8001",
    "sg:province":"Z\u00fcrich",
    "wof:name":"Die Christengemeinschaft",
    "wof:placetype":"venue"
},
  "geometry": {"coordinates":[8.5454969406,47.371635437],"type":"Point"}
}