{
  "type": "Feature",
  "properties": {
    "iso:country":"CH",
    "sg:address":"Avenue Du Gros-ch\u00eane 33bis",
    "sg:city":"Onex",
    "sg:orig_category":"Geb\u00e4ude, Wohnungsreinigung Reinigungsgewerbe",
    "sg:phone":"+41 22 342 60 43",
    "sg:postcode":"1213",
    "sg:province":"Gen\u00e8ve",
    "wof:name":"Nettoyages Tapis Chavan Sa",
    "wof:placetype":"venue"
},
  "geometry": {"coordinates":[6.1444468498,46.1856460571],"type":"Point"}
}