{
  "type": "Feature",
  "properties": {
    "iso:country":"CH",
    "sg:address":"Schauplatzgasse 1 3011 Bern. Postfach",
    "sg:city":"Bern",
    "sg:orig_category":"RESTAURANTS: TEA-ROOMS",
    "sg:phone":"+41 31 311 12 35",
    "sg:postcode":"3011",
    "sg:province":"Bern",
    "wof:name":"Bluecafe Koch Herbert Gastwirtschaftsbetrieb",
    "wof:placetype":"venue"
},
  "geometry": {"coordinates":[7.4435100555,46.9472198486],"type":"Point"}
}