{
  "type": "Feature",
  "properties": {
    "iso:country":"CH",
    "sg:address":"Wynaustrasse 101",
    "sg:city":"Aarwangen",
    "sg:orig_category":"Berufliche Weiterbildung, Erwachsenenbildung",
    "sg:phone":"+41 62 922 29 33",
    "sg:postcode":"4912",
    "sg:province":"Bern",
    "wof:name":"Regionales Zivilschutz- Ausbildungszentrum",
    "wof:placetype":"venue"
},
  "geometry": {"coordinates":[7.772643,47.241325],"type":"Point"}
}