{
  "type": "Feature",
  "properties": {
    "iso:country":"CH",
    "sg:address":"St. Dionysstrasse 31",
    "sg:city":"Jona",
    "sg:orig_category":"Non-Classified Establishments",
    "sg:postcode":"8645",
    "sg:province":"St. Gallen",
    "wof:name":"Intercos Holding Gmbh Beteiligungen, Bes. In Der Parf\u00fcmeriebranche",
    "wof:placetype":"venue"
},
  "geometry": {"coordinates":[8.7784986496,47.2003517151],"type":"Point"}
}