{
  "type": "Feature",
  "properties": {
    "iso:country":"CH",
    "sg:address":"M\u00fchlemattstrasse 32",
    "sg:city":"B\u00e4ttwil",
    "sg:orig_category":"Airborne Particulate Filter Plants",
    "sg:phone":"+41 61 313 26 25",
    "sg:postcode":"4112",
    "sg:province":"Solothurn",
    "wof:name":"Via Ag Engineering",
    "wof:placetype":"venue"
},
  "geometry": {"coordinates":[7.503603,47.490234],"type":"Point"}
}