{
  "type": "Feature",
  "properties": {
    "iso:country":"CH",
    "sg:address":"T\u00e4fernstrasse 20",
    "sg:city":"D\u00e4ttwil",
    "sg:classifiers":[
        {
            "category":"Communications",
            "subcategory":"Radio Station",
            "type":"Services"
        }
    ],
    "sg:phone":"+41 56 484 50 50",
    "sg:postcode":"5405",
    "sg:province":"Aargau",
    "sg:tags":[
        "installation",
        "network"
    ],
    "wof:name":"Md Computer",
    "wof:placetype":"venue"
},
  "geometry": {"coordinates":[8.2939882278,47.4476890564],"type":"Point"}
}