{
  "type": "Feature",
  "properties": {
    "iso:country":"CH",
    "sg:address":"Alte Landstrasse 17",
    "sg:city":"Unter\u00e4geri",
    "sg:orig_category":"Datenverarbeitungsdienste Wirtschaftspr\u00fcfung, Steuerberatung U Treuhand",
    "sg:phone":"+41 22 909 27 89",
    "sg:postcode":"6314",
    "sg:province":"Zug",
    "wof:name":"Sett Fiduciaire Sa",
    "wof:placetype":"venue"
},
  "geometry": {"coordinates":[6.139748,46.206284],"type":"Point"}
}