{
  "type": "Feature",
  "properties": {
    "iso:country":"CH",
    "sg:address":"Schiffl\u00e4nde 5",
    "sg:city":"Z\u00fcrich",
    "sg:orig_category":"Non-Classified Establishments",
    "sg:phone":"+41 12526022",
    "sg:postcode":"8001",
    "sg:province":"Z\u00fcrich",
    "wof:name":"Inter Scan Holding Ltd Beteiligungen Usw.",
    "wof:placetype":"venue"
},
  "geometry": {"coordinates":[8.5443372726,47.3686294556],"type":"Point"}
}