{
  "type": "Feature",
  "properties": {
    "iso:country":"CH",
    "sg:address":"Chemin Jules-edouard-gottret 6",
    "sg:city":"Veyrier",
    "sg:orig_category":"G\u00fcterbef\u00f6rderung im Strassenverkehr",
    "sg:phone":"+41 22 342 52 30",
    "sg:postcode":"1255",
    "sg:province":"Gen\u00e8ve",
    "wof:name":"Georges Tachon Transports",
    "wof:placetype":"venue"
},
  "geometry": {"coordinates":[6.1369481087,46.179889679],"type":"Point"}
}