{
  "type": "Feature",
  "properties": {
    "iso:country":"CH",
    "sg:address":"Seidenstrasse 14",
    "sg:city":"Oberurnen",
    "sg:orig_category":"Zimmerei, Dachdeckerei, Bauspenglerei U Abdichtung",
    "sg:phone":"+41 32 913 43 93",
    "sg:postcode":"8868",
    "sg:province":"Glarus",
    "wof:name":"S\u00e9timac - Bernasconi Gilbert Sa",
    "wof:placetype":"venue"
},
  "geometry": {"coordinates":[6.8217120171,47.0981674194],"type":"Point"}
}