{
  "type": "Feature",
  "properties": {
    "iso:country":"CH",
    "sg:address":"Haldenstrasse 7",
    "sg:city":"Feuerthalen",
    "sg:orig_category":"Vorschulen, Kinderg\u00e4rten",
    "sg:phone":"+41 52 659 35 24",
    "sg:postcode":"8245",
    "sg:province":"Z\u00fcrich",
    "wof:name":"Kindergarten Haldenstrasse",
    "wof:placetype":"venue"
},
  "geometry": {"coordinates":[8.6430206299,47.69190979],"type":"Point"}
}