{
  "type": "Feature",
  "properties": {
    "iso:country":"CH",
    "sg:address":"Sonnenweg 49",
    "sg:city":"N\u00e4fels",
    "sg:orig_category":"Wasserversorgung",
    "sg:phone":"+41 71 722 71 17",
    "sg:postcode":"8752",
    "sg:province":"Glarus",
    "wof:name":"Hwt Z\u00fcnd Ag",
    "wof:placetype":"venue"
},
  "geometry": {"coordinates":[9.6401844025,47.4348678589],"type":"Point"}
}