{
  "type": "Feature",
  "properties": {
    "iso:country":"CH",
    "sg:address":"Bahnhofstrasse 16",
    "sg:city":"Zug",
    "sg:orig_category":"Unternehmensberatung",
    "sg:postcode":"6300",
    "sg:province":"Zug",
    "wof:name":"Dirt Ag",
    "wof:placetype":"venue"
},
  "geometry": {"coordinates":[8.5158338547,47.1691551208],"type":"Point"}
}