{
  "type": "Feature",
  "properties": {
    "iso:country":"CH",
    "sg:address":"Eschenring 13",
    "sg:city":"Zug",
    "sg:orig_category":"Unternehmensberatung Wirtschaftspr\u00fcfung, Steuerberatung U Treuhand",
    "sg:phone":"+41 71 622 47 22",
    "sg:postcode":"6300",
    "sg:province":"Zug",
    "wof:name":"City Treuhand Weinfelden Ag",
    "wof:placetype":"venue"
},
  "geometry": {"coordinates":[9.1381845474,47.5666694641],"type":"Point"}
}