{
  "type": "Feature",
  "properties": {
    "iso:country":"CH",
    "sg:address":"Montana-vermala",
    "sg:city":"Bluche-randogne",
    "sg:orig_category":"Unclassifiable Establishments",
    "sg:postcode":"3975",
    "sg:province":"Valais",
    "wof:name":"Si Vacances \u00e0 Crans-sur-sierre No 3 Sa",
    "wof:placetype":"venue"
},
  "geometry": {"coordinates":[7.4955601692,46.309928894],"type":"Point"}
}