{
  "type": "Feature",
  "properties": {
    "iso:country":"CH",
    "sg:address":"Auf Der Burg",
    "sg:city":"Meilen",
    "sg:orig_category":"Unternehmensberatung",
    "sg:phone":"+41 12212962",
    "sg:postcode":"8706",
    "sg:province":"Z\u00fcrich",
    "wof:name":"Optirama Management Und Beratungs Ag",
    "wof:placetype":"venue"
},
  "geometry": {"coordinates":[8.643116951,47.2783813477],"type":"Point"}
}