{
  "type": "Feature",
  "properties": {
    "iso:country":"CH",
    "sg:address":"Loretostrasse 8",
    "sg:city":"Lichtensteig",
    "sg:orig_category":"Detailhandel mit Fleisch U Fleischwaren",
    "sg:phone":"+41 71 988 15 61",
    "sg:postcode":"9620",
    "sg:province":"St. Gallen",
    "wof:name":"Metzgerei Preisig Ag",
    "wof:placetype":"venue"
},
  "geometry": {"coordinates":[9.0870084763,47.3247795105],"type":"Point"}
}