{
  "type": "Feature",
  "properties": {
    "iso:country":"CH",
    "sg:address":"Landstrasse 49",
    "sg:city":"Vaduz",
    "sg:orig_category":"Offsetdruck Unternehmensberatung",
    "sg:phone":"+41 71 925 35 21",
    "sg:postcode":"9490",
    "wof:name":"Osterwalder Markus Gmbh Land, Garten, Forst- U. Transportarbeiten Usw.",
    "wof:placetype":"venue"
},
  "geometry": {"coordinates":[9.0375061035,47.4524307251],"type":"Point"}
}