{
  "type": "Feature",
  "properties": {
    "iso:country":"CH",
    "sg:address":"H\u00fcttenstrasse 3",
    "sg:city":"B\u00e4retswil",
    "sg:orig_category":"Schreib U \u00dcbersetzungsb\u00fcros Sonstige Hilfsdienste des Kultur U Unterhaltungswesens",
    "sg:phone":"+41 19392450",
    "sg:postcode":"8344",
    "sg:province":"Z\u00fcrich",
    "wof:name":"Soundswrite Gmbh",
    "wof:placetype":"venue"
},
  "geometry": {"coordinates":[8.857837677,47.3366699219],"type":"Point"}
}