{
  "type": "Feature",
  "properties": {
    "iso:country":"CH",
    "sg:address":"Alpenstrasse 2",
    "sg:city":"Interlaken",
    "sg:orig_category":"Wohnheime",
    "sg:phone":"+41 33 822 92 72",
    "sg:postcode":"3800",
    "sg:province":"Bern",
    "wof:name":"Pony-cap",
    "wof:placetype":"venue"
},
  "geometry": {"coordinates":[7.8577327728,46.6841468811],"type":"Point"}
}