{
  "type": "Feature",
  "properties": {
    "iso:country":"CH",
    "sg:address":"Sempacherstrasse 34 6003 Luzern. Postfach 2365",
    "sg:city":"Luzern",
    "sg:orig_category":"Allgemeiner Hochbau Tunnelbau",
    "sg:phone":"+41 71 688 10 90",
    "sg:postcode":"6002",
    "sg:province":"Luzern",
    "wof:name":"Zschokke Bau Ag",
    "wof:placetype":"venue"
},
  "geometry": {"coordinates":[9.188539,47.644096],"type":"Point"}
}