{
  "type": "Feature",
  "properties": {
    "iso:country":"CH",
    "sg:address":"Rue Des Moulins 88",
    "sg:city":"Yverdon-les-bains",
    "sg:orig_category":"Sonstige technische Beratung U Planung",
    "sg:phone":"+41 24 425 12 40",
    "sg:postcode":"1400",
    "sg:province":"Vaud",
    "wof:name":"Burri-umiglia S\u00e0rl",
    "wof:placetype":"venue"
},
  "geometry": {"coordinates":[6.6313891411,46.7734909058],"type":"Point"}
}