{
  "type": "Feature",
  "properties": {
    "iso:country":"CH",
    "sg:address":"Roman-burri-strasse 4",
    "sg:city":"Sursee",
    "sg:orig_category":"Sonstiger Grosshandel",
    "sg:postcode":"6210",
    "sg:province":"Luzern",
    "wof:name":"Graf Consulting Waren; Handel",
    "wof:placetype":"venue"
},
  "geometry": {"coordinates":[8.7831497192,47.2023239136],"type":"Point"}
}