{
  "type": "Feature",
  "properties": {
    "iso:country":"CH",
    "sg:address":"Sch\u00f6nengrund 26 6343 Risch. Postfach",
    "sg:city":"Rotkreuz",
    "sg:orig_category":"Wirtschaftspr\u00fcfung, Steuerberatung U Treuhand",
    "sg:phone":"+41 41 798 09 09",
    "sg:postcode":"6343",
    "sg:province":"Zug",
    "wof:name":"Beeler R. + Partner Treuhand Ag Treuhandgesch\u00e4fte, Bes. Steuer, Abschluss, Buchhaltungs Und Finanzberatungen",
    "wof:placetype":"venue"
},
  "geometry": {"coordinates":[8.4281053543,47.1457672119],"type":"Point"}
}