{
  "type": "Feature",
  "properties": {
    "iso:country":"CH",
    "sg:address":"Haus Arba",
    "sg:city":"Wengen",
    "sg:orig_category":"Allgemeiner Hochbau",
    "sg:phone":"+41 33 855 33 18",
    "sg:postcode":"3823",
    "sg:province":"Bern",
    "wof:name":"Graf Ag Hoch-& Tiefbau Holzbau",
    "wof:placetype":"venue"
},
  "geometry": {"coordinates":[7.9216,46.605194],"type":"Point"}
}