{
  "type": "Feature",
  "properties": {
    "iso:country":"CH",
    "sg:address":"Ruffinistrasse 7",
    "sg:city":"Grenchen",
    "sg:orig_category":"Gesundheitswesen",
    "sg:phone":"+41 32 652 69 79",
    "sg:postcode":"2540",
    "sg:province":"Solothurn",
    "wof:name":"Coi Fabrizio",
    "wof:placetype":"venue"
},
  "geometry": {"coordinates":[7.3820080757,47.1863670349],"type":"Point"}
}