{
  "type": "Feature",
  "properties": {
    "addr:full":"Rue Peillonnex 39 Ch\u00eane-bourg Gen\u00e8ve 1225",
    "addr:housenumber":"39",
    "addr:postcode":"1225",
    "addr:street":"Rue Peillonnex",
    "iso:country":"CH",
    "sg:address":"Rue Peillonnex 39",
    "sg:city":"Ch\u00eane-bourg",
    "sg:orig_category":"Bau U Wohngenossenschaften",
    "sg:phone":"+41 22 348 44 22",
    "sg:postcode":"1225",
    "sg:province":"Gen\u00e8ve",
    "wof:name":"Propri\u00e9t\u00e9 \u00e0 Tous Pat Sa Soci\u00e9t\u00e9 De Logement",
    "wof:placetype":"venue"
},
  "geometry": {"coordinates":[6.198813,46.195393],"type":"Point"}
}