{
  "type": "Feature",
  "properties": {
    "iso:country":"CH",
    "sg:address":"Aufeld",
    "sg:city":"Mosnang",
    "sg:orig_category":"Grosshandel mit lebenden Tieren",
    "sg:phone":"+41 71 944 10 71",
    "sg:postcode":"9607",
    "sg:province":"St. Gallen",
    "wof:name":"Breitenmoser Walter",
    "wof:placetype":"venue"
},
  "geometry": {"coordinates":[9.1112670898,47.4775733948],"type":"Point"}
}