{
  "type": "Feature",
  "properties": {
    "iso:country":"CH",
    "sg:address":"Seestrasse 73",
    "sg:city":"Zollikon",
    "sg:orig_category":"Reiseb\u00fcros U Reiseveranstalter",
    "sg:phone":"+41 13902580",
    "sg:postcode":"8702",
    "sg:province":"Z\u00fcrich",
    "wof:name":"Babil Handels Und Reisen Ag",
    "wof:placetype":"venue"
},
  "geometry": {"coordinates":[8.5692033768,47.3368911743],"type":"Point"}
}