{
  "type": "Feature",
  "properties": {
    "addr:full":"Route De La Pierre 22 Ecublens Vaud 1024",
    "addr:housenumber":"22",
    "addr:postcode":"1024",
    "addr:street":"Route De La Pierre",
    "iso:country":"CH",
    "sg:address":"Route De La Pierre 22",
    "sg:city":"Ecublens",
    "sg:classifiers":[
        {
            "category":"Wholesale",
            "subcategory":"Hardware",
            "type":"Manufacturing & Wholesale Goods"
        }
    ],
    "sg:phone":"+41 21 695 21 43",
    "sg:postcode":"1024",
    "sg:province":"Vaud",
    "sg:tags":[
        "anti-virus"
    ],
    "wof:name":"Dassault Syst\u00e8mes (suisse) Sa",
    "wof:placetype":"venue"
},
  "geometry": {"coordinates":[6.55975,46.53006],"type":"Point"}
}