{
  "type": "Feature",
  "properties": {
    "iso:country":"CH",
    "sg:address":"B\u00f6hler",
    "sg:city":"Untereggen",
    "sg:orig_category":"Dienstleistungen in der Forstwirtschaft",
    "sg:phone":"+41 71 866 17 81",
    "sg:postcode":"9033",
    "sg:province":"St. Gallen",
    "wof:name":"Anton Braunwalder Mobil-s\u00e4gerei",
    "wof:placetype":"venue"
},
  "geometry": {"coordinates":[9.4407100677,47.4492835999],"type":"Point"}
}