{
  "type": "Feature",
  "properties": {
    "iso:country":"CH",
    "sg:address":"Stotz 9",
    "sg:city":"Untervaz",
    "sg:classifiers":[
        {
            "category":"Restaurant",
            "type":"Food & Drink"
        }
    ],
    "sg:phone":"+41 81 322 19 82",
    "sg:postcode":"7204",
    "sg:province":"Graubunden",
    "wof:name":"Restaurant Tanne",
    "wof:placetype":"venue"
},
  "geometry": {"coordinates":[9.5343408585,46.9291877747],"type":"Point"}
}