{
  "type": "Feature",
  "properties": {
    "iso:country":"CH",
    "sg:address":"Ch. Champs De Feurs 13",
    "sg:city":"Mies",
    "sg:orig_category":"Schreib U \u00dcbersetzungsb\u00fcros",
    "sg:phone":"+41 22 755 32 90",
    "sg:postcode":"1295",
    "sg:province":"Vaud",
    "wof:name":"Palmer Verena",
    "wof:placetype":"venue"
},
  "geometry": {"coordinates":[6.1676249504,46.3045158386],"type":"Point"}
}