{
  "type": "Feature",
  "properties": {
    "iso:country":"CH",
    "sg:address":"9413",
    "sg:city":"Oberegg",
    "sg:orig_category":"Vereine Dramatische and Theater",
    "sg:postcode":"9413",
    "sg:province":"Appenzell Innerhoden",
    "wof:name":"Dramatischer Verein St.moritz",
    "wof:placetype":"venue"
},
  "geometry": {"coordinates":[9.8381900787,46.4970588684],"type":"Point"}
}