{
  "type": "Feature",
  "properties": {
    "iso:country":"CH",
    "sg:address":"Bruggerstrasse 115",
    "sg:city":"Baden",
    "sg:orig_category":"Instandhaltung U Reparatur von Automobilen",
    "sg:phone":"+41 56 222 98 06",
    "sg:postcode":"5400",
    "sg:province":"Aargau",
    "wof:name":"Francesco Gambino Garage",
    "wof:placetype":"venue"
},
  "geometry": {"coordinates":[8.2932567596,47.4832038879],"type":"Point"}
}