{
  "type": "Feature",
  "properties": {
    "iso:country":"CH",
    "sg:address":"4814",
    "sg:city":"Bottenwil",
    "sg:orig_category":"Vorschulen, Kinderg\u00e4rten",
    "sg:phone":"+41 62 721 39 88",
    "sg:postcode":"4814",
    "sg:province":"Aargau",
    "wof:name":"Kindergarten",
    "wof:placetype":"venue"
},
  "geometry": {"coordinates":[7.9994702339,47.2817802429],"type":"Point"}
}