{
  "type": "Feature",
  "properties": {
    "iso:country":"CH",
    "sg:address":"Fontaine Rue De La 7 1201 Gen\u00e8ve. Postfach",
    "sg:city":"Gen\u00e8ve",
    "sg:orig_category":"Forschung U Entwicklung im Bereich der Naturwissenschaften",
    "sg:postcode":"1201",
    "sg:province":"Gen\u00e8ve",
    "wof:name":"Undl Foundation Recherche Et D\u00e9veloppement Dans Le Dom. Informatique, En Part. D'un Syst\u00e8me De Communication Interlinguistique",
    "wof:placetype":"venue"
},
  "geometry": {"coordinates":[6.142701149,46.2083587646],"type":"Point"}
}