{
  "type": "Feature",
  "properties": {
    "iso:country":"CH",
    "sg:address":"Staatsstrasse 159",
    "sg:city":"H\u00fcnibach",
    "sg:orig_category":"Kosmetikinstitute",
    "sg:phone":"+41 71 311 20 44",
    "sg:postcode":"3626",
    "sg:province":"Bern",
    "wof:name":"Marianne Wettach Kosmetikinstitut Marianne",
    "wof:placetype":"venue"
},
  "geometry": {"coordinates":[9.3167734146,47.420589447],"type":"Point"}
}