{
  "type": "Feature",
  "properties": {
    "iso:country":"CH",
    "sg:address":"Schmiedgasse 57 6438 Ibach. Postfach",
    "sg:city":"Ibach",
    "sg:orig_category":"Grosshandel mit Getreide, Saatgut U Futtermitteln",
    "sg:phone":"+41 62 875 11 81",
    "sg:postcode":"6438",
    "sg:province":"Schwyz",
    "wof:name":"Viktor Oeschger Heuhandel",
    "wof:placetype":"venue"
},
  "geometry": {"coordinates":[8.1331262589,47.5567054749],"type":"Point"}
}