{
  "type": "Feature",
  "properties": {
    "iso:country":"CH",
    "sg:address":"Salmsacherstrasse 14",
    "sg:city":"Romanshorn",
    "sg:orig_category":"Vereine Hundedressur",
    "sg:phone":"+41 71 463 39 11",
    "sg:postcode":"8590",
    "sg:province":"Thurgau",
    "wof:name":"Kynolog.verein Romanshorn",
    "wof:placetype":"venue"
},
  "geometry": {"coordinates":[9.3729476929,47.5633468628],"type":"Point"}
}