{
  "type": "Feature",
  "properties": {
    "iso:country":"CH",
    "sg:address":"Route Des Ravi\u00e8res 1",
    "sg:city":"Perly",
    "sg:orig_category":"Tankstellen",
    "sg:phone":"+41 22 771 17 77",
    "sg:postcode":"1258",
    "sg:province":"Gen\u00e8ve",
    "wof:name":"Lahcen Benslimane Station-service Esso",
    "wof:placetype":"venue"
},
  "geometry": {"coordinates":[6.0949621201,46.1552848816],"type":"Point"}
}