{
  "type": "Feature",
  "properties": {
    "iso:country":"CH",
    "sg:address":"Am Pfisterh\u00f6lzli 25",
    "sg:city":"Greifensee",
    "sg:orig_category":"Softwareentwicklung U beratung",
    "sg:postcode":"8606",
    "sg:province":"Z\u00fcrich",
    "wof:name":"Infram, Amacher Ir\u00e8ne",
    "wof:placetype":"venue"
},
  "geometry": {"coordinates":[7.6748552322,46.6898498535],"type":"Point"}
}