{
  "type": "Feature",
  "properties": {
    "iso:country":"CH",
    "sg:address":"Sulzweidstrasse 16",
    "sg:city":"Gommiswald",
    "sg:orig_category":"Arztpraxen",
    "sg:phone":"+41 55 280 33 04",
    "sg:postcode":"8737",
    "sg:province":"St. Gallen",
    "wof:name":"Dr.med.emil Pfister Arzt F.allgemeine Medizin Fmh",
    "wof:placetype":"venue"
},
  "geometry": {"coordinates":[9.018833,47.235207],"type":"Point"}
}