{
  "type": "Feature",
  "properties": {
    "iso:country":"CH",
    "sg:address":"Br\u00fcckenstrasse 47 3005 Bern. Postfach",
    "sg:city":"Bern",
    "sg:orig_category":"Softwareentwicklung U beratung",
    "sg:phone":"+41 61 723 11 23",
    "sg:postcode":"3005",
    "sg:province":"Bern",
    "wof:name":"Dietrich Edv Gmbh Informatik-dienstleistungen",
    "wof:placetype":"venue"
},
  "geometry": {"coordinates":[7.5212221146,47.5045967102],"type":"Point"}
}