{
  "type": "Feature",
  "properties": {
    "iso:country":"CH",
    "sg:address":"1245",
    "sg:city":"Collonge-bellerive",
    "sg:classifiers":[
        {
            "category":"Travel",
            "subcategory":"Hotels & Motels",
            "type":"Entertainment"
        }
    ],
    "sg:postcode":"1245",
    "sg:province":"Gen\u00e8ve",
    "sg:tags":[
        "hotels",
        "mit",
        "restaurant"
    ],
    "wof:name":"M. Et Mme Nguyen-pham",
    "wof:placetype":"venue"
},
  "geometry": {"coordinates":[6.1956801414,46.255859375],"type":"Point"}
}