{
  "type": "Feature",
  "properties": {
    "iso:country":"CH",
    "sg:address":"Weissensteinstrasse 35",
    "sg:city":"Bern",
    "sg:orig_category":"Organisationen des Gesundheitswesen",
    "sg:phone":"+41 31 372 91 61",
    "sg:postcode":"3007",
    "sg:province":"Bern",
    "wof:name":"Schweizer Kneippverband",
    "wof:placetype":"venue"
},
  "geometry": {"coordinates":[7.4224119186,46.9401359558],"type":"Point"}
}