{
  "type": "Feature",
  "properties": {
    "iso:country":"CH",
    "sg:address":"Via Vecchia Dogana 3",
    "sg:city":"Muralto",
    "sg:classifiers":[
        {
            "category":"Bars & Pubs",
            "type":"Food & Drink"
        }
    ],
    "sg:phone":"+41 32 866 14 28",
    "sg:postcode":"6600",
    "sg:province":"Ticino",
    "wof:name":"Bar Relais De Meudon",
    "wof:placetype":"venue"
},
  "geometry": {"coordinates":[6.45874,46.901119],"type":"Point"}
}