{
  "type": "Feature",
  "properties": {
    "iso:country":"CH",
    "sg:address":"S\u00e4ntisstrasse 4",
    "sg:city":"Schmerikon",
    "sg:orig_category":"Grosshandel mit H\u00e4uten, Fellen U Leder",
    "sg:phone":"+41 19300588",
    "sg:postcode":"8716",
    "sg:province":"St. Gallen",
    "wof:name":"Markus Ryffel Schaffelle",
    "wof:placetype":"venue"
},
  "geometry": {"coordinates":[8.7999181747,47.3246536255],"type":"Point"}
}