{
  "type": "Feature",
  "properties": {
    "addr:full":"Bahnhofstrasse 15 Lenzburg Aargau 5600",
    "addr:housenumber":"15",
    "addr:postcode":"5600",
    "addr:street":"Bahnhofstrasse",
    "iso:country":"CH",
    "sg:address":"Bahnhofstrasse 15",
    "sg:city":"Lenzburg",
    "sg:orig_category":"Arztpraxen",
    "sg:phone":"+41 62 892 18 58",
    "sg:postcode":"5600",
    "sg:province":"Aargau",
    "wof:name":"Dr.med.beat Frei Arzt F\u00fcr Allgemeine Medizin",
    "wof:placetype":"venue"
},
  "geometry": {"coordinates":[8.175194,47.389069],"type":"Point"}
}