{
  "type": "Feature",
  "properties": {
    "iso:country":"CH",
    "sg:address":"Unionstrasse 13",
    "sg:city":"Goldach",
    "sg:orig_category":"Druck ohne Zeitungsdruck",
    "sg:phone":"+41 71 841 47 92",
    "sg:postcode":"9403",
    "sg:province":"St. Gallen",
    "wof:name":"Mascon Markus Schneider",
    "wof:placetype":"venue"
},
  "geometry": {"coordinates":[9.4628334045,47.4717216492],"type":"Point"}
}