{
  "type": "Feature",
  "properties": {
    "iso:country":"CH",
    "sg:address":"Landstrasse 80",
    "sg:city":"Gipf-oberfrick",
    "sg:orig_category":"Sonstiger Grosshandel",
    "sg:phone":"+41 62 871 05 70",
    "sg:postcode":"5073",
    "sg:province":"Aargau",
    "wof:name":"St\u00e4uble Trading",
    "wof:placetype":"venue"
},
  "geometry": {"coordinates":[7.9969558716,47.4916152954],"type":"Point"}
}