{
  "type": "Feature",
  "properties": {
    "iso:country":"CH",
    "sg:address":"Industriestrasse 15",
    "sg:city":"Berom\u00fcnster",
    "sg:orig_category":"Grosshandel mit Baumaschinen",
    "sg:phone":"+41 79 408 23 01",
    "sg:postcode":"6215",
    "sg:province":"Luzern",
    "wof:name":"Wicki Baumaschinen Baumaschinenhandel",
    "wof:placetype":"venue"
},
  "geometry": {"coordinates":[8.2040710449,47.2030677795],"type":"Point"}
}