{
  "type": "Feature",
  "properties": {
    "iso:country":"CH",
    "sg:address":"Baselstrasse 47",
    "sg:city":"Luzern",
    "sg:orig_category":"Grosshandel mit Geschenkartikeln U Souvenirs Grosshandel mit Getr\u00e4nken",
    "sg:phone":"+41 41 240 64 50",
    "sg:postcode":"6003",
    "sg:province":"Luzern",
    "wof:name":"Mdm Market Miladinovic M.",
    "wof:placetype":"venue"
},
  "geometry": {"coordinates":[8.2942810059,47.0532951355],"type":"Point"}
}