{
  "type": "Feature",
  "properties": {
    "iso:country":"CH",
    "sg:address":"Kohlenberggasse 21",
    "sg:city":"Basel",
    "sg:orig_category":"Vermietung von Automobilen",
    "sg:phone":"+41 61 281 12 54",
    "sg:postcode":"4051",
    "sg:province":"Basel-Stadt",
    "wof:name":"Limousine Service Z\u00fcst Mark",
    "wof:placetype":"venue"
},
  "geometry": {"coordinates":[7.5876731873,47.5525093079],"type":"Point"}
}