{
  "type": "Feature",
  "properties": {
    "iso:country":"CH",
    "sg:address":"Kernserstrasse 17",
    "sg:city":"Sarnen",
    "sg:orig_category":"Filmverleih U Videoprogrammanbieter",
    "sg:phone":"+41 14912727",
    "sg:postcode":"6060",
    "sg:province":"Obwalden",
    "wof:name":"Schmalfilm Ag",
    "wof:placetype":"venue"
},
  "geometry": {"coordinates":[8.6490488052,47.2412338257],"type":"Point"}
}