{
  "type": "Feature",
  "properties": {
    "iso:country":"CH",
    "sg:address":"Rue De La Chappelle 1958 Uvrier. Postfach",
    "sg:city":"Uvrier",
    "sg:orig_category":"Herstellung von Elektrizit\u00e4tsverteilungs U schalteinrichtungen",
    "sg:postcode":"1958",
    "sg:province":"Valais",
    "wof:name":"Pcb Production Sa",
    "wof:placetype":"venue"
},
  "geometry": {"coordinates":[7.4146900177,46.2510185242],"type":"Point"}
}