{
  "type": "Feature",
  "properties": {
    "iso:country":"CH",
    "sg:address":"Au Village",
    "sg:city":"Sorens",
    "sg:classifiers":[
        {
            "category":"Banks & Credit Unions",
            "subcategory":"Bank",
            "type":"Services"
        }
    ],
    "sg:phone":"+41 26 915 11 77",
    "sg:postcode":"1642",
    "sg:province":"Fribourg",
    "wof:name":"Raiffeisen",
    "wof:placetype":"venue"
},
  "geometry": {"coordinates":[7.058305,46.668987],"type":"Point"}
}