{
  "type": "Feature",
  "properties": {
    "iso:country":"CH",
    "sg:address":"Neuhausweg 1",
    "sg:city":"Baar",
    "sg:orig_category":"Detailhandel mit medizinischen U orthop\u00e4dischen Artikeln",
    "sg:phone":"+41 41 761 24 64",
    "sg:postcode":"6340",
    "sg:province":"Zug",
    "wof:name":"Josef Stalder Schuhmacherei & Fussorthop\u00e4die",
    "wof:placetype":"venue"
},
  "geometry": {"coordinates":[8.5211553574,47.1855621338],"type":"Point"}
}