{
  "type": "Feature",
  "properties": {
    "iso:country":"CH",
    "sg:address":"Untere Schieb 20",
    "sg:city":"Dietfurt",
    "sg:orig_category":"Detailhandel mit Haustieren U zoologischem Bedarf",
    "sg:phone":"+41 71 983 44 04",
    "sg:postcode":"9615",
    "sg:province":"St. Gallen",
    "wof:name":"Peter R\u00fcegg Zoofachgesch\u00e4ft",
    "wof:placetype":"venue"
},
  "geometry": {"coordinates":[9.0815229416,47.3430213928],"type":"Point"}
}