{
  "type": "Feature",
  "properties": {
    "iso:country":"CH",
    "sg:address":"Dufourstrasse 85",
    "sg:city":"Z\u00fcrich",
    "sg:orig_category":"Erbringung von Dienstleistungen f\u00fcr Unternehmen",
    "sg:phone":"+41 13838388",
    "sg:postcode":"8008",
    "sg:province":"Z\u00fcrich",
    "wof:name":"L'altro Visual Graphic Arts & Design",
    "wof:placetype":"venue"
},
  "geometry": {"coordinates":[8.5509033203,47.3599777222],"type":"Point"}
}