{
  "type": "Feature",
  "properties": {
    "iso:country":"CH",
    "sg:address":"Seebuchtstrasse 19",
    "sg:city":"Buochs",
    "sg:orig_category":"Detailhandel mit Teppichen Parkettleger",
    "sg:phone":"+41 41 620 14 61",
    "sg:postcode":"6374",
    "sg:province":"Nidwalden",
    "wof:name":"Vogel Ag Bodenbelags-center",
    "wof:placetype":"venue"
},
  "geometry": {"coordinates":[8.4215240479,46.9761238098],"type":"Point"}
}