{
  "type": "Feature",
  "properties": {
    "iso:country":"CH",
    "sg:address":"Clos Route Du 12 1197 Prangins. Postfach",
    "sg:city":"Prangins",
    "sg:orig_category":"Vermietung U Verpachtung von eigenen Immobilien",
    "sg:phone":"+41 22 361 02 19",
    "sg:postcode":"1197",
    "sg:province":"Vaud",
    "wof:name":"Siam-parc Sa Immobilier Etc",
    "wof:placetype":"venue"
},
  "geometry": {"coordinates":[6.2490000725,46.3943252563],"type":"Point"}
}