{
  "type": "Feature",
  "properties": {
    "iso:country":"CH",
    "sg:address":"Boulevard Carl-vogt 102",
    "sg:city":"Gen\u00e8ve",
    "sg:orig_category":"Elektro- and elektronische Maschinen Grosshandel Softwareentwicklung U beratung",
    "sg:phone":"+41 22 809 89 40",
    "sg:postcode":"1205",
    "sg:province":"Gen\u00e8ve",
    "wof:name":"Sweetcom S\u00e0rl",
    "wof:placetype":"venue"
},
  "geometry": {"coordinates":[6.1410341263,46.1949195862],"type":"Point"}
}