{
  "type": "Feature",
  "properties": {
    "iso:country":"CH",
    "sg:address":"Drahtzugstrasse 74-76 8008 Z\u00fcrich. Postfach",
    "sg:city":"Z\u00fcrich",
    "sg:orig_category":"Tagesheime f\u00fcr Behinderte, gesch\u00fctzte Werkst\u00e4tten Wohnheime",
    "sg:phone":"+41 13814426",
    "sg:postcode":"8032",
    "sg:province":"Z\u00fcrich",
    "wof:name":"Verein Werkst\u00e4tte Drahtzug",
    "wof:placetype":"venue"
},
  "geometry": {"coordinates":[8.5635480881,47.359500885],"type":"Point"}
}