{
  "type": "Feature",
  "properties": {
    "iso:country":"CH",
    "sg:address":"F\u00e4rberstrasse 33",
    "sg:city":"Z\u00fcrich",
    "sg:orig_category":"Herstellung von Duft U K\u00f6rperpflegemitteln",
    "sg:phone":"+41 18251530",
    "sg:postcode":"8008",
    "sg:province":"Z\u00fcrich",
    "wof:name":"P & R Corporation Ltd",
    "wof:placetype":"venue"
},
  "geometry": {"coordinates":[8.5498981476,47.3622512817],"type":"Point"}
}