{
  "type": "Feature",
  "properties": {
    "iso:country":"CH",
    "sg:address":"Kantonsstrasse 51",
    "sg:city":"Horw",
    "sg:orig_category":"Erbringung von Dienstleistungen f\u00fcr Unternehmen",
    "sg:postcode":"6048",
    "sg:province":"Luzern",
    "wof:name":"Deco-concept Sa",
    "wof:placetype":"venue"
},
  "geometry": {"coordinates":[6.8568668365,46.4530258179],"type":"Point"}
}