{
  "type": "Feature",
  "properties": {
    "iso:country":"CH",
    "sg:address":"Rue Du Bann\u00e9 29",
    "sg:city":"Porrentruy",
    "sg:orig_category":"Herstellung U Zusammensetzung von Uhren S\u00e4ge, Hobel U Holzimpr\u00e4gnierwerke",
    "sg:postcode":"2900",
    "sg:province":"Jura",
    "wof:name":"Rothenb\u00fchler Fran\u00e7ois",
    "wof:placetype":"venue"
},
  "geometry": {"coordinates":[7.0758738518,47.4106330872],"type":"Point"}
}