{
  "type": "Feature",
  "properties": {
    "iso:country":"CH",
    "sg:address":"Ringstrasse",
    "sg:city":"Agarn",
    "sg:orig_category":"Non-Classified Establishments",
    "sg:phone":"+41 55 442 10 29",
    "sg:postcode":"3951",
    "sg:province":"Valais",
    "wof:name":"Kalchofner Alfred & Co",
    "wof:placetype":"venue"
},
  "geometry": {"coordinates":[8.8509311676,47.1932182312],"type":"Point"}
}