{
  "type": "Feature",
  "properties": {
    "iso:country":"CH",
    "sg:address":"Sch\u00e4renmoosstrasse 105 8000 Z\u00fcrich. Postfach",
    "sg:city":"Seebach",
    "sg:orig_category":"Mit dem Versicherungsgewerbe verbundene T\u00e4tigkeiten",
    "sg:postcode":"8052",
    "sg:province":"Z\u00fcrich",
    "wof:name":"Veran Sutter + Sutter",
    "wof:placetype":"venue"
},
  "geometry": {"coordinates":[9.3518724442,47.4116821289],"type":"Point"}
}