{
  "type": "Feature",
  "properties": {
    "iso:country":"CH",
    "sg:address":"Dubematt 2",
    "sg:city":"Rain",
    "sg:orig_category":"Sanit\u00e4r, Heizungs U L\u00fcftungsinstallation Sanit\u00e4rinstallation",
    "sg:phone":"+41 31 332 26 26",
    "sg:postcode":"6026",
    "sg:province":"Luzern",
    "wof:name":"Eugen Ziehli & Co. Ag",
    "wof:placetype":"venue"
},
  "geometry": {"coordinates":[7.4481358528,46.9575576782],"type":"Point"}
}