{
  "type": "Feature",
  "properties": {
    "iso:country":"CH",
    "sg:address":"Aur\u00fctelistrasse 4",
    "sg:city":"Felben",
    "sg:orig_category":"Oberfl\u00e4chenveredlung U W\u00e4rmebehandlung",
    "sg:phone":"+41 62 929 41 16",
    "sg:postcode":"8552",
    "sg:province":"Thurgau",
    "wof:name":"Bot, B\u00e4ttig Bruno",
    "wof:placetype":"venue"
},
  "geometry": {"coordinates":[7.8286237717,47.2341651917],"type":"Point"}
}