{
  "type": "Feature",
  "properties": {
    "iso:country":"CH",
    "sg:address":"Apfhalterstrasse 41",
    "sg:city":"Muttenz",
    "sg:orig_category":"Fahrschulen, Flugschulen",
    "sg:phone":"+41 61 461 47 70",
    "sg:postcode":"4132",
    "sg:province":"Basel-Landschaft",
    "wof:name":"Fritz Steiner Autofahrschule",
    "wof:placetype":"venue"
},
  "geometry": {"coordinates":[7.6428880692,47.5324783325],"type":"Point"}
}