{
  "type": "Feature",
  "properties": {
    "iso:country":"CH",
    "sg:address":"Budron En A 14",
    "sg:city":"Mont-sur-lausanne",
    "sg:orig_category":"Erbringung von Dienstleistungen f\u00fcr Unternehmen",
    "sg:phone":"+41 21 652 15 10",
    "sg:postcode":"1052",
    "sg:province":"Vaud",
    "wof:name":"Ac-modul Design S\u00e0rl",
    "wof:placetype":"venue"
},
  "geometry": {"coordinates":[6.6302809715,46.5706710815],"type":"Point"}
}