{
  "type": "Feature",
  "properties": {
    "iso:country":"CH",
    "sg:address":"Oberwilerweg 62",
    "sg:city":"Rothrist",
    "sg:orig_category":"Softwareentwicklung U beratung",
    "sg:phone":"+41 62 794 37 81",
    "sg:postcode":"4852",
    "sg:province":"Aargau",
    "wof:name":"Bucher Software",
    "wof:placetype":"venue"
},
  "geometry": {"coordinates":[7.8711218834,47.2988967896],"type":"Point"}
}