{
  "type": "Feature",
  "properties": {
    "iso:country":"CH",
    "sg:address":"Zugerland Einkaufszentrum",
    "sg:city":"Steinhausen",
    "sg:orig_category":"Non-Classified Establishments",
    "sg:postcode":"6312",
    "sg:province":"Zug",
    "wof:name":"Drogerie Moser",
    "wof:placetype":"venue"
},
  "geometry": {"coordinates":[8.2733049393,47.3495101929],"type":"Point"}
}