{
  "type": "Feature",
  "properties": {
    "iso:country":"CH",
    "sg:address":"Solothurnstrasse 35",
    "sg:city":"Bettlach",
    "sg:orig_category":"Gasth\u00f6fe/Gasth\u00e4user mit Restaurant Kongress- and Tagungshotels mit Restaurant",
    "sg:phone":"+41 32 645 12 12",
    "sg:postcode":"2544",
    "sg:province":"Solothurn",
    "wof:name":"Landgasthof St.urs & Viktor",
    "wof:placetype":"venue"
},
  "geometry": {"coordinates":[7.4282069206,47.1980667114],"type":"Point"}
}