{
  "type": "Feature",
  "properties": {
    "addr:full":"Brunnenstrasse 10 Uster Z\u00fcrich 8610",
    "addr:housenumber":"10",
    "addr:postcode":"8610",
    "addr:street":"Brunnenstrasse",
    "iso:country":"CH",
    "sg:address":"Brunnenstrasse 10",
    "sg:city":"Uster",
    "sg:orig_category":"Datenbanken Softwareentwicklung U beratung",
    "sg:phone":"+41 19400370",
    "sg:postcode":"8610",
    "sg:province":"Z\u00fcrich",
    "wof:name":"Nicolaus Busch Edv",
    "wof:placetype":"venue"
},
  "geometry": {"coordinates":[8.720733,47.350536],"type":"Point"}
}