{
  "type": "Feature",
  "properties": {
    "iso:country":"CH",
    "sg:address":"Hinterzweienstrasse 26",
    "sg:city":"Muttenz",
    "sg:orig_category":"K\u00fcnstlerische Schulen",
    "sg:phone":"+41 61 461 15 23",
    "sg:postcode":"4132",
    "sg:province":"Basel-Landschaft",
    "wof:name":"Maria Fischer Musikschule",
    "wof:placetype":"venue"
},
  "geometry": {"coordinates":[7.6415920258,47.5258979797],"type":"Point"}
}