{
  "type": "Feature",
  "properties": {
    "iso:country":"CH",
    "sg:address":"4021 Basel. Postfach",
    "sg:city":"Basel",
    "sg:classifiers":[
        {
            "category":"Autos & Motor Vehicles",
            "subcategory":"Recreational Vehicle Sales",
            "type":"Retail Goods"
        }
    ],
    "sg:phone":"+41 61 361 88 77",
    "sg:postcode":"4021",
    "sg:tags":[
        "sportvereine",
        "go-kart",
        "kart"
    ],
    "wof:name":"Kart-driver-team Basel",
    "wof:placetype":"venue"
},
  "geometry": {"coordinates":[7.587679863,47.548740387],"type":"Point"}
}