{
  "type": "Feature",
  "properties": {
    "iso:country":"CH",
    "sg:address":"Bachstrasse 11",
    "sg:city":"Oberstammheim",
    "sg:orig_category":"Elektroinstallation",
    "sg:phone":"+41 52 745 18 80",
    "sg:postcode":"8477",
    "sg:province":"Z\u00fcrich",
    "wof:name":"Elektro Ag Stammheimertal",
    "wof:placetype":"venue"
},
  "geometry": {"coordinates":[8.7979888916,47.6320571899],"type":"Point"}
}