{
  "type": "Feature",
  "properties": {
    "iso:country":"CH",
    "sg:address":"Tscharnerstrasse 3",
    "sg:city":"Zollikofen",
    "sg:orig_category":"Gesundheitswesen",
    "sg:postcode":"3052",
    "sg:province":"Bern",
    "wof:name":"Sozial-psychiatrischer Spitex Amherd",
    "wof:placetype":"venue"
},
  "geometry": {"coordinates":[7.4473719597,46.9977149963],"type":"Point"}
}