{
  "type": "Feature",
  "properties": {
    "iso:country":"CH",
    "sg:address":"Bernstrasse 33",
    "sg:city":"B\u00fctzberg",
    "sg:orig_category":"RESTAURANTS: TEA-ROOMS",
    "sg:postcode":"4922",
    "sg:province":"Bern",
    "wof:name":"Sch\u00e4r Alfred",
    "wof:placetype":"venue"
},
  "geometry": {"coordinates":[7.7536468506,47.3325576782],"type":"Point"}
}