{
  "type": "Feature",
  "properties": {
    "iso:country":"CH",
    "sg:address":"1143",
    "sg:city":"Apples",
    "sg:orig_category":"Mechanik",
    "sg:phone":"+41 21 800 43 77",
    "sg:postcode":"1143",
    "sg:province":"Vaud",
    "wof:name":"Rectasev Sa",
    "wof:placetype":"venue"
},
  "geometry": {"coordinates":[6.4290990829,46.5518035889],"type":"Point"}
}