{
  "type": "Feature",
  "properties": {
    "iso:country":"CH",
    "sg:address":"Spiezstrasse",
    "sg:city":"Krattigen",
    "sg:orig_category":"Geb\u00e4ude, Wohnungsreinigung",
    "sg:phone":"+41 79 354 45 02",
    "sg:postcode":"3704",
    "sg:province":"Bern",
    "wof:name":"Rolf Gr\u00e4nacher Hauswartungen",
    "wof:placetype":"venue"
},
  "geometry": {"coordinates":[8.3508825302,47.3495635986],"type":"Point"}
}