{
  "type": "Feature",
  "properties": {
    "iso:country":"CH",
    "sg:address":"Route De Vevey",
    "sg:city":"Ch\u00e2tel-st-denis",
    "sg:classifiers":[
        {
            "category":"Government",
            "subcategory":"Post Office",
            "type":"Public Place"
        }
    ],
    "sg:phone":"+41 21 948 81 80",
    "sg:postcode":"1618",
    "sg:province":"Fribourg",
    "sg:tags":[
        "caf\u00e9s",
        "tea-rooms"
    ],
    "wof:name":"Bar \u00e0 Caf\u00e9 Le Milord",
    "wof:placetype":"venue"
},
  "geometry": {"coordinates":[6.9005699158,46.526424408],"type":"Point"}
}