{
  "type": "Feature",
  "properties": {
    "iso:country":"CH",
    "sg:address":"Bramantino Via 15 6600 Locarno. Postfach",
    "sg:city":"Locarno",
    "sg:orig_category":"Erschliessung von Grundst\u00fccken",
    "sg:postcode":"6600",
    "sg:province":"Ticino",
    "wof:name":"Saleggio Coop Costruzione Personale Federale",
    "wof:placetype":"venue"
},
  "geometry": {"coordinates":[8.7976608276,46.1667747498],"type":"Point"}
}