{
  "type": "Feature",
  "properties": {
    "addr:full":"Baselstrasse 56 Luzern Luzern 6003",
    "addr:housenumber":"56",
    "addr:postcode":"6003",
    "addr:street":"Baselstrasse",
    "iso:country":"CH",
    "sg:address":"Baselstrasse 56",
    "sg:city":"Luzern",
    "sg:orig_category":"Architektur U Ingenieurb\u00fcros",
    "sg:postcode":"6003",
    "sg:province":"Luzern",
    "wof:name":"Architekturb\u00fcro Sch\u00f6pfer Bruno Dipl. Arch. Htl Stv",
    "wof:placetype":"venue"
},
  "geometry": {"coordinates":[8.29404,47.053593],"type":"Point"}
}