{
  "type": "Feature",
  "properties": {
    "iso:country":"CH",
    "sg:address":"Stade Rue Du 1",
    "sg:city":"Boncourt",
    "sg:orig_category":"Unclassifiable Establishments",
    "sg:phone":"+41 32 953 19 36",
    "sg:postcode":"2926",
    "sg:province":"Jura",
    "wof:name":"Dousse Dominique",
    "wof:placetype":"venue"
},
  "geometry": {"coordinates":[6.9507842064,47.2144851685],"type":"Point"}
}