{
  "type": "Feature",
  "properties": {
    "iso:country":"CH",
    "sg:address":"Seilerstrasse 19",
    "sg:city":"Hitzkirch",
    "sg:orig_category":"Elektroinstallation",
    "sg:phone":"+41 41 919 90 90",
    "sg:postcode":"6285",
    "sg:province":"Luzern",
    "wof:name":"M\u00fcller Elektro Hitzkirch Ag",
    "wof:placetype":"venue"
},
  "geometry": {"coordinates":[8.2598552704,47.2203178406],"type":"Point"}
}