{
  "type": "Feature",
  "properties": {
    "iso:country":"CH",
    "sg:address":"Hotel Seiler Au Lac 3806 B\u00f6nigen. Postfach",
    "sg:city":"B\u00f6nigen",
    "sg:classifiers":[
        {
            "category":"Travel",
            "subcategory":"Hotels & Motels",
            "type":"Entertainment"
        }
    ],
    "sg:postcode":"3806",
    "sg:province":"Bern",
    "sg:tags":[
        "hotels",
        "mit",
        "restaurant"
    ],
    "wof:name":"Zisler, L\u00fczza",
    "wof:placetype":"venue"
},
  "geometry": {"coordinates":[9.8209104538,46.7938690186],"type":"Point"}
}