{
  "type": "Feature",
  "properties": {
    "iso:country":"CH",
    "sg:address":"3912",
    "sg:city":"Termen",
    "sg:orig_category":"Landesverteidigung, Sozialversicherung \u00d6ffentliche Verwaltung",
    "sg:phone":"+41 62 776 30 46",
    "sg:postcode":"3912",
    "sg:province":"Valais",
    "wof:name":"Zivilschutzstelle Teufenthal",
    "wof:placetype":"venue"
},
  "geometry": {"coordinates":[8.1267595291,47.328540802],"type":"Point"}
}