{
  "type": "Feature",
  "properties": {
    "iso:country":"CH",
    "sg:address":"Lausanne Route De 138",
    "sg:city":"Prangins",
    "sg:orig_category":"Unternehmensberatung",
    "sg:phone":"+41 21 728 91 47",
    "sg:postcode":"1197",
    "sg:province":"Vaud",
    "wof:name":"Grw Consulting Sa",
    "wof:placetype":"venue"
},
  "geometry": {"coordinates":[6.2472920418,46.3876953125],"type":"Point"}
}