{
  "type": "Feature",
  "properties": {
    "iso:country":"CH",
    "sg:address":"Gumprechtstr. 38",
    "sg:city":"Emmetten",
    "sg:orig_category":"Unternehmensberatung",
    "sg:phone":"+41 41 622 08 64",
    "sg:postcode":"6376",
    "sg:province":"Nidwalden",
    "wof:name":"Lippeck System Consult",
    "wof:placetype":"venue"
},
  "geometry": {"coordinates":[8.5145788193,46.9591636658],"type":"Point"}
}