{
  "type": "Feature",
  "properties": {
    "iso:country":"CH",
    "sg:address":"Buchsackerstrasse 20",
    "sg:city":"Dietikon",
    "sg:orig_category":"Sportvereine Triathlon Laufen, Schwimmen, Velo",
    "sg:postcode":"8953",
    "sg:province":"Z\u00fcrich",
    "wof:name":"Club Triathlon Du Chablais",
    "wof:placetype":"venue"
},
  "geometry": {"coordinates":[6.928689003,46.2804374695],"type":"Point"}
}