{
  "type": "Feature",
  "properties": {
    "iso:country":"CH",
    "sg:address":"Gstaadstrasse",
    "sg:city":"Saanen",
    "sg:orig_category":"Zahnarztpraxen",
    "sg:phone":"+41 33 748 73 73",
    "sg:postcode":"3792",
    "sg:province":"Bern",
    "wof:name":"Dr.med.dent.christian Tritten Zahnarzt",
    "wof:placetype":"venue"
},
  "geometry": {"coordinates":[7.2651309967,46.4884529114],"type":"Point"}
}