{
  "type": "Feature",
  "properties": {
    "iso:country":"CH",
    "sg:address":"Laufenburgerstrasse 1",
    "sg:city":"Eiken",
    "sg:orig_category":"Berufliche Weiterbildung, Erwachsenenbildung",
    "sg:phone":"+41 62 865 10 70",
    "sg:postcode":"5074",
    "sg:province":"Aargau",
    "wof:name":"Kantonales Zivilschutz- Ausbildungszentrum",
    "wof:placetype":"venue"
},
  "geometry": {"coordinates":[7.986358,47.536797],"type":"Point"}
}