{
  "type": "Feature",
  "properties": {
    "iso:country":"CH",
    "sg:address":"Grand-m\u00e9zel Place Du 10 1204 Gen\u00e8ve. Postfach",
    "sg:city":"Gen\u00e8ve",
    "sg:orig_category":"Unclassifiable Establishments",
    "sg:postcode":"1204",
    "sg:province":"Gen\u00e8ve",
    "wof:name":"Societe Des Immeubles Du Grand-mezel Nos 2, 4 Et 6",
    "wof:placetype":"venue"
},
  "geometry": {"coordinates":[6.1443309784,46.202003479],"type":"Point"}
}