{
  "type": "Feature",
  "properties": {
    "iso:country":"CH",
    "sg:address":"Brunnernstrasse 11",
    "sg:city":"Niederurnen",
    "sg:orig_category":"G\u00fcterbef\u00f6rderung im Strassenverkehr",
    "sg:phone":"+41 55 610 17 42",
    "sg:postcode":"8867",
    "sg:province":"Glarus",
    "wof:name":"Lienhard K. Transport Ag.",
    "wof:placetype":"venue"
},
  "geometry": {"coordinates":[9.0554561615,47.1294250488],"type":"Point"}
}