{
  "type": "Feature",
  "properties": {
    "iso:country":"CH",
    "sg:address":"Hauptstrasse 41",
    "sg:city":"B\u00e4ttwil",
    "sg:orig_category":"Physiotherapie",
    "sg:phone":"+41 61 731 33 73",
    "sg:postcode":"4112",
    "sg:province":"Solothurn",
    "wof:name":"Ursula Brogle Physiotherapie",
    "wof:placetype":"venue"
},
  "geometry": {"coordinates":[7.5071821213,47.4899597168],"type":"Point"}
}