{
  "type": "Feature",
  "properties": {
    "iso:country":"CH",
    "sg:address":"8638",
    "sg:city":"Goldingen",
    "sg:orig_category":"Schulpflegen",
    "sg:phone":"+41 71 385 50 94",
    "sg:postcode":"8638",
    "sg:province":"St. Gallen",
    "wof:name":"Schulrat Der Gemeinde Gossau",
    "wof:placetype":"venue"
},
  "geometry": {"coordinates":[9.2502555847,47.4146461487],"type":"Point"}
}