{
  "type": "Feature",
  "properties": {
    "addr:full":"Riedweg 11 Bern Bern 3012",
    "addr:housenumber":"11",
    "addr:postcode":"3012",
    "addr:street":"Riedweg",
    "iso:country":"CH",
    "sg:address":"Riedweg 11",
    "sg:city":"Bern",
    "sg:classifiers":[
        {
            "category":"Social Services",
            "subcategory":"Retirement Home",
            "type":"Services"
        }
    ],
    "sg:phone":"+41 31 309 91 11",
    "sg:postcode":"3012",
    "sg:province":"Bern",
    "sg:tags":[
        "pflegeheime",
        "u",
        "alters"
    ],
    "wof:name":"Engeried Alterswohnheim",
    "wof:placetype":"venue"
},
  "geometry": {"coordinates":[7.436512,46.959846],"type":"Point"}
}