{
  "type": "Feature",
  "properties": {
    "iso:country":"CH",
    "sg:address":"Rte De L'industrie 43",
    "sg:city":"Sion",
    "sg:orig_category":"Pensionskassen",
    "sg:phone":"+41 27 324 07 11",
    "sg:postcode":"1950",
    "sg:province":"Valais",
    "wof:name":"Fondation De Pr\u00e9voyance En Faveur Du Personnel De La Soci\u00e9t\u00e9 Traitement Electronique De L'information Sa",
    "wof:placetype":"venue"
},
  "geometry": {"coordinates":[7.3675408363,46.2279014587],"type":"Point"}
}