{
  "type": "Feature",
  "properties": {
    "iso:country":"CH",
    "sg:address":"Im Rotl\u00e4nd 7",
    "sg:city":"Fl\u00fch",
    "sg:orig_category":"Detailhandel mit Sportartikeln Fachdetailhandel in Verkaufsr\u00e4umen",
    "sg:phone":"+41 61 731 17 76",
    "sg:postcode":"4112",
    "sg:province":"Solothurn",
    "wof:name":"Sandro-sport",
    "wof:placetype":"venue"
},
  "geometry": {"coordinates":[7.4962921143,47.4829216003],"type":"Point"}
}