{
  "type": "Feature",
  "properties": {
    "iso:country":"CH",
    "sg:address":"Tschuopisstrasse 16",
    "sg:city":"Altendorf",
    "sg:orig_category":"Elektroinstallation Mechanische Werkst\u00e4tten",
    "sg:phone":"+41 56 282 21 15",
    "sg:postcode":"8852",
    "sg:province":"Schwyz",
    "wof:name":"Salath\u00e9 & Co",
    "wof:placetype":"venue"
},
  "geometry": {"coordinates":[8.2826013565,47.4986915588],"type":"Point"}
}