{
  "type": "Feature",
  "properties": {
    "iso:country":"CH",
    "sg:address":"Route Gouttes-d'or 5",
    "sg:city":"Neuch\u00e2tel",
    "sg:orig_category":"Fotografische Ateliers Fotografisches Gewerbe U fotografische Laboratorien",
    "sg:phone":"+41 32 724 76 46",
    "sg:postcode":"2000",
    "sg:province":"Neuch\u00e2tel",
    "wof:name":"Von Allmen Jo\u00ebl Photographe S\u00e0rl",
    "wof:placetype":"venue"
},
  "geometry": {"coordinates":[6.941450119,46.9826812744],"type":"Point"}
}