{
  "type": "Feature",
  "properties": {
    "iso:country":"CH",
    "sg:address":"Rte Du Bugnon 39",
    "sg:city":"Fribourg",
    "sg:orig_category":"RESTAURANTS: TEA-ROOMS",
    "sg:postcode":"1700",
    "sg:province":"Fribourg",
    "wof:name":"Caf\u00e9-restaurant Les Dailles, Risse M.",
    "wof:placetype":"venue"
},
  "geometry": {"coordinates":[7.1536831856,46.8037452698],"type":"Point"}
}