{
  "type": "Feature",
  "properties": {
    "iso:country":"CH",
    "sg:address":"Sennhofstrasse 12",
    "sg:city":"Chur",
    "sg:orig_category":"Erschliessung von Grundst\u00fccken",
    "sg:postcode":"7000",
    "sg:province":"Graubunden",
    "wof:name":"Wohnbaugenossenschaft Stiva",
    "wof:placetype":"venue"
},
  "geometry": {"coordinates":[9.5340929031,46.8492431641],"type":"Point"}
}