{
  "type": "Feature",
  "properties": {
    "addr:full":"Via Cresperone 7d Breganzona Ticino 6932",
    "addr:housenumber":"7d",
    "addr:postcode":"6932",
    "addr:street":"Via Cresperone",
    "iso:country":"CH",
    "sg:address":"Via Cresperone 7d",
    "sg:city":"Breganzona",
    "sg:orig_category":"Betrieb von Taxis",
    "sg:phone":"+41 91 966 22 22",
    "sg:postcode":"6932",
    "sg:province":"Ticino",
    "wof:name":"Jehudi Willimann Tassi",
    "wof:placetype":"venue"
},
  "geometry": {"coordinates":[8.929264,46.015202],"type":"Point"}
}