{
  "type": "Feature",
  "properties": {
    "iso:country":"CH",
    "sg:address":"Thalstrasse 11",
    "sg:city":"Kloten",
    "sg:orig_category":"RESTAURANTS: TEA-ROOMS",
    "sg:postcode":"8302",
    "sg:province":"Z\u00fcrich",
    "wof:name":"Kundert Rina, Rest. Paragraph 11.",
    "wof:placetype":"venue"
},
  "geometry": {"coordinates":[8.8182096481,47.2278671265],"type":"Point"}
}