{
  "type": "Feature",
  "properties": {
    "iso:country":"CH",
    "sg:address":"Nelkenstrasse 15",
    "sg:city":"Z\u00fcrich",
    "sg:orig_category":"Unternehmensberatung",
    "sg:phone":"+41 13611717",
    "sg:postcode":"8006",
    "sg:province":"Z\u00fcrich",
    "wof:name":"M\u00fcller Elisabeth A. Consultant Unternehmensberatung Usw.",
    "wof:placetype":"venue"
},
  "geometry": {"coordinates":[8.5467557907,47.3821105957],"type":"Point"}
}