{
  "type": "Feature",
  "properties": {
    "iso:country":"CH",
    "sg:address":"St. Gallerstrasse 82 8400 Winterthur. Postfach 932",
    "sg:city":"Winterthur",
    "sg:orig_category":"Architektur U Ingenieurb\u00fcros Grosshandel mit B\u00fcromaschinen",
    "sg:phone":"+41 52 238 09 09",
    "sg:postcode":"8401",
    "sg:province":"Z\u00fcrich",
    "wof:name":"Hauri Hard & Software Ingenieurb\u00fcro",
    "wof:placetype":"venue"
},
  "geometry": {"coordinates":[8.744567,47.498081],"type":"Point"}
}