{
  "type": "Feature",
  "properties": {
    "iso:country":"CH",
    "sg:address":"Birchstrasse 2",
    "sg:city":"Seuzach",
    "sg:orig_category":"Vermietung von Automobilen",
    "sg:phone":"+41 71 220 20 30",
    "sg:postcode":"8472",
    "sg:province":"Z\u00fcrich",
    "wof:name":"Herold Autovermietung Ag",
    "wof:placetype":"venue"
},
  "geometry": {"coordinates":[9.3877897263,47.4261054993],"type":"Point"}
}