{
  "type": "Feature",
  "properties": {
    "iso:country":"CH",
    "sg:address":"Mattenstrasse 84",
    "sg:city":"Biel/bienne",
    "sg:orig_category":"Grosshandel mit Textilien",
    "sg:phone":"+41 32 322 52 28",
    "sg:postcode":"2503",
    "sg:province":"Bern",
    "wof:name":"Modeagentur Keller J\u00f6rg",
    "wof:placetype":"venue"
},
  "geometry": {"coordinates":[7.2521910667,47.1351165771],"type":"Point"}
}