{
  "type": "Feature",
  "properties": {
    "addr:full":"Rue P\u00e9pinet 5 Lausanne Vaud 1003",
    "addr:housenumber":"5",
    "addr:postcode":"1003",
    "addr:street":"Rue Pe\u0301Pinet",
    "iso:country":"CH",
    "sg:address":"Rue P\u00e9pinet 5",
    "sg:city":"Lausanne",
    "sg:orig_category":"Detailhandel mit Damenbekleidung",
    "sg:phone":"+41 21 312 12 46",
    "sg:postcode":"1003",
    "sg:province":"Vaud",
    "wof:name":"Christina Br\u00fcgger Boutique",
    "wof:placetype":"venue"
},
  "geometry": {"coordinates":[6.632506,46.52005],"type":"Point"}
}