{
  "type": "Feature",
  "properties": {
    "iso:country":"CH",
    "sg:address":"Sunneggweg 1",
    "sg:city":"Steffisburg",
    "sg:orig_category":"Herstellung U Veredlung von sonstigem Glas Herstellung von Hohlglas",
    "sg:phone":"+41 33 437 08 08",
    "sg:postcode":"3612",
    "sg:province":"Bern",
    "wof:name":"Neonglasbl\u00e4serei B\u00e4rtschi",
    "wof:placetype":"venue"
},
  "geometry": {"coordinates":[7.63458395,46.7822685242],"type":"Point"}
}