{
  "type": "Feature",
  "properties": {
    "iso:country":"CH",
    "sg:address":"Erzenbergstrasse 51",
    "sg:city":"Liestal",
    "sg:orig_category":"Maler U Glasergewerbe",
    "sg:postcode":"4410",
    "sg:province":"Basel-Landschaft",
    "wof:name":"Malergesch\u00e4ft, Imhof + Rudin",
    "wof:placetype":"venue"
},
  "geometry": {"coordinates":[7.7345290184,47.4889984131],"type":"Point"}
}