{
  "type": "Feature",
  "properties": {
    "iso:country":"CH",
    "sg:address":"Cartouchi\u00e8rechemin De La 17",
    "sg:city":"Plan-les-ouates",
    "sg:orig_category":"Instandhaltung U Reparatur von Automobilen",
    "sg:postcode":"1228",
    "sg:province":"Gen\u00e8ve",
    "wof:name":"Balmer Automobiles",
    "wof:placetype":"venue"
},
  "geometry": {"coordinates":[6.1252379417,46.1708221436],"type":"Point"}
}