{
  "type": "Feature",
  "properties": {
    "iso:country":"CH",
    "sg:address":"Siewerdtstrasse 95",
    "sg:city":"Z\u00fcrich",
    "sg:classifiers":[
        {
            "category":"Utilities",
            "subcategory":"Mobile Phone",
            "type":"Services"
        }
    ],
    "sg:phone":"+41 13113311",
    "sg:postcode":"8050",
    "sg:province":"Z\u00fcrich",
    "sg:tags":[
        "decoder",
        "bar-code"
    ],
    "wof:name":"Dataphone Ag",
    "wof:placetype":"venue"
},
  "geometry": {"coordinates":[8.556916,47.412399],"type":"Point"}
}