{
  "type": "Feature",
  "properties": {
    "iso:country":"CH",
    "sg:address":"Schulerslehn",
    "sg:city":"Pfaffnau",
    "sg:orig_category":"Grosshandel mit Obst U Gem\u00fcse",
    "sg:phone":"+41 62 747 07 47",
    "sg:postcode":"6264",
    "sg:province":"Luzern",
    "wof:name":"Via Verde Ag",
    "wof:placetype":"venue"
},
  "geometry": {"coordinates":[7.9059419632,47.2418785095],"type":"Point"}
}