{
  "type": "Feature",
  "properties": {
    "iso:country":"CH",
    "sg:address":"Goldauerstrasse 7",
    "sg:city":"Steinen",
    "sg:orig_category":"Handels-H\u00e4user U Gesellschaften",
    "sg:postcode":"6422",
    "sg:province":"Schwyz",
    "wof:name":"Etesa Ag",
    "wof:placetype":"venue"
},
  "geometry": {"coordinates":[8.5993795395,47.0484848022],"type":"Point"}
}