{
  "type": "Feature",
  "properties": {
    "iso:country":"CH",
    "sg:address":"Via Alla Campagna 4 6900 Lugano. Postfach",
    "sg:city":"Lugano",
    "sg:orig_category":"Softwareentwicklung U beratung",
    "sg:phone":"+41 41 670 11 80",
    "sg:postcode":"6900",
    "sg:province":"Ticino",
    "wof:name":"Dreams & Emotion, Von Atzigen Guido",
    "wof:placetype":"venue"
},
  "geometry": {"coordinates":[8.2704515457,46.9383583069],"type":"Point"}
}