{
  "type": "Feature",
  "properties": {
    "iso:country":"CH",
    "sg:address":"B\u00e4renloch 1",
    "sg:city":"Chur",
    "sg:orig_category":"G\u00fcterbef\u00f6rderung im Strassenverkehr",
    "sg:phone":"+41 81 253 51 91",
    "sg:postcode":"7000",
    "sg:province":"Graubunden",
    "wof:name":"Hartmann Silvio",
    "wof:placetype":"venue"
},
  "geometry": {"coordinates":[9.5325145721,46.8478965759],"type":"Point"}
}