{
  "type": "Feature",
  "properties": {
    "iso:country":"CH",
    "sg:address":"Eglantines Impasse Des 1 1700 Fribourg. Postfach",
    "sg:city":"Fribourg",
    "sg:orig_category":"Interessenvertretungen",
    "sg:postcode":"1700",
    "sg:province":"Fribourg",
    "wof:name":"Fondation Emploi Et Solidarit\u00e9 Lutter Contre L'exclusion Au Nom Des Droits Fondamentaux De La Personne Humaine",
    "wof:placetype":"venue"
},
  "geometry": {"coordinates":[7.1723389626,46.8086280823],"type":"Point"}
}