{
  "type": "Feature",
  "properties": {
    "iso:country":"CH",
    "sg:address":"Werdstrasse 17",
    "sg:city":"Winterthur",
    "sg:classifiers":[
        {
            "category":"Building & Trades",
            "subcategory":"Construction",
            "type":"Services"
        }
    ],
    "sg:phone":"+41 52 233 54 00",
    "sg:postcode":"8405",
    "sg:province":"Z\u00fcrich",
    "sg:tags":[
        "installation",
        "air-conditioning",
        "system"
    ],
    "wof:name":"Widmann Ag",
    "wof:placetype":"venue"
},
  "geometry": {"coordinates":[8.760622,47.485535],"type":"Point"}
}