{
  "type": "Feature",
  "properties": {
    "iso:country":"CH",
    "sg:address":"Schulgasse 12",
    "sg:city":"Therwil",
    "sg:orig_category":"Instandhaltung U Reparatur von Automobilen",
    "sg:phone":"+41 61 721 26 26",
    "sg:postcode":"4106",
    "sg:province":"Basel-Landschaft",
    "wof:name":"Garage Wagner-cottiati Werner",
    "wof:placetype":"venue"
},
  "geometry": {"coordinates":[7.5520629883,47.50025177],"type":"Point"}
}