{
  "type": "Feature",
  "properties": {
    "addr:full":"Werkstrasse 33 Beringen Schaffhausen 8222",
    "addr:housenumber":"33",
    "addr:postcode":"8222",
    "addr:street":"Werkstrasse",
    "iso:country":"CH",
    "sg:address":"Werkstrasse 33",
    "sg:city":"Beringen",
    "sg:orig_category":"Bauschreinerei",
    "sg:phone":"+41 79 349 04 67",
    "sg:postcode":"8222",
    "sg:province":"Schaffhausen",
    "wof:name":"Hans Waldmeier Schreinerei",
    "wof:placetype":"venue"
},
  "geometry": {"coordinates":[8.568179,47.694183],"type":"Point"}
}