{
  "type": "Feature",
  "properties": {
    "iso:country":"CH",
    "sg:address":"3979",
    "sg:city":"Gr\u00f4ne",
    "sg:orig_category":"Fahrschulen, Flugschulen Vermietung von Automobilen",
    "sg:phone":"+41 21 625 13 25",
    "sg:postcode":"3979",
    "sg:province":"Valais",
    "wof:name":"Eurodriving Center Jean-pierre Pahud",
    "wof:placetype":"venue"
},
  "geometry": {"coordinates":[6.6164979935,46.5210952759],"type":"Point"}
}