{
  "type": "Feature",
  "properties": {
    "iso:country":"CH",
    "sg:address":"Weichlenstrasse 5",
    "sg:city":"Turgi",
    "sg:orig_category":"Sonstige Aktivit\u00e4ten der nicht-\u00e4rztlichen Medizinalberufe",
    "sg:phone":"+41 56 223 41 22",
    "sg:postcode":"5300",
    "sg:province":"Aargau",
    "wof:name":"Pia Rindlisbacher Kinesiologie-& Massagepraxis",
    "wof:placetype":"venue"
},
  "geometry": {"coordinates":[8.2540254593,47.4908676147],"type":"Point"}
}