{
  "type": "Feature",
  "properties": {
    "iso:country":"CH",
    "sg:address":"Konradstrasse 51 8005 Z\u00fcrich. Postfach",
    "sg:city":"Z\u00fcrich",
    "sg:orig_category":"Offsetdruck",
    "sg:phone":"+41 12713520",
    "sg:postcode":"8031",
    "sg:province":"Z\u00fcrich",
    "wof:name":"Ferrari Druck Z\u00fcrich Buchdruckerei.",
    "wof:placetype":"venue"
},
  "geometry": {"coordinates":[8.534765,47.381069],"type":"Point"}
}