{
  "type": "Feature",
  "properties": {
    "iso:country":"CH",
    "sg:address":"Chemin Du Ruttet 5 1196 Gland. Postfach",
    "sg:city":"Gland",
    "sg:orig_category":"RESTAURANTS: TEA-ROOMS",
    "sg:postcode":"1196",
    "sg:province":"Vaud",
    "wof:name":"Magdolna Nemeth",
    "wof:placetype":"venue"
},
  "geometry": {"coordinates":[6.2733712196,46.4222717285],"type":"Point"}
}