{
  "type": "Feature",
  "properties": {
    "addr:full":"Hauptstrasse 43 3860 Meiringen. Postfach Meiringen Bern 3860",
    "addr:housenumber":"43",
    "addr:postcode":"3860 meiringen. postfach;3860",
    "addr:street":"Hauptstrasse",
    "iso:country":"CH",
    "sg:address":"Hauptstrasse 43 3860 Meiringen. Postfach",
    "sg:city":"Meiringen",
    "sg:orig_category":"Allgemeiner Hoch U Tiefbau",
    "sg:postcode":"3860",
    "sg:province":"Bern",
    "wof:name":"Handwork Ruef Gmbh Handwerkliche T\u00e4tigkeiten U. Dienstleistungen, Bes. Geb\u00e4uderenovationen Usw.",
    "wof:placetype":"venue"
},
  "geometry": {"coordinates":[8.180484,46.729691],"type":"Point"}
}