{
  "type": "Feature",
  "properties": {
    "iso:country":"CH",
    "sg:address":"Rue Saint-georges 7",
    "sg:city":"Del\u00e9mont",
    "sg:orig_category":"Giessereiindustrie Herstellung von Metallerzeugnissen ohne Maschinenbau",
    "sg:phone":"+41 32 341 74 44",
    "sg:postcode":"2800",
    "sg:province":"Jura",
    "wof:name":"Von Roll Stahlgiesserei Biel Ag",
    "wof:placetype":"venue"
},
  "geometry": {"coordinates":[7.2877287865,47.1575431824],"type":"Point"}
}