{
  "type": "Feature",
  "properties": {
    "iso:country":"CH",
    "sg:address":"Haffnerstrasse 33",
    "sg:city":"Solothurn",
    "sg:orig_category":"Sonderschulen",
    "sg:phone":"+41 32 621 13 22",
    "sg:postcode":"4500",
    "sg:province":"Solothurn",
    "wof:name":"Heilp\u00e4dagogische Sonderschule",
    "wof:placetype":"venue"
},
  "geometry": {"coordinates":[7.5286860466,47.2165184021],"type":"Point"}
}