{
  "type": "Feature",
  "properties": {
    "iso:country":"CH",
    "sg:address":"Bleiki 2",
    "sg:city":"Stein Am Rhein",
    "sg:orig_category":"Medien, Kleinanzeigen",
    "sg:postcode":"8260",
    "sg:province":"Schaffhausen",
    "wof:name":"It Is Time To Worship Him - Mount Herron Studios",
    "wof:placetype":"venue"
},
  "geometry": {"coordinates":[8.872315,47.669785],"type":"Point"}
}