{
  "type": "Feature",
  "properties": {
    "iso:country":"CH",
    "sg:address":"Rosentalstrasse 55",
    "sg:city":"Winterthur",
    "sg:orig_category":"Verwaltung von Immobilien Wirtschaftspr\u00fcfung, Steuerberatung U Treuhand",
    "sg:phone":"+41 79 431 78 10",
    "sg:postcode":"8400",
    "sg:province":"Z\u00fcrich",
    "wof:name":"Humar Treuhand Huggenberger",
    "wof:placetype":"venue"
},
  "geometry": {"coordinates":[8.3260908127,47.4630432129],"type":"Point"}
}