{
  "type": "Feature",
  "properties": {
    "iso:country":"CH",
    "sg:address":"Lyssachstrasse 9b",
    "sg:city":"Burgdorf",
    "sg:orig_category":"Physiotherapie",
    "sg:phone":"+41 34 422 95 77",
    "sg:postcode":"3400",
    "sg:province":"Bern",
    "wof:name":"Physiotherapie Kohler",
    "wof:placetype":"venue"
},
  "geometry": {"coordinates":[7.6241979599,47.0583839417],"type":"Point"}
}