{
  "type": "Feature",
  "properties": {
    "iso:country":"CH",
    "sg:address":"Frankenstrasse 3",
    "sg:city":"Luzern",
    "sg:orig_category":"Kinderkrippen U horte",
    "sg:postcode":"6003",
    "sg:province":"Luzern",
    "wof:name":"Kinderstube Des Schweiz. Gemeinn\u00fctzigen Frauenvereins",
    "wof:placetype":"venue"
},
  "geometry": {"coordinates":[8.3090982437,47.049282074],"type":"Point"}
}