{
  "type": "Feature",
  "properties": {
    "iso:country":"CH",
    "sg:address":"Alte Kantonsstrasse 8",
    "sg:city":"B\u00fcron",
    "sg:orig_category":"Sonstige Aktivit\u00e4ten der nicht-\u00e4rztlichen Medizinalberufe",
    "sg:phone":"+41 41 933 25 58",
    "sg:postcode":"6233",
    "sg:province":"Luzern",
    "wof:name":"Rita Kirchhofer Natur\u00e4rztin",
    "wof:placetype":"venue"
},
  "geometry": {"coordinates":[8.0975208282,47.2095947266],"type":"Point"}
}