{
  "type": "Feature",
  "properties": {
    "iso:country":"CH",
    "sg:address":"Thunstrasse 7 3110 M\u00fcnsingen. Postfach 1208",
    "sg:city":"M\u00fcnsingen",
    "sg:orig_category":"Instandhaltung U Reparatur von Automobilen Mechanische Werkst\u00e4tten",
    "sg:phone":"+41 31 724 15 15",
    "sg:postcode":"3110",
    "sg:province":"Bern",
    "wof:name":"Garage Marti Ag",
    "wof:placetype":"venue"
},
  "geometry": {"coordinates":[7.5626740456,46.8733444214],"type":"Point"}
}