{
  "type": "Feature",
  "properties": {
    "iso:country":"CH",
    "sg:address":"Obernauerstrasse 41",
    "sg:city":"Kriens",
    "sg:classifiers":[
        {
            "category":"Restaurant",
            "type":"Food & Drink"
        }
    ],
    "sg:phone":"+41 41 320 20 20",
    "sg:postcode":"6010",
    "sg:province":"Luzern",
    "wof:name":"Restaurant Minerva",
    "wof:placetype":"venue"
},
  "geometry": {"coordinates":[8.2659378052,47.0341682434],"type":"Point"}
}