{
  "type": "Feature",
  "properties": {
    "iso:country":"CH",
    "sg:address":"Adligenswilerstrasse 101",
    "sg:city":"Ebikon",
    "sg:orig_category":"Fahrschulen, Flugschulen",
    "sg:phone":"+41 41 440 73 73",
    "sg:postcode":"6030",
    "sg:province":"Luzern",
    "wof:name":"Ruedi & Marlis Bernet Fahrschule City",
    "wof:placetype":"venue"
},
  "geometry": {"coordinates":[8.3369474411,47.0709266663],"type":"Point"}
}