{
  "type": "Feature",
  "properties": {
    "iso:country":"CH",
    "sg:address":"Frikartstrasse 2",
    "sg:city":"Zofingen",
    "sg:orig_category":"Mit dem Versicherungsgewerbe verbundene T\u00e4tigkeiten",
    "sg:postcode":"4800",
    "sg:province":"Aargau",
    "wof:name":"Mitscherlich Florian S.j., Lic. Jur.",
    "wof:placetype":"venue"
},
  "geometry": {"coordinates":[8.5977201462,47.381439209],"type":"Point"}
}