{
  "type": "Feature",
  "properties": {
    "iso:country":"CH",
    "sg:address":"Untere Austrasse 8",
    "sg:city":"Eichberg",
    "sg:orig_category":"Elektroinstallation",
    "sg:phone":"+41 71 755 62 30",
    "sg:postcode":"9453",
    "sg:province":"St. Gallen",
    "wof:name":"Elektro Schlegel",
    "wof:placetype":"venue"
},
  "geometry": {"coordinates":[9.5319681168,47.3413276672],"type":"Point"}
}