{
  "type": "Feature",
  "properties": {
    "iso:country":"CH",
    "sg:address":"Avenue Dumas 25c",
    "sg:city":"Gen\u00e8ve",
    "sg:orig_category":"Primarschulen",
    "sg:phone":"+41 22 346 43 61",
    "sg:postcode":"1206",
    "sg:province":"Gen\u00e8ve",
    "wof:name":"Ecole Primaire Dumas",
    "wof:placetype":"venue"
},
  "geometry": {"coordinates":[6.1577110291,46.1903266907],"type":"Point"}
}