{
  "type": "Feature",
  "properties": {
    "iso:country":"CH",
    "sg:address":"Via Falveng 16 7013 Domat/ems. Postfach 197",
    "sg:city":"Domat/ems",
    "sg:orig_category":"Sanit\u00e4r, Heizungs U L\u00fcftungsinstallation Sanit\u00e4rinstallation",
    "sg:phone":"+41 31 335 82 82",
    "sg:postcode":"7013",
    "sg:province":"Graubunden",
    "wof:name":"Sulzer Infra Westschweiz Ag Zweigniederlassung Bern",
    "wof:placetype":"venue"
},
  "geometry": {"coordinates":[7.4576678276,46.9553375244],"type":"Point"}
}