{
  "type": "Feature",
  "properties": {
    "iso:country":"CH",
    "sg:address":"4625",
    "sg:city":"Oberbuchsiten",
    "sg:orig_category":"Vereine Gesang",
    "sg:phone":"+41 34 445 74 74",
    "sg:postcode":"4625",
    "sg:province":"Solothurn",
    "wof:name":"M\u00e4nnerchor Oberburg",
    "wof:placetype":"venue"
},
  "geometry": {"coordinates":[7.5874061584,47.0852546692],"type":"Point"}
}