{
  "type": "Feature",
  "properties": {
    "iso:country":"CH",
    "sg:address":"Z\u00fcrcherstrasse 9",
    "sg:city":"Hedingen",
    "sg:orig_category":"Detailhandel mit Antiquit\u00e4ten",
    "sg:phone":"+41 17610513",
    "sg:postcode":"8908",
    "sg:province":"Z\u00fcrich",
    "wof:name":"Franz K\u00fchne Antiquit\u00e4ten",
    "wof:placetype":"venue"
},
  "geometry": {"coordinates":[8.448003,47.298191],"type":"Point"}
}