{
  "type": "Feature",
  "properties": {
    "iso:country":"CH",
    "sg:address":"Rue Du L\u00e9man 10 1820 Montreux. Postfach",
    "sg:city":"Clarens",
    "sg:classifiers":[
        {
            "category":"Professional",
            "subcategory":"Employment Agencies",
            "type":"Services"
        }
    ],
    "sg:postcode":"1815",
    "sg:province":"Vaud",
    "sg:tags":[
        "personal",
        "u",
        "stellenvermittlung"
    ],
    "wof:name":"Artline Models Anita Landis",
    "wof:placetype":"venue"
},
  "geometry": {"coordinates":[8.4492082596,47.2748146057],"type":"Point"}
}