{
  "type": "Feature",
  "properties": {
    "iso:country":"CH",
    "sg:address":"Rue Des Ecoles 1",
    "sg:city":"Martigny",
    "sg:orig_category":"Architekturb\u00fcros",
    "sg:phone":"+41 79 301 41 45",
    "sg:postcode":"1920",
    "sg:province":"Valais",
    "wof:name":"Armand Oreiller Bureau D'architecture",
    "wof:placetype":"venue"
},
  "geometry": {"coordinates":[7.071818,46.101067],"type":"Point"}
}