{
  "type": "Feature",
  "properties": {
    "iso:country":"CH",
    "sg:address":"G\u00fcrbeweg 20",
    "sg:city":"Belp",
    "sg:orig_category":"Werbegrafikateliers",
    "sg:phone":"+41 31 819 34 28",
    "sg:postcode":"3123",
    "sg:province":"Bern",
    "wof:name":"Grafic Studio Stettler",
    "wof:placetype":"venue"
},
  "geometry": {"coordinates":[7.4970030785,46.8914871216],"type":"Point"}
}