{
  "type": "Feature",
  "properties": {
    "iso:country":"CH",
    "sg:address":"Zeughausgasse 9",
    "sg:city":"Zug",
    "sg:orig_category":"Unclassifiable Establishments",
    "sg:postcode":"6300",
    "sg:province":"Zug",
    "wof:name":"Kip, Knoblauch Ingenieur Und Planer",
    "wof:placetype":"venue"
},
  "geometry": {"coordinates":[8.2784585953,47.3474273682],"type":"Point"}
}