{
  "type": "Feature",
  "properties": {
    "iso:country":"CH",
    "sg:address":"J\u00f6riacherstrasse 3 5242 Birr. Postfach 55",
    "sg:city":"Birr",
    "sg:orig_category":"Erbringung von Dienstleistungen f\u00fcr Unternehmen Siebdruck",
    "sg:phone":"+41 56 444 87 41",
    "sg:postcode":"5242",
    "sg:province":"Aargau",
    "wof:name":"Schriften Huber",
    "wof:placetype":"venue"
},
  "geometry": {"coordinates":[8.2155447006,47.4293327332],"type":"Point"}
}