{
  "type": "Feature",
  "properties": {
    "iso:country":"CH",
    "sg:address":"Industriestr. 6",
    "sg:city":"Dierikon",
    "sg:classifiers":[
        {
            "category":"Professional",
            "subcategory":"Engineering",
            "type":"Services"
        }
    ],
    "sg:phone":"+41 56 463 65 65",
    "sg:postcode":"6036",
    "sg:province":"Luzern",
    "sg:tags":[
        "electric",
        "-",
        "component",
        "machine",
        "mechanical",
        "electronic"
    ],
    "wof:name":"Mabi Ag",
    "wof:placetype":"venue"
},
  "geometry": {"coordinates":[8.1584196091,47.4368743896],"type":"Point"}
}