{
  "type": "Feature",
  "properties": {
    "iso:country":"CH",
    "sg:address":"Viale Cattori 11",
    "sg:city":"Paradiso",
    "sg:orig_category":"Vermittlung von Immobilien Verwaltung von Immobilien",
    "sg:phone":"+41 91 994 25 64",
    "sg:postcode":"6900",
    "sg:province":"Ticino",
    "wof:name":"Studio Immobiliare Sandra Comolatti",
    "wof:placetype":"venue"
},
  "geometry": {"coordinates":[8.9440021515,45.9921798706],"type":"Point"}
}