{
  "type": "Feature",
  "properties": {
    "iso:country":"CH",
    "sg:address":"Nussbaumerstrasse 5",
    "sg:city":"Sch\u00f6nenwerd",
    "sg:orig_category":"Sportvereine Ballsport Handball",
    "sg:phone":"+41 62 849 38 56",
    "sg:postcode":"5012",
    "sg:province":"Solothurn",
    "wof:name":"Fides Niderg\u00f6sgen",
    "wof:placetype":"venue"
},
  "geometry": {"coordinates":[8.0038719177,47.3686103821],"type":"Point"}
}