{
  "type": "Feature",
  "properties": {
    "iso:country":"CH",
    "sg:address":"Aarbergstrasse 21 2500 Biel/bienne. Postfach",
    "sg:city":"Biel/bienne",
    "sg:orig_category":"RESTAURANTS: TEA-ROOMS",
    "sg:postcode":"2503",
    "sg:province":"Bern",
    "wof:name":"Disler Rosita.",
    "wof:placetype":"venue"
},
  "geometry": {"coordinates":[7.2397289276,47.1303710938],"type":"Point"}
}