{
  "type": "Feature",
  "properties": {
    "iso:country":"CH",
    "sg:address":"Juden Ost",
    "sg:city":"Raron",
    "sg:orig_category":"Herstellung von sonstigen Metallwaren",
    "sg:postcode":"3942",
    "sg:province":"Valais",
    "wof:name":"Zes Zinn/etains Service, Dill Marcelle",
    "wof:placetype":"venue"
},
  "geometry": {"coordinates":[7.8045158386,46.3096733093],"type":"Point"}
}