{
  "type": "Feature",
  "properties": {
    "iso:country":"CH",
    "sg:address":"1372",
    "sg:city":"Bavois",
    "sg:orig_category":"Unclassifiable Establishments",
    "sg:postcode":"1372",
    "sg:province":"Vaud",
    "wof:name":"Lumat, Lorusso",
    "wof:placetype":"venue"
},
  "geometry": {"coordinates":[6.565223217,46.6858901978],"type":"Point"}
}