{
  "type": "Feature",
  "properties": {
    "iso:country":"CH",
    "sg:address":"Avenue De France 6",
    "sg:city":"Sion",
    "sg:classifiers":[
        {
            "category":"Professional",
            "subcategory":"Employment Agencies",
            "type":"Services"
        }
    ],
    "sg:postcode":"1950",
    "sg:province":"Valais",
    "sg:tags":[
        "personal",
        "u",
        "stellenvermittlung"
    ],
    "wof:name":"Gti Gestion Du Travail Int\u00e9rimaire Sa",
    "wof:placetype":"venue"
},
  "geometry": {"coordinates":[7.358235836,46.228187561],"type":"Point"}
}