{
  "type": "Feature",
  "properties": {
    "iso:country":"CH",
    "sg:address":"Seestrasse 201 8708 M\u00e4nnedorf. Postfach 957",
    "sg:city":"M\u00e4nnedorf",
    "sg:orig_category":"Konkurs- and Betreibungs\u00e4mter",
    "sg:phone":"+41 19201162",
    "sg:postcode":"8708",
    "sg:province":"Z\u00fcrich",
    "wof:name":"Betreibungsamt",
    "wof:placetype":"venue"
},
  "geometry": {"coordinates":[8.6900072098,47.253112793],"type":"Point"}
}