{
  "type": "Feature",
  "properties": {
    "addr:full":"Bielstrasse 14 Kappelen Bern 3273",
    "addr:housenumber":"14",
    "addr:postcode":"3273",
    "addr:street":"Bielstrasse",
    "iso:country":"CH",
    "sg:address":"Bielstrasse 14",
    "sg:city":"Kappelen",
    "sg:orig_category":"Bauschreinerei",
    "sg:phone":"+41 18693393",
    "sg:postcode":"3273",
    "sg:province":"Bern",
    "wof:name":"Schreinerei Eugen Kramer",
    "wof:placetype":"venue"
},
  "geometry": {"coordinates":[8.503062,47.602787],"type":"Point"}
}