{
  "type": "Feature",
  "properties": {
    "iso:country":"CH",
    "sg:address":"Lehmattweg 12",
    "sg:city":"F\u00fcllinsdorf",
    "sg:orig_category":"Bauingenieurb\u00fcros Heizung L\u00fcftung Klima Herstellung von Elektromotoren, Generatoren U Transformatore",
    "sg:postcode":"4414",
    "sg:province":"Basel-Landschaft",
    "wof:name":"Solvatec Gmbh",
    "wof:placetype":"venue"
},
  "geometry": {"coordinates":[7.730616,47.504871],"type":"Point"}
}