{
  "type": "Feature",
  "properties": {
    "iso:country":"CH",
    "sg:address":"Hammerstrasse 105",
    "sg:city":"Basel",
    "sg:orig_category":"Markt U Meinungsforschung",
    "sg:phone":"+41 61 692 41 63",
    "sg:postcode":"4057",
    "sg:province":"Basel-Stadt",
    "wof:name":"B. O. B. Marketing Und Werbung, Ott-bl\u00f6sch Beatrice",
    "wof:placetype":"venue"
},
  "geometry": {"coordinates":[7.595208168,47.5660133362],"type":"Point"}
}