{
  "type": "Feature",
  "properties": {
    "iso:country":"CH",
    "sg:address":"Schulhausstrasse 14b 7323 Wangs. Postfach",
    "sg:city":"Wangs",
    "sg:orig_category":"Sanit\u00e4r, Heizungs U L\u00fcftungsinstallation",
    "sg:phone":"+41 81 723 75 16",
    "sg:postcode":"7323",
    "sg:province":"St. Gallen",
    "wof:name":"Toni Good Ag",
    "wof:placetype":"venue"
},
  "geometry": {"coordinates":[9.4350481033,47.0339279175],"type":"Point"}
}