{
  "type": "Feature",
  "properties": {
    "iso:country":"CH",
    "sg:address":"Alpsteinstrasse 75 9100 Herisau. Postfach",
    "sg:city":"Herisau",
    "sg:orig_category":"Grosshandel mit B\u00fcrom\u00f6beln Sonstige Kurierdienste",
    "sg:phone":"+41 19365950",
    "sg:postcode":"9102",
    "sg:province":"Appenzell Ausserrhoden",
    "wof:name":"Lcs-zulieferservice, Condrau Laurenz A.",
    "wof:placetype":"venue"
},
  "geometry": {"coordinates":[8.7572603226,47.3070106506],"type":"Point"}
}