{
  "type": "Feature",
  "properties": {
    "iso:country":"CH",
    "sg:address":"Gewerbestrasse 3",
    "sg:city":"Langendorf",
    "sg:orig_category":"Vermietung U Verpachtung von eigenen Immobilien",
    "sg:phone":"+41 19301908",
    "sg:postcode":"4513",
    "sg:province":"Solothurn",
    "wof:name":"Weilenmann Th.",
    "wof:placetype":"venue"
},
  "geometry": {"coordinates":[8.7984800339,47.3245201111],"type":"Point"}
}