{
  "type": "Feature",
  "properties": {
    "iso:country":"CH",
    "sg:address":"Ebnaterstrasse 50 9642 Ebnat. Postfach 246",
    "sg:city":"Ebnat",
    "sg:orig_category":"Druck ohne Zeitungsdruck Offsetdruck",
    "sg:phone":"+41 71 993 17 41",
    "sg:postcode":"9642",
    "sg:province":"St. Gallen",
    "wof:name":"Haab C. A.",
    "wof:placetype":"venue"
},
  "geometry": {"coordinates":[9.1266517639,47.2593040466],"type":"Point"}
}