{
  "type": "Feature",
  "properties": {
    "iso:country":"CH",
    "sg:address":"Gartenstrasse 11",
    "sg:city":"Biberist",
    "sg:orig_category":"Feinmechanische and Pr\u00e4zisions Werkst\u00e4tten Herstellung von elektronischen Bauelementen",
    "sg:phone":"+41 32 672 15 91",
    "sg:postcode":"4562",
    "sg:province":"Solothurn",
    "wof:name":"Reto Schmid Sab Schmid Automationselemente",
    "wof:placetype":"venue"
},
  "geometry": {"coordinates":[7.5652427673,47.1837654114],"type":"Point"}
}