{
  "type": "Feature",
  "properties": {
    "iso:country":"CH",
    "sg:address":"Unterneuwilen",
    "sg:city":"Neuwilen",
    "sg:classifiers":[
        {
            "category":"Restaurant",
            "type":"Food & Drink"
        }
    ],
    "sg:phone":"+41 71 699 15 33",
    "sg:postcode":"8566",
    "sg:province":"Thurgau",
    "wof:name":"Gasthof Sch\u00f6ntal",
    "wof:placetype":"venue"
},
  "geometry": {"coordinates":[9.1345405579,47.6218528748],"type":"Point"}
}