{
  "type": "Feature",
  "properties": {
    "iso:country":"CH",
    "sg:address":"Wildsbergstrasse 31",
    "sg:city":"Uster",
    "sg:orig_category":"Softwareentwicklung U beratung",
    "sg:phone":"+41 19945630",
    "sg:postcode":"8610",
    "sg:province":"Z\u00fcrich",
    "wof:name":"Adrian Trapletti Statistical Computing",
    "wof:placetype":"venue"
},
  "geometry": {"coordinates":[8.7001161575,47.3511886597],"type":"Point"}
}