{
  "type": "Feature",
  "properties": {
    "iso:country":"CH",
    "sg:address":"Alte Landstrasse 22",
    "sg:city":"R\u00fcschlikon",
    "sg:orig_category":"Erbringung von Dienstleistungen f\u00fcr Unternehmen",
    "sg:phone":"+41 17155500",
    "sg:postcode":"8803",
    "sg:province":"Z\u00fcrich",
    "wof:name":"Marxer Treuhand",
    "wof:placetype":"venue"
},
  "geometry": {"coordinates":[8.5505828857,47.3125610352],"type":"Point"}
}