{
  "type": "Feature",
  "properties": {
    "iso:country":"CH",
    "sg:address":"Avenue Victor-ruffy 54",
    "sg:city":"Lausanne",
    "sg:orig_category":"Detailhandel mit Waren verschiedener Art, Hauptrichtung Nahrungsmittel Grosshandel mit Obst U Gem\u00fcse",
    "sg:phone":"+41 21 653 59 68",
    "sg:postcode":"1012",
    "sg:province":"Vaud",
    "wof:name":"Fruidale, Ferreira Das Neves Vitor",
    "wof:placetype":"venue"
},
  "geometry": {"coordinates":[6.6486959457,46.5292663574],"type":"Point"}
}