{
  "type": "Feature",
  "properties": {
    "iso:country":"CH",
    "sg:address":"Rue Du Village-suisse 10",
    "sg:city":"Gen\u00e8ve",
    "sg:orig_category":"Betrieb von Taxis",
    "sg:postcode":"1205",
    "sg:province":"Gen\u00e8ve",
    "wof:name":"Coop\u00e9rative Des Exploitants De Taxis De La R\u00e9gion Lausannoise",
    "wof:placetype":"venue"
},
  "geometry": {"coordinates":[6.57939,46.539082],"type":"Point"}
}