{
  "type": "Feature",
  "properties": {
    "iso:country":"CH",
    "sg:address":"Austrasse 50",
    "sg:city":"Triesenberg",
    "sg:classifiers":[
        {
            "category":"Banks & Credit Unions",
            "subcategory":"Bank",
            "type":"Services"
        }
    ],
    "sg:postcode":"9497",
    "wof:name":"Immobilien Du Th\u00e9\u00e2tre",
    "wof:placetype":"venue"
},
  "geometry": {"coordinates":[8.30437,47.049541],"type":"Point"}
}