{
  "type": "Feature",
  "properties": {
    "iso:country":"CH",
    "sg:address":"St. Margrethenstrasse 23",
    "sg:city":"Chur",
    "sg:orig_category":"Herstellung von konfektionierten Textilwaren ohne Bekleidung",
    "sg:phone":"+41 81 252 11 84",
    "sg:postcode":"7000",
    "sg:province":"Graubunden",
    "wof:name":"Couture Rahel, G\u00f6tz-vollenweider",
    "wof:placetype":"venue"
},
  "geometry": {"coordinates":[9.5274295807,46.8472633362],"type":"Point"}
}