{
  "type": "Feature",
  "properties": {
    "iso:country":"CH",
    "sg:address":"Bahnhofstrasse 102",
    "sg:city":"Aarau",
    "sg:orig_category":"Advertising Gifts Of Glass",
    "sg:phone":"+41 71 220 61 55",
    "sg:postcode":"5000",
    "sg:province":"Aargau",
    "wof:name":"Classic Decor Gmbh",
    "wof:placetype":"venue"
},
  "geometry": {"coordinates":[9.373298,47.421394],"type":"Point"}
}