{
  "type": "Feature",
  "properties": {
    "iso:country":"CH",
    "sg:address":"Allschwilerstrasse 106",
    "sg:city":"Basel",
    "sg:orig_category":"Pensionskassen",
    "sg:phone":"+41 61 307 33 33",
    "sg:postcode":"4055",
    "sg:province":"Basel-Stadt",
    "wof:name":"Personalf\u00fcrsorgestiftung Der Marcel Fischer Ag",
    "wof:placetype":"venue"
},
  "geometry": {"coordinates":[7.5666742325,47.5573387146],"type":"Point"}
}