{
  "type": "Feature",
  "properties": {
    "iso:country":"CH",
    "sg:address":"Bahnhofstrasse 14 8001 Z\u00fcrich. Postfach",
    "sg:city":"Z\u00fcrich",
    "sg:orig_category":"Detailhandel mit Uhren U Schmuck Fachdetailhandel in Verkaufsr\u00e4umen",
    "sg:phone":"+41 12111010",
    "sg:postcode":"8022",
    "sg:province":"Z\u00fcrich",
    "wof:name":"Tiffany And Company, New York, Zweigniederlassung Z\u00fcrich",
    "wof:placetype":"venue"
},
  "geometry": {"coordinates":[8.5399999619,47.3682365417],"type":"Point"}
}