{
  "type": "Feature",
  "properties": {
    "iso:country":"CH",
    "sg:address":"Nussbaumallee 6",
    "sg:city":"G\u00fcmligen",
    "sg:orig_category":"Institutionen f\u00fcr Behinderte Sonderschulen",
    "sg:phone":"+41 31 951 77 11",
    "sg:postcode":"3073",
    "sg:province":"Bern",
    "wof:name":"Sonderschulheim Aarhus Bern",
    "wof:placetype":"venue"
},
  "geometry": {"coordinates":[7.5156979561,46.9314231873],"type":"Point"}
}