{
  "type": "Feature",
  "properties": {
    "iso:country":"CH",
    "sg:address":"Schreinerstrasse 7",
    "sg:city":"St.gallen",
    "sg:orig_category":"Herstellung von medizinischen U chirurgischen Ger\u00e4ten sowie orthop\u00e4dischen Vorrichtungen",
    "sg:phone":"+41 71 222 27 23",
    "sg:postcode":"9000",
    "sg:province":"St. Gallen",
    "wof:name":"Mri Schreinerstrasse, Rodald",
    "wof:placetype":"venue"
},
  "geometry": {"coordinates":[9.3736743927,47.4218673706],"type":"Point"}
}