{
  "type": "Feature",
  "properties": {
    "iso:country":"CH",
    "sg:address":"En Rebaton",
    "sg:city":"Bottens",
    "sg:orig_category":"Fotografische Ateliers Korrespondenz U Nachrichtenb\u00fcros",
    "sg:phone":"+41 21 881 32 62",
    "sg:postcode":"1041",
    "sg:province":"Vaud",
    "wof:name":"Jean-guy Python Photographe De Presse",
    "wof:placetype":"venue"
},
  "geometry": {"coordinates":[6.661711216,46.6150436401],"type":"Point"}
}