{
  "type": "Feature",
  "properties": {
    "iso:country":"CH",
    "sg:address":"Steinistrasse",
    "sg:city":"Stadel",
    "sg:orig_category":"Allgemeiner Hoch U Tiefbau",
    "sg:postcode":"8174",
    "sg:province":"Z\u00fcrich",
    "wof:name":"Spezial Pipeline Service Duin J.",
    "wof:placetype":"venue"
},
  "geometry": {"coordinates":[8.88788,47.590221],"type":"Point"}
}