{
  "type": "Feature",
  "properties": {
    "iso:country":"CH",
    "sg:address":"Malvoisins Rue Des 15",
    "sg:city":"Porrentruy",
    "sg:classifiers":[
        {
            "category":"Travel",
            "subcategory":"Hotels & Motels",
            "type":"Entertainment"
        }
    ],
    "sg:phone":"+41 32 466 18 27",
    "sg:postcode":"2900",
    "sg:province":"Jura",
    "sg:tags":[
        "hotels",
        "mit",
        "restaurant"
    ],
    "wof:name":"Edith Grossniklaus",
    "wof:placetype":"venue"
},
  "geometry": {"coordinates":[7.0735478401,47.4170379639],"type":"Point"}
}