{
  "type": "Feature",
  "properties": {
    "iso:country":"CH",
    "sg:address":"Zollstrasse 86a",
    "sg:city":"Neuhausen",
    "sg:orig_category":"Tankstellen",
    "sg:postcode":"8212",
    "sg:province":"Schaffhausen",
    "wof:name":"Agip-garage N. Canzoniere.",
    "wof:placetype":"venue"
},
  "geometry": {"coordinates":[7.361427784,47.1805725098],"type":"Point"}
}