{
  "type": "Feature",
  "properties": {
    "iso:country":"CH",
    "sg:address":"Scie Route De La 3",
    "sg:city":"Estavayer-le-lac",
    "sg:orig_category":"Instandhaltung U Reparatur von Automobilen",
    "sg:phone":"+41 26 663 44 64",
    "sg:postcode":"1470",
    "sg:province":"Fribourg",
    "wof:name":"Garage F. Blazquez S\u00e0rl",
    "wof:placetype":"venue"
},
  "geometry": {"coordinates":[6.8482789993,46.8487930298],"type":"Point"}
}