{
  "type": "Feature",
  "properties": {
    "iso:country":"CH",
    "sg:address":"Hohfuristrasse 9",
    "sg:city":"B\u00fclach",
    "sg:orig_category":"Malerei",
    "sg:phone":"+41 18606351",
    "sg:postcode":"8180",
    "sg:province":"Z\u00fcrich",
    "wof:name":"Walter Br\u00e4m Malergesch\u00e4ft",
    "wof:placetype":"venue"
},
  "geometry": {"coordinates":[8.542593956,47.5274925232],"type":"Point"}
}