{
  "type": "Feature",
  "properties": {
    "iso:country":"CH",
    "sg:address":"Neu Simplonstasse 38",
    "sg:city":"Brig",
    "sg:orig_category":"Herstellung von Konstruktionsteilen, Fertigbauteilen U Ausbauelementen aus Holz",
    "sg:phone":"+41 27 922 47 11",
    "sg:postcode":"3900",
    "sg:province":"Valais",
    "wof:name":"Klafs Saunabau Ag Athletic Sport Equipment",
    "wof:placetype":"venue"
},
  "geometry": {"coordinates":[7.9917478561,46.3129959106],"type":"Point"}
}