{
  "type": "Feature",
  "properties": {
    "iso:country":"CH",
    "sg:address":"Nidaugasse 60",
    "sg:city":"Biel/bienne",
    "sg:orig_category":"Detailhandel mit Zeitungen U Zeitschriften Kioske",
    "sg:phone":"+41 32 322 69 29",
    "sg:postcode":"2502",
    "sg:province":"Bern",
    "wof:name":"Tina Schmid Kiosk Modesty",
    "wof:placetype":"venue"
},
  "geometry": {"coordinates":[7.2465391159,47.1381111145],"type":"Point"}
}