{
  "type": "Feature",
  "properties": {
    "iso:country":"CH",
    "sg:address":"Alte Landstrasse 70",
    "sg:city":"R\u00fcschlikon",
    "sg:classifiers":[
        {
            "category":"Professional",
            "subcategory":"Advertising",
            "type":"Services"
        }
    ],
    "sg:phone":"+41 17242420",
    "sg:postcode":"8803",
    "sg:province":"Z\u00fcrich",
    "sg:tags":[
        "film"
    ],
    "wof:name":"Metro-film",
    "wof:placetype":"venue"
},
  "geometry": {"coordinates":[8.553682,47.306431],"type":"Point"}
}