{
  "type": "Feature",
  "properties": {
    "iso:country":"CH",
    "sg:address":"Haltenstrasse 90",
    "sg:city":"Niederscherli",
    "sg:orig_category":"Architekturb\u00fcros",
    "sg:phone":"+41 55 410 26 54",
    "sg:postcode":"3145",
    "sg:province":"Bern",
    "wof:name":"Ernst Mettler Architekturb\u00fcro",
    "wof:placetype":"venue"
},
  "geometry": {"coordinates":[8.790095,47.202148],"type":"Point"}
}