{
  "type": "Feature",
  "properties": {
    "iso:country":"CH",
    "sg:address":"H\u00f6henweg 6 5040 Sch\u00f6ftland. Postfach",
    "sg:city":"Sch\u00f6ftland",
    "sg:orig_category":"Vermietung U Verpachtung von eigenen Immobilien",
    "sg:postcode":"5040",
    "sg:province":"Aargau",
    "wof:name":"Merag Immobilien Gmbh",
    "wof:placetype":"venue"
},
  "geometry": {"coordinates":[8.0554256439,47.3068084717],"type":"Point"}
}