{
  "type": "Feature",
  "properties": {
    "iso:country":"CH",
    "sg:address":"Luzernerstrasse 36",
    "sg:city":"Ebikon",
    "sg:orig_category":"Fotografische Ateliers",
    "sg:phone":"+41 41 420 30 02",
    "sg:postcode":"6030",
    "sg:province":"Luzern",
    "wof:name":"Daniel Frischherz Fotoreportagen",
    "wof:placetype":"venue"
},
  "geometry": {"coordinates":[8.3283700943,47.0742988586],"type":"Point"}
}