{
  "type": "Feature",
  "properties": {
    "iso:country":"CH",
    "sg:address":"Buchlenweg 6 3033 Wohlen B. Bern. Postfach",
    "sg:city":"Uettligen",
    "sg:orig_category":"Interessenvertretungen",
    "sg:postcode":"3043",
    "sg:province":"Bern",
    "wof:name":"Fortissimo, Stiftung Zur Unterst\u00fctzung Notleidender, Freischaffender Berufsmusikerinnen, Berufsmusiker Und Ihrer Angeh\u00f6rigen",
    "wof:placetype":"venue"
},
  "geometry": {"coordinates":[7.3561701775,46.9711647034],"type":"Point"}
}