{
  "type": "Feature",
  "properties": {
    "iso:country":"CH",
    "sg:address":"Grenzweg 1 3097 Liebefeld. Postfach 108",
    "sg:city":"Liebefeld",
    "sg:orig_category":"Vermittlung von Immobilien Verwaltung von Immobilien",
    "sg:phone":"+41 31 972 21 22",
    "sg:postcode":"3097",
    "sg:province":"Bern",
    "wof:name":"M\u00f6ssinger & Sohn, Immobilien-treuh\u00e4nder, Nachfolger: Herbert M\u00f6ssinger",
    "wof:placetype":"venue"
},
  "geometry": {"coordinates":[7.4230108261,46.9339065552],"type":"Point"}
}