{
  "type": "Feature",
  "properties": {
    "iso:country":"CH",
    "sg:address":"Rorschacherstrasse 5",
    "sg:city":"Steinach",
    "sg:orig_category":"Instandhaltung U Reparatur von Automobilen",
    "sg:phone":"+41 71 446 34 80",
    "sg:postcode":"9323",
    "sg:province":"St. Gallen",
    "wof:name":"Gm\u00fcnder Andreas",
    "wof:placetype":"venue"
},
  "geometry": {"coordinates":[9.433590889,47.4927253723],"type":"Point"}
}