{
  "type": "Feature",
  "properties": {
    "iso:country":"CH",
    "sg:address":"Ritterweg 5",
    "sg:city":"Sarnen",
    "sg:orig_category":"Detailhandel mit Beleuchtungs U Haushaltsgegenst\u00e4nden Innendekorationsateliers",
    "sg:phone":"+41 41 660 18 12",
    "sg:postcode":"6060",
    "sg:province":"Obwalden",
    "wof:name":"Paula Gasser Vorhanggesch\u00e4ft",
    "wof:placetype":"venue"
},
  "geometry": {"coordinates":[8.24795,46.893532],"type":"Point"}
}