{
  "type": "Feature",
  "properties": {
    "iso:country":"CH",
    "sg:address":"Rosengarten 8882 Unterterzen. Postfach",
    "sg:city":"Unterterzen",
    "sg:orig_category":"HOTELS: MIT RESTAURANT Unternehmensberatung",
    "sg:phone":"+41 81 710 33 00",
    "sg:postcode":"8882",
    "sg:province":"St. Gallen",
    "wof:name":"Jop Jossi Und Partnerinnen Gmbh Ausbildungsseminare, Kurse Usw.; Entwicklung, Durchf\u00fchrung, Verkauf, Vermittlung",
    "wof:placetype":"venue"
},
  "geometry": {"coordinates":[9.2409515381,47.11277771],"type":"Point"}
}