{
  "type": "Feature",
  "properties": {
    "addr:full":"Haus Sonne 7243 Pany. Postfach Pany Graubunden 7243",
    "addr:housenumber":"7243",
    "addr:postcode":"7243",
    "addr:street":"Pany. Postfach;Graubunden",
    "iso:country":"CH",
    "sg:address":"Haus Sonne 7243 Pany. Postfach",
    "sg:city":"Pany",
    "sg:orig_category":"Detailhandel mit Brot, Back U S\u00fcsswaren",
    "sg:postcode":"7243",
    "sg:province":"Graubunden",
    "wof:name":"Josef Gemperle",
    "wof:placetype":"venue"
},
  "geometry": {"coordinates":[9.770413,46.92836],"type":"Point"}
}