{
  "type": "Feature",
  "properties": {
    "iso:country":"CH",
    "sg:address":"T\u00fc\u00fcffegass 2 8226 Schleitheim. Postfach 110",
    "sg:city":"Schleitheim",
    "sg:orig_category":"Grosshandel mit medizinischen U orthop\u00e4dischen Artikeln Herstellung von medizinischen U chirurgische",
    "sg:phone":"+41 52 680 16 43",
    "sg:postcode":"8226",
    "sg:province":"Schaffhausen",
    "wof:name":"Ermed Ag",
    "wof:placetype":"venue"
},
  "geometry": {"coordinates":[8.4845428467,47.7506027222],"type":"Point"}
}