{
  "type": "Feature",
  "properties": {
    "addr:full":"Asphof M\u00fcnchenstein Basel-Landschaft 4142",
    "addr:postcode":"4142",
    "iso:country":"CH",
    "sg:address":"Asphof",
    "sg:city":"M\u00fcnchenstein",
    "sg:orig_category":"Architektur U Ingenieurb\u00fcros Architekturb\u00fcros",
    "sg:phone":"+41 61 411 00 88",
    "sg:postcode":"4142",
    "sg:province":"Basel-Landschaft",
    "wof:name":"Architektur Stalder Rolf Ag",
    "wof:placetype":"venue"
},
  "geometry": {"coordinates":[7.627936,47.517952],"type":"Point"}
}