{
  "type": "Feature",
  "properties": {
    "iso:country":"CH",
    "sg:address":"7402",
    "sg:city":"Bonaduz",
    "sg:orig_category":"Primarschulen",
    "sg:phone":"+41 81 641 17 60",
    "sg:postcode":"7402",
    "sg:province":"Graubunden",
    "wof:name":"Primarschule Am Plaz",
    "wof:placetype":"venue"
},
  "geometry": {"coordinates":[9.3999795914,46.8113365173],"type":"Point"}
}