{
  "type": "Feature",
  "properties": {
    "iso:country":"CH",
    "sg:address":"Risibuck 107",
    "sg:city":"Buchberg",
    "sg:orig_category":"Allgemeiner Gartenbau Dienstleistungen im Gartenbau",
    "sg:phone":"+41 79 227 50 86",
    "sg:postcode":"8454",
    "sg:province":"Schaffhausen",
    "wof:name":"Nanchen Pierre Paysagiste-arboriculteur",
    "wof:placetype":"venue"
},
  "geometry": {"coordinates":[7.028702,47.047382],"type":"Point"}
}