{
  "type": "Feature",
  "properties": {
    "iso:country":"CH",
    "sg:address":"Kalberweidli 2",
    "sg:city":"Schenkon",
    "sg:orig_category":"Grosshandel mit Erzen U Metallen",
    "sg:phone":"+41 41 921 77 70",
    "sg:postcode":"6214",
    "sg:province":"Luzern",
    "wof:name":"G. Rohner Ag Eisenwaren Engros",
    "wof:placetype":"venue"
},
  "geometry": {"coordinates":[8.138297081,47.1724777222],"type":"Point"}
}