{
  "type": "Feature",
  "properties": {
    "iso:country":"CH",
    "sg:address":"Jussy Route De 8 1226 Th\u00f4nex. Postfach",
    "sg:city":"Th\u00f4nex",
    "sg:orig_category":"RESTAURANTS: TEA-ROOMS",
    "sg:postcode":"1226",
    "sg:province":"Gen\u00e8ve",
    "wof:name":"Lois Duran Mercedes Restaurant Da Reno",
    "wof:placetype":"venue"
},
  "geometry": {"coordinates":[6.1982450485,46.1879501343],"type":"Point"}
}