{
  "type": "Feature",
  "properties": {
    "iso:country":"CH",
    "sg:address":"Rue Charles-humbert 9",
    "sg:city":"Gen\u00e8ve",
    "sg:orig_category":"Politische Parteien CVP",
    "sg:phone":"+41 27 322 15 37",
    "sg:postcode":"1205",
    "sg:province":"Gen\u00e8ve",
    "wof:name":"Parti D\u00e9mocrate-chr\u00e9tien Valaisan",
    "wof:placetype":"venue"
},
  "geometry": {"coordinates":[7.3599529266,46.2334365845],"type":"Point"}
}