{
  "type": "Feature",
  "properties": {
    "iso:country":"CH",
    "sg:address":"Fr\u00f6belstrasse 22 8032 Z\u00fcrich. Postfach 8032 Z\u00fcrich",
    "sg:city":"Zust",
    "sg:orig_category":"Betrieb U technische Hilfsdienste des Kultur U Unterhaltungswesens",
    "sg:postcode":"32",
    "wof:name":"Verein Explorer Experience World",
    "wof:placetype":"venue"
},
  "geometry": {"coordinates":[8.566758,47.36108],"type":"Point"}
}