{
  "type": "Feature",
  "properties": {
    "iso:country":"CH",
    "sg:address":"Buggenacher 3 6043 Adligenswil. Postfach 423",
    "sg:city":"Adligenswil",
    "sg:orig_category":"Instandhaltung U Reparatur von Automobilen",
    "sg:phone":"+41 41 370 61 40",
    "sg:postcode":"6043",
    "sg:province":"Luzern",
    "wof:name":"Amrein Autospritzwerk Gmbh",
    "wof:placetype":"venue"
},
  "geometry": {"coordinates":[8.3611431122,47.0649986267],"type":"Point"}
}