{
  "type": "Feature",
  "properties": {
    "iso:country":"CH",
    "sg:address":"Solothurnstrasse 122 2504 Biel/bienne. Postfach",
    "sg:city":"Biel/bienne",
    "sg:orig_category":"Handel mit Automobilen",
    "sg:postcode":"2504",
    "sg:province":"Bern",
    "wof:name":"Haag Jean-denis Sa Vente Automobiles",
    "wof:placetype":"venue"
},
  "geometry": {"coordinates":[6.8299050331,47.102809906],"type":"Point"}
}