{
  "type": "Feature",
  "properties": {
    "iso:country":"CH",
    "sg:address":"Zentralstrasse 45 2502 Biel/bienne. Postfach",
    "sg:city":"Biel/bienne",
    "sg:orig_category":"Wirtschaftspr\u00fcfung, Steuerberatung U Treuhand",
    "sg:phone":"+41 32 351 18 22",
    "sg:postcode":"2502",
    "sg:province":"Bern",
    "wof:name":"Treuhand Und Revisionsb\u00fcro Zulauf H.",
    "wof:placetype":"venue"
},
  "geometry": {"coordinates":[7.3765521049,47.1388473511],"type":"Point"}
}