{
  "type": "Feature",
  "properties": {
    "iso:country":"CH",
    "sg:address":"Gotthardstrasse 6454 Fl\u00fcelen. Postfach",
    "sg:city":"Fl\u00fcelen",
    "sg:classifiers":[
        {
            "category":"Travel",
            "subcategory":"Hotels & Motels",
            "type":"Entertainment"
        }
    ],
    "sg:phone":"+41 41 871 03 66",
    "sg:postcode":"6454",
    "sg:province":"Uri",
    "sg:tags":[
        "hotels",
        "mit",
        "restaurant"
    ],
    "wof:name":"N\u00e4f-truttmann A.",
    "wof:placetype":"venue"
},
  "geometry": {"coordinates":[8.6250371933,46.8984184265],"type":"Point"}
}