{
  "type": "Feature",
  "properties": {
    "iso:country":"CH",
    "sg:address":"Ryf 58",
    "sg:city":"Murten",
    "sg:orig_category":"Zahnarztpraxen",
    "sg:phone":"+41 26 670 24 14",
    "sg:postcode":"3280",
    "sg:province":"Fribourg",
    "wof:name":"Dr. Med. Dent. Sigrid Johner Zahn\u00e4rztin",
    "wof:placetype":"venue"
},
  "geometry": {"coordinates":[7.1170701981,46.9297332764],"type":"Point"}
}