{
  "type": "Feature",
  "properties": {
    "iso:country":"CH",
    "sg:address":"Route De La Bl\u00e9cherette 27",
    "sg:city":"Mont-sur-lausanne",
    "sg:orig_category":"Herstellung von Teppichen Verlegen von Fliesen U Platten",
    "sg:phone":"+41 21 652 94 75",
    "sg:postcode":"1052",
    "sg:province":"Vaud",
    "wof:name":"Dupuis C.",
    "wof:placetype":"venue"
},
  "geometry": {"coordinates":[6.6313648224,46.5568237305],"type":"Point"}
}