{
  "type": "Feature",
  "properties": {
    "iso:country":"CH",
    "sg:address":"Dreilindenstrasse 21",
    "sg:city":"Meggen",
    "sg:orig_category":"Vermittlung von Immobilien Wirtschaftspr\u00fcfung, Steuerberatung U Treuhand",
    "sg:phone":"+41 41 370 36 37",
    "sg:postcode":"6045",
    "sg:province":"Luzern",
    "wof:name":"Treuhand Und Revisionsb\u00fcro Thalmann Werner Ag",
    "wof:placetype":"venue"
},
  "geometry": {"coordinates":[8.3670969009,47.0466346741],"type":"Point"}
}