{
  "type": "Feature",
  "properties": {
    "iso:country":"CH",
    "sg:address":"Dorfstrasse 46",
    "sg:city":"Bauma",
    "sg:orig_category":"Regionalbanken U Sparkassen",
    "sg:phone":"+41 55 251 40 50",
    "sg:postcode":"8494",
    "sg:province":"Z\u00fcrich",
    "wof:name":"Sparkasse Z\u00fcrcher Oberland",
    "wof:placetype":"venue"
},
  "geometry": {"coordinates":[8.8515338898,47.2586936951],"type":"Point"}
}