{
  "type": "Feature",
  "properties": {
    "iso:country":"CH",
    "sg:address":"Fellerstrasse 23",
    "sg:city":"Thun",
    "sg:orig_category":"Elektroinstallation",
    "sg:phone":"+41 33 222 24 55",
    "sg:postcode":"3604",
    "sg:province":"Bern",
    "wof:name":"Elektro-& Telefonbau Ag Etag",
    "wof:placetype":"venue"
},
  "geometry": {"coordinates":[7.6171250343,46.7378997803],"type":"Point"}
}