{
  "type": "Feature",
  "properties": {
    "iso:country":"CH",
    "sg:address":"Spalenring 119",
    "sg:city":"Basel",
    "sg:orig_category":"Detailhandel mit Textilien Grosshandel mit Textilien",
    "sg:phone":"+41 61 271 30 73",
    "sg:postcode":"4055",
    "sg:province":"Basel-Stadt",
    "wof:name":"M. Orzel, Inh. Kurt Orzel",
    "wof:placetype":"venue"
},
  "geometry": {"coordinates":[7.5757660866,47.5561141968],"type":"Point"}
}