{
  "type": "Feature",
  "properties": {
    "iso:country":"CH",
    "sg:address":"B\u00fchlmattstrasse 7",
    "sg:city":"Meggen",
    "sg:orig_category":"Unclassifiable Establishments",
    "sg:postcode":"6045",
    "sg:province":"Luzern",
    "wof:name":"Manfredotti Roberto",
    "wof:placetype":"venue"
},
  "geometry": {"coordinates":[10.0616703033,46.3435783386],"type":"Point"}
}