{
  "type": "Feature",
  "properties": {
    "iso:country":"CH",
    "sg:address":"St. Urbanstrasse 3",
    "sg:city":"Langenthal",
    "sg:orig_category":"Advokaturb\u00fcros",
    "sg:phone":"+41 62 922 36 22",
    "sg:postcode":"4900",
    "sg:province":"Bern",
    "wof:name":"Liebi Engler & Partner Advokaturb\u00fcro",
    "wof:placetype":"venue"
},
  "geometry": {"coordinates":[7.789998,47.212257],"type":"Point"}
}