{
  "type": "Feature",
  "properties": {
    "iso:country":"CH",
    "sg:address":"Robiana Via",
    "sg:city":"Besazio",
    "sg:orig_category":"Fussboden, Fliesen U Plattenlegerei, Tapeziererei",
    "sg:postcode":"6863",
    "sg:province":"Ticino",
    "wof:name":"Predei, Pereira Ramiro",
    "wof:placetype":"venue"
},
  "geometry": {"coordinates":[7.2589159012,47.1263885498],"type":"Point"}
}