{
  "type": "Feature",
  "properties": {
    "iso:country":"CH",
    "sg:address":"Piazza Collegiata",
    "sg:city":"Bellinzona",
    "sg:orig_category":"Wirtschaftspr\u00fcfung, Steuerberatung U Treuhand",
    "sg:postcode":"6500",
    "sg:province":"Ticino",
    "wof:name":"Rioto Sa",
    "wof:placetype":"venue"
},
  "geometry": {"coordinates":[9.0230751038,46.1914558411],"type":"Point"}
}