{
  "type": "Feature",
  "properties": {
    "iso:country":"CH",
    "sg:address":"Wynernstrasse 20 5430 Wettingen. Postfach",
    "sg:city":"Wettingen",
    "sg:orig_category":"Non-Classified Establishments",
    "sg:postcode":"5430",
    "sg:province":"Aargau",
    "wof:name":"Utz Kommunikation & Marketing",
    "wof:placetype":"venue"
},
  "geometry": {"coordinates":[8.3285093307,47.4604606628],"type":"Point"}
}