{
  "type": "Feature",
  "properties": {
    "iso:country":"CH",
    "sg:address":"Wissenwegen",
    "sg:city":"Ballwil",
    "sg:orig_category":"Verarbeitung von Milch Verwertung von Milch",
    "sg:postcode":"6275",
    "sg:province":"Luzern",
    "wof:name":"Milchverwertungsgenossenschaft Gibelfl\u00fch",
    "wof:placetype":"venue"
},
  "geometry": {"coordinates":[8.3457546234,47.1532516479],"type":"Point"}
}