{
  "type": "Feature",
  "properties": {
    "iso:country":"CH",
    "sg:address":"Roggia Via Alla 28",
    "sg:city":"Viganello",
    "sg:orig_category":"Non-Classified Establishments",
    "sg:postcode":"6962",
    "sg:province":"Ticino",
    "wof:name":"S & S Service & Service Sa",
    "wof:placetype":"venue"
},
  "geometry": {"coordinates":[8.9657831192,46.0105056763],"type":"Point"}
}