{
  "type": "Feature",
  "properties": {
    "iso:country":"CH",
    "sg:address":"Route De Corminboeuf 37",
    "sg:city":"Belfaux",
    "sg:orig_category":"Herstellung U Zusammensetzung von Uhren",
    "sg:phone":"+41 26 475 13 44",
    "sg:postcode":"1782",
    "sg:province":"Fribourg",
    "wof:name":"Montres Dolmy Sa",
    "wof:placetype":"venue"
},
  "geometry": {"coordinates":[7.1062378883,46.8179931641],"type":"Point"}
}