{
  "type": "Feature",
  "properties": {
    "iso:country":"CH",
    "sg:address":"Grand Faubourg.",
    "sg:city":"Montricher",
    "sg:orig_category":"Sanit\u00e4r, Heizungs U L\u00fcftungsinstallation",
    "sg:phone":"+41 71 243 59 60",
    "sg:postcode":"1147",
    "sg:province":"Vaud",
    "wof:name":"Atel Elektrosanit\u00e4r Ag, Zweigniederlassung Sanit\u00e4r",
    "wof:placetype":"venue"
},
  "geometry": {"coordinates":[9.391242981,47.429107666],"type":"Point"}
}