{
  "type": "Feature",
  "properties": {
    "iso:country":"CH",
    "sg:address":"Heidenhubelstrasse 14",
    "sg:city":"Solothurn",
    "sg:orig_category":"Interessenvertretungen",
    "sg:phone":"+41 32 623 65 84",
    "sg:postcode":"4500",
    "sg:province":"Solothurn",
    "wof:name":"Stiftung Gr\u00fctter-schlatter Albert F\u00fcr Vortragshonorare Der Naturforschenden Gesellschaft Des Kantons Solothurn",
    "wof:placetype":"venue"
},
  "geometry": {"coordinates":[7.5230250359,47.2131690979],"type":"Point"}
}