{
  "type": "Feature",
  "properties": {
    "iso:country":"CH",
    "sg:address":"Gehristrasse 9",
    "sg:city":"Kriens",
    "sg:orig_category":"Sportschulen Ski-& Snowboardschulen",
    "sg:phone":"+41 41 320 28 48",
    "sg:postcode":"6010",
    "sg:province":"Luzern",
    "wof:name":"Schweizer Skischule Kriens- Pilatus",
    "wof:placetype":"venue"
},
  "geometry": {"coordinates":[8.276432991,47.0289115906],"type":"Point"}
}