{
  "type": "Feature",
  "properties": {
    "iso:country":"CH",
    "sg:address":"Artherstrasse 60",
    "sg:city":"Immensee",
    "sg:orig_category":"Werbung",
    "sg:phone":"+41 41 854 25 42",
    "sg:postcode":"6405",
    "sg:province":"Schwyz",
    "wof:name":"R\u00e4ber Information Management Gmbh",
    "wof:placetype":"venue"
},
  "geometry": {"coordinates":[8.4588003159,47.0932502747],"type":"Point"}
}