{
  "type": "Feature",
  "properties": {
    "iso:country":"CH",
    "sg:address":"Helv\u00e9tique Bvd 29 1207 Gen\u00e8ve. Postfach",
    "sg:city":"Gen\u00e8ve",
    "sg:orig_category":"Sonstiger Fachdetailhandel mit Nahrungsmitteln, Getr\u00e4nken U Tabak in Verkaufsr\u00e4umen",
    "sg:postcode":"1207",
    "sg:province":"Gen\u00e8ve",
    "wof:name":"Fromagerie La Fermi\u00e8re, Liliane Oguey",
    "wof:placetype":"venue"
},
  "geometry": {"coordinates":[6.5803780556,46.5378608704],"type":"Point"}
}