{
  "type": "Feature",
  "properties": {
    "iso:country":"CH",
    "sg:address":"Tiefengasse 1",
    "sg:city":"Schleitheim",
    "sg:orig_category":"Schlachten U Fleischverarbeitung",
    "sg:phone":"+41 52 680 17 63",
    "sg:postcode":"8226",
    "sg:province":"Schaffhausen",
    "wof:name":"Schlachthaus Der Gemeinde",
    "wof:placetype":"venue"
},
  "geometry": {"coordinates":[8.4880142212,47.7504005432],"type":"Point"}
}