{
  "type": "Feature",
  "properties": {
    "iso:country":"CH",
    "sg:address":"Bahnhofstrasse 23",
    "sg:city":"Egnach",
    "sg:orig_category":"Maler U Glasergewerbe Malerei",
    "sg:postcode":"9322",
    "sg:province":"Thurgau",
    "wof:name":"Markus Gloor",
    "wof:placetype":"venue"
},
  "geometry": {"coordinates":[9.379368782,47.5412254333],"type":"Point"}
}