{
  "type": "Feature",
  "properties": {
    "iso:country":"CH",
    "sg:address":"Geissensteinring 50",
    "sg:city":"Luzern",
    "sg:orig_category":"Unclassifiable Establishments",
    "sg:phone":"+41 41 361 10 36",
    "sg:postcode":"6005",
    "sg:province":"Luzern",
    "wof:name":"Produits Naturels Vielmi",
    "wof:placetype":"venue"
},
  "geometry": {"coordinates":[8.3163013458,47.041179657],"type":"Point"}
}