{
  "type": "Feature",
  "properties": {
    "iso:country":"CH",
    "sg:address":"Dennliweg 29",
    "sg:city":"Langenthal",
    "sg:orig_category":"Carving Tools",
    "sg:phone":"+41 62 922 45 65",
    "sg:postcode":"4900",
    "sg:province":"Bern",
    "wof:name":"F. Zulauf Messerschmiede Werkzeugfabrikations Ag",
    "wof:placetype":"venue"
},
  "geometry": {"coordinates":[7.780332,47.202896],"type":"Point"}
}