{
  "type": "Feature",
  "properties": {
    "iso:country":"CH",
    "sg:address":"Kirchgasse 7",
    "sg:city":"Weesen",
    "sg:orig_category":"Allgemeiner Hoch U Tiefbau",
    "sg:phone":"+41 55 616 17 30",
    "sg:postcode":"8872",
    "sg:province":"St. Gallen",
    "wof:name":"Rutechnik Ag",
    "wof:placetype":"venue"
},
  "geometry": {"coordinates":[9.103728,47.137222],"type":"Point"}
}