{
  "type": "Feature",
  "properties": {
    "iso:country":"CH",
    "sg:address":"Kerzersstrasse 32",
    "sg:city":"M\u00fcntschemier",
    "sg:orig_category":"Gem\u00fcsebau",
    "sg:phone":"+41 79 251 22 28",
    "sg:postcode":"3225",
    "sg:province":"Bern",
    "wof:name":"Ernst Niklaus Gem\u00fcsebau",
    "wof:placetype":"venue"
},
  "geometry": {"coordinates":[7.152908802,46.9945907593],"type":"Point"}
}