{
  "type": "Feature",
  "properties": {
    "iso:country":"CH",
    "sg:address":"Sasso Grande Via 32",
    "sg:city":"Giubiasco",
    "sg:orig_category":"Unclassifiable Establishments",
    "sg:postcode":"6512",
    "sg:province":"Ticino",
    "wof:name":"Efficiency Di Claudia Celio-lambrigger",
    "wof:placetype":"venue"
},
  "geometry": {"coordinates":[9.0190782547,46.1753158569],"type":"Point"}
}