{
  "type": "Feature",
  "properties": {
    "iso:country":"CH",
    "sg:address":"Ch. Des Sapins 19 1217 Meyrin. Postfach",
    "sg:city":"Cointrin",
    "sg:orig_category":"Herstellung von nachrichtentechnischen Ger\u00e4ten U Einrichtungen",
    "sg:postcode":"1216",
    "sg:province":"Gen\u00e8ve",
    "wof:name":"Furter A.",
    "wof:placetype":"venue"
},
  "geometry": {"coordinates":[6.1077628136,46.2261123657],"type":"Point"}
}