{
  "type": "Feature",
  "properties": {
    "iso:country":"CH",
    "sg:address":"Altikofenstr. 120 3063 Ittigen. Postfach",
    "sg:city":"Worblaufen",
    "sg:classifiers":[
        {
            "category":"Professional",
            "subcategory":"Employment Agencies",
            "type":"Services"
        }
    ],
    "sg:postcode":"3048",
    "sg:province":"Bern",
    "sg:tags":[
        "personal",
        "u",
        "stellenvermittlung"
    ],
    "wof:name":"K\u00fchnhanss",
    "wof:placetype":"venue"
},
  "geometry": {"coordinates":[7.4645700455,46.9821205139],"type":"Point"}
}