{
  "type": "Feature",
  "properties": {
    "iso:country":"CH",
    "sg:address":"1260",
    "sg:city":"Nyon",
    "sg:orig_category":"Bestattungswesen",
    "sg:phone":"+41 22 361 80 10",
    "sg:postcode":"1260",
    "sg:province":"Vaud",
    "wof:name":"Pompes Fun\u00e8bres Cl\u00e9ment Sa",
    "wof:placetype":"venue"
},
  "geometry": {"coordinates":[6.23908,46.382366],"type":"Point"}
}