{
  "type": "Feature",
  "properties": {
    "iso:country":"CH",
    "sg:address":"Alte Luzernstrasse 10",
    "sg:city":"Oberentfelden",
    "sg:orig_category":"Children's Skis",
    "sg:phone":"+41 62 737 55 60",
    "sg:postcode":"5036",
    "sg:province":"Aargau",
    "wof:name":"Catrade Sportmarketing Ag",
    "wof:placetype":"venue"
},
  "geometry": {"coordinates":[8.05177,47.354309],"type":"Point"}
}