{
  "type": "Feature",
  "properties": {
    "iso:country":"CH",
    "sg:address":"Gr\u00fcningerstrasse 342",
    "sg:city":"Ottikon",
    "sg:orig_category":"G\u00fcterbef\u00f6rderung im Strassenverkehr",
    "sg:phone":"+41 19353104",
    "sg:postcode":"8626",
    "sg:province":"Z\u00fcrich",
    "wof:name":"Ernst Jordi Transporte",
    "wof:placetype":"venue"
},
  "geometry": {"coordinates":[8.7757902145,47.2921714783],"type":"Point"}
}