{
  "type": "Feature",
  "properties": {
    "addr:full":"K\u00fchlhausstrasse 6 Langenthal Bern 4900",
    "addr:housenumber":"6",
    "addr:postcode":"4900",
    "addr:street":"Kuehlhausstrasse;Bern",
    "iso:country":"CH",
    "sg:address":"K\u00fchlhausstrasse 6",
    "sg:city":"Langenthal",
    "sg:orig_category":"Pensionskassen",
    "sg:phone":"+41 62 916 11 11",
    "sg:postcode":"4900",
    "sg:province":"Bern",
    "wof:name":"Wohlfahrtsstiftung Der Geiser Holding Ag",
    "wof:placetype":"venue"
},
  "geometry": {"coordinates":[7.78296,47.21777],"type":"Point"}
}