{
  "type": "Feature",
  "properties": {
    "iso:country":"CH",
    "sg:address":"Route De Chippis",
    "sg:city":"Chalais",
    "sg:orig_category":"Elektroinstallation",
    "sg:phone":"+41 27 458 20 11",
    "sg:postcode":"3966",
    "sg:province":"Valais",
    "wof:name":"Ballestraz & Weibel Installations \u00e9lectriques",
    "wof:placetype":"venue"
},
  "geometry": {"coordinates":[7.5264048576,46.2746925354],"type":"Point"}
}