{
  "type": "Feature",
  "properties": {
    "iso:country":"CH",
    "sg:address":"Bahnhofstrasse 105",
    "sg:city":"Wettingen",
    "sg:orig_category":"Herstellung von Elektrizit\u00e4tsverteilungs U schalteinrichtungen Herstellung von sonstigen Maschinen f",
    "sg:phone":"+41 22 342 48 00",
    "sg:postcode":"5430",
    "sg:province":"Aargau",
    "wof:name":"Printelec Sa",
    "wof:placetype":"venue"
},
  "geometry": {"coordinates":[6.1464037895,46.1828079224],"type":"Point"}
}