{
  "type": "Feature",
  "properties": {
    "iso:country":"CH",
    "sg:address":"Ensingerstrasse 37",
    "sg:city":"Bern",
    "sg:classifiers":[
        {
            "category":"Insurance",
            "subcategory":"Insurance Agent",
            "type":"Services"
        }
    ],
    "sg:phone":"+41 91 827 36 46",
    "sg:postcode":"3006",
    "sg:province":"Bern",
    "sg:tags":[
        "versicherungsagenturen",
        "-broker"
    ],
    "wof:name":"Mobiliare Svizzera Assicuraz. Agenzia Cristiano Pedrini",
    "wof:placetype":"venue"
},
  "geometry": {"coordinates":[9.1283597946,46.2375984192],"type":"Point"}
}