{
  "type": "Feature",
  "properties": {
    "iso:country":"CH",
    "sg:address":"Br\u00fchlstrasse 45",
    "sg:city":"Gebenstorf",
    "sg:orig_category":"Betrieb von Taxis",
    "sg:phone":"+41 56 223 22 22",
    "sg:postcode":"5412",
    "sg:province":"Aargau",
    "wof:name":"Kyburz Transporte",
    "wof:placetype":"venue"
},
  "geometry": {"coordinates":[8.236137,47.480949],"type":"Point"}
}