{
  "type": "Feature",
  "properties": {
    "iso:country":"CH",
    "sg:address":"Ziegelhofstrasse 2 8730 Uznach. Postfach 146",
    "sg:city":"Uznach",
    "sg:orig_category":"Herstellung von Maschinen f\u00fcr die Nahrungsmittel, Getr\u00e4nkeherstellung U die Tabakverarbeitung Stahl ",
    "sg:phone":"+41 55 280 24 40",
    "sg:postcode":"8730",
    "sg:province":"St. Gallen",
    "wof:name":"Bochsler Karl Ag",
    "wof:placetype":"venue"
},
  "geometry": {"coordinates":[8.980841,47.222157],"type":"Point"}
}