{
  "type": "Feature",
  "properties": {
    "iso:country":"CH",
    "sg:address":"Neugasse 27 6340 Baar. Postfach 1031",
    "sg:city":"Baar",
    "sg:orig_category":"Innenarchitekturb\u00fcros Innenausbau",
    "sg:phone":"+41 41 760 06 06",
    "sg:postcode":"6341",
    "sg:province":"Zug",
    "wof:name":"Radler Innendekorationen Ag",
    "wof:placetype":"venue"
},
  "geometry": {"coordinates":[8.5219764709,47.1982116699],"type":"Point"}
}