{
  "type": "Feature",
  "properties": {
    "iso:country":"CH",
    "sg:address":"Hinterburgstrasse 14",
    "sg:city":"Berneck",
    "sg:orig_category":"Autogaragen",
    "sg:phone":"+41 71 722 28 63",
    "sg:postcode":"9442",
    "sg:province":"St. Gallen",
    "wof:name":"Garage Schelling",
    "wof:placetype":"venue"
},
  "geometry": {"coordinates":[9.615757,47.419315],"type":"Point"}
}