{
  "type": "Feature",
  "properties": {
    "iso:country":"CH",
    "sg:address":"Hombrechtikerstrasse 46a",
    "sg:city":"Jona",
    "sg:orig_category":"Elektroinstallation",
    "sg:phone":"+41 18443222",
    "sg:postcode":"8645",
    "sg:province":"St. Gallen",
    "wof:name":"Stephan Hofer Elektrische Installationen",
    "wof:placetype":"venue"
},
  "geometry": {"coordinates":[8.8159503937,47.2428016663],"type":"Point"}
}