{
  "type": "Feature",
  "properties": {
    "iso:country":"CH",
    "sg:address":"Mattenstrasse 84 2503 Biel/bienne. Postfach",
    "sg:city":"Biel/bienne",
    "sg:orig_category":"Vermittlung von Immobilien Verwaltung von Immobilien",
    "sg:phone":"+41 32 322 82 15",
    "sg:postcode":"2501",
    "sg:province":"Bern",
    "wof:name":"Boesiger & Partner Ag Treuhandgesellschaft",
    "wof:placetype":"venue"
},
  "geometry": {"coordinates":[7.2521910667,47.1351165771],"type":"Point"}
}