{
  "type": "Feature",
  "properties": {
    "iso:country":"CH",
    "sg:address":"Via Bernardino Luini 18",
    "sg:city":"Locarno",
    "sg:orig_category":"Wirtschaftspr\u00fcfung, Steuerberatung U Treuhand",
    "sg:phone":"+41 91 751 38 44",
    "sg:postcode":"6600",
    "sg:province":"Ticino",
    "wof:name":"Sandro Ravasio Ufficio Contabile",
    "wof:placetype":"venue"
},
  "geometry": {"coordinates":[8.7969169617,46.1682472229],"type":"Point"}
}