{
  "type": "Feature",
  "properties": {
    "addr:full":"B\u00fcrgerheimstrasse 8 W\u00e4denswil Z\u00fcrich 8820",
    "addr:housenumber":"8",
    "addr:postcode":"8820",
    "addr:street":"Buergerheimstrasse;Zuerich",
    "iso:country":"CH",
    "sg:address":"B\u00fcrgerheimstrasse 8",
    "sg:city":"W\u00e4denswil",
    "sg:orig_category":"Alters U Pflegeheime Institutionen f\u00fcr Behinderte",
    "sg:phone":"+41 17892111",
    "sg:postcode":"8820",
    "sg:province":"Z\u00fcrich",
    "wof:name":"Krankenheim Frohmatt",
    "wof:placetype":"venue"
},
  "geometry": {"coordinates":[8.661715,47.230362],"type":"Point"}
}