{
  "type": "Feature",
  "properties": {
    "iso:country":"CH",
    "sg:address":"La Jorette 1899 Torgon Case Postale 1",
    "sg:city":"Torgon",
    "sg:orig_category":"Personenbef\u00f6rderung im Linienverkehr zu Land",
    "sg:phone":"+41 24 481 29 42",
    "sg:postcode":"1899",
    "sg:province":"Valais",
    "wof:name":"T\u00e9l\u00e9-torgon Sa",
    "wof:placetype":"venue"
},
  "geometry": {"coordinates":[6.8765802383,46.3203086853],"type":"Point"}
}