{
  "type": "Feature",
  "properties": {
    "iso:country":"CH",
    "sg:address":"Pflanzenbachstrasse 47",
    "sg:city":"Widen",
    "sg:orig_category":"Vereine Diverse",
    "sg:phone":"+41 56 633 37 02",
    "sg:postcode":"8967",
    "sg:province":"Aargau",
    "wof:name":"Verein Rigi 91",
    "wof:placetype":"venue"
},
  "geometry": {"coordinates":[8.3589935303,47.3623466492],"type":"Point"}
}