{
  "type": "Feature",
  "properties": {
    "iso:country":"CH",
    "sg:address":"Im Zentrum",
    "sg:city":"Regensdorf",
    "sg:orig_category":"Herstellung von W\u00e4sche",
    "sg:phone":"+41 18400028",
    "sg:postcode":"8105",
    "sg:province":"Z\u00fcrich",
    "wof:name":"\u00abbimbo Club\u00bb Archivio",
    "wof:placetype":"venue"
},
  "geometry": {"coordinates":[8.4675598145,47.4321556091],"type":"Point"}
}