{
  "type": "Feature",
  "properties": {
    "iso:country":"CH",
    "sg:address":"Oberhausensteig 34",
    "sg:city":"Wettswil",
    "sg:orig_category":"Datenverarbeitungsdienste",
    "sg:phone":"+41 17001566",
    "sg:postcode":"8907",
    "sg:province":"Z\u00fcrich",
    "wof:name":"Hardware Independent System Consultants Ag",
    "wof:placetype":"venue"
},
  "geometry": {"coordinates":[8.478524,47.338791],"type":"Point"}
}