{
  "type": "Feature",
  "properties": {
    "addr:full":"B\u00e4ckerstrasse 60 Z\u00fcrich Z\u00fcrich 8004",
    "addr:housenumber":"60",
    "addr:postcode":"8004",
    "addr:street":"Baeckerstrasse",
    "iso:country":"CH",
    "sg:address":"B\u00e4ckerstrasse 60",
    "sg:city":"Z\u00fcrich",
    "sg:orig_category":"Detailhandel mit B\u00fcchern, Zeitungen, Schreib U Papeteriewaren",
    "sg:postcode":"8004",
    "sg:province":"Z\u00fcrich",
    "wof:name":"Seng Poh Bok",
    "wof:placetype":"venue"
},
  "geometry": {"coordinates":[8.527854,47.375816],"type":"Point"}
}