{
  "type": "Feature",
  "properties": {
    "iso:country":"CH",
    "sg:address":"Rue Marignac 13 1200 Gen\u00e8ve. Postfach",
    "sg:city":"Gen\u00e8ve",
    "sg:orig_category":"Finanzierungsinstitutionen",
    "sg:phone":"+41 22 798 74 61",
    "sg:postcode":"1206",
    "sg:province":"Gen\u00e8ve",
    "wof:name":"Pearson R., Prisma Gen\u00e8ve",
    "wof:placetype":"venue"
},
  "geometry": {"coordinates":[6.1542282104,46.1956481934],"type":"Point"}
}