{
  "type": "Feature",
  "properties": {
    "iso:country":"CH",
    "sg:address":"Genferstr. 8",
    "sg:city":"Z\u00fcrich",
    "sg:classifiers":[
        {
            "category":"Banks & Credit Unions",
            "subcategory":"Financial Services",
            "type":"Services"
        }
    ],
    "sg:phone":"+41 4112067111",
    "sg:postcode":"8027",
    "sg:province":"Z\u00fcrich",
    "sg:tags":[
        "banking",
        "insurance",
        "institution",
        "finance"
    ],
    "wof:name":"Hsbc Guyerzeller Bank Ag",
    "wof:placetype":"venue"
},
  "geometry": {"coordinates":[8.534905,47.364388],"type":"Point"}
}