{
  "type": "Feature",
  "properties": {
    "iso:country":"CH",
    "sg:address":"Stationsstr. 41",
    "sg:city":"Richterswil",
    "sg:orig_category":"Instandhaltung U Reparatur von Automobilen",
    "sg:phone":"+41 79 334 60 00",
    "sg:postcode":"8805",
    "sg:province":"Z\u00fcrich",
    "wof:name":"W\u00fcrgler Auto",
    "wof:placetype":"venue"
},
  "geometry": {"coordinates":[7.7933840752,47.2371711731],"type":"Point"}
}