{
  "type": "Feature",
  "properties": {
    "addr:full":"Kreuzstrasse Sigriswil Bern 3655",
    "addr:postcode":"3655",
    "addr:street":"Kreuzstrasse",
    "iso:country":"CH",
    "sg:address":"Kreuzstrasse",
    "sg:city":"Sigriswil",
    "sg:classifiers":[
        {
            "category":"Home & Garden",
            "subcategory":"Building Materials",
            "type":"Retail Goods"
        }
    ],
    "sg:phone":"+41 33 251 14 44",
    "sg:postcode":"3655",
    "sg:province":"Bern",
    "sg:tags":[
        "aluminium",
        "gutter"
    ],
    "wof:name":"Hans Nyffenegger Gmbh",
    "wof:placetype":"venue"
},
  "geometry": {"coordinates":[7.713675,46.717587],"type":"Point"}
}