{
  "type": "Feature",
  "properties": {
    "iso:country":"CH",
    "sg:address":"Marktstrasse 4",
    "sg:city":"Heerbrugg",
    "sg:orig_category":"Warenh\u00e4user",
    "sg:phone":"+41 71 722 27 72",
    "sg:postcode":"9435",
    "sg:province":"St. Gallen",
    "wof:name":"Manor Ag",
    "wof:placetype":"venue"
},
  "geometry": {"coordinates":[9.6266098022,47.411151886],"type":"Point"}
}