{
  "type": "Feature",
  "properties": {
    "iso:country":"CH",
    "sg:address":"Alte Landstrasse 58",
    "sg:city":"K\u00fcsnacht",
    "sg:classifiers":[
        {
            "category":"Professional",
            "subcategory":"Advertising",
            "type":"Services"
        }
    ],
    "sg:phone":"+41 19122604",
    "sg:postcode":"8700",
    "sg:province":"Z\u00fcrich",
    "sg:tags":[
        "postcard"
    ],
    "wof:name":"Ms Medium Satz + Druck Gmbh",
    "wof:placetype":"venue"
},
  "geometry": {"coordinates":[8.580307,47.329082],"type":"Point"}
}