{
  "type": "Feature",
  "properties": {
    "iso:country":"CH",
    "sg:address":"Taux Chemin Du 5 1820 Montreux. Postfach",
    "sg:city":"Corseaux",
    "sg:orig_category":"Herstellung von k\u00e4lte U lufttechnischen Erzeugnissen f\u00fcr gewerbliche Zwecke",
    "sg:postcode":"1802",
    "sg:province":"Vaud",
    "wof:name":"M.s. Etudes En Energie S\u00e0rl",
    "wof:placetype":"venue"
},
  "geometry": {"coordinates":[6.9105057716,46.4316940308],"type":"Point"}
}