{
  "type": "Feature",
  "properties": {
    "iso:country":"CH",
    "sg:address":"B\u00f6zingenstrasse 169 2500 Biel/bienne. Postfach",
    "sg:city":"Biel/bienne",
    "sg:orig_category":"Detailhandel mit Fleisch U Fleischwaren",
    "sg:phone":"+41 32 953 11 26",
    "sg:postcode":"2504",
    "sg:province":"Bern",
    "wof:name":"Roland & Corine Dubois Boucherie & Charcuterie",
    "wof:placetype":"venue"
},
  "geometry": {"coordinates":[6.9577918053,47.2249565125],"type":"Point"}
}