{
  "type": "Feature",
  "properties": {
    "iso:country":"CH",
    "sg:address":"Zugerstrasse 25",
    "sg:city":"Unter\u00e4geri",
    "sg:orig_category":"Kinos",
    "sg:phone":"+41 41 750 16 31",
    "sg:postcode":"6314",
    "sg:province":"Zug",
    "wof:name":"Iten Georg",
    "wof:placetype":"venue"
},
  "geometry": {"coordinates":[8.5813331604,47.1374931335],"type":"Point"}
}