{
  "type": "Feature",
  "properties": {
    "iso:country":"CH",
    "sg:address":"Seestrasse 31",
    "sg:city":"Arbon",
    "sg:orig_category":"Vorschulen, Kinderg\u00e4rten",
    "sg:phone":"+41 61 911 06 95",
    "sg:postcode":"9320",
    "sg:province":"Thurgau",
    "wof:name":"Kindergarten",
    "wof:placetype":"venue"
},
  "geometry": {"coordinates":[7.6697711945,47.4490127563],"type":"Point"}
}