{
  "type": "Feature",
  "properties": {
    "iso:country":"CH",
    "sg:address":"Stampfenbachstrasse 48 8006 Z\u00fcrich. Postfach",
    "sg:city":"Z\u00fcrich",
    "sg:orig_category":"Personal U Stellenvermittlung Unternehmensberatung",
    "sg:phone":"+41 13657969",
    "sg:postcode":"8006",
    "sg:province":"Z\u00fcrich",
    "wof:name":"Mb Consulting Brechb\u00fchl Manuela Personalberatung. Fach, F\u00fchrungskr\u00e4fte; Suche",
    "wof:placetype":"venue"
},
  "geometry": {"coordinates":[8.5428533554,47.3806533813],"type":"Point"}
}