{
  "type": "Feature",
  "properties": {
    "iso:country":"CH",
    "sg:address":"Bahnhofstrasse 6",
    "sg:city":"Reichenburg",
    "sg:orig_category":"K\u00fcnstlerische U schriftstellerische T\u00e4tigkeiten U Darbietungen",
    "sg:phone":"+41 55 444 16 21",
    "sg:postcode":"8864",
    "sg:province":"Schwyz",
    "wof:name":"Musikagentur Scherrer",
    "wof:placetype":"venue"
},
  "geometry": {"coordinates":[8.9761734009,47.1701469421],"type":"Point"}
}