{
  "type": "Feature",
  "properties": {
    "iso:country":"CH",
    "sg:address":"Im Junkholz 68",
    "sg:city":"Barzheim",
    "sg:orig_category":"G\u00fcterbef\u00f6rderung im Strassenverkehr",
    "sg:phone":"+41 52 649 17 55",
    "sg:postcode":"8241",
    "sg:province":"Schaffhausen",
    "wof:name":"Ackermann Internationale Transporte",
    "wof:placetype":"venue"
},
  "geometry": {"coordinates":[8.7209005356,47.760055542],"type":"Point"}
}