{
  "type": "Feature",
  "properties": {
    "iso:country":"CH",
    "sg:address":"Hauptstrasse 41",
    "sg:city":"B\u00e4ttwil",
    "sg:orig_category":"Physiotherapie",
    "sg:phone":"+41 55 210 34 47",
    "sg:postcode":"4112",
    "sg:province":"Solothurn",
    "wof:name":"Ursula B\u00fcrgi Gut Physiotherapie",
    "wof:placetype":"venue"
},
  "geometry": {"coordinates":[8.8270397186,47.2282218933],"type":"Point"}
}