{
  "type": "Feature",
  "properties": {
    "iso:country":"CH",
    "sg:address":"Felsenhofstrasse 34",
    "sg:city":"D\u00fcrnten",
    "sg:orig_category":"Hoch U Tiefbau",
    "sg:phone":"+41 71 278 45 84",
    "sg:postcode":"8635",
    "sg:province":"Z\u00fcrich",
    "wof:name":"Ernst Lutz Bauunternehmung",
    "wof:placetype":"venue"
},
  "geometry": {"coordinates":[9.3624830246,47.4259223938],"type":"Point"}
}