{
  "type": "Feature",
  "properties": {
    "iso:country":"CH",
    "sg:address":"Julierstrasse",
    "sg:city":"Cunter",
    "sg:classifiers":[
        {
            "category":"Restaurant",
            "type":"Food & Drink"
        }
    ],
    "sg:phone":"+41 81 684 16 33",
    "sg:postcode":"7452",
    "sg:province":"Graubunden",
    "wof:name":"Restaurant-pizzeria Dafora",
    "wof:placetype":"venue"
},
  "geometry": {"coordinates":[9.5914831161,46.6088867188],"type":"Point"}
}