{
  "type": "Feature",
  "properties": {
    "iso:country":"CH",
    "sg:address":"Erlenstrasse 24 Ober-ohringen 8472 Seuzach. Postfach",
    "sg:city":"Seuzach",
    "sg:orig_category":"Autogaragen",
    "sg:phone":"+41 91 606 30 91",
    "sg:postcode":"8472",
    "sg:province":"Z\u00fcrich",
    "wof:name":"Nova Car Automobili",
    "wof:placetype":"venue"
},
  "geometry": {"coordinates":[8.86395,45.97081],"type":"Point"}
}