{
  "type": "Feature",
  "properties": {
    "iso:country":"CH",
    "sg:address":"Feld",
    "sg:city":"Altishofen",
    "sg:orig_category":"Bauschreinerei Innenausbau",
    "sg:phone":"+41 62 756 21 45",
    "sg:postcode":"6246",
    "sg:province":"Luzern",
    "wof:name":"Walter Kaufmann Schreinerei & Innenausbau",
    "wof:placetype":"venue"
},
  "geometry": {"coordinates":[7.968248,47.196354],"type":"Point"}
}