{
  "type": "Feature",
  "properties": {
    "iso:country":"CH",
    "sg:address":"7432",
    "sg:city":"Zillis",
    "sg:orig_category":"Kinos",
    "sg:phone":"+41 81 661 19 14",
    "sg:postcode":"7432",
    "sg:province":"Graubunden",
    "wof:name":"Campinplatz Rania R.& R.caduff",
    "wof:placetype":"venue"
},
  "geometry": {"coordinates":[9.4450998306,46.6354789734],"type":"Point"}
}