{
  "type": "Feature",
  "properties": {
    "iso:country":"CH",
    "sg:address":"Bassbeltweg 7",
    "sg:city":"Pieterlen",
    "sg:orig_category":"Herstellung von Konstruktionsteilen, Fertigbauteilen U Ausbauelementen aus Holz",
    "sg:phone":"+41 34 461 32 02",
    "sg:postcode":"2542",
    "sg:province":"Bern",
    "wof:name":"Antik Und M\u00f6belschreinerei Sch\u00f6ni Roland",
    "wof:placetype":"venue"
},
  "geometry": {"coordinates":[7.6560120583,46.9963531494],"type":"Point"}
}