{
  "type": "Feature",
  "properties": {
    "iso:country":"CH",
    "sg:address":"Oberalpstrasse 31",
    "sg:city":"Basel",
    "sg:orig_category":"Softwareentwicklung U beratung",
    "sg:phone":"+41 61 302 57 37",
    "sg:postcode":"4054",
    "sg:province":"Basel-Stadt",
    "wof:name":"Cbis Christian Burkhalter Informatik-systeme",
    "wof:placetype":"venue"
},
  "geometry": {"coordinates":[7.5643420219,47.5487937927],"type":"Point"}
}