{
  "type": "Feature",
  "properties": {
    "iso:country":"CH",
    "sg:address":"Fola Via 13",
    "sg:city":"Pregassona",
    "sg:orig_category":"Instandhaltung U Reparatur von Automobilen",
    "sg:phone":"+41 17131121",
    "sg:postcode":"6963",
    "sg:province":"Ticino",
    "wof:name":"Cp-garage Gmbh",
    "wof:placetype":"venue"
},
  "geometry": {"coordinates":[8.5436525345,47.2884368896],"type":"Point"}
}