{
  "type": "Feature",
  "properties": {
    "iso:country":"CH",
    "sg:address":"Neue Winterthurerstrasse 75/77",
    "sg:city":"Wallisellen",
    "sg:orig_category":"Sonstige mit Sport verbundene T\u00e4tigkeiten",
    "sg:phone":"+41 71 911 06 84",
    "sg:postcode":"8304",
    "sg:province":"Z\u00fcrich",
    "wof:name":"Shotokan Karateschule Wil",
    "wof:placetype":"venue"
},
  "geometry": {"coordinates":[9.0396499634,47.4640617371],"type":"Point"}
}