{
  "type": "Feature",
  "properties": {
    "iso:country":"CH",
    "sg:address":"Althardstrasse 70",
    "sg:city":"Regensdorf",
    "sg:orig_category":"Korrespondenz U Nachrichtenb\u00fcros, selbst\u00e4ndige Journalisten",
    "sg:postcode":"8105",
    "sg:province":"Z\u00fcrich",
    "wof:name":"Johner Illustriert",
    "wof:placetype":"venue"
},
  "geometry": {"coordinates":[8.4704666138,47.4381828308],"type":"Point"}
}