{
  "type": "Feature",
  "properties": {
    "iso:country":"CH",
    "sg:address":"Thalerstrasse 71",
    "sg:city":"Heiden",
    "sg:orig_category":"Elektroinstallation",
    "sg:phone":"+41 71 891 22 39",
    "sg:postcode":"9410",
    "sg:province":"Appenzell Ausserrhoden",
    "wof:name":"Stark Max Baumontagen",
    "wof:placetype":"venue"
},
  "geometry": {"coordinates":[9.5431003571,47.4611587524],"type":"Point"}
}