{
  "type": "Feature",
  "properties": {
    "iso:country":"CH",
    "sg:address":"Bundesplatz 4",
    "sg:city":"Zug",
    "sg:classifiers":[
        {
            "category":"Restaurant",
            "type":"Food & Drink"
        }
    ],
    "sg:phone":"+41 41 711 29 68",
    "sg:postcode":"6300",
    "sg:province":"Zug",
    "wof:name":"Caf\u00e9 Ascot",
    "wof:placetype":"venue"
},
  "geometry": {"coordinates":[8.5155467987,47.1714401245],"type":"Point"}
}