{
  "type": "Feature",
  "properties": {
    "iso:country":"CH",
    "sg:address":"Oltnerstrasse 45",
    "sg:city":"Oberg\u00f6sgen",
    "sg:classifiers":[
        {
            "category":"Building & Trades",
            "subcategory":"Construction",
            "type":"Services"
        }
    ],
    "sg:phone":"+41 62 295 38 51",
    "sg:postcode":"4653",
    "sg:province":"Solothurn",
    "sg:tags":[
        "wall",
        "assembling",
        "roof"
    ],
    "wof:name":"Urs Von Arx Gmbh",
    "wof:placetype":"venue"
},
  "geometry": {"coordinates":[7.943422,47.362942],"type":"Point"}
}