{
  "type": "Feature",
  "properties": {
    "iso:country":"CH",
    "sg:address":"K\u00e4figg\u00e4sschen 10",
    "sg:city":"Bern",
    "sg:orig_category":"Arztpraxen",
    "sg:phone":"+41 31 311 66 86",
    "sg:postcode":"3011",
    "sg:province":"Bern",
    "wof:name":"Dr.med.leander Tschopp Spezialarzt Fmh",
    "wof:placetype":"venue"
},
  "geometry": {"coordinates":[7.443995,46.947975],"type":"Point"}
}