{
  "type": "Feature",
  "properties": {
    "addr:full":"Russacher Entlebuch Luzern 6162",
    "addr:postcode":"6162",
    "iso:country":"CH",
    "sg:address":"Russacher",
    "sg:city":"Entlebuch",
    "sg:classifiers":[
        {
            "category":"Manufacturing",
            "subcategory":"Tools & Machinery",
            "type":"Manufacturing & Wholesale Goods"
        }
    ],
    "sg:phone":"+41 41 480 14 62",
    "sg:postcode":"6162",
    "sg:province":"Luzern",
    "sg:tags":[
        "machine",
        "equipment",
        "door",
        "automatic"
    ],
    "wof:name":"Entla Ag",
    "wof:placetype":"venue"
},
  "geometry": {"coordinates":[8.064999,46.992802],"type":"Point"}
}