{
  "type": "Feature",
  "properties": {
    "iso:country":"CH",
    "sg:address":"Casa Vintgin",
    "sg:city":"Schluein",
    "sg:orig_category":"Stukkateurgewerbe, Gipserei U Verputzerei",
    "sg:phone":"+41 21 944 35 61",
    "sg:postcode":"7151",
    "sg:province":"Graubunden",
    "wof:name":"Iamartino Michel",
    "wof:placetype":"venue"
},
  "geometry": {"coordinates":[6.8568601608,46.4530181885],"type":"Point"}
}