{
  "type": "Feature",
  "properties": {
    "iso:country":"CH",
    "sg:address":"Rohnenstrasse 20",
    "sg:city":"Feusisberg",
    "sg:orig_category":"Ingenieurb\u00fcros Elektro",
    "sg:phone":"+41 17848282",
    "sg:postcode":"8835",
    "sg:province":"Schwyz",
    "wof:name":"Koller-sp\u00f6rri & Partner Elektro-ingenieurb\u00fcro Sbhi",
    "wof:placetype":"venue"
},
  "geometry": {"coordinates":[8.7493629456,47.1865501404],"type":"Point"}
}