{
  "type": "Feature",
  "properties": {
    "iso:country":"CH",
    "sg:address":"Rue Saint-germain 3",
    "sg:city":"Courrendlin",
    "sg:orig_category":"Detailhandel mit Geschenkartikeln U Souvenirs",
    "sg:phone":"+41 32 435 57 63",
    "sg:postcode":"2830",
    "sg:province":"Jura",
    "wof:name":"Boutique La Tour Jean-claude Cuttat",
    "wof:placetype":"venue"
},
  "geometry": {"coordinates":[7.3754482269,47.3448257446],"type":"Point"}
}