{
  "type": "Feature",
  "properties": {
    "iso:country":"CH",
    "sg:address":"Z\u00fcrcherstrasse 312",
    "sg:city":"Winterthur",
    "sg:classifiers":[
        {
            "category":"Retail",
            "subcategory":"Car Wash",
            "type":"Services"
        }
    ],
    "sg:phone":"+41 52 208 32 32",
    "sg:postcode":"8406",
    "sg:province":"Z\u00fcrich",
    "sg:tags":[
        "air-conditioning",
        "system",
        "servicing"
    ],
    "wof:name":"Amag Automobil- & Motoren Ag",
    "wof:placetype":"venue"
},
  "geometry": {"coordinates":[8.70775,47.460693],"type":"Point"}
}