{
  "type": "Feature",
  "properties": {
    "iso:country":"CH",
    "sg:address":"Florastrasse 14",
    "sg:city":"Z\u00fcrich",
    "sg:orig_category":"Grosshandel mit Schmuck Grosshandel mit sonstigen Gebrauchs U Verbrauchsg\u00fctern",
    "sg:phone":"+41 13831733",
    "sg:postcode":"8008",
    "sg:province":"Z\u00fcrich",
    "wof:name":"Fourstar Ltd",
    "wof:placetype":"venue"
},
  "geometry": {"coordinates":[8.5488624573,47.3607215881],"type":"Point"}
}