{
  "type": "Feature",
  "properties": {
    "iso:country":"CH",
    "sg:address":"Rue De L'industrie 3 1030 Bussigny-lausanne Case Postale 156",
    "sg:city":"Bussigny-lausanne",
    "sg:orig_category":"Elektroinstallation",
    "sg:postcode":"1030",
    "sg:province":"Vaud",
    "wof:name":"Domon Jo\u00ebl",
    "wof:placetype":"venue"
},
  "geometry": {"coordinates":[6.5536141396,46.5485458374],"type":"Point"}
}