{
  "type": "Feature",
  "properties": {
    "iso:country":"CH",
    "sg:address":"Oberstrasse 218",
    "sg:city":"St.gallen",
    "sg:orig_category":"Sportvereine Wassersport Segeln",
    "sg:phone":"+41 19121820",
    "sg:postcode":"9000",
    "sg:province":"St. Gallen",
    "wof:name":"Segler-vereinig.erlenbach Sve",
    "wof:placetype":"venue"
},
  "geometry": {"coordinates":[8.5937757492,47.3049507141],"type":"Point"}
}