{
  "type": "Feature",
  "properties": {
    "iso:country":"CH",
    "sg:address":"Langstrasse 62 8004 Z\u00fcrich. Postfach",
    "sg:city":"Z\u00fcrich",
    "sg:orig_category":"Handelsvermittlung U Grosshandel",
    "sg:phone":"+41 12419353",
    "sg:postcode":"8026",
    "sg:province":"Z\u00fcrich",
    "wof:name":"Dani Ag Import/export",
    "wof:placetype":"venue"
},
  "geometry": {"coordinates":[8.5260305405,47.3766288757],"type":"Point"}
}