{
  "type": "Feature",
  "properties": {
    "iso:country":"CH",
    "sg:address":"Bachtobelstrasse 35",
    "sg:city":"Weinfelden",
    "sg:orig_category":"Architekturb\u00fcros Erschliessung von Grundst\u00fccken",
    "sg:phone":"+41 71 622 29 02",
    "sg:postcode":"8570",
    "sg:province":"Thurgau",
    "wof:name":"Wohnbau Weinfelden Ag",
    "wof:placetype":"venue"
},
  "geometry": {"coordinates":[9.100528717,47.5763435364],"type":"Point"}
}