{
  "type": "Feature",
  "properties": {
    "iso:country":"CH",
    "sg:address":"Ortschwabenstrasse 5",
    "sg:city":"Uettligen",
    "sg:classifiers":[
        {
            "category":"Bars & Pubs",
            "type":"Food & Drink"
        }
    ],
    "sg:postcode":"3043",
    "sg:province":"Bern",
    "wof:name":"Par & Music Aha",
    "wof:placetype":"venue"
},
  "geometry": {"coordinates":[7.386584,46.987621],"type":"Point"}
}