{
  "type": "Feature",
  "properties": {
    "iso:country":"CH",
    "sg:address":"Guntenb\u00fchl 5",
    "sg:city":"Steinhausen",
    "sg:orig_category":"Grosshandel mit sonstigen Maschinen U Ausr\u00fcstungen f\u00fcr Industrie, Handel U Schiffahrt",
    "sg:phone":"+41 41 741 13 33",
    "sg:postcode":"6312",
    "sg:province":"Zug",
    "wof:name":"Leasing-finanz Gmbh",
    "wof:placetype":"venue"
},
  "geometry": {"coordinates":[8.4967365265,47.193107605],"type":"Point"}
}