{
  "type": "Feature",
  "properties": {
    "iso:country":"CH",
    "sg:address":"Gliserallee 57",
    "sg:city":"Glis",
    "sg:orig_category":"Autoelektro and -elektronik Werkst\u00e4tten Autogaragen",
    "sg:phone":"+41 27 922 47 87",
    "sg:postcode":"3902",
    "sg:province":"Valais",
    "wof:name":"Aaron Autoelektro & Garage",
    "wof:placetype":"venue"
},
  "geometry": {"coordinates":[7.98498,46.314301],"type":"Point"}
}