{
  "type": "Feature",
  "properties": {
    "addr:full":"Gaswerkstrasse 70 Langenthal Bern 4900",
    "addr:housenumber":"70",
    "addr:postcode":"4900",
    "addr:street":"Gaswerkstrasse;Bern",
    "iso:country":"CH",
    "sg:address":"Gaswerkstrasse 70",
    "sg:city":"Langenthal",
    "sg:classifiers":[
        {
            "category":"Professional",
            "subcategory":"Business Services",
            "type":"Services"
        }
    ],
    "sg:phone":"+41 62 922 42 17",
    "sg:postcode":"4900",
    "sg:province":"Bern",
    "sg:tags":[
        "high-precision",
        "mechanic"
    ],
    "wof:name":"Erich G\u00fcnter",
    "wof:placetype":"venue"
},
  "geometry": {"coordinates":[7.791514,47.23209],"type":"Point"}
}