{
  "type": "Feature",
  "properties": {
    "iso:country":"CH",
    "sg:address":"Rue Des Grands-pr\u00e9s 71",
    "sg:city":"Bassecourt",
    "sg:orig_category":"Detailhandel mit Waren verschiedener Art, Hauptrichtung Nahrungsmittel",
    "sg:phone":"+41 32 426 79 70",
    "sg:postcode":"2854",
    "sg:province":"Jura",
    "wof:name":"Rosemarie & Hermann St\u00f6ckli Alimentation",
    "wof:placetype":"venue"
},
  "geometry": {"coordinates":[7.2359938622,47.3396377563],"type":"Point"}
}