{
  "type": "Feature",
  "properties": {
    "iso:country":"CH",
    "sg:address":"Via Tomaso Rodari 12 6900 Lugano. Postfach",
    "sg:city":"Lugano",
    "sg:orig_category":"Vermietung U Verpachtung von eigenen Immobilien",
    "sg:postcode":"6900",
    "sg:province":"Ticino",
    "wof:name":"Sief Sa",
    "wof:placetype":"venue"
},
  "geometry": {"coordinates":[8.9453048706,46.0045661926],"type":"Point"}
}