{
  "type": "Feature",
  "properties": {
    "iso:country":"CH",
    "sg:address":"Schulstrasse 7",
    "sg:city":"D\u00f6ttingen",
    "sg:orig_category":"Detailhandel mit Getr\u00e4nken Grosshandel mit Getr\u00e4nken",
    "sg:phone":"+41 56 245 10 56",
    "sg:postcode":"5312",
    "sg:province":"Aargau",
    "wof:name":"Josef Mittler Ag",
    "wof:placetype":"venue"
},
  "geometry": {"coordinates":[8.2625169754,47.5691337585],"type":"Point"}
}