{
  "type": "Feature",
  "properties": {
    "iso:country":"CH",
    "sg:address":"Industriestr. 121",
    "sg:city":"B\u00f6singen",
    "sg:classifiers":[
        {
            "category":"Shopping",
            "type":"Retail Goods"
        }
    ],
    "sg:phone":"+41 31 747 22 22",
    "sg:postcode":"3178",
    "sg:province":"Fribourg",
    "sg:tags":[
        "metallurgy",
        "finished",
        "-",
        "metalworking",
        "metallic"
    ],
    "wof:name":"Badelux Ag",
    "wof:placetype":"venue"
},
  "geometry": {"coordinates":[7.2233409882,46.8998222351],"type":"Point"}
}