{
  "type": "Feature",
  "properties": {
    "iso:country":"CH",
    "sg:address":"Brunnaderenstrasse 7",
    "sg:city":"Eglisau",
    "sg:orig_category":"Verm\u00f6gensverwaltung",
    "sg:phone":"+41 18671209",
    "sg:postcode":"8193",
    "sg:province":"Z\u00fcrich",
    "wof:name":"Bourbonia Invest Ag Verm\u00f6gensverwaltung",
    "wof:placetype":"venue"
},
  "geometry": {"coordinates":[8.5366697311,47.5789756775],"type":"Point"}
}