{
  "type": "Feature",
  "properties": {
    "iso:country":"CH",
    "sg:address":"Steinentorstrasse 26 4051 Basel. Postfach",
    "sg:city":"Basel",
    "sg:orig_category":"Sonstiger Grosshandel",
    "sg:postcode":"4051",
    "sg:province":"Basel-Stadt",
    "wof:name":"Notter Daniel Usa-import-g\u00fcter Usw; Handel",
    "wof:placetype":"venue"
},
  "geometry": {"coordinates":[7.5878901482,47.5514450073],"type":"Point"}
}