{
  "type": "Feature",
  "properties": {
    "iso:country":"CH",
    "sg:address":"Route Des H\u00f4tels 1884 Villars-sur-ollon Case Postale 212",
    "sg:city":"Villars-sur-ollon",
    "sg:orig_category":"HOTELS: MIT RESTAURANT Kongress- and Tagungshotels mit Restaurant",
    "sg:phone":"+41 24 495 21 21",
    "sg:postcode":"1884",
    "sg:province":"Vaud",
    "wof:name":"Grand-h\u00f4tel Du Parc",
    "wof:placetype":"venue"
},
  "geometry": {"coordinates":[7.0569009781,46.2975578308],"type":"Point"}
}