{
  "type": "Feature",
  "properties": {
    "iso:country":"CH",
    "sg:address":"1128",
    "sg:city":"Reverolle",
    "sg:orig_category":"Gemeindeverwaltungen",
    "sg:phone":"+41 21 800 39 59",
    "sg:postcode":"1128",
    "sg:province":"Vaud",
    "wof:name":"Administration Communale De Reverolle",
    "wof:placetype":"venue"
},
  "geometry": {"coordinates":[6.439620018,46.5414810181],"type":"Point"}
}