{
  "type": "Feature",
  "properties": {
    "iso:country":"CH",
    "sg:address":"Bahnh\u00f6heweg 96",
    "sg:city":"Bern",
    "sg:orig_category":"Non-Classified Establishments",
    "sg:phone":"+41 31 992 24 54",
    "sg:postcode":"3018",
    "sg:province":"Bern",
    "wof:name":"Bernasconi Natursteine Ag",
    "wof:placetype":"venue"
},
  "geometry": {"coordinates":[7.3965969086,46.9384841919],"type":"Point"}
}