{
  "type": "Feature",
  "properties": {
    "iso:country":"CH",
    "sg:address":"Mythenweg 23",
    "sg:city":"Volketswil",
    "sg:orig_category":"Wirtschaftspr\u00fcfung, Steuerberatung U Treuhand",
    "sg:phone":"+41 19104938",
    "sg:postcode":"8604",
    "sg:province":"Z\u00fcrich",
    "wof:name":"Treuhandb\u00fcro C. Thalmann",
    "wof:placetype":"venue"
},
  "geometry": {"coordinates":[8.5898084641,47.3099632263],"type":"Point"}
}