{
  "type": "Feature",
  "properties": {
    "iso:country":"CH",
    "sg:address":"Westerholz 9 2504 Biel/bienne Case Postale 313",
    "sg:city":"Biel/bienne",
    "sg:orig_category":"Herstellung von Ger\u00e4ten der Elektrizit\u00e4tserzeugung, -verteilung u.\u00e4. -Herstellung von elektronischen",
    "sg:phone":"+41 32 341 21 07",
    "sg:postcode":"2501",
    "sg:province":"Bern",
    "wof:name":"Roweg Ag Biel.",
    "wof:placetype":"venue"
},
  "geometry": {"coordinates":[7.2726559639,47.1508407593],"type":"Point"}
}