{
  "type": "Feature",
  "properties": {
    "iso:country":"CH",
    "sg:address":"Aarauerstrasse 4",
    "sg:city":"Sch\u00f6ftland",
    "sg:orig_category":"Detailhandel mit Spielwaren Erbringung von Dienstleistungen f\u00fcr Unternehmen",
    "sg:phone":"+41 62 721 11 70",
    "sg:postcode":"5040",
    "sg:province":"Aargau",
    "wof:name":"Hope-modellbau Ag",
    "wof:placetype":"venue"
},
  "geometry": {"coordinates":[8.0517597198,47.3096542358],"type":"Point"}
}