{
  "type": "Feature",
  "properties": {
    "iso:country":"CH",
    "sg:address":"Hauptstrasse 82",
    "sg:city":"Rorschach",
    "sg:orig_category":"Kauf U Verkauf von Immobilien auf eigene Rechnung",
    "sg:postcode":"9400",
    "sg:province":"St. Gallen",
    "wof:name":"Basis Ag",
    "wof:placetype":"venue"
},
  "geometry": {"coordinates":[9.4907894135,47.4791374207],"type":"Point"}
}