{
  "type": "Feature",
  "properties": {
    "iso:country":"CH",
    "sg:address":"Club De Bonmont",
    "sg:city":"Ch\u00e9serex",
    "sg:orig_category":"Non-Classified Establishments",
    "sg:phone":"+41 22 369 99 30",
    "sg:postcode":"1275",
    "sg:province":"Vaud",
    "wof:name":"Bonmont Country Clubs Sa",
    "wof:placetype":"venue"
},
  "geometry": {"coordinates":[6.15143013,46.4055862427],"type":"Point"}
}