{
  "type": "Feature",
  "properties": {
    "iso:country":"CH",
    "sg:address":"R\u00fcttiweg 52 4144 Arlesheim. Postfach",
    "sg:city":"Arlesheim",
    "sg:orig_category":"Softwareentwicklung U beratung",
    "sg:postcode":"4144",
    "sg:province":"Basel-Landschaft",
    "wof:name":"Pentalog Gmbh",
    "wof:placetype":"venue"
},
  "geometry": {"coordinates":[7.6239571571,47.5027236938],"type":"Point"}
}