{
  "type": "Feature",
  "properties": {
    "addr:full":"Vorstadt 14 Schaffhausen Schaffhausen 8200",
    "addr:housenumber":"14",
    "addr:postcode":"8200",
    "addr:street":"Vorstadt",
    "iso:country":"CH",
    "sg:address":"Vorstadt 14",
    "sg:city":"Schaffhausen",
    "sg:orig_category":"Detailhandel mit B\u00fcchern Detailhandel mit Ton U Bildtr\u00e4gern",
    "sg:phone":"+41 52 625 25 75",
    "sg:postcode":"8200",
    "sg:province":"Schaffhausen",
    "wof:name":"Ex Libris Ag",
    "wof:placetype":"venue"
},
  "geometry": {"coordinates":[8.634121,47.697815],"type":"Point"}
}