{
  "type": "Feature",
  "properties": {
    "iso:country":"CH",
    "sg:address":"Buhaldenstr. 354",
    "sg:city":"Biberstein",
    "sg:orig_category":"Erschliessung von Grundst\u00fccken",
    "sg:postcode":"5023",
    "sg:province":"Aargau",
    "wof:name":"Wohnbaugenossenschaft Biberstein",
    "wof:placetype":"venue"
},
  "geometry": {"coordinates":[8.0858001709,47.4172592163],"type":"Point"}
}