{
  "type": "Feature",
  "properties": {
    "iso:country":"CH",
    "sg:address":"Dorfstrasse 43",
    "sg:city":"Richterswil",
    "sg:classifiers":[
        {
            "category":"Restaurant",
            "type":"Food & Drink"
        }
    ],
    "sg:phone":"+41 17861636",
    "sg:postcode":"8805",
    "sg:province":"Z\u00fcrich",
    "sg:tags":[
        "tea-rooms",
        "restaurants"
    ],
    "wof:name":"Baumann + Treichler Baumann, Bar Restaurant Spielhof",
    "wof:placetype":"venue"
},
  "geometry": {"coordinates":[8.7048826218,47.2077178955],"type":"Point"}
}