{
  "type": "Feature",
  "properties": {
    "iso:country":"CH",
    "sg:address":"Steckbornerstrasse 14",
    "sg:city":"Pfyn",
    "sg:orig_category":"Verwaltung von Immobilien",
    "sg:phone":"+41 71 450 00 37",
    "sg:postcode":"8505",
    "sg:province":"Thurgau",
    "wof:name":"J\u00fcrg Brunner Liegenschaftenverwaltung",
    "wof:placetype":"venue"
},
  "geometry": {"coordinates":[9.3945417404,47.4855422974],"type":"Point"}
}