{
  "type": "Feature",
  "properties": {
    "addr:full":"Isla 7151 Schluein. Postfach Ilanz Graubunden 7130",
    "addr:housenumber":"7151",
    "addr:postcode":"7130",
    "addr:street":"Isla;Postfach;Graubunden",
    "iso:country":"CH",
    "sg:address":"Isla 7151 Schluein. Postfach",
    "sg:city":"Ilanz",
    "sg:orig_category":"Allgemeiner Hoch U Tiefbau Hoch U Tiefbau",
    "sg:phone":"+41 32 961 13 30",
    "sg:postcode":"7130",
    "sg:province":"Graubunden",
    "wof:name":"Cerini Guido & Cie",
    "wof:placetype":"venue"
},
  "geometry": {"coordinates":[6.89291,47.142944],"type":"Point"}
}