{
  "type": "Feature",
  "properties": {
    "iso:country":"CH",
    "sg:address":"Sandrainstrasse 9",
    "sg:city":"Oberhasli",
    "sg:orig_category":"Primarschulen",
    "sg:phone":"+41 18501294",
    "sg:postcode":"8156",
    "sg:province":"Z\u00fcrich",
    "wof:name":"Primarschule Oberhasli",
    "wof:placetype":"venue"
},
  "geometry": {"coordinates":[8.4994440079,47.4646759033],"type":"Point"}
}