{
  "type": "Feature",
  "properties": {
    "iso:country":"CH",
    "sg:address":"Badenerstrasse 663",
    "sg:city":"Z\u00fcrich",
    "sg:orig_category":"Detailhandel mit Brot, Back U S\u00fcsswaren",
    "sg:phone":"+41 14311160",
    "sg:postcode":"8048",
    "sg:province":"Z\u00fcrich",
    "wof:name":"Margrit B\u00e4nninger B\u00e4ckerei-konditorei",
    "wof:placetype":"venue"
},
  "geometry": {"coordinates":[8.487744,47.387241],"type":"Point"}
}