{
  "type": "Feature",
  "properties": {
    "iso:country":"CH",
    "sg:address":"Schulstrasse 14",
    "sg:city":"Frick",
    "sg:orig_category":"Vermietung U Verpachtung von eigenen Immobilien",
    "sg:postcode":"5070",
    "sg:province":"Aargau",
    "wof:name":"Jakob M\u00fcller Immobilien Ag",
    "wof:placetype":"venue"
},
  "geometry": {"coordinates":[8.0208625793,47.5054321289],"type":"Point"}
}