{
  "type": "Feature",
  "properties": {
    "iso:country":"CH",
    "sg:address":"Chemin Des Bois 9",
    "sg:city":"Veyrier",
    "sg:orig_category":"Wirtschaftspr\u00fcfung, Steuerberatung U Treuhand",
    "sg:phone":"+41 22 784 01 84",
    "sg:postcode":"1255",
    "sg:province":"Gen\u00e8ve",
    "wof:name":"Fiduciaire Fran\u00e7ois B\u00e9temps",
    "wof:placetype":"venue"
},
  "geometry": {"coordinates":[6.1747632027,46.1695671082],"type":"Point"}
}