{
  "type": "Feature",
  "properties": {
    "iso:country":"CH",
    "sg:address":"Kirchstr. 13",
    "sg:city":"Rorschach",
    "sg:orig_category":"Detailhandel mit Sportartikeln Fachdetailhandel in Verkaufsr\u00e4umen",
    "sg:phone":"+41 71 841 18 09",
    "sg:postcode":"9400",
    "sg:province":"St. Gallen",
    "wof:name":"Keil-sport Ag",
    "wof:placetype":"venue"
},
  "geometry": {"coordinates":[9.4943132401,47.4770584106],"type":"Point"}
}