{
  "type": "Feature",
  "properties": {
    "iso:country":"CH",
    "sg:address":"Rue Du 23 Juin 10",
    "sg:city":"Courrendlin",
    "sg:classifiers":[
        {
            "category":"Travel",
            "subcategory":"Hotels & Motels",
            "type":"Entertainment"
        }
    ],
    "sg:phone":"+41 32 435 51 13",
    "sg:postcode":"2830",
    "sg:province":"Jura",
    "sg:tags":[
        "hotels",
        "mit",
        "restaurant"
    ],
    "wof:name":"H\u00f4tel De La Couronne",
    "wof:placetype":"venue"
},
  "geometry": {"coordinates":[7.3732180595,47.339389801],"type":"Point"}
}