{
  "type": "Feature",
  "properties": {
    "iso:country":"CH",
    "sg:address":"Route Du Canal 2",
    "sg:city":"Sugiez",
    "sg:orig_category":"Campingpl\u00e4tze",
    "sg:phone":"+41 26 673 19 93",
    "sg:postcode":"1786",
    "sg:province":"Fribourg",
    "wof:name":"Camping Les 3 Lacs Sa",
    "wof:placetype":"venue"
},
  "geometry": {"coordinates":[7.107928,46.957409],"type":"Point"}
}