{
  "type": "Feature",
  "properties": {
    "iso:country":"CH",
    "sg:address":"Altschlossstrasse 14",
    "sg:city":"Richterswil",
    "sg:orig_category":"Erwachsenenbildung U Unterricht",
    "sg:phone":"+41 12605767",
    "sg:postcode":"8805",
    "sg:province":"Z\u00fcrich",
    "wof:name":"Fm Consult B\u00fchler",
    "wof:placetype":"venue"
},
  "geometry": {"coordinates":[8.6887464523,47.2119598389],"type":"Point"}
}