{
  "type": "Feature",
  "properties": {
    "iso:country":"CH",
    "sg:address":"Baumackerstrasse 24",
    "sg:city":"Z\u00fcrich",
    "sg:classifiers":[
        {
            "category":"Cinema",
            "subcategory":"Movie Theater",
            "type":"Entertainment"
        }
    ],
    "sg:phone":"+41 18507058",
    "sg:postcode":"8050",
    "sg:province":"Z\u00fcrich",
    "sg:tags":[
        "radio",
        "videofilmherstellung",
        "fernsehanstalten",
        "u",
        "film"
    ],
    "wof:name":"Audio-video Atelier Beles",
    "wof:placetype":"venue"
},
  "geometry": {"coordinates":[8.499215126,47.4874763489],"type":"Point"}
}