{
  "type": "Feature",
  "properties": {
    "iso:country":"CH",
    "sg:address":"Kestenbergstrasse 26",
    "sg:city":"M\u00fchlau",
    "sg:orig_category":"Autogaragen",
    "sg:phone":"+41 56 668 17 06",
    "sg:postcode":"5642",
    "sg:province":"Aargau",
    "wof:name":"Enrico Bernasconi Us Cars Garage",
    "wof:placetype":"venue"
},
  "geometry": {"coordinates":[8.3874,47.231621],"type":"Point"}
}