{
  "type": "Feature",
  "properties": {
    "iso:country":"CH",
    "sg:address":"Winterthurerstrasse 260",
    "sg:city":"Z\u00fcrich",
    "sg:orig_category":"Interessenvertretungen",
    "sg:postcode":"8057",
    "sg:province":"Z\u00fcrich",
    "wof:name":"Freibetten Und F\u00fcrsorgestiftung Klinik Littenheid",
    "wof:placetype":"venue"
},
  "geometry": {"coordinates":[8.9970979691,47.4621086121],"type":"Point"}
}