{
  "type": "Feature",
  "properties": {
    "addr:full":"Zelgliackerstrasse 4 Windisch Aargau 5210",
    "addr:housenumber":"4",
    "addr:postcode":"5210",
    "addr:street":"Zelgliackerstrasse",
    "iso:country":"CH",
    "sg:address":"Zelgliackerstrasse 4",
    "sg:city":"Windisch",
    "sg:orig_category":"Datenverarbeitungsdienste Softwareentwicklung U beratung",
    "sg:phone":"+41 56 460 87 13",
    "sg:postcode":"5210",
    "sg:province":"Aargau",
    "wof:name":"Data Standards Ag",
    "wof:placetype":"venue"
},
  "geometry": {"coordinates":[8.222109,47.477528],"type":"Point"}
}