{
  "type": "Feature",
  "properties": {
    "iso:country":"CH",
    "sg:address":"Rue Centrale 47",
    "sg:city":"Montagne-moutier",
    "sg:orig_category":"Installation von Heizungs, L\u00fcftungs U Klimaanlagen Sanit\u00e4r U Heizungsinstallation",
    "sg:phone":"+41 32 493 37 27",
    "sg:postcode":"2740",
    "sg:province":"Bern",
    "wof:name":"Sulzer Infra Romadie",
    "wof:placetype":"venue"
},
  "geometry": {"coordinates":[7.3738098145,47.2794876099],"type":"Point"}
}