{
  "type": "Feature",
  "properties": {
    "iso:country":"CH",
    "sg:address":"Rabbentaltreppe 4",
    "sg:city":"Bern",
    "sg:orig_category":"Unclassifiable Establishments",
    "sg:postcode":"3013",
    "sg:province":"Bern",
    "wof:name":"Gastrofacts Gmbh Kommunikations, Internet-dienstleistungen Auf Dem Gebiet Der Gastronomie, Hotellerie Usw",
    "wof:placetype":"venue"
},
  "geometry": {"coordinates":[8.4640798569,47.360660553],"type":"Point"}
}