{
  "type": "Feature",
  "properties": {
    "iso:country":"CH",
    "sg:address":"Via Nassa 62 6900 Lugano. Postfach Caselle Postale 2455",
    "sg:city":"Lugano",
    "sg:orig_category":"Advokaturb\u00fcros Notariate",
    "sg:phone":"+41 91 923 15 23",
    "sg:postcode":"6901",
    "sg:province":"Ticino",
    "wof:name":"Claudio Codoni Studio Legale & Notarile",
    "wof:placetype":"venue"
},
  "geometry": {"coordinates":[8.949373,46.001068],"type":"Point"}
}