{
  "type": "Feature",
  "properties": {
    "iso:country":"CH",
    "sg:address":"Strada Ponte Di Valle 6964 Davesco-soragno. Postfach",
    "sg:city":"Davesco-soragno",
    "sg:orig_category":"Druck ohne Zeitungsdruck Herstellung von sonstigen Kunststoffwaren",
    "sg:phone":"+41 91 941 02 01",
    "sg:postcode":"6964",
    "sg:province":"Ticino",
    "wof:name":"Twins Cards Sa Tessere Plastiche, Etichette Ecc.; Fabbricazione, Stampa, Riproduzione",
    "wof:placetype":"venue"
},
  "geometry": {"coordinates":[8.9784021378,46.0391578674],"type":"Point"}
}