{
  "type": "Feature",
  "properties": {
    "iso:country":"CH",
    "sg:address":"Schmidgasse 4 6300 Zug. Postfach",
    "sg:city":"Zug",
    "sg:orig_category":"Allgemeiner Hoch U Tiefbau",
    "sg:postcode":"6300",
    "sg:province":"Zug",
    "wof:name":"Epper Gebr\u00fcder Gmbh",
    "wof:placetype":"venue"
},
  "geometry": {"coordinates":[9.245207,47.417007],"type":"Point"}
}