{
  "type": "Feature",
  "properties": {
    "iso:country":"CH",
    "sg:address":"Picardistrasse 3",
    "sg:city":"Sch\u00f6ftland",
    "sg:orig_category":"Elektrizit\u00e4tsversorgung Grosshandel mit medizinischen U orthop\u00e4dischen Artikeln",
    "sg:phone":"+41 62 721 22 81",
    "sg:postcode":"5040",
    "sg:province":"Aargau",
    "wof:name":"Uehlinger-pfiffner Ag",
    "wof:placetype":"venue"
},
  "geometry": {"coordinates":[8.0472650528,47.303024292],"type":"Point"}
}