{
  "type": "Feature",
  "properties": {
    "iso:country":"CH",
    "sg:address":"Brunng\u00e4sslein 6",
    "sg:city":"Basel",
    "sg:orig_category":"Kosmetikinstitute",
    "sg:phone":"+41 61 272 44 30",
    "sg:postcode":"4052",
    "sg:province":"Basel-Stadt",
    "wof:name":"Mf Esthetic-bodyline Ag Gesichts-& Figurpflege",
    "wof:placetype":"venue"
},
  "geometry": {"coordinates":[7.5940032005,47.552482605],"type":"Point"}
}