{
  "type": "Feature",
  "properties": {
    "addr:full":"Paradiesli 4 Engelberg Obwalden 6390",
    "addr:housenumber":"4",
    "addr:postcode":"6390",
    "addr:street":"Paradiesli",
    "iso:country":"CH",
    "sg:address":"Paradiesli 4",
    "sg:city":"Engelberg",
    "sg:orig_category":"Architekturb\u00fcros",
    "sg:phone":"+41 41 870 90 39",
    "sg:postcode":"6390",
    "sg:province":"Obwalden",
    "wof:name":"Roland M\u00fcller Architekturb\u00fcro",
    "wof:placetype":"venue"
},
  "geometry": {"coordinates":[8.65083,46.871815],"type":"Point"}
}