{
  "type": "Feature",
  "properties": {
    "iso:country":"CH",
    "sg:address":"Ifangstrasse 105 8153 R\u00fcmlang. Postfach",
    "sg:city":"R\u00fcmlang",
    "sg:orig_category":"Technische B\u00fcros Heizung, L\u00fcftung, Klima Technische B\u00fcros Sanit\u00e4r",
    "sg:phone":"+41 18180000",
    "sg:postcode":"8153",
    "sg:province":"Z\u00fcrich",
    "wof:name":"Ensatech Ag",
    "wof:placetype":"venue"
},
  "geometry": {"coordinates":[8.5388593674,47.4459457397],"type":"Point"}
}