{
  "type": "Feature",
  "properties": {
    "iso:country":"CH",
    "sg:address":"Eschenweg 1",
    "sg:city":"Steffisburg",
    "sg:orig_category":"Non-Classified Establishments",
    "sg:postcode":"3613",
    "sg:province":"Bern",
    "wof:name":"Immorenova Steffisburg Gmbh",
    "wof:placetype":"venue"
},
  "geometry": {"coordinates":[7.6201529503,46.7651329041],"type":"Point"}
}