{
  "type": "Feature",
  "properties": {
    "addr:full":"Hofstrasse 1 8000 Z\u00fcrich. Postfach 8032 Z\u00fcrich Zust 32",
    "addr:housenumber":"1;32",
    "addr:postcode":"8000 zuerich. postfach 8032",
    "addr:street":"Hofstrasse;Zust",
    "iso:country":"CH",
    "sg:address":"Hofstrasse 1 8000 Z\u00fcrich. Postfach 8032 Z\u00fcrich",
    "sg:city":"Zust",
    "sg:orig_category":"Architektur U Ingenieurb\u00fcros",
    "sg:postcode":"32",
    "wof:name":"Lenca Ag Logistikkonzepte In Der Forstwirtschaft, Waldbewirtschaftungen, Holzhandel",
    "wof:placetype":"venue"
},
  "geometry": {"coordinates":[8.444865,47.088406],"type":"Point"}
}