{
  "type": "Feature",
  "properties": {
    "iso:country":"CH",
    "sg:address":"Schweinbrunnen 45",
    "sg:city":"Wyssachen",
    "sg:orig_category":"Unclassifiable Establishments",
    "sg:phone":"+41 61 761 86 86",
    "sg:postcode":"4954",
    "sg:province":"Bern",
    "wof:name":"Uni-cargo Ag",
    "wof:placetype":"venue"
},
  "geometry": {"coordinates":[7.8118648529,47.0946273804],"type":"Point"}
}