{
  "type": "Feature",
  "properties": {
    "iso:country":"CH",
    "sg:address":"Sunnahof",
    "sg:city":"Mels",
    "sg:orig_category":"Bau U Wohngenossenschaften",
    "sg:postcode":"8887",
    "sg:province":"St. Gallen",
    "wof:name":"Wohnbaugen.modell Schifflaube Preisg\u00fcnstiger, Gemeinn\u00fctziger Wohnungsbau Usw",
    "wof:placetype":"venue"
},
  "geometry": {"coordinates":[7.453567,46.946327],"type":"Point"}
}