{
  "type": "Feature",
  "properties": {
    "iso:country":"CH",
    "sg:address":"6018",
    "sg:city":"Buttisholz",
    "sg:orig_category":"Detailhandel mit Milcherzeugnissen U Eiern Verarbeitung von Milch",
    "sg:postcode":"6018",
    "sg:province":"Luzern",
    "wof:name":"K\u00e4sereigenossenschaft Allmend",
    "wof:placetype":"venue"
},
  "geometry": {"coordinates":[8.0937595367,47.1144142151],"type":"Point"}
}