{
  "type": "Feature",
  "properties": {
    "iso:country":"CH",
    "sg:address":"Heimstrasse 8",
    "sg:city":"Neuhausen",
    "sg:orig_category":"Softwareentwicklung U beratung",
    "sg:phone":"+41 52 672 36 78",
    "sg:postcode":"8212",
    "sg:province":"Schaffhausen",
    "wof:name":"Get On Gmbh",
    "wof:placetype":"venue"
},
  "geometry": {"coordinates":[8.6236562729,47.6796340942],"type":"Point"}
}