{
  "type": "Feature",
  "properties": {
    "iso:country":"CH",
    "sg:address":"3942",
    "sg:city":"Raron",
    "sg:classifiers":[
        {
            "category":"Insurance",
            "subcategory":"Insurance Agent",
            "type":"Services"
        }
    ],
    "sg:phone":"+41 27 934 14 21",
    "sg:postcode":"3942",
    "sg:province":"Valais",
    "sg:tags":[
        "versicherungsagenturen",
        "-broker"
    ],
    "wof:name":"Z\u00fcrich-versicherungen Agentur",
    "wof:placetype":"venue"
},
  "geometry": {"coordinates":[7.8000950813,46.3097190857],"type":"Point"}
}