{
  "type": "Feature",
  "properties": {
    "iso:country":"CH",
    "sg:address":"Frobenstrasse 75",
    "sg:city":"Basel",
    "sg:orig_category":"Vermittlung von Immobilien Verwaltung von Immobilien",
    "sg:phone":"+41 62 771 74 44",
    "sg:postcode":"4053",
    "sg:province":"Basel-Stadt",
    "wof:name":"Pemag Treuhand Ag",
    "wof:placetype":"venue"
},
  "geometry": {"coordinates":[8.1829795837,47.2511024475],"type":"Point"}
}