{
  "type": "Feature",
  "properties": {
    "iso:country":"CH",
    "sg:address":"Bammattenweg 10",
    "sg:city":"Naters",
    "sg:orig_category":"G\u00fcterbef\u00f6rderung im Strassenverkehr",
    "sg:phone":"+41 52 319 21 50",
    "sg:postcode":"3904",
    "sg:province":"Valais",
    "wof:name":"Christian Volk, Holztransport",
    "wof:placetype":"venue"
},
  "geometry": {"coordinates":[8.6564302444,47.653377533],"type":"Point"}
}