{
  "type": "Feature",
  "properties": {
    "iso:country":"CH",
    "sg:address":"Z\u00fcrcher Strasse 68a",
    "sg:city":"St.gallen",
    "sg:orig_category":"Linienflugverkehr",
    "sg:postcode":"9000",
    "sg:province":"St. Gallen",
    "wof:name":"Gallair Ag",
    "wof:placetype":"venue"
},
  "geometry": {"coordinates":[9.350435257,47.4176902771],"type":"Point"}
}