{
  "type": "Feature",
  "properties": {
    "iso:country":"CH",
    "sg:address":"Monthoux Rue De 58 1201 Gen\u00e8ve. Postfach",
    "sg:city":"Gen\u00e8ve",
    "sg:orig_category":"Handel mit Motorr\u00e4dern, Teilen U Zubeh\u00f6r Instandhaltung U Reparatur von Motorr\u00e4dern",
    "sg:postcode":"1201",
    "sg:province":"Gen\u00e8ve",
    "wof:name":"Chamotloc S\u00e0rl, \u00e0 Gaillard (haute-savoie/france), Succursale De Gen\u00e8ve",
    "wof:placetype":"venue"
},
  "geometry": {"coordinates":[6.14559412,46.211555481],"type":"Point"}
}