{
  "type": "Feature",
  "properties": {
    "iso:country":"CH",
    "sg:address":"K\u00fcntwilerstrasse 85",
    "sg:city":"Rotkreuz",
    "sg:orig_category":"D\u00e4mmung gegen K\u00e4lte, W\u00e4rme, Schall U Ersch\u00fctterung Grosshandel mit Eisenwaren sowie Installationsbed",
    "sg:phone":"+41 19292266",
    "sg:postcode":"6343",
    "sg:province":"Zug",
    "wof:name":"Airloc Schrepfer Ag",
    "wof:placetype":"venue"
},
  "geometry": {"coordinates":[8.7266149521,47.2731819153],"type":"Point"}
}