{
  "type": "Feature",
  "properties": {
    "iso:country":"CH",
    "sg:address":"Obere Hinterwies 3",
    "sg:city":"Speicher",
    "sg:orig_category":"Erbringung von Dienstleistungen f\u00fcr Unternehmen",
    "sg:phone":"+41 71 344 47 67",
    "sg:postcode":"9042",
    "sg:province":"Appenzell Ausserrhoden",
    "wof:name":"Zarava Gmbh",
    "wof:placetype":"venue"
},
  "geometry": {"coordinates":[9.4342079163,47.4156837463],"type":"Point"}
}