{
  "type": "Feature",
  "properties": {
    "iso:country":"CH",
    "sg:address":"Via Castagnola 27",
    "sg:city":"Lugano",
    "sg:orig_category":"Grosshandel mit Textilien Wollaufbereitung U Streichgarnspinnerei",
    "sg:phone":"+41 91 976 03 65",
    "sg:postcode":"6900",
    "sg:province":"Ticino",
    "wof:name":"Silvermax Corporation Limited, Dublino, Succursale Di Lugano",
    "wof:placetype":"venue"
},
  "geometry": {"coordinates":[8.9676961899,46.0058364868],"type":"Point"}
}