{
  "type": "Feature",
  "properties": {
    "iso:country":"CH",
    "sg:address":"Mittelstrasse 2 4900 Langenthal. Postfach",
    "sg:city":"Langenthal",
    "sg:orig_category":"Nationale Postdienste",
    "sg:phone":"+41 62 885 20 09",
    "sg:postcode":"4902",
    "sg:province":"Bern",
    "wof:name":"Die Schweizerische Post Lenzburg 2 Stadt",
    "wof:placetype":"venue"
},
  "geometry": {"coordinates":[8.1821689606,47.3856811523],"type":"Point"}
}