{
  "type": "Feature",
  "properties": {
    "iso:country":"CH",
    "sg:address":"R\u00f6merstrasse 7",
    "sg:city":"Derendingen",
    "sg:orig_category":"Politische Parteien CVP",
    "sg:phone":"+41 62 393 23 34",
    "sg:postcode":"4552",
    "sg:province":"Solothurn",
    "wof:name":"Cvp Ortspartei Derendingen",
    "wof:placetype":"venue"
},
  "geometry": {"coordinates":[7.5878400803,47.2021408081],"type":"Point"}
}