{
  "type": "Feature",
  "properties": {
    "iso:country":"CH",
    "sg:address":"Via Nassa 32",
    "sg:city":"Lugano",
    "sg:orig_category":"Kosmetikinstitute",
    "sg:phone":"+41 91 922 97 33",
    "sg:postcode":"6900",
    "sg:province":"Ticino",
    "wof:name":"Studio 17 Sa",
    "wof:placetype":"venue"
},
  "geometry": {"coordinates":[8.9496917725,46.0024261475],"type":"Point"}
}