{
  "type": "Feature",
  "properties": {
    "iso:country":"CH",
    "sg:address":"Stadtturmstrasse 13",
    "sg:city":"Baden",
    "sg:orig_category":"Schreib U \u00dcbersetzungsb\u00fcros",
    "sg:phone":"+41 56 222 41 81",
    "sg:postcode":"5400",
    "sg:province":"Aargau",
    "wof:name":"Sekretariats-service Sommer Hedi",
    "wof:placetype":"venue"
},
  "geometry": {"coordinates":[8.3060398102,47.4753227234],"type":"Point"}
}