{
  "type": "Feature",
  "properties": {
    "iso:country":"CH",
    "sg:address":"Via Besso 19 6900 Lugano. Postfach",
    "sg:city":"Lugano",
    "sg:orig_category":"Korrespondenz U Nachrichtenb\u00fcros",
    "sg:phone":"+41 91 966 73 73",
    "sg:postcode":"6903",
    "sg:province":"Ticino",
    "wof:name":"Agenzia Telegrafica Svizzera",
    "wof:placetype":"venue"
},
  "geometry": {"coordinates":[8.9424190521,46.0063743591],"type":"Point"}
}