{
  "type": "Feature",
  "properties": {
    "iso:country":"CH",
    "sg:address":"Holzh\u00e4usernstrasse 1",
    "sg:city":"Rotkreuz",
    "sg:orig_category":"Herstellung von sonstigen elektrischen Ausr\u00fcstungen",
    "sg:phone":"+41 56 493 03 63",
    "sg:postcode":"6343",
    "sg:province":"Zug",
    "wof:name":"Unisonic Gmbh",
    "wof:placetype":"venue"
},
  "geometry": {"coordinates":[8.2839050293,47.4557914734],"type":"Point"}
}