{
  "type": "Feature",
  "properties": {
    "iso:country":"CH",
    "sg:address":"Bielstrasse 15",
    "sg:city":"Lyss",
    "sg:orig_category":"Detailhandel mit Fahrr\u00e4dern Detailhandel mit Sportartikeln",
    "sg:phone":"+41 27 771 55 56",
    "sg:postcode":"3250",
    "sg:province":"Bern",
    "wof:name":"No Bounds Snowboard & Bike",
    "wof:placetype":"venue"
},
  "geometry": {"coordinates":[7.2318000793,46.094367981],"type":"Point"}
}