{
  "type": "Feature",
  "properties": {
    "iso:country":"CH",
    "sg:address":"1326",
    "sg:city":"Juriens",
    "sg:orig_category":"Universit\u00e4tsspit\u00e4ler, Spit\u00e4ler f\u00fcr allgemeine Pflege",
    "sg:phone":"+41 24 453 11 27",
    "sg:postcode":"1326",
    "sg:province":"Vaud",
    "wof:name":"Fondation Contesse Service Administratif",
    "wof:placetype":"venue"
},
  "geometry": {"coordinates":[6.4502148628,46.6913414001],"type":"Point"}
}