{
  "type": "Feature",
  "properties": {
    "iso:country":"CH",
    "sg:address":"Hafenstrasse 191",
    "sg:city":"Unterb\u00f6zberg",
    "sg:orig_category":"Vermietung U Verpachtung von eigenen Immobilien",
    "sg:phone":"+41 79 401 92 03",
    "sg:postcode":"5224",
    "sg:province":"Aargau",
    "wof:name":"Bih B\u00f6zberg Ag",
    "wof:placetype":"venue"
},
  "geometry": {"coordinates":[8.1765098572,47.4815292358],"type":"Point"}
}