{
  "type": "Feature",
  "properties": {
    "iso:country":"CH",
    "sg:address":"Rue De La L\u00e9ch\u00e8re",
    "sg:city":"Bulle",
    "sg:orig_category":"Detailhandel mit Schuhen Detailhandel mit Sportartikeln",
    "sg:phone":"+41 26 912 01 95",
    "sg:postcode":"1630",
    "sg:province":"Fribourg",
    "wof:name":"Dosenbach Chaussures & Sport",
    "wof:placetype":"venue"
},
  "geometry": {"coordinates":[7.0512681007,46.6258468628],"type":"Point"}
}