{
  "type": "Feature",
  "properties": {
    "iso:country":"CH",
    "sg:address":"Niederweg 53",
    "sg:city":"Wettswil",
    "sg:orig_category":"Vereine Frauen Vereine Gemeinn\u00fctzige",
    "sg:phone":"+41 17003406",
    "sg:postcode":"8907",
    "sg:province":"Z\u00fcrich",
    "wof:name":"Frauenverein Wettswil",
    "wof:placetype":"venue"
},
  "geometry": {"coordinates":[8.4754734039,47.3287734985],"type":"Point"}
}