{
  "type": "Feature",
  "properties": {
    "iso:country":"CH",
    "sg:address":"B\u00f6hnirainstrasse L3",
    "sg:city":"Thalwil",
    "sg:orig_category":"Mechanische Werkst\u00e4tten",
    "sg:phone":"+41 32 751 33 09",
    "sg:postcode":"8800",
    "sg:province":"Z\u00fcrich",
    "wof:name":"Pfl Mesure M\u00e9canique De Pr\u00e9cision",
    "wof:placetype":"venue"
},
  "geometry": {"coordinates":[7.0641651154,47.0518341064],"type":"Point"}
}