{
  "type": "Feature",
  "properties": {
    "iso:country":"CH",
    "sg:address":"Nelkenstrasse 1",
    "sg:city":"Zurzach",
    "sg:orig_category":"Zahnarztpraxen",
    "sg:phone":"+41 56 249 41 41",
    "sg:postcode":"5330",
    "sg:province":"Aargau",
    "wof:name":"Dres. Med. Dent. J. & H. Saxer Zahn\u00e4rzte",
    "wof:placetype":"venue"
},
  "geometry": {"coordinates":[8.2826480865,47.593372345],"type":"Point"}
}