{
  "type": "Feature",
  "properties": {
    "iso:country":"CH",
    "sg:address":"Limmatstrasse 102",
    "sg:city":"Turgi",
    "sg:orig_category":"Arztpraxen Gesundheitswesen",
    "sg:phone":"+41 56 223 43 40",
    "sg:postcode":"5300",
    "sg:province":"Aargau",
    "wof:name":"Dr.med.bernhard Hollinger Arzt F.allgemeine Medizin Fmh",
    "wof:placetype":"venue"
},
  "geometry": {"coordinates":[8.252372,47.495075],"type":"Point"}
}