{
  "type": "Feature",
  "properties": {
    "iso:country":"CH",
    "sg:address":"Z\u00fcrcherstrasse 6",
    "sg:city":"Schlieren",
    "sg:orig_category":"Musikschulen and Konservatorien",
    "sg:phone":"+41 17314273",
    "sg:postcode":"8952",
    "sg:province":"Z\u00fcrich",
    "wof:name":"V\u00f6geli Percussion Musikunterricht",
    "wof:placetype":"venue"
},
  "geometry": {"coordinates":[8.4488449097,47.3974380493],"type":"Point"}
}