{
  "type": "Feature",
  "properties": {
    "iso:country":"CH",
    "sg:address":"Forelstrasse 1 3072 Ostermundigen. Postfach 1039",
    "sg:city":"Ostermundigen",
    "sg:orig_category":"Verwaltung von Immobilien Wirtschaftspr\u00fcfung, Steuerberatung U Treuhand",
    "sg:phone":"+41 41 852 13 52",
    "sg:postcode":"3072",
    "sg:province":"Bern",
    "wof:name":"Beabolt Treuhand Gmbh Treuhandb\u00fcro",
    "wof:placetype":"venue"
},
  "geometry": {"coordinates":[8.4408140182,47.0863380432],"type":"Point"}
}