{
  "type": "Feature",
  "properties": {
    "iso:country":"CH",
    "sg:address":"Pidou Chemin Auguste- 5",
    "sg:city":"Lausanne",
    "sg:orig_category":"Architektur U Ingenieurb\u00fcros",
    "sg:phone":"+41 21 614 04 23",
    "sg:postcode":"1007",
    "sg:province":"Vaud",
    "wof:name":"Rtm Architecture S\u00e0rl",
    "wof:placetype":"venue"
},
  "geometry": {"coordinates":[6.625353,46.509686],"type":"Point"}
}