{
  "type": "Feature",
  "properties": {
    "iso:country":"CH",
    "sg:address":"Waffenweg 9 3014 Bern. Postfach",
    "sg:city":"Bern",
    "sg:orig_category":"Grosshandel mit Getr\u00e4nken",
    "sg:postcode":"3005",
    "sg:province":"Bern",
    "wof:name":"Mon Petit Caveau Weine, Getr\u00e4nke; Einkauf, Einfuhr, Lagerung, Vertrieb",
    "wof:placetype":"venue"
},
  "geometry": {"coordinates":[7.4528632164,46.960395813],"type":"Point"}
}