{
  "type": "Feature",
  "properties": {
    "iso:country":"CH",
    "sg:address":"Weihermattstrasse 75-77",
    "sg:city":"Aarau",
    "sg:orig_category":"Fachdetailhandel in Verkaufsr\u00e4umen Grosshandel mit Blumen U Pflanzen",
    "sg:phone":"+41 79 209 67 08",
    "sg:postcode":"5000",
    "sg:province":"Aargau",
    "wof:name":"Vroegindeweij Blumengrosshandel Gmbh",
    "wof:placetype":"venue"
},
  "geometry": {"coordinates":[8.2531223297,47.458404541],"type":"Point"}
}