{
  "type": "Feature",
  "properties": {
    "iso:country":"CH",
    "sg:address":"Binzikon",
    "sg:city":"Gr\u00fcningen",
    "sg:orig_category":"Grosshandel mit lebenden Tieren",
    "sg:phone":"+41 19351155",
    "sg:postcode":"8627",
    "sg:province":"Z\u00fcrich",
    "wof:name":"Walter Z\u00fcrcher Viehhandel",
    "wof:placetype":"venue"
},
  "geometry": {"coordinates":[8.759554863,47.2783813477],"type":"Point"}
}