{
  "type": "Feature",
  "properties": {
    "iso:country":"CH",
    "sg:address":"3920",
    "sg:city":"Zermatt",
    "sg:orig_category":"Grosshandel mit Nahrungsmitteln, Getr\u00e4nken U Tabakwaren ohne ausgepr\u00e4gten Schwerpunkt",
    "sg:postcode":"3920",
    "sg:province":"Valais",
    "wof:name":"Konsumverein Birgisch",
    "wof:placetype":"venue"
},
  "geometry": {"coordinates":[7.9558548927,46.3169174194],"type":"Point"}
}