{
  "type": "Feature",
  "properties": {
    "iso:country":"CH",
    "sg:address":"Seestrasse 5",
    "sg:city":"Cham",
    "sg:orig_category":"Grosshandel mit Textilien",
    "sg:postcode":"6330",
    "sg:province":"Zug",
    "wof:name":"Gr\u00e4flein Esther, Boutique Edelweiss",
    "wof:placetype":"venue"
},
  "geometry": {"coordinates":[9.8232135773,46.7939529419],"type":"Point"}
}