{
  "type": "Feature",
  "properties": {
    "iso:country":"CH",
    "sg:address":"H\u00f4tel Du L\u00e9man",
    "sg:city":"Ch\u00e2telard-lutry",
    "sg:orig_category":"Interessenvertretungen",
    "sg:postcode":"1095",
    "sg:province":"Vaud",
    "wof:name":"Konla\u00ef Film",
    "wof:placetype":"venue"
},
  "geometry": {"coordinates":[6.6857571602,46.5032806396],"type":"Point"}
}