{
  "type": "Feature",
  "properties": {
    "iso:country":"CH",
    "sg:address":"Einkaufszentrum Glatt 8301 Glattzentrum. Postfach",
    "sg:city":"Glattzentrum",
    "sg:orig_category":"Arztpraxen",
    "sg:phone":"+41 18394004",
    "sg:postcode":"8301",
    "sg:province":"Z\u00fcrich",
    "wof:name":"Dr. Med.andreas M\u00fchlethaler Spezialarzt Fmh",
    "wof:placetype":"venue"
},
  "geometry": {"coordinates":[8.59514,47.423672],"type":"Point"}
}