{
  "type": "Feature",
  "properties": {
    "iso:country":"CH",
    "sg:address":"Waldweg 20",
    "sg:city":"Magden",
    "sg:orig_category":"Erbringung von Dienstleistungen f\u00fcr Unternehmen Siebdruck",
    "sg:phone":"+41 61 841 24 33",
    "sg:postcode":"4312",
    "sg:province":"Aargau",
    "wof:name":"Atelier Dillier Design Ag",
    "wof:placetype":"venue"
},
  "geometry": {"coordinates":[7.8058772087,47.5308074951],"type":"Point"}
}