{
  "type": "Feature",
  "properties": {
    "iso:country":"CH",
    "sg:address":"Weissensteinstrasse 22 A 3008 Bern. Postfach",
    "sg:city":"Bern",
    "sg:orig_category":"Non-Classified Establishments",
    "sg:postcode":"3008",
    "sg:province":"Bern",
    "wof:name":"Xylop Gmbh Dienstleistungen Im Internet, Bes. Im Ber. E-commerce Usw.",
    "wof:placetype":"venue"
},
  "geometry": {"coordinates":[7.4172000885,46.9410820007],"type":"Point"}
}