{
  "type": "Feature",
  "properties": {
    "iso:country":"CH",
    "sg:address":"Zentrum 3",
    "sg:city":"Oberrohrdorf",
    "sg:orig_category":"Detailhandel mit Fleisch U Fleischwaren",
    "sg:postcode":"5452",
    "sg:province":"Aargau",
    "wof:name":"Knoblauch Walter Gmbh Metzgerei-ladengesch\u00e4fte. Fleisch, Wurstwaren, Usw.; Handel",
    "wof:placetype":"venue"
},
  "geometry": {"coordinates":[8.2726840973,47.3495025635],"type":"Point"}
}