{
  "type": "Feature",
  "properties": {
    "iso:country":"CH",
    "sg:address":"Spl\u00fcgenstrasse 11",
    "sg:city":"Z\u00fcrich",
    "sg:orig_category":"Verwaltung von Immobilien",
    "sg:phone":"+41 12026509",
    "sg:postcode":"8002",
    "sg:province":"Z\u00fcrich",
    "wof:name":"Tribo Sa",
    "wof:placetype":"venue"
},
  "geometry": {"coordinates":[8.5333881378,47.3641471863],"type":"Point"}
}