{
  "type": "Feature",
  "properties": {
    "iso:country":"CH",
    "sg:address":"Martinastrasse 12",
    "sg:city":"Flums",
    "sg:orig_category":"Sonstiger Fachdetailhandel in Verkaufsr\u00e4umen",
    "sg:phone":"+41 81 733 48 44",
    "sg:postcode":"8890",
    "sg:province":"St. Gallen",
    "wof:name":"Mineralien Anton Schlegel",
    "wof:placetype":"venue"
},
  "geometry": {"coordinates":[9.3425388336,47.0917549133],"type":"Point"}
}