{
  "type": "Feature",
  "properties": {
    "iso:country":"CH",
    "sg:address":"Hofacker 9",
    "sg:city":"Muhen",
    "sg:orig_category":"Politische Parteien SP",
    "sg:phone":"+41 62 723 61 46",
    "sg:postcode":"5037",
    "sg:province":"Aargau",
    "wof:name":"Sp Ortspartei Muhen",
    "wof:placetype":"venue"
},
  "geometry": {"coordinates":[8.0617313385,47.3345947266],"type":"Point"}
}