{
  "type": "Feature",
  "properties": {
    "iso:country":"CH",
    "sg:address":"Oberlandstrasse 6 3700 Spiez. Postfach 374",
    "sg:city":"Spiez",
    "sg:orig_category":"Verwaltung von Immobilien Wirtschaftspr\u00fcfung, Steuerberatung U Treuhand",
    "sg:phone":"+41 41 870 98 88",
    "sg:postcode":"3700",
    "sg:province":"Bern",
    "wof:name":"Probata Ag",
    "wof:placetype":"venue"
},
  "geometry": {"coordinates":[8.6442041397,46.8820762634],"type":"Point"}
}