{
  "type": "Feature",
  "properties": {
    "iso:country":"CH",
    "sg:address":"Bahnhofstrasse 4",
    "sg:city":"Romanshorn",
    "sg:orig_category":"Herstellung von nachrichtentechnischen Ger\u00e4ten U Einrichtungen",
    "sg:phone":"+41 71 461 10 57",
    "sg:postcode":"8590",
    "sg:province":"Thurgau",
    "wof:name":"Bogerfunk Funkanlagen",
    "wof:placetype":"venue"
},
  "geometry": {"coordinates":[9.3785409927,47.5655593872],"type":"Point"}
}