{
  "type": "Feature",
  "properties": {
    "iso:country":"CH",
    "sg:address":"Bahnhofstrasse 16 8956 Killwangen. Postfach 3",
    "sg:city":"Killwangen",
    "sg:orig_category":"Herstellung von Maschinen f\u00fcr die Nahrungsmittel, Getr\u00e4nkeherstellung U die Tabakverarbeitung",
    "sg:phone":"+41 56 401 27 77",
    "sg:postcode":"8956",
    "sg:province":"Aargau",
    "wof:name":"Dorit Ag F\u00fcr Ausr\u00fcstungen Zur Lebensmittelverarbeitung",
    "wof:placetype":"venue"
},
  "geometry": {"coordinates":[8.3556308746,47.4308662415],"type":"Point"}
}