{
  "type": "Feature",
  "properties": {
    "iso:country":"CH",
    "sg:address":"Wiesentalstrasse 29",
    "sg:city":"Chur",
    "sg:orig_category":"Wirtschaftspr\u00fcfung, Steuerberatung U Treuhand",
    "sg:phone":"+41 81 353 45 85",
    "sg:postcode":"7000",
    "sg:province":"Graubunden",
    "wof:name":"Presida Treuhand Ag Aarau",
    "wof:placetype":"venue"
},
  "geometry": {"coordinates":[9.5301542282,46.8576660156],"type":"Point"}
}