{
  "type": "Feature",
  "properties": {
    "iso:country":"CH",
    "sg:address":"Seefeldstrasse 27",
    "sg:city":"Z\u00fcrich",
    "sg:orig_category":"Verlagsgewerbe",
    "sg:phone":"+41 12699070",
    "sg:postcode":"8008",
    "sg:province":"Z\u00fcrich",
    "wof:name":"Schlumpf & Sigerist Ag",
    "wof:placetype":"venue"
},
  "geometry": {"coordinates":[8.5495662689,47.3635826111],"type":"Point"}
}