{
  "type": "Feature",
  "properties": {
    "iso:country":"CH",
    "sg:address":"Schwarzhaar 45",
    "sg:city":"Oftringen",
    "sg:orig_category":"Fahrschulen, Flugschulen",
    "sg:phone":"+41 62 797 30 50",
    "sg:postcode":"4665",
    "sg:province":"Aargau",
    "wof:name":"Erwin Dreier Autofahrschule",
    "wof:placetype":"venue"
},
  "geometry": {"coordinates":[7.9182448387,47.3243904114],"type":"Point"}
}