{
  "type": "Feature",
  "properties": {
    "iso:country":"CH",
    "sg:address":"Seefeldstrasse 40",
    "sg:city":"Z\u00fcrich",
    "sg:orig_category":"Detailhandel mit Uhren U Schmuck Fachdetailhandel in Verkaufsr\u00e4umen",
    "sg:phone":"+41 12522155",
    "sg:postcode":"8008",
    "sg:province":"Z\u00fcrich",
    "wof:name":"Bm-h Beryll Ag",
    "wof:placetype":"venue"
},
  "geometry": {"coordinates":[8.5496664047,47.3630905151],"type":"Point"}
}