{
  "type": "Feature",
  "properties": {
    "iso:country":"CH",
    "sg:address":"Route De L'a\u00e9roport 9",
    "sg:city":"Sion",
    "sg:orig_category":"B\u00e4ckereien Konditoreien",
    "sg:phone":"+41 27 323 45 15",
    "sg:postcode":"1950",
    "sg:province":"Valais",
    "wof:name":"Gaillard Et Fils Boulangerie Et P\u00e2tisserie",
    "wof:placetype":"venue"
},
  "geometry": {"coordinates":[7.341405,46.223568],"type":"Point"}
}