{
  "type": "Feature",
  "properties": {
    "iso:country":"CH",
    "sg:address":"Rue De La Pacotte 16",
    "sg:city":"Auvernier",
    "sg:orig_category":"Rebbau",
    "sg:phone":"+41 32 731 10 62",
    "sg:postcode":"2012",
    "sg:province":"Neuch\u00e2tel",
    "wof:name":"Alfred Zinder Viticulteur-caviste",
    "wof:placetype":"venue"
},
  "geometry": {"coordinates":[6.8757767677,46.9774627686],"type":"Point"}
}