{
  "type": "Feature",
  "properties": {
    "iso:country":"CH",
    "sg:address":"Dominik-banzer-strasse 10",
    "sg:city":"Triesen",
    "sg:orig_category":"Bezirks, Sekundar, Realschulen, Oberstufe der Primarschulen",
    "sg:phone":"+41 75 392 39 93",
    "sg:postcode":"9495",
    "wof:name":"Oberschule",
    "wof:placetype":"venue"
},
  "geometry": {"coordinates":[9.526968,47.104225],"type":"Point"}
}