{
  "type": "Feature",
  "properties": {
    "iso:country":"CH",
    "sg:address":"Friedenstrasse 4 6004 Luzern. Postfach",
    "sg:city":"Luzern",
    "sg:orig_category":"Pensionskassen",
    "sg:postcode":"6003",
    "sg:province":"Luzern",
    "wof:name":"Wohlfahrtsstiftung F\u00fcr Das Personal Der Fa. Ygnis Kessel Ag.",
    "wof:placetype":"venue"
},
  "geometry": {"coordinates":[8.3110132217,47.0563735962],"type":"Point"}
}