{
  "type": "Feature",
  "properties": {
    "iso:country":"CH",
    "sg:address":"Dorfplatz 2",
    "sg:city":"Zumikon",
    "sg:orig_category":"Sonstige Aktivit\u00e4ten der nicht-\u00e4rztlichen Medizinalberufe",
    "sg:phone":"+41 19182966",
    "sg:postcode":"8126",
    "sg:province":"Z\u00fcrich",
    "wof:name":"Dr.med.j\u00fcrg Kym Praxis F.biologische Medizin",
    "wof:placetype":"venue"
},
  "geometry": {"coordinates":[8.6240158081,47.33203125],"type":"Point"}
}