{
  "type": "Feature",
  "properties": {
    "iso:country":"CH",
    "sg:address":"Dorf 8765 Engi. Postfach",
    "sg:city":"Engi",
    "sg:orig_category":"Zimmerei, Dachdeckerei, Bauspenglerei U Abdichtung",
    "sg:phone":"+41 55 210 58 21",
    "sg:postcode":"8765",
    "sg:province":"Glarus",
    "wof:name":"D\u00f6rfler Alfred, Bauspenglerei",
    "wof:placetype":"venue"
},
  "geometry": {"coordinates":[8.8291740417,47.223033905],"type":"Point"}
}