{
  "type": "Feature",
  "properties": {
    "iso:country":"CH",
    "sg:address":"Weinbergstrasse 40",
    "sg:city":"Zug",
    "sg:orig_category":"Interessenvertretungen",
    "sg:postcode":"6300",
    "sg:province":"Zug",
    "wof:name":"Verein F\u00fcr Aktive Senioren",
    "wof:placetype":"venue"
},
  "geometry": {"coordinates":[8.5238409042,47.1655769348],"type":"Point"}
}