{
  "type": "Feature",
  "properties": {
    "iso:country":"CH",
    "sg:address":"Cours Des Bastions 13",
    "sg:city":"Gen\u00e8ve",
    "sg:orig_category":"Grosshandel mit Wein U Spirituosen Kreditinstitute ohne Spezialkreditinstitute",
    "sg:phone":"+41 22 346 25 24",
    "sg:postcode":"1205",
    "sg:province":"Gen\u00e8ve",
    "wof:name":"Rivier Daniel",
    "wof:placetype":"venue"
},
  "geometry": {"coordinates":[6.1498589516,46.1969795227],"type":"Point"}
}