{
  "type": "Feature",
  "properties": {
    "iso:country":"CH",
    "sg:address":"Adlermatte 21",
    "sg:city":"Willisau",
    "sg:orig_category":"Detailhandel mit M\u00f6beln Verlegen von Fussboden",
    "sg:phone":"+41 41 970 32 22",
    "sg:postcode":"6130",
    "sg:province":"Luzern",
    "wof:name":"Felix Bossard Inneneinrichtungen",
    "wof:placetype":"venue"
},
  "geometry": {"coordinates":[7.98878479,47.1209411621],"type":"Point"}
}