{
  "type": "Feature",
  "properties": {
    "iso:country":"CH",
    "sg:address":"Mohrenplatz 5 6130 Willisau. Postfach",
    "sg:city":"Willisau",
    "sg:orig_category":"Detailhandel mit Radio U Fernsehger\u00e4ten Detailhandel mit elektrischen Haushalts-,Radio U Fernsehger\u00e4",
    "sg:phone":"+41 41 970 22 72",
    "sg:postcode":"6130",
    "sg:province":"Luzern",
    "wof:name":"Kurmann, Radio-tv",
    "wof:placetype":"venue"
},
  "geometry": {"coordinates":[7.993391037,47.1206283569],"type":"Point"}
}