{
  "type": "Feature",
  "properties": {
    "iso:country":"CH",
    "sg:address":"Route Du Mandement 173",
    "sg:city":"Satigny",
    "sg:orig_category":"RESTAURANTS: TEA-ROOMS",
    "sg:phone":"+41 22531171",
    "sg:postcode":"1242",
    "sg:province":"Gen\u00e8ve",
    "wof:name":"Turian S.",
    "wof:placetype":"venue"
},
  "geometry": {"coordinates":[6.0329151154,46.2148170471],"type":"Point"}
}