{
  "type": "Feature",
  "properties": {
    "addr:full":"Rue Centrale 5 1003 Lausanne Case Postale 3149 Lausanne Vaud 1002",
    "addr:housenumber":"5",
    "addr:postcode":"1003;3149;1002",
    "addr:street":"Rue Centrale;Postale",
    "iso:country":"CH",
    "sg:address":"Rue Centrale 5 1003 Lausanne Case Postale 3149",
    "sg:city":"Lausanne",
    "sg:orig_category":"Advokaturb\u00fcros",
    "sg:phone":"+41 21 312 70 48",
    "sg:postcode":"1002",
    "sg:province":"Vaud",
    "wof:name":"Koelliker Morier-genoud Perrot & Seeger Tappy",
    "wof:placetype":"venue"
},
  "geometry": {"coordinates":[6.632357,46.520718],"type":"Point"}
}