{
  "type": "Feature",
  "properties": {
    "iso:country":"CH",
    "sg:address":"Zugerstrasse 14",
    "sg:city":"Unterlunkhofen",
    "sg:classifiers":[
        {
            "category":"Restaurant",
            "type":"Food & Drink"
        }
    ],
    "sg:phone":"+41 56 634 11 82",
    "sg:postcode":"8918",
    "sg:province":"Aargau",
    "wof:name":"Restaurant Rebstock",
    "wof:placetype":"venue"
},
  "geometry": {"coordinates":[8.3806772232,47.3216438293],"type":"Point"}
}