{
  "type": "Feature",
  "properties": {
    "iso:country":"CH",
    "sg:address":"Via Al Forte 10",
    "sg:city":"Lugano",
    "sg:orig_category":"Wirtschaftspr\u00fcfung, Steuerberatung U Treuhand",
    "sg:phone":"+41 91 922 89 66",
    "sg:postcode":"6900",
    "sg:province":"Ticino",
    "wof:name":"Alberto Montorfani Ufficio Fiduciario",
    "wof:placetype":"venue"
},
  "geometry": {"coordinates":[8.9536867142,46.005645752],"type":"Point"}
}