{
  "type": "Feature",
  "properties": {
    "iso:country":"CH",
    "sg:address":"Schwanenstrasse 38",
    "sg:city":"Einsiedeln",
    "sg:orig_category":"Selbst\u00e4ndige bildende K\u00fcnstler",
    "sg:phone":"+41 31 747 91 23",
    "sg:postcode":"8840",
    "sg:province":"Schwyz",
    "wof:name":"Glasmalerei Gertsch Ag",
    "wof:placetype":"venue"
},
  "geometry": {"coordinates":[7.2417521477,46.9113502502],"type":"Point"}
}