{
  "type": "Feature",
  "properties": {
    "iso:country":"CH",
    "sg:address":"H\u00fchnerhubelstrasse 100",
    "sg:city":"Belp",
    "sg:orig_category":"Mechanik Mechanische Werkst\u00e4tten",
    "sg:phone":"+41 31 819 55 77",
    "sg:postcode":"3123",
    "sg:province":"Bern",
    "wof:name":"Kammermann Ag",
    "wof:placetype":"venue"
},
  "geometry": {"coordinates":[7.4942240715,46.9067153931],"type":"Point"}
}