{
  "type": "Feature",
  "properties": {
    "iso:country":"CH",
    "sg:address":"Dufourstrasse 14 3005 Bern. Postfach",
    "sg:city":"Bern",
    "sg:orig_category":"Grosshandel mit Textilien",
    "sg:postcode":"3005",
    "sg:province":"Bern",
    "wof:name":"Schmidt Isabelle, Import-export Textilien, Waren Aller Art; Imp, Exp.",
    "wof:placetype":"venue"
},
  "geometry": {"coordinates":[7.4543361664,46.9426193237],"type":"Point"}
}