{
  "type": "Feature",
  "properties": {
    "iso:country":"CH",
    "sg:address":"Edisriederstrasse 85",
    "sg:city":"Sachseln",
    "sg:orig_category":"Allgemeiner Hoch U Tiefbau",
    "sg:phone":"+41 41 660 00 70",
    "sg:postcode":"6072",
    "sg:province":"Obwalden",
    "wof:name":"W\u00e4lti Bau Ag",
    "wof:placetype":"venue"
},
  "geometry": {"coordinates":[8.23248,46.86208],"type":"Point"}
}