{
  "type": "Feature",
  "properties": {
    "iso:country":"CH",
    "sg:address":"Pr\u00e9 Des Planches Ch. Du",
    "sg:city":"Blonay",
    "sg:orig_category":"Herstellung von konfektionierten Textilwaren ohne Bekleidung",
    "sg:postcode":"1807",
    "sg:province":"Vaud",
    "wof:name":"Polystore Sa, Port-louis, Succursale De Blonay",
    "wof:placetype":"venue"
},
  "geometry": {"coordinates":[6.8971190453,46.477519989],"type":"Point"}
}