{
  "type": "Feature",
  "properties": {
    "iso:country":"CH",
    "sg:address":"Rue Des Mouettes 13",
    "sg:city":"Payerne",
    "sg:classifiers":[
        {
            "category":"Education",
            "subcategory":"Library",
            "type":"Public Place"
        }
    ],
    "sg:phone":"+41 26 660 49 21",
    "sg:postcode":"1530",
    "sg:province":"Vaud",
    "sg:tags":[
        "u",
        "bibliotheken",
        "archive"
    ],
    "wof:name":"Biblioth\u00e8que Communale C/o M.bernard Ballaman",
    "wof:placetype":"venue"
},
  "geometry": {"coordinates":[6.936222,46.825233],"type":"Point"}
}