{
  "type": "Feature",
  "properties": {
    "iso:country":"CH",
    "sg:address":"Kirchstrasse 5a",
    "sg:city":"Dietikon",
    "sg:orig_category":"Physiotherapie",
    "sg:phone":"+41 71 633 22 30",
    "sg:postcode":"8953",
    "sg:province":"Z\u00fcrich",
    "wof:name":"Physiotherapie Im Zentrum",
    "wof:placetype":"venue"
},
  "geometry": {"coordinates":[9.1515369415,47.5506629944],"type":"Point"}
}