{
  "type": "Feature",
  "properties": {
    "iso:country":"CH",
    "sg:address":"Croix-rive 3 1028 Pr\u00e9verenges. Postfach",
    "sg:city":"Pr\u00e9verenges",
    "sg:orig_category":"Softwareentwicklung U beratung",
    "sg:phone":"+41 21 802 39 71",
    "sg:postcode":"1028",
    "sg:province":"Vaud",
    "wof:name":"Netinfo.ch. Addor Gabrielle Mise \u00e0 Disposition De Mat\u00e9riel Informatique, Formation Et Maintenance",
    "wof:placetype":"venue"
},
  "geometry": {"coordinates":[6.5288939476,46.5167999268],"type":"Point"}
}