{
  "type": "Feature",
  "properties": {
    "iso:country":"CH",
    "sg:address":"Im Str\u00e4ler 19",
    "sg:city":"Z\u00fcrich",
    "sg:orig_category":"Fahrschulen, Flugschulen",
    "sg:phone":"+41 14925858",
    "sg:postcode":"8047",
    "sg:province":"Z\u00fcrich",
    "wof:name":"Werner Bechter Autofahrschule",
    "wof:placetype":"venue"
},
  "geometry": {"coordinates":[8.4993991852,47.3717803955],"type":"Point"}
}