{
  "type": "Feature",
  "properties": {
    "iso:country":"CH",
    "sg:address":"Engelwisstrasse 8",
    "sg:city":"B\u00fclach",
    "sg:orig_category":"Handelsvermittlung U Grosshandel Herstellung von Pflanzenschutzmitteln U sonstigen agro- chemikalisc",
    "sg:phone":"+41 18610105",
    "sg:postcode":"8180",
    "sg:province":"Z\u00fcrich",
    "wof:name":"Barlocci Gmbh",
    "wof:placetype":"venue"
},
  "geometry": {"coordinates":[8.53647995,47.5101470947],"type":"Point"}
}