{
  "type": "Feature",
  "properties": {
    "iso:country":"CH",
    "sg:address":"Route De La Gruy\u00e8re 6",
    "sg:city":"Fribourg",
    "sg:orig_category":"Malerei",
    "sg:phone":"+41 79 230 72 82",
    "sg:postcode":"1700",
    "sg:province":"Fribourg",
    "wof:name":"Jean-marie Oudelet Entreprise De Peinture",
    "wof:placetype":"venue"
},
  "geometry": {"coordinates":[7.1439418793,46.7984962463],"type":"Point"}
}