{
  "type": "Feature",
  "properties": {
    "iso:country":"CH",
    "sg:address":"Cho D'punt 33",
    "sg:city":"Samedan",
    "sg:orig_category":"Instandhaltung U Reparatur von Automobilen",
    "sg:phone":"+41 81 852 39 00",
    "sg:postcode":"7503",
    "sg:province":"Graubunden",
    "wof:name":"Gredig & Partner",
    "wof:placetype":"venue"
},
  "geometry": {"coordinates":[9.8728303909,46.5353507996],"type":"Point"}
}