{
  "type": "Feature",
  "properties": {
    "addr:full":"Burgweg 22 Pfeffingen Basel-Landschaft 4148",
    "addr:housenumber":"22",
    "addr:postcode":"4148",
    "addr:street":"Burgweg",
    "iso:country":"CH",
    "sg:address":"Burgweg 22",
    "sg:city":"Pfeffingen",
    "sg:orig_category":"Architekturb\u00fcros",
    "sg:phone":"+41 61 751 28 88",
    "sg:postcode":"4148",
    "sg:province":"Basel-Landschaft",
    "wof:name":"Alphons Kaiser Architekturb\u00fcro",
    "wof:placetype":"venue"
},
  "geometry": {"coordinates":[7.594888,47.459618],"type":"Point"}
}