{
  "type": "Feature",
  "properties": {
    "iso:country":"CH",
    "sg:address":"Provence Avenue De 14 1007 Lausanne. Postfach",
    "sg:city":"Lausanne",
    "sg:orig_category":"Grosshandel mit Eisenwaren sowie Installationsbedarf f\u00fcr Gas, Wasser U Heizung",
    "sg:phone":"+41 21 620 63 21",
    "sg:postcode":"1003",
    "sg:province":"Vaud",
    "wof:name":"Miauton Sa, Succursale De Lausanne",
    "wof:placetype":"venue"
},
  "geometry": {"coordinates":[6.632335186,46.5195960999],"type":"Point"}
}