{
  "type": "Feature",
  "properties": {
    "iso:country":"CH",
    "sg:address":"Gr\u00fctlistrasse 44 8002 Z\u00fcrich. Postfach 658",
    "sg:city":"Z\u00fcrich",
    "sg:orig_category":"Herstellung von Industriegasen",
    "sg:postcode":"8027",
    "sg:province":"Z\u00fcrich",
    "wof:name":"Voegeli Gas + Zubeh\u00f6r Ag",
    "wof:placetype":"venue"
},
  "geometry": {"coordinates":[8.5927829742,47.3152503967],"type":"Point"}
}