{
  "type": "Feature",
  "properties": {
    "iso:country":"CH",
    "sg:address":"Ebnit",
    "sg:city":"Saanen",
    "sg:orig_category":"Grosshandel mit lebenden Tieren",
    "sg:phone":"+41 55 283 20 54",
    "sg:postcode":"3792",
    "sg:province":"Bern",
    "wof:name":"Otto Wick Viehhandel",
    "wof:placetype":"venue"
},
  "geometry": {"coordinates":[8.9944400787,47.1882705688],"type":"Point"}
}