{
  "type": "Feature",
  "properties": {
    "addr:full":"Via Sottochiesa 3 Losone Ticino 6616",
    "addr:housenumber":"3",
    "addr:postcode":"6616",
    "addr:street":"Via Sottochiesa",
    "iso:country":"CH",
    "sg:address":"Via Sottochiesa 3",
    "sg:city":"Losone",
    "sg:orig_category":"Betrieb von Taxis",
    "sg:phone":"+41 79 686 23 23",
    "sg:postcode":"6616",
    "sg:province":"Ticino",
    "wof:name":"Enrico Morasci Mini Taxi Corona",
    "wof:placetype":"venue"
},
  "geometry": {"coordinates":[8.761754,46.168545],"type":"Point"}
}