{
  "type": "Feature",
  "properties": {
    "iso:country":"CH",
    "sg:address":"H\u00f6henweg 57",
    "sg:city":"Untersiggenthal",
    "sg:orig_category":"Politische Parteien SVP",
    "sg:phone":"+41 56 288 29 23",
    "sg:postcode":"5417",
    "sg:province":"Aargau",
    "wof:name":"Svp Ortspartei Untersiggenthal",
    "wof:placetype":"venue"
},
  "geometry": {"coordinates":[8.2544336319,47.4981880188],"type":"Point"}
}