{
  "type": "Feature",
  "properties": {
    "iso:country":"CH",
    "sg:address":"Lausanne Rue De 35",
    "sg:city":"Sion",
    "sg:orig_category":"Architektur U Ingenieurb\u00fcros",
    "sg:phone":"+41 17611745",
    "sg:postcode":"1950",
    "sg:province":"Valais",
    "wof:name":"Iteco Ingenieurunternehmung Ag",
    "wof:placetype":"venue"
},
  "geometry": {"coordinates":[8.4389619827,47.2739562988],"type":"Point"}
}