{
  "type": "Feature",
  "properties": {
    "iso:country":"CH",
    "sg:address":"In Der R\u00fcti 15a",
    "sg:city":"Thalwil",
    "sg:orig_category":"Unternehmensberatung",
    "sg:phone":"+41 17221545",
    "sg:postcode":"8800",
    "sg:province":"Z\u00fcrich",
    "wof:name":"Smc Sch\u00f6nmann Management & Consulting",
    "wof:placetype":"venue"
},
  "geometry": {"coordinates":[8.5517930984,47.2944755554],"type":"Point"}
}