{
  "type": "Feature",
  "properties": {
    "iso:country":"CH",
    "sg:address":"Sch\u00f6nenwerderstrasse 35a 5000 Aarau. Postfach 2920",
    "sg:city":"Aarau",
    "sg:orig_category":"Vermietung U Verpachtung von eigenen Immobilien Vermittlung von Immobilien",
    "sg:phone":"+41 32 913 78 33",
    "sg:postcode":"5001",
    "sg:province":"Aargau",
    "wof:name":"G\u00e9rance Berset Charles Sa",
    "wof:placetype":"venue"
},
  "geometry": {"coordinates":[6.8220238686,47.0996894836],"type":"Point"}
}