{
  "type": "Feature",
  "properties": {
    "iso:country":"CH",
    "sg:address":"Rue De Gen\u00e8ve 100",
    "sg:city":"Th\u00f4nex",
    "sg:orig_category":"Sanit\u00e4r, Heizungs U L\u00fcftungsinstallation",
    "sg:postcode":"1226",
    "sg:province":"Gen\u00e8ve",
    "wof:name":"Rigoni & Luget.",
    "wof:placetype":"venue"
},
  "geometry": {"coordinates":[6.2012190819,46.1929779053],"type":"Point"}
}