{
  "type": "Feature",
  "properties": {
    "iso:country":"CH",
    "sg:address":"Sonnenbergstrasse 3",
    "sg:city":"Sarnen",
    "sg:orig_category":"Vermietung U Verpachtung von eigenen Immobilien",
    "sg:phone":"+41 19107822",
    "sg:postcode":"6060",
    "sg:province":"Obwalden",
    "wof:name":"B\u00fcrke Immobilien Ag",
    "wof:placetype":"venue"
},
  "geometry": {"coordinates":[8.5998849869,47.3247718811],"type":"Point"}
}