{
  "type": "Feature",
  "properties": {
    "addr:full":"Techno-pole 3 Sierre Valais 3960",
    "addr:housenumber":"3",
    "addr:postcode":"3960",
    "iso:country":"CH",
    "sg:address":"Techno-pole 3",
    "sg:city":"Sierre",
    "sg:orig_category":"Industrie, Fahrzeugbau",
    "sg:phone":"+41 27 606 85 14",
    "sg:postcode":"3960",
    "sg:province":"Valais",
    "wof:name":"Quot;kompetenzgruppe Infotronik Interdisziplin\u00e4re,route Du Rawyl 47; 1950; Sion",
    "wof:placetype":"venue"
},
  "geometry": {"coordinates":[8.22414,46.813091],"type":"Point"}
}