{
  "type": "Feature",
  "properties": {
    "iso:country":"CH",
    "sg:address":"Bahnhofstrasse 18 8353 Elgg. Postfach 312",
    "sg:city":"Elgg",
    "sg:orig_category":"Elektroinstallation",
    "sg:phone":"+41 52 366 11 00",
    "sg:postcode":"8353",
    "sg:province":"Z\u00fcrich",
    "wof:name":"Elektro Anlagen Schwendimann R. Ag Unternehmung F\u00fcr Elektro-installationen, Verkaufsgesch\u00e4ft",
    "wof:placetype":"venue"
},
  "geometry": {"coordinates":[8.8653469086,47.4947624207],"type":"Point"}
}