{
  "type": "Feature",
  "properties": {
    "iso:country":"CH",
    "sg:address":"Witterswilerstrasse 8",
    "sg:city":"Ettingen",
    "sg:orig_category":"Kauf U Verkauf von Immobilien auf eigene Rechnung",
    "sg:phone":"+41 61 721 10 45",
    "sg:postcode":"4107",
    "sg:province":"Basel-Landschaft",
    "wof:name":"Striby & Co",
    "wof:placetype":"venue"
},
  "geometry": {"coordinates":[7.5437998772,47.4821166992],"type":"Point"}
}