{
  "type": "Feature",
  "properties": {
    "addr:full":"Grunerstrasse 11 Burgdorf Bern 3400",
    "addr:housenumber":"11",
    "addr:postcode":"3400",
    "addr:street":"Grunerstrasse",
    "iso:country":"CH",
    "sg:address":"Grunerstrasse 11",
    "sg:city":"Burgdorf",
    "sg:orig_category":"Chalet- and Holzbau Zimmerei",
    "sg:phone":"+41 55 246 16 57",
    "sg:postcode":"3400",
    "sg:province":"Bern",
    "wof:name":"Holzbau Mettlen Gmbh",
    "wof:placetype":"venue"
},
  "geometry": {"coordinates":[8.9413,47.28841],"type":"Point"}
}