{
  "type": "Feature",
  "properties": {
    "iso:country":"CH",
    "sg:address":"Degersheimerstr. 2/glatthalde. 9230 Flawil. Postfach 151",
    "sg:city":"Flawil",
    "sg:orig_category":"K\u00fcnstlerische U schriftstellerische T\u00e4tigkeiten U Darbietungen",
    "sg:phone":"+41 71 393 16 81",
    "sg:postcode":"9230",
    "sg:province":"St. Gallen",
    "wof:name":"Steiger Joh. Ulrich",
    "wof:placetype":"venue"
},
  "geometry": {"coordinates":[9.1888751984,47.4148368835],"type":"Point"}
}