{
  "type": "Feature",
  "properties": {
    "iso:country":"CH",
    "sg:address":"Weissensteinstrasse 10",
    "sg:city":"Attiswil",
    "sg:orig_category":"Non-Classified Establishments",
    "sg:phone":"+41 32 637 23 06",
    "sg:postcode":"4536",
    "sg:province":"Bern",
    "wof:name":"Patrick Kurth & Partner",
    "wof:placetype":"venue"
},
  "geometry": {"coordinates":[7.6072788239,47.2491226196],"type":"Point"}
}