{
  "type": "Feature",
  "properties": {
    "iso:country":"CH",
    "sg:address":"Rudwies 2",
    "sg:city":"Egnach",
    "sg:orig_category":"Massagestudios",
    "sg:phone":"+41 71 477 14 72",
    "sg:postcode":"9322",
    "sg:province":"Thurgau",
    "wof:name":"Bettina Blust Massagepraxis",
    "wof:placetype":"venue"
},
  "geometry": {"coordinates":[9.3852262497,47.5436058044],"type":"Point"}
}