{
  "type": "Feature",
  "properties": {
    "iso:country":"CH",
    "sg:address":"Aarauerstrasse 1",
    "sg:city":"Sch\u00f6ftland",
    "sg:orig_category":"Detailhandel mit Brillen U anderen Sehhilfen Fachdetailhandel in Verkaufsr\u00e4umen",
    "sg:phone":"+41 21 866 73 61",
    "sg:postcode":"5040",
    "sg:province":"Aargau",
    "wof:name":"Salomon Claude",
    "wof:placetype":"venue"
},
  "geometry": {"coordinates":[6.512838,46.658398],"type":"Point"}
}