{
  "type": "Feature",
  "properties": {
    "iso:country":"CH",
    "sg:address":"Bleichistrasse 8 6300 Zug. Postfach 4746",
    "sg:city":"Zug",
    "sg:orig_category":"Grosshandel mit festen Brennstoffen U Mineral\u00f6lerzeugnissen",
    "sg:phone":"+41 71 747 99 22",
    "sg:postcode":"6300",
    "sg:province":"Zug",
    "wof:name":"Nussbaumer Eugen",
    "wof:placetype":"venue"
},
  "geometry": {"coordinates":[9.635173,47.454826],"type":"Point"}
}