{
  "type": "Feature",
  "properties": {
    "iso:country":"CH",
    "sg:address":"Bachstrasse 12",
    "sg:city":"M\u00f6nchaltorf",
    "sg:classifiers":[
        {
            "category":"Professional",
            "subcategory":"Computer Services",
            "type":"Services"
        }
    ],
    "sg:phone":"+41 19482419",
    "sg:postcode":"8617",
    "sg:province":"Z\u00fcrich",
    "sg:tags":[
        "development",
        "software"
    ],
    "wof:name":"Micro-tec Dr. A. M\u00fcller Mikroprozessor-consulting",
    "wof:placetype":"venue"
},
  "geometry": {"coordinates":[8.7204427719,47.3116073608],"type":"Point"}
}