{
  "type": "Feature",
  "properties": {
    "iso:country":"CH",
    "sg:address":"Rabengasse 5",
    "sg:city":"Zofingen",
    "sg:orig_category":"Arztpraxen",
    "sg:phone":"+41 62 752 58 34",
    "sg:postcode":"4800",
    "sg:province":"Aargau",
    "wof:name":"Dr.med. Brigitte Goller-henoch Spezial\u00e4rztin",
    "wof:placetype":"venue"
},
  "geometry": {"coordinates":[7.944921,47.289761],"type":"Point"}
}