{
  "type": "Feature",
  "properties": {
    "iso:country":"CH",
    "sg:address":"Schilfweg 19",
    "sg:city":"Merlischachen",
    "sg:orig_category":"Architektur U Ingenieurb\u00fcros",
    "sg:phone":"+41 41 850 49 94",
    "sg:postcode":"6402",
    "sg:province":"Schwyz",
    "wof:name":"Dirlewanger Baumanagement Gmbh",
    "wof:placetype":"venue"
},
  "geometry": {"coordinates":[8.40931,47.066475],"type":"Point"}
}