{
  "type": "Feature",
  "properties": {
    "iso:country":"CH",
    "sg:address":"1533",
    "sg:city":"M\u00e9ni\u00e8res",
    "sg:classifiers":[
        {
            "category":"Restaurant",
            "type":"Food & Drink"
        }
    ],
    "sg:phone":"+41 26 668 10 89",
    "sg:postcode":"1533",
    "sg:province":"Fribourg",
    "wof:name":"Restaurant Les Xix Cantons",
    "wof:placetype":"venue"
},
  "geometry": {"coordinates":[6.884250164,46.7857894897],"type":"Point"}
}