{
  "type": "Feature",
  "properties": {
    "iso:country":"CH",
    "sg:address":"9445",
    "sg:city":"Rebstein",
    "sg:orig_category":"Vereine Gesang",
    "sg:postcode":"9445",
    "sg:province":"St. Gallen",
    "wof:name":"Reformierter Kirchenchor",
    "wof:placetype":"venue"
},
  "geometry": {"coordinates":[9.5846652985,47.3987236023],"type":"Point"}
}