{
  "type": "Feature",
  "properties": {
    "iso:country":"CH",
    "sg:address":"W\u00fclflingerstrasse 39",
    "sg:city":"Winterthur",
    "sg:orig_category":"Fachdetailhandel in Verkaufsr\u00e4umen",
    "sg:postcode":"8400",
    "sg:province":"Z\u00fcrich",
    "wof:name":"Gold Discount Nikolic S.",
    "wof:placetype":"venue"
},
  "geometry": {"coordinates":[8.7159118652,47.5057525635],"type":"Point"}
}