{
  "type": "Feature",
  "properties": {
    "iso:country":"CH",
    "sg:address":"Asylstr. 81",
    "sg:city":"Z\u00fcrich",
    "sg:classifiers":[
        {
            "category":"Manufacturing",
            "subcategory":"Rubber & Plastics",
            "type":"Manufacturing & Wholesale Goods"
        }
    ],
    "sg:phone":"+41 4112612244",
    "sg:postcode":"8030",
    "wof:name":"Walter Ehrensberger Ag",
    "wof:placetype":"venue"
},
  "geometry": {"coordinates":[8.5616521835,47.3667831421],"type":"Point"}
}