{
  "type": "Feature",
  "properties": {
    "iso:country":"CH",
    "sg:address":"Schwanengasse 6 3011 Bern. Postfach",
    "sg:city":"Bern",
    "sg:orig_category":"Brillen Detailhandel",
    "sg:phone":"+41 31 311 79 82",
    "sg:postcode":"3001",
    "sg:province":"Bern",
    "wof:name":"Stefan Boday-bulloni Brillen & Kontaktlinsen",
    "wof:placetype":"venue"
},
  "geometry": {"coordinates":[7.438784,46.946892],"type":"Point"}
}