{
  "type": "Feature",
  "properties": {
    "iso:country":"CH",
    "sg:address":"2572",
    "sg:city":"Sutz",
    "sg:orig_category":"Schulpflegen",
    "sg:postcode":"2572",
    "sg:province":"Bern",
    "wof:name":"Primarschulkommission Der Gemeinde Sutz-lattrigen",
    "wof:placetype":"venue"
},
  "geometry": {"coordinates":[7.2185702324,47.1009101868],"type":"Point"}
}