{
  "type": "Feature",
  "properties": {
    "iso:country":"CH",
    "sg:address":"3263",
    "sg:city":"B\u00fcetigen",
    "sg:orig_category":"Schulpflegen",
    "sg:postcode":"3263",
    "sg:province":"Bern",
    "wof:name":"Primarschulkommission Der Gemeinde B\u00fcetigen",
    "wof:placetype":"venue"
},
  "geometry": {"coordinates":[7.3351202011,47.1051902771],"type":"Point"}
}