{
  "type": "Feature",
  "properties": {
    "iso:country":"CH",
    "sg:address":"Oberb\u00fcel",
    "sg:city":"Gelfingen",
    "sg:orig_category":"Wasserversorgung",
    "sg:phone":"+41 41 917 32 84",
    "sg:postcode":"6284",
    "sg:province":"Luzern",
    "wof:name":"Wasserversorgungsgen.gelfingen Jost Heim",
    "wof:placetype":"venue"
},
  "geometry": {"coordinates":[8.2654266357,47.2141952515],"type":"Point"}
}