{
  "type": "Feature",
  "properties": {
    "iso:country":"CH",
    "sg:address":"Burgdorfstrasse 6",
    "sg:city":"Th\u00f6rigen",
    "sg:orig_category":"Herstellung von Reiseartikeln, Leder U Sattlerwaren",
    "sg:phone":"+41 62 961 16 34",
    "sg:postcode":"3367",
    "sg:province":"Bern",
    "wof:name":"Hans J\u00f6rg Sattlerei",
    "wof:placetype":"venue"
},
  "geometry": {"coordinates":[7.7268810272,47.1729431152],"type":"Point"}
}