{
  "type": "Feature",
  "properties": {
    "iso:country":"CH",
    "sg:address":"2902",
    "sg:city":"Fontenais",
    "sg:orig_category":"Grosshandel mit Holz U Baustoffen Herstellung von Betonerzeugnissen f\u00fcr den Bau",
    "sg:phone":"+41 79 353 13 53",
    "sg:postcode":"2902",
    "sg:province":"Jura",
    "wof:name":"Equibat Sa",
    "wof:placetype":"venue"
},
  "geometry": {"coordinates":[7.0790200233,47.3992614746],"type":"Point"}
}