{
  "type": "Feature",
  "properties": {
    "iso:country":"CH",
    "sg:address":"Calandaweg 4",
    "sg:city":"Untervaz",
    "sg:orig_category":"Non-Classified Establishments",
    "sg:postcode":"7204",
    "sg:province":"Graubunden",
    "wof:name":"Holzindustrie Pfeifer Ag",
    "wof:placetype":"venue"
},
  "geometry": {"coordinates":[9.5475721359,47.2997016907],"type":"Point"}
}