{
  "type": "Feature",
  "properties": {
    "iso:country":"CH",
    "sg:address":"Im Amt 6",
    "sg:city":"Gutenswil",
    "sg:orig_category":"Unclassifiable Establishments",
    "sg:postcode":"8605",
    "sg:province":"Z\u00fcrich",
    "wof:name":"Rebusfilm Gmbh",
    "wof:placetype":"venue"
},
  "geometry": {"coordinates":[8.7186822891,47.3822097778],"type":"Point"}
}