{
  "type": "Feature",
  "properties": {
    "iso:country":"CH",
    "sg:address":"Beethovenstrasse 48",
    "sg:city":"Z\u00fcrich",
    "sg:orig_category":"Handels-H\u00e4user U Gesellschaften",
    "sg:postcode":"8002",
    "sg:province":"Z\u00fcrich",
    "wof:name":"Amwell Merchant Ltd, Z\u00fcrich",
    "wof:placetype":"venue"
},
  "geometry": {"coordinates":[8.5353393555,47.3684196472],"type":"Point"}
}