{
  "type": "Feature",
  "properties": {
    "addr:full":"Z\u00fcrcherstrasse 8a Wil St. Gallen 9500",
    "addr:housenumber":"8a;st.",
    "addr:postcode":"9500",
    "addr:street":"Zuercherstrasse;Wil",
    "iso:country":"CH",
    "sg:address":"Z\u00fcrcherstrasse 8a",
    "sg:city":"Wil",
    "sg:classifiers":[
        {
            "category":"Retail",
            "subcategory":"Auto Repair",
            "type":"Services"
        }
    ],
    "sg:phone":"+41 71 911 01 11",
    "sg:postcode":"9500",
    "sg:province":"St. Gallen",
    "sg:tags":[
        "machine",
        "automatic",
        "welding"
    ],
    "wof:name":"Herbert Burghard Schweisstechnik",
    "wof:placetype":"venue"
},
  "geometry": {"coordinates":[9.041622,47.464699],"type":"Point"}
}