{
  "type": "Feature",
  "properties": {
    "iso:country":"CH",
    "sg:address":"Im H\u00f6lderli 19",
    "sg:city":"Winterthur",
    "sg:classifiers":[
        {
            "category":"Manufacturing",
            "subcategory":"Chemicals & Compounds",
            "type":"Manufacturing & Wholesale Goods"
        }
    ],
    "sg:phone":"+41 52 234 88 00",
    "sg:postcode":"8405",
    "sg:province":"Z\u00fcrich",
    "sg:tags":[
        "pharmaceutical",
        "chemistry",
        "-",
        "by-product"
    ],
    "wof:name":"Reckitt Benckiser (switzerland) Ag",
    "wof:placetype":"venue"
},
  "geometry": {"coordinates":[8.762124,47.493488],"type":"Point"}
}