{
  "type": "Feature",
  "properties": {
    "iso:country":"CH",
    "sg:address":"Zugerstrasse 66",
    "sg:city":"Cham",
    "sg:orig_category":"Sonstiger Detailhandel mit Metallwaren, Anstrichmitteln, Glaswaren, Bau U Heimwerkerbedarf",
    "sg:phone":"+41 41 780 24 10",
    "sg:postcode":"6330",
    "sg:province":"Zug",
    "wof:name":"Moser Peter Gmbh Rasenm\u00e4her Motor-& Kleinger\u00e4te",
    "wof:placetype":"venue"
},
  "geometry": {"coordinates":[8.4697380066,47.182144165],"type":"Point"}
}