{
  "type": "Feature",
  "properties": {
    "iso:country":"CH",
    "sg:address":"Beauregard Avenue 1 1700 Fribourg Case Postale 30",
    "sg:city":"Fribourg",
    "sg:orig_category":"Sonstige mit der Informatik verbundene T\u00e4tigkeiten",
    "sg:phone":"+41 26 425 89 85",
    "sg:postcode":"1700",
    "sg:province":"Fribourg",
    "wof:name":"Cqs S\u00e0rl",
    "wof:placetype":"venue"
},
  "geometry": {"coordinates":[7.1489992142,46.8023338318],"type":"Point"}
}