{
  "type": "Feature",
  "properties": {
    "iso:country":"CH",
    "sg:address":"Dorfplatz 1",
    "sg:city":"Giffers",
    "sg:orig_category":"Detailhandel mit Milcherzeugnissen U Eiern Verarbeitung von Milch",
    "sg:phone":"+41 26 418 22 51",
    "sg:postcode":"1735",
    "sg:province":"Fribourg",
    "wof:name":"Edgar Rumo K\u00e4serei",
    "wof:placetype":"venue"
},
  "geometry": {"coordinates":[7.20941782,46.7619819641],"type":"Point"}
}