{
  "type": "Feature",
  "properties": {
    "iso:country":"CH",
    "sg:address":"8046 Z\u00fcrich. Postfach 321",
    "sg:city":"Z\u00fcrich",
    "sg:orig_category":"Sportvereine Wassersport Schwimmen",
    "sg:phone":"+41 12116693",
    "sg:postcode":"8046",
    "sg:province":"Z\u00fcrich",
    "wof:name":"Tauchclub Pasa-sub",
    "wof:placetype":"venue"
},
  "geometry": {"coordinates":[8.5097303391,47.4194984436],"type":"Point"}
}