{
  "type": "Feature",
  "properties": {
    "iso:country":"CH",
    "sg:address":"Kumme",
    "sg:city":"Hohtenn",
    "sg:orig_category":"Kaminbau",
    "sg:phone":"+41 27 932 30 20",
    "sg:postcode":"3949",
    "sg:province":"Valais",
    "wof:name":"Schnyder & W\u00fcthrich Ag Stahlkaminbau",
    "wof:placetype":"venue"
},
  "geometry": {"coordinates":[7.753991127,46.3185844421],"type":"Point"}
}