{
  "type": "Feature",
  "properties": {
    "iso:country":"CH",
    "sg:address":"Rebacherstrasse 5",
    "sg:city":"Aesch",
    "sg:orig_category":"Instandhaltung U Reparatur von Automobilen",
    "sg:phone":"+41 17371782",
    "sg:postcode":"8904",
    "sg:province":"Z\u00fcrich",
    "wof:name":"Carrosserie Nyffenegger Ag",
    "wof:placetype":"venue"
},
  "geometry": {"coordinates":[8.4408226013,47.3382072449],"type":"Point"}
}