{
  "type": "Feature",
  "properties": {
    "iso:country":"CH",
    "sg:address":"Langmoosstrasse 1",
    "sg:city":"Heiden",
    "sg:orig_category":"Grosshandel mit festen Brennstoffen U Mineral\u00f6lerzeugnissen G\u00fcterbef\u00f6rderung im Strassenverkehr",
    "sg:postcode":"9410",
    "sg:province":"Appenzell Ausserrhoden",
    "wof:name":"Willy Schl\u00e4pfer",
    "wof:placetype":"venue"
},
  "geometry": {"coordinates":[9.5372409821,47.4392051697],"type":"Point"}
}