{
  "type": "Feature",
  "properties": {
    "iso:country":"CH",
    "sg:address":"Route De Montimbert",
    "sg:city":"Ch\u00e2tel-st-denis",
    "sg:orig_category":"Tierarztpraxis",
    "sg:phone":"+41 32 725 50 77",
    "sg:postcode":"1618",
    "sg:province":"Fribourg",
    "wof:name":"Drs M\u00e9d.v\u00e9t. A.& M. Von Allmen M\u00e9decins V\u00e9t\u00e9rinaires",
    "wof:placetype":"venue"
},
  "geometry": {"coordinates":[6.9267110825,46.993309021],"type":"Point"}
}