{
  "type": "Feature",
  "properties": {
    "iso:country":"CH",
    "sg:address":"Kirchstrasse 33",
    "sg:city":"Rorschach",
    "sg:orig_category":"Detailhandel mit Teppichen Verlegen von Fussboden",
    "sg:phone":"+41 71 841 67 72",
    "sg:postcode":"9400",
    "sg:province":"St. Gallen",
    "wof:name":"Ernst Walser Teppichbel\u00e4ge",
    "wof:placetype":"venue"
},
  "geometry": {"coordinates":[9.4914293289,47.4768295288],"type":"Point"}
}