{
  "type": "Feature",
  "properties": {
    "iso:country":"CH",
    "sg:address":"Les Nioles 58c",
    "sg:city":"Cormoret",
    "sg:orig_category":"Feinmechanische and Pr\u00e4zisions Werkst\u00e4tten Herstellung von sonstigen Maschinen f\u00fcr unspezifische Ver",
    "sg:phone":"+41 32 926 02 25",
    "sg:postcode":"2612",
    "sg:province":"Bern",
    "wof:name":"Lm Technologie S\u00e0rl",
    "wof:placetype":"venue"
},
  "geometry": {"coordinates":[7.0467967987,47.170841217],"type":"Point"}
}