{
  "type": "Feature",
  "properties": {
    "iso:country":"CH",
    "sg:address":"Kreuzkappellenweg 2",
    "sg:city":"Wettingen",
    "sg:orig_category":"Bauschreinerei Herstellung von Konstruktionsteilen, Fertigbauteilen U Ausbauelementen aus Holz",
    "sg:phone":"+41 56 426 20 21",
    "sg:postcode":"5430",
    "sg:province":"Aargau",
    "wof:name":"Franz Berz Inh.niklaus Meier Schreinerei Innenausbau",
    "wof:placetype":"venue"
},
  "geometry": {"coordinates":[8.340497,47.460419],"type":"Point"}
}