{
  "type": "Feature",
  "properties": {
    "iso:country":"CH",
    "sg:address":"Chemin De Chatagny",
    "sg:city":"Denens",
    "sg:orig_category":"Grosshandel mit B\u00fcromaschinen Grosshandel mit Datenverarbeitungsger\u00e4ten",
    "sg:phone":"+41 21 636 00 42",
    "sg:postcode":"1135",
    "sg:province":"Vaud",
    "wof:name":"Micro Management Computer Systems",
    "wof:placetype":"venue"
},
  "geometry": {"coordinates":[6.5966649055,46.5391540527],"type":"Point"}
}