{
  "type": "Feature",
  "properties": {
    "iso:country":"CH",
    "sg:address":"Ackerstrasse 56 8610 Uster. Postfach",
    "sg:city":"Uster",
    "sg:orig_category":"Herstellung von Ger\u00e4ten der Elektrizit\u00e4tserzeugung, -verteilung u.\u00e4. -Herstellung von elektronischen",
    "sg:phone":"+41 19448111",
    "sg:postcode":"8610",
    "sg:province":"Z\u00fcrich",
    "wof:name":"Power-one Ag",
    "wof:placetype":"venue"
},
  "geometry": {"coordinates":[8.7055158615,47.3575172424],"type":"Point"}
}