{
  "type": "Feature",
  "properties": {
    "iso:country":"CH",
    "sg:address":"Etzelmatt 1",
    "sg:city":"Wettingen",
    "sg:orig_category":"Softwareentwicklung U beratung",
    "sg:postcode":"5430",
    "sg:province":"Aargau",
    "wof:name":"Primecalc Gmbh",
    "wof:placetype":"venue"
},
  "geometry": {"coordinates":[8.317363739,47.4599304199],"type":"Point"}
}