{
  "type": "Feature",
  "properties": {
    "iso:country":"CH",
    "sg:address":"5644",
    "sg:city":"Auw",
    "sg:orig_category":"Landw. Genossenschaften Viehzucht",
    "sg:postcode":"5644",
    "sg:province":"Aargau",
    "wof:name":"Viehzuchtgenossenschaft",
    "wof:placetype":"venue"
},
  "geometry": {"coordinates":[8.3645982742,47.2115135193],"type":"Point"}
}