{
  "type": "Feature",
  "properties": {
    "iso:country":"CH",
    "sg:address":"Hohenemserstrasse 76",
    "sg:city":"Diepoldsau",
    "sg:orig_category":"Stukkateurgewerbe, Gipserei U Verputzerei",
    "sg:phone":"+41 71 737 91 10",
    "sg:postcode":"9444",
    "sg:province":"St. Gallen",
    "wof:name":"Frei + Broger Ag",
    "wof:placetype":"venue"
},
  "geometry": {"coordinates":[9.6673574448,47.3791694641],"type":"Point"}
}