{
  "type": "Feature",
  "properties": {
    "iso:country":"CH",
    "sg:address":"Via Luigi Lavizzari 8 6850 Mendrisio. Postfach",
    "sg:city":"Mendrisio",
    "sg:orig_category":"Non-Classified Establishments",
    "sg:postcode":"6850",
    "sg:province":"Ticino",
    "wof:name":"Union Brands & Partecipations Sa",
    "wof:placetype":"venue"
},
  "geometry": {"coordinates":[8.9864873886,45.8702163696],"type":"Point"}
}