{
  "type": "Feature",
  "properties": {
    "iso:country":"CH",
    "sg:address":"Allmendstrasse 14",
    "sg:city":"Villmergen",
    "sg:orig_category":"Grosshandel mit Wein U Spirituosen Grosshandel mit sonstigen Nahrungsmitteln",
    "sg:phone":"+41 56 611 14 44",
    "sg:postcode":"5612",
    "sg:province":"Aargau",
    "wof:name":"Enrico Notter Gastroteca",
    "wof:placetype":"venue"
},
  "geometry": {"coordinates":[8.2487869263,47.3568000793],"type":"Point"}
}