{
  "type": "Feature",
  "properties": {
    "iso:country":"CH",
    "sg:address":"Neue Postbaracke",
    "sg:city":"Eggiwil",
    "sg:orig_category":"Regionalbanken U Sparkassen",
    "sg:phone":"+41 34 491 19 79",
    "sg:postcode":"3537",
    "sg:province":"Bern",
    "wof:name":"Valiant Bank",
    "wof:placetype":"venue"
},
  "geometry": {"coordinates":[7.795882,46.875065],"type":"Point"}
}