{
  "type": "Feature",
  "properties": {
    "addr:full":"Rue Centrale 6 Chamoson Valais 1955",
    "addr:housenumber":"6",
    "addr:postcode":"1955",
    "addr:street":"Rue Centrale",
    "iso:country":"CH",
    "sg:address":"Rue Centrale 6",
    "sg:city":"Chamoson",
    "sg:orig_category":"Advokaturb\u00fcros Notariate",
    "sg:phone":"+41 27 306 64 42",
    "sg:postcode":"1955",
    "sg:province":"Valais",
    "wof:name":"Thierry Roduit Etude D'avocat & Notaire",
    "wof:placetype":"venue"
},
  "geometry": {"coordinates":[7.224324,46.200512],"type":"Point"}
}