{
  "type": "Feature",
  "properties": {
    "iso:country":"CH",
    "sg:address":"Hauptstrasse 18 3186 D\u00fcdingen. Postfach 218",
    "sg:city":"D\u00fcdingen",
    "sg:orig_category":"Fachdetailhandel mit pharmazeutischen Produkten",
    "sg:phone":"+41 26 492 95 50",
    "sg:postcode":"3186",
    "sg:province":"Fribourg",
    "wof:name":"Central Apotheke Dr. Jean Claude Tarchini",
    "wof:placetype":"venue"
},
  "geometry": {"coordinates":[7.1905617714,46.8480644226],"type":"Point"}
}