{
  "type": "Feature",
  "properties": {
    "iso:country":"CH",
    "sg:address":"Chutweg 4 6010 Kriens. Postfach",
    "sg:city":"Kriens",
    "sg:orig_category":"Unternehmensberatung",
    "sg:postcode":"6010",
    "sg:province":"Luzern",
    "wof:name":"Probst Consulting Gmbh",
    "wof:placetype":"venue"
},
  "geometry": {"coordinates":[8.2754497528,47.0294456482],"type":"Point"}
}