{
  "type": "Feature",
  "properties": {
    "iso:country":"CH",
    "sg:address":"Jaquet Rue Jean- 15 1201 Gen\u00e8ve. Postfach",
    "sg:city":"Gen\u00e8ve",
    "sg:orig_category":"Mechanik",
    "sg:postcode":"1207",
    "sg:province":"Gen\u00e8ve",
    "wof:name":"Rs Tuning Sarl",
    "wof:placetype":"venue"
},
  "geometry": {"coordinates":[6.1508030891,46.2135009766],"type":"Point"}
}