{
  "type": "Feature",
  "properties": {
    "iso:country":"CH",
    "sg:address":"Lausanne Rue De 1950 Sitten. Postfach",
    "sg:city":"Sion",
    "sg:orig_category":"Unclassifiable Establishments",
    "sg:postcode":"1951",
    "sg:province":"Valais",
    "wof:name":"Papilloud Brigitte, Espace Beaut\u00e9 Clarins Paris",
    "wof:placetype":"venue"
},
  "geometry": {"coordinates":[7.3424482346,46.2279472351],"type":"Point"}
}