{
  "type": "Feature",
  "properties": {
    "iso:country":"CH",
    "sg:address":"Ruswilstrasse 7",
    "sg:city":"Hellb\u00fchl",
    "sg:orig_category":"Instandhaltung U Reparatur von Automobilen Tankstellen",
    "sg:phone":"+41 41 467 14 16",
    "sg:postcode":"6016",
    "sg:province":"Luzern",
    "wof:name":"Rotbach Garage Ag",
    "wof:placetype":"venue"
},
  "geometry": {"coordinates":[8.1956558228,47.0701980591],"type":"Point"}
}