{
  "type": "Feature",
  "properties": {
    "iso:country":"CH",
    "sg:address":"Piazza Brocchi 5",
    "sg:city":"Montagnola",
    "sg:orig_category":"Arztpraxen",
    "sg:phone":"+41 91 994 84 84",
    "sg:postcode":"6926",
    "sg:province":"Ticino",
    "wof:name":"Dott.med.floriano Belloni Medico Generico",
    "wof:placetype":"venue"
},
  "geometry": {"coordinates":[8.917778,45.982456],"type":"Point"}
}