{
  "type": "Feature",
  "properties": {
    "iso:country":"CH",
    "sg:address":"Hohgantweg 13 3506 Grossh\u00f6chstetten. Postfach",
    "sg:city":"Grossh\u00f6chstetten",
    "sg:orig_category":"Herstellung von Heizk\u00f6rpern U kesseln f\u00fcr die Zentralheizung Herstellung von Metallerzeugnissen ohne",
    "sg:phone":"+41 31 711 07 76",
    "sg:postcode":"3506",
    "sg:province":"Bern",
    "wof:name":"Bimag Ag Grossh\u00f6chstetten",
    "wof:placetype":"venue"
},
  "geometry": {"coordinates":[7.640861,46.902927],"type":"Point"}
}