{
  "type": "Feature",
  "properties": {
    "iso:country":"CH",
    "sg:address":"N\u00f6thenhaus",
    "sg:city":"Milken",
    "sg:orig_category":"Detailhandel mit Waren verschiedener Art, Hauptrichtung Nahrungsmittel Verarbeitung von Milch",
    "sg:phone":"+41 31 738 81 18",
    "sg:postcode":"3157",
    "sg:province":"Bern",
    "wof:name":"Franz K\u00fcenzi K\u00e4serei & Spezereiladen",
    "wof:placetype":"venue"
},
  "geometry": {"coordinates":[7.3591108322,46.793094635],"type":"Point"}
}