{
  "type": "Feature",
  "properties": {
    "iso:country":"CH",
    "sg:address":"Industriestrasse 6",
    "sg:city":"Gr\u00e4nichen",
    "sg:orig_category":"Gartenbau",
    "sg:phone":"+41 62 842 32 03",
    "sg:postcode":"5722",
    "sg:province":"Aargau",
    "wof:name":"Lenzin Ulrich",
    "wof:placetype":"venue"
},
  "geometry": {"coordinates":[8.1065368652,47.3510169983],"type":"Point"}
}