{
  "type": "Feature",
  "properties": {
    "iso:country":"CH",
    "sg:address":"Route De L'a\u00e9roport",
    "sg:city":"Sion",
    "sg:orig_category":"Sportvereine Flug Aero-Club",
    "sg:phone":"+41 31 971 05 08",
    "sg:postcode":"1950",
    "sg:province":"Valais",
    "wof:name":"Ballongruppe Bern Des Ae.c.s.",
    "wof:placetype":"venue"
},
  "geometry": {"coordinates":[7.4400601387,46.9251480103],"type":"Point"}
}