{
  "type": "Feature",
  "properties": {
    "iso:country":"CH",
    "sg:address":"Dammerkirchstrasse 63 4056 Basel. Postfach",
    "sg:city":"Basel",
    "sg:orig_category":"Non-Classified Establishments",
    "sg:postcode":"4056",
    "sg:province":"Basel-Stadt",
    "wof:name":"Innenausbau Christoph Kolb",
    "wof:placetype":"venue"
},
  "geometry": {"coordinates":[9.5101699829,47.4520683289],"type":"Point"}
}