{
  "type": "Feature",
  "properties": {
    "iso:country":"CH",
    "sg:address":"Weinbergstrasse 107",
    "sg:city":"Z\u00fcrich",
    "sg:classifiers":[
        {
            "category":"Restaurant",
            "type":"Food & Drink"
        }
    ],
    "sg:phone":"+41 13629333",
    "sg:postcode":"8006",
    "sg:province":"Z\u00fcrich",
    "wof:name":"Restaurant Thai Diamond",
    "wof:placetype":"venue"
},
  "geometry": {"coordinates":[8.5419273376,47.3857383728],"type":"Point"}
}