{
  "type": "Feature",
  "properties": {
    "iso:country":"CH",
    "sg:address":"Avenue De La Gare 27",
    "sg:city":"Del\u00e9mont",
    "sg:orig_category":"Sonstiger Grosshandel Warenh\u00e4user",
    "sg:phone":"+41 32 421 46 48",
    "sg:postcode":"2800",
    "sg:province":"Jura",
    "wof:name":"Manor",
    "wof:placetype":"venue"
},
  "geometry": {"coordinates":[7.3494968414,47.3643035889],"type":"Point"}
}