{
  "type": "Feature",
  "properties": {
    "iso:country":"CH",
    "sg:address":"1585",
    "sg:city":"Salavaux",
    "sg:orig_category":"Physiotherapie",
    "sg:phone":"+41 26 677 18 71",
    "sg:postcode":"1585",
    "sg:province":"Vaud",
    "wof:name":"A.-l. Loup & C.-l. Gentizon Physioth\u00e9rapie",
    "wof:placetype":"venue"
},
  "geometry": {"coordinates":[7.0223398209,46.9181594849],"type":"Point"}
}