{
  "type": "Feature",
  "properties": {
    "iso:country":"CH",
    "sg:address":"Grossacher 5",
    "sg:city":"Hildisrieden",
    "sg:orig_category":"Arztpraxen",
    "sg:phone":"+41 19306100",
    "sg:postcode":"6024",
    "sg:province":"Luzern",
    "wof:name":"Dr.med.urs Schlegel Spezialarzt Fmh",
    "wof:placetype":"venue"
},
  "geometry": {"coordinates":[8.803149,47.328228],"type":"Point"}
}