{
  "type": "Feature",
  "properties": {
    "iso:country":"CH",
    "sg:address":"Neugutstrasse 88",
    "sg:city":"D\u00fcbendorf",
    "sg:orig_category":"Wirtschaftspr\u00fcfung, Steuerberatung U Treuhand",
    "sg:postcode":"8600",
    "sg:province":"Z\u00fcrich",
    "wof:name":"Tresag Schenker Treuhand",
    "wof:placetype":"venue"
},
  "geometry": {"coordinates":[7.8774008751,47.3457489014],"type":"Point"}
}