{
  "type": "Feature",
  "properties": {
    "iso:country":"CH",
    "sg:address":"Elisabethenstrasse 44",
    "sg:city":"Basel",
    "sg:orig_category":"Wirtschaftspr\u00fcfung, Steuerberatung U Treuhand",
    "sg:phone":"+41 61 273 84 85",
    "sg:postcode":"4051",
    "sg:province":"Basel-Stadt",
    "wof:name":"Bmf Proconsulting Ag",
    "wof:placetype":"venue"
},
  "geometry": {"coordinates":[7.5906190872,47.5506019592],"type":"Point"}
}