{
  "type": "Feature",
  "properties": {
    "iso:country":"CH",
    "sg:address":"Loretostrasse 36",
    "sg:city":"Solothurn",
    "sg:orig_category":"Ger\u00fcstbau Maler U Glasergewerbe",
    "sg:phone":"+41 32 622 95 62",
    "sg:postcode":"4500",
    "sg:province":"Solothurn",
    "wof:name":"Bogaert Ren\u00e9",
    "wof:placetype":"venue"
},
  "geometry": {"coordinates":[7.528840065,47.2113189697],"type":"Point"}
}