{
  "type": "Feature",
  "properties": {
    "iso:country":"CH",
    "sg:address":"Dorfstrasse 126 8912 Obfelden. Postfach",
    "sg:city":"Obfelden",
    "sg:orig_category":"Grosshandel mit chemischen Erzeugnissen Herstellung von Verpackungen aus Kunststoff",
    "sg:phone":"+41 17614288",
    "sg:postcode":"8912",
    "sg:province":"Z\u00fcrich",
    "wof:name":"Plasti - Pac Z\u00fcrich Ag",
    "wof:placetype":"venue"
},
  "geometry": {"coordinates":[8.4072198868,47.2641868591],"type":"Point"}
}