{
  "type": "Feature",
  "properties": {
    "iso:country":"CH",
    "sg:address":"3054 Sch\u00fcpfen. Postfach",
    "sg:city":"Sch\u00fcpfen",
    "sg:orig_category":"Sportvereine Ballsport Tennis",
    "sg:phone":"+41 31 879 30 51",
    "sg:postcode":"3054",
    "sg:province":"Bern",
    "wof:name":"Tennisclub Sch\u00fcpfen",
    "wof:placetype":"venue"
},
  "geometry": {"coordinates":[7.3824448586,47.0429039001],"type":"Point"}
}