{
  "type": "Feature",
  "properties": {
    "iso:country":"CH",
    "sg:address":"Kirchweg 456",
    "sg:city":"K\u00fcnten",
    "sg:orig_category":"Vereine Bienenz\u00fcchter",
    "sg:phone":"+41 56 496 21 91",
    "sg:postcode":"5444",
    "sg:province":"Aargau",
    "wof:name":"Verein Deutschschweiz.& R\u00e4toromanischer Bienenfreunde",
    "wof:placetype":"venue"
},
  "geometry": {"coordinates":[8.3268127441,47.3892555237],"type":"Point"}
}