{
  "type": "Feature",
  "properties": {
    "iso:country":"CH",
    "sg:address":"Hinterdorfstrasse 6",
    "sg:city":"Boppelsen",
    "sg:orig_category":"Zimmerei, Dachdeckerei, Bauspenglerei U Abdichtung",
    "sg:phone":"+41 79 458 57 86",
    "sg:postcode":"8113",
    "sg:province":"Z\u00fcrich",
    "wof:name":"Streuli Bauspenglerei + Flachbedachungen",
    "wof:placetype":"venue"
},
  "geometry": {"coordinates":[8.4022531509,47.4713287354],"type":"Point"}
}