{
  "type": "Feature",
  "properties": {
    "iso:country":"CH",
    "sg:address":"Chemin De Praz-s\u00e9chaud 12",
    "sg:city":"Lausanne",
    "sg:orig_category":"Maurerarbeiten",
    "sg:phone":"+41 21 652 47 15",
    "sg:postcode":"1010",
    "sg:province":"Vaud",
    "wof:name":"Serge Nogare Travaux De Ma\u00e7onnerie",
    "wof:placetype":"venue"
},
  "geometry": {"coordinates":[6.6646060944,46.5377616882],"type":"Point"}
}