{
  "type": "Feature",
  "properties": {
    "iso:country":"CH",
    "sg:address":"Via Al Galletto",
    "sg:city":"Castione",
    "sg:orig_category":"Gewinnung von Kies U Sand",
    "sg:phone":"+41 91 820 10 20",
    "sg:postcode":"6532",
    "sg:province":"Ticino",
    "wof:name":"Scerri Otto Sa",
    "wof:placetype":"venue"
},
  "geometry": {"coordinates":[9.0365066528,46.2349243164],"type":"Point"}
}