{
  "type": "Feature",
  "properties": {
    "iso:country":"CH",
    "sg:address":"Kapellstrasse 3 Siebnen Sz 8862 Sch\u00fcbelbach. Postfach",
    "sg:city":"Siebnen",
    "sg:orig_category":"Softwareentwicklung U beratung",
    "sg:phone":"+41 71 388 62 80",
    "sg:postcode":"8854",
    "sg:province":"Schwyz",
    "wof:name":"Orgalex Legal Management Consulting Ag",
    "wof:placetype":"venue"
},
  "geometry": {"coordinates":[9.2514562607,47.4134788513],"type":"Point"}
}