{
  "type": "Feature",
  "properties": {
    "iso:country":"CH",
    "sg:address":"Ftan Via Da",
    "sg:city":"Scuol",
    "sg:orig_category":"Maler U Glasergewerbe",
    "sg:phone":"+41 81 864 00 66",
    "sg:postcode":"7550",
    "sg:province":"Graubunden",
    "wof:name":"Carmela Zanella",
    "wof:placetype":"venue"
},
  "geometry": {"coordinates":[10.3028278351,46.7987670898],"type":"Point"}
}