{
  "type": "Feature",
  "properties": {
    "iso:country":"CH",
    "sg:address":"Hirzenbachstrasse 7/11",
    "sg:city":"Z\u00fcrich",
    "sg:orig_category":"Eisenwaren Detailhandel",
    "sg:phone":"+41 848 800 545",
    "sg:postcode":"8051",
    "sg:province":"Z\u00fcrich",
    "wof:name":"Hauser Ag Eisenwarenhandel",
    "wof:placetype":"venue"
},
  "geometry": {"coordinates":[9.3766860962,47.5667114258],"type":"Point"}
}