{
  "type": "Feature",
  "properties": {
    "addr:full":"Via Baraggie 56 Ascona Ticino 6612",
    "addr:housenumber":"56",
    "addr:postcode":"6612",
    "addr:street":"Via Baraggie",
    "iso:country":"CH",
    "sg:address":"Via Baraggie 56",
    "sg:city":"Ascona",
    "sg:orig_category":"Architektur U Ingenieurb\u00fcros",
    "sg:phone":"+41 91 791 24 61",
    "sg:postcode":"6612",
    "sg:province":"Ticino",
    "wof:name":"Studio Tecnico Andina & Co",
    "wof:placetype":"venue"
},
  "geometry": {"coordinates":[8.774554,46.159168],"type":"Point"}
}