{
  "type": "Feature",
  "properties": {
    "iso:country":"CH",
    "sg:address":"R\u00fctihofstrasse 1",
    "sg:city":"Z\u00fcrich",
    "sg:orig_category":"Schreib U \u00dcbersetzungsb\u00fcros",
    "sg:postcode":"8049",
    "sg:province":"Z\u00fcrich",
    "wof:name":"Transtec-imhof Technische \u00dcbersetzungen",
    "wof:placetype":"venue"
},
  "geometry": {"coordinates":[8.4802618027,47.4142379761],"type":"Point"}
}