{
  "type": "Feature",
  "properties": {
    "addr:full":"Schmiedgasse 19 St.gallen St. Gallen 9000",
    "addr:housenumber":"19",
    "addr:postcode":"9000",
    "addr:street":"Schmiedgasse",
    "iso:country":"CH",
    "sg:address":"Schmiedgasse 19",
    "sg:city":"St.gallen",
    "sg:orig_category":"Detailhandel mit Bekleidung Detailhandel mit Herrenbekleidung",
    "sg:phone":"+41 71 622 51 56",
    "sg:postcode":"9000",
    "sg:province":"St. Gallen",
    "wof:name":"Schumacher Herrenmode",
    "wof:placetype":"venue"
},
  "geometry": {"coordinates":[9.138185,47.566669],"type":"Point"}
}