{
  "type": "Feature",
  "properties": {
    "iso:country":"CH",
    "sg:address":"Z\u00fcrcherstrasse 162",
    "sg:city":"Frauenfeld",
    "sg:classifiers":[
        {
            "category":"Banks & Credit Unions",
            "subcategory":"Bank",
            "type":"Services"
        }
    ],
    "sg:phone":"+41 26 495 90 90",
    "sg:postcode":"8500",
    "sg:province":"Thurgau",
    "wof:name":"Raiffeisenbank Freiburg Ost: St Antoni-tafers-freiburg",
    "wof:placetype":"venue"
},
  "geometry": {"coordinates":[7.25241,46.811985],"type":"Point"}
}