{
  "type": "Feature",
  "properties": {
    "iso:country":"CH",
    "sg:address":"Rue Peillonnex 39",
    "sg:city":"Ch\u00eane-bourg",
    "sg:orig_category":"Buchverlag Verlagsgewerbe",
    "sg:phone":"+41 17152621",
    "sg:postcode":"1225",
    "sg:province":"Gen\u00e8ve",
    "wof:name":"Edirep Ag",
    "wof:placetype":"venue"
},
  "geometry": {"coordinates":[8.543382,47.329384],"type":"Point"}
}