{
  "type": "Feature",
  "properties": {
    "iso:country":"CH",
    "sg:address":"Fenkernstrasse 12",
    "sg:city":"Kriens",
    "sg:orig_category":"Architekturb\u00fcros",
    "sg:phone":"+41 41 320 17 57",
    "sg:postcode":"6010",
    "sg:province":"Luzern",
    "wof:name":"Guido Oberholzer Bauberatung",
    "wof:placetype":"venue"
},
  "geometry": {"coordinates":[8.276245,47.033604],"type":"Point"}
}