{
  "type": "Feature",
  "properties": {
    "iso:country":"CH",
    "sg:address":"Pilatusstr. 7",
    "sg:city":"Luzern",
    "sg:classifiers":[
        {
            "category":"Shopping",
            "subcategory":"Clothing, Apparel, & Fashions",
            "type":"Retail Goods"
        }
    ],
    "sg:phone":"+41 21 652 67 05",
    "sg:postcode":"6003",
    "sg:province":"Luzern",
    "sg:tags":[
        "leather",
        "textile",
        "clothing",
        "shoe",
        "clothes"
    ],
    "wof:name":"Berger Diffusion Sa",
    "wof:placetype":"venue"
},
  "geometry": {"coordinates":[6.630149,46.555641],"type":"Point"}
}