{
  "type": "Feature",
  "properties": {
    "addr:full":"Zollikerstrasse 4 Z\u00fcrich Z\u00fcrich 8008",
    "addr:housenumber":"4",
    "addr:postcode":"8008",
    "addr:street":"Zollikerstrasse",
    "iso:country":"CH",
    "sg:address":"Zollikerstrasse 4",
    "sg:city":"Z\u00fcrich",
    "sg:orig_category":"Detailhandel mit Antiquit\u00e4ten U Gebrauchtwaren in Verkaufsr\u00e4umen",
    "sg:phone":"+41 13825533",
    "sg:postcode":"8008",
    "sg:province":"Z\u00fcrich",
    "wof:name":"D\u00e9j\u00e0-vu Second-hand Manuela Zamuner Weber",
    "wof:placetype":"venue"
},
  "geometry": {"coordinates":[8.554304,47.364201],"type":"Point"}
}