{
  "type": "Feature",
  "properties": {
    "iso:country":"CH",
    "sg:address":"Pavillonweg 6",
    "sg:city":"Biel/bienne",
    "sg:orig_category":"Atemtherapie Fussreflexzonenmassage",
    "sg:phone":"+41 32 322 75 05",
    "sg:postcode":"2502",
    "sg:province":"Bern",
    "wof:name":"Astrid Geisselhardt Atem-& Fussreflexzonentherapie",
    "wof:placetype":"venue"
},
  "geometry": {"coordinates":[7.235356,47.137779],"type":"Point"}
}