{
  "type": "Feature",
  "properties": {
    "iso:country":"CH",
    "sg:address":"Mellingerstrasse 160",
    "sg:city":"Baden",
    "sg:orig_category":"Tankstellen",
    "sg:phone":"+41 56 222 41 50",
    "sg:postcode":"5400",
    "sg:province":"Aargau",
    "wof:name":"Gebr. Sarescia",
    "wof:placetype":"venue"
},
  "geometry": {"coordinates":[8.2912921906,47.4663505554],"type":"Point"}
}