{
  "type": "Feature",
  "properties": {
    "iso:country":"CH",
    "sg:address":"Voa Sporz",
    "sg:city":"Lenzerheide/lai",
    "sg:orig_category":"Detailhandel mit Bekleidung Detailhandel mit Sportartikeln",
    "sg:phone":"+41 33 733 26 22",
    "sg:postcode":"7078",
    "sg:province":"Graubunden",
    "wof:name":"Andr\u00e9 Troxler Sport & Mode",
    "wof:placetype":"venue"
},
  "geometry": {"coordinates":[7.443727,46.454842],"type":"Point"}
}