{
  "type": "Feature",
  "properties": {
    "iso:country":"CH",
    "sg:address":"Chemin Du Boisy 40",
    "sg:city":"Lausanne",
    "sg:orig_category":"Detailhandel mit Textilien Detailhandel mit elektrischen Haushaltsger\u00e4ten",
    "sg:phone":"+41 71 755 43 42",
    "sg:postcode":"1004",
    "sg:province":"Vaud",
    "wof:name":"Basil Winiger Bernina N\u00e4hcenter",
    "wof:placetype":"venue"
},
  "geometry": {"coordinates":[9.5395040512,47.3778648376],"type":"Point"}
}