{
  "type": "Feature",
  "properties": {
    "addr:full":"Seefeldstrasse 6 Lachen Schwyz 8853",
    "addr:housenumber":"6",
    "addr:postcode":"8853",
    "addr:street":"Seefeldstrasse",
    "iso:country":"CH",
    "sg:address":"Seefeldstrasse 6",
    "sg:city":"Lachen",
    "sg:classifiers":[
        {
            "category":"Structure",
            "subcategory":"Office Building",
            "type":"Public Place"
        }
    ],
    "sg:phone":"+41 55 451 55 88",
    "sg:postcode":"8853",
    "sg:province":"Schwyz",
    "sg:tags":[
        "equipment",
        "alarm",
        "installation",
        "system"
    ],
    "wof:name":"Jurt Ag",
    "wof:placetype":"venue"
},
  "geometry": {"coordinates":[8.8575,47.196777],"type":"Point"}
}