{
  "type": "Feature",
  "properties": {
    "iso:country":"CH",
    "sg:address":"Rosenstrasse 48",
    "sg:city":"Dietikon",
    "sg:classifiers":[
        {
            "category":"Manufacturing",
            "subcategory":"Paper Products",
            "type":"Manufacturing & Wholesale Goods"
        }
    ],
    "sg:phone":"+41 17405951",
    "sg:postcode":"8953",
    "sg:province":"Z\u00fcrich",
    "sg:tags":[
        "adhesive",
        "self-adhesive",
        "labels",
        "label"
    ],
    "wof:name":"Rolf Weiss",
    "wof:placetype":"venue"
},
  "geometry": {"coordinates":[8.399712,47.392166],"type":"Point"}
}