{
  "type": "Feature",
  "properties": {
    "iso:country":"CH",
    "sg:address":"Fliederweg 5",
    "sg:city":"Staufen",
    "sg:orig_category":"Detailhandel mit elektrischen Haushalts-,Radio U Fernsehger\u00e4ten sowie Musikinstrumenten",
    "sg:phone":"+41 19916638",
    "sg:postcode":"5603",
    "sg:province":"Aargau",
    "wof:name":"Cetera Design Locher Urs J.",
    "wof:placetype":"venue"
},
  "geometry": {"coordinates":[8.1721191406,47.3828926086],"type":"Point"}
}