{
  "type": "Feature",
  "properties": {
    "iso:country":"CH",
    "sg:address":"Hutgasse 6",
    "sg:city":"Basel",
    "sg:orig_category":"RESTAURANTS: TEA-ROOMS",
    "sg:phone":"+41 61 261 20 91",
    "sg:postcode":"4001",
    "sg:province":"Basel-Stadt",
    "wof:name":"Schneiter Maja Rest. Zur Schuhmachernzunft",
    "wof:placetype":"venue"
},
  "geometry": {"coordinates":[7.5871992111,47.5576248169],"type":"Point"}
}