{
  "type": "Feature",
  "properties": {
    "iso:country":"CH",
    "sg:address":"B\u00fcrkiweg 8 3007 Bern. Postfach",
    "sg:city":"Bern",
    "sg:orig_category":"Unclassifiable Establishments",
    "sg:phone":"+41 37522575",
    "sg:postcode":"3005",
    "sg:province":"Bern",
    "wof:name":"Computer Solution Jaquier S\u00e0rl Programmes Et Mat\u00e9riel Informatiques; Achat, Vente Etc",
    "wof:placetype":"venue"
},
  "geometry": {"coordinates":[6.9182190895,46.6966667175],"type":"Point"}
}