{
  "type": "Feature",
  "properties": {
    "iso:country":"CH",
    "sg:address":"Multergasse 12",
    "sg:city":"St.gallen",
    "sg:orig_category":"Herstellung von medizinischen U chirurgischen Ger\u00e4ten sowie orthop\u00e4dischen Vorrichtungen",
    "sg:phone":"+41 71 223 21 81",
    "sg:postcode":"9000",
    "sg:province":"St. Gallen",
    "wof:name":"Dermlase Gmbh",
    "wof:placetype":"venue"
},
  "geometry": {"coordinates":[9.375576973,47.4244422913],"type":"Point"}
}