{
  "type": "Feature",
  "properties": {
    "iso:country":"CH",
    "sg:address":"Bonstettenstrasse 3",
    "sg:city":"Bern",
    "sg:orig_category":"Erschliessung von Grundst\u00fccken",
    "sg:postcode":"3012",
    "sg:province":"Bern",
    "wof:name":"Wohnbaugenossenschaft Immobilia",
    "wof:placetype":"venue"
},
  "geometry": {"coordinates":[7.4370851517,46.9579048157],"type":"Point"}
}