{
  "type": "Feature",
  "properties": {
    "iso:country":"CH",
    "sg:address":"Brisenstrasse 9",
    "sg:city":"Stans",
    "sg:orig_category":"Non-Classified Establishments",
    "sg:postcode":"6370",
    "sg:province":"Nidwalden",
    "wof:name":"Consularis Liegenschaften Und Beteiligungs Ag",
    "wof:placetype":"venue"
},
  "geometry": {"coordinates":[8.3148832321,46.9920654297],"type":"Point"}
}