{
  "type": "Feature",
  "properties": {
    "iso:country":"CH",
    "sg:address":"Bergli 17",
    "sg:city":"Ueberstorf",
    "sg:orig_category":"Softwareentwicklung U beratung",
    "sg:phone":"+41 31 741 47 77",
    "sg:postcode":"3182",
    "sg:province":"Fribourg",
    "wof:name":"Tms Consulting",
    "wof:placetype":"venue"
},
  "geometry": {"coordinates":[7.3193941116,46.875038147],"type":"Point"}
}