{
  "type": "Feature",
  "properties": {
    "iso:country":"CH",
    "sg:address":"1689",
    "sg:city":"Ch\u00e2telard-p-romont",
    "sg:orig_category":"Technische B\u00fcros Sanit\u00e4r",
    "sg:phone":"+41 56 634 33 33",
    "sg:postcode":"1689",
    "sg:province":"Fribourg",
    "wof:name":"Bio-cos Ag Planungsb\u00fcro",
    "wof:placetype":"venue"
},
  "geometry": {"coordinates":[8.4385242462,47.3228569031],"type":"Point"}
}