{
  "type": "Feature",
  "properties": {
    "iso:country":"CH",
    "sg:address":"6853 Ligornetto. Postfach",
    "sg:city":"Ligornetto",
    "sg:orig_category":"Non-Classified Establishments",
    "sg:postcode":"6853",
    "sg:province":"Ticino",
    "wof:name":"Palini Rocco",
    "wof:placetype":"venue"
},
  "geometry": {"coordinates":[8.9537200928,45.8623580933],"type":"Point"}
}