{
  "type": "Feature",
  "properties": {
    "iso:country":"CH",
    "sg:address":"6674",
    "sg:city":"Someo",
    "sg:orig_category":"Herstellung von Karosserien U Anh\u00e4ngern",
    "sg:phone":"+41 91 753 16 05",
    "sg:postcode":"6674",
    "sg:province":"Ticino",
    "wof:name":"Pezzali Alessio",
    "wof:placetype":"venue"
},
  "geometry": {"coordinates":[8.6663799286,46.2863311768],"type":"Point"}
}