{
  "type": "Feature",
  "properties": {
    "iso:country":"CH",
    "sg:address":"Guthirtstrasse 7",
    "sg:city":"Z\u00fcrich",
    "sg:orig_category":"Vorschulen, Kinderg\u00e4rten",
    "sg:phone":"+41 12718694",
    "sg:postcode":"8037",
    "sg:province":"Z\u00fcrich",
    "wof:name":"Katholischer Kindergarten Guthirt",
    "wof:placetype":"venue"
},
  "geometry": {"coordinates":[8.5277738571,47.3948287964],"type":"Point"}
}