{
  "type": "Feature",
  "properties": {
    "iso:country":"CH",
    "sg:address":"Zollbruckweg 2",
    "sg:city":"Landquart",
    "sg:orig_category":"Grosshandel mit B\u00fcromaschinen Grosshandel mit Datenverarbeitungsger\u00e4ten",
    "sg:phone":"+41 81 330 08 20",
    "sg:postcode":"7302",
    "sg:province":"Graubunden",
    "wof:name":"Grisocomp, Grischott",
    "wof:placetype":"venue"
},
  "geometry": {"coordinates":[9.5643577576,46.9665603638],"type":"Point"}
}