{
  "type": "Feature",
  "properties": {
    "iso:country":"CH",
    "sg:address":"Im Sp\u00e4ten 29",
    "sg:city":"Bonstetten",
    "sg:classifiers":[
        {
            "category":"Professional",
            "subcategory":"Employment Agencies",
            "type":"Services"
        }
    ],
    "sg:postcode":"8906",
    "sg:province":"Z\u00fcrich",
    "sg:tags":[
        "personal",
        "u",
        "stellenvermittlung"
    ],
    "wof:name":"Appella Ettore, Akkordunternehmung",
    "wof:placetype":"venue"
},
  "geometry": {"coordinates":[8.4747066498,47.3152770996],"type":"Point"}
}