{
  "type": "Feature",
  "properties": {
    "iso:country":"CH",
    "sg:address":"Pr\u00e9 Chemin Du 5",
    "sg:city":"St-prex",
    "sg:orig_category":"Sonstiges Versicherungsgewerbe",
    "sg:postcode":"1162",
    "sg:province":"Vaud",
    "wof:name":"As Assurances Services Moser Ernest",
    "wof:placetype":"venue"
},
  "geometry": {"coordinates":[6.4576702118,46.4821166992],"type":"Point"}
}