{
  "type": "Feature",
  "properties": {
    "iso:country":"CH",
    "sg:address":"Z\u00fcrcherstrasse 15",
    "sg:city":"Siebnen",
    "sg:orig_category":"Grosshandel mit Getr\u00e4nken",
    "sg:postcode":"8854",
    "sg:province":"Schwyz",
    "wof:name":"Keel-weine Ag",
    "wof:placetype":"venue"
},
  "geometry": {"coordinates":[8.8948497772,47.1753501892],"type":"Point"}
}