{
  "type": "Feature",
  "properties": {
    "iso:country":"CH",
    "sg:address":"Langenthalerstrasse 4 4802 Strengelbach. Postfach",
    "sg:city":"Strengelbach",
    "sg:orig_category":"Elektroinstallation Herstellung von sonstigen elektrischen Ausr\u00fcstungen",
    "sg:phone":"+41 17505958",
    "sg:postcode":"4802",
    "sg:province":"Aargau",
    "wof:name":"Elektro Weisser Und Partner Gmbh",
    "wof:placetype":"venue"
},
  "geometry": {"coordinates":[8.438501358,47.4180831909],"type":"Point"}
}