{
  "type": "Feature",
  "properties": {
    "iso:country":"CH",
    "sg:address":"Rue Sadaz 15",
    "sg:city":"Chavornay",
    "sg:orig_category":"Detailhandel mit elektrischen Haushalts-,Radio U Fernsehger\u00e4ten sowie Musikinstrumenten",
    "sg:postcode":"1373",
    "sg:province":"Vaud",
    "wof:name":"Sonomix Klay Et Vidmer",
    "wof:placetype":"venue"
},
  "geometry": {"coordinates":[6.5730748177,46.7145805359],"type":"Point"}
}