{
  "type": "Feature",
  "properties": {
    "iso:country":"CH",
    "sg:address":"Dorfgasse 8",
    "sg:city":"Arlesheim",
    "sg:orig_category":"Interessenvertretungen",
    "sg:phone":"+41 61 701 59 57",
    "sg:postcode":"4144",
    "sg:province":"Basel-Landschaft",
    "wof:name":"St. Ottilien, Hilfe, Schutz & Segen",
    "wof:placetype":"venue"
},
  "geometry": {"coordinates":[7.6214389801,47.4929237366],"type":"Point"}
}