{
  "type": "Feature",
  "properties": {
    "iso:country":"CH",
    "sg:address":"Ferrenmatt 20",
    "sg:city":"Hochdorf",
    "sg:orig_category":"Unternehmensberatung",
    "sg:phone":"+41 41 917 33 35",
    "sg:postcode":"6280",
    "sg:province":"Luzern",
    "wof:name":"Fs Management, Versicherungen Schnyder Franz",
    "wof:placetype":"venue"
},
  "geometry": {"coordinates":[8.2815465927,47.1872558594],"type":"Point"}
}