{
  "type": "Feature",
  "properties": {
    "iso:country":"CH",
    "sg:address":"Anglikerstrasse 42",
    "sg:city":"Villmergen",
    "sg:orig_category":"Herstellung von Konstruktionsteilen, Fertigbauteilen U Ausbauelementen aus Holz",
    "sg:postcode":"5612",
    "sg:province":"Aargau",
    "wof:name":"Peterhans Daniel",
    "wof:placetype":"venue"
},
  "geometry": {"coordinates":[8.2500400543,47.3493423462],"type":"Point"}
}