{
  "type": "Feature",
  "properties": {
    "iso:country":"CH",
    "sg:address":"Funkwiesenstrasse 35 8050 Z\u00fcrich. Postfach 8050 Z\u00fcrich",
    "sg:city":"Zust",
    "sg:orig_category":"Softwareentwicklung U beratung",
    "sg:phone":"+41 13114887",
    "sg:postcode":"50",
    "wof:name":"Ppc Project Procurement & Consulting Gmbh",
    "wof:placetype":"venue"
},
  "geometry": {"coordinates":[8.5580825806,47.4067611694],"type":"Point"}
}