{
  "type": "Feature",
  "properties": {
    "iso:country":"CH",
    "sg:address":"9107",
    "sg:city":"Urn\u00e4sch",
    "sg:orig_category":"Abwasserreinigung",
    "sg:phone":"+41 18441404",
    "sg:postcode":"9107",
    "sg:province":"Appenzell Ausserrhoden",
    "wof:name":"Abwasserreinigungsanlage Furthof",
    "wof:placetype":"venue"
},
  "geometry": {"coordinates":[8.425055,47.452076],"type":"Point"}
}