{
  "type": "Feature",
  "properties": {
    "iso:country":"CH",
    "sg:address":"Chirchgass 9",
    "sg:city":"Sevelen",
    "sg:orig_category":"Detailhandel mit Spielwaren Erbringung von Dienstleistungen f\u00fcr Unternehmen",
    "sg:phone":"+41 18693003",
    "sg:postcode":"9475",
    "sg:province":"St. Gallen",
    "wof:name":"Siegrist Modell-technik",
    "wof:placetype":"venue"
},
  "geometry": {"coordinates":[8.5087051392,47.6003112793],"type":"Point"}
}