{
  "type": "Feature",
  "properties": {
    "iso:country":"CH",
    "sg:address":"H\u00fcferen 7 8627 Gr\u00fcningen. Postfach",
    "sg:city":"Gr\u00fcningen",
    "sg:orig_category":"Grosshandel mit Holz U Baustoffen",
    "sg:postcode":"8627",
    "sg:province":"Z\u00fcrich",
    "wof:name":"Fisch Heinz Trading + Consulting",
    "wof:placetype":"venue"
},
  "geometry": {"coordinates":[8.7565450668,47.2822151184],"type":"Point"}
}