{
  "type": "Feature",
  "properties": {
    "iso:country":"CH",
    "sg:address":"Dorfstrasse 18",
    "sg:city":"Bonaduz",
    "sg:orig_category":"Detailhandel mit Spielwaren Detailhandel mit Textilien",
    "sg:phone":"+41 81 641 28 34",
    "sg:postcode":"7402",
    "sg:province":"Graubunden",
    "wof:name":"Rita Meyer's B\u00e4renwerkstatt",
    "wof:placetype":"venue"
},
  "geometry": {"coordinates":[9.3976888657,46.8116226196],"type":"Point"}
}