{
  "type": "Feature",
  "properties": {
    "iso:country":"CH",
    "sg:address":"Route De La B\u00e2tie 13",
    "sg:city":"Versoix",
    "sg:orig_category":"Mit Sport verbundene T\u00e4tigkeiten Sonstige mit Sport verbundene T\u00e4tigkeiten",
    "sg:phone":"+41 22 755 28 60",
    "sg:postcode":"1290",
    "sg:province":"Gen\u00e8ve",
    "wof:name":"Man\u00e8ge De Versoix Ecole De Dressage Sa",
    "wof:placetype":"venue"
},
  "geometry": {"coordinates":[6.1327328682,46.2826881409],"type":"Point"}
}