{
  "type": "Feature",
  "properties": {
    "iso:country":"CH",
    "sg:address":"8882",
    "sg:city":"Unterterzen",
    "sg:orig_category":"Reiseb\u00fcros U Reiseveranstalter",
    "sg:phone":"+41 55 220 57 57",
    "sg:postcode":"8882",
    "sg:province":"St. Gallen",
    "wof:name":"Verkehrs-& Versch\u00f6nerungs- Verein Rapperswil-jona",
    "wof:placetype":"venue"
},
  "geometry": {"coordinates":[8.8153409958,47.225605011],"type":"Point"}
}