{
  "type": "Feature",
  "properties": {
    "iso:country":"CH",
    "sg:address":"Ifangstrasse 91",
    "sg:city":"R\u00fcmlang",
    "sg:classifiers":[
        {
            "category":"Utilities",
            "subcategory":"Mobile Phone",
            "type":"Services"
        }
    ],
    "sg:phone":"+41 18177676",
    "sg:postcode":"8153",
    "sg:province":"Z\u00fcrich",
    "sg:tags":[
        "dictaphone",
        "accessory"
    ],
    "wof:name":"Europe Ag",
    "wof:placetype":"venue"
},
  "geometry": {"coordinates":[8.5381784439,47.4470672607],"type":"Point"}
}