{
  "type": "Feature",
  "properties": {
    "iso:country":"CH",
    "sg:address":"Mulflerstrasse 12",
    "sg:city":"Bachs",
    "sg:orig_category":"Grosshandel mit Blumen U Pflanzen Herstellung von Werkzeugen",
    "sg:phone":"+41 56 441 57 39",
    "sg:postcode":"8164",
    "sg:province":"Z\u00fcrich",
    "wof:name":"Hortima Ag",
    "wof:placetype":"venue"
},
  "geometry": {"coordinates":[8.2074804306,47.4637489319],"type":"Point"}
}