{
  "type": "Feature",
  "properties": {
    "addr:full":"Ra Car\u00e0 21 Scairolo Montagnola Ticino 6926",
    "addr:housenumber":"21",
    "addr:postcode":"6926",
    "addr:street":"Scairolo",
    "iso:country":"CH",
    "sg:address":"Ra Car\u00e0 21 Scairolo",
    "sg:city":"Montagnola",
    "sg:classifiers":[
        {
            "category":"Home & Garden",
            "subcategory":"Home Furnishings",
            "type":"Retail Goods"
        }
    ],
    "sg:phone":"+41 91 993 06 18",
    "sg:postcode":"6926",
    "sg:province":"Ticino",
    "sg:tags":[
        "air-conditioners"
    ],
    "wof:name":"Klm Suisse Sagl",
    "wof:placetype":"venue"
},
  "geometry": {"coordinates":[8.916906,45.981918],"type":"Point"}
}