{
  "type": "Feature",
  "properties": {
    "iso:country":"CH",
    "sg:address":"Felbenstrasse 24 9403 Goldach. Postfach",
    "sg:city":"Goldach",
    "sg:orig_category":"Vermietung von Automobilen",
    "sg:postcode":"9403",
    "sg:province":"St. Gallen",
    "wof:name":"Rent-it Ag Fahrzeuge, Maschinen U. Ger\u00e4te; Vermietung Usw.",
    "wof:placetype":"venue"
},
  "geometry": {"coordinates":[9.4669151306,47.4846191406],"type":"Point"}
}