{
  "type": "Feature",
  "properties": {
    "iso:country":"CH",
    "sg:address":"Rue De L'industrie 31",
    "sg:city":"Tramelan",
    "sg:orig_category":"Detailhandel mit Radio U Fernsehger\u00e4ten Detailhandel mit elektrischen Haushaltsger\u00e4ten",
    "sg:phone":"+41 32 487 66 55",
    "sg:postcode":"2720",
    "sg:province":"Bern",
    "wof:name":"Schnegg Sa",
    "wof:placetype":"venue"
},
  "geometry": {"coordinates":[7.0983691216,47.2239761353],"type":"Point"}
}