{
  "type": "Feature",
  "properties": {
    "iso:country":"CH",
    "sg:address":"Place Chauderon 16",
    "sg:city":"Lausanne",
    "sg:orig_category":"Zahnarztpraxen",
    "sg:phone":"+41 21 341 03 41",
    "sg:postcode":"1003",
    "sg:province":"Vaud",
    "wof:name":"Clinique Dentaire De Chauderon Sa",
    "wof:placetype":"venue"
},
  "geometry": {"coordinates":[6.6260609627,46.523601532],"type":"Point"}
}