{
  "type": "Feature",
  "properties": {
    "iso:country":"CH",
    "sg:address":"Plattenstrasse 62",
    "sg:city":"Meilen",
    "sg:orig_category":"Gesundheitswesen",
    "sg:postcode":"8706",
    "sg:province":"Z\u00fcrich",
    "wof:name":"Spitex-verein Meilen",
    "wof:placetype":"venue"
},
  "geometry": {"coordinates":[8.6387386322,47.2735404968],"type":"Point"}
}