{
  "type": "Feature",
  "properties": {
    "iso:country":"CH",
    "sg:address":"La Carmagnole",
    "sg:city":"Semsales",
    "sg:orig_category":"Architektur U Ingenieurb\u00fcros",
    "sg:postcode":"1623",
    "sg:province":"Fribourg",
    "wof:name":"Jean-claude Constantin, Succursale Du Bouveret",
    "wof:placetype":"venue"
},
  "geometry": {"coordinates":[6.869283,46.383884],"type":"Point"}
}