{
  "type": "Feature",
  "properties": {
    "iso:country":"CH",
    "sg:address":"Wellenried 6",
    "sg:city":"Schwarzenburg",
    "sg:orig_category":"Architektur U Ingenieurb\u00fcros Architekturb\u00fcros",
    "sg:phone":"+41 31 731 13 13",
    "sg:postcode":"3150",
    "sg:province":"Bern",
    "wof:name":"E + H Vifian + Partner Dipl Arch Ag",
    "wof:placetype":"venue"
},
  "geometry": {"coordinates":[7.351211,46.820034],"type":"Point"}
}