{
  "type": "Feature",
  "properties": {
    "iso:country":"CH",
    "sg:address":"Drosselweg 8",
    "sg:city":"Lenzburg",
    "sg:orig_category":"Herstellung von elektronischen Bauelementen",
    "sg:phone":"+41 62 891 19 66",
    "sg:postcode":"5600",
    "sg:province":"Aargau",
    "wof:name":"Voice Control S. Br\u00fcngger",
    "wof:placetype":"venue"
},
  "geometry": {"coordinates":[8.1887025833,47.3811645508],"type":"Point"}
}