{
  "type": "Feature",
  "properties": {
    "iso:country":"CH",
    "sg:address":"Route De Lausanne 43",
    "sg:city":"Mont-sur-lausanne",
    "sg:orig_category":"Wirtschaftspr\u00fcfung, Steuerberatung U Treuhand",
    "sg:phone":"+41 21 652 64 54",
    "sg:postcode":"1052",
    "sg:province":"Vaud",
    "wof:name":"Vullyamoz Antoinette",
    "wof:placetype":"venue"
},
  "geometry": {"coordinates":[6.6337828636,46.5527992249],"type":"Point"}
}