{
  "type": "Feature",
  "properties": {
    "iso:country":"CH",
    "sg:address":"Combes D'enges 67 2067 Chaumont. Postfach",
    "sg:city":"Chaumont",
    "sg:orig_category":"Finanzierungsinstitutionen",
    "sg:postcode":"2067",
    "sg:province":"Neuch\u00e2tel",
    "wof:name":"Confortex S\u00e0rl",
    "wof:placetype":"venue"
},
  "geometry": {"coordinates":[5.8745851517,46.3994598389],"type":"Point"}
}