{
  "type": "Feature",
  "properties": {
    "iso:country":"CH",
    "sg:address":"Kohlweg 134",
    "sg:city":"Wenslingen",
    "sg:orig_category":"Gartenbau Geb\u00e4ude, Wohnungsreinigung",
    "sg:phone":"+41 61 991 04 16",
    "sg:postcode":"4493",
    "sg:province":"Basel-Landschaft",
    "wof:name":"Ewald Erni Haus-& Gartenpflege",
    "wof:placetype":"venue"
},
  "geometry": {"coordinates":[7.9048547745,47.4415969849],"type":"Point"}
}