{
  "type": "Feature",
  "properties": {
    "iso:country":"CH",
    "sg:address":"8753",
    "sg:city":"Mollis",
    "sg:orig_category":"Wirtschaftspr\u00fcfung, Steuerberatung U Treuhand",
    "sg:postcode":"8753",
    "sg:province":"Glarus",
    "wof:name":"Nieder\u00f6st B.",
    "wof:placetype":"venue"
},
  "geometry": {"coordinates":[9.0745248795,47.0914382935],"type":"Point"}
}