{
  "type": "Feature",
  "properties": {
    "iso:country":"CH",
    "sg:address":"Gutenbergstrasse 33",
    "sg:city":"Bern",
    "sg:orig_category":"Kinderkrippen U horte",
    "sg:phone":"+41 31 381 62 60",
    "sg:postcode":"3011",
    "sg:province":"Bern",
    "wof:name":"Kinderkrippe Mikado D.berner-& Schweiz.mobiliarversicherungen",
    "wof:placetype":"venue"
},
  "geometry": {"coordinates":[7.4346899986,46.9437332153],"type":"Point"}
}