{
  "type": "Feature",
  "properties": {
    "iso:country":"CH",
    "sg:address":"Ober-kuonimattweg 24",
    "sg:city":"Kriens",
    "sg:orig_category":"Interessenvertretungen",
    "sg:postcode":"6010",
    "sg:province":"Luzern",
    "wof:name":"Parkplatzgenossenschaft Rosenstrasse, St. Margrethen",
    "wof:placetype":"venue"
},
  "geometry": {"coordinates":[9.6476955414,47.446811676],"type":"Point"}
}