{
  "type": "Feature",
  "properties": {
    "iso:country":"CH",
    "sg:address":"Bahnhofstrasse 54",
    "sg:city":"Schaffhausen",
    "sg:classifiers":[
        {
            "category":"Bars & Pubs",
            "type":"Food & Drink"
        }
    ],
    "sg:phone":"+41 52 625 11 35",
    "sg:postcode":"8200",
    "sg:province":"Schaffhausen",
    "wof:name":"Gleis 6 Bar Wildhaber P.",
    "wof:placetype":"venue"
},
  "geometry": {"coordinates":[8.633898,47.698849],"type":"Point"}
}