{
  "type": "Feature",
  "properties": {
    "iso:country":"CH",
    "sg:address":"Via Brogeda 3",
    "sg:city":"Chiasso",
    "sg:orig_category":"Autotransporte international Sonstige Verkehrsvermittlung",
    "sg:phone":"+41 91 682 30 91",
    "sg:postcode":"6830",
    "sg:province":"Ticino",
    "wof:name":"Pd Trans Sagl",
    "wof:placetype":"venue"
},
  "geometry": {"coordinates":[9.035436,45.837357],"type":"Point"}
}