{
  "type": "Feature",
  "properties": {
    "iso:country":"CH",
    "sg:address":"Halacherstrasse 3",
    "sg:city":"Berikon",
    "sg:orig_category":"Gymnastikschulen",
    "sg:phone":"+41 56 633 42 58",
    "sg:postcode":"8965",
    "sg:province":"Aargau",
    "wof:name":"Aloisia N\u00e4pflin Gymnastikstudio",
    "wof:placetype":"venue"
},
  "geometry": {"coordinates":[8.3720836639,47.3530158997],"type":"Point"}
}