{
  "type": "Feature",
  "properties": {
    "iso:country":"CH",
    "sg:address":"Joggenrainweg 15",
    "sg:city":"M\u00e4nnedorf",
    "sg:orig_category":"Politische Parteien CVP",
    "sg:phone":"+41 12062900",
    "sg:postcode":"8708",
    "sg:province":"Z\u00fcrich",
    "wof:name":"Cvp Sektion M\u00e4nnedorf",
    "wof:placetype":"venue"
},
  "geometry": {"coordinates":[8.6960773468,47.256111145],"type":"Point"}
}