{
  "type": "Feature",
  "properties": {
    "iso:country":"CH",
    "sg:address":"Sonnenrain 137",
    "sg:city":"Attelwil",
    "sg:orig_category":"Unclassifiable Establishments",
    "sg:postcode":"5056",
    "sg:province":"Aargau",
    "wof:name":"Top Heizungen Und Sanit\u00e4r Gmbh",
    "wof:placetype":"venue"
},
  "geometry": {"coordinates":[8.0407571793,47.2608947754],"type":"Point"}
}