{
  "type": "Feature",
  "properties": {
    "iso:country":"CH",
    "sg:address":"Route Des Bois-des-iles 1",
    "sg:city":"Collex",
    "sg:classifiers":[
        {
            "category":"Restaurant",
            "type":"Food & Drink"
        }
    ],
    "sg:phone":"+41 22 774 04 98",
    "sg:postcode":"1239",
    "sg:province":"Gen\u00e8ve",
    "wof:name":"Auberge Des Bois",
    "wof:placetype":"venue"
},
  "geometry": {"coordinates":[6.1235718727,46.2749404907],"type":"Point"}
}