{
  "type": "Feature",
  "properties": {
    "iso:country":"CH",
    "sg:address":"3257",
    "sg:city":"Grossaffoltern",
    "sg:orig_category":"Sportvereine Sch\u00fctzen",
    "sg:phone":"+41 32 351 31 07",
    "sg:postcode":"3257",
    "sg:province":"Bern",
    "wof:name":"Milit\u00e4rsch\u00fctzengesellschaft",
    "wof:placetype":"venue"
},
  "geometry": {"coordinates":[7.3634147644,47.1084861755],"type":"Point"}
}