{
  "type": "Feature",
  "properties": {
    "iso:country":"CH",
    "sg:address":"Sch\u00fctzenmattweg 12",
    "sg:city":"Olten",
    "sg:orig_category":"Herstellung von Metallkonstruktionen Stahl U Leichtmetallbau",
    "sg:phone":"+41 62 212 23 29",
    "sg:postcode":"4600",
    "sg:province":"Solothurn",
    "wof:name":"Schibli Gebr. Metallbau Ag",
    "wof:placetype":"venue"
},
  "geometry": {"coordinates":[7.9032502174,47.3490257263],"type":"Point"}
}