{
  "type": "Feature",
  "properties": {
    "iso:country":"CH",
    "sg:address":"Via Monte Br\u00e8 9",
    "sg:city":"Lugano",
    "sg:orig_category":"Patentverwertung Rechtsberatung",
    "sg:phone":"+41 91 922 08 19",
    "sg:postcode":"6900",
    "sg:province":"Ticino",
    "wof:name":"Nte Nuove Tecnologie Edili 3000 Sagl",
    "wof:placetype":"venue"
},
  "geometry": {"coordinates":[8.958111763,46.0122871399],"type":"Point"}
}