{
  "type": "Feature",
  "properties": {
    "iso:country":"CH",
    "sg:address":"Grand Place Immeuble 3963 Crans-sur-sierre. Postfach",
    "sg:city":"Crans-sur-sierre",
    "sg:orig_category":"Herstellung von elektronischen Bauelementen",
    "sg:phone":"+41 56 483 34 44",
    "sg:postcode":"3963",
    "sg:province":"Valais",
    "wof:name":"Mpi Distribution Ag",
    "wof:placetype":"venue"
},
  "geometry": {"coordinates":[8.2939882278,47.4476890564],"type":"Point"}
}