{
  "type": "Feature",
  "properties": {
    "iso:country":"CH",
    "sg:address":"Amthausgasse 7",
    "sg:city":"Bern",
    "sg:orig_category":"Unclassifiable Establishments",
    "sg:postcode":"3011",
    "sg:province":"Bern",
    "wof:name":"Dino Renner, Keramische Wand Und Bodenbel\u00e4ge",
    "wof:placetype":"venue"
},
  "geometry": {"coordinates":[9.8255939484,46.7957420349],"type":"Point"}
}