{
  "type": "Feature",
  "properties": {
    "iso:country":"CH",
    "sg:address":"Pfistergasse 38",
    "sg:city":"Zofingen",
    "sg:orig_category":"Fernmeldedienste",
    "sg:postcode":"4800",
    "sg:province":"Aargau",
    "wof:name":"Commscon Ag",
    "wof:placetype":"venue"
},
  "geometry": {"coordinates":[7.9450569153,47.2873382568],"type":"Point"}
}