{
  "type": "Feature",
  "properties": {
    "iso:country":"CH",
    "sg:address":"Sonnenbergstrasse 45",
    "sg:city":"Abtwil",
    "sg:orig_category":"Packaging Recycling",
    "sg:phone":"+41 71 311 38 62",
    "sg:postcode":"9030",
    "sg:province":"St. Gallen",
    "wof:name":"Aniva Ag",
    "wof:placetype":"venue"
},
  "geometry": {"coordinates":[9.3213653564,47.4281806946],"type":"Point"}
}