{
  "type": "Feature",
  "properties": {
    "iso:country":"CH",
    "sg:address":"Affolterstrasse 3",
    "sg:city":"Luterbach",
    "sg:orig_category":"Tierarztpraxis",
    "sg:phone":"+41 81 302 73 02",
    "sg:postcode":"4542",
    "sg:province":"Solothurn",
    "wof:name":"Dr. Med. Vet. Martin Klaas Tierarzt",
    "wof:placetype":"venue"
},
  "geometry": {"coordinates":[9.5057859421,47.00365448],"type":"Point"}
}