{
  "type": "Feature",
  "properties": {
    "iso:country":"CH",
    "sg:address":"Bahnhofstrasse 10 6244 Nebikon. Postfach",
    "sg:city":"Nebikon",
    "sg:classifiers":[
        {
            "category":"Travel",
            "subcategory":"Hotels & Motels",
            "type":"Entertainment"
        }
    ],
    "sg:phone":"+41 62 756 10 41",
    "sg:postcode":"6244",
    "sg:province":"Luzern",
    "sg:tags":[
        "hotels",
        "mit",
        "restaurant"
    ],
    "wof:name":"Gasthof Bahnhof Rogger R.",
    "wof:placetype":"venue"
},
  "geometry": {"coordinates":[7.9771242142,47.192325592],"type":"Point"}
}