{
  "type": "Feature",
  "properties": {
    "iso:country":"CH",
    "sg:address":"Eichhornweg 2",
    "sg:city":"Kreuzlingen",
    "sg:orig_category":"Softwareentwicklung U beratung",
    "sg:phone":"+41 71 672 29 52",
    "sg:postcode":"8280",
    "sg:province":"Thurgau",
    "wof:name":"Zwicky Media",
    "wof:placetype":"venue"
},
  "geometry": {"coordinates":[9.1812295914,47.637966156],"type":"Point"}
}