{
  "type": "Feature",
  "properties": {
    "iso:country":"CH",
    "sg:address":"Freie Strasse 97",
    "sg:city":"Basel",
    "sg:orig_category":"Detailhandel mit Textilien",
    "sg:phone":"+41 61 272 59 55",
    "sg:postcode":"4051",
    "sg:province":"Basel-Stadt",
    "wof:name":"Sphinx Gebr.erne & Co",
    "wof:placetype":"venue"
},
  "geometry": {"coordinates":[7.59126091,47.5548248291],"type":"Point"}
}