{
  "type": "Feature",
  "properties": {
    "addr:full":"Hauptstrasse 52 Meinisberg Bern 2554",
    "addr:housenumber":"52",
    "addr:postcode":"2554",
    "addr:street":"Hauptstrasse",
    "iso:country":"CH",
    "sg:address":"Hauptstrasse 52",
    "sg:city":"Meinisberg",
    "sg:orig_category":"Chemin\u00e9e- and Ofenbau",
    "sg:phone":"+41 32 377 20 52",
    "sg:postcode":"2554",
    "sg:province":"Bern",
    "wof:name":"Thomas Berger Ofen-& Chemin\u00e9ebau",
    "wof:placetype":"venue"
},
  "geometry": {"coordinates":[7.347708,47.159374],"type":"Point"}
}