{
  "type": "Feature",
  "properties": {
    "iso:country":"CH",
    "sg:address":"Hauptgasse 27",
    "sg:city":"Willisau",
    "sg:orig_category":"Detailhandel mit Geschenkartikeln U Souvenirs Grosshandel mit Textilien",
    "sg:phone":"+41 41 970 36 81",
    "sg:postcode":"6130",
    "sg:province":"Luzern",
    "wof:name":"Stilismo-flash Ag",
    "wof:placetype":"venue"
},
  "geometry": {"coordinates":[7.990073204,47.1203346252],"type":"Point"}
}