{
  "type": "Feature",
  "properties": {
    "iso:country":"CH",
    "sg:address":"Bahnhofstrasse 30",
    "sg:city":"Zug",
    "sg:orig_category":"Non-Classified Establishments",
    "sg:postcode":"6300",
    "sg:province":"Zug",
    "wof:name":"R+b+b Beteiligungen Ag",
    "wof:placetype":"venue"
},
  "geometry": {"coordinates":[8.555056572,47.316078186],"type":"Point"}
}