{
  "type": "Feature",
  "properties": {
    "iso:country":"CH",
    "sg:address":"Hertizentrum 10 6300 Zug. Postfach",
    "sg:city":"Zug",
    "sg:orig_category":"Verbraucherm\u00e4rkte > 2500 m2 Verwaltung von Immobilien",
    "sg:phone":"+41 26 407 77 77",
    "sg:postcode":"6303",
    "sg:province":"Zug",
    "wof:name":"Hypermarch\u00e9 Jumbo Sa",
    "wof:placetype":"venue"
},
  "geometry": {"coordinates":[6.2000789642,46.938709259],"type":"Point"}
}