{
  "type": "Feature",
  "properties": {
    "iso:country":"CH",
    "sg:address":"Fabrikstrasse 16",
    "sg:city":"Buchs",
    "sg:orig_category":"Vacuum Technology Components",
    "sg:phone":"+41 81 750 06 70",
    "sg:postcode":"9470",
    "sg:province":"St. Gallen",
    "wof:name":"Evac Ag",
    "wof:placetype":"venue"
},
  "geometry": {"coordinates":[9.4827594757,47.1726951599],"type":"Point"}
}