{
  "type": "Feature",
  "properties": {
    "iso:country":"CH",
    "sg:address":"Kirchstrasse 12",
    "sg:city":"Flums",
    "sg:orig_category":"Kantonalbanken",
    "sg:phone":"+41 81 733 22 23",
    "sg:postcode":"8890",
    "sg:province":"St. Gallen",
    "wof:name":"St.galler Kantonalbank",
    "wof:placetype":"venue"
},
  "geometry": {"coordinates":[9.3440446854,47.0904312134],"type":"Point"}
}