{
  "type": "Feature",
  "properties": {
    "iso:country":"CH",
    "sg:address":"Boulevard Georges-favon 16",
    "sg:city":"Gen\u00e8ve",
    "sg:orig_category":"Detailhandel mit Geschenkartikeln U Souvenirs",
    "sg:phone":"+41 22 329 47 77",
    "sg:postcode":"1204",
    "sg:province":"Gen\u00e8ve",
    "wof:name":"Boutique Evasion Jeans & Casuals",
    "wof:placetype":"venue"
},
  "geometry": {"coordinates":[6.1400408745,46.2028961182],"type":"Point"}
}