{
  "type": "Feature",
  "properties": {
    "iso:country":"CH",
    "sg:address":"6674",
    "sg:city":"Someo",
    "sg:orig_category":"Allgemeiner Hoch U Tiefbau",
    "sg:phone":"+41 91 754 22 68",
    "sg:postcode":"6674",
    "sg:province":"Ticino",
    "wof:name":"Guardini Fernando",
    "wof:placetype":"venue"
},
  "geometry": {"coordinates":[8.66638,46.286331],"type":"Point"}
}