{
  "type": "Feature",
  "properties": {
    "iso:country":"CH",
    "sg:address":"Rue Des Moulins 39",
    "sg:city":"Versoix",
    "sg:orig_category":"Innendekorationsateliers Maler U Glasergewerbe",
    "sg:phone":"+41 22 300 15 80",
    "sg:postcode":"1290",
    "sg:province":"Gen\u00e8ve",
    "wof:name":"Sch\u00fctt Willy",
    "wof:placetype":"venue"
},
  "geometry": {"coordinates":[6.1436758041,46.1862754822],"type":"Point"}
}