{
  "type": "Feature",
  "properties": {
    "iso:country":"CH",
    "sg:address":"Guldifeld 33",
    "sg:city":"Ueberstorf",
    "sg:classifiers":[
        {
            "category":"Insurance",
            "subcategory":"Insurance Agent",
            "type":"Services"
        }
    ],
    "sg:phone":"+41 31 741 18 44",
    "sg:postcode":"3182",
    "sg:province":"Fribourg",
    "sg:tags":[
        "versicherungsagenturen",
        "-broker"
    ],
    "wof:name":"Berner Lebensversicherungen Agentur Charles Binggeli",
    "wof:placetype":"venue"
},
  "geometry": {"coordinates":[7.3242287636,46.8745956421],"type":"Point"}
}