{
  "type": "Feature",
  "properties": {
    "iso:country":"CH",
    "sg:address":"Rain 24",
    "sg:city":"Aarau",
    "sg:orig_category":"Detailhandel mit Geschenkartikeln U Souvenirs Sonstige k\u00fcnstlerische U schriftstellerische T\u00e4tigkeit",
    "sg:phone":"+41 62 822 04 80",
    "sg:postcode":"5000",
    "sg:province":"Aargau",
    "wof:name":"Viviane Nicol",
    "wof:placetype":"venue"
},
  "geometry": {"coordinates":[8.0440349579,47.3907814026],"type":"Point"}
}