{
  "type": "Feature",
  "properties": {
    "iso:country":"CH",
    "sg:address":"Haag 20",
    "sg:city":"Selzach",
    "sg:classifiers":[
        {
            "category":"Restaurant",
            "type":"Food & Drink"
        }
    ],
    "sg:phone":"+41 32 641 10 71",
    "sg:postcode":"2545",
    "sg:province":"Solothurn",
    "wof:name":"Restaurant Zur S\u00e4ge",
    "wof:placetype":"venue"
},
  "geometry": {"coordinates":[7.4402661324,47.2006378174],"type":"Point"}
}