{
  "type": "Feature",
  "properties": {
    "iso:country":"CH",
    "sg:address":"Gr\u00e4tzlistrasse 16 Glattbrugg",
    "sg:city":"Opfikon",
    "sg:orig_category":"Maler U Glasergewerbe",
    "sg:phone":"+41 18510791",
    "sg:postcode":"8152",
    "sg:province":"Z\u00fcrich",
    "wof:name":"Bachmann Und D\u00fctschler, Maler Und Tapezierergesch\u00e4ft",
    "wof:placetype":"venue"
},
  "geometry": {"coordinates":[8.4942111969,47.4951286316],"type":"Point"}
}