{
  "type": "Feature",
  "properties": {
    "iso:country":"CH",
    "sg:address":"Via Nasora 21",
    "sg:city":"Comano",
    "sg:orig_category":"Vermietung U Verpachtung von eigenen Immobilien",
    "sg:postcode":"6949",
    "sg:province":"Ticino",
    "wof:name":"Tischhauser Immobilien Ag",
    "wof:placetype":"venue"
},
  "geometry": {"coordinates":[9.3842525482,47.3920249939],"type":"Point"}
}