{
  "type": "Feature",
  "properties": {
    "iso:country":"CH",
    "sg:address":"Igis",
    "sg:city":"Igis",
    "sg:classifiers":[
        {
            "category":"Banks & Credit Unions",
            "subcategory":"Bank",
            "type":"Services"
        }
    ],
    "sg:phone":"+41 81 300 04 10",
    "sg:postcode":"7206",
    "sg:province":"Graubunden",
    "wof:name":"Graub\u00fcndner Kantonalbank",
    "wof:placetype":"venue"
},
  "geometry": {"coordinates":[9.57442,46.944061],"type":"Point"}
}