{
  "type": "Feature",
  "properties": {
    "iso:country":"CH",
    "sg:address":"Basch\u00e4rstrasse 28",
    "sg:city":"Vilters",
    "sg:orig_category":"Allgemeiner Hoch U Tiefbau Hoch U Tiefbau",
    "sg:phone":"+41 81 723 32 62",
    "sg:postcode":"7324",
    "sg:province":"St. Gallen",
    "wof:name":"Anton Vils Bauunternehmung",
    "wof:placetype":"venue"
},
  "geometry": {"coordinates":[9.461328,47.02483],"type":"Point"}
}