{
  "type": "Feature",
  "properties": {
    "iso:country":"CH",
    "sg:address":"Feldstrasse 11",
    "sg:city":"B\u00fcron",
    "sg:orig_category":"Herstellung von Konstruktionsteilen, Fertigbauteilen U Ausbauelementen aus Holz",
    "sg:postcode":"6233",
    "sg:province":"Luzern",
    "wof:name":"Dubach Urs Ag",
    "wof:placetype":"venue"
},
  "geometry": {"coordinates":[8.0901355743,47.2123031616],"type":"Point"}
}