{
  "type": "Feature",
  "properties": {
    "iso:country":"CH",
    "sg:address":"Chamin Vieux",
    "sg:city":"St-cergue",
    "sg:orig_category":"Technische, physikalische U chemische Untersuchung",
    "sg:phone":"+41 22 360 15 39",
    "sg:postcode":"1264",
    "sg:province":"Vaud",
    "wof:name":"Garret Patrice",
    "wof:placetype":"venue"
},
  "geometry": {"coordinates":[6.1360931396,46.4477310181],"type":"Point"}
}