{
  "type": "Feature",
  "properties": {
    "iso:country":"CH",
    "sg:address":"Rebenweg 17",
    "sg:city":"L\u00fcscherz",
    "sg:orig_category":"Allgemeiner Hoch U Tiefbau",
    "sg:postcode":"2576",
    "sg:province":"Bern",
    "wof:name":"Neoplan Bau Ag",
    "wof:placetype":"venue"
},
  "geometry": {"coordinates":[9.373715,47.426392],"type":"Point"}
}