{
  "type": "Feature",
  "properties": {
    "iso:country":"CH",
    "sg:address":"Wassermatte 1",
    "sg:city":"Sursee",
    "sg:orig_category":"Herstellung von Anstrichmitteln, Druckfarben U Kitten Herstellung von Kunststoff in Prim\u00e4rformen",
    "sg:phone":"+41 41 469 91 11",
    "sg:postcode":"6210",
    "sg:province":"Luzern",
    "wof:name":"Collano Ag",
    "wof:placetype":"venue"
},
  "geometry": {"coordinates":[8.1944198608,47.115650177],"type":"Point"}
}