{
  "type": "Feature",
  "properties": {
    "iso:country":"CH",
    "sg:address":"B\u00fc\u00fcneweg 46",
    "sg:city":"Wanzwil",
    "sg:orig_category":"Grosshandel mit Getr\u00e4nken Grosshandel mit sonstigen Getr\u00e4nken",
    "sg:phone":"+41 62 961 43 73",
    "sg:postcode":"3372",
    "sg:province":"Bern",
    "wof:name":"Hugo Hess Valserdepot",
    "wof:placetype":"venue"
},
  "geometry": {"coordinates":[7.6921977997,47.2015609741],"type":"Point"}
}