{
  "type": "Feature",
  "properties": {
    "iso:country":"CH",
    "sg:address":"Untere B\u00f6nigstrasse 68",
    "sg:city":"Interlaken",
    "sg:orig_category":"Gartenbau",
    "sg:postcode":"3800",
    "sg:province":"Bern",
    "wof:name":"Baumschule Bugmann W. + L.",
    "wof:placetype":"venue"
},
  "geometry": {"coordinates":[7.5834679604,47.4911842346],"type":"Point"}
}