{
  "type": "Feature",
  "properties": {
    "iso:country":"CH",
    "sg:address":"Hauptgasse 25",
    "sg:city":"Olten",
    "sg:orig_category":"RESTAURANTS: TEA-ROOMS",
    "sg:postcode":"4600",
    "sg:province":"Solothurn",
    "wof:name":"Nakamura-voisard Toshinobu",
    "wof:placetype":"venue"
},
  "geometry": {"coordinates":[6.904610157,47.1760635376],"type":"Point"}
}