{
  "type": "Feature",
  "properties": {
    "iso:country":"CH",
    "sg:address":"Arzthausstrasse 1",
    "sg:city":"Rothenthurm",
    "sg:orig_category":"Arztpraxen",
    "sg:phone":"+41 41 838 12 21",
    "sg:postcode":"6418",
    "sg:province":"Schwyz",
    "wof:name":"Dr.med. Martin Huber Arzt F.allgemeine Medizin Fmh",
    "wof:placetype":"venue"
},
  "geometry": {"coordinates":[8.677575,47.104267],"type":"Point"}
}