{
  "type": "Feature",
  "properties": {
    "iso:country":"CH",
    "sg:address":"Rosenbordstrasse 16",
    "sg:city":"Niederurnen",
    "sg:orig_category":"Detailhandel mit Textilien",
    "sg:phone":"+41 55 610 13 27",
    "sg:postcode":"8867",
    "sg:province":"Glarus",
    "wof:name":"Melanie Schneider Innendekorationen",
    "wof:placetype":"venue"
},
  "geometry": {"coordinates":[9.0554103851,47.1227874756],"type":"Point"}
}