{
  "type": "Feature",
  "properties": {
    "iso:country":"CH",
    "sg:address":"Rotseeh\u00f6he 21",
    "sg:city":"Luzern",
    "sg:orig_category":"Unclassifiable Establishments",
    "sg:phone":"+41 41 422 01 05",
    "sg:postcode":"6006",
    "sg:province":"Luzern",
    "wof:name":"H\u00fcsler Peter Landschaftsarchitekt Bsla",
    "wof:placetype":"venue"
},
  "geometry": {"coordinates":[8.3132781982,47.0666923523],"type":"Point"}
}