{
  "type": "Feature",
  "properties": {
    "iso:country":"CH",
    "sg:address":"Gottetaz En B1",
    "sg:city":"Monnaz",
    "sg:orig_category":"Sonstiger Grosshandel",
    "sg:phone":"+41 21036770",
    "sg:postcode":"1125",
    "sg:province":"Vaud",
    "wof:name":"Sodist S. Spring",
    "wof:placetype":"venue"
},
  "geometry": {"coordinates":[6.4791522026,46.5285568237],"type":"Point"}
}