{
  "type": "Feature",
  "properties": {
    "iso:country":"CH",
    "sg:address":"1643",
    "sg:city":"Gumefens",
    "sg:orig_category":"G\u00fcterbef\u00f6rderung im Strassenverkehr",
    "sg:phone":"+41 26 915 23 15",
    "sg:postcode":"1643",
    "sg:province":"Fribourg",
    "wof:name":"Andr\u00e9 Bapst Transports",
    "wof:placetype":"venue"
},
  "geometry": {"coordinates":[7.0685901642,46.6771697998],"type":"Point"}
}