{
  "type": "Feature",
  "properties": {
    "iso:country":"CH",
    "sg:address":"Office Du Tourisme Passage Du Temple 11",
    "sg:city":"Vallorbe",
    "sg:orig_category":"Reiseb\u00fcros U Reiseveranstalter",
    "sg:phone":"+41 21 843 22 62",
    "sg:postcode":"1337",
    "sg:province":"Vaud",
    "wof:name":"Grottes De Vallorbe Sa",
    "wof:placetype":"venue"
},
  "geometry": {"coordinates":[6.3790950775,46.7119598389],"type":"Point"}
}