{
  "type": "Feature",
  "properties": {
    "iso:country":"CH",
    "sg:address":"Saumackerstrasse 2",
    "sg:city":"Z\u00fcrich",
    "sg:orig_category":"Geb\u00e4ude, Wohnungsreinigung",
    "sg:phone":"+41 14318854",
    "sg:postcode":"8048",
    "sg:province":"Z\u00fcrich",
    "wof:name":"Walter Ecker Reinigungen",
    "wof:placetype":"venue"
},
  "geometry": {"coordinates":[8.4894447327,47.3905143738],"type":"Point"}
}