{
  "type": "Feature",
  "properties": {
    "iso:country":"CH",
    "sg:address":"Fronwagplatz 28",
    "sg:city":"Schaffhausen",
    "sg:orig_category":"RESTAURANTS: TEA-ROOMS",
    "sg:phone":"+41 52 625 25 63",
    "sg:postcode":"8200",
    "sg:province":"Schaffhausen",
    "wof:name":"Caf\u00e9 City Gn\u00e4dinger",
    "wof:placetype":"venue"
},
  "geometry": {"coordinates":[8.6336517334,47.697353363],"type":"Point"}
}