{
  "type": "Feature",
  "properties": {
    "addr:full":"Tannenweg 4 Schafisheim Aargau 5503",
    "addr:housenumber":"4",
    "addr:postcode":"5503",
    "addr:street":"Tannenweg",
    "iso:country":"CH",
    "sg:address":"Tannenweg 4",
    "sg:city":"Schafisheim",
    "sg:orig_category":"Assembling, Disassembling",
    "sg:phone":"+41 62 891 52 65",
    "sg:postcode":"5503",
    "sg:province":"Aargau",
    "wof:name":"Heinz Sch\u00f6nauer Ag",
    "wof:placetype":"venue"
},
  "geometry": {"coordinates":[8.14195,47.377502],"type":"Point"}
}