{
  "type": "Feature",
  "properties": {
    "iso:country":"CH",
    "sg:address":"Badisch-bahnhofstrasse 16 8212 Neuhausen. Postfach",
    "sg:city":"Neuhausen",
    "sg:orig_category":"Pensionskassen",
    "sg:phone":"+41 71 877 17 10",
    "sg:postcode":"8212",
    "sg:province":"Schaffhausen",
    "wof:name":"Schlesinger Dr. Ren\u00e9 Und Renia-stiftung",
    "wof:placetype":"venue"
},
  "geometry": {"coordinates":[9.4870901108,47.4191017151],"type":"Point"}
}