{
  "type": "Feature",
  "properties": {
    "iso:country":"CH",
    "sg:address":"Vers-encier",
    "sg:city":"Troistorrents",
    "sg:orig_category":"G\u00fcterbef\u00f6rderung im Strassenverkehr",
    "sg:phone":"+41 79 310 16 33",
    "sg:postcode":"1872",
    "sg:province":"Valais",
    "wof:name":"Armand Noti Transporte",
    "wof:placetype":"venue"
},
  "geometry": {"coordinates":[7.8920350075,46.2011413574],"type":"Point"}
}