{
  "type": "Feature",
  "properties": {
    "iso:country":"CH",
    "sg:address":"Steinmattstrasse 26",
    "sg:city":"Derendingen",
    "sg:orig_category":"Regionalbanken U Sparkassen",
    "sg:phone":"+41 32 681 44 44",
    "sg:postcode":"4552",
    "sg:province":"Solothurn",
    "wof:name":"Baloise Bank Soba",
    "wof:placetype":"venue"
},
  "geometry": {"coordinates":[7.5852007866,47.1962432861],"type":"Point"}
}