{
  "type": "Feature",
  "properties": {
    "iso:country":"CH",
    "sg:address":"Industriestrasse 26",
    "sg:city":"Volketswil",
    "sg:orig_category":"Detailhandel mit M\u00f6beln U Haushaltsgegenst\u00e4nden Grosshandel mit M\u00f6beln, Wohnbedarf, Teppichen U Bode",
    "sg:phone":"+41 19453868",
    "sg:postcode":"8604",
    "sg:province":"Z\u00fcrich",
    "wof:name":"Vosag Ag",
    "wof:placetype":"venue"
},
  "geometry": {"coordinates":[8.6788740158,47.3794898987],"type":"Point"}
}