{
  "type": "Feature",
  "properties": {
    "iso:country":"CH",
    "sg:address":"B\u00e4lliz 59",
    "sg:city":"Thun",
    "sg:orig_category":"Interessenvertretungen",
    "sg:postcode":"3600",
    "sg:province":"Bern",
    "wof:name":"Yatra Stiftung",
    "wof:placetype":"venue"
},
  "geometry": {"coordinates":[8.8799800873,47.1947555542],"type":"Point"}
}