{
  "type": "Feature",
  "properties": {
    "iso:country":"CH",
    "sg:address":"Rue De La Gare 17",
    "sg:city":"Nyon",
    "sg:orig_category":"Handels-H\u00e4user U Gesellschaften",
    "sg:phone":"+41 27 305 66 66",
    "sg:postcode":"1260",
    "sg:province":"Vaud",
    "wof:name":"Soci\u00e9t\u00e9 Des Montres West End Sa",
    "wof:placetype":"venue"
},
  "geometry": {"coordinates":[7.2086448669,46.1864585876],"type":"Point"}
}