{
  "type": "Feature",
  "properties": {
    "iso:country":"CH",
    "sg:address":"3537",
    "sg:city":"Eggiwil",
    "sg:orig_category":"Wasserversorgung",
    "sg:phone":"+41 34 491 93 93",
    "sg:postcode":"3537",
    "sg:province":"Bern",
    "wof:name":"Wasserversorgung Der Gemeinde Eggiwil",
    "wof:placetype":"venue"
},
  "geometry": {"coordinates":[7.795882225,46.8750648499],"type":"Point"}
}