{
  "type": "Feature",
  "properties": {
    "iso:country":"CH",
    "sg:address":"5724",
    "sg:city":"D\u00fcrren\u00e4sch",
    "sg:orig_category":"Sportvereine Sch\u00fctzen",
    "sg:phone":"+41 62 797 21 67",
    "sg:postcode":"5724",
    "sg:province":"Aargau",
    "wof:name":"Sch\u00fctzengesellschaft",
    "wof:placetype":"venue"
},
  "geometry": {"coordinates":[8.1532297134,47.3168106079],"type":"Point"}
}