{
  "type": "Feature",
  "properties": {
    "iso:country":"CH",
    "sg:address":"Pilatusstrasse 35",
    "sg:city":"Luzern",
    "sg:orig_category":"Unclassifiable Establishments",
    "sg:postcode":"6003",
    "sg:province":"Luzern",
    "wof:name":"Santa Monica Ag",
    "wof:placetype":"venue"
},
  "geometry": {"coordinates":[8.3048696518,47.0480651855],"type":"Point"}
}