{
  "type": "Feature",
  "properties": {
    "addr:full":"Chemin De Grange-canal 23b Gen\u00e8ve Gen\u00e8ve 1208",
    "addr:housenumber":"23b",
    "addr:postcode":"1208",
    "addr:street":"Chemin De Grange-Canal",
    "iso:country":"CH",
    "sg:address":"Chemin De Grange-canal 23b",
    "sg:city":"Gen\u00e8ve",
    "sg:orig_category":"Arztpraxen",
    "sg:phone":"+41 32 968 28 60",
    "sg:postcode":"1208",
    "sg:province":"Gen\u00e8ve",
    "wof:name":"Dr M\u00e9d. Tonci Tripalo M\u00e9decin Sp\u00e9cialiste Fmh",
    "wof:placetype":"venue"
},
  "geometry": {"coordinates":[6.836967,47.103767],"type":"Point"}
}