{
  "type": "Feature",
  "properties": {
    "iso:country":"CH",
    "sg:address":"Bristenstrasse 2",
    "sg:city":"Brunnen",
    "sg:orig_category":"Vereine Vogel-& Naturschutz",
    "sg:phone":"+41 41 820 12 30",
    "sg:postcode":"6440",
    "sg:province":"Schwyz",
    "wof:name":"Ornitholog.verein Schwyz & Umgebung",
    "wof:placetype":"venue"
},
  "geometry": {"coordinates":[8.5997314453,46.9950332642],"type":"Point"}
}