{
  "type": "Feature",
  "properties": {
    "iso:country":"CH",
    "sg:address":"Klausweg 33 8200 Schaffhausen. Postfach",
    "sg:city":"Schaffhausen",
    "sg:orig_category":"Fachdetailhandel in Verkaufsr\u00e4umen Grosshandel mit Schmuck",
    "sg:phone":"+41 52 625 37 37",
    "sg:postcode":"8206",
    "wof:name":"Reschek-roth Ag",
    "wof:placetype":"venue"
},
  "geometry": {"coordinates":[8.6455087662,47.705280304],"type":"Point"}
}