{
  "type": "Feature",
  "properties": {
    "iso:country":"CH",
    "sg:address":"Postg\u00e4ssli 7",
    "sg:city":"Meikirch",
    "sg:orig_category":"Detailhandel mit Geschenkartikeln U Souvenirs",
    "sg:phone":"+41 31 829 06 71",
    "sg:postcode":"3045",
    "sg:province":"Bern",
    "wof:name":"Keramik K.& S.zimmermann",
    "wof:placetype":"venue"
},
  "geometry": {"coordinates":[7.3659172058,47.008808136],"type":"Point"}
}