{
  "type": "Feature",
  "properties": {
    "iso:country":"CH",
    "sg:address":"Lohstampfestrasse 2",
    "sg:city":"T\u00e4gerwilen",
    "sg:orig_category":"Allgemeiner Hochbau Strassenbau",
    "sg:phone":"+41 71 911 40 12",
    "sg:postcode":"8274",
    "sg:province":"Thurgau",
    "wof:name":"Ernst Locher Ag Baugesch\u00e4ft",
    "wof:placetype":"venue"
},
  "geometry": {"coordinates":[9.062568,47.469242],"type":"Point"}
}