{
  "type": "Feature",
  "properties": {
    "iso:country":"CH",
    "sg:address":"Mitteldorf 7 4422 Arisdorf. Postfach",
    "sg:city":"Arisdorf",
    "sg:orig_category":"Gesundheitswesen",
    "sg:postcode":"4422",
    "sg:province":"Basel-Landschaft",
    "wof:name":"Blb Beatrice Lebens Beratung Gmbh",
    "wof:placetype":"venue"
},
  "geometry": {"coordinates":[7.7646780014,47.5085334778],"type":"Point"}
}