{
  "type": "Feature",
  "properties": {
    "iso:country":"CH",
    "sg:address":"Werner-k\u00e4lin-strasse 1",
    "sg:city":"Einsiedeln",
    "sg:orig_category":"Detailhandel mit Textilien Sonstiger Detailhandel mit Metallwaren, Anstrichmitteln, Glaswaren, Bau U",
    "sg:phone":"+41 55 412 82 27",
    "sg:postcode":"8840",
    "sg:province":"Schwyz",
    "wof:name":"Bastel- + Wundertruckli, Berta Karin Bastel- U. Geschenkartikel",
    "wof:placetype":"venue"
},
  "geometry": {"coordinates":[8.7471599579,47.1265907288],"type":"Point"}
}