{
  "type": "Feature",
  "properties": {
    "iso:country":"CH",
    "sg:address":"M\u00fchlemattstrasse 23 4112 B\u00e4ttwil. Postfach",
    "sg:city":"B\u00e4ttwil",
    "sg:orig_category":"Unclassifiable Establishments",
    "sg:phone":"+41 61 731 21 19",
    "sg:postcode":"4112",
    "sg:province":"Solothurn",
    "wof:name":"Herzig Reparaturdienst Ger\u00e4te Und Apparatereparaturen",
    "wof:placetype":"venue"
},
  "geometry": {"coordinates":[7.5032410622,47.4898071289],"type":"Point"}
}