{
  "type": "Feature",
  "properties": {
    "iso:country":"CH",
    "sg:address":"Bederstrasse 4",
    "sg:city":"Z\u00fcrich",
    "sg:orig_category":"Pensionskassen",
    "sg:postcode":"8002",
    "sg:province":"Z\u00fcrich",
    "wof:name":"Pensionskasse Schneidergewerbe",
    "wof:placetype":"venue"
},
  "geometry": {"coordinates":[8.5311069489,47.364982605],"type":"Point"}
}