{
  "type": "Feature",
  "properties": {
    "iso:country":"CH",
    "sg:address":"Gerliswilstrasse 49",
    "sg:city":"Emmenbr\u00fccke",
    "sg:orig_category":"Sonstiger Detailhandel mit Waren verschiedener Art, Hauptrichtung Nichtnahrungsmittel",
    "sg:phone":"+41 41 260 56 75",
    "sg:postcode":"6020",
    "sg:province":"Luzern",
    "wof:name":"Gjergjaj Pashk Luis Markt",
    "wof:placetype":"venue"
},
  "geometry": {"coordinates":[8.2766742706,47.0744895935],"type":"Point"}
}