{
  "type": "Feature",
  "properties": {
    "iso:country":"CH",
    "sg:address":"Kantonsstrasse 229 A 7748 Campascio. Postfach",
    "sg:city":"Campascio",
    "sg:orig_category":"Grosshandel mit Obst U Gem\u00fcse",
    "sg:phone":"+41 81 839 20 21",
    "sg:postcode":"7748",
    "sg:province":"Graubunden",
    "wof:name":"Fruit Service Gmbh",
    "wof:placetype":"venue"
},
  "geometry": {"coordinates":[10.1302528381,46.2464294434],"type":"Point"}
}