{
  "type": "Feature",
  "properties": {
    "addr:full":"Rue Du Ch\u00e2teau-vieux 3a Monthey Valais 1870",
    "addr:housenumber":"3a",
    "addr:postcode":"1870",
    "addr:street":"Rue Du Cha\u0302Teau-Vieux",
    "iso:country":"CH",
    "sg:address":"Rue Du Ch\u00e2teau-vieux 3a",
    "sg:city":"Monthey",
    "sg:orig_category":"Alters U Hinterlassenenversicherung AHV, Invalidenversicherung IV, Arbeitslosenversicherung ALV",
    "sg:phone":"+41 21 921 00 21",
    "sg:postcode":"1870",
    "sg:province":"Valais",
    "wof:name":"Caisse Publique Cantonale Vaudoise De Ch\u00f4mage",
    "wof:placetype":"venue"
},
  "geometry": {"coordinates":[5.18087,45.897339],"type":"Point"}
}