{
  "type": "Feature",
  "properties": {
    "iso:country":"CH",
    "sg:address":"Burketen",
    "sg:city":"Niedergampel",
    "sg:classifiers":[
        {
            "category":"Restaurant",
            "type":"Food & Drink"
        }
    ],
    "sg:phone":"+41 27 932 15 67",
    "sg:postcode":"3945",
    "sg:province":"Valais",
    "sg:tags":[
        "tea-rooms",
        "restaurants"
    ],
    "wof:name":"Restaurant Traube, Fryand Manuela",
    "wof:placetype":"venue"
},
  "geometry": {"coordinates":[7.7135381699,46.3121566772],"type":"Point"}
}