{
  "type": "Feature",
  "properties": {
    "iso:country":"CH",
    "sg:address":"Hartenfelsstrasse 102",
    "sg:city":"Ebikon",
    "sg:orig_category":"Unternehmensberatung",
    "sg:phone":"+41 41 442 00 55",
    "sg:postcode":"6030",
    "sg:province":"Luzern",
    "wof:name":"Odr (schweiz) Ag",
    "wof:placetype":"venue"
},
  "geometry": {"coordinates":[8.3613214493,47.0908088684],"type":"Point"}
}