{
  "type": "Feature",
  "properties": {
    "iso:country":"CH",
    "sg:address":"Thurgauerstrasse 56",
    "sg:city":"Z\u00fcrich",
    "sg:orig_category":"Zivilschutz",
    "sg:phone":"+41 13067111",
    "sg:postcode":"8050",
    "sg:province":"Z\u00fcrich",
    "wof:name":"Kant. Amt F\u00fcr Zivilschutz",
    "wof:placetype":"venue"
},
  "geometry": {"coordinates":[8.5529708862,47.4160308838],"type":"Point"}
}