{
  "type": "Feature",
  "properties": {
    "iso:country":"CH",
    "sg:address":"Lutzertstrasse 38",
    "sg:city":"Muttenz",
    "sg:orig_category":"Drogerien Parf\u00fcmerien U sonstiger Detailhandel mit kosmetischen Artikeln U K\u00f6rperpflegemitteln",
    "sg:phone":"+41 61 461 72 77",
    "sg:postcode":"4132",
    "sg:province":"Basel-Landschaft",
    "wof:name":"Dellgro Ag",
    "wof:placetype":"venue"
},
  "geometry": {"coordinates":[7.6332030296,47.5341377258],"type":"Point"}
}