{
  "type": "Feature",
  "properties": {
    "addr:full":"Lettenstr. 6 Rotkreuz Zug 6343",
    "addr:housenumber":"6",
    "addr:postcode":"6343",
    "addr:street":"Lettenstr.;Zug",
    "iso:country":"CH",
    "sg:address":"Lettenstr. 6",
    "sg:city":"Rotkreuz",
    "sg:classifiers":[
        {
            "category":"Shopping",
            "type":"Retail Goods"
        }
    ],
    "sg:phone":"+41 41 798 08 88",
    "sg:postcode":"6343",
    "sg:province":"Zug",
    "sg:tags":[
        "metallurgy",
        "finished",
        "-",
        "metalworking",
        "metallic"
    ],
    "wof:name":"Gag",
    "wof:placetype":"venue"
},
  "geometry": {"coordinates":[8.431786,47.148087],"type":"Point"}
}