{
  "type": "Feature",
  "properties": {
    "iso:country":"CH",
    "sg:address":"Paradiesstrasse 19 8645 Jona. Postfach",
    "sg:city":"Jona",
    "sg:orig_category":"Institutionen f\u00fcr Finanzierungsleasing",
    "sg:phone":"+41 55 214 36 63",
    "sg:postcode":"8645",
    "sg:province":"St. Gallen",
    "wof:name":"Global Lease Ag Leasinggesch\u00e4fte, Bes. An- U. Verkauf Von Investitionsg\u00fctern Usw.",
    "wof:placetype":"venue"
},
  "geometry": {"coordinates":[8.8123188019,47.2416381836],"type":"Point"}
}