{
  "type": "Feature",
  "properties": {
    "iso:country":"CH",
    "sg:address":"Ziegelh\u00fcttenweg",
    "sg:city":"Berschis",
    "sg:orig_category":"Rebbau",
    "sg:phone":"+41 81 733 41 24",
    "sg:postcode":"8892",
    "sg:province":"St. Gallen",
    "wof:name":"Kgb-bio-land-& Weinbau",
    "wof:placetype":"venue"
},
  "geometry": {"coordinates":[9.3465423584,47.1090011597],"type":"Point"}
}