{
  "type": "Feature",
  "properties": {
    "iso:country":"CH",
    "sg:address":"Schwerzistrasse 12",
    "sg:city":"Freienbach",
    "sg:orig_category":"Maschinenbau Mechanische Werkst\u00e4tten",
    "sg:phone":"+41 32 341 48 34",
    "sg:postcode":"8807",
    "sg:province":"Schwyz",
    "wof:name":"Fl\u00fcckiger & Cie, Succ. Ballaman + Cie",
    "wof:placetype":"venue"
},
  "geometry": {"coordinates":[7.2584371567,47.1466674805],"type":"Point"}
}