{
  "type": "Feature",
  "properties": {
    "iso:country":"CH",
    "sg:address":"Pavillons Rue Des 7 1205 Gen\u00e8ve. Postfach",
    "sg:city":"Gen\u00e8ve",
    "sg:orig_category":"Non-Classified Establishments",
    "sg:postcode":"1205",
    "sg:province":"Gen\u00e8ve",
    "wof:name":"Soci\u00e9t\u00e9 Anonyme Immobili\u00e8re Des Nouveaux Quartiers, Lettre B",
    "wof:placetype":"venue"
},
  "geometry": {"coordinates":[6.1392149925,46.1968688965],"type":"Point"}
}