{
  "type": "Feature",
  "properties": {
    "iso:country":"CH",
    "sg:address":"Mittlerfeldweg 3",
    "sg:city":"Kienberg",
    "sg:orig_category":"Politische Parteien FDP",
    "sg:postcode":"4468",
    "sg:province":"Solothurn",
    "wof:name":"Fdp Ortspartei Kienberg",
    "wof:placetype":"venue"
},
  "geometry": {"coordinates":[7.9671368599,47.4410247803],"type":"Point"}
}