{
  "type": "Feature",
  "properties": {
    "iso:country":"CH",
    "sg:address":"Baarerstrasse 109 6300 Zug. Postfach 2430",
    "sg:city":"Zug",
    "sg:orig_category":"Handel mit Motorr\u00e4dern, Teilen U Zubeh\u00f6r Instandhaltung U Reparatur von Motorr\u00e4dern",
    "sg:phone":"+41 32 841 35 70",
    "sg:postcode":"6302",
    "sg:province":"Zug",
    "wof:name":"Motocarrefour Colombier, Corradini Michel",
    "wof:placetype":"venue"
},
  "geometry": {"coordinates":[6.857986927,46.9656143188],"type":"Point"}
}