{
  "type": "Feature",
  "properties": {
    "iso:country":"CH",
    "sg:address":"Neugutstrasse 90",
    "sg:city":"D\u00fcbendorf",
    "sg:orig_category":"Non-Classified Establishments",
    "sg:postcode":"8600",
    "sg:province":"Z\u00fcrich",
    "wof:name":"Ralph Leuthold K\u00e4lte Klima & W\u00e4rme",
    "wof:placetype":"venue"
},
  "geometry": {"coordinates":[8.6036071777,47.4017295837],"type":"Point"}
}