{
  "type": "Feature",
  "properties": {
    "iso:country":"CH",
    "sg:address":"Sonneggstrasse 39",
    "sg:city":"Arth",
    "sg:orig_category":"Fernmeldedienste",
    "sg:phone":"+41 41 855 31 52",
    "sg:postcode":"6415",
    "sg:province":"Schwyz",
    "wof:name":"Steiner Jac. S\u00f6hne Gmbh",
    "wof:placetype":"venue"
},
  "geometry": {"coordinates":[8.548327446,47.044670105],"type":"Point"}
}