{
  "type": "Feature",
  "properties": {
    "iso:country":"CH",
    "sg:address":"Grenzstrasse 15 4057 Basel. Postfach 242",
    "sg:city":"Basel",
    "sg:orig_category":"Abwasserreinigung Abwasserreinigung, Abfallbeseitigung U sonstige Entsorgung",
    "sg:phone":"+41 61 639 92 00",
    "sg:postcode":"4019",
    "sg:province":"Basel-Stadt",
    "wof:name":"Prorheno Ag",
    "wof:placetype":"venue"
},
  "geometry": {"coordinates":[7.60165,47.583549],"type":"Point"}
}