{
  "type": "Feature",
  "properties": {
    "iso:country":"CH",
    "sg:address":"Baselstrasse 57 4125 Riehen. Postfach",
    "sg:city":"Riehen",
    "sg:orig_category":"Werbeagenturen Werbevermittlung",
    "sg:phone":"+41 61 641 28 08",
    "sg:postcode":"4125",
    "sg:province":"Basel-Stadt",
    "wof:name":"Cfp Werbeagentur Ag",
    "wof:placetype":"venue"
},
  "geometry": {"coordinates":[7.6500058174,47.5856323242],"type":"Point"}
}