{
  "type": "Feature",
  "properties": {
    "iso:country":"CH",
    "sg:address":"M\u00e4rzengasse 52",
    "sg:city":"Wettingen",
    "sg:orig_category":"Unclassifiable Establishments",
    "sg:postcode":"5430",
    "sg:province":"Aargau",
    "wof:name":"Restaurant Alte Post, Singh & Geisser",
    "wof:placetype":"venue"
},
  "geometry": {"coordinates":[8.3352108002,47.4664154053],"type":"Point"}
}