{
  "type": "Feature",
  "properties": {
    "iso:country":"CH",
    "sg:address":"Seftigenstrasse 83",
    "sg:city":"Bern",
    "sg:classifiers":[
        {
            "category":"Bars & Pubs",
            "subcategory":"Gay Bar",
            "type":"Food & Drink"
        }
    ],
    "sg:phone":"+41 52 742 01 00",
    "sg:postcode":"3007",
    "sg:province":"Bern",
    "sg:tags":[
        "injection",
        "moulding",
        "clean-room"
    ],
    "wof:name":"Silcotech Ag",
    "wof:placetype":"venue"
},
  "geometry": {"coordinates":[8.851658,47.651588],"type":"Point"}
}