{
  "type": "Feature",
  "properties": {
    "iso:country":"CH",
    "sg:address":"Via Principala",
    "sg:city":"Trun",
    "sg:orig_category":"Offsetdruck",
    "sg:phone":"+41 81 943 24 17",
    "sg:postcode":"7166",
    "sg:province":"Graubunden",
    "wof:name":"Ervin Wolf Stampetta Ferrera",
    "wof:placetype":"venue"
},
  "geometry": {"coordinates":[8.983795166,46.742401123],"type":"Point"}
}