{
  "type": "Feature",
  "properties": {
    "iso:country":"CH",
    "sg:address":"Scheuchzerstrasse 35",
    "sg:city":"Z\u00fcrich",
    "sg:orig_category":"Erwachsenenbildung U Unterricht Unternehmensberatung",
    "sg:phone":"+41 13505454",
    "sg:postcode":"8006",
    "sg:province":"Z\u00fcrich",
    "wof:name":"Brintzinger Marianne Personalentwicklung Und Organisationsberatung",
    "wof:placetype":"venue"
},
  "geometry": {"coordinates":[8.5446805954,47.3848075867],"type":"Point"}
}