{
  "type": "Feature",
  "properties": {
    "iso:country":"CH",
    "sg:address":"Kalchengasse 7",
    "sg:city":"Kloten",
    "sg:orig_category":"Fahrschulen, Flugschulen",
    "sg:phone":"+41 71 891 50 11",
    "sg:postcode":"8302",
    "sg:province":"Z\u00fcrich",
    "wof:name":"Richard Knaus Fahrschule",
    "wof:placetype":"venue"
},
  "geometry": {"coordinates":[9.5106172562,47.4525718689],"type":"Point"}
}