{
  "type": "Feature",
  "properties": {
    "iso:country":"CH",
    "sg:address":"Werkhof H\u00fctten",
    "sg:city":"Linthal",
    "sg:classifiers":[
        {
            "category":"Restaurant",
            "type":"Food & Drink"
        }
    ],
    "sg:phone":"+41 55 643 13 85",
    "sg:postcode":"8783",
    "sg:province":"Glarus",
    "wof:name":"Restaurant H\u00fctten",
    "wof:placetype":"venue"
},
  "geometry": {"coordinates":[8.9878005981,46.9051475525],"type":"Point"}
}