{
  "type": "Feature",
  "properties": {
    "iso:country":"CH",
    "sg:address":"Kreuzstrasse 110 8442 Hettlingen. Postfach",
    "sg:city":"Hettlingen",
    "sg:orig_category":"Architektur U Ingenieurb\u00fcros",
    "sg:postcode":"8442",
    "sg:province":"Z\u00fcrich",
    "wof:name":"Herter, Fritschi, Ruosch Hfr Architekten Ag",
    "wof:placetype":"venue"
},
  "geometry": {"coordinates":[8.70852,47.547329],"type":"Point"}
}