{
  "type": "Feature",
  "properties": {
    "iso:country":"CH",
    "sg:address":"Reussinsel 59",
    "sg:city":"Luzern",
    "sg:orig_category":"Malerei Tapeziererei",
    "sg:phone":"+41 41 240 14 92",
    "sg:postcode":"6003",
    "sg:province":"Luzern",
    "wof:name":"Lustenberger Und Nauer Ag Maler, Tapezierergesch\u00e4ft Usw, Liegenschaftenhandel, Beteiligungen",
    "wof:placetype":"venue"
},
  "geometry": {"coordinates":[8.3043746948,47.0495452881],"type":"Point"}
}