{
  "type": "Feature",
  "properties": {
    "iso:country":"CH",
    "sg:address":"Nollisweid 21",
    "sg:city":"Appenzell",
    "sg:orig_category":"Architektur U Ingenieurb\u00fcros",
    "sg:phone":"+41 91 994 81 65",
    "sg:postcode":"9050",
    "sg:province":"Appenzell Innerhoden",
    "wof:name":"Mazzi Progetti Sa",
    "wof:placetype":"venue"
},
  "geometry": {"coordinates":[8.94624,45.98975],"type":"Point"}
}