{
  "type": "Feature",
  "properties": {
    "iso:country":"CH",
    "sg:address":"Chemin Des Guenandes 2",
    "sg:city":"Chamb\u00e9sy",
    "sg:orig_category":"Architektur U Ingenieurb\u00fcros",
    "sg:phone":"+41 22 758 18 49",
    "sg:postcode":"1292",
    "sg:province":"Gen\u00e8ve",
    "wof:name":"Fac R.gunthart Bureau Technique",
    "wof:placetype":"venue"
},
  "geometry": {"coordinates":[6.140674,46.249065],"type":"Point"}
}