{
  "type": "Feature",
  "properties": {
    "addr:full":"4663 Aarburg Aargau 4663",
    "addr:postcode":"4663;4663",
    "iso:country":"CH",
    "sg:address":"4663",
    "sg:city":"Aarburg",
    "sg:orig_category":"Bau\u00e4mter",
    "sg:phone":"+41 62 791 45 67",
    "sg:postcode":"4663",
    "sg:province":"Aargau",
    "wof:name":"Bauverwaltung Aarburg",
    "wof:placetype":"venue"
},
  "geometry": {"coordinates":[7.899079,47.32019],"type":"Point"}
}