{
  "type": "Feature",
  "properties": {
    "addr:full":"Kramgasse 35 Bern Bern 3011",
    "addr:housenumber":"35",
    "addr:postcode":"3011",
    "addr:street":"Kramgasse",
    "iso:country":"CH",
    "sg:address":"Kramgasse 35",
    "sg:city":"Bern",
    "sg:orig_category":"Arztpraxen",
    "sg:phone":"+41 31 311 49 49",
    "sg:postcode":"3011",
    "sg:province":"Bern",
    "wof:name":"Dr.med.ingrid Minder Spezial\u00e4rztin Fmh",
    "wof:placetype":"venue"
},
  "geometry": {"coordinates":[7.450322,46.947872],"type":"Point"}
}