{
  "type": "Feature",
  "properties": {
    "iso:country":"CH",
    "sg:address":"Rue De Montchoisy 7",
    "sg:city":"Gen\u00e8ve",
    "sg:classifiers":[
        {
            "category":"Restaurant",
            "type":"Food & Drink"
        }
    ],
    "sg:phone":"+41 22 700 05 24",
    "sg:postcode":"1207",
    "sg:province":"Gen\u00e8ve",
    "wof:name":"Caf\u00e9 De L' Amiti\u00e9",
    "wof:placetype":"venue"
},
  "geometry": {"coordinates":[6.159154892,46.2028312683],"type":"Point"}
}