{
  "type": "Feature",
  "properties": {
    "iso:country":"CH",
    "sg:address":"Rue Sigismond-thalberg 12",
    "sg:city":"Gen\u00e8ve",
    "sg:orig_category":"Tankstellen",
    "sg:phone":"+41 22 755 52 22",
    "sg:postcode":"1201",
    "sg:province":"Gen\u00e8ve",
    "wof:name":"Sepeca Sa Cha\u00eene De Garages",
    "wof:placetype":"venue"
},
  "geometry": {"coordinates":[6.1463570595,46.209854126],"type":"Point"}
}