{
  "type": "Feature",
  "properties": {
    "iso:country":"CH",
    "sg:address":"Via Dei Cipressi 3",
    "sg:city":"Muralto",
    "sg:orig_category":"Architekturb\u00fcros",
    "sg:phone":"+41 91 743 65 84",
    "sg:postcode":"6600",
    "sg:province":"Ticino",
    "wof:name":"Michele Pera Studio D'architettura",
    "wof:placetype":"venue"
},
  "geometry": {"coordinates":[8.808361,46.174061],"type":"Point"}
}