{
  "type": "Feature",
  "properties": {
    "iso:country":"CH",
    "sg:address":"Chemin Du Lussex 54",
    "sg:city":"Jouxtens-m\u00e9zery",
    "sg:orig_category":"Sonstige k\u00fcnstlerische U schriftstellerische T\u00e4tigkeiten U Darbietungen",
    "sg:phone":"+41 21 635 75 34",
    "sg:postcode":"1008",
    "sg:province":"Vaud",
    "wof:name":"Eliane Humbert Peinture Sur Porcelaine",
    "wof:placetype":"venue"
},
  "geometry": {"coordinates":[6.5975418091,46.5619468689],"type":"Point"}
}