{
  "type": "Feature",
  "properties": {
    "iso:country":"CH",
    "sg:address":"Rue Du Chasselas 2",
    "sg:city":"Neuch\u00e2tel",
    "sg:orig_category":"Vorschulen, Kinderg\u00e4rten",
    "sg:phone":"+41 32 730 47 31",
    "sg:postcode":"2000",
    "sg:province":"Neuch\u00e2tel",
    "wof:name":"Ecole Enfantine De Maillefer",
    "wof:placetype":"venue"
},
  "geometry": {"coordinates":[6.909060955,46.9870071411],"type":"Point"}
}