{
  "type": "Feature",
  "properties": {
    "iso:country":"CH",
    "sg:address":"Flughafengeb\u00e4ude 8058 Z\u00fcrich. Postfach",
    "sg:city":"Z\u00fcrich",
    "sg:orig_category":"Unternehmensberatung",
    "sg:postcode":"8001",
    "sg:province":"Z\u00fcrich",
    "wof:name":"Cgs Consulting Ground Service Ag Beratung Im Zusammenhang Von Dienstleistungen F\u00fcr Die Bef\u00f6rderung Von Gep\u00e4ck U. Passagieren Auf Airports. Beteiligungen Usw",
    "wof:placetype":"venue"
},
  "geometry": {"coordinates":[8.5739517212,47.4530754089],"type":"Point"}
}