{
  "type": "Feature",
  "properties": {
    "iso:country":"CH",
    "sg:address":"2874",
    "sg:city":"St-brais",
    "sg:orig_category":"Primarschulen",
    "sg:phone":"+41 32 955 13 35",
    "sg:postcode":"2874",
    "sg:province":"Jura",
    "wof:name":"Ecole Primaire",
    "wof:placetype":"venue"
},
  "geometry": {"coordinates":[7.0488529205,47.2900543213],"type":"Point"}
}