{
  "type": "Feature",
  "properties": {
    "iso:country":"CH",
    "sg:address":"Via Cantonale",
    "sg:city":"Cugnasco",
    "sg:orig_category":"Gemischte Landwirtschaft",
    "sg:phone":"+41 91 859 17 36",
    "sg:postcode":"6516",
    "sg:province":"Ticino",
    "wof:name":"Azienda Agricola Forestale Di Luchessa Antonio",
    "wof:placetype":"venue"
},
  "geometry": {"coordinates":[8.9189109802,46.1752662659],"type":"Point"}
}