{
  "type": "Feature",
  "properties": {
    "iso:country":"CH",
    "sg:address":"Rosenbergstrasse 50",
    "sg:city":"St.gallen",
    "sg:orig_category":"Markt U Meinungsforschung Unternehmensberatung",
    "sg:phone":"+41 61 831 44 66",
    "sg:postcode":"9000",
    "sg:province":"St. Gallen",
    "wof:name":"Markt-praxis A-z - Praxisinstitut F\u00fcr Marketing, Management & Kommunikation",
    "wof:placetype":"venue"
},
  "geometry": {"coordinates":[7.7930688858,47.5551223755],"type":"Point"}
}