{
  "type": "Feature",
  "properties": {
    "iso:country":"CH",
    "sg:address":"Fischerweg 79",
    "sg:city":"Oftringen",
    "sg:orig_category":"Herstellung von Teppichen",
    "sg:phone":"+41 62 797 58 18",
    "sg:postcode":"4665",
    "sg:province":"Aargau",
    "wof:name":"Team 2000 Bodenbel\u00e4ge Gmbh",
    "wof:placetype":"venue"
},
  "geometry": {"coordinates":[7.9381790161,47.2996482849],"type":"Point"}
}