{
  "type": "Feature",
  "properties": {
    "iso:country":"CH",
    "sg:address":"Lausanne Rue De 49",
    "sg:city":"Pr\u00e9verenges",
    "sg:orig_category":"Herstellung von k\u00e4lte U lufttechnischen Erzeugnissen f\u00fcr gewerbliche Zwecke",
    "sg:postcode":"1028",
    "sg:province":"Vaud",
    "wof:name":"Triatec Sa, Port-louis, Succursale De Pr\u00e9verenges",
    "wof:placetype":"venue"
},
  "geometry": {"coordinates":[6.5302782059,46.5172576904],"type":"Point"}
}