{
  "type": "Feature",
  "properties": {
    "iso:country":"CH",
    "sg:address":"Via Della Posta 6 6600 Locarno. Postfach",
    "sg:city":"Locarno",
    "sg:classifiers":[
        {
            "category":"Bars & Pubs",
            "type":"Food & Drink"
        }
    ],
    "sg:phone":"+41 91 751 57 98",
    "sg:postcode":"6601",
    "sg:province":"Ticino",
    "sg:tags":[
        "restaurant"
    ],
    "wof:name":"Ristorante Bar Locarno",
    "wof:placetype":"venue"
},
  "geometry": {"coordinates":[8.797097,46.168465],"type":"Point"}
}