{
  "type": "Feature",
  "properties": {
    "iso:country":"CH",
    "sg:address":"Fr\u00f6hlichstrasse 54",
    "sg:city":"Z\u00fcrich",
    "sg:orig_category":"Non-Classified Establishments",
    "sg:postcode":"8008",
    "sg:province":"Z\u00fcrich",
    "wof:name":"Peter Rytz Gmbh Informatik-dienstleistungen",
    "wof:placetype":"venue"
},
  "geometry": {"coordinates":[8.5569982529,47.3547401428],"type":"Point"}
}