{
  "type": "Feature",
  "properties": {
    "iso:country":"CH",
    "sg:address":"Paulstrasse 12",
    "sg:city":"Z\u00fcrich",
    "sg:orig_category":"Werbeagenturen Werbegrafikateliers",
    "sg:phone":"+41 13821937",
    "sg:postcode":"8008",
    "sg:province":"Z\u00fcrich",
    "wof:name":"Peter Fischer Eldorade Verde Design",
    "wof:placetype":"venue"
},
  "geometry": {"coordinates":[8.5580606461,47.3535690308],"type":"Point"}
}