{
  "type": "Feature",
  "properties": {
    "iso:country":"CH",
    "sg:address":"Ingelsteinweg 6",
    "sg:city":"Basel",
    "sg:orig_category":"Bezirks, Sekundar, Realschulen, Oberstufe der Primarschulen Primarschulen",
    "sg:phone":"+41 56 622 15 50",
    "sg:postcode":"4053",
    "sg:province":"Basel-Stadt",
    "wof:name":"Primar-& Oberstufenschule Junkholz Rektorat",
    "wof:placetype":"venue"
},
  "geometry": {"coordinates":[8.27806,47.350529],"type":"Point"}
}