{
  "type": "Feature",
  "properties": {
    "iso:country":"CH",
    "sg:address":"Hauptstrasse 42",
    "sg:city":"Brienz/brinzauls",
    "sg:orig_category":"Reinigungsgewerbe",
    "sg:phone":"+41 81 681 18 15",
    "sg:postcode":"7084",
    "sg:province":"Graubunden",
    "wof:name":"Rizzi Daniel",
    "wof:placetype":"venue"
},
  "geometry": {"coordinates":[9.5953903198,46.6690597534],"type":"Point"}
}