{
  "type": "Feature",
  "properties": {
    "addr:full":"Chatelstrasse 21 Aadorf Thurgau 8355",
    "addr:housenumber":"21",
    "addr:postcode":"8355",
    "addr:street":"Chatelstrasse",
    "iso:country":"CH",
    "sg:address":"Chatelstrasse 21",
    "sg:city":"Aadorf",
    "sg:classifiers":[
        {
            "category":"Utilities",
            "subcategory":"Mobile Phone",
            "type":"Services"
        }
    ],
    "sg:phone":"+41 52 368 34 70",
    "sg:postcode":"8355",
    "sg:province":"Thurgau",
    "sg:tags":[
        "consulting",
        "china"
    ],
    "wof:name":"Nova Energie Gmbh",
    "wof:placetype":"venue"
},
  "geometry": {"coordinates":[8.902856,47.489109],"type":"Point"}
}