{
  "type": "Feature",
  "properties": {
    "iso:country":"CH",
    "sg:address":"Bois-de-la-chapelle Av. 65",
    "sg:city":"Onex",
    "sg:orig_category":"Sonstiger spezialisierter Hoch U Tiefbau",
    "sg:phone":"+41 22 793 05 90",
    "sg:postcode":"1213",
    "sg:province":"Gen\u00e8ve",
    "wof:name":"Bonard P.",
    "wof:placetype":"venue"
},
  "geometry": {"coordinates":[6.1023340225,46.1891326904],"type":"Point"}
}