{
  "type": "Feature",
  "properties": {
    "iso:country":"CH",
    "sg:address":"Urstalden",
    "sg:city":"Gohl",
    "sg:orig_category":"Mechanik Softwareentwicklung U beratung",
    "sg:phone":"+41 91 600 23 07",
    "sg:postcode":"3553",
    "sg:province":"Bern",
    "wof:name":"Forging Technologies Gm Sa",
    "wof:placetype":"venue"
},
  "geometry": {"coordinates":[9.3769798279,47.4262161255],"type":"Point"}
}