{
  "type": "Feature",
  "properties": {
    "iso:country":"CH",
    "sg:address":"1737",
    "sg:city":"Plasselb",
    "sg:orig_category":"Vorschulen, Kinderg\u00e4rten",
    "sg:phone":"+41 26 419 19 25",
    "sg:postcode":"1737",
    "sg:province":"Fribourg",
    "wof:name":"Kindergarten",
    "wof:placetype":"venue"
},
  "geometry": {"coordinates":[7.2509431839,46.7351074219],"type":"Point"}
}