{
  "type": "Feature",
  "properties": {
    "iso:country":"CH",
    "sg:address":"Glattstegweg 6",
    "sg:city":"Z\u00fcrich",
    "sg:orig_category":"Architektur U Ingenieurb\u00fcros",
    "sg:postcode":"8051",
    "sg:province":"Z\u00fcrich",
    "wof:name":"Itubag",
    "wof:placetype":"venue"
},
  "geometry": {"coordinates":[8.573806,47.406528],"type":"Point"}
}