{
  "type": "Feature",
  "properties": {
    "iso:country":"CH",
    "sg:address":"Rue Du March\u00e9 2",
    "sg:city":"Gen\u00e8ve",
    "sg:orig_category":"Detailhandel mit Damenbekleidung Grosshandel mit Textilien",
    "sg:phone":"+41 22 311 67 77",
    "sg:postcode":"1204",
    "sg:province":"Gen\u00e8ve",
    "wof:name":"Michel Ausoni Sa",
    "wof:placetype":"venue"
},
  "geometry": {"coordinates":[6.1454820633,46.2034454346],"type":"Point"}
}