{
  "type": "Feature",
  "properties": {
    "iso:country":"CH",
    "sg:address":"Baselstrasse 60 4142 M\u00fcnchenstein. Postfach",
    "sg:city":"M\u00fcnchenstein",
    "sg:orig_category":"Erbringung von Dienstleistungen f\u00fcr Unternehmen",
    "sg:postcode":"4142",
    "sg:province":"Basel-Landschaft",
    "wof:name":"Innendekorationen Steinmann J. Ag",
    "wof:placetype":"venue"
},
  "geometry": {"coordinates":[7.6169672012,47.5228996277],"type":"Point"}
}