{
  "type": "Feature",
  "properties": {
    "iso:country":"CH",
    "sg:address":"Crappun 15",
    "sg:city":"Samedan",
    "sg:orig_category":"Fahrschulen, Flugschulen",
    "sg:phone":"+41 41 870 42 26",
    "sg:postcode":"7503",
    "sg:province":"Graubunden",
    "wof:name":"Georg Regli Autofahrschule",
    "wof:placetype":"venue"
},
  "geometry": {"coordinates":[8.6425333023,46.8825798035],"type":"Point"}
}