{
  "type": "Feature",
  "properties": {
    "iso:country":"CH",
    "sg:address":"Talacherstrasse 17 6340 Baar. Postfach",
    "sg:city":"Baar",
    "sg:orig_category":"Non-Classified Establishments",
    "sg:phone":"+41 19321625",
    "sg:postcode":"6340",
    "sg:province":"Zug",
    "wof:name":"Fischer & Govoni Ag",
    "wof:placetype":"venue"
},
  "geometry": {"coordinates":[8.7846345901,47.310005188],"type":"Point"}
}