{
  "type": "Feature",
  "properties": {
    "addr:full":"Rindermarkt 17 Z\u00fcrich Z\u00fcrich 8001",
    "addr:housenumber":"17",
    "addr:postcode":"8001",
    "addr:street":"Rindermarkt",
    "iso:country":"CH",
    "sg:address":"Rindermarkt 17",
    "sg:city":"Z\u00fcrich",
    "sg:orig_category":"Bauschreinerei Innenausbau",
    "sg:phone":"+41 22 342 08 84",
    "sg:postcode":"8001",
    "sg:province":"Z\u00fcrich",
    "wof:name":"Hiltpold Sa",
    "wof:placetype":"venue"
},
  "geometry": {"coordinates":[6.144084,46.184433],"type":"Point"}
}