{
  "type": "Feature",
  "properties": {
    "addr:full":"Chalet Les M\u00e9l\u00e8zes Montana 3962",
    "addr:housenumber":"3962",
    "iso:country":"CH",
    "sg:address":"Chalet Les M\u00e9l\u00e8zes",
    "sg:city":"Montana",
    "sg:orig_category":"Betrieb von Taxis",
    "sg:phone":"+41 27 481 13 12",
    "sg:postcode":"3962",
    "wof:name":"C\u00e9sar Pott Taxis & Teinturerie",
    "wof:placetype":"venue"
},
  "geometry": {"coordinates":[7.473436,46.301601],"type":"Point"}
}