{
  "type": "Feature",
  "properties": {
    "iso:country":"CH",
    "sg:address":"Industriestrasse 24",
    "sg:city":"D\u00e4llikon",
    "sg:orig_category":"Electroformed Parts",
    "sg:phone":"+41 18441144",
    "sg:postcode":"8108",
    "sg:province":"Z\u00fcrich",
    "wof:name":"Erne Surface Ag",
    "wof:placetype":"venue"
},
  "geometry": {"coordinates":[8.434762001,47.4456977844],"type":"Point"}
}