{
  "type": "Feature",
  "properties": {
    "iso:country":"CH",
    "sg:address":"Badenerstrasse 431",
    "sg:city":"Z\u00fcrich",
    "sg:orig_category":"Saunas, Solarien, Fitnesszentren U \u00e4hnliches",
    "sg:phone":"+41 79 419 80 04",
    "sg:postcode":"8003",
    "sg:province":"Z\u00fcrich",
    "wof:name":"Paradise Sun Schirmer Linda + Co",
    "wof:placetype":"venue"
},
  "geometry": {"coordinates":[8.43653965,47.3547554016],"type":"Point"}
}