{
  "type": "Feature",
  "properties": {
    "iso:country":"CH",
    "sg:address":"Ringstrasse 37 7000 Chur. Postfach 209",
    "sg:city":"Chur",
    "sg:orig_category":"Herstellung von konfektionierten Textilwaren ohne Bekleidung",
    "sg:phone":"+41 848 888 111",
    "sg:postcode":"7004",
    "sg:province":"Graubunden",
    "wof:name":"Griesser Ag",
    "wof:placetype":"venue"
},
  "geometry": {"coordinates":[9.5151882172,46.8547096252],"type":"Point"}
}