{
  "type": "Feature",
  "properties": {
    "addr:full":"R\u00e4mistrasse 5 8001 Z\u00fcrich. Postfach Z\u00fcrich Z\u00fcrich 8024",
    "addr:housenumber":"5",
    "addr:postcode":"8001 zuerich. postfach;8024",
    "addr:street":"Raemistrasse",
    "iso:country":"CH",
    "sg:address":"R\u00e4mistrasse 5 8001 Z\u00fcrich. Postfach",
    "sg:city":"Z\u00fcrich",
    "sg:orig_category":"Detailhandel mit B\u00fcchern Detailhandel mit B\u00fcchern, Zeitungen, Schreib U Papeteriewaren",
    "sg:postcode":"8024",
    "sg:province":"Z\u00fcrich",
    "wof:name":"Buchhandlung Pfannenstiel Dorothee Neubauer",
    "wof:placetype":"venue"
},
  "geometry": {"coordinates":[8.690055,47.300556],"type":"Point"}
}