{
  "type": "Feature",
  "properties": {
    "iso:country":"CH",
    "sg:address":"Zuchwilerstrasse 41 4500 Solothurn. Postfach 353",
    "sg:city":"Solothurn",
    "sg:orig_category":"Non-Classified Establishments",
    "sg:phone":"+41 32 625 79 99",
    "sg:postcode":"4501",
    "sg:province":"Solothurn",
    "wof:name":"Dr.med.max Hintermann Spezialarzt Fmh",
    "wof:placetype":"venue"
},
  "geometry": {"coordinates":[7.5431661606,47.2031059265],"type":"Point"}
}