{
  "type": "Feature",
  "properties": {
    "iso:country":"CH",
    "sg:address":"Bahnstrasse 19",
    "sg:city":"Wauwil",
    "sg:orig_category":"Herstellung von Automobilen",
    "sg:phone":"+41 41 818 25 25",
    "sg:postcode":"6242",
    "sg:province":"Luzern",
    "wof:name":"Kiener Hans",
    "wof:placetype":"venue"
},
  "geometry": {"coordinates":[8.6252470016,47.0317306519],"type":"Point"}
}