{
  "type": "Feature",
  "properties": {
    "iso:country":"CH",
    "sg:address":"Dorfstrasse 123 8192 Glattfelden. Postfach",
    "sg:city":"Glattfelden",
    "sg:orig_category":"Elektrizit\u00e4tsversorgung",
    "sg:phone":"+41 18670216",
    "sg:postcode":"8192",
    "sg:province":"Z\u00fcrich",
    "wof:name":"Licht Und Kraftwerke Glattfelden",
    "wof:placetype":"venue"
},
  "geometry": {"coordinates":[8.494931221,47.5604171753],"type":"Point"}
}