{
  "type": "Feature",
  "properties": {
    "iso:country":"CH",
    "sg:address":"En Bronjon 1510 Moudon Case Postale",
    "sg:city":"Moudon",
    "sg:orig_category":"Mechanische Werkst\u00e4tten",
    "sg:phone":"+41 21 905 16 81",
    "sg:postcode":"1510",
    "sg:province":"Vaud",
    "wof:name":"Procoma S\u00e0rl",
    "wof:placetype":"venue"
},
  "geometry": {"coordinates":[6.808169,46.670959],"type":"Point"}
}