{
  "type": "Feature",
  "properties": {
    "iso:country":"CH",
    "sg:address":"Aeussere Baselstrasse 381",
    "sg:city":"Riehen",
    "sg:orig_category":"Erdbewegungsarbeiten Gartenbau",
    "sg:phone":"+41 61 601 14 60",
    "sg:postcode":"4125",
    "sg:province":"Basel-Stadt",
    "wof:name":"A. Bechtle",
    "wof:placetype":"venue"
},
  "geometry": {"coordinates":[7.6257228851,47.572429657],"type":"Point"}
}