{
  "type": "Feature",
  "properties": {
    "iso:country":"CH",
    "sg:address":"Via Sorengo 20a 6900 Lugano. Postfach",
    "sg:city":"Lugano",
    "sg:orig_category":"Elektromechanische Werkst\u00e4tten Mechanik",
    "sg:phone":"+41 91 967 65 60",
    "sg:postcode":"6900",
    "sg:province":"Ticino",
    "wof:name":"Belmori Sagl Officina Di Riparazioni Meccaniche",
    "wof:placetype":"venue"
},
  "geometry": {"coordinates":[8.9418697357,46.0045509338],"type":"Point"}
}