{
  "type": "Feature",
  "properties": {
    "iso:country":"CH",
    "sg:address":"Avenue De Pratifori 10",
    "sg:city":"Sion",
    "sg:orig_category":"Unternehmensberatung Wirtschaftspr\u00fcfung, Steuerberatung U Treuhand",
    "sg:phone":"+41 27 323 88 70",
    "sg:postcode":"1950",
    "sg:province":"Valais",
    "wof:name":"Fiduciaire Transalp Donald Moos",
    "wof:placetype":"venue"
},
  "geometry": {"coordinates":[7.3569688797,46.2312011719],"type":"Point"}
}