{
  "type": "Feature",
  "properties": {
    "iso:country":"CH",
    "sg:address":"Les Pingeons 3",
    "sg:city":"Montmirail",
    "sg:orig_category":"Unternehmensberatung",
    "sg:phone":"+41 32 754 37 17",
    "sg:postcode":"2075",
    "sg:province":"Neuch\u00e2tel",
    "wof:name":"Pegastar-development Sa",
    "wof:placetype":"venue"
},
  "geometry": {"coordinates":[7.0214400291,47.0255508423],"type":"Point"}
}