{
  "type": "Feature",
  "properties": {
    "iso:country":"CH",
    "sg:address":"Chaletweg 7",
    "sg:city":"Meisterschwanden",
    "sg:orig_category":"Wirtschaftspr\u00fcfung, Steuerberatung U Treuhand",
    "sg:phone":"+41 56 667 37 04",
    "sg:postcode":"5616",
    "sg:province":"Aargau",
    "wof:name":"Arseven Ali Y\u00fccel",
    "wof:placetype":"venue"
},
  "geometry": {"coordinates":[8.2239332199,47.2929916382],"type":"Point"}
}