{
  "type": "Feature",
  "properties": {
    "iso:country":"CH",
    "sg:address":"Leisibachstrasse 18",
    "sg:city":"Buchrain",
    "sg:orig_category":"Grosshandel mit Eisenwaren sowie Installationsbedarf f\u00fcr Gas, Wasser U Heizung Grosshandel mit Holz ",
    "sg:phone":"+41 21 624 58 11",
    "sg:postcode":"6033",
    "sg:province":"Luzern",
    "wof:name":"Wilba Outillage & Fourn.technique",
    "wof:placetype":"venue"
},
  "geometry": {"coordinates":[6.6075639725,46.524055481],"type":"Point"}
}