{
  "type": "Feature",
  "properties": {
    "iso:country":"CH",
    "sg:address":"Rheinweg 12",
    "sg:city":"Bannwil",
    "sg:classifiers":[
        {
            "category":"Utilities",
            "subcategory":"Cable",
            "type":"Services"
        }
    ],
    "sg:phone":"+41 62 958 50 00",
    "sg:postcode":"4913",
    "sg:province":"Bern",
    "sg:tags":[
        "integrated",
        "solution",
        "software"
    ],
    "wof:name":"Sofag Computer Center Gmbh",
    "wof:placetype":"venue"
},
  "geometry": {"coordinates":[7.7390270233,47.2408638],"type":"Point"}
}