{
  "type": "Feature",
  "properties": {
    "iso:country":"CH",
    "sg:address":"Riedmattstrasse 10",
    "sg:city":"Ebikon",
    "sg:orig_category":"Herstellung von sonstigen elektrischen Ausr\u00fcstungen",
    "sg:phone":"+41 41 440 26 53",
    "sg:postcode":"6030",
    "sg:province":"Luzern",
    "wof:name":"Micronic, Jaroslav Hlinovsky",
    "wof:placetype":"venue"
},
  "geometry": {"coordinates":[8.3415565491,47.0829620361],"type":"Point"}
}