{
  "type": "Feature",
  "properties": {
    "iso:country":"CH",
    "sg:address":"Bodenhof",
    "sg:city":"Littau",
    "sg:orig_category":"G\u00fcterbef\u00f6rderung im Strassenverkehr Haltung von Schweinen",
    "sg:phone":"+41 79 641 27 57",
    "sg:postcode":"6014",
    "sg:province":"Luzern",
    "wof:name":"Oscar Blaser Schweinem\u00e4sterei & Transporte",
    "wof:placetype":"venue"
},
  "geometry": {"coordinates":[8.2586946487,47.0566749573],"type":"Point"}
}