{
  "type": "Feature",
  "properties": {
    "iso:country":"CH",
    "sg:address":"Hauptstrasse 33",
    "sg:city":"Ziefen",
    "sg:orig_category":"Grosshandel mit landwirtschaftlichen Maschinen U Ger\u00e4ten Herstellung von sonstigen landwirtschaftlic",
    "sg:phone":"+41 61 931 11 81",
    "sg:postcode":"4417",
    "sg:province":"Basel-Landschaft",
    "wof:name":"Hanspeter Abt Landmaschinen & Traktoren",
    "wof:placetype":"venue"
},
  "geometry": {"coordinates":[7.7153520584,47.4333381653],"type":"Point"}
}