{
  "type": "Feature",
  "properties": {
    "iso:country":"CH",
    "sg:address":"Corso San Gottardo 35",
    "sg:city":"Chiasso",
    "sg:orig_category":"Grosshandel mit Holz U Bauelementen aus Holz",
    "sg:phone":"+41 91 682 81 51",
    "sg:postcode":"6830",
    "sg:province":"Ticino",
    "wof:name":"Briantea & Eurasian Sa Luxembourg-kirchberg",
    "wof:placetype":"venue"
},
  "geometry": {"coordinates":[9.0298109055,45.8340835571],"type":"Point"}
}