{
  "type": "Feature",
  "properties": {
    "iso:country":"CH",
    "sg:address":"Hauptstrasse 60",
    "sg:city":"Frick",
    "sg:orig_category":"Detailhandel mit Textilien Detailhandel mit elektrischen Haushalts-,Radio U Fernsehger\u00e4ten sowie Mus",
    "sg:phone":"+41 56 442 13 30",
    "sg:postcode":"5070",
    "sg:province":"Aargau",
    "wof:name":"Obrist Bernina-n\u00e4hcenter.",
    "wof:placetype":"venue"
},
  "geometry": {"coordinates":[8.0211706161,47.5069847107],"type":"Point"}
}