{
  "type": "Feature",
  "properties": {
    "iso:country":"CH",
    "sg:address":"Sonnenrain",
    "sg:city":"Schenkon",
    "sg:orig_category":"Haltung von Schweinen",
    "sg:phone":"+41 41 921 76 09",
    "sg:postcode":"6214",
    "sg:province":"Luzern",
    "wof:name":"Hans Schmid Schweinezuchtbetrieb",
    "wof:placetype":"venue"
},
  "geometry": {"coordinates":[8.127532959,47.1833724976],"type":"Point"}
}