{
  "type": "Feature",
  "properties": {
    "addr:full":"Stettbachstrasse 12 Zollikon Z\u00fcrich 8702",
    "addr:housenumber":"12",
    "addr:postcode":"8702",
    "addr:street":"Stettbachstrasse",
    "iso:country":"CH",
    "sg:address":"Stettbachstrasse 12",
    "sg:city":"Zollikon",
    "sg:orig_category":"Architektur U Ingenieurb\u00fcros",
    "sg:phone":"+41 13913068",
    "sg:postcode":"8702",
    "sg:province":"Z\u00fcrich",
    "wof:name":"Interplan Architekten Ag/ipa",
    "wof:placetype":"venue"
},
  "geometry": {"coordinates":[8.578586,47.340919],"type":"Point"}
}