{
  "type": "Feature",
  "properties": {
    "iso:country":"CH",
    "sg:address":"Tanneggweg 12",
    "sg:city":"Thun",
    "sg:orig_category":"Haltung von Schafen, Ziegen, Pferden U Eseln",
    "sg:postcode":"3600",
    "sg:province":"Bern",
    "wof:name":"Pferdezuchtgenossenschaft Des Amtes Thun",
    "wof:placetype":"venue"
},
  "geometry": {"coordinates":[7.6101088524,46.7354049683],"type":"Point"}
}