{
  "type": "Feature",
  "properties": {
    "iso:country":"CH",
    "sg:address":"Dorfstrasse 18 6026 Rain. Postfach",
    "sg:city":"Rain",
    "sg:orig_category":"Elektroinstallation",
    "sg:phone":"+41 41 458 12 17",
    "sg:postcode":"6026",
    "sg:province":"Luzern",
    "wof:name":"Elektro Burkart Ag, Rain",
    "wof:placetype":"venue"
},
  "geometry": {"coordinates":[8.2570209503,47.1298103333],"type":"Point"}
}