{
  "type": "Feature",
  "properties": {
    "iso:country":"CH",
    "sg:address":"Kronenstrasse 6 8712 St\u00e4fa. Postfach",
    "sg:city":"St\u00e4fa",
    "sg:orig_category":"Sonstiger Grosshandel",
    "sg:postcode":"8712",
    "sg:province":"Z\u00fcrich",
    "wof:name":"Di Lena Import Export",
    "wof:placetype":"venue"
},
  "geometry": {"coordinates":[8.7244939804,47.2414894104],"type":"Point"}
}