{
  "type": "Feature",
  "properties": {
    "iso:country":"CH",
    "sg:address":"Chemin Des Planches 21",
    "sg:city":"Mont-sur-lausanne",
    "sg:orig_category":"Elektroinstallation",
    "sg:phone":"+41 21 652 64 56",
    "sg:postcode":"1052",
    "sg:province":"Vaud",
    "wof:name":"Electrofil Jenny Daniel",
    "wof:placetype":"venue"
},
  "geometry": {"coordinates":[6.6485948563,46.5652351379],"type":"Point"}
}