{
  "type": "Feature",
  "properties": {
    "iso:country":"CH",
    "sg:address":"Hohrain B4",
    "sg:city":"M\u00fchlehorn",
    "sg:orig_category":"Unclassifiable Establishments",
    "sg:postcode":"8874",
    "sg:province":"Glarus",
    "wof:name":"Rusc Ag",
    "wof:placetype":"venue"
},
  "geometry": {"coordinates":[9.172659874,47.1170082092],"type":"Point"}
}