{
  "type": "Feature",
  "properties": {
    "iso:country":"CH",
    "sg:address":"Bahnhofstrasse 2",
    "sg:city":"Visp",
    "sg:orig_category":"Herstellung von k\u00e4lte U lufttechnischen Erzeugnissen f\u00fcr gewerbliche Zwecke",
    "sg:phone":"+41 71 245 05 09",
    "sg:postcode":"3930",
    "sg:province":"Valais",
    "wof:name":"Wepo Wenk J.",
    "wof:placetype":"venue"
},
  "geometry": {"coordinates":[9.3088684082,47.4151916504],"type":"Point"}
}