{
  "type": "Feature",
  "properties": {
    "iso:country":"CH",
    "sg:address":"Fries Rue Hans- 1",
    "sg:city":"Fribourg",
    "sg:orig_category":"Architektur U Ingenieurb\u00fcros",
    "sg:postcode":"1700",
    "sg:province":"Fribourg",
    "wof:name":"Construicop Sa",
    "wof:placetype":"venue"
},
  "geometry": {"coordinates":[6.91466,46.690819],"type":"Point"}
}