{
  "type": "Feature",
  "properties": {
    "iso:country":"CH",
    "sg:address":"Luzernerstrasse 30 6030 Ebikon. Postfach 81",
    "sg:city":"Ebikon",
    "sg:orig_category":"Druck ohne Zeitungsdruck Offsetdruck",
    "sg:phone":"+41 41 445 70 50",
    "sg:postcode":"6031",
    "sg:province":"Luzern",
    "wof:name":"Buchdruckerei Ebikon Ag",
    "wof:placetype":"venue"
},
  "geometry": {"coordinates":[8.3297691345,47.075302124],"type":"Point"}
}