{
  "type": "Feature",
  "properties": {
    "iso:country":"CH",
    "sg:address":"Rue De La Combe 11",
    "sg:city":"Nyon",
    "sg:orig_category":"Unternehmensberatung",
    "sg:phone":"+41 31 305 20 10",
    "sg:postcode":"1260",
    "sg:province":"Vaud",
    "wof:name":"Karl H. Kellenberger Change Management",
    "wof:placetype":"venue"
},
  "geometry": {"coordinates":[7.4330191612,46.9743881226],"type":"Point"}
}