{
  "type": "Feature",
  "properties": {
    "iso:country":"CH",
    "sg:address":"Untere Mangelegg 3 6430 Schwyz. Postfach",
    "sg:city":"Schwyz",
    "sg:orig_category":"Bauingenieurb\u00fcros Heizung L\u00fcftung Klima",
    "sg:phone":"+41 41 811 40 70",
    "sg:postcode":"6430",
    "sg:province":"Schwyz",
    "wof:name":"Haus - Technik - Planung Spescha Otmar",
    "wof:placetype":"venue"
},
  "geometry": {"coordinates":[8.656671,47.027473],"type":"Point"}
}