{
  "type": "Feature",
  "properties": {
    "iso:country":"CH",
    "sg:address":"Rue St-didier 41",
    "sg:city":"Collombey",
    "sg:orig_category":"Sanit\u00e4r U Heizungsinstallation Sanit\u00e4rinstallation",
    "sg:phone":"+41 24 471 90 20",
    "sg:postcode":"1868",
    "sg:province":"Valais",
    "wof:name":"Ecoeur Fr\u00e8res Sa Install.chauffage-sanitaire",
    "wof:placetype":"venue"
},
  "geometry": {"coordinates":[6.9506540298,46.2688369751],"type":"Point"}
}