{
  "type": "Feature",
  "properties": {
    "iso:country":"CH",
    "sg:address":"Weinbergstrasse 41 8006 Z\u00fcrich. Postfach 231",
    "sg:city":"Z\u00fcrich",
    "sg:orig_category":"Unternehmensberatung",
    "sg:phone":"+41 12515221",
    "sg:postcode":"8028",
    "wof:name":"Cosit Ag",
    "wof:placetype":"venue"
},
  "geometry": {"coordinates":[8.5441904068,47.3798904419],"type":"Point"}
}