{
  "type": "Feature",
  "properties": {
    "iso:country":"CH",
    "sg:address":"Erlenweg 4",
    "sg:city":"Safenwil",
    "sg:orig_category":"Sportvereine Ballsport Handball",
    "sg:phone":"+41 31 839 09 88",
    "sg:postcode":"5745",
    "sg:province":"Aargau",
    "wof:name":"Satus Sv G\u00fcmligen",
    "wof:placetype":"venue"
},
  "geometry": {"coordinates":[7.5442538261,46.927406311],"type":"Point"}
}