{
  "type": "Feature",
  "properties": {
    "iso:country":"CH",
    "sg:address":"Route De Base 66",
    "sg:city":"Confignon",
    "sg:orig_category":"Blumen U Zierpflanzenbau Landschaftsplanungsb\u00fcros U Gartenarchitekturb\u00fcros",
    "sg:phone":"+41 22 794 80 66",
    "sg:postcode":"1232",
    "sg:province":"Gen\u00e8ve",
    "wof:name":"Orfeo Leonelli Etablissement Horticole",
    "wof:placetype":"venue"
},
  "geometry": {"coordinates":[6.10193,46.168388],"type":"Point"}
}