{
  "type": "Feature",
  "properties": {
    "iso:country":"CH",
    "sg:address":"6747",
    "sg:city":"Chironico",
    "sg:orig_category":"Allgemeiner Gartenbau Grosshandel mit Blumen U Pflanzen",
    "sg:phone":"+41 19840204",
    "sg:postcode":"6747",
    "sg:province":"Ticino",
    "wof:name":"Fawer Staudenkulturen Ag",
    "wof:placetype":"venue"
},
  "geometry": {"coordinates":[8.690055,47.300556],"type":"Point"}
}