{
  "type": "Feature",
  "properties": {
    "iso:country":"CH",
    "sg:address":"Route Des Jeunes 41g",
    "sg:city":"Carouge",
    "sg:classifiers":[
        {
            "category":"Shopping",
            "subcategory":"Computers & Home Electronics",
            "type":"Retail Goods"
        }
    ],
    "sg:phone":"+41 22 343 67 00",
    "sg:postcode":"1227",
    "sg:province":"Gen\u00e8ve",
    "sg:tags":[
        "blanket"
    ],
    "wof:name":"Multitoit Sa",
    "wof:placetype":"venue"
},
  "geometry": {"coordinates":[6.1303830147,46.1830711365],"type":"Point"}
}