{
  "type": "Feature",
  "properties": {
    "iso:country":"CH",
    "sg:address":"Bahnhofstrasse",
    "sg:city":"Langwies",
    "sg:orig_category":"Handel mit Automobilen",
    "sg:phone":"+41 81 374 22 73",
    "sg:postcode":"7057",
    "sg:province":"Graubunden",
    "wof:name":"Hafen Albert",
    "wof:placetype":"venue"
},
  "geometry": {"coordinates":[9.7078199387,46.8191871643],"type":"Point"}
}