{
  "type": "Feature",
  "properties": {
    "iso:country":"CH",
    "sg:address":"Weidstrasse 1 9602 Bazenheid. Postfach",
    "sg:city":"Bazenheid",
    "sg:orig_category":"Herstellung von Klebstoffen U Gelatinen",
    "sg:phone":"+41 71 931 47 10",
    "sg:postcode":"9602",
    "sg:province":"St. Gallen",
    "wof:name":"Turbo Klebstofftechnik Gmbh",
    "wof:placetype":"venue"
},
  "geometry": {"coordinates":[9.0632801056,47.4101066589],"type":"Point"}
}