{
  "type": "Feature",
  "properties": {
    "iso:country":"CH",
    "sg:address":"Via Cantonale",
    "sg:city":"Riazzino",
    "sg:classifiers":[
        {
            "category":"Organizations",
            "subcategory":"Labor Organization",
            "type":"Services"
        }
    ],
    "sg:phone":"+41 91 829 02 14",
    "sg:postcode":"6595",
    "sg:province":"Ticino",
    "sg:tags":[
        "varnishing",
        "painting",
        "system"
    ],
    "wof:name":"Termocolor Sagl",
    "wof:placetype":"venue"
},
  "geometry": {"coordinates":[8.9000196457,46.1742401123],"type":"Point"}
}