{
  "type": "Feature",
  "properties": {
    "iso:country":"CH",
    "sg:address":"Kapelle 1718 Rechthalten. Postfach",
    "sg:city":"Rechthalten",
    "sg:orig_category":"Herstellung von Konstruktionsteilen, Fertigbauteilen U Ausbauelementen aus Holz",
    "sg:postcode":"1718",
    "sg:province":"Fribourg",
    "wof:name":"Delaquis Leo",
    "wof:placetype":"venue"
},
  "geometry": {"coordinates":[7.2483091354,46.7665901184],"type":"Point"}
}