{
  "type": "Feature",
  "properties": {
    "iso:country":"CH",
    "sg:address":"M\u00fchlegasse 11 8001 Z\u00fcrich. Postfach",
    "sg:city":"Z\u00fcrich",
    "sg:orig_category":"Finanzierungsinstitutionen Herstellung von Papier, Karton U Pappe",
    "sg:phone":"+41 12612025",
    "sg:postcode":"8025",
    "wof:name":"Zurich/switzerland Branch Of Apr Consulting (international) Ltd, Tortola (british Virgin Islands",
    "wof:placetype":"venue"
},
  "geometry": {"coordinates":[8.543964386,47.3743553162],"type":"Point"}
}