{
  "type": "Feature",
  "properties": {
    "iso:country":"CH",
    "sg:address":"1626",
    "sg:city":"Romanens",
    "sg:orig_category":"Detailhandel mit Milcherzeugnissen U Eiern Verwertung von Milch",
    "sg:phone":"+41 26 917 81 06",
    "sg:postcode":"1626",
    "sg:province":"Fribourg",
    "wof:name":"Caille Dominique",
    "wof:placetype":"venue"
},
  "geometry": {"coordinates":[6.9699897766,46.6510314941],"type":"Point"}
}