{
  "type": "Feature",
  "properties": {
    "iso:country":"CH",
    "sg:address":"Entlebucherstrasse 36",
    "sg:city":"Wolhusen",
    "sg:orig_category":"Unclassifiable Establishments",
    "sg:postcode":"6110",
    "sg:province":"Luzern",
    "wof:name":"Hofstetter Paul Ern\u00e4hrungsberater / Dipl. Sportmasseur",
    "wof:placetype":"venue"
},
  "geometry": {"coordinates":[8.070356369,47.0580177307],"type":"Point"}
}