{
  "type": "Feature",
  "properties": {
    "iso:country":"CH",
    "sg:address":"Champ-du-moulin La Coccinelle",
    "sg:city":"Noiraigue",
    "sg:orig_category":"Allgemeiner Hoch U Tiefbau",
    "sg:postcode":"2103",
    "sg:province":"Neuch\u00e2tel",
    "wof:name":"Acro-b\u00e2t, Racine",
    "wof:placetype":"venue"
},
  "geometry": {"coordinates":[6.718931,46.956524],"type":"Point"}
}