{
  "type": "Feature",
  "properties": {
    "iso:country":"CH",
    "sg:address":"Route De Cl\u00e9menty 62",
    "sg:city":"Nyon",
    "sg:orig_category":"Rechtsberatung Wirtschaftspr\u00fcfung, Steuerberatung U Treuhand",
    "sg:phone":"+41 22 362 17 26",
    "sg:postcode":"1260",
    "sg:province":"Vaud",
    "wof:name":"Cabinet Fiduciaire Jean-fran\u00e7ois Duc",
    "wof:placetype":"venue"
},
  "geometry": {"coordinates":[6.2285428047,46.3815231323],"type":"Point"}
}