{
  "type": "Feature",
  "properties": {
    "iso:country":"CH",
    "sg:address":"Buggenacherstrasse 26",
    "sg:city":"Adligenswil",
    "sg:orig_category":"Sonstige mit der Informatik verbundene T\u00e4tigkeiten",
    "sg:phone":"+41 41 372 03 40",
    "sg:postcode":"6043",
    "sg:province":"Luzern",
    "wof:name":"Intelligent Object Systems Gmbh Informatik; Consulting, Beratung, Projektleitung Usw",
    "wof:placetype":"venue"
},
  "geometry": {"coordinates":[8.3570890427,47.0647926331],"type":"Point"}
}