{
  "type": "Feature",
  "properties": {
    "iso:country":"CH",
    "sg:address":"Rue Centrale 67",
    "sg:city":"Avenches",
    "sg:orig_category":"Chemische Reinigung",
    "sg:phone":"+41 26 675 20 16",
    "sg:postcode":"1580",
    "sg:province":"Vaud",
    "wof:name":"Nettoyage Chimique",
    "wof:placetype":"venue"
},
  "geometry": {"coordinates":[7.0396738052,46.8792228699],"type":"Point"}
}