{
  "type": "Feature",
  "properties": {
    "iso:country":"CH",
    "sg:address":"Circoli Via Dei",
    "sg:city":"Cadro",
    "sg:orig_category":"Interessenvertretungen",
    "sg:postcode":"6965",
    "sg:province":"Ticino",
    "wof:name":"Fondazione Fumasoli Silvio, Fu Di Pietro Alfredo",
    "wof:placetype":"venue"
},
  "geometry": {"coordinates":[8.9858007431,46.0512542725],"type":"Point"}
}