{
  "type": "Feature",
  "properties": {
    "iso:country":"CH",
    "sg:address":"8514",
    "sg:city":"Strohwilen",
    "sg:orig_category":"Schulpflegen",
    "sg:phone":"+41 71 651 17 15",
    "sg:postcode":"8514",
    "sg:province":"Thurgau",
    "wof:name":"Primarschulkommission Der Gemeinde Strohwilen-wolfikon",
    "wof:placetype":"venue"
},
  "geometry": {"coordinates":[9.0156497955,47.5522117615],"type":"Point"}
}