{
  "type": "Feature",
  "properties": {
    "iso:country":"CH",
    "sg:address":"Sch\u00f6ngr\u00fcnstrasse 2 4500 Solothurn. Postfach",
    "sg:city":"Solothurn",
    "sg:orig_category":"Grosshandel mit Werkzeugmaschinen Grosshandel mit sonstigen Maschinen U Ausr\u00fcstungen f\u00fcr Industrie, ",
    "sg:phone":"+41 21 802 31 41",
    "sg:postcode":"4502",
    "sg:province":"Solothurn",
    "wof:name":"Fmo Sa Fournitures Pour Machines-outils",
    "wof:placetype":"venue"
},
  "geometry": {"coordinates":[6.4852838516,46.5030937195],"type":"Point"}
}