{
  "type": "Feature",
  "properties": {
    "iso:country":"CH",
    "sg:address":"Avenue De Tourbillon 26c 1950 Sion Case Postale 80",
    "sg:city":"Sion",
    "sg:orig_category":"Geb\u00e4ude, Wohnungsreinigung Reinigungsgewerbe",
    "sg:phone":"+41 27 323 12 19",
    "sg:postcode":"1951",
    "sg:province":"Valais",
    "wof:name":"Bruttin Paul-henri, Nettoyage",
    "wof:placetype":"venue"
},
  "geometry": {"coordinates":[7.3630590439,46.2288856506],"type":"Point"}
}