{
  "type": "Feature",
  "properties": {
    "iso:country":"CH",
    "sg:address":"Via Dogana 10",
    "sg:city":"Bellinzona",
    "sg:orig_category":"Detailhandel mit Sportartikeln",
    "sg:phone":"+41 91 825 13 73",
    "sg:postcode":"6500",
    "sg:province":"Ticino",
    "wof:name":"Colombo Edoardo Articoli Di Ferramenta, Di Armeria, Ecc; Commercio",
    "wof:placetype":"venue"
},
  "geometry": {"coordinates":[9.0212545395,46.1905479431],"type":"Point"}
}