{
  "type": "Feature",
  "properties": {
    "iso:country":"CH",
    "sg:address":"Calandastrasse 28 7000 Chur. Postfach 126",
    "sg:city":"Chur",
    "sg:orig_category":"Interessenvertretungen Sonstige Institutionen des Sozialwesens ohne Beherbergung",
    "sg:phone":"+41 81 353 38 88",
    "sg:postcode":"7002",
    "sg:province":"Graubunden",
    "wof:name":"B\u00fcndner Hilfe F\u00fcr Mutter Und Kind",
    "wof:placetype":"venue"
},
  "geometry": {"coordinates":[9.5286655426,46.8566360474],"type":"Point"}
}