{
  "type": "Feature",
  "properties": {
    "iso:country":"CH",
    "sg:address":"Schulstrasse 361",
    "sg:city":"B\u00e4rschwil",
    "sg:orig_category":"Sportvereine Turnen Vereine Damen",
    "sg:postcode":"4252",
    "sg:province":"Solothurn",
    "wof:name":"Damenriege Stv B\u00e4rschwil",
    "wof:placetype":"venue"
},
  "geometry": {"coordinates":[7.4750537872,47.3837890625],"type":"Point"}
}