{
  "type": "Feature",
  "properties": {
    "iso:country":"CH",
    "sg:address":"Niederhofenrain 33",
    "sg:city":"Zollikon",
    "sg:orig_category":"Detailhandel mit Schuhen Sonstiger Grosshandel",
    "sg:phone":"+41 13921866",
    "sg:postcode":"8702",
    "sg:province":"Z\u00fcrich",
    "wof:name":"Willy L\u00f6w Shoes Ag",
    "wof:placetype":"venue"
},
  "geometry": {"coordinates":[8.5769805908,47.3480262756],"type":"Point"}
}