{
  "type": "Feature",
  "properties": {
    "iso:country":"CH",
    "sg:address":"Via Adamini 24 6900 Lugano. Postfach 6907 Lugano",
    "sg:city":"Caselle",
    "sg:orig_category":"Architekturb\u00fcros",
    "sg:phone":"+41 91 994 82 59",
    "sg:postcode":"7",
    "wof:name":"Giovanzana & Montofani Studio D'architettura",
    "wof:placetype":"venue"
},
  "geometry": {"coordinates":[8.944071,45.997681],"type":"Point"}
}