{
  "type": "Feature",
  "properties": {
    "iso:country":"CH",
    "sg:address":"Industriestrasse 78",
    "sg:city":"Olten",
    "sg:orig_category":"Herstellung von Bergwerks U Baumaschinen",
    "sg:phone":"+41 62 287 69 10",
    "sg:postcode":"4600",
    "sg:province":"Solothurn",
    "wof:name":"Baumann Bautechnik Ag",
    "wof:placetype":"venue"
},
  "geometry": {"coordinates":[7.9137067795,47.3616333008],"type":"Point"}
}