{
  "type": "Feature",
  "properties": {
    "iso:country":"CH",
    "sg:address":"H\u00fcbel 72",
    "sg:city":"Zeglingen",
    "sg:orig_category":"Zimmerei, Dachdeckerei, Bauspenglerei U Abdichtung",
    "sg:phone":"+41 61 981 61 06",
    "sg:postcode":"4495",
    "sg:province":"Basel-Landschaft",
    "wof:name":"Zimmerei, Bedachungen Rickenbacher",
    "wof:placetype":"venue"
},
  "geometry": {"coordinates":[7.9076099396,47.4159317017],"type":"Point"}
}