{
  "type": "Feature",
  "properties": {
    "iso:country":"CH",
    "sg:address":"Lausanne Rue De 81",
    "sg:city":"Fribourg",
    "sg:orig_category":"Interessenvertretungen",
    "sg:postcode":"1700",
    "sg:province":"Fribourg",
    "wof:name":"L'a\u00e9rotique Fondation",
    "wof:placetype":"venue"
},
  "geometry": {"coordinates":[7.1570320129,46.805393219],"type":"Point"}
}