{
  "type": "Feature",
  "properties": {
    "iso:country":"CH",
    "sg:address":"Bahnhofstrasse 40",
    "sg:city":"Chur",
    "sg:orig_category":"Mechanik",
    "sg:postcode":"7000",
    "sg:province":"Graubunden",
    "wof:name":"Leitner Ag, Sterzing (i), Zweigniederlassung Chur",
    "wof:placetype":"venue"
},
  "geometry": {"coordinates":[9.5316858292,46.8511428833],"type":"Point"}
}