{
  "type": "Feature",
  "properties": {
    "iso:country":"CH",
    "sg:address":"Rue Tour",
    "sg:city":"Crassier",
    "sg:orig_category":"Detailhandel mit Geschenkartikeln U Souvenirs Herstellung von Teppichen",
    "sg:phone":"+41 22 367 16 37",
    "sg:postcode":"1263",
    "sg:province":"Vaud",
    "wof:name":"Corth\u00e9sy Eric.",
    "wof:placetype":"venue"
},
  "geometry": {"coordinates":[6.1735501289,46.3780136108],"type":"Point"}
}