{
  "type": "Feature",
  "properties": {
    "iso:country":"CH",
    "sg:address":"Unterdorfstrasse 15",
    "sg:city":"Oberentfelden",
    "sg:orig_category":"RESTAURANTS: TEA-ROOMS",
    "sg:phone":"+41 79 332 57 75",
    "sg:postcode":"5036",
    "sg:province":"Aargau",
    "wof:name":"Peccianti Giuliano Pizzeria Toscana",
    "wof:placetype":"venue"
},
  "geometry": {"coordinates":[8.0484876633,47.3599777222],"type":"Point"}
}