{
  "type": "Feature",
  "properties": {
    "iso:country":"CH",
    "sg:address":"Schulstrasse 4",
    "sg:city":"Kaisten",
    "sg:classifiers":[
        {
            "category":"Restaurant",
            "type":"Food & Drink"
        }
    ],
    "sg:phone":"+41 22 301 37 97",
    "sg:postcode":"5082",
    "sg:province":"Aargau",
    "wof:name":"Caf\u00e9-restaurant El Mansoura",
    "wof:placetype":"venue"
},
  "geometry": {"coordinates":[6.1385560036,46.1879920959],"type":"Point"}
}