{
  "type": "Feature",
  "properties": {
    "iso:country":"CH",
    "sg:address":"Im Zentrum 9b",
    "sg:city":"Adligenswil",
    "sg:orig_category":"Elektroinstallation Herstellung von sonstigen elektrischen Ausr\u00fcstungen",
    "sg:phone":"+41 79 233 20 16",
    "sg:postcode":"6043",
    "sg:province":"Luzern",
    "wof:name":"Sapeg Sa",
    "wof:placetype":"venue"
},
  "geometry": {"coordinates":[6.3349947929,46.4712104797],"type":"Point"}
}