{
  "type": "Feature",
  "properties": {
    "iso:country":"CH",
    "sg:address":"Le-corbusier Rue 18 1208 Gen\u00e8ve. Postfach",
    "sg:city":"Gen\u00e8ve",
    "sg:orig_category":"Fachdetailhandel in Verkaufsr\u00e4umen",
    "sg:postcode":"1208",
    "sg:province":"Gen\u00e8ve",
    "wof:name":"Ch\u00e4bu Ming Gmbh",
    "wof:placetype":"venue"
},
  "geometry": {"coordinates":[8.3134536743,46.9878044128],"type":"Point"}
}