{
  "type": "Feature",
  "properties": {
    "iso:country":"CH",
    "sg:address":"Niederdorfstrasse 67",
    "sg:city":"Z\u00fcrich",
    "sg:orig_category":"Werbeagenturen Werbegrafikateliers",
    "sg:phone":"+41 12529875",
    "sg:postcode":"8001",
    "sg:province":"Z\u00fcrich",
    "wof:name":"Zoix Design Neumayer Carmen",
    "wof:placetype":"venue"
},
  "geometry": {"coordinates":[8.5439577103,47.3758468628],"type":"Point"}
}