{
  "type": "Feature",
  "properties": {
    "iso:country":"CH",
    "sg:address":"G\u00f6tze 7",
    "sg:city":"Rafz",
    "sg:orig_category":"Unternehmensberatung",
    "sg:postcode":"8197",
    "sg:province":"Z\u00fcrich",
    "wof:name":"Leconsult E.e. Lengacher",
    "wof:placetype":"venue"
},
  "geometry": {"coordinates":[8.5416593552,47.6128730774],"type":"Point"}
}