{
  "type": "Feature",
  "properties": {
    "iso:country":"CH",
    "sg:address":"Route D'italie",
    "sg:city":"Uvrier",
    "sg:orig_category":"Instandhaltung U Reparatur von Automobilen",
    "sg:phone":"+41 27 203 22 80",
    "sg:postcode":"1958",
    "sg:province":"Valais",
    "wof:name":"Garage Stop, Masoch Et Salina.",
    "wof:placetype":"venue"
},
  "geometry": {"coordinates":[7.4114508629,46.2519340515],"type":"Point"}
}