{
  "type": "Feature",
  "properties": {
    "iso:country":"CH",
    "sg:address":"Oberdorfstrasse 23",
    "sg:city":"W\u00e4denswil",
    "sg:orig_category":"Arztpraxen",
    "sg:phone":"+41 55 210 44 55",
    "sg:postcode":"8820",
    "sg:province":"Z\u00fcrich",
    "wof:name":"Dr.med.andres Billeter Spezialarzt Fmh",
    "wof:placetype":"venue"
},
  "geometry": {"coordinates":[8.816333,47.227016],"type":"Point"}
}