{
  "type": "Feature",
  "properties": {
    "iso:country":"CH",
    "sg:address":"Fehlwiesstrasse 12",
    "sg:city":"Amriswil",
    "sg:classifiers":[
        {
            "category":"Shopping",
            "subcategory":"Computers & Home Electronics",
            "type":"Retail Goods"
        }
    ],
    "sg:phone":"+41 71 466 24 00",
    "sg:postcode":"8580",
    "sg:province":"Thurgau",
    "sg:tags":[
        "equipment",
        "household",
        "electrical",
        "appliance",
        "electronic"
    ],
    "wof:name":"Eugster/frismag Ag",
    "wof:placetype":"venue"
},
  "geometry": {"coordinates":[9.3091173172,47.5486831665],"type":"Point"}
}