{
  "type": "Feature",
  "properties": {
    "iso:country":"CH",
    "sg:address":"Zaunweg 2",
    "sg:city":"Wabern",
    "sg:classifiers":[
        {
            "category":"Professional",
            "subcategory":"Employment Agencies",
            "type":"Services"
        }
    ],
    "sg:phone":"+41 31 972 22 00",
    "sg:postcode":"3084",
    "sg:province":"Bern",
    "sg:tags":[
        "personal",
        "u",
        "stellenvermittlung"
    ],
    "wof:name":"Aktiv Personal Ag",
    "wof:placetype":"venue"
},
  "geometry": {"coordinates":[7.4397711754,46.9295806885],"type":"Point"}
}