{
  "type": "Feature",
  "properties": {
    "iso:country":"CH",
    "sg:address":"Hauptstr.",
    "sg:city":"Kandersteg",
    "sg:orig_category":"Detailhandel mit Brot, Back U S\u00fcsswaren",
    "sg:postcode":"3718",
    "sg:province":"Bern",
    "wof:name":"K\u00fcnzi-klopfer, Frau N.",
    "wof:placetype":"venue"
},
  "geometry": {"coordinates":[7.664167,46.478172],"type":"Point"}
}