{
  "type": "Feature",
  "properties": {
    "iso:country":"CH",
    "sg:address":"1446",
    "sg:city":"Baulmes",
    "sg:orig_category":"Vereine Gesang",
    "sg:postcode":"1446",
    "sg:province":"Vaud",
    "wof:name":"Choeur D'hommes De Bagnes",
    "wof:placetype":"venue"
},
  "geometry": {"coordinates":[7.2124481201,46.0804595947],"type":"Point"}
}