{
  "type": "Feature",
  "properties": {
    "iso:country":"CH",
    "sg:address":"Caguils Via 23",
    "sg:city":"Domat/ems",
    "sg:orig_category":"Herstellung von Konstruktionsteilen, Fertigbauteilen U Ausbauelementen aus Holz",
    "sg:postcode":"7013",
    "sg:province":"Graubunden",
    "wof:name":"Rico Huber",
    "wof:placetype":"venue"
},
  "geometry": {"coordinates":[9.4590835571,46.8356513977],"type":"Point"}
}