{
  "type": "Feature",
  "properties": {
    "iso:country":"CH",
    "sg:address":"Place Du March\u00e9 23",
    "sg:city":"Bex",
    "sg:orig_category":"Architektur U Ingenieurb\u00fcros",
    "sg:phone":"+41 24 463 02 92",
    "sg:postcode":"1880",
    "sg:province":"Vaud",
    "wof:name":"Le Cov\u00e9 Sa",
    "wof:placetype":"venue"
},
  "geometry": {"coordinates":[7.014884,46.251129],"type":"Point"}
}