{
  "type": "Feature",
  "properties": {
    "addr:full":"Thesenacher 44 Zumikon Z\u00fcrich 8126",
    "addr:housenumber":"44",
    "addr:postcode":"8126",
    "addr:street":"Thesenacher",
    "iso:country":"CH",
    "sg:address":"Thesenacher 44",
    "sg:city":"Zumikon",
    "sg:classifiers":[
        {
            "category":"Communications",
            "subcategory":"Television Station",
            "type":"Services"
        }
    ],
    "sg:phone":"+41 19190333",
    "sg:postcode":"8126",
    "sg:province":"Z\u00fcrich",
    "sg:tags":[
        "avionics"
    ],
    "wof:name":"Utzinger Handel & Technik",
    "wof:placetype":"venue"
},
  "geometry": {"coordinates":[8.629449,47.327839],"type":"Point"}
}