{
  "type": "Feature",
  "properties": {
    "iso:country":"CH",
    "sg:address":"Dorf 8765 Engi. Postfach",
    "sg:city":"Engi",
    "sg:orig_category":"Zimmerei, Dachdeckerei, Bauspenglerei U Abdichtung",
    "sg:phone":"+41 71 636 14 71",
    "sg:postcode":"8765",
    "sg:province":"Glarus",
    "wof:name":"D\u00f6rig Norbert Ag",
    "wof:placetype":"venue"
},
  "geometry": {"coordinates":[9.1711502075,47.5755577087],"type":"Point"}
}