{
  "type": "Feature",
  "properties": {
    "iso:country":"CH",
    "sg:address":"Baselstrasse 21",
    "sg:city":"Dittingen",
    "sg:orig_category":"Grosshandel mit Eisenwaren sowie Installationsbedarf f\u00fcr Gas, Wasser U Heizung Herstellung von Schre",
    "sg:phone":"+41 61 765 97 65",
    "sg:postcode":"4243",
    "sg:province":"Basel-Landschaft",
    "wof:name":"Zeugin Ag",
    "wof:placetype":"venue"
},
  "geometry": {"coordinates":[7.5093178749,47.426738739],"type":"Point"}
}