{
  "type": "Feature",
  "properties": {
    "iso:country":"CH",
    "sg:address":"Parkstrasse 1",
    "sg:city":"Sch\u00f6nenwerd",
    "sg:orig_category":"Pensionskassen",
    "sg:postcode":"5012",
    "sg:province":"Solothurn",
    "wof:name":"Alters Und Hinterbliebenenf\u00fcrsorge Der Bally Schuhfabriken Ag",
    "wof:placetype":"venue"
},
  "geometry": {"coordinates":[7.9991569519,47.3719558716],"type":"Point"}
}