{
  "type": "Feature",
  "properties": {
    "iso:country":"CH",
    "sg:address":"Freienhofgasse 5 3600 Thun. Postfach",
    "sg:city":"Thun",
    "sg:orig_category":"Film U Videofilmherstellung Werbeagenturen",
    "sg:phone":"+41 71 913 89 07",
    "sg:postcode":"3600",
    "sg:province":"Bern",
    "wof:name":"Rebell - Concepts Ag",
    "wof:placetype":"venue"
},
  "geometry": {"coordinates":[9.0328617096,47.4650878906],"type":"Point"}
}