{
  "type": "Feature",
  "properties": {
    "iso:country":"CH",
    "sg:address":"Nassackerstrasse 18",
    "sg:city":"Schlieren",
    "sg:orig_category":"RESTAURANTS: TEA-ROOMS",
    "sg:phone":"+41 17304352",
    "sg:postcode":"8952",
    "sg:province":"Z\u00fcrich",
    "wof:name":"Restaurant Nassacker, L\u00f6hrli R. + K., Schlieren",
    "wof:placetype":"venue"
},
  "geometry": {"coordinates":[8.441781044,47.3950576782],"type":"Point"}
}