{
  "type": "Feature",
  "properties": {
    "iso:country":"CH",
    "sg:address":"Tribeystr. 27",
    "sg:city":"Worben",
    "sg:orig_category":"Zimmerei, Dachdeckerei, Bauspenglerei U Abdichtung",
    "sg:postcode":"3252",
    "sg:province":"Bern",
    "wof:name":"Zimmerei W. B\u00fcrge Gmbh",
    "wof:placetype":"venue"
},
  "geometry": {"coordinates":[8.9961204529,47.4795417786],"type":"Point"}
}