{
  "type": "Feature",
  "properties": {
    "iso:country":"CH",
    "sg:address":"Feldhofstrasse 49 9230 Flawil. Postfach 212",
    "sg:city":"Flawil",
    "sg:orig_category":"Detailhandel mit Waren verschiedener Art, Hauptrichtung Nahrungsmittel Verwaltung von Immobilien",
    "sg:phone":"+41 91 857 57 67",
    "sg:postcode":"9230",
    "sg:province":"St. Gallen",
    "wof:name":"Satellite Denner Di Crema Mohammod Elena",
    "wof:placetype":"venue"
},
  "geometry": {"coordinates":[8.9955282211,46.187713623],"type":"Point"}
}