{
  "type": "Feature",
  "properties": {
    "iso:country":"CH",
    "sg:address":"Bahnhofstrasse 18 8880 Walenstadt. Postfach 100",
    "sg:city":"Walenstadt",
    "sg:orig_category":"Detailhandel mit Waren verschiedener Art, Hauptrichtung Nahrungsmittel",
    "sg:phone":"+41 81 735 28 10",
    "sg:postcode":"8880",
    "sg:province":"St. Gallen",
    "wof:name":"Migros Ostschweiz",
    "wof:placetype":"venue"
},
  "geometry": {"coordinates":[9.3137817383,47.1229476929],"type":"Point"}
}