{
  "type": "Feature",
  "properties": {
    "iso:country":"CH",
    "sg:address":"In Den R\u00fctenen 6",
    "sg:city":"Z\u00fcrich",
    "sg:orig_category":"Detailhandel mit Fahrr\u00e4dern Handel mit Motorr\u00e4dern, Teilen U Zubeh\u00f6r Instandhaltung U Reparatur von ",
    "sg:phone":"+41 14620672",
    "sg:postcode":"8055",
    "sg:province":"Z\u00fcrich",
    "wof:name":"Roberto Treccani Velofachhandel",
    "wof:placetype":"venue"
},
  "geometry": {"coordinates":[8.4925355911,47.366733551],"type":"Point"}
}