{
  "type": "Feature",
  "properties": {
    "iso:country":"CH",
    "sg:address":"Kurfirstenstrasse 12",
    "sg:city":"Chur",
    "sg:orig_category":"Tanzschulen, Tanzlehrer",
    "sg:phone":"+41 81 353 29 69",
    "sg:postcode":"7000",
    "sg:province":"Graubunden",
    "wof:name":"Tanz & Show-kompanie Tanzschule & Tanzclub",
    "wof:placetype":"venue"
},
  "geometry": {"coordinates":[9.5196590424,46.8586387634],"type":"Point"}
}