{
  "type": "Feature",
  "properties": {
    "iso:country":"CH",
    "sg:address":"3271",
    "sg:city":"Radelfingen",
    "sg:orig_category":"Verwertung von Milch",
    "sg:postcode":"3271",
    "sg:province":"Bern",
    "wof:name":"K\u00e4sereigenossenschaft Langnau",
    "wof:placetype":"venue"
},
  "geometry": {"coordinates":[7.9581828117,47.2328720093],"type":"Point"}
}