{
  "type": "Feature",
  "properties": {
    "iso:country":"CH",
    "sg:address":"Avouillons Route Des 6",
    "sg:city":"Gland",
    "sg:orig_category":"Unclassifiable Establishments",
    "sg:postcode":"1196",
    "sg:province":"Vaud",
    "wof:name":"Itris Informatik Sa, Succursale De Gland",
    "wof:placetype":"venue"
},
  "geometry": {"coordinates":[6.2679300308,46.4157905579],"type":"Point"}
}