{
  "type": "Feature",
  "properties": {
    "iso:country":"CH",
    "sg:address":"St. Galler Strasse 241",
    "sg:city":"Arbon",
    "sg:classifiers":[
        {
            "category":"Manufacturing",
            "subcategory":"Metals",
            "type":"Manufacturing & Wholesale Goods"
        }
    ],
    "sg:phone":"+41 71 446 03 23",
    "sg:postcode":"9320",
    "sg:province":"Thurgau",
    "sg:tags":[
        "u",
        "leichtmetallbau",
        "stahl"
    ],
    "wof:name":"R & S Metallbau Ag",
    "wof:placetype":"venue"
},
  "geometry": {"coordinates":[9.4080486298,47.5058326721],"type":"Point"}
}