{
  "type": "Feature",
  "properties": {
    "iso:country":"CH",
    "sg:address":"Incella 6614 Brissago. Postfach",
    "sg:city":"Brissago",
    "sg:orig_category":"Handelsvermittlung von Maschinen, technischem Bedarf, Wasser U Luftfahrzeugen",
    "sg:postcode":"6614",
    "sg:province":"Ticino",
    "wof:name":"Brimetal Sa",
    "wof:placetype":"venue"
},
  "geometry": {"coordinates":[8.7032365799,46.1161384583],"type":"Point"}
}