{
  "type": "Feature",
  "properties": {
    "iso:country":"CH",
    "sg:address":"Wetzikonerstrasse 43",
    "sg:city":"Auslikon",
    "sg:orig_category":"Kauf U Verkauf von Immobilien auf eigene Rechnung",
    "sg:postcode":"8331",
    "sg:province":"Z\u00fcrich",
    "wof:name":"Sunneschy Immobilien Ag",
    "wof:placetype":"venue"
},
  "geometry": {"coordinates":[8.8073453903,47.3432502747],"type":"Point"}
}