{
  "type": "Feature",
  "properties": {
    "addr:full":"Sch\u00f6ngrund 26 Rotkreuz 6343 Risch. Postfach Rotkreuz Zug 6343",
    "addr:housenumber":"26",
    "addr:postcode":"6343 risch. postfach;6343",
    "addr:street":"Schoengrund;Zug",
    "iso:country":"CH",
    "sg:address":"Sch\u00f6ngrund 26 Rotkreuz 6343 Risch. Postfach",
    "sg:city":"Rotkreuz",
    "sg:orig_category":"Architektur U Ingenieurb\u00fcros",
    "sg:postcode":"6343",
    "sg:province":"Zug",
    "wof:name":"Archidesign Rogenmoser D.",
    "wof:placetype":"venue"
},
  "geometry": {"coordinates":[8.466031,47.13414],"type":"Point"}
}