{
  "type": "Feature",
  "properties": {
    "addr:full":"Br\u00fcnnenstrasse 104 Bern Bern 3018",
    "addr:housenumber":"104",
    "addr:postcode":"3018",
    "addr:street":"Bruennenstrasse",
    "iso:country":"CH",
    "sg:address":"Br\u00fcnnenstrasse 104",
    "sg:city":"Bern",
    "sg:orig_category":"Detailhandel mit Bekleidung",
    "sg:phone":"+41 31 991 67 71",
    "sg:postcode":"3018",
    "sg:province":"Bern",
    "wof:name":"Sahara-laden Secondhand & Fair Trade",
    "wof:placetype":"venue"
},
  "geometry": {"coordinates":[7.389663,46.942051],"type":"Point"}
}