{
  "type": "Feature",
  "properties": {
    "iso:country":"CH",
    "sg:address":"Winkelgasse 2 3900 Brig. Postfach",
    "sg:city":"Brig",
    "sg:orig_category":"Werbung",
    "sg:phone":"+41 27 922 16 40",
    "sg:postcode":"3900",
    "sg:province":"Valais",
    "wof:name":"Visucom Ag",
    "wof:placetype":"venue"
},
  "geometry": {"coordinates":[7.9880161285,46.3174476624],"type":"Point"}
}