{
  "type": "Feature",
  "properties": {
    "iso:country":"CH",
    "sg:address":"Sch\u00fctzenrain 5",
    "sg:city":"Z\u00fcrich",
    "sg:orig_category":"Detailhandel mit B\u00fcchern",
    "sg:phone":"+41 14930146",
    "sg:postcode":"8047",
    "sg:province":"Z\u00fcrich",
    "wof:name":"Urs Heinz Aerni Buchhandel",
    "wof:placetype":"venue"
},
  "geometry": {"coordinates":[8.485742,47.372448],"type":"Point"}
}