{
  "type": "Feature",
  "properties": {
    "iso:country":"CH",
    "sg:address":"Junkerbifangstrasse 9",
    "sg:city":"Zofingen",
    "sg:orig_category":"Unclassifiable Establishments",
    "sg:postcode":"4800",
    "sg:province":"Aargau",
    "wof:name":"3c Facility Management Gmbh",
    "wof:placetype":"venue"
},
  "geometry": {"coordinates":[7.9465880394,47.2838058472],"type":"Point"}
}