{
  "type": "Feature",
  "properties": {
    "iso:country":"CH",
    "sg:address":"Baselstrasse 10",
    "sg:city":"Zwingen",
    "sg:orig_category":"Detailhandel mit Waren verschiedener Art, Hauptrichtung Nahrungsmittel Sonstiger Detailhandel mit Me",
    "sg:phone":"+41 61 765 95 95",
    "sg:postcode":"4222",
    "sg:province":"Basel-Landschaft",
    "wof:name":"Coop Bau & Hobbymarkt",
    "wof:placetype":"venue"
},
  "geometry": {"coordinates":[7.5344429016,47.43932724],"type":"Point"}
}