{
  "type": "Feature",
  "properties": {
    "iso:country":"CH",
    "sg:address":"Dorfstrasse 39",
    "sg:city":"W\u00fcrenlingen",
    "sg:orig_category":"Bauschreinerei Innenausbau",
    "sg:phone":"+41 56 281 18 81",
    "sg:postcode":"5303",
    "sg:province":"Aargau",
    "wof:name":"Urban Hirt Schreinerei & Innenausbau",
    "wof:placetype":"venue"
},
  "geometry": {"coordinates":[8.254957,47.533558],"type":"Point"}
}