{
  "type": "Feature",
  "properties": {
    "iso:country":"CH",
    "sg:address":"Strickhofstrasse 39",
    "sg:city":"Z\u00fcrich",
    "sg:orig_category":"Organisationen der Wohlfahrtspflege",
    "sg:phone":"+41 16356131",
    "sg:postcode":"8057",
    "sg:province":"Z\u00fcrich",
    "wof:name":"Infodienst Wildbiologie & Oekologie",
    "wof:placetype":"venue"
},
  "geometry": {"coordinates":[8.5493478775,47.3954734802],"type":"Point"}
}