{
  "type": "Feature",
  "properties": {
    "iso:country":"CH",
    "sg:address":"B\u00e4nnli 14",
    "sg:city":"Wolfwil",
    "sg:orig_category":"Grosshandel mit sonstigen Maschinen U Ausr\u00fcstungen f\u00fcr Industrie, Handel U Schiffahrt Herstellung vo",
    "sg:phone":"+41 55 240 52 61",
    "sg:postcode":"4628",
    "sg:province":"Solothurn",
    "wof:name":"Rebellato Schweisstechnik Gmbh",
    "wof:placetype":"venue"
},
  "geometry": {"coordinates":[8.8443202972,47.2569503784],"type":"Point"}
}