{
  "type": "Feature",
  "properties": {
    "iso:country":"CH",
    "sg:address":"Dorfstrasse 38",
    "sg:city":"Thalwil",
    "sg:classifiers":[
        {
            "category":"Restaurant",
            "type":"Food & Drink"
        }
    ],
    "sg:phone":"+41 17200565",
    "sg:postcode":"8800",
    "sg:province":"Z\u00fcrich",
    "wof:name":"Restaurant Grundstein",
    "wof:placetype":"venue"
},
  "geometry": {"coordinates":[8.564953804,47.2886695862],"type":"Point"}
}