{
  "type": "Feature",
  "properties": {
    "iso:country":"CH",
    "sg:address":"Rue De Cossonay 13",
    "sg:city":"Crissier",
    "sg:orig_category":"Grosshandel mit Wein U Spirituosen",
    "sg:phone":"+41 21 636 15 90",
    "sg:postcode":"1023",
    "sg:province":"Vaud",
    "wof:name":"Zanini Vini Sa Vins D'italie & Du Tessin",
    "wof:placetype":"venue"
},
  "geometry": {"coordinates":[6.5689702034,46.5557785034],"type":"Point"}
}