{
  "type": "Feature",
  "properties": {
    "iso:country":"CH",
    "sg:address":"Br\u00fchlgasse 44",
    "sg:city":"St.gallen",
    "sg:orig_category":"Mit dem Versicherungsgewerbe verbundene T\u00e4tigkeiten",
    "sg:phone":"+41 22 310 80 05",
    "sg:postcode":"9000",
    "sg:province":"St. Gallen",
    "wof:name":"Borella Et Cie Sa",
    "wof:placetype":"venue"
},
  "geometry": {"coordinates":[6.1401529312,46.2037315369],"type":"Point"}
}