{
  "type": "Feature",
  "properties": {
    "iso:country":"CH",
    "sg:address":"2545",
    "sg:city":"Selzach",
    "sg:orig_category":"Verarbeitung von Milch Verwertung von Milch",
    "sg:postcode":"2545",
    "sg:province":"Solothurn",
    "wof:name":"K\u00e4sereigenossenschaft Sempach-stadt",
    "wof:placetype":"venue"
},
  "geometry": {"coordinates":[8.2235832214,47.131149292],"type":"Point"}
}