{
  "type": "Feature",
  "properties": {
    "iso:country":"CH",
    "sg:address":"Thurgauerstrasse 72 8050 Z\u00fcrich. Postfach 8050 Z\u00fcrich",
    "sg:city":"Zust",
    "sg:orig_category":"Betrieb von Sportanlagen Textilgewerbe",
    "sg:phone":"+41 13121653",
    "sg:postcode":"50",
    "wof:name":"Basta Freizeit Und Sportanlagen Ag",
    "wof:placetype":"venue"
},
  "geometry": {"coordinates":[8.554675,47.417824],"type":"Point"}
}