{
  "type": "Feature",
  "properties": {
    "iso:country":"CH",
    "sg:address":"Krummbach 394",
    "sg:city":"Trogen",
    "sg:orig_category":"Allgemeiner Hoch U Tiefbau Allgemeiner Hochbau",
    "sg:phone":"+41 71 344 37 84",
    "sg:postcode":"9043",
    "sg:province":"Appenzell Ausserrhoden",
    "wof:name":"Schefer Hans",
    "wof:placetype":"venue"
},
  "geometry": {"coordinates":[9.464567,47.407932],"type":"Point"}
}