{
  "type": "Feature",
  "properties": {
    "iso:country":"CH",
    "sg:address":"T\u00f6belistrasse 4",
    "sg:city":"D\u00fcrnten",
    "sg:orig_category":"Grosshandel mit sonstigen Getr\u00e4nken",
    "sg:phone":"+41 33 676 12 20",
    "sg:postcode":"8635",
    "sg:province":"Z\u00fcrich",
    "wof:name":"Ernst Scherz Bier-& Mineralwasserdepot",
    "wof:placetype":"venue"
},
  "geometry": {"coordinates":[7.6914949417,46.6263656616],"type":"Point"}
}