{
  "type": "Feature",
  "properties": {
    "iso:country":"CH",
    "sg:address":"Teufental",
    "sg:city":"Bubendorf",
    "sg:orig_category":"Detailhandel mit Pelzwaren",
    "sg:phone":"+41 61 931 16 38",
    "sg:postcode":"4416",
    "sg:province":"Basel-Landschaft",
    "wof:name":"Hans B. Mayer K\u00fcrschneratelier",
    "wof:placetype":"venue"
},
  "geometry": {"coordinates":[7.7538409233,47.4522247314],"type":"Point"}
}