{
  "type": "Feature",
  "properties": {
    "iso:country":"CH",
    "sg:address":"Chemin Du Frut 1071 Chexbres. Postfach",
    "sg:city":"Chexbres",
    "sg:orig_category":"Sonstige mit Sport verbundene T\u00e4tigkeiten",
    "sg:postcode":"1071",
    "sg:province":"Vaud",
    "wof:name":"M\u00e9dia Sport, Lehmann",
    "wof:placetype":"venue"
},
  "geometry": {"coordinates":[6.7753958702,46.4852905273],"type":"Point"}
}