{
  "type": "Feature",
  "properties": {
    "iso:country":"CH",
    "sg:address":"Gehrenstrasse 23",
    "sg:city":"Muhen",
    "sg:orig_category":"Sonstiger Detailhandel nicht in Verkaufsr\u00e4umen",
    "sg:phone":"+41 62 723 78 24",
    "sg:postcode":"5037",
    "sg:province":"Aargau",
    "wof:name":"St\u00fctzli Snack Streit Thomas",
    "wof:placetype":"venue"
},
  "geometry": {"coordinates":[8.0588569641,47.3268127441],"type":"Point"}
}