{
  "type": "Feature",
  "properties": {
    "iso:country":"CH",
    "sg:address":"Rue Fontaines",
    "sg:city":"Chailly-montreux",
    "sg:orig_category":"Detailhandel mit Brot, Back U S\u00fcsswaren Detailhandel mit Waren verschiedener Art, Hauptrichtung Nahr",
    "sg:phone":"+41 33 744 13 24",
    "sg:postcode":"1816",
    "sg:province":"Vaud",
    "wof:name":"Dubi Christian, B\u00e4ckerei, Konditorei",
    "wof:placetype":"venue"
},
  "geometry": {"coordinates":[7.277245,46.480255],"type":"Point"}
}