{
  "type": "Feature",
  "properties": {
    "iso:country":"CH",
    "sg:address":"Seilerstrasse 18",
    "sg:city":"Hitzkirch",
    "sg:orig_category":"Strassenbau",
    "sg:phone":"+41 41 917 10 66",
    "sg:postcode":"6285",
    "sg:province":"Luzern",
    "wof:name":"Gebr. Amrein Ag Kieswerk Strassenbau & Muldenservice",
    "wof:placetype":"venue"
},
  "geometry": {"coordinates":[8.2596330643,47.2206954956],"type":"Point"}
}