{
  "type": "Feature",
  "properties": {
    "iso:country":"CH",
    "sg:address":"Huswisenstrasse 16",
    "sg:city":"Lufingen",
    "sg:orig_category":"Erschliessung von Grundst\u00fccken",
    "sg:postcode":"8426",
    "sg:province":"Z\u00fcrich",
    "wof:name":"Wohnbaugen.lufingen Wgl",
    "wof:placetype":"venue"
},
  "geometry": {"coordinates":[8.5947122574,47.491104126],"type":"Point"}
}