{
  "type": "Feature",
  "properties": {
    "iso:country":"CH",
    "sg:address":"Louis Giroud-strasse 20",
    "sg:city":"Olten",
    "sg:orig_category":"Arztpraxen",
    "sg:phone":"+41 62 286 66 86",
    "sg:postcode":"4600",
    "sg:province":"Solothurn",
    "wof:name":"Dr.med.rolf Obrecht Spezialarzt Fmh",
    "wof:placetype":"venue"
},
  "geometry": {"coordinates":[7.909667,47.346996],"type":"Point"}
}