{
  "type": "Feature",
  "properties": {
    "iso:country":"CH",
    "sg:address":"Leschot Rue 11 1205 Gen\u00e8ve. Postfach",
    "sg:city":"Gen\u00e8ve",
    "sg:orig_category":"Vermietung von Gebrauchsg\u00fctern",
    "sg:postcode":"1205",
    "sg:province":"Gen\u00e8ve",
    "wof:name":"Au Bal Masque, Sonia Schroeter-th\u00e9odoloz",
    "wof:placetype":"venue"
},
  "geometry": {"coordinates":[6.1441831589,46.1967163086],"type":"Point"}
}