{
  "type": "Feature",
  "properties": {
    "iso:country":"CH",
    "sg:address":"Obere Seestrasse 16",
    "sg:city":"Ermatingen",
    "sg:orig_category":"Gem\u00fcsebau",
    "sg:phone":"+41 71 664 11 23",
    "sg:postcode":"8272",
    "sg:province":"Thurgau",
    "wof:name":"August L\u00e4ubli Gem\u00fcsebau",
    "wof:placetype":"venue"
},
  "geometry": {"coordinates":[9.0864210129,47.6735343933],"type":"Point"}
}