{
  "type": "Feature",
  "properties": {
    "iso:country":"CH",
    "sg:address":"Bellikerstrasse 24",
    "sg:city":"Rudolfstetten",
    "sg:orig_category":"Non-Classified Establishments",
    "sg:phone":"+41 91 827 14 31",
    "sg:postcode":"8964",
    "sg:province":"Aargau",
    "wof:name":"Marco Pacciarelli Scalpellino",
    "wof:placetype":"venue"
},
  "geometry": {"coordinates":[9.1118984222,46.2385520935],"type":"Point"}
}