{
  "type": "Feature",
  "properties": {
    "iso:country":"CH",
    "sg:address":"Bahnhofstrasse 19",
    "sg:city":"Kreuzlingen",
    "sg:orig_category":"Detailhandel Reparatur von Gebrauchsg\u00fctern Vermietung von Gebrauchsg\u00fctern",
    "sg:phone":"+41 71 670 02 11",
    "sg:postcode":"8280",
    "sg:province":"Thurgau",
    "wof:name":"Joe's Multimedia Ag",
    "wof:placetype":"venue"
},
  "geometry": {"coordinates":[9.1703586578,47.6519851685],"type":"Point"}
}