{
  "type": "Feature",
  "properties": {
    "iso:country":"CH",
    "sg:address":"Trungen",
    "sg:city":"Bronschhofen",
    "sg:orig_category":"Grosshandel mit lebenden Tieren",
    "sg:phone":"+41 71 911 02 13",
    "sg:postcode":"9552",
    "sg:province":"St. Gallen",
    "wof:name":"Braun August Viehhandel",
    "wof:placetype":"venue"
},
  "geometry": {"coordinates":[9.0213499069,47.4786186218],"type":"Point"}
}