{
  "type": "Feature",
  "properties": {
    "addr:full":"Via Fontanone 7 Locarno Ticino 6600",
    "addr:housenumber":"7",
    "addr:postcode":"6600",
    "addr:street":"Via Fontanone;Ticino",
    "iso:country":"CH",
    "sg:address":"Via Fontanone 7",
    "sg:city":"Locarno",
    "sg:orig_category":"Allgemeiner Hoch U Tiefbau",
    "sg:phone":"+41 91 751 12 23",
    "sg:postcode":"6600",
    "sg:province":"Ticino",
    "wof:name":"Filipelli & Agustoni",
    "wof:placetype":"venue"
},
  "geometry": {"coordinates":[8.778168,46.17067],"type":"Point"}
}