{
  "type": "Feature",
  "properties": {
    "iso:country":"CH",
    "sg:address":"Blumenstrasse 3",
    "sg:city":"W\u00e4denswil",
    "sg:orig_category":"Zahnarztpraxen",
    "sg:phone":"+41 17803566",
    "sg:postcode":"8820",
    "sg:province":"Z\u00fcrich",
    "wof:name":"Dr. Med. Dent. Hans Frey Zahnarzt",
    "wof:placetype":"venue"
},
  "geometry": {"coordinates":[8.670706749,47.2291221619],"type":"Point"}
}