{
  "type": "Feature",
  "properties": {
    "iso:country":"CH",
    "sg:address":"Scherrerstrasse 4",
    "sg:city":"Winterthur",
    "sg:orig_category":"Gartenbau",
    "sg:phone":"+41 52 233 34 32",
    "sg:postcode":"8400",
    "sg:province":"Z\u00fcrich",
    "wof:name":"Christoph Styger Paradiesische G\u00e4rten",
    "wof:placetype":"venue"
},
  "geometry": {"coordinates":[8.742524147,47.4969711304],"type":"Point"}
}