{
  "type": "Feature",
  "properties": {
    "iso:country":"CH",
    "sg:address":"Bachelin Rue Auguste- 16",
    "sg:city":"Neuch\u00e2tel",
    "sg:orig_category":"Reiseb\u00fcros U Reiseveranstalter",
    "sg:phone":"+41 32 725 75 24",
    "sg:postcode":"2000",
    "sg:province":"Neuch\u00e2tel",
    "wof:name":"Thal\u00e8s Neuch\u00e2tel Sa",
    "wof:placetype":"venue"
},
  "geometry": {"coordinates":[6.9201879501,46.9941940308],"type":"Point"}
}