{
  "type": "Feature",
  "properties": {
    "iso:country":"CH",
    "sg:address":"Liebewilstrasse 220",
    "sg:city":"Gasel",
    "sg:orig_category":"Allgemeiner Gartenbau Landschaftsplanungsb\u00fcros U Gartenarchitekturb\u00fcros",
    "sg:phone":"+41 31 849 31 42",
    "sg:postcode":"3144",
    "sg:province":"Bern",
    "wof:name":"Br\u00fcgger Adrian Gartengestaltung Gmbh",
    "wof:placetype":"venue"
},
  "geometry": {"coordinates":[7.401854,46.899948],"type":"Point"}
}