{
  "type": "Feature",
  "properties": {
    "iso:country":"CH",
    "sg:address":"1907",
    "sg:city":"Mayens-de-saxon",
    "sg:orig_category":"Finanzierungsinstitutionen",
    "sg:postcode":"1907",
    "sg:province":"Valais",
    "wof:name":"Brumar Sa",
    "wof:placetype":"venue"
},
  "geometry": {"coordinates":[6.1042528152,46.1490287781],"type":"Point"}
}