{
  "type": "Feature",
  "properties": {
    "iso:country":"CH",
    "sg:address":"Vorderdorf 9043 Trogen. Postfach 241",
    "sg:city":"Trogen",
    "sg:orig_category":"Institutionen f\u00fcr Behinderte Wohnheime",
    "sg:phone":"+41 71 344 17 51",
    "sg:postcode":"9043",
    "sg:province":"Appenzell Ausserrhoden",
    "wof:name":"Ostschweizerisches Wohn Und Altersheim F\u00fcr Geh\u00f6rlose",
    "wof:placetype":"venue"
},
  "geometry": {"coordinates":[9.4657793045,47.4078025818],"type":"Point"}
}