{
  "type": "Feature",
  "properties": {
    "iso:country":"CH",
    "sg:address":"Chemin Des Celtes",
    "sg:city":"Lausanne",
    "sg:classifiers":[
        {
            "category":"Restaurant",
            "type":"Food & Drink"
        }
    ],
    "sg:phone":"+41 21 647 39 29",
    "sg:postcode":"1018",
    "sg:province":"Vaud",
    "wof:name":"Auberge Du Lac De Sauvabelin",
    "wof:placetype":"venue"
},
  "geometry": {"coordinates":[6.6390748024,46.5382423401],"type":"Point"}
}