{
  "type": "Feature",
  "properties": {
    "iso:country":"CH",
    "sg:address":"Bahnhofplatz 6",
    "sg:city":"Sarnen",
    "sg:orig_category":"Allgemeiner Hoch U Tiefbau",
    "sg:phone":"+41 17843390",
    "sg:postcode":"6060",
    "sg:province":"Obwalden",
    "wof:name":"Davinci Haus Ag",
    "wof:placetype":"venue"
},
  "geometry": {"coordinates":[8.247113,46.895287],"type":"Point"}
}