{
  "type": "Feature",
  "properties": {
    "iso:country":"CH",
    "sg:address":"Hirzbodenweg 48 4052 Basel. Postfach",
    "sg:city":"Basel",
    "sg:orig_category":"Herstellung von Uhren",
    "sg:postcode":"4051",
    "sg:province":"Basel-Stadt",
    "wof:name":"Imaging Duschletta Dokumentenverarbeitung Auf Elektronischem Weg, Beratung Usw",
    "wof:placetype":"venue"
},
  "geometry": {"coordinates":[7.6078429222,47.549697876],"type":"Point"}
}