{
  "type": "Feature",
  "properties": {
    "iso:country":"CH",
    "sg:address":"Rue C\u00f4tes-de-montbenon 24",
    "sg:city":"Lausanne",
    "sg:orig_category":"D\u00e4mmung gegen K\u00e4lte, W\u00e4rme, Schall U Ersch\u00fctterung Stukkateurgewerbe, Gipserei U Verputzerei",
    "sg:phone":"+41 21 312 49 15",
    "sg:postcode":"1003",
    "sg:province":"Vaud",
    "wof:name":"Fr Staff Sa",
    "wof:placetype":"venue"
},
  "geometry": {"coordinates":[6.6257500648,46.52135849],"type":"Point"}
}