{
  "type": "Feature",
  "properties": {
    "iso:country":"CH",
    "sg:address":"Nussbergstrasse 2 8483 Kollbrunn. Postfach",
    "sg:city":"Kollbrunn",
    "sg:orig_category":"Sonstige mit der Informatik verbundene T\u00e4tigkeiten",
    "sg:phone":"+41 52 394 01 01",
    "sg:postcode":"8483",
    "sg:province":"Z\u00fcrich",
    "wof:name":"Kds, Kaufmann Development & Support",
    "wof:placetype":"venue"
},
  "geometry": {"coordinates":[8.784538269,47.456703186],"type":"Point"}
}