{
  "type": "Feature",
  "properties": {
    "iso:country":"CH",
    "sg:address":"Oetlingerstrasse 163",
    "sg:city":"Basel",
    "sg:orig_category":"Detailhandel mit Musikinstrumenten",
    "sg:phone":"+41 61 692 45 28",
    "sg:postcode":"4057",
    "sg:province":"Basel-Stadt",
    "wof:name":"Franz Portmann Musikinstrumente",
    "wof:placetype":"venue"
},
  "geometry": {"coordinates":[7.5946788788,47.5679244995],"type":"Point"}
}