{
  "type": "Feature",
  "properties": {
    "addr:full":"Jurastrasse 4 Aarwangen Bern 4912",
    "addr:housenumber":"4",
    "addr:postcode":"4912",
    "addr:street":"Jurastrasse;Bern",
    "iso:country":"CH",
    "sg:address":"Jurastrasse 4",
    "sg:city":"Aarwangen",
    "sg:orig_category":"Detailhandel mit Bekleidung Grosshandel mit Textilien",
    "sg:phone":"+41 81 416 46 72",
    "sg:postcode":"4912",
    "sg:province":"Bern",
    "wof:name":"Mode Graf, Inhaber W\u00fcthrich Fritz",
    "wof:placetype":"venue"
},
  "geometry": {"coordinates":[9.835458,46.802238],"type":"Point"}
}