{
  "type": "Feature",
  "properties": {
    "iso:country":"CH",
    "sg:address":"Seestrasse 3",
    "sg:city":"Z\u00fcrich",
    "sg:orig_category":"RESTAURANTS: TEA-ROOMS",
    "sg:phone":"+41 26 652 33 77",
    "sg:postcode":"8002",
    "sg:province":"Z\u00fcrich",
    "wof:name":"Escale-caf\u00e9 S\u00e0rl",
    "wof:placetype":"venue"
},
  "geometry": {"coordinates":[6.9189181328,46.6969299316],"type":"Point"}
}