{
  "type": "Feature",
  "properties": {
    "iso:country":"CH",
    "sg:address":"Eugstisriet",
    "sg:city":"Sennwald",
    "sg:classifiers":[
        {
            "category":"Banks & Credit Unions",
            "subcategory":"Bank",
            "type":"Services"
        }
    ],
    "sg:phone":"+41 81 750 40 40",
    "sg:postcode":"9466",
    "sg:province":"St. Gallen",
    "wof:name":"Raiffeisenbank Sennwald",
    "wof:placetype":"venue"
},
  "geometry": {"coordinates":[9.50362,47.260658],"type":"Point"}
}