{
  "type": "Feature",
  "properties": {
    "iso:country":"CH",
    "sg:address":"Sch\u00f6ntalstrasse 1",
    "sg:city":"Z\u00fcrich",
    "sg:classifiers":[
        {
            "category":"Education",
            "subcategory":"Library",
            "type":"Public Place"
        }
    ],
    "sg:postcode":"8004",
    "sg:province":"Z\u00fcrich",
    "sg:tags":[
        "u",
        "bibliotheken",
        "archive"
    ],
    "wof:name":"Photo-archiv Bellavista Ag",
    "wof:placetype":"venue"
},
  "geometry": {"coordinates":[8.528251,47.369671],"type":"Point"}
}