{
  "type": "Feature",
  "properties": {
    "iso:country":"CH",
    "sg:address":"Aarwangenstrasse 4 4900 Langenthal. Postfach",
    "sg:city":"Langenthal",
    "sg:orig_category":"Kauf U Verkauf von Immobilien auf eigene Rechnung Vermietung U Verpachtung von eigenen Immobilien",
    "sg:phone":"+41 62 922 92 32",
    "sg:postcode":"4900",
    "sg:province":"Bern",
    "wof:name":"Tona Ag",
    "wof:placetype":"venue"
},
  "geometry": {"coordinates":[7.7883911133,47.2134246826],"type":"Point"}
}