{
  "type": "Feature",
  "properties": {
    "iso:country":"CH",
    "sg:address":"Temple Rue Du 8 2114 Fleurier. Postfach",
    "sg:city":"Fleurier",
    "sg:orig_category":"Interessenvertretungen",
    "sg:postcode":"2114",
    "sg:province":"Neuch\u00e2tel",
    "wof:name":"Fondation Jequier Andr\u00e9e Allouer Des Bourses D'\u00e9tudes Ou D'apprentissages, Sous Forme D'une Allocation Unique Ou Renouvelable \u00e0 Des Jeunes Gens Ou Jeunes Filles De Moins De Trente Ans Etc",
    "wof:placetype":"venue"
},
  "geometry": {"coordinates":[6.5848860741,46.9019737244],"type":"Point"}
}