{
  "type": "Feature",
  "properties": {
    "iso:country":"CH",
    "sg:address":"Rue Du Bourg 16",
    "sg:city":"Sierre",
    "sg:orig_category":"Wirtschaftspr\u00fcfung, Steuerberatung U Treuhand",
    "sg:phone":"+41 27 455 30 12",
    "sg:postcode":"3960",
    "sg:province":"Valais",
    "wof:name":"Fiduciaire Emery Fernand",
    "wof:placetype":"venue"
},
  "geometry": {"coordinates":[7.5343608856,46.293346405],"type":"Point"}
}