{
  "type": "Feature",
  "properties": {
    "iso:country":"CH",
    "sg:address":"La Roche 4 2315 Petit-martel. Postfach",
    "sg:city":"Petit-martel",
    "sg:orig_category":"M\u00f6belschreinereien",
    "sg:phone":"+41 32 937 14 34",
    "sg:postcode":"2315",
    "wof:name":"Yannopoulos St\u00e9phane",
    "wof:placetype":"venue"
},
  "geometry": {"coordinates":[6.7594099045,47.0115585327],"type":"Point"}
}