{
  "type": "Feature",
  "properties": {
    "iso:country":"CH",
    "sg:address":"Thaler Strasse 33",
    "sg:city":"Heiden",
    "sg:orig_category":"Vereine Vogel-& Naturschutz",
    "sg:phone":"+41 32 631 11 75",
    "sg:postcode":"9410",
    "sg:province":"Appenzell Ausserrhoden",
    "wof:name":"Ornitholog.verein Lachen/umg.",
    "wof:placetype":"venue"
},
  "geometry": {"coordinates":[8.8989076614,47.1829948425],"type":"Point"}
}