{
  "type": "Feature",
  "properties": {
    "iso:country":"CH",
    "sg:address":"Freiherrenstrasse 21",
    "sg:city":"Attinghausen",
    "sg:orig_category":"G\u00fcterbef\u00f6rderung im Strassenverkehr",
    "sg:postcode":"6468",
    "sg:province":"Uri",
    "wof:name":"Zurfluh Transporte Gmbh",
    "wof:placetype":"venue"
},
  "geometry": {"coordinates":[8.6308202744,46.860370636],"type":"Point"}
}