{
  "type": "Feature",
  "properties": {
    "iso:country":"CH",
    "sg:address":"B\u00fcttenen 7 4203 Grellingen. Postfach",
    "sg:city":"Grellingen",
    "sg:orig_category":"Herstellung von Schrauben, Nieten, Ketten U Federn",
    "sg:phone":"+41 61 741 17 65",
    "sg:postcode":"4203",
    "sg:province":"Basel-Landschaft",
    "wof:name":"H. Finger, Citovis",
    "wof:placetype":"venue"
},
  "geometry": {"coordinates":[7.5973858833,47.4425811768],"type":"Point"}
}