{
  "type": "Feature",
  "properties": {
    "iso:country":"CH",
    "sg:address":"Talbachstrasse 7",
    "sg:city":"Frauenfeld",
    "sg:orig_category":"Softwareentwicklung U beratung",
    "sg:postcode":"8500",
    "sg:province":"Thurgau",
    "wof:name":"Cansizyan Elektronik",
    "wof:placetype":"venue"
},
  "geometry": {"coordinates":[8.8818807602,47.5531997681],"type":"Point"}
}