{
  "type": "Feature",
  "properties": {
    "iso:country":"CH",
    "sg:address":"Dorfstrasse 181",
    "sg:city":"Oberkulm",
    "sg:orig_category":"Ger\u00fcstbau Sonstiger spezialisierter Hoch U Tiefbau",
    "sg:phone":"+41 62 773 26 26",
    "sg:postcode":"5727",
    "sg:province":"Aargau",
    "wof:name":"Pamo Ger\u00fcste Ag",
    "wof:placetype":"venue"
},
  "geometry": {"coordinates":[8.1141500473,47.303527832],"type":"Point"}
}