{
  "type": "Feature",
  "properties": {
    "addr:full":"R\u00f6telstrasse 18 8006 Z\u00fcrich. Postfach Z\u00fcrich Z\u00fcrich 8033",
    "addr:housenumber":"18",
    "addr:postcode":"8006 zuerich. postfach;8033",
    "addr:street":"Roetelstrasse",
    "iso:country":"CH",
    "sg:address":"R\u00f6telstrasse 18 8006 Z\u00fcrich. Postfach",
    "sg:city":"Z\u00fcrich",
    "sg:orig_category":"Architektur U Ingenieurb\u00fcros Webdesign",
    "sg:phone":"+41 13614055",
    "sg:postcode":"8033",
    "sg:province":"Z\u00fcrich",
    "wof:name":"Ditoy Gmbh",
    "wof:placetype":"venue"
},
  "geometry": {"coordinates":[8.537469,47.390591],"type":"Point"}
}