{
  "type": "Feature",
  "properties": {
    "iso:country":"CH",
    "sg:address":"Dorfstrasse 66",
    "sg:city":"Dachsen",
    "sg:orig_category":"Herstellung von Musikinstrumenten",
    "sg:phone":"+41 52 659 15 76",
    "sg:postcode":"8447",
    "sg:province":"Z\u00fcrich",
    "wof:name":"Orgelbau De Gier Ag",
    "wof:placetype":"venue"
},
  "geometry": {"coordinates":[8.6207199097,47.6634902954],"type":"Point"}
}