{
  "type": "Feature",
  "properties": {
    "iso:country":"CH",
    "sg:address":"Chemin De La Scie 15",
    "sg:city":"Bex",
    "sg:classifiers":[
        {
            "category":"Restaurant",
            "type":"Food & Drink"
        }
    ],
    "sg:phone":"+41 24 463 21 33",
    "sg:postcode":"1880",
    "sg:province":"Vaud",
    "wof:name":"Caf\u00e9 Des Alpes",
    "wof:placetype":"venue"
},
  "geometry": {"coordinates":[7.0260457993,46.2546691895],"type":"Point"}
}