{
  "type": "Feature",
  "properties": {
    "iso:country":"CH",
    "sg:address":"M\u00e4derslehn",
    "sg:city":"Wolhusen",
    "sg:orig_category":"Grosshandel mit lebenden Tieren",
    "sg:phone":"+41 41 490 24 20",
    "sg:postcode":"6110",
    "sg:province":"Luzern",
    "wof:name":"Ren\u00e9 Koch Schweinehandel",
    "wof:placetype":"venue"
},
  "geometry": {"coordinates":[8.0732545853,47.0589408875],"type":"Point"}
}