{
  "type": "Feature",
  "properties": {
    "iso:country":"CH",
    "sg:address":"Comte-g\u00e9raud Rue Du 17",
    "sg:city":"Onex",
    "sg:orig_category":"Forschung U Entwicklung im Bereich der Naturwissenschaften",
    "sg:phone":"+41 22 792 80 28",
    "sg:postcode":"1213",
    "sg:province":"Gen\u00e8ve",
    "wof:name":"F\u00e9d\u00e9ration Suisse Fibromyalgie",
    "wof:placetype":"venue"
},
  "geometry": {"coordinates":[6.1022548676,46.1924285889],"type":"Point"}
}