{
  "type": "Feature",
  "properties": {
    "iso:country":"CH",
    "sg:address":"Chemin Esparcette 5 1023 Crissier Case Postale",
    "sg:city":"Crissier",
    "sg:orig_category":"Herstellung von elektrischen Lampen U Leuchten",
    "sg:phone":"+41 21 903 02 35",
    "sg:postcode":"1023",
    "sg:province":"Vaud",
    "wof:name":"A+g Schr\u00e9der Sa",
    "wof:placetype":"venue"
},
  "geometry": {"coordinates":[6.7596287727,46.5948371887],"type":"Point"}
}