{
  "type": "Feature",
  "properties": {
    "iso:country":"CH",
    "sg:address":"Br\u00fchlstrasse 125",
    "sg:city":"Solothurn",
    "sg:orig_category":"Softwareentwicklung U beratung",
    "sg:postcode":"4500",
    "sg:province":"Solothurn",
    "wof:name":"Marmier Consulting Gmbh Beratung In Den Bereichen Informatik, Management, Organisation U. Projektf\u00fchrung",
    "wof:placetype":"venue"
},
  "geometry": {"coordinates":[8.5433559418,47.3211097717],"type":"Point"}
}