{
  "type": "Feature",
  "properties": {
    "iso:country":"CH",
    "sg:address":"M\u00fclimatthof 4",
    "sg:city":"M\u00fcnchringen",
    "sg:orig_category":"Unclassifiable Establishments",
    "sg:postcode":"3303",
    "sg:province":"Bern",
    "wof:name":"Suter Swiss Composite Group",
    "wof:placetype":"venue"
},
  "geometry": {"coordinates":[7.5190968513,47.0427436829],"type":"Point"}
}