{
  "type": "Feature",
  "properties": {
    "iso:country":"CH",
    "sg:address":"1978 Lens. Postfach",
    "sg:city":"Chermignon",
    "sg:orig_category":"Vermietung U Verpachtung von eigenen Immobilien",
    "sg:postcode":"3971",
    "sg:province":"Valais",
    "wof:name":"Clivaz Gaston.",
    "wof:placetype":"venue"
},
  "geometry": {"coordinates":[7.4485402107,46.2786102295],"type":"Point"}
}