{
  "type": "Feature",
  "properties": {
    "iso:country":"CH",
    "sg:address":"Neugasse 23",
    "sg:city":"Zug",
    "sg:orig_category":"Non-Classified Establishments",
    "sg:postcode":"6300",
    "sg:province":"Zug",
    "wof:name":"Imotas Gmbh",
    "wof:placetype":"venue"
},
  "geometry": {"coordinates":[8.8290872574,47.2285652161],"type":"Point"}
}