{
  "type": "Feature",
  "properties": {
    "iso:country":"CH",
    "sg:address":"Via Ramello 11",
    "sg:city":"Pregassona",
    "sg:orig_category":"Detailhandel mit M\u00f6beln U Haushaltsgegenst\u00e4nden Grosshandel mit M\u00f6beln, Wohnbedarf, Teppichen U Bode",
    "sg:phone":"+41 91 940 46 91",
    "sg:postcode":"6963",
    "sg:province":"Ticino",
    "wof:name":"Virgilio Martinelli Arredamento All'ingrosso",
    "wof:placetype":"venue"
},
  "geometry": {"coordinates":[8.9783964157,46.0259132385],"type":"Point"}
}