{
  "type": "Feature",
  "properties": {
    "iso:country":"CH",
    "sg:address":"3086 Zimmerwald. Postfach",
    "sg:city":"Zimmerwald",
    "sg:orig_category":"Wasserversorgung",
    "sg:postcode":"3086",
    "sg:province":"Bern",
    "wof:name":"Wanez Gmbh",
    "wof:placetype":"venue"
},
  "geometry": {"coordinates":[7.4716010094,46.8815917969],"type":"Point"}
}