{
  "type": "Feature",
  "properties": {
    "iso:country":"CH",
    "sg:address":"Reberastrasse 31",
    "sg:city":"Schaan",
    "sg:orig_category":"Handelsvermittlung U Grosshandel",
    "sg:phone":"+41 79 422 37 63",
    "sg:postcode":"9494",
    "wof:name":"Schneider Feuerschutz Ag",
    "wof:placetype":"venue"
},
  "geometry": {"coordinates":[9.5107088089,47.1651992798],"type":"Point"}
}