{
  "type": "Feature",
  "properties": {
    "iso:country":"CH",
    "sg:address":"Zelgliweg 36 4704 Niederbipp. Postfach 147",
    "sg:city":"Niederbipp",
    "sg:orig_category":"Sonstiger Grosshandel",
    "sg:phone":"+41 32 633 28 08",
    "sg:postcode":"4704",
    "sg:province":"Bern",
    "wof:name":"Paul Nebiker Vaportek Handelsagentur",
    "wof:placetype":"venue"
},
  "geometry": {"coordinates":[7.6883020401,47.272983551],"type":"Point"}
}