{
  "type": "Feature",
  "properties": {
    "iso:country":"CH",
    "sg:address":"Chemin De Pr\u00e9-gentil 1",
    "sg:city":"Satigny",
    "sg:orig_category":"Handel mit Automobilen",
    "sg:postcode":"1242",
    "sg:province":"Gen\u00e8ve",
    "wof:name":"Mc Motorhome Sa",
    "wof:placetype":"venue"
},
  "geometry": {"coordinates":[6.038962841,46.2155685425],"type":"Point"}
}