{
  "type": "Feature",
  "properties": {
    "iso:country":"CH",
    "sg:address":"Vicolo Fontanile 2",
    "sg:city":"Stabio",
    "sg:classifiers":[
        {
            "category":"Restaurant",
            "type":"Food & Drink"
        }
    ],
    "sg:phone":"+41 91 647 17 65",
    "sg:postcode":"6855",
    "sg:province":"Ticino",
    "wof:name":"Ristorante Svizzero",
    "wof:placetype":"venue"
},
  "geometry": {"coordinates":[8.9384679794,45.8513832092],"type":"Point"}
}