{
  "type": "Feature",
  "properties": {
    "iso:country":"CH",
    "sg:address":"Sagiweg 5",
    "sg:city":"Fulenbach",
    "sg:orig_category":"Architektur U Ingenieurb\u00fcros Architekturb\u00fcros",
    "sg:phone":"+41 62 926 36 49",
    "sg:postcode":"4629",
    "sg:province":"Solothurn",
    "wof:name":"Studer Markus Architektur + Bauleitungen",
    "wof:placetype":"venue"
},
  "geometry": {"coordinates":[7.835764,47.273911],"type":"Point"}
}