{
  "type": "Feature",
  "properties": {
    "iso:country":"CH",
    "sg:address":"Route Des Plaines-du-loup 7",
    "sg:city":"Lausanne",
    "sg:classifiers":[
        {
            "category":"Restaurant",
            "type":"Food & Drink"
        }
    ],
    "sg:phone":"+41 21 646 09 98",
    "sg:postcode":"1018",
    "sg:province":"Vaud",
    "wof:name":"Lausanne-sports",
    "wof:placetype":"venue"
},
  "geometry": {"coordinates":[6.6254529953,46.5344467163],"type":"Point"}
}