{
  "type": "Feature",
  "properties": {
    "iso:country":"CH",
    "sg:address":"Rishaldenweg 11c",
    "sg:city":"Rothrist",
    "sg:orig_category":"Handel mit Automobilen",
    "sg:phone":"+41 62 794 27 07",
    "sg:postcode":"4852",
    "sg:province":"Aargau",
    "wof:name":"Ato-buhowicz + Co",
    "wof:placetype":"venue"
},
  "geometry": {"coordinates":[7.892054081,47.3112640381],"type":"Point"}
}