{
  "type": "Feature",
  "properties": {
    "iso:country":"CH",
    "sg:address":"Via San Jorio 8",
    "sg:city":"Locarno",
    "sg:orig_category":"Arztpraxen",
    "sg:phone":"+41 91 752 22 22",
    "sg:postcode":"6600",
    "sg:province":"Ticino",
    "wof:name":"Dott.med.diana De Pedroni Medico Generico & Homeopata",
    "wof:placetype":"venue"
},
  "geometry": {"coordinates":[8.789805,46.16589],"type":"Point"}
}