{
  "type": "Feature",
  "properties": {
    "addr:full":"Via Tuma Cast\u00e9 7013 Domat/ems. Postfach 138 Domat/ems Graubunden 7013",
    "addr:housenumber":"138",
    "addr:postcode":"7013;7013",
    "addr:street":"Via Tuma Caste\u0301;Postfach",
    "iso:country":"CH",
    "sg:address":"Via Tuma Cast\u00e9 7013 Domat/ems. Postfach 138",
    "sg:city":"Domat/ems",
    "sg:orig_category":"Bauschreinerei Zimmerei, Dachdeckerei, Bauspenglerei U Abdichtung",
    "sg:phone":"+41 52 643 28 17",
    "sg:postcode":"7013",
    "sg:province":"Graubunden",
    "wof:name":"B\u00fchrer Holzbau Ag",
    "wof:placetype":"venue"
},
  "geometry": {"coordinates":[8.661946,47.739788],"type":"Point"}
}