{
  "type": "Feature",
  "properties": {
    "iso:country":"CH",
    "sg:address":"Schloss",
    "sg:city":"Interlaken",
    "sg:orig_category":"Interessenvertretungen",
    "sg:postcode":"3800",
    "sg:province":"Bern",
    "wof:name":"Stiftung Zur F\u00f6rderung Von Tradition Und Geschichte",
    "wof:placetype":"venue"
},
  "geometry": {"coordinates":[7.863530159,46.6876716614],"type":"Point"}
}