{
  "type": "Feature",
  "properties": {
    "iso:country":"CH",
    "sg:address":"Unterm\u00fcli 7",
    "sg:city":"Zug",
    "sg:classifiers":[
        {
            "category":"Professional",
            "subcategory":"Employment Agencies",
            "type":"Services"
        }
    ],
    "sg:postcode":"6300",
    "sg:province":"Zug",
    "sg:tags":[
        "personal",
        "u",
        "stellenvermittlung"
    ],
    "wof:name":"Suebo Informatik Ag",
    "wof:placetype":"venue"
},
  "geometry": {"coordinates":[8.5177021027,47.1804161072],"type":"Point"}
}