{
  "type": "Feature",
  "properties": {
    "iso:country":"CH",
    "sg:address":"Chemin Des Chanats 10",
    "sg:city":"Bellevue",
    "sg:orig_category":"Detailhandel mit Fleisch U Fleischwaren",
    "sg:phone":"+41 22 774 12 70",
    "sg:postcode":"1293",
    "sg:province":"Gen\u00e8ve",
    "wof:name":"D. Chiarello",
    "wof:placetype":"venue"
},
  "geometry": {"coordinates":[6.1356658936,46.254573822],"type":"Point"}
}