{
  "type": "Feature",
  "properties": {
    "iso:country":"CH",
    "sg:address":"Obergass 14 9494 Schaan. Postfach 465",
    "sg:city":"Schaan",
    "sg:orig_category":"Korrespondenz U Nachrichtenb\u00fcros",
    "sg:phone":"+41 26 411 28 31",
    "sg:postcode":"9494",
    "wof:name":"Roger De Diesbach Brri Agence De Presse",
    "wof:placetype":"venue"
},
  "geometry": {"coordinates":[7.1032958031,46.7191467285],"type":"Point"}
}