{
  "type": "Feature",
  "properties": {
    "iso:country":"CH",
    "sg:address":"Hauptstrasse 4",
    "sg:city":"K\u00fcblis",
    "sg:orig_category":"Herstellung von Konstruktionsteilen, Fertigbauteilen U Ausbauelementen aus Holz M\u00f6belschreinerei",
    "sg:phone":"+41 81 330 53 63",
    "sg:postcode":"7240",
    "sg:province":"Graubunden",
    "wof:name":"T + M Schreinerei Und Holzbau Gmbh",
    "wof:placetype":"venue"
},
  "geometry": {"coordinates":[9.7705440521,46.9136161804],"type":"Point"}
}