{
  "type": "Feature",
  "properties": {
    "iso:country":"CH",
    "sg:address":"Hauptstrasse 1",
    "sg:city":"Winistorf",
    "sg:orig_category":"Herstellung von Reiseartikeln, Leder U Sattlerwaren Innendekorationsateliers",
    "sg:phone":"+41 62 968 90 16",
    "sg:postcode":"4558",
    "sg:province":"Solothurn",
    "wof:name":"Jakob Kistler Sattler-tapezierer",
    "wof:placetype":"venue"
},
  "geometry": {"coordinates":[7.6354799271,47.1668548584],"type":"Point"}
}