{
  "type": "Feature",
  "properties": {
    "iso:country":"CH",
    "sg:address":"Zollstrasse 4",
    "sg:city":"Landquart",
    "sg:orig_category":"Zahnarztpraxen",
    "sg:phone":"+41 81 300 03 30",
    "sg:postcode":"7302",
    "sg:province":"Graubunden",
    "wof:name":"Dres Med.dent.s. & V. Rominger Zahn\u00e4rzte",
    "wof:placetype":"venue"
},
  "geometry": {"coordinates":[9.5587272644,46.9663352966],"type":"Point"}
}