{
  "type": "Feature",
  "properties": {
    "iso:country":"CH",
    "sg:address":"Sennengasse 7",
    "sg:city":"Unterstammheim",
    "sg:orig_category":"Inseratevermittlung Public-Relations-Agenturen",
    "sg:phone":"+41 52 745 32 31",
    "sg:postcode":"8476",
    "sg:province":"Z\u00fcrich",
    "wof:name":"Kurath Wirz & Partner",
    "wof:placetype":"venue"
},
  "geometry": {"coordinates":[8.7905464172,47.6385498047],"type":"Point"}
}