{
  "type": "Feature",
  "properties": {
    "iso:country":"CH",
    "sg:address":"Hirsackerstrasse 32",
    "sg:city":"Horgen",
    "sg:orig_category":"Schlossereien",
    "sg:phone":"+41 17257970",
    "sg:postcode":"8810",
    "sg:province":"Z\u00fcrich",
    "wof:name":"Rudolf G\u00e4hler Schlosserei",
    "wof:placetype":"venue"
},
  "geometry": {"coordinates":[8.6079759598,47.2577400208],"type":"Point"}
}