{
  "type": "Feature",
  "properties": {
    "iso:country":"CH",
    "sg:address":"Dietrichstrasse 3a",
    "sg:city":"Rheineck",
    "sg:orig_category":"Bauschreinerei Zimmerei, Ingenieurholzbau",
    "sg:phone":"+41 71 888 16 55",
    "sg:postcode":"9424",
    "sg:province":"St. Gallen",
    "wof:name":"Alfred B\u00fchler Gmbh Holzbau",
    "wof:placetype":"venue"
},
  "geometry": {"coordinates":[9.581723,47.474316],"type":"Point"}
}