{
  "type": "Feature",
  "properties": {
    "iso:country":"CH",
    "sg:address":"Letzigraben 142",
    "sg:city":"Z\u00fcrich",
    "sg:orig_category":"Kinderkrippen U horte",
    "sg:phone":"+41 14926188",
    "sg:postcode":"8047",
    "sg:province":"Z\u00fcrich",
    "wof:name":"Erfinder-treff",
    "wof:placetype":"venue"
},
  "geometry": {"coordinates":[8.4963006973,47.3754081726],"type":"Point"}
}