{
  "type": "Feature",
  "properties": {
    "iso:country":"CH",
    "sg:address":"Zeltweg 25",
    "sg:city":"Uster",
    "sg:orig_category":"Herstellung von Elektrizit\u00e4tsverteilungs U schalteinrichtungen",
    "sg:postcode":"8610",
    "sg:province":"Z\u00fcrich",
    "wof:name":"Lauper Instruments",
    "wof:placetype":"venue"
},
  "geometry": {"coordinates":[7.107916832,46.9198036194],"type":"Point"}
}