{
  "type": "Feature",
  "properties": {
    "iso:country":"CH",
    "sg:address":"Badstrasse 4j",
    "sg:city":"Blumenstein",
    "sg:orig_category":"Personal U Stellenvermittlung Sonstige mit der Informatik verbundene T\u00e4tigkeiten",
    "sg:phone":"+41 33 356 47 38",
    "sg:postcode":"3638",
    "sg:province":"Bern",
    "wof:name":"Beat Fritz Nydegger Consulting",
    "wof:placetype":"venue"
},
  "geometry": {"coordinates":[7.5205402374,46.741481781],"type":"Point"}
}