{
  "type": "Feature",
  "properties": {
    "iso:country":"CH",
    "sg:address":"Jakob-strasse 56 2504 Biel/bienne. Postfach",
    "sg:city":"Biel/bienne",
    "sg:orig_category":"Erschliessung von Grundst\u00fccken",
    "sg:postcode":"2504",
    "sg:province":"Bern",
    "wof:name":"Baugenossenschaft Concorde",
    "wof:placetype":"venue"
},
  "geometry": {"coordinates":[7.2745399475,47.1490020752],"type":"Point"}
}