{
  "type": "Feature",
  "properties": {
    "iso:country":"CH",
    "sg:address":"Rue De Combamare 21",
    "sg:city":"Chez-le-bart",
    "sg:orig_category":"Herstellung von Frischmilchprodukten",
    "sg:phone":"+41 32 835 13 24",
    "sg:postcode":"2025",
    "sg:province":"Neuch\u00e2tel",
    "wof:name":"Estavayer Lait Sa",
    "wof:placetype":"venue"
},
  "geometry": {"coordinates":[6.7841029167,46.8999252319],"type":"Point"}
}