{
  "type": "Feature",
  "properties": {
    "iso:country":"CH",
    "sg:address":"Champoussin",
    "sg:city":"Val-d'illiez",
    "sg:classifiers":[
        {
            "category":"Travel",
            "subcategory":"Hotels & Motels",
            "type":"Entertainment"
        }
    ],
    "sg:phone":"+41 81 833 38 67",
    "sg:postcode":"1873",
    "sg:province":"Valais",
    "sg:tags":[
        "hotels",
        "mit",
        "restaurant"
    ],
    "wof:name":"Testa Sergio & Co",
    "wof:placetype":"venue"
},
  "geometry": {"coordinates":[9.8306560516,46.5009880066],"type":"Point"}
}