{
  "type": "Feature",
  "properties": {
    "iso:country":"CH",
    "sg:address":"Freilagerstrasse 47 8000 Z\u00fcrich. Postfach",
    "sg:city":"Z\u00fcrich",
    "sg:orig_category":"Detailhandel mit M\u00f6beln U Haushaltsgegenst\u00e4nden",
    "sg:phone":"+41 81 740 57 10",
    "sg:postcode":"8043",
    "sg:province":"Z\u00fcrich",
    "wof:name":"Tavola E Cucina Gmbh",
    "wof:placetype":"venue"
},
  "geometry": {"coordinates":[9.4626941681,47.169380188],"type":"Point"}
}