{
  "type": "Feature",
  "properties": {
    "iso:country":"CH",
    "sg:address":"Zum H\u00f6lzli 33",
    "sg:city":"Winterthur",
    "sg:orig_category":"Organisationen der Wohlfahrtspflege",
    "sg:phone":"+41 27 952 18 74",
    "sg:postcode":"8405",
    "sg:province":"Z\u00fcrich",
    "wof:name":"Pro Juventute Des Bezirkes Visp",
    "wof:placetype":"venue"
},
  "geometry": {"coordinates":[7.8920350075,46.2011413574],"type":"Point"}
}