{
  "type": "Feature",
  "properties": {
    "iso:country":"CH",
    "sg:address":"Spalenring 90 4055 Basel. Postfach",
    "sg:city":"Basel",
    "sg:orig_category":"Unclassifiable Establishments",
    "sg:phone":"+41 61 307 94 94",
    "sg:postcode":"4009",
    "sg:province":"Basel-Stadt",
    "wof:name":"Adelga Ag Immobilien",
    "wof:placetype":"venue"
},
  "geometry": {"coordinates":[7.5746121407,47.5579071045],"type":"Point"}
}