{
  "type": "Feature",
  "properties": {
    "iso:country":"CH",
    "sg:address":"Bangarten 22 9490 Vaduz. Postfach 622",
    "sg:city":"Vaduz",
    "sg:orig_category":"Personal U Stellenvermittlung Unternehmensberatung",
    "sg:phone":"+423 237 55 77",
    "sg:postcode":"9490",
    "wof:name":"Sch\u00e4dler & Partner Consulting Ag",
    "wof:placetype":"venue"
},
  "geometry": {"coordinates":[9.5184497833,47.1417617798],"type":"Point"}
}