{
  "type": "Feature",
  "properties": {
    "iso:country":"CH",
    "sg:address":"Bocksrietstrasse 54",
    "sg:city":"Schaffhausen",
    "sg:orig_category":"Softwareentwicklung U beratung",
    "sg:postcode":"8200",
    "sg:province":"Schaffhausen",
    "wof:name":"Christen Informatik",
    "wof:placetype":"venue"
},
  "geometry": {"coordinates":[8.6466121674,47.7140159607],"type":"Point"}
}