{
  "type": "Feature",
  "properties": {
    "iso:country":"CH",
    "sg:address":"Neuhauserstrasse 73",
    "sg:city":"Frauenfeld",
    "sg:orig_category":"Sportvereine Ballsport Tennis",
    "sg:phone":"+41 21 691 56 53",
    "sg:postcode":"8500",
    "sg:province":"Thurgau",
    "wof:name":"Tennisclub Saint-sulpice",
    "wof:placetype":"venue"
},
  "geometry": {"coordinates":[6.547978878,46.5090827942],"type":"Point"}
}