{
  "type": "Feature",
  "properties": {
    "iso:country":"CH",
    "sg:address":"Susenbergstrasse 5",
    "sg:city":"Z\u00fcrich",
    "sg:orig_category":"Sportvereine Ballsport Tennis",
    "sg:phone":"+41 19303371",
    "sg:postcode":"8044",
    "sg:province":"Z\u00fcrich",
    "wof:name":"Tc Wetzikon",
    "wof:placetype":"venue"
},
  "geometry": {"coordinates":[8.8084897995,47.3316688538],"type":"Point"}
}