{
  "type": "Feature",
  "properties": {
    "iso:country":"CH",
    "sg:address":"Via Buonamano 22 6612 Ascona. Postfach",
    "sg:city":"Ascona",
    "sg:orig_category":"Mit dem Versicherungsgewerbe verbundene T\u00e4tigkeiten",
    "sg:postcode":"6612",
    "sg:province":"Ticino",
    "wof:name":"Revaca Consulting Sarl, Succursale D'ascona",
    "wof:placetype":"venue"
},
  "geometry": {"coordinates":[8.773979187,46.1571617126],"type":"Point"}
}