{
  "type": "Feature",
  "properties": {
    "iso:country":"CH",
    "sg:address":"Rathausgasse 30",
    "sg:city":"Bern",
    "sg:classifiers":[
        {
            "category":"Personal",
            "subcategory":"Piercing",
            "type":"Services"
        }
    ],
    "sg:phone":"+41 31 311 84 01",
    "sg:postcode":"3011",
    "sg:province":"Bern",
    "sg:tags":[
        "tattoo"
    ],
    "wof:name":"Tattoo-piercing Studio Mr.t",
    "wof:placetype":"venue"
},
  "geometry": {"coordinates":[7.4501600266,46.9486312866],"type":"Point"}
}