{
  "type": "Feature",
  "properties": {
    "addr:full":"7050 Arosa. Postfach 82 Arosa Graubunden 7050",
    "addr:housenumber":"7050;82",
    "addr:postcode":"7050",
    "addr:street":"Arosa. Postfach;Graubunden",
    "iso:country":"CH",
    "sg:address":"7050 Arosa. Postfach 82",
    "sg:city":"Arosa",
    "sg:orig_category":"Blumen U Zierpflanzenbau Detailhandel mit Blumen U Pflanzen",
    "sg:postcode":"7050",
    "sg:province":"Graubunden",
    "wof:name":"Jean-louis Crot Schyrr Fleurs",
    "wof:placetype":"venue"
},
  "geometry": {"coordinates":[6.857837,46.458206],"type":"Point"}
}