{
  "type": "Feature",
  "properties": {
    "iso:country":"CH",
    "sg:address":"Buchenweg 2 8136 Gattikon. Postfach",
    "sg:city":"Gattikon",
    "sg:orig_category":"Verwaltung von Immobilien",
    "sg:phone":"+41 17203253",
    "sg:postcode":"8136",
    "sg:province":"Z\u00fcrich",
    "wof:name":"Hansruedi Meyer Immobilienverwaltung",
    "wof:placetype":"venue"
},
  "geometry": {"coordinates":[8.5492086411,47.2823143005],"type":"Point"}
}