{
  "type": "Feature",
  "properties": {
    "addr:full":"Bahnhofstrasse 17 Ebikon Luzern 6030",
    "addr:housenumber":"17",
    "addr:postcode":"6030",
    "addr:street":"Bahnhofstrasse",
    "iso:country":"CH",
    "sg:address":"Bahnhofstrasse 17",
    "sg:city":"Ebikon",
    "sg:orig_category":"Berufsorganisationen",
    "sg:phone":"+41 41 440 23 63",
    "sg:postcode":"6030",
    "sg:province":"Luzern",
    "wof:name":"Genossenschaft Zagg",
    "wof:placetype":"venue"
},
  "geometry": {"coordinates":[8.345575,47.085079],"type":"Point"}
}