{
  "type": "Feature",
  "properties": {
    "iso:country":"CH",
    "sg:address":"Industriestrasse",
    "sg:city":"Berom\u00fcnster",
    "sg:orig_category":"Grosshandel mit pharmazeutischen Erzeugnissen, medizinischen U orthop\u00e4dischen Artikeln",
    "sg:phone":"+41 41 930 07 07",
    "sg:postcode":"6215",
    "sg:province":"Luzern",
    "wof:name":"Scherer Grossk\u00fcchen",
    "wof:placetype":"venue"
},
  "geometry": {"coordinates":[8.2038154602,47.2032432556],"type":"Point"}
}