{
  "type": "Feature",
  "properties": {
    "iso:country":"CH",
    "sg:address":"Sagenrainstrasse 20b",
    "sg:city":"Fehraltorf",
    "sg:orig_category":"Unclassifiable Establishments",
    "sg:postcode":"8320",
    "sg:province":"Z\u00fcrich",
    "wof:name":"Ruprecht Consulting Gmbh",
    "wof:placetype":"venue"
},
  "geometry": {"coordinates":[8.7507534027,47.3900032043],"type":"Point"}
}