{
  "type": "Feature",
  "properties": {
    "iso:country":"CH",
    "sg:address":"1427",
    "sg:city":"Bonvillars",
    "sg:orig_category":"Herstellung von sonstigen landwirtschaftlichen Maschinen",
    "sg:phone":"+41 24 436 14 77",
    "sg:postcode":"1427",
    "sg:province":"Vaud",
    "wof:name":"H\u00e4nggeli Georges.",
    "wof:placetype":"venue"
},
  "geometry": {"coordinates":[6.679019928,46.8333282471],"type":"Point"}
}