{
  "type": "Feature",
  "properties": {
    "iso:country":"CH",
    "sg:address":"Rosenweg 1 6033 Buchrain. Postfach 149",
    "sg:city":"Buchrain",
    "sg:orig_category":"Kaminfeger",
    "sg:phone":"+41 61 711 38 30",
    "sg:postcode":"6033",
    "sg:province":"Luzern",
    "wof:name":"Martin Von Rohr Kaminfegergesch\u00e4ft",
    "wof:placetype":"venue"
},
  "geometry": {"coordinates":[7.6034832001,47.5059280396],"type":"Point"}
}