{
  "type": "Feature",
  "properties": {
    "iso:country":"CH",
    "sg:address":"Ringstrasse 15",
    "sg:city":"Goldau",
    "sg:orig_category":"Maurerarbeiten Sonstiger spezialisierter Hoch U Tiefbau",
    "sg:phone":"+41 41 855 19 38",
    "sg:postcode":"6410",
    "sg:province":"Schwyz",
    "wof:name":"Reichlin Maurerunternehmung Gmbh",
    "wof:placetype":"venue"
},
  "geometry": {"coordinates":[8.5470457077,47.0523834229],"type":"Point"}
}