{
  "type": "Feature",
  "properties": {
    "iso:country":"CH",
    "sg:address":"Ch. Du Vieux-canal 44 Ch\u00e2teauneuf 1950 Sion. Postfach",
    "sg:city":"Conthey",
    "sg:orig_category":"Handels-H\u00e4user U Gesellschaften",
    "sg:phone":"+41 81 416 35 04",
    "sg:postcode":"1964",
    "sg:province":"Valais",
    "wof:name":"B\u00f6rtji Ag Davos",
    "wof:placetype":"venue"
},
  "geometry": {"coordinates":[9.8209161758,46.7938766479],"type":"Point"}
}