{
  "type": "Feature",
  "properties": {
    "iso:country":"CH",
    "sg:address":"Z\u00e4hringerstrasse 42",
    "sg:city":"Bern",
    "sg:orig_category":"Fachdetailhandel in Verkaufsr\u00e4umen",
    "sg:phone":"+41 31 301 47 01",
    "sg:postcode":"3012",
    "sg:province":"Bern",
    "wof:name":"Gerber Rosmarie Zur Sattelkammer",
    "wof:placetype":"venue"
},
  "geometry": {"coordinates":[7.4333639145,46.9559402466],"type":"Point"}
}