{
  "type": "Feature",
  "properties": {
    "iso:country":"CH",
    "sg:address":"Chrummatt 42 3184 W\u00fcnnewil. Postfach",
    "sg:city":"Flamatt",
    "sg:orig_category":"Druck ohne Zeitungsdruck",
    "sg:phone":"+41 71 931 10 11",
    "sg:postcode":"3175",
    "sg:province":"Fribourg",
    "wof:name":"Kalberer E. Ag, Bazenheid",
    "wof:placetype":"venue"
},
  "geometry": {"coordinates":[9.0266399384,47.4199295044],"type":"Point"}
}