{
  "type": "Feature",
  "properties": {
    "iso:country":"CH",
    "sg:address":"Rue De L'ile Falcon",
    "sg:city":"Sierre",
    "sg:orig_category":"Herstellung von Maschinen f\u00fcr die Nahrungsmittel, Getr\u00e4nkeherstellung U die Tabakverarbeitung",
    "sg:postcode":"3960",
    "sg:province":"Valais",
    "wof:name":"Antartica Sa",
    "wof:placetype":"venue"
},
  "geometry": {"coordinates":[7.550339222,46.2863006592],"type":"Point"}
}