{
  "type": "Feature",
  "properties": {
    "addr:full":"Ried 9 Schmitten Fribourg 3185",
    "addr:housenumber":"9",
    "addr:postcode":"3185",
    "addr:street":"Ried",
    "iso:country":"CH",
    "sg:address":"Ried 9",
    "sg:city":"Schmitten",
    "sg:classifiers":[
        {
            "category":"Building & Trades",
            "subcategory":"Construction",
            "type":"Services"
        }
    ],
    "sg:phone":"+41 26 496 11 77",
    "sg:postcode":"3185",
    "sg:province":"Fribourg",
    "sg:tags":[
        "carpenter's",
        "work",
        "supraregional"
    ],
    "wof:name":"Vonlanthen Holzbau Ag",
    "wof:placetype":"venue"
},
  "geometry": {"coordinates":[7.22593,46.840767],"type":"Point"}
}