{
  "type": "Feature",
  "properties": {
    "iso:country":"CH",
    "sg:address":"6656",
    "sg:city":"Golino",
    "sg:orig_category":"Unclassifiable Establishments",
    "sg:postcode":"6656",
    "sg:province":"Ticino",
    "wof:name":"Al Ponte Vecchio Sa",
    "wof:placetype":"venue"
},
  "geometry": {"coordinates":[8.7133903503,46.1785011292],"type":"Point"}
}