{
  "type": "Feature",
  "properties": {
    "iso:country":"CH",
    "sg:address":"Sophiestrasse 4b",
    "sg:city":"Ostermundigen",
    "sg:orig_category":"Arztpraxen",
    "sg:phone":"+41 31 931 44 31",
    "sg:postcode":"3072",
    "sg:province":"Bern",
    "wof:name":"Dr.med.lorenz Fischer Arzt F.allgemeine Medizin Fmh",
    "wof:placetype":"venue"
},
  "geometry": {"coordinates":[7.486716,46.958035],"type":"Point"}
}