{
  "type": "Feature",
  "properties": {
    "addr:full":"Leimbachstrasse 56 Z\u00fcrich Z\u00fcrich 8041",
    "addr:housenumber":"56",
    "addr:postcode":"8041",
    "addr:street":"Leimbachstrasse",
    "iso:country":"CH",
    "sg:address":"Leimbachstrasse 56",
    "sg:city":"Z\u00fcrich",
    "sg:orig_category":"Detailhandel mit Damenbekleidung",
    "sg:phone":"+41 14830220",
    "sg:postcode":"8041",
    "sg:province":"Z\u00fcrich",
    "wof:name":"Gromod Damenmode Verena Burkhard Damenmode-verkauf",
    "wof:placetype":"venue"
},
  "geometry": {"coordinates":[8.518382,47.333225],"type":"Point"}
}