{
  "type": "Feature",
  "properties": {
    "iso:country":"CH",
    "sg:address":"Schaanerstrasse 40",
    "sg:city":"Vaduz",
    "sg:orig_category":"Herstellung von Werkzeugen",
    "sg:phone":"+423 237 54 54",
    "sg:postcode":"9490",
    "wof:name":"Pav Pr\u00e4zisions-apparatebau Vaduz Ag",
    "wof:placetype":"venue"
},
  "geometry": {"coordinates":[9.5071992874,47.1505508423],"type":"Point"}
}