{
  "type": "Feature",
  "properties": {
    "iso:country":"CH",
    "sg:address":"Neustadtgasse 18",
    "sg:city":"Winterthur",
    "sg:orig_category":"Druckweiterverarbeitung",
    "sg:phone":"+41 52 212 05 76",
    "sg:postcode":"8400",
    "sg:province":"Z\u00fcrich",
    "wof:name":"Susette Largiad\u00e9r Buchbinderei",
    "wof:placetype":"venue"
},
  "geometry": {"coordinates":[8.7326984406,47.499042511],"type":"Point"}
}