{
  "type": "Feature",
  "properties": {
    "iso:country":"CH",
    "sg:address":"Habsburgstrasse 33 8037 Z\u00fcrich. Postfach",
    "sg:city":"Z\u00fcrich",
    "sg:orig_category":"Non-Classified Establishments",
    "sg:postcode":"8037",
    "sg:province":"Z\u00fcrich",
    "wof:name":"Eyelight Spiegelberg",
    "wof:placetype":"venue"
},
  "geometry": {"coordinates":[9.3970746994,47.3870391846],"type":"Point"}
}