{
  "type": "Feature",
  "properties": {
    "iso:country":"CH",
    "sg:address":"Dorfgasse 76",
    "sg:city":"Niederdorf",
    "sg:orig_category":"Vermittlung von Immobilien Verwaltung von Immobilien",
    "sg:phone":"+41 61 951 23 74",
    "sg:postcode":"4435",
    "sg:province":"Basel-Landschaft",
    "wof:name":"Arga Verwaltungsgesellschaft Mbh",
    "wof:placetype":"venue"
},
  "geometry": {"coordinates":[7.7529201508,47.4066734314],"type":"Point"}
}