{
  "type": "Feature",
  "properties": {
    "addr:full":"Chissiez Chemin De 26 1006 Lausanne. Postfach Lausanne Vaud 1003",
    "addr:housenumber":"26",
    "addr:postcode":"1006;postfach;1003",
    "addr:street":"Chemin De",
    "iso:country":"CH",
    "sg:address":"Chissiez Chemin De 26 1006 Lausanne. Postfach",
    "sg:city":"Lausanne",
    "sg:orig_category":"Betrieb von Taxis",
    "sg:postcode":"1003",
    "sg:province":"Vaud",
    "wof:name":"Taxi De Poche, Frank Paillard",
    "wof:placetype":"venue"
},
  "geometry": {"coordinates":[6.632335,46.519596],"type":"Point"}
}