{
  "type": "Feature",
  "properties": {
    "iso:country":"CH",
    "sg:address":"1312",
    "sg:city":"Ecl\u00e9pens",
    "sg:orig_category":"Fernw\u00e4rmeversorgung",
    "sg:phone":"+41 21 866 91 11",
    "sg:postcode":"1312",
    "sg:province":"Vaud",
    "wof:name":"Cadcime Sa",
    "wof:placetype":"venue"
},
  "geometry": {"coordinates":[6.544479847,46.6521987915],"type":"Point"}
}