{
  "type": "Feature",
  "properties": {
    "iso:country":"CH",
    "sg:address":"Feldstrasse 2",
    "sg:city":"Sarnen",
    "sg:orig_category":"Grosshandel mit elektrischen Haushaltsger\u00e4ten Herstellung von elektrischen Lampen U Leuchten",
    "sg:phone":"+41 21 323 14 34",
    "sg:postcode":"6060",
    "sg:province":"Obwalden",
    "wof:name":"Orlamp Sa",
    "wof:placetype":"venue"
},
  "geometry": {"coordinates":[6.6406641006,46.5212059021],"type":"Point"}
}