{
  "type": "Feature",
  "properties": {
    "iso:country":"CH",
    "sg:address":"G\u00e4ssliackerweg 2",
    "sg:city":"Schafisheim",
    "sg:orig_category":"Unternehmensberatung",
    "sg:phone":"+41 62 892 94 80",
    "sg:postcode":"5503",
    "sg:province":"Aargau",
    "wof:name":"Niklaus Sch\u00e4r, Wirtschafts Und Sozialgestaltung",
    "wof:placetype":"venue"
},
  "geometry": {"coordinates":[8.1427593231,47.3769226074],"type":"Point"}
}