{
  "type": "Feature",
  "properties": {
    "iso:country":"CH",
    "sg:address":"Wolfeggstrasse 12",
    "sg:city":"Widen",
    "sg:orig_category":"Gesundheitswesen",
    "sg:postcode":"8967",
    "sg:province":"Aargau",
    "wof:name":"Steffen Dr. Telemedicin Gmbh",
    "wof:placetype":"venue"
},
  "geometry": {"coordinates":[7.4870638847,46.9323997498],"type":"Point"}
}