{
  "type": "Feature",
  "properties": {
    "addr:full":"M\u00fchleschwendi Unter\u00e4geri Zug 6314",
    "addr:postcode":"6314",
    "addr:street":"Zug",
    "iso:country":"CH",
    "sg:address":"M\u00fchleschwendi",
    "sg:city":"Unter\u00e4geri",
    "sg:orig_category":"Detailhandel mit Computern U Software Grosshandel mit Software",
    "sg:phone":"+41 41 750 66 84",
    "sg:postcode":"6314",
    "sg:province":"Zug",
    "wof:name":"Unique Software Ltd",
    "wof:placetype":"venue"
},
  "geometry": {"coordinates":[8.583835,47.137405],"type":"Point"}
}