{
  "type": "Feature",
  "properties": {
    "iso:country":"CH",
    "sg:address":"Via Degli Albricci 6 6830 Chiasso. Postfach",
    "sg:city":"Chiasso",
    "sg:orig_category":"Fachdetailhandel mit pharmazeutischen Produkten",
    "sg:postcode":"6830",
    "sg:province":"Ticino",
    "wof:name":"Farmacom Sa",
    "wof:placetype":"venue"
},
  "geometry": {"coordinates":[9.034113884,45.834197998],"type":"Point"}
}