{
  "type": "Feature",
  "properties": {
    "iso:country":"CH",
    "sg:address":"Riva Antonio Caccia 1e 6900 Lugano. Postfach",
    "sg:city":"Lugano",
    "sg:orig_category":"W\u00e4scherei U chemische Reinigung",
    "sg:postcode":"6900",
    "sg:province":"Ticino",
    "wof:name":"Lavanderia Cometa Sagl",
    "wof:placetype":"venue"
},
  "geometry": {"coordinates":[8.9475860596,45.9980354309],"type":"Point"}
}