{
  "type": "Feature",
  "properties": {
    "addr:full":"Gufer 295 Triesenberg 9497",
    "addr:housenumber":"295",
    "addr:postcode":"9497",
    "addr:street":"Gufer",
    "iso:country":"CH",
    "sg:address":"Gufer 295",
    "sg:city":"Triesenberg",
    "sg:orig_category":"Bauschreinerei Herstellung von M\u00f6beln verschiedener Art",
    "sg:phone":"+423 262 19 27",
    "sg:postcode":"9497",
    "wof:name":"Eugen Sch\u00e4dler Mech.bau-& M\u00f6belschreinerei",
    "wof:placetype":"venue"
},
  "geometry": {"coordinates":[9.546258,47.114361],"type":"Point"}
}