{
  "type": "Feature",
  "properties": {
    "iso:country":"CH",
    "sg:address":"Landenbergstrasse 8c 6020 Emmenbr\u00fccke. Postfach",
    "sg:city":"Emmenbr\u00fccke",
    "sg:orig_category":"Kauf U Verkauf von Immobilien auf eigene Rechnung",
    "sg:postcode":"6020",
    "sg:province":"Luzern",
    "wof:name":"Bl\u00e4ttler Immobilien Und Handels Gmbh",
    "wof:placetype":"venue"
},
  "geometry": {"coordinates":[8.2732820511,47.0788269043],"type":"Point"}
}