{
  "type": "Feature",
  "properties": {
    "iso:country":"CH",
    "sg:address":"Vorstadt 44",
    "sg:city":"Schaffhausen",
    "sg:orig_category":"Fachdetailhandel in Verkaufsr\u00e4umen Sonstiger Detailhandel mit Metallwaren, Anstrichmitteln, Glasware",
    "sg:phone":"+41 52 624 57 57",
    "sg:postcode":"8200",
    "sg:province":"Schaffhausen",
    "wof:name":"Uschis Bastelstube Ursula Massatsch & Co",
    "wof:placetype":"venue"
},
  "geometry": {"coordinates":[8.6348867416,47.6987800598],"type":"Point"}
}