{
  "type": "Feature",
  "properties": {
    "iso:country":"CH",
    "sg:address":"Route D'arbaz 11",
    "sg:city":"Grimisuat",
    "sg:classifiers":[
        {
            "category":"Home & Garden",
            "subcategory":"Hardware",
            "type":"Retail Goods"
        }
    ],
    "sg:phone":"+41 32 925 35 15",
    "sg:postcode":"1971",
    "sg:province":"Valais",
    "sg:tags":[
        "compressor",
        "air"
    ],
    "wof:name":"Roxer S.a.",
    "wof:placetype":"venue"
},
  "geometry": {"coordinates":[6.800591,47.08252],"type":"Point"}
}