{
  "type": "Feature",
  "properties": {
    "iso:country":"CH",
    "sg:address":"Sonnenbergstrasse 9 8000 Z\u00fcrich. Postfach 8032 Z\u00fcrich",
    "sg:city":"Zust",
    "sg:orig_category":"Unternehmensberatung",
    "sg:postcode":"32",
    "wof:name":"Management-diagnostics Jakob Dr. Phil. A. & Hohmann Jakob F.",
    "wof:placetype":"venue"
},
  "geometry": {"coordinates":[8.5666399002,47.3654975891],"type":"Point"}
}