{
  "type": "Feature",
  "properties": {
    "iso:country":"CH",
    "sg:address":"Aarestrasse 13 3627 Heimberg. Postfach 318",
    "sg:city":"Heimberg",
    "sg:orig_category":"Herstellung von Ger\u00e4ten der Elektrizit\u00e4tserzeugung, -verteilung u.\u00e4. -Herstellung von sonstigen elek",
    "sg:phone":"+41 33 437 87 37",
    "sg:postcode":"3627",
    "sg:province":"Bern",
    "wof:name":"Argus Electronic Ag",
    "wof:placetype":"venue"
},
  "geometry": {"coordinates":[7.6076250076,46.7832717896],"type":"Point"}
}