{
  "type": "Feature",
  "properties": {
    "addr:full":"Oberdorfstrasse 11 Reiden Luzern 6260",
    "addr:housenumber":"11",
    "addr:postcode":"6260",
    "addr:street":"Oberdorfstrasse",
    "iso:country":"CH",
    "sg:address":"Oberdorfstrasse 11",
    "sg:city":"Reiden",
    "sg:orig_category":"Architektur U Ingenieurb\u00fcros G\u00fcterbef\u00f6rderung im Strassenverkehr",
    "sg:phone":"+41 62 758 30 77",
    "sg:postcode":"6260",
    "sg:province":"Luzern",
    "wof:name":"Di Giacomo Reiden Umz\u00fcge & Einrichtungen",
    "wof:placetype":"venue"
},
  "geometry": {"coordinates":[7.97426,47.247223],"type":"Point"}
}