{
  "type": "Feature",
  "properties": {
    "iso:country":"CH",
    "sg:address":"Grossackerstrasse 54",
    "sg:city":"Bern",
    "sg:orig_category":"Bauschreinerei Innenausbau",
    "sg:phone":"+41 71 944 15 40",
    "sg:postcode":"3018",
    "sg:province":"Bern",
    "wof:name":"Ehret Paul",
    "wof:placetype":"venue"
},
  "geometry": {"coordinates":[9.113134,47.474518],"type":"Point"}
}