{
  "type": "Feature",
  "properties": {
    "iso:country":"CH",
    "sg:address":"Rue De Monthoux 17",
    "sg:city":"Gen\u00e8ve",
    "sg:classifiers":[
        {
            "category":"Restaurant",
            "type":"Food & Drink"
        }
    ],
    "sg:phone":"+41 22 738 80 55",
    "sg:postcode":"1201",
    "sg:province":"Gen\u00e8ve",
    "wof:name":"Caf\u00e9-restaurant Sam-lor Thai",
    "wof:placetype":"venue"
},
  "geometry": {"coordinates":[6.1488389969,46.2102851868],"type":"Point"}
}