{
  "type": "Feature",
  "properties": {
    "iso:country":"CH",
    "sg:address":"Chesa Cumuenela",
    "sg:city":"Pontresina",
    "sg:orig_category":"Sonstige mit Sport verbundene T\u00e4tigkeiten",
    "sg:phone":"+41 81 850 55 50",
    "sg:postcode":"7504",
    "sg:province":"Graubunden",
    "wof:name":"Engadin Skimarathon",
    "wof:placetype":"venue"
},
  "geometry": {"coordinates":[9.9048089981,46.4893798828],"type":"Point"}
}