{
  "type": "Feature",
  "properties": {
    "iso:country":"CH",
    "sg:address":"Neumatt",
    "sg:city":"Oppligen",
    "sg:classifiers":[
        {
            "category":"Insurance",
            "subcategory":"Insurance Agent",
            "type":"Services"
        }
    ],
    "sg:phone":"+41 33 227 86 11",
    "sg:postcode":"3629",
    "sg:province":"Bern",
    "sg:tags":[
        "versicherungsagenturen",
        "-broker"
    ],
    "wof:name":"Helvetia Patria Versicherungen Agentur",
    "wof:placetype":"venue"
},
  "geometry": {"coordinates":[7.5950632095,46.8178825378],"type":"Point"}
}