{
  "type": "Feature",
  "properties": {
    "iso:country":"CH",
    "sg:address":"Route De Lausanne 33",
    "sg:city":"Mont-sur-lausanne",
    "sg:orig_category":"Wirtschaftspr\u00fcfung, Steuerberatung U Treuhand",
    "sg:phone":"+41 21 653 41 21",
    "sg:postcode":"1052",
    "sg:province":"Vaud",
    "wof:name":"Sofichima Sa",
    "wof:placetype":"venue"
},
  "geometry": {"coordinates":[6.6347618103,46.5541572571],"type":"Point"}
}