{
  "type": "Feature",
  "properties": {
    "iso:country":"CH",
    "sg:address":"Riedtalstrasse 7a",
    "sg:city":"Zofingen",
    "sg:orig_category":"Herstellung von Fenstern U T\u00fcren aus Holz Herstellung von Konstruktionsteilen, Fertigbauteilen U Aus",
    "sg:phone":"+41 71 766 22 33",
    "sg:postcode":"4800",
    "sg:province":"Aargau",
    "wof:name":"Alfena Ag",
    "wof:placetype":"venue"
},
  "geometry": {"coordinates":[9.5377502441,47.2937507629],"type":"Point"}
}