{
  "type": "Feature",
  "properties": {
    "iso:country":"CH",
    "sg:address":"9314",
    "sg:city":"Steinebrunn",
    "sg:orig_category":"Primarschulen",
    "sg:phone":"+41 71 477 22 92",
    "sg:postcode":"9314",
    "sg:province":"Thurgau",
    "wof:name":"Primarschule",
    "wof:placetype":"venue"
},
  "geometry": {"coordinates":[9.3428497314,47.5318717957],"type":"Point"}
}