{
  "type": "Feature",
  "properties": {
    "addr:full":"Stadthausstrasse 12 Winterthur Z\u00fcrich 8400",
    "addr:housenumber":"12",
    "addr:postcode":"8400",
    "addr:street":"Stadthausstrasse",
    "iso:country":"CH",
    "sg:address":"Stadthausstrasse 12",
    "sg:city":"Winterthur",
    "sg:orig_category":"Arztpraxen",
    "sg:phone":"+41 52 212 14 46",
    "sg:postcode":"8400",
    "sg:province":"Z\u00fcrich",
    "wof:name":"Dr.med. Gerhard Weber Spezialarzt Fmh",
    "wof:placetype":"venue"
},
  "geometry": {"coordinates":[8.726916,47.500103],"type":"Point"}
}