{
  "type": "Feature",
  "properties": {
    "iso:country":"CH",
    "sg:address":"R\u00fcfiwisweg 12 7203 Trimmis. Postfach",
    "sg:city":"Trimmis",
    "sg:orig_category":"Herstellung von konfektionierten Textilwaren ohne Bekleidung",
    "sg:postcode":"7203",
    "sg:province":"Graubunden",
    "wof:name":"Sleep Grischa Gmbh Waren, Bes. Bettwaren; Handel Usw",
    "wof:placetype":"venue"
},
  "geometry": {"coordinates":[9.5595769882,46.9004402161],"type":"Point"}
}