{
  "type": "Feature",
  "properties": {
    "iso:country":"CH",
    "sg:address":"Hauptstrasse",
    "sg:city":"K\u00fcblis",
    "sg:orig_category":"Physiotherapie",
    "sg:phone":"+41 81 332 44 22",
    "sg:postcode":"7240",
    "sg:province":"Graubunden",
    "wof:name":"Physiotherapie Unterm Rappen",
    "wof:placetype":"venue"
},
  "geometry": {"coordinates":[9.7697753906,46.9135971069],"type":"Point"}
}