{
  "type": "Feature",
  "properties": {
    "iso:country":"CH",
    "sg:address":"Dorfstrasse 16",
    "sg:city":"Baar",
    "sg:classifiers":[
        {
            "category":"Professional",
            "subcategory":"Computer Services",
            "type":"Services"
        }
    ],
    "sg:phone":"+41 41 767 46 74",
    "sg:postcode":"6340",
    "sg:province":"Zug",
    "sg:tags":[
        "informatics",
        "consulting"
    ],
    "wof:name":"Sapienza Gmbh",
    "wof:placetype":"venue"
},
  "geometry": {"coordinates":[8.5248403549,47.1942100525],"type":"Point"}
}