{
  "type": "Feature",
  "properties": {
    "addr:full":"Bettenh\u00f6lzliweg 10 Langenthal Bern 4900",
    "addr:housenumber":"10",
    "addr:postcode":"4900",
    "addr:street":"Bettenhoelzliweg;Bern",
    "iso:country":"CH",
    "sg:address":"Bettenh\u00f6lzliweg 10",
    "sg:city":"Langenthal",
    "sg:orig_category":"Bezirks, Sekundar, Realschulen, Oberstufe der Primarschulen Primarschulen",
    "sg:phone":"+41 81 911 12 69",
    "sg:postcode":"4900",
    "sg:province":"Bern",
    "wof:name":"Sch\u00fclerinternat Der Stadt Z\u00fcrich",
    "wof:placetype":"venue"
},
  "geometry": {"coordinates":[9.288318,46.826241],"type":"Point"}
}