{
  "type": "Feature",
  "properties": {
    "iso:country":"CH",
    "sg:address":"Austrasse 40",
    "sg:city":"Chur",
    "sg:orig_category":"Sportvereine Ballsport Handball",
    "sg:phone":"+41 76 388 73 95",
    "sg:postcode":"7000",
    "sg:province":"Graubunden",
    "wof:name":"Hc Chur",
    "wof:placetype":"venue"
},
  "geometry": {"coordinates":[9.5163908005,46.8631820679],"type":"Point"}
}