{
  "type": "Feature",
  "properties": {
    "iso:country":"CH",
    "sg:address":"Unterm\u00fcli 1",
    "sg:city":"Zug",
    "sg:orig_category":"Architektur U Ingenieurb\u00fcros Architekturb\u00fcros",
    "sg:phone":"+41 41 760 00 77",
    "sg:postcode":"6300",
    "sg:province":"Zug",
    "wof:name":"Joseph Smolenicky Architekturb\u00fcro",
    "wof:placetype":"venue"
},
  "geometry": {"coordinates":[8.517419,47.179966],"type":"Point"}
}