{
  "type": "Feature",
  "properties": {
    "iso:country":"CH",
    "sg:address":"Baarerstrasse 63",
    "sg:city":"Zug",
    "sg:orig_category":"Herstellung von gewirktem U gestricktem Stoff Stickerei",
    "sg:phone":"+41 81 833 40 27",
    "sg:postcode":"6300",
    "sg:province":"Zug",
    "wof:name":"Ebneter & Biel Ag",
    "wof:placetype":"venue"
},
  "geometry": {"coordinates":[9.8390455246,46.4986000061],"type":"Point"}
}