{
  "type": "Feature",
  "properties": {
    "iso:country":"CH",
    "sg:address":"Chemin Du Ch\u00e2teau-bloc 15 1219 Le Lignon Case Postale 856",
    "sg:city":"Grand-lancy",
    "sg:orig_category":"Detailhandel mit Parf\u00fcmerieartikeln U K\u00f6rperpflegemitteln",
    "sg:phone":"+41 22 884 00 00",
    "sg:postcode":"1212",
    "sg:province":"Gen\u00e8ve",
    "wof:name":"Parlux Sa",
    "wof:placetype":"venue"
},
  "geometry": {"coordinates":[6.1013131142,46.2066268921],"type":"Point"}
}