{
  "type": "Feature",
  "properties": {
    "iso:country":"CH",
    "sg:address":"Weinfelderstrasse 1",
    "sg:city":"M\u00fcnchwilen",
    "sg:orig_category":"Bathrooms, Exclusive",
    "sg:phone":"+41 71 960 06 58",
    "sg:postcode":"9542",
    "sg:province":"Thurgau",
    "wof:name":"Natura Design Ag",
    "wof:placetype":"venue"
},
  "geometry": {"coordinates":[8.999461,47.476913],"type":"Point"}
}