{
  "type": "Feature",
  "properties": {
    "iso:country":"CH",
    "sg:address":"Feldwiesstrasse 21",
    "sg:city":"Oberhelfenschwil",
    "sg:orig_category":"Herstellung von Werkzeugen",
    "sg:phone":"+41 55 444 26 28",
    "sg:postcode":"9621",
    "sg:province":"St. Gallen",
    "wof:name":"Technoform Hunziker Gmbh Werkzeug-formenbau. Spezial-werkzeuge F\u00fcr Die Kunststoffindustrie; Herstellung Usw",
    "wof:placetype":"venue"
},
  "geometry": {"coordinates":[8.9527902603,47.1751785278],"type":"Point"}
}