{
  "type": "Feature",
  "properties": {
    "iso:country":"CH",
    "sg:address":"Juravorstadt 31",
    "sg:city":"Biel/bienne",
    "sg:orig_category":"Detailhandel mit Sportartikeln Reiseb\u00fcros U Reiseveranstalter",
    "sg:phone":"+41 32 322 32 20",
    "sg:postcode":"2502",
    "sg:province":"Bern",
    "wof:name":"Marlin Sport Fishing & Adventure Weisskopf",
    "wof:placetype":"venue"
},
  "geometry": {"coordinates":[7.2483410835,47.1437911987],"type":"Point"}
}