{
  "type": "Feature",
  "properties": {
    "iso:country":"CH",
    "sg:address":"Le Bourg Village",
    "sg:city":"Montana",
    "sg:orig_category":"Fussreflexzonenmassage",
    "sg:phone":"+41 27 481 10 76",
    "sg:postcode":"3962",
    "wof:name":"Maryline Bonvin Institut Evasion",
    "wof:placetype":"venue"
},
  "geometry": {"coordinates":[11.9115991592,46.6565704346],"type":"Point"}
}