{
  "type": "Feature",
  "properties": {
    "iso:country":"CH",
    "sg:address":"Talstrasse 84",
    "sg:city":"Arlesheim",
    "sg:orig_category":"Unclassifiable Establishments",
    "sg:postcode":"4144",
    "sg:province":"Basel-Landschaft",
    "wof:name":"Make It Happen Gmbh",
    "wof:placetype":"venue"
},
  "geometry": {"coordinates":[7.6091899872,47.4987258911],"type":"Point"}
}