{
  "type": "Feature",
  "properties": {
    "iso:country":"CH",
    "sg:address":"M\u00e4rtplatz 1",
    "sg:city":"Effretikon",
    "sg:classifiers":[
        {
            "category":"Banks & Credit Unions",
            "subcategory":"Bank",
            "type":"Services"
        }
    ],
    "sg:phone":"+41 4152323021",
    "sg:postcode":"8307",
    "sg:province":"Z\u00fcrich",
    "wof:name":"Credit Suisse",
    "wof:placetype":"venue"
},
  "geometry": {"coordinates":[8.686242,47.428131],"type":"Point"}
}