{
  "type": "Feature",
  "properties": {
    "iso:country":"CH",
    "sg:address":"Sch\u00fctzenwisstrasse 4 8124 Maur. Postfach",
    "sg:city":"Br\u00fcttisellen",
    "sg:orig_category":"Sonstiger Grosshandel",
    "sg:phone":"+41 18337684",
    "sg:postcode":"8306",
    "sg:province":"Z\u00fcrich",
    "wof:name":"Ggp Haustech Gmbh",
    "wof:placetype":"venue"
},
  "geometry": {"coordinates":[8.6591844559,47.3432235718],"type":"Point"}
}