{
  "type": "Feature",
  "properties": {
    "iso:country":"CH",
    "sg:address":"Gestadeckplatz 8",
    "sg:city":"Liestal",
    "sg:orig_category":"Arbeitnehmerverb\u00e4nde",
    "sg:phone":"+41 61 921 25 36",
    "sg:postcode":"4410",
    "sg:province":"Basel-Landschaft",
    "wof:name":"Kaufm. Verein Baselland",
    "wof:placetype":"venue"
},
  "geometry": {"coordinates":[7.737526,47.486008],"type":"Point"}
}