{
  "type": "Feature",
  "properties": {
    "iso:country":"CH",
    "sg:address":"Solothurnerstrasse 8",
    "sg:city":"H\u00e4gendorf",
    "sg:orig_category":"Elektroinstallation",
    "sg:phone":"+41 62 216 20 20",
    "sg:postcode":"4614",
    "sg:province":"Solothurn",
    "wof:name":"Haefeli Elektro",
    "wof:placetype":"venue"
},
  "geometry": {"coordinates":[7.8421940804,47.3327674866],"type":"Point"}
}