{
  "type": "Feature",
  "properties": {
    "iso:country":"CH",
    "sg:address":"B\u00fcntgasse 6",
    "sg:city":"N\u00e4fels",
    "sg:orig_category":"Gesundheitswesen",
    "sg:phone":"+41 55 612 38 23",
    "sg:postcode":"8752",
    "sg:province":"Glarus",
    "wof:name":"Giger Massagen",
    "wof:placetype":"venue"
},
  "geometry": {"coordinates":[9.0607337952,47.0979347229],"type":"Point"}
}