{
  "type": "Feature",
  "properties": {
    "iso:country":"CH",
    "sg:address":"Route De Florissant 47bis",
    "sg:city":"Gen\u00e8ve",
    "sg:orig_category":"Kosmetikinstitute",
    "sg:phone":"+41 55 440 40 09",
    "sg:postcode":"1206",
    "sg:province":"Gen\u00e8ve",
    "wof:name":"Cosmedic Vazsonyi Sandra",
    "wof:placetype":"venue"
},
  "geometry": {"coordinates":[8.8872652054,47.2036247253],"type":"Point"}
}