{
  "type": "Feature",
  "properties": {
    "iso:country":"CH",
    "sg:address":"Schwendistrasse 968",
    "sg:city":"Unterwasser",
    "sg:orig_category":"Non-Classified Establishments",
    "sg:postcode":"9657",
    "sg:province":"St. Gallen",
    "wof:name":"N\u00e4f - Consulting U. Risikenmanagement",
    "wof:placetype":"venue"
},
  "geometry": {"coordinates":[9.3127603531,47.1964149475],"type":"Point"}
}