{
  "type": "Feature",
  "properties": {
    "iso:country":"CH",
    "sg:address":"9113 Degersheim. Postfach 23",
    "sg:city":"Degersheim",
    "sg:orig_category":"Erschliessung von Grundst\u00fccken",
    "sg:postcode":"9113",
    "sg:province":"St. Gallen",
    "wof:name":"Wohnbaugen.h\u00f6ren",
    "wof:placetype":"venue"
},
  "geometry": {"coordinates":[9.200012207,47.3739433289],"type":"Point"}
}