{
  "type": "Feature",
  "properties": {
    "iso:country":"CH",
    "sg:address":"Wirzboden 28",
    "sg:city":"Stans",
    "sg:orig_category":"Herstellung von homogenisierten U di\u00e4tetischen Nahrungsmitteln",
    "sg:phone":"+41 41 611 07 77",
    "sg:postcode":"6370",
    "sg:province":"Nidwalden",
    "wof:name":"Bio-athletik Ern\u00e4hrungs-erg\u00e4nzung, Egli Hugo",
    "wof:placetype":"venue"
},
  "geometry": {"coordinates":[8.3559350967,46.9592323303],"type":"Point"}
}