{
  "type": "Feature",
  "properties": {
    "iso:country":"CH",
    "sg:address":"Rue Du Grand-pont 1",
    "sg:city":"Orbe",
    "sg:orig_category":"Versicherungen Hauptagenturen",
    "sg:phone":"+41 24 441 30 85",
    "sg:postcode":"1350",
    "sg:province":"Vaud",
    "wof:name":"Assurance Cantonale Contre L'incendie & Les \u00e9l\u00e9ments Nat.",
    "wof:placetype":"venue"
},
  "geometry": {"coordinates":[6.5322880745,46.7228279114],"type":"Point"}
}