{
  "type": "Feature",
  "properties": {
    "iso:country":"CH",
    "sg:address":"Avril Avenue Du Quatorze 7c 1020 Renens Vd. Postfach",
    "sg:city":"Mont-sur-lausanne",
    "sg:orig_category":"Herstellung von medizinischen U chirurgischen Ger\u00e4ten sowie orthop\u00e4dischen Vorrichtungen",
    "sg:phone":"+41 21 657 09 10",
    "sg:postcode":"1052",
    "sg:province":"Vaud",
    "wof:name":"Cytyc S.\u00e0 R.l.",
    "wof:placetype":"venue"
},
  "geometry": {"coordinates":[6.5804548264,46.5393638611],"type":"Point"}
}