{
  "type": "Feature",
  "properties": {
    "iso:country":"CH",
    "sg:address":"Chavannes Route De 11",
    "sg:city":"Lausanne",
    "sg:orig_category":"Herstellung von medizinischen U chirurgischen Ger\u00e4ten sowie orthop\u00e4dischen Vorrichtungen",
    "sg:phone":"+41 21 622 87 87",
    "sg:postcode":"1007",
    "sg:province":"Vaud",
    "wof:name":"Vidy-ortho Sa",
    "wof:placetype":"venue"
},
  "geometry": {"coordinates":[6.6009321213,46.5183105469],"type":"Point"}
}