{
  "type": "Feature",
  "properties": {
    "iso:country":"CH",
    "sg:address":"Bahnhofstrasse 21 6300 Zug. Postfach 4824",
    "sg:city":"Zug",
    "sg:orig_category":"Unternehmensberatung Wirtschaftspr\u00fcfung, Steuerberatung U Treuhand",
    "sg:phone":"+41 18445500",
    "sg:postcode":"6304",
    "sg:province":"Zug",
    "wof:name":"Temperli-treuhand",
    "wof:placetype":"venue"
},
  "geometry": {"coordinates":[8.40508461,47.4478797913],"type":"Point"}
}