{
  "type": "Feature",
  "properties": {
    "iso:country":"CH",
    "sg:address":"Mittlere Dorfstrasse 2",
    "sg:city":"Suhr",
    "sg:orig_category":"Herstellung von medizinischen U chirurgischen Ger\u00e4ten sowie orthop\u00e4dischen Vorrichtungen",
    "sg:postcode":"5034",
    "sg:province":"Aargau",
    "wof:name":"Gwl Cehic M Gesundheitsger\u00e4te Usw.; Handel",
    "wof:placetype":"venue"
},
  "geometry": {"coordinates":[8.852396965,47.1925964355],"type":"Point"}
}