{
  "type": "Feature",
  "properties": {
    "iso:country":"CH",
    "sg:address":"H\u00f6henweg 15",
    "sg:city":"M\u00f6rigen",
    "sg:orig_category":"Unclassifiable Establishments",
    "sg:postcode":"2572",
    "sg:province":"Bern",
    "wof:name":"Sucons Gmbh",
    "wof:placetype":"venue"
},
  "geometry": {"coordinates":[7.2108221054,47.0801925659],"type":"Point"}
}