{
  "type": "Feature",
  "properties": {
    "iso:country":"CH",
    "sg:address":"Dorfstrasse 20",
    "sg:city":"Zumikon",
    "sg:orig_category":"Vereine Musik/Blasmusik",
    "sg:phone":"+41 2142515",
    "sg:postcode":"8126",
    "sg:province":"Z\u00fcrich",
    "wof:name":"Harmonie Zumikon",
    "wof:placetype":"venue"
},
  "geometry": {"coordinates":[8.6203737259,47.3351554871],"type":"Point"}
}