{
  "type": "Feature",
  "properties": {
    "iso:country":"CH",
    "sg:address":"Rue Neuve-du-molard 4-6 1200 Gen\u00e8ve. Postfach",
    "sg:city":"Gen\u00e8ve",
    "sg:orig_category":"Herstellung von W\u00e4sche",
    "sg:phone":"+41 22 312 04 40",
    "sg:postcode":"1204",
    "sg:province":"Gen\u00e8ve",
    "wof:name":"Tr\u00e9sor D'ali B\u00e9b\u00e9, Werlen Campanini Catherine",
    "wof:placetype":"venue"
},
  "geometry": {"coordinates":[6.1482491493,46.2033157349],"type":"Point"}
}