{
  "type": "Feature",
  "properties": {
    "addr:full":"Seefeldstrasse 56 Z\u00fcrich Z\u00fcrich 8008",
    "addr:housenumber":"56",
    "addr:postcode":"8008",
    "addr:street":"Seefeldstrasse",
    "iso:country":"CH",
    "sg:address":"Seefeldstrasse 56",
    "sg:city":"Z\u00fcrich",
    "sg:orig_category":"Detailhandel mit Damenbekleidung",
    "sg:phone":"+41 12519905",
    "sg:postcode":"8008",
    "sg:province":"Z\u00fcrich",
    "wof:name":"Margaretha Schoch Boutique Maggy",
    "wof:placetype":"venue"
},
  "geometry": {"coordinates":[8.550362,47.362343],"type":"Point"}
}