{
  "type": "Feature",
  "properties": {
    "iso:country":"CH",
    "sg:address":"Bardella",
    "sg:city":"Flums",
    "sg:orig_category":"Erdbewegungsarbeiten",
    "sg:phone":"+41 81 733 32 50",
    "sg:postcode":"8890",
    "sg:province":"St. Gallen",
    "wof:name":"David Wildhaber Trax-& Grabarbeiten",
    "wof:placetype":"venue"
},
  "geometry": {"coordinates":[9.3425388336,47.0917549133],"type":"Point"}
}