{
  "type": "Feature",
  "properties": {
    "iso:country":"CH",
    "sg:address":"Degersheimer Strasse",
    "sg:city":"Dicken",
    "sg:orig_category":"Detailhandel mit Waren verschiedener Art, Hauptrichtung Nahrungsmittel",
    "sg:phone":"+41 71 377 11 28",
    "sg:postcode":"9115",
    "sg:province":"St. Gallen",
    "wof:name":"Hans Pf\u00e4ndler Dorfladen",
    "wof:placetype":"venue"
},
  "geometry": {"coordinates":[9.1904716492,47.3367614746],"type":"Point"}
}