{
  "type": "Feature",
  "properties": {
    "iso:country":"CH",
    "sg:address":"Avenue Haldimand 41",
    "sg:city":"Yverdon-les-bains",
    "sg:orig_category":"Physiotherapie",
    "sg:phone":"+41 24 425 26 16",
    "sg:postcode":"1400",
    "sg:province":"Vaud",
    "wof:name":"V\u00e9ronique Baatard Physioth\u00e9rapie",
    "wof:placetype":"venue"
},
  "geometry": {"coordinates":[6.6465358734,46.779006958],"type":"Point"}
}