{
  "type": "Feature",
  "properties": {
    "iso:country":"CH",
    "sg:address":"Casa Vanari",
    "sg:city":"Campascio",
    "sg:orig_category":"Grosshandel mit Wasch U Reinigungsmitteln Herstellung von Seifen, Wasch U Reinigungsmitteln",
    "sg:phone":"+41 81 846 54 44",
    "sg:postcode":"7748",
    "sg:province":"Graubunden",
    "wof:name":"Micro Vip Ag",
    "wof:placetype":"venue"
},
  "geometry": {"coordinates":[10.1302528381,46.2464294434],"type":"Point"}
}