{
  "type": "Feature",
  "properties": {
    "iso:country":"CH",
    "sg:address":"Spalenvorstadt 43",
    "sg:city":"Basel",
    "sg:orig_category":"Detailhandel mit Spielwaren",
    "sg:phone":"+41 61 261 99 39",
    "sg:postcode":"4051",
    "sg:province":"Basel-Stadt",
    "wof:name":"Zauberl\u00e4deli Inh.s.& K.blum Zauber-& Scherzartikel",
    "wof:placetype":"venue"
},
  "geometry": {"coordinates":[7.5817089081,47.5576820374],"type":"Point"}
}