{
  "type": "Feature",
  "properties": {
    "addr:full":"Zugerstrasse 35 Horgen Z\u00fcrich 8810",
    "addr:housenumber":"35",
    "addr:postcode":"8810",
    "addr:street":"Zugerstrasse",
    "iso:country":"CH",
    "sg:address":"Zugerstrasse 35",
    "sg:city":"Horgen",
    "sg:orig_category":"Arztpraxen",
    "sg:phone":"+41 17255055",
    "sg:postcode":"8810",
    "sg:province":"Z\u00fcrich",
    "wof:name":"Dr.med.kurt Dettwiler Spezialarzt Fmh",
    "wof:placetype":"venue"
},
  "geometry": {"coordinates":[8.598777,47.259083],"type":"Point"}
}