{
  "type": "Feature",
  "properties": {
    "iso:country":"CH",
    "sg:address":"Freie Strasse 26 4001 Basel. Postfach",
    "sg:city":"Basel",
    "sg:orig_category":"Detailhandel mit Damenbekleidung Grosshandel mit Textilien",
    "sg:phone":"+41 31 859 50 85",
    "sg:postcode":"4001",
    "sg:province":"Basel-Stadt",
    "wof:name":"H & M Hennes & Mauritz Ag",
    "wof:placetype":"venue"
},
  "geometry": {"coordinates":[7.4949731827,47.0172996521],"type":"Point"}
}