{
  "type": "Feature",
  "properties": {
    "addr:full":"Aarestrasse 59 3661 Uetendorf. Postfach 7 Uetendorf Bern 3661",
    "addr:housenumber":"59;7",
    "addr:postcode":"3661 uetendorf.;3661",
    "addr:street":"Aarestrasse;Postfach",
    "iso:country":"CH",
    "sg:address":"Aarestrasse 59 3661 Uetendorf. Postfach 7",
    "sg:city":"Uetendorf",
    "sg:orig_category":"Herstellung von Werkzeugen",
    "sg:phone":"+41 33 345 29 92",
    "sg:postcode":"3661",
    "sg:province":"Bern",
    "wof:name":"Brand G. Werkzeugmaschinenfabrik Ag",
    "wof:placetype":"venue"
},
  "geometry": {"coordinates":[7.597362,46.779648],"type":"Point"}
}