{
  "type": "Feature",
  "properties": {
    "iso:country":"CH",
    "sg:address":"Weberstrasse 10",
    "sg:city":"Z\u00fcrich",
    "sg:orig_category":"Technische, physikalische U chemische Untersuchung",
    "sg:phone":"+41 13639981",
    "sg:postcode":"8001",
    "sg:province":"Z\u00fcrich",
    "wof:name":"Kiefer & Partners Ag",
    "wof:placetype":"venue"
},
  "geometry": {"coordinates":[8.5287351608,47.3705368042],"type":"Point"}
}