{
  "type": "Feature",
  "properties": {
    "iso:country":"CH",
    "sg:address":"Holzgass 2",
    "sg:city":"Lupfig",
    "sg:orig_category":"Schlossereien",
    "sg:phone":"+41 56 444 94 58",
    "sg:postcode":"5242",
    "sg:province":"Aargau",
    "wof:name":"Alois Hitz Bau-& Kunstschlosserei",
    "wof:placetype":"venue"
},
  "geometry": {"coordinates":[8.1983499527,47.4399452209],"type":"Point"}
}