{
  "type": "Feature",
  "properties": {
    "iso:country":"CH",
    "sg:address":"8756 Mitl\u00f6di. Postfach 17",
    "sg:city":"Mitl\u00f6di",
    "sg:orig_category":"Maschinen-Fabrikation",
    "sg:phone":"+41 17151418",
    "sg:postcode":"8756",
    "sg:province":"Glarus",
    "wof:name":"Boder Engineering Gmbh",
    "wof:placetype":"venue"
},
  "geometry": {"coordinates":[8.5479516983,47.3265800476],"type":"Point"}
}