{
  "type": "Feature",
  "properties": {
    "iso:country":"CH",
    "sg:address":"Rue De Cossonay 1 1023 Crissier Case Postale 216",
    "sg:city":"Crissier",
    "sg:orig_category":"Grosshandel mit Bekleidung Grosshandel mit Schuhen",
    "sg:phone":"+41 21 635 56 30",
    "sg:postcode":"1023",
    "sg:province":"Vaud",
    "wof:name":"Asd Diffusion Sa",
    "wof:placetype":"venue"
},
  "geometry": {"coordinates":[6.57124,46.557301],"type":"Point"}
}