{
  "type": "Feature",
  "properties": {
    "iso:country":"CH",
    "sg:address":"Altenbachstrasse 4a",
    "sg:city":"Wollerau",
    "sg:orig_category":"Sonstiger Grosshandel Vermittlung von Immobilien",
    "sg:phone":"+41 17842244",
    "sg:postcode":"8832",
    "sg:province":"Schwyz",
    "wof:name":"Immobilien & Dienstleistungen Freddy Lins",
    "wof:placetype":"venue"
},
  "geometry": {"coordinates":[8.7110471725,47.1954460144],"type":"Point"}
}