{
  "type": "Feature",
  "properties": {
    "addr:full":"Jakob Signerstrasse 3 Appenzell Appenzell Innerhoden 9050",
    "addr:housenumber":"3",
    "addr:postcode":"9050",
    "addr:street":"Signerstrasse",
    "iso:country":"CH",
    "sg:address":"Jakob Signerstrasse 3",
    "sg:city":"Appenzell",
    "sg:orig_category":"Architektur U Ingenieurb\u00fcros Architekturb\u00fcros",
    "sg:phone":"+41 41 280 13 53",
    "sg:postcode":"9050",
    "sg:province":"Appenzell Innerhoden",
    "wof:name":"Architekturb\u00fcro M\u00fcller K. Ag Emmenbr\u00fccke",
    "wof:placetype":"venue"
},
  "geometry": {"coordinates":[8.272505,47.085098],"type":"Point"}
}