{
  "type": "Feature",
  "properties": {
    "iso:country":"CH",
    "sg:address":"T\u00f6pferstrasse 36",
    "sg:city":"Z\u00fcrich",
    "sg:orig_category":"Non-Classified Establishments",
    "sg:postcode":"8045",
    "sg:province":"Z\u00fcrich",
    "wof:name":"R\u00f6thlisberger Moden",
    "wof:placetype":"venue"
},
  "geometry": {"coordinates":[8.5157613754,47.3595542908],"type":"Point"}
}