{
  "type": "Feature",
  "properties": {
    "iso:country":"CH",
    "sg:address":"Passage De La Matze 11 1950 Sion. Postfach",
    "sg:city":"Sitten",
    "sg:orig_category":"Fachdetailhandel in Verkaufsr\u00e4umen",
    "sg:postcode":"1950",
    "sg:province":"Valais",
    "wof:name":"Solioz Georges",
    "wof:placetype":"venue"
},
  "geometry": {"coordinates":[7.3547668457,46.2298126221],"type":"Point"}
}