{
  "type": "Feature",
  "properties": {
    "iso:country":"CH",
    "sg:address":"Jurastrasse 9",
    "sg:city":"Feldbrunnen",
    "sg:orig_category":"Unclassifiable Establishments",
    "sg:phone":"+41 32 623 55 71",
    "sg:postcode":"4532",
    "sg:province":"Solothurn",
    "wof:name":"Eugen Meier + Partner Ag",
    "wof:placetype":"venue"
},
  "geometry": {"coordinates":[7.5583238602,47.2213249207],"type":"Point"}
}