{
  "type": "Feature",
  "properties": {
    "iso:country":"CH",
    "sg:address":"Oberfahrstr.",
    "sg:city":"Au",
    "sg:classifiers":[
        {
            "category":"Real Estate",
            "subcategory":"Architect",
            "type":"Services"
        }
    ],
    "sg:phone":"+41 71 222 80 55",
    "sg:postcode":"9434",
    "sg:province":"St. Gallen",
    "sg:tags":[
        "textile",
        "clothing"
    ],
    "wof:name":"Ernst Brunner Ag",
    "wof:placetype":"venue"
},
  "geometry": {"coordinates":[9.3713655472,47.4222373962],"type":"Point"}
}