{
  "type": "Feature",
  "properties": {
    "iso:country":"CH",
    "sg:address":"Rue De Vevey 103",
    "sg:city":"Bulle",
    "sg:orig_category":"Detailhandel mit Sportartikeln",
    "sg:phone":"+41 26 913 17 50",
    "sg:postcode":"1630",
    "sg:province":"Fribourg",
    "wof:name":"Surf Machine Pro Shop Snowboards",
    "wof:placetype":"venue"
},
  "geometry": {"coordinates":[7.0512709618,46.6150283813],"type":"Point"}
}