{
  "type": "Feature",
  "properties": {
    "iso:country":"CH",
    "sg:address":"Chesa Gl\u00fcschaint",
    "sg:city":"Pontresina",
    "sg:orig_category":"Sportvereine Ballsport Badminton",
    "sg:phone":"+41 81 842 79 32",
    "sg:postcode":"7504",
    "sg:province":"Graubunden",
    "wof:name":"Badminton-club Engiadina",
    "wof:placetype":"venue"
},
  "geometry": {"coordinates":[9.9012298584,46.4963035583],"type":"Point"}
}