{
  "type": "Feature",
  "properties": {
    "iso:country":"CH",
    "sg:address":"Burgstrasse 3 8570 Hard B. Weinfelden. Postfach",
    "sg:city":"Herisau",
    "sg:orig_category":"Gesundheitswesen",
    "sg:postcode":"9100",
    "sg:province":"Appenzell Ausserrhoden",
    "wof:name":"Humana Dignity-center Im Zedernpark Ag Betreuung Von Betagten, Behinderten Oder Sonst Wie Unterst\u00fctzungsbed\u00fcrftige Personen Usw",
    "wof:placetype":"venue"
},
  "geometry": {"coordinates":[9.1381845474,47.5666694641],"type":"Point"}
}