{
  "type": "Feature",
  "properties": {
    "iso:country":"CH",
    "sg:address":"Route De Saint-cergue 303",
    "sg:city":"Nyon",
    "sg:orig_category":"Hardwareberatung Softwareentwicklung U beratung",
    "sg:postcode":"1260",
    "sg:province":"Vaud",
    "wof:name":"Proactive Partners Sa",
    "wof:placetype":"venue"
},
  "geometry": {"coordinates":[6.2258281708,46.3964614868],"type":"Point"}
}