{
  "type": "Feature",
  "properties": {
    "iso:country":"CH",
    "sg:address":"Kanzleistrasse 1 9230 Flawil. Postfach 121",
    "sg:city":"Flawil",
    "sg:orig_category":"Sonstiges Versicherungsgewerbe",
    "sg:phone":"+41 71 393 34 89",
    "sg:postcode":"9230",
    "sg:province":"St. Gallen",
    "wof:name":"Roland B\u00fceler Hauptagentur Flawil",
    "wof:placetype":"venue"
},
  "geometry": {"coordinates":[9.1883440018,47.4136123657],"type":"Point"}
}