{
  "type": "Feature",
  "properties": {
    "iso:country":"CH",
    "sg:address":"Gotthardstrasse 66 6410 Goldau. Postfach 263",
    "sg:city":"Goldau",
    "sg:orig_category":"Herstellung von Metallerzeugnissen ohne Maschinenbau Maschinenbau",
    "sg:phone":"+41 79 358 68 10",
    "sg:postcode":"6410",
    "sg:province":"Schwyz",
    "wof:name":"B\u00fcrgi-infra-grill & K\u00fcchenmaschinen Ag",
    "wof:placetype":"venue"
},
  "geometry": {"coordinates":[8.5484333038,47.0433425903],"type":"Point"}
}