{
  "type": "Feature",
  "properties": {
    "iso:country":"CH",
    "sg:address":"Perron Rue Du 66",
    "sg:city":"Gland",
    "sg:orig_category":"Detailhandel mit elektrischen Haushalts-,Radio U Fernsehger\u00e4ten sowie Musikinstrumenten",
    "sg:postcode":"1196",
    "sg:province":"Vaud",
    "wof:name":"Rainbow Video Service Veillard Alain",
    "wof:placetype":"venue"
},
  "geometry": {"coordinates":[6.2815961838,46.4203186035],"type":"Point"}
}