{
  "type": "Feature",
  "properties": {
    "iso:country":"CH",
    "sg:address":"Rue Du 23 Juin 19",
    "sg:city":"Courroux",
    "sg:orig_category":"Architektur U Ingenieurb\u00fcros",
    "sg:phone":"+41 32 422 30 41",
    "sg:postcode":"2822",
    "sg:province":"Jura",
    "wof:name":"Cgc Cremona Et Fleury Bureau D'ing\u00e9nieurs Sa.",
    "wof:placetype":"venue"
},
  "geometry": {"coordinates":[7.371762,47.362392],"type":"Point"}
}