{
  "type": "Feature",
  "properties": {
    "iso:country":"CH",
    "sg:address":"Rosenbergstrasse 93",
    "sg:city":"St.gallen",
    "sg:classifiers":[
        {
            "category":"Professional",
            "subcategory":"Employment Agencies",
            "type":"Services"
        }
    ],
    "sg:phone":"+41 71 274 52 60",
    "sg:postcode":"9000",
    "sg:province":"St. Gallen",
    "sg:tags":[
        "personal",
        "u",
        "stellenvermittlung"
    ],
    "wof:name":"Personalberatung Hungerb\u00fchler & Partner",
    "wof:placetype":"venue"
},
  "geometry": {"coordinates":[9.3650655746,47.4221000671],"type":"Point"}
}