{
  "type": "Feature",
  "properties": {
    "iso:country":"CH",
    "sg:address":"Kirchgasse 6",
    "sg:city":"Bischofszell",
    "sg:orig_category":"Detailhandel mit Radio U Fernsehger\u00e4ten",
    "sg:phone":"+41 71 422 46 66",
    "sg:postcode":"9220",
    "sg:province":"Thurgau",
    "wof:name":"Paul Bohren Radio Tv-service",
    "wof:placetype":"venue"
},
  "geometry": {"coordinates":[9.2401218414,47.4934120178],"type":"Point"}
}