{
  "type": "Feature",
  "properties": {
    "iso:country":"CH",
    "sg:address":"Ebnetrain 2",
    "sg:city":"Meggen",
    "sg:orig_category":"Herstellung von medizinischen U chirurgischen Ger\u00e4ten sowie orthop\u00e4dischen Vorrichtungen Medizinisch",
    "sg:phone":"+41 41 377 00 87",
    "sg:postcode":"6045",
    "sg:province":"Luzern",
    "wof:name":"Mtm Medical High Tech Meggen Gmbh",
    "wof:placetype":"venue"
},
  "geometry": {"coordinates":[8.364563942,47.046836853],"type":"Point"}
}