{
  "type": "Feature",
  "properties": {
    "iso:country":"CH",
    "sg:address":"Bleuen",
    "sg:city":"Oeschenbach",
    "sg:orig_category":"Primarschulen",
    "sg:phone":"+41 62 965 32 02",
    "sg:postcode":"4943",
    "sg:province":"Bern",
    "wof:name":"Primarschule Oeschenbach",
    "wof:placetype":"venue"
},
  "geometry": {"coordinates":[7.7536001205,47.1153450012],"type":"Point"}
}