{
  "type": "Feature",
  "properties": {
    "iso:country":"CH",
    "sg:address":"7744",
    "sg:city":"Campocologno",
    "sg:orig_category":"Detailhandel mit Waren verschiedener Art, Hauptrichtung Nahrungsmittel Tankstellen",
    "sg:phone":"+41 81 846 57 54",
    "sg:postcode":"7744",
    "sg:province":"Graubunden",
    "wof:name":"Enrico Marantelli",
    "wof:placetype":"venue"
},
  "geometry": {"coordinates":[10.1414899826,46.2340316772],"type":"Point"}
}