{
  "type": "Feature",
  "properties": {
    "iso:country":"CH",
    "sg:address":"Schlossstrasse 14 4922 B\u00fctzberg. Postfach",
    "sg:city":"B\u00fctzberg",
    "sg:orig_category":"Herstellung von Ger\u00e4ten der Elektrizit\u00e4tserzeugung, -verteilung u.\u00e4. -Herstellung von sonstigen elek",
    "sg:phone":"+41 62 963 14 24",
    "sg:postcode":"4922",
    "sg:province":"Bern",
    "wof:name":"Hegel Ag Elektronische Apparate",
    "wof:placetype":"venue"
},
  "geometry": {"coordinates":[7.748705864,47.2147445679],"type":"Point"}
}