{
  "type": "Feature",
  "properties": {
    "iso:country":"CH",
    "sg:address":"Le Sentier Commune Du Chenit Les Moulins 14 1347 Le Sentier. Postfach",
    "sg:city":"Orient",
    "sg:orig_category":"Handel mit Automobilteilen U Zubeh\u00f6r",
    "sg:postcode":"1341",
    "sg:province":"Vaud",
    "wof:name":"Gotzmann Racing Autozubeh\u00f6r; Handel",
    "wof:placetype":"venue"
},
  "geometry": {"coordinates":[7.2787652016,47.1268119812],"type":"Point"}
}