{
  "type": "Feature",
  "properties": {
    "iso:country":"CH",
    "sg:address":"Br\u00fcckenstrasse 1",
    "sg:city":"Bern",
    "sg:orig_category":"Arztpraxen",
    "sg:phone":"+41 31 311 63 62",
    "sg:postcode":"3005",
    "sg:province":"Bern",
    "wof:name":"Dr.med.peter Schl\u00e4ppi Arzt F.allgemeine Medizin Fmh",
    "wof:placetype":"venue"
},
  "geometry": {"coordinates":[7.44468,46.944653],"type":"Point"}
}