{
  "type": "Feature",
  "properties": {
    "addr:full":"Chemin De Richemond 3 1700 Fribourg. Postfach Fribourg Fribourg 1701",
    "addr:housenumber":"3",
    "addr:postcode":"1700;postfach;1701",
    "addr:street":"Chemin De Richemond",
    "iso:country":"CH",
    "sg:address":"Chemin De Richemond 3 1700 Fribourg. Postfach",
    "sg:city":"Fribourg",
    "sg:orig_category":"Bauschreinerei Herstellung von Konstruktionsteilen, Fertigbauteilen U Ausbauelementen aus Holz",
    "sg:postcode":"1701",
    "sg:province":"Fribourg",
    "wof:name":"Dessiex Henri",
    "wof:placetype":"venue"
},
  "geometry": {"coordinates":[7.14829,46.801804],"type":"Point"}
}