{
  "type": "Feature",
  "properties": {
    "iso:country":"CH",
    "sg:address":"1325",
    "sg:city":"Vaulion",
    "sg:orig_category":"Herstellung von Seifen, Wasch U Reinigungsmitteln",
    "sg:postcode":"1325",
    "sg:province":"Vaud",
    "wof:name":"Tripet Raoul",
    "wof:placetype":"venue"
},
  "geometry": {"coordinates":[6.3902349472,46.6893463135],"type":"Point"}
}