{
  "type": "Feature",
  "properties": {
    "iso:country":"CH",
    "sg:address":"M\u00fchle 8479 Altikon. Postfach",
    "sg:city":"Winterthur",
    "sg:orig_category":"Instandhaltung U Reparatur von Automobilen",
    "sg:postcode":"8405",
    "sg:province":"Z\u00fcrich",
    "wof:name":"Frysys Automobile M. Friedery",
    "wof:placetype":"venue"
},
  "geometry": {"coordinates":[8.7876596451,47.5735702515],"type":"Point"}
}