{
  "type": "Feature",
  "properties": {
    "iso:country":"CH",
    "sg:address":"Rietwis 2813",
    "sg:city":"Herisau",
    "sg:classifiers":[
        {
            "category":"Travel",
            "subcategory":"Hotels & Motels",
            "type":"Entertainment"
        }
    ],
    "sg:postcode":"9100",
    "sg:province":"Appenzell Ausserrhoden",
    "sg:tags":[
        "hotels",
        "mit",
        "restaurant"
    ],
    "wof:name":"Jakob M.",
    "wof:placetype":"venue"
},
  "geometry": {"coordinates":[7.7268161774,46.8702774048],"type":"Point"}
}