{
  "type": "Feature",
  "properties": {
    "iso:country":"CH",
    "sg:address":"1874",
    "sg:city":"Champ\u00e9ry",
    "sg:orig_category":"Fussreflexzonenmassage",
    "sg:phone":"+41 22 343 00 78",
    "sg:postcode":"1874",
    "sg:province":"Valais",
    "wof:name":"Ornella Kummer Massage & R\u00e9flexologie",
    "wof:placetype":"venue"
},
  "geometry": {"coordinates":[6.1407551765,46.1808280945],"type":"Point"}
}