{
  "type": "Feature",
  "properties": {
    "iso:country":"CH",
    "sg:address":"Schl\u00f6sslirain 5",
    "sg:city":"Luzern",
    "sg:classifiers":[
        {
            "category":"Shopping",
            "subcategory":"Baby Store",
            "type":"Retail Goods"
        }
    ],
    "sg:phone":"+41 41 370 36 63",
    "sg:postcode":"6006",
    "sg:province":"Luzern",
    "sg:tags":[
        "children's",
        "sock"
    ],
    "wof:name":"E-socks",
    "wof:placetype":"venue"
},
  "geometry": {"coordinates":[8.338015,47.055878],"type":"Point"}
}