{
  "type": "Feature",
  "properties": {
    "iso:country":"CH",
    "sg:address":"Avenue Du Valais 3 1896 Vouvry. Postfach",
    "sg:city":"Vouvry",
    "sg:orig_category":"RESTAURANTS: TEA-ROOMS",
    "sg:postcode":"1896",
    "sg:province":"Valais",
    "wof:name":"Giovanni Cannata Et Maria Caeiro",
    "wof:placetype":"venue"
},
  "geometry": {"coordinates":[6.8910307884,46.3360671997],"type":"Point"}
}