{
  "type": "Feature",
  "properties": {
    "iso:country":"CH",
    "sg:address":"Beugenweg 5",
    "sg:city":"H\u00e4gendorf",
    "sg:orig_category":"Herstellung von konfektionierten Textilwaren ohne Bekleidung",
    "sg:phone":"+41 62 216 35 35",
    "sg:postcode":"4614",
    "sg:province":"Solothurn",
    "wof:name":"Pasti-storen H.pastoinegg",
    "wof:placetype":"venue"
},
  "geometry": {"coordinates":[7.847867012,47.3341026306],"type":"Point"}
}