{
  "type": "Feature",
  "properties": {
    "iso:country":"CH",
    "sg:address":"Stettenstr. 6",
    "sg:city":"Geroldswil",
    "sg:orig_category":"Wirtschaftspr\u00fcfung, Steuerberatung U Treuhand",
    "sg:postcode":"8954",
    "sg:province":"Z\u00fcrich",
    "wof:name":"Libo Treuhand Lisser & Bobsin",
    "wof:placetype":"venue"
},
  "geometry": {"coordinates":[8.4072847366,47.421169281],"type":"Point"}
}