{
  "type": "Feature",
  "properties": {
    "iso:country":"CH",
    "sg:address":"Schwertgasse 5",
    "sg:city":"Zurzach",
    "sg:orig_category":"Detailhandel mit Geschenkartikeln U Souvenirs",
    "sg:phone":"+41 56 249 33 23",
    "sg:postcode":"5330",
    "sg:province":"Aargau",
    "wof:name":"Gerlinde Ludwig Boutique Dreispitz",
    "wof:placetype":"venue"
},
  "geometry": {"coordinates":[8.2940940857,47.5875091553],"type":"Point"}
}