{
  "type": "Feature",
  "properties": {
    "iso:country":"CH",
    "sg:address":"Route De Cugy 136",
    "sg:city":"Mont-sur-lausanne",
    "sg:orig_category":"Instandhaltung U Reparatur von Automobilen",
    "sg:phone":"+41 21 652 38 58",
    "sg:postcode":"1052",
    "sg:province":"Vaud",
    "wof:name":"Forney Garage Auto-electricit\u00e9 Garage",
    "wof:placetype":"venue"
},
  "geometry": {"coordinates":[6.6346788406,46.5767211914],"type":"Point"}
}