{
  "type": "Feature",
  "properties": {
    "iso:country":"CH",
    "sg:address":"Freier Platz G\u00fctwrhof 8200 Schaffhausen. Postfach",
    "sg:city":"Schaffhausen",
    "sg:orig_category":"RESTAURANTS: TEA-ROOMS",
    "sg:phone":"+41 52 624 34 14",
    "sg:postcode":"8202",
    "sg:province":"Schaffhausen",
    "wof:name":"Schlatter Peter",
    "wof:placetype":"venue"
},
  "geometry": {"coordinates":[8.6404600143,47.695400238],"type":"Point"}
}