{
  "type": "Feature",
  "properties": {
    "iso:country":"CH",
    "sg:address":"Kantonsstrasse 40 6048 Horw. Postfach 379",
    "sg:city":"Horw",
    "sg:orig_category":"Grossbanken",
    "sg:phone":"+41 32 652 73 31",
    "sg:postcode":"6048",
    "sg:province":"Luzern",
    "wof:name":"Credit Suisse",
    "wof:placetype":"venue"
},
  "geometry": {"coordinates":[7.3986091614,47.1937065125],"type":"Point"}
}