{
  "type": "Feature",
  "properties": {
    "iso:country":"CH",
    "sg:address":"R\u00fcttimattstrasse 5 4557 Horriwil. Postfach 15",
    "sg:city":"Horriwil",
    "sg:orig_category":"Bauspenglerei Zimmerei, Dachdeckerei, Bauspenglerei U Abdichtung",
    "sg:phone":"+41 71 278 67 20",
    "sg:postcode":"4557",
    "sg:province":"Solothurn",
    "wof:name":"Schudel & Hinder Gmbh Bauspenglerei",
    "wof:placetype":"venue"
},
  "geometry": {"coordinates":[9.355565,47.420704],"type":"Point"}
}