{
  "type": "Feature",
  "properties": {
    "iso:country":"CH",
    "sg:address":"3919",
    "sg:city":"Blatten(l\u00f6tschen)",
    "sg:orig_category":"Personenbef\u00f6rderung im Linienverkehr zu Land",
    "sg:phone":"+41 27 939 13 63",
    "sg:postcode":"3919",
    "sg:province":"Valais",
    "wof:name":"Skilift Blatten-l\u00f6tschental Ag",
    "wof:placetype":"venue"
},
  "geometry": {"coordinates":[7.8191571236,46.4194755554],"type":"Point"}
}