{
  "type": "Feature",
  "properties": {
    "iso:country":"CH",
    "sg:address":"1442",
    "sg:city":"Montagny-yverdon",
    "sg:orig_category":"RESTAURANTS: TEA-ROOMS",
    "sg:postcode":"1442",
    "sg:province":"Vaud",
    "wof:name":"Brandt Claudine",
    "wof:placetype":"venue"
},
  "geometry": {"coordinates":[6.609389782,46.7890090942],"type":"Point"}
}