{
  "type": "Feature",
  "properties": {
    "iso:country":"CH",
    "sg:address":"Bahnhofstrasse 2a",
    "sg:city":"Lyss",
    "sg:orig_category":"Offsetdruck Schnelldruck U Kopierservice",
    "sg:phone":"+41 71 911 47 11",
    "sg:postcode":"3250",
    "sg:province":"Bern",
    "wof:name":"Copy-& Druck-csc Ag",
    "wof:placetype":"venue"
},
  "geometry": {"coordinates":[9.0464000702,47.4631958008],"type":"Point"}
}