{
  "type": "Feature",
  "properties": {
    "iso:country":"CH",
    "sg:address":"Friedensgasse 2",
    "sg:city":"Dornach",
    "sg:orig_category":"Arztpraxen",
    "sg:phone":"+41 71 222 77 12",
    "sg:postcode":"4143",
    "sg:province":"Solothurn",
    "wof:name":"Dr.med.hans-peter Oetiker Spezialarzt",
    "wof:placetype":"venue"
},
  "geometry": {"coordinates":[9.390344,47.415016],"type":"Point"}
}