{
  "type": "Feature",
  "properties": {
    "iso:country":"CH",
    "sg:address":"R\u00fctenenstrasse 18a",
    "sg:city":"Killwangen",
    "sg:orig_category":"Fachdetailhandel in Verkaufsr\u00e4umen",
    "sg:phone":"+41 56 402 08 38",
    "sg:postcode":"8956",
    "sg:province":"Aargau",
    "wof:name":"Philchin Gmbh",
    "wof:placetype":"venue"
},
  "geometry": {"coordinates":[8.3483495712,47.4303398132],"type":"Point"}
}