{
  "type": "Feature",
  "properties": {
    "iso:country":"CH",
    "sg:address":"Sitterdorf 8589 Sitterdorf. Postfach",
    "sg:city":"Sitterdorf",
    "sg:orig_category":"Grosshandel mit lebenden Tieren",
    "sg:postcode":"8589",
    "sg:province":"Thurgau",
    "wof:name":"Baumgartner Otto",
    "wof:placetype":"venue"
},
  "geometry": {"coordinates":[9.2544803619,47.5071716309],"type":"Point"}
}