{
  "type": "Feature",
  "properties": {
    "iso:country":"CH",
    "sg:address":"Gl\u00e4rnischstrasse 2b",
    "sg:city":"W\u00e4denswil",
    "sg:orig_category":"Bau U Wohngenossenschaften",
    "sg:phone":"+41 17806641",
    "sg:postcode":"8820",
    "sg:province":"Z\u00fcrich",
    "wof:name":"Arbeiter-bau-& Siedlungsgen.",
    "wof:placetype":"venue"
},
  "geometry": {"coordinates":[8.668881,47.230072],"type":"Point"}
}