{
  "type": "Feature",
  "properties": {
    "iso:country":"CH",
    "sg:address":"Ringstr. 30 8487 Zell Zh. Postfach",
    "sg:city":"Kollbrunn",
    "sg:orig_category":"Herstellung von \u00d6fen U Brennern",
    "sg:postcode":"8483",
    "sg:province":"Z\u00fcrich",
    "wof:name":"Gelbhaar H. W.",
    "wof:placetype":"venue"
},
  "geometry": {"coordinates":[8.8226995468,47.446521759],"type":"Point"}
}