{
  "type": "Feature",
  "properties": {
    "iso:country":"CH",
    "sg:address":"Neptunstrasse 14",
    "sg:city":"Kreuzlingen",
    "sg:orig_category":"Geb\u00e4ude, Wohnungsreinigung Reinigungsgewerbe",
    "sg:phone":"+41 71 672 15 60",
    "sg:postcode":"8280",
    "sg:province":"Thurgau",
    "wof:name":"Bachmann H. Reinigungen",
    "wof:placetype":"venue"
},
  "geometry": {"coordinates":[9.1773328781,47.6496276855],"type":"Point"}
}