{
  "type": "Feature",
  "properties": {
    "iso:country":"CH",
    "sg:address":"Riedstrasse 14",
    "sg:city":"Dietikon",
    "sg:orig_category":"Grosshandel mit Software Softwareentwicklung U beratung",
    "sg:phone":"+41 71 911 46 14",
    "sg:postcode":"8953",
    "sg:province":"Z\u00fcrich",
    "wof:name":"Daniel Schl\u00e4pfer Rese Applications Schl\u00e4pfer",
    "wof:placetype":"venue"
},
  "geometry": {"coordinates":[9.0534296036,47.4628791809],"type":"Point"}
}