{
  "type": "Feature",
  "properties": {
    "iso:country":"CH",
    "sg:address":"Lido Via 2 6612 Ascona. Postfach",
    "sg:city":"Ascona",
    "sg:orig_category":"Herstellung von K\u00fcchenm\u00f6beln",
    "sg:phone":"+41 32 969 29 29",
    "sg:postcode":"6612",
    "sg:province":"Ticino",
    "wof:name":"Objectif Cuis'in, Reichen St\u00e9phane",
    "wof:placetype":"venue"
},
  "geometry": {"coordinates":[6.8469409943,47.1312637329],"type":"Point"}
}