{
  "type": "Feature",
  "properties": {
    "iso:country":"CH",
    "sg:address":"R\u00f6merswilstrasse",
    "sg:city":"Rain",
    "sg:orig_category":"Sanit\u00e4r, Heizungs U L\u00fcftungsinstallation",
    "sg:postcode":"6026",
    "sg:province":"Luzern",
    "wof:name":"Weber Reinhold Heizungen Und Sanit\u00e4r Gmbh",
    "wof:placetype":"venue"
},
  "geometry": {"coordinates":[8.6583003998,47.7358093262],"type":"Point"}
}