{
  "type": "Feature",
  "properties": {
    "iso:country":"CH",
    "sg:address":"Grossmattstrasse 17",
    "sg:city":"Rudolfstetten",
    "sg:orig_category":"Herstellung von industriellen Prozesssteuerungsanlagen",
    "sg:phone":"+41 14003910",
    "sg:postcode":"8964",
    "sg:province":"Aargau",
    "wof:name":"Amsler Engineering Ag",
    "wof:placetype":"venue"
},
  "geometry": {"coordinates":[8.4665021896,47.3607711792],"type":"Point"}
}