{
  "type": "Feature",
  "properties": {
    "iso:country":"CH",
    "sg:address":"Hauptstrasse 46a",
    "sg:city":"Sissach",
    "sg:orig_category":"Versicherungen Hauptagenturen",
    "sg:phone":"+41 61 976 96 66",
    "sg:postcode":"4450",
    "sg:province":"Basel-Landschaft",
    "wof:name":"Die Mobiliar Versicherungen & Vorsorge",
    "wof:placetype":"venue"
},
  "geometry": {"coordinates":[7.8141489029,47.4633750916],"type":"Point"}
}