{
  "type": "Feature",
  "properties": {
    "iso:country":"CH",
    "sg:address":"Grafenauweg 6 6300 Zug. Postfach",
    "sg:city":"Biel/bienne",
    "sg:orig_category":"Sonstige pers\u00f6nliche Dienstleistungen",
    "sg:postcode":"2502",
    "sg:province":"Bern",
    "wof:name":"Twintel Ag Wiederverkauf Von Telefongespr\u00e4chsminuten Usw",
    "wof:placetype":"venue"
},
  "geometry": {"coordinates":[8.3319120407,47.3523216248],"type":"Point"}
}