{
  "type": "Feature",
  "properties": {
    "iso:country":"CH",
    "sg:address":"3715",
    "sg:city":"Adelboden",
    "sg:orig_category":"Vereine Musik/Blasmusik",
    "sg:phone":"+41 33 673 24 03",
    "sg:postcode":"3715",
    "sg:province":"Bern",
    "wof:name":"Musikgesellschaft",
    "wof:placetype":"venue"
},
  "geometry": {"coordinates":[7.5602669716,46.4932365417],"type":"Point"}
}