{
  "type": "Feature",
  "properties": {
    "iso:country":"CH",
    "sg:address":"Gr\u00fcngasse 1",
    "sg:city":"Z\u00fcrich",
    "sg:orig_category":"Massagestudios",
    "sg:postcode":"8004",
    "sg:province":"Z\u00fcrich",
    "wof:name":"Adrian Kissling Massagen",
    "wof:placetype":"venue"
},
  "geometry": {"coordinates":[8.5267095566,47.3722381592],"type":"Point"}
}