{
  "type": "Feature",
  "properties": {
    "iso:country":"CH",
    "sg:address":"B\u00fcrenstrasse",
    "sg:city":"Pieterlen",
    "sg:orig_category":"Herstellung von Ziegeln U sonstiger Baukeramik",
    "sg:phone":"+41 62 929 36 36",
    "sg:postcode":"2542",
    "sg:province":"Bern",
    "wof:name":"Ziegelwerke Roggwil Ag",
    "wof:placetype":"venue"
},
  "geometry": {"coordinates":[7.8360600471,47.2304229736],"type":"Point"}
}