{
  "type": "Feature",
  "properties": {
    "iso:country":"CH",
    "sg:address":"Route De Prilly 21",
    "sg:city":"Crissier",
    "sg:orig_category":"Grosshandel mit B\u00fcromaschinen U einrichtungen",
    "sg:postcode":"1023",
    "sg:province":"Vaud",
    "wof:name":"Stilfat Fatton Ph.",
    "wof:placetype":"venue"
},
  "geometry": {"coordinates":[6.5821409225,46.5474433899],"type":"Point"}
}