{
  "type": "Feature",
  "properties": {
    "iso:country":"CH",
    "sg:address":"K\u00e4nerkindenstrasse 2",
    "sg:city":"Diegten",
    "sg:orig_category":"Gasth\u00f6fe/Gasth\u00e4user mit Restaurant HOTELS: MIT RESTAURANT",
    "sg:phone":"+41 61 971 22 35",
    "sg:postcode":"4457",
    "sg:province":"Basel-Landschaft",
    "wof:name":"Gasthof Hirschen Ag",
    "wof:placetype":"venue"
},
  "geometry": {"coordinates":[7.8117489815,47.4131774902],"type":"Point"}
}