{
  "type": "Feature",
  "properties": {
    "iso:country":"CH",
    "sg:address":"Schulhausstrasse 2",
    "sg:city":"Kriegstetten",
    "sg:orig_category":"Wein Detailhandel",
    "sg:phone":"+41 32 675 40 64",
    "sg:postcode":"4566",
    "sg:province":"Solothurn",
    "wof:name":"Walter Affolter Weinhandlung",
    "wof:placetype":"venue"
},
  "geometry": {"coordinates":[7.5987839699,47.1744308472],"type":"Point"}
}