{
  "type": "Feature",
  "properties": {
    "iso:country":"CH",
    "sg:address":"Lausanne Rue De 24",
    "sg:city":"Fribourg",
    "sg:orig_category":"Herstellung von homogenisierten U di\u00e4tetischen Nahrungsmitteln",
    "sg:phone":"+41 26 323 35 03",
    "sg:postcode":"1700",
    "sg:province":"Fribourg",
    "wof:name":"Le Petit Paradis, Robatel Alexandre",
    "wof:placetype":"venue"
},
  "geometry": {"coordinates":[7.1597747803,46.8057365417],"type":"Point"}
}