{
  "type": "Feature",
  "properties": {
    "iso:country":"CH",
    "sg:address":"Haus Bergblick",
    "sg:city":"Bellwald",
    "sg:orig_category":"Allgemeiner Hoch U Tiefbau Zimmerei, Ingenieurholzbau",
    "sg:phone":"+41 79 221 10 36",
    "sg:postcode":"3997",
    "sg:province":"Valais",
    "wof:name":"Bittel & Jeiziner Bau Gmbh Chaletbau & Renovationen",
    "wof:placetype":"venue"
},
  "geometry": {"coordinates":[8.158277,46.426254],"type":"Point"}
}