{
  "type": "Feature",
  "properties": {
    "iso:country":"CH",
    "sg:address":"Rue Du Ch\u00e2teau D'en Bas 2 1630 Bulle Case Postale 528",
    "sg:city":"Bulle",
    "sg:orig_category":"Fachdetailhandel in Verkaufsr\u00e4umen",
    "sg:phone":"+41 32 910 91 31",
    "sg:postcode":"1630",
    "sg:province":"Fribourg",
    "wof:name":"Optic 2000-horlogerie Von Gunten, Von Gunten Ch.-a. Et Nagel-von Gunten C.",
    "wof:placetype":"venue"
},
  "geometry": {"coordinates":[6.8291797638,47.1021652222],"type":"Point"}
}