{
  "type": "Feature",
  "properties": {
    "iso:country":"CH",
    "sg:address":"Lindenplatz 4",
    "sg:city":"Z\u00fcrich",
    "sg:classifiers":[
        {
            "category":"Education",
            "subcategory":"Library",
            "type":"Public Place"
        }
    ],
    "sg:phone":"+41 12167111",
    "sg:postcode":"8048",
    "sg:province":"Z\u00fcrich",
    "sg:tags":[
        "u",
        "bibliotheken",
        "archive"
    ],
    "wof:name":"Quartierbibliothek Altstetten",
    "wof:placetype":"venue"
},
  "geometry": {"coordinates":[8.485792,47.387249],"type":"Point"}
}