{
  "type": "Feature",
  "properties": {
    "iso:country":"CH",
    "sg:address":"6517",
    "sg:city":"Arbedo",
    "sg:orig_category":"Pensionskassen",
    "sg:phone":"+41 91 857 18 35",
    "sg:postcode":"6517",
    "sg:province":"Ticino",
    "wof:name":"Fondazione Di Previdenza Della Geniobeton Sa",
    "wof:placetype":"venue"
},
  "geometry": {"coordinates":[9.0421895981,46.2133483887],"type":"Point"}
}