{
  "type": "Feature",
  "properties": {
    "addr:full":"Neugass 4 Berneck St. Gallen 9442",
    "addr:housenumber":"4;st.",
    "addr:postcode":"9442",
    "addr:street":"Neugass;Berneck",
    "iso:country":"CH",
    "sg:address":"Neugass 4",
    "sg:city":"Berneck",
    "sg:orig_category":"Detailhandel mit Bekleidung Detailhandel mit Textilien",
    "sg:phone":"+41 71 744 11 85",
    "sg:postcode":"9442",
    "sg:province":"St. Gallen",
    "wof:name":"Kl\u00e4rly M\u00e4tzler Textilien Mercerie",
    "wof:placetype":"venue"
},
  "geometry": {"coordinates":[9.61039,47.425102],"type":"Point"}
}