{
  "type": "Feature",
  "properties": {
    "iso:country":"CH",
    "sg:address":"Im Bungert 15",
    "sg:city":"Wettingen",
    "sg:orig_category":"Vermittlung von Immobilien Verwaltung von Immobilien",
    "sg:postcode":"5430",
    "sg:province":"Aargau",
    "wof:name":"Imoscot Ag Immobilien",
    "wof:placetype":"venue"
},
  "geometry": {"coordinates":[8.3402671814,47.4692459106],"type":"Point"}
}