{
  "type": "Feature",
  "properties": {
    "iso:country":"CH",
    "sg:address":"Engelweg 7",
    "sg:city":"Wauwil",
    "sg:orig_category":"Fahrschulen, Flugschulen",
    "sg:phone":"+41 79 210 78 55",
    "sg:postcode":"6242",
    "sg:province":"Luzern",
    "wof:name":"L\u00e9onard Palmisano Auto-\u00e9cole",
    "wof:placetype":"venue"
},
  "geometry": {"coordinates":[6.5825080872,46.53723526],"type":"Point"}
}