{
  "type": "Feature",
  "properties": {
    "iso:country":"CH",
    "sg:address":"Ennetmooserstrasse 19",
    "sg:city":"Stans",
    "sg:orig_category":"Sonstiges Gesundheitswesen",
    "sg:phone":"+41 77424922",
    "sg:postcode":"6370",
    "sg:province":"Nidwalden",
    "wof:name":"Blutspendezentrum Am Kantonsspital Obwalden",
    "wof:placetype":"venue"
},
  "geometry": {"coordinates":[8.2455673218,46.8891601562],"type":"Point"}
}