{
  "type": "Feature",
  "properties": {
    "iso:country":"CH",
    "sg:address":"Spitalstrasse 23",
    "sg:city":"Wolhusen",
    "sg:orig_category":"RESTAURANTS: TEA-ROOMS",
    "sg:phone":"+41 41 490 14 15",
    "sg:postcode":"6110",
    "sg:province":"Luzern",
    "wof:name":"Tea-room Terasse, Othmar Grossmann",
    "wof:placetype":"venue"
},
  "geometry": {"coordinates":[8.0729112625,47.0675964355],"type":"Point"}
}