{
  "type": "Feature",
  "properties": {
    "iso:country":"CH",
    "sg:address":"Rosenstrasse 19",
    "sg:city":"Dietikon",
    "sg:orig_category":"Sportvereine Ballsport Handball",
    "sg:phone":"+41 55 246 55 78",
    "sg:postcode":"8953",
    "sg:province":"Z\u00fcrich",
    "wof:name":"Handballclub R\u00fcti",
    "wof:placetype":"venue"
},
  "geometry": {"coordinates":[8.9312076569,47.2665061951],"type":"Point"}
}