{
  "type": "Feature",
  "properties": {
    "iso:country":"CH",
    "sg:address":"Reichsgasse 61",
    "sg:city":"Chur",
    "sg:orig_category":"Sonstiger Detailhandel mit Metallwaren, Anstrichmitteln, Glaswaren, Bau U Heimwerkerbedarf",
    "sg:phone":"+41 56 622 77 87",
    "sg:postcode":"7000",
    "sg:province":"Graubunden",
    "wof:name":"Farben-shop Ag",
    "wof:placetype":"venue"
},
  "geometry": {"coordinates":[8.2771215439,47.3543319702],"type":"Point"}
}