{
  "type": "Feature",
  "properties": {
    "iso:country":"CH",
    "sg:address":"Au Village 79",
    "sg:city":"Autigny",
    "sg:orig_category":"Detailhandel mit Waren verschiedener Art, Hauptrichtung Nahrungsmittel",
    "sg:phone":"+41 26 477 12 24",
    "sg:postcode":"1742",
    "sg:province":"Fribourg",
    "wof:name":"Henri Gobet Negociant",
    "wof:placetype":"venue"
},
  "geometry": {"coordinates":[7.0197110176,46.7363739014],"type":"Point"}
}