{
  "type": "Feature",
  "properties": {
    "iso:country":"CH",
    "sg:address":"D'alberti Via 4",
    "sg:city":"Chiasso",
    "sg:orig_category":"Handels-H\u00e4user U Gesellschaften",
    "sg:postcode":"6830",
    "sg:province":"Ticino",
    "wof:name":"B Tools Trading Bv, Haarlem, Succursale Di Chiasso",
    "wof:placetype":"venue"
},
  "geometry": {"coordinates":[9.0249595642,45.8330001831],"type":"Point"}
}