{
  "type": "Feature",
  "properties": {
    "iso:country":"CH",
    "sg:address":"1669",
    "sg:city":"Albeuve",
    "sg:orig_category":"Landesverteidigung, Sozialversicherung \u00d6ffentliche Verwaltung",
    "sg:phone":"+41 26 928 12 68",
    "sg:postcode":"1669",
    "sg:province":"Fribourg",
    "wof:name":"Centre De Protection Civile",
    "wof:placetype":"venue"
},
  "geometry": {"coordinates":[7.0558800697,46.5188217163],"type":"Point"}
}