{
  "type": "Feature",
  "properties": {
    "iso:country":"CH",
    "sg:address":"Route De La Foulaz 21",
    "sg:city":"Chez-le-bart",
    "sg:orig_category":"Druckweiterverarbeitung",
    "sg:phone":"+41 32 835 11 56",
    "sg:postcode":"2025",
    "sg:province":"Neuch\u00e2tel",
    "wof:name":"Philip & Nathalie Gremaud Atelier Du Livre",
    "wof:placetype":"venue"
},
  "geometry": {"coordinates":[6.7849559784,46.9015579224],"type":"Point"}
}