{
  "type": "Feature",
  "properties": {
    "iso:country":"CH",
    "sg:address":"Talacker 35",
    "sg:city":"Z\u00fcrich",
    "sg:orig_category":"Wirtschaftspr\u00fcfung, Steuerberatung U Treuhand",
    "sg:phone":"+41 12111823",
    "sg:postcode":"8001",
    "sg:province":"Z\u00fcrich",
    "wof:name":"Rudolf Bl\u00e4ttler Dipl. B\u00fccherexperte",
    "wof:placetype":"venue"
},
  "geometry": {"coordinates":[8.5353307724,47.3716888428],"type":"Point"}
}