{
  "type": "Feature",
  "properties": {
    "iso:country":"CH",
    "sg:address":"Piazza Del Ponte 9",
    "sg:city":"Mendrisio",
    "sg:orig_category":"Non-Classified Establishments",
    "sg:postcode":"6850",
    "sg:province":"Ticino",
    "wof:name":"Novipharma Sa",
    "wof:placetype":"venue"
},
  "geometry": {"coordinates":[8.9886398315,45.8701286316],"type":"Point"}
}