{
  "type": "Feature",
  "properties": {
    "addr:full":"Bahnhofstrasse 6 Menziken Aargau 5737",
    "addr:housenumber":"6",
    "addr:postcode":"5737",
    "addr:street":"Bahnhofstrasse",
    "iso:country":"CH",
    "sg:address":"Bahnhofstrasse 6",
    "sg:city":"Menziken",
    "sg:orig_category":"Detailhandel mit Brot, Back U S\u00fcsswaren RESTAURANTS: TEA-ROOMS",
    "sg:phone":"+41 27 958 12 59",
    "sg:postcode":"5737",
    "sg:province":"Aargau",
    "wof:name":"B\u00e4ckerei-konditorei Tea-room Imseng Confiserie/backstubenverband Imseng",
    "wof:placetype":"venue"
},
  "geometry": {"coordinates":[7.933673,46.111717],"type":"Point"}
}