{
  "type": "Feature",
  "properties": {
    "iso:country":"CH",
    "sg:address":"Bahnhofplatz/r\u00fctihof",
    "sg:city":"Romanshorn",
    "sg:orig_category":"Sonstige mit der Informatik verbundene T\u00e4tigkeiten",
    "sg:postcode":"8590",
    "sg:province":"Thurgau",
    "wof:name":"Provida Verwaltungs Ag",
    "wof:placetype":"venue"
},
  "geometry": {"coordinates":[9.3779754639,47.5657196045],"type":"Point"}
}