{
  "type": "Feature",
  "properties": {
    "iso:country":"CH",
    "sg:address":"Ried",
    "sg:city":"Gstaad",
    "sg:orig_category":"Mechanische Werkst\u00e4tten",
    "sg:phone":"+41 33 744 20 05",
    "sg:postcode":"3780",
    "sg:province":"Bern",
    "wof:name":"Walter Brand Elektromechanische Werkstatt",
    "wof:placetype":"venue"
},
  "geometry": {"coordinates":[7.2827391624,46.474155426],"type":"Point"}
}