{
  "type": "Feature",
  "properties": {
    "iso:country":"CH",
    "sg:address":"Route De Buix 36",
    "sg:city":"Montignez",
    "sg:orig_category":"Detailhandel mit Waren verschiedener Art, Hauptrichtung Nahrungsmittel",
    "sg:phone":"+41 32 475 56 36",
    "sg:postcode":"2924",
    "sg:province":"Jura",
    "wof:name":"Philippe Vuillaume Alimentation",
    "wof:placetype":"venue"
},
  "geometry": {"coordinates":[7.0585999489,47.4871368408],"type":"Point"}
}