{
  "type": "Feature",
  "properties": {
    "iso:country":"CH",
    "sg:address":"Kreuzmattweg 7",
    "sg:city":"Hochwald",
    "sg:orig_category":"Gymnastik U Fitnesszentren",
    "sg:phone":"+41 61 751 33 39",
    "sg:postcode":"4146",
    "sg:province":"Solothurn",
    "wof:name":"Fitness Studio 5 Hans Rudin & Sohn",
    "wof:placetype":"venue"
},
  "geometry": {"coordinates":[7.6429138184,47.4566917419],"type":"Point"}
}