{
  "type": "Feature",
  "properties": {
    "iso:country":"CH",
    "sg:address":"Gotthardstrasse 62 6438 Ibach. Postfach 254",
    "sg:city":"Ibach",
    "sg:orig_category":"Kantonalbanken",
    "sg:phone":"+41 41 811 55 75",
    "sg:postcode":"6438",
    "sg:province":"Schwyz",
    "wof:name":"Schwyzer Kantonalbank",
    "wof:placetype":"venue"
},
  "geometry": {"coordinates":[8.6436653137,47.0106620789],"type":"Point"}
}