{
  "type": "Feature",
  "properties": {
    "iso:country":"CH",
    "sg:address":"Corso San Gottardo 88",
    "sg:city":"Chiasso",
    "sg:orig_category":"Detailhandel mit B\u00fcchern Detailhandel mit B\u00fcchern, Zeitungen, Schreib U Papeteriewaren",
    "sg:phone":"+41 91 683 10 05",
    "sg:postcode":"6830",
    "sg:province":"Ticino",
    "wof:name":"Leggere Libreria In Chiasso Di Mombelli Edy",
    "wof:placetype":"venue"
},
  "geometry": {"coordinates":[9.02514,45.836613],"type":"Point"}
}