{
  "type": "Feature",
  "properties": {
    "iso:country":"CH",
    "sg:address":"B\u00e4hnlistrasse",
    "sg:city":"Eischoll",
    "sg:orig_category":"Detailhandel mit Waren verschiedener Art, Hauptrichtung Nahrungsmittel",
    "sg:phone":"+41 17133839",
    "sg:postcode":"3943",
    "sg:province":"Valais",
    "wof:name":"Primo H\u00f6fli St.& M.sch\u00fcpfer",
    "wof:placetype":"venue"
},
  "geometry": {"coordinates":[8.5355987549,47.294631958],"type":"Point"}
}