{
  "type": "Feature",
  "properties": {
    "iso:country":"CH",
    "sg:address":"Piazza Grande 13 6600 Locarno. Postfach Caselle Postale 715",
    "sg:city":"Locarno",
    "sg:orig_category":"Herstellung von Schneidwaren U Bestecken Schmieden",
    "sg:phone":"+41 91 751 62 03",
    "sg:postcode":"6601",
    "sg:province":"Ticino",
    "wof:name":"Fabio & Carmen Bianda Coltelleria",
    "wof:placetype":"venue"
},
  "geometry": {"coordinates":[8.7959737778,46.1698722839],"type":"Point"}
}