{
  "type": "Feature",
  "properties": {
    "iso:country":"CH",
    "sg:address":"B\u00e4chenmoosstrasse 15",
    "sg:city":"Hirzel",
    "sg:orig_category":"Grosshandel mit Getr\u00e4nken Grosshandel mit Wein U Spirituosen",
    "sg:phone":"+41 79 419 63 27",
    "sg:postcode":"8816",
    "sg:province":"Z\u00fcrich",
    "wof:name":"Uvicom Sa Weinhandel",
    "wof:placetype":"venue"
},
  "geometry": {"coordinates":[8.6189899445,47.2089653015],"type":"Point"}
}