{
  "type": "Feature",
  "properties": {
    "iso:country":"CH",
    "sg:address":"Chemin Des Clos 110",
    "sg:city":"Aubonne",
    "sg:orig_category":"Unternehmensberatung Wirtschaftspr\u00fcfung, Steuerberatung U Treuhand",
    "sg:phone":"+41 41 630 04 42",
    "sg:postcode":"1170",
    "sg:province":"Vaud",
    "wof:name":"Dr. Balsiger Unternehmensberatung Ag Unternehmensberatung, Treuhandaufgaben Usw",
    "wof:placetype":"venue"
},
  "geometry": {"coordinates":[8.3104372025,46.9823074341],"type":"Point"}
}