{
  "type": "Feature",
  "properties": {
    "iso:country":"CH",
    "sg:address":"Altes Schulhaus",
    "sg:city":"Obergoldbach",
    "sg:orig_category":"Vorschulen, Kinderg\u00e4rten",
    "sg:phone":"+41 31 701 00 27",
    "sg:postcode":"3434",
    "sg:province":"Bern",
    "wof:name":"Kindergarten Landiswil",
    "wof:placetype":"venue"
},
  "geometry": {"coordinates":[7.6799798012,46.9578666687],"type":"Point"}
}