{
  "type": "Feature",
  "properties": {
    "addr:full":"L\u00f6berenstrasse 22 Zug Zug 6300",
    "addr:housenumber":"22",
    "addr:postcode":"6300",
    "addr:street":"Loeberenstrasse;Zug",
    "iso:country":"CH",
    "sg:address":"L\u00f6berenstrasse 22",
    "sg:city":"Zug",
    "sg:orig_category":"Bauschreinerei",
    "sg:phone":"+41 81 416 18 59",
    "sg:postcode":"6300",
    "sg:province":"Zug",
    "wof:name":"Hans Rudolf Heldstab Mechanische Schreinerei",
    "wof:placetype":"venue"
},
  "geometry": {"coordinates":[9.856911,46.826805],"type":"Point"}
}