{
  "type": "Feature",
  "properties": {
    "iso:country":"CH",
    "sg:address":"Murtenstrasse 3",
    "sg:city":"Bern",
    "sg:orig_category":"RESTAURANTS: TEA-ROOMS",
    "sg:phone":"+41 31 382 41 34",
    "sg:postcode":"3008",
    "sg:province":"Bern",
    "wof:name":"Pizza Berna Kaya Mehmet-ali",
    "wof:placetype":"venue"
},
  "geometry": {"coordinates":[7.4273262024,46.9483337402],"type":"Point"}
}