{
  "type": "Feature",
  "properties": {
    "iso:country":"CH",
    "sg:address":"Hirzlistrasse 20",
    "sg:city":"Schmerikon",
    "sg:orig_category":"Non-Classified Establishments",
    "sg:phone":"+41 55 282 17 47",
    "sg:postcode":"8716",
    "sg:province":"St. Gallen",
    "wof:name":"Hermann M\u00fcller Steinhauer",
    "wof:placetype":"venue"
},
  "geometry": {"coordinates":[8.9465370178,47.227596283],"type":"Point"}
}