{
  "type": "Feature",
  "properties": {
    "iso:country":"CH",
    "sg:address":"6242",
    "sg:city":"Wauwil",
    "sg:orig_category":"Primarschulen",
    "sg:phone":"+41 41 980 34 45",
    "sg:postcode":"6242",
    "sg:province":"Luzern",
    "wof:name":"Primarschule",
    "wof:placetype":"venue"
},
  "geometry": {"coordinates":[8.033370018,47.184261322],"type":"Point"}
}