{
  "type": "Feature",
  "properties": {
    "iso:country":"CH",
    "sg:address":"Route Cantonale 30",
    "sg:city":"Conthey",
    "sg:orig_category":"Autospenglereien",
    "sg:phone":"+41 27 346 15 36",
    "sg:postcode":"1964",
    "sg:province":"Valais",
    "wof:name":"Roger & Guy Putallaz Carrosserie De La Morge",
    "wof:placetype":"venue"
},
  "geometry": {"coordinates":[7.308423,46.224464],"type":"Point"}
}