{
  "type": "Feature",
  "properties": {
    "iso:country":"CH",
    "sg:address":"8447",
    "sg:city":"Dachsen",
    "sg:orig_category":"Sportvereine Turnen",
    "sg:phone":"+41 52 659 62 82",
    "sg:postcode":"8447",
    "sg:province":"Z\u00fcrich",
    "wof:name":"Satus-turnverein",
    "wof:placetype":"venue"
},
  "geometry": {"coordinates":[8.6241998672,47.6626281738],"type":"Point"}
}