{
  "type": "Feature",
  "properties": {
    "iso:country":"CH",
    "sg:address":"St. Peterhofstatt 3",
    "sg:city":"Z\u00fcrich",
    "sg:orig_category":"Detailhandel mit B\u00fcchern Detailhandel mit B\u00fcchern, Zeitungen, Schreib U Papeteriewaren",
    "sg:phone":"+41 12126216",
    "sg:postcode":"8001",
    "sg:province":"Z\u00fcrich",
    "wof:name":"M\u00e4rchen Und Sagenb\u00fccher L\u00fcthi Ursina",
    "wof:placetype":"venue"
},
  "geometry": {"coordinates":[8.540511,47.371593],"type":"Point"}
}