{
  "type": "Feature",
  "properties": {
    "iso:country":"CH",
    "sg:address":"Pierre Rue Saint- 10 1700 Freiburg. Postfach",
    "sg:city":"Freiburg",
    "sg:orig_category":"Pensionskassen",
    "sg:phone":"+41 26 347 12 40",
    "sg:postcode":"1700",
    "sg:province":"Fribourg",
    "wof:name":"Fondation Fribourgeoise 'pro Senectute / Pour La Vieillesse'",
    "wof:placetype":"venue"
},
  "geometry": {"coordinates":[7.1555271149,46.8039703369],"type":"Point"}
}