{
  "type": "Feature",
  "properties": {
    "iso:country":"CH",
    "sg:address":"Schlossstrasse 5",
    "sg:city":"Utzenstorf",
    "sg:orig_category":"Sportvereine Ballsport Tennis",
    "sg:phone":"+41 32 665 50 36",
    "sg:postcode":"3427",
    "sg:province":"Bern",
    "wof:name":"Tc Utzenstof",
    "wof:placetype":"venue"
},
  "geometry": {"coordinates":[7.5501999855,47.1367912292],"type":"Point"}
}