{
  "type": "Feature",
  "properties": {
    "iso:country":"CH",
    "sg:address":"M\u00fclistrasse 18",
    "sg:city":"Fehraltorf",
    "sg:orig_category":"Grosshandel mit medizinischen U orthop\u00e4dischen Artikeln Herstellung von medizinischen U chirurgische",
    "sg:phone":"+41 19540204",
    "sg:postcode":"8320",
    "sg:province":"Z\u00fcrich",
    "wof:name":"Cobaco Ag",
    "wof:placetype":"venue"
},
  "geometry": {"coordinates":[8.7428607941,47.3901824951],"type":"Point"}
}