{
  "type": "Feature",
  "properties": {
    "addr:full":"Obere Bahnhofstrasse 28 3714 Frutigen. Postfach 24 Frutigen Bern 3714",
    "addr:housenumber":"28;24",
    "addr:postcode":"3714;3714",
    "addr:street":"Obere Bahnhofstrasse;Postfach",
    "iso:country":"CH",
    "sg:address":"Obere Bahnhofstrasse 28 3714 Frutigen. Postfach 24",
    "sg:city":"Frutigen",
    "sg:orig_category":"Allgemeiner Hochbau Strassenbau",
    "sg:phone":"+41 33 671 13 43",
    "sg:postcode":"3714",
    "sg:province":"Bern",
    "wof:name":"Seeberger & Jordi Ag Bauunternehmung",
    "wof:placetype":"venue"
},
  "geometry": {"coordinates":[7.650012,46.590218],"type":"Point"}
}