{
  "type": "Feature",
  "properties": {
    "iso:country":"CH",
    "sg:address":"Bannwaldweg 15",
    "sg:city":"Igis",
    "sg:orig_category":"Handelsvermittlung U Grosshandel",
    "sg:phone":"+41 81 322 42 38",
    "sg:postcode":"7206",
    "sg:province":"Graubunden",
    "wof:name":"Arno Buschauer Feuerl\u00f6schger\u00e4te",
    "wof:placetype":"venue"
},
  "geometry": {"coordinates":[9.5777454376,46.9472923279],"type":"Point"}
}