{
  "type": "Feature",
  "properties": {
    "addr:full":"Avenue De Savoie 14 Vevey Vaud 1800",
    "addr:housenumber":"14",
    "addr:postcode":"1800",
    "addr:street":"Avenue De Savoie",
    "iso:country":"CH",
    "sg:address":"Avenue De Savoie 14",
    "sg:city":"Vevey",
    "sg:orig_category":"Chemische Reinigung W\u00e4schereien",
    "sg:phone":"+41 21 921 18 46",
    "sg:postcode":"1800",
    "sg:province":"Vaud",
    "wof:name":"Solange Delosea Blanchisserie La Lavandi\u00e8re",
    "wof:placetype":"venue"
},
  "geometry": {"coordinates":[6.83672,46.465939],"type":"Point"}
}