{
  "type": "Feature",
  "properties": {
    "iso:country":"CH",
    "sg:address":"Hauelen 88a 4955 Gondiswil. Postfach",
    "sg:city":"Gondiswil",
    "sg:orig_category":"Instandhaltung U Reparatur von Automobilen",
    "sg:postcode":"4955",
    "sg:province":"Bern",
    "wof:name":"Garage Alternative, Stettler Adrian",
    "wof:placetype":"venue"
},
  "geometry": {"coordinates":[7.8664541245,47.1460189819],"type":"Point"}
}