{
  "type": "Feature",
  "properties": {
    "iso:country":"CH",
    "sg:address":"Oberegger Strasse 36",
    "sg:city":"Berneck",
    "sg:orig_category":"Detailhandel mit Getr\u00e4nken",
    "sg:phone":"+41 71 744 78 04",
    "sg:postcode":"9442",
    "sg:province":"St. Gallen",
    "wof:name":"Alfred Thurnheer Getr\u00e4nke",
    "wof:placetype":"venue"
},
  "geometry": {"coordinates":[9.6038618088,47.4261932373],"type":"Point"}
}