{
  "type": "Feature",
  "properties": {
    "iso:country":"CH",
    "sg:address":"3124",
    "sg:city":"Belpberg",
    "sg:orig_category":"Religi\u00f6se Vereinigungen divers",
    "sg:postcode":"3124",
    "sg:province":"Bern",
    "wof:name":"Cvjm",
    "wof:placetype":"venue"
},
  "geometry": {"coordinates":[7.5252900124,46.8671188354],"type":"Point"}
}