{
  "type": "Feature",
  "properties": {
    "iso:country":"CH",
    "sg:address":"Via Locarno 8",
    "sg:city":"Losone",
    "sg:orig_category":"Tierarztpraxis",
    "sg:phone":"+41 91 792 13 33",
    "sg:postcode":"6616",
    "sg:province":"Ticino",
    "wof:name":"Dott. Med. Vet. Daniele Varini Veterinario",
    "wof:placetype":"venue"
},
  "geometry": {"coordinates":[8.761548996,46.1645507812],"type":"Point"}
}