{
  "type": "Feature",
  "properties": {
    "iso:country":"CH",
    "sg:address":"Sonnenbergstrasse 36",
    "sg:city":"Schwerzenbach",
    "sg:orig_category":"Softwareentwicklung U beratung",
    "sg:postcode":"8603",
    "sg:province":"Z\u00fcrich",
    "wof:name":"Hola Informatik Gmbh",
    "wof:placetype":"venue"
},
  "geometry": {"coordinates":[8.6515779495,47.3849487305],"type":"Point"}
}