{
  "type": "Feature",
  "properties": {
    "addr:full":"Chilestrasse 11 Bonstetten Z\u00fcrich 8906",
    "addr:housenumber":"11",
    "addr:postcode":"8906",
    "addr:street":"Chilestrasse",
    "iso:country":"CH",
    "sg:address":"Chilestrasse 11",
    "sg:city":"Bonstetten",
    "sg:orig_category":"Arztpraxen",
    "sg:phone":"+41 17000452",
    "sg:postcode":"8906",
    "sg:province":"Z\u00fcrich",
    "wof:name":"Dres Med. Kern & Scheuring Aerzte F\u00fcr Allg.medizin Fmh",
    "wof:placetype":"venue"
},
  "geometry": {"coordinates":[8.466865,47.31551],"type":"Point"}
}