{
  "type": "Feature",
  "properties": {
    "iso:country":"CH",
    "sg:address":"6113",
    "sg:city":"Romoos",
    "sg:orig_category":"Primarschulen",
    "sg:phone":"+41 41 480 45 92",
    "sg:postcode":"6113",
    "sg:province":"Luzern",
    "wof:name":"Primarschule",
    "wof:placetype":"venue"
},
  "geometry": {"coordinates":[8.0288896561,47.0113868713],"type":"Point"}
}