{
  "type": "Feature",
  "properties": {
    "iso:country":"CH",
    "sg:address":"Rosenstrasse 8 4127 Birsfelden. Postfach",
    "sg:city":"Birsfelden",
    "sg:orig_category":"Reinigungsgewerbe",
    "sg:postcode":"4127",
    "sg:province":"Basel-Landschaft",
    "wof:name":"Asteam Gmbh",
    "wof:placetype":"venue"
},
  "geometry": {"coordinates":[7.6244449615,47.5563087463],"type":"Point"}
}