{
  "type": "Feature",
  "properties": {
    "iso:country":"CH",
    "sg:address":"Rue De La Ribe 10 2854 Bassecourt Case Postale 326",
    "sg:city":"Bassecourt",
    "sg:orig_category":"Bauspenglerei Sanit\u00e4r, Heizungs U L\u00fcftungsinstallation",
    "sg:phone":"+41 32 426 76 07",
    "sg:postcode":"2854",
    "sg:province":"Jura",
    "wof:name":"Kiener Fils S\u00e0rl Inst.sanitaires & Ferblanterie",
    "wof:placetype":"venue"
},
  "geometry": {"coordinates":[7.248336,47.337963],"type":"Point"}
}