{
  "type": "Feature",
  "properties": {
    "iso:country":"CH",
    "sg:address":"Jungholzstrasse 43 8000 Z\u00fcrich. Postfach 8050 Z\u00fcrich",
    "sg:city":"Zust",
    "sg:orig_category":"Non-Classified Establishments",
    "sg:postcode":"50",
    "wof:name":"Limacher J. Beteiligungs Ag",
    "wof:placetype":"venue"
},
  "geometry": {"coordinates":[8.5439758301,47.4157943726],"type":"Point"}
}