{
  "type": "Feature",
  "properties": {
    "iso:country":"CH",
    "sg:address":"B\u00fcrenstrasse 72",
    "sg:city":"Solothurn",
    "sg:orig_category":"Autospenglereien",
    "sg:phone":"+41 32 622 93 63",
    "sg:postcode":"4500",
    "sg:province":"Solothurn",
    "wof:name":"Hansueli Winz Carrosserie",
    "wof:placetype":"venue"
},
  "geometry": {"coordinates":[7.531503,47.200062],"type":"Point"}
}