{
  "type": "Feature",
  "properties": {
    "iso:country":"CH",
    "sg:address":"9620",
    "sg:city":"Lichtensteig",
    "sg:orig_category":"Vereine Gesang",
    "sg:postcode":"9620",
    "sg:province":"St. Gallen",
    "wof:name":"Reformierter Kirchenchor",
    "wof:placetype":"venue"
},
  "geometry": {"coordinates":[9.0877408981,47.3240470886],"type":"Point"}
}