{
  "type": "Feature",
  "properties": {
    "iso:country":"CH",
    "sg:address":"Morges Avenue De 143",
    "sg:city":"Lausanne",
    "sg:orig_category":"Herstellung von Teilen U Zubeh\u00f6r f\u00fcr Automobile",
    "sg:postcode":"1004",
    "sg:province":"Vaud",
    "wof:name":"Oggenfuss M. + K",
    "wof:placetype":"venue"
},
  "geometry": {"coordinates":[9.6348628998,47.4308128357],"type":"Point"}
}