{
  "type": "Feature",
  "properties": {
    "iso:country":"CH",
    "sg:address":"Stadthausstr. 69-71. 8400 Winterthur. Postfach 571",
    "sg:city":"Winterthur",
    "sg:orig_category":"RESTAURANTS: TEA-ROOMS",
    "sg:postcode":"8401",
    "sg:province":"Z\u00fcrich",
    "wof:name":"Speiserestaurant \u00abdon Quichote\u00bb Segui Ramos Pedro J.",
    "wof:placetype":"venue"
},
  "geometry": {"coordinates":[8.7293672562,47.5001296997],"type":"Point"}
}