{
  "type": "Feature",
  "properties": {
    "iso:country":"CH",
    "sg:address":"Pasteur Ch. Dr-adolphe- 9 1209 Gen\u00e8ve. Postfach",
    "sg:city":"Gen\u00e8ve",
    "sg:orig_category":"Handels-H\u00e4user U Gesellschaften",
    "sg:postcode":"1209",
    "sg:province":"Gen\u00e8ve",
    "wof:name":"Valflo Sa",
    "wof:placetype":"venue"
},
  "geometry": {"coordinates":[6.1279067993,46.2215232849],"type":"Point"}
}