{
  "type": "Feature",
  "properties": {
    "iso:country":"CH",
    "sg:address":"Bahnhofstrasse 50a",
    "sg:city":"Koblenz",
    "sg:orig_category":"Sonstiger Grosshandel",
    "sg:phone":"+41 56 246 15 40",
    "sg:postcode":"5322",
    "sg:province":"Aargau",
    "wof:name":"Knill B. Gmbh",
    "wof:placetype":"venue"
},
  "geometry": {"coordinates":[8.2265977859,47.601108551],"type":"Point"}
}