{
  "type": "Feature",
  "properties": {
    "addr:full":"Schwarztorstrasse 7 3007 Bern. Postfach Bern Bern 3005",
    "addr:housenumber":"7",
    "addr:postcode":"3007;postfach;3005",
    "addr:street":"Schwarztorstrasse",
    "iso:country":"CH",
    "sg:address":"Schwarztorstrasse 7 3007 Bern. Postfach",
    "sg:city":"Bern",
    "sg:orig_category":"Allgemeiner Hoch U Tiefbau",
    "sg:postcode":"3005",
    "sg:province":"Bern",
    "wof:name":"Kapp & Cie Ag Hoch, Tiefbau; Zimmerei U. Schreinerei; Liegenschaften-handel.",
    "wof:placetype":"venue"
},
  "geometry": {"coordinates":[7.436424,46.942738],"type":"Point"}
}