{
  "type": "Feature",
  "properties": {
    "iso:country":"CH",
    "sg:address":"Stafflerstrasse 51",
    "sg:city":"Hermetschwil-staff",
    "sg:orig_category":"Grosshandel mit Getreide, Saatgut U Futtermitteln",
    "sg:phone":"+41 56 633 15 33",
    "sg:postcode":"5626",
    "sg:province":"Aargau",
    "wof:name":"Leo St\u00f6ckli",
    "wof:placetype":"venue"
},
  "geometry": {"coordinates":[8.3443431854,47.3246231079],"type":"Point"}
}