{
  "type": "Feature",
  "properties": {
    "iso:country":"CH",
    "sg:address":"Gewerbestrasse 2",
    "sg:city":"L\u00fctzelfl\u00fch-goldb",
    "sg:orig_category":"Sportvereine Velo Rad-& Motorfahrer-Bund SRB",
    "sg:postcode":"3432",
    "sg:province":"Bern",
    "wof:name":"Rv Ersigen",
    "wof:placetype":"venue"
},
  "geometry": {"coordinates":[7.6845550537,47.0052032471],"type":"Point"}
}