{
  "type": "Feature",
  "properties": {
    "iso:country":"CH",
    "sg:address":"Bahnhofstrasse 3",
    "sg:city":"Bellach",
    "sg:orig_category":"Pensionskassen",
    "sg:postcode":"4512",
    "sg:province":"Solothurn",
    "wof:name":"Bvg-personalvorsorgestiftung Kisag Ag Bellach",
    "wof:placetype":"venue"
},
  "geometry": {"coordinates":[7.4959559441,47.2085609436],"type":"Point"}
}