{
  "type": "Feature",
  "properties": {
    "iso:country":"CH",
    "sg:address":"M\u00fchleweg 17 5034 Suhr. Postfach",
    "sg:city":"Suhr",
    "sg:orig_category":"RESTAURANTS: TEA-ROOMS",
    "sg:postcode":"5034",
    "sg:province":"Aargau",
    "wof:name":"Suhrwide Gmbh Gastgewerbliche Ode \u00e4hnliche Betriebe, Handwerkerbetrieb Usw",
    "wof:placetype":"venue"
},
  "geometry": {"coordinates":[8.0823221207,47.3774375916],"type":"Point"}
}