{
  "type": "Feature",
  "properties": {
    "iso:country":"CH",
    "sg:address":"Fl\u00fcckenstrasse 838",
    "sg:city":"Meisterschwanden",
    "sg:orig_category":"Vermietung U Verpachtung von eigenen Immobilien",
    "sg:postcode":"5616",
    "sg:province":"Aargau",
    "wof:name":"Stadag Ag",
    "wof:placetype":"venue"
},
  "geometry": {"coordinates":[8.2334718704,47.2922706604],"type":"Point"}
}