{
  "type": "Feature",
  "properties": {
    "iso:country":"CH",
    "sg:address":"Rue Des Racettes 51",
    "sg:city":"Onex",
    "sg:orig_category":"G\u00fcterbef\u00f6rderung im Strassenverkehr",
    "sg:phone":"+41 71 455 18 49",
    "sg:postcode":"1213",
    "sg:province":"Gen\u00e8ve",
    "wof:name":"Pege Transport Gmbh",
    "wof:placetype":"venue"
},
  "geometry": {"coordinates":[9.4082813263,47.4878616333],"type":"Point"}
}