{
  "type": "Feature",
  "properties": {
    "iso:country":"CH",
    "sg:address":"Eichhaldenstrasse 9",
    "sg:city":"Wila",
    "sg:orig_category":"Vorschulen, Kinderg\u00e4rten",
    "sg:phone":"+41 52 385 30 55",
    "sg:postcode":"8492",
    "sg:province":"Z\u00fcrich",
    "wof:name":"Kindergarten Eichhalde Frau Hanni Keller",
    "wof:placetype":"venue"
},
  "geometry": {"coordinates":[8.8428888321,47.4209671021],"type":"Point"}
}