{
  "type": "Feature",
  "properties": {
    "iso:country":"CH",
    "sg:address":"Kantonsstrasse 60",
    "sg:city":"Reichenburg",
    "sg:orig_category":"Detailhandel mit Bekleidung",
    "sg:postcode":"8864",
    "sg:province":"Schwyz",
    "wof:name":"Mc Jeans-shop-betriebs Gmbh Reichenburg",
    "wof:placetype":"venue"
},
  "geometry": {"coordinates":[8.979393,47.167912],"type":"Point"}
}