{
  "type": "Feature",
  "properties": {
    "iso:country":"CH",
    "sg:address":"Allmendstr. 23",
    "sg:city":"Turgi",
    "sg:classifiers":[
        {
            "category":"Manufacturing",
            "subcategory":"Wood Products",
            "type":"Manufacturing & Wholesale Goods"
        }
    ],
    "sg:phone":"+41 56 201 08 08",
    "sg:postcode":"5300",
    "sg:province":"Aargau",
    "sg:tags":[
        "professional",
        "furniture"
    ],
    "wof:name":"J. Killer Ag",
    "wof:placetype":"venue"
},
  "geometry": {"coordinates":[8.2606401443,47.4872817993],"type":"Point"}
}