{
  "type": "Feature",
  "properties": {
    "iso:country":"CH",
    "sg:address":"Centre Commercial Riviera",
    "sg:city":"Rennaz",
    "sg:orig_category":"Detailhandel mit Geschenkartikeln U Souvenirs",
    "sg:phone":"+41 21 968 18 63",
    "sg:postcode":"1847",
    "sg:province":"Vaud",
    "wof:name":"Boutiques Shop In The Shop",
    "wof:placetype":"venue"
},
  "geometry": {"coordinates":[6.9189429283,46.3752441406],"type":"Point"}
}