{
  "type": "Feature",
  "properties": {
    "iso:country":"CH",
    "sg:address":"Schwanengasse 8",
    "sg:city":"Bern",
    "sg:orig_category":"Arztpraxen",
    "sg:phone":"+41 31 312 01 26",
    "sg:postcode":"3011",
    "sg:province":"Bern",
    "wof:name":"Dr. Med. Marzia Messerli Spezial\u00e4rztin Fmh",
    "wof:placetype":"venue"
},
  "geometry": {"coordinates":[7.438822,46.946781],"type":"Point"}
}