{
  "type": "Feature",
  "properties": {
    "iso:country":"CH",
    "sg:address":"Zollstrasse 63",
    "sg:city":"Schaan",
    "sg:orig_category":"Mechanische Werkst\u00e4tten",
    "sg:phone":"+423 232 19 48",
    "sg:postcode":"9494",
    "wof:name":"Hans Verling Mechanische Werkst\u00e4tte",
    "wof:placetype":"venue"
},
  "geometry": {"coordinates":[9.4983882904,47.1689834595],"type":"Point"}
}