{
  "type": "Feature",
  "properties": {
    "iso:country":"CH",
    "sg:address":"Place Du Vingt-trois Juin 2 2350 Saignel\u00e9gier. Postfach",
    "sg:city":"Saignel\u00e9gier",
    "sg:orig_category":"Fachdetailhandel mit pharmazeutischen Produkten",
    "sg:phone":"+41 32 951 12 03",
    "sg:postcode":"2350",
    "sg:province":"Jura",
    "wof:name":"Pharmacie Des Franches-montagnes, Ma\u00eetre Dr Jean-michel",
    "wof:placetype":"venue"
},
  "geometry": {"coordinates":[6.9965391159,47.256149292],"type":"Point"}
}