{
  "type": "Feature",
  "properties": {
    "iso:country":"CH",
    "sg:address":"Industriestrasse 10 3110 M\u00fcnsingen. Postfach",
    "sg:city":"M\u00fcnsingen",
    "sg:orig_category":"Pensionskassen",
    "sg:phone":"+41 61 711 73 33",
    "sg:postcode":"3110",
    "sg:province":"Bern",
    "wof:name":"Personalf\u00fcrsorgestiftung Der Firma Petrofer Ag Reinach Bl",
    "wof:placetype":"venue"
},
  "geometry": {"coordinates":[7.589193821,47.4915771484],"type":"Point"}
}