{
  "type": "Feature",
  "properties": {
    "iso:country":"CH",
    "sg:address":"Hauptstrasse",
    "sg:city":"Hemishofen",
    "sg:orig_category":"Grosshandel mit lebenden Tieren",
    "sg:phone":"+41 79 200 47 34",
    "sg:postcode":"8261",
    "sg:province":"Schaffhausen",
    "wof:name":"Walter Kienast Viehhandel",
    "wof:placetype":"venue"
},
  "geometry": {"coordinates":[8.834446907,47.6748771667],"type":"Point"}
}