{
  "type": "Feature",
  "properties": {
    "iso:country":"CH",
    "sg:address":"Steinerstrasse 40",
    "sg:city":"Diessenhofen",
    "sg:orig_category":"Organisationen der Wohlfahrtspflege",
    "sg:phone":"+41 52 657 26 91",
    "sg:postcode":"8253",
    "sg:province":"Thurgau",
    "wof:name":"Caroline Mink Pro Juventute",
    "wof:placetype":"venue"
},
  "geometry": {"coordinates":[8.7603616714,47.685798645],"type":"Point"}
}