{
  "type": "Feature",
  "properties": {
    "iso:country":"CH",
    "sg:address":"Davos Must\u00e9r",
    "sg:city":"Disentis/must\u00e9r",
    "sg:orig_category":"Organisationen des Gesundheitswesen",
    "sg:phone":"+41 81 947 56 37",
    "sg:postcode":"7180",
    "sg:province":"Graubunden",
    "wof:name":"Samariterverein",
    "wof:placetype":"venue"
},
  "geometry": {"coordinates":[8.8597249985,46.7071533203],"type":"Point"}
}