{
  "type": "Feature",
  "properties": {
    "iso:country":"CH",
    "sg:address":"Geerenstrasse 1",
    "sg:city":"Fehraltorf",
    "sg:orig_category":"Nationale Postdienste",
    "sg:phone":"+41 19565111",
    "sg:postcode":"8320",
    "sg:province":"Z\u00fcrich",
    "wof:name":"Die Schweizerische Post",
    "wof:placetype":"venue"
},
  "geometry": {"coordinates":[8.7523946762,47.386013031],"type":"Point"}
}