{
  "type": "Feature",
  "properties": {
    "iso:country":"CH",
    "sg:address":"Chemin Des Baules 8 1268 Begnins. Postfach",
    "sg:city":"Gen\u00e8ve",
    "sg:orig_category":"Detailhandel mit Waren verschiedener Art, Hauptrichtung Nahrungsmittel Grosshandel mit Kaffee, Tee, ",
    "sg:phone":"+41 22 366 67 77",
    "sg:postcode":"1201",
    "sg:province":"Gen\u00e8ve",
    "wof:name":"Afritrade Sa Produits Et Marchandises, Notamm. De Denr\u00e9es Alimentaires Etc.; Im, Export., Commerce",
    "wof:placetype":"venue"
},
  "geometry": {"coordinates":[6.2448878288,46.4421310425],"type":"Point"}
}