{
  "type": "Feature",
  "properties": {
    "iso:country":"CH",
    "sg:address":"Neuhof",
    "sg:city":"Quarten",
    "sg:orig_category":"Sanit\u00e4r, Heizungs U L\u00fcftungsinstallation Sanit\u00e4rinstallation",
    "sg:phone":"+41 81 738 10 67",
    "sg:postcode":"8883",
    "sg:province":"St. Gallen",
    "wof:name":"Merk Ag Quarten",
    "wof:placetype":"venue"
},
  "geometry": {"coordinates":[9.2357254028,47.1068458557],"type":"Point"}
}