{
  "type": "Feature",
  "properties": {
    "iso:country":"CH",
    "sg:address":"Isenrietstr. 20",
    "sg:city":"M\u00f6nchaltorf",
    "sg:classifiers":[
        {
            "category":"Utilities",
            "subcategory":"Telephone",
            "type":"Services"
        }
    ],
    "sg:phone":"+41 62 288 90 60",
    "sg:postcode":"8617",
    "sg:province":"Z\u00fcrich",
    "sg:tags":[
        "telecommunication"
    ],
    "wof:name":"Studer Ag Werk Hard",
    "wof:placetype":"venue"
},
  "geometry": {"coordinates":[7.967441082,47.3531951904],"type":"Point"}
}