{
  "type": "Feature",
  "properties": {
    "iso:country":"CH",
    "sg:address":"Rue Saint-paul 7",
    "sg:city":"Fribourg",
    "sg:orig_category":"Non-Classified Establishments",
    "sg:phone":"+41 26 322 22 67",
    "sg:postcode":"1700",
    "sg:province":"Fribourg",
    "wof:name":"Marguet, Albert",
    "wof:placetype":"venue"
},
  "geometry": {"coordinates":[7.1516690254,46.7988395691],"type":"Point"}
}