{
  "type": "Feature",
  "properties": {
    "iso:country":"CH",
    "sg:address":"Stollbergstrasse 2 6003 Luzern. Postfach",
    "sg:city":"Luzern",
    "sg:orig_category":"Vermietung von Automobilen",
    "sg:postcode":"6003",
    "sg:province":"Luzern",
    "wof:name":"Globo Autohaus Ag Autos; Vermietung. Taxiunternehmen, Usw",
    "wof:placetype":"venue"
},
  "geometry": {"coordinates":[8.2857398987,47.0540428162],"type":"Point"}
}