{
  "type": "Feature",
  "properties": {
    "iso:country":"CH",
    "sg:address":"Via Fabrizia 13",
    "sg:city":"Giubiasco",
    "sg:orig_category":"Bezirks, Sekundar, Realschulen, Oberstufe der Primarschulen",
    "sg:phone":"+41 91 857 13 41",
    "sg:postcode":"6512",
    "sg:province":"Ticino",
    "wof:name":"Scuola Media Cantonale",
    "wof:placetype":"venue"
},
  "geometry": {"coordinates":[9.017327,46.176502],"type":"Point"}
}