{
  "type": "Feature",
  "properties": {
    "addr:full":"Im Glockenacker 9 Z\u00fcrich Z\u00fcrich 8053",
    "addr:housenumber":"9",
    "addr:postcode":"8053",
    "addr:street":"Im Glockenacker",
    "iso:country":"CH",
    "sg:address":"Im Glockenacker 9",
    "sg:city":"Z\u00fcrich",
    "sg:classifiers":[
        {
            "category":"Utilities",
            "subcategory":"Water",
            "type":"Services"
        }
    ],
    "sg:phone":"+41 14220230",
    "sg:postcode":"8053",
    "sg:province":"Z\u00fcrich",
    "sg:tags":[
        "cooler",
        "cooling",
        "plant",
        "air"
    ],
    "wof:name":"Hoffmann & Partner",
    "wof:placetype":"venue"
},
  "geometry": {"coordinates":[8.597146,47.359386],"type":"Point"}
}