{
  "type": "Feature",
  "properties": {
    "iso:country":"CH",
    "sg:address":"Z\u00fcrcherstrasse 145 8952 Schlieren. Postfach",
    "sg:city":"Schlieren",
    "sg:orig_category":"Interessenvertretungen",
    "sg:phone":"+41 71887171",
    "sg:postcode":"8952",
    "sg:province":"Z\u00fcrich",
    "wof:name":"Personalf\u00fcrsorgestiftung Der Braun Ag, Gossau",
    "wof:placetype":"venue"
},
  "geometry": {"coordinates":[9.2568712234,47.4136199951],"type":"Point"}
}