{
  "type": "Feature",
  "properties": {
    "iso:country":"CH",
    "sg:address":"Etzelstrasse 42",
    "sg:city":"Einsiedeln",
    "sg:orig_category":"Herstellung von Metallkonstruktionen Mechanik",
    "sg:phone":"+41 55 412 17 51",
    "sg:postcode":"8840",
    "sg:province":"Schwyz",
    "wof:name":"Schlosserei Sch\u00f6nb\u00e4chler",
    "wof:placetype":"venue"
},
  "geometry": {"coordinates":[8.7571220398,47.1396789551],"type":"Point"}
}