{
  "type": "Feature",
  "properties": {
    "iso:country":"CH",
    "sg:address":"Glarnerstrasse 2",
    "sg:city":"Siebnen",
    "sg:orig_category":"Herstellung von sonstigen elektrischen Ausr\u00fcstungen",
    "sg:phone":"+41 55 440 31 61",
    "sg:postcode":"8854",
    "sg:province":"Schwyz",
    "wof:name":"Jowetronic Josef Wessner Elektronik-handel",
    "wof:placetype":"venue"
},
  "geometry": {"coordinates":[8.8974123001,47.1744499207],"type":"Point"}
}