{
  "type": "Feature",
  "properties": {
    "iso:country":"CH",
    "sg:address":"Schulhausstrasse",
    "sg:city":"Obergerlafingen",
    "sg:orig_category":"Primarschulen",
    "sg:phone":"+41 32 675 01 40",
    "sg:postcode":"4564",
    "sg:province":"Bern",
    "wof:name":"Primarschule",
    "wof:placetype":"venue"
},
  "geometry": {"coordinates":[7.5881547928,47.162815094],"type":"Point"}
}