{
  "type": "Feature",
  "properties": {
    "addr:full":"Via Degli Orti 5 Losone Ticino 6616",
    "addr:housenumber":"5",
    "addr:postcode":"6616",
    "addr:street":"Via Degli Orti",
    "iso:country":"CH",
    "sg:address":"Via Degli Orti 5",
    "sg:city":"Losone",
    "sg:orig_category":"Bauspenglerei Dachdeckerei",
    "sg:phone":"+41 91 791 48 04",
    "sg:postcode":"6616",
    "sg:province":"Ticino",
    "wof:name":"Hans Blumenstein Imp.lattoniere & Tetti Piani",
    "wof:placetype":"venue"
},
  "geometry": {"coordinates":[8.759261,46.16761],"type":"Point"}
}