{
  "type": "Feature",
  "properties": {
    "iso:country":"CH",
    "sg:address":"Rainmattstrasse 93",
    "sg:city":"Anglikon",
    "sg:orig_category":"Werbevermittlung",
    "sg:phone":"+41 56 611 03 05",
    "sg:postcode":"5611",
    "sg:province":"Aargau",
    "wof:name":"Externa Media Ag Aussenwerbung",
    "wof:placetype":"venue"
},
  "geometry": {"coordinates":[8.2666540146,47.3636169434],"type":"Point"}
}