{
  "type": "Feature",
  "properties": {
    "addr:full":"Via Rodr\u00e9e 2 Massagno Ticino 6900",
    "addr:housenumber":"2",
    "addr:postcode":"6900",
    "addr:street":"Via Rodre\u0301E",
    "iso:country":"CH",
    "sg:address":"Via Rodr\u00e9e 2",
    "sg:city":"Massagno",
    "sg:orig_category":"Architekturb\u00fcros",
    "sg:phone":"+41 91 921 06 56",
    "sg:postcode":"6900",
    "sg:province":"Ticino",
    "wof:name":"Oscar Hofmann Studio D'architettura",
    "wof:placetype":"venue"
},
  "geometry": {"coordinates":[8.950168,46.013149],"type":"Point"}
}