{
  "type": "Feature",
  "properties": {
    "iso:country":"CH",
    "sg:address":"Chrummacherstr. 3",
    "sg:city":"Geroldswil",
    "sg:classifiers":[
        {
            "category":"Professional",
            "subcategory":"Engineering",
            "type":"Services"
        }
    ],
    "sg:phone":"+41 4117493060",
    "sg:postcode":"8954",
    "sg:province":"Z\u00fcrich",
    "sg:tags":[
        "machine",
        "-",
        "mechanical"
    ],
    "wof:name":"Mechafin Ag",
    "wof:placetype":"venue"
},
  "geometry": {"coordinates":[8.417263031,47.4178543091],"type":"Point"}
}