{
  "type": "Feature",
  "properties": {
    "iso:country":"CH",
    "sg:address":"Rosengartenstrasse 18",
    "sg:city":"Rothenburg",
    "sg:orig_category":"Detailhandel mit Metallwaren, Anstrichmitteln, Glaswaren, Bau U Heimwerkerbedarf",
    "sg:phone":"+41 41 281 21 80",
    "sg:postcode":"6023",
    "sg:province":"Luzern",
    "wof:name":"Schnider",
    "wof:placetype":"venue"
},
  "geometry": {"coordinates":[8.2618169785,47.0997962952],"type":"Point"}
}