{
  "type": "Feature",
  "properties": {
    "iso:country":"CH",
    "sg:address":"Europe Promenade De L' 11",
    "sg:city":"Gen\u00e8ve",
    "sg:orig_category":"Non-Classified Establishments",
    "sg:postcode":"1203",
    "sg:province":"Gen\u00e8ve",
    "wof:name":"Coffee Land, G\u00dcrer",
    "wof:placetype":"venue"
},
  "geometry": {"coordinates":[6.1226501465,46.208190918],"type":"Point"}
}