{
  "type": "Feature",
  "properties": {
    "addr:full":"3233 Tschugg Bern 3233",
    "addr:postcode":"3233;3233",
    "addr:street":"Bern",
    "iso:country":"CH",
    "sg:address":"3233",
    "sg:city":"Tschugg",
    "sg:orig_category":"Betrieb U technische Hilfsdienste des Kultur U Unterhaltungswesens",
    "sg:postcode":"3233",
    "sg:province":"Bern",
    "wof:name":"Fondation Moradpour Patrick",
    "wof:placetype":"venue"
},
  "geometry": {"coordinates":[7.0739,47.02784],"type":"Point"}
}