{
  "type": "Feature",
  "properties": {
    "iso:country":"CH",
    "sg:address":"Neugutstrasse 21 8102 Oberengstringen. Postfach",
    "sg:city":"Oberengstringen",
    "sg:orig_category":"Herstellung von Metallkonstruktionen Schlossereien",
    "sg:phone":"+41 71 923 23 51",
    "sg:postcode":"8102",
    "sg:province":"Z\u00fcrich",
    "wof:name":"Wehrli Metallbau Ag",
    "wof:placetype":"venue"
},
  "geometry": {"coordinates":[9.040725708,47.4559822083],"type":"Point"}
}