{
  "type": "Feature",
  "properties": {
    "iso:country":"CH",
    "sg:address":"Noyer Girod 1",
    "sg:city":"Etoy",
    "sg:orig_category":"Autotransporte international Frachtumschlag",
    "sg:phone":"+41 22 342 42 43",
    "sg:postcode":"1163",
    "sg:province":"Vaud",
    "wof:name":"Tz Romandie Sa Transports",
    "wof:placetype":"venue"
},
  "geometry": {"coordinates":[6.129517,46.183971],"type":"Point"}
}