{
  "type": "Feature",
  "properties": {
    "iso:country":"CH",
    "sg:address":"Stockhornweg 3",
    "sg:city":"Uetendorf",
    "sg:orig_category":"Mechanik",
    "sg:phone":"+41 33 345 10 94",
    "sg:postcode":"3661",
    "sg:province":"Bern",
    "wof:name":"Walter Aegerter",
    "wof:placetype":"venue"
},
  "geometry": {"coordinates":[7.5961999893,46.776638031],"type":"Point"}
}