{
  "type": "Feature",
  "properties": {
    "iso:country":"CH",
    "sg:address":"Chemin Des Ormeaux 18",
    "sg:city":"Epalinges",
    "sg:orig_category":"Fotografische Laboratorien",
    "sg:phone":"+41 21 652 22 45",
    "sg:postcode":"1066",
    "sg:province":"Vaud",
    "wof:name":"Colorama Laboratoire Photographique",
    "wof:placetype":"venue"
},
  "geometry": {"coordinates":[6.6534118652,46.5445976257],"type":"Point"}
}