{
  "type": "Feature",
  "properties": {
    "iso:country":"CH",
    "sg:address":"Grosserstrasse 4",
    "sg:city":"Gross",
    "sg:orig_category":"Organisationen des Gesundheitswesen",
    "sg:postcode":"8841",
    "sg:province":"Schwyz",
    "wof:name":"Samariterverein Einsiedeln",
    "wof:placetype":"venue"
},
  "geometry": {"coordinates":[8.7744340897,47.1225547791],"type":"Point"}
}