{
  "type": "Feature",
  "properties": {
    "iso:country":"CH",
    "sg:address":"Eichirebenweg 21",
    "sg:city":"Sarmenstorf",
    "sg:orig_category":"Allgemeiner Hoch U Tiefbau",
    "sg:postcode":"5614",
    "sg:province":"Aargau",
    "wof:name":"Bauleitungsb\u00fcro Joller Martin",
    "wof:placetype":"venue"
},
  "geometry": {"coordinates":[8.254356,47.316231],"type":"Point"}
}