{
  "type": "Feature",
  "properties": {
    "iso:country":"CH",
    "sg:address":"Gerbergasse 30 4001 Basel. Postfach",
    "sg:city":"Basel",
    "sg:orig_category":"Erbringung von Dienstleistungen f\u00fcr Unternehmen",
    "sg:postcode":"4001",
    "sg:province":"Basel-Stadt",
    "wof:name":"K\u00fcnzler Andreas",
    "wof:placetype":"venue"
},
  "geometry": {"coordinates":[8.2025403976,46.7372512817],"type":"Point"}
}