{
  "type": "Feature",
  "properties": {
    "iso:country":"CH",
    "sg:address":"Feldstrasse 129",
    "sg:city":"Z\u00fcrich",
    "sg:orig_category":"Herstellung von sonstigen Produkten aus nichtmetallischen Mineralien",
    "sg:phone":"+41 12913946",
    "sg:postcode":"8004",
    "sg:province":"Z\u00fcrich",
    "wof:name":"Petrovic Dragan Und Ostojic Miloje",
    "wof:placetype":"venue"
},
  "geometry": {"coordinates":[8.5242128372,47.379863739],"type":"Point"}
}