{
  "type": "Feature",
  "properties": {
    "iso:country":"CH",
    "sg:address":"Tramstrasse 57 5034 Suhr. Postfach",
    "sg:city":"Suhr",
    "sg:orig_category":"Fachdetailhandel in Verkaufsr\u00e4umen Fotografische Ateliers",
    "sg:phone":"+41 62 842 53 18",
    "sg:postcode":"5034",
    "sg:province":"Aargau",
    "wof:name":"Foto-video Studio Mk F. B\u00f6niger",
    "wof:placetype":"venue"
},
  "geometry": {"coordinates":[8.0759716034,47.3787384033],"type":"Point"}
}