{
  "type": "Feature",
  "properties": {
    "iso:country":"CH",
    "sg:address":"Hauptstrasse 62",
    "sg:city":"Kriegstetten",
    "sg:orig_category":"RESTAURANTS: TEA-ROOMS",
    "sg:postcode":"4566",
    "sg:province":"Solothurn",
    "wof:name":"Ettlin Eva",
    "wof:placetype":"venue"
},
  "geometry": {"coordinates":[7.5979242325,47.1745262146],"type":"Point"}
}