{
  "type": "Feature",
  "properties": {
    "iso:country":"CH",
    "sg:address":"Baarerstrasse 98",
    "sg:city":"Zug",
    "sg:orig_category":"Softwareentwicklung U beratung",
    "sg:phone":"+41 41 766 11 99",
    "sg:postcode":"6300",
    "sg:province":"Zug",
    "wof:name":"Smart Solutions Ag",
    "wof:placetype":"venue"
},
  "geometry": {"coordinates":[8.5185146332,47.1786804199],"type":"Point"}
}