{
  "type": "Feature",
  "properties": {
    "iso:country":"CH",
    "sg:address":"Wyler",
    "sg:city":"Diemtigen",
    "sg:orig_category":"Sonstiges Versicherungsgewerbe",
    "sg:phone":"+41 34 431 16 69",
    "sg:postcode":"3754",
    "sg:province":"Bern",
    "wof:name":"Emmentalische Mobiliarversich. Bezirksagent.peter Zimmermann",
    "wof:placetype":"venue"
},
  "geometry": {"coordinates":[7.797205925,47.0447731018],"type":"Point"}
}