{
  "type": "Feature",
  "properties": {
    "iso:country":"CH",
    "sg:address":"Forchstrasse 163",
    "sg:city":"Z\u00fcrich",
    "sg:orig_category":"Detailhandel mit Waren verschiedener Art, Hauptrichtung Nahrungsmittel",
    "sg:phone":"+41 14228645",
    "sg:postcode":"8032",
    "sg:province":"Z\u00fcrich",
    "wof:name":"Pick Pay Partner Werner Ruf",
    "wof:placetype":"venue"
},
  "geometry": {"coordinates":[8.5651302338,47.3604774475],"type":"Point"}
}