{
  "type": "Feature",
  "properties": {
    "iso:country":"CH",
    "sg:address":"Vingt-quatre-janvier Av. 4 1003 Lausanne. Postfach",
    "sg:city":"Lausanne",
    "sg:orig_category":"RESTAURANTS: TEA-ROOMS",
    "sg:phone":"+41 62 822 58 40",
    "sg:postcode":"1003",
    "sg:province":"Vaud",
    "wof:name":"Zetti Ag",
    "wof:placetype":"venue"
},
  "geometry": {"coordinates":[8.0637722015,47.3899002075],"type":"Point"}
}