{
  "type": "Feature",
  "properties": {
    "iso:country":"CH",
    "sg:address":"Route Des Layeux 1884 Villars-sur-ollon Case Postale 210",
    "sg:city":"Villars-sur-ollon",
    "sg:orig_category":"HOTELS: MIT RESTAURANT Kongress- and Tagungshotels mit Restaurant",
    "sg:phone":"+41 24 492 37 21",
    "sg:postcode":"1884",
    "sg:province":"Vaud",
    "wof:name":"Eurotel Victoria",
    "wof:placetype":"venue"
},
  "geometry": {"coordinates":[7.1578841209,46.3474845886],"type":"Point"}
}