{
  "type": "Feature",
  "properties": {
    "iso:country":"CH",
    "sg:address":"H\u00fcbeli",
    "sg:city":"Huttwil",
    "sg:orig_category":"Detailhandel mit Sportartikeln",
    "sg:phone":"+41 62 962 13 15",
    "sg:postcode":"4950",
    "sg:province":"Bern",
    "wof:name":"Josef Krieger Skiservice",
    "wof:placetype":"venue"
},
  "geometry": {"coordinates":[7.8617291451,47.1055755615],"type":"Point"}
}