{
  "type": "Feature",
  "properties": {
    "iso:country":"CH",
    "sg:address":"Laubeggstrasse 22 3000 Bern. Postfach",
    "sg:city":"Bern",
    "sg:orig_category":"Sonstige Hilfs U Nebent\u00e4tigkeiten f\u00fcr die Schiffahrt",
    "sg:postcode":"3005",
    "sg:province":"Bern",
    "wof:name":"Bernische Hafenbau Ag",
    "wof:placetype":"venue"
},
  "geometry": {"coordinates":[7.4624729156,46.9514122009],"type":"Point"}
}