{
  "type": "Feature",
  "properties": {
    "iso:country":"CH",
    "sg:address":"Schachenstrasse",
    "sg:city":"Winznau",
    "sg:orig_category":"Herstellung von Kunststoffwaren",
    "sg:phone":"+41 62 295 40 41",
    "sg:postcode":"4652",
    "sg:province":"Solothurn",
    "wof:name":"Stucortec Ag Korrosionsschutz-industrie",
    "wof:placetype":"venue"
},
  "geometry": {"coordinates":[7.9285821915,47.3597946167],"type":"Point"}
}