{
  "type": "Feature",
  "properties": {
    "iso:country":"CH",
    "sg:address":"Chemin Des M\u00fbriers 7",
    "sg:city":"Orbe",
    "sg:orig_category":"Detailhandel mit Waren verschiedener Art, Hauptrichtung Nahrungsmittel Handelsvermittlung U Grosshan",
    "sg:phone":"+41 24 441 40 91",
    "sg:postcode":"1350",
    "sg:province":"Vaud",
    "wof:name":"Ordis",
    "wof:placetype":"venue"
},
  "geometry": {"coordinates":[6.5346598625,46.7337532043],"type":"Point"}
}