{
  "type": "Feature",
  "properties": {
    "iso:country":"CH",
    "sg:address":"Winterthurerstrasse 4 8370 Sirnach. Postfach",
    "sg:city":"Sirnach",
    "sg:orig_category":"Versicherungen Generalagenturen",
    "sg:phone":"+41 17407077",
    "sg:postcode":"8370",
    "sg:province":"Thurgau",
    "wof:name":"Die Mobiliar Versicherungen & Vorsorge",
    "wof:placetype":"venue"
},
  "geometry": {"coordinates":[8.4023628235,47.4048042297],"type":"Point"}
}