{
  "type": "Feature",
  "properties": {
    "iso:country":"CH",
    "sg:address":"Langenl\u00e4ngenweg 14",
    "sg:city":"Riehen",
    "sg:orig_category":"Bezirks, Sekundar, Realschulen, Oberstufe der Primarschulen",
    "sg:phone":"+41 61 606 91 90",
    "sg:postcode":"4125",
    "sg:province":"Basel-Stadt",
    "wof:name":"Realschule Hebelschulhaus",
    "wof:placetype":"venue"
},
  "geometry": {"coordinates":[7.635293,47.572361],"type":"Point"}
}