{
  "type": "Feature",
  "properties": {
    "addr:full":"Spisergasse 28 St.gallen St. Gallen 9000",
    "addr:housenumber":"28",
    "addr:postcode":"9000",
    "addr:street":"Spisergasse",
    "iso:country":"CH",
    "sg:address":"Spisergasse 28",
    "sg:city":"St.gallen",
    "sg:orig_category":"Arztpraxen",
    "sg:phone":"+41 71 228 33 33",
    "sg:postcode":"9000",
    "sg:province":"St. Gallen",
    "wof:name":"Dr.med. Reto Widrig Spezialarzt Fmh",
    "wof:placetype":"venue"
},
  "geometry": {"coordinates":[9.378271,47.424492],"type":"Point"}
}