{
  "type": "Feature",
  "properties": {
    "iso:country":"CH",
    "sg:address":"Zollikerstrasse 172",
    "sg:city":"Z\u00fcrich",
    "sg:orig_category":"Museen",
    "sg:phone":"+41 33 243 30 38",
    "sg:postcode":"8008",
    "sg:province":"Z\u00fcrich",
    "wof:name":"Sammlung Im Obersteg",
    "wof:placetype":"venue"
},
  "geometry": {"coordinates":[7.671875,46.7284507751],"type":"Point"}
}