{
  "type": "Feature",
  "properties": {
    "iso:country":"CH",
    "sg:address":"Juraweg 47",
    "sg:city":"Rothrist",
    "sg:orig_category":"Herstellung von Holzstoff, Papier, Karton U Pappe Herstellung von Schreibwaren U B\u00fcrobedarf aus Papi",
    "sg:phone":"+41 62 794 10 21",
    "sg:postcode":"4852",
    "sg:province":"Aargau",
    "wof:name":"Pletscher Ag",
    "wof:placetype":"venue"
},
  "geometry": {"coordinates":[7.8720040321,47.3057632446],"type":"Point"}
}