{
  "type": "Feature",
  "properties": {
    "iso:country":"CH",
    "sg:address":"Chemin Neuf 59",
    "sg:city":"Pr\u00e9verenges",
    "sg:orig_category":"Detailhandel mit Waren verschiedener Art, Hauptrichtung Nahrungsmittel",
    "sg:phone":"+41 21 802 37 62",
    "sg:postcode":"1028",
    "sg:province":"Vaud",
    "wof:name":"Giuseppe Di Pasquale Commerce D'alimentation",
    "wof:placetype":"venue"
},
  "geometry": {"coordinates":[6.534268856,46.5117034912],"type":"Point"}
}