{
  "type": "Feature",
  "properties": {
    "iso:country":"CH",
    "sg:address":"Konservenstrasse 620",
    "sg:city":"Hallau",
    "sg:orig_category":"Herstellung von \u00d6fen U Brennern Verlegen von Fliesen U Platten",
    "sg:phone":"+41 52 681 16 61",
    "sg:postcode":"8215",
    "sg:province":"Schaffhausen",
    "wof:name":"Schmucki Meinrad",
    "wof:placetype":"venue"
},
  "geometry": {"coordinates":[8.4646530151,47.6951217651],"type":"Point"}
}