{
  "type": "Feature",
  "properties": {
    "iso:country":"CH",
    "sg:address":"Birmensdorferstrasse 28",
    "sg:city":"Urdorf",
    "sg:orig_category":"Fernmeldedienste",
    "sg:phone":"+41 17773777",
    "sg:postcode":"8902",
    "sg:province":"Z\u00fcrich",
    "wof:name":"5net Ag",
    "wof:placetype":"venue"
},
  "geometry": {"coordinates":[8.4182882309,47.3918380737],"type":"Point"}
}