{
  "type": "Feature",
  "properties": {
    "iso:country":"CH",
    "sg:address":"Rue Du Bugnon 46",
    "sg:city":"Lausanne",
    "sg:orig_category":"Kantonalbanken",
    "sg:phone":"+41 21 323 43 57",
    "sg:postcode":"1011",
    "sg:province":"Vaud",
    "wof:name":"Banque Cantonale Vaudoise",
    "wof:placetype":"venue"
},
  "geometry": {"coordinates":[6.6420121193,46.5255851746],"type":"Point"}
}