{
  "type": "Feature",
  "properties": {
    "addr:full":"Rheinstrasse 69c Frenkendorf Basel-Landschaft 4402",
    "addr:housenumber":"69c",
    "addr:postcode":"4402",
    "addr:street":"Rheinstrasse",
    "iso:country":"CH",
    "sg:address":"Rheinstrasse 69c",
    "sg:city":"Frenkendorf",
    "sg:orig_category":"Autolackierereien Autospenglereien",
    "sg:phone":"+41 62 758 29 28",
    "sg:postcode":"4402",
    "sg:province":"Basel-Landschaft",
    "wof:name":"Albert Kull Carrosserie & Spritzwerk",
    "wof:placetype":"venue"
},
  "geometry": {"coordinates":[7.962536,47.230709],"type":"Point"}
}