{
  "type": "Feature",
  "properties": {
    "iso:country":"CH",
    "sg:address":"Badenerstrasse 15",
    "sg:city":"Dietikon",
    "sg:orig_category":"Sonstige Institutionen des Sozialwesens ohne Beherbergung",
    "sg:phone":"+41 62 771 11 24",
    "sg:postcode":"8953",
    "sg:province":"Z\u00fcrich",
    "wof:name":"La Leche Liga Schweiz",
    "wof:placetype":"venue"
},
  "geometry": {"coordinates":[8.1795949936,47.2371101379],"type":"Point"}
}