{
  "type": "Feature",
  "properties": {
    "iso:country":"CH",
    "sg:address":"Stadacherstrasse 46",
    "sg:city":"Fehraltorf",
    "sg:orig_category":"Unternehmensberatung Wirtschaftspr\u00fcfung, Steuerberatung U Treuhand",
    "sg:phone":"+41 19550242",
    "sg:postcode":"8320",
    "sg:province":"Z\u00fcrich",
    "wof:name":"Treuhandb\u00fcro Tr\u00fcb Jeannette",
    "wof:placetype":"venue"
},
  "geometry": {"coordinates":[8.7563810349,47.3835945129],"type":"Point"}
}