{
  "type": "Feature",
  "properties": {
    "iso:country":"CH",
    "sg:address":"Rue Mo\u00efse-marcinhes 1",
    "sg:city":"Meyrin",
    "sg:orig_category":"Flavourings, Aromas",
    "sg:phone":"+41 22 782 00 77",
    "sg:postcode":"1217",
    "sg:province":"Gen\u00e8ve",
    "wof:name":"R.-l. Dougoud S.a.",
    "wof:placetype":"venue"
},
  "geometry": {"coordinates":[6.0638418198,46.2237625122],"type":"Point"}
}