{
  "type": "Feature",
  "properties": {
    "iso:country":"CH",
    "sg:address":"Schaffhauserstrasse 21",
    "sg:city":"Z\u00fcrich",
    "sg:orig_category":"W\u00e4schereien",
    "sg:phone":"+41 13629977",
    "sg:postcode":"8006",
    "sg:province":"Z\u00fcrich",
    "wof:name":"Gisella Macher W\u00e4scherei",
    "wof:placetype":"venue"
},
  "geometry": {"coordinates":[8.5388755798,47.3896446228],"type":"Point"}
}