{
  "type": "Feature",
  "properties": {
    "iso:country":"CH",
    "sg:address":"7457",
    "sg:city":"Bivio",
    "sg:orig_category":"Maler U Glasergewerbe Malerei",
    "sg:phone":"+41 81 684 52 55",
    "sg:postcode":"7457",
    "sg:province":"Graubunden",
    "wof:name":"Rizzi & S\u00f6hne",
    "wof:placetype":"venue"
},
  "geometry": {"coordinates":[9.6504049301,46.4682044983],"type":"Point"}
}