{
  "type": "Feature",
  "properties": {
    "iso:country":"CH",
    "sg:address":"Im Bretscha 6",
    "sg:city":"Schaan",
    "sg:classifiers":[
        {
            "category":"Personal",
            "subcategory":"Piercing",
            "type":"Services"
        }
    ],
    "sg:phone":"+41 79 404 80 23",
    "sg:postcode":"9494",
    "sg:tags":[
        "tattoo"
    ],
    "wof:name":"Tattoo Steve",
    "wof:placetype":"venue"
},
  "geometry": {"coordinates":[9.509762764,47.167842865],"type":"Point"}
}