{
  "type": "Feature",
  "properties": {
    "iso:country":"CH",
    "sg:address":"Bleicherweg 62",
    "sg:city":"Z\u00fcrich",
    "sg:orig_category":"Interessenvertretungen",
    "sg:postcode":"8002",
    "sg:province":"Z\u00fcrich",
    "wof:name":"Gesellschaft F\u00fcr Angewandte Oelhydraulik Und Pneumatik",
    "wof:placetype":"venue"
},
  "geometry": {"coordinates":[8.5334177017,47.3670578003],"type":"Point"}
}