{
  "type": "Feature",
  "properties": {
    "iso:country":"CH",
    "sg:address":"W\u00fcrzenbachmatte 35",
    "sg:city":"Luzern",
    "sg:orig_category":"Non-Classified Establishments",
    "sg:postcode":"6006",
    "sg:province":"Luzern",
    "wof:name":"Jolliet Schaustellerbetriebe Gmbh",
    "wof:placetype":"venue"
},
  "geometry": {"coordinates":[8.3492107391,47.0567855835],"type":"Point"}
}