{
  "type": "Feature",
  "properties": {
    "iso:country":"CH",
    "sg:address":"Gen\u00e8ve Rue De 91",
    "sg:city":"Th\u00f4nex",
    "sg:orig_category":"Sonstiger Grosshandel",
    "sg:postcode":"1226",
    "sg:province":"Gen\u00e8ve",
    "wof:name":"Alfal Consultants Sa",
    "wof:placetype":"venue"
},
  "geometry": {"coordinates":[6.1999049187,46.1936073303],"type":"Point"}
}