{
  "type": "Feature",
  "properties": {
    "iso:country":"CH",
    "sg:address":"La Brinaz",
    "sg:city":"Valeyres-montagny",
    "sg:orig_category":"Herstellung von Duft U K\u00f6rperpflegemitteln",
    "sg:postcode":"1441",
    "sg:province":"Vaud",
    "wof:name":"News Form, St\u00e9phanie Vauthey",
    "wof:placetype":"venue"
},
  "geometry": {"coordinates":[6.6185297966,46.7946014404],"type":"Point"}
}