{
  "type": "Feature",
  "properties": {
    "iso:country":"CH",
    "sg:address":"Unterer Lebernweg 20",
    "sg:city":"Nunningen",
    "sg:orig_category":"Sportvereine Sch\u00fctzen",
    "sg:postcode":"4208",
    "sg:province":"Solothurn",
    "wof:name":"Freisch\u00fctzen Wasen",
    "wof:placetype":"venue"
},
  "geometry": {"coordinates":[7.7976498604,47.0435600281],"type":"Point"}
}