{
  "type": "Feature",
  "properties": {
    "iso:country":"CH",
    "sg:address":"3986",
    "sg:city":"Ried-m\u00f6rel",
    "sg:classifiers":[
        {
            "category":"Restaurant",
            "type":"Food & Drink"
        }
    ],
    "sg:phone":"+41 41 660 15 91",
    "sg:postcode":"3986",
    "sg:province":"Valais",
    "wof:name":"Restaurant Alpenblick",
    "wof:placetype":"venue"
},
  "geometry": {"coordinates":[8.2812299728,46.8747406006],"type":"Point"}
}