{
  "type": "Feature",
  "properties": {
    "addr:full":"Via Renera Gaggio Vernate Ticino 6992",
    "addr:postcode":"6992",
    "addr:street":"Via Renera Gaggio;Ticino",
    "iso:country":"CH",
    "sg:address":"Via Renera Gaggio",
    "sg:city":"Vernate",
    "sg:orig_category":"Architektur U Ingenieurb\u00fcros",
    "sg:phone":"+41 79 230 05 06",
    "sg:postcode":"6992",
    "sg:province":"Ticino",
    "wof:name":"Orler Graziano Sie Studio D'ingeneria Elettro",
    "wof:placetype":"venue"
},
  "geometry": {"coordinates":[8.887973,45.995098],"type":"Point"}
}