{
  "type": "Feature",
  "properties": {
    "iso:country":"CH",
    "sg:address":"Piazza Grande 43",
    "sg:city":"Giubiasco",
    "sg:orig_category":"Malerei Tapeziererei",
    "sg:postcode":"6512",
    "sg:province":"Ticino",
    "wof:name":"Fratelli Manighetti Sagl Impresa Pittura",
    "wof:placetype":"venue"
},
  "geometry": {"coordinates":[9.0109062195,46.1702575684],"type":"Point"}
}