{
  "type": "Feature",
  "properties": {
    "iso:country":"CH",
    "sg:address":"Industriestrasse 15",
    "sg:city":"Safnern",
    "sg:orig_category":"Herstellung von elektrischen Lampen U Leuchten Ingenieurb\u00fcros Elektro",
    "sg:phone":"+41 32 357 12 20",
    "sg:postcode":"2553",
    "sg:province":"Bern",
    "wof:name":"Geubbelmans Engineering S\u00e0rl",
    "wof:placetype":"venue"
},
  "geometry": {"coordinates":[7.3329648972,47.156047821],"type":"Point"}
}