{
  "type": "Feature",
  "properties": {
    "iso:country":"CH",
    "sg:address":"Alte Bernstrasse 10",
    "sg:city":"Aegerten",
    "sg:orig_category":"Handel mit Motorr\u00e4dern, Teilen U Zubeh\u00f6r Instandhaltung U Reparatur von Motorr\u00e4dern",
    "sg:phone":"+41 32 730 18 18",
    "sg:postcode":"2558",
    "sg:province":"Bern",
    "wof:name":"Grandjean Diffusion Sa V\u00e9hicules \u00e0 Deux Roues Etc; Distrib., Achat, Import., Vente",
    "wof:placetype":"venue"
},
  "geometry": {"coordinates":[6.857986927,46.9656143188],"type":"Point"}
}