{
  "type": "Feature",
  "properties": {
    "addr:full":"Dorfstrasse 66 Richterswil Z\u00fcrich 8805",
    "addr:housenumber":"66",
    "addr:postcode":"8805",
    "addr:street":"Dorfstrasse",
    "iso:country":"CH",
    "sg:address":"Dorfstrasse 66",
    "sg:city":"Richterswil",
    "sg:orig_category":"Blumen U Zierpflanzenbau Fachdetailhandel in Verkaufsr\u00e4umen",
    "sg:phone":"+41 17846065",
    "sg:postcode":"8805",
    "sg:province":"Z\u00fcrich",
    "wof:name":"Blumen Strickler Gartenbau Ag",
    "wof:placetype":"venue"
},
  "geometry": {"coordinates":[8.704591,47.208977],"type":"Point"}
}