{
  "type": "Feature",
  "properties": {
    "addr:full":"Marktplatz 11-13 4001 Basel. Postfach 216 Basel Basel-Stadt 4001",
    "addr:housenumber":"11-13;216",
    "addr:postcode":"4001;4001",
    "addr:street":"Marktplatz;Postfach",
    "iso:country":"CH",
    "sg:address":"Marktplatz 11-13 4001 Basel. Postfach 216",
    "sg:city":"Basel",
    "sg:orig_category":"Aktivit\u00e4t der Bankinstitute Kreditinstitute ohne Spezialkreditinstitute",
    "sg:phone":"+41 22 312 24 40",
    "sg:postcode":"4001",
    "sg:province":"Basel-Stadt",
    "wof:name":"Bank Hapoalim (switzerland) Ltd Succle De Gen\u00e8ve",
    "wof:placetype":"venue"
},
  "geometry": {"coordinates":[6.14754,46.204086],"type":"Point"}
}