{
  "type": "Feature",
  "properties": {
    "iso:country":"CH",
    "sg:address":"Sch\u00f6nfeld 7",
    "sg:city":"Dietwil",
    "sg:orig_category":"Non-Classified Establishments",
    "sg:postcode":"6042",
    "sg:province":"Aargau",
    "wof:name":"A-zehnder Integration, Beratung Und Verkauf",
    "wof:placetype":"venue"
},
  "geometry": {"coordinates":[8.3916292191,47.1457901001],"type":"Point"}
}