{
  "type": "Feature",
  "properties": {
    "iso:country":"CH",
    "sg:address":"Meienbergweg 50",
    "sg:city":"Jona",
    "sg:orig_category":"Gemischte Landwirtschaft",
    "sg:postcode":"8645",
    "sg:province":"St. Gallen",
    "wof:name":"Gut Meienberg Ag",
    "wof:placetype":"venue"
},
  "geometry": {"coordinates":[8.8376483917,47.2301635742],"type":"Point"}
}