{
  "type": "Feature",
  "properties": {
    "addr:full":"Alte Winterthurerstrasse 53 Wallisellen Z\u00fcrich 8304",
    "addr:housenumber":"53",
    "addr:postcode":"8304",
    "addr:street":"Alte Winterthurerstrasse",
    "iso:country":"CH",
    "sg:address":"Alte Winterthurerstrasse 53",
    "sg:city":"Wallisellen",
    "sg:orig_category":"Circuits, Customized",
    "sg:phone":"+41 18302727",
    "sg:postcode":"8304",
    "sg:province":"Z\u00fcrich",
    "wof:name":"National Semiconductor",
    "wof:placetype":"venue"
},
  "geometry": {"coordinates":[8.591874,47.417164],"type":"Point"}
}