{
  "type": "Feature",
  "properties": {
    "iso:country":"CH",
    "sg:address":"Waldegg",
    "sg:city":"Beatenberg",
    "sg:orig_category":"Grosshandel mit Nahrungsmitteln, Getr\u00e4nken U Tabakwaren ohne ausgepr\u00e4gten Schwerpunkt",
    "sg:postcode":"3803",
    "sg:province":"Bern",
    "wof:name":"B\u00fchlmannn-von Allmen T. Und D.",
    "wof:placetype":"venue"
},
  "geometry": {"coordinates":[7.8136191368,46.7040863037],"type":"Point"}
}