{
  "type": "Feature",
  "properties": {
    "iso:country":"CH",
    "sg:address":"Rue Sigismond-thalberg 2 1200 Genf. Postfach",
    "sg:city":"Gen\u00e8ve",
    "sg:orig_category":"Wirtschaftspr\u00fcfung, Steuerberatung U Treuhand",
    "sg:postcode":"1201",
    "sg:province":"Gen\u00e8ve",
    "wof:name":"Nbil Ag",
    "wof:placetype":"venue"
},
  "geometry": {"coordinates":[8.8515090942,47.1901092529],"type":"Point"}
}