{
  "type": "Feature",
  "properties": {
    "iso:country":"CH",
    "sg:address":"Route Des Jeunes 6",
    "sg:city":"Grand-lancy",
    "sg:orig_category":"Interessenvertretungen",
    "sg:postcode":"1212",
    "sg:province":"Gen\u00e8ve",
    "wof:name":"Syndicat Pour Chemins Et Routes Alpestres Dosirain-balisaz-recardetes",
    "wof:placetype":"venue"
},
  "geometry": {"coordinates":[7.1641640663,46.6192207336],"type":"Point"}
}