{
  "type": "Feature",
  "properties": {
    "iso:country":"CH",
    "sg:address":"Avenue De S\u00e9velin 18 1004 Lausanne. Postfach",
    "sg:city":"Lausanne",
    "sg:orig_category":"Architektur U Ingenieurb\u00fcros Dienstleistungen von Beteiligungsgesellschaften",
    "sg:phone":"+41 21 620 03 90",
    "sg:postcode":"1003",
    "sg:province":"Vaud",
    "wof:name":"Pluggit International S\u00e0rl Gestion Centralis\u00e9e, Planification, Commerce De Produits Etc",
    "wof:placetype":"venue"
},
  "geometry": {"coordinates":[6.619271,46.522099],"type":"Point"}
}