{
  "type": "Feature",
  "properties": {
    "iso:country":"CH",
    "sg:address":"2926",
    "sg:city":"Boncourt",
    "sg:orig_category":"Vereine Gesang",
    "sg:postcode":"2926",
    "sg:province":"Jura",
    "wof:name":"St\u00e9 De Chant C\u00e9cilia",
    "wof:placetype":"venue"
},
  "geometry": {"coordinates":[7.0156798363,47.4972915649],"type":"Point"}
}