{
  "type": "Feature",
  "properties": {
    "iso:country":"CH",
    "sg:address":"Pray\u00e9 83. 2854 Bassecourt. Postfach",
    "sg:city":"Bassecourt",
    "sg:orig_category":"Zimmerei, Dachdeckerei, Bauspenglerei U Abdichtung",
    "sg:postcode":"2854",
    "sg:province":"Jura",
    "wof:name":"Marius Cattin",
    "wof:placetype":"venue"
},
  "geometry": {"coordinates":[7.2390389442,47.333656311],"type":"Point"}
}