{
  "type": "Feature",
  "properties": {
    "iso:country":"CH",
    "sg:address":"Zieglerstrasse 51",
    "sg:city":"Bern",
    "sg:orig_category":"Kinesiologie",
    "sg:phone":"+41 31 382 55 07",
    "sg:postcode":"3007",
    "sg:province":"Bern",
    "wof:name":"Daniela Ellenberger Kinesiologie",
    "wof:placetype":"venue"
},
  "geometry": {"coordinates":[7.4306340218,46.9426307678],"type":"Point"}
}