{
  "type": "Feature",
  "properties": {
    "iso:country":"CH",
    "sg:address":"Ravi\u00e8res 55b 2856 Bo\u00e9court. Postfach",
    "sg:city":"Bo\u00e9court",
    "sg:orig_category":"Gesundheitswesen",
    "sg:postcode":"2856",
    "sg:province":"Jura",
    "wof:name":"Ck Pnl, Kocher Carmen",
    "wof:placetype":"venue"
},
  "geometry": {"coordinates":[7.2099618912,47.3490257263],"type":"Point"}
}