{
  "type": "Feature",
  "properties": {
    "iso:country":"CH",
    "sg:address":"Rue Pr\u00e9-vuillemin 4",
    "sg:city":"Cheseaux-nor\u00e9az",
    "sg:orig_category":"Vereine Radio, Film and Foto",
    "sg:phone":"+41 24 425 47 20",
    "sg:postcode":"1400",
    "sg:province":"Vaud",
    "wof:name":"Cine-photo-club Amateurs",
    "wof:placetype":"venue"
},
  "geometry": {"coordinates":[6.6736211777,46.7825889587],"type":"Point"}
}