{
  "type": "Feature",
  "properties": {
    "addr:full":"Niedern Trogen Appenzell Ausserrhoden 9043",
    "addr:postcode":"9043",
    "addr:street":"Niedern;Ausserrhoden",
    "iso:country":"CH",
    "sg:address":"Niedern",
    "sg:city":"Trogen",
    "sg:classifiers":[
        {
            "category":"Social Services",
            "subcategory":"Retirement Home",
            "type":"Services"
        }
    ],
    "sg:phone":"+41 71 344 17 61",
    "sg:postcode":"9043",
    "sg:province":"Appenzell Ausserrhoden",
    "sg:tags":[
        "pflegeheime",
        "u",
        "alters"
    ],
    "wof:name":"Krankenheim Trogen",
    "wof:placetype":"venue"
},
  "geometry": {"coordinates":[9.460753,47.408405],"type":"Point"}
}