{
  "type": "Feature",
  "properties": {
    "iso:country":"CH",
    "sg:address":"Augio 6547 Augio. Postfach",
    "sg:city":"Augio",
    "sg:orig_category":"RESTAURANTS: TEA-ROOMS",
    "sg:postcode":"6547",
    "sg:province":"Graubunden",
    "wof:name":"Ristobelnova Sa",
    "wof:placetype":"venue"
},
  "geometry": {"coordinates":[9.1269903183,46.3647193909],"type":"Point"}
}