{
  "type": "Feature",
  "properties": {
    "addr:full":"Rue Centrale 24 Lausanne Vaud 1003",
    "addr:housenumber":"24",
    "addr:postcode":"1003",
    "addr:street":"Rue Centrale",
    "iso:country":"CH",
    "sg:address":"Rue Centrale 24",
    "sg:city":"Lausanne",
    "sg:orig_category":"Detailhandel mit Antiquit\u00e4ten",
    "sg:phone":"+41 21 320 47 79",
    "sg:postcode":"1003",
    "sg:province":"Vaud",
    "wof:name":"Pietro Marino Antiquit\u00e9s",
    "wof:placetype":"venue"
},
  "geometry": {"coordinates":[6.63485,46.520592],"type":"Point"}
}