{
  "type": "Feature",
  "properties": {
    "iso:country":"CH",
    "sg:address":"Wagistrasse 18 8952 Schlieren. Postfach",
    "sg:city":"Schlieren",
    "sg:orig_category":"Herstellung von Metallkonstruktionen",
    "sg:phone":"+41 17309000",
    "sg:postcode":"8952",
    "sg:province":"Z\u00fcrich",
    "wof:name":"Hubler Metallbau Ag",
    "wof:placetype":"venue"
},
  "geometry": {"coordinates":[8.4584560394,47.3991279602],"type":"Point"}
}