{
  "type": "Feature",
  "properties": {
    "iso:country":"CH",
    "sg:address":"Schaftenholzweg 18",
    "sg:city":"Studen",
    "sg:classifiers":[
        {
            "category":"Building & Trades",
            "subcategory":"Construction",
            "type":"Services"
        }
    ],
    "sg:phone":"+41 32 372 14 15",
    "sg:postcode":"2557",
    "sg:province":"Bern",
    "sg:tags":[
        "front",
        "door"
    ],
    "wof:name":"Kammag Biel Ag",
    "wof:placetype":"venue"
},
  "geometry": {"coordinates":[7.3063030243,47.1091842651],"type":"Point"}
}