{
  "type": "Feature",
  "properties": {
    "iso:country":"CH",
    "sg:address":"Kreuzhausweg 7.",
    "sg:city":"Kriens",
    "sg:orig_category":"Grosshandel mit Getr\u00e4nken",
    "sg:phone":"+41 41 320 32 20",
    "sg:postcode":"6010",
    "sg:province":"Luzern",
    "wof:name":"Mahler Louis.",
    "wof:placetype":"venue"
},
  "geometry": {"coordinates":[8.2679414749,47.0347061157],"type":"Point"}
}