{
  "type": "Feature",
  "properties": {
    "iso:country":"CH",
    "sg:address":"Sporgasse 7 9472 Grabs. Postfach 64",
    "sg:city":"Grabs",
    "sg:orig_category":"Landesverteidigung, Sozialversicherung \u00d6ffentliche Verwaltung",
    "sg:phone":"+41 81 750 35 12",
    "sg:postcode":"9472",
    "sg:province":"St. Gallen",
    "wof:name":"Zivilschutzstelle Grabs",
    "wof:placetype":"venue"
},
  "geometry": {"coordinates":[9.4445981979,47.1812400818],"type":"Point"}
}