{
  "type": "Feature",
  "properties": {
    "iso:country":"CH",
    "sg:address":"Sportstrasse 1",
    "sg:city":"Grenchen",
    "sg:classifiers":[
        {
            "category":"Professional",
            "subcategory":"Detective & Security Services",
            "type":"Services"
        }
    ],
    "sg:phone":"+41 32 654 10 00",
    "sg:postcode":"2540",
    "sg:province":"Solothurn",
    "sg:tags":[
        "abrasion",
        "protection"
    ],
    "wof:name":"Kaltbrunner Ag",
    "wof:placetype":"venue"
},
  "geometry": {"coordinates":[7.400255,47.185463],"type":"Point"}
}