{
  "type": "Feature",
  "properties": {
    "iso:country":"CH",
    "sg:address":"Rebmattweg 6",
    "sg:city":"Merlischachen",
    "sg:orig_category":"Campingpl\u00e4tze",
    "sg:phone":"+41 81 302 37 10",
    "sg:postcode":"6402",
    "sg:province":"Schwyz",
    "wof:name":"Campingplatz Giessenpark",
    "wof:placetype":"venue"
},
  "geometry": {"coordinates":[9.501325,47.003681],"type":"Point"}
}