{
  "type": "Feature",
  "properties": {
    "iso:country":"CH",
    "sg:address":"Fabrikstrasse 4",
    "sg:city":"Solothurn",
    "sg:orig_category":"Fussreflexzonenmassage",
    "sg:phone":"+41 32 621 55 74",
    "sg:postcode":"4500",
    "sg:province":"Solothurn",
    "wof:name":"Olga Meier Reflexzonenmassage",
    "wof:placetype":"venue"
},
  "geometry": {"coordinates":[7.5254068375,47.2114295959],"type":"Point"}
}