{
  "type": "Feature",
  "properties": {
    "iso:country":"CH",
    "sg:address":"Chamerstrasse 158",
    "sg:city":"Zug",
    "sg:orig_category":"Architektur U Ingenieurb\u00fcros",
    "sg:postcode":"6300",
    "sg:province":"Zug",
    "wof:name":"Hoppler P. Bauorganisation Innenarchitektur Bauorganisation, Bauf\u00fchrung, Innenarchitektur, Designstudio",
    "wof:placetype":"venue"
},
  "geometry": {"coordinates":[8.525275,47.480457],"type":"Point"}
}