{
  "type": "Feature",
  "properties": {
    "iso:country":"CH",
    "sg:address":"Schlossstrasse 57",
    "sg:city":"Oensingen",
    "sg:orig_category":"Herstellung von keramischen Haushaltswaren U Ziergegenst\u00e4nden",
    "sg:phone":"+41 79 211 59 60",
    "sg:postcode":"4702",
    "sg:province":"Solothurn",
    "wof:name":"Jean Riggenbach T\u00f6pferei",
    "wof:placetype":"venue"
},
  "geometry": {"coordinates":[7.7183327675,47.2941703796],"type":"Point"}
}