{
  "type": "Feature",
  "properties": {
    "iso:country":"CH",
    "sg:address":"Ueberlandstrasse 444",
    "sg:city":"Z\u00fcrich",
    "sg:orig_category":"Fahrschulen, Flugschulen",
    "sg:phone":"+41 13224411",
    "sg:postcode":"8051",
    "sg:province":"Z\u00fcrich",
    "wof:name":"Andreas Mannale Autofahrschule Albatros",
    "wof:placetype":"venue"
},
  "geometry": {"coordinates":[8.593752861,47.4048233032],"type":"Point"}
}