{
  "type": "Feature",
  "properties": {
    "iso:country":"CH",
    "sg:address":"Seestrasse 3",
    "sg:city":"Mammern",
    "sg:orig_category":"RESTAURANTS: TEA-ROOMS",
    "sg:phone":"+41 52 741 24 44",
    "sg:postcode":"8265",
    "sg:province":"Thurgau",
    "wof:name":"Gasthof Schiff Ag Gastronomiebetrieb; F\u00fchrung, Verpachtung",
    "wof:placetype":"venue"
},
  "geometry": {"coordinates":[8.9158334732,47.6463737488],"type":"Point"}
}