{
  "type": "Feature",
  "properties": {
    "iso:country":"CH",
    "sg:address":"Kreuzstrasse 4",
    "sg:city":"St\u00e4fa",
    "sg:orig_category":"Grosshandel mit B\u00fcromaschinen U einrichtungen",
    "sg:phone":"+41 19263385",
    "sg:postcode":"8712",
    "sg:province":"Z\u00fcrich",
    "wof:name":"Huber B\u00fcrocenter Ag",
    "wof:placetype":"venue"
},
  "geometry": {"coordinates":[8.7258710861,47.2395248413],"type":"Point"}
}