{
  "type": "Feature",
  "properties": {
    "iso:country":"CH",
    "sg:address":"Hegarstrasse 16",
    "sg:city":"Z\u00fcrich",
    "sg:orig_category":"Werbeberatung",
    "sg:phone":"+41 13806535",
    "sg:postcode":"8032",
    "sg:province":"Z\u00fcrich",
    "wof:name":"Christoph Dill Abcdill.com Communication",
    "wof:placetype":"venue"
},
  "geometry": {"coordinates":[8.555937767,47.3647155762],"type":"Point"}
}