{
  "type": "Feature",
  "properties": {
    "addr:full":"Rue Du Centre 17 Crissier Vaud 1023",
    "addr:housenumber":"17",
    "addr:postcode":"1023",
    "addr:street":"Rue Du Centre",
    "iso:country":"CH",
    "sg:address":"Rue Du Centre 17",
    "sg:city":"Crissier",
    "sg:orig_category":"Bauschreinerei Herstellung von M\u00f6beln verschiedener Art",
    "sg:phone":"+41 21 635 58 30",
    "sg:postcode":"1023",
    "sg:province":"Vaud",
    "wof:name":"Pierre Chapuis Eb\u00e9nisterie",
    "wof:placetype":"venue"
},
  "geometry": {"coordinates":[6.57834,46.552238],"type":"Point"}
}