{
  "type": "Feature",
  "properties": {
    "iso:country":"CH",
    "sg:address":"Gen\u00e8ve Rue De 98",
    "sg:city":"Th\u00f4nex",
    "sg:orig_category":"Interessenvertretungen",
    "sg:postcode":"1226",
    "sg:province":"Gen\u00e8ve",
    "wof:name":"Association Cor\u00e9enne De La R\u00e9gion Du L\u00e9man",
    "wof:placetype":"venue"
},
  "geometry": {"coordinates":[6.2008938789,46.193031311],"type":"Point"}
}