{
  "type": "Feature",
  "properties": {
    "addr:full":"Theodorshofweg 22 4310 Rheinfelden. Postfach Rheinfelden Aargau 4310",
    "addr:housenumber":"22",
    "addr:postcode":"4310 rheinfelden. postfach;4310",
    "addr:street":"Theodorshofweg",
    "iso:country":"CH",
    "sg:address":"Theodorshofweg 22 4310 Rheinfelden. Postfach",
    "sg:city":"Rheinfelden",
    "sg:orig_category":"Ingenieurb\u00fcros Elektro",
    "sg:phone":"+41 56 484 70 70",
    "sg:postcode":"4310",
    "sg:province":"Aargau",
    "wof:name":"Herzog Kull Group Baden Beratende Energie-ingenieure",
    "wof:placetype":"venue"
},
  "geometry": {"coordinates":[8.286929,47.456108],"type":"Point"}
}