{
  "type": "Feature",
  "properties": {
    "iso:country":"CH",
    "sg:address":"Fr\u00f6schbach 61",
    "sg:city":"F\u00e4llanden",
    "sg:orig_category":"Fahrschulen, Flugschulen",
    "sg:phone":"+41 18261211",
    "sg:postcode":"8117",
    "sg:province":"Z\u00fcrich",
    "wof:name":"Ren\u00e9 Beck Autofahrschule",
    "wof:placetype":"venue"
},
  "geometry": {"coordinates":[8.6443729401,47.3691253662],"type":"Point"}
}