{
  "type": "Feature",
  "properties": {
    "iso:country":"CH",
    "sg:address":"Grand Rue 114",
    "sg:city":"Montreux",
    "sg:orig_category":"RESTAURANTS: TEA-ROOMS",
    "sg:phone":"+41 21 961 21 70",
    "sg:postcode":"1820",
    "sg:province":"Vaud",
    "wof:name":"Kwong Ming, Hau & Cie",
    "wof:placetype":"venue"
},
  "geometry": {"coordinates":[6.9038338661,46.440120697],"type":"Point"}
}