{
  "type": "Feature",
  "properties": {
    "iso:country":"CH",
    "sg:address":"Herzogstrasse 41",
    "sg:city":"Aarau",
    "sg:orig_category":"Sonstige pers\u00f6nliche Dienstleistungen",
    "sg:postcode":"5000",
    "sg:province":"Aargau",
    "wof:name":"Begleitagentur G. Martinuzzi",
    "wof:placetype":"venue"
},
  "geometry": {"coordinates":[8.8628807068,47.2594108582],"type":"Point"}
}