{
  "type": "Feature",
  "properties": {
    "iso:country":"CH",
    "sg:address":"Cementweg 30",
    "sg:city":"Olten",
    "sg:orig_category":"Granit",
    "sg:phone":"+41 32 654 80 54",
    "sg:postcode":"4600",
    "sg:province":"Solothurn",
    "wof:name":"Sostag Steinbruch Ag",
    "wof:placetype":"venue"
},
  "geometry": {"coordinates":[7.8971328735,47.346321106],"type":"Point"}
}