{
  "type": "Feature",
  "properties": {
    "iso:country":"CH",
    "sg:address":"Via Sursilvana",
    "sg:city":"Disentis",
    "sg:classifiers":[
        {
            "category":"Banks & Credit Unions",
            "subcategory":"Bank",
            "type":"Services"
        }
    ],
    "sg:phone":"+41 81 947 47 47",
    "sg:postcode":"7180",
    "sg:province":"Graubunden",
    "wof:name":"Schweiz. Bankgesellschaft",
    "wof:placetype":"venue"
},
  "geometry": {"coordinates":[8.85716,46.706619],"type":"Point"}
}