{
  "type": "Feature",
  "properties": {
    "iso:country":"CH",
    "sg:address":"B\u00fcndenweg 8",
    "sg:city":"Muntelier",
    "sg:orig_category":"Detailhandel mit Milcherzeugnissen U Eiern",
    "sg:phone":"+41 32 677 10 92",
    "sg:postcode":"3286",
    "sg:province":"Fribourg",
    "wof:name":"Hans Schenk Milchprodukte",
    "wof:placetype":"venue"
},
  "geometry": {"coordinates":[7.524810791,47.1698150635],"type":"Point"}
}