{
  "type": "Feature",
  "properties": {
    "iso:country":"CH",
    "sg:address":"Bahnhofstrasse 37 8001 Z\u00fcrich. Postfach",
    "sg:city":"Z\u00fcrich",
    "sg:orig_category":"Werbung",
    "sg:phone":"+41 18843102",
    "sg:postcode":"8022",
    "sg:province":"Z\u00fcrich",
    "wof:name":"Interpubli Ag",
    "wof:placetype":"venue"
},
  "geometry": {"coordinates":[8.4616155624,47.4524536133],"type":"Point"}
}