{
  "type": "Feature",
  "properties": {
    "iso:country":"CH",
    "sg:address":"Hauptstr. 60",
    "sg:city":"Reinach",
    "sg:classifiers":[
        {
            "category":"Banks & Credit Unions",
            "subcategory":"Bank",
            "type":"Services"
        }
    ],
    "sg:phone":"+41 4164718871",
    "sg:postcode":"5734",
    "sg:province":"Aargau",
    "wof:name":"Aargauische Kantonalbank",
    "wof:placetype":"venue"
},
  "geometry": {"coordinates":[8.182831,47.251335],"type":"Point"}
}