{
  "type": "Feature",
  "properties": {
    "iso:country":"CH",
    "sg:address":"Jonschwiler Strasse 39",
    "sg:city":"Schwarzenbach",
    "sg:classifiers":[
        {
            "category":"Transit Center",
            "subcategory":"Freight",
            "type":"Transportation"
        }
    ],
    "sg:phone":"+41 71 923 46 66",
    "sg:postcode":"9536",
    "sg:province":"St. Gallen",
    "sg:tags":[
        "elevator"
    ],
    "wof:name":"Josef Zehnder",
    "wof:placetype":"venue"
},
  "geometry": {"coordinates":[9.075737,47.437649],"type":"Point"}
}