{
  "type": "Feature",
  "properties": {
    "addr:full":"Landstrasse 142 9494 Schaan. Postfach 78 Schaan 9494",
    "addr:housenumber":"142;78",
    "addr:postcode":"9494;9494",
    "addr:street":"Landstrasse;Postfach",
    "iso:country":"CH",
    "sg:address":"Landstrasse 142 9494 Schaan. Postfach 78",
    "sg:city":"Schaan",
    "sg:orig_category":"Detailhandel mit B\u00fcromaschinen U einrichtungen",
    "sg:phone":"+41 55 251 20 20",
    "sg:postcode":"9494",
    "wof:name":"Morger Paul Ag",
    "wof:placetype":"venue"
},
  "geometry": {"coordinates":[8.845207,47.254673],"type":"Point"}
}