{
  "type": "Feature",
  "properties": {
    "iso:country":"CH",
    "sg:address":"Grande-rue",
    "sg:city":"Ponts-de-martel",
    "sg:orig_category":"Instandhaltung U Reparatur von Automobilen",
    "sg:phone":"+41 32 937 19 29",
    "sg:postcode":"2316",
    "sg:province":"Neuch\u00e2tel",
    "wof:name":"Haldimann Jacques, Garage Du Bouleau",
    "wof:placetype":"venue"
},
  "geometry": {"coordinates":[6.7227010727,46.9955177307],"type":"Point"}
}