{
  "type": "Feature",
  "properties": {
    "iso:country":"CH",
    "sg:address":"Le Postillon",
    "sg:city":"Attalens",
    "sg:orig_category":"Gesundheitswesen",
    "sg:postcode":"1616",
    "sg:province":"Fribourg",
    "wof:name":"Vallat Alain Pedagotel",
    "wof:placetype":"venue"
},
  "geometry": {"coordinates":[6.8493890762,46.5091896057],"type":"Point"}
}