{
  "type": "Feature",
  "properties": {
    "iso:country":"CH",
    "sg:address":"Avenue Du G\u00e9n\u00e9ral Guisan 4",
    "sg:city":"Sierre",
    "sg:orig_category":"Warenh\u00e4user",
    "sg:phone":"+41 27 455 46 81",
    "sg:postcode":"3960",
    "sg:province":"Valais",
    "wof:name":"Epa Ag",
    "wof:placetype":"venue"
},
  "geometry": {"coordinates":[7.5320339203,46.2928771973],"type":"Point"}
}