{
  "type": "Feature",
  "properties": {
    "iso:country":"CH",
    "sg:address":"Freigutstrasse 4",
    "sg:city":"Z\u00fcrich",
    "sg:orig_category":"Reiseb\u00fcros U Reiseveranstalter",
    "sg:phone":"+41 12811677",
    "sg:postcode":"8002",
    "sg:province":"Z\u00fcrich",
    "wof:name":"Intermar Kreuzfahrten, Lenz Edith",
    "wof:placetype":"venue"
},
  "geometry": {"coordinates":[8.5322170258,47.3675117493],"type":"Point"}
}