{
  "type": "Feature",
  "properties": {
    "iso:country":"CH",
    "sg:address":"Route De Lo\u00ebx 176",
    "sg:city":"Bernex",
    "sg:classifiers":[
        {
            "category":"Restaurant",
            "type":"Food & Drink"
        }
    ],
    "sg:phone":"+41 22 757 17 98",
    "sg:postcode":"1233",
    "sg:province":"Gen\u00e8ve",
    "wof:name":"Auberge De Lo\u00ebx",
    "wof:placetype":"venue"
},
  "geometry": {"coordinates":[6.0876407623,46.1999015808],"type":"Point"}
}