{
  "type": "Feature",
  "properties": {
    "iso:country":"CH",
    "sg:address":"Bodenacherstrasse 18 8121 Benglen. Postfach",
    "sg:city":"Benglen",
    "sg:orig_category":"Unternehmensberatung",
    "sg:phone":"+41 18253657",
    "sg:postcode":"8121",
    "sg:province":"Z\u00fcrich",
    "wof:name":"Ccc Call Centre Consulting Gmbh",
    "wof:placetype":"venue"
},
  "geometry": {"coordinates":[8.6356897354,47.3616485596],"type":"Point"}
}