{
  "type": "Feature",
  "properties": {
    "iso:country":"CH",
    "sg:address":"Rue De La Gare 1 1860 Aigle Case Postale 186",
    "sg:city":"Aigle",
    "sg:orig_category":"Detailhandel mit Brillen U anderen Sehhilfen Fachdetailhandel in Verkaufsr\u00e4umen",
    "sg:phone":"+41 22 798 39 66",
    "sg:postcode":"1860",
    "sg:province":"Vaud",
    "wof:name":"Optique Du Grand-saconnex Mathieu & Cie.",
    "wof:placetype":"venue"
},
  "geometry": {"coordinates":[6.117524,46.230667],"type":"Point"}
}