{
  "type": "Feature",
  "properties": {
    "iso:country":"CH",
    "sg:address":"Rue De La Mor\u00e2che 8",
    "sg:city":"Nyon",
    "sg:orig_category":"Werbegrafikateliers",
    "sg:phone":"+41 22 365 22 22",
    "sg:postcode":"1260",
    "sg:province":"Vaud",
    "wof:name":"Atelier Vincent Zuppiger Sa Graphisme",
    "wof:placetype":"venue"
},
  "geometry": {"coordinates":[6.2340488434,46.3833503723],"type":"Point"}
}