{
  "type": "Feature",
  "properties": {
    "iso:country":"CH",
    "sg:address":"Pilatusstrasse 12 6004 Luzern. Postfach",
    "sg:city":"Luzern",
    "sg:orig_category":"Reiseb\u00fcros U Reiseveranstalter",
    "sg:phone":"+41 71 222 61 61",
    "sg:postcode":"6002",
    "sg:province":"Luzern",
    "wof:name":"Hotelplan Internationale Reiseorganisation Ag",
    "wof:placetype":"venue"
},
  "geometry": {"coordinates":[9.3728303909,47.4247970581],"type":"Point"}
}