{
  "type": "Feature",
  "properties": {
    "iso:country":"CH",
    "sg:address":"Rohrhaldenstrasse 25",
    "sg:city":"St\u00e4fa",
    "sg:orig_category":"Wohnheime f\u00fcr Kinder U Jugendliche",
    "sg:phone":"+41 17812010",
    "sg:postcode":"8712",
    "sg:province":"Z\u00fcrich",
    "wof:name":"Kinderheim Gr\u00fcnau",
    "wof:placetype":"venue"
},
  "geometry": {"coordinates":[8.6496343613,47.2441520691],"type":"Point"}
}