{
  "type": "Feature",
  "properties": {
    "iso:country":"CH",
    "sg:address":"Mattgraf 6373 Ennetb\u00fcrgen. Postfach",
    "sg:city":"Ennetb\u00fcrgen",
    "sg:orig_category":"Detailhandel Handel mit Motorr\u00e4dern, Teilen U Zubeh\u00f6r Instandhaltung U Reparatur von Motorr\u00e4dern Rep",
    "sg:phone":"+41 79 340 80 36",
    "sg:postcode":"6373",
    "sg:province":"Nidwalden",
    "wof:name":"Ducati Motos",
    "wof:placetype":"venue"
},
  "geometry": {"coordinates":[8.4159765244,46.9983215332],"type":"Point"}
}