{
  "type": "Feature",
  "properties": {
    "iso:country":"CH",
    "sg:city":"Castiel",
    "sg:classifiers":[
        {
            "category":"Banks & Credit Unions",
            "subcategory":"Bank",
            "type":"Services"
        }
    ],
    "sg:phone":"+41 4181226041",
    "sg:postcode":"7027",
    "sg:province":"Graubunden",
    "wof:name":"Graub\u00fcndner Kantonalbank",
    "wof:placetype":"venue"
},
  "geometry": {"coordinates":[9.603626,46.83931],"type":"Point"}
}