{
  "type": "Feature",
  "properties": {
    "iso:country":"CH",
    "sg:address":"Seetalstrasse 52",
    "sg:city":"Boniswil",
    "sg:orig_category":"Einzelhandel mit Automobilen Wohnwagen and Wohnmobile Grosshandel",
    "sg:phone":"+41 62 777 02 88",
    "sg:postcode":"5706",
    "sg:province":"Aargau",
    "wof:name":"Waibel Caravan Ag",
    "wof:placetype":"venue"
},
  "geometry": {"coordinates":[8.1898698807,47.3109397888],"type":"Point"}
}