{
  "type": "Feature",
  "properties": {
    "iso:country":"CH",
    "sg:address":"Orbe Rue D' 96",
    "sg:city":"Yverdon-les-bains",
    "sg:orig_category":"Bau von Strassen, Sportanlagen U Bahnverkehrsstrecken",
    "sg:postcode":"1400",
    "sg:province":"Vaud",
    "wof:name":"Piscines Ph7, Vouilloz Cl.-a Entretien De Piscines",
    "wof:placetype":"venue"
},
  "geometry": {"coordinates":[6.857639,46.452316],"type":"Point"}
}