{
  "type": "Feature",
  "properties": {
    "iso:country":"CH",
    "sg:address":"Rebstockhalde 27",
    "sg:city":"Luzern",
    "sg:orig_category":"Unternehmensberatung",
    "sg:phone":"+41 41 370 74 48",
    "sg:postcode":"6006",
    "sg:province":"Luzern",
    "wof:name":"Rohde Consulting",
    "wof:placetype":"venue"
},
  "geometry": {"coordinates":[8.3523483276,47.0430374146],"type":"Point"}
}