{
  "type": "Feature",
  "properties": {
    "iso:country":"CH",
    "sg:address":"Neugasse 11 9220 Bischofszell. Postfach",
    "sg:city":"Bischofszell",
    "sg:orig_category":"Detailhandel mit B\u00fcromaschinen U einrichtungen Detailhandel mit Schreib U Papeteriewaren",
    "sg:phone":"+41 71 422 28 11",
    "sg:postcode":"9220",
    "sg:province":"Thurgau",
    "wof:name":"Sauder Ag B\u00fcrofachgesch\u00e4ft",
    "wof:placetype":"venue"
},
  "geometry": {"coordinates":[9.241777,47.493698],"type":"Point"}
}