{
  "type": "Feature",
  "properties": {
    "iso:country":"CH",
    "sg:address":"Hintere Sch\u00fctzengasse 10",
    "sg:city":"St.gallen",
    "sg:orig_category":"Pensionskassen",
    "sg:phone":"+41 71 222 26 94",
    "sg:postcode":"9000",
    "sg:province":"St. Gallen",
    "wof:name":"Personalvorsorgestiftung Der Hugentobler Ag",
    "wof:placetype":"venue"
},
  "geometry": {"coordinates":[9.3725070953,47.4241333008],"type":"Point"}
}