{
  "type": "Feature",
  "properties": {
    "iso:country":"CH",
    "sg:address":"Tonackerstrasse 11",
    "sg:city":"Volketswil",
    "sg:orig_category":"Herstellung von Platten, Folien, Schl\u00e4uchen U Profilen aus Kunststoff",
    "sg:phone":"+41 19454571",
    "sg:postcode":"8604",
    "sg:province":"Z\u00fcrich",
    "wof:name":"Ernst Selinger Industrie-& Autospritzwerk",
    "wof:placetype":"venue"
},
  "geometry": {"coordinates":[8.6967353821,47.3904075623],"type":"Point"}
}