{
  "type": "Feature",
  "properties": {
    "iso:country":"CH",
    "sg:address":"Belsitostrasse 18",
    "sg:city":"Z\u00fcrich",
    "sg:orig_category":"Interessenvertretungen",
    "sg:phone":"+41 12520019",
    "sg:postcode":"8044",
    "sg:province":"Z\u00fcrich",
    "wof:name":"Weil-stiftung Ernst Und Jacqueline",
    "wof:placetype":"venue"
},
  "geometry": {"coordinates":[8.5628042221,47.3739852905],"type":"Point"}
}