{
  "type": "Feature",
  "properties": {
    "iso:country":"CH",
    "sg:address":"Contrada Al Lago 9",
    "sg:city":"Caslano",
    "sg:orig_category":"Detailhandel mit Waren verschiedener Art, Hauptrichtung Nahrungsmittel",
    "sg:phone":"+41 91 606 51 12",
    "sg:postcode":"6987",
    "sg:province":"Ticino",
    "wof:name":"Franco & Ivana Capelli Negozio Alimentari",
    "wof:placetype":"venue"
},
  "geometry": {"coordinates":[8.8831806183,45.9708824158],"type":"Point"}
}