{
  "type": "Feature",
  "properties": {
    "iso:country":"CH",
    "sg:address":"G\u00e4mpi 10 6043 Adligenswil. Postfach 36",
    "sg:city":"Adligenswil",
    "sg:orig_category":"Sonstiger Grosshandel",
    "sg:phone":"+41 41 370 25 20",
    "sg:postcode":"6043",
    "sg:province":"Luzern",
    "wof:name":"Cmb Handel Alfred Barden",
    "wof:placetype":"venue"
},
  "geometry": {"coordinates":[8.3651199341,47.0668754578],"type":"Point"}
}