{
  "type": "Feature",
  "properties": {
    "iso:country":"CH",
    "sg:address":"Fauquez Route Aloys- 98 1018 Lausanne. Postfach",
    "sg:city":"Lausanne",
    "sg:orig_category":"RESTAURANTS: TEA-ROOMS",
    "sg:postcode":"1018",
    "sg:province":"Vaud",
    "wof:name":"Condemi Girolamo. Caf\u00e9-restaurant Du Nord.",
    "wof:placetype":"venue"
},
  "geometry": {"coordinates":[6.6339221001,46.5374107361],"type":"Point"}
}