{
  "type": "Feature",
  "properties": {
    "iso:country":"CH",
    "sg:address":"Hardstrasse 11 4052 Basel. Postfach",
    "sg:city":"Basel",
    "sg:orig_category":"Personal U Stellenvermittlung Unternehmensberatung",
    "sg:phone":"+41 61 271 40 00",
    "sg:postcode":"4002",
    "sg:province":"Basel-Stadt",
    "wof:name":"Hess Tina + Partner",
    "wof:placetype":"venue"
},
  "geometry": {"coordinates":[7.6015849113,47.5520439148],"type":"Point"}
}