{
  "type": "Feature",
  "properties": {
    "addr:full":"7462 Salouf Graubunden 7462",
    "addr:housenumber":"7462",
    "addr:postcode":"7462",
    "addr:street":"Salouf Graubunden",
    "iso:country":"CH",
    "sg:address":"7462",
    "sg:city":"Salouf",
    "sg:orig_category":"Architekturb\u00fcros",
    "sg:phone":"+41 81 684 18 35",
    "sg:postcode":"7462",
    "sg:province":"Graubunden",
    "wof:name":"M. Maier & N. Melcher Architekturb\u00fcro",
    "wof:placetype":"venue"
},
  "geometry": {"coordinates":[9.576055,46.624546],"type":"Point"}
}