{
  "type": "Feature",
  "properties": {
    "iso:country":"CH",
    "sg:address":"Staubishub",
    "sg:city":"Egnach",
    "sg:orig_category":"Grosshandel mit Obst U Gem\u00fcse",
    "sg:postcode":"9322",
    "sg:province":"Thurgau",
    "wof:name":"Sun-trade Ltd Liab Co, Cheyenne (wyoming Usa), Succursale Di Morbio Inferiore",
    "wof:placetype":"venue"
},
  "geometry": {"coordinates":[9.0207433701,45.8513183594],"type":"Point"}
}