{
  "type": "Feature",
  "properties": {
    "iso:country":"CH",
    "sg:address":"Degenbalmstrasse",
    "sg:city":"Morschach",
    "sg:classifiers":[
        {
            "category":"Travel",
            "subcategory":"Hotels & Motels",
            "type":"Entertainment"
        }
    ],
    "sg:phone":"+41 81 404 11 50",
    "sg:postcode":"6443",
    "sg:province":"Schwyz",
    "sg:tags":[
        "hotels",
        "mit",
        "restaurant"
    ],
    "wof:name":"Hotel Bellevue",
    "wof:placetype":"venue"
},
  "geometry": {"coordinates":[9.7150812149,46.7045097351],"type":"Point"}
}