{
  "type": "Feature",
  "properties": {
    "iso:country":"CH",
    "sg:address":"Gottardo Via San 2",
    "sg:city":"Bellinzona",
    "sg:orig_category":"Sonstiges Versicherungsgewerbe",
    "sg:phone":"+41 91 826 32 32",
    "sg:postcode":"6500",
    "sg:province":"Ticino",
    "wof:name":"Mobiliare Svizzera Societ\u00e0 D'assicurazioni Agenzia Generale Di Bellinzona, Franco R. Ferrari",
    "wof:placetype":"venue"
},
  "geometry": {"coordinates":[9.026758194,46.1977577209],"type":"Point"}
}