{
  "type": "Feature",
  "properties": {
    "iso:country":"CH",
    "sg:address":"St\u00e4mpflistrasse 14",
    "sg:city":"Bern",
    "sg:orig_category":"Betrieb von Taxis",
    "sg:postcode":"3008",
    "sg:province":"Bern",
    "wof:name":"M & B Service Gmbh",
    "wof:placetype":"venue"
},
  "geometry": {"coordinates":[7.413629,46.942478],"type":"Point"}
}