{
  "type": "Feature",
  "properties": {
    "iso:country":"CH",
    "sg:address":"Z\u00fcrcherstrasse 9",
    "sg:city":"Sargans",
    "sg:orig_category":"Technische, physikalische U chemische Untersuchung",
    "sg:postcode":"7320",
    "sg:province":"St. Gallen",
    "wof:name":"Fachberatung Chemie Haiber Dr. F.",
    "wof:placetype":"venue"
},
  "geometry": {"coordinates":[9.4387998581,47.0475921631],"type":"Point"}
}