{
  "type": "Feature",
  "properties": {
    "iso:country":"CH",
    "sg:address":"Wolfriet",
    "sg:city":"Mels",
    "sg:orig_category":"Detailhandel mit Haustieren U zoologischem Bedarf",
    "sg:phone":"+41 81 723 76 86",
    "sg:postcode":"8887",
    "sg:province":"St. Gallen",
    "wof:name":"Qualipet Ag Haustierbedarfs-center",
    "wof:placetype":"venue"
},
  "geometry": {"coordinates":[9.438624382,47.0403938293],"type":"Point"}
}