{
  "type": "Feature",
  "properties": {
    "iso:country":"CH",
    "sg:address":"Hauptstrasse 43",
    "sg:city":"Sissach",
    "sg:orig_category":"RESTAURANTS: TEA-ROOMS",
    "sg:postcode":"4450",
    "sg:province":"Basel-Landschaft",
    "wof:name":"Restaurant Chapeau De Napol\u00e9on, Stoudmann Caf\u00e9-restaurant",
    "wof:placetype":"venue"
},
  "geometry": {"coordinates":[6.5584697723,46.9128417969],"type":"Point"}
}