{
  "type": "Feature",
  "properties": {
    "addr:full":"Hauptstrasse 19 Schlattingen Thurgau 8255",
    "addr:housenumber":"19",
    "addr:postcode":"8255",
    "addr:street":"Hauptstrasse",
    "iso:country":"CH",
    "sg:address":"Hauptstrasse 19",
    "sg:city":"Schlattingen",
    "sg:orig_category":"Autogaragen",
    "sg:phone":"+41 52 657 14 90",
    "sg:postcode":"8255",
    "sg:province":"Thurgau",
    "wof:name":"Kurt M\u00fcller Autoreparaturwerkst\u00e4tte",
    "wof:placetype":"venue"
},
  "geometry": {"coordinates":[8.77043,47.66497],"type":"Point"}
}