{
  "type": "Feature",
  "properties": {
    "iso:country":"CH",
    "sg:address":"Bahnhofplatz",
    "sg:city":"Zermatt",
    "sg:orig_category":"Vermittlung von Immobilien",
    "sg:phone":"+41 27 967 20 01",
    "sg:postcode":"3920",
    "sg:province":"Valais",
    "wof:name":"Immobilien Lochmatter Anton",
    "wof:placetype":"venue"
},
  "geometry": {"coordinates":[7.7484002113,46.024143219],"type":"Point"}
}