{
  "type": "Feature",
  "properties": {
    "iso:country":"CH",
    "sg:address":"Rebenstrasse 1",
    "sg:city":"Steinhausen",
    "sg:orig_category":"Herstellung von B\u00fcro U Ladenm\u00f6beln",
    "sg:postcode":"6312",
    "sg:province":"Zug",
    "wof:name":"Dritt-welt-laden Steinhausen.",
    "wof:placetype":"venue"
},
  "geometry": {"coordinates":[8.4845561981,47.2013053894],"type":"Point"}
}