{
  "type": "Feature",
  "properties": {
    "iso:country":"CH",
    "sg:address":"Von Roll-areal 53",
    "sg:city":"Klus",
    "sg:orig_category":"Oberfl\u00e4chenveredlung U W\u00e4rmebehandlung",
    "sg:phone":"+41 62 296 44 44",
    "sg:postcode":"4710",
    "sg:province":"Solothurn",
    "wof:name":"Taufer Ag",
    "wof:placetype":"venue"
},
  "geometry": {"coordinates":[7.6957130432,47.3024482727],"type":"Point"}
}