{
  "type": "Feature",
  "properties": {
    "iso:country":"CH",
    "sg:address":"Hub 271 9492 Eschen. Postfach 163",
    "sg:city":"Eschen",
    "sg:orig_category":"Sanit\u00e4r U Heizungsinstallation Sanit\u00e4rinstallation",
    "sg:phone":"+41 79 432 78 06",
    "sg:postcode":"9492",
    "wof:name":"Oehrli Und Reichenbach Gmbh",
    "wof:placetype":"venue"
},
  "geometry": {"coordinates":[7.3220500946,46.4248199463],"type":"Point"}
}