{
  "type": "Feature",
  "properties": {
    "iso:country":"CH",
    "sg:address":"1510 Moudon Case Postale 257",
    "sg:city":"Moudon",
    "sg:orig_category":"Detailhandel mit Waren verschiedener Art, Hauptrichtung Nahrungsmittel",
    "sg:phone":"+41 26 651 93 51",
    "sg:postcode":"1510",
    "sg:province":"Vaud",
    "wof:name":"Soci\u00e9t\u00e9 D'agriculture De Romont Et Environs",
    "wof:placetype":"venue"
},
  "geometry": {"coordinates":[6.9533801079,46.6943054199],"type":"Point"}
}