{
  "type": "Feature",
  "properties": {
    "iso:country":"CH",
    "sg:address":"Untere Greibengasse 2 4500 Solothurn. Postfach",
    "sg:city":"Solothurn",
    "sg:orig_category":"Architektur U Ingenieurb\u00fcros",
    "sg:phone":"+41 32 624 47 99",
    "sg:postcode":"4502",
    "sg:province":"Solothurn",
    "wof:name":"Friedli Geotechnik Ag Ingenieurb\u00fcro",
    "wof:placetype":"venue"
},
  "geometry": {"coordinates":[7.534122,47.209705],"type":"Point"}
}