{
  "type": "Feature",
  "properties": {
    "iso:country":"CH",
    "sg:address":"Forchstrasse 135 8032 Z\u00fcrich",
    "sg:city":"Zust",
    "sg:orig_category":"Satzherstellung U Reproduktion",
    "sg:phone":"+41 32 485 17 91",
    "sg:postcode":"32",
    "wof:name":"Herren Fotosatz Ag",
    "wof:placetype":"venue"
},
  "geometry": {"coordinates":[7.221765995,47.1908340454],"type":"Point"}
}