{
  "type": "Feature",
  "properties": {
    "iso:country":"CH",
    "sg:address":"Sinserstrasse 100",
    "sg:city":"Cham",
    "sg:orig_category":"RESTAURANTS: TEA-ROOMS",
    "sg:phone":"+41 41 780 10 88",
    "sg:postcode":"6330",
    "sg:province":"Zug",
    "wof:name":"Restaurant Rosengarten",
    "wof:placetype":"venue"
},
  "geometry": {"coordinates":[8.4553604126,47.1851615906],"type":"Point"}
}