{
  "type": "Feature",
  "properties": {
    "iso:country":"CH",
    "sg:address":"Gysnauweg 7 3400 Burgdorf. Postfach",
    "sg:city":"Burgdorf",
    "sg:orig_category":"Herstellung von Metallkonstruktionen Mechanik",
    "sg:postcode":"3401",
    "sg:province":"Bern",
    "wof:name":"Heinrich Tschanz",
    "wof:placetype":"venue"
},
  "geometry": {"coordinates":[7.6279687881,47.0596885681],"type":"Point"}
}