{
  "type": "Feature",
  "properties": {
    "iso:country":"CH",
    "sg:address":"Letziwiesstrasse 5",
    "sg:city":"L\u00fctisburg",
    "sg:orig_category":"Reiseb\u00fcros U Reiseveranstalter",
    "sg:phone":"+41 71 931 54 40",
    "sg:postcode":"9604",
    "sg:province":"St. Gallen",
    "wof:name":"Gb Reisen Und Handel Gmbh",
    "wof:placetype":"venue"
},
  "geometry": {"coordinates":[9.0824241638,47.3945617676],"type":"Point"}
}