{
  "type": "Feature",
  "properties": {
    "iso:country":"CH",
    "sg:address":"Cassina",
    "sg:city":"Gorduno",
    "sg:orig_category":"Detailhandel mit Waren verschiedener Art, Hauptrichtung Nahrungsmittel",
    "sg:phone":"+41 41 610 87 91",
    "sg:postcode":"6518",
    "sg:province":"Ticino",
    "wof:name":"Hansbeat Odermatt Olivenoel",
    "wof:placetype":"venue"
},
  "geometry": {"coordinates":[9.0319223404,46.2233085632],"type":"Point"}
}