{
  "type": "Feature",
  "properties": {
    "iso:country":"CH",
    "sg:address":"Jurastrasse 23 5102 Rupperswil. Postfach 128",
    "sg:city":"Rupperswil",
    "sg:orig_category":"Herstellung von Kakao, Schokoladeerzeugnissen U Zuckerwaren Herstellung von Kunststoffwaren",
    "sg:phone":"+41 62 889 40 40",
    "sg:postcode":"5102",
    "sg:province":"Aargau",
    "wof:name":"Max Riner Ag",
    "wof:placetype":"venue"
},
  "geometry": {"coordinates":[8.1224431992,47.3999862671],"type":"Point"}
}