{
  "type": "Feature",
  "properties": {
    "addr:full":"1727 Corpataux Fribourg 1727",
    "addr:housenumber":"1727",
    "addr:postcode":"1727",
    "addr:street":"Corpataux Fribourg",
    "iso:country":"CH",
    "sg:address":"1727",
    "sg:city":"Corpataux",
    "sg:orig_category":"Detailhandel mit Brot, Back U S\u00fcsswaren",
    "sg:phone":"+41 26 411 12 41",
    "sg:postcode":"1727",
    "sg:province":"Fribourg",
    "wof:name":"G\u00e9rard Monney Boulangerie",
    "wof:placetype":"venue"
},
  "geometry": {"coordinates":[7.09838,46.744541],"type":"Point"}
}