{
  "type": "Feature",
  "properties": {
    "iso:country":"CH",
    "sg:address":"Fischmarkt 15",
    "sg:city":"Liestal",
    "sg:orig_category":"Unternehmensberatung",
    "sg:postcode":"4410",
    "sg:province":"Basel-Landschaft",
    "wof:name":"Ibiv Gmbh",
    "wof:placetype":"venue"
},
  "geometry": {"coordinates":[7.7347841263,47.4835624695],"type":"Point"}
}