{
  "type": "Feature",
  "properties": {
    "iso:country":"CH",
    "sg:address":"Sihlstrasse 43 8001 Z\u00fcrich. Postfach",
    "sg:city":"Z\u00fcrich",
    "sg:orig_category":"Detailhandel mit Herrenbekleidung",
    "sg:phone":"+41 12212680",
    "sg:postcode":"8021",
    "sg:province":"Z\u00fcrich",
    "wof:name":"Schild Ag",
    "wof:placetype":"venue"
},
  "geometry": {"coordinates":[8.5355300903,47.3727684021],"type":"Point"}
}