{
  "type": "Feature",
  "properties": {
    "iso:country":"CH",
    "sg:address":"Nidlaustrasse 34",
    "sg:city":"Unteriberg",
    "sg:orig_category":"Herstellung von Werkzeugen",
    "sg:postcode":"8842",
    "sg:province":"Schwyz",
    "wof:name":"Fritz Bryner, Hartmetallwerkzeuge",
    "wof:placetype":"venue"
},
  "geometry": {"coordinates":[8.183930397,47.4136161804],"type":"Point"}
}