{
  "type": "Feature",
  "properties": {
    "iso:country":"CH",
    "sg:address":"Feldstrasse 133",
    "sg:city":"Z\u00fcrich",
    "sg:orig_category":"Hochschulen U h\u00f6here Ausbildung",
    "sg:phone":"+41 12914111",
    "sg:postcode":"8004",
    "sg:province":"Z\u00fcrich",
    "wof:name":"Interdisziplin\u00e4res Spitex-bildungszentrum Isb",
    "wof:placetype":"venue"
},
  "geometry": {"coordinates":[8.5243558884,47.3800239563],"type":"Point"}
}