{
  "type": "Feature",
  "properties": {
    "iso:country":"CH",
    "sg:address":"Alpsu Via 61",
    "sg:city":"Sedrun",
    "sg:orig_category":"Detailhandel mit Waren verschiedener Art, Hauptrichtung Nahrungsmittel",
    "sg:postcode":"7188",
    "sg:province":"Graubunden",
    "wof:name":"Associaziun Libra Da Consum Tujetsch",
    "wof:placetype":"venue"
},
  "geometry": {"coordinates":[8.7751913071,46.6805915833],"type":"Point"}
}