{
  "type": "Feature",
  "properties": {
    "iso:country":"CH",
    "sg:address":"Mittelbach",
    "sg:city":"Heimisbach",
    "sg:orig_category":"Detailhandel mit Brot, Back U S\u00fcsswaren Detailhandel mit Waren verschiedener Art, Hauptrichtung Nahr",
    "sg:phone":"+41 34 431 13 65",
    "sg:postcode":"3453",
    "sg:province":"Bern",
    "wof:name":"Fritz Kramer",
    "wof:placetype":"venue"
},
  "geometry": {"coordinates":[7.760311,47.011757],"type":"Point"}
}