{
  "type": "Feature",
  "properties": {
    "iso:country":"CH",
    "sg:address":"Alte Selfrangastrasse 2 7250 Klosters. Postfach",
    "sg:city":"Klosters",
    "sg:orig_category":"Fachdetailhandel in Verkaufsr\u00e4umen Grosshandel mit Sportartikeln",
    "sg:phone":"+41 81 422 55 24",
    "sg:postcode":"7250",
    "sg:province":"Graubunden",
    "wof:name":"S\u00f6re Agentur Sprecher Andreas",
    "wof:placetype":"venue"
},
  "geometry": {"coordinates":[9.8818311691,46.8630638123],"type":"Point"}
}