{
  "type": "Feature",
  "properties": {
    "iso:country":"CH",
    "sg:address":"Au Village 1436 Chamblon Case Postale 53",
    "sg:city":"Chamblon",
    "sg:orig_category":"Detailhandel mit M\u00f6beln U Haushaltsgegenst\u00e4nden",
    "sg:phone":"+41 32 861 21 21",
    "sg:postcode":"1436",
    "sg:province":"Vaud",
    "wof:name":"Agencements Techniques Modernes Atm Sa",
    "wof:placetype":"venue"
},
  "geometry": {"coordinates":[6.6037330627,46.7782745361],"type":"Point"}
}