{
  "type": "Feature",
  "properties": {
    "iso:country":"CH",
    "sg:address":"Thunstrasse 32 3150 Schwarzenburg. Postfach 30",
    "sg:city":"Schwarzenburg",
    "sg:orig_category":"Herstellung von Teppichen",
    "sg:phone":"+41 31 731 10 76",
    "sg:postcode":"3150",
    "sg:province":"Bern",
    "wof:name":"Lanz Martin",
    "wof:placetype":"venue"
},
  "geometry": {"coordinates":[7.3500599861,46.8188514709],"type":"Point"}
}