{
  "type": "Feature",
  "properties": {
    "iso:country":"CH",
    "sg:address":"Bifig",
    "sg:city":"Sennwald",
    "sg:orig_category":"Non-Classified Establishments",
    "sg:phone":"+41 27 957 11 06",
    "sg:postcode":"9466",
    "sg:province":"St. Gallen",
    "wof:name":"Anthamatten, Gebr., Sanit\u00e4r-installationen & Schreinerei",
    "wof:placetype":"venue"
},
  "geometry": {"coordinates":[7.9573631287,46.0964317322],"type":"Point"}
}