{
  "type": "Feature",
  "properties": {
    "iso:country":"CH",
    "sg:address":"Mooswiesstrasse 42",
    "sg:city":"Gossau",
    "sg:classifiers":[
        {
            "category":"Food & Beverages",
            "subcategory":"Groceries & Convenience Stores",
            "type":"Retail Goods"
        }
    ],
    "sg:phone":"+41 71 388 13 00",
    "sg:postcode":"9200",
    "sg:province":"St. Gallen",
    "sg:tags":[
        "flour",
        "meal"
    ],
    "wof:name":"Cash + Carry Angehrn Ag",
    "wof:placetype":"venue"
},
  "geometry": {"coordinates":[9.2609348297,47.4127044678],"type":"Point"}
}