{
  "type": "Feature",
  "properties": {
    "iso:country":"CH",
    "sg:address":"R\u00fcttihardstrasse 3/12",
    "sg:city":"Birsfelden",
    "sg:orig_category":"Unclassifiable Establishments",
    "sg:postcode":"4127",
    "sg:province":"Basel-Landschaft",
    "wof:name":"M. Blumenstein Transporte",
    "wof:placetype":"venue"
},
  "geometry": {"coordinates":[7.6296448708,47.5516052246],"type":"Point"}
}