{
  "type": "Feature",
  "properties": {
    "iso:country":"CH",
    "sg:address":"Via Giuseppe Motta 7 6900 Lugano. Postfach",
    "sg:city":"Lugano",
    "sg:orig_category":"Sonstiger Grosshandel",
    "sg:postcode":"6900",
    "sg:province":"Ticino",
    "wof:name":"La Svolta Sagl",
    "wof:placetype":"venue"
},
  "geometry": {"coordinates":[8.9498710632,46.0038261414],"type":"Point"}
}