{
  "type": "Feature",
  "properties": {
    "iso:country":"CH",
    "sg:address":"Champriond Route De 3 1700 Fribourg. Postfach",
    "sg:city":"Fribourg",
    "sg:orig_category":"Stukkateurgewerbe, Gipserei U Verputzerei",
    "sg:phone":"+41 26 424 17 20",
    "sg:postcode":"1700",
    "sg:province":"Fribourg",
    "wof:name":"Polygyps, Eraslan Ahmet Entreprise De Gypserie, R\u00e9novation",
    "wof:placetype":"venue"
},
  "geometry": {"coordinates":[7.1422920227,46.7943077087],"type":"Point"}
}