{
  "type": "Feature",
  "properties": {
    "iso:country":"CH",
    "sg:address":"Z\u00fcrcherstrasse 218",
    "sg:city":"Frauenfeld",
    "sg:orig_category":"Vereine Quartier",
    "sg:phone":"+41 52 721 13 61",
    "sg:postcode":"8500",
    "sg:province":"Thurgau",
    "wof:name":"Quartierverein Vorstadt",
    "wof:placetype":"venue"
},
  "geometry": {"coordinates":[8.9006757736,47.5587005615],"type":"Point"}
}