{
  "type": "Feature",
  "properties": {
    "iso:country":"CH",
    "sg:address":"Ahornweg 11 3012 Bern. Postfach",
    "sg:city":"Bern",
    "sg:orig_category":"Grosshandel mit Holz U Baustoffen Herstellung von Bergwerks U Baumaschinen",
    "sg:phone":"+41 31 302 51 51",
    "sg:postcode":"3005",
    "sg:province":"Bern",
    "wof:name":"Wiederkehr Ag, Buchrain, Filiale Bern Bauwerkzeuge, Malerwerkzeuge, Fassaden, Rollger\u00fcsete; Handel, Vermiet Ung, Usw",
    "wof:placetype":"venue"
},
  "geometry": {"coordinates":[7.4356851578,46.9542770386],"type":"Point"}
}