{
  "type": "Feature",
  "properties": {
    "iso:country":"CH",
    "sg:address":"Hauptstrasse 23a",
    "sg:city":"Frieswil",
    "sg:orig_category":"Detailhandel mit Brot, Back U S\u00fcsswaren",
    "sg:phone":"+41 77536619",
    "sg:postcode":"3035",
    "sg:province":"Bern",
    "wof:name":"Hans Liechti B\u00e4ckerei Lebensmittel",
    "wof:placetype":"venue"
},
  "geometry": {"coordinates":[7.285063,46.995049],"type":"Point"}
}