{
  "type": "Feature",
  "properties": {
    "iso:country":"CH",
    "sg:address":"Rue Du Grand-ch\u00eane 1",
    "sg:city":"Lausanne",
    "sg:classifiers":[
        {
            "category":"Banks & Credit Unions",
            "subcategory":"Financial Services",
            "type":"Services"
        }
    ],
    "sg:phone":"+41 21 311 52 04",
    "sg:postcode":"1003",
    "sg:province":"Vaud",
    "sg:tags":[
        "industry"
    ],
    "wof:name":"Equitys Sa",
    "wof:placetype":"venue"
},
  "geometry": {"coordinates":[6.6319541931,46.5195159912],"type":"Point"}
}