{
  "type": "Feature",
  "properties": {
    "iso:country":"CH",
    "sg:address":"Alte Landstrasse 53b",
    "sg:city":"Oberrieden",
    "sg:orig_category":"Erbringung von Dienstleistungen f\u00fcr Unternehmen",
    "sg:postcode":"8942",
    "sg:province":"Z\u00fcrich",
    "wof:name":"Caridon Financial Services Gmbh",
    "wof:placetype":"venue"
},
  "geometry": {"coordinates":[8.580163002,47.2736930847],"type":"Point"}
}