{
  "type": "Feature",
  "properties": {
    "iso:country":"CH",
    "sg:address":"B\u00fcntenriet 8890 Flums. Postfach 108",
    "sg:city":"Flums",
    "sg:orig_category":"Herstellung von Kunststoffwaren Herstellung von Metallerzeugnissen ohne Maschinenbau",
    "sg:phone":"+41 81 733 25 25",
    "sg:postcode":"8890",
    "sg:province":"St. Gallen",
    "wof:name":"Schneider W. & Co Ag Werk Flums",
    "wof:placetype":"venue"
},
  "geometry": {"coordinates":[9.3513689041,47.0931930542],"type":"Point"}
}