{
  "type": "Feature",
  "properties": {
    "addr:full":"Zelgstrasse 9 8280 Kreuzlingen. Postfach 24 Kreuzlingen Thurgau 8280",
    "addr:housenumber":"9;24",
    "addr:postcode":"8280;8280",
    "addr:street":"Zelgstrasse;Postfach",
    "iso:country":"CH",
    "sg:address":"Zelgstrasse 9 8280 Kreuzlingen. Postfach 24",
    "sg:city":"Kreuzlingen",
    "sg:orig_category":"Detailhandel mit Computern U Software Informatikdienste",
    "sg:phone":"+41 71 686 91 11",
    "sg:postcode":"8280",
    "sg:province":"Thurgau",
    "wof:name":"Bdk Informatik Ag",
    "wof:placetype":"venue"
},
  "geometry": {"coordinates":[9.201754,47.642426],"type":"Point"}
}