{
  "type": "Feature",
  "properties": {
    "iso:country":"CH",
    "sg:address":"Frohheimweg 26",
    "sg:city":"Olten",
    "sg:orig_category":"Schulpflegen",
    "sg:phone":"+41 62 212 77 19",
    "sg:postcode":"4600",
    "sg:province":"Solothurn",
    "wof:name":"Rektorat Der Schulen Von Olten",
    "wof:placetype":"venue"
},
  "geometry": {"coordinates":[7.8999900818,47.3534507751],"type":"Point"}
}