{
  "type": "Feature",
  "properties": {
    "addr:full":"Rudenzweg 14 Z\u00fcrich Z\u00fcrich 8048",
    "addr:housenumber":"14",
    "addr:postcode":"8048",
    "addr:street":"Rudenzweg",
    "iso:country":"CH",
    "sg:address":"Rudenzweg 14",
    "sg:city":"Z\u00fcrich",
    "sg:orig_category":"Allgemeiner Hoch U Tiefbau",
    "sg:phone":"+41 14933535",
    "sg:postcode":"8048",
    "sg:province":"Z\u00fcrich",
    "wof:name":"Rezibau Gmbh",
    "wof:placetype":"venue"
},
  "geometry": {"coordinates":[8.498322,47.384613],"type":"Point"}
}