{
  "type": "Feature",
  "properties": {
    "iso:country":"CH",
    "sg:address":"Dorfstrasse 32",
    "sg:city":"Uetendorf",
    "sg:orig_category":"RESTAURANTS: TEA-ROOMS",
    "sg:phone":"+41 31 747 72 40",
    "sg:postcode":"3661",
    "sg:province":"Bern",
    "wof:name":"Restaurant Zum L\u00f6wen, Yvette Schaller & Franz Studer",
    "wof:placetype":"venue"
},
  "geometry": {"coordinates":[7.2399301529,46.9022407532],"type":"Point"}
}