{
  "type": "Feature",
  "properties": {
    "iso:country":"CH",
    "sg:address":"Sonnenwiesenstrasse 9",
    "sg:city":"Kreuzlingen",
    "sg:orig_category":"Herstellung von elektrischen Ausr\u00fcstungen f\u00fcr Motoren U Fahrzeuge",
    "sg:phone":"+41 71 688 22 61",
    "sg:postcode":"8280",
    "sg:province":"Thurgau",
    "wof:name":"Neuweiler Kurt.",
    "wof:placetype":"venue"
},
  "geometry": {"coordinates":[9.189576149,47.6457061768],"type":"Point"}
}