{
  "type": "Feature",
  "properties": {
    "addr:full":"Alte Tiefenaustrasse 6 Bern Bern 3050",
    "addr:housenumber":"6",
    "addr:postcode":"3050",
    "addr:street":"Alte Tiefenaustrasse",
    "iso:country":"CH",
    "sg:address":"Alte Tiefenaustrasse 6",
    "sg:city":"Bern",
    "sg:classifiers":[
        {
            "category":"Industrial Area",
            "type":"Public Place"
        }
    ],
    "sg:phone":"+41 31 342 11 11",
    "sg:postcode":"3050",
    "sg:province":"Bern",
    "sg:tags":[
        "large",
        "private"
    ],
    "wof:name":"Swisscom Ag",
    "wof:placetype":"venue"
},
  "geometry": {"coordinates":[7.44821,46.948021],"type":"Point"}
}