{
  "type": "Feature",
  "properties": {
    "iso:country":"CH",
    "sg:address":"Fabrikstrasse",
    "sg:city":"Uzwil",
    "sg:orig_category":"Eisengiesserei Giessereiindustrie",
    "sg:phone":"+41 71 955 88 00",
    "sg:postcode":"9240",
    "sg:province":"St. Gallen",
    "wof:name":"Benninger Guss Ag",
    "wof:placetype":"venue"
},
  "geometry": {"coordinates":[9.1386299133,47.437789917],"type":"Point"}
}