{
  "type": "Feature",
  "properties": {
    "iso:country":"CH",
    "sg:address":"Lausanne Route De 17 1400 Yverdon-les-bains. Postfach",
    "sg:city":"Yverdon-les-bains",
    "sg:orig_category":"Vermietung U Verpachtung von eigenen Immobilien",
    "sg:postcode":"1400",
    "sg:province":"Vaud",
    "wof:name":"Novabital Sa",
    "wof:placetype":"venue"
},
  "geometry": {"coordinates":[6.6504621506,46.7653083801],"type":"Point"}
}