{
  "type": "Feature",
  "properties": {
    "addr:full":"Chemin De Planta 5 Cologny Gen\u00e8ve 1223",
    "addr:housenumber":"5",
    "addr:postcode":"1223",
    "addr:street":"Chemin De Planta",
    "iso:country":"CH",
    "sg:address":"Chemin De Planta 5",
    "sg:city":"Cologny",
    "sg:orig_category":"Datenverarbeitungsdienste Softwareentwicklung U beratung",
    "sg:phone":"+41 22 840 07 25",
    "sg:postcode":"1223",
    "sg:province":"Gen\u00e8ve",
    "wof:name":"Morger Heinz W.",
    "wof:placetype":"venue"
},
  "geometry": {"coordinates":[6.187268,46.213882],"type":"Point"}
}