{
  "type": "Feature",
  "properties": {
    "iso:country":"CH",
    "sg:address":"Felderstrasse 7",
    "sg:city":"Schattdorf",
    "sg:orig_category":"Malerei",
    "sg:phone":"+41 41 870 61 70",
    "sg:postcode":"6467",
    "sg:province":"Uri",
    "wof:name":"Walter Dittli Malergesch\u00e4ft",
    "wof:placetype":"venue"
},
  "geometry": {"coordinates":[8.6543445587,46.8680686951],"type":"Point"}
}