{
  "type": "Feature",
  "properties": {
    "iso:country":"CH",
    "sg:address":"Sonnmatt 2",
    "sg:city":"Allenwinden",
    "sg:orig_category":"Markt U Meinungsforschung",
    "sg:postcode":"6319",
    "sg:province":"Zug",
    "wof:name":"Diatech Electronics Gmbh",
    "wof:placetype":"venue"
},
  "geometry": {"coordinates":[8.5542783737,47.166305542],"type":"Point"}
}