{
  "type": "Feature",
  "properties": {
    "iso:country":"CH",
    "sg:address":"H\u00f6henweg 6",
    "sg:city":"Huttwil",
    "sg:orig_category":"Detailhandel mit Gebrauchtwaren in Verkaufsr\u00e4umen",
    "sg:phone":"+41 62 962 30 03",
    "sg:postcode":"4950",
    "sg:province":"Bern",
    "wof:name":"Brockenstube Der Heilsarmee",
    "wof:placetype":"venue"
},
  "geometry": {"coordinates":[7.8513917923,47.1154441833],"type":"Point"}
}