{
  "type": "Feature",
  "properties": {
    "iso:country":"CH",
    "sg:address":"Via Della Posta 6 6600 Locarno. Postfach Caselle Postale 1050",
    "sg:city":"Locarno",
    "sg:orig_category":"Advokaturb\u00fcros Notariate",
    "sg:phone":"+41 91 760 09 00",
    "sg:postcode":"6601",
    "sg:province":"Ticino",
    "wof:name":"Patrizia Bett\u00e8 Studio Legale E Notarile",
    "wof:placetype":"venue"
},
  "geometry": {"coordinates":[8.797097,46.168465],"type":"Point"}
}