{
  "type": "Feature",
  "properties": {
    "addr:full":"Oberstadtstrasse 8 Frauenfeld Thurgau 8500",
    "addr:housenumber":"8",
    "addr:postcode":"8500",
    "addr:street":"Oberstadtstrasse",
    "iso:country":"CH",
    "sg:address":"Oberstadtstrasse 8",
    "sg:city":"Frauenfeld",
    "sg:orig_category":"Detailhandel mit Bekleidung",
    "sg:postcode":"8500",
    "sg:province":"Thurgau",
    "wof:name":"La Jeanette Moden Hadler",
    "wof:placetype":"venue"
},
  "geometry": {"coordinates":[8.89702,47.557308],"type":"Point"}
}