{
  "type": "Feature",
  "properties": {
    "iso:country":"CH",
    "sg:address":"Eugen Huber-strasse 11 8048 Z\u00fcrich. Postfach",
    "sg:city":"Z\u00fcrich",
    "sg:orig_category":"Schiffsbau ohne Boots U Yachtbau",
    "sg:postcode":"8048",
    "sg:province":"Z\u00fcrich",
    "wof:name":"Mare-diesel-produkte Ag",
    "wof:placetype":"venue"
},
  "geometry": {"coordinates":[8.4853439331,47.3847732544],"type":"Point"}
}