{
  "type": "Feature",
  "properties": {
    "iso:country":"CH",
    "sg:address":"Pf\u00e4ndwiesenstrasse 1",
    "sg:city":"Opfikon",
    "sg:orig_category":"Webdesign",
    "sg:phone":"+41 52 232 14 56",
    "sg:postcode":"8152",
    "sg:province":"Z\u00fcrich",
    "wof:name":"Go Out Production Gmbh",
    "wof:placetype":"venue"
},
  "geometry": {"coordinates":[8.7607221603,47.4835586548],"type":"Point"}
}