{
  "type": "Feature",
  "properties": {
    "iso:country":"CH",
    "sg:address":"Steinberggasse 41",
    "sg:city":"Winterthur",
    "sg:orig_category":"Detailhandel mit Antiquit\u00e4ten",
    "sg:phone":"+41 52 212 15 55",
    "sg:postcode":"8400",
    "sg:province":"Z\u00fcrich",
    "wof:name":"Plunder-kabinett Antiquit\u00e4ten",
    "wof:placetype":"venue"
},
  "geometry": {"coordinates":[8.728347,47.498135],"type":"Point"}
}