{
  "type": "Feature",
  "properties": {
    "iso:country":"CH",
    "sg:address":"Kasernenstrasse 88",
    "sg:city":"Herisau",
    "sg:orig_category":"Herstellung von Fenstern U T\u00fcren aus Holz Herstellung von Konstruktionsteilen, Fertigbauteilen U Aus",
    "sg:phone":"+41 71 353 09 53",
    "sg:postcode":"9100",
    "sg:province":"Appenzell Ausserrhoden",
    "wof:name":"Blumer Techno Fenster Ag",
    "wof:placetype":"venue"
},
  "geometry": {"coordinates":[9.29226017,47.3908119202],"type":"Point"}
}