{
  "type": "Feature",
  "properties": {
    "iso:country":"CH",
    "sg:address":"Immeuble Le Postillon",
    "sg:city":"Crans-sur-sierre",
    "sg:orig_category":"Detailhandel mit Antiquit\u00e4ten Kunsthandel",
    "sg:phone":"+41 27 481 68 39",
    "sg:postcode":"3963",
    "sg:province":"Valais",
    "wof:name":"Anna Von Siebenthal Galerie D'art Des Neiges",
    "wof:placetype":"venue"
},
  "geometry": {"coordinates":[7.469152,46.305954],"type":"Point"}
}