{
  "type": "Feature",
  "properties": {
    "iso:country":"CH",
    "sg:address":"Hessstrasse 45",
    "sg:city":"Liebefeld",
    "sg:orig_category":"Detailhandel mit Waren verschiedener Art, Hauptrichtung Nahrungsmittel",
    "sg:phone":"+41 17132585",
    "sg:postcode":"3097",
    "sg:province":"Bern",
    "wof:name":"Migros-markt",
    "wof:placetype":"venue"
},
  "geometry": {"coordinates":[8.5379734039,47.291305542],"type":"Point"}
}