{
  "type": "Feature",
  "properties": {
    "iso:country":"CH",
    "sg:address":"Rue Du Vieux-moulin 57",
    "sg:city":"Court\u00e9telle",
    "sg:orig_category":"Bauschreinerei",
    "sg:postcode":"2852",
    "sg:province":"Jura",
    "wof:name":"Antonio Di Biase Menuiserie",
    "wof:placetype":"venue"
},
  "geometry": {"coordinates":[7.304353,47.337643],"type":"Point"}
}