{
  "type": "Feature",
  "properties": {
    "iso:country":"CH",
    "sg:address":"Sigmundstrasse 1",
    "sg:city":"Liestal",
    "sg:orig_category":"Fernmeldedienste",
    "sg:postcode":"4410",
    "sg:province":"Basel-Landschaft",
    "wof:name":"Idea Information Ag",
    "wof:placetype":"venue"
},
  "geometry": {"coordinates":[7.7433481216,47.4788589478],"type":"Point"}
}