{
  "type": "Feature",
  "properties": {
    "iso:country":"CH",
    "sg:address":"Via Valmara 22",
    "sg:city":"Brissago",
    "sg:orig_category":"Werbeagenturen",
    "sg:postcode":"6614",
    "sg:province":"Ticino",
    "wof:name":"Kit-marketing Ag",
    "wof:placetype":"venue"
},
  "geometry": {"coordinates":[8.7023649216,46.1105194092],"type":"Point"}
}