{
  "type": "Feature",
  "properties": {
    "iso:country":"CH",
    "sg:address":"Schindlersteig 5 8006 Z\u00fcrich. Postfach",
    "sg:city":"Z\u00fcrich",
    "sg:orig_category":"Personal U Stellenvermittlung Sonstige mit der Informatik verbundene T\u00e4tigkeiten",
    "sg:phone":"+41 13609300",
    "sg:postcode":"8006",
    "sg:province":"Z\u00fcrich",
    "wof:name":"Freestar-consulting Gmbh Personen Und Berufsberatung",
    "wof:placetype":"venue"
},
  "geometry": {"coordinates":[8.5398054123,47.3896827698],"type":"Point"}
}