{
  "type": "Feature",
  "properties": {
    "iso:country":"CH",
    "sg:address":"Unterdorfstrasse 12",
    "sg:city":"Flawil",
    "sg:orig_category":"Maler U Glasergewerbe Verlegen von Fussboden",
    "sg:phone":"+41 71 393 16 20",
    "sg:postcode":"9230",
    "sg:province":"St. Gallen",
    "wof:name":"Hm Schadegg",
    "wof:placetype":"venue"
},
  "geometry": {"coordinates":[9.1884422302,47.4132804871],"type":"Point"}
}