{
  "type": "Feature",
  "properties": {
    "iso:country":"CH",
    "sg:address":"Zeughausplatz 27",
    "sg:city":"Liestal",
    "sg:orig_category":"Arbeitnehmerverb\u00e4nde",
    "sg:phone":"+41 61 921 21 55",
    "sg:postcode":"4410",
    "sg:province":"Basel-Landschaft",
    "wof:name":"Gewerkschaft Bau & Industrie Sektion Beider Basel",
    "wof:placetype":"venue"
},
  "geometry": {"coordinates":[7.735724,47.485268],"type":"Point"}
}