{
  "type": "Feature",
  "properties": {
    "iso:country":"CH",
    "sg:address":"Gaishaus",
    "sg:city":"Hugelshofen",
    "sg:orig_category":"S\u00e4gewerke",
    "sg:phone":"+41 71 657 12 19",
    "sg:postcode":"8565",
    "sg:province":"Thurgau",
    "wof:name":"Walter Forster",
    "wof:placetype":"venue"
},
  "geometry": {"coordinates":[9.1162338257,47.5984420776],"type":"Point"}
}