{
  "type": "Feature",
  "properties": {
    "iso:country":"CH",
    "sg:address":"Hotel Seilbahn",
    "sg:city":"Rh\u00e4z\u00fcns",
    "sg:classifiers":[
        {
            "category":"Travel",
            "subcategory":"Hotels & Motels",
            "type":"Entertainment"
        }
    ],
    "sg:phone":"+41 81 641 11 49",
    "sg:postcode":"7403",
    "sg:province":"Graubunden",
    "sg:tags":[
        "hotels",
        "mit",
        "restaurant"
    ],
    "wof:name":"Simoness Erika",
    "wof:placetype":"venue"
},
  "geometry": {"coordinates":[9.3979654312,46.7985496521],"type":"Point"}
}