{
  "type": "Feature",
  "properties": {
    "iso:country":"CH",
    "sg:address":"Le Parlet 2",
    "sg:city":"Lamboing",
    "sg:orig_category":"Zimmerei, Dachdeckerei, Bauspenglerei U Abdichtung Zimmerei, Ingenieurholzbau",
    "sg:phone":"+41 32 315 18 41",
    "sg:postcode":"2516",
    "sg:province":"Bern",
    "wof:name":"Samuel Carnal Charpente & Couverture",
    "wof:placetype":"venue"
},
  "geometry": {"coordinates":[7.1331129074,47.1170349121],"type":"Point"}
}