{
  "type": "Feature",
  "properties": {
    "iso:country":"CH",
    "sg:address":"Eppenberg 9242 Oberuzwil. Postfach",
    "sg:city":"Oberuzwil",
    "sg:orig_category":"RESTAURANTS: TEA-ROOMS",
    "sg:postcode":"9242",
    "sg:province":"St. Gallen",
    "wof:name":"Emmi Sutter, Rest. Eppenberg",
    "wof:placetype":"venue"
},
  "geometry": {"coordinates":[9.1374282837,47.4107933044],"type":"Point"}
}