{
  "type": "Feature",
  "properties": {
    "iso:country":"CH",
    "sg:address":"Bahnhofstrasse 25 3800 Interlaken. Postfach",
    "sg:city":"Interlaken",
    "sg:orig_category":"Detailhandel mit Bekleidung Fachdetailhandel in Verkaufsr\u00e4umen",
    "sg:phone":"+41 22 343 78 83",
    "sg:postcode":"3800",
    "sg:province":"Bern",
    "wof:name":"William Thomas Sports",
    "wof:placetype":"venue"
},
  "geometry": {"coordinates":[6.1396,46.18399],"type":"Point"}
}