{
  "type": "Feature",
  "properties": {
    "iso:country":"CH",
    "sg:address":"Cure Cath",
    "sg:city":"Vicques",
    "sg:orig_category":"Interessenvertretungen",
    "sg:postcode":"2824",
    "sg:province":"Jura",
    "wof:name":"Fonds De Missions Et Retraites De La Paroisse Catholique-romaine De Vicques \u00e0 Vicques",
    "wof:placetype":"venue"
},
  "geometry": {"coordinates":[7.4162049294,47.3487281799],"type":"Point"}
}