{
  "type": "Feature",
  "properties": {
    "iso:country":"CH",
    "sg:address":"Brodlaube 18",
    "sg:city":"Rheinfelden",
    "sg:orig_category":"Softwareentwicklung U beratung",
    "sg:postcode":"4310",
    "sg:province":"Aargau",
    "wof:name":"H\u00fcbscher Edv Gmbh",
    "wof:placetype":"venue"
},
  "geometry": {"coordinates":[7.7937231064,47.5544242859],"type":"Point"}
}