{
  "type": "Feature",
  "properties": {
    "iso:country":"CH",
    "sg:address":"Weiherstrasse 4 6020 Emmenbr\u00fccke. Postfach",
    "sg:city":"Emmenbr\u00fccke",
    "sg:orig_category":"Handel mit Motorr\u00e4dern, Teilen U Zubeh\u00f6r Instandhaltung U Reparatur von Motorr\u00e4dern",
    "sg:phone":"+41 41 280 98 09",
    "sg:postcode":"6020",
    "sg:province":"Luzern",
    "wof:name":"Bike Underground B\u00fcrgi R.",
    "wof:placetype":"venue"
},
  "geometry": {"coordinates":[8.2642917633,47.0829658508],"type":"Point"}
}