{
  "type": "Feature",
  "properties": {
    "iso:country":"CH",
    "sg:address":"Baarerstrasse 96 6302 Zug. Postfach",
    "sg:city":"Zug",
    "sg:orig_category":"Hochschulen U h\u00f6here Ausbildung",
    "sg:phone":"+41 41 766 02 25",
    "sg:postcode":"6302",
    "sg:province":"Zug",
    "wof:name":"Ipv Institut Profiliertes Verhalten Ag",
    "wof:placetype":"venue"
},
  "geometry": {"coordinates":[8.5184669495,47.1785049438],"type":"Point"}
}