{
  "type": "Feature",
  "properties": {
    "iso:country":"CH",
    "sg:address":"Hornbachstrasse 69",
    "sg:city":"Z\u00fcrich",
    "sg:orig_category":"Massagestudios",
    "sg:phone":"+41 13837421",
    "sg:postcode":"8008",
    "sg:province":"Z\u00fcrich",
    "wof:name":"Jean-louis Kilcher Massagen",
    "wof:placetype":"venue"
},
  "geometry": {"coordinates":[8.5567970276,47.356716156],"type":"Point"}
}