{
  "type": "Feature",
  "properties": {
    "iso:country":"CH",
    "sg:address":"Chemin Des Vauches 5",
    "sg:city":"Porrentruy",
    "sg:orig_category":"Herstellung von Radio U Fernsehger\u00e4ten sowie phono U videotechnischen Ger\u00e4ten",
    "sg:phone":"+41 32 466 44 07",
    "sg:postcode":"2900",
    "sg:province":"Jura",
    "wof:name":"T\u00e9l\u00e9-service Chappuis Yves",
    "wof:placetype":"venue"
},
  "geometry": {"coordinates":[7.0792851448,47.4170761108],"type":"Point"}
}