{
  "type": "Feature",
  "properties": {
    "iso:country":"CH",
    "sg:address":"Keltenstrasse 45",
    "sg:city":"Z\u00fcrich",
    "sg:orig_category":"Kunsthandel",
    "sg:phone":"+41 12613737",
    "sg:postcode":"8044",
    "sg:province":"Z\u00fcrich",
    "wof:name":"Kelten-keller Claude Paillard Galerie",
    "wof:placetype":"venue"
},
  "geometry": {"coordinates":[8.5645637512,47.3755187988],"type":"Point"}
}