{
  "type": "Feature",
  "properties": {
    "iso:country":"CH",
    "sg:address":"Turnplatzstrasse 1",
    "sg:city":"Menziken",
    "sg:classifiers":[
        {
            "category":"Restaurant",
            "type":"Food & Drink"
        }
    ],
    "sg:phone":"+41 62 771 18 01",
    "sg:postcode":"5737",
    "sg:province":"Aargau",
    "wof:name":"Restaurant Wynental",
    "wof:placetype":"venue"
},
  "geometry": {"coordinates":[8.1890277863,47.2382087708],"type":"Point"}
}