{
  "type": "Feature",
  "properties": {
    "iso:country":"CH",
    "sg:address":"Postw\u00e4ldli 13",
    "sg:city":"Freienbach",
    "sg:orig_category":"Fachdetailhandel in Verkaufsr\u00e4umen",
    "sg:postcode":"8807",
    "sg:province":"Schwyz",
    "wof:name":"Kwb Kunstwertbrief Ag",
    "wof:placetype":"venue"
},
  "geometry": {"coordinates":[8.752951622,47.2056312561],"type":"Point"}
}