{
  "type": "Feature",
  "properties": {
    "addr:full":"Ankerstrasse 116 8004 Z\u00fcrich. Postfach Z\u00fcrich Z\u00fcrich 8001",
    "addr:housenumber":"116",
    "addr:postcode":"8004 zuerich. postfach;8001",
    "addr:street":"Ankerstrasse",
    "iso:country":"CH",
    "sg:address":"Ankerstrasse 116 8004 Z\u00fcrich. Postfach",
    "sg:city":"Z\u00fcrich",
    "sg:orig_category":"Detailhandel mit B\u00fcchern, Zeitungen, Schreib U Papeteriewaren",
    "sg:phone":"+41 12428931",
    "sg:postcode":"8001",
    "sg:province":"Z\u00fcrich",
    "wof:name":"Y\u00fckselen G. Kiosk",
    "wof:placetype":"venue"
},
  "geometry": {"coordinates":[8.528376,47.376446],"type":"Point"}
}