{
  "type": "Feature",
  "properties": {
    "iso:country":"CH",
    "sg:address":"Schwarzenbach 748",
    "sg:city":"Gohl",
    "sg:orig_category":"Innenausbau Zimmerei, Ingenieurholzbau",
    "sg:phone":"+41 34 402 69 78",
    "sg:postcode":"3553",
    "sg:province":"Bern",
    "wof:name":"Thomas & Ruth Baumgartner Holzbau & Innenausbau",
    "wof:placetype":"venue"
},
  "geometry": {"coordinates":[7.8069791794,46.9549293518],"type":"Point"}
}