{
  "type": "Feature",
  "properties": {
    "iso:country":"CH",
    "sg:address":"St. Alban-vorstadt 53a",
    "sg:city":"Basel",
    "sg:orig_category":"Non-Classified Establishments",
    "sg:postcode":"4052",
    "sg:province":"Basel-Stadt",
    "wof:name":"Von Ow Klaviertransporte",
    "wof:placetype":"venue"
},
  "geometry": {"coordinates":[7.5979142189,47.5544624329],"type":"Point"}
}