{
  "type": "Feature",
  "properties": {
    "addr:full":"Mooshaldenstrasse 40 M\u00e4nnedorf Z\u00fcrich 8708",
    "addr:housenumber":"40",
    "addr:postcode":"8708",
    "addr:street":"Mooshaldenstrasse;Zuerich",
    "iso:country":"CH",
    "sg:address":"Mooshaldenstrasse 40",
    "sg:city":"M\u00e4nnedorf",
    "sg:orig_category":"Arztpraxen",
    "sg:phone":"+41 19204414",
    "sg:postcode":"8708",
    "sg:province":"Z\u00fcrich",
    "wof:name":"Dr.med.daniel Huber Arzt F.allgemeine Medizin Fmh",
    "wof:placetype":"venue"
},
  "geometry": {"coordinates":[8.703206,47.250458],"type":"Point"}
}