{
  "type": "Feature",
  "properties": {
    "iso:country":"CH",
    "sg:address":"Sch\u00e4ublinstrasse 68 4102 Binningen. Postfach",
    "sg:city":"Binningen",
    "sg:orig_category":"Unclassifiable Establishments",
    "sg:phone":"+41 61 361 38 44",
    "sg:postcode":"4102",
    "sg:province":"Basel-Landschaft",
    "wof:name":"Keramik-&licht-dekor Leibundgut Marianne Keramikerzeugnisse Usw.; Herstellung, Vertrieb",
    "wof:placetype":"venue"
},
  "geometry": {"coordinates":[7.5834798813,47.5337028503],"type":"Point"}
}