{
  "type": "Feature",
  "properties": {
    "iso:country":"CH",
    "sg:address":"Rue Du Rh\u00f4ne 40",
    "sg:city":"Gen\u00e8ve",
    "sg:orig_category":"Sonstige Finanzierungsinstitutionen Vermietung U Verpachtung von eigenen Immobilien",
    "sg:phone":"+41 81 852 45 51",
    "sg:postcode":"1204",
    "sg:province":"Gen\u00e8ve",
    "wof:name":"Gualdana Ag",
    "wof:placetype":"venue"
},
  "geometry": {"coordinates":[9.9117059708,46.559841156],"type":"Point"}
}