{
  "type": "Feature",
  "properties": {
    "iso:country":"CH",
    "sg:address":"Rue Du Ch\u00e2teau-d'en-bas 1",
    "sg:city":"Bulle",
    "sg:orig_category":"Allgemeiner Hoch U Tiefbau",
    "sg:postcode":"1630",
    "sg:province":"Fribourg",
    "wof:name":"Forma Constructions Sa, Succursale De Bulle",
    "wof:placetype":"venue"
},
  "geometry": {"coordinates":[7.082385,46.584309],"type":"Point"}
}