{
  "type": "Feature",
  "properties": {
    "iso:country":"CH",
    "sg:address":"Ocostrasse 20",
    "sg:city":"Zurzach",
    "sg:classifiers":[
        {
            "category":"Wholesale",
            "subcategory":"Construction Materials",
            "type":"Manufacturing & Wholesale Goods"
        }
    ],
    "sg:phone":"+41 56 249 44 30",
    "sg:postcode":"5330",
    "sg:province":"Aargau",
    "sg:tags":[
        "mould",
        "injection"
    ],
    "wof:name":"Willy Kalt",
    "wof:placetype":"venue"
},
  "geometry": {"coordinates":[8.2907733917,47.5918197632],"type":"Point"}
}