{
  "type": "Feature",
  "properties": {
    "iso:country":"CH",
    "sg:address":"Dammbodenstrasse 8",
    "sg:city":"Volketswil",
    "sg:orig_category":"Zahnarztpraxen",
    "sg:phone":"+41 19455781",
    "sg:postcode":"8604",
    "sg:province":"Z\u00fcrich",
    "wof:name":"Dr. Med. Dent. Georg Szegvary Zahnarzt",
    "wof:placetype":"venue"
},
  "geometry": {"coordinates":[8.6631326675,47.3856468201],"type":"Point"}
}