{
  "type": "Feature",
  "properties": {
    "iso:country":"CH",
    "sg:address":"Sihlhallenstrasse 5-7",
    "sg:city":"Z\u00fcrich",
    "sg:orig_category":"Detailhandel mit Waren verschiedener Art, Hauptrichtung Nahrungsmittel",
    "sg:phone":"+41 12423949",
    "sg:postcode":"8004",
    "sg:province":"Z\u00fcrich",
    "wof:name":"Denner Top Superdiscount",
    "wof:placetype":"venue"
},
  "geometry": {"coordinates":[8.527050972,47.3794975281],"type":"Point"}
}