{
  "type": "Feature",
  "properties": {
    "iso:country":"CH",
    "sg:address":"Via Nassa 1 6900 Lugano. Postfach",
    "sg:city":"Lugano",
    "sg:orig_category":"Detailhandel mit elektrischen Haushalts-,Radio U Fernsehger\u00e4ten sowie Musikinstrumenten",
    "sg:postcode":"6900",
    "sg:province":"Ticino",
    "wof:name":"Nordisk Boutique Stalder Susanne Sagl",
    "wof:placetype":"venue"
},
  "geometry": {"coordinates":[8.9508190155,46.0034713745],"type":"Point"}
}