{
  "type": "Feature",
  "properties": {
    "iso:country":"CH",
    "sg:address":"Baslerstrasse 24",
    "sg:city":"Umiken",
    "sg:orig_category":"Tankstellen",
    "sg:phone":"+41 56 450 28 25",
    "sg:postcode":"5222",
    "sg:province":"Aargau",
    "wof:name":"Markus Erb Garage & Tankstelle",
    "wof:placetype":"venue"
},
  "geometry": {"coordinates":[8.193104744,47.4836616516],"type":"Point"}
}