{
  "type": "Feature",
  "properties": {
    "iso:country":"CH",
    "sg:address":"Chemin De L'argili\u00e8re 28 1234 Vessy Case Postale",
    "sg:city":"Vessy",
    "sg:orig_category":"Grosshandel mit Nahrungsmitteln, Getr\u00e4nken U Tabakwaren Grosshandel mit Nahrungsmitteln, Getr\u00e4nken U",
    "sg:phone":"+41 22 890 01 30",
    "sg:postcode":"1234",
    "sg:province":"Gen\u00e8ve",
    "wof:name":"Imsynex S\u00e0rl Produits Alimentaires, Cosm\u00e9tiques; Commerce, Repr\u00e9sentation, Courtage",
    "wof:placetype":"venue"
},
  "geometry": {"coordinates":[6.1564660072,46.1747970581],"type":"Point"}
}