{
  "type": "Feature",
  "properties": {
    "iso:country":"CH",
    "sg:address":"Dorf 24",
    "sg:city":"Wald",
    "sg:classifiers":[
        {
            "category":"Military Area",
            "subcategory":"Air Force Base",
            "type":"Public Place"
        }
    ],
    "sg:phone":"+41 71 878 78 78",
    "sg:postcode":"9044",
    "sg:province":"Appenzell Ausserrhoden",
    "sg:tags":[
        "heaters",
        "electric"
    ],
    "wof:name":"Walser & Co Ag",
    "wof:placetype":"venue"
},
  "geometry": {"coordinates":[9.489115,47.415188],"type":"Point"}
}