{
  "type": "Feature",
  "properties": {
    "iso:country":"CH",
    "sg:address":"Spitalstrasse 52",
    "sg:city":"Grabs",
    "sg:orig_category":"Grosshandel mit keramischen Erzeugnissen, Glaswaren U Reinigungsmitteln Herstellung von Hohlglas",
    "sg:phone":"+41 81 771 75 63",
    "sg:postcode":"9472",
    "sg:province":"St. Gallen",
    "wof:name":"Werdenberger Glas Design, Gnehm Hedy",
    "wof:placetype":"venue"
},
  "geometry": {"coordinates":[9.4526071548,47.1727676392],"type":"Point"}
}