{
  "type": "Feature",
  "properties": {
    "iso:country":"CH",
    "sg:address":"Goldgasse 7 4500 Solothurn. Postfach",
    "sg:city":"Solothurn",
    "sg:orig_category":"Herstellung von keramischen Haushaltswaren U Ziergegenst\u00e4nden",
    "sg:postcode":"4500",
    "sg:province":"Solothurn",
    "wof:name":"Chillum Werkstatt Schmid Marcel",
    "wof:placetype":"venue"
},
  "geometry": {"coordinates":[7.5377840996,47.2071151733],"type":"Point"}
}