{
  "type": "Feature",
  "properties": {
    "iso:country":"CH",
    "sg:address":"Webereistrasse 66",
    "sg:city":"Adliswil",
    "sg:orig_category":"Elektroinstallation",
    "sg:phone":"+41 31 311 13 11",
    "sg:postcode":"8134",
    "sg:province":"Z\u00fcrich",
    "wof:name":"A. Steiger Elektro Ag",
    "wof:placetype":"venue"
},
  "geometry": {"coordinates":[7.4489412308,46.9480438232],"type":"Point"}
}