{
  "type": "Feature",
  "properties": {
    "iso:country":"CH",
    "sg:address":"Hauptstrasse 11",
    "sg:city":"R\u00fcnenberg",
    "sg:orig_category":"Kantonalbanken",
    "sg:phone":"+41 61 401 03 33",
    "sg:postcode":"4497",
    "sg:province":"Basel-Landschaft",
    "wof:name":"Basellandschaftliche Kantonalbank",
    "wof:placetype":"venue"
},
  "geometry": {"coordinates":[7.5549578667,47.5137214661],"type":"Point"}
}