{
  "type": "Feature",
  "properties": {
    "iso:country":"CH",
    "sg:address":"Angensteinerstrasse 16",
    "sg:city":"Basel",
    "sg:orig_category":"Hardwareberatung",
    "sg:phone":"+41 61 373 34 60",
    "sg:postcode":"4052",
    "sg:province":"Basel-Stadt",
    "wof:name":"Oliver L\u00fcscher L\u00fcscher Macmedia",
    "wof:placetype":"venue"
},
  "geometry": {"coordinates":[7.6035017967,47.5488891602],"type":"Point"}
}