{
  "type": "Feature",
  "properties": {
    "iso:country":"CH",
    "sg:address":"B\u00f6tt Via 6983 Magliaso. Postfach",
    "sg:city":"Magliaso",
    "sg:orig_category":"Sonstige mit Sport verbundene T\u00e4tigkeiten",
    "sg:postcode":"6983",
    "sg:province":"Ticino",
    "wof:name":"Golf Projects Academies Ltd, Uckfield, Succursale Di Magliaso Societ\u00e0 Commerciale Spec. Studio, Gestione Ecc. Di Scuole Di Golf",
    "wof:placetype":"venue"
},
  "geometry": {"coordinates":[8.8814296722,45.9820137024],"type":"Point"}
}