{
  "type": "Feature",
  "properties": {
    "iso:country":"CH",
    "sg:address":"Seestr. 18",
    "sg:city":"Thalwil",
    "sg:classifiers":[
        {
            "category":"Professional",
            "subcategory":"Business Services",
            "type":"Services"
        }
    ],
    "sg:phone":"+41 4117231410",
    "sg:postcode":"8800",
    "sg:province":"Z\u00fcrich",
    "sg:tags":[
        "information",
        "peripheral",
        "-",
        "softw",
        "technology",
        "advice"
    ],
    "wof:name":"Tradeware Ag",
    "wof:placetype":"venue"
},
  "geometry": {"coordinates":[8.577436,47.283512],"type":"Point"}
}