{
  "type": "Feature",
  "properties": {
    "iso:country":"CH",
    "sg:address":"Kurried",
    "sg:city":"Albligen",
    "sg:orig_category":"Mechanik Schlossereien",
    "sg:phone":"+41 79 691 31 82",
    "sg:postcode":"3183",
    "sg:province":"Bern",
    "wof:name":"B. M\u00e4der Gmbh",
    "wof:placetype":"venue"
},
  "geometry": {"coordinates":[7.316450119,46.8576164246],"type":"Point"}
}