{
  "type": "Feature",
  "properties": {
    "iso:country":"CH",
    "sg:address":"Avenue Edouard-baud 1225 Ch\u00eane-bourg Case Postale 72",
    "sg:city":"Ch\u00eane-bourg",
    "sg:orig_category":"Gartenbau Herstellung von sonstigen landwirtschaftlichen Maschinen",
    "sg:phone":"+41 22 348 66 22",
    "sg:postcode":"1225",
    "sg:province":"Gen\u00e8ve",
    "wof:name":"Eug\u00e8ne Baud Sa",
    "wof:placetype":"venue"
},
  "geometry": {"coordinates":[6.1950111389,46.1966171265],"type":"Point"}
}