{
  "type": "Feature",
  "properties": {
    "iso:country":"CH",
    "sg:address":"Guttet",
    "sg:city":"Feschel-guttet",
    "sg:orig_category":"Sonstige pers\u00f6nliche Dienstleistungen",
    "sg:postcode":"3956",
    "sg:province":"Valais",
    "wof:name":"Kundendienst K\u00f6ppel",
    "wof:placetype":"venue"
},
  "geometry": {"coordinates":[7.6684679985,46.3243484497],"type":"Point"}
}