{
  "type": "Feature",
  "properties": {
    "iso:country":"CH",
    "sg:address":"Graben\u00e4ckerstrasse 2",
    "sg:city":"Fislisbach",
    "sg:orig_category":"Bauspenglerei Sanit\u00e4rinstallation U Spenglerei",
    "sg:phone":"+41 71 352 18 86",
    "sg:postcode":"5442",
    "sg:province":"Aargau",
    "wof:name":"Willi Schiess Ag",
    "wof:placetype":"venue"
},
  "geometry": {"coordinates":[9.242228,47.383419],"type":"Point"}
}