{
  "type": "Feature",
  "properties": {
    "iso:country":"CH",
    "sg:address":"Hauptstrasse 24a",
    "sg:city":"Auswil",
    "sg:orig_category":"Non-Classified Establishments",
    "sg:postcode":"4944",
    "sg:province":"Bern",
    "wof:name":"Steinemann Beschallungstechnik",
    "wof:placetype":"venue"
},
  "geometry": {"coordinates":[7.8314270973,47.1364707947],"type":"Point"}
}