{
  "type": "Feature",
  "properties": {
    "iso:country":"CH",
    "sg:address":"Route De Ch\u00e9salles 18",
    "sg:city":"Marly",
    "sg:orig_category":"Grosshandel mit Milch, Milcherzeugnissen, Eiern, Speise\u00f6len U Nahrungsfetten",
    "sg:phone":"+41 26 439 99 99",
    "sg:postcode":"1723",
    "sg:province":"Fribourg",
    "wof:name":"Berger Sa Prod.frais & Surgel\u00e9s Fromages",
    "wof:placetype":"venue"
},
  "geometry": {"coordinates":[7.1579470634,46.7725105286],"type":"Point"}
}