{
  "type": "Feature",
  "properties": {
    "iso:country":"CH",
    "sg:address":"Philosophes Place Des 8 1205 Gen\u00e8ve. Postfach",
    "sg:city":"Gen\u00e8ve",
    "sg:orig_category":"Non-Classified Establishments",
    "sg:phone":"+41 22 781 11 11",
    "sg:postcode":"1205",
    "sg:province":"Gen\u00e8ve",
    "wof:name":"Soci\u00e9t\u00e9 Immobili\u00e8re Grand Air No V",
    "wof:placetype":"venue"
},
  "geometry": {"coordinates":[6.1441049576,46.197227478],"type":"Point"}
}