{
  "type": "Feature",
  "properties": {
    "iso:country":"CH",
    "sg:address":"6313",
    "sg:city":"Menzingen",
    "sg:orig_category":"Organisationen des Gesundheitswesen",
    "sg:phone":"+41 41 755 14 08",
    "sg:postcode":"6313",
    "sg:province":"Zug",
    "wof:name":"Samariterverein",
    "wof:placetype":"venue"
},
  "geometry": {"coordinates":[8.5906457901,47.1783485413],"type":"Point"}
}