{
  "type": "Feature",
  "properties": {
    "iso:country":"CH",
    "sg:address":"Aem\u00e4ttlistrasse 2",
    "sg:city":"Stans",
    "sg:orig_category":"Softwareentwicklung U beratung",
    "sg:phone":"+41 41 874 31 10",
    "sg:postcode":"6370",
    "sg:province":"Nidwalden",
    "wof:name":"Lisag",
    "wof:placetype":"venue"
},
  "geometry": {"coordinates":[8.6399507523,46.8827018738],"type":"Point"}
}