{
  "type": "Feature",
  "properties": {
    "iso:country":"CH",
    "sg:address":"Haufen 651",
    "sg:city":"Lutzenberg",
    "sg:orig_category":"Allgemeiner Hoch U Tiefbau",
    "sg:phone":"+41 71 888 04 61",
    "sg:postcode":"9426",
    "sg:province":"Appenzell Ausserrhoden",
    "wof:name":"Erwin Brand Gmbh",
    "wof:placetype":"venue"
},
  "geometry": {"coordinates":[9.566486,47.460609],"type":"Point"}
}