{
  "type": "Feature",
  "properties": {
    "iso:country":"CH",
    "sg:address":"Talgut-zentrum 19 3063 Ittigen. Postfach",
    "sg:city":"Ittigen",
    "sg:orig_category":"Fachdetailhandel mit pharmazeutischen Produkten",
    "sg:postcode":"3063",
    "sg:province":"Bern",
    "wof:name":"Pharmedic Hauri Und Partner",
    "wof:placetype":"venue"
},
  "geometry": {"coordinates":[7.4817447662,46.9744415283],"type":"Point"}
}