{
  "type": "Feature",
  "properties": {
    "iso:country":"CH",
    "sg:address":"Avenue Bois-de-la-chapelle 13",
    "sg:city":"Onex",
    "sg:orig_category":"Detailhandel mit Antiquit\u00e4ten",
    "sg:phone":"+41 32 751 20 33",
    "sg:postcode":"1213",
    "sg:province":"Gen\u00e8ve",
    "wof:name":"Charles & Marie-jos\u00e9 Wermeille Antiquit\u00e9s",
    "wof:placetype":"venue"
},
  "geometry": {"coordinates":[7.064337,47.050468],"type":"Point"}
}