{
  "type": "Feature",
  "properties": {
    "iso:country":"CH",
    "sg:address":"Entfelderstrasse 82",
    "sg:city":"Aarau",
    "sg:orig_category":"Architekturb\u00fcros",
    "sg:phone":"+41 32 351 21 70",
    "sg:postcode":"5000",
    "sg:province":"Aargau",
    "wof:name":"Werner Heiri",
    "wof:placetype":"venue"
},
  "geometry": {"coordinates":[7.36173,47.141048],"type":"Point"}
}