{
  "type": "Feature",
  "properties": {
    "iso:country":"CH",
    "sg:address":"Dorfgarage",
    "sg:city":"Illighausen",
    "sg:orig_category":"Instandhaltung U Reparatur von Automobilen",
    "sg:phone":"+41 19323637",
    "sg:postcode":"8574",
    "sg:province":"Thurgau",
    "wof:name":"Wildbachgarage Ag",
    "wof:placetype":"venue"
},
  "geometry": {"coordinates":[8.7981739044,47.3147354126],"type":"Point"}
}