{
  "type": "Feature",
  "properties": {
    "iso:country":"CH",
    "sg:address":"Les Ilettes",
    "sg:city":"Monthey",
    "sg:orig_category":"Detailhandel mit Getr\u00e4nken Grosshandel mit Getr\u00e4nken",
    "sg:phone":"+41 24 471 96 84",
    "sg:postcode":"1870",
    "sg:province":"Valais",
    "wof:name":"Boissons Chablais",
    "wof:placetype":"venue"
},
  "geometry": {"coordinates":[6.9609351158,46.2472343445],"type":"Point"}
}