{
  "type": "Feature",
  "properties": {
    "iso:country":"CH",
    "sg:address":"Lettenstrasse 8",
    "sg:city":"Rotkreuz",
    "sg:orig_category":"Offsetdruck Satzherstellung U Reproduktion",
    "sg:phone":"+41 41 790 48 20",
    "sg:postcode":"6343",
    "sg:province":"Zug",
    "wof:name":"Anderhub Druck-service Ag",
    "wof:placetype":"venue"
},
  "geometry": {"coordinates":[8.431429863,47.1476821899],"type":"Point"}
}