{
  "type": "Feature",
  "properties": {
    "iso:country":"CH",
    "sg:address":"Kirchweg 10",
    "sg:city":"Bubikon",
    "sg:orig_category":"Politische Parteien SP",
    "sg:phone":"+41 55 243 21 54",
    "sg:postcode":"8608",
    "sg:province":"Z\u00fcrich",
    "wof:name":"Sp Ortspartei Bubikon",
    "wof:placetype":"venue"
},
  "geometry": {"coordinates":[8.8183202744,47.2704391479],"type":"Point"}
}