{
  "type": "Feature",
  "properties": {
    "iso:country":"CH",
    "sg:address":"Avenue Des Alpes 22",
    "sg:city":"Montreux",
    "sg:orig_category":"Grosshandel mit festen Brennstoffen U Mineral\u00f6lerzeugnissen",
    "sg:postcode":"1820",
    "sg:province":"Vaud",
    "wof:name":"Th\u00e9venaz A.",
    "wof:placetype":"venue"
},
  "geometry": {"coordinates":[6.911427021,46.4323997498],"type":"Point"}
}