{
  "type": "Feature",
  "properties": {
    "iso:country":"CH",
    "sg:address":"9125",
    "sg:city":"Brunnadern",
    "sg:orig_category":"Vereine Musik/Blasmusik",
    "sg:phone":"+41 56 622 42 40",
    "sg:postcode":"9125",
    "sg:province":"St. Gallen",
    "wof:name":"Musikgesellschaft",
    "wof:placetype":"venue"
},
  "geometry": {"coordinates":[9.1977596283,47.4382591248],"type":"Point"}
}