{
  "type": "Feature",
  "properties": {
    "addr:full":"Nelkenweg 5b Orpund Bern 2552",
    "addr:housenumber":"5b",
    "addr:postcode":"2552",
    "addr:street":"Nelkenweg",
    "iso:country":"CH",
    "sg:address":"Nelkenweg 5b",
    "sg:city":"Orpund",
    "sg:orig_category":"Architektur U Ingenieurb\u00fcros",
    "sg:phone":"+41 32 357 15 01",
    "sg:postcode":"2552",
    "sg:province":"Bern",
    "wof:name":"Kohler + Partner Gmbh",
    "wof:placetype":"venue"
},
  "geometry": {"coordinates":[7.30037,47.139236],"type":"Point"}
}