{
  "type": "Feature",
  "properties": {
    "iso:country":"CH",
    "sg:address":"Simplon Rue Du 8",
    "sg:city":"Fribourg",
    "sg:orig_category":"Detailhandel mit Waren verschiedener Art, Hauptrichtung Nahrungsmittel",
    "sg:postcode":"1700",
    "sg:province":"Fribourg",
    "wof:name":"Boschung & Baechler, Alimentation G\u00e9n\u00e9rale Sa.",
    "wof:placetype":"venue"
},
  "geometry": {"coordinates":[7.1501531601,46.7990379333],"type":"Point"}
}