{
  "type": "Feature",
  "properties": {
    "addr:full":"Chemin J-s.farinet Saxon Valais 1907",
    "addr:postcode":"1907",
    "addr:street":"Chemin J-S.Farinet",
    "iso:country":"CH",
    "sg:address":"Chemin J-s.farinet",
    "sg:city":"Saxon",
    "sg:classifiers":[
        {
            "category":"Bars & Pubs",
            "type":"Food & Drink"
        }
    ],
    "sg:postcode":"1907",
    "sg:province":"Valais",
    "wof:name":"Joao Carlos Soares Branco, Bar-discoth\u00e8que Le Vague \u00e0 L'ame",
    "wof:placetype":"venue"
},
  "geometry": {"coordinates":[7.33646,46.185768],"type":"Point"}
}