{
  "type": "Feature",
  "properties": {
    "iso:country":"CH",
    "sg:address":"Bruggweg 13",
    "sg:city":"Arlesheim",
    "sg:orig_category":"Buntmetallgiesserei Pulvermetallurgie Schmieden, Pressen, Stanzen U Profilwalzen von Metallen",
    "sg:phone":"+41 61 701 29 31",
    "sg:postcode":"4144",
    "sg:province":"Basel-Landschaft",
    "wof:name":"Metallatelier Hilden Gmbh Kunsthandwerkliche Therapieinstrumente Aus Bunt- U. Edelmetallen; Herstellung, Vertrieb Usw",
    "wof:placetype":"venue"
},
  "geometry": {"coordinates":[7.615116,47.490017],"type":"Point"}
}