{
  "type": "Feature",
  "properties": {
    "iso:country":"CH",
    "sg:address":"Hofrainstrasse 7",
    "sg:city":"Eich",
    "sg:orig_category":"Herstellung von Radio U Fernsehger\u00e4ten sowie phono U videotechnischen Ger\u00e4ten",
    "sg:phone":"+41 41 460 16 22",
    "sg:postcode":"6205",
    "sg:province":"Luzern",
    "wof:name":"Brissoni Elektro Und Telekommunikation",
    "wof:placetype":"venue"
},
  "geometry": {"coordinates":[8.1651601791,47.1558990479],"type":"Point"}
}