{
  "type": "Feature",
  "properties": {
    "iso:country":"CH",
    "sg:address":"Blattenheimatstrasse 3 9050 Appenzell. Postfach",
    "sg:city":"Appenzell",
    "sg:orig_category":"Grosshandel mit festen Brennstoffen U Mineral\u00f6lerzeugnissen",
    "sg:postcode":"9050",
    "sg:province":"Appenzell Innerhoden",
    "wof:name":"Genossenschaft F\u00fcr Brennstoff-lagerhaltung",
    "wof:placetype":"venue"
},
  "geometry": {"coordinates":[9.3573493958,47.4141426086],"type":"Point"}
}