{
  "type": "Feature",
  "properties": {
    "iso:country":"CH",
    "sg:address":"Rte Du L\u00e9man",
    "sg:city":"Saxon",
    "sg:classifiers":[
        {
            "category":"Home & Garden",
            "subcategory":"Furniture",
            "type":"Retail Goods"
        }
    ],
    "sg:phone":"+41 24 475 71 31",
    "sg:postcode":"1907",
    "sg:province":"Valais",
    "sg:tags":[
        "household",
        "wood"
    ],
    "wof:name":"Marcel Michellod & Fils",
    "wof:placetype":"venue"
},
  "geometry": {"coordinates":[6.9705700874,46.2445793152],"type":"Point"}
}