{
  "type": "Feature",
  "properties": {
    "iso:country":"CH",
    "sg:address":"Schulhausstrasse 66 8704 Herrliberg. Postfach",
    "sg:city":"Herrliberg",
    "sg:orig_category":"Kauf U Verkauf von Immobilien auf eigene Rechnung",
    "sg:postcode":"8704",
    "sg:province":"Z\u00fcrich",
    "wof:name":"Alder-spieler J. & L. Liegenschaften Usw",
    "wof:placetype":"venue"
},
  "geometry": {"coordinates":[7.6352658272,46.3170318604],"type":"Point"}
}