{
  "type": "Feature",
  "properties": {
    "iso:country":"CH",
    "sg:address":"Zugerstrasse 195 6314 Unter\u00e4geri. Postfach 438",
    "sg:city":"Unter\u00e4geri",
    "sg:orig_category":"Detailhandel mit M\u00f6beln Grosshandel mit B\u00fcromaschinen U einrichtungen",
    "sg:phone":"+41 41 750 61 01",
    "sg:postcode":"6314",
    "sg:province":"Zug",
    "wof:name":"Trendline Ag",
    "wof:placetype":"venue"
},
  "geometry": {"coordinates":[8.5640697479,47.149181366],"type":"Point"}
}