{
  "type": "Feature",
  "properties": {
    "iso:country":"CH",
    "sg:address":"Hauptstrasse 1",
    "sg:city":"Fischingen",
    "sg:orig_category":"S\u00e4ge, Hobel U Holzimpr\u00e4gnierwerke S\u00e4gewerke",
    "sg:phone":"+41 71 977 15 27",
    "sg:postcode":"8376",
    "sg:province":"Thurgau",
    "wof:name":"Thaddey Ag, David.",
    "wof:placetype":"venue"
},
  "geometry": {"coordinates":[8.9172821045,47.4006004333],"type":"Point"}
}