{
  "type": "Feature",
  "properties": {
    "iso:country":"CH",
    "sg:address":"Route Chenaux 11",
    "sg:city":"Lugnorre",
    "sg:orig_category":"Detailhandel mit Milcherzeugnissen U Eiern Verarbeitung von Milch",
    "sg:phone":"+41 26 673 14 31",
    "sg:postcode":"1789",
    "sg:province":"Fribourg",
    "wof:name":"Walter Reist Laiterie Fromagerie",
    "wof:placetype":"venue"
},
  "geometry": {"coordinates":[7.069630146,46.9510917664],"type":"Point"}
}