{
  "type": "Feature",
  "properties": {
    "iso:country":"CH",
    "sg:address":"Bernstr. 32",
    "sg:city":"Z\u00e4ziwil",
    "sg:classifiers":[
        {
            "category":"Professional",
            "subcategory":"Engineering",
            "type":"Services"
        }
    ],
    "sg:phone":"+41 55 250 39 00",
    "sg:postcode":"3532",
    "sg:province":"Bern",
    "sg:tags":[
        "machine",
        "-",
        "mechanical"
    ],
    "wof:name":"Kmk Maschinen Ag",
    "wof:placetype":"venue"
},
  "geometry": {"coordinates":[8.7520399094,51.7181396484],"type":"Point"}
}