{
  "type": "Feature",
  "properties": {
    "iso:country":"CH",
    "sg:address":"Hauptstrasse 89 4313 M\u00f6hlin. Postfach",
    "sg:city":"Rheinfelden",
    "sg:orig_category":"Verwaltung von Immobilien",
    "sg:phone":"+41 21 653 33 66",
    "sg:postcode":"4310",
    "sg:province":"Aargau",
    "wof:name":"Mangold Management Co Ltd",
    "wof:placetype":"venue"
},
  "geometry": {"coordinates":[6.6491770744,46.5232582092],"type":"Point"}
}