{
  "type": "Feature",
  "properties": {
    "iso:country":"CH",
    "sg:address":"Heidenerstrasse 10",
    "sg:city":"Eggersriet",
    "sg:classifiers":[
        {
            "category":"Banks & Credit Unions",
            "subcategory":"Bank",
            "type":"Services"
        }
    ],
    "sg:phone":"+41 4171952244",
    "sg:postcode":"9034",
    "sg:province":"St. Gallen",
    "wof:name":"Raiffeisenbank",
    "wof:placetype":"venue"
},
  "geometry": {"coordinates":[9.47363,47.441963],"type":"Point"}
}