{
  "type": "Feature",
  "properties": {
    "iso:country":"CH",
    "sg:address":"Kramgasse 36 3011 Bern. Postfach",
    "sg:city":"Bern",
    "sg:orig_category":"Interessenvertretungen",
    "sg:postcode":"3005",
    "sg:province":"Bern",
    "wof:name":"Hilfsfonds F\u00fcr Lehrkr\u00e4fte Des Konservatoriums Bern",
    "wof:placetype":"venue"
},
  "geometry": {"coordinates":[7.450261116,46.948097229],"type":"Point"}
}