{
  "type": "Feature",
  "properties": {
    "iso:country":"CH",
    "sg:address":"6653",
    "sg:city":"Verscio",
    "sg:orig_category":"Vereine Fasnacht",
    "sg:postcode":"6653",
    "sg:province":"Ticino",
    "wof:name":"Comitato Carnevale",
    "wof:placetype":"venue"
},
  "geometry": {"coordinates":[8.7288999557,46.1915283203],"type":"Point"}
}