{
  "type": "Feature",
  "properties": {
    "iso:country":"CH",
    "sg:address":"Kellberg",
    "sg:city":"Inwil",
    "sg:orig_category":"Wasserversorgung",
    "sg:postcode":"6034",
    "sg:province":"Luzern",
    "wof:name":"Wasserversorgungsgenossenschaft Schwerzlen",
    "wof:placetype":"venue"
},
  "geometry": {"coordinates":[8.3678636551,47.1268844604],"type":"Point"}
}