{
  "type": "Feature",
  "properties": {
    "iso:country":"CH",
    "sg:address":"Laurenzenvorstadt 119",
    "sg:city":"Aarau",
    "sg:orig_category":"Architektur U Ingenieurb\u00fcros",
    "sg:postcode":"5000",
    "sg:province":"Aargau",
    "wof:name":"Berger, Fux Und K\u00fcng Bfk Baumanagement Architektur, Planungs, Bauleitungsaufgaben",
    "wof:placetype":"venue"
},
  "geometry": {"coordinates":[8.442287,47.350269],"type":"Point"}
}