{
  "type": "Feature",
  "properties": {
    "iso:country":"CH",
    "sg:address":"Neuhofstrasse 4",
    "sg:city":"Baar",
    "sg:orig_category":"Dienstleistungen von Beteiligungsgesellschaften",
    "sg:phone":"+41 41 768 78 80",
    "sg:postcode":"6340",
    "sg:province":"Zug",
    "wof:name":"Scout24 Holding Ag",
    "wof:placetype":"venue"
},
  "geometry": {"coordinates":[8.5136909485,47.1903457642],"type":"Point"}
}