{
  "type": "Feature",
  "properties": {
    "iso:country":"CH",
    "sg:address":"Wachtelweg 2 4553 Subingen. Postfach",
    "sg:city":"Subingen",
    "sg:orig_category":"Herstellung von Konstruktionsteilen, Fertigbauteilen U Ausbauelementen aus Holz",
    "sg:phone":"+41 32 614 44 11",
    "sg:postcode":"4553",
    "sg:province":"Solothurn",
    "wof:name":"Repa-mont Christen & Herren",
    "wof:placetype":"venue"
},
  "geometry": {"coordinates":[7.611246109,47.1970863342],"type":"Point"}
}