{
  "type": "Feature",
  "properties": {
    "iso:country":"CH",
    "sg:address":"Hirzenwis 18 8493 Saland. Postfach",
    "sg:city":"Saland",
    "sg:orig_category":"Unternehmensberatung",
    "sg:postcode":"8493",
    "sg:province":"Z\u00fcrich",
    "wof:name":"A. Blindenbacher & Co",
    "wof:placetype":"venue"
},
  "geometry": {"coordinates":[8.8541097641,47.3906326294],"type":"Point"}
}