{
  "type": "Feature",
  "properties": {
    "iso:country":"CH",
    "sg:address":"Bahnhofstrasse 36",
    "sg:city":"Dornach",
    "sg:orig_category":"Politische Parteien SVP",
    "sg:postcode":"4143",
    "sg:province":"Solothurn",
    "wof:name":"Svp Ortspartei Dornach",
    "wof:placetype":"venue"
},
  "geometry": {"coordinates":[7.6115889549,47.4886131287],"type":"Point"}
}