{
  "type": "Feature",
  "properties": {
    "iso:country":"CH",
    "sg:address":"Bois-genoud Route Du 1a",
    "sg:city":"Crissier",
    "sg:orig_category":"Non-Classified Establishments",
    "sg:postcode":"1023",
    "sg:province":"Vaud",
    "wof:name":"Cygnet Gmbh",
    "wof:placetype":"venue"
},
  "geometry": {"coordinates":[9.2117004395,47.4424667358],"type":"Point"}
}