{
  "type": "Feature",
  "properties": {
    "iso:country":"CH",
    "sg:address":"Zurlindenstrasse 300",
    "sg:city":"Z\u00fcrich",
    "sg:orig_category":"Detailhandel mit Waren verschiedener Art, Hauptrichtung Nahrungsmittel",
    "sg:phone":"+41 24 471 01 55",
    "sg:postcode":"8003",
    "sg:province":"Z\u00fcrich",
    "wof:name":"Coop Le Market",
    "wof:placetype":"venue"
},
  "geometry": {"coordinates":[6.950398922,46.2524642944],"type":"Point"}
}