{
  "type": "Feature",
  "properties": {
    "addr:full":"Forchstrasse 92 Z\u00fcrich Z\u00fcrich 8008",
    "addr:housenumber":"92",
    "addr:postcode":"8008",
    "addr:street":"Forchstrasse",
    "iso:country":"CH",
    "sg:address":"Forchstrasse 92",
    "sg:city":"Z\u00fcrich",
    "sg:orig_category":"Arztpraxen",
    "sg:phone":"+41 13823434",
    "sg:postcode":"8008",
    "sg:province":"Z\u00fcrich",
    "wof:name":"Dr.med.johann Walter Meyer Spezialarzt Fmh",
    "wof:placetype":"venue"
},
  "geometry": {"coordinates":[8.55586,47.363972],"type":"Point"}
}