{
  "type": "Feature",
  "properties": {
    "iso:country":"CH",
    "sg:address":"3752",
    "sg:city":"Wimmis",
    "sg:orig_category":"Sportvereine Ski",
    "sg:phone":"+41 52 315 36 91",
    "sg:postcode":"3752",
    "sg:province":"Bern",
    "wof:name":"Skiclub Winterthur",
    "wof:placetype":"venue"
},
  "geometry": {"coordinates":[8.853597641,47.4728622437],"type":"Point"}
}