{
  "type": "Feature",
  "properties": {
    "iso:country":"CH",
    "sg:address":"Baldeggstrasse 12",
    "sg:city":"Hochdorf",
    "sg:orig_category":"Herstellung von Verbrennungsmotoren U Turbinen ohne Motoren f\u00fcr Luft U Strassenfahrzeuge",
    "sg:postcode":"6280",
    "sg:province":"Luzern",
    "wof:name":"Pettrup G. Elektromotoren U. -apparate",
    "wof:placetype":"venue"
},
  "geometry": {"coordinates":[8.2870960236,47.1704826355],"type":"Point"}
}