{
  "type": "Feature",
  "properties": {
    "iso:country":"CH",
    "sg:address":"Iffwilstrasse 10",
    "sg:city":"Jegenstorf",
    "sg:classifiers":[
        {
            "category":"Education",
            "subcategory":"Vocational School",
            "type":"Public Place"
        }
    ],
    "sg:phone":"+41 31 761 00 54",
    "sg:postcode":"3303",
    "sg:province":"Bern",
    "sg:tags":[
        "koch-",
        "haushaltschulen"
    ],
    "wof:name":"Haushaltungsschule",
    "wof:placetype":"venue"
},
  "geometry": {"coordinates":[7.505256176,47.0510368347],"type":"Point"}
}