{
  "type": "Feature",
  "properties": {
    "addr:full":"Via Don Gagliardi 23 Breganzona Ticino 6932",
    "addr:housenumber":"23",
    "addr:postcode":"6932",
    "addr:street":"Via Don Gagliardi;Ticino",
    "iso:country":"CH",
    "sg:address":"Via Don Gagliardi 23",
    "sg:city":"Breganzona",
    "sg:orig_category":"Allgemeiner Hoch U Tiefbau",
    "sg:postcode":"6932",
    "sg:province":"Ticino",
    "wof:name":"Bonnet Bernard Entrepreneur",
    "wof:placetype":"venue"
},
  "geometry": {"coordinates":[6.891537,46.585361],"type":"Point"}
}