{
  "type": "Feature",
  "properties": {
    "iso:country":"CH",
    "sg:address":"1352",
    "sg:city":"Agiez",
    "sg:classifiers":[
        {
            "category":"Education",
            "subcategory":"Library",
            "type":"Public Place"
        }
    ],
    "sg:postcode":"1352",
    "sg:province":"Vaud",
    "sg:tags":[
        "u",
        "bibliotheken",
        "archive"
    ],
    "wof:name":"Biblioth\u00e8que Populaire",
    "wof:placetype":"venue"
},
  "geometry": {"coordinates":[6.50547,46.716011],"type":"Point"}
}