{
  "type": "Feature",
  "properties": {
    "iso:country":"CH",
    "sg:address":"Oetlingerstrasse 189",
    "sg:city":"Basel",
    "sg:orig_category":"Verlegen von Fliesen U Platten",
    "sg:phone":"+41 61 692 49 42",
    "sg:postcode":"4057",
    "sg:province":"Basel-Stadt",
    "wof:name":"Regina K\u00f6sters Keramische Wand-& Bodenbel\u00e4ge",
    "wof:placetype":"venue"
},
  "geometry": {"coordinates":[7.596932888,47.5682258606],"type":"Point"}
}