{
  "type": "Feature",
  "properties": {
    "iso:country":"CH",
    "sg:address":"Kantonsstrasse 132",
    "sg:city":"Horw",
    "sg:orig_category":"Non-Classified Establishments",
    "sg:postcode":"6048",
    "sg:province":"Luzern",
    "wof:name":"Cvp Sa",
    "wof:placetype":"venue"
},
  "geometry": {"coordinates":[6.6867198944,46.5139198303],"type":"Point"}
}