{
  "type": "Feature",
  "properties": {
    "iso:country":"CH",
    "sg:address":"Via Cassinelle 6",
    "sg:city":"Agno",
    "sg:classifiers":[
        {
            "category":"Banks & Credit Unions",
            "subcategory":"Investment Brokerage",
            "type":"Services"
        }
    ],
    "sg:phone":"+41 91 604 54 59",
    "sg:postcode":"6982",
    "sg:province":"Ticino",
    "sg:tags":[
        "stairway",
        "disabled",
        "lift",
        "elevator",
        "persons"
    ],
    "wof:name":"Rigert Ag Treppenlifte",
    "wof:placetype":"venue"
},
  "geometry": {"coordinates":[8.9022750854,46.0087814331],"type":"Point"}
}