{
  "type": "Feature",
  "properties": {
    "iso:country":"CH",
    "sg:address":"Luchswiesenstrasse 217",
    "sg:city":"Z\u00fcrich",
    "sg:orig_category":"Mahl U Sch\u00e4lm\u00fchlen",
    "sg:phone":"+41 12615716",
    "sg:postcode":"8051",
    "sg:province":"Z\u00fcrich",
    "wof:name":"Alfred Gubser Gew\u00fcrzfabrikation",
    "wof:placetype":"venue"
},
  "geometry": {"coordinates":[8.5848636627,47.4057044983],"type":"Point"}
}