{
  "type": "Feature",
  "properties": {
    "iso:country":"CH",
    "sg:address":"Geiger Rue Hermann- 13",
    "sg:city":"Sitten",
    "sg:orig_category":"Non-Classified Establishments",
    "sg:postcode":"1950",
    "sg:province":"Valais",
    "wof:name":"Fiduciaire Mp Treuhand Mazotti P.",
    "wof:placetype":"venue"
},
  "geometry": {"coordinates":[7.3369579315,46.2250289917],"type":"Point"}
}