{
  "type": "Feature",
  "properties": {
    "iso:country":"CH",
    "sg:address":"Wissmannstrasse 9",
    "sg:city":"Z\u00fcrich",
    "sg:orig_category":"Aktivit\u00e4ten der Krankenschwestern U Hebammen, Hauspflege",
    "sg:phone":"+41 13619162",
    "sg:postcode":"8057",
    "sg:province":"Z\u00fcrich",
    "wof:name":"Ambulante Kinderkrankenpflege Kanton Z\u00fcrich",
    "wof:placetype":"venue"
},
  "geometry": {"coordinates":[8.536268,47.393829],"type":"Point"}
}