{
  "type": "Feature",
  "properties": {
    "iso:country":"CH",
    "sg:address":"Industriestrasse 3",
    "sg:city":"Schlieren",
    "sg:orig_category":"Effektenvermittlung Broker Finanzierungsinstitutionen",
    "sg:phone":"+41 17307010",
    "sg:postcode":"8952",
    "sg:province":"Z\u00fcrich",
    "wof:name":"Hedag Ag",
    "wof:placetype":"venue"
},
  "geometry": {"coordinates":[8.4589691162,47.4016151428],"type":"Point"}
}