{
  "type": "Feature",
  "properties": {
    "iso:country":"CH",
    "sg:address":"Via Generoso 6",
    "sg:city":"Lugano",
    "sg:orig_category":"Grosshandel mit Schmuck",
    "sg:phone":"+41 91 994 64 24",
    "sg:postcode":"6900",
    "sg:province":"Ticino",
    "wof:name":"Mayer Gul Import-export Commercio Preziosi",
    "wof:placetype":"venue"
},
  "geometry": {"coordinates":[8.9436836243,45.9959068298],"type":"Point"}
}