{
  "type": "Feature",
  "properties": {
    "iso:country":"CH",
    "sg:address":"Kirchweg 80",
    "sg:city":"Glarus",
    "sg:orig_category":"Architektur U Ingenieurb\u00fcros",
    "sg:postcode":"8750",
    "sg:province":"Glarus",
    "wof:name":"Glaronit Ag",
    "wof:placetype":"venue"
},
  "geometry": {"coordinates":[9.072195,47.036274],"type":"Point"}
}