{
  "type": "Feature",
  "properties": {
    "iso:country":"CH",
    "sg:address":"Village",
    "sg:city":"S\u00e9very",
    "sg:orig_category":"Sonstiger spezialisierter Hoch U Tiefbau",
    "sg:postcode":"1141",
    "sg:province":"Vaud",
    "wof:name":"Charpente-menuiserie, Maridor",
    "wof:placetype":"venue"
},
  "geometry": {"coordinates":[6.931224823,47.0302581787],"type":"Point"}
}