{
  "type": "Feature",
  "properties": {
    "iso:country":"CH",
    "sg:address":"Thurtalstrasse 53",
    "sg:city":"Thalheim",
    "sg:orig_category":"Unclassifiable Establishments",
    "sg:phone":"+41 18443401",
    "sg:postcode":"8478",
    "sg:province":"Z\u00fcrich",
    "wof:name":"Leuenberger Holding Ag",
    "wof:placetype":"venue"
},
  "geometry": {"coordinates":[8.4049654007,47.4481544495],"type":"Point"}
}