{
  "type": "Feature",
  "properties": {
    "iso:country":"CH",
    "sg:address":"Weingartenstrasse 4",
    "sg:city":"H\u00f6ri",
    "sg:orig_category":"Herstellung von Werkzeugmaschinen",
    "sg:postcode":"8181",
    "sg:province":"Z\u00fcrich",
    "wof:name":"Fluri Ren\u00e9 Elektrowerkzeuge",
    "wof:placetype":"venue"
},
  "geometry": {"coordinates":[8.4989881516,47.504737854],"type":"Point"}
}