{
  "type": "Feature",
  "properties": {
    "iso:country":"CH",
    "sg:address":"Landstrasse 55",
    "sg:city":"Wettingen",
    "sg:orig_category":"Elektroinstallation Herstellung von Elektrizit\u00e4tsverteilungs U schalteinrichtungen",
    "sg:phone":"+41 17861216",
    "sg:postcode":"5430",
    "sg:province":"Aargau",
    "wof:name":"Ernst Burkhalter Ing. Ag Elektrotechnische Anlagen",
    "wof:placetype":"venue"
},
  "geometry": {"coordinates":[8.7341480255,47.1973953247],"type":"Point"}
}