{
  "type": "Feature",
  "properties": {
    "iso:country":"CH",
    "sg:address":"Rue Du Simplon 2",
    "sg:city":"Vevey",
    "sg:orig_category":"Zahnarztpraxen",
    "sg:phone":"+41 21 921 06 12",
    "sg:postcode":"1800",
    "sg:province":"Vaud",
    "wof:name":"Dr M\u00e9d. Dent. Eva Balt Klunge M\u00e9decin-dentiste",
    "wof:placetype":"venue"
},
  "geometry": {"coordinates":[6.8472251892,46.4590606689],"type":"Point"}
}