{
  "type": "Feature",
  "properties": {
    "iso:country":"CH",
    "sg:address":"Gemeindehausstrasse 14",
    "sg:city":"Kriens",
    "sg:orig_category":"Bauschreinerei Innenausbau",
    "sg:phone":"+41 41 320 30 43",
    "sg:postcode":"6010",
    "sg:province":"Luzern",
    "wof:name":"Bachmann Innenausbau Ag Schreinerei",
    "wof:placetype":"venue"
},
  "geometry": {"coordinates":[8.279377,47.036655],"type":"Point"}
}