{
  "type": "Feature",
  "properties": {
    "iso:country":"CH",
    "sg:address":"Ramisb\u00fchl 524",
    "sg:city":"Matzendorf",
    "sg:orig_category":"G\u00fcterbef\u00f6rderung im Strassenverkehr",
    "sg:postcode":"4713",
    "sg:province":"Solothurn",
    "wof:name":"Neuenschwander P.",
    "wof:placetype":"venue"
},
  "geometry": {"coordinates":[7.5278601646,47.1663360596],"type":"Point"}
}