{
  "type": "Feature",
  "properties": {
    "iso:country":"CH",
    "sg:address":"Beundenfeldstrasse 18",
    "sg:city":"Bern",
    "sg:orig_category":"Detailhandel mit Geschenkartikeln U Souvenirs",
    "sg:phone":"+41 31 331 97 93",
    "sg:postcode":"3013",
    "sg:province":"Bern",
    "wof:name":"Boutique Chez Ruth Ruth Zimmermann",
    "wof:placetype":"venue"
},
  "geometry": {"coordinates":[7.4530439377,46.9556312561],"type":"Point"}
}