{
  "type": "Feature",
  "properties": {
    "iso:country":"CH",
    "sg:address":"Meistersr\u00fcte",
    "sg:city":"Appenzell",
    "sg:orig_category":"Bauschreinerei Herstellung von M\u00f6beln verschiedener Art",
    "sg:phone":"+41 71 787 36 74",
    "sg:postcode":"9050",
    "sg:province":"Appenzell Innerhoden",
    "wof:name":"Josef Breitenmoser Schreinerei & K\u00fcchen",
    "wof:placetype":"venue"
},
  "geometry": {"coordinates":[9.407683,47.331436],"type":"Point"}
}