{
  "type": "Feature",
  "properties": {
    "iso:country":"CH",
    "sg:address":"Rathausg\u00e4ssli 6",
    "sg:city":"Biel/bienne",
    "sg:classifiers":[
        {
            "category":"Government",
            "subcategory":"Post Office",
            "type":"Public Place"
        }
    ],
    "sg:phone":"+41 32 323 95 14",
    "sg:postcode":"2502",
    "sg:province":"Bern",
    "sg:tags":[
        "caf\u00e9s",
        "tea-rooms"
    ],
    "wof:name":"Tea-room Loggia",
    "wof:placetype":"venue"
},
  "geometry": {"coordinates":[7.2458901405,47.1411437988],"type":"Point"}
}