{
  "type": "Feature",
  "properties": {
    "iso:country":"CH",
    "sg:address":"Bourg-aux-favre Rue Du 3",
    "sg:city":"Monthey",
    "sg:orig_category":"Unclassifiable Establishments",
    "sg:postcode":"1870",
    "sg:province":"Valais",
    "wof:name":"Au Miam-miam, Sacko Demba",
    "wof:placetype":"venue"
},
  "geometry": {"coordinates":[6.9467148781,46.2520027161],"type":"Point"}
}