{
  "type": "Feature",
  "properties": {
    "iso:country":"CH",
    "sg:address":"Dorfstrasse 21",
    "sg:city":"W\u00e4ngi",
    "sg:orig_category":"Arztpraxen",
    "sg:phone":"+41 52 378 12 03",
    "sg:postcode":"9545",
    "sg:province":"Thurgau",
    "wof:name":"Dr.med.ulrich Rasi Spezialarzt Fmh",
    "wof:placetype":"venue"
},
  "geometry": {"coordinates":[8.954165,47.498882],"type":"Point"}
}