{
  "type": "Feature",
  "properties": {
    "iso:country":"CH",
    "sg:address":"Avenue Nestl\u00e9 15 1820 Montreux. Postfach",
    "sg:city":"Montreux",
    "sg:orig_category":"Malerei Stukkateurgewerbe, Gipserei U Verputzerei",
    "sg:phone":"+41 22 343 53 52",
    "sg:postcode":"1820",
    "sg:province":"Vaud",
    "wof:name":"Louis Chiappini Gypserie & Peinture",
    "wof:placetype":"venue"
},
  "geometry": {"coordinates":[6.1369199753,46.1791381836],"type":"Point"}
}