{
  "type": "Feature",
  "properties": {
    "iso:country":"CH",
    "sg:address":"Avenue Des Alpes 112",
    "sg:city":"Montreux",
    "sg:orig_category":"Elektroinstallation",
    "sg:phone":"+41 21 963 65 79",
    "sg:postcode":"1820",
    "sg:province":"Vaud",
    "wof:name":"Bmp Electricit\u00e9 Sa",
    "wof:placetype":"venue"
},
  "geometry": {"coordinates":[6.9082698822,46.4386863708],"type":"Point"}
}