{
  "type": "Feature",
  "properties": {
    "iso:country":"CH",
    "sg:address":"Kalkofen 156",
    "sg:city":"Matzendorf",
    "sg:orig_category":"Stukkateurgewerbe, Gipserei U Verputzerei Tapeziererei",
    "sg:phone":"+41 62 394 11 34",
    "sg:postcode":"4713",
    "sg:province":"Solothurn",
    "wof:name":"Ernst Christ Ag Hauptsitz",
    "wof:placetype":"venue"
},
  "geometry": {"coordinates":[7.6250019073,47.2988586426],"type":"Point"}
}