{
  "type": "Feature",
  "properties": {
    "iso:country":"CH",
    "sg:address":"Wilstrasse 11 8610 Uster. Postfach",
    "sg:city":"Uster",
    "sg:orig_category":"Pensionskassen",
    "sg:phone":"+41 61 461 69 61",
    "sg:postcode":"8610",
    "sg:province":"Z\u00fcrich",
    "wof:name":"Zeitungsfonds Der Fourier Fachzeitschrift Und Offizielles Organ Des Schweizerischen Fourierverbandes (stiftung)",
    "wof:placetype":"venue"
},
  "geometry": {"coordinates":[7.5928969383,47.4687614441],"type":"Point"}
}