{
  "type": "Feature",
  "properties": {
    "iso:country":"CH",
    "sg:address":"Yersin Rue Docteur 9",
    "sg:city":"Morges",
    "sg:orig_category":"Non-Classified Establishments",
    "sg:postcode":"1110",
    "sg:province":"Vaud",
    "wof:name":"Four Winds Leasing Sa",
    "wof:placetype":"venue"
},
  "geometry": {"coordinates":[6.4978880882,46.5125732422],"type":"Point"}
}