{
  "type": "Feature",
  "properties": {
    "iso:country":"CH",
    "sg:address":"L\u00e4ttenstrasse 23",
    "sg:city":"Dietikon",
    "sg:orig_category":"Architekturb\u00fcros",
    "sg:phone":"+41 17410710",
    "sg:postcode":"8953",
    "sg:province":"Z\u00fcrich",
    "wof:name":"Peter Vetsch Ag Architekturb\u00fcro",
    "wof:placetype":"venue"
},
  "geometry": {"coordinates":[8.383769,47.403713],"type":"Point"}
}