{
  "type": "Feature",
  "properties": {
    "iso:country":"CH",
    "sg:address":"Centre Magro",
    "sg:city":"Uvrier",
    "sg:orig_category":"Fachdetailhandel mit pharmazeutischen Produkten",
    "sg:phone":"+41 27 203 47 74",
    "sg:postcode":"1958",
    "sg:province":"Valais",
    "wof:name":"Pascal Caloz Pharmacie Du Centre",
    "wof:placetype":"venue"
},
  "geometry": {"coordinates":[7.4116902351,46.2523155212],"type":"Point"}
}