{
  "type": "Feature",
  "properties": {
    "iso:country":"CH",
    "sg:address":"Hammerstrasse 123",
    "sg:city":"Basel",
    "sg:orig_category":"Datenverarbeitungsdienste Softwareentwicklung U beratung",
    "sg:phone":"+41 61 692 60 11",
    "sg:postcode":"4057",
    "sg:province":"Basel-Stadt",
    "wof:name":"Mor Informatik Ag",
    "wof:placetype":"venue"
},
  "geometry": {"coordinates":[7.594996,47.566849],"type":"Point"}
}