{
  "type": "Feature",
  "properties": {
    "iso:country":"CH",
    "sg:address":"Schulstrasse 31",
    "sg:city":"Z\u00fcrich",
    "sg:orig_category":"Architekturb\u00fcros",
    "sg:phone":"+41 33 676 32 52",
    "sg:postcode":"8050",
    "sg:province":"Z\u00fcrich",
    "wof:name":"Hans-j\u00fcrg M\u00fcller Architektur & Bau Gmbh",
    "wof:placetype":"venue"
},
  "geometry": {"coordinates":[7.692735,46.62553],"type":"Point"}
}