{
  "type": "Feature",
  "properties": {
    "iso:country":"CH",
    "sg:address":"Bildfeldstrasse 41",
    "sg:city":"Bronschhofen",
    "sg:orig_category":"Erbringung von sonstigen Dienstleistungen f\u00fcr Unternehmen Fachdetailhandel in Verkaufsr\u00e4umen",
    "sg:phone":"+41 71 911 98 32",
    "sg:postcode":"9552",
    "sg:province":"St. Gallen",
    "wof:name":"Animationart St\u00fcrm Ismael",
    "wof:placetype":"venue"
},
  "geometry": {"coordinates":[9.0359678268,47.4731864929],"type":"Point"}
}