{
  "type": "Feature",
  "properties": {
    "iso:country":"CH",
    "sg:address":"Schulstrasse 20 8952 Schlieren. Postfach 811",
    "sg:city":"Z\u00fcrich-m\u00fclligen",
    "sg:orig_category":"Grosshandel mit Getr\u00e4nken Markt U Meinungsforschung",
    "sg:phone":"+41 17301033",
    "sg:postcode":"8010",
    "sg:province":"Z\u00fcrich",
    "wof:name":"Vitana Ag",
    "wof:placetype":"venue"
},
  "geometry": {"coordinates":[8.4529886246,47.3970108032],"type":"Point"}
}