{
  "type": "Feature",
  "properties": {
    "iso:country":"CH",
    "sg:address":"Rue Du Jura 7",
    "sg:city":"Del\u00e9mont",
    "sg:orig_category":"Arztpraxen",
    "sg:phone":"+41 32 422 63 74",
    "sg:postcode":"2800",
    "sg:province":"Jura",
    "wof:name":"Dr M\u00e9d. Ahmed El-hoiydi M\u00e9decin G\u00e9n\u00e9raliste Fmh",
    "wof:placetype":"venue"
},
  "geometry": {"coordinates":[7.353417,47.363537],"type":"Point"}
}