{
  "type": "Feature",
  "properties": {
    "iso:country":"CH",
    "sg:address":"B\u00e4renweg 36",
    "sg:city":"W\u00fcrenlingen",
    "sg:orig_category":"Herstellung von Ger\u00e4ten der Elektrizit\u00e4tserzeugung, -verteilung u.\u00e4. -Herstellung von sonstigen elek",
    "sg:phone":"+41 56 290 00 88",
    "sg:postcode":"5303",
    "sg:province":"Aargau",
    "wof:name":"Km-elektronik M\u00fcller Kurt",
    "wof:placetype":"venue"
},
  "geometry": {"coordinates":[8.2527151108,47.5346183777],"type":"Point"}
}