{
  "type": "Feature",
  "properties": {
    "iso:country":"CH",
    "sg:address":"Schulhausstrasse 14",
    "sg:city":"Brig",
    "sg:orig_category":"Grosshandel mit Nahrungsmitteln, Getr\u00e4nken U Tabakwaren ohne ausgepr\u00e4gten Schwerpunkt",
    "sg:postcode":"3900",
    "sg:province":"Valais",
    "wof:name":"Orquidia Lebensmittel, Cardoso Santos Soeiro Maria Amelia",
    "wof:placetype":"venue"
},
  "geometry": {"coordinates":[7.9891748428,46.3169174194],"type":"Point"}
}