{
  "type": "Feature",
  "properties": {
    "iso:country":"CH",
    "sg:address":"R\u00fctmattstrasse 7",
    "sg:city":"Aarau",
    "sg:orig_category":"Softwareentwicklung U beratung",
    "sg:phone":"+41 56 442 58 00",
    "sg:postcode":"5004",
    "sg:province":"Aargau",
    "wof:name":"Cadima, Schulung Und Beratung, Verena Kornfeld",
    "wof:placetype":"venue"
},
  "geometry": {"coordinates":[8.2024517059,47.4788551331],"type":"Point"}
}