{
  "type": "Feature",
  "properties": {
    "iso:country":"CH",
    "sg:address":"Schnaihalde 68",
    "sg:city":"R\u00fcdlingen",
    "sg:orig_category":"Detailhandel mit Antiquit\u00e4ten",
    "sg:phone":"+41 18673027",
    "sg:postcode":"8455",
    "sg:province":"Schaffhausen",
    "wof:name":"Paul H\u00fcrsch Rhy-boutique Antiquit\u00e4ten",
    "wof:placetype":"venue"
},
  "geometry": {"coordinates":[8.571552,47.579758],"type":"Point"}
}