{
  "type": "Feature",
  "properties": {
    "iso:country":"CH",
    "sg:address":"Haldenbachstrasse 2 8006 Z\u00fcrich. Postfach",
    "sg:city":"Z\u00fcrich",
    "sg:orig_category":"Advokaturb\u00fcros",
    "sg:phone":"+41 12619068",
    "sg:postcode":"8033",
    "sg:province":"Z\u00fcrich",
    "wof:name":"Marcel Bosonnet Advokaturb\u00fcro",
    "wof:placetype":"venue"
},
  "geometry": {"coordinates":[8.547114,47.379761],"type":"Point"}
}