{
  "type": "Feature",
  "properties": {
    "iso:country":"CH",
    "sg:address":"Unterzelgstrasse 16 5612 Villmergen. Postfach 40",
    "sg:city":"Villmergen",
    "sg:orig_category":"Fachdetailhandel in Verkaufsr\u00e4umen Gartenbau",
    "sg:phone":"+41 56 622 13 39",
    "sg:postcode":"5612",
    "sg:province":"Aargau",
    "wof:name":"G\u00e4rtnerei Vock Blumengesch\u00e4ft",
    "wof:placetype":"venue"
},
  "geometry": {"coordinates":[8.2399635315,47.3540115356],"type":"Point"}
}