{
  "type": "Feature",
  "properties": {
    "iso:country":"CH",
    "sg:address":"Spalenvorstadt 37",
    "sg:city":"Basel",
    "sg:orig_category":"Sanit\u00e4rinstallation Sanit\u00e4rinstallation U Spenglerei",
    "sg:phone":"+41 61 261 43 70",
    "sg:postcode":"4051",
    "sg:province":"Basel-Stadt",
    "wof:name":"Max Br\u00fchl Ag Spenglerei Usw",
    "wof:placetype":"venue"
},
  "geometry": {"coordinates":[7.5818939209,47.557598114],"type":"Point"}
}