{
  "type": "Feature",
  "properties": {
    "iso:country":"CH",
    "sg:address":"3929 T\u00e4sch. Postfach",
    "sg:city":"T\u00e4sch",
    "sg:classifiers":[
        {
            "category":"Travel",
            "subcategory":"Hotels & Motels",
            "type":"Entertainment"
        }
    ],
    "sg:postcode":"3929",
    "sg:province":"Valais",
    "sg:tags":[
        "hotels",
        "mit",
        "restaurant"
    ],
    "wof:name":"Imex Gastro Gmbh",
    "wof:placetype":"venue"
},
  "geometry": {"coordinates":[8.7577753067,47.2063064575],"type":"Point"}
}