{
  "type": "Feature",
  "properties": {
    "addr:full":"Route De Moncor 4 1752 Villars-sur-gl\u00e2ne Case Postale 1071 Fribourg Fribourg 1701",
    "addr:housenumber":"4",
    "addr:postcode":"1752;1071;1701",
    "addr:street":"Route De Moncor;Postale",
    "iso:country":"CH",
    "sg:address":"Route De Moncor 4 1752 Villars-sur-gl\u00e2ne Case Postale 1071",
    "sg:city":"Fribourg",
    "sg:orig_category":"Herstellung von Ger\u00e4ten der Elektrizit\u00e4tserzeugung, -verteilung u.\u00e4. -Herstellung von elektronischen",
    "sg:phone":"+41 26 407 11 11",
    "sg:postcode":"1701",
    "sg:province":"Fribourg",
    "wof:name":"Vibro-meter Bvg-stiftung",
    "wof:placetype":"venue"
},
  "geometry": {"coordinates":[7.126434,46.799084],"type":"Point"}
}