{
  "type": "Feature",
  "properties": {
    "iso:country":"CH",
    "sg:address":"Chamerstrasse 89",
    "sg:city":"Zug",
    "sg:orig_category":"Herstellung von Konstruktionsteilen, Fertigbauteilen U Ausbauelementen aus Holz",
    "sg:phone":"+41 41 850 61 61",
    "sg:postcode":"6300",
    "sg:province":"Zug",
    "wof:name":"Bm Steiner Gmbh",
    "wof:placetype":"venue"
},
  "geometry": {"coordinates":[8.4973897934,47.1775627136],"type":"Point"}
}