{
  "type": "Feature",
  "properties": {
    "iso:country":"CH",
    "sg:address":"Gass 8 8226 Schleitheim. Postfach",
    "sg:city":"Schleitheim",
    "sg:orig_category":"Softwareentwicklung U beratung",
    "sg:postcode":"8226",
    "sg:province":"Schaffhausen",
    "wof:name":"Top-site Kientsch",
    "wof:placetype":"venue"
},
  "geometry": {"coordinates":[8.4863014221,47.7511672974],"type":"Point"}
}