{
  "type": "Feature",
  "properties": {
    "iso:country":"CH",
    "sg:address":"Boulevard De P\u00e9rolles 10",
    "sg:city":"Fribourg",
    "sg:orig_category":"Herstellung von medizinischen U chirurgischen Ger\u00e4ten sowie orthop\u00e4dischen Vorrichtungen Zahntechnis",
    "sg:phone":"+41 26 322 57 58",
    "sg:postcode":"1700",
    "sg:province":"Fribourg",
    "wof:name":"Dentoceram Sa",
    "wof:placetype":"venue"
},
  "geometry": {"coordinates":[7.151966095,46.8016242981],"type":"Point"}
}