{
  "type": "Feature",
  "properties": {
    "iso:country":"CH",
    "sg:address":"Lect Rue 29",
    "sg:city":"Meyrin",
    "sg:orig_category":"Unclassifiable Establishments",
    "sg:phone":"+41 22 785 88 88",
    "sg:postcode":"1217",
    "sg:province":"Gen\u00e8ve",
    "wof:name":"Tr Andr\u00e9 Curchod Sa",
    "wof:placetype":"venue"
},
  "geometry": {"coordinates":[6.0815730095,46.2250823975],"type":"Point"}
}