{
  "type": "Feature",
  "properties": {
    "iso:country":"CH",
    "sg:address":"St\u00fcdliackerstrasse 11",
    "sg:city":"Schaffhausen",
    "sg:orig_category":"Non-Classified Establishments",
    "sg:phone":"+41 52 232 46 01",
    "sg:postcode":"8207",
    "sg:province":"Schaffhausen",
    "wof:name":"Restaurant Hirschen",
    "wof:placetype":"venue"
},
  "geometry": {"coordinates":[8.7443170547,47.4578056335],"type":"Point"}
}