{
  "type": "Feature",
  "properties": {
    "addr:full":"Levant Chemin Du 27 Crans-pr\u00e8s-c\u00e9ligny Vaud 1299",
    "addr:housenumber":"1299",
    "addr:street":"Chemin Du 27 Crans-Pre\u0300S-Ce\u0301Ligny",
    "iso:country":"CH",
    "sg:address":"Levant Chemin Du 27",
    "sg:city":"Crans-pr\u00e8s-c\u00e9ligny",
    "sg:classifiers":[
        {
            "category":"Professional",
            "subcategory":"Accounting & Tax Preparation",
            "type":"Services"
        }
    ],
    "sg:postcode":"1299",
    "sg:province":"Vaud",
    "sg:tags":[
        "u",
        "yachtbau",
        "boot"
    ],
    "wof:name":"M\u00e9canique Navale Muller Sa",
    "wof:placetype":"venue"
},
  "geometry": {"coordinates":[6.20611,46.359386],"type":"Point"}
}