{
  "type": "Feature",
  "properties": {
    "iso:country":"CH",
    "sg:address":"Dorfstrasse 7 3634 Thierachern. Postfach",
    "sg:city":"Thierachern",
    "sg:orig_category":"Sonstiger Grosshandel",
    "sg:postcode":"3634",
    "sg:province":"Bern",
    "wof:name":"Fsg Handels Ag",
    "wof:placetype":"venue"
},
  "geometry": {"coordinates":[7.5748901367,46.7538871765],"type":"Point"}
}