{
  "type": "Feature",
  "properties": {
    "iso:country":"CH",
    "sg:address":"Hauptstrasse 118b",
    "sg:city":"Niederteufen",
    "sg:orig_category":"Unternehmensberatung",
    "sg:phone":"+41 71 274 19 00",
    "sg:postcode":"9052",
    "sg:province":"Appenzell Ausserrhoden",
    "wof:name":"Ms Management Service (europa) Ag",
    "wof:placetype":"venue"
},
  "geometry": {"coordinates":[9.3665962219,47.3924942017],"type":"Point"}
}