{
  "type": "Feature",
  "properties": {
    "iso:country":"CH",
    "sg:address":"Industrie Allmend",
    "sg:city":"Rohrbach",
    "sg:orig_category":"Zimmerei, Dachdeckerei, Bauspenglerei U Abdichtung",
    "sg:phone":"+41 62 961 52 70",
    "sg:postcode":"4938",
    "sg:province":"Bern",
    "wof:name":"S. Kaufmann",
    "wof:placetype":"venue"
},
  "geometry": {"coordinates":[7.820016861,47.1348381042],"type":"Point"}
}