{
  "type": "Feature",
  "properties": {
    "iso:country":"CH",
    "sg:address":"Postgasse 4",
    "sg:city":"Arbon",
    "sg:orig_category":"Detailhandel mit Uhren U Schmuck",
    "sg:phone":"+41 71 446 68 50",
    "sg:postcode":"9320",
    "sg:province":"Thurgau",
    "wof:name":"Lisa Dumermuth Goldschmiede",
    "wof:placetype":"venue"
},
  "geometry": {"coordinates":[9.4358167648,47.5157203674],"type":"Point"}
}