{
  "type": "Feature",
  "properties": {
    "iso:country":"CH",
    "sg:address":"Alpenstrasse 2 6300 Zug. Postfach 4461",
    "sg:city":"Zug",
    "sg:orig_category":"Grosshandel mit Erzen U Metallen",
    "sg:phone":"+41 41 710 71 86",
    "sg:postcode":"6304",
    "sg:province":"Zug",
    "wof:name":"Ferrobras Ag",
    "wof:placetype":"venue"
},
  "geometry": {"coordinates":[8.5138454437,47.1707572937],"type":"Point"}
}