{
  "type": "Feature",
  "properties": {
    "iso:country":"CH",
    "sg:address":"1037 Etagni\u00e8res Case Postale 9",
    "sg:city":"Etagni\u00e8res",
    "sg:orig_category":"Sportvereine Ballsport Fussball",
    "sg:phone":"+41 21 731 40 96",
    "sg:postcode":"1037",
    "sg:province":"Vaud",
    "wof:name":"Fc Etagni\u00e8res",
    "wof:placetype":"venue"
},
  "geometry": {"coordinates":[6.6100001335,46.6005897522],"type":"Point"}
}