{
  "type": "Feature",
  "properties": {
    "iso:country":"CH",
    "sg:address":"6017",
    "sg:city":"Ruswil",
    "sg:orig_category":"Sportvereine Sch\u00fctzen",
    "sg:phone":"+41 19543213",
    "sg:postcode":"6017",
    "sg:province":"Luzern",
    "wof:name":"Sch\u00fctzenverein",
    "wof:placetype":"venue"
},
  "geometry": {"coordinates":[8.1267347336,47.0835609436],"type":"Point"}
}