{
  "type": "Feature",
  "properties": {
    "iso:country":"CH",
    "sg:address":"Stationsstrasse 26",
    "sg:city":"Seuzach",
    "sg:orig_category":"Maler U Glasergewerbe Malerei",
    "sg:phone":"+41 41 460 18 81",
    "sg:postcode":"8472",
    "sg:province":"Z\u00fcrich",
    "wof:name":"Ren\u00e9 Acklin Malergesch\u00e4ft",
    "wof:placetype":"venue"
},
  "geometry": {"coordinates":[8.2235832214,47.131149292],"type":"Point"}
}