{
  "type": "Feature",
  "properties": {
    "iso:country":"CH",
    "sg:address":"Luzernerstrasse 37",
    "sg:city":"Oftringen",
    "sg:orig_category":"Handelsvermittlung von Nahrungsmitteln, Getr\u00e4nken U Tabakwaren RESTAURANTS: TEA-ROOMS",
    "sg:phone":"+41 62 797 18 12",
    "sg:postcode":"4665",
    "sg:province":"Aargau",
    "wof:name":"K\u00e4ser & Kaltenrieder Gmbh",
    "wof:placetype":"venue"
},
  "geometry": {"coordinates":[7.9256000519,47.309261322],"type":"Point"}
}