{
  "type": "Feature",
  "properties": {
    "addr:full":"Champ De La Croix 11 Courtepin Fribourg 1784",
    "addr:housenumber":"11",
    "addr:postcode":"1784",
    "addr:street":"Champ De La Croix",
    "iso:country":"CH",
    "sg:address":"Champ De La Croix 11",
    "sg:city":"Courtepin",
    "sg:orig_category":"Autotransporte M\u00f6bel",
    "sg:phone":"+41 26 684 13 42",
    "sg:postcode":"1784",
    "sg:province":"Fribourg",
    "wof:name":"Afrim Balija A.n.b. Express",
    "wof:placetype":"venue"
},
  "geometry": {"coordinates":[7.124136,46.867226],"type":"Point"}
}