{
  "type": "Feature",
  "properties": {
    "iso:country":"CH",
    "sg:address":"Oberhof 15",
    "sg:city":"Weisslingen",
    "sg:orig_category":"Detailhandel mit Zeitungen U Zeitschriften Kioske Tankstellen",
    "sg:phone":"+41 52 384 26 02",
    "sg:postcode":"8484",
    "sg:province":"Z\u00fcrich",
    "wof:name":"Tamoil Service Station, Fritz Oberle",
    "wof:placetype":"venue"
},
  "geometry": {"coordinates":[8.7667131424,47.4279670715],"type":"Point"}
}