{
  "type": "Feature",
  "properties": {
    "addr:full":"Schulweg 1 Eiken Aargau 5074",
    "addr:housenumber":"1",
    "addr:postcode":"5074",
    "addr:street":"Schulweg",
    "iso:country":"CH",
    "sg:address":"Schulweg 1",
    "sg:city":"Eiken",
    "sg:orig_category":"Bezirks, Sekundar, Realschulen, Oberstufe der Primarschulen",
    "sg:postcode":"5074",
    "sg:province":"Aargau",
    "wof:name":"Sekundarschule",
    "wof:placetype":"venue"
},
  "geometry": {"coordinates":[7.983271,47.539921],"type":"Point"}
}