{
  "type": "Feature",
  "properties": {
    "iso:country":"CH",
    "sg:address":"Au Village",
    "sg:city":"Ursy",
    "sg:classifiers":[
        {
            "category":"Travel",
            "subcategory":"Hotels & Motels",
            "type":"Entertainment"
        }
    ],
    "sg:postcode":"1670",
    "sg:province":"Fribourg",
    "sg:tags":[
        "hotels",
        "mit",
        "restaurant"
    ],
    "wof:name":"H\u00f4tel De Ville De Rue, Overney J.-l. Et C.",
    "wof:placetype":"venue"
},
  "geometry": {"coordinates":[6.8347401619,46.6346282959],"type":"Point"}
}