{
  "type": "Feature",
  "properties": {
    "iso:country":"CH",
    "sg:address":"Helgisried",
    "sg:city":"R\u00fceggisberg",
    "sg:orig_category":"RESTAURANTS: TEA-ROOMS",
    "sg:postcode":"3088",
    "sg:province":"Bern",
    "wof:name":"Restaurant Zum J\u00e4ger, Erwin Kallabis",
    "wof:placetype":"venue"
},
  "geometry": {"coordinates":[7.4389481544,46.8215065002],"type":"Point"}
}