{
  "type": "Feature",
  "properties": {
    "iso:country":"CH",
    "sg:address":"Industriestrasse 2",
    "sg:city":"Rupperswil",
    "sg:orig_category":"Detailhandel mit Getr\u00e4nken",
    "sg:phone":"+41 62 897 57 30",
    "sg:postcode":"5102",
    "sg:province":"Aargau",
    "wof:name":"Hansruedi Schmid Ruedis Getr\u00e4nke",
    "wof:placetype":"venue"
},
  "geometry": {"coordinates":[8.1427822113,47.409034729],"type":"Point"}
}