{
  "type": "Feature",
  "properties": {
    "iso:country":"CH",
    "sg:address":"Bossons Rue Des 23",
    "sg:city":"Onex",
    "sg:orig_category":"Grosshandel mit Textilien",
    "sg:phone":"+41 22 793 54 19",
    "sg:postcode":"1213",
    "sg:province":"Gen\u00e8ve",
    "wof:name":"Sinouhe Inc. Dover, Succursale D'onex",
    "wof:placetype":"venue"
},
  "geometry": {"coordinates":[6.1053581238,46.187587738],"type":"Point"}
}