{
  "type": "Feature",
  "properties": {
    "iso:country":"CH",
    "sg:address":"Oberdorfstrasse 17 8852 Altendorf. Postfach",
    "sg:city":"Altendorf",
    "sg:orig_category":"Gartenbau",
    "sg:postcode":"8852",
    "sg:province":"Schwyz",
    "wof:name":"Xl-plant Klein Thomas",
    "wof:placetype":"venue"
},
  "geometry": {"coordinates":[8.8299894333,47.1890068054],"type":"Point"}
}