{
  "type": "Feature",
  "properties": {
    "iso:country":"CH",
    "sg:address":"B\u00fchlstrasse 8",
    "sg:city":"Jona",
    "sg:orig_category":"Massagestudios P\u00e9dicure",
    "sg:phone":"+41 71 925 39 29",
    "sg:postcode":"8645",
    "sg:province":"St. Gallen",
    "wof:name":"Eva Kn\u00f6pfel",
    "wof:placetype":"venue"
},
  "geometry": {"coordinates":[9.0400209427,47.457988739],"type":"Point"}
}