{
  "type": "Feature",
  "properties": {
    "iso:country":"CH",
    "sg:address":"Spielmatte 4",
    "sg:city":"Unterseen",
    "sg:orig_category":"Herstellung von k\u00e4lte U lufttechnischen Erzeugnissen f\u00fcr gewerbliche Zwecke",
    "sg:phone":"+41 61 831 65 55",
    "sg:postcode":"3800",
    "sg:province":"Bern",
    "wof:name":"Odoro Gmbh",
    "wof:placetype":"venue"
},
  "geometry": {"coordinates":[7.8512659073,46.6870002747],"type":"Point"}
}