{
  "type": "Feature",
  "properties": {
    "iso:country":"CH",
    "sg:address":"Rue Saint-randoald 4",
    "sg:city":"Courrendlin",
    "sg:orig_category":"Vermittlung von Immobilien",
    "sg:phone":"+41 32 435 69 69",
    "sg:postcode":"2830",
    "sg:province":"Jura",
    "wof:name":"R. & F. Menghini Rfm Immobilier",
    "wof:placetype":"venue"
},
  "geometry": {"coordinates":[7.3756098747,47.3445510864],"type":"Point"}
}