{
  "type": "Feature",
  "properties": {
    "iso:country":"CH",
    "sg:address":"Pretorio Via 7",
    "sg:city":"Lugano",
    "sg:orig_category":"Unclassifiable Establishments",
    "sg:postcode":"6900",
    "sg:province":"Ticino",
    "wof:name":"Finty Sa",
    "wof:placetype":"venue"
},
  "geometry": {"coordinates":[9.1283597946,46.2375984192],"type":"Point"}
}