{
  "type": "Feature",
  "properties": {
    "iso:country":"CH",
    "sg:address":"6927",
    "sg:city":"Agra",
    "sg:orig_category":"Unclassifiable Establishments",
    "sg:postcode":"6927",
    "sg:province":"Ticino",
    "wof:name":"Ab-artig.ch Glauser + Zahnd",
    "wof:placetype":"venue"
},
  "geometry": {"coordinates":[7.524810791,47.1698150635],"type":"Point"}
}