{
  "type": "Feature",
  "properties": {
    "iso:country":"CH",
    "sg:address":"Rue De Rive 67",
    "sg:city":"Nyon",
    "sg:orig_category":"Schiffs U Bootsbau",
    "sg:phone":"+41 22 361 12 50",
    "sg:postcode":"1260",
    "sg:province":"Vaud",
    "wof:name":"Chantier Navale Paul Muller",
    "wof:placetype":"venue"
},
  "geometry": {"coordinates":[6.241435051,46.380657196],"type":"Point"}
}