{
  "type": "Feature",
  "properties": {
    "iso:country":"CH",
    "sg:address":"Oberdorf",
    "sg:city":"N\u00e4fels",
    "sg:orig_category":"Handel mit Automobilen Tankstellen",
    "sg:phone":"+41 91 973 33 33",
    "sg:postcode":"8752",
    "sg:province":"Glarus",
    "wof:name":"Garage Cassarate Sa",
    "wof:placetype":"venue"
},
  "geometry": {"coordinates":[8.9607639313,46.0176086426],"type":"Point"}
}