{
  "type": "Feature",
  "properties": {
    "iso:country":"CH",
    "sg:address":"Bahnhofstrasse 126",
    "sg:city":"Schiers",
    "sg:orig_category":"Unclassifiable Establishments",
    "sg:phone":"+41 81 328 10 35",
    "sg:postcode":"7220",
    "sg:province":"Graubunden",
    "wof:name":"Thomas Bhend",
    "wof:placetype":"venue"
},
  "geometry": {"coordinates":[9.6882944107,46.9684448242],"type":"Point"}
}