{
  "type": "Feature",
  "properties": {
    "iso:country":"CH",
    "sg:address":"Hostattstrasse 7",
    "sg:city":"Sarnen",
    "sg:orig_category":"Architektur U Ingenieurb\u00fcros",
    "sg:phone":"+41 41 660 07 07",
    "sg:postcode":"6060",
    "sg:province":"Obwalden",
    "wof:name":"B\u00fcro 7 Halter",
    "wof:placetype":"venue"
},
  "geometry": {"coordinates":[8.250314,46.895393],"type":"Point"}
}