{
  "type": "Feature",
  "properties": {
    "iso:country":"CH",
    "sg:address":"Werkstrasse 25 7000 Chur. Postfach",
    "sg:city":"Chur",
    "sg:orig_category":"Erbringung von Dienstleistungen f\u00fcr Unternehmen",
    "sg:postcode":"7000",
    "sg:province":"Graubunden",
    "wof:name":"Image Solutions Jetzer Grafik Und Werbung",
    "wof:placetype":"venue"
},
  "geometry": {"coordinates":[9.5270996094,46.8562507629],"type":"Point"}
}