{
  "type": "Feature",
  "properties": {
    "iso:country":"CH",
    "sg:address":"Lyon Rue De 75 1203 Gen\u00e8ve. Postfach",
    "sg:city":"Gen\u00e8ve",
    "sg:orig_category":"Grosshandel mit Getreide, Saatgut U Futtermitteln",
    "sg:phone":"+41 21 617 74 61",
    "sg:postcode":"1203",
    "sg:province":"Gen\u00e8ve",
    "wof:name":"Association Suisse Des S\u00e9lectionneurs, Ass",
    "wof:placetype":"venue"
},
  "geometry": {"coordinates":[6.6281042099,46.5098152161],"type":"Point"}
}