{
  "type": "Feature",
  "properties": {
    "addr:full":"Route De Thonon 146 V\u00e9senaz 1245 Collonge-bellerive. Postfach V\u00e9senaz Gen\u00e8ve 1222",
    "addr:housenumber":"146",
    "addr:postcode":"1245 collonge-bellerive. postfach ve\u0301senaz;1222",
    "addr:street":"Route De Thonon",
    "iso:country":"CH",
    "sg:address":"Route De Thonon 146 V\u00e9senaz 1245 Collonge-bellerive. Postfach",
    "sg:city":"V\u00e9senaz",
    "sg:classifiers":[
        {
            "category":"Professional",
            "subcategory":"Accounting & Tax Preparation",
            "type":"Services"
        }
    ],
    "sg:postcode":"1222",
    "sg:province":"Gen\u00e8ve",
    "sg:tags":[
        "u",
        "yachtbau",
        "boot"
    ],
    "wof:name":"Internautique S\u00e0rl",
    "wof:placetype":"venue"
},
  "geometry": {"coordinates":[6.204244,46.253563],"type":"Point"}
}