{
  "type": "Feature",
  "properties": {
    "iso:country":"CH",
    "sg:address":"Rue Des Bossons 21",
    "sg:city":"Onex",
    "sg:orig_category":"Reiseb\u00fcros",
    "sg:phone":"+41 22 879 88 90",
    "sg:postcode":"1213",
    "sg:province":"Gen\u00e8ve",
    "wof:name":"Helvetic Tours",
    "wof:placetype":"venue"
},
  "geometry": {"coordinates":[6.1048622131,46.1874008179],"type":"Point"}
}