{
  "type": "Feature",
  "properties": {
    "iso:country":"CH",
    "sg:address":"Eifeldweg 17",
    "sg:city":"Wimmis",
    "sg:orig_category":"Sportvereine Sch\u00fctzen",
    "sg:phone":"+41 33 657 20 50",
    "sg:postcode":"3752",
    "sg:province":"Bern",
    "wof:name":"Sch\u00fctzengesellschaft Spiez",
    "wof:placetype":"venue"
},
  "geometry": {"coordinates":[7.6394691467,46.682144165],"type":"Point"}
}