{
  "type": "Feature",
  "properties": {
    "iso:country":"CH",
    "sg:address":"1115",
    "sg:city":"Vullierens",
    "sg:orig_category":"Dienstleistungen im landwirtschaftlichen Pflanzen U Gartenbau",
    "sg:postcode":"1115",
    "sg:province":"Vaud",
    "wof:name":"Battoir \u00e0 Grains De Vullierens-gland",
    "wof:placetype":"venue"
},
  "geometry": {"coordinates":[6.482336998,46.5726203918],"type":"Point"}
}