{
  "type": "Feature",
  "properties": {
    "iso:country":"CH",
    "sg:address":"Champs-montants 14a 2074 Marin-centre. Postfach",
    "sg:city":"Marin-centre",
    "sg:orig_category":"Herstellung von Ger\u00e4ten der Elektrizit\u00e4tserzeugung, -verteilung u.\u00e4. -Herstellung von elektronischen",
    "sg:phone":"+41 32 755 63 56",
    "sg:postcode":"2074",
    "sg:province":"Neuch\u00e2tel",
    "wof:name":"Tag Heuer Sa",
    "wof:placetype":"venue"
},
  "geometry": {"coordinates":[7.0001649857,47.0123138428],"type":"Point"}
}