{
  "type": "Feature",
  "properties": {
    "iso:country":"CH",
    "sg:address":"R\u00fctistrasse 11 5400 Baden. Postfach",
    "sg:city":"Baden",
    "sg:orig_category":"Erbringung von Dienstleistungen f\u00fcr Unternehmen",
    "sg:phone":"+41 17716181",
    "sg:postcode":"5400",
    "sg:province":"Aargau",
    "wof:name":"Frentzel Marco, Visuelle Gestaltung Und Digitale Kommunikation",
    "wof:placetype":"venue"
},
  "geometry": {"coordinates":[8.547659874,47.3237609863],"type":"Point"}
}