{
  "type": "Feature",
  "properties": {
    "iso:country":"CH",
    "sg:address":"Von May-strasse 39",
    "sg:city":"Thun",
    "sg:orig_category":"Detailhandel mit Brot, Back U S\u00fcsswaren",
    "sg:phone":"+41 33 336 76 06",
    "sg:postcode":"3604",
    "sg:province":"Bern",
    "wof:name":"Peter & Edith Linder B\u00e4ckerei & Konditorei",
    "wof:placetype":"venue"
},
  "geometry": {"coordinates":[7.615507,46.732399],"type":"Point"}
}