{
  "type": "Feature",
  "properties": {
    "iso:country":"CH",
    "sg:address":"Witikonstrasse 4",
    "sg:city":"Pfaffhausen",
    "sg:orig_category":"Geb\u00e4ude, Wohnungsreinigung",
    "sg:phone":"+41 56 282 36 66",
    "sg:postcode":"8118",
    "sg:province":"Z\u00fcrich",
    "wof:name":"Alvina-reinigung",
    "wof:placetype":"venue"
},
  "geometry": {"coordinates":[8.2940158844,47.4893493652],"type":"Point"}
}