{
  "type": "Feature",
  "properties": {
    "iso:country":"CH",
    "sg:address":"Kr\u00e4zernstrasse 10 9014 St. Gallen. Postfach 9014 St. Gallen",
    "sg:city":"Zust",
    "sg:orig_category":"Saunas, Solarien, Fitnesszentren U \u00e4hnliches",
    "sg:postcode":"14",
    "wof:name":"Sauna Solarium Stocken Gmbh",
    "wof:placetype":"venue"
},
  "geometry": {"coordinates":[9.3255529404,47.4074172974],"type":"Point"}
}