{
  "type": "Feature",
  "properties": {
    "iso:country":"CH",
    "sg:address":"Badenerstrasse 125 8004 Z\u00fcrich. Postfach",
    "sg:city":"Z\u00fcrich",
    "sg:classifiers":[
        {
            "category":"Professional",
            "subcategory":"Employment Agencies",
            "type":"Services"
        }
    ],
    "sg:phone":"+41 12972838",
    "sg:postcode":"8036",
    "sg:province":"Z\u00fcrich",
    "sg:tags":[
        "personal",
        "u",
        "stellenvermittlung"
    ],
    "wof:name":"Smile Job Ag",
    "wof:placetype":"venue"
},
  "geometry": {"coordinates":[8.5235452652,47.3742332458],"type":"Point"}
}