{
  "type": "Feature",
  "properties": {
    "iso:country":"CH",
    "sg:address":"Grubenstrasse 1 8200 Schaffhausen. Postfach 201",
    "sg:city":"Schaffhausen",
    "sg:orig_category":"Non-Classified Establishments",
    "sg:phone":"+41 52 624 07 75",
    "sg:postcode":"8201",
    "sg:province":"Schaffhausen",
    "wof:name":"Susanne Bachmann Treuhand",
    "wof:placetype":"venue"
},
  "geometry": {"coordinates":[8.6403551102,47.7015419006],"type":"Point"}
}