{
  "type": "Feature",
  "properties": {
    "iso:country":"CH",
    "sg:address":"Di Sacco Via Alberto 1",
    "sg:city":"Bellinzona",
    "sg:orig_category":"Non-Classified Establishments",
    "sg:postcode":"6500",
    "sg:province":"Ticino",
    "wof:name":"Rivo Sa",
    "wof:placetype":"venue"
},
  "geometry": {"coordinates":[9.0259609222,46.1954307556],"type":"Point"}
}