{
  "type": "Feature",
  "properties": {
    "iso:country":"CH",
    "sg:address":"3940",
    "sg:city":"Steg",
    "sg:classifiers":[
        {
            "category":"Utilities",
            "subcategory":"Electric",
            "type":"Services"
        }
    ],
    "sg:phone":"+41 56 267 02 20",
    "sg:postcode":"3940",
    "sg:province":"Valais",
    "sg:tags":[
        "electricity",
        "raw",
        "energy",
        "material"
    ],
    "wof:name":"Kraftwerk Rekingen Ag",
    "wof:placetype":"venue"
},
  "geometry": {"coordinates":[8.3222703934,47.5677680969],"type":"Point"}
}