{
  "type": "Feature",
  "properties": {
    "iso:country":"CH",
    "sg:address":"Zentralstrasse 12 6030 Ebikon. Postfach 2168",
    "sg:city":"Luzern",
    "sg:orig_category":"Unternehmensberatung Wirtschaftspr\u00fcfung, Steuerberatung U Treuhand",
    "sg:phone":"+41 41 445 01 50",
    "sg:postcode":"6002",
    "sg:province":"Luzern",
    "wof:name":"Attendus Treuhandgesellschaft",
    "wof:placetype":"venue"
},
  "geometry": {"coordinates":[8.3388977051,47.0800323486],"type":"Point"}
}