{
  "type": "Feature",
  "properties": {
    "iso:country":"CH",
    "sg:address":"Boulevard Georges-favon 20",
    "sg:city":"Gen\u00e8ve",
    "sg:orig_category":"Datenverarbeitungsdienste Sonstige mit der Informatik verbundene T\u00e4tigkeiten",
    "sg:phone":"+41 22 800 35 00",
    "sg:postcode":"1204",
    "sg:province":"Gen\u00e8ve",
    "wof:name":"Birdnet, Christophi Claude",
    "wof:placetype":"venue"
},
  "geometry": {"coordinates":[6.13997,46.202435],"type":"Point"}
}