{
  "type": "Feature",
  "properties": {
    "iso:country":"CH",
    "sg:address":"Brunnenwiesenstrasse",
    "sg:city":"Neuhausen",
    "sg:orig_category":"Schwimmb\u00e4der",
    "sg:phone":"+41 52 672 33 03",
    "sg:postcode":"8212",
    "sg:province":"Schaffhausen",
    "wof:name":"Schwimmbad Otterstall",
    "wof:placetype":"venue"
},
  "geometry": {"coordinates":[8.6036701202,47.677482605],"type":"Point"}
}