{
  "type": "Feature",
  "properties": {
    "iso:country":"CH",
    "sg:address":"Kublihoschet 41",
    "sg:city":"Netstal",
    "sg:orig_category":"Kauf U Verkauf von Immobilien auf eigene Rechnung",
    "sg:postcode":"8754",
    "sg:province":"Glarus",
    "wof:name":"Gaspa Ag",
    "wof:placetype":"venue"
},
  "geometry": {"coordinates":[9.0567770004,47.0566635132],"type":"Point"}
}