{
  "type": "Feature",
  "properties": {
    "iso:country":"CH",
    "sg:address":"In Der Euelwies 22 8400 Winterthur. Postfach",
    "sg:city":"Winterthur",
    "sg:orig_category":"Grosshandel mit Erzen U Metallen",
    "sg:phone":"+41 52 209 08 28",
    "sg:postcode":"8400",
    "sg:province":"Z\u00fcrich",
    "wof:name":"Hauser Ag, Winterthur",
    "wof:placetype":"venue"
},
  "geometry": {"coordinates":[8.6759376526,47.507484436],"type":"Point"}
}