{
  "type": "Feature",
  "properties": {
    "iso:country":"CH",
    "sg:address":"Katzenbachstrasse 80",
    "sg:city":"Z\u00fcrich",
    "sg:orig_category":"Schreibb\u00fcros",
    "sg:phone":"+41 13026031",
    "sg:postcode":"8052",
    "sg:province":"Z\u00fcrich",
    "wof:name":"Erika D\u00fcrm\u00fcller Expresstex Schreibb\u00fcro",
    "wof:placetype":"venue"
},
  "geometry": {"coordinates":[8.5476799011,47.4223594666],"type":"Point"}
}