{
  "type": "Feature",
  "properties": {
    "iso:country":"CH",
    "sg:address":"Schulhausstrasse 2",
    "sg:city":"Zuchwil",
    "sg:orig_category":"RESTAURANTS: TEA-ROOMS",
    "sg:phone":"+41 32 685 50 53",
    "sg:postcode":"4528",
    "sg:province":"Solothurn",
    "wof:name":"Flury-leibundgut Sonja",
    "wof:placetype":"venue"
},
  "geometry": {"coordinates":[7.5575728416,47.2038383484],"type":"Point"}
}