{
  "type": "Feature",
  "properties": {
    "iso:country":"CH",
    "sg:address":"1669",
    "sg:city":"Albeuve",
    "sg:orig_category":"Verwertung von Milch",
    "sg:postcode":"1669",
    "sg:province":"Fribourg",
    "wof:name":"Soci\u00e9t\u00e9 De Laiterie Des Thioleyres.",
    "wof:placetype":"venue"
},
  "geometry": {"coordinates":[6.8111100197,46.5389404297],"type":"Point"}
}