{
  "type": "Feature",
  "properties": {
    "iso:country":"CH",
    "sg:address":"Reuenthalerstrasse 949",
    "sg:city":"Leuggern",
    "sg:orig_category":"Sonstige Kurierdienste",
    "sg:phone":"+41 56 245 51 24",
    "sg:postcode":"5316",
    "sg:province":"Aargau",
    "wof:name":"Zoebel-kurier",
    "wof:placetype":"venue"
},
  "geometry": {"coordinates":[8.2134504318,47.5829315186],"type":"Point"}
}