{
  "type": "Feature",
  "properties": {
    "iso:country":"CH",
    "sg:address":"Hofmattstrasse 24 3360 Herzogenbuchsee. Postfach",
    "sg:city":"Herzogenbuchsee",
    "sg:orig_category":"Herstellung von Tanks U Sammelbeh\u00e4ltern aus Metall Sonstiger spezialisierter Hoch U Tiefbau",
    "sg:phone":"+41 71 761 26 32",
    "sg:postcode":"3360",
    "sg:province":"Bern",
    "wof:name":"Sch\u00f6b Edwin Ag",
    "wof:placetype":"venue"
},
  "geometry": {"coordinates":[9.5337734222,47.3148155212],"type":"Point"}
}