{
  "type": "Feature",
  "properties": {
    "iso:country":"CH",
    "sg:address":"Zypressenstrasse 40 8000 Z\u00fcrich. Postfach",
    "sg:city":"Z\u00fcrich",
    "sg:orig_category":"Herstellung von optischen U fotografischen Ger\u00e4ten",
    "sg:postcode":"8001",
    "sg:province":"Z\u00fcrich",
    "wof:name":"Gigant-kino-markt Enz",
    "wof:placetype":"venue"
},
  "geometry": {"coordinates":[8.5122623444,47.3767852783],"type":"Point"}
}