{
  "type": "Feature",
  "properties": {
    "iso:country":"CH",
    "sg:address":"Hebrig 1163",
    "sg:city":"Gais",
    "sg:orig_category":"Softwareentwicklung U beratung",
    "sg:phone":"+41 19951970",
    "sg:postcode":"9056",
    "sg:province":"Appenzell Ausserrhoden",
    "wof:name":"Copal Opr Systems Gmbh",
    "wof:placetype":"venue"
},
  "geometry": {"coordinates":[8.7684745789,47.3700904846],"type":"Point"}
}