{
  "type": "Feature",
  "properties": {
    "iso:country":"CH",
    "sg:address":"H\u00f6henring 53",
    "sg:city":"Z\u00fcrich",
    "sg:orig_category":"Sportvereine Turnen",
    "sg:postcode":"8052",
    "sg:province":"Z\u00fcrich",
    "wof:name":"M\u00e4nnerriege Ktv Seebach",
    "wof:placetype":"venue"
},
  "geometry": {"coordinates":[8.5403318405,47.420173645],"type":"Point"}
}