{
  "type": "Feature",
  "properties": {
    "iso:country":"CH",
    "sg:address":"Talstrasse 4",
    "sg:city":"Ennetmoos",
    "sg:orig_category":"Architektur U Ingenieurb\u00fcros",
    "sg:postcode":"6372",
    "sg:province":"Nidwalden",
    "wof:name":"Gassner Architektur Gmbh",
    "wof:placetype":"venue"
},
  "geometry": {"coordinates":[8.334621,46.955578],"type":"Point"}
}