{
  "type": "Feature",
  "properties": {
    "iso:country":"CH",
    "sg:address":"D\u00f6rfli",
    "sg:city":"Unteriberg",
    "sg:orig_category":"Allgemeiner Hoch U Tiefbau",
    "sg:postcode":"8842",
    "sg:province":"Schwyz",
    "wof:name":"Josef F\u00e4ssler, Bau Und Baggerunternehmen",
    "wof:placetype":"venue"
},
  "geometry": {"coordinates":[8.80399,47.06308],"type":"Point"}
}