{
  "type": "Feature",
  "properties": {
    "iso:country":"CH",
    "sg:address":"Dorfplatz",
    "sg:city":"Zernez",
    "sg:orig_category":"HOTELS: OHNE RESTAURANT",
    "sg:phone":"+41 81 856 14 14",
    "sg:postcode":"7530",
    "sg:province":"Graubunden",
    "wof:name":"Hotel Piz Terza Garni",
    "wof:placetype":"venue"
},
  "geometry": {"coordinates":[10.0953445435,46.6998558044],"type":"Point"}
}