{
  "type": "Feature",
  "properties": {
    "iso:country":"CH",
    "sg:address":"Rousseau Avenue J.-j.",
    "sg:city":"Neuenburg",
    "sg:orig_category":"Herstellung von Medikamenten U sonstigen pharmazeutischen Erzeugnissen",
    "sg:phone":"+41 32 729 97 40",
    "sg:postcode":"2000",
    "sg:province":"Neuch\u00e2tel",
    "wof:name":"Ime Intermed Entreprises Sa",
    "wof:placetype":"venue"
},
  "geometry": {"coordinates":[6.9329419136,46.9939727783],"type":"Point"}
}