{
  "type": "Feature",
  "properties": {
    "iso:country":"CH",
    "sg:address":"Allmendstrasse 2",
    "sg:city":"Villmergen",
    "sg:orig_category":"D\u00e4mmung gegen K\u00e4lte, W\u00e4rme, Schall U Ersch\u00fctterung Verlegen von Fussboden",
    "sg:phone":"+41 56 621 05 05",
    "sg:postcode":"5612",
    "sg:province":"Aargau",
    "wof:name":"Bernhard H\u00fcbscher Unterlagsb\u00f6den",
    "wof:placetype":"venue"
},
  "geometry": {"coordinates":[8.2511816025,47.3553504944],"type":"Point"}
}