{
  "type": "Feature",
  "properties": {
    "iso:country":"CH",
    "sg:address":"Rotfarb 11",
    "sg:city":"Hauptwil",
    "sg:orig_category":"Unternehmensberatung",
    "sg:phone":"+41 71 420 06 92",
    "sg:postcode":"9213",
    "sg:province":"Thurgau",
    "wof:name":"Ochsner Management M.tobler",
    "wof:placetype":"venue"
},
  "geometry": {"coordinates":[9.2471103668,47.479850769],"type":"Point"}
}