{
  "type": "Feature",
  "properties": {
    "addr:full":"R\u00f6tistrasse 4 Feldbrunnen Solothurn 4532",
    "addr:housenumber":"4",
    "addr:postcode":"4532",
    "addr:street":"Roetistrasse;Feldbrunnen Solothurn",
    "iso:country":"CH",
    "sg:address":"R\u00f6tistrasse 4",
    "sg:city":"Feldbrunnen",
    "sg:orig_category":"Allgemeiner Hoch U Tiefbau Unterhalt U Reparatur im Hoch U Tiefbau",
    "sg:phone":"+41 79 631 75 70",
    "sg:postcode":"4532",
    "sg:province":"Solothurn",
    "wof:name":"Trio Bauservice Gmbh Feldbrunnen",
    "wof:placetype":"venue"
},
  "geometry": {"coordinates":[7.555892,47.220165],"type":"Point"}
}