{
  "type": "Feature",
  "properties": {
    "iso:country":"CH",
    "sg:address":"Gumprechtstrasse 38a",
    "sg:city":"Emmetten",
    "sg:orig_category":"Fotografische Ateliers",
    "sg:phone":"+41 41 620 50 56",
    "sg:postcode":"6376",
    "sg:province":"Nidwalden",
    "wof:name":"Christian Perret Werbefotografie",
    "wof:placetype":"venue"
},
  "geometry": {"coordinates":[8.5145788193,46.9591636658],"type":"Point"}
}