{
  "type": "Feature",
  "properties": {
    "iso:country":"CH",
    "sg:address":"H\u00f6cklistein",
    "sg:city":"Jona",
    "sg:orig_category":"Sonstige mit der Informatik verbundene T\u00e4tigkeiten",
    "sg:phone":"+41 79 615 03 33",
    "sg:postcode":"8645",
    "sg:province":"St. Gallen",
    "wof:name":"Pc-formation Lambert",
    "wof:placetype":"venue"
},
  "geometry": {"coordinates":[6.8299050331,47.102809906],"type":"Point"}
}