{
  "type": "Feature",
  "properties": {
    "iso:country":"CH",
    "sg:address":"Arbonerstrasse 62",
    "sg:city":"Romanshorn",
    "sg:orig_category":"Herstellung von Drahtwaren Herstellung von Konstruktionsteilen, Fertigbauteilen U Ausbauelementen au",
    "sg:phone":"+41 71 461 19 20",
    "sg:postcode":"8590",
    "sg:province":"Thurgau",
    "wof:name":"Burgstaller-z\u00e4une-ag",
    "wof:placetype":"venue"
},
  "geometry": {"coordinates":[9.369477,47.557812],"type":"Point"}
}