{
  "type": "Feature",
  "properties": {
    "iso:country":"CH",
    "sg:address":"Gerbegraben 8 3110 M\u00fcnsingen. Postfach 1388",
    "sg:city":"M\u00fcnsingen",
    "sg:orig_category":"Herstellung von Metallkonstruktionen",
    "sg:phone":"+41 31 721 08 18",
    "sg:postcode":"3110",
    "sg:province":"Bern",
    "wof:name":"Burkhalter Beltec Faltw\u00e4nde Winterg\u00e4rten",
    "wof:placetype":"venue"
},
  "geometry": {"coordinates":[7.5597629547,46.877658844],"type":"Point"}
}