{
  "type": "Feature",
  "properties": {
    "iso:country":"CH",
    "sg:address":"Bahnhofstrasse 23",
    "sg:city":"Brunnen",
    "sg:orig_category":"Detailhandel mit Spielwaren",
    "sg:phone":"+41 32 653 00 87",
    "sg:postcode":"6440",
    "sg:province":"Schwyz",
    "wof:name":"Martin Kuster Modellbahnen",
    "wof:placetype":"venue"
},
  "geometry": {"coordinates":[7.3634819984,47.1797294617],"type":"Point"}
}