{
  "type": "Feature",
  "properties": {
    "addr:full":"Grand-rue 22 Nyon Vaud 1260",
    "addr:housenumber":"22",
    "addr:postcode":"1260",
    "addr:street":"Grand-Rue",
    "iso:country":"CH",
    "sg:address":"Grand-rue 22",
    "sg:city":"Nyon",
    "sg:orig_category":"Detailhandel mit B\u00fcchern, Zeitungen, Schreib U Papeteriewaren Detailhandel mit Tabakwaren",
    "sg:phone":"+41 22 361 17 08",
    "sg:postcode":"1260",
    "sg:province":"Vaud",
    "wof:name":"Chez Meta, Deleury Meta",
    "wof:placetype":"venue"
},
  "geometry": {"coordinates":[6.238858,46.38187],"type":"Point"}
}