{
  "type": "Feature",
  "properties": {
    "iso:country":"CH",
    "sg:address":"Aar\u00fctistrasse 4",
    "sg:city":"Glattfelden",
    "sg:orig_category":"Instandhaltung U Reparatur von Automobilen Tankstellen",
    "sg:phone":"+41 18673866",
    "sg:postcode":"8192",
    "sg:province":"Z\u00fcrich",
    "wof:name":"Uhlig Ag Touringgarage & Tankstelle",
    "wof:placetype":"venue"
},
  "geometry": {"coordinates":[8.4923505783,47.5601234436],"type":"Point"}
}