{
  "type": "Feature",
  "properties": {
    "iso:country":"CH",
    "sg:address":"Thalerstrasse 19",
    "sg:city":"Rheineck",
    "sg:orig_category":"RESTAURANTS: TEA-ROOMS",
    "sg:phone":"+41 71 888 01 98",
    "sg:postcode":"9424",
    "sg:province":"St. Gallen",
    "wof:name":"Restaurant National, Elsa Sent\u00fcrk",
    "wof:placetype":"venue"
},
  "geometry": {"coordinates":[9.5857686996,47.46692276],"type":"Point"}
}