{
  "type": "Feature",
  "properties": {
    "iso:country":"CH",
    "sg:address":"Grand-rue 43",
    "sg:city":"Courtelary",
    "sg:orig_category":"Polizei",
    "sg:phone":"+41 32 861 14 23",
    "sg:postcode":"2608",
    "sg:province":"Bern",
    "wof:name":"Police Cantonale",
    "wof:placetype":"venue"
},
  "geometry": {"coordinates":[6.6116337776,46.9101142883],"type":"Point"}
}