{
  "type": "Feature",
  "properties": {
    "iso:country":"CH",
    "sg:address":"Klybeckstrasse 15 4057 Basel. Postfach",
    "sg:city":"Basel",
    "sg:orig_category":"Pensionskassen",
    "sg:phone":"+41 61 267 24 00",
    "sg:postcode":"4051",
    "sg:province":"Basel-Stadt",
    "wof:name":"Louise Aubry-kappeler-stiftung Finanz. Hilfe An Einwohner D. Kt. Basel-stadt",
    "wof:placetype":"venue"
},
  "geometry": {"coordinates":[7.591023922,47.5655021667],"type":"Point"}
}