{
  "type": "Feature",
  "properties": {
    "iso:country":"CH",
    "sg:address":"Rue Des Casernes 5",
    "sg:city":"Yverdon-les-bains",
    "sg:orig_category":"Zahnarztpraxen",
    "sg:phone":"+41 24 425 89 49",
    "sg:postcode":"1400",
    "sg:province":"Vaud",
    "wof:name":"Dr M\u00e9d. Dent. Jo\u00ebl Mevs M\u00e9decin-dentiste",
    "wof:placetype":"venue"
},
  "geometry": {"coordinates":[6.6376538277,46.7794189453],"type":"Point"}
}