{
  "type": "Feature",
  "properties": {
    "iso:country":"CH",
    "sg:address":"Bahnhofstrasse 40",
    "sg:city":"Rebstein",
    "sg:orig_category":"Arztpraxen",
    "sg:phone":"+41 71 775 80 50",
    "sg:postcode":"9445",
    "sg:province":"St. Gallen",
    "wof:name":"Dres Med. M. & C. Knierim Aerzte F\u00fcr Allgemeine Medizin",
    "wof:placetype":"venue"
},
  "geometry": {"coordinates":[9.583964,47.396763],"type":"Point"}
}