{
  "type": "Feature",
  "properties": {
    "iso:country":"CH",
    "sg:address":"Thur",
    "sg:city":"Wildhaus",
    "sg:orig_category":"Abwasserreinigung",
    "sg:phone":"+41 71 999 34 79",
    "sg:postcode":"9658",
    "sg:province":"St. Gallen",
    "wof:name":"Abwasserkorporation Ara",
    "wof:placetype":"venue"
},
  "geometry": {"coordinates":[9.350921,47.202866],"type":"Point"}
}