{
  "type": "Feature",
  "properties": {
    "iso:country":"CH",
    "sg:address":"Bahnhofstrasse 9",
    "sg:city":"Wattwil",
    "sg:orig_category":"Kosmetikinstitute",
    "sg:phone":"+41 71 988 13 12",
    "sg:postcode":"9630",
    "sg:province":"St. Gallen",
    "wof:name":"Silvia Abderhalden Kosmetikinstitut",
    "wof:placetype":"venue"
},
  "geometry": {"coordinates":[9.0865716934,47.3005867004],"type":"Point"}
}