{
  "type": "Feature",
  "properties": {
    "iso:country":"CH",
    "sg:address":"6514",
    "sg:city":"Sementina",
    "sg:orig_category":"Sanit\u00e4r, Heizungs U L\u00fcftungsinstallation Sanit\u00e4rinstallation",
    "sg:phone":"+41 79 331 40 00",
    "sg:postcode":"6514",
    "sg:province":"Ticino",
    "wof:name":"Pasotti, Fratelli",
    "wof:placetype":"venue"
},
  "geometry": {"coordinates":[8.9902734756,46.1847915649],"type":"Point"}
}