{
  "type": "Feature",
  "properties": {
    "iso:country":"CH",
    "sg:address":"D\u00e9lices Chemin Des 9 1006 Lausanne. Postfach",
    "sg:city":"Lausanne",
    "sg:orig_category":"Pensionskassen",
    "sg:postcode":"1006",
    "sg:province":"Vaud",
    "wof:name":"Fondation En Faveur Du Personnel Des Entreprises Du Groupe Pernod-ricard En Suisse",
    "wof:placetype":"venue"
},
  "geometry": {"coordinates":[6.1323800087,46.1763534546],"type":"Point"}
}