{
  "type": "Feature",
  "properties": {
    "iso:country":"CH",
    "sg:address":"Rue Baptiste-savoye 69",
    "sg:city":"St-imier",
    "sg:orig_category":"Detailhandel mit Getr\u00e4nken Grosshandel mit Wein U Spirituosen",
    "sg:phone":"+41 32 940 10 60",
    "sg:postcode":"2610",
    "sg:province":"Bern",
    "wof:name":"Wate Ag",
    "wof:placetype":"venue"
},
  "geometry": {"coordinates":[6.9953951836,47.1519737244],"type":"Point"}
}