{
  "type": "Feature",
  "properties": {
    "iso:country":"CH",
    "sg:address":"Dorfstr. 5 Post 9125 Brunnadern",
    "sg:city":"Mogelsberg",
    "sg:orig_category":"RESTAURANTS: TEA-ROOMS",
    "sg:postcode":"9122",
    "sg:province":"St. Gallen",
    "wof:name":"Luder-nef Ernst, Rest. Bahnhof",
    "wof:placetype":"venue"
},
  "geometry": {"coordinates":[9.1347303391,47.3629608154],"type":"Point"}
}