{
  "type": "Feature",
  "properties": {
    "iso:country":"CH",
    "sg:address":"Sumpfstrasse 15 6312 Steinhausen. Postfach",
    "sg:city":"Steinhausen",
    "sg:orig_category":"Sonstiger Grosshandel",
    "sg:postcode":"6312",
    "sg:province":"Zug",
    "wof:name":"Culinary World Ag Warenhandel, Bes. Weitergabe Von Lizenzierungen Von Immaterialg\u00fcterrechten",
    "wof:placetype":"venue"
},
  "geometry": {"coordinates":[8.4888143539,47.1867141724],"type":"Point"}
}