{
  "type": "Feature",
  "properties": {
    "iso:country":"CH",
    "sg:address":"Poststrasse 7",
    "sg:city":"Wigoltingen",
    "sg:orig_category":"Sportvereine Sch\u00fctzen",
    "sg:phone":"+41 52 763 36 37",
    "sg:postcode":"8556",
    "sg:province":"Thurgau",
    "wof:name":"Sch\u00fctzenverein",
    "wof:placetype":"venue"
},
  "geometry": {"coordinates":[9.0309143066,47.5980873108],"type":"Point"}
}