{
  "type": "Feature",
  "properties": {
    "iso:country":"CH",
    "sg:address":"Horbacherstrasse 5",
    "sg:city":"Hauptwil",
    "sg:orig_category":"Selbst\u00e4ndige bildende K\u00fcnstler",
    "sg:phone":"+41 71 422 36 60",
    "sg:postcode":"9213",
    "sg:province":"Thurgau",
    "wof:name":"Louise Baumgartner Kunstatelier",
    "wof:placetype":"venue"
},
  "geometry": {"coordinates":[9.2584247589,47.4844436646],"type":"Point"}
}