{
  "type": "Feature",
  "properties": {
    "iso:country":"CH",
    "sg:address":"Hauptstrasse 65 9400 Rorschach. Postfach 401",
    "sg:city":"Rorschach",
    "sg:orig_category":"Rechtsberatung Wirtschaftspr\u00fcfung, Steuerberatung U Treuhand",
    "sg:phone":"+41 32 724 35 07",
    "sg:postcode":"9401",
    "sg:province":"St. Gallen",
    "wof:name":"Dynafisc Sa",
    "wof:placetype":"venue"
},
  "geometry": {"coordinates":[6.9306921959,46.991355896],"type":"Point"}
}