{
  "type": "Feature",
  "properties": {
    "iso:country":"CH",
    "sg:address":"Hauptstrasse 14",
    "sg:city":"Flaach",
    "sg:orig_category":"Sonstiger spezialisierter Hoch U Tiefbau",
    "sg:phone":"+41 52 318 19 91",
    "sg:postcode":"8416",
    "sg:province":"Z\u00fcrich",
    "wof:name":"Diacron, Alaj E.",
    "wof:placetype":"venue"
},
  "geometry": {"coordinates":[8.6072902679,47.5751304626],"type":"Point"}
}