{
  "type": "Feature",
  "properties": {
    "iso:country":"CH",
    "sg:address":"Hubstrasse 60",
    "sg:city":"Wil",
    "sg:classifiers":[
        {
            "category":"Professional",
            "subcategory":"Printing & Photocopies",
            "type":"Services"
        }
    ],
    "sg:phone":"+41 71 913 47 11",
    "sg:postcode":"9500",
    "sg:province":"St. Gallen",
    "sg:tags":[
        "job"
    ],
    "wof:name":"Rolf-peter Zehnder Ag",
    "wof:placetype":"venue"
},
  "geometry": {"coordinates":[9.0354967117,47.4612007141],"type":"Point"}
}