{
  "type": "Feature",
  "properties": {
    "addr:full":"Rue Du Gothard 18 B Ch\u00eane-bourg Gen\u00e8ve 1225",
    "addr:housenumber":"18 b",
    "addr:postcode":"1225",
    "addr:street":"Rue Du Gothard",
    "iso:country":"CH",
    "sg:address":"Rue Du Gothard 18 B",
    "sg:city":"Ch\u00eane-bourg",
    "sg:orig_category":"Detailhandel mit Bekleidung",
    "sg:phone":"+41 22 349 75 60",
    "sg:postcode":"1225",
    "sg:province":"Gen\u00e8ve",
    "wof:name":"L'amour En Soie Sarl",
    "wof:placetype":"venue"
},
  "geometry": {"coordinates":[6.192096,46.194736],"type":"Point"}
}