{
  "type": "Feature",
  "properties": {
    "addr:full":"Sihlquai 55 Z\u00fcrich Z\u00fcrich 8005",
    "addr:housenumber":"55",
    "addr:postcode":"8005",
    "addr:street":"Sihlquai",
    "iso:country":"CH",
    "sg:address":"Sihlquai 55",
    "sg:city":"Z\u00fcrich",
    "sg:orig_category":"Bauschreinerei",
    "sg:phone":"+41 12720064",
    "sg:postcode":"8005",
    "sg:province":"Z\u00fcrich",
    "wof:name":"Claude Schmidt Schreinerei",
    "wof:placetype":"venue"
},
  "geometry": {"coordinates":[8.53776,47.381966],"type":"Point"}
}