{
  "type": "Feature",
  "properties": {
    "iso:country":"CH",
    "sg:address":"7403",
    "sg:city":"Rh\u00e4z\u00fcns",
    "sg:classifiers":[
        {
            "category":"Education",
            "subcategory":"Vocational School",
            "type":"Public Place"
        }
    ],
    "sg:phone":"+41 81 651 29 81",
    "sg:postcode":"7403",
    "sg:province":"Graubunden",
    "sg:tags":[
        "koch-",
        "haushaltschulen"
    ],
    "wof:name":"Haushaltungsschule",
    "wof:placetype":"venue"
},
  "geometry": {"coordinates":[9.3979654312,46.7985496521],"type":"Point"}
}