{
  "type": "Feature",
  "properties": {
    "iso:country":"CH",
    "sg:address":"Via Simen 14",
    "sg:city":"Lugano",
    "sg:orig_category":"RESTAURANTS: TEA-ROOMS",
    "sg:postcode":"6900",
    "sg:province":"Ticino",
    "wof:name":"Torri Lino E Daniela.",
    "wof:placetype":"venue"
},
  "geometry": {"coordinates":[8.9571809769,46.0132369995],"type":"Point"}
}