{
  "type": "Feature",
  "properties": {
    "iso:country":"CH",
    "sg:address":"Florhofgasse 6",
    "sg:city":"Z\u00fcrich",
    "sg:orig_category":"Interessenvertretungen",
    "sg:phone":"+41 33 952 15 15",
    "sg:postcode":"8001",
    "sg:province":"Z\u00fcrich",
    "wof:name":"Landschaftstheater Ballenberg",
    "wof:placetype":"venue"
},
  "geometry": {"coordinates":[8.0348644257,46.7542877197],"type":"Point"}
}