{
  "type": "Feature",
  "properties": {
    "iso:country":"CH",
    "sg:address":"Linckweg 9",
    "sg:city":"Zollikofen",
    "sg:orig_category":"Unclassifiable Establishments",
    "sg:postcode":"3052",
    "sg:province":"Bern",
    "wof:name":"Joachim Theis",
    "wof:placetype":"venue"
},
  "geometry": {"coordinates":[7.4534420967,46.993309021],"type":"Point"}
}