{
  "type": "Feature",
  "properties": {
    "iso:country":"CH",
    "sg:address":"Rue De L'ale 46 1000 Lausanne Case Postale",
    "sg:city":"Lausanne",
    "sg:orig_category":"Detailhandel mit Uhren U Schmuck Reparatur von Uhren U Schmuck",
    "sg:phone":"+41 21 312 44 01",
    "sg:postcode":"1003",
    "sg:province":"Vaud",
    "wof:name":"Probijoux Sa Achat Et Vente De Tous Articles De Joaillerie, Bijouterie, Horlogerie, Antiquit\u00e9s Et Divers.",
    "wof:placetype":"venue"
},
  "geometry": {"coordinates":[6.608353138,46.5362319946],"type":"Point"}
}