{
  "type": "Feature",
  "properties": {
    "iso:country":"CH",
    "sg:address":"Eichholzstrasse 2",
    "sg:city":"Waltenschwil",
    "sg:orig_category":"Softwareentwicklung U beratung",
    "sg:postcode":"5622",
    "sg:province":"Aargau",
    "wof:name":"Inter-dev, Ochman Andr\u00e9",
    "wof:placetype":"venue"
},
  "geometry": {"coordinates":[6.857986927,46.9656143188],"type":"Point"}
}