{
  "type": "Feature",
  "properties": {
    "iso:country":"CH",
    "sg:address":"Locherhof",
    "sg:city":"Engelburg",
    "sg:orig_category":"Politische Parteien CVP",
    "sg:phone":"+41 71 222 33 84",
    "sg:postcode":"9032",
    "sg:province":"St. Gallen",
    "wof:name":"Cvp Ortspartei Waldkirch",
    "wof:placetype":"venue"
},
  "geometry": {"coordinates":[9.3417654037,47.4435043335],"type":"Point"}
}