{
  "type": "Feature",
  "properties": {
    "addr:full":"Gerbistrasse 8 Uznach St. Gallen 8730",
    "addr:housenumber":"8",
    "addr:postcode":"8730",
    "addr:street":"Gerbistrasse",
    "iso:country":"CH",
    "sg:address":"Gerbistrasse 8",
    "sg:city":"Uznach",
    "sg:orig_category":"Bauschreinerei Verlegen von Fussboden",
    "sg:phone":"+41 55 280 12 68",
    "sg:postcode":"8730",
    "sg:province":"St. Gallen",
    "wof:name":"Pius Betschart Schreinerei Bodenbel\u00e4ge",
    "wof:placetype":"venue"
},
  "geometry": {"coordinates":[8.978122,47.226418],"type":"Point"}
}