{
  "type": "Feature",
  "properties": {
    "iso:country":"CH",
    "sg:address":"Asylstrasse 56",
    "sg:city":"Spiez",
    "sg:orig_category":"Reparatur von Uhren U Schmuck",
    "sg:phone":"+41 33 654 11 68",
    "sg:postcode":"3700",
    "sg:province":"Bern",
    "wof:name":"Hartwig & Rosmarie Trunz Uhrmacher Studio",
    "wof:placetype":"venue"
},
  "geometry": {"coordinates":[7.6699528694,46.6919250488],"type":"Point"}
}