{
  "type": "Feature",
  "properties": {
    "addr:full":"Alte Kantonsstrasse 11 6440 Brunnen. Postfach 121 Brunnen Schwyz 6440",
    "addr:housenumber":"11;121",
    "addr:postcode":"6440 brunnen.;6440",
    "addr:street":"Alte Kantonsstrasse;Postfach;Schwyz",
    "iso:country":"CH",
    "sg:address":"Alte Kantonsstrasse 11 6440 Brunnen. Postfach 121",
    "sg:city":"Brunnen",
    "sg:orig_category":"Bahnhofbuffets",
    "sg:phone":"+41 41 820 33 96",
    "sg:postcode":"6440",
    "sg:province":"Schwyz",
    "wof:name":"Bahnhofbuffet",
    "wof:placetype":"venue"
},
  "geometry": {"coordinates":[8.613959,47.000652],"type":"Point"}
}