{
  "type": "Feature",
  "properties": {
    "iso:country":"CH",
    "sg:address":"Zelgweg 24",
    "sg:city":"Baden",
    "sg:orig_category":"Sanit\u00e4r, Heizungs U L\u00fcftungsinstallation",
    "sg:postcode":"5400",
    "sg:province":"Aargau",
    "wof:name":"Kellerhals Rudolf, Heizungsbau",
    "wof:placetype":"venue"
},
  "geometry": {"coordinates":[8.2836065292,47.4558448792],"type":"Point"}
}