{
  "type": "Feature",
  "properties": {
    "iso:country":"CH",
    "sg:address":"Dorfstrasse 9-13",
    "sg:city":"Grossh\u00f6chstetten",
    "sg:orig_category":"Galvanische Betriebe Pensionskassen",
    "sg:phone":"+41 32 344 20 00",
    "sg:postcode":"3506",
    "sg:province":"Bern",
    "wof:name":"Fondation En Faveur Du Personnel De La Maison Aloxyd Sa",
    "wof:placetype":"venue"
},
  "geometry": {"coordinates":[7.6416988373,46.9057197571],"type":"Point"}
}