{
  "type": "Feature",
  "properties": {
    "iso:country":"CH",
    "sg:address":"Nydeggstalden 34 3011 Bern. Postfach",
    "sg:city":"Bern",
    "sg:orig_category":"Interessenvertretungen",
    "sg:postcode":"3005",
    "sg:province":"Bern",
    "wof:name":"Marianus-stiftung Anregung Und Entfaltung Wissenschaftlicher, K\u00fcnstlerischer Und Sozialer F\u00e4higkeiten Des Menschen Usw.",
    "wof:placetype":"venue"
},
  "geometry": {"coordinates":[7.4565258026,46.9488868713],"type":"Point"}
}