{
  "type": "Feature",
  "properties": {
    "iso:country":"CH",
    "sg:address":"Seestrasse 106",
    "sg:city":"St\u00e4fa",
    "sg:orig_category":"Herstellung von Mess U Kontrollinstrumenten U vorrichtungen",
    "sg:phone":"+41 17963950",
    "sg:postcode":"8712",
    "sg:province":"Z\u00fcrich",
    "wof:name":"Enumtec Gmbh",
    "wof:placetype":"venue"
},
  "geometry": {"coordinates":[8.7265901566,47.2377357483],"type":"Point"}
}