{
  "type": "Feature",
  "properties": {
    "iso:country":"CH",
    "sg:address":"8564 Wagerswil. Postfach",
    "sg:city":"Wagerswil",
    "sg:orig_category":"Detailhandel mit Waren verschiedener Art, Hauptrichtung Nahrungsmittel",
    "sg:phone":"+41 41 870 11 83",
    "sg:postcode":"8564",
    "sg:province":"Thurgau",
    "wof:name":"Alfred Simmen Fr\u00fcchte & Gem\u00fcse",
    "wof:placetype":"venue"
},
  "geometry": {"coordinates":[8.6416654587,46.8827934265],"type":"Point"}
}