{
  "type": "Feature",
  "properties": {
    "iso:country":"CH",
    "sg:address":"Conradin-zschokkestrasse 39",
    "sg:city":"D\u00f6ttingen",
    "sg:classifiers":[
        {
            "category":"Transit Center",
            "subcategory":"Freight",
            "type":"Transportation"
        }
    ],
    "sg:phone":"+41 56 245 11 72",
    "sg:postcode":"5312",
    "sg:province":"Aargau",
    "sg:tags":[
        "forwarding",
        "agency"
    ],
    "wof:name":"Torri Ag",
    "wof:placetype":"venue"
},
  "geometry": {"coordinates":[8.25688,47.569572],"type":"Point"}
}