{
  "type": "Feature",
  "properties": {
    "iso:country":"CH",
    "sg:address":"Grindelstrasse 50",
    "sg:city":"Bassersdorf",
    "sg:orig_category":"Detailhandel mit Radio U Fernsehger\u00e4ten Detailhandel mit elektrischen Haushalts-,Radio U Fernsehger\u00e4",
    "sg:phone":"+41 32 913 29 93",
    "sg:postcode":"8303",
    "sg:province":"Z\u00fcrich",
    "wof:name":"M\u00fcller-musique Sa",
    "wof:placetype":"venue"
},
  "geometry": {"coordinates":[6.8301749229,47.1029930115],"type":"Point"}
}