{
  "type": "Feature",
  "properties": {
    "iso:country":"CH",
    "sg:address":"Tavel Route De 17",
    "sg:city":"Fribourg",
    "sg:orig_category":"Unclassifiable Establishments",
    "sg:postcode":"1700",
    "sg:province":"Fribourg",
    "wof:name":"Plan\u00e8te V\u00e9nus Sa",
    "wof:placetype":"venue"
},
  "geometry": {"coordinates":[7.1536831856,46.8037452698],"type":"Point"}
}