{
  "type": "Feature",
  "properties": {
    "iso:country":"CH",
    "sg:address":"Birmensdorferstrasse 272",
    "sg:city":"Z\u00fcrich",
    "sg:orig_category":"Non-Classified Establishments",
    "sg:phone":"+41 14622128",
    "sg:postcode":"8055",
    "sg:province":"Z\u00fcrich",
    "wof:name":"Zitt J\u00fcrg, Nachfolger M. Lacher, Elektromotoren. Reparaturwerkst\u00e4tte Und Wicklerei F. Elektromotoren.",
    "wof:placetype":"venue"
},
  "geometry": {"coordinates":[8.5108823776,47.3701477051],"type":"Point"}
}