{
  "type": "Feature",
  "properties": {
    "iso:country":"CH",
    "sg:address":"Hauptstrasse 42",
    "sg:city":"Glarus",
    "sg:orig_category":"Interessenvertretungen",
    "sg:phone":"+41 55 640 83 76",
    "sg:postcode":"8750",
    "sg:province":"Glarus",
    "wof:name":"Honegger-stiftung",
    "wof:placetype":"venue"
},
  "geometry": {"coordinates":[9.0676250458,47.0407295227],"type":"Point"}
}