{
  "type": "Feature",
  "properties": {
    "iso:country":"CH",
    "sg:address":"Wiesenstrasse 10",
    "sg:city":"Basel",
    "sg:orig_category":"Herstellung von Konstruktionsteilen, Fertigbauteilen U Ausbauelementen aus Holz",
    "sg:phone":"+41 61 631 11 15",
    "sg:postcode":"4057",
    "sg:province":"Basel-Stadt",
    "wof:name":"Ed. Borer Ag",
    "wof:placetype":"venue"
},
  "geometry": {"coordinates":[7.5934619904,47.5773735046],"type":"Point"}
}