{
  "type": "Feature",
  "properties": {
    "iso:country":"CH",
    "sg:address":"Scalettastrasse 93a 7000 Chur. Postfach",
    "sg:city":"Chur",
    "sg:orig_category":"Kauf U Verkauf von Immobilien auf eigene Rechnung Vermietung U Verpachtung von eigenen Immobilien",
    "sg:phone":"+41 81 250 34 77",
    "sg:postcode":"7000",
    "sg:province":"Graubunden",
    "wof:name":"Terra Immobilien, Del Cubo Arroyo Immobilien-handel",
    "wof:placetype":"venue"
},
  "geometry": {"coordinates":[9.5214595795,46.8598518372],"type":"Point"}
}