{
  "type": "Feature",
  "properties": {
    "addr:full":"Avenue De La Gare 15-17 Sion Valais 1950",
    "addr:postcode":"15-17;1950",
    "addr:street":"Avenue De La Gare",
    "iso:country":"CH",
    "sg:address":"Avenue De La Gare 15-17",
    "sg:city":"Sion",
    "sg:orig_category":"Detailhandel mit Brot, Back U S\u00fcsswaren",
    "sg:phone":"+41 27 323 52 18",
    "sg:postcode":"1950",
    "sg:province":"Valais",
    "wof:name":"Michelle Parra Confiserie Au Bonbec",
    "wof:placetype":"venue"
},
  "geometry": {"coordinates":[7.35837,46.229504],"type":"Point"}
}