{
  "type": "Feature",
  "properties": {
    "iso:country":"CH",
    "sg:address":"1874",
    "sg:city":"Champ\u00e9ry",
    "sg:orig_category":"Herstellung von Konstruktionsteilen, Fertigbauteilen U Ausbauelementen aus Holz",
    "sg:phone":"+41 24 479 13 02",
    "sg:postcode":"1874",
    "sg:province":"Valais",
    "wof:name":"Sfumat Gino",
    "wof:placetype":"venue"
},
  "geometry": {"coordinates":[6.8706860542,46.1794052124],"type":"Point"}
}