{
  "type": "Feature",
  "properties": {
    "iso:country":"CH",
    "sg:address":"Franklinstrasse 41",
    "sg:city":"Z\u00fcrich",
    "sg:classifiers":[
        {
            "category":"Restaurant",
            "type":"Food & Drink"
        }
    ],
    "sg:phone":"+41 71 744 12 84",
    "sg:postcode":"8050",
    "sg:province":"Z\u00fcrich",
    "wof:name":"Restaurant Baumgarten",
    "wof:placetype":"venue"
},
  "geometry": {"coordinates":[9.6481027603,47.4458694458],"type":"Point"}
}