{
  "type": "Feature",
  "properties": {
    "addr:full":"Parc Dinu-lipatti 1 Ch\u00eane-bourg Gen\u00e8ve 1225",
    "addr:housenumber":"1",
    "addr:postcode":"1225",
    "addr:street":"Parc Dinu-Lipatti;Che\u0302Ne-Bourg",
    "iso:country":"CH",
    "sg:address":"Parc Dinu-lipatti 1",
    "sg:city":"Ch\u00eane-bourg",
    "sg:orig_category":"Arztpraxen",
    "sg:phone":"+41 22 348 50 28",
    "sg:postcode":"1225",
    "sg:province":"Gen\u00e8ve",
    "wof:name":"Dr M\u00e9d. Yves Gaudin M\u00e9decin G\u00e9n\u00e9raliste Fmh",
    "wof:placetype":"venue"
},
  "geometry": {"coordinates":[6.193395,46.194962],"type":"Point"}
}