{
  "type": "Feature",
  "properties": {
    "iso:country":"CH",
    "sg:address":"Viale Cattaneo 6",
    "sg:city":"Lugano",
    "sg:classifiers":[
        {
            "category":"Education",
            "subcategory":"Library",
            "type":"Public Place"
        }
    ],
    "sg:phone":"+41 91 911 53 50",
    "sg:postcode":"6900",
    "sg:province":"Ticino",
    "sg:tags":[
        "u",
        "bibliotheken",
        "archive"
    ],
    "wof:name":"Biblioteca Cantonale",
    "wof:placetype":"venue"
},
  "geometry": {"coordinates":[8.9596967697,46.004032135],"type":"Point"}
}