{
  "type": "Feature",
  "properties": {
    "iso:country":"CH",
    "sg:address":"7159",
    "sg:city":"Andiast",
    "sg:orig_category":"Primarschulen",
    "sg:postcode":"7159",
    "sg:province":"Graubunden",
    "wof:name":"Primarschule",
    "wof:placetype":"venue"
},
  "geometry": {"coordinates":[9.1143198013,46.7845954895],"type":"Point"}
}