{
  "type": "Feature",
  "properties": {
    "iso:country":"CH",
    "sg:address":"Rebhaldenstrasse 10",
    "sg:city":"Seltisberg",
    "sg:orig_category":"Architekturb\u00fcros",
    "sg:phone":"+41 61 911 96 22",
    "sg:postcode":"4411",
    "sg:province":"Basel-Landschaft",
    "wof:name":"Georg Spinnler Architekturb\u00fcro",
    "wof:placetype":"venue"
},
  "geometry": {"coordinates":[7.727182,47.46706],"type":"Point"}
}