{
  "type": "Feature",
  "properties": {
    "iso:country":"CH",
    "sg:address":"Via Giuseppe Motta 4",
    "sg:city":"Lugano",
    "sg:orig_category":"Betrieb von Taxis",
    "sg:postcode":"6900",
    "sg:province":"Ticino",
    "wof:name":"Longoni Giuseppe",
    "wof:placetype":"venue"
},
  "geometry": {"coordinates":[8.948888,46.007519],"type":"Point"}
}