{
  "type": "Feature",
  "properties": {
    "iso:country":"CH",
    "sg:address":"Rue De L'ile Falcon 5",
    "sg:city":"Sierre",
    "sg:orig_category":"Grosshandel mit Milch, Milcherzeugnissen, Eiern, Speise\u00f6len U Nahrungsfetten Sonstiger Fachdetailhan",
    "sg:phone":"+41 22 301 01 62",
    "sg:postcode":"3960",
    "sg:province":"Valais",
    "wof:name":"Vivadis Sa",
    "wof:placetype":"venue"
},
  "geometry": {"coordinates":[6.1056361198,46.1680374146],"type":"Point"}
}