{
  "type": "Feature",
  "properties": {
    "iso:country":"CH",
    "sg:address":"Mittlere Gasse 6",
    "sg:city":"Romanshorn",
    "sg:orig_category":"Malerei",
    "sg:phone":"+41 71 463 10 61",
    "sg:postcode":"8590",
    "sg:province":"Thurgau",
    "wof:name":"Urs Baerel Malergesch\u00e4ft",
    "wof:placetype":"venue"
},
  "geometry": {"coordinates":[9.3779153824,47.564704895],"type":"Point"}
}