{
  "type": "Feature",
  "properties": {
    "iso:country":"CH",
    "sg:address":"Wassersch\u00f6pfi 71",
    "sg:city":"Z\u00fcrich",
    "sg:orig_category":"RESTAURANTS: TEA-ROOMS",
    "sg:postcode":"8055",
    "sg:province":"Z\u00fcrich",
    "wof:name":"Rest. Hirschen Burg Seewen, Auf Der Maur & Zgraggen",
    "wof:placetype":"venue"
},
  "geometry": {"coordinates":[8.6323652267,47.026550293],"type":"Point"}
}