{
  "type": "Feature",
  "properties": {
    "iso:country":"CH",
    "sg:address":"H\u00f6heweg 49",
    "sg:city":"Interlaken",
    "sg:orig_category":"Detailhandel mit Bekleidung Detailhandel mit Schuhen U Lederwaren",
    "sg:postcode":"3800",
    "sg:province":"Bern",
    "wof:name":"Boutique Walter",
    "wof:placetype":"venue"
},
  "geometry": {"coordinates":[-75.973755,40.4305],"type":"Point"}
}