{
  "type": "Feature",
  "properties": {
    "iso:country":"CH",
    "sg:address":"Sonnenbergstrasse 32",
    "sg:city":"Adliswil",
    "sg:orig_category":"Handelsvermittlung von Textilien, Bekleidung, Schuhen U Lederwaren",
    "sg:postcode":"8134",
    "sg:province":"Z\u00fcrich",
    "wof:name":"P & P, Pastega-palmquist Christina",
    "wof:placetype":"venue"
},
  "geometry": {"coordinates":[8.5199213028,47.3104057312],"type":"Point"}
}