{
  "type": "Feature",
  "properties": {
    "iso:country":"CH",
    "sg:address":"Reuss-strasse 8",
    "sg:city":"Gisikon",
    "sg:orig_category":"Fachdetailhandel in Verkaufsr\u00e4umen",
    "sg:postcode":"6038",
    "sg:province":"Luzern",
    "wof:name":"Mlo Sportnahrungsmittelvertrieb Roth",
    "wof:placetype":"venue"
},
  "geometry": {"coordinates":[8.3980264664,47.1261329651],"type":"Point"}
}