{
  "type": "Feature",
  "properties": {
    "iso:country":"CH",
    "sg:address":"Chemin De Rennier 25",
    "sg:city":"Pully",
    "sg:orig_category":"Tanzschulen, Tanzlehrer",
    "sg:phone":"+41 21 728 99 18",
    "sg:postcode":"1009",
    "sg:province":"Vaud",
    "wof:name":"Acad\u00e9mie De Danse Classique Madame Janine Wyss",
    "wof:placetype":"venue"
},
  "geometry": {"coordinates":[6.6625947952,46.5145454407],"type":"Point"}
}