{
  "type": "Feature",
  "properties": {
    "iso:country":"CH",
    "sg:address":"Speerstrasse 12",
    "sg:city":"Richterswil",
    "sg:orig_category":"Unclassifiable Establishments",
    "sg:postcode":"8805",
    "sg:province":"Z\u00fcrich",
    "wof:name":"Kellerhals & Partner Unternehmensberatung Ag",
    "wof:placetype":"venue"
},
  "geometry": {"coordinates":[8.6906681061,47.2068595886],"type":"Point"}
}