{
  "type": "Feature",
  "properties": {
    "iso:country":"CH",
    "sg:address":"B\u00fcckenweg 33",
    "sg:city":"Bettingen",
    "sg:orig_category":"Vermietung U Verpachtung von eigenen Immobilien",
    "sg:postcode":"4126",
    "sg:province":"Basel-Stadt",
    "wof:name":"Zum Linsberg Ag",
    "wof:placetype":"venue"
},
  "geometry": {"coordinates":[7.6609501839,47.5701293945],"type":"Point"}
}