{
  "type": "Feature",
  "properties": {
    "iso:country":"CH",
    "sg:address":"Voisins Rue Des 20 1205 Gen\u00e8ve. Postfach",
    "sg:city":"Gen\u00e8ve",
    "sg:orig_category":"Sonstige mit der Informatik verbundene T\u00e4tigkeiten",
    "sg:phone":"+41 22 329 36 44",
    "sg:postcode":"1201",
    "sg:province":"Gen\u00e8ve",
    "wof:name":"Betrust Concepts S\u00e0rl Informatique, Notamm. Conseil Et Assistance, D\u00e9veloppement Et Commercialisation De Produits Etc",
    "wof:placetype":"venue"
},
  "geometry": {"coordinates":[6.1442389488,46.1954727173],"type":"Point"}
}