{
  "type": "Feature",
  "properties": {
    "iso:country":"CH",
    "sg:address":"Gemeindestrasse 924",
    "sg:city":"Ueberstorf",
    "sg:orig_category":"Maler U Glasergewerbe Malerei",
    "sg:phone":"+41 31 741 10 18",
    "sg:postcode":"3182",
    "sg:province":"Fribourg",
    "wof:name":"Bertschy Oswald",
    "wof:placetype":"venue"
},
  "geometry": {"coordinates":[7.3105697632,46.8647842407],"type":"Point"}
}