{
  "type": "Feature",
  "properties": {
    "iso:country":"CH",
    "sg:address":"H\u00e4derlistrasse 6",
    "sg:city":"Rudolfstetten",
    "sg:orig_category":"Informatikdienste Unternehmensberatung",
    "sg:phone":"+41 56 631 27 55",
    "sg:postcode":"8964",
    "sg:province":"Aargau",
    "wof:name":"Rzi Zurbriggen Roland Informatik",
    "wof:placetype":"venue"
},
  "geometry": {"coordinates":[8.3816404343,47.3682899475],"type":"Point"}
}