{
  "type": "Feature",
  "properties": {
    "iso:country":"CH",
    "sg:address":"Staufbergweg 10",
    "sg:city":"Schafisheim",
    "sg:orig_category":"Sportvereine Unihockey",
    "sg:phone":"+41 62 891 50 14",
    "sg:postcode":"5503",
    "sg:province":"Aargau",
    "wof:name":"Red Wings Schafisheim",
    "wof:placetype":"venue"
},
  "geometry": {"coordinates":[8.1480951309,47.3772659302],"type":"Point"}
}