{
  "type": "Feature",
  "properties": {
    "iso:country":"CH",
    "sg:address":"Oberdorf 134 8455 R\u00fcdlingen. Postfach",
    "sg:city":"R\u00fcdlingen",
    "sg:orig_category":"Laboratoriums-Chemikalien",
    "sg:postcode":"8455",
    "sg:province":"Schaffhausen",
    "wof:name":"Inochem Systems Gmbh Biochemische Reagenzien; Herstellung, Entwicklung, Verkauf",
    "wof:placetype":"venue"
},
  "geometry": {"coordinates":[8.5687379837,47.5779037476],"type":"Point"}
}