{
  "type": "Feature",
  "properties": {
    "iso:country":"CH",
    "sg:address":"Av. A. Cailler",
    "sg:city":"Broc",
    "sg:orig_category":"Mechanik",
    "sg:postcode":"1636",
    "sg:province":"Fribourg",
    "wof:name":"Rossi Jean, Succursale De Broc",
    "wof:placetype":"venue"
},
  "geometry": {"coordinates":[7.0968379974,46.6060829163],"type":"Point"}
}