{
  "type": "Feature",
  "properties": {
    "iso:country":"CH",
    "sg:address":"Rue Des Grives 12 1762 Givisiez. Postfach",
    "sg:city":"Givisiez",
    "sg:orig_category":"Politische Parteien FDP",
    "sg:phone":"+41 26 466 60 07",
    "sg:postcode":"1762",
    "sg:province":"Fribourg",
    "wof:name":"Parti Radical-d\u00e9mocratique Fribourgeois",
    "wof:placetype":"venue"
},
  "geometry": {"coordinates":[7.132475853,46.8099784851],"type":"Point"}
}