{
  "type": "Feature",
  "properties": {
    "iso:country":"CH",
    "sg:address":"Hegenheimermattweg 21 4123 Allschwil. Postfach",
    "sg:city":"Allschwil",
    "sg:orig_category":"Softwareentwicklung U beratung",
    "sg:phone":"+41 61 903 12 20",
    "sg:postcode":"4123",
    "sg:province":"Basel-Landschaft",
    "wof:name":"Werren Informatik",
    "wof:placetype":"venue"
},
  "geometry": {"coordinates":[7.5389251709,47.5530128479],"type":"Point"}
}