{
  "type": "Feature",
  "properties": {
    "addr:full":"Asylstrasse 16 Aarau Aargau 5000",
    "addr:housenumber":"16",
    "addr:postcode":"5000",
    "addr:street":"Asylstrasse",
    "iso:country":"CH",
    "sg:address":"Asylstrasse 16",
    "sg:city":"Aarau",
    "sg:orig_category":"Detailhandel mit Bekleidung",
    "sg:phone":"+41 62 822 24 77",
    "sg:postcode":"5000",
    "sg:province":"Aargau",
    "wof:name":"Lucia Vogel Hutatelier Ueberhaupt",
    "wof:placetype":"venue"
},
  "geometry": {"coordinates":[8.041875,47.392048],"type":"Point"}
}