{
  "type": "Feature",
  "properties": {
    "iso:country":"CH",
    "sg:address":"Viale Castagnola 25",
    "sg:city":"Lugano",
    "sg:orig_category":"Herstellung von Pumpen U Kompressoren Herstellung von Werkzeugen",
    "sg:postcode":"6900",
    "sg:province":"Ticino",
    "wof:name":"O-mega Packaging Sa",
    "wof:placetype":"venue"
},
  "geometry": {"coordinates":[8.9673690796,46.0058517456],"type":"Point"}
}