{
  "type": "Feature",
  "properties": {
    "iso:country":"CH",
    "sg:address":"Zimmelstrasse 85 6314 Unter\u00e4geri. Postfach",
    "sg:city":"Zug",
    "sg:orig_category":"Optische Ger\u00e4te Grosshandel Sonstiger Grosshandel",
    "sg:phone":"+41 41 761 44 54",
    "sg:postcode":"6300",
    "sg:province":"Zug",
    "wof:name":"Eye Trading + Consulting Ag R\u00f6hren, Bes. Stahlr\u00f6hren, Leitungen. Usw; Handel, Vertrieb",
    "wof:placetype":"venue"
},
  "geometry": {"coordinates":[8.5712118149,47.1410331726],"type":"Point"}
}