{
  "type": "Feature",
  "properties": {
    "iso:country":"CH",
    "sg:address":"Via Balestra 29",
    "sg:city":"Lugano",
    "sg:orig_category":"Mechanische Werkst\u00e4tten",
    "sg:phone":"+41 91 923 98 72",
    "sg:postcode":"6900",
    "sg:province":"Ticino",
    "wof:name":"Luciano Galfetti Affilatura Lame",
    "wof:placetype":"venue"
},
  "geometry": {"coordinates":[8.9585199356,46.0080032349],"type":"Point"}
}