{
  "type": "Feature",
  "properties": {
    "iso:country":"CH",
    "sg:address":"Margarethenstrasse 63",
    "sg:city":"Binningen",
    "sg:orig_category":"Unternehmensberatung",
    "sg:phone":"+41 61 421 48 38",
    "sg:postcode":"4102",
    "sg:province":"Basel-Landschaft",
    "wof:name":"Wamco Consult W.j. Hrecska",
    "wof:placetype":"venue"
},
  "geometry": {"coordinates":[7.5767989159,47.5357170105],"type":"Point"}
}