{
  "type": "Feature",
  "properties": {
    "iso:country":"CH",
    "sg:address":"Aeschenvorstadt 67",
    "sg:city":"Basel",
    "sg:orig_category":"Vermietung U Verpachtung von eigenen Immobilien",
    "sg:postcode":"4051",
    "sg:province":"Basel-Stadt",
    "wof:name":"Burca Ag",
    "wof:placetype":"venue"
},
  "geometry": {"coordinates":[7.5942587852,47.5520133972],"type":"Point"}
}