{
  "type": "Feature",
  "properties": {
    "iso:country":"CH",
    "sg:address":"Spitalgasse 38",
    "sg:city":"Bern",
    "sg:orig_category":"Detailhandel mit Brillen U anderen Sehhilfen Detailhandel mit medizinischen U orthop\u00e4dischen Artikel",
    "sg:phone":"+41 31 312 43 33",
    "sg:postcode":"3011",
    "sg:province":"Bern",
    "wof:name":"H\u00f6rberatung Haldemann",
    "wof:placetype":"venue"
},
  "geometry": {"coordinates":[7.441452,46.947933],"type":"Point"}
}