{
  "type": "Feature",
  "properties": {
    "iso:country":"CH",
    "sg:address":"Chemin De Sallin 5",
    "sg:city":"Belmont-lausanne",
    "sg:orig_category":"Grosshandel mit Radio U Fernsehger\u00e4ten Herstellung von Radio U Fernsehger\u00e4ten sowie phono U videotec",
    "sg:phone":"+41 21 728 38 36",
    "sg:postcode":"1092",
    "sg:province":"Vaud",
    "wof:name":"Audioteam Sa",
    "wof:placetype":"venue"
},
  "geometry": {"coordinates":[6.6751689911,46.5196838379],"type":"Point"}
}