{
  "type": "Feature",
  "properties": {
    "iso:country":"CH",
    "sg:address":"Ahornstrasse 2",
    "sg:city":"Sch\u00f6nengrund",
    "sg:orig_category":"Detailhandel mit Damenbekleidung Detailhandel mit S\u00e4uglings U Kinderbekleidung",
    "sg:phone":"+41 79 234 19 25",
    "sg:postcode":"9105",
    "sg:province":"Appenzell Ausserrhoden",
    "wof:name":"Maggies Braut-& Kinder-shop",
    "wof:placetype":"venue"
},
  "geometry": {"coordinates":[9.227145195,47.3293418884],"type":"Point"}
}