{
  "type": "Feature",
  "properties": {
    "iso:country":"CH",
    "sg:address":"Alex Rue Pierre 11",
    "sg:city":"Bulle",
    "sg:orig_category":"Non-Classified Establishments",
    "sg:phone":"+41 26 913 98 52",
    "sg:postcode":"1630",
    "sg:province":"Fribourg",
    "wof:name":"Animations Plus S\u00e0rl",
    "wof:placetype":"venue"
},
  "geometry": {"coordinates":[7.0602669716,46.6233291626],"type":"Point"}
}