{
  "type": "Feature",
  "properties": {
    "iso:country":"CH",
    "sg:address":"Fischmattstrasse 20",
    "sg:city":"Buochs",
    "sg:orig_category":"Stukkateurgewerbe, Gipserei U Verputzerei",
    "sg:postcode":"6374",
    "sg:province":"Nidwalden",
    "wof:name":"W\u00e4lti E. Ag, Gipsergesch\u00e4ft",
    "wof:placetype":"venue"
},
  "geometry": {"coordinates":[8.4244365692,46.9758262634],"type":"Point"}
}