{
  "type": "Feature",
  "properties": {
    "addr:full":"Via Dufour 4 6900 Lugano. Postfach Caselle Postale 2169 Lugano Ticino 6901",
    "addr:housenumber":"4",
    "addr:postcode":"6900;postale 2169;6901",
    "addr:street":"Via Dufour",
    "iso:country":"CH",
    "sg:address":"Via Dufour 4 6900 Lugano. Postfach Caselle Postale 2169",
    "sg:city":"Lugano",
    "sg:orig_category":"Advokaturb\u00fcros Notariate",
    "sg:phone":"+41 91 911 87 10",
    "sg:postcode":"6901",
    "sg:province":"Ticino",
    "wof:name":"Nello Bernasconi Studio Legale & Notarile",
    "wof:placetype":"venue"
},
  "geometry": {"coordinates":[8.951969,46.008785],"type":"Point"}
}