{
  "type": "Feature",
  "properties": {
    "iso:country":"CH",
    "sg:address":"Rehalpstrasse 105",
    "sg:city":"Z\u00fcrich",
    "sg:orig_category":"Unclassifiable Establishments",
    "sg:postcode":"8008",
    "sg:province":"Z\u00fcrich",
    "wof:name":"Oboenatelier Christian Voss",
    "wof:placetype":"venue"
},
  "geometry": {"coordinates":[8.5833482742,47.3516464233],"type":"Point"}
}