{
  "type": "Feature",
  "properties": {
    "iso:country":"CH",
    "sg:address":"Butzenstrasse 20",
    "sg:city":"Wallisellen",
    "sg:orig_category":"Rechtsberatung",
    "sg:phone":"+41 1304823",
    "sg:postcode":"8304",
    "sg:province":"Z\u00fcrich",
    "wof:name":"Seko-patent Gmbh",
    "wof:placetype":"venue"
},
  "geometry": {"coordinates":[8.6055831909,47.4129180908],"type":"Point"}
}