{
  "type": "Feature",
  "properties": {
    "iso:country":"CH",
    "sg:address":"Via Besso 37 6900 Lugano. Postfach Caselle Postale 33",
    "sg:city":"Lugano",
    "sg:orig_category":"Advokaturb\u00fcros",
    "sg:phone":"+41 91 967 11 34",
    "sg:postcode":"6900",
    "sg:province":"Ticino",
    "wof:name":"Claudio Cereghetti Studio Legale",
    "wof:placetype":"venue"
},
  "geometry": {"coordinates":[8.939768,46.008945],"type":"Point"}
}