{
  "type": "Feature",
  "properties": {
    "iso:country":"CH",
    "sg:address":"Rietbergstrasse 37 9403 Goldach. Postfach",
    "sg:city":"Goldach",
    "sg:orig_category":"Herstellung von sonstigen Maschinen f\u00fcr bestimmte Verwendung Mechanische Werkst\u00e4tten",
    "sg:phone":"+41 79 600 31 78",
    "sg:postcode":"9403",
    "sg:province":"St. Gallen",
    "wof:name":"Ik-office-service Bogdan Ilic",
    "wof:placetype":"venue"
},
  "geometry": {"coordinates":[9.4733753204,47.4818534851],"type":"Point"}
}