{
  "type": "Feature",
  "properties": {
    "iso:country":"CH",
    "sg:address":"H\u00e4rdlistrasse 44",
    "sg:city":"Eichberg",
    "sg:orig_category":"Bauschreinerei Zimmerei, Ingenieurholzbau",
    "sg:phone":"+41 71 755 17 05",
    "sg:postcode":"9453",
    "sg:province":"St. Gallen",
    "wof:name":"Paul D\u00fcrr Zimmerei & Schreinerei",
    "wof:placetype":"venue"
},
  "geometry": {"coordinates":[9.528624,47.343822],"type":"Point"}
}