{
  "type": "Feature",
  "properties": {
    "iso:country":"CH",
    "sg:address":"Eichmatt 1",
    "sg:city":"Rotkreuz",
    "sg:orig_category":"Hardwareberatung Informatikdienste",
    "sg:phone":"+41 41 792 06 06",
    "sg:postcode":"6343",
    "sg:province":"Zug",
    "wof:name":"Hansrudolf Irniger Computerinstallationen",
    "wof:placetype":"venue"
},
  "geometry": {"coordinates":[8.4248466492,47.1352729797],"type":"Point"}
}