{
  "type": "Feature",
  "properties": {
    "addr:full":"Ergisch Valais 3947",
    "addr:postcode":"ergisch;3947",
    "iso:country":"CH",
    "sg:city":"Ergisch",
    "sg:classifiers":[
        {
            "category":"Banks & Credit Unions",
            "subcategory":"Bank",
            "type":"Services"
        }
    ],
    "sg:phone":"+41 27 932 34 24",
    "sg:postcode":"3947",
    "sg:province":"Valais",
    "wof:name":"Raiffeisenbank",
    "wof:placetype":"venue"
},
  "geometry": {"coordinates":[7.713582,46.293324],"type":"Point"}
}