{
  "type": "Feature",
  "properties": {
    "iso:country":"CH",
    "sg:address":"Bahnhofstrasse 22",
    "sg:city":"Zollikon",
    "sg:orig_category":"Hoch U Tiefbau",
    "sg:phone":"+41 13920575",
    "sg:postcode":"8702",
    "sg:province":"Z\u00fcrich",
    "wof:name":"Mario Ramunno Baugesch\u00e4ft",
    "wof:placetype":"venue"
},
  "geometry": {"coordinates":[8.5708322525,47.3367042542],"type":"Point"}
}