{
  "type": "Feature",
  "properties": {
    "iso:country":"CH",
    "sg:address":"Tempelstrasse 1",
    "sg:city":"Thun",
    "sg:classifiers":[
        {
            "category":"Military Area",
            "subcategory":"Air Force Base",
            "type":"Public Place"
        }
    ],
    "sg:phone":"+41 33 336 50 30",
    "sg:postcode":"3608",
    "sg:province":"Bern",
    "sg:tags":[
        "module",
        "automation"
    ],
    "wof:name":"Kurt Schneider Ag",
    "wof:placetype":"venue"
},
  "geometry": {"coordinates":[7.596906,46.744762],"type":"Point"}
}