{
  "type": "Feature",
  "properties": {
    "iso:country":"CH",
    "sg:address":"Egnacherstrasse 79 9320 Frasnacht. Postfach",
    "sg:city":"Frasnacht",
    "sg:orig_category":"Detailhandel mit M\u00f6beln U Haushaltsgegenst\u00e4nden",
    "sg:phone":"+41 19371051",
    "sg:postcode":"9320",
    "sg:province":"Thurgau",
    "wof:name":"M\u00f6bel Discount Z\u00fcrich Oberland Gmbh",
    "wof:placetype":"venue"
},
  "geometry": {"coordinates":[8.8203344345,47.3052139282],"type":"Point"}
}