{
  "type": "Feature",
  "properties": {
    "iso:country":"CH",
    "sg:address":"Via Prada 10",
    "sg:city":"Biasca",
    "sg:orig_category":"Grosshandel mit Textilien",
    "sg:phone":"+41 91 862 49 44",
    "sg:postcode":"6710",
    "sg:province":"Ticino",
    "wof:name":"Tesla Engineering Sa Prodotti Speciali",
    "wof:placetype":"venue"
},
  "geometry": {"coordinates":[8.9737539291,46.3476486206],"type":"Point"}
}