{
  "type": "Feature",
  "properties": {
    "iso:country":"CH",
    "sg:address":"Rennweg 29",
    "sg:city":"Z\u00fcrich",
    "sg:orig_category":"P\u00e9dicure",
    "sg:phone":"+41 12212455",
    "sg:postcode":"8001",
    "sg:province":"Z\u00fcrich",
    "wof:name":"Rita Burkart P\u00e9dicure",
    "wof:placetype":"venue"
},
  "geometry": {"coordinates":[8.5392284393,47.3731422424],"type":"Point"}
}