{
  "type": "Feature",
  "properties": {
    "iso:country":"CH",
    "sg:address":"Tannenweg 10 5703 Seon. Postfach",
    "sg:city":"Seon",
    "sg:orig_category":"Gasversorgung",
    "sg:phone":"+41 17502800",
    "sg:postcode":"5703",
    "sg:province":"Aargau",
    "wof:name":"Gasotec Ag",
    "wof:placetype":"venue"
},
  "geometry": {"coordinates":[8.4409542084,47.4158477783],"type":"Point"}
}