{
  "type": "Feature",
  "properties": {
    "iso:country":"CH",
    "sg:address":"5040",
    "sg:city":"Sch\u00f6ftland",
    "sg:orig_category":"Sportvereine Ballsport Handball",
    "sg:postcode":"5040",
    "sg:province":"Aargau",
    "wof:name":"Hv Suhrental",
    "wof:placetype":"venue"
},
  "geometry": {"coordinates":[8.0513896942,47.3075447083],"type":"Point"}
}