{
  "type": "Feature",
  "properties": {
    "addr:full":"Hauptstrasse 18 Rheineck St. Gallen 9424",
    "addr:housenumber":"18",
    "addr:postcode":"9424",
    "addr:street":"Hauptstrasse",
    "iso:country":"CH",
    "sg:address":"Hauptstrasse 18",
    "sg:city":"Rheineck",
    "sg:orig_category":"Detailhandel mit Bekleidung Herstellung von Lederbekleidung",
    "sg:phone":"+41 19303633",
    "sg:postcode":"9424",
    "sg:province":"St. Gallen",
    "wof:name":"Lemo Ledermode Wetzikon Ag",
    "wof:placetype":"venue"
},
  "geometry": {"coordinates":[8.802751,47.32972],"type":"Point"}
}