{
  "type": "Feature",
  "properties": {
    "iso:country":"CH",
    "sg:address":"Obere Z\u00e4une 8",
    "sg:city":"Z\u00fcrich",
    "sg:orig_category":"Kunsthandel Museen",
    "sg:phone":"+41 81 833 28 24",
    "sg:postcode":"8001",
    "sg:province":"Z\u00fcrich",
    "wof:name":"Galleria Curtins Ag",
    "wof:placetype":"venue"
},
  "geometry": {"coordinates":[9.8383436203,46.4989013672],"type":"Point"}
}