{
  "type": "Feature",
  "properties": {
    "iso:country":"CH",
    "sg:address":"Falkenweg 9 3012 Bern. Postfach",
    "sg:city":"Bern",
    "sg:orig_category":"Sonstiger Grosshandel",
    "sg:postcode":"3005",
    "sg:province":"Bern",
    "wof:name":"Schwendener R.",
    "wof:placetype":"venue"
},
  "geometry": {"coordinates":[9.4626941681,47.169380188],"type":"Point"}
}