{
  "type": "Feature",
  "properties": {
    "iso:country":"CH",
    "sg:address":"3534",
    "sg:city":"Signau",
    "sg:orig_category":"Grosshandel mit Getreide, Saatgut U Futtermitteln",
    "sg:postcode":"3534",
    "sg:province":"Bern",
    "wof:name":"Maitex-einkaufsgenossenschaft",
    "wof:placetype":"venue"
},
  "geometry": {"coordinates":[7.7206711769,46.916934967],"type":"Point"}
}