{
  "type": "Feature",
  "properties": {
    "iso:country":"CH",
    "sg:address":"Haldenweg 11",
    "sg:city":"Klingnau",
    "sg:orig_category":"Grosshandel mit sonstigen Maschinen U Ausr\u00fcstungen f\u00fcr Industrie, Handel U Schiffahrt Handelsvermitt",
    "sg:phone":"+41 56 245 20 61",
    "sg:postcode":"5313",
    "sg:province":"Aargau",
    "wof:name":"Walter Knecht Export & Handel",
    "wof:placetype":"venue"
},
  "geometry": {"coordinates":[8.2527923584,47.5824775696],"type":"Point"}
}