{
  "type": "Feature",
  "properties": {
    "iso:country":"CH",
    "sg:address":"Emmentalstrasse 23",
    "sg:city":"Konolfingen",
    "sg:classifiers":[
        {
            "category":"Insurance",
            "subcategory":"Insurance Agent",
            "type":"Services"
        }
    ],
    "sg:phone":"+41 807 903 130",
    "sg:postcode":"3510",
    "sg:province":"Bern",
    "sg:tags":[
        "versicherungsagenturen",
        "-broker"
    ],
    "wof:name":"Z\u00fcrich-versicherungen Agentur Jakob Moser",
    "wof:placetype":"venue"
},
  "geometry": {"coordinates":[7.624019146,46.8811187744],"type":"Point"}
}