{
  "type": "Feature",
  "properties": {
    "iso:country":"CH",
    "sg:address":"Oberdorfstr. 64",
    "sg:city":"D\u00fcbendorf",
    "sg:orig_category":"Electrical and Electronic Equipment Electricity Environment - machinery and equipment Mechanical Eng",
    "sg:phone":"+41 4118203191",
    "sg:postcode":"8600",
    "sg:province":"Z\u00fcrich",
    "wof:name":"Kockum Sonics Ag",
    "wof:placetype":"venue"
},
  "geometry": {"coordinates":[8.6225576401,47.3928527832],"type":"Point"}
}