{
  "type": "Feature",
  "properties": {
    "iso:country":"CH",
    "sg:address":"Rue De La Gare 1",
    "sg:city":"Aigle",
    "sg:orig_category":"Detailhandel mit Bekleidung",
    "sg:phone":"+41 24 466 50 39",
    "sg:postcode":"1860",
    "sg:province":"Vaud",
    "wof:name":"Propuls Diffusion Sciascia Monika",
    "wof:placetype":"venue"
},
  "geometry": {"coordinates":[6.964526,46.316059],"type":"Point"}
}