{
  "type": "Feature",
  "properties": {
    "iso:country":"CH",
    "sg:address":"Rue Du Diorama 4",
    "sg:city":"Gen\u00e8ve",
    "sg:orig_category":"Instandhaltung U Reparatur von Automobilen",
    "sg:postcode":"1204",
    "sg:province":"Gen\u00e8ve",
    "wof:name":"Garage Trachsel",
    "wof:placetype":"venue"
},
  "geometry": {"coordinates":[6.1385068893,46.2023658752],"type":"Point"}
}