{
  "type": "Feature",
  "properties": {
    "iso:country":"CH",
    "sg:address":"Oberzwislen",
    "sg:city":"Gais",
    "sg:orig_category":"Dachdeckerei Zimmerei, Dachdeckerei, Bauspenglerei U Abdichtung",
    "sg:phone":"+41 71 793 11 79",
    "sg:postcode":"9056",
    "sg:province":"Appenzell Ausserrhoden",
    "wof:name":"Fitzi Bedachungen & Bauspenglerei Ag",
    "wof:placetype":"venue"
},
  "geometry": {"coordinates":[9.458875,47.357342],"type":"Point"}
}