{
  "type": "Feature",
  "properties": {
    "addr:full":"Zielmatte 1 Stansstad Nidwalden 6362",
    "addr:housenumber":"1",
    "addr:postcode":"6362",
    "addr:street":"Zielmatte",
    "iso:country":"CH",
    "sg:address":"Zielmatte 1",
    "sg:city":"Stansstad",
    "sg:classifiers":[
        {
            "category":"Banks & Credit Unions",
            "subcategory":"Investment Brokerage",
            "type":"Services"
        }
    ],
    "sg:phone":"+41 41 618 80 90",
    "sg:postcode":"6362",
    "sg:province":"Nidwalden",
    "sg:tags":[
        "consulting"
    ],
    "wof:name":"Eura Treuhand Ag",
    "wof:placetype":"venue"
},
  "geometry": {"coordinates":[8.341613,46.977531],"type":"Point"}
}