{
  "type": "Feature",
  "properties": {
    "iso:country":"CH",
    "sg:address":"Schwendi 6314 Unter\u00e4geri. Postfach 154",
    "sg:city":"Unter\u00e4geri",
    "sg:orig_category":"Berufliche Weiterbildung, Erwachsenenbildung",
    "sg:phone":"+41 41 750 78 88",
    "sg:postcode":"6314",
    "sg:province":"Zug",
    "wof:name":"Markus Hotz Consulting Gmbh Mental- & Team-coaching",
    "wof:placetype":"venue"
},
  "geometry": {"coordinates":[8.583835,47.137405],"type":"Point"}
}