{
  "type": "Feature",
  "properties": {
    "iso:country":"CH",
    "sg:address":"St. Gallerstrasse 80",
    "sg:city":"Sargans",
    "sg:orig_category":"Autogaragen",
    "sg:phone":"+41 17881765",
    "sg:postcode":"7320",
    "sg:province":"St. Gallen",
    "wof:name":"Hansruedi Korrodi Autoreparaturwerkst\u00e4tte",
    "wof:placetype":"venue"
},
  "geometry": {"coordinates":[8.637348,47.212215],"type":"Point"}
}