{
  "type": "Feature",
  "properties": {
    "iso:country":"CH",
    "sg:address":"Avenue Du L\u00e9man 62",
    "sg:city":"Lausanne",
    "sg:orig_category":"Physiotherapie",
    "sg:phone":"+41 21 729 37 65",
    "sg:postcode":"1004",
    "sg:province":"Vaud",
    "wof:name":"Anne-g. Vernet Naturopathe",
    "wof:placetype":"venue"
},
  "geometry": {"coordinates":[6.6529631615,46.5142822266],"type":"Point"}
}