{
  "type": "Feature",
  "properties": {
    "iso:country":"CH",
    "sg:address":"Charpilloz Rue Aim\u00e9- 6a 2735 B\u00e9vilard. Postfach",
    "sg:city":"B\u00e9vilard",
    "sg:orig_category":"Architektur U Ingenieurb\u00fcros",
    "sg:phone":"+41 32 492 22 32",
    "sg:postcode":"2735",
    "sg:province":"Bern",
    "wof:name":"Niederh\u00e4user P.a. Bureau D'ing\u00e9nieurs Sa",
    "wof:placetype":"venue"
},
  "geometry": {"coordinates":[7.284739,47.237026],"type":"Point"}
}