{
  "type": "Feature",
  "properties": {
    "iso:country":"CH",
    "sg:address":"Himmelrichstrasse 5",
    "sg:city":"Luzern",
    "sg:orig_category":"Sonstiger Grosshandel",
    "sg:phone":"+41 41 211 08 82",
    "sg:postcode":"6003",
    "sg:province":"Luzern",
    "wof:name":"Egli Jeyaraja Petra Rp Import Export",
    "wof:placetype":"venue"
},
  "geometry": {"coordinates":[8.3058776855,47.0449867249],"type":"Point"}
}