{
  "type": "Feature",
  "properties": {
    "iso:country":"CH",
    "sg:address":"Hauptstrasse 57",
    "sg:city":"Oensingen",
    "sg:orig_category":"Betrieb von Taxis",
    "sg:postcode":"4702",
    "sg:province":"Solothurn",
    "wof:name":"Dakaj-tours",
    "wof:placetype":"venue"
},
  "geometry": {"coordinates":[7.720787,47.290409],"type":"Point"}
}