{
  "type": "Feature",
  "properties": {
    "iso:country":"CH",
    "sg:address":"Dorfstrasse 66",
    "sg:city":"Adelboden",
    "sg:orig_category":"Reiseb\u00fcros U Reiseveranstalter",
    "sg:phone":"+41 33 673 10 57",
    "sg:postcode":"3715",
    "sg:province":"Bern",
    "wof:name":"Portenier E. Ag, Carreisen + Kursbetriebe",
    "wof:placetype":"venue"
},
  "geometry": {"coordinates":[7.5557150841,46.4904136658],"type":"Point"}
}