{
  "type": "Feature",
  "properties": {
    "iso:country":"CH",
    "sg:address":"Bergweg 157",
    "sg:city":"Kallnach",
    "sg:orig_category":"Handel mit Automobilen",
    "sg:postcode":"3283",
    "sg:province":"Bern",
    "wof:name":"Autocenter D\u00fcrig Und Bertschi Ag Kallnach",
    "wof:placetype":"venue"
},
  "geometry": {"coordinates":[7.2337899208,47.019241333],"type":"Point"}
}