{
  "type": "Feature",
  "properties": {
    "iso:country":"CH",
    "sg:address":"Weissensteinstrasse 20",
    "sg:city":"Wolfwil",
    "sg:classifiers":[
        {
            "category":"Insurance",
            "subcategory":"Insurance Agent",
            "type":"Services"
        }
    ],
    "sg:phone":"+41 79 204 83 12",
    "sg:postcode":"4628",
    "sg:province":"Solothurn",
    "sg:tags":[
        "versicherungsagenturen",
        "-broker"
    ],
    "wof:name":"Karl K\u00fcng Versicherungen",
    "wof:placetype":"venue"
},
  "geometry": {"coordinates":[7.7847681046,47.2694091797],"type":"Point"}
}