{
  "type": "Feature",
  "properties": {
    "iso:country":"CH",
    "sg:address":"Pfrundmatte 3",
    "sg:city":"Neuenkirch",
    "sg:orig_category":"Naturheil\u00e4rzte and Heilpraktiker",
    "sg:phone":"+41 41 467 13 64",
    "sg:postcode":"6206",
    "sg:province":"Luzern",
    "wof:name":"Niklaus Peter Heilpraktiker",
    "wof:placetype":"venue"
},
  "geometry": {"coordinates":[8.2028808594,47.1010475159],"type":"Point"}
}