{
  "type": "Feature",
  "properties": {
    "iso:country":"CH",
    "sg:address":"Freihofstrasse 7",
    "sg:city":"Heiden",
    "sg:orig_category":"Naturheil\u00e4rzte and Heilpraktiker",
    "sg:phone":"+41 71 891 59 09",
    "sg:postcode":"9410",
    "sg:province":"Appenzell Ausserrhoden",
    "wof:name":"Andr\u00e9 Peter Naturarzt",
    "wof:placetype":"venue"
},
  "geometry": {"coordinates":[9.5328712463,47.4442901611],"type":"Point"}
}