{
  "type": "Feature",
  "properties": {
    "iso:country":"CH",
    "sg:address":"Spilberg 9113 Degersheim. Postfach",
    "sg:city":"Wolfertswil",
    "sg:orig_category":"Herstellung von elektrischen Lampen U Leuchten",
    "sg:postcode":"9116",
    "sg:province":"St. Gallen",
    "wof:name":"Beleuchtungs-genossenschaft Moos-dieselbach Und Umgebung",
    "wof:placetype":"venue"
},
  "geometry": {"coordinates":[9.200012207,47.3739433289],"type":"Point"}
}