{
  "type": "Feature",
  "properties": {
    "iso:country":"CH",
    "sg:address":"4853",
    "sg:city":"Murgenthal",
    "sg:orig_category":"Politische Parteien SP",
    "sg:phone":"+41 56 664 10 34",
    "sg:postcode":"4853",
    "sg:province":"Aargau",
    "wof:name":"Sp Ortspartei Muri",
    "wof:placetype":"venue"
},
  "geometry": {"coordinates":[8.3174819946,47.2825775146],"type":"Point"}
}