{
  "type": "Feature",
  "properties": {
    "iso:country":"CH",
    "sg:address":"Beggingerstrasse 37",
    "sg:city":"Schleitheim",
    "sg:orig_category":"Instandhaltung U Reparatur von Automobilen",
    "sg:phone":"+41 52 680 12 21",
    "sg:postcode":"8226",
    "sg:province":"Schaffhausen",
    "wof:name":"Meyer Heinz, Autospritzwerk.",
    "wof:placetype":"venue"
},
  "geometry": {"coordinates":[8.4892673492,47.7515830994],"type":"Point"}
}