{
  "type": "Feature",
  "properties": {
    "iso:country":"CH",
    "sg:address":"Rue Du Ch\u00e2telard 3",
    "sg:city":"Peseux",
    "sg:classifiers":[
        {
            "category":"Travel",
            "subcategory":"Hotels & Motels",
            "type":"Entertainment"
        }
    ],
    "sg:phone":"+41 32 731 12 40",
    "sg:postcode":"2034",
    "sg:province":"Neuch\u00e2tel",
    "sg:tags":[
        "hotels",
        "mit",
        "restaurant"
    ],
    "wof:name":"H\u00f4tel Restaurant Du Vignoble S\u00e0rl",
    "wof:placetype":"venue"
},
  "geometry": {"coordinates":[6.8945741653,46.9882545471],"type":"Point"}
}