{
  "type": "Feature",
  "properties": {
    "iso:country":"CH",
    "sg:address":"Meisenweg 10",
    "sg:city":"Hilterfingen",
    "sg:orig_category":"Architektur U Ingenieurb\u00fcros Hoch U Tiefbau",
    "sg:postcode":"3652",
    "sg:province":"Bern",
    "wof:name":"A. Lorenzi",
    "wof:placetype":"venue"
},
  "geometry": {"coordinates":[7.495512,46.924034],"type":"Point"}
}