{
  "type": "Feature",
  "properties": {
    "iso:country":"CH",
    "sg:address":"Einsteinstrasse 8049 Z\u00fcrich. Postfach",
    "sg:city":"Z\u00fcrich",
    "sg:orig_category":"Technische, physikalische U chemische Untersuchung",
    "sg:phone":"+41 13774411",
    "sg:postcode":"8093",
    "sg:province":"Z\u00fcrich",
    "wof:name":"Eth Z\u00fcrich Institut F\u00fcr Molekularbiologie Ger\u00e4telabor",
    "wof:placetype":"venue"
},
  "geometry": {"coordinates":[8.5043554306,47.4087791443],"type":"Point"}
}