{
  "type": "Feature",
  "properties": {
    "iso:country":"CH",
    "sg:address":"Aum\u00fchlestrasse",
    "sg:city":"Ennetb\u00fcrgen",
    "sg:orig_category":"Luft U Raumfahrzeugbau",
    "sg:phone":"+41 41 624 48 48",
    "sg:postcode":"6373",
    "sg:province":"Nidwalden",
    "wof:name":"Wyss Xaver Ag",
    "wof:placetype":"venue"
},
  "geometry": {"coordinates":[8.4098501205,46.9821434021],"type":"Point"}
}