{
  "type": "Feature",
  "properties": {
    "iso:country":"CH",
    "sg:address":"Allschwilerstrasse 85 4055 Basel. Postfach",
    "sg:city":"Basel",
    "sg:orig_category":"Maler U Glasergewerbe",
    "sg:postcode":"4051",
    "sg:province":"Basel-Stadt",
    "wof:name":"Vogt Maleratelier Ag, Filiale Basel",
    "wof:placetype":"venue"
},
  "geometry": {"coordinates":[7.5692081451,47.5571937561],"type":"Point"}
}