{
  "type": "Feature",
  "properties": {
    "iso:country":"CH",
    "sg:address":"Chemin Des Sapins 12",
    "sg:city":"Aubonne",
    "sg:orig_category":"Datenverarbeitungsdienste",
    "sg:phone":"+41 16871912",
    "sg:postcode":"1170",
    "sg:province":"Vaud",
    "wof:name":"Max Giger Edv Beratung",
    "wof:placetype":"venue"
},
  "geometry": {"coordinates":[8.743401,47.199097],"type":"Point"}
}