{
  "type": "Feature",
  "properties": {
    "iso:country":"CH",
    "sg:address":"Monbielerstrasse",
    "sg:city":"Klosters",
    "sg:classifiers":[
        {
            "category":"Travel",
            "subcategory":"Hotels & Motels",
            "type":"Entertainment"
        }
    ],
    "sg:phone":"+41 81 832 21 11",
    "sg:postcode":"7250",
    "sg:province":"Graubunden",
    "sg:tags":[
        "hotels",
        "mit",
        "restaurant"
    ],
    "wof:name":"Hotel Park Hotel Kurhaus",
    "wof:placetype":"venue"
},
  "geometry": {"coordinates":[9.8331003189,46.4826164246],"type":"Point"}
}