{
  "type": "Feature",
  "properties": {
    "iso:country":"CH",
    "sg:address":"Badstrasse",
    "sg:city":"Blumenstein",
    "sg:orig_category":"Detailhandel mit Brot, Back U S\u00fcsswaren",
    "sg:phone":"+41 33 356 12 16",
    "sg:postcode":"3638",
    "sg:province":"Bern",
    "wof:name":"Beck Winkler Ag",
    "wof:placetype":"venue"
},
  "geometry": {"coordinates":[7.520185,46.74218],"type":"Point"}
}