{
  "type": "Feature",
  "properties": {
    "iso:country":"CH",
    "sg:address":"Im Heimg\u00e4rtli 18",
    "sg:city":"Z\u00fcrich",
    "sg:orig_category":"Maler U Glasergewerbe",
    "sg:phone":"+41 14624161",
    "sg:postcode":"8047",
    "sg:province":"Z\u00fcrich",
    "wof:name":"Seglias Malerbedarf Ag Malerarbeiten Usw",
    "wof:placetype":"venue"
},
  "geometry": {"coordinates":[8.4885253906,47.3704490662],"type":"Point"}
}