{
  "type": "Feature",
  "properties": {
    "iso:country":"CH",
    "sg:address":"Adlermatte 17 6130 Willisau. Postfach",
    "sg:city":"Willisau",
    "sg:orig_category":"Vermittlung von Immobilien Wirtschaftspr\u00fcfung, Steuerberatung U Treuhand",
    "sg:phone":"+41 41 970 20 40",
    "sg:postcode":"6130",
    "sg:province":"Luzern",
    "wof:name":"Treuhand Kunz",
    "wof:placetype":"venue"
},
  "geometry": {"coordinates":[7.9893212318,47.1211395264],"type":"Point"}
}