{
  "type": "Feature",
  "properties": {
    "iso:country":"CH",
    "sg:address":"Oberseetal 8752 N\u00e4fels. Postfach 35",
    "sg:city":"N\u00e4fels",
    "sg:classifiers":[
        {
            "category":"Travel",
            "subcategory":"Hotels & Motels",
            "type":"Entertainment"
        }
    ],
    "sg:phone":"+41 55 612 10 73",
    "sg:postcode":"8752",
    "sg:province":"Glarus",
    "sg:tags":[
        "hotels",
        "mit",
        "restaurant"
    ],
    "wof:name":"Berghotel Obersee",
    "wof:placetype":"venue"
},
  "geometry": {"coordinates":[9.0210790634,47.0881195068],"type":"Point"}
}