{
  "type": "Feature",
  "properties": {
    "iso:country":"CH",
    "sg:address":"Chesa Rievanot",
    "sg:city":"Berg\u00fcn/bravuogn",
    "sg:orig_category":"Interessenvertretungen",
    "sg:postcode":"7482",
    "sg:province":"Graubunden",
    "wof:name":"Fundaziun Museum Bravuogn",
    "wof:placetype":"venue"
},
  "geometry": {"coordinates":[9.7510938644,46.6278152466],"type":"Point"}
}