{
  "type": "Feature",
  "properties": {
    "iso:country":"CH",
    "sg:address":"Rigiblick 13",
    "sg:city":"Ottenbach",
    "sg:orig_category":"Maschinen and Apparate divers Grosshandel",
    "sg:phone":"+41 17762576",
    "sg:postcode":"8913",
    "sg:province":"Z\u00fcrich",
    "wof:name":"Rational Schweiz Ag",
    "wof:placetype":"venue"
},
  "geometry": {"coordinates":[8.4059772491,47.27784729],"type":"Point"}
}