{
  "type": "Feature",
  "properties": {
    "iso:country":"CH",
    "sg:address":"Martin Disteli-strasse 5",
    "sg:city":"Olten",
    "sg:orig_category":"Sonstiges Versicherungsgewerbe",
    "sg:phone":"+41 62 849 25 34",
    "sg:postcode":"4600",
    "sg:province":"Solothurn",
    "wof:name":"Hoti Agentur",
    "wof:placetype":"venue"
},
  "geometry": {"coordinates":[7.9088330269,47.3513183594],"type":"Point"}
}