{
  "type": "Feature",
  "properties": {
    "iso:country":"CH",
    "sg:address":"3425 Koppigen. Postfach",
    "sg:city":"Koppigen",
    "sg:orig_category":"Sportvereine Eissport Eishockey",
    "sg:postcode":"3425",
    "sg:province":"Bern",
    "wof:name":"Eishockey-club Kreuzlingen",
    "wof:placetype":"venue"
},
  "geometry": {"coordinates":[9.173210144,47.641368866],"type":"Point"}
}