{
  "type": "Feature",
  "properties": {
    "iso:country":"CH",
    "sg:address":"Gotthardstrasse 55 6490 Andermatt. Postfach 127",
    "sg:city":"Andermatt",
    "sg:orig_category":"Detailhandel mit Sportartikeln Fachdetailhandel in Verkaufsr\u00e4umen",
    "sg:phone":"+41 41 887 12 51",
    "sg:postcode":"6490",
    "sg:province":"Uri",
    "wof:name":"Sporthaus Christen Inhaber Tauderer-christen",
    "wof:placetype":"venue"
},
  "geometry": {"coordinates":[8.5968055725,46.6344299316],"type":"Point"}
}