{
  "type": "Feature",
  "properties": {
    "iso:country":"CH",
    "sg:address":"Avenue De France 3",
    "sg:city":"Monthey",
    "sg:orig_category":"Grosshandel mit Nahrungsmitteln, Getr\u00e4nken U Tabakwaren ohne ausgepr\u00e4gten Schwerpunkt",
    "sg:postcode":"1870",
    "sg:province":"Valais",
    "wof:name":"T\u00e9j\u00e9da Mercedes",
    "wof:placetype":"venue"
},
  "geometry": {"coordinates":[6.9465761185,46.2525634766],"type":"Point"}
}