{
  "type": "Feature",
  "properties": {
    "iso:country":"CH",
    "sg:address":"Industriestr. 5",
    "sg:city":"Liesberg",
    "sg:classifiers":[
        {
            "category":"Train Station",
            "subcategory":"Rail",
            "type":"Transportation"
        }
    ],
    "sg:phone":"+41 61 775 22 22",
    "sg:postcode":"4253",
    "sg:province":"Basel-Landschaft",
    "sg:tags":[
        "steel",
        "pipe",
        "sheet",
        "metal",
        "metallurgy",
        "metalworking"
    ],
    "wof:name":"Aluminium Laufen Ag",
    "wof:placetype":"venue"
},
  "geometry": {"coordinates":[7.4295458794,47.3949317932],"type":"Point"}
}