{
  "type": "Feature",
  "properties": {
    "iso:country":"CH",
    "sg:address":"Seestrasse 147a 8800 Thalwil. Postfach",
    "sg:city":"Thalwil",
    "sg:orig_category":"Softwareentwicklung U beratung",
    "sg:postcode":"8800",
    "sg:province":"Z\u00fcrich",
    "wof:name":"Klik Technologies Gmbh",
    "wof:placetype":"venue"
},
  "geometry": {"coordinates":[8.5652389526,47.2982559204],"type":"Point"}
}