{
  "type": "Feature",
  "properties": {
    "iso:country":"CH",
    "sg:address":"Florimont Avenue De 1",
    "sg:city":"Lausanne",
    "sg:orig_category":"Interessenvertretungen",
    "sg:phone":"+41 21 343 40 60",
    "sg:postcode":"1006",
    "sg:province":"Vaud",
    "wof:name":"Fondation Pour La Maison De La Communication",
    "wof:placetype":"venue"
},
  "geometry": {"coordinates":[6.6380681992,46.5164527893],"type":"Point"}
}