{
  "type": "Feature",
  "properties": {
    "addr:full":"Fuchsweg 15 Liebefeld Bern 3097",
    "addr:housenumber":"15",
    "addr:postcode":"3097",
    "addr:street":"Fuchsweg",
    "iso:country":"CH",
    "sg:address":"Fuchsweg 15",
    "sg:city":"Liebefeld",
    "sg:classifiers":[
        {
            "category":"Social Services",
            "subcategory":"Retirement Home",
            "type":"Services"
        }
    ],
    "sg:phone":"+41 31 972 30 30",
    "sg:postcode":"3097",
    "sg:province":"Bern",
    "sg:tags":[
        "pflegeheime",
        "u",
        "alters"
    ],
    "wof:name":"Hessgut Alterssiedlung",
    "wof:placetype":"venue"
},
  "geometry": {"coordinates":[7.42432,46.933819],"type":"Point"}
}