{
  "type": "Feature",
  "properties": {
    "iso:country":"CH",
    "sg:address":"Rue Gambetta 27",
    "sg:city":"Clarens",
    "sg:orig_category":"Arztpraxen",
    "sg:phone":"+41 21 964 26 53",
    "sg:postcode":"1815",
    "sg:province":"Vaud",
    "wof:name":"Dr M\u00e9d. M. Katchaluba Jun. M\u00e9decin Sp\u00e9cialiste Fmh",
    "wof:placetype":"venue"
},
  "geometry": {"coordinates":[6.896265,46.442238],"type":"Point"}
}