{
  "type": "Feature",
  "properties": {
    "iso:country":"CH",
    "sg:address":"Bifangstrasse 69 4663 Aarburg. Postfach",
    "sg:city":"Aarburg",
    "sg:orig_category":"Schreib U \u00dcbersetzungsb\u00fcros",
    "sg:phone":"+41 62 791 54 58",
    "sg:postcode":"4663",
    "sg:province":"Aargau",
    "wof:name":"Pache Pierre-herv\u00e9 Gmbh Sprachdienstleistungen Usw",
    "wof:placetype":"venue"
},
  "geometry": {"coordinates":[7.8983888626,47.3260726929],"type":"Point"}
}