{
  "type": "Feature",
  "properties": {
    "addr:full":"Dalmaziquai 29 Bern Bern 3005",
    "addr:housenumber":"29",
    "addr:postcode":"3005",
    "addr:street":"Dalmaziquai",
    "iso:country":"CH",
    "sg:address":"Dalmaziquai 29",
    "sg:city":"Bern",
    "sg:orig_category":"Architekturb\u00fcros",
    "sg:phone":"+41 31 352 18 83",
    "sg:postcode":"3005",
    "sg:province":"Bern",
    "wof:name":"Franz Meister Architekturb\u00fcro",
    "wof:placetype":"venue"
},
  "geometry": {"coordinates":[7.446357,46.943817],"type":"Point"}
}