{
  "type": "Feature",
  "properties": {
    "iso:country":"CH",
    "sg:address":"Lettengrund 1",
    "sg:city":"Sins",
    "sg:orig_category":"Chemische Reinigung W\u00e4schereien",
    "sg:phone":"+41 41 787 27 70",
    "sg:postcode":"5643",
    "sg:province":"Aargau",
    "wof:name":"Erika Meyer Textilreinigung & W\u00e4scherei",
    "wof:placetype":"venue"
},
  "geometry": {"coordinates":[8.395127,47.189438],"type":"Point"}
}