{
  "type": "Feature",
  "properties": {
    "iso:country":"CH",
    "sg:address":"Seefeldstrasse 174",
    "sg:city":"Z\u00fcrich",
    "sg:orig_category":"Detailhandel mit Uhren U Schmuck Herstellung von Schmuck, Gold U Silberschmiedwaren",
    "sg:phone":"+41 17616112",
    "sg:postcode":"8008",
    "sg:province":"Z\u00fcrich",
    "wof:name":"Meyer Raphael Goldschmiede",
    "wof:placetype":"venue"
},
  "geometry": {"coordinates":[8.4537439346,47.2772483826],"type":"Point"}
}