{
  "type": "Feature",
  "properties": {
    "iso:country":"CH",
    "sg:address":"Zentralstrasse 7 6003 Luzern. Postfach",
    "sg:city":"Luzern",
    "sg:orig_category":"Pensionskassen",
    "sg:phone":"+41 41 228 76 40",
    "sg:postcode":"6002",
    "sg:province":"Luzern",
    "wof:name":"Luzerner Pensionskasse",
    "wof:placetype":"venue"
},
  "geometry": {"coordinates":[8.3092842102,47.0491523743],"type":"Point"}
}