{
  "type": "Feature",
  "properties": {
    "iso:country":"CH",
    "sg:address":"Birmensdorferstrasse 299",
    "sg:city":"Z\u00fcrich",
    "sg:classifiers":[
        {
            "category":"Bars & Pubs",
            "subcategory":"Sports Bar",
            "type":"Food & Drink"
        }
    ],
    "sg:phone":"+41 14618729",
    "sg:postcode":"8055",
    "sg:province":"Z\u00fcrich",
    "sg:tags":[
        "accessory",
        "cd"
    ],
    "wof:name":"Soundseduction",
    "wof:placetype":"venue"
},
  "geometry": {"coordinates":[8.509784,47.369663],"type":"Point"}
}