{
  "type": "Feature",
  "properties": {
    "iso:country":"CH",
    "sg:address":"Grabackerstr. 161.",
    "sg:city":"Horriwil",
    "sg:orig_category":"Detailhandel mit elektrischen Haushalts-,Radio U Fernsehger\u00e4ten sowie Musikinstrumenten",
    "sg:phone":"+41 79 415 57 39",
    "sg:postcode":"4557",
    "sg:province":"Solothurn",
    "wof:name":"Leutenegger Viteco",
    "wof:placetype":"venue"
},
  "geometry": {"coordinates":[7.6248002052,47.1847190857],"type":"Point"}
}