{
  "type": "Feature",
  "properties": {
    "iso:country":"CH",
    "sg:address":"Avenue Robert 33",
    "sg:city":"Fontainemelon",
    "sg:orig_category":"Nationale Postdienste",
    "sg:phone":"+41 32 853 21 66",
    "sg:postcode":"2052",
    "sg:province":"Neuch\u00e2tel",
    "wof:name":"La Poste Suisse",
    "wof:placetype":"venue"
},
  "geometry": {"coordinates":[6.8882279396,47.0553321838],"type":"Point"}
}