{
  "type": "Feature",
  "properties": {
    "iso:country":"CH",
    "sg:address":"Untere Chennerstrasse 20a",
    "sg:city":"Waldkirch",
    "sg:orig_category":"Softwareentwicklung U beratung Sonstige mit der Informatik verbundene T\u00e4tigkeiten",
    "sg:phone":"+41 71 430 02 11",
    "sg:postcode":"9205",
    "sg:province":"St. Gallen",
    "wof:name":"Objtec Gmbh",
    "wof:placetype":"venue"
},
  "geometry": {"coordinates":[9.2947835922,47.4696464539],"type":"Point"}
}