{
  "type": "Feature",
  "properties": {
    "iso:country":"CH",
    "sg:address":"Sonnhalde 3555 Trubschachen. Postfach 41",
    "sg:city":"Trubschachen",
    "sg:orig_category":"Sportvereine Ballsport Fussball",
    "sg:phone":"+41 34 495 53 44",
    "sg:postcode":"3555",
    "sg:province":"Bern",
    "wof:name":"Fc Trubschachen",
    "wof:placetype":"venue"
},
  "geometry": {"coordinates":[7.842168808,46.9237136841],"type":"Point"}
}