{
  "type": "Feature",
  "properties": {
    "iso:country":"CH",
    "sg:address":"Rosenstrasse 19a",
    "sg:city":"Eschlikon",
    "sg:classifiers":[
        {
            "category":"Professional",
            "subcategory":"Computer Services",
            "type":"Services"
        }
    ],
    "sg:phone":"+41 52 670 04 70",
    "sg:postcode":"8360",
    "sg:province":"Thurgau",
    "sg:tags":[
        "development",
        "software"
    ],
    "wof:name":"M.b.f. Mega Byte Focus Gmbh",
    "wof:placetype":"venue"
},
  "geometry": {"coordinates":[8.6099252701,47.6833763123],"type":"Point"}
}