{
  "type": "Feature",
  "properties": {
    "iso:country":"CH",
    "sg:address":"Ravagl",
    "sg:city":"Scuol",
    "sg:orig_category":"Sportvereine Flug Delta",
    "sg:phone":"+41 81 864 02 81",
    "sg:postcode":"7550",
    "sg:province":"Graubunden",
    "wof:name":"Corniglias D'engadina",
    "wof:placetype":"venue"
},
  "geometry": {"coordinates":[10.3124513626,46.8005905151],"type":"Point"}
}