{
  "type": "Feature",
  "properties": {
    "iso:country":"CH",
    "sg:address":"Orelli Piazza 6600 Locarno. Postfach",
    "sg:city":"Locarno",
    "sg:orig_category":"Verwaltung von Immobilien",
    "sg:postcode":"6600",
    "sg:province":"Ticino",
    "wof:name":"Ani Sagl Esercizi Pubblici Ecc",
    "wof:placetype":"venue"
},
  "geometry": {"coordinates":[8.8003940582,46.1705741882],"type":"Point"}
}