{
  "type": "Feature",
  "properties": {
    "iso:country":"CH",
    "sg:address":"Quatre-ministrauxch. Des 22",
    "sg:city":"Neuenburg",
    "sg:orig_category":"Non-Classified Establishments",
    "sg:postcode":"2000",
    "sg:province":"Neuch\u00e2tel",
    "wof:name":"Calame Consulting",
    "wof:placetype":"venue"
},
  "geometry": {"coordinates":[6.9209461212,46.9988861084],"type":"Point"}
}