{
  "type": "Feature",
  "properties": {
    "iso:country":"CH",
    "sg:address":"Seewjinenstrasse 1",
    "sg:city":"Visp",
    "sg:classifiers":[
        {
            "category":"Restaurant",
            "type":"Food & Drink"
        }
    ],
    "sg:phone":"+41 55 644 11 89",
    "sg:postcode":"3930",
    "sg:province":"Valais",
    "wof:name":"Restaurant Sonne",
    "wof:placetype":"venue"
},
  "geometry": {"coordinates":[9.0746030807,46.9944915771],"type":"Point"}
}