{
  "type": "Feature",
  "properties": {
    "iso:country":"CH",
    "sg:address":"Piazza Della Riforma",
    "sg:city":"Lugano",
    "sg:orig_category":"Strassenverkehrs\u00e4mter and -inspektorate",
    "sg:phone":"+41 61 706 28 80",
    "sg:postcode":"6900",
    "sg:province":"Ticino",
    "wof:name":"Kant. Motorfahrzeugkontrolle",
    "wof:placetype":"venue"
},
  "geometry": {"coordinates":[7.6087441444,47.4882621765],"type":"Point"}
}