{
  "type": "Feature",
  "properties": {
    "iso:country":"CH",
    "sg:address":"D\u00f6ltschweg",
    "sg:city":"Schmerikon",
    "sg:orig_category":"Mechanische Werkst\u00e4tten",
    "sg:phone":"+41 55 282 17 19",
    "sg:postcode":"8716",
    "sg:province":"St. Gallen",
    "wof:name":"Hansueli Dubach Apparatebau",
    "wof:placetype":"venue"
},
  "geometry": {"coordinates":[8.9468650818,47.2288093567],"type":"Point"}
}