{
  "type": "Feature",
  "properties": {
    "iso:country":"CH",
    "sg:address":"Route De Suisse 97",
    "sg:city":"Versoix",
    "sg:orig_category":"Grosshandel mit B\u00fcromaschinen Grosshandel mit Datenverarbeitungsger\u00e4ten",
    "sg:phone":"+41 22 755 19 49",
    "sg:postcode":"1290",
    "sg:province":"Gen\u00e8ve",
    "wof:name":"Doors Computer Sa",
    "wof:placetype":"venue"
},
  "geometry": {"coordinates":[6.1654849052,46.2854957581],"type":"Point"}
}