{
  "type": "Feature",
  "properties": {
    "iso:country":"CH",
    "sg:address":"Abt-beda-strasse 49",
    "sg:city":"Oberb\u00fcren",
    "sg:orig_category":"Sonstiger spezialisierter Hoch U Tiefbau Verlegen von Fliesen U Platten",
    "sg:phone":"+41 21 691 65 06",
    "sg:postcode":"9245",
    "sg:province":"St. Gallen",
    "wof:name":"Bourgoz Jean-roland Sa",
    "wof:placetype":"venue"
},
  "geometry": {"coordinates":[6.5458350182,46.5143089294],"type":"Point"}
}