{
  "type": "Feature",
  "properties": {
    "iso:country":"CH",
    "sg:address":"Grossbruggerweg 1",
    "sg:city":"Chur",
    "sg:orig_category":"Allgemeiner Hoch U Tiefbau Allgemeiner Hochbau",
    "sg:phone":"+41 81 284 57 76",
    "sg:postcode":"7000",
    "sg:province":"Graubunden",
    "wof:name":"Lazzarini G. & Co Ag",
    "wof:placetype":"venue"
},
  "geometry": {"coordinates":[9.509432,46.857738],"type":"Point"}
}