{
  "type": "Feature",
  "properties": {
    "iso:country":"CH",
    "sg:address":"Avenue Gennecy 2",
    "sg:city":"Avully",
    "sg:orig_category":"Nationale Postdienste",
    "sg:phone":"+41 22 756 12 51",
    "sg:postcode":"1237",
    "sg:province":"Gen\u00e8ve",
    "wof:name":"La Poste Suisse",
    "wof:placetype":"venue"
},
  "geometry": {"coordinates":[5.9942121506,46.1682853699],"type":"Point"}
}