{
  "type": "Feature",
  "properties": {
    "iso:country":"CH",
    "sg:address":"Im Stetterfeld 1",
    "sg:city":"Stetten",
    "sg:classifiers":[
        {
            "category":"Building & Trades",
            "subcategory":"Cleaning & Sanitation",
            "type":"Services"
        }
    ],
    "sg:phone":"+41 56 485 81 81",
    "sg:postcode":"5608",
    "sg:province":"Aargau",
    "sg:tags":[
        "device"
    ],
    "wof:name":"Birchmeier Spr\u00fchtechnik Ag",
    "wof:placetype":"venue"
},
  "geometry": {"coordinates":[8.31325,47.406349],"type":"Point"}
}