{
  "type": "Feature",
  "properties": {
    "iso:country":"CH",
    "sg:address":"Bahnhofstrasse 29",
    "sg:city":"Zollikon",
    "sg:orig_category":"Handel mit Automobilen",
    "sg:phone":"+41 13921414",
    "sg:postcode":"8702",
    "sg:province":"Z\u00fcrich",
    "wof:name":"Baumgartner Automobile Ag",
    "wof:placetype":"venue"
},
  "geometry": {"coordinates":[8.5705747604,47.3369369507],"type":"Point"}
}