{
  "type": "Feature",
  "properties": {
    "iso:country":"CH",
    "sg:address":"Lyssachstrasse 80",
    "sg:city":"Burgdorf",
    "sg:orig_category":"RESTAURANTS: TEA-ROOMS",
    "sg:postcode":"3400",
    "sg:province":"Bern",
    "wof:name":"Leuenberger Restaurant National Gmbh",
    "wof:placetype":"venue"
},
  "geometry": {"coordinates":[7.6132831573,47.0596313477],"type":"Point"}
}