{
  "type": "Feature",
  "properties": {
    "iso:country":"CH",
    "sg:address":"Hauptstrasse 6",
    "sg:city":"Frenkendorf",
    "sg:orig_category":"Elektroinstallation",
    "sg:phone":"+41 61 901 44 55",
    "sg:postcode":"4402",
    "sg:province":"Basel-Landschaft",
    "wof:name":"Zemp + Kiefer Ag",
    "wof:placetype":"venue"
},
  "geometry": {"coordinates":[7.7149291039,47.5032234192],"type":"Point"}
}