{
  "type": "Feature",
  "properties": {
    "iso:country":"CH",
    "sg:address":"Fulenbachstrasse 454",
    "sg:city":"H\u00e4rkingen",
    "sg:orig_category":"Kunststoff-Produkte",
    "sg:phone":"+41 62 398 03 63",
    "sg:postcode":"4624",
    "sg:province":"Solothurn",
    "wof:name":"Moser Konstruktionsb\u00fcro",
    "wof:placetype":"venue"
},
  "geometry": {"coordinates":[7.8202280998,47.304725647],"type":"Point"}
}