{
  "type": "Feature",
  "properties": {
    "addr:full":"Rue Madeleine 1 Lausanne Vaud 1003",
    "addr:housenumber":"1",
    "addr:postcode":"1003",
    "addr:street":"Rue Madeleine",
    "iso:country":"CH",
    "sg:address":"Rue Madeleine 1",
    "sg:city":"Lausanne",
    "sg:orig_category":"Detailhandel mit Bekleidung Detailhandel mit Damenbekleidung",
    "sg:phone":"+41 21 312 58 75",
    "sg:postcode":"1003",
    "sg:province":"Vaud",
    "wof:name":"Palud Modes Sa",
    "wof:placetype":"venue"
},
  "geometry": {"coordinates":[6.632867,46.522068],"type":"Point"}
}