{
  "type": "Feature",
  "properties": {
    "iso:country":"CH",
    "sg:address":"Chemin Colladon 5-7",
    "sg:city":"Gen\u00e8ve",
    "sg:classifiers":[
        {
            "category":"Social Services",
            "subcategory":"Retirement Home",
            "type":"Services"
        }
    ],
    "sg:phone":"+41 22 730 79 00",
    "sg:postcode":"1209",
    "sg:province":"Gen\u00e8ve",
    "sg:tags":[
        "pflegeheime",
        "u",
        "alters"
    ],
    "wof:name":"Si R\u00e9sidence Colladon",
    "wof:placetype":"venue"
},
  "geometry": {"coordinates":[6.123267,46.222683],"type":"Point"}
}