{
  "type": "Feature",
  "properties": {
    "iso:country":"CH",
    "sg:address":"Spl\u00fcgenstrasse 9 8002 Z\u00fcrich. Postfach",
    "sg:city":"Z\u00fcrich",
    "sg:orig_category":"Reiseb\u00fcros",
    "sg:phone":"+41 12023636",
    "sg:postcode":"8027",
    "sg:province":"Z\u00fcrich",
    "wof:name":"Golf-frei Travel",
    "wof:placetype":"venue"
},
  "geometry": {"coordinates":[8.5336847305,47.3642120361],"type":"Point"}
}