{
  "type": "Feature",
  "properties": {
    "iso:country":"CH",
    "sg:address":"Berneckerstr. 22 9434 Au Sg. Postfach",
    "sg:city":"Heerbrugg",
    "sg:orig_category":"Grosshandel mit Textilien",
    "sg:postcode":"9435",
    "sg:province":"St. Gallen",
    "wof:name":"Eichenberger-beyeler Ag",
    "wof:placetype":"venue"
},
  "geometry": {"coordinates":[8.1969232559,47.2762718201],"type":"Point"}
}