{
  "type": "Feature",
  "properties": {
    "iso:country":"CH",
    "sg:address":"Dornacherstr. 33",
    "sg:city":"Solothurn",
    "sg:orig_category":"Herstellung von Uhren",
    "sg:phone":"+41 32 641 34 35",
    "sg:postcode":"4500",
    "sg:province":"Solothurn",
    "wof:name":"Huther Sa Montres Brunela",
    "wof:placetype":"venue"
},
  "geometry": {"coordinates":[7.5404272079,47.2042541504],"type":"Point"}
}