{
  "type": "Feature",
  "properties": {
    "iso:country":"CH",
    "sg:address":"Grossholzweg 21",
    "sg:city":"G\u00fcmligen",
    "sg:orig_category":"Architektur U Ingenieurb\u00fcros",
    "sg:phone":"+41 31 951 35 73",
    "sg:postcode":"3073",
    "sg:province":"Bern",
    "wof:name":"Aquawet Kaufmann Peter",
    "wof:placetype":"venue"
},
  "geometry": {"coordinates":[7.505451,46.937256],"type":"Point"}
}