{
  "type": "Feature",
  "properties": {
    "iso:country":"CH",
    "sg:address":"Techcenterstrasse 2",
    "sg:city":"Bubikon",
    "sg:classifiers":[
        {
            "category":"Utilities",
            "subcategory":"Water",
            "type":"Services"
        }
    ],
    "sg:phone":"+41 55 253 31 71",
    "sg:postcode":"8608",
    "sg:province":"Z\u00fcrich",
    "sg:tags":[
        "plants",
        "installation",
        "softening",
        "deliming"
    ],
    "wof:name":"Perma-trade Wassertechnik Ag",
    "wof:placetype":"venue"
},
  "geometry": {"coordinates":[8.833741188,47.2626991272],"type":"Point"}
}