{
  "type": "Feature",
  "properties": {
    "iso:country":"CH",
    "sg:address":"6218",
    "sg:city":"Ettiswil",
    "sg:orig_category":"Konkurs- and Betreibungs\u00e4mter",
    "sg:phone":"+41 41 980 17 50",
    "sg:postcode":"6218",
    "sg:province":"Luzern",
    "wof:name":"Betreibungsamt",
    "wof:placetype":"venue"
},
  "geometry": {"coordinates":[8.017583847,47.147808075],"type":"Point"}
}