{
  "type": "Feature",
  "properties": {
    "iso:country":"CH",
    "sg:address":"Zopfstrasse 10 8134 Adliswil. Postfach",
    "sg:city":"Adliswil",
    "sg:orig_category":"Detailhandel mit M\u00f6beln U Haushaltsgegenst\u00e4nden",
    "sg:phone":"+41 17091435",
    "sg:postcode":"8134",
    "sg:province":"Z\u00fcrich",
    "wof:name":"Impex Firouzian Gmbh",
    "wof:placetype":"venue"
},
  "geometry": {"coordinates":[8.5164632797,47.3179168701],"type":"Point"}
}