{
  "type": "Feature",
  "properties": {
    "iso:country":"CH",
    "sg:address":"G\u00f6sgerstrasse 9",
    "sg:city":"Niedererlinsbach",
    "sg:orig_category":"Malerei",
    "sg:phone":"+41 62 844 38 79",
    "sg:postcode":"5015",
    "sg:province":"Solothurn",
    "wof:name":"Marcel Parrat Malergesch\u00e4ft",
    "wof:placetype":"venue"
},
  "geometry": {"coordinates":[8.0088796616,47.3963699341],"type":"Point"}
}