{
  "type": "Feature",
  "properties": {
    "iso:country":"CH",
    "sg:address":"Solothurnstrasse 65",
    "sg:city":"Oensingen",
    "sg:orig_category":"Maler U Glasergewerbe",
    "sg:postcode":"4702",
    "sg:province":"Solothurn",
    "wof:name":"Maler Krasniqi Sh.",
    "wof:placetype":"venue"
},
  "geometry": {"coordinates":[7.7146978378,47.2893676758],"type":"Point"}
}