{
  "type": "Feature",
  "properties": {
    "iso:country":"CH",
    "sg:address":"Kaiserstrasse 30 4310 Rheinfelden. Postfach",
    "sg:city":"Rheinfelden",
    "sg:orig_category":"Autogaragen Tankstellen",
    "sg:phone":"+41 61 831 50 52",
    "sg:postcode":"4310",
    "sg:province":"Aargau",
    "wof:name":"Casino Garage Ag",
    "wof:placetype":"venue"
},
  "geometry": {"coordinates":[7.788318,47.551914],"type":"Point"}
}