{
  "type": "Feature",
  "properties": {
    "iso:country":"CH",
    "sg:address":"Chemin De Belmont 4",
    "sg:city":"Prilly",
    "sg:orig_category":"Verlegen von Fliesen U Platten",
    "sg:phone":"+41 21 634 13 51",
    "sg:postcode":"1008",
    "sg:province":"Vaud",
    "wof:name":"Wicanders Amorim Sa Rev\u00eatements De Sols",
    "wof:placetype":"venue"
},
  "geometry": {"coordinates":[6.6003079414,46.5390510559],"type":"Point"}
}