{
  "type": "Feature",
  "properties": {
    "iso:country":"CH",
    "sg:address":"Route D'avenches",
    "sg:city":"Domdidier",
    "sg:orig_category":"Fahrschulen, Flugschulen",
    "sg:phone":"+41 26 675 36 44",
    "sg:postcode":"1564",
    "sg:province":"Fribourg",
    "wof:name":"Pierre Aebischer Auto-\u00e9cole",
    "wof:placetype":"venue"
},
  "geometry": {"coordinates":[7.015130043,46.8652992249],"type":"Point"}
}