{
  "type": "Feature",
  "properties": {
    "iso:country":"CH",
    "sg:address":"Brunhof 36",
    "sg:city":"Benzenschwil",
    "sg:orig_category":"Schreib U \u00dcbersetzungsb\u00fcros",
    "sg:phone":"+41 56 668 24 66",
    "sg:postcode":"5636",
    "sg:province":"Aargau",
    "wof:name":"Esther Reusser Schreibstube",
    "wof:placetype":"venue"
},
  "geometry": {"coordinates":[8.3635492325,47.2480583191],"type":"Point"}
}