{
  "type": "Feature",
  "properties": {
    "iso:country":"CH",
    "sg:address":"Giacomettistrasse 110",
    "sg:city":"Chur",
    "sg:orig_category":"Architektur U Ingenieurb\u00fcros",
    "sg:postcode":"7000",
    "sg:province":"Graubunden",
    "wof:name":"Lutz, Schmid Ingenieure Ag",
    "wof:placetype":"venue"
},
  "geometry": {"coordinates":[9.528853,46.863483],"type":"Point"}
}