{
  "type": "Feature",
  "properties": {
    "iso:country":"CH",
    "sg:address":"4924",
    "sg:city":"Obersteckholz",
    "sg:orig_category":"Vereine Musik/Blasmusik",
    "sg:postcode":"4924",
    "sg:province":"Bern",
    "wof:name":"Blechmusikverein",
    "wof:placetype":"venue"
},
  "geometry": {"coordinates":[7.8258800507,47.2011299133],"type":"Point"}
}