{
  "type": "Feature",
  "properties": {
    "iso:country":"CH",
    "sg:address":"R\u00f6merbrunnenweg 20",
    "sg:city":"Grenchen",
    "sg:orig_category":"Vereine Z\u00fcnfte",
    "sg:phone":"+41 79 631 77 05",
    "sg:postcode":"2540",
    "sg:province":"Solothurn",
    "wof:name":"Luna-zunft Grenchen",
    "wof:placetype":"venue"
},
  "geometry": {"coordinates":[7.3941898346,47.1853904724],"type":"Point"}
}