{
  "type": "Feature",
  "properties": {
    "iso:country":"CH",
    "sg:address":"Mon-repos Avenue 10 1005 Lausanne. Postfach",
    "sg:city":"Lausanne",
    "sg:orig_category":"Architektur U Ingenieurb\u00fcros",
    "sg:phone":"+41 21 312 81 50",
    "sg:postcode":"1005",
    "sg:province":"Vaud",
    "wof:name":"D\u00e9riaz Dominique, Architecte",
    "wof:placetype":"venue"
},
  "geometry": {"coordinates":[6.639728,46.519226],"type":"Point"}
}