{
  "type": "Feature",
  "properties": {
    "addr:full":"Alte Landstrasse 165 Gamsen Valais 3900",
    "addr:housenumber":"165",
    "addr:postcode":"3900",
    "addr:street":"Alte Landstrasse",
    "iso:country":"CH",
    "sg:address":"Alte Landstrasse 165",
    "sg:city":"Gamsen",
    "sg:classifiers":[
        {
            "category":"Banks & Credit Unions",
            "subcategory":"Atm",
            "type":"Services"
        }
    ],
    "sg:phone":"+41 27 923 25 55",
    "sg:postcode":"3900",
    "sg:province":"Valais",
    "sg:tags":[
        "conduit",
        "made",
        "cable",
        "plastic"
    ],
    "wof:name":"Macro-mol Ag",
    "wof:placetype":"venue"
},
  "geometry": {"coordinates":[7.946644,46.30452],"type":"Point"}
}