{
  "type": "Feature",
  "properties": {
    "iso:country":"CH",
    "sg:address":"Fichtenweg 13 3506 Grossh\u00f6chstetten. Postfach",
    "sg:city":"Grossh\u00f6chstetten",
    "sg:orig_category":"Detailhandel mit Brot, Back U S\u00fcsswaren Herstellung von Maschinen f\u00fcr die Nahrungsmittel, Getr\u00e4nkehe",
    "sg:phone":"+41 31 711 35 44",
    "sg:postcode":"3506",
    "sg:province":"Bern",
    "wof:name":"Schenk Engineering Gmbh",
    "wof:placetype":"venue"
},
  "geometry": {"coordinates":[7.636482,46.910629],"type":"Point"}
}