{
  "type": "Feature",
  "properties": {
    "iso:country":"CH",
    "sg:address":"Balmfluhstrasse 6",
    "sg:city":"Feldbrunnen",
    "sg:orig_category":"P\u00e9dicure",
    "sg:phone":"+41 32 623 14 22",
    "sg:postcode":"4532",
    "sg:province":"Solothurn",
    "wof:name":"Liliana V\u00f6geli P\u00e9dicure",
    "wof:placetype":"venue"
},
  "geometry": {"coordinates":[7.5561189651,47.2223587036],"type":"Point"}
}