{
  "type": "Feature",
  "properties": {
    "iso:country":"CH",
    "sg:address":"Duensstrasse 32",
    "sg:city":"D\u00fcdingen",
    "sg:orig_category":"Landesverteidigung, Zivilschutz Stahl U Leichtmetallbau",
    "sg:phone":"+41 26 493 16 65",
    "sg:postcode":"3186",
    "sg:province":"Fribourg",
    "wof:name":"Hans Hodel Ag Zweigniederlassung D\u00fcdingen",
    "wof:placetype":"venue"
},
  "geometry": {"coordinates":[7.1914248466,46.8407745361],"type":"Point"}
}