{
  "type": "Feature",
  "properties": {
    "iso:country":"CH",
    "sg:address":"2562 Port. Postfach 139",
    "sg:city":"Port",
    "sg:orig_category":"Sportvereine Unihockey",
    "sg:postcode":"2562",
    "sg:province":"Bern",
    "wof:name":"Uht Vertex-port",
    "wof:placetype":"venue"
},
  "geometry": {"coordinates":[7.2550401688,47.1164245605],"type":"Point"}
}