{
  "type": "Feature",
  "properties": {
    "iso:country":"CH",
    "sg:address":"Auf Der Halde 28",
    "sg:city":"N\u00fcrensdorf",
    "sg:orig_category":"Detailhandel mit Bekleidung Grosshandel mit Holz U Baustoffen",
    "sg:phone":"+41 18366395",
    "sg:postcode":"8309",
    "sg:province":"Z\u00fcrich",
    "wof:name":"Kneller Ag",
    "wof:placetype":"venue"
},
  "geometry": {"coordinates":[8.652836,47.444988],"type":"Point"}
}