{
  "type": "Feature",
  "properties": {
    "iso:country":"CH",
    "sg:address":"March\u00e9 Rue Du 18 1204 Gen\u00e8ve. Postfach",
    "sg:city":"Gen\u00e8ve",
    "sg:orig_category":"Sonstiger Grosshandel",
    "sg:postcode":"1201",
    "sg:province":"Gen\u00e8ve",
    "wof:name":"Herminjard Jean-pierre",
    "wof:placetype":"venue"
},
  "geometry": {"coordinates":[6.771586895,46.5445823669],"type":"Point"}
}