{
  "type": "Feature",
  "properties": {
    "iso:country":"CH",
    "sg:address":"Seidenbaum",
    "sg:city":"Tr\u00fcbbach",
    "sg:orig_category":"Sportvereine Sch\u00fctzen Pistolen-& Gewehr",
    "sg:phone":"+41 81 783 18 05",
    "sg:postcode":"9477",
    "sg:province":"St. Gallen",
    "wof:name":"Pistolen-& Kleinkaliber- Sektion Wartau",
    "wof:placetype":"venue"
},
  "geometry": {"coordinates":[9.4878797531,47.0797042847],"type":"Point"}
}