{
  "type": "Feature",
  "properties": {
    "iso:country":"CH",
    "sg:address":"Brunngasse 6",
    "sg:city":"Winterthur",
    "sg:classifiers":[
        {
            "category":"Organizations",
            "subcategory":"Professional Association",
            "type":"Services"
        }
    ],
    "sg:phone":"+41 52 268 91 00",
    "sg:postcode":"8400",
    "sg:province":"Z\u00fcrich",
    "sg:tags":[
        "customer",
        "software",
        "management",
        "relationship",
        "crm"
    ],
    "wof:name":"Ambit Ag",
    "wof:placetype":"venue"
},
  "geometry": {"coordinates":[8.725231,47.505371],"type":"Point"}
}