{
  "type": "Feature",
  "properties": {
    "iso:country":"CH",
    "sg:address":"1510",
    "sg:city":"Syens",
    "sg:orig_category":"Druck ohne Zeitungsdruck Offsetdruck",
    "sg:phone":"+41 32 725 00 85",
    "sg:postcode":"1510",
    "sg:province":"Vaud",
    "wof:name":"Impressvit Seidel H.",
    "wof:placetype":"venue"
},
  "geometry": {"coordinates":[6.9421520233,46.9951133728],"type":"Point"}
}