{
  "type": "Feature",
  "properties": {
    "iso:country":"CH",
    "sg:address":"Rigistrasse 6",
    "sg:city":"Zug",
    "sg:orig_category":"Vermietung von Baumaschinen U ger\u00e4ten mit Bedienungspersonal",
    "sg:postcode":"6300",
    "sg:province":"Zug",
    "wof:name":"Cse Crane Service Equipment Ag",
    "wof:placetype":"venue"
},
  "geometry": {"coordinates":[8.5147066116,47.1699905396],"type":"Point"}
}