{
  "type": "Feature",
  "properties": {
    "addr:full":"Place De La Fusterie 7 Gen\u00e8ve Gen\u00e8ve 1204",
    "addr:housenumber":"7",
    "addr:postcode":"1204",
    "addr:street":"Place De La Fusterie",
    "iso:country":"CH",
    "sg:address":"Place De La Fusterie 7",
    "sg:city":"Gen\u00e8ve",
    "sg:orig_category":"Advokaturb\u00fcros",
    "sg:phone":"+41 55 451 50 50",
    "sg:postcode":"1204",
    "sg:province":"Gen\u00e8ve",
    "wof:name":"Onz & Fleischli Advokaturb\u00fcro",
    "wof:placetype":"venue"
},
  "geometry": {"coordinates":[8.854178,47.191624],"type":"Point"}
}