{
  "type": "Feature",
  "properties": {
    "iso:country":"CH",
    "sg:address":"D\u00e4ttlig",
    "sg:city":"Biglen",
    "sg:orig_category":"Pensionskassen",
    "sg:phone":"+41 31 705 23 23",
    "sg:postcode":"3507",
    "sg:province":"Bern",
    "wof:name":"Personalf\u00fcrsorgestiftung Der Fr. Schneider Ag",
    "wof:placetype":"venue"
},
  "geometry": {"coordinates":[7.6258468628,46.9249382019],"type":"Point"}
}