{
  "type": "Feature",
  "properties": {
    "iso:country":"CH",
    "sg:address":"Churerstrasse 1",
    "sg:city":"Altendorf",
    "sg:classifiers":[
        {
            "category":"Travel",
            "subcategory":"Hotels & Motels",
            "type":"Entertainment"
        }
    ],
    "sg:phone":"+41 55 442 11 42",
    "sg:postcode":"8852",
    "sg:province":"Schwyz",
    "sg:tags":[
        "hotels",
        "mit",
        "restaurant"
    ],
    "wof:name":"Landgasthof Rose, Bellmont M. Gasthof",
    "wof:placetype":"venue"
},
  "geometry": {"coordinates":[8.8309183121,47.1923446655],"type":"Point"}
}