{
  "type": "Feature",
  "properties": {
    "iso:country":"CH",
    "sg:address":"Weierlistrasse 2",
    "sg:city":"Dachsen",
    "sg:orig_category":"Sonstige mit Sport verbundene T\u00e4tigkeiten",
    "sg:postcode":"8447",
    "sg:province":"Z\u00fcrich",
    "wof:name":"Rauber Taucharbeiten",
    "wof:placetype":"venue"
},
  "geometry": {"coordinates":[8.6134786606,47.6691474915],"type":"Point"}
}