{
  "type": "Feature",
  "properties": {
    "iso:country":"CH",
    "sg:address":"M\u00fchlebachstr. 72",
    "sg:city":"Z\u00fcrich",
    "sg:classifiers":[
        {
            "category":"Banks & Credit Unions",
            "subcategory":"Bank",
            "type":"Services"
        }
    ],
    "sg:phone":"+41 12523434",
    "sg:postcode":"8032",
    "sg:province":"Z\u00fcrich",
    "wof:name":"Habibsons Bank Ltd",
    "wof:placetype":"venue"
},
  "geometry": {"coordinates":[8.552887,47.362801],"type":"Point"}
}