{
  "type": "Feature",
  "properties": {
    "iso:country":"CH",
    "sg:address":"Hochdorf",
    "sg:city":"Hochdorf",
    "sg:classifiers":[
        {
            "category":"Banks & Credit Unions",
            "subcategory":"Bank",
            "type":"Services"
        }
    ],
    "sg:phone":"+41 4141883322",
    "sg:postcode":"6280",
    "sg:province":"Luzern",
    "wof:name":"Volksbank Hochdorf",
    "wof:placetype":"venue"
},
  "geometry": {"coordinates":[8.28345,47.160542],"type":"Point"}
}