{
  "type": "Feature",
  "properties": {
    "iso:country":"CH",
    "sg:address":"Curt Goetz-strasse 1",
    "sg:city":"Binningen",
    "sg:orig_category":"Interessenvertretungen",
    "sg:postcode":"4102",
    "sg:province":"Basel-Landschaft",
    "wof:name":"Rebbergverein St. Margarethen",
    "wof:placetype":"venue"
},
  "geometry": {"coordinates":[7.5746068954,47.5419158936],"type":"Point"}
}