{
  "type": "Feature",
  "properties": {
    "iso:country":"CH",
    "sg:address":"Saint-l\u00e9ger Rue 24",
    "sg:city":"Gen\u00e8ve",
    "sg:orig_category":"Unclassifiable Establishments",
    "sg:postcode":"1204",
    "sg:province":"Gen\u00e8ve",
    "wof:name":"Listen To The Picture, Nicolas Gisiger",
    "wof:placetype":"venue"
},
  "geometry": {"coordinates":[6.1482348442,46.1991958618],"type":"Point"}
}