{
  "type": "Feature",
  "properties": {
    "iso:country":"CH",
    "sg:address":"Poststrasse 6",
    "sg:city":"Rheineck",
    "sg:orig_category":"Detailhandel mit Waren verschiedener Art, Hauptrichtung Nahrungsmittel Grosshandel mit Nahrungsmitte",
    "sg:phone":"+41 71 888 18 28",
    "sg:postcode":"9424",
    "sg:province":"St. Gallen",
    "wof:name":"Denner Satelit M. Und A. Manis",
    "wof:placetype":"venue"
},
  "geometry": {"coordinates":[9.5897312164,47.4674949646],"type":"Point"}
}