{
  "type": "Feature",
  "properties": {
    "iso:country":"CH",
    "sg:address":"L\u00e4nggasse 14",
    "sg:city":"Biel/bienne",
    "sg:orig_category":"Unclassifiable Establishments",
    "sg:phone":"+41 32 341 72 48",
    "sg:postcode":"2504",
    "sg:province":"Bern",
    "wof:name":"Dtv & Frauenr.biel-b\u00f6zingen",
    "wof:placetype":"venue"
},
  "geometry": {"coordinates":[7.2719531059,47.1550559998],"type":"Point"}
}