{
  "type": "Feature",
  "properties": {
    "iso:country":"CH",
    "sg:address":"Eggiwilstrasse 13",
    "sg:city":"Sch\u00fcpbach",
    "sg:orig_category":"Detailhandel mit Fleisch U Fleischwaren Grosshandel mit lebenden Tieren",
    "sg:phone":"+41 34 497 18 17",
    "sg:postcode":"3535",
    "sg:province":"Bern",
    "wof:name":"K. Rychener",
    "wof:placetype":"venue"
},
  "geometry": {"coordinates":[7.7363138199,46.9260635376],"type":"Point"}
}