{
  "type": "Feature",
  "properties": {
    "iso:country":"CH",
    "sg:address":"Sternengasse 10",
    "sg:city":"Basel",
    "sg:orig_category":"Parf\u00fcmerien U sonstiger Detailhandel mit kosmetischen Artikeln U K\u00f6rperpflegemitteln",
    "sg:phone":"+41 61 272 89 00",
    "sg:postcode":"4051",
    "sg:province":"Basel-Stadt",
    "wof:name":"Impo Import Parf\u00fcmerien Ag",
    "wof:placetype":"venue"
},
  "geometry": {"coordinates":[7.5928149223,47.552028656],"type":"Point"}
}