{
  "type": "Feature",
  "properties": {
    "iso:country":"CH",
    "sg:address":"Chemin Des Dailles 36",
    "sg:city":"Monthey",
    "sg:orig_category":"Malerei Malerei-Gipserei",
    "sg:phone":"+41 56 622 36 26",
    "sg:postcode":"1870",
    "sg:province":"Valais",
    "wof:name":"Bolliger Ag, Malergesch\u00e4ft",
    "wof:placetype":"venue"
},
  "geometry": {"coordinates":[8.2677822113,47.3622398376],"type":"Point"}
}