{
  "type": "Feature",
  "properties": {
    "iso:country":"CH",
    "sg:address":"Frankenstrasse 20 6003 Luzern. Postfach 2632",
    "sg:city":"Luzern",
    "sg:orig_category":"Advokaturb\u00fcros Steuerberatung",
    "sg:phone":"+41 41 210 23 61",
    "sg:postcode":"6002",
    "sg:province":"Luzern",
    "wof:name":"Dr.hans D\u00fcggelin Advokaturb\u00fcro",
    "wof:placetype":"venue"
},
  "geometry": {"coordinates":[8.306909,47.048698],"type":"Point"}
}