{
  "type": "Feature",
  "properties": {
    "iso:country":"CH",
    "sg:address":"1753",
    "sg:city":"Matran",
    "sg:classifiers":[
        {
            "category":"Travel",
            "subcategory":"Hotels & Motels",
            "type":"Entertainment"
        }
    ],
    "sg:phone":"+41 26 402 17 45",
    "sg:postcode":"1753",
    "sg:province":"Fribourg",
    "sg:tags":[
        "hotels",
        "mit",
        "restaurant"
    ],
    "wof:name":"Volery Maurice",
    "wof:placetype":"venue"
},
  "geometry": {"coordinates":[7.0887098312,46.7851715088],"type":"Point"}
}