{
  "type": "Feature",
  "properties": {
    "iso:country":"CH",
    "sg:address":"Industriestrasse 622",
    "sg:city":"Kestenholz",
    "sg:orig_category":"Handel mit Automobilen Handel mit Motorr\u00e4dern, Teilen U Zubeh\u00f6r Instandhaltung U Reparatur von Motor",
    "sg:phone":"+41 62 393 29 88",
    "sg:postcode":"4703",
    "sg:province":"Solothurn",
    "wof:name":"Ackermann Marius",
    "wof:placetype":"venue"
},
  "geometry": {"coordinates":[7.7490859032,47.2797317505],"type":"Point"}
}