{
  "type": "Feature",
  "properties": {
    "iso:country":"CH",
    "sg:address":"Bahnhofstrasse 21",
    "sg:city":"Pratteln",
    "sg:orig_category":"Reiseb\u00fcros U Reiseveranstalter",
    "sg:postcode":"4133",
    "sg:province":"Basel-Landschaft",
    "wof:name":"Wyss Johny Hans Peter",
    "wof:placetype":"venue"
},
  "geometry": {"coordinates":[7.5958781242,47.5016555786],"type":"Point"}
}