{
  "type": "Feature",
  "properties": {
    "iso:country":"CH",
    "sg:address":"Turnhallestrasse 17",
    "sg:city":"Aarwangen",
    "sg:orig_category":"Kosmetikinstitute",
    "sg:phone":"+41 19303737",
    "sg:postcode":"4912",
    "sg:province":"Bern",
    "wof:name":"Renate Geiger Kosmetikinstitut",
    "wof:placetype":"venue"
},
  "geometry": {"coordinates":[8.8040800095,47.3290481567],"type":"Point"}
}