{
  "type": "Feature",
  "properties": {
    "iso:country":"CH",
    "sg:address":"Neusetzi 1 5108 Oberflachs. Postfach",
    "sg:city":"Oberflachs",
    "sg:orig_category":"Unternehmensberatung",
    "sg:postcode":"5108",
    "sg:province":"Aargau",
    "wof:name":"Resultcom Gmbh Beratung, Ausbildung In Den Bereichen Verkauf, Management, Kommunikation Usw",
    "wof:placetype":"venue"
},
  "geometry": {"coordinates":[8.901799202,47.48254776],"type":"Point"}
}