{
  "type": "Feature",
  "properties": {
    "iso:country":"CH",
    "sg:address":"Via Giuseppe Motta 22",
    "sg:city":"Mendrisio",
    "sg:orig_category":"Kosmetikinstitute",
    "sg:phone":"+41 91 646 24 04",
    "sg:postcode":"6850",
    "sg:province":"Ticino",
    "wof:name":"Barbara Pozzi Estetica Barbara",
    "wof:placetype":"venue"
},
  "geometry": {"coordinates":[8.9840373993,45.8686103821],"type":"Point"}
}