{
  "type": "Feature",
  "properties": {
    "iso:country":"CH",
    "sg:address":"Kappeliweg 10/12",
    "sg:city":"Herzogenbuchsee",
    "sg:orig_category":"Erschliessung von Grundst\u00fccken",
    "sg:phone":"+41 17155461",
    "sg:postcode":"3360",
    "sg:province":"Bern",
    "wof:name":"Baugenossenschaft Kilchberg",
    "wof:placetype":"venue"
},
  "geometry": {"coordinates":[8.5391025543,47.3179740906],"type":"Point"}
}