{
  "type": "Feature",
  "properties": {
    "iso:country":"CH",
    "sg:address":"Kreuzstrasse 2",
    "sg:city":"Oftringen",
    "sg:orig_category":"Elektroinstallation Herstellung von Elektromotoren, Generatoren U Transformatoren",
    "sg:phone":"+41 62 797 12 22",
    "sg:postcode":"4665",
    "sg:province":"Aargau",
    "wof:name":"Elektro L\u00fcscher Oftringen Ag",
    "wof:placetype":"venue"
},
  "geometry": {"coordinates":[7.9201917648,47.3131561279],"type":"Point"}
}