{
  "type": "Feature",
  "properties": {
    "iso:country":"CH",
    "sg:address":"Via Molinazzo 4a 6900 Lugano. Postfach",
    "sg:city":"Calprino",
    "sg:orig_category":"Non-Classified Establishments",
    "sg:postcode":"6900",
    "sg:province":"Ticino",
    "wof:name":"Essbee Associates Sa",
    "wof:placetype":"venue"
},
  "geometry": {"coordinates":[8.9645967484,46.0092658997],"type":"Point"}
}