{
  "type": "Feature",
  "properties": {
    "iso:country":"CH",
    "sg:address":"M\u00fchlemoosweg 6a",
    "sg:city":"Oberarth",
    "sg:orig_category":"Handelsvermittlung U Grosshandel",
    "sg:phone":"+41 41 855 13 72",
    "sg:postcode":"6414",
    "sg:province":"Schwyz",
    "wof:name":"Hawart Ag Import & Export",
    "wof:placetype":"venue"
},
  "geometry": {"coordinates":[8.5370569229,47.0566596985],"type":"Point"}
}