{
  "type": "Feature",
  "properties": {
    "iso:country":"CH",
    "sg:address":"Eisenbahnstrasse 19",
    "sg:city":"Einsiedeln",
    "sg:orig_category":"Pensionskassen",
    "sg:postcode":"8840",
    "sg:province":"Schwyz",
    "wof:name":"Personalf\u00fcrsorgestiftung Der Firma Schoch + Hirzel Ag",
    "wof:placetype":"venue"
},
  "geometry": {"coordinates":[8.9308795929,47.3462104797],"type":"Point"}
}