{
  "type": "Feature",
  "properties": {
    "iso:country":"CH",
    "sg:address":"Sot-tga 7",
    "sg:city":"Savognin",
    "sg:orig_category":"Vermietung U Verpachtung von eigenen Immobilien",
    "sg:postcode":"7460",
    "sg:province":"Graubunden",
    "wof:name":"Dundy's Ag.",
    "wof:placetype":"venue"
},
  "geometry": {"coordinates":[9.5944671631,46.5924987793],"type":"Point"}
}