{
  "type": "Feature",
  "properties": {
    "iso:country":"CH",
    "sg:address":"Plong Muling",
    "sg:city":"Domat/ems",
    "sg:orig_category":"Ger\u00fcstbau Sonstiger spezialisierter Hoch U Tiefbau",
    "sg:phone":"+41 79 405 95 90",
    "sg:postcode":"7013",
    "sg:province":"Graubunden",
    "wof:name":"Ger\u00fcstbau Tscharner Rico",
    "wof:placetype":"venue"
},
  "geometry": {"coordinates":[9.4588518143,46.8373641968],"type":"Point"}
}