{
  "type": "Feature",
  "properties": {
    "iso:country":"CH",
    "sg:address":"3638",
    "sg:city":"Blumenstein",
    "sg:orig_category":"Verkehrs- and Tourismusb\u00fcros",
    "sg:phone":"+41 33 356 33 08",
    "sg:postcode":"3638",
    "sg:province":"Bern",
    "wof:name":"Verkehrsverein",
    "wof:placetype":"venue"
},
  "geometry": {"coordinates":[7.5206098557,46.7410163879],"type":"Point"}
}