{
  "type": "Feature",
  "properties": {
    "iso:country":"CH",
    "sg:address":"Obere Dorfstrasse 2",
    "sg:city":"Zezikon",
    "sg:orig_category":"Bauspenglerei Sanit\u00e4rinstallation U Spenglerei",
    "sg:phone":"+41 71 917 17 64",
    "sg:postcode":"9556",
    "sg:province":"Thurgau",
    "wof:name":"Johannes Frei Spenglerei & Kaminbau",
    "wof:placetype":"venue"
},
  "geometry": {"coordinates":[9.020623,47.535336],"type":"Point"}
}