{
  "type": "Feature",
  "properties": {
    "iso:country":"CH",
    "sg:address":"Bernstrasse 12",
    "sg:city":"Fraubrunnen",
    "sg:orig_category":"Sonstiges Versicherungsgewerbe",
    "sg:phone":"+41 31 760 65 65",
    "sg:postcode":"3312",
    "sg:province":"Bern",
    "wof:name":"Schweizerische Mobiliar Versicherungsgesellschaft, Generalagentur Fraubrunnen, Sonderegger Urs",
    "wof:placetype":"venue"
},
  "geometry": {"coordinates":[7.5251898766,47.0851173401],"type":"Point"}
}