{
  "type": "Feature",
  "properties": {
    "iso:country":"CH",
    "sg:address":"Herdern 7",
    "sg:city":"Ennetb\u00fcrgen",
    "sg:orig_category":"Herstellung von sonstigen landwirtschaftlichen Maschinen Mechanische Werkst\u00e4tten",
    "sg:phone":"+41 41 620 41 91",
    "sg:postcode":"6373",
    "sg:province":"Nidwalden",
    "wof:name":"Frank Ag, Marco",
    "wof:placetype":"venue"
},
  "geometry": {"coordinates":[8.3955087662,46.9788818359],"type":"Point"}
}