{
  "type": "Feature",
  "properties": {
    "iso:country":"CH",
    "sg:address":"Weidlistrasse 1",
    "sg:city":"Steinen",
    "sg:orig_category":"Sonderschulen Wohnheime f\u00fcr Kinder U Jugendliche",
    "sg:phone":"+41 41 832 13 15",
    "sg:postcode":"6422",
    "sg:province":"Schwyz",
    "wof:name":"Sprachheilschule",
    "wof:placetype":"venue"
},
  "geometry": {"coordinates":[8.6040973663,47.051109314],"type":"Point"}
}