{
  "type": "Feature",
  "properties": {
    "iso:country":"CH",
    "sg:address":"Bruggerstrasse 137",
    "sg:city":"Baden",
    "sg:orig_category":"D\u00e4mmung gegen K\u00e4lte, W\u00e4rme, Schall U Ersch\u00fctterung Herstellung von sonstigen Metallwaren",
    "sg:phone":"+41 56 221 17 75",
    "sg:postcode":"5400",
    "sg:province":"Aargau",
    "wof:name":"Vasiljko Mitic Fassadenisolationen",
    "wof:placetype":"venue"
},
  "geometry": {"coordinates":[8.2902402878,47.4834136963],"type":"Point"}
}