{
  "type": "Feature",
  "properties": {
    "iso:country":"CH",
    "sg:address":"Dorfstrasse",
    "sg:city":"Saanen",
    "sg:orig_category":"Verkehrs- and Tourismusb\u00fcros",
    "sg:phone":"+41 33 744 66 90",
    "sg:postcode":"3792",
    "sg:province":"Bern",
    "wof:name":"Tourismus Gstaad-saanenland",
    "wof:placetype":"venue"
},
  "geometry": {"coordinates":[7.2864999771,46.4729537964],"type":"Point"}
}