{
  "type": "Feature",
  "properties": {
    "iso:country":"CH",
    "sg:address":"Rue Des Pianos 55",
    "sg:city":"Biel/bienne",
    "sg:classifiers":[
        {
            "category":"Shopping",
            "subcategory":"Jewelry",
            "type":"Retail Goods"
        }
    ],
    "sg:phone":"+41 32 967 97 97",
    "sg:postcode":"2503",
    "sg:province":"Bern",
    "sg:tags":[
        "watch"
    ],
    "wof:name":"Jaquet Sa",
    "wof:placetype":"venue"
},
  "geometry": {"coordinates":[6.841753006,47.1108283997],"type":"Point"}
}