{
  "type": "Feature",
  "properties": {
    "iso:country":"CH",
    "sg:address":"Zuzwilstrasse 12",
    "sg:city":"Jegenstorf",
    "sg:classifiers":[
        {
            "category":"Communications",
            "subcategory":"Radio Station",
            "type":"Services"
        }
    ],
    "sg:phone":"+41 31 762 02 25",
    "sg:postcode":"3303",
    "sg:province":"Bern",
    "sg:tags":[
        "fernsehanstalten",
        "u"
    ],
    "wof:name":"Artification Ag",
    "wof:placetype":"venue"
},
  "geometry": {"coordinates":[7.5039448738,47.0493202209],"type":"Point"}
}