{
  "type": "Feature",
  "properties": {
    "iso:country":"CH",
    "sg:address":"Au Pontet",
    "sg:city":"Remaufens",
    "sg:orig_category":"Herstellung von Konstruktionsteilen, Fertigbauteilen U Ausbauelementen aus Holz",
    "sg:postcode":"1617",
    "sg:province":"Fribourg",
    "wof:name":"Treboux Claude",
    "wof:placetype":"venue"
},
  "geometry": {"coordinates":[6.2361369133,46.4635696411],"type":"Point"}
}