{
  "type": "Feature",
  "properties": {
    "iso:country":"CH",
    "sg:address":"Eichhaldenstrasse 8614 Bertschikon. Postfach",
    "sg:city":"Bertschikon",
    "sg:orig_category":"Vermietung U Verpachtung von eigenen Immobilien",
    "sg:phone":"+41 19352788",
    "sg:postcode":"8614",
    "sg:province":"Z\u00fcrich",
    "wof:name":"Dobler Fridolin A. Consulting",
    "wof:placetype":"venue"
},
  "geometry": {"coordinates":[8.7597923279,47.3238563538],"type":"Point"}
}