{
  "type": "Feature",
  "properties": {
    "iso:country":"CH",
    "sg:address":"Sennereistrasse 91",
    "sg:city":"Schaffhausen",
    "sg:orig_category":"Fahrschulen, Flugschulen",
    "sg:phone":"+41 52 643 32 66",
    "sg:postcode":"8200",
    "sg:province":"Schaffhausen",
    "wof:name":"Willi Kolb Fahrschule",
    "wof:placetype":"venue"
},
  "geometry": {"coordinates":[8.6494417191,47.7149887085],"type":"Point"}
}