{
  "type": "Feature",
  "properties": {
    "iso:country":"CH",
    "sg:address":"Reichenauerstr.",
    "sg:city":"Domat/ems",
    "sg:classifiers":[
        {
            "category":"Manufacturing",
            "subcategory":"Chemicals & Compounds",
            "type":"Manufacturing & Wholesale Goods"
        }
    ],
    "sg:phone":"+41 81 632 61 11",
    "sg:postcode":"7013",
    "sg:province":"Graubunden",
    "sg:tags":[
        "pharmaceutical",
        "chemistry"
    ],
    "wof:name":"Ems-chemie Ag",
    "wof:placetype":"venue"
},
  "geometry": {"coordinates":[9.444345,46.832298],"type":"Point"}
}