{
  "type": "Feature",
  "properties": {
    "iso:country":"CH",
    "sg:address":"Industriestrasse 1 4922 B\u00fctzberg. Postfach 132",
    "sg:city":"B\u00fctzberg",
    "sg:orig_category":"Elektroinstallation Herstellung von Elektrizit\u00e4tsverteilungs U schalteinrichtungen",
    "sg:phone":"+41 71 971 33 30",
    "sg:postcode":"4922",
    "sg:province":"Bern",
    "wof:name":"Miesch Elektro Gmbh",
    "wof:placetype":"venue"
},
  "geometry": {"coordinates":[8.9627552032,47.4631996155],"type":"Point"}
}