{
  "type": "Feature",
  "properties": {
    "iso:country":"CH",
    "sg:address":"8514",
    "sg:city":"Griesenberg",
    "sg:orig_category":"Landw. Genossenschaften Viehzucht",
    "sg:postcode":"8514",
    "sg:province":"Thurgau",
    "wof:name":"Braunviehzuchtgenossenschaft Griesenberg-harenwilen & Umg.",
    "wof:placetype":"venue"
},
  "geometry": {"coordinates":[9.0137195587,47.5678787231],"type":"Point"}
}