{
  "type": "Feature",
  "properties": {
    "iso:country":"CH",
    "sg:address":"La Capite",
    "sg:city":"F\u00e9chy",
    "sg:orig_category":"Sonstiger Grosshandel",
    "sg:postcode":"1173",
    "sg:province":"Vaud",
    "wof:name":"The Nordic Company S\u00e0rl",
    "wof:placetype":"venue"
},
  "geometry": {"coordinates":[6.3701400757,46.4815368652],"type":"Point"}
}