{
  "type": "Feature",
  "properties": {
    "iso:country":"CH",
    "sg:address":"Hammerstrasse 93",
    "sg:city":"Z\u00fcrich",
    "sg:orig_category":"Religi\u00f6se Vereinigungen divers",
    "sg:postcode":"8032",
    "sg:province":"Z\u00fcrich",
    "wof:name":"Freimaurerloge Fgl",
    "wof:placetype":"venue"
},
  "geometry": {"coordinates":[8.5659160614,47.3599014282],"type":"Point"}
}