{
  "type": "Feature",
  "properties": {
    "iso:country":"CH",
    "sg:address":"Chamerstrasse 30",
    "sg:city":"Zug",
    "sg:orig_category":"Unternehmensberatung",
    "sg:phone":"+41 41 710 77 73",
    "sg:postcode":"6300",
    "sg:province":"Zug",
    "wof:name":"R\u00fcfenacht H.p. Unternehmensberatung",
    "wof:placetype":"venue"
},
  "geometry": {"coordinates":[8.5089349747,47.1728401184],"type":"Point"}
}