{
  "type": "Feature",
  "properties": {
    "iso:country":"CH",
    "sg:address":"Allmendstrasse 8",
    "sg:city":"Fehraltorf",
    "sg:orig_category":"Grosshandel mit Flachglas, Sanit\u00e4rkeramik U Anstrichmitteln Grosshandel mit sonstigen Halbwaren",
    "sg:phone":"+41 71 666 77 92",
    "sg:postcode":"8320",
    "sg:province":"Z\u00fcrich",
    "wof:name":"Braendle & Partner Acrylglas",
    "wof:placetype":"venue"
},
  "geometry": {"coordinates":[8.7439899445,47.391166687],"type":"Point"}
}