{
  "type": "Feature",
  "properties": {
    "iso:country":"CH",
    "sg:address":"8352",
    "sg:city":"R\u00e4terschen",
    "sg:orig_category":"Abwasserreinigung",
    "sg:phone":"+41 52 363 19 70",
    "sg:postcode":"8352",
    "sg:province":"Z\u00fcrich",
    "wof:name":"Kl\u00e4ranlage",
    "wof:placetype":"venue"
},
  "geometry": {"coordinates":[8.793205,47.49881],"type":"Point"}
}