{
  "type": "Feature",
  "properties": {
    "iso:country":"CH",
    "sg:address":"Alte Steinhauserstrasse 19",
    "sg:city":"Cham",
    "sg:orig_category":"Handelsvermittlung U Grosshandel Sonstiger Grosshandel",
    "sg:phone":"+41 26 493 50 00",
    "sg:postcode":"6330",
    "sg:province":"Zug",
    "wof:name":"Neutromedics Ag",
    "wof:placetype":"venue"
},
  "geometry": {"coordinates":[8.4743642807,47.1882553101],"type":"Point"}
}