{
  "type": "Feature",
  "properties": {
    "iso:country":"CH",
    "sg:address":"Premier-mars Avenue Du 18",
    "sg:city":"Neuch\u00e2tel",
    "sg:orig_category":"Allgemeiner Hoch U Tiefbau",
    "sg:postcode":"2000",
    "sg:province":"Neuch\u00e2tel",
    "wof:name":"Construction Montblanc, Talaia Alex Entreprise De Construction, Notamm. Gros Oeuvre",
    "wof:placetype":"venue"
},
  "geometry": {"coordinates":[6.55807,46.510078],"type":"Point"}
}