{
  "type": "Feature",
  "properties": {
    "iso:country":"CH",
    "sg:address":"Hopfenweg 18",
    "sg:city":"Bern",
    "sg:orig_category":"Kinderkrippen U horte",
    "sg:phone":"+41 31 371 72 74",
    "sg:postcode":"3007",
    "sg:province":"Bern",
    "wof:name":"Kinderkrippe Kinderhaus Elfenau",
    "wof:placetype":"venue"
},
  "geometry": {"coordinates":[7.4271159172,46.9416351318],"type":"Point"}
}