{
  "type": "Feature",
  "properties": {
    "iso:country":"CH",
    "sg:address":"Chrischonaweg 307",
    "sg:city":"Rafz",
    "sg:orig_category":"Fotografisches Gewerbe U fotografische Laboratorien",
    "sg:postcode":"8197",
    "sg:province":"Z\u00fcrich",
    "wof:name":"Foto-studio Beetschen, Fsb",
    "wof:placetype":"venue"
},
  "geometry": {"coordinates":[8.5391902924,47.6116905212],"type":"Point"}
}