{
  "type": "Feature",
  "properties": {
    "iso:country":"CH",
    "sg:address":"Rue Centrale 1884 Villars-sur-ollon Case Postale 213",
    "sg:city":"Villars-sur-ollon",
    "sg:orig_category":"HOTELS: MIT RESTAURANT Kongress- and Tagungshotels mit Restaurant",
    "sg:phone":"+41 24 492 26 53",
    "sg:postcode":"1884",
    "sg:province":"Vaud",
    "wof:name":"H\u00f4tel Le Chamois",
    "wof:placetype":"venue"
},
  "geometry": {"coordinates":[7.1587100029,46.3500404358],"type":"Point"}
}