{
  "type": "Feature",
  "properties": {
    "iso:country":"CH",
    "sg:address":"6997",
    "sg:city":"Sessa",
    "sg:orig_category":"Detailhandel mit Waren verschiedener Art, Hauptrichtung Nahrungsmittel",
    "sg:phone":"+41 91 608 12 74",
    "sg:postcode":"6997",
    "sg:province":"Ticino",
    "wof:name":"Coop Ticino",
    "wof:placetype":"venue"
},
  "geometry": {"coordinates":[8.8117704391,46.0023994446],"type":"Point"}
}