{
  "type": "Feature",
  "properties": {
    "iso:country":"CH",
    "sg:address":"Steinenvorstadt 77",
    "sg:city":"Basel",
    "sg:orig_category":"Kosmetikinstitute",
    "sg:phone":"+41 61 281 53 73",
    "sg:postcode":"4051",
    "sg:province":"Basel-Stadt",
    "wof:name":"Institut De Beaut\u00e9 Jolie D. Grob",
    "wof:placetype":"venue"
},
  "geometry": {"coordinates":[7.587348938,47.5513114929],"type":"Point"}
}