{
  "type": "Feature",
  "properties": {
    "iso:country":"CH",
    "sg:address":"Foss\u00e9s Rue Des 27 1110 Morges. Postfach",
    "sg:city":"Morges",
    "sg:orig_category":"Herstellung von W\u00e4sche",
    "sg:phone":"+41 21 803 25 31",
    "sg:postcode":"1110",
    "sg:province":"Vaud",
    "wof:name":"Freestyle S\u00e0rl Boutique De V\u00eatements, Plus Sp\u00e9c. Destin\u00e9e Aux Enfants Etc",
    "wof:placetype":"venue"
},
  "geometry": {"coordinates":[6.4987850189,46.5085639954],"type":"Point"}
}