{
  "type": "Feature",
  "properties": {
    "iso:country":"CH",
    "sg:address":"Forchstrasse 145 8032 Z\u00fcrich. Postfach",
    "sg:city":"Z\u00fcrich",
    "sg:orig_category":"Interessenvertretungen U sonstige Vereinigungen Organisationen der Wohlfahrtspflege",
    "sg:phone":"+41 14215151",
    "sg:postcode":"8032",
    "sg:province":"Z\u00fcrich",
    "wof:name":"Pro Senectute Z\u00fcrich",
    "wof:placetype":"venue"
},
  "geometry": {"coordinates":[8.5636501312,47.3606414795],"type":"Point"}
}