{
  "type": "Feature",
  "properties": {
    "iso:country":"CH",
    "sg:address":"Coppet Rue Du 18 1870 Monthey. Postfach",
    "sg:city":"Monthey",
    "sg:orig_category":"Dienstleistungen von Beteiligungsgesellschaften",
    "sg:phone":"+41 24 471 44 11",
    "sg:postcode":"1870",
    "sg:province":"Valais",
    "wof:name":"Garenne Sa",
    "wof:placetype":"venue"
},
  "geometry": {"coordinates":[6.9511289597,46.2528343201],"type":"Point"}
}