{
  "type": "Feature",
  "properties": {
    "addr:full":"Seestrasse 1 Fl\u00fcelen Uri 6454",
    "addr:housenumber":"1",
    "addr:postcode":"6454",
    "addr:street":"Seestrasse;Uri",
    "iso:country":"CH",
    "sg:address":"Seestrasse 1",
    "sg:city":"Fl\u00fcelen",
    "sg:orig_category":"Binnenschiffahrt Fachdetailhandel in Verkaufsr\u00e4umen",
    "sg:phone":"+41 71 333 22 20",
    "sg:postcode":"6454",
    "sg:province":"Uri",
    "wof:name":"Rigoletto-yachting Ag",
    "wof:placetype":"venue"
},
  "geometry": {"coordinates":[9.362168,47.386242],"type":"Point"}
}