{
  "type": "Feature",
  "properties": {
    "iso:country":"CH",
    "sg:address":"Hausmattstrasse 24",
    "sg:city":"Langenthal",
    "sg:classifiers":[
        {
            "category":"Professional",
            "subcategory":"Employment Agencies",
            "type":"Services"
        }
    ],
    "sg:phone":"+41 62 923 82 83",
    "sg:postcode":"4900",
    "sg:province":"Bern",
    "sg:tags":[
        "personal",
        "u",
        "stellenvermittlung"
    ],
    "wof:name":"Pm Personalmarketing Gmbh",
    "wof:placetype":"venue"
},
  "geometry": {"coordinates":[7.7747721672,47.2121009827],"type":"Point"}
}