{
  "type": "Feature",
  "properties": {
    "iso:country":"CH",
    "sg:address":"Haus 53 A",
    "sg:city":"Donath",
    "sg:orig_category":"G\u00fcterbef\u00f6rderung im Strassenverkehr",
    "sg:phone":"+41 81 661 11 68",
    "sg:postcode":"7433",
    "sg:province":"Graubunden",
    "wof:name":"Cantieni, Transporte + Garage",
    "wof:placetype":"venue"
},
  "geometry": {"coordinates":[9.4082431793,46.6270637512],"type":"Point"}
}