{
  "type": "Feature",
  "properties": {
    "iso:country":"CH",
    "sg:address":"Via Codeborgo 10",
    "sg:city":"Bellinzona",
    "sg:orig_category":"Detailhandel mit Brillen U anderen Sehhilfen Detailhandel mit medizinischen U orthop\u00e4dischen Artikel",
    "sg:phone":"+41 91 835 45 30",
    "sg:postcode":"6500",
    "sg:province":"Ticino",
    "wof:name":"M&m Acustica Sa",
    "wof:placetype":"venue"
},
  "geometry": {"coordinates":[9.023664,46.192493],"type":"Point"}
}