{
  "type": "Feature",
  "properties": {
    "iso:country":"CH",
    "sg:address":"Kirchstrasse 12-14",
    "sg:city":"Spreitenbach",
    "sg:orig_category":"Herstellung von medizinischen U chirurgischen Ger\u00e4ten sowie orthop\u00e4dischen Vorrichtungen Zahntechnis",
    "sg:phone":"+41 56 401 52 25",
    "sg:postcode":"8957",
    "sg:province":"Aargau",
    "wof:name":"Dental Labor Huber Und Waser Gmbh",
    "wof:placetype":"venue"
},
  "geometry": {"coordinates":[8.3653898239,47.4173278809],"type":"Point"}
}