{
  "type": "Feature",
  "properties": {
    "iso:country":"CH",
    "sg:address":"Hegi",
    "sg:city":"Winden",
    "sg:orig_category":"Zimmerei, Dachdeckerei, Bauspenglerei U Abdichtung",
    "sg:phone":"+41 71 477 22 63",
    "sg:postcode":"9315",
    "sg:province":"Thurgau",
    "wof:name":"Mannhart-holzbau Ag",
    "wof:placetype":"venue"
},
  "geometry": {"coordinates":[9.3692731857,47.5288887024],"type":"Point"}
}