{
  "type": "Feature",
  "properties": {
    "iso:country":"CH",
    "sg:address":"R\u00fcttelerweg 4",
    "sg:city":"Bolligen",
    "sg:orig_category":"Bauschreinerei Zimmerei",
    "sg:phone":"+41 31 921 64 38",
    "sg:postcode":"3065",
    "sg:province":"Bern",
    "wof:name":"Herzog Bau & Holzbau Ag",
    "wof:placetype":"venue"
},
  "geometry": {"coordinates":[7.504986,46.981979],"type":"Point"}
}