{
  "type": "Feature",
  "properties": {
    "iso:country":"CH",
    "sg:address":"Oberfeld",
    "sg:city":"Root",
    "sg:orig_category":"Detailhandel Reparatur von Gebrauchsg\u00fctern",
    "sg:phone":"+41 41 450 00 40",
    "sg:postcode":"6037",
    "sg:province":"Luzern",
    "wof:name":"Erotik Markt",
    "wof:placetype":"venue"
},
  "geometry": {"coordinates":[8.376660347,47.1031494141],"type":"Point"}
}