{
  "type": "Feature",
  "properties": {
    "iso:country":"CH",
    "sg:address":"Bankstrasse 20",
    "sg:city":"Niederuzwil",
    "sg:classifiers":[
        {
            "category":"Restaurant",
            "type":"Food & Drink"
        }
    ],
    "sg:phone":"+41 71 951 51 94",
    "sg:postcode":"9244",
    "sg:province":"St. Gallen",
    "wof:name":"Restaurant Eintracht",
    "wof:placetype":"venue"
},
  "geometry": {"coordinates":[9.139251709,47.4484672546],"type":"Point"}
}