{
  "type": "Feature",
  "properties": {
    "iso:country":"CH",
    "sg:address":"Via Belvedere 3 6952 Canobbio. Postfach",
    "sg:city":"Canobbio",
    "sg:orig_category":"Unclassifiable Establishments",
    "sg:postcode":"6952",
    "sg:province":"Ticino",
    "wof:name":"Bachmann Fredy Giardini-tennis Sa",
    "wof:placetype":"venue"
},
  "geometry": {"coordinates":[8.9687509537,46.0299186707],"type":"Point"}
}