{
  "type": "Feature",
  "properties": {
    "iso:country":"CH",
    "sg:address":"Farnsburgerstrasse 37",
    "sg:city":"Basel",
    "sg:orig_category":"Detailhandel mit Waren verschiedener Art, Hauptrichtung Nahrungsmittel",
    "sg:phone":"+41 61 311 32 22",
    "sg:postcode":"4052",
    "sg:province":"Basel-Stadt",
    "wof:name":"Coop Breite",
    "wof:placetype":"venue"
},
  "geometry": {"coordinates":[7.6137528419,47.5552062988],"type":"Point"}
}