{
  "type": "Feature",
  "properties": {
    "iso:country":"CH",
    "sg:address":"Grundstrasse 242",
    "sg:city":"Kirchleerau",
    "sg:classifiers":[
        {
            "category":"Wholesale",
            "subcategory":"Chemicals & Plastics",
            "type":"Manufacturing & Wholesale Goods"
        }
    ],
    "sg:phone":"+41 62 726 15 41",
    "sg:postcode":"5054",
    "sg:province":"Aargau",
    "sg:tags":[
        "pipe",
        "industrial",
        "cleaning"
    ],
    "wof:name":"Kanalifant Adrian Hunziker",
    "wof:placetype":"venue"
},
  "geometry": {"coordinates":[8.0689067841,47.273601532],"type":"Point"}
}