{
  "type": "Feature",
  "properties": {
    "iso:country":"CH",
    "sg:address":"Rue Comble Emine 1",
    "sg:city":"Cernier",
    "sg:orig_category":"Bauspenglerei Dachdeckerei",
    "sg:phone":"+41 32 853 70 10",
    "sg:postcode":"2053",
    "sg:province":"Neuch\u00e2tel",
    "wof:name":"Cavaler Claudio",
    "wof:placetype":"venue"
},
  "geometry": {"coordinates":[6.901439,47.057991],"type":"Point"}
}