{
  "type": "Feature",
  "properties": {
    "iso:country":"CH",
    "sg:address":"Wispel",
    "sg:city":"Grabs",
    "sg:orig_category":"Mahl U Sch\u00e4lm\u00fchlen",
    "sg:phone":"+41 56 241 11 10",
    "sg:postcode":"9472",
    "sg:province":"St. Gallen",
    "wof:name":"Suter M\u00fchlen Ag",
    "wof:placetype":"venue"
},
  "geometry": {"coordinates":[8.3312911987,47.5197525024],"type":"Point"}
}