{
  "type": "Feature",
  "properties": {
    "iso:country":"CH",
    "sg:address":"Via Campaccio 4",
    "sg:city":"Mendrisio",
    "sg:orig_category":"Grosshandel mit Erzen U Metallen Grosshandel mit Schmuck",
    "sg:postcode":"6850",
    "sg:province":"Ticino",
    "wof:name":"Arteoro Sa",
    "wof:placetype":"venue"
},
  "geometry": {"coordinates":[8.9773588181,45.8925895691],"type":"Point"}
}