{
  "type": "Feature",
  "properties": {
    "addr:full":"Tirage Avenue Du 7 1009 Pully. Postfach Pully Vaud 1009",
    "addr:postcode":"1009;postfach;1009",
    "addr:street":"Tirage Avenue Du 7",
    "iso:country":"CH",
    "sg:address":"Tirage Avenue Du 7 1009 Pully. Postfach",
    "sg:city":"Pully",
    "sg:orig_category":"Architektur U Ingenieurb\u00fcros",
    "sg:postcode":"1009",
    "sg:province":"Vaud",
    "wof:name":"Wyler Hp., Technisches B\u00fcro",
    "wof:placetype":"venue"
},
  "geometry": {"coordinates":[8.9413,47.28841],"type":"Point"}
}