{
  "type": "Feature",
  "properties": {
    "iso:country":"CH",
    "sg:address":"Via Cantonale 13 6900 Lugano. Postfach Caselle Postale 2911",
    "sg:city":"Lugano",
    "sg:orig_category":"Verwaltung von Immobilien Wirtschaftspr\u00fcfung, Steuerberatung U Treuhand",
    "sg:phone":"+41 91 913 70 50",
    "sg:postcode":"6901",
    "sg:province":"Ticino",
    "wof:name":"Fiduciaria Taddei Sa",
    "wof:placetype":"venue"
},
  "geometry": {"coordinates":[8.9501237869,46.0081596375],"type":"Point"}
}