{
  "type": "Feature",
  "properties": {
    "iso:country":"CH",
    "sg:address":"Chemin Du Paradis 1",
    "sg:city":"Blonay",
    "sg:orig_category":"Beherbergungsgewerbe",
    "sg:phone":"+41 26 927 18 09",
    "sg:postcode":"1807",
    "sg:province":"Vaud",
    "wof:name":"Cologestion S\u00e0rl",
    "wof:placetype":"venue"
},
  "geometry": {"coordinates":[7.164164,46.619221],"type":"Point"}
}