{
  "type": "Feature",
  "properties": {
    "iso:country":"CH",
    "sg:address":"3945",
    "sg:city":"Gampel",
    "sg:orig_category":"Bezirks, Sekundar, Realschulen, Oberstufe der Primarschulen",
    "sg:postcode":"3945",
    "sg:province":"Valais",
    "wof:name":"Orientierungsschule Regionalschulhaus",
    "wof:placetype":"venue"
},
  "geometry": {"coordinates":[7.744009,46.316509],"type":"Point"}
}