{
  "type": "Feature",
  "properties": {
    "iso:country":"CH",
    "sg:address":"Feldeggstrasse 65 8008 Z\u00fcrich. Postfach",
    "sg:city":"Z\u00fcrich",
    "sg:orig_category":"Wirtschaftspr\u00fcfung, Steuerberatung U Treuhand",
    "sg:phone":"+41 13831120",
    "sg:postcode":"8008",
    "sg:province":"Z\u00fcrich",
    "wof:name":"Kontrofina Ag F\u00fcr Kontroll Und Finanzgesch\u00e4fte",
    "wof:placetype":"venue"
},
  "geometry": {"coordinates":[8.5537481308,47.361125946],"type":"Point"}
}