{
  "type": "Feature",
  "properties": {
    "iso:country":"CH",
    "sg:address":"Avenue Du Rothorn 22",
    "sg:city":"Sierre",
    "sg:orig_category":"Zahnarztpraxen",
    "sg:phone":"+41 27 455 30 37",
    "sg:postcode":"3960",
    "sg:province":"Valais",
    "wof:name":"Dr M\u00e9d. Dent. Serge Roh M\u00e9decin-dentiste",
    "wof:placetype":"venue"
},
  "geometry": {"coordinates":[7.5313057899,46.2935829163],"type":"Point"}
}