{
  "type": "Feature",
  "properties": {
    "iso:country":"CH",
    "sg:address":"Funtanella 2",
    "sg:city":"Samedan",
    "sg:orig_category":"Sportvereine Renn-& Reitsport",
    "sg:postcode":"7503",
    "sg:province":"Graubunden",
    "wof:name":"Pferdesportgenossenschaft St.moritz",
    "wof:placetype":"venue"
},
  "geometry": {"coordinates":[9.8680830002,46.532623291],"type":"Point"}
}