{
  "type": "Feature",
  "properties": {
    "iso:country":"CH",
    "sg:address":"Alte Steinhauserstrasse 15",
    "sg:city":"Cham",
    "sg:orig_category":"Bauschreinerei Herstellung von K\u00fcchenm\u00f6beln",
    "sg:phone":"+41 41 743 01 40",
    "sg:postcode":"6330",
    "sg:province":"Zug",
    "wof:name":"Kilian Huwyler K\u00fcchenbau & Kundenschreiner",
    "wof:placetype":"venue"
},
  "geometry": {"coordinates":[8.474197,47.187653],"type":"Point"}
}