{
  "type": "Feature",
  "properties": {
    "iso:country":"CH",
    "sg:address":"Thomas Bornhauserstrasse 18",
    "sg:city":"Weinfelden",
    "sg:orig_category":"Bezirks, Sekundar, Realschulen, Oberstufe der Primarschulen",
    "sg:phone":"+41 79 328 40 17",
    "sg:postcode":"8570",
    "sg:province":"Thurgau",
    "wof:name":"Sekundarschule",
    "wof:placetype":"venue"
},
  "geometry": {"coordinates":[9.113129,47.566345],"type":"Point"}
}