{
  "type": "Feature",
  "properties": {
    "iso:country":"CH",
    "sg:address":"Lutertalstrasse 53",
    "sg:city":"Bolligen",
    "sg:orig_category":"Erschliessung von Grundst\u00fccken",
    "sg:postcode":"3065",
    "sg:province":"Bern",
    "wof:name":"Wohnbaugenossenschaft R\u00fcti, Oberwil",
    "wof:placetype":"venue"
},
  "geometry": {"coordinates":[7.5416588783,47.5081825256],"type":"Point"}
}