{
  "type": "Feature",
  "properties": {
    "iso:country":"CH",
    "sg:address":"Zw\u00fcscheteich 8153 R\u00fcmlang. Postfach",
    "sg:city":"R\u00fcmlang",
    "sg:orig_category":"Sonstiger spezialisierter Hoch U Tiefbau",
    "sg:phone":"+41 18172075",
    "sg:postcode":"8153",
    "sg:province":"Z\u00fcrich",
    "wof:name":"Tar - Tankanlage R\u00fcmlang Ag",
    "wof:placetype":"venue"
},
  "geometry": {"coordinates":[8.5300750732,47.4530143738],"type":"Point"}
}