{
  "type": "Feature",
  "properties": {
    "iso:country":"CH",
    "sg:address":"Reinacherstrasse 271",
    "sg:city":"Basel",
    "sg:orig_category":"Herstellung von Nahrungsmitteln undGetr\u00e4nken Herstellung von sonstigen organischen Grundstoffen U Ch",
    "sg:phone":"+41 71 686 55 55",
    "sg:postcode":"4053",
    "sg:province":"Basel-Stadt",
    "wof:name":"Meyhall Ag",
    "wof:placetype":"venue"
},
  "geometry": {"coordinates":[9.1917448044,47.6445655823],"type":"Point"}
}