{
  "type": "Feature",
  "properties": {
    "iso:country":"CH",
    "sg:address":"Pr\u00e9 De La Croix 44",
    "sg:city":"Orsonnens",
    "sg:orig_category":"G\u00fcterbef\u00f6rderung im Strassenverkehr",
    "sg:phone":"+41 26 653 16 34",
    "sg:postcode":"1693",
    "wof:name":"Papaux Fr\u00e8res Sa",
    "wof:placetype":"venue"
},
  "geometry": {"coordinates":[6.9952511787,46.7164039612],"type":"Point"}
}