{
  "type": "Feature",
  "properties": {
    "iso:country":"CH",
    "sg:address":"Bahnhofstrasse 92",
    "sg:city":"Wettingen",
    "sg:orig_category":"Arztpraxen",
    "sg:phone":"+41 56 426 33 56",
    "sg:postcode":"5430",
    "sg:province":"Aargau",
    "wof:name":"Dr.med.heinz Gehring Spezialarzt Fmh",
    "wof:placetype":"venue"
},
  "geometry": {"coordinates":[8.328813,47.464596],"type":"Point"}
}