{
  "type": "Feature",
  "properties": {
    "iso:country":"CH",
    "sg:address":"En Vernancy A",
    "sg:city":"Villars-le-terroir",
    "sg:orig_category":"Grosshandel mit H\u00e4uten, Fellen U Leder",
    "sg:postcode":"1040",
    "sg:province":"Vaud",
    "wof:name":"Schopfer Patrick Produits En Cuir; Repr\u00e9sentation",
    "wof:placetype":"venue"
},
  "geometry": {"coordinates":[6.6343631744,46.6408653259],"type":"Point"}
}