{
  "type": "Feature",
  "properties": {
    "iso:country":"CH",
    "sg:address":"Bulle",
    "sg:city":"Bulle",
    "sg:classifiers":[
        {
            "category":"Banks & Credit Unions",
            "subcategory":"Bank",
            "type":"Services"
        }
    ],
    "sg:phone":"+41 2928686",
    "sg:postcode":"1630",
    "sg:province":"Fribourg",
    "wof:name":"Banque De L'etat De Fribourg",
    "wof:placetype":"venue"
},
  "geometry": {"coordinates":[7.0232,46.607079],"type":"Point"}
}