{
  "type": "Feature",
  "properties": {
    "iso:country":"CH",
    "sg:address":"Rautihalde 15",
    "sg:city":"Z\u00fcrich",
    "sg:orig_category":"HERSTELLUNG VON GER\u00c4TEN DER ELEKTRIZIT\u00c4TSERZEUGUNG, -VERTEILUNG U.\u00c4 Herstellung von Metallerzeugniss",
    "sg:phone":"+41 14315983",
    "sg:postcode":"8048",
    "sg:province":"Z\u00fcrich",
    "wof:name":"Ks-mikrotype Ag Mikro-datentr\u00e4ger F. D. Grafische Industrie; Entw., Fabr., Handel",
    "wof:placetype":"venue"
},
  "geometry": {"coordinates":[8.4745759964,47.3871688843],"type":"Point"}
}