{
  "type": "Feature",
  "properties": {
    "iso:country":"CH",
    "sg:address":"Schulstrasse 20",
    "sg:city":"R\u00fcmlang",
    "sg:orig_category":"Instandhaltung U Reparatur von Automobilen",
    "sg:phone":"+41 18170931",
    "sg:postcode":"8153",
    "sg:province":"Z\u00fcrich",
    "wof:name":"Spritzwerk Pfenninger Rolf",
    "wof:placetype":"venue"
},
  "geometry": {"coordinates":[8.5317401886,47.4519615173],"type":"Point"}
}