{
  "type": "Feature",
  "properties": {
    "iso:country":"CH",
    "sg:address":"Kurhausstrasse 65 8000 Z\u00fcrich. Postfach 337",
    "sg:city":"Z\u00fcrich",
    "sg:orig_category":"Pensionskassen",
    "sg:postcode":"8030",
    "wof:name":"Wohlfahrtsfonds Der Dolder Hotel Ag",
    "wof:placetype":"venue"
},
  "geometry": {"coordinates":[8.574180603,47.3724937439],"type":"Point"}
}