{
  "type": "Feature",
  "properties": {
    "iso:country":"CH",
    "sg:address":"Aegertenstrasse 1a 2562 Port. Postfach",
    "sg:city":"Port",
    "sg:orig_category":"Herstellung von Kunststoffwaren Herstellung von sonstigen Kunststoffwaren",
    "sg:phone":"+41 52 385 25 13",
    "sg:postcode":"2562",
    "sg:province":"Bern",
    "wof:name":"Formtech Ag",
    "wof:placetype":"venue"
},
  "geometry": {"coordinates":[8.8460283279,47.4196014404],"type":"Point"}
}