{
  "type": "Feature",
  "properties": {
    "addr:full":"T\u00e4sch T\u00e4sch Valais 3929",
    "addr:postcode":"3929",
    "iso:country":"CH",
    "sg:address":"T\u00e4sch",
    "sg:city":"T\u00e4sch",
    "sg:classifiers":[
        {
            "category":"Banks & Credit Unions",
            "subcategory":"Bank",
            "type":"Services"
        }
    ],
    "sg:phone":"+41 27 967 24 35",
    "sg:postcode":"3929",
    "sg:province":"Valais",
    "wof:name":"Raiffeisenbank",
    "wof:placetype":"venue"
},
  "geometry": {"coordinates":[7.776325,46.069695],"type":"Point"}
}