{
  "type": "Feature",
  "properties": {
    "iso:country":"CH",
    "sg:address":"Stadelmattenstrasse",
    "sg:city":"Raron",
    "sg:orig_category":"Granit",
    "sg:phone":"+41 24 499 14 13",
    "sg:postcode":"3942",
    "sg:province":"Valais",
    "wof:name":"Camandona Sa, Succursale De St-triphon",
    "wof:placetype":"venue"
},
  "geometry": {"coordinates":[6.9953799248,46.2966117859],"type":"Point"}
}