{
  "type": "Feature",
  "properties": {
    "iso:country":"CH",
    "sg:address":"Rappoltshof 3",
    "sg:city":"Basel",
    "sg:orig_category":"Markt U Meinungsforschung",
    "sg:postcode":"4057",
    "sg:province":"Basel-Stadt",
    "wof:name":"Trendmark Gmbh",
    "wof:placetype":"venue"
},
  "geometry": {"coordinates":[7.5928030014,47.5629882812],"type":"Point"}
}