{
  "type": "Feature",
  "properties": {
    "iso:country":"CH",
    "sg:address":"Loh",
    "sg:city":"Balterswil",
    "sg:classifiers":[
        {
            "category":"Restaurant",
            "type":"Food & Drink"
        }
    ],
    "sg:phone":"+41 19324583",
    "sg:postcode":"8362",
    "sg:province":"Thurgau",
    "wof:name":"Restaurant Morgental",
    "wof:placetype":"venue"
},
  "geometry": {"coordinates":[8.7868099213,47.3309936523],"type":"Point"}
}