{
  "type": "Feature",
  "properties": {
    "iso:country":"CH",
    "sg:address":"Rue De La Libert\u00e9 13",
    "sg:city":"Develier",
    "sg:orig_category":"G\u00fcterbef\u00f6rderung im Strassenverkehr",
    "sg:phone":"+41 32 422 02 15",
    "sg:postcode":"2802",
    "sg:province":"Jura",
    "wof:name":"John Hanser Transports",
    "wof:placetype":"venue"
},
  "geometry": {"coordinates":[7.2956628799,47.3575286865],"type":"Point"}
}