{
  "type": "Feature",
  "properties": {
    "addr:full":"Viale Filippo Reina Agno Ticino 6982",
    "addr:postcode":"6982",
    "addr:street":"Viale Filippo Reina",
    "iso:country":"CH",
    "sg:address":"Viale Filippo Reina",
    "sg:city":"Agno",
    "sg:orig_category":"Architektur U Ingenieurb\u00fcros Vermittlung von Immobilien",
    "sg:phone":"+41 79 423 69 24",
    "sg:postcode":"6982",
    "sg:province":"Ticino",
    "wof:name":"Immoprogetti Sa",
    "wof:placetype":"venue"
},
  "geometry": {"coordinates":[8.899555,45.996456],"type":"Point"}
}