{
  "type": "Feature",
  "properties": {
    "iso:country":"CH",
    "sg:address":"Konstanzerstrasse 40",
    "sg:city":"Kreuzlingen",
    "sg:orig_category":"Sonstige Kultur U Unterhaltungseinrichtungen",
    "sg:phone":"+41 71 672 89 83",
    "sg:postcode":"8280",
    "sg:province":"Thurgau",
    "wof:name":"Jugendtreff",
    "wof:placetype":"venue"
},
  "geometry": {"coordinates":[9.1656866074,47.6520195007],"type":"Point"}
}