{
  "type": "Feature",
  "properties": {
    "iso:country":"CH",
    "sg:address":"Friedentalstrasse 8",
    "sg:city":"Luzern",
    "sg:orig_category":"Wirtschaftspr\u00fcfung, Steuerberatung U Treuhand",
    "sg:phone":"+41 41 420 50 55",
    "sg:postcode":"6004",
    "sg:province":"Luzern",
    "wof:name":"Wagner Toni",
    "wof:placetype":"venue"
},
  "geometry": {"coordinates":[8.3075780869,47.0610313416],"type":"Point"}
}