{
  "type": "Feature",
  "properties": {
    "iso:country":"CH",
    "sg:address":"Sch\u00f6nenbergstrasse 8",
    "sg:city":"W\u00e4denswil",
    "sg:orig_category":"Fotografisches Gewerbe U fotografische Laboratorien",
    "sg:postcode":"8820",
    "sg:province":"Z\u00fcrich",
    "wof:name":"Foto Widmer",
    "wof:placetype":"venue"
},
  "geometry": {"coordinates":[8.6711807251,47.2285385132],"type":"Point"}
}