{
  "type": "Feature",
  "properties": {
    "iso:country":"CH",
    "sg:address":"Chemin Des P\u00eacheurs 5",
    "sg:city":"Lausanne",
    "sg:orig_category":"Schiffs U Bootsbau",
    "sg:phone":"+41 79 243 77 88",
    "sg:postcode":"1007",
    "sg:province":"Vaud",
    "wof:name":"Marine Blanchard At.nautiques Du Port D'ouchy",
    "wof:placetype":"venue"
},
  "geometry": {"coordinates":[6.6234002113,46.5078086853],"type":"Point"}
}