{
  "type": "Feature",
  "properties": {
    "iso:country":"CH",
    "sg:address":"Waldhaus 54",
    "sg:city":"Gossliwil",
    "sg:orig_category":"Architektur U Ingenieurb\u00fcros",
    "sg:phone":"+41 32 652 06 38",
    "sg:postcode":"4579",
    "sg:province":"Solothurn",
    "wof:name":"Jakob St\u00fcbi Planungsb\u00fcro",
    "wof:placetype":"venue"
},
  "geometry": {"coordinates":[7.434441,47.136208],"type":"Point"}
}