{
  "type": "Feature",
  "properties": {
    "addr:full":"Hammerstrasse 196 Basel Basel-Stadt 4057",
    "addr:housenumber":"196",
    "addr:postcode":"4057",
    "addr:street":"Hammerstrasse",
    "iso:country":"CH",
    "sg:address":"Hammerstrasse 196",
    "sg:city":"Basel",
    "sg:orig_category":"Detailhandel mit Brot, Back U S\u00fcsswaren",
    "sg:phone":"+41 76 325 51 51",
    "sg:postcode":"4057",
    "sg:province":"Basel-Stadt",
    "wof:name":"Bruno Bachmann B\u00e4ckerei-konditorei",
    "wof:placetype":"venue"
},
  "geometry": {"coordinates":[7.595221,47.57019],"type":"Point"}
}