{
  "type": "Feature",
  "properties": {
    "iso:country":"CH",
    "sg:address":"Fries Rue Hans- 1",
    "sg:city":"Fribourg",
    "sg:orig_category":"Finanzierungsinstitutionen",
    "sg:phone":"+41 26 322 63 66",
    "sg:postcode":"1700",
    "sg:province":"Fribourg",
    "wof:name":"Tan-be Compagnie Sa",
    "wof:placetype":"venue"
},
  "geometry": {"coordinates":[7.1527738571,46.8000068665],"type":"Point"}
}