{
  "type": "Feature",
  "properties": {
    "iso:country":"CH",
    "sg:address":"Rue Centrale 5 1003 Lausanne Case Postale 2794",
    "sg:city":"Lausanne",
    "sg:classifiers":[
        {
            "category":"Professional",
            "subcategory":"Employment Agencies",
            "type":"Services"
        }
    ],
    "sg:phone":"+41 21 311 18 35",
    "sg:postcode":"1002",
    "sg:province":"Vaud",
    "sg:tags":[
        "personal",
        "u",
        "stellenvermittlung"
    ],
    "wof:name":"Fb Leader Search Sa Personnel; Recrutement, Conseil, Placement. Cadres; S\u00e9lection Etc",
    "wof:placetype":"venue"
},
  "geometry": {"coordinates":[6.6323571205,46.5207176208],"type":"Point"}
}