{
  "type": "Feature",
  "properties": {
    "iso:country":"CH",
    "sg:address":"Pizzo Di Claro Via 43",
    "sg:city":"Bellinzona",
    "sg:orig_category":"Interessenvertretungen",
    "sg:phone":"+41 91 825 89 01",
    "sg:postcode":"6500",
    "sg:province":"Ticino",
    "wof:name":"Societ\u00e0 Cooperativa Costruzioni Bellinzona",
    "wof:placetype":"venue"
},
  "geometry": {"coordinates":[9.0270805359,46.2066383362],"type":"Point"}
}