{
  "type": "Feature",
  "properties": {
    "iso:country":"CH",
    "sg:address":"Habsburgerstr. 20",
    "sg:city":"Luzern",
    "sg:classifiers":[
        {
            "category":"Professional",
            "type":"Services"
        }
    ],
    "sg:phone":"+41 41 624 40 40",
    "sg:postcode":"6002",
    "sg:province":"Luzern",
    "sg:tags":[
        "transport",
        "road"
    ],
    "wof:name":"Gabriel Transport Ag",
    "wof:placetype":"venue"
},
  "geometry": {"coordinates":[8.3074474335,47.0471115112],"type":"Point"}
}