{
  "type": "Feature",
  "properties": {
    "iso:country":"CH",
    "sg:address":"Poststrasse 16",
    "sg:city":"St.gallen",
    "sg:orig_category":"Fachdetailhandel mit pharmazeutischen Produkten",
    "sg:phone":"+41 71 911 13 45",
    "sg:postcode":"9000",
    "sg:province":"St. Gallen",
    "wof:name":"Bahnhof-apotheke + Drogerie Uec\u00fcnc\u00fc Christiane",
    "wof:placetype":"venue"
},
  "geometry": {"coordinates":[9.0461912155,47.4631118774],"type":"Point"}
}