{
  "type": "Feature",
  "properties": {
    "iso:country":"CH",
    "sg:address":"Rue Du Clos 35",
    "sg:city":"Peseux",
    "sg:orig_category":"Detailhandel mit Bekleidung Detailhandel mit Textilien",
    "sg:phone":"+41 81 833 44 86",
    "sg:postcode":"2034",
    "sg:province":"Neuch\u00e2tel",
    "wof:name":"J. Mathis Erben Textilwaren",
    "wof:placetype":"venue"
},
  "geometry": {"coordinates":[9.835211,46.488815],"type":"Point"}
}