{
  "type": "Feature",
  "properties": {
    "iso:country":"CH",
    "sg:address":"Furkastrasse",
    "sg:city":"Ulrichen",
    "sg:orig_category":"G\u00fcterbef\u00f6rderung im Strassenverkehr",
    "sg:phone":"+41 27 973 12 63",
    "sg:postcode":"3988",
    "sg:province":"Valais",
    "wof:name":"Fredy Imstepf Transporte",
    "wof:placetype":"venue"
},
  "geometry": {"coordinates":[8.2980461121,46.5050239563],"type":"Point"}
}