{
  "type": "Feature",
  "properties": {
    "iso:country":"CH",
    "sg:address":"Weidstrasse 13",
    "sg:city":"Heiden",
    "sg:orig_category":"Markt U Meinungsforschung",
    "sg:phone":"+41 71 891 39 85",
    "sg:postcode":"9410",
    "sg:province":"Appenzell Ausserrhoden",
    "wof:name":"Sonderegger & Sonderegger, Marketing Und Unternehmensberatung",
    "wof:placetype":"venue"
},
  "geometry": {"coordinates":[9.5294370651,47.4456939697],"type":"Point"}
}