{
  "type": "Feature",
  "properties": {
    "iso:country":"CH",
    "sg:address":"Gr\u00fcndenstrasse 29",
    "sg:city":"Flurlingen",
    "sg:orig_category":"Nationale Postdienste",
    "sg:phone":"+41 52 659 15 58",
    "sg:postcode":"8247",
    "sg:province":"Z\u00fcrich",
    "wof:name":"Die Schweizerische Post",
    "wof:placetype":"venue"
},
  "geometry": {"coordinates":[8.6273050308,47.6860427856],"type":"Point"}
}