{
  "type": "Feature",
  "properties": {
    "iso:country":"CH",
    "sg:address":"Obere Reppischstrasse 37",
    "sg:city":"Dietikon",
    "sg:orig_category":"Non-Classified Establishments",
    "sg:postcode":"8953",
    "sg:province":"Z\u00fcrich",
    "wof:name":"Portugal Shop Gmbh",
    "wof:placetype":"venue"
},
  "geometry": {"coordinates":[8.3985548019,47.4031562805],"type":"Point"}
}