{
  "type": "Feature",
  "properties": {
    "iso:country":"CH",
    "sg:address":"Auer Strasse 35",
    "sg:city":"Berneck",
    "sg:orig_category":"Geb\u00e4ude, Wohnungsreinigung Grosshandel mit sonstigen Maschinen U Ausr\u00fcstungen f\u00fcr Industrie, Handel ",
    "sg:phone":"+41 56 443 39 40",
    "sg:postcode":"9442",
    "sg:province":"St. Gallen",
    "wof:name":"Weber Reinigungssysteme",
    "wof:placetype":"venue"
},
  "geometry": {"coordinates":[8.1668834686,47.4528236389],"type":"Point"}
}