{
  "type": "Feature",
  "properties": {
    "iso:country":"CH",
    "sg:address":"Schulstrasse 50",
    "sg:city":"M\u00f6hlin",
    "sg:orig_category":"G\u00fcterbef\u00f6rderung im Strassenverkehr",
    "sg:phone":"+41 61 853 94 54",
    "sg:postcode":"4313",
    "sg:province":"Aargau",
    "wof:name":"Boutellier Transport Ag",
    "wof:placetype":"venue"
},
  "geometry": {"coordinates":[7.8425579071,47.568447113],"type":"Point"}
}