{
  "type": "Feature",
  "properties": {
    "iso:country":"CH",
    "sg:address":"Seestrasse 824",
    "sg:city":"Meilen",
    "sg:orig_category":"Allgemeinbildende weiterf\u00fchrende Schulen",
    "sg:postcode":"8706",
    "sg:province":"Z\u00fcrich",
    "wof:name":"Institut F\u00fcr Hochseenavigation, Neuhaus Und Schadegg Ag",
    "wof:placetype":"venue"
},
  "geometry": {"coordinates":[8.65213,47.2654],"type":"Point"}
}