{
  "type": "Feature",
  "properties": {
    "iso:country":"CH",
    "sg:address":"Sonneggstrasse 28 6410 Goldau. Postfach 258",
    "sg:city":"Goldau",
    "sg:orig_category":"Instandhaltung U Reparatur von Automobilen",
    "sg:phone":"+41 41 855 22 55",
    "sg:postcode":"6410",
    "sg:province":"Schwyz",
    "wof:name":"Chr\u00e4bel-garage, Kunz Andr\u00e9",
    "wof:placetype":"venue"
},
  "geometry": {"coordinates":[8.5485191345,47.0454177856],"type":"Point"}
}