{
  "type": "Feature",
  "properties": {
    "iso:country":"CH",
    "sg:address":"Vielfallen",
    "sg:city":"Kandersteg",
    "sg:classifiers":[
        {
            "category":"Travel",
            "subcategory":"Hotels & Motels",
            "type":"Entertainment"
        }
    ],
    "sg:phone":"+41 33 675 14 51",
    "sg:postcode":"3718",
    "sg:province":"Bern",
    "sg:tags":[
        "hotels",
        "mit",
        "restaurant"
    ],
    "wof:name":"Hotel Crystal",
    "wof:placetype":"venue"
},
  "geometry": {"coordinates":[7.6677808762,46.4847106934],"type":"Point"}
}