{
  "type": "Feature",
  "properties": {
    "iso:country":"CH",
    "sg:address":"Am Oberen Gletscher",
    "sg:city":"Grindelwald",
    "sg:classifiers":[
        {
            "category":"Travel",
            "subcategory":"Hotels & Motels",
            "type":"Entertainment"
        }
    ],
    "sg:phone":"+41 33 853 12 18",
    "sg:postcode":"3818",
    "sg:province":"Bern",
    "sg:tags":[
        "hotels",
        "mit",
        "restaurant"
    ],
    "wof:name":"Hotel Wetterhorn",
    "wof:placetype":"venue"
},
  "geometry": {"coordinates":[8.0497198105,46.6290855408],"type":"Point"}
}