{
  "type": "Feature",
  "properties": {
    "iso:country":"CH",
    "sg:address":"G\u00fcterstrasse 90",
    "sg:city":"Basel",
    "sg:orig_category":"Kauf U Verkauf von Immobilien auf eigene Rechnung",
    "sg:postcode":"4053",
    "sg:province":"Basel-Stadt",
    "wof:name":"Vermana Ag",
    "wof:placetype":"venue"
},
  "geometry": {"coordinates":[7.5854759216,47.5461387634],"type":"Point"}
}