{
  "type": "Feature",
  "properties": {
    "addr:full":"Via S.materno 1 6616 Losone. Postfach Caselle Postale 1263 Losone Ticino 6616",
    "addr:housenumber":"1",
    "addr:postcode":"6616 losone. postfach caselle postale 1263;6616",
    "addr:street":"Via S.Materno",
    "iso:country":"CH",
    "sg:address":"Via S.materno 1 6616 Losone. Postfach Caselle Postale 1263",
    "sg:city":"Losone",
    "sg:orig_category":"Advokaturb\u00fcros Notariate",
    "sg:phone":"+41 91 785 80 40",
    "sg:postcode":"6616",
    "sg:province":"Ticino",
    "wof:name":"Enrico Broggini Studio Legale & Notarile",
    "wof:placetype":"venue"
},
  "geometry": {"coordinates":[8.761521,46.164337],"type":"Point"}
}