{
  "type": "Feature",
  "properties": {
    "iso:country":"CH",
    "sg:address":"Rue Alexandre-calame 16 1200 Gen\u00e8ve. Postfach",
    "sg:city":"Gen\u00e8ve",
    "sg:orig_category":"RESTAURANTS: TEA-ROOMS",
    "sg:postcode":"1204",
    "sg:province":"Gen\u00e8ve",
    "wof:name":"Nassel C\u00e9cile",
    "wof:placetype":"venue"
},
  "geometry": {"coordinates":[6.0069198608,46.1545410156],"type":"Point"}
}