{
  "type": "Feature",
  "properties": {
    "addr:full":"Hard 5 8400 Winterthur. Postfach Winterthur Z\u00fcrich 8408",
    "addr:housenumber":"5",
    "addr:postcode":"8400;8408",
    "addr:street":"Hard;Postfach",
    "iso:country":"CH",
    "sg:address":"Hard 5 8400 Winterthur. Postfach",
    "sg:city":"Winterthur",
    "sg:orig_category":"Architektur U Ingenieurb\u00fcros",
    "sg:phone":"+41 52 222 78 26",
    "sg:postcode":"8408",
    "sg:province":"Z\u00fcrich",
    "wof:name":"Ingenieurb\u00fcro Hunn",
    "wof:placetype":"venue"
},
  "geometry": {"coordinates":[8.676081,47.517433],"type":"Point"}
}