{
  "type": "Feature",
  "properties": {
    "iso:country":"CH",
    "sg:address":"Koloniestrasse 11",
    "sg:city":"Kemptthal",
    "sg:orig_category":"Hardwareberatung Sonstige mit der Informatik verbundene T\u00e4tigkeiten",
    "sg:phone":"+41 71 242 71 00",
    "sg:postcode":"8310",
    "sg:province":"Z\u00fcrich",
    "wof:name":"Gus Schweiz Ag Informatikl\u00f6sungen; Errichtung, Vertrieb Usw.",
    "wof:placetype":"venue"
},
  "geometry": {"coordinates":[9.3926448822,47.4364776611],"type":"Point"}
}