{
  "type": "Feature",
  "properties": {
    "iso:country":"CH",
    "sg:address":"Merdisel Chemin De 71",
    "sg:city":"Satigny",
    "sg:orig_category":"Unternehmensberatung",
    "sg:phone":"+41 41 460 00 25",
    "sg:postcode":"1242",
    "sg:province":"Gen\u00e8ve",
    "wof:name":"Mps Marktpartner Ag Unternehmensberatung",
    "wof:placetype":"venue"
},
  "geometry": {"coordinates":[8.2235832214,47.131149292],"type":"Point"}
}