{
  "type": "Feature",
  "properties": {
    "iso:country":"CH",
    "sg:address":"B\u00f6tmeweg 152",
    "sg:city":"Kaiseraugst",
    "sg:orig_category":"Grosshandel mit Nahrungsmitteln, Getr\u00e4nken U Tabakwaren ohne ausgepr\u00e4gten Schwerpunkt",
    "sg:postcode":"4303",
    "sg:province":"Aargau",
    "wof:name":"A. Hohler Lebensmittel",
    "wof:placetype":"venue"
},
  "geometry": {"coordinates":[7.7261800766,47.5354194641],"type":"Point"}
}