{
  "type": "Feature",
  "properties": {
    "addr:full":"Zelglistrasse 31 Engelberg Obwalden 6390",
    "addr:housenumber":"31",
    "addr:postcode":"6390",
    "addr:street":"Zelglistrasse",
    "iso:country":"CH",
    "sg:address":"Zelglistrasse 31",
    "sg:city":"Engelberg",
    "sg:orig_category":"Allgemeiner Hoch U Tiefbau",
    "sg:postcode":"6390",
    "sg:province":"Obwalden",
    "wof:name":"L\u00e4ndi Ag",
    "wof:placetype":"venue"
},
  "geometry": {"coordinates":[8.399585,46.824131],"type":"Point"}
}