{
  "type": "Feature",
  "properties": {
    "iso:country":"CH",
    "sg:address":"Hauptstrasse 41",
    "sg:city":"Guntershausen",
    "sg:classifiers":[
        {
            "category":"Restaurant",
            "type":"Food & Drink"
        }
    ],
    "sg:phone":"+41 52 365 29 48",
    "sg:postcode":"8357",
    "sg:province":"Thurgau",
    "wof:name":"Restaurant Bahnhof",
    "wof:placetype":"venue"
},
  "geometry": {"coordinates":[8.916097641,47.4752388],"type":"Point"}
}