{
  "type": "Feature",
  "properties": {
    "iso:country":"CH",
    "sg:address":"Hofmattstrasse 14 3360 Herzogenbuchsee. Postfach",
    "sg:city":"Herzogenbuchsee",
    "sg:orig_category":"Pensionskassen",
    "sg:postcode":"3360",
    "sg:province":"Bern",
    "wof:name":"Baumann-personalvorsorge",
    "wof:placetype":"venue"
},
  "geometry": {"coordinates":[8.8533010483,47.2576026917],"type":"Point"}
}