{
  "type": "Feature",
  "properties": {
    "iso:country":"CH",
    "sg:address":"Hammerstrasse 62c 8032 Z\u00fcrich 32 Zust. Postfach 8032 Z\u00fcrich",
    "sg:city":"Zust",
    "sg:orig_category":"Unternehmensberatung",
    "sg:phone":"+41 81 756 34 07",
    "sg:postcode":"32",
    "wof:name":"Schreyer Und Partner Ag",
    "wof:placetype":"venue"
},
  "geometry": {"coordinates":[9.4814300537,47.1677818298],"type":"Point"}
}