{
  "type": "Feature",
  "properties": {
    "addr:full":"Alte Distelbergstrasse 1 5035 Unterentfelden. Postfach Unterentfelden Aargau 5035",
    "addr:housenumber":"1",
    "addr:postcode":"5035;postfach;5035",
    "addr:street":"Alte Distelbergstrasse",
    "iso:country":"CH",
    "sg:address":"Alte Distelbergstrasse 1 5035 Unterentfelden. Postfach",
    "sg:city":"Unterentfelden",
    "sg:orig_category":"Datenverarbeitungsdienste Sonstige mit der Informatik verbundene T\u00e4tigkeiten",
    "sg:phone":"+41 52 233 12 20",
    "sg:postcode":"5035",
    "sg:province":"Aargau",
    "wof:name":"Cpl, Milan Kryka.",
    "wof:placetype":"venue"
},
  "geometry": {"coordinates":[8.760722,47.483559],"type":"Point"}
}