{
  "type": "Feature",
  "properties": {
    "iso:country":"CH",
    "sg:address":"Route De Vernier 213 1214 Vernier. Postfach",
    "sg:city":"Vernier",
    "sg:orig_category":"Elektroinstallation",
    "sg:postcode":"1214",
    "sg:province":"Gen\u00e8ve",
    "wof:name":"Electrocontr\u00f4le, Heldner Eric",
    "wof:placetype":"venue"
},
  "geometry": {"coordinates":[6.0869970322,46.2164802551],"type":"Point"}
}