{
  "type": "Feature",
  "properties": {
    "iso:country":"CH",
    "sg:address":"Immeuble Laitiere",
    "sg:city":"Siviriez",
    "sg:orig_category":"Grosshandel mit lebenden Tieren",
    "sg:phone":"+41 26 656 13 24",
    "sg:postcode":"1678",
    "sg:province":"Fribourg",
    "wof:name":"Emile D\u00e9nervaud Commerce De B\u00e9tail",
    "wof:placetype":"venue"
},
  "geometry": {"coordinates":[6.8745250702,46.656879425],"type":"Point"}
}