{
  "type": "Feature",
  "properties": {
    "iso:country":"CH",
    "sg:address":"1483",
    "sg:city":"Vesin",
    "sg:orig_category":"Detailhandel mit Schuhen Detailhandel mit Schuhen U Lederwaren",
    "sg:phone":"+41 26 665 12 20",
    "sg:postcode":"1483",
    "sg:province":"Fribourg",
    "wof:name":"Louis Veth Chaussures",
    "wof:placetype":"venue"
},
  "geometry": {"coordinates":[6.8734898567,46.8085403442],"type":"Point"}
}