{
  "type": "Feature",
  "properties": {
    "iso:country":"CH",
    "sg:address":"Rebbergstrasse 1",
    "sg:city":"D\u00f6ttingen",
    "sg:orig_category":"Herstellung von Wein",
    "sg:postcode":"5312",
    "sg:province":"Aargau",
    "wof:name":"Weinbaugenossenschaft Au",
    "wof:placetype":"venue"
},
  "geometry": {"coordinates":[9.6351919174,47.4310073853],"type":"Point"}
}