{
  "type": "Feature",
  "properties": {
    "addr:full":"Alte Distelbergstrasse 24 Unterentfelden Aargau 5035",
    "addr:housenumber":"24",
    "addr:postcode":"5035",
    "addr:street":"Alte Distelbergstrasse",
    "iso:country":"CH",
    "sg:address":"Alte Distelbergstrasse 24",
    "sg:city":"Unterentfelden",
    "sg:orig_category":"Bauschreinerei Glaserei",
    "sg:phone":"+41 62 723 70 20",
    "sg:postcode":"5035",
    "sg:province":"Aargau",
    "wof:name":"Mario Braus Schreinerei & Glaserei",
    "wof:placetype":"venue"
},
  "geometry": {"coordinates":[8.04831,47.375256],"type":"Point"}
}