{
  "type": "Feature",
  "properties": {
    "iso:country":"CH",
    "sg:address":"Fichtenweg 1 3097 Liebefeld. Postfach",
    "sg:city":"Liebefeld",
    "sg:orig_category":"Unternehmensberatung",
    "sg:postcode":"3097",
    "sg:province":"Bern",
    "wof:name":"Michel + Partner Gmbh",
    "wof:placetype":"venue"
},
  "geometry": {"coordinates":[7.4152708054,46.9359283447],"type":"Point"}
}