{
  "type": "Feature",
  "properties": {
    "iso:country":"CH",
    "sg:address":"Etzelstrasse 6",
    "sg:city":"Z\u00fcrich",
    "sg:orig_category":"Zahnarztpraxen",
    "sg:phone":"+41 71 223 23 39",
    "sg:postcode":"8038",
    "sg:province":"Z\u00fcrich",
    "wof:name":"Dr.med.dent.andreas Betschart Zahnarzt",
    "wof:placetype":"venue"
},
  "geometry": {"coordinates":[9.3732070923,47.4222679138],"type":"Point"}
}