{
  "type": "Feature",
  "properties": {
    "iso:country":"CH",
    "sg:address":"Rankstrasse 35",
    "sg:city":"Jona",
    "sg:orig_category":"Architektur U Ingenieurb\u00fcros",
    "sg:postcode":"8645",
    "sg:province":"St. Gallen",
    "wof:name":"Martin Miller Artep Architecture Et Plus",
    "wof:placetype":"venue"
},
  "geometry": {"coordinates":[8.845397,47.234489],"type":"Point"}
}