{
  "type": "Feature",
  "properties": {
    "iso:country":"CH",
    "sg:address":"Weite Gasse 35",
    "sg:city":"Baden",
    "sg:orig_category":"Vermietung U Verpachtung von eigenen Immobilien",
    "sg:phone":"+41 56 424 01 51",
    "sg:postcode":"5400",
    "sg:province":"Aargau",
    "wof:name":"Peterhans Liegenschaften Ag",
    "wof:placetype":"venue"
},
  "geometry": {"coordinates":[8.3064451218,47.4743309021],"type":"Point"}
}