{
  "type": "Feature",
  "properties": {
    "iso:country":"CH",
    "sg:address":"Via Della Posta 9 6900 Lugano. Postfach",
    "sg:city":"Lugano",
    "sg:orig_category":"RESTAURANTS: TEA-ROOMS",
    "sg:postcode":"6900",
    "sg:province":"Ticino",
    "wof:name":"Del.pe. Sagl Bar, Ristoranti, Alberghi Ecc",
    "wof:placetype":"venue"
},
  "geometry": {"coordinates":[8.9523878098,46.004901886],"type":"Point"}
}