{
  "type": "Feature",
  "properties": {
    "iso:country":"CH",
    "sg:address":"Asylstrasse 58",
    "sg:city":"Z\u00fcrich",
    "sg:orig_category":"Gartenbau Landschaftsplanungsb\u00fcros U Gartenarchitekturb\u00fcros",
    "sg:phone":"+41 12515282",
    "sg:postcode":"8032",
    "sg:province":"Z\u00fcrich",
    "wof:name":"Fred Eicher Gartenarchitekt",
    "wof:placetype":"venue"
},
  "geometry": {"coordinates":[8.5597505569,47.3681373596],"type":"Point"}
}