{
  "type": "Feature",
  "properties": {
    "iso:country":"CH",
    "sg:address":"6710",
    "sg:city":"Biasca",
    "sg:classifiers":[
        {
            "category":"Wholesale",
            "subcategory":"Scrap",
            "type":"Manufacturing & Wholesale Goods"
        }
    ],
    "sg:phone":"+41 91 858 10 24",
    "sg:postcode":"6710",
    "sg:province":"Ticino",
    "sg:tags":[
        "metal"
    ],
    "wof:name":"Lombardi Ponti & Co Sa",
    "wof:placetype":"venue"
},
  "geometry": {"coordinates":[8.9698448181,46.3577651978],"type":"Point"}
}