{
  "type": "Feature",
  "properties": {
    "iso:country":"CH",
    "sg:address":"Giovanni Via San 7",
    "sg:city":"Bellinzona",
    "sg:orig_category":"RESTAURANTS: TEA-ROOMS",
    "sg:phone":"+41 91 825 19 19",
    "sg:postcode":"6500",
    "sg:province":"Ticino",
    "wof:name":"Ristorante San Giovanni Di Princzes",
    "wof:placetype":"venue"
},
  "geometry": {"coordinates":[9.019364357,46.189037323],"type":"Point"}
}