{
  "type": "Feature",
  "properties": {
    "addr:full":"Hauptstrasse 14 D\u00f6ttingen Aargau 5312",
    "addr:housenumber":"14",
    "addr:postcode":"5312",
    "addr:street":"Hauptstrasse",
    "iso:country":"CH",
    "sg:address":"Hauptstrasse 14",
    "sg:city":"D\u00f6ttingen",
    "sg:orig_category":"Detailhandel mit Beleuchtungs U Haushaltsgegenst\u00e4nden Grosshandel mit Eisenwaren sowie Installations",
    "sg:phone":"+41 56 245 16 05",
    "sg:postcode":"5312",
    "sg:province":"Aargau",
    "wof:name":"Eisenwaren N\u00e4f Gmbh",
    "wof:placetype":"venue"
},
  "geometry": {"coordinates":[8.255135,47.576744],"type":"Point"}
}