{
  "type": "Feature",
  "properties": {
    "iso:country":"CH",
    "sg:address":"Ador Quai Gustave- 26 1207 Gen\u00e8ve. Postfach",
    "sg:city":"Gen\u00e8ve",
    "sg:orig_category":"Non-Classified Establishments",
    "sg:postcode":"1207",
    "sg:province":"Gen\u00e8ve",
    "wof:name":"Sdc Investissements Sa",
    "wof:placetype":"venue"
},
  "geometry": {"coordinates":[6.1578741074,46.2057189941],"type":"Point"}
}