{
  "type": "Feature",
  "properties": {
    "iso:country":"CH",
    "sg:address":"Plaine Rue De La 10 3960 Sierre. Postfach",
    "sg:city":"Sierre",
    "sg:orig_category":"Institutionen des Sozialwesens ohne Beherbergung",
    "sg:postcode":"3960",
    "sg:province":"Valais",
    "wof:name":"Association De Bienfaisance Sainte Claire Aide Aux Personnes D\u00e9favoris\u00e9es, Conseils Et Soutien Financier Dans Les Domaines De La Formation, De La Sant\u00e9 Etc",
    "wof:placetype":"venue"
},
  "geometry": {"coordinates":[7.5306549072,46.2924041748],"type":"Point"}
}