{
  "type": "Feature",
  "properties": {
    "iso:country":"CH",
    "sg:address":"Kirchweg 9",
    "sg:city":"Geuensee",
    "sg:orig_category":"Aktivit\u00e4ten der Krankenschwestern U Hebammen, Hauspflege Organisationen des Gesundheitswesen",
    "sg:phone":"+41 41 920 32 22",
    "sg:postcode":"6232",
    "sg:province":"Luzern",
    "wof:name":"Spitex Verein F.krankenpflege A.m\u00fcller",
    "wof:placetype":"venue"
},
  "geometry": {"coordinates":[8.11042,47.199421],"type":"Point"}
}