{
  "type": "Feature",
  "properties": {
    "iso:country":"CH",
    "sg:address":"M\u00fchlebachstrasse 30",
    "sg:city":"Flawil",
    "sg:orig_category":"Grosshandel mit sonstigen Maschinen U Ausr\u00fcstungen f\u00fcr Industrie, Handel U Schiffahrt",
    "sg:phone":"+41 71 393 53 09",
    "sg:postcode":"9230",
    "sg:province":"St. Gallen",
    "wof:name":"Baumann",
    "wof:placetype":"venue"
},
  "geometry": {"coordinates":[9.1702184677,47.4155731201],"type":"Point"}
}