{
  "type": "Feature",
  "properties": {
    "iso:country":"CH",
    "sg:address":"Neugutstr. 83",
    "sg:city":"D\u00fcbendorf",
    "sg:classifiers":[
        {
            "category":"Professional",
            "type":"Services"
        }
    ],
    "sg:phone":"+41 4118028787",
    "sg:postcode":"8600",
    "sg:province":"Z\u00fcrich",
    "sg:tags":[
        "transport",
        "road"
    ],
    "wof:name":"Dachser Spedition Ag",
    "wof:placetype":"venue"
},
  "geometry": {"coordinates":[8.6043748856,47.401096344],"type":"Point"}
}