{
  "type": "Feature",
  "properties": {
    "iso:country":"CH",
    "sg:address":"Pflugstrasse 20 9490 Vaduz. Postfach 1268",
    "sg:city":"Vaduz",
    "sg:orig_category":"Verwaltung von Immobilien",
    "sg:phone":"+423 233 25 75",
    "sg:postcode":"9490",
    "wof:name":"Eduard Hilti Treuhand Ag",
    "wof:placetype":"venue"
},
  "geometry": {"coordinates":[9.5244855881,47.1255226135],"type":"Point"}
}