{
  "type": "Feature",
  "properties": {
    "iso:country":"CH",
    "sg:address":"Klausstrasse 49",
    "sg:city":"Z\u00fcrich",
    "sg:orig_category":"Werbung",
    "sg:phone":"+41 13837552",
    "sg:postcode":"8008",
    "sg:province":"Z\u00fcrich",
    "wof:name":"Sport-promotion, Chris Gonzenbach",
    "wof:placetype":"venue"
},
  "geometry": {"coordinates":[8.5525503159,47.3595466614],"type":"Point"}
}