{
  "type": "Feature",
  "properties": {
    "addr:full":"Lindenstrasse 9 Sarnen Obwalden 6060",
    "addr:housenumber":"9",
    "addr:postcode":"6060",
    "addr:street":"Lindenstrasse",
    "iso:country":"CH",
    "sg:address":"Lindenstrasse 9",
    "sg:city":"Sarnen",
    "sg:orig_category":"Bauschreinerei",
    "sg:phone":"+41 41 660 21 77",
    "sg:postcode":"6060",
    "sg:province":"Obwalden",
    "wof:name":"Franz Ziegler Schreinerei",
    "wof:placetype":"venue"
},
  "geometry": {"coordinates":[8.247304,46.896648],"type":"Point"}
}