{
  "type": "Feature",
  "properties": {
    "iso:country":"CH",
    "sg:address":"Dorfplatz",
    "sg:city":"Niederwichtrach",
    "sg:orig_category":"Gemeindeverwaltungen",
    "sg:phone":"+41 31 781 02 73",
    "sg:postcode":"3114",
    "sg:province":"Bern",
    "wof:name":"Gemeindeverwaltung Niederwichtrach",
    "wof:placetype":"venue"
},
  "geometry": {"coordinates":[7.5750951767,46.850818634],"type":"Point"}
}