{
  "type": "Feature",
  "properties": {
    "iso:country":"CH",
    "sg:address":"Dorfstrasse 12",
    "sg:city":"Bachs",
    "sg:orig_category":"G\u00fcterbef\u00f6rderung im Strassenverkehr Personenbef\u00f6rderung im Nahverkehr",
    "sg:phone":"+41 18581444",
    "sg:postcode":"8164",
    "sg:province":"Z\u00fcrich",
    "wof:name":"K\u00f6chli Ag Carreisen & Transporte",
    "wof:placetype":"venue"
},
  "geometry": {"coordinates":[8.4374542236,47.5248832703],"type":"Point"}
}