{
  "type": "Feature",
  "properties": {
    "iso:country":"CH",
    "sg:address":"Kirchplatz 4 4800 Zofingen. Postfach",
    "sg:city":"Zofingen",
    "sg:orig_category":"Architektur U Ingenieurb\u00fcros",
    "sg:phone":"+41 62 216 31 38",
    "sg:postcode":"4800",
    "sg:province":"Aargau",
    "wof:name":"Robert Architektur",
    "wof:placetype":"venue"
},
  "geometry": {"coordinates":[7.84909,47.343861],"type":"Point"}
}