{
  "type": "Feature",
  "properties": {
    "iso:country":"CH",
    "sg:address":"Generoso Via Monte",
    "sg:city":"Rovio",
    "sg:orig_category":"Detailhandel mit elektrischen Haushalts-,Radio U Fernsehger\u00e4ten sowie Musikinstrumenten",
    "sg:phone":"+41 71 755 48 48",
    "sg:postcode":"6821",
    "sg:province":"Ticino",
    "wof:name":"Walt Ernst, Musikhaus.",
    "wof:placetype":"venue"
},
  "geometry": {"coordinates":[9.5378980637,47.3769378662],"type":"Point"}
}