{
  "type": "Feature",
  "properties": {
    "iso:country":"CH",
    "sg:address":"Cibleries Chemin Des 18",
    "sg:city":"Crissier",
    "sg:orig_category":"Mechanik",
    "sg:phone":"+41 22 300 40 25",
    "sg:postcode":"1023",
    "sg:province":"Vaud",
    "wof:name":"Gros Christian",
    "wof:placetype":"venue"
},
  "geometry": {"coordinates":[6.1323451996,46.1880149841],"type":"Point"}
}