{
  "type": "Feature",
  "properties": {
    "iso:country":"CH",
    "sg:address":"Franklinstrasse 33 8050 Z\u00fcrich. Postfach 8050 Z\u00fcrich",
    "sg:city":"Zust",
    "sg:orig_category":"Reiseb\u00fcros Reiseb\u00fcros U Reiseveranstalter",
    "sg:phone":"+41 13188090",
    "sg:postcode":"50",
    "wof:name":"Tempo Travel Ag Tour-operating-betrieb Zum Verkauf U. Zur Organisation Von Reisen Usw",
    "wof:placetype":"venue"
},
  "geometry": {"coordinates":[8.5429563522,47.4099082947],"type":"Point"}
}