{
  "type": "Feature",
  "properties": {
    "iso:country":"CH",
    "sg:address":"Seebahnstrasse 155",
    "sg:city":"Z\u00fcrich",
    "sg:classifiers":[
        {
            "category":"Manufacturing",
            "subcategory":"Tools & Machinery",
            "type":"Manufacturing & Wholesale Goods"
        }
    ],
    "sg:phone":"+41 14627011",
    "sg:postcode":"8003",
    "sg:province":"Z\u00fcrich",
    "sg:tags":[
        "machine",
        "aircraft",
        "engineering"
    ],
    "wof:name":"Heusser & Bachmann",
    "wof:placetype":"venue"
},
  "geometry": {"coordinates":[8.5186414719,47.3748092651],"type":"Point"}
}