{
  "type": "Feature",
  "properties": {
    "iso:country":"CH",
    "sg:address":"Rue Michel-chauvet 22",
    "sg:city":"Gen\u00e8ve",
    "sg:orig_category":"Primarschulen",
    "sg:postcode":"1208",
    "sg:province":"Gen\u00e8ve",
    "wof:name":"Ecole Primaire Contamines",
    "wof:placetype":"venue"
},
  "geometry": {"coordinates":[6.1586318016,46.1969108582],"type":"Point"}
}