{
  "type": "Feature",
  "properties": {
    "iso:country":"CH",
    "sg:address":"6473",
    "sg:city":"Silenen",
    "sg:orig_category":"Schulpflegen",
    "sg:phone":"+41 41 883 14 30",
    "sg:postcode":"6473",
    "sg:province":"Uri",
    "wof:name":"Schulrat Der Gemeinde Amsteg",
    "wof:placetype":"venue"
},
  "geometry": {"coordinates":[8.6697206497,46.7857894897],"type":"Point"}
}