{
  "type": "Feature",
  "properties": {
    "iso:country":"CH",
    "sg:address":"Laliforcha 1",
    "sg:city":"Bavois",
    "sg:orig_category":"Forstwirtschaft ohne Dienstleistungen in der Forstwirtschaft",
    "sg:postcode":"1372",
    "sg:province":"Vaud",
    "wof:name":"Wyrsch Damian Forstsektor Gmbh",
    "wof:placetype":"venue"
},
  "geometry": {"coordinates":[8.6412963867,46.8804130554],"type":"Point"}
}