{
  "type": "Feature",
  "properties": {
    "iso:country":"CH",
    "sg:address":"W\u00f6schnauerstrasse 38",
    "sg:city":"Sch\u00f6nenwerd",
    "sg:orig_category":"Herstellung von Metallerzeugnissen ohne Maschinenbau Maschinenbau",
    "sg:phone":"+41 62 858 40 00",
    "sg:postcode":"5012",
    "sg:province":"Solothurn",
    "wof:name":"Glatt Inox Ag",
    "wof:placetype":"venue"
},
  "geometry": {"coordinates":[8.0125904083,47.3789710999],"type":"Point"}
}