{
  "type": "Feature",
  "properties": {
    "iso:country":"CH",
    "sg:address":"Bahnhofstrasse 35b 6210 Sursee. Postfach 3142",
    "sg:city":"Sursee",
    "sg:orig_category":"Detailhandel mit Herrenbekleidung Herstellung von Oberbekleidung",
    "sg:phone":"+41 41 921 26 67",
    "sg:postcode":"6210",
    "sg:province":"Luzern",
    "wof:name":"Kottmann Herrenmode Ag",
    "wof:placetype":"venue"
},
  "geometry": {"coordinates":[8.1003379822,47.1716423035],"type":"Point"}
}