{
  "type": "Feature",
  "properties": {
    "iso:country":"CH",
    "sg:address":"Pilatusstrasse 3a",
    "sg:city":"Luzern",
    "sg:orig_category":"Detailhandel mit Uhren U Schmuck Reparatur von Uhren U Schmuck",
    "sg:phone":"+41 41 210 26 37",
    "sg:postcode":"6003",
    "sg:province":"Luzern",
    "wof:name":"Peter Bader Juwelen & Uhren",
    "wof:placetype":"venue"
},
  "geometry": {"coordinates":[8.3086452484,47.0498085022],"type":"Point"}
}