{
  "type": "Feature",
  "properties": {
    "iso:country":"CH",
    "sg:address":"Chemin De L'union 7 1008 Prilly Case Postale 363",
    "sg:city":"Prilly",
    "sg:orig_category":"Bauspenglerei Dachdeckerei",
    "sg:phone":"+41 21 624 00 11",
    "sg:postcode":"1008",
    "sg:province":"Vaud",
    "wof:name":"Vannaz Armand Sa",
    "wof:placetype":"venue"
},
  "geometry": {"coordinates":[6.606423,46.535954],"type":"Point"}
}