{
  "type": "Feature",
  "properties": {
    "iso:country":"CH",
    "sg:address":"9477",
    "sg:city":"Tr\u00fcbbach",
    "sg:orig_category":"Giessereiindustrie Herstellung von Kunststoffwaren",
    "sg:phone":"+41 81 784 01 00",
    "sg:postcode":"9477",
    "sg:province":"St. Gallen",
    "wof:name":"B\u00fchler Ag Maschinenfabrik & Anlagenbau",
    "wof:placetype":"venue"
},
  "geometry": {"coordinates":[9.4787502289,47.071018219],"type":"Point"}
}