{
  "type": "Feature",
  "properties": {
    "iso:country":"CH",
    "sg:address":"4574",
    "sg:city":"L\u00fcsslingen",
    "sg:orig_category":"Landw. Genossenschaften Viehzucht",
    "sg:postcode":"4574",
    "sg:province":"Solothurn",
    "wof:name":"Fleckviehzuchtgenossenschaft",
    "wof:placetype":"venue"
},
  "geometry": {"coordinates":[7.5017929077,47.1903800964],"type":"Point"}
}