{
  "type": "Feature",
  "properties": {
    "iso:country":"CH",
    "sg:address":"Chatellenie 4",
    "sg:city":"St-blaise",
    "sg:orig_category":"Unclassifiable Establishments",
    "sg:postcode":"2072",
    "sg:province":"Neuch\u00e2tel",
    "wof:name":"I-pages International Curtil I-media",
    "wof:placetype":"venue"
},
  "geometry": {"coordinates":[6.9897799492,47.0144309998],"type":"Point"}
}