{
  "type": "Feature",
  "properties": {
    "iso:country":"CH",
    "sg:address":"Sch\u00fctzenstrasse 28",
    "sg:city":"Dietikon",
    "sg:orig_category":"Detailhandel mit Getr\u00e4nken Grosshandel mit Getr\u00e4nken",
    "sg:phone":"+41 17404223",
    "sg:postcode":"8953",
    "sg:province":"Z\u00fcrich",
    "wof:name":"Gt Service K.breitenmoser",
    "wof:placetype":"venue"
},
  "geometry": {"coordinates":[8.3924255371,47.4039916992],"type":"Point"}
}