{
  "type": "Feature",
  "properties": {
    "iso:country":"CH",
    "sg:address":"Allex Route De L' 36a 1880 Bex Case Postale 274",
    "sg:city":"Bex",
    "sg:orig_category":"Zimmerei, Dachdeckerei, Bauspenglerei U Abdichtung",
    "sg:postcode":"1880",
    "sg:province":"Vaud",
    "wof:name":"Richard, Raymond",
    "wof:placetype":"venue"
},
  "geometry": {"coordinates":[6.7695250511,46.5411186218],"type":"Point"}
}