{
  "type": "Feature",
  "properties": {
    "iso:country":"CH",
    "sg:address":"Seelistrasse 10",
    "sg:city":"Haag",
    "sg:classifiers":[
        {
            "category":"Retail",
            "subcategory":"Repair Shop",
            "type":"Services"
        }
    ],
    "sg:phone":"+41 81 771 11 92",
    "sg:postcode":"9469",
    "sg:province":"St. Gallen",
    "sg:tags":[
        "agricultural",
        "machinery"
    ],
    "wof:name":"Garage W. Roth Gmbh",
    "wof:placetype":"venue"
},
  "geometry": {"coordinates":[9.493121,47.20998],"type":"Point"}
}