{
  "type": "Feature",
  "properties": {
    "iso:country":"CH",
    "sg:address":"Industriestrasse 31 6300 Zug. Postfach 704",
    "sg:city":"Zug",
    "sg:orig_category":"Non-Classified Establishments",
    "sg:postcode":"6300",
    "sg:province":"Zug",
    "wof:name":"Riso Swiss Gmbh",
    "wof:placetype":"venue"
},
  "geometry": {"coordinates":[8.9146499634,47.5575675964],"type":"Point"}
}