{
  "type": "Feature",
  "properties": {
    "iso:country":"CH",
    "sg:address":"M\u00fclistrasse 2 8872 Weesen. Postfach",
    "sg:city":"Weesen",
    "sg:orig_category":"Bau von Strassen, Sportanlagen U Bahnverkehrsstrecken",
    "sg:postcode":"8872",
    "sg:province":"St. Gallen",
    "wof:name":"H\u00f6sli Walter Strassenbau Ag",
    "wof:placetype":"venue"
},
  "geometry": {"coordinates":[9.101615,47.136185],"type":"Point"}
}