{
  "type": "Feature",
  "properties": {
    "addr:full":"Via Mola 14 Lugano Ticino 6900",
    "addr:housenumber":"14",
    "addr:postcode":"6900",
    "addr:street":"Via Mola",
    "iso:country":"CH",
    "sg:address":"Via Mola 14",
    "sg:city":"Lugano",
    "sg:orig_category":"Allgemeiner Hoch U Tiefbau",
    "sg:postcode":"6900",
    "sg:province":"Ticino",
    "wof:name":"Cavadini Arturo",
    "wof:placetype":"venue"
},
  "geometry": {"coordinates":[8.930912,45.978058],"type":"Point"}
}