{
  "type": "Feature",
  "properties": {
    "iso:country":"CH",
    "sg:address":"Z\u00fcrichstrasse 1",
    "sg:city":"Luzern",
    "sg:orig_category":"Kinos",
    "sg:phone":"+41 41 410 44 04",
    "sg:postcode":"6004",
    "sg:province":"Luzern",
    "wof:name":"Kino Piccolo",
    "wof:placetype":"venue"
},
  "geometry": {"coordinates":[8.310336113,47.055973053],"type":"Point"}
}