{
  "type": "Feature",
  "properties": {
    "iso:country":"CH",
    "sg:address":"Reiterstrasse 23",
    "sg:city":"Basel",
    "sg:orig_category":"Massagestudios",
    "sg:phone":"+41 61 302 01 01",
    "sg:postcode":"4054",
    "sg:province":"Basel-Stadt",
    "wof:name":"Willy Th. Martin Massageinstitut",
    "wof:placetype":"venue"
},
  "geometry": {"coordinates":[7.565723896,47.5488052368],"type":"Point"}
}