{
  "type": "Feature",
  "properties": {
    "iso:country":"CH",
    "sg:address":"Bleiche 338",
    "sg:city":"Trogen",
    "sg:orig_category":"Bauschreinerei Herstellung von Konstruktionsteilen, Fertigbauteilen U Ausbauelementen aus Holz",
    "sg:phone":"+41 79 236 76 43",
    "sg:postcode":"9043",
    "sg:province":"Appenzell Ausserrhoden",
    "wof:name":"Weber, Christoph Ag",
    "wof:placetype":"venue"
},
  "geometry": {"coordinates":[9.474549,47.408077],"type":"Point"}
}