{
  "type": "Feature",
  "properties": {
    "iso:country":"CH",
    "sg:address":"Technikumstrasse 10",
    "sg:city":"Winterthur",
    "sg:orig_category":"Allgemeiner Hoch U Tiefbau",
    "sg:postcode":"8400",
    "sg:province":"Z\u00fcrich",
    "wof:name":"Bauberatung Herren Edwin",
    "wof:placetype":"venue"
},
  "geometry": {"coordinates":[8.730773,47.498001],"type":"Point"}
}