{
  "type": "Feature",
  "properties": {
    "iso:country":"CH",
    "sg:address":"8426",
    "sg:city":"Lufingen",
    "sg:orig_category":"Vorschulen, Kinderg\u00e4rten",
    "sg:phone":"+41 18135620",
    "sg:postcode":"8426",
    "sg:province":"Z\u00fcrich",
    "wof:name":"Kindergarten Altes Schulhaus",
    "wof:placetype":"venue"
},
  "geometry": {"coordinates":[8.5896100998,47.4827308655],"type":"Point"}
}