{
  "type": "Feature",
  "properties": {
    "iso:country":"CH",
    "sg:address":"St. Gallerstrasse 81",
    "sg:city":"Flawil",
    "sg:orig_category":"Museen",
    "sg:phone":"+41 27 973 11 62",
    "sg:postcode":"9230",
    "sg:province":"St. Gallen",
    "wof:name":"Museum M\u00fcnster",
    "wof:placetype":"venue"
},
  "geometry": {"coordinates":[8.2618379593,46.4867591858],"type":"Point"}
}