{
  "type": "Feature",
  "properties": {
    "iso:country":"CH",
    "sg:address":"S\u00fcdringstrasse 6",
    "sg:city":"Recherswil",
    "sg:orig_category":"Handelsvermittlung von Maschinen, technischem Bedarf, Wasser U Luftfahrzeugen",
    "sg:phone":"+41 79 208 29 07",
    "sg:postcode":"4565",
    "sg:province":"Solothurn",
    "wof:name":"K\u00fcnzi U. Sch\u00fctz",
    "wof:placetype":"venue"
},
  "geometry": {"coordinates":[7.5965189934,47.1587867737],"type":"Point"}
}