{
  "type": "Feature",
  "properties": {
    "iso:country":"CH",
    "sg:address":"Erismannstrasse 30",
    "sg:city":"Z\u00fcrich",
    "sg:orig_category":"Handelsvermittlung U Grosshandel Unternehmensberatung",
    "sg:phone":"+41 52 347 08 05",
    "sg:postcode":"8000",
    "sg:province":"Z\u00fcrich",
    "wof:name":"Sophistica Gmbh",
    "wof:placetype":"venue"
},
  "geometry": {"coordinates":[8.5180454254,47.3789749146],"type":"Point"}
}