{
  "type": "Feature",
  "properties": {
    "iso:country":"CH",
    "sg:address":"9492",
    "sg:city":"Eschen",
    "sg:orig_category":"Politische Vereinigungen",
    "sg:phone":"+41 75 373 36 63",
    "sg:postcode":"9492",
    "wof:name":"Fbp Ortsgruppe Mauren-schaanwald",
    "wof:placetype":"venue"
},
  "geometry": {"coordinates":[9.541352272,47.2190284729],"type":"Point"}
}