{
  "type": "Feature",
  "properties": {
    "iso:country":"CH",
    "sg:address":"Grund",
    "sg:city":"Trub",
    "sg:orig_category":"Sportvereine Sch\u00fctzen",
    "sg:phone":"+41 34 495 57 68",
    "sg:postcode":"3556",
    "sg:province":"Bern",
    "wof:name":"Sch\u00fctzengesellschaft",
    "wof:placetype":"venue"
},
  "geometry": {"coordinates":[7.8803958893,46.9411315918],"type":"Point"}
}