{
  "type": "Feature",
  "properties": {
    "iso:country":"CH",
    "sg:address":"Seefeldstrasse 135",
    "sg:city":"Z\u00fcrich",
    "sg:orig_category":"Unternehmensberatung",
    "sg:phone":"+41 33 676 26 29",
    "sg:postcode":"8008",
    "sg:province":"Z\u00fcrich",
    "wof:name":"As Consulting Ag Stahl, Metall, Leichtmetall, Glas Usw.; Herst., Montage, Handel U. Vertrieb",
    "wof:placetype":"venue"
},
  "geometry": {"coordinates":[7.6368107796,46.5884361267],"type":"Point"}
}