{
  "type": "Feature",
  "properties": {
    "iso:country":"CH",
    "sg:address":"Flughafen Bern-belp",
    "sg:city":"Belp",
    "sg:orig_category":"Satzherstellung U Reproduktion",
    "sg:phone":"+41 14056900",
    "sg:postcode":"3123",
    "sg:province":"Bern",
    "wof:name":"Topjobsscout24 Schweiz Ag",
    "wof:placetype":"venue"
},
  "geometry": {"coordinates":[8.455909729,47.3601608276],"type":"Point"}
}