{
  "type": "Feature",
  "properties": {
    "iso:country":"CH",
    "sg:address":"G\u00fcterstrasse 1 4133 Pratteln. Postfach",
    "sg:city":"Pratteln",
    "sg:orig_category":"Abwasserreinigung, Abfallbeseitigung U sonstige Entsorgung",
    "sg:phone":"+41 61 821 65 33",
    "sg:postcode":"4133",
    "sg:province":"Basel-Landschaft",
    "wof:name":"Arewa Ag F\u00fcr Regionale Entsorgung Und Wiederverwertung Von Aushub Und Abf\u00e4llen",
    "wof:placetype":"venue"
},
  "geometry": {"coordinates":[7.691586,47.52232],"type":"Point"}
}