{
  "type": "Feature",
  "properties": {
    "iso:country":"CH",
    "sg:address":"Seestrasse 187",
    "sg:city":"Horgen",
    "sg:orig_category":"Herstellung von konfektionierten Textilwaren ohne Bekleidung",
    "sg:phone":"+41 18501806",
    "sg:postcode":"8810",
    "sg:province":"Z\u00fcrich",
    "wof:name":"Ivens Storenbau",
    "wof:placetype":"venue"
},
  "geometry": {"coordinates":[8.5188446045,47.4763755798],"type":"Point"}
}