{
  "type": "Feature",
  "properties": {
    "iso:country":"CH",
    "sg:address":"Rue Michel-servet 18",
    "sg:city":"Gen\u00e8ve",
    "sg:orig_category":"Architekturb\u00fcros Grafikateliers, Design",
    "sg:phone":"+41 22 346 83 62",
    "sg:postcode":"1206",
    "sg:province":"Gen\u00e8ve",
    "wof:name":"Andr\u00e9 Oberson Architecte Et Designer",
    "wof:placetype":"venue"
},
  "geometry": {"coordinates":[6.153279,46.192661],"type":"Point"}
}