{
  "type": "Feature",
  "properties": {
    "iso:country":"CH",
    "sg:address":"Arfenb\u00fchl",
    "sg:city":"Amden",
    "sg:classifiers":[
        {
            "category":"Restaurant",
            "type":"Food & Drink"
        }
    ],
    "sg:phone":"+41 55 611 12 92",
    "sg:postcode":"8873",
    "sg:province":"St. Gallen",
    "wof:name":"Restaurant Caf\u00e9 Arfenh\u00f6he Ag",
    "wof:placetype":"venue"
},
  "geometry": {"coordinates":[9.1726703644,47.1472091675],"type":"Point"}
}