{
  "type": "Feature",
  "properties": {
    "iso:country":"CH",
    "sg:address":"8301",
    "sg:city":"Glattzentrum",
    "sg:orig_category":"Detailhandel mit Schuhen Detailhandel mit Sportartikeln",
    "sg:phone":"+41 18774080",
    "sg:postcode":"8301",
    "sg:province":"Z\u00fcrich",
    "wof:name":"Ochsner Schuhe & Sport Ag",
    "wof:placetype":"venue"
},
  "geometry": {"coordinates":[8.5951404572,47.4236717224],"type":"Point"}
}