{
  "type": "Feature",
  "properties": {
    "iso:country":"CH",
    "sg:address":"Kirchweg 1",
    "sg:city":"L\u00fcchingen",
    "sg:orig_category":"Primarschulen",
    "sg:phone":"+41 71 755 43 20",
    "sg:postcode":"9450",
    "sg:province":"St. Gallen",
    "wof:name":"Primarschule Kirchfeld",
    "wof:placetype":"venue"
},
  "geometry": {"coordinates":[9.5531415939,47.3866081238],"type":"Point"}
}