{
  "type": "Feature",
  "properties": {
    "iso:country":"CH",
    "sg:address":"Courtepin",
    "sg:city":"Courtepin",
    "sg:orig_category":"Betrieb von Sportanlagen",
    "sg:phone":"+41 21 634 08 58",
    "sg:postcode":"1784",
    "sg:province":"Fribourg",
    "wof:name":"Gym \u00e9vasion, Vence Juan",
    "wof:placetype":"venue"
},
  "geometry": {"coordinates":[6.589571,46.534599],"type":"Point"}
}