{
  "type": "Feature",
  "properties": {
    "iso:country":"CH",
    "sg:address":"Wilhofstrasse 34",
    "sg:city":"Zollikerberg",
    "sg:orig_category":"Sportvereine Ballsport Tennis",
    "sg:postcode":"8125",
    "sg:province":"Z\u00fcrich",
    "wof:name":"Tc Zumikon",
    "wof:placetype":"venue"
},
  "geometry": {"coordinates":[8.6025800705,47.3477897644],"type":"Point"}
}