{
  "type": "Feature",
  "properties": {
    "iso:country":"CH",
    "sg:address":"F\u00f6rrlibuckstrasse 110",
    "sg:city":"Z\u00fcrich",
    "sg:orig_category":"Softwareentwicklung U beratung",
    "sg:phone":"+41 14451717",
    "sg:postcode":"8005",
    "sg:province":"Z\u00fcrich",
    "wof:name":"Forum Informatik Ag",
    "wof:placetype":"venue"
},
  "geometry": {"coordinates":[8.5126361847,47.3921432495],"type":"Point"}
}