{
  "type": "Feature",
  "properties": {
    "iso:country":"CH",
    "sg:address":"Haus Viktoria",
    "sg:city":"Zermatt",
    "sg:orig_category":"Saunas, Solarien, Fitnesszentren U \u00e4hnliches",
    "sg:postcode":"3920",
    "sg:province":"Valais",
    "wof:name":"Fitness-pool Duppenthaler Ag",
    "wof:placetype":"venue"
},
  "geometry": {"coordinates":[9.2547416687,47.4168777466],"type":"Point"}
}