{
  "type": "Feature",
  "properties": {
    "iso:country":"CH",
    "sg:address":"Z\u00fcrcherstrasse 240 8406 Winterthur. Postfach 289",
    "sg:city":"Winterthur",
    "sg:orig_category":"Autogaragen",
    "sg:phone":"+41 41 671 04 71",
    "sg:postcode":"8406",
    "sg:province":"Z\u00fcrich",
    "wof:name":"Avus Auto Ag Garage",
    "wof:placetype":"venue"
},
  "geometry": {"coordinates":[8.275752,46.935982],"type":"Point"}
}