{
  "type": "Feature",
  "properties": {
    "iso:country":"CH",
    "sg:address":"Hauptstrasse 388",
    "sg:city":"Rohrbach",
    "sg:orig_category":"Instandhaltung U Reparatur von Automobilen Schmieden",
    "sg:phone":"+41 62 965 27 50",
    "sg:postcode":"4938",
    "sg:province":"Bern",
    "wof:name":"Sch\u00fcrch Gebr. Garage Und Schmiede.",
    "wof:placetype":"venue"
},
  "geometry": {"coordinates":[7.8224849701,47.1305198669],"type":"Point"}
}