{
  "type": "Feature",
  "properties": {
    "iso:country":"CH",
    "sg:address":"Z\u00fcrcherstrasse 211",
    "sg:city":"Frauenfeld",
    "sg:orig_category":"Detailhandel mit Damenbekleidung Detailhandel mit Geschenkartikeln U Souvenirs",
    "sg:phone":"+41 52 722 20 80",
    "sg:postcode":"8500",
    "sg:province":"Thurgau",
    "wof:name":"Art & Fashion Verena Saxer",
    "wof:placetype":"venue"
},
  "geometry": {"coordinates":[8.899697,47.558205],"type":"Point"}
}