{
  "type": "Feature",
  "properties": {
    "iso:country":"CH",
    "sg:address":"Hamelirainstrasse 80",
    "sg:city":"Kloten",
    "sg:orig_category":"Maler U Glasergewerbe Tapeziererei",
    "sg:phone":"+41 18131742",
    "sg:postcode":"8302",
    "sg:province":"Z\u00fcrich",
    "wof:name":"Maltaplast I. Horvath & Co, Maler Und Tapezierergesch\u00e4ft",
    "wof:placetype":"venue"
},
  "geometry": {"coordinates":[8.5917053223,47.4470367432],"type":"Point"}
}