{
  "type": "Feature",
  "properties": {
    "iso:country":"CH",
    "sg:address":"Kreuzlinger Strasse 76",
    "sg:city":"Oberaach",
    "sg:orig_category":"Grosshandel mit elektrischen Haushaltsger\u00e4ten Installation von Heizungs, L\u00fcftungs U Klimaanlagen",
    "sg:phone":"+41 71 411 38 79",
    "sg:postcode":"8587",
    "sg:province":"Thurgau",
    "wof:name":"Lks K\u00e4lteschweiz Ag",
    "wof:placetype":"venue"
},
  "geometry": {"coordinates":[9.2701253891,47.5537528992],"type":"Point"}
}