{
  "type": "Feature",
  "properties": {
    "iso:country":"CH",
    "sg:address":"Avenue De La Plantaud 14a",
    "sg:city":"Monthey",
    "sg:orig_category":"Elektroinstallation",
    "sg:postcode":"1870",
    "sg:province":"Valais",
    "wof:name":"Delta Concept, Lupu G. Et Pousaz O.",
    "wof:placetype":"venue"
},
  "geometry": {"coordinates":[6.9511351585,46.2508544922],"type":"Point"}
}