{
  "type": "Feature",
  "properties": {
    "iso:country":"CH",
    "sg:address":"Konstanzerstrasse 50",
    "sg:city":"Kreuzlingen",
    "sg:orig_category":"Versicherungen Hauptagenturen",
    "sg:phone":"+41 71 228 84 36",
    "sg:postcode":"8280",
    "sg:province":"Thurgau",
    "wof:name":"National-versicherung Hauptagentur",
    "wof:placetype":"venue"
},
  "geometry": {"coordinates":[9.1648950577,47.6507339478],"type":"Point"}
}