{
  "type": "Feature",
  "properties": {
    "iso:country":"CH",
    "sg:address":"Bahnhofstrasse 21 6300 Zug. Postfach 207",
    "sg:city":"Zug",
    "sg:orig_category":"Markt U Meinungsforschung Unternehmensberatung",
    "sg:phone":"+41 41 711 41 88",
    "sg:postcode":"6301",
    "sg:province":"Zug",
    "wof:name":"Bms Ag",
    "wof:placetype":"venue"
},
  "geometry": {"coordinates":[8.5156917572,47.1697540283],"type":"Point"}
}