{
  "type": "Feature",
  "properties": {
    "iso:country":"CH",
    "sg:address":"Mettlenstrasse 16 6363 Obb\u00fcrgen. Postfach",
    "sg:city":"Obb\u00fcrgen",
    "sg:orig_category":"Kauf U Verkauf von Immobilien auf eigene Rechnung",
    "sg:postcode":"6363",
    "sg:province":"Nidwalden",
    "wof:name":"Betaplus Ag",
    "wof:placetype":"venue"
},
  "geometry": {"coordinates":[8.3625602722,46.9820289612],"type":"Point"}
}