{
  "type": "Feature",
  "properties": {
    "iso:country":"CH",
    "sg:address":"Breitenmattstrasse",
    "sg:city":"D\u00fcrnten",
    "sg:orig_category":"RESTAURANTS: TEA-ROOMS",
    "sg:phone":"+41 55 240 11 40",
    "sg:postcode":"8635",
    "sg:province":"Z\u00fcrich",
    "wof:name":"Restaurant Breitenmatt, R. Schiesser & G. Gregori",
    "wof:placetype":"venue"
},
  "geometry": {"coordinates":[8.8723917007,47.2758522034],"type":"Point"}
}