{
  "type": "Feature",
  "properties": {
    "iso:country":"CH",
    "sg:address":"Moosweg",
    "sg:city":"Ersigen",
    "sg:orig_category":"Instandhaltung U Reparatur von Automobilen",
    "sg:phone":"+41 34 445 98 55",
    "sg:postcode":"3423",
    "sg:province":"Bern",
    "wof:name":"Dorfgarage Ersigen, Peter Odermatt",
    "wof:placetype":"venue"
},
  "geometry": {"coordinates":[7.5974550247,47.0894165039],"type":"Point"}
}