{
  "type": "Feature",
  "properties": {
    "iso:country":"CH",
    "sg:address":"Hintergasse 16",
    "sg:city":"Elgg",
    "sg:orig_category":"Maler U Glasergewerbe Tapeziererei",
    "sg:phone":"+41 52 364 12 90",
    "sg:postcode":"8353",
    "sg:province":"Z\u00fcrich",
    "wof:name":"Sch\u00f6chli Ag",
    "wof:placetype":"venue"
},
  "geometry": {"coordinates":[8.8671522141,47.4890632629],"type":"Point"}
}