{
  "type": "Feature",
  "properties": {
    "iso:country":"CH",
    "sg:address":"Rue Bellefontaine 2",
    "sg:city":"Lausanne",
    "sg:orig_category":"Advokaturb\u00fcros",
    "sg:phone":"+41 21 331 40 80",
    "sg:postcode":"1003",
    "sg:province":"Vaud",
    "wof:name":"Kenny Bl\u00f6chlinger Etude D'avocat",
    "wof:placetype":"venue"
},
  "geometry": {"coordinates":[6.637971,46.516521],"type":"Point"}
}