{
  "type": "Feature",
  "properties": {
    "iso:country":"CH",
    "sg:address":"Neum\u00fchlequai 10",
    "sg:city":"Z\u00fcrich",
    "sg:classifiers":[
        {
            "category":"Education",
            "subcategory":"Library",
            "type":"Public Place"
        }
    ],
    "sg:phone":"+41 12591111",
    "sg:postcode":"8090",
    "sg:province":"Z\u00fcrich",
    "sg:tags":[
        "u",
        "bibliotheken",
        "archive"
    ],
    "wof:name":"Bibliothek Der Kantonalen Direktion Des Innern",
    "wof:placetype":"venue"
},
  "geometry": {"coordinates":[8.542953,47.37833],"type":"Point"}
}