{
  "type": "Feature",
  "properties": {
    "iso:country":"CH",
    "sg:address":"Immeuble Le Fleuron 17 Crans",
    "sg:city":"Lens",
    "sg:orig_category":"Elektroinstallation",
    "sg:phone":"+41 27 481 74 06",
    "sg:postcode":"1978",
    "sg:province":"Valais",
    "wof:name":"Faran Sa",
    "wof:placetype":"venue"
},
  "geometry": {"coordinates":[7.4480681419,46.2825813293],"type":"Point"}
}