{
  "type": "Feature",
  "properties": {
    "addr:full":"Garage 6112 Doppleschwand. Postfach Doppleschwand Luzern 6112",
    "addr:housenumber":"6112",
    "addr:postcode":"6112",
    "addr:street":"Doppleschwand. Postfach",
    "iso:country":"CH",
    "sg:address":"Garage 6112 Doppleschwand. Postfach",
    "sg:city":"Doppleschwand",
    "sg:orig_category":"Autogaragen Instandhaltung U Reparatur von Automobilen",
    "sg:phone":"+41 41 480 11 79",
    "sg:postcode":"6112",
    "sg:province":"Luzern",
    "wof:name":"Garage Glanzmann Ag Automobile; Reparatur, Handel Usw",
    "wof:placetype":"venue"
},
  "geometry": {"coordinates":[8.05579,47.019714],"type":"Point"}
}