{
  "type": "Feature",
  "properties": {
    "iso:country":"CH",
    "sg:address":"Kohlrutistrasse 7",
    "sg:city":"Leuzigen",
    "sg:orig_category":"Instandhaltung U Reparatur von Automobilen",
    "sg:phone":"+41 62 961 36 59",
    "sg:postcode":"3297",
    "sg:province":"Bern",
    "wof:name":"Garage Affolter K.",
    "wof:placetype":"venue"
},
  "geometry": {"coordinates":[7.6989850998,47.2085762024],"type":"Point"}
}