{
  "type": "Feature",
  "properties": {
    "iso:country":"CH",
    "sg:address":"1226 Th\u00f4nex. Postfach",
    "sg:city":"Th\u00f4nex",
    "sg:orig_category":"Schulpflegen",
    "sg:postcode":"1226",
    "sg:province":"Gen\u00e8ve",
    "wof:name":"Commission Scolaire De L'\u00e9cole Primaire",
    "wof:placetype":"venue"
},
  "geometry": {"coordinates":[6.2055101395,46.1978683472],"type":"Point"}
}