{
  "type": "Feature",
  "properties": {
    "iso:country":"CH",
    "sg:address":"F\u00e4rchstrasse 10",
    "sg:city":"Fulenbach",
    "sg:orig_category":"Autolackierereien Autospenglereien",
    "sg:phone":"+41 62 926 04 04",
    "sg:postcode":"4629",
    "sg:province":"Solothurn",
    "wof:name":"Markus Schumacher Carrosserie Autospritzwerk",
    "wof:placetype":"venue"
},
  "geometry": {"coordinates":[7.832131,47.284172],"type":"Point"}
}