{
  "type": "Feature",
  "properties": {
    "iso:country":"CH",
    "sg:address":"B\u00fchlmoosstrasse 1",
    "sg:city":"Sarmenstorf",
    "sg:orig_category":"Herstellung von Tanks U Sammelbeh\u00e4ltern aus Metall Stahl U Leichtmetallbau",
    "sg:phone":"+41 79 353 32 81",
    "sg:postcode":"5614",
    "sg:province":"Aargau",
    "wof:name":"Muff Josef Ag Rohrleitungsbau",
    "wof:placetype":"venue"
},
  "geometry": {"coordinates":[8.2449970245,47.3058700562],"type":"Point"}
}