{
  "type": "Feature",
  "properties": {
    "iso:country":"CH",
    "sg:address":"Hauptstrasse 1",
    "sg:city":"Binningen",
    "sg:orig_category":"Detailhandel mit Textilien Grosshandel mit Textilien",
    "sg:phone":"+41 61 421 62 66",
    "sg:postcode":"4102",
    "sg:province":"Basel-Landschaft",
    "wof:name":"Gianmara Gmbh",
    "wof:placetype":"venue"
},
  "geometry": {"coordinates":[7.5753798485,47.5436859131],"type":"Point"}
}