{
  "type": "Feature",
  "properties": {
    "iso:country":"CH",
    "sg:address":"6744 Personico. Postfach",
    "sg:city":"Biasca",
    "sg:orig_category":"Non-Classified Establishments",
    "sg:phone":"+41 91 862 21 61",
    "sg:postcode":"6710",
    "sg:province":"Ticino",
    "wof:name":"Forni Sa",
    "wof:placetype":"venue"
},
  "geometry": {"coordinates":[8.9183044434,46.3701972961],"type":"Point"}
}