{
  "type": "Feature",
  "properties": {
    "iso:country":"CH",
    "sg:address":"Missionsstrasse 44",
    "sg:city":"Basel",
    "sg:orig_category":"Arztpraxen",
    "sg:phone":"+41 61 281 84 82",
    "sg:postcode":"4055",
    "sg:province":"Basel-Stadt",
    "wof:name":"Dr.med.david S. Erlanger Spezialarzt",
    "wof:placetype":"venue"
},
  "geometry": {"coordinates":[7.576515,47.560604],"type":"Point"}
}