{
  "type": "Feature",
  "properties": {
    "iso:country":"CH",
    "sg:address":"Zollstrasse 19",
    "sg:city":"Sch\u00f6nenbuch",
    "sg:orig_category":"Sportvereine Turnen",
    "sg:phone":"+41 81 416 17 37",
    "sg:postcode":"4124",
    "sg:province":"Basel-Landschaft",
    "wof:name":"Turnverein Davos Dorf",
    "wof:placetype":"venue"
},
  "geometry": {"coordinates":[9.8414525986,46.811214447],"type":"Point"}
}