{
  "type": "Feature",
  "properties": {
    "iso:country":"CH",
    "sg:address":"Krummackerstr. 542",
    "sg:city":"Egerkingen",
    "sg:classifiers":[
        {
            "category":"Banks & Credit Unions",
            "subcategory":"Bank",
            "type":"Services"
        }
    ],
    "sg:phone":"+41 62 398 43 10",
    "sg:postcode":"4622",
    "sg:province":"Solothurn",
    "wof:name":"Raiffeisenbank Egerkingen",
    "wof:placetype":"venue"
},
  "geometry": {"coordinates":[7.78789,47.319752],"type":"Point"}
}