{
  "type": "Feature",
  "properties": {
    "iso:country":"CH",
    "sg:address":"Obholzstrasse 17",
    "sg:city":"Frauenfeld",
    "sg:orig_category":"Arztpraxen",
    "sg:phone":"+41 52 722 40 40",
    "sg:postcode":"8500",
    "sg:province":"Thurgau",
    "wof:name":"Dr.med.anita Meyer Spezial\u00e4rztin Fmh",
    "wof:placetype":"venue"
},
  "geometry": {"coordinates":[8.915245,47.546532],"type":"Point"}
}