{
  "type": "Feature",
  "properties": {
    "iso:country":"CH",
    "sg:address":"Chapella",
    "sg:city":"Cinuos-chel",
    "sg:orig_category":"Campingpl\u00e4tze Detailhandel mit Zeitungen U Zeitschriften Kioske",
    "sg:phone":"+41 81 845 12 06",
    "sg:postcode":"7526",
    "sg:province":"Graubunden",
    "wof:name":"Camping Chapella Gmbh",
    "wof:placetype":"venue"
},
  "geometry": {"coordinates":[10.007675,46.629768],"type":"Point"}
}