{
  "type": "Feature",
  "properties": {
    "iso:country":"CH",
    "sg:address":"Holeestr. 155a",
    "sg:city":"Basel",
    "sg:classifiers":[
        {
            "category":"Manufacturing",
            "subcategory":"Metals",
            "type":"Manufacturing & Wholesale Goods"
        }
    ],
    "sg:phone":"+41 32 933 06 33",
    "sg:postcode":"4054",
    "sg:province":"Basel-Stadt",
    "sg:tags":[
        "-",
        "machine",
        "equipment",
        "engineering",
        "machinery",
        "mechanical"
    ],
    "wof:name":"Pibomulti Sa",
    "wof:placetype":"venue"
},
  "geometry": {"coordinates":[6.767013073,47.0661315918],"type":"Point"}
}