{
  "type": "Feature",
  "properties": {
    "iso:country":"CH",
    "sg:address":"Lehenmattstrasse 81",
    "sg:city":"Basel",
    "sg:orig_category":"Architekturb\u00fcros",
    "sg:phone":"+41 31 311 38 48",
    "sg:postcode":"4052",
    "sg:province":"Basel-Stadt",
    "wof:name":"Schwob Und Sutter Architekten Eth Sia Htl",
    "wof:placetype":"venue"
},
  "geometry": {"coordinates":[7.615068,47.553223],"type":"Point"}
}