{
  "type": "Feature",
  "properties": {
    "iso:country":"CH",
    "sg:address":"Thundorferstrasse 31a",
    "sg:city":"Frauenfeld",
    "sg:orig_category":"Zahnarztpraxen",
    "sg:phone":"+41 52 722 19 22",
    "sg:postcode":"8500",
    "sg:province":"Thurgau",
    "wof:name":"Dr. Med. Dent. J\u00fcrg D\u00e4hler Zahnarzt",
    "wof:placetype":"venue"
},
  "geometry": {"coordinates":[8.9010267258,47.5544548035],"type":"Point"}
}