{
  "type": "Feature",
  "properties": {
    "iso:country":"CH",
    "sg:address":"Bleichenbergstrasse 32",
    "sg:city":"Biberist",
    "sg:orig_category":"Unclassifiable Establishments",
    "sg:phone":"+41 32 672 47 40",
    "sg:postcode":"4562",
    "sg:province":"Solothurn",
    "wof:name":"Roth Consulting Medien, Multimedia Usw.; Beratungen, Schulungen",
    "wof:placetype":"venue"
},
  "geometry": {"coordinates":[7.561645031,47.1903114319],"type":"Point"}
}