{
  "type": "Feature",
  "properties": {
    "iso:country":"CH",
    "sg:address":"Stationsstrasse 15",
    "sg:city":"N\u00e4nikon",
    "sg:orig_category":"Detailhandel mit Waren verschiedener Art, Hauptrichtung Nahrungsmittel",
    "sg:phone":"+41 52 264 26 16",
    "sg:postcode":"8606",
    "sg:province":"Z\u00fcrich",
    "wof:name":"Volg Detailhandels Ag Volg-laden",
    "wof:placetype":"venue"
},
  "geometry": {"coordinates":[8.1418218613,47.4470977783],"type":"Point"}
}