{
  "type": "Feature",
  "properties": {
    "iso:country":"CH",
    "sg:address":"G\u00f6sgerstrasse 2",
    "sg:city":"Sch\u00f6nenwerd",
    "sg:orig_category":"Regionalbanken U Sparkassen",
    "sg:phone":"+41 62 858 48 48",
    "sg:postcode":"5012",
    "sg:province":"Solothurn",
    "wof:name":"Baloise Bank Soba",
    "wof:placetype":"venue"
},
  "geometry": {"coordinates":[8.002114,47.372269],"type":"Point"}
}