{
  "type": "Feature",
  "properties": {
    "iso:country":"CH",
    "sg:address":"Sagnes Chemin Des 3",
    "sg:city":"Bevaix",
    "sg:orig_category":"Rechtsberatung",
    "sg:postcode":"2022",
    "sg:province":"Neuch\u00e2tel",
    "wof:name":"Clad Lizenz Ag",
    "wof:placetype":"venue"
},
  "geometry": {"coordinates":[8.9666671753,47.4585838318],"type":"Point"}
}