{
  "type": "Feature",
  "properties": {
    "iso:country":"CH",
    "sg:address":"Vordergasse 12",
    "sg:city":"Neunkirch",
    "sg:orig_category":"Gemeindeverwaltungen",
    "sg:phone":"+41 52 687 00 11",
    "sg:postcode":"8213",
    "sg:province":"Schaffhausen",
    "wof:name":"Gemeindeverwaltung Neunkirch",
    "wof:placetype":"venue"
},
  "geometry": {"coordinates":[8.5001487732,47.6904373169],"type":"Point"}
}