{
  "type": "Feature",
  "properties": {
    "iso:country":"CH",
    "sg:address":"Simplon Rue Du 10",
    "sg:city":"Lausanne",
    "sg:orig_category":"Non-Classified Establishments",
    "sg:postcode":"1006",
    "sg:province":"Vaud",
    "wof:name":"Af Institut Moderne De Langues S\u00e0rl",
    "wof:placetype":"venue"
},
  "geometry": {"coordinates":[6.6314558983,46.5157318115],"type":"Point"}
}