{
  "type": "Feature",
  "properties": {
    "iso:country":"CH",
    "sg:address":"Industriestrasse 24",
    "sg:city":"Oberentfelden",
    "sg:orig_category":"Grosshandel mit Textilien",
    "sg:postcode":"5036",
    "sg:province":"Aargau",
    "wof:name":"Gewag-tex, L. Neeser",
    "wof:placetype":"venue"
},
  "geometry": {"coordinates":[8.0563821793,47.3559150696],"type":"Point"}
}