{
  "type": "Feature",
  "properties": {
    "iso:country":"CH",
    "sg:address":"Spillstatt 2",
    "sg:city":"Grindelwald",
    "sg:orig_category":"Betrieb von Taxis",
    "sg:postcode":"3818",
    "sg:province":"Bern",
    "wof:name":"Oechslin & Graf",
    "wof:placetype":"venue"
},
  "geometry": {"coordinates":[8.02759,46.626751],"type":"Point"}
}