{
  "type": "Feature",
  "properties": {
    "iso:country":"CH",
    "sg:address":"Kehlhof Str. 54",
    "sg:city":"Frauenfeld",
    "sg:classifiers":[
        {
            "category":"Manufacturing",
            "subcategory":"Glass & Minerals",
            "type":"Manufacturing & Wholesale Goods"
        }
    ],
    "sg:phone":"+41 52 728 81 11",
    "sg:postcode":"8500",
    "sg:province":"Thurgau",
    "sg:tags":[
        "building",
        "material"
    ],
    "wof:name":"Tuchschmid Constructa Ag",
    "wof:placetype":"venue"
},
  "geometry": {"coordinates":[8.9034061432,47.5662918091],"type":"Point"}
}