{
  "type": "Feature",
  "properties": {
    "iso:country":"CH",
    "sg:address":"Industriestrasse 2",
    "sg:city":"Steinhausen",
    "sg:orig_category":"Sonstiges Gesundheitswesen",
    "sg:phone":"+41 41 741 44 63",
    "sg:postcode":"6312",
    "sg:province":"Zug",
    "wof:name":"Krankenmobilienmagazin",
    "wof:placetype":"venue"
},
  "geometry": {"coordinates":[8.486620903,47.1921615601],"type":"Point"}
}