{
  "type": "Feature",
  "properties": {
    "iso:country":"CH",
    "sg:address":"Lindenweg 6",
    "sg:city":"Herznach",
    "sg:orig_category":"Schreib U \u00dcbersetzungsb\u00fcros",
    "sg:phone":"+41 62 878 30 21",
    "sg:postcode":"5027",
    "sg:province":"Aargau",
    "wof:name":"Gewerbe- & Handelssekretariat, M\u00fcller J.",
    "wof:placetype":"venue"
},
  "geometry": {"coordinates":[8.0553750992,47.4685173035],"type":"Point"}
}