{
  "type": "Feature",
  "properties": {
    "iso:country":"CH",
    "sg:address":"Bernstrasse 10",
    "sg:city":"B\u00e4tterkinden",
    "sg:orig_category":"Detailhandel mit Schuhen",
    "sg:phone":"+41 32 665 44 08",
    "sg:postcode":"3315",
    "sg:province":"Bern",
    "wof:name":"Jakob Schl\u00e4pfer Schuhgesch\u00e4ft",
    "wof:placetype":"venue"
},
  "geometry": {"coordinates":[7.5395121574,47.1295089722],"type":"Point"}
}