{
  "type": "Feature",
  "properties": {
    "iso:country":"CH",
    "sg:address":"Rue Peillonex 3",
    "sg:city":"Ch\u00eane-bourg",
    "sg:orig_category":"Innendekorationsateliers",
    "sg:phone":"+41 22 320 10 73",
    "sg:postcode":"1225",
    "sg:province":"Gen\u00e8ve",
    "wof:name":"Ivar Petterson Tapissier-d\u00e9corateur",
    "wof:placetype":"venue"
},
  "geometry": {"coordinates":[6.1954069138,46.1945457458],"type":"Point"}
}