{
  "type": "Feature",
  "properties": {
    "iso:country":"CH",
    "sg:address":"Bitzighoferstrasse 2",
    "sg:city":"Sarnen",
    "sg:orig_category":"Kosmetikinstitute",
    "sg:phone":"+41 41 660 53 14",
    "sg:postcode":"6060",
    "sg:province":"Obwalden",
    "wof:name":"Anny Burch Kosmetikinstitut",
    "wof:placetype":"venue"
},
  "geometry": {"coordinates":[8.2472734451,46.9029541016],"type":"Point"}
}