{
  "type": "Feature",
  "properties": {
    "iso:country":"CH",
    "sg:address":"Spielhof 18",
    "sg:city":"Glarus",
    "sg:orig_category":"Instandhaltung U Reparatur von Automobilen",
    "sg:phone":"+41 55 640 21 17",
    "sg:postcode":"8750",
    "sg:province":"Glarus",
    "wof:name":"Weber Autoelektrik Ag",
    "wof:placetype":"venue"
},
  "geometry": {"coordinates":[9.0657110214,47.0423278809],"type":"Point"}
}