{
  "type": "Feature",
  "properties": {
    "iso:country":"CH",
    "sg:address":"Oeschstrasse 9 4553 Subingen. Postfach",
    "sg:city":"Subingen",
    "sg:orig_category":"Mechanik",
    "sg:postcode":"4553",
    "sg:province":"Solothurn",
    "wof:name":"Steiner Mechanik",
    "wof:placetype":"venue"
},
  "geometry": {"coordinates":[7.6174578667,47.1966438293],"type":"Point"}
}