{
  "type": "Feature",
  "properties": {
    "iso:country":"CH",
    "sg:address":"Rte Principale 46",
    "sg:city":"Nant-sugiez",
    "sg:classifiers":[
        {
            "category":"Farming",
            "subcategory":"Farm",
            "type":"Manufacturing & Wholesale Goods"
        }
    ],
    "sg:phone":"+41 26 673 14 25",
    "sg:postcode":"1786",
    "sg:province":"Fribourg",
    "sg:tags":[
        "horticulture",
        "agriculture",
        "livestock"
    ],
    "wof:name":"Gugger-guillod Sa Nant",
    "wof:placetype":"venue"
},
  "geometry": {"coordinates":[7.107928,46.957409],"type":"Point"}
}