{
  "type": "Feature",
  "properties": {
    "iso:country":"CH",
    "sg:address":"Via Dufour 2 6900 Lugano. Postfach Caselle Postale 3198",
    "sg:city":"Lugano",
    "sg:orig_category":"Advokaturb\u00fcros Notariate",
    "sg:phone":"+41 91 922 08 61",
    "sg:postcode":"6901",
    "sg:province":"Ticino",
    "wof:name":"Probst & Pozzoli Studio Legale & Notarile",
    "wof:placetype":"venue"
},
  "geometry": {"coordinates":[8.951773,46.008492],"type":"Point"}
}