{
  "type": "Feature",
  "properties": {
    "iso:country":"CH",
    "sg:address":"Rue De La Gare 26 2500 Biel/bienne. Postfach",
    "sg:city":"Biel/bienne",
    "sg:orig_category":"Erschliessung von Grundst\u00fccken",
    "sg:postcode":"2501",
    "sg:province":"Bern",
    "wof:name":"L\u00e9vy-fleury Max",
    "wof:placetype":"venue"
},
  "geometry": {"coordinates":[7.2449269295,47.1351470947],"type":"Point"}
}