{
  "type": "Feature",
  "properties": {
    "iso:country":"CH",
    "sg:address":"Geren 14 8712 St\u00e4fa. Postfach 617",
    "sg:city":"St\u00e4fa",
    "sg:orig_category":"Vermittlung von Immobilien Verwaltung von Immobilien",
    "sg:phone":"+41 24 471 42 84",
    "sg:postcode":"8712",
    "sg:province":"Z\u00fcrich",
    "wof:name":"Bussien Dominique Sa",
    "wof:placetype":"venue"
},
  "geometry": {"coordinates":[6.9491910934,46.2522583008],"type":"Point"}
}