{
  "type": "Feature",
  "properties": {
    "iso:country":"CH",
    "sg:address":"Gartenstrasse 71 4132 Muttenz. Postfach",
    "sg:city":"Muttenz",
    "sg:orig_category":"Blumen U Zierpflanzenbau Gartenbau",
    "sg:phone":"+41 61 461 69 33",
    "sg:postcode":"4132",
    "sg:province":"Basel-Landschaft",
    "wof:name":"Gebr\u00fcder Allemann",
    "wof:placetype":"venue"
},
  "geometry": {"coordinates":[7.638993,47.531727],"type":"Point"}
}