{
  "type": "Feature",
  "properties": {
    "addr:full":"Sunneggweg 3 Steffisburg Bern 3612",
    "addr:housenumber":"3",
    "addr:postcode":"3612",
    "addr:street":"Sunneggweg;Bern",
    "iso:country":"CH",
    "sg:address":"Sunneggweg 3",
    "sg:city":"Steffisburg",
    "sg:orig_category":"Bauschreinerei Herstellung von Konstruktionsteilen, Fertigbauteilen U Ausbauelementen aus Holz",
    "sg:phone":"+41 33 437 23 84",
    "sg:postcode":"3612",
    "sg:province":"Bern",
    "wof:name":"Meinen Daniel",
    "wof:placetype":"venue"
},
  "geometry": {"coordinates":[7.635035,46.782082],"type":"Point"}
}