{
  "type": "Feature",
  "properties": {
    "iso:country":"CH",
    "sg:address":"Dorfstrasse 3",
    "sg:city":"Islisberg",
    "sg:orig_category":"Sportvereine Unihockey",
    "sg:phone":"+41 800 808 080",
    "sg:postcode":"8905",
    "sg:province":"Aargau",
    "wof:name":"Uhc Crusaders 95 Z\u00fcrich",
    "wof:placetype":"venue"
},
  "geometry": {"coordinates":[8.4392261505,47.3233451843],"type":"Point"}
}