{
  "type": "Feature",
  "properties": {
    "iso:country":"CH",
    "sg:address":"6294",
    "sg:city":"Ermensee",
    "sg:orig_category":"Primarschulen",
    "sg:phone":"+41 41 917 23 16",
    "sg:postcode":"6294",
    "sg:province":"Luzern",
    "wof:name":"Primarschule",
    "wof:placetype":"venue"
},
  "geometry": {"coordinates":[8.2368497849,47.2244491577],"type":"Point"}
}