{
  "type": "Feature",
  "properties": {
    "iso:country":"CH",
    "sg:address":"Weinfelderstrasse 62",
    "sg:city":"Amriswil",
    "sg:orig_category":"Detailhandel mit Waren verschiedener Art, Hauptrichtung Nahrungsmittel Verarbeitung von Milch",
    "sg:phone":"+41 71 923 83 13",
    "sg:postcode":"8580",
    "sg:province":"Thurgau",
    "wof:name":"Ulrich Siegfried Molkerei Hub",
    "wof:placetype":"venue"
},
  "geometry": {"coordinates":[-96.68799591059999,30.1493644714],"type":"Point"}
}