{
  "type": "Feature",
  "properties": {
    "iso:country":"CH",
    "sg:address":"Humboldtstrasse 31",
    "sg:city":"Bern",
    "sg:orig_category":"Public-Relations-Agenturen",
    "sg:phone":"+41 56 470 26 03",
    "sg:postcode":"3013",
    "sg:province":"Bern",
    "wof:name":"Peter Schmid Sms Schmid Management Services",
    "wof:placetype":"venue"
},
  "geometry": {"coordinates":[8.2855997086,47.4521484375],"type":"Point"}
}