{
  "type": "Feature",
  "properties": {
    "iso:country":"CH",
    "sg:address":"Rue Du Temple 23",
    "sg:city":"B\u00f4le",
    "sg:orig_category":"Rebbau",
    "sg:phone":"+41 32 842 55 88",
    "sg:postcode":"2014",
    "sg:province":"Neuch\u00e2tel",
    "wof:name":"Michel Egli Viticulteur-encaveur",
    "wof:placetype":"venue"
},
  "geometry": {"coordinates":[6.8401417732,46.966003418],"type":"Point"}
}