{
  "type": "Feature",
  "properties": {
    "iso:country":"CH",
    "sg:address":"Lettenstrasse 11",
    "sg:city":"Rotkreuz",
    "sg:orig_category":"Mechanische Werkst\u00e4tten",
    "sg:phone":"+41 18582404",
    "sg:postcode":"6343",
    "sg:province":"Zug",
    "wof:name":"Toff Drehteile Ag",
    "wof:placetype":"venue"
},
  "geometry": {"coordinates":[8.4181404114,47.5692558289],"type":"Point"}
}