{
  "type": "Feature",
  "properties": {
    "iso:country":"CH",
    "sg:address":"Plattis 9478 Azmoos. Postfach",
    "sg:city":"Azmoos",
    "sg:orig_category":"Instandhaltung U Reparatur von Automobilen",
    "sg:phone":"+41 81 785 12 52",
    "sg:postcode":"9478",
    "sg:province":"St. Gallen",
    "wof:name":"Garage Willi Ag",
    "wof:placetype":"venue"
},
  "geometry": {"coordinates":[9.4766893387,47.0802955627],"type":"Point"}
}