{
  "type": "Feature",
  "properties": {
    "iso:country":"CH",
    "sg:address":"Papierm\u00fchlestrasse 11/11a 3013 Bern. Postfach",
    "sg:city":"Bern",
    "sg:orig_category":"Pensionskassen",
    "sg:phone":"+41 31 332 22 11",
    "sg:postcode":"3005",
    "sg:province":"Bern",
    "wof:name":"Personal-f\u00fcrsorgestiftung Der Edwin Lanz Ag",
    "wof:placetype":"venue"
},
  "geometry": {"coordinates":[7.4600338936,46.9545898438],"type":"Point"}
}