{
  "type": "Feature",
  "properties": {
    "iso:country":"CH",
    "sg:address":"Schaffhauserstrasse 468",
    "sg:city":"Z\u00fcrich",
    "sg:classifiers":[
        {
            "category":"Retail",
            "subcategory":"Auto Repair",
            "type":"Services"
        }
    ],
    "sg:phone":"+41 13012651",
    "sg:postcode":"8052",
    "sg:province":"Z\u00fcrich",
    "sg:tags":[
        "machine",
        "equipment",
        "construction"
    ],
    "wof:name":"Metall- & Apparatebau Z\u00fcrich Ag",
    "wof:placetype":"venue"
},
  "geometry": {"coordinates":[8.548995018,47.4186706543],"type":"Point"}
}