{
  "type": "Feature",
  "properties": {
    "iso:country":"CH",
    "sg:address":"Eisengasse 15",
    "sg:city":"Luzern",
    "sg:orig_category":"RESTAURANTS: TEA-ROOMS",
    "sg:phone":"+41 55 240 72 05",
    "sg:postcode":"6004",
    "sg:province":"Luzern",
    "wof:name":"Sp\u00f6rri E.",
    "wof:placetype":"venue"
},
  "geometry": {"coordinates":[8.8477220535,47.2580223083],"type":"Point"}
}