{
  "type": "Feature",
  "properties": {
    "iso:country":"CH",
    "sg:address":"8117 F\u00e4llanden. Postfach 30",
    "sg:city":"F\u00e4llanden",
    "sg:orig_category":"Sportvereine Ballsport Fussball",
    "sg:phone":"+41 18254694",
    "sg:postcode":"8117",
    "sg:province":"Z\u00fcrich",
    "wof:name":"Fc F\u00e4llanden",
    "wof:placetype":"venue"
},
  "geometry": {"coordinates":[8.6397953033,47.3714904785],"type":"Point"}
}