{
  "type": "Feature",
  "properties": {
    "iso:country":"CH",
    "sg:address":"Via La Santa 29",
    "sg:city":"Viganello",
    "sg:orig_category":"Interessenvertretungen U sonstige Vereinigungen",
    "sg:phone":"+41 91 825 54 44",
    "sg:postcode":"6962",
    "sg:province":"Ticino",
    "wof:name":"Fed.ticinese Di Calcio",
    "wof:placetype":"venue"
},
  "geometry": {"coordinates":[9.0127038956,46.1851081848],"type":"Point"}
}