{
  "type": "Feature",
  "properties": {
    "iso:country":"CH",
    "sg:address":"5504",
    "sg:city":"Othmarsingen",
    "sg:orig_category":"Sportvereine Turnen",
    "sg:postcode":"5504",
    "sg:province":"Aargau",
    "wof:name":"Turnverein",
    "wof:placetype":"venue"
},
  "geometry": {"coordinates":[8.2161197662,47.4028701782],"type":"Point"}
}