{
  "type": "Feature",
  "properties": {
    "iso:country":"CH",
    "sg:address":"Chemin De Malley 12",
    "sg:city":"Lausanne",
    "sg:orig_category":"Elektroinstallation Herstellung von sonstigen elektrischen Ausr\u00fcstungen",
    "sg:phone":"+41 21 312 26 56",
    "sg:postcode":"1007",
    "sg:province":"Vaud",
    "wof:name":"Home S\u00e9curit\u00e9, Heymoz P.",
    "wof:placetype":"venue"
},
  "geometry": {"coordinates":[6.6071581841,46.5242424011],"type":"Point"}
}