{
  "type": "Feature",
  "properties": {
    "iso:country":"CH",
    "sg:address":"Rue Du Petit-b\u00e2le 12",
    "sg:city":"Tavannes",
    "sg:orig_category":"Mechanik Mechanische Werkst\u00e4tten",
    "sg:phone":"+41 32 481 30 49",
    "sg:postcode":"2710",
    "sg:province":"Bern",
    "wof:name":"Paroz Claude-alain, Revita",
    "wof:placetype":"venue"
},
  "geometry": {"coordinates":[7.2009711266,47.222328186],"type":"Point"}
}