{
  "type": "Feature",
  "properties": {
    "iso:country":"CH",
    "sg:address":"Randenstrasse 59",
    "sg:city":"Schaffhausen",
    "sg:orig_category":"Non-Classified Establishments",
    "sg:phone":"+41 52 632 19 00",
    "sg:postcode":"8202",
    "sg:province":"Schaffhausen",
    "wof:name":"Klinik Belair Ag",
    "wof:placetype":"venue"
},
  "geometry": {"coordinates":[8.6240797043,47.7009887695],"type":"Point"}
}