{
  "type": "Feature",
  "properties": {
    "iso:country":"CH",
    "sg:address":"Ebmattstrasse 12",
    "sg:city":"Bubikon",
    "sg:orig_category":"Mechanik",
    "sg:phone":"+41 55 243 16 27",
    "sg:postcode":"8608",
    "sg:province":"Z\u00fcrich",
    "wof:name":"Bauert Ag",
    "wof:placetype":"venue"
},
  "geometry": {"coordinates":[8.8231048584,47.2687454224],"type":"Point"}
}