{
  "type": "Feature",
  "properties": {
    "iso:country":"CH",
    "sg:address":"5035",
    "sg:city":"Unterentfelden",
    "sg:orig_category":"Politische Parteien CVP",
    "sg:phone":"+41 56 222 97 97",
    "sg:postcode":"5035",
    "sg:province":"Aargau",
    "wof:name":"Cvp Ortsparteipr\u00e4sident",
    "wof:placetype":"venue"
},
  "geometry": {"coordinates":[8.0446243286,47.3672866821],"type":"Point"}
}