{
  "type": "Feature",
  "properties": {
    "iso:country":"CH",
    "sg:address":"Route De La Vieille Crausa 2",
    "sg:city":"Lugnorre",
    "sg:orig_category":"Bauschreinerei Herstellung von M\u00f6beln verschiedener Art",
    "sg:phone":"+41 26 673 18 32",
    "sg:postcode":"1789",
    "sg:province":"Fribourg",
    "wof:name":"Michel Petter Menuiserie & \u00e9b\u00e9nisterie",
    "wof:placetype":"venue"
},
  "geometry": {"coordinates":[7.0763669014,46.9496154785],"type":"Point"}
}