{
  "type": "Feature",
  "properties": {
    "addr:full":"Dorfstrasse 38 Matzendorf Solothurn 4713",
    "addr:housenumber":"38",
    "addr:postcode":"4713",
    "addr:street":"Dorfstrasse",
    "iso:country":"CH",
    "sg:address":"Dorfstrasse 38",
    "sg:city":"Matzendorf",
    "sg:orig_category":"Bauspenglerei Sanit\u00e4rinstallation",
    "sg:phone":"+41 62 394 12 87",
    "sg:postcode":"4713",
    "sg:province":"Solothurn",
    "wof:name":"Kurt Wyss San.installationen Spenglerei",
    "wof:placetype":"venue"
},
  "geometry": {"coordinates":[7.629594,47.306255],"type":"Point"}
}