{
  "type": "Feature",
  "properties": {
    "iso:country":"CH",
    "sg:address":"Luzernerstrasse 186",
    "sg:city":"Merlischachen",
    "sg:orig_category":"Herstellung von Ger\u00e4ten der Elektrizit\u00e4tserzeugung, -verteilung u.\u00e4. -Herstellung von elektronischen",
    "sg:phone":"+41 41 448 04 44",
    "sg:postcode":"6402",
    "sg:province":"Schwyz",
    "wof:name":"Reltec Gmbh",
    "wof:placetype":"venue"
},
  "geometry": {"coordinates":[8.4100608826,47.0669784546],"type":"Point"}
}