{
  "type": "Feature",
  "properties": {
    "iso:country":"CH",
    "sg:city":"Sempach",
    "sg:orig_category":"Bildung and Forschung, Sonstiges zu Bildung U Forschung",
    "sg:phone":"+41 41 462 97 00",
    "sg:postcode":"6204",
    "sg:province":"Luzern",
    "wof:name":"Schweizerische Vogelwarte",
    "wof:placetype":"venue"
},
  "geometry": {"coordinates":[8.192195,47.134716],"type":"Point"}
}