{
  "type": "Feature",
  "properties": {
    "iso:country":"CH",
    "sg:address":"H\u00fchnerb\u00fchlstrasse 4 3065 Bolligen. Postfach",
    "sg:city":"Bolligen",
    "sg:orig_category":"Druck ohne Zeitungsdruck Offsetdruck",
    "sg:phone":"+41 71 744 45 22",
    "sg:postcode":"3065",
    "sg:province":"Bern",
    "wof:name":"Stahlstich-druck Zellweger Ag",
    "wof:placetype":"venue"
},
  "geometry": {"coordinates":[9.6377496719,47.4223709106],"type":"Point"}
}