{
  "type": "Feature",
  "properties": {
    "iso:country":"CH",
    "sg:address":"Sonnenhof 10",
    "sg:city":"Luzern",
    "sg:orig_category":"Fachdetailhandel in Verkaufsr\u00e4umen",
    "sg:postcode":"6004",
    "sg:province":"Luzern",
    "wof:name":"Ilokit Sa",
    "wof:placetype":"venue"
},
  "geometry": {"coordinates":[8.9501132965,45.9898834229],"type":"Point"}
}