{
  "type": "Feature",
  "properties": {
    "iso:country":"CH",
    "sg:address":"Aarauerstrasse 23",
    "sg:city":"Reinach",
    "sg:classifiers":[
        {
            "category":"Military Area",
            "subcategory":"Air Force Base",
            "type":"Public Place"
        }
    ],
    "sg:phone":"+41 62 771 90 20",
    "sg:postcode":"5734",
    "sg:province":"Aargau",
    "sg:tags":[
        "conservatory",
        "aluminium",
        "construction",
        "system"
    ],
    "wof:name":"Wintergarten Neogard Ag",
    "wof:placetype":"venue"
},
  "geometry": {"coordinates":[8.178472,47.259781],"type":"Point"}
}