{
  "type": "Feature",
  "properties": {
    "iso:country":"CH",
    "sg:address":"Industrie Kleinzaun",
    "sg:city":"Netstal",
    "sg:orig_category":"Herstellung von Metallerzeugnissen ohne Maschinenbau",
    "sg:phone":"+41 55 645 53 53",
    "sg:postcode":"8754",
    "sg:province":"Glarus",
    "wof:name":"Inotec Edelstahltechnik Ag",
    "wof:placetype":"venue"
},
  "geometry": {"coordinates":[9.0603437424,47.0675811768],"type":"Point"}
}