{
  "type": "Feature",
  "properties": {
    "iso:country":"CH",
    "sg:address":"Weingasse 179",
    "sg:city":"Jonen",
    "sg:orig_category":"Elektrizit\u00e4tsversorgung",
    "sg:phone":"+41 56 634 16 25",
    "sg:postcode":"8916",
    "sg:province":"Aargau",
    "wof:name":"Elektrizit\u00e4tsgenossenschaft Jonen",
    "wof:placetype":"venue"
},
  "geometry": {"coordinates":[8.3983201981,47.2931098938],"type":"Point"}
}