{
  "type": "Feature",
  "properties": {
    "iso:country":"CH",
    "sg:address":"Sahlistrasse 42",
    "sg:city":"Bern",
    "sg:orig_category":"Kinderkrippen U horte",
    "sg:phone":"+41 31 301 91 09",
    "sg:postcode":"3012",
    "sg:province":"Bern",
    "wof:name":"Studentenkinderkrippe Bern",
    "wof:placetype":"venue"
},
  "geometry": {"coordinates":[7.4260687828,46.9523849487],"type":"Point"}
}