{
  "type": "Feature",
  "properties": {
    "addr:full":"Lachenstrasse 3 Wittinsburg Basel-Landschaft 4443",
    "addr:housenumber":"3",
    "addr:postcode":"4443",
    "addr:street":"Lachenstrasse",
    "iso:country":"CH",
    "sg:address":"Lachenstrasse 3",
    "sg:city":"Wittinsburg",
    "sg:orig_category":"Allgemeiner Hoch U Tiefbau",
    "sg:phone":"+41 62 299 03 30",
    "sg:postcode":"4443",
    "sg:province":"Basel-Landschaft",
    "wof:name":"Hansruedi M\u00fcller, Baugesch\u00e4ft",
    "wof:placetype":"venue"
},
  "geometry": {"coordinates":[7.843086,47.426563],"type":"Point"}
}