{
  "type": "Feature",
  "properties": {
    "iso:country":"CH",
    "sg:address":"Ziegelbr\u00fcckstrasse 34 8867 Niederurnen. Postfach",
    "sg:city":"Niederurnen",
    "sg:orig_category":"Grosshandel mit Nahrungsmitteln, Getr\u00e4nken U Tabakwaren ohne ausgepr\u00e4gten Schwerpunkt Handelsvermitt",
    "sg:phone":"+41 26 672 27 48",
    "sg:postcode":"8867",
    "sg:province":"Glarus",
    "wof:name":"Steffen's Gmbh Food Products Halbfabrikate F\u00fcr Die Verarbeitende Lebensmittelindustrie U. Konsumfertige Lebensmittel F\u00fcr Den Einzelhandel; Handel",
    "wof:placetype":"venue"
},
  "geometry": {"coordinates":[7.2000718117,46.9318275452],"type":"Point"}
}