{
  "type": "Feature",
  "properties": {
    "iso:country":"CH",
    "sg:address":"Cho D'punt",
    "sg:city":"Samedan",
    "sg:orig_category":"Einzelhandel mit Automobilen Einzelhandel mit Automobilteilen U Zubeh\u00f6r",
    "sg:phone":"+41 81 852 47 43",
    "sg:postcode":"7503",
    "sg:province":"Graubunden",
    "wof:name":"Auto Drei Piz Ag Suzuki Vertretung Autoshop Automobile Pal\u00fc Ag Ford Vertretung",
    "wof:placetype":"venue"
},
  "geometry": {"coordinates":[9.8728303909,46.5353507996],"type":"Point"}
}