{
  "type": "Feature",
  "properties": {
    "iso:country":"CH",
    "sg:address":"Rue Benjamin-franklin 2",
    "sg:city":"Gen\u00e8ve",
    "sg:orig_category":"Arztpraxen",
    "sg:phone":"+41 22 344 55 80",
    "sg:postcode":"1201",
    "sg:province":"Gen\u00e8ve",
    "wof:name":"Dr M\u00e9d. Marie-pascale Paccolat M\u00e9decin Sp\u00e9cialiste Fmh",
    "wof:placetype":"venue"
},
  "geometry": {"coordinates":[6.136934,46.208164],"type":"Point"}
}