{
  "type": "Feature",
  "properties": {
    "iso:country":"CH",
    "sg:address":"Rue Du Four 7",
    "sg:city":"Yverdon-les-bains",
    "sg:orig_category":"Advokaturb\u00fcros",
    "sg:phone":"+41 19307505",
    "sg:postcode":"1400",
    "sg:province":"Vaud",
    "wof:name":"Streiff Pellegrini & Von Kaenel",
    "wof:placetype":"venue"
},
  "geometry": {"coordinates":[8.796392,47.321712],"type":"Point"}
}