{
  "type": "Feature",
  "properties": {
    "iso:country":"CH",
    "sg:address":"Chemin De L'etang 46",
    "sg:city":"Ch\u00e2telaine",
    "sg:orig_category":"Erwachsenenbildung U Unterricht",
    "sg:phone":"+41 22 979 33 79",
    "sg:postcode":"1219",
    "sg:province":"Gen\u00e8ve",
    "wof:name":"Esm Ecole De Management",
    "wof:placetype":"venue"
},
  "geometry": {"coordinates":[6.0969829559,49.6145744324],"type":"Point"}
}