{
  "type": "Feature",
  "properties": {
    "iso:country":"CH",
    "sg:address":"L\u00f6wengrube 12 6014 Littau. Postfach",
    "sg:city":"Littau",
    "sg:orig_category":"Architektur U Ingenieurb\u00fcros",
    "sg:postcode":"6014",
    "sg:province":"Luzern",
    "wof:name":"K\u00e4ch Bauberatungen Ag",
    "wof:placetype":"venue"
},
  "geometry": {"coordinates":[8.258295,47.048363],"type":"Point"}
}