{
  "type": "Feature",
  "properties": {
    "iso:country":"CH",
    "sg:address":"Melchr\u00fctistrasse 21",
    "sg:city":"Wallisellen",
    "sg:orig_category":"Unternehmensberatung",
    "sg:phone":"+41 22 311 89 78",
    "sg:postcode":"8304",
    "sg:province":"Z\u00fcrich",
    "wof:name":"Tmf Services Sa",
    "wof:placetype":"venue"
},
  "geometry": {"coordinates":[6.1420769691,46.202419281],"type":"Point"}
}