{
  "type": "Feature",
  "properties": {
    "iso:country":"CH",
    "sg:address":"Birkenstrasse 3b 9240 Uzwil. Postfach",
    "sg:city":"Uzwil",
    "sg:orig_category":"Maler U Glasergewerbe",
    "sg:postcode":"9240",
    "sg:province":"St. Gallen",
    "wof:name":"Malereibetrieb Tairi",
    "wof:placetype":"venue"
},
  "geometry": {"coordinates":[9.1317119598,47.4346084595],"type":"Point"}
}