{
  "type": "Feature",
  "properties": {
    "iso:country":"CH",
    "sg:address":"Bleichmattstrasse 24",
    "sg:city":"Olten",
    "sg:orig_category":"Interessenvertretungen",
    "sg:postcode":"4600",
    "sg:province":"Solothurn",
    "wof:name":"Freie Evangelische Gemeinde Olten",
    "wof:placetype":"venue"
},
  "geometry": {"coordinates":[7.8975849152,47.3533363342],"type":"Point"}
}