{
  "type": "Feature",
  "properties": {
    "iso:country":"CH",
    "sg:address":"Bahnhofstrasse 4 6440 Brunnen. Postfach 656",
    "sg:city":"Brunnen",
    "sg:classifiers":[
        {
            "category":"Restaurant",
            "type":"Food & Drink"
        }
    ],
    "sg:phone":"+41 71 761 12 01",
    "sg:postcode":"6440",
    "sg:province":"Schwyz",
    "wof:name":"Restaurant Taube",
    "wof:placetype":"venue"
},
  "geometry": {"coordinates":[9.5461158752,47.3184547424],"type":"Point"}
}