{
  "type": "Feature",
  "properties": {
    "iso:country":"CH",
    "sg:address":"Fabrikstrasse 5",
    "sg:city":"Ermenswil",
    "sg:orig_category":"Herstellung von Metallerzeugnissen ohne Maschinenbau Maschinenbau",
    "sg:phone":"+41 32 351 20 81",
    "sg:postcode":"8734",
    "sg:province":"St. Gallen",
    "wof:name":"Bandi & Gerber Ag",
    "wof:placetype":"venue"
},
  "geometry": {"coordinates":[7.3849539757,47.1432189941],"type":"Point"}
}