{
  "type": "Feature",
  "properties": {
    "iso:country":"CH",
    "sg:address":"Sonnenrain 19",
    "sg:city":"Biberist",
    "sg:orig_category":"Vermietung U Verpachtung von eigenen Immobilien Vermittlung von Immobilien",
    "sg:phone":"+41 71 911 17 33",
    "sg:postcode":"4562",
    "sg:province":"Solothurn",
    "wof:name":"Valista Immobilien Ag",
    "wof:placetype":"venue"
},
  "geometry": {"coordinates":[9.0449714661,47.4638404846],"type":"Point"}
}