{
  "type": "Feature",
  "properties": {
    "iso:country":"CH",
    "sg:address":"Neuweg 6",
    "sg:city":"Lausen",
    "sg:orig_category":"Druckweiterverarbeitung",
    "sg:phone":"+41 61 921 25 67",
    "sg:postcode":"4415",
    "sg:province":"Basel-Landschaft",
    "wof:name":"Andr\u00e9 H\u00e4gler Buchbinderei",
    "wof:placetype":"venue"
},
  "geometry": {"coordinates":[7.758035183,47.4738922119],"type":"Point"}
}