{
  "type": "Feature",
  "properties": {
    "iso:country":"CH",
    "sg:address":"Hottingerstrasse 14a 8032 Z\u00fcrich",
    "sg:city":"Zust",
    "sg:orig_category":"Fachdetailhandel in Verkaufsr\u00e4umen",
    "sg:phone":"+41 12017988",
    "sg:postcode":"32",
    "wof:name":"Bijoux, Grognot Jocelyne, Gemmologue Gia Schmuck, Edelsteine, Perlen Usw; Expertisen, Herst., Kauf, Verkauf",
    "wof:placetype":"venue"
},
  "geometry": {"coordinates":[8.5679702759,47.3668403625],"type":"Point"}
}