{
  "type": "Feature",
  "properties": {
    "iso:country":"CH",
    "sg:address":"Rue Du Coppet 12",
    "sg:city":"Monthey",
    "sg:orig_category":"Fachdetailhandel in Verkaufsr\u00e4umen",
    "sg:phone":"+41 24 471 38 61",
    "sg:postcode":"1870",
    "sg:province":"Valais",
    "wof:name":"Massa, Giovanni",
    "wof:placetype":"venue"
},
  "geometry": {"coordinates":[6.9500861168,46.2525253296],"type":"Point"}
}