{
  "type": "Feature",
  "properties": {
    "iso:country":"CH",
    "sg:address":"Lindenweg 10",
    "sg:city":"Dotzigen",
    "sg:orig_category":"Grosshandel mit Werkzeugmaschinen",
    "sg:phone":"+41 32 351 31 76",
    "sg:postcode":"3293",
    "sg:province":"Bern",
    "wof:name":"Scheidegger Max",
    "wof:placetype":"venue"
},
  "geometry": {"coordinates":[7.3380708694,47.1173019409],"type":"Point"}
}