{
  "type": "Feature",
  "properties": {
    "iso:country":"CH",
    "sg:address":"M\u00f6nchhof 1",
    "sg:city":"M\u00f6nchaltorf",
    "sg:orig_category":"Detailhandel mit Brot, Back U S\u00fcsswaren",
    "sg:phone":"+41 19481090",
    "sg:postcode":"8617",
    "sg:province":"Z\u00fcrich",
    "wof:name":"M\u00f6nchhof Beck",
    "wof:placetype":"venue"
},
  "geometry": {"coordinates":[8.722126,47.311272],"type":"Point"}
}