{
  "type": "Feature",
  "properties": {
    "iso:country":"CH",
    "sg:address":"B\u00f6rsenstrasse 14",
    "sg:city":"Z\u00fcrich",
    "sg:orig_category":"Glaserei",
    "sg:phone":"+41 12115576",
    "sg:postcode":"8001",
    "sg:province":"Z\u00fcrich",
    "wof:name":"Aurelio Rom\u00e9o De Giacomi Glaserei",
    "wof:placetype":"venue"
},
  "geometry": {"coordinates":[8.5408935547,47.3681526184],"type":"Point"}
}