{
  "type": "Feature",
  "properties": {
    "iso:country":"CH",
    "sg:address":"Laamenstr. 715",
    "sg:city":"Hallau",
    "sg:orig_category":"Detailhandel mit Metallwaren, Anstrichmitteln, Glaswaren, Bau U Heimwerkerbedarf",
    "sg:phone":"+41 52 681 16 92",
    "sg:postcode":"8215",
    "sg:province":"Schaffhausen",
    "wof:name":"Schmid Otto, Handelsvertretungen",
    "wof:placetype":"venue"
},
  "geometry": {"coordinates":[8.4509487152,47.6948471069],"type":"Point"}
}