{
  "type": "Feature",
  "properties": {
    "addr:full":"Morderloch 3 Klosters Graubunden 7250",
    "addr:housenumber":"3",
    "addr:postcode":"7250",
    "addr:street":"Morderloch",
    "iso:country":"CH",
    "sg:address":"Morderloch 3",
    "sg:city":"Klosters",
    "sg:orig_category":"Allgemeiner Hoch U Tiefbau Hoch U Tiefbau",
    "sg:phone":"+41 81 422 25 04",
    "sg:postcode":"7250",
    "sg:province":"Graubunden",
    "wof:name":"Johann Rudolf Klucker Bauunternehmung",
    "wof:placetype":"venue"
},
  "geometry": {"coordinates":[9.880635,46.880001],"type":"Point"}
}