{
  "type": "Feature",
  "properties": {
    "iso:country":"CH",
    "sg:address":"Zweierstrasse 18 8000 Z\u00fcrich. Postfach",
    "sg:city":"Z\u00fcrich",
    "sg:orig_category":"Kauf U Verkauf von Immobilien auf eigene Rechnung",
    "sg:postcode":"8001",
    "sg:province":"Z\u00fcrich",
    "wof:name":"Properties Finance Ag",
    "wof:placetype":"venue"
},
  "geometry": {"coordinates":[8.5276021957,47.3732681274],"type":"Point"}
}