{
  "type": "Feature",
  "properties": {
    "iso:country":"CH",
    "sg:address":"Luzernerstrasse 19 6330 Cham. Postfach",
    "sg:city":"Cham",
    "sg:orig_category":"RESTAURANTS: TEA-ROOMS",
    "sg:postcode":"6330",
    "sg:province":"Zug",
    "wof:name":"Da Silva Abel & Maria Helena",
    "wof:placetype":"venue"
},
  "geometry": {"coordinates":[23.8774108887,47.1442298889],"type":"Point"}
}