{
  "type": "Feature",
  "properties": {
    "iso:country":"CH",
    "sg:address":"R\u00fctistrasse 1",
    "sg:city":"Emmen",
    "sg:orig_category":"Sanit\u00e4r, Heizungs U L\u00fcftungsinstallation",
    "sg:phone":"+41 41 250 57 40",
    "sg:postcode":"6032",
    "sg:province":"Luzern",
    "wof:name":"Stutz W. Ag",
    "wof:placetype":"venue"
},
  "geometry": {"coordinates":[8.2855882645,47.0826339722],"type":"Point"}
}