{
  "type": "Feature",
  "properties": {
    "iso:country":"CH",
    "sg:address":"Metallstrasse 9a",
    "sg:city":"Zug",
    "sg:orig_category":"Maschinen and Apparate divers Grosshandel",
    "sg:phone":"+41 41 726 56 94",
    "sg:postcode":"6300",
    "sg:province":"Zug",
    "wof:name":"Wille Geotechnik Ag",
    "wof:placetype":"venue"
},
  "geometry": {"coordinates":[8.5183458328,47.1736183167],"type":"Point"}
}