{
  "type": "Feature",
  "properties": {
    "iso:country":"CH",
    "sg:address":"Ringstrasse 38 7000 Chur. Postfach 165",
    "sg:city":"Chur",
    "sg:orig_category":"Instandhaltung U Reparatur von Automobilen",
    "sg:phone":"+41 81 284 84 54",
    "sg:postcode":"7007",
    "sg:province":"Graubunden",
    "wof:name":"Sport-garage Berger Silvio",
    "wof:placetype":"venue"
},
  "geometry": {"coordinates":[9.515332222,46.8544464111],"type":"Point"}
}