{
  "type": "Feature",
  "properties": {
    "iso:country":"CH",
    "sg:address":"Ramuz Avenue C.-f.- 43 1009 Pully. Postfach",
    "sg:city":"Pully",
    "sg:orig_category":"Unclassifiable Establishments",
    "sg:phone":"+41 22 318 59 80",
    "sg:postcode":"1009",
    "sg:province":"Vaud",
    "wof:name":"Globeholding Sa",
    "wof:placetype":"venue"
},
  "geometry": {"coordinates":[6.6598000526,46.5102577209],"type":"Point"}
}