{
  "type": "Feature",
  "properties": {
    "iso:country":"CH",
    "sg:address":"Steigstrasse 53",
    "sg:city":"Uster",
    "sg:classifiers":[
        {
            "category":"Banks & Credit Unions",
            "subcategory":"Bank",
            "type":"Services"
        }
    ],
    "sg:phone":"+41 19403838",
    "sg:postcode":"8610",
    "sg:province":"Z\u00fcrich",
    "wof:name":"Schweiz. Mobiliar",
    "wof:placetype":"venue"
},
  "geometry": {"coordinates":[8.727237,47.340847],"type":"Point"}
}