{
  "type": "Feature",
  "properties": {
    "iso:country":"CH",
    "sg:address":"Sus-chez-carrel",
    "sg:city":"Dully",
    "sg:orig_category":"Herstellung von Konstruktionsteilen, Fertigbauteilen U Ausbauelementen aus Holz Innenarchitekturb\u00fcro",
    "sg:phone":"+41 21 824 14 32",
    "sg:postcode":"1195",
    "sg:province":"Vaud",
    "wof:name":"Marcel Blondel Ensemblier",
    "wof:placetype":"venue"
},
  "geometry": {"coordinates":[6.2956819534,46.4300880432],"type":"Point"}
}