{
  "type": "Feature",
  "properties": {
    "iso:country":"CH",
    "sg:address":"Rue Richemont 16",
    "sg:city":"Gen\u00e8ve",
    "sg:classifiers":[
        {
            "category":"Bars & Pubs",
            "type":"Food & Drink"
        }
    ],
    "sg:phone":"+41 22 738 00 36",
    "sg:postcode":"1202",
    "sg:province":"Gen\u00e8ve",
    "sg:tags":[
        "restaurant"
    ],
    "wof:name":"Caf\u00e9 Dolly Club",
    "wof:placetype":"venue"
},
  "geometry": {"coordinates":[6.148351,46.215004],"type":"Point"}
}