{
  "type": "Feature",
  "properties": {
    "iso:country":"CH",
    "sg:address":"Bernasconi Via 12 6853 Ligornetto. Postfach",
    "sg:city":"Ligornetto",
    "sg:orig_category":"Verwaltung von Immobilien",
    "sg:postcode":"6853",
    "sg:province":"Ticino",
    "wof:name":"Flufer Sagl Esercizi Pubblici Ecc",
    "wof:placetype":"venue"
},
  "geometry": {"coordinates":[8.9539613724,45.8620796204],"type":"Point"}
}