{
  "type": "Feature",
  "properties": {
    "addr:full":"Chemin De La Concorde 33 Bernex Gen\u00e8ve 1233",
    "addr:housenumber":"33",
    "addr:postcode":"1233",
    "addr:street":"Chemin De La Concorde",
    "iso:country":"CH",
    "sg:address":"Chemin De La Concorde 33",
    "sg:city":"Bernex",
    "sg:orig_category":"Bauspenglerei Sanit\u00e4r, Heizungs U L\u00fcftungsinstallation",
    "sg:phone":"+41 22 757 02 04",
    "sg:postcode":"1233",
    "sg:province":"Gen\u00e8ve",
    "wof:name":"Formica",
    "wof:placetype":"venue"
},
  "geometry": {"coordinates":[6.07269,46.174946],"type":"Point"}
}