{
  "type": "Feature",
  "properties": {
    "iso:country":"CH",
    "sg:address":"Linoleum Via 14",
    "sg:city":"Giubiasco",
    "sg:orig_category":"Erbringung von Dienstleistungen f\u00fcr Unternehmen",
    "sg:phone":"+41 91 857 53 78",
    "sg:postcode":"6512",
    "sg:province":"Ticino",
    "wof:name":"Smf - Sondermodellefabrik Ag",
    "wof:placetype":"venue"
},
  "geometry": {"coordinates":[9.0051240921,46.1746940613],"type":"Point"}
}