{
  "type": "Feature",
  "properties": {
    "iso:country":"CH",
    "sg:address":"Alte Chamerstrasse 19",
    "sg:city":"Rotkreuz",
    "sg:orig_category":"Ingenieurb\u00fcros Maschinenbau",
    "sg:phone":"+41 41 790 20 66",
    "sg:postcode":"6343",
    "sg:province":"Zug",
    "wof:name":"J. Himmelrich & J. Bachmann Ingenieurb\u00fcro",
    "wof:placetype":"venue"
},
  "geometry": {"coordinates":[8.4298095703,47.1433296204],"type":"Point"}
}