{
  "type": "Feature",
  "properties": {
    "iso:country":"CH",
    "sg:address":"M\u00fchlentalstrasse 243",
    "sg:city":"Schaffhausen",
    "sg:orig_category":"Allgemeiner Hoch U Tiefbau Hoch U Tiefbau",
    "sg:phone":"+41 79 236 54 26",
    "sg:postcode":"8200",
    "sg:province":"Schaffhausen",
    "wof:name":"Arche Bau Battel Gmbh",
    "wof:placetype":"venue"
},
  "geometry": {"coordinates":[8.632682,47.711803],"type":"Point"}
}