{
  "type": "Feature",
  "properties": {
    "iso:country":"CH",
    "sg:address":"Margarethenstrasse 77",
    "sg:city":"Binningen",
    "sg:orig_category":"Installation von Heizungs, L\u00fcftungs U Klimaanlagen",
    "sg:phone":"+41 61 421 19 10",
    "sg:postcode":"4102",
    "sg:province":"Basel-Landschaft",
    "wof:name":"Robert Schweiger K\u00fchlanlagen",
    "wof:placetype":"venue"
},
  "geometry": {"coordinates":[7.5760998726,47.5351409912],"type":"Point"}
}