{
  "type": "Feature",
  "properties": {
    "iso:country":"CH",
    "sg:address":"1942",
    "sg:city":"Levron",
    "sg:orig_category":"Bauschreinerei",
    "sg:phone":"+41 27 481 53 89",
    "sg:postcode":"1942",
    "sg:province":"Valais",
    "wof:name":"L\u00e9opold Gasser Entreprise De Menuiserie",
    "wof:placetype":"venue"
},
  "geometry": {"coordinates":[7.52025,46.316292],"type":"Point"}
}