{
  "type": "Feature",
  "properties": {
    "iso:country":"CH",
    "sg:address":"Blumenrain 12",
    "sg:city":"Basel",
    "sg:orig_category":"RESTAURANTS: TEA-ROOMS",
    "sg:phone":"+41 61 261 30 44",
    "sg:postcode":"4051",
    "sg:province":"Basel-Stadt",
    "wof:name":"Picobello Gastro Ag",
    "wof:placetype":"venue"
},
  "geometry": {"coordinates":[7.5873222351,47.5607795715],"type":"Point"}
}