{
  "type": "Feature",
  "properties": {
    "addr:full":"Schwarzenburgstr. 761 3098 K\u00f6niz. Postfach Niederscherli Bern 3145",
    "addr:housenumber":"761",
    "addr:postcode":"3098;3145",
    "addr:street":"Postfach",
    "iso:country":"CH",
    "sg:address":"Schwarzenburgstr. 761 3098 K\u00f6niz. Postfach",
    "sg:city":"Niederscherli",
    "sg:orig_category":"Detailhandel mit Bekleidung",
    "sg:postcode":"3145",
    "sg:province":"Bern",
    "wof:name":"Sening Trading Lehmann Jocelyn",
    "wof:placetype":"venue"
},
  "geometry": {"coordinates":[7.40073,46.908909],"type":"Point"}
}