{
  "type": "Feature",
  "properties": {
    "iso:country":"CH",
    "sg:address":"Hauptstrasse 18",
    "sg:city":"Kleind\u00f6ttingen",
    "sg:classifiers":[
        {
            "category":"Banks & Credit Unions",
            "subcategory":"Bank",
            "type":"Services"
        }
    ],
    "sg:phone":"+41 62 876 15 15",
    "sg:postcode":"5314",
    "sg:province":"Aargau",
    "wof:name":"Raiffeisenbank B\u00f6zberg West",
    "wof:placetype":"venue"
},
  "geometry": {"coordinates":[8.08908,47.496479],"type":"Point"}
}