{
  "type": "Feature",
  "properties": {
    "iso:country":"CH",
    "sg:address":"Elisabethenanlage 11",
    "sg:city":"Basel",
    "sg:orig_category":"Factory Planning",
    "sg:phone":"+41 61 279 44 44",
    "sg:postcode":"4051",
    "sg:province":"Basel-Stadt",
    "wof:name":"Otb Ag Planung Und Beratung F\u00fcr Organisation,technik Und Bau",
    "wof:placetype":"venue"
},
  "geometry": {"coordinates":[7.5885748863,47.5489883423],"type":"Point"}
}