{
  "type": "Feature",
  "properties": {
    "iso:country":"CH",
    "sg:address":"3970",
    "sg:city":"Salgesch",
    "sg:orig_category":"Bauschreinerei",
    "sg:phone":"+41 27 456 36 50",
    "sg:postcode":"3970",
    "sg:province":"Valais",
    "wof:name":"Jean-claude Brunner Schreinerei",
    "wof:placetype":"venue"
},
  "geometry": {"coordinates":[7.569615,46.311401],"type":"Point"}
}