{
  "type": "Feature",
  "properties": {
    "iso:country":"CH",
    "sg:address":"Rue Des Marronniers 4",
    "sg:city":"Martigny",
    "sg:classifiers":[
        {
            "category":"Restaurant",
            "type":"Food & Drink"
        }
    ],
    "sg:phone":"+41 27 722 22 68",
    "sg:postcode":"1920",
    "sg:province":"Valais",
    "wof:name":"Caf\u00e9 Midi",
    "wof:placetype":"venue"
},
  "geometry": {"coordinates":[7.0734992027,46.1009788513],"type":"Point"}
}