{
  "type": "Feature",
  "properties": {
    "addr:full":"Langnaustrasse 21 Zollbr\u00fcck Bern 3436",
    "addr:housenumber":"21",
    "addr:postcode":"3436",
    "addr:street":"Langnaustrasse",
    "iso:country":"CH",
    "sg:address":"Langnaustrasse 21",
    "sg:city":"Zollbr\u00fcck",
    "sg:orig_category":"Regionalbanken U Sparkassen",
    "sg:phone":"+41 34 496 94 11",
    "sg:postcode":"3436",
    "sg:province":"Bern",
    "wof:name":"Valiant Bank",
    "wof:placetype":"venue"
},
  "geometry": {"coordinates":[7.749183,46.97242],"type":"Point"}
}