{
  "type": "Feature",
  "properties": {
    "iso:country":"CH",
    "sg:address":"Av De La Gare 2",
    "sg:city":"Grandson",
    "sg:classifiers":[
        {
            "category":"Shopping",
            "subcategory":"Hobbies, Toys, & Games",
            "type":"Retail Goods"
        }
    ],
    "sg:phone":"+41 24 445 44 33",
    "sg:postcode":"1422",
    "sg:province":"Vaud",
    "sg:tags":[
        "product",
        "miscellaneous",
        "entertainment"
    ],
    "wof:name":"Sugyp Import Chez Porchet",
    "wof:placetype":"venue"
},
  "geometry": {"coordinates":[6.6421508789,46.8067855835],"type":"Point"}
}