{
  "type": "Feature",
  "properties": {
    "iso:country":"CH",
    "sg:address":"Altenweg 7",
    "sg:city":"Frutigen",
    "sg:orig_category":"Bauspenglerei Zimmerei, Dachdeckerei, Bauspenglerei U Abdichtung",
    "sg:phone":"+41 33 671 16 06",
    "sg:postcode":"3714",
    "sg:province":"Bern",
    "wof:name":"Paul Ryter Ag, Sanit\u00e4re Anlagen-spenglerei, Heizungen, In Frutigen",
    "wof:placetype":"venue"
},
  "geometry": {"coordinates":[7.649774,46.583569],"type":"Point"}
}