{
  "type": "Feature",
  "properties": {
    "iso:country":"CH",
    "sg:address":"Hof",
    "sg:city":"Wildhaus",
    "sg:orig_category":"Fahrschulen, Flugschulen",
    "sg:phone":"+41 71 999 22 77",
    "sg:postcode":"9658",
    "sg:province":"St. Gallen",
    "wof:name":"Peter Vetsch Autofahrschule",
    "wof:placetype":"venue"
},
  "geometry": {"coordinates":[9.3526554108,47.204826355],"type":"Point"}
}