{
  "type": "Feature",
  "properties": {
    "iso:country":"CH",
    "sg:address":"General Guisan-strasse 75",
    "sg:city":"Zofingen",
    "sg:orig_category":"Polizei",
    "sg:phone":"+41 62 751 41 55",
    "sg:postcode":"4800",
    "sg:province":"Aargau",
    "wof:name":"Kantonspolizei",
    "wof:placetype":"venue"
},
  "geometry": {"coordinates":[7.9463100433,47.2886199951],"type":"Point"}
}