{
  "type": "Feature",
  "properties": {
    "iso:country":"CH",
    "sg:address":"Cit\u00e9 De La Rosi\u00e8re 2",
    "sg:city":"Estavayer-le-lac",
    "sg:orig_category":"Physiotherapie",
    "sg:phone":"+41 26 663 21 62",
    "sg:postcode":"1470",
    "sg:province":"Fribourg",
    "wof:name":"Jean-marc Thorimbert Physioth\u00e9rapie",
    "wof:placetype":"venue"
},
  "geometry": {"coordinates":[6.8421139717,46.8458442688],"type":"Point"}
}