{
  "type": "Feature",
  "properties": {
    "iso:country":"CH",
    "sg:address":"2746",
    "sg:city":"Cr\u00e9mines",
    "sg:orig_category":"Herstellung von Konstruktionsteilen, Fertigbauteilen U Ausbauelementen aus Holz",
    "sg:postcode":"2746",
    "sg:province":"Bern",
    "wof:name":"Girod S\u00e0rl",
    "wof:placetype":"venue"
},
  "geometry": {"coordinates":[6.6878461838,46.8391838074],"type":"Point"}
}