{
  "type": "Feature",
  "properties": {
    "iso:country":"CH",
    "sg:address":"Via Capelli 28",
    "sg:city":"Lugano",
    "sg:orig_category":"Erbringung von Dienstleistungen f\u00fcr Unternehmen",
    "sg:phone":"+41 91 971 79 42",
    "sg:postcode":"6900",
    "sg:province":"Ticino",
    "wof:name":"Identity Sa",
    "wof:placetype":"venue"
},
  "geometry": {"coordinates":[8.9605493546,46.0087547302],"type":"Point"}
}