{
  "type": "Feature",
  "properties": {
    "iso:country":"CH",
    "sg:address":"Via Vite 3",
    "sg:city":"Stabio",
    "sg:classifiers":[
        {
            "category":"Shopping",
            "subcategory":"Clothing, Apparel, & Fashions",
            "type":"Retail Goods"
        }
    ],
    "sg:phone":"+41 71 277 70 55",
    "sg:postcode":"6855",
    "sg:province":"Ticino",
    "sg:tags":[
        "clothing",
        "fabric"
    ],
    "wof:name":"Steiger Textil Ag",
    "wof:placetype":"venue"
},
  "geometry": {"coordinates":[9.335933,47.409859],"type":"Point"}
}