{
  "type": "Feature",
  "properties": {
    "iso:country":"CH",
    "sg:address":"Grand-rue 16",
    "sg:city":"Founex",
    "sg:orig_category":"Softwareentwicklung U beratung",
    "sg:phone":"+41 22 776 92 76",
    "sg:postcode":"1297",
    "sg:province":"Vaud",
    "wof:name":"Cabling Services, B. Colacioppo",
    "wof:placetype":"venue"
},
  "geometry": {"coordinates":[6.1942181587,46.3343849182],"type":"Point"}
}