{
  "type": "Feature",
  "properties": {
    "addr:full":"Ebnaterstrasse 39 Ebnat-kappel St. Gallen 9642",
    "addr:housenumber":"39",
    "addr:postcode":"9642",
    "addr:street":"Ebnaterstrasse",
    "iso:country":"CH",
    "sg:address":"Ebnaterstrasse 39",
    "sg:city":"Ebnat-kappel",
    "sg:orig_category":"Autogaragen",
    "sg:phone":"+41 71 993 17 21",
    "sg:postcode":"9642",
    "sg:province":"St. Gallen",
    "wof:name":"Ernst Wymann Hofgarage",
    "wof:placetype":"venue"
},
  "geometry": {"coordinates":[9.12566,47.26075],"type":"Point"}
}