{
  "type": "Feature",
  "properties": {
    "addr:full":"Hegiweg 4 Eglisau Z\u00fcrich 8193",
    "addr:housenumber":"4",
    "addr:postcode":"8193",
    "addr:street":"Hegiweg",
    "iso:country":"CH",
    "sg:address":"Hegiweg 4",
    "sg:city":"Eglisau",
    "sg:orig_category":"Bauingenieurb\u00fcros allgemein",
    "sg:phone":"+41 24 499 16 56",
    "sg:postcode":"8193",
    "sg:province":"Z\u00fcrich",
    "wof:name":"Hans-gerhard Dauner Bureau D'ing\u00e9nieur",
    "wof:placetype":"venue"
},
  "geometry": {"coordinates":[6.99538,46.296612],"type":"Point"}
}