{
  "type": "Feature",
  "properties": {
    "iso:country":"CH",
    "sg:address":"Parkweg 5",
    "sg:city":"H\u00fcnibach",
    "sg:orig_category":"Non-Classified Establishments",
    "sg:postcode":"3626",
    "sg:province":"Bern",
    "wof:name":"B/maxim Ag",
    "wof:placetype":"venue"
},
  "geometry": {"coordinates":[7.6431808472,46.7466506958],"type":"Point"}
}