{
  "type": "Feature",
  "properties": {
    "iso:country":"CH",
    "sg:address":"Hirssattel",
    "sg:city":"Baar",
    "sg:classifiers":[
        {
            "category":"Restaurant",
            "type":"Food & Drink"
        }
    ],
    "sg:phone":"+41 41 761 95 25",
    "sg:postcode":"6340",
    "sg:province":"Zug",
    "wof:name":"Restaurant Hirssattel",
    "wof:placetype":"venue"
},
  "geometry": {"coordinates":[8.5059747696,47.2071418762],"type":"Point"}
}