{
  "type": "Feature",
  "properties": {
    "iso:country":"CH",
    "sg:address":"Costa Di Mezzo Via 85b",
    "sg:city":"Brissago",
    "sg:orig_category":"Architektur U Ingenieurb\u00fcros",
    "sg:postcode":"6614",
    "sg:province":"Ticino",
    "wof:name":"Immo-glass Sagl",
    "wof:placetype":"venue"
},
  "geometry": {"coordinates":[8.702356,46.115906],"type":"Point"}
}