{
  "type": "Feature",
  "properties": {
    "iso:country":"CH",
    "sg:address":"Rue Du Mont-blanc 4",
    "sg:city":"Gen\u00e8ve",
    "sg:orig_category":"Arztpraxen",
    "sg:phone":"+41 22 731 24 21",
    "sg:postcode":"1201",
    "sg:province":"Gen\u00e8ve",
    "wof:name":"Dr M\u00e9d. Erika Beck-t\u00fcske M\u00e9decin Sp\u00e9cialiste",
    "wof:placetype":"venue"
},
  "geometry": {"coordinates":[6.147487,46.207245],"type":"Point"}
}