{
  "type": "Feature",
  "properties": {
    "iso:country":"CH",
    "sg:address":"Engenb\u00fcelstrasse 12",
    "sg:city":"Wallisellen",
    "sg:orig_category":"Erwachsenenbildung U Unterricht",
    "sg:phone":"+41 18313910",
    "sg:postcode":"8304",
    "sg:province":"Z\u00fcrich",
    "wof:name":"Musikschule Peter Maurer",
    "wof:placetype":"venue"
},
  "geometry": {"coordinates":[8.5969934464,47.4223213196],"type":"Point"}
}