{
  "type": "Feature",
  "properties": {
    "iso:country":"CH",
    "sg:address":"En Budron 1",
    "sg:city":"Mont-sur-lausanne",
    "sg:orig_category":"Erbringung von Dienstleistungen f\u00fcr Unternehmen",
    "sg:phone":"+41 21 654 01 60",
    "sg:postcode":"1052",
    "sg:province":"Vaud",
    "wof:name":"M-design Sa",
    "wof:placetype":"venue"
},
  "geometry": {"coordinates":[6.6331439018,46.5709495544],"type":"Point"}
}