{
  "type": "Feature",
  "properties": {
    "iso:country":"CH",
    "sg:address":"Chamerstrasse 3",
    "sg:city":"Zug",
    "sg:orig_category":"Herstellung von Metallkonstruktionen Mechanik",
    "sg:phone":"+41 41 711 80 20",
    "sg:postcode":"6300",
    "sg:province":"Zug",
    "wof:name":"Schwerzmann Metallbau",
    "wof:placetype":"venue"
},
  "geometry": {"coordinates":[8.5120458603,47.171295166],"type":"Point"}
}