{
  "type": "Feature",
  "properties": {
    "iso:country":"CH",
    "sg:address":"3988",
    "sg:city":"Ulrichen",
    "sg:orig_category":"Darlehenskassen U Raiffeisenbanken",
    "sg:phone":"+41 27 973 22 56",
    "sg:postcode":"3988",
    "sg:province":"Valais",
    "wof:name":"Raiffeisenbank Obergoms",
    "wof:placetype":"venue"
},
  "geometry": {"coordinates":[8.30434,46.506405],"type":"Point"}
}