{
  "type": "Feature",
  "properties": {
    "iso:country":"CH",
    "sg:address":"Laubstenstrasse 16",
    "sg:city":"St\u00e4fa",
    "sg:orig_category":"Innendekorationsateliers",
    "sg:phone":"+41 19108807",
    "sg:postcode":"8712",
    "sg:province":"Z\u00fcrich",
    "wof:name":"Hans K\u00f6lla Tapezierergesch\u00e4ft",
    "wof:placetype":"venue"
},
  "geometry": {"coordinates":[8.5858545303,47.3183135986],"type":"Point"}
}