{
  "type": "Feature",
  "properties": {
    "iso:country":"CH",
    "sg:address":"Stationsstrasse 17a",
    "sg:city":"Schlieren",
    "sg:orig_category":"Elektrizit\u00e4tsversorgung",
    "sg:postcode":"8952",
    "sg:province":"Z\u00fcrich",
    "wof:name":"Soledia Gmbh",
    "wof:placetype":"venue"
},
  "geometry": {"coordinates":[8.4425010681,47.3932342529],"type":"Point"}
}