{
  "type": "Feature",
  "properties": {
    "iso:country":"CH",
    "sg:address":"Dorfstrasse 20",
    "sg:city":"Killwangen",
    "sg:orig_category":"G\u00fcterbef\u00f6rderung im Strassenverkehr",
    "sg:phone":"+41 56 401 28 77",
    "sg:postcode":"8956",
    "sg:province":"Aargau",
    "wof:name":"Franz Schmid Camionnage & Transporte",
    "wof:placetype":"venue"
},
  "geometry": {"coordinates":[8.3451499939,47.4310684204],"type":"Point"}
}