{
  "type": "Feature",
  "properties": {
    "iso:country":"CH",
    "sg:address":"Riedmattstrasse 16",
    "sg:city":"R\u00fcmlang",
    "sg:orig_category":"Autogaragen",
    "sg:phone":"+41 18171852",
    "sg:postcode":"8153",
    "sg:province":"Z\u00fcrich",
    "wof:name":"Matteo D'arienzo Garage",
    "wof:placetype":"venue"
},
  "geometry": {"coordinates":[8.521656,47.460766],"type":"Point"}
}