{
  "type": "Feature",
  "properties": {
    "iso:country":"CH",
    "sg:address":"Eigenackerstrasse 19",
    "sg:city":"Eglisau",
    "sg:orig_category":"Non-Classified Establishments",
    "sg:phone":"+41 18866336",
    "sg:postcode":"8193",
    "sg:province":"Z\u00fcrich",
    "wof:name":"Koch G\u00e4rten",
    "wof:placetype":"venue"
},
  "geometry": {"coordinates":[8.5176467896,47.5784301758],"type":"Point"}
}