{
  "type": "Feature",
  "properties": {
    "addr:full":"Stansstaderstrasse 80 Stans Nidwalden 6370",
    "addr:housenumber":"80",
    "addr:postcode":"6370",
    "addr:street":"Stansstaderstrasse",
    "iso:country":"CH",
    "sg:address":"Stansstaderstrasse 80",
    "sg:city":"Stans",
    "sg:orig_category":"Architektur U Ingenieurb\u00fcros Architekturb\u00fcros",
    "sg:phone":"+41 41 610 20 20",
    "sg:postcode":"6370",
    "sg:province":"Nidwalden",
    "wof:name":"B\u00fcnter & Partner, Architekturb\u00fcro",
    "wof:placetype":"venue"
},
  "geometry": {"coordinates":[8.356414,46.965424],"type":"Point"}
}