{
  "type": "Feature",
  "properties": {
    "iso:country":"CH",
    "sg:address":"Girixweg 12 5000 Aarau. Postfach",
    "sg:city":"Aarau",
    "sg:classifiers":[
        {
            "category":"Restaurant",
            "type":"Food & Drink"
        }
    ],
    "sg:phone":"+41 62 822 86 52",
    "sg:postcode":"5004",
    "sg:province":"Aargau",
    "wof:name":"Restaurant Malibu",
    "wof:placetype":"venue"
},
  "geometry": {"coordinates":[8.0577278137,47.3986320496],"type":"Point"}
}