{
  "type": "Feature",
  "properties": {
    "iso:country":"CH",
    "sg:address":"Jostenstrasse 21",
    "sg:city":"Galgenen",
    "sg:orig_category":"Hochschulen U h\u00f6here Ausbildung",
    "sg:phone":"+41 17863322",
    "sg:postcode":"8854",
    "sg:province":"Schwyz",
    "wof:name":"Steiner Dr. Hansruedi / Pro-motion",
    "wof:placetype":"venue"
},
  "geometry": {"coordinates":[8.8744277954,47.1783943176],"type":"Point"}
}