{
  "type": "Feature",
  "properties": {
    "iso:country":"CH",
    "sg:address":"Schmitterstrasse 30",
    "sg:city":"Diepoldsau",
    "sg:orig_category":"Geb\u00e4ude, Wohnungsreinigung",
    "sg:phone":"+41 71 733 77 30",
    "sg:postcode":"9444",
    "sg:province":"St. Gallen",
    "wof:name":"Jules Kuster Reinigungsunternehmen",
    "wof:placetype":"venue"
},
  "geometry": {"coordinates":[9.6565885544,47.3896903992],"type":"Point"}
}