{
  "type": "Feature",
  "properties": {
    "iso:country":"CH",
    "sg:address":"Chemin De Vers Pousaz 41",
    "sg:city":"Aigle",
    "sg:orig_category":"Gartenbau",
    "sg:phone":"+41 24 466 20 33",
    "sg:postcode":"1860",
    "sg:province":"Vaud",
    "wof:name":"Marcel Kovar Horticulture",
    "wof:placetype":"venue"
},
  "geometry": {"coordinates":[6.9660210609,46.3244018555],"type":"Point"}
}