{
  "type": "Feature",
  "properties": {
    "iso:country":"CH",
    "sg:address":"Sumpfstrasse 26 6300 Zug. Postfach",
    "sg:city":"Zug",
    "sg:orig_category":"Unternehmensberatung",
    "sg:postcode":"6300",
    "sg:province":"Zug",
    "wof:name":"Quopa Gmbh Beratung Bei Kauf Und Verkauf Von Unternehmungen Usw",
    "wof:placetype":"venue"
},
  "geometry": {"coordinates":[8.7995347977,47.2133331299],"type":"Point"}
}