{
  "type": "Feature",
  "properties": {
    "iso:country":"CH",
    "sg:address":"Casinoplatz 8 3011 Bern. Postfach",
    "sg:city":"Bern",
    "sg:orig_category":"Pensionskassen",
    "sg:postcode":"3005",
    "sg:province":"Bern",
    "wof:name":"Bvg-stiftung Der Gautschi Ag",
    "wof:placetype":"venue"
},
  "geometry": {"coordinates":[9.6220798492,47.4559402466],"type":"Point"}
}