{
  "type": "Feature",
  "properties": {
    "iso:country":"CH",
    "sg:address":"Baarerstrasse 10 6300 Zug. Postfach 1552",
    "sg:city":"Zug",
    "sg:orig_category":"Unternehmensberatung",
    "sg:phone":"+41 41 729 13 53",
    "sg:postcode":"6301",
    "sg:province":"Zug",
    "wof:name":"Aroma Caf\u00e9s Suisse Ag",
    "wof:placetype":"venue"
},
  "geometry": {"coordinates":[8.5164327621,47.1715621948],"type":"Point"}
}