{
  "type": "Feature",
  "properties": {
    "iso:country":"CH",
    "sg:address":"Ragazerstrasse 15 7320 Sargans. Postfach",
    "sg:city":"Mols",
    "sg:orig_category":"Grosshandel mit sonstigen Gebrauchs U Verbrauchsg\u00fctern",
    "sg:postcode":"8885",
    "sg:province":"St. Gallen",
    "wof:name":"Carisma Gmbh",
    "wof:placetype":"venue"
},
  "geometry": {"coordinates":[9.4443426132,47.0443572998],"type":"Point"}
}