{
  "type": "Feature",
  "properties": {
    "iso:country":"CH",
    "sg:address":"Walzm\u00fchlestrasse 51",
    "sg:city":"Frauenfeld",
    "sg:orig_category":"Personal U Stellenvermittlung Unternehmensberatung",
    "sg:phone":"+41 52 730 17 30",
    "sg:postcode":"8500",
    "sg:province":"Thurgau",
    "wof:name":"Furger & Partner Seminare & Beratung Ag",
    "wof:placetype":"venue"
},
  "geometry": {"coordinates":[8.8930978775,47.547870636],"type":"Point"}
}