{
  "type": "Feature",
  "properties": {
    "iso:country":"CH",
    "sg:address":"M\u00fchlemoosweg 1",
    "sg:city":"Oberarth",
    "sg:orig_category":"Vorschulen, Kinderg\u00e4rten",
    "sg:phone":"+41 81 416 39 10",
    "sg:postcode":"6414",
    "sg:province":"Schwyz",
    "wof:name":"Kindergarten",
    "wof:placetype":"venue"
},
  "geometry": {"coordinates":[9.8418684006,46.8077354431],"type":"Point"}
}