{
  "type": "Feature",
  "properties": {
    "iso:country":"CH",
    "sg:address":"Grand'rue 1071 Chexbres. Postfach",
    "sg:city":"Chexbres",
    "sg:orig_category":"Detailhandel mit Brot, Back U S\u00fcsswaren",
    "sg:phone":"+41 41 480 11 75",
    "sg:postcode":"1071",
    "sg:province":"Vaud",
    "wof:name":"Bieri-steiner Pius",
    "wof:placetype":"venue"
},
  "geometry": {"coordinates":[8.04946,46.978844],"type":"Point"}
}