{
  "type": "Feature",
  "properties": {
    "iso:country":"CH",
    "sg:address":"Vernand 1032 Romanel-s-lausanne Case Postale 96",
    "sg:city":"Romanel-s-lausanne",
    "sg:orig_category":"Non-Classified Establishments",
    "sg:postcode":"1032",
    "sg:province":"Vaud",
    "wof:name":"Bois, J. Cattin",
    "wof:placetype":"venue"
},
  "geometry": {"coordinates":[6.904610157,47.1760635376],"type":"Point"}
}