{
  "type": "Feature",
  "properties": {
    "addr:full":"Hobielstrasse 17 Kerns Obwalden 6064",
    "addr:housenumber":"17",
    "addr:postcode":"6064",
    "addr:street":"Hobielstrasse",
    "iso:country":"CH",
    "sg:address":"Hobielstrasse 17",
    "sg:city":"Kerns",
    "sg:orig_category":"Betrieb von Taxis Einzelhandel mit Automobilen",
    "sg:phone":"+41 41 660 41 41",
    "sg:postcode":"6064",
    "sg:province":"Obwalden",
    "wof:name":"Lussi Otto, Taxi Und Garagebetrieb",
    "wof:placetype":"venue"
},
  "geometry": {"coordinates":[8.26999,46.902298],"type":"Point"}
}