{
  "type": "Feature",
  "properties": {
    "iso:country":"CH",
    "sg:address":"Hauptstrasse 17",
    "sg:city":"Neuwilen",
    "sg:orig_category":"Tankstellen",
    "sg:phone":"+41 71 699 16 60",
    "sg:postcode":"8566",
    "sg:province":"Thurgau",
    "wof:name":"Ewald Hauri Aral-servicestation",
    "wof:placetype":"venue"
},
  "geometry": {"coordinates":[9.1345405579,47.6218528748],"type":"Point"}
}