{
  "type": "Feature",
  "properties": {
    "iso:country":"CH",
    "sg:address":"1565",
    "sg:city":"Missy",
    "sg:orig_category":"Herstellung von sonstigen landwirtschaftlichen Maschinen Instandhaltung U Reparatur von Automobilen",
    "sg:phone":"+41 26 667 13 44",
    "sg:postcode":"1565",
    "sg:province":"Fribourg",
    "wof:name":"Cottier Missy Sa",
    "wof:placetype":"venue"
},
  "geometry": {"coordinates":[6.9726400375,46.8835906982],"type":"Point"}
}