{
  "type": "Feature",
  "properties": {
    "iso:country":"CH",
    "sg:address":"Stationsstrasse 50 8472 Seuzach. Postfach",
    "sg:city":"Seuzach",
    "sg:orig_category":"Detailhandel mit Brillen U anderen Sehhilfen Fachdetailhandel in Verkaufsr\u00e4umen",
    "sg:phone":"+41 52 335 33 95",
    "sg:postcode":"8472",
    "sg:province":"Z\u00fcrich",
    "wof:name":"Optik Sonderer",
    "wof:placetype":"venue"
},
  "geometry": {"coordinates":[8.738786,47.535568],"type":"Point"}
}