{
  "type": "Feature",
  "properties": {
    "iso:country":"CH",
    "sg:address":"R\u00fceggisingerstrasse 67",
    "sg:city":"Emmen",
    "sg:orig_category":"Sonstige Kultur U Unterhaltungseinrichtungen",
    "sg:postcode":"6032",
    "sg:province":"Luzern",
    "wof:name":"Martinig Gmbh",
    "wof:placetype":"venue"
},
  "geometry": {"coordinates":[8.2844085693,47.0825500488],"type":"Point"}
}