{
  "type": "Feature",
  "properties": {
    "iso:country":"CH",
    "sg:address":"H\u00fchnerhubelstrasse 12",
    "sg:city":"Belp",
    "sg:orig_category":"Einbau von Schreinerwaren Herstellung von K\u00fcchenm\u00f6beln",
    "sg:phone":"+41 79 604 00 77",
    "sg:postcode":"3123",
    "sg:province":"Bern",
    "wof:name":"Hugo Br\u00fcnisholz K\u00fcchenbau & Parkett",
    "wof:placetype":"venue"
},
  "geometry": {"coordinates":[7.4986629486,46.9013442993],"type":"Point"}
}