{
  "type": "Feature",
  "properties": {
    "iso:country":"CH",
    "sg:address":"Neugasse 25",
    "sg:city":"Zug",
    "sg:orig_category":"Druckweiterverarbeitung",
    "sg:phone":"+41 41 711 09 15",
    "sg:postcode":"6300",
    "sg:province":"Zug",
    "wof:name":"Wyss Rupert",
    "wof:placetype":"venue"
},
  "geometry": {"coordinates":[8.515630722,47.1664276123],"type":"Point"}
}