{
  "type": "Feature",
  "properties": {
    "iso:country":"CH",
    "sg:address":"Lonay Avenue De 15",
    "sg:city":"Morges",
    "sg:orig_category":"Architektur U Ingenieurb\u00fcros",
    "sg:postcode":"1110",
    "sg:province":"Vaud",
    "wof:name":"Tecmo Sermier A.",
    "wof:placetype":"venue"
},
  "geometry": {"coordinates":[6.498785,46.508564],"type":"Point"}
}