{
  "type": "Feature",
  "properties": {
    "iso:country":"CH",
    "sg:address":"Rue Industrielle 26",
    "sg:city":"Montreux",
    "sg:orig_category":"Vermittlung von Immobilien Verwaltung von Immobilien",
    "sg:phone":"+41 21 963 52 51",
    "sg:postcode":"1820",
    "sg:province":"Vaud",
    "wof:name":"R\u00e9gie De La Riviera Sa",
    "wof:placetype":"venue"
},
  "geometry": {"coordinates":[6.913672924,46.4328689575],"type":"Point"}
}