{
  "type": "Feature",
  "properties": {
    "iso:country":"CH",
    "sg:address":"Rautistrasse 31",
    "sg:city":"Z\u00fcrich",
    "sg:orig_category":"Satzherstellung U Reproduktion Sonstiges Druckgewerbe",
    "sg:phone":"+41 17372010",
    "sg:postcode":"8047",
    "sg:province":"Z\u00fcrich",
    "wof:name":"Helio-blitz, L\u00fcthi Verena",
    "wof:placetype":"venue"
},
  "geometry": {"coordinates":[8.4487962723,47.3553581238],"type":"Point"}
}