{
  "type": "Feature",
  "properties": {
    "iso:country":"CH",
    "sg:address":"Rebenstrasse 5",
    "sg:city":"Steinhausen",
    "sg:orig_category":"Sanit\u00e4r, Heizungs U L\u00fcftungsinstallation",
    "sg:postcode":"6312",
    "sg:province":"Zug",
    "wof:name":"Stutz Ulrich",
    "wof:placetype":"venue"
},
  "geometry": {"coordinates":[8.4838476181,47.201751709],"type":"Point"}
}