{
  "type": "Feature",
  "properties": {
    "iso:country":"CH",
    "sg:address":"Bundesplatz 3011 Bern. Postfach",
    "sg:city":"Bern",
    "sg:orig_category":"Nationale Postdienste",
    "sg:phone":"+41 31 352 51 82",
    "sg:postcode":"3003",
    "sg:province":"Bern",
    "wof:name":"Die Schweizerische Post Bern 32 Schlosshalde",
    "wof:placetype":"venue"
},
  "geometry": {"coordinates":[7.4661159515,46.9471206665],"type":"Point"}
}