{
  "type": "Feature",
  "properties": {
    "iso:country":"CH",
    "sg:address":"Oberh\u00fcnigenstrasse 2",
    "sg:city":"Z\u00e4ziwil",
    "sg:orig_category":"Herstellung von Konstruktionsteilen, Fertigbauteilen U Ausbauelementen aus Holz",
    "sg:phone":"+41 31 711 45 05",
    "sg:postcode":"3532",
    "sg:province":"Bern",
    "wof:name":"Dolder Deckenmontagen",
    "wof:placetype":"venue"
},
  "geometry": {"coordinates":[7.6609492302,46.8964309692],"type":"Point"}
}