{
  "type": "Feature",
  "properties": {
    "iso:country":"CH",
    "sg:address":"Artherstrasse 23a",
    "sg:city":"Zug",
    "sg:orig_category":"Satzherstellung U Reproduktion",
    "sg:postcode":"6300",
    "sg:province":"Zug",
    "wof:name":"Priodata Ag",
    "wof:placetype":"venue"
},
  "geometry": {"coordinates":[8.5135231018,47.1616477966],"type":"Point"}
}