{
  "type": "Feature",
  "properties": {
    "iso:country":"CH",
    "sg:address":"Hauptstrasse 65 8840 Einsiedeln. Postfach 425",
    "sg:city":"Einsiedeln",
    "sg:orig_category":"Fachdetailhandel in Verkaufsr\u00e4umen",
    "sg:phone":"+41 55 412 58 42",
    "sg:postcode":"8840",
    "sg:province":"Schwyz",
    "wof:name":"Optrin Ag",
    "wof:placetype":"venue"
},
  "geometry": {"coordinates":[8.7482824326,47.1272392273],"type":"Point"}
}