{
  "type": "Feature",
  "properties": {
    "iso:country":"CH",
    "sg:address":"Sonnhalde 653",
    "sg:city":"Unterkulm",
    "sg:orig_category":"Sportvereine Velo Rad-& Motorfahrer-Bund SRB",
    "sg:postcode":"5726",
    "sg:province":"Aargau",
    "wof:name":"Veloclub Kulm",
    "wof:placetype":"venue"
},
  "geometry": {"coordinates":[8.0996103287,47.3107910156],"type":"Point"}
}