{
  "type": "Feature",
  "properties": {
    "iso:country":"CH",
    "sg:address":"Progressastrasse 35",
    "sg:city":"Oberburg",
    "sg:orig_category":"Detailhandel mit Waren verschiedener Art, Hauptrichtung Nahrungsmittel",
    "sg:phone":"+41 34 422 22 59",
    "sg:postcode":"3414",
    "sg:province":"Bern",
    "wof:name":"Coop Bern/biel",
    "wof:placetype":"venue"
},
  "geometry": {"coordinates":[7.6304221153,47.03698349],"type":"Point"}
}