{
  "type": "Feature",
  "properties": {
    "iso:country":"CH",
    "sg:address":"Bahnhofstrasse 21",
    "sg:city":"Buchs",
    "sg:classifiers":[
        {
            "category":"Manufacturing",
            "subcategory":"Metals",
            "type":"Manufacturing & Wholesale Goods"
        }
    ],
    "sg:phone":"+41 18473111",
    "sg:postcode":"8107",
    "sg:province":"Z\u00fcrich",
    "sg:tags":[
        "aluminium"
    ],
    "wof:name":"Blockmetall Ag",
    "wof:placetype":"venue"
},
  "geometry": {"coordinates":[8.438094,47.453533],"type":"Point"}
}