{
  "type": "Feature",
  "properties": {
    "addr:full":"St. Gallerstrasse 39 9230 Flawil. Postfach Flawil St. Gallen 9230",
    "addr:housenumber":"39",
    "addr:postcode":"9230 flawil. postfach;9230",
    "addr:street":"St. Gallerstrasse",
    "iso:country":"CH",
    "sg:address":"St. Gallerstrasse 39 9230 Flawil. Postfach",
    "sg:city":"Flawil",
    "sg:orig_category":"Detailhandel mit B\u00fcromaschinen U einrichtungen Detailhandel mit M\u00f6beln",
    "sg:phone":"+41 71 393 30 83",
    "sg:postcode":"9230",
    "sg:province":"St. Gallen",
    "wof:name":"Brenner Inneneinrichtungen",
    "wof:placetype":"venue"
},
  "geometry": {"coordinates":[9.189033,47.411972],"type":"Point"}
}