{
  "type": "Feature",
  "properties": {
    "iso:country":"CH",
    "sg:address":"Rosemont Avenue 12bis 1208 Gen\u00e8ve. Postfach",
    "sg:city":"Gen\u00e8ve",
    "sg:orig_category":"Non-Classified Establishments",
    "sg:postcode":"1208",
    "sg:province":"Gen\u00e8ve",
    "wof:name":"Soci\u00e9t\u00e9 Immobili\u00e8re Rosemont-avenir",
    "wof:placetype":"venue"
},
  "geometry": {"coordinates":[6.1725440025,46.2019386292],"type":"Point"}
}