{
  "type": "Feature",
  "properties": {
    "iso:country":"CH",
    "sg:address":"1267",
    "sg:city":"Vich",
    "sg:orig_category":"Allgemeiner Hoch U Tiefbau Allgemeiner Hochbau",
    "sg:phone":"+41 22 364 18 85",
    "sg:postcode":"1267",
    "sg:province":"Vaud",
    "wof:name":"Perrin Fr\u00e8res Sa",
    "wof:placetype":"venue"
},
  "geometry": {"coordinates":[6.250275,46.428848],"type":"Point"}
}