{
  "type": "Feature",
  "properties": {
    "addr:full":"Via Angelo Maspoli 18 Mendrisio Ticino 6850",
    "addr:housenumber":"18",
    "addr:postcode":"6850",
    "addr:street":"Via Angelo Maspoli",
    "iso:country":"CH",
    "sg:address":"Via Angelo Maspoli 18",
    "sg:city":"Mendrisio",
    "sg:orig_category":"Detailhandel mit Bekleidung",
    "sg:phone":"+41 91 646 08 35",
    "sg:postcode":"6850",
    "sg:province":"Ticino",
    "wof:name":"Agata Sa La Casa Ital.intimo & Lingerie",
    "wof:placetype":"venue"
},
  "geometry": {"coordinates":[8.978729,45.875259],"type":"Point"}
}