{
  "type": "Feature",
  "properties": {
    "iso:country":"CH",
    "sg:address":"Au Bandalet",
    "sg:city":"Poliez-le-grand",
    "sg:orig_category":"Fahrschulen, Flugschulen",
    "sg:phone":"+41 81 302 13 76",
    "sg:postcode":"1041",
    "sg:province":"Vaud",
    "wof:name":"Robert Rosenkranz Autofahrschule",
    "wof:placetype":"venue"
},
  "geometry": {"coordinates":[9.5069789886,47.0078163147],"type":"Point"}
}