{
  "type": "Feature",
  "properties": {
    "iso:country":"CH",
    "sg:address":"Seilergraben 61b",
    "sg:city":"Z\u00fcrich",
    "sg:orig_category":"Detailhandel mit Musikinstrumenten",
    "sg:phone":"+41 12623420",
    "sg:postcode":"8001",
    "sg:province":"Z\u00fcrich",
    "wof:name":"Gamberucci & B\u00e4chli Central Music",
    "wof:placetype":"venue"
},
  "geometry": {"coordinates":[8.5449466705,47.3757896423],"type":"Point"}
}