{
  "type": "Feature",
  "properties": {
    "iso:country":"CH",
    "sg:address":"Rohrerstrasse 87",
    "sg:city":"Aarau",
    "sg:classifiers":[
        {
            "category":"Restaurant",
            "type":"Food & Drink"
        }
    ],
    "sg:phone":"+41 62 824 75 55",
    "sg:postcode":"5000",
    "sg:province":"Aargau",
    "wof:name":"Restaurant Jura",
    "wof:placetype":"venue"
},
  "geometry": {"coordinates":[8.0624866486,47.3954048157],"type":"Point"}
}