{
  "type": "Feature",
  "properties": {
    "addr:full":"Guschastrasse 44 Sevelen St. Gallen 9475",
    "addr:housenumber":"44",
    "addr:postcode":"9475",
    "addr:street":"Guschastrasse",
    "iso:country":"CH",
    "sg:address":"Guschastrasse 44",
    "sg:city":"Sevelen",
    "sg:classifiers":[
        {
            "category":"Manufacturing",
            "subcategory":"Printing",
            "type":"Manufacturing & Wholesale Goods"
        }
    ],
    "sg:phone":"+41 81 785 23 00",
    "sg:postcode":"9475",
    "sg:province":"St. Gallen",
    "sg:tags":[
        "house",
        "book"
    ],
    "wof:name":"Alvier-druck",
    "wof:placetype":"venue"
},
  "geometry": {"coordinates":[9.492342,47.126556],"type":"Point"}
}