{
  "type": "Feature",
  "properties": {
    "iso:country":"CH",
    "sg:address":"K\u00fcssnachterstr. 6",
    "sg:city":"Udligenswil",
    "sg:classifiers":[
        {
            "category":"Home & Garden",
            "subcategory":"Furniture",
            "type":"Retail Goods"
        }
    ],
    "sg:phone":"+41 41 371 07 82",
    "sg:postcode":"6044",
    "sg:province":"Luzern",
    "sg:tags":[
        "household",
        "wood"
    ],
    "wof:name":"Moser Und Partner Ag",
    "wof:placetype":"venue"
},
  "geometry": {"coordinates":[8.4016008377,47.0896110535],"type":"Point"}
}