{
  "type": "Feature",
  "properties": {
    "iso:country":"CH",
    "sg:address":"Romanshorner Strasse 90",
    "sg:city":"Arbon",
    "sg:orig_category":"Bauschreinerei Herstellung von Konstruktionsteilen, Fertigbauteilen U Ausbauelementen aus Holz",
    "sg:phone":"+41 71 447 20 70",
    "sg:postcode":"9320",
    "sg:province":"Thurgau",
    "wof:name":"Schreinerei Moser Magnus Ag",
    "wof:placetype":"venue"
},
  "geometry": {"coordinates":[9.419981,47.519867],"type":"Point"}
}