{
  "type": "Feature",
  "properties": {
    "iso:country":"CH",
    "sg:address":"General-wille-strasse 284 8706 Meilen. Postfach",
    "sg:city":"Meilen",
    "sg:orig_category":"Softwareentwicklung U beratung",
    "sg:postcode":"8706",
    "sg:province":"Z\u00fcrich",
    "wof:name":"Meier-it Gmbh",
    "wof:placetype":"venue"
},
  "geometry": {"coordinates":[8.6251783371,47.273979187],"type":"Point"}
}