{
  "type": "Feature",
  "properties": {
    "iso:country":"CH",
    "sg:address":"B\u00fchlstrasse 12a",
    "sg:city":"Emmenbr\u00fccke",
    "sg:orig_category":"Herstellung von industriellen Prozesssteuerungsanlagen Softwareentwicklung U beratung",
    "sg:phone":"+41 41 260 60 16",
    "sg:postcode":"6020",
    "sg:province":"Luzern",
    "wof:name":"At Engineering Gmbh",
    "wof:placetype":"venue"
},
  "geometry": {"coordinates":[8.2788295746,47.0769805908],"type":"Point"}
}