{
  "type": "Feature",
  "properties": {
    "iso:country":"CH",
    "sg:address":"Riet",
    "sg:city":"Azmoos",
    "sg:orig_category":"Grosshandel mit Obst U Gem\u00fcse",
    "sg:postcode":"9478",
    "sg:province":"St. Gallen",
    "wof:name":"Vertragsproduzentengemeinschaft Vpg Ag",
    "wof:placetype":"venue"
},
  "geometry": {"coordinates":[9.4812002182,47.08360672],"type":"Point"}
}