{
  "type": "Feature",
  "properties": {
    "iso:country":"CH",
    "sg:address":"Fabrikstrasse 2",
    "sg:city":"Hinwil",
    "sg:orig_category":"Autolackierereien Lackiererei",
    "sg:phone":"+41 19371252",
    "sg:postcode":"8340",
    "sg:province":"Z\u00fcrich",
    "wof:name":"Spritz-atelier Erik Buser",
    "wof:placetype":"venue"
},
  "geometry": {"coordinates":[8.838872,47.299698],"type":"Point"}
}