{
  "type": "Feature",
  "properties": {
    "iso:country":"CH",
    "sg:address":"Krummackerweg 188",
    "sg:city":"Himmelried",
    "sg:orig_category":"Herstellung von k\u00e4lte U lufttechnischen Erzeugnissen f\u00fcr gewerbliche Zwecke",
    "sg:phone":"+41 61 741 19 95",
    "sg:postcode":"4204",
    "sg:province":"Solothurn",
    "wof:name":"Kurz A. Heizungstechnik",
    "wof:placetype":"venue"
},
  "geometry": {"coordinates":[7.6046991348,47.4215316772],"type":"Point"}
}