{
  "type": "Feature",
  "properties": {
    "iso:country":"CH",
    "sg:address":"3658",
    "sg:city":"Merligen",
    "sg:orig_category":"Sportvereine Sch\u00fctzen",
    "sg:phone":"+41 31 791 38 28",
    "sg:postcode":"3658",
    "sg:province":"Bern",
    "wof:name":"Feldsch\u00fctzengesellschaft",
    "wof:placetype":"venue"
},
  "geometry": {"coordinates":[7.7376198769,46.69713974],"type":"Point"}
}