{
  "type": "Feature",
  "properties": {
    "iso:country":"CH",
    "sg:address":"Schlossm\u00fchlestrasse 9",
    "sg:city":"Frauenfeld",
    "sg:orig_category":"Detailhandel mit Gebrauchtwaren in Verkaufsr\u00e4umen",
    "sg:phone":"+41 52 721 79 50",
    "sg:postcode":"8500",
    "sg:province":"Thurgau",
    "wof:name":"Brockenstube Der Heilsarmee Frauenfeld",
    "wof:placetype":"venue"
},
  "geometry": {"coordinates":[8.8976373672,47.5542297363],"type":"Point"}
}