{
  "type": "Feature",
  "properties": {
    "iso:country":"CH",
    "sg:address":"Rue De La Gare 5",
    "sg:city":"Bussigny-lausanne",
    "sg:orig_category":"RESTAURANTS: TEA-ROOMS",
    "sg:phone":"+41 21 701 21 08",
    "sg:postcode":"1030",
    "sg:province":"Vaud",
    "wof:name":"Phan Lai Say",
    "wof:placetype":"venue"
},
  "geometry": {"coordinates":[6.5526170731,46.5482063293],"type":"Point"}
}