{
  "type": "Feature",
  "properties": {
    "iso:country":"CH",
    "sg:address":"Oberriedstrasse 14",
    "sg:city":"Zweisimmen",
    "sg:orig_category":"G\u00fcterbef\u00f6rderung im Strassenverkehr",
    "sg:phone":"+41 33 722 25 22",
    "sg:postcode":"3770",
    "sg:province":"Bern",
    "wof:name":"Armin Eschler Autotransporte",
    "wof:placetype":"venue"
},
  "geometry": {"coordinates":[7.3870601654,46.5567626953],"type":"Point"}
}