{
  "type": "Feature",
  "properties": {
    "addr:full":"Buzibachstrasse 44 Rothenburg Luzern 6023",
    "addr:housenumber":"44",
    "addr:postcode":"6023",
    "addr:street":"Buzibachstrasse",
    "iso:country":"CH",
    "sg:address":"Buzibachstrasse 44",
    "sg:city":"Rothenburg",
    "sg:orig_category":"Architektur U Ingenieurb\u00fcros Hoch U Tiefbau",
    "sg:phone":"+41 41 280 17 21",
    "sg:postcode":"6023",
    "sg:province":"Luzern",
    "wof:name":"Waser Bau Ag",
    "wof:placetype":"venue"
},
  "geometry": {"coordinates":[8.253913,47.090252],"type":"Point"}
}