{
  "type": "Feature",
  "properties": {
    "addr:full":"Rheinquai 16 Schaffhausen Schaffhausen 8200",
    "addr:housenumber":"16",
    "addr:postcode":"8200",
    "addr:street":"Rheinquai",
    "iso:country":"CH",
    "sg:address":"Rheinquai 16",
    "sg:city":"Schaffhausen",
    "sg:orig_category":"Binnenschiffahrt",
    "sg:phone":"+41 52 624 07 07",
    "sg:postcode":"8200",
    "sg:province":"Schaffhausen",
    "wof:name":"Stoll Schifffahrten Ag",
    "wof:placetype":"venue"
},
  "geometry": {"coordinates":[8.643488,47.695328],"type":"Point"}
}