{
  "type": "Feature",
  "properties": {
    "iso:country":"CH",
    "sg:address":"Feldstrasse 18 8180 B\u00fclach. Postfach 16",
    "sg:city":"B\u00fclach",
    "sg:orig_category":"Herstellung von sonstigen elektrischen Ausr\u00fcstungen",
    "sg:phone":"+41 18605220",
    "sg:postcode":"8180",
    "sg:province":"Z\u00fcrich",
    "wof:name":"Tyco Integrated Systems Ag",
    "wof:placetype":"venue"
},
  "geometry": {"coordinates":[8.5342006683,47.513168335],"type":"Point"}
}