{
  "type": "Feature",
  "properties": {
    "iso:country":"CH",
    "sg:address":"Pl. Du Tilleul 11",
    "sg:city":"Bulle",
    "sg:classifiers":[
        {
            "category":"Banks & Credit Unions",
            "subcategory":"Bank",
            "type":"Services"
        }
    ],
    "sg:phone":"+41 26 919 24 00",
    "sg:postcode":"1630",
    "sg:province":"Fribourg",
    "wof:name":"Cantonale De Fribourg",
    "wof:placetype":"venue"
},
  "geometry": {"coordinates":[7.057403,46.617901],"type":"Point"}
}