{
  "type": "Feature",
  "properties": {
    "iso:country":"CH",
    "sg:address":"Tenuta Loro",
    "sg:city":"Arzo",
    "sg:orig_category":"Kauf U Verkauf von Immobilien auf eigene Rechnung",
    "sg:postcode":"6864",
    "sg:province":"Ticino",
    "wof:name":"Euro-immo Gmbh",
    "wof:placetype":"venue"
},
  "geometry": {"coordinates":[8.7341480255,47.1973953247],"type":"Point"}
}