{
  "type": "Feature",
  "properties": {
    "iso:country":"CH",
    "sg:address":"Industriestr. 4",
    "sg:city":"Etziken",
    "sg:classifiers":[
        {
            "category":"Manufacturing",
            "subcategory":"Metals",
            "type":"Manufacturing & Wholesale Goods"
        }
    ],
    "sg:phone":"+41 32 613 31 31",
    "sg:postcode":"4554",
    "sg:province":"Solothurn",
    "sg:tags":[
        "-",
        "machine",
        "equipment",
        "engineering",
        "machinery",
        "mechanical"
    ],
    "wof:name":"Ewag Ag",
    "wof:placetype":"venue"
},
  "geometry": {"coordinates":[7.6355810165,47.1900596619],"type":"Point"}
}