{
  "type": "Feature",
  "properties": {
    "iso:country":"CH",
    "sg:address":"Stutz.",
    "sg:city":"Z\u00e4ziwil",
    "sg:orig_category":"Herstellung von Konstruktionsteilen, Fertigbauteilen U Ausbauelementen aus Holz",
    "sg:phone":"+41 33 681 19 60",
    "sg:postcode":"3532",
    "sg:province":"Bern",
    "wof:name":"Schreinerei, Innenausbau, M\u00f6bel, Christian Scheidegger",
    "wof:placetype":"venue"
},
  "geometry": {"coordinates":[7.8617801666,49.1125106812],"type":"Point"}
}