{
  "type": "Feature",
  "properties": {
    "iso:country":"CH",
    "sg:address":"7242",
    "sg:city":"Luzein",
    "sg:classifiers":[
        {
            "category":"Restaurant",
            "type":"Food & Drink"
        }
    ],
    "sg:phone":"+41 81 332 15 83",
    "sg:postcode":"7242",
    "sg:province":"Graubunden",
    "wof:name":"Restaurant Rathaus",
    "wof:placetype":"venue"
},
  "geometry": {"coordinates":[9.7630796432,46.9208908081],"type":"Point"}
}