{
  "type": "Feature",
  "properties": {
    "iso:country":"CH",
    "sg:address":"Chappelistrasse 3",
    "sg:city":"Volketswil",
    "sg:orig_category":"Softwareentwicklung U beratung",
    "sg:phone":"+41 19971771",
    "sg:postcode":"8604",
    "sg:province":"Z\u00fcrich",
    "wof:name":"Pcx Progression Codex Multimedia & Kommunikation",
    "wof:placetype":"venue"
},
  "geometry": {"coordinates":[8.673661232,47.3892173767],"type":"Point"}
}