{
  "type": "Feature",
  "properties": {
    "iso:country":"CH",
    "sg:address":"P\u00fcntenstrasse 2 8184 Bachenb\u00fclach. Postfach",
    "sg:city":"Bachenb\u00fclach",
    "sg:orig_category":"Fussboden, Fliesen U Plattenlegerei, Tapeziererei Parkettleger",
    "sg:phone":"+41 18621549",
    "sg:postcode":"8184",
    "sg:province":"Z\u00fcrich",
    "wof:name":"Kleinert Parkett Gmbh Arbeiten Im Bereich Holzb\u00f6den U. Parkett, Bes. Verlegen, Bearbeiten U. Pflege",
    "wof:placetype":"venue"
},
  "geometry": {"coordinates":[8.5483961105,47.5050125122],"type":"Point"}
}