{
  "type": "Feature",
  "properties": {
    "addr:full":"Flughafen 8302 Kloten. Postfach Z\u00fcrich Z\u00fcrich 8058",
    "addr:postcode":"8302;postfach;8058",
    "addr:street":"Kloten.",
    "iso:country":"CH",
    "sg:address":"Flughafen 8302 Kloten. Postfach",
    "sg:city":"Z\u00fcrich",
    "sg:orig_category":"Autotransporte international",
    "sg:phone":"+41 71 744 22 22",
    "sg:postcode":"8058",
    "sg:province":"Z\u00fcrich",
    "wof:name":"Gondrand Ag Internationale Transporte",
    "wof:placetype":"venue"
},
  "geometry": {"coordinates":[9.63487,47.451469],"type":"Point"}
}