{
  "type": "Feature",
  "properties": {
    "iso:country":"CH",
    "sg:address":"Huebwiesenstrasse 64",
    "sg:city":"Geroldswil",
    "sg:classifiers":[
        {
            "category":"Insurance",
            "subcategory":"Insurance Agent",
            "type":"Services"
        }
    ],
    "sg:phone":"+41 79 663 84 30",
    "sg:postcode":"8954",
    "sg:province":"Z\u00fcrich",
    "sg:tags":[
        "versicherungsagenturen",
        "-broker"
    ],
    "wof:name":"Helvetia Patria Versicherungen Agentur",
    "wof:placetype":"venue"
},
  "geometry": {"coordinates":[8.405040741,47.4232635498],"type":"Point"}
}