{
  "type": "Feature",
  "properties": {
    "iso:country":"CH",
    "sg:address":"Wettsteinallee 70 4051 Basel. Postfach",
    "sg:city":"Basel",
    "sg:orig_category":"Interessenvertretungen",
    "sg:postcode":"4051",
    "sg:province":"Basel-Stadt",
    "wof:name":"Stiftung Deutsche Christentumsgesellschaft",
    "wof:placetype":"venue"
},
  "geometry": {"coordinates":[7.5956082344,47.5560035706],"type":"Point"}
}