{
  "type": "Feature",
  "properties": {
    "iso:country":"CH",
    "sg:address":"Marktstrasse 34 9244 Niederuzwil. Postfach 142",
    "sg:city":"Niederuzwil",
    "sg:orig_category":"Grosshandel mit Kaffee, Tee, Kakao U Gew\u00fcrzen Grosshandel mit Nahrungsmitteln, Getr\u00e4nken U Tabakware",
    "sg:phone":"+41 79 365 80 44",
    "sg:postcode":"9244",
    "sg:province":"St. Gallen",
    "wof:name":"M\u00fchlehof Gew\u00fcrze Ag",
    "wof:placetype":"venue"
},
  "geometry": {"coordinates":[9.14366436,47.4494781494],"type":"Point"}
}