{
  "type": "Feature",
  "properties": {
    "iso:country":"CH",
    "sg:address":"Bachtelstrasse 32",
    "sg:city":"Hinwil",
    "sg:orig_category":"Cable Drum Winders",
    "sg:phone":"+41 19374827",
    "sg:postcode":"8340",
    "sg:province":"Z\u00fcrich",
    "wof:name":"Industrie-technik Fritz Burkhard",
    "wof:placetype":"venue"
},
  "geometry": {"coordinates":[8.848082,47.300369],"type":"Point"}
}