{
  "type": "Feature",
  "properties": {
    "iso:country":"CH",
    "sg:address":"Keltenweg 3",
    "sg:city":"Pfeffingen",
    "sg:orig_category":"Handels-H\u00e4user U Gesellschaften",
    "sg:postcode":"4148",
    "sg:province":"Basel-Landschaft",
    "wof:name":"H&d Gmbh",
    "wof:placetype":"venue"
},
  "geometry": {"coordinates":[7.5932388306,47.4595680237],"type":"Point"}
}