{
  "type": "Feature",
  "properties": {
    "addr:full":"Rue Robert C\u00e9ard 12 Gen\u00e8ve Gen\u00e8ve 1211",
    "addr:housenumber":"12",
    "addr:postcode":"1211",
    "addr:street":"Rue Robert Ce\u0301Ard",
    "iso:country":"CH",
    "sg:address":"Rue Robert C\u00e9ard 12",
    "sg:city":"Gen\u00e8ve",
    "sg:classifiers":[
        {
            "category":"Banks & Credit Unions",
            "subcategory":"Bank",
            "type":"Services"
        }
    ],
    "sg:phone":"+41 22 818 55 55",
    "sg:postcode":"1211",
    "sg:province":"Gen\u00e8ve",
    "wof:name":"Banque Hyposwiss Hypoth\u00e9caire, Schweiz.hypotheken-u.handelsbank",
    "wof:placetype":"venue"
},
  "geometry": {"coordinates":[6.14866,46.202751],"type":"Point"}
}