{
  "type": "Feature",
  "properties": {
    "iso:country":"CH",
    "sg:address":"D\u00f6rflistrasse 40 8000 Z\u00fcrich. Postfach 8050 Z\u00fcrich",
    "sg:city":"Zust",
    "sg:orig_category":"Wirtschaftspr\u00fcfung, Steuerberatung U Treuhand",
    "sg:postcode":"50",
    "wof:name":"Gemeinschaftspraxis D\u00f6rflistrasse 40 Gmbh",
    "wof:placetype":"venue"
},
  "geometry": {"coordinates":[8.5502080917,47.4057044983],"type":"Point"}
}