{
  "type": "Feature",
  "properties": {
    "iso:country":"CH",
    "sg:address":"Av. Louis-casa\u00ef 76 1217 Meyrin. Postfach",
    "sg:city":"Cointrin",
    "sg:orig_category":"Handel mit Automobilen",
    "sg:phone":"+41 71 278 33 33",
    "sg:postcode":"1216",
    "sg:province":"Gen\u00e8ve",
    "wof:name":"Fayad Automobile",
    "wof:placetype":"venue"
},
  "geometry": {"coordinates":[9.3387699127,47.41381073],"type":"Point"}
}