{
  "type": "Feature",
  "properties": {
    "iso:country":"CH",
    "sg:address":"Waldeggstrasse 4",
    "sg:city":"Horgen",
    "sg:orig_category":"Allgemeiner Hoch U Tiefbau Allgemeiner Hoch U Tiefbau ohne ausgepr\u00e4gten Schwerpunkt",
    "sg:phone":"+41 16876600",
    "sg:postcode":"8810",
    "sg:province":"Z\u00fcrich",
    "wof:name":"Sihlsee Inter Ag",
    "wof:placetype":"venue"
},
  "geometry": {"coordinates":[8.734148,47.197395],"type":"Point"}
}