{
  "type": "Feature",
  "properties": {
    "iso:country":"CH",
    "sg:address":"Rue De Fin-de-praz 22",
    "sg:city":"St-aubin-sauges",
    "sg:orig_category":"Kunsthandel Museen",
    "sg:phone":"+41 32 835 30 03",
    "sg:postcode":"2024",
    "sg:province":"Neuch\u00e2tel",
    "wof:name":"Galerie Du Bac Beroche Art Center Jeanneret-gris, Devos Et Cie Galerie D'art Etc",
    "wof:placetype":"venue"
},
  "geometry": {"coordinates":[6.7794499397,46.8963546753],"type":"Point"}
}