{
  "type": "Feature",
  "properties": {
    "iso:country":"CH",
    "sg:address":"Via Soldino 28",
    "sg:city":"Lugano",
    "sg:orig_category":"Architektur U Ingenieurb\u00fcros Unternehmensberatung",
    "sg:phone":"+41 56 622 79 30",
    "sg:postcode":"6900",
    "sg:province":"Ticino",
    "wof:name":"Tecova Ag",
    "wof:placetype":"venue"
},
  "geometry": {"coordinates":[8.27393,47.357735],"type":"Point"}
}