{
  "type": "Feature",
  "properties": {
    "iso:country":"CH",
    "sg:address":"Via San Gottardo 30",
    "sg:city":"Biasca",
    "sg:orig_category":"Primarschulen",
    "sg:phone":"+41 91 862 17 37",
    "sg:postcode":"6710",
    "sg:province":"Ticino",
    "wof:name":"Scuola Elementare Bosciorina",
    "wof:placetype":"venue"
},
  "geometry": {"coordinates":[8.9652957916,46.3599662781],"type":"Point"}
}