{
  "type": "Feature",
  "properties": {
    "iso:country":"CH",
    "sg:address":"Rue Marc Morand 7",
    "sg:city":"Martigny",
    "sg:orig_category":"Reinigungsgewerbe",
    "sg:phone":"+41 62 212 82 84",
    "sg:postcode":"1920",
    "sg:province":"Valais",
    "wof:name":"Cs Geb\u00e4udemanagement Gmbh Reinigung, Hauswartung, Liegenschaftsverwaltung",
    "wof:placetype":"venue"
},
  "geometry": {"coordinates":[7.8740367889,47.344745636],"type":"Point"}
}