{
  "type": "Feature",
  "properties": {
    "iso:country":"CH",
    "sg:address":"Chemin Des Cr\u00eates 15",
    "sg:city":"Clarens",
    "sg:orig_category":"Sonstige pers\u00f6nliche Dienstleistungen",
    "sg:phone":"+41 21 964 63 63",
    "sg:postcode":"1815",
    "sg:province":"Vaud",
    "wof:name":"Le Bonheur Est Au Rendez-vous S\u00e0rl",
    "wof:placetype":"venue"
},
  "geometry": {"coordinates":[6.8908047676,46.4409446716],"type":"Point"}
}