{
  "type": "Feature",
  "properties": {
    "addr:full":"Rinaustrasse Gen\u00e8ve Aargau 4303",
    "addr:postcode":"4303",
    "addr:street":"Rinaustrasse",
    "iso:country":"CH",
    "sg:address":"Rinaustrasse",
    "sg:city":"Gen\u00e8ve",
    "sg:classifiers":[
        {
            "category":"Manufacturing",
            "subcategory":"Chemicals & Compounds",
            "type":"Manufacturing & Wholesale Goods"
        }
    ],
    "sg:phone":"+41 22 348 65 00",
    "sg:postcode":"4303",
    "sg:province":"Aargau",
    "sg:tags":[
        "pharmaceutical",
        "energy",
        "chemistry",
        "-",
        "by-product"
    ],
    "wof:name":"Bp Suisse",
    "wof:placetype":"venue"
},
  "geometry": {"coordinates":[7.725714,47.538872],"type":"Point"}
}