{
  "type": "Feature",
  "properties": {
    "iso:country":"CH",
    "sg:address":"Morgartenring 168",
    "sg:city":"Basel",
    "sg:orig_category":"Non-Classified Establishments",
    "sg:postcode":"4054",
    "sg:province":"Basel-Stadt",
    "wof:name":"Marga Su Haller Typohaller",
    "wof:placetype":"venue"
},
  "geometry": {"coordinates":[7.5656208992,47.5505447388],"type":"Point"}
}