{
  "type": "Feature",
  "properties": {
    "iso:country":"CH",
    "sg:address":"Rue Du Vingt-trois Juin 24",
    "sg:city":"Courrendlin",
    "sg:orig_category":"Detailhandel mit Milcherzeugnissen U Eiern",
    "sg:phone":"+41 32 435 51 51",
    "sg:postcode":"2830",
    "sg:province":"Jura",
    "wof:name":"Alphonse Lang Laiterie",
    "wof:placetype":"venue"
},
  "geometry": {"coordinates":[7.3740539551,47.3381118774],"type":"Point"}
}