{
  "type": "Feature",
  "properties": {
    "iso:country":"CH",
    "sg:address":"Steinerstrasse 12",
    "sg:city":"Schwyz",
    "sg:orig_category":"Instandhaltung U Reparatur von Automobilen Tankstellen",
    "sg:phone":"+41 41 811 51 37",
    "sg:postcode":"6430",
    "sg:province":"Schwyz",
    "wof:name":"Garage Marty",
    "wof:placetype":"venue"
},
  "geometry": {"coordinates":[8.6450691223,47.0252952576],"type":"Point"}
}