{
  "type": "Feature",
  "properties": {
    "iso:country":"CH",
    "sg:address":"Schwarzerde",
    "sg:city":"Plaffeien",
    "sg:orig_category":"Fachdetailhandel in Verkaufsr\u00e4umen",
    "sg:postcode":"1716",
    "sg:province":"Fribourg",
    "wof:name":"Sonny-sport Ag",
    "wof:placetype":"venue"
},
  "geometry": {"coordinates":[7.2822418213,46.7396507263],"type":"Point"}
}