{
  "type": "Feature",
  "properties": {
    "iso:country":"CH",
    "sg:address":"Cart Avenue Jean-jacques 12 1110 Morges. Postfach",
    "sg:city":"Morges",
    "sg:orig_category":"Herstellung von elektronischen Bauelementen",
    "sg:postcode":"1110",
    "sg:province":"Vaud",
    "wof:name":"Pielectronic, B\u00fcrer Mat\u00e9riel \u00e9lectronique; Commerce",
    "wof:placetype":"venue"
},
  "geometry": {"coordinates":[6.4928421974,46.5134773254],"type":"Point"}
}