{
  "type": "Feature",
  "properties": {
    "iso:country":"CH",
    "sg:address":"P\u00e9pinet Place 3 1003 Lausanne. Postfach",
    "sg:city":"Lausanne",
    "sg:orig_category":"Eisenbahnverkehr",
    "sg:postcode":"1003",
    "sg:province":"Vaud",
    "wof:name":"Sa De Wagons Sp\u00e9ciaux. Acquis., Vente, Placem. Et Gestion De Wagons Sp\u00e9ciaux, De Mat\u00e9riel Ferroviaire, De Transport Destin\u00e9 Au Trafic Internat. Etc.",
    "wof:placetype":"venue"
},
  "geometry": {"coordinates":[6.6326899529,46.5210533142],"type":"Point"}
}