{
  "type": "Feature",
  "properties": {
    "iso:country":"CH",
    "sg:address":"Gotthardstrasse 61 6410 Goldau. Postfach",
    "sg:city":"Goldau",
    "sg:orig_category":"Rechtsberatung",
    "sg:phone":"+41 21 802 38 79",
    "sg:postcode":"6410",
    "sg:province":"Schwyz",
    "wof:name":"Opferhilfe Beratungsstelle Marciante Evelyne",
    "wof:placetype":"venue"
},
  "geometry": {"coordinates":[8.5486001968,47.0436210632],"type":"Point"}
}