{
  "type": "Feature",
  "properties": {
    "iso:country":"CH",
    "sg:address":"Haut Du Village 53",
    "sg:city":"Courtema\u00eeche",
    "sg:orig_category":"Herstellung von Musikinstrumenten",
    "sg:phone":"+41 32 466 79 34",
    "sg:postcode":"2923",
    "sg:province":"Jura",
    "wof:name":"Alfred P\u00f6schl Facteur D'orgues",
    "wof:placetype":"venue"
},
  "geometry": {"coordinates":[7.0484418869,47.4559059143],"type":"Point"}
}