{
  "type": "Feature",
  "properties": {
    "iso:country":"CH",
    "sg:address":"Grabenstrasse 1 8952 Schlieren. Postfach",
    "sg:city":"Widen",
    "sg:orig_category":"Finanzierungsinstitutionen Zimmerei, Dachdeckerei, Bauspenglerei U Abdichtung",
    "sg:phone":"+41 19147050",
    "sg:postcode":"8967",
    "sg:province":"Aargau",
    "wof:name":"Beerli Und Partner Ag Bedachungs, Spengler, Holzbau- U. Fassadenarbeiten; Beratung, Projektierung, Ausf\u00fchrung Usw.",
    "wof:placetype":"venue"
},
  "geometry": {"coordinates":[8.5787334442,47.3212051392],"type":"Point"}
}