{
  "type": "Feature",
  "properties": {
    "iso:country":"CH",
    "sg:address":"Viale C. Olgiati 20.3",
    "sg:city":"Giubiasco",
    "sg:orig_category":"Fachdetailhandel mit pharmazeutischen Produkten",
    "sg:phone":"+41 91 966 01 28",
    "sg:postcode":"6512",
    "sg:province":"Ticino",
    "wof:name":"Farmacia San Gottardo Sa",
    "wof:placetype":"venue"
},
  "geometry": {"coordinates":[8.945233345,46.0128707886],"type":"Point"}
}