{
  "type": "Feature",
  "properties": {
    "iso:country":"CH",
    "sg:address":"Viale Giuseppe Cattori 5 6900 Paradiso. Postfach",
    "sg:city":"Paradiso",
    "sg:orig_category":"Unternehmensberatung",
    "sg:phone":"+41 91 994 95 62",
    "sg:postcode":"6900",
    "sg:province":"Ticino",
    "wof:name":"Sendal Sa",
    "wof:placetype":"venue"
},
  "geometry": {"coordinates":[8.9448156357,45.9926605225],"type":"Point"}
}