{
  "type": "Feature",
  "properties": {
    "iso:country":"CH",
    "sg:address":"Lorzenweidstrasse 88",
    "sg:city":"Hagendorn",
    "sg:orig_category":"Unternehmensberatung",
    "sg:postcode":"6332",
    "sg:province":"Zug",
    "wof:name":"Andr\u00e9e Marcel, International Business Facilitation & Consultancy",
    "wof:placetype":"venue"
},
  "geometry": {"coordinates":[8.4341201782,47.2021408081],"type":"Point"}
}