{
  "type": "Feature",
  "properties": {
    "iso:country":"CH",
    "sg:address":"Rue Maurice 1 1204 Gen\u00e8ve. Postfach",
    "sg:city":"Gen\u00e8ve",
    "sg:orig_category":"Effekten U Warenterminb\u00f6rsen Finanzierungsinstitutionen",
    "sg:phone":"+41 22 310 19 10",
    "sg:postcode":"1201",
    "sg:province":"Gen\u00e8ve",
    "wof:name":"Gcb Strat\u00e9gies Sa",
    "wof:placetype":"venue"
},
  "geometry": {"coordinates":[6.1496171951,46.1992874146],"type":"Point"}
}