{
  "type": "Feature",
  "properties": {
    "iso:country":"CH",
    "sg:address":"M\u00fchlenenfeld",
    "sg:city":"Wilderswil",
    "sg:orig_category":"Grosshandel mit Textilien",
    "sg:phone":"+41 32 685 06 70",
    "sg:postcode":"3812",
    "sg:province":"Bern",
    "wof:name":"Swisspol Textilhandels Gmbh",
    "wof:placetype":"venue"
},
  "geometry": {"coordinates":[7.8654751778,46.6622390747],"type":"Point"}
}