{
  "type": "Feature",
  "properties": {
    "iso:country":"CH",
    "sg:address":"Industriestrasse",
    "sg:city":"Reichenburg",
    "sg:orig_category":"Non-Classified Establishments",
    "sg:postcode":"8864",
    "sg:province":"Schwyz",
    "wof:name":"Steinhoff Europe Ag",
    "wof:placetype":"venue"
},
  "geometry": {"coordinates":[8.7316665649,47.1995658875],"type":"Point"}
}