{
  "type": "Feature",
  "properties": {
    "iso:country":"CH",
    "sg:address":"Via San Gottardo 56",
    "sg:city":"Lugano",
    "sg:orig_category":"Non-Classified Establishments",
    "sg:phone":"+41 91 923 23 32",
    "sg:postcode":"6900",
    "sg:province":"Ticino",
    "wof:name":"Computer Associates Sa",
    "wof:placetype":"venue"
},
  "geometry": {"coordinates":[8.9469089508,46.0086174011],"type":"Point"}
}