{
  "type": "Feature",
  "properties": {
    "iso:country":"CH",
    "sg:address":"Spitalhalde 9",
    "sg:city":"Rheinfelden",
    "sg:orig_category":"Fahrschulen, Flugschulen",
    "sg:phone":"+41 79 320 54 54",
    "sg:postcode":"4310",
    "sg:province":"Aargau",
    "wof:name":"Kurt Kym Autofahrschule",
    "wof:placetype":"venue"
},
  "geometry": {"coordinates":[7.8037967682,47.5556716919],"type":"Point"}
}