{
  "type": "Feature",
  "properties": {
    "iso:country":"CH",
    "sg:address":"Zielackerstrasse 25",
    "sg:city":"Wallisellen",
    "sg:classifiers":[
        {
            "category":"Communications",
            "subcategory":"Radio Station",
            "type":"Services"
        }
    ],
    "sg:postcode":"8304",
    "sg:province":"Z\u00fcrich",
    "sg:tags":[
        "fernsehanstalten",
        "u"
    ],
    "wof:name":"Mediawork-x Gmbh",
    "wof:placetype":"venue"
},
  "geometry": {"coordinates":[8.6075696945,47.4151115417],"type":"Point"}
}