{
  "type": "Feature",
  "properties": {
    "iso:country":"CH",
    "sg:address":"Bahnhofstrasse 80 3920 Zermatt. Postfach 220",
    "sg:city":"Zermatt",
    "sg:classifiers":[
        {
            "category":"Travel",
            "subcategory":"Hotels & Motels",
            "type":"Entertainment"
        }
    ],
    "sg:phone":"+41 27 957 35 25",
    "sg:postcode":"3920",
    "sg:province":"Valais",
    "sg:tags":[
        "hotels",
        "mit",
        "restaurant"
    ],
    "wof:name":"Hotel Monte-rosa, Pius Burgener",
    "wof:placetype":"venue"
},
  "geometry": {"coordinates":[7.9367241859,46.1232452393],"type":"Point"}
}