{
  "type": "Feature",
  "properties": {
    "addr:full":"Kirchweg Gunzgen Solothurn 4617",
    "addr:postcode":"4617",
    "addr:street":"Kirchweg",
    "iso:country":"CH",
    "sg:address":"Kirchweg",
    "sg:city":"Gunzgen",
    "sg:orig_category":"Allgemeiner Hoch U Tiefbau",
    "sg:postcode":"4617",
    "sg:province":"Solothurn",
    "wof:name":"G.i.b. \u00ac Gesellschaft F\u00fcr Individuelles Bauen",
    "wof:placetype":"venue"
},
  "geometry": {"coordinates":[7.82958,47.315498],"type":"Point"}
}