{
  "type": "Feature",
  "properties": {
    "iso:country":"CH",
    "sg:address":"Hessstr. 27 A 3098 K\u00f6niz. Postfach",
    "sg:city":"Liebefeld",
    "sg:orig_category":"Vermietung U Verpachtung von eigenen Immobilien",
    "sg:postcode":"3097",
    "sg:province":"Bern",
    "wof:name":"Inaebnit Immobilien Treuhand Bern",
    "wof:placetype":"venue"
},
  "geometry": {"coordinates":[7.4255328178,46.9313735962],"type":"Point"}
}