{
  "type": "Feature",
  "properties": {
    "iso:country":"CH",
    "sg:address":"Steinhaldenring 4",
    "sg:city":"Geroldswil",
    "sg:orig_category":"Handel mit Motorr\u00e4dern, Teilen U Zubeh\u00f6r Instandhaltung U Reparatur von Motorr\u00e4dern",
    "sg:phone":"+41 17481421",
    "sg:postcode":"8954",
    "sg:province":"Z\u00fcrich",
    "wof:name":"St\u00f6ckli",
    "wof:placetype":"venue"
},
  "geometry": {"coordinates":[8.4137325287,47.4192733765],"type":"Point"}
}