{
  "type": "Feature",
  "properties": {
    "iso:country":"CH",
    "sg:address":"Hardegg 9473 Gams. Postfach",
    "sg:city":"Gams",
    "sg:orig_category":"Autoreiseunternehmen Sonstige Personenbef\u00f6rderung im Landverkehr",
    "sg:phone":"+41 81 771 37 70",
    "sg:postcode":"9473",
    "sg:province":"St. Gallen",
    "wof:name":"Hardegger Personaltransporte Gmbh Car- Bus Und Gesellschaftsreisen",
    "wof:placetype":"venue"
},
  "geometry": {"coordinates":[9.442275,47.204071],"type":"Point"}
}