{
  "type": "Feature",
  "properties": {
    "iso:country":"CH",
    "sg:address":"9514 Wuppenau. Postfach",
    "sg:city":"Wuppenau",
    "sg:classifiers":[
        {
            "category":"Travel",
            "subcategory":"Hotels & Motels",
            "type":"Entertainment"
        }
    ],
    "sg:postcode":"9514",
    "sg:province":"Thurgau",
    "sg:tags":[
        "hotels",
        "mit",
        "restaurant"
    ],
    "wof:name":"Georg Rupf",
    "wof:placetype":"venue"
},
  "geometry": {"coordinates":[9.1058082581,47.4948806763],"type":"Point"}
}