{
  "type": "Feature",
  "properties": {
    "iso:country":"CH",
    "sg:address":"Robach 25",
    "sg:city":"Rehetobel",
    "sg:classifiers":[
        {
            "category":"Restaurant",
            "type":"Food & Drink"
        }
    ],
    "sg:phone":"+41 71 877 14 65",
    "sg:postcode":"9038",
    "sg:province":"Appenzell Ausserrhoden",
    "wof:name":"Restaurant B\u00e4ren",
    "wof:placetype":"venue"
},
  "geometry": {"coordinates":[9.4670372009,47.4317588806],"type":"Point"}
}