{
  "type": "Feature",
  "properties": {
    "iso:country":"CH",
    "sg:address":"Spitalstrasse 12",
    "sg:city":"Biel/bienne",
    "sg:orig_category":"Kosmetikinstitute",
    "sg:phone":"+41 32 322 29 29",
    "sg:postcode":"2502",
    "sg:province":"Bern",
    "wof:name":"Beauty Biel",
    "wof:placetype":"venue"
},
  "geometry": {"coordinates":[7.2416081429,47.1370620728],"type":"Point"}
}