{
  "type": "Feature",
  "properties": {
    "iso:country":"CH",
    "sg:address":"Mooshaldestrasse",
    "sg:city":"Hefenhofen",
    "sg:classifiers":[
        {
            "category":"Restaurant",
            "type":"Food & Drink"
        }
    ],
    "sg:phone":"+41 71 412 71 20",
    "sg:postcode":"8580",
    "sg:province":"Thurgau",
    "wof:name":"Gasthaus Sonne",
    "wof:placetype":"venue"
},
  "geometry": {"coordinates":[9.2991819382,47.5622787476],"type":"Point"}
}