{
  "type": "Feature",
  "properties": {
    "iso:country":"CH",
    "sg:address":"Gaswerkstrasse 1",
    "sg:city":"Brugg",
    "sg:classifiers":[
        {
            "category":"Ice Cream",
            "type":"Food & Drink"
        }
    ],
    "sg:phone":"+41 56 441 69 81",
    "sg:postcode":"5200",
    "sg:province":"Aargau",
    "sg:tags":[
        "barrier"
    ],
    "wof:name":"Lysoform Ag",
    "wof:placetype":"venue"
},
  "geometry": {"coordinates":[8.214326,47.484348],"type":"Point"}
}