{
  "type": "Feature",
  "properties": {
    "iso:country":"CH",
    "sg:address":"Fuchshalten",
    "sg:city":"Boltigen",
    "sg:orig_category":"Unclassifiable Establishments",
    "sg:phone":"+41 33 773 63 41",
    "sg:postcode":"3766",
    "sg:province":"Bern",
    "wof:name":"Peter Siegenthaler",
    "wof:placetype":"venue"
},
  "geometry": {"coordinates":[7.4126639366,46.6377792358],"type":"Point"}
}