{
  "type": "Feature",
  "properties": {
    "iso:country":"CH",
    "sg:address":"Alte Steinhauserstrasse 33",
    "sg:city":"Cham",
    "sg:orig_category":"Unternehmensberatung Verwaltung von Immobilien",
    "sg:phone":"+41 41 741 87 87",
    "sg:postcode":"6330",
    "sg:province":"Zug",
    "wof:name":"Oet Management Und Treuhand Ag",
    "wof:placetype":"venue"
},
  "geometry": {"coordinates":[8.4734687805,47.190158844],"type":"Point"}
}