{
  "type": "Feature",
  "properties": {
    "iso:country":"CH",
    "sg:address":"Br\u00fcnigstrasse 157",
    "sg:city":"Sarnen",
    "sg:orig_category":"Bibliotheken U Archive Wohnheime",
    "sg:phone":"+41 41 660 11 61",
    "sg:postcode":"6060",
    "sg:province":"Obwalden",
    "wof:name":"Frauenkloster St.andreas",
    "wof:placetype":"venue"
},
  "geometry": {"coordinates":[8.247772,46.902527],"type":"Point"}
}