{
  "type": "Feature",
  "properties": {
    "addr:full":"Fischerm\u00e4tteli 13 Burgdorf Bern 3400",
    "addr:housenumber":"13",
    "addr:postcode":"3400",
    "addr:street":"Fischermaetteli",
    "iso:country":"CH",
    "sg:address":"Fischerm\u00e4tteli 13",
    "sg:city":"Burgdorf",
    "sg:orig_category":"Herstellung von Automobilen",
    "sg:phone":"+41 34 424 14 44",
    "sg:postcode":"3400",
    "sg:province":"Bern",
    "wof:name":"Beck Burgdorf Ag",
    "wof:placetype":"venue"
},
  "geometry": {"coordinates":[7.6389,47.04834],"type":"Point"}
}