{
  "type": "Feature",
  "properties": {
    "iso:country":"CH",
    "sg:address":"Geissburghalde 23",
    "sg:city":"Willisau",
    "sg:orig_category":"Forst\u00e4mter",
    "sg:phone":"+41 41 970 15 45",
    "sg:postcode":"6130",
    "sg:province":"Luzern",
    "wof:name":"Kreisforstamt Iv",
    "wof:placetype":"venue"
},
  "geometry": {"coordinates":[7.9827189445,47.1173324585],"type":"Point"}
}