{
  "type": "Feature",
  "properties": {
    "iso:country":"CH",
    "sg:address":"Im L\u00f6rler 3",
    "sg:city":"Urdorf",
    "sg:classifiers":[
        {
            "category":"Military Area",
            "subcategory":"Air Force Base",
            "type":"Public Place"
        }
    ],
    "sg:phone":"+41 17773503",
    "sg:postcode":"8902",
    "sg:province":"Z\u00fcrich",
    "sg:tags":[
        "fire",
        "extinguishing",
        "inergen",
        "system"
    ],
    "wof:name":"Technisches Brandschutzb\u00fcro Urdorf",
    "wof:placetype":"venue"
},
  "geometry": {"coordinates":[8.4243364334,47.3917198181],"type":"Point"}
}