{
  "type": "Feature",
  "properties": {
    "iso:country":"CH",
    "sg:address":"Altgasse 82",
    "sg:city":"Baar",
    "sg:classifiers":[
        {
            "category":"Professional",
            "subcategory":"Employment Agencies",
            "type":"Services"
        }
    ],
    "sg:postcode":"6340",
    "sg:province":"Zug",
    "sg:tags":[
        "personal",
        "u",
        "stellenvermittlung"
    ],
    "wof:name":"Executive Search Wolf Ruth",
    "wof:placetype":"venue"
},
  "geometry": {"coordinates":[7.5956759453,47.550403595],"type":"Point"}
}