{
  "type": "Feature",
  "properties": {
    "iso:country":"CH",
    "sg:address":"M\u00e4rtplatz 9",
    "sg:city":"Effretikon",
    "sg:orig_category":"Verwaltung von Immobilien",
    "sg:phone":"+41 22 347 70 40",
    "sg:postcode":"8307",
    "sg:province":"Z\u00fcrich",
    "wof:name":"William Ingoglia G\u00e9rance Immobili\u00e8re",
    "wof:placetype":"venue"
},
  "geometry": {"coordinates":[6.1538448334,46.1948127747],"type":"Point"}
}