{
  "type": "Feature",
  "properties": {
    "iso:country":"CH",
    "sg:address":"Reichsgasse 69 7000 Chur. Postfach",
    "sg:city":"Chur",
    "sg:orig_category":"Fachdetailhandel mit pharmazeutischen Produkten",
    "sg:phone":"+41 81 252 11 36",
    "sg:postcode":"7002",
    "sg:province":"Graubunden",
    "wof:name":"L\u00f6wen-apotheke U.zehnder & N.graff",
    "wof:placetype":"venue"
},
  "geometry": {"coordinates":[9.5328073502,46.8488578796],"type":"Point"}
}