{
  "type": "Feature",
  "properties": {
    "iso:country":"CH",
    "sg:address":"Kirchstrasse 5a",
    "sg:city":"Kreuzlingen",
    "sg:orig_category":"Instandhaltung U Reparatur von Automobilen",
    "sg:phone":"+41 71 672 26 60",
    "sg:postcode":"8280",
    "sg:province":"Thurgau",
    "wof:name":"Hof-garage Gmbh",
    "wof:placetype":"venue"
},
  "geometry": {"coordinates":[9.173122406,47.646987915],"type":"Point"}
}