{
  "type": "Feature",
  "properties": {
    "iso:country":"CH",
    "sg:address":"Hauptstrasse 37",
    "sg:city":"Meggen",
    "sg:classifiers":[
        {
            "category":"Travel",
            "subcategory":"Hotels & Motels",
            "type":"Entertainment"
        }
    ],
    "sg:phone":"+41 41 377 44 00",
    "sg:postcode":"6045",
    "sg:province":"Luzern",
    "sg:tags":[
        "hotels",
        "mit",
        "restaurant"
    ],
    "wof:name":"Hotel Restaurant Sonnegg Schmidli Pius",
    "wof:placetype":"venue"
},
  "geometry": {"coordinates":[8.3768281937,47.047618866],"type":"Point"}
}