{
  "type": "Feature",
  "properties": {
    "iso:country":"CH",
    "sg:address":"Sandb\u00fcelstrasse 6",
    "sg:city":"Volketswil",
    "sg:orig_category":"Vereine Diverse",
    "sg:phone":"+41 19462544",
    "sg:postcode":"8604",
    "sg:province":"Z\u00fcrich",
    "wof:name":"Insider Club",
    "wof:placetype":"venue"
},
  "geometry": {"coordinates":[8.6790971756,47.3829689026],"type":"Point"}
}