{
  "type": "Feature",
  "properties": {
    "iso:country":"CH",
    "sg:address":"Oberfeldstrasse 12b 8302 Kloten. Postfach 216",
    "sg:city":"Kloten",
    "sg:orig_category":"Herstellung von Automobilen",
    "sg:postcode":"8302",
    "sg:province":"Z\u00fcrich",
    "wof:name":"Steffen",
    "wof:placetype":"venue"
},
  "geometry": {"coordinates":[7.8991041183,47.228553772],"type":"Point"}
}