{
  "type": "Feature",
  "properties": {
    "iso:country":"CH",
    "sg:address":"Via Borghese 22",
    "sg:city":"Locarno",
    "sg:orig_category":"Sonstige k\u00fcnstlerische U schriftstellerische T\u00e4tigkeiten U Darbietungen",
    "sg:phone":"+41 91 751 24 73",
    "sg:postcode":"6600",
    "sg:province":"Ticino",
    "wof:name":"Tienda Mapu Silvia Cienfuegos Artigianato Latino-americano",
    "wof:placetype":"venue"
},
  "geometry": {"coordinates":[8.792675972,46.1702461243],"type":"Point"}
}