{
  "type": "Feature",
  "properties": {
    "iso:country":"CH",
    "sg:address":"Kantonsstrasse 2",
    "sg:city":"Bubendorf",
    "sg:orig_category":"Tankstellen",
    "sg:phone":"+41 61 931 19 26",
    "sg:postcode":"4416",
    "sg:province":"Basel-Landschaft",
    "wof:name":"Emil Werder Ag Garage",
    "wof:placetype":"venue"
},
  "geometry": {"coordinates":[7.7404999733,47.4607543945],"type":"Point"}
}