{
  "type": "Feature",
  "properties": {
    "iso:country":"CH",
    "sg:address":"7222",
    "sg:city":"Mittellunden",
    "sg:orig_category":"Tierheime",
    "sg:phone":"+41 81 328 15 33",
    "sg:postcode":"7222",
    "sg:province":"Graubunden",
    "wof:name":"Christian Mathis Hundeheim",
    "wof:placetype":"venue"
},
  "geometry": {"coordinates":[9.7124900818,46.9490203857],"type":"Point"}
}