{
  "type": "Feature",
  "properties": {
    "iso:country":"CH",
    "sg:address":"Steigstrasse 35",
    "sg:city":"Schaffhausen",
    "sg:orig_category":"Sportvereine Ballsport Tennis",
    "sg:phone":"+41 26 924 58 70",
    "sg:postcode":"8200",
    "sg:province":"Schaffhausen",
    "wof:name":"Tennisclub Ch\u00e2teau-d'oex",
    "wof:placetype":"venue"
},
  "geometry": {"coordinates":[7.1039891243,46.4213485718],"type":"Point"}
}