{
  "type": "Feature",
  "properties": {
    "iso:country":"CH",
    "sg:address":"Dorfstrasse 57",
    "sg:city":"Pf\u00e4ffikon",
    "sg:classifiers":[
        {
            "category":"Professional",
            "subcategory":"Engineering",
            "type":"Services"
        }
    ],
    "sg:phone":"+41 19525757",
    "sg:postcode":"8330",
    "sg:province":"Z\u00fcrich",
    "wof:name":"Marenco Ag",
    "wof:placetype":"venue"
},
  "geometry": {"coordinates":[8.7952785492,47.3630638123],"type":"Point"}
}