{
  "type": "Feature",
  "properties": {
    "iso:country":"CH",
    "sg:address":"Via San Salvatore 13 6900 Paradiso. Postfach",
    "sg:city":"Paradiso",
    "sg:orig_category":"Erbringung von Dienstleistungen f\u00fcr Unternehmen",
    "sg:postcode":"6900",
    "sg:province":"Ticino",
    "wof:name":"Documedica Sa Preparazione Di Documentazione Tecnico-scientifica Per Nuovi Prodotti Farmaceutici Ecc",
    "wof:placetype":"venue"
},
  "geometry": {"coordinates":[8.9454631805,45.9909362793],"type":"Point"}
}