{
  "type": "Feature",
  "properties": {
    "iso:country":"CH",
    "sg:address":"Wylerstrasse 109",
    "sg:city":"Bern",
    "sg:orig_category":"Solarien",
    "sg:phone":"+41 31 333 83 80",
    "sg:postcode":"3014",
    "sg:province":"Bern",
    "wof:name":"Club 42 Solarium",
    "wof:placetype":"venue"
},
  "geometry": {"coordinates":[7.447581768,46.9613990784],"type":"Point"}
}