{
  "type": "Feature",
  "properties": {
    "addr:full":"Delsbergerallee 77 Basel Basel-Stadt 4053",
    "addr:housenumber":"77",
    "addr:postcode":"4053",
    "addr:street":"Delsbergerallee",
    "iso:country":"CH",
    "sg:address":"Delsbergerallee 77",
    "sg:city":"Basel",
    "sg:orig_category":"Architektur U Ingenieurb\u00fcros Architekturb\u00fcros",
    "sg:phone":"+41 61 332 04 55",
    "sg:postcode":"4053",
    "sg:province":"Basel-Stadt",
    "wof:name":"Kaufmann Andr\u00e9 Architekt",
    "wof:placetype":"venue"
},
  "geometry": {"coordinates":[7.598935,47.538681],"type":"Point"}
}