{
  "type": "Feature",
  "properties": {
    "iso:country":"CH",
    "sg:address":"Stradun",
    "sg:city":"Scuol",
    "sg:orig_category":"Detailhandel mit Uhren U Schmuck Reparatur von Uhren U Schmuck",
    "sg:phone":"+41 81 864 90 44",
    "sg:postcode":"7550",
    "sg:province":"Graubunden",
    "wof:name":"J\u00f6rg Buchholz Uras & Bischutaria",
    "wof:placetype":"venue"
},
  "geometry": {"coordinates":[10.2936811447,46.7949409485],"type":"Point"}
}