{
  "type": "Feature",
  "properties": {
    "iso:country":"CH",
    "sg:address":"Viale Carlo Cattaneo",
    "sg:city":"Lugano",
    "sg:orig_category":"Vermietung U Verpachtung von eigenen Immobilien",
    "sg:postcode":"6900",
    "sg:province":"Ticino",
    "wof:name":"La Cappuccina Sa",
    "wof:placetype":"venue"
},
  "geometry": {"coordinates":[8.9594402313,46.0058059692],"type":"Point"}
}