{
  "type": "Feature",
  "properties": {
    "addr:full":"Panoramastr. 19 Kirchberg St. Gallen 9533",
    "addr:housenumber":"19;st.",
    "addr:postcode":"9533",
    "addr:street":"Panoramastr.;Kirchberg",
    "iso:country":"CH",
    "sg:address":"Panoramastr. 19",
    "sg:city":"Kirchberg",
    "sg:classifiers":[
        {
            "category":"Manufacturing",
            "subcategory":"Wood Products",
            "type":"Manufacturing & Wholesale Goods"
        }
    ],
    "sg:phone":"+41 71 932 32 32",
    "sg:postcode":"9533",
    "sg:province":"St. Gallen",
    "sg:tags":[
        "professional",
        "furniture"
    ],
    "wof:name":"Syma-system Ag",
    "wof:placetype":"venue"
},
  "geometry": {"coordinates":[9.046281,47.410202],"type":"Point"}
}