{
  "type": "Feature",
  "properties": {
    "iso:country":"CH",
    "sg:address":"Lauriedstrasse 4",
    "sg:city":"Zug",
    "sg:orig_category":"Detailhandel mit Radio U Fernsehger\u00e4ten",
    "sg:phone":"+41 41 711 91 81",
    "sg:postcode":"6300",
    "sg:province":"Zug",
    "wof:name":"Joe Br\u00e4ndli Electronic-center",
    "wof:placetype":"venue"
},
  "geometry": {"coordinates":[8.5185146332,47.1750640869],"type":"Point"}
}