{
  "type": "Feature",
  "properties": {
    "iso:country":"CH",
    "sg:address":"Weidenpark 1",
    "sg:city":"M\u00f6hlin",
    "sg:orig_category":"Fachdetailhandel in Verkaufsr\u00e4umen Grosshandel mit Sportartikeln",
    "sg:phone":"+41 61 303 12 10",
    "sg:postcode":"4313",
    "sg:province":"Aargau",
    "wof:name":"Sporteria Zenklusen",
    "wof:placetype":"venue"
},
  "geometry": {"coordinates":[7.8402910233,47.5601501465],"type":"Point"}
}