{
  "type": "Feature",
  "properties": {
    "iso:country":"CH",
    "sg:address":"Immeuble Cassiop\u00e9e 1",
    "sg:city":"Mol\u00e9son-village",
    "sg:orig_category":"Aktivit\u00e4ten der Generalunternehmen im Baugewerbe Unternehmensberatung",
    "sg:phone":"+41 26 921 15 78",
    "sg:postcode":"1662",
    "wof:name":"Gratisa Sa",
    "wof:placetype":"venue"
},
  "geometry": {"coordinates":[7.03771,46.56131],"type":"Point"}
}