{
  "type": "Feature",
  "properties": {
    "iso:country":"CH",
    "sg:address":"Via Lucomagno 27",
    "sg:city":"Biasca",
    "sg:classifiers":[
        {
            "category":"Restaurant",
            "type":"Food & Drink"
        }
    ],
    "sg:phone":"+41 91 862 55 95",
    "sg:postcode":"6710",
    "sg:province":"Ticino",
    "wof:name":"Ristorante Rotonda",
    "wof:placetype":"venue"
},
  "geometry": {"coordinates":[8.9705400467,46.3616371155],"type":"Point"}
}