{
  "type": "Feature",
  "properties": {
    "iso:country":"CH",
    "sg:address":"Kirchlindachstrasse 22",
    "sg:city":"Zollikofen",
    "sg:orig_category":"Blumen U Zierpflanzenbau",
    "sg:phone":"+41 31 911 11 10",
    "sg:postcode":"3052",
    "sg:province":"Bern",
    "wof:name":"Arthur Welti Gartenbau & Unterhalt",
    "wof:placetype":"venue"
},
  "geometry": {"coordinates":[7.458833,47.000751],"type":"Point"}
}