{
  "type": "Feature",
  "properties": {
    "iso:country":"CH",
    "sg:address":"Chemin De La Gravi\u00e8re 9",
    "sg:city":"Ch\u00eane-bourg",
    "sg:orig_category":"Herstellung von homogenisierten U di\u00e4tetischen Nahrungsmitteln Werbung",
    "sg:phone":"+41 22 348 63 40",
    "sg:postcode":"1225",
    "sg:province":"Gen\u00e8ve",
    "wof:name":"Vickland Sa",
    "wof:placetype":"venue"
},
  "geometry": {"coordinates":[6.2000608444,46.1970024109],"type":"Point"}
}