{
  "type": "Feature",
  "properties": {
    "iso:country":"CH",
    "sg:address":"Rue De Neuch\u00e2tel",
    "sg:city":"Yverdon-les-bains",
    "sg:orig_category":"Herstellung von elektrischen Lampen U Leuchten",
    "sg:postcode":"1400",
    "sg:province":"Vaud",
    "wof:name":"Space Lights, P. Martin",
    "wof:placetype":"venue"
},
  "geometry": {"coordinates":[6.6338119507,46.7837982178],"type":"Point"}
}