{
  "type": "Feature",
  "properties": {
    "iso:country":"CH",
    "sg:address":"Im Chalch 611",
    "sg:city":"Wallbach",
    "sg:orig_category":"G\u00fcterbef\u00f6rderung im Strassenverkehr",
    "sg:phone":"+41 61 861 15 56",
    "sg:postcode":"4323",
    "sg:province":"Aargau",
    "wof:name":"B\u00e4umle-steiner Ag",
    "wof:placetype":"venue"
},
  "geometry": {"coordinates":[7.9057660103,47.5572624207],"type":"Point"}
}