{
  "type": "Feature",
  "properties": {
    "iso:country":"CH",
    "sg:address":"Winkelriedstrasse 65 5430 Wettingen. Postfach 38",
    "sg:city":"Wettingen",
    "sg:orig_category":"Vermietung U Verpachtung von eigenen Immobilien",
    "sg:postcode":"5430",
    "sg:province":"Aargau",
    "wof:name":"Immobiliengesellschaft Wettingen Ag",
    "wof:placetype":"venue"
},
  "geometry": {"coordinates":[8.3143920898,47.463306427],"type":"Point"}
}