{
  "type": "Feature",
  "properties": {
    "iso:country":"CH",
    "sg:address":"Habsburgerstrasse 44",
    "sg:city":"Luzern",
    "sg:orig_category":"Zeitungsverlag",
    "sg:postcode":"6003",
    "sg:province":"Luzern",
    "wof:name":"Verein Zur Herausgabe Einer Zeitschrift F\u00fcr Praktische Pfarreiarbeit",
    "wof:placetype":"venue"
},
  "geometry": {"coordinates":[8.3050041199,47.0461082458],"type":"Point"}
}