{
  "type": "Feature",
  "properties": {
    "iso:country":"CH",
    "sg:address":"Route De Pra De Plan 3",
    "sg:city":"Ch\u00e2tel-st-denis",
    "sg:orig_category":"Grosshandel mit Parf\u00fcmerieartikeln U K\u00f6rperpflegemitteln Grosshandel mit pharmazeutischen Erzeugniss",
    "sg:phone":"+41 55 451 21 21",
    "sg:postcode":"1618",
    "sg:province":"Fribourg",
    "wof:name":"Octapharma Ag",
    "wof:placetype":"venue"
},
  "geometry": {"coordinates":[8.8541784286,47.1916236877],"type":"Point"}
}