{
  "type": "Feature",
  "properties": {
    "iso:country":"CH",
    "sg:address":"Solothurnerstr. 259 Pf 1817",
    "sg:city":"Olten",
    "sg:classifiers":[
        {
            "category":"Wholesale",
            "subcategory":"Machinery & Supplies",
            "type":"Manufacturing & Wholesale Goods"
        }
    ],
    "sg:phone":"+41 62 205 95 11",
    "sg:postcode":"4601",
    "sg:province":"Solothurn",
    "sg:tags":[
        "handling",
        "material",
        "-",
        "machine",
        "equipment",
        "engineering",
        "mechanical"
    ],
    "wof:name":"Stirnimann Ag",
    "wof:placetype":"venue"
},
  "geometry": {"coordinates":[7.9040288925,47.3521194458],"type":"Point"}
}