{
  "type": "Feature",
  "properties": {
    "iso:country":"CH",
    "sg:address":"Seestrasse 153",
    "sg:city":"St\u00e4fa",
    "sg:orig_category":"Saunas, Solarien, Fitnesszentren U \u00e4hnliches",
    "sg:phone":"+41 79 401 41 18",
    "sg:postcode":"8712",
    "sg:province":"Z\u00fcrich",
    "wof:name":"Sunpower Sa",
    "wof:placetype":"venue"
},
  "geometry": {"coordinates":[8.7342596054,47.2345581055],"type":"Point"}
}