{
  "type": "Feature",
  "properties": {
    "iso:country":"CH",
    "sg:address":"Soldini Via 28",
    "sg:city":"Chiasso",
    "sg:orig_category":"Finanzierungsinstitutionen",
    "sg:phone":"+41 91 682 93 91",
    "sg:postcode":"6830",
    "sg:province":"Ticino",
    "wof:name":"Edie Sa",
    "wof:placetype":"venue"
},
  "geometry": {"coordinates":[9.0186901093,45.8350105286],"type":"Point"}
}