{
  "type": "Feature",
  "properties": {
    "iso:country":"CH",
    "sg:address":"Riedeggweg 70",
    "sg:city":"Bern",
    "sg:orig_category":"Sonstiger Grosshandel",
    "sg:postcode":"3020",
    "sg:province":"Bern",
    "wof:name":"Egli Lilly's Importe",
    "wof:placetype":"venue"
},
  "geometry": {"coordinates":[7.3325209618,46.9382820129],"type":"Point"}
}