{
  "type": "Feature",
  "properties": {
    "iso:country":"CH",
    "sg:address":"Ohne Domizil",
    "sg:city":"Niederurnen",
    "sg:orig_category":"Unclassifiable Establishments",
    "sg:phone":"+41 81 322 74 59",
    "sg:postcode":"8867",
    "sg:province":"Glarus",
    "wof:name":"Gort Hans Peter",
    "wof:placetype":"venue"
},
  "geometry": {"coordinates":[9.5717229843,46.9813728333],"type":"Point"}
}