{
  "type": "Feature",
  "properties": {
    "addr:full":"Bahnhofstrasse 2 Schlieren Z\u00fcrich 8952",
    "addr:housenumber":"2",
    "addr:postcode":"8952",
    "addr:street":"Bahnhofstrasse",
    "iso:country":"CH",
    "sg:address":"Bahnhofstrasse 2",
    "sg:city":"Schlieren",
    "sg:orig_category":"Arztpraxen",
    "sg:phone":"+41 17306646",
    "sg:postcode":"8952",
    "sg:province":"Z\u00fcrich",
    "wof:name":"Dres Inauen Gross Oggenfuss Aerzte F\u00fcr Allg.medizin Fmh",
    "wof:placetype":"venue"
},
  "geometry": {"coordinates":[8.448379,47.398289],"type":"Point"}
}