{
  "type": "Feature",
  "properties": {
    "addr:full":"Eggen 27 Gurzelen Bern 3663",
    "addr:housenumber":"27",
    "addr:postcode":"3663",
    "addr:street":"Eggen",
    "iso:country":"CH",
    "sg:address":"Eggen 27",
    "sg:city":"Gurzelen",
    "sg:orig_category":"Architektur U Ingenieurb\u00fcros",
    "sg:phone":"+41 33 345 06 28",
    "sg:postcode":"3663",
    "sg:province":"Bern",
    "wof:name":"Kusag Engineering Ag",
    "wof:placetype":"venue"
},
  "geometry": {"coordinates":[7.542336,46.77639],"type":"Point"}
}