{
  "type": "Feature",
  "properties": {
    "iso:country":"CH",
    "sg:address":"R\u00e4sch 9",
    "sg:city":"D\u00fcdingen",
    "sg:orig_category":"Grosshandel mit landwirtschaftlichen Maschinen U Ger\u00e4ten",
    "sg:phone":"+41 26 493 40 37",
    "sg:postcode":"3186",
    "sg:province":"Fribourg",
    "wof:name":"Ambi-farm Ag Surge Melkanlagen",
    "wof:placetype":"venue"
},
  "geometry": {"coordinates":[7.1577601433,46.8332061768],"type":"Point"}
}