{
  "type": "Feature",
  "properties": {
    "iso:country":"CH",
    "sg:address":"Austrasse 109",
    "sg:city":"Neuenegg",
    "sg:orig_category":"Einzelhandel mit Automobilteilen U Zubeh\u00f6r",
    "sg:phone":"+41 31 741 10 50",
    "sg:postcode":"3176",
    "sg:province":"Bern",
    "wof:name":"Hans Sch\u00fcrch Pneuhandel",
    "wof:placetype":"venue"
},
  "geometry": {"coordinates":[7.3190121651,46.8940162659],"type":"Point"}
}