{
  "type": "Feature",
  "properties": {
    "iso:country":"CH",
    "sg:address":"Place Pestalozzi 13",
    "sg:city":"Yverdon-les-bains",
    "sg:orig_category":"RESTAURANTS: TEA-ROOMS",
    "sg:phone":"+41 24 425 37 34",
    "sg:postcode":"1400",
    "sg:province":"Vaud",
    "wof:name":"M\u00e9groz Michel",
    "wof:placetype":"venue"
},
  "geometry": {"coordinates":[6.6416578293,46.77866745],"type":"Point"}
}