{
  "type": "Feature",
  "properties": {
    "iso:country":"CH",
    "sg:address":"Via Canova 15",
    "sg:city":"Lugano",
    "sg:classifiers":[
        {
            "category":"Banks & Credit Unions",
            "subcategory":"Bank",
            "type":"Services"
        }
    ],
    "sg:phone":"+41 91 206 11 11",
    "sg:postcode":"6901",
    "sg:province":"Ticino",
    "wof:name":"Credit Suisse",
    "wof:placetype":"venue"
},
  "geometry": {"coordinates":[8.954594,46.004562],"type":"Point"}
}