{
  "type": "Feature",
  "properties": {
    "iso:country":"CH",
    "sg:address":"Sonnhaldestrasse 74",
    "sg:city":"Ebikon",
    "sg:orig_category":"Architektur U Ingenieurb\u00fcros",
    "sg:phone":"+41 61 751 49 50",
    "sg:postcode":"6030",
    "sg:province":"Luzern",
    "wof:name":"B\u00fcro F\u00fcr Planung Und Bauleitung Marioni Rinaldo",
    "wof:placetype":"venue"
},
  "geometry": {"coordinates":[7.5613,47.5196],"type":"Point"}
}