{
  "type": "Feature",
  "properties": {
    "iso:country":"CH",
    "sg:address":"1309",
    "sg:city":"Cuarnens",
    "sg:orig_category":"Bauschreinerei Herstellung von M\u00f6beln verschiedener Art",
    "sg:phone":"+41 22 343 19 65",
    "sg:postcode":"1309",
    "wof:name":"Pierre-albert Casagrande Eb\u00e9nisterie",
    "wof:placetype":"venue"
},
  "geometry": {"coordinates":[6.143907,46.186241],"type":"Point"}
}