{
  "type": "Feature",
  "properties": {
    "iso:country":"CH",
    "sg:address":"Staadstrasse 40",
    "sg:city":"Grenchen",
    "sg:classifiers":[
        {
            "category":"Wholesale",
            "subcategory":"Machinery & Supplies",
            "type":"Manufacturing & Wholesale Goods"
        }
    ],
    "sg:phone":"+41 61 481 40 03",
    "sg:postcode":"2540",
    "sg:province":"Solothurn",
    "sg:tags":[
        "equipment",
        "equipement",
        "precision",
        "timekeeping"
    ],
    "wof:name":"H. Moebius & Fils",
    "wof:placetype":"venue"
},
  "geometry": {"coordinates":[7.5371499062,47.5522193909],"type":"Point"}
}