{
  "type": "Feature",
  "properties": {
    "iso:country":"CH",
    "sg:address":"M\u00fchlethalstrasse 67",
    "sg:city":"Zofingen",
    "sg:orig_category":"Herstellung von Metallerzeugnissen ohne Maschinenbau Herstellung von sonstigen Maschinen f\u00fcr unspezi",
    "sg:phone":"+41 62 746 92 02",
    "sg:postcode":"4800",
    "sg:province":"Aargau",
    "wof:name":"W\u00fclsag Apparatebau Ag",
    "wof:placetype":"venue"
},
  "geometry": {"coordinates":[7.9548068047,47.297290802],"type":"Point"}
}