{
  "type": "Feature",
  "properties": {
    "iso:country":"CH",
    "sg:address":"Ifangstrasse 6",
    "sg:city":"Schlieren",
    "sg:orig_category":"Personal U Stellenvermittlung Vermietung von Luftfahrzeugen",
    "sg:phone":"+41 19103970",
    "sg:postcode":"8952",
    "sg:province":"Z\u00fcrich",
    "wof:name":"Asa Air Services Associates Ag Dienstleistungen I.luftverkehr",
    "wof:placetype":"venue"
},
  "geometry": {"coordinates":[8.5840988159,47.32447052],"type":"Point"}
}