{
  "type": "Feature",
  "properties": {
    "iso:country":"CH",
    "sg:address":"Schleifentobelweg 11",
    "sg:city":"Hittnau",
    "sg:orig_category":"Politische Parteien FDP",
    "sg:phone":"+41 19505861",
    "sg:postcode":"8335",
    "sg:province":"Z\u00fcrich",
    "wof:name":"Fdp Ortspartei Hittnau",
    "wof:placetype":"venue"
},
  "geometry": {"coordinates":[8.8309688568,47.3644981384],"type":"Point"}
}