{
  "type": "Feature",
  "properties": {
    "iso:country":"CH",
    "sg:address":"Lindenstrasse 2 5430 Wettingen. Postfach",
    "sg:city":"Baden",
    "sg:orig_category":"Unternehmensberatung",
    "sg:postcode":"5400",
    "sg:province":"Aargau",
    "wof:name":"D\u00fcrig & St\u00e4hli Innovative Services Dienstleistungen F\u00fcr Unternehmen U. Privatpersonen Der Internetgeneration",
    "wof:placetype":"venue"
},
  "geometry": {"coordinates":[8.3204021454,47.4648284912],"type":"Point"}
}