{
  "type": "Feature",
  "properties": {
    "iso:country":"CH",
    "sg:address":"Avenue G\u00e9n\u00e9ral-guisan 19",
    "sg:city":"Vevey",
    "sg:classifiers":[
        {
            "category":"Personal",
            "subcategory":"Piercing",
            "type":"Services"
        }
    ],
    "sg:phone":"+41 79 436 90 65",
    "sg:postcode":"1800",
    "sg:province":"Vaud",
    "sg:tags":[
        "tattoo"
    ],
    "wof:name":"Nestor Tattoo Studio",
    "wof:placetype":"venue"
},
  "geometry": {"coordinates":[6.8404979706,46.4637031555],"type":"Point"}
}