{
  "type": "Feature",
  "properties": {
    "iso:country":"CH",
    "sg:address":"Rue De La Fin",
    "sg:city":"Cortaillod",
    "sg:orig_category":"Detailhandel mit Waren verschiedener Art, Hauptrichtung Nahrungsmittel",
    "sg:phone":"+41 32 954 11 50",
    "sg:postcode":"2016",
    "sg:province":"Neuch\u00e2tel",
    "wof:name":"Coop Neuch\u00e2tel-jura",
    "wof:placetype":"venue"
},
  "geometry": {"coordinates":[7.0041618347,47.2100524902],"type":"Point"}
}