{
  "type": "Feature",
  "properties": {
    "iso:country":"CH",
    "sg:address":"Avant-poste Avenue De L' 5 1005 Lausanne Case Postale",
    "sg:city":"Lausanne",
    "sg:orig_category":"Instandhaltung U Reparatur von Automobilen",
    "sg:phone":"+41 26 418 12 67",
    "sg:postcode":"1005",
    "sg:province":"Vaud",
    "wof:name":"Garage Rumo & Trachsel Ag",
    "wof:placetype":"venue"
},
  "geometry": {"coordinates":[7.2057070732,46.7494049072],"type":"Point"}
}