{
  "type": "Feature",
  "properties": {
    "iso:country":"CH",
    "sg:address":"Via Vincenzo Vela 6 6830 Chiasso Casella Postale",
    "sg:city":"Chiasso",
    "sg:orig_category":"Detailhandel mit B\u00fcchern Detailhandel mit B\u00fcchern, Zeitungen, Schreib U Papeteriewaren",
    "sg:phone":"+41 32 842 10 78",
    "sg:postcode":"6830",
    "sg:province":"Ticino",
    "wof:name":"Cbf Papeteries & Librairies",
    "wof:placetype":"venue"
},
  "geometry": {"coordinates":[6.750693,47.058323],"type":"Point"}
}