{
  "type": "Feature",
  "properties": {
    "iso:country":"CH",
    "sg:address":"Gurzelestrasse 2",
    "sg:city":"Wimmis",
    "sg:orig_category":"G\u00fcterbef\u00f6rderung im Strassenverkehr",
    "sg:phone":"+41 33 853 29 51",
    "sg:postcode":"3752",
    "sg:province":"Bern",
    "wof:name":"Kaspar Wenger Transporte",
    "wof:placetype":"venue"
},
  "geometry": {"coordinates":[7.6393852234,46.6765289307],"type":"Point"}
}