{
  "type": "Feature",
  "properties": {
    "iso:country":"CH",
    "sg:address":"Baslerstrasse 57 4310 Rheinfelden. Postfach",
    "sg:city":"Rheinfelden",
    "sg:orig_category":"Detailhandel mit elektrischen Haushalts-,Radio U Fernsehger\u00e4ten sowie Musikinstrumenten",
    "sg:postcode":"4310",
    "sg:province":"Aargau",
    "wof:name":"Professional-service K\u00e4stli Tino",
    "wof:placetype":"venue"
},
  "geometry": {"coordinates":[7.7774591446,47.5507049561],"type":"Point"}
}