{
  "type": "Feature",
  "properties": {
    "iso:country":"CH",
    "sg:address":"Avenue Louis-pictet 6",
    "sg:city":"Vernier",
    "sg:orig_category":"Grosshandel mit B\u00fcromaschinen Grosshandel mit B\u00fcrom\u00f6beln",
    "sg:phone":"+41 32 373 30 42",
    "sg:postcode":"1214",
    "sg:province":"Gen\u00e8ve",
    "wof:name":"Afa Organisation Sa",
    "wof:placetype":"venue"
},
  "geometry": {"coordinates":[7.2592320442,47.1212043762],"type":"Point"}
}