{
  "type": "Feature",
  "properties": {
    "iso:country":"CH",
    "sg:address":"Via Pobbia",
    "sg:city":"Sementina",
    "sg:orig_category":"Herstellung von Ger\u00e4ten der Elektrizit\u00e4tserzeugung, -verteilung u.\u00e4. -Handel mit Automobilen",
    "sg:phone":"+41 79 207 06 74",
    "sg:postcode":"6514",
    "sg:province":"Ticino",
    "wof:name":"Roll-star Di Reto Semmler Carrozzelli Per Invalidi",
    "wof:placetype":"venue"
},
  "geometry": {"coordinates":[8.9997558594,46.1812362671],"type":"Point"}
}