{
  "type": "Feature",
  "properties": {
    "addr:full":"Rosentalstrasse 18 Hochdorf Luzern 6280",
    "addr:housenumber":"18",
    "addr:postcode":"6280",
    "addr:street":"Rosentalstrasse",
    "iso:country":"CH",
    "sg:address":"Rosentalstrasse 18",
    "sg:city":"Hochdorf",
    "sg:orig_category":"Bauspenglerei Sanit\u00e4rinstallation",
    "sg:phone":"+41 79 910 05 60",
    "sg:postcode":"6280",
    "sg:province":"Luzern",
    "wof:name":"Fiorendo Vidoni San.installationen Spenglerei",
    "wof:placetype":"venue"
},
  "geometry": {"coordinates":[8.288683,47.169735],"type":"Point"}
}