{
  "type": "Feature",
  "properties": {
    "iso:country":"CH",
    "sg:address":"M\u00fchlegutstrasse 15",
    "sg:city":"Steinach",
    "sg:orig_category":"Dachdeckerei Zimmerei, Dachdeckerei, Bauspenglerei U Abdichtung",
    "sg:phone":"+41 71 446 77 19",
    "sg:postcode":"9323",
    "sg:province":"St. Gallen",
    "wof:name":"K\u00fcndig Krohn Bedachungs Ag",
    "wof:placetype":"venue"
},
  "geometry": {"coordinates":[9.440091,47.501507],"type":"Point"}
}