{
  "type": "Feature",
  "properties": {
    "iso:country":"CH",
    "sg:address":"In Der Fuchsh\u00fctte 14",
    "sg:city":"D\u00fcbendorf",
    "sg:orig_category":"Kauf U Verkauf von Immobilien auf eigene Rechnung Vermittlung von Immobilien",
    "sg:phone":"+41 18215486",
    "sg:postcode":"8600",
    "sg:province":"Z\u00fcrich",
    "wof:name":"Christand Ag Liegenschaftenhandel",
    "wof:placetype":"venue"
},
  "geometry": {"coordinates":[8.614733696,47.406414032],"type":"Point"}
}