{
  "type": "Feature",
  "properties": {
    "iso:country":"CH",
    "sg:address":"Boden",
    "sg:city":"Unterterzen",
    "sg:orig_category":"Elektrizit\u00e4tsversorgung",
    "sg:phone":"+41 79 410 18 23",
    "sg:postcode":"8882",
    "sg:province":"St. Gallen",
    "wof:name":"Elektrizit\u00e4tswerk Der Ortsgemeinde Quarten",
    "wof:placetype":"venue"
},
  "geometry": {"coordinates":[9.252325058,47.1129150391],"type":"Point"}
}