{
  "type": "Feature",
  "properties": {
    "iso:country":"CH",
    "sg:address":"Rue Des Plantys 4",
    "sg:city":"Chamoson",
    "sg:orig_category":"Herstellung von sonstigen landwirtschaftlichen Maschinen Mechanische Werkst\u00e4tten",
    "sg:phone":"+41 27 306 54 54",
    "sg:postcode":"1955",
    "sg:province":"Valais",
    "wof:name":"Daniel Aubert Atelier M\u00e9canique",
    "wof:placetype":"venue"
},
  "geometry": {"coordinates":[7.228017807,46.1977081299],"type":"Point"}
}