{
  "type": "Feature",
  "properties": {
    "iso:country":"CH",
    "sg:address":"Auberge Les Colombettes",
    "sg:city":"Vuadens",
    "sg:orig_category":"Interessenvertretungen",
    "sg:postcode":"1628",
    "sg:province":"Fribourg",
    "wof:name":"Fondation Les Colombettes De L'association Bovet Joseph",
    "wof:placetype":"venue"
},
  "geometry": {"coordinates":[6.9935059547,46.6104621887],"type":"Point"}
}