{
  "type": "Feature",
  "properties": {
    "iso:country":"CH",
    "sg:address":"Kronwiesenstrasse 47",
    "sg:city":"Z\u00fcrich",
    "sg:orig_category":"Fahrschulen, Flugschulen",
    "sg:phone":"+41 71 222 42 65",
    "sg:postcode":"8051",
    "sg:province":"Z\u00fcrich",
    "wof:name":"Arnold Siegfried Autofahrschule",
    "wof:placetype":"venue"
},
  "geometry": {"coordinates":[9.3943939209,47.4151954651],"type":"Point"}
}