{
  "type": "Feature",
  "properties": {
    "iso:country":"CH",
    "sg:address":"Cantonale Via 16",
    "sg:city":"Lugano",
    "sg:orig_category":"Vermietung U Verpachtung von eigenen Immobilien",
    "sg:postcode":"6900",
    "sg:province":"Ticino",
    "wof:name":"Bonavia Sa",
    "wof:placetype":"venue"
},
  "geometry": {"coordinates":[8.9507102966,46.0086479187],"type":"Point"}
}