{
  "type": "Feature",
  "properties": {
    "iso:country":"CH",
    "sg:address":"Chemin D'epinglis 20 1258 Perly. Postfach",
    "sg:city":"Perly",
    "sg:orig_category":"G\u00fcterbef\u00f6rderung im Strassenverkehr",
    "sg:phone":"+41 22 771 22 00",
    "sg:postcode":"1258",
    "sg:province":"Gen\u00e8ve",
    "wof:name":"Bellereaux Sa Gen\u00e8ve Transports Internationaux",
    "wof:placetype":"venue"
},
  "geometry": {"coordinates":[6.0988988876,46.1510047913],"type":"Point"}
}