{
  "type": "Feature",
  "properties": {
    "iso:country":"CH",
    "sg:address":"Mattenhofstrasse 17",
    "sg:city":"Bern",
    "sg:classifiers":[
        {
            "category":"Manufacturing",
            "subcategory":"Glass & Minerals",
            "type":"Manufacturing & Wholesale Goods"
        }
    ],
    "sg:phone":"+41 31 381 22 55",
    "sg:postcode":"3007",
    "sg:province":"Bern",
    "sg:tags":[
        "flat"
    ],
    "wof:name":"Glas Scherz Ag",
    "wof:placetype":"venue"
},
  "geometry": {"coordinates":[7.4304270744,46.9430923462],"type":"Point"}
}