{
  "type": "Feature",
  "properties": {
    "iso:country":"CH",
    "sg:address":"R\u00fcdigerstrasse 11",
    "sg:city":"Z\u00fcrich",
    "sg:orig_category":"Grosshandel mit Textil, N\u00e4h U Strickmaschinen Grosshandel mit Textilien",
    "sg:phone":"+41 12010221",
    "sg:postcode":"8045",
    "sg:province":"Z\u00fcrich",
    "wof:name":"Freespring Ag",
    "wof:placetype":"venue"
},
  "geometry": {"coordinates":[8.5217065811,47.3603057861],"type":"Point"}
}