{
  "type": "Feature",
  "properties": {
    "iso:country":"CH",
    "sg:address":"Via Mercoli 1",
    "sg:city":"Lugano",
    "sg:orig_category":"Detailhandel mit medizinischen U orthop\u00e4dischen Artikeln Herstellung von medizinischen U chirurgisch",
    "sg:phone":"+41 41 850 66 94",
    "sg:postcode":"6900",
    "sg:province":"Ticino",
    "wof:name":"Fuss-orthop\u00e4die Camenzind Paul",
    "wof:placetype":"venue"
},
  "geometry": {"coordinates":[8.4417600632,47.0846099854],"type":"Point"}
}