{
  "type": "Feature",
  "properties": {
    "iso:country":"CH",
    "sg:address":"Dorfstrasse 30",
    "sg:city":"Tegerfelden",
    "sg:orig_category":"Berufliche Weiterbildung, Erwachsenenbildung",
    "sg:phone":"+41 56 245 55 84",
    "sg:postcode":"5306",
    "sg:province":"Aargau",
    "wof:name":"Volkshochschule Region Zurzach",
    "wof:placetype":"venue"
},
  "geometry": {"coordinates":[8.288614,47.558006],"type":"Point"}
}