{
  "type": "Feature",
  "properties": {
    "iso:country":"CH",
    "sg:address":"Scheuermattweg 7",
    "sg:city":"Uettligen",
    "sg:orig_category":"Kosmetikinstitute",
    "sg:phone":"+41 31 829 18 80",
    "sg:postcode":"3043",
    "sg:province":"Bern",
    "wof:name":"Gisela Rohner Kosmetik Silhouette",
    "wof:placetype":"venue"
},
  "geometry": {"coordinates":[7.3855519295,46.987361908],"type":"Point"}
}