{
  "type": "Feature",
  "properties": {
    "iso:country":"CH",
    "sg:address":"Dammstrasse 13",
    "sg:city":"Hettlingen",
    "sg:orig_category":"Gesundheitswesen Unternehmensberatung",
    "sg:phone":"+41 52 301 13 03",
    "sg:postcode":"8442",
    "sg:province":"Z\u00fcrich",
    "wof:name":"Intermed Consulting Ag Unternehmensberatung",
    "wof:placetype":"venue"
},
  "geometry": {"coordinates":[8.6972894669,47.5433197021],"type":"Point"}
}