{
  "type": "Feature",
  "properties": {
    "iso:country":"CH",
    "sg:address":"Rathaus 7430 Thusis. Postfach 149",
    "sg:city":"Thusis",
    "sg:orig_category":"Verwaltung der Rechtspflege, Gerichte",
    "sg:phone":"+41 55 286 13 26",
    "sg:postcode":"7430",
    "sg:province":"Graubunden",
    "wof:name":"Grundbuchamt",
    "wof:placetype":"venue"
},
  "geometry": {"coordinates":[8.9213428497,47.2407341003],"type":"Point"}
}