{
  "type": "Feature",
  "properties": {
    "iso:country":"CH",
    "sg:address":"Rue Industrielle 16",
    "sg:city":"Moutier",
    "sg:classifiers":[
        {
            "category":"Manufacturing",
            "subcategory":"Tools & Machinery",
            "type":"Manufacturing & Wholesale Goods"
        }
    ],
    "sg:phone":"+41 32 961 17 17",
    "sg:postcode":"2740",
    "sg:province":"Bern",
    "sg:tags":[
        "part",
        "turned",
        "cnc"
    ],
    "wof:name":"Z\u00fcrcher Fr\u00e8res Sa",
    "wof:placetype":"venue"
},
  "geometry": {"coordinates":[6.90385,47.176754],"type":"Point"}
}