{
  "type": "Feature",
  "properties": {
    "addr:full":"Hammerstrasse 123 Basel Basel-Stadt 4057",
    "addr:housenumber":"123",
    "addr:postcode":"4057",
    "addr:street":"Hammerstrasse",
    "iso:country":"CH",
    "sg:address":"Hammerstrasse 123",
    "sg:city":"Basel",
    "sg:orig_category":"Arztpraxen",
    "sg:phone":"+41 61 693 10 55",
    "sg:postcode":"4057",
    "sg:province":"Basel-Stadt",
    "wof:name":"Dr.med.felix Walther Eymann Spezialarzt",
    "wof:placetype":"venue"
},
  "geometry": {"coordinates":[7.594996,47.566849],"type":"Point"}
}