{
  "type": "Feature",
  "properties": {
    "iso:country":"CH",
    "sg:address":"Luzernerstrasse 44",
    "sg:city":"Kriens",
    "sg:orig_category":"Grosshandel mit sonstigen Gebrauchs U Verbrauchsg\u00fctern",
    "sg:postcode":"6010",
    "sg:province":"Luzern",
    "wof:name":"Duss Automaten",
    "wof:placetype":"venue"
},
  "geometry": {"coordinates":[8.2851276398,47.0342025757],"type":"Point"}
}