{
  "type": "Feature",
  "properties": {
    "iso:country":"CH",
    "sg:address":"Waldeggstrasse 38",
    "sg:city":"K\u00f6niz",
    "sg:orig_category":"Unternehmensberatung",
    "sg:postcode":"3098",
    "sg:province":"Bern",
    "wof:name":"Carba Aktiengesellschaft",
    "wof:placetype":"venue"
},
  "geometry": {"coordinates":[7.419069767,46.9332962036],"type":"Point"}
}