{
  "type": "Feature",
  "properties": {
    "iso:country":"CH",
    "sg:address":"Rue Des Parcs 129",
    "sg:city":"Neuch\u00e2tel",
    "sg:classifiers":[
        {
            "category":"Manufacturing",
            "subcategory":"Tools & Machinery",
            "type":"Manufacturing & Wholesale Goods"
        }
    ],
    "sg:phone":"+41 32 724 12 66",
    "sg:postcode":"2000",
    "sg:province":"Neuch\u00e2tel",
    "sg:tags":[
        "machine"
    ],
    "wof:name":"Willy Perret-gentil",
    "wof:placetype":"venue"
},
  "geometry": {"coordinates":[6.9139289856,46.9906768799],"type":"Point"}
}