{
  "type": "Feature",
  "properties": {
    "iso:country":"CH",
    "sg:address":"Grund 13",
    "sg:city":"Grindelwald",
    "sg:orig_category":"Vorschulen, Kinderg\u00e4rten",
    "sg:phone":"+41 33 853 25 68",
    "sg:postcode":"3818",
    "sg:province":"Bern",
    "wof:name":"Kindergarten Zahnredli",
    "wof:placetype":"venue"
},
  "geometry": {"coordinates":[8.0196399689,46.6256790161],"type":"Point"}
}