{
  "type": "Feature",
  "properties": {
    "iso:country":"CH",
    "sg:address":"Giornico",
    "sg:city":"Giornico",
    "sg:classifiers":[
        {
            "category":"Banks & Credit Unions",
            "subcategory":"Bank",
            "type":"Services"
        }
    ],
    "sg:phone":"+41 92742727",
    "sg:postcode":"6745",
    "sg:province":"Ticino",
    "wof:name":"Rentenanstalt Swiss Life",
    "wof:placetype":"venue"
},
  "geometry": {"coordinates":[8.875468,46.402813],"type":"Point"}
}