{
  "type": "Feature",
  "properties": {
    "iso:country":"CH",
    "sg:address":"Bahnhofstrasse 14 4900 Langenthal. Postfach",
    "sg:city":"Langenthal",
    "sg:orig_category":"Druck ohne Zeitungsdruck Siebdruck",
    "sg:phone":"+41 62 922 53 57",
    "sg:postcode":"4901",
    "sg:province":"Bern",
    "wof:name":"Sidler + Co. Schriften Siebdruck",
    "wof:placetype":"venue"
},
  "geometry": {"coordinates":[7.7880558968,47.2131881714],"type":"Point"}
}