{
  "type": "Feature",
  "properties": {
    "iso:country":"CH",
    "sg:address":"Hangweg 7",
    "sg:city":"Brittnau",
    "sg:orig_category":"Architektur U Ingenieurb\u00fcros",
    "sg:phone":"+41 62 751 92 47",
    "sg:postcode":"4805",
    "sg:province":"Aargau",
    "wof:name":"H\u00f6lzle Ingenieurb\u00fcro.",
    "wof:placetype":"venue"
},
  "geometry": {"coordinates":[7.94683,47.253689],"type":"Point"}
}