{
  "type": "Feature",
  "properties": {
    "iso:country":"CH",
    "sg:address":"Chemin Du Tr\u00e9si 6d",
    "sg:city":"Pr\u00e9verenges",
    "sg:orig_category":"Detailhandel mit elektrischen Haushalts-,Radio U Fernsehger\u00e4ten sowie Musikinstrumenten Herstellung ",
    "sg:phone":"+41 21 633 07 70",
    "sg:postcode":"1028",
    "sg:province":"Vaud",
    "wof:name":"Feusier Engineering Sa, Succursale De Pr\u00e9verenges",
    "wof:placetype":"venue"
},
  "geometry": {"coordinates":[6.5308151245,46.5229797363],"type":"Point"}
}