{
  "type": "Feature",
  "properties": {
    "iso:country":"CH",
    "sg:address":"Unterm\u00fcli 1",
    "sg:city":"Zug",
    "sg:classifiers":[
        {
            "category":"Airport",
            "type":"Transportation"
        }
    ],
    "sg:phone":"+41 41 760 20 66",
    "sg:postcode":"6300",
    "sg:province":"Zug",
    "sg:tags":[
        "air-freight",
        "forwarders"
    ],
    "wof:name":"Tpl Lager & Verpackungsservice",
    "wof:placetype":"venue"
},
  "geometry": {"coordinates":[8.517419,47.179966],"type":"Point"}
}