{
  "type": "Feature",
  "properties": {
    "addr:full":"Langenthalstrasse 92 Aarwangen Bern 4912",
    "addr:housenumber":"92",
    "addr:postcode":"4912",
    "addr:street":"Langenthalstrasse",
    "iso:country":"CH",
    "sg:address":"Langenthalstrasse 92",
    "sg:city":"Aarwangen",
    "sg:orig_category":"Betrieb von Sportanlagen Gymnastik U Fitnesszentren",
    "sg:phone":"+41 32 652 25 74",
    "sg:postcode":"4912",
    "sg:province":"Bern",
    "wof:name":"S.t.a. Show Time Agency",
    "wof:placetype":"venue"
},
  "geometry": {"coordinates":[7.37167,47.183041],"type":"Point"}
}