{
  "type": "Feature",
  "properties": {
    "iso:country":"CH",
    "sg:address":"Industriestrasse 6 6300 Zug. Postfach 958",
    "sg:city":"Zug",
    "sg:orig_category":"Grosshandel mit M\u00f6beln, Wohnbedarf, Teppichen U Bodenbel\u00e4gen Grosshandel mit Uhren",
    "sg:phone":"+41 41 710 22 44",
    "sg:postcode":"6301",
    "sg:province":"Zug",
    "wof:name":"Amara Schmuck Gmbh, Pforzheim, Zweigniederlassung Zug",
    "wof:placetype":"venue"
},
  "geometry": {"coordinates":[8.5180082321,47.1709365845],"type":"Point"}
}