{
  "type": "Feature",
  "properties": {
    "iso:country":"CH",
    "sg:address":"Beauregard Avenue 12",
    "sg:city":"Fribourg",
    "sg:orig_category":"Unclassifiable Establishments",
    "sg:phone":"+41 19301687",
    "sg:postcode":"1700",
    "sg:province":"Fribourg",
    "wof:name":"Estra Holding Ag",
    "wof:placetype":"venue"
},
  "geometry": {"coordinates":[8.7984800339,47.3245201111],"type":"Point"}
}