{
  "type": "Feature",
  "properties": {
    "iso:country":"CH",
    "sg:address":"Schulstrasse 8",
    "sg:city":"Neftenbach",
    "sg:orig_category":"Nationale Postdienste",
    "sg:phone":"+41 52 315 14 64",
    "sg:postcode":"8413",
    "sg:province":"Z\u00fcrich",
    "wof:name":"Die Schweizerische Post",
    "wof:placetype":"venue"
},
  "geometry": {"coordinates":[8.6650238037,47.526348114],"type":"Point"}
}