{
  "type": "Feature",
  "properties": {
    "iso:country":"CH",
    "sg:address":"Bahnweg 67",
    "sg:city":"Mels",
    "sg:orig_category":"Mechanik Mechanische Werkst\u00e4tten",
    "sg:phone":"+41 81 723 58 20",
    "sg:postcode":"8887",
    "sg:province":"St. Gallen",
    "wof:name":"Tony Eicher Schleifwerk",
    "wof:placetype":"venue"
},
  "geometry": {"coordinates":[9.4201517105,47.0526618958],"type":"Point"}
}