{
  "type": "Feature",
  "properties": {
    "iso:country":"CH",
    "sg:address":"Oberlandstrasse 7",
    "sg:city":"St\u00e4fa",
    "sg:orig_category":"Detailhandel mit Blumen U Pflanzen Fachdetailhandel in Verkaufsr\u00e4umen",
    "sg:phone":"+41 19268668",
    "sg:postcode":"8712",
    "sg:province":"Z\u00fcrich",
    "wof:name":"Papavero Arte & Fiori Blumengesch\u00e4ft",
    "wof:placetype":"venue"
},
  "geometry": {"coordinates":[8.72182,47.239475],"type":"Point"}
}