{
  "type": "Feature",
  "properties": {
    "iso:country":"CH",
    "sg:address":"Baarerstrasse 10",
    "sg:city":"Zug",
    "sg:orig_category":"Fachdetailhandel mit pharmazeutischen Produkten",
    "sg:phone":"+41 71 288 20 40",
    "sg:postcode":"6300",
    "sg:province":"Zug",
    "wof:name":"S\u00e4ntis-apotheke, Teo Koslar",
    "wof:placetype":"venue"
},
  "geometry": {"coordinates":[9.4050827026,47.4365921021],"type":"Point"}
}