{
  "type": "Feature",
  "properties": {
    "iso:country":"CH",
    "sg:address":"Chemin Du Pr\u00e9-de-la-tour 7",
    "sg:city":"Pully",
    "sg:orig_category":"Handelsvermittlung U Grosshandel Sonstiger Grosshandel",
    "sg:phone":"+41 21 728 17 68",
    "sg:postcode":"1009",
    "sg:province":"Vaud",
    "wof:name":"Hildenbrand C. Diffusion",
    "wof:placetype":"venue"
},
  "geometry": {"coordinates":[6.6605191231,46.5115585327],"type":"Point"}
}