{
  "type": "Feature",
  "properties": {
    "iso:country":"CH",
    "sg:address":"Dorfstrasse 26",
    "sg:city":"Wilchingen",
    "sg:classifiers":[
        {
            "category":"Restaurant",
            "type":"Food & Drink"
        }
    ],
    "sg:phone":"+41 22 343 14 25",
    "sg:postcode":"8217",
    "sg:province":"Schaffhausen",
    "wof:name":"Pizzeria Mi-piace",
    "wof:placetype":"venue"
},
  "geometry": {"coordinates":[6.1331768036,46.1870384216],"type":"Point"}
}