{
  "type": "Feature",
  "properties": {
    "iso:country":"CH",
    "sg:address":"Hellm\u00fchlestrasse 4 8580 Amriswil. Postfach",
    "sg:city":"Amriswil",
    "sg:orig_category":"Unternehmensberatung",
    "sg:postcode":"8580",
    "sg:province":"Thurgau",
    "wof:name":"Best-b-marketing Gmbh",
    "wof:placetype":"venue"
},
  "geometry": {"coordinates":[9.2931308746,47.5437431335],"type":"Point"}
}