{
  "type": "Feature",
  "properties": {
    "iso:country":"CH",
    "sg:address":"3801",
    "sg:city":"Jungfraujoch",
    "sg:classifiers":[
        {
            "category":"Government",
            "subcategory":"Post Office",
            "type":"Public Place"
        }
    ],
    "sg:phone":"+41 33 855 24 05",
    "sg:postcode":"3801",
    "sg:province":"Valais",
    "sg:tags":[
        "die",
        "poststellen"
    ],
    "wof:name":"Die Post",
    "wof:placetype":"venue"
},
  "geometry": {"coordinates":[7.9823098183,46.5470314026],"type":"Point"}
}