{
  "type": "Feature",
  "properties": {
    "iso:country":"CH",
    "sg:address":"Rue De Lausanne 65",
    "sg:city":"Gen\u00e8ve",
    "sg:orig_category":"Psychotherapie",
    "sg:phone":"+41 22 738 98 11",
    "sg:postcode":"1202",
    "sg:province":"Gen\u00e8ve",
    "wof:name":"Norbert Apter Psychoth\u00e9rapie",
    "wof:placetype":"venue"
},
  "geometry": {"coordinates":[6.1469159126,46.2155914307],"type":"Point"}
}