{
  "type": "Feature",
  "properties": {
    "iso:country":"CH",
    "sg:address":"Bahnhofstrasse 108",
    "sg:city":"Uzwil",
    "sg:orig_category":"Non-Classified Establishments",
    "sg:postcode":"9240",
    "sg:province":"St. Gallen",
    "wof:name":"Per4m & Partner Ag",
    "wof:placetype":"venue"
},
  "geometry": {"coordinates":[9.1341590881,47.438369751],"type":"Point"}
}