{
  "type": "Feature",
  "properties": {
    "iso:country":"CH",
    "sg:address":"Subingenstrasse 274",
    "sg:city":"Horriwil",
    "sg:orig_category":"Fachdetailhandel in Verkaufsr\u00e4umen Handel mit Motorr\u00e4dern, Teilen U Zubeh\u00f6r Instandhaltung U Reparat",
    "sg:phone":"+41 32 614 37 26",
    "sg:postcode":"4557",
    "sg:province":"Solothurn",
    "wof:name":"J\u00e4ggi A.",
    "wof:placetype":"venue"
},
  "geometry": {"coordinates":[7.6173977852,47.1880607605],"type":"Point"}
}