{
  "type": "Feature",
  "properties": {
    "iso:country":"CH",
    "sg:address":"Z\u00fcrcherstrasse 8",
    "sg:city":"Unterengstringen",
    "sg:orig_category":"Herstellung von Konstruktionsteilen, Fertigbauteilen U Ausbauelementen aus Holz",
    "sg:postcode":"8103",
    "sg:province":"Z\u00fcrich",
    "wof:name":"Vojnovic Einbauprodukte",
    "wof:placetype":"venue"
},
  "geometry": {"coordinates":[8.4545326233,47.412147522],"type":"Point"}
}