{
  "type": "Feature",
  "properties": {
    "iso:country":"CH",
    "sg:address":"Bifang",
    "sg:city":"Engi",
    "sg:orig_category":"Forstwirtschaft ohne Dienstleistungen in der Forstwirtschaft",
    "sg:phone":"+41 55 642 22 21",
    "sg:postcode":"8765",
    "sg:province":"Glarus",
    "wof:name":"Rast Jakob, Forstbetrieb Und Beratungen",
    "wof:placetype":"venue"
},
  "geometry": {"coordinates":[9.1510381699,46.9860305786],"type":"Point"}
}