{
  "type": "Feature",
  "properties": {
    "iso:country":"CH",
    "sg:address":"Stampfenbachstrasse 72",
    "sg:city":"Z\u00fcrich",
    "sg:orig_category":"Detailhandel mit Blumen U Pflanzen",
    "sg:phone":"+41 13624277",
    "sg:postcode":"8006",
    "sg:province":"Z\u00fcrich",
    "wof:name":"Margaritha Kern Blumengesch\u00e4ft",
    "wof:placetype":"venue"
},
  "geometry": {"coordinates":[8.542046,47.381584],"type":"Point"}
}