{
  "type": "Feature",
  "properties": {
    "addr:full":"Talstrasse 5 Th\u00f6rishaus Bern 3174",
    "addr:housenumber":"5",
    "addr:postcode":"3174",
    "addr:street":"Talstrasse",
    "iso:country":"CH",
    "sg:address":"Talstrasse 5",
    "sg:city":"Th\u00f6rishaus",
    "sg:orig_category":"Blumen U Zierpflanzenbau",
    "sg:phone":"+41 31 889 02 74",
    "sg:postcode":"3174",
    "sg:province":"Bern",
    "wof:name":"Ulrich M\u00fcnger Gartenbau Blumeng\u00e4rtnerei",
    "wof:placetype":"venue"
},
  "geometry": {"coordinates":[7.350508,46.891602],"type":"Point"}
}