{
  "type": "Feature",
  "properties": {
    "iso:country":"CH",
    "sg:address":"Heub\u00e4chliring 1 6020 Emmenbr\u00fccke. Postfach",
    "sg:city":"Emmenbr\u00fccke",
    "sg:orig_category":"G\u00fcterbef\u00f6rderung im Strassenverkehr",
    "sg:postcode":"6020",
    "sg:province":"Luzern",
    "wof:name":"Schneeberger Transporte",
    "wof:placetype":"venue"
},
  "geometry": {"coordinates":[8.272892952,47.0826797485],"type":"Point"}
}