{
  "type": "Feature",
  "properties": {
    "iso:country":"CH",
    "sg:address":"Sackstrasse 18",
    "sg:city":"Wernetshausen",
    "sg:orig_category":"Herstellung von keramischen Wand U Bodenfliesen U platten Verlegen von Fliesen U Platten",
    "sg:phone":"+41 31 981 00 44",
    "sg:postcode":"8342",
    "sg:province":"Z\u00fcrich",
    "wof:name":"Haldemann Kurt",
    "wof:placetype":"venue"
},
  "geometry": {"coordinates":[7.372838974,46.9206466675],"type":"Point"}
}