{
  "type": "Feature",
  "properties": {
    "iso:country":"CH",
    "sg:address":"Horburgstrasse 54",
    "sg:city":"Basel",
    "sg:orig_category":"Physiotherapie",
    "sg:phone":"+41 17610578",
    "sg:postcode":"4057",
    "sg:province":"Basel-Stadt",
    "wof:name":"Eva Matousek Physiotherapie",
    "wof:placetype":"venue"
},
  "geometry": {"coordinates":[8.4504442215,47.2720870972],"type":"Point"}
}