{
  "type": "Feature",
  "properties": {
    "addr:full":"Allmannstrasse 18 Winterthur Z\u00fcrich 8400",
    "addr:housenumber":"18",
    "addr:postcode":"8400",
    "addr:street":"Allmannstrasse",
    "iso:country":"CH",
    "sg:address":"Allmannstrasse 18",
    "sg:city":"Winterthur",
    "sg:orig_category":"Detailhandel mit Computern U Software",
    "sg:phone":"+41 32 344 84 84",
    "sg:postcode":"8400",
    "sg:province":"Z\u00fcrich",
    "wof:name":"Top-d Computer Ag",
    "wof:placetype":"venue"
},
  "geometry": {"coordinates":[7.2835,47.16095],"type":"Point"}
}