{
  "type": "Feature",
  "properties": {
    "iso:country":"CH",
    "sg:address":"Hintere Grundstrasse 22",
    "sg:city":"Fehraltorf",
    "sg:classifiers":[
        {
            "category":"Organizations",
            "subcategory":"Professional Association",
            "type":"Services"
        }
    ],
    "sg:phone":"+41 19551288",
    "sg:postcode":"8320",
    "sg:province":"Z\u00fcrich",
    "sg:tags":[
        "consulting",
        "planning"
    ],
    "wof:name":"Kerod Planungen",
    "wof:placetype":"venue"
},
  "geometry": {"coordinates":[8.7583637238,47.3866119385],"type":"Point"}
}