{
  "type": "Feature",
  "properties": {
    "addr:full":"M\u00fchlebachstrasse 72 Z\u00fcrich Z\u00fcrich 8008",
    "addr:housenumber":"72",
    "addr:postcode":"8008",
    "addr:street":"Muehlebachstrasse",
    "iso:country":"CH",
    "sg:address":"M\u00fchlebachstrasse 72",
    "sg:city":"Z\u00fcrich",
    "sg:orig_category":"Detailhandel mit B\u00fcchern, Zeitungen, Schreib U Papeteriewaren",
    "sg:phone":"+41 12516286",
    "sg:postcode":"8008",
    "sg:province":"Z\u00fcrich",
    "wof:name":"Wisah Hotelwerbung Ag",
    "wof:placetype":"venue"
},
  "geometry": {"coordinates":[8.552887,47.362801],"type":"Point"}
}