{
  "type": "Feature",
  "properties": {
    "iso:country":"CH",
    "sg:address":"Pelli Via Ferruccio 7",
    "sg:city":"Lugano",
    "sg:orig_category":"Satzherstellung U Reproduktion",
    "sg:postcode":"6900",
    "sg:province":"Ticino",
    "wof:name":"Insane Bertolo, Muljana, Schwyter",
    "wof:placetype":"venue"
},
  "geometry": {"coordinates":[8.8208293915,47.3299255371],"type":"Point"}
}