{
  "type": "Feature",
  "properties": {
    "iso:country":"CH",
    "sg:address":"Combamare 10",
    "sg:city":"Gorgier",
    "sg:orig_category":"Gartenbau Landschaftsplanungsb\u00fcros U Gartenarchitekturb\u00fcros",
    "sg:phone":"+41 79 439 46 01",
    "sg:postcode":"2023",
    "sg:province":"Neuch\u00e2tel",
    "wof:name":"Verdon Mme - Fleurs.",
    "wof:placetype":"venue"
},
  "geometry": {"coordinates":[6.781701088,46.901386261],"type":"Point"}
}