{
  "type": "Feature",
  "properties": {
    "iso:country":"CH",
    "sg:address":"Rue Louis-favre 49",
    "sg:city":"Boudry",
    "sg:orig_category":"Einzelhandel mit Automobilteilen U Zubeh\u00f6r Grosshandel mit Radio U Fernsehger\u00e4ten",
    "sg:postcode":"2017",
    "sg:province":"Neuch\u00e2tel",
    "wof:name":"David Pinero Vibration Syst\u00e8me David Pinero",
    "wof:placetype":"venue"
},
  "geometry": {"coordinates":[6.8351812363,46.9486656189],"type":"Point"}
}