{
  "type": "Feature",
  "properties": {
    "iso:country":"CH",
    "sg:address":"Spitalgasse 35",
    "sg:city":"Bern",
    "sg:orig_category":"Spielsalons",
    "sg:phone":"+41 71 622 63 83",
    "sg:postcode":"3011",
    "sg:province":"Bern",
    "wof:name":"Spielsalon Atlantis",
    "wof:placetype":"venue"
},
  "geometry": {"coordinates":[9.1381845474,47.5666694641],"type":"Point"}
}