{
  "type": "Feature",
  "properties": {
    "iso:country":"CH",
    "sg:address":"Guggenb\u00fchlstrasse 140",
    "sg:city":"Winterthur",
    "sg:orig_category":"Vorschulen, Kinderg\u00e4rten",
    "sg:phone":"+41 52 242 05 20",
    "sg:postcode":"8404",
    "sg:province":"Z\u00fcrich",
    "wof:name":"Kindergarten Wallr\u00fcti",
    "wof:placetype":"venue"
},
  "geometry": {"coordinates":[8.7598142624,47.5178718567],"type":"Point"}
}