{
  "type": "Feature",
  "properties": {
    "iso:country":"CH",
    "sg:address":"2807",
    "sg:city":"Pleigne",
    "sg:orig_category":"Sportvereine Sch\u00fctzen",
    "sg:phone":"+41 32 967 65 11",
    "sg:postcode":"2807",
    "sg:province":"Jura",
    "wof:name":"St\u00e9 De Tir Police Locale C/o Police Locale",
    "wof:placetype":"venue"
},
  "geometry": {"coordinates":[6.8329558372,47.1031303406],"type":"Point"}
}