{
  "type": "Feature",
  "properties": {
    "iso:country":"CH",
    "sg:address":"M\u00fchlestrasse 14",
    "sg:city":"Grenchen",
    "sg:classifiers":[
        {
            "category":"Ferry Terminal",
            "type":"Transportation"
        }
    ],
    "sg:phone":"+41 32 655 82 82",
    "sg:postcode":"2540",
    "sg:province":"Solothurn",
    "sg:tags":[
        "oscillator"
    ],
    "wof:name":"Micro Crystal A Div. Of Eta Sa",
    "wof:placetype":"venue"
},
  "geometry": {"coordinates":[7.3938798904,47.1976547241],"type":"Point"}
}