{
  "type": "Feature",
  "properties": {
    "iso:country":"CH",
    "sg:address":"Dorfstrasse 7",
    "sg:city":"Zollbr\u00fcck",
    "sg:orig_category":"Detailhandel mit Brot, Back U S\u00fcsswaren",
    "sg:phone":"+41 34 496 73 70",
    "sg:postcode":"3436",
    "sg:province":"Bern",
    "wof:name":"Aeschlimann Gebr\u00fcder",
    "wof:placetype":"venue"
},
  "geometry": {"coordinates":[7.74454,46.974823],"type":"Point"}
}