{
  "type": "Feature",
  "properties": {
    "iso:country":"CH",
    "sg:address":"Engadinstrasse 44",
    "sg:city":"Chur",
    "sg:orig_category":"Interessenvertretungen",
    "sg:postcode":"7000",
    "sg:province":"Graubunden",
    "wof:name":"Menzi-jenny-getrud-stiftung",
    "wof:placetype":"venue"
},
  "geometry": {"coordinates":[9.5289154053,46.8494567871],"type":"Point"}
}