{
  "type": "Feature",
  "properties": {
    "iso:country":"CH",
    "sg:address":"Mahrenstrasse 154",
    "sg:city":"Lostorf",
    "sg:orig_category":"Herstellung von Konstruktionsteilen, Fertigbauteilen U Ausbauelementen aus Holz",
    "sg:phone":"+41 62 298 35 42",
    "sg:postcode":"4654",
    "sg:province":"Solothurn",
    "wof:name":"Schreinerei Meier Gmbh",
    "wof:placetype":"venue"
},
  "geometry": {"coordinates":[7.9144001007,47.3803977966],"type":"Point"}
}