{
  "type": "Feature",
  "properties": {
    "iso:country":"CH",
    "sg:address":"Klungelisei 6110 Wolhusen. Postfach",
    "sg:city":"Wolhusen",
    "sg:orig_category":"Herstellung von Elektromotoren, Generatoren U Transformatoren",
    "sg:postcode":"6110",
    "sg:province":"Luzern",
    "wof:name":"Planzer Metallbau Metallbauteile, Bes. Toranlagen; Herstellung, Montage",
    "wof:placetype":"venue"
},
  "geometry": {"coordinates":[8.0732545853,47.0589408875],"type":"Point"}
}