{
  "type": "Feature",
  "properties": {
    "iso:country":"CH",
    "sg:address":"Vogtackerweg 13",
    "sg:city":"Sissach",
    "sg:orig_category":"Malerei",
    "sg:phone":"+41 61 971 18 11",
    "sg:postcode":"4450",
    "sg:province":"Basel-Landschaft",
    "wof:name":"Thomas Kamber Malergesch\u00e4ft",
    "wof:placetype":"venue"
},
  "geometry": {"coordinates":[7.8126502037,47.4580688477],"type":"Point"}
}