{
  "type": "Feature",
  "properties": {
    "iso:country":"CH",
    "sg:address":"Sonnmattstrasse 23",
    "sg:city":"Rombach",
    "sg:orig_category":"Vereine Gesang",
    "sg:phone":"+41 62 827 06 13",
    "sg:postcode":"5022",
    "sg:province":"Aargau",
    "wof:name":"Stefan & Raffaella Blumer Reformierter Kirchenchor",
    "wof:placetype":"venue"
},
  "geometry": {"coordinates":[8.0518093109,47.4092025757],"type":"Point"}
}