{
  "type": "Feature",
  "properties": {
    "iso:country":"CH",
    "sg:address":"Rampe De La Gare 2 / Cp 127",
    "sg:city":"Versoix",
    "sg:classifiers":[
        {
            "category":"Banks & Credit Unions",
            "subcategory":"Bank",
            "type":"Services"
        }
    ],
    "sg:phone":"+41 22 755 15 85",
    "sg:postcode":"1290",
    "sg:province":"Gen\u00e8ve",
    "wof:name":"Union De Banques Suisses",
    "wof:placetype":"venue"
},
  "geometry": {"coordinates":[6.16752,46.279415],"type":"Point"}
}