{
  "type": "Feature",
  "properties": {
    "iso:country":"CH",
    "sg:address":"Place Du Grand-m\u00e9zel 3",
    "sg:city":"Gen\u00e8ve",
    "sg:orig_category":"Herstellung U Zusammensetzung von Uhren Herstellung der Ausstattung von Uhren",
    "sg:postcode":"1204",
    "sg:province":"Gen\u00e8ve",
    "wof:name":"Maspoli Sa Fabrique De Bracelets",
    "wof:placetype":"venue"
},
  "geometry": {"coordinates":[6.9327859879,46.3916435242],"type":"Point"}
}