{
  "type": "Feature",
  "properties": {
    "iso:country":"CH",
    "sg:address":"Bahnhofstrasse 45",
    "sg:city":"Frauenfeld",
    "sg:orig_category":"Herstellung von Elektromotoren, Generatoren U Transformatoren",
    "sg:phone":"+41 79 623 30 00",
    "sg:postcode":"8500",
    "sg:province":"Thurgau",
    "wof:name":"Enumplan Ag F\u00fcr Energie Und Umweltplanung",
    "wof:placetype":"venue"
},
  "geometry": {"coordinates":[8.890958786,47.5550842285],"type":"Point"}
}