{
  "type": "Feature",
  "properties": {
    "iso:country":"CH",
    "sg:address":"Schauenburgerstrasse 26",
    "sg:city":"Basel",
    "sg:orig_category":"G\u00fcterbef\u00f6rderung im Strassenverkehr",
    "sg:phone":"+41 61 312 40 02",
    "sg:postcode":"4052",
    "sg:province":"Basel-Stadt",
    "wof:name":"Hypa Papezik",
    "wof:placetype":"venue"
},
  "geometry": {"coordinates":[7.6099801064,47.5544776917],"type":"Point"}
}