{
  "type": "Feature",
  "properties": {
    "iso:country":"CH",
    "sg:address":"Rue Du Criblet 10",
    "sg:city":"Fribourg",
    "sg:orig_category":"Herstellung von sonstiger Bekleidung U Bekleidungszubeh\u00f6r",
    "sg:postcode":"1700",
    "sg:province":"Fribourg",
    "wof:name":"Sch\u00f6ni Marguerite.",
    "wof:placetype":"venue"
},
  "geometry": {"coordinates":[7.1533927917,46.8051261902],"type":"Point"}
}