{
  "type": "Feature",
  "properties": {
    "iso:country":"CH",
    "sg:address":"Kirchrain 3",
    "sg:city":"Kaisten",
    "sg:orig_category":"Gem\u00fcsebau Herstellung von Nahrungsmitteln undGetr\u00e4nken",
    "sg:phone":"+41 62 874 23 01",
    "sg:postcode":"5082",
    "sg:province":"Aargau",
    "wof:name":"Kurt Meier Champignon-z\u00fcchterei",
    "wof:placetype":"venue"
},
  "geometry": {"coordinates":[8.0452222824,47.5403404236],"type":"Point"}
}