{
  "type": "Feature",
  "properties": {
    "iso:country":"CH",
    "sg:address":"Industriestr. 4",
    "sg:city":"Romanshorn",
    "sg:classifiers":[
        {
            "category":"Manufacturing",
            "subcategory":"Tools & Machinery",
            "type":"Manufacturing & Wholesale Goods"
        }
    ],
    "sg:phone":"+41 71 466 41 00",
    "sg:postcode":"8590",
    "sg:province":"Thurgau",
    "sg:tags":[
        "equipment",
        "measurement",
        "-",
        "precision",
        "instrument"
    ],
    "wof:name":"Rinco Ultrasonics Ag",
    "wof:placetype":"venue"
},
  "geometry": {"coordinates":[9.3683462143,47.5567550659],"type":"Point"}
}