{
  "type": "Feature",
  "properties": {
    "iso:country":"CH",
    "sg:address":"1134",
    "sg:city":"Chigny",
    "sg:orig_category":"Non-Classified Establishments",
    "sg:postcode":"1134",
    "sg:province":"Vaud",
    "wof:name":"Inter-lack, Didier Weibel",
    "wof:placetype":"venue"
},
  "geometry": {"coordinates":[7.5275640488,47.0201683044],"type":"Point"}
}