{
  "type": "Feature",
  "properties": {
    "iso:country":"CH",
    "sg:address":"Tramweg 39",
    "sg:city":"Arth",
    "sg:orig_category":"Erschliessung von Grundst\u00fccken",
    "sg:postcode":"6415",
    "sg:province":"Schwyz",
    "wof:name":"Baugenossenschaft Daheim",
    "wof:placetype":"venue"
},
  "geometry": {"coordinates":[8.5263795853,47.0631217957],"type":"Point"}
}