{
  "type": "Feature",
  "properties": {
    "iso:country":"CH",
    "sg:address":"Badenerstrasse 790",
    "sg:city":"Z\u00fcrich",
    "sg:orig_category":"Herstellung von k\u00e4lte U lufttechnischen Erzeugnissen f\u00fcr gewerbliche Zwecke",
    "sg:postcode":"8048",
    "sg:province":"Z\u00fcrich",
    "wof:name":"Fl\u00e4kt Woods Group Ag",
    "wof:placetype":"venue"
},
  "geometry": {"coordinates":[8.4765510559,47.3925323486],"type":"Point"}
}