{
  "type": "Feature",
  "properties": {
    "iso:country":"CH",
    "sg:address":"Ammerswilerstrasse 36 5600 Lenzburg. Postfach",
    "sg:city":"Lenzburg",
    "sg:orig_category":"Architektur U Ingenieurb\u00fcros",
    "sg:phone":"+41 61 401 26 55",
    "sg:postcode":"5600",
    "sg:province":"Aargau",
    "wof:name":"Hsa Bauberatung Gmbh Bauprojekte; Beratung, Planung, Realisierung Usw",
    "wof:placetype":"venue"
},
  "geometry": {"coordinates":[7.552776,47.514702],"type":"Point"}
}