{
  "type": "Feature",
  "properties": {
    "iso:country":"CH",
    "sg:address":"G\u00fcterstrasse 6",
    "sg:city":"Egerkingen",
    "sg:orig_category":"Unclassifiable Establishments",
    "sg:postcode":"4622",
    "sg:province":"Solothurn",
    "wof:name":"Erich Von Arx Ing. B\u00fcro F\u00fcr Automation",
    "wof:placetype":"venue"
},
  "geometry": {"coordinates":[7.7984480858,47.3149223328],"type":"Point"}
}