{
  "type": "Feature",
  "properties": {
    "iso:country":"CH",
    "sg:address":"Altes Schulhaus 9555 Tobel. Postfach",
    "sg:city":"Tobel",
    "sg:orig_category":"Fachdetailhandel in Verkaufsr\u00e4umen",
    "sg:postcode":"9555",
    "sg:province":"Thurgau",
    "wof:name":"Dog Dog Hundefutter Heusser S. Hunde- U. Katzenfutter; Handel",
    "wof:placetype":"venue"
},
  "geometry": {"coordinates":[9.0303897858,47.5119667053],"type":"Point"}
}