{
  "type": "Feature",
  "properties": {
    "iso:country":"CH",
    "sg:address":"Pr\u00e9-bois Route De 20 1217 Meyrin Case Postale",
    "sg:city":"Meyrin",
    "sg:orig_category":"Dienstleistungen von Beteiligungsgesellschaften",
    "sg:phone":"+41 22 918 55 62",
    "sg:postcode":"1217",
    "sg:province":"Gen\u00e8ve",
    "wof:name":"Acierco Sa, Luxembourg, Succursale De Meyrin",
    "wof:placetype":"venue"
},
  "geometry": {"coordinates":[6.0722160339,46.2284431458],"type":"Point"}
}