{
  "type": "Feature",
  "properties": {
    "iso:country":"CH",
    "sg:address":"Kirchweg 8",
    "sg:city":"Horw",
    "sg:orig_category":"Sonstiger Fachdetailhandel mit Nahrungsmitteln, Getr\u00e4nken U Tabak in Verkaufsr\u00e4umen",
    "sg:phone":"+41 26 419 10 88",
    "sg:postcode":"6048",
    "sg:province":"Luzern",
    "wof:name":"Lauber Elisabeth",
    "wof:placetype":"venue"
},
  "geometry": {"coordinates":[8.3122587204,47.0197181702],"type":"Point"}
}