{
  "type": "Feature",
  "properties": {
    "iso:country":"CH",
    "sg:address":"Robert Durrer-strasse 22",
    "sg:city":"Stans",
    "sg:orig_category":"Grosshandel mit Nahrungsmitteln, Getr\u00e4nken U Tabakwaren ohne ausgepr\u00e4gten Schwerpunkt",
    "sg:phone":"+41 41 619 20 50",
    "sg:postcode":"6370",
    "sg:province":"Nidwalden",
    "wof:name":"Ruedi Schoch Ag",
    "wof:placetype":"venue"
},
  "geometry": {"coordinates":[8.3648881912,46.9604110718],"type":"Point"}
}