{
  "type": "Feature",
  "properties": {
    "iso:country":"CH",
    "sg:address":"Rue Des Remparts 18 1400 Yverdon-les-bains. Postfach",
    "sg:city":"Yverdon-les-bains",
    "sg:orig_category":"Grosshandel mit Getreide, Saatgut U Futtermitteln",
    "sg:phone":"+41 24 425 24 50",
    "sg:postcode":"1400",
    "sg:province":"Vaud",
    "wof:name":"Biovet Mc Sa",
    "wof:placetype":"venue"
},
  "geometry": {"coordinates":[6.639731884,46.780002594],"type":"Point"}
}