{
  "type": "Feature",
  "properties": {
    "iso:country":"CH",
    "sg:address":"Schwerzenbachstrasse 7",
    "sg:city":"F\u00e4llanden",
    "sg:classifiers":[
        {
            "category":"Insurance",
            "subcategory":"Insurance Agent",
            "type":"Services"
        }
    ],
    "sg:phone":"+41 79 404 08 15",
    "sg:postcode":"8117",
    "sg:province":"Z\u00fcrich",
    "sg:tags":[
        "versicherungsagenturen",
        "-broker"
    ],
    "wof:name":"Die Mobiliar Versicherungen & Vorsorge",
    "wof:placetype":"venue"
},
  "geometry": {"coordinates":[8.6395215988,47.3712921143],"type":"Point"}
}