{
  "type": "Feature",
  "properties": {
    "iso:country":"CH",
    "sg:address":"Rheinstrasse 1",
    "sg:city":"Widnau",
    "sg:orig_category":"Detailhandel mit Radio U Fernsehger\u00e4ten Fachdetailhandel in Verkaufsr\u00e4umen",
    "sg:phone":"+41 56 426 27 03",
    "sg:postcode":"9443",
    "sg:province":"St. Gallen",
    "wof:name":"Foto-radio Schiebler",
    "wof:placetype":"venue"
},
  "geometry": {"coordinates":[8.3286600113,47.4651222229],"type":"Point"}
}