{
  "type": "Feature",
  "properties": {
    "addr:full":"Artherstrasse 61a Walchwil Zug 6318",
    "addr:housenumber":"61a",
    "addr:postcode":"6318",
    "addr:street":"Artherstrasse;Zug",
    "iso:country":"CH",
    "sg:address":"Artherstrasse 61a",
    "sg:city":"Walchwil",
    "sg:orig_category":"Autogaragen",
    "sg:phone":"+41 41 758 14 72",
    "sg:postcode":"6318",
    "sg:province":"Zug",
    "wof:name":"Garage St. Adrian Gmbh",
    "wof:placetype":"venue"
},
  "geometry": {"coordinates":[8.522936,47.089958],"type":"Point"}
}