{
  "type": "Feature",
  "properties": {
    "iso:country":"CH",
    "sg:address":"Clochettes Chemin Des 18 1206 Gen\u00e8ve. Postfach",
    "sg:city":"Gen\u00e8ve",
    "sg:orig_category":"Grosshandel mit Getr\u00e4nken",
    "sg:phone":"+41 22 738 39 89",
    "sg:postcode":"1206",
    "sg:province":"Gen\u00e8ve",
    "wof:name":"Arrabit Jean-louis.",
    "wof:placetype":"venue"
},
  "geometry": {"coordinates":[6.1588988304,46.1888008118],"type":"Point"}
}