{
  "type": "Feature",
  "properties": {
    "iso:country":"CH",
    "sg:address":"Rue Maurice-braillard 36 1200 Gen\u00e8ve. Postfach",
    "sg:city":"Gen\u00e8ve",
    "sg:orig_category":"Interessenvertretungen",
    "sg:postcode":"1202",
    "sg:province":"Gen\u00e8ve",
    "wof:name":"Association La Voie De La Libert\u00e9",
    "wof:placetype":"venue"
},
  "geometry": {"coordinates":[6.1300301552,46.2209815979],"type":"Point"}
}