{
  "type": "Feature",
  "properties": {
    "addr:full":"Postgasse 3 Felsberg Graubunden 7012",
    "addr:housenumber":"3",
    "addr:postcode":"7012",
    "addr:street":"Postgasse",
    "iso:country":"CH",
    "sg:address":"Postgasse 3",
    "sg:city":"Felsberg",
    "sg:orig_category":"Allgemeiner Gartenbau",
    "sg:phone":"+41 81 252 20 06",
    "sg:postcode":"7012",
    "sg:province":"Graubunden",
    "wof:name":"Trudi Danuser Forstbaumschulen",
    "wof:placetype":"venue"
},
  "geometry": {"coordinates":[9.480714,46.845074],"type":"Point"}
}