{
  "type": "Feature",
  "properties": {
    "iso:country":"CH",
    "sg:address":"Rue Basse 8",
    "sg:city":"St-imier",
    "sg:orig_category":"Herstellung von Reiseartikeln, Leder U Sattlerwaren",
    "sg:phone":"+41 32 941 43 77",
    "sg:postcode":"2610",
    "sg:province":"Bern",
    "wof:name":"Andr\u00e9 Moser Sellerie",
    "wof:placetype":"venue"
},
  "geometry": {"coordinates":[6.9976639748,47.1521492004],"type":"Point"}
}