{
  "type": "Feature",
  "properties": {
    "iso:country":"CH",
    "sg:address":"L\u00f6wenstein 12",
    "sg:city":"Neuhausen",
    "sg:orig_category":"Kauf U Verkauf von Immobilien auf eigene Rechnung Vermittlung von Immobilien",
    "sg:phone":"+41 52 632 04 06",
    "sg:postcode":"8212",
    "sg:province":"Schaffhausen",
    "wof:name":"Wideco Ag",
    "wof:placetype":"venue"
},
  "geometry": {"coordinates":[8.6205005646,47.6937942505],"type":"Point"}
}