{
  "type": "Feature",
  "properties": {
    "iso:country":"CH",
    "sg:address":"Sch\u00fctzenstrasse 43",
    "sg:city":"Bellikon",
    "sg:orig_category":"Fahrschulen, Flugschulen",
    "sg:phone":"+41 79 467 16 85",
    "sg:postcode":"5454",
    "sg:province":"Aargau",
    "wof:name":"Ruedi Hediger Autofahrschule",
    "wof:placetype":"venue"
},
  "geometry": {"coordinates":[8.3470535278,47.3909797668],"type":"Point"}
}