{
  "type": "Feature",
  "properties": {
    "iso:country":"CH",
    "sg:address":"Franklinstrasse 27",
    "sg:city":"Z\u00fcrich",
    "sg:orig_category":"Detailhandel mit Geschenkartikeln U Souvenirs Parf\u00fcmerien U sonstiger Detailhandel mit kosmetischen ",
    "sg:phone":"+41 13130721",
    "sg:postcode":"8050",
    "sg:province":"Z\u00fcrich",
    "wof:name":"Simba Shop Geschenke Dekorationen D\u00fcfte",
    "wof:placetype":"venue"
},
  "geometry": {"coordinates":[8.5434818268,47.4096870422],"type":"Point"}
}