{
  "type": "Feature",
  "properties": {
    "iso:country":"CH",
    "sg:address":"Via Tasso 8",
    "sg:city":"Lugano",
    "sg:orig_category":"Non-Classified Establishments",
    "sg:postcode":"6900",
    "sg:province":"Ticino",
    "wof:name":"Conservatorio Della Svizzera Italiana",
    "wof:placetype":"venue"
},
  "geometry": {"coordinates":[8.9485607147,46.0028800964],"type":"Point"}
}