{
  "type": "Feature",
  "properties": {
    "iso:country":"CH",
    "sg:address":"Rue De L'ecole-de-m\u00e9decine 7 7",
    "sg:city":"Genf",
    "sg:orig_category":"Unclassifiable Establishments",
    "sg:postcode":"1200",
    "sg:province":"Gen\u00e8ve",
    "wof:name":"Fondation Caduc\u00e9e Pour La Promotion De La Sant\u00e9",
    "wof:placetype":"venue"
},
  "geometry": {"coordinates":[6.1387410164,46.197353363],"type":"Point"}
}