{
  "type": "Feature",
  "properties": {
    "iso:country":"CH",
    "sg:address":"Via Cartiera",
    "sg:city":"Tenero",
    "sg:classifiers":[
        {
            "category":"Professional",
            "subcategory":"Printing & Photocopies",
            "type":"Services"
        }
    ],
    "sg:phone":"+41 91 735 65 65",
    "sg:postcode":"6598",
    "sg:province":"Ticino",
    "sg:tags":[
        "paper"
    ],
    "wof:name":"Cartiera Cham Tenero Sa",
    "wof:placetype":"venue"
},
  "geometry": {"coordinates":[8.8523750305,46.1769790649],"type":"Point"}
}