{
  "type": "Feature",
  "properties": {
    "iso:country":"CH",
    "sg:address":"Industrieweg 1",
    "sg:city":"Oberg\u00f6sgen",
    "sg:orig_category":"Mechanische Werkst\u00e4tten",
    "sg:phone":"+41 62 295 35 12",
    "sg:postcode":"4653",
    "sg:province":"Solothurn",
    "wof:name":"Bruno Eng Mechanische Werkstatt",
    "wof:placetype":"venue"
},
  "geometry": {"coordinates":[7.9582371712,47.3566169739],"type":"Point"}
}