{
  "type": "Feature",
  "properties": {
    "iso:country":"CH",
    "sg:address":"Chauderon Place 18",
    "sg:city":"Lausanne",
    "sg:orig_category":"Finanzierungsinstitutionen",
    "sg:postcode":"1003",
    "sg:province":"Vaud",
    "wof:name":"Montano + Palermo",
    "wof:placetype":"venue"
},
  "geometry": {"coordinates":[7.5224552155,47.1706314087],"type":"Point"}
}