{
  "type": "Feature",
  "properties": {
    "iso:country":"CH",
    "sg:address":"Tannenweg 3",
    "sg:city":"Derendingen",
    "sg:orig_category":"Allgemeiner Hoch U Tiefbau Architekturb\u00fcros",
    "sg:phone":"+41 19371793",
    "sg:postcode":"4552",
    "sg:province":"Solothurn",
    "wof:name":"H\u00f6sli Bauberatungen Gmbh",
    "wof:placetype":"venue"
},
  "geometry": {"coordinates":[8.843153,47.297501],"type":"Point"}
}