{
  "type": "Feature",
  "properties": {
    "iso:country":"CH",
    "sg:address":"Landstrasse 121",
    "sg:city":"Wettingen",
    "sg:orig_category":"Benzin, Heiz\u00f6l and Mineral\u00f6lprodukte Grosshandel Tankstellen",
    "sg:phone":"+41 56 427 27 48",
    "sg:postcode":"5430",
    "sg:province":"Aargau",
    "wof:name":"Agip (suisse) Sa",
    "wof:placetype":"venue"
},
  "geometry": {"coordinates":[8.3305454254,47.4641113281],"type":"Point"}
}