{
  "type": "Feature",
  "properties": {
    "iso:country":"CH",
    "sg:address":"Siggenthaler Str. 16",
    "sg:city":"W\u00fcrenlingen",
    "sg:classifiers":[
        {
            "category":"Home & Garden",
            "subcategory":"Furniture",
            "type":"Retail Goods"
        }
    ],
    "sg:phone":"+41 56 281 24 74",
    "sg:postcode":"5303",
    "sg:province":"Aargau",
    "sg:tags":[
        "wood"
    ],
    "wof:name":"J. Kalt Ag M\u00d6belfabrikation",
    "wof:placetype":"venue"
},
  "geometry": {"coordinates":[8.2484102249,47.5265159607],"type":"Point"}
}