{
  "type": "Feature",
  "properties": {
    "iso:country":"CH",
    "sg:address":"Lyssachstrasse 118 3400 Burgdorf. Postfach",
    "sg:city":"Burgdorf",
    "sg:orig_category":"Handel mit Automobilen",
    "sg:phone":"+41 32 752 48 00",
    "sg:postcode":"3402",
    "sg:province":"Bern",
    "wof:name":"Cc Cars Consulting Sa V\u00e9hicules \u00e0 Moteur; Comm., Import-export Etc",
    "wof:placetype":"venue"
},
  "geometry": {"coordinates":[7.0641651154,47.0518341064],"type":"Point"}
}