{
  "type": "Feature",
  "properties": {
    "iso:country":"CH",
    "sg:address":"R\u00e9sidence Eden",
    "sg:city":"Anz\u00e8re",
    "sg:orig_category":"Wirtschaftspr\u00fcfung, Steuerberatung U Treuhand",
    "sg:phone":"+41 27 398 17 37",
    "sg:postcode":"1972",
    "sg:province":"Valais",
    "wof:name":"Soci\u00e9t\u00e9 Fiduciaire Conseils Et G\u00e9rance Sa",
    "wof:placetype":"venue"
},
  "geometry": {"coordinates":[7.4004211426,46.2969818115],"type":"Point"}
}