{
  "type": "Feature",
  "properties": {
    "iso:country":"CH",
    "sg:address":"In Der Rebhalden 17",
    "sg:city":"Urdorf",
    "sg:orig_category":"Elektroinstallation",
    "sg:postcode":"8902",
    "sg:province":"Z\u00fcrich",
    "wof:name":"Obras Electromecanicas Tisch Tkv",
    "wof:placetype":"venue"
},
  "geometry": {"coordinates":[8.4344367981,47.3859825134],"type":"Point"}
}