{
  "type": "Feature",
  "properties": {
    "addr:full":"1837 Ch\u00e2teau-d'oex 1837",
    "addr:housenumber":"1837;1837",
    "addr:street":"Cha\u0302Teau-D ' Oex",
    "iso:country":"CH",
    "sg:address":"1837",
    "sg:city":"Ch\u00e2teau-d'oex",
    "sg:classifiers":[
        {
            "category":"Education",
            "subcategory":"Library",
            "type":"Public Place"
        }
    ],
    "sg:postcode":"1837",
    "sg:tags":[
        "u",
        "bibliotheken",
        "archive"
    ],
    "wof:name":"Biblioth\u00e8que De L'ibm",
    "wof:placetype":"venue"
},
  "geometry": {"coordinates":[6.13521,46.219627],"type":"Point"}
}