{
  "type": "Feature",
  "properties": {
    "iso:country":"CH",
    "sg:address":"Rue D'octodure 10b",
    "sg:city":"Martigny",
    "sg:orig_category":"F\u00fcrsorge\u00e4mter",
    "sg:phone":"+41 27 721 26 80",
    "sg:postcode":"1920",
    "sg:province":"Valais",
    "wof:name":"Administration Communale Service Social",
    "wof:placetype":"venue"
},
  "geometry": {"coordinates":[7.0732851028,46.1036491394],"type":"Point"}
}