{
  "type": "Feature",
  "properties": {
    "iso:country":"CH",
    "sg:address":"Simmentalstrasse 28",
    "sg:city":"Wimmis",
    "sg:orig_category":"Fachdetailhandel in Verkaufsr\u00e4umen",
    "sg:postcode":"3752",
    "sg:province":"Bern",
    "wof:name":"Schifflechner Gleitschirme",
    "wof:placetype":"venue"
},
  "geometry": {"coordinates":[7.6310009956,46.6806488037],"type":"Point"}
}