{
  "type": "Feature",
  "properties": {
    "iso:country":"CH",
    "sg:address":"Erlenstrasse 11 8408 Winterthur. Postfach",
    "sg:city":"Winterthur",
    "sg:orig_category":"Gesundheitswesen",
    "sg:phone":"+41 52 222 17 11",
    "sg:postcode":"8408",
    "sg:province":"Z\u00fcrich",
    "wof:name":"Cura Sana Merz-winkler Christina",
    "wof:placetype":"venue"
},
  "geometry": {"coordinates":[8.701002121,47.5078544617],"type":"Point"}
}