{
  "type": "Feature",
  "properties": {
    "iso:country":"CH",
    "sg:address":"Karl-stamm-weg 2 8820 W\u00e4denswil. Postfach",
    "sg:city":"W\u00e4denswil",
    "sg:orig_category":"Unclassifiable Establishments",
    "sg:postcode":"8820",
    "sg:province":"Z\u00fcrich",
    "wof:name":"Siebke-siffert.",
    "wof:placetype":"venue"
},
  "geometry": {"coordinates":[7.2485480309,46.8556518555],"type":"Point"}
}