{
  "type": "Feature",
  "properties": {
    "iso:country":"CH",
    "sg:address":"Rue De La C\u00f4te 3",
    "sg:city":"Tavannes",
    "sg:orig_category":"Allgemeiner Hoch U Tiefbau",
    "sg:phone":"+41 32 481 23 93",
    "sg:postcode":"2710",
    "sg:province":"Bern",
    "wof:name":"Pozzoli S.",
    "wof:placetype":"venue"
},
  "geometry": {"coordinates":[7.205855,47.220692],"type":"Point"}
}