{
  "type": "Feature",
  "properties": {
    "iso:country":"CH",
    "sg:address":"Schwalbenweg 2",
    "sg:city":"Hilterfingen",
    "sg:orig_category":"Wirtschafts- and Arbeitgeberverb\u00e4nde",
    "sg:postcode":"3652",
    "sg:province":"Bern",
    "wof:name":"Schreinermeisterverband Thun & Umgebung",
    "wof:placetype":"venue"
},
  "geometry": {"coordinates":[7.6595320702,46.7415122986],"type":"Point"}
}