{
  "type": "Feature",
  "properties": {
    "iso:country":"CH",
    "sg:address":"Graben 31",
    "sg:city":"Aarau",
    "sg:orig_category":"Parf\u00fcmerien U sonstiger Detailhandel mit kosmetischen Artikeln U K\u00f6rperpflegemitteln",
    "sg:phone":"+41 81 771 11 39",
    "sg:postcode":"5000",
    "sg:province":"Aargau",
    "wof:name":"Alrodo Ag",
    "wof:placetype":"venue"
},
  "geometry": {"coordinates":[9.496723175,47.2124633789],"type":"Point"}
}