{
  "type": "Feature",
  "properties": {
    "iso:country":"CH",
    "sg:address":"Freilagerstrasse 9 + 11",
    "sg:city":"Z\u00fcrich",
    "sg:orig_category":"Herstellung von Konstruktionsteilen, Fertigbauteilen U Ausbauelementen aus Holz",
    "sg:postcode":"8047",
    "sg:province":"Z\u00fcrich",
    "wof:name":"Ega, Gagliardi E.",
    "wof:placetype":"venue"
},
  "geometry": {"coordinates":[8.4924373627,47.3782043457],"type":"Point"}
}