{
  "type": "Feature",
  "properties": {
    "iso:country":"CH",
    "sg:address":"Hauptstr. 51",
    "sg:city":"Berg",
    "sg:classifiers":[
        {
            "category":"Banks & Credit Unions",
            "subcategory":"Bank",
            "type":"Services"
        }
    ],
    "sg:phone":"+41 81 641 23 21",
    "sg:postcode":"8572",
    "sg:province":"Thurgau",
    "wof:name":"Raiffeisenbank Bonaduz",
    "wof:placetype":"venue"
},
  "geometry": {"coordinates":[9.39998,46.811337],"type":"Point"}
}