{
  "type": "Feature",
  "properties": {
    "iso:country":"CH",
    "sg:address":"Gellertstrasse 18 4000 Basel. Postfach",
    "sg:city":"Basel",
    "sg:orig_category":"Pensionskassen",
    "sg:postcode":"4052",
    "sg:province":"Basel-Stadt",
    "wof:name":"Hauser Personalf\u00fcrsorgestiftung",
    "wof:placetype":"venue"
},
  "geometry": {"coordinates":[8.7683649063,47.3047981262],"type":"Point"}
}