{
  "type": "Feature",
  "properties": {
    "iso:country":"CH",
    "sg:address":"Deucherstrasse 36",
    "sg:city":"Weinfelden",
    "sg:classifiers":[
        {
            "category":"Shopping",
            "subcategory":"Clothing, Apparel, & Fashions",
            "type":"Retail Goods"
        }
    ],
    "sg:phone":"+41 71 622 32 32",
    "sg:postcode":"8570",
    "sg:province":"Thurgau",
    "sg:tags":[
        "hanger",
        "clothes"
    ],
    "wof:name":"Sturo Ag",
    "wof:placetype":"venue"
},
  "geometry": {"coordinates":[9.12182,47.562244],"type":"Point"}
}