{
  "type": "Feature",
  "properties": {
    "addr:full":"Thunstrasse 60 Hasle-r\u00fcegsau Bern 3415",
    "addr:housenumber":"60",
    "addr:postcode":"3415",
    "addr:street":"Thunstrasse",
    "iso:country":"CH",
    "sg:address":"Thunstrasse 60",
    "sg:city":"Hasle-r\u00fcegsau",
    "sg:classifiers":[
        {
            "category":"Bars & Pubs",
            "type":"Food & Drink"
        }
    ],
    "sg:phone":"+41 34 461 07 08",
    "sg:postcode":"3415",
    "sg:province":"Bern",
    "wof:name":"Bar Zum Ch\u00fcele Fass",
    "wof:placetype":"venue"
},
  "geometry": {"coordinates":[7.655874,46.994736],"type":"Point"}
}