{
  "type": "Feature",
  "properties": {
    "iso:country":"CH",
    "sg:address":"Neugutstrasse 49",
    "sg:city":"D\u00fcbendorf",
    "sg:orig_category":"Sportvereine Sch\u00fctzen Armbrust",
    "sg:phone":"+41 18215784",
    "sg:postcode":"8600",
    "sg:province":"Z\u00fcrich",
    "wof:name":"Armbrustsch\u00fctzen.d\u00fcbendorf",
    "wof:placetype":"venue"
},
  "geometry": {"coordinates":[8.6092147827,47.3994865417],"type":"Point"}
}