{
  "type": "Feature",
  "properties": {
    "iso:country":"CH",
    "sg:address":"M\u00fchlegasse 23",
    "sg:city":"Gerlafingen",
    "sg:classifiers":[
        {
            "category":"Restaurant",
            "type":"Food & Drink"
        }
    ],
    "sg:phone":"+41 32 675 43 43",
    "sg:postcode":"4563",
    "sg:province":"Solothurn",
    "wof:name":"Pizzeria Boccia",
    "wof:placetype":"venue"
},
  "geometry": {"coordinates":[7.5729007721,47.1696586609],"type":"Point"}
}