{
  "type": "Feature",
  "properties": {
    "iso:country":"CH",
    "sg:address":"Wiesentalstrasse 54",
    "sg:city":"Chur",
    "sg:orig_category":"Unclassifiable Establishments",
    "sg:postcode":"7000",
    "sg:province":"Graubunden",
    "wof:name":"Reina Outdoor Gmbh",
    "wof:placetype":"venue"
},
  "geometry": {"coordinates":[9.5314998627,46.8586502075],"type":"Point"}
}