{
  "type": "Feature",
  "properties": {
    "iso:country":"CH",
    "sg:address":"Route Du Signal 21",
    "sg:city":"Lausanne",
    "sg:orig_category":"Bauingenieurb\u00fcros Eisenbetonbau Bauingenieurb\u00fcros allgemein",
    "sg:phone":"+41 71 223 13 21",
    "sg:postcode":"1018",
    "sg:province":"Vaud",
    "wof:name":"Bkm Ingenieure Ag St. Gallen",
    "wof:placetype":"venue"
},
  "geometry": {"coordinates":[9.375883,47.41938],"type":"Point"}
}