{
  "type": "Feature",
  "properties": {
    "iso:country":"CH",
    "sg:address":"Alte Tannerstrasse",
    "sg:city":"Tann",
    "sg:orig_category":"Architektur U Ingenieurb\u00fcros Vermittlung von Immobilien",
    "sg:phone":"+41 55 251 52 00",
    "sg:postcode":"8632",
    "sg:province":"Z\u00fcrich",
    "wof:name":"Inova Partner Ag",
    "wof:placetype":"venue"
},
  "geometry": {"coordinates":[8.851474,47.269058],"type":"Point"}
}