{
  "type": "Feature",
  "properties": {
    "iso:country":"CH",
    "sg:address":"Rue Des Vaudr\u00e8s 7",
    "sg:city":"Clarens",
    "sg:orig_category":"Relocation Management Services",
    "sg:phone":"+41 79 509 89 67",
    "sg:postcode":"1815",
    "sg:province":"Vaud",
    "wof:name":"Rapid'dem",
    "wof:placetype":"venue"
},
  "geometry": {"coordinates":[6.8899049759,46.443107605],"type":"Point"}
}