{
  "type": "Feature",
  "properties": {
    "addr:full":"Place De La Gare 2 Sierre Valais 3960",
    "addr:housenumber":"2",
    "addr:postcode":"3960",
    "addr:street":"Place De La Gare",
    "iso:country":"CH",
    "sg:address":"Place De La Gare 2",
    "sg:city":"Sierre",
    "sg:orig_category":"Detailhandel mit Bekleidung Detailhandel mit Damenbekleidung",
    "sg:phone":"+41 27 455 18 83",
    "sg:postcode":"3960",
    "sg:province":"Valais",
    "wof:name":"M'habit Mabillard Gaby.",
    "wof:placetype":"venue"
},
  "geometry": {"coordinates":[7.532519,46.292732],"type":"Point"}
}