{
  "type": "Feature",
  "properties": {
    "iso:country":"CH",
    "sg:address":"Baarerstrasse 59",
    "sg:city":"Zug",
    "sg:orig_category":"Unclassifiable Establishments",
    "sg:postcode":"6300",
    "sg:province":"Zug",
    "wof:name":"Contrain Gmbh",
    "wof:placetype":"venue"
},
  "geometry": {"coordinates":[7.555850029,47.5172157288],"type":"Point"}
}