{
  "type": "Feature",
  "properties": {
    "iso:country":"CH",
    "sg:address":"B\u00f6sch 106",
    "sg:city":"H\u00fcnenberg",
    "sg:orig_category":"Herstellung von medizinischen U chirurgischen Ger\u00e4ten sowie orthop\u00e4dischen Vorrichtungen",
    "sg:phone":"+41 41 781 13 30",
    "sg:postcode":"6331",
    "sg:province":"Zug",
    "wof:name":"Meditech Ag",
    "wof:placetype":"venue"
},
  "geometry": {"coordinates":[8.4337129593,47.1614151001],"type":"Point"}
}