{
  "type": "Feature",
  "properties": {
    "iso:country":"CH",
    "sg:address":"Via Camminata 2",
    "sg:city":"Bellinzona",
    "sg:orig_category":"Detailhandel mit Bekleidung",
    "sg:phone":"+41 79 230 42 00",
    "sg:postcode":"6500",
    "sg:province":"Ticino",
    "wof:name":"Switcher Shop Camminata Sagl",
    "wof:placetype":"venue"
},
  "geometry": {"coordinates":[9.022446,46.190674],"type":"Point"}
}