{
  "type": "Feature",
  "properties": {
    "iso:country":"CH",
    "sg:address":"Place Croix-blanche 3",
    "sg:city":"Epalinges",
    "sg:orig_category":"Detailhandel mit Blumen U Pflanzen",
    "sg:phone":"+41 21 784 20 54",
    "sg:postcode":"1066",
    "sg:province":"Vaud",
    "wof:name":"Aux Arcades Fleurs Christine Widmer",
    "wof:placetype":"venue"
},
  "geometry": {"coordinates":[6.671602,46.548176],"type":"Point"}
}