{
  "type": "Feature",
  "properties": {
    "iso:country":"CH",
    "sg:address":"Schulstrasse 21",
    "sg:city":"Bussnang",
    "sg:orig_category":"Fachdetailhandel in Verkaufsr\u00e4umen",
    "sg:phone":"+41 71 669 11 84",
    "sg:postcode":"9565",
    "sg:province":"Thurgau",
    "wof:name":"Blumen M\u00fcller",
    "wof:placetype":"venue"
},
  "geometry": {"coordinates":[9.0852680206,47.5545158386],"type":"Point"}
}