{
  "type": "Feature",
  "properties": {
    "iso:country":"CH",
    "sg:address":"Hofmattstrasse 10",
    "sg:city":"Huttwil",
    "sg:orig_category":"G\u00fcterbef\u00f6rderung im Strassenverkehr",
    "sg:phone":"+41 62 962 21 15",
    "sg:postcode":"4950",
    "sg:province":"Bern",
    "wof:name":"Hans Z\u00fcrcher Transporte",
    "wof:placetype":"venue"
},
  "geometry": {"coordinates":[7.8476858139,47.1131896973],"type":"Point"}
}