{
  "type": "Feature",
  "properties": {
    "addr:full":"Matthofstrand 8 Luzern Luzern 6005",
    "addr:housenumber":"8",
    "addr:postcode":"6005",
    "addr:street":"Matthofstrand",
    "iso:country":"CH",
    "sg:address":"Matthofstrand 8",
    "sg:city":"Luzern",
    "sg:classifiers":[
        {
            "category":"Professional",
            "subcategory":"Accounting & Tax Preparation",
            "type":"Services"
        }
    ],
    "sg:phone":"+41 41 368 10 80",
    "sg:postcode":"6005",
    "sg:province":"Luzern",
    "sg:tags":[
        "book-keeping"
    ],
    "wof:name":"Studhalter Treuhand Ag",
    "wof:placetype":"venue"
},
  "geometry": {"coordinates":[8.33243,47.035984],"type":"Point"}
}