{
  "type": "Feature",
  "properties": {
    "iso:country":"CH",
    "sg:address":"Allmendstrasse 11 6048 Horw. Postfach",
    "sg:city":"Horw",
    "sg:orig_category":"Herstellung von Hebezeugen U F\u00f6rdermitteln Stahl U Leichtmetallbau",
    "sg:phone":"+41 33 334 54 50",
    "sg:postcode":"6048",
    "sg:province":"Luzern",
    "wof:name":"Erich Friedli Ag",
    "wof:placetype":"venue"
},
  "geometry": {"coordinates":[7.6194648743,46.7328681946],"type":"Point"}
}