{
  "type": "Feature",
  "properties": {
    "iso:country":"CH",
    "sg:address":"Wolfswinkel 9",
    "sg:city":"Z\u00fcrich",
    "sg:classifiers":[
        {
            "category":"Social Services",
            "subcategory":"Retirement Home",
            "type":"Services"
        }
    ],
    "sg:phone":"+41 13716766",
    "sg:postcode":"8046",
    "sg:province":"Z\u00fcrich",
    "sg:tags":[
        "pflegeheime",
        "u",
        "alters"
    ],
    "wof:name":"Unteraffoltern Cafeteria",
    "wof:placetype":"venue"
},
  "geometry": {"coordinates":[8.512345,47.42432],"type":"Point"}
}