{
  "type": "Feature",
  "properties": {
    "iso:country":"CH",
    "sg:address":"Stanserstrasse 9",
    "sg:city":"Stansstad",
    "sg:orig_category":"Herstellung von Radio U Fernsehger\u00e4ten sowie phono U videotechnischen Ger\u00e4ten",
    "sg:phone":"+41 79 341 48 78",
    "sg:postcode":"6362",
    "sg:province":"Nidwalden",
    "wof:name":"Wanner",
    "wof:placetype":"venue"
},
  "geometry": {"coordinates":[8.3368873596,46.9778709412],"type":"Point"}
}