{
  "type": "Feature",
  "properties": {
    "iso:country":"CH",
    "sg:address":"Rehhubelstrasse 2",
    "sg:city":"Feldbrunnen",
    "sg:orig_category":"Wirtschaftsverb\u00e4nde Pressewirtschaft",
    "sg:postcode":"4532",
    "sg:province":"Solothurn",
    "wof:name":"Arbeitsgem.d.lokal-& Regional- Presse,pr\u00e4s.herrn U.reinhardt",
    "wof:placetype":"venue"
},
  "geometry": {"coordinates":[7.5561637878,47.2209854126],"type":"Point"}
}