{
  "type": "Feature",
  "properties": {
    "iso:country":"CH",
    "sg:address":"3942",
    "sg:city":"Raron",
    "sg:orig_category":"Dachdeckerei Zimmerei, Dachdeckerei, Bauspenglerei U Abdichtung",
    "sg:phone":"+41 27 934 24 79",
    "sg:postcode":"3942",
    "sg:province":"Valais",
    "wof:name":"Stoffel Paul Ag",
    "wof:placetype":"venue"
},
  "geometry": {"coordinates":[7.800095,46.309719],"type":"Point"}
}