{
  "type": "Feature",
  "properties": {
    "iso:country":"CH",
    "sg:address":"Rue De La Corraterie 14",
    "sg:city":"Gen\u00e8ve",
    "sg:orig_category":"Advokaturb\u00fcros",
    "sg:phone":"+41 71 222 61 83",
    "sg:postcode":"1204",
    "sg:province":"Gen\u00e8ve",
    "wof:name":"Brunner Geiser & B\u00fcrgi Advokaturb\u00fcro",
    "wof:placetype":"venue"
},
  "geometry": {"coordinates":[9.375248,47.424789],"type":"Point"}
}