{
  "type": "Feature",
  "properties": {
    "iso:country":"CH",
    "sg:address":"Laternengasse 4",
    "sg:city":"Z\u00fcrich",
    "sg:orig_category":"Unternehmensberatung",
    "sg:postcode":"8001",
    "sg:province":"Z\u00fcrich",
    "wof:name":"Jenni Life Science Services",
    "wof:placetype":"venue"
},
  "geometry": {"coordinates":[8.543762207,47.3695526123],"type":"Point"}
}