{
  "type": "Feature",
  "properties": {
    "iso:country":"CH",
    "sg:address":"Mettstrasse 152",
    "sg:city":"Biel/bienne",
    "sg:orig_category":"Geb\u00e4ude, Wohnungsreinigung",
    "sg:phone":"+41 79 325 62 63",
    "sg:postcode":"2504",
    "sg:province":"Bern",
    "wof:name":"Br\u00fchlmann Reinigungen",
    "wof:placetype":"venue"
},
  "geometry": {"coordinates":[7.273419857,47.1431541443],"type":"Point"}
}