{
  "type": "Feature",
  "properties": {
    "iso:country":"CH",
    "sg:address":"Spiegelhofstrasse 43",
    "sg:city":"Z\u00fcrich",
    "sg:orig_category":"Kunsthandel",
    "sg:phone":"+41 12615566",
    "sg:postcode":"8032",
    "sg:province":"Z\u00fcrich",
    "wof:name":"Galerie Koller Ag Kunsthandel",
    "wof:placetype":"venue"
},
  "geometry": {"coordinates":[8.5584535599,47.3741035461],"type":"Point"}
}