{
  "type": "Feature",
  "properties": {
    "iso:country":"CH",
    "sg:address":"Schmelzistrasse 36",
    "sg:city":"Erschwil",
    "sg:orig_category":"Allgemeiner Hoch U Tiefbau",
    "sg:postcode":"4228",
    "sg:province":"Solothurn",
    "wof:name":"Karrer Immobilien Ag",
    "wof:placetype":"venue"
},
  "geometry": {"coordinates":[7.541662,47.37151],"type":"Point"}
}