{
  "type": "Feature",
  "properties": {
    "iso:country":"CH",
    "sg:address":"Rothenring 9",
    "sg:city":"Reussb\u00fchl",
    "sg:orig_category":"Bauschreinerei",
    "sg:phone":"+41 41 260 40 60",
    "sg:postcode":"6015",
    "sg:province":"Luzern",
    "wof:name":"Ren\u00e9 Renggli Schreinerei",
    "wof:placetype":"venue"
},
  "geometry": {"coordinates":[8.277671,47.065979],"type":"Point"}
}