{
  "type": "Feature",
  "properties": {
    "iso:country":"CH",
    "sg:address":"Ottoplatz 19",
    "sg:city":"Chur",
    "sg:orig_category":"Vermietung U Verpachtung von eigenen Immobilien",
    "sg:postcode":"7000",
    "sg:province":"Graubunden",
    "wof:name":"Multi Rent Ag",
    "wof:placetype":"venue"
},
  "geometry": {"coordinates":[9.5318384171,46.85364151],"type":"Point"}
}