{
  "type": "Feature",
  "properties": {
    "iso:country":"CH",
    "sg:address":"Rechweg 4",
    "sg:city":"D\u00fcbendorf",
    "sg:orig_category":"Maler U Glasergewerbe",
    "sg:phone":"+41 18218275",
    "sg:postcode":"8600",
    "sg:province":"Z\u00fcrich",
    "wof:name":"Malergesch\u00e4ft Milan Milosevic",
    "wof:placetype":"venue"
},
  "geometry": {"coordinates":[8.6273498535,47.4016685486],"type":"Point"}
}