{
  "type": "Feature",
  "properties": {
    "iso:country":"CH",
    "sg:address":"Industrie Rue De L' 43 1950 Sion. Postfach",
    "sg:city":"Sitten",
    "sg:classifiers":[
        {
            "category":"Communications",
            "subcategory":"Radio Station",
            "type":"Services"
        }
    ],
    "sg:phone":"+41 27 481 35 41",
    "sg:postcode":"1950",
    "sg:province":"Valais",
    "sg:tags":[
        "fernsehanstalten",
        "u"
    ],
    "wof:name":"T\u00e9l\u00e9distribution Intercommunale Sa",
    "wof:placetype":"venue"
},
  "geometry": {"coordinates":[7.3685722351,46.2284126282],"type":"Point"}
}