{
  "type": "Feature",
  "properties": {
    "iso:country":"CH",
    "sg:address":"H\u00fcttenacherstrasse 17",
    "sg:city":"St\u00e4fa",
    "sg:orig_category":"K\u00fcnstlerische U schriftstellerische T\u00e4tigkeiten U Darbietungen Sonstige k\u00fcnstlerische U schriftstell",
    "sg:phone":"+41 31 747 89 88",
    "sg:postcode":"8712",
    "sg:province":"Z\u00fcrich",
    "wof:name":"Atelier F\u00fcr Gem\u00e4lde-& Skulpturenrestaurierung",
    "wof:placetype":"venue"
},
  "geometry": {"coordinates":[7.2370109558,46.9003105164],"type":"Point"}
}