{
  "type": "Feature",
  "properties": {
    "iso:country":"CH",
    "sg:address":"Neuve-du-molard Rue 19 1204 Gen\u00e8ve. Postfach",
    "sg:city":"Gen\u00e8ve",
    "sg:orig_category":"RESTAURANTS: TEA-ROOMS",
    "sg:postcode":"1204",
    "sg:province":"Gen\u00e8ve",
    "wof:name":"Marrip Gmbh",
    "wof:placetype":"venue"
},
  "geometry": {"coordinates":[7.5534300804,47.5203437805],"type":"Point"}
}