{
  "type": "Feature",
  "properties": {
    "iso:country":"CH",
    "sg:address":"Grubenstrasse 27 3123 Belp. Postfach",
    "sg:city":"Belp",
    "sg:orig_category":"Detailhandel mit Metallwaren, Anstrichmitteln, Glaswaren, Bau U Heimwerkerbedarf",
    "sg:postcode":"3123",
    "sg:province":"Bern",
    "wof:name":"Fibre Technics Guggisberg Fibre-technische Produkte; Beratung, Schulung Usw",
    "wof:placetype":"venue"
},
  "geometry": {"coordinates":[7.4954190254,46.8922767639],"type":"Point"}
}