{
  "type": "Feature",
  "properties": {
    "iso:country":"CH",
    "sg:address":"Ratskellergasse 6",
    "sg:city":"Schwyz",
    "sg:orig_category":"Detailhandel mit Uhren U Schmuck Fachdetailhandel in Verkaufsr\u00e4umen",
    "sg:phone":"+41 41 810 11 20",
    "sg:postcode":"6430",
    "sg:province":"Schwyz",
    "wof:name":"Heinzer Benno, Goldschmied-atelier",
    "wof:placetype":"venue"
},
  "geometry": {"coordinates":[8.6540584564,47.020866394],"type":"Point"}
}