{
  "type": "Feature",
  "properties": {
    "iso:country":"CH",
    "sg:address":"Boden 55",
    "sg:city":"Murgenthal",
    "sg:orig_category":"Bauschreinerei Herstellung von M\u00f6beln verschiedener Art",
    "sg:phone":"+41 62 926 01 61",
    "sg:postcode":"4853",
    "sg:province":"Aargau",
    "wof:name":"Walter Birrer Schreinerei",
    "wof:placetype":"venue"
},
  "geometry": {"coordinates":[7.8371567726,47.2683372498],"type":"Point"}
}