{
  "type": "Feature",
  "properties": {
    "addr:full":"B\u00fchlstrasse 256 Oberhof Aargau 5062",
    "addr:housenumber":"256",
    "addr:postcode":"5062",
    "addr:street":"Buehlstrasse",
    "iso:country":"CH",
    "sg:address":"B\u00fchlstrasse 256",
    "sg:city":"Oberhof",
    "sg:classifiers":[
        {
            "category":"Shopping",
            "subcategory":"Used Merchandise",
            "type":"Retail Goods"
        }
    ],
    "sg:phone":"+41 62 877 11 55",
    "sg:postcode":"5062",
    "sg:province":"Aargau",
    "sg:tags":[
        "agricultural",
        "machinery"
    ],
    "wof:name":"Kuoni Landtechnik Ag",
    "wof:placetype":"venue"
},
  "geometry": {"coordinates":[8.00549,47.4515],"type":"Point"}
}