{
  "type": "Feature",
  "properties": {
    "iso:country":"CH",
    "sg:address":"Hohrain",
    "sg:city":"Bangerten",
    "sg:orig_category":"Detailhandel mit Waren verschiedener Art, Hauptrichtung Nahrungsmittel",
    "sg:phone":"+41 31 869 05 78",
    "sg:postcode":"3256",
    "sg:province":"Bern",
    "wof:name":"Rosa Burri Handlung",
    "wof:placetype":"venue"
},
  "geometry": {"coordinates":[7.4397139549,47.0553474426],"type":"Point"}
}