{
  "type": "Feature",
  "properties": {
    "iso:country":"CH",
    "sg:address":"Rue De Graman 97",
    "sg:city":"Puplinge",
    "sg:orig_category":"Detailhandel mit B\u00fcchern, Zeitungen, Schreib U Papeteriewaren",
    "sg:phone":"+41 22 349 21 17",
    "sg:postcode":"1241",
    "sg:province":"Gen\u00e8ve",
    "wof:name":"Aeschlimann Marcel",
    "wof:placetype":"venue"
},
  "geometry": {"coordinates":[6.232895,46.21199],"type":"Point"}
}