{
  "type": "Feature",
  "properties": {
    "iso:country":"CH",
    "sg:address":"Sankt Jakobs-strasse 3",
    "sg:city":"Basel",
    "sg:orig_category":"Unternehmensberatung Wirtschaftspr\u00fcfung, Steuerberatung U Treuhand",
    "sg:phone":"+41 71 622 86 86",
    "sg:postcode":"4052",
    "sg:province":"Basel-Stadt",
    "wof:name":"Hartmann Adrian Ag",
    "wof:placetype":"venue"
},
  "geometry": {"coordinates":[9.1381845474,47.5666694641],"type":"Point"}
}