{
  "type": "Feature",
  "properties": {
    "iso:country":"CH",
    "sg:address":"Schlossberg",
    "sg:city":"Bowil",
    "sg:orig_category":"G\u00fcterbef\u00f6rderung im Strassenverkehr",
    "sg:phone":"+41 34 497 14 78",
    "sg:postcode":"3533",
    "sg:province":"Bern",
    "wof:name":"Hofer-transporte",
    "wof:placetype":"venue"
},
  "geometry": {"coordinates":[7.7122898102,46.9082717896],"type":"Point"}
}