{
  "type": "Feature",
  "properties": {
    "iso:country":"CH",
    "sg:address":"Wildbrunnstrasse 18",
    "sg:city":"Kaltbrunn",
    "sg:orig_category":"Herstellung von Konstruktionsteilen, Fertigbauteilen U Ausbauelementen aus Holz",
    "sg:phone":"+41 55 615 24 16",
    "sg:postcode":"8722",
    "sg:province":"St. Gallen",
    "wof:name":"Moos Urs",
    "wof:placetype":"venue"
},
  "geometry": {"coordinates":[9.0106401443,47.2158813477],"type":"Point"}
}