{
  "type": "Feature",
  "properties": {
    "iso:country":"CH",
    "sg:address":"Bahnhofstrasse 7",
    "sg:city":"Biel/bienne",
    "sg:orig_category":"Non-Classified Establishments",
    "sg:postcode":"2505",
    "sg:province":"Bern",
    "wof:name":"Jade Orchidee Gmbh",
    "wof:placetype":"venue"
},
  "geometry": {"coordinates":[7.2428531647,47.1337509155],"type":"Point"}
}