{
  "type": "Feature",
  "properties": {
    "iso:country":"CH",
    "sg:address":"Chemin Des Esserpys 7",
    "sg:city":"Romanel-s-lausanne",
    "sg:orig_category":"Softwareentwicklung U beratung",
    "sg:phone":"+41 21 647 77 83",
    "sg:postcode":"1032",
    "sg:province":"Vaud",
    "wof:name":"Solutions Informatiques, Cuomo",
    "wof:placetype":"venue"
},
  "geometry": {"coordinates":[6.5992131233,46.5667953491],"type":"Point"}
}