{
  "type": "Feature",
  "properties": {
    "iso:country":"CH",
    "sg:address":"Rue De Lyon 74",
    "sg:city":"Gen\u00e8ve",
    "sg:orig_category":"Fachdetailhandel mit pharmazeutischen Produkten",
    "sg:phone":"+41 22 345 27 00",
    "sg:postcode":"1203",
    "sg:province":"Gen\u00e8ve",
    "wof:name":"Pharmacie Perregaux Sa",
    "wof:placetype":"venue"
},
  "geometry": {"coordinates":[6.127436161,46.2084274292],"type":"Point"}
}