{
  "type": "Feature",
  "properties": {
    "iso:country":"CH",
    "sg:address":"Hubel 1036 3805 Goldswil. Postfach",
    "sg:city":"Goldswil",
    "sg:orig_category":"Instandhaltung U Reparatur von Automobilen",
    "sg:postcode":"3805",
    "sg:province":"Bern",
    "wof:name":"Wyss Daniel Autoreinigungsservice",
    "wof:placetype":"venue"
},
  "geometry": {"coordinates":[7.8742089272,46.6956787109],"type":"Point"}
}