{
  "type": "Feature",
  "properties": {
    "iso:country":"CH",
    "sg:address":"Chemin Vudalla 6a",
    "sg:city":"Bulle",
    "sg:orig_category":"Zahnkliniken",
    "sg:phone":"+41 32 931 56 01",
    "sg:postcode":"1630",
    "sg:province":"Fribourg",
    "wof:name":"Clinique Dentaire Scolaire",
    "wof:placetype":"venue"
},
  "geometry": {"coordinates":[6.7507967949,47.0595703125],"type":"Point"}
}