{
  "type": "Feature",
  "properties": {
    "iso:country":"CH",
    "sg:address":"Avenue De La Gare 4",
    "sg:city":"Bulle",
    "sg:orig_category":"Zahnarztpraxen",
    "sg:phone":"+41 26 912 53 17",
    "sg:postcode":"1630",
    "sg:province":"Fribourg",
    "wof:name":"Dr M\u00e9d. Dent. Nicolas Rime M\u00e9decin-dentiste",
    "wof:placetype":"venue"
},
  "geometry": {"coordinates":[7.0566439629,46.6179733276],"type":"Point"}
}