{
  "type": "Feature",
  "properties": {
    "iso:country":"CH",
    "sg:address":"1115",
    "sg:city":"Vullierens",
    "sg:orig_category":"Detailhandel mit Waren verschiedener Art, Hauptrichtung Nahrungsmittel",
    "sg:postcode":"1115",
    "sg:province":"Vaud",
    "wof:name":"Syndicat Agricole & D'\u00e9levage Vullierens",
    "wof:placetype":"venue"
},
  "geometry": {"coordinates":[6.482336998,46.5726203918],"type":"Point"}
}