{
  "type": "Feature",
  "properties": {
    "addr:full":"3934 Zeneggen Valais 3934",
    "addr:housenumber":"3934",
    "addr:postcode":"3934",
    "addr:street":"Zeneggen Valais",
    "iso:country":"CH",
    "sg:address":"3934",
    "sg:city":"Zeneggen",
    "sg:orig_category":"Betrieb von Sportanlagen",
    "sg:postcode":"3934",
    "sg:province":"Valais",
    "wof:name":"Tennishalle Aawisen Ag",
    "wof:placetype":"venue"
},
  "geometry": {"coordinates":[8.790208,47.330978],"type":"Point"}
}