{
  "type": "Feature",
  "properties": {
    "iso:country":"CH",
    "sg:address":"H\u00f6ldeliweg 22",
    "sg:city":"Gelterkinden",
    "sg:orig_category":"G\u00fcterbef\u00f6rderung im Strassenverkehr",
    "sg:postcode":"4460",
    "sg:province":"Basel-Landschaft",
    "wof:name":"Geneto Eugen Transporte",
    "wof:placetype":"venue"
},
  "geometry": {"coordinates":[7.8461298943,47.4628601074],"type":"Point"}
}