{
  "type": "Feature",
  "properties": {
    "iso:country":"CH",
    "sg:address":"Kasinostrasse 32 5000 Aarau. Postfach",
    "sg:city":"Aarau",
    "sg:orig_category":"Vermietung U Verpachtung von eigenen Immobilien",
    "sg:postcode":"5000",
    "sg:province":"Aargau",
    "wof:name":"G & Z Services Ag Immobilien; Dienstl., Bes. Marketing, Beratung Usw",
    "wof:placetype":"venue"
},
  "geometry": {"coordinates":[8.0470514297,47.3916931152],"type":"Point"}
}