{
  "type": "Feature",
  "properties": {
    "iso:country":"CH",
    "sg:address":"Schlossstrasse 18",
    "sg:city":"M\u00fcnsingen",
    "sg:orig_category":"Sonstige Institutionen des Sozialwesens ohne Beherbergung",
    "sg:phone":"+41 31 721 49 75",
    "sg:postcode":"3110",
    "sg:province":"Bern",
    "wof:name":"Jugendberatungsstelle",
    "wof:placetype":"venue"
},
  "geometry": {"coordinates":[7.559525013,46.8754234314],"type":"Point"}
}