{
  "type": "Feature",
  "properties": {
    "iso:country":"CH",
    "sg:address":"Pestalozzistrasse 11",
    "sg:city":"Rorschach",
    "sg:orig_category":"Herstellung von Metallerzeugnissen ohne Maschinenbau Maschinenbau",
    "sg:phone":"+41 71 277 04 74",
    "sg:postcode":"9400",
    "sg:province":"St. Gallen",
    "wof:name":"Sp\u00f6rndli & Seger Ag",
    "wof:placetype":"venue"
},
  "geometry": {"coordinates":[9.3220691681,47.4104881287],"type":"Point"}
}