{
  "type": "Feature",
  "properties": {
    "iso:country":"CH",
    "sg:address":"Untere Maressenstrasse 29",
    "sg:city":"Leukerbad",
    "sg:orig_category":"Personenbef\u00f6rderung im Linienverkehr zu Land",
    "sg:phone":"+41 27 472 81 10",
    "sg:postcode":"3954",
    "sg:province":"Valais",
    "wof:name":"Torrent-bahnen Leukerbad-albinen Ag",
    "wof:placetype":"venue"
},
  "geometry": {"coordinates":[7.6283230782,46.3765029907],"type":"Point"}
}