{
  "type": "Feature",
  "properties": {
    "iso:country":"CH",
    "sg:address":"Molard Place Du 7 1204 Gen\u00e8ve. Postfach",
    "sg:city":"Gen\u00e8ve",
    "sg:orig_category":"Rechtsberatung",
    "sg:postcode":"1204",
    "sg:province":"Gen\u00e8ve",
    "wof:name":"Etude Christian Pirker",
    "wof:placetype":"venue"
},
  "geometry": {"coordinates":[6.1486139297,46.2035331726],"type":"Point"}
}