{
  "type": "Feature",
  "properties": {
    "iso:country":"CH",
    "sg:address":"Rudolfstrasse 25",
    "sg:city":"Basel",
    "sg:orig_category":"Maler U Glasergewerbe Malerei",
    "sg:phone":"+41 61 301 62 70",
    "sg:postcode":"4054",
    "sg:province":"Basel-Stadt",
    "wof:name":"F. & R. Klauser, Malergesch\u00e4ft, Inhaber R. Klauser",
    "wof:placetype":"venue"
},
  "geometry": {"coordinates":[7.5752148628,47.5547523499],"type":"Point"}
}