{
  "type": "Feature",
  "properties": {
    "iso:country":"CH",
    "sg:address":"Hardhofstrasse 15",
    "sg:city":"Embrach",
    "sg:orig_category":"Grosshandel mit Nahrungsmitteln, Getr\u00e4nken U Tabakwaren Grosshandel mit Nahrungsmitteln, Getr\u00e4nken U",
    "sg:phone":"+41 62 824 11 12",
    "sg:postcode":"8424",
    "sg:province":"Z\u00fcrich",
    "wof:name":"Handel Und Organisation Zadik",
    "wof:placetype":"venue"
},
  "geometry": {"coordinates":[8.0793466568,47.3991584778],"type":"Point"}
}