{
  "type": "Feature",
  "properties": {
    "iso:country":"CH",
    "sg:address":"Stationsstrasse 33",
    "sg:city":"Br\u00fcttisellen",
    "sg:orig_category":"Mineralquellen, Herstellung von alkoholfreien Getr\u00e4nken",
    "sg:phone":"+41 18359111",
    "sg:postcode":"8306",
    "sg:province":"Z\u00fcrich",
    "wof:name":"Coca-cola Ag",
    "wof:placetype":"venue"
},
  "geometry": {"coordinates":[8.6243391037,47.4204101562],"type":"Point"}
}