{
  "type": "Feature",
  "properties": {
    "iso:country":"CH",
    "sg:address":"Sunned\u00f6rfli 170 3512 Walkringen. Postfach 22",
    "sg:city":"Walkringen",
    "sg:orig_category":"Fachdetailhandel in Verkaufsr\u00e4umen Grosshandel mit Sportartikeln",
    "sg:phone":"+41 31 701 03 07",
    "sg:postcode":"3512",
    "sg:province":"Bern",
    "wof:name":"Fly Over Gmbh",
    "wof:placetype":"venue"
},
  "geometry": {"coordinates":[7.6219801903,46.9479103088],"type":"Point"}
}