{
  "type": "Feature",
  "properties": {
    "iso:country":"CH",
    "sg:address":"Eustrasse 2",
    "sg:city":"Menzingen",
    "sg:orig_category":"Handelsvermittlung U Grosshandel",
    "sg:phone":"+41 71 278 77 60",
    "sg:postcode":"6313",
    "sg:province":"Zug",
    "wof:name":"Mehmet Akg\u00fcn Matratzen-import",
    "wof:placetype":"venue"
},
  "geometry": {"coordinates":[9.3554611206,47.4201660156],"type":"Point"}
}