{
  "type": "Feature",
  "properties": {
    "addr:full":"Rue Des Parcs 3 Neuch\u00e2tel Neuch\u00e2tel 2000",
    "addr:housenumber":"3",
    "addr:postcode":"2000",
    "addr:street":"Rue Des Parcs",
    "iso:country":"CH",
    "sg:address":"Rue Des Parcs 3",
    "sg:city":"Neuch\u00e2tel",
    "sg:classifiers":[
        {
            "category":"Social Services",
            "subcategory":"Retirement Home",
            "type":"Services"
        }
    ],
    "sg:phone":"+41 32 721 33 73",
    "sg:postcode":"2000",
    "sg:province":"Neuch\u00e2tel",
    "sg:tags":[
        "pflegeheime",
        "u",
        "alters"
    ],
    "wof:name":"M\u00e9dicalis\u00e9 Les Myosotis Pr Personnes \u00e2g\u00e9es & Convalescent",
    "wof:placetype":"venue"
},
  "geometry": {"coordinates":[6.926783,46.994232],"type":"Point"}
}