{
  "type": "Feature",
  "properties": {
    "iso:country":"CH",
    "sg:address":"1964",
    "sg:city":"Conthey",
    "sg:orig_category":"Vorschulen, Kinderg\u00e4rten",
    "sg:postcode":"1964",
    "sg:province":"Valais",
    "wof:name":"Ecole Enfantine",
    "wof:placetype":"venue"
},
  "geometry": {"coordinates":[7.302670002,46.2224006653],"type":"Point"}
}