{
  "type": "Feature",
  "properties": {
    "iso:country":"CH",
    "sg:address":"Henric Petri-strasse 26",
    "sg:city":"Basel",
    "sg:orig_category":"Herstellung von konfektionierten Textilwaren ohne Bekleidung",
    "sg:postcode":"4051",
    "sg:province":"Basel-Stadt",
    "wof:name":"Modo Ag",
    "wof:placetype":"venue"
},
  "geometry": {"coordinates":[7.5937581062,47.5512123108],"type":"Point"}
}