{
  "type": "Feature",
  "properties": {
    "iso:country":"CH",
    "sg:address":"Grand'rue 4",
    "sg:city":"St-prex",
    "sg:classifiers":[
        {
            "category":"Insurance",
            "subcategory":"Insurance Agent",
            "type":"Services"
        }
    ],
    "sg:phone":"+41 21 806 27 27",
    "sg:postcode":"1162",
    "sg:province":"Vaud",
    "sg:tags":[
        "versicherungsagenturen",
        "-broker"
    ],
    "wof:name":"Winterthur Assurances Agence Serge Buchard",
    "wof:placetype":"venue"
},
  "geometry": {"coordinates":[6.4603710175,46.4790992737],"type":"Point"}
}