{
  "type": "Feature",
  "properties": {
    "iso:country":"CH",
    "sg:address":"Banackerweg 586",
    "sg:city":"Neuendorf",
    "sg:orig_category":"G\u00fcterbef\u00f6rderung im Strassenverkehr",
    "sg:postcode":"4623",
    "sg:province":"Solothurn",
    "wof:name":"Lc+s K\u00fcnzi Bernhard",
    "wof:placetype":"venue"
},
  "geometry": {"coordinates":[7.7953262329,47.2954788208],"type":"Point"}
}