{
  "type": "Feature",
  "properties": {
    "iso:country":"CH",
    "sg:address":"Strada Maestra-carlin 215",
    "sg:city":"Campascio",
    "sg:orig_category":"Blumen U Zierpflanzenbau",
    "sg:phone":"+41 81 844 01 78",
    "sg:postcode":"7748",
    "sg:province":"Graubunden",
    "wof:name":"Mario Compagnoni Giardiniere & Fiorista",
    "wof:placetype":"venue"
},
  "geometry": {"coordinates":[10.130253,46.246429],"type":"Point"}
}