{
  "type": "Feature",
  "properties": {
    "iso:country":"CH",
    "sg:address":"Steinenberg 1",
    "sg:city":"Basel",
    "sg:classifiers":[
        {
            "category":"Banks & Credit Unions",
            "subcategory":"Bank",
            "type":"Services"
        }
    ],
    "sg:phone":"+41 61 271 15 97",
    "sg:postcode":"4051",
    "sg:province":"Basel-Stadt",
    "wof:name":"Regiobank",
    "wof:placetype":"venue"
},
  "geometry": {"coordinates":[7.591854,47.553654],"type":"Point"}
}