{
  "type": "Feature",
  "properties": {
    "iso:country":"CH",
    "sg:address":"3202",
    "sg:city":"Frauenkappelen",
    "sg:orig_category":"Organisationen des Gesundheitswesen",
    "sg:phone":"+41 32 313 13 25",
    "sg:postcode":"3202",
    "sg:province":"Bern",
    "wof:name":"Samariterverein",
    "wof:placetype":"venue"
},
  "geometry": {"coordinates":[7.3368749619,46.9553031921],"type":"Point"}
}