{
  "type": "Feature",
  "properties": {
    "addr:full":"Hauptstrasse 78 Steinach St. Gallen 9323",
    "addr:housenumber":"78;st.",
    "addr:postcode":"9323",
    "addr:street":"Hauptstrasse;Steinach",
    "iso:country":"CH",
    "sg:address":"Hauptstrasse 78",
    "sg:city":"Steinach",
    "sg:orig_category":"Datenverarbeitungsdienste Sonstige mit der Informatik verbundene T\u00e4tigkeiten",
    "sg:phone":"+41 71 440 00 20",
    "sg:postcode":"9323",
    "sg:province":"St. Gallen",
    "wof:name":"Rossi Informatik",
    "wof:placetype":"venue"
},
  "geometry": {"coordinates":[9.448014,47.500767],"type":"Point"}
}