{
  "type": "Feature",
  "properties": {
    "iso:country":"CH",
    "sg:address":"Hauptstrasse 56",
    "sg:city":"Zunzgen",
    "sg:orig_category":"Nationale Postdienste",
    "sg:phone":"+41 61 971 10 32",
    "sg:postcode":"4455",
    "sg:province":"Basel-Landschaft",
    "wof:name":"Die Schweizerische Post",
    "wof:placetype":"venue"
},
  "geometry": {"coordinates":[7.8075871468,47.4504814148],"type":"Point"}
}