{
  "type": "Feature",
  "properties": {
    "iso:country":"CH",
    "sg:address":"B\u00fcelacker 2",
    "sg:city":"Aadorf",
    "sg:orig_category":"Herstellung von gewirktem U gestricktem Stoff",
    "sg:phone":"+41 52 365 43 61",
    "sg:postcode":"8355",
    "sg:province":"Thurgau",
    "wof:name":"Entress Wenger & Bommer Advokaturb\u00fcro",
    "wof:placetype":"venue"
},
  "geometry": {"coordinates":[8.9064102173,47.4980545044],"type":"Point"}
}