{
  "type": "Feature",
  "properties": {
    "iso:country":"CH",
    "sg:address":"Chemin Des Cr\u00eats-de-champel 35",
    "sg:city":"Gen\u00e8ve",
    "sg:classifiers":[
        {
            "category":"Insurance",
            "subcategory":"Insurance Agent",
            "type":"Services"
        }
    ],
    "sg:phone":"+41 22 346 58 44",
    "sg:postcode":"1206",
    "sg:province":"Gen\u00e8ve",
    "sg:tags":[
        "versicherungsagenturen",
        "-broker"
    ],
    "wof:name":"Bernard Roth Assurances Ttes Branches",
    "wof:placetype":"venue"
},
  "geometry": {"coordinates":[6.1567540169,46.187046051],"type":"Point"}
}