{
  "type": "Feature",
  "properties": {
    "iso:country":"CH",
    "sg:address":"Neuengasse 25 3011 Bern. Postfach",
    "sg:city":"Bern",
    "sg:orig_category":"Softwareentwicklung U beratung",
    "sg:phone":"+41 19913012",
    "sg:postcode":"3005",
    "sg:province":"Bern",
    "wof:name":"Datalizard Ag",
    "wof:placetype":"venue"
},
  "geometry": {"coordinates":[8.5773153305,47.3270492554],"type":"Point"}
}