{
  "type": "Feature",
  "properties": {
    "iso:country":"CH",
    "sg:address":"Grossmattstrasse 1",
    "sg:city":"Rudolfstetten",
    "sg:orig_category":"Instandhaltung U Reparatur von Automobilen",
    "sg:phone":"+41 56 631 92 31",
    "sg:postcode":"8964",
    "sg:province":"Aargau",
    "wof:name":"Garage Trottmann K. & K\u00fcnzli Th.",
    "wof:placetype":"venue"
},
  "geometry": {"coordinates":[8.385799408,47.3745574951],"type":"Point"}
}