{
  "type": "Feature",
  "properties": {
    "iso:country":"CH",
    "sg:address":"Neuch\u00e2tel Rue De 34",
    "sg:city":"Peseux",
    "sg:orig_category":"Handel mit Motorr\u00e4dern, Teilen U Zubeh\u00f6r Instandhaltung U Reparatur von Motorr\u00e4dern",
    "sg:phone":"+41 32 730 17 01",
    "sg:postcode":"2034",
    "sg:province":"Neuch\u00e2tel",
    "wof:name":"Coulon Philippe Sa",
    "wof:placetype":"venue"
},
  "geometry": {"coordinates":[6.8968491554,46.9884529114],"type":"Point"}
}