{
  "type": "Feature",
  "properties": {
    "iso:country":"CH",
    "sg:address":"1034",
    "sg:city":"Boussens",
    "sg:orig_category":"Bauschreinerei Herstellung von Metallkonstruktionen",
    "sg:phone":"+41 61 711 45 45",
    "sg:postcode":"1034",
    "sg:province":"Vaud",
    "wof:name":"Erlenhof",
    "wof:placetype":"venue"
},
  "geometry": {"coordinates":[7.580791,47.491886],"type":"Point"}
}