{
  "type": "Feature",
  "properties": {
    "iso:country":"CH",
    "sg:address":"Webergasse 27",
    "sg:city":"Schaffhausen",
    "sg:orig_category":"RESTAURANTS: TEA-ROOMS",
    "sg:phone":"+41 52 625 99 03",
    "sg:postcode":"8200",
    "sg:province":"Schaffhausen",
    "wof:name":"Pizzeria La Rondine",
    "wof:placetype":"venue"
},
  "geometry": {"coordinates":[8.6356048584,47.6982040405],"type":"Point"}
}