{
  "type": "Feature",
  "properties": {
    "iso:country":"CH",
    "sg:address":"Buhnrain 40",
    "sg:city":"Z\u00fcrich",
    "sg:orig_category":"Kinderkrippen U horte",
    "sg:phone":"+41 13011224",
    "sg:postcode":"8052",
    "sg:province":"Z\u00fcrich",
    "wof:name":"Hort Des Schulamtes Der Stadt Z\u00fcrich",
    "wof:placetype":"venue"
},
  "geometry": {"coordinates":[8.5423164368,47.4213104248],"type":"Point"}
}