{
  "type": "Feature",
  "properties": {
    "iso:country":"CH",
    "sg:address":"Grand-rue 9",
    "sg:city":"Attalens",
    "sg:orig_category":"Non-Classified Establishments",
    "sg:postcode":"1616",
    "sg:province":"Fribourg",
    "wof:name":"Pharmacie D'attalens Sa",
    "wof:placetype":"venue"
},
  "geometry": {"coordinates":[6.8484501839,46.5102882385],"type":"Point"}
}