{
  "type": "Feature",
  "properties": {
    "iso:country":"CH",
    "sg:address":"Winkelriedstrasse 58 6003 Luzern. Postfach",
    "sg:city":"Luzern",
    "sg:orig_category":"Sonstiges Versicherungsgewerbe",
    "sg:phone":"+41 41 210 34 33",
    "sg:postcode":"6003",
    "sg:province":"Luzern",
    "wof:name":"Neuenburger Versicherungen Generalagentur Leben Luzern, Weber Josef",
    "wof:placetype":"venue"
},
  "geometry": {"coordinates":[8.3072071075,47.0462722778],"type":"Point"}
}