{
  "type": "Feature",
  "properties": {
    "iso:country":"CH",
    "sg:address":"Zeughausweg 3 2542 Pieterlen. Postfach",
    "sg:city":"Pieterlen",
    "sg:orig_category":"Instandhaltung U Reparatur von Automobilen",
    "sg:postcode":"2542",
    "sg:province":"Bern",
    "wof:name":"Pro Speed, Fahrzeuge, Maschinen Und Teile W\u00e4lti M.",
    "wof:placetype":"venue"
},
  "geometry": {"coordinates":[8.811504364,47.3359489441],"type":"Point"}
}