{
  "type": "Feature",
  "properties": {
    "iso:country":"CH",
    "sg:address":"Industrie B\u00e4nnli 19",
    "sg:city":"Wolfwil",
    "sg:orig_category":"Grosshandel mit Maschinen U Ausr\u00fcstungen Grosshandel mit sonstigen Maschinen U Ausr\u00fcstungen f\u00fcr Indu",
    "sg:phone":"+41 62 926 23 13",
    "sg:postcode":"4628",
    "sg:province":"Solothurn",
    "wof:name":"Khs Kl\u00f6ckner Holstein Seitz Gmbh",
    "wof:placetype":"venue"
},
  "geometry": {"coordinates":[7.7994689941,47.2698783875],"type":"Point"}
}