{
  "type": "Feature",
  "properties": {
    "iso:country":"CH",
    "sg:address":"Gapil",
    "sg:city":"Gurtnellen",
    "sg:orig_category":"Haltung von Rindern",
    "sg:postcode":"6482",
    "sg:province":"Uri",
    "wof:name":"Viehzuchtgenossenschaft Gurtnellen",
    "wof:placetype":"venue"
},
  "geometry": {"coordinates":[8.6291093826,46.7416572571],"type":"Point"}
}