{
  "type": "Feature",
  "properties": {
    "iso:country":"CH",
    "sg:address":"Leimbachstrasse 93",
    "sg:city":"Z\u00fcrich",
    "sg:orig_category":"G\u00fcterbef\u00f6rderung im Strassenverkehr",
    "sg:postcode":"8041",
    "sg:province":"Z\u00fcrich",
    "wof:name":"Ren\u00e9 Br\u00e4ndli Transporte",
    "wof:placetype":"venue"
},
  "geometry": {"coordinates":[8.5164890289,47.3314704895],"type":"Point"}
}