{
  "type": "Feature",
  "properties": {
    "iso:country":"CH",
    "sg:address":"Scheuermatt 258",
    "sg:city":"Biembach",
    "sg:orig_category":"Mechanik Mechanische Werkst\u00e4tten",
    "sg:phone":"+41 34 461 33 39",
    "sg:postcode":"3419",
    "sg:province":"Bern",
    "wof:name":"Schleifservice Reist Hans",
    "wof:placetype":"venue"
},
  "geometry": {"coordinates":[7.628308773,47.0022506714],"type":"Point"}
}