{
  "type": "Feature",
  "properties": {
    "iso:country":"CH",
    "sg:address":"Kesselstrasse 6",
    "sg:city":"Frauenfeld",
    "sg:orig_category":"Detailhandel mit Fahrr\u00e4dern Handel mit Motorr\u00e4dern, Teilen U Zubeh\u00f6r Instandhaltung U Reparatur von ",
    "sg:phone":"+41 52 720 21 82",
    "sg:postcode":"8500",
    "sg:province":"Thurgau",
    "wof:name":"Fritz Egli Velos-motos",
    "wof:placetype":"venue"
},
  "geometry": {"coordinates":[8.8931417465,47.5531463623],"type":"Point"}
}