{
  "type": "Feature",
  "properties": {
    "iso:country":"CH",
    "sg:address":"Chemin St-hubert 5 1950 Sion Case Postale 696",
    "sg:city":"Sion",
    "sg:orig_category":"Fotografische Ateliers Fotografisches Gewerbe U fotografische Laboratorien",
    "sg:phone":"+41 27 322 89 92",
    "sg:postcode":"1951",
    "sg:province":"Valais",
    "wof:name":"Photostudio Preisig Heinz",
    "wof:placetype":"venue"
},
  "geometry": {"coordinates":[7.3512010574,46.2248268127],"type":"Point"}
}