{
  "type": "Feature",
  "properties": {
    "iso:country":"CH",
    "sg:address":"Hertensteinstrasse 28",
    "sg:city":"Luzern",
    "sg:orig_category":"Arztpraxen",
    "sg:phone":"+41 41 412 18 08",
    "sg:postcode":"6004",
    "sg:province":"Luzern",
    "wof:name":"Drs Med. Suppiger & Peter Spezial\u00e4rzte Fmh",
    "wof:placetype":"venue"
},
  "geometry": {"coordinates":[8.309089,47.054741],"type":"Point"}
}