{
  "type": "Feature",
  "properties": {
    "iso:country":"CH",
    "sg:address":"Chemin Du Viaduc 1. 1000 Lausanne. Postfach",
    "sg:city":"Pully",
    "sg:orig_category":"Pensionskassen",
    "sg:postcode":"1009",
    "sg:province":"Vaud",
    "wof:name":"Fonds De Pr\u00e9voyance En Faveur Du Personnel Du Comptoir Des Eaux Min\u00e9rales Sa Lausanne.",
    "wof:placetype":"venue"
},
  "geometry": {"coordinates":[6.6947751045,46.5545883179],"type":"Point"}
}