{
  "type": "Feature",
  "properties": {
    "addr:full":"Sch\u00f6nenwerderstrasse 59 Oberentfelden Aargau 5036",
    "addr:housenumber":"59",
    "addr:postcode":"5036",
    "addr:street":"Schoenenwerderstrasse",
    "iso:country":"CH",
    "sg:address":"Sch\u00f6nenwerderstrasse 59",
    "sg:city":"Oberentfelden",
    "sg:classifiers":[
        {
            "category":"Organizations",
            "subcategory":"Labor Organization",
            "type":"Services"
        }
    ],
    "sg:phone":"+41 79 232 87 67",
    "sg:postcode":"5036",
    "sg:province":"Aargau",
    "sg:tags":[
        "work",
        "assembling",
        "assembly",
        "contract"
    ],
    "wof:name":"Mia Montagen G. Berchtold",
    "wof:placetype":"venue"
},
  "geometry": {"coordinates":[8.036422,47.359997],"type":"Point"}
}