{
  "type": "Feature",
  "properties": {
    "iso:country":"CH",
    "sg:address":"D\u00fcnnernstrasse 34",
    "sg:city":"Oensingen",
    "sg:orig_category":"Herstellung von Metallkonstruktionen",
    "sg:phone":"+41 62 396 30 50",
    "sg:postcode":"4702",
    "sg:province":"Solothurn",
    "wof:name":"Marbet Toni Metallbau",
    "wof:placetype":"venue"
},
  "geometry": {"coordinates":[7.7186608315,47.2818450928],"type":"Point"}
}