{
  "type": "Feature",
  "properties": {
    "iso:country":"CH",
    "sg:address":"Chemin De La D\u00eeme 1",
    "sg:city":"Genthod",
    "sg:orig_category":"Markt U Meinungsforschung",
    "sg:phone":"+41 22 744 24 24",
    "sg:postcode":"1294",
    "sg:province":"Gen\u00e8ve",
    "wof:name":"Rds Retail & Development Services Sa",
    "wof:placetype":"venue"
},
  "geometry": {"coordinates":[6.1483931541,46.2615318298],"type":"Point"}
}