{
  "type": "Feature",
  "properties": {
    "iso:country":"CH",
    "sg:address":"Haldenfeld 135",
    "sg:city":"Uffikon",
    "sg:orig_category":"Herstellung von Ger\u00e4ten der Elektrizit\u00e4tserzeugung, -verteilung u.\u00e4. -Herstellung von elektronischen",
    "sg:phone":"+41 32 373 38 58",
    "sg:postcode":"6253",
    "sg:province":"Luzern",
    "wof:name":"Anapol-ger\u00e4tetechnik Ag",
    "wof:placetype":"venue"
},
  "geometry": {"coordinates":[7.2665920258,47.123046875],"type":"Point"}
}