{
  "type": "Feature",
  "properties": {
    "iso:country":"CH",
    "sg:address":"Ermitagestrasse 13",
    "sg:city":"Arlesheim",
    "sg:orig_category":"Arztpraxen",
    "sg:phone":"+41 61 702 00 48",
    "sg:postcode":"4144",
    "sg:province":"Basel-Landschaft",
    "wof:name":"Dr.med. Brigitte Schaub Spezial\u00e4rztin Fmh",
    "wof:placetype":"venue"
},
  "geometry": {"coordinates":[7.62083,47.494492],"type":"Point"}
}