{
  "type": "Feature",
  "properties": {
    "addr:full":"Langstrasse 88 Z\u00fcrich Z\u00fcrich 8004",
    "addr:housenumber":"88",
    "addr:postcode":"8004",
    "addr:street":"Langstrasse",
    "iso:country":"CH",
    "sg:address":"Langstrasse 88",
    "sg:city":"Z\u00fcrich",
    "sg:orig_category":"Detailhandel mit Damenbekleidung",
    "sg:phone":"+41 12418785",
    "sg:postcode":"8004",
    "sg:province":"Z\u00fcrich",
    "wof:name":"Kurt Isaac Textilhaus Bonna",
    "wof:placetype":"venue"
},
  "geometry": {"coordinates":[8.52671,47.377979],"type":"Point"}
}