{
  "type": "Feature",
  "properties": {
    "iso:country":"CH",
    "sg:address":"Bernstrasse 115 3613 Steffisburg. Postfach",
    "sg:city":"Steffisburg",
    "sg:orig_category":"Handelsvermittlung U Grosshandel mit Automobilen Herstellung von Karosserien U Anh\u00e4ngern",
    "sg:phone":"+41 33 437 74 37",
    "sg:postcode":"3613",
    "sg:province":"Bern",
    "wof:name":"Ruchti Ag",
    "wof:placetype":"venue"
},
  "geometry": {"coordinates":[7.6156139374,46.7749404907],"type":"Point"}
}