{
  "type": "Feature",
  "properties": {
    "iso:country":"CH",
    "sg:address":"Dorfstrasse 20 8484 Weisslingen. Postfach",
    "sg:city":"Weisslingen",
    "sg:orig_category":"Sonstiger spezialisierter Hoch U Tiefbau",
    "sg:postcode":"8484",
    "sg:province":"Z\u00fcrich",
    "wof:name":"Hotz Natur\u00f6fen Gmbh",
    "wof:placetype":"venue"
},
  "geometry": {"coordinates":[8.7641410828,47.4313201904],"type":"Point"}
}