{
  "type": "Feature",
  "properties": {
    "iso:country":"CH",
    "sg:address":"3306",
    "sg:city":"Etzelkofen",
    "sg:classifiers":[
        {
            "category":"Government",
            "subcategory":"Post Office",
            "type":"Public Place"
        }
    ],
    "sg:phone":"+41 31 765 52 02",
    "sg:postcode":"3306",
    "sg:province":"Bern",
    "sg:tags":[
        "die",
        "poststellen"
    ],
    "wof:name":"Die Post",
    "wof:placetype":"venue"
},
  "geometry": {"coordinates":[7.4799199104,47.0840911865],"type":"Point"}
}