{
  "type": "Feature",
  "properties": {
    "iso:country":"CH",
    "sg:address":"Im Ifang 10-12",
    "sg:city":"Baden",
    "sg:orig_category":"Mattress Protectors",
    "sg:phone":"+41 71 313 90 80",
    "sg:postcode":"5400",
    "sg:province":"Aargau",
    "wof:name":"Doc Ag",
    "wof:placetype":"venue"
},
  "geometry": {"coordinates":[9.3098201752,47.4035072327],"type":"Point"}
}