{
  "type": "Feature",
  "properties": {
    "iso:country":"CH",
    "sg:address":"Plazzet Via 14",
    "sg:city":"Samedan",
    "sg:orig_category":"Museen",
    "sg:postcode":"7503",
    "sg:province":"Graubunden",
    "wof:name":"Plazzet Galerie, Helmreich Doris",
    "wof:placetype":"venue"
},
  "geometry": {"coordinates":[9.8717031479,46.5347557068],"type":"Point"}
}