{
  "type": "Feature",
  "properties": {
    "iso:country":"CH",
    "sg:address":"Seftigenstrasse 358",
    "sg:city":"Wabern",
    "sg:classifiers":[
        {
            "category":"Banks & Credit Unions",
            "subcategory":"Bank",
            "type":"Services"
        }
    ],
    "sg:phone":"+41 31 961 51 21",
    "sg:postcode":"3084",
    "sg:province":"Bern",
    "wof:name":"Spar + Leihkasse In Bern",
    "wof:placetype":"venue"
},
  "geometry": {"coordinates":[7.459121,46.923248],"type":"Point"}
}