{
  "type": "Feature",
  "properties": {
    "addr:full":"Alte St. Wolfgangstrasse 5 H\u00fcnenberg Zug 6331",
    "addr:housenumber":"5",
    "addr:postcode":"6331",
    "addr:street":"Alte St. Wolfgangstrasse;Huenenberg Zug",
    "iso:country":"CH",
    "sg:address":"Alte St. Wolfgangstrasse 5",
    "sg:city":"H\u00fcnenberg",
    "sg:classifiers":[
        {
            "category":"Professional",
            "subcategory":"Detective & Security Services",
            "type":"Services"
        }
    ],
    "sg:phone":"+41 41 785 55 99",
    "sg:postcode":"6331",
    "sg:province":"Zug",
    "sg:tags":[
        "customer",
        "information"
    ],
    "wof:name":"Adim Agentur F\u00fcr Direkt-marketing Ag",
    "wof:placetype":"venue"
},
  "geometry": {"coordinates":[8.426294,47.176785],"type":"Point"}
}