{
  "type": "Feature",
  "properties": {
    "iso:country":"CH",
    "sg:address":"Rte De Ch\u00e2tel-saint-denis",
    "sg:city":"St-l\u00e9gier",
    "sg:classifiers":[
        {
            "category":"Restaurant",
            "type":"Food & Drink"
        }
    ],
    "sg:phone":"+41 32 853 16 84",
    "sg:postcode":"1806",
    "sg:province":"Vaud",
    "wof:name":"Caf\u00e9 De La Vieille Fontaine",
    "wof:placetype":"venue"
},
  "geometry": {"coordinates":[6.9875998497,47.0987815857],"type":"Point"}
}