{
  "type": "Feature",
  "properties": {
    "iso:country":"CH",
    "sg:address":"Rue Du Nant 4-6",
    "sg:city":"Gen\u00e8ve",
    "sg:orig_category":"Universit\u00e4tsspit\u00e4ler, Spit\u00e4ler f\u00fcr allgemeine Pflege",
    "sg:phone":"+41 22 735 55 50",
    "sg:postcode":"1207",
    "sg:province":"Gen\u00e8ve",
    "wof:name":"Permanence Des Eaux-vives Sa",
    "wof:placetype":"venue"
},
  "geometry": {"coordinates":[6.159845829,46.2018280029],"type":"Point"}
}