{
  "type": "Feature",
  "properties": {
    "iso:country":"CH",
    "sg:address":"Livio Via 5",
    "sg:city":"Chiasso",
    "sg:orig_category":"Saunas, Solarien, Fitnesszentren U \u00e4hnliches",
    "sg:postcode":"6830",
    "sg:province":"Ticino",
    "wof:name":"World Sun Club Sagl",
    "wof:placetype":"venue"
},
  "geometry": {"coordinates":[9.0294589996,45.8333625793],"type":"Point"}
}