{
  "type": "Feature",
  "properties": {
    "iso:country":"CH",
    "sg:address":"Wesemlinstrasse 2",
    "sg:city":"Luzern",
    "sg:classifiers":[
        {
            "category":"Health Services",
            "subcategory":"Medical Lab",
            "type":"Services"
        }
    ],
    "sg:phone":"+41 41 420 58 36",
    "sg:postcode":"6006",
    "sg:province":"Luzern",
    "sg:tags":[
        "appliance",
        "system"
    ],
    "wof:name":"Esogetics Gmbh",
    "wof:placetype":"venue"
},
  "geometry": {"coordinates":[8.3093938828,47.0602226257],"type":"Point"}
}