{
  "type": "Feature",
  "properties": {
    "iso:country":"CH",
    "sg:address":"Binzstrasse 352 5072 Oeschgen. Postfach",
    "sg:city":"Oeschgen",
    "sg:orig_category":"Softwareentwicklung U beratung Webdesign",
    "sg:phone":"+41 62 871 74 52",
    "sg:postcode":"5072",
    "sg:province":"Aargau",
    "wof:name":"Mynet Consulting Gmbh Informationstechnologien, Bes. Projektleitungen Usw",
    "wof:placetype":"venue"
},
  "geometry": {"coordinates":[8.0159778595,47.521522522],"type":"Point"}
}