{
  "type": "Feature",
  "properties": {
    "iso:country":"CH",
    "sg:address":"L\u00f6chliweg 29 3014 Bern. Postfach 56",
    "sg:city":"Worblaufen",
    "sg:orig_category":"Grosshandel mit Blumen U Pflanzen Grosshandel mit sonstigen Gebrauchs U Verbrauchsg\u00fctern",
    "sg:phone":"+41 31 332 50 52",
    "sg:postcode":"3048",
    "sg:province":"Bern",
    "wof:name":"Schenker Ag Floristenbedarf Engros",
    "wof:placetype":"venue"
},
  "geometry": {"coordinates":[7.4668550491,46.9703102112],"type":"Point"}
}