{
  "type": "Feature",
  "properties": {
    "iso:country":"CH",
    "sg:address":"Zaunplatz 6",
    "sg:city":"Glarus",
    "sg:classifiers":[
        {
            "category":"Restaurant",
            "type":"Food & Drink"
        }
    ],
    "sg:phone":"+41 55 640 17 10",
    "sg:postcode":"8750",
    "sg:province":"Glarus",
    "wof:name":"Restaurant Glarnerst\u00fcbli",
    "wof:placetype":"venue"
},
  "geometry": {"coordinates":[9.0676765442,47.0388412476],"type":"Point"}
}