{
  "type": "Feature",
  "properties": {
    "iso:country":"CH",
    "sg:address":"Hauptstrasse 16",
    "sg:city":"Rheineck",
    "sg:orig_category":"Detailhandel mit Waren verschiedener Art, Hauptrichtung Nahrungsmittel",
    "sg:phone":"+41 71 888 17 87",
    "sg:postcode":"9424",
    "sg:province":"St. Gallen",
    "wof:name":"Coop Ostschweiz",
    "wof:placetype":"venue"
},
  "geometry": {"coordinates":[9.5897550583,47.4665756226],"type":"Point"}
}