{
  "type": "Feature",
  "properties": {
    "iso:country":"CH",
    "sg:address":"Baselstrasse 71 4142 M\u00fcnchenstein. Postfach 39",
    "sg:city":"M\u00fcnchenstein",
    "sg:orig_category":"Detailhandel mit Bekleidung",
    "sg:phone":"+41 61 411 05 11",
    "sg:postcode":"4142",
    "sg:province":"Basel-Landschaft",
    "wof:name":"Big Fashion I. B\u00f6ll",
    "wof:placetype":"venue"
},
  "geometry": {"coordinates":[7.61767,47.522919],"type":"Point"}
}