{
  "type": "Feature",
  "properties": {
    "iso:country":"CH",
    "sg:address":"Mittelstrasse 20 2502 Biel/bienne. Postfach",
    "sg:city":"Biel/bienne",
    "sg:orig_category":"Herstellung von Uhren",
    "sg:postcode":"2502",
    "sg:province":"Bern",
    "wof:name":"Horlogerie Streit Ds",
    "wof:placetype":"venue"
},
  "geometry": {"coordinates":[6.8200030327,47.0983428955],"type":"Point"}
}