{
  "type": "Feature",
  "properties": {
    "iso:country":"CH",
    "sg:address":"Hangstrasse 11 8952 Schlieren. Postfach",
    "sg:city":"Schlieren",
    "sg:orig_category":"Gesundheitswesen",
    "sg:phone":"+41 17309389",
    "sg:postcode":"8952",
    "sg:province":"Z\u00fcrich",
    "wof:name":"Krusche Andreas Hausbesuche F\u00fcr Cellulitemassagen",
    "wof:placetype":"venue"
},
  "geometry": {"coordinates":[8.430557251,47.3964118958],"type":"Point"}
}