{
  "type": "Feature",
  "properties": {
    "iso:country":"CH",
    "sg:address":"Hindereseggen 15",
    "sg:city":"Adelboden",
    "sg:orig_category":"Unclassifiable Establishments",
    "sg:postcode":"3715",
    "sg:province":"Bern",
    "wof:name":"Burn Erwin, Naturnahe G\u00e4rten",
    "wof:placetype":"venue"
},
  "geometry": {"coordinates":[7.5525898933,46.487411499],"type":"Point"}
}