{
  "type": "Feature",
  "properties": {
    "iso:country":"CH",
    "sg:address":"Via Promulins 49",
    "sg:city":"Samedan",
    "sg:orig_category":"Organisationen des Gesundheitswesen",
    "sg:phone":"+41 81 925 15 20",
    "sg:postcode":"7503",
    "sg:province":"Graubunden",
    "wof:name":"Samariterverein Samedan",
    "wof:placetype":"venue"
},
  "geometry": {"coordinates":[9.8790493011,46.5373916626],"type":"Point"}
}