{
  "type": "Feature",
  "properties": {
    "iso:country":"CH",
    "sg:address":"Rebhalde",
    "sg:city":"Wynigen",
    "sg:orig_category":"Sportvereine Sch\u00fctzen Pistolen-& Gewehr",
    "sg:phone":"+41 31 839 16 70",
    "sg:postcode":"3472",
    "sg:province":"Bern",
    "wof:name":"Pistolensch\u00fctzen Z\u00e4ziwil",
    "wof:placetype":"venue"
},
  "geometry": {"coordinates":[7.550110817,46.9389266968],"type":"Point"}
}