{
  "type": "Feature",
  "properties": {
    "iso:country":"CH",
    "sg:address":"Grenchenstrasse 14",
    "sg:city":"Solothurn",
    "sg:orig_category":"Pensionskassen",
    "sg:phone":"+41 62 866 41 41",
    "sg:postcode":"4500",
    "sg:province":"Solothurn",
    "wof:name":"Wohlfahrtsfonds Der Sipharm Sisseln Ag",
    "wof:placetype":"venue"
},
  "geometry": {"coordinates":[7.9896440506,47.5515098572],"type":"Point"}
}