{
  "type": "Feature",
  "properties": {
    "iso:country":"CH",
    "sg:address":"Viale Stefano Franscini 5",
    "sg:city":"Lugano",
    "sg:orig_category":"Detailhandel mit Bekleidung",
    "sg:postcode":"6900",
    "sg:province":"Ticino",
    "wof:name":"Noiman Sagl",
    "wof:placetype":"venue"
},
  "geometry": {"coordinates":[8.952736,46.008537],"type":"Point"}
}