{
  "type": "Feature",
  "properties": {
    "iso:country":"CH",
    "sg:address":"Lischmatt 7",
    "sg:city":"H\u00e4rkingen",
    "sg:orig_category":"Autotransporte international",
    "sg:phone":"+41 71 282 52 22",
    "sg:postcode":"4624",
    "sg:province":"Solothurn",
    "wof:name":"Emil Egger Ag",
    "wof:placetype":"venue"
},
  "geometry": {"coordinates":[9.420197,47.440063],"type":"Point"}
}