{
  "type": "Feature",
  "properties": {
    "iso:country":"CH",
    "sg:address":"Chemin De La Forge 2",
    "sg:city":"Vufflens-la-ville",
    "sg:orig_category":"Herstellung von Tanks U Sammelbeh\u00e4ltern aus Metall Sanit\u00e4rinstallation",
    "sg:phone":"+41 21 701 37 17",
    "sg:postcode":"1302",
    "sg:province":"Vaud",
    "wof:name":"Jean-louis Barbey Inst.sanitaires & Chauffages",
    "wof:placetype":"venue"
},
  "geometry": {"coordinates":[6.5413808823,46.5769309998],"type":"Point"}
}