{
  "type": "Feature",
  "properties": {
    "iso:country":"CH",
    "sg:address":"Wohlenstrasse 40",
    "sg:city":"Uettligen",
    "sg:orig_category":"Bauspenglerei Sanit\u00e4rinstallation",
    "sg:phone":"+41 31 829 15 64",
    "sg:postcode":"3043",
    "sg:province":"Bern",
    "wof:name":"Rudolf Zehnder Sanit\u00e4re Anlagen & Spenglerei",
    "wof:placetype":"venue"
},
  "geometry": {"coordinates":[7.382061,46.985603],"type":"Point"}
}