{
  "type": "Feature",
  "properties": {
    "iso:country":"CH",
    "sg:address":"Brunnwiesenstrasse 56",
    "sg:city":"Z\u00fcrich",
    "sg:orig_category":"Herstellung von Metallerzeugnissen ohne Maschinenbau Herstellung von Werkzeugen",
    "sg:phone":"+41 52 649 40 80",
    "sg:postcode":"8049",
    "sg:province":"Z\u00fcrich",
    "wof:name":"Amidia Ag",
    "wof:placetype":"venue"
},
  "geometry": {"coordinates":[8.673541069,47.7542953491],"type":"Point"}
}