{
  "type": "Feature",
  "properties": {
    "iso:country":"CH",
    "sg:address":"Gotthardstrasse 69 6410 Goldau. Postfach 147",
    "sg:city":"Goldau",
    "sg:orig_category":"Einzelhandel mit Automobilteilen U Zubeh\u00f6r Tankstellen",
    "sg:phone":"+41 41 855 59 07",
    "sg:postcode":"6410",
    "sg:province":"Schwyz",
    "wof:name":"Walter Pfister Pneu-service",
    "wof:placetype":"venue"
},
  "geometry": {"coordinates":[8.5511837006,47.0426712036],"type":"Point"}
}