{
  "type": "Feature",
  "properties": {
    "iso:country":"CH",
    "sg:address":"B\u00e4chlimatt",
    "sg:city":"Uebeschi",
    "sg:orig_category":"Unclassifiable Establishments",
    "sg:phone":"+41 33 345 48 09",
    "sg:postcode":"3635",
    "sg:province":"Bern",
    "wof:name":"Wyss Walter",
    "wof:placetype":"venue"
},
  "geometry": {"coordinates":[7.5503211021,46.7446212769],"type":"Point"}
}