{
  "type": "Feature",
  "properties": {
    "iso:country":"CH",
    "sg:address":"S\u00e4ngetelmatten 20",
    "sg:city":"Gretzenbach",
    "sg:orig_category":"Verarbeitung von Tee U Kaffee",
    "sg:phone":"+41 62 849 04 16",
    "sg:postcode":"5014",
    "sg:province":"Solothurn",
    "wof:name":"Dorado Caf\u00e9 Gbmh",
    "wof:placetype":"venue"
},
  "geometry": {"coordinates":[8.0024909973,47.3608779907],"type":"Point"}
}