{
  "type": "Feature",
  "properties": {
    "iso:country":"CH",
    "sg:address":"Effingerstrasse 12 3011 Bern. Postfach",
    "sg:city":"Bern",
    "sg:orig_category":"Sonstige Kultur U Unterhaltungseinrichtungen",
    "sg:phone":"+41 31 381 02 52",
    "sg:postcode":"3005",
    "sg:province":"Bern",
    "wof:name":"New Dance Hofstetter Matthias Tanzschule F Gesellschaftstanz",
    "wof:placetype":"venue"
},
  "geometry": {"coordinates":[7.4355430603,46.9459838867],"type":"Point"}
}