{
  "type": "Feature",
  "properties": {
    "iso:country":"CH",
    "sg:address":"Route De L'allex",
    "sg:city":"Bex",
    "sg:orig_category":"RESTAURANTS: TEA-ROOMS",
    "sg:phone":"+41 31 738 86 21",
    "sg:postcode":"1880",
    "sg:province":"Vaud",
    "wof:name":"Keiser-strahm Franziska",
    "wof:placetype":"venue"
},
  "geometry": {"coordinates":[7.4180898666,46.7700996399],"type":"Point"}
}