{
  "type": "Feature",
  "properties": {
    "iso:country":"CH",
    "sg:address":"Sur Falveng 4",
    "sg:city":"Domat/ems",
    "sg:classifiers":[
        {
            "category":"Social Services",
            "subcategory":"Retirement Home",
            "type":"Services"
        }
    ],
    "sg:phone":"+41 81 650 31 41",
    "sg:postcode":"7013",
    "sg:province":"Graubunden",
    "sg:tags":[
        "pflegeheime",
        "u",
        "alters"
    ],
    "wof:name":"Alters-& Pflegeheim Casa Falveng",
    "wof:placetype":"venue"
},
  "geometry": {"coordinates":[9.452481,46.830383],"type":"Point"}
}