{
  "type": "Feature",
  "properties": {
    "iso:country":"CH",
    "sg:address":"Im Hofacker 29",
    "sg:city":"Magden",
    "sg:orig_category":"Sonstige mit der Informatik verbundene T\u00e4tigkeiten",
    "sg:phone":"+41 79 334 67 47",
    "sg:postcode":"4312",
    "sg:province":"Aargau",
    "wof:name":"B\u00fcrgi Ncs, Network Computer Systems",
    "wof:placetype":"venue"
},
  "geometry": {"coordinates":[7.80981493,47.5256690979],"type":"Point"}
}