{
  "type": "Feature",
  "properties": {
    "iso:country":"CH",
    "sg:address":"Hansmatt 5 6370 Stans. Postfach 953",
    "sg:city":"Stans",
    "sg:orig_category":"Betrieb von Sportanlagen Detailhandel mit Sportartikeln",
    "sg:phone":"+41 32 351 60 51",
    "sg:postcode":"6371",
    "sg:province":"Nidwalden",
    "wof:name":"Sportpark B\u00fcren Ag",
    "wof:placetype":"venue"
},
  "geometry": {"coordinates":[7.360553,47.144608],"type":"Point"}
}