{
  "type": "Feature",
  "properties": {
    "iso:country":"CH",
    "sg:address":"Rue Ernest-roulet 2",
    "sg:city":"Peseux",
    "sg:orig_category":"Landesverteidigung, Sozialversicherung \u00d6ffentliche Verwaltung",
    "sg:phone":"+41 32 737 11 25",
    "sg:postcode":"2034",
    "sg:province":"Neuch\u00e2tel",
    "wof:name":"Administration Communale Protection Civile",
    "wof:placetype":"venue"
},
  "geometry": {"coordinates":[6.8871822357,46.9857063293],"type":"Point"}
}