{
  "type": "Feature",
  "properties": {
    "iso:country":"CH",
    "sg:address":"Thunstrasse 2",
    "sg:city":"Konolfingen",
    "sg:orig_category":"Herstellung von elektrischen Lampen U Leuchten",
    "sg:postcode":"3510",
    "sg:province":"Bern",
    "wof:name":"Buena Sa",
    "wof:placetype":"venue"
},
  "geometry": {"coordinates":[7.6203980446,46.8779525757],"type":"Point"}
}