{
  "type": "Feature",
  "properties": {
    "iso:country":"CH",
    "sg:address":"Rue De La Blancherie 61",
    "sg:city":"Sion",
    "sg:orig_category":"Grosshandel mit B\u00fcromaschinen Grosshandel mit Datenverarbeitungsger\u00e4ten",
    "sg:phone":"+41 27 323 34 33",
    "sg:postcode":"1950",
    "sg:province":"Valais",
    "wof:name":"Oc\u00e9 (schweiz) Ag",
    "wof:placetype":"venue"
},
  "geometry": {"coordinates":[7.3482589722,46.2245597839],"type":"Point"}
}