{
  "type": "Feature",
  "properties": {
    "iso:country":"CH",
    "sg:address":"Industriestrasse 1",
    "sg:city":"Embrach",
    "sg:orig_category":"Instandhaltung U Reparatur von Automobilen Tankstellen",
    "sg:phone":"+41 56 633 02 44",
    "sg:postcode":"8424",
    "sg:province":"Z\u00fcrich",
    "wof:name":"Garage Hersan Antonio Hernandez.",
    "wof:placetype":"venue"
},
  "geometry": {"coordinates":[8.3359003067,47.350479126],"type":"Point"}
}