{
  "type": "Feature",
  "properties": {
    "iso:country":"CH",
    "sg:address":"Bluttrainweg 12",
    "sg:city":"Riehen",
    "sg:orig_category":"Sonstige Kultur U Unterhaltungseinrichtungen",
    "sg:phone":"+41 61 601 93 43",
    "sg:postcode":"4125",
    "sg:province":"Basel-Stadt",
    "wof:name":"Freizeitanlage Landauer Der Gemeinde Riehen",
    "wof:placetype":"venue"
},
  "geometry": {"coordinates":[7.635969162,47.570110321],"type":"Point"}
}