{
  "type": "Feature",
  "properties": {
    "iso:country":"CH",
    "sg:address":"Rue Du Petit-bois 2",
    "sg:city":"Ponts-de-martel",
    "sg:orig_category":"Elektroinstallation",
    "sg:phone":"+41 32 937 15 41",
    "sg:postcode":"2316",
    "sg:province":"Neuch\u00e2tel",
    "wof:name":"Electropro Sa",
    "wof:placetype":"venue"
},
  "geometry": {"coordinates":[6.7252922058,46.996509552],"type":"Point"}
}