{
  "type": "Feature",
  "properties": {
    "iso:country":"CH",
    "sg:address":"Fontanette",
    "sg:city":"Rue De La 13",
    "sg:orig_category":"Herstellung von Konstruktionsteilen, Fertigbauteilen U Ausbauelementen aus Holz",
    "sg:phone":"+41 32 835 23 67",
    "sg:postcode":"2026",
    "wof:name":"Menuiserie Paiano Salvatore",
    "wof:placetype":"venue"
},
  "geometry": {"coordinates":[6.837433815,46.6106910706],"type":"Point"}
}