{
  "type": "Feature",
  "properties": {
    "iso:country":"CH",
    "sg:address":"Bahnstrasse 14",
    "sg:city":"Rickenbach-attikon",
    "sg:orig_category":"Herstellung von Verpackungsmitteln aus Holz Herstellung von Wellpapier U pappe sowie von Verpackungs",
    "sg:phone":"+41 71 313 94 00",
    "sg:postcode":"8544",
    "sg:province":"Z\u00fcrich",
    "wof:name":"B. Heer Ag Verpackungen",
    "wof:placetype":"venue"
},
  "geometry": {"coordinates":[9.3123550415,47.4113883972],"type":"Point"}
}