{
  "type": "Feature",
  "properties": {
    "iso:country":"CH",
    "sg:address":"Route L\u00e9man 2",
    "sg:city":"Vionnaz",
    "sg:orig_category":"Wirtschaftspr\u00fcfung, Steuerberatung U Treuhand",
    "sg:phone":"+41 24 481 47 47",
    "sg:postcode":"1895",
    "sg:province":"Valais",
    "wof:name":"Fran\u00e7ois Sapin Bureau Fiduciaire",
    "wof:placetype":"venue"
},
  "geometry": {"coordinates":[6.9023079872,46.3105773926],"type":"Point"}
}