{
  "type": "Feature",
  "properties": {
    "iso:country":"CH",
    "sg:address":"Schulhausstrasse 74",
    "sg:city":"Herrliberg",
    "sg:classifiers":[
        {
            "category":"Banks & Credit Unions",
            "subcategory":"Bank",
            "type":"Services"
        }
    ],
    "sg:phone":"+41 19152045",
    "sg:postcode":"8704",
    "sg:province":"Z\u00fcrich",
    "wof:name":"Schweiz. National",
    "wof:placetype":"venue"
},
  "geometry": {"coordinates":[8.625421,47.288273],"type":"Point"}
}