{
  "type": "Feature",
  "properties": {
    "iso:country":"CH",
    "sg:address":"H\u00fcningerstrasse 4",
    "sg:city":"Basel",
    "sg:orig_category":"Architektur U Ingenieurb\u00fcros Herstellung von Metallkonstruktionen",
    "sg:phone":"+41 61 321 60 36",
    "sg:postcode":"4056",
    "sg:province":"Basel-Stadt",
    "wof:name":"Midea M\u00fcller Martin",
    "wof:placetype":"venue"
},
  "geometry": {"coordinates":[7.573869,47.570122],"type":"Point"}
}