{
  "type": "Feature",
  "properties": {
    "iso:country":"CH",
    "sg:address":"Ischmattstrasse 12 4573 Lohn So. Postfach",
    "sg:city":"Ammannsegg",
    "sg:orig_category":"Mit dem Versicherungsgewerbe verbundene T\u00e4tigkeiten",
    "sg:postcode":"4573",
    "sg:province":"Solothurn",
    "wof:name":"Aa Allfinanz, Allenbach A. Versicherungs Und Finanzprodukte; Beratung, Verkauf",
    "wof:placetype":"venue"
},
  "geometry": {"coordinates":[7.524810791,47.1698150635],"type":"Point"}
}