{
  "type": "Feature",
  "properties": {
    "iso:country":"CH",
    "sg:address":"6436 Muotathal. Postfach 4",
    "sg:city":"Muotathal",
    "sg:orig_category":"Primarschulen",
    "sg:phone":"+41 41 870 21 89",
    "sg:postcode":"6436",
    "sg:province":"Schwyz",
    "wof:name":"Primarschule St.karl",
    "wof:placetype":"venue"
},
  "geometry": {"coordinates":[8.6417417526,46.8793106079],"type":"Point"}
}