{
  "type": "Feature",
  "properties": {
    "iso:country":"CH",
    "sg:address":"Jussy Route De 14 B",
    "sg:city":"Th\u00f4nex",
    "sg:orig_category":"G\u00fcterbef\u00f6rderung im Strassenverkehr",
    "sg:postcode":"1226",
    "sg:province":"Gen\u00e8ve",
    "wof:name":"Transport-d\u00e9m\u00e9nagement, Bedogne",
    "wof:placetype":"venue"
},
  "geometry": {"coordinates":[6.1982450485,46.1879501343],"type":"Point"}
}