{
  "type": "Feature",
  "properties": {
    "iso:country":"CH",
    "sg:address":"Bussy Avenue De 39",
    "sg:city":"Moudon",
    "sg:orig_category":"Non-Classified Establishments",
    "sg:postcode":"1510",
    "sg:province":"Vaud",
    "wof:name":"Si St-michel Moudon",
    "wof:placetype":"venue"
},
  "geometry": {"coordinates":[6.8003668785,46.6674957275],"type":"Point"}
}