{
  "type": "Feature",
  "properties": {
    "iso:country":"CH",
    "sg:address":"1648",
    "sg:city":"Hauteville",
    "sg:orig_category":"Allgemeiner Hoch U Tiefbau",
    "sg:phone":"+41 79 358 35 42",
    "sg:postcode":"1648",
    "sg:province":"Fribourg",
    "wof:name":"Egger Marius",
    "wof:placetype":"venue"
},
  "geometry": {"coordinates":[7.10975,46.669346],"type":"Point"}
}