{
  "type": "Feature",
  "properties": {
    "iso:country":"CH",
    "sg:address":"Gewerbestrasse 24",
    "sg:city":"Allschwil",
    "sg:orig_category":"Detailhandel mit Metallwaren, Anstrichmitteln, Glaswaren, Bau U Heimwerkerbedarf Grosshandel mit son",
    "sg:phone":"+41 17154733",
    "sg:postcode":"4123",
    "sg:province":"Basel-Landschaft",
    "wof:name":"Stalder Louis",
    "wof:placetype":"venue"
},
  "geometry": {"coordinates":[8.5452337265,47.321598053],"type":"Point"}
}