{
  "type": "Feature",
  "properties": {
    "iso:country":"CH",
    "sg:address":"Zeughausstrasse 67",
    "sg:city":"Z\u00fcrich",
    "sg:classifiers":[
        {
            "category":"Personal",
            "subcategory":"Nail Salon",
            "type":"Services"
        }
    ],
    "sg:phone":"+41 12428505",
    "sg:postcode":"8004",
    "sg:province":"Z\u00fcrich",
    "sg:tags":[
        "manicure"
    ],
    "wof:name":"Rada Mikic Kosmetikinstitut Aniko",
    "wof:placetype":"venue"
},
  "geometry": {"coordinates":[8.5288581848,47.3765640259],"type":"Point"}
}