{
  "type": "Feature",
  "properties": {
    "iso:country":"CH",
    "sg:address":"Industriestrasse 9 8404 Stadel(winterthur). Postfach 1099",
    "sg:city":"Winterthur",
    "sg:orig_category":"Non-Classified Establishments",
    "sg:phone":"+41 56 442 22 46",
    "sg:postcode":"8401",
    "sg:province":"Z\u00fcrich",
    "wof:name":"Corti Naturstein Ag",
    "wof:placetype":"venue"
},
  "geometry": {"coordinates":[8.1986942291,47.4822044373],"type":"Point"}
}