{
  "type": "Feature",
  "properties": {
    "iso:country":"CH",
    "sg:address":"Place Saint-fran\u00e7ois 2 1003 Lausanne Case Postale",
    "sg:city":"Lausanne",
    "sg:orig_category":"Architektur U Ingenieurb\u00fcros Architekturb\u00fcros",
    "sg:phone":"+41 21 317 00 71",
    "sg:postcode":"1002",
    "sg:province":"Vaud",
    "wof:name":"Retail Rites Sa Travaux D'architecture Etc",
    "wof:placetype":"venue"
},
  "geometry": {"coordinates":[6.632491,46.519878],"type":"Point"}
}