{
  "type": "Feature",
  "properties": {
    "iso:country":"CH",
    "sg:address":"B\u00f6lchenstrasse 2",
    "sg:city":"Seltisberg",
    "sg:orig_category":"Vereine Musik/Blasmusik",
    "sg:phone":"+41 61 911 12 36",
    "sg:postcode":"4411",
    "sg:province":"Basel-Landschaft",
    "wof:name":"Musikgesellschaft Seltisberg",
    "wof:placetype":"venue"
},
  "geometry": {"coordinates":[7.7234158516,47.4647903442],"type":"Point"}
}