{
  "type": "Feature",
  "properties": {
    "iso:country":"CH",
    "sg:address":"Dorf",
    "sg:city":"Neuheim",
    "sg:orig_category":"Primarschulen",
    "sg:phone":"+41 41 755 23 60",
    "sg:postcode":"6345",
    "sg:province":"Zug",
    "wof:name":"Primarschule",
    "wof:placetype":"venue"
},
  "geometry": {"coordinates":[8.5754499435,47.2051849365],"type":"Point"}
}