{
  "type": "Feature",
  "properties": {
    "iso:country":"CH",
    "sg:address":"Via Olgiati 20.2a",
    "sg:city":"Giubiasco",
    "sg:orig_category":"D\u00e4mmung gegen K\u00e4lte, W\u00e4rme, Schall U Ersch\u00fctterung Stukkateurgewerbe, Gipserei U Verputzerei",
    "sg:postcode":"6512",
    "sg:province":"Ticino",
    "wof:name":"Sogir Sa Impresa Di Gessatura",
    "wof:placetype":"venue"
},
  "geometry": {"coordinates":[9.014093399,46.1761703491],"type":"Point"}
}