{
  "type": "Feature",
  "properties": {
    "iso:country":"CH",
    "sg:address":"Oberdorfstrasse 48",
    "sg:city":"Seengen",
    "sg:orig_category":"Non-Classified Establishments",
    "sg:postcode":"5707",
    "sg:province":"Aargau",
    "wof:name":"H\u00e4usermann T. + M., M\u00fchle",
    "wof:placetype":"venue"
},
  "geometry": {"coordinates":[8.2098798752,47.3276290894],"type":"Point"}
}