{
  "type": "Feature",
  "properties": {
    "iso:country":"CH",
    "sg:address":"5463",
    "sg:city":"Wislikofen",
    "sg:orig_category":"Primarschulen",
    "sg:postcode":"5463",
    "sg:province":"Aargau",
    "wof:name":"Primarschule",
    "wof:placetype":"venue"
},
  "geometry": {"coordinates":[8.3685503006,47.5530815125],"type":"Point"}
}