{
  "type": "Feature",
  "properties": {
    "iso:country":"CH",
    "sg:address":"Chemin De Grange-canal 28",
    "sg:city":"Ch\u00eane-bougeries",
    "sg:orig_category":"Grosshandel mit Nahrungsmitteln, Getr\u00e4nken U Tabakwaren ohne ausgepr\u00e4gten Schwerpunkt",
    "sg:postcode":"1224",
    "sg:province":"Gen\u00e8ve",
    "wof:name":"Syc Chamorel's & Co",
    "wof:placetype":"venue"
},
  "geometry": {"coordinates":[6.1768288612,46.202003479],"type":"Point"}
}