{
  "type": "Feature",
  "properties": {
    "iso:country":"CH",
    "sg:address":"Lohstampfestrasse 11",
    "sg:city":"T\u00e4gerwilen",
    "sg:orig_category":"Zahnarztpraxen",
    "sg:phone":"+41 71 666 72 02",
    "sg:postcode":"8274",
    "sg:province":"Thurgau",
    "wof:name":"Dr. Med. Dent. Jan Larsson Zahnarzt",
    "wof:placetype":"venue"
},
  "geometry": {"coordinates":[9.1292333603,47.659740448],"type":"Point"}
}