{
  "type": "Feature",
  "properties": {
    "iso:country":"CH",
    "sg:address":"1034",
    "sg:city":"Boussens",
    "sg:classifiers":[
        {
            "category":"Restaurant",
            "type":"Food & Drink"
        }
    ],
    "sg:phone":"+41 21 731 11 28",
    "sg:postcode":"1034",
    "sg:province":"Vaud",
    "wof:name":"Caf\u00e9 Le Chalet",
    "wof:placetype":"venue"
},
  "geometry": {"coordinates":[6.5845799446,46.6043014526],"type":"Point"}
}