{
  "type": "Feature",
  "properties": {
    "iso:country":"CH",
    "sg:address":"Boulevard Des Philosophes 19",
    "sg:city":"Gen\u00e8ve",
    "sg:orig_category":"Architekturb\u00fcros",
    "sg:phone":"+41 22 320 64 10",
    "sg:postcode":"1205",
    "sg:province":"Gen\u00e8ve",
    "wof:name":"Claude Morel Bureau D'architecture",
    "wof:placetype":"venue"
},
  "geometry": {"coordinates":[6.146025,46.196785],"type":"Point"}
}