{
  "type": "Feature",
  "properties": {
    "iso:country":"CH",
    "sg:address":"Kanzleistrasse 19",
    "sg:city":"Z\u00fcrich",
    "sg:orig_category":"Wohnheime",
    "sg:phone":"+41 12416979",
    "sg:postcode":"8004",
    "sg:province":"Z\u00fcrich",
    "wof:name":"Haus Zur Stauffacherin F\u00fcr Frauen",
    "wof:placetype":"venue"
},
  "geometry": {"coordinates":[8.5270023346,47.3740882874],"type":"Point"}
}