{
  "type": "Feature",
  "properties": {
    "iso:country":"CH",
    "sg:address":"Baselstrasse 30",
    "sg:city":"Grellingen",
    "sg:orig_category":"Schlossereien Schmieden",
    "sg:phone":"+41 61 741 16 36",
    "sg:postcode":"4203",
    "sg:province":"Basel-Landschaft",
    "wof:name":"Werner Bigler Schlosserei",
    "wof:placetype":"venue"
},
  "geometry": {"coordinates":[7.5915331841,47.4428710938],"type":"Point"}
}