{
  "type": "Feature",
  "properties": {
    "iso:country":"CH",
    "sg:address":"Im Zentrum 17",
    "sg:city":"Volketswil",
    "sg:orig_category":"Sonstige Kurierdienste",
    "sg:postcode":"8604",
    "sg:province":"Z\u00fcrich",
    "wof:name":"Alpenblitz - Marques Frau Maria Do Carmo",
    "wof:placetype":"venue"
},
  "geometry": {"coordinates":[8.681479454,47.3876724243],"type":"Point"}
}