{
  "type": "Feature",
  "properties": {
    "addr:full":"Blumenrain 16 4051 Basel. Postfach Basel Basel-Stadt 4051",
    "addr:housenumber":"16",
    "addr:postcode":"4051;4051",
    "addr:street":"Blumenrain;Postfach",
    "iso:country":"CH",
    "sg:address":"Blumenrain 16 4051 Basel. Postfach",
    "sg:city":"Basel",
    "sg:orig_category":"Binnenschiffahrt",
    "sg:phone":"+41 61 261 48 25",
    "sg:postcode":"4051",
    "sg:province":"Basel-Stadt",
    "wof:name":"Navitax Ag Reedereibetrieb, Schiffsmakler, Waren, Fahrzeughandel Usw",
    "wof:placetype":"venue"
},
  "geometry": {"coordinates":[7.587192,47.560898],"type":"Point"}
}