{
  "type": "Feature",
  "properties": {
    "iso:country":"CH",
    "sg:address":"Ahornstrasse 2",
    "sg:city":"Sch\u00f6nengrund",
    "sg:orig_category":"Detailhandel mit Damenbekleidung Detailhandel mit S\u00e4uglings U Kinderbekleidung",
    "sg:phone":"+41 62 771 26 07",
    "sg:postcode":"9105",
    "sg:province":"Appenzell Ausserrhoden",
    "wof:name":"Manuela Kummli Manuela Mode",
    "wof:placetype":"venue"
},
  "geometry": {"coordinates":[8.1829977036,47.2530975342],"type":"Point"}
}