{
  "type": "Feature",
  "properties": {
    "iso:country":"CH",
    "sg:address":"Obmoos 4",
    "sg:city":"Zug",
    "sg:orig_category":"Sonstiger Grosshandel",
    "sg:phone":"+41 41 632 50 20",
    "sg:postcode":"6300",
    "sg:province":"Zug",
    "wof:name":"Ergoline Ag Solarien & Massageliegen",
    "wof:placetype":"venue"
},
  "geometry": {"coordinates":[8.3066082001,46.9928817749],"type":"Point"}
}