{
  "type": "Feature",
  "properties": {
    "iso:country":"CH",
    "sg:address":"Webergasse 39 8200 Schaffhausen. Postfach",
    "sg:city":"Schaffhausen",
    "sg:orig_category":"Politische Parteien SP",
    "sg:phone":"+41 52 741 19 33",
    "sg:postcode":"8201",
    "sg:province":"Schaffhausen",
    "wof:name":"Sp Sozialdemokratische Partei",
    "wof:placetype":"venue"
},
  "geometry": {"coordinates":[8.848780632,47.6653594971],"type":"Point"}
}