{
  "type": "Feature",
  "properties": {
    "addr:full":"Industriestrasse 23 B\u00f6singen Fribourg 3178",
    "addr:housenumber":"23",
    "addr:postcode":"3178",
    "addr:street":"Industriestrasse;Fribourg",
    "iso:country":"CH",
    "sg:address":"Industriestrasse 23",
    "sg:city":"B\u00f6singen",
    "sg:classifiers":[
        {
            "category":"Shopping",
            "subcategory":"Computers & Home Electronics",
            "type":"Retail Goods"
        }
    ],
    "sg:phone":"+41 31 740 20 20",
    "sg:postcode":"3178",
    "sg:province":"Fribourg",
    "sg:tags":[
        "system",
        "automation"
    ],
    "wof:name":"Sigwel Ag",
    "wof:placetype":"venue"
},
  "geometry": {"coordinates":[7.231518,46.900322],"type":"Point"}
}