{
  "type": "Feature",
  "properties": {
    "iso:country":"CH",
    "sg:address":"Hauptstr. 15",
    "sg:city":"L\u00e4ufelfingen",
    "sg:orig_category":"Herstellung von Maschinen f\u00fcr die Nahrungsmittel, Getr\u00e4nkeherstellung U die Tabakverarbeitung",
    "sg:phone":"+41 62 299 28 00",
    "sg:postcode":"4448",
    "sg:province":"Basel-Landschaft",
    "wof:name":"B\u00e4ckerei Konditorei Confiserie Schaub & Co",
    "wof:placetype":"venue"
},
  "geometry": {"coordinates":[7.8553099632,47.395565033],"type":"Point"}
}