{
  "type": "Feature",
  "properties": {
    "iso:country":"CH",
    "sg:address":"1704 Fribourg Case Postale 43",
    "sg:city":"Fribourg",
    "sg:orig_category":"Sportvereine Eissport Eishockey",
    "sg:postcode":"1704",
    "sg:province":"Fribourg",
    "wof:name":"Hockey-club Star Fribourg",
    "wof:placetype":"venue"
},
  "geometry": {"coordinates":[7.1512799263,46.8025016785],"type":"Point"}
}