{
  "type": "Feature",
  "properties": {
    "iso:country":"CH",
    "sg:address":"Kalchrainstrasse 9",
    "sg:city":"Ober\u00e4geri",
    "sg:orig_category":"Grosshandel mit sonstigen Maschinen U Ausr\u00fcstungen f\u00fcr Industrie, Handel U Schiffahrt",
    "sg:phone":"+41 41 871 14 40",
    "sg:postcode":"6315",
    "sg:province":"Zug",
    "wof:name":"Cero Ag",
    "wof:placetype":"venue"
},
  "geometry": {"coordinates":[8.6150550842,46.8873558044],"type":"Point"}
}