{
  "type": "Feature",
  "properties": {
    "iso:country":"CH",
    "sg:address":"Tobelhof 14",
    "sg:city":"Adliswil",
    "sg:orig_category":"Vereine Gesang",
    "sg:phone":"+41 17104253",
    "sg:postcode":"8134",
    "sg:province":"Z\u00fcrich",
    "wof:name":"Kath.kirchenchor Adliswil",
    "wof:placetype":"venue"
},
  "geometry": {"coordinates":[8.5308046341,47.3086090088],"type":"Point"}
}