{
  "type": "Feature",
  "properties": {
    "iso:country":"CH",
    "sg:address":"Vordergasse 52",
    "sg:city":"Neunkirch",
    "sg:orig_category":"Unclassifiable Establishments",
    "sg:postcode":"8213",
    "sg:province":"Schaffhausen",
    "wof:name":"Crash Film P\u00f6tschke R.",
    "wof:placetype":"venue"
},
  "geometry": {"coordinates":[8.497256279,47.6902999878],"type":"Point"}
}