{
  "type": "Feature",
  "properties": {
    "iso:country":"CH",
    "sg:address":"Via Nassa 29",
    "sg:city":"Lugano",
    "sg:classifiers":[
        {
            "category":"Bars & Pubs",
            "type":"Food & Drink"
        }
    ],
    "sg:phone":"+41 91 922 09 58",
    "sg:postcode":"6900",
    "sg:province":"Ticino",
    "wof:name":"Bar Piccadilly",
    "wof:placetype":"venue"
},
  "geometry": {"coordinates":[8.949542,46.000599],"type":"Point"}
}