{
  "type": "Feature",
  "properties": {
    "iso:country":"CH",
    "sg:address":"Sonnenhalde 2",
    "sg:city":"Oberhelfenschwil",
    "sg:orig_category":"Architektur U Ingenieurb\u00fcros",
    "sg:phone":"+41 21 691 69 48",
    "sg:postcode":"9621",
    "sg:province":"St. Gallen",
    "wof:name":"Vincent Beucler Bureau Technique",
    "wof:placetype":"venue"
},
  "geometry": {"coordinates":[6.553049,46.515663],"type":"Point"}
}