{
  "type": "Feature",
  "properties": {
    "iso:country":"CH",
    "sg:address":"Hofacherstrasse 6",
    "sg:city":"Untersiggenthal",
    "sg:orig_category":"Unternehmensberatung",
    "sg:phone":"+41 56 288 05 22",
    "sg:postcode":"5417",
    "sg:province":"Aargau",
    "wof:name":"Aba Management Ag Unternehmens, Marketing- U. Engineeringberatungen Usw",
    "wof:placetype":"venue"
},
  "geometry": {"coordinates":[8.2564725876,47.5009384155],"type":"Point"}
}