{
  "type": "Feature",
  "properties": {
    "iso:country":"CH",
    "sg:address":"Avenue Max-huber 9 3960 Sierre Case Postale 183",
    "sg:city":"Sierre",
    "sg:orig_category":"Fahrschulen, Flugschulen",
    "sg:phone":"+41 79 355 43 06",
    "sg:postcode":"3960",
    "sg:province":"Valais",
    "wof:name":"Martial B\u00e9trisey Auto-\u00e9cole",
    "wof:placetype":"venue"
},
  "geometry": {"coordinates":[7.5375328064,46.2955436707],"type":"Point"}
}