{
  "type": "Feature",
  "properties": {
    "iso:country":"CH",
    "sg:address":"Claragraben 105 4057 Basel. Postfach",
    "sg:city":"Basel",
    "sg:orig_category":"G\u00fcterbef\u00f6rderung im Strassenverkehr",
    "sg:phone":"+41 61 691 50 60",
    "sg:postcode":"4004",
    "sg:province":"Basel-Stadt",
    "wof:name":"Hanspeter Pauli Camionnage & Transporte",
    "wof:placetype":"venue"
},
  "geometry": {"coordinates":[7.5933427811,47.5632667542],"type":"Point"}
}