{
  "type": "Feature",
  "properties": {
    "iso:country":"CH",
    "sg:address":"Spannerstrasse 31",
    "sg:city":"Frauenfeld",
    "sg:orig_category":"Landesverteidigung, Sozialversicherung \u00d6ffentliche Verwaltung",
    "sg:phone":"+41 52 724 22 64",
    "sg:postcode":"8500",
    "sg:province":"Thurgau",
    "wof:name":"Kantonale Verwaltung Kanton Thurgau",
    "wof:placetype":"venue"
},
  "geometry": {"coordinates":[8.9007301331,47.557975769],"type":"Point"}
}