{
  "type": "Feature",
  "properties": {
    "iso:country":"CH",
    "sg:address":"Route Des Plaines-du-loup 4a 1018 Lausanne. Postfach",
    "sg:city":"Lausanne",
    "sg:orig_category":"Alters U Pflegeheime Wohnheime",
    "sg:phone":"+41 21 641 62 00",
    "sg:postcode":"1018",
    "sg:province":"Vaud",
    "wof:name":"Fondation De L'orme",
    "wof:placetype":"venue"
},
  "geometry": {"coordinates":[6.627842,46.532902],"type":"Point"}
}