{
  "type": "Feature",
  "properties": {
    "iso:country":"CH",
    "sg:address":"Dorfstrasse 32 8248 Uhwiesen. Postfach",
    "sg:city":"Uhwiesen",
    "sg:orig_category":"Erwachsenenbildung U Unterricht",
    "sg:phone":"+41 81 302 28 75",
    "sg:postcode":"8248",
    "sg:province":"Z\u00fcrich",
    "wof:name":"Willy Berghamer-stiftung Bed\u00fcrftige, Hochtalentierte Musikstudente Aus Bad Ragaz; Ausbildung",
    "wof:placetype":"venue"
},
  "geometry": {"coordinates":[9.4958639145,47.0096092224],"type":"Point"}
}