{
  "type": "Feature",
  "properties": {
    "iso:country":"CH",
    "sg:address":"Industriestrasse 18a",
    "sg:city":"Wattwil",
    "sg:orig_category":"Non-Classified Establishments",
    "sg:phone":"+41 71 988 17 18",
    "sg:postcode":"9630",
    "sg:province":"St. Gallen",
    "wof:name":"Gramo Ag",
    "wof:placetype":"venue"
},
  "geometry": {"coordinates":[9.0942115784,47.2921066284],"type":"Point"}
}