{
  "type": "Feature",
  "properties": {
    "iso:country":"CH",
    "sg:address":"Wilerstrasse 12",
    "sg:city":"Oberuzwil",
    "sg:orig_category":"RESTAURANTS: TEA-ROOMS",
    "sg:postcode":"9242",
    "sg:province":"St. Gallen",
    "wof:name":"Erni-b\u00f6sch Kurt",
    "wof:placetype":"venue"
},
  "geometry": {"coordinates":[9.1223573685,47.431186676],"type":"Point"}
}