{
  "type": "Feature",
  "properties": {
    "iso:country":"CH",
    "sg:address":"Bellikonerstrasse 250",
    "sg:city":"Widen",
    "sg:orig_category":"Sanit\u00e4r U Heizungsinstallation Sanit\u00e4rinstallation",
    "sg:phone":"+41 31 747 00 69",
    "sg:postcode":"8967",
    "sg:province":"Aargau",
    "wof:name":"P. Graf & Magnenat Sanit\u00e4re & Heizungen",
    "wof:placetype":"venue"
},
  "geometry": {"coordinates":[7.2406539917,46.9019241333],"type":"Point"}
}