{
  "type": "Feature",
  "properties": {
    "iso:country":"CH",
    "sg:address":"Zinggentorstrasse 4 6006 Luzern. Postfach",
    "sg:city":"Luzern",
    "sg:orig_category":"Sonstige mit Sport verbundene T\u00e4tigkeiten",
    "sg:phone":"+41 91 743 37 29",
    "sg:postcode":"6003",
    "sg:province":"Luzern",
    "wof:name":"Interrace (suisse) Sa",
    "wof:placetype":"venue"
},
  "geometry": {"coordinates":[8.8131160736,46.1837806702],"type":"Point"}
}