{
  "type": "Feature",
  "properties": {
    "iso:country":"CH",
    "sg:address":"Eichenweg 1",
    "sg:city":"Liestal",
    "sg:orig_category":"Autogaragen Autospenglereien",
    "sg:phone":"+41 32 927 31 27",
    "sg:postcode":"4410",
    "sg:province":"Basel-Landschaft",
    "wof:name":"Blanc & Paiche-garages Sa Garages, Atelier De R\u00e9paration, Carrosserie Etc",
    "wof:placetype":"venue"
},
  "geometry": {"coordinates":[6.81159,47.091721],"type":"Point"}
}