{
  "type": "Feature",
  "properties": {
    "iso:country":"CH",
    "sg:address":"Piazza Dante 8",
    "sg:city":"Lugano",
    "sg:classifiers":[
        {
            "category":"Government",
            "subcategory":"Post Office",
            "type":"Public Place"
        }
    ],
    "sg:phone":"+41 91 923 33 07",
    "sg:postcode":"6900",
    "sg:province":"Ticino",
    "sg:tags":[
        "caf\u00e9s",
        "tea-rooms"
    ],
    "wof:name":"Tea-room-pizzeria Vanini",
    "wof:placetype":"venue"
},
  "geometry": {"coordinates":[8.951086998,46.0051116943],"type":"Point"}
}