{
  "type": "Feature",
  "properties": {
    "addr:full":"Sonnhaldestrasse 52b H\u00fcnenberg Zug 6331",
    "addr:housenumber":"52b",
    "addr:postcode":"6331",
    "addr:street":"Sonnhaldestrasse;Huenenberg Zug",
    "iso:country":"CH",
    "sg:address":"Sonnhaldestrasse 52b",
    "sg:city":"H\u00fcnenberg",
    "sg:orig_category":"Allgemeiner Hoch U Tiefbau",
    "sg:postcode":"6331",
    "sg:province":"Zug",
    "wof:name":"A. & B. Generalbau Ag",
    "wof:placetype":"venue"
},
  "geometry": {"coordinates":[8.422583,47.180244],"type":"Point"}
}