{
  "type": "Feature",
  "properties": {
    "iso:country":"CH",
    "sg:address":"Hertizentrum 11",
    "sg:city":"Zug",
    "sg:orig_category":"Sonstige mit der Informatik verbundene T\u00e4tigkeiten",
    "sg:phone":"+41 79 215 67 91",
    "sg:postcode":"6300",
    "sg:province":"Zug",
    "wof:name":"Alsoft Technology Gmbh",
    "wof:placetype":"venue"
},
  "geometry": {"coordinates":[8.5048923492,47.1774559021],"type":"Point"}
}