{
  "type": "Feature",
  "properties": {
    "iso:country":"CH",
    "sg:address":"H\u00f6henstrasse 27 6454 Fl\u00fcelen. Postfach",
    "sg:city":"Fl\u00fcelen",
    "sg:orig_category":"Konkurs- and Betreibungs\u00e4mter",
    "sg:phone":"+41 41 870 30 77",
    "sg:postcode":"6454",
    "sg:province":"Uri",
    "wof:name":"Betreibungsamt",
    "wof:placetype":"venue"
},
  "geometry": {"coordinates":[8.6239643097,46.9117584229],"type":"Point"}
}