{
  "type": "Feature",
  "properties": {
    "addr:full":"Gartenstadtstr. 8 Liebefeld Bern 3097",
    "addr:housenumber":"8",
    "addr:postcode":"3097",
    "addr:street":"Gartenstadtstr.",
    "iso:country":"CH",
    "sg:address":"Gartenstadtstr. 8",
    "sg:city":"Liebefeld",
    "sg:classifiers":[
        {
            "category":"Food & Beverages",
            "subcategory":"Dairy",
            "type":"Retail Goods"
        }
    ],
    "sg:phone":"+41 31 978 31 31",
    "sg:postcode":"3097",
    "sg:province":"Bern",
    "sg:tags":[
        "product",
        "related"
    ],
    "wof:name":"Zingg Ag",
    "wof:placetype":"venue"
},
  "geometry": {"coordinates":[7.411615,46.927361],"type":"Point"}
}