{
  "type": "Feature",
  "properties": {
    "iso:country":"CH",
    "sg:address":"Via San Gottardo",
    "sg:city":"Castione",
    "sg:orig_category":"Autogaragen",
    "sg:phone":"+41 91 829 14 94",
    "sg:postcode":"6532",
    "sg:province":"Ticino",
    "wof:name":"Gaetano Riccioli Garage",
    "wof:placetype":"venue"
},
  "geometry": {"coordinates":[9.042295,46.22567],"type":"Point"}
}