{
  "type": "Feature",
  "properties": {
    "addr:full":"Cresciano Cresciano Ticino 6705",
    "addr:postcode":"6705",
    "iso:country":"CH",
    "sg:address":"Cresciano",
    "sg:city":"Cresciano",
    "sg:classifiers":[
        {
            "category":"Banks & Credit Unions",
            "subcategory":"Bank",
            "type":"Services"
        }
    ],
    "sg:phone":"+41 91 857 35 69",
    "sg:postcode":"6705",
    "sg:province":"Ticino",
    "wof:name":"Banca Raiffeisen Giubiasco E Valle Morobbia",
    "wof:placetype":"venue"
},
  "geometry": {"coordinates":[9.00609,46.176281],"type":"Point"}
}