{
  "type": "Feature",
  "properties": {
    "iso:country":"CH",
    "sg:address":"Flughafenstrasse 8302 Kloten. Postfach 317",
    "sg:city":"Kloten",
    "sg:orig_category":"Non-Classified Establishments",
    "sg:phone":"+41 18001717",
    "sg:postcode":"8302",
    "sg:province":"Z\u00fcrich",
    "wof:name":"Schneider & Cie Ag Internationale Transporte",
    "wof:placetype":"venue"
},
  "geometry": {"coordinates":[8.579870224,47.4535865784],"type":"Point"}
}