{
  "type": "Feature",
  "properties": {
    "iso:country":"CH",
    "sg:address":"Rue Du Temple 4",
    "sg:city":"Moudon",
    "sg:orig_category":"Detailhandel mit B\u00fcchern Detailhandel mit B\u00fcchern, Zeitungen, Schreib U Papeteriewaren",
    "sg:phone":"+41 21 905 12 79",
    "sg:postcode":"1510",
    "sg:province":"Vaud",
    "wof:name":"Librairie Papeterie Moudonnoise Pidoux N.",
    "wof:placetype":"venue"
},
  "geometry": {"coordinates":[6.797489,46.668472],"type":"Point"}
}