{
  "type": "Feature",
  "properties": {
    "iso:country":"CH",
    "sg:address":"4813",
    "sg:city":"Uerkheim",
    "sg:orig_category":"Landesverteidigung, Sozialversicherung \u00d6ffentliche Verwaltung",
    "sg:phone":"+41 62 721 19 54",
    "sg:postcode":"4813",
    "sg:province":"Aargau",
    "wof:name":"Zivilschutzstelle Bottenwil",
    "wof:placetype":"venue"
},
  "geometry": {"coordinates":[8.0247764587,47.3047218323],"type":"Point"}
}