{
  "type": "Feature",
  "properties": {
    "iso:country":"CH",
    "sg:address":"Eterpaz 26 1337 Vallorbe Case Postale",
    "sg:city":"Vallorbe",
    "sg:orig_category":"Sanit\u00e4r, Heizungs U L\u00fcftungsinstallation",
    "sg:postcode":"1337",
    "sg:province":"Vaud",
    "wof:name":"Sabatella Sanitaire",
    "wof:placetype":"venue"
},
  "geometry": {"coordinates":[6.7677898407,46.5281066895],"type":"Point"}
}