{
  "type": "Feature",
  "properties": {
    "iso:country":"CH",
    "sg:address":"Fichtenweg 3a",
    "sg:city":"Bern",
    "sg:orig_category":"Stukkateurgewerbe, Gipserei U Verputzerei",
    "sg:phone":"+41 31 302 61 10",
    "sg:postcode":"3012",
    "sg:province":"Bern",
    "wof:name":"Gipsergesch\u00e4ft Romano Gmbh",
    "wof:placetype":"venue"
},
  "geometry": {"coordinates":[7.4267458916,46.9547042847],"type":"Point"}
}