{
  "type": "Feature",
  "properties": {
    "iso:country":"CH",
    "sg:address":"Beaupr\u00e9",
    "sg:city":"Gy",
    "sg:orig_category":"Verwertung von Milch",
    "sg:postcode":"1251",
    "sg:province":"Gen\u00e8ve",
    "wof:name":"Soci\u00e9t\u00e9 De Laiterie Et D'agriculture De Gy",
    "wof:placetype":"venue"
},
  "geometry": {"coordinates":[6.2532501221,46.2582778931],"type":"Point"}
}