{
  "type": "Feature",
  "properties": {
    "iso:country":"CH",
    "sg:address":"Lindenstrasse 40",
    "sg:city":"R\u00fcmlang",
    "sg:orig_category":"Sonstiges Versicherungsgewerbe",
    "sg:postcode":"8153",
    "sg:province":"Z\u00fcrich",
    "wof:name":"Wagni\u00e8res Paul",
    "wof:placetype":"venue"
},
  "geometry": {"coordinates":[6.8432750702,46.4621353149],"type":"Point"}
}