{
  "type": "Feature",
  "properties": {
    "iso:country":"CH",
    "sg:address":"Av. De Lavaux 67.",
    "sg:city":"Pully",
    "sg:orig_category":"Non-Classified Establishments",
    "sg:postcode":"1009",
    "sg:province":"Vaud",
    "wof:name":"Clavis Stella S.a.",
    "wof:placetype":"venue"
},
  "geometry": {"coordinates":[6.663380146,46.510471344],"type":"Point"}
}