{
  "type": "Feature",
  "properties": {
    "iso:country":"CH",
    "sg:address":"Avenue Bertrand 5",
    "sg:city":"Gen\u00e8ve",
    "sg:orig_category":"Detailhandel mit medizinischen U orthop\u00e4dischen Artikeln",
    "sg:phone":"+41 22 789 57 60",
    "sg:postcode":"1206",
    "sg:province":"Gen\u00e8ve",
    "wof:name":"Denise Furst Medi-furst",
    "wof:placetype":"venue"
},
  "geometry": {"coordinates":[6.1552271843,46.1936531067],"type":"Point"}
}