{
  "type": "Feature",
  "properties": {
    "iso:country":"CH",
    "sg:address":"Industriestrasse 7 6300 Zug. Postfach 1355",
    "sg:city":"Zug",
    "sg:orig_category":"Unternehmensberatung",
    "sg:postcode":"6301",
    "sg:province":"Zug",
    "wof:name":"John R. Stettler Innovative Strategien",
    "wof:placetype":"venue"
},
  "geometry": {"coordinates":[8.5821685791,47.332233429],"type":"Point"}
}