{
  "type": "Feature",
  "properties": {
    "iso:country":"CH",
    "sg:address":"Rue De La Tservetta 24",
    "sg:city":"Sierre",
    "sg:orig_category":"Physiotherapie",
    "sg:phone":"+41 27 456 42 26",
    "sg:postcode":"3960",
    "sg:province":"Valais",
    "wof:name":"Marinette Loretan Physioth\u00e9rapie",
    "wof:placetype":"venue"
},
  "geometry": {"coordinates":[7.5328822136,46.2966804504],"type":"Point"}
}