{
  "type": "Feature",
  "properties": {
    "iso:country":"CH",
    "sg:address":"Kolinplatz 8",
    "sg:city":"Zug",
    "sg:orig_category":"Datenverarbeitungsdienste Softwareentwicklung U beratung",
    "sg:phone":"+41 41 729 88 55",
    "sg:postcode":"6300",
    "sg:province":"Zug",
    "wof:name":"Kneller Informatik Ag",
    "wof:placetype":"venue"
},
  "geometry": {"coordinates":[8.515206,47.166115],"type":"Point"}
}