{
  "type": "Feature",
  "properties": {
    "addr:full":"Heinrich Wehrli-strasse 27 5033 Buchs Ag. Postfach Aarau Aargau 5001",
    "addr:housenumber":"27",
    "addr:postcode":"5033;postfach;5001",
    "addr:street":"Heinrich Wehrli-Strasse",
    "iso:country":"CH",
    "sg:address":"Heinrich Wehrli-strasse 27 5033 Buchs Ag. Postfach",
    "sg:city":"Aarau",
    "sg:orig_category":"Datenverarbeitungsdienste Softwareentwicklung U beratung",
    "sg:phone":"+41 62 822 44 33",
    "sg:postcode":"5001",
    "sg:province":"Aargau",
    "wof:name":"Presida Treuhand Ag Aarau",
    "wof:placetype":"venue"
},
  "geometry": {"coordinates":[8.070473,47.391739],"type":"Point"}
}