{
  "type": "Feature",
  "properties": {
    "iso:country":"CH",
    "sg:address":"Forchstrasse 2 8000 Z\u00fcrich. Postfach",
    "sg:city":"Z\u00fcrich",
    "sg:orig_category":"Architektur U Ingenieurb\u00fcros",
    "sg:postcode":"8008",
    "sg:province":"Z\u00fcrich",
    "wof:name":"Cultural Backup Service Ag",
    "wof:placetype":"venue"
},
  "geometry": {"coordinates":[8.554772,47.364464],"type":"Point"}
}