{
  "type": "Feature",
  "properties": {
    "iso:country":"CH",
    "sg:address":"Feldstrasse 7",
    "sg:city":"B\u00fctzberg",
    "sg:orig_category":"Herstellung von Werkzeugmaschinen",
    "sg:phone":"+41 62 963 28 36",
    "sg:postcode":"4922",
    "sg:province":"Bern",
    "wof:name":"M\u00fchlheim Ren\u00e9, Elektrowerkzeuge",
    "wof:placetype":"venue"
},
  "geometry": {"coordinates":[7.739235878,47.2125663757],"type":"Point"}
}