{
  "type": "Feature",
  "properties": {
    "iso:country":"CH",
    "sg:address":"Route De Reculan 2 1030 Bussigny-lausanne Case Postale 197",
    "sg:city":"Bussigny-lausanne",
    "sg:orig_category":"Bauingenieurb\u00fcros allgemein",
    "sg:phone":"+41 21 701 17 81",
    "sg:postcode":"1030",
    "sg:province":"Vaud",
    "wof:name":"Gcba Sa Bureau D'ing\u00e9nieurs",
    "wof:placetype":"venue"
},
  "geometry": {"coordinates":[6.552985,46.542908],"type":"Point"}
}