{
  "type": "Feature",
  "properties": {
    "iso:country":"CH",
    "sg:address":"Furkastrasse 3988 Ulrichen. Postfach",
    "sg:city":"Ulrichen",
    "sg:orig_category":"Detailhandel mit Bekleidung Kleiderboutiquen",
    "sg:phone":"+41 33 951 73 77",
    "sg:postcode":"3988",
    "sg:province":"Valais",
    "wof:name":"Mode Sunshine, Luchs Modegesch\u00e4ft. Waren; Handel",
    "wof:placetype":"venue"
},
  "geometry": {"coordinates":[8.026766,46.755569],"type":"Point"}
}