{
  "type": "Feature",
  "properties": {
    "iso:country":"CH",
    "sg:address":"S\u00f6mmerlistrasse 14",
    "sg:city":"St.gallen",
    "sg:orig_category":"G\u00fcterbef\u00f6rderung im Strassenverkehr",
    "sg:phone":"+41 71 278 55 75",
    "sg:postcode":"9000",
    "sg:province":"St. Gallen",
    "wof:name":"Guido Enderli Transport Gmbh",
    "wof:placetype":"venue"
},
  "geometry": {"coordinates":[9.3510398865,47.4196510315],"type":"Point"}
}