{
  "type": "Feature",
  "properties": {
    "iso:country":"CH",
    "sg:address":"Schachengasse 7",
    "sg:city":"Schattdorf",
    "sg:orig_category":"D\u00e4mmung gegen K\u00e4lte, W\u00e4rme, Schall U Ersch\u00fctterung",
    "sg:phone":"+41 41 870 64 30",
    "sg:postcode":"6467",
    "sg:province":"Uri",
    "wof:name":"Nieder\u00f6st A. Ag",
    "wof:placetype":"venue"
},
  "geometry": {"coordinates":[8.6454029083,46.8518295288],"type":"Point"}
}