{
  "type": "Feature",
  "properties": {
    "addr:full":"Z\u00fcrcherstrasse 48 Dietikon Z\u00fcrich 8953",
    "addr:housenumber":"48",
    "addr:postcode":"8953",
    "addr:street":"Zuercherstrasse",
    "iso:country":"CH",
    "sg:address":"Z\u00fcrcherstrasse 48",
    "sg:city":"Dietikon",
    "sg:orig_category":"Chiropraktik",
    "sg:phone":"+41 17415757",
    "sg:postcode":"8953",
    "sg:province":"Z\u00fcrich",
    "wof:name":"Dr.matthias Naef Chiropraktor",
    "wof:placetype":"venue"
},
  "geometry": {"coordinates":[8.403243,47.404076],"type":"Point"}
}