{
  "type": "Feature",
  "properties": {
    "iso:country":"CH",
    "sg:address":"Pal.arredorama Via Cantonale 2",
    "sg:city":"Barbengo",
    "sg:classifiers":[
        {
            "category":"Bars & Pubs",
            "type":"Food & Drink"
        }
    ],
    "sg:phone":"+41 91 993 33 95",
    "sg:postcode":"6917",
    "sg:province":"Ticino",
    "wof:name":"Bar Eclisse",
    "wof:placetype":"venue"
},
  "geometry": {"coordinates":[8.925066,45.966976],"type":"Point"}
}