{
  "type": "Feature",
  "properties": {
    "addr:full":"Z\u00fcrcherstrasse 205 Frauenfeld Thurgau 8500",
    "addr:housenumber":"205",
    "addr:postcode":"8500",
    "addr:street":"Zuercherstrasse",
    "iso:country":"CH",
    "sg:address":"Z\u00fcrcherstrasse 205",
    "sg:city":"Frauenfeld",
    "sg:orig_category":"Detailhandel mit Brot, Back U S\u00fcsswaren",
    "sg:phone":"+41 52 721 12 43",
    "sg:postcode":"8500",
    "sg:province":"Thurgau",
    "wof:name":"Holzofen B\u00e4ckerei Vorstadt Ag",
    "wof:placetype":"venue"
},
  "geometry": {"coordinates":[8.899505,47.558067],"type":"Point"}
}