{
  "type": "Feature",
  "properties": {
    "iso:country":"CH",
    "sg:address":"Im Geissacker 61 8404 Oberwinterthur. Postfach",
    "sg:city":"Winterthur",
    "sg:orig_category":"Mechanik",
    "sg:phone":"+41 52 242 18 29",
    "sg:postcode":"8404",
    "sg:province":"Z\u00fcrich",
    "wof:name":"Eva Sluch",
    "wof:placetype":"venue"
},
  "geometry": {"coordinates":[8.7553567886,47.5147590637],"type":"Point"}
}