{
  "type": "Feature",
  "properties": {
    "iso:country":"CH",
    "sg:address":"Wachtmeistergasse 2",
    "sg:city":"Frutigen",
    "sg:orig_category":"D\u00e9colletagen and Schrauben Herstellung Mechanische Werkst\u00e4tten",
    "sg:phone":"+41 33 671 39 71",
    "sg:postcode":"3714",
    "sg:province":"Bern",
    "wof:name":"Moser Mechanik",
    "wof:placetype":"venue"
},
  "geometry": {"coordinates":[7.6431698799,46.5884284973],"type":"Point"}
}