{
  "type": "Feature",
  "properties": {
    "iso:country":"CH",
    "sg:address":"Landstrasse 29",
    "sg:city":"Wettingen",
    "sg:orig_category":"Detailhandel mit Waren verschiedener Art, Hauptrichtung Nahrungsmittel Grosshandel mit Nahrungsmitte",
    "sg:phone":"+41 56 426 48 22",
    "sg:postcode":"5430",
    "sg:province":"Aargau",
    "wof:name":"Frei K. Lebensmittel.",
    "wof:placetype":"venue"
},
  "geometry": {"coordinates":[8.3200187683,47.4688987732],"type":"Point"}
}