{
  "type": "Feature",
  "properties": {
    "iso:country":"CH",
    "sg:address":"Gewerbestrasse 27",
    "sg:city":"Bellach",
    "sg:orig_category":"Instandhaltung U Reparatur von Automobilen",
    "sg:phone":"+41 32 618 35 35",
    "sg:postcode":"4512",
    "sg:province":"Solothurn",
    "wof:name":"Mohamed Mekaouar Autowaschstrasse",
    "wof:placetype":"venue"
},
  "geometry": {"coordinates":[7.4930348396,47.2097244263],"type":"Point"}
}