{
  "type": "Feature",
  "properties": {
    "iso:country":"CH",
    "sg:address":"Badenerstrasse 400 8004 Z\u00fcrich. Postfach",
    "sg:city":"Z\u00fcrich",
    "sg:orig_category":"Pensionskassen",
    "sg:phone":"+41 71 274 88 66",
    "sg:postcode":"8001",
    "sg:province":"Z\u00fcrich",
    "wof:name":"Personal-f\u00fcrsorgestiftung Der Huber Und Monsch Ag",
    "wof:placetype":"venue"
},
  "geometry": {"coordinates":[9.3462257385,47.4120941162],"type":"Point"}
}