{
  "type": "Feature",
  "properties": {
    "iso:country":"CH",
    "sg:address":"Bahnhofstrasse 33",
    "sg:city":"Nebikon",
    "sg:orig_category":"Herstellung von Holzstoff, Papier, Karton U Pappe Herstellung von sonstigen Waren aus Papier, Karton",
    "sg:phone":"+41 17614411",
    "sg:postcode":"6244",
    "sg:province":"Luzern",
    "wof:name":"Bawarel Ag",
    "wof:placetype":"venue"
},
  "geometry": {"coordinates":[8.4404354095,47.2727775574],"type":"Point"}
}