{
  "type": "Feature",
  "properties": {
    "iso:country":"CH",
    "sg:address":"Bahnhofstrasse 21 6285 Hitzkirch. Postfach 161",
    "sg:city":"Hitzkirch",
    "sg:orig_category":"Detailhandel mit M\u00f6beln Innendekorationsateliers",
    "sg:postcode":"6285",
    "sg:province":"Luzern",
    "wof:name":"Wohn-center R\u00e4ber Ag",
    "wof:placetype":"venue"
},
  "geometry": {"coordinates":[8.2588338852,47.2237968445],"type":"Point"}
}