{
  "type": "Feature",
  "properties": {
    "iso:country":"CH",
    "sg:address":"Alter Schulweg 36 B",
    "sg:city":"Rupperswil",
    "sg:orig_category":"Erschliessung von Grundst\u00fccken",
    "sg:postcode":"5102",
    "sg:province":"Aargau",
    "wof:name":"Baugenossenschaft Alte Spinnerei Rupperswil",
    "wof:placetype":"venue"
},
  "geometry": {"coordinates":[8.1308097839,47.4034309387],"type":"Point"}
}