{
  "type": "Feature",
  "properties": {
    "iso:country":"CH",
    "sg:address":"Station",
    "sg:city":"Versam",
    "sg:orig_category":"Sonstige mit Sport verbundene T\u00e4tigkeiten",
    "sg:phone":"+41 81 645 13 24",
    "sg:postcode":"7104",
    "sg:province":"Graubunden",
    "wof:name":"Kanuschule Versam Steinmann, Fellmann, Keller, Rogenmoser, Zurbr\u00fcgg-greenaway",
    "wof:placetype":"venue"
},
  "geometry": {"coordinates":[9.3364896774,46.792640686],"type":"Point"}
}