{
  "type": "Feature",
  "properties": {
    "iso:country":"CH",
    "sg:address":"Bahnhofstrasse 3",
    "sg:city":"Ins",
    "sg:orig_category":"RESTAURANTS: TEA-ROOMS",
    "sg:phone":"+41 32 313 15 15",
    "sg:postcode":"3232",
    "sg:province":"Bern",
    "wof:name":"Binggeli Hans Ulrich",
    "wof:placetype":"venue"
},
  "geometry": {"coordinates":[7.1046638489,47.0059051514],"type":"Point"}
}