{
  "type": "Feature",
  "properties": {
    "iso:country":"CH",
    "sg:address":"Bahnhofstrasse 17",
    "sg:city":"Herisau",
    "sg:orig_category":"RESTAURANTS: TEA-ROOMS",
    "sg:phone":"+41 71 351 13 33",
    "sg:postcode":"9100",
    "sg:province":"Appenzell Ausserrhoden",
    "wof:name":"Pizzeria Pomodoro Gmbh",
    "wof:placetype":"venue"
},
  "geometry": {"coordinates":[9.2773151398,47.387348175],"type":"Point"}
}