{
  "type": "Feature",
  "properties": {
    "iso:country":"CH",
    "sg:address":"Ettenbergstrasse 267",
    "sg:city":"Schwarzsee",
    "sg:classifiers":[
        {
            "category":"Restaurant",
            "type":"Food & Drink"
        }
    ],
    "sg:phone":"+41 26 412 13 30",
    "sg:postcode":"1711",
    "wof:name":"Restaurant M\u00f6sli",
    "wof:placetype":"venue"
},
  "geometry": {"coordinates":[7.2838859558,46.6706886292],"type":"Point"}
}