{
  "type": "Feature",
  "properties": {
    "iso:country":"CH",
    "sg:address":"In Der Grand-strasse 5",
    "sg:city":"Zumikon",
    "sg:orig_category":"Allgemeiner Hoch U Tiefbau",
    "sg:phone":"+41 19181608",
    "sg:postcode":"8126",
    "sg:province":"Z\u00fcrich",
    "wof:name":"Wilczek Nikolaus, Dipl. Ing. Eth/sia, Baukom, Baubegleitung Und Kommunikation",
    "wof:placetype":"venue"
},
  "geometry": {"coordinates":[8.626091,47.33007],"type":"Point"}
}