{
  "type": "Feature",
  "properties": {
    "iso:country":"CH",
    "sg:address":"Rue Du Four 7",
    "sg:city":"Yverdon-les-bains",
    "sg:orig_category":"Advokaturb\u00fcros",
    "sg:phone":"+41 52 365 11 41",
    "sg:postcode":"1400",
    "sg:province":"Vaud",
    "wof:name":"Strehler & Epper Advokaturb\u00fcro",
    "wof:placetype":"venue"
},
  "geometry": {"coordinates":[8.900662,47.477913],"type":"Point"}
}