{
  "type": "Feature",
  "properties": {
    "iso:country":"CH",
    "sg:address":"9000",
    "sg:city":"St.gallen",
    "sg:orig_category":"Pensionskassen",
    "sg:phone":"+41 71 626 61 11",
    "sg:postcode":"9000",
    "sg:province":"St. Gallen",
    "wof:name":"Vorsorgestiftung Sparen 3 Der Thurgauer Kantonalbank",
    "wof:placetype":"venue"
},
  "geometry": {"coordinates":[9.138185,47.566669],"type":"Point"}
}