{
  "type": "Feature",
  "properties": {
    "iso:country":"CH",
    "sg:address":"Blumenbergstrasse 50 3013 Bern. Postfach",
    "sg:city":"Bern",
    "sg:orig_category":"Maler U Glasergewerbe",
    "sg:phone":"+41 31 332 87 81",
    "sg:postcode":"3005",
    "sg:province":"Bern",
    "wof:name":"Aebersold Hans-rudolf Malergesch\u00e4ft",
    "wof:placetype":"venue"
},
  "geometry": {"coordinates":[7.4568400383,46.9568328857],"type":"Point"}
}