{
  "type": "Feature",
  "properties": {
    "iso:country":"CH",
    "sg:address":"Sonnenweg 7",
    "sg:city":"Otelfingen",
    "sg:orig_category":"Sportvereine Wassersport Rudern",
    "sg:postcode":"8112",
    "sg:province":"Z\u00fcrich",
    "wof:name":"Ruder-club Blauweiss Basel",
    "wof:placetype":"venue"
},
  "geometry": {"coordinates":[8.3891830444,47.4656028748],"type":"Point"}
}