{
  "type": "Feature",
  "properties": {
    "iso:country":"CH",
    "sg:address":"Rue De Zaehringen 7 1700 Fribourg Case Postale 43",
    "sg:city":"Fribourg",
    "sg:orig_category":"Detailhandel mit Computern U Software Softwareentwicklung U beratung",
    "sg:phone":"+41 26 322 57 07",
    "sg:postcode":"1702",
    "sg:province":"Fribourg",
    "wof:name":"Bti Bit Tech Informatics Sa",
    "wof:placetype":"venue"
},
  "geometry": {"coordinates":[7.165363,46.805389],"type":"Point"}
}