{
  "type": "Feature",
  "properties": {
    "iso:country":"CH",
    "sg:address":"Monbijoustrasse 6 3011 Bern. Postfach",
    "sg:city":"Bern",
    "sg:orig_category":"Non-Classified Establishments",
    "sg:postcode":"3001",
    "sg:province":"Bern",
    "wof:name":"Matthias Fritz Gfeller Geodata Raumplanung",
    "wof:placetype":"venue"
},
  "geometry": {"coordinates":[8.8316926956,47.2311439514],"type":"Point"}
}