{
  "type": "Feature",
  "properties": {
    "iso:country":"CH",
    "sg:address":"Kirchweg 80 8750 Glarus. Postfach",
    "sg:city":"Glarus",
    "sg:orig_category":"Architektur U Ingenieurb\u00fcros",
    "sg:phone":"+41 55 240 87 27",
    "sg:postcode":"8750",
    "sg:province":"Glarus",
    "wof:name":"Aschwanden & Partner Ingenieure Und Planer Eth/sia Ag",
    "wof:placetype":"venue"
},
  "geometry": {"coordinates":[8.848832,47.258869],"type":"Point"}
}