{
  "type": "Feature",
  "properties": {
    "iso:country":"CH",
    "sg:address":"Rorschacher Strasse 25",
    "sg:city":"St.gallen",
    "sg:orig_category":"Erwachsenenbildung U Unterricht",
    "sg:phone":"+41 71 224 59 59",
    "sg:postcode":"9000",
    "sg:province":"St. Gallen",
    "wof:name":"Musikakademie St. Gallen, H\u00f6here Fachschule F\u00fcr Musik",
    "wof:placetype":"venue"
},
  "geometry": {"coordinates":[9.3811635971,47.4264945984],"type":"Point"}
}