{
  "type": "Feature",
  "properties": {
    "iso:country":"CH",
    "sg:address":"Musigweg 10",
    "sg:city":"Gansingen",
    "sg:orig_category":"Hundesalons",
    "sg:phone":"+41 62 875 00 82",
    "sg:postcode":"5272",
    "sg:province":"Aargau",
    "wof:name":"Agnes Rau Bijou",
    "wof:placetype":"venue"
},
  "geometry": {"coordinates":[8.1365661621,47.5437431335],"type":"Point"}
}