{
  "type": "Feature",
  "properties": {
    "iso:country":"CH",
    "sg:address":"Wiler",
    "sg:city":"Innertkirchen",
    "sg:orig_category":"Campingpl\u00e4tze Detailhandel Reparatur von Gebrauchsg\u00fctern",
    "sg:phone":"+41 33 971 14 27",
    "sg:postcode":"3862",
    "sg:province":"Bern",
    "wof:name":"Camping Wyler Adrian Th\u00f6ni",
    "wof:placetype":"venue"
},
  "geometry": {"coordinates":[8.240407,46.708565],"type":"Point"}
}