{
  "type": "Feature",
  "properties": {
    "iso:country":"CH",
    "sg:address":"Strada Principale",
    "sg:city":"Besazio",
    "sg:orig_category":"Grosshandel mit Bekleidung",
    "sg:phone":"+41 91 646 01 56",
    "sg:postcode":"6863",
    "sg:province":"Ticino",
    "wof:name":"Bentex Production Sa Commercio Di Abbigliamento",
    "wof:placetype":"venue"
},
  "geometry": {"coordinates":[8.9523448944,45.8734092712],"type":"Point"}
}