{
  "type": "Feature",
  "properties": {
    "iso:country":"CH",
    "sg:address":"St. Martinistrasse 2 3930 Visp. Postfach",
    "sg:city":"Visp",
    "sg:orig_category":"Restaurants Verwaltung von Immobilien",
    "sg:phone":"+41 27 946 22 65",
    "sg:postcode":"3930",
    "sg:province":"Valais",
    "wof:name":"Wiwanni Ag",
    "wof:placetype":"venue"
},
  "geometry": {"coordinates":[7.8814191818,46.2904548645],"type":"Point"}
}