{
  "type": "Feature",
  "properties": {
    "iso:country":"CH",
    "sg:address":"Rue L\u00e9on-michaud 3",
    "sg:city":"Yverdon-les-bains",
    "sg:orig_category":"Bezirks, Sekundar, Realschulen, Oberstufe der Primarschulen",
    "sg:phone":"+41 24 423 64 60",
    "sg:postcode":"1400",
    "sg:province":"Vaud",
    "wof:name":"Ecole Secondaire Coll\u00e8ge L\u00e9on-michaud",
    "wof:placetype":"venue"
},
  "geometry": {"coordinates":[6.635728,46.774715],"type":"Point"}
}