{
  "type": "Feature",
  "properties": {
    "addr:full":"Schloss-strasse 77 Oensingen Solothurn 4702",
    "addr:housenumber":"77",
    "addr:postcode":"4702",
    "addr:street":"Schloss-Strasse",
    "iso:country":"CH",
    "sg:address":"Schloss-strasse 77",
    "sg:city":"Oensingen",
    "sg:orig_category":"Detailhandel mit Damenbekleidung Detailhandel mit Herrenbekleidung",
    "sg:phone":"+41 32 682 19 70",
    "sg:postcode":"4702",
    "sg:province":"Solothurn",
    "wof:name":"Boutique Sancho A.h\u00e4nni Mode & Dessous F\u00fcr Sie & Ihn",
    "wof:placetype":"venue"
},
  "geometry": {"coordinates":[7.722079,47.294189],"type":"Point"}
}