{
  "type": "Feature",
  "properties": {
    "iso:country":"CH",
    "sg:address":"Freibachstrasse 24b 9424 Rheineck. Postfach",
    "sg:city":"Rheineck",
    "sg:orig_category":"Detailhandel mit Textilien Herstellung von konfektionierten Textilwaren ohne Bekleidung",
    "sg:phone":"+41 71 886 99 44",
    "sg:postcode":"9424",
    "sg:province":"St. Gallen",
    "wof:name":"Siag-heimtextilien Ag",
    "wof:placetype":"venue"
},
  "geometry": {"coordinates":[9.5823888779,47.468585968],"type":"Point"}
}