{
  "type": "Feature",
  "properties": {
    "iso:country":"CH",
    "sg:address":"Ringstr. 5",
    "sg:city":"Port",
    "sg:orig_category":"Pensionskassen",
    "sg:postcode":"2562",
    "sg:province":"Bern",
    "wof:name":"Personalf\u00fcrsorgestiftung Der Firma Strama, Staumann + Matter Ag",
    "wof:placetype":"venue"
},
  "geometry": {"coordinates":[7.2513699532,47.1225242615],"type":"Point"}
}