{
  "type": "Feature",
  "properties": {
    "iso:country":"CH",
    "sg:address":"Eiweg 12",
    "sg:city":"Gelterkinden",
    "sg:orig_category":"Sonstiger spezialisierter Hoch U Tiefbau",
    "sg:phone":"+41 61 981 30 06",
    "sg:postcode":"4460",
    "sg:province":"Basel-Landschaft",
    "wof:name":"Paul Fiechter Ag",
    "wof:placetype":"venue"
},
  "geometry": {"coordinates":[7.844274044,47.4658088684],"type":"Point"}
}