{
  "type": "Feature",
  "properties": {
    "iso:country":"CH",
    "sg:address":"Rue Thomas-wyttenbach 2",
    "sg:city":"Biel/bienne",
    "sg:classifiers":[
        {
            "category":"Shopping",
            "subcategory":"Jewelry",
            "type":"Retail Goods"
        }
    ],
    "sg:phone":"+41 32 329 40 00",
    "sg:postcode":"2502",
    "sg:province":"Bern",
    "sg:tags":[
        "watch"
    ],
    "wof:name":"Rama Watch Sa",
    "wof:placetype":"venue"
},
  "geometry": {"coordinates":[7.2445168495,47.1334342957],"type":"Point"}
}