{
  "type": "Feature",
  "properties": {
    "iso:country":"CH",
    "sg:address":"Grubenstrasse 7",
    "sg:city":"Spreitenbach",
    "sg:orig_category":"Handel mit Automobilen",
    "sg:postcode":"8957",
    "sg:province":"Aargau",
    "wof:name":"Autopark Asp, M. Lamberti & Ch. Zweifel",
    "wof:placetype":"venue"
},
  "geometry": {"coordinates":[8.3823766708,47.4148292542],"type":"Point"}
}