{
  "type": "Feature",
  "properties": {
    "iso:country":"CH",
    "sg:address":"Rue De Maillefer 11d",
    "sg:city":"Neuch\u00e2tel",
    "sg:classifiers":[
        {
            "category":"Manufacturing",
            "subcategory":"Motor Vehicles & Parts",
            "type":"Manufacturing & Wholesale Goods"
        }
    ],
    "sg:phone":"+41 32 731 28 88",
    "sg:postcode":"2000",
    "sg:province":"Neuch\u00e2tel",
    "sg:tags":[
        "precision",
        "mechanic"
    ],
    "wof:name":"Ab Technique Sa",
    "wof:placetype":"venue"
},
  "geometry": {"coordinates":[6.9064540863,46.9841156006],"type":"Point"}
}