{
  "type": "Feature",
  "properties": {
    "iso:country":"CH",
    "sg:address":"St. Gallerstrasse 35",
    "sg:city":"Tuggen",
    "sg:orig_category":"Hoch U Tiefbau",
    "sg:phone":"+41 55 445 18 87",
    "sg:postcode":"8856",
    "sg:province":"Schwyz",
    "wof:name":"Anton Bommer Baugesch\u00e4ft",
    "wof:placetype":"venue"
},
  "geometry": {"coordinates":[8.9468955994,47.2037277222],"type":"Point"}
}