{
  "type": "Feature",
  "properties": {
    "iso:country":"CH",
    "sg:address":"En Budron E7 1052 Mont-sur-lausanne Case Postale 287",
    "sg:city":"Mont-sur-lausanne",
    "sg:orig_category":"Grosshandel mit Nahrungsmitteln, Getr\u00e4nken U Tabakwaren",
    "sg:phone":"+41 61 461 42 24",
    "sg:postcode":"1052",
    "sg:province":"Vaud",
    "wof:name":"Zeltra Bruno Zeller Lebensmittelgrosshandel",
    "wof:placetype":"venue"
},
  "geometry": {"coordinates":[7.6472978592,47.5281486511],"type":"Point"}
}