{
  "type": "Feature",
  "properties": {
    "iso:country":"CH",
    "sg:address":"Zollstrasse 80",
    "sg:city":"Schaan",
    "sg:orig_category":"Fahrschulen, Flugschulen",
    "sg:phone":"+41 75 232 76 75",
    "sg:postcode":"9494",
    "wof:name":"Reto Carisch Autofahrschule",
    "wof:placetype":"venue"
},
  "geometry": {"coordinates":[9.4975748062,47.1694107056],"type":"Point"}
}