{
  "type": "Feature",
  "properties": {
    "iso:country":"CH",
    "sg:address":"Belalpstrasse 4",
    "sg:city":"Naters",
    "sg:classifiers":[
        {
            "category":"Restaurant",
            "type":"Food & Drink"
        }
    ],
    "sg:phone":"+41 26 322 31 95",
    "sg:postcode":"3904",
    "sg:province":"Valais",
    "sg:tags":[
        "tea-rooms",
        "restaurants"
    ],
    "wof:name":"Suard No\u00eblle, Tea-room Capri",
    "wof:placetype":"venue"
},
  "geometry": {"coordinates":[7.9869837761,46.3246612549],"type":"Point"}
}