{
  "type": "Feature",
  "properties": {
    "iso:country":"CH",
    "sg:address":"Unterdorfstrasse 9",
    "sg:city":"Sch\u00f6nb\u00fchl-urtenen",
    "sg:orig_category":"Unternehmensberatung",
    "sg:phone":"+41 31 852 06 01",
    "sg:postcode":"3322",
    "sg:province":"Bern",
    "wof:name":"Wab Werbe Ag",
    "wof:placetype":"venue"
},
  "geometry": {"coordinates":[7.5042490959,47.0272407532],"type":"Point"}
}