{
  "type": "Feature",
  "properties": {
    "iso:country":"CH",
    "sg:address":"Breitenstrasse 6",
    "sg:city":"Altendorf",
    "sg:orig_category":"Detailhandel mit Teppichen Verlegen von Fussboden",
    "sg:phone":"+41 55 462 15 01",
    "sg:postcode":"8852",
    "sg:province":"Schwyz",
    "wof:name":"Hansj\u00f6rg F\u00e4h Ag Teppiche Parkett Bodenbel\u00e4ge",
    "wof:placetype":"venue"
},
  "geometry": {"coordinates":[8.847278595,47.185585022],"type":"Point"}
}