{
  "type": "Feature",
  "properties": {
    "addr:full":"Schwendistrasse 5 M\u00fcselbach St. Gallen 9602",
    "addr:housenumber":"5;st.",
    "addr:postcode":"9602",
    "addr:street":"Schwendistrasse",
    "iso:country":"CH",
    "sg:address":"Schwendistrasse 5",
    "sg:city":"M\u00fcselbach",
    "sg:classifiers":[
        {
            "category":"Banks & Credit Unions",
            "subcategory":"Bank",
            "type":"Services"
        }
    ],
    "sg:phone":"+41 4173313907",
    "sg:postcode":"9602",
    "sg:province":"St. Gallen",
    "wof:name":"Schweiz. Mobiliar",
    "wof:placetype":"venue"
},
  "geometry": {"coordinates":[9.040719,47.392025],"type":"Point"}
}