{
  "type": "Feature",
  "properties": {
    "iso:country":"CH",
    "sg:address":"C\u00e9r\u00e8ce Route De La 2 1092 Belmont-lausanne. Postfach",
    "sg:city":"Belmont-lausanne",
    "sg:orig_category":"R\u00fcckgewinnung U Vorbereitung f\u00fcr die Wiederverwertung Recycling von nichtmetallischen Altmaterialien",
    "sg:phone":"+41 21 784 27 12",
    "sg:postcode":"1092",
    "sg:province":"Vaud",
    "wof:name":"Eco Cert S\u00e0rl Conseil En Gestion De D\u00e9chets, \u00e9tude De Faisabilit\u00e9 Etc",
    "wof:placetype":"venue"
},
  "geometry": {"coordinates":[6.6782422066,46.519859314],"type":"Point"}
}