{
  "type": "Feature",
  "properties": {
    "iso:country":"CH",
    "sg:address":"Sch\u00fctzlerweg 3 8560 M\u00e4rstetten. Postfach 271",
    "sg:city":"M\u00e4rstetten",
    "sg:orig_category":"Offsetdruck Sonstiger Druck",
    "sg:phone":"+41 71 658 61 61",
    "sg:postcode":"8560",
    "sg:province":"Thurgau",
    "wof:name":"Druckerei Hess",
    "wof:placetype":"venue"
},
  "geometry": {"coordinates":[9.06537,47.589535],"type":"Point"}
}