{
  "type": "Feature",
  "properties": {
    "iso:country":"CH",
    "sg:address":"Leutschenbachstrasse 95",
    "sg:city":"Z\u00fcrich",
    "sg:orig_category":"Softwareentwicklung U beratung",
    "sg:postcode":"8000",
    "sg:province":"Z\u00fcrich",
    "wof:name":"E3 Ag Soft, Hardware Usw.; Entwicklung, Vermarktung, Handel",
    "wof:placetype":"venue"
},
  "geometry": {"coordinates":[8.4562854767,47.3696937561],"type":"Point"}
}