{
  "type": "Feature",
  "properties": {
    "iso:country":"CH",
    "sg:address":"Im Grund",
    "sg:city":"Salenstein",
    "sg:orig_category":"Primarschulen",
    "sg:phone":"+41 807 232 121",
    "sg:postcode":"8268",
    "sg:province":"Thurgau",
    "wof:name":"Primarschule Salenstein",
    "wof:placetype":"venue"
},
  "geometry": {"coordinates":[9.0602197647,47.6672363281],"type":"Point"}
}