{
  "type": "Feature",
  "properties": {
    "iso:country":"CH",
    "sg:address":"Untere Rebgasse 7",
    "sg:city":"Basel",
    "sg:classifiers":[
        {
            "category":"Banks & Credit Unions",
            "subcategory":"Bank",
            "type":"Services"
        }
    ],
    "sg:phone":"+41 4161297211",
    "sg:postcode":"4005",
    "sg:province":"Basel-Stadt",
    "wof:name":"Cr\u00e9dit Suisse",
    "wof:placetype":"venue"
},
  "geometry": {"coordinates":[7.592859,47.561756],"type":"Point"}
}