{
  "type": "Feature",
  "properties": {
    "iso:country":"CH",
    "sg:address":"Z.i.ouest Rte Des Artisans 10",
    "sg:city":"Avenches",
    "sg:orig_category":"Grosshandel mit Wein U Spirituosen Grosshandel mit sonstigen Getr\u00e4nken",
    "sg:phone":"+41 26 675 15 81",
    "sg:postcode":"1580",
    "sg:province":"Vaud",
    "wof:name":"La Cave Romaine Sa Boissons; Comm. Etc",
    "wof:placetype":"venue"
},
  "geometry": {"coordinates":[7.0407848358,46.8800582886],"type":"Point"}
}