{
  "type": "Feature",
  "properties": {
    "iso:country":"CH",
    "sg:address":"Weidstrasse 16",
    "sg:city":"Diepoldsau",
    "sg:orig_category":"Herstellung von konfektionierten Textilwaren ohne Bekleidung",
    "sg:phone":"+41 71 733 17 73",
    "sg:postcode":"9444",
    "sg:province":"St. Gallen",
    "wof:name":"Heimtextilien Fini Hutter-scherer",
    "wof:placetype":"venue"
},
  "geometry": {"coordinates":[9.6648740768,47.3844032288],"type":"Point"}
}