{
  "type": "Feature",
  "properties": {
    "iso:country":"CH",
    "sg:address":"Avenue Des Figuiers 37",
    "sg:city":"Lausanne",
    "sg:orig_category":"Instandhaltung U Reparatur von Automobilen",
    "sg:postcode":"1007",
    "sg:province":"Vaud",
    "wof:name":"Du Mecc Di Dubach Ueli",
    "wof:placetype":"venue"
},
  "geometry": {"coordinates":[9.0061903,45.8562393188],"type":"Point"}
}