{
  "type": "Feature",
  "properties": {
    "iso:country":"CH",
    "sg:address":"Rue De La Tillette 1145 Bi\u00e8re. Postfach",
    "sg:city":"Bi\u00e8re",
    "sg:classifiers":[
        {
            "category":"Travel",
            "subcategory":"Hotels & Motels",
            "type":"Entertainment"
        }
    ],
    "sg:postcode":"1145",
    "sg:province":"Vaud",
    "sg:tags":[
        "hotels",
        "mit",
        "restaurant"
    ],
    "wof:name":"Urfer Didier H\u00f4tel-caf\u00e9-restaurant Etc",
    "wof:placetype":"venue"
},
  "geometry": {"coordinates":[6.3332748413,46.5371246338],"type":"Point"}
}