{
  "type": "Feature",
  "properties": {
    "iso:country":"CH",
    "sg:address":"Alter Postplatz 2 6370 Stans. Postfach 6361",
    "sg:city":"Stans",
    "sg:orig_category":"Vermietung U Verpachtung von eigenen Immobilien Vermittlung von Immobilien",
    "sg:phone":"+41 41 610 57 57",
    "sg:postcode":"6370",
    "sg:province":"Nidwalden",
    "wof:name":"Hm Immobilien Ag",
    "wof:placetype":"venue"
},
  "geometry": {"coordinates":[8.3658685684,46.9577560425],"type":"Point"}
}