{
  "type": "Feature",
  "properties": {
    "iso:country":"CH",
    "sg:address":"Avenue Du Parc-de-la-rouvraie 4",
    "sg:city":"Lausanne",
    "sg:orig_category":"Herstellung von sonstigen M\u00f6beln",
    "sg:postcode":"1003",
    "sg:province":"Vaud",
    "wof:name":"Reliure Rouiller R.",
    "wof:placetype":"venue"
},
  "geometry": {"coordinates":[6.6332230568,46.531791687],"type":"Point"}
}