{
  "type": "Feature",
  "properties": {
    "iso:country":"CH",
    "sg:address":"Albisstrasse 116",
    "sg:city":"Z\u00fcrich",
    "sg:classifiers":[
        {
            "category":"Home & Garden",
            "subcategory":"Building Materials",
            "type":"Retail Goods"
        }
    ],
    "sg:phone":"+41 14800057",
    "sg:postcode":"8038",
    "sg:province":"Z\u00fcrich",
    "sg:tags":[
        "installation",
        "electric"
    ],
    "wof:name":"Elor Gmbh",
    "wof:placetype":"venue"
},
  "geometry": {"coordinates":[8.5298299789,47.3275642395],"type":"Point"}
}