{
  "type": "Feature",
  "properties": {
    "iso:country":"CH",
    "sg:address":"Schulanlage 6",
    "sg:city":"Steinen",
    "sg:classifiers":[
        {
            "category":"Education",
            "subcategory":"Vocational School",
            "type":"Public Place"
        }
    ],
    "sg:postcode":"6422",
    "sg:province":"Schwyz",
    "sg:tags":[
        "koch-",
        "haushaltschulen"
    ],
    "wof:name":"Haushaltungsschule",
    "wof:placetype":"venue"
},
  "geometry": {"coordinates":[8.6120262146,47.0507583618],"type":"Point"}
}