{
  "type": "Feature",
  "properties": {
    "iso:country":"CH",
    "sg:address":"B\u00e4lliz 67 3600 Thun. Postfach 1503",
    "sg:city":"Thun",
    "sg:orig_category":"Fachdetailhandel mit pharmazeutischen Produkten Gesundheits U Sozialwesen",
    "sg:postcode":"3601",
    "sg:province":"Bern",
    "wof:name":"St. Margarethen-apotheke",
    "wof:placetype":"venue"
},
  "geometry": {"coordinates":[7.5712170601,47.538028717],"type":"Point"}
}