{
  "type": "Feature",
  "properties": {
    "iso:country":"CH",
    "sg:address":"G\u00fctschweg 4",
    "sg:city":"Brunnen",
    "sg:orig_category":"Malerei-Gipserei Stukkateurgewerbe, Gipserei U Verputzerei",
    "sg:phone":"+41 41 820 14 13",
    "sg:postcode":"6440",
    "sg:province":"Schwyz",
    "wof:name":"Gottlieb Senn Gipsergesch\u00e4ft",
    "wof:placetype":"venue"
},
  "geometry": {"coordinates":[8.6071233749,46.9940490723],"type":"Point"}
}