{
  "type": "Feature",
  "properties": {
    "iso:country":"CH",
    "sg:address":"Herrenwiese 3",
    "sg:city":"Freidorf",
    "sg:classifiers":[
        {
            "category":"Home & Garden",
            "subcategory":"Garden Supply",
            "type":"Retail Goods"
        }
    ],
    "sg:phone":"+41 71 450 06 30",
    "sg:postcode":"9306",
    "sg:province":"Thurgau",
    "sg:tags":[
        "lamp"
    ],
    "wof:name":"Visione Licht Gmbh",
    "wof:placetype":"venue"
},
  "geometry": {"coordinates":[9.396191597,47.4852485657],"type":"Point"}
}