{
  "type": "Feature",
  "properties": {
    "iso:country":"CH",
    "sg:address":"Hauptstrasse 99",
    "sg:city":"Frick",
    "sg:classifiers":[
        {
            "category":"Professional",
            "subcategory":"Employment Agencies",
            "type":"Services"
        }
    ],
    "sg:phone":"+41 62 865 40 00",
    "sg:postcode":"5070",
    "sg:province":"Aargau",
    "sg:tags":[
        "personal",
        "u",
        "stellenvermittlung"
    ],
    "wof:name":"Manpower Ag",
    "wof:placetype":"venue"
},
  "geometry": {"coordinates":[8.0248432159,47.5055427551],"type":"Point"}
}