{
  "type": "Feature",
  "properties": {
    "iso:country":"CH",
    "sg:address":"Burgerstrasse 22",
    "sg:city":"Luzern",
    "sg:orig_category":"Physiotherapie",
    "sg:phone":"+41 41 210 17 93",
    "sg:postcode":"6003",
    "sg:province":"Luzern",
    "wof:name":"Harry Roth Physiotherapie",
    "wof:placetype":"venue"
},
  "geometry": {"coordinates":[8.3025112152,47.0494194031],"type":"Point"}
}