{
  "type": "Feature",
  "properties": {
    "iso:country":"CH",
    "sg:address":"Obere Gasse 12",
    "sg:city":"Chur",
    "sg:orig_category":"Unclassifiable Establishments",
    "sg:postcode":"7000",
    "sg:province":"Graubunden",
    "wof:name":"Elektro Oberholzer Gmbh",
    "wof:placetype":"venue"
},
  "geometry": {"coordinates":[8.5255060196,47.4801979065],"type":"Point"}
}