{
  "type": "Feature",
  "properties": {
    "iso:country":"CH",
    "sg:address":"Gribstrasse 1 9475 Sevelen. Postfach 133",
    "sg:city":"Sevelen",
    "sg:orig_category":"Herstellung von Teppichen",
    "sg:phone":"+41 62 873 41 26",
    "sg:postcode":"9475",
    "sg:province":"St. Gallen",
    "wof:name":"Teppich Kurbel Service Kym P.",
    "wof:placetype":"venue"
},
  "geometry": {"coordinates":[7.9576091766,47.5427131653],"type":"Point"}
}