{
  "type": "Feature",
  "properties": {
    "iso:country":"CH",
    "sg:address":"Nansenstrasse 16",
    "sg:city":"Z\u00fcrich",
    "sg:orig_category":"Arztpraxen",
    "sg:phone":"+41 19292631",
    "sg:postcode":"8050",
    "sg:province":"Z\u00fcrich",
    "wof:name":"Dr.med.georgina Brandenberger Spezial\u00e4rztin Fmh",
    "wof:placetype":"venue"
},
  "geometry": {"coordinates":[8.720237,47.276806],"type":"Point"}
}