{
  "type": "Feature",
  "properties": {
    "iso:country":"CH",
    "sg:address":"Kantonsstrasse 63a 3930 Visp Case Postale 116",
    "sg:city":"Visp",
    "sg:orig_category":"Grosshandel mit Wein U Spirituosen Grosshandel mit sonstigen Getr\u00e4nken",
    "sg:phone":"+41 79 221 15 70",
    "sg:postcode":"3930",
    "sg:province":"Valais",
    "wof:name":"Gevag-getr\u00e4nke Ag",
    "wof:placetype":"venue"
},
  "geometry": {"coordinates":[7.8966288567,46.2946090698],"type":"Point"}
}