{
  "type": "Feature",
  "properties": {
    "iso:country":"CH",
    "sg:address":"Pr\u00e9-fleuri Rue De 6",
    "sg:city":"Sitten",
    "sg:orig_category":"Finanzierungsinstitutionen",
    "sg:postcode":"1950",
    "sg:province":"Valais",
    "wof:name":"Valdanice Sa",
    "wof:placetype":"venue"
},
  "geometry": {"coordinates":[9.1073904037,46.2385597229],"type":"Point"}
}