{
  "type": "Feature",
  "properties": {
    "addr:full":"Chemin D'orzens 58 Lutry Vaud 1095",
    "addr:housenumber":"58",
    "addr:postcode":"1095",
    "addr:street":"Chemin D'Orzens",
    "iso:country":"CH",
    "sg:address":"Chemin D'orzens 58",
    "sg:city":"Lutry",
    "sg:orig_category":"Allgemeiner Hoch U Tiefbau Hoch U Tiefbau",
    "sg:phone":"+41 79 205 46 54",
    "sg:postcode":"1095",
    "sg:province":"Vaud",
    "wof:name":"Jos\u00e9 Ramos Entreprise De Construction",
    "wof:placetype":"venue"
},
  "geometry": {"coordinates":[6.679201,46.514175],"type":"Point"}
}