{
  "type": "Feature",
  "properties": {
    "iso:country":"CH",
    "sg:address":"Saint-gervais Place De 2 1201 Gen\u00e8ve. Postfach",
    "sg:city":"Gen\u00e8ve",
    "sg:orig_category":"Dienstleistungen von Beteiligungsgesellschaften",
    "sg:postcode":"1201",
    "sg:province":"Gen\u00e8ve",
    "wof:name":"Soci\u00e9t\u00e9 Coop\u00e9rative Corswant Andr\u00e9",
    "wof:placetype":"venue"
},
  "geometry": {"coordinates":[6.8305969238,47.105670929],"type":"Point"}
}