{
  "type": "Feature",
  "properties": {
    "iso:country":"CH",
    "sg:address":"Laupen\u00e4ckerstrasse 6",
    "sg:city":"Unterlunkhofen",
    "sg:orig_category":"Detailhandel mit elektrischen Haushalts-,Radio U Fernsehger\u00e4ten sowie Musikinstrumenten Grosshandel ",
    "sg:phone":"+41 56 634 12 55",
    "sg:postcode":"8918",
    "sg:province":"Aargau",
    "wof:name":"Digital-unterhaltungs Ag",
    "wof:placetype":"venue"
},
  "geometry": {"coordinates":[8.3812570572,47.322719574],"type":"Point"}
}