{
  "type": "Feature",
  "properties": {
    "iso:country":"CH",
    "sg:address":"Chemin De L'abb\u00e9-freeley 9",
    "sg:city":"Fribourg",
    "sg:orig_category":"Detektivb\u00fcros U \u00dcberwachung",
    "sg:phone":"+41 26 322 20 95",
    "sg:postcode":"1700",
    "sg:province":"Fribourg",
    "wof:name":"Securis Sa, Agence Fribourg.de S\u00e9curit\u00e9 & De D\u00e9tectives",
    "wof:placetype":"venue"
},
  "geometry": {"coordinates":[7.1538147926,46.8156242371],"type":"Point"}
}