{
  "type": "Feature",
  "properties": {
    "iso:country":"CH",
    "sg:address":"Bretzwilerstrasse 9",
    "sg:city":"Nunningen",
    "sg:orig_category":"Satzherstellung U Reproduktion",
    "sg:phone":"+41 79 659 07 65",
    "sg:postcode":"4208",
    "sg:province":"Solothurn",
    "wof:name":"Xandesign H\u00e4ner",
    "wof:placetype":"venue"
},
  "geometry": {"coordinates":[7.6207637787,47.3938064575],"type":"Point"}
}