{
  "type": "Feature",
  "properties": {
    "iso:country":"CH",
    "sg:address":"Route De L'a\u00e9roport 25 1215 Gen\u00e8ve Case Postale 1215 Gen\u00e8ve",
    "sg:city":"D\u00e9p\u00f4t",
    "sg:classifiers":[
        {
            "category":"Restaurant",
            "type":"Food & Drink"
        }
    ],
    "sg:phone":"+41 22 735 15 80",
    "sg:postcode":"15",
    "wof:name":"Caf\u00e9 Aux Bonnes Choses",
    "wof:placetype":"venue"
},
  "geometry": {"coordinates":[6.1105661392,46.2317199707],"type":"Point"}
}