{
  "type": "Feature",
  "properties": {
    "iso:country":"CH",
    "sg:address":"Av. De La Gare 5 1700 Fribourg. Postfach",
    "sg:city":"Freiburg",
    "sg:orig_category":"Fachdetailhandel in Verkaufsr\u00e4umen",
    "sg:postcode":"1700",
    "sg:province":"Fribourg",
    "wof:name":"Rw-interways Gmbh",
    "wof:placetype":"venue"
},
  "geometry": {"coordinates":[8.3105154037,46.9811897278],"type":"Point"}
}