{
  "type": "Feature",
  "properties": {
    "iso:country":"CH",
    "sg:address":"Rigi Kaltbad/weggis",
    "sg:city":"Weggis",
    "sg:orig_category":"Interessenvertretungen",
    "sg:phone":"+41 41971005",
    "sg:postcode":"6353",
    "sg:province":"Luzern",
    "wof:name":"Stiftung Zur F\u00f6rderung Der Rigischule",
    "wof:placetype":"venue"
},
  "geometry": {"coordinates":[8.4343938828,47.0322952271],"type":"Point"}
}