{
  "type": "Feature",
  "properties": {
    "iso:country":"CH",
    "sg:address":"Rue Des Eaux-vives 8",
    "sg:city":"Gen\u00e8ve",
    "sg:orig_category":"Detailhandel mit Brot, Back U S\u00fcsswaren",
    "sg:postcode":"1207",
    "sg:province":"Gen\u00e8ve",
    "wof:name":"Anderegg B\u00e4ckerei.",
    "wof:placetype":"venue"
},
  "geometry": {"coordinates":[7.654852,47.235695],"type":"Point"}
}