{
  "type": "Feature",
  "properties": {
    "iso:country":"CH",
    "sg:address":"Bremgarterstrasse 6",
    "sg:city":"Fischbach-g\u00f6slikon",
    "sg:orig_category":"Politische Parteien SVP",
    "sg:phone":"+41 56 622 15 86",
    "sg:postcode":"5525",
    "sg:province":"Aargau",
    "wof:name":"Svp Ortspartei Fischbach",
    "wof:placetype":"venue"
},
  "geometry": {"coordinates":[8.3134536743,47.3671607971],"type":"Point"}
}