{
  "type": "Feature",
  "properties": {
    "iso:country":"CH",
    "sg:address":"Poststrasse 6 7000 Chur. Postfach",
    "sg:city":"Chur",
    "sg:orig_category":"Grosshandel mit Textilien",
    "sg:phone":"+41 81 252 49 19",
    "sg:postcode":"7000",
    "sg:province":"Graubunden",
    "wof:name":"Seks Gmbh Textilwarenhandel, Boutiquen F\u00fcr Damen- U. Herrenbekleidung",
    "wof:placetype":"venue"
},
  "geometry": {"coordinates":[9.5319375992,46.8501243591],"type":"Point"}
}