{
  "type": "Feature",
  "properties": {
    "iso:country":"CH",
    "sg:address":"Niederau",
    "sg:city":"Bauma",
    "sg:orig_category":"Ger\u00fcstbau Vermietung von Baumaschinen U ger\u00e4ten",
    "sg:phone":"+41 52 386 10 01",
    "sg:postcode":"8494",
    "sg:province":"Z\u00fcrich",
    "wof:name":"Fredy Schaufelberger Ger\u00fcstebau",
    "wof:placetype":"venue"
},
  "geometry": {"coordinates":[8.9105119705,47.3588409424],"type":"Point"}
}