{
  "type": "Feature",
  "properties": {
    "iso:country":"CH",
    "sg:address":"Langenstrasse 56",
    "sg:city":"Wiesendangen",
    "sg:orig_category":"Fahrschulen, Flugschulen",
    "sg:phone":"+41 52 337 27 63",
    "sg:postcode":"8542",
    "sg:province":"Z\u00fcrich",
    "wof:name":"Jack St\u00e4nz Autofahrschule",
    "wof:placetype":"venue"
},
  "geometry": {"coordinates":[8.7934246063,47.5188369751],"type":"Point"}
}