{
  "type": "Feature",
  "properties": {
    "iso:country":"CH",
    "sg:address":"Oberdorfstrasse 18a",
    "sg:city":"Stettlen",
    "sg:orig_category":"Instandhaltung U Reparatur von Automobilen",
    "sg:phone":"+41 31 931 27 17",
    "sg:postcode":"3066",
    "sg:province":"Bern",
    "wof:name":"Carrosserie Perren",
    "wof:placetype":"venue"
},
  "geometry": {"coordinates":[7.5258069038,46.9594078064],"type":"Point"}
}