{
  "type": "Feature",
  "properties": {
    "iso:country":"CH",
    "sg:address":"Hurdacker 9",
    "sg:city":"St\u00fcsslingen",
    "sg:orig_category":"Herstellung von sonstigen elektrischen Ausr\u00fcstungen",
    "sg:postcode":"4655",
    "sg:province":"Solothurn",
    "wof:name":"Sicherheitsdienst Von Arx M.",
    "wof:placetype":"venue"
},
  "geometry": {"coordinates":[7.9690451622,47.3900299072],"type":"Point"}
}