{
  "type": "Feature",
  "properties": {
    "iso:country":"CH",
    "sg:address":"Steinenring 10 4000 Basel. Postfach",
    "sg:city":"Basel",
    "sg:orig_category":"Architektur U Ingenieurb\u00fcros",
    "sg:postcode":"4051",
    "sg:province":"Basel-Stadt",
    "wof:name":"Architekten Kl\u00e4y & Weber Ag",
    "wof:placetype":"venue"
},
  "geometry": {"coordinates":[7.577634,47.552536],"type":"Point"}
}