{
  "type": "Feature",
  "properties": {
    "iso:country":"CH",
    "sg:address":"Hagenbuchenweg 1 4805 Brittnau. Postfach",
    "sg:city":"Brittnau",
    "sg:orig_category":"Unternehmensberatung",
    "sg:postcode":"4805",
    "sg:province":"Aargau",
    "wof:name":"Phabicon Pharma Biometrie Consulting Gmbh Vermarktung V. Dienstl. F. Pharmazeutische Unternehmen, Bes. Beratung Usw",
    "wof:placetype":"venue"
},
  "geometry": {"coordinates":[7.9466080666,47.2601356506],"type":"Point"}
}