{
  "type": "Feature",
  "properties": {
    "iso:country":"CH",
    "sg:address":"L\u00f6wenstr. 53",
    "sg:city":"Z\u00fcrich",
    "sg:classifiers":[
        {
            "category":"Banks & Credit Unions",
            "subcategory":"Bank",
            "type":"Services"
        }
    ],
    "sg:phone":"+41 91 695 67 11",
    "sg:postcode":"8022",
    "sg:province":"Z\u00fcrich",
    "wof:name":"Banca Del Sempione",
    "wof:placetype":"venue"
},
  "geometry": {"coordinates":[9.021454,45.83786],"type":"Point"}
}