{
  "type": "Feature",
  "properties": {
    "iso:country":"CH",
    "sg:address":"Dorfwiesenstrasse 14 8165 Sch\u00f6fflisdorf. Postfach",
    "sg:city":"Sch\u00f6fflisdorf",
    "sg:orig_category":"Detektivb\u00fcros U \u00dcberwachung",
    "sg:postcode":"8165",
    "sg:province":"Z\u00fcrich",
    "wof:name":"Etterli \u00dcberwachung Gmbh Dienstleistungen Im Bereich Laden Und Betriebs\u00fcberwachungen Usw",
    "wof:placetype":"venue"
},
  "geometry": {"coordinates":[8.4143428802,47.4989089966],"type":"Point"}
}