{
  "type": "Feature",
  "properties": {
    "iso:country":"CH",
    "sg:address":"Heerengarten 350",
    "sg:city":"Hallau",
    "sg:classifiers":[
        {
            "category":"Banks & Credit Unions",
            "subcategory":"Bank",
            "type":"Services"
        }
    ],
    "sg:postcode":"8215",
    "sg:province":"Schaffhausen",
    "wof:name":"Bsi Online Sa",
    "wof:placetype":"venue"
},
  "geometry": {"coordinates":[8.9513,46.002972],"type":"Point"}
}