{
  "type": "Feature",
  "properties": {
    "iso:country":"CH",
    "sg:address":"Birchweg 5",
    "sg:city":"B\u00f6ttstein",
    "sg:orig_category":"Sanit\u00e4r U Heizungsinstallation Sanit\u00e4rinstallation",
    "sg:phone":"+41 56 245 12 76",
    "sg:postcode":"5315",
    "sg:province":"Aargau",
    "wof:name":"Haustechnik-heizung-sanit\u00e4r Bruno Baumgartner",
    "wof:placetype":"venue"
},
  "geometry": {"coordinates":[8.2230825424,47.5575714111],"type":"Point"}
}