{
  "type": "Feature",
  "properties": {
    "addr:full":"Werkstrasse 4 K\u00e4giswil Obwalden 6056",
    "addr:housenumber":"4",
    "addr:postcode":"6056",
    "addr:street":"Werkstrasse;Obwalden",
    "iso:country":"CH",
    "sg:address":"Werkstrasse 4",
    "sg:city":"K\u00e4giswil",
    "sg:orig_category":"Autospenglereien",
    "sg:phone":"+41 41 660 35 60",
    "sg:postcode":"6056",
    "sg:province":"Obwalden",
    "wof:name":"Walter Fanger Carrosserie",
    "wof:placetype":"venue"
},
  "geometry": {"coordinates":[8.2571,46.913574],"type":"Point"}
}