{
  "type": "Feature",
  "properties": {
    "iso:country":"CH",
    "sg:address":"Burkertsmatt 4",
    "sg:city":"Widen",
    "sg:classifiers":[
        {
            "category":"Social Services",
            "subcategory":"Retirement Home",
            "type":"Services"
        }
    ],
    "sg:phone":"+41 56 649 37 37",
    "sg:postcode":"8967",
    "sg:province":"Aargau",
    "sg:tags":[
        "pflegeheime",
        "u",
        "alters"
    ],
    "wof:name":"Regionales Altersheim",
    "wof:placetype":"venue"
},
  "geometry": {"coordinates":[8.365896,47.366482],"type":"Point"}
}