{
  "type": "Feature",
  "properties": {
    "iso:country":"CH",
    "sg:address":"Cad'mat\u00e9",
    "sg:city":"Maloja",
    "sg:orig_category":"Detailhandel mit M\u00f6beln Innendekorationsateliers",
    "sg:phone":"+41 79 419 04 36",
    "sg:postcode":"7516",
    "sg:province":"Graubunden",
    "wof:name":"Bruno Clal\u00fcna Arvenm\u00f6bel",
    "wof:placetype":"venue"
},
  "geometry": {"coordinates":[9.5828914642,46.609703064],"type":"Point"}
}