{
  "type": "Feature",
  "properties": {
    "iso:country":"CH",
    "sg:address":"Sonnengasse 14",
    "sg:city":"Klingnau",
    "sg:orig_category":"Arztpraxen",
    "sg:phone":"+41 56 245 77 75",
    "sg:postcode":"5313",
    "sg:province":"Aargau",
    "wof:name":"Dr.med.erich B\u00fchler Arzt F\u00fcr Allgemeine Medizin",
    "wof:placetype":"venue"
},
  "geometry": {"coordinates":[8.250829,47.580597],"type":"Point"}
}