{
  "type": "Feature",
  "properties": {
    "iso:country":"CH",
    "sg:address":"Schneidersmatt 16",
    "sg:city":"W\u00fcnnewil",
    "sg:orig_category":"Tankstellen",
    "sg:phone":"+41 31 931 29 66",
    "sg:postcode":"3184",
    "sg:province":"Fribourg",
    "wof:name":"Willy Blaser Garage Ag",
    "wof:placetype":"venue"
},
  "geometry": {"coordinates":[7.4785618782,46.9545326233],"type":"Point"}
}