{
  "type": "Feature",
  "properties": {
    "iso:country":"CH",
    "sg:address":"B\u00fchlstrasse 51",
    "sg:city":"Sirnach",
    "sg:orig_category":"Vermittlung von Immobilien Verwaltung von Immobilien",
    "sg:phone":"+41 71 960 01 60",
    "sg:postcode":"8370",
    "sg:province":"Thurgau",
    "wof:name":"Kvr Immobilien Ag",
    "wof:placetype":"venue"
},
  "geometry": {"coordinates":[8.9845380783,47.4679946899],"type":"Point"}
}