{
  "type": "Feature",
  "properties": {
    "iso:country":"CH",
    "sg:address":"Amietstrasse 24 3400 Burgdorf. Postfach",
    "sg:city":"Burgdorf",
    "sg:orig_category":"Finanzierungsinstitutionen",
    "sg:postcode":"3402",
    "sg:province":"Bern",
    "wof:name":"Fousek Thomas",
    "wof:placetype":"venue"
},
  "geometry": {"coordinates":[7.6238498688,47.0464515686],"type":"Point"}
}