{
  "type": "Feature",
  "properties": {
    "iso:country":"CH",
    "sg:address":"Hauptstrasse 34",
    "sg:city":"Muhen",
    "sg:orig_category":"Biotopes",
    "sg:phone":"+41 62 737 20 50",
    "sg:postcode":"5037",
    "sg:province":"Aargau",
    "wof:name":"Blumen Schaffner Ag",
    "wof:placetype":"venue"
},
  "geometry": {"coordinates":[8.053069,47.337532],"type":"Point"}
}