{
  "type": "Feature",
  "properties": {
    "iso:country":"CH",
    "sg:address":"Scharnagelnstrasse 3 4704 Niederbipp. Postfach 105",
    "sg:city":"Niederbipp",
    "sg:orig_category":"Unclassifiable Establishments",
    "sg:postcode":"4704",
    "sg:province":"Bern",
    "wof:name":"Ms Gartenservice Michael Sch\u00e4rer",
    "wof:placetype":"venue"
},
  "geometry": {"coordinates":[7.5200119019,47.5044212341],"type":"Point"}
}