{
  "type": "Feature",
  "properties": {
    "iso:country":"CH",
    "sg:address":"Schlettstadtstrasse 4 2540 Grenchen. Postfach 1340",
    "sg:city":"Grenchen",
    "sg:orig_category":"Architektur U Ingenieurb\u00fcros",
    "sg:postcode":"2540",
    "sg:province":"Solothurn",
    "wof:name":"H + B Bau-consult Gmbh",
    "wof:placetype":"venue"
},
  "geometry": {"coordinates":[7.554958,47.513721],"type":"Point"}
}