{
  "type": "Feature",
  "properties": {
    "iso:country":"CH",
    "sg:address":"Hochhaus 9",
    "sg:city":"Spreitenbach",
    "sg:orig_category":"Detailhandel mit Damenbekleidung Herstellung von Oberbekleidung",
    "sg:phone":"+41 17411170",
    "sg:postcode":"8957",
    "sg:province":"Aargau",
    "wof:name":"Chicor\u00e9e Mode Ag",
    "wof:placetype":"venue"
},
  "geometry": {"coordinates":[8.3656835556,47.4180450439],"type":"Point"}
}