{
  "type": "Feature",
  "properties": {
    "iso:country":"CH",
    "sg:address":"Les Briesses 3971 Chermignon. Postfach",
    "sg:city":"Lens",
    "sg:orig_category":"Stukkateurgewerbe, Gipserei U Verputzerei",
    "sg:phone":"+41 21 634 40 28",
    "sg:postcode":"1978",
    "sg:province":"Valais",
    "wof:name":"Sblandano Salvatore",
    "wof:placetype":"venue"
},
  "geometry": {"coordinates":[6.5840139389,46.5395889282],"type":"Point"}
}