{
  "type": "Feature",
  "properties": {
    "iso:country":"CH",
    "sg:address":"Kirchweg 11",
    "sg:city":"Beckenried",
    "sg:orig_category":"Druckweiterverarbeitung",
    "sg:postcode":"6375",
    "sg:province":"Nidwalden",
    "wof:name":"Lochschmidt Jos., Kundert's Hch. Nachfolger",
    "wof:placetype":"venue"
},
  "geometry": {"coordinates":[9.0725097656,46.9936103821],"type":"Point"}
}