{
  "type": "Feature",
  "properties": {
    "iso:country":"CH",
    "sg:address":"Waldhof 4313 M\u00f6hlin. Postfach",
    "sg:city":"M\u00f6hlin",
    "sg:orig_category":"Sonstiger Grosshandel",
    "sg:postcode":"4313",
    "sg:province":"Aargau",
    "wof:name":"Sodexim, Mihale",
    "wof:placetype":"venue"
},
  "geometry": {"coordinates":[6.579390049,46.5390815735],"type":"Point"}
}