{
  "type": "Feature",
  "properties": {
    "addr:full":"Sch\u00fcrrainweg 2 Schlieren Z\u00fcrich 8952",
    "addr:housenumber":"2",
    "addr:postcode":"8952",
    "addr:street":"Schuerrainweg",
    "iso:country":"CH",
    "sg:address":"Sch\u00fcrrainweg 2",
    "sg:city":"Schlieren",
    "sg:orig_category":"Bezirks, Sekundar, Realschulen, Oberstufe der Primarschulen",
    "sg:phone":"+41 17300497",
    "sg:postcode":"8952",
    "sg:province":"Z\u00fcrich",
    "wof:name":"Berufswahlschule Limmattal",
    "wof:placetype":"venue"
},
  "geometry": {"coordinates":[8.43777,47.394054],"type":"Point"}
}