{
  "type": "Feature",
  "properties": {
    "iso:country":"CH",
    "sg:address":"Staatsstrasse 142",
    "sg:city":"H\u00fcnibach",
    "sg:classifiers":[
        {
            "category":"Travel",
            "subcategory":"Hotels & Motels",
            "type":"Entertainment"
        }
    ],
    "sg:phone":"+41 33 744 51 21",
    "sg:postcode":"3626",
    "sg:province":"Bern",
    "sg:tags":[
        "hotels",
        "mit",
        "restaurant"
    ],
    "wof:name":"Hotel-restaurant Christiania, Frau I. Geadah-nopper",
    "wof:placetype":"venue"
},
  "geometry": {"coordinates":[7.2826681137,46.4774971008],"type":"Point"}
}