{
  "type": "Feature",
  "properties": {
    "iso:country":"CH",
    "sg:address":"1667",
    "sg:city":"Enney",
    "sg:orig_category":"Reinigungsgewerbe",
    "sg:postcode":"1667",
    "sg:province":"Fribourg",
    "wof:name":"Roger Schillig, Kaminfegergesch\u00e4ft",
    "wof:placetype":"venue"
},
  "geometry": {"coordinates":[8.6299219131,46.8910903931],"type":"Point"}
}