{
  "type": "Feature",
  "properties": {
    "iso:country":"CH",
    "sg:address":"Saffental",
    "sg:city":"Gunzwil",
    "sg:orig_category":"Wasserversorgung",
    "sg:postcode":"6222",
    "sg:province":"Luzern",
    "wof:name":"Wasserversorgungs-genossenschaft Hasenhusen-saffental",
    "wof:placetype":"venue"
},
  "geometry": {"coordinates":[8.1574239731,47.2043457031],"type":"Point"}
}