{
  "type": "Feature",
  "properties": {
    "iso:country":"CH",
    "sg:address":"3931",
    "sg:city":"Lalden",
    "sg:orig_category":"Sportvereine Sch\u00fctzen",
    "sg:postcode":"3931",
    "sg:province":"Valais",
    "wof:name":"Milit\u00e4rsch\u00fctzen",
    "wof:placetype":"venue"
},
  "geometry": {"coordinates":[7.9004998207,46.3002090454],"type":"Point"}
}