{
  "type": "Feature",
  "properties": {
    "iso:country":"CH",
    "sg:address":"4245",
    "sg:city":"Kleinl\u00fctzel",
    "sg:orig_category":"Landw. Genossenschaften Viehzucht",
    "sg:postcode":"4245",
    "sg:province":"Solothurn",
    "wof:name":"Braunviehzuchtgenossenschaft Huggerwald",
    "wof:placetype":"venue"
},
  "geometry": {"coordinates":[7.4160170555,47.425819397],"type":"Point"}
}