{
  "type": "Feature",
  "properties": {
    "iso:country":"CH",
    "sg:address":"Berg",
    "sg:city":"Rutschwil-d\u00e4gerlen",
    "sg:orig_category":"Sportvereine Turnen Vereine Damen",
    "sg:phone":"+41 52 316 29 49",
    "sg:postcode":"8471",
    "sg:province":"Z\u00fcrich",
    "wof:name":"Damenriege D\u00e4gerlen",
    "wof:placetype":"venue"
},
  "geometry": {"coordinates":[8.7157821655,47.5734825134],"type":"Point"}
}