{
  "type": "Feature",
  "properties": {
    "iso:country":"CH",
    "sg:address":"Unterdorfstrasse 83",
    "sg:city":"Widnau",
    "sg:orig_category":"Detailhandel mit B\u00fcchern, Zeitungen, Schreib U Papeteriewaren",
    "sg:phone":"+41 71 722 64 01",
    "sg:postcode":"9443",
    "sg:province":"St. Gallen",
    "wof:name":"Kiosk Gutzwiller",
    "wof:placetype":"venue"
},
  "geometry": {"coordinates":[9.634107,47.415089],"type":"Point"}
}