{
  "type": "Feature",
  "properties": {
    "iso:country":"CH",
    "sg:address":"Praz-devant Chemin De 18",
    "sg:city":"Romanel-s-lausanne",
    "sg:orig_category":"Mechanik",
    "sg:phone":"+41 21 732 11 71",
    "sg:postcode":"1032",
    "sg:province":"Vaud",
    "wof:name":"Carrosserie Rodriguez S\u00e0rl",
    "wof:placetype":"venue"
},
  "geometry": {"coordinates":[6.6038780212,46.5632209778],"type":"Point"}
}