{
  "type": "Feature",
  "properties": {
    "iso:country":"CH",
    "sg:address":"Steinacherstrasse 18 9327 T\u00fcbach. Postfach",
    "sg:city":"T\u00fcbach",
    "sg:orig_category":"Hardwareberatung",
    "sg:postcode":"9327",
    "sg:province":"St. Gallen",
    "wof:name":"Njd Informatique, Dougoud Mat\u00e9riel Informatique; Commerce",
    "wof:placetype":"venue"
},
  "geometry": {"coordinates":[6.2350459099,46.6112594604],"type":"Point"}
}