{
  "type": "Feature",
  "properties": {
    "iso:country":"CH",
    "sg:address":"Bahnhofstrasse 2",
    "sg:city":"Dietikon",
    "sg:orig_category":"RESTAURANTS: TEA-ROOMS",
    "sg:phone":"+41 14930374",
    "sg:postcode":"8953",
    "sg:province":"Z\u00fcrich",
    "wof:name":"Yak + Yeti Gmbh",
    "wof:placetype":"venue"
},
  "geometry": {"coordinates":[8.4639034271,47.3640403748],"type":"Point"}
}