{
  "type": "Feature",
  "properties": {
    "iso:country":"CH",
    "sg:address":"Via Giuseppe Motta 29 6900 Lugano. Postfach",
    "sg:city":"Lugano",
    "sg:orig_category":"Finanzierungsinstitutionen",
    "sg:phone":"+41 91 967 64 19",
    "sg:postcode":"6900",
    "sg:province":"Ticino",
    "wof:name":"Mediaset Investment Sarl, Luxembourg, Succursale Di Lugano",
    "wof:placetype":"venue"
},
  "geometry": {"coordinates":[8.9486055374,46.0009765625],"type":"Point"}
}