{
  "type": "Feature",
  "properties": {
    "iso:country":"CH",
    "sg:address":"Winterhalde 9",
    "sg:city":"Binningen",
    "sg:orig_category":"Unclassifiable Establishments",
    "sg:phone":"+41 61 925 11 11",
    "sg:postcode":"4102",
    "sg:province":"Basel-Landschaft",
    "wof:name":"Rosenmund Ht Holding Ag",
    "wof:placetype":"venue"
},
  "geometry": {"coordinates":[7.5644140244,47.5378684998],"type":"Point"}
}