{
  "type": "Feature",
  "properties": {
    "iso:country":"CH",
    "sg:address":"Chemin De Belleroche 7",
    "sg:city":"Neuch\u00e2tel",
    "sg:orig_category":"Vereine Gesang",
    "sg:postcode":"2000",
    "sg:province":"Neuch\u00e2tel",
    "wof:name":"St\u00e9 De Chant L'avenir",
    "wof:placetype":"venue"
},
  "geometry": {"coordinates":[6.9437298775,46.9995765686],"type":"Point"}
}