{
  "type": "Feature",
  "properties": {
    "iso:country":"CH",
    "sg:address":"Rosengasse 15 7324 Vilters. Postfach 37",
    "sg:city":"Vilters",
    "sg:orig_category":"Bauschreinerei Herstellung von Konstruktionsteilen, Fertigbauteilen U Ausbauelementen aus Holz",
    "sg:phone":"+41 81 723 34 75",
    "sg:postcode":"7324",
    "sg:province":"St. Gallen",
    "wof:name":"J\u00e4ger Cornelius",
    "wof:placetype":"venue"
},
  "geometry": {"coordinates":[9.45293,47.02354],"type":"Point"}
}