{
  "type": "Feature",
  "properties": {
    "iso:country":"CH",
    "sg:address":"Avenue Du G\u00e9n\u00e9ral-guisan 12",
    "sg:city":"Rolle",
    "sg:orig_category":"Sanit\u00e4r U Heizungsinstallation",
    "sg:phone":"+41 21 825 22 62",
    "sg:postcode":"1180",
    "sg:province":"Vaud",
    "wof:name":"Hermann Boschung Chauffages",
    "wof:placetype":"venue"
},
  "geometry": {"coordinates":[6.3336939812,46.460308075],"type":"Point"}
}