{
  "type": "Feature",
  "properties": {
    "iso:country":"CH",
    "sg:address":"1270",
    "sg:city":"Tr\u00e9lex",
    "sg:orig_category":"Detailhandel mit Waren verschiedener Art, Hauptrichtung Nahrungsmittel",
    "sg:phone":"+41 22 369 13 80",
    "sg:postcode":"1270",
    "sg:province":"Vaud",
    "wof:name":"Bossey Lucy",
    "wof:placetype":"venue"
},
  "geometry": {"coordinates":[6.1947498322,46.4204711914],"type":"Point"}
}