{
  "type": "Feature",
  "properties": {
    "iso:country":"CH",
    "sg:address":"Burgerstrasse 21",
    "sg:city":"Luzern",
    "sg:classifiers":[
        {
            "category":"Bars & Pubs",
            "type":"Food & Drink"
        }
    ],
    "sg:phone":"+41 21 635 05 98",
    "sg:postcode":"6003",
    "sg:province":"Luzern",
    "wof:name":"Henry's Pub",
    "wof:placetype":"venue"
},
  "geometry": {"coordinates":[6.579993,46.539467],"type":"Point"}
}