{
  "type": "Feature",
  "properties": {
    "iso:country":"CH",
    "sg:address":"Talgutweg 12a",
    "sg:city":"Ittigen",
    "sg:orig_category":"Unternehmensberatung",
    "sg:phone":"+41 31 771 22 71",
    "sg:postcode":"3063",
    "sg:province":"Bern",
    "wof:name":"Adconsult Holding Ag",
    "wof:placetype":"venue"
},
  "geometry": {"coordinates":[7.4814729691,46.9798545837],"type":"Point"}
}