{
  "type": "Feature",
  "properties": {
    "iso:country":"CH",
    "sg:address":"Bahnhofstrasse 34",
    "sg:city":"Buchs",
    "sg:orig_category":"Fine Wire Welding Services",
    "sg:phone":"+41 81 756 40 58",
    "sg:postcode":"9470",
    "sg:province":"St. Gallen",
    "wof:name":"Rossell \u00e9lectronique Sa",
    "wof:placetype":"venue"
},
  "geometry": {"coordinates":[9.473912,47.166355],"type":"Point"}
}