{
  "type": "Feature",
  "properties": {
    "iso:country":"CH",
    "sg:address":"Weingartenstrassse 28 8268 Salenstein. Postfach",
    "sg:city":"Salenstein",
    "sg:orig_category":"Non-Classified Establishments",
    "sg:postcode":"8268",
    "sg:province":"Thurgau",
    "wof:name":"Irsslinger Holding Ag",
    "wof:placetype":"venue"
},
  "geometry": {"coordinates":[9.0550966263,47.6733970642],"type":"Point"}
}