{
  "type": "Feature",
  "properties": {
    "iso:country":"CH",
    "sg:address":"Grabenstrasse 9 8200 Schaffhausen. Postfach",
    "sg:city":"Schaffhausen",
    "sg:orig_category":"Versicherungen Generalagenturen",
    "sg:phone":"+41 52 624 50 21",
    "sg:postcode":"8201",
    "sg:province":"Schaffhausen",
    "wof:name":"National-versicherungen Generalagentur",
    "wof:placetype":"venue"
},
  "geometry": {"coordinates":[8.6314115524,47.694694519],"type":"Point"}
}