{
  "type": "Feature",
  "properties": {
    "iso:country":"CH",
    "sg:address":"Eichenstrasse 1",
    "sg:city":"Basel",
    "sg:orig_category":"Vereine Gesang",
    "sg:phone":"+41 61 301 88 82",
    "sg:postcode":"4054",
    "sg:province":"Basel-Stadt",
    "wof:name":"Gemischter Chor Der Evang.-methodistischen Kirche",
    "wof:placetype":"venue"
},
  "geometry": {"coordinates":[7.5703940392,47.5568695068],"type":"Point"}
}