{
  "type": "Feature",
  "properties": {
    "iso:country":"CH",
    "sg:address":"Avenue Louis-ruchonnet 1",
    "sg:city":"Lausanne",
    "sg:orig_category":"Aktivit\u00e4t der Bankinstitute",
    "sg:phone":"+41 21 310 40 50",
    "sg:postcode":"1003",
    "sg:province":"Vaud",
    "wof:name":"Ge Capital Bank",
    "wof:placetype":"venue"
},
  "geometry": {"coordinates":[6.627567,46.517696],"type":"Point"}
}