{
  "type": "Feature",
  "properties": {
    "iso:country":"CH",
    "sg:address":"R\u00f6ssligasse 19",
    "sg:city":"Riehen",
    "sg:orig_category":"RESTAURANTS: TEA-ROOMS",
    "sg:phone":"+41 61 641 47 74",
    "sg:postcode":"4125",
    "sg:province":"Basel-Stadt",
    "wof:name":"Cafe Schweizerhaus Urs Mumenthaler",
    "wof:placetype":"venue"
},
  "geometry": {"coordinates":[7.6516342163,47.5857009888],"type":"Point"}
}