{
  "type": "Feature",
  "properties": {
    "iso:country":"CH",
    "sg:address":"D\u00fcbendorfstrasse 420",
    "sg:city":"Z\u00fcrich",
    "sg:orig_category":"Fahrschulen, Flugschulen",
    "sg:phone":"+41 13214840",
    "sg:postcode":"8051",
    "sg:province":"Z\u00fcrich",
    "wof:name":"Bruno Rohner Autofahrschule",
    "wof:placetype":"venue"
},
  "geometry": {"coordinates":[8.5935277939,47.3974876404],"type":"Point"}
}