{
  "type": "Feature",
  "properties": {
    "iso:country":"CH",
    "sg:address":"Haldenstrasse 46 8045 Z\u00fcrich",
    "sg:city":"Zust",
    "sg:orig_category":"Erbringung von sonstigen Dienstleistungen f\u00fcr Unterhaltung, Erholung U Freizeit",
    "sg:phone":"+41 14615383",
    "sg:postcode":"45",
    "wof:name":"Rumora, Ruch Rudolf Beratung, Organisation Im Musik- U. Theaterwesen, T\u00e4tigkeiten Im Audiobereich Usw",
    "wof:placetype":"venue"
},
  "geometry": {"coordinates":[8.5118503571,47.3567810059],"type":"Point"}
}