{
  "type": "Feature",
  "properties": {
    "iso:country":"CH",
    "sg:address":"Route D'italie 35 1950 Sion Case Postale 445",
    "sg:city":"Sion",
    "sg:orig_category":"Autogaragen Lastwagen and Nutzfahrzeuge",
    "sg:phone":"+41 27 322 01 31",
    "sg:postcode":"1951",
    "sg:province":"Valais",
    "wof:name":"Garage Hediger Sa",
    "wof:placetype":"venue"
},
  "geometry": {"coordinates":[7.385187,46.273449],"type":"Point"}
}