{
  "type": "Feature",
  "properties": {
    "iso:country":"CH",
    "sg:address":"Jurastrasse 35",
    "sg:city":"Langenthal",
    "sg:orig_category":"Zahnarztpraxen",
    "sg:phone":"+41 62 922 50 29",
    "sg:postcode":"4900",
    "sg:province":"Bern",
    "wof:name":"Dr. Med. Dent. Christoph Gujer Zahnarzt",
    "wof:placetype":"venue"
},
  "geometry": {"coordinates":[7.7863550186,47.215473175],"type":"Point"}
}