{
  "type": "Feature",
  "properties": {
    "iso:country":"CH",
    "sg:address":"Industriestrasse 9 6300 Zug. Postfach",
    "sg:city":"Zug",
    "sg:orig_category":"Grosshandel mit festen Brennstoffen U Mineral\u00f6lerzeugnissen",
    "sg:postcode":"6300",
    "sg:province":"Zug",
    "wof:name":"Montax Ag",
    "wof:placetype":"venue"
},
  "geometry": {"coordinates":[8.7784986496,47.2003517151],"type":"Point"}
}