{
  "type": "Feature",
  "properties": {
    "iso:country":"CH",
    "sg:address":"Chemin De L'esplanade 6",
    "sg:city":"Vernier",
    "sg:orig_category":"G\u00fcterbef\u00f6rderung im Strassenverkehr",
    "sg:postcode":"1214",
    "sg:province":"Gen\u00e8ve",
    "wof:name":"Werlen Hubert Transport.",
    "wof:placetype":"venue"
},
  "geometry": {"coordinates":[6.0883507729,46.2168006897],"type":"Point"}
}