{
  "type": "Feature",
  "properties": {
    "iso:country":"CH",
    "sg:address":"Dorfstrasse 33 6376 Emmetten. Postfach 86",
    "sg:city":"Emmetten",
    "sg:classifiers":[
        {
            "category":"Travel",
            "subcategory":"Hotels & Motels",
            "type":"Entertainment"
        }
    ],
    "sg:phone":"+41 41 620 13 51",
    "sg:postcode":"6376",
    "sg:province":"Nidwalden",
    "sg:tags":[
        "hotels",
        "mit",
        "restaurant"
    ],
    "wof:name":"Hotel Post",
    "wof:placetype":"venue"
},
  "geometry": {"coordinates":[8.5137529373,46.956829071],"type":"Point"}
}