{
  "type": "Feature",
  "properties": {
    "iso:country":"CH",
    "sg:address":"Nidaugasse 41",
    "sg:city":"Biel/bienne",
    "sg:orig_category":"Detailhandel mit Blumen U Pflanzen",
    "sg:phone":"+41 32 322 44 70",
    "sg:postcode":"2502",
    "sg:province":"Bern",
    "wof:name":"Oscar Fischer Florist Inh. U. Heubach",
    "wof:placetype":"venue"
},
  "geometry": {"coordinates":[7.246849,47.137997],"type":"Point"}
}