{
  "type": "Feature",
  "properties": {
    "iso:country":"CH",
    "sg:address":"Lilienweg 1",
    "sg:city":"K\u00f6niz",
    "sg:orig_category":"Interessenvertretungen U sonstige Vereinigungen",
    "sg:postcode":"3098",
    "sg:province":"Bern",
    "wof:name":"Schweiz.gras-ski Verband",
    "wof:placetype":"venue"
},
  "geometry": {"coordinates":[7.4108672142,46.9231414795],"type":"Point"}
}