{
  "type": "Feature",
  "properties": {
    "iso:country":"CH",
    "sg:address":"Asylstrasse 25",
    "sg:city":"Spiez",
    "sg:orig_category":"Sonstiges Gesundheitswesen",
    "sg:phone":"+41 33 654 23 56",
    "sg:postcode":"3700",
    "sg:province":"Bern",
    "wof:name":"Krankenmobilienmagazin Frau Ilse Staub",
    "wof:placetype":"venue"
},
  "geometry": {"coordinates":[7.6703038216,46.6916770935],"type":"Point"}
}