{
  "type": "Feature",
  "properties": {
    "iso:country":"CH",
    "sg:address":"Hauptstrasse 41",
    "sg:city":"Necker",
    "sg:orig_category":"Detailhandel mit Bekleidung Herstellung von Arbeits U Berufsbekleidung",
    "sg:phone":"+41 71 374 20 40",
    "sg:postcode":"9126",
    "sg:province":"St. Gallen",
    "wof:name":"Bitschnau Paul",
    "wof:placetype":"venue"
},
  "geometry": {"coordinates":[9.13051,47.346329],"type":"Point"}
}