{
  "type": "Feature",
  "properties": {
    "iso:country":"CH",
    "sg:address":"Kloosweg 83a",
    "sg:city":"Biel/bienne",
    "sg:orig_category":"Architekturb\u00fcros",
    "sg:phone":"+41 32 323 62 50",
    "sg:postcode":"2502",
    "sg:province":"Bern",
    "wof:name":"Rolf Weber Architekturb\u00fcro",
    "wof:placetype":"venue"
},
  "geometry": {"coordinates":[7.244806,47.145088],"type":"Point"}
}