{
  "type": "Feature",
  "properties": {
    "iso:country":"CH",
    "sg:address":"Hauptstrasse 92",
    "sg:city":"Wegenstetten",
    "sg:orig_category":"G\u00fcterbef\u00f6rderung im Strassenverkehr",
    "sg:phone":"+41 61 871 04 27",
    "sg:postcode":"4317",
    "sg:province":"Aargau",
    "wof:name":"Ernst Schlienger Metzgerei",
    "wof:placetype":"venue"
},
  "geometry": {"coordinates":[7.9294061661,47.4957580566],"type":"Point"}
}