{
  "type": "Feature",
  "properties": {
    "iso:country":"CH",
    "sg:address":"Rue Jules-baillods 17",
    "sg:city":"Couvet",
    "sg:orig_category":"Herstellung von Metallerzeugnissen ohne Maschinenbau Herstellung von sonstigen Maschinen f\u00fcr unspezi",
    "sg:phone":"+41 32 863 29 22",
    "sg:postcode":"2108",
    "sg:province":"Neuch\u00e2tel",
    "wof:name":"Ammann Waagen & Co Waagen & W\u00e4gesysteme",
    "wof:placetype":"venue"
},
  "geometry": {"coordinates":[6.6278390884,46.9221076965],"type":"Point"}
}