{
  "type": "Feature",
  "properties": {
    "iso:country":"CH",
    "sg:address":"Woka 1",
    "sg:city":"Scuol",
    "sg:orig_category":"Wohnheime",
    "sg:phone":"+41 81 864 02 06",
    "sg:postcode":"7550",
    "sg:province":"Graubunden",
    "wof:name":"Ferienhaus Des Zollpersonals Chasa Funtana Tr\u00fc",
    "wof:placetype":"venue"
},
  "geometry": {"coordinates":[10.3028278351,46.7987670898],"type":"Point"}
}