{
  "type": "Feature",
  "properties": {
    "iso:country":"CH",
    "sg:address":"Etzelstrasse 10",
    "sg:city":"W\u00e4denswil",
    "sg:orig_category":"Unternehmensberatung Wirtschaftspr\u00fcfung, Steuerberatung U Treuhand",
    "sg:phone":"+41 17806500",
    "sg:postcode":"8820",
    "sg:province":"Z\u00fcrich",
    "wof:name":"Tribelhorn Ernst, Treuhand Und Buchhaltungen",
    "wof:placetype":"venue"
},
  "geometry": {"coordinates":[8.673204422,47.2258071899],"type":"Point"}
}