{
  "type": "Feature",
  "properties": {
    "iso:country":"CH",
    "sg:address":"Baarerstrasse 82 6300 Zug. Postfach",
    "sg:city":"Zug",
    "sg:orig_category":"Grosshandel mit Erzen U Metallen",
    "sg:phone":"+41 41 726 05 35",
    "sg:postcode":"6300",
    "sg:province":"Zug",
    "wof:name":"Mmk Steel Trade Ag Stahl Und Metallprodukte; Handel Usw",
    "wof:placetype":"venue"
},
  "geometry": {"coordinates":[8.5180339813,47.1771469116],"type":"Point"}
}