{
  "type": "Feature",
  "properties": {
    "iso:country":"CH",
    "sg:address":"T\u00f6dihof 10",
    "sg:city":"St\u00e4fa",
    "sg:orig_category":"Sportvereine Motorrad Sportvereine Velo Rad-& Motorfahrer-Bund SRB",
    "sg:postcode":"8712",
    "sg:province":"Z\u00fcrich",
    "wof:name":"Rmv Fortuna Buchs",
    "wof:placetype":"venue"
},
  "geometry": {"coordinates":[9.474612236,47.1567230225],"type":"Point"}
}