{
  "type": "Feature",
  "properties": {
    "iso:country":"CH",
    "sg:address":"Route De Grandson 28",
    "sg:city":"Boudry",
    "sg:orig_category":"Mechanische Werkst\u00e4tten",
    "sg:phone":"+41 32 841 47 84",
    "sg:postcode":"2017",
    "sg:province":"Neuch\u00e2tel",
    "wof:name":"Louis Blaser M\u00e9canique De Pr\u00e9cision",
    "wof:placetype":"venue"
},
  "geometry": {"coordinates":[6.8330001831,46.9463233948],"type":"Point"}
}