{
  "type": "Feature",
  "properties": {
    "iso:country":"CH",
    "sg:address":"Anternstrasse",
    "sg:city":"Niederbipp",
    "sg:classifiers":[
        {
            "category":"Education",
            "subcategory":"Library",
            "type":"Public Place"
        }
    ],
    "sg:phone":"+41 32 633 23 83",
    "sg:postcode":"4704",
    "sg:province":"Bern",
    "sg:tags":[
        "u",
        "bibliotheken",
        "archive"
    ],
    "wof:name":"Spital Region Oberaargau Ag",
    "wof:placetype":"venue"
},
  "geometry": {"coordinates":[7.684314,47.271378],"type":"Point"}
}