{
  "type": "Feature",
  "properties": {
    "iso:country":"CH",
    "sg:address":"Reuslistrasse 62",
    "sg:city":"Sissach",
    "sg:orig_category":"Elektro- and elektronische Maschinen Grosshandel",
    "sg:phone":"+41 61 976 95 95",
    "sg:postcode":"4450",
    "sg:province":"Basel-Landschaft",
    "wof:name":"Hueber & Grieder Werkvertretungen",
    "wof:placetype":"venue"
},
  "geometry": {"coordinates":[7.8132200241,47.4580955505],"type":"Point"}
}