{
  "type": "Feature",
  "properties": {
    "iso:country":"CH",
    "sg:address":"Brunnenwiesstrasse 6",
    "sg:city":"Gr\u00fcningen",
    "sg:orig_category":"Architektur U Ingenieurb\u00fcros",
    "sg:phone":"+41 19352413",
    "sg:postcode":"8627",
    "sg:province":"Z\u00fcrich",
    "wof:name":"Inter Com Production Ag",
    "wof:placetype":"venue"
},
  "geometry": {"coordinates":[8.758274,47.284424],"type":"Point"}
}