{
  "type": "Feature",
  "properties": {
    "iso:country":"CH",
    "sg:address":"Lindenmad",
    "sg:city":"Kriessern",
    "sg:orig_category":"Haltung von Gefl\u00fcgel",
    "sg:phone":"+41 71 385 29 11",
    "sg:postcode":"9451",
    "sg:province":"St. Gallen",
    "wof:name":"Willy Villiger Gefl\u00fcgelzucht",
    "wof:placetype":"venue"
},
  "geometry": {"coordinates":[9.2767095566,47.4403915405],"type":"Point"}
}