{
  "type": "Feature",
  "properties": {
    "iso:country":"CH",
    "sg:address":"Grand'rue 5a 1522 Lucens Case Postale 40",
    "sg:city":"Lucens",
    "sg:orig_category":"Fachdetailhandel mit pharmazeutischen Produkten",
    "sg:phone":"+41 21 906 81 45",
    "sg:postcode":"1522",
    "sg:province":"Vaud",
    "wof:name":"Pharmacie De Lucens, Van Pernis-erni M. Et R.",
    "wof:placetype":"venue"
},
  "geometry": {"coordinates":[6.8393740654,46.7089576721],"type":"Point"}
}