{
  "type": "Feature",
  "properties": {
    "iso:country":"CH",
    "sg:address":"Forren 9056 Gais. Postfach 35",
    "sg:city":"Gais",
    "sg:orig_category":"Druck ohne Zeitungsdruck Verlagsgewerbe",
    "sg:phone":"+41 79 207 42 77",
    "sg:postcode":"9056",
    "sg:province":"Appenzell Ausserrhoden",
    "wof:name":"H. Kern Ag",
    "wof:placetype":"venue"
},
  "geometry": {"coordinates":[9.4464120865,47.3568000793],"type":"Point"}
}