{
  "type": "Feature",
  "properties": {
    "iso:country":"CH",
    "sg:address":"Wynigenstrasse 15",
    "sg:city":"Burgdorf",
    "sg:orig_category":"Detailhandel mit Fahrr\u00e4dern Detailhandel mit Sportartikeln",
    "sg:phone":"+41 34 422 70 80",
    "sg:postcode":"3400",
    "sg:province":"Bern",
    "wof:name":"Peter Gerber Snow & Bike Sport",
    "wof:placetype":"venue"
},
  "geometry": {"coordinates":[7.6298589706,47.0583114624],"type":"Point"}
}