{
  "type": "Feature",
  "properties": {
    "iso:country":"CH",
    "sg:address":"Steinbockstrasse 8 7000 Chur. Postfach 621",
    "sg:city":"Chur",
    "sg:orig_category":"Verwaltung von Immobilien Wirtschaftspr\u00fcfung, Steuerberatung U Treuhand",
    "sg:phone":"+41 81 252 25 26",
    "sg:postcode":"7002",
    "sg:province":"Graubunden",
    "wof:name":"Refina Treuhand Ag",
    "wof:placetype":"venue"
},
  "geometry": {"coordinates":[9.5299034119,46.852306366],"type":"Point"}
}