{
  "type": "Feature",
  "properties": {
    "iso:country":"CH",
    "sg:address":"Rue De Bernex 232",
    "sg:city":"Bernex",
    "sg:orig_category":"Elektroinstallation",
    "sg:phone":"+41 22 757 10 02",
    "sg:postcode":"1233",
    "sg:province":"Gen\u00e8ve",
    "wof:name":"Michel Puchat Installations \u00e9lectriques",
    "wof:placetype":"venue"
},
  "geometry": {"coordinates":[6.0760917664,46.1770324707],"type":"Point"}
}