{
  "type": "Feature",
  "properties": {
    "iso:country":"CH",
    "sg:address":"Frassen 2",
    "sg:city":"Domat/ems",
    "sg:orig_category":"Interessenvertretungen",
    "sg:postcode":"7013",
    "sg:province":"Graubunden",
    "wof:name":"Verein Der B\u00fcrger Von Bosnien Und Herzegowina Goldene Lilien",
    "wof:placetype":"venue"
},
  "geometry": {"coordinates":[9.4408845901,46.8352088928],"type":"Point"}
}