{
  "type": "Feature",
  "properties": {
    "iso:country":"CH",
    "sg:address":"Kammernholz",
    "sg:city":"Herisau",
    "sg:orig_category":"Sportvereine Sch\u00fctzen Armbrust",
    "sg:phone":"+41 71 385 48 82",
    "sg:postcode":"9100",
    "sg:province":"Appenzell Ausserrhoden",
    "wof:name":"Armbrustsch\u00fctzen-verein",
    "wof:placetype":"venue"
},
  "geometry": {"coordinates":[9.2450017929,47.4207458496],"type":"Point"}
}