{
  "type": "Feature",
  "properties": {
    "iso:country":"CH",
    "sg:address":"Hauptstrasse 10 3860 Meiringen. Postfach 268",
    "sg:city":"Meiringen",
    "sg:orig_category":"Architekturb\u00fcros",
    "sg:phone":"+41 33 971 52 12",
    "sg:postcode":"3860",
    "sg:province":"Bern",
    "wof:name":"Bys\u00e4th & Linke Architekturb\u00fcro",
    "wof:placetype":"venue"
},
  "geometry": {"coordinates":[8.184169,46.728306],"type":"Point"}
}