{
  "type": "Feature",
  "properties": {
    "iso:country":"CH",
    "sg:address":"Rotwandstrasse 65 8003 Z\u00fcrich. Postfach 8721",
    "sg:city":"Z\u00fcrich",
    "sg:orig_category":"Politische Vereinigungen",
    "sg:phone":"+41 12417722",
    "sg:postcode":"8036",
    "sg:province":"Z\u00fcrich",
    "wof:name":"Partei Der Arbeit Der Schweiz",
    "wof:placetype":"venue"
},
  "geometry": {"coordinates":[8.5291948318,47.3760032654],"type":"Point"}
}