{
  "type": "Feature",
  "properties": {
    "iso:country":"CH",
    "sg:address":"Langstrasse 241",
    "sg:city":"Z\u00fcrich",
    "sg:orig_category":"Detailhandel mit B\u00fcchern, Zeitungen, Schreib U Papeteriewaren Detailhandel mit Lederwaren U Reiseart",
    "sg:phone":"+41 12716240",
    "sg:postcode":"8005",
    "sg:province":"Z\u00fcrich",
    "wof:name":"Ryffel + Co, Papeterie Und Lederwaren",
    "wof:placetype":"venue"
},
  "geometry": {"coordinates":[8.530964,47.384182],"type":"Point"}
}