{
  "type": "Feature",
  "properties": {
    "iso:country":"CH",
    "sg:address":"Bahnhofstrasse 32",
    "sg:city":"Zug",
    "sg:orig_category":"Non-Classified Establishments",
    "sg:postcode":"6300",
    "sg:province":"Zug",
    "wof:name":"Q.p. Intertrade Gmbh",
    "wof:placetype":"venue"
},
  "geometry": {"coordinates":[8.5160121918,47.1704101562],"type":"Point"}
}