{
  "type": "Feature",
  "properties": {
    "iso:country":"CH",
    "sg:address":"Lavaterstrasse 85 8000 Z\u00fcrich. Postfach",
    "sg:city":"Z\u00fcrich",
    "sg:orig_category":"Sonstiges Versicherungsgewerbe",
    "sg:postcode":"8001",
    "sg:province":"Z\u00fcrich",
    "wof:name":"Xl Europe Ltd, Dublin, Zweigniederlassung Z\u00fcrich",
    "wof:placetype":"venue"
},
  "geometry": {"coordinates":[8.5333890915,47.3603172302],"type":"Point"}
}