{
  "type": "Feature",
  "properties": {
    "iso:country":"CH",
    "sg:address":"La Pinte De Lys 1669 Albeuve. Postfach",
    "sg:city":"Albeuve",
    "sg:classifiers":[
        {
            "category":"Travel",
            "subcategory":"Hotels & Motels",
            "type":"Entertainment"
        }
    ],
    "sg:phone":"+41 26 652 27 21",
    "sg:postcode":"1669",
    "sg:province":"Fribourg",
    "sg:tags":[
        "hotels",
        "mit",
        "restaurant"
    ],
    "wof:name":"La Poularde Sa",
    "wof:placetype":"venue"
},
  "geometry": {"coordinates":[6.9267129898,46.702495575],"type":"Point"}
}