{
  "type": "Feature",
  "properties": {
    "iso:country":"CH",
    "sg:address":"Kreuzplatz 2",
    "sg:city":"Z\u00fcrich",
    "sg:orig_category":"Werbeagenturen",
    "sg:phone":"+41 12609494",
    "sg:postcode":"8032",
    "sg:province":"Z\u00fcrich",
    "wof:name":"Maurice Codourey Fishwishion",
    "wof:placetype":"venue"
},
  "geometry": {"coordinates":[8.5541248322,47.3647918701],"type":"Point"}
}