{
  "type": "Feature",
  "properties": {
    "iso:country":"CH",
    "sg:address":"Rue Maunoir 16",
    "sg:city":"Gen\u00e8ve",
    "sg:orig_category":"Arztpraxen",
    "sg:phone":"+41 21 636 11 37",
    "sg:postcode":"1207",
    "sg:province":"Gen\u00e8ve",
    "wof:name":"Dr M\u00e9d. Anne Devries M\u00e9decin Sp\u00e9cialiste",
    "wof:placetype":"venue"
},
  "geometry": {"coordinates":[6.583014,46.543041],"type":"Point"}
}