{
  "type": "Feature",
  "properties": {
    "addr:full":"Rue Des Plantys 2 Chamoson Valais 1955",
    "addr:housenumber":"2",
    "addr:postcode":"1955",
    "addr:street":"Rue Des Plantys",
    "iso:country":"CH",
    "sg:address":"Rue Des Plantys 2",
    "sg:city":"Chamoson",
    "sg:orig_category":"Autogaragen Instandhaltung U Reparatur von Automobilen",
    "sg:phone":"+41 27 306 29 60",
    "sg:postcode":"1955",
    "sg:province":"Valais",
    "wof:name":"Garage Des Plantys Carrupt Christophe S\u00e0rl",
    "wof:placetype":"venue"
},
  "geometry": {"coordinates":[7.22824,46.197491],"type":"Point"}
}