{
  "type": "Feature",
  "properties": {
    "iso:country":"CH",
    "sg:address":"Buttiweg 29",
    "sg:city":"B\u00e4ttwil-fl\u00fch",
    "sg:orig_category":"Grosshandel mit Tabakwaren Handelsvermittlung von Nahrungsmitteln, Getr\u00e4nken U Tabakwaren",
    "sg:phone":"+41 61 731 35 60",
    "sg:postcode":"4112",
    "sg:province":"Solothurn",
    "wof:name":"Tabana Ag",
    "wof:placetype":"venue"
},
  "geometry": {"coordinates":[7.4958558083,47.4848518372],"type":"Point"}
}