{
  "type": "Feature",
  "properties": {
    "iso:country":"CH",
    "sg:address":"Au Village",
    "sg:city":"Gollion",
    "sg:orig_category":"Herstellung von Heizk\u00f6rpern U kesseln f\u00fcr die Zentralheizung",
    "sg:phone":"+41 21 861 03 13",
    "sg:postcode":"1124",
    "sg:province":"Vaud",
    "wof:name":"Regitherm S\u00e0rl",
    "wof:placetype":"venue"
},
  "geometry": {"coordinates":[6.5060391426,46.5849685669],"type":"Point"}
}