{
  "type": "Feature",
  "properties": {
    "iso:country":"CH",
    "sg:address":"Maienstrasse 9",
    "sg:city":"Grenchen",
    "sg:orig_category":"Cnc-Tool Grinders",
    "sg:phone":"+41 32 652 25 22",
    "sg:postcode":"2540",
    "sg:province":"Solothurn",
    "wof:name":"Urs Tschudin",
    "wof:placetype":"venue"
},
  "geometry": {"coordinates":[7.404896,47.190739],"type":"Point"}
}