{
  "type": "Feature",
  "properties": {
    "addr:full":"Oberm\u00fchle 8353 Elgg. Postfach 82 Elgg Z\u00fcrich 8353",
    "addr:housenumber":"82",
    "addr:postcode":"8353 elgg.;8353",
    "addr:street":"Obermuehle;Postfach",
    "iso:country":"CH",
    "sg:address":"Oberm\u00fchle 8353 Elgg. Postfach 82",
    "sg:city":"Elgg",
    "sg:orig_category":"Bauschreinerei Herstellung von Konstruktionsteilen, Fertigbauteilen U Ausbauelementen aus Holz",
    "sg:phone":"+41 52 368 61 61",
    "sg:postcode":"8353",
    "sg:province":"Z\u00fcrich",
    "wof:name":"Elibag Elgger Innenausbau Ag",
    "wof:placetype":"venue"
},
  "geometry": {"coordinates":[8.863083,47.491493],"type":"Point"}
}