{
  "type": "Feature",
  "properties": {
    "addr:full":"Metteliweg 8 Glattfelden Z\u00fcrich 8192",
    "addr:housenumber":"8",
    "addr:postcode":"8192",
    "addr:street":"Metteliweg",
    "iso:country":"CH",
    "sg:address":"Metteliweg 8",
    "sg:city":"Glattfelden",
    "sg:orig_category":"Datenverarbeitungsdienste Sonstige mit der Informatik verbundene T\u00e4tigkeiten",
    "sg:phone":"+41 71 944 30 28",
    "sg:postcode":"8192",
    "sg:province":"Z\u00fcrich",
    "wof:name":"Br\u00fchwiler Dienstleistungen Gmbh",
    "wof:placetype":"venue"
},
  "geometry": {"coordinates":[8.961124,47.430317],"type":"Point"}
}