{
  "type": "Feature",
  "properties": {
    "iso:country":"CH",
    "sg:address":"1149",
    "sg:city":"Berolle",
    "sg:classifiers":[
        {
            "category":"Restaurant",
            "type":"Food & Drink"
        }
    ],
    "sg:phone":"+41 21 809 50 29",
    "sg:postcode":"1149",
    "sg:province":"Vaud",
    "wof:name":"Auberge Communale",
    "wof:placetype":"venue"
},
  "geometry": {"coordinates":[6.3381319046,46.5589561462],"type":"Point"}
}