{
  "type": "Feature",
  "properties": {
    "iso:country":"CH",
    "sg:address":"Reussstrasse 10",
    "sg:city":"Gisikon",
    "sg:classifiers":[
        {
            "category":"Banks & Credit Unions",
            "subcategory":"Bank",
            "type":"Services"
        }
    ],
    "sg:phone":"+41 41 450 37 44",
    "sg:postcode":"6038",
    "sg:province":"Luzern",
    "sg:tags":[
        "stone",
        "natural"
    ],
    "wof:name":"Tosca Ton Manufaktur Ag",
    "wof:placetype":"venue"
},
  "geometry": {"coordinates":[8.3982791901,47.1264076233],"type":"Point"}
}