{
  "type": "Feature",
  "properties": {
    "iso:country":"CH",
    "sg:address":"Eichholz",
    "sg:city":"Berneck",
    "sg:orig_category":"Rebbau",
    "sg:phone":"+41 71 744 51 10",
    "sg:postcode":"9442",
    "sg:province":"St. Gallen",
    "wof:name":"Felix Indermaur Rebschule & Weinbau",
    "wof:placetype":"venue"
},
  "geometry": {"coordinates":[9.6104745865,47.4252433777],"type":"Point"}
}