{
  "type": "Feature",
  "properties": {
    "iso:country":"CH",
    "sg:address":"Mattenhofstrasse 39 3007 Bern. Postfach",
    "sg:city":"Bern",
    "sg:orig_category":"Sonstiger Grosshandel",
    "sg:postcode":"3005",
    "sg:province":"Bern",
    "wof:name":"M\u00fchlemann P.a. & Co, Import & Export Import, Export",
    "wof:placetype":"venue"
},
  "geometry": {"coordinates":[7.4277000427,46.9438743591],"type":"Point"}
}