{
  "type": "Feature",
  "properties": {
    "addr:full":"Avenue Vinet 30 Lausanne Vaud 1004",
    "addr:housenumber":"30",
    "addr:postcode":"1004",
    "addr:street":"Avenue Vinet",
    "iso:country":"CH",
    "sg:address":"Avenue Vinet 30",
    "sg:city":"Lausanne",
    "sg:classifiers":[
        {
            "category":"Education",
            "subcategory":"Library",
            "type":"Public Place"
        }
    ],
    "sg:phone":"+41 21 925 27 27",
    "sg:postcode":"1004",
    "sg:province":"Vaud",
    "sg:tags":[
        "u",
        "bibliotheken",
        "archive"
    ],
    "wof:name":"Clinique De Nant",
    "wof:placetype":"venue"
},
  "geometry": {"coordinates":[6.85156,46.476971],"type":"Point"}
}