{
  "type": "Feature",
  "properties": {
    "iso:country":"CH",
    "sg:address":"Querstrasse 4 8424 Embrach. Postfach",
    "sg:city":"Embrach",
    "sg:orig_category":"Sonstiger Grosshandel",
    "sg:postcode":"8424",
    "sg:province":"Z\u00fcrich",
    "wof:name":"Mbsa-nikola Gmbh",
    "wof:placetype":"venue"
},
  "geometry": {"coordinates":[8.5923109055,47.5119972229],"type":"Point"}
}