{
  "type": "Feature",
  "properties": {
    "iso:country":"CH",
    "sg:address":"Place De Jargonnant 3",
    "sg:city":"Gen\u00e8ve",
    "sg:orig_category":"Non-Classified Establishments",
    "sg:postcode":"1201",
    "sg:province":"Gen\u00e8ve",
    "wof:name":"Rifka Amazon Naturopathe",
    "wof:placetype":"venue"
},
  "geometry": {"coordinates":[6.1598668098,46.2007522583],"type":"Point"}
}