{
  "type": "Feature",
  "properties": {
    "iso:country":"CH",
    "sg:address":"Rumpumpsteig 3",
    "sg:city":"Z\u00fcrich",
    "sg:orig_category":"Geb\u00e4ude, Wohnungsreinigung Reinigungsgewerbe",
    "sg:phone":"+41 14822623",
    "sg:postcode":"8038",
    "sg:province":"Z\u00fcrich",
    "wof:name":"Walro Geb\u00e4udereinigung, Walter Roshard",
    "wof:placetype":"venue"
},
  "geometry": {"coordinates":[8.5343093872,47.3435325623],"type":"Point"}
}