{
  "type": "Feature",
  "properties": {
    "addr:full":"Fauquez Route Aloys- 103 Lausanne Vaud 1018",
    "addr:housenumber":"103",
    "addr:postcode":"1018",
    "addr:street":"Route Aloys",
    "iso:country":"CH",
    "sg:address":"Fauquez Route Aloys- 103",
    "sg:city":"Lausanne",
    "sg:orig_category":"Allgemeiner Hoch U Tiefbau",
    "sg:phone":"+41 21 691 24 61",
    "sg:postcode":"1018",
    "sg:province":"Vaud",
    "wof:name":"Imhof Sa Lausanne",
    "wof:placetype":"venue"
},
  "geometry": {"coordinates":[6.63364,46.537891],"type":"Point"}
}