{
  "type": "Feature",
  "properties": {
    "iso:country":"CH",
    "sg:address":"Z\u00fcrcherstrasse 115",
    "sg:city":"Neuenhof",
    "sg:orig_category":"Detailhandel mit Uhren U Schmuck Fachdetailhandel in Verkaufsr\u00e4umen",
    "sg:phone":"+41 56 406 20 11",
    "sg:postcode":"5432",
    "sg:province":"Aargau",
    "wof:name":"Bruno Keller Uhren-bijouterie",
    "wof:placetype":"venue"
},
  "geometry": {"coordinates":[8.3273954391,47.4497299194],"type":"Point"}
}