{
  "type": "Feature",
  "properties": {
    "iso:country":"CH",
    "sg:address":"S\u00fcdstrasse 1",
    "sg:city":"M\u00fcnsingen",
    "sg:orig_category":"Sonstige Finanzierungsinstitutionen",
    "sg:phone":"+41 31 721 50 00",
    "sg:postcode":"3110",
    "sg:province":"Bern",
    "wof:name":"Net Research Holding Ag",
    "wof:placetype":"venue"
},
  "geometry": {"coordinates":[7.5633740425,46.868724823],"type":"Point"}
}