{
  "type": "Feature",
  "properties": {
    "iso:country":"CH",
    "sg:address":"Place La",
    "sg:city":"Ch\u00e2teau-d'oex",
    "sg:orig_category":"Interessenvertretungen",
    "sg:postcode":"1837",
    "wof:name":"Fondation Minu Balkanski",
    "wof:placetype":"venue"
},
  "geometry": {"coordinates":[-118.1657333374,34.0966873169],"type":"Point"}
}