{
  "type": "Feature",
  "properties": {
    "iso:country":"CH",
    "sg:address":"Chemin Mons\u00e9jour 9/19",
    "sg:city":"Fribourg",
    "sg:orig_category":"Instandhaltung U Reparatur von Automobilen",
    "sg:phone":"+41 26 424 24 70",
    "sg:postcode":"1700",
    "sg:province":"Fribourg",
    "wof:name":"Carrosserie Du Midi Sa",
    "wof:placetype":"venue"
},
  "geometry": {"coordinates":[7.1474027634,46.8009605408],"type":"Point"}
}