{
  "type": "Feature",
  "properties": {
    "iso:country":"CH",
    "sg:address":"Lerchenweg 3",
    "sg:city":"Obergerlafingen",
    "sg:orig_category":"Dienstleistungen in der Forstwirtschaft Forstwirtschaft ohne Dienstleistungen in der Forstwirtschaft",
    "sg:phone":"+41 32 675 17 24",
    "sg:postcode":"4564",
    "sg:province":"Bern",
    "wof:name":"Niklaus Peter",
    "wof:placetype":"venue"
},
  "geometry": {"coordinates":[7.5880742073,47.1633148193],"type":"Point"}
}