{
  "type": "Feature",
  "properties": {
    "addr:full":"Bachtobel 8 7204 Untervaz. Postfach Untervaz Graubunden 7204",
    "addr:housenumber":"8;7204",
    "addr:postcode":"7204",
    "addr:street":"Bachtobel;Postfach Untervaz Graubunden",
    "iso:country":"CH",
    "sg:address":"Bachtobel 8 7204 Untervaz. Postfach",
    "sg:city":"Untervaz",
    "sg:orig_category":"Architektur U Ingenieurb\u00fcros",
    "sg:postcode":"7204",
    "sg:province":"Graubunden",
    "wof:name":"Kohler",
    "wof:placetype":"venue"
},
  "geometry": {"coordinates":[9.530801,46.927002],"type":"Point"}
}