{
  "type": "Feature",
  "properties": {
    "addr:full":"Kirchenfeldstrasse 29 Bern Bern 3005",
    "addr:housenumber":"29",
    "addr:postcode":"3005",
    "addr:street":"Kirchenfeldstrasse",
    "iso:country":"CH",
    "sg:address":"Kirchenfeldstrasse 29",
    "sg:city":"Bern",
    "sg:orig_category":"Chiropraktik",
    "sg:phone":"+41 31 352 66 88",
    "sg:postcode":"3005",
    "sg:province":"Bern",
    "wof:name":"Dr.ernst W. Schroeder Chiropraktor",
    "wof:placetype":"venue"
},
  "geometry": {"coordinates":[7.451934,46.940323],"type":"Point"}
}