{
  "type": "Feature",
  "properties": {
    "iso:country":"CH",
    "sg:address":"Steinenring 10",
    "sg:city":"Basel",
    "sg:orig_category":"Architekturb\u00fcros",
    "sg:phone":"+41 81 911 16 42",
    "sg:postcode":"4051",
    "sg:province":"Basel-Stadt",
    "wof:name":"Hans Peter Fontana Architekturb\u00fcro",
    "wof:placetype":"venue"
},
  "geometry": {"coordinates":[9.285231,46.836693],"type":"Point"}
}