{
  "type": "Feature",
  "properties": {
    "iso:country":"CH",
    "sg:address":"Frauenfelderstrasse 5 8370 Sirnach. Postfach",
    "sg:city":"Sirnach",
    "sg:orig_category":"Kantonalbanken",
    "sg:phone":"+41 848 803 113",
    "sg:postcode":"8370",
    "sg:province":"Thurgau",
    "wof:name":"Thurgauer Kantonalbank",
    "wof:placetype":"venue"
},
  "geometry": {"coordinates":[8.998208046,47.4632835388],"type":"Point"}
}