{
  "type": "Feature",
  "properties": {
    "iso:country":"CH",
    "sg:address":"Gibraltarstrasse 10",
    "sg:city":"Luzern",
    "sg:orig_category":"Detailhandel mit Bekleidung Detailhandel mit Damenbekleidung",
    "sg:phone":"+41 41 240 92 92",
    "sg:postcode":"6003",
    "sg:province":"Luzern",
    "wof:name":"New Trends Gr\u00fcter Urs",
    "wof:placetype":"venue"
},
  "geometry": {"coordinates":[8.299443,47.050053],"type":"Point"}
}