{
  "type": "Feature",
  "properties": {
    "iso:country":"CH",
    "sg:address":"Kapellacker 52",
    "sg:city":"Ueberstorf",
    "sg:orig_category":"Grosshandel mit Milch, Milcherzeugnissen, Eiern, Speise\u00f6len U Nahrungsfetten Sonstiger Fachdetailhan",
    "sg:phone":"+41 26 411 26 66",
    "sg:postcode":"3182",
    "sg:province":"Fribourg",
    "wof:name":"Huguenin H. Sa, Fromages En Gros, Import-export",
    "wof:placetype":"venue"
},
  "geometry": {"coordinates":[6.9189238548,46.3783493042],"type":"Point"}
}