{
  "type": "Feature",
  "properties": {
    "iso:country":"CH",
    "sg:address":"Obere Hauptgasse 78 3600 Thun. Postfach 82",
    "sg:city":"Thun",
    "sg:orig_category":"Chemische Industrie",
    "sg:phone":"+41 33 222 37 37",
    "sg:postcode":"3602",
    "sg:province":"Bern",
    "wof:name":"Citropan Ag Chemische Produkte",
    "wof:placetype":"venue"
},
  "geometry": {"coordinates":[7.631812,46.758022],"type":"Point"}
}