{
  "type": "Feature",
  "properties": {
    "iso:country":"CH",
    "sg:address":"Frohburgstrasse 95",
    "sg:city":"Z\u00fcrich",
    "sg:orig_category":"Architektur U Ingenieurb\u00fcros Unternehmensberatung",
    "sg:phone":"+41 13623631",
    "sg:postcode":"8006",
    "sg:province":"Z\u00fcrich",
    "wof:name":"Function Gmbh",
    "wof:placetype":"venue"
},
  "geometry": {"coordinates":[8.549296,47.390522],"type":"Point"}
}