{
  "type": "Feature",
  "properties": {
    "iso:country":"CH",
    "sg:address":"Eggweg 4",
    "sg:city":"Bolligen",
    "sg:orig_category":"Vorschulen, Kinderg\u00e4rten",
    "sg:phone":"+41 31 921 49 74",
    "sg:postcode":"3065",
    "sg:province":"Bern",
    "wof:name":"Kindergarten",
    "wof:placetype":"venue"
},
  "geometry": {"coordinates":[7.4997339249,46.9718132019],"type":"Point"}
}