{
  "type": "Feature",
  "properties": {
    "iso:country":"CH",
    "sg:address":"Rue Du Lac 27 1400 Yverdon-les-bains Case Postale 415",
    "sg:city":"Yverdon",
    "sg:orig_category":"Fachdetailhandel mit pharmazeutischen Produkten",
    "sg:phone":"+41 24 423 00 23",
    "sg:postcode":"1401",
    "sg:province":"Vaud",
    "wof:name":"Georges Emery Pharmacie Centrale",
    "wof:placetype":"venue"
},
  "geometry": {"coordinates":[6.6392011642,46.7794456482],"type":"Point"}
}