{
  "type": "Feature",
  "properties": {
    "iso:country":"CH",
    "sg:address":"Via Maggio 1 C",
    "sg:city":"Lugano",
    "sg:orig_category":"Unclassifiable Establishments",
    "sg:phone":"+41 18882040",
    "sg:postcode":"6900",
    "sg:province":"Ticino",
    "wof:name":"B. Tolen, B\u00fcroautomation",
    "wof:placetype":"venue"
},
  "geometry": {"coordinates":[8.6508789062,47.405921936],"type":"Point"}
}