{
  "type": "Feature",
  "properties": {
    "iso:country":"CH",
    "sg:address":"Rheinaustrasse 10",
    "sg:city":"Widnau",
    "sg:orig_category":"Elektroinstallation",
    "sg:phone":"+41 71 722 57 39",
    "sg:postcode":"9443",
    "sg:province":"St. Gallen",
    "wof:name":"Elektro Sieber Armin Gmbh",
    "wof:placetype":"venue"
},
  "geometry": {"coordinates":[9.6478357315,47.4076461792],"type":"Point"}
}