{
  "type": "Feature",
  "properties": {
    "iso:country":"CH",
    "sg:address":"Dorfstrasse 11",
    "sg:city":"Uttigen",
    "sg:orig_category":"Mahl U Sch\u00e4lm\u00fchlen S\u00e4gewerke",
    "sg:phone":"+41 33 345 13 10",
    "sg:postcode":"3628",
    "sg:province":"Bern",
    "wof:name":"Ernst Maurer Knochenm\u00fchle & S\u00e4gerei",
    "wof:placetype":"venue"
},
  "geometry": {"coordinates":[7.5726280212,46.79529953],"type":"Point"}
}