{
  "type": "Feature",
  "properties": {
    "addr:full":"Viale Castagnola 21f Calprino Ticino 6900",
    "addr:housenumber":"21f",
    "addr:postcode":"6900",
    "addr:street":"Viale Castagnola",
    "iso:country":"CH",
    "sg:address":"Viale Castagnola 21f",
    "sg:city":"Calprino",
    "sg:orig_category":"Arztpraxen",
    "sg:phone":"+41 91 972 55 33",
    "sg:postcode":"6900",
    "sg:province":"Ticino",
    "wof:name":"Dott.med.giorgio Bronz Specialista Fmh",
    "wof:placetype":"venue"
},
  "geometry": {"coordinates":[8.951305,46.002975],"type":"Point"}
}