{
  "type": "Feature",
  "properties": {
    "iso:country":"CH",
    "sg:address":"Alberich Zwyssigstrasse 24",
    "sg:city":"Wettingen",
    "sg:orig_category":"Herstellung von keramischen Wand U Bodenfliesen U platten",
    "sg:phone":"+41 56 426 39 12",
    "sg:postcode":"5430",
    "sg:province":"Aargau",
    "wof:name":"Frick Keramik Ag, Wettingen",
    "wof:placetype":"venue"
},
  "geometry": {"coordinates":[8.3202104568,47.4612312317],"type":"Point"}
}