{
  "type": "Feature",
  "properties": {
    "iso:country":"CH",
    "sg:address":"Konstanzerstrasse 14",
    "sg:city":"T\u00e4gerwilen",
    "sg:orig_category":"Non-Classified Establishments",
    "sg:postcode":"8274",
    "sg:province":"Thurgau",
    "wof:name":"Brenner Geschenkideen + Party-shop",
    "wof:placetype":"venue"
},
  "geometry": {"coordinates":[9.3475437164,47.4126434326],"type":"Point"}
}