{
  "type": "Feature",
  "properties": {
    "iso:country":"CH",
    "sg:address":"Im Lettenacker 6",
    "sg:city":"Binningen",
    "sg:orig_category":"Werbegrafikateliers",
    "sg:phone":"+41 61 302 48 86",
    "sg:postcode":"4102",
    "sg:province":"Basel-Landschaft",
    "wof:name":"Ferdi Afflerbach Atelier F\u00fcr Werbegrafik",
    "wof:placetype":"venue"
},
  "geometry": {"coordinates":[7.5590758324,47.5444068909],"type":"Point"}
}