{
  "type": "Feature",
  "properties": {
    "iso:country":"CH",
    "sg:address":"Linth-escher-strasse 27",
    "sg:city":"Bilten",
    "sg:orig_category":"Lagerung",
    "sg:phone":"+41 55 615 18 18",
    "sg:postcode":"8865",
    "sg:province":"Glarus",
    "wof:name":"Tiefk\u00fchlhaus Ag",
    "wof:placetype":"venue"
},
  "geometry": {"coordinates":[9.0311899185,47.1502037048],"type":"Point"}
}