{
  "type": "Feature",
  "properties": {
    "iso:country":"CH",
    "sg:address":"Schachenrain 36",
    "sg:city":"Biberist",
    "sg:orig_category":"Trailer Hitches Car",
    "sg:phone":"+41 32 672 36 83",
    "sg:postcode":"4562",
    "sg:province":"Solothurn",
    "wof:name":"Ambofix Ag",
    "wof:placetype":"venue"
},
  "geometry": {"coordinates":[7.5587849617,47.171913147],"type":"Point"}
}