{
  "type": "Feature",
  "properties": {
    "iso:country":"CH",
    "sg:address":"Burgstrasse 75",
    "sg:city":"Meilen",
    "sg:orig_category":"Unternehmensberatung",
    "sg:phone":"+41 19235553",
    "sg:postcode":"8706",
    "sg:province":"Z\u00fcrich",
    "wof:name":"Anita Gurtner Consulting",
    "wof:placetype":"venue"
},
  "geometry": {"coordinates":[8.6422700882,47.2720565796],"type":"Point"}
}