{
  "type": "Feature",
  "properties": {
    "iso:country":"CH",
    "sg:address":"Obere Sternengasse 20",
    "sg:city":"Solothurn",
    "sg:orig_category":"Gartenbau",
    "sg:phone":"+41 32 623 90 59",
    "sg:postcode":"4500",
    "sg:province":"Solothurn",
    "wof:name":"Waibel-hofer Martin & Theresia",
    "wof:placetype":"venue"
},
  "geometry": {"coordinates":[7.543651104,47.2137680054],"type":"Point"}
}