{
  "type": "Feature",
  "properties": {
    "iso:country":"CH",
    "sg:address":"Guglern 4",
    "sg:city":"Buttisholz",
    "sg:orig_category":"Detailhandel mit Fahrr\u00e4dern Handel mit Motorr\u00e4dern, Teilen U Zubeh\u00f6r Instandhaltung U Reparatur von ",
    "sg:phone":"+41 56 441 31 47",
    "sg:postcode":"6018",
    "sg:province":"Luzern",
    "wof:name":"Peter Seiler Velos-motos",
    "wof:placetype":"venue"
},
  "geometry": {"coordinates":[8.2073249817,47.4822731018],"type":"Point"}
}