{
  "type": "Feature",
  "properties": {
    "iso:country":"CH",
    "sg:address":"Bahnhofplatz 14",
    "sg:city":"Winterthur",
    "sg:orig_category":"Reiseb\u00fcros U Reiseveranstalter",
    "sg:postcode":"8400",
    "sg:province":"Z\u00fcrich",
    "wof:name":"Tiger Travel Weber Wil",
    "wof:placetype":"venue"
},
  "geometry": {"coordinates":[9.0382499695,47.4628448486],"type":"Point"}
}