{
  "type": "Feature",
  "properties": {
    "iso:country":"CH",
    "sg:address":"Unter Rennweg 11d Wolfhausen 8608 Bubikon. Postfach",
    "sg:city":"Wolfhausen",
    "sg:orig_category":"Erbringung von Dienstleistungen f\u00fcr Unternehmen",
    "sg:postcode":"8633",
    "sg:province":"Z\u00fcrich",
    "wof:name":"Picture Design By Marty H.",
    "wof:placetype":"venue"
},
  "geometry": {"coordinates":[8.8189096451,47.2684555054],"type":"Point"}
}