{
  "type": "Feature",
  "properties": {
    "iso:country":"CH",
    "sg:address":"Bahnhofstrasse 16",
    "sg:city":"N\u00e4fels",
    "sg:orig_category":"Zahnarztpraxen",
    "sg:phone":"+41 55 612 11 78",
    "sg:postcode":"8752",
    "sg:province":"Glarus",
    "wof:name":"Dr. Med. Dent. Walter Landolt Zahnarzt",
    "wof:placetype":"venue"
},
  "geometry": {"coordinates":[9.0660066605,47.0993232727],"type":"Point"}
}