{
  "type": "Feature",
  "properties": {
    "iso:country":"CH",
    "sg:address":"Einsiedlerstrasse 292",
    "sg:city":"Horgen",
    "sg:orig_category":"Detailhandel mit M\u00f6beln U Haushaltsgegenst\u00e4nden",
    "sg:phone":"+41 17256375",
    "sg:postcode":"8810",
    "sg:province":"Z\u00fcrich",
    "wof:name":"Teppichleger-service, Jos\u00e9 Luque",
    "wof:placetype":"venue"
},
  "geometry": {"coordinates":[8.6046333313,47.2486114502],"type":"Point"}
}