{
  "type": "Feature",
  "properties": {
    "iso:country":"CH",
    "sg:address":"Im Hof",
    "sg:city":"Lichtensteig",
    "sg:orig_category":"Non-Classified Establishments",
    "sg:phone":"+41 71 374 29 61",
    "sg:postcode":"9620",
    "sg:province":"St. Gallen",
    "wof:name":"Mauron & Giezendanner Gmbh",
    "wof:placetype":"venue"
},
  "geometry": {"coordinates":[9.0867376328,47.3248672485],"type":"Point"}
}