{
  "type": "Feature",
  "properties": {
    "iso:country":"CH",
    "sg:address":"Thiersteinerallee 66",
    "sg:city":"Basel",
    "sg:orig_category":"Non-Classified Establishments",
    "sg:postcode":"4053",
    "sg:province":"Basel-Stadt",
    "wof:name":"Thomas Alt Naturarzt",
    "wof:placetype":"venue"
},
  "geometry": {"coordinates":[7.5968818665,47.5404472351],"type":"Point"}
}