{
  "type": "Feature",
  "properties": {
    "iso:country":"CH",
    "sg:address":"Avenue De La Gare",
    "sg:city":"V\u00e9troz",
    "sg:classifiers":[
        {
            "category":"Utilities",
            "subcategory":"Recycling",
            "type":"Services"
        }
    ],
    "sg:phone":"+41 27 346 39 62",
    "sg:postcode":"1963",
    "sg:province":"Valais",
    "sg:tags":[
        "metal"
    ],
    "wof:name":"Jean-jacques Bader",
    "wof:placetype":"venue"
},
  "geometry": {"coordinates":[7.2725601196,46.2191390991],"type":"Point"}
}