{
  "type": "Feature",
  "properties": {
    "iso:country":"CH",
    "sg:address":"Prattelerstrasse 44",
    "sg:city":"Birsfelden",
    "sg:orig_category":"RESTAURANTS: TEA-ROOMS",
    "sg:phone":"+41 61 711 66 06",
    "sg:postcode":"4127",
    "sg:province":"Basel-Landschaft",
    "wof:name":"Antonio Bandera, Transporte",
    "wof:placetype":"venue"
},
  "geometry": {"coordinates":[7.6268129349,47.5471763611],"type":"Point"}
}