{
  "type": "Feature",
  "properties": {
    "iso:country":"CH",
    "sg:address":"Oberdorfstrasse 91",
    "sg:city":"M\u00fcnchenbuchsee",
    "sg:orig_category":"Unclassifiable Establishments",
    "sg:phone":"+41 31 869 61 69",
    "sg:postcode":"3053",
    "sg:province":"Bern",
    "wof:name":"Pizza Italy Akdemir Mehmet",
    "wof:placetype":"venue"
},
  "geometry": {"coordinates":[7.4369797707,47.0197906494],"type":"Point"}
}