{
  "type": "Feature",
  "properties": {
    "iso:country":"CH",
    "sg:address":"Route De Vernier 185",
    "sg:city":"Vernier",
    "sg:orig_category":"Autogaragen",
    "sg:phone":"+41 22 341 28 17",
    "sg:postcode":"1214",
    "sg:province":"Gen\u00e8ve",
    "wof:name":"Gaetano De Stefano Garage De Vernier",
    "wof:placetype":"venue"
},
  "geometry": {"coordinates":[6.090779,46.218666],"type":"Point"}
}