{
  "type": "Feature",
  "properties": {
    "iso:country":"CH",
    "sg:address":"Landstrasse 64",
    "sg:city":"Naters",
    "sg:orig_category":"Fahrschulen, Flugschulen",
    "sg:phone":"+41 27 924 13 50",
    "sg:postcode":"3904",
    "sg:province":"Valais",
    "wof:name":"Herbert Eyer Autofahrschule",
    "wof:placetype":"venue"
},
  "geometry": {"coordinates":[7.9939498901,46.3265914917],"type":"Point"}
}