{
  "type": "Feature",
  "properties": {
    "iso:country":"CH",
    "sg:address":"Karl-mathy-strasse 44",
    "sg:city":"Grenchen",
    "sg:orig_category":"Werbeberatung Werbung",
    "sg:phone":"+41 79 311 86 33",
    "sg:postcode":"2540",
    "sg:province":"Solothurn",
    "wof:name":"Ernst Gander Weag Werbeagentur",
    "wof:placetype":"venue"
},
  "geometry": {"coordinates":[7.3799600601,47.1870727539],"type":"Point"}
}