{
  "type": "Feature",
  "properties": {
    "iso:country":"CH",
    "sg:address":"Eggen 93",
    "sg:city":"Unterlangenegg",
    "sg:orig_category":"Herstellung von sonstigen landwirtschaftlichen Maschinen",
    "sg:phone":"+41 33 453 22 10",
    "sg:postcode":"3614",
    "sg:province":"Bern",
    "wof:name":"M\u00fchlethaler H.-u.",
    "wof:placetype":"venue"
},
  "geometry": {"coordinates":[7.691193,46.801003],"type":"Point"}
}