{
  "type": "Feature",
  "properties": {
    "iso:country":"CH",
    "sg:address":"Spitalgasse 4751 3011 Bern. Postfach",
    "sg:city":"Bern",
    "sg:orig_category":"Detailhandel mit Waren verschiedener Art, Hauptrichtung Nichtnahrungsmittel",
    "sg:phone":"+41 31 320 71 11",
    "sg:postcode":"3011",
    "sg:province":"Bern",
    "wof:name":"Loeb Ag",
    "wof:placetype":"venue"
},
  "geometry": {"coordinates":[7.4408202171,46.9477310181],"type":"Point"}
}