{
  "type": "Feature",
  "properties": {
    "iso:country":"CH",
    "sg:address":"L\u00f6wensteinstrasse 3",
    "sg:city":"Neuhausen",
    "sg:orig_category":"Fahrschulen, Flugschulen",
    "sg:phone":"+41 52 625 30 49",
    "sg:postcode":"8212",
    "sg:province":"Schaffhausen",
    "wof:name":"Scherrer Autofahrschule Gmbh",
    "wof:placetype":"venue"
},
  "geometry": {"coordinates":[8.6213054657,47.6941986084],"type":"Point"}
}