{
  "type": "Feature",
  "properties": {
    "iso:country":"CH",
    "sg:address":"Rheinsfelderstrasse 25 8193 Eglisau. Postfach",
    "sg:city":"Eglisau",
    "sg:orig_category":"Grosshandel mit Holz U Baustoffen Zimmerei, Ingenieurholzbau",
    "sg:phone":"+41 18670242",
    "sg:postcode":"8193",
    "sg:province":"Z\u00fcrich",
    "wof:name":"Hausheer Holzbau Ag",
    "wof:placetype":"venue"
},
  "geometry": {"coordinates":[8.5143728256,47.5742073059],"type":"Point"}
}