{
  "type": "Feature",
  "properties": {
    "iso:country":"CH",
    "sg:address":"Via Bossi 6",
    "sg:city":"Lugano",
    "sg:classifiers":[
        {
            "category":"Banks & Credit Unions",
            "subcategory":"Bank",
            "type":"Services"
        }
    ],
    "sg:phone":"+41 91 649 73 91",
    "sg:postcode":"6900",
    "sg:province":"Ticino",
    "wof:name":"Banca Raiffeisen Maroggia",
    "wof:placetype":"venue"
},
  "geometry": {"coordinates":[8.96975,45.936371],"type":"Point"}
}