{
  "type": "Feature",
  "properties": {
    "iso:country":"CH",
    "sg:address":"Els\u00e4sserstrasse 22 4056 Basel. Postfach",
    "sg:city":"Basel",
    "sg:orig_category":"Detailhandel mit B\u00fcchern Detailhandel mit B\u00fcchern, Zeitungen, Schreib U Papeteriewaren",
    "sg:phone":"+41 61 321 45 45",
    "sg:postcode":"4013",
    "sg:province":"Basel-Stadt",
    "wof:name":"Derba Buchhandlung Polat Y.",
    "wof:placetype":"venue"
},
  "geometry": {"coordinates":[7.58003,47.568768],"type":"Point"}
}