{
  "type": "Feature",
  "properties": {
    "iso:country":"CH",
    "sg:address":"Meierh\u00f6fliring 2",
    "sg:city":"Ruswil",
    "sg:orig_category":"Herstellung von k\u00e4lte U lufttechnischen Erzeugnissen f\u00fcr gewerbliche Zwecke",
    "sg:postcode":"6017",
    "sg:province":"Luzern",
    "wof:name":"Jenni Stall\u00fcftungen",
    "wof:placetype":"venue"
},
  "geometry": {"coordinates":[8.1347532272,47.0841140747],"type":"Point"}
}