{
  "type": "Feature",
  "properties": {
    "iso:country":"CH",
    "sg:address":"Via Aerodromo 44",
    "sg:city":"Ascona",
    "sg:orig_category":"Reinigungsgewerbe",
    "sg:postcode":"6612",
    "sg:province":"Ticino",
    "wof:name":"Pulita Putzteam Gmbh Bau Und Geb\u00e4udeunterhaltsreinigungen",
    "wof:placetype":"venue"
},
  "geometry": {"coordinates":[8.9322891235,47.2402305603],"type":"Point"}
}