{
  "type": "Feature",
  "properties": {
    "iso:country":"CH",
    "sg:address":"Via Cantonale Ostarietta",
    "sg:city":"Lamone",
    "sg:classifiers":[
        {
            "category":"Insurance",
            "subcategory":"Insurance Agent",
            "type":"Services"
        }
    ],
    "sg:phone":"+41 91 967 30 22",
    "sg:postcode":"6814",
    "sg:province":"Ticino",
    "sg:tags":[
        "versicherungsagenturen",
        "-broker"
    ],
    "wof:name":"Basilese Assicurazioni Agenzia O.bonomi & R.richina",
    "wof:placetype":"venue"
},
  "geometry": {"coordinates":[8.93151474,46.0453643799],"type":"Point"}
}