{
  "type": "Feature",
  "properties": {
    "addr:full":"Stockhornstrasse 12 Wichtrach Bern 3114",
    "addr:housenumber":"12",
    "addr:postcode":"3114",
    "addr:street":"Stockhornstrasse",
    "iso:country":"CH",
    "sg:address":"Stockhornstrasse 12",
    "sg:city":"Wichtrach",
    "sg:orig_category":"Internet, Alle Internetdienstleistungen",
    "sg:phone":"+41 31 781 45 67",
    "sg:postcode":"3114",
    "sg:province":"Bern",
    "wof:name":"The Swiss Design Factory",
    "wof:placetype":"venue"
},
  "geometry": {"coordinates":[7.567127,46.83646],"type":"Point"}
}