{
  "type": "Feature",
  "properties": {
    "iso:country":"CH",
    "sg:address":"1890",
    "sg:city":"St-maurice",
    "sg:orig_category":"Detailhandel mit Schuhen U Lederwaren",
    "sg:phone":"+41 24 485 28 38",
    "sg:postcode":"1890",
    "sg:province":"Valais",
    "wof:name":"Costanza Francesco",
    "wof:placetype":"venue"
},
  "geometry": {"coordinates":[7.0044598579,46.2167739868],"type":"Point"}
}