{
  "type": "Feature",
  "properties": {
    "iso:country":"CH",
    "sg:address":"Muttenzerstrasse 56",
    "sg:city":"Birsfelden",
    "sg:orig_category":"Non-Classified Establishments",
    "sg:postcode":"4127",
    "sg:province":"Basel-Landschaft",
    "wof:name":"Ernst Oberhauser Transporte",
    "wof:placetype":"venue"
},
  "geometry": {"coordinates":[7.6246581078,47.5481643677],"type":"Point"}
}