{
  "type": "Feature",
  "properties": {
    "iso:country":"CH",
    "sg:address":"1432",
    "sg:city":"Belmont-yverdon",
    "sg:orig_category":"Verwertung von Milch",
    "sg:postcode":"1432",
    "sg:province":"Vaud",
    "wof:name":"Societ\u00e9 De Laiterie Et D'agriculture De Ch\u00e9serex.",
    "wof:placetype":"venue"
},
  "geometry": {"coordinates":[6.1621308327,46.40990448],"type":"Point"}
}