{
  "type": "Feature",
  "properties": {
    "iso:country":"CH",
    "sg:address":"Dorfstrasse 26 4452 Itingen. Postfach",
    "sg:city":"Itingen",
    "sg:orig_category":"Herstellung von k\u00e4lte U lufttechnischen Erzeugnissen f\u00fcr gewerbliche Zwecke Installation von Heizung",
    "sg:phone":"+41 61 971 40 46",
    "sg:postcode":"4452",
    "sg:province":"Basel-Landschaft",
    "wof:name":"D & M K\u00e4ltebau Ag",
    "wof:placetype":"venue"
},
  "geometry": {"coordinates":[7.7847452164,47.4657897949],"type":"Point"}
}