{
  "type": "Feature",
  "properties": {
    "iso:country":"CH",
    "sg:address":"Obermattweg 33",
    "sg:city":"D\u00fcdingen",
    "sg:orig_category":"Erschliessung von Grundst\u00fccken",
    "sg:postcode":"3186",
    "sg:province":"Fribourg",
    "wof:name":"Mietergenossenschaft Obermattweg",
    "wof:placetype":"venue"
},
  "geometry": {"coordinates":[7.1845049858,46.8468208313],"type":"Point"}
}