{
  "type": "Feature",
  "properties": {
    "iso:country":"CH",
    "sg:address":"Hauptstr.",
    "sg:city":"Cazis",
    "sg:orig_category":"Maler U Glasergewerbe",
    "sg:phone":"+41 81 651 15 66",
    "sg:postcode":"7408",
    "sg:province":"Graubunden",
    "wof:name":"Derungs Umberto",
    "wof:placetype":"venue"
},
  "geometry": {"coordinates":[9.4273872375,46.7245292664],"type":"Point"}
}