{
  "type": "Feature",
  "properties": {
    "iso:country":"CH",
    "sg:address":"Lyssachstrasse 7",
    "sg:city":"Burgdorf",
    "sg:orig_category":"Handelsvermittlung von Brennstoffen, Erzen, Metallen U Chemikalien",
    "sg:phone":"+41 34 424 11 66",
    "sg:postcode":"3400",
    "sg:province":"Bern",
    "wof:name":"Rv Schwitter Trading",
    "wof:placetype":"venue"
},
  "geometry": {"coordinates":[7.6244158745,47.0583152771],"type":"Point"}
}