{
  "type": "Feature",
  "properties": {
    "iso:country":"CH",
    "sg:address":"Bielstrasse 26",
    "sg:city":"Br\u00fcgg",
    "sg:classifiers":[
        {
            "category":"Personal",
            "subcategory":"Hair Removal",
            "type":"Services"
        }
    ],
    "sg:phone":"+41 32 924 02 33",
    "sg:postcode":"2555",
    "sg:province":"Bern",
    "sg:tags":[
        "length",
        "cutting",
        "precision"
    ],
    "wof:name":"Pr\u00e9cimet Sa",
    "wof:placetype":"venue"
},
  "geometry": {"coordinates":[6.8075690269,47.0866279602],"type":"Point"}
}