{
  "type": "Feature",
  "properties": {
    "iso:country":"CH",
    "sg:address":"Boulevard Du Pont-d'arve 22 1205 Gen\u00e8ve. Postfach",
    "sg:city":"Gen\u00e8ve",
    "sg:classifiers":[
        {
            "category":"Professional",
            "subcategory":"Employment Agencies",
            "type":"Services"
        }
    ],
    "sg:phone":"+41 22 322 80 22",
    "sg:postcode":"1201",
    "sg:province":"Gen\u00e8ve",
    "sg:tags":[
        "personal",
        "u",
        "stellenvermittlung"
    ],
    "wof:name":"Val-job, Pierre-alain Revaz",
    "wof:placetype":"venue"
},
  "geometry": {"coordinates":[6.1900620461,46.1969070435],"type":"Point"}
}