{
  "type": "Feature",
  "properties": {
    "addr:full":"Rte Des Pralettes 1 Marly Fribourg 1723",
    "addr:housenumber":"1",
    "addr:postcode":"1723",
    "addr:street":"Rte Des Pralettes",
    "iso:country":"CH",
    "sg:address":"Rte Des Pralettes 1",
    "sg:city":"Marly",
    "sg:classifiers":[
        {
            "category":"Banks & Credit Unions",
            "subcategory":"Bank",
            "type":"Services"
        }
    ],
    "sg:phone":"+41 26 435 28 52",
    "sg:postcode":"1723",
    "sg:province":"Fribourg",
    "wof:name":"Union De Banques Suisses, Centre Commercial",
    "wof:placetype":"venue"
},
  "geometry": {"coordinates":[7.161209,46.775772],"type":"Point"}
}