{
  "type": "Feature",
  "properties": {
    "iso:country":"CH",
    "sg:address":"Gygerweg 35 3700 Spiez. Postfach 450",
    "sg:city":"Spiez",
    "sg:orig_category":"Betrieb von Taxis",
    "sg:phone":"+41 33 650 15 15",
    "sg:postcode":"3700",
    "sg:province":"Bern",
    "wof:name":"Dorf-taxi-spiez, Wagner & Kernen",
    "wof:placetype":"venue"
},
  "geometry": {"coordinates":[7.665144,46.684944],"type":"Point"}
}