{
  "type": "Feature",
  "properties": {
    "iso:country":"CH",
    "sg:address":"Route Principale 31",
    "sg:city":"Evilard",
    "sg:classifiers":[
        {
            "category":"Restaurant",
            "type":"Food & Drink"
        }
    ],
    "sg:phone":"+41 32 322 48 78",
    "sg:postcode":"2533",
    "sg:province":"Bern",
    "wof:name":"Caf\u00e9 Le Cyrano",
    "wof:placetype":"venue"
},
  "geometry": {"coordinates":[7.2397699356,47.1499900818],"type":"Point"}
}