{
  "type": "Feature",
  "properties": {
    "iso:country":"CH",
    "sg:address":"Rue Du Jeu-de-l'arc 15",
    "sg:city":"Gen\u00e8ve",
    "sg:orig_category":"Zahnarztpraxen",
    "sg:phone":"+41 21 903 12 17",
    "sg:postcode":"1200",
    "sg:province":"Gen\u00e8ve",
    "wof:name":"Dr M\u00e9d.dent. P\u00e0l De Bencz\u00e9di M\u00e9decin Dentiste",
    "wof:placetype":"venue"
},
  "geometry": {"coordinates":[6.0962400436,46.2026824951],"type":"Point"}
}