{
  "type": "Feature",
  "properties": {
    "iso:country":"CH",
    "sg:address":"Haldenstrasse 17",
    "sg:city":"Luzern",
    "sg:orig_category":"Museen",
    "sg:postcode":"6006",
    "sg:province":"Luzern",
    "wof:name":"Galerie Fischer Kollektivgesellschaft",
    "wof:placetype":"venue"
},
  "geometry": {"coordinates":[8.3148546219,47.0550804138],"type":"Point"}
}