{
  "type": "Feature",
  "properties": {
    "addr:full":"9466 Sennwald St. Gallen 9466",
    "addr:postcode":"9466;9466",
    "iso:country":"CH",
    "sg:address":"9466",
    "sg:city":"Sennwald",
    "sg:orig_category":"Allgemeiner Hoch U Tiefbau",
    "sg:phone":"+41 81 723 45 40",
    "sg:postcode":"9466",
    "sg:province":"St. Gallen",
    "wof:name":"Gantner E. + R. Ag",
    "wof:placetype":"venue"
},
  "geometry": {"coordinates":[9.41649,47.055885],"type":"Point"}
}