{
  "type": "Feature",
  "properties": {
    "iso:country":"CH",
    "sg:address":"Le Ch\u00e2teau",
    "sg:city":"Daillens",
    "sg:orig_category":"Mechanik Mechanische Werkst\u00e4tten",
    "sg:phone":"+41 61 713 21 21",
    "sg:postcode":"1306",
    "sg:province":"Vaud",
    "wof:name":"Moser Schleiferei & Poliererei Ag",
    "wof:placetype":"venue"
},
  "geometry": {"coordinates":[7.5976419449,47.4871902466],"type":"Point"}
}