{
  "type": "Feature",
  "properties": {
    "iso:country":"CH",
    "sg:address":"Langmauerstr. 109 8006 Z\u00fcrich. Postfach",
    "sg:city":"Z\u00fcrich",
    "sg:orig_category":"Architektur U Ingenieurb\u00fcros",
    "sg:phone":"+41 13641412",
    "sg:postcode":"8006",
    "sg:province":"Z\u00fcrich",
    "wof:name":"Verenum, Nussbaumer Dr. Thomas",
    "wof:placetype":"venue"
},
  "geometry": {"coordinates":[8.544212,47.393532],"type":"Point"}
}