{
  "type": "Feature",
  "properties": {
    "iso:country":"CH",
    "sg:address":"Sandrainstr. 11",
    "sg:city":"Niederhasli",
    "sg:orig_category":"Maschinen-Fabrikation",
    "sg:postcode":"8155",
    "sg:province":"Z\u00fcrich",
    "wof:name":"Wilkuma Ag",
    "wof:placetype":"venue"
},
  "geometry": {"coordinates":[8.2676105499,47.3589935303],"type":"Point"}
}