{
  "type": "Feature",
  "properties": {
    "iso:country":"CH",
    "sg:address":"Anglikerstrasse 34",
    "sg:city":"Villmergen",
    "sg:orig_category":"Dachdeckerei Zimmerei, Dachdeckerei, Bauspenglerei U Abdichtung",
    "sg:phone":"+41 56 622 68 02",
    "sg:postcode":"5612",
    "sg:province":"Aargau",
    "wof:name":"Peter L\u00fctolf Bedachungen",
    "wof:placetype":"venue"
},
  "geometry": {"coordinates":[8.248693,47.349411],"type":"Point"}
}