{
  "type": "Feature",
  "properties": {
    "iso:country":"CH",
    "sg:address":"B\u00f6hnirainstrasse 14/16",
    "sg:city":"Thalwil",
    "sg:orig_category":"Softwareentwicklung U beratung",
    "sg:postcode":"8800",
    "sg:province":"Z\u00fcrich",
    "wof:name":"Iacazzi Christian Electronique Et Informatique",
    "wof:placetype":"venue"
},
  "geometry": {"coordinates":[7.1084527969,46.9252319336],"type":"Point"}
}