{
  "type": "Feature",
  "properties": {
    "iso:country":"CH",
    "sg:address":"Gasometerstrasse 39",
    "sg:city":"Z\u00fcrich",
    "sg:orig_category":"Vorschulen, Kinderg\u00e4rten",
    "sg:postcode":"8005",
    "sg:province":"Z\u00fcrich",
    "wof:name":"St\u00e4dtischer Kindergarten",
    "wof:placetype":"venue"
},
  "geometry": {"coordinates":[8.5297775269,47.3850402832],"type":"Point"}
}