{
  "type": "Feature",
  "properties": {
    "iso:country":"CH",
    "sg:address":"Neuhofstrasse 1",
    "sg:city":"Baar",
    "sg:orig_category":"Unclassifiable Establishments",
    "sg:postcode":"6340",
    "sg:province":"Zug",
    "wof:name":"Megaposter.ch Ag",
    "wof:placetype":"venue"
},
  "geometry": {"coordinates":[8.5131387711,47.1912651062],"type":"Point"}
}