{
  "type": "Feature",
  "properties": {
    "iso:country":"CH",
    "sg:address":"Schaffhauserstrasse 110 8152 Glattbrugg. Postfach 47",
    "sg:city":"Glattbrugg",
    "sg:orig_category":"Versicherungen Hauptagenturen",
    "sg:phone":"+41 18105322",
    "sg:postcode":"8152",
    "sg:province":"Z\u00fcrich",
    "wof:name":"Z\u00fcrich Versicherungen Hauptagentur Glattbrugg",
    "wof:placetype":"venue"
},
  "geometry": {"coordinates":[8.5657157898,47.4332313538],"type":"Point"}
}