{
  "type": "Feature",
  "properties": {
    "iso:country":"CH",
    "sg:address":"Stationsstrasse 49 8833 Samstagern. Postfach 82",
    "sg:city":"Samstagern",
    "sg:classifiers":[
        {
            "category":"Restaurant",
            "type":"Food & Drink"
        }
    ],
    "sg:phone":"+41 17840988",
    "sg:postcode":"8833",
    "sg:province":"Z\u00fcrich",
    "wof:name":"Restaurant R\u00f6ssli",
    "wof:placetype":"venue"
},
  "geometry": {"coordinates":[8.6796751022,47.1928787231],"type":"Point"}
}