{
  "type": "Feature",
  "properties": {
    "addr:full":"Bahnhofstrasse 19 Wimmis Bern 3752",
    "addr:housenumber":"19",
    "addr:postcode":"3752",
    "addr:street":"Bahnhofstrasse;Bern",
    "iso:country":"CH",
    "sg:address":"Bahnhofstrasse 19",
    "sg:city":"Wimmis",
    "sg:orig_category":"Arztpraxen",
    "sg:phone":"+41 33 657 14 74",
    "sg:postcode":"3752",
    "sg:province":"Bern",
    "wof:name":"Dr.med.fritz Coester Arzt F.allgemeine Medizin Fmh",
    "wof:placetype":"venue"
},
  "geometry": {"coordinates":[7.637897,46.676178],"type":"Point"}
}