{
  "type": "Feature",
  "properties": {
    "iso:country":"CH",
    "sg:address":"Badenerstrasse 406 8004 Z\u00fcrich. Postfach",
    "sg:city":"Z\u00fcrich",
    "sg:orig_category":"Verarbeitung U Konservierung von Obst U Gem\u00fcse",
    "sg:postcode":"8004",
    "sg:province":"Z\u00fcrich",
    "wof:name":"Schlenk Franz & Co, Inh. Schlenk & Co",
    "wof:placetype":"venue"
},
  "geometry": {"coordinates":[8.5073423386,47.3797531128],"type":"Point"}
}