{
  "type": "Feature",
  "properties": {
    "iso:country":"CH",
    "sg:address":"Gru\u00e8re Rue De La 2 2350 Saignel\u00e9gier. Postfach",
    "sg:city":"Saignel\u00e9gier",
    "sg:orig_category":"Fachdetailhandel in Verkaufsr\u00e4umen",
    "sg:postcode":"2350",
    "sg:province":"Jura",
    "wof:name":"Jolwa Decor Scherer",
    "wof:placetype":"venue"
},
  "geometry": {"coordinates":[8.2043647766,47.0989952087],"type":"Point"}
}