{
  "type": "Feature",
  "properties": {
    "iso:country":"CH",
    "sg:address":"Gemsenstrasse 10",
    "sg:city":"Z\u00fcrich",
    "sg:orig_category":"Sonstige Institutionen des Sozialwesens ohne Beherbergung",
    "sg:phone":"+41 13625202",
    "sg:postcode":"8006",
    "sg:province":"Z\u00fcrich",
    "wof:name":"Claude Zangger Waespe M\u00fctterberatung Kreis 5",
    "wof:placetype":"venue"
},
  "geometry": {"coordinates":[8.5400362015,47.3887672424],"type":"Point"}
}