{
  "type": "Feature",
  "properties": {
    "iso:country":"CH",
    "sg:address":"Jaquet Rue Jean- 16 1201 Gen\u00e8ve. Postfach",
    "sg:city":"Gen\u00e8ve",
    "sg:orig_category":"Wirtschaftspr\u00fcfung, Steuerberatung U Treuhand",
    "sg:postcode":"1201",
    "sg:province":"Gen\u00e8ve",
    "wof:name":"Martinoli Gianpietro",
    "wof:placetype":"venue"
},
  "geometry": {"coordinates":[6.1511759758,46.2133255005],"type":"Point"}
}