{
  "type": "Feature",
  "properties": {
    "iso:country":"CH",
    "sg:address":"Avenue G\u00e9n\u00e9rale-guisan 44",
    "sg:city":"Rolle",
    "sg:orig_category":"D\u00e4mmung gegen K\u00e4lte, W\u00e4rme, Schall U Ersch\u00fctterung",
    "sg:phone":"+41 21 825 28 96",
    "sg:postcode":"1180",
    "sg:province":"Vaud",
    "wof:name":"Ruedy Tarsa Etanch\u00e9it\u00e9 & Isolation",
    "wof:placetype":"venue"
},
  "geometry": {"coordinates":[6.3306860924,46.458278656],"type":"Point"}
}