{
  "type": "Feature",
  "properties": {
    "iso:country":"CH",
    "sg:address":"T\u00f6sstalstrasse 23",
    "sg:city":"Winterthur",
    "sg:orig_category":"Kauf U Verkauf von Immobilien auf eigene Rechnung",
    "sg:postcode":"8400",
    "sg:province":"Z\u00fcrich",
    "wof:name":"Breity Ag",
    "wof:placetype":"venue"
},
  "geometry": {"coordinates":[8.733332634,47.4978065491],"type":"Point"}
}