{
  "type": "Feature",
  "properties": {
    "iso:country":"CH",
    "sg:address":"Br\u00fcckenstrasse 6a 4950 Huttwil. Postfach 326",
    "sg:city":"Huttwil",
    "sg:orig_category":"Herstellung von Rohren Stahl U Leichtmetallbau",
    "sg:phone":"+41 62 962 19 08",
    "sg:postcode":"4950",
    "sg:province":"Bern",
    "wof:name":"Peter Scheidegger Stahlrohrfabrikate, Rohrbiegerei Und Metallbau",
    "wof:placetype":"venue"
},
  "geometry": {"coordinates":[7.8637962341,47.1154403687],"type":"Point"}
}