{
  "type": "Feature",
  "properties": {
    "iso:country":"CH",
    "sg:address":"Chemin Du Carroz",
    "sg:city":"Chesi\u00e8res",
    "sg:orig_category":"Bauschreinerei Zimmerei, Dachdeckerei, Bauspenglerei U Abdichtung",
    "sg:phone":"+41 24 495 13 09",
    "sg:postcode":"1885",
    "sg:province":"Vaud",
    "wof:name":"Gallaz Gilbert",
    "wof:placetype":"venue"
},
  "geometry": {"coordinates":[7.043845,46.301235],"type":"Point"}
}