{
  "type": "Feature",
  "properties": {
    "iso:country":"CH",
    "sg:address":"Technikumstrasse 47",
    "sg:city":"Burgdorf",
    "sg:orig_category":"P\u00e9dicure",
    "sg:phone":"+41 34 422 99 84",
    "sg:postcode":"3400",
    "sg:province":"Bern",
    "wof:name":"Verena Bisig Huber P\u00e9dicure",
    "wof:placetype":"venue"
},
  "geometry": {"coordinates":[7.6148281097,47.059173584],"type":"Point"}
}