{
  "type": "Feature",
  "properties": {
    "iso:country":"CH",
    "sg:address":"Mittelstrasse 46",
    "sg:city":"Kirchlindach",
    "sg:orig_category":"Detailhandel mit Beleuchtungs U Haushaltsgegenst\u00e4nden",
    "sg:phone":"+41 79 278 52 92",
    "sg:postcode":"3038",
    "sg:province":"Bern",
    "wof:name":"Werner Bill Korbwarengesch\u00e4ft",
    "wof:placetype":"venue"
},
  "geometry": {"coordinates":[7.4040732384,46.9942436218],"type":"Point"}
}