{
  "type": "Feature",
  "properties": {
    "iso:country":"CH",
    "sg:address":"Untere Gasse 43",
    "sg:city":"Felsberg",
    "sg:orig_category":"Praxis f\u00fcr Atlaslogie",
    "sg:phone":"+41 81 252 82 59",
    "sg:postcode":"7012",
    "sg:province":"Graubunden",
    "wof:name":"Tino Schatz Praxis F\u00fcr Atlaslogie",
    "wof:placetype":"venue"
},
  "geometry": {"coordinates":[9.4736404419,46.8465042114],"type":"Point"}
}