{
  "type": "Feature",
  "properties": {
    "iso:country":"CH",
    "sg:address":"Via Vignascia 7",
    "sg:city":"Stabio",
    "sg:orig_category":"Institutionen f\u00fcr psychosoziale F\u00e4lle Sonderschulen",
    "sg:phone":"+41 91 647 19 31",
    "sg:postcode":"6855",
    "sg:province":"Ticino",
    "wof:name":"Centro Psico-educativo",
    "wof:placetype":"venue"
},
  "geometry": {"coordinates":[8.9347677231,45.8504638672],"type":"Point"}
}