{
  "type": "Feature",
  "properties": {
    "iso:country":"CH",
    "sg:address":"Schw\u00e4rzistrasse 7 8752 N\u00e4fels. Postfach",
    "sg:city":"N\u00e4fels",
    "sg:orig_category":"Ger\u00fcstbau Maler U Glasergewerbe",
    "sg:phone":"+41 31 971 52 70",
    "sg:postcode":"8752",
    "sg:province":"Glarus",
    "wof:name":"H\u00e4nni Ernst Gipserei Malerei Ag",
    "wof:placetype":"venue"
},
  "geometry": {"coordinates":[7.4403262138,46.9267234802],"type":"Point"}
}