{
  "type": "Feature",
  "properties": {
    "iso:country":"CH",
    "sg:address":"Ernetschwilerstrasse",
    "sg:city":"Gommiswald",
    "sg:orig_category":"Herstellung von Arbeits U Berufsbekleidung",
    "sg:phone":"+41 55 280 16 36",
    "sg:postcode":"8737",
    "sg:province":"St. Gallen",
    "wof:name":"Drabiga, P. Reiser",
    "wof:placetype":"venue"
},
  "geometry": {"coordinates":[9.0173406601,47.2365379333],"type":"Point"}
}