{
  "type": "Feature",
  "properties": {
    "iso:country":"CH",
    "sg:address":"Via Sond Paul 5",
    "sg:city":"Rh\u00e4z\u00fcns",
    "sg:classifiers":[
        {
            "category":"Utilities",
            "subcategory":"Sewage",
            "type":"Services"
        }
    ],
    "sg:phone":"+41 81 630 26 01",
    "sg:postcode":"7403",
    "sg:province":"Graubunden",
    "sg:tags":[
        "plant",
        "digestion",
        "tank",
        "equipment",
        "treatment",
        "sludge"
    ],
    "wof:name":"Cavelti & Partner",
    "wof:placetype":"venue"
},
  "geometry": {"coordinates":[9.3956041336,46.7960548401],"type":"Point"}
}