{
  "type": "Feature",
  "properties": {
    "iso:country":"CH",
    "sg:address":"Nordringstrasse 23 4702 Oensingen. Postfach 417",
    "sg:city":"Oensingen",
    "sg:orig_category":"Herstellung von Wellpapier U pappe sowie von Verpackungsmitteln aus Papier, Karton U Pappe",
    "sg:phone":"+41 62 388 01 23",
    "sg:postcode":"4702",
    "sg:province":"Solothurn",
    "wof:name":"Bourquin Sa",
    "wof:placetype":"venue"
},
  "geometry": {"coordinates":[7.7123231888,47.282661438],"type":"Point"}
}