{
  "type": "Feature",
  "properties": {
    "iso:country":"CH",
    "sg:address":"Unterer Quai 45",
    "sg:city":"Biel/bienne",
    "sg:classifiers":[
        {
            "category":"Social Services",
            "subcategory":"Retirement Home",
            "type":"Services"
        }
    ],
    "sg:phone":"+41 32 322 82 05",
    "sg:postcode":"2502",
    "sg:province":"Bern",
    "sg:tags":[
        "pflegeheime",
        "u",
        "alters"
    ],
    "wof:name":"Centre Rochat Betagten-& Pflegeheim",
    "wof:placetype":"venue"
},
  "geometry": {"coordinates":[7.245729,47.136959],"type":"Point"}
}