{
  "type": "Feature",
  "properties": {
    "iso:country":"CH",
    "sg:address":"Via San Salvatore 6 6900 Paradiso. Postfach",
    "sg:city":"Paradiso",
    "sg:orig_category":"Fachdetailhandel in Verkaufsr\u00e4umen",
    "sg:postcode":"6900",
    "sg:province":"Ticino",
    "wof:name":"Tecnigold International Sa, Madrid, Succursale Di Paradiso Articoli Di Gioielleria, Orologeria, Metalli Preziosi; Fabbricazione, Comm. Ecc",
    "wof:placetype":"venue"
},
  "geometry": {"coordinates":[8.9450292587,45.9919433594],"type":"Point"}
}