{
  "type": "Feature",
  "properties": {
    "iso:country":"CH",
    "sg:address":"Kirchstrasse 11",
    "sg:city":"Glarus",
    "sg:orig_category":"Detailhandel mit Damenbekleidung Detailhandel mit Herrenbekleidung",
    "sg:phone":"+41 55 640 19 81",
    "sg:postcode":"8750",
    "sg:province":"Glarus",
    "wof:name":"Hansruedi & Claudia Gubler Blue Hill Jeans-store",
    "wof:placetype":"venue"
},
  "geometry": {"coordinates":[9.0677442551,47.0408744812],"type":"Point"}
}