{
  "type": "Feature",
  "properties": {
    "iso:country":"CH",
    "sg:address":"Weinbergstrasse 57",
    "sg:city":"Grenchen",
    "sg:orig_category":"Verlegen von Fliesen U Platten",
    "sg:phone":"+41 32 682 24 92",
    "sg:postcode":"2540",
    "sg:province":"Solothurn",
    "wof:name":"Paul & Linda Vogt Chemin\u00e9ebau & Plattenbel\u00e4ge",
    "wof:placetype":"venue"
},
  "geometry": {"coordinates":[7.3848409653,47.1943054199],"type":"Point"}
}