{
  "type": "Feature",
  "properties": {
    "iso:country":"CH",
    "sg:address":"Rotachstrasse 30 8003 Z\u00fcrich. Postfach",
    "sg:city":"Z\u00fcrich",
    "sg:orig_category":"Detailhandel mit Antiquit\u00e4ten Detailhandel mit Uhren U Schmuck",
    "sg:phone":"+41 14511866",
    "sg:postcode":"8022",
    "sg:province":"Z\u00fcrich",
    "wof:name":"Matthias M\u00fcri Antiquit\u00e4ten Uhren Schmuck",
    "wof:placetype":"venue"
},
  "geometry": {"coordinates":[8.515098,47.370899],"type":"Point"}
}