{
  "type": "Feature",
  "properties": {
    "iso:country":"CH",
    "sg:address":"Dorfstrasse 42",
    "sg:city":"Bolligen",
    "sg:orig_category":"Vereine Gesang",
    "sg:phone":"+41 31 921 28 53",
    "sg:postcode":"3065",
    "sg:province":"Bern",
    "wof:name":"Reformierter Kirchenchor",
    "wof:placetype":"venue"
},
  "geometry": {"coordinates":[7.4991230965,46.9840087891],"type":"Point"}
}