{
  "type": "Feature",
  "properties": {
    "iso:country":"CH",
    "sg:address":"Grand-rue 20",
    "sg:city":"Vouvry",
    "sg:orig_category":"Reinigungsgewerbe",
    "sg:phone":"+41 24 481 45 79",
    "sg:postcode":"1896",
    "sg:province":"Valais",
    "wof:name":"Pot Gr\u00e9gory - Syst\u00e8me 3 D",
    "wof:placetype":"venue"
},
  "geometry": {"coordinates":[6.8886060715,46.3362197876],"type":"Point"}
}