{
  "type": "Feature",
  "properties": {
    "iso:country":"CH",
    "sg:address":"Adelmatt 359",
    "sg:city":"Birr",
    "sg:orig_category":"Non-Classified Establishments",
    "sg:phone":"+41 56 444 89 89",
    "sg:postcode":"5242",
    "sg:province":"Aargau",
    "wof:name":"Sasso Handels Und Transport Ag",
    "wof:placetype":"venue"
},
  "geometry": {"coordinates":[8.2047901154,47.4378013611],"type":"Point"}
}