{
  "type": "Feature",
  "properties": {
    "iso:country":"CH",
    "sg:address":"3087",
    "sg:city":"Niedermuhlern",
    "sg:orig_category":"Detailhandel mit Milcherzeugnissen U Eiern Verarbeitung von Milch",
    "sg:phone":"+41 34 435 12 17",
    "sg:postcode":"3087",
    "sg:province":"Bern",
    "wof:name":"Fritz Jakob K\u00e4serei",
    "wof:placetype":"venue"
},
  "geometry": {"coordinates":[7.730618,47.065246582],"type":"Point"}
}