{
  "type": "Feature",
  "properties": {
    "iso:country":"CH",
    "sg:address":"Roswiesenstrasse 4",
    "sg:city":"Z\u00fcrich",
    "sg:orig_category":"Massagestudios",
    "sg:phone":"+41 56 664 16 49",
    "sg:postcode":"8051",
    "sg:province":"Z\u00fcrich",
    "wof:name":"Elsbeth Stierli Arnold Massagen",
    "wof:placetype":"venue"
},
  "geometry": {"coordinates":[8.3174819946,47.2825775146],"type":"Point"}
}