{
  "type": "Feature",
  "properties": {
    "iso:country":"CH",
    "sg:address":"J\u00f6riacherstrasse 3",
    "sg:city":"Birr",
    "sg:classifiers":[
        {
            "category":"Manufacturing",
            "subcategory":"Motor Vehicles & Parts",
            "type":"Manufacturing & Wholesale Goods"
        }
    ],
    "sg:phone":"+41 56 450 05 10",
    "sg:postcode":"5242",
    "sg:province":"Aargau",
    "sg:tags":[
        "automotive",
        "industry",
        "component",
        "plastic"
    ],
    "wof:name":"M\u00fcller Kunststofftechnik Ag",
    "wof:placetype":"venue"
},
  "geometry": {"coordinates":[8.2155447006,47.4293327332],"type":"Point"}
}