{
  "type": "Feature",
  "properties": {
    "iso:country":"CH",
    "sg:address":"Ebenalpstrasse 12",
    "sg:city":"Kreuzlingen",
    "sg:orig_category":"Architektur U Ingenieurb\u00fcros Architekturb\u00fcros",
    "sg:phone":"+41 71 677 40 60",
    "sg:postcode":"8280",
    "sg:province":"Thurgau",
    "wof:name":"Klein & M\u00fcller Architekten",
    "wof:placetype":"venue"
},
  "geometry": {"coordinates":[9.170609,47.641396],"type":"Point"}
}