{
  "type": "Feature",
  "properties": {
    "iso:country":"CH",
    "sg:address":"Industriestrasse 1563",
    "sg:city":"Spiez",
    "sg:classifiers":[
        {
            "category":"Professional",
            "subcategory":"Engineering",
            "type":"Services"
        }
    ],
    "sg:phone":"+41 33 654 20 32",
    "sg:postcode":"3700",
    "sg:province":"Bern",
    "sg:tags":[
        "utensil",
        "baking",
        "pan"
    ],
    "wof:name":"Schnydrig Ag",
    "wof:placetype":"venue"
},
  "geometry": {"coordinates":[7.640822,46.697887],"type":"Point"}
}