{
  "type": "Feature",
  "properties": {
    "iso:country":"CH",
    "sg:address":"Rue Du Vallon 32",
    "sg:city":"Lausanne",
    "sg:orig_category":"Druck ohne Zeitungsdruck Offsetdruck",
    "sg:phone":"+41 32 725 26 25",
    "sg:postcode":"1005",
    "sg:province":"Vaud",
    "wof:name":"Imprimerie Commerciale Baillod Et Aub\u00e9e Sa",
    "wof:placetype":"venue"
},
  "geometry": {"coordinates":[6.9363808632,46.9942970276],"type":"Point"}
}