{
  "type": "Feature",
  "properties": {
    "iso:country":"CH",
    "sg:address":"Hauptstrasse 86",
    "sg:city":"Birsfelden",
    "sg:classifiers":[
        {
            "category":"Restaurant",
            "type":"Food & Drink"
        }
    ],
    "sg:postcode":"4127",
    "sg:province":"Basel-Landschaft",
    "wof:name":"Restaurant Nemrut",
    "wof:placetype":"venue"
},
  "geometry": {"coordinates":[6.8280057907,47.1011314392],"type":"Point"}
}