{
  "type": "Feature",
  "properties": {
    "iso:country":"CH",
    "sg:address":"Tramstrasse 7 9444 Diepoldsau. Postfach",
    "sg:city":"Diepoldsau",
    "sg:orig_category":"Fachdetailhandel in Verkaufsr\u00e4umen",
    "sg:phone":"+41 71 733 23 83",
    "sg:postcode":"9444",
    "sg:province":"St. Gallen",
    "wof:name":"Velo Hangar, R. Burkhard",
    "wof:placetype":"venue"
},
  "geometry": {"coordinates":[9.6533851624,47.3869819641],"type":"Point"}
}