{
  "type": "Feature",
  "properties": {
    "iso:country":"CH",
    "sg:address":"Rue Du Coll\u00e8ge 22",
    "sg:city":"Clarens",
    "sg:orig_category":"Herstellung von Metallerzeugnissen ohne Maschinenbau Maschinenbau",
    "sg:phone":"+41 21 964 42 41",
    "sg:postcode":"1815",
    "sg:province":"Vaud",
    "wof:name":"Hytronic Sa",
    "wof:placetype":"venue"
},
  "geometry": {"coordinates":[6.8947529793,46.443523407],"type":"Point"}
}