{
  "type": "Feature",
  "properties": {
    "iso:country":"CH",
    "sg:address":"L\u00e4rchenb\u00fchl",
    "sg:city":"Malters",
    "sg:orig_category":"Allgemeiner Hoch U Tiefbau Hoch U Tiefbau",
    "sg:phone":"+41 41 497 46 00",
    "sg:postcode":"6102",
    "sg:province":"Luzern",
    "wof:name":"Hans Bucheli Baugesch\u00e4ft",
    "wof:placetype":"venue"
},
  "geometry": {"coordinates":[8.182725,47.036816],"type":"Point"}
}