{
  "type": "Feature",
  "properties": {
    "iso:country":"CH",
    "sg:address":"Ursy-centre B",
    "sg:city":"Ursy",
    "sg:orig_category":"Fachdetailhandel mit pharmazeutischen Produkten",
    "sg:phone":"+41 27 957 26 18",
    "sg:postcode":"1670",
    "sg:province":"Fribourg",
    "wof:name":"Valesia Apotheke Dr. Brantschen Dr. A.",
    "wof:placetype":"venue"
},
  "geometry": {"coordinates":[7.933672905,46.1117172241],"type":"Point"}
}