{
  "type": "Feature",
  "properties": {
    "iso:country":"CH",
    "sg:address":"Chilchrain 23",
    "sg:city":"Limpach",
    "sg:orig_category":"Wirtschaftspr\u00fcfung, Steuerberatung U Treuhand",
    "sg:postcode":"3317",
    "sg:province":"Bern",
    "wof:name":"Treuhandb\u00fcro Feurer P.",
    "wof:placetype":"venue"
},
  "geometry": {"coordinates":[7.4944500923,47.1063117981],"type":"Point"}
}