{
  "type": "Feature",
  "properties": {
    "addr:full":"Freie Strasse 103 4051 Basel. Postfach 304 Basel Basel-Stadt 4010",
    "addr:housenumber":"103;304",
    "addr:postcode":"4051;4010",
    "addr:street":"Freie Strasse;Postfach",
    "iso:country":"CH",
    "sg:address":"Freie Strasse 103 4051 Basel. Postfach 304",
    "sg:city":"Basel",
    "sg:orig_category":"Advokaturb\u00fcros Notariate",
    "sg:phone":"+41 61 272 45 42",
    "sg:postcode":"4010",
    "sg:province":"Basel-Stadt",
    "wof:name":"Dr.rolf Holliger Advokatur-& Notariatsb\u00fcro",
    "wof:placetype":"venue"
},
  "geometry": {"coordinates":[7.591784,47.554405],"type":"Point"}
}