{
  "type": "Feature",
  "properties": {
    "iso:country":"CH",
    "sg:address":"Avenue Pictet-de-rochemont 24",
    "sg:city":"Gen\u00e8ve",
    "sg:orig_category":"Tanzschulen, Tanzlehrer",
    "sg:phone":"+41 22 736 72 86",
    "sg:postcode":"1207",
    "sg:province":"Gen\u00e8ve",
    "wof:name":"Ecole De Danse Rozecclub Madame Yvonne Rozec",
    "wof:placetype":"venue"
},
  "geometry": {"coordinates":[6.161465168,46.2005615234],"type":"Point"}
}