{
  "type": "Feature",
  "properties": {
    "iso:country":"CH",
    "sg:address":"Z\u00e4hringerstrasse 22",
    "sg:city":"Bern",
    "sg:classifiers":[
        {
            "category":"Social Services",
            "subcategory":"Retirement Home",
            "type":"Services"
        }
    ],
    "sg:phone":"+41 31 301 37 92",
    "sg:postcode":"3012",
    "sg:province":"Bern",
    "sg:tags":[
        "pflegeheime",
        "u",
        "alters"
    ],
    "wof:name":"Altersheim Mon Repos",
    "wof:placetype":"venue"
},
  "geometry": {"coordinates":[7.434893,46.955093],"type":"Point"}
}