{
  "type": "Feature",
  "properties": {
    "iso:country":"CH",
    "sg:address":"Zilistude 168",
    "sg:city":"Mellikon",
    "sg:orig_category":"Architektur U Ingenieurb\u00fcros",
    "sg:phone":"+41 56 243 10 10",
    "sg:postcode":"5465",
    "sg:province":"Aargau",
    "wof:name":"Air Engineering",
    "wof:placetype":"venue"
},
  "geometry": {"coordinates":[8.337855,47.568508],"type":"Point"}
}