{
  "type": "Feature",
  "properties": {
    "iso:country":"CH",
    "sg:address":"7417",
    "sg:city":"Paspels",
    "sg:classifiers":[
        {
            "category":"Restaurant",
            "type":"Food & Drink"
        }
    ],
    "sg:phone":"+41 81 655 12 53",
    "sg:postcode":"7417",
    "sg:province":"Graubunden",
    "wof:name":"Restaurant Hirschen",
    "wof:placetype":"venue"
},
  "geometry": {"coordinates":[9.4423751831,46.7492599487],"type":"Point"}
}