{
  "type": "Feature",
  "properties": {
    "iso:country":"CH",
    "sg:address":"St-julien Route De 78 1212 Grand-lancy. Postfach",
    "sg:city":"Cointrin",
    "sg:orig_category":"Sonstiger Grosshandel",
    "sg:phone":"+41 19354801",
    "sg:postcode":"1216",
    "sg:province":"Gen\u00e8ve",
    "wof:name":"Avalange Ag",
    "wof:placetype":"venue"
},
  "geometry": {"coordinates":[8.7636432648,47.3047790527],"type":"Point"}
}