{
  "type": "Feature",
  "properties": {
    "iso:country":"CH",
    "sg:address":"Seestrasse",
    "sg:city":"Meggen",
    "sg:orig_category":"Detailhandel mit Zeitungen U Zeitschriften Kioske",
    "sg:phone":"+41 41 349 12 84",
    "sg:postcode":"6045",
    "sg:province":"Luzern",
    "wof:name":"Strandbad",
    "wof:placetype":"venue"
},
  "geometry": {"coordinates":[8.3788404465,47.0455818176],"type":"Point"}
}