{
  "type": "Feature",
  "properties": {
    "iso:country":"CH",
    "sg:address":"Brunnmattstrasse 46 8103 Unterengstringen. Postfach 117",
    "sg:city":"Unterengstringen",
    "sg:orig_category":"Architektur U Ingenieurb\u00fcros Unternehmensberatung",
    "sg:phone":"+41 17751111",
    "sg:postcode":"8103",
    "sg:province":"Z\u00fcrich",
    "wof:name":"Schlumpf + Partner",
    "wof:placetype":"venue"
},
  "geometry": {"coordinates":[8.446698,47.415771],"type":"Point"}
}