{
  "type": "Feature",
  "properties": {
    "iso:country":"CH",
    "sg:address":"Via Novazzano",
    "sg:city":"Genestrerio",
    "sg:orig_category":"Instandhaltung U Reparatur von Automobilen",
    "sg:postcode":"6852",
    "sg:province":"Ticino",
    "wof:name":"Garage Cuenot, Succ. Oberli & Cie",
    "wof:placetype":"venue"
},
  "geometry": {"coordinates":[6.7551341057,47.0612411499],"type":"Point"}
}