{
  "type": "Feature",
  "properties": {
    "iso:country":"CH",
    "sg:address":"Oberboden 512 9052 Niederteufen. Postfach",
    "sg:city":"Niederteufen",
    "sg:orig_category":"Pensionskassen",
    "sg:postcode":"9052",
    "sg:province":"Appenzell Ausserrhoden",
    "wof:name":"Stiftung Fritz Z\u00fcrcher",
    "wof:placetype":"venue"
},
  "geometry": {"coordinates":[9.3662052155,47.3930549622],"type":"Point"}
}