{
  "type": "Feature",
  "properties": {
    "iso:country":"CH",
    "sg:address":"Imfeldstrasse 63 8037 Z\u00fcrich. Postfach",
    "sg:city":"Z\u00fcrich",
    "sg:orig_category":"Werbung",
    "sg:phone":"+41 21 634 60 63",
    "sg:postcode":"8037",
    "sg:province":"Z\u00fcrich",
    "wof:name":"Blanchet Jean-claude",
    "wof:placetype":"venue"
},
  "geometry": {"coordinates":[6.5887241364,46.5350456238],"type":"Point"}
}