{
  "type": "Feature",
  "properties": {
    "iso:country":"CH",
    "sg:address":"Flurweg 3",
    "sg:city":"Wettingen",
    "sg:orig_category":"Informatikdienste Softwareentwicklung U beratung",
    "sg:phone":"+41 19056556",
    "sg:postcode":"5430",
    "sg:province":"Aargau",
    "wof:name":"Bytics Technologie Ag",
    "wof:placetype":"venue"
},
  "geometry": {"coordinates":[8.7090778351,47.3452835083],"type":"Point"}
}