{
  "type": "Feature",
  "properties": {
    "iso:country":"CH",
    "sg:address":"Hauptstrasse 175",
    "sg:city":"Bubendorf",
    "sg:classifiers":[
        {
            "category":"Military Area",
            "subcategory":"Air Force Base",
            "type":"Public Place"
        }
    ],
    "sg:phone":"+41 61 931 40 30",
    "sg:postcode":"4416",
    "sg:province":"Basel-Landschaft",
    "sg:tags":[
        "steel",
        "pipe",
        "fitting",
        "made",
        "stainless"
    ],
    "wof:name":"Ef Edelstahl Fittings Ag",
    "wof:placetype":"venue"
},
  "geometry": {"coordinates":[7.730403,47.440578],"type":"Point"}
}