{
  "type": "Feature",
  "properties": {
    "iso:country":"CH",
    "sg:address":"Impasse De La Palaz 12",
    "sg:city":"Payerne",
    "sg:orig_category":"Malerei",
    "sg:phone":"+41 26 660 13 44",
    "sg:postcode":"1530",
    "sg:province":"Vaud",
    "wof:name":"Edgar Heer Peinture",
    "wof:placetype":"venue"
},
  "geometry": {"coordinates":[6.9333090782,46.8233947754],"type":"Point"}
}