{
  "type": "Feature",
  "properties": {
    "iso:country":"CH",
    "sg:address":"St\u00f6ckackerstrasse 92 3018 Bern. Postfach",
    "sg:city":"Bern",
    "sg:orig_category":"Sonstiger Grosshandel",
    "sg:postcode":"3018",
    "sg:province":"Bern",
    "wof:name":"Rubli L. B. Rubano-trading Waren Aller Art; Handel",
    "wof:placetype":"venue"
},
  "geometry": {"coordinates":[7.3998689651,46.9441604614],"type":"Point"}
}