{
  "type": "Feature",
  "properties": {
    "iso:country":"CH",
    "sg:address":"St. Johanns-vorstadt 70",
    "sg:city":"Basel",
    "sg:orig_category":"Gesundheitswesen",
    "sg:phone":"+41 61 383 27 80",
    "sg:postcode":"4056",
    "sg:province":"Basel-Stadt",
    "wof:name":"Medizinische Laserpraxis Am Rhein Gmbh",
    "wof:placetype":"venue"
},
  "geometry": {"coordinates":[7.5834407806,47.5650024414],"type":"Point"}
}