{
  "type": "Feature",
  "properties": {
    "addr:full":"Alte Simplonstrasse 8 Brig Valais 3900",
    "addr:housenumber":"8",
    "addr:postcode":"3900",
    "addr:street":"Alte Simplonstrasse",
    "iso:country":"CH",
    "sg:address":"Alte Simplonstrasse 8",
    "sg:city":"Brig",
    "sg:orig_category":"Detailhandel mit Bekleidung Detailhandel mit Damenbekleidung",
    "sg:phone":"+41 27 923 07 24",
    "sg:postcode":"3900",
    "sg:province":"Valais",
    "wof:name":"Boutique Mona Lisa",
    "wof:placetype":"venue"
},
  "geometry": {"coordinates":[7.9889,46.316341],"type":"Point"}
}