{
  "type": "Feature",
  "properties": {
    "iso:country":"CH",
    "sg:address":"Schlossgasse 12",
    "sg:city":"Weinfelden",
    "sg:orig_category":"Fotografische Ateliers",
    "sg:phone":"+41 71 622 03 60",
    "sg:postcode":"8570",
    "sg:province":"Thurgau",
    "wof:name":"Lukas Fleischer Fotografisches Atelier",
    "wof:placetype":"venue"
},
  "geometry": {"coordinates":[9.1063909531,47.571434021],"type":"Point"}
}