{
  "type": "Feature",
  "properties": {
    "addr:full":"St. Johanns-vorstadt 19 4056 Basel. Postfach Basel Basel-Stadt 4051",
    "addr:housenumber":"19",
    "addr:postcode":"4056;4051",
    "addr:street":"Postfach",
    "iso:country":"CH",
    "sg:address":"St. Johanns-vorstadt 19 4056 Basel. Postfach",
    "sg:city":"Basel",
    "sg:orig_category":"Allgemeiner Hoch U Tiefbau",
    "sg:postcode":"4051",
    "sg:province":"Basel-Stadt",
    "wof:name":"Arch 4 Gmbh Geb\u00e4udebau, Technischer Hilfsdienst, Betonarbeiten",
    "wof:placetype":"venue"
},
  "geometry": {"coordinates":[7.584411,47.563332],"type":"Point"}
}