{
  "type": "Feature",
  "properties": {
    "iso:country":"CH",
    "sg:address":"Lodrino-prosito",
    "sg:city":"Lodrino",
    "sg:orig_category":"Zimmerei, Dachdeckerei, Bauspenglerei U Abdichtung",
    "sg:postcode":"6527",
    "sg:province":"Ticino",
    "wof:name":"Laube Augusto",
    "wof:placetype":"venue"
},
  "geometry": {"coordinates":[8.9821529388,46.300365448],"type":"Point"}
}