{
  "type": "Feature",
  "properties": {
    "iso:country":"CH",
    "sg:address":"8604",
    "sg:city":"Volketswil",
    "sg:orig_category":"Unclassifiable Establishments",
    "sg:postcode":"8604",
    "sg:province":"Z\u00fcrich",
    "wof:name":"Prs Ag, Zweigniederlassung Volki-land",
    "wof:placetype":"venue"
},
  "geometry": {"coordinates":[8.6897258759,47.3896369934],"type":"Point"}
}