{
  "type": "Feature",
  "properties": {
    "iso:country":"CH",
    "sg:address":"Via Brentani 9",
    "sg:city":"Lugano",
    "sg:orig_category":"Herstellung von Betonerzeugnissen f\u00fcr den Bau Herstellung von elektronischen Bauelementen",
    "sg:phone":"+41 91 972 18 83",
    "sg:postcode":"6900",
    "sg:province":"Ticino",
    "wof:name":"Richter System Gmbh",
    "wof:placetype":"venue"
},
  "geometry": {"coordinates":[8.9594650269,46.0191688538],"type":"Point"}
}