{
  "type": "Feature",
  "properties": {
    "iso:country":"CH",
    "sg:address":"Im Ifang 7",
    "sg:city":"Effretikon",
    "sg:orig_category":"Gartenbau",
    "sg:phone":"+41 52 343 59 17",
    "sg:postcode":"8307",
    "sg:province":"Z\u00fcrich",
    "wof:name":"Ralf & Irene Kn\u00fcppel Gartenbau",
    "wof:placetype":"venue"
},
  "geometry": {"coordinates":[8.6885528564,47.4311332703],"type":"Point"}
}