{
  "type": "Feature",
  "properties": {
    "iso:country":"CH",
    "sg:address":"Klosbachstrasse 67",
    "sg:city":"Z\u00fcrich",
    "sg:orig_category":"Lebensversicherung Versicherungsgewerbe",
    "sg:phone":"+41 12607363",
    "sg:postcode":"8032",
    "sg:province":"Z\u00fcrich",
    "wof:name":"Andre Br\u00fcgger, Swiss Life",
    "wof:placetype":"venue"
},
  "geometry": {"coordinates":[8.5588550568,47.3671875],"type":"Point"}
}