{
  "type": "Feature",
  "properties": {
    "iso:country":"CH",
    "sg:address":"Pury Place 4",
    "sg:city":"Neuch\u00e2tel",
    "sg:orig_category":"Pensionskassen",
    "sg:phone":"+41 38236111",
    "sg:postcode":"2000",
    "sg:province":"Neuch\u00e2tel",
    "wof:name":"Fondation Collective Banque Cantonale Neuch\u00e2teloise Deuxi\u00e8me Pilier",
    "wof:placetype":"venue"
},
  "geometry": {"coordinates":[6.9287929535,46.9898796082],"type":"Point"}
}