{
  "type": "Feature",
  "properties": {
    "iso:country":"CH",
    "sg:address":"Bleikenstrasse 12",
    "sg:city":"Wattwil",
    "sg:orig_category":"Einbau von Schreinerwaren",
    "sg:phone":"+41 71 277 26 52",
    "sg:postcode":"9630",
    "sg:province":"St. Gallen",
    "wof:name":"Franz Manser Einbauk\u00fcchen",
    "wof:placetype":"venue"
},
  "geometry": {"coordinates":[9.3259153366,47.4036445618],"type":"Point"}
}