{
  "type": "Feature",
  "properties": {
    "addr:full":"Hauptstrasse 54 Magden Aargau 4312",
    "addr:housenumber":"54",
    "addr:postcode":"4312",
    "addr:street":"Hauptstrasse",
    "iso:country":"CH",
    "sg:address":"Hauptstrasse 54",
    "sg:city":"Magden",
    "sg:orig_category":"Aktivit\u00e4ten der Generalunternehmen im Baugewerbe Allgemeiner Hoch U Tiefbau",
    "sg:phone":"+41 79 415 35 02",
    "sg:postcode":"4312",
    "sg:province":"Aargau",
    "wof:name":"Nowe Bau Ag Generalunternehmung",
    "wof:placetype":"venue"
},
  "geometry": {"coordinates":[7.809168,47.529816],"type":"Point"}
}