{
  "type": "Feature",
  "properties": {
    "iso:country":"CH",
    "sg:address":"Chemin De Valerie 63",
    "sg:city":"Chamb\u00e9sy",
    "sg:orig_category":"Reiseb\u00fcros U Reiseveranstalter",
    "sg:postcode":"1292",
    "sg:province":"Gen\u00e8ve",
    "wof:name":"Hosts Sa",
    "wof:placetype":"venue"
},
  "geometry": {"coordinates":[6.1371321678,46.246723175],"type":"Point"}
}