{
  "type": "Feature",
  "properties": {
    "iso:country":"CH",
    "sg:address":"Worbstrasse 185 3073 G\u00fcmligen. Postfach",
    "sg:city":"G\u00fcmligen",
    "sg:orig_category":"Gesundheitswesen",
    "sg:postcode":"3073",
    "sg:province":"Bern",
    "wof:name":"Vogt Dr. Med. E. Gmbh",
    "wof:placetype":"venue"
},
  "geometry": {"coordinates":[7.5026640892,46.9344673157],"type":"Point"}
}