{
  "type": "Feature",
  "properties": {
    "iso:country":"CH",
    "sg:address":"Rue Du Fort-barreau 19",
    "sg:city":"Gen\u00e8ve",
    "sg:orig_category":"Organisationen des Gesundheitswesen",
    "sg:phone":"+41 22 733 13 90",
    "sg:postcode":"1201",
    "sg:province":"Gen\u00e8ve",
    "wof:name":"Centre M\u00e9dico-social Des Grottes",
    "wof:placetype":"venue"
},
  "geometry": {"coordinates":[6.1399321556,46.2115135193],"type":"Point"}
}