{
  "type": "Feature",
  "properties": {
    "addr:full":"Soor B\u00fctschwil St. Gallen 9606",
    "addr:housenumber":"9606",
    "iso:country":"CH",
    "sg:address":"Soor",
    "sg:city":"B\u00fctschwil",
    "sg:orig_category":"Architektur U Ingenieurb\u00fcros",
    "sg:phone":"+41 71 982 70 90",
    "sg:postcode":"9606",
    "sg:province":"St. Gallen",
    "wof:name":"Steiger + Partner Ag",
    "wof:placetype":"venue"
},
  "geometry": {"coordinates":[9.076065,47.357254],"type":"Point"}
}