{
  "type": "Feature",
  "properties": {
    "iso:country":"CH",
    "sg:address":"Buckstrasse 2",
    "sg:city":"Oberriet",
    "sg:classifiers":[
        {
            "category":"Health Services",
            "subcategory":"Dentist",
            "type":"Services"
        }
    ],
    "sg:phone":"+41 71 761 06 60",
    "sg:postcode":"9463",
    "sg:province":"St. Gallen",
    "sg:tags":[
        "dental",
        "material",
        "protheses"
    ],
    "wof:name":"Ruedi K\u00fchnis Dental-labor",
    "wof:placetype":"venue"
},
  "geometry": {"coordinates":[9.5621986389,47.3128242493],"type":"Point"}
}