{
  "type": "Feature",
  "properties": {
    "iso:country":"CH",
    "sg:address":"Rainallee 155",
    "sg:city":"Riehen",
    "sg:orig_category":"Malerei",
    "sg:phone":"+41 61 601 86 15",
    "sg:postcode":"4125",
    "sg:province":"Basel-Stadt",
    "wof:name":"Fuchs & Schneider Maleratelier",
    "wof:placetype":"venue"
},
  "geometry": {"coordinates":[7.6403059959,47.5693130493],"type":"Point"}
}