{
  "type": "Feature",
  "properties": {
    "iso:country":"CH",
    "sg:address":"8174",
    "sg:city":"Stadel",
    "sg:orig_category":"Sportvereine Sch\u00fctzen Pistolen-& Gewehr",
    "sg:postcode":"8174",
    "sg:province":"Z\u00fcrich",
    "wof:name":"Pistolenschiessverein",
    "wof:placetype":"venue"
},
  "geometry": {"coordinates":[8.4733800888,47.5290298462],"type":"Point"}
}