{
  "type": "Feature",
  "properties": {
    "iso:country":"CH",
    "sg:address":"Landstrasse 62",
    "sg:city":"Rafz",
    "sg:orig_category":"Herstellung von k\u00e4lte U lufttechnischen Erzeugnissen f\u00fcr gewerbliche Zwecke",
    "sg:postcode":"8197",
    "sg:province":"Z\u00fcrich",
    "wof:name":"Hoppler J., Nachfolgerin Hoppler G.",
    "wof:placetype":"venue"
},
  "geometry": {"coordinates":[7.5089869499,47.2304916382],"type":"Point"}
}