{
  "type": "Feature",
  "properties": {
    "iso:country":"CH",
    "sg:address":"Weissbadstrasse 44",
    "sg:city":"Appenzell",
    "sg:orig_category":"Unclassifiable Establishments",
    "sg:postcode":"9050",
    "sg:province":"Appenzell Innerhoden",
    "wof:name":"Easi-paperhandling Ag",
    "wof:placetype":"venue"
},
  "geometry": {"coordinates":[9.412115097,47.3291473389],"type":"Point"}
}