{
  "type": "Feature",
  "properties": {
    "iso:country":"CH",
    "sg:address":"Abernstrasse 16",
    "sg:city":"Tann",
    "sg:orig_category":"Verlagsgewerbe Werbeberatung",
    "sg:postcode":"8632",
    "sg:province":"Z\u00fcrich",
    "wof:name":"Tomislav Mustac Mustac Melodies",
    "wof:placetype":"venue"
},
  "geometry": {"coordinates":[8.8533172607,47.2670059204],"type":"Point"}
}