{
  "type": "Feature",
  "properties": {
    "iso:country":"CH",
    "sg:address":"Rue De Cond\u00e9mines 43",
    "sg:city":"Sion",
    "sg:orig_category":"Grosshandel mit sonstigen Halbwaren Herstellung von Maschinen f\u00fcr die Nahrungsmittel, Getr\u00e4nkeherste",
    "sg:phone":"+41 62 216 28 58",
    "sg:postcode":"1950",
    "sg:province":"Valais",
    "wof:name":"Turbovac Lanz E.",
    "wof:placetype":"venue"
},
  "geometry": {"coordinates":[7.8567447662,47.343170166],"type":"Point"}
}