{
  "type": "Feature",
  "properties": {
    "iso:country":"CH",
    "sg:address":"Oberneuhofstrasse 8",
    "sg:city":"Baar",
    "sg:orig_category":"Buchf\u00fchrung Wirtschaftspr\u00fcfung, Steuerberatung U Treuhand",
    "sg:phone":"+41 41 766 07 80",
    "sg:postcode":"6340",
    "sg:province":"Zug",
    "wof:name":"Financial Consultancy & Services Treuhandb\u00fcro F\u00e4ssler & Hiebl",
    "wof:placetype":"venue"
},
  "geometry": {"coordinates":[8.516292,47.188278],"type":"Point"}
}