{
  "type": "Feature",
  "properties": {
    "iso:country":"CH",
    "sg:address":"7477",
    "sg:city":"Filisur",
    "sg:classifiers":[
        {
            "category":"Travel",
            "subcategory":"Hotels & Motels",
            "type":"Entertainment"
        }
    ],
    "sg:phone":"+41 81 422 47 47",
    "sg:postcode":"7477",
    "sg:province":"Graubunden",
    "sg:tags":[
        "hotels",
        "mit",
        "restaurant"
    ],
    "wof:name":"Hotel R\u00e4tia",
    "wof:placetype":"venue"
},
  "geometry": {"coordinates":[9.8763208389,46.8817596436],"type":"Point"}
}