{
  "type": "Feature",
  "properties": {
    "iso:country":"CH",
    "sg:address":"Lochstrasse 10",
    "sg:city":"Rorschacherberg",
    "sg:orig_category":"Herstellung von Konstruktionsteilen, Fertigbauteilen U Ausbauelementen aus Holz",
    "sg:phone":"+41 31 738 80 30",
    "sg:postcode":"9404",
    "sg:province":"St. Gallen",
    "wof:name":"W. Hostettler",
    "wof:placetype":"venue"
},
  "geometry": {"coordinates":[7.4019579887,46.7949676514],"type":"Point"}
}