{
  "type": "Feature",
  "properties": {
    "iso:country":"CH",
    "sg:address":"Avenue De Champel 8c 1206 Gen\u00e8ve Case Postale 1211 Gen\u00e8ve",
    "sg:city":"Cs",
    "sg:orig_category":"Grossbanken",
    "sg:phone":"+41 22 391 21 11",
    "sg:postcode":"70",
    "wof:name":"Credit Suisse Succursale Lancy",
    "wof:placetype":"venue"
},
  "geometry": {"coordinates":[6.1132569313,46.1880760193],"type":"Point"}
}