{
  "type": "Feature",
  "properties": {
    "iso:country":"CH",
    "sg:address":"Im Halbiacker 5",
    "sg:city":"R\u00e4terschen",
    "sg:classifiers":[
        {
            "category":"Building & Trades",
            "subcategory":"Construction",
            "type":"Services"
        }
    ],
    "sg:phone":"+41 52 363 18 19",
    "sg:postcode":"8352",
    "sg:province":"Z\u00fcrich",
    "sg:tags":[
        "machine",
        "attachment"
    ],
    "wof:name":"Rizzardo Ag",
    "wof:placetype":"venue"
},
  "geometry": {"coordinates":[8.783738,47.501774],"type":"Point"}
}