{
  "type": "Feature",
  "properties": {
    "iso:country":"CH",
    "sg:address":"Route Du Lac 2 1094 Paudex Case Postale 1215",
    "sg:city":"Lausanne",
    "sg:orig_category":"Pensionskassen",
    "sg:phone":"+41 22 793 60 62",
    "sg:postcode":"1001",
    "sg:province":"Vaud",
    "wof:name":"Fondation Paritaire D'assurance-vie Du Personnel De Naville Sa Et Des Soci\u00e9t\u00e9s Affili\u00e9es",
    "wof:placetype":"venue"
},
  "geometry": {"coordinates":[6.1343998909,46.1831016541],"type":"Point"}
}