{
  "type": "Feature",
  "properties": {
    "iso:country":"CH",
    "sg:address":"Principale Route 4",
    "sg:city":"Vermes",
    "sg:orig_category":"RESTAURANTS: TEA-ROOMS",
    "sg:postcode":"2829",
    "sg:province":"Jura",
    "wof:name":"Canon D'or S\u00e0rl",
    "wof:placetype":"venue"
},
  "geometry": {"coordinates":[7.4719109535,47.3293304443],"type":"Point"}
}