{
  "type": "Feature",
  "properties": {
    "iso:country":"CH",
    "sg:address":"Rte Des Jeunes 9",
    "sg:city":"Gen\u00e8ve",
    "sg:orig_category":"Unternehmensberatung",
    "sg:phone":"+41 22 343 03 03",
    "sg:postcode":"1200",
    "sg:province":"Gen\u00e8ve",
    "wof:name":"R Management",
    "wof:placetype":"venue"
},
  "geometry": {"coordinates":[6.1283950806,46.1881332397],"type":"Point"}
}