{
  "type": "Feature",
  "properties": {
    "iso:country":"CH",
    "sg:address":"Schildstrasse 20 9475 Sevelen. Postfach 162",
    "sg:city":"Sevelen",
    "sg:orig_category":"Erzeugung U Erstbearbeitung von Aluminium Herstellung von Metallerzeugnissen ohne Maschinenbau",
    "sg:phone":"+41 81 750 12 10",
    "sg:postcode":"9475",
    "sg:province":"St. Gallen",
    "wof:name":"Sevex Stichter G. & Co",
    "wof:placetype":"venue"
},
  "geometry": {"coordinates":[9.4894046783,47.1300621033],"type":"Point"}
}