{
  "type": "Feature",
  "properties": {
    "iso:country":"CH",
    "sg:address":"8352",
    "sg:city":"R\u00e4terschen",
    "sg:orig_category":"Bezirks, Sekundar, Realschulen, Oberstufe der Primarschulen",
    "sg:phone":"+41 52 368 71 71",
    "sg:postcode":"8352",
    "sg:province":"Z\u00fcrich",
    "wof:name":"Oberstufenschule",
    "wof:placetype":"venue"
},
  "geometry": {"coordinates":[8.793205,47.49881],"type":"Point"}
}