{
  "type": "Feature",
  "properties": {
    "iso:country":"CH",
    "sg:address":"Mittlerestrasse 42c 3800 Unterseen. Postfach",
    "sg:city":"Unterseen",
    "sg:orig_category":"Buchf\u00fchrung Wirtschaftspr\u00fcfung, Steuerberatung U Treuhand",
    "sg:phone":"+41 33 823 86 42",
    "sg:postcode":"3800",
    "sg:province":"Bern",
    "wof:name":"Ct Treuhand Gmbh, Thiebet Claudia Treuhandb\u00fcro, Bes. Buchf\u00fchrung, Unternehmens- U. Steuerberatung Usw.",
    "wof:placetype":"venue"
},
  "geometry": {"coordinates":[7.839075,46.683277],"type":"Point"}
}