{
  "type": "Feature",
  "properties": {
    "iso:country":"CH",
    "sg:address":"Allenmoosstrasse 118",
    "sg:city":"Z\u00fcrich",
    "sg:orig_category":"P\u00e9dicure",
    "sg:phone":"+41 13117708",
    "sg:postcode":"8057",
    "sg:province":"Z\u00fcrich",
    "wof:name":"Anita Gleichner P\u00e9dicure",
    "wof:placetype":"venue"
},
  "geometry": {"coordinates":[8.5469875336,47.4051475525],"type":"Point"}
}