{
  "type": "Feature",
  "properties": {
    "iso:country":"CH",
    "sg:address":"Avenue Du Ch\u00e2teau 26",
    "sg:city":"Prilly",
    "sg:orig_category":"Grosshandel mit M\u00f6beln, Wohnbedarf, Teppichen U Bodenbel\u00e4gen Herstellung von Besen U B\u00fcrsten",
    "sg:phone":"+41 21 635 85 44",
    "sg:postcode":"1008",
    "sg:province":"Vaud",
    "wof:name":"Rovero & Cie Succr Roggli Brosserie Engros",
    "wof:placetype":"venue"
},
  "geometry": {"coordinates":[6.6045007706,46.5380477905],"type":"Point"}
}