{
  "type": "Feature",
  "properties": {
    "iso:country":"CH",
    "sg:address":"Rigastrasse 15",
    "sg:city":"Chur",
    "sg:orig_category":"Non-Classified Establishments",
    "sg:postcode":"7000",
    "sg:province":"Graubunden",
    "wof:name":"Tagtraum Gmbh",
    "wof:placetype":"venue"
},
  "geometry": {"coordinates":[9.5339641571,46.8557243347],"type":"Point"}
}