{
  "type": "Feature",
  "properties": {
    "iso:country":"CH",
    "sg:address":"3969",
    "sg:city":"Varen",
    "sg:orig_category":"Landw. Genossenschaften Viehzucht",
    "sg:postcode":"3969",
    "wof:name":"Fleckviehzuchtgenossenschaft Varen-inden",
    "wof:placetype":"venue"
},
  "geometry": {"coordinates":[32.143699646,-27.3739700317],"type":"Point"}
}