{
  "type": "Feature",
  "properties": {
    "iso:country":"CH",
    "sg:address":"Via Gerolamo Vegezzi 4",
    "sg:city":"Lugano",
    "sg:orig_category":"Unternehmensberatung",
    "sg:postcode":"6900",
    "sg:province":"Ticino",
    "wof:name":"Schwarz Unternehmer-beratungs Ag",
    "wof:placetype":"venue"
},
  "geometry": {"coordinates":[8.953248024,46.0047225952],"type":"Point"}
}