{
  "type": "Feature",
  "properties": {
    "iso:country":"CH",
    "sg:address":"6130",
    "sg:city":"Willisau",
    "sg:orig_category":"Pensionskassen",
    "sg:postcode":"6130",
    "sg:province":"Luzern",
    "wof:name":"Personalf\u00fcrsorgestiftung Des Grafischen Unternehmens Willisauer Bote",
    "wof:placetype":"venue"
},
  "geometry": {"coordinates":[7.9928841591,47.1222229004],"type":"Point"}
}