{
  "type": "Feature",
  "properties": {
    "iso:country":"CH",
    "sg:address":"Wagistrasse 23",
    "sg:city":"Schlieren",
    "sg:orig_category":"Berufsorganisationen Handelsvermittlung U Grosshandel",
    "sg:phone":"+41 17308321",
    "sg:postcode":"8952",
    "sg:province":"Z\u00fcrich",
    "wof:name":"Ghz Gewerbe-& Handelszentrum Schlieren Ag",
    "wof:placetype":"venue"
},
  "geometry": {"coordinates":[8.458524,47.399467],"type":"Point"}
}