{
  "type": "Feature",
  "properties": {
    "iso:country":"CH",
    "sg:address":"Dorfstrasse 76",
    "sg:city":"Embrach",
    "sg:orig_category":"Detailhandel mit B\u00fcchern, Zeitungen, Schreib U Papeteriewaren Detailhandel mit Schreib U Papeteriewa",
    "sg:phone":"+41 18650045",
    "sg:postcode":"8424",
    "sg:province":"Z\u00fcrich",
    "wof:name":"Studach Margrit, Papeterie Und B\u00fcrobedarf",
    "wof:placetype":"venue"
},
  "geometry": {"coordinates":[8.593757,47.50613],"type":"Point"}
}