{
  "type": "Feature",
  "properties": {
    "iso:country":"CH",
    "sg:address":"Innere G\u00fcterstrasse 4",
    "sg:city":"Zug",
    "sg:orig_category":"Verlagsgewerbe Zeitungsverlag",
    "sg:phone":"+41 71 245 72 72",
    "sg:postcode":"6300",
    "sg:province":"Zug",
    "wof:name":"St. Galler Nachrichten Ag",
    "wof:placetype":"venue"
},
  "geometry": {"coordinates":[9.3881206512,47.4373703003],"type":"Point"}
}