{
  "type": "Feature",
  "properties": {
    "iso:country":"CH",
    "sg:address":"Stadion Gitterli",
    "sg:city":"Liestal",
    "sg:classifiers":[
        {
            "category":"Restaurant",
            "type":"Food & Drink"
        }
    ],
    "sg:phone":"+41 61 921 02 60",
    "sg:postcode":"4410",
    "sg:province":"Basel-Landschaft",
    "wof:name":"Restaurant Arena",
    "wof:placetype":"venue"
},
  "geometry": {"coordinates":[7.7406802177,47.4793739319],"type":"Point"}
}