{
  "type": "Feature",
  "properties": {
    "iso:country":"CH",
    "sg:address":"Beckenriederstrasse 25 6374 Buochs. Postfach 319",
    "sg:city":"Buochs",
    "sg:orig_category":"Betrieb von Taxis",
    "sg:phone":"+41 41 620 60 01",
    "sg:postcode":"6374",
    "sg:province":"Nidwalden",
    "wof:name":"Risicar",
    "wof:placetype":"venue"
},
  "geometry": {"coordinates":[8.424992,46.974396],"type":"Point"}
}