{
  "type": "Feature",
  "properties": {
    "iso:country":"CH",
    "sg:address":"Neumarktstrasse 64 2503 Biel/bienne. Postfach",
    "sg:city":"Biel/bienne",
    "sg:orig_category":"Pensionskassen",
    "sg:phone":"+41 32229916",
    "sg:postcode":"2503",
    "sg:province":"Bern",
    "wof:name":"Pensionskasse Der Vereinigten Drahtwerke Ag, Biel",
    "wof:placetype":"venue"
},
  "geometry": {"coordinates":[7.2515420914,47.1367225647],"type":"Point"}
}