{
  "type": "Feature",
  "properties": {
    "iso:country":"CH",
    "sg:address":"Jungfraustrasse 40",
    "sg:city":"Bern",
    "sg:orig_category":"Innenarchitekturb\u00fcros",
    "sg:phone":"+41 31 352 33 21",
    "sg:postcode":"3005",
    "sg:province":"Bern",
    "wof:name":"Arthur Moeckli Innenarchitektur",
    "wof:placetype":"venue"
},
  "geometry": {"coordinates":[7.4574418068,46.9411735535],"type":"Point"}
}