{
  "type": "Feature",
  "properties": {
    "iso:country":"CH",
    "sg:address":"Zeughausstrasse 48",
    "sg:city":"Mels",
    "sg:classifiers":[
        {
            "category":"Home & Garden",
            "subcategory":"Building Materials",
            "type":"Retail Goods"
        }
    ],
    "sg:phone":"+41 81 723 13 56",
    "sg:postcode":"8887",
    "sg:province":"St. Gallen",
    "sg:tags":[
        "steel",
        "metal",
        "made",
        "door",
        "gate"
    ],
    "wof:name":"Ackermann Metallbau Ag",
    "wof:placetype":"venue"
},
  "geometry": {"coordinates":[9.4072542191,47.0570068359],"type":"Point"}
}