{
  "type": "Feature",
  "properties": {
    "iso:country":"CH",
    "sg:address":"Scheiben\u00e4cherweg 407",
    "sg:city":"Full-reuenthal",
    "sg:orig_category":"Autogaragen Regelm\u00e4ssige Personenbef\u00f6rderung im Fernverkehr",
    "sg:phone":"+41 56 246 10 39",
    "sg:postcode":"5324",
    "sg:province":"Aargau",
    "wof:name":"Karl Erne Rheingarage",
    "wof:placetype":"venue"
},
  "geometry": {"coordinates":[8.213533,47.617142],"type":"Point"}
}