{
  "type": "Feature",
  "properties": {
    "iso:country":"CH",
    "sg:address":"Hennimoosstrasse 56",
    "sg:city":"Diepoldsau",
    "sg:orig_category":"Sicherheitsdienste",
    "sg:phone":"+41 71 733 35 02",
    "sg:postcode":"9444",
    "sg:province":"St. Gallen",
    "wof:name":"Security Profi Gmbh",
    "wof:placetype":"venue"
},
  "geometry": {"coordinates":[9.6484956741,47.3872108459],"type":"Point"}
}