{
  "type": "Feature",
  "properties": {
    "iso:country":"CH",
    "sg:address":"Emetstrasse 377",
    "sg:city":"Matzendorf",
    "sg:orig_category":"Unclassifiable Establishments",
    "sg:postcode":"4713",
    "sg:province":"Solothurn",
    "wof:name":"Gerber Reisen Car- & Oldtimerfahrten",
    "wof:placetype":"venue"
},
  "geometry": {"coordinates":[7.6274318695,47.3088226318],"type":"Point"}
}