{
  "type": "Feature",
  "properties": {
    "iso:country":"CH",
    "sg:address":"Poststrasse 16",
    "sg:city":"St.gallen",
    "sg:orig_category":"Fachdetailhandel mit pharmazeutischen Produkten",
    "sg:phone":"+41 71 228 07 60",
    "sg:postcode":"9000",
    "sg:province":"St. Gallen",
    "wof:name":"Bahnhof Apotheke, Thaler",
    "wof:placetype":"venue"
},
  "geometry": {"coordinates":[9.3724393845,47.424659729],"type":"Point"}
}