{
  "type": "Feature",
  "properties": {
    "iso:country":"CH",
    "sg:address":"Hauptstr. 591 B. Dieter Wild.",
    "sg:city":"Unterkulm",
    "sg:orig_category":"Vermietung U Verpachtung von eigenen Immobilien",
    "sg:postcode":"5726",
    "sg:province":"Aargau",
    "wof:name":"Kulma Ag",
    "wof:placetype":"venue"
},
  "geometry": {"coordinates":[8.1150026321,47.3104400635],"type":"Point"}
}