{
  "type": "Feature",
  "properties": {
    "iso:country":"CH",
    "sg:address":"Rue De Soleure 25 2740 Montagne-moutier Case Postale",
    "sg:city":"Payerne",
    "sg:orig_category":"Detailhandel mit M\u00f6beln U Haushaltsgegenst\u00e4nden Grosshandel mit B\u00fcrom\u00f6beln",
    "sg:phone":"+41 26 662 11 40",
    "sg:postcode":"1530",
    "sg:province":"Vaud",
    "wof:name":"Axial Diffusion S\u00e0rl Mobilier De Bureau, Collectivit\u00e9 Et Accessoires; Commerce Et Commercialisation",
    "wof:placetype":"venue"
},
  "geometry": {"coordinates":[7.3864498138,47.2810592651],"type":"Point"}
}