{
  "type": "Feature",
  "properties": {
    "iso:country":"CH",
    "sg:address":"Austrasse 3",
    "sg:city":"Weissbad",
    "sg:orig_category":"Berufsbildende weiterf\u00fchrende Schulen",
    "sg:phone":"+41 71 912 24 30",
    "sg:postcode":"9057",
    "sg:province":"Appenzell Innerhoden",
    "wof:name":"E & R Consult Ag",
    "wof:placetype":"venue"
},
  "geometry": {"coordinates":[9.43707,47.304726],"type":"Point"}
}