{
  "type": "Feature",
  "properties": {
    "iso:country":"CH",
    "sg:address":"Hauptstrasse 3",
    "sg:city":"Worb",
    "sg:orig_category":"Reiseb\u00fcros",
    "sg:phone":"+41 31 839 90 00",
    "sg:postcode":"3076",
    "sg:province":"Bern",
    "wof:name":"Round The World Travel",
    "wof:placetype":"venue"
},
  "geometry": {"coordinates":[7.5632457733,46.9294433594],"type":"Point"}
}