{
  "type": "Feature",
  "properties": {
    "iso:country":"CH",
    "sg:address":"Rue Saint-henri 11",
    "sg:city":"Del\u00e9mont",
    "sg:orig_category":"Interessenvertretungen",
    "sg:postcode":"2800",
    "sg:province":"Jura",
    "wof:name":"Ffi Fondation Pour La Formation Industrielle",
    "wof:placetype":"venue"
},
  "geometry": {"coordinates":[7.3396902084,47.3520317078],"type":"Point"}
}