{
  "type": "Feature",
  "properties": {
    "iso:country":"CH",
    "sg:address":"Au Village 224",
    "sg:city":"Autigny",
    "sg:orig_category":"Primarschulen",
    "sg:phone":"+41 26 477 16 40",
    "sg:postcode":"1742",
    "sg:province":"Fribourg",
    "wof:name":"Ecole Primaire",
    "wof:placetype":"venue"
},
  "geometry": {"coordinates":[7.0198140144,46.7368545532],"type":"Point"}
}