{
  "type": "Feature",
  "properties": {
    "iso:country":"CH",
    "sg:address":"Seestrasse 147",
    "sg:city":"Horgen",
    "sg:orig_category":"Non-Classified Establishments",
    "sg:postcode":"8810",
    "sg:province":"Z\u00fcrich",
    "wof:name":"Dr.med.urs Walter Spezialarzt Fmh",
    "wof:placetype":"venue"
},
  "geometry": {"coordinates":[8.5974063873,47.2608375549],"type":"Point"}
}