{
  "type": "Feature",
  "properties": {
    "iso:country":"CH",
    "sg:address":"3132",
    "sg:city":"Riggisberg",
    "sg:orig_category":"Vereine Gesang",
    "sg:postcode":"3132",
    "sg:province":"Bern",
    "wof:name":"M\u00e4nnerchor Riggisberg",
    "wof:placetype":"venue"
},
  "geometry": {"coordinates":[7.4764299393,46.8093109131],"type":"Point"}
}