{
  "type": "Feature",
  "properties": {
    "iso:country":"CH",
    "sg:address":"Bahnhofplatz 4",
    "sg:city":"Hinwil",
    "sg:orig_category":"RESTAURANTS: TEA-ROOMS",
    "sg:phone":"+41 19373108",
    "sg:postcode":"8340",
    "sg:province":"Z\u00fcrich",
    "wof:name":"Restaurant Bahnhof, Hinwil, H. Keller",
    "wof:placetype":"venue"
},
  "geometry": {"coordinates":[8.8400287628,47.3002853394],"type":"Point"}
}