{
  "type": "Feature",
  "properties": {
    "iso:country":"CH",
    "sg:address":"Bellinzona Nord",
    "sg:city":"Bellinzona",
    "sg:classifiers":[
        {
            "category":"Restaurant",
            "type":"Food & Drink"
        }
    ],
    "sg:phone":"+41 91 826 31 01",
    "sg:postcode":"6500",
    "sg:province":"Ticino",
    "wof:name":"Ristoro M\u00f6venpick Autostradale N2",
    "wof:placetype":"venue"
},
  "geometry": {"coordinates":[9.0370845795,46.2150764465],"type":"Point"}
}