{
  "type": "Feature",
  "properties": {
    "iso:country":"CH",
    "sg:address":"Beau-s\u00e9jour Rue 10",
    "sg:city":"Lausanne",
    "sg:orig_category":"Interessenvertretungen",
    "sg:postcode":"1003",
    "sg:province":"Vaud",
    "wof:name":"Fondation Biart Edgard Et Marthe",
    "wof:placetype":"venue"
},
  "geometry": {"coordinates":[6.6357932091,46.5176506042],"type":"Point"}
}