{
  "type": "Feature",
  "properties": {
    "iso:country":"CH",
    "sg:address":"C\u00f4te-\u00e0-tenot 1",
    "sg:city":"Echallens",
    "sg:orig_category":"Vermietung U Verpachtung von eigenen Immobilien",
    "sg:postcode":"1040",
    "sg:province":"Vaud",
    "wof:name":"Immobill Sa",
    "wof:placetype":"venue"
},
  "geometry": {"coordinates":[6.6308169365,46.6430740356],"type":"Point"}
}