{
  "type": "Feature",
  "properties": {
    "iso:country":"CH",
    "sg:address":"Zugerstrasse 6",
    "sg:city":"Cham",
    "sg:orig_category":"Druck ohne Zeitungsdruck",
    "sg:postcode":"6330",
    "sg:province":"Zug",
    "wof:name":"Copyprint Colmelet",
    "wof:placetype":"venue"
},
  "geometry": {"coordinates":[8.4603967667,47.1813468933],"type":"Point"}
}