{
  "type": "Feature",
  "properties": {
    "iso:country":"CH",
    "sg:address":"Hans Br\u00fchlmannstrasse 7a",
    "sg:city":"Amriswil",
    "sg:orig_category":"Wirtschaftsverb\u00e4nde Gewerbeverb\u00e4nde/-vereine",
    "sg:phone":"+41 71 411 10 61",
    "sg:postcode":"8580",
    "sg:province":"Thurgau",
    "wof:name":"Gewerbeverein Amriswil",
    "wof:placetype":"venue"
},
  "geometry": {"coordinates":[9.2886371613,47.5433731079],"type":"Point"}
}