{
  "type": "Feature",
  "properties": {
    "iso:country":"CH",
    "sg:address":"Hauptstrasse 52",
    "sg:city":"Sissach",
    "sg:orig_category":"RESTAURANTS: TEA-ROOMS",
    "sg:postcode":"4450",
    "sg:province":"Basel-Landschaft",
    "wof:name":"Sara Gastro Gmbh",
    "wof:placetype":"venue"
},
  "geometry": {"coordinates":[7.8130941391,47.4635925293],"type":"Point"}
}