{
  "type": "Feature",
  "properties": {
    "iso:country":"CH",
    "sg:address":"Riedstrasse 4",
    "sg:city":"Dietikon",
    "sg:classifiers":[
        {
            "category":"Shopping",
            "subcategory":"Stationery & Office Supplies",
            "type":"Retail Goods"
        }
    ],
    "sg:phone":"+41 17444111",
    "sg:postcode":"8953",
    "sg:province":"Z\u00fcrich",
    "sg:tags":[
        "furniture"
    ],
    "wof:name":"B\u00fcro-f\u00fcrrer Ag",
    "wof:placetype":"venue"
},
  "geometry": {"coordinates":[8.3935346603,47.419254303],"type":"Point"}
}