{
  "type": "Feature",
  "properties": {
    "iso:country":"CH",
    "sg:address":"Denkmalstrasse 13",
    "sg:city":"Luzern",
    "sg:orig_category":"Gesundheitswesen",
    "sg:phone":"+41 91 871 29 70",
    "sg:postcode":"6006",
    "sg:province":"Luzern",
    "wof:name":"Pre-h Sagl",
    "wof:placetype":"venue"
},
  "geometry": {"coordinates":[8.9337301254,46.4823417664],"type":"Point"}
}