{
  "type": "Feature",
  "properties": {
    "iso:country":"CH",
    "sg:address":"Seestrasse 289",
    "sg:city":"Z\u00fcrich",
    "sg:orig_category":"Interessenvertretungen",
    "sg:phone":"+41 12714070",
    "sg:postcode":"8038",
    "sg:province":"Z\u00fcrich",
    "wof:name":"Saint Germain Foundation",
    "wof:placetype":"venue"
},
  "geometry": {"coordinates":[8.5324802399,47.3498306274],"type":"Point"}
}