{
  "type": "Feature",
  "properties": {
    "iso:country":"CH",
    "sg:address":"Bruggliweg 6",
    "sg:city":"Netstal",
    "sg:orig_category":"Advokaturb\u00fcros",
    "sg:phone":"+41 55 640 15 20",
    "sg:postcode":"8754",
    "sg:province":"Glarus",
    "wof:name":"Willi Berchten Advokaturb\u00fcro",
    "wof:placetype":"venue"
},
  "geometry": {"coordinates":[9.056478,47.060581],"type":"Point"}
}