{
  "type": "Feature",
  "properties": {
    "iso:country":"CH",
    "sg:address":"Tafelstattweg 3",
    "sg:city":"Arth",
    "sg:orig_category":"Unternehmensberatung",
    "sg:phone":"+41 41 758 20 83",
    "sg:postcode":"6415",
    "sg:province":"Schwyz",
    "wof:name":"Medeme Comp. Gmbh",
    "wof:placetype":"venue"
},
  "geometry": {"coordinates":[8.5280199051,47.0702705383],"type":"Point"}
}