{
  "type": "Feature",
  "properties": {
    "iso:country":"CH",
    "sg:address":"Avenue De France 67",
    "sg:city":"Sion",
    "sg:orig_category":"Druck ohne Zeitungsdruck",
    "sg:phone":"+41 27 322 46 44",
    "sg:postcode":"1950",
    "sg:province":"Valais",
    "wof:name":"Zufferey Offset Sion.",
    "wof:placetype":"venue"
},
  "geometry": {"coordinates":[7.3476538658,46.228427887],"type":"Point"}
}