{
  "type": "Feature",
  "properties": {
    "iso:country":"CH",
    "sg:address":"Wilenhalde 2",
    "sg:city":"Herisau",
    "sg:orig_category":"Elektroinstallation",
    "sg:phone":"+41 62 291 11 22",
    "sg:postcode":"9100",
    "sg:province":"Appenzell Ausserrhoden",
    "wof:name":"Meier Elektro Ag",
    "wof:placetype":"venue"
},
  "geometry": {"coordinates":[7.9847640991,47.3565368652],"type":"Point"}
}