{
  "type": "Feature",
  "properties": {
    "iso:country":"CH",
    "sg:address":"Rue Du Maupas 8bis",
    "sg:city":"Lausanne",
    "sg:orig_category":"Siebdruck",
    "sg:phone":"+41 21 648 38 15",
    "sg:postcode":"1004",
    "sg:province":"Vaud",
    "wof:name":"Georg Gara S\u00e9rigraphie",
    "wof:placetype":"venue"
},
  "geometry": {"coordinates":[6.6270031929,46.5241851807],"type":"Point"}
}