{
  "type": "Feature",
  "properties": {
    "iso:country":"CH",
    "sg:address":"Route De Provence",
    "sg:city":"Concise",
    "sg:orig_category":"Herstellung von Ger\u00e4ten der Elektrizit\u00e4tserzeugung, -verteilung u.\u00e4. -Herstellung von elektronischen",
    "sg:phone":"+41 24 434 10 41",
    "sg:postcode":"1426",
    "sg:province":"Vaud",
    "wof:name":"Invertag Sa Electronics-t\u00e9l\u00e9communication",
    "wof:placetype":"venue"
},
  "geometry": {"coordinates":[6.7187781334,46.8558578491],"type":"Point"}
}