{
  "type": "Feature",
  "properties": {
    "iso:country":"CH",
    "sg:address":"Industriezone Leukerfeld",
    "sg:city":"Leukerbad",
    "sg:orig_category":"Non-Classified Establishments",
    "sg:postcode":"3954",
    "sg:province":"Valais",
    "wof:name":"Bauunternehmung L\u00f6tscher Susten Ag",
    "wof:placetype":"venue"
},
  "geometry": {"coordinates":[7.6253261566,46.3759307861],"type":"Point"}
}