{
  "type": "Feature",
  "properties": {
    "iso:country":"CH",
    "sg:address":"1415",
    "sg:city":"Molondin",
    "sg:orig_category":"Darlehenskassen U Raiffeisenbanken",
    "sg:phone":"+41 24 433 13 12",
    "sg:postcode":"1415",
    "sg:province":"Vaud",
    "wof:name":"Banque Raiffeisen",
    "wof:placetype":"venue"
},
  "geometry": {"coordinates":[6.748875,46.760181],"type":"Point"}
}