{
  "type": "Feature",
  "properties": {
    "iso:country":"CH",
    "sg:address":"Br\u00fcnigstrasse 18",
    "sg:city":"Luzern",
    "sg:orig_category":"Unternehmensberatung",
    "sg:phone":"+41 41 360 79 79",
    "sg:postcode":"6005",
    "sg:province":"Luzern",
    "wof:name":"Amrhein Joe Unternehmensberatung Personal Fach- U. F\u00fchrungskr\u00e4fte; Selektion. Unternehmensberatung In Personalfragen",
    "wof:placetype":"venue"
},
  "geometry": {"coordinates":[8.3111276627,47.0429000854],"type":"Point"}
}