{
  "type": "Feature",
  "properties": {
    "iso:country":"CH",
    "sg:address":"Schachenstr. 12",
    "sg:city":"Auenstein",
    "sg:orig_category":"Schreib U \u00dcbersetzungsb\u00fcros",
    "sg:postcode":"5105",
    "sg:province":"Aargau",
    "wof:name":"Valerie Stauffer B\u00fcro F\u00fcr Uebersetzungen",
    "wof:placetype":"venue"
},
  "geometry": {"coordinates":[8.1292390823,47.4143981934],"type":"Point"}
}