{
  "type": "Feature",
  "properties": {
    "iso:country":"CH",
    "sg:address":"Gotthardstrasse 63",
    "sg:city":"Ibach",
    "sg:orig_category":"Detailhandel mit Brot, Back U S\u00fcsswaren",
    "sg:phone":"+41 41 811 14 65",
    "sg:postcode":"6438",
    "sg:province":"Schwyz",
    "wof:name":"Schwegler & Sohn, B\u00e4ckerei",
    "wof:placetype":"venue"
},
  "geometry": {"coordinates":[8.643361,47.010918],"type":"Point"}
}