{
  "type": "Feature",
  "properties": {
    "iso:country":"CH",
    "sg:address":"B\u00fcrgenstock Obb\u00fcrgen",
    "sg:city":"B\u00fcrgenstock",
    "sg:orig_category":"Personenbef\u00f6rderung im Linienverkehr zu Land",
    "sg:postcode":"6363",
    "sg:province":"Nidwalden",
    "wof:name":"Cable Stop Sa",
    "wof:placetype":"venue"
},
  "geometry": {"coordinates":[6.9885149002,47.1489372253],"type":"Point"}
}