{
  "type": "Feature",
  "properties": {
    "iso:country":"CH",
    "sg:address":"Rue Des Remparts 19",
    "sg:city":"Sion",
    "sg:classifiers":[
        {
            "category":"Personal",
            "subcategory":"Piercing",
            "type":"Services"
        }
    ],
    "sg:phone":"+41 79 220 39 29",
    "sg:postcode":"1950",
    "sg:province":"Valais",
    "sg:tags":[
        "tattoo"
    ],
    "wof:name":"Tattoo Studio By Chris",
    "wof:placetype":"venue"
},
  "geometry": {"coordinates":[7.3596830368,46.2318458557],"type":"Point"}
}