{
  "type": "Feature",
  "properties": {
    "iso:country":"CH",
    "sg:address":"Waffenplatzstrasse 15",
    "sg:city":"Solothurn",
    "sg:orig_category":"Datenverarbeitungsdienste Softwareentwicklung U beratung",
    "sg:postcode":"4500",
    "sg:province":"Solothurn",
    "wof:name":"Orca Informatik Ag Edv-dienstleistung",
    "wof:placetype":"venue"
},
  "geometry": {"coordinates":[7.589291,47.493027],"type":"Point"}
}