{
  "type": "Feature",
  "properties": {
    "iso:country":"CH",
    "sg:address":"Rebbergstrasse 92",
    "sg:city":"Thayngen",
    "sg:orig_category":"Sanit\u00e4r, Heizungs U L\u00fcftungsinstallation",
    "sg:phone":"+41 52 649 43 64",
    "sg:postcode":"8240",
    "sg:province":"Schaffhausen",
    "wof:name":"Waldvogel Heizung",
    "wof:placetype":"venue"
},
  "geometry": {"coordinates":[8.7233934402,47.7482872009],"type":"Point"}
}