{
  "type": "Feature",
  "properties": {
    "iso:country":"CH",
    "sg:address":"Birren 10 5703 Seon. Postfach 106",
    "sg:city":"Niederlenz",
    "sg:orig_category":"Handelsvermittlung U Grosshandel",
    "sg:phone":"+41 62 769 60 49",
    "sg:postcode":"5702",
    "sg:province":"Aargau",
    "wof:name":"Atw Import Techn.produkte",
    "wof:placetype":"venue"
},
  "geometry": {"coordinates":[8.1648778915,47.361995697],"type":"Point"}
}