{
  "type": "Feature",
  "properties": {
    "iso:country":"CH",
    "sg:address":"Postplatz 3 6430 Schwyz. Postfach 763",
    "sg:city":"Schwyz",
    "sg:orig_category":"Versicherungen Generalagenturen",
    "sg:phone":"+41 800 808 080",
    "sg:postcode":"6431",
    "sg:province":"Schwyz",
    "wof:name":"Z\u00fcrich Versicherungen Generalagentur",
    "wof:placetype":"venue"
},
  "geometry": {"coordinates":[8.6529417038,47.020401001],"type":"Point"}
}