{
  "type": "Feature",
  "properties": {
    "iso:country":"CH",
    "sg:address":"Z. I. En Vanel 1880 Bex Case Postale 276",
    "sg:city":"Bex",
    "sg:orig_category":"Herstellung von Metallkonstruktionen Stahl U Leichtmetallbau",
    "sg:phone":"+41 81 783 35 53",
    "sg:postcode":"1880",
    "sg:province":"Vaud",
    "wof:name":"Meko-tech Produktions Gmbh",
    "wof:placetype":"venue"
},
  "geometry": {"coordinates":[9.4857654572,47.1649169922],"type":"Point"}
}