{
  "type": "Feature",
  "properties": {
    "iso:country":"CH",
    "sg:address":"Kasernenstrasse 58a",
    "sg:city":"Herisau",
    "sg:orig_category":"Vereine Wissenschaftliche",
    "sg:postcode":"9100",
    "sg:province":"Appenzell Ausserrhoden",
    "wof:name":"Anthrop.-forschungs-verein",
    "wof:placetype":"venue"
},
  "geometry": {"coordinates":[9.2874927521,47.3884010315],"type":"Point"}
}