{
  "type": "Feature",
  "properties": {
    "iso:country":"CH",
    "sg:address":"Herrengrabenweg 11",
    "sg:city":"Basel",
    "sg:orig_category":"K\u00fcnstlerische U schriftstellerische T\u00e4tigkeiten U Darbietungen",
    "sg:phone":"+41 61 301 46 60",
    "sg:postcode":"4054",
    "sg:province":"Basel-Stadt",
    "wof:name":"Zingg Gebr\u00fcder",
    "wof:placetype":"venue"
},
  "geometry": {"coordinates":[7.5725297928,47.555683136],"type":"Point"}
}