{
  "type": "Feature",
  "properties": {
    "iso:country":"CH",
    "sg:address":"B\u00fchlstrasse 72",
    "sg:city":"Sulgen",
    "sg:orig_category":"R\u00fcckgewinnung U Vorbereitung f\u00fcr die Wiederverwertung Recycling von nichtmetallischen Altmaterialien",
    "sg:phone":"+41 71 642 48 90",
    "sg:postcode":"8583",
    "sg:province":"Thurgau",
    "wof:name":"Replast Recycling Gmbh",
    "wof:placetype":"venue"
},
  "geometry": {"coordinates":[9.1733169556,47.541934967],"type":"Point"}
}