{
  "type": "Feature",
  "properties": {
    "iso:country":"CH",
    "sg:address":"Z\u00fcrcherstrasse 104",
    "sg:city":"Altendorf",
    "sg:orig_category":"Detailhandel mit M\u00f6beln Detailhandel mit Textilien",
    "sg:phone":"+41 55 442 44 70",
    "sg:postcode":"8852",
    "sg:province":"Schwyz",
    "wof:name":"Top Tip Rudolf M\u00fcller Ag M\u00f6bel Teppiche",
    "wof:placetype":"venue"
},
  "geometry": {"coordinates":[8.8116512299,47.1985473633],"type":"Point"}
}