{
  "type": "Feature",
  "properties": {
    "iso:country":"CH",
    "sg:address":"Schaffhauserstrasse 115 8302 Kloten. Postfach 675",
    "sg:city":"Kloten",
    "sg:orig_category":"Autoreiseunternehmen Pneus Detailhandel",
    "sg:phone":"+41 24 499 16 25",
    "sg:postcode":"8302",
    "sg:province":"Z\u00fcrich",
    "wof:name":"Jean-marc Stooss Pneumatiques & Excursions",
    "wof:placetype":"venue"
},
  "geometry": {"coordinates":[-120.31500200000001,34.885986],"type":"Point"}
}