{
  "type": "Feature",
  "properties": {
    "addr:full":"Rotachstrasse 5 Z\u00fcrich Z\u00fcrich 8003",
    "addr:housenumber":"5",
    "addr:postcode":"8003",
    "addr:street":"Rotachstrasse",
    "iso:country":"CH",
    "sg:address":"Rotachstrasse 5",
    "sg:city":"Z\u00fcrich",
    "sg:orig_category":"Autogaragen",
    "sg:phone":"+41 14627953",
    "sg:postcode":"8003",
    "sg:province":"Z\u00fcrich",
    "wof:name":"Luciano Doria Auto-reparaturen",
    "wof:placetype":"venue"
},
  "geometry": {"coordinates":[8.516788,47.369404],"type":"Point"}
}