{
  "type": "Feature",
  "properties": {
    "iso:country":"CH",
    "sg:address":"Route De Sion 20",
    "sg:city":"Sierre",
    "sg:orig_category":"Instandhaltung U Reparatur von Automobilen",
    "sg:phone":"+41 22 798 71 32",
    "sg:postcode":"3960",
    "sg:province":"Valais",
    "wof:name":"Garage Du Nouveau Salon Sa",
    "wof:placetype":"venue"
},
  "geometry": {"coordinates":[6.1237878799,46.2359313965],"type":"Point"}
}