{
  "type": "Feature",
  "properties": {
    "iso:country":"CH",
    "sg:address":"Schweizerhofstrasse 14",
    "sg:city":"Glarus",
    "sg:orig_category":"Erbringung von Dienstleistungen f\u00fcr Unternehmen Herstellung von sonstigen elektrischen Ausr\u00fcstungen",
    "sg:phone":"+41 55 640 67 37",
    "sg:postcode":"8750",
    "sg:province":"Glarus",
    "wof:name":"Ronner Management Ag",
    "wof:placetype":"venue"
},
  "geometry": {"coordinates":[9.0702962875,47.040813446],"type":"Point"}
}