{
  "type": "Feature",
  "properties": {
    "iso:country":"CH",
    "sg:address":"Bvd Georges-favon 15 1200 Genf. Postfach",
    "sg:city":"Gen\u00e8ve",
    "sg:orig_category":"Fachdetailhandel in Verkaufsr\u00e4umen",
    "sg:postcode":"1204",
    "sg:province":"Gen\u00e8ve",
    "wof:name":"Gadgetissimo, Josiane Gaugaz",
    "wof:placetype":"venue"
},
  "geometry": {"coordinates":[6.1404027939,46.2021369934],"type":"Point"}
}