{
  "type": "Feature",
  "properties": {
    "iso:country":"CH",
    "sg:address":"Balmerstrasse 36",
    "sg:city":"Bern",
    "sg:orig_category":"Herstellung von Radio U Fernsehger\u00e4ten sowie phono U videotechnischen Ger\u00e4ten",
    "sg:phone":"+41 31 311 57 60",
    "sg:postcode":"3006",
    "sg:province":"Bern",
    "wof:name":"Mpz Audio Beschallungstechnik Zach Michael",
    "wof:placetype":"venue"
},
  "geometry": {"coordinates":[7.4780240059,46.9473381042],"type":"Point"}
}