{
  "type": "Feature",
  "properties": {
    "iso:country":"CH",
    "sg:address":"Insstrasse 15",
    "sg:city":"Erlach",
    "sg:orig_category":"Unternehmensberatung",
    "sg:phone":"+41 79 277 29 11",
    "sg:postcode":"3235",
    "sg:province":"Bern",
    "wof:name":"Mst Methode Gmbh",
    "wof:placetype":"venue"
},
  "geometry": {"coordinates":[7.0968279839,47.0398254395],"type":"Point"}
}