{
  "type": "Feature",
  "properties": {
    "iso:country":"CH",
    "sg:address":"Gewerbehaus Haslen",
    "sg:city":"Sch\u00fcbelbach",
    "sg:orig_category":"Vermietung von Automobilen",
    "sg:phone":"+41 55 440 77 47",
    "sg:postcode":"8862",
    "sg:province":"Schwyz",
    "wof:name":"Traversa-racing",
    "wof:placetype":"venue"
},
  "geometry": {"coordinates":[8.9290122986,47.1734046936],"type":"Point"}
}