{
  "type": "Feature",
  "properties": {
    "iso:country":"CH",
    "sg:address":"Via Codeborgo 20",
    "sg:city":"Bellinzona",
    "sg:orig_category":"Fachdetailhandel mit pharmazeutischen Produkten",
    "sg:phone":"+41 91 825 60 45",
    "sg:postcode":"6500",
    "sg:province":"Ticino",
    "wof:name":"Farmacia Rondi",
    "wof:placetype":"venue"
},
  "geometry": {"coordinates":[9.0240621567,46.1927185059],"type":"Point"}
}