{
  "type": "Feature",
  "properties": {
    "iso:country":"CH",
    "sg:address":"Heinrich Guyerstrasse 20",
    "sg:city":"Bauma",
    "sg:orig_category":"Gesundheitswesen",
    "sg:phone":"+41 52 386 35 35",
    "sg:postcode":"8494",
    "sg:province":"Z\u00fcrich",
    "wof:name":"Massagepraxis Und Kosmetische Fusspflege, Mattenberger-widmer M.",
    "wof:placetype":"venue"
},
  "geometry": {"coordinates":[8.8787517548,47.3682174683],"type":"Point"}
}