{
  "type": "Feature",
  "properties": {
    "iso:country":"CH",
    "sg:address":"Baarerstr. 23 Pf 302",
    "sg:city":"Zug",
    "sg:classifiers":[
        {
            "category":"Home & Garden",
            "subcategory":"Building Materials",
            "type":"Retail Goods"
        }
    ],
    "sg:phone":"+41 41 711 86 21",
    "sg:postcode":"6300",
    "sg:province":"Zug",
    "sg:tags":[
        "fabric",
        "textile",
        "linen",
        "wood",
        "clothing",
        "furniture"
    ],
    "wof:name":"Hans Hassler Ag",
    "wof:placetype":"venue"
},
  "geometry": {"coordinates":[8.5162153244,47.1715087891],"type":"Point"}
}