{
  "type": "Feature",
  "properties": {
    "iso:country":"CH",
    "sg:address":"1673",
    "sg:city":"Promasens",
    "sg:orig_category":"Bauspenglerei Dachdeckerei",
    "sg:phone":"+41 21 909 53 08",
    "sg:postcode":"1673",
    "sg:province":"Fribourg",
    "wof:name":"G. Ottet & F. Cochard Toiture & Ferblanterie",
    "wof:placetype":"venue"
},
  "geometry": {"coordinates":[6.82225,46.59988],"type":"Point"}
}