{
  "type": "Feature",
  "properties": {
    "iso:country":"CH",
    "sg:address":"Hungerbergstrasse 12a",
    "sg:city":"Z\u00fcrich",
    "sg:orig_category":"Sportvereine Ski",
    "sg:phone":"+41 13713570",
    "sg:postcode":"8046",
    "sg:province":"Z\u00fcrich",
    "wof:name":"Ski-& Bergclub Z\u00fcrich R\u00e4tia",
    "wof:placetype":"venue"
},
  "geometry": {"coordinates":[8.5004291534,47.4200630188],"type":"Point"}
}