{
  "type": "Feature",
  "properties": {
    "iso:country":"CH",
    "sg:address":"Bahnhofstrasse 3 9443 Widnau. Postfach",
    "sg:city":"Widnau",
    "sg:orig_category":"Handels-H\u00e4user U Gesellschaften",
    "sg:postcode":"9443",
    "sg:province":"St. Gallen",
    "wof:name":"Neuhard Agentur Gmbh Techn. Produkte, Waren; Handel",
    "wof:placetype":"venue"
},
  "geometry": {"coordinates":[9.6293144226,47.4079322815],"type":"Point"}
}