{
  "type": "Feature",
  "properties": {
    "iso:country":"CH",
    "sg:address":"M\u00fchledorfstrasse 61",
    "sg:city":"Niederg\u00f6sgen",
    "sg:orig_category":"Fahrschulen, Flugschulen",
    "sg:phone":"+41 62 849 55 66",
    "sg:postcode":"5013",
    "sg:province":"Solothurn",
    "wof:name":"Gerhard Gr\u00fctter Autofahrschule",
    "wof:placetype":"venue"
},
  "geometry": {"coordinates":[7.9692640305,47.3685340881],"type":"Point"}
}