{
  "type": "Feature",
  "properties": {
    "iso:country":"CH",
    "sg:address":"Hauptstrasse 39 4133 Pratteln. Postfach 1022",
    "sg:city":"Pratteln",
    "sg:orig_category":"Bauspenglerei Sanit\u00e4r, Heizungs U L\u00fcftungsinstallation",
    "sg:phone":"+41 61 821 81 31",
    "sg:postcode":"4133",
    "sg:province":"Basel-Landschaft",
    "wof:name":"U. Amsler Ag",
    "wof:placetype":"venue"
},
  "geometry": {"coordinates":[7.696413,47.516903],"type":"Point"}
}