{
  "type": "Feature",
  "properties": {
    "iso:country":"CH",
    "sg:address":"Austrasse 110",
    "sg:city":"Basel",
    "sg:orig_category":"Architektur U Ingenieurb\u00fcros Architekturb\u00fcros",
    "sg:phone":"+41 61 271 47 09",
    "sg:postcode":"4051",
    "sg:province":"Basel-Stadt",
    "wof:name":"Kroepfli Charles Dipl. Architekt Htl/sia Gmbh",
    "wof:placetype":"venue"
},
  "geometry": {"coordinates":[7.577491,47.555397],"type":"Point"}
}