{
  "type": "Feature",
  "properties": {
    "iso:country":"CH",
    "sg:address":"Gotthardstrasse 20 6300 Zug. Postfach 4261",
    "sg:city":"Zug",
    "sg:orig_category":"Effektenvermittlung Broker Versicherungsagenturen and -broker",
    "sg:postcode":"6304",
    "sg:province":"Zug",
    "wof:name":"Fag Finanzinstitut Ag Finanz-&versicherungsgesch\u00e4fte",
    "wof:placetype":"venue"
},
  "geometry": {"coordinates":[8.5139894485,47.1727676392],"type":"Point"}
}