{
  "type": "Feature",
  "properties": {
    "addr:full":"Rue De L'aub\u00e9pine 1 Gen\u00e8ve Gen\u00e8ve 1205",
    "addr:housenumber":"1",
    "addr:postcode":"1205",
    "addr:street":"Rue De L'Aube \u0301Pine",
    "iso:country":"CH",
    "sg:address":"Rue De L'aub\u00e9pine 1",
    "sg:city":"Gen\u00e8ve",
    "sg:orig_category":"Architekturb\u00fcros",
    "sg:phone":"+41 22 329 80 77",
    "sg:postcode":"1205",
    "sg:province":"Gen\u00e8ve",
    "wof:name":"Andr\u00e9 Billaud & Max Hirschi Bureau D'architecture",
    "wof:placetype":"venue"
},
  "geometry": {"coordinates":[6.145667,46.188503],"type":"Point"}
}