{
  "type": "Feature",
  "properties": {
    "addr:full":"Br\u00fcggstrasse 68 Biel/bienne Bern 2503",
    "addr:housenumber":"68",
    "addr:postcode":"2503",
    "addr:street":"Brueggstrasse",
    "iso:country":"CH",
    "sg:address":"Br\u00fcggstrasse 68",
    "sg:city":"Biel/bienne",
    "sg:orig_category":"Detailhandel mit Boden U Wandbel\u00e4gen ohne Teppiche Verlegen von Fussboden",
    "sg:phone":"+41 31 331 06 50",
    "sg:postcode":"2503",
    "sg:province":"Bern",
    "wof:name":"Rimann & Walpen Ag Wand, Bodenbel\u00e4geusw; Handel, Verarbeitung",
    "wof:placetype":"venue"
},
  "geometry": {"coordinates":[7.454859,46.959625],"type":"Point"}
}