{
  "type": "Feature",
  "properties": {
    "iso:country":"CH",
    "sg:address":"M\u00fchlegasse 18",
    "sg:city":"Baar",
    "sg:orig_category":"Unternehmensberatung",
    "sg:postcode":"6340",
    "sg:province":"Zug",
    "wof:name":"Printsign Management Ag Unternehmungen Der Beschriftungs, Werbetechnik- U. Druckbranche Usw",
    "wof:placetype":"venue"
},
  "geometry": {"coordinates":[9.4024896622,47.4351501465],"type":"Point"}
}