{
  "type": "Feature",
  "properties": {
    "iso:country":"CH",
    "sg:address":"Sterneng\u00e4sschen 1 3011 Bern. Postfach 5447",
    "sg:city":"Bern",
    "sg:orig_category":"Interessenvertretungen U sonstige Vereinigungen",
    "sg:phone":"+41 31 311 64 11",
    "sg:postcode":"3001",
    "sg:province":"Bern",
    "wof:name":"Bern.verb.f.behindertensport Bvbs",
    "wof:placetype":"venue"
},
  "geometry": {"coordinates":[7.4430189133,46.9496879578],"type":"Point"}
}