{
  "type": "Feature",
  "properties": {
    "iso:country":"CH",
    "sg:address":"R\u00f6tihof",
    "sg:city":"Solothurn",
    "sg:orig_category":"Bau\u00e4mter",
    "sg:phone":"+41 32 627 25 43",
    "sg:postcode":"4500",
    "sg:province":"Solothurn",
    "wof:name":"Kantonales Baudepartement",
    "wof:placetype":"venue"
},
  "geometry": {"coordinates":[7.542105,47.20681],"type":"Point"}
}