{
  "type": "Feature",
  "properties": {
    "iso:country":"CH",
    "sg:address":"Route De Chantemerle 58 1763 Granges-paccot Case Postale 88",
    "sg:city":"Granges-paccot",
    "sg:orig_category":"Werbung",
    "sg:phone":"+41 26 466 83 68",
    "sg:postcode":"1763",
    "sg:province":"Fribourg",
    "wof:name":"Buchheim & Crausaz Communication Company",
    "wof:placetype":"venue"
},
  "geometry": {"coordinates":[7.140182972,46.820224762],"type":"Point"}
}