{
  "type": "Feature",
  "properties": {
    "addr:full":"Bahnhofstrasse 11 6362 Stansstad. Postfach 364 Stansstad Nidwalden 6362",
    "addr:housenumber":"11;364",
    "addr:postcode":"6362 stansstad.;6362",
    "addr:street":"Bahnhofstrasse;Postfach",
    "iso:country":"CH",
    "sg:address":"Bahnhofstrasse 11 6362 Stansstad. Postfach 364",
    "sg:city":"Stansstad",
    "sg:orig_category":"Advokaturb\u00fcros Notariate",
    "sg:phone":"+41 41 630 30 33",
    "sg:postcode":"6362",
    "sg:province":"Nidwalden",
    "wof:name":"Iten Tsch\u00fcmperlin & Poli Advokatur- & Notariatsb\u00fcro",
    "wof:placetype":"venue"
},
  "geometry": {"coordinates":[8.312817,46.987144],"type":"Point"}
}