{
  "type": "Feature",
  "properties": {
    "iso:country":"CH",
    "sg:address":"Berneckerstrasse 26 9435 Heerbrugg. Postfach",
    "sg:city":"Heerbrugg",
    "sg:orig_category":"Unclassifiable Establishments",
    "sg:phone":"+41 71 727 16 53",
    "sg:postcode":"9435",
    "sg:province":"St. Gallen",
    "wof:name":"Yomimasiro Holding Ag",
    "wof:placetype":"venue"
},
  "geometry": {"coordinates":[9.625412941,47.412322998],"type":"Point"}
}