{
  "type": "Feature",
  "properties": {
    "iso:country":"CH",
    "sg:address":"Quartiere Maghetti 20",
    "sg:city":"Lugano",
    "sg:orig_category":"Detailhandel mit Bekleidung",
    "sg:phone":"+41 91 923 95 41",
    "sg:postcode":"6900",
    "sg:province":"Ticino",
    "wof:name":"Boutique Jean Marie Mode Luciana De Santis",
    "wof:placetype":"venue"
},
  "geometry": {"coordinates":[8.953345,46.005192],"type":"Point"}
}