{
  "type": "Feature",
  "properties": {
    "iso:country":"CH",
    "sg:address":"Lerchenstrasse 42",
    "sg:city":"Bottmingen",
    "sg:orig_category":"Unclassifiable Establishments",
    "sg:postcode":"4103",
    "sg:province":"Basel-Landschaft",
    "wof:name":"Consulting.works Leuenberger",
    "wof:placetype":"venue"
},
  "geometry": {"coordinates":[7.5692000389,47.5188484192],"type":"Point"}
}