{
  "type": "Feature",
  "properties": {
    "iso:country":"CH",
    "sg:address":"Alleestrasse 20",
    "sg:city":"Kreuzlingen",
    "sg:orig_category":"Abwasserreinigung Ausbaugewerbe",
    "sg:phone":"+41 32 351 56 56",
    "sg:postcode":"8280",
    "sg:province":"Thurgau",
    "wof:name":"B. Kruse, Rohr-reinigungen",
    "wof:placetype":"venue"
},
  "geometry": {"coordinates":[7.361119,47.142731],"type":"Point"}
}