{
  "type": "Feature",
  "properties": {
    "iso:country":"CH",
    "sg:address":"Sportweg 7 3098 K\u00f6niz. Postfach",
    "sg:city":"Liebefeld",
    "sg:orig_category":"Fotografisches Gewerbe U fotografische Laboratorien",
    "sg:postcode":"3097",
    "sg:province":"Bern",
    "wof:name":"Hans Neuenschwander",
    "wof:placetype":"venue"
},
  "geometry": {"coordinates":[7.4171710014,46.9323577881],"type":"Point"}
}