{
  "type": "Feature",
  "properties": {
    "iso:country":"CH",
    "sg:address":"Bramantino Via 24",
    "sg:city":"Locarno",
    "sg:orig_category":"Saunas, Solarien, Fitnesszentren U \u00e4hnliches",
    "sg:postcode":"6600",
    "sg:province":"Ticino",
    "wof:name":"Supre Sa",
    "wof:placetype":"venue"
},
  "geometry": {"coordinates":[8.7948532104,46.1664848328],"type":"Point"}
}