{
  "type": "Feature",
  "properties": {
    "iso:country":"CH",
    "sg:address":"Furkastrasse 46",
    "sg:city":"Schaffhausen",
    "sg:orig_category":"Vereine Musik/Blasmusik",
    "sg:phone":"+41 52 624 52 35",
    "sg:postcode":"8203",
    "sg:province":"Schaffhausen",
    "wof:name":"Stadtmusik Schaffhausen",
    "wof:placetype":"venue"
},
  "geometry": {"coordinates":[8.6492786407,47.6954498291],"type":"Point"}
}