{
  "type": "Feature",
  "properties": {
    "iso:country":"CH",
    "sg:address":"Stationsrain 2",
    "sg:city":"Rupperswil",
    "sg:orig_category":"RESTAURANTS: TEA-ROOMS",
    "sg:phone":"+41 62 897 12 60",
    "sg:postcode":"5102",
    "sg:province":"Aargau",
    "wof:name":"Restaurant Rainstube",
    "wof:placetype":"venue"
},
  "geometry": {"coordinates":[8.1269960403,47.4044151306],"type":"Point"}
}