{
  "type": "Feature",
  "properties": {
    "iso:country":"CH",
    "sg:address":"Bern-z\u00fcrich-strasse 31",
    "sg:city":"Langenthal",
    "sg:orig_category":"Erbringung von Dienstleistungen f\u00fcr Unternehmen",
    "sg:phone":"+41 31 332 51 82",
    "sg:postcode":"4900",
    "sg:province":"Bern",
    "wof:name":"Motorex-toptech Ag",
    "wof:placetype":"venue"
},
  "geometry": {"coordinates":[7.7824292183,47.2259025574],"type":"Point"}
}