{
  "type": "Feature",
  "properties": {
    "addr:full":"Rue Margencel 27 Aigle Vaud 1860",
    "addr:housenumber":"27",
    "addr:postcode":"1860",
    "addr:street":"Rue Margencel",
    "iso:country":"CH",
    "sg:address":"Rue Margencel 27",
    "sg:city":"Aigle",
    "sg:orig_category":"Bauingenieurb\u00fcros Hochbau Bauingenieurb\u00fcros allgemein",
    "sg:phone":"+41 24 466 15 05",
    "sg:postcode":"1860",
    "sg:province":"Vaud",
    "wof:name":"J.-f. Petignat D'ing\u00e9nieurs-conseils Sa",
    "wof:placetype":"venue"
},
  "geometry": {"coordinates":[6.964978,46.318039],"type":"Point"}
}