{
  "type": "Feature",
  "properties": {
    "iso:country":"CH",
    "sg:address":"Via Baragge 10",
    "sg:city":"Ascona",
    "sg:orig_category":"Unclassifiable Establishments",
    "sg:postcode":"6612",
    "sg:province":"Ticino",
    "wof:name":"Franz-josef B\u00fcchler",
    "wof:placetype":"venue"
},
  "geometry": {"coordinates":[8.7717971802,46.1568107605],"type":"Point"}
}