{
  "type": "Feature",
  "properties": {
    "iso:country":"CH",
    "sg:address":"Vorstadtstrasse 18",
    "sg:city":"Gr\u00e4nichen",
    "sg:orig_category":"RESTAURANTS: TEA-ROOMS",
    "sg:phone":"+41 62 842 02 20",
    "sg:postcode":"5722",
    "sg:province":"Aargau",
    "wof:name":"Liselotte Brechb\u00fchl",
    "wof:placetype":"venue"
},
  "geometry": {"coordinates":[8.0994234085,47.3624038696],"type":"Point"}
}