{
  "type": "Feature",
  "properties": {
    "iso:country":"CH",
    "sg:address":"6490",
    "sg:city":"Andermatt",
    "sg:orig_category":"Landesverteidigung",
    "sg:phone":"+41 41 888 83 32",
    "sg:postcode":"6490",
    "sg:province":"Uri",
    "wof:name":"Eidg. Zeughausbetriebe Waffenplatz Andermatt",
    "wof:placetype":"venue"
},
  "geometry": {"coordinates":[8.5947551727,46.6329498291],"type":"Point"}
}