{
  "type": "Feature",
  "properties": {
    "iso:country":"CH",
    "sg:address":"Hobacherweg 5",
    "sg:city":"Kriens",
    "sg:orig_category":"Herstellung von Metallkonstruktionen Schlossereien",
    "sg:phone":"+41 41 320 42 60",
    "sg:postcode":"6010",
    "sg:province":"Luzern",
    "wof:name":"Max Eberli Schlosserei & Metallbau",
    "wof:placetype":"venue"
},
  "geometry": {"coordinates":[8.2724046707,47.0344009399],"type":"Point"}
}