{
  "type": "Feature",
  "properties": {
    "iso:country":"CH",
    "sg:address":"Hatzenb\u00fchlstrasse 11",
    "sg:city":"N\u00fcrensdorf",
    "sg:orig_category":"Herstellung von Elektromotoren, Generatoren U Transformatoren",
    "sg:phone":"+41 18370110",
    "sg:postcode":"8309",
    "sg:province":"Z\u00fcrich",
    "wof:name":"Aguva Homberger + Partner",
    "wof:placetype":"venue"
},
  "geometry": {"coordinates":[8.6465711594,47.4508323669],"type":"Point"}
}