{
  "type": "Feature",
  "properties": {
    "iso:country":"CH",
    "sg:address":"Seilerbahnweg 8 7000 Chur. Postfach",
    "sg:city":"Chur",
    "sg:orig_category":"Grosshandel mit Tabakwaren",
    "sg:phone":"+41 81 252 12 33",
    "sg:postcode":"7001",
    "sg:province":"Graubunden",
    "wof:name":"Grisotabak Ag",
    "wof:placetype":"venue"
},
  "geometry": {"coordinates":[9.5268115997,46.846950531],"type":"Point"}
}