{
  "type": "Feature",
  "properties": {
    "iso:country":"CH",
    "sg:address":"6577",
    "sg:city":"Ranzo",
    "sg:orig_category":"Gemeindeverwaltungen",
    "sg:phone":"+41 91 827 31 20",
    "sg:postcode":"6577",
    "sg:province":"Ticino",
    "wof:name":"Amministrazione Comunale Di Santa Maria In Calanca",
    "wof:placetype":"venue"
},
  "geometry": {"coordinates":[9.1445598602,46.2630996704],"type":"Point"}
}