{
  "type": "Feature",
  "properties": {
    "iso:country":"CH",
    "sg:address":"Buttenstrasse 8",
    "sg:city":"Oensingen",
    "sg:orig_category":"Primarschulen",
    "sg:phone":"+41 62 396 11 43",
    "sg:postcode":"4702",
    "sg:province":"Solothurn",
    "wof:name":"Primarschule Oberdorf",
    "wof:placetype":"venue"
},
  "geometry": {"coordinates":[7.7168831825,47.2922668457],"type":"Point"}
}