{
  "type": "Feature",
  "properties": {
    "iso:country":"CH",
    "sg:address":"T\u00fcfenaustrasse 5",
    "sg:city":"Herisau",
    "sg:orig_category":"Zimmerei, Dachdeckerei, Bauspenglerei U Abdichtung",
    "sg:phone":"+41 71 377 18 88",
    "sg:postcode":"9100",
    "sg:province":"Appenzell Ausserrhoden",
    "wof:name":"Mettler Josua.",
    "wof:placetype":"venue"
},
  "geometry": {"coordinates":[9.1932601929,47.3048744202],"type":"Point"}
}