{
  "type": "Feature",
  "properties": {
    "iso:country":"CH",
    "sg:address":"Sonnhalde 6056 K\u00e4giswil. Postfach",
    "sg:city":"K\u00e4giswil",
    "sg:orig_category":"Sonstiger spezialisierter Hoch U Tiefbau",
    "sg:phone":"+41 41 660 75 13",
    "sg:postcode":"6056",
    "sg:province":"Obwalden",
    "wof:name":"Kuhn Billy K.",
    "wof:placetype":"venue"
},
  "geometry": {"coordinates":[8.262720108,46.921661377],"type":"Point"}
}