{
  "type": "Feature",
  "properties": {
    "iso:country":"CH",
    "sg:address":"Blumenbergstrasse 39 3013 Bern. Postfach",
    "sg:city":"Bern",
    "sg:orig_category":"Unternehmensberatung",
    "sg:phone":"+41 31 324 31 19",
    "sg:postcode":"3003",
    "sg:province":"Bern",
    "wof:name":"Generalstab Logistik Disposition Ziviler Fahrzeuge",
    "wof:placetype":"venue"
},
  "geometry": {"coordinates":[7.4558677673,46.9558753967],"type":"Point"}
}