{
  "type": "Feature",
  "properties": {
    "iso:country":"CH",
    "sg:address":"Rue Deux-fontaines",
    "sg:city":"Chernex",
    "sg:orig_category":"Fachdetailhandel mit pharmazeutischen Produkten",
    "sg:phone":"+41 21 964 12 55",
    "sg:postcode":"1822",
    "sg:province":"Vaud",
    "wof:name":"Pharmacie De Chernex, M\u00e9rat Ariane",
    "wof:placetype":"venue"
},
  "geometry": {"coordinates":[6.9109158516,46.4437294006],"type":"Point"}
}