{
  "type": "Feature",
  "properties": {
    "iso:country":"CH",
    "sg:address":"Dachslernstrasse 188",
    "sg:city":"Z\u00fcrich",
    "sg:orig_category":"Allgemeinbildende weiterf\u00fchrende Schulen",
    "sg:postcode":"8048",
    "sg:province":"Z\u00fcrich",
    "wof:name":"Edulink.ch Wieland Men Bildungsberatung + Expertisen",
    "wof:placetype":"venue"
},
  "geometry": {"coordinates":[8.470594,47.392765],"type":"Point"}
}