{
  "type": "Feature",
  "properties": {
    "iso:country":"CH",
    "sg:address":"Gajeb\u00e4rg 10b",
    "sg:city":"Rafz",
    "sg:orig_category":"Sonstige Aktivit\u00e4ten der nicht-\u00e4rztlichen Medizinalberufe",
    "sg:phone":"+41 18691960",
    "sg:postcode":"8197",
    "sg:province":"Z\u00fcrich",
    "wof:name":"Ursula Berger Kinesiologie",
    "wof:placetype":"venue"
},
  "geometry": {"coordinates":[8.5446710587,47.6134338379],"type":"Point"}
}