{
  "type": "Feature",
  "properties": {
    "iso:country":"CH",
    "sg:address":"Centro 2000 6595 Riazzino. Postfach",
    "sg:city":"Riazzino",
    "sg:orig_category":"Wirtschaftspr\u00fcfung, Steuerberatung U Treuhand",
    "sg:postcode":"6595",
    "sg:province":"Ticino",
    "wof:name":"Fiduciaria Del Sindaco & Associati Sa",
    "wof:placetype":"venue"
},
  "geometry": {"coordinates":[8.8976049423,46.1745452881],"type":"Point"}
}