{
  "type": "Feature",
  "properties": {
    "addr:full":"Amandiers Chemin Des 1 1950 Sion. Postfach Sitten Valais 1950",
    "addr:postcode":"1950;1950",
    "addr:street":"Chemin Des 1",
    "iso:country":"CH",
    "sg:address":"Amandiers Chemin Des 1 1950 Sion. Postfach",
    "sg:city":"Sitten",
    "sg:orig_category":"Betrieb U technische Hilfsdienste des Kultur U Unterhaltungswesens",
    "sg:postcode":"1950",
    "sg:province":"Valais",
    "wof:name":"Freizag",
    "wof:placetype":"venue"
},
  "geometry": {"coordinates":[8.016311,46.882038],"type":"Point"}
}