{
  "type": "Feature",
  "properties": {
    "iso:country":"CH",
    "sg:address":"D\u00f6rfli 9 3476 Oschwand. Postfach",
    "sg:city":"Oschwand",
    "sg:orig_category":"RESTAURANTS: TEA-ROOMS",
    "sg:postcode":"3476",
    "sg:province":"Bern",
    "wof:name":"Sch\u00f6ni, P.",
    "wof:placetype":"venue"
},
  "geometry": {"coordinates":[7.7126808167,47.1410598755],"type":"Point"}
}