{
  "type": "Feature",
  "properties": {
    "iso:country":"CH",
    "sg:address":"Rue Du Grand-pont 2bis",
    "sg:city":"Lausanne",
    "sg:orig_category":"Zahnarztpraxen",
    "sg:phone":"+41 21 312 66 81",
    "sg:postcode":"1003",
    "sg:province":"Vaud",
    "wof:name":"Dr M\u00e9d.dent. Pierre-g. Parvex M\u00e9decin-dentiste",
    "wof:placetype":"venue"
},
  "geometry": {"coordinates":[6.6319561005,46.5200805664],"type":"Point"}
}