{
  "type": "Feature",
  "properties": {
    "iso:country":"CH",
    "sg:address":"Schmiedenmattstrasse 6",
    "sg:city":"Biberist",
    "sg:orig_category":"Herstellung von Verbrennungsmotoren U Turbinen ohne Motoren f\u00fcr Luft U Strassenfahrzeuge",
    "sg:phone":"+41 19501269",
    "sg:postcode":"4562",
    "sg:province":"Solothurn",
    "wof:name":"Stelzer Motor Ag",
    "wof:placetype":"venue"
},
  "geometry": {"coordinates":[8.7701253891,47.3688316345],"type":"Point"}
}