{
  "type": "Feature",
  "properties": {
    "iso:country":"CH",
    "sg:address":"Im Oberdorf 52",
    "sg:city":"Eptingen",
    "sg:orig_category":"Architektur U Ingenieurb\u00fcros",
    "sg:phone":"+41 61 921 27 21",
    "sg:postcode":"4458",
    "sg:province":"Basel-Landschaft",
    "wof:name":"Egli Design",
    "wof:placetype":"venue"
},
  "geometry": {"coordinates":[7.822503,47.384426],"type":"Point"}
}