{
  "type": "Feature",
  "properties": {
    "iso:country":"CH",
    "sg:address":"Industriestrasse 31",
    "sg:city":"Dietlikon",
    "sg:orig_category":"Detailhandel mit M\u00f6beln Detailhandel mit Teppichen",
    "sg:phone":"+41 18881795",
    "sg:postcode":"8305",
    "sg:province":"Z\u00fcrich",
    "wof:name":"Lipo-m\u00f6belposten Ag",
    "wof:placetype":"venue"
},
  "geometry": {"coordinates":[8.6185569763,47.4122657776],"type":"Point"}
}