{
  "type": "Feature",
  "properties": {
    "iso:country":"CH",
    "sg:address":"Rheinstrasse 8",
    "sg:city":"Birsfelden",
    "sg:orig_category":"Datenverarbeitungsdienste Sonstige mit der Informatik verbundene T\u00e4tigkeiten",
    "sg:phone":"+41 61 312 19 61",
    "sg:postcode":"4127",
    "sg:province":"Basel-Landschaft",
    "wof:name":"Bencze Philip It Services",
    "wof:placetype":"venue"
},
  "geometry": {"coordinates":[7.620308,47.554916],"type":"Point"}
}