{
  "type": "Feature",
  "properties": {
    "iso:country":"CH",
    "sg:address":"Chemin Des Bossons 39bis",
    "sg:city":"Lausanne",
    "sg:orig_category":"Sonstige Kultur U Unterhaltungseinrichtungen",
    "sg:phone":"+41 21 647 09 46",
    "sg:postcode":"1018",
    "sg:province":"Vaud",
    "wof:name":"Assoc.de Quartier Les Bossons",
    "wof:placetype":"venue"
},
  "geometry": {"coordinates":[6.6191978455,46.5382766724],"type":"Point"}
}