{
  "type": "Feature",
  "properties": {
    "iso:country":"CH",
    "sg:address":"W\u00fclflingerstrasse 172",
    "sg:city":"Winterthur",
    "sg:classifiers":[
        {
            "category":"Organizations",
            "subcategory":"Community Association",
            "type":"Services"
        }
    ],
    "sg:phone":"+41 52 243 33 91",
    "sg:postcode":"8408",
    "sg:province":"Z\u00fcrich",
    "sg:tags":[
        "fire",
        "insulation"
    ],
    "wof:name":"Ibk Isolblitz Kolonja Gmbh",
    "wof:placetype":"venue"
},
  "geometry": {"coordinates":[8.690038681,47.51537323],"type":"Point"}
}