{
  "type": "Feature",
  "properties": {
    "iso:country":"CH",
    "sg:address":"Pessot Route Du 23",
    "sg:city":"Broc",
    "sg:orig_category":"Stukkateurgewerbe, Gipserei U Verputzerei",
    "sg:postcode":"1636",
    "sg:province":"Fribourg",
    "wof:name":"Comby S\u00e0rl",
    "wof:placetype":"venue"
},
  "geometry": {"coordinates":[6.8265938759,47.1072921753],"type":"Point"}
}