{
  "type": "Feature",
  "properties": {
    "iso:country":"CH",
    "sg:address":"Feldhofstrasse 49",
    "sg:city":"Flawil",
    "sg:orig_category":"Herstellung von Gummi U Kunststoffwaren",
    "sg:phone":"+41 17840529",
    "sg:postcode":"9230",
    "sg:province":"St. Gallen",
    "wof:name":"Pedrazzini C., Yacht- U. Bootswerft",
    "wof:placetype":"venue"
},
  "geometry": {"coordinates":[8.7265129089,47.2013015747],"type":"Point"}
}