{
  "type": "Feature",
  "properties": {
    "iso:country":"CH",
    "sg:address":"Rue Du Scex 2",
    "sg:city":"Sion",
    "sg:orig_category":"Architektur U Ingenieurb\u00fcros Architekturb\u00fcros",
    "sg:phone":"+41 27 323 70 70",
    "sg:postcode":"1950",
    "sg:province":"Valais",
    "wof:name":"Adt Architecture Et Direction De Travaux S\u00e0rl, Sion",
    "wof:placetype":"venue"
},
  "geometry": {"coordinates":[7.362569,46.231602],"type":"Point"}
}