{
  "type": "Feature",
  "properties": {
    "iso:country":"CH",
    "sg:address":"Br\u00fccke 8716 Schmerikon. Postfach",
    "sg:city":"Schmerikon",
    "sg:orig_category":"Fachdetailhandel in Verkaufsr\u00e4umen",
    "sg:postcode":"8716",
    "sg:province":"St. Gallen",
    "wof:name":"Stucki Fritz, Zweirad-center Und Motorradrahmen-richtwerk Ag",
    "wof:placetype":"venue"
},
  "geometry": {"coordinates":[8.9452991486,47.2260437012],"type":"Point"}
}