{
  "type": "Feature",
  "properties": {
    "iso:country":"CH",
    "sg:address":"Matthofstrasse 15",
    "sg:city":"Aadorf",
    "sg:orig_category":"Erschliessung von Grundst\u00fccken",
    "sg:phone":"+41 52 365 24 13",
    "sg:postcode":"8355",
    "sg:province":"Thurgau",
    "wof:name":"Wohnbaugen.lilie Aadorf",
    "wof:placetype":"venue"
},
  "geometry": {"coordinates":[8.9030218124,47.4847640991],"type":"Point"}
}