{
  "type": "Feature",
  "properties": {
    "iso:country":"CH",
    "sg:address":"Rue De L'h\u00f4tel-de-ville 7",
    "sg:city":"Gen\u00e8ve",
    "sg:orig_category":"Fachdetailhandel in Verkaufsr\u00e4umen Verlagsgewerbe",
    "sg:phone":"+41 22 311 61 36",
    "sg:postcode":"1204",
    "sg:province":"Gen\u00e8ve",
    "wof:name":"Galerie Jacques Benador",
    "wof:placetype":"venue"
},
  "geometry": {"coordinates":[6.1477022171,46.2006797791],"type":"Point"}
}