{
  "type": "Feature",
  "properties": {
    "iso:country":"CH",
    "sg:address":"Landstrasse 56",
    "sg:city":"Wettingen",
    "sg:orig_category":"Werbung",
    "sg:phone":"+41 56 430 26 36",
    "sg:postcode":"5430",
    "sg:province":"Aargau",
    "wof:name":"Productive Pixel, Molinari + Amrein",
    "wof:placetype":"venue"
},
  "geometry": {"coordinates":[8.3227519989,47.4674377441],"type":"Point"}
}