{
  "type": "Feature",
  "properties": {
    "addr:full":"Avenue De Pratifori 22 Sion Valais 1950",
    "addr:housenumber":"22",
    "addr:postcode":"1950",
    "addr:street":"Avenue De Pratifori",
    "iso:country":"CH",
    "sg:address":"Avenue De Pratifori 22",
    "sg:city":"Sion",
    "sg:orig_category":"Alters U Hinterlassenenversicherung AHV, Invalidenversicherung IV, Arbeitslosenversicherung ALV",
    "sg:phone":"+41 27 322 72 95",
    "sg:postcode":"1950",
    "sg:province":"Valais",
    "wof:name":"Caisse De Compensation Du Canton Du Valais Avs Ai Apg Af",
    "wof:placetype":"venue"
},
  "geometry": {"coordinates":[7.354902,46.230522],"type":"Point"}
}