{
  "type": "Feature",
  "properties": {
    "iso:country":"CH",
    "sg:address":"Guggistrasse 15",
    "sg:city":"Luzern",
    "sg:orig_category":"Sonstige mit der Informatik verbundene T\u00e4tigkeiten",
    "sg:phone":"+41 41 242 12 11",
    "sg:postcode":"6005",
    "sg:province":"Luzern",
    "wof:name":"Tangarena Engineering Ag",
    "wof:placetype":"venue"
},
  "geometry": {"coordinates":[8.3005800247,47.0433273315],"type":"Point"}
}