{
  "type": "Feature",
  "properties": {
    "iso:country":"CH",
    "sg:address":"Frohburgstrasse 11",
    "sg:city":"Z\u00fcrich",
    "sg:orig_category":"Unternehmensberatung",
    "sg:phone":"+41 13631015",
    "sg:postcode":"8006",
    "sg:province":"Z\u00fcrich",
    "wof:name":"Triple T Lang Michael",
    "wof:placetype":"venue"
},
  "geometry": {"coordinates":[8.5483360291,47.3869743347],"type":"Point"}
}