{
  "type": "Feature",
  "properties": {
    "addr:full":"Rue Berne 9 Gen\u00e8ve 12010",
    "addr:housenumber":"9",
    "addr:postcode":"12010",
    "addr:street":"Rue Berne",
    "iso:country":"CH",
    "sg:address":"Rue Berne 9",
    "sg:city":"Gen\u00e8ve",
    "sg:classifiers":[
        {
            "category":"Banks & Credit Unions",
            "subcategory":"Bank",
            "type":"Services"
        }
    ],
    "sg:phone":"+41 22 731 34 18",
    "sg:postcode":"12010",
    "wof:name":"Banco Cooperativo Espanol Sa",
    "wof:placetype":"venue"
},
  "geometry": {"coordinates":[6.144612,46.209019],"type":"Point"}
}