{
  "type": "Feature",
  "properties": {
    "iso:country":"CH",
    "sg:address":"Technikumstrasse 9 8400 Winterthur. Postfach 805",
    "sg:city":"Winterthur",
    "sg:orig_category":"H\u00f6here Fachschulen",
    "sg:phone":"+41 32 344 38 11",
    "sg:postcode":"8401",
    "sg:province":"Z\u00fcrich",
    "wof:name":"Technische Fachschule Des Bbz",
    "wof:placetype":"venue"
},
  "geometry": {"coordinates":[7.2556781769,47.1471786499],"type":"Point"}
}