{
  "type": "Feature",
  "properties": {
    "iso:country":"CH",
    "sg:address":"Villars Route De 12",
    "sg:city":"Avenches",
    "sg:orig_category":"Herstellung von Sportger\u00e4ten",
    "sg:phone":"+41 61 751 30 62",
    "sg:postcode":"1580",
    "sg:province":"Vaud",
    "wof:name":"Frau R. Gubler",
    "wof:placetype":"venue"
},
  "geometry": {"coordinates":[7.5996589661,47.471698761],"type":"Point"}
}