{
  "type": "Feature",
  "properties": {
    "iso:country":"CH",
    "sg:address":"Zw\u00e4ngiweg 4",
    "sg:city":"Adliswil",
    "sg:classifiers":[
        {
            "category":"Insurance",
            "subcategory":"Insurance Agent",
            "type":"Services"
        }
    ],
    "sg:phone":"+41 17105112",
    "sg:postcode":"8134",
    "sg:province":"Z\u00fcrich",
    "sg:tags":[
        "versicherungsagenturen",
        "-broker"
    ],
    "wof:name":"Ren\u00e9 Oberholzer Versicherungsb\u00fcro",
    "wof:placetype":"venue"
},
  "geometry": {"coordinates":[8.5337677002,47.3298835754],"type":"Point"}
}