{
  "type": "Feature",
  "properties": {
    "iso:country":"CH",
    "sg:address":"G\u00fctschh\u00f6he 29 6000 Luzern. Postfach",
    "sg:city":"Luzern",
    "sg:orig_category":"Grosshandel mit Getr\u00e4nken",
    "sg:postcode":"6003",
    "sg:province":"Luzern",
    "wof:name":"La Cappelletta Straub J\u00fcrg",
    "wof:placetype":"venue"
},
  "geometry": {"coordinates":[8.2941532135,47.0520935059],"type":"Point"}
}