{
  "type": "Feature",
  "properties": {
    "iso:country":"CH",
    "sg:address":"Stationsstrasse 12",
    "sg:city":"Greifensee",
    "sg:orig_category":"HOTELS: MIT RESTAURANT Sprachschulen",
    "sg:phone":"+41 61 823 92 75",
    "sg:postcode":"8606",
    "sg:province":"Z\u00fcrich",
    "wof:name":"Lid\u00e9n & Denz Gmbh Sprachreisen",
    "wof:placetype":"venue"
},
  "geometry": {"coordinates":[8.6790685654,47.3659515381],"type":"Point"}
}