{
  "type": "Feature",
  "properties": {
    "iso:country":"CH",
    "sg:address":"Abl\u00e4schstrasse 58a 8750 Glarus. Postfach",
    "sg:city":"Glarus",
    "sg:orig_category":"Kauf U Verkauf von Immobilien auf eigene Rechnung",
    "sg:postcode":"8750",
    "sg:province":"Glarus",
    "wof:name":"Gewerbeliegenschaft Kleinzaun Ag",
    "wof:placetype":"venue"
},
  "geometry": {"coordinates":[9.0703411102,47.0363464355],"type":"Point"}
}