{
  "type": "Feature",
  "properties": {
    "addr:full":"Schmerikon Schmerikon St. Gallen 8716",
    "addr:housenumber":"8716",
    "addr:street":"Schmerikon",
    "iso:country":"CH",
    "sg:address":"Schmerikon",
    "sg:city":"Schmerikon",
    "sg:classifiers":[
        {
            "category":"Banks & Credit Unions",
            "subcategory":"Bank",
            "type":"Services"
        }
    ],
    "sg:phone":"+41 55861182",
    "sg:postcode":"8716",
    "sg:province":"St. Gallen",
    "wof:name":"Bank Linth",
    "wof:placetype":"venue"
},
  "geometry": {"coordinates":[8.94206,47.224789],"type":"Point"}
}