{
  "type": "Feature",
  "properties": {
    "iso:country":"CH",
    "sg:address":"Haldenstrasse 9",
    "sg:city":"Sumiswald",
    "sg:orig_category":"Datenverarbeitungsdienste Grosshandel mit Tabakwaren",
    "sg:phone":"+41 34 431 34 66",
    "sg:postcode":"3454",
    "sg:province":"Bern",
    "wof:name":"Philipp Baumann Gmbh",
    "wof:placetype":"venue"
},
  "geometry": {"coordinates":[7.744304,47.026199],"type":"Point"}
}