{
  "type": "Feature",
  "properties": {
    "iso:country":"CH",
    "sg:address":"Rue Centrale 31",
    "sg:city":"Orbe",
    "sg:orig_category":"Herstellung von Uhren Reparatur von Uhren U Schmuck",
    "sg:phone":"+41 32 486 90 50",
    "sg:postcode":"1350",
    "sg:province":"Vaud",
    "wof:name":"Paratte, Maxime.",
    "wof:placetype":"venue"
},
  "geometry": {"coordinates":[7.08335495,47.2246208191],"type":"Point"}
}