{
  "type": "Feature",
  "properties": {
    "iso:country":"CH",
    "sg:address":"Kirchb\u00fchl 10",
    "sg:city":"Burgdorf",
    "sg:orig_category":"Interessenvertretungen",
    "sg:postcode":"3400",
    "sg:province":"Bern",
    "wof:name":"Stiftung Paul Zuppinger",
    "wof:placetype":"venue"
},
  "geometry": {"coordinates":[7.6261138916,47.0564422607],"type":"Point"}
}