{
  "type": "Feature",
  "properties": {
    "iso:country":"CH",
    "sg:address":"Luppmenstrasse 11",
    "sg:city":"Fehraltorf",
    "sg:classifiers":[
        {
            "category":"Home & Garden",
            "subcategory":"Home Furnishings",
            "type":"Retail Goods"
        }
    ],
    "sg:phone":"+41 19541911",
    "sg:postcode":"8320",
    "sg:province":"Z\u00fcrich",
    "sg:tags":[
        "air-conditioners"
    ],
    "wof:name":"R. Lemmenmeier Ag",
    "wof:placetype":"venue"
},
  "geometry": {"coordinates":[8.745855,47.38784],"type":"Point"}
}