{
  "type": "Feature",
  "properties": {
    "iso:country":"CH",
    "sg:address":"R\u00fcschlistrasse 31",
    "sg:city":"Biel/bienne",
    "sg:orig_category":"Non-Classified Establishments",
    "sg:postcode":"2502",
    "sg:province":"Bern",
    "wof:name":"Suzanne Castelberg Atelier Design Desire",
    "wof:placetype":"venue"
},
  "geometry": {"coordinates":[7.2448067665,47.1377296448],"type":"Point"}
}