{
  "type": "Feature",
  "properties": {
    "iso:country":"CH",
    "sg:address":"Mafroi 6",
    "sg:city":"Nyon",
    "sg:orig_category":"Erdbewegungsarbeiten Strassenbau",
    "sg:phone":"+41 22 362 18 30",
    "sg:postcode":"1260",
    "sg:province":"Vaud",
    "wof:name":"Bossert Graf Sa Terrassement & Construction",
    "wof:placetype":"venue"
},
  "geometry": {"coordinates":[6.2421908379,46.3849754333],"type":"Point"}
}