{
  "type": "Feature",
  "properties": {
    "iso:country":"CH",
    "sg:address":"Marktgasse 11",
    "sg:city":"Appenzell",
    "sg:orig_category":"Detailhandel mit M\u00f6beln U Haushaltsgegenst\u00e4nden Innenarchitekturb\u00fcros",
    "sg:phone":"+41 71 787 22 14",
    "sg:postcode":"9050",
    "sg:province":"Appenzell Innerhoden",
    "wof:name":"Franz Th\u00fcr Ag",
    "wof:placetype":"venue"
},
  "geometry": {"coordinates":[9.4084596634,47.3315353394],"type":"Point"}
}