{
  "type": "Feature",
  "properties": {
    "iso:country":"CH",
    "sg:address":"Neugasse 49",
    "sg:city":"St.gallen",
    "sg:classifiers":[
        {
            "category":"Professional",
            "subcategory":"Employment Agencies",
            "type":"Services"
        }
    ],
    "sg:phone":"+41 71 228 08 80",
    "sg:postcode":"9000",
    "sg:province":"St. Gallen",
    "sg:tags":[
        "personal",
        "u",
        "stellenvermittlung"
    ],
    "wof:name":"Progress Personal Ag Zweigniederlassung St. Gallen",
    "wof:placetype":"venue"
},
  "geometry": {"coordinates":[9.3747529984,47.4241943359],"type":"Point"}
}