{
  "type": "Feature",
  "properties": {
    "iso:country":"CH",
    "sg:address":"Kasernenstrasse 68",
    "sg:city":"Herisau",
    "sg:orig_category":"Tankstellen",
    "sg:phone":"+41 71 351 23 41",
    "sg:postcode":"9100",
    "sg:province":"Appenzell Ausserrhoden",
    "wof:name":"K. + W. Kuratli Bp Service Herisau",
    "wof:placetype":"venue"
},
  "geometry": {"coordinates":[9.2892808914,47.3893318176],"type":"Point"}
}