{
  "type": "Feature",
  "properties": {
    "iso:country":"CH",
    "sg:address":"6644 Orselina. Postfach Caselle Postale 87",
    "sg:city":"Orselina",
    "sg:orig_category":"Sportvereine Boxen",
    "sg:postcode":"6644",
    "sg:province":"Ticino",
    "wof:name":"Societ\u00e0 Podistica Locarnese",
    "wof:placetype":"venue"
},
  "geometry": {"coordinates":[8.7967700958,46.1801109314],"type":"Point"}
}