{
  "type": "Feature",
  "properties": {
    "iso:country":"CH",
    "sg:address":"Savoie Rue Louis De 49",
    "sg:city":"Morges",
    "sg:orig_category":"Markt U Meinungsforschung",
    "sg:postcode":"1110",
    "sg:province":"Vaud",
    "wof:name":"One Up, Bengt A. Berglund",
    "wof:placetype":"venue"
},
  "geometry": {"coordinates":[6.4988970757,46.5084457397],"type":"Point"}
}