{
  "type": "Feature",
  "properties": {
    "iso:country":"CH",
    "sg:address":"M\u00f6\u00f6sli 49",
    "sg:city":"Oberhof",
    "sg:orig_category":"Verarbeitung von Milch Verwertung von Milch",
    "sg:postcode":"5062",
    "sg:province":"Aargau",
    "wof:name":"Milchgenossenschaft Oberhof",
    "wof:placetype":"venue"
},
  "geometry": {"coordinates":[8.0064573288,47.4502944946],"type":"Point"}
}