{
  "type": "Feature",
  "properties": {
    "iso:country":"CH",
    "sg:address":"Erismannstrasse 54",
    "sg:city":"Z\u00fcrich",
    "sg:orig_category":"Non-Classified Establishments",
    "sg:postcode":"8004",
    "sg:province":"Z\u00fcrich",
    "wof:name":"Remotephoto.com, Stollenwerk",
    "wof:placetype":"venue"
},
  "geometry": {"coordinates":[8.5166339874,47.377281189],"type":"Point"}
}