{
  "type": "Feature",
  "properties": {
    "iso:country":"CH",
    "sg:address":"Rue Des Vollandes 24",
    "sg:city":"Gen\u00e8ve",
    "sg:orig_category":"Schiffs U Bootsbau",
    "sg:phone":"+41 32 932 14 14",
    "sg:postcode":"1207",
    "sg:province":"Gen\u00e8ve",
    "wof:name":"Durig Jean-claude",
    "wof:placetype":"venue"
},
  "geometry": {"coordinates":[6.6982851028,47.0666809082],"type":"Point"}
}