{
  "type": "Feature",
  "properties": {
    "iso:country":"CH",
    "sg:address":"Clus V\u00e9lez 26",
    "sg:city":"Malleray",
    "sg:orig_category":"Unternehmensberatung",
    "sg:postcode":"2735",
    "sg:province":"Bern",
    "wof:name":"Grossmann Thomas A. Conseil D'entreprise",
    "wof:placetype":"venue"
},
  "geometry": {"coordinates":[7.267127037,47.241268158],"type":"Point"}
}