{
  "type": "Feature",
  "properties": {
    "iso:country":"CH",
    "sg:address":"Hauptstrasse 55",
    "sg:city":"Bilten",
    "sg:classifiers":[
        {
            "category":"Autos & Motor Vehicles",
            "subcategory":"Auto Supplies",
            "type":"Retail Goods"
        }
    ],
    "sg:phone":"+41 55 619 21 11",
    "sg:postcode":"8865",
    "sg:province":"Glarus",
    "sg:tags":[
        "automobile",
        "painting"
    ],
    "wof:name":"St\u00fcssi Automobile Ag",
    "wof:placetype":"venue"
},
  "geometry": {"coordinates":[9.02801,47.143604],"type":"Point"}
}