{
  "type": "Feature",
  "properties": {
    "iso:country":"CH",
    "sg:address":"Rue St-hubert 4 2854 Bassecourt Case Postale 242",
    "sg:city":"Bassecourt",
    "sg:orig_category":"Bauspenglerei Sanit\u00e4rinstallation",
    "sg:phone":"+41 32 426 53 57",
    "sg:postcode":"2854",
    "sg:province":"Jura",
    "wof:name":"Marius Cattin Inst.sanitaires & Ferblanterie",
    "wof:placetype":"venue"
},
  "geometry": {"coordinates":[7.241974,47.338795],"type":"Point"}
}