{
  "type": "Feature",
  "properties": {
    "addr:full":"Seestrasse 50 Kreuzlingen Thurgau 8280",
    "addr:housenumber":"50",
    "addr:postcode":"8280",
    "addr:street":"Seestrasse",
    "iso:country":"CH",
    "sg:address":"Seestrasse 50",
    "sg:city":"Kreuzlingen",
    "sg:orig_category":"Detailhandel mit Antiquit\u00e4ten",
    "sg:phone":"+41 71 672 55 71",
    "sg:postcode":"8280",
    "sg:province":"Thurgau",
    "wof:name":"Fritz Zbornik Antiquit\u00e4ten",
    "wof:placetype":"venue"
},
  "geometry": {"coordinates":[9.180459,47.65123],"type":"Point"}
}