{
  "type": "Feature",
  "properties": {
    "iso:country":"CH",
    "sg:address":"T\u00f6distrasse 1",
    "sg:city":"Dietlikon",
    "sg:orig_category":"Herstellung von sonstigen organischen Grundstoffen U Chemikalien",
    "sg:phone":"+41 18334733",
    "sg:postcode":"8305",
    "sg:province":"Z\u00fcrich",
    "wof:name":"Printec Van Der Meulen",
    "wof:placetype":"venue"
},
  "geometry": {"coordinates":[8.6171646118,47.4189147949],"type":"Point"}
}