{
  "type": "Feature",
  "properties": {
    "iso:country":"CH",
    "sg:address":"Marktgasse 11",
    "sg:city":"Baar",
    "sg:classifiers":[
        {
            "category":"Banks & Credit Unions",
            "subcategory":"Bank",
            "type":"Services"
        }
    ],
    "sg:phone":"+41 62 391 32 19",
    "sg:postcode":"6340",
    "sg:province":"Zug",
    "wof:name":"Raiffeisenbank Balsthal",
    "wof:placetype":"venue"
},
  "geometry": {"coordinates":[7.610532,47.304459],"type":"Point"}
}