{
  "type": "Feature",
  "properties": {
    "iso:country":"CH",
    "sg:address":"Bizenenstrasse 25",
    "sg:city":"Muttenz",
    "sg:orig_category":"Wohnheime",
    "sg:phone":"+41 61 462 08 51",
    "sg:postcode":"4132",
    "sg:province":"Basel-Landschaft",
    "wof:name":"Asylbewerberheim",
    "wof:placetype":"venue"
},
  "geometry": {"coordinates":[7.651966095,47.530254364],"type":"Point"}
}