{
  "type": "Feature",
  "properties": {
    "iso:country":"CH",
    "sg:address":"3214",
    "sg:city":"Ulmiz",
    "sg:orig_category":"Organisationen des Gesundheitswesen",
    "sg:phone":"+41 18561521",
    "sg:postcode":"3214",
    "sg:province":"Fribourg",
    "wof:name":"Samariterverein Unterer Reiath",
    "wof:placetype":"venue"
},
  "geometry": {"coordinates":[8.6779251099,47.7832641602],"type":"Point"}
}