{
  "type": "Feature",
  "properties": {
    "iso:country":"CH",
    "sg:address":"Seestrasse 36",
    "sg:city":"Altendorf",
    "sg:classifiers":[
        {
            "category":"Autos & Motor Vehicles",
            "subcategory":"Boat Sales",
            "type":"Retail Goods"
        }
    ],
    "sg:phone":"+41 55 451 55 55",
    "sg:postcode":"8852",
    "sg:province":"Schwyz",
    "sg:tags":[
        "cover"
    ],
    "wof:name":"Hensa Werft Ag",
    "wof:placetype":"venue"
},
  "geometry": {"coordinates":[8.82175,47.19442],"type":"Point"}
}