{
  "type": "Feature",
  "properties": {
    "addr:full":"Gerechtigkeitsgasse 64 Bern Bern 3011",
    "addr:housenumber":"64",
    "addr:postcode":"3011",
    "addr:street":"Gerechtigkeitsgasse",
    "iso:country":"CH",
    "sg:address":"Gerechtigkeitsgasse 64",
    "sg:city":"Bern",
    "sg:orig_category":"Detailhandel mit Antiquit\u00e4ten",
    "sg:phone":"+41 31 311 04 13",
    "sg:postcode":"3011",
    "sg:province":"Bern",
    "wof:name":"Boutique Luciano Berti Antiquit\u00e4ten",
    "wof:placetype":"venue"
},
  "geometry": {"coordinates":[7.453207,46.94825],"type":"Point"}
}