{
  "type": "Feature",
  "properties": {
    "iso:country":"CH",
    "sg:address":"Arlesheimerstrasse 52",
    "sg:city":"Basel",
    "sg:orig_category":"Vorschulen, Kinderg\u00e4rten",
    "sg:phone":"+41 61 733 93 55",
    "sg:postcode":"4053",
    "sg:province":"Basel-Stadt",
    "wof:name":"Kindergarten",
    "wof:placetype":"venue"
},
  "geometry": {"coordinates":[7.5166249275,47.4780158997],"type":"Point"}
}