{
  "type": "Feature",
  "properties": {
    "iso:country":"CH",
    "sg:address":"Alte Winterthurerstrasse 5",
    "sg:city":"Wallisellen",
    "sg:orig_category":"Allgemeiner Hoch U Tiefbau",
    "sg:phone":"+41 18305022",
    "sg:postcode":"8304",
    "sg:province":"Z\u00fcrich",
    "wof:name":"Geworag Ag",
    "wof:placetype":"venue"
},
  "geometry": {"coordinates":[8.584631,47.41489],"type":"Point"}
}