{
  "type": "Feature",
  "properties": {
    "iso:country":"CH",
    "sg:address":"Bundesplatz 1",
    "sg:city":"Zug",
    "sg:orig_category":"Unclassifiable Establishments",
    "sg:postcode":"6300",
    "sg:province":"Zug",
    "wof:name":"Safeprotect Ag",
    "wof:placetype":"venue"
},
  "geometry": {"coordinates":[8.5155754089,47.1706352234],"type":"Point"}
}