{
  "type": "Feature",
  "properties": {
    "iso:country":"CH",
    "sg:address":"Rue Industrielle",
    "sg:city":"Montreux",
    "sg:orig_category":"Architektur U Ingenieurb\u00fcros",
    "sg:phone":"+41 21 964 72 76",
    "sg:postcode":"1820",
    "sg:province":"Vaud",
    "wof:name":"Atelier D'architecture Thomann & Thomann Sa",
    "wof:placetype":"venue"
},
  "geometry": {"coordinates":[6.913115,46.433674],"type":"Point"}
}