{
  "type": "Feature",
  "properties": {
    "iso:country":"CH",
    "sg:address":"Route De Pampigny",
    "sg:city":"Apples",
    "sg:orig_category":"Herstellung von Metallerzeugnissen ohne Maschinenbau Herstellung von Rohren",
    "sg:phone":"+41 31 747 85 11",
    "sg:postcode":"1143",
    "sg:province":"Vaud",
    "wof:name":"Maurer Ludwig Ag, Ofenrohre & Metallwaren.",
    "wof:placetype":"venue"
},
  "geometry": {"coordinates":[7.2354688644,46.9057388306],"type":"Point"}
}