{
  "type": "Feature",
  "properties": {
    "iso:country":"CH",
    "sg:address":"Giufsteinweg 4",
    "sg:city":"Sevelen",
    "sg:orig_category":"Grosshandel mit chemischen Erzeugnissen",
    "sg:postcode":"9475",
    "sg:province":"St. Gallen",
    "wof:name":"Meier Consulting",
    "wof:placetype":"venue"
},
  "geometry": {"coordinates":[8.5683469772,47.5493431091],"type":"Point"}
}