{
  "type": "Feature",
  "properties": {
    "iso:country":"CH",
    "sg:address":"Niederbleiken 102",
    "sg:city":"Bleiken",
    "sg:orig_category":"G\u00fcterbef\u00f6rderung im Strassenverkehr",
    "sg:phone":"+41 31 771 18 62",
    "sg:postcode":"3674",
    "sg:province":"Bern",
    "wof:name":"Christian Jutzi Transporte",
    "wof:placetype":"venue"
},
  "geometry": {"coordinates":[7.6340842247,46.8139305115],"type":"Point"}
}