{
  "type": "Feature",
  "properties": {
    "iso:country":"CH",
    "sg:address":"M\u00fchlestock 122a 3271 Radelfingen. Postfach",
    "sg:city":"Detligen",
    "sg:orig_category":"Softwareentwicklung U beratung",
    "sg:postcode":"3036",
    "sg:province":"Bern",
    "wof:name":"Hunziker Stefan",
    "wof:placetype":"venue"
},
  "geometry": {"coordinates":[7.2724680901,47.0219154358],"type":"Point"}
}