{
  "type": "Feature",
  "properties": {
    "iso:country":"CH",
    "sg:address":"Feldstrasse 20",
    "sg:city":"Turbenthal",
    "sg:orig_category":"Dienstleistungen von Beteiligungsgesellschaften",
    "sg:phone":"+41 52 385 28 85",
    "sg:postcode":"8488",
    "sg:province":"Z\u00fcrich",
    "wof:name":"B\u00fcro Service Zimmermann Maya",
    "wof:placetype":"venue"
},
  "geometry": {"coordinates":[8.8558912277,47.436290741],"type":"Point"}
}