{
  "type": "Feature",
  "properties": {
    "iso:country":"CH",
    "sg:address":"Niederglatterstrasse 10",
    "sg:city":"Niederhasli",
    "sg:orig_category":"Detailhandel mit Waren verschiedener Art in Verkaufsr\u00e4umen Grosshandel mit Nahrungsmitteln, Getr\u00e4nke",
    "sg:phone":"+41 18851055",
    "sg:postcode":"8155",
    "sg:province":"Z\u00fcrich",
    "wof:name":"Epa-superdiscount Haslim\u00e4rt, R\u00fcdis\u00fcli U.",
    "wof:placetype":"venue"
},
  "geometry": {"coordinates":[8.4858007431,47.4811019897],"type":"Point"}
}