{
  "type": "Feature",
  "properties": {
    "addr:full":"Bruderholzallee 47 Basel Basel-Stadt 4059",
    "addr:housenumber":"47",
    "addr:postcode":"4059",
    "addr:street":"Bruderholzallee",
    "iso:country":"CH",
    "sg:address":"Bruderholzallee 47",
    "sg:city":"Basel",
    "sg:orig_category":"Abwasserreinigung",
    "sg:phone":"+41 800 321 222",
    "sg:postcode":"4059",
    "sg:province":"Basel-Stadt",
    "wof:name":"A-z Marquis Ag Kanal-service",
    "wof:placetype":"venue"
},
  "geometry": {"coordinates":[7.58777,47.534271],"type":"Point"}
}