{
  "type": "Feature",
  "properties": {
    "iso:country":"CH",
    "sg:address":"Obere Gasse 10",
    "sg:city":"Chur",
    "sg:orig_category":"Arztpraxen",
    "sg:phone":"+41 81 252 14 94",
    "sg:postcode":"7000",
    "sg:province":"Graubunden",
    "wof:name":"Dr.med.jachen Vonzun Arzt F.allgemeine Medizin Fmh",
    "wof:placetype":"venue"
},
  "geometry": {"coordinates":[9.531765,46.848366],"type":"Point"}
}