{
  "type": "Feature",
  "properties": {
    "addr:full":"Wiesenweg 37 5102 Rupperswil. Postfach Rupperswil Aargau 5102",
    "addr:housenumber":"37",
    "addr:postcode":"5102 rupperswil. postfach;5102",
    "addr:street":"Wiesenweg",
    "iso:country":"CH",
    "sg:address":"Wiesenweg 37 5102 Rupperswil. Postfach",
    "sg:city":"Rupperswil",
    "sg:orig_category":"Architektur U Ingenieurb\u00fcros",
    "sg:phone":"+41 62 889 22 60",
    "sg:postcode":"5102",
    "sg:province":"Aargau",
    "wof:name":"Setz Werner",
    "wof:placetype":"venue"
},
  "geometry": {"coordinates":[8.140559,47.407833],"type":"Point"}
}