{
  "type": "Feature",
  "properties": {
    "iso:country":"CH",
    "sg:address":"Leonhard Ragaz-weg 1",
    "sg:city":"Z\u00fcrich",
    "sg:orig_category":"Wirtschaftspr\u00fcfung, Steuerberatung U Treuhand",
    "sg:phone":"+41 14632078",
    "sg:postcode":"8055",
    "sg:province":"Z\u00fcrich",
    "wof:name":"Ganahl Treuhand",
    "wof:placetype":"venue"
},
  "geometry": {"coordinates":[8.5084848404,47.371055603],"type":"Point"}
}