{
  "type": "Feature",
  "properties": {
    "iso:country":"CH",
    "sg:address":"Rue Porc\u00e9laine 13",
    "sg:city":"Nyon",
    "sg:orig_category":"Unternehmensberatung",
    "sg:phone":"+41 32 853 14 12",
    "sg:postcode":"1260",
    "sg:province":"Vaud",
    "wof:name":"Jean-robert L'eplattenier Conseils De Direction",
    "wof:placetype":"venue"
},
  "geometry": {"coordinates":[6.9220199585,47.0640907288],"type":"Point"}
}