{
  "type": "Feature",
  "properties": {
    "iso:country":"CH",
    "sg:address":"Rue Du Simplon 14",
    "sg:city":"Martigny",
    "sg:orig_category":"Schreib U \u00dcbersetzungsb\u00fcros Schreibb\u00fcros",
    "sg:phone":"+41 62 842 07 70",
    "sg:postcode":"1920",
    "sg:province":"Valais",
    "wof:name":"Schreibservice Corina L\u00fcthi",
    "wof:placetype":"venue"
},
  "geometry": {"coordinates":[8.087061882,47.3906440735],"type":"Point"}
}