{
  "type": "Feature",
  "properties": {
    "iso:country":"CH",
    "sg:address":"Branvaude Route De La 53",
    "sg:city":"Chavannes-des-bois",
    "sg:orig_category":"Reiseb\u00fcros U Reiseveranstalter",
    "sg:phone":"+41 79 202 34 74",
    "sg:postcode":"1290",
    "sg:province":"Gen\u00e8ve",
    "wof:name":"Petit Prince Min, Jee",
    "wof:placetype":"venue"
},
  "geometry": {"coordinates":[6.1671500206,46.280292511],"type":"Point"}
}