{
  "type": "Feature",
  "properties": {
    "iso:country":"CH",
    "sg:address":"Efringerstrasse 86",
    "sg:city":"Basel",
    "sg:orig_category":"Herstellung von Glas U Glaswaren Herstellung von keramischen Haushaltswaren U Ziergegenst\u00e4nden",
    "sg:phone":"+41 41 850 70 80",
    "sg:postcode":"4057",
    "sg:province":"Basel-Stadt",
    "wof:name":"Fragile Glas Und Porzellan Gmbh",
    "wof:placetype":"venue"
},
  "geometry": {"coordinates":[8.4403533936,47.0812263489],"type":"Point"}
}