{
  "type": "Feature",
  "properties": {
    "iso:country":"CH",
    "sg:address":"Grunibodenstrasse 23 3954 Leukerbad. Postfach",
    "sg:city":"Leukerbad",
    "sg:orig_category":"Detailhandel mit Waren verschiedener Art, Hauptrichtung Nahrungsmittel Grosshandel mit Nahrungsmitte",
    "sg:phone":"+41 71 744 78 83",
    "sg:postcode":"3954",
    "sg:province":"Valais",
    "wof:name":"Denner-satellit Karlstetter Max",
    "wof:placetype":"venue"
},
  "geometry": {"coordinates":[9.6351919174,47.4310073853],"type":"Point"}
}