{
  "type": "Feature",
  "properties": {
    "iso:country":"CH",
    "sg:address":"Promenadenstrasse 13",
    "sg:city":"Rorschach",
    "sg:orig_category":"Herstellung von Radio U Fernsehger\u00e4ten sowie phono U videotechnischen Ger\u00e4ten",
    "sg:postcode":"9400",
    "sg:province":"St. Gallen",
    "wof:name":"Bulgheroni Bruno Import",
    "wof:placetype":"venue"
},
  "geometry": {"coordinates":[9.5067358017,47.4771575928],"type":"Point"}
}