{
  "type": "Feature",
  "properties": {
    "iso:country":"CH",
    "sg:address":"Chemin De Pierrefleur 74 1000 Lausanne. Postfach",
    "sg:city":"Lausanne",
    "sg:orig_category":"RESTAURANTS: TEA-ROOMS",
    "sg:postcode":"1003",
    "sg:province":"Vaud",
    "wof:name":"Volluz Gilbert",
    "wof:placetype":"venue"
},
  "geometry": {"coordinates":[6.6130290031,46.5408439636],"type":"Point"}
}