{
  "type": "Feature",
  "properties": {
    "iso:country":"CH",
    "sg:address":"Gewerbestrasse 5b 8708 M\u00e4nnedorf. Postfach 879",
    "sg:city":"M\u00e4nnedorf",
    "sg:orig_category":"Architektur U Ingenieurb\u00fcros",
    "sg:phone":"+41 19224040",
    "sg:postcode":"8708",
    "sg:province":"Z\u00fcrich",
    "wof:name":"Fontana & Partner Ag, Architektur + Planung",
    "wof:placetype":"venue"
},
  "geometry": {"coordinates":[8.701081,47.258392],"type":"Point"}
}