{
  "type": "Feature",
  "properties": {
    "iso:country":"CH",
    "sg:address":"Grand-rue",
    "sg:city":"Champ\u00e9ry",
    "sg:orig_category":"RESTAURANTS: TEA-ROOMS",
    "sg:phone":"+41 24 479 15 50",
    "sg:postcode":"1874",
    "sg:province":"Valais",
    "wof:name":"Riley Martin John",
    "wof:placetype":"venue"
},
  "geometry": {"coordinates":[6.8717827797,46.1801567078],"type":"Point"}
}