{
  "type": "Feature",
  "properties": {
    "iso:country":"CH",
    "sg:address":"Schmittlistrasse 6c",
    "sg:city":"Ebnat-kappel",
    "sg:orig_category":"Kosmetikinstitute",
    "sg:phone":"+41 71 993 11 21",
    "sg:postcode":"9642",
    "sg:province":"St. Gallen",
    "wof:name":"Anna Lusti Kosmetikinstitut",
    "wof:placetype":"venue"
},
  "geometry": {"coordinates":[9.1270627975,47.264289856],"type":"Point"}
}