{
  "type": "Feature",
  "properties": {
    "iso:country":"CH",
    "sg:address":"Zumhof-terrasse 11",
    "sg:city":"Kriens",
    "sg:orig_category":"Mit dem Versicherungsgewerbe verbundene T\u00e4tigkeiten",
    "sg:phone":"+41 61 261 04 80",
    "sg:postcode":"6010",
    "sg:province":"Luzern",
    "wof:name":"Anlageberatung Aebi Urs & Partner",
    "wof:placetype":"venue"
},
  "geometry": {"coordinates":[8.2726240158,47.0376586914],"type":"Point"}
}