{
  "type": "Feature",
  "properties": {
    "iso:country":"CH",
    "sg:address":"Avenue De La Gare 1",
    "sg:city":"Neuch\u00e2tel",
    "sg:orig_category":"Arztpraxen",
    "sg:phone":"+41 21 946 17 11",
    "sg:postcode":"2000",
    "sg:province":"Neuch\u00e2tel",
    "wof:name":"Dr M\u00e9d. Philippe Chapuis M\u00e9decin G\u00e9n\u00e9raliste Fmh",
    "wof:placetype":"venue"
},
  "geometry": {"coordinates":[7.09619,46.089569],"type":"Point"}
}