{
  "type": "Feature",
  "properties": {
    "iso:country":"CH",
    "sg:address":"1749",
    "sg:city":"Middes",
    "sg:orig_category":"Dienstleistungen von Beteiligungsgesellschaften",
    "sg:phone":"+41 26 658 12 30",
    "sg:postcode":"1749",
    "sg:province":"Fribourg",
    "wof:name":"Le Praticien, Marcel Linder",
    "wof:placetype":"venue"
},
  "geometry": {"coordinates":[6.9493298531,46.7676506042],"type":"Point"}
}