{
  "type": "Feature",
  "properties": {
    "iso:country":"CH",
    "sg:address":"Ebnaterstrasse 62 9642 Ebnat. Postfach 297",
    "sg:city":"Ebnat",
    "sg:orig_category":"Herstellung von Kunststoffwaren Herstellung von sonstigen chemischen Erzeugnissen",
    "sg:phone":"+41 71 993 18 81",
    "sg:postcode":"9642",
    "sg:province":"St. Gallen",
    "wof:name":"Chemie-faser Ebnat Ag",
    "wof:placetype":"venue"
},
  "geometry": {"coordinates":[9.1286096573,47.2590789795],"type":"Point"}
}