{
  "type": "Feature",
  "properties": {
    "iso:country":"CH",
    "sg:address":"Viktoriastrasse 36 3084 Wabern. Postfach",
    "sg:city":"Wabern",
    "sg:orig_category":"Wirtschaftspr\u00fcfung, Steuerberatung U Treuhand",
    "sg:postcode":"3084",
    "sg:province":"Bern",
    "wof:name":"Contafin Treuhand Und Revisions Ag",
    "wof:placetype":"venue"
},
  "geometry": {"coordinates":[7.4546608925,46.9294815063],"type":"Point"}
}