{
  "type": "Feature",
  "properties": {
    "addr:full":"Buristrasse 12 3006 Bern. Postfach Bern Bern 3005",
    "addr:housenumber":"12",
    "addr:postcode":"3006;postfach;3005",
    "addr:street":"Buristrasse",
    "iso:country":"CH",
    "sg:address":"Buristrasse 12 3006 Bern. Postfach",
    "sg:city":"Bern",
    "sg:orig_category":"Detailhandel mit Bekleidung",
    "sg:postcode":"3005",
    "sg:province":"Bern",
    "wof:name":"Happy Day Engel Pia Brautmode U Couture",
    "wof:placetype":"venue"
},
  "geometry": {"coordinates":[7.474815,46.945087],"type":"Point"}
}