{
  "type": "Feature",
  "properties": {
    "iso:country":"CH",
    "sg:address":"G\u00e4nseackerweg 5",
    "sg:city":"Balsthal",
    "sg:orig_category":"Druckweiterverarbeitung",
    "sg:phone":"+41 62 391 25 64",
    "sg:postcode":"4710",
    "sg:province":"Solothurn",
    "wof:name":"Karin Stauffer Buchbinderei",
    "wof:placetype":"venue"
},
  "geometry": {"coordinates":[7.6920390129,47.3166503906],"type":"Point"}
}