{
  "type": "Feature",
  "properties": {
    "iso:country":"CH",
    "sg:address":"Horwerstrasse 40",
    "sg:city":"Kriens",
    "sg:orig_category":"Ingenieurb\u00fcros Elektro",
    "sg:phone":"+41 41 310 80 22",
    "sg:postcode":"6010",
    "sg:province":"Luzern",
    "wof:name":"Fischer Ingenieurb\u00fcro",
    "wof:placetype":"venue"
},
  "geometry": {"coordinates":[8.2915258408,47.0295257568],"type":"Point"}
}