{
  "type": "Feature",
  "properties": {
    "iso:country":"CH",
    "sg:address":"Via Boschina 3b",
    "sg:city":"Pregassona",
    "sg:orig_category":"Sportvereine Orientierungslauf",
    "sg:postcode":"6963",
    "sg:province":"Ticino",
    "wof:name":"Asco Regione Di Lugano",
    "wof:placetype":"venue"
},
  "geometry": {"coordinates":[8.963312149,46.018119812],"type":"Point"}
}