{
  "type": "Feature",
  "properties": {
    "iso:country":"CH",
    "sg:address":"Rue Abb\u00e9-g.-joliat 2",
    "sg:city":"Court\u00e9telle",
    "sg:classifiers":[
        {
            "category":"Restaurant",
            "type":"Food & Drink"
        }
    ],
    "sg:phone":"+41 32 423 36 89",
    "sg:postcode":"2852",
    "sg:province":"Jura",
    "wof:name":"Caf\u00e9 De La Couronne",
    "wof:placetype":"venue"
},
  "geometry": {"coordinates":[7.3182291985,47.3396034241],"type":"Point"}
}