{
  "type": "Feature",
  "properties": {
    "addr:full":"Ch\u00f6pfliweg Metzerlen Solothurn 4116",
    "addr:postcode":"4116",
    "addr:street":"Metzerlen",
    "iso:country":"CH",
    "sg:address":"Ch\u00f6pfliweg",
    "sg:city":"Metzerlen",
    "sg:classifiers":[
        {
            "category":"Banks & Credit Unions",
            "subcategory":"Bank",
            "type":"Services"
        }
    ],
    "sg:phone":"+41 61 735 90 90",
    "sg:postcode":"4116",
    "sg:province":"Solothurn",
    "wof:name":"Raiffeisenbank Metzerlen-mariastein-burg",
    "wof:placetype":"venue"
},
  "geometry": {"coordinates":[7.536927,47.210541],"type":"Point"}
}