{
  "type": "Feature",
  "properties": {
    "iso:country":"CH",
    "sg:address":"Ruelle De Ancienne Poste 3",
    "sg:city":"Montreux",
    "sg:orig_category":"Detailhandel mit Waren verschiedener Art, Hauptrichtung Nahrungsmittel Fachdetailhandel mit Nahrungs",
    "sg:phone":"+41 21 963 63 72",
    "sg:postcode":"1820",
    "sg:province":"Vaud",
    "wof:name":"Ernest Calame Comestibles",
    "wof:placetype":"venue"
},
  "geometry": {"coordinates":[6.9105057716,46.4316940308],"type":"Point"}
}