{
  "type": "Feature",
  "properties": {
    "iso:country":"CH",
    "sg:address":"Milieu Du Village 9",
    "sg:city":"Undervelier",
    "sg:orig_category":"Darlehenskassen U Raiffeisenbanken",
    "sg:phone":"+41 32 426 57 33",
    "sg:postcode":"2863",
    "sg:province":"Jura",
    "wof:name":"Banque Raiffeisen",
    "wof:placetype":"venue"
},
  "geometry": {"coordinates":[7.223189,47.303986],"type":"Point"}
}