{
  "type": "Feature",
  "properties": {
    "iso:country":"CH",
    "sg:address":"Hauptstrasse 25",
    "sg:city":"Kreuzlingen",
    "sg:classifiers":[
        {
            "category":"Personal",
            "subcategory":"Piercing",
            "type":"Services"
        }
    ],
    "sg:phone":"+41 71 672 32 34",
    "sg:postcode":"8280",
    "sg:province":"Thurgau",
    "sg:tags":[
        "tattoo"
    ],
    "wof:name":"Piercing Kiko",
    "wof:placetype":"venue"
},
  "geometry": {"coordinates":[9.1740541458,47.65234375],"type":"Point"}
}