{
  "type": "Feature",
  "properties": {
    "iso:country":"CH",
    "sg:address":"Largo Mario Soldini 2",
    "sg:city":"Mendrisio",
    "sg:orig_category":"Detailhandel mit Parf\u00fcmerieartikeln U K\u00f6rperpflegemitteln Parf\u00fcmerien U sonstiger Detailhandel mit k",
    "sg:phone":"+41 22 817 82 00",
    "sg:postcode":"6850",
    "sg:province":"Ticino",
    "wof:name":"Artilux Sa",
    "wof:placetype":"venue"
},
  "geometry": {"coordinates":[6.1475400925,46.2030181885],"type":"Point"}
}