{
  "type": "Feature",
  "properties": {
    "iso:country":"CH",
    "sg:address":"Neugrasseli Gersauerweg",
    "sg:city":"Vitznau",
    "sg:orig_category":"Detailhandel mit Fleisch U Fleischwaren",
    "sg:phone":"+41 26 413 11 36",
    "sg:postcode":"6354",
    "sg:province":"Luzern",
    "wof:name":"Joseph K\u00fcnzli Boucherie De La Croix Blanche",
    "wof:placetype":"venue"
},
  "geometry": {"coordinates":[7.1649050713,46.7464141846],"type":"Point"}
}