{
  "type": "Feature",
  "properties": {
    "iso:country":"CH",
    "sg:address":"Hubelstrasse 48",
    "sg:city":"Obernau",
    "sg:orig_category":"Fahrschulen, Flugschulen",
    "sg:phone":"+41 41 320 98 27",
    "sg:postcode":"6012",
    "sg:province":"Luzern",
    "wof:name":"Thomas Schmid Autofahrschule",
    "wof:placetype":"venue"
},
  "geometry": {"coordinates":[8.2530097961,47.0310897827],"type":"Point"}
}