{
  "type": "Feature",
  "properties": {
    "iso:country":"CH",
    "sg:address":"Challstrasse 36",
    "sg:city":"Metzerlen",
    "sg:classifiers":[
        {
            "category":"Restaurant",
            "type":"Food & Drink"
        }
    ],
    "sg:phone":"+41 71 385 17 72",
    "sg:postcode":"4116",
    "sg:province":"Solothurn",
    "wof:name":"Restaurant Fennhof",
    "wof:placetype":"venue"
},
  "geometry": {"coordinates":[9.2557849884,47.4035835266],"type":"Point"}
}