{
  "type": "Feature",
  "properties": {
    "iso:country":"CH",
    "sg:address":"Gasterstrasse",
    "sg:city":"Uznach",
    "sg:orig_category":"Haltung von Rindern",
    "sg:phone":"+41 55 280 25 87",
    "sg:postcode":"8730",
    "sg:province":"St. Gallen",
    "wof:name":"Viehzuchtgenossenschaft Uznach",
    "wof:placetype":"venue"
},
  "geometry": {"coordinates":[8.9950342178,47.223991394],"type":"Point"}
}