{
  "type": "Feature",
  "properties": {
    "iso:country":"CH",
    "sg:address":"Walchestrasse 25",
    "sg:city":"Z\u00fcrich",
    "sg:orig_category":"Architektur U Ingenieurb\u00fcros",
    "sg:phone":"+41 79 401 50 38",
    "sg:postcode":"8006",
    "sg:province":"Z\u00fcrich",
    "wof:name":"Bauherrenberatung Hans-heiner Kern",
    "wof:placetype":"venue"
},
  "geometry": {"coordinates":[8.541474,47.381237],"type":"Point"}
}