{
  "type": "Feature",
  "properties": {
    "iso:country":"CH",
    "sg:address":"Vers-chez-l'ecrivain 47",
    "sg:city":"Grandval",
    "sg:orig_category":"Erschliessung von Grundst\u00fccken",
    "sg:postcode":"2745",
    "sg:province":"Bern",
    "wof:name":"St\u00e9.coop.d'habitation Magenta",
    "wof:placetype":"venue"
},
  "geometry": {"coordinates":[5.7830867767,46.7102851868],"type":"Point"}
}