{
  "type": "Feature",
  "properties": {
    "iso:country":"CH",
    "sg:address":"Witikonerstrasse 368",
    "sg:city":"Z\u00fcrich",
    "sg:orig_category":"Architekturb\u00fcros",
    "sg:phone":"+41 14228811",
    "sg:postcode":"8053",
    "sg:province":"Z\u00fcrich",
    "wof:name":"Georges Strickler Architekturb\u00fcro",
    "wof:placetype":"venue"
},
  "geometry": {"coordinates":[8.591602,47.358829],"type":"Point"}
}