{
  "type": "Feature",
  "properties": {
    "iso:country":"CH",
    "sg:address":"Orm\u00f4ne",
    "sg:city":"Savi\u00e8se",
    "sg:orig_category":"Interessenvertretungen U sonstige Vereinigungen",
    "sg:phone":"+41 91 967 12 65",
    "sg:postcode":"1965",
    "sg:province":"Valais",
    "wof:name":"Assoc.ticin.pallacanestro Atp",
    "wof:placetype":"venue"
},
  "geometry": {"coordinates":[8.937754631,46.0318832397],"type":"Point"}
}