{
  "type": "Feature",
  "properties": {
    "iso:country":"CH",
    "sg:address":"Hauptgasse 41",
    "sg:city":"Appenzell",
    "sg:orig_category":"Unclassifiable Establishments",
    "sg:phone":"+41 71 788 89 89",
    "sg:postcode":"9050",
    "sg:province":"Appenzell Innerhoden",
    "wof:name":"Orentrade Ag",
    "wof:placetype":"venue"
},
  "geometry": {"coordinates":[9.406867981,47.3313827515],"type":"Point"}
}