{
  "type": "Feature",
  "properties": {
    "iso:country":"CH",
    "sg:address":"Route De St-maurice",
    "sg:city":"Bex",
    "sg:orig_category":"S\u00e4ge, Hobel U Holzimpr\u00e4gnierwerke",
    "sg:postcode":"1880",
    "sg:province":"Vaud",
    "wof:name":"Morelli, Giuseppe",
    "wof:placetype":"venue"
},
  "geometry": {"coordinates":[7.0033259392,46.2454605103],"type":"Point"}
}