{
  "type": "Feature",
  "properties": {
    "iso:country":"CH",
    "sg:address":"Rue Du 23 Juin 79 2830 Courrendlin. Postfach",
    "sg:city":"Courrendlin",
    "sg:classifiers":[
        {
            "category":"Travel",
            "subcategory":"Hotels & Motels",
            "type":"Entertainment"
        }
    ],
    "sg:postcode":"2830",
    "sg:province":"Jura",
    "sg:tags":[
        "hotels",
        "mit",
        "restaurant"
    ],
    "wof:name":"Mobelair Sa",
    "wof:placetype":"venue"
},
  "geometry": {"coordinates":[7.3738870621,47.333820343],"type":"Point"}
}