{
  "type": "Feature",
  "properties": {
    "addr:full":"Freudenbergstrasse 120 8000 Z\u00fcrich. Postfach Z\u00fcrich Z\u00fcrich 8044",
    "addr:housenumber":"120",
    "addr:postcode":"8000 zuerich. postfach;8044",
    "addr:street":"Freudenbergstrasse",
    "iso:country":"CH",
    "sg:address":"Freudenbergstrasse 120 8000 Z\u00fcrich. Postfach",
    "sg:city":"Z\u00fcrich",
    "sg:orig_category":"Architektur U Ingenieurb\u00fcros",
    "sg:postcode":"8044",
    "sg:province":"Z\u00fcrich",
    "wof:name":"Gammert & Partner Ag",
    "wof:placetype":"venue"
},
  "geometry": {"coordinates":[8.554898,47.385746],"type":"Point"}
}