{
  "type": "Feature",
  "properties": {
    "addr:full":"Baarerstrasse 75 Zug Zug 6300",
    "addr:housenumber":"75",
    "addr:postcode":"6300",
    "addr:street":"Baarerstrasse;Zug",
    "iso:country":"CH",
    "sg:address":"Baarerstrasse 75",
    "sg:city":"Zug",
    "sg:orig_category":"Architektur U Ingenieurb\u00fcros",
    "sg:phone":"+41 41 711 30 91",
    "sg:postcode":"6300",
    "sg:province":"Zug",
    "wof:name":"Rinam Services Ag",
    "wof:placetype":"venue"
},
  "geometry": {"coordinates":[8.517616,47.176998],"type":"Point"}
}