{
  "type": "Feature",
  "properties": {
    "iso:country":"CH",
    "sg:address":"B\u00f6hlerstrasse 6",
    "sg:city":"Unterkulm",
    "sg:orig_category":"Herstellung von Schuhen",
    "sg:phone":"+41 56 443 12 19",
    "sg:postcode":"5726",
    "sg:province":"Aargau",
    "wof:name":"Aeschlimann & Cie. Aktiengesellschaft, Schuhfabrik, Veltheim",
    "wof:placetype":"venue"
},
  "geometry": {"coordinates":[8.142385,47.439018],"type":"Point"}
}