{
  "type": "Feature",
  "properties": {
    "iso:country":"CH",
    "sg:address":"5724",
    "sg:city":"D\u00fcrren\u00e4sch",
    "sg:orig_category":"Organisationen des Gesundheitswesen",
    "sg:phone":"+41 62 777 23 89",
    "sg:postcode":"5724",
    "sg:province":"Aargau",
    "wof:name":"Samariterverein",
    "wof:placetype":"venue"
},
  "geometry": {"coordinates":[8.1532297134,47.3168106079],"type":"Point"}
}