{
  "type": "Feature",
  "properties": {
    "iso:country":"CH",
    "sg:address":"Diepoldsauerstrasse 63",
    "sg:city":"Widnau",
    "sg:classifiers":[
        {
            "category":"Restaurant",
            "type":"Food & Drink"
        }
    ],
    "sg:phone":"+41 71 722 22 82",
    "sg:postcode":"9443",
    "sg:province":"St. Gallen",
    "wof:name":"Restaurant Gr\u00fcnau",
    "wof:placetype":"venue"
},
  "geometry": {"coordinates":[9.6419496536,47.3962440491],"type":"Point"}
}