{
  "type": "Feature",
  "properties": {
    "addr:full":"Turnhallenstrasse 1 Gelterkinden Basel-Landschaft 4460",
    "addr:housenumber":"1",
    "addr:postcode":"4460",
    "addr:street":"Turnhallenstrasse",
    "iso:country":"CH",
    "sg:address":"Turnhallenstrasse 1",
    "sg:city":"Gelterkinden",
    "sg:orig_category":"Alters U Pflegeheime Pensionskassen",
    "sg:phone":"+41 61 981 39 39",
    "sg:postcode":"4460",
    "sg:province":"Basel-Landschaft",
    "wof:name":"Altersheimstiftung Der B\u00fcrgergemeinde Gelterkinden",
    "wof:placetype":"venue"
},
  "geometry": {"coordinates":[7.853046,47.465172],"type":"Point"}
}