{
  "type": "Feature",
  "properties": {
    "iso:country":"CH",
    "sg:address":"Dorfstrasse 7 6467 Schattdorf. Postfach",
    "sg:city":"Schattdorf",
    "sg:orig_category":"Architektur U Ingenieurb\u00fcros Architekturb\u00fcros",
    "sg:phone":"+41 41 870 95 35",
    "sg:postcode":"6467",
    "sg:province":"Uri",
    "wof:name":"Arpag Ag",
    "wof:placetype":"venue"
},
  "geometry": {"coordinates":[8.654474,46.865795],"type":"Point"}
}