{
  "type": "Feature",
  "properties": {
    "iso:country":"CH",
    "sg:address":"Seestrasse 11b 8280 Kreuzlingen. Postfach 75",
    "sg:city":"Kreuzlingen",
    "sg:orig_category":"Betrieb von Sportanlagen",
    "sg:phone":"+41 71 672 30 05",
    "sg:postcode":"8280",
    "sg:province":"Thurgau",
    "wof:name":"Bodensee-arena Ag",
    "wof:placetype":"venue"
},
  "geometry": {"coordinates":[9.179272,47.654251],"type":"Point"}
}