{
  "type": "Feature",
  "properties": {
    "iso:country":"CH",
    "sg:address":"Fabrikstrasse 6 4513 Langendorf. Postfach",
    "sg:city":"Langendorf",
    "sg:orig_category":"Institutionen des Sozialwesens ohne Beherbergung",
    "sg:postcode":"4513",
    "sg:province":"Solothurn",
    "wof:name":"Soziale Dienste Weissenstein Gmbh",
    "wof:placetype":"venue"
},
  "geometry": {"coordinates":[7.5131158829,47.2183418274],"type":"Point"}
}