{
  "type": "Feature",
  "properties": {
    "iso:country":"CH",
    "sg:address":"Siewerdtstrasse 25",
    "sg:city":"Z\u00fcrich",
    "sg:orig_category":"Architekturb\u00fcros",
    "sg:phone":"+41 13158282",
    "sg:postcode":"8050",
    "sg:province":"Z\u00fcrich",
    "wof:name":"S & M Architekten Ag",
    "wof:placetype":"venue"
},
  "geometry": {"coordinates":[8.54991,47.41235],"type":"Point"}
}