{
  "type": "Feature",
  "properties": {
    "iso:country":"CH",
    "sg:address":"Oberer Ch\u00e4mletenweg 42e 6330 Cham. Postfach",
    "sg:city":"Cham",
    "sg:orig_category":"Unternehmensberatung",
    "sg:phone":"+41 41 781 14 81",
    "sg:postcode":"6330",
    "sg:province":"Zug",
    "wof:name":"Dr. Stefan Michel & Partner Gmbh",
    "wof:placetype":"venue"
},
  "geometry": {"coordinates":[8.4479427338,47.1693267822],"type":"Point"}
}