{
  "type": "Feature",
  "properties": {
    "iso:country":"CH",
    "sg:address":"Haltenstrasse 1",
    "sg:city":"Adelboden",
    "sg:orig_category":"Politische Parteien FDP",
    "sg:phone":"+41 33 673 13 31",
    "sg:postcode":"3715",
    "sg:province":"Bern",
    "wof:name":"Fdp Amt Frutigen",
    "wof:placetype":"venue"
},
  "geometry": {"coordinates":[7.5578961372,46.4931030273],"type":"Point"}
}