{
  "type": "Feature",
  "properties": {
    "iso:country":"CH",
    "sg:address":"Lenggenweg 13",
    "sg:city":"Wettswil",
    "sg:orig_category":"Vermietung von Automobilen",
    "sg:phone":"+41 17000016",
    "sg:postcode":"8907",
    "sg:province":"Z\u00fcrich",
    "wof:name":"St\u00fcssi Peter Mietfahrzeuge",
    "wof:placetype":"venue"
},
  "geometry": {"coordinates":[8.4682302475,47.3414497375],"type":"Point"}
}