{
  "type": "Feature",
  "properties": {
    "iso:country":"CH",
    "sg:address":"Piazza Collegiata 9",
    "sg:city":"Bellinzona",
    "sg:orig_category":"Detailhandel mit Lederwaren U Reiseartikeln Detailhandel mit Schuhen",
    "sg:phone":"+41 91 825 93 88",
    "sg:postcode":"6500",
    "sg:province":"Ticino",
    "wof:name":"Altalena Ag Divarese Calzature Pelletteria",
    "wof:placetype":"venue"
},
  "geometry": {"coordinates":[9.0231609344,46.1916923523],"type":"Point"}
}