{
  "type": "Feature",
  "properties": {
    "iso:country":"CH",
    "sg:address":"4414",
    "sg:city":"F\u00fcllinsdorf",
    "sg:orig_category":"Erschliessung von Grundst\u00fccken",
    "sg:phone":"+41 41 410 81 21",
    "sg:postcode":"4414",
    "sg:province":"Basel-Landschaft",
    "wof:name":"Gemeinschaftsstiftung Zur Erhaltung Und Schaffung Von Preisg\u00fcnstigem Wohnraum (gsw)",
    "wof:placetype":"venue"
},
  "geometry": {"coordinates":[8.3043117523,47.0523147583],"type":"Point"}
}