{
  "type": "Feature",
  "properties": {
    "iso:country":"CH",
    "sg:address":"Anetswil",
    "sg:city":"W\u00e4ngi",
    "sg:classifiers":[
        {
            "category":"Restaurant",
            "type":"Food & Drink"
        }
    ],
    "sg:phone":"+41 52 378 11 66",
    "sg:postcode":"9545",
    "sg:province":"Thurgau",
    "wof:name":"Restaurant Frohsinn",
    "wof:placetype":"venue"
},
  "geometry": {"coordinates":[8.9769153595,47.4996948242],"type":"Point"}
}