{
  "type": "Feature",
  "properties": {
    "iso:country":"CH",
    "sg:address":"6744",
    "sg:city":"Personico",
    "sg:orig_category":"Primarschulen",
    "sg:phone":"+41 91 867 17 07",
    "sg:postcode":"6744",
    "sg:province":"Ticino",
    "wof:name":"Scuola Elementare",
    "wof:placetype":"venue"
},
  "geometry": {"coordinates":[8.9183044434,46.3701972961],"type":"Point"}
}