{
  "type": "Feature",
  "properties": {
    "iso:country":"CH",
    "sg:address":"Bucher Strasse 21",
    "sg:city":"Affeltrangen",
    "sg:orig_category":"Detailhandel mit Herrenbekleidung",
    "sg:phone":"+41 71 917 21 45",
    "sg:postcode":"9556",
    "sg:province":"Thurgau",
    "wof:name":"Isolde H\u00f6ppli Herrenbekleidung",
    "wof:placetype":"venue"
},
  "geometry": {"coordinates":[9.040763855,47.5285797119],"type":"Point"}
}