{
  "type": "Feature",
  "properties": {
    "iso:country":"CH",
    "sg:address":"3942 Raron Case Postale 66",
    "sg:city":"Raron",
    "sg:orig_category":"Erdbewegungsarbeiten G\u00fcterbef\u00f6rderung im Strassenverkehr",
    "sg:phone":"+41 27 934 11 72",
    "sg:postcode":"3942",
    "sg:province":"Valais",
    "wof:name":"Ernst Bregy Ag Tiefbau-unternehmung",
    "wof:placetype":"venue"
},
  "geometry": {"coordinates":[7.8000950813,46.3097190857],"type":"Point"}
}