{
  "type": "Feature",
  "properties": {
    "addr:full":"Thanh\u00fcsli 3436 Zollbr\u00fcck. Postfach Zollbr\u00fcck Bern 3436",
    "addr:housenumber":"3436",
    "addr:postcode":"3436",
    "addr:street":"Zollbrueck. Postfach",
    "iso:country":"CH",
    "sg:address":"Thanh\u00fcsli 3436 Zollbr\u00fcck. Postfach",
    "sg:city":"Zollbr\u00fcck",
    "sg:classifiers":[
        {
            "category":"Manufacturing",
            "subcategory":"Metals",
            "type":"Manufacturing & Wholesale Goods"
        }
    ],
    "sg:phone":"+41 34 496 86 00",
    "sg:postcode":"3436",
    "sg:province":"Bern",
    "sg:tags":[
        "edelstahl",
        "u",
        "blank"
    ],
    "wof:name":"Burkhalter Daniel & Maja Gmbh",
    "wof:placetype":"venue"
},
  "geometry": {"coordinates":[7.740897,46.973988],"type":"Point"}
}