{
  "type": "Feature",
  "properties": {
    "iso:country":"CH",
    "sg:address":"S\u00fcdstrasse 17",
    "sg:city":"B\u00fclach",
    "sg:orig_category":"Sportvereine Velo Rad-& Motorfahrer-Bund SRB",
    "sg:phone":"+41 18606803",
    "sg:postcode":"8180",
    "sg:province":"Z\u00fcrich",
    "wof:name":"Radfahrer-verein B\u00fclach",
    "wof:placetype":"venue"
},
  "geometry": {"coordinates":[8.5409288406,47.514339447],"type":"Point"}
}