{
  "type": "Feature",
  "properties": {
    "iso:country":"CH",
    "sg:address":"Hauptstrasse 27",
    "sg:city":"Schwadernau",
    "sg:orig_category":"S\u00e4gewerke Zimmerei, Dachdeckerei, Bauspenglerei U Abdichtung",
    "sg:phone":"+41 32 373 19 91",
    "sg:postcode":"2556",
    "sg:province":"Bern",
    "wof:name":"Eigenmann + Jordi Holztechnik Gmbh",
    "wof:placetype":"venue"
},
  "geometry": {"coordinates":[7.3026080132,47.1279335022],"type":"Point"}
}