{
  "type": "Feature",
  "properties": {
    "iso:country":"CH",
    "sg:address":"Grienbachstrasse 36",
    "sg:city":"Zug",
    "sg:orig_category":"Wirtschaftspr\u00fcfung, Steuerberatung U Treuhand",
    "sg:phone":"+41 79 642 84 18",
    "sg:postcode":"6300",
    "sg:province":"Zug",
    "wof:name":"Gerschwiler A. Consulting",
    "wof:placetype":"venue"
},
  "geometry": {"coordinates":[8.5259389877,47.182144165],"type":"Point"}
}