{
  "type": "Feature",
  "properties": {
    "iso:country":"CH",
    "sg:address":"Rue Du Petit Pont 11a",
    "sg:city":"Conthey",
    "sg:orig_category":"Grosshandel mit sonstigen Gebrauchs U Verbrauchsg\u00fctern Vermittlung U Verwaltung von Immobilien",
    "sg:postcode":"1964",
    "sg:province":"Valais",
    "wof:name":"Gastro-rent Sa Location Mat.de Restauration",
    "wof:placetype":"venue"
},
  "geometry": {"coordinates":[7.3003811836,46.2140922546],"type":"Point"}
}