{
  "type": "Feature",
  "properties": {
    "iso:country":"CH",
    "sg:address":"Peter Ochs-strasse 33",
    "sg:city":"Basel",
    "sg:orig_category":"Werbung",
    "sg:phone":"+41 19842787",
    "sg:postcode":"4059",
    "sg:province":"Basel-Stadt",
    "wof:name":"H\u00e4mmerle Werbe Ag",
    "wof:placetype":"venue"
},
  "geometry": {"coordinates":[8.791973114,47.3602371216],"type":"Point"}
}