{
  "type": "Feature",
  "properties": {
    "iso:country":"CH",
    "sg:address":"6980",
    "sg:city":"Castelrotto",
    "sg:orig_category":"RESTAURANTS: TEA-ROOMS",
    "sg:postcode":"6980",
    "sg:province":"Ticino",
    "wof:name":"Gastroflam Ag",
    "wof:placetype":"venue"
},
  "geometry": {"coordinates":[8.7220458984,47.2735824585],"type":"Point"}
}