{
  "type": "Feature",
  "properties": {
    "iso:country":"CH",
    "sg:address":"Zelgliweg 12",
    "sg:city":"Itingen",
    "sg:orig_category":"Herstellung von Elektrizit\u00e4tsverteilungs U schalteinrichtungen",
    "sg:phone":"+41 32 757 23 23",
    "sg:postcode":"4452",
    "sg:province":"Basel-Landschaft",
    "wof:name":"Sanfi Sa",
    "wof:placetype":"venue"
},
  "geometry": {"coordinates":[7.0333590508,47.0478248596],"type":"Point"}
}