{
  "type": "Feature",
  "properties": {
    "iso:country":"CH",
    "sg:address":"Parkring 57",
    "sg:city":"Z\u00fcrich",
    "sg:orig_category":"Grosshandel mit Textilien",
    "sg:postcode":"8027",
    "sg:province":"Z\u00fcrich",
    "wof:name":"Central Power Ag",
    "wof:placetype":"venue"
},
  "geometry": {"coordinates":[8.464345932,47.3649597168],"type":"Point"}
}