{
  "type": "Feature",
  "properties": {
    "iso:country":"CH",
    "sg:address":"Bahnhofstrasse 19",
    "sg:city":"Rheinfelden",
    "sg:classifiers":[
        {
            "category":"Education",
            "subcategory":"Library",
            "type":"Public Place"
        }
    ],
    "sg:phone":"+41 61 281 30 20",
    "sg:postcode":"4310",
    "sg:province":"Aargau",
    "sg:tags":[
        "u",
        "bibliotheken",
        "archive"
    ],
    "wof:name":"Klinik Sch\u00fctzen Bibliothek",
    "wof:placetype":"venue"
},
  "geometry": {"coordinates":[7.792402,47.553017],"type":"Point"}
}