{
  "type": "Feature",
  "properties": {
    "iso:country":"CH",
    "sg:address":"Hauptstrasse 22",
    "sg:city":"Waldenburg",
    "sg:orig_category":"Unclassifiable Establishments",
    "sg:postcode":"4437",
    "sg:province":"Basel-Landschaft",
    "wof:name":"Waldenburger Anzeiger & Oberbaselbieter Zeitung Red.",
    "wof:placetype":"venue"
},
  "geometry": {"coordinates":[7.7489438057,47.3850593567],"type":"Point"}
}