{
  "type": "Feature",
  "properties": {
    "iso:country":"CH",
    "sg:address":"Via Stefano Franscini 20",
    "sg:city":"Mendrisio",
    "sg:orig_category":"W\u00e4scherei U chemische Reinigung",
    "sg:phone":"+41 91 646 08 92",
    "sg:postcode":"6850",
    "sg:province":"Ticino",
    "wof:name":"Jefferson I. Sa",
    "wof:placetype":"venue"
},
  "geometry": {"coordinates":[8.9808959961,45.8703727722],"type":"Point"}
}