{
  "type": "Feature",
  "properties": {
    "addr:full":"Quai Du Seujet 14 Gen\u00e8ve Gen\u00e8ve 1201",
    "addr:housenumber":"14",
    "addr:postcode":"1201",
    "addr:street":"Quai Du Seujet",
    "iso:country":"CH",
    "sg:address":"Quai Du Seujet 14",
    "sg:city":"Gen\u00e8ve",
    "sg:classifiers":[
        {
            "category":"Banks & Credit Unions",
            "subcategory":"Bank",
            "type":"Services"
        }
    ],
    "sg:phone":"+41 22 906 08 08",
    "sg:postcode":"1201",
    "sg:province":"Gen\u00e8ve",
    "wof:name":"Amas Bank (suisse)ltd",
    "wof:placetype":"venue"
},
  "geometry": {"coordinates":[6.136371,46.205624],"type":"Point"}
}