{
  "type": "Feature",
  "properties": {
    "iso:country":"CH",
    "sg:address":"Kohlg\u00e4ssli 1",
    "sg:city":"W\u00fcnnewil",
    "sg:orig_category":"Erdbewegungsarbeiten",
    "sg:phone":"+41 26 496 45 44",
    "sg:postcode":"3184",
    "sg:province":"Fribourg",
    "wof:name":"Josef Spicher Baggerbetrieb",
    "wof:placetype":"venue"
},
  "geometry": {"coordinates":[7.2768468857,46.876373291],"type":"Point"}
}