{
  "type": "Feature",
  "properties": {
    "iso:country":"CH",
    "sg:address":"Grubenstrasse 2 8045 Z\u00fcrich. Postfach",
    "sg:city":"Z\u00fcrich",
    "sg:orig_category":"Zimmerei, Ingenieurholzbau",
    "sg:phone":"+41 71 277 11 57",
    "sg:postcode":"8045",
    "sg:province":"Z\u00fcrich",
    "wof:name":"Sutter Ag Holzbau St. Gallen Zimmerei, Schreinerei- U. Treppenbau-unternehmen Usw",
    "wof:placetype":"venue"
},
  "geometry": {"coordinates":[9.3445711136,47.4132614136],"type":"Point"}
}