{
  "type": "Feature",
  "properties": {
    "iso:country":"CH",
    "sg:address":"Buchserstrasse 9 8108 D\u00e4llikon. Postfach",
    "sg:city":"D\u00e4llikon",
    "sg:orig_category":"Handel mit Automobilen",
    "sg:phone":"+41 18450345",
    "sg:postcode":"8108",
    "sg:province":"Z\u00fcrich",
    "wof:name":"Car - Fit Marthaler Neu- U. Gebrauchtwagen; Handel",
    "wof:placetype":"venue"
},
  "geometry": {"coordinates":[8.438908577,47.4407043457],"type":"Point"}
}