{
  "type": "Feature",
  "properties": {
    "iso:country":"CH",
    "sg:address":"Bruggwaldstrasse 1 9303 Wittenbach. Postfach",
    "sg:city":"Wittenbach",
    "sg:orig_category":"Reinigungsgewerbe",
    "sg:postcode":"9303",
    "wof:name":"Tip-top Reinigung Brahimi",
    "wof:placetype":"venue"
},
  "geometry": {"coordinates":[9.3960475922,47.4478645325],"type":"Point"}
}