{
  "type": "Feature",
  "properties": {
    "iso:country":"CH",
    "sg:address":"Holbergstrasse 1",
    "sg:city":"Kloten",
    "sg:orig_category":"RESTAURANTS: TEA-ROOMS",
    "sg:phone":"+41 27 957 28 45",
    "sg:postcode":"8302",
    "sg:province":"Z\u00fcrich",
    "wof:name":"Hotel-restaurant Adler, Zurbriggen Hermann",
    "wof:placetype":"venue"
},
  "geometry": {"coordinates":[7.9426851273,46.1098899841],"type":"Point"}
}