{
  "type": "Feature",
  "properties": {
    "iso:country":"CH",
    "sg:address":"S\u00e4ntisstrasse 71",
    "sg:city":"Schaffhausen",
    "sg:orig_category":"Sportvereine Ballsport Handball",
    "sg:phone":"+41 52 625 36 40",
    "sg:postcode":"8200",
    "sg:province":"Schaffhausen",
    "wof:name":"Tv F\u00e4senstaub",
    "wof:placetype":"venue"
},
  "geometry": {"coordinates":[8.6463832855,47.6968078613],"type":"Point"}
}