{
  "type": "Feature",
  "properties": {
    "iso:country":"CH",
    "sg:address":"Amstutzstrasse 15 6010 Kriens. Postfach",
    "sg:city":"Emmen",
    "sg:orig_category":"Hochschulen U h\u00f6here Ausbildung Unternehmensberatung",
    "sg:phone":"+41 41 310 77 09",
    "sg:postcode":"6032",
    "sg:province":"Luzern",
    "wof:name":"Universaly W\u00fcest & Herzog Institut F\u00fcr Neue M\u00f6glichkeiten Im Bereich Pers\u00f6nlichkeitsbilding Usw",
    "wof:placetype":"venue"
},
  "geometry": {"coordinates":[8.2911977768,47.0389633179],"type":"Point"}
}