{
  "type": "Feature",
  "properties": {
    "iso:country":"CH",
    "sg:address":"Landstrasse 44",
    "sg:city":"Untersiggenthal",
    "sg:orig_category":"Non-Classified Establishments",
    "sg:postcode":"5417",
    "sg:province":"Aargau",
    "wof:name":"Tanviva Gmbh",
    "wof:placetype":"venue"
},
  "geometry": {"coordinates":[8.2601890564,47.4984931946],"type":"Point"}
}