{
  "type": "Feature",
  "properties": {
    "iso:country":"CH",
    "sg:address":"Seestrasse 69",
    "sg:city":"St\u00e4fa",
    "sg:orig_category":"Detailhandel mit Waren verschiedener Art, Hauptrichtung Nahrungsmittel Fachdetailhandel mit Nahrungs",
    "sg:phone":"+41 17963938",
    "sg:postcode":"8712",
    "sg:province":"Z\u00fcrich",
    "wof:name":"Delizie Ag",
    "wof:placetype":"venue"
},
  "geometry": {"coordinates":[8.7204380035,47.2390213013],"type":"Point"}
}