{
  "type": "Feature",
  "properties": {
    "iso:country":"CH",
    "sg:address":"Thorenbergstrasse 25",
    "sg:city":"Littau",
    "sg:orig_category":"Instandhaltung U Reparatur von Automobilen",
    "sg:phone":"+41 79 401 78 88",
    "sg:postcode":"6014",
    "sg:province":"Luzern",
    "wof:name":"Ads, Michel Boesch",
    "wof:placetype":"venue"
},
  "geometry": {"coordinates":[6.6390252113,46.5873908997],"type":"Point"}
}