{
  "type": "Feature",
  "properties": {
    "iso:country":"CH",
    "sg:address":"Monte S.salvatore",
    "sg:city":"Carona",
    "sg:classifiers":[
        {
            "category":"Restaurant",
            "type":"Food & Drink"
        }
    ],
    "sg:phone":"+41 91 994 77 56",
    "sg:postcode":"6914",
    "sg:province":"Ticino",
    "wof:name":"Ristorante Vetta",
    "wof:placetype":"venue"
},
  "geometry": {"coordinates":[8.9401350021,45.9677848816],"type":"Point"}
}