{
  "type": "Feature",
  "properties": {
    "addr:full":"Rue Des Jordils 33 1400 Yverdon-les-bains Case Postale 72 Yverdon Vaud 1401",
    "addr:housenumber":"33",
    "addr:postcode":"1400;72;1401",
    "addr:street":"Rue Des Jordils;Postale",
    "iso:country":"CH",
    "sg:address":"Rue Des Jordils 33 1400 Yverdon-les-bains Case Postale 72",
    "sg:city":"Yverdon",
    "sg:orig_category":"Architektur U Ingenieurb\u00fcros Gartenbau",
    "sg:phone":"+41 24 423 04 30",
    "sg:postcode":"1401",
    "sg:province":"Vaud",
    "wof:name":"Groupe Y Architecture Et Urbanisme Sa",
    "wof:placetype":"venue"
},
  "geometry": {"coordinates":[6.63953,46.776287],"type":"Point"}
}