{
  "type": "Feature",
  "properties": {
    "iso:country":"CH",
    "sg:address":"Klybeckstrasse 44 4057 Basel. Postfach",
    "sg:city":"Basel",
    "sg:orig_category":"Fachdetailhandel in Verkaufsr\u00e4umen Grosshandel mit Nahrungsmitteln, Getr\u00e4nken U Tabakwaren",
    "sg:phone":"+41 61 681 02 44",
    "sg:postcode":"4057",
    "sg:province":"Basel-Stadt",
    "wof:name":"Akcakoca Nurcan Import Export Waren, Bes. Geschenkartikel, Lebensmittel, Textilien Usw.; Import, Export",
    "wof:placetype":"venue"
},
  "geometry": {"coordinates":[7.5915799141,47.5648994446],"type":"Point"}
}