{
  "type": "Feature",
  "properties": {
    "iso:country":"CH",
    "sg:address":"Z\u00fcrcherstrasse 221",
    "sg:city":"Frauenfeld",
    "sg:orig_category":"Landesverteidigung",
    "sg:phone":"+41 41 619 55 21",
    "sg:postcode":"8500",
    "sg:province":"Thurgau",
    "wof:name":"Kriegskommissariat Des Kantons Nidwalden",
    "wof:placetype":"venue"
},
  "geometry": {"coordinates":[8.3864660263,46.9583129883],"type":"Point"}
}