{
  "type": "Feature",
  "properties": {
    "iso:country":"CH",
    "sg:address":"L\u00f6wenplatz 3a",
    "sg:city":"Jegenstorf",
    "sg:orig_category":"Finanzierungsinstitutionen Immobilienwesen",
    "sg:phone":"+41 31 762 01 25",
    "sg:postcode":"3303",
    "sg:province":"Bern",
    "wof:name":"Arifin Ag",
    "wof:placetype":"venue"
},
  "geometry": {"coordinates":[7.5064730644,47.0486755371],"type":"Point"}
}