{
  "type": "Feature",
  "properties": {
    "iso:country":"CH",
    "sg:address":"Dorfstrasse 11",
    "sg:city":"W\u00e4ngi",
    "sg:orig_category":"Verwaltung der Rechtspflege, Gerichte",
    "sg:phone":"+41 52 378 15 92",
    "sg:postcode":"9545",
    "sg:province":"Thurgau",
    "wof:name":"Grundbuchamt & Notariat",
    "wof:placetype":"venue"
},
  "geometry": {"coordinates":[8.9536008835,47.4976882935],"type":"Point"}
}