{
  "type": "Feature",
  "properties": {
    "iso:country":"CH",
    "sg:address":"Route De C\u00e9ligny 45",
    "sg:city":"C\u00e9ligny",
    "sg:orig_category":"G\u00fcterbef\u00f6rderung im Strassenverkehr",
    "sg:phone":"+41 22 776 16 46",
    "sg:postcode":"1298",
    "sg:province":"Gen\u00e8ve",
    "wof:name":"Guy Bolay Transports",
    "wof:placetype":"venue"
},
  "geometry": {"coordinates":[6.1989221573,46.3487701416],"type":"Point"}
}