{
  "type": "Feature",
  "properties": {
    "iso:country":"CH",
    "sg:address":"Hofstettenstrasse 35 3600 Thun. Postfach",
    "sg:city":"Thun",
    "sg:orig_category":"Sonstige Kultur U Unterhaltungseinrichtungen",
    "sg:postcode":"3600",
    "sg:province":"Bern",
    "wof:name":"Casino Kursaal Thun Ag",
    "wof:placetype":"venue"
},
  "geometry": {"coordinates":[7.6363229752,46.7546310425],"type":"Point"}
}