{
  "type": "Feature",
  "properties": {
    "iso:country":"CH",
    "sg:address":"Albisstrasse 11a",
    "sg:city":"Adliswil",
    "sg:orig_category":"Detailhandel mit Milcherzeugnissen U Eiern",
    "sg:phone":"+41 17105885",
    "sg:postcode":"8134",
    "sg:province":"Z\u00fcrich",
    "wof:name":"Ch\u00e4s-ch\u00e4ller",
    "wof:placetype":"venue"
},
  "geometry": {"coordinates":[8.5257167816,47.3112068176],"type":"Point"}
}