{
  "type": "Feature",
  "properties": {
    "iso:country":"CH",
    "sg:address":"9126",
    "sg:city":"Necker",
    "sg:orig_category":"Vorschulen, Kinderg\u00e4rten",
    "sg:phone":"+41 71 374 22 64",
    "sg:postcode":"9126",
    "sg:province":"St. Gallen",
    "wof:name":"Kindergarten",
    "wof:placetype":"venue"
},
  "geometry": {"coordinates":[9.1291904449,47.3433113098],"type":"Point"}
}