{
  "type": "Feature",
  "properties": {
    "iso:country":"CH",
    "sg:address":"Buebenaustrasse 16 8954 Geroldswil. Postfach",
    "sg:city":"Geroldswil",
    "sg:orig_category":"Advokaturb\u00fcros",
    "sg:phone":"+41 41 420 18 26",
    "sg:postcode":"8954",
    "sg:province":"Z\u00fcrich",
    "wof:name":"Dr.markus Bachmann Advokaturb\u00fcro",
    "wof:placetype":"venue"
},
  "geometry": {"coordinates":[8.320151,47.063072],"type":"Point"}
}