{
  "type": "Feature",
  "properties": {
    "iso:country":"CH",
    "sg:address":"Postmatte 1",
    "sg:city":"Schenkon",
    "sg:orig_category":"Grosshandel mit sonstigen Gebrauchs U Verbrauchsg\u00fctern Herstellung von sonstigen elektrischen Ausr\u00fcs",
    "sg:phone":"+41 41 922 03 14",
    "sg:postcode":"6214",
    "sg:province":"Luzern",
    "wof:name":"Key Soft Service Christen Peter & Schmid Roland",
    "wof:placetype":"venue"
},
  "geometry": {"coordinates":[8.1327133179,47.177646637],"type":"Point"}
}