{
  "type": "Feature",
  "properties": {
    "addr:full":"Lischenweg 29 Biel/bienne Bern 2503",
    "addr:housenumber":"29",
    "addr:postcode":"2503",
    "addr:street":"Lischenweg",
    "iso:country":"CH",
    "sg:address":"Lischenweg 29",
    "sg:city":"Biel/bienne",
    "sg:classifiers":[
        {
            "category":"Social Services",
            "subcategory":"Retirement Home",
            "type":"Services"
        }
    ],
    "sg:phone":"+41 32 365 53 11",
    "sg:postcode":"2503",
    "sg:province":"Bern",
    "sg:tags":[
        "pflegeheime",
        "u",
        "alters"
    ],
    "wof:name":"Cristal Alters-& Pflegeheim",
    "wof:placetype":"venue"
},
  "geometry": {"coordinates":[7.257515,47.125801],"type":"Point"}
}