{
  "type": "Feature",
  "properties": {
    "iso:country":"CH",
    "sg:address":"Hofenstrasse 7",
    "sg:city":"M\u00e4nnedorf",
    "sg:orig_category":"Verwaltung der Rechtspflege, Gerichte",
    "sg:phone":"+41 18503600",
    "sg:postcode":"8708",
    "sg:province":"Z\u00fcrich",
    "wof:name":"Notariat Grundbuch-& Konkursamt Niederglatt",
    "wof:placetype":"venue"
},
  "geometry": {"coordinates":[8.5003890991,47.4926300049],"type":"Point"}
}