{
  "type": "Feature",
  "properties": {
    "iso:country":"CH",
    "sg:address":"Rue De La Place 24",
    "sg:city":"Chamoson",
    "sg:orig_category":"Detailhandel mit Fleisch U Fleischwaren",
    "sg:phone":"+41 27 306 28 81",
    "sg:postcode":"1955",
    "sg:province":"Valais",
    "wof:name":"Jean-daniel Biollaz Boucherie & Charcuterie",
    "wof:placetype":"venue"
},
  "geometry": {"coordinates":[7.2226867676,46.1997528076],"type":"Point"}
}