{
  "type": "Feature",
  "properties": {
    "addr:full":"Unterdorfstrasse 24 Stettfurt Thurgau 9507",
    "addr:housenumber":"24",
    "addr:postcode":"9507",
    "addr:street":"Unterdorfstrasse",
    "iso:country":"CH",
    "sg:address":"Unterdorfstrasse 24",
    "sg:city":"Stettfurt",
    "sg:orig_category":"Bauspenglerei Zimmerei, Dachdeckerei, Bauspenglerei U Abdichtung",
    "sg:phone":"+41 19841246",
    "sg:postcode":"9507",
    "sg:province":"Thurgau",
    "wof:name":"Kaufmann Spenglerei + Sanit\u00e4r Ag",
    "wof:placetype":"venue"
},
  "geometry": {"coordinates":[8.690055,47.300556],"type":"Point"}
}