{
  "type": "Feature",
  "properties": {
    "iso:country":"CH",
    "sg:address":"M\u00fchlemattstrasse",
    "sg:city":"Buochs",
    "sg:orig_category":"Non-Classified Establishments",
    "sg:postcode":"6374",
    "sg:province":"Nidwalden",
    "wof:name":"Kebal Ag",
    "wof:placetype":"venue"
},
  "geometry": {"coordinates":[8.4177904129,46.9737167358],"type":"Point"}
}