{
  "type": "Feature",
  "properties": {
    "iso:country":"CH",
    "sg:address":"Meiliweg 23",
    "sg:city":"Z\u00fcrich",
    "sg:orig_category":"Softwareentwicklung U beratung",
    "sg:phone":"+41 14630806",
    "sg:postcode":"8055",
    "sg:province":"Z\u00fcrich",
    "wof:name":"Bausch & Co Gmbh",
    "wof:placetype":"venue"
},
  "geometry": {"coordinates":[8.5158433914,47.366809845],"type":"Point"}
}