{
  "type": "Feature",
  "properties": {
    "iso:country":"CH",
    "sg:address":"B\u00e4chigenstrasse 17",
    "sg:city":"Arnegg",
    "sg:orig_category":"Herstellung von sonstigen Metallwaren Stahl U Leichtmetallbau",
    "sg:phone":"+41 71 385 23 85",
    "sg:postcode":"9212",
    "sg:province":"St. Gallen",
    "wof:name":"Brunschwiler J. Ag",
    "wof:placetype":"venue"
},
  "geometry": {"coordinates":[9.2533035278,47.443195343],"type":"Point"}
}