{
  "type": "Feature",
  "properties": {
    "addr:full":"Ettingerstrasse 17 Hofstetten Solothurn 4114",
    "addr:housenumber":"17",
    "addr:postcode":"4114",
    "addr:street":"Ettingerstrasse",
    "iso:country":"CH",
    "sg:address":"Ettingerstrasse 17",
    "sg:city":"Hofstetten",
    "sg:classifiers":[
        {
            "category":"Banks & Credit Unions",
            "subcategory":"Bank",
            "type":"Services"
        }
    ],
    "sg:phone":"+41 41 910 13 87",
    "sg:postcode":"4114",
    "sg:province":"Solothurn",
    "wof:name":"Raiffeisenbank Hohenrain",
    "wof:placetype":"venue"
},
  "geometry": {"coordinates":[8.304375,47.049545],"type":"Point"}
}