{
  "type": "Feature",
  "properties": {
    "iso:country":"CH",
    "sg:address":"Huebstrasse 4",
    "sg:city":"Ipsach",
    "sg:orig_category":"Sportvereine Turnen",
    "sg:phone":"+41 32 331 87 59",
    "sg:postcode":"2563",
    "sg:province":"Bern",
    "wof:name":"M\u00e4nnerturnverein Stv Ipsach",
    "wof:placetype":"venue"
},
  "geometry": {"coordinates":[7.2426781654,47.1187705994],"type":"Point"}
}