{
  "type": "Feature",
  "properties": {
    "iso:country":"CH",
    "sg:address":"Route De Moutier 1",
    "sg:city":"Del\u00e9mont",
    "sg:orig_category":"Herstellung von Oberbekleidung",
    "sg:phone":"+41 32 422 46 78",
    "sg:postcode":"2800",
    "sg:province":"Jura",
    "wof:name":"Jeff Confection S\u00e0rl",
    "wof:placetype":"venue"
},
  "geometry": {"coordinates":[7.3503251076,47.3628387451],"type":"Point"}
}