{
  "type": "Feature",
  "properties": {
    "iso:country":"CH",
    "sg:address":"Via Cantonale 34a",
    "sg:city":"Manno",
    "sg:orig_category":"Rechtsberatung Wirtschaftspr\u00fcfung, Steuerberatung U Treuhand",
    "sg:phone":"+41 91 605 44 44",
    "sg:postcode":"6928",
    "sg:province":"Ticino",
    "wof:name":"E-legal.ch Stock Corporation Ltd.",
    "wof:placetype":"venue"
},
  "geometry": {"coordinates":[8.9234104156,46.0330581665],"type":"Point"}
}