{
  "type": "Feature",
  "properties": {
    "iso:country":"CH",
    "sg:address":"Meriedweg 11",
    "sg:city":"Niederwangen",
    "sg:classifiers":[
        {
            "category":"Professional",
            "subcategory":"Management & Consulting",
            "type":"Services"
        }
    ],
    "sg:phone":"+41 31 985 25 10",
    "sg:postcode":"3172",
    "sg:province":"Bern",
    "sg:tags":[
        "consultancy"
    ],
    "wof:name":"Netmodule Ag",
    "wof:placetype":"venue"
},
  "geometry": {"coordinates":[7.3731942177,46.9208259583],"type":"Point"}
}