{
  "type": "Feature",
  "properties": {
    "iso:country":"CH",
    "sg:address":"Hauptstrasse 30",
    "sg:city":"Pfeffingen",
    "sg:classifiers":[
        {
            "category":"Restaurant",
            "type":"Food & Drink"
        }
    ],
    "sg:phone":"+41 62 291 17 06",
    "sg:postcode":"4148",
    "sg:province":"Basel-Landschaft",
    "wof:name":"Restaurant Rebstock",
    "wof:placetype":"venue"
},
  "geometry": {"coordinates":[7.9785652161,47.355140686],"type":"Point"}
}