{
  "type": "Feature",
  "properties": {
    "addr:full":"Flughafenstrasse Grenchen Solothurn 2540",
    "addr:postcode":"2540",
    "addr:street":"Flughafenstrasse",
    "iso:country":"CH",
    "sg:address":"Flughafenstrasse",
    "sg:city":"Grenchen",
    "sg:classifiers":[
        {
            "category":"School Buses",
            "type":"Transportation"
        }
    ],
    "sg:phone":"+41 32 652 21 49",
    "sg:postcode":"2540",
    "sg:province":"Solothurn",
    "sg:tags":[
        "aircraft"
    ],
    "wof:name":"Aerotec Ltd.",
    "wof:placetype":"venue"
},
  "geometry": {"coordinates":[7.40465,47.189877],"type":"Point"}
}