{
  "type": "Feature",
  "properties": {
    "iso:country":"CH",
    "sg:address":"6243",
    "sg:city":"Egolzwil",
    "sg:orig_category":"Vereine Musik/Blasmusik",
    "sg:postcode":"6243",
    "sg:province":"Luzern",
    "wof:name":"Musikgesellschaft",
    "wof:placetype":"venue"
},
  "geometry": {"coordinates":[7.9983000755,47.1843299866],"type":"Point"}
}