{
  "type": "Feature",
  "properties": {
    "iso:country":"CH",
    "sg:address":"Bahnhofstrasse 9",
    "sg:city":"Herisau",
    "sg:orig_category":"Detailhandel mit Lederwaren U Reiseartikeln Detailhandel mit Schuhen U Lederwaren",
    "sg:postcode":"9100",
    "sg:province":"Appenzell Ausserrhoden",
    "wof:name":"Roland B\u00fcsser",
    "wof:placetype":"venue"
},
  "geometry": {"coordinates":[9.2781591415,47.3868103027],"type":"Point"}
}