{
  "type": "Feature",
  "properties": {
    "iso:country":"CH",
    "sg:address":"Mont-blanc Avenue Du 2",
    "sg:city":"Gland",
    "sg:orig_category":"Vermietung U Verpachtung von eigenen Immobilien",
    "sg:phone":"+41 22 364 60 40",
    "sg:postcode":"1196",
    "sg:province":"Vaud",
    "wof:name":"Mauron Georges, Cabinet Immobilier",
    "wof:placetype":"venue"
},
  "geometry": {"coordinates":[6.2614498138,46.4224014282],"type":"Point"}
}