{
  "type": "Feature",
  "properties": {
    "iso:country":"CH",
    "sg:address":"Feldstrasse 6",
    "sg:city":"Horn",
    "sg:orig_category":"Allgemeiner Hoch U Tiefbau",
    "sg:phone":"+41 14555040",
    "sg:postcode":"9326",
    "sg:province":"Thurgau",
    "wof:name":"Porr Suisse Ag Bauunternehmung",
    "wof:placetype":"venue"
},
  "geometry": {"coordinates":[8.627421,46.88306],"type":"Point"}
}