{
  "type": "Feature",
  "properties": {
    "iso:country":"CH",
    "sg:address":"Haus Sprecher",
    "sg:city":"Arosa",
    "sg:orig_category":"Sportvereine Alpinismus",
    "sg:phone":"+41 55 240 59 03",
    "sg:postcode":"7050",
    "sg:province":"Graubunden",
    "wof:name":"Sac Sektion Bachtel",
    "wof:placetype":"venue"
},
  "geometry": {"coordinates":[8.8541440964,47.2528800964],"type":"Point"}
}