{
  "type": "Feature",
  "properties": {
    "iso:country":"CH",
    "sg:address":"6670",
    "sg:city":"Avegno",
    "sg:orig_category":"Vereine Geselligkeit",
    "sg:phone":"+41 71 455 17 66",
    "sg:postcode":"6670",
    "sg:province":"Ticino",
    "wof:name":"Anglo-swiss Circle",
    "wof:placetype":"venue"
},
  "geometry": {"coordinates":[9.391793251,47.4875526428],"type":"Point"}
}