{
  "type": "Feature",
  "properties": {
    "iso:country":"CH",
    "sg:address":"Klusstrasse 16",
    "sg:city":"St.gallen",
    "sg:orig_category":"K\u00fcnstlerische U schriftstellerische T\u00e4tigkeiten U Darbietungen",
    "sg:phone":"+41 71 222 55 50",
    "sg:postcode":"9000",
    "sg:province":"St. Gallen",
    "wof:name":"Gersbach Ren\u00e9",
    "wof:placetype":"venue"
},
  "geometry": {"coordinates":[9.3773183823,47.4188461304],"type":"Point"}
}