{
  "type": "Feature",
  "properties": {
    "addr:full":"Obergasse 5 Zumikon Z\u00fcrich 8126",
    "addr:housenumber":"5",
    "addr:postcode":"8126",
    "addr:street":"Obergasse",
    "iso:country":"CH",
    "sg:address":"Obergasse 5",
    "sg:city":"Zumikon",
    "sg:orig_category":"Architekturb\u00fcros",
    "sg:phone":"+41 19182581",
    "sg:postcode":"8126",
    "sg:province":"Z\u00fcrich",
    "wof:name":"R\u00fcegger Architekten",
    "wof:placetype":"venue"
},
  "geometry": {"coordinates":[8.624814,47.32526],"type":"Point"}
}