{
  "type": "Feature",
  "properties": {
    "iso:country":"CH",
    "sg:address":"Burgerstrasse 37b 3600 Thun. Postfach 35",
    "sg:city":"Thun",
    "sg:orig_category":"Herstellung von elektrischen Ausr\u00fcstungen f\u00fcr Motoren U Fahrzeuge Mechanische Werkst\u00e4tten",
    "sg:phone":"+41 33 222 16 42",
    "sg:postcode":"3607",
    "sg:province":"Bern",
    "wof:name":"Marineservice Von Gunten Ag",
    "wof:placetype":"venue"
},
  "geometry": {"coordinates":[7.6122112274,46.7465782166],"type":"Point"}
}