{
  "type": "Feature",
  "properties": {
    "iso:country":"CH",
    "sg:address":"Buholz",
    "sg:city":"Ruswil",
    "sg:orig_category":"Fussreflexzonenmassage",
    "sg:phone":"+41 71 755 27 70",
    "sg:postcode":"6017",
    "sg:province":"Luzern",
    "wof:name":"Rosa R\u00f6thlisberger Fussreflexzonen-massage",
    "wof:placetype":"venue"
},
  "geometry": {"coordinates":[9.5473680496,47.3723106384],"type":"Point"}
}