{
  "type": "Feature",
  "properties": {
    "iso:country":"CH",
    "sg:address":"Ringstrasse 20",
    "sg:city":"Oekingen",
    "sg:orig_category":"Sportvereine Unihockey",
    "sg:postcode":"4566",
    "sg:province":"Solothurn",
    "wof:name":"Uhc Oekingen",
    "wof:placetype":"venue"
},
  "geometry": {"coordinates":[7.6018538475,47.1795043945],"type":"Point"}
}