{
  "type": "Feature",
  "properties": {
    "iso:country":"CH",
    "sg:address":"Z\u00fcrichstrasse 30",
    "sg:city":"D\u00fcbendorf",
    "sg:orig_category":"Non-Classified Establishments",
    "sg:postcode":"8600",
    "sg:province":"Z\u00fcrich",
    "wof:name":"Andr\u00e9 Wittwer Teppich & Bodenbel\u00e4ge Gmbh",
    "wof:placetype":"venue"
},
  "geometry": {"coordinates":[8.6137561798,47.3968391418],"type":"Point"}
}