{
  "type": "Feature",
  "properties": {
    "addr:full":"Weyerstrasse 7 Wabern Bern 3084",
    "addr:housenumber":"7",
    "addr:postcode":"3084",
    "addr:street":"Weyerstrasse",
    "iso:country":"CH",
    "sg:address":"Weyerstrasse 7",
    "sg:city":"Wabern",
    "sg:orig_category":"Blumen U Zierpflanzenbau",
    "sg:phone":"+41 31 961 23 92",
    "sg:postcode":"3084",
    "sg:province":"Bern",
    "wof:name":"Rolf Bodmer Gartenbau & Friedhofg\u00e4rtnerei",
    "wof:placetype":"venue"
},
  "geometry": {"coordinates":[7.455476,46.927601],"type":"Point"}
}