{
  "type": "Feature",
  "properties": {
    "iso:country":"CH",
    "sg:address":"Bruggm\u00fchlestrasse 29",
    "sg:city":"Goldach",
    "sg:orig_category":"Wirtschafts- and Arbeitgeberverb\u00e4nde",
    "sg:phone":"+41 71 841 58 19",
    "sg:postcode":"9403",
    "sg:province":"St. Gallen",
    "wof:name":"Schweiz.dachdeckermeister- Verband",
    "wof:placetype":"venue"
},
  "geometry": {"coordinates":[9.4620990753,47.4768676758],"type":"Point"}
}