{
  "type": "Feature",
  "properties": {
    "iso:country":"CH",
    "sg:address":"Chemin De Verey 14",
    "sg:city":"Gen\u00e8ve",
    "sg:classifiers":[
        {
            "category":"Professional",
            "subcategory":"Employment Agencies",
            "type":"Services"
        }
    ],
    "sg:phone":"+41 22 736 69 73",
    "sg:postcode":"1208",
    "sg:province":"Gen\u00e8ve",
    "sg:tags":[
        "personal",
        "u",
        "stellenvermittlung"
    ],
    "wof:name":"Nba Cabinet Conseil, Nunez Wenderdel Ben-amor Mme X.",
    "wof:placetype":"venue"
},
  "geometry": {"coordinates":[6.1615309715,46.1988220215],"type":"Point"}
}