{
  "type": "Feature",
  "properties": {
    "iso:country":"CH",
    "sg:address":"Rue De Bernex 302",
    "sg:city":"Bernex",
    "sg:orig_category":"Bauspenglerei Zimmerei, Dachdeckerei, Bauspenglerei U Abdichtung",
    "sg:phone":"+41 22 757 43 78",
    "sg:postcode":"1233",
    "sg:province":"Gen\u00e8ve",
    "wof:name":"Sturzenegger Laurent",
    "wof:placetype":"venue"
},
  "geometry": {"coordinates":[6.070734,46.17458],"type":"Point"}
}