{
  "type": "Feature",
  "properties": {
    "iso:country":"CH",
    "sg:address":"Hornstrasse 6",
    "sg:city":"Feldbach",
    "sg:orig_category":"Obstbau",
    "sg:phone":"+41 56 496 13 79",
    "sg:postcode":"8714",
    "sg:province":"Z\u00fcrich",
    "wof:name":"Kurt Fischer Tafelobstproduktion",
    "wof:placetype":"venue"
},
  "geometry": {"coordinates":[8.3019828796,47.4007568359],"type":"Point"}
}