{
  "type": "Feature",
  "properties": {
    "iso:country":"CH",
    "sg:address":"Sch\u00f6neckstrasse 361 8215 Hallau. Postfach",
    "sg:city":"Hallau",
    "sg:orig_category":"Grosshandel mit Software Softwareentwicklung U beratung",
    "sg:phone":"+41 52 682 23 02",
    "sg:postcode":"8215",
    "sg:province":"Schaffhausen",
    "wof:name":"Cape2000 Gmbh Hard- U. Software; Vertrieb Usw.",
    "wof:placetype":"venue"
},
  "geometry": {"coordinates":[8.4592342377,47.695602417],"type":"Point"}
}