{
  "type": "Feature",
  "properties": {
    "iso:country":"CH",
    "sg:address":"Schmiedengasse 9 5012 Sch\u00f6nenwerd. Postfach",
    "sg:city":"Sch\u00f6nenwerd",
    "sg:orig_category":"Non-Classified Establishments",
    "sg:postcode":"5012",
    "sg:province":"Solothurn",
    "wof:name":"Nagel & Kosmetik Guarino Patrizia Genannt Paty",
    "wof:placetype":"venue"
},
  "geometry": {"coordinates":[8.0032157898,47.3715248108],"type":"Point"}
}