{
  "type": "Feature",
  "properties": {
    "iso:country":"CH",
    "sg:address":"3780",
    "sg:city":"Gstaad",
    "sg:orig_category":"Campingpl\u00e4tze",
    "sg:phone":"+41 32 751 27 62",
    "sg:postcode":"3780",
    "sg:province":"Bern",
    "wof:name":"Camping Bellerive Famille Jakob",
    "wof:placetype":"venue"
},
  "geometry": {"coordinates":[7.086751,47.061211],"type":"Point"}
}