{
  "type": "Feature",
  "properties": {
    "iso:country":"CH",
    "sg:address":"Waldistrasse 18",
    "sg:city":"Adliswil",
    "sg:orig_category":"Abdichtung",
    "sg:phone":"+41 17109739",
    "sg:postcode":"8134",
    "sg:province":"Z\u00fcrich",
    "wof:name":"Baudicht Gmbh",
    "wof:placetype":"venue"
},
  "geometry": {"coordinates":[8.522392,47.299267],"type":"Point"}
}