{
  "type": "Feature",
  "properties": {
    "iso:country":"CH",
    "sg:address":"Staatsstrasse 63 9472 Grabs. Postfach 2",
    "sg:city":"Grabs",
    "sg:orig_category":"Detailhandel mit Brot, Back U S\u00fcsswaren",
    "sg:phone":"+41 81 771 29 66",
    "sg:postcode":"9472",
    "sg:province":"St. Gallen",
    "wof:name":"Hans Locher, B\u00e4ckerei-konditorei",
    "wof:placetype":"venue"
},
  "geometry": {"coordinates":[9.445332,47.181602],"type":"Point"}
}