{
  "type": "Feature",
  "properties": {
    "addr:full":"1423 Villars-burquin Vaud 1423",
    "addr:postcode":"1423;1423",
    "iso:country":"CH",
    "sg:address":"1423",
    "sg:city":"Villars-burquin",
    "sg:classifiers":[
        {
            "category":"Education",
            "subcategory":"Library",
            "type":"Public Place"
        }
    ],
    "sg:postcode":"1423",
    "sg:province":"Vaud",
    "sg:tags":[
        "u",
        "bibliotheken",
        "archive"
    ],
    "wof:name":"Biblioth\u00e8que Populaire",
    "wof:placetype":"venue"
},
  "geometry": {"coordinates":[6.62632,46.847759],"type":"Point"}
}