{
  "type": "Feature",
  "properties": {
    "iso:country":"CH",
    "sg:address":"Madretschstrasse 10",
    "sg:city":"Biel/bienne",
    "sg:orig_category":"Detailhandel mit Tabakwaren",
    "sg:phone":"+41 32 365 81 15",
    "sg:postcode":"2503",
    "sg:province":"Bern",
    "wof:name":"Patrick Baty Kiosk Do Sol",
    "wof:placetype":"venue"
},
  "geometry": {"coordinates":[7.2528619766,47.1325378418],"type":"Point"}
}