{
  "type": "Feature",
  "properties": {
    "addr:full":"Scheibenschachenstrasse 4 5000 Aarau. Postfach Oberentfelden Aargau 5036",
    "addr:housenumber":"4",
    "addr:postcode":"5000 aarau. postfach;5036",
    "addr:street":"Scheibenschachenstrasse",
    "iso:country":"CH",
    "sg:address":"Scheibenschachenstrasse 4 5000 Aarau. Postfach",
    "sg:city":"Oberentfelden",
    "sg:orig_category":"Aktivit\u00e4ten der Generalunternehmen im Baugewerbe Kauf U Verkauf von Immobilien auf eigene Rechnung",
    "sg:phone":"+41 62 723 43 03",
    "sg:postcode":"5036",
    "sg:province":"Aargau",
    "wof:name":"Mobest Ag",
    "wof:placetype":"venue"
},
  "geometry": {"coordinates":[8.044458,47.39716],"type":"Point"}
}