{
  "type": "Feature",
  "properties": {
    "iso:country":"CH",
    "sg:address":"Steinmattstrasse 43",
    "sg:city":"Zermatt",
    "sg:orig_category":"Detailhandel mit Damenbekleidung Kosmetikinstitute",
    "sg:phone":"+41 27 967 59 55",
    "sg:postcode":"3920",
    "sg:province":"Valais",
    "wof:name":"Rita Zuber",
    "wof:placetype":"venue"
},
  "geometry": {"coordinates":[7.7491979599,46.018863678],"type":"Point"}
}