{
  "type": "Feature",
  "properties": {
    "iso:country":"CH",
    "sg:address":"Matt 3 5046 Schmiedrued. Postfach",
    "sg:city":"Schmiedrued",
    "sg:orig_category":"Allgemeiner Hoch U Tiefbau Baugewerbe",
    "sg:phone":"+41 62 758 45 65",
    "sg:postcode":"5046",
    "sg:province":"Aargau",
    "wof:name":"Ts Bauunternehmung Gmbh Bauarbeiten Usw",
    "wof:placetype":"venue"
},
  "geometry": {"coordinates":[7.962396,47.226677],"type":"Point"}
}