{
  "type": "Feature",
  "properties": {
    "iso:country":"CH",
    "sg:address":"Weissenhaldenstrasse 7",
    "sg:city":"Rorbas",
    "sg:orig_category":"Herstellung von Fenstern U T\u00fcren aus Holz",
    "sg:phone":"+41 52 762 75 75",
    "sg:postcode":"8427",
    "sg:province":"Z\u00fcrich",
    "wof:name":"Herzog Fensterbau Ag",
    "wof:placetype":"venue"
},
  "geometry": {"coordinates":[9.0000743866,47.6001167297],"type":"Point"}
}