{
  "type": "Feature",
  "properties": {
    "iso:country":"CH",
    "sg:address":"2717",
    "sg:city":"Fornet-dessous",
    "sg:classifiers":[
        {
            "category":"Government",
            "subcategory":"Post Office",
            "type":"Public Place"
        }
    ],
    "sg:phone":"+41 32 487 43 05",
    "sg:postcode":"2717",
    "sg:province":"Bern",
    "sg:tags":[
        "die",
        "poststellen"
    ],
    "wof:name":"La Poste",
    "wof:placetype":"venue"
},
  "geometry": {"coordinates":[7.0833501816,47.2246208191],"type":"Point"}
}