{
  "type": "Feature",
  "properties": {
    "iso:country":"CH",
    "sg:address":"Im Kl\u00e4yhof 14",
    "sg:city":"Zollikofen",
    "sg:orig_category":"Aktivit\u00e4ten der Generalunternehmen im Baugewerbe",
    "sg:phone":"+41 31 911 45 87",
    "sg:postcode":"3052",
    "sg:province":"Bern",
    "wof:name":"Bruno Meier",
    "wof:placetype":"venue"
},
  "geometry": {"coordinates":[7.444173,47.000153],"type":"Point"}
}