{
  "type": "Feature",
  "properties": {
    "iso:country":"CH",
    "sg:address":"Dohlenweg 28 8050 Z\u00fcrich",
    "sg:city":"Zust",
    "sg:orig_category":"Werbung",
    "sg:phone":"+41 71 311 82 30",
    "sg:postcode":"50",
    "wof:name":"Mediapolis Ag F\u00fcr Kommunikations-management Christian Ledergerber",
    "wof:placetype":"venue"
},
  "geometry": {"coordinates":[9.3145666122,47.4094848633],"type":"Point"}
}