{
  "type": "Feature",
  "properties": {
    "iso:country":"CH",
    "sg:address":"Im Winkel 21",
    "sg:city":"B\u00fcnzen",
    "sg:orig_category":"Organisationen des Gesundheitswesen",
    "sg:phone":"+41 56 666 21 72",
    "sg:postcode":"5624",
    "sg:province":"Aargau",
    "wof:name":"Schweizer Kneippverband",
    "wof:placetype":"venue"
},
  "geometry": {"coordinates":[8.3234529495,47.3069877625],"type":"Point"}
}