{
  "type": "Feature",
  "properties": {
    "iso:country":"CH",
    "sg:address":"Chemin De Cyrano 3",
    "sg:city":"Pully",
    "sg:orig_category":"Grosshandel mit Baumaterialien Sanit\u00e4rkeramik Grosshandel",
    "sg:postcode":"1009",
    "sg:province":"Vaud",
    "wof:name":"Ceram Concept Sa C\u00e9ramiques & Art. Sanitaires",
    "wof:placetype":"venue"
},
  "geometry": {"coordinates":[6.6428360939,46.5057182312],"type":"Point"}
}