{
  "type": "Feature",
  "properties": {
    "iso:country":"CH",
    "sg:address":"Grossmattrain 1",
    "sg:city":"Rudolfstetten",
    "sg:orig_category":"Fans, Blowers",
    "sg:phone":"+41 56 648 48 38",
    "sg:postcode":"8964",
    "sg:province":"Aargau",
    "wof:name":"Fanair Ag",
    "wof:placetype":"venue"
},
  "geometry": {"coordinates":[8.387339592,47.3742256165],"type":"Point"}
}