{
  "type": "Feature",
  "properties": {
    "addr:full":"Kanonengasse 32 Basel Basel-Stadt 4051",
    "addr:housenumber":"32",
    "addr:postcode":"4051",
    "addr:street":"Kanonengasse",
    "iso:country":"CH",
    "sg:address":"Kanonengasse 32",
    "sg:city":"Basel",
    "sg:classifiers":[
        {
            "category":"Shopping",
            "subcategory":"Books",
            "type":"Retail Goods"
        }
    ],
    "sg:phone":"+41 61 270 15 15",
    "sg:postcode":"4051",
    "sg:province":"Basel-Stadt",
    "wof:name":"Werner Druck Ag",
    "wof:placetype":"venue"
},
  "geometry": {"coordinates":[7.58493,47.553249],"type":"Point"}
}