{
  "type": "Feature",
  "properties": {
    "iso:country":"CH",
    "sg:address":"Chemin De La Damataire 1",
    "sg:city":"Pully",
    "sg:orig_category":"Bauschreinerei Herstellung von Konstruktionsteilen, Fertigbauteilen U Ausbauelementen aus Holz",
    "sg:phone":"+41 21 729 79 93",
    "sg:postcode":"1009",
    "sg:province":"Vaud",
    "wof:name":"Artemos Alain Vaucher Eb\u00e9nisterie D'art",
    "wof:placetype":"venue"
},
  "geometry": {"coordinates":[6.669923,46.508072],"type":"Point"}
}