{
  "type": "Feature",
  "properties": {
    "iso:country":"CH",
    "sg:address":"Via Angelo Maspoli 25",
    "sg:city":"Mendrisio",
    "sg:orig_category":"Museen",
    "sg:postcode":"6850",
    "sg:province":"Ticino",
    "wof:name":"Club Del San Gottardo",
    "wof:placetype":"venue"
},
  "geometry": {"coordinates":[8.9784212112,45.8754234314],"type":"Point"}
}