{
  "type": "Feature",
  "properties": {
    "iso:country":"CH",
    "sg:address":"Blumenrainweg 3",
    "sg:city":"Appenzell",
    "sg:orig_category":"Organisationen des Gesundheitswesen",
    "sg:phone":"+41 71 780 03 90",
    "sg:postcode":"9050",
    "sg:province":"Appenzell Innerhoden",
    "wof:name":"Rheumaliga Sozialberatung C/o Pro Infirmis",
    "wof:placetype":"venue"
},
  "geometry": {"coordinates":[9.4126062393,47.331401825],"type":"Point"}
}