{
  "type": "Feature",
  "properties": {
    "iso:country":"CH",
    "sg:address":"Torstrasse 25",
    "sg:city":"St.gallen",
    "sg:orig_category":"Sonstige pers\u00f6nliche Dienstleistungen",
    "sg:phone":"+41 71 330 09 90",
    "sg:postcode":"9000",
    "sg:province":"St. Gallen",
    "wof:name":"Singleserve Gmbh",
    "wof:placetype":"venue"
},
  "geometry": {"coordinates":[9.3621683121,47.3862419128],"type":"Point"}
}