{
  "type": "Feature",
  "properties": {
    "iso:country":"CH",
    "sg:address":"S\u00e4riswilerstrasse 65",
    "sg:city":"Uettligen",
    "sg:orig_category":"Non-Classified Establishments",
    "sg:phone":"+41 31 822 00 00",
    "sg:postcode":"3043",
    "sg:province":"Bern",
    "wof:name":"Besico Ag",
    "wof:placetype":"venue"
},
  "geometry": {"coordinates":[7.3712100983,46.9895515442],"type":"Point"}
}