{
  "type": "Feature",
  "properties": {
    "iso:country":"CH",
    "sg:address":"M\u00fchlebachstrasse 9 8008 Z\u00fcrich. Postfach",
    "sg:city":"Z\u00fcrich",
    "sg:orig_category":"Sonstiger Grosshandel",
    "sg:phone":"+41 56 619 70 60",
    "sg:postcode":"8001",
    "sg:province":"Z\u00fcrich",
    "wof:name":"Kronenberg E. Nicht Metallische Produkte; Handel. Immobilien Usw",
    "wof:placetype":"venue"
},
  "geometry": {"coordinates":[8.2792854309,47.355091095],"type":"Point"}
}