{
  "type": "Feature",
  "properties": {
    "iso:country":"CH",
    "sg:address":"Kaiserstrasse 6",
    "sg:city":"Rheinfelden",
    "sg:orig_category":"Nationale Postdienste",
    "sg:phone":"+41 61 641 90 45",
    "sg:postcode":"4310",
    "sg:province":"Aargau",
    "wof:name":"Die Schweizerische Post Riehen 1",
    "wof:placetype":"venue"
},
  "geometry": {"coordinates":[7.6516971588,47.5831451416],"type":"Point"}
}