{
  "type": "Feature",
  "properties": {
    "addr:full":"Tillierstrasse 4 Bern Bern 3005",
    "addr:housenumber":"4",
    "addr:postcode":"3005",
    "addr:street":"Tillierstrasse",
    "iso:country":"CH",
    "sg:address":"Tillierstrasse 4",
    "sg:city":"Bern",
    "sg:orig_category":"Advokaturb\u00fcros",
    "sg:phone":"+41 31 356 16 16",
    "sg:postcode":"3005",
    "sg:province":"Bern",
    "wof:name":"Philippe Landtwing Advokaturb\u00fcro",
    "wof:placetype":"venue"
},
  "geometry": {"coordinates":[7.446657,46.939014],"type":"Point"}
}