{
  "type": "Feature",
  "properties": {
    "iso:country":"CH",
    "sg:address":"4056 Basel. Postfach",
    "sg:city":"Basel",
    "sg:orig_category":"G\u00fcterbef\u00f6rderung im Strassenverkehr",
    "sg:phone":"+41 61 271 84 01",
    "sg:postcode":"4030",
    "sg:province":"Basel-Stadt",
    "wof:name":"Gin Transport (schweiz) Ag",
    "wof:placetype":"venue"
},
  "geometry": {"coordinates":[7.5725798607,47.5679893494],"type":"Point"}
}