{
  "type": "Feature",
  "properties": {
    "iso:country":"CH",
    "sg:address":"Chemin Du Levant 23",
    "sg:city":"Crans-pr\u00e8s-c\u00e9ligny",
    "sg:orig_category":"Physiotherapie",
    "sg:phone":"+41 22 776 08 08",
    "sg:postcode":"1299",
    "sg:province":"Vaud",
    "wof:name":"Dorreen Varsori Physioth\u00e9rapie",
    "wof:placetype":"venue"
},
  "geometry": {"coordinates":[6.2153139114,46.3609619141],"type":"Point"}
}