{
  "type": "Feature",
  "properties": {
    "iso:country":"CH",
    "sg:address":"Rigistrasse 3 6330 Cham. Postfach 584",
    "sg:city":"Cham",
    "sg:classifiers":[
        {
            "category":"Social Services",
            "subcategory":"Retirement Home",
            "type":"Services"
        }
    ],
    "sg:phone":"+41 32 351 47 11",
    "sg:postcode":"6330",
    "sg:province":"Zug",
    "sg:tags":[
        "pflegeheime",
        "u",
        "alters"
    ],
    "wof:name":"Altersheim B\u00fcren An Der Aare",
    "wof:placetype":"venue"
},
  "geometry": {"coordinates":[7.370536,47.137703],"type":"Point"}
}