{
  "type": "Feature",
  "properties": {
    "iso:country":"CH",
    "sg:address":"Gutschstrasse 24",
    "sg:city":"Menzingen",
    "sg:orig_category":"Unternehmensberatung",
    "sg:phone":"+41 41 755 07 07",
    "sg:postcode":"6313",
    "sg:province":"Zug",
    "wof:name":"Mgm Management Michael Gross Wirtschaftsberatung",
    "wof:placetype":"venue"
},
  "geometry": {"coordinates":[8.598575592,47.1739273071],"type":"Point"}
}