{
  "type": "Feature",
  "properties": {
    "iso:country":"CH",
    "sg:address":"1148",
    "sg:city":"L'isle",
    "sg:orig_category":"Rebbau",
    "sg:phone":"+41 21 799 20 63",
    "sg:postcode":"1148",
    "sg:province":"Vaud",
    "wof:name":"Jean-louis Cardinaux Vigneron-encaveur",
    "wof:placetype":"venue"
},
  "geometry": {"coordinates":[54.3694496155,24.4995651245],"type":"Point"}
}