{
  "type": "Feature",
  "properties": {
    "iso:country":"CH",
    "sg:address":"Via Alla Riva 8",
    "sg:city":"Minusio",
    "sg:orig_category":"Sportvereine Wassersport Segeln",
    "sg:phone":"+41 91 743 40 29",
    "sg:postcode":"6648",
    "sg:province":"Ticino",
    "wof:name":"Yachtclub Verbano",
    "wof:placetype":"venue"
},
  "geometry": {"coordinates":[8.811621666,46.1719322205],"type":"Point"}
}