{
  "type": "Feature",
  "properties": {
    "iso:country":"CH",
    "sg:address":"1983",
    "sg:city":"Evol\u00e8ne",
    "sg:orig_category":"W\u00e4schereien",
    "sg:phone":"+41 27 283 18 18",
    "sg:postcode":"1983",
    "sg:province":"Valais",
    "wof:name":"Lucie Follonier Pressing Les Chamois",
    "wof:placetype":"venue"
},
  "geometry": {"coordinates":[7.4961590767,46.1144752502],"type":"Point"}
}