{
  "type": "Feature",
  "properties": {
    "iso:country":"CH",
    "sg:address":"Rue Du Simplon 25",
    "sg:city":"Lausanne",
    "sg:classifiers":[
        {
            "category":"Professional",
            "subcategory":"Employment Agencies",
            "type":"Services"
        }
    ],
    "sg:phone":"+41 21 613 12 05",
    "sg:postcode":"1006",
    "sg:province":"Vaud",
    "sg:tags":[
        "editorial"
    ],
    "wof:name":"Msm Le Mensuel De L'industrie",
    "wof:placetype":"venue"
},
  "geometry": {"coordinates":[6.6294112206,46.5159759521],"type":"Point"}
}