{
  "type": "Feature",
  "properties": {
    "iso:country":"CH",
    "sg:address":"Zentralstr. 23",
    "sg:city":"Boswil",
    "sg:classifiers":[
        {
            "category":"Banks & Credit Unions",
            "subcategory":"Bank",
            "type":"Services"
        }
    ],
    "sg:phone":"+41 56 666 33 20",
    "sg:postcode":"5623",
    "sg:province":"Aargau",
    "wof:name":"Aargauische Kantonalbank, Agentur Boswil",
    "wof:placetype":"venue"
},
  "geometry": {"coordinates":[8.314654,47.29974],"type":"Point"}
}