{
  "type": "Feature",
  "properties": {
    "addr:full":"Echallens Avenue D' 107 Lausanne Vaud 1004",
    "addr:housenumber":"107",
    "addr:postcode":"1004",
    "addr:street":"Echallens Avenue D '",
    "iso:country":"CH",
    "sg:address":"Echallens Avenue D' 107",
    "sg:city":"Lausanne",
    "sg:orig_category":"Detailhandel mit B\u00fcchern, Zeitungen, Schreib U Papeteriewaren",
    "sg:postcode":"1004",
    "sg:province":"Vaud",
    "wof:name":"Kiosque Du Rialto, B\u00e9rod Tatiana Tabacs, Journaux, Articles De Diverse Nature; Commerce",
    "wof:placetype":"venue"
},
  "geometry": {"coordinates":[6.420094,45.752941],"type":"Point"}
}