{
  "type": "Feature",
  "properties": {
    "iso:country":"CH",
    "sg:address":"5724",
    "sg:city":"D\u00fcrren\u00e4sch",
    "sg:classifiers":[
        {
            "category":"Social Services",
            "subcategory":"Retirement Home",
            "type":"Services"
        }
    ],
    "sg:phone":"+41 62 777 15 29",
    "sg:postcode":"5724",
    "sg:province":"Aargau",
    "sg:tags":[
        "pflegeheime",
        "u",
        "alters"
    ],
    "wof:name":"B\u00fcrgerheim",
    "wof:placetype":"venue"
},
  "geometry": {"coordinates":[8.15323,47.316811],"type":"Point"}
}