{
  "type": "Feature",
  "properties": {
    "iso:country":"CH",
    "sg:address":"Holgasse 20",
    "sg:city":"Mellikon",
    "sg:orig_category":"Briefmarken Detailhandel Erbringung von sonstigen Dienstleistungen f\u00fcr Unternehmen",
    "sg:phone":"+41 71 385 85 66",
    "sg:postcode":"5465",
    "sg:province":"Aargau",
    "wof:name":"Silvio Chiani Briefmarkenauktionen",
    "wof:placetype":"venue"
},
  "geometry": {"coordinates":[9.252257,47.407055],"type":"Point"}
}