{
  "type": "Feature",
  "properties": {
    "iso:country":"CH",
    "sg:address":"4581",
    "sg:city":"K\u00fcttigkofen",
    "sg:orig_category":"Sportvereine Sch\u00fctzen",
    "sg:postcode":"4581",
    "sg:province":"Solothurn",
    "wof:name":"Sch\u00fctzengesellschaft Lauffohr",
    "wof:placetype":"venue"
},
  "geometry": {"coordinates":[8.2035999298,47.4864692688],"type":"Point"}
}