{
  "type": "Feature",
  "properties": {
    "iso:country":"CH",
    "sg:address":"B\u00f6sch 106",
    "sg:city":"H\u00fcnenberg",
    "sg:orig_category":"Herstellung von Elektrizit\u00e4tsverteilungs U schalteinrichtungen",
    "sg:phone":"+41 41 780 05 68",
    "sg:postcode":"6331",
    "sg:province":"Zug",
    "wof:name":"Eran Annen",
    "wof:placetype":"venue"
},
  "geometry": {"coordinates":[8.4337129593,47.1614151001],"type":"Point"}
}