{
  "type": "Feature",
  "properties": {
    "iso:country":"CH",
    "sg:address":"Am Letzibach 5",
    "sg:city":"Zug",
    "sg:classifiers":[
        {
            "category":"Insurance",
            "subcategory":"Insurance Agent",
            "type":"Services"
        }
    ],
    "sg:phone":"+41 41 741 30 38",
    "sg:postcode":"6300",
    "sg:province":"Zug",
    "sg:tags":[
        "versicherungsagenturen",
        "-broker"
    ],
    "wof:name":"Linus Roth Versicherungen",
    "wof:placetype":"venue"
},
  "geometry": {"coordinates":[8.5005149841,47.1787757874],"type":"Point"}
}