{
  "type": "Feature",
  "properties": {
    "iso:country":"CH",
    "sg:address":"Grand-rue 15",
    "sg:city":"Courcelon",
    "sg:classifiers":[
        {
            "category":"Restaurant",
            "type":"Food & Drink"
        }
    ],
    "sg:phone":"+41 32 422 12 10",
    "sg:postcode":"2823",
    "sg:province":"Jura",
    "wof:name":"Restaurant La Couronne",
    "wof:placetype":"venue"
},
  "geometry": {"coordinates":[7.3911218643,47.3620223999],"type":"Point"}
}