{
  "type": "Feature",
  "properties": {
    "iso:country":"CH",
    "sg:address":"W\u00e4ltigasse 7",
    "sg:city":"Mels",
    "sg:orig_category":"Geb\u00e4ude, Wohnungsreinigung Reinigungsgewerbe",
    "sg:phone":"+41 81 723 80 50",
    "sg:postcode":"8887",
    "sg:province":"St. Gallen",
    "wof:name":"Isabell Mullis Reinigungsunternehmen",
    "wof:placetype":"venue"
},
  "geometry": {"coordinates":[9.4175357819,47.0516548157],"type":"Point"}
}