{
  "type": "Feature",
  "properties": {
    "iso:country":"CH",
    "sg:address":"Haldenstrasse 1",
    "sg:city":"Mammern",
    "sg:orig_category":"Interessenvertretungen",
    "sg:postcode":"8265",
    "sg:province":"Thurgau",
    "wof:name":"Verein F\u00fcr Sinnvolle Freizeitgestaltung",
    "wof:placetype":"venue"
},
  "geometry": {"coordinates":[9.1381845474,47.5666694641],"type":"Point"}
}