{
  "type": "Feature",
  "properties": {
    "iso:country":"CH",
    "sg:address":"Abendweg 19",
    "sg:city":"Luzern",
    "sg:orig_category":"Chiropraktik",
    "sg:phone":"+41 41 420 11 22",
    "sg:postcode":"6006",
    "sg:province":"Luzern",
    "wof:name":"Dr.mario Sassi Chiropraktor",
    "wof:placetype":"venue"
},
  "geometry": {"coordinates":[8.314521,47.059219],"type":"Point"}
}