{
  "type": "Feature",
  "properties": {
    "iso:country":"CH",
    "sg:address":"Vordorf 29",
    "sg:city":"Reutigen",
    "sg:orig_category":"Darlehenskassen U Raiffeisenbanken",
    "sg:phone":"+41 33 657 80 50",
    "sg:postcode":"3647",
    "sg:province":"Bern",
    "wof:name":"Raiffeisenbank Diemtigen",
    "wof:placetype":"venue"
},
  "geometry": {"coordinates":[7.620934,46.6936],"type":"Point"}
}