{
  "type": "Feature",
  "properties": {
    "iso:country":"CH",
    "sg:address":"Dorfplatz 7",
    "sg:city":"Giffers",
    "sg:orig_category":"Darlehenskassen U Raiffeisenbanken",
    "sg:phone":"+41 41 885 11 44",
    "sg:postcode":"1735",
    "sg:province":"Fribourg",
    "wof:name":"Raiffeisenbank",
    "wof:placetype":"venue"
},
  "geometry": {"coordinates":[8.59961,46.70649],"type":"Point"}
}