{
  "type": "Feature",
  "properties": {
    "iso:country":"CH",
    "sg:address":"4410 Liestal. Postfach 80",
    "sg:city":"Liestal",
    "sg:orig_category":"Berufsorganisationen",
    "sg:postcode":"4410",
    "sg:province":"Basel-Landschaft",
    "wof:name":"Wirtschaftskammer Baselland",
    "wof:placetype":"venue"
},
  "geometry": {"coordinates":[7.732417,47.485458],"type":"Point"}
}