{
  "type": "Feature",
  "properties": {
    "iso:country":"CH",
    "sg:address":"Aemtlerstrasse 78",
    "sg:city":"Z\u00fcrich",
    "sg:orig_category":"Sonstiger Grosshandel",
    "sg:phone":"+41 22 301 25 46",
    "sg:postcode":"8003",
    "sg:province":"Z\u00fcrich",
    "wof:name":"Espaces Temps, Cullati Chantal",
    "wof:placetype":"venue"
},
  "geometry": {"coordinates":[6.1337270737,46.1893730164],"type":"Point"}
}