{
  "type": "Feature",
  "properties": {
    "iso:country":"CH",
    "sg:address":"Pfistergasse 15",
    "sg:city":"Luzern",
    "sg:orig_category":"Detailhandel mit Brillen U anderen Sehhilfen Herstellung von medizinischen U chirurgischen Ger\u00e4ten s",
    "sg:phone":"+41 41 240 79 41",
    "sg:postcode":"6003",
    "sg:province":"Luzern",
    "wof:name":"Contactlinsen-studio Ag Luzern",
    "wof:placetype":"venue"
},
  "geometry": {"coordinates":[8.30221,47.050781],"type":"Point"}
}