{
  "type": "Feature",
  "properties": {
    "iso:country":"CH",
    "sg:address":"Rue De La Pr\u00e9fecture 10",
    "sg:city":"Del\u00e9mont",
    "sg:orig_category":"Bau U Wohngenossenschaften",
    "sg:phone":"+41 32 422 67 77",
    "sg:postcode":"2800",
    "sg:province":"Jura",
    "wof:name":"St\u00e9 Coop.d'hab.pres Fleuris",
    "wof:placetype":"venue"
},
  "geometry": {"coordinates":[7.344009,47.366016],"type":"Point"}
}