{
  "type": "Feature",
  "properties": {
    "iso:country":"CH",
    "sg:address":"R\u00fcti",
    "sg:city":"Inwil",
    "sg:orig_category":"Detailhandel mit Milcherzeugnissen U Eiern Verarbeitung von Milch",
    "sg:postcode":"6034",
    "sg:province":"Luzern",
    "wof:name":"Milchgenossenschaft Pfaffwil C/o Herrn Franz Mattmann",
    "wof:placetype":"venue"
},
  "geometry": {"coordinates":[8.3512601852,47.1242904663],"type":"Point"}
}