{
  "type": "Feature",
  "properties": {
    "iso:country":"CH",
    "sg:address":"Ch\u00e2telaine Avenue De 43",
    "sg:city":"Gen\u00e8ve",
    "sg:orig_category":"Unclassifiable Establishments",
    "sg:postcode":"1203",
    "sg:province":"Gen\u00e8ve",
    "wof:name":"Zz Outillages, Zeier",
    "wof:placetype":"venue"
},
  "geometry": {"coordinates":[6.1161599159,46.210308075],"type":"Point"}
}