{
  "type": "Feature",
  "properties": {
    "iso:country":"CH",
    "sg:address":"Chemin De La Chavanne 17",
    "sg:city":"Gland",
    "sg:orig_category":"S\u00e4ge, Hobel U Holzimpr\u00e4gnierwerke",
    "sg:phone":"+41 22 364 32 20",
    "sg:postcode":"1196",
    "sg:province":"Vaud",
    "wof:name":"Map, Adjemian Mario",
    "wof:placetype":"venue"
},
  "geometry": {"coordinates":[6.2725830078,46.4212646484],"type":"Point"}
}