{
  "type": "Feature",
  "properties": {
    "iso:country":"CH",
    "sg:address":"Mettlenweg 43",
    "sg:city":"Biel/bienne",
    "sg:orig_category":"Maler U Glasergewerbe Stukkateurgewerbe, Gipserei U Verputzerei",
    "sg:phone":"+41 32 341 63 83",
    "sg:postcode":"2504",
    "sg:province":"Bern",
    "wof:name":"Eisbacher F.",
    "wof:placetype":"venue"
},
  "geometry": {"coordinates":[7.2801680565,47.1497192383],"type":"Point"}
}