{
  "type": "Feature",
  "properties": {
    "addr:full":"Gotthelfstrasse 106 Basel Basel-Stadt 4054",
    "addr:housenumber":"106",
    "addr:postcode":"4054",
    "addr:street":"Gotthelfstrasse",
    "iso:country":"CH",
    "sg:address":"Gotthelfstrasse 106",
    "sg:city":"Basel",
    "sg:orig_category":"Chemin\u00e9e- and Ofenbau Fussboden, Fliesen U Plattenlegerei, Tapeziererei",
    "sg:phone":"+41 41 830 22 37",
    "sg:postcode":"4054",
    "sg:province":"Basel-Stadt",
    "wof:name":"Gwerder Eugen, Plattenbel\u00e4ge, Ofen Und Chemineebau",
    "wof:placetype":"venue"
},
  "geometry": {"coordinates":[8.70542,46.9879],"type":"Point"}
}