{
  "type": "Feature",
  "properties": {
    "iso:country":"CH",
    "sg:address":"Rue De Lyon 8",
    "sg:city":"Gen\u00e8ve",
    "sg:orig_category":"Chemische Reinigung",
    "sg:phone":"+41 22 340 48 22",
    "sg:postcode":"1201",
    "sg:province":"Gen\u00e8ve",
    "wof:name":"Maria-emilia Coelho Quali-cline Pressing",
    "wof:placetype":"venue"
},
  "geometry": {"coordinates":[6.138293,46.209278],"type":"Point"}
}