{
  "type": "Feature",
  "properties": {
    "iso:country":"CH",
    "sg:address":"Chesa Fidela",
    "sg:city":"Pontresina",
    "sg:orig_category":"Datenverarbeitungsdienste Softwareentwicklung U beratung",
    "sg:phone":"+41 81 834 58 31",
    "sg:postcode":"7504",
    "sg:province":"Graubunden",
    "wof:name":"Panorgan Ag Datenverarbeitung",
    "wof:placetype":"venue"
},
  "geometry": {"coordinates":[9.903692,46.490185],"type":"Point"}
}