{
  "type": "Feature",
  "properties": {
    "iso:country":"CH",
    "sg:address":"Solthurnstrasse 22",
    "sg:city":"Klus",
    "sg:classifiers":[
        {
            "category":"Bars & Pubs",
            "type":"Food & Drink"
        }
    ],
    "sg:postcode":"4710",
    "sg:province":"Solothurn",
    "wof:name":"Sipa-bar Gmbh",
    "wof:placetype":"venue"
},
  "geometry": {"coordinates":[7.689831,47.306744],"type":"Point"}
}