{
  "type": "Feature",
  "properties": {
    "iso:country":"CH",
    "sg:address":"Gutenbergstrasse 15",
    "sg:city":"Z\u00fcrich",
    "sg:orig_category":"Maturit\u00e4tsschulen, Lehrerseminarien",
    "sg:phone":"+41 12028040",
    "sg:postcode":"8002",
    "sg:province":"Z\u00fcrich",
    "wof:name":"Kantonsschule Freudenberg",
    "wof:placetype":"venue"
},
  "geometry": {"coordinates":[8.52987957,47.3656692505],"type":"Point"}
}