{
  "type": "Feature",
  "properties": {
    "iso:country":"CH",
    "sg:address":"Boningerstrasse 57",
    "sg:city":"Aarburg",
    "sg:orig_category":"RESTAURANTS: TEA-ROOMS",
    "sg:phone":"+41 62 791 55 35",
    "sg:postcode":"4663",
    "sg:province":"Aargau",
    "wof:name":"Restaurant Aareblick",
    "wof:placetype":"venue"
},
  "geometry": {"coordinates":[7.899078846,47.3201904297],"type":"Point"}
}