{
  "type": "Feature",
  "properties": {
    "iso:country":"CH",
    "sg:address":"Schulstrasse 11a",
    "sg:city":"Balterswil",
    "sg:orig_category":"Grosshandel mit Milch, Milcherzeugnissen, Eiern, Speise\u00f6len U Nahrungsfetten Haltung von Gefl\u00fcgel",
    "sg:phone":"+41 71 971 18 28",
    "sg:postcode":"8362",
    "sg:province":"Thurgau",
    "wof:name":"Eugster Eier Ag Gefl\u00fcgelfarm",
    "wof:placetype":"venue"
},
  "geometry": {"coordinates":[8.9376888275,47.4546432495],"type":"Point"}
}