{
  "type": "Feature",
  "properties": {
    "iso:country":"CH",
    "sg:address":"Vieux-moulin Rue Du 1",
    "sg:city":"Sion",
    "sg:orig_category":"Herstellung von konfektionierten Textilwaren ohne Bekleidung",
    "sg:phone":"+41 56 443 00 63",
    "sg:postcode":"1950",
    "sg:province":"Valais",
    "wof:name":"Ombra Ag",
    "wof:placetype":"venue"
},
  "geometry": {"coordinates":[8.1563596725,47.4637374878],"type":"Point"}
}