{
  "type": "Feature",
  "properties": {
    "addr:full":"Bruckackerstrasse 6 Liestal Basel-Landschaft 4410",
    "addr:housenumber":"6",
    "addr:postcode":"4410",
    "addr:street":"Bruckackerstrasse",
    "iso:country":"CH",
    "sg:address":"Bruckackerstrasse 6",
    "sg:city":"Liestal",
    "sg:orig_category":"Detailhandel mit Brot, Back U S\u00fcsswaren",
    "sg:phone":"+41 61 921 44 71",
    "sg:postcode":"4410",
    "sg:province":"Basel-Landschaft",
    "wof:name":"Erich Gysin B\u00e4ckerei-konditorei",
    "wof:placetype":"venue"
},
  "geometry": {"coordinates":[7.737742,47.479965],"type":"Point"}
}