{
  "type": "Feature",
  "properties": {
    "addr:full":"Gewerbezentrum Wissibach Sachseln Obwalden 6072",
    "addr:postcode":"6072",
    "iso:country":"CH",
    "sg:address":"Gewerbezentrum Wissibach",
    "sg:city":"Sachseln",
    "sg:orig_category":"Bauschreinerei Herstellung von Konstruktionsteilen, Fertigbauteilen U Ausbauelementen aus Holz",
    "sg:phone":"+41 21 866 76 92",
    "sg:postcode":"6072",
    "sg:province":"Obwalden",
    "wof:name":"Brocard Eric",
    "wof:placetype":"venue"
},
  "geometry": {"coordinates":[6.512838,46.658398],"type":"Point"}
}