{
  "type": "Feature",
  "properties": {
    "addr:full":"Palettes Chemin Des 3 Grand-lancy Gen\u00e8ve 1212",
    "addr:postcode":"1212",
    "addr:street":"Chemin Des 3 Grand-Lancy",
    "iso:country":"CH",
    "sg:address":"Palettes Chemin Des 3",
    "sg:city":"Grand-lancy",
    "sg:orig_category":"Detailhandel mit Antiquit\u00e4ten U Gebrauchtwaren in Verkaufsr\u00e4umen",
    "sg:postcode":"1212",
    "sg:province":"Gen\u00e8ve",
    "wof:name":"Brocante, Collomb Agnieszka Vente D'objets Anciens",
    "wof:placetype":"venue"
},
  "geometry": {"coordinates":[6.12683,46.236816],"type":"Point"}
}