{
  "type": "Feature",
  "properties": {
    "iso:country":"CH",
    "sg:address":"Mittlere Strasse 69",
    "sg:city":"Basel",
    "sg:orig_category":"Informatikdienste Sonstige mit der Informatik verbundene T\u00e4tigkeiten",
    "sg:phone":"+41 79 643 30 29",
    "sg:postcode":"4056",
    "sg:province":"Basel-Stadt",
    "wof:name":"D. Schmid Consulting",
    "wof:placetype":"venue"
},
  "geometry": {"coordinates":[7.5775289536,47.5619697571],"type":"Point"}
}