{
  "type": "Feature",
  "properties": {
    "iso:country":"CH",
    "sg:address":"Hutmatt 453",
    "sg:city":"D\u00fcrren\u00e4sch",
    "sg:classifiers":[
        {
            "category":"Professional",
            "type":"Services"
        }
    ],
    "sg:phone":"+41 62 767 67 00",
    "sg:postcode":"5724",
    "sg:province":"Aargau",
    "sg:tags":[
        "transport",
        "road"
    ],
    "wof:name":"Bertschi Transport Ag",
    "wof:placetype":"venue"
},
  "geometry": {"coordinates":[8.1560115814,47.3207206726],"type":"Point"}
}