{
  "type": "Feature",
  "properties": {
    "iso:country":"CH",
    "sg:address":"Thurgauer Str. 39",
    "sg:city":"Z\u00fcrich",
    "sg:classifiers":[
        {
            "category":"Manufacturing",
            "subcategory":"Chemicals & Compounds",
            "type":"Manufacturing & Wholesale Goods"
        }
    ],
    "sg:phone":"+41 4113086969",
    "sg:postcode":"8050",
    "sg:province":"Z\u00fcrich",
    "sg:tags":[
        "pharmaceutical",
        "chemistry",
        "-",
        "by-product"
    ],
    "wof:name":"Kl\u00dcber Lubrication Ag Schweiz",
    "wof:placetype":"venue"
},
  "geometry": {"coordinates":[8.550297,47.414555],"type":"Point"}
}