{
  "type": "Feature",
  "properties": {
    "iso:country":"CH",
    "sg:address":"Route De Bussigny 26",
    "sg:city":"Crissier",
    "sg:orig_category":"Druckweiterverarbeitung",
    "sg:phone":"+41 62 771 08 28",
    "sg:postcode":"1023",
    "sg:province":"Vaud",
    "wof:name":"Isografik Ag",
    "wof:placetype":"venue"
},
  "geometry": {"coordinates":[8.1803684235,47.2364234924],"type":"Point"}
}