{
  "type": "Feature",
  "properties": {
    "iso:country":"CH",
    "sg:address":"Rigistrasse 5",
    "sg:city":"Merenschwand",
    "sg:orig_category":"Packaging Logistics",
    "sg:phone":"+41 56 675 55 45",
    "sg:postcode":"5634",
    "sg:province":"Aargau",
    "wof:name":"Orgapack Gmbh",
    "wof:placetype":"venue"
},
  "geometry": {"coordinates":[8.387761116,47.2609634399],"type":"Point"}
}