{
  "type": "Feature",
  "properties": {
    "addr:full":"Via Gesero 4a Giubiasco Ticino 6512",
    "addr:housenumber":"4a",
    "addr:postcode":"6512",
    "addr:street":"Via Gesero",
    "iso:country":"CH",
    "sg:address":"Via Gesero 4a",
    "sg:city":"Giubiasco",
    "sg:orig_category":"Bauspenglerei Sanit\u00e4r, Heizungs U L\u00fcftungsinstallation",
    "sg:phone":"+41 34 402 11 14",
    "sg:postcode":"6512",
    "sg:province":"Ticino",
    "wof:name":"Lauber P., Inhaber K\u00fchni J.",
    "wof:placetype":"venue"
},
  "geometry": {"coordinates":[7.75759,46.949127],"type":"Point"}
}