{
  "type": "Feature",
  "properties": {
    "iso:country":"CH",
    "sg:address":"Chemin Des Gavardes 11 1073 Savigny Case Postale 67",
    "sg:city":"Savigny",
    "sg:orig_category":"Ger\u00fcstbau Sonstiger spezialisierter Hoch U Tiefbau",
    "sg:phone":"+41 21 652 88 48",
    "sg:postcode":"1073",
    "sg:province":"Vaud",
    "wof:name":"Pirali Chauvet Montage Sa",
    "wof:placetype":"venue"
},
  "geometry": {"coordinates":[6.7101898193,46.540802002],"type":"Point"}
}