{
  "type": "Feature",
  "properties": {
    "iso:country":"CH",
    "sg:address":"Rue Du Village 32",
    "sg:city":"Ch\u00e2telard-lutry",
    "sg:orig_category":"Herstellung von K\u00fcchenm\u00f6beln Rebbau",
    "sg:phone":"+41 21 791 17 92",
    "sg:postcode":"1095",
    "sg:province":"Vaud",
    "wof:name":"Chevalley Andr\u00e9",
    "wof:placetype":"venue"
},
  "geometry": {"coordinates":[6.6943531036,46.5074462891],"type":"Point"}
}