{
  "type": "Feature",
  "properties": {
    "iso:country":"CH",
    "sg:address":"K\u00f6nizstrasse 194 3097 Liebefeld. Postfach",
    "sg:city":"Liebefeld",
    "sg:orig_category":"Unclassifiable Establishments",
    "sg:postcode":"3097",
    "sg:province":"Bern",
    "wof:name":"Ws-holding Ag Liebefeld",
    "wof:placetype":"venue"
},
  "geometry": {"coordinates":[7.4146318436,46.9333114624],"type":"Point"}
}