{
  "type": "Feature",
  "properties": {
    "iso:country":"CH",
    "sg:address":"Via Ciseri 19",
    "sg:city":"Locarno",
    "sg:orig_category":"RESTAURANTS: TEA-ROOMS",
    "sg:phone":"+41 91 752 15 80",
    "sg:postcode":"6600",
    "sg:province":"Ticino",
    "wof:name":"Bar-rosticceria Gipsy S.a.g.l.",
    "wof:placetype":"venue"
},
  "geometry": {"coordinates":[8.796672821,46.1685409546],"type":"Point"}
}