{
  "type": "Feature",
  "properties": {
    "iso:country":"CH",
    "sg:address":"Bahnhofstrasse 3900 Brig. Postfach 648",
    "sg:city":"Brig",
    "sg:orig_category":"Wirtschaftspr\u00fcfung, Steuerberatung U Treuhand",
    "sg:phone":"+41 27 922 20 50",
    "sg:postcode":"3900",
    "sg:province":"Valais",
    "wof:name":"Dr. Viktor K\u00c4mpfen Treuhand Ag Revisionen, Bilanz- U Steuerberatungen Usw",
    "wof:placetype":"venue"
},
  "geometry": {"coordinates":[7.9882102013,46.3184509277],"type":"Point"}
}