{
  "type": "Feature",
  "properties": {
    "iso:country":"CH",
    "sg:address":"Dorfstrasse 24 2545 Selzach. Postfach",
    "sg:city":"Selzach",
    "sg:orig_category":"Detailhandel mit Brot, Back U S\u00fcsswaren",
    "sg:phone":"+41 32 641 10 42",
    "sg:postcode":"2545",
    "sg:province":"Solothurn",
    "wof:name":"Dubach Erich",
    "wof:placetype":"venue"
},
  "geometry": {"coordinates":[7.454121,47.205441],"type":"Point"}
}