{
  "type": "Feature",
  "properties": {
    "iso:country":"CH",
    "sg:address":"Badener-landstrasse 17",
    "sg:city":"Rafz",
    "sg:orig_category":"Fahrschulen, Flugschulen",
    "sg:phone":"+41 18693040",
    "sg:postcode":"8197",
    "sg:province":"Z\u00fcrich",
    "wof:name":"Markus Ammann Auto-& Motorrad-fahrschule",
    "wof:placetype":"venue"
},
  "geometry": {"coordinates":[8.5353851318,47.6099433899],"type":"Point"}
}