{
  "type": "Feature",
  "properties": {
    "iso:country":"CH",
    "sg:address":"Lindenstrasse 20 8302 Kloten. Postfach",
    "sg:city":"Kloten",
    "sg:orig_category":"G\u00fcterbef\u00f6rderung im Strassenverkehr Lagerung",
    "sg:phone":"+41 18137858",
    "sg:postcode":"8302",
    "sg:province":"Z\u00fcrich",
    "wof:name":"Lagerhaus Kloten Ag",
    "wof:placetype":"venue"
},
  "geometry": {"coordinates":[8.5844049454,47.4489479065],"type":"Point"}
}