{
  "type": "Feature",
  "properties": {
    "iso:country":"CH",
    "sg:address":"R\u00fcttistrasse 9 1716 Plaffeien. Postfach 563",
    "sg:city":"Plaffeien",
    "sg:orig_category":"Oberfl\u00e4chenveredlung U W\u00e4rmebehandlung",
    "sg:phone":"+41 26 419 90 90",
    "sg:postcode":"1716",
    "sg:province":"Fribourg",
    "wof:name":"Extramet Ag",
    "wof:placetype":"venue"
},
  "geometry": {"coordinates":[7.2911381721,46.7316513062],"type":"Point"}
}