{
  "type": "Feature",
  "properties": {
    "iso:country":"CH",
    "sg:address":"La Vieille-forge",
    "sg:city":"Froideville",
    "sg:orig_category":"Arztpraxen",
    "sg:phone":"+41 21 881 21 21",
    "sg:postcode":"1055",
    "sg:province":"Vaud",
    "wof:name":"Dr M\u00e9d. Pierre-alain Nicod M\u00e9decin G\u00e9n\u00e9raliste Fmh",
    "wof:placetype":"venue"
},
  "geometry": {"coordinates":[6.681076,46.60078],"type":"Point"}
}