{
  "type": "Feature",
  "properties": {
    "iso:country":"CH",
    "sg:address":"Bahnhofstrasse 2",
    "sg:city":"Lyss",
    "sg:orig_category":"Detailhandel mit Bekleidung",
    "sg:postcode":"3250",
    "sg:province":"Bern",
    "wof:name":"Boutique Zorro Di Muro Bekleidung; Handel U. Verkauf",
    "wof:placetype":"venue"
},
  "geometry": {"coordinates":[7.238204,46.903625],"type":"Point"}
}