{
  "type": "Feature",
  "properties": {
    "iso:country":"CH",
    "sg:address":"Unterb\u00fchlenstrasse 12",
    "sg:city":"Uster",
    "sg:orig_category":"Arztpraxen",
    "sg:phone":"+41 19400356",
    "sg:postcode":"8610",
    "sg:province":"Z\u00fcrich",
    "wof:name":"Dr.med.heinz Thalmann Arzt F.allgemeine Medizin Fmh",
    "wof:placetype":"venue"
},
  "geometry": {"coordinates":[8.706547,47.343494],"type":"Point"}
}