{
  "type": "Feature",
  "properties": {
    "iso:country":"CH",
    "sg:address":"Route De Founex 10",
    "sg:city":"Commugny",
    "sg:orig_category":"Grosshandel mit Sportartikeln Grosshandel mit Textilien",
    "sg:phone":"+41 22 776 75 24",
    "sg:postcode":"1291",
    "sg:province":"Vaud",
    "wof:name":"Panik System Jean-paul Sironi Distribution Articles De Sport",
    "wof:placetype":"venue"
},
  "geometry": {"coordinates":[6.1808009148,46.3211250305],"type":"Point"}
}