{
  "type": "Feature",
  "properties": {
    "iso:country":"CH",
    "sg:address":"Poststrasse 160 8957 Spreitenbach. Postfach",
    "sg:city":"Spreitenbach",
    "sg:orig_category":"Sonstige mit der Informatik verbundene T\u00e4tigkeiten",
    "sg:postcode":"8957",
    "sg:province":"Aargau",
    "wof:name":"Seifried Project Consulting Gmbh Edv; Beratung, Dienstl., Projektrealisationen. Entwicklung Von Software Usw",
    "wof:placetype":"venue"
},
  "geometry": {"coordinates":[8.3587093353,47.4268493652],"type":"Point"}
}