{
  "type": "Feature",
  "properties": {
    "iso:country":"CH",
    "sg:address":"Oberseestrasse 22",
    "sg:city":"Rapperswil",
    "sg:classifiers":[
        {
            "category":"Internet Cafe",
            "subcategory":"None",
            "type":"Food & Drink"
        }
    ],
    "sg:phone":"+41 55 220 04 04",
    "sg:postcode":"8640",
    "sg:province":"Schwyz",
    "sg:tags":[
        "provider"
    ],
    "wof:name":"Hostpoint Gmbh",
    "wof:placetype":"venue"
},
  "geometry": {"coordinates":[8.8192739487,47.2238578796],"type":"Point"}
}