{
  "type": "Feature",
  "properties": {
    "iso:country":"CH",
    "sg:address":"Ilgenweidstrasse",
    "sg:city":"Einsiedeln",
    "sg:orig_category":"RESTAURANTS: TEA-ROOMS",
    "sg:phone":"+41 55 412 59 09",
    "sg:postcode":"8840",
    "sg:province":"Schwyz",
    "wof:name":"Styger Geschwister",
    "wof:placetype":"venue"
},
  "geometry": {"coordinates":[8.7482376099,47.1254272461],"type":"Point"}
}