{
  "type": "Feature",
  "properties": {
    "iso:country":"CH",
    "sg:address":"Avenue De Montbenon 2 1000 Lausanne. Postfach",
    "sg:city":"Lausanne",
    "sg:orig_category":"Sonstige mit Sport verbundene T\u00e4tigkeiten",
    "sg:postcode":"1003",
    "sg:province":"Vaud",
    "wof:name":"Fondation Moves Mouvement Ethique & Sport",
    "wof:placetype":"venue"
},
  "geometry": {"coordinates":[6.6285300255,46.5197067261],"type":"Point"}
}