{
  "type": "Feature",
  "properties": {
    "iso:country":"CH",
    "sg:address":"Via Pestariso",
    "sg:city":"Agno",
    "sg:orig_category":"Betrieb von Sportanlagen",
    "sg:phone":"+41 91 604 51 16",
    "sg:postcode":"6982",
    "sg:province":"Ticino",
    "wof:name":"Atlantide Sa",
    "wof:placetype":"venue"
},
  "geometry": {"coordinates":[8.90472,46.00016],"type":"Point"}
}