{
  "type": "Feature",
  "properties": {
    "iso:country":"CH",
    "sg:address":"Bettlachstr. 230",
    "sg:city":"Grenchen",
    "sg:classifiers":[
        {
            "category":"Manufacturing",
            "subcategory":"Metals",
            "type":"Manufacturing & Wholesale Goods"
        }
    ],
    "sg:phone":"+41 32 644 33 11",
    "sg:postcode":"2540",
    "sg:province":"Solothurn",
    "sg:tags":[
        "metallurgy",
        "metalworking",
        "processing"
    ],
    "wof:name":"Heinz H\u00c4nggi Ag",
    "wof:placetype":"venue"
},
  "geometry": {"coordinates":[7.4093208313,47.1972312927],"type":"Point"}
}