{
  "type": "Feature",
  "properties": {
    "iso:country":"CH",
    "sg:address":"Bernstrasse 143",
    "sg:city":"Rothrist",
    "sg:orig_category":"Interessenvertretungen",
    "sg:postcode":"4852",
    "sg:province":"Aargau",
    "wof:name":"Pro Fachgesch\u00e4fte Region Zofingen",
    "wof:placetype":"venue"
},
  "geometry": {"coordinates":[7.8857359886,47.3050346375],"type":"Point"}
}