{
  "type": "Feature",
  "properties": {
    "iso:country":"CH",
    "sg:address":"Chemin De La Joliette 4",
    "sg:city":"Lausanne",
    "sg:orig_category":"Allgemeiner Hoch U Tiefbau Strassenbau",
    "sg:phone":"+41 17131728",
    "sg:postcode":"1006",
    "sg:province":"Vaud",
    "wof:name":"Bachmann Walter Bauunternehmung Ag",
    "wof:placetype":"venue"
},
  "geometry": {"coordinates":[8.542869,47.286087],"type":"Point"}
}