{
  "type": "Feature",
  "properties": {
    "iso:country":"CH",
    "sg:address":"4601 Olten. Postfach 661",
    "sg:city":"Olten",
    "sg:orig_category":"Sportvereine Ballsport Fussball",
    "sg:phone":"+41 62 296 69 04",
    "sg:postcode":"4601",
    "sg:province":"Solothurn",
    "wof:name":"Fc Olten",
    "wof:placetype":"venue"
},
  "geometry": {"coordinates":[7.902589798,47.3501014709],"type":"Point"}
}