{
  "type": "Feature",
  "properties": {
    "iso:country":"CH",
    "sg:address":"Gundeldingerstrasse 171",
    "sg:city":"Basel",
    "sg:orig_category":"Grosshandel mit chemischen Erzeugnissen",
    "sg:postcode":"4053",
    "sg:province":"Basel-Stadt",
    "wof:name":"Prodan Ag",
    "wof:placetype":"venue"
},
  "geometry": {"coordinates":[7.5893268585,47.5413627625],"type":"Point"}
}