{
  "type": "Feature",
  "properties": {
    "iso:country":"CH",
    "sg:address":"Scheideggstrasse 12",
    "sg:city":"Winterthur",
    "sg:orig_category":"Kinderkrippen U horte",
    "sg:phone":"+41 52 232 15 52",
    "sg:postcode":"8400",
    "sg:province":"Z\u00fcrich",
    "wof:name":"Hort Im Kindergarten Gutschick I",
    "wof:placetype":"venue"
},
  "geometry": {"coordinates":[8.7501869202,47.4919433594],"type":"Point"}
}