{
  "type": "Feature",
  "properties": {
    "iso:country":"CH",
    "sg:address":"Vordergasse 26",
    "sg:city":"Schaffhausen",
    "sg:orig_category":"Konkurs- and Betreibungs\u00e4mter",
    "sg:phone":"+41 52 632 54 60",
    "sg:postcode":"8200",
    "sg:province":"Schaffhausen",
    "wof:name":"Betreibungs-& Konkursamt",
    "wof:placetype":"venue"
},
  "geometry": {"coordinates":[8.6368017197,47.6961631775],"type":"Point"}
}