{
  "type": "Feature",
  "properties": {
    "iso:country":"CH",
    "sg:address":"Route De Rionda 12 3968 Veyras Case Postale 361",
    "sg:city":"Sierre",
    "sg:orig_category":"Feinmechanische and Pr\u00e4zisions Werkst\u00e4tten Landwirtschaftliche Maschinen Wartung and Reparatur",
    "sg:phone":"+41 27 455 10 01",
    "sg:postcode":"3960",
    "sg:province":"Valais",
    "wof:name":"M\u00e9catron Sa",
    "wof:placetype":"venue"
},
  "geometry": {"coordinates":[7.5365557671,46.2990341187],"type":"Point"}
}