{
  "type": "Feature",
  "properties": {
    "iso:country":"CH",
    "sg:address":"Gartenweg 10 8604 Volketswil. Postfach",
    "sg:city":"Volketswil",
    "sg:orig_category":"Unclassifiable Establishments",
    "sg:postcode":"8604",
    "sg:province":"Z\u00fcrich",
    "wof:name":"Artemis Cosmetics Lutovski Marzia Nagel- U. Hautkosmetik",
    "wof:placetype":"venue"
},
  "geometry": {"coordinates":[8.673822403,47.3882331848],"type":"Point"}
}