{
  "type": "Feature",
  "properties": {
    "iso:country":"CH",
    "sg:address":"Tirggelweg 3",
    "sg:city":"Sch\u00f6nenberg",
    "sg:classifiers":[
        {
            "category":"Wholesale",
            "subcategory":"Vending Machines",
            "type":"Manufacturing & Wholesale Goods"
        }
    ],
    "sg:phone":"+41 17881618",
    "sg:postcode":"8824",
    "sg:province":"Z\u00fcrich",
    "sg:tags":[
        "packing",
        "automatic",
        "machines"
    ],
    "wof:name":"Peter Seibold Verpackungsmaschinen",
    "wof:placetype":"venue"
},
  "geometry": {"coordinates":[8.6439437866,47.1902008057],"type":"Point"}
}