{
  "type": "Feature",
  "properties": {
    "iso:country":"CH",
    "sg:address":"Brislachstrasse 12b",
    "sg:city":"Laufen",
    "sg:orig_category":"Sonstige pers\u00f6nliche Dienstleistungen",
    "sg:postcode":"4242",
    "sg:province":"Basel-Landschaft",
    "wof:name":"Hess + Steiner Gmbh",
    "wof:placetype":"venue"
},
  "geometry": {"coordinates":[7.5056681633,47.4190597534],"type":"Point"}
}