{
  "type": "Feature",
  "properties": {
    "iso:country":"CH",
    "sg:address":"Zentralstrasse 8",
    "sg:city":"Volketswil",
    "sg:orig_category":"Grosshandel mit B\u00fcromaschinen Grosshandel mit Datenverarbeitungsger\u00e4ten",
    "sg:phone":"+41 62 867 20 52",
    "sg:postcode":"8604",
    "sg:province":"Z\u00fcrich",
    "wof:name":"Bielec S.a.",
    "wof:placetype":"venue"
},
  "geometry": {"coordinates":[8.1552801132,47.5617485046],"type":"Point"}
}