{
  "type": "Feature",
  "properties": {
    "iso:country":"CH",
    "sg:address":"Rue Du Cr\u00e8t 16",
    "sg:city":"Biel/bienne",
    "sg:orig_category":"Pensionskassen",
    "sg:postcode":"2500",
    "sg:province":"Bern",
    "wof:name":"Fonds De Pr\u00e9voyance En Faveur Du Personnel De Roventa-henex Sa, Fabrique D'horlogerie",
    "wof:placetype":"venue"
},
  "geometry": {"coordinates":[7.256289959,47.1333656311],"type":"Point"}
}