{
  "type": "Feature",
  "properties": {
    "iso:country":"CH",
    "sg:address":"Hummelbergstrasse 21",
    "sg:city":"Jona",
    "sg:orig_category":"Unternehmensberatung",
    "sg:postcode":"8645",
    "sg:province":"St. Gallen",
    "wof:name":"Schmid Beratungen",
    "wof:placetype":"venue"
},
  "geometry": {"coordinates":[8.8531332016,47.2315788269],"type":"Point"}
}