{
  "type": "Feature",
  "properties": {
    "iso:country":"CH",
    "sg:address":"Grubenstrasse 11",
    "sg:city":"Z\u00fcrich",
    "sg:orig_category":"Grosshandel mit B\u00fcromaschinen Grosshandel mit Datenverarbeitungsger\u00e4ten",
    "sg:phone":"+41 22 301 12 20",
    "sg:postcode":"8045",
    "sg:province":"Z\u00fcrich",
    "wof:name":"Multim\u00e9dias Diffusion R.reber Informatique",
    "wof:placetype":"venue"
},
  "geometry": {"coordinates":[6.1434750557,46.1856079102],"type":"Point"}
}