{
  "type": "Feature",
  "properties": {
    "iso:country":"CH",
    "sg:address":"Thundorferstrasse 110",
    "sg:city":"Frauenfeld",
    "sg:classifiers":[
        {
            "category":"Restaurant",
            "type":"Food & Drink"
        }
    ],
    "sg:phone":"+41 52 721 22 30",
    "sg:postcode":"8500",
    "sg:province":"Thurgau",
    "wof:name":"Restaurant Obstgarten Huben",
    "wof:placetype":"venue"
},
  "geometry": {"coordinates":[8.9089174271,47.5476646423],"type":"Point"}
}