{
  "type": "Feature",
  "properties": {
    "iso:country":"CH",
    "sg:address":"Kantonsstrasse 88",
    "sg:city":"Uffikon",
    "sg:orig_category":"Bauschreinerei Herstellung von Konstruktionsteilen, Fertigbauteilen U Ausbauelementen aus Holz",
    "sg:phone":"+41 62 756 31 36",
    "sg:postcode":"6253",
    "sg:province":"Luzern",
    "wof:name":"Zemp Alfred Bau Und M\u00f6belschreinerei",
    "wof:placetype":"venue"
},
  "geometry": {"coordinates":[8.015797,47.210548],"type":"Point"}
}