{
  "type": "Feature",
  "properties": {
    "iso:country":"CH",
    "sg:address":"Ruedenweg 5",
    "sg:city":"Boll",
    "sg:orig_category":"Detailhandel mit Metallwaren, Anstrichmitteln, Glaswaren, Bau U Heimwerkerbedarf",
    "sg:phone":"+41 31393971",
    "sg:postcode":"3067",
    "sg:province":"Bern",
    "wof:name":"Widmer H. R., Ing. Htl",
    "wof:placetype":"venue"
},
  "geometry": {"coordinates":[7.546353817,46.9590759277],"type":"Point"}
}