{
  "type": "Feature",
  "properties": {
    "addr:full":"Unterm\u00fcli 7 Zug Zug 6300",
    "addr:housenumber":"7",
    "addr:postcode":"6300",
    "addr:street":"Untermueli;Zug",
    "iso:country":"CH",
    "sg:address":"Unterm\u00fcli 7",
    "sg:city":"Zug",
    "sg:orig_category":"Betrieb von Sportanlagen",
    "sg:postcode":"6300",
    "sg:province":"Zug",
    "wof:name":"Genossenschaft Eiszentrum Zugerland",
    "wof:placetype":"venue"
},
  "geometry": {"coordinates":[8.517702,47.180416],"type":"Point"}
}