{
  "type": "Feature",
  "properties": {
    "iso:country":"CH",
    "sg:address":"Industriestrasse 9 6345 Neuheim. Postfach",
    "sg:city":"Neuheim",
    "sg:orig_category":"Autospenglereien Instandhaltung U Reparatur von Automobilen",
    "sg:phone":"+41 41 755 05 69",
    "sg:postcode":"6345",
    "sg:province":"Zug",
    "wof:name":"Carrosserie Steiner Rolf Pw-fahrzeuge; Reparatur",
    "wof:placetype":"venue"
},
  "geometry": {"coordinates":[8.577177,47.202526],"type":"Point"}
}