{
  "type": "Feature",
  "properties": {
    "iso:country":"CH",
    "sg:address":"Quellenstrasse 2 8005 Z\u00fcrich. Postfach",
    "sg:city":"Z\u00fcrich",
    "sg:orig_category":"Softwareentwicklung U beratung",
    "sg:phone":"+41 18307696",
    "sg:postcode":"8005",
    "sg:province":"Z\u00fcrich",
    "wof:name":"Incaa Services Ag",
    "wof:placetype":"venue"
},
  "geometry": {"coordinates":[8.5275373459,47.3840370178],"type":"Point"}
}