{
  "type": "Feature",
  "properties": {
    "iso:country":"CH",
    "sg:address":"Parkstrasse 4",
    "sg:city":"Goldau",
    "sg:orig_category":"Detailhandel mit Teppichen Verlegen von Fussboden",
    "sg:phone":"+41 79 435 51 08",
    "sg:postcode":"6410",
    "sg:province":"Schwyz",
    "wof:name":"Peter Guler Teppiche & Novilon",
    "wof:placetype":"venue"
},
  "geometry": {"coordinates":[8.5481042862,47.0496559143],"type":"Point"}
}