{
  "type": "Feature",
  "properties": {
    "iso:country":"CH",
    "sg:address":"Court-chemin 18",
    "sg:city":"Fribourg",
    "sg:orig_category":"Fahrschulen, Flugschulen",
    "sg:phone":"+41 26 322 24 73",
    "sg:postcode":"1700",
    "sg:province":"Fribourg",
    "wof:name":"Emerick Wicky Auto-\u00e9cole",
    "wof:placetype":"venue"
},
  "geometry": {"coordinates":[7.1606621742,46.804397583],"type":"Point"}
}