{
  "type": "Feature",
  "properties": {
    "iso:country":"CH",
    "sg:address":"Lettenackerstrasse 13",
    "sg:city":"Hedingen",
    "sg:orig_category":"Vereine Frauen Vereine Gemeinn\u00fctzige",
    "sg:phone":"+41 17616556",
    "sg:postcode":"8908",
    "sg:province":"Z\u00fcrich",
    "wof:name":"Frauenverein Hedingen",
    "wof:placetype":"venue"
},
  "geometry": {"coordinates":[8.4505968094,47.2933616638],"type":"Point"}
}