{
  "type": "Feature",
  "properties": {
    "iso:country":"CH",
    "sg:address":"Viktoriastrasse 5 3900 Brig. Postfach",
    "sg:city":"Brig",
    "sg:orig_category":"Gesundheitswesen",
    "sg:postcode":"3900",
    "sg:province":"Valais",
    "wof:name":"Praxis F\u00fcr Traditionelle Chinesische Medizin, Jossen Yann",
    "wof:placetype":"venue"
},
  "geometry": {"coordinates":[7.9869260788,46.3186912537],"type":"Point"}
}