{
  "type": "Feature",
  "properties": {
    "iso:country":"CH",
    "sg:address":"Feldlistrasse 9",
    "sg:city":"Jona",
    "sg:orig_category":"Fachdetailhandel in Verkaufsr\u00e4umen",
    "sg:postcode":"8645",
    "sg:province":"St. Gallen",
    "wof:name":"Bury Mato, Handel-service",
    "wof:placetype":"venue"
},
  "geometry": {"coordinates":[8.8480138779,47.2288284302],"type":"Point"}
}