{
  "type": "Feature",
  "properties": {
    "iso:country":"CH",
    "sg:address":"Stansstaderstrasse 54",
    "sg:city":"Stans",
    "sg:orig_category":"Unclassifiable Establishments",
    "sg:postcode":"6370",
    "sg:province":"Nidwalden",
    "wof:name":"Sirinidia Trading Ag",
    "wof:placetype":"venue"
},
  "geometry": {"coordinates":[8.3599538803,46.9624671936],"type":"Point"}
}