{
  "type": "Feature",
  "properties": {
    "iso:country":"CH",
    "sg:address":"Via G. Papa 1",
    "sg:city":"Biasca",
    "sg:orig_category":"Bauschreinerei Herstellung von M\u00f6beln verschiedener Art",
    "sg:phone":"+41 91 945 10 88",
    "sg:postcode":"6710",
    "sg:province":"Ticino",
    "wof:name":"Sergio Lotti Posa Serramenti & Mobili",
    "wof:placetype":"venue"
},
  "geometry": {"coordinates":[8.95034,46.061974],"type":"Point"}
}