{
  "type": "Feature",
  "properties": {
    "addr:full":"Flughafen Airport Z\u00fcrich Z\u00fcrich 8058",
    "addr:postcode":"8058",
    "iso:country":"CH",
    "sg:address":"Flughafen Airport",
    "sg:city":"Z\u00fcrich",
    "sg:classifiers":[
        {
            "category":"Banks & Credit Unions",
            "subcategory":"Bank",
            "type":"Services"
        }
    ],
    "sg:phone":"+41 18043711",
    "sg:postcode":"8058",
    "sg:province":"Z\u00fcrich",
    "wof:name":"Credit Suisse",
    "wof:placetype":"venue"
},
  "geometry": {"coordinates":[8.573952,47.453075],"type":"Point"}
}