{
  "type": "Feature",
  "properties": {
    "iso:country":"CH",
    "sg:address":"Birch 45",
    "sg:city":"Gontenschwil",
    "sg:orig_category":"Politische Parteien SP",
    "sg:phone":"+41 62 773 14 38",
    "sg:postcode":"5728",
    "sg:province":"Aargau",
    "wof:name":"Sp Ortspartei Gontenschwil",
    "wof:placetype":"venue"
},
  "geometry": {"coordinates":[8.1386823654,47.2785644531],"type":"Point"}
}