{
  "type": "Feature",
  "properties": {
    "iso:country":"CH",
    "sg:address":"Bahnhofstrasse 8",
    "sg:city":"Biel/bienne",
    "sg:orig_category":"Detailhandel mit Parf\u00fcmerieartikeln U K\u00f6rperpflegemitteln Parf\u00fcmerien U sonstiger Detailhandel mit k",
    "sg:phone":"+41 32 322 08 22",
    "sg:postcode":"2502",
    "sg:province":"Bern",
    "wof:name":"Parfumerie Prati Erica",
    "wof:placetype":"venue"
},
  "geometry": {"coordinates":[7.2440037727,47.1329078674],"type":"Point"}
}