{
  "type": "Feature",
  "properties": {
    "iso:country":"CH",
    "sg:address":"Avenue Mayor-vautier 19",
    "sg:city":"Clarens",
    "sg:orig_category":"W\u00e4scherei U chemische Reinigung",
    "sg:phone":"+41 21 964 58 95",
    "sg:postcode":"1815",
    "sg:province":"Vaud",
    "wof:name":"Le Rideau-neuf St\u00e4uble Philippe.",
    "wof:placetype":"venue"
},
  "geometry": {"coordinates":[6.89311409,46.4423294067],"type":"Point"}
}