{
  "type": "Feature",
  "properties": {
    "iso:country":"CH",
    "sg:address":"Lerchenweg 13",
    "sg:city":"Rotkreuz",
    "sg:orig_category":"Sonstiger Grosshandel Vermietung von sonstigen Maschinen U Ger\u00e4ten",
    "sg:phone":"+41 41 790 68 20",
    "sg:postcode":"6343",
    "sg:province":"Zug",
    "wof:name":"Steinemann Ag Spielautomaten",
    "wof:placetype":"venue"
},
  "geometry": {"coordinates":[8.4349431992,47.1386833191],"type":"Point"}
}