{
  "type": "Feature",
  "properties": {
    "iso:country":"CH",
    "sg:address":"Lerchenfeldstrasse 54",
    "sg:city":"Thun",
    "sg:orig_category":"Detailhandel mit M\u00f6beln U Haushaltsgegenst\u00e4nden",
    "sg:phone":"+41 79 651 07 32",
    "sg:postcode":"3603",
    "sg:province":"Bern",
    "wof:name":"Nydegger Interieur Ag",
    "wof:placetype":"venue"
},
  "geometry": {"coordinates":[7.5991711617,46.7639923096],"type":"Point"}
}