{
  "type": "Feature",
  "properties": {
    "iso:country":"CH",
    "sg:address":"Charpilloz Rue Aim\u00e9- 11 2735 B\u00e9vilard. Postfach",
    "sg:city":"B\u00e9vilard",
    "sg:orig_category":"RESTAURANTS: TEA-ROOMS",
    "sg:postcode":"2735",
    "sg:province":"Bern",
    "wof:name":"Corsano-nanni Ornella",
    "wof:placetype":"venue"
},
  "geometry": {"coordinates":[7.2859349251,47.2373695374],"type":"Point"}
}