{
  "type": "Feature",
  "properties": {
    "iso:country":"CH",
    "sg:address":"Niderwil",
    "sg:city":"Cham",
    "sg:orig_category":"Zimmerei, Dachdeckerei, Bauspenglerei U Abdichtung",
    "sg:phone":"+41 41 781 02 24",
    "sg:postcode":"6330",
    "sg:province":"Zug",
    "wof:name":"Georges Helfenstein Gmbh",
    "wof:placetype":"venue"
},
  "geometry": {"coordinates":[8.4490251541,47.2128868103],"type":"Point"}
}