{
  "type": "Feature",
  "properties": {
    "iso:country":"CH",
    "sg:address":"Dorfstrasse 10",
    "sg:city":"Leuzigen",
    "sg:orig_category":"Gemeindeverwaltungen",
    "sg:phone":"+41 32 679 21 10",
    "sg:postcode":"3297",
    "sg:province":"Bern",
    "wof:name":"Gemeindeverwaltung Leuzigen",
    "wof:placetype":"venue"
},
  "geometry": {"coordinates":[7.4598441124,47.1739082336],"type":"Point"}
}