{
  "type": "Feature",
  "properties": {
    "iso:country":"CH",
    "sg:address":"Oberdorf 7",
    "sg:city":"Treiten",
    "sg:orig_category":"Gem\u00fcsebau",
    "sg:phone":"+41 32 313 22 54",
    "sg:postcode":"3226",
    "sg:province":"Bern",
    "wof:name":"Armin Baumberger Gem\u00fcsebau",
    "wof:placetype":"venue"
},
  "geometry": {"coordinates":[7.1621599197,47.0094070435],"type":"Point"}
}