{
  "type": "Feature",
  "properties": {
    "iso:country":"CH",
    "sg:address":"Via Adamini 21",
    "sg:city":"Lugano",
    "sg:orig_category":"Betrieb von Taxis",
    "sg:phone":"+41 91 993 32 32",
    "sg:postcode":"6900",
    "sg:province":"Ticino",
    "wof:name":"Liliana Perini-bairactarova Taxi Limousine",
    "wof:placetype":"venue"
},
  "geometry": {"coordinates":[8.944239,45.997433],"type":"Point"}
}