{
  "type": "Feature",
  "properties": {
    "iso:country":"CH",
    "sg:address":"T\u00f6sstalstrasse 12",
    "sg:city":"Winterthur",
    "sg:orig_category":"Unclassifiable Establishments",
    "sg:postcode":"8400",
    "sg:province":"Z\u00fcrich",
    "wof:name":"Hanorex Aktiengesellschaft",
    "wof:placetype":"venue"
},
  "geometry": {"coordinates":[8.6907100677,47.2693214417],"type":"Point"}
}