{
  "type": "Feature",
  "properties": {
    "iso:country":"CH",
    "sg:address":"Lagerstrasse 1 8004 Z\u00fcrich. Postfach",
    "sg:city":"Z\u00fcrich",
    "sg:classifiers":[
        {
            "category":"Restaurant",
            "type":"Food & Drink"
        }
    ],
    "sg:phone":"+41 12425320",
    "sg:postcode":"8021",
    "sg:province":"Z\u00fcrich",
    "sg:tags":[
        "tea-rooms",
        "restaurants"
    ],
    "wof:name":"Restaurant Clipper, Kopp E.",
    "wof:placetype":"venue"
},
  "geometry": {"coordinates":[8.5344638824,47.3765945435],"type":"Point"}
}