{
  "type": "Feature",
  "properties": {
    "iso:country":"CH",
    "sg:address":"Stauffacherstrasse 26 3014 Bern. Postfach",
    "sg:city":"Bern",
    "sg:orig_category":"Sonstige pers\u00f6nliche Dienstleistungen",
    "sg:postcode":"3005",
    "sg:province":"Bern",
    "wof:name":"Kunst B. Baeren Gorsatt P.k.s.s. Objekt- U. Installationskunst; Produktion U. Vertrieb",
    "wof:placetype":"venue"
},
  "geometry": {"coordinates":[7.4549069405,46.9619407654],"type":"Point"}
}