{
  "type": "Feature",
  "properties": {
    "iso:country":"CH",
    "sg:address":"Hallwylstrasse 48",
    "sg:city":"Bern",
    "sg:orig_category":"Wirtschaft U Handel, Wirtschaftliche Beratungsdienste",
    "sg:phone":"+41 31 352 83 33",
    "sg:postcode":"3005",
    "sg:province":"Bern",
    "wof:name":"Treuhand & Verwaltungs Ag Bern",
    "wof:placetype":"venue"
},
  "geometry": {"coordinates":[7.454895,46.941513],"type":"Point"}
}