{
  "type": "Feature",
  "properties": {
    "iso:country":"CH",
    "sg:address":"Bahnhofstrasse 13",
    "sg:city":"Lotzwil",
    "sg:orig_category":"RESTAURANTS: TEA-ROOMS",
    "sg:postcode":"4932",
    "sg:province":"Bern",
    "wof:name":"Jakob Heidi",
    "wof:placetype":"venue"
},
  "geometry": {"coordinates":[7.789085865,47.189163208],"type":"Point"}
}