{
  "type": "Feature",
  "properties": {
    "iso:country":"CH",
    "sg:address":"L\u00e4ngenbergstrasse 3-5",
    "sg:city":"Schaffhausen",
    "sg:orig_category":"Pipes, Resistant To Chemicals",
    "sg:phone":"+41 52 643 52 25",
    "sg:postcode":"8200",
    "sg:province":"Schaffhausen",
    "wof:name":"Geba-plast Ag",
    "wof:placetype":"venue"
},
  "geometry": {"coordinates":[8.6323461533,47.7258491516],"type":"Point"}
}