{
  "type": "Feature",
  "properties": {
    "iso:country":"CH",
    "sg:address":"Buchenweg 22 3012 Bern. Postfach",
    "sg:city":"Bern",
    "sg:orig_category":"Unternehmensberatung",
    "sg:postcode":"3005",
    "sg:province":"Bern",
    "wof:name":"Gebert Dr. A. Consulting. Wirkungsbeurteilung F. Private U. \u00f6ffentl. Unternehmen.",
    "wof:placetype":"venue"
},
  "geometry": {"coordinates":[7.4243130684,46.9554443359],"type":"Point"}
}