{
  "type": "Feature",
  "properties": {
    "iso:country":"CH",
    "sg:address":"Gewerbezentrum Hirschen",
    "sg:city":"Oberehrendingen",
    "sg:orig_category":"Herstellung von sonstigen elektrischen Ausr\u00fcstungen",
    "sg:phone":"+41 56 221 21 20",
    "sg:postcode":"5422",
    "wof:name":"Profi Print Ag",
    "wof:placetype":"venue"
},
  "geometry": {"coordinates":[8.3418102264,47.4908294678],"type":"Point"}
}