{
  "type": "Feature",
  "properties": {
    "iso:country":"CH",
    "sg:address":"Vorderdorfstrasse 28",
    "sg:city":"Mollis",
    "sg:orig_category":"Detailhandel mit Waren verschiedener Art, Hauptrichtung Nahrungsmittel Grosshandel mit Nahrungsmitte",
    "sg:phone":"+41 55 612 12 88",
    "sg:postcode":"8753",
    "sg:province":"Glarus",
    "wof:name":"Gygli Lebensmittel Gmbh",
    "wof:placetype":"venue"
},
  "geometry": {"coordinates":[9.0744781494,47.0915184021],"type":"Point"}
}