{
  "type": "Feature",
  "properties": {
    "iso:country":"CH",
    "sg:address":"Bellefontaine Rue 8 1003 Lausanne. Postfach",
    "sg:city":"Lausanne",
    "sg:classifiers":[
        {
            "category":"Professional",
            "subcategory":"Employment Agencies",
            "type":"Services"
        }
    ],
    "sg:postcode":"1003",
    "sg:province":"Vaud",
    "sg:tags":[
        "personal",
        "u",
        "stellenvermittlung"
    ],
    "wof:name":"Cabinet Conseil Jfk - Fasel Juliette Conseil En Ressources Humaines, Recrutement De Cadres Et Personnel Sp\u00e9cialis\u00e9",
    "wof:placetype":"venue"
},
  "geometry": {"coordinates":[6.6390910149,46.5165519714],"type":"Point"}
}