{
  "type": "Feature",
  "properties": {
    "iso:country":"CH",
    "sg:address":"Rinikerstr. 19",
    "sg:city":"Remigen",
    "sg:orig_category":"Haltung von Rindern",
    "sg:postcode":"5236",
    "sg:province":"Aargau",
    "wof:name":"Fleckviehzuchtgenossenschaft Remigen",
    "wof:placetype":"venue"
},
  "geometry": {"coordinates":[8.1887845993,47.5144386292],"type":"Point"}
}