{
  "type": "Feature",
  "properties": {
    "iso:country":"CH",
    "sg:address":"Marktgasse 11 9220 Bischofszell. Postfach",
    "sg:city":"Bischofszell",
    "sg:orig_category":"Landesverteidigung, Sozialversicherung \u00d6ffentliche Verwaltung",
    "sg:phone":"+41 71 424 24 30",
    "sg:postcode":"9220",
    "sg:province":"Thurgau",
    "wof:name":"Zivilschutzstelle Bischofszell",
    "wof:placetype":"venue"
},
  "geometry": {"coordinates":[9.2397470474,47.4940338135],"type":"Point"}
}