{
  "type": "Feature",
  "properties": {
    "iso:country":"CH",
    "sg:address":"H\u00f4pital Cantonal 1700 Fribourg. Postfach",
    "sg:city":"Fribourg",
    "sg:orig_category":"Sonstiges Gesundheitswesen",
    "sg:phone":"+41 26 426 81 80",
    "sg:postcode":"1708",
    "sg:province":"Fribourg",
    "wof:name":"Centre De Transfusion Sanguine Croix-rouge Suisse",
    "wof:placetype":"venue"
},
  "geometry": {"coordinates":[7.1536831856,46.8037452698],"type":"Point"}
}