{
  "type": "Feature",
  "properties": {
    "iso:country":"CH",
    "sg:address":"Burgunderstrasse 1",
    "sg:city":"Basel",
    "sg:orig_category":"Massagestudios",
    "sg:phone":"+41 61 272 36 01",
    "sg:postcode":"4051",
    "sg:province":"Basel-Stadt",
    "wof:name":"Antoinette Osterwald Biodynamische Massage-praxis",
    "wof:placetype":"venue"
},
  "geometry": {"coordinates":[7.5807580948,47.5538330078],"type":"Point"}
}