{
  "type": "Feature",
  "properties": {
    "iso:country":"CH",
    "sg:address":"Unterb\u00f6singenstr. 314",
    "sg:city":"B\u00f6singen",
    "sg:orig_category":"Detailhandel mit Metallwaren, Anstrichmitteln, Glaswaren, Bau U Heimwerkerbedarf",
    "sg:postcode":"3178",
    "sg:province":"Fribourg",
    "wof:name":"Seeber Manuela, Spielhaus, Spiel Und Bastelbedarf F\u00fcr Spielgruppen",
    "wof:placetype":"venue"
},
  "geometry": {"coordinates":[7.2257699966,46.896900177],"type":"Point"}
}