{
  "type": "Feature",
  "properties": {
    "iso:country":"CH",
    "sg:address":"Kilchgrundstrasse 34",
    "sg:city":"Riehen",
    "sg:orig_category":"Physiotherapie",
    "sg:phone":"+41 79 329 57 78",
    "sg:postcode":"4125",
    "sg:province":"Basel-Stadt",
    "wof:name":"Verena Iten Physiotherapie",
    "wof:placetype":"venue"
},
  "geometry": {"coordinates":[7.5921840668,47.4910430908],"type":"Point"}
}