{
  "type": "Feature",
  "properties": {
    "iso:country":"CH",
    "sg:address":"Suisse Route 9",
    "sg:city":"Mies",
    "sg:orig_category":"Softwareentwicklung U beratung",
    "sg:phone":"+41 22 950 07 00",
    "sg:postcode":"1295",
    "sg:province":"Vaud",
    "wof:name":"Lartigue David R\u00e9solution",
    "wof:placetype":"venue"
},
  "geometry": {"coordinates":[6.1678080559,46.2968559265],"type":"Point"}
}