{
  "type": "Feature",
  "properties": {
    "addr:full":"Bahnhofstrasse 20 Wohlen Luzern 6110",
    "addr:housenumber":"20",
    "addr:postcode":"6110",
    "addr:street":"Bahnhofstrasse",
    "iso:country":"CH",
    "sg:address":"Bahnhofstrasse 20",
    "sg:city":"Wohlen",
    "sg:classifiers":[
        {
            "category":"Banks & Credit Unions",
            "subcategory":"Bank",
            "type":"Services"
        }
    ],
    "sg:phone":"+41 4141711333",
    "sg:postcode":"6110",
    "sg:province":"Luzern",
    "wof:name":"Schweiz. Bankverein",
    "wof:placetype":"venue"
},
  "geometry": {"coordinates":[8.27003,47.348854],"type":"Point"}
}