{
  "type": "Feature",
  "properties": {
    "addr:full":"Zelgli 16 Klingnau Aargau 5313",
    "addr:housenumber":"16",
    "addr:postcode":"5313",
    "addr:street":"Zelgli",
    "iso:country":"CH",
    "sg:address":"Zelgli 16",
    "sg:city":"Klingnau",
    "sg:orig_category":"Autogaragen",
    "sg:phone":"+41 41 870 83 26",
    "sg:postcode":"5313",
    "sg:province":"Aargau",
    "wof:name":"Walter Wicki Autogarage",
    "wof:placetype":"venue"
},
  "geometry": {"coordinates":[8.675268,46.877991],"type":"Point"}
}