{
  "type": "Feature",
  "properties": {
    "addr:full":"Les Maisons Neuves Yvorne Vaud 1853",
    "addr:housenumber":"1853",
    "iso:country":"CH",
    "sg:address":"Les Maisons Neuves",
    "sg:city":"Yvorne",
    "sg:orig_category":"Dachdeckerei Sanit\u00e4r, Heizungs U L\u00fcftungsinstallation",
    "sg:phone":"+41 24 466 28 38",
    "sg:postcode":"1853",
    "sg:province":"Vaud",
    "wof:name":"Mordasini G.",
    "wof:placetype":"venue"
},
  "geometry": {"coordinates":[6.959228,46.330917],"type":"Point"}
}