{
  "type": "Feature",
  "properties": {
    "iso:country":"CH",
    "sg:address":"Route Du Chavalard 89",
    "sg:city":"Fully",
    "sg:orig_category":"Instandhaltung U Reparatur von Automobilen",
    "sg:phone":"+41 27 746 26 12",
    "sg:postcode":"1926",
    "sg:province":"Valais",
    "wof:name":"Rouiller Yvon, Garage De Verdan.",
    "wof:placetype":"venue"
},
  "geometry": {"coordinates":[7.1188101768,46.1409301758],"type":"Point"}
}