{
  "type": "Feature",
  "properties": {
    "iso:country":"CH",
    "sg:address":"Gartematt 9",
    "sg:city":"B\u00fclach",
    "sg:orig_category":"Unclassifiable Establishments",
    "sg:postcode":"8180",
    "sg:province":"Z\u00fcrich",
    "wof:name":"Audiovision R. Fuchs",
    "wof:placetype":"venue"
},
  "geometry": {"coordinates":[8.5428199768,47.5186691284],"type":"Point"}
}