{
  "type": "Feature",
  "properties": {
    "iso:country":"CH",
    "sg:address":"Leisib\u00fchl 27",
    "sg:city":"Nunningen",
    "sg:orig_category":"Architektur U Ingenieurb\u00fcros",
    "sg:phone":"+41 17614766",
    "sg:postcode":"4208",
    "sg:province":"Solothurn",
    "wof:name":"Bruno Gautschi Technisches B\u00fcro",
    "wof:placetype":"venue"
},
  "geometry": {"coordinates":[8.444458,47.276264],"type":"Point"}
}