{
  "type": "Feature",
  "properties": {
    "iso:country":"CH",
    "sg:address":"Akazienstrasse 6",
    "sg:city":"M\u00fcnchenstein",
    "sg:orig_category":"Sportvereine Turnen Vereine Damen",
    "sg:postcode":"4142",
    "sg:province":"Basel-Landschaft",
    "wof:name":"Alemannia-turnerinnen Stv Bs",
    "wof:placetype":"venue"
},
  "geometry": {"coordinates":[7.6090750694,47.5152931213],"type":"Point"}
}