{
  "type": "Feature",
  "properties": {
    "iso:country":"CH",
    "sg:address":"Chemin Du Delay 9",
    "sg:city":"Vernier",
    "sg:orig_category":"G\u00fcterbef\u00f6rderung im Strassenverkehr",
    "sg:phone":"+41 22 341 36 20",
    "sg:postcode":"1214",
    "sg:province":"Gen\u00e8ve",
    "wof:name":"Car Trafic Transport De Voitures",
    "wof:placetype":"venue"
},
  "geometry": {"coordinates":[6.0775032043,46.2187805176],"type":"Point"}
}