{
  "type": "Feature",
  "properties": {
    "iso:country":"CH",
    "sg:address":"Industrie S\u00fcd",
    "sg:city":"Ennenda",
    "sg:orig_category":"Closing Force Measurement Instruments",
    "sg:phone":"+41 55 640 18 45",
    "sg:postcode":"8755",
    "sg:province":"Glarus",
    "wof:name":"M\u00fcller-leuthold Ag",
    "wof:placetype":"venue"
},
  "geometry": {"coordinates":[9.078795,47.032909],"type":"Point"}
}