{
  "type": "Feature",
  "properties": {
    "iso:country":"CH",
    "sg:address":"Bundesplatz 5 6300 Zug. Postfach",
    "sg:city":"Zug",
    "sg:orig_category":"Warenh\u00e4user",
    "sg:phone":"+41 41 729 16 99",
    "sg:postcode":"6304",
    "sg:province":"Zug",
    "wof:name":"Manor",
    "wof:placetype":"venue"
},
  "geometry": {"coordinates":[8.5150003433,47.1708755493],"type":"Point"}
}