{
  "type": "Feature",
  "properties": {
    "iso:country":"CH",
    "sg:address":"Route De St-cergue",
    "sg:city":"Begnins",
    "sg:orig_category":"Fachdetailhandel mit pharmazeutischen Produkten",
    "sg:phone":"+41 22 366 13 03",
    "sg:postcode":"1268",
    "sg:province":"Vaud",
    "wof:name":"Anita Gotheil Pharmacie De Begnins",
    "wof:placetype":"venue"
},
  "geometry": {"coordinates":[6.2384910583,46.4438209534],"type":"Point"}
}