{
  "type": "Feature",
  "properties": {
    "iso:country":"CH",
    "sg:address":"Viaduc Rue Du 58",
    "sg:city":"Montagne-moutier",
    "sg:orig_category":"Werbung",
    "sg:postcode":"2740",
    "sg:province":"Bern",
    "wof:name":"Ipra S\u00e0rl",
    "wof:placetype":"venue"
},
  "geometry": {"coordinates":[7.3724632263,47.2787246704],"type":"Point"}
}