{
  "type": "Feature",
  "properties": {
    "iso:country":"CH",
    "sg:address":"J\u00e4gerweg 20",
    "sg:city":"Lyss",
    "sg:orig_category":"Allgemeiner Gartenbau Gartenbau",
    "sg:phone":"+41 56 463 62 02",
    "sg:postcode":"3250",
    "sg:province":"Bern",
    "wof:name":"Baumschule Zulauf Ag",
    "wof:placetype":"venue"
},
  "geometry": {"coordinates":[8.146311,47.450817],"type":"Point"}
}