{
  "type": "Feature",
  "properties": {
    "addr:full":"Bahnhofstrasse 7 9630 Wattwil. Postfach Wattwil St. Gallen 9630",
    "addr:housenumber":"7",
    "addr:postcode":"9630 wattwil. postfach wattwil;9630",
    "addr:street":"Bahnhofstrasse",
    "iso:country":"CH",
    "sg:address":"Bahnhofstrasse 7 9630 Wattwil. Postfach",
    "sg:city":"Wattwil",
    "sg:orig_category":"Detailhandel mit Blumen U Pflanzen Fachdetailhandel in Verkaufsr\u00e4umen",
    "sg:phone":"+41 71 988 60 44",
    "sg:postcode":"9630",
    "sg:province":"St. Gallen",
    "wof:name":"Arum-blumen Kr\u00e4henb\u00fchl & Keller Blumengesch\u00e4ft Usw",
    "wof:placetype":"venue"
},
  "geometry": {"coordinates":[9.086439,47.300957],"type":"Point"}
}