{
  "type": "Feature",
  "properties": {
    "iso:country":"CH",
    "sg:address":"Pilatusstrasse 18",
    "sg:city":"Luzern",
    "sg:orig_category":"Unclassifiable Establishments",
    "sg:postcode":"6003",
    "sg:province":"Luzern",
    "wof:name":"Kelly Investment Ag",
    "wof:placetype":"venue"
},
  "geometry": {"coordinates":[8.3059082031,47.0487670898],"type":"Point"}
}