{
  "type": "Feature",
  "properties": {
    "iso:country":"CH",
    "sg:address":"Rue Georges-jordil 4 1700 Fribourg Case Postale 363",
    "sg:city":"Fribourg",
    "sg:orig_category":"Herstellung von Medikamenten U sonstigen pharmazeutischen Erzeugnissen Herstellung von pharmazeutisc",
    "sg:phone":"+41 19303940",
    "sg:postcode":"1701",
    "sg:province":"Fribourg",
    "wof:name":"Padma Ag Tibetische Rezepturen",
    "wof:placetype":"venue"
},
  "geometry": {"coordinates":[8.8035001755,47.3288803101],"type":"Point"}
}