{
  "type": "Feature",
  "properties": {
    "iso:country":"CH",
    "sg:address":"Clausiusstrasse 60",
    "sg:city":"Z\u00fcrich",
    "sg:orig_category":"Fotografische Ateliers Korrespondenz U Nachrichtenb\u00fcros",
    "sg:phone":"+41 12518012",
    "sg:postcode":"8006",
    "sg:province":"Z\u00fcrich",
    "wof:name":"Otto Pfenninger Fotografisches Atelier",
    "wof:placetype":"venue"
},
  "geometry": {"coordinates":[8.5451850891,47.380657196],"type":"Point"}
}