{
  "type": "Feature",
  "properties": {
    "iso:country":"CH",
    "sg:address":"Gotthardstrasse 11",
    "sg:city":"Schattdorf",
    "sg:orig_category":"Haltung von Rindern",
    "sg:postcode":"6467",
    "sg:province":"Uri",
    "wof:name":"Viehzuchtgenossenschaft Schattdorf",
    "wof:placetype":"venue"
},
  "geometry": {"coordinates":[8.6510629654,46.8684539795],"type":"Point"}
}