{
  "type": "Feature",
  "properties": {
    "iso:country":"CH",
    "sg:address":"Weihermattstrasse 5",
    "sg:city":"Urdorf",
    "sg:orig_category":"Manicure P\u00e9dicure",
    "sg:phone":"+41 17342073",
    "sg:postcode":"8902",
    "sg:province":"Z\u00fcrich",
    "wof:name":"Ursula Balmer P\u00e9dicure & Nail-kosmetik",
    "wof:placetype":"venue"
},
  "geometry": {"coordinates":[8.4258365631,47.3839454651],"type":"Point"}
}