{
  "type": "Feature",
  "properties": {
    "iso:country":"CH",
    "sg:address":"1617",
    "sg:city":"Remaufens",
    "sg:orig_category":"Vereine Gesang",
    "sg:postcode":"1617",
    "sg:province":"Fribourg",
    "wof:name":"Choeur Mixte",
    "wof:placetype":"venue"
},
  "geometry": {"coordinates":[6.8788499832,46.5283584595],"type":"Point"}
}