{
  "type": "Feature",
  "properties": {
    "iso:country":"CH",
    "sg:address":"Bielackerstrasse 16",
    "sg:city":"Gretzenbach",
    "sg:orig_category":"Sonstiger Grosshandel",
    "sg:phone":"+41 62 849 02 02",
    "sg:postcode":"5014",
    "sg:province":"Solothurn",
    "wof:name":"Dienemann Sack Container, Inhaber Ramel Erhard",
    "wof:placetype":"venue"
},
  "geometry": {"coordinates":[7.9993457794,47.3589668274],"type":"Point"}
}