{
  "type": "Feature",
  "properties": {
    "iso:country":"CH",
    "sg:address":"Langenhagstrasse 68",
    "sg:city":"Birsfelden",
    "sg:orig_category":"Herstellung von Metallkonstruktionen Schlossereien",
    "sg:phone":"+41 22 736 49 44",
    "sg:postcode":"4127",
    "sg:province":"Basel-Landschaft",
    "wof:name":"Rachel Rieben Troll W. Serrurerie",
    "wof:placetype":"venue"
},
  "geometry": {"coordinates":[6.1620187759,46.2018890381],"type":"Point"}
}