{
  "type": "Feature",
  "properties": {
    "iso:country":"CH",
    "sg:address":"De-candolle Rue 34 1205 Gen\u00e8ve. Postfach",
    "sg:city":"Gen\u00e8ve",
    "sg:orig_category":"Reiseb\u00fcros U Reiseveranstalter",
    "sg:postcode":"1201",
    "sg:province":"Gen\u00e8ve",
    "wof:name":"At-touristik And Trade Gmbh Reisen Usw; An- U. Verkauf, Vermittlung, Organisation",
    "wof:placetype":"venue"
},
  "geometry": {"coordinates":[7.8021011353,46.1756629944],"type":"Point"}
}