{
  "type": "Feature",
  "properties": {
    "iso:country":"CH",
    "sg:address":"Hotel Steingletscher 3863 Gadmen. Postfach",
    "sg:city":"Gadmen",
    "sg:orig_category":"RESTAURANTS: TEA-ROOMS",
    "sg:postcode":"3863",
    "sg:province":"Bern",
    "wof:name":"Alpin Center Sustenpass Ag Gastgewerbe- U. Andere Touristische Unternehmen Usw.",
    "wof:placetype":"venue"
},
  "geometry": {"coordinates":[8.3496618271,46.7370605469],"type":"Point"}
}