{
  "type": "Feature",
  "properties": {
    "iso:country":"CH",
    "sg:address":"St\u00f6ckli Lueg Emmentalstrasse 298",
    "sg:city":"Oberburg",
    "sg:orig_category":"Elektroinstallation",
    "sg:phone":"+41 34 461 06 08",
    "sg:postcode":"3414",
    "sg:province":"Bern",
    "wof:name":"Elektro H\u00fcrzeler",
    "wof:placetype":"venue"
},
  "geometry": {"coordinates":[7.6260499954,47.0390052795],"type":"Point"}
}