{
  "type": "Feature",
  "properties": {
    "iso:country":"CH",
    "sg:address":"4423 Hersberg. Postfach",
    "sg:city":"Hersberg",
    "sg:orig_category":"Verwertung von Milch",
    "sg:postcode":"4423",
    "sg:province":"Basel-Landschaft",
    "wof:name":"Milchgenossenschaft Hersberg",
    "wof:placetype":"venue"
},
  "geometry": {"coordinates":[7.781730175,47.4921188354],"type":"Point"}
}