{
  "type": "Feature",
  "properties": {
    "iso:country":"CH",
    "sg:address":"Nidaugasse 35 2502 Biel/bienne Case Postale 925",
    "sg:city":"Biel/bienne",
    "sg:orig_category":"Fachdetailhandel in Verkaufsr\u00e4umen Grosshandel mit Uhren",
    "sg:phone":"+41 32 329 37 00",
    "sg:postcode":"2501",
    "sg:province":"Bern",
    "wof:name":"Montres Movado Bienne Sa",
    "wof:placetype":"venue"
},
  "geometry": {"coordinates":[7.2467780113,47.1385726929],"type":"Point"}
}