{
  "type": "Feature",
  "properties": {
    "iso:country":"CH",
    "sg:address":"Zugerstrasse 77",
    "sg:city":"Baar",
    "sg:orig_category":"Verwaltung von Immobilien",
    "sg:phone":"+41 32 913 73 24",
    "sg:postcode":"6340",
    "sg:province":"Zug",
    "wof:name":"Maurice Favre Etude D'avocat & Notaire",
    "wof:placetype":"venue"
},
  "geometry": {"coordinates":[6.8241219521,47.0995979309],"type":"Point"}
}