{
  "type": "Feature",
  "properties": {
    "iso:country":"CH",
    "sg:address":"Chemin De Mallieu 7",
    "sg:city":"Pully",
    "sg:orig_category":"Fotografische Ateliers",
    "sg:phone":"+41 21 729 63 96",
    "sg:postcode":"1009",
    "sg:province":"Vaud",
    "wof:name":"Edouard Baumgartner Atelier Photographique",
    "wof:placetype":"venue"
},
  "geometry": {"coordinates":[6.6660652161,46.5079917908],"type":"Point"}
}