{
  "type": "Feature",
  "properties": {
    "iso:country":"CH",
    "sg:address":"Imberg\u00e4sslein 1",
    "sg:city":"Basel",
    "sg:orig_category":"Detailhandel mit Uhren U Schmuck Reparatur von Uhren U Schmuck",
    "sg:phone":"+41 61 261 42 75",
    "sg:postcode":"4051",
    "sg:province":"Basel-Stadt",
    "wof:name":"L. Egedi Uhren U. Bijouterie; Handel U. Reparaturen.",
    "wof:placetype":"venue"
},
  "geometry": {"coordinates":[7.5866618156,47.5579719543],"type":"Point"}
}