{
  "type": "Feature",
  "properties": {
    "iso:country":"CH",
    "sg:address":"Bahnhofstrasse 5",
    "sg:city":"Erlen",
    "sg:orig_category":"Detailhandel mit Waren verschiedener Art, Hauptrichtung Nahrungsmittel Grosshandel mit Nahrungsmitte",
    "sg:phone":"+41 71 648 16 66",
    "sg:postcode":"8586",
    "sg:province":"Thurgau",
    "wof:name":"Spar-markt Studer J. Erlen Lebensmittel; Verkauf",
    "wof:placetype":"venue"
},
  "geometry": {"coordinates":[9.226436615,47.5511436462],"type":"Point"}
}