{
  "type": "Feature",
  "properties": {
    "iso:country":"CH",
    "sg:address":"Untere Grabenstrasse 8",
    "sg:city":"Zofingen",
    "sg:orig_category":"Fahrschulen, Flugschulen",
    "sg:postcode":"4800",
    "sg:province":"Aargau",
    "wof:name":"Fahrschule Und Autohandel B\u00f6sch",
    "wof:placetype":"venue"
},
  "geometry": {"coordinates":[7.9429798126,47.290309906],"type":"Point"}
}