{
  "type": "Feature",
  "properties": {
    "iso:country":"CH",
    "sg:address":"Wartbadstrasse 18",
    "sg:city":"D\u00e4ttlikon",
    "sg:orig_category":"Unclassifiable Establishments",
    "sg:postcode":"8421",
    "sg:province":"Z\u00fcrich",
    "wof:name":"Hansruedi Bernhard Schlosserei Lanmaschinen",
    "wof:placetype":"venue"
},
  "geometry": {"coordinates":[8.6395177841,47.5211639404],"type":"Point"}
}