{
  "type": "Feature",
  "properties": {
    "iso:country":"CH",
    "sg:address":"Terreaux Chemin Des 14",
    "sg:city":"Romanel-s-lausanne",
    "sg:orig_category":"Verwertung von Milch",
    "sg:postcode":"1032",
    "sg:province":"Vaud",
    "wof:name":"Soci\u00e9t\u00e9 De Laiterie De Romanel",
    "wof:placetype":"venue"
},
  "geometry": {"coordinates":[6.6038780212,46.5632209778],"type":"Point"}
}