{
  "type": "Feature",
  "properties": {
    "iso:country":"CH",
    "sg:address":"Mattenweg 2",
    "sg:city":"Hunzenschwil",
    "sg:orig_category":"Sportvereine Ballsport Badminton",
    "sg:phone":"+41 62 897 19 48",
    "sg:postcode":"5502",
    "sg:province":"Aargau",
    "wof:name":"First Badminton-club Aarau",
    "wof:placetype":"venue"
},
  "geometry": {"coordinates":[8.1163730621,47.3797111511],"type":"Point"}
}