{
  "type": "Feature",
  "properties": {
    "iso:country":"CH",
    "sg:address":"Z\u00fcrcherstrasse 36",
    "sg:city":"H\u00fcttikon",
    "sg:orig_category":"Instandhaltung U Reparatur von Automobilen",
    "sg:phone":"+41 18444777",
    "sg:postcode":"8115",
    "sg:province":"Z\u00fcrich",
    "wof:name":"Garage-carrosserie Kobler Ag",
    "wof:placetype":"venue"
},
  "geometry": {"coordinates":[8.3886871338,47.4461097717],"type":"Point"}
}