{
  "type": "Feature",
  "properties": {
    "iso:country":"CH",
    "sg:address":"Margarethenstrasse 59",
    "sg:city":"Basel",
    "sg:orig_category":"Detailhandel mit Fahrr\u00e4dern Handel mit Motorr\u00e4dern, Teilen U Zubeh\u00f6r Instandhaltung U Reparatur von ",
    "sg:phone":"+41 61 272 22 22",
    "sg:postcode":"4053",
    "sg:province":"Basel-Stadt",
    "wof:name":"2 Rad Basilisk Ag",
    "wof:placetype":"venue"
},
  "geometry": {"coordinates":[7.5839152336,47.5461006165],"type":"Point"}
}