{
  "type": "Feature",
  "properties": {
    "iso:country":"CH",
    "sg:address":"Fichtenweg 10",
    "sg:city":"Steffisburg",
    "sg:orig_category":"Herstellung von Hebezeugen U F\u00f6rdermitteln",
    "sg:phone":"+41 33 437 56 61",
    "sg:postcode":"3612",
    "sg:province":"Bern",
    "wof:name":"Kr\u00e4henb\u00fchl Peter",
    "wof:placetype":"venue"
},
  "geometry": {"coordinates":[7.6439089775,46.7792053223],"type":"Point"}
}