{
  "type": "Feature",
  "properties": {
    "iso:country":"CH",
    "sg:address":"Lerchenweg 14",
    "sg:city":"Sch\u00f6nb\u00fchl-urtenen",
    "sg:orig_category":"Grosshandel mit Getr\u00e4nken Grosshandel mit Uhren",
    "sg:phone":"+41 31 859 18 32",
    "sg:postcode":"3322",
    "sg:province":"Bern",
    "wof:name":"Polyvag- Verkaufsgesellschaft Ag",
    "wof:placetype":"venue"
},
  "geometry": {"coordinates":[7.4888191223,47.0212020874],"type":"Point"}
}