{
  "type": "Feature",
  "properties": {
    "iso:country":"CH",
    "sg:address":"Bahnhofstrasse 40",
    "sg:city":"Chur",
    "sg:orig_category":"Architektur U Ingenieurb\u00fcros",
    "sg:postcode":"7000",
    "sg:province":"Graubunden",
    "wof:name":"Provos Immobilien Ag",
    "wof:placetype":"venue"
},
  "geometry": {"coordinates":[9.531686,46.851143],"type":"Point"}
}