{
  "type": "Feature",
  "properties": {
    "iso:country":"CH",
    "sg:address":"Br\u00fcggelbachstrasse 4",
    "sg:city":"Neuenegg",
    "sg:orig_category":"Hoch U Tiefbau",
    "sg:phone":"+41 31 741 41 02",
    "sg:postcode":"3176",
    "sg:province":"Bern",
    "wof:name":"Daniel Zbinden Baugesch\u00e4ft",
    "wof:placetype":"venue"
},
  "geometry": {"coordinates":[7.2985301018,46.8974723816],"type":"Point"}
}