{
  "type": "Feature",
  "properties": {
    "iso:country":"CH",
    "sg:address":"Bundesplatz 10",
    "sg:city":"Zug",
    "sg:orig_category":"Finanzierungsinstitutionen",
    "sg:phone":"+41 27 329 25 55",
    "sg:postcode":"6300",
    "sg:province":"Zug",
    "wof:name":"Atag Capital Ag",
    "wof:placetype":"venue"
},
  "geometry": {"coordinates":[8.5151939392,47.1716957092],"type":"Point"}
}