{
  "type": "Feature",
  "properties": {
    "iso:country":"CH",
    "sg:address":"Wiler Strasse 63",
    "sg:city":"Wattwil",
    "sg:orig_category":"Grosshandel mit Textilien",
    "sg:postcode":"9630",
    "sg:province":"St. Gallen",
    "wof:name":"Mikado - Sport Und Freitzeitmode, Gabriela M\u00f6rtlseder",
    "wof:placetype":"venue"
},
  "geometry": {"coordinates":[9.0836400986,47.3109855652],"type":"Point"}
}