{
  "type": "Feature",
  "properties": {
    "iso:country":"CH",
    "sg:address":"Achereggstrasse 6a",
    "sg:city":"Stansstad",
    "sg:orig_category":"Detailhandel mit M\u00f6beln U Haushaltsgegenst\u00e4nden",
    "sg:phone":"+41 62 206 06 36",
    "sg:postcode":"6362",
    "sg:province":"Nidwalden",
    "wof:name":"Composwiss Ag",
    "wof:placetype":"venue"
},
  "geometry": {"coordinates":[8.3358659744,46.9791374207],"type":"Point"}
}