{
  "type": "Feature",
  "properties": {
    "iso:country":"CH",
    "sg:address":"Boulevard Des Philosophes 26",
    "sg:city":"Gen\u00e8ve",
    "sg:classifiers":[
        {
            "category":"Insurance",
            "subcategory":"Insurance Agent",
            "type":"Services"
        }
    ],
    "sg:phone":"+41 22 320 39 55",
    "sg:postcode":"1205",
    "sg:province":"Gen\u00e8ve",
    "sg:tags":[
        "versicherungsagenturen",
        "-broker"
    ],
    "wof:name":"Acg Assurances-conseils- Gestion",
    "wof:placetype":"venue"
},
  "geometry": {"coordinates":[6.1488671303,46.1963233948],"type":"Point"}
}