{
  "type": "Feature",
  "properties": {
    "iso:country":"CH",
    "sg:address":"Bachstrasse 5",
    "sg:city":"Brig",
    "sg:orig_category":"Interessenvertretungen U sonstige Vereinigungen",
    "sg:phone":"+41 71 223 29 85",
    "sg:postcode":"3900",
    "sg:province":"Valais",
    "wof:name":"Wwf Appenzell",
    "wof:placetype":"venue"
},
  "geometry": {"coordinates":[9.3715200424,47.4236068726],"type":"Point"}
}