{
  "type": "Feature",
  "properties": {
    "iso:country":"CH",
    "sg:address":"Feierabendstrasse 47",
    "sg:city":"Basel",
    "sg:orig_category":"Detailhandel mit Bekleidungszubeh\u00f6r U Bekleidung ohne ausgepr\u00e4gten Schwerpunkt Detailhandel mit medi",
    "sg:phone":"+41 61 381 05 05",
    "sg:postcode":"4051",
    "sg:province":"Basel-Stadt",
    "wof:name":"Reha Mobil Gmbh Rolli Moden & Reha-hilfen",
    "wof:placetype":"venue"
},
  "geometry": {"coordinates":[7.58035,47.552658],"type":"Point"}
}