{
  "type": "Feature",
  "properties": {
    "iso:country":"CH",
    "sg:address":"Industriestrasse 24",
    "sg:city":"Safnern",
    "sg:orig_category":"Herstellung von Werkzeugen Maschinenbau",
    "sg:phone":"+41 32 751 40 20",
    "sg:postcode":"2553",
    "sg:province":"Bern",
    "wof:name":"Landromatic Sa",
    "wof:placetype":"venue"
},
  "geometry": {"coordinates":[7.0742778778,47.0604057312],"type":"Point"}
}