{
  "type": "Feature",
  "properties": {
    "iso:country":"CH",
    "sg:address":"Alte Lenzburgerstrasse 7",
    "sg:city":"Birr",
    "sg:orig_category":"Autogaragen",
    "sg:phone":"+41 56 444 00 34",
    "sg:postcode":"5242",
    "sg:province":"Aargau",
    "wof:name":"Ren\u00e9 Kohler Garage",
    "wof:placetype":"venue"
},
  "geometry": {"coordinates":[8.220165,47.423676],"type":"Point"}
}