{
  "type": "Feature",
  "properties": {
    "iso:country":"CH",
    "sg:address":"Lohwisstrasse 50 8123 Ebmatingen. Postfach",
    "sg:city":"Ebmatingen",
    "sg:orig_category":"Sonstige mit der Informatik verbundene T\u00e4tigkeiten",
    "sg:phone":"+41 18876600",
    "sg:postcode":"8123",
    "sg:province":"Z\u00fcrich",
    "wof:name":"Sw Engineering Gmbh",
    "wof:placetype":"venue"
},
  "geometry": {"coordinates":[8.6434001923,47.3563499451],"type":"Point"}
}