{
  "type": "Feature",
  "properties": {
    "iso:country":"CH",
    "sg:address":"Im Grund 21",
    "sg:city":"Embrach",
    "sg:orig_category":"Internet Provider Sonstige mit der Informatik verbundene T\u00e4tigkeiten",
    "sg:phone":"+41 18650853",
    "sg:postcode":"8424",
    "sg:province":"Z\u00fcrich",
    "wof:name":"Swissart Network Arthur Woods",
    "wof:placetype":"venue"
},
  "geometry": {"coordinates":[8.5971164703,47.5080299377],"type":"Point"}
}