{
  "type": "Feature",
  "properties": {
    "addr:full":"Jurastrasse 16 Langenthal Bern 4900",
    "addr:housenumber":"16",
    "addr:postcode":"4900",
    "addr:street":"Jurastrasse;Bern",
    "iso:country":"CH",
    "sg:address":"Jurastrasse 16",
    "sg:city":"Langenthal",
    "sg:orig_category":"Bauschreinerei Herstellung von M\u00f6beln verschiedener Art",
    "sg:phone":"+41 31 311 07 71",
    "sg:postcode":"4900",
    "sg:province":"Bern",
    "wof:name":"Nyffeler & Co",
    "wof:placetype":"venue"
},
  "geometry": {"coordinates":[7.789712,47.21344],"type":"Point"}
}