{
  "type": "Feature",
  "properties": {
    "iso:country":"CH",
    "sg:address":"Furlenstrasse 24",
    "sg:city":"Lausen",
    "sg:orig_category":"Malerei",
    "sg:phone":"+41 61 921 54 80",
    "sg:postcode":"4415",
    "sg:province":"Basel-Landschaft",
    "wof:name":"Markus Miesch Malergesch\u00e4ft",
    "wof:placetype":"venue"
},
  "geometry": {"coordinates":[7.7592148781,47.4695320129],"type":"Point"}
}