{
  "type": "Feature",
  "properties": {
    "iso:country":"CH",
    "sg:address":"B\u00e4raustrasse 14",
    "sg:city":"B\u00e4rau",
    "sg:orig_category":"Detailhandel mit elektrischen Haushaltsger\u00e4ten",
    "sg:phone":"+41 34 402 81 91",
    "sg:postcode":"3552",
    "sg:province":"Bern",
    "wof:name":"Markus Hirschi Haushaltger\u00e4te-service",
    "wof:placetype":"venue"
},
  "geometry": {"coordinates":[7.8066477776,46.9348564148],"type":"Point"}
}