{
  "type": "Feature",
  "properties": {
    "iso:country":"CH",
    "sg:address":"Chemin Des Cond\u00e9mines 1",
    "sg:city":"Ligni\u00e8res",
    "sg:orig_category":"Nationale Postdienste",
    "sg:phone":"+41 32 751 22 61",
    "sg:postcode":"2523",
    "sg:province":"Neuch\u00e2tel",
    "wof:name":"La Poste Suisse",
    "wof:placetype":"venue"
},
  "geometry": {"coordinates":[7.0648069382,47.0804481506],"type":"Point"}
}