{
  "type": "Feature",
  "properties": {
    "iso:country":"CH",
    "sg:address":"Ochseng\u00e4ssli 7",
    "sg:city":"Aarau",
    "sg:classifiers":[
        {
            "category":"Personal",
            "subcategory":"Piercing",
            "type":"Services"
        }
    ],
    "sg:phone":"+41 62 822 09 33",
    "sg:postcode":"5000",
    "sg:province":"Aargau",
    "sg:tags":[
        "tattoo"
    ],
    "wof:name":"Jakie's Tattoo Planet",
    "wof:placetype":"venue"
},
  "geometry": {"coordinates":[8.0445041656,47.3936233521],"type":"Point"}
}