{
  "type": "Feature",
  "properties": {
    "iso:country":"CH",
    "sg:address":"Dans Ses Propres Locaux",
    "sg:city":"Billens",
    "sg:orig_category":"RESTAURANTS: TEA-ROOMS",
    "sg:postcode":"1681",
    "sg:province":"Fribourg",
    "wof:name":"Caf\u00e9 De L'union S\u00e0rl",
    "wof:placetype":"venue"
},
  "geometry": {"coordinates":[6.8989658356,46.6905021667],"type":"Point"}
}