{
  "type": "Feature",
  "properties": {
    "iso:country":"CH",
    "sg:address":"Kirchstrasse 8 4125 Riehen. Postfach",
    "sg:city":"Riehen",
    "sg:orig_category":"Unclassifiable Establishments",
    "sg:postcode":"4125",
    "sg:province":"Basel-Stadt",
    "wof:name":"Holdges Ag Beteiligungen Usw",
    "wof:placetype":"venue"
},
  "geometry": {"coordinates":[7.6489138603,47.5844192505],"type":"Point"}
}