{
  "type": "Feature",
  "properties": {
    "iso:country":"CH",
    "sg:address":"Rue Du Diorama 5",
    "sg:city":"Gen\u00e8ve",
    "sg:classifiers":[
        {
            "category":"Wholesale",
            "subcategory":"Home Furnishings",
            "type":"Manufacturing & Wholesale Goods"
        }
    ],
    "sg:phone":"+41 22 329 10 12",
    "sg:postcode":"1204",
    "sg:province":"Gen\u00e8ve",
    "sg:tags":[
        "house",
        "paint"
    ],
    "wof:name":"Bugnon Et Schneider",
    "wof:placetype":"venue"
},
  "geometry": {"coordinates":[6.138862133,46.2022514343],"type":"Point"}
}