{
  "type": "Feature",
  "properties": {
    "iso:country":"CH",
    "sg:address":"Uech 262",
    "sg:city":"Huttwil",
    "sg:orig_category":"Sportvereine Sch\u00fctzen",
    "sg:phone":"+41 62 962 28 56",
    "sg:postcode":"4950",
    "sg:province":"Bern",
    "wof:name":"Infanteriesch\u00fctzen-gesell.",
    "wof:placetype":"venue"
},
  "geometry": {"coordinates":[7.8579587936,47.1087036133],"type":"Point"}
}