{
  "type": "Feature",
  "properties": {
    "iso:country":"CH",
    "sg:address":"Jurastrasse 5",
    "sg:city":"R\u00fctihof",
    "sg:orig_category":"Blumen U Zierpflanzenbau",
    "sg:phone":"+41 27 458 18 74",
    "sg:postcode":"5406",
    "sg:province":"Aargau",
    "wof:name":"Aloys & Th\u00e9odul Bonvin Etablissement Horticole",
    "wof:placetype":"venue"
},
  "geometry": {"coordinates":[7.463645,46.258438],"type":"Point"}
}