{
  "type": "Feature",
  "properties": {
    "iso:country":"CH",
    "sg:address":"Arterstrasse 106 6405 Immensee. Postfach 45",
    "sg:city":"Immensee",
    "sg:orig_category":"Geb\u00e4ude, Wohnungsreinigung Reinigungsgewerbe",
    "sg:phone":"+41 41 850 47 65",
    "sg:postcode":"6405",
    "sg:province":"Schwyz",
    "wof:name":"Rigi-reinigung Ag",
    "wof:placetype":"venue"
},
  "geometry": {"coordinates":[8.4601011276,47.093044281],"type":"Point"}
}