{
  "type": "Feature",
  "properties": {
    "iso:country":"CH",
    "sg:address":"Hauptstrasse 50",
    "sg:city":"Niederg\u00f6sgen",
    "sg:orig_category":"Gemeindeverwaltungen",
    "sg:phone":"+41 62 849 18 21",
    "sg:postcode":"5013",
    "sg:province":"Solothurn",
    "wof:name":"Gemeindeverwaltung Niederg\u00f6sgen",
    "wof:placetype":"venue"
},
  "geometry": {"coordinates":[7.9922571182,47.3722572327],"type":"Point"}
}