{
  "type": "Feature",
  "properties": {
    "iso:country":"CH",
    "sg:address":"Morgenstrasse 129 Berner Technopark",
    "sg:city":"Bern",
    "sg:orig_category":"Softwareentwicklung U beratung",
    "sg:phone":"+41 31 998 44 11",
    "sg:postcode":"3018",
    "sg:province":"Bern",
    "wof:name":"Comsol Ag Technische Software",
    "wof:placetype":"venue"
},
  "geometry": {"coordinates":[7.3706941605,46.939781189],"type":"Point"}
}