{
  "type": "Feature",
  "properties": {
    "iso:country":"CH",
    "sg:address":"Wehntalerstrasse 200",
    "sg:city":"Regensdorf",
    "sg:orig_category":"Architektur U Ingenieurb\u00fcros",
    "sg:phone":"+41 18708980",
    "sg:postcode":"8105",
    "sg:province":"Z\u00fcrich",
    "wof:name":"De Luigi M., Ingenieurb\u00fcro Und Bauleitungen",
    "wof:placetype":"venue"
},
  "geometry": {"coordinates":[8.46688,47.444489],"type":"Point"}
}