{
  "type": "Feature",
  "properties": {
    "addr:full":"Kapellgasse 1 Arbon Thurgau 9320",
    "addr:housenumber":"1",
    "addr:postcode":"9320",
    "addr:street":"Kapellgasse",
    "iso:country":"CH",
    "sg:address":"Kapellgasse 1",
    "sg:city":"Arbon",
    "sg:orig_category":"Detailhandel mit Brot, Back U S\u00fcsswaren",
    "sg:phone":"+41 71 446 11 17",
    "sg:postcode":"9320",
    "sg:province":"Thurgau",
    "wof:name":"Josef Kunz B\u00e4ckerei-konditorei",
    "wof:placetype":"venue"
},
  "geometry": {"coordinates":[9.435896,47.515976],"type":"Point"}
}