{
  "type": "Feature",
  "properties": {
    "iso:country":"CH",
    "sg:address":"Hofstettenstrasse 81 3600 Thun. Postfach",
    "sg:city":"Thun",
    "sg:orig_category":"Allgemeiner Hoch U Tiefbau",
    "sg:postcode":"3600",
    "sg:province":"Bern",
    "wof:name":"Haueter Rolf Altbausanierungen Renovation Und Sanierung Von Altbauten",
    "wof:placetype":"venue"
},
  "geometry": {"coordinates":[7.638512,46.749565],"type":"Point"}
}