{
  "type": "Feature",
  "properties": {
    "iso:country":"CH",
    "sg:address":"3672",
    "sg:city":"Aeschlen",
    "sg:orig_category":"Sportvereine Sch\u00fctzen",
    "sg:phone":"+41 33 676 25 33",
    "sg:postcode":"3672",
    "sg:province":"Bern",
    "wof:name":"Milit\u00e4rsch\u00fctzen",
    "wof:placetype":"venue"
},
  "geometry": {"coordinates":[7.6804499626,46.6164894104],"type":"Point"}
}