{
  "type": "Feature",
  "properties": {
    "iso:country":"CH",
    "sg:address":"Felsenaustrasse 18/20",
    "sg:city":"Bern",
    "sg:orig_category":"Elektroinstallation",
    "sg:phone":"+41 31 301 73 73",
    "sg:postcode":"3004",
    "sg:province":"Bern",
    "wof:name":"Sch\u00e4rer-elektro",
    "wof:placetype":"venue"
},
  "geometry": {"coordinates":[7.4430170059,46.9719276428],"type":"Point"}
}