{
  "type": "Feature",
  "properties": {
    "addr:full":"Schlegelistrasse 1 Adelboden Bern 3715",
    "addr:housenumber":"1",
    "addr:postcode":"3715",
    "addr:street":"Schlegelistrasse",
    "iso:country":"CH",
    "sg:address":"Schlegelistrasse 1",
    "sg:city":"Adelboden",
    "sg:orig_category":"Autogaragen",
    "sg:phone":"+41 33 673 24 55",
    "sg:postcode":"3715",
    "sg:province":"Bern",
    "wof:name":"Adolf B\u00fcschlen Garage",
    "wof:placetype":"venue"
},
  "geometry": {"coordinates":[7.56254,46.494686],"type":"Point"}
}