{
  "type": "Feature",
  "properties": {
    "iso:country":"CH",
    "sg:address":"Hof 630",
    "sg:city":"Gams",
    "sg:orig_category":"Nationale Postdienste",
    "sg:phone":"+41 81 771 11 18",
    "sg:postcode":"9473",
    "sg:province":"St. Gallen",
    "wof:name":"Die Schweizerische Post",
    "wof:placetype":"venue"
},
  "geometry": {"coordinates":[9.4411172867,47.2039031982],"type":"Point"}
}