{
  "type": "Feature",
  "properties": {
    "addr:full":"Rue Du Port 11 Gen\u00e8ve Gen\u00e8ve 1204",
    "addr:housenumber":"11",
    "addr:postcode":"1204",
    "addr:street":"Rue Du Port",
    "iso:country":"CH",
    "sg:address":"Rue Du Port 11",
    "sg:city":"Gen\u00e8ve",
    "sg:orig_category":"Arztpraxen",
    "sg:phone":"+41 22 312 03 03",
    "sg:postcode":"1204",
    "sg:province":"Gen\u00e8ve",
    "wof:name":"Dr M\u00e9d. Tatiana I. Redali\u00e9 M\u00e9decin Sp\u00e9cialiste Fmh",
    "wof:placetype":"venue"
},
  "geometry": {"coordinates":[6.150641,46.202461],"type":"Point"}
}