{
  "type": "Feature",
  "properties": {
    "iso:country":"CH",
    "sg:address":"Hirondelles Chemin Des 3 1700 Fribourg. Postfach",
    "sg:city":"Fribourg",
    "sg:orig_category":"Sonstiger Grosshandel",
    "sg:phone":"+41 21 977 21 25",
    "sg:postcode":"1700",
    "sg:province":"Fribourg",
    "wof:name":"Solaso S\u00e0rl",
    "wof:placetype":"venue"
},
  "geometry": {"coordinates":[6.8689317703,46.4490242004],"type":"Point"}
}