{
  "type": "Feature",
  "properties": {
    "iso:country":"CH",
    "sg:address":"Staatsstrasse 21",
    "sg:city":"Niederb\u00fcren",
    "sg:orig_category":"Detailhandel mit Brot, Back U S\u00fcsswaren",
    "sg:postcode":"9246",
    "sg:province":"St. Gallen",
    "wof:name":"Holzer-kl\u00f6tzli B.",
    "wof:placetype":"venue"
},
  "geometry": {"coordinates":[7.50591,47.048679],"type":"Point"}
}