{
  "type": "Feature",
  "properties": {
    "iso:country":"CH",
    "sg:address":"1636",
    "sg:city":"Broc",
    "sg:orig_category":"Landesverteidigung, Sozialversicherung \u00d6ffentliche Verwaltung",
    "sg:phone":"+41 26 921 31 70",
    "sg:postcode":"1636",
    "sg:province":"Fribourg",
    "wof:name":"Centre De Protection Civile",
    "wof:placetype":"venue"
},
  "geometry": {"coordinates":[7.1003518105,46.6031494141],"type":"Point"}
}