{
  "type": "Feature",
  "properties": {
    "addr:full":"Route Alexandre-daguet 7 Fribourg Fribourg 1700",
    "addr:housenumber":"7",
    "addr:postcode":"1700",
    "addr:street":"Route Alexandre-Daguet",
    "iso:country":"CH",
    "sg:address":"Route Alexandre-daguet 7",
    "sg:city":"Fribourg",
    "sg:orig_category":"Bauingenieurb\u00fcros allgemein",
    "sg:phone":"+41 26 466 26 43",
    "sg:postcode":"1700",
    "sg:province":"Fribourg",
    "wof:name":"Pierre El Soda Bureau D'ing\u00e9nieur",
    "wof:placetype":"venue"
},
  "geometry": {"coordinates":[7.145789,46.813984],"type":"Point"}
}