{
  "type": "Feature",
  "properties": {
    "iso:country":"CH",
    "sg:address":"Corso San Gottardo 89 6830 Chiasso. Postfach",
    "sg:city":"Chiasso",
    "sg:orig_category":"Vermietung U Verpachtung von eigenen Immobilien",
    "sg:phone":"+41 91 682 67 42",
    "sg:postcode":"6830",
    "sg:province":"Ticino",
    "wof:name":"Mauriam Sa Immobili Ecc",
    "wof:placetype":"venue"
},
  "geometry": {"coordinates":[9.0256509781,45.8360481262],"type":"Point"}
}