{
  "type": "Feature",
  "properties": {
    "iso:country":"CH",
    "sg:address":"Ameism\u00fchleweg 3",
    "sg:city":"Tafers",
    "sg:orig_category":"Unclassifiable Establishments",
    "sg:phone":"+41 18410789",
    "sg:postcode":"1712",
    "sg:province":"Fribourg",
    "wof:name":"Gartenbau Zaugg",
    "wof:placetype":"venue"
},
  "geometry": {"coordinates":[7.2166857719,46.8058586121],"type":"Point"}
}