{
  "type": "Feature",
  "properties": {
    "iso:country":"CH",
    "sg:address":"Bleiken 34",
    "sg:city":"Sulgen",
    "sg:orig_category":"Herstellung von Werkzeugen",
    "sg:phone":"+41 71 642 27 42",
    "sg:postcode":"8583",
    "sg:province":"Thurgau",
    "wof:name":"Julius Sennhauser Stanzmesserfabrikation",
    "wof:placetype":"venue"
},
  "geometry": {"coordinates":[9.1938428879,47.5335197449],"type":"Point"}
}