{
  "type": "Feature",
  "properties": {
    "iso:country":"CH",
    "sg:address":"Freiestr. 73",
    "sg:city":"Winterthur",
    "sg:classifiers":[
        {
            "category":"Professional",
            "subcategory":"Engineering",
            "type":"Services"
        }
    ],
    "sg:phone":"+41 52 202 65 69",
    "sg:postcode":"8406",
    "sg:province":"Z\u00fcrich",
    "sg:tags":[
        "machine",
        "-",
        "mechanical"
    ],
    "wof:name":"M\u00dcller & Christen Ag",
    "wof:placetype":"venue"
},
  "geometry": {"coordinates":[8.7079191208,47.4891967773],"type":"Point"}
}