{
  "type": "Feature",
  "properties": {
    "iso:country":"CH",
    "sg:address":"1816",
    "sg:city":"Chailly-montreux",
    "sg:classifiers":[
        {
            "category":"Restaurant",
            "type":"Food & Drink"
        }
    ],
    "sg:phone":"+41 21 964 64 65",
    "sg:postcode":"1816",
    "sg:province":"Vaud",
    "wof:name":"Restaurant La Vieille Ferme",
    "wof:placetype":"venue"
},
  "geometry": {"coordinates":[6.8924798965,46.4537391663],"type":"Point"}
}