{
  "type": "Feature",
  "properties": {
    "iso:country":"CH",
    "sg:address":"Rufacherstrasse 84",
    "sg:city":"Basel",
    "sg:orig_category":"Non-Classified Establishments",
    "sg:postcode":"4055",
    "sg:province":"Basel-Stadt",
    "wof:name":"Haute Coiffure Steinmann Ag",
    "wof:placetype":"venue"
},
  "geometry": {"coordinates":[9.2463998795,47.4141082764],"type":"Point"}
}