{
  "type": "Feature",
  "properties": {
    "iso:country":"CH",
    "sg:address":"Hauptstrasse 47",
    "sg:city":"Murgenthal",
    "sg:orig_category":"Elektroinstallation",
    "sg:phone":"+41 62 926 35 49",
    "sg:postcode":"4853",
    "sg:province":"Aargau",
    "wof:name":"Esit Murgenthal Gmbh",
    "wof:placetype":"venue"
},
  "geometry": {"coordinates":[7.8423638344,47.2733840942],"type":"Point"}
}