{
  "type": "Feature",
  "properties": {
    "iso:country":"CH",
    "sg:address":"Rossweidweg 3",
    "sg:city":"Zollikofen",
    "sg:orig_category":"RESTAURANTS: TEA-ROOMS",
    "sg:postcode":"3052",
    "sg:province":"Bern",
    "wof:name":"Hayat Gastro Gmbh",
    "wof:placetype":"venue"
},
  "geometry": {"coordinates":[7.4537978172,46.9944915771],"type":"Point"}
}