{
  "type": "Feature",
  "properties": {
    "iso:country":"CH",
    "sg:address":"St\u00e4mpfligasse 1",
    "sg:city":"Melchnau",
    "sg:orig_category":"Malerei",
    "sg:phone":"+41 62 927 26 05",
    "sg:postcode":"4917",
    "sg:province":"Bern",
    "wof:name":"Peter Beck Malergesch\u00e4ft",
    "wof:placetype":"venue"
},
  "geometry": {"coordinates":[7.8524050713,47.1792831421],"type":"Point"}
}