{
  "type": "Feature",
  "properties": {
    "iso:country":"CH",
    "sg:address":"Rue De La L\u00e9ch\u00e8re 11",
    "sg:city":"Bulle",
    "sg:orig_category":"Kosmetikinstitute",
    "sg:phone":"+41 26 912 67 00",
    "sg:postcode":"1630",
    "sg:province":"Fribourg",
    "wof:name":"Andr\u00e9e Descloux Institut De Beaut\u00e9 Jesabel",
    "wof:placetype":"venue"
},
  "geometry": {"coordinates":[7.0555291176,46.6191101074],"type":"Point"}
}