{
  "type": "Feature",
  "properties": {
    "addr:full":"Rue Louis Ruchonnet 14 Vallorbe Vaud 1337",
    "addr:housenumber":"14",
    "addr:postcode":"1337",
    "addr:street":"Rue Louis Ruchonnet",
    "iso:country":"CH",
    "sg:address":"Rue Louis Ruchonnet 14",
    "sg:city":"Vallorbe",
    "sg:orig_category":"Arztpraxen",
    "sg:phone":"+41 26 413 11 37",
    "sg:postcode":"1337",
    "sg:province":"Vaud",
    "wof:name":"Dr M\u00e9d. Charles Muller M\u00e9decin G\u00e9n\u00e9raliste Fmh",
    "wof:placetype":"venue"
},
  "geometry": {"coordinates":[7.164905,46.746414],"type":"Point"}
}