{
  "type": "Feature",
  "properties": {
    "iso:country":"CH",
    "sg:address":"Hausmattstrasse 9",
    "sg:city":"Bergdietikon",
    "sg:orig_category":"Non-Classified Establishments",
    "sg:postcode":"8962",
    "sg:province":"Aargau",
    "wof:name":"Heinz Lienhard",
    "wof:placetype":"venue"
},
  "geometry": {"coordinates":[8.3753175735,47.3952102661],"type":"Point"}
}