{
  "type": "Feature",
  "properties": {
    "iso:country":"CH",
    "sg:address":"Meierhofrain 5",
    "sg:city":"W\u00e4denswil",
    "sg:orig_category":"Datenverarbeitungsdienste Unternehmensberatung",
    "sg:phone":"+41 17802811",
    "sg:postcode":"8820",
    "sg:province":"Z\u00fcrich",
    "wof:name":"Agora Management Consulting Dr.selim Hacisalihzade",
    "wof:placetype":"venue"
},
  "geometry": {"coordinates":[8.680315,47.221916],"type":"Point"}
}