{
  "type": "Feature",
  "properties": {
    "iso:country":"CH",
    "sg:address":"Avenue Alfred-bertrand 4 1200 Genf. Postfach",
    "sg:city":"Gen\u00e8ve",
    "sg:orig_category":"Gesundheitswesen",
    "sg:postcode":"1201",
    "sg:province":"Gen\u00e8ve",
    "wof:name":"Aretaeus S\u00e0rl",
    "wof:placetype":"venue"
},
  "geometry": {"coordinates":[6.1537899971,46.1919746399],"type":"Point"}
}