{
  "type": "Feature",
  "properties": {
    "iso:country":"CH",
    "sg:address":"Signalstrasse 6 9400 Rorschach. Postfach",
    "sg:city":"Rorschach",
    "sg:orig_category":"Grosshandel mit Textilien",
    "sg:phone":"+41 71 335 09 70",
    "sg:postcode":"9400",
    "sg:province":"St. Gallen",
    "wof:name":"Rau & Co Ag Waren, Bes. Textilien Usw; Verkauf, Import, Export",
    "wof:placetype":"venue"
},
  "geometry": {"coordinates":[9.4921398163,47.4778785706],"type":"Point"}
}