{
  "type": "Feature",
  "properties": {
    "iso:country":"CH",
    "sg:address":"Aarestrasse 31a",
    "sg:city":"Heimberg",
    "sg:orig_category":"Unclassifiable Establishments",
    "sg:postcode":"3627",
    "sg:province":"Bern",
    "wof:name":"M\u00fcller Jascha Webdesign",
    "wof:placetype":"venue"
},
  "geometry": {"coordinates":[9.4028501511,47.434879303],"type":"Point"}
}