{
  "type": "Feature",
  "properties": {
    "iso:country":"CH",
    "sg:address":"Olivier Avenue Juste- 6 1006 Lausanne. Postfach",
    "sg:city":"Lausanne",
    "sg:orig_category":"Reiseb\u00fcros U Reiseveranstalter",
    "sg:postcode":"1006",
    "sg:province":"Vaud",
    "wof:name":"Rainbow Golfing, Jean-pierre Moirandat",
    "wof:placetype":"venue"
},
  "geometry": {"coordinates":[6.637111187,46.5161323547],"type":"Point"}
}