{
  "type": "Feature",
  "properties": {
    "iso:country":"CH",
    "sg:address":"Avenue De La Gare 39 1003 Lausanne Case Postale 615",
    "sg:city":"Lausanne",
    "sg:orig_category":"Verlagsgewerbe",
    "sg:phone":"+41 21 349 32 00",
    "sg:postcode":"1001",
    "sg:province":"Vaud",
    "wof:name":"Femina & T\u00e9l\u00e9-top-matin",
    "wof:placetype":"venue"
},
  "geometry": {"coordinates":[6.6340880394,46.5168762207],"type":"Point"}
}