{
  "type": "Feature",
  "properties": {
    "iso:country":"CH",
    "sg:address":"Hochwachtstrasse 30",
    "sg:city":"St.gallen",
    "sg:orig_category":"Allgemeiner Hoch U Tiefbau",
    "sg:postcode":"9000",
    "sg:province":"St. Gallen",
    "wof:name":"Rosenb\u00fcchel Bau Und Immobilien Ag, St. Gallen",
    "wof:placetype":"venue"
},
  "geometry": {"coordinates":[9.358195,47.411797],"type":"Point"}
}