{
  "type": "Feature",
  "properties": {
    "addr:full":"Buchmattstrasse 118 3400 Burgdorf. Postfach Burgdorf Bern 3401",
    "addr:housenumber":"118",
    "addr:postcode":"3400 burgdorf. postfach;3401",
    "addr:street":"Buchmattstrasse;Bern",
    "iso:country":"CH",
    "sg:address":"Buchmattstrasse 118 3400 Burgdorf. Postfach",
    "sg:city":"Burgdorf",
    "sg:orig_category":"Detailhandel mit Beleuchtungs U Haushaltsgegenst\u00e4nden Einbau von Schreinerwaren",
    "sg:phone":"+41 34 428 21 10",
    "sg:postcode":"3401",
    "sg:province":"Bern",
    "wof:name":"Fust Ag",
    "wof:placetype":"venue"
},
  "geometry": {"coordinates":[7.59976,47.067024],"type":"Point"}
}