{
  "type": "Feature",
  "properties": {
    "iso:country":"CH",
    "sg:address":"Bahnhofstrasse 12",
    "sg:city":"Villmergen",
    "sg:orig_category":"Detailhandel mit Waren verschiedener Art, Hauptrichtung Nahrungsmittel",
    "sg:phone":"+41 56 622 13 52",
    "sg:postcode":"5612",
    "sg:province":"Aargau",
    "wof:name":"Werner Stegm\u00fcller Handlung",
    "wof:placetype":"venue"
},
  "geometry": {"coordinates":[8.2456159592,47.3466033936],"type":"Point"}
}