{
  "type": "Feature",
  "properties": {
    "iso:country":"CH",
    "sg:address":"Kempttalstrasse 74",
    "sg:city":"Illnau",
    "sg:orig_category":"Malerei",
    "sg:phone":"+41 52 346 11 63",
    "sg:postcode":"8308",
    "sg:province":"Z\u00fcrich",
    "wof:name":"Walter Gujer Malergesch\u00e4ft",
    "wof:placetype":"venue"
},
  "geometry": {"coordinates":[8.7250261307,47.409992218],"type":"Point"}
}