{
  "type": "Feature",
  "properties": {
    "iso:country":"CH",
    "sg:address":"Zugerstrasse 50 6340 Baar. Postfach",
    "sg:city":"Baar",
    "sg:orig_category":"Unclassifiable Establishments",
    "sg:postcode":"6340",
    "sg:province":"Zug",
    "wof:name":"Hbm Bioventures Ag Beteiligungen Usw., Bes. Im Sektor Biotechnologie, Gesundheitswesen, Medizintechnik U. Pharma",
    "wof:placetype":"venue"
},
  "geometry": {"coordinates":[8.520857811,47.1869239807],"type":"Point"}
}