{
  "type": "Feature",
  "properties": {
    "iso:country":"CH",
    "sg:address":"Rieserstrasse 24",
    "sg:city":"Muttenz",
    "sg:orig_category":"Reiseb\u00fcros U Reiseveranstalter",
    "sg:phone":"+41 61 461 39 81",
    "sg:postcode":"4132",
    "sg:province":"Basel-Landschaft",
    "wof:name":"Sina Orient Tours",
    "wof:placetype":"venue"
},
  "geometry": {"coordinates":[7.6507201195,47.5184555054],"type":"Point"}
}