{
  "type": "Feature",
  "properties": {
    "iso:country":"CH",
    "sg:address":"Rue De La Plaine 84",
    "sg:city":"Yverdon-les-bains",
    "sg:orig_category":"Grosshandel mit Holz U Baustoffen Sonstiger Grosshandel",
    "sg:phone":"+41 24 426 72 27",
    "sg:postcode":"1400",
    "sg:province":"Vaud",
    "wof:name":"Benovatec Ag Automat.t\u00fcr-& Sicherheitsanl.",
    "wof:placetype":"venue"
},
  "geometry": {"coordinates":[6.6464319229,46.7766571045],"type":"Point"}
}