{
  "type": "Feature",
  "properties": {
    "iso:country":"CH",
    "sg:address":"M\u00f6nchstrasse 16",
    "sg:city":"Thun",
    "sg:orig_category":"Religi\u00f6se Vereinigungen divers",
    "sg:phone":"+41 33 222 32 01",
    "sg:postcode":"3600",
    "sg:province":"Bern",
    "wof:name":"Freimaurerloge Ph\u00f6nix",
    "wof:placetype":"venue"
},
  "geometry": {"coordinates":[7.6311907768,46.7522163391],"type":"Point"}
}