{
  "type": "Feature",
  "properties": {
    "iso:country":"CH",
    "sg:address":"Dorfstr. 87",
    "sg:city":"Trasadingen",
    "sg:orig_category":"Sonstiger Grosshandel",
    "sg:postcode":"8219",
    "sg:province":"Schaffhausen",
    "wof:name":"Koloseum Gmbh",
    "wof:placetype":"venue"
},
  "geometry": {"coordinates":[9.3602437973,47.4159584045],"type":"Point"}
}