{
  "type": "Feature",
  "properties": {
    "iso:country":"CH",
    "sg:address":"S\u00e4delstrasse 31",
    "sg:city":"Gerzensee",
    "sg:orig_category":"Unclassifiable Establishments",
    "sg:postcode":"3115",
    "sg:province":"Bern",
    "wof:name":"Simone G\u00fcrman",
    "wof:placetype":"venue"
},
  "geometry": {"coordinates":[6.4200940132,45.7529411316],"type":"Point"}
}