{
  "type": "Feature",
  "properties": {
    "iso:country":"CH",
    "sg:address":"Niderhof 2",
    "sg:city":"Marthalen",
    "sg:orig_category":"Detailhandel mit Schuhen Reparatur von Schuhen U Lederwaren",
    "sg:phone":"+41 41 850 13 85",
    "sg:postcode":"8460",
    "sg:province":"Z\u00fcrich",
    "wof:name":"Willi Z'graggen",
    "wof:placetype":"venue"
},
  "geometry": {"coordinates":[8.4375009537,47.0829811096],"type":"Point"}
}