{
  "type": "Feature",
  "properties": {
    "iso:country":"CH",
    "sg:address":"Gerechtigkeitsgasse 26",
    "sg:city":"Bern",
    "sg:orig_category":"Detailhandel mit B\u00fcchern Detailhandel mit B\u00fcchern, Zeitungen, Schreib U Papeteriewaren",
    "sg:phone":"+41 31 311 15 89",
    "sg:postcode":"3011",
    "sg:province":"Bern",
    "wof:name":"Chinderbuechlade Bern Ag Chibula",
    "wof:placetype":"venue"
},
  "geometry": {"coordinates":[7.4550819397,46.9486656189],"type":"Point"}
}