{
  "type": "Feature",
  "properties": {
    "iso:country":"CH",
    "sg:address":"Placa Du Village",
    "sg:city":"Rougemont",
    "sg:orig_category":"Detailhandel mit Geschenkartikeln U Souvenirs Erbringung von Dienstleistungen f\u00fcr Unternehmen",
    "sg:phone":"+41 26 925 94 00",
    "sg:postcode":"1838",
    "wof:name":"Tamara's S\u00e0rl",
    "wof:placetype":"venue"
},
  "geometry": {"coordinates":[-78.9260559082,36.2178535461],"type":"Point"}
}