{
  "type": "Feature",
  "properties": {
    "iso:country":"CH",
    "sg:address":"Steinwiesstrasse 26",
    "sg:city":"Z\u00fcrich",
    "sg:orig_category":"Finanzierungsinstitutionen Kunsthandel",
    "sg:phone":"+41 12681010",
    "sg:postcode":"8032",
    "sg:province":"Z\u00fcrich",
    "wof:name":"Christie's (international) Ag",
    "wof:placetype":"venue"
},
  "geometry": {"coordinates":[8.5524663925,47.3699417114],"type":"Point"}
}