{
  "type": "Feature",
  "properties": {
    "iso:country":"CH",
    "sg:address":"Lichtstrasse 35 4056 Basel. Postfach",
    "sg:city":"Basel",
    "sg:orig_category":"Kauf U Verkauf von Immobilien auf eigene Rechnung",
    "sg:postcode":"4051",
    "sg:province":"Basel-Stadt",
    "wof:name":"Graf Immo Gmbh Grundst\u00fccke Usw.",
    "wof:placetype":"venue"
},
  "geometry": {"coordinates":[9.3969125748,47.4498100281],"type":"Point"}
}