{
  "type": "Feature",
  "properties": {
    "iso:country":"CH",
    "sg:address":"Untertor 34",
    "sg:city":"Winterthur",
    "sg:classifiers":[
        {
            "category":"Restaurant",
            "type":"Food & Drink"
        }
    ],
    "sg:phone":"+41 52 212 09 05",
    "sg:postcode":"8400",
    "sg:province":"Z\u00fcrich",
    "wof:name":"Restaurant Gotthard 1900",
    "wof:placetype":"venue"
},
  "geometry": {"coordinates":[8.7240753174,47.4992675781],"type":"Point"}
}