{
  "type": "Feature",
  "properties": {
    "iso:country":"CH",
    "sg:address":"Hertenholz 2",
    "sg:city":"Meinisberg",
    "sg:orig_category":"Gem\u00fcsebau",
    "sg:phone":"+41 32 377 22 50",
    "sg:postcode":"2554",
    "sg:province":"Bern",
    "wof:name":"Paul Wanner Gem\u00fcsebau",
    "wof:placetype":"venue"
},
  "geometry": {"coordinates":[7.3401989937,47.1560897827],"type":"Point"}
}