{
  "type": "Feature",
  "properties": {
    "iso:country":"CH",
    "sg:address":"M\u00fchlematt 391",
    "sg:city":"Wohlenschwil",
    "sg:orig_category":"Softwareentwicklung U beratung",
    "sg:postcode":"5512",
    "sg:province":"Aargau",
    "wof:name":"Asb Strasser",
    "wof:placetype":"venue"
},
  "geometry": {"coordinates":[8.260020256,47.4124298096],"type":"Point"}
}