{
  "type": "Feature",
  "properties": {
    "iso:country":"CH",
    "sg:address":"Bellerivematte 7a",
    "sg:city":"Luzern",
    "sg:orig_category":"Unclassifiable Establishments",
    "sg:postcode":"6006",
    "sg:province":"Luzern",
    "wof:name":"Torben Maersk Consulting Gmbh",
    "wof:placetype":"venue"
},
  "geometry": {"coordinates":[8.3285751343,47.0562553406],"type":"Point"}
}