{
  "type": "Feature",
  "properties": {
    "iso:country":"CH",
    "sg:address":"Winkelstrasse 2",
    "sg:city":"Herisau",
    "sg:orig_category":"Sonstige Aktivit\u00e4ten der nicht-\u00e4rztlichen Medizinalberufe",
    "sg:phone":"+41 71 351 26 76",
    "sg:postcode":"9100",
    "sg:province":"Appenzell Ausserrhoden",
    "wof:name":"Anton B\u00e4chli Akupunktur",
    "wof:placetype":"venue"
},
  "geometry": {"coordinates":[9.2734308243,47.3910980225],"type":"Point"}
}