{
  "type": "Feature",
  "properties": {
    "iso:country":"CH",
    "sg:address":"Avenue De France 42",
    "sg:city":"Lausanne",
    "sg:orig_category":"Grafikateliers, Design",
    "sg:phone":"+41 22 797 22 09",
    "sg:postcode":"1004",
    "sg:province":"Vaud",
    "wof:name":"Jean-pierre Habegger Peinture D'enseignes",
    "wof:placetype":"venue"
},
  "geometry": {"coordinates":[6.1094369888,46.219783783],"type":"Point"}
}