{
  "type": "Feature",
  "properties": {
    "addr:full":"Kirchstrasse 1 Wallisellen Z\u00fcrich 8304",
    "addr:housenumber":"1",
    "addr:postcode":"8304",
    "addr:street":"Kirchstrasse",
    "iso:country":"CH",
    "sg:address":"Kirchstrasse 1",
    "sg:city":"Wallisellen",
    "sg:orig_category":"Architektur U Ingenieurb\u00fcros Architekturb\u00fcros",
    "sg:phone":"+41 91 985 20 70",
    "sg:postcode":"8304",
    "sg:province":"Z\u00fcrich",
    "wof:name":"Francesco Ghelfa Sa Studio D'architettura",
    "wof:placetype":"venue"
},
  "geometry": {"coordinates":[8.94522,46.058514],"type":"Point"}
}