{
  "type": "Feature",
  "properties": {
    "iso:country":"CH",
    "sg:address":"Sch\u00fctzenstrasse 27",
    "sg:city":"Urdorf",
    "sg:orig_category":"Herstellung von optischen U fotografischen Ger\u00e4ten",
    "sg:postcode":"8902",
    "sg:province":"Z\u00fcrich",
    "wof:name":"Laser Therapie Sekyra-rulf Dr. Gmbh",
    "wof:placetype":"venue"
},
  "geometry": {"coordinates":[8.6019382477,47.2991409302],"type":"Point"}
}