{
  "type": "Feature",
  "properties": {
    "iso:country":"CH",
    "sg:address":"Industriestrasse 17",
    "sg:city":"Neuenhof",
    "sg:orig_category":"Herstellung von Automobilen Herstellung von Metallerzeugnissen ohne Maschinenbau",
    "sg:phone":"+41 56 406 20 22",
    "sg:postcode":"5432",
    "sg:province":"Aargau",
    "wof:name":"Primus Transportger\u00e4te Ag",
    "wof:placetype":"venue"
},
  "geometry": {"coordinates":[8.3284196854,47.455078125],"type":"Point"}
}