{
  "type": "Feature",
  "properties": {
    "iso:country":"CH",
    "sg:address":"Buchenrain 5 8184 Bachenb\u00fclach. Postfach",
    "sg:city":"Bachenb\u00fclach",
    "sg:orig_category":"Non-Classified Establishments",
    "sg:postcode":"8184",
    "sg:province":"Z\u00fcrich",
    "wof:name":"Horv\u00e1th-montagen",
    "wof:placetype":"venue"
},
  "geometry": {"coordinates":[7.6605858803,47.4321403503],"type":"Point"}
}