{
  "type": "Feature",
  "properties": {
    "iso:country":"CH",
    "sg:address":"Wartbodenstrasse 1k 3626 H\u00fcnibach. Postfach",
    "sg:city":"H\u00fcnibach",
    "sg:orig_category":"Herstellung von medizinischen U chirurgischen Ger\u00e4ten sowie orthop\u00e4dischen Vorrichtungen",
    "sg:postcode":"3626",
    "sg:province":"Bern",
    "wof:name":"Orthopro Sa",
    "wof:placetype":"venue"
},
  "geometry": {"coordinates":[7.2500958443,47.194355011],"type":"Point"}
}