{
  "type": "Feature",
  "properties": {
    "addr:full":"Claragraben 43 Basel Basel-Stadt 4058",
    "addr:housenumber":"43",
    "addr:postcode":"4058",
    "addr:street":"Claragraben",
    "iso:country":"CH",
    "sg:address":"Claragraben 43",
    "sg:city":"Basel",
    "sg:orig_category":"Aktivit\u00e4ten der Krankenschwestern U Hebammen, Hauspflege Organisationen des Gesundheitswesen",
    "sg:phone":"+41 61 691 94 27",
    "sg:postcode":"4058",
    "sg:province":"Basel-Stadt",
    "wof:name":"Spitex Gemeindekrankenpflege St.theodor/st.clara",
    "wof:placetype":"venue"
},
  "geometry": {"coordinates":[7.595873,47.560543],"type":"Point"}
}