{
  "type": "Feature",
  "properties": {
    "iso:country":"CH",
    "sg:address":"G\u00fcterstrasse 15 2500 Biel/bienne. Postfach",
    "sg:city":"Biel/bienne",
    "sg:orig_category":"Detailhandel mit B\u00fcchern, Zeitungen, Schreib U Papeteriewaren",
    "sg:postcode":"2502",
    "sg:province":"Bern",
    "wof:name":"Kiosk Steiner Dagmar",
    "wof:placetype":"venue"
},
  "geometry": {"coordinates":[7.246252,47.135128],"type":"Point"}
}