{
  "type": "Feature",
  "properties": {
    "iso:country":"CH",
    "sg:address":"Feldheim",
    "sg:city":"Steinhausen",
    "sg:orig_category":"Vorschulen, Kinderg\u00e4rten",
    "sg:phone":"+41 41 741 25 84",
    "sg:postcode":"6312",
    "sg:province":"Zug",
    "wof:name":"Kindergarten Feldheim",
    "wof:placetype":"venue"
},
  "geometry": {"coordinates":[8.4900770187,47.1913108826],"type":"Point"}
}