{
  "type": "Feature",
  "properties": {
    "iso:country":"CH",
    "sg:address":"Via Gemmo 11 6900 Lugano. Postfach",
    "sg:city":"Lugano",
    "sg:orig_category":"Alters U Hinterlassenenversicherung AHV, Invalidenversicherung IV, Arbeitslosenversicherung ALV",
    "sg:phone":"+41 22 795 91 11",
    "sg:postcode":"6903",
    "sg:province":"Ticino",
    "wof:name":"Centrale De Compensation Fonds De L'avs Office Ai",
    "wof:placetype":"venue"
},
  "geometry": {"coordinates":[6.118449,46.215431],"type":"Point"}
}