{
  "type": "Feature",
  "properties": {
    "iso:country":"CH",
    "sg:address":"B\u00fctzbergstrasse 98",
    "sg:city":"Langenthal",
    "sg:orig_category":"Instandhaltung U Reparatur von Automobilen",
    "sg:phone":"+41 62 916 10 10",
    "sg:postcode":"4900",
    "sg:province":"Bern",
    "wof:name":"Garage Gautschi Ag",
    "wof:placetype":"venue"
},
  "geometry": {"coordinates":[7.7702651024,47.2171821594],"type":"Point"}
}