{
  "type": "Feature",
  "properties": {
    "iso:country":"CH",
    "sg:address":"Trottenweg 2",
    "sg:city":"Kleinandelfingen",
    "sg:orig_category":"Instandhaltung U Reparatur von Automobilen",
    "sg:phone":"+41 71 944 20 26",
    "sg:postcode":"8451",
    "sg:province":"Z\u00fcrich",
    "wof:name":"Garage Hinnen Roland",
    "wof:placetype":"venue"
},
  "geometry": {"coordinates":[9.0644187927,47.4640769958],"type":"Point"}
}