{
  "type": "Feature",
  "properties": {
    "iso:country":"CH",
    "sg:address":"Grande-rue 45",
    "sg:city":"Aubonne",
    "sg:orig_category":"Detailhandel mit Fahrr\u00e4dern Handel mit Motorr\u00e4dern, Teilen U Zubeh\u00f6r Instandhaltung U Reparatur von ",
    "sg:phone":"+41 21 808 53 78",
    "sg:postcode":"1170",
    "sg:province":"Vaud",
    "wof:name":"Jacky Noverraz Cycles & Motos",
    "wof:placetype":"venue"
},
  "geometry": {"coordinates":[6.3896369934,46.4957618713],"type":"Point"}
}