{
  "type": "Feature",
  "properties": {
    "iso:country":"CH",
    "sg:address":"Gutenbr\u00fcnnenweg 67",
    "sg:city":"Kaufdorf",
    "sg:classifiers":[
        {
            "category":"Travel",
            "subcategory":"Hotels & Motels",
            "type":"Entertainment"
        }
    ],
    "sg:phone":"+41 31 809 15 21",
    "sg:postcode":"3126",
    "sg:province":"Bern",
    "sg:tags":[
        "hotels",
        "mit",
        "restaurant"
    ],
    "wof:name":"Hotel Gutenbr\u00fcnnen",
    "wof:placetype":"venue"
},
  "geometry": {"coordinates":[7.4986290932,46.8381843567],"type":"Point"}
}