{
  "type": "Feature",
  "properties": {
    "addr:full":"Sihlfeldstrasse 81 Z\u00fcrich Z\u00fcrich 8004",
    "addr:housenumber":"81",
    "addr:postcode":"8004",
    "addr:street":"Sihlfeldstrasse",
    "iso:country":"CH",
    "sg:address":"Sihlfeldstrasse 81",
    "sg:city":"Z\u00fcrich",
    "sg:orig_category":"Arztpraxen",
    "sg:phone":"+41 12404999",
    "sg:postcode":"8004",
    "sg:province":"Z\u00fcrich",
    "wof:name":"Dr.med.thomas A. Ermatinger Arzt F\u00fcr Allgemeine Medizin",
    "wof:placetype":"venue"
},
  "geometry": {"coordinates":[8.516609,47.375698],"type":"Point"}
}