{
  "type": "Feature",
  "properties": {
    "iso:country":"CH",
    "sg:address":"B\u00fcel",
    "sg:city":"Niederteufen",
    "sg:orig_category":"Non-Classified Establishments",
    "sg:phone":"+41 71 649 21 11",
    "sg:postcode":"9052",
    "sg:province":"Appenzell Ausserrhoden",
    "wof:name":"Alid Holding Ag",
    "wof:placetype":"venue"
},
  "geometry": {"coordinates":[9.3642950058,47.3936843872],"type":"Point"}
}