{
  "type": "Feature",
  "properties": {
    "iso:country":"CH",
    "sg:address":"Dailles Route Des 1958 St-l\u00e9onard. Postfach",
    "sg:city":"St-l\u00e9onard",
    "sg:orig_category":"Herstellung von sonstigen landwirtschaftlichen Maschinen",
    "sg:phone":"+41 27 203 45 03",
    "sg:postcode":"1958",
    "sg:province":"Valais",
    "wof:name":"Morard Meinrad, Machines Agricoles, Installations De Ferme Machines Agricoles; Vente Et R\u00e9paration Etc",
    "wof:placetype":"venue"
},
  "geometry": {"coordinates":[7.4179301262,46.2533912659],"type":"Point"}
}