{
  "type": "Feature",
  "properties": {
    "iso:country":"CH",
    "sg:address":"Hasel 17",
    "sg:city":"Termen",
    "sg:orig_category":"Unternehmensberatung",
    "sg:phone":"+41 27 924 39 79",
    "sg:postcode":"3912",
    "sg:province":"Valais",
    "wof:name":"Wallital Baldo & Co.",
    "wof:placetype":"venue"
},
  "geometry": {"coordinates":[8.0285549164,46.3254318237],"type":"Point"}
}