{
  "type": "Feature",
  "properties": {
    "iso:country":"CH",
    "sg:address":"Crans-chermignon",
    "sg:city":"Lens",
    "sg:orig_category":"Vermietung U Verpachtung von eigenen Immobilien",
    "sg:phone":"+41 27 481 31 61",
    "sg:postcode":"1978",
    "sg:province":"Valais",
    "wof:name":"Falvar Sa",
    "wof:placetype":"venue"
},
  "geometry": {"coordinates":[7.4507079124,46.2817382812],"type":"Point"}
}