{
  "type": "Feature",
  "properties": {
    "iso:country":"CH",
    "sg:address":"Baselstrasse 67",
    "sg:city":"Grellingen",
    "sg:orig_category":"Autogaragen",
    "sg:phone":"+41 61 741 16 66",
    "sg:postcode":"4203",
    "sg:province":"Basel-Landschaft",
    "wof:name":"Pierre M\u00fcller Garage",
    "wof:placetype":"venue"
},
  "geometry": {"coordinates":[7.598061,47.443443],"type":"Point"}
}