{
  "type": "Feature",
  "properties": {
    "iso:country":"CH",
    "sg:address":"Rue De L'industrie 17",
    "sg:city":"Tramelan",
    "sg:orig_category":"Arztpraxen",
    "sg:phone":"+41 32 487 40 28",
    "sg:postcode":"2720",
    "sg:province":"Bern",
    "wof:name":"Dr M\u00e9d. Pierre-alain Meyer M\u00e9decin G\u00e9n\u00e9raliste Fmh",
    "wof:placetype":"venue"
},
  "geometry": {"coordinates":[7.097228,47.223763],"type":"Point"}
}