{
  "type": "Feature",
  "properties": {
    "iso:country":"CH",
    "sg:address":"Avenue Juste-olivier 15",
    "sg:city":"Lausanne",
    "sg:orig_category":"Detailhandel mit Beleuchtungs U Haushaltsgegenst\u00e4nden Innendekorationsateliers",
    "sg:phone":"+41 21 320 08 92",
    "sg:postcode":"1006",
    "sg:province":"Vaud",
    "wof:name":"Rideaux D\u00e9co Christiane Vocat D\u00e9coration D'int\u00e9rieur",
    "wof:placetype":"venue"
},
  "geometry": {"coordinates":[6.636743,46.514637],"type":"Point"}
}