{
  "type": "Feature",
  "properties": {
    "iso:country":"CH",
    "sg:address":"Florastrasse 49 8008 Z\u00fcrich. Postfach",
    "sg:city":"Z\u00fcrich",
    "sg:orig_category":"Non-Classified Establishments",
    "sg:phone":"+41 13832048",
    "sg:postcode":"8001",
    "sg:province":"Z\u00fcrich",
    "wof:name":"Inter Clamp Holding Ag Beteiligungen Usw",
    "wof:placetype":"venue"
},
  "geometry": {"coordinates":[8.5528945923,47.3619651794],"type":"Point"}
}