{
  "type": "Feature",
  "properties": {
    "iso:country":"CH",
    "sg:address":"Viale Canavee 2",
    "sg:city":"Mendrisio",
    "sg:orig_category":"Kosmetikinstitute",
    "sg:phone":"+41 91 646 13 54",
    "sg:postcode":"6850",
    "sg:province":"Ticino",
    "wof:name":"Marzia Vergani Istituto Di Bellezza Marzia",
    "wof:placetype":"venue"
},
  "geometry": {"coordinates":[8.9837007523,45.8663787842],"type":"Point"}
}