{
  "type": "Feature",
  "properties": {
    "iso:country":"CH",
    "sg:address":"Via Cantonale 73",
    "sg:city":"Magliaso",
    "sg:orig_category":"Herstellung von Wein Rebbau",
    "sg:phone":"+41 91 606 10 91",
    "sg:postcode":"6983",
    "sg:province":"Ticino",
    "wof:name":"Tenuta Del Torchio Sagl",
    "wof:placetype":"venue"
},
  "geometry": {"coordinates":[8.8799161911,45.9821968079],"type":"Point"}
}