{
  "type": "Feature",
  "properties": {
    "iso:country":"CH",
    "sg:address":"Kaiserstrasse 7b",
    "sg:city":"Rheinfelden",
    "sg:orig_category":"Fachdetailhandel mit pharmazeutischen Produkten",
    "sg:phone":"+41 61 831 18 18",
    "sg:postcode":"4310",
    "sg:province":"Aargau",
    "wof:name":"Rosenau-apotheke Almapharm Ag",
    "wof:placetype":"venue"
},
  "geometry": {"coordinates":[7.7941589355,47.5523300171],"type":"Point"}
}