{
  "type": "Feature",
  "properties": {
    "iso:country":"CH",
    "sg:address":"Gerechtigkeitsgasse 56",
    "sg:city":"Bern",
    "sg:orig_category":"Detailhandel mit Damenbekleidung",
    "sg:phone":"+41 31 311 27 72",
    "sg:postcode":"3011",
    "sg:province":"Bern",
    "wof:name":"Boutique More For Less Second Season Damenkleider",
    "wof:placetype":"venue"
},
  "geometry": {"coordinates":[7.453553,46.948303],"type":"Point"}
}