{
  "type": "Feature",
  "properties": {
    "iso:country":"CH",
    "sg:address":"Z\u00fcrichstrasse 37",
    "sg:city":"Neftenbach",
    "sg:orig_category":"Detailhandel mit Blumen U Pflanzen Fachdetailhandel in Verkaufsr\u00e4umen",
    "sg:phone":"+41 52 315 37 38",
    "sg:postcode":"8413",
    "sg:province":"Z\u00fcrich",
    "wof:name":"B\u00fcchi's Bluemel\u00e4deli",
    "wof:placetype":"venue"
},
  "geometry": {"coordinates":[8.663863,47.526943],"type":"Point"}
}