{
  "type": "Feature",
  "properties": {
    "iso:country":"CH",
    "sg:address":"Bahnhofstrasse 29 6078 Lungern. Postfach 49",
    "sg:city":"Lungern",
    "sg:orig_category":"Organisationen des Gesundheitswesen",
    "sg:phone":"+41 41 678 19 59",
    "sg:postcode":"6078",
    "sg:province":"Obwalden",
    "wof:name":"Verein F\u00fcr Krankenpflege Frau H\u00e9l\u00e8ne Hofer",
    "wof:placetype":"venue"
},
  "geometry": {"coordinates":[8.1630582809,46.7870025635],"type":"Point"}
}