{
  "type": "Feature",
  "properties": {
    "iso:country":"CH",
    "sg:address":"Buchholzstrasse 83",
    "sg:city":"Z\u00fcrich",
    "sg:orig_category":"Fernmeldedienste",
    "sg:phone":"+41 12710070",
    "sg:postcode":"8053",
    "sg:province":"Z\u00fcrich",
    "wof:name":"A Marca De Donatz Gmbh",
    "wof:placetype":"venue"
},
  "geometry": {"coordinates":[8.5870990753,47.3608512878],"type":"Point"}
}