{
  "type": "Feature",
  "properties": {
    "iso:country":"CH",
    "sg:address":"Sonnhalde 13",
    "sg:city":"Benglen",
    "sg:orig_category":"Non-Classified Establishments",
    "sg:postcode":"8121",
    "sg:province":"Z\u00fcrich",
    "wof:name":"Home Interiors Ag",
    "wof:placetype":"venue"
},
  "geometry": {"coordinates":[8.6359739304,47.3582496643],"type":"Point"}
}