{
  "type": "Feature",
  "properties": {
    "iso:country":"CH",
    "sg:address":"Bahnhofstrasse 13 6130 Willisau. Postfach",
    "sg:city":"Willisau",
    "sg:orig_category":"Markt U Meinungsforschung Unternehmensberatung",
    "sg:phone":"+41 41 970 20 80",
    "sg:postcode":"6130",
    "sg:province":"Luzern",
    "wof:name":"Ap Marketing Steinmann Tony",
    "wof:placetype":"venue"
},
  "geometry": {"coordinates":[7.995265007,47.1219291687],"type":"Point"}
}