{
  "type": "Feature",
  "properties": {
    "iso:country":"CH",
    "sg:address":"Oberwilerstrasse 21",
    "sg:city":"Therwil",
    "sg:orig_category":"Herstellung von Schmuck, Gold U Silberschmiedwaren Kunsthandel",
    "sg:phone":"+41 61 721 54 58",
    "sg:postcode":"4106",
    "sg:province":"Basel-Landschaft",
    "wof:name":"Gebr.g. & B. Hasenb\u00f6hler",
    "wof:placetype":"venue"
},
  "geometry": {"coordinates":[7.5534658432,47.5004920959],"type":"Point"}
}