{
  "type": "Feature",
  "properties": {
    "iso:country":"CH",
    "sg:address":"Hertistrasse 29",
    "sg:city":"Wallisellen",
    "sg:orig_category":"Softwareentwicklung U beratung",
    "sg:postcode":"8304",
    "sg:province":"Z\u00fcrich",
    "wof:name":"H\u00e4schmi Martin Schmid",
    "wof:placetype":"venue"
},
  "geometry": {"coordinates":[7.8686690331,47.3450698853],"type":"Point"}
}