{
  "type": "Feature",
  "properties": {
    "iso:country":"CH",
    "sg:address":"Bois-de-bay Route Du 61",
    "sg:city":"Satigny",
    "sg:orig_category":"R\u00fcckgewinnung U Vorbereitung f\u00fcr die Wiederverwertung Recycling von Schrott",
    "sg:phone":"+41 32 493 55 92",
    "sg:postcode":"1242",
    "sg:province":"Gen\u00e8ve",
    "wof:name":"D\u00e9molition Helbling",
    "wof:placetype":"venue"
},
  "geometry": {"coordinates":[7.385032177,47.3029441833],"type":"Point"}
}