{
  "type": "Feature",
  "properties": {
    "iso:country":"CH",
    "sg:address":"Schulstrasse 33",
    "sg:city":"Thun",
    "sg:orig_category":"Primarschulen",
    "sg:phone":"+41 33 336 17 00",
    "sg:postcode":"3604",
    "sg:province":"Bern",
    "wof:name":"Primarschule D\u00fcrrenast",
    "wof:placetype":"venue"
},
  "geometry": {"coordinates":[7.6217498779,46.7397346497],"type":"Point"}
}