{
  "type": "Feature",
  "properties": {
    "addr:full":"Kernstrasse 57 Z\u00fcrich Z\u00fcrich 8004",
    "addr:housenumber":"57",
    "addr:postcode":"8004",
    "addr:street":"Kernstrasse",
    "iso:country":"CH",
    "sg:address":"Kernstrasse 57",
    "sg:city":"Z\u00fcrich",
    "sg:orig_category":"Architektur U Ingenieurb\u00fcros Architekturb\u00fcros",
    "sg:phone":"+41 12419933",
    "sg:postcode":"8004",
    "sg:province":"Z\u00fcrich",
    "wof:name":"Amz Architekten Ag",
    "wof:placetype":"venue"
},
  "geometry": {"coordinates":[8.525832,47.377991],"type":"Point"}
}