{
  "type": "Feature",
  "properties": {
    "iso:country":"CH",
    "sg:address":"Chartreusestrasse 7",
    "sg:city":"H\u00fcnibach",
    "sg:orig_category":"Hochschulen U h\u00f6here Ausbildung",
    "sg:postcode":"3626",
    "sg:province":"Bern",
    "wof:name":"Stiftung Hsg Alumni",
    "wof:placetype":"venue"
},
  "geometry": {"coordinates":[9.3755378723,47.4308624268],"type":"Point"}
}