{
  "type": "Feature",
  "properties": {
    "iso:country":"CH",
    "sg:address":"Pretorio Via 7",
    "sg:city":"Lugano",
    "sg:orig_category":"G\u00fcterbef\u00f6rderung im Strassenverkehr",
    "sg:postcode":"6900",
    "sg:province":"Ticino",
    "wof:name":"Mezhduna Trading Sa",
    "wof:placetype":"venue"
},
  "geometry": {"coordinates":[8.951464653,46.0056495667],"type":"Point"}
}