{
  "type": "Feature",
  "properties": {
    "iso:country":"CH",
    "sg:address":"Baslerstrasse 86",
    "sg:city":"Allschwil",
    "sg:orig_category":"Pensionskassen",
    "sg:phone":"+41 61 481 63 86",
    "sg:postcode":"4123",
    "sg:province":"Basel-Landschaft",
    "wof:name":"Wohlfahrtsfonds Der Firma Springinsfeld Ag",
    "wof:placetype":"venue"
},
  "geometry": {"coordinates":[7.5419540405,47.5527915955],"type":"Point"}
}