{
  "type": "Feature",
  "properties": {
    "iso:country":"CH",
    "sg:address":"Chemin Emile-javelle 12",
    "sg:city":"Vevey",
    "sg:orig_category":"Glaserei Herstellung von sonstigen M\u00f6beln",
    "sg:phone":"+41 79 210 54 79",
    "sg:postcode":"1800",
    "sg:province":"Vaud",
    "wof:name":"Stasi Robert",
    "wof:placetype":"venue"
},
  "geometry": {"coordinates":[6.854886055,46.4583282471],"type":"Point"}
}