{
  "type": "Feature",
  "properties": {
    "iso:country":"CH",
    "sg:address":"Grienbachstrasse 17",
    "sg:city":"Zug",
    "sg:orig_category":"Binnenschiffahrt",
    "sg:phone":"+41 41 761 98 15",
    "sg:postcode":"6300",
    "sg:province":"Zug",
    "wof:name":"Rondeau Bulk Ag",
    "wof:placetype":"venue"
},
  "geometry": {"coordinates":[8.523443,47.183281],"type":"Point"}
}