{
  "type": "Feature",
  "properties": {
    "iso:country":"CH",
    "sg:address":"Lerchenstrasse 22",
    "sg:city":"Netstal",
    "sg:orig_category":"Grosshandel mit sonstigen Halbwaren",
    "sg:phone":"+41 55 640 74 68",
    "sg:postcode":"8754",
    "sg:province":"Glarus",
    "wof:name":"Mettler Zwirn Ag",
    "wof:placetype":"venue"
},
  "geometry": {"coordinates":[9.0518379211,47.0543441772],"type":"Point"}
}