{
  "type": "Feature",
  "properties": {
    "iso:country":"CH",
    "sg:address":"Poststrasse 18 6300 Zug. Postfach 455",
    "sg:city":"Zug",
    "sg:orig_category":"Gesundheits\u00e4mter",
    "sg:phone":"+41 21 316 42 00",
    "sg:postcode":"6301",
    "sg:province":"Zug",
    "wof:name":"Service De La Sant\u00e9 Publique",
    "wof:placetype":"venue"
},
  "geometry": {"coordinates":[6.6334500313,46.5194282532],"type":"Point"}
}