{
  "type": "Feature",
  "properties": {
    "addr:full":"Multergasse 22 St.gallen St. Gallen 9000",
    "addr:housenumber":"22",
    "addr:postcode":"9000",
    "addr:street":"Multergasse",
    "iso:country":"CH",
    "sg:address":"Multergasse 22",
    "sg:city":"St.gallen",
    "sg:classifiers":[
        {
            "category":"Bars & Pubs",
            "type":"Food & Drink"
        }
    ],
    "sg:phone":"+41 71 222 64 94",
    "sg:postcode":"9000",
    "sg:province":"St. Gallen",
    "wof:name":"Baracca Gmbh",
    "wof:placetype":"venue"
},
  "geometry": {"coordinates":[9.371523,47.421192],"type":"Point"}
}