{
  "type": "Feature",
  "properties": {
    "iso:country":"CH",
    "sg:address":"Grand-rue 23",
    "sg:city":"Gen\u00e8ve",
    "sg:orig_category":"Reiseb\u00fcros U Reiseveranstalter",
    "sg:phone":"+41 22 818 00 40",
    "sg:postcode":"1204",
    "sg:province":"Gen\u00e8ve",
    "wof:name":"Bc Business Class Sa",
    "wof:placetype":"venue"
},
  "geometry": {"coordinates":[6.1459441185,46.2018852234],"type":"Point"}
}