{
  "type": "Feature",
  "properties": {
    "iso:country":"CH",
    "sg:address":"Via Quartier Nuovo",
    "sg:city":"Lostallo",
    "sg:orig_category":"Allgemeiner Hoch U Tiefbau",
    "sg:phone":"+41 91 830 11 78",
    "sg:postcode":"6558",
    "sg:province":"Graubunden",
    "wof:name":"Studio D'ingegneria Franciolli Sa",
    "wof:placetype":"venue"
},
  "geometry": {"coordinates":[9.195985,46.313126],"type":"Point"}
}