{
  "type": "Feature",
  "properties": {
    "iso:country":"CH",
    "sg:address":"Vicques Route De 1",
    "sg:city":"Courrendlin",
    "sg:orig_category":"RESTAURANTS: TEA-ROOMS",
    "sg:phone":"+41 32 435 59 14",
    "sg:postcode":"2830",
    "sg:province":"Jura",
    "wof:name":"Droz-dit-busset Christian",
    "wof:placetype":"venue"
},
  "geometry": {"coordinates":[7.3730211258,47.3398246765],"type":"Point"}
}