{
  "type": "Feature",
  "properties": {
    "iso:country":"CH",
    "sg:address":"Brunnackerstrasse 8",
    "sg:city":"Stettfurt",
    "sg:orig_category":"Sonstiger Grosshandel",
    "sg:phone":"+41 52 369 69 29",
    "sg:postcode":"9507",
    "sg:province":"Thurgau",
    "wof:name":"Rioca Import - Export Gmbh",
    "wof:placetype":"venue"
},
  "geometry": {"coordinates":[8.9530973434,47.5263252258],"type":"Point"}
}