{
  "type": "Feature",
  "properties": {
    "iso:country":"CH",
    "sg:address":"Gerbergasse 30",
    "sg:city":"Basel",
    "sg:orig_category":"Darlehenskassen U Raiffeisenbanken Spezialkreditinstitute",
    "sg:phone":"+41 71 222 92 22",
    "sg:postcode":"4001",
    "sg:province":"Basel-Stadt",
    "wof:name":"Evangelische B\u00fcrgschafts Und Darlehensgenossenschaft Des Kantons St. Gallen (hika)",
    "wof:placetype":"venue"
},
  "geometry": {"coordinates":[9.377158,47.424725],"type":"Point"}
}