{
  "type": "Feature",
  "properties": {
    "iso:country":"CH",
    "sg:address":"Bernstrasse 1",
    "sg:city":"Worb",
    "sg:orig_category":"Stickerei",
    "sg:phone":"+41 31 839 25 55",
    "sg:postcode":"3076",
    "sg:province":"Bern",
    "wof:name":"Max Speich Stickerei",
    "wof:placetype":"venue"
},
  "geometry": {"coordinates":[7.5584998131,46.9294395447],"type":"Point"}
}