{
  "type": "Feature",
  "properties": {
    "iso:country":"CH",
    "sg:address":"Kramgasse 33 3011 Bern. Postfach",
    "sg:city":"Bern",
    "sg:orig_category":"Non-Classified Establishments",
    "sg:phone":"+41 71 244 29 53",
    "sg:postcode":"3011",
    "sg:province":"Bern",
    "wof:name":"Investmodels.com Ag Bereitstellung B\u00f6rsen- U. Fondsbezogener Informationen Aus Dem Internet Usw.",
    "wof:placetype":"venue"
},
  "geometry": {"coordinates":[9.3732051849,47.4279899597],"type":"Point"}
}