{
  "type": "Feature",
  "properties": {
    "iso:country":"CH",
    "sg:address":"Riehenstrasse 74 4058 Basel. Postfach",
    "sg:city":"Basel",
    "sg:orig_category":"Kauf U Verkauf von Immobilien auf eigene Rechnung",
    "sg:postcode":"4051",
    "sg:province":"Basel-Stadt",
    "wof:name":"Agb Langnau, Ag F\u00fcr Das Bauen",
    "wof:placetype":"venue"
},
  "geometry": {"coordinates":[7.757589817,46.9491271973],"type":"Point"}
}