{
  "type": "Feature",
  "properties": {
    "iso:country":"CH",
    "sg:address":"Les Trois Bornes 17",
    "sg:city":"Courtelary",
    "sg:orig_category":"Sonstiges Druckgewerbe",
    "sg:postcode":"2608",
    "sg:province":"Bern",
    "wof:name":"Meier Success",
    "wof:placetype":"venue"
},
  "geometry": {"coordinates":[7.0673961639,47.1789894104],"type":"Point"}
}