{
  "type": "Feature",
  "properties": {
    "iso:country":"CH",
    "sg:address":"Rheinstrasse 81",
    "sg:city":"Frenkendorf",
    "sg:orig_category":"Sportvereine Sch\u00fctzen",
    "sg:phone":"+41 61 901 89 12",
    "sg:postcode":"4402",
    "sg:province":"Basel-Landschaft",
    "wof:name":"Sch\u00fctzengesellschaft",
    "wof:placetype":"venue"
},
  "geometry": {"coordinates":[7.7209448814,47.5070228577],"type":"Point"}
}