{
  "type": "Feature",
  "properties": {
    "iso:country":"CH",
    "sg:address":"Hofgasse 8",
    "sg:city":"Arlesheim",
    "sg:orig_category":"Vorschulen, Kinderg\u00e4rten",
    "sg:postcode":"4144",
    "sg:province":"Basel-Landschaft",
    "wof:name":"Kindergarten Hofgasse",
    "wof:placetype":"venue"
},
  "geometry": {"coordinates":[7.6222000122,47.4943962097],"type":"Point"}
}