{
  "type": "Feature",
  "properties": {
    "iso:country":"CH",
    "sg:address":"Chemin Saint-hubert 40 1950 Sion Case Postale",
    "sg:city":"Sion",
    "sg:orig_category":"Werbevermittlung",
    "sg:phone":"+41 27 323 48 58",
    "sg:postcode":"1951",
    "sg:province":"Valais",
    "wof:name":"Sga/apg Soci\u00e9t\u00e9 G\u00e9n\u00e9rale D'affichage",
    "wof:placetype":"venue"
},
  "geometry": {"coordinates":[7.3525948524,46.2222175598],"type":"Point"}
}