{
  "type": "Feature",
  "properties": {
    "iso:country":"CH",
    "sg:address":"Hauptstrasse 13",
    "sg:city":"Worben",
    "sg:orig_category":"RESTAURANTS: TEA-ROOMS",
    "sg:phone":"+41 71 222 58 60",
    "sg:postcode":"3252",
    "sg:province":"Bern",
    "wof:name":"Restaurant Il Kolosseum Larcher Riccardo",
    "wof:placetype":"venue"
},
  "geometry": {"coordinates":[9.3728971481,47.4254875183],"type":"Point"}
}