{
  "type": "Feature",
  "properties": {
    "iso:country":"CH",
    "sg:address":"Brent",
    "sg:city":"Montreux",
    "sg:orig_category":"Verwertung von Milch",
    "sg:postcode":"1820",
    "sg:province":"Vaud",
    "wof:name":"Soci\u00e9t\u00e9 Des Alpages De Jaman",
    "wof:placetype":"venue"
},
  "geometry": {"coordinates":[6.8976941109,46.4554023743],"type":"Point"}
}