{
  "type": "Feature",
  "properties": {
    "iso:country":"CH",
    "sg:address":"Schmidtengasse 2",
    "sg:city":"Reigoldswil",
    "sg:orig_category":"Sonstige Hilfsdienste des Kultur U Unterhaltungswesens Verlag von bespielten Tontr\u00e4gern",
    "sg:phone":"+41 61 943 91 18",
    "sg:postcode":"4418",
    "sg:province":"Basel-Landschaft",
    "wof:name":"Chantal & David Denham More Music Entertainments",
    "wof:placetype":"venue"
},
  "geometry": {"coordinates":[7.692565918,47.3982429504],"type":"Point"}
}