{
  "type": "Feature",
  "properties": {
    "iso:country":"CH",
    "sg:address":"Kirchweg 6b",
    "sg:city":"Zuchwil",
    "sg:orig_category":"Instandhaltung U Reparatur von Automobilen",
    "sg:phone":"+41 21 921 20 20",
    "sg:postcode":"4528",
    "sg:province":"Solothurn",
    "wof:name":"Sas Service Auto Secours S\u00e0rl D\u00e9pannage, Transport De V\u00e9hicules, Atelier De R\u00e9paration Etc",
    "wof:placetype":"venue"
},
  "geometry": {"coordinates":[6.8432750702,46.4621353149],"type":"Point"}
}