{
  "type": "Feature",
  "properties": {
    "iso:country":"CH",
    "sg:address":"Rte De Sion 4 3960 Sierre Case Postale",
    "sg:city":"Siders",
    "sg:orig_category":"Non-Classified Establishments",
    "sg:postcode":"3960",
    "sg:province":"Valais",
    "wof:name":"Gracia F\u00e9lix Organisation De Bureau Felix. Achat, Vente, R\u00e9paration De Machines De Bureau, Caisses, Etc",
    "wof:placetype":"venue"
},
  "geometry": {"coordinates":[7.5262942314,46.2913818359],"type":"Point"}
}