{
  "type": "Feature",
  "properties": {
    "iso:country":"CH",
    "sg:address":"Frutigenstrasse 25",
    "sg:city":"Thun",
    "sg:orig_category":"Vermietung U Verpachtung von eigenen Immobilien",
    "sg:phone":"+41 32 931 21 02",
    "sg:postcode":"3600",
    "sg:province":"Bern",
    "wof:name":"Matile Charles-eug\u00e8ne & Cie",
    "wof:placetype":"venue"
},
  "geometry": {"coordinates":[6.7498149872,47.058921814],"type":"Point"}
}