{
  "type": "Feature",
  "properties": {
    "iso:country":"CH",
    "sg:address":"Sedelstrasse 30 6004 Luzern. Postfach",
    "sg:city":"Luzern",
    "sg:orig_category":"Unternehmensberatung",
    "sg:phone":"+41 41 420 32 58",
    "sg:postcode":"6004",
    "sg:province":"Luzern",
    "wof:name":"Meier Stefan Unternehmensberatung Unternehmensberatung. Edv- Service-leistungen. Software; Herstellung U. Handel. Internet",
    "wof:placetype":"venue"
},
  "geometry": {"coordinates":[8.3009462357,47.0624198914],"type":"Point"}
}