{
  "type": "Feature",
  "properties": {
    "iso:country":"CH",
    "sg:address":"Altgasse 82",
    "sg:city":"Baar",
    "sg:orig_category":"Gesundheitswesen",
    "sg:phone":"+41 41 763 19 63",
    "sg:postcode":"6340",
    "sg:province":"Zug",
    "wof:name":"Belle Body Ag",
    "wof:placetype":"venue"
},
  "geometry": {"coordinates":[8.5167999268,47.1905403137],"type":"Point"}
}