{
  "type": "Feature",
  "properties": {
    "iso:country":"CH",
    "sg:address":"Rheinstr.",
    "sg:city":"Trimmis",
    "sg:classifiers":[
        {
            "category":"Manufacturing",
            "subcategory":"Metals",
            "type":"Manufacturing & Wholesale Goods"
        }
    ],
    "sg:phone":"+41 32 933 06 66",
    "sg:postcode":"7203",
    "sg:province":"Graubunden",
    "sg:tags":[
        "-",
        "machine",
        "equipment",
        "engineering",
        "machinery",
        "mechanical"
    ],
    "wof:name":"Emissa Sa",
    "wof:placetype":"venue"
},
  "geometry": {"coordinates":[6.7392778397,47.0541343689],"type":"Point"}
}