{
  "type": "Feature",
  "properties": {
    "iso:country":"CH",
    "sg:address":"Florastrasse 28 2500 Biel/bienne. Postfach",
    "sg:city":"Biel/bienne",
    "sg:orig_category":"Instandhaltung U Reparatur von Automobilen",
    "sg:phone":"+41 32221921",
    "sg:postcode":"2502",
    "sg:province":"Bern",
    "wof:name":"Zingg Ulrich",
    "wof:placetype":"venue"
},
  "geometry": {"coordinates":[7.2489547729,47.138759613],"type":"Point"}
}