{
  "type": "Feature",
  "properties": {
    "iso:country":"CH",
    "sg:address":"Via Cantonale",
    "sg:city":"Grono",
    "sg:orig_category":"Fachdetailhandel mit pharmazeutischen Produkten",
    "sg:phone":"+41 91 827 15 01",
    "sg:postcode":"6537",
    "sg:province":"Graubunden",
    "wof:name":"Farmacia Moretti Sa",
    "wof:placetype":"venue"
},
  "geometry": {"coordinates":[9.1564559937,46.2529716492],"type":"Point"}
}