{
  "type": "Feature",
  "properties": {
    "iso:country":"CH",
    "sg:address":"Schleusenweg 1a",
    "sg:city":"Biel/bienne",
    "sg:orig_category":"Zahntechnische Laboratorien",
    "sg:phone":"+41 32 342 32 30",
    "sg:postcode":"2502",
    "sg:province":"Bern",
    "wof:name":"Pierre Monn\u00e9 Zahntechnisches Labor",
    "wof:placetype":"venue"
},
  "geometry": {"coordinates":[7.2552890778,47.1420669556],"type":"Point"}
}