{
  "type": "Feature",
  "properties": {
    "iso:country":"CH",
    "sg:address":"Husmattstrasse 18",
    "sg:city":"Steinerberg",
    "sg:orig_category":"Massagestudios Naturheil\u00e4rzte and Heilpraktiker",
    "sg:phone":"+41 41 832 29 57",
    "sg:postcode":"6416",
    "sg:province":"Schwyz",
    "wof:name":"Christian Graf Vitalogie & Massagen",
    "wof:placetype":"venue"
},
  "geometry": {"coordinates":[8.5873117447,47.056388855],"type":"Point"}
}