{
  "type": "Feature",
  "properties": {
    "iso:country":"CH",
    "sg:address":"Eigasse 1",
    "sg:city":"Egerkingen",
    "sg:orig_category":"Detailhandel mit Beleuchtungs U Haushaltsgegenst\u00e4nden Detailhandel mit elektrischen Haushalts-,Radio",
    "sg:phone":"+41 62 398 00 40",
    "sg:postcode":"4622",
    "sg:province":"Solothurn",
    "wof:name":"Indutronic Ag",
    "wof:placetype":"venue"
},
  "geometry": {"coordinates":[7.803385,47.323513],"type":"Point"}
}