{
  "type": "Feature",
  "properties": {
    "iso:country":"CH",
    "sg:address":"Hauptstrasse 8",
    "sg:city":"Wolfenschiessen",
    "sg:orig_category":"Elektroinstallation Personal U Stellenvermittlung",
    "sg:phone":"+41 41 628 11 76",
    "sg:postcode":"6386",
    "sg:province":"Nidwalden",
    "wof:name":"Odermatt Alois Bauarbeiten",
    "wof:placetype":"venue"
},
  "geometry": {"coordinates":[8.3955411911,46.9099617004],"type":"Point"}
}