{
  "type": "Feature",
  "properties": {
    "iso:country":"CH",
    "sg:address":"Fellenbergstrasse 292 8047 Z\u00fcrich. Postfach",
    "sg:city":"Z\u00fcrich",
    "sg:orig_category":"Detailhandel mit Radio U Fernsehger\u00e4ten Detailhandel mit elektrischen Haushalts-,Radio U Fernsehger\u00e4",
    "sg:phone":"+41 14914777",
    "sg:postcode":"8047",
    "sg:province":"Z\u00fcrich",
    "wof:name":"Tera Balmer Karl Ag",
    "wof:placetype":"venue"
},
  "geometry": {"coordinates":[8.4895954132,47.3755645752],"type":"Point"}
}