{
  "type": "Feature",
  "properties": {
    "iso:country":"CH",
    "sg:address":"Bahnhofstrasse 106",
    "sg:city":"Ins",
    "sg:orig_category":"RESTAURANTS: TEA-ROOMS",
    "sg:postcode":"3232",
    "sg:province":"Bern",
    "wof:name":"Schmid Hanni Frau.",
    "wof:placetype":"venue"
},
  "geometry": {"coordinates":[9.0368242264,47.4611778259],"type":"Point"}
}