{
  "type": "Feature",
  "properties": {
    "iso:country":"CH",
    "sg:address":"Hauptstrasse 60",
    "sg:city":"Zuchwil",
    "sg:orig_category":"Arztpraxen",
    "sg:phone":"+41 32 685 51 51",
    "sg:postcode":"4528",
    "sg:province":"Solothurn",
    "wof:name":"Dr.med.benedikt Baltisberger Spezialarzt Fmh",
    "wof:placetype":"venue"
},
  "geometry": {"coordinates":[7.560023,47.203678],"type":"Point"}
}