{
  "type": "Feature",
  "properties": {
    "iso:country":"CH",
    "sg:address":"Sch\u00f6nmattweg 11",
    "sg:city":"Thun",
    "sg:orig_category":"Vermietung U Verpachtung von eigenen Immobilien",
    "sg:postcode":"3600",
    "sg:province":"Bern",
    "wof:name":"Sabbimmob Ag",
    "wof:placetype":"venue"
},
  "geometry": {"coordinates":[7.6290569305,46.7494888306],"type":"Point"}
}