{
  "type": "Feature",
  "properties": {
    "iso:country":"CH",
    "sg:address":"W\u00fclflingerstrasse 250",
    "sg:city":"Winterthur",
    "sg:orig_category":"Non-Classified Establishments",
    "sg:postcode":"8408",
    "sg:province":"Z\u00fcrich",
    "wof:name":"Werner Huber, Restaurant Zur Alten Post",
    "wof:placetype":"venue"
},
  "geometry": {"coordinates":[8.6944026947,47.5107841492],"type":"Point"}
}