{
  "type": "Feature",
  "properties": {
    "iso:country":"CH",
    "sg:address":"Grande-poya 3 1580 Avenches. Postfach",
    "sg:city":"Avenches",
    "sg:orig_category":"Polizei",
    "sg:phone":"+41 32 931 54 54",
    "sg:postcode":"1580",
    "sg:province":"Vaud",
    "wof:name":"Police Cantonale",
    "wof:placetype":"venue"
},
  "geometry": {"coordinates":[6.74893713,47.0580101013],"type":"Point"}
}