{
  "type": "Feature",
  "properties": {
    "iso:country":"CH",
    "sg:address":"Belalpstrasse 9 Brig 3900 Berisal. Postfach",
    "sg:city":"Brig",
    "sg:orig_category":"Gesundheitswesen",
    "sg:postcode":"3900",
    "sg:province":"Valais",
    "wof:name":"Praxis F\u00fcr Physikalische Therapy D. Curlic",
    "wof:placetype":"venue"
},
  "geometry": {"coordinates":[8.5430688858,47.2899017334],"type":"Point"}
}