{
  "type": "Feature",
  "properties": {
    "iso:country":"CH",
    "sg:address":"Fl\u00fchgasse 17",
    "sg:city":"Z\u00fcrich",
    "sg:orig_category":"Unternehmensberatung",
    "sg:phone":"+41 14212300",
    "sg:postcode":"8008",
    "sg:province":"Z\u00fcrich",
    "wof:name":"Horv\u00e1th & Partner Ag",
    "wof:placetype":"venue"
},
  "geometry": {"coordinates":[8.5642366409,47.3493003845],"type":"Point"}
}