{
  "type": "Feature",
  "properties": {
    "iso:country":"CH",
    "sg:address":"D\u00fcnnernstrasse 32 4702 Oensingen. Postfach",
    "sg:city":"Oensingen",
    "sg:orig_category":"Softwareentwicklung U beratung",
    "sg:phone":"+41 62 388 45 45",
    "sg:postcode":"4702",
    "sg:province":"Solothurn",
    "wof:name":"Microtronic Ag",
    "wof:placetype":"venue"
},
  "geometry": {"coordinates":[7.7183542252,47.2821731567],"type":"Point"}
}