{
  "type": "Feature",
  "properties": {
    "iso:country":"CH",
    "sg:address":"K\u00fcntwilerstrasse 31",
    "sg:city":"Rotkreuz",
    "sg:orig_category":"Softwareentwicklung U beratung",
    "sg:postcode":"6343",
    "sg:province":"Zug",
    "wof:name":"Gn Electronic Nicod",
    "wof:placetype":"venue"
},
  "geometry": {"coordinates":[8.4285697937,47.1370277405],"type":"Point"}
}