{
  "type": "Feature",
  "properties": {
    "addr:full":"Metzerstrasse 14 Basel Basel-Stadt 4056",
    "addr:housenumber":"14",
    "addr:postcode":"4056",
    "addr:street":"Metzerstrasse",
    "iso:country":"CH",
    "sg:address":"Metzerstrasse 14",
    "sg:city":"Basel",
    "sg:orig_category":"Apparatus, Containers, Tanks, Boilers Of Plastic",
    "sg:phone":"+41 61 321 07 72",
    "sg:postcode":"4056",
    "sg:province":"Basel-Stadt",
    "wof:name":"Ms Kunststoffapparatebau Ag",
    "wof:placetype":"venue"
},
  "geometry": {"coordinates":[7.577935,47.564369],"type":"Point"}
}