{
  "type": "Feature",
  "properties": {
    "addr:full":"Steinweg 6 Lyss Bern 3250",
    "addr:housenumber":"6",
    "addr:postcode":"3250",
    "addr:street":"Steinweg;Bern",
    "iso:country":"CH",
    "sg:address":"Steinweg 6",
    "sg:city":"Lyss",
    "sg:orig_category":"Architektur U Ingenieurb\u00fcros Architekturb\u00fcros",
    "sg:phone":"+41 81 911 30 07",
    "sg:postcode":"3250",
    "sg:province":"Bern",
    "wof:name":"Heisch + Partner Ag, Architekturb\u00fcro",
    "wof:placetype":"venue"
},
  "geometry": {"coordinates":[9.283536,46.836666],"type":"Point"}
}