{
  "type": "Feature",
  "properties": {
    "iso:country":"CH",
    "sg:address":"Schmittengasse 5",
    "sg:city":"Bettlach",
    "sg:orig_category":"Vorschulen, Kinderg\u00e4rten",
    "sg:phone":"+41 32 645 26 07",
    "sg:postcode":"2544",
    "sg:province":"Solothurn",
    "wof:name":"Kindergarten Stellihof",
    "wof:placetype":"venue"
},
  "geometry": {"coordinates":[7.4225897789,47.202999115],"type":"Point"}
}