{
  "type": "Feature",
  "properties": {
    "iso:country":"CH",
    "sg:address":"Boulevard De Grancy 1 1006 Lausanne. Postfach",
    "sg:city":"Lausanne",
    "sg:orig_category":"Vermittlung von Immobilien",
    "sg:phone":"+41 21 617 54 55",
    "sg:postcode":"1001",
    "sg:province":"Vaud",
    "wof:name":"Getisa Sa Agence Immobili\u00e8re",
    "wof:placetype":"venue"
},
  "geometry": {"coordinates":[6.6322541237,46.5148658752],"type":"Point"}
}