{
  "type": "Feature",
  "properties": {
    "iso:country":"CH",
    "sg:address":"T\u00fcfi 9",
    "sg:city":"Herisau",
    "sg:orig_category":"Herstellung von Metallkonstruktionen",
    "sg:postcode":"9100",
    "sg:province":"Appenzell Ausserrhoden",
    "wof:name":"J. Frischknecht",
    "wof:placetype":"venue"
},
  "geometry": {"coordinates":[9.278169632,47.3851013184],"type":"Point"}
}