{
  "type": "Feature",
  "properties": {
    "iso:country":"CH",
    "sg:address":"Wynentalstrasse 2 5726 Unterkulm. Postfach",
    "sg:city":"Unterkulm",
    "sg:orig_category":"Stukkateurgewerbe, Gipserei U Verputzerei",
    "sg:postcode":"5726",
    "sg:province":"Aargau",
    "wof:name":"Handwerkerexpress Mulaj Gipsergesch\u00e4ft U. Fassadenbau",
    "wof:placetype":"venue"
},
  "geometry": {"coordinates":[8.1134853363,47.3255233765],"type":"Point"}
}