{
  "type": "Feature",
  "properties": {
    "iso:country":"CH",
    "sg:address":"Bahnhofstrasse 10",
    "sg:city":"Zug",
    "sg:orig_category":"Finanzierungsinstitutionen",
    "sg:postcode":"6300",
    "sg:province":"Zug",
    "wof:name":"Nosmas Investment Holdings B.v., Zeist, Netherlands, Zug Branch",
    "wof:placetype":"venue"
},
  "geometry": {"coordinates":[8.5159254074,47.1686897278],"type":"Point"}
}