{
  "type": "Feature",
  "properties": {
    "iso:country":"CH",
    "sg:address":"Schulhausstrasse 3945 Gampel. Postfach 40",
    "sg:city":"Gampel",
    "sg:orig_category":"Architektur U Ingenieurb\u00fcros",
    "sg:phone":"+41 27 932 24 25",
    "sg:postcode":"3945",
    "sg:province":"Valais",
    "wof:name":"Ingenieurb\u00fcro F\u00fcr Hoch Und Tiefbau, Gustav Martig.",
    "wof:placetype":"venue"
},
  "geometry": {"coordinates":[7.742205,46.314682],"type":"Point"}
}