{
  "type": "Feature",
  "properties": {
    "iso:country":"CH",
    "sg:address":"1864",
    "sg:city":"Vers-l'eglise",
    "sg:orig_category":"Landw. Genossenschaften Viehzucht",
    "sg:postcode":"1864",
    "sg:province":"Vaud",
    "wof:name":"Synd.d'\u00e9levage Du B\u00e9tail Bovin De Montfaucon & Environ",
    "wof:placetype":"venue"
},
  "geometry": {"coordinates":[7.0132098198,47.2637939453],"type":"Point"}
}