{
  "type": "Feature",
  "properties": {
    "iso:country":"CH",
    "sg:address":"Aescherweg 10",
    "sg:city":"Arlesheim",
    "sg:orig_category":"Informatikschulen Sonstige mit der Informatik verbundene T\u00e4tigkeiten",
    "sg:phone":"+41 61 702 03 22",
    "sg:postcode":"4144",
    "sg:province":"Basel-Landschaft",
    "wof:name":"Pro Data Dr.g\u00fcnther Lapp Schule F\u00fcr Datenverarbeitung",
    "wof:placetype":"venue"
},
  "geometry": {"coordinates":[7.6157031059,47.4961013794],"type":"Point"}
}