{
  "type": "Feature",
  "properties": {
    "iso:country":"CH",
    "sg:address":"Moosstrasse 95 8715 Bollingen. Postfach",
    "sg:city":"Bollingen",
    "sg:orig_category":"Berufsbildende weiterf\u00fchrende Schulen",
    "sg:postcode":"8715",
    "sg:province":"St. Gallen",
    "wof:name":"Andere Kader-schule Moos Helbling",
    "wof:placetype":"venue"
},
  "geometry": {"coordinates":[8.893383,47.220047],"type":"Point"}
}