{
  "type": "Feature",
  "properties": {
    "iso:country":"CH",
    "sg:address":"Murtenstrasse 45 2502 Biel/bienne. Postfach",
    "sg:city":"Biel/bienne",
    "sg:orig_category":"Detailhandel mit Uhren U Schmuck Fachdetailhandel in Verkaufsr\u00e4umen",
    "sg:phone":"+41 32 322 05 50",
    "sg:postcode":"2501",
    "sg:province":"Bern",
    "wof:name":"Le Carat, Sottanella Mario",
    "wof:placetype":"venue"
},
  "geometry": {"coordinates":[7.2456698418,47.1320762634],"type":"Point"}
}