{
  "type": "Feature",
  "properties": {
    "iso:country":"CH",
    "sg:address":"San Gottardo Corso 32",
    "sg:city":"Chiasso",
    "sg:orig_category":"Grosshandel mit sonstigen Maschinen U Ausr\u00fcstungen f\u00fcr Industrie, Handel U Schiffahrt",
    "sg:postcode":"6830",
    "sg:province":"Ticino",
    "wof:name":"Niederberger & Co Ag Hergiswil",
    "wof:placetype":"venue"
},
  "geometry": {"coordinates":[8.3084316254,46.9950485229],"type":"Point"}
}