{
  "type": "Feature",
  "properties": {
    "iso:country":"CH",
    "sg:address":"Resgia 8",
    "sg:city":"Lenzerheide/lai",
    "sg:orig_category":"Abdichtung Sonstiger spezialisierter Hoch U Tiefbau",
    "sg:phone":"+41 56 281 30 09",
    "sg:postcode":"7078",
    "sg:province":"Graubunden",
    "wof:name":"Renato Luceri Betonbohren Gipserei Kittfugen",
    "wof:placetype":"venue"
},
  "geometry": {"coordinates":[8.241587,47.517899],"type":"Point"}
}