{
  "type": "Feature",
  "properties": {
    "iso:country":"CH",
    "sg:address":"Chemin Du Pr\u00e9-fleuri 25b",
    "sg:city":"Plan-les-ouates",
    "sg:orig_category":"Ger\u00fcstbau Vermietung von Baumaschinen U ger\u00e4ten",
    "sg:phone":"+41 17445999",
    "sg:postcode":"1228",
    "sg:province":"Gen\u00e8ve",
    "wof:name":"Bertani Bauger\u00fcste Ag Verwaltung",
    "wof:placetype":"venue"
},
  "geometry": {"coordinates":[8.4041032791,47.4021530151],"type":"Point"}
}