{
  "type": "Feature",
  "properties": {
    "iso:country":"CH",
    "sg:address":"Hauptstrasse 50",
    "sg:city":"Steinmaur",
    "sg:orig_category":"Detailhandel mit Blumen U Pflanzen",
    "sg:phone":"+41 18540142",
    "sg:postcode":"8162",
    "sg:province":"Z\u00fcrich",
    "wof:name":"Steimer's Bluemelade",
    "wof:placetype":"venue"
},
  "geometry": {"coordinates":[8.454056,47.497742],"type":"Point"}
}