{
  "type": "Feature",
  "properties": {
    "iso:country":"CH",
    "sg:address":"Rue De La Praise 32",
    "sg:city":"Vouvry",
    "sg:orig_category":"HOTELS: OHNE RESTAURANT",
    "sg:phone":"+41 24 481 14 16",
    "sg:postcode":"1896",
    "sg:province":"Valais",
    "wof:name":"H\u00f4tel Garni Edirol",
    "wof:placetype":"venue"
},
  "geometry": {"coordinates":[6.8873748779,46.3426017761],"type":"Point"}
}