{
  "type": "Feature",
  "properties": {
    "iso:country":"CH",
    "sg:address":"Drosselstrasse 15",
    "sg:city":"Z\u00fcrich",
    "sg:orig_category":"Vereine Lions",
    "sg:phone":"+41 13607070",
    "sg:postcode":"8038",
    "sg:province":"Z\u00fcrich",
    "wof:name":"Lions Club Z\u00fcrich-oerlikon",
    "wof:placetype":"venue"
},
  "geometry": {"coordinates":[8.5257005692,47.3417396545],"type":"Point"}
}