{
  "type": "Feature",
  "properties": {
    "iso:country":"CH",
    "sg:address":"R\u00f6telstrasse 86 8057 Z\u00fcrich. Postfach",
    "sg:city":"Z\u00fcrich",
    "sg:orig_category":"Religi\u00f6se Vereinigungen",
    "sg:postcode":"8057",
    "sg:province":"Z\u00fcrich",
    "wof:name":"Stiftung Islamische Gemeinschaft Z\u00fcrich",
    "wof:placetype":"venue"
},
  "geometry": {"coordinates":[8.5322780609,47.3988876343],"type":"Point"}
}