{
  "type": "Feature",
  "properties": {
    "iso:country":"CH",
    "sg:address":"Saumackerstrasse 34",
    "sg:city":"Z\u00fcrich",
    "sg:orig_category":"Ern\u00e4hrungsberatung",
    "sg:phone":"+41 14328355",
    "sg:postcode":"8048",
    "sg:province":"Z\u00fcrich",
    "wof:name":"Sonja Gubler Ern\u00e4hrungsberatung",
    "wof:placetype":"venue"
},
  "geometry": {"coordinates":[8.4887199402,47.3882484436],"type":"Point"}
}