{
  "type": "Feature",
  "properties": {
    "iso:country":"CH",
    "sg:address":"Herzogstrasse 17",
    "sg:city":"Bern",
    "sg:orig_category":"Grosshandel mit Getr\u00e4nken",
    "sg:phone":"+41 31 331 27 33",
    "sg:postcode":"3014",
    "sg:province":"Bern",
    "wof:name":"La Vigna Sybille Hauser",
    "wof:placetype":"venue"
},
  "geometry": {"coordinates":[7.4553070068,46.9582023621],"type":"Point"}
}