{
  "type": "Feature",
  "properties": {
    "iso:country":"CH",
    "sg:address":"B\u00fcttenenhalde 39",
    "sg:city":"Luzern",
    "sg:orig_category":"Fotografische Ateliers Fotografisches Gewerbe U fotografische Laboratorien",
    "sg:phone":"+41 41 660 46 44",
    "sg:postcode":"6006",
    "sg:province":"Luzern",
    "wof:name":"Foto Wagner Gmbh",
    "wof:placetype":"venue"
},
  "geometry": {"coordinates":[8.2486715317,46.8960037231],"type":"Point"}
}