{
  "type": "Feature",
  "properties": {
    "iso:country":"CH",
    "sg:address":"Rottenschwilerstrasse 16",
    "sg:city":"Unterlunkhofen",
    "sg:orig_category":"Gemeindeverwaltungen",
    "sg:phone":"+41 56 634 10 12",
    "sg:postcode":"8918",
    "sg:province":"Aargau",
    "wof:name":"Gemeindeverwaltung Unterlunkhofen",
    "wof:placetype":"venue"
},
  "geometry": {"coordinates":[8.3797922134,47.32056427],"type":"Point"}
}