{
  "type": "Feature",
  "properties": {
    "iso:country":"CH",
    "sg:address":"Hasli 6",
    "sg:city":"Glash\u00fctten",
    "sg:orig_category":"Datenverarbeitungsdienste Softwareentwicklung U beratung",
    "sg:phone":"+41 19408687",
    "sg:postcode":"4856",
    "sg:province":"Aargau",
    "wof:name":"Andreas Jegerlehner Lean Projects",
    "wof:placetype":"venue"
},
  "geometry": {"coordinates":[7.84517,47.258648],"type":"Point"}
}