{
  "type": "Feature",
  "properties": {
    "iso:country":"CH",
    "sg:address":"1435",
    "sg:city":"Essert-pittet",
    "sg:orig_category":"Gemeindeverwaltungen",
    "sg:phone":"+41 24 441 14 67",
    "sg:postcode":"1435",
    "sg:province":"Vaud",
    "wof:name":"Administration Communale De Essert-pittet",
    "wof:placetype":"venue"
},
  "geometry": {"coordinates":[6.5789198875,46.7288017273],"type":"Point"}
}