{
  "type": "Feature",
  "properties": {
    "iso:country":"CH",
    "sg:address":"Wildsbergstrasse 44",
    "sg:city":"Greifensee",
    "sg:orig_category":"Autogaragen",
    "sg:phone":"+41 19407097",
    "sg:postcode":"8606",
    "sg:province":"Z\u00fcrich",
    "wof:name":"B. Weidmann Automobile Ag Garage",
    "wof:placetype":"venue"
},
  "geometry": {"coordinates":[8.691553,47.357059],"type":"Point"}
}