{
  "type": "Feature",
  "properties": {
    "iso:country":"CH",
    "sg:address":"Hohwindenstrasse 20",
    "sg:city":"Glattfelden",
    "sg:orig_category":"Rolladen- and Storenmontage",
    "sg:phone":"+41 18673560",
    "sg:postcode":"8192",
    "sg:province":"Z\u00fcrich",
    "wof:name":"Hans-peter Maurer Rolladen Storen",
    "wof:placetype":"venue"
},
  "geometry": {"coordinates":[8.5102949142,47.5559997559],"type":"Point"}
}