{
  "type": "Feature",
  "properties": {
    "iso:country":"CH",
    "sg:address":"Berchtoldstrasse 49 3000 Bern. Postfach",
    "sg:city":"Bern",
    "sg:orig_category":"Unclassifiable Establishments",
    "sg:postcode":"3005",
    "sg:province":"Bern",
    "wof:name":"K\u00f6stliches F\u00fcr Kenner, Widmer Remund Beate",
    "wof:placetype":"venue"
},
  "geometry": {"coordinates":[7.4369401932,46.95728302],"type":"Point"}
}