{
  "type": "Feature",
  "properties": {
    "iso:country":"CH",
    "sg:address":"Grafenriedstrasse 63",
    "sg:city":"Etzelkofen",
    "sg:orig_category":"Elektroinstallation",
    "sg:phone":"+41 31 765 55 48",
    "sg:postcode":"3306",
    "sg:province":"Bern",
    "wof:name":"Elektro Z\u00fcrcher + M\u00fchlemann",
    "wof:placetype":"venue"
},
  "geometry": {"coordinates":[7.4817080498,47.082901001],"type":"Point"}
}