{
  "type": "Feature",
  "properties": {
    "iso:country":"CH",
    "sg:address":"Hochh\u00fcsliweid 9",
    "sg:city":"Luzern",
    "sg:orig_category":"Rolladen- and Storenmontage Textilveredlung",
    "sg:phone":"+41 41 370 27 16",
    "sg:postcode":"6006",
    "sg:province":"Luzern",
    "wof:name":"Clean Factory Gmbh Sonnenstorenreinigung Impr\u00e4gn.",
    "wof:placetype":"venue"
},
  "geometry": {"coordinates":[8.3532037735,47.0593566895],"type":"Point"}
}