{
  "type": "Feature",
  "properties": {
    "iso:country":"CH",
    "sg:address":"8212",
    "sg:city":"Neuhausen",
    "sg:orig_category":"Vereine Damen Vereine Gesang",
    "sg:phone":"+41 52 672 19 77",
    "sg:postcode":"8212",
    "sg:province":"Schaffhausen",
    "wof:name":"Frauen-& T\u00f6chterchor",
    "wof:placetype":"venue"
},
  "geometry": {"coordinates":[8.6196098328,47.6815681458],"type":"Point"}
}