{
  "type": "Feature",
  "properties": {
    "iso:country":"CH",
    "sg:address":"Im Zentrum 8604 Volketswil. Postfach",
    "sg:city":"Volketswil",
    "sg:orig_category":"Detailhandel mit Beleuchtungs U Haushaltsgegenst\u00e4nden Grosshandel mit elektrischen Haushaltsger\u00e4ten,",
    "sg:phone":"+41 31 311 47 07",
    "sg:postcode":"8604",
    "sg:province":"Z\u00fcrich",
    "wof:name":"Electras Gmbh Elektr. Apparate; Vertrieb",
    "wof:placetype":"venue"
},
  "geometry": {"coordinates":[7.446021,46.94775],"type":"Point"}
}