{
  "type": "Feature",
  "properties": {
    "iso:country":"CH",
    "sg:address":"Route De Nonfoux",
    "sg:city":"Essertines-yverdon",
    "sg:orig_category":"Herstellung von Fenstern U T\u00fcren aus Holz Herstellung von Konstruktionsteilen, Fertigbauteilen U Aus",
    "sg:phone":"+41 24 435 13 60",
    "sg:postcode":"1417",
    "sg:province":"Vaud",
    "wof:name":"Menuiserie-charpente Rottet S\u00e0rl",
    "wof:placetype":"venue"
},
  "geometry": {"coordinates":[6.6389789581,46.7156486511],"type":"Point"}
}