{
  "type": "Feature",
  "properties": {
    "iso:country":"CH",
    "sg:address":"7078 Lenzerheide/lai. Postfach 72",
    "sg:city":"Lenzerheide/lai",
    "sg:orig_category":"Sportvereine Ballsport Fussball",
    "sg:phone":"+41 81 384 49 98",
    "sg:postcode":"7078",
    "sg:province":"Graubunden",
    "wof:name":"Fc Lenzerheide",
    "wof:placetype":"venue"
},
  "geometry": {"coordinates":[9.5578527451,46.7245788574],"type":"Point"}
}