{
  "type": "Feature",
  "properties": {
    "addr:full":"Nelkenweg 5 Bern Bern 3005",
    "addr:housenumber":"5",
    "addr:postcode":"3005",
    "addr:street":"Nelkenweg",
    "iso:country":"CH",
    "sg:address":"Nelkenweg 5",
    "sg:city":"Bern",
    "sg:orig_category":"Datenbanken",
    "sg:phone":"+41 79 335 83 77",
    "sg:postcode":"3005",
    "sg:province":"Bern",
    "wof:name":"Huber Emi Multimedia Solutions",
    "wof:placetype":"venue"
},
  "geometry": {"coordinates":[7.473567,46.940853],"type":"Point"}
}