{
  "type": "Feature",
  "properties": {
    "iso:country":"CH",
    "sg:address":"Bas-du-village",
    "sg:city":"Etoy",
    "sg:orig_category":"Maurerarbeiten Sonstiger spezialisierter Hoch U Tiefbau",
    "sg:phone":"+41 21 808 76 67",
    "sg:postcode":"1163",
    "sg:province":"Vaud",
    "wof:name":"Guignard Didier",
    "wof:placetype":"venue"
},
  "geometry": {"coordinates":[6.4193058014,46.4849510193],"type":"Point"}
}