{
  "type": "Feature",
  "properties": {
    "iso:country":"CH",
    "sg:address":"Baselstrasse 33",
    "sg:city":"Zwingen",
    "sg:orig_category":"Grosshandel mit Holz U Baustoffen Herstellung von keramischen Wand U Bodenfliesen U platten",
    "sg:phone":"+41 61 761 65 66",
    "sg:postcode":"4222",
    "sg:province":"Basel-Landschaft",
    "wof:name":"Mpz Plattenhandel Ag",
    "wof:placetype":"venue"
},
  "geometry": {"coordinates":[7.536465168,47.4396286011],"type":"Point"}
}