{
  "type": "Feature",
  "properties": {
    "iso:country":"CH",
    "sg:address":"Mettlenweg 9b 2504 Biel/bienne. Postfach",
    "sg:city":"Biel/bienne",
    "sg:orig_category":"Herstellung von Elektromotoren, Generatoren U Transformatoren",
    "sg:postcode":"2504",
    "sg:province":"Bern",
    "wof:name":"Ei Energie Invest Ag",
    "wof:placetype":"venue"
},
  "geometry": {"coordinates":[7.2751131058,47.1464195251],"type":"Point"}
}