{
  "type": "Feature",
  "properties": {
    "iso:country":"CH",
    "sg:address":"Bodenstrasse 30",
    "sg:city":"Andermatt",
    "sg:orig_category":"G\u00fcterbef\u00f6rderung im Strassenverkehr",
    "sg:phone":"+41 33 744 12 40",
    "sg:postcode":"6490",
    "sg:province":"Uri",
    "wof:name":"Rieben Ag",
    "wof:placetype":"venue"
},
  "geometry": {"coordinates":[7.2772450447,46.480255127],"type":"Point"}
}