{
  "type": "Feature",
  "properties": {
    "iso:country":"CH",
    "sg:address":"Neuwiesenstrasse 15",
    "sg:city":"Winterthur",
    "sg:orig_category":"Informatikdienste Sonstige mit der Informatik verbundene T\u00e4tigkeiten",
    "sg:phone":"+41 17151834",
    "sg:postcode":"8400",
    "sg:province":"Z\u00fcrich",
    "wof:name":"Serviteco Ag",
    "wof:placetype":"venue"
},
  "geometry": {"coordinates":[8.5371570587,47.3310317993],"type":"Point"}
}