{
  "type": "Feature",
  "properties": {
    "iso:country":"CH",
    "sg:address":"Place De Cornavin 12",
    "sg:city":"Gen\u00e8ve",
    "sg:classifiers":[
        {
            "category":"Banks & Credit Unions",
            "subcategory":"Bank",
            "type":"Services"
        }
    ],
    "sg:phone":"+41 22 738 66 55",
    "sg:postcode":"1201",
    "sg:province":"Gen\u00e8ve",
    "wof:name":"Banesto Banco Espanol, De Credito",
    "wof:placetype":"venue"
},
  "geometry": {"coordinates":[6.143268,46.209549],"type":"Point"}
}