{
  "type": "Feature",
  "properties": {
    "iso:country":"CH",
    "sg:address":"Vers Corpataux",
    "sg:city":"Treyvaux",
    "sg:orig_category":"Instandhaltung U Reparatur von Automobilen",
    "sg:phone":"+41 21 731 20 17",
    "sg:postcode":"1733",
    "sg:province":"Fribourg",
    "wof:name":"Career Group Management Sa",
    "wof:placetype":"venue"
},
  "geometry": {"coordinates":[6.6639499664,46.5902061462],"type":"Point"}
}