{
  "type": "Feature",
  "properties": {
    "iso:country":"CH",
    "sg:address":"Grossbruggerweg 3",
    "sg:city":"Chur",
    "sg:orig_category":"Baugewerbe Herstellung von sonstigen Maschinen f\u00fcr bestimmte Verwendung",
    "sg:phone":"+41 81 284 77 88",
    "sg:postcode":"7000",
    "sg:province":"Graubunden",
    "wof:name":"Cavelti + Partner",
    "wof:placetype":"venue"
},
  "geometry": {"coordinates":[9.508564,46.85791],"type":"Point"}
}