{
  "type": "Feature",
  "properties": {
    "iso:country":"CH",
    "sg:address":"Moos",
    "sg:city":"Urn\u00e4sch",
    "sg:orig_category":"Sportvereine Turnen Vereine Damen",
    "sg:postcode":"9107",
    "sg:province":"Appenzell Ausserrhoden",
    "wof:name":"Frauenturnverein",
    "wof:placetype":"venue"
},
  "geometry": {"coordinates":[9.2739048004,47.3103713989],"type":"Point"}
}