{
  "type": "Feature",
  "properties": {
    "iso:country":"CH",
    "sg:address":"Chappelistrasse 3",
    "sg:city":"Volketswil",
    "sg:orig_category":"Kauf U Verkauf von Immobilien auf eigene Rechnung",
    "sg:postcode":"8604",
    "sg:province":"Z\u00fcrich",
    "wof:name":"Gewerbehaus H\u00f6lzliwisen Ag.",
    "wof:placetype":"venue"
},
  "geometry": {"coordinates":[8.673661232,47.3892173767],"type":"Point"}
}