{
  "type": "Feature",
  "properties": {
    "iso:country":"CH",
    "sg:address":"Bahnhofstrasse 52 8001 Z\u00fcrich. Postfach",
    "sg:city":"Jona",
    "sg:orig_category":"Unternehmensberatung",
    "sg:phone":"+41 55 214 27 54",
    "sg:postcode":"8645",
    "sg:province":"St. Gallen",
    "wof:name":"Ab Ammann Anita Beratungen",
    "wof:placetype":"venue"
},
  "geometry": {"coordinates":[8.5383844376,47.3728256226],"type":"Point"}
}