{
  "type": "Feature",
  "properties": {
    "iso:country":"CH",
    "sg:address":"Clarastrasse 27 4058 Basel. Postfach",
    "sg:city":"Basel",
    "sg:classifiers":[
        {
            "category":"Restaurant",
            "type":"Food & Drink"
        }
    ],
    "sg:phone":"+41 61 692 35 94",
    "sg:postcode":"4005",
    "sg:province":"Basel-Stadt",
    "wof:name":"Restaurant Walliserstube",
    "wof:placetype":"venue"
},
  "geometry": {"coordinates":[7.5963602066,47.562713623],"type":"Point"}
}