{
  "type": "Feature",
  "properties": {
    "iso:country":"CH",
    "sg:address":"Arcuaul",
    "sg:city":"Schluein",
    "sg:orig_category":"Bauschreinerei Herstellung von K\u00fcchenm\u00f6beln",
    "sg:phone":"+41 81 925 16 16",
    "sg:postcode":"7151",
    "sg:province":"Graubunden",
    "wof:name":"Battaglia Martin Ag",
    "wof:placetype":"venue"
},
  "geometry": {"coordinates":[9.223553,46.786549],"type":"Point"}
}