{
  "type": "Feature",
  "properties": {
    "iso:country":"CH",
    "sg:address":"Voltastrasse 43",
    "sg:city":"Z\u00fcrich",
    "sg:orig_category":"Forschung U Entwicklung im Bereich der Naturwissenschaften",
    "sg:postcode":"8044",
    "sg:province":"Z\u00fcrich",
    "wof:name":"Forschungs-stiftung Johann Caspar Lavater",
    "wof:placetype":"venue"
},
  "geometry": {"coordinates":[8.5536079407,47.3784141541],"type":"Point"}
}