{
  "type": "Feature",
  "properties": {
    "iso:country":"CH",
    "sg:address":"L\u00e4ndtestrasse 45",
    "sg:city":"Biel/bienne",
    "sg:orig_category":"Detailhandel mit Waren verschiedener Art, Hauptrichtung Nahrungsmittel",
    "sg:phone":"+41 32 323 49 11",
    "sg:postcode":"2503",
    "sg:province":"Bern",
    "wof:name":"Jean Gut Gem\u00fcse",
    "wof:placetype":"venue"
},
  "geometry": {"coordinates":[7.2387928963,47.132144928],"type":"Point"}
}