{
  "type": "Feature",
  "properties": {
    "iso:country":"CH",
    "sg:address":"Rue Des Finettes 110",
    "sg:city":"Martigny",
    "sg:orig_category":"Herstellung von Papier, Karton U Pappe Herstellung von Tapeten",
    "sg:postcode":"1920",
    "sg:province":"Valais",
    "wof:name":"Sjp (suisse) Sa Panoval Papier Autocollant",
    "wof:placetype":"venue"
},
  "geometry": {"coordinates":[7.1001219749,46.1090888977],"type":"Point"}
}