{
  "type": "Feature",
  "properties": {
    "iso:country":"CH",
    "sg:address":"Riedwies",
    "sg:city":"Pany",
    "sg:classifiers":[
        {
            "category":"Government",
            "subcategory":"Post Office",
            "type":"Public Place"
        }
    ],
    "sg:phone":"+41 81 332 18 55",
    "sg:postcode":"7243",
    "sg:province":"Graubunden",
    "sg:tags":[
        "caf\u00e9s",
        "tea-rooms"
    ],
    "wof:name":"Caf\u00e9 Diana",
    "wof:placetype":"venue"
},
  "geometry": {"coordinates":[9.7704133987,46.9283599854],"type":"Point"}
}