{
  "type": "Feature",
  "properties": {
    "iso:country":"CH",
    "sg:address":"Sch\u00fctzenhausstrasse 5",
    "sg:city":"Rorbas",
    "sg:orig_category":"Sportvereine Boccia",
    "sg:phone":"+41 18654650",
    "sg:postcode":"8427",
    "sg:province":"Z\u00fcrich",
    "wof:name":"Boccia-club Rorbas",
    "wof:placetype":"venue"
},
  "geometry": {"coordinates":[8.5725431442,47.5366592407],"type":"Point"}
}