{
  "type": "Feature",
  "properties": {
    "iso:country":"CH",
    "sg:address":"Chemin Lanche",
    "sg:city":"Bouveret",
    "sg:orig_category":"Kosmetikinstitute",
    "sg:phone":"+41 24 481 38 29",
    "sg:postcode":"1897",
    "sg:province":"Valais",
    "wof:name":"Giovanna Martorana Institut De Beaut\u00e9 Colibri",
    "wof:placetype":"venue"
},
  "geometry": {"coordinates":[6.8591499329,46.3823699951],"type":"Point"}
}