{
  "type": "Feature",
  "properties": {
    "addr:full":"Hauptstrasse 47 9436 Balgach. Postfach Balgach St. Gallen 9436",
    "addr:housenumber":"47",
    "addr:postcode":"9436 balgach. postfach;9436",
    "addr:street":"Hauptstrasse",
    "iso:country":"CH",
    "sg:address":"Hauptstrasse 47 9436 Balgach. Postfach",
    "sg:city":"Balgach",
    "sg:orig_category":"Arztpraxen",
    "sg:phone":"+41 71 722 21 45",
    "sg:postcode":"9436",
    "sg:province":"St. Gallen",
    "wof:name":"Dr.med.arnold N\u00fcesch Arzt F.allgemeine Medizin Fmh",
    "wof:placetype":"venue"
},
  "geometry": {"coordinates":[9.605613,47.406605],"type":"Point"}
}