{
  "type": "Feature",
  "properties": {
    "iso:country":"CH",
    "sg:address":"Fey",
    "sg:city":"Haute-nendaz",
    "sg:orig_category":"Softwareentwicklung U beratung",
    "sg:phone":"+41 56 290 04 04",
    "sg:postcode":"1997",
    "sg:province":"Valais",
    "wof:name":"Rodriguez J., Computer Service",
    "wof:placetype":"venue"
},
  "geometry": {"coordinates":[8.2457876205,47.5239143372],"type":"Point"}
}