{
  "type": "Feature",
  "properties": {
    "iso:country":"CH",
    "sg:address":"Reinacherstrasse 257",
    "sg:city":"Gontenschwil",
    "sg:orig_category":"Haltung von Rindern",
    "sg:phone":"+41 71852206",
    "sg:postcode":"5728",
    "sg:province":"Aargau",
    "wof:name":"Viehzuchtgenossenschaft Gossau",
    "wof:placetype":"venue"
},
  "geometry": {"coordinates":[9.2420396805,47.4030952454],"type":"Point"}
}