{
  "type": "Feature",
  "properties": {
    "iso:country":"CH",
    "sg:address":"Fauquez Route Aloys- 122",
    "sg:city":"Lausanne",
    "sg:orig_category":"RESTAURANTS: TEA-ROOMS",
    "sg:postcode":"1018",
    "sg:province":"Vaud",
    "wof:name":"Le Baladin, Comte Michelle",
    "wof:placetype":"venue"
},
  "geometry": {"coordinates":[6.6336188316,46.5403785706],"type":"Point"}
}