{
  "type": "Feature",
  "properties": {
    "iso:country":"CH",
    "sg:address":"Industriestrasse",
    "sg:city":"Spiez",
    "sg:orig_category":"Forstwirtschaft ohne Dienstleistungen in der Forstwirtschaft",
    "sg:postcode":"3700",
    "sg:province":"Bern",
    "wof:name":"Henzen Dominique Sa",
    "wof:placetype":"venue"
},
  "geometry": {"coordinates":[6.1783900261,46.4088439941],"type":"Point"}
}