{
  "type": "Feature",
  "properties": {
    "iso:country":"CH",
    "sg:address":"Falkenstrasse 50",
    "sg:city":"Biel/bienne",
    "sg:orig_category":"Fussreflexzonenmassage",
    "sg:phone":"+41 32 342 04 50",
    "sg:postcode":"2502",
    "sg:province":"Bern",
    "wof:name":"Pia Campioli Fussreflexzonentherapie",
    "wof:placetype":"venue"
},
  "geometry": {"coordinates":[7.2604060173,47.1444549561],"type":"Point"}
}