{
  "type": "Feature",
  "properties": {
    "iso:country":"CH",
    "sg:address":"Avenue Des Jordils 5",
    "sg:city":"Lausanne",
    "sg:orig_category":"Grosshandel mit sonstigen Maschinen U Ausr\u00fcstungen f\u00fcr Industrie, Handel U Schiffahrt",
    "sg:phone":"+41 21 616 51 51",
    "sg:postcode":"1006",
    "sg:province":"Vaud",
    "wof:name":"Chanfil Sa",
    "wof:placetype":"venue"
},
  "geometry": {"coordinates":[6.6274261475,46.5094261169],"type":"Point"}
}