{
  "type": "Feature",
  "properties": {
    "iso:country":"CH",
    "sg:address":"Buholzstrasse",
    "sg:city":"Wolhusen",
    "sg:orig_category":"Grosshandel mit sonstigen Maschinen U Ausr\u00fcstungen f\u00fcr Industrie, Handel U Schiffahrt Mechanische We",
    "sg:phone":"+41 79 277 11 42",
    "sg:postcode":"6110",
    "sg:province":"Luzern",
    "wof:name":"W\u00fcthrich Albrecht, Maschinen + Mechanik Ag",
    "wof:placetype":"venue"
},
  "geometry": {"coordinates":[8.0897445679,47.059715271],"type":"Point"}
}