{
  "type": "Feature",
  "properties": {
    "iso:country":"CH",
    "sg:address":"6922",
    "sg:city":"Morcote",
    "sg:orig_category":"Detailhandel mit Geschenkartikeln U Souvenirs",
    "sg:phone":"+41 32 725 66 14",
    "sg:postcode":"6922",
    "sg:province":"Ticino",
    "wof:name":"Au Bon Tailleur Boutique F.de Turris",
    "wof:placetype":"venue"
},
  "geometry": {"coordinates":[6.9289879799,46.9907073975],"type":"Point"}
}