{
  "type": "Feature",
  "properties": {
    "iso:country":"CH",
    "sg:address":"Borgo Via 10",
    "sg:city":"Ascona",
    "sg:orig_category":"Non-Classified Establishments",
    "sg:postcode":"6612",
    "sg:province":"Ticino",
    "wof:name":"Kuoni Viaggi Sa, Succursale Ascona",
    "wof:placetype":"venue"
},
  "geometry": {"coordinates":[8.7685155869,46.1564750671],"type":"Point"}
}