{
  "type": "Feature",
  "properties": {
    "iso:country":"CH",
    "sg:address":"Guggiweg 9",
    "sg:city":"Zug",
    "sg:orig_category":"Architektur U Ingenieurb\u00fcros",
    "sg:phone":"+41 12687275",
    "sg:postcode":"6300",
    "sg:province":"Zug",
    "wof:name":"Projektgruppe Wilgut Gmbh",
    "wof:placetype":"venue"
},
  "geometry": {"coordinates":[8.518304,47.169659],"type":"Point"}
}