{
  "type": "Feature",
  "properties": {
    "iso:country":"CH",
    "sg:address":"Talstation",
    "sg:city":"Grindelwald",
    "sg:orig_category":"Seilbahnen Sessellifte and Skilifte",
    "sg:phone":"+41 41 811 45 22",
    "sg:postcode":"3818",
    "sg:province":"Bern",
    "wof:name":"Sportbahnen Schwyz-stoos Fronalpstock Ag",
    "wof:placetype":"venue"
},
  "geometry": {"coordinates":[8.6675300598,46.9832611084],"type":"Point"}
}