{
  "type": "Feature",
  "properties": {
    "iso:country":"CH",
    "sg:address":"Chemin Mo\u00efse-duboule 55",
    "sg:city":"Gen\u00e8ve",
    "sg:orig_category":"Reiseb\u00fcros U Reiseveranstalter",
    "sg:phone":"+41 61 711 55 77",
    "sg:postcode":"1209",
    "sg:province":"Gen\u00e8ve",
    "wof:name":"Weber Eurobus Reisen Ag",
    "wof:placetype":"venue"
},
  "geometry": {"coordinates":[7.5894851685,47.4911994934],"type":"Point"}
}