{
  "type": "Feature",
  "properties": {
    "iso:country":"CH",
    "sg:address":"1197 Prangins Case Postale 36",
    "sg:city":"Prangins",
    "sg:orig_category":"Sportvereine Ballsport Fussball",
    "sg:phone":"+41 22 361 17 31",
    "sg:postcode":"1197",
    "sg:province":"Vaud",
    "wof:name":"Prangins-sports",
    "wof:placetype":"venue"
},
  "geometry": {"coordinates":[6.2490000725,46.3943252563],"type":"Point"}
}