{
  "type": "Feature",
  "properties": {
    "addr:full":"Derri\u00e8re L'eglise Valangin Neuch\u00e2tel 2042",
    "addr:postcode":"valangin;2042",
    "addr:street":"Derrie\u0300Re L'Eglise",
    "iso:country":"CH",
    "sg:address":"Derri\u00e8re L'eglise",
    "sg:city":"Valangin",
    "sg:orig_category":"Arztpraxen",
    "sg:phone":"+41 32 857 14 14",
    "sg:postcode":"2042",
    "sg:province":"Neuch\u00e2tel",
    "wof:name":"Dr M\u00e9d. Pierre Pilloud M\u00e9decin Sp\u00e9cialiste Fmh",
    "wof:placetype":"venue"
},
  "geometry": {"coordinates":[6.907263,47.016106],"type":"Point"}
}