{
  "type": "Feature",
  "properties": {
    "iso:country":"CH",
    "sg:address":"Bahnhofstrasse 47",
    "sg:city":"Z\u00fcrich",
    "sg:orig_category":"Detailhandel mit Beleuchtungs U Haushaltsgegenst\u00e4nden Herstellung von keramischen Haushaltswaren U Z",
    "sg:phone":"+41 12111750",
    "sg:postcode":"8001",
    "sg:province":"Z\u00fcrich",
    "wof:name":"Rosenthal-studiohaus Bender Ag",
    "wof:placetype":"venue"
},
  "geometry": {"coordinates":[8.538238,47.372002],"type":"Point"}
}