{
  "type": "Feature",
  "properties": {
    "iso:country":"CH",
    "sg:address":"Fehrenstrasse 5",
    "sg:city":"Breitenbach",
    "sg:orig_category":"Landesverteidigung, Sozialversicherung \u00d6ffentliche Verwaltung",
    "sg:phone":"+41 31 302 24 53",
    "sg:postcode":"4226",
    "sg:province":"Solothurn",
    "wof:name":"Zivilschutzstelle Bremgarten Bei Bern",
    "wof:placetype":"venue"
},
  "geometry": {"coordinates":[7.4361581802,46.9776229858],"type":"Point"}
}