{
  "type": "Feature",
  "properties": {
    "addr:full":"Rue Peillonnex 39 Ch\u00eane-bourg Gen\u00e8ve 1225",
    "addr:housenumber":"39",
    "addr:postcode":"1225",
    "addr:street":"Rue Peillonnex",
    "iso:country":"CH",
    "sg:address":"Rue Peillonnex 39",
    "sg:city":"Ch\u00eane-bourg",
    "sg:orig_category":"Buchverlag Verlagsgewerbe",
    "sg:phone":"+41 62 827 02 30",
    "sg:postcode":"1225",
    "sg:province":"Gen\u00e8ve",
    "wof:name":"Edition Fona Gmbh",
    "wof:placetype":"venue"
},
  "geometry": {"coordinates":[8.181891,47.387024],"type":"Point"}
}