{
  "type": "Feature",
  "properties": {
    "iso:country":"CH",
    "sg:address":"Hauptstrasse 25",
    "sg:city":"Arbon",
    "sg:orig_category":"Detailhandel mit fotografischen Artikeln Fachdetailhandel in Verkaufsr\u00e4umen",
    "sg:phone":"+41 71 446 55 47",
    "sg:postcode":"9320",
    "sg:province":"Thurgau",
    "wof:name":"Foto-leder-kopieczek",
    "wof:placetype":"venue"
},
  "geometry": {"coordinates":[9.4344921112,47.5160675049],"type":"Point"}
}