{
  "type": "Feature",
  "properties": {
    "iso:country":"CH",
    "sg:address":"Neum\u00fcnsterstrasse 2",
    "sg:city":"Z\u00fcrich",
    "sg:orig_category":"Wohnheime f\u00fcr Kinder U Jugendliche",
    "sg:phone":"+41 13836415",
    "sg:postcode":"8008",
    "sg:province":"Z\u00fcrich",
    "wof:name":"St\u00e4dt.durchgangsheim Riesbach Kinder-& Jugendheim",
    "wof:placetype":"venue"
},
  "geometry": {"coordinates":[8.5576677322,47.3606300354],"type":"Point"}
}