{
  "type": "Feature",
  "properties": {
    "iso:country":"CH",
    "sg:address":"Stansstaderstrasse 104 6370 Stans. Postfach 320",
    "sg:city":"Stans",
    "sg:orig_category":"Softwareentwicklung U beratung",
    "sg:phone":"+41 79 340 53 35",
    "sg:postcode":"6370",
    "sg:province":"Nidwalden",
    "wof:name":"Fr-informatik Ag",
    "wof:placetype":"venue"
},
  "geometry": {"coordinates":[8.3518152237,46.9697914124],"type":"Point"}
}