{
  "type": "Feature",
  "properties": {
    "iso:country":"CH",
    "sg:address":"Blumenweg 3",
    "sg:city":"Adelboden",
    "sg:orig_category":"Wohnheime",
    "sg:phone":"+41 33 673 40 20",
    "sg:postcode":"3715",
    "sg:province":"Bern",
    "wof:name":"Wohngemeinschaft Zueflucht",
    "wof:placetype":"venue"
},
  "geometry": {"coordinates":[7.5696611404,46.501499176],"type":"Point"}
}