{
  "type": "Feature",
  "properties": {
    "iso:country":"CH",
    "sg:address":"Route De Lamboing 48c",
    "sg:city":"Diesse",
    "sg:orig_category":"G\u00fcterbef\u00f6rderung im Strassenverkehr",
    "sg:phone":"+41 32 315 12 44",
    "sg:postcode":"2517",
    "sg:province":"Bern",
    "wof:name":"Willy Bourquin",
    "wof:placetype":"venue"
},
  "geometry": {"coordinates":[7.1191477776,47.1136856079],"type":"Point"}
}