{
  "type": "Feature",
  "properties": {
    "iso:country":"CH",
    "sg:address":"Grabenstrasse 4 6004 Luzern. Postfach 3365",
    "sg:city":"Luzern",
    "sg:orig_category":"Detailhandel mit Schuhen Detailhandel mit Schuhen U Lederwaren",
    "sg:phone":"+41 41 410 31 78",
    "sg:postcode":"6002",
    "sg:province":"Luzern",
    "wof:name":"Schuhhaus Imgr\u00fcth + Co",
    "wof:placetype":"venue"
},
  "geometry": {"coordinates":[8.3060359955,47.0533981323],"type":"Point"}
}