{
  "type": "Feature",
  "properties": {
    "iso:country":"CH",
    "sg:address":"Kehlstrasse 45",
    "sg:city":"Baden",
    "sg:orig_category":"Sonstiger Grosshandel",
    "sg:postcode":"5400",
    "sg:province":"Aargau",
    "wof:name":"Mohanty Liddy Entreprise",
    "wof:placetype":"venue"
},
  "geometry": {"coordinates":[8.2886276245,47.4652633667],"type":"Point"}
}