{
  "type": "Feature",
  "properties": {
    "iso:country":"CH",
    "sg:address":"Frauenfelderstrasse 33 8370 Sirnach. Postfach",
    "sg:city":"Sirnach",
    "sg:orig_category":"Detailhandel mit Getr\u00e4nken Grosshandel mit sonstigen Getr\u00e4nken",
    "sg:phone":"+41 71 966 11 45",
    "sg:postcode":"8370",
    "sg:province":"Thurgau",
    "wof:name":"Ernst Sammer Mineralwasser Engros",
    "wof:placetype":"venue"
},
  "geometry": {"coordinates":[8.9988336563,47.4683494568],"type":"Point"}
}