{
  "type": "Feature",
  "properties": {
    "iso:country":"CH",
    "sg:address":"Bd De P\u00e9rolles 5a 1700 Fribourg. Postfach",
    "sg:city":"Fribourg",
    "sg:orig_category":"Verwaltung von Immobilien",
    "sg:postcode":"1701",
    "sg:province":"Fribourg",
    "wof:name":"Kappeler Jean-pierre",
    "wof:placetype":"venue"
},
  "geometry": {"coordinates":[7.1515917778,46.8015441895],"type":"Point"}
}