{
  "type": "Feature",
  "properties": {
    "iso:country":"CH",
    "sg:address":"Nordstrasse 10",
    "sg:city":"Oberentfelden",
    "sg:orig_category":"Sportvereine Velo Rad-& Motorfahrer-Bund SRB",
    "sg:postcode":"5036",
    "sg:province":"Aargau",
    "wof:name":"Velo-moto-club Oberentfelden",
    "wof:placetype":"venue"
},
  "geometry": {"coordinates":[8.04870224,47.3604164124],"type":"Point"}
}