{
  "type": "Feature",
  "properties": {
    "iso:country":"CH",
    "sg:address":"Route De Benex 4",
    "sg:city":"Prangins",
    "sg:orig_category":"Tanzschulen, Tanzlehrer",
    "sg:phone":"+41 21 361 67 14",
    "sg:postcode":"1197",
    "sg:province":"Vaud",
    "wof:name":"Muriel Hardy Ecole De Danse",
    "wof:placetype":"venue"
},
  "geometry": {"coordinates":[6.2495989799,46.3947410583],"type":"Point"}
}