{
  "type": "Feature",
  "properties": {
    "addr:full":"Pradaweg 15 Oberschan St. Gallen 9479",
    "addr:housenumber":"15;st.",
    "addr:postcode":"9479",
    "addr:street":"Pradaweg",
    "iso:country":"CH",
    "sg:address":"Pradaweg 15",
    "sg:city":"Oberschan",
    "sg:orig_category":"Bauschreinerei Herstellung von Konstruktionsteilen, Fertigbauteilen U Ausbauelementen aus Holz",
    "sg:phone":"+41 79 412 42 86",
    "sg:postcode":"9479",
    "sg:province":"St. Gallen",
    "wof:name":"H\u00f6hener Peter",
    "wof:placetype":"venue"
},
  "geometry": {"coordinates":[9.475473,47.096016],"type":"Point"}
}