{
  "type": "Feature",
  "properties": {
    "iso:country":"CH",
    "sg:address":"Kaiserstrasse 22-24",
    "sg:city":"Rheinfelden",
    "sg:classifiers":[
        {
            "category":"Banks & Credit Unions",
            "subcategory":"Investment Brokerage",
            "type":"Services"
        }
    ],
    "sg:phone":"+41 61 836 90 70",
    "sg:postcode":"4310",
    "sg:province":"Aargau",
    "sg:tags":[
        "ball",
        "valve"
    ],
    "wof:name":"M. Hoffmann Ag",
    "wof:placetype":"venue"
},
  "geometry": {"coordinates":[7.789525,47.552132],"type":"Point"}
}