{
  "type": "Feature",
  "properties": {
    "iso:country":"CH",
    "sg:address":"Lausanne Rue De 114 1202 Gen\u00e8ve. Postfach",
    "sg:city":"Gen\u00e8ve",
    "sg:orig_category":"Institutionen des Sozialwesens ohne Beherbergung",
    "sg:postcode":"1201",
    "sg:province":"Gen\u00e8ve",
    "wof:name":"Centre Henry Dunant Pour Le Dialogue Humanitaire",
    "wof:placetype":"venue"
},
  "geometry": {"coordinates":[6.1493778229,46.219367981],"type":"Point"}
}