{
  "type": "Feature",
  "properties": {
    "iso:country":"CH",
    "sg:address":"Hauptstrasse 35a 6418 Rothenthurm. Postfach",
    "sg:city":"Rothenthurm",
    "sg:classifiers":[
        {
            "category":"Bars & Pubs",
            "type":"Food & Drink"
        }
    ],
    "sg:postcode":"6418",
    "sg:province":"Schwyz",
    "wof:name":"Michi's Sport Bar, Saxer-huber",
    "wof:placetype":"venue"
},
  "geometry": {"coordinates":[8.674922,47.102276],"type":"Point"}
}