{
  "type": "Feature",
  "properties": {
    "iso:country":"CH",
    "sg:address":"Eggerstanden",
    "sg:city":"Appenzell",
    "sg:orig_category":"Instandhaltung U Reparatur von Automobilen",
    "sg:postcode":"9050",
    "sg:province":"Appenzell Innerhoden",
    "wof:name":"Mara Handels Gmbh",
    "wof:placetype":"venue"
},
  "geometry": {"coordinates":[9.1381845474,47.5666694641],"type":"Point"}
}