{
  "type": "Feature",
  "properties": {
    "iso:country":"CH",
    "sg:address":"Kasparstrasse 7/9 3027 Bern. Postfach",
    "sg:city":"Bern",
    "sg:orig_category":"Detailhandel mit Getr\u00e4nken Detailhandel mit Waren verschiedener Art, Hauptrichtung Nahrungsmittel",
    "sg:phone":"+41 31 998 66 11",
    "sg:postcode":"3001",
    "sg:province":"Bern",
    "wof:name":"Coop Region Bern",
    "wof:placetype":"venue"
},
  "geometry": {"coordinates":[7.3922371864,46.9504585266],"type":"Point"}
}