{
  "type": "Feature",
  "properties": {
    "iso:country":"CH",
    "sg:address":"Route Du Village 1",
    "sg:city":"Blonay",
    "sg:orig_category":"Physiotherapie",
    "sg:phone":"+41 21 943 13 63",
    "sg:postcode":"1807",
    "sg:province":"Vaud",
    "wof:name":"Fran\u00e7oise Amiguet Physioth\u00e9rapie",
    "wof:placetype":"venue"
},
  "geometry": {"coordinates":[6.8941221237,46.467956543],"type":"Point"}
}