{
  "type": "Feature",
  "properties": {
    "iso:country":"CH",
    "sg:address":"Weierstrasse 55",
    "sg:city":"Klingnau",
    "sg:orig_category":"Zeitungsverlag",
    "sg:phone":"+41 56 204 21 21",
    "sg:postcode":"5313",
    "sg:province":"Aargau",
    "wof:name":"Aargauer Zeitung Region Aaretal/ Zurzach Red.",
    "wof:placetype":"venue"
},
  "geometry": {"coordinates":[8.2519025803,47.5797996521],"type":"Point"}
}