{
  "type": "Feature",
  "properties": {
    "iso:country":"CH",
    "sg:address":"Br\u00fcnnenstrasse 26",
    "sg:city":"Bern",
    "sg:orig_category":"Sportvereine Ballsport Basketball",
    "sg:phone":"+41 31 991 58 77",
    "sg:postcode":"3027",
    "sg:province":"Bern",
    "wof:name":"Korbballgr.stv Bern-b\u00fcmpliz",
    "wof:placetype":"venue"
},
  "geometry": {"coordinates":[7.3822999001,46.9452896118],"type":"Point"}
}