{
  "type": "Feature",
  "properties": {
    "iso:country":"CH",
    "sg:address":"Avenue G\u00e9n\u00e9ral-guisan 2",
    "sg:city":"Pully",
    "sg:orig_category":"Einzelhandel mit Automobilteilen U Zubeh\u00f6r Instandhaltung U Reparatur von Automobilen",
    "sg:phone":"+41 21 728 78 39",
    "sg:postcode":"1009",
    "sg:province":"Vaud",
    "wof:name":"Garage Des Chamblandes S\u00e0rl",
    "wof:placetype":"venue"
},
  "geometry": {"coordinates":[6.6562972069,46.5066452026],"type":"Point"}
}