{
  "type": "Feature",
  "properties": {
    "iso:country":"CH",
    "sg:address":"Heinrichstrasse 15",
    "sg:city":"Wallisellen",
    "sg:orig_category":"Reiseb\u00fcros U Reiseveranstalter",
    "sg:phone":"+41 18303491",
    "sg:postcode":"8304",
    "sg:province":"Z\u00fcrich",
    "wof:name":"Cosmont Travel, Piwnik Richard",
    "wof:placetype":"venue"
},
  "geometry": {"coordinates":[8.5884628296,47.4140396118],"type":"Point"}
}