{
  "type": "Feature",
  "properties": {
    "iso:country":"CH",
    "sg:address":"3937",
    "sg:city":"Baltschieder",
    "sg:classifiers":[
        {
            "category":"Restaurant",
            "type":"Food & Drink"
        }
    ],
    "sg:phone":"+41 27 946 55 70",
    "sg:postcode":"3937",
    "sg:province":"Valais",
    "wof:name":"Pizzeria Cavallo",
    "wof:placetype":"venue"
},
  "geometry": {"coordinates":[7.8553299904,46.3068313599],"type":"Point"}
}