{
  "type": "Feature",
  "properties": {
    "iso:country":"CH",
    "sg:address":"Wuhrmattstrasse 4 4800 Zofingen. Postfach",
    "sg:city":"Zofingen",
    "sg:orig_category":"Stukkateurgewerbe, Gipserei U Verputzerei",
    "sg:phone":"+41 62 751 18 46",
    "sg:postcode":"4800",
    "sg:province":"Aargau",
    "wof:name":"Gipsergesch\u00e4ft B\u00e4r Ag",
    "wof:placetype":"venue"
},
  "geometry": {"coordinates":[7.9432320595,47.2833862305],"type":"Point"}
}