{
  "type": "Feature",
  "properties": {
    "iso:country":"CH",
    "sg:address":"Bahnhofstrasse 9 4553 Subingen. Postfach 139",
    "sg:city":"Subingen",
    "sg:orig_category":"Arztpraxen",
    "sg:phone":"+41 32 614 36 36",
    "sg:postcode":"4553",
    "sg:province":"Solothurn",
    "wof:name":"Dr.med.urban Wirz Arzt F.allgemeine Medizin Fmh",
    "wof:placetype":"venue"
},
  "geometry": {"coordinates":[7.613579,47.194408],"type":"Point"}
}