{
  "type": "Feature",
  "properties": {
    "iso:country":"CH",
    "sg:address":"Kirchstrasse 1",
    "sg:city":"Kreuzlingen",
    "sg:orig_category":"Detailhandel mit Fahrr\u00e4dern",
    "sg:phone":"+41 71 672 30 11",
    "sg:postcode":"8280",
    "sg:province":"Thurgau",
    "wof:name":"B\u00f6gli Und Sp\u00e4ni, Velodrom Bodensee",
    "wof:placetype":"venue"
},
  "geometry": {"coordinates":[9.1732139587,47.6474075317],"type":"Point"}
}