{
  "type": "Feature",
  "properties": {
    "iso:country":"CH",
    "sg:address":"Montchoisy Rue De 37 1207 Gen\u00e8ve. Postfach",
    "sg:city":"Gen\u00e8ve",
    "sg:orig_category":"Unclassifiable Establishments",
    "sg:postcode":"1207",
    "sg:province":"Gen\u00e8ve",
    "wof:name":"Hana Inter Sa",
    "wof:placetype":"venue"
},
  "geometry": {"coordinates":[6.162129879,46.2044448853],"type":"Point"}
}