{
  "type": "Feature",
  "properties": {
    "iso:country":"CH",
    "sg:address":"Via Gottardo 10",
    "sg:city":"Bellinzona",
    "sg:classifiers":[
        {
            "category":"Arena",
            "subcategory":"Sports Club",
            "type":"Entertainment"
        }
    ],
    "sg:postcode":"6500",
    "sg:province":"Ticino",
    "sg:tags":[
        "karate",
        "judo",
        "sportvereine"
    ],
    "wof:name":"Shung Do Kwan Bellinzona",
    "wof:placetype":"venue"
},
  "geometry": {"coordinates":[9.0275554657,46.198135376],"type":"Point"}
}