{
  "type": "Feature",
  "properties": {
    "iso:country":"CH",
    "sg:address":"Grand-rue 8-12",
    "sg:city":"Payerne",
    "sg:orig_category":"Pensionskassen",
    "sg:postcode":"1530",
    "sg:province":"Vaud",
    "wof:name":"Fonds De Pr\u00e9voyance En Faveur Du Personnel De Grands Magasins Manor Bladt Sa",
    "wof:placetype":"venue"
},
  "geometry": {"coordinates":[6.9394822121,46.8217582703],"type":"Point"}
}