{
  "type": "Feature",
  "properties": {
    "iso:country":"CH",
    "sg:address":"Route De La Gemmi 151",
    "sg:city":"Sierre",
    "sg:orig_category":"Glaserei Verarbeitung U Veredlung von Flachglas",
    "sg:phone":"+41 31 336 81 81",
    "sg:postcode":"3960",
    "sg:province":"Valais",
    "wof:name":"Giesbrecht Ag Isolier- U. Flachglas, Spezialgl\u00e4ser, Spiegel; Fabr, Verarbeitung",
    "wof:placetype":"venue"
},
  "geometry": {"coordinates":[7.4643001556,46.9686279297],"type":"Point"}
}