{
  "type": "Feature",
  "properties": {
    "iso:country":"CH",
    "sg:address":"Rebenstrasse 28",
    "sg:city":"B\u00e4ttwil",
    "sg:orig_category":"Schulpflegen",
    "sg:phone":"+41 61 731 22 61",
    "sg:postcode":"4112",
    "sg:province":"Solothurn",
    "wof:name":"Primarschulkommission Herrn Ren\u00e9 Stalder",
    "wof:placetype":"venue"
},
  "geometry": {"coordinates":[7.5107030869,47.4885063171],"type":"Point"}
}