{
  "type": "Feature",
  "properties": {
    "iso:country":"CH",
    "sg:address":"Speerstrasse 13",
    "sg:city":"N\u00e4fels",
    "sg:orig_category":"Sportvereine Turnen Damen",
    "sg:phone":"+41 55 618 45 45",
    "sg:postcode":"8752",
    "sg:province":"Glarus",
    "wof:name":"Damenturnverein N\u00e4fels",
    "wof:placetype":"venue"
},
  "geometry": {"coordinates":[9.0618572235,47.0896034241],"type":"Point"}
}