{
  "type": "Feature",
  "properties": {
    "iso:country":"CH",
    "sg:address":"Eintrachtstrasse 16 8820 W\u00e4denswil. Postfach",
    "sg:city":"W\u00e4denswil",
    "sg:orig_category":"Unternehmensberatung",
    "sg:postcode":"8820",
    "sg:province":"Z\u00fcrich",
    "wof:name":"Von Bernuth Beratung Beratung Von Handelsgesch\u00e4ften",
    "wof:placetype":"venue"
},
  "geometry": {"coordinates":[8.6736536026,47.2273330688],"type":"Point"}
}