{
  "type": "Feature",
  "properties": {
    "iso:country":"CH",
    "sg:address":"Avenue Du Plan 13",
    "sg:city":"Morges",
    "sg:orig_category":"Stukkateurgewerbe, Gipserei U Verputzerei",
    "sg:phone":"+41 21 802 33 79",
    "sg:postcode":"1110",
    "sg:province":"Vaud",
    "wof:name":"Salvatore D'agostino Peinture & Gypserie",
    "wof:placetype":"venue"
},
  "geometry": {"coordinates":[6.5054759979,46.5180053711],"type":"Point"}
}