{
  "type": "Feature",
  "properties": {
    "iso:country":"CH",
    "sg:address":"Weingartenstrasse 54",
    "sg:city":"Naters",
    "sg:orig_category":"Architektur U Ingenieurb\u00fcros",
    "sg:phone":"+41 19306233",
    "sg:postcode":"3904",
    "sg:province":"Valais",
    "wof:name":"Alex Brunner, Architekt Htl",
    "wof:placetype":"venue"
},
  "geometry": {"coordinates":[8.799421,47.32666],"type":"Point"}
}