{
  "type": "Feature",
  "properties": {
    "iso:country":"CH",
    "sg:address":"Rosengasse 6",
    "sg:city":"Liestal",
    "sg:orig_category":"Detailhandel mit elektrischen Haushalts-,Radio U Fernsehger\u00e4ten sowie Musikinstrumenten",
    "sg:phone":"+41 61 921 04 05",
    "sg:postcode":"4410",
    "sg:province":"Basel-Landschaft",
    "wof:name":"Glaser-landert Peter",
    "wof:placetype":"venue"
},
  "geometry": {"coordinates":[7.7354989052,47.4846305847],"type":"Point"}
}