{
  "type": "Feature",
  "properties": {
    "iso:country":"CH",
    "sg:address":"Froburgstrasse 25 4052 Basel. Postfach",
    "sg:city":"Basel",
    "sg:orig_category":"Werbeagenturen Werbegrafikateliers",
    "sg:phone":"+41 56 450 27 17",
    "sg:postcode":"4006",
    "wof:name":"A. Dennler Multimedia",
    "wof:placetype":"venue"
},
  "geometry": {"coordinates":[8.2079238892,47.4831848145],"type":"Point"}
}