{
  "type": "Feature",
  "properties": {
    "iso:country":"CH",
    "sg:address":"Suhrerstrasse 13",
    "sg:city":"Oberentfelden",
    "sg:orig_category":"Versicherungen Hauptagenturen",
    "sg:phone":"+41 81 410 07 11",
    "sg:postcode":"5036",
    "sg:province":"Aargau",
    "wof:name":"Die Mobiliar Versicherungen & Vorsorge",
    "wof:placetype":"venue"
},
  "geometry": {"coordinates":[9.8305082321,46.7986831665],"type":"Point"}
}