{
  "type": "Feature",
  "properties": {
    "iso:country":"CH",
    "sg:address":"Dorfstrasse 44",
    "sg:city":"Uetendorf",
    "sg:orig_category":"Detailhandel mit Brot, Back U S\u00fcsswaren",
    "sg:phone":"+41 33 345 47 22",
    "sg:postcode":"3661",
    "sg:province":"Bern",
    "wof:name":"Beck Winkler Ag",
    "wof:placetype":"venue"
},
  "geometry": {"coordinates":[7.574093,46.773579],"type":"Point"}
}