{
  "type": "Feature",
  "properties": {
    "iso:country":"CH",
    "sg:address":"Lehengasse 38",
    "sg:city":"M\u00fcnchenstein",
    "sg:orig_category":"Vorschulen, Kinderg\u00e4rten",
    "sg:phone":"+41 18411246",
    "sg:postcode":"4142",
    "sg:province":"Basel-Landschaft",
    "wof:name":"Kindergarten B\u00fcngertli",
    "wof:placetype":"venue"
},
  "geometry": {"coordinates":[8.463809967,47.4514694214],"type":"Point"}
}