{
  "type": "Feature",
  "properties": {
    "iso:country":"CH",
    "sg:address":"Route De St-georges 72",
    "sg:city":"Petit-lancy",
    "sg:orig_category":"Non-Classified Establishments",
    "sg:phone":"+41 22 792 16 50",
    "sg:postcode":"1213",
    "sg:province":"Gen\u00e8ve",
    "wof:name":"Baerlocher Harry Sa",
    "wof:placetype":"venue"
},
  "geometry": {"coordinates":[6.1188998222,46.1964492798],"type":"Point"}
}