{
  "type": "Feature",
  "properties": {
    "iso:country":"CH",
    "sg:address":"Strassburgerallee 102 4055 Basel. Postfach",
    "sg:city":"Basel",
    "sg:orig_category":"RESTAURANTS: TEA-ROOMS",
    "sg:postcode":"4051",
    "sg:province":"Basel-Stadt",
    "wof:name":"Arthur Von K\u00e4nel-fuchs Restaurant",
    "wof:placetype":"venue"
},
  "geometry": {"coordinates":[7.5688018799,47.561504364],"type":"Point"}
}