{
  "type": "Feature",
  "properties": {
    "iso:country":"CH",
    "sg:address":"Bitzibergstrasse 2",
    "sg:city":"Winkel",
    "sg:orig_category":"Gem\u00fcsebau Grosshandel mit Obst U Gem\u00fcse",
    "sg:phone":"+41 18440325",
    "sg:postcode":"8185",
    "sg:province":"Z\u00fcrich",
    "wof:name":"Meier Gebr\u00fcder Fritz & Rudolf, Gem\u00fcsebau",
    "wof:placetype":"venue"
},
  "geometry": {"coordinates":[8.4249954224,47.4535598755],"type":"Point"}
}