{
  "type": "Feature",
  "properties": {
    "iso:country":"CH",
    "sg:address":"Bruderholzstrasse 12",
    "sg:city":"Basel",
    "sg:orig_category":"Unclassifiable Establishments",
    "sg:postcode":"4053",
    "sg:province":"Basel-Stadt",
    "wof:name":"Transport Ceklic",
    "wof:placetype":"venue"
},
  "geometry": {"coordinates":[7.5948019028,47.5441131592],"type":"Point"}
}