{
  "type": "Feature",
  "properties": {
    "iso:country":"CH",
    "sg:address":"1681",
    "sg:city":"Billens",
    "sg:orig_category":"Landesverteidigung, Sozialversicherung \u00d6ffentliche Verwaltung",
    "sg:phone":"+41 26 652 15 00",
    "sg:postcode":"1681",
    "sg:province":"Fribourg",
    "wof:name":"Centre De Protection Civile",
    "wof:placetype":"venue"
},
  "geometry": {"coordinates":[6.8989601135,46.6904983521],"type":"Point"}
}