{
  "type": "Feature",
  "properties": {
    "iso:country":"CH",
    "sg:address":"Fischerweg 36",
    "sg:city":"Oftringen",
    "sg:orig_category":"Innendekorationsateliers",
    "sg:phone":"+41 62 797 70 10",
    "sg:postcode":"4665",
    "sg:province":"Aargau",
    "wof:name":"Bernard Keiser Vorhangatelier",
    "wof:placetype":"venue"
},
  "geometry": {"coordinates":[7.9401311874,47.299243927],"type":"Point"}
}