{
  "type": "Feature",
  "properties": {
    "iso:country":"CH",
    "sg:address":"Bahnhofstrasse 23",
    "sg:city":"N\u00e4fels",
    "sg:orig_category":"Unclassifiable Establishments",
    "sg:postcode":"8752",
    "sg:province":"Glarus",
    "wof:name":"Tentalus \u00dcbersetzungen Bermudez",
    "wof:placetype":"venue"
},
  "geometry": {"coordinates":[9.0663518906,47.0995903015],"type":"Point"}
}