{
  "type": "Feature",
  "properties": {
    "iso:country":"CH",
    "sg:address":"Rue Des Fahys 249",
    "sg:city":"Neuenburg",
    "sg:orig_category":"G\u00fcterbef\u00f6rderung im Strassenverkehr",
    "sg:phone":"+41 32 725 05 16",
    "sg:postcode":"2000",
    "sg:province":"Neuch\u00e2tel",
    "wof:name":"Hdt Humbert-droz Transports",
    "wof:placetype":"venue"
},
  "geometry": {"coordinates":[6.9487781525,47.0020484924],"type":"Point"}
}