{
  "type": "Feature",
  "properties": {
    "iso:country":"CH",
    "sg:address":"Pal.polti",
    "sg:city":"Grono",
    "sg:orig_category":"Physiotherapie",
    "sg:phone":"+41 79 223 97 63",
    "sg:postcode":"6537",
    "sg:province":"Graubunden",
    "wof:name":"Antonio Maesano Fisioterapia",
    "wof:placetype":"venue"
},
  "geometry": {"coordinates":[9.1464338303,46.2478141785],"type":"Point"}
}