{
  "type": "Feature",
  "properties": {
    "iso:country":"CH",
    "sg:address":"B\u00fcntenstrasse 1",
    "sg:city":"Fislisbach",
    "sg:orig_category":"Reiseb\u00fcros U Reiseveranstalter",
    "sg:postcode":"5442",
    "sg:province":"Aargau",
    "wof:name":"Otto Reisen, Christen O.",
    "wof:placetype":"venue"
},
  "geometry": {"coordinates":[8.2895555496,47.4402160645],"type":"Point"}
}