{
  "type": "Feature",
  "properties": {
    "iso:country":"CH",
    "sg:address":"Rheinstrasse",
    "sg:city":"Trimmis",
    "sg:orig_category":"Mineral\u00f6lverarbeitung",
    "sg:phone":"+41 71 912 13 43",
    "sg:postcode":"7203",
    "sg:province":"Graubunden",
    "wof:name":"Halter Ag Wil",
    "wof:placetype":"venue"
},
  "geometry": {"coordinates":[9.0650749207,47.4642295837],"type":"Point"}
}