{
  "type": "Feature",
  "properties": {
    "iso:country":"CH",
    "sg:address":"Ebnatstrasse 86 8200 Schaffhausen. Postfach",
    "sg:city":"Schaffhausen",
    "sg:classifiers":[
        {
            "category":"Education",
            "subcategory":"Library",
            "type":"Public Place"
        }
    ],
    "sg:phone":"+41 79 430 23 51",
    "sg:postcode":"8201",
    "sg:province":"Schaffhausen",
    "sg:tags":[
        "u",
        "bibliotheken",
        "archive"
    ],
    "wof:name":"Georg Fischer Ag Literatur-b\u00fcro Mfb 3557",
    "wof:placetype":"venue"
},
  "geometry": {"coordinates":[8.646116,47.707928],"type":"Point"}
}