{
  "type": "Feature",
  "properties": {
    "addr:full":"Montchoisi Avenue De 21 1006 Lausanne. Postfach Lausanne Vaud 1003",
    "addr:housenumber":"21",
    "addr:postcode":"1006;postfach;1003",
    "addr:street":"Montchoisi Avenue De",
    "iso:country":"CH",
    "sg:address":"Montchoisi Avenue De 21 1006 Lausanne. Postfach",
    "sg:city":"Lausanne",
    "sg:orig_category":"Architektur U Ingenieurb\u00fcros",
    "sg:phone":"+41 32 721 20 20",
    "sg:postcode":"1003",
    "sg:province":"Vaud",
    "wof:name":"Urbaplan",
    "wof:placetype":"venue"
},
  "geometry": {"coordinates":[6.929386,46.990898],"type":"Point"}
}