{
  "type": "Feature",
  "properties": {
    "iso:country":"CH",
    "sg:address":"Florimont Chemin De 6",
    "sg:city":"Villars-sur-gl\u00e2ne",
    "sg:orig_category":"Interessenvertretungen",
    "sg:phone":"+41 26 402 23 27",
    "sg:postcode":"1752",
    "sg:province":"Fribourg",
    "wof:name":"Fondation Du Cur\u00e9 Louis Koerber",
    "wof:placetype":"venue"
},
  "geometry": {"coordinates":[7.130428791,46.7955818176],"type":"Point"}
}