{
  "type": "Feature",
  "properties": {
    "iso:country":"CH",
    "sg:address":"B\u00e4nkliholzweg 6 8335 Hittnau. Postfach 271",
    "sg:city":"Hittnau",
    "sg:orig_category":"Sanit\u00e4r, Heizungs U L\u00fcftungsinstallation Sanit\u00e4rinstallation",
    "sg:phone":"+41 19500459",
    "sg:postcode":"8335",
    "sg:province":"Z\u00fcrich",
    "wof:name":"Meibach Ag",
    "wof:placetype":"venue"
},
  "geometry": {"coordinates":[8.8248271942,47.3704032898],"type":"Point"}
}