{
  "type": "Feature",
  "properties": {
    "iso:country":"CH",
    "sg:address":"Bahnhofstrasse 10",
    "sg:city":"Brig",
    "sg:orig_category":"Detailhandel mit Brillen U anderen Sehhilfen",
    "sg:phone":"+41 31 311 73 13",
    "sg:postcode":"3900",
    "sg:province":"Valais",
    "wof:name":"Raphael Eschmann Augenoptik",
    "wof:placetype":"venue"
},
  "geometry": {"coordinates":[7.449693,46.948097],"type":"Point"}
}