{
  "type": "Feature",
  "properties": {
    "iso:country":"CH",
    "sg:address":"Sch\u00fctzenstrasse 12a",
    "sg:city":"Heimberg",
    "sg:orig_category":"Fahrschulen, Flugschulen",
    "sg:phone":"+41 31 302 62 56",
    "sg:postcode":"3627",
    "sg:province":"Bern",
    "wof:name":"Heinz Dysli Autofahrschule",
    "wof:placetype":"venue"
},
  "geometry": {"coordinates":[7.4397039413,46.9823226929],"type":"Point"}
}