{
  "type": "Feature",
  "properties": {
    "iso:country":"CH",
    "sg:address":"Grand-rue 140",
    "sg:city":"Tramelan",
    "sg:orig_category":"Detailhandel mit Bekleidung",
    "sg:phone":"+41 61 712 50 55",
    "sg:postcode":"2720",
    "sg:province":"Bern",
    "wof:name":"Boutique Oceane Chapuis-gross Fabienne",
    "wof:placetype":"venue"
},
  "geometry": {"coordinates":[7.591615,47.493404],"type":"Point"}
}