{
  "type": "Feature",
  "properties": {
    "iso:country":"CH",
    "sg:address":"Rathausstrasse 38",
    "sg:city":"Leukerbad",
    "sg:classifiers":[
        {
            "category":"Travel",
            "subcategory":"Hotels & Motels",
            "type":"Entertainment"
        }
    ],
    "sg:phone":"+41 27 472 79 60",
    "sg:postcode":"3954",
    "sg:province":"Valais",
    "sg:tags":[
        "hotels",
        "mit",
        "restaurant"
    ],
    "wof:name":"Hotel Walliserhof",
    "wof:placetype":"venue"
},
  "geometry": {"coordinates":[7.6262497902,46.3767547607],"type":"Point"}
}