{
  "type": "Feature",
  "properties": {
    "iso:country":"CH",
    "sg:address":"9490 Vaduz. Postfach 164",
    "sg:city":"Vaduz",
    "sg:classifiers":[
        {
            "category":"Arena",
            "subcategory":"Sports Club",
            "type":"Entertainment"
        }
    ],
    "sg:postcode":"9490",
    "sg:tags":[
        "karate",
        "judo",
        "sportvereine"
    ],
    "wof:name":"Shotokan Kc Arbon",
    "wof:placetype":"venue"
},
  "geometry": {"coordinates":[9.401640892,47.4876899719],"type":"Point"}
}