{
  "type": "Feature",
  "properties": {
    "iso:country":"CH",
    "sg:address":"Am Rain 1",
    "sg:city":"Netstal",
    "sg:orig_category":"Kauf U Verkauf von Immobilien auf eigene Rechnung",
    "sg:postcode":"8754",
    "sg:province":"Glarus",
    "wof:name":"Bachhoschet Ag",
    "wof:placetype":"venue"
},
  "geometry": {"coordinates":[9.0559082031,47.0621643066],"type":"Point"}
}