{
  "type": "Feature",
  "properties": {
    "iso:country":"CH",
    "sg:address":"Biltnerstrasse 42",
    "sg:city":"Sch\u00e4nis",
    "sg:classifiers":[
        {
            "category":"Shopping",
            "subcategory":"Discount & Variety Stores",
            "type":"Retail Goods"
        }
    ],
    "sg:phone":"+41 55 619 66 00",
    "sg:postcode":"8718",
    "sg:province":"St. Gallen",
    "sg:tags":[
        "shop",
        "self-service",
        "bedding",
        "cash",
        "carry"
    ],
    "wof:name":"Bico Ag",
    "wof:placetype":"venue"
},
  "geometry": {"coordinates":[9.036909,47.15485],"type":"Point"}
}