{
  "type": "Feature",
  "properties": {
    "iso:country":"CH",
    "sg:address":"General Guisan-strasse 46",
    "sg:city":"Basel",
    "sg:orig_category":"Arztpraxen",
    "sg:phone":"+41 61 301 38 63",
    "sg:postcode":"4054",
    "sg:province":"Basel-Stadt",
    "wof:name":"Dr.med.heinz Probst Spezialarzt Fmh",
    "wof:placetype":"venue"
},
  "geometry": {"coordinates":[7.568222,47.551144],"type":"Point"}
}