{
  "type": "Feature",
  "properties": {
    "iso:country":"CH",
    "sg:address":"Eisfeldstrasse 16",
    "sg:city":"Z\u00fcrich",
    "sg:orig_category":"Herstellung von sonstigen elektrischen Ausr\u00fcstungen",
    "sg:phone":"+41 13010101",
    "sg:postcode":"8050",
    "sg:province":"Z\u00fcrich",
    "wof:name":"Transelec Ag",
    "wof:placetype":"venue"
},
  "geometry": {"coordinates":[8.5476293564,47.4151077271],"type":"Point"}
}