{
  "type": "Feature",
  "properties": {
    "iso:country":"CH",
    "sg:address":"Muttenzerstrasse 70",
    "sg:city":"Birsfelden",
    "sg:orig_category":"G\u00fcterbef\u00f6rderung im Strassenverkehr",
    "sg:phone":"+41 61 313 05 21",
    "sg:postcode":"4127",
    "sg:province":"Basel-Landschaft",
    "wof:name":"Henri Grieder Transporte",
    "wof:placetype":"venue"
},
  "geometry": {"coordinates":[7.6250967979,47.5472679138],"type":"Point"}
}