{
  "type": "Feature",
  "properties": {
    "iso:country":"CH",
    "sg:address":"Leimgrubenweg 9 4053 Basel. Postfach",
    "sg:city":"Basel",
    "sg:orig_category":"Betrieb U technische Hilfsdienste des Kultur U Unterhaltungswesens",
    "sg:phone":"+41 61 333 22 33",
    "sg:postcode":"4053",
    "sg:province":"Basel-Stadt",
    "wof:name":"3-spitz Fun-park, Reinle K. Freizeitanlagen. Veranstaltungen Auf Den Gebieten Sport, Unterhaltung U. Kultur",
    "wof:placetype":"venue"
},
  "geometry": {"coordinates":[7.608173,47.53685],"type":"Point"}
}