{
  "type": "Feature",
  "properties": {
    "iso:country":"CH",
    "sg:address":"Bernstrasse 71",
    "sg:city":"Moosseedorf",
    "sg:orig_category":"Sonstiger Grosshandel",
    "sg:postcode":"3302",
    "sg:province":"Bern",
    "wof:name":"Huki Trading Ag",
    "wof:placetype":"venue"
},
  "geometry": {"coordinates":[7.4837021828,47.0169410706],"type":"Point"}
}