{
  "type": "Feature",
  "properties": {
    "addr:full":"M\u00fchledorfstrasse 1/62 3018 Bern. Postfach Bern Bern 3018",
    "addr:housenumber":"1 / 62",
    "addr:postcode":"3018;postfach;3018",
    "addr:street":"Muehledorfstrasse",
    "iso:country":"CH",
    "sg:address":"M\u00fchledorfstrasse 1/62 3018 Bern. Postfach",
    "sg:city":"Bern",
    "sg:orig_category":"Architektur U Ingenieurb\u00fcros",
    "sg:phone":"+41 31 991 39 63",
    "sg:postcode":"3018",
    "sg:province":"Bern",
    "wof:name":"Mek, Ag F\u00fcr Interdisziplin\u00e4res Projektmanagement",
    "wof:placetype":"venue"
},
  "geometry": {"coordinates":[7.391687,46.945564],"type":"Point"}
}