{
  "type": "Feature",
  "properties": {
    "iso:country":"CH",
    "sg:address":"Weiningerstrasse 48 8103 Unterengstringen. Postfach 123",
    "sg:city":"Unterengstringen",
    "sg:orig_category":"Buchf\u00fchrung Wirtschaftspr\u00fcfung, Steuerberatung U Treuhand",
    "sg:phone":"+41 17501922",
    "sg:postcode":"8103",
    "sg:province":"Z\u00fcrich",
    "wof:name":"W\u00e4lte Consulting Buchhaltung & Steuerberatung",
    "wof:placetype":"venue"
},
  "geometry": {"coordinates":[8.449126,47.41309],"type":"Point"}
}