{
  "type": "Feature",
  "properties": {
    "iso:country":"CH",
    "sg:address":"Bruderholzallee 152",
    "sg:city":"Basel",
    "sg:orig_category":"Detailhandel mit Milcherzeugnissen U Eiern",
    "sg:phone":"+41 61 361 91 11",
    "sg:postcode":"4059",
    "sg:province":"Basel-Stadt",
    "wof:name":"Ch\u00e4s-hummeli H\u00e4nggi Christoph Lebensmittelgesch\u00e4ft, Bes. K\u00e4se U. Frischprodukte",
    "wof:placetype":"venue"
},
  "geometry": {"coordinates":[7.5937409401,47.5322875977],"type":"Point"}
}