{
  "type": "Feature",
  "properties": {
    "iso:country":"CH",
    "sg:address":"Freiburgstrasse 500",
    "sg:city":"W\u00fcnnewil",
    "sg:orig_category":"Grosshandel mit Holz U Baustoffen",
    "sg:postcode":"3184",
    "sg:province":"Fribourg",
    "wof:name":"Schneider Paul",
    "wof:placetype":"venue"
},
  "geometry": {"coordinates":[7.3098402023,46.8880996704],"type":"Point"}
}