{
  "type": "Feature",
  "properties": {
    "iso:country":"CH",
    "sg:address":"2950",
    "sg:city":"Courgenay",
    "sg:orig_category":"Sportvereine Turnen",
    "sg:postcode":"2950",
    "sg:province":"Jura",
    "wof:name":"St\u00e9 De Gymnastique",
    "wof:placetype":"venue"
},
  "geometry": {"coordinates":[7.1266851425,47.403213501],"type":"Point"}
}