{
  "type": "Feature",
  "properties": {
    "iso:country":"CH",
    "sg:address":"S. Catrina",
    "sg:city":"Disentis/must\u00e9r",
    "sg:orig_category":"Personenbef\u00f6rderung im Linienverkehr zu Land",
    "sg:postcode":"7180",
    "sg:province":"Graubunden",
    "wof:name":"Bergbahnen Flumserberg Ag",
    "wof:placetype":"venue"
},
  "geometry": {"coordinates":[9.3425388336,47.0917549133],"type":"Point"}
}