{
  "type": "Feature",
  "properties": {
    "iso:country":"CH",
    "sg:address":"Pfaffenhalde 1",
    "sg:city":"Boniswil",
    "sg:orig_category":"Softwareentwicklung U beratung",
    "sg:postcode":"5706",
    "sg:province":"Aargau",
    "wof:name":"Becker Dienstleistungen",
    "wof:placetype":"venue"
},
  "geometry": {"coordinates":[8.1820573807,47.3137779236],"type":"Point"}
}