{
  "type": "Feature",
  "properties": {
    "iso:country":"CH",
    "sg:address":"Klosbachstrasse 33",
    "sg:city":"Z\u00fcrich",
    "sg:orig_category":"Werbegrafikateliers",
    "sg:phone":"+41 12531665",
    "sg:postcode":"8032",
    "sg:province":"Z\u00fcrich",
    "wof:name":"Katharina Gassmann Atelier F.visuelle Gestaltung",
    "wof:placetype":"venue"
},
  "geometry": {"coordinates":[8.5562362671,47.3659820557],"type":"Point"}
}