{
  "type": "Feature",
  "properties": {
    "iso:country":"CH",
    "sg:address":"Lindenstrasse 12",
    "sg:city":"Niederhasli",
    "sg:orig_category":"Herstellung von sonstigen Maschinen f\u00fcr unspezifische Verwendung",
    "sg:postcode":"8155",
    "sg:province":"Z\u00fcrich",
    "wof:name":"W. Hauser, Apparate- & Metallbau",
    "wof:placetype":"venue"
},
  "geometry": {"coordinates":[9.3956680298,47.4401702881],"type":"Point"}
}