{
  "type": "Feature",
  "properties": {
    "addr:full":"Junkerhof Naters Valais 3904",
    "addr:postcode":"3904",
    "iso:country":"CH",
    "sg:address":"Junkerhof",
    "sg:city":"Naters",
    "sg:orig_category":"Betrieb U technische Hilfsdienste des Kultur U Unterhaltungswesens",
    "sg:phone":"+41 17617861",
    "sg:postcode":"3904",
    "sg:province":"Valais",
    "wof:name":"Stockmatt Freizeit Ag",
    "wof:placetype":"venue"
},
  "geometry": {"coordinates":[8.452604,47.287052],"type":"Point"}
}