{
  "type": "Feature",
  "properties": {
    "iso:country":"CH",
    "sg:address":"Grenzacherstrasse 124",
    "sg:city":"Basel",
    "sg:orig_category":"Erbringung von Dienstleistungen f\u00fcr Unternehmen",
    "sg:postcode":"4058",
    "sg:province":"Basel-Stadt",
    "wof:name":"Ronexus Services Ag",
    "wof:placetype":"venue"
},
  "geometry": {"coordinates":[7.6080927849,47.5590171814],"type":"Point"}
}