{
  "type": "Feature",
  "properties": {
    "iso:country":"CH",
    "sg:address":"Place Saint-fran\u00e7ois 4 1003 Lausanne. Postfach",
    "sg:city":"Lausanne",
    "sg:orig_category":"Detailhandel mit Brillen U anderen Sehhilfen Fachdetailhandel in Verkaufsr\u00e4umen",
    "sg:phone":"+41 21 312 85 31",
    "sg:postcode":"1002",
    "sg:province":"Vaud",
    "wof:name":"De Malm Optique Sa",
    "wof:placetype":"venue"
},
  "geometry": {"coordinates":[6.632859,46.520023],"type":"Point"}
}