{
  "type": "Feature",
  "properties": {
    "addr:full":"Aeschenvorstadt 55 4051 Basel. Postfach Basel Basel-Stadt 4051",
    "addr:housenumber":"55",
    "addr:postcode":"4051;4051",
    "addr:street":"Aeschenvorstadt;Postfach",
    "iso:country":"CH",
    "sg:address":"Aeschenvorstadt 55 4051 Basel. Postfach",
    "sg:city":"Basel",
    "sg:orig_category":"Detailhandel mit Bekleidung",
    "sg:phone":"+41 61 311 34 37",
    "sg:postcode":"4051",
    "sg:province":"Basel-Stadt",
    "wof:name":"Number One Productions Gmbh",
    "wof:placetype":"venue"
},
  "geometry": {"coordinates":[7.593755,47.552391],"type":"Point"}
}