{
  "type": "Feature",
  "properties": {
    "iso:country":"CH",
    "sg:address":"Rue Gabriel-lory 8",
    "sg:city":"Neuch\u00e2tel",
    "sg:orig_category":"Mechanik Stahl U Leichtmetallbau",
    "sg:phone":"+41 32 730 32 00",
    "sg:postcode":"2000",
    "sg:province":"Neuch\u00e2tel",
    "wof:name":"Vessaz F. Sa",
    "wof:placetype":"venue"
},
  "geometry": {"coordinates":[6.9071669579,46.9863357544],"type":"Point"}
}