{
  "type": "Feature",
  "properties": {
    "iso:country":"CH",
    "sg:address":"Wieslergasse 7",
    "sg:city":"Z\u00fcrich",
    "sg:orig_category":"Detailhandel mit Metallwaren, Anstrichmitteln, Glaswaren, Bau U Heimwerkerbedarf",
    "sg:phone":"+41 19951895",
    "sg:postcode":"8049",
    "sg:province":"Z\u00fcrich",
    "wof:name":"Marenco Ag Techn. Produkte Bes. Prototypen, Zeichnungen Usw.; Herst., Handel",
    "wof:placetype":"venue"
},
  "geometry": {"coordinates":[8.7952785492,47.3630638123],"type":"Point"}
}