{
  "type": "Feature",
  "properties": {
    "iso:country":"CH",
    "sg:address":"Rue Du Grand-pont 17",
    "sg:city":"Sion",
    "sg:orig_category":"Detailhandel mit Uhren U Schmuck Kunsthandel",
    "sg:phone":"+41 79 611 52 36",
    "sg:postcode":"1950",
    "sg:province":"Valais",
    "wof:name":"Galerie De La Vieille Fontaine",
    "wof:placetype":"venue"
},
  "geometry": {"coordinates":[7.3603458405,46.2342414856],"type":"Point"}
}