{
  "type": "Feature",
  "properties": {
    "iso:country":"CH",
    "sg:address":"Route De Coeuve 46",
    "sg:city":"Porrentruy",
    "sg:orig_category":"Herstellung U Zusammensetzung von Uhren",
    "sg:phone":"+41 22 343 67 82",
    "sg:postcode":"2900",
    "sg:province":"Jura",
    "wof:name":"Perroud & Viollier Terminage D'horlogerie",
    "wof:placetype":"venue"
},
  "geometry": {"coordinates":[6.1407971382,46.1885795593],"type":"Point"}
}