{
  "type": "Feature",
  "properties": {
    "iso:country":"CH",
    "sg:address":"Hauptstrasse",
    "sg:city":"H\u00fcttwilen",
    "sg:orig_category":"Detailhandel mit Fleisch U Fleischwaren",
    "sg:phone":"+41 52 747 16 47",
    "sg:postcode":"8536",
    "sg:province":"Thurgau",
    "wof:name":"Christian & Lilian Levi Dorfmetzg",
    "wof:placetype":"venue"
},
  "geometry": {"coordinates":[8.8737602234,47.6048088074],"type":"Point"}
}