{
  "type": "Feature",
  "properties": {
    "iso:country":"CH",
    "sg:address":"Steinentorstrasse 14 4051 Basel. Postfach",
    "sg:city":"Basel",
    "sg:orig_category":"G\u00fcterbef\u00f6rderung im Strassenverkehr",
    "sg:postcode":"4051",
    "sg:province":"Basel-Stadt",
    "wof:name":"Bader Transport Ag Spedition, Internat. Warentransport Usw",
    "wof:placetype":"venue"
},
  "geometry": {"coordinates":[7.5889968872,47.5519180298],"type":"Point"}
}