{
  "type": "Feature",
  "properties": {
    "iso:country":"CH",
    "sg:address":"Pr\u00e4ttigauerstrasse 213l",
    "sg:city":"Landquart",
    "sg:orig_category":"Detailhandel mit Textilien Detailhandel mit elektrischen Haushaltsger\u00e4ten",
    "sg:phone":"+41 81 322 46 64",
    "sg:postcode":"7302",
    "sg:province":"Graubunden",
    "wof:name":"Elsbeth D\u00fcrst Handarbeits-corner",
    "wof:placetype":"venue"
},
  "geometry": {"coordinates":[9.5707778931,46.968624115],"type":"Point"}
}