{
  "type": "Feature",
  "properties": {
    "iso:country":"CH",
    "sg:address":"1200",
    "sg:city":"Gen\u00e8ve",
    "sg:orig_category":"G\u00fcterbef\u00f6rderung im Strassenverkehr",
    "sg:phone":"+41 22 320 77 07",
    "sg:postcode":"1200",
    "sg:province":"Gen\u00e8ve",
    "wof:name":"Bornand Michel.",
    "wof:placetype":"venue"
},
  "geometry": {"coordinates":[6.1399297714,46.2038192749],"type":"Point"}
}