{
  "type": "Feature",
  "properties": {
    "iso:country":"CH",
    "sg:address":"Lanzenbergstrasse 23",
    "sg:city":"Magden",
    "sg:orig_category":"Religi\u00f6se Vereinigungen",
    "sg:postcode":"4312",
    "sg:province":"Aargau",
    "wof:name":"Stalder Karl-stiftung",
    "wof:placetype":"venue"
},
  "geometry": {"coordinates":[7.816160202,47.529586792],"type":"Point"}
}