{
  "type": "Feature",
  "properties": {
    "iso:country":"CH",
    "sg:address":"Bahnhofstrasse 14",
    "sg:city":"Chur",
    "sg:orig_category":"Herstellung von k\u00e4lte U lufttechnischen Erzeugnissen f\u00fcr gewerbliche Zwecke Installation von Heizung",
    "sg:phone":"+41 77627184",
    "sg:postcode":"7000",
    "sg:province":"Graubunden",
    "wof:name":"Christener Klima-k\u00e4lte",
    "wof:placetype":"venue"
},
  "geometry": {"coordinates":[8.5070953369,47.4804382324],"type":"Point"}
}