{
  "type": "Feature",
  "properties": {
    "iso:country":"CH",
    "sg:address":"Mutwil",
    "sg:city":"Niederb\u00fcren",
    "sg:orig_category":"Verarbeitung von Milch Verwertung von Milch",
    "sg:phone":"+41 71 422 16 30",
    "sg:postcode":"9246",
    "sg:province":"St. Gallen",
    "wof:name":"Ledergerber Marcel.",
    "wof:placetype":"venue"
},
  "geometry": {"coordinates":[9.2181978226,47.4546699524],"type":"Point"}
}