{
  "type": "Feature",
  "properties": {
    "iso:country":"CH",
    "sg:address":"Mousquines Avenue Des 16 1005 Lausanne. Postfach",
    "sg:city":"Lausanne",
    "sg:orig_category":"Beherbergungsgewerbe",
    "sg:postcode":"1003",
    "sg:province":"Vaud",
    "wof:name":"Sporthotel Grischa, G. Kuhn",
    "wof:placetype":"venue"
},
  "geometry": {"coordinates":[9.764172,46.428764],"type":"Point"}
}