{
  "type": "Feature",
  "properties": {
    "iso:country":"CH",
    "sg:address":"Hollenweg 10",
    "sg:city":"Lampenberg",
    "sg:orig_category":"Physiotherapie",
    "sg:phone":"+41 61 951 19 14",
    "sg:postcode":"4432",
    "sg:province":"Basel-Landschaft",
    "wof:name":"Doris Grossmann Physiotherapie",
    "wof:placetype":"venue"
},
  "geometry": {"coordinates":[7.7597851753,47.4248886108],"type":"Point"}
}