{
  "type": "Feature",
  "properties": {
    "iso:country":"CH",
    "sg:address":"Balzenhofweg 20",
    "sg:city":"Buchrain",
    "sg:orig_category":"Wirtschaftspr\u00fcfung, Steuerberatung U Treuhand",
    "sg:postcode":"6033",
    "sg:province":"Luzern",
    "wof:name":"Piacevole Gmbh",
    "wof:placetype":"venue"
},
  "geometry": {"coordinates":[8.351184845,47.0950241089],"type":"Point"}
}