{
  "type": "Feature",
  "properties": {
    "iso:country":"CH",
    "sg:address":"Glockengasse 9",
    "sg:city":"Z\u00fcrich",
    "sg:orig_category":"Unclassifiable Establishments",
    "sg:phone":"+41 16322317",
    "sg:postcode":"8000",
    "sg:province":"Z\u00fcrich",
    "wof:name":"Ion Marieni Enea Agentur F. Kommunikation, Werbung",
    "wof:placetype":"venue"
},
  "geometry": {"coordinates":[8.5401659012,47.3719711304],"type":"Point"}
}