{
  "type": "Feature",
  "properties": {
    "iso:country":"CH",
    "sg:address":"Bernstrasse 20b",
    "sg:city":"R\u00fcmligen",
    "sg:orig_category":"Instandhaltung U Reparatur von Automobilen",
    "sg:phone":"+41 19291600",
    "sg:postcode":"3128",
    "sg:province":"Bern",
    "wof:name":"Bruno Sperandio Garage",
    "wof:placetype":"venue"
},
  "geometry": {"coordinates":[8.7195224762,47.2763404846],"type":"Point"}
}