{
  "type": "Feature",
  "properties": {
    "iso:country":"CH",
    "sg:address":"Bahnhofstrasse 8",
    "sg:city":"Zug",
    "sg:orig_category":"Sonstige pers\u00f6nliche Dienstleistungen",
    "sg:phone":"+41 41 710 52 52",
    "sg:postcode":"6300",
    "sg:province":"Zug",
    "wof:name":"Repsol Inco Ag",
    "wof:placetype":"venue"
},
  "geometry": {"coordinates":[8.515917778,47.1685752869],"type":"Point"}
}