{
  "type": "Feature",
  "properties": {
    "iso:country":"CH",
    "sg:address":"Stumpenweg 2",
    "sg:city":"W\u00fcrenlingen",
    "sg:orig_category":"Softwareentwicklung U beratung",
    "sg:phone":"+41 56 281 37 00",
    "sg:postcode":"5303",
    "sg:province":"Aargau",
    "wof:name":"Zos, Zero One Soluffons Gmbh",
    "wof:placetype":"venue"
},
  "geometry": {"coordinates":[8.2655677795,47.5297546387],"type":"Point"}
}