{
  "type": "Feature",
  "properties": {
    "addr:full":"Z\u00fcrcherstrasse 104 Neuenhof Aargau 5432",
    "addr:housenumber":"104",
    "addr:postcode":"5432",
    "addr:street":"Zuercherstrasse",
    "iso:country":"CH",
    "sg:address":"Z\u00fcrcherstrasse 104",
    "sg:city":"Neuenhof",
    "sg:orig_category":"Autogaragen Tankstellen",
    "sg:phone":"+41 56 406 63 93",
    "sg:postcode":"5432",
    "sg:province":"Aargau",
    "wof:name":"Notter & Co Autogarage & Tankstelle",
    "wof:placetype":"venue"
},
  "geometry": {"coordinates":[8.324621,47.451427],"type":"Point"}
}