{
  "type": "Feature",
  "properties": {
    "iso:country":"CH",
    "sg:address":"Route De Pr\u00e9vessin 30",
    "sg:city":"Meyrin",
    "sg:orig_category":"Gem\u00fcsebau",
    "sg:phone":"+41 26 673 11 22",
    "sg:postcode":"1217",
    "sg:province":"Gen\u00e8ve",
    "wof:name":"Michel Biolley Maraicher",
    "wof:placetype":"venue"
},
  "geometry": {"coordinates":[7.1029229164,46.9554214478],"type":"Point"}
}