{
  "type": "Feature",
  "properties": {
    "iso:country":"CH",
    "sg:address":"Rue Du Pont-levis 11",
    "sg:city":"St-prex",
    "sg:orig_category":"RESTAURANTS: TEA-ROOMS",
    "sg:phone":"+41 21 806 42 87",
    "sg:postcode":"1162",
    "sg:province":"Vaud",
    "wof:name":"Margreth Gabriel",
    "wof:placetype":"venue"
},
  "geometry": {"coordinates":[6.4584889412,46.4797592163],"type":"Point"}
}