{
  "type": "Feature",
  "properties": {
    "iso:country":"CH",
    "sg:address":"Luzernerring 136",
    "sg:city":"Basel",
    "sg:orig_category":"Instandhaltung U Reparatur von Automobilen",
    "sg:phone":"+41 81 413 53 23",
    "sg:postcode":"4056",
    "sg:province":"Basel-Stadt",
    "wof:name":"Luzi Casutt Autospenglerei",
    "wof:placetype":"venue"
},
  "geometry": {"coordinates":[9.8272304535,46.793598175],"type":"Point"}
}