{
  "type": "Feature",
  "properties": {
    "iso:country":"CH",
    "sg:address":"Wasserwerkgassse 5",
    "sg:city":"Bern",
    "sg:orig_category":"Unclassifiable Establishments",
    "sg:postcode":"3011",
    "sg:province":"Bern",
    "wof:name":"Balsi Lefthanded Grafics Christoph Balsiger",
    "wof:placetype":"venue"
},
  "geometry": {"coordinates":[7.4574670792,46.9468955994],"type":"Point"}
}