{
  "type": "Feature",
  "properties": {
    "iso:country":"CH",
    "sg:address":"Chemin Des Blanchards 6",
    "sg:city":"Evilard",
    "sg:orig_category":"Arztpraxen",
    "sg:phone":"+41 32 322 77 53",
    "sg:postcode":"2533",
    "sg:province":"Bern",
    "wof:name":"Dr M\u00e9d. Hans-peter Richard M\u00e9decin G\u00e9n\u00e9raliste Fmh",
    "wof:placetype":"venue"
},
  "geometry": {"coordinates":[7.234141,47.14867],"type":"Point"}
}