{
  "type": "Feature",
  "properties": {
    "addr:full":"Gemeindehaus Widen Aargau 8967",
    "addr:postcode":"8967",
    "iso:country":"CH",
    "sg:address":"Gemeindehaus",
    "sg:city":"Widen",
    "sg:orig_category":"Bau\u00e4mter",
    "sg:phone":"+41 56 631 12 30",
    "sg:postcode":"8967",
    "sg:province":"Aargau",
    "wof:name":"Bauverwaltung Der Gemeinde Widen",
    "wof:placetype":"venue"
},
  "geometry": {"coordinates":[8.359476,47.366718],"type":"Point"}
}