{
  "type": "Feature",
  "properties": {
    "iso:country":"CH",
    "sg:address":"Kronengasse 6362 Stansstad. Postfach",
    "sg:city":"Stansstad",
    "sg:orig_category":"Non-Classified Establishments",
    "sg:postcode":"6362",
    "sg:province":"Nidwalden",
    "wof:name":"Degli Amici Gmbh",
    "wof:placetype":"venue"
},
  "geometry": {"coordinates":[8.3380069733,46.9796142578],"type":"Point"}
}