{
  "type": "Feature",
  "properties": {
    "iso:country":"CH",
    "sg:address":"Schaffhauserstrasse 79",
    "sg:city":"Winterthur",
    "sg:orig_category":"Arztpraxen",
    "sg:phone":"+41 52 212 05 00",
    "sg:postcode":"8400",
    "sg:province":"Z\u00fcrich",
    "wof:name":"Dr.med.j\u00fcrg Diener Spezialarzt Fmh",
    "wof:placetype":"venue"
},
  "geometry": {"coordinates":[8.72244,47.509754],"type":"Point"}
}