{
  "type": "Feature",
  "properties": {
    "iso:country":"CH",
    "sg:address":"Kirchstrasse 9",
    "sg:city":"Naters",
    "sg:orig_category":"Detailhandel mit Schuhen Reparatur von Schuhen U Lederwaren",
    "sg:phone":"+41 27 923 72 45",
    "sg:postcode":"3904",
    "sg:province":"Valais",
    "wof:name":"Leander Salzmann Schuhmacher & Schuhwaren",
    "wof:placetype":"venue"
},
  "geometry": {"coordinates":[7.9875998497,46.3258285522],"type":"Point"}
}