{
  "type": "Feature",
  "properties": {
    "iso:country":"CH",
    "sg:address":"Lorzenmattstrasse 2",
    "sg:city":"Baar",
    "sg:orig_category":"Wirtschaftsverb\u00e4nde Industrie, Handel and Gewerbe",
    "sg:phone":"+41 41 761 98 24",
    "sg:postcode":"6340",
    "sg:province":"Zug",
    "wof:name":"Baumeisterverband Zug & Umgeb.",
    "wof:placetype":"venue"
},
  "geometry": {"coordinates":[8.5337133408,47.2002372742],"type":"Point"}
}