{
  "type": "Feature",
  "properties": {
    "iso:country":"CH",
    "sg:address":"Ebnetstrasse 5 9545 W\u00e4ngi. Postfach",
    "sg:city":"W\u00e4ngi",
    "sg:orig_category":"Gesundheitswesen",
    "sg:postcode":"9545",
    "sg:province":"Thurgau",
    "wof:name":"Trisana Ag",
    "wof:placetype":"venue"
},
  "geometry": {"coordinates":[8.947262764,47.4963188171],"type":"Point"}
}