{
  "type": "Feature",
  "properties": {
    "iso:country":"CH",
    "sg:address":"Feldstrasse 11 5430 Wettingen. Postfach",
    "sg:city":"Wettingen",
    "sg:orig_category":"Erbringung von Dienstleistungen f\u00fcr Unternehmen Herstellung von Phantasieschmuck",
    "sg:phone":"+41 56 427 49 69",
    "sg:postcode":"5430",
    "sg:province":"Aargau",
    "wof:name":"Artikel F\u00fcr K\u00f6rper Und Raum Fry, Girod, Lenzhofer Wohn- U. Schmuckaccessoires; Entwicklung, Produktion, Vertrieb",
    "wof:placetype":"venue"
},
  "geometry": {"coordinates":[8.3152713776,47.4670257568],"type":"Point"}
}