{
  "type": "Feature",
  "properties": {
    "iso:country":"CH",
    "sg:address":"Hauptstrasse 7a",
    "sg:city":"Mitl\u00f6di",
    "sg:orig_category":"G\u00fcterbef\u00f6rderung im Strassenverkehr Lagerung",
    "sg:phone":"+41 55 644 12 07",
    "sg:postcode":"8756",
    "sg:province":"Glarus",
    "wof:name":"Jakob Kundert Jun. M\u00f6beltransporte-umz\u00fcge",
    "wof:placetype":"venue"
},
  "geometry": {"coordinates":[9.0788564682,47.0091171265],"type":"Point"}
}