{
  "type": "Feature",
  "properties": {
    "iso:country":"CH",
    "sg:address":"1426",
    "sg:city":"Corcelles-concise",
    "sg:orig_category":"RESTAURANTS: TEA-ROOMS",
    "sg:phone":"+41 79 364 92 05",
    "sg:postcode":"1426",
    "sg:province":"Vaud",
    "wof:name":"Arnoux Antonietta",
    "wof:placetype":"venue"
},
  "geometry": {"coordinates":[6.7186899185,46.8510704041],"type":"Point"}
}