{
  "type": "Feature",
  "properties": {
    "iso:country":"CH",
    "sg:address":"Waffenplatzstrasse 87",
    "sg:city":"Z\u00fcrich",
    "sg:orig_category":"Grosshandel mit elektrischen Haushaltsger\u00e4ten Herstellung von elektrischen Lampen U Leuchten",
    "sg:phone":"+41 12016651",
    "sg:postcode":"8002",
    "sg:province":"Z\u00fcrich",
    "wof:name":"Orlux Amiache Gmbh",
    "wof:placetype":"venue"
},
  "geometry": {"coordinates":[8.5271100998,47.3564682007],"type":"Point"}
}