{
  "type": "Feature",
  "properties": {
    "iso:country":"CH",
    "sg:address":"Hauptstrasse 183",
    "sg:city":"Zuzgen",
    "sg:orig_category":"Detailhandel mit Waren verschiedener Art, Hauptrichtung Nahrungsmittel Grosshandel mit Nahrungsmitte",
    "sg:phone":"+41 61 871 04 30",
    "sg:postcode":"4315",
    "sg:province":"Aargau",
    "wof:name":"A. Brogli Ag",
    "wof:placetype":"venue"
},
  "geometry": {"coordinates":[7.9016661644,47.5244255066],"type":"Point"}
}