{
  "type": "Feature",
  "properties": {
    "iso:country":"CH",
    "sg:address":"Troxlerweg 10",
    "sg:city":"Aarau",
    "sg:orig_category":"Herstellung von Bier",
    "sg:phone":"+41 62 822 50 08",
    "sg:postcode":"5000",
    "sg:province":"Aargau",
    "wof:name":"Brauerei Karbacher Ag Filiale Aarau",
    "wof:placetype":"venue"
},
  "geometry": {"coordinates":[8.0427646637,47.3967285156],"type":"Point"}
}