{
  "type": "Feature",
  "properties": {
    "iso:country":"CH",
    "sg:address":"Boulevard De P\u00e9rolles 12",
    "sg:city":"Fribourg",
    "sg:orig_category":"Unternehmensberatung",
    "sg:postcode":"1700",
    "sg:province":"Fribourg",
    "wof:name":"J.j. Nigg Consulting",
    "wof:placetype":"venue"
},
  "geometry": {"coordinates":[8.4391508102,47.0705223083],"type":"Point"}
}