{
  "type": "Feature",
  "properties": {
    "iso:country":"CH",
    "sg:address":"Am Kirchplatz 6130 Willisau. Postfach 3151",
    "sg:city":"Willisau",
    "sg:orig_category":"Grosshandel mit Eisenwaren sowie Installationsbedarf f\u00fcr Gas, Wasser U Heizung Sonstiger Grosshandel",
    "sg:phone":"+41 19153361",
    "sg:postcode":"6130",
    "sg:province":"Luzern",
    "wof:name":"Airtool Ag",
    "wof:placetype":"venue"
},
  "geometry": {"coordinates":[8.5984859467,47.2972259521],"type":"Point"}
}