{
  "type": "Feature",
  "properties": {
    "iso:country":"CH",
    "sg:address":"Gerberngasse 2",
    "sg:city":"Solothurn",
    "sg:orig_category":"Non-Classified Establishments",
    "sg:phone":"+41 32 622 33 32",
    "sg:postcode":"4500",
    "sg:province":"Solothurn",
    "wof:name":"Restaurant Cube In Gmbh",
    "wof:placetype":"venue"
},
  "geometry": {"coordinates":[7.5356650352,47.2061309814],"type":"Point"}
}