{
  "type": "Feature",
  "properties": {
    "iso:country":"CH",
    "sg:address":"Fuchsweidstrasse 15",
    "sg:city":"Widen",
    "sg:orig_category":"Finanzierungsinstitutionen",
    "sg:phone":"+41 56 631 13 93",
    "sg:postcode":"8967",
    "sg:province":"Aargau",
    "wof:name":"Payer Wilhelm, Finanz Und Wirtschaftsberatung",
    "wof:placetype":"venue"
},
  "geometry": {"coordinates":[8.3562965393,47.363193512],"type":"Point"}
}