{
  "type": "Feature",
  "properties": {
    "iso:country":"CH",
    "sg:address":"Gewerbestrasse 9b",
    "sg:city":"Unter\u00e4geri",
    "sg:orig_category":"Non-Classified Establishments",
    "sg:postcode":"6314",
    "sg:province":"Zug",
    "wof:name":"Titanic-film K\u00fchn B. & C. Und Blickle R.",
    "wof:placetype":"venue"
},
  "geometry": {"coordinates":[8.5739250183,47.1342964172],"type":"Point"}
}