{
  "type": "Feature",
  "properties": {
    "iso:country":"CH",
    "sg:address":"8352 R\u00e4terschen. Postfach 66",
    "sg:city":"R\u00e4terschen",
    "sg:orig_category":"Sportvereine Ballsport Fussball",
    "sg:phone":"+41 52 222 54 83",
    "sg:postcode":"8352",
    "sg:province":"Z\u00fcrich",
    "wof:name":"Fc R\u00e4terschen",
    "wof:placetype":"venue"
},
  "geometry": {"coordinates":[8.7931995392,47.4988098145],"type":"Point"}
}