{
  "type": "Feature",
  "properties": {
    "iso:country":"CH",
    "sg:address":"Forchstrasse 113",
    "sg:city":"Forch",
    "sg:classifiers":[
        {
            "category":"Restaurant",
            "type":"Food & Drink"
        }
    ],
    "sg:phone":"+41 19802070",
    "sg:postcode":"8127",
    "sg:province":"Z\u00fcrich",
    "wof:name":"Restaurant Sch\u00fcrli",
    "wof:placetype":"venue"
},
  "geometry": {"coordinates":[8.6500453949,47.3248100281],"type":"Point"}
}