{
  "type": "Feature",
  "properties": {
    "iso:country":"CH",
    "sg:address":"Dorfstrasse 28",
    "sg:city":"Zollbr\u00fcck",
    "sg:orig_category":"Detailhandel mit elektrischen Haushaltsger\u00e4ten",
    "sg:phone":"+41 34 496 84 89",
    "sg:postcode":"3436",
    "sg:province":"Bern",
    "wof:name":"Fritz Frieden Bernina N\u00e4hmaschinen",
    "wof:placetype":"venue"
},
  "geometry": {"coordinates":[7.7427711487,46.9756278992],"type":"Point"}
}