{
  "type": "Feature",
  "properties": {
    "iso:country":"CH",
    "sg:address":"Florastrasse 42",
    "sg:city":"Uster",
    "sg:orig_category":"Massagestudios",
    "sg:phone":"+41 19405929",
    "sg:postcode":"8610",
    "sg:province":"Z\u00fcrich",
    "wof:name":"Susan Balmer Akupunktur-massage",
    "wof:placetype":"venue"
},
  "geometry": {"coordinates":[8.7256355286,47.3461036682],"type":"Point"}
}