{
  "type": "Feature",
  "properties": {
    "iso:country":"CH",
    "sg:address":"Gen\u00e8ve Rue De 84",
    "sg:city":"Lausanne",
    "sg:orig_category":"Grosshandel mit sonstigen Gebrauchs U Verbrauchsg\u00fctern",
    "sg:phone":"+41 21 626 07 00",
    "sg:postcode":"1004",
    "sg:province":"Vaud",
    "wof:name":"Saphir Product Sa, Succursale De Lausanne",
    "wof:placetype":"venue"
},
  "geometry": {"coordinates":[6.614648819,46.5248641968],"type":"Point"}
}