{
  "type": "Feature",
  "properties": {
    "iso:country":"CH",
    "sg:address":"Industrie Avenue De L'",
    "sg:city":"Monthey",
    "sg:orig_category":"Herstellung von Schl\u00f6ssern U Beschl\u00e4gen",
    "sg:phone":"+41 24 472 28 00",
    "sg:postcode":"1870",
    "sg:province":"Valais",
    "wof:name":"Val-tube Sa",
    "wof:placetype":"venue"
},
  "geometry": {"coordinates":[6.9495830536,46.2520637512],"type":"Point"}
}