{
  "type": "Feature",
  "properties": {
    "iso:country":"CH",
    "sg:address":"Erlenstrasse 2",
    "sg:city":"Kreuzlingen",
    "sg:orig_category":"Interessenvertretungen U sonstige Vereinigungen",
    "sg:phone":"+41 71 677 96 51",
    "sg:postcode":"8280",
    "sg:province":"Thurgau",
    "wof:name":"Vsss Verband Schweizerischer Segelschulen",
    "wof:placetype":"venue"
},
  "geometry": {"coordinates":[9.1635761261,47.6404571533],"type":"Point"}
}