{
  "type": "Feature",
  "properties": {
    "addr:full":"Flughofstrasse 35 Glattbrugg Z\u00fcrich 8152",
    "addr:housenumber":"35",
    "addr:postcode":"8152",
    "addr:street":"Flughofstrasse",
    "iso:country":"CH",
    "sg:address":"Flughofstrasse 35",
    "sg:city":"Glattbrugg",
    "sg:classifiers":[
        {
            "category":"Banks & Credit Unions",
            "subcategory":"Bank",
            "type":"Services"
        }
    ],
    "sg:phone":"+41 18283111",
    "sg:postcode":"8152",
    "sg:province":"Z\u00fcrich",
    "wof:name":"Ubs Card Center Ag",
    "wof:placetype":"venue"
},
  "geometry": {"coordinates":[8.561389,47.437443],"type":"Point"}
}