{
  "type": "Feature",
  "properties": {
    "iso:country":"CH",
    "sg:address":"Rabengasse 18 8704 Herrliberg. Postfach",
    "sg:city":"Herrliberg",
    "sg:orig_category":"Architektur U Ingenieurb\u00fcros Architekturb\u00fcros",
    "sg:phone":"+41 79 212 34 72",
    "sg:postcode":"8704",
    "sg:province":"Z\u00fcrich",
    "wof:name":"Kuenzy D. Sa",
    "wof:placetype":"venue"
},
  "geometry": {"coordinates":[6.903338,46.982922],"type":"Point"}
}