{
  "type": "Feature",
  "properties": {
    "iso:country":"CH",
    "sg:address":"Technikumstrasse 12 8400 Winterthur. Postfach",
    "sg:city":"Winterthur",
    "sg:orig_category":"Politische Parteien FDP",
    "sg:phone":"+41 52 212 84 43",
    "sg:postcode":"8402",
    "sg:province":"Z\u00fcrich",
    "wof:name":"Fdp Winterthur",
    "wof:placetype":"venue"
},
  "geometry": {"coordinates":[8.7304840088,47.4980049133],"type":"Point"}
}