{
  "type": "Feature",
  "properties": {
    "iso:country":"CH",
    "sg:address":"Amalervenstrasse 9467 Fr\u00fcmsen. Postfach",
    "sg:city":"Fr\u00fcmsen",
    "sg:orig_category":"Unternehmensberatung",
    "sg:phone":"+41 81 757 19 39",
    "sg:postcode":"9467",
    "sg:province":"St. Gallen",
    "wof:name":"Gotthardt Consulting Ag",
    "wof:placetype":"venue"
},
  "geometry": {"coordinates":[9.4734773636,47.245136261],"type":"Point"}
}