{
  "type": "Feature",
  "properties": {
    "iso:country":"CH",
    "sg:address":"Saint-fran\u00e7ois Place 1",
    "sg:city":"Lausanne",
    "sg:orig_category":"Non-Classified Establishments",
    "sg:phone":"+41 32 968 67 01",
    "sg:postcode":"1003",
    "sg:province":"Vaud",
    "wof:name":"Si Place Neuve No 8 Sa",
    "wof:placetype":"venue"
},
  "geometry": {"coordinates":[6.8308000565,47.1039848328],"type":"Point"}
}