{
  "type": "Feature",
  "properties": {
    "addr:full":"Igelweid 5 Aarau Aargau 5000",
    "addr:housenumber":"5",
    "addr:postcode":"5000",
    "addr:street":"Igelweid",
    "iso:country":"CH",
    "sg:address":"Igelweid 5",
    "sg:city":"Aarau",
    "sg:orig_category":"Advokaturb\u00fcros Notariate",
    "sg:phone":"+41 62 824 85 65",
    "sg:postcode":"5000",
    "sg:province":"Aargau",
    "wof:name":"Buttliger & Winkler",
    "wof:placetype":"venue"
},
  "geometry": {"coordinates":[8.046044,47.391972],"type":"Point"}
}