{
  "type": "Feature",
  "properties": {
    "iso:country":"CH",
    "sg:address":"1243",
    "sg:city":"Presinge",
    "sg:orig_category":"Schulpflegen",
    "sg:phone":"+41 22 759 12 14",
    "sg:postcode":"1243",
    "sg:province":"Gen\u00e8ve",
    "wof:name":"Commission Scolaire De L'ecole Primaire",
    "wof:placetype":"venue"
},
  "geometry": {"coordinates":[6.2626700401,46.2158584595],"type":"Point"}
}