{
  "type": "Feature",
  "properties": {
    "iso:country":"CH",
    "sg:address":"H\u00f6fnerstr. 96",
    "sg:city":"Unter\u00e4geri",
    "sg:classifiers":[
        {
            "category":"Transit Center",
            "subcategory":"Freight",
            "type":"Transportation"
        }
    ],
    "sg:phone":"+41 41 754 50 40",
    "sg:postcode":"6314",
    "sg:province":"Zug",
    "sg:tags":[
        "metallurgy",
        "pipe",
        "metalworking",
        "sheet"
    ],
    "wof:name":"C Schweiger Ag",
    "wof:placetype":"venue"
},
  "geometry": {"coordinates":[8.579372406,47.1285705566],"type":"Point"}
}