{
  "type": "Feature",
  "properties": {
    "iso:country":"CH",
    "sg:address":"Via Canova",
    "sg:city":"Genestrerio",
    "sg:classifiers":[
        {
            "category":"Restaurant",
            "type":"Food & Drink"
        }
    ],
    "sg:phone":"+41 91 872 16 56",
    "sg:postcode":"6852",
    "sg:province":"Ticino",
    "wof:name":"Osteria Dello Sciatore",
    "wof:placetype":"venue"
},
  "geometry": {"coordinates":[8.9422903061,46.569644928],"type":"Point"}
}