{
  "type": "Feature",
  "properties": {
    "iso:country":"CH",
    "sg:address":"Spiegelgasse 2",
    "sg:city":"Basel",
    "sg:orig_category":"Pensionskassen",
    "sg:postcode":"4051",
    "sg:province":"Basel-Stadt",
    "wof:name":"Paul Scherrer Fonds",
    "wof:placetype":"venue"
},
  "geometry": {"coordinates":[7.586977005,47.5605316162],"type":"Point"}
}