{
  "type": "Feature",
  "properties": {
    "iso:country":"CH",
    "sg:address":"Stockenstrasse 7",
    "sg:city":"Ebnat",
    "sg:orig_category":"Druck ohne Zeitungsdruck",
    "sg:postcode":"9642",
    "sg:province":"St. Gallen",
    "wof:name":"Berben-grafik Benzoni",
    "wof:placetype":"venue"
},
  "geometry": {"coordinates":[9.129275322,47.2607040405],"type":"Point"}
}