{
  "type": "Feature",
  "properties": {
    "iso:country":"CH",
    "sg:address":"Grand-rue 32",
    "sg:city":"Tavannes",
    "sg:orig_category":"Sonstiger Grosshandel Warenh\u00e4user",
    "sg:phone":"+41 22 361 13 51",
    "sg:postcode":"2710",
    "sg:province":"Bern",
    "wof:name":"Manor",
    "wof:placetype":"venue"
},
  "geometry": {"coordinates":[6.2366700172,46.3832893372],"type":"Point"}
}