{
  "type": "Feature",
  "properties": {
    "iso:country":"CH",
    "sg:address":"Im Abt 10",
    "sg:city":"Thayngen",
    "sg:orig_category":"Organisationen des Gesundheitswesen",
    "sg:phone":"+41 52 649 26 78",
    "sg:postcode":"8240",
    "sg:province":"Schaffhausen",
    "wof:name":"Samariterverein Thayngen",
    "wof:placetype":"venue"
},
  "geometry": {"coordinates":[8.7215585709,47.7472991943],"type":"Point"}
}