{
  "type": "Feature",
  "properties": {
    "iso:country":"CH",
    "sg:address":"Vignerons Rue Des 27",
    "sg:city":"V\u00e9troz",
    "sg:orig_category":"Unclassifiable Establishments",
    "sg:postcode":"1963",
    "sg:province":"Valais",
    "wof:name":"Night Flower S\u00e0rl",
    "wof:placetype":"venue"
},
  "geometry": {"coordinates":[7.2878518105,46.2273597717],"type":"Point"}
}