{
  "type": "Feature",
  "properties": {
    "iso:country":"CH",
    "sg:address":"Chamerstrasse 50",
    "sg:city":"Zug",
    "sg:orig_category":"Unternehmensberatung",
    "sg:phone":"+41 41 710 58 40",
    "sg:postcode":"6300",
    "sg:province":"Zug",
    "wof:name":"Rensch Beratungen",
    "wof:placetype":"venue"
},
  "geometry": {"coordinates":[8.5057764053,47.1738319397],"type":"Point"}
}