{
  "type": "Feature",
  "properties": {
    "iso:country":"CH",
    "sg:address":"Dorfstrasse 34",
    "sg:city":"Bettlach",
    "sg:orig_category":"Detailhandel mit Brot, Back U S\u00fcsswaren",
    "sg:phone":"+41 32 645 19 60",
    "sg:postcode":"2544",
    "sg:province":"Solothurn",
    "wof:name":"Hansj\u00f6rg Habegger B\u00e4ckerei-konditorei",
    "wof:placetype":"venue"
},
  "geometry": {"coordinates":[7.42483,47.20195],"type":"Point"}
}