{
  "type": "Feature",
  "properties": {
    "iso:country":"CH",
    "sg:address":"Br\u00fcnigstrasse 87",
    "sg:city":"Sachseln",
    "sg:orig_category":"Hobel U Holzimpr\u00e4gnierwerke",
    "sg:phone":"+41 41 917 21 57",
    "sg:postcode":"6072",
    "sg:province":"Obwalden",
    "wof:name":"Julius Roos Bau-& M\u00f6belbeizerei",
    "wof:placetype":"venue"
},
  "geometry": {"coordinates":[8.2396364212,47.2609100342],"type":"Point"}
}