{
  "type": "Feature",
  "properties": {
    "iso:country":"CH",
    "sg:address":"Br\u00fchlstrasse 21 5304 Endingen. Postfach",
    "sg:city":"Endingen",
    "sg:orig_category":"Herstellung von Sitzm\u00f6beln",
    "sg:phone":"+41 56 281 24 74",
    "sg:postcode":"5304",
    "sg:province":"Aargau",
    "wof:name":"J. Kalt Ag M\u00f6belfabrikation",
    "wof:placetype":"venue"
},
  "geometry": {"coordinates":[8.2441701889,47.5217819214],"type":"Point"}
}