{
  "type": "Feature",
  "properties": {
    "iso:country":"CH",
    "sg:address":"S\u00e4ntisstrasse 4 Ebmatingen 8124 Maur. Postfach",
    "sg:city":"Ebmatingen",
    "sg:orig_category":"Kauf U Verkauf von Immobilien auf eigene Rechnung",
    "sg:postcode":"8123",
    "sg:province":"Z\u00fcrich",
    "wof:name":"Casacarina Ag",
    "wof:placetype":"venue"
},
  "geometry": {"coordinates":[8.6676130295,47.3403167725],"type":"Point"}
}