{
  "type": "Feature",
  "properties": {
    "iso:country":"CH",
    "sg:address":"Sott'c\u00e0 11",
    "sg:city":"Montagnola",
    "sg:orig_category":"Interessenvertretungen",
    "sg:phone":"+41 91 994 71 47",
    "sg:postcode":"6926",
    "sg:province":"Ticino",
    "wof:name":"Fondazione Unit\u00e0 Di Ogni Vita",
    "wof:placetype":"venue"
},
  "geometry": {"coordinates":[8.8742218018,44.4913215637],"type":"Point"}
}