{
  "type": "Feature",
  "properties": {
    "iso:country":"CH",
    "sg:address":"Manoir Rue Du 5bis",
    "sg:city":"Pully",
    "sg:orig_category":"Erbringung von Dienstleistungen f\u00fcr Unternehmen",
    "sg:phone":"+41 21 617 31 34",
    "sg:postcode":"1009",
    "sg:province":"Vaud",
    "wof:name":"Dominodesign S\u00e0rl",
    "wof:placetype":"venue"
},
  "geometry": {"coordinates":[6.6452798843,46.5074119568],"type":"Point"}
}