{
  "type": "Feature",
  "properties": {
    "iso:country":"CH",
    "sg:address":"Urdorferstrasse 19 8953 Dietikon. Postfach",
    "sg:city":"Dietikon",
    "sg:orig_category":"Einzelhandel mit Automobilen Handel mit Automobilen",
    "sg:phone":"+41 17420776",
    "sg:postcode":"8953",
    "sg:province":"Z\u00fcrich",
    "wof:name":"Houchaimi Jihad, Autohandel",
    "wof:placetype":"venue"
},
  "geometry": {"coordinates":[8.4145460129,47.3984298706],"type":"Point"}
}