{
  "type": "Feature",
  "properties": {
    "iso:country":"CH",
    "sg:address":"Eggenweg 2",
    "sg:city":"Thun",
    "sg:orig_category":"Architektur U Ingenieurb\u00fcros",
    "sg:phone":"+41 33 336 87 16",
    "sg:postcode":"3604",
    "sg:province":"Bern",
    "wof:name":"Tbs Konstruktionsb\u00fcro Gmbh",
    "wof:placetype":"venue"
},
  "geometry": {"coordinates":[7.620664,46.741547],"type":"Point"}
}