{
  "type": "Feature",
  "properties": {
    "iso:country":"CH",
    "sg:address":"Rue Mauborget 4",
    "sg:city":"Moudon",
    "sg:classifiers":[
        {
            "category":"Travel",
            "subcategory":"Hotels & Motels",
            "type":"Entertainment"
        }
    ],
    "sg:phone":"+41 21 905 11 06",
    "sg:postcode":"1510",
    "sg:province":"Vaud",
    "sg:tags":[
        "hotels",
        "mit",
        "restaurant"
    ],
    "wof:name":"H\u00f4tel Du Pont",
    "wof:placetype":"venue"
},
  "geometry": {"coordinates":[6.7968177795,46.6681632996],"type":"Point"}
}