{
  "type": "Feature",
  "properties": {
    "iso:country":"CH",
    "sg:address":"Feldm\u00fchlestrasse 18 6010 Kriens. Postfach",
    "sg:city":"Luzern",
    "sg:orig_category":"Non-Classified Establishments",
    "sg:phone":"+41 41 360 87 34",
    "sg:postcode":"6003",
    "sg:province":"Luzern",
    "wof:name":"Nebo Mvs Gmbh Marketing-dienstleistungen, Produktevertrieb, Bes. Im Bereich Autopflege Usw",
    "wof:placetype":"venue"
},
  "geometry": {"coordinates":[8.2689523697,47.0356826782],"type":"Point"}
}