{
  "type": "Feature",
  "properties": {
    "iso:country":"CH",
    "sg:address":"B\u00e4rchistrasse 4 8460 Marthalen. Postfach",
    "sg:city":"Marthalen",
    "sg:orig_category":"Detailhandel mit Metallwaren, Anstrichmitteln, Glaswaren, Bau U Heimwerkerbedarf Grosshandel mit son",
    "sg:phone":"+41 52 305 40 50",
    "sg:postcode":"8460",
    "sg:province":"Z\u00fcrich",
    "wof:name":"Bomec Ag Werkzeuge; Handel",
    "wof:placetype":"venue"
},
  "geometry": {"coordinates":[8.6598863602,47.6349372864],"type":"Point"}
}