{
  "type": "Feature",
  "properties": {
    "iso:country":"CH",
    "sg:address":"2540",
    "sg:city":"Grenchen",
    "sg:orig_category":"Vorschulen, Kinderg\u00e4rten",
    "sg:phone":"+41 32 653 01 28",
    "sg:postcode":"2540",
    "sg:province":"Solothurn",
    "wof:name":"Kindergarten Witmatt",
    "wof:placetype":"venue"
},
  "geometry": {"coordinates":[7.3994011879,47.1928863525],"type":"Point"}
}