{
  "type": "Feature",
  "properties": {
    "iso:country":"CH",
    "sg:address":"Route Plantaz",
    "sg:city":"Montagny-yverdon",
    "sg:orig_category":"Detailhandel mit Fleisch U Fleischwaren Grosshandel mit Fleisch U Fleischwaren",
    "sg:phone":"+41 24 445 38 33",
    "sg:postcode":"1442",
    "sg:province":"Vaud",
    "wof:name":"Martin Jean-daniel",
    "wof:placetype":"venue"
},
  "geometry": {"coordinates":[6.6089630127,46.7895545959],"type":"Point"}
}