{
  "type": "Feature",
  "properties": {
    "iso:country":"CH",
    "sg:address":"Seestrasse 235",
    "sg:city":"Herrliberg",
    "sg:orig_category":"Erbringung von Dienstleistungen f\u00fcr Unternehmen Werbegrafikateliers",
    "sg:phone":"+41 19154548",
    "sg:postcode":"8704",
    "sg:province":"Z\u00fcrich",
    "wof:name":"Lp Layout Production Gmbh",
    "wof:placetype":"venue"
},
  "geometry": {"coordinates":[8.6095371246,47.2842025757],"type":"Point"}
}