{
  "type": "Feature",
  "properties": {
    "iso:country":"CH",
    "sg:address":"Burgstrasse 9",
    "sg:city":"Sch\u00f6nenwerd",
    "sg:classifiers":[
        {
            "category":"Insurance",
            "subcategory":"Insurance Agent",
            "type":"Services"
        }
    ],
    "sg:phone":"+41 62 849 59 20",
    "sg:postcode":"5012",
    "sg:province":"Solothurn",
    "sg:tags":[
        "versicherungsagenturen",
        "-broker"
    ],
    "wof:name":"Rentenanstalt/swiss Life Agentur Fabrizio Cerpolloni",
    "wof:placetype":"venue"
},
  "geometry": {"coordinates":[8.0029697418,47.3704566956],"type":"Point"}
}