{
  "type": "Feature",
  "properties": {
    "iso:country":"CH",
    "sg:address":"Chamerstrasse 61",
    "sg:city":"Zug",
    "sg:orig_category":"Bauingenieurb\u00fcros Hochbau Bauingenieurb\u00fcros allgemein",
    "sg:phone":"+41 56 441 91 43",
    "sg:postcode":"6300",
    "sg:province":"Zug",
    "wof:name":"Maerki Ganz & Partner Ag Ingenieurb\u00fcro",
    "wof:placetype":"venue"
},
  "geometry": {"coordinates":[8.200164,47.474621],"type":"Point"}
}