{
  "type": "Feature",
  "properties": {
    "iso:country":"CH",
    "sg:address":"Marktstrasse 11",
    "sg:city":"Sarmenstorf",
    "sg:orig_category":"Detailhandel mit Brot, Back U S\u00fcsswaren",
    "sg:phone":"+41 62 962 10 08",
    "sg:postcode":"5614",
    "sg:province":"Aargau",
    "wof:name":"Markus & Lucia Ruckli B\u00e4ckerei-konditorei",
    "wof:placetype":"venue"
},
  "geometry": {"coordinates":[8.249497,47.309875],"type":"Point"}
}