{
  "type": "Feature",
  "properties": {
    "iso:country":"CH",
    "sg:address":"Rue De Fin-de-praz 26",
    "sg:city":"St-aubin-sauges",
    "sg:orig_category":"Sanit\u00e4rinstallation",
    "sg:phone":"+41 32 835 48 35",
    "sg:postcode":"2024",
    "sg:province":"Neuch\u00e2tel",
    "wof:name":"Alain Marti Installations Sanitaires",
    "wof:placetype":"venue"
},
  "geometry": {"coordinates":[6.7799458504,46.8968582153],"type":"Point"}
}