{
  "type": "Feature",
  "properties": {
    "iso:country":"CH",
    "sg:address":"Im Mittelleimbach 23",
    "sg:city":"Z\u00fcrich",
    "sg:orig_category":"Bauschreinerei Innenausbau",
    "sg:phone":"+41 14825810",
    "sg:postcode":"8041",
    "sg:province":"Z\u00fcrich",
    "wof:name":"Hans Gsch\u00e4ll Schreinerei Innenausbau",
    "wof:placetype":"venue"
},
  "geometry": {"coordinates":[8.514931,47.324081],"type":"Point"}
}