{
  "type": "Feature",
  "properties": {
    "iso:country":"CH",
    "sg:address":"Aoste Rue D' 4 1204 Gen\u00e8ve Case Postale",
    "sg:city":"Gen\u00e8ve",
    "sg:orig_category":"Wirtschaftspr\u00fcfung, Steuerberatung U Treuhand",
    "sg:phone":"+41 22 311 93 93",
    "sg:postcode":"1204",
    "sg:province":"Gen\u00e8ve",
    "wof:name":"Mandogest, Gestion Fiduciaire Sa",
    "wof:placetype":"venue"
},
  "geometry": {"coordinates":[7.3148818016,45.7403640747],"type":"Point"}
}