{
  "type": "Feature",
  "properties": {
    "iso:country":"CH",
    "sg:address":"Rue Charles-bonnet 2",
    "sg:city":"Gen\u00e8ve",
    "sg:orig_category":"Herstellung anderer Uhrenbestandteile Herstellung der Ausstattung von Uhren",
    "sg:phone":"+41 32 344 65 65",
    "sg:postcode":"1201",
    "sg:province":"Gen\u00e8ve",
    "wof:name":"Aiguilla Sa Aiguilles De Montres, De Pendules, De Compteurs Etc; Fabr, Commerce",
    "wof:placetype":"venue"
},
  "geometry": {"coordinates":[7.2572541237,47.1484565735],"type":"Point"}
}