{
  "type": "Feature",
  "properties": {
    "iso:country":"CH",
    "sg:address":"Hauptstrasse 42",
    "sg:city":"Weite",
    "sg:orig_category":"Verarbeitung von Milch Verwertung von Milch",
    "sg:phone":"+41 81 783 16 63",
    "sg:postcode":"9476",
    "sg:province":"St. Gallen",
    "wof:name":"Milchgenossenschaft Weite & Umgebung Milchzentrale",
    "wof:placetype":"venue"
},
  "geometry": {"coordinates":[9.4972553253,47.0925712585],"type":"Point"}
}