{
  "type": "Feature",
  "properties": {
    "iso:country":"CH",
    "sg:address":"Greifengasse 23 4058 Basel. Postfach",
    "sg:city":"Basel",
    "sg:orig_category":"Sonstige Institutionen des Sozialwesens ohne Beherbergung",
    "sg:phone":"+41 61 261 64 70",
    "sg:postcode":"4005",
    "sg:province":"Basel-Stadt",
    "wof:name":"Familien-& Erziehungsberatung",
    "wof:placetype":"venue"
},
  "geometry": {"coordinates":[7.5923848152,47.5611114502],"type":"Point"}
}