{
  "type": "Feature",
  "properties": {
    "iso:country":"CH",
    "sg:address":"Bahnhofstrasse 12",
    "sg:city":"Biel",
    "sg:classifiers":[
        {
            "category":"Banks & Credit Unions",
            "subcategory":"Bank",
            "type":"Services"
        }
    ],
    "sg:phone":"+41 32221162",
    "sg:postcode":"2502",
    "sg:province":"Bern",
    "wof:name":"Hypotheken-b\u00fcrgschafts-, Genossenschaft In Biel",
    "wof:placetype":"venue"
},
  "geometry": {"coordinates":[7.243626,47.133205],"type":"Point"}
}