{
  "type": "Feature",
  "properties": {
    "iso:country":"CH",
    "sg:address":"3962",
    "sg:city":"Montana-vermala",
    "sg:orig_category":"Antennenbau",
    "sg:phone":"+41 27 481 35 41",
    "sg:postcode":"3962",
    "wof:name":"L'energie De Sion-r\u00e9gion Sa",
    "wof:placetype":"venue"
},
  "geometry": {"coordinates":[7.492434,46.314419],"type":"Point"}
}