{
  "type": "Feature",
  "properties": {
    "addr:full":"Hauptstr. 110 Hallau Schaffhausen 8215",
    "addr:housenumber":"110",
    "addr:postcode":"8215",
    "addr:street":"Hauptstr.",
    "iso:country":"CH",
    "sg:address":"Hauptstr. 110",
    "sg:city":"Hallau",
    "sg:classifiers":[
        {
            "category":"Banks & Credit Unions",
            "subcategory":"Bank",
            "type":"Services"
        }
    ],
    "sg:phone":"+41 52 681 44 40",
    "sg:postcode":"8215",
    "sg:province":"Schaffhausen",
    "wof:name":"Raiffeisenbank",
    "wof:placetype":"venue"
},
  "geometry": {"coordinates":[8.463766,47.697784],"type":"Point"}
}