{
  "type": "Feature",
  "properties": {
    "iso:country":"CH",
    "sg:address":"Rue De L'eglise Village",
    "sg:city":"Montana-vermala",
    "sg:orig_category":"Detailhandel mit Milcherzeugnissen U Eiern Detailhandel mit Waren verschiedener Art, Hauptrichtung N",
    "sg:phone":"+41 27 481 18 14",
    "sg:postcode":"3962",
    "wof:name":"Visavis Alimentation Filval Sa",
    "wof:placetype":"venue"
},
  "geometry": {"coordinates":[7.5104351044,46.3118782043],"type":"Point"}
}