{
  "type": "Feature",
  "properties": {
    "iso:country":"CH",
    "sg:address":"Sternenbergstrasse 59",
    "sg:city":"Bauma",
    "sg:orig_category":"Sonstige mit Sport verbundene T\u00e4tigkeiten",
    "sg:phone":"+41 52 386 31 18",
    "sg:postcode":"8494",
    "sg:province":"Z\u00fcrich",
    "wof:name":"Schwimmschule H.p. Schoeb",
    "wof:placetype":"venue"
},
  "geometry": {"coordinates":[8.8879728317,47.3708152771],"type":"Point"}
}