{
  "type": "Feature",
  "properties": {
    "iso:country":"CH",
    "sg:address":"Sinserstrasse 23",
    "sg:city":"Auw",
    "sg:orig_category":"Elektroinstallation",
    "sg:phone":"+41 56 668 23 00",
    "sg:postcode":"5644",
    "sg:province":"Aargau",
    "wof:name":"Steinemann Elektro Gmbh",
    "wof:placetype":"venue"
},
  "geometry": {"coordinates":[8.3674516678,47.2088851929],"type":"Point"}
}