{
  "type": "Feature",
  "properties": {
    "iso:country":"CH",
    "sg:address":"1588 Cudrefin Case Postale 1011",
    "sg:city":"Cudrefin",
    "sg:orig_category":"Gemeindeverwaltungen",
    "sg:phone":"+41 26 660 16 92",
    "sg:postcode":"1588",
    "sg:province":"Vaud",
    "wof:name":"Administration Communale De Cugy",
    "wof:placetype":"venue"
},
  "geometry": {"coordinates":[6.8926100731,46.8147010803],"type":"Point"}
}