{
  "type": "Feature",
  "properties": {
    "iso:country":"CH",
    "sg:address":"Fischenh\u00f6lzlistrasse 24",
    "sg:city":"Amriswil",
    "sg:orig_category":"Sportvereine Turnen Vereine Damen",
    "sg:phone":"+41 71 411 81 58",
    "sg:postcode":"8580",
    "sg:province":"Thurgau",
    "wof:name":"Frauenriege Stv Amriswil",
    "wof:placetype":"venue"
},
  "geometry": {"coordinates":[9.2983665466,47.5530929565],"type":"Point"}
}