{
  "type": "Feature",
  "properties": {
    "iso:country":"CH",
    "sg:address":"Rue Du Milieu 38",
    "sg:city":"Yverdon-les-bains",
    "sg:orig_category":"Detailhandel mit Schuhen",
    "sg:phone":"+41 24 425 57 91",
    "sg:postcode":"1400",
    "sg:province":"Vaud",
    "wof:name":"Boutique Teinture D'iode",
    "wof:placetype":"venue"
},
  "geometry": {"coordinates":[6.6381530762,46.7792205811],"type":"Point"}
}