{
  "type": "Feature",
  "properties": {
    "iso:country":"CH",
    "sg:address":"Chemin De La Fontanne 8",
    "sg:city":"Pr\u00e9verenges",
    "sg:orig_category":"Rolladen- and Storenmontage",
    "sg:postcode":"1028",
    "sg:province":"Vaud",
    "wof:name":"Carlo Pennesi-hunziker Stores, Fen\u00eatres Pvc",
    "wof:placetype":"venue"
},
  "geometry": {"coordinates":[6.5294351578,46.5203094482],"type":"Point"}
}