{
  "type": "Feature",
  "properties": {
    "iso:country":"CH",
    "sg:address":"Rue Du Clos 9",
    "sg:city":"Gen\u00e8ve",
    "sg:classifiers":[
        {
            "category":"Restaurant",
            "type":"Food & Drink"
        }
    ],
    "sg:phone":"+41 22 786 33 33",
    "sg:postcode":"1207",
    "sg:province":"Gen\u00e8ve",
    "wof:name":"Caf\u00e9-restaurant Pizza Prest'o",
    "wof:placetype":"venue"
},
  "geometry": {"coordinates":[6.1623530388,46.2057609558],"type":"Point"}
}