{
  "type": "Feature",
  "properties": {
    "iso:country":"CH",
    "sg:address":"Bernstrasse 135 3052 Zollikofen. Postfach",
    "sg:city":"Zollikofen",
    "sg:orig_category":"Regionalbanken U Sparkassen",
    "sg:phone":"+41 31 911 44 15",
    "sg:postcode":"3052",
    "sg:province":"Bern",
    "wof:name":"Valiant Bank",
    "wof:placetype":"venue"
},
  "geometry": {"coordinates":[7.4583559036,46.9961051941],"type":"Point"}
}