{
  "type": "Feature",
  "properties": {
    "iso:country":"CH",
    "sg:address":"Clos-de-l'auberge B 1077 Servion Case Postale 37",
    "sg:city":"Servion",
    "sg:orig_category":"Offsetdruck Sonstiges Textilgewerbe",
    "sg:phone":"+41 21 903 45 36",
    "sg:postcode":"1077",
    "sg:province":"Vaud",
    "wof:name":"Kustom Diffusion Impression Sur Textiles",
    "wof:placetype":"venue"
},
  "geometry": {"coordinates":[6.7826528549,46.5690956116],"type":"Point"}
}