{
  "type": "Feature",
  "properties": {
    "iso:country":"CH",
    "sg:address":"La Tuili\u00e8re",
    "sg:city":"Luins",
    "sg:orig_category":"Dienstleistungen von Beteiligungsgesellschaften",
    "sg:phone":"+41 21 824 22 27",
    "sg:postcode":"1184",
    "sg:province":"Vaud",
    "wof:name":"Inter-link Schell A.",
    "wof:placetype":"venue"
},
  "geometry": {"coordinates":[6.2726101875,46.4440612793],"type":"Point"}
}