{
  "type": "Feature",
  "properties": {
    "iso:country":"CH",
    "sg:address":"Hof 525",
    "sg:city":"Waldstatt",
    "sg:orig_category":"Herstellung von Futtermitteln f\u00fcr Nutztiere",
    "sg:phone":"+41 71 352 80 15",
    "sg:postcode":"9104",
    "sg:province":"Appenzell Ausserrhoden",
    "wof:name":"Grastrocknungsanlage Ag Waldstatt Und Umgebung",
    "wof:placetype":"venue"
},
  "geometry": {"coordinates":[9.299612999,47.3620414734],"type":"Point"}
}