{
  "type": "Feature",
  "properties": {
    "iso:country":"CH",
    "sg:address":"Oberriederns",
    "sg:city":"Riedern",
    "sg:orig_category":"Politische Parteien SVP",
    "sg:postcode":"8750",
    "sg:province":"Glarus",
    "wof:name":"Dvp/svp Sektion Glarus",
    "wof:placetype":"venue"
},
  "geometry": {"coordinates":[9.0465288162,47.0476722717],"type":"Point"}
}