{
  "type": "Feature",
  "properties": {
    "iso:country":"CH",
    "sg:address":"Waldegg 8",
    "sg:city":"Jens",
    "sg:orig_category":"Herstellung von Elektrizit\u00e4tsverteilungs U schalteinrichtungen",
    "sg:postcode":"2565",
    "sg:province":"Bern",
    "wof:name":"Ipc Inter Power, Gr\u00e4ppi Walter",
    "wof:placetype":"venue"
},
  "geometry": {"coordinates":[7.254802227,47.1017608643],"type":"Point"}
}