{
  "type": "Feature",
  "properties": {
    "iso:country":"CH",
    "sg:address":"Schlossbergstrasse 12",
    "sg:city":"Winterthur",
    "sg:orig_category":"Mechanische Werkst\u00e4tten",
    "sg:phone":"+41 52 203 34 27",
    "sg:postcode":"8408",
    "sg:province":"Z\u00fcrich",
    "wof:name":"Johann Bisig Z-technik",
    "wof:placetype":"venue"
},
  "geometry": {"coordinates":[8.6957960129,47.4998664856],"type":"Point"}
}