{
  "type": "Feature",
  "properties": {
    "iso:country":"CH",
    "sg:address":"Bahnhofstrasse 9",
    "sg:city":"Weinfelden",
    "sg:classifiers":[
        {
            "category":"Restaurant",
            "type":"Food & Drink"
        }
    ],
    "sg:phone":"+41 71 622 61 22",
    "sg:postcode":"8570",
    "sg:province":"Thurgau",
    "wof:name":"Restaurant B\u00e4ren",
    "wof:placetype":"venue"
},
  "geometry": {"coordinates":[9.1064052582,47.5679206848],"type":"Point"}
}