{
  "type": "Feature",
  "properties": {
    "iso:country":"CH",
    "sg:address":"1248",
    "sg:city":"Hermance",
    "sg:orig_category":"Schulpflegen",
    "sg:phone":"+41 22 751 12 95",
    "sg:postcode":"1248",
    "sg:province":"Gen\u00e8ve",
    "wof:name":"Commission Scolaire De L'ecole Primaire",
    "wof:placetype":"venue"
},
  "geometry": {"coordinates":[6.2308797836,46.2983589172],"type":"Point"}
}