{
  "type": "Feature",
  "properties": {
    "iso:country":"CH",
    "sg:address":"Industriestrasse",
    "sg:city":"Menzingen",
    "sg:orig_category":"Betrieb von Sportanlagen",
    "sg:phone":"+41 32 373 17 47",
    "sg:postcode":"6313",
    "sg:province":"Zug",
    "wof:name":"Tennis & Squash L\u00e4ngmatten Ag Br\u00fcgg",
    "wof:placetype":"venue"
},
  "geometry": {"coordinates":[7.270269,47.122616],"type":"Point"}
}