{
  "type": "Feature",
  "properties": {
    "iso:country":"CH",
    "sg:address":"Zinggstrasse 12",
    "sg:city":"Bern",
    "sg:orig_category":"Wirtschaftspr\u00fcfung, Steuerberatung U Treuhand",
    "sg:postcode":"3007",
    "sg:province":"Bern",
    "wof:name":"L\u00f6ffel H. Treuhand",
    "wof:placetype":"venue"
},
  "geometry": {"coordinates":[7.4413461685,46.9353103638],"type":"Point"}
}