{
  "type": "Feature",
  "properties": {
    "iso:country":"CH",
    "sg:address":"Grundackerstrasse 2",
    "sg:city":"Zunzgen",
    "sg:orig_category":"Reparatur von Uhren U Schmuck",
    "sg:phone":"+41 61 971 58 16",
    "sg:postcode":"4455",
    "sg:province":"Basel-Landschaft",
    "wof:name":"Max M\u00fcller Reparaturen Von Grossuhren",
    "wof:placetype":"venue"
},
  "geometry": {"coordinates":[7.8058748245,47.4520721436],"type":"Point"}
}