{
  "type": "Feature",
  "properties": {
    "iso:country":"CH",
    "sg:address":"Croix Du Pont 3979 Gr\u00f4ne. Postfach",
    "sg:city":"Gr\u00f4ne",
    "sg:orig_category":"RESTAURANTS: TEA-ROOMS",
    "sg:postcode":"3979",
    "sg:province":"Valais",
    "wof:name":"Schaal G\u00e9rard",
    "wof:placetype":"venue"
},
  "geometry": {"coordinates":[7.4697351456,46.2555389404],"type":"Point"}
}