{
  "type": "Feature",
  "properties": {
    "iso:country":"CH",
    "sg:address":"Chemin Neuf 8",
    "sg:city":"Chamoson",
    "sg:orig_category":"Detailhandel mit Boden U Wandbel\u00e4gen ohne Teppiche Verlegen von Fussboden",
    "sg:phone":"+41 27 306 34 22",
    "sg:postcode":"1955",
    "sg:province":"Valais",
    "wof:name":"Fernand Carruzzo Rev\u00eatements De Sols",
    "wof:placetype":"venue"
},
  "geometry": {"coordinates":[7.222458,46.201225],"type":"Point"}
}