{
  "type": "Feature",
  "properties": {
    "iso:country":"CH",
    "sg:address":"Solothurnstrasse 24",
    "sg:city":"Luterbach",
    "sg:orig_category":"Grosshandel mit Nahrungsmitteln, Getr\u00e4nken U Tabakwaren ohne ausgepr\u00e4gten Schwerpunkt",
    "sg:postcode":"4542",
    "sg:province":"Solothurn",
    "wof:name":"Fankhauser Markus",
    "wof:placetype":"venue"
},
  "geometry": {"coordinates":[7.5842318535,47.2149658203],"type":"Point"}
}