{
  "type": "Feature",
  "properties": {
    "iso:country":"CH",
    "sg:address":"Gaiserau 40 9056 Gais. Postfach",
    "sg:city":"Gais",
    "sg:orig_category":"Herstellung von sonstigen landwirtschaftlichen Maschinen",
    "sg:phone":"+41 71 793 20 17",
    "sg:postcode":"9056",
    "sg:province":"Appenzell Ausserrhoden",
    "wof:name":"H\u00f6hener Landmaschinen Ag Landmaschinenreparaturwerkstatt. Land, Kommunalmaschinen Usw; Handel",
    "wof:placetype":"venue"
},
  "geometry": {"coordinates":[9.451269,47.359482],"type":"Point"}
}