{
  "type": "Feature",
  "properties": {
    "iso:country":"CH",
    "sg:address":"Rue De La Prairie",
    "sg:city":"Montmollin",
    "sg:orig_category":"Unclassifiable Establishments",
    "sg:postcode":"2205",
    "wof:name":"Munt Immobilien Ag",
    "wof:placetype":"venue"
},
  "geometry": {"coordinates":[9.8386106491,46.497631073],"type":"Point"}
}