{
  "type": "Feature",
  "properties": {
    "iso:country":"CH",
    "sg:address":"Badenerstrasse 288",
    "sg:city":"Z\u00fcrich",
    "sg:orig_category":"Diskotheken, Dancings, Night Clubs",
    "sg:phone":"+41 12424959",
    "sg:postcode":"8004",
    "sg:province":"Z\u00fcrich",
    "wof:name":"Bar & Night-club Pattaya",
    "wof:placetype":"venue"
},
  "geometry": {"coordinates":[8.5136299133,47.3770446777],"type":"Point"}
}