{
  "type": "Feature",
  "properties": {
    "iso:country":"CH",
    "sg:address":"Rodi Fiesso",
    "sg:city":"Rodi Fiesso",
    "sg:classifiers":[
        {
            "category":"Banks & Credit Unions",
            "subcategory":"Bank",
            "type":"Services"
        }
    ],
    "sg:phone":"+41 91 649 66 68",
    "sg:postcode":"6772",
    "sg:province":"Ticino",
    "wof:name":"Banca Raiffeisen Rovio",
    "wof:placetype":"venue"
},
  "geometry": {"coordinates":[8.99966,45.935452],"type":"Point"}
}