{
  "type": "Feature",
  "properties": {
    "iso:country":"CH",
    "sg:address":"Eimatt",
    "sg:city":"Willisau",
    "sg:orig_category":"Bauschreinerei S\u00e4gewerke",
    "sg:phone":"+41 41 970 32 44",
    "sg:postcode":"6130",
    "sg:province":"Luzern",
    "wof:name":"Eugen Vogel Schreinerei & S\u00e4gerei",
    "wof:placetype":"venue"
},
  "geometry": {"coordinates":[7.992884,47.122223],"type":"Point"}
}