{
  "type": "Feature",
  "properties": {
    "iso:country":"CH",
    "sg:address":"6707 Iragna. Postfach",
    "sg:city":"Iragna",
    "sg:orig_category":"Softwareentwicklung U beratung",
    "sg:postcode":"6707",
    "sg:province":"Ticino",
    "wof:name":"Studio Informatico Kappazeta Di Dal Zovo Andrea",
    "wof:placetype":"venue"
},
  "geometry": {"coordinates":[8.9680175781,46.330280304],"type":"Point"}
}