{
  "type": "Feature",
  "properties": {
    "iso:country":"CH",
    "sg:address":"Im Spitzler 7",
    "sg:city":"Urdorf",
    "sg:orig_category":"Erwachsenenbildung U Unterricht",
    "sg:phone":"+41 79 653 73 78",
    "sg:postcode":"8902",
    "sg:province":"Z\u00fcrich",
    "wof:name":"Berger Roman",
    "wof:placetype":"venue"
},
  "geometry": {"coordinates":[8.4219007492,47.3815116882],"type":"Point"}
}