{
  "type": "Feature",
  "properties": {
    "iso:country":"CH",
    "sg:address":"Rue Des Bosquets 31",
    "sg:city":"Vevey",
    "sg:classifiers":[
        {
            "category":"Professional",
            "subcategory":"Accounting & Tax Preparation",
            "type":"Services"
        }
    ],
    "sg:phone":"+41 21 925 30 00",
    "sg:postcode":"1800",
    "sg:province":"Vaud",
    "sg:tags":[
        "audio",
        "mastering"
    ],
    "wof:name":"Decibel S.a.",
    "wof:placetype":"venue"
},
  "geometry": {"coordinates":[6.845692,46.46574],"type":"Point"}
}