{
  "type": "Feature",
  "properties": {
    "iso:country":"CH",
    "sg:address":"Chemin Du Milieu 100 1920 Martigny. Postfach",
    "sg:city":"Martigny",
    "sg:orig_category":"Betrieb von Taxis",
    "sg:postcode":"1920",
    "sg:province":"Valais",
    "wof:name":"Klibet Hamid",
    "wof:placetype":"venue"
},
  "geometry": {"coordinates":[7.069976,46.110176],"type":"Point"}
}