{
  "type": "Feature",
  "properties": {
    "addr:full":"Quartier Beau-site 4a Crissier Vaud 1023",
    "addr:housenumber":"4a",
    "addr:postcode":"1023",
    "addr:street":"Quartier Beau-Site",
    "iso:country":"CH",
    "sg:address":"Quartier Beau-site 4a",
    "sg:city":"Crissier",
    "sg:orig_category":"Arztpraxen",
    "sg:phone":"+41 21 635 93 23",
    "sg:postcode":"1023",
    "sg:province":"Vaud",
    "wof:name":"Dr M\u00e9d. Jean-paul Bussien M\u00e9decin Sp\u00e9cialiste Fmh",
    "wof:placetype":"venue"
},
  "geometry": {"coordinates":[6.578867,46.54715],"type":"Point"}
}