{
  "type": "Feature",
  "properties": {
    "iso:country":"CH",
    "sg:address":"1972",
    "sg:city":"Anz\u00e8re",
    "sg:classifiers":[
        {
            "category":"Travel",
            "subcategory":"Hotels & Motels",
            "type":"Entertainment"
        }
    ],
    "sg:phone":"+41 27 398 35 35",
    "sg:postcode":"1972",
    "sg:province":"Valais",
    "sg:tags":[
        "hotels",
        "mit",
        "restaurant"
    ],
    "wof:name":"Apparth\u00f4tel Grand-roc",
    "wof:placetype":"venue"
},
  "geometry": {"coordinates":[7.4004211426,46.2969818115],"type":"Point"}
}