{
  "type": "Feature",
  "properties": {
    "iso:country":"CH",
    "sg:address":"Viale Portone 9",
    "sg:city":"Bellinzona",
    "sg:orig_category":"Chemische Reinigung",
    "sg:phone":"+41 91 825 95 12",
    "sg:postcode":"6500",
    "sg:province":"Ticino",
    "wof:name":"Lavachimica Espresso Sa Lavanderia Chimica",
    "wof:placetype":"venue"
},
  "geometry": {"coordinates":[9.021439,46.193684],"type":"Point"}
}