{
  "type": "Feature",
  "properties": {
    "iso:country":"CH",
    "sg:address":"Hauptgasse 18",
    "sg:city":"Solothurn",
    "sg:classifiers":[
        {
            "category":"Restaurant",
            "type":"Food & Drink"
        }
    ],
    "sg:phone":"+41 32 623 28 28",
    "sg:postcode":"4500",
    "sg:province":"Solothurn",
    "wof:name":"Restaurant M\u00e4rli",
    "wof:placetype":"venue"
},
  "geometry": {"coordinates":[7.5363869667,47.2069015503],"type":"Point"}
}