{
  "type": "Feature",
  "properties": {
    "iso:country":"CH",
    "sg:address":"Ramsenburgweg 15",
    "sg:city":"Herisau",
    "sg:orig_category":"Herstellung von Metallerzeugnissen ohne Maschinenbau Herstellung von elektrischen Haushaltsger\u00e4ten",
    "sg:phone":"+41 62 891 76 51",
    "sg:postcode":"9100",
    "sg:province":"Appenzell Ausserrhoden",
    "wof:name":"E.g.o. Staufen Ag",
    "wof:placetype":"venue"
},
  "geometry": {"coordinates":[8.1662902832,47.3872299194],"type":"Point"}
}