{
  "type": "Feature",
  "properties": {
    "iso:country":"CH",
    "sg:address":"Pavement Route Du 1 1018 Lausanne. Postfach",
    "sg:city":"Lausanne",
    "sg:orig_category":"Pensionskassen",
    "sg:phone":"+41 21 647 74 61",
    "sg:postcode":"1018",
    "sg:province":"Vaud",
    "wof:name":"Fondation De Pr\u00e9voyance En Faveur Du Personnel De La Soci\u00e9t\u00e9 Anonyme Cu\u00e9nod Et Payot Sa",
    "wof:placetype":"venue"
},
  "geometry": {"coordinates":[6.636015892,46.5300712585],"type":"Point"}
}