{
  "type": "Feature",
  "properties": {
    "iso:country":"CH",
    "sg:address":"Linseb\u00fchlstrasse 32",
    "sg:city":"St.gallen",
    "sg:orig_category":"Unclassifiable Establishments",
    "sg:postcode":"9000",
    "sg:province":"St. Gallen",
    "wof:name":"A. Pagnotta",
    "wof:placetype":"venue"
},
  "geometry": {"coordinates":[8.5399808884,47.2878990173],"type":"Point"}
}