{
  "type": "Feature",
  "properties": {
    "iso:country":"CH",
    "sg:address":"Hofstrasse 22",
    "sg:city":"Romanshorn",
    "sg:orig_category":"Architektur U Ingenieurb\u00fcros",
    "sg:postcode":"8590",
    "sg:province":"Thurgau",
    "wof:name":"Etb Technique Architecture B\u00f6gli Etienne",
    "wof:placetype":"venue"
},
  "geometry": {"coordinates":[7.04263,47.020039],"type":"Point"}
}