{
  "type": "Feature",
  "properties": {
    "iso:country":"CH",
    "sg:address":"Langenentschwil 1482",
    "sg:city":"Flawil",
    "sg:orig_category":"Bauschreinerei",
    "sg:phone":"+41 71 393 19 36",
    "sg:postcode":"9230",
    "sg:province":"St. Gallen",
    "wof:name":"Werner Reifler Schreinerei",
    "wof:placetype":"venue"
},
  "geometry": {"coordinates":[9.209698,47.396069],"type":"Point"}
}