{
  "type": "Feature",
  "properties": {
    "iso:country":"CH",
    "sg:address":"Guntenbachstrasse 21 8603 Schwerzenbach. Postfach 700",
    "sg:city":"Schwerzenbach",
    "sg:orig_category":"Grosshandel mit Baumaschinen Herstellung von Bergwerks U Baumaschinen",
    "sg:phone":"+41 18261290",
    "sg:postcode":"8603",
    "sg:province":"Z\u00fcrich",
    "wof:name":"Afa Ag F\u00fcr Anbauger\u00e4te",
    "wof:placetype":"venue"
},
  "geometry": {"coordinates":[8.6642932892,47.3802757263],"type":"Point"}
}