{
  "type": "Feature",
  "properties": {
    "iso:country":"CH",
    "sg:address":"Mayens-de-conthey",
    "sg:city":"Erde",
    "sg:orig_category":"Hoch U Tiefbau Verlegen von Fliesen U Platten",
    "sg:phone":"+41 27 346 23 34",
    "sg:postcode":"1976",
    "sg:province":"Valais",
    "wof:name":"Gaby Duc Entreprise De Carrelage",
    "wof:placetype":"venue"
},
  "geometry": {"coordinates":[7.2959799767,46.2425804138],"type":"Point"}
}