{
  "type": "Feature",
  "properties": {
    "iso:country":"CH",
    "sg:address":"St.-antons-gasse 4a",
    "sg:city":"Zug",
    "sg:orig_category":"Unclassifiable Establishments",
    "sg:postcode":"6300",
    "sg:province":"Zug",
    "wof:name":"Ozelot Ethologie Studio Singenberger + Co",
    "wof:placetype":"venue"
},
  "geometry": {"coordinates":[7.9459810257,47.54139328],"type":"Point"}
}