{
  "type": "Feature",
  "properties": {
    "iso:country":"CH",
    "sg:address":"Pfadackerstrasse 6",
    "sg:city":"Spreitenbach",
    "sg:orig_category":"Unclassifiable Establishments",
    "sg:phone":"+41 56 418 15 00",
    "sg:postcode":"8957",
    "sg:province":"Aargau",
    "wof:name":"Dr-miro Ag",
    "wof:placetype":"venue"
},
  "geometry": {"coordinates":[8.3703260422,47.4245185852],"type":"Point"}
}