{
  "type": "Feature",
  "properties": {
    "iso:country":"CH",
    "sg:address":"Steinbach",
    "sg:city":"Einsiedeln",
    "sg:orig_category":"RESTAURANTS: TEA-ROOMS",
    "sg:postcode":"8840",
    "sg:province":"Schwyz",
    "wof:name":"Krone Alpnach Ag",
    "wof:placetype":"venue"
},
  "geometry": {"coordinates":[8.2711229324,46.9415664673],"type":"Point"}
}