{
  "type": "Feature",
  "properties": {
    "iso:country":"CH",
    "sg:address":"Grand-pont Rue Du 44",
    "sg:city":"Sion",
    "sg:orig_category":"Dauerkulturbau",
    "sg:phone":"+41 27 323 74 00",
    "sg:postcode":"1950",
    "sg:province":"Valais",
    "wof:name":"Cave Les Futailles Sa",
    "wof:placetype":"venue"
},
  "geometry": {"coordinates":[7.360652,46.23521],"type":"Point"}
}