{
  "type": "Feature",
  "properties": {
    "iso:country":"CH",
    "sg:address":"Via Cantonale 1 6855 Stabio. Postfach",
    "sg:city":"Stabio",
    "sg:orig_category":"Detailhandel mit Fleisch U Fleischwaren",
    "sg:postcode":"6855",
    "sg:province":"Ticino",
    "wof:name":"Beretta Fratelli Sa",
    "wof:placetype":"venue"
},
  "geometry": {"coordinates":[8.9457483292,45.8518562317],"type":"Point"}
}