{
  "type": "Feature",
  "properties": {
    "iso:country":"CH",
    "sg:address":"Sch\u00fctzenmattstrasse 19-21",
    "sg:city":"B\u00fclach",
    "sg:orig_category":"Unternehmensberatung Warenh\u00e4user",
    "sg:phone":"+41 18728080",
    "sg:postcode":"8180",
    "sg:province":"Z\u00fcrich",
    "wof:name":"Abm Au Bon March\u00e9",
    "wof:placetype":"venue"
},
  "geometry": {"coordinates":[8.5331268311,47.5279045105],"type":"Point"}
}