{
  "type": "Feature",
  "properties": {
    "iso:country":"CH",
    "sg:address":"Avenue G\u00e9n\u00e9ral-guisan 52 1180 Rolle. Postfach",
    "sg:city":"Rolle",
    "sg:orig_category":"Non-Classified Establishments",
    "sg:postcode":"1180",
    "sg:province":"Vaud",
    "wof:name":"Agenceweb.ch, Courbat R\u00e9gis",
    "wof:placetype":"venue"
},
  "geometry": {"coordinates":[6.3314061165,46.4579238892],"type":"Point"}
}