{
  "type": "Feature",
  "properties": {
    "iso:country":"CH",
    "sg:address":"Campingweg 11",
    "sg:city":"Oftringen",
    "sg:orig_category":"Einzelhandel mit Automobilteilen U Zubeh\u00f6r Tankstellen",
    "sg:phone":"+41 62 791 58 85",
    "sg:postcode":"4665",
    "sg:province":"Aargau",
    "wof:name":"Shell Tankstelle & Shop",
    "wof:placetype":"venue"
},
  "geometry": {"coordinates":[7.930770874,47.3051528931],"type":"Point"}
}