{
  "type": "Feature",
  "properties": {
    "iso:country":"CH",
    "sg:address":"Reberastrasse 40",
    "sg:city":"Schaan",
    "sg:orig_category":"Architekturb\u00fcros",
    "sg:phone":"+41 81 833 41 44",
    "sg:postcode":"9494",
    "wof:name":"Arnd K\u00fcchel Architekturb\u00fcro",
    "wof:placetype":"venue"
},
  "geometry": {"coordinates":[9.838898,46.498245],"type":"Point"}
}