{
  "type": "Feature",
  "properties": {
    "iso:country":"CH",
    "sg:address":"Sut Il Vitg 14",
    "sg:city":"Trun",
    "sg:orig_category":"Maler U Glasergewerbe Malerei",
    "sg:phone":"+41 81 943 31 21",
    "sg:postcode":"7166",
    "sg:province":"Graubunden",
    "wof:name":"3 Picturs, Defuns Und Bearth",
    "wof:placetype":"venue"
},
  "geometry": {"coordinates":[8.9874401093,46.7414245605],"type":"Point"}
}