{
  "type": "Feature",
  "properties": {
    "iso:country":"CH",
    "sg:address":"1706 Fribourg Case Postale 79",
    "sg:city":"Fribourg",
    "sg:classifiers":[
        {
            "category":"Arena",
            "subcategory":"Sports Club",
            "type":"Entertainment"
        }
    ],
    "sg:postcode":"1706",
    "sg:tags":[
        "karate",
        "judo",
        "sportvereine"
    ],
    "wof:name":"Judo Club Fribourg",
    "wof:placetype":"venue"
},
  "geometry": {"coordinates":[7.1512799263,46.8025016785],"type":"Point"}
}