{
  "type": "Feature",
  "properties": {
    "iso:country":"CH",
    "sg:address":"Huobmattstrasse 4",
    "sg:city":"Meggen",
    "sg:orig_category":"P\u00e9dicure",
    "sg:phone":"+41 41 377 02 28",
    "sg:postcode":"6045",
    "sg:province":"Luzern",
    "wof:name":"Christiane Gloggner Podologie Huob",
    "wof:placetype":"venue"
},
  "geometry": {"coordinates":[8.3805541992,47.0508079529],"type":"Point"}
}