{
  "type": "Feature",
  "properties": {
    "iso:country":"CH",
    "sg:address":"Parkstrasse 1 9320 Arbon. Postfach 234",
    "sg:city":"Arbon",
    "sg:orig_category":"Versicherungen Generalagenturen",
    "sg:phone":"+41 71 446 76 76",
    "sg:postcode":"9320",
    "sg:province":"Thurgau",
    "wof:name":"Winterthur-versicherungen Generalagentur",
    "wof:placetype":"venue"
},
  "geometry": {"coordinates":[9.433889389,47.5132827759],"type":"Point"}
}