{
  "type": "Feature",
  "properties": {
    "iso:country":"CH",
    "sg:address":"Quaderstrasse 7",
    "sg:city":"Zizers",
    "sg:orig_category":"Vereine Abstinenten",
    "sg:phone":"+41 81 322 45 49",
    "sg:postcode":"7205",
    "sg:province":"Graubunden",
    "wof:name":"Blaues Kreuz Graub\u00fcnden",
    "wof:placetype":"venue"
},
  "geometry": {"coordinates":[9.5641202927,46.9372940063],"type":"Point"}
}