{
  "type": "Feature",
  "properties": {
    "iso:country":"CH",
    "sg:address":"Oltnerstrasse 3",
    "sg:city":"Aarburg",
    "sg:orig_category":"Arztpraxen",
    "sg:phone":"+41 62 791 41 21",
    "sg:postcode":"4663",
    "sg:province":"Aargau",
    "wof:name":"Dr.med.manfred Andrea Frey Arzt F.allgemeine Medizin Fmh",
    "wof:placetype":"venue"
},
  "geometry": {"coordinates":[7.898997,47.322334],"type":"Point"}
}