{
  "type": "Feature",
  "properties": {
    "iso:country":"CH",
    "sg:address":"Sonnhaldenstrasse 4",
    "sg:city":"Illnau",
    "sg:orig_category":"Technische B\u00fcros Hoch-& Tiefbau",
    "sg:phone":"+41 71 245 26 65",
    "sg:postcode":"8308",
    "sg:province":"Z\u00fcrich",
    "wof:name":"Rolf Oettli Technisches Baub\u00fcro",
    "wof:placetype":"venue"
},
  "geometry": {"coordinates":[9.4017305374,47.4344978333],"type":"Point"}
}