{
  "type": "Feature",
  "properties": {
    "iso:country":"CH",
    "sg:address":"Via Alla Roggia 10c",
    "sg:city":"Sementina",
    "sg:orig_category":"Fotografisches Gewerbe U fotografische Laboratorien",
    "sg:postcode":"6514",
    "sg:province":"Ticino",
    "wof:name":"All Access Di Ducrey Fran\u00e7oise",
    "wof:placetype":"venue"
},
  "geometry": {"coordinates":[8.989988327,46.182220459],"type":"Point"}
}