{
  "type": "Feature",
  "properties": {
    "iso:country":"CH",
    "sg:address":"Hasliweg 234",
    "sg:city":"Schupfart",
    "sg:orig_category":"Herstellung von konfektionierten Textilwaren ohne Bekleidung",
    "sg:phone":"+41 62 871 30 18",
    "sg:postcode":"4325",
    "sg:province":"Aargau",
    "wof:name":"Tschanz Ag Sonnen-& Wetterschutz",
    "wof:placetype":"venue"
},
  "geometry": {"coordinates":[7.9620680809,47.5108261108],"type":"Point"}
}