{
  "type": "Feature",
  "properties": {
    "iso:country":"CH",
    "sg:address":"Neugutstrasse 52 8600 D\u00fcbendorf. Postfach",
    "sg:city":"D\u00fcbendorf",
    "sg:orig_category":"Herstellung von sonstigen elektrischen Ausr\u00fcstungen",
    "sg:phone":"+41 18243040",
    "sg:postcode":"8600",
    "sg:province":"Z\u00fcrich",
    "wof:name":"Isocon Ag",
    "wof:placetype":"venue"
},
  "geometry": {"coordinates":[8.6091136932,47.3998908997],"type":"Point"}
}