{
  "type": "Feature",
  "properties": {
    "addr:full":"Dorfstrasse 19 Wattenwil Bern 3665",
    "addr:housenumber":"19",
    "addr:postcode":"3665",
    "addr:street":"Dorfstrasse",
    "iso:country":"CH",
    "sg:address":"Dorfstrasse 19",
    "sg:city":"Wattenwil",
    "sg:orig_category":"Blumen U Zierpflanzenbau Detailhandel mit Blumen U Pflanzen",
    "sg:phone":"+41 33 356 12 34",
    "sg:postcode":"3665",
    "sg:province":"Bern",
    "wof:name":"Liechti Hans J\u00f6rg",
    "wof:placetype":"venue"
},
  "geometry": {"coordinates":[7.509397,46.770054],"type":"Point"}
}