{
  "type": "Feature",
  "properties": {
    "iso:country":"CH",
    "sg:address":"Route Des Neigles 6",
    "sg:city":"Fribourg",
    "sg:orig_category":"Mechanik",
    "sg:phone":"+41 26 322 13 49",
    "sg:postcode":"1700",
    "sg:province":"Fribourg",
    "wof:name":"Durret Louis",
    "wof:placetype":"venue"
},
  "geometry": {"coordinates":[7.1680002213,46.8060722351],"type":"Point"}
}