{
  "type": "Feature",
  "properties": {
    "iso:country":"CH",
    "sg:address":"Entfelderstrasse 7",
    "sg:city":"Sch\u00f6nenwerd",
    "sg:orig_category":"Unternehmensberatung",
    "sg:phone":"+41 14472040",
    "sg:postcode":"5012",
    "sg:province":"Solothurn",
    "wof:name":"Pietro Sassi & Partner Gmbh",
    "wof:placetype":"venue"
},
  "geometry": {"coordinates":[8.7919330597,47.3121109009],"type":"Point"}
}