{
  "type": "Feature",
  "properties": {
    "iso:country":"CH",
    "sg:address":"Dorfstrasse 11",
    "sg:city":"Brittnau",
    "sg:classifiers":[
        {
            "category":"Education",
            "subcategory":"Library",
            "type":"Public Place"
        }
    ],
    "sg:phone":"+41 61 751 51 61",
    "sg:postcode":"4805",
    "sg:province":"Aargau",
    "sg:tags":[
        "u",
        "bibliotheken",
        "archive"
    ],
    "wof:name":"Gemeinde-& Schulbibliothek",
    "wof:placetype":"venue"
},
  "geometry": {"coordinates":[7.594113,47.472431],"type":"Point"}
}