{
  "type": "Feature",
  "properties": {
    "iso:country":"CH",
    "sg:address":"Walperswilstrasse 59",
    "sg:city":"Aarberg",
    "sg:orig_category":"Blumen U Zierpflanzenbau Detailhandel mit Blumen U Pflanzen",
    "sg:phone":"+41 32 392 12 91",
    "sg:postcode":"3270",
    "sg:province":"Bern",
    "wof:name":"Wiedmer-blumen Ag",
    "wof:placetype":"venue"
},
  "geometry": {"coordinates":[7.262559,47.046764],"type":"Point"}
}