{
  "type": "Feature",
  "properties": {
    "iso:country":"CH",
    "sg:address":"Kirchenstrasse 2 8854 Siebnen. Postfach",
    "sg:city":"Siebnen",
    "sg:orig_category":"Herstellung von Teppichen",
    "sg:postcode":"8854",
    "sg:province":"Schwyz",
    "wof:name":"Tenner Armin Dienstleistungen Im Bereich Bodenbel\u00e4ge Usw",
    "wof:placetype":"venue"
},
  "geometry": {"coordinates":[8.8975019455,47.1752815247],"type":"Point"}
}