{
  "type": "Feature",
  "properties": {
    "iso:country":"CH",
    "sg:address":"Pr\u00e9-de-la-fontaine Rue Du 13",
    "sg:city":"Satigny",
    "sg:orig_category":"Detailhandel mit B\u00fcchern, Zeitungen, Schreib U Papeteriewaren",
    "sg:phone":"+41 22 783 02 72",
    "sg:postcode":"1242",
    "sg:province":"Gen\u00e8ve",
    "wof:name":"Media Pack Sa",
    "wof:placetype":"venue"
},
  "geometry": {"coordinates":[6.053568,46.223598],"type":"Point"}
}