{
  "type": "Feature",
  "properties": {
    "iso:country":"CH",
    "sg:address":"Weck-reynold Av. Louis",
    "sg:city":"Fribourg",
    "sg:orig_category":"Sonstiger spezialisierter Hoch U Tiefbau",
    "sg:postcode":"1700",
    "sg:province":"Fribourg",
    "wof:name":"A. Zucco Sa",
    "wof:placetype":"venue"
},
  "geometry": {"coordinates":[7.1499361992,46.8079452515],"type":"Point"}
}