{
  "type": "Feature",
  "properties": {
    "iso:country":"CH",
    "sg:address":"Hauptstrasse",
    "sg:city":"Cazis",
    "sg:orig_category":"Herstellung von Metallkonstruktionen Stahl U Leichtmetallbau",
    "sg:phone":"+41 81 651 46 46",
    "sg:postcode":"7408",
    "sg:province":"Graubunden",
    "wof:name":"Ughini Metallbau Ag",
    "wof:placetype":"venue"
},
  "geometry": {"coordinates":[9.4273872375,46.7245292664],"type":"Point"}
}