{
  "type": "Feature",
  "properties": {
    "iso:country":"CH",
    "sg:address":"Terbinerstr. 2",
    "sg:city":"Visp",
    "sg:classifiers":[
        {
            "category":"Professional",
            "subcategory":"Printing & Photocopies",
            "type":"Services"
        }
    ],
    "sg:phone":"+41 27 948 30 30",
    "sg:postcode":"3930",
    "sg:province":"Valais",
    "sg:tags":[
        "publishing"
    ],
    "wof:name":"Mengis Druck U Verlag Ag",
    "wof:placetype":"venue"
},
  "geometry": {"coordinates":[7.883245945,46.2934761047],"type":"Point"}
}