{
  "type": "Feature",
  "properties": {
    "iso:country":"CH",
    "sg:address":"Tittwiesenstrasse 27",
    "sg:city":"Chur",
    "sg:orig_category":"Informatikschulen",
    "sg:phone":"+41 81 286 60 60",
    "sg:postcode":"7000",
    "sg:province":"Graubunden",
    "wof:name":"Digicomp Ag",
    "wof:placetype":"venue"
},
  "geometry": {"coordinates":[9.5273103714,46.8569335938],"type":"Point"}
}