{
  "type": "Feature",
  "properties": {
    "iso:country":"CH",
    "sg:address":"Hagenstrasse 24",
    "sg:city":"Illnau",
    "sg:orig_category":"Vorschulen, Kinderg\u00e4rten",
    "sg:phone":"+41 52 346 17 36",
    "sg:postcode":"8308",
    "sg:province":"Z\u00fcrich",
    "wof:name":"Kindergarten Hagen",
    "wof:placetype":"venue"
},
  "geometry": {"coordinates":[8.7208900452,47.4089889526],"type":"Point"}
}