{
  "type": "Feature",
  "properties": {
    "iso:country":"CH",
    "sg:address":"Via Cabiagh 8",
    "sg:city":"Davesco-soragno",
    "sg:orig_category":"Herstellung von Konstruktionsteilen, Fertigbauteilen U Ausbauelementen aus Holz",
    "sg:postcode":"6964",
    "sg:province":"Ticino",
    "wof:name":"Figa, Alexandre Commergnat Et Philippe Valiton",
    "wof:placetype":"venue"
},
  "geometry": {"coordinates":[6.7695250511,46.5411186218],"type":"Point"}
}