{
  "type": "Feature",
  "properties": {
    "iso:country":"CH",
    "sg:address":"Alte Rheinstrasse 91",
    "sg:city":"Embrach",
    "sg:orig_category":"R\u00fcckgewinnung U Vorbereitung f\u00fcr die Wiederverwertung Recycling von Schrott",
    "sg:phone":"+41 18650212",
    "sg:postcode":"8424",
    "sg:province":"Z\u00fcrich",
    "wof:name":"Fritz Meier Autoverwertung",
    "wof:placetype":"venue"
},
  "geometry": {"coordinates":[8.5834569931,47.5216026306],"type":"Point"}
}