{
  "type": "Feature",
  "properties": {
    "iso:country":"CH",
    "sg:address":"Rue Robert-c\u00e9ard 5",
    "sg:city":"Gen\u00e8ve",
    "sg:orig_category":"Detailhandel mit Pelzwaren",
    "sg:phone":"+41 22 311 36 87",
    "sg:postcode":"1204",
    "sg:province":"Gen\u00e8ve",
    "wof:name":"Benjamin Fourrures Sa",
    "wof:placetype":"venue"
},
  "geometry": {"coordinates":[6.1492152214,46.2035331726],"type":"Point"}
}