{
  "type": "Feature",
  "properties": {
    "iso:country":"CH",
    "sg:address":"Kleinfeldstrasse 20",
    "sg:city":"Ipsach",
    "sg:orig_category":"Gesundheitswesen",
    "sg:postcode":"2563",
    "sg:province":"Bern",
    "wof:name":"Center F\u00fcr Pers\u00f6nlichkeitsentfaltung F. Meyer-perret",
    "wof:placetype":"venue"
},
  "geometry": {"coordinates":[7.2282772064,47.110370636],"type":"Point"}
}