{
  "type": "Feature",
  "properties": {
    "iso:country":"CH",
    "sg:address":"Wallisrain 7",
    "sg:city":"K\u00f6lliken",
    "sg:orig_category":"Politische Parteien FDP",
    "sg:phone":"+41 62 723 50 13",
    "sg:postcode":"5742",
    "sg:province":"Aargau",
    "wof:name":"Fdp Ortspartei Hunzenschwil",
    "wof:placetype":"venue"
},
  "geometry": {"coordinates":[8.0183439255,47.335899353],"type":"Point"}
}