{
  "type": "Feature",
  "properties": {
    "iso:country":"CH",
    "sg:address":"Sch\u00e4renmoosstrasse 91",
    "sg:city":"Seebach",
    "sg:classifiers":[
        {
            "category":"Communications",
            "subcategory":"Radio Station",
            "type":"Services"
        }
    ],
    "sg:phone":"+41 13088000",
    "sg:postcode":"8052",
    "sg:province":"Z\u00fcrich",
    "sg:tags":[
        "fernsehanstalten",
        "u"
    ],
    "wof:name":"Media Station Gmbh",
    "wof:placetype":"venue"
},
  "geometry": {"coordinates":[8.5402402878,47.4224815369],"type":"Point"}
}