{
  "type": "Feature",
  "properties": {
    "iso:country":"CH",
    "sg:address":"Hauptstrasse 67",
    "sg:city":"Oensingen",
    "sg:classifiers":[
        {
            "category":"Travel",
            "subcategory":"Hotels & Motels",
            "type":"Entertainment"
        }
    ],
    "sg:phone":"+41 33 951 10 72",
    "sg:postcode":"4702",
    "sg:province":"Solothurn",
    "sg:tags":[
        "hotels",
        "mit",
        "restaurant"
    ],
    "wof:name":"Hotel Lindenhof Ag",
    "wof:placetype":"venue"
},
  "geometry": {"coordinates":[8.0372343063,46.7566795349],"type":"Point"}
}