{
  "type": "Feature",
  "properties": {
    "iso:country":"CH",
    "sg:address":"Derri\u00e8re L'eglise 5",
    "sg:city":"Ch\u00e9zard-st-martin",
    "sg:orig_category":"Grosshandel mit Eisenwaren sowie Installationsbedarf f\u00fcr Gas, Wasser U Heizung",
    "sg:phone":"+41 32 853 34 40",
    "sg:postcode":"2054",
    "sg:province":"Neuch\u00e2tel",
    "wof:name":"Jet Flam S\u00e0rl Mat\u00e9riel De Chauffage",
    "wof:placetype":"venue"
},
  "geometry": {"coordinates":[6.9342851639,47.0675506592],"type":"Point"}
}