{
  "type": "Feature",
  "properties": {
    "iso:country":"CH",
    "sg:address":"L\u00e4rchenstrasse 6",
    "sg:city":"Wattwil",
    "sg:orig_category":"Detailhandel mit M\u00f6beln U Haushaltsgegenst\u00e4nden",
    "sg:postcode":"9630",
    "sg:province":"St. Gallen",
    "wof:name":"Pacific 81. Huynh",
    "wof:placetype":"venue"
},
  "geometry": {"coordinates":[9.0980882645,47.2924385071],"type":"Point"}
}