{
  "type": "Feature",
  "properties": {
    "iso:country":"CH",
    "sg:address":"Eichstrasse 42",
    "sg:city":"Glattbrugg",
    "sg:classifiers":[
        {
            "category":"Government",
            "subcategory":"Department Of Motor Vehicles",
            "type":"Public Place"
        }
    ],
    "sg:phone":"+41 18096969",
    "sg:postcode":"8152",
    "sg:province":"Z\u00fcrich",
    "sg:tags":[
        "dyestuff",
        "dispersion"
    ],
    "wof:name":"Rupf + Co. Ag",
    "wof:placetype":"venue"
},
  "geometry": {"coordinates":[8.556609,47.431355],"type":"Point"}
}