{
  "type": "Feature",
  "properties": {
    "addr:full":"Ziegelmattstrasse 13 Grenchen Solothurn 2540",
    "addr:housenumber":"13",
    "addr:postcode":"2540",
    "addr:street":"Ziegelmattstrasse",
    "iso:country":"CH",
    "sg:address":"Ziegelmattstrasse 13",
    "sg:city":"Grenchen",
    "sg:orig_category":"Betrieb von Taxis",
    "sg:phone":"+41 32 645 45 12",
    "sg:postcode":"2540",
    "sg:province":"Solothurn",
    "wof:name":"R.o.s. Wyssbrod",
    "wof:placetype":"venue"
},
  "geometry": {"coordinates":[7.408013,47.196182],"type":"Point"}
}