{
  "type": "Feature",
  "properties": {
    "iso:country":"CH",
    "sg:address":"Neuhauserstrasse 68a",
    "sg:city":"Frauenfeld",
    "sg:orig_category":"Unclassifiable Establishments",
    "sg:postcode":"8500",
    "sg:province":"Thurgau",
    "wof:name":"Garimo Consulting Gmbh",
    "wof:placetype":"venue"
},
  "geometry": {"coordinates":[8.9107160568,47.5534591675],"type":"Point"}
}