{
  "type": "Feature",
  "properties": {
    "iso:country":"CH",
    "sg:address":"Hinterbergstrasse 30 6312 Steinhausen. Postfach",
    "sg:city":"Steinhausen",
    "sg:orig_category":"Pensionskassen",
    "sg:postcode":"6312",
    "sg:province":"Zug",
    "wof:name":"Personalf\u00fcrsorgestiftung Der Oswald Ag, Nahrungsmittel",
    "wof:placetype":"venue"
},
  "geometry": {"coordinates":[8.4784517288,47.1871185303],"type":"Point"}
}