{
  "type": "Feature",
  "properties": {
    "addr:full":"Grottenweg 10 Wegenstetten Aargau 4317",
    "addr:housenumber":"10",
    "addr:postcode":"4317",
    "addr:street":"Grottenweg",
    "iso:country":"CH",
    "sg:address":"Grottenweg 10",
    "sg:city":"Wegenstetten",
    "sg:orig_category":"Detailhandel mit B\u00fcromaschinen U einrichtungen",
    "sg:phone":"+41 61 875 90 90",
    "sg:postcode":"4317",
    "sg:province":"Aargau",
    "wof:name":"Buma B\u00fcromaterial",
    "wof:placetype":"venue"
},
  "geometry": {"coordinates":[7.934269,47.497089],"type":"Point"}
}