{
  "type": "Feature",
  "properties": {
    "iso:country":"CH",
    "sg:address":"Oberriedenstrasse 63",
    "sg:city":"Gebenstorf",
    "sg:orig_category":"Markt U Meinungsforschung",
    "sg:phone":"+41 31 350 94 49",
    "sg:postcode":"5412",
    "sg:province":"Aargau",
    "wof:name":"Publica Data Ag Daten Der Medien, Publikumsforschung Der Schweiz. Radio Und Fernsehgesellsch. Usw.; Verkauf, Vertrieb",
    "wof:placetype":"venue"
},
  "geometry": {"coordinates":[7.4738278389,46.9438514709],"type":"Point"}
}