{
  "type": "Feature",
  "properties": {
    "iso:country":"CH",
    "sg:address":"Grande Salle Place De La 1124 Gollion. Postfach",
    "sg:city":"Gollion",
    "sg:orig_category":"Herstellung von Mess U Kontrollinstrumenten U vorrichtungen",
    "sg:postcode":"1124",
    "sg:province":"Vaud",
    "wof:name":"Mecasoew S\u00e0rl Atelier M\u00e9canique De Pr\u00e9cision, Montage, C\u00e2blage De Machines Etc",
    "wof:placetype":"venue"
},
  "geometry": {"coordinates":[6.5100998878,46.5864105225],"type":"Point"}
}