{
  "type": "Feature",
  "properties": {
    "iso:country":"CH",
    "sg:address":"9657 Unterwasser. Postfach",
    "sg:city":"Unterwasser",
    "sg:orig_category":"Sonstige mit Sport verbundene T\u00e4tigkeiten",
    "sg:postcode":"9657",
    "sg:province":"St. Gallen",
    "wof:name":"Tennis Academy Tea Gmbh",
    "wof:placetype":"venue"
},
  "geometry": {"coordinates":[9.3059768677,47.1969718933],"type":"Point"}
}