{
  "type": "Feature",
  "properties": {
    "iso:country":"CH",
    "sg:address":"Via Trevani 2",
    "sg:city":"Locarno",
    "sg:orig_category":"Sonstige mit der Informatik verbundene T\u00e4tigkeiten",
    "sg:postcode":"6600",
    "sg:province":"Ticino",
    "wof:name":"Scuola D'informatica Maier",
    "wof:placetype":"venue"
},
  "geometry": {"coordinates":[8.7957201004,46.1687088013],"type":"Point"}
}