{
  "type": "Feature",
  "properties": {
    "iso:country":"CH",
    "sg:address":"Rue De La Gare 20e",
    "sg:city":"Sonceboz-sombeval",
    "sg:orig_category":"Gewinnung von Kies U Sand",
    "sg:postcode":"2605",
    "sg:province":"Bern",
    "wof:name":"Aggregat Sa, Succursale De Sonceboz-sombeval",
    "wof:placetype":"venue"
},
  "geometry": {"coordinates":[7.1732082367,47.1952667236],"type":"Point"}
}