{
  "type": "Feature",
  "properties": {
    "iso:country":"CH",
    "sg:address":"Via Principala 126",
    "sg:city":"Trun",
    "sg:orig_category":"Nationale Postdienste",
    "sg:phone":"+41 81 921 40 50",
    "sg:postcode":"7166",
    "sg:province":"Graubunden",
    "wof:name":"Die Schweizerische Post",
    "wof:placetype":"venue"
},
  "geometry": {"coordinates":[9.257900238,46.8063430786],"type":"Point"}
}