{
  "type": "Feature",
  "properties": {
    "iso:country":"CH",
    "sg:address":"Marktgasse 3",
    "sg:city":"Appenzell",
    "sg:orig_category":"Detailhandel mit Waren verschiedener Art, Hauptrichtung Nahrungsmittel Grosshandel mit Nahrungsmitte",
    "sg:phone":"+41 71 787 19 43",
    "sg:postcode":"9050",
    "sg:province":"Appenzell Innerhoden",
    "wof:name":"Srecko Jurec",
    "wof:placetype":"venue"
},
  "geometry": {"coordinates":[9.4087553024,47.331199646],"type":"Point"}
}