{
  "type": "Feature",
  "properties": {
    "iso:country":"CH",
    "sg:address":"Holzmatt 1",
    "sg:city":"Grossh\u00f6chstetten",
    "sg:classifiers":[
        {
            "category":"Military Area",
            "subcategory":"Restricted Area",
            "type":"Public Place"
        }
    ],
    "sg:phone":"+41 31 711 04 36",
    "sg:postcode":"3506",
    "sg:province":"Bern",
    "sg:tags":[
        "platform",
        "lifting"
    ],
    "wof:name":"Alclic Ag",
    "wof:placetype":"venue"
},
  "geometry": {"coordinates":[7.6337108612,46.8965072632],"type":"Point"}
}