{
  "type": "Feature",
  "properties": {
    "iso:country":"CH",
    "sg:address":"Grand-rue 1",
    "sg:city":"Vallorbe",
    "sg:orig_category":"Detailhandel mit elektrischen Haushalts, Radio U Fernsehger\u00e4ten ohne ausgepr\u00e4gten Schwerpunkt",
    "sg:phone":"+41 21 843 12 10",
    "sg:postcode":"1337",
    "sg:province":"Vaud",
    "wof:name":"Soci\u00e9t\u00e9 \u00e9lectrique Du Ch\u00e2telard",
    "wof:placetype":"venue"
},
  "geometry": {"coordinates":[6.3789777756,46.7119407654],"type":"Point"}
}