{
  "type": "Feature",
  "properties": {
    "iso:country":"CH",
    "sg:address":"Z\u00fcrcherstrasse 5 Hegnau 8604 Volketswil. Postfach",
    "sg:city":"Volketswil",
    "sg:orig_category":"Handel mit Automobilen",
    "sg:postcode":"8604",
    "sg:province":"Z\u00fcrich",
    "wof:name":"Garage G. Zell Gmbh",
    "wof:placetype":"venue"
},
  "geometry": {"coordinates":[8.6897258759,47.3896369934],"type":"Point"}
}