{
  "type": "Feature",
  "properties": {
    "iso:country":"CH",
    "sg:address":"Industrie Nord 7204 Untervaz. Postfach",
    "sg:city":"Untervaz",
    "sg:orig_category":"Bauingenieurb\u00fcros allgemein",
    "sg:phone":"+41 81 322 49 59",
    "sg:postcode":"7204",
    "sg:province":"Graubunden",
    "wof:name":"Hans G\u00f6pfert Ingenieurb\u00fcro",
    "wof:placetype":"venue"
},
  "geometry": {"coordinates":[9.555341,46.919895],"type":"Point"}
}