{
  "type": "Feature",
  "properties": {
    "addr:full":"Steinhofstrasse 4-6 Burgdorf Bern 3400",
    "addr:housenumber":"4-6",
    "addr:postcode":"3400",
    "addr:street":"Steinhofstrasse",
    "iso:country":"CH",
    "sg:address":"Steinhofstrasse 4-6",
    "sg:city":"Burgdorf",
    "sg:orig_category":"Bauschreinerei Herstellung von Konstruktionsteilen, Fertigbauteilen U Ausbauelementen aus Holz",
    "sg:postcode":"3400",
    "sg:province":"Bern",
    "wof:name":"Markus Fust Schreinerei",
    "wof:placetype":"venue"
},
  "geometry": {"coordinates":[9.057013,47.463078],"type":"Point"}
}