{
  "type": "Feature",
  "properties": {
    "iso:country":"CH",
    "sg:address":"Valmont Chemin 168 1260 Nyon. Postfach",
    "sg:city":"Nyon",
    "sg:orig_category":"Non-Classified Establishments",
    "sg:postcode":"1260",
    "sg:province":"Vaud",
    "wof:name":"Copriger Sa",
    "wof:placetype":"venue"
},
  "geometry": {"coordinates":[6.2212958336,46.3811149597],"type":"Point"}
}