{
  "type": "Feature",
  "properties": {
    "iso:country":"CH",
    "sg:address":"S\u00e4ntisstrasse 4 Ebmatingen 8124 Maur. Postfach",
    "sg:city":"Ebmatingen",
    "sg:orig_category":"Kauf U Verkauf von Immobilien auf eigene Rechnung",
    "sg:phone":"+41 27 475 31 65",
    "sg:postcode":"8123",
    "sg:province":"Z\u00fcrich",
    "wof:name":"Casada Jimmy.",
    "wof:placetype":"venue"
},
  "geometry": {"coordinates":[7.6151399612,46.1528205872],"type":"Point"}
}