{
  "type": "Feature",
  "properties": {
    "iso:country":"CH",
    "sg:address":"Route D'echallens 32 1032 Romanel-s-lausanne Case Postale 97",
    "sg:city":"Romanel-s-lausanne",
    "sg:orig_category":"Herstellung von Bier Mineralquellen, Herstellung von alkoholfreien Getr\u00e4nken",
    "sg:phone":"+41 21 646 53 63",
    "sg:postcode":"1032",
    "sg:province":"Vaud",
    "wof:name":"Brasserie Boxer",
    "wof:placetype":"venue"
},
  "geometry": {"coordinates":[6.6049871445,46.5690307617],"type":"Point"}
}