{
  "type": "Feature",
  "properties": {
    "iso:country":"CH",
    "sg:address":"Seftigenstrasse 264",
    "sg:city":"Wabern",
    "sg:orig_category":"Landesverteidigung, Sozialversicherung \u00d6ffentliche Verwaltung",
    "sg:phone":"+41 32 843 44 55",
    "sg:postcode":"3084",
    "sg:province":"Bern",
    "wof:name":"Etablissements & Installations Militaires",
    "wof:placetype":"venue"
},
  "geometry": {"coordinates":[6.8590650558,46.9655685425],"type":"Point"}
}