{
  "type": "Feature",
  "properties": {
    "iso:country":"CH",
    "sg:address":"Sch\u00e4renmoosstrasse 97",
    "sg:city":"Z\u00fcrich",
    "sg:orig_category":"Grosshandel mit Bekleidung Grosshandel mit Textilien",
    "sg:phone":"+41 21 312 92 92",
    "sg:postcode":"8052",
    "sg:province":"Z\u00fcrich",
    "wof:name":"Mgb Sa",
    "wof:placetype":"venue"
},
  "geometry": {"coordinates":[6.6531500816,46.5265808105],"type":"Point"}
}