{
  "type": "Feature",
  "properties": {
    "addr:full":"Gstaldenstrasse 9 9442 Berneck. Postfach 88 Berneck St. Gallen 9442",
    "addr:housenumber":"9;88;st.",
    "addr:postcode":"9442 berneck.;9442",
    "addr:street":"Gstaldenstrasse;Postfach;Berneck",
    "iso:country":"CH",
    "sg:address":"Gstaldenstrasse 9 9442 Berneck. Postfach 88",
    "sg:city":"Berneck",
    "sg:orig_category":"Architektur U Ingenieurb\u00fcros",
    "sg:phone":"+41 32 373 53 28",
    "sg:postcode":"9442",
    "sg:province":"St. Gallen",
    "wof:name":"Dieter Diblitz Ingenieurb\u00fcro",
    "wof:placetype":"venue"
},
  "geometry": {"coordinates":[7.299191,47.116856],"type":"Point"}
}