{
  "type": "Feature",
  "properties": {
    "iso:country":"CH",
    "sg:address":"Kirchgasse 13",
    "sg:city":"Henggart",
    "sg:orig_category":"Massagestudios",
    "sg:phone":"+41 52 316 21 15",
    "sg:postcode":"8444",
    "sg:province":"Z\u00fcrich",
    "wof:name":"Vitalstudio Massagen",
    "wof:placetype":"venue"
},
  "geometry": {"coordinates":[8.6829032898,47.5625610352],"type":"Point"}
}