{
  "type": "Feature",
  "properties": {
    "iso:country":"CH",
    "sg:address":"Guthirtstrasse 10",
    "sg:city":"Z\u00fcrich",
    "sg:classifiers":[
        {
            "category":"Professional",
            "subcategory":"Advertising",
            "type":"Services"
        }
    ],
    "sg:phone":"+41 62 771 12 77",
    "sg:postcode":"8037",
    "sg:province":"Z\u00fcrich",
    "sg:tags":[
        "postcard"
    ],
    "wof:name":"Willy Thurnherr Druckerei",
    "wof:placetype":"venue"
},
  "geometry": {"coordinates":[8.200795,47.26746],"type":"Point"}
}