{
  "type": "Feature",
  "properties": {
    "iso:country":"CH",
    "sg:address":"Hauptstrasse 9",
    "sg:city":"Ligerz",
    "sg:orig_category":"Grosshandel mit Geschenkartikeln U Souvenirs Herstellung von sonstigen Erzeugnissen",
    "sg:phone":"+41 32 315 21 71",
    "sg:postcode":"2514",
    "sg:province":"Bern",
    "wof:name":"Neuhaus, Nachfolger Schl\u00e4fli Peter",
    "wof:placetype":"venue"
},
  "geometry": {"coordinates":[7.1358017921,47.0843772888],"type":"Point"}
}