{
  "type": "Feature",
  "properties": {
    "iso:country":"CH",
    "sg:address":"Oberalpstrasse 87 4054 Basel. Postfach",
    "sg:city":"Basel",
    "sg:orig_category":"Bauingenieurb\u00fcros Sanit\u00e4r Ingenieurb\u00fcros Elektro",
    "sg:phone":"+41 81 302 26 48",
    "sg:postcode":"4015",
    "sg:province":"Basel-Stadt",
    "wof:name":"Espro Ag Elektro-ingenieurb\u00fcro",
    "wof:placetype":"venue"
},
  "geometry": {"coordinates":[9.4977,47.008362],"type":"Point"}
}