{
  "type": "Feature",
  "properties": {
    "iso:country":"CH",
    "sg:address":"Saint-georges Bvd De 34",
    "sg:city":"Gen\u00e8ve",
    "sg:orig_category":"Unternehmensberatung",
    "sg:phone":"+41 22 788 24 20",
    "sg:postcode":"1205",
    "sg:province":"Gen\u00e8ve",
    "wof:name":"Csc Critical Skills Consulting Sa",
    "wof:placetype":"venue"
},
  "geometry": {"coordinates":[6.1339907646,46.2011909485],"type":"Point"}
}