{
  "type": "Feature",
  "properties": {
    "iso:country":"CH",
    "sg:address":"Stadelhoferstrasse 8",
    "sg:city":"Z\u00fcrich",
    "sg:orig_category":"Drogerien Parf\u00fcmerien U sonstiger Detailhandel mit kosmetischen Artikeln U K\u00f6rperpflegemitteln",
    "sg:phone":"+41 12522144",
    "sg:postcode":"8001",
    "sg:province":"Z\u00fcrich",
    "wof:name":"Wernle Ag Drogerien Parfumerien",
    "wof:placetype":"venue"
},
  "geometry": {"coordinates":[8.5482368469,47.3664855957],"type":"Point"}
}