{
  "type": "Feature",
  "properties": {
    "iso:country":"CH",
    "sg:address":"Neuweilerstrasse 49",
    "sg:city":"Allschwil",
    "sg:orig_category":"Sportvereine Sch\u00fctzen Pistolen-& Gewehr",
    "sg:phone":"+41 61 481 21 64",
    "sg:postcode":"4123",
    "sg:province":"Basel-Landschaft",
    "wof:name":"Pistolenklub",
    "wof:placetype":"venue"
},
  "geometry": {"coordinates":[7.531003952,47.5472335815],"type":"Point"}
}