{
  "type": "Feature",
  "properties": {
    "iso:country":"CH",
    "sg:address":"Rue Du Centre 13",
    "sg:city":"Tolochenaz",
    "sg:orig_category":"Druck ohne Zeitungsdruck Offsetdruck",
    "sg:phone":"+41 21 802 47 35",
    "sg:postcode":"1131",
    "sg:province":"Vaud",
    "wof:name":"Imprimerie Chabloz Sa",
    "wof:placetype":"venue"
},
  "geometry": {"coordinates":[6.474132061,46.5050621033],"type":"Point"}
}