{
  "type": "Feature",
  "properties": {
    "iso:country":"CH",
    "sg:address":"Lausanne Route De 7",
    "sg:city":"Rolle",
    "sg:orig_category":"Handel mit Automobilen",
    "sg:phone":"+41 79 433 39 04",
    "sg:postcode":"1180",
    "sg:province":"Vaud",
    "wof:name":"Autos Accident\u00e9es La Ferri\u00e8re, Schafer Daniel",
    "wof:placetype":"venue"
},
  "geometry": {"coordinates":[6.8929100037,47.1429443359],"type":"Point"}
}