{
  "type": "Feature",
  "properties": {
    "iso:country":"CH",
    "sg:address":"Gottardo Via San 111",
    "sg:city":"Balerna",
    "sg:orig_category":"RESTAURANTS: TEA-ROOMS",
    "sg:postcode":"6828",
    "sg:province":"Ticino",
    "wof:name":"Pado Sagl",
    "wof:placetype":"venue"
},
  "geometry": {"coordinates":[9.0016307831,45.8523635864],"type":"Point"}
}