{
  "type": "Feature",
  "properties": {
    "iso:country":"CH",
    "sg:address":"Hammer 27",
    "sg:city":"Aarau",
    "sg:orig_category":"Unternehmensberatung",
    "sg:phone":"+41 62 834 54 43",
    "sg:postcode":"5000",
    "sg:province":"Aargau",
    "wof:name":"Hkg Management Ag",
    "wof:placetype":"venue"
},
  "geometry": {"coordinates":[8.044875145,47.3947029114],"type":"Point"}
}