{
  "type": "Feature",
  "properties": {
    "iso:country":"CH",
    "sg:address":"2813",
    "sg:city":"Ederswiler",
    "sg:classifiers":[
        {
            "category":"Restaurant",
            "type":"Food & Drink"
        }
    ],
    "sg:phone":"+41 56 664 11 16",
    "sg:postcode":"2813",
    "sg:province":"Jura",
    "wof:name":"Restaurant Rebstock",
    "wof:placetype":"venue"
},
  "geometry": {"coordinates":[8.3174819946,47.2825775146],"type":"Point"}
}