{
  "type": "Feature",
  "properties": {
    "iso:country":"CH",
    "sg:address":"Bleicherstrasse 11",
    "sg:city":"Luzern",
    "sg:orig_category":"Architektur U Ingenieurb\u00fcros Architekturb\u00fcros",
    "sg:phone":"+41 41 228 19 19",
    "sg:postcode":"6003",
    "sg:province":"Luzern",
    "wof:name":"H\u00e4usermann + Partner Architekten Ag",
    "wof:placetype":"venue"
},
  "geometry": {"coordinates":[8.307413,47.044498],"type":"Point"}
}