{
  "type": "Feature",
  "properties": {
    "iso:country":"CH",
    "sg:address":"Kriegacker Str. 91",
    "sg:city":"Muttenz",
    "sg:classifiers":[
        {
            "category":"Professional",
            "type":"Services"
        }
    ],
    "sg:phone":"+41 32 968 78 28",
    "sg:postcode":"4132",
    "sg:province":"Basel-Landschaft",
    "sg:tags":[
        "transport",
        "road"
    ],
    "wof:name":"Tanner Et Fils",
    "wof:placetype":"venue"
},
  "geometry": {"coordinates":[6.8419771194,47.0939598083],"type":"Point"}
}