{
  "type": "Feature",
  "properties": {
    "iso:country":"CH",
    "sg:address":"Zone Industrielle",
    "sg:city":"Ecl\u00e9pens",
    "sg:classifiers":[
        {
            "category":"Manufacturing",
            "subcategory":"Rubber & Plastics",
            "type":"Manufacturing & Wholesale Goods"
        }
    ],
    "sg:phone":"+41 21 866 06 66",
    "sg:postcode":"1312",
    "sg:province":"Vaud",
    "sg:tags":[
        "pipe",
        "piping"
    ],
    "wof:name":"Plastag S.a.",
    "wof:placetype":"venue"
},
  "geometry": {"coordinates":[6.5289797783,46.6511039734],"type":"Point"}
}