{
  "type": "Feature",
  "properties": {
    "iso:country":"CH",
    "sg:address":"Poststrasse 7 4500 Solothurn. Postfach",
    "sg:city":"Solothurn",
    "sg:orig_category":"Grosshandel mit Getreide, Saatgut U Futtermitteln",
    "sg:postcode":"4500",
    "sg:province":"Solothurn",
    "wof:name":"Saatzuchtgenossenschaft Solothurn",
    "wof:placetype":"venue"
},
  "geometry": {"coordinates":[7.5323348045,47.206577301],"type":"Point"}
}