{
  "type": "Feature",
  "properties": {
    "iso:country":"CH",
    "sg:address":"Haldenstrasse 5 6340 Baar. Postfach",
    "sg:city":"Baar",
    "sg:orig_category":"Unclassifiable Establishments",
    "sg:postcode":"6340",
    "sg:province":"Zug",
    "wof:name":"Gr\u00f6blhammer Holding Ag Beteiligungen Usw",
    "wof:placetype":"venue"
},
  "geometry": {"coordinates":[8.5383815765,47.1966171265],"type":"Point"}
}