{
  "type": "Feature",
  "properties": {
    "iso:country":"CH",
    "sg:address":"Hagenfirst 5317 Hettenschwil. Postfach",
    "sg:city":"Hettenschwil",
    "sg:orig_category":"Haltung von Rindern",
    "sg:postcode":"5317",
    "sg:province":"Aargau",
    "wof:name":"Fleckviehzuchtgenossenschaft Leuk",
    "wof:placetype":"venue"
},
  "geometry": {"coordinates":[7.6346597672,46.3163299561],"type":"Point"}
}