{
  "type": "Feature",
  "properties": {
    "iso:country":"CH",
    "sg:address":"8708",
    "sg:city":"M\u00e4nnedorf",
    "sg:orig_category":"Erschliessung von Grundst\u00fccken",
    "sg:postcode":"8708",
    "sg:province":"Z\u00fcrich",
    "wof:name":"Bau-& Wohngen.uf Dorf",
    "wof:placetype":"venue"
},
  "geometry": {"coordinates":[8.6905107498,47.253944397],"type":"Point"}
}