{
  "type": "Feature",
  "properties": {
    "iso:country":"CH",
    "sg:address":"Criblet 7 Et Rue De Romont 15 1700 Fribourg. Postfach",
    "sg:city":"Fribourg",
    "sg:classifiers":[
        {
            "category":"Travel",
            "subcategory":"Hotels & Motels",
            "type":"Entertainment"
        }
    ],
    "sg:postcode":"1701",
    "sg:province":"Fribourg",
    "sg:tags":[
        "hotels",
        "mit",
        "restaurant"
    ],
    "wof:name":"Baeriswyl-eggertswyler Marie Louise",
    "wof:placetype":"venue"
},
  "geometry": {"coordinates":[7.1536831856,46.8037452698],"type":"Point"}
}