{
  "type": "Feature",
  "properties": {
    "iso:country":"CH",
    "sg:address":"Steffisburgstrasse 5",
    "sg:city":"Thun",
    "sg:orig_category":"Erbringung von Dienstleistungen f\u00fcr Unternehmen",
    "sg:phone":"+41 33 223 37 84",
    "sg:postcode":"3600",
    "sg:province":"Bern",
    "wof:name":"Umhang Ernst, Inhaber Erwin Heis.",
    "wof:placetype":"venue"
},
  "geometry": {"coordinates":[7.6297821999,46.7621002197],"type":"Point"}
}