{
  "type": "Feature",
  "properties": {
    "addr:full":"Eichtalstrasse 8634 Hombrechtikon. Postfach 163 Hombrechtikon Z\u00fcrich 8634",
    "addr:housenumber":"163",
    "addr:postcode":"8634 hombrechtikon.;8634",
    "addr:street":"Eichtalstrasse;Postfach",
    "iso:country":"CH",
    "sg:address":"Eichtalstrasse 8634 Hombrechtikon. Postfach 163",
    "sg:city":"Hombrechtikon",
    "sg:orig_category":"Datenverarbeitungsdienste",
    "sg:phone":"+41 55 244 51 10",
    "sg:postcode":"8634",
    "sg:province":"Z\u00fcrich",
    "wof:name":"W. Reichenberger Reiconsulting Edv-beratung",
    "wof:placetype":"venue"
},
  "geometry": {"coordinates":[8.77396,47.249287],"type":"Point"}
}