{
  "type": "Feature",
  "properties": {
    "iso:country":"CH",
    "sg:address":"Rue De Bernex 289",
    "sg:city":"Bernex",
    "sg:classifiers":[
        {
            "category":"Shopping",
            "subcategory":"Clothing, Apparel, & Fashions",
            "type":"Retail Goods"
        }
    ],
    "sg:phone":"+41 22 757 04 02",
    "sg:postcode":"1233",
    "sg:province":"Gen\u00e8ve",
    "sg:tags":[
        "children's",
        "clothing"
    ],
    "wof:name":"Kis Textile-services Sa",
    "wof:placetype":"venue"
},
  "geometry": {"coordinates":[6.074115,46.175724],"type":"Point"}
}