{
  "type": "Feature",
  "properties": {
    "iso:country":"CH",
    "sg:address":"Buchserstrasse 32",
    "sg:city":"Aarau",
    "sg:orig_category":"Detailhandel mit Brillen U anderen Sehhilfen",
    "sg:phone":"+41 62 822 05 37",
    "sg:postcode":"5000",
    "sg:province":"Aargau",
    "wof:name":"Hansj\u00f6rg Bauhofer Brillenspezialgesch\u00e4ft",
    "wof:placetype":"venue"
},
  "geometry": {"coordinates":[8.060255,47.390835],"type":"Point"}
}