{
  "type": "Feature",
  "properties": {
    "iso:country":"CH",
    "sg:address":"Girardstrasse 66",
    "sg:city":"Grenchen",
    "sg:orig_category":"Detailhandel mit Waren verschiedener Art, Hauptrichtung Nahrungsmittel",
    "sg:phone":"+41 32 652 17 34",
    "sg:postcode":"2540",
    "sg:province":"Solothurn",
    "wof:name":"Landi,landw. Genossenschaft Grenchen & Umgebung",
    "wof:placetype":"venue"
},
  "geometry": {"coordinates":[7.4000821114,47.1896972656],"type":"Point"}
}