{
  "type": "Feature",
  "properties": {
    "iso:country":"CH",
    "sg:address":"Steinackerstrasse 39 8902 Urdorf. Postfach",
    "sg:city":"Urdorf",
    "sg:orig_category":"S\u00e4ge, Hobel U Holzimpr\u00e4gnierwerke",
    "sg:phone":"+41 17361050",
    "sg:postcode":"8902",
    "sg:province":"Z\u00fcrich",
    "wof:name":"Impregna Gmbh Korrosionsschutz Freileitungsunterhalt",
    "wof:placetype":"venue"
},
  "geometry": {"coordinates":[8.420715332,47.3945465088],"type":"Point"}
}