{
  "type": "Feature",
  "properties": {
    "iso:country":"CH",
    "sg:address":"2501 Biel/bienne Case Postale 68",
    "sg:city":"Biel/bienne",
    "sg:orig_category":"Politische Parteien FDP",
    "sg:phone":"+41 34 445 10 60",
    "sg:postcode":"2501",
    "sg:province":"Bern",
    "wof:name":"Fdp Amt Burgdorf",
    "wof:placetype":"venue"
},
  "geometry": {"coordinates":[7.5876817703,47.0886306763],"type":"Point"}
}