{
  "type": "Feature",
  "properties": {
    "iso:country":"CH",
    "sg:address":"Baarerstrasse 8",
    "sg:city":"Zug",
    "sg:orig_category":"Datenverarbeitungsdienste",
    "sg:phone":"+41 32 372 18 60",
    "sg:postcode":"6300",
    "sg:province":"Zug",
    "wof:name":"Elogistics Ag Lagerf\u00fchrung, Verarbeitung, Verpackung U. Versand Von Artikel Usw.",
    "wof:placetype":"venue"
},
  "geometry": {"coordinates":[7.266592,47.123047],"type":"Point"}
}