{
  "type": "Feature",
  "properties": {
    "addr:full":"Kengelwiesstrasse 5 Tann Z\u00fcrich 8632",
    "addr:housenumber":"5",
    "addr:postcode":"8632",
    "addr:street":"Kengelwiesstrasse",
    "iso:country":"CH",
    "sg:address":"Kengelwiesstrasse 5",
    "sg:city":"Tann",
    "sg:orig_category":"Architektur U Ingenieurb\u00fcros",
    "sg:postcode":"8632",
    "sg:province":"Z\u00fcrich",
    "wof:name":"Macchi Caesar Dipl. Bauingenieur Eth/sia",
    "wof:placetype":"venue"
},
  "geometry": {"coordinates":[8.283905,47.455791],"type":"Point"}
}