{
  "type": "Feature",
  "properties": {
    "iso:country":"CH",
    "sg:address":"Lerchenweg 9",
    "sg:city":"Kloten",
    "sg:orig_category":"Bezirks, Sekundar, Realschulen, Oberstufe der Primarschulen",
    "sg:phone":"+41 17812030",
    "sg:postcode":"8302",
    "sg:province":"Z\u00fcrich",
    "wof:name":"Oberstufenschule Steinacher",
    "wof:placetype":"venue"
},
  "geometry": {"coordinates":[8.64415,47.243431],"type":"Point"}
}