{
  "type": "Feature",
  "properties": {
    "iso:country":"CH",
    "sg:address":"Industriestrasse 18",
    "sg:city":"Veltheim",
    "sg:classifiers":[
        {
            "category":"Manufacturing",
            "subcategory":"Tools & Machinery",
            "type":"Manufacturing & Wholesale Goods"
        }
    ],
    "sg:phone":"+41 56 463 69 69",
    "sg:postcode":"5106",
    "sg:province":"Aargau",
    "sg:tags":[
        "machining",
        "hard",
        "metal",
        "internal",
        "external"
    ],
    "wof:name":"Deni Ag",
    "wof:placetype":"venue"
},
  "geometry": {"coordinates":[8.1576557159,47.4346466064],"type":"Point"}
}