{
  "type": "Feature",
  "properties": {
    "iso:country":"CH",
    "sg:address":"Dorfplatz 6 6383 Dallenwil. Postfach",
    "sg:city":"Dallenwil",
    "sg:orig_category":"Architektur U Ingenieurb\u00fcros Architekturb\u00fcros",
    "sg:phone":"+41 55 619 56 00",
    "sg:postcode":"6383",
    "sg:province":"Nidwalden",
    "wof:name":"Architekturb\u00fcro Jud Peter Gmbh",
    "wof:placetype":"venue"
},
  "geometry": {"coordinates":[9.054515,47.172451],"type":"Point"}
}