{
  "type": "Feature",
  "properties": {
    "iso:country":"CH",
    "sg:address":"B\u00fchlstrasse 1",
    "sg:city":"Zollikerberg",
    "sg:orig_category":"Unclassifiable Establishments",
    "sg:postcode":"8125",
    "sg:province":"Z\u00fcrich",
    "wof:name":"Omd Optimm Media Direction Ag",
    "wof:placetype":"venue"
},
  "geometry": {"coordinates":[8.6062870026,47.3473014832],"type":"Point"}
}