{
  "type": "Feature",
  "properties": {
    "iso:country":"CH",
    "sg:address":"2943",
    "sg:city":"Vendlincourt",
    "sg:orig_category":"Detailhandel mit Textilien Detailhandel mit Waren verschiedener Art, Hauptrichtung Nahrungsmittel",
    "sg:phone":"+41 32 474 44 91",
    "sg:postcode":"2943",
    "sg:province":"Jura",
    "wof:name":"Raymond Pouillard Epicerie Mercerie",
    "wof:placetype":"venue"
},
  "geometry": {"coordinates":[7.1505169868,47.4510688782],"type":"Point"}
}