{
  "type": "Feature",
  "properties": {
    "iso:country":"CH",
    "sg:address":"Parkstrasse 6",
    "sg:city":"Frenkendorf",
    "sg:orig_category":"HERSTELLUNG VON GER\u00c4TEN DER ELEKTRIZIT\u00c4TSERZEUGUNG, -VERTEILUNG U.\u00c4 Mechanische Werkst\u00e4tten",
    "sg:phone":"+41 32 731 25 75",
    "sg:postcode":"4402",
    "sg:province":"Basel-Landschaft",
    "wof:name":"Microm\u00e9canique Soci\u00e9t\u00e9 De M\u00e9trologie",
    "wof:placetype":"venue"
},
  "geometry": {"coordinates":[6.898725,46.988636],"type":"Point"}
}