{
  "type": "Feature",
  "properties": {
    "iso:country":"CH",
    "sg:address":"Wilstrasse 1",
    "sg:city":"D\u00fcbendorf",
    "sg:orig_category":"Nationale Postdienste",
    "sg:phone":"+41 71 393 15 66",
    "sg:postcode":"8600",
    "sg:province":"Z\u00fcrich",
    "wof:name":"Die Schweizerische Post Flawil 1",
    "wof:placetype":"venue"
},
  "geometry": {"coordinates":[9.1877880096,47.4137496948],"type":"Point"}
}