{
  "type": "Feature",
  "properties": {
    "iso:country":"CH",
    "sg:address":"Sports Avenue Des 13",
    "sg:city":"Yverdon-les-bains",
    "sg:orig_category":"Herstellung von Karosserien U Anh\u00e4ngern",
    "sg:phone":"+41 32 967 50 00",
    "sg:postcode":"1400",
    "sg:province":"Vaud",
    "wof:name":"Carrosserie B. Perinetti",
    "wof:placetype":"venue"
},
  "geometry": {"coordinates":[6.839381218,47.1071662903],"type":"Point"}
}