{
  "type": "Feature",
  "properties": {
    "iso:country":"CH",
    "sg:address":"Rue Du Fort-barreau 23",
    "sg:city":"Gen\u00e8ve",
    "sg:orig_category":"Detailhandel mit Bekleidung Detailhandel mit Sportartikeln",
    "sg:phone":"+41 24 492 32 18",
    "sg:postcode":"1201",
    "sg:province":"Gen\u00e8ve",
    "wof:name":"Jacky Sports",
    "wof:placetype":"venue"
},
  "geometry": {"coordinates":[7.153517,46.351875],"type":"Point"}
}