{
  "type": "Feature",
  "properties": {
    "iso:country":"CH",
    "sg:address":"Rue Des Vollandes 13",
    "sg:city":"Gen\u00e8ve",
    "sg:classifiers":[
        {
            "category":"Communications",
            "subcategory":"Film & Video Production",
            "type":"Services"
        }
    ],
    "sg:phone":"+41 22 736 99 66",
    "sg:postcode":"1207",
    "sg:province":"Gen\u00e8ve",
    "sg:tags":[
        "videofilmherstellung",
        "u"
    ],
    "wof:name":"Monique Gr\u00f6bli Production De Films",
    "wof:placetype":"venue"
},
  "geometry": {"coordinates":[6.1606311798,46.2051353455],"type":"Point"}
}