{
  "type": "Feature",
  "properties": {
    "iso:country":"CH",
    "sg:address":"Via Magoria 8",
    "sg:city":"Bellinzona",
    "sg:orig_category":"Detailhandel mit Brillen U anderen Sehhilfen Fachdetailhandel in Verkaufsr\u00e4umen",
    "sg:phone":"+41 91 835 53 33",
    "sg:postcode":"6500",
    "sg:province":"Ticino",
    "wof:name":"Studio Ottico Cervo Sa",
    "wof:placetype":"venue"
},
  "geometry": {"coordinates":[9.024135,46.191074],"type":"Point"}
}