{
  "type": "Feature",
  "properties": {
    "addr:full":"Bruggerstrasse 38 5400 Baden. Postfach 525 Baden Aargau 5400",
    "addr:housenumber":"38;525",
    "addr:postcode":"5400;5400",
    "addr:street":"Bruggerstrasse;Postfach",
    "iso:country":"CH",
    "sg:address":"Bruggerstrasse 38 5400 Baden. Postfach 525",
    "sg:city":"Baden",
    "sg:orig_category":"Arbeitnehmerverb\u00e4nde",
    "sg:postcode":"5400",
    "sg:province":"Aargau",
    "wof:name":"Angestelltenverband Der Asea Brown Boveri Ag",
    "wof:placetype":"venue"
},
  "geometry": {"coordinates":[8.304968,47.476883],"type":"Point"}
}