{
  "type": "Feature",
  "properties": {
    "iso:country":"CH",
    "sg:address":"9545",
    "sg:city":"W\u00e4ngi",
    "sg:orig_category":"Interessenvertretungen",
    "sg:postcode":"9545",
    "sg:province":"Thurgau",
    "wof:name":"Stiftung Ostschweizer Medienpreis Verleihung Von Preisen Zur F\u00f6rderung U. Unterst\u00fctzung Des Qualit\u00e4tsjournalismus Usw",
    "wof:placetype":"venue"
},
  "geometry": {"coordinates":[9.3652887344,47.4241447449],"type":"Point"}
}