{
  "type": "Feature",
  "properties": {
    "addr:full":"Wesemlinstrasse 15 Luzern Luzern 6006",
    "addr:housenumber":"15",
    "addr:postcode":"6006",
    "addr:street":"Wesemlinstrasse",
    "iso:country":"CH",
    "sg:address":"Wesemlinstrasse 15",
    "sg:city":"Luzern",
    "sg:orig_category":"Arztpraxen",
    "sg:phone":"+41 41 410 15 44",
    "sg:postcode":"6006",
    "sg:province":"Luzern",
    "wof:name":"Dr.med.annemarie B\u00fchler Spezial\u00e4rztin Fmh",
    "wof:placetype":"venue"
},
  "geometry": {"coordinates":[8.309785,47.060242],"type":"Point"}
}