{
  "type": "Feature",
  "properties": {
    "iso:country":"CH",
    "sg:address":"Studhaldenh\u00f6he 18",
    "sg:city":"Luzern",
    "sg:orig_category":"Sportvereine Sch\u00fctzen",
    "sg:phone":"+41 41 360 76 22",
    "sg:postcode":"6005",
    "sg:province":"Luzern",
    "wof:name":"Helvetia-sch\u00fctzenges.luzern",
    "wof:placetype":"venue"
},
  "geometry": {"coordinates":[8.3257780075,47.0360221863],"type":"Point"}
}