{
  "type": "Feature",
  "properties": {
    "iso:country":"CH",
    "sg:address":"Zona S. Giovanni 3",
    "sg:city":"Capolago",
    "sg:orig_category":"Zimmerei, Dachdeckerei, Bauspenglerei U Abdichtung",
    "sg:postcode":"6825",
    "sg:province":"Ticino",
    "wof:name":"Fratelli Colombo Sagl",
    "wof:placetype":"venue"
},
  "geometry": {"coordinates":[8.9767541885,45.897567749],"type":"Point"}
}