{
  "type": "Feature",
  "properties": {
    "iso:country":"CH",
    "sg:address":"1514",
    "sg:city":"Bussy-sur-moudon",
    "sg:orig_category":"Sanit\u00e4r, Heizungs U L\u00fcftungsinstallation Sanit\u00e4rinstallation",
    "sg:phone":"+41 21 905 24 69",
    "sg:postcode":"1514",
    "sg:province":"Vaud",
    "wof:name":"Christian Gillabert Inst.sanitaires & Chauffages",
    "wof:placetype":"venue"
},
  "geometry": {"coordinates":[6.8088698387,46.6912117004],"type":"Point"}
}