{
  "type": "Feature",
  "properties": {
    "iso:country":"CH",
    "sg:address":"Dufourstrasse 50 4000 Basel. Postfach",
    "sg:city":"Basel",
    "sg:orig_category":"Pensionskassen",
    "sg:postcode":"4052",
    "sg:province":"Basel-Stadt",
    "wof:name":"Gemeinschaftsstiftung Der Coop Versicherung",
    "wof:placetype":"venue"
},
  "geometry": {"coordinates":[7.5951957703,47.551864624],"type":"Point"}
}