{
  "type": "Feature",
  "properties": {
    "addr:full":"Lang\u00e4gertenstrasse 20 Zollikerberg Z\u00fcrich 8125",
    "addr:housenumber":"20",
    "addr:postcode":"8125",
    "addr:street":"Langaegertenstrasse",
    "iso:country":"CH",
    "sg:address":"Lang\u00e4gertenstrasse 20",
    "sg:city":"Zollikerberg",
    "sg:orig_category":"Arztpraxen",
    "sg:phone":"+41 31 839 53 00",
    "sg:postcode":"8125",
    "sg:province":"Z\u00fcrich",
    "wof:name":"Dr.med.rudolf E. Fetscherin Spezialarzt Fmh",
    "wof:placetype":"venue"
},
  "geometry": {"coordinates":[7.530528,46.930557],"type":"Point"}
}