{
  "type": "Feature",
  "properties": {
    "iso:country":"CH",
    "sg:address":"M\u00fchlehof 6",
    "sg:city":"Herisau",
    "sg:classifiers":[
        {
            "category":"Professional",
            "subcategory":"Engineering",
            "type":"Services"
        }
    ],
    "sg:phone":"+41 71 350 07 55",
    "sg:postcode":"9100",
    "sg:province":"Appenzell Ausserrhoden",
    "sg:tags":[
        "organizational",
        "information",
        "consulting",
        "technology"
    ],
    "wof:name":"Ren\u00e9 M\u00fcller Edv Consulting",
    "wof:placetype":"venue"
},
  "geometry": {"coordinates":[9.2727508545,47.3841323853],"type":"Point"}
}