{
  "type": "Feature",
  "properties": {
    "iso:country":"CH",
    "sg:address":"Kirchgasse 1",
    "sg:city":"Herzogenbuchsee",
    "sg:classifiers":[
        {
            "category":"Restaurant",
            "type":"Food & Drink"
        }
    ],
    "sg:phone":"+41 62 961 60 31",
    "sg:postcode":"3360",
    "sg:province":"Bern",
    "wof:name":"Restaurant Kreuz",
    "wof:placetype":"venue"
},
  "geometry": {"coordinates":[7.7064838409,47.1881217957],"type":"Point"}
}