{
  "type": "Feature",
  "properties": {
    "iso:country":"CH",
    "sg:address":"B\u00f6sch 23",
    "sg:city":"H\u00fcnenberg",
    "sg:orig_category":"Elektroinstallation",
    "sg:phone":"+41 22 300 35 35",
    "sg:postcode":"6331",
    "sg:province":"Zug",
    "wof:name":"Vernet Sa Entreprise G\u00e9n.d'\u00e9lectricit\u00e9",
    "wof:placetype":"venue"
},
  "geometry": {"coordinates":[6.1461629868,46.185836792],"type":"Point"}
}