{
  "type": "Feature",
  "properties": {
    "iso:country":"CH",
    "sg:address":"Kleinh\u00fcningerstrasse 162",
    "sg:city":"Basel",
    "sg:orig_category":"Hoch U Tiefbau",
    "sg:phone":"+41 61 631 08 45",
    "sg:postcode":"4057",
    "sg:province":"Basel-Stadt",
    "wof:name":"Egeler Lutz Ag Baugesch\u00e4ft",
    "wof:placetype":"venue"
},
  "geometry": {"coordinates":[7.5909929276,47.5795593262],"type":"Point"}
}