{
  "type": "Feature",
  "properties": {
    "iso:country":"CH",
    "sg:address":"Gerbergasse 48 4001 Basel. Postfach 711",
    "sg:city":"Basel",
    "sg:orig_category":"Advokaturb\u00fcros",
    "sg:phone":"+41 61 261 18 88",
    "sg:postcode":"4001",
    "sg:province":"Basel-Stadt",
    "wof:name":"Dr.markus B\u00fcrgin Advokaturb\u00fcro",
    "wof:placetype":"venue"
},
  "geometry": {"coordinates":[7.588547,47.555817],"type":"Point"}
}