{
  "type": "Feature",
  "properties": {
    "iso:country":"CH",
    "sg:address":"Altstetterstrasse 289 8047 Z\u00fcrich. Postfach 464",
    "sg:city":"Albisrieden",
    "sg:orig_category":"Detailhandel mit Teppichen Verlegen von Fussboden",
    "sg:phone":"+41 14925292",
    "sg:postcode":"8047",
    "sg:province":"Z\u00fcrich",
    "wof:name":"Marco Bianchera Innendekorationen",
    "wof:placetype":"venue"
},
  "geometry": {"coordinates":[8.4834623337,47.3778800964],"type":"Point"}
}