{
  "type": "Feature",
  "properties": {
    "iso:country":"CH",
    "sg:address":"Am Bruggrain 1",
    "sg:city":"Reinach",
    "sg:classifiers":[
        {
            "category":"Home & Garden",
            "subcategory":"Furniture",
            "type":"Retail Goods"
        }
    ],
    "sg:phone":"+41 61 717 66 00",
    "sg:postcode":"4153",
    "sg:province":"Basel-Landschaft",
    "sg:tags":[
        "household",
        "wood"
    ],
    "wof:name":"Lipo M\u00d6belposten Ag",
    "wof:placetype":"venue"
},
  "geometry": {"coordinates":[7.6001458168,47.48878479],"type":"Point"}
}