{
  "type": "Feature",
  "properties": {
    "iso:country":"CH",
    "sg:address":"G\u00e9n\u00e9ral-guisan Avenue 9",
    "sg:city":"Pully",
    "sg:orig_category":"Werbung",
    "sg:postcode":"1009",
    "sg:province":"Vaud",
    "wof:name":"Wpmp Sa",
    "wof:placetype":"venue"
},
  "geometry": {"coordinates":[6.6566710472,46.5065841675],"type":"Point"}
}