{
  "type": "Feature",
  "properties": {
    "iso:country":"CH",
    "sg:address":"Rinderwaldstrasse 53",
    "sg:city":"Achseten",
    "sg:orig_category":"Grosshandel mit lebenden Tieren",
    "sg:phone":"+41 33 673 17 52",
    "sg:postcode":"3725",
    "sg:province":"Bern",
    "wof:name":"Gilgian Schmid Viehhandel",
    "wof:placetype":"venue"
},
  "geometry": {"coordinates":[7.5972189903,46.5278053284],"type":"Point"}
}