{
  "type": "Feature",
  "properties": {
    "iso:country":"CH",
    "sg:address":"4442",
    "sg:city":"Diepflingen",
    "sg:orig_category":"Vorschulen, Kinderg\u00e4rten",
    "sg:phone":"+41 61 816 90 49",
    "sg:postcode":"4442",
    "sg:province":"Basel-Landschaft",
    "wof:name":"Kindergarten",
    "wof:placetype":"venue"
},
  "geometry": {"coordinates":[7.8421502113,47.4449806213],"type":"Point"}
}