{
  "type": "Feature",
  "properties": {
    "iso:country":"CH",
    "sg:address":"Hasenbergstrasse 39",
    "sg:city":"Steinhausen",
    "sg:orig_category":"Non-Classified Establishments",
    "sg:phone":"+41 56 470 32 90",
    "sg:postcode":"6312",
    "sg:province":"Zug",
    "wof:name":"Familienrestaurant Mcdonalds",
    "wof:placetype":"venue"
},
  "geometry": {"coordinates":[8.289773941,47.4522094727],"type":"Point"}
}