{
  "type": "Feature",
  "properties": {
    "iso:country":"CH",
    "sg:address":"Steinackerstrasse 39",
    "sg:city":"Kloten",
    "sg:orig_category":"Pensionskassen",
    "sg:phone":"+41 18143644",
    "sg:postcode":"8302",
    "sg:province":"Z\u00fcrich",
    "wof:name":"Personalvorsorgestiftung Der Hochstrasser Haustechnik Ag",
    "wof:placetype":"venue"
},
  "geometry": {"coordinates":[8.6013317108,47.4482078552],"type":"Point"}
}