{
  "type": "Feature",
  "properties": {
    "iso:country":"CH",
    "sg:address":"Hasli 56c",
    "sg:city":"Riggisberg",
    "sg:orig_category":"Hoch U Tiefbau",
    "sg:phone":"+41 31 809 15 66",
    "sg:postcode":"3132",
    "sg:province":"Bern",
    "wof:name":"Andres Botta Baugesch\u00e4ft Gmbh",
    "wof:placetype":"venue"
},
  "geometry": {"coordinates":[7.4761800766,46.8206291199],"type":"Point"}
}