{
  "type": "Feature",
  "properties": {
    "iso:country":"CH",
    "sg:address":"Seestrasse 79",
    "sg:city":"Kastanienbaum",
    "sg:orig_category":"Technische, physikalische U chemische Untersuchung",
    "sg:postcode":"6047",
    "sg:province":"Luzern",
    "wof:name":"Ebs Expertenb\u00fcro Sch\u00fcpbach Gmbh Schadenanalyse U. Wertsch\u00e4tzungen Im Bereiche Von Fahrzeugen Usw.",
    "wof:placetype":"venue"
},
  "geometry": {"coordinates":[7.5690069199,46.9266777039],"type":"Point"}
}