{
  "type": "Feature",
  "properties": {
    "addr:full":"Cendrier Rue Du 18 1201 Gen\u00e8ve. Postfach Gen\u00e8ve Gen\u00e8ve 1201",
    "addr:postcode":"1201;postfach;1201",
    "addr:street":"Rue Du 18",
    "iso:country":"CH",
    "sg:address":"Cendrier Rue Du 18 1201 Gen\u00e8ve. Postfach",
    "sg:city":"Gen\u00e8ve",
    "sg:orig_category":"Detailhandel mit B\u00fcchern, Zeitungen, Schreib U Papeteriewaren",
    "sg:postcode":"1201",
    "sg:province":"Gen\u00e8ve",
    "wof:name":"Kaid Idir Kiosque De Tabacs-journaux",
    "wof:placetype":"venue"
},
  "geometry": {"coordinates":[6.145188,46.207279],"type":"Point"}
}