{
  "type": "Feature",
  "properties": {
    "iso:country":"CH",
    "sg:address":"Martinsberg Wiesenstrasse 32",
    "sg:city":"Baden",
    "sg:orig_category":"H\u00f6here Fachschulen",
    "sg:phone":"+41 56 203 10 50",
    "sg:postcode":"5400",
    "sg:province":"Aargau",
    "wof:name":"Fachhochschule Aargau Bereich Wirtschaft",
    "wof:placetype":"venue"
},
  "geometry": {"coordinates":[8.3020277023,47.475730896],"type":"Point"}
}