{
  "type": "Feature",
  "properties": {
    "iso:country":"CH",
    "sg:address":"Via Lucchini 8",
    "sg:city":"Lugano",
    "sg:orig_category":"Effektenvermittlung U verwaltung Vermittlung von Immobilien",
    "sg:phone":"+41 22 301 01 94",
    "sg:postcode":"6900",
    "sg:province":"Ticino",
    "wof:name":"Immo-virtuel Associ\u00e9s",
    "wof:placetype":"venue"
},
  "geometry": {"coordinates":[6.1397547722,46.1816978455],"type":"Point"}
}