{
  "type": "Feature",
  "properties": {
    "iso:country":"CH",
    "sg:address":"Frohberg 7",
    "sg:city":"Richterswil",
    "sg:orig_category":"Detailhandel mit M\u00f6beln U Haushaltsgegenst\u00e4nden",
    "sg:phone":"+41 14003934",
    "sg:postcode":"8805",
    "sg:province":"Z\u00fcrich",
    "wof:name":"Elmer Wohnart Agentur Gmbh",
    "wof:placetype":"venue"
},
  "geometry": {"coordinates":[8.4601354599,47.3635139465],"type":"Point"}
}