{
  "type": "Feature",
  "properties": {
    "iso:country":"CH",
    "sg:address":"Langenmattstrasse 18",
    "sg:city":"M\u00f6nchaltorf",
    "sg:orig_category":"Handel mit Automobilen",
    "sg:postcode":"8617",
    "sg:province":"Z\u00fcrich",
    "wof:name":"Schulz-executive-cars,-generalimport, Tr\u00fcmmel Gerhard",
    "wof:placetype":"venue"
},
  "geometry": {"coordinates":[8.7196540833,47.316280365],"type":"Point"}
}