{
  "type": "Feature",
  "properties": {
    "iso:country":"CH",
    "sg:address":"Piazza De Capitani 10",
    "sg:city":"Locarno",
    "sg:orig_category":"Politische Parteien FDP",
    "sg:phone":"+41 91 745 39 39",
    "sg:postcode":"6600",
    "sg:province":"Ticino",
    "wof:name":"Partito Liberale Radicale",
    "wof:placetype":"venue"
},
  "geometry": {"coordinates":[8.7945861816,46.1699409485],"type":"Point"}
}