{
  "type": "Feature",
  "properties": {
    "addr:full":"6563 Mesocco Graubunden 6563",
    "addr:housenumber":"6563",
    "addr:postcode":"6563",
    "addr:street":"Mesocco Graubunden",
    "iso:country":"CH",
    "sg:address":"6563",
    "sg:city":"Mesocco",
    "sg:orig_category":"Darlehenskassen U Raiffeisenbanken",
    "sg:phone":"+41 91 831 15 75",
    "sg:postcode":"6563",
    "sg:province":"Graubunden",
    "wof:name":"Banca Raiffeisen Di Mesocco",
    "wof:placetype":"venue"
},
  "geometry": {"coordinates":[9.2329,46.391632],"type":"Point"}
}