{
  "type": "Feature",
  "properties": {
    "iso:country":"CH",
    "sg:address":"Luzernerstrasse 14",
    "sg:city":"Weggis",
    "sg:orig_category":"Wirtschaftspr\u00fcfung, Steuerberatung U Treuhand",
    "sg:postcode":"6353",
    "sg:province":"Luzern",
    "wof:name":"M\u00f6schler Treuhand-immo Gmbh",
    "wof:placetype":"venue"
},
  "geometry": {"coordinates":[8.4321489334,47.0325202942],"type":"Point"}
}