{
  "type": "Feature",
  "properties": {
    "iso:country":"CH",
    "sg:address":"Chemin De L'eglise",
    "sg:city":"Meyriez",
    "sg:orig_category":"Detailhandel mit Blumen U Pflanzen",
    "sg:phone":"+41 26 670 21 56",
    "sg:postcode":"3280",
    "sg:province":"Fribourg",
    "wof:name":"Ren\u00e9 Gander Blumen",
    "wof:placetype":"venue"
},
  "geometry": {"coordinates":[7.111383,46.924393],"type":"Point"}
}