{
  "type": "Feature",
  "properties": {
    "iso:country":"CH",
    "sg:address":"Lindenstrasse 38",
    "sg:city":"Reussb\u00fchl",
    "sg:orig_category":"Unclassifiable Establishments",
    "sg:postcode":"6015",
    "sg:province":"Luzern",
    "wof:name":"Lebensmittel 'jelena' Jezdic",
    "wof:placetype":"venue"
},
  "geometry": {"coordinates":[8.2855119705,47.0593795776],"type":"Point"}
}