{
  "type": "Feature",
  "properties": {
    "iso:country":"CH",
    "sg:address":"Sternenstrasse 12",
    "sg:city":"Z\u00fcrich",
    "sg:orig_category":"Handelsvermittlung U Grosshandel Herstellung von Papier, Karton U Pappe",
    "sg:phone":"+41 71 923 63 84",
    "sg:postcode":"8002",
    "sg:province":"Z\u00fcrich",
    "wof:name":"Kk-l\u00fcftungs Ag",
    "wof:placetype":"venue"
},
  "geometry": {"coordinates":[9.0346240997,47.4517211914],"type":"Point"}
}