{
  "type": "Feature",
  "properties": {
    "iso:country":"CH",
    "sg:address":"Sch\u00e4racherweg 1",
    "sg:city":"Oberweningen",
    "sg:orig_category":"Herstellung von landwirtschaftlichen Maschinen",
    "sg:phone":"+41 18562133",
    "sg:postcode":"8165",
    "sg:province":"Z\u00fcrich",
    "wof:name":"Hans Peter Zimmermann Gascoigne-melotte Vertretung",
    "wof:placetype":"venue"
},
  "geometry": {"coordinates":[8.4071083069,47.502658844],"type":"Point"}
}