{
  "type": "Feature",
  "properties": {
    "iso:country":"CH",
    "sg:address":"Hans-hugi-strasse 7",
    "sg:city":"Biel/bienne",
    "sg:orig_category":"Kosmetikinstitute",
    "sg:phone":"+41 79 429 20 61",
    "sg:postcode":"2502",
    "sg:province":"Bern",
    "wof:name":"Sandra Botrugno Institut Espace Bien-\u00eatre",
    "wof:placetype":"venue"
},
  "geometry": {"coordinates":[6.7350077629,47.0534057617],"type":"Point"}
}