{
  "type": "Feature",
  "properties": {
    "iso:country":"CH",
    "sg:address":"Utengasse 44",
    "sg:city":"Basel",
    "sg:orig_category":"Unternehmensberatung",
    "sg:phone":"+41 61 690 67 67",
    "sg:postcode":"4058",
    "sg:province":"Basel-Stadt",
    "wof:name":"Europartner Pfau Claude",
    "wof:placetype":"venue"
},
  "geometry": {"coordinates":[7.5935640335,47.5595626831],"type":"Point"}
}