{
  "type": "Feature",
  "properties": {
    "iso:country":"CH",
    "sg:address":"Seestrasse 119",
    "sg:city":"Zollikon",
    "sg:orig_category":"Sportvereine Renn-& Reitsport",
    "sg:phone":"+41 13962591",
    "sg:postcode":"8702",
    "sg:province":"Z\u00fcrich",
    "wof:name":"Z\u00fcrcher Polo Club Fista Finanzier.-& Handels Ag",
    "wof:placetype":"venue"
},
  "geometry": {"coordinates":[8.5717277527,47.3325119019],"type":"Point"}
}