{
  "type": "Feature",
  "properties": {
    "iso:country":"CH",
    "sg:address":"Zelgmatt 6",
    "sg:city":"Gr\u00fcningen",
    "sg:orig_category":"Saunas, Solarien, Fitnesszentren U \u00e4hnliches",
    "sg:postcode":"8627",
    "sg:province":"Z\u00fcrich",
    "wof:name":"Mega Sun Solariumcenter Wirth & Lips",
    "wof:placetype":"venue"
},
  "geometry": {"coordinates":[8.7571229935,47.2813720703],"type":"Point"}
}