{
  "type": "Feature",
  "properties": {
    "iso:country":"CH",
    "sg:address":"Masescha 133",
    "sg:city":"Triesenberg",
    "sg:classifiers":[
        {
            "category":"Restaurant",
            "type":"Food & Drink"
        }
    ],
    "sg:postcode":"9497",
    "wof:name":"Bergrestaurant Masescha",
    "wof:placetype":"venue"
},
  "geometry": {"coordinates":[9.5436315536,47.1319160461],"type":"Point"}
}