{
  "type": "Feature",
  "properties": {
    "iso:country":"CH",
    "sg:address":"Flurstr. 43",
    "sg:city":"Hagendorn",
    "sg:classifiers":[
        {
            "category":"Home & Garden",
            "subcategory":"Furniture",
            "type":"Retail Goods"
        }
    ],
    "sg:phone":"+41 41 785 50 00",
    "sg:postcode":"6332",
    "sg:province":"Zug",
    "sg:tags":[
        "household",
        "wood"
    ],
    "wof:name":"Bartscher Ag",
    "wof:placetype":"venue"
},
  "geometry": {"coordinates":[8.4298830032,47.2030639648],"type":"Point"}
}