{
  "type": "Feature",
  "properties": {
    "iso:country":"CH",
    "sg:address":"Susenbergstrasse 143 8044 Z\u00fcrich. Postfach",
    "sg:city":"Z\u00fcrich",
    "sg:orig_category":"Finanzierungsinstitutionen",
    "sg:postcode":"8044",
    "sg:province":"Z\u00fcrich",
    "wof:name":"P.m.e.-holding Ag Finanzierung, Beteiligung; Erwerb U. Verwaltung Usw.",
    "wof:placetype":"venue"
},
  "geometry": {"coordinates":[8.5592632294,47.3844566345],"type":"Point"}
}