{
  "type": "Feature",
  "properties": {
    "iso:country":"CH",
    "sg:address":"Bahnhofstrasse",
    "sg:city":"Willisau",
    "sg:classifiers":[
        {
            "category":"Banks & Credit Unions",
            "subcategory":"Bank",
            "type":"Services"
        }
    ],
    "sg:phone":"+41 4145811212",
    "sg:postcode":"6130",
    "sg:province":"Luzern",
    "wof:name":"Volksbank Willisau",
    "wof:placetype":"venue"
},
  "geometry": {"coordinates":[7.992884,47.122223],"type":"Point"}
}