{
  "type": "Feature",
  "properties": {
    "iso:country":"CH",
    "sg:address":"Rue De La Gare 34",
    "sg:city":"Nyon",
    "sg:classifiers":[
        {
            "category":"Government",
            "subcategory":"Post Office",
            "type":"Public Place"
        }
    ],
    "sg:phone":"+41 22 361 29 75",
    "sg:postcode":"1260",
    "sg:province":"Vaud",
    "sg:tags":[
        "caf\u00e9s",
        "tea-rooms"
    ],
    "wof:name":"Bar \u00e0 Caf\u00e9 Le Magot",
    "wof:placetype":"venue"
},
  "geometry": {"coordinates":[6.2363710403,46.3831329346],"type":"Point"}
}