{
  "type": "Feature",
  "properties": {
    "iso:country":"CH",
    "sg:address":"Rheinfelderstrasse 119",
    "sg:city":"Olsberg",
    "sg:orig_category":"Softwareentwicklung U beratung",
    "sg:phone":"+41 18335514",
    "sg:postcode":"4305",
    "sg:province":"Aargau",
    "wof:name":"Alphasoft Computer Ag",
    "wof:placetype":"venue"
},
  "geometry": {"coordinates":[8.6438646317,47.412311554],"type":"Point"}
}