{
  "type": "Feature",
  "properties": {
    "iso:country":"CH",
    "sg:address":"1837",
    "sg:city":"Ch\u00e2teau-d'oex",
    "sg:classifiers":[
        {
            "category":"Education",
            "subcategory":"Vocational School",
            "type":"Public Place"
        }
    ],
    "sg:phone":"+41 26 924 69 03",
    "sg:postcode":"1837",
    "sg:tags":[
        "koch-",
        "haushaltschulen"
    ],
    "wof:name":"Ecole M\u00e9nag\u00e8re Du Pays-d'enhaut",
    "wof:placetype":"venue"
},
  "geometry": {"coordinates":[0.6858400106,45.2460517883],"type":"Point"}
}