{
  "type": "Feature",
  "properties": {
    "addr:full":"N\u00f6schikonerstrasse 11 Niederhasli Z\u00fcrich 8155",
    "addr:housenumber":"11",
    "addr:postcode":"8155",
    "addr:street":"Noeschikonerstrasse",
    "iso:country":"CH",
    "sg:address":"N\u00f6schikonerstrasse 11",
    "sg:city":"Niederhasli",
    "sg:orig_category":"Detailhandel mit Blumen U Pflanzen Fachdetailhandel in Verkaufsr\u00e4umen",
    "sg:phone":"+41 41 885 19 20",
    "sg:postcode":"8155",
    "sg:province":"Z\u00fcrich",
    "wof:name":"Blumenhaus Niederhasli Blueme-stil Gmbh",
    "wof:placetype":"venue"
},
  "geometry": {"coordinates":[8.484757,47.483059],"type":"Point"}
}