{
  "type": "Feature",
  "properties": {
    "iso:country":"CH",
    "sg:address":"6713",
    "sg:city":"Malvaglia",
    "sg:orig_category":"Detailhandel mit Fleisch U Fleischwaren",
    "sg:phone":"+41 91 864 11 54",
    "sg:postcode":"6713",
    "sg:province":"Ticino",
    "wof:name":"Maspero Gianluigi",
    "wof:placetype":"venue"
},
  "geometry": {"coordinates":[8.9068098068,46.3802680969],"type":"Point"}
}