{
  "type": "Feature",
  "properties": {
    "iso:country":"CH",
    "sg:address":"Luzernstrasse 2",
    "sg:city":"Huttwil",
    "sg:orig_category":"Erbringung von Dienstleistungen f\u00fcr Unternehmen Verlegen von Fussboden",
    "sg:phone":"+41 62 962 14 31",
    "sg:postcode":"4950",
    "sg:province":"Bern",
    "wof:name":"Fl\u00fcckiger J\u00f6rg, Innendekorationen",
    "wof:placetype":"venue"
},
  "geometry": {"coordinates":[7.8510570526,47.1134262085],"type":"Point"}
}