{
  "type": "Feature",
  "properties": {
    "iso:country":"CH",
    "sg:address":"Riesern 56",
    "sg:city":"Gais",
    "sg:orig_category":"Unclassifiable Establishments",
    "sg:phone":"+41 71 793 21 24",
    "sg:postcode":"9056",
    "sg:province":"Appenzell Ausserrhoden",
    "wof:name":"Metis Ag",
    "wof:placetype":"venue"
},
  "geometry": {"coordinates":[9.4485273361,47.3624992371],"type":"Point"}
}