{
  "type": "Feature",
  "properties": {
    "iso:country":"CH",
    "sg:address":"Fief-de-chapitre Ch. Du 10",
    "sg:city":"Petit-lancy",
    "sg:orig_category":"Unclassifiable Establishments",
    "sg:postcode":"1213",
    "sg:province":"Gen\u00e8ve",
    "wof:name":"J. P. Grand-guillaume-perrenoud & Partenaire - Consultants",
    "wof:placetype":"venue"
},
  "geometry": {"coordinates":[6.1231307983,46.1955490112],"type":"Point"}
}