{
  "type": "Feature",
  "properties": {
    "iso:country":"CH",
    "sg:address":"Linseb\u00fchlstrasse 14",
    "sg:city":"St.gallen",
    "sg:orig_category":"Unclassifiable Establishments",
    "sg:postcode":"9000",
    "sg:province":"St. Gallen",
    "wof:name":"Frewy Parkett Gmbh",
    "wof:placetype":"venue"
},
  "geometry": {"coordinates":[9.3808050156,47.4242210388],"type":"Point"}
}