{
  "type": "Feature",
  "properties": {
    "iso:country":"CH",
    "sg:address":"Oberwilerstrasse 35",
    "sg:city":"Berikon",
    "sg:orig_category":"Sonstige Aktivit\u00e4ten der nicht-\u00e4rztlichen Medizinalberufe",
    "sg:phone":"+41 56 633 26 53",
    "sg:postcode":"8965",
    "sg:province":"Aargau",
    "wof:name":"Greta Grunder Massagen & Kinesiologie",
    "wof:placetype":"venue"
},
  "geometry": {"coordinates":[8.3757266998,47.3483924866],"type":"Point"}
}