{
  "type": "Feature",
  "properties": {
    "iso:country":"CH",
    "sg:address":"Zumikerstrasse 31",
    "sg:city":"Zollikon",
    "sg:orig_category":"Unternehmensberatung",
    "sg:phone":"+41 26 652 51 44",
    "sg:postcode":"8702",
    "sg:province":"Z\u00fcrich",
    "wof:name":"Olivier Bugnon Care Management",
    "wof:placetype":"venue"
},
  "geometry": {"coordinates":[6.9140758514,46.6940689087],"type":"Point"}
}