{
  "type": "Feature",
  "properties": {
    "iso:country":"CH",
    "sg:address":"L\u00e4nggasse 100 3600 Thun. Postfach",
    "sg:city":"Thun",
    "sg:orig_category":"Non-Classified Establishments",
    "sg:phone":"+41 33 223 56 34",
    "sg:postcode":"3600",
    "sg:province":"Bern",
    "wof:name":"Creasign, K\u00fcchler Web-design, Webelemente-design, Web-publishing",
    "wof:placetype":"venue"
},
  "geometry": {"coordinates":[7.6119117737,46.7489204407],"type":"Point"}
}