{
  "type": "Feature",
  "properties": {
    "iso:country":"CH",
    "sg:address":"Sous-les-vignes 10",
    "sg:city":"Buchillon",
    "sg:orig_category":"Sonstige pers\u00f6nliche Dienstleistungen",
    "sg:phone":"+41 21 808 82 20",
    "sg:postcode":"1164",
    "sg:province":"Vaud",
    "wof:name":"Gembler Andreas",
    "wof:placetype":"venue"
},
  "geometry": {"coordinates":[6.4261798859,46.4699821472],"type":"Point"}
}