{
  "type": "Feature",
  "properties": {
    "iso:country":"CH",
    "sg:address":"Hottingerstrasse 21 8032 Z\u00fcrich. Postfach 526",
    "sg:city":"Z\u00fcrich",
    "sg:orig_category":"Advokaturb\u00fcros",
    "sg:phone":"+41 12666500",
    "sg:postcode":"8024",
    "sg:province":"Z\u00fcrich",
    "wof:name":"Henrici Wicki & Guggisberg Rechtsanw\u00e4lte",
    "wof:placetype":"venue"
},
  "geometry": {"coordinates":[8.551997,47.37006],"type":"Point"}
}