{
  "type": "Feature",
  "properties": {
    "iso:country":"CH",
    "sg:address":"6387",
    "sg:city":"Oberrickenbach",
    "sg:classifiers":[
        {
            "category":"Travel",
            "subcategory":"Hotels & Motels",
            "type":"Entertainment"
        }
    ],
    "sg:phone":"+41 81 413 40 10",
    "sg:postcode":"6387",
    "sg:province":"Nidwalden",
    "sg:tags":[
        "hotels",
        "mit",
        "restaurant"
    ],
    "wof:name":"Hotel Post",
    "wof:placetype":"venue"
},
  "geometry": {"coordinates":[9.8005599976,46.7686195374],"type":"Point"}
}