{
  "type": "Feature",
  "properties": {
    "iso:country":"CH",
    "sg:address":"Corraterie Rue De La 26 1204 Gen\u00e8ve. Postfach",
    "sg:city":"Gen\u00e8ve",
    "sg:orig_category":"Non-Classified Establishments",
    "sg:postcode":"1204",
    "sg:province":"Gen\u00e8ve",
    "wof:name":"Soci\u00e9t\u00e9 Immobili\u00e8re Les Hutins J",
    "wof:placetype":"venue"
},
  "geometry": {"coordinates":[6.1436948776,46.2014884949],"type":"Point"}
}