{
  "type": "Feature",
  "properties": {
    "iso:country":"CH",
    "sg:address":"6037 Root. Postfach",
    "sg:city":"Perlen",
    "sg:orig_category":"Instandhaltung U Reparatur von Automobilen",
    "sg:postcode":"6035",
    "sg:province":"Luzern",
    "wof:name":"Suter Marcel, Garage Farnrain.",
    "wof:placetype":"venue"
},
  "geometry": {"coordinates":[8.3884801865,47.1109580994],"type":"Point"}
}