{
  "type": "Feature",
  "properties": {
    "iso:country":"CH",
    "sg:address":"Dufourstrasse 119 8008 Z\u00fcrich. Postfach",
    "sg:city":"Z\u00fcrich",
    "sg:orig_category":"Non-Classified Establishments",
    "sg:phone":"+41 13883886",
    "sg:postcode":"8008",
    "sg:province":"Z\u00fcrich",
    "wof:name":"Carpa Ag",
    "wof:placetype":"venue"
},
  "geometry": {"coordinates":[8.5525140762,47.3580093384],"type":"Point"}
}