{
  "type": "Feature",
  "properties": {
    "iso:country":"CH",
    "sg:address":"Bahnhofstrasse 4",
    "sg:city":"Walenstadt",
    "sg:orig_category":"Vermietung U Verpachtung von eigenen Immobilien",
    "sg:postcode":"8880",
    "sg:province":"St. Gallen",
    "wof:name":"Wimoritz Ag",
    "wof:placetype":"venue"
},
  "geometry": {"coordinates":[9.8377103806,46.4975395203],"type":"Point"}
}