{
  "type": "Feature",
  "properties": {
    "iso:country":"CH",
    "sg:address":"Ahornweg 1",
    "sg:city":"Bern",
    "sg:orig_category":"Chemische Reinigung W\u00e4schereien",
    "sg:phone":"+41 31 301 35 81",
    "sg:postcode":"3012",
    "sg:province":"Bern",
    "wof:name":"Ursula Zimmermann Chem.reinigung & W\u00e4scherei",
    "wof:placetype":"venue"
},
  "geometry": {"coordinates":[7.435018,46.953732],"type":"Point"}
}