{
  "type": "Feature",
  "properties": {
    "iso:country":"CH",
    "sg:address":"Im Sch\u00f6rli 17/19",
    "sg:city":"D\u00fcbendorf",
    "sg:orig_category":"Maschinen and Apparate divers Grosshandel Vermietung von sonstigen Maschinen U Ger\u00e4ten",
    "sg:phone":"+41 18019006",
    "sg:postcode":"8600",
    "sg:province":"Z\u00fcrich",
    "wof:name":"Lift-ex Ag Arbeitsb\u00fchnen Vermiet.& Handel",
    "wof:placetype":"venue"
},
  "geometry": {"coordinates":[8.6382541656,47.3947257996],"type":"Point"}
}