{
  "type": "Feature",
  "properties": {
    "iso:country":"CH",
    "sg:address":"1318",
    "sg:city":"Pompaples",
    "sg:orig_category":"Verwertung von Milch",
    "sg:postcode":"1318",
    "sg:province":"Vaud",
    "wof:name":"Soci\u00e9t\u00e9 De La Fromagerie Du Parc",
    "wof:placetype":"venue"
},
  "geometry": {"coordinates":[6.5584697723,46.9128417969],"type":"Point"}
}