{
  "type": "Feature",
  "properties": {
    "iso:country":"CH",
    "sg:address":"7122",
    "sg:city":"Valendas",
    "sg:orig_category":"Sportvereine Sch\u00fctzen",
    "sg:phone":"+41 81 854 34 00",
    "sg:postcode":"7122",
    "sg:province":"Graubunden",
    "wof:name":"Sch\u00fctzenverein",
    "wof:placetype":"venue"
},
  "geometry": {"coordinates":[9.2821350098,46.7875747681],"type":"Point"}
}