{
  "type": "Feature",
  "properties": {
    "iso:country":"CH",
    "sg:address":"Belpstrasse 3 3074 Muri B. Bern. Postfach",
    "sg:city":"Bern",
    "sg:orig_category":"Unternehmensberatung",
    "sg:postcode":"3007",
    "sg:province":"Bern",
    "wof:name":"Bab Quality Management Gmbh",
    "wof:placetype":"venue"
},
  "geometry": {"coordinates":[8.3148832321,46.9920654297],"type":"Point"}
}