{
  "type": "Feature",
  "properties": {
    "iso:country":"CH",
    "sg:address":"Salzfassstrasse 15 6006 Luzern. Postfach",
    "sg:city":"Luzern",
    "sg:orig_category":"Allgemeinbildende weiterf\u00fchrende Schulen",
    "sg:phone":"+41 79 341 67 12",
    "sg:postcode":"6003",
    "sg:province":"Luzern",
    "wof:name":"Eb Mitarbeiterschulung Badertscher Esther Erwachsenenbildung; Schulung V. Mitarbeitern",
    "wof:placetype":"venue"
},
  "geometry": {"coordinates":[8.345742,47.046501],"type":"Point"}
}