{
  "type": "Feature",
  "properties": {
    "addr:full":"Schwarzenburgstrasse 200 3097 Liebefeld. Postfach Liebefeld Bern 3097",
    "addr:housenumber":"200",
    "addr:postcode":"3097;postfach;3097",
    "addr:street":"Schwarzenburgstrasse",
    "iso:country":"CH",
    "sg:address":"Schwarzenburgstrasse 200 3097 Liebefeld. Postfach",
    "sg:city":"Liebefeld",
    "sg:orig_category":"Architektur U Ingenieurb\u00fcros Architekturb\u00fcros",
    "sg:phone":"+41 71 761 32 33",
    "sg:postcode":"3097",
    "sg:province":"Bern",
    "wof:name":"Mattle Urs Architektur Ag, Oberriet",
    "wof:placetype":"venue"
},
  "geometry": {"coordinates":[9.56194,47.318565],"type":"Point"}
}