{
  "type": "Feature",
  "properties": {
    "iso:country":"CH",
    "sg:address":"Muhlernstrasse 9 3098 K\u00f6niz. Postfach",
    "sg:city":"K\u00f6niz",
    "sg:classifiers":[
        {
            "category":"Restaurant",
            "type":"Food & Drink"
        }
    ],
    "sg:phone":"+41 14927267",
    "sg:postcode":"3098",
    "sg:province":"Bern",
    "sg:tags":[
        "tea-rooms",
        "restaurants"
    ],
    "wof:name":"Bistro, Lovasz P.",
    "wof:placetype":"venue"
},
  "geometry": {"coordinates":[8.4553575516,47.3696136475],"type":"Point"}
}