{
  "type": "Feature",
  "properties": {
    "iso:country":"CH",
    "sg:address":"1115",
    "sg:city":"Vullierens",
    "sg:orig_category":"Herstellung von K\u00fcchenm\u00f6beln",
    "sg:phone":"+41 21 869 95 46",
    "sg:postcode":"1115",
    "sg:province":"Vaud",
    "wof:name":"Urfer Pierre.",
    "wof:placetype":"venue"
},
  "geometry": {"coordinates":[6.482336998,46.5726203918],"type":"Point"}
}