{
  "type": "Feature",
  "properties": {
    "iso:country":"CH",
    "sg:address":"Sulgenrain 27 3007 Bern. Postfach",
    "sg:city":"Bern",
    "sg:orig_category":"Radio U Fernsehanstalten Werbeagenturen",
    "sg:phone":"+41 31 398 38 68",
    "sg:postcode":"3011",
    "sg:province":"Bern",
    "wof:name":"Bewegungsmelder Medien & Kultur Gmbh",
    "wof:placetype":"venue"
},
  "geometry": {"coordinates":[7.4390788078,46.9407463074],"type":"Point"}
}