{
  "type": "Feature",
  "properties": {
    "iso:country":"CH",
    "sg:address":"Route Des Tattes D'oie 5",
    "sg:city":"Nyon",
    "sg:orig_category":"Druck ohne Zeitungsdruck Offsetdruck",
    "sg:phone":"+41 22 361 62 33",
    "sg:postcode":"1260",
    "sg:province":"Vaud",
    "wof:name":"Claude Uldry Imprimerie",
    "wof:placetype":"venue"
},
  "geometry": {"coordinates":[6.2390799522,46.382358551],"type":"Point"}
}