{
  "type": "Feature",
  "properties": {
    "iso:country":"CH",
    "sg:address":"N\u00fcnenenweg 16",
    "sg:city":"Riggisberg",
    "sg:orig_category":"G\u00fcterbef\u00f6rderung im Strassenverkehr",
    "sg:phone":"+41 31 809 31 59",
    "sg:postcode":"3132",
    "sg:province":"Bern",
    "wof:name":"Kropf Martin",
    "wof:placetype":"venue"
},
  "geometry": {"coordinates":[7.4828147888,46.8091278076],"type":"Point"}
}