{
  "type": "Feature",
  "properties": {
    "iso:country":"CH",
    "sg:address":"Ch\u00fcngengass 6",
    "sg:city":"Richterswil",
    "sg:classifiers":[
        {
            "category":"Education",
            "subcategory":"Library",
            "type":"Public Place"
        }
    ],
    "sg:phone":"+41 17850078",
    "sg:postcode":"8805",
    "sg:province":"Z\u00fcrich",
    "sg:tags":[
        "u",
        "bibliotheken",
        "archive"
    ],
    "wof:name":"Pestalozzi-bibliothek- Richterswil",
    "wof:placetype":"venue"
},
  "geometry": {"coordinates":[8.70563,47.209011],"type":"Point"}
}