{
  "type": "Feature",
  "properties": {
    "iso:country":"CH",
    "sg:address":"La Cl\u00e9-des-champs 1372 Bavois. Postfach",
    "sg:city":"Bavois",
    "sg:orig_category":"Fussboden, Fliesen U Plattenlegerei, Tapeziererei",
    "sg:phone":"+41 24 441 53 62",
    "sg:postcode":"1372",
    "sg:province":"Vaud",
    "wof:name":"Seletto Parquet Parquets; Pose, Pon\u00e7age Etc",
    "wof:placetype":"venue"
},
  "geometry": {"coordinates":[6.5647950172,46.6787147522],"type":"Point"}
}