{
  "type": "Feature",
  "properties": {
    "iso:country":"CH",
    "sg:address":"Bogenstrasse 13",
    "sg:city":"St.gallen",
    "sg:orig_category":"Handel mit Automobilen",
    "sg:phone":"+41 32 373 30 40",
    "sg:postcode":"9000",
    "sg:province":"St. Gallen",
    "wof:name":"Houmard Automobile",
    "wof:placetype":"venue"
},
  "geometry": {"coordinates":[7.2761597633,47.1213417053],"type":"Point"}
}