{
  "type": "Feature",
  "properties": {
    "iso:country":"CH",
    "sg:address":"Lindenstrasse 2",
    "sg:city":"Binningen",
    "sg:orig_category":"Gartenbau",
    "sg:phone":"+41 61 421 28 22",
    "sg:postcode":"4102",
    "sg:province":"Basel-Landschaft",
    "wof:name":"Dieter Bauer G\u00e4rtnerei",
    "wof:placetype":"venue"
},
  "geometry": {"coordinates":[7.5723371506,47.5305404663],"type":"Point"}
}