{
  "type": "Feature",
  "properties": {
    "iso:country":"CH",
    "sg:address":"Hauptstrasse 42",
    "sg:city":"H\u00f6rhausen",
    "sg:orig_category":"Elektroinstallation",
    "sg:phone":"+41 52 763 24 65",
    "sg:postcode":"8507",
    "sg:province":"Thurgau",
    "wof:name":"Ilg & K\u00f6stli Ag",
    "wof:placetype":"venue"
},
  "geometry": {"coordinates":[8.9719657898,47.6329689026],"type":"Point"}
}