{
  "type": "Feature",
  "properties": {
    "iso:country":"CH",
    "sg:address":"M\u00fbriers Chemin Des 1",
    "sg:city":"Aubonne",
    "sg:orig_category":"Non-Classified Establishments",
    "sg:postcode":"1170",
    "sg:province":"Vaud",
    "wof:name":"Pharmacia Enterprises S\u00e0rl",
    "wof:placetype":"venue"
},
  "geometry": {"coordinates":[6.391699791,46.4952468872],"type":"Point"}
}