{
  "type": "Feature",
  "properties": {
    "iso:country":"CH",
    "sg:address":"Engelgasse 119 4052 Basel. Postfach 48",
    "sg:city":"Basel",
    "sg:orig_category":"G\u00fcterbef\u00f6rderung im Strassenverkehr",
    "sg:phone":"+41 61 312 31 41",
    "sg:postcode":"4020",
    "sg:province":"Basel-Stadt",
    "wof:name":"Dtb Transintex Ag",
    "wof:placetype":"venue"
},
  "geometry": {"coordinates":[7.605700016,47.5472335815],"type":"Point"}
}