{
  "type": "Feature",
  "properties": {
    "iso:country":"CH",
    "sg:address":"Stationsstrasse 33 8306 Br\u00fcttisellen. Postfach",
    "sg:city":"Br\u00fcttisellen",
    "sg:orig_category":"Pensionskassen",
    "sg:postcode":"8306",
    "sg:province":"Z\u00fcrich",
    "wof:name":"Personalvorsorgestiftung Der Coca-cola Ag",
    "wof:placetype":"venue"
},
  "geometry": {"coordinates":[8.6243391037,47.4204101562],"type":"Point"}
}