{
  "type": "Feature",
  "properties": {
    "iso:country":"CH",
    "sg:address":"Rue Du Bourg 17",
    "sg:city":"Sierre",
    "sg:orig_category":"Chiropraktik",
    "sg:phone":"+41 27 456 84 05",
    "sg:postcode":"3960",
    "sg:province":"Valais",
    "wof:name":"Dr. Pascale Schmid Chiropraktorin",
    "wof:placetype":"venue"
},
  "geometry": {"coordinates":[7.533834,46.293468],"type":"Point"}
}