{
  "type": "Feature",
  "properties": {
    "iso:country":"CH",
    "sg:address":"Route De Florissant 112",
    "sg:city":"Gen\u00e8ve",
    "sg:orig_category":"Architektur U Ingenieurb\u00fcros",
    "sg:phone":"+41 22 347 97 07",
    "sg:postcode":"1206",
    "sg:province":"Gen\u00e8ve",
    "wof:name":"Fischer Cl. Sa Bureau D'ig\u00e9nieurs Civils",
    "wof:placetype":"venue"
},
  "geometry": {"coordinates":[6.166422,46.190376],"type":"Point"}
}