{
  "type": "Feature",
  "properties": {
    "iso:country":"CH",
    "sg:address":"Zweierstrasse 141",
    "sg:city":"Z\u00fcrich",
    "sg:orig_category":"Arztpraxen",
    "sg:phone":"+41 61 711 50 50",
    "sg:postcode":"8003",
    "sg:province":"Z\u00fcrich",
    "wof:name":"Dr.med.esther Waldmann Spezial\u00e4rztin Fmh",
    "wof:placetype":"venue"
},
  "geometry": {"coordinates":[7.58684,47.493832],"type":"Point"}
}