{
  "type": "Feature",
  "properties": {
    "iso:country":"CH",
    "sg:address":"T\u00e4mperlistrasse 4",
    "sg:city":"F\u00e4llanden",
    "sg:orig_category":"Herstellung von Werkzeugen",
    "sg:phone":"+41 18250307",
    "sg:postcode":"8117",
    "sg:province":"Z\u00fcrich",
    "wof:name":"Werkzeugbau Siegler Georg",
    "wof:placetype":"venue"
},
  "geometry": {"coordinates":[8.6439685822,47.3767471313],"type":"Point"}
}