{
  "type": "Feature",
  "properties": {
    "iso:country":"CH",
    "sg:address":"Ramogna Via Alla 4",
    "sg:city":"Locarno",
    "sg:orig_category":"Non-Classified Establishments",
    "sg:postcode":"6600",
    "sg:province":"Ticino",
    "wof:name":"Mevena Sa",
    "wof:placetype":"venue"
},
  "geometry": {"coordinates":[8.7995786667,46.1711425781],"type":"Point"}
}