{
  "type": "Feature",
  "properties": {
    "iso:country":"CH",
    "sg:address":"Canovastrasse",
    "sg:city":"Thusis",
    "sg:orig_category":"Architekturb\u00fcros",
    "sg:phone":"+41 81 651 21 81",
    "sg:postcode":"7430",
    "sg:province":"Graubunden",
    "wof:name":"Hans Marugg Architekturb\u00fcro",
    "wof:placetype":"venue"
},
  "geometry": {"coordinates":[9.435526,46.69342],"type":"Point"}
}