{
  "type": "Feature",
  "properties": {
    "iso:country":"CH",
    "sg:address":"Regensdorferstrasse 40",
    "sg:city":"D\u00e4llikon",
    "sg:classifiers":[
        {
            "category":"Restaurant",
            "type":"Food & Drink"
        }
    ],
    "sg:phone":"+41 18441115",
    "sg:postcode":"8108",
    "sg:province":"Z\u00fcrich",
    "wof:name":"Restaurant Bistro",
    "wof:placetype":"venue"
},
  "geometry": {"coordinates":[8.4443616867,47.4386978149],"type":"Point"}
}