{
  "type": "Feature",
  "properties": {
    "iso:country":"CH",
    "sg:address":"Dorfstrasse 40",
    "sg:city":"Opfikon",
    "sg:orig_category":"Hochschulen U h\u00f6here Ausbildung",
    "sg:phone":"+41 18101360",
    "sg:postcode":"8152",
    "sg:province":"Z\u00fcrich",
    "wof:name":"Kiebits Gmbh",
    "wof:placetype":"venue"
},
  "geometry": {"coordinates":[8.5768566132,47.4315299988],"type":"Point"}
}