{
  "type": "Feature",
  "properties": {
    "iso:country":"CH",
    "sg:address":"R\u00f6thenbachstrasse 2",
    "sg:city":"Heimenhausen",
    "sg:orig_category":"Mit Sport verbundene T\u00e4tigkeiten",
    "sg:phone":"+41 32 675 54 11",
    "sg:postcode":"3373",
    "sg:province":"Bern",
    "wof:name":"Rudolf & Susanna Widmer Reit-& Fahrbetrieb",
    "wof:placetype":"venue"
},
  "geometry": {"coordinates":[7.6955242157,47.2060432434],"type":"Point"}
}