{
  "type": "Feature",
  "properties": {
    "iso:country":"CH",
    "sg:address":"Regensbergstrasse 35",
    "sg:city":"Boppelsen",
    "sg:orig_category":"Sanit\u00e4r U Heizungsinstallation",
    "sg:phone":"+41 18442464",
    "sg:postcode":"8113",
    "sg:province":"Z\u00fcrich",
    "wof:name":"Jakob Bongni Heizungen Oelfeuerungen",
    "wof:placetype":"venue"
},
  "geometry": {"coordinates":[8.4081220627,47.4689598083],"type":"Point"}
}