{
  "type": "Feature",
  "properties": {
    "addr:full":"Chemin Des Chalets 6 1225 Ch\u00eane-bourg Case Postale 136 Ch\u00eane-bourg Gen\u00e8ve 1225",
    "addr:housenumber":"6",
    "addr:postcode":"1225;1225",
    "addr:street":"Chemin Des Chalets;Postale 136 Che\u0302Ne-Bourg",
    "iso:country":"CH",
    "sg:address":"Chemin Des Chalets 6 1225 Ch\u00eane-bourg Case Postale 136",
    "sg:city":"Ch\u00eane-bourg",
    "sg:orig_category":"Detailhandel mit Antiquit\u00e4ten U Gebrauchtwaren in Verkaufsr\u00e4umen Sonstiger Fachdetailhandel in Verka",
    "sg:phone":"+41 22 349 33 00",
    "sg:postcode":"1225",
    "sg:province":"Gen\u00e8ve",
    "wof:name":"Philnova Sa",
    "wof:placetype":"venue"
},
  "geometry": {"coordinates":[6.197452,46.192158],"type":"Point"}
}