{
  "type": "Feature",
  "properties": {
    "iso:country":"CH",
    "sg:address":"Ismatt 1",
    "sg:city":"Hedingen",
    "sg:orig_category":"Allgemeiner Hoch U Tiefbau",
    "sg:phone":"+41 17601066",
    "sg:postcode":"8908",
    "sg:province":"Z\u00fcrich",
    "wof:name":"Everplan Dennler Eva",
    "wof:placetype":"venue"
},
  "geometry": {"coordinates":[8.433189,47.300648],"type":"Point"}
}