{
  "type": "Feature",
  "properties": {
    "iso:country":"CH",
    "sg:address":"1715",
    "sg:city":"Alterswil",
    "sg:orig_category":"Erschliessung von Grundst\u00fccken",
    "sg:postcode":"1715",
    "sg:province":"Fribourg",
    "wof:name":"Wohn Und Baugenossenschaft Zum Bauernhaus Im Dorf",
    "wof:placetype":"venue"
},
  "geometry": {"coordinates":[7.2517352104,46.7967453003],"type":"Point"}
}