{
  "type": "Feature",
  "properties": {
    "iso:country":"CH",
    "sg:address":"F\u00fcrtenmattestrasse 6",
    "sg:city":"Gr\u00fcnen",
    "sg:orig_category":"Zimmerei, Ingenieurholzbau",
    "sg:phone":"+41 34 431 13 10",
    "sg:postcode":"3455",
    "sg:province":"Bern",
    "wof:name":"Iseli & Trachsel Holzbau Zimmerei & Bedachungen",
    "wof:placetype":"venue"
},
  "geometry": {"coordinates":[7.7347822189,47.0226707458],"type":"Point"}
}