{
  "type": "Feature",
  "properties": {
    "iso:country":"CH",
    "sg:address":"Schulstrasse 16",
    "sg:city":"Goldach",
    "sg:orig_category":"Primarschulen",
    "sg:phone":"+41 79 677 26 60",
    "sg:postcode":"9403",
    "sg:province":"St. Gallen",
    "wof:name":"Schulhaus Rosenacker Primarschule",
    "wof:placetype":"venue"
},
  "geometry": {"coordinates":[9.4668598175,47.4772186279],"type":"Point"}
}