{
  "type": "Feature",
  "properties": {
    "iso:country":"CH",
    "sg:address":"Dorfstr. 3b 9524 Zuzwil Sg. Postfach",
    "sg:city":"Z\u00fcberwangen",
    "sg:orig_category":"Sonstige mit der Informatik verbundene T\u00e4tigkeiten",
    "sg:postcode":"9523",
    "sg:province":"St. Gallen",
    "wof:name":"Sauter Informatik",
    "wof:placetype":"venue"
},
  "geometry": {"coordinates":[9.1234006882,47.4656410217],"type":"Point"}
}