{
  "type": "Feature",
  "properties": {
    "iso:country":"CH",
    "sg:address":"Schaffhauserstrasse 41",
    "sg:city":"Eglisau",
    "sg:orig_category":"Pensionskassen Tankstellen",
    "sg:phone":"+41 18670816",
    "sg:postcode":"8193",
    "sg:province":"Z\u00fcrich",
    "wof:name":"Touring-garage Eglisau Ag",
    "wof:placetype":"venue"
},
  "geometry": {"coordinates":[8.516617775,47.5811920166],"type":"Point"}
}