{
  "type": "Feature",
  "properties": {
    "iso:country":"CH",
    "sg:address":"Z.i. Alcan Division",
    "sg:city":"Chippis",
    "sg:orig_category":"Herstellung von Werkzeugen Mechanische Werkst\u00e4tten",
    "sg:phone":"+41 27 457 56 96",
    "sg:postcode":"3965",
    "sg:province":"Valais",
    "wof:name":"Formtec Ag Formenbau & Mechanik",
    "wof:placetype":"venue"
},
  "geometry": {"coordinates":[7.5415549278,46.2804908752],"type":"Point"}
}