{
  "type": "Feature",
  "properties": {
    "iso:country":"CH",
    "sg:address":"Via Manzoni 19",
    "sg:city":"Mendrisio",
    "sg:orig_category":"Herstellung von Teppichen Verlegen von Fliesen U Platten",
    "sg:phone":"+41 21 903 20 46",
    "sg:postcode":"6850",
    "sg:province":"Ticino",
    "wof:name":"Cherpillod Jean-marc.",
    "wof:placetype":"venue"
},
  "geometry": {"coordinates":[6.7878599167,46.5902786255],"type":"Point"}
}