{
  "type": "Feature",
  "properties": {
    "iso:country":"CH",
    "sg:address":"Lindenstr. 2 4118 Rodersdorf. Postfach",
    "sg:city":"Rodersdorf",
    "sg:orig_category":"Fotografisches Gewerbe U fotografische Laboratorien",
    "sg:postcode":"4118",
    "sg:province":"Solothurn",
    "wof:name":"N\u00fcssli Armin Werbefoto Und Reprografik",
    "wof:placetype":"venue"
},
  "geometry": {"coordinates":[7.4587669373,47.4795379639],"type":"Point"}
}