{
  "type": "Feature",
  "properties": {
    "iso:country":"CH",
    "sg:address":"Hungerb\u00fcelstrasse 22",
    "sg:city":"Frauenfeld",
    "sg:orig_category":"Elektroinstallation",
    "sg:phone":"+41 52 720 87 87",
    "sg:postcode":"8500",
    "sg:province":"Thurgau",
    "wof:name":"Grossenbacher Installationen Ag",
    "wof:placetype":"venue"
},
  "geometry": {"coordinates":[8.8733463287,47.5624771118],"type":"Point"}
}