{
  "type": "Feature",
  "properties": {
    "iso:country":"CH",
    "sg:address":"Avenue De Tourbillon 9 1950 Sion Case Postale 715",
    "sg:city":"Sion",
    "sg:orig_category":"Rebbau",
    "sg:phone":"+41 27 323 24 51",
    "sg:postcode":"1951",
    "sg:province":"Valais",
    "wof:name":"Cave Coop\u00e9rative De Sion & Environs",
    "wof:placetype":"venue"
},
  "geometry": {"coordinates":[7.3602452278,46.2285614014],"type":"Point"}
}