{
  "type": "Feature",
  "properties": {
    "iso:country":"CH",
    "sg:address":"Etzelstrasse 5",
    "sg:city":"Uznach",
    "sg:orig_category":"Innenausbau Zimmerei, Ingenieurholzbau",
    "sg:phone":"+41 81 302 47 91",
    "sg:postcode":"8730",
    "sg:province":"St. Gallen",
    "wof:name":"Josef Widrig Zimmerei & Innenausbau",
    "wof:placetype":"venue"
},
  "geometry": {"coordinates":[9.496468544,47.0064926147],"type":"Point"}
}