{
  "type": "Feature",
  "properties": {
    "addr:full":"Florastrasse 9 Interlaken Bern 3800",
    "addr:housenumber":"9",
    "addr:postcode":"3800",
    "addr:street":"Florastrasse",
    "iso:country":"CH",
    "sg:address":"Florastrasse 9",
    "sg:city":"Interlaken",
    "sg:orig_category":"Bauschreinerei Einbau von Schreinerwaren",
    "sg:phone":"+41 33 822 18 27",
    "sg:postcode":"3800",
    "sg:province":"Bern",
    "wof:name":"Beat Zaugg Schreinerei & Ladenbau",
    "wof:placetype":"venue"
},
  "geometry": {"coordinates":[7.854832,46.683022],"type":"Point"}
}