{
  "type": "Feature",
  "properties": {
    "iso:country":"CH",
    "sg:address":"Kronenstrasse 10",
    "sg:city":"Adliswil",
    "sg:orig_category":"Detailhandel mit Brot, Back U S\u00fcsswaren",
    "sg:postcode":"8134",
    "sg:province":"Z\u00fcrich",
    "wof:name":"B\u00e4ckerei Konditorei Winter S.",
    "wof:placetype":"venue"
},
  "geometry": {"coordinates":[8.526887,47.311749],"type":"Point"}
}