{
  "type": "Feature",
  "properties": {
    "iso:country":"CH",
    "sg:address":"8867",
    "sg:city":"Niederurnen",
    "sg:orig_category":"Landesverteidigung, Sozialversicherung \u00d6ffentliche Verwaltung",
    "sg:phone":"+41 55 617 22 09",
    "sg:postcode":"8867",
    "sg:province":"Glarus",
    "wof:name":"Zivilschutzstelle Niederurnen",
    "wof:placetype":"venue"
},
  "geometry": {"coordinates":[9.052895546,47.1254081726],"type":"Point"}
}