{
  "type": "Feature",
  "properties": {
    "iso:country":"CH",
    "sg:address":"Place Du Tunnel 10",
    "sg:city":"Lausanne",
    "sg:classifiers":[
        {
            "category":"Restaurant",
            "type":"Food & Drink"
        }
    ],
    "sg:phone":"+41 24 492 35 44",
    "sg:postcode":"1005",
    "sg:province":"Vaud",
    "wof:name":"Caf\u00e9 Du Glacier Des Diablerets",
    "wof:placetype":"venue"
},
  "geometry": {"coordinates":[7.1541619301,46.3529930115],"type":"Point"}
}