{
  "type": "Feature",
  "properties": {
    "iso:country":"CH",
    "sg:address":"Sch\u00fctzengasse 54",
    "sg:city":"Biel/bienne",
    "sg:orig_category":"Primarschulen Vorschulen, Kinderg\u00e4rten",
    "sg:phone":"+41 19324455",
    "sg:postcode":"2502",
    "sg:province":"Bern",
    "wof:name":"Rudolf-steiner-schule Z\u00fcrcher Oberland",
    "wof:placetype":"venue"
},
  "geometry": {"coordinates":[8.7826042175,47.3294067383],"type":"Point"}
}