{
  "type": "Feature",
  "properties": {
    "iso:country":"CH",
    "sg:address":"T\u00f6sstalstrasse 23",
    "sg:city":"Kollbrunn",
    "sg:orig_category":"Handel mit Automobilen",
    "sg:postcode":"8483",
    "sg:province":"Z\u00fcrich",
    "wof:name":"Sporting Car, Brahami Serge",
    "wof:placetype":"venue"
},
  "geometry": {"coordinates":[6.1291642189,46.187335968],"type":"Point"}
}