{
  "type": "Feature",
  "properties": {
    "iso:country":"CH",
    "sg:address":"Guggig\u00e4ssli",
    "sg:city":"Frutigen",
    "sg:orig_category":"Vorschulen, Kinderg\u00e4rten",
    "sg:phone":"+41 33 671 34 24",
    "sg:postcode":"3714",
    "sg:province":"Bern",
    "wof:name":"Kindergarten Kanderbr\u00fcck",
    "wof:placetype":"venue"
},
  "geometry": {"coordinates":[7.6536741257,46.5799560547],"type":"Point"}
}