{
  "type": "Feature",
  "properties": {
    "iso:country":"CH",
    "sg:address":"Postgasse 11 3800 Interlaken. Postfach",
    "sg:city":"Interlaken",
    "sg:orig_category":"Sanit\u00e4r, Heizungs U L\u00fcftungsinstallation",
    "sg:phone":"+41 79 656 32 87",
    "sg:postcode":"3800",
    "sg:province":"Bern",
    "wof:name":"M\u00fchlemann, Peter.",
    "wof:placetype":"venue"
},
  "geometry": {"coordinates":[7.8541469574,46.6869926453],"type":"Point"}
}