{
  "type": "Feature",
  "properties": {
    "iso:country":"CH",
    "sg:address":"Aarmattweg 51 3052 Zollikofen. Postfach",
    "sg:city":"Zollikofen",
    "sg:orig_category":"Interessenvertretungen",
    "sg:postcode":"3052",
    "sg:province":"Bern",
    "wof:name":"Tres Soles",
    "wof:placetype":"venue"
},
  "geometry": {"coordinates":[7.4540119171,46.989566803],"type":"Point"}
}