{
  "type": "Feature",
  "properties": {
    "iso:country":"CH",
    "sg:address":"Centre Magro",
    "sg:city":"Uvrier",
    "sg:orig_category":"Detailhandel mit Haustieren U zoologischem Bedarf",
    "sg:phone":"+41 27 203 70 50",
    "sg:postcode":"1958",
    "sg:province":"Valais",
    "wof:name":"Qualipet Ag Haustierbedarfs-center",
    "wof:placetype":"venue"
},
  "geometry": {"coordinates":[7.4116902351,46.2523155212],"type":"Point"}
}