{
  "type": "Feature",
  "properties": {
    "iso:country":"CH",
    "sg:address":"Chemin De La Poste 10",
    "sg:city":"Corminboeuf",
    "sg:orig_category":"Unternehmensberatung",
    "sg:postcode":"1720",
    "sg:province":"Fribourg",
    "wof:name":"Ecoute Et Conseil En Communication S\u00e0rl",
    "wof:placetype":"venue"
},
  "geometry": {"coordinates":[7.0970158577,46.8072624207],"type":"Point"}
}