{
  "type": "Feature",
  "properties": {
    "addr:full":"Bocklerstrasse 37 Z\u00fcrich Z\u00fcrich 8051",
    "addr:housenumber":"37",
    "addr:postcode":"8051",
    "addr:street":"Bocklerstrasse",
    "iso:country":"CH",
    "sg:address":"Bocklerstrasse 37",
    "sg:city":"Z\u00fcrich",
    "sg:orig_category":"Architektur U Ingenieurb\u00fcros Zahntechnische Laboratorien",
    "sg:phone":"+41 13201155",
    "sg:postcode":"8051",
    "sg:province":"Z\u00fcrich",
    "wof:name":"Walter Products",
    "wof:placetype":"venue"
},
  "geometry": {"coordinates":[8.568967,47.402542],"type":"Point"}
}