{
  "type": "Feature",
  "properties": {
    "iso:country":"CH",
    "sg:address":"Trevano Via 7a",
    "sg:city":"Lugano",
    "sg:orig_category":"Sonstige mit der Informatik verbundene T\u00e4tigkeiten",
    "sg:phone":"+41 91 912 27 22",
    "sg:postcode":"6900",
    "sg:province":"Ticino",
    "wof:name":"Walnut Sa",
    "wof:placetype":"venue"
},
  "geometry": {"coordinates":[8.954832077,46.0131225586],"type":"Point"}
}