{
  "type": "Feature",
  "properties": {
    "addr:full":"Freudenfels Eschenz Thurgau 8264",
    "addr:postcode":"8264",
    "iso:country":"CH",
    "sg:address":"Freudenfels",
    "sg:city":"Eschenz",
    "sg:orig_category":"Berufliche Weiterbildung, Erwachsenenbildung Bezirks, Sekundar, Realschulen, Oberstufe der Primarsch",
    "sg:phone":"+41 557723",
    "sg:postcode":"8264",
    "sg:province":"Thurgau",
    "wof:name":"Berufswahl-& Weiterbildungs- Schule Bws Z\u00fcrcher Oberland",
    "wof:placetype":"venue"
},
  "geometry": {"coordinates":[8.815681,47.33252],"type":"Point"}
}