{
  "type": "Feature",
  "properties": {
    "iso:country":"CH",
    "sg:address":"Rue Beau-s\u00e9jour 15 1003 Lausanne. Postfach",
    "sg:city":"Lausanne",
    "sg:orig_category":"Versicherungen Generalagenturen",
    "sg:phone":"+41 81 837 88 00",
    "sg:postcode":"1002",
    "sg:province":"Vaud",
    "wof:name":"Winterthur Versicherung Generalagentur",
    "wof:placetype":"venue"
},
  "geometry": {"coordinates":[9.8386106491,46.497631073],"type":"Point"}
}