{
  "type": "Feature",
  "properties": {
    "iso:country":"CH",
    "sg:address":"Schulhausstrasse 273",
    "sg:city":"Bellikon",
    "sg:orig_category":"Primarschulen",
    "sg:postcode":"5454",
    "sg:province":"Aargau",
    "wof:name":"Primarschule",
    "wof:placetype":"venue"
},
  "geometry": {"coordinates":[8.2703800201,46.9387588501],"type":"Point"}
}