{
  "type": "Feature",
  "properties": {
    "iso:country":"CH",
    "sg:address":"Rue De L'ile Falcon 3960 Sierre Case Postale 195",
    "sg:city":"Sierre",
    "sg:orig_category":"Elektrizit\u00e4tsversorgung",
    "sg:phone":"+41 27 455 22 12",
    "sg:postcode":"3960",
    "sg:province":"Valais",
    "wof:name":"Energie Solaire Sa",
    "wof:placetype":"venue"
},
  "geometry": {"coordinates":[7.550339222,46.2863006592],"type":"Point"}
}