{
  "type": "Feature",
  "properties": {
    "iso:country":"CH",
    "sg:address":"Gerichtsgasse 85",
    "sg:city":"Laufenburg",
    "sg:orig_category":"F\u00fcrsorge\u00e4mter",
    "sg:phone":"+41 61 961 06 06",
    "sg:postcode":"5080",
    "sg:province":"Aargau",
    "wof:name":"Amtsvormundschaft Des Bezirks Waldenburg",
    "wof:placetype":"venue"
},
  "geometry": {"coordinates":[7.7490792274,47.3940467834],"type":"Point"}
}