{
  "type": "Feature",
  "properties": {
    "iso:country":"CH",
    "sg:address":"Via Al Fiume 21",
    "sg:city":"Gordola",
    "sg:classifiers":[
        {
            "category":"Insurance",
            "subcategory":"Insurance Agent",
            "type":"Services"
        }
    ],
    "sg:phone":"+41 91 745 32 60",
    "sg:postcode":"6596",
    "sg:province":"Ticino",
    "sg:tags":[
        "versicherungsagenturen",
        "-broker"
    ],
    "wof:name":"Helvetia Patria Assicurazioni Agenzia",
    "wof:placetype":"venue"
},
  "geometry": {"coordinates":[8.8608732224,46.1785812378],"type":"Point"}
}