{
  "type": "Feature",
  "properties": {
    "iso:country":"CH",
    "sg:address":"S\u00e4delstrasse 29",
    "sg:city":"Gerzensee",
    "sg:orig_category":"Grosshandel mit lebenden Tieren",
    "sg:phone":"+41 27 956 14 17",
    "sg:postcode":"3115",
    "sg:province":"Bern",
    "wof:name":"Siegfried Fux Viehhandel",
    "wof:placetype":"venue"
},
  "geometry": {"coordinates":[7.8158550262,46.1855125427],"type":"Point"}
}