{
  "type": "Feature",
  "properties": {
    "iso:country":"CH",
    "sg:address":"Rue De La Fabrique 2 2016 Cortaillod Case Postale",
    "sg:city":"Cortaillod",
    "sg:orig_category":"Herstellung von Drahtwaren Herstellung von Kunststoffwaren",
    "sg:phone":"+41 32 843 55 55",
    "sg:postcode":"2016",
    "sg:province":"Neuch\u00e2tel",
    "wof:name":"Nexans Suisse Sa",
    "wof:placetype":"venue"
},
  "geometry": {"coordinates":[6.8464298248,46.943031311],"type":"Point"}
}