{
  "type": "Feature",
  "properties": {
    "iso:country":"CH",
    "sg:address":"Oberhausen",
    "sg:city":"Braunau",
    "sg:orig_category":"Landwirtschaft, Jagd U damit verbundene Dienstleistungen",
    "sg:phone":"+41 91 858 30 07",
    "sg:postcode":"9502",
    "sg:province":"Thurgau",
    "wof:name":"Luciano Mocettini Azienda Agricola",
    "wof:placetype":"venue"
},
  "geometry": {"coordinates":[8.9789495468,46.1534805298],"type":"Point"}
}