{
  "type": "Feature",
  "properties": {
    "iso:country":"CH",
    "sg:address":"Rue Gambetta 27 1820 Montreux. Postfach",
    "sg:city":"Clarens",
    "sg:orig_category":"Sonstiger Grosshandel",
    "sg:postcode":"1815",
    "sg:province":"Vaud",
    "wof:name":"Ls Diffusion, J. B\u00fceler",
    "wof:placetype":"venue"
},
  "geometry": {"coordinates":[6.8962650299,46.442237854],"type":"Point"}
}