{
  "type": "Feature",
  "properties": {
    "iso:country":"CH",
    "sg:address":"Rue De Savoie 78 1962 Pont-de-la-morge Case Postale 246",
    "sg:city":"Sion",
    "sg:orig_category":"Notariate",
    "sg:phone":"+41 27 346 20 68",
    "sg:postcode":"1951",
    "sg:province":"Valais",
    "wof:name":"Patricia Clavien Etude D'avocate Et De Notaire",
    "wof:placetype":"venue"
},
  "geometry": {"coordinates":[7.3187122345,46.2250061035],"type":"Point"}
}