{
  "type": "Feature",
  "properties": {
    "iso:country":"CH",
    "sg:address":"Rinderpl\u00e4tzstrasse 26",
    "sg:city":"Willerzell",
    "sg:orig_category":"Datenverarbeitungsdienste Satzherstellung U Reproduktion",
    "sg:phone":"+41 17373406",
    "sg:postcode":"8846",
    "sg:province":"Schwyz",
    "wof:name":"Sterndata Ag",
    "wof:placetype":"venue"
},
  "geometry": {"coordinates":[8.458104,47.358711],"type":"Point"}
}