{
  "type": "Feature",
  "properties": {
    "iso:country":"CH",
    "sg:address":"Via Merlina 3a",
    "sg:city":"Viganello",
    "sg:classifiers":[
        {
            "category":"Banks & Credit Unions",
            "subcategory":"Investment Brokerage",
            "type":"Services"
        }
    ],
    "sg:phone":"+41 91 971 43 10",
    "sg:postcode":"6962",
    "sg:province":"Ticino",
    "sg:tags":[
        "agricultural",
        "disinfectant",
        "cleaning",
        "agent",
        "enterprise"
    ],
    "wof:name":"S & S Service & Service Sa",
    "wof:placetype":"venue"
},
  "geometry": {"coordinates":[8.962395,46.011795],"type":"Point"}
}