{
  "type": "Feature",
  "properties": {
    "iso:country":"CH",
    "sg:address":"Bahnhofstrasse",
    "sg:city":"Zermatt",
    "sg:orig_category":"Detailhandel mit Bekleidung",
    "sg:phone":"+41 91 683 32 86",
    "sg:postcode":"3920",
    "sg:province":"Valais",
    "wof:name":"Sports-wear Antonio Moda Maschile Sagl",
    "wof:placetype":"venue"
},
  "geometry": {"coordinates":[9.017929,45.844406],"type":"Point"}
}