{
  "type": "Feature",
  "properties": {
    "iso:country":"CH",
    "sg:address":"Chamerstrasse 15 6331 H\u00fcnenberg. Postfach 186",
    "sg:city":"H\u00fcnenberg",
    "sg:orig_category":"Non-Classified Establishments",
    "sg:phone":"+41 13815577",
    "sg:postcode":"6331",
    "sg:province":"Zug",
    "wof:name":"Esemtag Ag Beteiligungen Usw",
    "wof:placetype":"venue"
},
  "geometry": {"coordinates":[8.4270572662,47.1775817871],"type":"Point"}
}