{
  "type": "Feature",
  "properties": {
    "addr:full":"Saint-fran\u00e7ois Place 7 Lausanne Vaud 1003",
    "addr:housenumber":"7",
    "addr:postcode":"1003",
    "iso:country":"CH",
    "sg:address":"Saint-fran\u00e7ois Place 7",
    "sg:city":"Lausanne",
    "sg:orig_category":"Detailhandel an Verkaufsst\u00e4nden U auf M\u00e4rkten",
    "sg:postcode":"1003",
    "sg:province":"Vaud",
    "wof:name":"Bazar Vaudois Sa",
    "wof:placetype":"venue"
},
  "geometry": {"coordinates":[6.633218,46.520172],"type":"Point"}
}