{
  "type": "Feature",
  "properties": {
    "iso:country":"CH",
    "sg:address":"Rue Du Sex 57",
    "sg:city":"Sion",
    "sg:orig_category":"Betrieb von Taxis",
    "sg:phone":"+41 27 322 26 71",
    "sg:postcode":"1950",
    "sg:province":"Valais",
    "wof:name":"Taxis A.b.c., Jean Loye",
    "wof:placetype":"venue"
},
  "geometry": {"coordinates":[7.368625,46.233479],"type":"Point"}
}