{
  "type": "Feature",
  "properties": {
    "iso:country":"CH",
    "sg:address":"Berninaplatz 1 8057 Z\u00fcrich. Postfach",
    "sg:city":"Z\u00fcrich",
    "sg:orig_category":"Grosshandel mit Getr\u00e4nken Grosshandel mit Wein U Spirituosen",
    "sg:phone":"+41 18131666",
    "sg:postcode":"8057",
    "sg:province":"Z\u00fcrich",
    "wof:name":"Wegm\u00fcller Gerhard Gmbh",
    "wof:placetype":"venue"
},
  "geometry": {"coordinates":[8.5480651855,47.403137207],"type":"Point"}
}