{
  "type": "Feature",
  "properties": {
    "iso:country":"CH",
    "sg:address":"Grossmannstrasse 25 8049 Z\u00fcrich. Postfach",
    "sg:city":"Z\u00fcrich",
    "sg:orig_category":"Unclassifiable Establishments",
    "sg:phone":"+41 13401000",
    "sg:postcode":"8049",
    "sg:province":"Z\u00fcrich",
    "wof:name":"Interwac Gmbh Beteiligungen Usw",
    "wof:placetype":"venue"
},
  "geometry": {"coordinates":[8.5072546005,47.3958854675],"type":"Point"}
}