{
  "type": "Feature",
  "properties": {
    "iso:country":"CH",
    "sg:address":"Gr\u00e9sy Chemin De 19",
    "sg:city":"Lausanne",
    "sg:orig_category":"Wohnheime",
    "sg:phone":"+41 32 861 26 48",
    "sg:postcode":"1012",
    "sg:province":"Vaud",
    "wof:name":"Fondation Ressource",
    "wof:placetype":"venue"
},
  "geometry": {"coordinates":[6.4908499718,46.8687477112],"type":"Point"}
}