{
  "type": "Feature",
  "properties": {
    "iso:country":"CH",
    "sg:address":"1974",
    "sg:city":"Arbaz",
    "sg:orig_category":"Verkehrs- and Tourismusb\u00fcros",
    "sg:phone":"+41 27 398 36 77",
    "sg:postcode":"1974",
    "sg:province":"Valais",
    "wof:name":"Office Du Tourisme",
    "wof:placetype":"venue"
},
  "geometry": {"coordinates":[7.3841748238,46.273109436],"type":"Point"}
}