{
  "type": "Feature",
  "properties": {
    "iso:country":"CH",
    "sg:address":"Thunstrasse 76 3700 Spiez. Postfach 384",
    "sg:city":"Spiez",
    "sg:orig_category":"Fahrschulen, Flugschulen",
    "sg:phone":"+41 79 211 61 61",
    "sg:postcode":"3700",
    "sg:province":"Bern",
    "wof:name":"Hans-j\u00fcrg Brand Autofahrschule",
    "wof:placetype":"venue"
},
  "geometry": {"coordinates":[7.757589817,46.9491271973],"type":"Point"}
}