{
  "type": "Feature",
  "properties": {
    "iso:country":"CH",
    "sg:address":"Avenue De La Harpe 13",
    "sg:city":"Lausanne",
    "sg:orig_category":"Detailhandel mit Textilien Sonstiger Fachdetailhandel in Verkaufsr\u00e4umen",
    "sg:phone":"+41 21 616 36 75",
    "sg:postcode":"1007",
    "sg:province":"Vaud",
    "wof:name":"Claudine Cottier Sissi Laines Mercerie Lingerie",
    "wof:placetype":"venue"
},
  "geometry": {"coordinates":[6.6258511543,46.5126419067],"type":"Point"}
}