{
  "type": "Feature",
  "properties": {
    "iso:country":"CH",
    "sg:address":"L\u00f6wenmattweg 7",
    "sg:city":"M\u00fcnsingen",
    "sg:orig_category":"Arztpraxen",
    "sg:phone":"+41 31 721 05 55",
    "sg:postcode":"3110",
    "sg:province":"Bern",
    "wof:name":"Dr.med.emanuel Rubeli Arzt F.allgemeine Medizin Fmh",
    "wof:placetype":"venue"
},
  "geometry": {"coordinates":[7.561086,46.880005],"type":"Point"}
}