{
  "type": "Feature",
  "properties": {
    "iso:country":"CH",
    "sg:address":"Campascio 7748 Campascio. Postfach",
    "sg:city":"Campascio",
    "sg:orig_category":"Grosshandel mit Getr\u00e4nken",
    "sg:phone":"+41 79 210 74 16",
    "sg:postcode":"7748",
    "sg:province":"Graubunden",
    "wof:name":"Cav\u00e9 Bernard",
    "wof:placetype":"venue"
},
  "geometry": {"coordinates":[6.9953799248,46.2966117859],"type":"Point"}
}