{
  "type": "Feature",
  "properties": {
    "iso:country":"CH",
    "sg:address":"Peter Merian-strasse 30",
    "sg:city":"Basel",
    "sg:orig_category":"Krankenh\u00e4user Sonderschulen",
    "sg:phone":"+41 61 271 42 72",
    "sg:postcode":"4052",
    "sg:province":"Basel-Stadt",
    "wof:name":"Jufa",
    "wof:placetype":"venue"
},
  "geometry": {"coordinates":[7.5955348015,47.5481529236],"type":"Point"}
}