{
  "type": "Feature",
  "properties": {
    "iso:country":"CH",
    "sg:address":"R\u00f6tistrasse 5",
    "sg:city":"Solothurn",
    "sg:orig_category":"Softwareentwicklung U beratung",
    "sg:phone":"+41 32 344 87 00",
    "sg:postcode":"4500",
    "sg:province":"Solothurn",
    "wof:name":"Ixos Software (international) Ag",
    "wof:placetype":"venue"
},
  "geometry": {"coordinates":[7.2855648994,47.1602210999],"type":"Point"}
}