{
  "type": "Feature",
  "properties": {
    "addr:full":"Hauptstrasse Ermatingen Thurgau 8272",
    "addr:postcode":"8272",
    "addr:street":"Hauptstrasse",
    "iso:country":"CH",
    "sg:address":"Hauptstrasse",
    "sg:city":"Ermatingen",
    "sg:orig_category":"Allgemeiner Hoch U Tiefbau",
    "sg:postcode":"8272",
    "sg:province":"Thurgau",
    "wof:name":"Keller-janett",
    "wof:placetype":"venue"
},
  "geometry": {"coordinates":[8.397466,47.3438],"type":"Point"}
}