{
  "type": "Feature",
  "properties": {
    "iso:country":"CH",
    "sg:address":"B\u00e4rengasse 10",
    "sg:city":"Z\u00fcrich",
    "sg:orig_category":"Parf\u00fcmerien U sonstiger Detailhandel mit kosmetischen Artikeln U K\u00f6rperpflegemitteln",
    "sg:phone":"+41 12117077",
    "sg:postcode":"8001",
    "sg:province":"Z\u00fcrich",
    "wof:name":"Intercoiffure Sommer, Inh. G\u00fcntensperger B. Coiffeursalon Usw",
    "wof:placetype":"venue"
},
  "geometry": {"coordinates":[8.5371713638,47.3700218201],"type":"Point"}
}