{
  "type": "Feature",
  "properties": {
    "iso:country":"CH",
    "sg:address":"Weinbergstrasse 9",
    "sg:city":"Weiach",
    "sg:orig_category":"Schreib U \u00dcbersetzungsb\u00fcros -\u00dcbersetzungsb\u00fcros",
    "sg:phone":"+41 18581321",
    "sg:postcode":"8187",
    "sg:province":"Z\u00fcrich",
    "wof:name":"Herbert Hind Uebersetzungen",
    "wof:placetype":"venue"
},
  "geometry": {"coordinates":[8.4338474274,47.5573234558],"type":"Point"}
}