{
  "type": "Feature",
  "properties": {
    "addr:full":"Dorfstrasse Wengen Bern 3823",
    "addr:postcode":"3823",
    "addr:street":"Dorfstrasse",
    "iso:country":"CH",
    "sg:address":"Dorfstrasse",
    "sg:city":"Wengen",
    "sg:orig_category":"Detailhandel mit Brot, Back U S\u00fcsswaren",
    "sg:phone":"+41 33 855 15 35",
    "sg:postcode":"3823",
    "sg:province":"Bern",
    "wof:name":"Urs Pfluger Ag B\u00e4ckerei-konditorei",
    "wof:placetype":"venue"
},
  "geometry": {"coordinates":[7.9216,46.605194],"type":"Point"}
}