{
  "type": "Feature",
  "properties": {
    "iso:country":"CH",
    "sg:address":"Pralay Chemin De La 12",
    "sg:city":"Creux-de-genthod",
    "sg:orig_category":"Architektur U Ingenieurb\u00fcros",
    "sg:phone":"+41 22 774 32 51",
    "sg:postcode":"1294",
    "sg:province":"Gen\u00e8ve",
    "wof:name":"Alliance East, Thierry Dindeleux",
    "wof:placetype":"venue"
},
  "geometry": {"coordinates":[6.155553,46.264839],"type":"Point"}
}