{
  "type": "Feature",
  "properties": {
    "iso:country":"CH",
    "sg:address":"Haldenstrasse 8",
    "sg:city":"Balterswil",
    "sg:orig_category":"Grosshandel mit Eisenwaren sowie Installationsbedarf f\u00fcr Gas, Wasser U Heizung Grosshandel mit Masch",
    "sg:postcode":"8362",
    "sg:province":"Thurgau",
    "wof:name":"Emb-pumpen Ag",
    "wof:placetype":"venue"
},
  "geometry": {"coordinates":[8.935136795,47.4549980164],"type":"Point"}
}