{
  "type": "Feature",
  "properties": {
    "iso:country":"CH",
    "sg:address":"Chemin Du Vallon 22 1030 Bussigny-lausanne Case Postale 173",
    "sg:city":"Bussigny-lausanne",
    "sg:orig_category":"Herstellung von Metallkonstruktionen",
    "sg:phone":"+41 21 702 27 61",
    "sg:postcode":"1030",
    "sg:province":"Vaud",
    "wof:name":"Constructions M\u00e9talliques Fenaroli Oswald S\u00e0rl",
    "wof:placetype":"venue"
},
  "geometry": {"coordinates":[6.5528059006,46.5439453125],"type":"Point"}
}