{
  "type": "Feature",
  "properties": {
    "iso:country":"CH",
    "sg:address":"Grynaustrasse 5 8730 Uznach. Postfach",
    "sg:city":"Uznach",
    "sg:orig_category":"Gewinnung von Natursteinen f\u00fcr den Bau Herstellung von sonstigen Produkten aus nichtmetallischen Min",
    "sg:phone":"+41 55 280 28 44",
    "sg:postcode":"8730",
    "sg:province":"St. Gallen",
    "wof:name":"De Zanet P. & Co Ag Uznach",
    "wof:placetype":"venue"
},
  "geometry": {"coordinates":[8.9839658737,47.2240982056],"type":"Point"}
}