{
  "type": "Feature",
  "properties": {
    "iso:country":"CH",
    "sg:address":"3215",
    "sg:city":"Gempenach",
    "sg:orig_category":"Verwertung von Milch",
    "sg:postcode":"3215",
    "sg:province":"Fribourg",
    "wof:name":"K\u00e4sereigenossenschaft Lurtigen",
    "wof:placetype":"venue"
},
  "geometry": {"coordinates":[7.1979608536,46.940700531],"type":"Point"}
}