{
  "type": "Feature",
  "properties": {
    "iso:country":"CH",
    "sg:address":"Bernstrasse 36 3175 Flamatt. Postfach",
    "sg:city":"Flamatt",
    "sg:orig_category":"Herstellung von Schreibwaren U B\u00fcrobedarf aus Papier, Karton U Pappe Herstellung von Wellpapier U pa",
    "sg:phone":"+41 31 744 64 64",
    "sg:postcode":"3175",
    "sg:province":"Fribourg",
    "wof:name":"Model Inopac Ag",
    "wof:placetype":"venue"
},
  "geometry": {"coordinates":[7.3186249733,46.8900146484],"type":"Point"}
}