{
  "type": "Feature",
  "properties": {
    "iso:country":"CH",
    "sg:address":"Br\u00fcel 3",
    "sg:city":"Schleitheim",
    "sg:orig_category":"Kinderkrippen U horte",
    "sg:phone":"+41 52 680 19 12",
    "sg:postcode":"8226",
    "sg:province":"Schaffhausen",
    "wof:name":"Kinderhort",
    "wof:placetype":"venue"
},
  "geometry": {"coordinates":[8.486866951,47.747844696],"type":"Point"}
}