{
  "type": "Feature",
  "properties": {
    "iso:country":"CH",
    "sg:address":"B\u00e4renwilerstrasse 14",
    "sg:city":"Langenbruck",
    "sg:orig_category":"Oberfl\u00e4chenveredlung U W\u00e4rmebehandlung",
    "sg:phone":"+41 62 390 12 81",
    "sg:postcode":"4438",
    "sg:province":"Basel-Landschaft",
    "wof:name":"H\u00e4rterei Tschan Ag",
    "wof:placetype":"venue"
},
  "geometry": {"coordinates":[7.7704501152,47.3459625244],"type":"Point"}
}