{
  "type": "Feature",
  "properties": {
    "iso:country":"CH",
    "sg:address":"Viehmarktgasse 1",
    "sg:city":"Laufen",
    "sg:orig_category":"Detailhandel mit Tabakwaren",
    "sg:phone":"+41 61 761 60 83",
    "sg:postcode":"4242",
    "sg:province":"Basel-Landschaft",
    "wof:name":"Tabakwaren Zum T\u00f6rli G.wohlgemuth",
    "wof:placetype":"venue"
},
  "geometry": {"coordinates":[7.5002560616,47.4209213257],"type":"Point"}
}