{
  "type": "Feature",
  "properties": {
    "iso:country":"CH",
    "sg:address":"Hutmatte 6",
    "sg:city":"Biglen",
    "sg:orig_category":"Kaminfeger",
    "sg:phone":"+41 31 701 16 82",
    "sg:postcode":"3507",
    "sg:province":"Bern",
    "wof:name":"Fritz Wermuth Kaminfegergesch\u00e4ft",
    "wof:placetype":"venue"
},
  "geometry": {"coordinates":[7.6207327843,46.9266242981],"type":"Point"}
}