{
  "type": "Feature",
  "properties": {
    "iso:country":"CH",
    "sg:address":"Weidenweg 211",
    "sg:city":"Brig",
    "sg:orig_category":"Bauschreinerei Herstellung von Konstruktionsteilen, Fertigbauteilen U Ausbauelementen aus Holz",
    "sg:phone":"+41 17133189",
    "sg:postcode":"3900",
    "sg:province":"Valais",
    "wof:name":"Schreinerei Schneiter Ag",
    "wof:placetype":"venue"
},
  "geometry": {"coordinates":[8.538246,47.289883],"type":"Point"}
}