{
  "type": "Feature",
  "properties": {
    "iso:country":"CH",
    "sg:address":"Z.i. La Foge 1816 Chailly-montreux Case Postale 89",
    "sg:city":"Chailly-montreux",
    "sg:orig_category":"Architekturb\u00fcros",
    "sg:phone":"+41 21 964 74 77",
    "sg:postcode":"1816",
    "sg:province":"Vaud",
    "wof:name":"Gilles Bellmann Architecte",
    "wof:placetype":"venue"
},
  "geometry": {"coordinates":[6.89248,46.453739],"type":"Point"}
}