{
  "type": "Feature",
  "properties": {
    "iso:country":"CH",
    "sg:address":"M\u00e4ritgasse 1",
    "sg:city":"Zollikofen",
    "sg:orig_category":"Detailhandel mit Waren verschiedener Art, Hauptrichtung Nahrungsmittel",
    "sg:phone":"+41 56 621 01 08",
    "sg:postcode":"3052",
    "sg:province":"Bern",
    "wof:name":"Coop Super Center",
    "wof:placetype":"venue"
},
  "geometry": {"coordinates":[8.2717924118,47.3504600525],"type":"Point"}
}