{
  "type": "Feature",
  "properties": {
    "iso:country":"CH",
    "sg:address":"Dammweg 3",
    "sg:city":"Biel/bienne",
    "sg:orig_category":"Architekturb\u00fcros",
    "sg:phone":"+41 56 460 72 60",
    "sg:postcode":"2502",
    "sg:province":"Bern",
    "wof:name":"Walker Architekten Ag",
    "wof:placetype":"venue"
},
  "geometry": {"coordinates":[8.208816,47.481991],"type":"Point"}
}