{
  "type": "Feature",
  "properties": {
    "iso:country":"CH",
    "sg:address":"Rindermarkt 17",
    "sg:city":"Z\u00fcrich",
    "sg:orig_category":"Detailhandel mit Uhren U Schmuck Kunsthandel",
    "sg:phone":"+41 12526525",
    "sg:postcode":"8001",
    "sg:province":"Z\u00fcrich",
    "wof:name":"Maya Behn-eschenburg Galerie",
    "wof:placetype":"venue"
},
  "geometry": {"coordinates":[8.5447902679,47.3725624084],"type":"Point"}
}