{
  "type": "Feature",
  "properties": {
    "iso:country":"CH",
    "sg:address":"Brand-strasse 18",
    "sg:city":"M\u00fchleberg",
    "sg:orig_category":"S\u00e4ge, Hobel U Holzimpr\u00e4gnierwerke S\u00e4gewerke",
    "sg:phone":"+41 41 497 12 50",
    "sg:postcode":"3203",
    "sg:province":"Bern",
    "wof:name":"Josef & Martin Zurkirchen",
    "wof:placetype":"venue"
},
  "geometry": {"coordinates":[8.1812734604,47.0151748657],"type":"Point"}
}