{
  "type": "Feature",
  "properties": {
    "iso:country":"CH",
    "sg:address":"Teufenerstrasse 42",
    "sg:city":"St.gallen",
    "sg:orig_category":"Non-Classified Establishments",
    "sg:postcode":"9000",
    "sg:province":"St. Gallen",
    "wof:name":"'coiffeur Imperial Dali' Pantelic",
    "wof:placetype":"venue"
},
  "geometry": {"coordinates":[9.3687744141,47.4187774658],"type":"Point"}
}