{
  "type": "Feature",
  "properties": {
    "iso:country":"CH",
    "sg:address":"Hauptstrasse 23",
    "sg:city":"Zuckenriet",
    "sg:orig_category":"Lagerung",
    "sg:phone":"+41 71 947 12 23",
    "sg:postcode":"9526",
    "sg:province":"St. Gallen",
    "wof:name":"Landi Zuckenriet",
    "wof:placetype":"venue"
},
  "geometry": {"coordinates":[9.1641321182,47.4852218628],"type":"Point"}
}