{
  "type": "Feature",
  "properties": {
    "iso:country":"CH",
    "sg:address":"Klingental 5",
    "sg:city":"Basel",
    "sg:orig_category":"Interessenvertretungen",
    "sg:postcode":"4058",
    "sg:province":"Basel-Stadt",
    "wof:name":"Schweizerische Schmerzstiftung",
    "wof:placetype":"venue"
},
  "geometry": {"coordinates":[7.590596199,47.5623207092],"type":"Point"}
}