{
  "type": "Feature",
  "properties": {
    "iso:country":"CH",
    "sg:address":"Hauptstrasse 136",
    "sg:city":"Ormalingen",
    "sg:classifiers":[
        {
            "category":"Restaurant",
            "type":"Food & Drink"
        }
    ],
    "sg:phone":"+41 61 981 13 38",
    "sg:postcode":"4466",
    "sg:province":"Basel-Landschaft",
    "wof:name":"Restaurant J\u00e4gerst\u00fcbli",
    "wof:placetype":"venue"
},
  "geometry": {"coordinates":[7.8800339699,47.4675674438],"type":"Point"}
}