{
  "type": "Feature",
  "properties": {
    "iso:country":"CH",
    "sg:address":"Rte Du Levant",
    "sg:city":"Martigny",
    "sg:orig_category":"Instandhaltung U Reparatur von Automobilen",
    "sg:phone":"+41 32 867 21 21",
    "sg:postcode":"1920",
    "sg:province":"Valais",
    "wof:name":"Michel & Isabelle Piaget S\u00e0rl",
    "wof:placetype":"venue"
},
  "geometry": {"coordinates":[6.4872279167,46.865776062],"type":"Point"}
}