{
  "type": "Feature",
  "properties": {
    "iso:country":"CH",
    "sg:address":"2043",
    "sg:city":"Boudevilliers",
    "sg:orig_category":"Grosshandel mit Holz U Baustoffen",
    "sg:postcode":"2043",
    "sg:province":"Neuch\u00e2tel",
    "wof:name":"Mat\u00e9riaux De Construction Fivaz Gilbert",
    "wof:placetype":"venue"
},
  "geometry": {"coordinates":[6.889480114,47.0277748108],"type":"Point"}
}