{
  "type": "Feature",
  "properties": {
    "iso:country":"CH",
    "sg:address":"Wallisellenstrasse 9",
    "sg:city":"D\u00fcbendorf",
    "sg:classifiers":[
        {
            "category":"Restaurant",
            "type":"Food & Drink"
        }
    ],
    "sg:phone":"+41 52 318 11 32",
    "sg:postcode":"8600",
    "sg:province":"Z\u00fcrich",
    "wof:name":"Restaurant Zur Trotte",
    "wof:placetype":"venue"
},
  "geometry": {"coordinates":[8.5978527069,47.56980896],"type":"Point"}
}