{
  "type": "Feature",
  "properties": {
    "iso:country":"CH",
    "sg:address":"8205 Schaffhausen. Postfach 95",
    "sg:city":"Schaffhausen",
    "sg:classifiers":[
        {
            "category":"Autos & Motor Vehicles",
            "subcategory":"Recreational Vehicle Sales",
            "type":"Retail Goods"
        }
    ],
    "sg:phone":"+41 81 302 28 97",
    "sg:postcode":"8205",
    "sg:province":"Schaffhausen",
    "sg:tags":[
        "sportvereine",
        "go-kart",
        "kart"
    ],
    "wof:name":"Kart-club St.galler Oberland",
    "wof:placetype":"venue"
},
  "geometry": {"coordinates":[9.5065355301,47.0128631592],"type":"Point"}
}