{
  "type": "Feature",
  "properties": {
    "iso:country":"CH",
    "sg:address":"Hertnerstr. 9",
    "sg:city":"Pratteln",
    "sg:classifiers":[
        {
            "category":"Transit Center",
            "subcategory":"Freight",
            "type":"Transportation"
        }
    ],
    "sg:phone":"+41 61 821 14 14",
    "sg:postcode":"4133",
    "sg:province":"Basel-Landschaft",
    "sg:tags":[
        "metallurgy",
        "pipe",
        "metalworking",
        "sheet"
    ],
    "wof:name":"Aroba Weisskopf Ag",
    "wof:placetype":"venue"
},
  "geometry": {"coordinates":[7.6956157684,47.5247917175],"type":"Point"}
}