{
  "type": "Feature",
  "properties": {
    "iso:country":"CH",
    "sg:address":"Delsbergerstrasse 19",
    "sg:city":"Laufen",
    "sg:orig_category":"Detailhandel mit Blumen U Pflanzen",
    "sg:phone":"+41 61 761 25 12",
    "sg:postcode":"4242",
    "sg:province":"Basel-Landschaft",
    "wof:name":"Rita Jermann Blumengesch\u00e4ft",
    "wof:placetype":"venue"
},
  "geometry": {"coordinates":[7.500532,47.419788],"type":"Point"}
}