{
  "type": "Feature",
  "properties": {
    "iso:country":"CH",
    "sg:address":"Frauenfelderstrasse 57",
    "sg:city":"Weinfelden",
    "sg:classifiers":[
        {
            "category":"Restaurant",
            "type":"Food & Drink"
        }
    ],
    "sg:phone":"+41 71 622 40 60",
    "sg:postcode":"8570",
    "sg:province":"Thurgau",
    "wof:name":"Restaurant Storchen",
    "wof:placetype":"venue"
},
  "geometry": {"coordinates":[9.105266571,47.5698890686],"type":"Point"}
}