{
  "type": "Feature",
  "properties": {
    "iso:country":"CH",
    "sg:address":"Gartenstrasse 4",
    "sg:city":"Pratteln",
    "sg:orig_category":"Non-Classified Establishments",
    "sg:phone":"+41 61 821 52 08",
    "sg:postcode":"4133",
    "sg:province":"Basel-Landschaft",
    "wof:name":"Eduard Meyer Ag",
    "wof:placetype":"venue"
},
  "geometry": {"coordinates":[7.697414875,47.5207290649],"type":"Point"}
}