{
  "type": "Feature",
  "properties": {
    "iso:country":"CH",
    "sg:address":"Avenue De Tourbillon 21 1950 Sion Case Postale 665",
    "sg:city":"Sion",
    "sg:orig_category":"Detailhandel mit Teppichen Verlegen von Fussboden",
    "sg:phone":"+41 27 323 25 55",
    "sg:postcode":"1951",
    "sg:province":"Valais",
    "wof:name":"Adolphe Meystre Sa",
    "wof:placetype":"venue"
},
  "geometry": {"coordinates":[7.3626999855,46.2289009094],"type":"Point"}
}