{
  "type": "Feature",
  "properties": {
    "addr:full":"Steinstrasse 35 8003 Z\u00fcrich. Postfach 716 Z\u00fcrich Z\u00fcrich 8045",
    "addr:housenumber":"35;716",
    "addr:postcode":"8003 zuerich.;8045",
    "addr:street":"Steinstrasse;Postfach",
    "iso:country":"CH",
    "sg:address":"Steinstrasse 35 8003 Z\u00fcrich. Postfach 716",
    "sg:city":"Z\u00fcrich",
    "sg:orig_category":"Herstellung von sonstiger Bekleidung U Bekleidungszubeh\u00f6r Sonstiges Textilgewerbe",
    "sg:phone":"+41 14563434",
    "sg:postcode":"8045",
    "sg:province":"Z\u00fcrich",
    "wof:name":"Maurer K. & Co Ag",
    "wof:placetype":"venue"
},
  "geometry": {"coordinates":[8.520319,47.36694],"type":"Point"}
}