{
  "type": "Feature",
  "properties": {
    "iso:country":"CH",
    "sg:address":"Gr\u00fcningerstrasse",
    "sg:city":"Hombrechtikon",
    "sg:orig_category":"Interessenvertretungen",
    "sg:postcode":"8634",
    "sg:province":"Z\u00fcrich",
    "wof:name":"Br\u00e4ndli-bertschi Heinrich Und Martha-stiftung",
    "wof:placetype":"venue"
},
  "geometry": {"coordinates":[8.7655601501,47.253868103],"type":"Point"}
}