{
  "type": "Feature",
  "properties": {
    "iso:country":"CH",
    "sg:address":"Kirchstrasse 42",
    "sg:city":"Freienbach",
    "sg:orig_category":"Erschliessung von Grundst\u00fccken",
    "sg:phone":"+41 71234301",
    "sg:postcode":"8807",
    "sg:province":"Schwyz",
    "wof:name":"Stiftung F\u00fcr Sozialen Wohnungsbau St. Gallen Swb",
    "wof:placetype":"venue"
},
  "geometry": {"coordinates":[9.2506904602,47.4096298218],"type":"Point"}
}