{
  "type": "Feature",
  "properties": {
    "iso:country":"CH",
    "sg:address":"Frohwiesstrasse 34",
    "sg:city":"Adetswil",
    "sg:orig_category":"Grosshandel mit sonstigen Maschinen U Ausr\u00fcstungen f\u00fcr Industrie, Handel U Schiffahrt Herstellung vo",
    "sg:phone":"+41 19404352",
    "sg:postcode":"8345",
    "sg:province":"Z\u00fcrich",
    "wof:name":"Wunderli & Co Ag",
    "wof:placetype":"venue"
},
  "geometry": {"coordinates":[8.716170311,47.3536720276],"type":"Point"}
}