{
  "type": "Feature",
  "properties": {
    "iso:country":"CH",
    "sg:address":"La Stampa",
    "sg:city":"Cadro",
    "sg:orig_category":"Schiffsbau ohne Boots U Yachtbau",
    "sg:postcode":"6965",
    "sg:province":"Ticino",
    "wof:name":"Cbm Carrozzeria Barche Motori Sagl",
    "wof:placetype":"venue"
},
  "geometry": {"coordinates":[8.9743824005,46.0413742065],"type":"Point"}
}