{
  "type": "Feature",
  "properties": {
    "iso:country":"CH",
    "sg:address":"Spitalackerstrasse 26 3013 Bern. Postfach",
    "sg:city":"Bern",
    "sg:classifiers":[
        {
            "category":"Professional",
            "subcategory":"Employment Agencies",
            "type":"Services"
        }
    ],
    "sg:postcode":"3005",
    "sg:province":"Bern",
    "sg:tags":[
        "personal",
        "u",
        "stellenvermittlung"
    ],
    "wof:name":"Simeoni Paolo - Typ-top Montage, D\u00e9pannage, Entrepr. De Pr\u00eat De Personell Dans Le B\u00e2timent Etc.",
    "wof:placetype":"venue"
},
  "geometry": {"coordinates":[7.0927248001,47.0635795593],"type":"Point"}
}