{
  "type": "Feature",
  "properties": {
    "iso:country":"CH",
    "sg:address":"1890 St-maurice. Postfach",
    "sg:city":"St-maurice",
    "sg:orig_category":"Verwertung von Milch",
    "sg:postcode":"1890",
    "sg:province":"Valais",
    "wof:name":"Soci\u00e9t\u00e9 Des Producteurs De Lait Et De C\u00e9r\u00e9ales De Vuguelles",
    "wof:placetype":"venue"
},
  "geometry": {"coordinates":[6.5751399994,46.8234176636],"type":"Point"}
}