{
  "type": "Feature",
  "properties": {
    "iso:country":"CH",
    "sg:address":"Avenue De V\u00e9rolliez 11",
    "sg:city":"St-maurice",
    "sg:orig_category":"Maurerarbeiten",
    "sg:phone":"+41 24 485 23 67",
    "sg:postcode":"1890",
    "sg:province":"Valais",
    "wof:name":"Andr\u00e9 Gay Entreprise De Ma\u00e7onnerie",
    "wof:placetype":"venue"
},
  "geometry": {"coordinates":[7.0020198822,46.2108192444],"type":"Point"}
}