{
  "type": "Feature",
  "properties": {
    "iso:country":"CH",
    "sg:address":"B\u00e4raustrasse 107 3552 B\u00e4rau. Postfach 629",
    "sg:city":"B\u00e4rau",
    "sg:orig_category":"Einzelhandel mit Automobilteilen U Zubeh\u00f6r Herstellung von Bereifungen",
    "sg:phone":"+41 34 402 42 92",
    "sg:postcode":"3552",
    "sg:province":"Bern",
    "wof:name":"Pneuservice Jau Ag",
    "wof:placetype":"venue"
},
  "geometry": {"coordinates":[7.8140501976,46.9265899658],"type":"Point"}
}