{
  "type": "Feature",
  "properties": {
    "iso:country":"CH",
    "sg:address":"Waldmannstrasse 4 8001 Z\u00fcrich. Postfach",
    "sg:city":"Z\u00fcrich",
    "sg:orig_category":"Steuerberatung",
    "sg:phone":"+41 12611640",
    "sg:postcode":"8024",
    "sg:province":"Z\u00fcrich",
    "wof:name":"Dr.rolf Peter Utzinger Steuerrechts-& Treuhandpraxis",
    "wof:placetype":"venue"
},
  "geometry": {"coordinates":[8.5466442108,47.3685302734],"type":"Point"}
}