{
  "type": "Feature",
  "properties": {
    "iso:country":"CH",
    "sg:address":"Brunnhof",
    "sg:city":"Hornussen",
    "sg:orig_category":"Verarbeitung von Milch Verwertung von Milch",
    "sg:phone":"+41 62713504",
    "sg:postcode":"5075",
    "sg:province":"Aargau",
    "wof:name":"Milchgenossenschaft Hornussen",
    "wof:placetype":"venue"
},
  "geometry": {"coordinates":[8.0574359894,47.494682312],"type":"Point"}
}