{
  "type": "Feature",
  "properties": {
    "addr:full":"Flurstrasse 44 Bettlach Solothurn 2544",
    "addr:housenumber":"44",
    "addr:postcode":"2544",
    "addr:street":"Flurstrasse",
    "iso:country":"CH",
    "sg:address":"Flurstrasse 44",
    "sg:city":"Bettlach",
    "sg:orig_category":"Bauingenieurb\u00fcros Hochbau Bauingenieurb\u00fcros allgemein",
    "sg:phone":"+41 32 645 02 40",
    "sg:postcode":"2544",
    "sg:province":"Solothurn",
    "wof:name":"Wulf Seele Ingenieurb\u00fcro F\u00fcr Hoch- & Tiefbau",
    "wof:placetype":"venue"
},
  "geometry": {"coordinates":[7.414898,47.198196],"type":"Point"}
}