{
  "type": "Feature",
  "properties": {
    "iso:country":"CH",
    "sg:address":"Rebmattli 23",
    "sg:city":"Baar",
    "sg:orig_category":"Rechtsberatung",
    "sg:postcode":"6340",
    "sg:province":"Zug",
    "wof:name":"Gefinex Ag",
    "wof:placetype":"venue"
},
  "geometry": {"coordinates":[8.643989563,46.8819503784],"type":"Point"}
}