{
  "type": "Feature",
  "properties": {
    "iso:country":"CH",
    "sg:address":"Closalet Chemin De 19 1023 Crissier Case Postale 198",
    "sg:city":"Crissier",
    "sg:orig_category":"Handel mit Automobilteilen U Zubeh\u00f6r",
    "sg:phone":"+41 21 631 24 11",
    "sg:postcode":"1023",
    "sg:province":"Vaud",
    "wof:name":"Frey Emil Sa, Gen\u00e8ve",
    "wof:placetype":"venue"
},
  "geometry": {"coordinates":[6.5774769783,46.5531997681],"type":"Point"}
}