{
  "type": "Feature",
  "properties": {
    "iso:country":"CH",
    "sg:address":"Grossbachstrasse 45 8841 Gross. Postfach 36",
    "sg:city":"Gross",
    "sg:orig_category":"Herstellung von k\u00e4lte U lufttechnischen Erzeugnissen f\u00fcr gewerbliche Zwecke",
    "sg:phone":"+41 55 422 28 70",
    "sg:postcode":"8841",
    "sg:province":"Schwyz",
    "wof:name":"Emk Engineering Ag, Triesen, F\u00fcrstentum Lichtenstein, Zweigniederlassung Gross/sz",
    "wof:placetype":"venue"
},
  "geometry": {"coordinates":[8.7752199173,47.1116485596],"type":"Point"}
}