{
  "type": "Feature",
  "properties": {
    "iso:country":"CH",
    "sg:address":"Winkelstrasse 12",
    "sg:city":"Horw",
    "sg:orig_category":"D\u00e4mmung gegen K\u00e4lte, W\u00e4rme, Schall U Ersch\u00fctterung Sonstiger spezialisierter Hoch U Tiefbau",
    "sg:postcode":"6048",
    "sg:province":"Luzern",
    "wof:name":"J\u00fcrg Schmutz",
    "wof:placetype":"venue"
},
  "geometry": {"coordinates":[7.5906691551,47.0842094421],"type":"Point"}
}