{
  "type": "Feature",
  "properties": {
    "iso:country":"CH",
    "sg:address":"Burgauerstrasse 18 9230 Flawil. Postfach",
    "sg:city":"Flawil",
    "sg:classifiers":[
        {
            "category":"Restaurant",
            "type":"Food & Drink"
        }
    ],
    "sg:phone":"+41 71 393 21 44",
    "sg:postcode":"9230",
    "sg:province":"St. Gallen",
    "wof:name":"Restaurant National",
    "wof:placetype":"venue"
},
  "geometry": {"coordinates":[9.1981039047,47.4111328125],"type":"Point"}
}