{
  "type": "Feature",
  "properties": {
    "iso:country":"CH",
    "sg:address":"Dorfstrasse 6",
    "sg:city":"Schattdorf",
    "sg:orig_category":"Non-Classified Establishments",
    "sg:postcode":"6467",
    "sg:province":"Uri",
    "wof:name":"Pibierre Ag",
    "wof:placetype":"venue"
},
  "geometry": {"coordinates":[8.6550178528,46.865688324],"type":"Point"}
}