{
  "type": "Feature",
  "properties": {
    "iso:country":"CH",
    "sg:address":"Vallin Rue 2 1201 Gen\u00e8ve. Postfach",
    "sg:city":"Gen\u00e8ve",
    "sg:orig_category":"Unclassifiable Establishments",
    "sg:postcode":"1201",
    "sg:province":"Gen\u00e8ve",
    "wof:name":"Impartrust Sa De Participations Et D'investissements",
    "wof:placetype":"venue"
},
  "geometry": {"coordinates":[6.1424689293,46.2061309814],"type":"Point"}
}