{
  "type": "Feature",
  "properties": {
    "iso:country":"CH",
    "sg:address":"Birsigstrasse 125",
    "sg:city":"Basel",
    "sg:orig_category":"Non-Classified Establishments",
    "sg:phone":"+41 61 281 02 07",
    "sg:postcode":"4054",
    "sg:province":"Basel-Stadt",
    "wof:name":"B\u00f6ni Corporate Finance",
    "wof:placetype":"venue"
},
  "geometry": {"coordinates":[7.576862812,47.5505828857],"type":"Point"}
}