{
  "type": "Feature",
  "properties": {
    "addr:full":"Hauptstrasse 50 Wollerau Schwyz 8832",
    "addr:housenumber":"50",
    "addr:postcode":"8832",
    "addr:street":"Hauptstrasse;Schwyz",
    "iso:country":"CH",
    "sg:address":"Hauptstrasse 50",
    "sg:city":"Wollerau",
    "sg:classifiers":[
        {
            "category":"Bars & Pubs",
            "type":"Food & Drink"
        }
    ],
    "sg:phone":"+41 17861848",
    "sg:postcode":"8832",
    "sg:province":"Schwyz",
    "wof:name":"Fassbar",
    "wof:placetype":"venue"
},
  "geometry": {"coordinates":[8.719041,47.193684],"type":"Point"}
}