{
  "type": "Feature",
  "properties": {
    "iso:country":"CH",
    "sg:address":"Lyssstrasse 7 3270 Aarberg. Postfach",
    "sg:city":"Aarberg",
    "sg:orig_category":"Betrieb U technische Hilfsdienste des Kultur U Unterhaltungswesens Grosshandel mit Radio U Fernsehge",
    "sg:phone":"+41 22 827 15 50",
    "sg:postcode":"3270",
    "sg:province":"Bern",
    "wof:name":"Dinifan Sa",
    "wof:placetype":"venue"
},
  "geometry": {"coordinates":[6.15948,46.189629],"type":"Point"}
}