{
  "type": "Feature",
  "properties": {
    "iso:country":"CH",
    "sg:address":"Bahnhofstrasse 2",
    "sg:city":"Elgg",
    "sg:classifiers":[
        {
            "category":"Restaurant",
            "type":"Food & Drink"
        }
    ],
    "sg:phone":"+41 52 364 32 02",
    "sg:postcode":"8353",
    "sg:province":"Z\u00fcrich",
    "wof:name":"Restaurant Bahnh\u00f6fli",
    "wof:placetype":"venue"
},
  "geometry": {"coordinates":[8.8642873764,47.4979972839],"type":"Point"}
}