{
  "type": "Feature",
  "properties": {
    "iso:country":"CH",
    "sg:address":"Les Moilles",
    "sg:city":"Ropraz",
    "sg:orig_category":"Allgemeiner Hoch U Tiefbau Sanit\u00e4rinstallation",
    "sg:phone":"+41 21 903 19 74",
    "sg:postcode":"1088",
    "sg:province":"Vaud",
    "wof:name":"Pascal Paltenghi Installations De Chauffages",
    "wof:placetype":"venue"
},
  "geometry": {"coordinates":[6.74739,46.593048],"type":"Point"}
}