{
  "type": "Feature",
  "properties": {
    "iso:country":"CH",
    "sg:address":"T\u00f6pferstrasse 5",
    "sg:city":"Luzern",
    "sg:orig_category":"Aktivit\u00e4ten der Generalunternehmen im Baugewerbe Kauf U Verkauf von Immobilien auf eigene Rechnung",
    "sg:phone":"+41 41 418 40 10",
    "sg:postcode":"6004",
    "sg:province":"Luzern",
    "wof:name":"Intercity Verwaltungs-ag",
    "wof:placetype":"venue"
},
  "geometry": {"coordinates":[8.310234,47.055058],"type":"Point"}
}