{
  "type": "Feature",
  "properties": {
    "iso:country":"CH",
    "sg:address":"1613",
    "sg:city":"Maracon",
    "sg:orig_category":"Verwertung von Milch",
    "sg:postcode":"1613",
    "sg:province":"Vaud",
    "wof:name":"Soci\u00e9t\u00e9 De Laiterie De Maracon",
    "wof:placetype":"venue"
},
  "geometry": {"coordinates":[6.8825302124,46.556060791],"type":"Point"}
}