{
  "type": "Feature",
  "properties": {
    "iso:country":"CH",
    "sg:address":"Rosenstrasse 3 9400 Rorschach. Postfach",
    "sg:city":"Rorschach",
    "sg:classifiers":[
        {
            "category":"Restaurant",
            "type":"Food & Drink"
        }
    ],
    "sg:phone":"+41 71 841 10 31",
    "sg:postcode":"9401",
    "sg:province":"St. Gallen",
    "wof:name":"Restaurant Comunidad Espanola",
    "wof:placetype":"venue"
},
  "geometry": {"coordinates":[9.4868211746,47.4762992859],"type":"Point"}
}