{
  "type": "Feature",
  "properties": {
    "iso:country":"CH",
    "sg:address":"Z\u00fcrcherstrasse 35",
    "sg:city":"Schlieren",
    "sg:orig_category":"Detailhandel Handel mit Motorr\u00e4dern, Teilen U Zubeh\u00f6r Instandhaltung U Reparatur von Motorr\u00e4dern Rep",
    "sg:phone":"+41 17305301",
    "sg:postcode":"8952",
    "sg:province":"Z\u00fcrich",
    "wof:name":"J\u00fcrg F\u00fcrst Motos",
    "wof:placetype":"venue"
},
  "geometry": {"coordinates":[8.4518842697,47.3984298706],"type":"Point"}
}