{
  "type": "Feature",
  "properties": {
    "iso:country":"CH",
    "sg:address":"Route De La Croix-blanche 1 1066 Epalinges Case Postale 176",
    "sg:city":"Epalinges",
    "sg:orig_category":"Handelsvermittlung U Grosshandel Herstellung von sonstigen Maschinen f\u00fcr bestimmte Verwendung",
    "sg:phone":"+41 21 784 23 33",
    "sg:postcode":"1066",
    "sg:province":"Vaud",
    "wof:name":"Pentagon Trading Sa Import-export",
    "wof:placetype":"venue"
},
  "geometry": {"coordinates":[6.6634178162,46.5443572998],"type":"Point"}
}