{
  "type": "Feature",
  "properties": {
    "addr:full":"Rte Du Ch\u00e2teau D'affry 10 Givisiez Fribourg 1762",
    "addr:housenumber":"10",
    "addr:postcode":"1762",
    "addr:street":"Rte Du Cha\u0302Teau D'Affry",
    "iso:country":"CH",
    "sg:address":"Rte Du Ch\u00e2teau D'affry 10",
    "sg:city":"Givisiez",
    "sg:classifiers":[
        {
            "category":"Banks & Credit Unions",
            "subcategory":"Bank",
            "type":"Services"
        }
    ],
    "sg:phone":"+41 26 466 46 24",
    "sg:postcode":"1762",
    "sg:province":"Fribourg",
    "wof:name":"Raiffeisen Fribourg-ouest",
    "wof:placetype":"venue"
},
  "geometry": {"coordinates":[7.12554,46.812801],"type":"Point"}
}