{
  "type": "Feature",
  "properties": {
    "iso:country":"CH",
    "sg:address":"Doktorg\u00e4ssli 338",
    "sg:city":"Gurmels",
    "sg:orig_category":"Allgemeiner Hoch U Tiefbau",
    "sg:postcode":"3212",
    "sg:province":"Fribourg",
    "wof:name":"Atelier Zaugg R.",
    "wof:placetype":"venue"
},
  "geometry": {"coordinates":[7.17396,46.892471],"type":"Point"}
}