{
  "type": "Feature",
  "properties": {
    "iso:country":"CH",
    "sg:address":"Paradiesweg 3",
    "sg:city":"Zurzach",
    "sg:orig_category":"Herstellung von sonstigen landwirtschaftlichen Maschinen Mechanische Werkst\u00e4tten",
    "sg:phone":"+41 33 336 49 25",
    "sg:postcode":"5330",
    "sg:province":"Aargau",
    "wof:name":"Wittwer Alfred",
    "wof:placetype":"venue"
},
  "geometry": {"coordinates":[7.6261482239,46.7306213379],"type":"Point"}
}