{
  "type": "Feature",
  "properties": {
    "iso:country":"CH",
    "sg:address":"Bahnhofstr. 13",
    "sg:city":"Oberr\u00fcti",
    "sg:classifiers":[
        {
            "category":"Professional",
            "subcategory":"Engineering",
            "type":"Services"
        }
    ],
    "sg:phone":"+41 41 787 28 80",
    "sg:postcode":"5647",
    "sg:province":"Aargau",
    "sg:tags":[
        "machine",
        "-",
        "environment",
        "equipment",
        "machinery",
        "mechanical"
    ],
    "wof:name":"Villiger Entsorgungssysteme Ag",
    "wof:placetype":"venue"
},
  "geometry": {"coordinates":[8.402630806,47.1677436829],"type":"Point"}
}