{
  "type": "Feature",
  "properties": {
    "iso:country":"CH",
    "sg:address":"Rossettan Rue De 34",
    "sg:city":"Martigny",
    "sg:orig_category":"Softwareentwicklung U beratung",
    "sg:phone":"+41 27 722 03 23",
    "sg:postcode":"1920",
    "sg:province":"Valais",
    "wof:name":"Guex Informatique",
    "wof:placetype":"venue"
},
  "geometry": {"coordinates":[7.0729198456,46.1013793945],"type":"Point"}
}