{
  "type": "Feature",
  "properties": {
    "iso:country":"CH",
    "sg:address":"Br\u00fchlstrasse 41",
    "sg:city":"Arbon",
    "sg:orig_category":"Verlegen von Fliesen U Platten",
    "sg:phone":"+41 31 839 06 86",
    "sg:postcode":"9320",
    "sg:province":"Thurgau",
    "wof:name":"Anton Ramseier Chemin\u00e9ebau & Plattenbel\u00e4ge",
    "wof:placetype":"venue"
},
  "geometry": {"coordinates":[7.5442538261,46.927406311],"type":"Point"}
}