{
  "type": "Feature",
  "properties": {
    "iso:country":"CH",
    "sg:address":"2800",
    "sg:city":"Del\u00e9mont",
    "sg:orig_category":"Verwaltung von Immobilien",
    "sg:postcode":"2800",
    "sg:province":"Jura",
    "wof:name":"Butt M. Et K.",
    "wof:placetype":"venue"
},
  "geometry": {"coordinates":[6.3650588989,46.8927841187],"type":"Point"}
}