{
  "type": "Feature",
  "properties": {
    "iso:country":"CH",
    "sg:address":"Obergasse 24",
    "sg:city":"Biel/bienne",
    "sg:orig_category":"Detailhandel mit Damenbekleidung",
    "sg:phone":"+41 32 322 23 61",
    "sg:postcode":"2502",
    "sg:province":"Bern",
    "wof:name":"Inge Buddee Couture",
    "wof:placetype":"venue"
},
  "geometry": {"coordinates":[7.246975,47.142735],"type":"Point"}
}