{
  "type": "Feature",
  "properties": {
    "iso:country":"CH",
    "sg:address":"Via Verdella 12",
    "sg:city":"Savosa",
    "sg:orig_category":"Physiotherapie",
    "sg:phone":"+41 91 968 13 68",
    "sg:postcode":"6942",
    "sg:province":"Ticino",
    "wof:name":"Christa Minder Studio Di Fisioterapia",
    "wof:placetype":"venue"
},
  "geometry": {"coordinates":[8.9472703934,46.0199890137],"type":"Point"}
}