{
  "type": "Feature",
  "properties": {
    "iso:country":"CH",
    "sg:address":"Beau-site",
    "sg:city":"Sullens",
    "sg:orig_category":"Instandhaltung U Reparatur von Automobilen",
    "sg:phone":"+41 21 731 32 38",
    "sg:postcode":"1036",
    "sg:province":"Vaud",
    "wof:name":"Auto-electro-diesel Olivier Papaux S\u00e0rl",
    "wof:placetype":"venue"
},
  "geometry": {"coordinates":[6.5663352013,46.5934906006],"type":"Point"}
}