{
  "type": "Feature",
  "properties": {
    "addr:full":"Grange-canal Chemin Du 24 Ch\u00eane-bougeries Gen\u00e8ve 1224",
    "addr:postcode":"1224",
    "addr:street":"Chemin Du 24",
    "iso:country":"CH",
    "sg:address":"Grange-canal Chemin Du 24",
    "sg:city":"Ch\u00eane-bougeries",
    "sg:orig_category":"Allgemeiner Hoch U Tiefbau",
    "sg:postcode":"1224",
    "sg:province":"Gen\u00e8ve",
    "wof:name":"A.a. Am\u00e9nagement Et Agencement, Silvia Antonio",
    "wof:placetype":"venue"
},
  "geometry": {"coordinates":[6.187205,46.197926],"type":"Point"}
}