{
  "type": "Feature",
  "properties": {
    "iso:country":"CH",
    "sg:address":"Schmidgasse 26",
    "sg:city":"St.gallen",
    "sg:orig_category":"Interessenvertretungen",
    "sg:postcode":"9000",
    "sg:province":"St. Gallen",
    "wof:name":"Tw Stiftung Zugunsten Von Kulturellen Und Sozialen Institutionen",
    "wof:placetype":"venue"
},
  "geometry": {"coordinates":[9.3755207062,47.4239273071],"type":"Point"}
}