{
  "type": "Feature",
  "properties": {
    "iso:country":"CH",
    "sg:address":"Oberstrasse 141",
    "sg:city":"St.gallen",
    "sg:orig_category":"Herstellung von Tanks U Sammelbeh\u00e4ltern aus Metall Tankstellen",
    "sg:phone":"+41 71 226 78 26",
    "sg:postcode":"9000",
    "sg:province":"St. Gallen",
    "wof:name":"Lv-energieservice Ag",
    "wof:placetype":"venue"
},
  "geometry": {"coordinates":[9.3757143021,47.4253845215],"type":"Point"}
}