{
  "type": "Feature",
  "properties": {
    "iso:country":"CH",
    "sg:address":"8765 Engi. Postfach",
    "sg:city":"Engi",
    "sg:orig_category":"Detailhandel mit Brot, Back U S\u00fcsswaren",
    "sg:phone":"+41 55 642 10 19",
    "sg:postcode":"8765",
    "sg:province":"Glarus",
    "wof:name":"B\u00e4ckerei-konditorei Hefti",
    "wof:placetype":"venue"
},
  "geometry": {"coordinates":[9.151791,46.984814],"type":"Point"}
}