{
  "type": "Feature",
  "properties": {
    "iso:country":"CH",
    "sg:address":"Limmattalstrasse 45",
    "sg:city":"Geroldswil",
    "sg:orig_category":"Herstellung von sonstigen Maschinen f\u00fcr unspezifische Verwendung",
    "sg:phone":"+41 17470420",
    "sg:postcode":"8954",
    "sg:province":"Z\u00fcrich",
    "wof:name":"Elchem Gmbh",
    "wof:placetype":"venue"
},
  "geometry": {"coordinates":[8.4118156433,47.4201583862],"type":"Point"}
}