{
  "type": "Feature",
  "properties": {
    "iso:country":"CH",
    "sg:address":"Winterthurerstrasse 304",
    "sg:city":"Z\u00fcrich",
    "sg:orig_category":"Fachdetailhandel in Verkaufsr\u00e4umen",
    "sg:postcode":"8057",
    "sg:province":"Z\u00fcrich",
    "wof:name":"Handicraft House, Caregnato A. Handarbeitserzeugnisse Aus Nepal, Indien; Imp, Handel",
    "wof:placetype":"venue"
},
  "geometry": {"coordinates":[8.555138588,47.4028663635],"type":"Point"}
}