{
  "type": "Feature",
  "properties": {
    "iso:country":"CH",
    "sg:address":"Els\u00e4sserstrasse 252 4056 Basel. Postfach",
    "sg:city":"Basel",
    "sg:orig_category":"Sonstige pers\u00f6nliche Dienstleistungen",
    "sg:phone":"+41 61 322 45 20",
    "sg:postcode":"4000",
    "sg:province":"Basel-Stadt",
    "wof:name":"Walter Schnegg, Wechselstube",
    "wof:placetype":"venue"
},
  "geometry": {"coordinates":[7.5727329254,47.5765953064],"type":"Point"}
}