{
  "type": "Feature",
  "properties": {
    "iso:country":"CH",
    "sg:address":"R\u00f6ssligutstrasse 15 5000 Aarau. Postfach 2645",
    "sg:city":"Aarau",
    "sg:orig_category":"Organisationen der Wohlfahrtspflege",
    "sg:phone":"+41 62 824 84 44",
    "sg:postcode":"5001",
    "sg:province":"Aargau",
    "wof:name":"Dargebotene Hand Aarau",
    "wof:placetype":"venue"
},
  "geometry": {"coordinates":[8.0546560287,47.3951950073],"type":"Point"}
}