{
  "type": "Feature",
  "properties": {
    "iso:country":"CH",
    "sg:address":"B\u00f6liweg 3",
    "sg:city":"Oberbipp",
    "sg:orig_category":"Politische Parteien FDP",
    "sg:phone":"+41 32 636 38 65",
    "sg:postcode":"4538",
    "sg:province":"Bern",
    "wof:name":"Fdp Sektion Oberbipp",
    "wof:placetype":"venue"
},
  "geometry": {"coordinates":[7.6571378708,47.2625923157],"type":"Point"}
}