{
  "type": "Feature",
  "properties": {
    "iso:country":"CH",
    "sg:address":"8846",
    "sg:city":"Willerzell",
    "sg:orig_category":"Sportvereine Sch\u00fctzen",
    "sg:phone":"+41 71 923 63 59",
    "sg:postcode":"8846",
    "sg:province":"Schwyz",
    "wof:name":"Milit\u00e4rsch\u00fctzenverein",
    "wof:placetype":"venue"
},
  "geometry": {"coordinates":[8.7920799255,47.1321411133],"type":"Point"}
}