{
  "type": "Feature",
  "properties": {
    "iso:country":"CH",
    "sg:address":"Neuhofstrasse 25",
    "sg:city":"Baar",
    "sg:orig_category":"Non-Classified Establishments",
    "sg:postcode":"6340",
    "sg:province":"Zug",
    "wof:name":"Andavit Immobilien Ag",
    "wof:placetype":"venue"
},
  "geometry": {"coordinates":[8.5159425735,47.1894416809],"type":"Point"}
}