{
  "type": "Feature",
  "properties": {
    "iso:country":"CH",
    "sg:address":"St\u00e4dtlistrasse 5",
    "sg:city":"Ilanz",
    "sg:orig_category":"Detailhandel mit B\u00fcromaschinen U einrichtungen",
    "sg:phone":"+41 81 925 22 45",
    "sg:postcode":"7130",
    "sg:province":"Graubunden",
    "wof:name":"B\u00fcrocenter Ilanz Ag",
    "wof:placetype":"venue"
},
  "geometry": {"coordinates":[9.203907,46.773518],"type":"Point"}
}