{
  "type": "Feature",
  "properties": {
    "iso:country":"CH",
    "sg:address":"V\u00e9roz",
    "sg:city":"Troistorrents",
    "sg:orig_category":"Grosshandel mit lebenden Tieren",
    "sg:phone":"+41 41 988 11 08",
    "sg:postcode":"1872",
    "sg:province":"Valais",
    "wof:name":"Gr\u00fcter Viehhandels Ag",
    "wof:placetype":"venue"
},
  "geometry": {"coordinates":[7.9321951866,47.1377639771],"type":"Point"}
}