{
  "type": "Feature",
  "properties": {
    "iso:country":"CH",
    "sg:address":"Bodenstrasse 27",
    "sg:city":"Adelboden",
    "sg:orig_category":"Softwareentwicklung U beratung",
    "sg:phone":"+41 33 673 40 68",
    "sg:postcode":"3715",
    "sg:province":"Bern",
    "wof:name":"Informatik Zimmermann Christian",
    "wof:placetype":"venue"
},
  "geometry": {"coordinates":[7.5629940033,46.4859886169],"type":"Point"}
}