{
  "type": "Feature",
  "properties": {
    "iso:country":"CH",
    "sg:address":"Zypressenstrasse 56/58",
    "sg:city":"Z\u00fcrich",
    "sg:orig_category":"Grosshandel mit B\u00fcromaschinen Grosshandel mit Datenverarbeitungsger\u00e4ten",
    "sg:phone":"+41 12459080",
    "sg:postcode":"8004",
    "sg:province":"Z\u00fcrich",
    "wof:name":"Agfb Ag F\u00fcr Betriebswirtschaft Und Informatik",
    "wof:placetype":"venue"
},
  "geometry": {"coordinates":[8.5135269165,47.3776473999],"type":"Point"}
}