{
  "type": "Feature",
  "properties": {
    "iso:country":"CH",
    "sg:address":"Z\u00fcrcherstrasse 232",
    "sg:city":"Frauenfeld",
    "sg:orig_category":"Detailhandel mit Waren verschiedener Art, Hauptrichtung Nahrungsmittel",
    "sg:phone":"+41 52 721 01 03",
    "sg:postcode":"8500",
    "sg:province":"Thurgau",
    "wof:name":"Nuk's Asia Shop + Take Away Zuber",
    "wof:placetype":"venue"
},
  "geometry": {"coordinates":[8.9016103745,47.5597076416],"type":"Point"}
}