{
  "type": "Feature",
  "properties": {
    "iso:country":"CH",
    "sg:address":"Bahnhofstrasse 34",
    "sg:city":"Steinhausen",
    "sg:orig_category":"Dienstleistungen von Beteiligungsgesellschaften",
    "sg:phone":"+41 41 741 51 45",
    "sg:postcode":"6312",
    "sg:province":"Zug",
    "wof:name":"Mbco Gmbh Informatik",
    "wof:placetype":"venue"
},
  "geometry": {"coordinates":[8.4817790985,47.1966972351],"type":"Point"}
}