{
  "type": "Feature",
  "properties": {
    "iso:country":"CH",
    "sg:address":"Immeuble Val-centre",
    "sg:city":"Montana-vermala",
    "sg:orig_category":"Detailhandel mit Waren verschiedener Art, Hauptrichtung Nahrungsmittel",
    "sg:phone":"+41 27 481 42 47",
    "sg:postcode":"3962",
    "wof:name":"Migros",
    "wof:placetype":"venue"
},
  "geometry": {"coordinates":[7.4924340248,46.3144187927],"type":"Point"}
}