{
  "type": "Feature",
  "properties": {
    "iso:country":"CH",
    "sg:address":"Wartenbergstrasse 54",
    "sg:city":"Pratteln",
    "sg:orig_category":"Arbeitnehmerverb\u00e4nde",
    "sg:phone":"+41 61 821 88 00",
    "sg:postcode":"4133",
    "sg:province":"Basel-Landschaft",
    "wof:name":"Schweiz.verband Des Personals \u00f6ffentl.dienste,m.aebersold",
    "wof:placetype":"venue"
},
  "geometry": {"coordinates":[7.681668,47.518402],"type":"Point"}
}