{
  "type": "Feature",
  "properties": {
    "iso:country":"CH",
    "sg:address":"Gr\u00fctlistrasse 44 8002 Z\u00fcrich. Postfach 658",
    "sg:city":"Z\u00fcrich",
    "sg:orig_category":"Interessenvertretungen",
    "sg:phone":"+41 12883333",
    "sg:postcode":"8027",
    "sg:province":"Z\u00fcrich",
    "wof:name":"Schweizerischer Verein Des Gas Und Wasserfaches (svgw)",
    "wof:placetype":"venue"
},
  "geometry": {"coordinates":[8.5309324265,47.3617286682],"type":"Point"}
}