{
  "type": "Feature",
  "properties": {
    "iso:country":"CH",
    "sg:address":"Ringstrasse 5",
    "sg:city":"Schwerzenbach",
    "sg:classifiers":[
        {
            "category":"Shopping",
            "subcategory":"Computers & Home Electronics",
            "type":"Retail Goods"
        }
    ],
    "sg:phone":"+41 18066464",
    "sg:postcode":"8603",
    "sg:province":"Z\u00fcrich",
    "sg:tags":[
        "system",
        "automation"
    ],
    "wof:name":"Bfa Solutions Ltd",
    "wof:placetype":"venue"
},
  "geometry": {"coordinates":[8.654571,47.387615],"type":"Point"}
}