{
  "type": "Feature",
  "properties": {
    "iso:country":"CH",
    "sg:address":"Hauptstrasse 33",
    "sg:city":"Wollerau",
    "sg:orig_category":"Herstellung von K\u00fcchenm\u00f6beln",
    "sg:phone":"+41 17840539",
    "sg:postcode":"8832",
    "sg:province":"Schwyz",
    "wof:name":"Theiler Alois",
    "wof:placetype":"venue"
},
  "geometry": {"coordinates":[8.7186222076,47.1952133179],"type":"Point"}
}