{
  "type": "Feature",
  "properties": {
    "iso:country":"CH",
    "sg:address":"Gotthardstrasse 74",
    "sg:city":"Andermatt",
    "sg:orig_category":"Elektrizit\u00e4tsversorgung",
    "sg:phone":"+41 41 887 12 70",
    "sg:postcode":"6490",
    "sg:province":"Uri",
    "wof:name":"Elektrizit\u00e4tswerk Ursern",
    "wof:placetype":"venue"
},
  "geometry": {"coordinates":[8.5953330994,46.633140564],"type":"Point"}
}