{
  "type": "Feature",
  "properties": {
    "iso:country":"CH",
    "sg:address":"Route D'arnex",
    "sg:city":"Eysins",
    "sg:orig_category":"Unternehmensberatung",
    "sg:phone":"+41 22 362 11 89",
    "sg:postcode":"1262",
    "sg:province":"Vaud",
    "wof:name":"St\u00e9phane Waser Actuaire-conseils Asa",
    "wof:placetype":"venue"
},
  "geometry": {"coordinates":[6.2037391663,46.3815612793],"type":"Point"}
}