{
  "type": "Feature",
  "properties": {
    "addr:full":"Vordergasse 56 Schaffhausen Schaffhausen 8200",
    "addr:housenumber":"56",
    "addr:postcode":"8200",
    "addr:street":"Vordergasse",
    "iso:country":"CH",
    "sg:address":"Vordergasse 56",
    "sg:city":"Schaffhausen",
    "sg:orig_category":"Detailhandel mit Bekleidung Detailhandel mit Damenbekleidung",
    "sg:phone":"+41 52 625 59 49",
    "sg:postcode":"8200",
    "sg:province":"Schaffhausen",
    "wof:name":"Mode-shop Roland Huber",
    "wof:placetype":"venue"
},
  "geometry": {"coordinates":[8.635497,47.696373],"type":"Point"}
}