{
  "type": "Feature",
  "properties": {
    "iso:country":"CH",
    "sg:address":"H\u00fcbeli 6153 Ufhusen. Postfach",
    "sg:city":"Ufhusen",
    "sg:orig_category":"Allgemeiner Hoch U Tiefbau",
    "sg:postcode":"6153",
    "sg:province":"Luzern",
    "wof:name":"Planwerk S Gmbh",
    "wof:placetype":"venue"
},
  "geometry": {"coordinates":[7.892675,47.117199],"type":"Point"}
}