{
  "type": "Feature",
  "properties": {
    "iso:country":"CH",
    "sg:address":"Frobenstrasse 63",
    "sg:city":"Basel",
    "sg:orig_category":"Erbringung von Dienstleistungen f\u00fcr Unternehmen",
    "sg:phone":"+41 61 283 33 03",
    "sg:postcode":"4053",
    "sg:province":"Basel-Stadt",
    "wof:name":"C. + I. Grafik Beschriftung Gmbh",
    "wof:placetype":"venue"
},
  "geometry": {"coordinates":[7.5852150917,47.5436668396],"type":"Point"}
}