{
  "type": "Feature",
  "properties": {
    "iso:country":"CH",
    "sg:address":"7503",
    "sg:city":"Samedan",
    "sg:classifiers":[
        {
            "category":"Travel",
            "subcategory":"Hotels & Motels",
            "type":"Entertainment"
        }
    ],
    "sg:phone":"+41 55 653 12 70",
    "sg:postcode":"7503",
    "sg:province":"Graubunden",
    "sg:tags":[
        "hotels",
        "mit",
        "restaurant"
    ],
    "wof:name":"Hotel-restaurant R\u00fctihof L\u00fc\u00f6nd + Michel",
    "wof:placetype":"venue"
},
  "geometry": {"coordinates":[9.0061674118,46.9284286499],"type":"Point"}
}