{
  "type": "Feature",
  "properties": {
    "iso:country":"CH",
    "sg:address":"Ganischastrasse 25",
    "sg:city":"Flums",
    "sg:orig_category":"Haltung von Rindern",
    "sg:postcode":"8890",
    "sg:province":"St. Gallen",
    "wof:name":"Viehzuchtgenossenschaft Flums-dorf",
    "wof:placetype":"venue"
},
  "geometry": {"coordinates":[9.3396549225,47.0958366394],"type":"Point"}
}