{
  "type": "Feature",
  "properties": {
    "iso:country":"CH",
    "sg:address":"Baarerstrasse 96",
    "sg:city":"Zug",
    "sg:orig_category":"Sonstiger Grosshandel",
    "sg:phone":"+41 71 966 50 27",
    "sg:postcode":"6300",
    "sg:province":"Zug",
    "wof:name":"Schmidli Irina Trade-consulting",
    "wof:placetype":"venue"
},
  "geometry": {"coordinates":[8.996462822,47.4798316956],"type":"Point"}
}