{
  "type": "Feature",
  "properties": {
    "addr:full":"1115 Vullierens Vaud 1115",
    "addr:housenumber":"1115",
    "addr:postcode":"1115",
    "addr:street":"Vullierens",
    "iso:country":"CH",
    "sg:address":"1115",
    "sg:city":"Vullierens",
    "sg:orig_category":"Bauschreinerei Zimmerei, Ingenieurholzbau",
    "sg:phone":"+41 21 869 93 66",
    "sg:postcode":"1115",
    "sg:province":"Vaud",
    "wof:name":"R\u00e9my Demont Menuiserie & Charpenterie",
    "wof:placetype":"venue"
},
  "geometry": {"coordinates":[6.482337,46.57262],"type":"Point"}
}