{
  "type": "Feature",
  "properties": {
    "iso:country":"CH",
    "sg:address":"Grabenstrasse 15 7000 Chur. Postfach",
    "sg:city":"Chur",
    "sg:orig_category":"Sonstiger Grosshandel",
    "sg:phone":"+41 81 252 20 22",
    "sg:postcode":"7000",
    "sg:province":"Graubunden",
    "wof:name":"Clementina Ag",
    "wof:placetype":"venue"
},
  "geometry": {"coordinates":[9.5321493149,46.8507995605],"type":"Point"}
}