{
  "type": "Feature",
  "properties": {
    "iso:country":"CH",
    "sg:address":"Gos Rue Albert- 3 1206 Gen\u00e8ve Case Postale 74",
    "sg:city":"Gen\u00e8ve",
    "sg:orig_category":"Finanzierungsinstitutionen",
    "sg:phone":"+41 22 839 86 15",
    "sg:postcode":"1206",
    "sg:province":"Gen\u00e8ve",
    "wof:name":"Perastra Finance Sa",
    "wof:placetype":"venue"
},
  "geometry": {"coordinates":[6.1560778618,46.1887626648],"type":"Point"}
}