{
  "type": "Feature",
  "properties": {
    "iso:country":"CH",
    "sg:address":"Rhonesandstrasse 13 3900 Brig. Postfach",
    "sg:city":"Brig",
    "sg:orig_category":"Versicherungen Generalagenturen",
    "sg:phone":"+41 27 922 26 80",
    "sg:postcode":"3900",
    "sg:province":"Valais",
    "wof:name":"National-versicherungen Generalagentur Oberwallis",
    "wof:placetype":"venue"
},
  "geometry": {"coordinates":[7.989634037,46.3178482056],"type":"Point"}
}