{
  "type": "Feature",
  "properties": {
    "iso:country":"CH",
    "sg:address":"Grand-rue 47",
    "sg:city":"Ch\u00e2telard-lutry",
    "sg:orig_category":"Datenverarbeitungsdienste Erbringung von Dienstleistungen f\u00fcr Unternehmen",
    "sg:phone":"+41 21 791 11 82",
    "sg:postcode":"1095",
    "sg:province":"Vaud",
    "wof:name":"Simic Informatique, Simon Marcel.",
    "wof:placetype":"venue"
},
  "geometry": {"coordinates":[6.685757,46.503281],"type":"Point"}
}