{
  "type": "Feature",
  "properties": {
    "iso:country":"CH",
    "sg:address":"Gartenstrasse 5c",
    "sg:city":"H\u00fcnenberg",
    "sg:orig_category":"Architektur U Ingenieurb\u00fcros",
    "sg:postcode":"6331",
    "sg:province":"Zug",
    "wof:name":"Emo Consulting Gmbh",
    "wof:placetype":"venue"
},
  "geometry": {"coordinates":[8.428044,47.178955],"type":"Point"}
}