{
  "type": "Feature",
  "properties": {
    "iso:country":"CH",
    "sg:address":"Birkenweg 2",
    "sg:city":"Ersigen",
    "sg:orig_category":"Non-Classified Establishments",
    "sg:postcode":"3423",
    "sg:province":"Bern",
    "wof:name":"Zbinden Architekten Gmbh",
    "wof:placetype":"venue"
},
  "geometry": {"coordinates":[7.6051421165,47.0931167603],"type":"Point"}
}