{
  "type": "Feature",
  "properties": {
    "iso:country":"CH",
    "sg:address":"Alex Rue Pierre 11 1630 Bulle. Postfach",
    "sg:city":"Bulle",
    "sg:orig_category":"Softwareentwicklung U beratung",
    "sg:phone":"+41 26 919 50 89",
    "sg:postcode":"1630",
    "sg:province":"Fribourg",
    "wof:name":"Cm-informatique, Maurer Mat\u00e9riel Informatique; Achat, Vente, R\u00e9paration",
    "wof:placetype":"venue"
},
  "geometry": {"coordinates":[7.0602669716,46.6233291626],"type":"Point"}
}