{
  "type": "Feature",
  "properties": {
    "iso:country":"CH",
    "sg:address":"Hauptstrasse 15",
    "sg:city":"B\u00f6nigen",
    "sg:orig_category":"Detailhandel mit Fleisch U Fleischwaren",
    "sg:phone":"+41 33233450",
    "sg:postcode":"3806",
    "sg:province":"Bern",
    "wof:name":"Heinz Seiler",
    "wof:placetype":"venue"
},
  "geometry": {"coordinates":[7.8916978836,46.6849021912],"type":"Point"}
}