{
  "type": "Feature",
  "properties": {
    "iso:country":"CH",
    "sg:address":"Hinterdorfstrasse 87",
    "sg:city":"Mollis",
    "sg:orig_category":"Instandhaltung U Reparatur von Automobilen",
    "sg:postcode":"8753",
    "sg:province":"Glarus",
    "wof:name":"Van Vliet Dirk, Garage",
    "wof:placetype":"venue"
},
  "geometry": {"coordinates":[9.0724201202,47.1006889343],"type":"Point"}
}