{
  "type": "Feature",
  "properties": {
    "iso:country":"CH",
    "sg:address":"Hottingerstrasse 37",
    "sg:city":"Z\u00fcrich",
    "sg:orig_category":"Detailhandel mit Beleuchtungs U Haushaltsgegenst\u00e4nden Detailhandel mit elektrischen Haushalts-,Radio",
    "sg:phone":"+41 12515223",
    "sg:postcode":"8032",
    "sg:province":"Z\u00fcrich",
    "wof:name":"K\u00fcche & Haushalt Giesbrecht Verena",
    "wof:placetype":"venue"
},
  "geometry": {"coordinates":[8.554249,47.369591],"type":"Point"}
}