{
  "type": "Feature",
  "properties": {
    "iso:country":"CH",
    "sg:address":"Junkholzweg 3",
    "sg:city":"Kaiseraugst",
    "sg:classifiers":[
        {
            "category":"Community Center",
            "subcategory":"Senior",
            "type":"Public Place"
        }
    ],
    "sg:phone":"+41 61 811 22 55",
    "sg:postcode":"4303",
    "sg:province":"Aargau",
    "sg:tags":[
        "steel",
        "metal",
        "part",
        "sheet"
    ],
    "wof:name":"Thommen Stahl Ag",
    "wof:placetype":"venue"
},
  "geometry": {"coordinates":[7.7308330536,47.5379562378],"type":"Point"}
}