{
  "type": "Feature",
  "properties": {
    "iso:country":"CH",
    "sg:address":"Grofstrasse 1",
    "sg:city":"Mels",
    "sg:classifiers":[
        {
            "category":"Travel",
            "subcategory":"Hotels & Motels",
            "type":"Entertainment"
        }
    ],
    "sg:phone":"+41 81 723 65 16",
    "sg:postcode":"8887",
    "sg:province":"St. Gallen",
    "sg:tags":[
        "hotels",
        "mit",
        "restaurant"
    ],
    "wof:name":"Hotel Rebstock, Mullis Martin",
    "wof:placetype":"venue"
},
  "geometry": {"coordinates":[9.4198760986,47.0501289368],"type":"Point"}
}