{
  "type": "Feature",
  "properties": {
    "iso:country":"CH",
    "sg:address":"Dufour Place 2",
    "sg:city":"Morges",
    "sg:orig_category":"Detailhandel mit Brot, Back U S\u00fcsswaren",
    "sg:postcode":"1110",
    "sg:province":"Vaud",
    "wof:name":"Boulangerie-p\u00e2tisserie-confiserie-glacier Michoud S\u00e0rl",
    "wof:placetype":"venue"
},
  "geometry": {"coordinates":[6.495713,46.507782],"type":"Point"}
}