{
  "type": "Feature",
  "properties": {
    "iso:country":"CH",
    "sg:address":"Coll\u00e8ge Rue Du 2 1860 Aigle. Postfach",
    "sg:city":"Aigle",
    "sg:orig_category":"Vermietung U Verpachtung von eigenen Immobilien",
    "sg:postcode":"1860",
    "sg:province":"Vaud",
    "wof:name":"Immob 3000 S\u00e0rl Immobiliers Etc",
    "wof:placetype":"venue"
},
  "geometry": {"coordinates":[6.9702548981,46.3180389404],"type":"Point"}
}