{
  "type": "Feature",
  "properties": {
    "iso:country":"CH",
    "sg:address":"Galsstrasse 3",
    "sg:city":"Erlach",
    "sg:orig_category":"Kunsthandel",
    "sg:phone":"+41 32 338 20 88",
    "sg:postcode":"3235",
    "sg:province":"Bern",
    "wof:name":"Ren\u00e9 Steiner Galerie & Edition",
    "wof:placetype":"venue"
},
  "geometry": {"coordinates":[7.0961952209,47.0452575684],"type":"Point"}
}