{
  "type": "Feature",
  "properties": {
    "iso:country":"CH",
    "sg:address":"Industrie Rue De L' 10 1950 Sitten. Postfach",
    "sg:city":"Sion",
    "sg:orig_category":"Unclassifiable Establishments",
    "sg:postcode":"1950",
    "sg:province":"Valais",
    "wof:name":"Sportaccess Sa Participations Etc",
    "wof:placetype":"venue"
},
  "geometry": {"coordinates":[7.3685722351,46.2284126282],"type":"Point"}
}