{
  "type": "Feature",
  "properties": {
    "iso:country":"CH",
    "sg:address":"Bahnhofstr. 63",
    "sg:city":"Schwyz",
    "sg:classifiers":[
        {
            "category":"Food & Beverages",
            "subcategory":"Groceries & Convenience Stores",
            "type":"Retail Goods"
        }
    ],
    "sg:phone":"+41 41 819 65 65",
    "sg:postcode":"6431",
    "sg:province":"Schwyz",
    "sg:tags":[
        "product",
        "related"
    ],
    "wof:name":"Max Felchlin Ag",
    "wof:placetype":"venue"
},
  "geometry": {"coordinates":[8.641119957,47.0228500366],"type":"Point"}
}