{
  "type": "Feature",
  "properties": {
    "addr:full":"Brahmsweg 9 Thun Bern 3600",
    "addr:housenumber":"9",
    "addr:postcode":"3600",
    "addr:street":"Brahmsweg;Bern",
    "iso:country":"CH",
    "sg:address":"Brahmsweg 9",
    "sg:city":"Thun",
    "sg:orig_category":"Betrieb von Taxis",
    "sg:phone":"+41 33 222 22 22",
    "sg:postcode":"3600",
    "sg:province":"Bern",
    "wof:name":"Alfred Oesch Taxi",
    "wof:placetype":"venue"
},
  "geometry": {"coordinates":[7.622989,46.750835],"type":"Point"}
}