{
  "type": "Feature",
  "properties": {
    "iso:country":"CH",
    "sg:address":"Neuwiesenstrasse 5",
    "sg:city":"Winterthur",
    "sg:orig_category":"Datenverarbeitungsdienste Sonstige mit der Informatik verbundene T\u00e4tigkeiten",
    "sg:phone":"+41 52 202 34 50",
    "sg:postcode":"8400",
    "sg:province":"Z\u00fcrich",
    "wof:name":"Organisation Miller",
    "wof:placetype":"venue"
},
  "geometry": {"coordinates":[8.717476,47.498554],"type":"Point"}
}