{
  "type": "Feature",
  "properties": {
    "addr:full":"Via Lucomagno 6 6710 Biasca. Postfach Biasca Ticino 6710",
    "addr:housenumber":"6",
    "addr:postcode":"6710;6710",
    "addr:street":"Via Lucomagno;Postfach;Ticino",
    "iso:country":"CH",
    "sg:address":"Via Lucomagno 6 6710 Biasca. Postfach",
    "sg:city":"Biasca",
    "sg:orig_category":"Allgemeiner Hoch U Tiefbau",
    "sg:postcode":"6710",
    "sg:province":"Ticino",
    "wof:name":"Porr Suisse Ag, Succursale Di Biasca",
    "wof:placetype":"venue"
},
  "geometry": {"coordinates":[8.971093,46.360504],"type":"Point"}
}