{
  "type": "Feature",
  "properties": {
    "iso:country":"CH",
    "sg:address":"S\u00fcdstrasse 124",
    "sg:city":"Dielsdorf",
    "sg:orig_category":"Non-Classified Establishments",
    "sg:postcode":"8157",
    "sg:province":"Z\u00fcrich",
    "wof:name":"Bisig Richard, Dr. Oec. Publ., Unternehmensberatung",
    "wof:placetype":"venue"
},
  "geometry": {"coordinates":[8.447974205,47.4800415039],"type":"Point"}
}