{
  "type": "Feature",
  "properties": {
    "iso:country":"CH",
    "sg:address":"Tagelswangerstrasse 3 8307 Effretikon. Postfach",
    "sg:city":"Effretikon",
    "sg:orig_category":"Finanzierungsinstitutionen",
    "sg:postcode":"8307",
    "sg:province":"Z\u00fcrich",
    "wof:name":"Walder Andreas Finanzplanung",
    "wof:placetype":"venue"
},
  "geometry": {"coordinates":[8.6855010986,47.4264717102],"type":"Point"}
}