{
  "type": "Feature",
  "properties": {
    "iso:country":"CH",
    "sg:address":"Rue De La Poste 3",
    "sg:city":"Martigny",
    "sg:orig_category":"Autogaragen Personenwagen Grosshandel",
    "sg:phone":"+41 71 466 70 10",
    "sg:postcode":"1920",
    "sg:province":"Valais",
    "wof:name":"Amag Automobil- & Motoren Ag",
    "wof:placetype":"venue"
},
  "geometry": {"coordinates":[9.37359,47.570702],"type":"Point"}
}