{
  "type": "Feature",
  "properties": {
    "iso:country":"CH",
    "sg:address":"Route Des Ecussons 1950 Sion Case Postale 252",
    "sg:city":"Sion",
    "sg:classifiers":[
        {
            "category":"Restaurant",
            "type":"Food & Drink"
        }
    ],
    "sg:phone":"+41 27 345 38 30",
    "sg:postcode":"1951",
    "sg:province":"Valais",
    "wof:name":"Caf\u00e9 Pic-vert",
    "wof:placetype":"venue"
},
  "geometry": {"coordinates":[7.3092131615,46.2135276794],"type":"Point"}
}