{
  "type": "Feature",
  "properties": {
    "iso:country":"CH",
    "sg:address":"Niklaus Wengistrasse 36",
    "sg:city":"Grenchen",
    "sg:orig_category":"Fachdetailhandel in Verkaufsr\u00e4umen",
    "sg:phone":"+41 32 652 24 26",
    "sg:postcode":"2540",
    "sg:province":"Solothurn",
    "wof:name":"Its Inter Time Services",
    "wof:placetype":"venue"
},
  "geometry": {"coordinates":[7.4036288261,47.1877288818],"type":"Point"}
}