{
  "type": "Feature",
  "properties": {
    "iso:country":"CH",
    "sg:address":"Seedorfstrasse 5",
    "sg:city":"Landschlacht",
    "sg:orig_category":"Sonstiger Grosshandel",
    "sg:phone":"+41 71 690 01 77",
    "sg:postcode":"8597",
    "sg:province":"Thurgau",
    "wof:name":"Relax-pool Patrick Reinli Schwimmb\u00e4der Sauna Solarien",
    "wof:placetype":"venue"
},
  "geometry": {"coordinates":[9.2460613251,47.6290206909],"type":"Point"}
}