{
  "type": "Feature",
  "properties": {
    "iso:country":"CH",
    "sg:address":"Rue De La Gare 8",
    "sg:city":"St-aubin-sauges",
    "sg:orig_category":"Grosshandel mit Erzen U Metallen Grosshandel mit sonstigen Konsumg\u00fctern",
    "sg:phone":"+41 17404142",
    "sg:postcode":"2024",
    "sg:province":"Neuch\u00e2tel",
    "wof:name":"Mobia Ag",
    "wof:placetype":"venue"
},
  "geometry": {"coordinates":[8.397151947,47.4199066162],"type":"Point"}
}