{
  "type": "Feature",
  "properties": {
    "iso:country":"CH",
    "sg:address":"Viale Stazione 25",
    "sg:city":"Bellinzona",
    "sg:orig_category":"Detailhandel mit Geschenkartikeln U Souvenirs",
    "sg:phone":"+41 91 826 38 83",
    "sg:postcode":"6500",
    "sg:province":"Ticino",
    "wof:name":"Maria Ventimiglia Boutique Ciao Ciao",
    "wof:placetype":"venue"
},
  "geometry": {"coordinates":[9.0271425247,46.1944541931],"type":"Point"}
}