{
  "type": "Feature",
  "properties": {
    "iso:country":"CH",
    "sg:address":"Am Stausee 13",
    "sg:city":"Birsfelden",
    "sg:classifiers":[
        {
            "category":"Social Services",
            "subcategory":"Retirement Home",
            "type":"Services"
        }
    ],
    "sg:phone":"+41 61 313 01 93",
    "sg:postcode":"4127",
    "sg:province":"Basel-Landschaft",
    "sg:tags":[
        "pflegeheime",
        "u",
        "alters"
    ],
    "wof:name":"Senioren-tagesheim Birsfelden",
    "wof:placetype":"venue"
},
  "geometry": {"coordinates":[7.628481,47.557068],"type":"Point"}
}