{
  "type": "Feature",
  "properties": {
    "iso:country":"CH",
    "sg:address":"Route De Sullens",
    "sg:city":"Villars-ste-croix",
    "sg:orig_category":"Pulvermetallurgie Schmieden, Pressen, Stanzen U Profilwalzen von Metallen",
    "sg:phone":"+41 21 701 30 75",
    "sg:postcode":"1029",
    "sg:province":"Vaud",
    "wof:name":"Thommen Poin\u00e7onnage Sa",
    "wof:placetype":"venue"
},
  "geometry": {"coordinates":[6.5717749596,46.5742340088],"type":"Point"}
}