{
  "type": "Feature",
  "properties": {
    "iso:country":"CH",
    "sg:address":"Ringstrasse 11a",
    "sg:city":"Siebnen",
    "sg:orig_category":"Detailhandel mit M\u00f6beln U Haushaltsgegenst\u00e4nden",
    "sg:phone":"+41 41 743 16 10",
    "sg:postcode":"8854",
    "sg:province":"Schwyz",
    "wof:name":"Belle Decoration Ag",
    "wof:placetype":"venue"
},
  "geometry": {"coordinates":[8.9093265533,47.1745223999],"type":"Point"}
}