{
  "type": "Feature",
  "properties": {
    "iso:country":"CH",
    "sg:address":"Bellerivestrasse 42 8008 Z\u00fcrich. Postfach",
    "sg:city":"Z\u00fcrich",
    "sg:orig_category":"Interessenvertretungen",
    "sg:postcode":"8001",
    "sg:province":"Z\u00fcrich",
    "wof:name":"Foundation For Interventional Imaging And Radiology Research And Education In Europe (f.i.r.e.) F\u00f6rderung D. Forschung U. Ausbildung Im Bereich Diagnostische U. Interventionelle Radiologie U. Bildgebu",
    "wof:placetype":"venue"
},
  "geometry": {"coordinates":[8.5507879257,47.3570480347],"type":"Point"}
}