{
  "type": "Feature",
  "properties": {
    "iso:country":"CH",
    "sg:address":"Heinihalde 63",
    "sg:city":"Bellikon",
    "sg:orig_category":"Haltung von Rindern",
    "sg:postcode":"5454",
    "sg:province":"Aargau",
    "wof:name":"Fleckviehzuchtgenossenschaft Benken Zh",
    "wof:placetype":"venue"
},
  "geometry": {"coordinates":[8.6528196335,47.6536598206],"type":"Point"}
}