{
  "type": "Feature",
  "properties": {
    "iso:country":"CH",
    "sg:address":"1426",
    "sg:city":"Concise",
    "sg:orig_category":"Unclassifiable Establishments",
    "sg:postcode":"1426",
    "sg:province":"Vaud",
    "wof:name":"Si De La Petite Gryonne",
    "wof:placetype":"venue"
},
  "geometry": {"coordinates":[6.9953799248,46.2966117859],"type":"Point"}
}