{
  "type": "Feature",
  "properties": {
    "addr:full":"Bahnhofstrasse 33 2502 Biel/bienne Case Postale 844 Biel/bienne Bern 2501",
    "addr:housenumber":"33;844",
    "addr:postcode":"2502;2501",
    "addr:street":"Bahnhofstrasse;Postale",
    "iso:country":"CH",
    "sg:address":"Bahnhofstrasse 33 2502 Biel/bienne Case Postale 844",
    "sg:city":"Biel/bienne",
    "sg:orig_category":"Aktivit\u00e4t der Bankinstitute",
    "sg:phone":"+41 32 328 81 81",
    "sg:postcode":"2501",
    "sg:province":"Bern",
    "wof:name":"Bank Coop Gesch\u00e4ftsstelle Biel",
    "wof:placetype":"venue"
},
  "geometry": {"coordinates":[7.24412,47.133179],"type":"Point"}
}