{
  "type": "Feature",
  "properties": {
    "addr:full":"7424 Pr\u00e4z Graubunden 7424",
    "addr:housenumber":"7424",
    "addr:postcode":"7424",
    "addr:street":"Praez Graubunden",
    "iso:country":"CH",
    "sg:address":"7424",
    "sg:city":"Pr\u00e4z",
    "sg:orig_category":"Bezirks, Sekundar, Realschulen, Oberstufe der Primarschulen",
    "sg:phone":"+41 81 723 66 35",
    "sg:postcode":"7424",
    "sg:province":"Graubunden",
    "wof:name":"Sekundarschule",
    "wof:placetype":"venue"
},
  "geometry": {"coordinates":[9.404459,46.741058],"type":"Point"}
}