{
  "type": "Feature",
  "properties": {
    "iso:country":"CH",
    "sg:address":"Rue Gustave Amweg 51",
    "sg:city":"Porrentruy",
    "sg:classifiers":[
        {
            "category":"Insurance",
            "subcategory":"Insurance Agent",
            "type":"Services"
        }
    ],
    "sg:phone":"+41 32 466 31 31",
    "sg:postcode":"2900",
    "sg:province":"Jura",
    "sg:tags":[
        "versicherungsagenturen",
        "-broker"
    ],
    "wof:name":"Vaudoise Assurances Bureau De Porrentruy",
    "wof:placetype":"venue"
},
  "geometry": {"coordinates":[7.0795102119,47.4205207825],"type":"Point"}
}