{
  "type": "Feature",
  "properties": {
    "iso:country":"CH",
    "sg:address":"Rue De Malagny 6a",
    "sg:city":"Gland",
    "sg:orig_category":"Personal U Stellenvermittlung Unternehmensberatung",
    "sg:phone":"+41 22 364 62 00",
    "sg:postcode":"1196",
    "sg:province":"Vaud",
    "wof:name":"Ace Complete Outsourcing Services S\u00e0rl",
    "wof:placetype":"venue"
},
  "geometry": {"coordinates":[6.2785391808,46.4180107117],"type":"Point"}
}