{
  "type": "Feature",
  "properties": {
    "iso:country":"CH",
    "sg:address":"Borgo Via 7",
    "sg:city":"Ascona",
    "sg:orig_category":"Detailhandel mit Bekleidung",
    "sg:phone":"+41 91 791 17 66",
    "sg:postcode":"6612",
    "sg:province":"Ticino",
    "wof:name":"Boutique Ren\u00e9e Sagl",
    "wof:placetype":"venue"
},
  "geometry": {"coordinates":[8.768405,46.156239],"type":"Point"}
}