{
  "type": "Feature",
  "properties": {
    "iso:country":"CH",
    "sg:address":"Br\u00fcckenstrasse 12",
    "sg:city":"Huttwil",
    "sg:orig_category":"Schlossereien Stahl U Leichtmetallbau",
    "sg:phone":"+41 62 962 33 62",
    "sg:postcode":"4950",
    "sg:province":"Bern",
    "wof:name":"Greub Schlosserei Ag Konstruktionsschlosserei",
    "wof:placetype":"venue"
},
  "geometry": {"coordinates":[7.8644142151,47.1163902283],"type":"Point"}
}