{
  "type": "Feature",
  "properties": {
    "iso:country":"CH",
    "sg:address":"1921 Martigny-croix Case Postale 20",
    "sg:city":"Martigny-croix",
    "sg:orig_category":"Sportvereine Ballsport Fussball",
    "sg:phone":"+41 32 933 99 39",
    "sg:postcode":"1921",
    "sg:province":"Valais",
    "wof:name":"Fc La Sagne",
    "wof:placetype":"venue"
},
  "geometry": {"coordinates":[6.8148818016,47.0494384766],"type":"Point"}
}