{
  "type": "Feature",
  "properties": {
    "iso:country":"CH",
    "sg:address":"Via Al Forte 3",
    "sg:city":"Lugano",
    "sg:orig_category":"Vermietung U Verpachtung von eigenen Immobilien",
    "sg:postcode":"6900",
    "sg:province":"Ticino",
    "wof:name":"Immobiliare Comorgio Sa",
    "wof:placetype":"venue"
},
  "geometry": {"coordinates":[8.9533481598,46.0056495667],"type":"Point"}
}