{
  "type": "Feature",
  "properties": {
    "addr:full":"Flumis 171b. Untervaz Graubunden 7204",
    "addr:housenumber":"171b;7204",
    "addr:street":"Untervaz Graubunden",
    "iso:country":"CH",
    "sg:address":"Flumis 171b.",
    "sg:city":"Untervaz",
    "sg:orig_category":"Allgemeiner Hoch U Tiefbau",
    "sg:phone":"+41 81 935 11 12",
    "sg:postcode":"7204",
    "sg:province":"Graubunden",
    "wof:name":"Berni Bau Ag",
    "wof:placetype":"venue"
},
  "geometry": {"coordinates":[9.26783,46.815769],"type":"Point"}
}