{
  "type": "Feature",
  "properties": {
    "iso:country":"CH",
    "sg:address":"Sumpfstrasse 32 6300 Zug. Postfach",
    "sg:city":"Zug",
    "sg:orig_category":"Mechanik",
    "sg:postcode":"6300",
    "sg:province":"Zug",
    "wof:name":"Copera Rogenmoser & K\u00e4gi",
    "wof:placetype":"venue"
},
  "geometry": {"coordinates":[8.4851512909,47.1778526306],"type":"Point"}
}