{
  "type": "Feature",
  "properties": {
    "iso:country":"CH",
    "sg:address":"3822",
    "sg:city":"Lauterbrunnen",
    "sg:orig_category":"RESTAURANTS: TEA-ROOMS",
    "sg:postcode":"3822",
    "sg:province":"Bern",
    "wof:name":"Thomasius Max",
    "wof:placetype":"venue"
},
  "geometry": {"coordinates":[9.8188991547,46.7913131714],"type":"Point"}
}