{
  "type": "Feature",
  "properties": {
    "addr:full":"St. Jakobstrasse 54 Z\u00fcrich Z\u00fcrich 8004",
    "addr:housenumber":"54",
    "addr:postcode":"8004",
    "addr:street":"St. Jakobstrasse",
    "iso:country":"CH",
    "sg:address":"St. Jakobstrasse 54",
    "sg:city":"Z\u00fcrich",
    "sg:orig_category":"Bauschreinerei Herstellung von M\u00f6beln verschiedener Art",
    "sg:phone":"+41 12413258",
    "sg:postcode":"8004",
    "sg:province":"Z\u00fcrich",
    "wof:name":"Fritz Furrer Bauschreinerei Stabilia M\u00f6bel",
    "wof:placetype":"venue"
},
  "geometry": {"coordinates":[8.530526,47.37537],"type":"Point"}
}