{
  "type": "Feature",
  "properties": {
    "iso:country":"CH",
    "sg:address":"Hinterwees",
    "sg:city":"Gonten",
    "sg:orig_category":"Wirtschaftsverb\u00e4nde Industrie, Handel and Gewerbe",
    "sg:phone":"+41 71 794 10 06",
    "sg:postcode":"9108",
    "sg:province":"Appenzell Innerhoden",
    "wof:name":"Alt\u00f6lenergie-genossenschaft",
    "wof:placetype":"venue"
},
  "geometry": {"coordinates":[9.3437042236,47.3260803223],"type":"Point"}
}