{
  "type": "Feature",
  "properties": {
    "iso:country":"CH",
    "sg:address":"Geibelstrasse 5",
    "sg:city":"Z\u00fcrich",
    "sg:classifiers":[
        {
            "category":"Professional",
            "subcategory":"Advertising",
            "type":"Services"
        }
    ],
    "sg:phone":"+41 12715150",
    "sg:postcode":"8037",
    "sg:province":"Z\u00fcrich",
    "sg:tags":[
        "postcard"
    ],
    "wof:name":"Prader + Studer Ag",
    "wof:placetype":"venue"
},
  "geometry": {"coordinates":[8.529084,47.394772],"type":"Point"}
}