{
  "type": "Feature",
  "properties": {
    "iso:country":"CH",
    "sg:address":"Frey.heros\u00e9-strasse 20",
    "sg:city":"Aarau",
    "sg:orig_category":"Advokaturb\u00fcros Notariate",
    "sg:phone":"+41 62 824 84 00",
    "sg:postcode":"5000",
    "sg:province":"Aargau",
    "wof:name":"Zinniker Fischer & L\u00fcscher Advokatur- & Notariatsb\u00fcro",
    "wof:placetype":"venue"
},
  "geometry": {"coordinates":[8.051982,47.389935],"type":"Point"}
}