{
  "type": "Feature",
  "properties": {
    "iso:country":"CH",
    "sg:address":"Gewerbestrasse 9",
    "sg:city":"Subingen",
    "sg:orig_category":"Herstellung von Fenstern U T\u00fcren aus Holz Herstellung von Konstruktionsteilen, Fertigbauteilen U Aus",
    "sg:phone":"+41 32 614 12 30",
    "sg:postcode":"4553",
    "sg:province":"Solothurn",
    "wof:name":"Balmer Ag Subingen",
    "wof:placetype":"venue"
},
  "geometry": {"coordinates":[7.6049418449,47.196559906],"type":"Point"}
}