{
  "type": "Feature",
  "properties": {
    "iso:country":"CH",
    "sg:address":"Industriestrasse 10 4806 Wikon. Postfach",
    "sg:city":"Wikon",
    "sg:orig_category":"Pensionskassen",
    "sg:postcode":"4806",
    "sg:province":"Luzern",
    "wof:name":"Personalf\u00fcrsorgestiftung Der Pilkington Glas Wikon Ag",
    "wof:placetype":"venue"
},
  "geometry": {"coordinates":[7.9635829926,47.2565155029],"type":"Point"}
}