{
  "type": "Feature",
  "properties": {
    "iso:country":"CH",
    "sg:address":"Schwanenplatz 6a",
    "sg:city":"Luzern",
    "sg:orig_category":"Markt U Meinungsforschung Wirtschaftspr\u00fcfung, Steuerberatung U Treuhand",
    "sg:phone":"+41 26 341 90 40",
    "sg:postcode":"6004",
    "sg:province":"Luzern",
    "wof:name":"Innovative Concept Schmid Rita",
    "wof:placetype":"venue"
},
  "geometry": {"coordinates":[8.3085870743,47.0537033081],"type":"Point"}
}