{
  "type": "Feature",
  "properties": {
    "iso:country":"CH",
    "sg:address":"Kantonsschulstrasse 23",
    "sg:city":"B\u00fclach",
    "sg:orig_category":"Maturit\u00e4tsschulen, Lehrerseminarien",
    "sg:phone":"+41 18723131",
    "sg:postcode":"8180",
    "sg:province":"Z\u00fcrich",
    "wof:name":"Kantonsschule Z\u00fcrcher Unterland",
    "wof:placetype":"venue"
},
  "geometry": {"coordinates":[8.547039032,47.5180053711],"type":"Point"}
}