{
  "type": "Feature",
  "properties": {
    "iso:country":"CH",
    "sg:address":"Via Pioda 9",
    "sg:city":"Freienbach",
    "sg:orig_category":"Finanzierungsinstitutionen",
    "sg:phone":"+41 17847422",
    "sg:postcode":"8807",
    "sg:province":"Schwyz",
    "wof:name":"Marian Ag.",
    "wof:placetype":"venue"
},
  "geometry": {"coordinates":[8.7577753067,47.2063064575],"type":"Point"}
}