{
  "type": "Feature",
  "properties": {
    "iso:country":"CH",
    "sg:address":"Obere H\u00f6nggerstrasse 15",
    "sg:city":"Unterengstringen",
    "sg:orig_category":"Handelsvermittlung U Grosshandel Herstellung von k\u00e4lte U lufttechnischen Erzeugnissen f\u00fcr gewerblich",
    "sg:phone":"+41 17503787",
    "sg:postcode":"8103",
    "sg:province":"Z\u00fcrich",
    "wof:name":"Narr Gmbh Schweiz K\u00fchlzellensysteme",
    "wof:placetype":"venue"
},
  "geometry": {"coordinates":[8.4514560699,47.4117584229],"type":"Point"}
}