{
  "type": "Feature",
  "properties": {
    "iso:country":"CH",
    "sg:address":"Obere Hauptgasse 33",
    "sg:city":"Thun",
    "sg:orig_category":"Fachdetailhandel mit pharmazeutischen Produkten",
    "sg:phone":"+41 33 222 45 51",
    "sg:postcode":"3600",
    "sg:province":"Bern",
    "wof:name":"Schloss-apotheke, Fellmann T.",
    "wof:placetype":"venue"
},
  "geometry": {"coordinates":[7.6298761368,46.7589302063],"type":"Point"}
}