{
  "type": "Feature",
  "properties": {
    "iso:country":"CH",
    "sg:address":"St\u00fcssistrasse 59",
    "sg:city":"Z\u00fcrich",
    "sg:orig_category":"Detailhandel mit M\u00f6beln",
    "sg:phone":"+41 34 445 55 15",
    "sg:postcode":"8057",
    "sg:province":"Z\u00fcrich",
    "wof:name":"Eric Weber Werbe-dekor",
    "wof:placetype":"venue"
},
  "geometry": {"coordinates":[7.5844497681,47.0851898193],"type":"Point"}
}