{
  "type": "Feature",
  "properties": {
    "iso:country":"CH",
    "sg:address":"Im T\u00e4li 5",
    "sg:city":"Zollikofen",
    "sg:orig_category":"Softwareentwicklung U beratung Unternehmensberatung",
    "sg:phone":"+41 31 911 25 50",
    "sg:postcode":"3052",
    "sg:province":"Bern",
    "wof:name":"Emc M\u00fcller Edgar Consulting",
    "wof:placetype":"venue"
},
  "geometry": {"coordinates":[7.4446058273,46.9989433289],"type":"Point"}
}