{
  "type": "Feature",
  "properties": {
    "iso:country":"CH",
    "sg:address":"Luziaweg 9",
    "sg:city":"Freienbach",
    "sg:orig_category":"Wirtschaftspr\u00fcfung, Steuerberatung U Treuhand",
    "sg:phone":"+41 55 410 72 34",
    "sg:postcode":"8807",
    "sg:province":"Schwyz",
    "wof:name":"Roos Peter Treuhand",
    "wof:placetype":"venue"
},
  "geometry": {"coordinates":[8.7625465393,47.2031135559],"type":"Point"}
}