{
  "type": "Feature",
  "properties": {
    "iso:country":"CH",
    "sg:address":"G\u00fcterstrasse 8 3150 Schwarzenburg. Postfach",
    "sg:city":"Schwarzenburg",
    "sg:orig_category":"Pensionskassen",
    "sg:postcode":"3150",
    "sg:province":"Bern",
    "wof:name":"Personalf\u00fcrsorgestiftung Hans Binggeli Ag",
    "wof:placetype":"venue"
},
  "geometry": {"coordinates":[7.3443517685,46.8192329407],"type":"Point"}
}