{
  "type": "Feature",
  "properties": {
    "iso:country":"CH",
    "sg:address":"Im Grund 30",
    "sg:city":"Gretzenbach",
    "sg:orig_category":"Herstellung von Metallkonstruktionen Stahl U Leichtmetallbau",
    "sg:phone":"+41 62 849 15 56",
    "sg:postcode":"5014",
    "sg:province":"Solothurn",
    "wof:name":"Hch. Schnyder Ag",
    "wof:placetype":"venue"
},
  "geometry": {"coordinates":[7.9918007851,47.3582458496],"type":"Point"}
}