{
  "type": "Feature",
  "properties": {
    "iso:country":"CH",
    "sg:address":"Rue Du Pont-mur\u00e9 4",
    "sg:city":"Fribourg",
    "sg:orig_category":"Detailhandel mit fotografischen Artikeln Fotografische Ateliers",
    "sg:phone":"+41 26 322 27 05",
    "sg:postcode":"1700",
    "sg:province":"Fribourg",
    "wof:name":"Jean M\u00fclhauser",
    "wof:placetype":"venue"
},
  "geometry": {"coordinates":[7.1614551544,46.8059997559],"type":"Point"}
}