{
  "type": "Feature",
  "properties": {
    "iso:country":"CH",
    "sg:address":"Unteraustrasse 30",
    "sg:city":"Kradolf",
    "sg:orig_category":"Betrieb von Sportanlagen",
    "sg:postcode":"9214",
    "sg:province":"Thurgau",
    "wof:name":"Genossenschaft Schwimmbad Thurfeld",
    "wof:placetype":"venue"
},
  "geometry": {"coordinates":[9.2017,47.52422],"type":"Point"}
}