{
  "type": "Feature",
  "properties": {
    "iso:country":"CH",
    "sg:address":"Burgauerstrasse 48",
    "sg:city":"Flawil",
    "sg:classifiers":[
        {
            "category":"Wholesale",
            "subcategory":"Electrical",
            "type":"Manufacturing & Wholesale Goods"
        }
    ],
    "sg:phone":"+41 71 394 10 62",
    "sg:postcode":"9230",
    "sg:province":"St. Gallen",
    "sg:tags":[
        "heat",
        "pump",
        "system"
    ],
    "wof:name":"Carnovision Ag",
    "wof:placetype":"venue"
},
  "geometry": {"coordinates":[9.2008190155,47.4103393555],"type":"Point"}
}