{
  "type": "Feature",
  "properties": {
    "iso:country":"CH",
    "sg:address":"3306",
    "sg:city":"Etzelkofen",
    "sg:orig_category":"Primarschulen",
    "sg:phone":"+41 31 765 53 02",
    "sg:postcode":"3306",
    "sg:province":"Bern",
    "wof:name":"Primarschule",
    "wof:placetype":"venue"
},
  "geometry": {"coordinates":[7.4799199104,47.0840911865],"type":"Point"}
}