{
  "type": "Feature",
  "properties": {
    "iso:country":"CH",
    "sg:address":"Tittwiesenstrasse 66",
    "sg:city":"Chur",
    "sg:orig_category":"Detailhandel mit Waren verschiedener Art, Hauptrichtung Nahrungsmittel",
    "sg:phone":"+41 81 286 92 30",
    "sg:postcode":"7000",
    "sg:province":"Graubunden",
    "wof:name":"Coop Ostschweiz",
    "wof:placetype":"venue"
},
  "geometry": {"coordinates":[9.5266103745,46.8591156006],"type":"Point"}
}