{
  "type": "Feature",
  "properties": {
    "iso:country":"CH",
    "sg:address":"Weggisgasse 8",
    "sg:city":"Luzern",
    "sg:orig_category":"Detailhandel mit Uhren U Schmuck Reparatur von Uhren U Schmuck",
    "sg:phone":"+41 41 410 33 88",
    "sg:postcode":"6004",
    "sg:province":"Luzern",
    "wof:name":"Adam Bijouterie & Uhren",
    "wof:placetype":"venue"
},
  "geometry": {"coordinates":[8.3093919754,47.0633811951],"type":"Point"}
}