{
  "type": "Feature",
  "properties": {
    "iso:country":"CH",
    "sg:address":"Pfannenstielstrasse",
    "sg:city":"Meilen",
    "sg:orig_category":"Allgemeiner Hoch U Tiefbau",
    "sg:postcode":"8706",
    "sg:province":"Z\u00fcrich",
    "wof:name":"Billeter Walter",
    "wof:placetype":"venue"
},
  "geometry": {"coordinates":[8.652545,47.270229],"type":"Point"}
}