{
  "type": "Feature",
  "properties": {
    "iso:country":"CH",
    "sg:address":"Ibelweg 18a 6340 Baar. Postfach 143",
    "sg:city":"Zug",
    "sg:orig_category":"Vermittlung von Immobilien Verwaltung von Immobilien",
    "sg:phone":"+41 41 760 02 62",
    "sg:postcode":"6301",
    "sg:province":"Zug",
    "wof:name":"Gasser Und Partner Immobilien Ag",
    "wof:placetype":"venue"
},
  "geometry": {"coordinates":[8.5254907608,47.1805229187],"type":"Point"}
}