{
  "type": "Feature",
  "properties": {
    "iso:country":"CH",
    "sg:address":"Aebischen 39",
    "sg:city":"Frauenkappelen",
    "sg:orig_category":"Gem\u00fcsebau Obstbau",
    "sg:phone":"+41 26 663 26 50",
    "sg:postcode":"3202",
    "sg:province":"Bern",
    "wof:name":"Jean-claude Marmy Production De Fruits & L\u00e9gumes",
    "wof:placetype":"venue"
},
  "geometry": {"coordinates":[6.8875799179,46.8348007202],"type":"Point"}
}