{
  "type": "Feature",
  "properties": {
    "addr:full":"Ratsteig 4 Thayngen Schaffhausen 8240",
    "addr:housenumber":"4",
    "addr:postcode":"8240",
    "addr:street":"Ratsteig",
    "iso:country":"CH",
    "sg:address":"Ratsteig 4",
    "sg:city":"Thayngen",
    "sg:orig_category":"Bauschreinerei Detailhandel mit Sportartikeln",
    "sg:phone":"+41 52 649 36 56",
    "sg:postcode":"8240",
    "sg:province":"Schaffhausen",
    "wof:name":"Ernst Stamm",
    "wof:placetype":"venue"
},
  "geometry": {"coordinates":[8.71,47.748055],"type":"Point"}
}