{
  "type": "Feature",
  "properties": {
    "iso:country":"CH",
    "sg:address":"Schwerzistrasse 6 8807 Freienbach. Postfach",
    "sg:city":"Freienbach",
    "sg:orig_category":"Herstellung von Metallerzeugnissen ohne Maschinenbau Maschinenbau",
    "sg:phone":"+41 55 410 35 23",
    "sg:postcode":"8807",
    "sg:province":"Schwyz",
    "wof:name":"R\u00f6thlin Urs Ag",
    "wof:placetype":"venue"
},
  "geometry": {"coordinates":[8.7587518692,47.2014312744],"type":"Point"}
}