{
  "type": "Feature",
  "properties": {
    "iso:country":"CH",
    "sg:address":"Grossackerstrasse 73",
    "sg:city":"Z\u00fcrich",
    "sg:orig_category":"Saunas, Solarien, Fitnesszentren U \u00e4hnliches",
    "sg:phone":"+41 14812217",
    "sg:postcode":"8041",
    "sg:province":"Z\u00fcrich",
    "wof:name":"Z\u00fcrifit Ag",
    "wof:placetype":"venue"
},
  "geometry": {"coordinates":[8.5097198486,47.324508667],"type":"Point"}
}