{
  "type": "Feature",
  "properties": {
    "iso:country":"CH",
    "sg:address":"Luzernerstrasse 20",
    "sg:city":"Sins",
    "sg:orig_category":"Kantonalbanken",
    "sg:phone":"+41 41 789 71 11",
    "sg:postcode":"5643",
    "sg:province":"Aargau",
    "wof:name":"Aargauische Kantonalbank",
    "wof:placetype":"venue"
},
  "geometry": {"coordinates":[8.3961277008,47.1882286072],"type":"Point"}
}