{
  "type": "Feature",
  "properties": {
    "iso:country":"CH",
    "sg:address":"Lindenstrasse 12a 8370 Sirnach. Postfach",
    "sg:city":"Sirnach",
    "sg:orig_category":"Allgemeiner Hoch U Tiefbau",
    "sg:postcode":"8370",
    "sg:province":"Thurgau",
    "wof:name":"A & B Lagrotteria A. Und Maiolo B.",
    "wof:placetype":"venue"
},
  "geometry": {"coordinates":[8.990911,47.461536],"type":"Point"}
}