{
  "type": "Feature",
  "properties": {
    "iso:country":"CH",
    "sg:address":"Route L\u00e9man 10",
    "sg:city":"Vionnaz",
    "sg:orig_category":"Nationale Postdienste",
    "sg:phone":"+41 24 481 11 25",
    "sg:postcode":"1895",
    "sg:province":"Valais",
    "wof:name":"La Poste Suisse",
    "wof:placetype":"venue"
},
  "geometry": {"coordinates":[6.9007668495,46.3109817505],"type":"Point"}
}