{
  "type": "Feature",
  "properties": {
    "iso:country":"CH",
    "sg:address":"Letzistrasse 32",
    "sg:city":"Zug",
    "sg:orig_category":"Wirtschaftspr\u00fcfung, Steuerberatung U Treuhand",
    "sg:postcode":"6300",
    "sg:province":"Zug",
    "wof:name":"Ring-treuhand Curt Jauch",
    "wof:placetype":"venue"
},
  "geometry": {"coordinates":[8.5030879974,47.179851532],"type":"Point"}
}