{
  "type": "Feature",
  "properties": {
    "iso:country":"CH",
    "sg:address":"Schwarzwaldalp-alp",
    "sg:city":"Meiringen",
    "sg:classifiers":[
        {
            "category":"Travel",
            "subcategory":"Hotels & Motels",
            "type":"Entertainment"
        }
    ],
    "sg:phone":"+41 33 971 35 15",
    "sg:postcode":"3860",
    "sg:province":"Bern",
    "sg:tags":[
        "hotels",
        "mit",
        "restaurant"
    ],
    "wof:name":"Hotel Schwarzwald-alp",
    "wof:placetype":"venue"
},
  "geometry": {"coordinates":[8.1340703964,46.6754608154],"type":"Point"}
}