{
  "type": "Feature",
  "properties": {
    "iso:country":"CH",
    "sg:address":"Bachmattweg 20",
    "sg:city":"Z\u00fcrich",
    "sg:orig_category":"Non-Classified Establishments",
    "sg:phone":"+41 14304035",
    "sg:postcode":"8048",
    "sg:province":"Z\u00fcrich",
    "wof:name":"Silvia Streule Kinderkrippe Gummib\u00e4rli",
    "wof:placetype":"venue"
},
  "geometry": {"coordinates":[8.4848680496,47.3903999329],"type":"Point"}
}