{
  "type": "Feature",
  "properties": {
    "iso:country":"CH",
    "sg:address":"Pr\u00e9 De L'etang Route Du 6",
    "sg:city":"Villars-sur-gl\u00e2ne",
    "sg:orig_category":"Elektroinstallation",
    "sg:phone":"+41 32 925 99 99",
    "sg:postcode":"1752",
    "sg:province":"Fribourg",
    "wof:name":"Instel Sa",
    "wof:placetype":"venue"
},
  "geometry": {"coordinates":[6.8222398758,47.0933837891],"type":"Point"}
}