{
  "type": "Feature",
  "properties": {
    "iso:country":"CH",
    "sg:address":"Vordere Hauptgasse 71",
    "sg:city":"Zofingen",
    "sg:orig_category":"Detailhandel mit Textilien",
    "sg:phone":"+41 62 751 82 00",
    "sg:postcode":"4800",
    "sg:province":"Aargau",
    "wof:name":"Tendenza Donna Ursula Kettner",
    "wof:placetype":"venue"
},
  "geometry": {"coordinates":[7.9458041191,47.2874717712],"type":"Point"}
}