{
  "type": "Feature",
  "properties": {
    "iso:country":"CH",
    "sg:address":"Hegifeldstrasse 10 8400 Winterthur. Postfach 414",
    "sg:city":"Winterthur",
    "sg:orig_category":"Herstellung von Pumpen U Kompressoren",
    "sg:phone":"+41 52 262 11 55",
    "sg:postcode":"8401",
    "sg:province":"Z\u00fcrich",
    "wof:name":"Sulzer Pumpen Ag",
    "wof:placetype":"venue"
},
  "geometry": {"coordinates":[8.7621946335,47.5068817139],"type":"Point"}
}