{
  "type": "Feature",
  "properties": {
    "iso:country":"CH",
    "sg:address":"March\u00e9-neuf 9.",
    "sg:city":"Arch",
    "sg:orig_category":"Fachdetailhandel in Verkaufsr\u00e4umen",
    "sg:postcode":"3296",
    "sg:province":"Bern",
    "wof:name":"Hanifi Chantal.",
    "wof:placetype":"venue"
},
  "geometry": {"coordinates":[7.4276208878,47.1672363281],"type":"Point"}
}