{
  "type": "Feature",
  "properties": {
    "iso:country":"CH",
    "sg:address":"6549 Laura. Postfach",
    "sg:city":"Laura",
    "sg:orig_category":"Allgemeiner Hoch U Tiefbau",
    "sg:postcode":"6549",
    "sg:province":"Graubunden",
    "wof:name":"Cerini Guido & Cie, Succursale Des Bois",
    "wof:placetype":"venue"
},
  "geometry": {"coordinates":[6.90461,47.176064],"type":"Point"}
}