{
  "type": "Feature",
  "properties": {
    "iso:country":"CH",
    "sg:address":"Pramylon",
    "sg:city":"Nax",
    "sg:orig_category":"Grosshandel mit lebenden Tieren",
    "sg:phone":"+41 27 203 42 85",
    "sg:postcode":"1973",
    "sg:province":"Valais",
    "wof:name":"Raymond Favre Commerce De B\u00e9tail",
    "wof:placetype":"venue"
},
  "geometry": {"coordinates":[7.4267139435,46.227809906],"type":"Point"}
}