{
  "type": "Feature",
  "properties": {
    "iso:country":"CH",
    "sg:address":"Wiesenstrasse 22",
    "sg:city":"Thalwil",
    "sg:orig_category":"Sanit\u00e4r, Heizungs U L\u00fcftungsinstallation Sanit\u00e4rinstallation",
    "sg:phone":"+41 17201615",
    "sg:postcode":"8800",
    "sg:province":"Z\u00fcrich",
    "wof:name":"Lang H.p.",
    "wof:placetype":"venue"
},
  "geometry": {"coordinates":[8.5664148331,47.2896194458],"type":"Point"}
}