{
  "type": "Feature",
  "properties": {
    "addr:full":"Hauptstrasse Murg St. Gallen 8877",
    "addr:postcode":"8877",
    "addr:street":"Hauptstrasse",
    "iso:country":"CH",
    "sg:address":"Hauptstrasse",
    "sg:city":"Murg",
    "sg:classifiers":[
        {
            "category":"Banks & Credit Unions",
            "subcategory":"Bank",
            "type":"Services"
        }
    ],
    "sg:phone":"+41 81 738 16 26",
    "sg:postcode":"8877",
    "sg:province":"St. Gallen",
    "wof:name":"Raiffeisenbank Murg",
    "wof:placetype":"venue"
},
  "geometry": {"coordinates":[9.216112,47.113022],"type":"Point"}
}