{
  "type": "Feature",
  "properties": {
    "iso:country":"CH",
    "sg:address":"Route Aloys-fauquez 106",
    "sg:city":"Lausanne",
    "sg:orig_category":"Non-Classified Establishments",
    "sg:postcode":"1018",
    "sg:province":"Vaud",
    "wof:name":"Pierre M\u00fcrner, Bauunternehmung + Immobilien",
    "wof:placetype":"venue"
},
  "geometry": {"coordinates":[7.6936101913,46.6225547791],"type":"Point"}
}