{
  "type": "Feature",
  "properties": {
    "iso:country":"CH",
    "sg:address":"L\u00e4ngmatt 3",
    "sg:city":"Ettiswil",
    "sg:orig_category":"G\u00fcterbef\u00f6rderung im Strassenverkehr",
    "sg:phone":"+41 41 980 10 75",
    "sg:postcode":"6218",
    "sg:province":"Luzern",
    "wof:name":"Hans Duss Transporte",
    "wof:placetype":"venue"
},
  "geometry": {"coordinates":[8.0200109482,47.1462249756],"type":"Point"}
}