{
  "type": "Feature",
  "properties": {
    "iso:country":"CH",
    "sg:address":"Wolfbuchenoberstocken",
    "sg:city":"Stocken",
    "sg:orig_category":"Sportvereine Wassersport",
    "sg:phone":"+41 33 341 13 91",
    "sg:postcode":"3632",
    "sg:province":"Bern",
    "wof:name":"Kanu Klub Thun",
    "wof:placetype":"venue"
},
  "geometry": {"coordinates":[7.5561900139,46.7165985107],"type":"Point"}
}