{
  "type": "Feature",
  "properties": {
    "iso:country":"CH",
    "sg:address":"Hallenstrasse 10",
    "sg:city":"Z\u00fcrich",
    "sg:classifiers":[
        {
            "category":"Communications",
            "subcategory":"Film & Video Production",
            "type":"Services"
        }
    ],
    "sg:phone":"+41 12536555",
    "sg:postcode":"8008",
    "sg:province":"Z\u00fcrich",
    "sg:tags":[
        "videoaktivit\u00e4ten",
        "u"
    ],
    "wof:name":"C-films Ag",
    "wof:placetype":"venue"
},
  "geometry": {"coordinates":[8.5487289429,47.3632011414],"type":"Point"}
}