{
  "type": "Feature",
  "properties": {
    "iso:country":"CH",
    "sg:address":"Ried",
    "sg:city":"Schwarzenegg",
    "sg:orig_category":"Schmieden",
    "sg:phone":"+41 33 453 11 34",
    "sg:postcode":"3616",
    "sg:province":"Bern",
    "wof:name":"Heinz Moser Schmiede",
    "wof:placetype":"venue"
},
  "geometry": {"coordinates":[7.7116689682,46.7950744629],"type":"Point"}
}