{
  "type": "Feature",
  "properties": {
    "iso:country":"CH",
    "sg:address":"Pestalozzistrasse 5",
    "sg:city":"Rorschach",
    "sg:orig_category":"Sonstiger Grosshandel",
    "sg:postcode":"9400",
    "sg:province":"St. Gallen",
    "wof:name":"Weibel Patrick R. Consulting",
    "wof:placetype":"venue"
},
  "geometry": {"coordinates":[9.4907436371,47.4737052917],"type":"Point"}
}