{
  "type": "Feature",
  "properties": {
    "iso:country":"CH",
    "sg:address":"Retica Via 26 7503 Samedan. Postfach",
    "sg:city":"Samedan",
    "sg:orig_category":"Vermietung U Verpachtung von eigenen Immobilien",
    "sg:postcode":"7503",
    "sg:province":"Graubunden",
    "wof:name":"Immobiliare Gorni Sa",
    "wof:placetype":"venue"
},
  "geometry": {"coordinates":[9.872800827,46.534450531],"type":"Point"}
}