{
  "type": "Feature",
  "properties": {
    "iso:country":"CH",
    "sg:address":"D\u00f6rfli 4",
    "sg:city":"Reisiswil",
    "sg:orig_category":"Verwertung von Milch",
    "sg:postcode":"4919",
    "sg:province":"Bern",
    "wof:name":"K\u00e4sereigenossenschaft Reisiswil",
    "wof:placetype":"venue"
},
  "geometry": {"coordinates":[7.8458838463,47.1661186218],"type":"Point"}
}