{
  "type": "Feature",
  "properties": {
    "iso:country":"CH",
    "sg:address":"Schulhaus Buch B.frauenfeld",
    "sg:city":"Uesslingen",
    "sg:orig_category":"Vereine Frauen",
    "sg:phone":"+41 52 746 12 34",
    "sg:postcode":"8524",
    "sg:province":"Thurgau",
    "wof:name":"Frauenturnverein Buch & Umg.",
    "wof:placetype":"venue"
},
  "geometry": {"coordinates":[8.8314847946,47.580280304],"type":"Point"}
}