{
  "type": "Feature",
  "properties": {
    "iso:country":"CH",
    "sg:address":"Poststrasse 2",
    "sg:city":"Oetwil",
    "sg:orig_category":"Nationale Postdienste",
    "sg:phone":"+41 17482365",
    "sg:postcode":"8955",
    "sg:province":"Z\u00fcrich",
    "wof:name":"Die Schweizerische Post",
    "wof:placetype":"venue"
},
  "geometry": {"coordinates":[8.3948879242,47.427646637],"type":"Point"}
}