{
  "type": "Feature",
  "properties": {
    "iso:country":"CH",
    "sg:address":"Quartier De La Verrerie 59 2740 Montagne-moutier. Postfach",
    "sg:city":"Montagne-moutier",
    "sg:orig_category":"Instandhaltung U Reparatur von Automobilen",
    "sg:postcode":"2740",
    "sg:province":"Bern",
    "wof:name":"Garage Aeschlimann",
    "wof:placetype":"venue"
},
  "geometry": {"coordinates":[7.3594121933,47.2669296265],"type":"Point"}
}