{
  "type": "Feature",
  "properties": {
    "iso:country":"CH",
    "sg:address":"Gutenbergstr. 14",
    "sg:city":"Bern",
    "sg:classifiers":[
        {
            "category":"Manufacturing",
            "subcategory":"Printing",
            "type":"Manufacturing & Wholesale Goods"
        }
    ],
    "sg:phone":"+41 31 380 88 88",
    "sg:postcode":"3011",
    "sg:province":"Bern",
    "sg:tags":[
        "publishing"
    ],
    "wof:name":"Schlatter Ag",
    "wof:placetype":"venue"
},
  "geometry": {"coordinates":[7.4352779388,46.944934845],"type":"Point"}
}