{
  "type": "Feature",
  "properties": {
    "iso:country":"CH",
    "sg:address":"Rue Du Camus 2 1470 Estavayer-le-lac. Postfach",
    "sg:city":"Estavayer-le-lac",
    "sg:orig_category":"Versicherungen Generalagenturen",
    "sg:phone":"+41 26 663 14 65",
    "sg:postcode":"1470",
    "sg:province":"Fribourg",
    "wof:name":"Union Suisse Assurances Agence G\u00e9n\u00e9rale De La Broye",
    "wof:placetype":"venue"
},
  "geometry": {"coordinates":[6.8491392136,46.8497581482],"type":"Point"}
}