{
  "type": "Feature",
  "properties": {
    "iso:country":"CH",
    "sg:address":"Thunstrasse 27",
    "sg:city":"Bern",
    "sg:orig_category":"Arztpraxen",
    "sg:phone":"+41 31 352 65 40",
    "sg:postcode":"3005",
    "sg:province":"Bern",
    "wof:name":"Dres Bratschi Fravi & Meisels Spezial\u00e4rzte Fmh",
    "wof:placetype":"venue"
},
  "geometry": {"coordinates":[7.453613,46.94241],"type":"Point"}
}