{
  "type": "Feature",
  "properties": {
    "iso:country":"CH",
    "sg:address":"B\u00fchl 12",
    "sg:city":"Engelberg",
    "sg:orig_category":"W\u00e4schereien",
    "sg:phone":"+41 41 637 18 29",
    "sg:postcode":"6390",
    "sg:province":"Obwalden",
    "wof:name":"Marie Dillier W\u00e4scherei & Gl\u00e4tterei",
    "wof:placetype":"venue"
},
  "geometry": {"coordinates":[8.4059782028,46.8222351074],"type":"Point"}
}