{
  "type": "Feature",
  "properties": {
    "iso:country":"CH",
    "sg:address":"Heidelerstrasse 5 9425 Thal. Postfach",
    "sg:city":"Thal",
    "sg:orig_category":"Elektroinstallation",
    "sg:phone":"+41 81 750 01 01",
    "sg:postcode":"9425",
    "sg:province":"St. Gallen",
    "wof:name":"Elektro Rohrer Ag",
    "wof:placetype":"venue"
},
  "geometry": {"coordinates":[9.4690408707,47.1616859436],"type":"Point"}
}