{
  "type": "Feature",
  "properties": {
    "iso:country":"CH",
    "sg:address":"Bad K\u00e4mmoos",
    "sg:city":"Bubikon",
    "sg:classifiers":[
        {
            "category":"Restaurant",
            "type":"Food & Drink"
        }
    ],
    "sg:phone":"+41 55 243 27 27",
    "sg:postcode":"8608",
    "sg:province":"Z\u00fcrich",
    "wof:name":"Pizzeria Isola Bella",
    "wof:placetype":"venue"
},
  "geometry": {"coordinates":[8.8300924301,47.2613220215],"type":"Point"}
}