{
  "type": "Feature",
  "properties": {
    "iso:country":"CH",
    "sg:address":"Rittergasse 27 4103 Bottmingen. Postfach",
    "sg:city":"Bottmingen",
    "sg:orig_category":"Herstellung von medizinischen U chirurgischen Ger\u00e4ten sowie orthop\u00e4dischen Vorrichtungen Herstellung",
    "sg:phone":"+41 61 425 77 00",
    "sg:postcode":"4103",
    "sg:province":"Basel-Landschaft",
    "wof:name":"Infors Ag Anlagen Und Ger\u00e4te F\u00fcr Biotechnologie Und Medizin",
    "wof:placetype":"venue"
},
  "geometry": {"coordinates":[7.5718178749,47.5262336731],"type":"Point"}
}