{
  "type": "Feature",
  "properties": {
    "iso:country":"CH",
    "sg:address":"Schwandenholzstrasse 284",
    "sg:city":"Z\u00fcrich",
    "sg:orig_category":"Fotografisches Gewerbe U fotografische Laboratorien",
    "sg:phone":"+41 13718488",
    "sg:postcode":"8046",
    "sg:province":"Z\u00fcrich",
    "wof:name":"Daniel Zannantonio, Reportage- + Pressefotos Fotostudio",
    "wof:placetype":"venue"
},
  "geometry": {"coordinates":[8.5206041336,47.4243164062],"type":"Point"}
}