{
  "type": "Feature",
  "properties": {
    "addr:full":"Route De S\u00e9prais 24l Bo\u00e9court Jura 2856",
    "addr:housenumber":"24l",
    "addr:postcode":"2856",
    "addr:street":"Route De Se\u0301Prais;Jura",
    "iso:country":"CH",
    "sg:address":"Route De S\u00e9prais 24l",
    "sg:city":"Bo\u00e9court",
    "sg:classifiers":[
        {
            "category":"Manufacturing",
            "subcategory":"Glass & Minerals",
            "type":"Manufacturing & Wholesale Goods"
        }
    ],
    "sg:phone":"+41 32 426 74 56",
    "sg:postcode":"2856",
    "sg:province":"Jura",
    "sg:tags":[
        "crystal",
        "watch",
        "clock"
    ],
    "wof:name":"Erma Bo\u00e9court S.a.",
    "wof:placetype":"venue"
},
  "geometry": {"coordinates":[7.216292,47.350822],"type":"Point"}
}