{
  "type": "Feature",
  "properties": {
    "iso:country":"CH",
    "sg:address":"Gesellschaftsstrasse 41 3000 Bern. Postfach",
    "sg:city":"Bern",
    "sg:orig_category":"Forschung U Entwicklung im Bereich der Naturwissenschaften",
    "sg:phone":"+41 55 420 24 60",
    "sg:postcode":"3005",
    "sg:province":"Bern",
    "wof:name":"Karamed Handels Ag",
    "wof:placetype":"venue"
},
  "geometry": {"coordinates":[8.7890787125,47.2009925842],"type":"Point"}
}