{
  "type": "Feature",
  "properties": {
    "iso:country":"CH",
    "sg:address":"2852 Court\u00e9telle Case Postale 24",
    "sg:city":"Court\u00e9telle",
    "sg:orig_category":"Sportvereine Eissport Eishockey",
    "sg:postcode":"2852",
    "sg:province":"Jura",
    "wof:name":"Hockey-club Court\u00e9telle",
    "wof:placetype":"venue"
},
  "geometry": {"coordinates":[7.3167719841,47.3426017761],"type":"Point"}
}