{
  "type": "Feature",
  "properties": {
    "iso:country":"CH",
    "sg:address":"Via G. E F. Ciani 1",
    "sg:city":"Lugano",
    "sg:orig_category":"Gesundheitswesen",
    "sg:phone":"+41 91 921 32 20",
    "sg:postcode":"6900",
    "sg:province":"Ticino",
    "wof:name":"Istituto Laura Di Chabloz & Clerici",
    "wof:placetype":"venue"
},
  "geometry": {"coordinates":[8.9596376419,46.0114097595],"type":"Point"}
}