{
  "type": "Feature",
  "properties": {
    "iso:country":"CH",
    "sg:address":"Route Du Simplon 47",
    "sg:city":"Paudex",
    "sg:orig_category":"Detailhandel mit Bekleidung",
    "sg:phone":"+41 21 791 25 11",
    "sg:postcode":"1094",
    "sg:province":"Vaud",
    "wof:name":"Team Style, Vlamopoulos P.",
    "wof:placetype":"venue"
},
  "geometry": {"coordinates":[6.675352,46.505863],"type":"Point"}
}