{
  "type": "Feature",
  "properties": {
    "iso:country":"CH",
    "sg:address":"Chemin Des Roches 8a 1700 Fribourg Case Postale 2",
    "sg:city":"Fribourg",
    "sg:orig_category":"Elektroinstallation",
    "sg:phone":"+41 26 466 18 66",
    "sg:postcode":"1706",
    "wof:name":"Electricit\u00e9 Progin Sa",
    "wof:placetype":"venue"
},
  "geometry": {"coordinates":[7.150780201,46.8108901978],"type":"Point"}
}