{
  "type": "Feature",
  "properties": {
    "iso:country":"CH",
    "sg:address":"Mittelstrasse 53",
    "sg:city":"Bern",
    "sg:orig_category":"Psychotherapie",
    "sg:phone":"+41 31 301 72 70",
    "sg:postcode":"3012",
    "sg:province":"Bern",
    "wof:name":"Yvonne B\u00e4chli Psychologische Beratung",
    "wof:placetype":"venue"
},
  "geometry": {"coordinates":[7.436850071,46.9562225342],"type":"Point"}
}