{
  "type": "Feature",
  "properties": {
    "iso:country":"CH",
    "sg:address":"D\u00f6rfli",
    "sg:city":"Schweizersholz",
    "sg:orig_category":"Hoch U Tiefbau",
    "sg:phone":"+41 79 209 98 48",
    "sg:postcode":"9223",
    "sg:province":"Thurgau",
    "wof:name":"Anton Rousselot Storenbau & Baumontagen",
    "wof:placetype":"venue"
},
  "geometry": {"coordinates":[9.2014122009,47.5017318726],"type":"Point"}
}