{
  "type": "Feature",
  "properties": {
    "iso:country":"CH",
    "sg:address":"Mayrstrasse 4a",
    "sg:city":"Arbon",
    "sg:orig_category":"Bauschreinerei Herstellung von Konstruktionsteilen, Fertigbauteilen U Ausbauelementen aus Holz",
    "sg:phone":"+41 71 446 71 55",
    "sg:postcode":"9320",
    "sg:province":"Thurgau",
    "wof:name":"Bruggesser Beat",
    "wof:placetype":"venue"
},
  "geometry": {"coordinates":[9.435062,47.515335],"type":"Point"}
}