{
  "type": "Feature",
  "properties": {
    "iso:country":"CH",
    "sg:address":"Bolsternstrasse 14",
    "sg:city":"Kollbrunn",
    "sg:orig_category":"Instandhaltung U Reparatur von Automobilen",
    "sg:phone":"+41 52 383 27 70",
    "sg:postcode":"8483",
    "sg:province":"Z\u00fcrich",
    "wof:name":"Dorfgarage Kollbrunn Gmbh",
    "wof:placetype":"venue"
},
  "geometry": {"coordinates":[8.7762317657,47.4589576721],"type":"Point"}
}