{
  "type": "Feature",
  "properties": {
    "iso:country":"CH",
    "sg:address":"Bachtalen 1",
    "sg:city":"Emmenbr\u00fccke",
    "sg:orig_category":"Organisationen des Gesundheitswesen Sonstiges Gesundheitswesen",
    "sg:phone":"+41 79 418 35 35",
    "sg:postcode":"6020",
    "sg:province":"Luzern",
    "wof:name":"Rols Dienstleistungs Gmbh Spitex Rollstuhltaxi",
    "wof:placetype":"venue"
},
  "geometry": {"coordinates":[8.2720832825,47.0905380249],"type":"Point"}
}