{
  "type": "Feature",
  "properties": {
    "iso:country":"CH",
    "sg:address":"Rue De La Gare 45 1260 Nyon Case Postale 287",
    "sg:city":"Nyon",
    "sg:orig_category":"Versicherungen Generalagenturen",
    "sg:phone":"+41 22 361 76 33",
    "sg:postcode":"1260",
    "sg:province":"Vaud",
    "wof:name":"Winterthur Assurances Agence G\u00e9n\u00e9rale",
    "wof:placetype":"venue"
},
  "geometry": {"coordinates":[6.2358288765,46.3837242126],"type":"Point"}
}