{
  "type": "Feature",
  "properties": {
    "iso:country":"CH",
    "sg:address":"Bahnhofstrasse 30",
    "sg:city":"Laufen",
    "sg:orig_category":"Einbau von Schreinerwaren",
    "sg:phone":"+41 61 761 66 45",
    "sg:postcode":"4242",
    "sg:province":"Basel-Landschaft",
    "wof:name":"Nobby's Optimismus Gmbh",
    "wof:placetype":"venue"
},
  "geometry": {"coordinates":[7.5019087791,47.4186820984],"type":"Point"}
}