{
  "type": "Feature",
  "properties": {
    "iso:country":"CH",
    "sg:address":"Rue Du Clos 1",
    "sg:city":"Montagne-moutier",
    "sg:orig_category":"Sportvereine Turnen Vereine Damen",
    "sg:phone":"+41 32 493 73 73",
    "sg:postcode":"2740",
    "sg:province":"Bern",
    "wof:name":"St\u00e9 De Gymnastique De Dames",
    "wof:placetype":"venue"
},
  "geometry": {"coordinates":[7.3702430725,47.277431488],"type":"Point"}
}