{
  "type": "Feature",
  "properties": {
    "iso:country":"CH",
    "sg:address":"Langstrasse 135",
    "sg:city":"Z\u00fcrich",
    "sg:orig_category":"Unclassifiable Establishments",
    "sg:postcode":"8004",
    "sg:province":"Z\u00fcrich",
    "wof:name":"Imbiss Elite, Makbule Pisgin-senal",
    "wof:placetype":"venue"
},
  "geometry": {"coordinates":[8.5277290344,47.3800239563],"type":"Point"}
}