{
  "type": "Feature",
  "properties": {
    "iso:country":"CH",
    "sg:address":"T\u00f6sstalstrasse 14 8360 Eschlikon Tg. Postfach",
    "sg:city":"Wallenwil",
    "sg:orig_category":"RESTAURANTS: TEA-ROOMS",
    "sg:postcode":"8360",
    "sg:province":"Thurgau",
    "wof:name":"Alci Gastro Gmbh",
    "wof:placetype":"venue"
},
  "geometry": {"coordinates":[8.9522886276,47.4605522156],"type":"Point"}
}