{
  "type": "Feature",
  "properties": {
    "iso:country":"CH",
    "sg:address":"Itenhoschet 12",
    "sg:city":"Mollis",
    "sg:orig_category":"Fernmeldedienste",
    "sg:phone":"+41 55 640 50 84",
    "sg:postcode":"8753",
    "sg:province":"Glarus",
    "wof:name":"Carrara Haushaltger\u00e4te Gmbh",
    "wof:placetype":"venue"
},
  "geometry": {"coordinates":[9.0770254135,47.0964202881],"type":"Point"}
}