{
  "type": "Feature",
  "properties": {
    "iso:country":"CH",
    "sg:address":"Lettenstrasse 3",
    "sg:city":"Rotkreuz",
    "sg:classifiers":[
        {
            "category":"Banks & Credit Unions",
            "subcategory":"Investment Brokerage",
            "type":"Services"
        }
    ],
    "sg:phone":"+41 41 799 05 05",
    "sg:postcode":"6343",
    "sg:province":"Zug",
    "sg:tags":[
        "condition",
        "work",
        "assembly",
        "room",
        "clean"
    ],
    "wof:name":"Gem\u00dc Gmbh",
    "wof:placetype":"venue"
},
  "geometry": {"coordinates":[8.432124,47.147945],"type":"Point"}
}