{
  "type": "Feature",
  "properties": {
    "iso:country":"CH",
    "sg:address":"Hauptstrasse 23",
    "sg:city":"Laupen",
    "sg:classifiers":[
        {
            "category":"Manufacturing",
            "subcategory":"Glass & Minerals",
            "type":"Manufacturing & Wholesale Goods"
        }
    ],
    "sg:phone":"+41 55 246 71 70",
    "sg:postcode":"8637",
    "sg:province":"Z\u00fcrich",
    "sg:tags":[
        "fibre",
        "network"
    ],
    "wof:name":"Speedo-optic Ag",
    "wof:placetype":"venue"
},
  "geometry": {"coordinates":[8.9263000488,47.2655487061],"type":"Point"}
}