{
  "type": "Feature",
  "properties": {
    "iso:country":"CH",
    "sg:address":"8355",
    "sg:city":"Aadorf",
    "sg:orig_category":"Detailhandel mit Zeitungen U Zeitschriften Kioske",
    "sg:phone":"+41 52 365 12 76",
    "sg:postcode":"8355",
    "sg:province":"Thurgau",
    "wof:name":"Schwimmbad Am Heidelberg",
    "wof:placetype":"venue"
},
  "geometry": {"coordinates":[8.9033498764,47.4896583557],"type":"Point"}
}