{
  "type": "Feature",
  "properties": {
    "iso:country":"CH",
    "sg:address":"Eaux-vives Rue Des 21 1207 Gen\u00e8ve. Postfach",
    "sg:city":"Gen\u00e8ve",
    "sg:classifiers":[
        {
            "category":"Bars & Pubs",
            "type":"Food & Drink"
        }
    ],
    "sg:postcode":"1207",
    "sg:province":"Gen\u00e8ve",
    "wof:name":"Sbi Pub's Sa Bars, Pubs, Restaurants, Caf\u00e9; Cr\u00e9ation, Achat, Vente Usw",
    "wof:placetype":"venue"
},
  "geometry": {"coordinates":[6.168573,46.202278],"type":"Point"}
}