{
  "type": "Feature",
  "properties": {
    "iso:country":"CH",
    "sg:address":"Duboule Chemin Mo\u00efse- 33 1209 Gen\u00e8ve. Postfach",
    "sg:city":"Gen\u00e8ve",
    "sg:orig_category":"Herstellung von Elektrizit\u00e4tsverteilungs U schalteinrichtungen",
    "sg:postcode":"1209",
    "sg:province":"Gen\u00e8ve",
    "wof:name":"Sissel Technology Wolfgang Mehl",
    "wof:placetype":"venue"
},
  "geometry": {"coordinates":[6.1253437996,46.2248954773],"type":"Point"}
}