{
  "type": "Feature",
  "properties": {
    "iso:country":"CH",
    "sg:address":"Via Da Bernina",
    "sg:city":"Pontresina",
    "sg:classifiers":[
        {
            "category":"Utilities",
            "subcategory":"Recycling",
            "type":"Services"
        }
    ],
    "sg:phone":"+41 81 838 82 82",
    "sg:postcode":"7504",
    "sg:province":"Graubunden",
    "sg:tags":[
        "polystyrene",
        "expanded",
        "eps"
    ],
    "wof:name":"Bernina Recycling Ag",
    "wof:placetype":"venue"
},
  "geometry": {"coordinates":[9.9145498276,46.4819259644],"type":"Point"}
}