{
  "type": "Feature",
  "properties": {
    "iso:country":"CH",
    "sg:address":"Jurastrasse 9",
    "sg:city":"Aarau",
    "sg:orig_category":"Pensionskassen",
    "sg:phone":"+41 62 824 63 79",
    "sg:postcode":"5000",
    "sg:province":"Aargau",
    "wof:name":"Veska-pensionskasse",
    "wof:placetype":"venue"
},
  "geometry": {"coordinates":[8.0511617661,47.3883781433],"type":"Point"}
}