{
  "type": "Feature",
  "properties": {
    "iso:country":"CH",
    "sg:address":"Blegistrasse 25",
    "sg:city":"Baar",
    "sg:orig_category":"Unclassifiable Establishments",
    "sg:postcode":"6340",
    "sg:province":"Zug",
    "wof:name":"Cjb Immobilien Ag",
    "wof:placetype":"venue"
},
  "geometry": {"coordinates":[8.5663824081,47.2145271301],"type":"Point"}
}