{
  "type": "Feature",
  "properties": {
    "addr:full":"Unterstadt 38/40 Schaffhausen Schaffhausen 8200",
    "addr:housenumber":"38 / 40",
    "addr:postcode":"8200",
    "addr:street":"Unterstadt",
    "iso:country":"CH",
    "sg:address":"Unterstadt 38/40",
    "sg:city":"Schaffhausen",
    "sg:classifiers":[
        {
            "category":"Banks & Credit Unions",
            "subcategory":"Investment Brokerage",
            "type":"Services"
        }
    ],
    "sg:phone":"+41 52 625 73 41",
    "sg:postcode":"8200",
    "sg:province":"Schaffhausen",
    "sg:tags":[
        "bearing",
        "ball"
    ],
    "wof:name":"Gummi-haus Roost & Co Inh. R. Doggwiler",
    "wof:placetype":"venue"
},
  "geometry": {"coordinates":[8.638699,47.695938],"type":"Point"}
}