{
  "type": "Feature",
  "properties": {
    "iso:country":"CH",
    "sg:address":"Breitensteinstrasse 96 5417 Untersiggenthal. Postfach",
    "sg:city":"Untersiggenthal",
    "sg:orig_category":"Unclassifiable Establishments",
    "sg:phone":"+41 14474090",
    "sg:postcode":"5417",
    "sg:province":"Aargau",
    "wof:name":"Hbh Communications & Events Gmbh",
    "wof:placetype":"venue"
},
  "geometry": {"coordinates":[8.2535047531,47.4991493225],"type":"Point"}
}