{
  "type": "Feature",
  "properties": {
    "iso:country":"CH",
    "sg:address":"Rue Du Pr\u00e9-du-pont 26",
    "sg:city":"Collombey",
    "sg:orig_category":"Malerei Stukkateurgewerbe, Gipserei U Verputzerei",
    "sg:phone":"+41 24 472 43 14",
    "sg:postcode":"1868",
    "sg:province":"Valais",
    "wof:name":"Gangemi Peinture Sa",
    "wof:placetype":"venue"
},
  "geometry": {"coordinates":[6.9543290138,46.2692222595],"type":"Point"}
}