{
  "type": "Feature",
  "properties": {
    "addr:full":"Rue Le-corbusier 24 Gen\u00e8ve Gen\u00e8ve 1208",
    "addr:housenumber":"24",
    "addr:postcode":"1208",
    "addr:street":"Rue Le-Corbusier",
    "iso:country":"CH",
    "sg:address":"Rue Le-corbusier 24",
    "sg:city":"Gen\u00e8ve",
    "sg:orig_category":"Allgemeiner Hochbau",
    "sg:phone":"+41 41 630 37 34",
    "sg:postcode":"1208",
    "sg:province":"Gen\u00e8ve",
    "wof:name":"Walo Bertschinger Ag Bauunternehmung",
    "wof:placetype":"venue"
},
  "geometry": {"coordinates":[8.309725,46.996948],"type":"Point"}
}