{
  "type": "Feature",
  "properties": {
    "iso:country":"CH",
    "sg:address":"Seenerstrasse 143",
    "sg:city":"Winterthur",
    "sg:classifiers":[
        {
            "category":"Government",
            "subcategory":"Department Of Motor Vehicles",
            "type":"Public Place"
        }
    ],
    "sg:phone":"+41 22 338 38 38",
    "sg:postcode":"8405",
    "sg:province":"Z\u00fcrich",
    "sg:tags":[
        "equipment",
        "industrial",
        "transport",
        "motor-cars"
    ],
    "wof:name":"Fiat Auto Suisse Sa",
    "wof:placetype":"venue"
},
  "geometry": {"coordinates":[6.1220960617,46.2092971802],"type":"Point"}
}