{
  "type": "Feature",
  "properties": {
    "iso:country":"CH",
    "sg:address":"Rheinweg 4",
    "sg:city":"Schaffhausen",
    "sg:classifiers":[
        {
            "category":"Internet Cafe",
            "subcategory":"None",
            "type":"Food & Drink"
        }
    ],
    "sg:phone":"+41 52 620 09 43",
    "sg:postcode":"8200",
    "sg:province":"Schaffhausen",
    "sg:tags":[
        "provider"
    ],
    "wof:name":"Cybernet (schweiz) Ag Application Service Provider",
    "wof:placetype":"venue"
},
  "geometry": {"coordinates":[8.6347980499,47.6939506531],"type":"Point"}
}