{
  "type": "Feature",
  "properties": {
    "addr:full":"Bl\u00e4uenstrasse 8a Erlinsbach Solothurn 5018",
    "addr:housenumber":"8a",
    "addr:postcode":"5018",
    "addr:street":"Blaeuenstrasse",
    "iso:country":"CH",
    "sg:address":"Bl\u00e4uenstrasse 8a",
    "sg:city":"Erlinsbach",
    "sg:orig_category":"Arztpraxen",
    "sg:phone":"+41 62 844 22 77",
    "sg:postcode":"5018",
    "sg:province":"Solothurn",
    "wof:name":"Dr.med.hanspeter Kurth Arzt F.allgemeine Medizin Fmh",
    "wof:placetype":"venue"
},
  "geometry": {"coordinates":[8.013959,47.395748],"type":"Point"}
}