{
  "type": "Feature",
  "properties": {
    "iso:country":"CH",
    "sg:address":"H\u00e4ldelistrasse 9",
    "sg:city":"St\u00e4fa",
    "sg:orig_category":"Wirtschaftspr\u00fcfung, Steuerberatung U Treuhand",
    "sg:postcode":"8712",
    "sg:province":"Z\u00fcrich",
    "wof:name":"Erx Treuhand Markus Steiner",
    "wof:placetype":"venue"
},
  "geometry": {"coordinates":[8.7187643051,47.2419433594],"type":"Point"}
}