{
  "type": "Feature",
  "properties": {
    "iso:country":"CH",
    "sg:address":"Obfelderstrasse 16",
    "sg:city":"Kloten",
    "sg:orig_category":"Pensionskassen",
    "sg:phone":"+41 79 666 78 17",
    "sg:postcode":"8302",
    "sg:province":"Z\u00fcrich",
    "wof:name":"Finanzierungsstiftung Der Iveco (schweiz) Ag",
    "wof:placetype":"venue"
},
  "geometry": {"coordinates":[8.5930433273,47.448387146],"type":"Point"}
}