{
  "type": "Feature",
  "properties": {
    "iso:country":"CH",
    "sg:address":"Willisauerstrasse 1",
    "sg:city":"Menznau",
    "sg:orig_category":"RESTAURANTS: TEA-ROOMS",
    "sg:phone":"+41 41 493 12 10",
    "sg:postcode":"6122",
    "sg:province":"Luzern",
    "wof:name":"Restaurant Krone Portmann Adolf",
    "wof:placetype":"venue"
},
  "geometry": {"coordinates":[8.038523674,47.0834007263],"type":"Point"}
}