{
  "type": "Feature",
  "properties": {
    "iso:country":"CH",
    "sg:address":"Luzernerstrasse 56",
    "sg:city":"Kriens",
    "sg:orig_category":"Vermietung von Automobilen",
    "sg:phone":"+41 71 855 36 36",
    "sg:postcode":"6010",
    "sg:province":"Luzern",
    "wof:name":"Avis Autovermietung Ag",
    "wof:placetype":"venue"
},
  "geometry": {"coordinates":[9.539598465,47.4810714722],"type":"Point"}
}