{
  "type": "Feature",
  "properties": {
    "iso:country":"CH",
    "sg:address":"Gerbi 28",
    "sg:city":"N\u00e4fels",
    "sg:orig_category":"Vermietung U Verpachtung von eigenen Immobilien",
    "sg:postcode":"8752",
    "sg:province":"Glarus",
    "wof:name":"Tradom Gmbh",
    "wof:placetype":"venue"
},
  "geometry": {"coordinates":[9.0607757568,47.1004486084],"type":"Point"}
}