{
  "type": "Feature",
  "properties": {
    "iso:country":"CH",
    "sg:address":"Schulhausstrasse 9",
    "sg:city":"Brig",
    "sg:orig_category":"Wirtschaftspr\u00fcfung, Steuerberatung U Treuhand",
    "sg:phone":"+41 27 923 83 42",
    "sg:postcode":"3900",
    "sg:province":"Valais",
    "wof:name":"Schwery Bernhard, Treuhandb\u00fcro.",
    "wof:placetype":"venue"
},
  "geometry": {"coordinates":[7.989713192,46.3171463013],"type":"Point"}
}