{
  "type": "Feature",
  "properties": {
    "iso:country":"CH",
    "sg:address":"Hauptstrasse 76",
    "sg:city":"D\u00f6ttingen",
    "sg:orig_category":"Non-Classified Establishments",
    "sg:postcode":"5312",
    "sg:province":"Aargau",
    "wof:name":"Pizzeria Roma, Arizanova",
    "wof:placetype":"venue"
},
  "geometry": {"coordinates":[9.2503404617,47.4142189026],"type":"Point"}
}