{
  "type": "Feature",
  "properties": {
    "iso:country":"CH",
    "sg:address":"Bahnhofstrasse 14",
    "sg:city":"Arlesheim",
    "sg:orig_category":"Kinderkrippen U horte Vorschulen, Kinderg\u00e4rten",
    "sg:phone":"+41 61 701 37 22",
    "sg:postcode":"4144",
    "sg:province":"Basel-Landschaft",
    "wof:name":"Kindergarten & -krippe Der Missione Cattolica Italiana",
    "wof:placetype":"venue"
},
  "geometry": {"coordinates":[7.6106319427,47.4894104004],"type":"Point"}
}