{
  "type": "Feature",
  "properties": {
    "iso:country":"CH",
    "sg:address":"Birchstrasse 155",
    "sg:city":"Z\u00fcrich",
    "sg:orig_category":"Sportvereine Ballsport Tennis",
    "sg:phone":"+41 56 622 46 76",
    "sg:postcode":"8050",
    "sg:province":"Z\u00fcrich",
    "wof:name":"Tennisclub B\u00fcnzmatt Wohlen",
    "wof:placetype":"venue"
},
  "geometry": {"coordinates":[8.2780599594,47.350528717],"type":"Point"}
}