{
  "type": "Feature",
  "properties": {
    "iso:country":"CH",
    "sg:address":"Chemin Des Croisettes 29 1066 Epalinges Case Postale 53",
    "sg:city":"Epalinges",
    "sg:orig_category":"Kinderkrippen U horte",
    "sg:phone":"+41 21 652 55 83",
    "sg:postcode":"1066",
    "sg:province":"Vaud",
    "wof:name":"Garderie D'enfants La P\u00e9pini\u00e8re",
    "wof:placetype":"venue"
},
  "geometry": {"coordinates":[6.6598448753,46.5449790955],"type":"Point"}
}