{
  "type": "Feature",
  "properties": {
    "iso:country":"CH",
    "sg:address":"Guggiweg 7",
    "sg:city":"Zug",
    "sg:orig_category":"Unternehmensberatung",
    "sg:phone":"+41 41 758 17 78",
    "sg:postcode":"6300",
    "sg:province":"Zug",
    "wof:name":"Hanspeter Br\u00e4ndli Hpb Management Services",
    "wof:placetype":"venue"
},
  "geometry": {"coordinates":[8.518280983,47.1699142456],"type":"Point"}
}