{
  "type": "Feature",
  "properties": {
    "iso:country":"CH",
    "sg:address":"Rue De La Place 1 3965 Chippis Case Postale 15",
    "sg:city":"Chippis",
    "sg:orig_category":"Mechanische Werkst\u00e4tten",
    "sg:phone":"+41 27 455 09 93",
    "sg:postcode":"3965",
    "sg:province":"Valais",
    "wof:name":"Pierre Bornand Atelier \u00e9lectrom\u00e9canique",
    "wof:placetype":"venue"
},
  "geometry": {"coordinates":[7.5418682098,46.2793807983],"type":"Point"}
}