{
  "type": "Feature",
  "properties": {
    "iso:country":"CH",
    "sg:address":"Hallwylstrasse 8000 Z\u00fcrich. Postfach",
    "sg:city":"Z\u00fcrich",
    "sg:orig_category":"Unclassifiable Establishments",
    "sg:postcode":"8001",
    "sg:province":"Z\u00fcrich",
    "wof:name":"Wild Heinz, Visuelle Kommunikation",
    "wof:placetype":"venue"
},
  "geometry": {"coordinates":[8.5290699005,47.3717193604],"type":"Point"}
}