{
  "type": "Feature",
  "properties": {
    "iso:country":"CH",
    "sg:address":"Hauptstrasse 35",
    "sg:city":"Zurzach",
    "sg:orig_category":"Vereine Musik/Blasmusik",
    "sg:postcode":"5330",
    "sg:province":"Aargau",
    "wof:name":"Musikgesellschaft Zurzach",
    "wof:placetype":"venue"
},
  "geometry": {"coordinates":[8.2921924591,47.5867652893],"type":"Point"}
}