{
  "type": "Feature",
  "properties": {
    "iso:country":"CH",
    "sg:address":"Eichholzstr. 35",
    "sg:city":"Selzach",
    "sg:classifiers":[
        {
            "category":"Manufacturing",
            "subcategory":"Metals",
            "type":"Manufacturing & Wholesale Goods"
        }
    ],
    "sg:phone":"+41 32 641 15 65",
    "sg:postcode":"2545",
    "sg:province":"Solothurn",
    "sg:tags":[
        "metallurgy",
        "metalworking",
        "processing"
    ],
    "wof:name":"Brotschi D\u00c9colletage Ag",
    "wof:placetype":"venue"
},
  "geometry": {"coordinates":[7.461250782,47.2017631531],"type":"Point"}
}