{
  "type": "Feature",
  "properties": {
    "iso:country":"CH",
    "sg:address":"Rainstrasse 23",
    "sg:city":"Biel/bienne",
    "sg:orig_category":"G\u00fcterbef\u00f6rderung im Strassenverkehr Reinigungsgewerbe",
    "sg:phone":"+41 79 215 80 63",
    "sg:postcode":"2503",
    "sg:province":"Bern",
    "wof:name":"Hadorn Allround-service",
    "wof:placetype":"venue"
},
  "geometry": {"coordinates":[7.2562742233,47.1338653564],"type":"Point"}
}