{
  "type": "Feature",
  "properties": {
    "iso:country":"CH",
    "sg:address":"Rue Du Temple 1",
    "sg:city":"Rolle",
    "sg:orig_category":"Detailhandel mit Radio U Fernsehger\u00e4ten Detailhandel mit elektrischen Haushalts-,Radio U Fernsehger\u00e4",
    "sg:phone":"+41 79 212 75 50",
    "sg:postcode":"1180",
    "sg:province":"Vaud",
    "wof:name":"Marcel Gall Radio-tv Vid\u00e9o-hi-fi",
    "wof:placetype":"venue"
},
  "geometry": {"coordinates":[6.3381681442,46.4578704834],"type":"Point"}
}