{
  "type": "Feature",
  "properties": {
    "iso:country":"CH",
    "sg:address":"Via Locarno 85",
    "sg:city":"Losone",
    "sg:orig_category":"Sanit\u00e4r, Heizungs U L\u00fcftungsinstallation Sanit\u00e4rinstallation",
    "sg:phone":"+41 32 351 40 46",
    "sg:postcode":"6616",
    "sg:province":"Ticino",
    "wof:name":"Spack Gmbh Heizung/sanit\u00e4r",
    "wof:placetype":"venue"
},
  "geometry": {"coordinates":[7.3715801239,47.1387825012],"type":"Point"}
}