{
  "type": "Feature",
  "properties": {
    "iso:country":"CH",
    "sg:address":"Clavadoiras 15 7078 Lenzerheide/lai. Postfach 91",
    "sg:city":"Lenzerheide/lai",
    "sg:orig_category":"Bauschreinerei Herstellung von Fenstern U T\u00fcren aus Holz",
    "sg:phone":"+41 81 384 42 04",
    "sg:postcode":"7078",
    "sg:province":"Graubunden",
    "wof:name":"Ernest Fran\u00e7ois Gurtner Fensterfabrik & Schreinerei",
    "wof:placetype":"venue"
},
  "geometry": {"coordinates":[9.557569,46.719246],"type":"Point"}
}