{
  "type": "Feature",
  "properties": {
    "iso:country":"CH",
    "sg:address":"Oberstadtstrasse 4",
    "sg:city":"Frauenfeld",
    "sg:classifiers":[
        {
            "category":"Travel",
            "subcategory":"Hotels & Motels",
            "type":"Entertainment"
        }
    ],
    "sg:phone":"+41 52 721 47 28",
    "sg:postcode":"8500",
    "sg:province":"Thurgau",
    "sg:tags":[
        "hotels",
        "mit",
        "restaurant"
    ],
    "wof:name":"Hotel Blumenstein",
    "wof:placetype":"venue"
},
  "geometry": {"coordinates":[8.8966569901,47.5575408936],"type":"Point"}
}