{
  "type": "Feature",
  "properties": {
    "iso:country":"CH",
    "sg:address":"Via Belsoggiorno 11",
    "sg:city":"Bellinzona",
    "sg:orig_category":"Physiotherapie",
    "sg:phone":"+41 91 825 08 55",
    "sg:postcode":"6500",
    "sg:province":"Ticino",
    "wof:name":"Evi Coldesina Fisioterapia",
    "wof:placetype":"venue"
},
  "geometry": {"coordinates":[9.0239257812,46.1849479675],"type":"Point"}
}