{
  "type": "Feature",
  "properties": {
    "iso:country":"CH",
    "sg:address":"Riva Da S. Bartolom\u00e9e",
    "sg:city":"Morcote",
    "sg:orig_category":"Herstellung von Seifen, Wasch U Reinigungsmitteln",
    "sg:phone":"+41 71 664 11 31",
    "sg:postcode":"6922",
    "sg:province":"Ticino",
    "wof:name":"Howa Reinigungschemie Ag",
    "wof:placetype":"venue"
},
  "geometry": {"coordinates":[8.9038190842,45.928768158],"type":"Point"}
}