{
  "type": "Feature",
  "properties": {
    "iso:country":"CH",
    "sg:address":"Gallusstrasse 14",
    "sg:city":"Olten",
    "sg:orig_category":"Schreib U \u00dcbersetzungsb\u00fcros",
    "sg:phone":"+41 62 212 08 15",
    "sg:postcode":"4600",
    "sg:province":"Solothurn",
    "wof:name":"Sudan Pia",
    "wof:placetype":"venue"
},
  "geometry": {"coordinates":[7.8909068108,47.3509483337],"type":"Point"}
}