{
  "type": "Feature",
  "properties": {
    "iso:country":"CH",
    "sg:address":"Le Hameau",
    "sg:city":"Verbier",
    "sg:orig_category":"Detailhandel mit Waren verschiedener Art, Hauptrichtung Nahrungsmittel Grosshandel mit Nahrungsmitte",
    "sg:phone":"+41 91 794 13 68",
    "sg:postcode":"1936",
    "sg:province":"Valais",
    "wof:name":"Antognini Luca.",
    "wof:placetype":"venue"
},
  "geometry": {"coordinates":[8.8021802902,46.1322402954],"type":"Point"}
}