{
  "type": "Feature",
  "properties": {
    "iso:country":"CH",
    "sg:address":"Hinterburgstrasse 4",
    "sg:city":"Neuheim",
    "sg:orig_category":"G\u00fcterbef\u00f6rderung im Strassenverkehr",
    "sg:phone":"+41 41 755 22 79",
    "sg:postcode":"6345",
    "sg:province":"Zug",
    "wof:name":"Alois Trinkler Autotransporte",
    "wof:placetype":"venue"
},
  "geometry": {"coordinates":[8.5729160309,47.1997299194],"type":"Point"}
}