{
  "type": "Feature",
  "properties": {
    "iso:country":"CH",
    "sg:address":"1906",
    "sg:city":"Charrat",
    "sg:orig_category":"Herstellung von sonstigen landwirtschaftlichen Maschinen",
    "sg:postcode":"1906",
    "sg:province":"Valais",
    "wof:name":"Chappot S\u00e0rl Charrat",
    "wof:placetype":"venue"
},
  "geometry": {"coordinates":[7.1296892166,46.1249885559],"type":"Point"}
}