{
  "type": "Feature",
  "properties": {
    "iso:country":"CH",
    "sg:address":"Etraz Rue 1 1003 Lausanne. Postfach",
    "sg:city":"Lausanne",
    "sg:orig_category":"Detailhandel mit Tabakwaren",
    "sg:postcode":"1003",
    "sg:province":"Vaud",
    "wof:name":"Papaux Heitraud.",
    "wof:placetype":"venue"
},
  "geometry": {"coordinates":[6.5797348022,46.5377731323],"type":"Point"}
}