{
  "type": "Feature",
  "properties": {
    "iso:country":"CH",
    "sg:address":"Vorderthal",
    "sg:city":"Vorderthal",
    "sg:classifiers":[
        {
            "category":"Banks & Credit Unions",
            "subcategory":"Bank",
            "type":"Services"
        }
    ],
    "sg:phone":"+41 55691105",
    "sg:postcode":"8857",
    "sg:province":"Schwyz",
    "wof:name":"Kantonalbank Schwyz",
    "wof:placetype":"venue"
},
  "geometry": {"coordinates":[8.901355,47.119888],"type":"Point"}
}