{
  "type": "Feature",
  "properties": {
    "iso:country":"CH",
    "sg:address":"La Clairi\u00e8re B 1974 Arbaz Case Postale",
    "sg:city":"Arbaz",
    "sg:orig_category":"Sonstiger Grosshandel",
    "sg:phone":"+41 27 398 70 07",
    "sg:postcode":"1974",
    "sg:province":"Valais",
    "wof:name":"Pl-march\u00e9 Sa",
    "wof:placetype":"venue"
},
  "geometry": {"coordinates":[7.3841748238,46.273109436],"type":"Point"}
}