{
  "type": "Feature",
  "properties": {
    "iso:country":"CH",
    "sg:address":"Effingerstrasse 59",
    "sg:city":"Bern",
    "sg:orig_category":"Detailhandel mit Zeitungen U Zeitschriften Kioske RESTAURANTS: TEA-ROOMS",
    "sg:phone":"+41 71 633 37 13",
    "sg:postcode":"3008",
    "sg:province":"Bern",
    "wof:name":"Kiosk-caf\u00e9-bar Rondelle Ricchiuto",
    "wof:placetype":"venue"
},
  "geometry": {"coordinates":[9.1524839401,47.5499153137],"type":"Point"}
}