{
  "type": "Feature",
  "properties": {
    "iso:country":"CH",
    "sg:address":"Flurweg 15",
    "sg:city":"Rothrist",
    "sg:orig_category":"Unternehmensberatung",
    "sg:phone":"+41 62 794 52 60",
    "sg:postcode":"4852",
    "sg:province":"Aargau",
    "wof:name":"Bos Consulting Gmbh",
    "wof:placetype":"venue"
},
  "geometry": {"coordinates":[7.8762598038,47.3001899719],"type":"Point"}
}