{
  "type": "Feature",
  "properties": {
    "iso:country":"CH",
    "sg:address":"Oberdorfstrasse 11",
    "sg:city":"Baar",
    "sg:orig_category":"Kauf U Verkauf von Immobilien auf eigene Rechnung",
    "sg:postcode":"6340",
    "sg:province":"Zug",
    "wof:name":"Alltra - Planungs Und Immobilien Ag",
    "wof:placetype":"venue"
},
  "geometry": {"coordinates":[7.6804499626,46.6164894104],"type":"Point"}
}