{
  "type": "Feature",
  "properties": {
    "iso:country":"CH",
    "sg:address":"Hauptstrasse 16",
    "sg:city":"Bennwil",
    "sg:orig_category":"Sportvereine Ski",
    "sg:phone":"+41 61 961 95 44",
    "sg:postcode":"4431",
    "sg:province":"Basel-Landschaft",
    "wof:name":"Skiclub Oberdorf",
    "wof:placetype":"venue"
},
  "geometry": {"coordinates":[7.7845230103,47.4068069458],"type":"Point"}
}