{
  "type": "Feature",
  "properties": {
    "iso:country":"CH",
    "sg:address":"Freiestrasse 20",
    "sg:city":"Bern",
    "sg:orig_category":"Institutionen des Sozialwesens ohne Beherbergung",
    "sg:postcode":"3005",
    "sg:province":"Bern",
    "wof:name":"Unterst\u00fctzungskasse F\u00fcr Bed\u00fcrftige Insassen Und G\u00e4ste Des Vereins Asyl R\u00e4mism\u00fchle",
    "wof:placetype":"venue"
},
  "geometry": {"coordinates":[8.8194599152,47.4399490356],"type":"Point"}
}