{
  "type": "Feature",
  "properties": {
    "iso:country":"CH",
    "sg:address":"Fluestrasse 30",
    "sg:city":"R\u00fcmlang",
    "sg:orig_category":"Allgemeiner Hoch U Tiefbau",
    "sg:postcode":"8153",
    "sg:province":"Z\u00fcrich",
    "wof:name":"Peterer Ag",
    "wof:placetype":"venue"
},
  "geometry": {"coordinates":[9.411415,47.490601],"type":"Point"}
}