{
  "type": "Feature",
  "properties": {
    "iso:country":"CH",
    "sg:address":"R\u00f6ssligasse 15",
    "sg:city":"Gelterkinden",
    "sg:orig_category":"Detailhandel mit Brillen U anderen Sehhilfen Fachdetailhandel in Verkaufsr\u00e4umen",
    "sg:phone":"+41 19772710",
    "sg:postcode":"4460",
    "sg:province":"Basel-Landschaft",
    "wof:name":"Optic For You Gmbh",
    "wof:placetype":"venue"
},
  "geometry": {"coordinates":[8.8426246643,47.300868988],"type":"Point"}
}