{
  "type": "Feature",
  "properties": {
    "iso:country":"CH",
    "sg:address":"Schmiedenstrasse 4",
    "sg:city":"Niederg\u00f6sgen",
    "sg:orig_category":"Bauspenglerei Sanit\u00e4rinstallation",
    "sg:phone":"+41 62 849 55 50",
    "sg:postcode":"5013",
    "sg:province":"Solothurn",
    "wof:name":"Carlo Castegnaro Spenglerei Sanit\u00e4re Anlagen",
    "wof:placetype":"venue"
},
  "geometry": {"coordinates":[7.986591,47.3717],"type":"Point"}
}