{
  "type": "Feature",
  "properties": {
    "iso:country":"CH",
    "sg:address":"Rte Des Acacias 20",
    "sg:city":"Gen\u00e8ve",
    "sg:orig_category":"RESTAURANTS: TEA-ROOMS",
    "sg:postcode":"1200",
    "sg:province":"Gen\u00e8ve",
    "wof:name":"Benedetti M. Et Mme",
    "wof:placetype":"venue"
},
  "geometry": {"coordinates":[6.1362700462,46.1914405823],"type":"Point"}
}