{
  "type": "Feature",
  "properties": {
    "iso:country":"CH",
    "sg:address":"Gutweg 1 5422 Oberehrendingen. Postfach",
    "sg:city":"Oberehrendingen",
    "sg:orig_category":"Non-Classified Establishments",
    "sg:phone":"+41 56 222 47 67",
    "sg:postcode":"5422",
    "wof:name":"Schwitter Peter G\u00e4rtnerei Blumeng\u00e4rtnerei M. Verkaufsladen",
    "wof:placetype":"venue"
},
  "geometry": {"coordinates":[8.3369112015,47.4887733459],"type":"Point"}
}