{
  "type": "Feature",
  "properties": {
    "iso:country":"CH",
    "sg:address":"Robinsonweg 46 3006 Bern. Postfach",
    "sg:city":"Bern",
    "sg:orig_category":"Sonstige pers\u00f6nliche Dienstleistungen",
    "sg:postcode":"3005",
    "sg:province":"Bern",
    "wof:name":"Sitael, Leider Margot",
    "wof:placetype":"venue"
},
  "geometry": {"coordinates":[7.1247320175,46.9275741577],"type":"Point"}
}