{
  "type": "Feature",
  "properties": {
    "iso:country":"CH",
    "sg:address":"6548",
    "sg:city":"Rossa",
    "sg:classifiers":[
        {
            "category":"Restaurant",
            "type":"Food & Drink"
        }
    ],
    "sg:phone":"+41 91 828 11 67",
    "sg:postcode":"6548",
    "sg:province":"Graubunden",
    "wof:name":"Ristorante Alpino",
    "wof:placetype":"venue"
},
  "geometry": {"coordinates":[9.1255588531,46.3726005554],"type":"Point"}
}