{
  "type": "Feature",
  "properties": {
    "iso:country":"CH",
    "sg:address":"Staatsstrasse 151a",
    "sg:city":"Gunten",
    "sg:orig_category":"Autogaragen",
    "sg:phone":"+41 33 251 14 50",
    "sg:postcode":"3654",
    "sg:province":"Bern",
    "wof:name":"Andreas Schl\u00fcchter Garage",
    "wof:placetype":"venue"
},
  "geometry": {"coordinates":[7.7014,46.712708],"type":"Point"}
}