{
  "type": "Feature",
  "properties": {
    "addr:full":"Bahnhofstrasse 32 Landquart Graubunden 7302",
    "addr:housenumber":"32",
    "addr:postcode":"7302",
    "addr:street":"Bahnhofstrasse",
    "iso:country":"CH",
    "sg:address":"Bahnhofstrasse 32",
    "sg:city":"Landquart",
    "sg:classifiers":[
        {
            "category":"Bars & Pubs",
            "type":"Food & Drink"
        }
    ],
    "sg:phone":"+41 81 322 92 52",
    "sg:postcode":"7302",
    "sg:province":"Graubunden",
    "sg:tags":[
        "restaurant"
    ],
    "wof:name":"Bistro-pub Mac Key",
    "wof:placetype":"venue"
},
  "geometry": {"coordinates":[9.559021,46.967754],"type":"Point"}
}