{
  "type": "Feature",
  "properties": {
    "iso:country":"CH",
    "sg:address":"Birkenweg 6",
    "sg:city":"Visp",
    "sg:orig_category":"Erschliessung von Grundst\u00fccken",
    "sg:postcode":"3930",
    "sg:province":"Valais",
    "wof:name":"Baugenossenschaft F\u00fcr Sozialen Wohnungsbau Visp",
    "wof:placetype":"venue"
},
  "geometry": {"coordinates":[7.8787698746,46.2960090637],"type":"Point"}
}