{
  "type": "Feature",
  "properties": {
    "iso:country":"CH",
    "sg:address":"Kreuzwiesen 17",
    "sg:city":"Z\u00fcrich",
    "sg:orig_category":"Fahrschulen, Flugschulen",
    "sg:phone":"+41 13228403",
    "sg:postcode":"8051",
    "sg:province":"Z\u00fcrich",
    "wof:name":"Stefan Domanski Autofahrschule",
    "wof:placetype":"venue"
},
  "geometry": {"coordinates":[8.5750923157,47.4067268372],"type":"Point"}
}