{
  "type": "Feature",
  "properties": {
    "iso:country":"CH",
    "sg:address":"Untere Hauptgasse 7",
    "sg:city":"Thun",
    "sg:orig_category":"RESTAURANTS: TEA-ROOMS",
    "sg:phone":"+41 33 222 44 70",
    "sg:postcode":"3600",
    "sg:province":"Bern",
    "wof:name":"Ristorante Boccalino Gmbh",
    "wof:placetype":"venue"
},
  "geometry": {"coordinates":[7.6284990311,46.7601852417],"type":"Point"}
}