{
  "type": "Feature",
  "properties": {
    "iso:country":"CH",
    "sg:address":"Chemin Des Sorbiers 21",
    "sg:city":"Chardonne",
    "sg:orig_category":"Naturheil\u00e4rzte and Heilpraktiker",
    "sg:phone":"+41 19500777",
    "sg:postcode":"1803",
    "sg:province":"Vaud",
    "wof:name":"Brigitte M\u00fcller Naturheilpraxis",
    "wof:placetype":"venue"
},
  "geometry": {"coordinates":[8.7927894592,47.361541748],"type":"Point"}
}