{
  "type": "Feature",
  "properties": {
    "iso:country":"CH",
    "sg:address":"Sch\u00e4ndrichstrasse 6",
    "sg:city":"Flawil",
    "sg:orig_category":"Herstellung von Werkzeugen Mechanische Werkst\u00e4tten",
    "sg:phone":"+41 71 393 39 39",
    "sg:postcode":"9230",
    "sg:province":"St. Gallen",
    "wof:name":"Tbs Werkzeugsch\u00e4rferei Ag",
    "wof:placetype":"venue"
},
  "geometry": {"coordinates":[9.2004032135,47.4094696045],"type":"Point"}
}