{
  "type": "Feature",
  "properties": {
    "iso:country":"CH",
    "sg:address":"Dorfstrasse 2",
    "sg:city":"Thierachern",
    "sg:classifiers":[
        {
            "category":"Restaurant",
            "type":"Food & Drink"
        }
    ],
    "sg:phone":"+41 33 345 32 68",
    "sg:postcode":"3634",
    "sg:province":"Bern",
    "wof:name":"Restaurant B\u00e4ren",
    "wof:placetype":"venue"
},
  "geometry": {"coordinates":[7.5758509636,46.7541122437],"type":"Point"}
}