{
  "type": "Feature",
  "properties": {
    "iso:country":"CH",
    "sg:address":"Via Zorzi 23",
    "sg:city":"Bellinzona",
    "sg:orig_category":"Instandhaltung U Reparatur von Automobilen Tankstellen",
    "sg:phone":"+41 91 825 77 75",
    "sg:postcode":"6500",
    "sg:province":"Ticino",
    "wof:name":"Intercar Sa",
    "wof:placetype":"venue"
},
  "geometry": {"coordinates":[9.0140123367,46.1860923767],"type":"Point"}
}