{
  "type": "Feature",
  "properties": {
    "iso:country":"CH",
    "sg:address":"Via Emmaus 1 6616 Losone. Postfach Caselle Postale 6879",
    "sg:city":"Losone",
    "sg:orig_category":"Verbraucherm\u00e4rkte > 2500 m2",
    "sg:phone":"+41 91 785 80 81",
    "sg:postcode":"6616",
    "sg:province":"Ticino",
    "wof:name":"Centro Comm.mercato Cattori",
    "wof:placetype":"venue"
},
  "geometry": {"coordinates":[8.7683925629,46.1649589539],"type":"Point"}
}