{
  "type": "Feature",
  "properties": {
    "iso:country":"CH",
    "sg:address":"Chemin De Chantegrive 17",
    "sg:city":"Sierre",
    "sg:orig_category":"Herstellung von sonstigen Metallwaren",
    "sg:phone":"+41 41 480 42 12",
    "sg:postcode":"3960",
    "sg:province":"Valais",
    "wof:name":"Richard Marti Gravuren",
    "wof:placetype":"venue"
},
  "geometry": {"coordinates":[8.0499401093,46.9792098999],"type":"Point"}
}