{
  "type": "Feature",
  "properties": {
    "iso:country":"CH",
    "sg:address":"Route De L' Industrie 25 1784 Courtepin Case Postale 128",
    "sg:city":"Courtepin",
    "sg:orig_category":"Haltung von Gefl\u00fcgel",
    "sg:phone":"+41 21 651 72 72",
    "sg:postcode":"1784",
    "sg:province":"Fribourg",
    "wof:name":"Optigal Sa Produits De Volailles",
    "wof:placetype":"venue"
},
  "geometry": {"coordinates":[7.1208529472,46.8660240173],"type":"Point"}
}