{
  "type": "Feature",
  "properties": {
    "iso:country":"CH",
    "sg:address":"Am Marktplatz 9400 Rorschach. Postfach 118",
    "sg:city":"Rorschach",
    "sg:orig_category":"Wirtschafts- and Arbeitgeberverb\u00e4nde",
    "sg:phone":"+41 71 228 26 26",
    "sg:postcode":"9401",
    "sg:province":"St. Gallen",
    "wof:name":"Arbeitgeber-verband Rorschach & Umgebung",
    "wof:placetype":"venue"
},
  "geometry": {"coordinates":[9.4907989502,47.4782447815],"type":"Point"}
}