{
  "type": "Feature",
  "properties": {
    "addr:full":"Buchillon Route De 3 St-prex Vaud 1162",
    "addr:housenumber":"buchillon;3",
    "addr:postcode":"1162",
    "addr:street":"Route De",
    "iso:country":"CH",
    "sg:address":"Buchillon Route De 3",
    "sg:city":"St-prex",
    "sg:orig_category":"Architektur U Ingenieurb\u00fcros",
    "sg:phone":"+41 21 806 19 60",
    "sg:postcode":"1162",
    "sg:province":"Vaud",
    "wof:name":"Archi-service, Desgraz M.",
    "wof:placetype":"venue"
},
  "geometry": {"coordinates":[6.447581,46.476784],"type":"Point"}
}