{
  "type": "Feature",
  "properties": {
    "iso:country":"CH",
    "sg:address":"Binzm\u00fchlestrasse 229 8046 Z\u00fcrich. Postfach",
    "sg:city":"Z\u00fcrich",
    "sg:orig_category":"Detailhandel mit Metallwaren, Anstrichmitteln, Glaswaren, Bau U Heimwerkerbedarf",
    "sg:postcode":"8046",
    "sg:province":"Z\u00fcrich",
    "wof:name":"Minira Trade Gmbh",
    "wof:placetype":"venue"
},
  "geometry": {"coordinates":[8.5296268463,47.4134025574],"type":"Point"}
}