{
  "type": "Feature",
  "properties": {
    "iso:country":"CH",
    "sg:address":"Im G\u00fcetli 6 5504 Othmarsingen. Postfach",
    "sg:city":"Othmarsingen",
    "sg:orig_category":"Detailhandel mit Sportartikeln Fachdetailhandel in Verkaufsr\u00e4umen",
    "sg:phone":"+41 17154433",
    "sg:postcode":"5504",
    "sg:province":"Aargau",
    "wof:name":"Tauchl\u00e4deli Peter Bamert Ag",
    "wof:placetype":"venue"
},
  "geometry": {"coordinates":[8.5464086533,47.3297386169],"type":"Point"}
}