{
  "type": "Feature",
  "properties": {
    "iso:country":"CH",
    "sg:address":"Perdtemps Avenue 9",
    "sg:city":"Nyon",
    "sg:orig_category":"Herstellung von medizinischen U chirurgischen Ger\u00e4ten sowie orthop\u00e4dischen Vorrichtungen",
    "sg:phone":"+41 19771497",
    "sg:postcode":"1260",
    "sg:province":"Vaud",
    "wof:name":"Ramsauer Engineering",
    "wof:placetype":"venue"
},
  "geometry": {"coordinates":[8.8588104248,47.287776947],"type":"Point"}
}