{
  "type": "Feature",
  "properties": {
    "iso:country":"CH",
    "sg:address":"Institut Baldegg",
    "sg:city":"Hochdorf",
    "sg:orig_category":"Wohnheime",
    "sg:postcode":"6280",
    "sg:province":"Luzern",
    "wof:name":"St. Galler Jugendheime",
    "wof:placetype":"venue"
},
  "geometry": {"coordinates":[9.2972230911,47.4022865295],"type":"Point"}
}