{
  "type": "Feature",
  "properties": {
    "iso:country":"CH",
    "sg:address":"Hauptstrasse 92",
    "sg:city":"Kreuzlingen",
    "sg:orig_category":"Sonstiger Fachdetailhandel in Verkaufsr\u00e4umen",
    "sg:phone":"+41 71 672 14 85",
    "sg:postcode":"8280",
    "sg:province":"Thurgau",
    "wof:name":"Heinz Kussmann Briefmarken-fachgesch\u00e4ft",
    "wof:placetype":"venue"
},
  "geometry": {"coordinates":[9.1774091721,47.6457328796],"type":"Point"}
}