{
  "type": "Feature",
  "properties": {
    "iso:country":"CH",
    "sg:address":"Chantemerle Route De 39",
    "sg:city":"Granges-paccot",
    "sg:orig_category":"Unclassifiable Establishments",
    "sg:postcode":"1763",
    "sg:province":"Fribourg",
    "wof:name":"Schako K\u00fcbler Ag, Succursale De Granges-paccot",
    "wof:placetype":"venue"
},
  "geometry": {"coordinates":[7.1423649788,46.8250312805],"type":"Point"}
}