{
  "type": "Feature",
  "properties": {
    "iso:country":"CH",
    "sg:address":"Richard Wagner-strasse 28 8002 Z\u00fcrich. Postfach",
    "sg:city":"Z\u00fcrich",
    "sg:orig_category":"Herstellung von Metallerzeugnissen ohne Maschinenbau Herstellung von \u00d6fen U Brennern",
    "sg:phone":"+41 34 402 32 62",
    "sg:postcode":"8027",
    "sg:province":"Z\u00fcrich",
    "wof:name":"Ofenfabrik Schenk Ag",
    "wof:placetype":"venue"
},
  "geometry": {"coordinates":[7.757589817,46.9491271973],"type":"Point"}
}