{
  "type": "Feature",
  "properties": {
    "iso:country":"CH",
    "sg:address":"Holeerain 7a",
    "sg:city":"Binningen",
    "sg:orig_category":"Pensionskassen",
    "sg:phone":"+41 61 821 41 41",
    "sg:postcode":"4102",
    "sg:province":"Basel-Landschaft",
    "wof:name":"Personalf\u00fcrsorgestiftung Der Fribos Ag",
    "wof:placetype":"venue"
},
  "geometry": {"coordinates":[7.5732312202,47.5426445007],"type":"Point"}
}