{
  "type": "Feature",
  "properties": {
    "iso:country":"CH",
    "sg:address":"Via Delle Scuole 6",
    "sg:city":"Lugano",
    "sg:orig_category":"Non-Classified Establishments",
    "sg:postcode":"6900",
    "sg:province":"Ticino",
    "wof:name":"Tc Business Control Sa Agenzia Viaggi Magic Travel",
    "wof:placetype":"venue"
},
  "geometry": {"coordinates":[8.9636154175,46.0245704651],"type":"Point"}
}