{
  "type": "Feature",
  "properties": {
    "iso:country":"CH",
    "sg:address":"Dammstrasse 8 6300 Zug. Postfach",
    "sg:city":"Zug",
    "sg:orig_category":"Sonstige pers\u00f6nliche Dienstleistungen",
    "sg:phone":"+41 55 442 91 41",
    "sg:postcode":"6300",
    "sg:province":"Zug",
    "wof:name":"G\u00fcntensperger Stefan Consulting",
    "wof:placetype":"venue"
},
  "geometry": {"coordinates":[8.7741804123,47.2050476074],"type":"Point"}
}