{
  "type": "Feature",
  "properties": {
    "addr:full":"Industriestrasse Pratteln Basel-Landschaft 4133",
    "addr:postcode":"pratteln;4133",
    "addr:street":"Industriestrasse",
    "iso:country":"CH",
    "sg:address":"Industriestrasse",
    "sg:city":"Pratteln",
    "sg:classifiers":[
        {
            "category":"Structure",
            "subcategory":"Warehouse",
            "type":"Public Place"
        }
    ],
    "sg:phone":"+41 61 825 68 00",
    "sg:postcode":"4133",
    "sg:province":"Basel-Landschaft",
    "sg:tags":[
        "air-conditioning",
        "system"
    ],
    "wof:name":"Klimatherm Gmbh",
    "wof:placetype":"venue"
},
  "geometry": {"coordinates":[7.686981,47.52317],"type":"Point"}
}