{
  "type": "Feature",
  "properties": {
    "iso:country":"CH",
    "sg:address":"Zuchwilerstrasse 21 4500 Solothurn. Postfach",
    "sg:city":"Solothurn",
    "sg:orig_category":"Zeitungsverlag",
    "sg:postcode":"4500",
    "sg:province":"Solothurn",
    "wof:name":"Solprint Ag",
    "wof:placetype":"venue"
},
  "geometry": {"coordinates":[7.5395798683,47.2030334473],"type":"Point"}
}