{
  "type": "Feature",
  "properties": {
    "iso:country":"CH",
    "sg:address":"Route Du Crochet 7 1762 Givisiez Case Postale 1",
    "sg:city":"Givisiez",
    "sg:orig_category":"Satzherstellung U Reproduktion",
    "sg:phone":"+41 26 466 88 80",
    "sg:postcode":"1762",
    "sg:province":"Fribourg",
    "wof:name":"Mls-microlaser Services Sa",
    "wof:placetype":"venue"
},
  "geometry": {"coordinates":[7.1341409683,46.8158798218],"type":"Point"}
}