{
  "type": "Feature",
  "properties": {
    "iso:country":"CH",
    "sg:address":"Industriestrasse 28",
    "sg:city":"Wittenbach",
    "sg:orig_category":"Finanzierungsinstitutionen",
    "sg:phone":"+41 31 751 00 38",
    "sg:postcode":"9303",
    "wof:name":"Ca Consulting Gmbh",
    "wof:placetype":"venue"
},
  "geometry": {"coordinates":[9.3932647705,47.4628143311],"type":"Point"}
}