{
  "type": "Feature",
  "properties": {
    "iso:country":"CH",
    "sg:address":"Erlimattstrasse 18",
    "sg:city":"Sirnach",
    "sg:orig_category":"RESTAURANTS: TEA-ROOMS",
    "sg:phone":"+41 71 966 72 21",
    "sg:postcode":"8370",
    "sg:province":"Thurgau",
    "wof:name":"Starlight - Betriebs - Gmbh",
    "wof:placetype":"venue"
},
  "geometry": {"coordinates":[9.002243042,47.4708595276],"type":"Point"}
}