{
  "type": "Feature",
  "properties": {
    "iso:country":"CH",
    "sg:address":"6662",
    "sg:city":"Russo",
    "sg:orig_category":"Stukkateurgewerbe, Gipserei U Verputzerei Tapeziererei",
    "sg:phone":"+41 81 302 78 48",
    "sg:postcode":"6662",
    "sg:province":"Ticino",
    "wof:name":"Brunner Malerei Ag",
    "wof:placetype":"venue"
},
  "geometry": {"coordinates":[9.5013246536,47.0036811829],"type":"Point"}
}