{
  "type": "Feature",
  "properties": {
    "iso:country":"CH",
    "sg:address":"Hohlstrasse 193 8004 Z\u00fcrich. Postfach",
    "sg:city":"Z\u00fcrich",
    "sg:orig_category":"Herstellung von Metallkonstruktionen",
    "sg:postcode":"8001",
    "sg:province":"Z\u00fcrich",
    "wof:name":"Intermont Nocco S. Montagearbeiten",
    "wof:placetype":"venue"
},
  "geometry": {"coordinates":[8.5176582336,47.3810348511],"type":"Point"}
}