{
  "type": "Feature",
  "properties": {
    "iso:country":"CH",
    "sg:address":"Weinfelderstrasse 54",
    "sg:city":"Amriswil",
    "sg:classifiers":[
        {
            "category":"Restaurant",
            "type":"Food & Drink"
        }
    ],
    "sg:phone":"+41 71 411 26 55",
    "sg:postcode":"8580",
    "sg:province":"Thurgau",
    "wof:name":"Restaurant Sonne Amriswil",
    "wof:placetype":"venue"
},
  "geometry": {"coordinates":[9.2890443802,47.5446739197],"type":"Point"}
}