{
  "type": "Feature",
  "properties": {
    "iso:country":"CH",
    "sg:address":"Hauptgasse 10 6130 Willisau. Postfach",
    "sg:city":"Willisau",
    "sg:orig_category":"Vereine Fasnacht",
    "sg:phone":"+41 41 970 27 09",
    "sg:postcode":"6130",
    "sg:province":"Luzern",
    "wof:name":"Fasnachtsges.karn\u00f6ttelzunft Hotel Hirschen",
    "wof:placetype":"venue"
},
  "geometry": {"coordinates":[7.9914679527,47.1209526062],"type":"Point"}
}