{
  "type": "Feature",
  "properties": {
    "iso:country":"CH",
    "sg:address":"Bahnhofstrasse 11",
    "sg:city":"Visp",
    "sg:orig_category":"RESTAURANTS: TEA-ROOMS",
    "sg:postcode":"3930",
    "sg:province":"Valais",
    "wof:name":"Tea-room-restaurant J\u00e4ger Furrer-fercher Cresenz",
    "wof:placetype":"venue"
},
  "geometry": {"coordinates":[7.8817811012,46.2929344177],"type":"Point"}
}