{
  "type": "Feature",
  "properties": {
    "iso:country":"CH",
    "sg:address":"Thermes De Val-d'illiez",
    "sg:city":"Val-d'illiez",
    "sg:classifiers":[
        {
            "category":"Travel",
            "subcategory":"Hotels & Motels",
            "type":"Entertainment"
        }
    ],
    "sg:postcode":"1873",
    "sg:province":"Valais",
    "sg:tags":[
        "hotels",
        "mit",
        "restaurant"
    ],
    "wof:name":"Soci\u00e9t\u00e9 H\u00f4teli\u00e8re Des Termes De Val D'illiez Sa",
    "wof:placetype":"venue"
},
  "geometry": {"coordinates":[3.891422987,51.3344230652],"type":"Point"}
}