{
  "type": "Feature",
  "properties": {
    "iso:country":"CH",
    "sg:address":"Chemin Du Chamoliet 44",
    "sg:city":"Th\u00f4nex",
    "sg:orig_category":"HOTELS: MIT RESTAURANT Unternehmensberatung",
    "sg:phone":"+41 22 348 57 70",
    "sg:postcode":"1226",
    "sg:province":"Gen\u00e8ve",
    "wof:name":"Profia Sa",
    "wof:placetype":"venue"
},
  "geometry": {"coordinates":[6.2189660072,46.2045593262],"type":"Point"}
}