{
  "type": "Feature",
  "properties": {
    "iso:country":"CH",
    "sg:address":"F\u00e4rberstrasse 15",
    "sg:city":"Z\u00fcrich",
    "sg:orig_category":"Non-Classified Establishments",
    "sg:postcode":"8008",
    "sg:province":"Z\u00fcrich",
    "wof:name":"Dr.med. Andreas E. Benz Spezialarzt Fmh",
    "wof:placetype":"venue"
},
  "geometry": {"coordinates":[8.5489015579,47.3621025085],"type":"Point"}
}