{
  "type": "Feature",
  "properties": {
    "addr:full":"Biberlinstrasse 16 Z\u00fcrich Z\u00fcrich 8032",
    "addr:housenumber":"16",
    "addr:postcode":"8032",
    "addr:street":"Biberlinstrasse",
    "iso:country":"CH",
    "sg:address":"Biberlinstrasse 16",
    "sg:city":"Z\u00fcrich",
    "sg:orig_category":"Bauingenieurb\u00fcros Eisenbetonbau Bauingenieurb\u00fcros allgemein",
    "sg:phone":"+41 13891727",
    "sg:postcode":"8032",
    "sg:province":"Z\u00fcrich",
    "wof:name":"Minikus Witta & Voss Ingenieurb\u00fcro",
    "wof:placetype":"venue"
},
  "geometry": {"coordinates":[8.568987,47.363083],"type":"Point"}
}