{
  "type": "Feature",
  "properties": {
    "iso:country":"CH",
    "sg:address":"Allr\u00fctiweg 9 6343 Rotkreuz. Postfach 636",
    "sg:city":"Rotkreuz",
    "sg:orig_category":"Elektro- and elektronische Maschinen Grosshandel Hardwareberatung",
    "sg:phone":"+41 41 792 08 30",
    "sg:postcode":"6343",
    "sg:province":"Zug",
    "wof:name":"Cdz Cabling Discount Z\u00fcger",
    "wof:placetype":"venue"
},
  "geometry": {"coordinates":[8.4660310745,47.1341400146],"type":"Point"}
}