{
  "type": "Feature",
  "properties": {
    "addr:full":"D\u00e4llikerstrasse 44 Regensdorf Z\u00fcrich 8105",
    "addr:housenumber":"44",
    "addr:postcode":"8105",
    "addr:street":"Daellikerstrasse",
    "iso:country":"CH",
    "sg:address":"D\u00e4llikerstrasse 44",
    "sg:city":"Regensdorf",
    "sg:orig_category":"Arztpraxen",
    "sg:phone":"+41 18406612",
    "sg:postcode":"8105",
    "sg:province":"Z\u00fcrich",
    "wof:name":"Dr.med.felix Hess Spezialarzt Fmh",
    "wof:placetype":"venue"
},
  "geometry": {"coordinates":[8.462591,47.431503],"type":"Point"}
}