{
  "type": "Feature",
  "properties": {
    "iso:country":"CH",
    "sg:address":"Imbisb\u00fchlstrasse 25a",
    "sg:city":"Z\u00fcrich",
    "sg:orig_category":"Maurerarbeiten",
    "sg:phone":"+41 79 236 58 00",
    "sg:postcode":"8049",
    "sg:province":"Z\u00fcrich",
    "wof:name":"Ren\u00e9 Piatti Maurergesch\u00e4ft",
    "wof:placetype":"venue"
},
  "geometry": {"coordinates":[8.4921941757,47.4034881592],"type":"Point"}
}