{
  "type": "Feature",
  "properties": {
    "iso:country":"CH",
    "sg:address":"Place De La Fusterie 12",
    "sg:city":"Gen\u00e8ve",
    "sg:orig_category":"RESTAURANTS: TEA-ROOMS",
    "sg:phone":"+41 22 311 05 15",
    "sg:postcode":"1204",
    "sg:province":"Gen\u00e8ve",
    "wof:name":"Restaurant Baroque",
    "wof:placetype":"venue"
},
  "geometry": {"coordinates":[6.1455030441,46.2039413452],"type":"Point"}
}