{
  "type": "Feature",
  "properties": {
    "iso:country":"CH",
    "sg:address":"Rue De Lausanne 53",
    "sg:city":"Vallorbe",
    "sg:orig_category":"Erbringung von Dienstleistungen f\u00fcr Unternehmen",
    "sg:postcode":"1337",
    "sg:province":"Vaud",
    "wof:name":"Ideal Fiorito Luigi",
    "wof:placetype":"venue"
},
  "geometry": {"coordinates":[6.3843097687,46.7115592957],"type":"Point"}
}