{
  "type": "Feature",
  "properties": {
    "iso:country":"CH",
    "sg:address":"Breisacherstrasse 82 4057 Basel. Postfach",
    "sg:city":"Basel",
    "sg:orig_category":"Herstellung von Konstruktionsteilen, Fertigbauteilen U Ausbauelementen aus Holz",
    "sg:postcode":"4051",
    "sg:province":"Basel-Stadt",
    "wof:name":"Graf-streif Aug. Bau, M\u00f6belschreinerei",
    "wof:placetype":"venue"
},
  "geometry": {"coordinates":[7.5889258385,47.5677490234],"type":"Point"}
}