{
  "type": "Feature",
  "properties": {
    "addr:full":"Plage Route De La Estavayer-le-lac Fribourg 1470",
    "addr:postcode":"1470",
    "addr:street":"Route De La Estavayer-Le-Lac Fribourg",
    "iso:country":"CH",
    "sg:address":"Plage Route De La",
    "sg:city":"Estavayer-le-lac",
    "sg:orig_category":"Betrieb von Sportanlagen",
    "sg:phone":"+41 32 724 57 58",
    "sg:postcode":"1470",
    "sg:province":"Fribourg",
    "wof:name":"Minigolf Des Jeunes Rives Neuch\u00e2tel Sa",
    "wof:placetype":"venue"
},
  "geometry": {"coordinates":[6.94464,46.994614],"type":"Point"}
}