{
  "type": "Feature",
  "properties": {
    "iso:country":"CH",
    "sg:address":"Grandes-buttes Promenade 14",
    "sg:city":"Rolle",
    "sg:orig_category":"Kinderg\u00e4rten, Vor U Grundschulen",
    "sg:postcode":"1180",
    "sg:province":"Vaud",
    "wof:name":"Fondation Soroptimist International Pour La Cr\u00e8che \u00e0 Rolle",
    "wof:placetype":"venue"
},
  "geometry": {"coordinates":[6.3372449875,46.4611282349],"type":"Point"}
}