{
  "type": "Feature",
  "properties": {
    "addr:full":"Feldstrasse 1 Buchrain Luzern 6033",
    "addr:housenumber":"1",
    "addr:postcode":"6033",
    "addr:street":"Feldstrasse",
    "iso:country":"CH",
    "sg:address":"Feldstrasse 1",
    "sg:city":"Buchrain",
    "sg:orig_category":"Bauschreinerei",
    "sg:phone":"+41 41 440 31 55",
    "sg:postcode":"6033",
    "sg:province":"Luzern",
    "wof:name":"Thomas Scheidegger Schreinerei",
    "wof:placetype":"venue"
},
  "geometry": {"coordinates":[8.35346,47.098618],"type":"Point"}
}