{
  "type": "Feature",
  "properties": {
    "iso:country":"CH",
    "sg:address":"Auenring 11",
    "sg:city":"Bassersdorf",
    "sg:orig_category":"Zoll- and Grenzb\u00fcros",
    "sg:phone":"+41 32 724 44 88",
    "sg:postcode":"8303",
    "sg:province":"Z\u00fcrich",
    "wof:name":"Douane Suisse & Contr\u00f4le Des M\u00e9taux Pr\u00e9cieux",
    "wof:placetype":"venue"
},
  "geometry": {"coordinates":[6.941450119,46.9826812744],"type":"Point"}
}