{
  "type": "Feature",
  "properties": {
    "iso:country":"CH",
    "sg:address":"2807 Pleigne. Postfach",
    "sg:city":"Pleigne",
    "sg:orig_category":"Verwertung von Milch",
    "sg:postcode":"2807",
    "sg:province":"Jura",
    "wof:name":"Soci\u00e9t\u00e9 De Laiterie De Poliez-le-grand",
    "wof:placetype":"venue"
},
  "geometry": {"coordinates":[6.6645698547,46.6371917725],"type":"Point"}
}