{
  "type": "Feature",
  "properties": {
    "iso:country":"CH",
    "sg:address":"Freiestrasse 2",
    "sg:city":"Uster",
    "sg:classifiers":[
        {
            "category":"Banks & Credit Unions",
            "subcategory":"Bank",
            "type":"Services"
        }
    ],
    "sg:phone":"+41 19054444",
    "sg:postcode":"8610",
    "sg:province":"Z\u00fcrich",
    "wof:name":"Z\u00fcrcher Kantonalbank",
    "wof:placetype":"venue"
},
  "geometry": {"coordinates":[8.719426,47.349304],"type":"Point"}
}