{
  "type": "Feature",
  "properties": {
    "iso:country":"CH",
    "sg:address":"Weidwiesen",
    "sg:city":"Oberaach",
    "sg:orig_category":"Herstellung von Tanks U Sammelbeh\u00e4ltern aus Metall Stahl U Leichtmetallbau",
    "sg:phone":"+41 56 496 19 59",
    "sg:postcode":"8587",
    "sg:province":"Thurgau",
    "wof:name":"H. Huber Ag, Tank Und Metallbau",
    "wof:placetype":"venue"
},
  "geometry": {"coordinates":[8.3134889603,47.4082374573],"type":"Point"}
}