{
  "type": "Feature",
  "properties": {
    "iso:country":"CH",
    "sg:address":"1921",
    "sg:city":"Martigny-croix",
    "sg:classifiers":[
        {
            "category":"Restaurant",
            "type":"Food & Drink"
        }
    ],
    "sg:phone":"+41 27 776 12 06",
    "sg:postcode":"1921",
    "sg:province":"Valais",
    "wof:name":"Caf\u00e9 Place",
    "wof:placetype":"venue"
},
  "geometry": {"coordinates":[7.2124481201,46.0804595947],"type":"Point"}
}