{
  "type": "Feature",
  "properties": {
    "iso:country":"CH",
    "sg:address":"Fahrweidstrasse 46",
    "sg:city":"Fahrweid",
    "sg:orig_category":"Einbau von Schreinerwaren Innenausbau",
    "sg:phone":"+41 33 722 33 17",
    "sg:postcode":"8951",
    "sg:province":"Z\u00fcrich",
    "wof:name":"Rudolf Bergmann K\u00fcchenbau & Innenausbau",
    "wof:placetype":"venue"
},
  "geometry": {"coordinates":[7.3931250572,46.5120162964],"type":"Point"}
}