{
  "type": "Feature",
  "properties": {
    "iso:country":"CH",
    "sg:address":"Seonerstrasse 322",
    "sg:city":"Egliswil",
    "sg:orig_category":"Herstellung von Kunststoffwaren Herstellung von sonstigen Erzeugnissen",
    "sg:phone":"+41 62 775 10 72",
    "sg:postcode":"5704",
    "sg:province":"Aargau",
    "wof:name":"Bouton Helvetia Sa",
    "wof:placetype":"venue"
},
  "geometry": {"coordinates":[8.1771373749,47.3495826721],"type":"Point"}
}