{
  "type": "Feature",
  "properties": {
    "iso:country":"CH",
    "sg:address":"Industrie Rue De L' 43 1950 Sion. Postfach",
    "sg:city":"Sitten",
    "sg:classifiers":[
        {
            "category":"Communications",
            "subcategory":"Radio Station",
            "type":"Services"
        }
    ],
    "sg:phone":"+41 22 708 99 11",
    "sg:postcode":"1950",
    "sg:province":"Valais",
    "sg:tags":[
        "fernsehanstalten",
        "u"
    ],
    "wof:name":"T\u00e9l\u00e9vision Suisse Romande",
    "wof:placetype":"venue"
},
  "geometry": {"coordinates":[6.1359410286,46.1959495544],"type":"Point"}
}