{
  "type": "Feature",
  "properties": {
    "iso:country":"CH",
    "sg:address":"Aeuli",
    "sg:city":"Sargans",
    "sg:orig_category":"Detailhandel mit Getr\u00e4nken",
    "sg:phone":"+41 81 723 28 88",
    "sg:postcode":"7320",
    "sg:province":"St. Gallen",
    "wof:name":"Franz Anrig Getr\u00e4nkehandel",
    "wof:placetype":"venue"
},
  "geometry": {"coordinates":[9.4566698074,47.0543632507],"type":"Point"}
}