{
  "type": "Feature",
  "properties": {
    "iso:country":"CH",
    "sg:address":"Th\u00e9\u00e2tre Avenue Du 8bis",
    "sg:city":"Lausanne",
    "sg:orig_category":"Unclassifiable Establishments",
    "sg:postcode":"1005",
    "sg:province":"Vaud",
    "wof:name":"Granito Holding Ag",
    "wof:placetype":"venue"
},
  "geometry": {"coordinates":[7.3147788048,47.1114120483],"type":"Point"}
}