{
  "type": "Feature",
  "properties": {
    "iso:country":"CH",
    "sg:address":"Schaffhauserstrasse 360",
    "sg:city":"Z\u00fcrich",
    "sg:orig_category":"Kosmetikinstitute",
    "sg:phone":"+41 19106464",
    "sg:postcode":"8050",
    "sg:province":"Z\u00fcrich",
    "wof:name":"Beauty Place Kosmetik Studio Karin Schmid",
    "wof:placetype":"venue"
},
  "geometry": {"coordinates":[8.5829353333,47.3197097778],"type":"Point"}
}