{
  "type": "Feature",
  "properties": {
    "iso:country":"CH",
    "sg:address":"Centro Carvina 6",
    "sg:city":"Taverne",
    "sg:orig_category":"Grosshandel mit elektrischen Haushaltsger\u00e4ten Herstellung von elektrischen Lampen U Leuchten",
    "sg:phone":"+41 91 945 41 43",
    "sg:postcode":"6807",
    "sg:province":"Ticino",
    "wof:name":"New Nacsa Sa",
    "wof:placetype":"venue"
},
  "geometry": {"coordinates":[8.9333286285,46.0671730042],"type":"Point"}
}