{
  "type": "Feature",
  "properties": {
    "iso:country":"CH",
    "sg:address":"Schrotm\u00e4ttli 1 6014 Littau. Postfach",
    "sg:city":"Littau",
    "sg:orig_category":"Fachdetailhandel in Verkaufsr\u00e4umen",
    "sg:phone":"+41 41 250 80 15",
    "sg:postcode":"6014",
    "sg:province":"Luzern",
    "wof:name":"Hw Horse World Gmbh",
    "wof:placetype":"venue"
},
  "geometry": {"coordinates":[8.2568702698,47.0471725464],"type":"Point"}
}