{
  "type": "Feature",
  "properties": {
    "iso:country":"CH",
    "sg:address":"1588",
    "sg:city":"Cudrefin",
    "sg:orig_category":"RESTAURANTS: TEA-ROOMS",
    "sg:postcode":"1588",
    "sg:province":"Vaud",
    "wof:name":"Stosch Harald E Marilena",
    "wof:placetype":"venue"
},
  "geometry": {"coordinates":[8.7835540771,46.1219673157],"type":"Point"}
}