{
  "type": "Feature",
  "properties": {
    "iso:country":"CH",
    "sg:address":"3652",
    "sg:city":"Hilterfingen",
    "sg:orig_category":"Schulpflegen",
    "sg:postcode":"3652",
    "sg:province":"Bern",
    "wof:name":"Schulkommission Der M\u00e4dchensekundarschule Laubegg",
    "wof:placetype":"venue"
},
  "geometry": {"coordinates":[7.4657149315,46.9473228455],"type":"Point"}
}