{
  "type": "Feature",
  "properties": {
    "iso:country":"CH",
    "sg:address":"G\u00e4ssli 5",
    "sg:city":"Wynigen",
    "sg:orig_category":"Softwareentwicklung U beratung",
    "sg:postcode":"3472",
    "sg:province":"Bern",
    "wof:name":"Edv + Cad Im Handwerk, Ruth",
    "wof:placetype":"venue"
},
  "geometry": {"coordinates":[7.6674489975,47.1045913696],"type":"Point"}
}