{
  "type": "Feature",
  "properties": {
    "iso:country":"CH",
    "sg:address":"6248",
    "sg:city":"Alberswil",
    "sg:classifiers":[
        {
            "category":"Travel",
            "subcategory":"Hotels & Motels",
            "type":"Entertainment"
        }
    ],
    "sg:phone":"+41 41 980 17 12",
    "sg:postcode":"6248",
    "sg:province":"Luzern",
    "sg:tags":[
        "hotels",
        "mit",
        "restaurant"
    ],
    "wof:name":"Heimann-lustenberger Karl",
    "wof:placetype":"venue"
},
  "geometry": {"coordinates":[7.9967498779,47.1450691223],"type":"Point"}
}