{
  "type": "Feature",
  "properties": {
    "iso:country":"CH",
    "sg:address":"Route Du Ch\u00eane",
    "sg:city":"Belprahon",
    "sg:orig_category":"Schlossereien Schmieden",
    "sg:phone":"+41 32 493 51 57",
    "sg:postcode":"2744",
    "sg:province":"Bern",
    "wof:name":"Walter Kropf Mar\u00e9chal",
    "wof:placetype":"venue"
},
  "geometry": {"coordinates":[7.4050998688,47.2823638916],"type":"Point"}
}