{
  "type": "Feature",
  "properties": {
    "iso:country":"CH",
    "sg:address":"Industriestrasse 4",
    "sg:city":"Maienfeld",
    "sg:orig_category":"Herstellung von Ger\u00e4ten der Elektrizit\u00e4tserzeugung, -verteilung u.\u00e4. -Herstellung von elektrischen L",
    "sg:phone":"+41 81 300 48 48",
    "sg:postcode":"7304",
    "sg:province":"Graubunden",
    "wof:name":"Eldur Ag Maienfeld",
    "wof:placetype":"venue"
},
  "geometry": {"coordinates":[9.5265827179,47.0027542114],"type":"Point"}
}