{
  "type": "Feature",
  "properties": {
    "iso:country":"CH",
    "sg:address":"7027",
    "sg:city":"Calfreisen",
    "sg:orig_category":"Landesverteidigung, Sozialversicherung \u00d6ffentliche Verwaltung",
    "sg:phone":"+41 81 252 79 12",
    "sg:postcode":"7027",
    "sg:province":"Graubunden",
    "wof:name":"Zivilschutzstelle Calfreisen",
    "wof:placetype":"venue"
},
  "geometry": {"coordinates":[9.5937423706,46.8413963318],"type":"Point"}
}