{
  "type": "Feature",
  "properties": {
    "iso:country":"CH",
    "sg:address":"Rue De Chantepoulet 1-3",
    "sg:city":"Gen\u00e8ve",
    "sg:classifiers":[
        {
            "category":"Banks & Credit Unions",
            "subcategory":"Atm",
            "type":"Services"
        }
    ],
    "sg:phone":"+41 22 732 05 60",
    "sg:postcode":"1201",
    "sg:province":"Gen\u00e8ve",
    "sg:tags":[
        "carrier",
        "airlines",
        "air-freight"
    ],
    "wof:name":"Air Mauritius",
    "wof:placetype":"venue"
},
  "geometry": {"coordinates":[6.145472,46.207935],"type":"Point"}
}