{
  "type": "Feature",
  "properties": {
    "iso:country":"CH",
    "sg:address":"Hummelweg 13 9244 Niederuzwil. Postfach",
    "sg:city":"Niederuzwil",
    "sg:orig_category":"Herstellung von Platten, Folien, Schl\u00e4uchen U Profilen aus Kunststoff",
    "sg:phone":"+41 71 951 94 02",
    "sg:postcode":"9244",
    "sg:province":"St. Gallen",
    "wof:name":"Cucchia Walter Nova-spritzwerk",
    "wof:placetype":"venue"
},
  "geometry": {"coordinates":[9.1455821991,47.4492111206],"type":"Point"}
}