{
  "type": "Feature",
  "properties": {
    "iso:country":"CH",
    "sg:address":"Edlischwil",
    "sg:city":"Waldkirch",
    "sg:orig_category":"Haltung von Gefl\u00fcgel",
    "sg:phone":"+41 71 433 21 33",
    "sg:postcode":"9205",
    "sg:province":"St. Gallen",
    "wof:name":"Elmar & Erna Gossner Gefl\u00fcgelfarm",
    "wof:placetype":"venue"
},
  "geometry": {"coordinates":[9.3056201935,47.4738502502],"type":"Point"}
}