{
  "type": "Feature",
  "properties": {
    "iso:country":"CH",
    "sg:address":"Altstetterstrasse 145",
    "sg:city":"Z\u00fcrich",
    "sg:orig_category":"Drogerien Fachdetailhandel mit pharmazeutischen Produkten",
    "sg:phone":"+41 31 311 14 81",
    "sg:postcode":"8048",
    "sg:province":"Z\u00fcrich",
    "wof:name":"Rathaus Apotheke Bern, Dr. S. Fritz Ag Rathaus-apotheke U. Drogerie",
    "wof:placetype":"venue"
},
  "geometry": {"coordinates":[7.4521198273,46.9481391907],"type":"Point"}
}