{
  "type": "Feature",
  "properties": {
    "iso:country":"CH",
    "sg:address":"Via Sonvico 17",
    "sg:city":"Canobbio",
    "sg:orig_category":"Instandhaltung U Reparatur von Automobilen",
    "sg:phone":"+41 91 935 05 60",
    "sg:postcode":"6952",
    "sg:province":"Ticino",
    "wof:name":"Amicar Sa",
    "wof:placetype":"venue"
},
  "geometry": {"coordinates":[8.970574379,46.0311851501],"type":"Point"}
}