{
  "type": "Feature",
  "properties": {
    "iso:country":"CH",
    "sg:address":"Alpenstrasse 15",
    "sg:city":"Lohn-ammannsegg",
    "sg:classifiers":[
        {
            "category":"Home & Garden",
            "subcategory":"Carpets & Floor Coverings",
            "type":"Retail Goods"
        }
    ],
    "sg:phone":"+41 32 677 14 91",
    "sg:postcode":"4573",
    "sg:province":"Solothurn",
    "sg:tags":[
        "impregnation"
    ],
    "wof:name":"Quintex Ag",
    "wof:placetype":"venue"
},
  "geometry": {"coordinates":[7.526193,47.172398],"type":"Point"}
}