{
  "type": "Feature",
  "properties": {
    "iso:country":"CH",
    "sg:address":"Corso San Gottardo 32",
    "sg:city":"Chiasso",
    "sg:orig_category":"Unclassifiable Establishments",
    "sg:postcode":"6830",
    "sg:province":"Ticino",
    "wof:name":"Merlinsparg Ag",
    "wof:placetype":"venue"
},
  "geometry": {"coordinates":[9.0298786163,45.8341331482],"type":"Point"}
}