{
  "type": "Feature",
  "properties": {
    "iso:country":"CH",
    "sg:address":"M\u00fchlenstrasse 56",
    "sg:city":"Schaffhausen",
    "sg:orig_category":"Hochschulen U h\u00f6here Ausbildung",
    "sg:phone":"+41 52 632 17 77",
    "sg:postcode":"8200",
    "sg:province":"Schaffhausen",
    "wof:name":"Neuland Schulung Training Beratung Gmbh",
    "wof:placetype":"venue"
},
  "geometry": {"coordinates":[8.627035141,47.69323349],"type":"Point"}
}