{
  "type": "Feature",
  "properties": {
    "iso:country":"CH",
    "sg:address":"Hauptstrasse 65 4107 Ettingen. Postfach",
    "sg:city":"Ettingen",
    "sg:orig_category":"Sonstige pers\u00f6nliche Dienstleistungen",
    "sg:postcode":"4107",
    "sg:province":"Basel-Landschaft",
    "wof:name":"Mandapro Ag Gesellschaftlich Sinnvolle Kommerzielle U. Nichtkommerzielle Aktivit\u00e4ten Usw",
    "wof:placetype":"venue"
},
  "geometry": {"coordinates":[7.5436358452,47.4787445068],"type":"Point"}
}