{
  "type": "Feature",
  "properties": {
    "iso:country":"CH",
    "sg:address":"Endorf",
    "sg:city":"Sigriswil",
    "sg:orig_category":"Detailhandel mit Waren verschiedener Art, Hauptrichtung Nahrungsmittel Verarbeitung von Milch",
    "sg:postcode":"3655",
    "sg:province":"Bern",
    "wof:name":"Milchgenossenschaft Endorf",
    "wof:placetype":"venue"
},
  "geometry": {"coordinates":[7.7218008041,46.7146720886],"type":"Point"}
}