{
  "type": "Feature",
  "properties": {
    "addr:full":"Langwisstrasse 5 Zumikon Z\u00fcrich 8126",
    "addr:housenumber":"5",
    "addr:postcode":"8126",
    "addr:street":"Langwisstrasse",
    "iso:country":"CH",
    "sg:address":"Langwisstrasse 5",
    "sg:city":"Zumikon",
    "sg:orig_category":"Architektur U Ingenieurb\u00fcros",
    "sg:phone":"+41 19180715",
    "sg:postcode":"8126",
    "sg:province":"Z\u00fcrich",
    "wof:name":"Dr.hans Schicht Ag Contamination Control Consult.",
    "wof:placetype":"venue"
},
  "geometry": {"coordinates":[8.633761,47.330605],"type":"Point"}
}