{
  "type": "Feature",
  "properties": {
    "iso:country":"CH",
    "sg:address":"Steinhaldenweg 24",
    "sg:city":"Romanshorn",
    "sg:orig_category":"Unternehmensberatung",
    "sg:phone":"+41 71 463 31 26",
    "sg:postcode":"8590",
    "sg:province":"Thurgau",
    "wof:name":"Kriesi Industrial Management And Engineering Services",
    "wof:placetype":"venue"
},
  "geometry": {"coordinates":[9.3726968765,47.573387146],"type":"Point"}
}