{
  "type": "Feature",
  "properties": {
    "iso:country":"CH",
    "sg:address":"Mittelstrasse 24 2560 Nidau. Postfach",
    "sg:city":"Nidau",
    "sg:orig_category":"Softwareentwicklung U beratung",
    "sg:postcode":"2560",
    "sg:province":"Bern",
    "wof:name":"Ontos Ag",
    "wof:placetype":"venue"
},
  "geometry": {"coordinates":[7.238158226,47.1252098083],"type":"Point"}
}