{
  "type": "Feature",
  "properties": {
    "iso:country":"CH",
    "sg:address":"Route De Suisse 36",
    "sg:city":"Versoix",
    "sg:orig_category":"Detailhandel mit elektrischen Haushalts-,Radio U Fernsehger\u00e4ten sowie Musikinstrumenten",
    "sg:phone":"+41 22 755 49 30",
    "sg:postcode":"1290",
    "sg:province":"Gen\u00e8ve",
    "wof:name":"Radio Des Nations, Cascallar Jos\u00e9 Manuel",
    "wof:placetype":"venue"
},
  "geometry": {"coordinates":[6.1692872047,46.2772064209],"type":"Point"}
}