{
  "type": "Feature",
  "properties": {
    "iso:country":"CH",
    "sg:address":"Strandbadweg 5",
    "sg:city":"Uster",
    "sg:orig_category":"Jugendorganisationen",
    "sg:postcode":"8610",
    "sg:province":"Z\u00fcrich",
    "wof:name":"Jugendriege Des Tv Uster",
    "wof:placetype":"venue"
},
  "geometry": {"coordinates":[8.6967353821,47.344707489],"type":"Point"}
}