{
  "type": "Feature",
  "properties": {
    "iso:country":"CH",
    "sg:address":"Gottardo Via San",
    "sg:city":"Gordola",
    "sg:orig_category":"Vermietung U Verpachtung von eigenen Immobilien",
    "sg:postcode":"6596",
    "sg:province":"Ticino",
    "wof:name":"Gidial Sa",
    "wof:placetype":"venue"
},
  "geometry": {"coordinates":[8.858505249,46.1816749573],"type":"Point"}
}