{
  "type": "Feature",
  "properties": {
    "iso:country":"CH",
    "sg:address":"R\u00fctistrasse 12 8952 Schlieren. Postfach",
    "sg:city":"Schlieren",
    "sg:orig_category":"Grosshandel mit Radio U Fernsehger\u00e4ten Herstellung von sonstigen elektrischen Ausr\u00fcstungen",
    "sg:phone":"+41 848 808 480",
    "sg:postcode":"8952",
    "sg:province":"Z\u00fcrich",
    "wof:name":"Sony Overseas Ag",
    "wof:placetype":"venue"
},
  "geometry": {"coordinates":[8.4489212036,47.400932312],"type":"Point"}
}