{
  "type": "Feature",
  "properties": {
    "iso:country":"CH",
    "sg:address":"Amriswiler Strasse 8",
    "sg:city":"Weinfelden",
    "sg:orig_category":"Fahrschulen, Flugschulen",
    "sg:phone":"+41 71 622 22 02",
    "sg:postcode":"8570",
    "sg:province":"Thurgau",
    "wof:name":"Urs Kolb Autofahrschule",
    "wof:placetype":"venue"
},
  "geometry": {"coordinates":[9.110370636,47.568069458],"type":"Point"}
}