{
  "type": "Feature",
  "properties": {
    "iso:country":"CH",
    "sg:address":"Chalet Le Pinson 3963 Crans-sur-sierre. Postfach",
    "sg:city":"Crans-sur-sierre",
    "sg:orig_category":"Vermietung U Verpachtung von eigenen Immobilien",
    "sg:postcode":"3963",
    "sg:province":"Valais",
    "wof:name":"Ehruppus Sa Biens Immobiliers Etc",
    "wof:placetype":"venue"
},
  "geometry": {"coordinates":[7.4734501839,46.3016090393],"type":"Point"}
}