{
  "type": "Feature",
  "properties": {
    "iso:country":"CH",
    "sg:address":"S\u00fcdstrasse 22 6010 Kriens. Postfach",
    "sg:city":"Kriens",
    "sg:orig_category":"Sonstiger Grosshandel",
    "sg:phone":"+41 41 302 56 24",
    "sg:postcode":"6010",
    "sg:province":"Luzern",
    "wof:name":"Sisal By Cocchiarella Waren; Handel, Import, Export Usw",
    "wof:placetype":"venue"
},
  "geometry": {"coordinates":[8.2674942017,47.0331382751],"type":"Point"}
}