{
  "type": "Feature",
  "properties": {
    "iso:country":"CH",
    "sg:address":"Dr.joachim Heer-strasse 1 8750 Glarus. Postfach 331",
    "sg:city":"Glarus",
    "sg:orig_category":"K\u00fcnstlerische Schulen",
    "sg:phone":"+41 71 222 31 08",
    "sg:postcode":"8750",
    "sg:province":"Glarus",
    "wof:name":"Guido Minicus Musikschule",
    "wof:placetype":"venue"
},
  "geometry": {"coordinates":[9.3681602478,47.423664093],"type":"Point"}
}