{
  "type": "Feature",
  "properties": {
    "iso:country":"CH",
    "sg:address":"Wildensteinerstrasse 21 4132 Muttenz. Postfach",
    "sg:city":"Muttenz",
    "sg:orig_category":"Sonstiger Grosshandel",
    "sg:postcode":"4132",
    "sg:province":"Basel-Landschaft",
    "wof:name":"Niwag Handelsagentur Nickel + Wagner",
    "wof:placetype":"venue"
},
  "geometry": {"coordinates":[7.6575517654,47.5289077759],"type":"Point"}
}