{
  "type": "Feature",
  "properties": {
    "iso:country":"CH",
    "sg:address":"Hammerstrasse 114",
    "sg:city":"Basel",
    "sg:orig_category":"Detailhandel mit Waren verschiedener Art, Hauptrichtung Nahrungsmittel Fachdetailhandel mit Nahrungs",
    "sg:phone":"+41 19326300",
    "sg:postcode":"4057",
    "sg:province":"Basel-Stadt",
    "wof:name":"La Mediterranea Hs Gmbh Italienische Spezialit\u00e4ten",
    "wof:placetype":"venue"
},
  "geometry": {"coordinates":[8.7931146622,47.3196983337],"type":"Point"}
}