{
  "type": "Feature",
  "properties": {
    "iso:country":"CH",
    "sg:address":"Schmidtenbaumgarten 27 8917 Oberlunkhofen. Postfach",
    "sg:city":"Oberlunkhofen",
    "sg:orig_category":"Maschinen-Fabrikation",
    "sg:postcode":"8917",
    "sg:province":"Aargau",
    "wof:name":"Ponca Engineering",
    "wof:placetype":"venue"
},
  "geometry": {"coordinates":[8.3869953156,47.3141860962],"type":"Point"}
}