{
  "type": "Feature",
  "properties": {
    "iso:country":"CH",
    "sg:address":"Poststrasse 19 2500 Biel/bienne. Postfach",
    "sg:city":"Biel/bienne",
    "sg:orig_category":"W\u00e4scherei U chemische Reinigung",
    "sg:phone":"+41 79 408 75 46",
    "sg:postcode":"2504",
    "sg:province":"Bern",
    "wof:name":"Rideaux Entretien, G. Angeloni",
    "wof:placetype":"venue"
},
  "geometry": {"coordinates":[6.1407799721,46.1872215271],"type":"Point"}
}