{
  "type": "Feature",
  "properties": {
    "addr:full":"Hauptstrasse 90 Pratteln Basel-Landschaft 4133",
    "addr:housenumber":"90",
    "addr:postcode":"4133",
    "addr:street":"Hauptstrasse",
    "iso:country":"CH",
    "sg:address":"Hauptstrasse 90",
    "sg:city":"Pratteln",
    "sg:orig_category":"Architektur U Ingenieurb\u00fcros Architekturb\u00fcros",
    "sg:phone":"+41 26 672 93 50",
    "sg:postcode":"4133",
    "sg:province":"Basel-Landschaft",
    "wof:name":"Bd Architekten Ag",
    "wof:placetype":"venue"
},
  "geometry": {"coordinates":[7.108453,46.925232],"type":"Point"}
}