{
  "type": "Feature",
  "properties": {
    "iso:country":"CH",
    "sg:address":"Rue Crespin 16",
    "sg:city":"Gen\u00e8ve",
    "sg:orig_category":"Detailhandel mit Getr\u00e4nken Grosshandel mit Getr\u00e4nken",
    "sg:phone":"+41 22 346 01 42",
    "sg:postcode":"1206",
    "sg:province":"Gen\u00e8ve",
    "wof:name":"Jean-roger Egger",
    "wof:placetype":"venue"
},
  "geometry": {"coordinates":[6.1596927643,46.1947059631],"type":"Point"}
}