{
  "type": "Feature",
  "properties": {
    "iso:country":"CH",
    "sg:address":"Kirchgasse",
    "sg:city":"Wilderswil",
    "sg:orig_category":"Detailhandel mit Geschenkartikeln U Souvenirs",
    "sg:phone":"+41 71 333 36 52",
    "sg:postcode":"3812",
    "sg:province":"Bern",
    "wof:name":"Margrit Brunnschweiler Boutique Fema",
    "wof:placetype":"venue"
},
  "geometry": {"coordinates":[9.3893995285,47.3909683228],"type":"Point"}
}