{
  "type": "Feature",
  "properties": {
    "iso:country":"CH",
    "sg:address":"Rue Des Vignettes",
    "sg:city":"Ardon",
    "sg:orig_category":"Rebbau",
    "sg:phone":"+41 27 305 15 31",
    "sg:postcode":"1957",
    "sg:province":"Valais",
    "wof:name":"Maison Les Vignettes Alex & Yves Deleloye",
    "wof:placetype":"venue"
},
  "geometry": {"coordinates":[7.2523207664,46.2085571289],"type":"Point"}
}