{
  "type": "Feature",
  "properties": {
    "iso:country":"CH",
    "sg:address":"Terracestrasse 33 6390 Engelberg. Postfach 88",
    "sg:city":"Engelberg",
    "sg:classifiers":[
        {
            "category":"Travel",
            "subcategory":"Hotels & Motels",
            "type":"Entertainment"
        }
    ],
    "sg:phone":"+41 41 639 66 66",
    "sg:postcode":"6391",
    "sg:province":"Obwalden",
    "sg:tags":[
        "hotels",
        "mit",
        "restaurant"
    ],
    "wof:name":"Hotel Terrace",
    "wof:placetype":"venue"
},
  "geometry": {"coordinates":[8.4012346268,46.8230705261],"type":"Point"}
}