{
  "type": "Feature",
  "properties": {
    "iso:country":"CH",
    "sg:address":"Industriestrasse 31 8305 Dietlikon. Postfach",
    "sg:city":"Volketswil",
    "sg:orig_category":"Herstellung von sonstigen Maschinen f\u00fcr unspezifische Verwendung",
    "sg:phone":"+41 56 622 90 21",
    "sg:postcode":"8604",
    "sg:province":"Z\u00fcrich",
    "wof:name":"Blum Erwin",
    "wof:placetype":"venue"
},
  "geometry": {"coordinates":[8.2697610855,47.3465919495],"type":"Point"}
}