{
  "type": "Feature",
  "properties": {
    "iso:country":"CH",
    "sg:address":"Z\u00fcrcherstrasse 142",
    "sg:city":"Basel",
    "sg:orig_category":"Instandhaltung U Reparatur von Automobilen",
    "sg:phone":"+41 61 311 50 60",
    "sg:postcode":"4052",
    "sg:province":"Basel-Stadt",
    "wof:name":"Agence Alban Ag",
    "wof:placetype":"venue"
},
  "geometry": {"coordinates":[7.6129350662,47.5550918579],"type":"Point"}
}