{
  "type": "Feature",
  "properties": {
    "iso:country":"CH",
    "sg:address":"Stationsstrasse 30",
    "sg:city":"Uttigen",
    "sg:orig_category":"Mechanik Mechanische Werkst\u00e4tten",
    "sg:phone":"+41 33 345 42 32",
    "sg:postcode":"3628",
    "sg:province":"Bern",
    "wof:name":"Rothen Anton",
    "wof:placetype":"venue"
},
  "geometry": {"coordinates":[7.5799517632,46.7942581177],"type":"Point"}
}