{
  "type": "Feature",
  "properties": {
    "iso:country":"CH",
    "sg:address":"Les Prys",
    "sg:city":"Albeuve",
    "sg:orig_category":"Bauschreinerei Herstellung von Konstruktionsteilen, Fertigbauteilen U Ausbauelementen aus Holz",
    "sg:phone":"+41 26 928 17 86",
    "sg:postcode":"1669",
    "sg:province":"Fribourg",
    "wof:name":"Jolliet Christian.",
    "wof:placetype":"venue"
},
  "geometry": {"coordinates":[7.05515,46.519115],"type":"Point"}
}