{
  "type": "Feature",
  "properties": {
    "iso:country":"CH",
    "sg:address":"Feldeggstrasse 7",
    "sg:city":"Utzenstorf",
    "sg:orig_category":"Erbringung von Dienstleistungen f\u00fcr Unternehmen Erbringung von sonstigen Dienstleistungen f\u00fcr Untern",
    "sg:phone":"+41 32 665 14 44",
    "sg:postcode":"3427",
    "sg:province":"Bern",
    "wof:name":"Urs Habegger Modell-& Formenbau",
    "wof:placetype":"venue"
},
  "geometry": {"coordinates":[7.5582551956,47.1316795349],"type":"Point"}
}