{
  "type": "Feature",
  "properties": {
    "iso:country":"CH",
    "sg:address":"Grosstannen",
    "sg:city":"Eggiwil",
    "sg:orig_category":"Landw. Genossenschaften Dresch",
    "sg:phone":"+41 34 491 16 65",
    "sg:postcode":"3537",
    "sg:province":"Bern",
    "wof:name":"Fritz Gasser Drescherei",
    "wof:placetype":"venue"
},
  "geometry": {"coordinates":[7.8148012161,46.8754463196],"type":"Point"}
}