{
  "type": "Feature",
  "properties": {
    "addr:full":"Dorfstrasse 53 Kloten Z\u00fcrich 8302",
    "addr:housenumber":"53",
    "addr:postcode":"8302",
    "addr:street":"Dorfstrasse",
    "iso:country":"CH",
    "sg:address":"Dorfstrasse 53",
    "sg:city":"Kloten",
    "sg:orig_category":"Bauschreinerei",
    "sg:phone":"+41 18133122",
    "sg:postcode":"8302",
    "sg:province":"Z\u00fcrich",
    "wof:name":"Peter Hegetschweiler Schreinerei",
    "wof:placetype":"venue"
},
  "geometry": {"coordinates":[8.588382,47.452057],"type":"Point"}
}