{
  "type": "Feature",
  "properties": {
    "iso:country":"CH",
    "sg:address":"Z\u00fcrcher Strasse 118",
    "sg:city":"St.gallen",
    "sg:orig_category":"RESTAURANTS: TEA-ROOMS",
    "sg:phone":"+41 71 277 71 27",
    "sg:postcode":"9000",
    "sg:province":"St. Gallen",
    "wof:name":"Barbarossa Zurcherstrasse Spaghetteria",
    "wof:placetype":"venue"
},
  "geometry": {"coordinates":[9.3447084427,47.4161605835],"type":"Point"}
}