{
  "type": "Feature",
  "properties": {
    "iso:country":"CH",
    "sg:address":"Limmattalstrasse 222",
    "sg:city":"Z\u00fcrich",
    "sg:orig_category":"Bijouterien Reparatur von Uhren U Schmuck",
    "sg:postcode":"8049",
    "sg:province":"Z\u00fcrich",
    "wof:name":"Nussio Gmbh Uhren & Bijouterie",
    "wof:placetype":"venue"
},
  "geometry": {"coordinates":[7.245361,46.853607],"type":"Point"}
}