{
  "type": "Feature",
  "properties": {
    "addr:full":"Route De La Gl\u00e2ne 121 Villars-sur-gl\u00e2ne Fribourg 1752",
    "addr:housenumber":"121",
    "addr:postcode":"1752",
    "addr:street":"Route De La Gla\u0302Ne",
    "iso:country":"CH",
    "sg:address":"Route De La Gl\u00e2ne 121",
    "sg:city":"Villars-sur-gl\u00e2ne",
    "sg:orig_category":"Architektur U Ingenieurb\u00fcros",
    "sg:postcode":"1752",
    "sg:province":"Fribourg",
    "wof:name":"Bureau D'architectes Baechler Y Et Pasquier F. Sa",
    "wof:placetype":"venue"
},
  "geometry": {"coordinates":[7.14016,46.79071],"type":"Point"}
}