{
  "type": "Feature",
  "properties": {
    "iso:country":"CH",
    "sg:address":"Promenade Des P\u00eacheurs 54",
    "sg:city":"Sion",
    "sg:classifiers":[
        {
            "category":"Restaurant",
            "type":"Food & Drink"
        }
    ],
    "sg:phone":"+41 27 203 41 98",
    "sg:postcode":"1950",
    "sg:province":"Valais",
    "wof:name":"Restaurant Paladin",
    "wof:placetype":"venue"
},
  "geometry": {"coordinates":[7.3751392365,46.2348022461],"type":"Point"}
}