{
  "type": "Feature",
  "properties": {
    "iso:country":"CH",
    "sg:address":"Buttes Rue De 18 2114 Fleurier. Postfach",
    "sg:city":"Fleurier",
    "sg:orig_category":"Stukkateurgewerbe, Gipserei U Verputzerei",
    "sg:postcode":"2114",
    "sg:province":"Neuch\u00e2tel",
    "wof:name":"Semedo Barreto Antonio, Pl\u00e2trerie Et Peinture",
    "wof:placetype":"venue"
},
  "geometry": {"coordinates":[6.576444149,46.8989868164],"type":"Point"}
}