{
  "type": "Feature",
  "properties": {
    "iso:country":"CH",
    "sg:address":"Appenberg Zentrum",
    "sg:city":"Mirchel",
    "sg:orig_category":"Vereine Trachten",
    "sg:postcode":"3532",
    "sg:province":"Bern",
    "wof:name":"Trachtegruppe Appeb\u00e4rg",
    "wof:placetype":"venue"
},
  "geometry": {"coordinates":[7.6595101357,46.8833618164],"type":"Point"}
}