{
  "type": "Feature",
  "properties": {
    "iso:country":"CH",
    "sg:address":"3555",
    "sg:city":"Trubschachen",
    "sg:orig_category":"Sportvereine Sch\u00fctzen",
    "sg:phone":"+41 32 373 60 11",
    "sg:postcode":"3555",
    "sg:province":"Bern",
    "wof:name":"Sch\u00fctzengesellschaft Br\u00fcgg",
    "wof:placetype":"venue"
},
  "geometry": {"coordinates":[7.2653207779,47.1244239807],"type":"Point"}
}