{
  "type": "Feature",
  "properties": {
    "iso:country":"CH",
    "sg:address":"Rue Edouard-rod 24",
    "sg:city":"Gen\u00e8ve",
    "sg:orig_category":"Instandhaltung U Reparatur von Automobilen",
    "sg:phone":"+41 22 345 94 30",
    "sg:postcode":"1203",
    "sg:province":"Gen\u00e8ve",
    "wof:name":"Garage As Gmbh Neu- U. Gebrauchtwagen; Handel",
    "wof:placetype":"venue"
},
  "geometry": {"coordinates":[6.1235589981,46.2142448425],"type":"Point"}
}