{
  "type": "Feature",
  "properties": {
    "iso:country":"CH",
    "sg:address":"Moosstrasse 2 3073 G\u00fcmligen. Postfach",
    "sg:city":"G\u00fcmligen",
    "sg:orig_category":"Architektur U Ingenieurb\u00fcros",
    "sg:phone":"+41 31 958 48 48",
    "sg:postcode":"3073",
    "sg:province":"Bern",
    "wof:name":"Binder Peter Ag",
    "wof:placetype":"venue"
},
  "geometry": {"coordinates":[7.504954,46.932652],"type":"Point"}
}