{
  "type": "Feature",
  "properties": {
    "iso:country":"CH",
    "sg:address":"Hauptstr. 9",
    "sg:city":"Hubersdorf",
    "sg:orig_category":"RESTAURANTS: TEA-ROOMS",
    "sg:phone":"+41 81 833 33 55",
    "sg:postcode":"4535",
    "sg:province":"Solothurn",
    "wof:name":"Zuber Peter",
    "wof:placetype":"venue"
},
  "geometry": {"coordinates":[9.8306560516,46.5009880066],"type":"Point"}
}