{
  "type": "Feature",
  "properties": {
    "iso:country":"CH",
    "sg:address":"Hauptstrasse",
    "sg:city":"Altwis",
    "sg:orig_category":"Detailhandel mit Fleisch U Fleischwaren",
    "sg:phone":"+41 41 670 12 05",
    "sg:postcode":"6286",
    "sg:province":"Luzern",
    "wof:name":"Paul Wirz Metzgerei",
    "wof:placetype":"venue"
},
  "geometry": {"coordinates":[8.2710447311,46.9413337708],"type":"Point"}
}