{
  "type": "Feature",
  "properties": {
    "iso:country":"CH",
    "sg:address":"Rue De Neuch\u00e2tel 3 1400 Yverdon-les-bains. Postfach",
    "sg:city":"Yverdon",
    "sg:orig_category":"Versicherungen Generalagenturen",
    "sg:phone":"+41 21 802 35 35",
    "sg:postcode":"1401",
    "sg:province":"Vaud",
    "wof:name":"Winterthur Assurances Agence G\u00e9n\u00e9rale",
    "wof:placetype":"venue"
},
  "geometry": {"coordinates":[6.4983768463,46.5080680847],"type":"Point"}
}