{
  "type": "Feature",
  "properties": {
    "iso:country":"CH",
    "sg:address":"Colombara Via 33",
    "sg:city":"Ligornetto",
    "sg:orig_category":"G\u00fcterbef\u00f6rderung im Strassenverkehr",
    "sg:postcode":"6853",
    "sg:province":"Ticino",
    "wof:name":"Hp Distribution, Philippe H\u00e4nni",
    "wof:placetype":"venue"
},
  "geometry": {"coordinates":[6.8366498947,47.1124763489],"type":"Point"}
}