{
  "type": "Feature",
  "properties": {
    "iso:country":"CH",
    "sg:address":"Unterer Waldbachweg 3",
    "sg:city":"Melchnau",
    "sg:orig_category":"Sportvereine Velo Rad-& Motorfahrer-Bund SRB",
    "sg:phone":"+41 62 927 14 20",
    "sg:postcode":"4917",
    "sg:province":"Bern",
    "wof:name":"Arbeiter-radfahrer-verein Hochwacht",
    "wof:placetype":"venue"
},
  "geometry": {"coordinates":[7.8504171371,47.1906776428],"type":"Point"}
}