{
  "type": "Feature",
  "properties": {
    "iso:country":"CH",
    "sg:address":"Ch. De Champrilly 18. 1000 Lausanne. Postfach",
    "sg:city":"Lausanne",
    "sg:orig_category":"Erbringung von Dienstleistungen f\u00fcr Unternehmen",
    "sg:postcode":"1000",
    "sg:province":"Vaud",
    "wof:name":"Pittet Raoul.",
    "wof:placetype":"venue"
},
  "geometry": {"coordinates":[6.6081461906,46.5313148499],"type":"Point"}
}