{
  "type": "Feature",
  "properties": {
    "iso:country":"CH",
    "sg:address":"M\u00f6sliweg",
    "sg:city":"Biel/bienne",
    "sg:orig_category":"Detailhandel mit B\u00fcchern, Zeitungen, Schreib U Papeteriewaren Detailhandel mit Zeitungen U Zeitschri",
    "sg:phone":"+41 32 365 05 64",
    "sg:postcode":"2503",
    "sg:province":"Bern",
    "wof:name":"Christine Barmaverain Kiosk",
    "wof:placetype":"venue"
},
  "geometry": {"coordinates":[7.263365,47.129292],"type":"Point"}
}