{
  "type": "Feature",
  "properties": {
    "iso:country":"CH",
    "sg:address":"Hallerstrasse 6/8",
    "sg:city":"Bern",
    "sg:orig_category":"Allgemeinbildende weiterf\u00fchrende Schulen",
    "sg:postcode":"3012",
    "sg:province":"Bern",
    "wof:name":"World Trade Institute Foundation",
    "wof:placetype":"venue"
},
  "geometry": {"coordinates":[7.435012,46.952145],"type":"Point"}
}