{
  "type": "Feature",
  "properties": {
    "iso:country":"CH",
    "sg:address":"Rainstrasse 20 8309 N\u00fcrensdorf. Postfach",
    "sg:city":"N\u00fcrensdorf",
    "sg:orig_category":"Public-Relations-Agenturen Sonstige pers\u00f6nliche Dienstleistungen",
    "sg:postcode":"8309",
    "sg:province":"Z\u00fcrich",
    "wof:name":"Isler Gmbh Beratungen Und Dienstleistungen",
    "wof:placetype":"venue"
},
  "geometry": {"coordinates":[8.6373243332,47.4624443054],"type":"Point"}
}