{
  "type": "Feature",
  "properties": {
    "iso:country":"CH",
    "sg:address":"Br\u00fchlstrasse 51 2500 Biel/bienne. Postfach",
    "sg:city":"Biel/bienne",
    "sg:orig_category":"Unternehmensberatung",
    "sg:postcode":"2503",
    "sg:province":"Bern",
    "wof:name":"Graber, Management & Trust",
    "wof:placetype":"venue"
},
  "geometry": {"coordinates":[7.2561421394,47.1366195679],"type":"Point"}
}