{
  "type": "Feature",
  "properties": {
    "iso:country":"CH",
    "sg:address":"Nassa Via 11",
    "sg:city":"Lugano",
    "sg:orig_category":"Unclassifiable Establishments",
    "sg:phone":"+41 91 911 03 40",
    "sg:postcode":"6900",
    "sg:province":"Ticino",
    "wof:name":"Bipielle International Holding Sa Partecipazione Ecc",
    "wof:placetype":"venue"
},
  "geometry": {"coordinates":[8.9499826431,46.0024528503],"type":"Point"}
}