{
  "type": "Feature",
  "properties": {
    "iso:country":"CH",
    "sg:address":"Dorfstrasse 21 6390 Engelberg. Postfach",
    "sg:city":"Engelberg",
    "sg:orig_category":"Non-Classified Establishments",
    "sg:postcode":"6390",
    "sg:province":"Obwalden",
    "wof:name":"Manix Gmbh",
    "wof:placetype":"venue"
},
  "geometry": {"coordinates":[8.4054889679,46.8211936951],"type":"Point"}
}