{
  "type": "Feature",
  "properties": {
    "iso:country":"CH",
    "sg:address":"Corso Elvezia 1",
    "sg:city":"Lugano",
    "sg:orig_category":"Detailhandel mit Brillen U anderen Sehhilfen",
    "sg:phone":"+41 31 331 70 80",
    "sg:postcode":"6900",
    "sg:province":"Ticino",
    "wof:name":"Eschmann Augenoptik Ag Augenoptiker. Brillen, Kontaktlinsen Usw; Handel",
    "wof:placetype":"venue"
},
  "geometry": {"coordinates":[7.454192,46.960556],"type":"Point"}
}