{
  "type": "Feature",
  "properties": {
    "iso:country":"CH",
    "sg:address":"Via Cantonale 19 6900 Lugano. Postfach",
    "sg:city":"Lugano",
    "sg:orig_category":"Herstellung von Elektromotoren, Generatoren U Transformatoren",
    "sg:postcode":"6900",
    "sg:province":"Ticino",
    "wof:name":"Cete Sa, Lussemburgo, Succursale Di Lugano",
    "wof:placetype":"venue"
},
  "geometry": {"coordinates":[8.9502239227,46.0093307495],"type":"Point"}
}