{
  "type": "Feature",
  "properties": {
    "iso:country":"CH",
    "sg:address":"Bachstrasse 14",
    "sg:city":"Schaffhausen",
    "sg:orig_category":"Kauf U Verkauf von Immobilien auf eigene Rechnung",
    "sg:phone":"+41 52 672 45 05",
    "sg:postcode":"8200",
    "sg:province":"Schaffhausen",
    "wof:name":"Mbk-anlagen Ag",
    "wof:placetype":"venue"
},
  "geometry": {"coordinates":[8.6383256912,47.6961708069],"type":"Point"}
}