{
  "type": "Feature",
  "properties": {
    "iso:country":"CH",
    "sg:address":"Bireggring 14 6000 Luzern. Postfach",
    "sg:city":"Luzern",
    "sg:orig_category":"Non-Classified Establishments",
    "sg:postcode":"6003",
    "sg:province":"Luzern",
    "wof:name":"Pathworks Gmbh",
    "wof:placetype":"venue"
},
  "geometry": {"coordinates":[8.3048143387,47.0421066284],"type":"Point"}
}