{
  "type": "Feature",
  "properties": {
    "iso:country":"CH",
    "sg:address":"Industriering 7a 3250 Lyss. Postfach",
    "sg:city":"Lyss",
    "sg:orig_category":"Herstellung von Radio U Fernsehger\u00e4ten sowie phono U videotechnischen Ger\u00e4ten",
    "sg:postcode":"3250",
    "sg:province":"Bern",
    "wof:name":"Rainbow Music Lyss Gmbh",
    "wof:placetype":"venue"
},
  "geometry": {"coordinates":[7.3059601784,47.0857582092],"type":"Point"}
}