{
  "type": "Feature",
  "properties": {
    "iso:country":"CH",
    "sg:address":"Bahnhofstrasse 7",
    "sg:city":"Zug",
    "sg:orig_category":"Herstellung von sonstigen elektrischen Ausr\u00fcstungen",
    "sg:phone":"+41 62 398 00 74",
    "sg:postcode":"6300",
    "sg:province":"Zug",
    "wof:name":"Alpine-invent Gmbh",
    "wof:placetype":"venue"
},
  "geometry": {"coordinates":[8.5155220032,47.168586731],"type":"Point"}
}