{
  "type": "Feature",
  "properties": {
    "iso:country":"CH",
    "sg:address":"Stapfenstrasse 13",
    "sg:city":"K\u00f6niz",
    "sg:orig_category":"Sonstige Institutionen des Sozialwesens ohne Beherbergung",
    "sg:phone":"+41 31 970 94 14",
    "sg:postcode":"3098",
    "sg:province":"Bern",
    "wof:name":"Beratungsstelle F\u00fcr Suchtfragen",
    "wof:placetype":"venue"
},
  "geometry": {"coordinates":[7.4159760475,46.9225769043],"type":"Point"}
}