{
  "type": "Feature",
  "properties": {
    "iso:country":"CH",
    "sg:address":"Klosbachstrasse 72",
    "sg:city":"Z\u00fcrich",
    "sg:orig_category":"Unclassifiable Establishments",
    "sg:postcode":"8032",
    "sg:province":"Z\u00fcrich",
    "wof:name":"Jean-luc Grossmann Photographie",
    "wof:placetype":"venue"
},
  "geometry": {"coordinates":[8.5592365265,47.3670310974],"type":"Point"}
}