{
  "type": "Feature",
  "properties": {
    "addr:full":"Chemin Du Ch\u00e2teau 8 Broc Fribourg 1636",
    "addr:housenumber":"8",
    "addr:postcode":"1636",
    "addr:street":"Chemin Du Cha\u0302Teau",
    "iso:country":"CH",
    "sg:address":"Chemin Du Ch\u00e2teau 8",
    "sg:city":"Broc",
    "sg:orig_category":"Bauspenglerei Dachdeckerei",
    "sg:phone":"+41 79 634 28 40",
    "sg:postcode":"1636",
    "sg:province":"Fribourg",
    "wof:name":"Marc Tercier Ferblanterie & Couverture",
    "wof:placetype":"venue"
},
  "geometry": {"coordinates":[7.103082,46.599625],"type":"Point"}
}