{
  "type": "Feature",
  "properties": {
    "iso:country":"CH",
    "sg:address":"Gemeindeplatz 1",
    "sg:city":"Oberdiessbach",
    "sg:orig_category":"Gemeindeverwaltungen",
    "sg:phone":"+41 61 961 01 33",
    "sg:postcode":"3672",
    "sg:province":"Bern",
    "wof:name":"Gemeindeverwaltung Oberdorf",
    "wof:placetype":"venue"
},
  "geometry": {"coordinates":[7.751595974,47.3937263489],"type":"Point"}
}