{
  "type": "Feature",
  "properties": {
    "iso:country":"CH",
    "sg:address":"Via C. Cattaneo 5",
    "sg:city":"Chiasso",
    "sg:orig_category":"Non-Classified Establishments",
    "sg:postcode":"6830",
    "sg:province":"Ticino",
    "wof:name":"Simedia Sagl",
    "wof:placetype":"venue"
},
  "geometry": {"coordinates":[9.0263547897,45.8312416077],"type":"Point"}
}