{
  "type": "Feature",
  "properties": {
    "iso:country":"CH",
    "sg:address":"Westerholz 5 2500 Biel/bienne. Postfach",
    "sg:city":"Biel/bienne",
    "sg:orig_category":"Herstellung von industriellen Prozesssteuerungsanlagen",
    "sg:postcode":"2504",
    "sg:province":"Bern",
    "wof:name":"Rasel Elektronik J. R\u00e4ber",
    "wof:placetype":"venue"
},
  "geometry": {"coordinates":[7.272028923,47.1505661011],"type":"Point"}
}