{
  "type": "Feature",
  "properties": {
    "iso:country":"CH",
    "sg:address":"Dorfstrasse 17",
    "sg:city":"Fulenbach",
    "sg:orig_category":"Detailhandel mit Fleisch U Fleischwaren",
    "sg:postcode":"4629",
    "sg:province":"Solothurn",
    "wof:name":"Metzgerei Keller",
    "wof:placetype":"venue"
},
  "geometry": {"coordinates":[7.8338670731,47.2751731873],"type":"Point"}
}