{
  "type": "Feature",
  "properties": {
    "addr:full":"1925 Finhaut Valais 1925",
    "addr:postcode":"1925;1925",
    "iso:country":"CH",
    "sg:address":"1925",
    "sg:city":"Finhaut",
    "sg:orig_category":"Betrieb von Taxis",
    "sg:postcode":"1925",
    "sg:province":"Valais",
    "wof:name":"Fioretti Giorgio",
    "wof:placetype":"venue"
},
  "geometry": {"coordinates":[6.11967,46.23164],"type":"Point"}
}