{
  "type": "Feature",
  "properties": {
    "addr:full":"M\u00fchlemattstrasse 57 Bern Bern 3007",
    "addr:housenumber":"57",
    "addr:postcode":"3007",
    "addr:street":"Muehlemattstrasse",
    "iso:country":"CH",
    "sg:address":"M\u00fchlemattstrasse 57",
    "sg:city":"Bern",
    "sg:orig_category":"Detailhandel mit Fleisch U Fleischwaren",
    "sg:phone":"+41 31 378 45 45",
    "sg:postcode":"3007",
    "sg:province":"Bern",
    "wof:name":"M\u00e9rat & Cie Ag Metzgerei",
    "wof:placetype":"venue"
},
  "geometry": {"coordinates":[7.431966,46.94162],"type":"Point"}
}