{
  "type": "Feature",
  "properties": {
    "iso:country":"CH",
    "sg:address":"Lengnaustrasse 11",
    "sg:city":"Grenchen",
    "sg:orig_category":"Elektroinstallation",
    "sg:phone":"+41 32 652 17 36",
    "sg:postcode":"2540",
    "sg:province":"Solothurn",
    "wof:name":"Pfister Ernst + Co. Ag",
    "wof:placetype":"venue"
},
  "geometry": {"coordinates":[7.3820528984,47.1857795715],"type":"Point"}
}