{
  "type": "Feature",
  "properties": {
    "iso:country":"CH",
    "sg:address":"Buzibachstrasse 33",
    "sg:city":"Rothenburg",
    "sg:orig_category":"Maler U Glasergewerbe Tapeziererei",
    "sg:phone":"+41 41 280 30 30",
    "sg:postcode":"6023",
    "sg:province":"Luzern",
    "wof:name":"Maler Lipp Ag",
    "wof:placetype":"venue"
},
  "geometry": {"coordinates":[8.2566518784,47.0911369324],"type":"Point"}
}