{
  "type": "Feature",
  "properties": {
    "iso:country":"CH",
    "sg:address":"Geissburgstrasse 12a 6130 Willisau. Postfach",
    "sg:city":"Willisau",
    "sg:orig_category":"Maler U Glasergewerbe",
    "sg:postcode":"6130",
    "sg:province":"Luzern",
    "wof:name":"Maler Contrino",
    "wof:placetype":"venue"
},
  "geometry": {"coordinates":[7.9859662056,47.116973877],"type":"Point"}
}