{
  "type": "Feature",
  "properties": {
    "iso:country":"CH",
    "sg:address":"Derri\u00e8re-ville",
    "sg:city":"Buttes",
    "sg:orig_category":"Sonstiger spezialisierter Hoch U Tiefbau",
    "sg:phone":"+41 32 861 32 44",
    "sg:postcode":"2115",
    "sg:province":"Neuch\u00e2tel",
    "wof:name":"Arcolaci Salvatore",
    "wof:placetype":"venue"
},
  "geometry": {"coordinates":[6.5512890816,46.8871002197],"type":"Point"}
}