{
  "type": "Feature",
  "properties": {
    "iso:country":"CH",
    "sg:address":"R\u00f6merstrasse 8 4512 Bellach. Postfach 632",
    "sg:city":"Bellach",
    "sg:orig_category":"Autogaragen Lastwagen and Nutzfahrzeuge",
    "sg:phone":"+41 32 617 44 44",
    "sg:postcode":"4512",
    "sg:province":"Solothurn",
    "wof:name":"Werkhof-garage Ag",
    "wof:placetype":"venue"
},
  "geometry": {"coordinates":[7.507802,47.212399],"type":"Point"}
}