{
  "type": "Feature",
  "properties": {
    "iso:country":"CH",
    "sg:address":"La Cond\u00e9mine",
    "sg:city":"Attalens",
    "sg:orig_category":"RESTAURANTS: TEA-ROOMS",
    "sg:postcode":"1616",
    "sg:province":"Fribourg",
    "wof:name":"Vieira Ribeiro De Lemos Jorge",
    "wof:placetype":"venue"
},
  "geometry": {"coordinates":[6.8493890762,46.5091896057],"type":"Point"}
}