{
  "type": "Feature",
  "properties": {
    "iso:country":"CH",
    "sg:address":"Paddock De Five",
    "sg:city":"St-saphorin-morges",
    "sg:orig_category":"Verlagsgewerbe Werbung",
    "sg:phone":"+41 21 801 11 20",
    "sg:postcode":"1113",
    "sg:province":"Vaud",
    "wof:name":"Agence De Publicit\u00e9 Et D'edition Neumann M. Et R. Savar\u00e8 Succ.",
    "wof:placetype":"venue"
},
  "geometry": {"coordinates":[6.4868998528,46.5460166931],"type":"Point"}
}