{
  "type": "Feature",
  "properties": {
    "iso:country":"CH",
    "sg:address":"M\u00fchle 18",
    "sg:city":"Scherz",
    "sg:orig_category":"Mahl U Sch\u00e4lm\u00fchlen",
    "sg:phone":"+41 71 385 33 11",
    "sg:postcode":"5246",
    "sg:province":"Aargau",
    "wof:name":"Haslenm\u00fchle Aushilfsb\u00e4ckerei Gossau Ag",
    "wof:placetype":"venue"
},
  "geometry": {"coordinates":[9.2450656891,47.4150619507],"type":"Point"}
}