{
  "type": "Feature",
  "properties": {
    "iso:country":"CH",
    "sg:address":"Nordstrasse 38 8006 Z\u00fcrich. Postfach",
    "sg:city":"Z\u00fcrich",
    "sg:orig_category":"Detailhandel mit elektrischen Haushalts-,Radio U Fernsehger\u00e4ten sowie Musikinstrumenten",
    "sg:postcode":"8001",
    "sg:province":"Z\u00fcrich",
    "wof:name":"Heeb Roman, Haushaltapparate",
    "wof:placetype":"venue"
},
  "geometry": {"coordinates":[9.5730075836,47.3220176697],"type":"Point"}
}