{
  "type": "Feature",
  "properties": {
    "iso:country":"CH",
    "sg:address":"8352",
    "sg:city":"R\u00e4terschen",
    "sg:orig_category":"Elektrizit\u00e4tsversorgung",
    "sg:postcode":"8352",
    "sg:province":"Z\u00fcrich",
    "wof:name":"Elektrizit\u00e4tsgenossenschaft R\u00fcmikon Egr",
    "wof:placetype":"venue"
},
  "geometry": {"coordinates":[8.7932052612,47.4988098145],"type":"Point"}
}