{
  "type": "Feature",
  "properties": {
    "addr:full":"Wohlenstrasse 40 Uettligen Bern 3043",
    "addr:housenumber":"40",
    "addr:postcode":"3043",
    "addr:street":"Wohlenstrasse",
    "iso:country":"CH",
    "sg:address":"Wohlenstrasse 40",
    "sg:city":"Uettligen",
    "sg:orig_category":"Bauspenglerei Sanit\u00e4rinstallation",
    "sg:postcode":"3043",
    "sg:province":"Bern",
    "wof:name":"Rupp Sanit\u00e4r Ag Sanit\u00e4r Heizung Spenglerei",
    "wof:placetype":"venue"
},
  "geometry": {"coordinates":[7.480607,46.933895],"type":"Point"}
}