{
  "type": "Feature",
  "properties": {
    "iso:country":"CH",
    "sg:address":"Hochfeldstrasse 40-50",
    "sg:city":"Bern",
    "sg:orig_category":"Primarschulen",
    "sg:phone":"+41 31 301 18 34",
    "sg:postcode":"3012",
    "sg:province":"Bern",
    "wof:name":"Primarschule Hochfeld",
    "wof:placetype":"venue"
},
  "geometry": {"coordinates":[7.4286952019,46.9565925598],"type":"Point"}
}