{
  "type": "Feature",
  "properties": {
    "iso:country":"CH",
    "sg:address":"Viehmarktgasse 7 4242 Laufen. Postfach",
    "sg:city":"Laufen",
    "sg:orig_category":"RESTAURANTS: TEA-ROOMS",
    "sg:postcode":"4242",
    "sg:province":"Basel-Landschaft",
    "wof:name":"Pizzeria Baslerhof Da Luca Gmbh",
    "wof:placetype":"venue"
},
  "geometry": {"coordinates":[7.5000300407,47.4210968018],"type":"Point"}
}