{
  "type": "Feature",
  "properties": {
    "iso:country":"CH",
    "sg:address":"Riehentorstrasse 28",
    "sg:city":"Basel",
    "sg:orig_category":"RESTAURANTS: TEA-ROOMS",
    "sg:phone":"+41 61 691 32 83",
    "sg:postcode":"4058",
    "sg:province":"Basel-Stadt",
    "wof:name":"Pizzeria Firenze Stojanov Mile",
    "wof:placetype":"venue"
},
  "geometry": {"coordinates":[7.5962991714,47.5595207214],"type":"Point"}
}