{
  "type": "Feature",
  "properties": {
    "iso:country":"CH",
    "sg:address":"Fabrikmattenweg 21",
    "sg:city":"Arlesheim",
    "sg:orig_category":"Allgemeiner Hoch U Tiefbau D\u00e4mmung gegen K\u00e4lte, W\u00e4rme, Schall U Ersch\u00fctterung",
    "sg:phone":"+41 61 701 33 10",
    "sg:postcode":"4144",
    "sg:province":"Basel-Landschaft",
    "wof:name":"Prorefa Ag Abdichtungen & Isolationen",
    "wof:placetype":"venue"
},
  "geometry": {"coordinates":[7.609323,47.49551],"type":"Point"}
}