{
  "type": "Feature",
  "properties": {
    "iso:country":"CH",
    "sg:address":"Dorngasse 41",
    "sg:city":"Widen",
    "sg:orig_category":"Grosshandel mit B\u00fcromaschinen Grosshandel mit Datenverarbeitungsger\u00e4ten",
    "sg:phone":"+41 56 631 86 86",
    "sg:postcode":"8967",
    "sg:province":"Aargau",
    "wof:name":"Mit Moderne Informations- Technologien Ag",
    "wof:placetype":"venue"
},
  "geometry": {"coordinates":[8.3603906631,47.3650474548],"type":"Point"}
}