{
  "type": "Feature",
  "properties": {
    "iso:country":"CH",
    "sg:address":"Lommiswilerstrasse 29b 4512 Bellach. Postfach 311",
    "sg:city":"Bellach",
    "sg:orig_category":"Elektroinstallation",
    "sg:postcode":"4512",
    "sg:province":"Solothurn",
    "wof:name":"Herbert Schraner Elektrische, Telefoninstallationen. Elektr. Apparate, Ger\u00e4te; Verkauf",
    "wof:placetype":"venue"
},
  "geometry": {"coordinates":[8.0967502594,47.5433883667],"type":"Point"}
}