{
  "type": "Feature",
  "properties": {
    "iso:country":"CH",
    "sg:address":"Hauptstrasse 17",
    "sg:city":"Fischingen",
    "sg:orig_category":"Wasserversorgung",
    "sg:phone":"+41 41 660 32 66",
    "sg:postcode":"8376",
    "sg:province":"Thurgau",
    "wof:name":"Wasserversorgungs- Genossenschaft",
    "wof:placetype":"venue"
},
  "geometry": {"coordinates":[8.2112092972,46.8866157532],"type":"Point"}
}