{
  "type": "Feature",
  "properties": {
    "iso:country":"CH",
    "sg:address":"Albisstrasse 27 8038 Z\u00fcrich. Postfach",
    "sg:city":"Z\u00fcrich",
    "sg:orig_category":"Detailhandel mit Waren verschiedener Art, Hauptrichtung Nahrungsmittel Grosshandel mit Nahrungsmitte",
    "sg:phone":"+41 27 475 18 09",
    "sg:postcode":"8038",
    "sg:province":"Z\u00fcrich",
    "wof:name":"Carovilla Sa",
    "wof:placetype":"venue"
},
  "geometry": {"coordinates":[7.5763998032,46.1804466248],"type":"Point"}
}