{
  "type": "Feature",
  "properties": {
    "iso:country":"CH",
    "sg:address":"Oberdorfgasse 16 4107 Ettingen. Postfach",
    "sg:city":"Ettingen",
    "sg:orig_category":"Herstellung von Platten, Folien, Schl\u00e4uchen U Profilen aus Kunststoff",
    "sg:postcode":"4107",
    "sg:province":"Basel-Landschaft",
    "wof:name":"Dubro Spritzwerk Gmbh",
    "wof:placetype":"venue"
},
  "geometry": {"coordinates":[7.5435900688,47.4774017334],"type":"Point"}
}