{
  "type": "Feature",
  "properties": {
    "iso:country":"CH",
    "sg:address":"Seetalstrasse 29",
    "sg:city":"Boniswil",
    "sg:orig_category":"Architekturb\u00fcros",
    "sg:phone":"+41 62 777 39 22",
    "sg:postcode":"5706",
    "sg:province":"Aargau",
    "wof:name":"Zoltan Librecz Architekturb\u00fcro",
    "wof:placetype":"venue"
},
  "geometry": {"coordinates":[8.186584,47.314991],"type":"Point"}
}