{
  "type": "Feature",
  "properties": {
    "iso:country":"CH",
    "sg:address":"Wasserturmplatz 5",
    "sg:city":"Liestal",
    "sg:orig_category":"Herstellung von elektronischen Bauelementen Softwareentwicklung U beratung",
    "sg:phone":"+41 61 921 53 52",
    "sg:postcode":"4410",
    "sg:province":"Basel-Landschaft",
    "wof:name":"H.p. Roth Cds Datensysteme",
    "wof:placetype":"venue"
},
  "geometry": {"coordinates":[7.7351241112,47.4827041626],"type":"Point"}
}