{
  "type": "Feature",
  "properties": {
    "iso:country":"CH",
    "sg:address":"Muttenzerstrasse 37",
    "sg:city":"Pratteln",
    "sg:orig_category":"Wirtschaftspr\u00fcfung, Steuerberatung U Treuhand",
    "sg:phone":"+41 61 821 66 60",
    "sg:postcode":"4133",
    "sg:province":"Basel-Landschaft",
    "wof:name":"Sollberger Treuhand",
    "wof:placetype":"venue"
},
  "geometry": {"coordinates":[7.6866440773,47.5184211731],"type":"Point"}
}