{
  "type": "Feature",
  "properties": {
    "iso:country":"CH",
    "sg:address":"Talacker 7",
    "sg:city":"Kaltenbach",
    "sg:orig_category":"Einzelhandel mit Automobilteilen U Zubeh\u00f6r Fachdetailhandel in Verkaufsr\u00e4umen",
    "sg:phone":"+41 52 741 40 60",
    "sg:postcode":"8259",
    "sg:province":"Thurgau",
    "wof:name":"Salinas Geschenkboutique, Auto Und Truckshop",
    "wof:placetype":"venue"
},
  "geometry": {"coordinates":[8.8401231766,47.6532936096],"type":"Point"}
}