{
  "type": "Feature",
  "properties": {
    "iso:country":"CH",
    "sg:address":"Hinterbergstrasse 30 6330 Cham. Postfach 277",
    "sg:city":"Cham",
    "sg:orig_category":"Herstellung von B\u00fcro U Ladenm\u00f6beln Herstellung von Metallerzeugnissen ohne Maschinenbau",
    "sg:phone":"+41 41 741 15 88",
    "sg:postcode":"6330",
    "sg:province":"Zug",
    "wof:name":"Iem Office Ag",
    "wof:placetype":"venue"
},
  "geometry": {"coordinates":[8.4762506485,47.1866188049],"type":"Point"}
}