{
  "type": "Feature",
  "properties": {
    "iso:country":"CH",
    "sg:address":"Sonnenstrasse 3",
    "sg:city":"Bischofszell",
    "sg:orig_category":"Bauschreinerei",
    "sg:phone":"+41 56 633 95 33",
    "sg:postcode":"9220",
    "sg:province":"Thurgau",
    "wof:name":"Felix Schaufelb\u00fchl Schreinerei F\u00fcr Baubiologie",
    "wof:placetype":"venue"
},
  "geometry": {"coordinates":[8.33983,47.350952],"type":"Point"}
}