{
  "type": "Feature",
  "properties": {
    "iso:country":"CH",
    "sg:address":"St. Gallerstrasse 43",
    "sg:city":"Rorschach",
    "sg:orig_category":"Pensionskassen",
    "sg:postcode":"9400",
    "sg:province":"St. Gallen",
    "wof:name":"Personalf\u00fcrsorgestiftung Der Brauerei L\u00f6wengarten Ag, Rorschach",
    "wof:placetype":"venue"
},
  "geometry": {"coordinates":[9.4820241928,47.4782867432],"type":"Point"}
}