{
  "type": "Feature",
  "properties": {
    "iso:country":"CH",
    "sg:address":"Gubelstrasse 46",
    "sg:city":"Z\u00fcrich",
    "sg:orig_category":"Kinderkrippen U horte",
    "sg:phone":"+41 13124882",
    "sg:postcode":"8050",
    "sg:province":"Z\u00fcrich",
    "wof:name":"Spielgruppe Pippilotta",
    "wof:placetype":"venue"
},
  "geometry": {"coordinates":[8.5422506332,47.409122467],"type":"Point"}
}