{
  "type": "Feature",
  "properties": {
    "iso:country":"CH",
    "sg:address":"Brunngasse 14",
    "sg:city":"Z\u00fcrich",
    "sg:orig_category":"Non-Classified Establishments",
    "sg:postcode":"8001",
    "sg:province":"Z\u00fcrich",
    "wof:name":"Immagine, Salvatore Aventaggiato",
    "wof:placetype":"venue"
},
  "geometry": {"coordinates":[8.5447912216,47.373260498],"type":"Point"}
}