{
  "type": "Feature",
  "properties": {
    "iso:country":"CH",
    "sg:address":"Kaistenbergstrasse 3",
    "sg:city":"Kaisten",
    "sg:orig_category":"Kauf U Verkauf von Immobilien auf eigene Rechnung",
    "sg:phone":"+41 62 874 25 66",
    "sg:postcode":"5082",
    "sg:province":"Aargau",
    "wof:name":"Immovent Gmbh",
    "wof:placetype":"venue"
},
  "geometry": {"coordinates":[8.0443382263,47.5374412537],"type":"Point"}
}