{
  "type": "Feature",
  "properties": {
    "iso:country":"CH",
    "sg:address":"Zimmergasse 17",
    "sg:city":"Z\u00fcrich",
    "sg:classifiers":[
        {
            "category":"Banks & Credit Unions",
            "subcategory":"Financial Services",
            "type":"Services"
        }
    ],
    "sg:phone":"+41 4112656666",
    "sg:postcode":"8008",
    "sg:province":"Z\u00fcrich",
    "sg:tags":[
        "banking",
        "finance",
        "insurance"
    ],
    "wof:name":"Aeberli Treuhand Ag",
    "wof:placetype":"venue"
},
  "geometry": {"coordinates":[8.551544,47.362385],"type":"Point"}
}