{
  "type": "Feature",
  "properties": {
    "iso:country":"CH",
    "sg:address":"1937",
    "sg:city":"Orsi\u00e8res",
    "sg:orig_category":"Detailhandel mit Schuhen U Lederwaren",
    "sg:postcode":"1937",
    "sg:province":"Valais",
    "wof:name":"Joris Hortense",
    "wof:placetype":"venue"
},
  "geometry": {"coordinates":[7.1462898254,46.0306968689],"type":"Point"}
}