{
  "type": "Feature",
  "properties": {
    "iso:country":"CH",
    "sg:address":"9642 Ebnat. Postfach",
    "sg:city":"Ebnat-kappel",
    "sg:orig_category":"Pensionskassen",
    "sg:postcode":"9642",
    "sg:province":"St. Gallen",
    "wof:name":"Hilfsfonds F\u00fcr Die Angestellten Des Vereins Missionsheim Arche",
    "wof:placetype":"venue"
},
  "geometry": {"coordinates":[9.1167001724,47.25],"type":"Point"}
}