{
  "type": "Feature",
  "properties": {
    "iso:country":"CH",
    "sg:address":"Spitalstrasse 44",
    "sg:city":"Schlieren",
    "sg:orig_category":"Einzelhandel mit Automobilteilen U Zubeh\u00f6r",
    "sg:phone":"+41 17309272",
    "sg:postcode":"8952",
    "sg:province":"Z\u00fcrich",
    "wof:name":"Guido Arn Pneuhandel",
    "wof:placetype":"venue"
},
  "geometry": {"coordinates":[8.4275093079,47.3943862915],"type":"Point"}
}