{
  "type": "Feature",
  "properties": {
    "iso:country":"CH",
    "sg:address":"Le Muids Chemin Fin D'elez 1273 Arzier. Postfach",
    "sg:city":"Arzier",
    "sg:orig_category":"Handel mit Automobilen",
    "sg:phone":"+41 22 366 30 45",
    "sg:postcode":"1273",
    "sg:province":"Vaud",
    "wof:name":"Bureau D'expertises Automobiles Neutre, Br\u00fcgger Christian Expertises D'automobiles",
    "wof:placetype":"venue"
},
  "geometry": {"coordinates":[6.1784172058,46.4513130188],"type":"Point"}
}