{
  "type": "Feature",
  "properties": {
    "iso:country":"CH",
    "sg:address":"Rautistrasse 77 8000 Z\u00fcrich. Postfach",
    "sg:city":"Z\u00fcrich",
    "sg:orig_category":"Fachdetailhandel in Verkaufsr\u00e4umen",
    "sg:postcode":"8048",
    "sg:province":"Z\u00fcrich",
    "wof:name":"Bigiotteria E Profumeria Le Follie Sa",
    "wof:placetype":"venue"
},
  "geometry": {"coordinates":[8.8598842621,45.9677848816],"type":"Point"}
}