{
  "type": "Feature",
  "properties": {
    "iso:country":"CH",
    "sg:address":"5236",
    "sg:city":"Remigen",
    "sg:orig_category":"Vorschulen, Kinderg\u00e4rten",
    "sg:phone":"+41 56 284 14 89",
    "sg:postcode":"5236",
    "sg:province":"Aargau",
    "wof:name":"Kindergarten",
    "wof:placetype":"venue"
},
  "geometry": {"coordinates":[8.1892366409,47.5150871277],"type":"Point"}
}