{
  "type": "Feature",
  "properties": {
    "iso:country":"CH",
    "sg:address":"H\u00f6fnerstrasse 96 6314 Unter\u00e4geri. Postfach",
    "sg:city":"Baar",
    "sg:orig_category":"Mechanik Stahl U Leichtmetallbau",
    "sg:phone":"+41 41 761 23 08",
    "sg:postcode":"6341",
    "sg:province":"Zug",
    "wof:name":"C. Schweiger Ag Metallbau",
    "wof:placetype":"venue"
},
  "geometry": {"coordinates":[8.579372406,47.1285705566],"type":"Point"}
}