{
  "type": "Feature",
  "properties": {
    "iso:country":"CH",
    "sg:address":"Moserweg 7",
    "sg:city":"Villmergen",
    "sg:orig_category":"Organisationen des Gesundheitswesen",
    "sg:phone":"+41 56 622 85 37",
    "sg:postcode":"5612",
    "sg:province":"Aargau",
    "wof:name":"Krankenpflegeverein Frau Doris Keusch",
    "wof:placetype":"venue"
},
  "geometry": {"coordinates":[8.2550764084,47.3452911377],"type":"Point"}
}