{
  "type": "Feature",
  "properties": {
    "iso:country":"CH",
    "sg:address":"Es Epechoux",
    "sg:city":"Riaz",
    "sg:orig_category":"Erdbewegungsarbeiten G\u00fcterbef\u00f6rderung im Strassenverkehr",
    "sg:phone":"+41 21 691 22 63",
    "sg:postcode":"1632",
    "sg:province":"Fribourg",
    "wof:name":"Jean-pierre Fournier Transports & Terrassements",
    "wof:placetype":"venue"
},
  "geometry": {"coordinates":[6.5575327873,46.510093689],"type":"Point"}
}