{
  "type": "Feature",
  "properties": {
    "iso:country":"CH",
    "sg:address":"Hebelstrasse 112 4000 Basel. Postfach",
    "sg:city":"Basel",
    "sg:orig_category":"Sonstiger Grosshandel",
    "sg:postcode":"4051",
    "sg:province":"Basel-Stadt",
    "wof:name":"Jusinfo Gmbh",
    "wof:placetype":"venue"
},
  "geometry": {"coordinates":[7.5772800446,47.5636901855],"type":"Point"}
}