{
  "type": "Feature",
  "properties": {
    "iso:country":"CH",
    "sg:address":"Neuhofweg 10",
    "sg:city":"Hombrechtikon",
    "sg:orig_category":"Herstellung von k\u00e4lte U lufttechnischen Erzeugnissen f\u00fcr gewerbliche Zwecke Herstellung von sonstige",
    "sg:phone":"+41 55 244 12 24",
    "sg:postcode":"8634",
    "sg:province":"Z\u00fcrich",
    "wof:name":"St\u00fccklin & Cie Ag",
    "wof:placetype":"venue"
},
  "geometry": {"coordinates":[8.7770910263,47.2531776428],"type":"Point"}
}