{
  "type": "Feature",
  "properties": {
    "iso:country":"CH",
    "sg:address":"4468",
    "sg:city":"Kienberg",
    "sg:orig_category":"Sportvereine Sch\u00fctzen",
    "sg:phone":"+41 62 293 52 29",
    "sg:postcode":"4468",
    "sg:province":"Solothurn",
    "wof:name":"Feldsch\u00fctzengesellschaft",
    "wof:placetype":"venue"
},
  "geometry": {"coordinates":[7.9668068886,47.439163208],"type":"Point"}
}