{
  "type": "Feature",
  "properties": {
    "iso:country":"CH",
    "sg:address":"Seeheimstrasse 5b",
    "sg:city":"Goldach",
    "sg:orig_category":"Bauschreinerei Herstellung von elektrischen Haushaltsger\u00e4ten",
    "sg:phone":"+41 79 698 53 65",
    "sg:postcode":"9403",
    "sg:province":"St. Gallen",
    "wof:name":"Walser Ag K\u00fchlm\u00f6bel Und Bauschreinerei",
    "wof:placetype":"venue"
},
  "geometry": {"coordinates":[9.48111,47.47913],"type":"Point"}
}