{
  "type": "Feature",
  "properties": {
    "iso:country":"CH",
    "sg:address":"Baumgartenweg 3",
    "sg:city":"L\u00e4ufelfingen",
    "sg:orig_category":"Architektur U Ingenieurb\u00fcros",
    "sg:phone":"+41 62 299 21 43",
    "sg:postcode":"4448",
    "sg:province":"Basel-Landschaft",
    "wof:name":"Rickenbacher Atelier 3 Ag",
    "wof:placetype":"venue"
},
  "geometry": {"coordinates":[7.856871,47.398182],"type":"Point"}
}