{
  "type": "Feature",
  "properties": {
    "iso:country":"CH",
    "sg:address":"Frauholzstrasse 36",
    "sg:city":"Steinen",
    "sg:orig_category":"Haltung von Schweinen",
    "sg:phone":"+41 41 832 18 52",
    "sg:postcode":"6422",
    "sg:province":"Schwyz",
    "wof:name":"Franz Annen Schweinezucht",
    "wof:placetype":"venue"
},
  "geometry": {"coordinates":[8.6047706604,47.0445709229],"type":"Point"}
}