{
  "type": "Feature",
  "properties": {
    "iso:country":"CH",
    "sg:address":"Via Stazione 6702 Claro. Postfach",
    "sg:city":"Biasca",
    "sg:orig_category":"Detailhandel mit Fleisch U Fleischwaren",
    "sg:postcode":"6710",
    "sg:province":"Ticino",
    "wof:name":"Macelleria Mennite Antonio Biasca",
    "wof:placetype":"venue"
},
  "geometry": {"coordinates":[9.0172748566,46.2535362244],"type":"Point"}
}