{
  "type": "Feature",
  "properties": {
    "iso:country":"CH",
    "sg:address":"Kusterwiesstrasse 1",
    "sg:city":"Bilten",
    "sg:orig_category":"Unternehmensberatung",
    "sg:phone":"+41 55 619 52 65",
    "sg:postcode":"8865",
    "sg:province":"Glarus",
    "wof:name":"Matrix.cmf Gmbh",
    "wof:placetype":"venue"
},
  "geometry": {"coordinates":[9.0237121582,47.1510658264],"type":"Point"}
}