{
  "type": "Feature",
  "properties": {
    "iso:country":"CH",
    "sg:address":"Via Gismonda 15",
    "sg:city":"Mendrisio",
    "sg:orig_category":"Vermietung U Verpachtung von eigenen Immobilien",
    "sg:postcode":"6850",
    "sg:province":"Ticino",
    "wof:name":"Edeno Sa",
    "wof:placetype":"venue"
},
  "geometry": {"coordinates":[8.9857692719,45.868938446],"type":"Point"}
}