{
  "type": "Feature",
  "properties": {
    "iso:country":"CH",
    "sg:address":"Zollikerstrasse 65",
    "sg:city":"Zollikon",
    "sg:orig_category":"Pensionskassen",
    "sg:postcode":"8702",
    "sg:province":"Z\u00fcrich",
    "wof:name":"Personalf\u00fcrsorgekasse Der Baumann Emil Ag",
    "wof:placetype":"venue"
},
  "geometry": {"coordinates":[8.639749527,46.8880310059],"type":"Point"}
}