{
  "type": "Feature",
  "properties": {
    "iso:country":"CH",
    "sg:address":"Spitzackerstrasse 2a",
    "sg:city":"Liestal",
    "sg:orig_category":"Bauingenieurb\u00fcros Hochbau Bauingenieurb\u00fcros allgemein",
    "sg:phone":"+41 61 921 30 20",
    "sg:postcode":"4410",
    "sg:province":"Basel-Landschaft",
    "wof:name":"Walter Gudenrath Ingenieurb\u00fcro",
    "wof:placetype":"venue"
},
  "geometry": {"coordinates":[7.737902,47.479717],"type":"Point"}
}