{
  "type": "Feature",
  "properties": {
    "iso:country":"CH",
    "sg:address":"Breitfeldstrasse 1",
    "sg:city":"Kesswil",
    "sg:orig_category":"Vermietung von Luftfahrzeugen",
    "sg:phone":"+41 13966600",
    "sg:postcode":"8593",
    "sg:province":"Thurgau",
    "wof:name":"B&m Balloon & Airship Company Gmbh",
    "wof:placetype":"venue"
},
  "geometry": {"coordinates":[9.3173770905,47.5898551941],"type":"Point"}
}