{
  "type": "Feature",
  "properties": {
    "addr:full":"Z\u00fcrichstrasse 967 Uster Z\u00fcrich 8610",
    "addr:housenumber":"967",
    "addr:postcode":"8610",
    "addr:street":"Zuerichstrasse",
    "iso:country":"CH",
    "sg:address":"Z\u00fcrichstrasse 967",
    "sg:city":"Uster",
    "sg:classifiers":[
        {
            "category":"Government",
            "subcategory":"Department Of Motor Vehicles",
            "type":"Public Place"
        }
    ],
    "sg:phone":"+41 19052030",
    "sg:postcode":"8610",
    "sg:province":"Z\u00fcrich",
    "sg:tags":[
        "sealant",
        "adhesive"
    ],
    "wof:name":"Bamert Ag",
    "wof:placetype":"venue"
},
  "geometry": {"coordinates":[8.709063,47.351482],"type":"Point"}
}