{
  "type": "Feature",
  "properties": {
    "iso:country":"CH",
    "sg:address":"Lavaterstrasse 57",
    "sg:city":"Z\u00fcrich",
    "sg:orig_category":"Interessenvertretungen",
    "sg:phone":"+41 12026080",
    "sg:postcode":"8002",
    "sg:province":"Z\u00fcrich",
    "wof:name":"Verband Schweizerischer Bodenbelagsgrossisten (vsbg)",
    "wof:placetype":"venue"
},
  "geometry": {"coordinates":[8.5328950882,47.3617286682],"type":"Point"}
}