{
  "type": "Feature",
  "properties": {
    "iso:country":"CH",
    "sg:address":"Zaehringen Rue De 1",
    "sg:city":"Freiburg",
    "sg:orig_category":"Non-Classified Establishments",
    "sg:postcode":"1700",
    "sg:province":"Fribourg",
    "wof:name":"Phytec Limited, \u00e0 Londres (gb), Succursale De Fribourg",
    "wof:placetype":"venue"
},
  "geometry": {"coordinates":[7.1652750969,46.8055839539],"type":"Point"}
}