{
  "type": "Feature",
  "properties": {
    "iso:country":"CH",
    "sg:address":"Via Boschina 10",
    "sg:city":"Pregassona",
    "sg:orig_category":"Bauspenglerei Sanit\u00e4r, Heizungs U L\u00fcftungsinstallation",
    "sg:phone":"+41 79 352 89 25",
    "sg:postcode":"6963",
    "sg:province":"Ticino",
    "wof:name":"Gilomen Gmbh",
    "wof:placetype":"venue"
},
  "geometry": {"coordinates":[7.326828,47.102654],"type":"Point"}
}