{
  "type": "Feature",
  "properties": {
    "iso:country":"CH",
    "sg:address":"Grange-collomb Chemin De 7",
    "sg:city":"Grand-lancy",
    "sg:orig_category":"Herstellung von sonstigen Maschinen f\u00fcr unspezifische Verwendung",
    "sg:phone":"+41 22 820 21 10",
    "sg:postcode":"1212",
    "sg:province":"Gen\u00e8ve",
    "wof:name":"Resina Application Et Production Sa",
    "wof:placetype":"venue"
},
  "geometry": {"coordinates":[6.1341428757,46.1752891541],"type":"Point"}
}