{
  "type": "Feature",
  "properties": {
    "iso:country":"CH",
    "sg:address":"Rue De La Terrassi\u00e8re 58",
    "sg:city":"Gen\u00e8ve",
    "sg:orig_category":"Elektro- and elektronische Maschinen Grosshandel Softwareentwicklung U beratung",
    "sg:phone":"+41 81 420 60 00",
    "sg:postcode":"1207",
    "sg:province":"Gen\u00e8ve",
    "wof:name":"Xiax Solutions Gmbh",
    "wof:placetype":"venue"
},
  "geometry": {"coordinates":[9.8305082321,46.7986831665],"type":"Point"}
}