{
  "type": "Feature",
  "properties": {
    "addr:full":"Rheinstrasse Trimmis Graubunden 7203",
    "addr:postcode":"7203",
    "addr:street":"Rheinstrasse;Graubunden",
    "iso:country":"CH",
    "sg:address":"Rheinstrasse",
    "sg:city":"Trimmis",
    "sg:orig_category":"Bauspenglerei Sanit\u00e4rinstallation U Spenglerei",
    "sg:phone":"+41 81 354 90 40",
    "sg:postcode":"7203",
    "sg:province":"Graubunden",
    "wof:name":"G. Calanca Ag L\u00fcftungsspenglerei",
    "wof:placetype":"venue"
},
  "geometry": {"coordinates":[9.556243,46.917664],"type":"Point"}
}