{
  "type": "Feature",
  "properties": {
    "iso:country":"CH",
    "sg:address":"Tannenstrasse 104",
    "sg:city":"Embrach",
    "sg:orig_category":"Mechanik",
    "sg:phone":"+41 19211626",
    "sg:postcode":"8424",
    "sg:province":"Z\u00fcrich",
    "wof:name":"R. + L. Mechanik Gmbh",
    "wof:placetype":"venue"
},
  "geometry": {"coordinates":[8.8498697281,47.2590713501],"type":"Point"}
}