{
  "type": "Feature",
  "properties": {
    "iso:country":"CH",
    "sg:address":"Rue De Gen\u00e8ve 52 1225 Ch\u00eane-bourg. Postfach",
    "sg:city":"Regensdorf",
    "sg:orig_category":"Grosshandel mit Baumaterialien",
    "sg:phone":"+41 19321160",
    "sg:postcode":"8105",
    "sg:province":"Z\u00fcrich",
    "wof:name":"Peter Weiss Baustoffe Winterg\u00e4rten",
    "wof:placetype":"venue"
},
  "geometry": {"coordinates":[8.7865333557,47.3295516968],"type":"Point"}
}