{
  "type": "Feature",
  "properties": {
    "iso:country":"CH",
    "sg:address":"Staffelackerstrasse 6",
    "sg:city":"Dietikon",
    "sg:orig_category":"K\u00fcnstlerische Schulen",
    "sg:phone":"+41 17407325",
    "sg:postcode":"8953",
    "sg:province":"Z\u00fcrich",
    "wof:name":"Adelheid Trepp Musik-& Rhythmikschule",
    "wof:placetype":"venue"
},
  "geometry": {"coordinates":[8.3911724091,47.4017524719],"type":"Point"}
}