{
  "type": "Feature",
  "properties": {
    "iso:country":"CH",
    "sg:address":"Albisriederstrasse 166",
    "sg:city":"Z\u00fcrich",
    "sg:orig_category":"Kunsthandel Museen",
    "sg:phone":"+41 79 349 00 00",
    "sg:postcode":"8003",
    "sg:province":"Z\u00fcrich",
    "wof:name":"Galerie Strohschneider",
    "wof:placetype":"venue"
},
  "geometry": {"coordinates":[8.4998474121,47.3775444031],"type":"Point"}
}