{
  "type": "Feature",
  "properties": {
    "iso:country":"CH",
    "sg:address":"Saint-fran\u00e7ois Place 14",
    "sg:city":"Lausanne",
    "sg:orig_category":"Pensionskassen",
    "sg:phone":"+41 21 633 02 02",
    "sg:postcode":"1003",
    "sg:province":"Vaud",
    "wof:name":"Fondation Commune De La Soci\u00e9t\u00e9 Garage De L'etoile Sa",
    "wof:placetype":"venue"
},
  "geometry": {"coordinates":[6.597099781,46.5390167236],"type":"Point"}
}