{
  "type": "Feature",
  "properties": {
    "iso:country":"CH",
    "sg:address":"Ruelle Du Chauderon 1",
    "sg:city":"Montreux",
    "sg:orig_category":"Kunsthandel",
    "sg:phone":"+41 21 963 78 91",
    "sg:postcode":"1820",
    "sg:province":"Vaud",
    "wof:name":"Galerie Les Planches Th\u00e9odore Klaus",
    "wof:placetype":"venue"
},
  "geometry": {"coordinates":[6.9167180061,46.4333686829],"type":"Point"}
}