{
  "type": "Feature",
  "properties": {
    "iso:country":"CH",
    "sg:address":"Rue Des Pr\u00e9s 40",
    "sg:city":"Boudry",
    "sg:orig_category":"Architektur U Ingenieurb\u00fcros",
    "sg:phone":"+41 32 842 25 45",
    "sg:postcode":"2017",
    "sg:province":"Neuch\u00e2tel",
    "wof:name":"Jean-pierre Kneub\u00fchler Bureau Technique",
    "wof:placetype":"venue"
},
  "geometry": {"coordinates":[6.826445,46.952007],"type":"Point"}
}