{
  "type": "Feature",
  "properties": {
    "iso:country":"CH",
    "sg:address":"Kraftwerkstrasse 52",
    "sg:city":"M\u00f6hlin",
    "sg:orig_category":"RESTAURANTS: TEA-ROOMS",
    "sg:phone":"+41 61 851 11 26",
    "sg:postcode":"4313",
    "sg:province":"Aargau",
    "wof:name":"Rest. J\u00e4gerst\u00fcbli Kurt Meier",
    "wof:placetype":"venue"
},
  "geometry": {"coordinates":[7.8368678093,47.5725631714],"type":"Point"}
}