{
  "type": "Feature",
  "properties": {
    "iso:country":"CH",
    "sg:address":"Maistrasse 15",
    "sg:city":"Courlevon",
    "sg:orig_category":"Sportschulen Wassersport",
    "sg:phone":"+41 26 684 12 82",
    "sg:postcode":"1795",
    "sg:province":"Fribourg",
    "wof:name":"Martin Schweizer Surfschule",
    "wof:placetype":"venue"
},
  "geometry": {"coordinates":[7.1116948128,46.8910217285],"type":"Point"}
}