{
  "type": "Feature",
  "properties": {
    "iso:country":"CH",
    "sg:address":"Lehenweg 21 3705 Faulensee. Postfach",
    "sg:city":"Faulensee",
    "sg:orig_category":"Handels-H\u00e4user U Gesellschaften",
    "sg:phone":"+41 33550808",
    "sg:postcode":"3705",
    "sg:province":"Bern",
    "wof:name":"Cosmos Gmbh",
    "wof:placetype":"venue"
},
  "geometry": {"coordinates":[7.7013411522,46.680896759],"type":"Point"}
}