{
  "type": "Feature",
  "properties": {
    "iso:country":"CH",
    "sg:address":"Oberdorf",
    "sg:city":"Grossdietwil",
    "sg:orig_category":"B\u00e4ckereien Detailhandel mit Waren verschiedener Art, Hauptrichtung Nahrungsmittel",
    "sg:phone":"+41 62 927 11 65",
    "sg:postcode":"6146",
    "sg:province":"Luzern",
    "wof:name":"Franz R\u00f6thlin",
    "wof:placetype":"venue"
},
  "geometry": {"coordinates":[7.889223,47.170368],"type":"Point"}
}