{
  "type": "Feature",
  "properties": {
    "iso:country":"CH",
    "sg:address":"Asylstrasse 40",
    "sg:city":"Glarus",
    "sg:orig_category":"Vermietung U Verpachtung von eigenen Immobilien",
    "sg:postcode":"8750",
    "sg:province":"Glarus",
    "wof:name":"Charitas Sa",
    "wof:placetype":"venue"
},
  "geometry": {"coordinates":[9.0633611679,47.0460548401],"type":"Point"}
}