{
  "type": "Feature",
  "properties": {
    "iso:country":"CH",
    "sg:address":"Rue Marterey 28",
    "sg:city":"Lausanne",
    "sg:orig_category":"Detailhandel mit fotografischen Artikeln Fotografische Ateliers",
    "sg:phone":"+41 21 323 75 95",
    "sg:postcode":"1005",
    "sg:province":"Vaud",
    "wof:name":"Photo Marterey, Testard Jean Appareils Photographiques Etc; Comm",
    "wof:placetype":"venue"
},
  "geometry": {"coordinates":[6.6384148598,46.520401001],"type":"Point"}
}