{
  "type": "Feature",
  "properties": {
    "iso:country":"CH",
    "sg:address":"Seilerstrasse 8",
    "sg:city":"Bern",
    "sg:orig_category":"Detailhandel mit Ton U Bildtr\u00e4gern Detailhandel mit elektrischen Haushalts-,Radio U Fernsehger\u00e4ten s",
    "sg:phone":"+41 31 381 50 30",
    "sg:postcode":"3011",
    "sg:province":"Bern",
    "wof:name":"Hifi Discount Glanzmann",
    "wof:placetype":"venue"
},
  "geometry": {"coordinates":[7.4349842072,46.9463195801],"type":"Point"}
}