{
  "type": "Feature",
  "properties": {
    "iso:country":"CH",
    "sg:address":"Route Principale",
    "sg:city":"Cronay",
    "sg:orig_category":"Vereine Hundedressur",
    "sg:phone":"+41 24 433 18 02",
    "sg:postcode":"1406",
    "sg:province":"Vaud",
    "wof:name":"Club De Cynologie St-aubin",
    "wof:placetype":"venue"
},
  "geometry": {"coordinates":[6.6957669258,46.7572021484],"type":"Point"}
}