{
  "type": "Feature",
  "properties": {
    "iso:country":"CH",
    "sg:address":"Hengelweg 24",
    "sg:city":"W\u00fcrenlingen",
    "sg:orig_category":"Sportvereine Ballsport Handball",
    "sg:postcode":"5303",
    "sg:province":"Aargau",
    "wof:name":"Sv Altst\u00e4tten",
    "wof:placetype":"venue"
},
  "geometry": {"coordinates":[9.5369033813,47.3797683716],"type":"Point"}
}