{
  "type": "Feature",
  "properties": {
    "iso:country":"CH",
    "sg:address":"Ifangstrasse 7",
    "sg:city":"R\u00fcmlang",
    "sg:orig_category":"Instandhaltung U Reparatur von Automobilen",
    "sg:postcode":"8153",
    "sg:province":"Z\u00fcrich",
    "wof:name":"Jc Motorsport Gmbh",
    "wof:placetype":"venue"
},
  "geometry": {"coordinates":[8.5337114334,47.4526634216],"type":"Point"}
}