{
  "type": "Feature",
  "properties": {
    "iso:country":"CH",
    "sg:address":"Michelstrasse 44",
    "sg:city":"Z\u00fcrich",
    "sg:orig_category":"Detailhandel mit Waren verschiedener Art, Hauptrichtung Nahrungsmittel Grosshandel mit Nahrungsmitte",
    "sg:phone":"+41 13416651",
    "sg:postcode":"8049",
    "sg:province":"Z\u00fcrich",
    "wof:name":"J. Und W. Stamm",
    "wof:placetype":"venue"
},
  "geometry": {"coordinates":[8.4953956604,47.4067459106],"type":"Point"}
}