{
  "type": "Feature",
  "properties": {
    "iso:country":"CH",
    "sg:address":"Fiera Via Alla 14",
    "sg:city":"Biasca",
    "sg:orig_category":"Detailhandel mit Bekleidung",
    "sg:postcode":"6710",
    "sg:province":"Ticino",
    "wof:name":"Marival Sa",
    "wof:placetype":"venue"
},
  "geometry": {"coordinates":[8.972628,46.362564],"type":"Point"}
}