{
  "type": "Feature",
  "properties": {
    "iso:country":"CH",
    "sg:address":"Gerechtigkeitsgasse 6",
    "sg:city":"Z\u00fcrich",
    "sg:orig_category":"Herstellung von Elektromotoren, Generatoren U Transformatoren",
    "sg:phone":"+41 12013595",
    "sg:postcode":"8002",
    "sg:province":"Z\u00fcrich",
    "wof:name":"Huser Elektro-anlagen Ag",
    "wof:placetype":"venue"
},
  "geometry": {"coordinates":[8.5321187973,47.3701133728],"type":"Point"}
}