{
  "type": "Feature",
  "properties": {
    "iso:country":"CH",
    "sg:address":"Dorfstrasse 84",
    "sg:city":"Geroldswil",
    "sg:orig_category":"Kosmetikinstitute",
    "sg:phone":"+41 17480887",
    "sg:postcode":"8954",
    "sg:province":"Z\u00fcrich",
    "wof:name":"Jacqueline Altenaichinger Kosmetikinstitut",
    "wof:placetype":"venue"
},
  "geometry": {"coordinates":[8.4119462967,47.4239082336],"type":"Point"}
}