{
  "type": "Feature",
  "properties": {
    "iso:country":"CH",
    "sg:address":"Allmendstrasse",
    "sg:city":"Reutigen",
    "sg:orig_category":"Naturheil\u00e4rzte and Heilpraktiker",
    "sg:phone":"+41 33 657 22 59",
    "sg:postcode":"3647",
    "sg:province":"Bern",
    "wof:name":"Peter Gugger Nat\u00fcrliche Therapien",
    "wof:placetype":"venue"
},
  "geometry": {"coordinates":[7.6247038841,46.6958465576],"type":"Point"}
}