{
  "type": "Feature",
  "properties": {
    "iso:country":"CH",
    "sg:address":"Alemannengasse 33 4058 Basel. Postfach",
    "sg:city":"Basel",
    "sg:orig_category":"Datenverarbeitungsdienste Ingenieurb\u00fcros Datenverarbeitung",
    "sg:phone":"+41 61 273 58 71",
    "sg:postcode":"4009",
    "sg:province":"Basel-Stadt",
    "wof:name":"Mike S. Krischker Muinar Internet Studios",
    "wof:placetype":"venue"
},
  "geometry": {"coordinates":[7.60083,47.557739],"type":"Point"}
}