{
  "type": "Feature",
  "properties": {
    "iso:country":"CH",
    "sg:address":"Amperestr. 3",
    "sg:city":"Steinach",
    "sg:classifiers":[
        {
            "category":"Utilities",
            "subcategory":"Electric",
            "type":"Services"
        }
    ],
    "sg:phone":"+41 71 447 04 47",
    "sg:postcode":"9323",
    "sg:province":"St. Gallen",
    "sg:tags":[
        "electricity",
        "electronic",
        "electrical",
        "equipment"
    ],
    "wof:name":"Tyco Electronic Ag",
    "wof:placetype":"venue"
},
  "geometry": {"coordinates":[9.4477910995,47.4996490479],"type":"Point"}
}