{
  "type": "Feature",
  "properties": {
    "iso:country":"CH",
    "sg:address":"Auf Der Maur",
    "sg:city":"Lohnstorf",
    "sg:orig_category":"Herstellung von sonstigen Holzwaren",
    "sg:postcode":"3127",
    "sg:province":"Bern",
    "wof:name":"Burri Paul, Vorm. Pfau Walter",
    "wof:placetype":"venue"
},
  "geometry": {"coordinates":[7.5075750351,46.8137397766],"type":"Point"}
}