{
  "type": "Feature",
  "properties": {
    "iso:country":"CH",
    "sg:address":"Weinbergstrasse 42c",
    "sg:city":"Zug",
    "sg:orig_category":"Museen",
    "sg:phone":"+41 41 711 39 67",
    "sg:postcode":"6300",
    "sg:province":"Zug",
    "wof:name":"Stadlin Daniel, B\u00fcro F\u00fcr Kulturg\u00fcterschutz Und Denkmalpflege, Photogrammetrie",
    "wof:placetype":"venue"
},
  "geometry": {"coordinates":[8.5240402222,47.164768219],"type":"Point"}
}