{
  "type": "Feature",
  "properties": {
    "iso:country":"CH",
    "sg:address":"Pellitteri Vincenzo",
    "sg:city":"Quartino",
    "sg:orig_category":"Verwaltung von Immobilien",
    "sg:postcode":"6572",
    "sg:province":"Ticino",
    "wof:name":"Martirio Sagl",
    "wof:placetype":"venue"
},
  "geometry": {"coordinates":[8.8953781128,46.1506347656],"type":"Point"}
}