{
  "type": "Feature",
  "properties": {
    "addr:full":"Rue De Rhone 100 Geneva Gen\u00e8ve 1204",
    "addr:housenumber":"100",
    "addr:postcode":"1204",
    "addr:street":"Rue De Rhone",
    "iso:country":"CH",
    "sg:address":"Rue De Rhone 100",
    "sg:city":"Geneva",
    "sg:classifiers":[
        {
            "category":"Banks & Credit Unions",
            "subcategory":"Bank",
            "type":"Services"
        }
    ],
    "sg:phone":"+41 22 312 28 28",
    "sg:postcode":"1204",
    "sg:province":"Gen\u00e8ve",
    "wof:name":"Alexander Trust Co Ag",
    "wof:placetype":"venue"
},
  "geometry": {"coordinates":[6.152224,46.203037],"type":"Point"}
}