{
  "type": "Feature",
  "properties": {
    "iso:country":"CH",
    "sg:address":"Musy Avenue Jean-marie- 16",
    "sg:city":"Fribourg",
    "sg:orig_category":"Maler U Glasergewerbe",
    "sg:phone":"+41 79 230 58 30",
    "sg:postcode":"1700",
    "sg:province":"Fribourg",
    "wof:name":"Pedrosa Eduardo Et Fils Sa",
    "wof:placetype":"venue"
},
  "geometry": {"coordinates":[7.176636219,46.8084106445],"type":"Point"}
}