{
  "type": "Feature",
  "properties": {
    "iso:country":"CH",
    "sg:address":"Allmendstrasse 14",
    "sg:city":"Villmergen",
    "sg:orig_category":"Detailhandel mit elektrischen Haushalts-,Radio U Fernsehger\u00e4ten sowie Musikinstrumenten",
    "sg:phone":"+41 56 610 00 30",
    "sg:postcode":"5612",
    "sg:province":"Aargau",
    "wof:name":"Le Creuset Swiss Ag",
    "wof:placetype":"venue"
},
  "geometry": {"coordinates":[8.2487869263,47.3568000793],"type":"Point"}
}