{
  "type": "Feature",
  "properties": {
    "iso:country":"CH",
    "sg:address":"Ringstrasse 1",
    "sg:city":"Schwerzenbach",
    "sg:orig_category":"Grosshandel mit Datenverarbeitungsger\u00e4ten Softwareentwicklung U beratung",
    "sg:phone":"+41 18063535",
    "sg:postcode":"8603",
    "sg:province":"Z\u00fcrich",
    "wof:name":"Mtf Data Ag",
    "wof:placetype":"venue"
},
  "geometry": {"coordinates":[8.6550178528,47.3872375488],"type":"Point"}
}