{
  "type": "Feature",
  "properties": {
    "iso:country":"CH",
    "sg:address":"Haldenstrasse 19a",
    "sg:city":"Biel/bienne",
    "sg:orig_category":"Herstellung von Mess U Kontrollinstrumenten U vorrichtungen Softwareentwicklung U beratung",
    "sg:phone":"+41 32 342 69 10",
    "sg:postcode":"2502",
    "sg:province":"Bern",
    "wof:name":"Captec Gmbh",
    "wof:placetype":"venue"
},
  "geometry": {"coordinates":[7.2574419975,47.1490783691],"type":"Point"}
}