{
  "type": "Feature",
  "properties": {
    "iso:country":"CH",
    "sg:address":"Impasse Saint-michel 7",
    "sg:city":"Boncourt",
    "sg:orig_category":"Markt U Meinungsforschung",
    "sg:postcode":"2926",
    "sg:province":"Jura",
    "wof:name":"Pos Marketing Sa",
    "wof:placetype":"venue"
},
  "geometry": {"coordinates":[7.0075888634,47.4926643372],"type":"Point"}
}