{
  "type": "Feature",
  "properties": {
    "iso:country":"CH",
    "sg:address":"Rue Des Gorges 32",
    "sg:city":"Court",
    "sg:orig_category":"Non-Classified Establishments",
    "sg:postcode":"2738",
    "sg:province":"Bern",
    "wof:name":"Esat Frei Roland",
    "wof:placetype":"venue"
},
  "geometry": {"coordinates":[7.3461551666,47.2425994873],"type":"Point"}
}