{
  "type": "Feature",
  "properties": {
    "iso:country":"CH",
    "sg:address":"Sch\u00fcrmatt 6387 Oberrickenbach. Postfach",
    "sg:city":"Oberrickenbach",
    "sg:orig_category":"Abbruch U Sprenggewerbe, Erdbewegungsarbeiten",
    "sg:postcode":"6387",
    "sg:province":"Nidwalden",
    "wof:name":"Tobe Gmbh, Zweigniederlassung Wolfenschiessen",
    "wof:placetype":"venue"
},
  "geometry": {"coordinates":[8.38986,46.896019],"type":"Point"}
}