{
  "type": "Feature",
  "properties": {
    "iso:country":"CH",
    "sg:address":"St.-leodegar-strasse 2",
    "sg:city":"Luzern",
    "sg:orig_category":"Hochschulen U h\u00f6here Ausbildung",
    "sg:phone":"+41 41 410 96 92",
    "sg:postcode":"6006",
    "sg:province":"Luzern",
    "wof:name":"Heilpraktikerschule Hps Gmbh",
    "wof:placetype":"venue"
},
  "geometry": {"coordinates":[8.3128080368,47.0549354553],"type":"Point"}
}