{
  "type": "Feature",
  "properties": {
    "iso:country":"CH",
    "sg:address":"Charmilles Rue Des 14",
    "sg:city":"Gen\u00e8ve",
    "sg:orig_category":"Non-Classified Establishments",
    "sg:postcode":"1203",
    "sg:province":"Gen\u00e8ve",
    "wof:name":"Muji Avduraman - Moni Commerce",
    "wof:placetype":"venue"
},
  "geometry": {"coordinates":[6.1308321953,46.2064285278],"type":"Point"}
}