{
  "type": "Feature",
  "properties": {
    "iso:country":"CH",
    "sg:address":"Gampelengasse 2b",
    "sg:city":"Ins",
    "sg:orig_category":"Instandhaltung U Reparatur von Automobilen",
    "sg:phone":"+41 32 313 41 93",
    "sg:postcode":"3232",
    "sg:province":"Bern",
    "wof:name":"Garage Loosli",
    "wof:placetype":"venue"
},
  "geometry": {"coordinates":[7.1036448479,47.0063171387],"type":"Point"}
}