{
  "type": "Feature",
  "properties": {
    "iso:country":"CH",
    "sg:address":"General Guisan-strasse 35",
    "sg:city":"Arlesheim",
    "sg:orig_category":"Wirtschaftspr\u00fcfung, Steuerberatung U Treuhand",
    "sg:phone":"+41 61 701 25 78",
    "sg:postcode":"4144",
    "sg:province":"Basel-Landschaft",
    "wof:name":"Obrist T.",
    "wof:placetype":"venue"
},
  "geometry": {"coordinates":[7.6142821312,47.5002174377],"type":"Point"}
}