{
  "type": "Feature",
  "properties": {
    "iso:country":"CH",
    "sg:address":"M\u00fchlestrasse 148",
    "sg:city":"Aristau",
    "sg:orig_category":"Hoch U Tiefbau",
    "sg:phone":"+41 79 401 06 37",
    "sg:postcode":"5628",
    "sg:province":"Aargau",
    "wof:name":"Hans & Nancy Fischli Baugesch\u00e4ft",
    "wof:placetype":"venue"
},
  "geometry": {"coordinates":[8.362739563,47.2966766357],"type":"Point"}
}