{
  "type": "Feature",
  "properties": {
    "addr:full":"Burgdorfstrasse 7 Alchenfl\u00fch Bern 3422",
    "addr:housenumber":"7",
    "addr:postcode":"3422",
    "addr:street":"Burgdorfstrasse",
    "iso:country":"CH",
    "sg:address":"Burgdorfstrasse 7",
    "sg:city":"Alchenfl\u00fch",
    "sg:orig_category":"Bauschreinerei Herstellung von Konstruktionsteilen, Fertigbauteilen U Ausbauelementen aus Holz",
    "sg:phone":"+41 34 445 22 57",
    "sg:postcode":"3422",
    "sg:province":"Bern",
    "wof:name":"Anton Kr\u00e4uchi, Bau Und M\u00f6belschreinerei",
    "wof:placetype":"venue"
},
  "geometry": {"coordinates":[7.581659,47.081802],"type":"Point"}
}