{
  "type": "Feature",
  "properties": {
    "iso:country":"CH",
    "sg:address":"Grenzweg 2",
    "sg:city":"Dornach",
    "sg:orig_category":"Verwaltung von Immobilien Wirtschaftspr\u00fcfung, Steuerberatung U Treuhand",
    "sg:phone":"+41 81 837 05 40",
    "sg:postcode":"4143",
    "sg:province":"Solothurn",
    "wof:name":"Parsonia Ag",
    "wof:placetype":"venue"
},
  "geometry": {"coordinates":[9.8361730576,46.4885673523],"type":"Point"}
}