{
  "type": "Feature",
  "properties": {
    "addr:full":"Obere Gasse 24 7000 Chur. Postfach Chur Graubunden 7002",
    "addr:housenumber":"24",
    "addr:postcode":"7000;postfach;7002",
    "addr:street":"Obere Gasse",
    "iso:country":"CH",
    "sg:address":"Obere Gasse 24 7000 Chur. Postfach",
    "sg:city":"Chur",
    "sg:orig_category":"Advokaturb\u00fcros",
    "sg:phone":"+41 81 257 04 31",
    "sg:postcode":"7002",
    "sg:province":"Graubunden",
    "wof:name":"Regula Str\u00e4ssler Advokaturb\u00fcro",
    "wof:placetype":"venue"
},
  "geometry": {"coordinates":[9.5309,46.848152],"type":"Point"}
}