{
  "type": "Feature",
  "properties": {
    "addr:full":"Bavurca Trin Graubunden 7014",
    "addr:postcode":"7014",
    "iso:country":"CH",
    "sg:address":"Bavurca",
    "sg:city":"Trin",
    "sg:orig_category":"Architekturb\u00fcros",
    "sg:phone":"+41 81 630 41 05",
    "sg:postcode":"7014",
    "sg:province":"Graubunden",
    "wof:name":"Ruedi Berchtold Architekturb\u00fcro",
    "wof:placetype":"venue"
},
  "geometry": {"coordinates":[9.364002,46.828598],"type":"Point"}
}