{
  "type": "Feature",
  "properties": {
    "iso:country":"CH",
    "sg:address":"Aufdorfstrasse 214",
    "sg:city":"M\u00e4nnedorf",
    "sg:orig_category":"Luft U Raumfahrzeugbau",
    "sg:postcode":"8708",
    "sg:province":"Z\u00fcrich",
    "wof:name":"Aircraft Paintwork Gmbh",
    "wof:placetype":"venue"
},
  "geometry": {"coordinates":[8.7022943497,47.2571983337],"type":"Point"}
}