{
  "type": "Feature",
  "properties": {
    "iso:country":"CH",
    "sg:address":"Morand Rue Marc 22",
    "sg:city":"Martigny",
    "sg:orig_category":"Interessenvertretungen",
    "sg:postcode":"1920",
    "sg:province":"Valais",
    "wof:name":"Fondation Lugeon Maurice",
    "wof:placetype":"venue"
},
  "geometry": {"coordinates":[6.5606098175,46.5287094116],"type":"Point"}
}