{
  "type": "Feature",
  "properties": {
    "addr:full":"Albisriederstrasse 169 Z\u00fcrich Z\u00fcrich 8047",
    "addr:housenumber":"169",
    "addr:postcode":"8047",
    "addr:street":"Albisriederstrasse",
    "iso:country":"CH",
    "sg:address":"Albisriederstrasse 169",
    "sg:city":"Z\u00fcrich",
    "sg:orig_category":"Detailhandel mit B\u00fcchern, Zeitungen, Schreib U Papeteriewaren",
    "sg:postcode":"8047",
    "sg:province":"Z\u00fcrich",
    "wof:name":"Hubertus-kiosk Frei",
    "wof:placetype":"venue"
},
  "geometry": {"coordinates":[8.498655,47.377411],"type":"Point"}
}