{
  "type": "Feature",
  "properties": {
    "iso:country":"CH",
    "sg:address":"Cl\u00e9menty Route De 38",
    "sg:city":"Nyon",
    "sg:orig_category":"Handels-H\u00e4user U Gesellschaften",
    "sg:phone":"+41 22 361 26 09",
    "sg:postcode":"1260",
    "sg:province":"Vaud",
    "wof:name":"Gonet Sybille",
    "wof:placetype":"venue"
},
  "geometry": {"coordinates":[6.2331562042,46.3797225952],"type":"Point"}
}