{
  "type": "Feature",
  "properties": {
    "iso:country":"CH",
    "sg:address":"Bernerring",
    "sg:city":"Arth",
    "sg:orig_category":"Tankstellen",
    "sg:postcode":"6415",
    "sg:province":"Schwyz",
    "wof:name":"Pfister Walter",
    "wof:placetype":"venue"
},
  "geometry": {"coordinates":[8.560256958,47.0407447815],"type":"Point"}
}