{
  "type": "Feature",
  "properties": {
    "addr:full":"Sagenrainstrasse 21 Fehraltorf Z\u00fcrich 8320",
    "addr:housenumber":"21",
    "addr:postcode":"8320",
    "addr:street":"Sagenrainstrasse",
    "iso:country":"CH",
    "sg:address":"Sagenrainstrasse 21",
    "sg:city":"Fehraltorf",
    "sg:orig_category":"Aktivit\u00e4ten der Krankenschwestern U Hebammen, Hauspflege",
    "sg:phone":"+41 19543050",
    "sg:postcode":"8320",
    "sg:province":"Z\u00fcrich",
    "wof:name":"Spitex-fehraltorf St\u00fctzpunkt",
    "wof:placetype":"venue"
},
  "geometry": {"coordinates":[8.751887,47.390896],"type":"Point"}
}