{
  "type": "Feature",
  "properties": {
    "iso:country":"CH",
    "sg:address":"Dorfstrasse 39",
    "sg:city":"Bellach",
    "sg:orig_category":"Unclassifiable Establishments",
    "sg:postcode":"4512",
    "sg:province":"Solothurn",
    "wof:name":"Edwin Rohrer Atelier Gestalten Mit Blumen",
    "wof:placetype":"venue"
},
  "geometry": {"coordinates":[7.4929180145,47.2122344971],"type":"Point"}
}