{
  "type": "Feature",
  "properties": {
    "iso:country":"CH",
    "sg:address":"Buchserstrasse 27",
    "sg:city":"D\u00e4llikon",
    "sg:orig_category":"Instandhaltung U Reparatur von Automobilen",
    "sg:phone":"+41 18443376",
    "sg:postcode":"8108",
    "sg:province":"Z\u00fcrich",
    "wof:name":"B\u00e4chtold Gerhard, Autospritzwerk",
    "wof:placetype":"venue"
},
  "geometry": {"coordinates":[8.438331604,47.4472465515],"type":"Point"}
}