{
  "type": "Feature",
  "properties": {
    "iso:country":"CH",
    "sg:address":"Grosspeterstrasse 25 4052 Basel. Postfach 3703",
    "sg:city":"Basel",
    "sg:orig_category":"Bauingenieurb\u00fcros Heizung L\u00fcftung Klima Bauingenieurb\u00fcros Sanit\u00e4r",
    "sg:phone":"+41 61 317 95 00",
    "sg:postcode":"4002",
    "sg:province":"Basel-Stadt",
    "wof:name":"M\u00fcller & Partner Ag",
    "wof:placetype":"venue"
},
  "geometry": {"coordinates":[7.60087,47.545349],"type":"Point"}
}