{
  "type": "Feature",
  "properties": {
    "iso:country":"CH",
    "sg:address":"Bahnhof Shop",
    "sg:city":"Bern",
    "sg:orig_category":"Detailhandel mit Lederwaren U Reiseartikeln",
    "sg:phone":"+41 31 311 20 39",
    "sg:postcode":"3011",
    "sg:province":"Bern",
    "wof:name":"Hummel Lederwaren Ag",
    "wof:placetype":"venue"
},
  "geometry": {"coordinates":[7.4409608841,46.948135376],"type":"Point"}
}