{
  "type": "Feature",
  "properties": {
    "addr:full":"Bahnhofstrasse 12 3600 Thun. Postfach Thun Bern 3601",
    "addr:housenumber":"12",
    "addr:postcode":"3600 thun. postfach;3601",
    "addr:street":"Bahnhofstrasse",
    "iso:country":"CH",
    "sg:address":"Bahnhofstrasse 12 3600 Thun. Postfach",
    "sg:city":"Thun",
    "sg:orig_category":"Detailhandel mit Brillen U anderen Sehhilfen Detailhandel mit medizinischen U orthop\u00e4dischen Artikel",
    "sg:phone":"+41 81 416 43 53",
    "sg:postcode":"3601",
    "sg:province":"Bern",
    "wof:name":"Micro-electric H\u00f6rger\u00e4te Ag",
    "wof:placetype":"venue"
},
  "geometry": {"coordinates":[9.841723,46.809452],"type":"Point"}
}