{
  "type": "Feature",
  "properties": {
    "addr:full":"Rue Du Mont-d'amin 11 Ch\u00e9zard-st-martin Neuch\u00e2tel 2054",
    "addr:housenumber":"11",
    "addr:postcode":"2054",
    "addr:street":"Rue Du Mont-D'Amin;Che\u0301Zard-St-Martin Neucha\u0302Tel",
    "iso:country":"CH",
    "sg:address":"Rue Du Mont-d'amin 11",
    "sg:city":"Ch\u00e9zard-st-martin",
    "sg:orig_category":"Datenverarbeitungsdienste Softwareentwicklung U beratung",
    "sg:phone":"+41 32 852 04 41",
    "sg:postcode":"2054",
    "sg:province":"Neuch\u00e2tel",
    "wof:name":"Pellaton Informatique",
    "wof:placetype":"venue"
},
  "geometry": {"coordinates":[6.403514,49.110985],"type":"Point"}
}