{
  "type": "Feature",
  "properties": {
    "iso:country":"CH",
    "sg:address":"Rue Du Mont-d'amin 11",
    "sg:city":"Ch\u00e9zard-st-martin",
    "sg:orig_category":"Datenverarbeitungsdienste Softwareentwicklung U beratung",
    "sg:phone":"+41 32 852 04 41",
    "sg:postcode":"2054",
    "sg:province":"Neuch\u00e2tel",
    "wof:name":"Pellaton Informatique",
    "wof:placetype":"venue"
},
  "geometry": {"coordinates":[6.403514,49.110985],"type":"Point"}
}