{
  "type": "Feature",
  "properties": {
    "iso:country":"CH",
    "sg:address":"Eichholzstrasse 25",
    "sg:city":"Gerlafingen",
    "sg:orig_category":"Mushrooms, Dried",
    "sg:phone":"+41 24 447 00 88",
    "sg:postcode":"4563",
    "sg:province":"Solothurn",
    "wof:name":"Ischy S.a.",
    "wof:placetype":"venue"
},
  "geometry": {"coordinates":[6.627248764,46.7982902527],"type":"Point"}
}