{
  "type": "Feature",
  "properties": {
    "iso:country":"CH",
    "sg:address":"Schl\u00f6sslipark 1",
    "sg:city":"Bottighofen",
    "sg:orig_category":"Kauf U Verkauf von Immobilien auf eigene Rechnung",
    "sg:phone":"+41 71 688 15 17",
    "sg:postcode":"8598",
    "sg:province":"Thurgau",
    "wof:name":"K\u00e4lin Verwaltungen",
    "wof:placetype":"venue"
},
  "geometry": {"coordinates":[9.2108850479,47.6436347961],"type":"Point"}
}