{
  "type": "Feature",
  "properties": {
    "iso:country":"CH",
    "sg:address":"Badenerstrasse 288",
    "sg:city":"Z\u00fcrich",
    "sg:orig_category":"RESTAURANTS: TEA-ROOMS",
    "sg:postcode":"8004",
    "sg:province":"Z\u00fcrich",
    "wof:name":"Battaya Restaurations Ag",
    "wof:placetype":"venue"
},
  "geometry": {"coordinates":[8.5136299133,47.3770446777],"type":"Point"}
}