{
  "type": "Feature",
  "properties": {
    "iso:country":"CH",
    "sg:address":"Martkgasse 14",
    "sg:city":"Interlaken",
    "sg:orig_category":"Herstellung von Schmuck, Gold U Silberschmiedwaren",
    "sg:phone":"+41 33 823 88 80",
    "sg:postcode":"3800",
    "sg:province":"Bern",
    "wof:name":"Goldschmied-atelier Habl\u00fctzel Peter",
    "wof:placetype":"venue"
},
  "geometry": {"coordinates":[7.8534431458,46.6856918335],"type":"Point"}
}