{
  "type": "Feature",
  "properties": {
    "addr:full":"Prattlerstrasse 6 Frenkendorf Basel-Landschaft 4402",
    "addr:housenumber":"6",
    "addr:postcode":"4402",
    "addr:street":"Prattlerstrasse",
    "iso:country":"CH",
    "sg:address":"Prattlerstrasse 6",
    "sg:city":"Frenkendorf",
    "sg:orig_category":"Allgemeiner Hoch U Tiefbau",
    "sg:postcode":"4402",
    "sg:province":"Basel-Landschaft",
    "wof:name":"J.m.j. Sagl",
    "wof:placetype":"venue"
},
  "geometry": {"coordinates":[8.783554,46.121967],"type":"Point"}
}