{
  "type": "Feature",
  "properties": {
    "iso:country":"CH",
    "sg:address":"Im Kindli 6442 Gersau. Postfach",
    "sg:city":"Gersau",
    "sg:orig_category":"Finanzierungsinstitutionen",
    "sg:phone":"+41 56 441 82 89",
    "sg:postcode":"6442",
    "sg:province":"Schwyz",
    "wof:name":"Di Fluri Dienstleistungen Finanzdienstleistungen. Liegenschaften Usw",
    "wof:placetype":"venue"
},
  "geometry": {"coordinates":[8.2182798386,47.4568939209],"type":"Point"}
}