{
  "type": "Feature",
  "properties": {
    "iso:country":"CH",
    "sg:address":"Maiengasse 19",
    "sg:city":"Basel",
    "sg:orig_category":"\u00dcbersetzungsb\u00fcros",
    "sg:phone":"+41 61 261 45 52",
    "sg:postcode":"4056",
    "sg:province":"Basel-Stadt",
    "wof:name":"Barbara Kugler Uebersetzungen",
    "wof:placetype":"venue"
},
  "geometry": {"coordinates":[7.5793008804,47.562046051],"type":"Point"}
}