{
  "type": "Feature",
  "properties": {
    "iso:country":"CH",
    "sg:address":"Via Industria 13 6814 Lamone. Postfach Caselle Postale 3333",
    "sg:city":"Lugano",
    "sg:orig_category":"Herstellung von pharmazeutischen Grundstoffen Herstellung von sonstigen organischen Grundstoffen U C",
    "sg:phone":"+41 91 923 96 61",
    "sg:postcode":"6900",
    "sg:province":"Ticino",
    "wof:name":"Siphar Sa",
    "wof:placetype":"venue"
},
  "geometry": {"coordinates":[8.9250164032,46.0383682251],"type":"Point"}
}