{
  "type": "Feature",
  "properties": {
    "iso:country":"CH",
    "sg:address":"Kasernenstrasse 43",
    "sg:city":"Liestal",
    "sg:orig_category":"Advokaturb\u00fcros",
    "sg:phone":"+41 61 272 68 76",
    "sg:postcode":"4410",
    "sg:province":"Basel-Landschaft",
    "wof:name":"Markus Mattle Advokaturb\u00fcro",
    "wof:placetype":"venue"
},
  "geometry": {"coordinates":[7.740131,47.481281],"type":"Point"}
}