{
  "type": "Feature",
  "properties": {
    "iso:country":"CH",
    "sg:address":"Parkstrasse 6",
    "sg:city":"Wabern",
    "sg:orig_category":"Bauspenglerei Sanit\u00e4rinstallation",
    "sg:phone":"+41 31 961 54 41",
    "sg:postcode":"3084",
    "sg:province":"Bern",
    "wof:name":"Schibli Haustechnik Ag",
    "wof:placetype":"venue"
},
  "geometry": {"coordinates":[7.448077,46.930557],"type":"Point"}
}