{
  "type": "Feature",
  "properties": {
    "iso:country":"CH",
    "sg:address":"Neugasse 2",
    "sg:city":"Bischofszell",
    "sg:orig_category":"Detailhandel mit M\u00f6beln Kunsthandel",
    "sg:phone":"+41 71 422 55 44",
    "sg:postcode":"9220",
    "sg:province":"Thurgau",
    "wof:name":"Peter St\u00e4cker Einrahmungen Bilder Wohnen",
    "wof:placetype":"venue"
},
  "geometry": {"coordinates":[9.2425403595,47.4934272766],"type":"Point"}
}