{
  "type": "Feature",
  "properties": {
    "iso:country":"CH",
    "sg:address":"Mattstrasse 45",
    "sg:city":"Netstal",
    "sg:orig_category":"Malerei Tapeziererei",
    "sg:phone":"+41 55 640 42 40",
    "sg:postcode":"8754",
    "sg:province":"Glarus",
    "wof:name":"Alois Michel Maler-& Tapezierergesch\u00e4ft",
    "wof:placetype":"venue"
},
  "geometry": {"coordinates":[9.0587406158,47.0565452576],"type":"Point"}
}