{
  "type": "Feature",
  "properties": {
    "iso:country":"CH",
    "sg:address":"Chrischonastrasse 50",
    "sg:city":"Muttenz",
    "sg:orig_category":"Innendekorationsateliers",
    "sg:phone":"+41 61 461 67 61",
    "sg:postcode":"4132",
    "sg:province":"Basel-Landschaft",
    "wof:name":"Vorhangatelier Trudy Kunkler",
    "wof:placetype":"venue"
},
  "geometry": {"coordinates":[7.6439270973,47.5317840576],"type":"Point"}
}