{
  "type": "Feature",
  "properties": {
    "iso:country":"CH",
    "sg:address":"Stadtbachstrasse 42 3012 Bern. Postfach",
    "sg:city":"Bern",
    "sg:orig_category":"Architektur U Ingenieurb\u00fcros",
    "sg:postcode":"3005",
    "sg:province":"Bern",
    "wof:name":"H + S Architekten H\u00fcrlimann + Scialli Architekturb\u00fcro, Bauarbeitenplanung U -ausf\u00fchrung",
    "wof:placetype":"venue"
},
  "geometry": {"coordinates":[7.431721,46.948929],"type":"Point"}
}