{
  "type": "Feature",
  "properties": {
    "iso:country":"CH",
    "sg:address":"Ch\u00e2teau",
    "sg:city":"Ch\u00e2tel-st-denis",
    "sg:orig_category":"Polizei",
    "sg:phone":"+41 21 948 28 38",
    "sg:postcode":"1618",
    "sg:province":"Fribourg",
    "wof:name":"Police Cantonale",
    "wof:placetype":"venue"
},
  "geometry": {"coordinates":[6.9015398026,46.5275344849],"type":"Point"}
}