{
  "type": "Feature",
  "properties": {
    "iso:country":"CH",
    "sg:address":"Untermattstrasse 14 8370 Sirnach. Postfach",
    "sg:city":"Sirnach",
    "sg:orig_category":"Grosshandel mit Nahrungsmitteln, Getr\u00e4nken U Tabakwaren ohne ausgepr\u00e4gten Schwerpunkt",
    "sg:postcode":"8370",
    "sg:province":"Thurgau",
    "wof:name":"Marmara Market Gmbh Lebensmittelladen Mit Frisch- U. Fertigprodukten Usw",
    "wof:placetype":"venue"
},
  "geometry": {"coordinates":[9.0030889511,47.4646606445],"type":"Point"}
}