{
  "type": "Feature",
  "properties": {
    "iso:country":"CH",
    "sg:address":"Grand-rue 68",
    "sg:city":"Cormondr\u00e8che",
    "sg:orig_category":"Allgemeiner Hochbau Stukkateurgewerbe, Gipserei U Verputzerei",
    "sg:phone":"+41 79 240 32 07",
    "sg:postcode":"2036",
    "sg:province":"Neuch\u00e2tel",
    "wof:name":"Serge Rappo Gypserie Peinture Fa\u00e7ades",
    "wof:placetype":"venue"
},
  "geometry": {"coordinates":[6.86803,46.981796],"type":"Point"}
}