{
  "type": "Feature",
  "properties": {
    "iso:country":"CH",
    "sg:address":"St\u00f6cken 6340 Baar. Postfach",
    "sg:city":"Baar",
    "sg:orig_category":"Unclassifiable Establishments",
    "sg:postcode":"6340",
    "sg:province":"Zug",
    "wof:name":"Reptech Gmbh Regie Und Reparaturarbeiten",
    "wof:placetype":"venue"
},
  "geometry": {"coordinates":[8.5162696838,47.2124862671],"type":"Point"}
}