{
  "type": "Feature",
  "properties": {
    "iso:country":"CH",
    "sg:address":"Kr\u00e4yigenweg 2",
    "sg:city":"Muri Bei Bern",
    "sg:classifiers":[
        {
            "category":"Utilities",
            "subcategory":"Cable",
            "type":"Services"
        }
    ],
    "sg:phone":"+41 31 950 64 64",
    "sg:postcode":"3074",
    "sg:province":"Bern",
    "sg:tags":[
        "tv",
        "medien",
        "u",
        "radio"
    ],
    "wof:name":"Cosmos Verlag",
    "wof:placetype":"venue"
},
  "geometry": {"coordinates":[7.488939,46.929062],"type":"Point"}
}