{
  "type": "Feature",
  "properties": {
    "iso:country":"CH",
    "sg:address":"Grand-rue 37",
    "sg:city":"Fribourg",
    "sg:orig_category":"Polizei",
    "sg:phone":"+41 32 931 10 17",
    "sg:postcode":"1700",
    "sg:province":"Fribourg",
    "wof:name":"Police Locale",
    "wof:placetype":"venue"
},
  "geometry": {"coordinates":[6.7489571571,47.0580978394],"type":"Point"}
}