{
  "type": "Feature",
  "properties": {
    "addr:full":"Fronwagplatz 28 Schaffhausen Schaffhausen 8200",
    "addr:housenumber":"28",
    "addr:postcode":"8200",
    "addr:street":"Fronwagplatz",
    "iso:country":"CH",
    "sg:address":"Fronwagplatz 28",
    "sg:city":"Schaffhausen",
    "sg:orig_category":"Allgemeiner Hoch U Tiefbau",
    "sg:postcode":"8200",
    "sg:province":"Schaffhausen",
    "wof:name":"Improved Piping Products International Europe Gmbh",
    "wof:placetype":"venue"
},
  "geometry": {"coordinates":[8.633652,47.697353],"type":"Point"}
}