{
  "type": "Feature",
  "properties": {
    "iso:country":"CH",
    "sg:address":"Langhagweg 47.",
    "sg:city":"Laufen",
    "sg:orig_category":"Instandhaltung U Reparatur von Automobilen",
    "sg:phone":"+41 55 282 47 17",
    "sg:postcode":"4242",
    "sg:province":"Basel-Landschaft",
    "wof:name":"Carrosserie Imlig",
    "wof:placetype":"venue"
},
  "geometry": {"coordinates":[8.9213428497,47.2407341003],"type":"Point"}
}