{
  "type": "Feature",
  "properties": {
    "iso:country":"CH",
    "sg:address":"Bourg-de-four Place Du 13 1204 Gen\u00e8ve. Postfach",
    "sg:city":"Gen\u00e8ve",
    "sg:orig_category":"RESTAURANTS: TEA-ROOMS",
    "sg:postcode":"1204",
    "sg:province":"Gen\u00e8ve",
    "wof:name":"Milos Petrovic",
    "wof:placetype":"venue"
},
  "geometry": {"coordinates":[6.1491270065,46.1999053955],"type":"Point"}
}