{
  "type": "Feature",
  "properties": {
    "iso:country":"CH",
    "sg:address":"Via San Salvatore 4",
    "sg:city":"Lugano",
    "sg:orig_category":"Erbringung von Dienstleistungen f\u00fcr Unternehmen Public-Relations-Agenturen",
    "sg:postcode":"6900",
    "sg:province":"Ticino",
    "wof:name":"Bv Buildings & Fittings B.v. Amsterdam, Succ. Di Bissione",
    "wof:placetype":"venue"
},
  "geometry": {"coordinates":[8.9492349625,46.0029067993],"type":"Point"}
}