{
  "type": "Feature",
  "properties": {
    "iso:country":"CH",
    "sg:address":"Rothenring 22",
    "sg:city":"Reussb\u00fchl",
    "sg:orig_category":"Herstellung von industriellen Prozesssteuerungsanlagen Softwareentwicklung U beratung",
    "sg:phone":"+41 41 260 96 30",
    "sg:postcode":"6015",
    "sg:province":"Luzern",
    "wof:name":"M\u00fcller & Waser Ag",
    "wof:placetype":"venue"
},
  "geometry": {"coordinates":[8.2779417038,47.0671272278],"type":"Point"}
}