{
  "type": "Feature",
  "properties": {
    "addr:full":"R\u00f6merstrasse 34 Reinach Basel-Landschaft 4153",
    "addr:housenumber":"34",
    "addr:postcode":"4153",
    "addr:street":"Roemerstrasse",
    "iso:country":"CH",
    "sg:address":"R\u00f6merstrasse 34",
    "sg:city":"Reinach",
    "sg:classifiers":[
        {
            "category":"Utilities",
            "subcategory":"Mobile Phone",
            "type":"Services"
        }
    ],
    "sg:phone":"+41 61 711 95 95",
    "sg:postcode":"4153",
    "sg:province":"Basel-Landschaft",
    "sg:tags":[
        "dictaphone",
        "accessory"
    ],
    "wof:name":"Butscher + Jost Ag",
    "wof:placetype":"venue"
},
  "geometry": {"coordinates":[7.596329,47.493294],"type":"Point"}
}