{
  "type": "Feature",
  "properties": {
    "iso:country":"CH",
    "sg:address":"Baarerstrasse 79 6300 Zug. Postfach",
    "sg:city":"Zug",
    "sg:orig_category":"Betrieb von Taxis",
    "sg:postcode":"6300",
    "sg:province":"Zug",
    "wof:name":"Top Taxi-kulja Taxi-transporte",
    "wof:placetype":"venue"
},
  "geometry": {"coordinates":[8.517719,47.1772],"type":"Point"}
}