{
  "type": "Feature",
  "properties": {
    "iso:country":"CH",
    "sg:address":"Oberburgstrasse 27",
    "sg:city":"Burgdorf",
    "sg:orig_category":"Maler U Glasergewerbe Malerei",
    "sg:phone":"+41 34 422 42 97",
    "sg:postcode":"3400",
    "sg:province":"Bern",
    "wof:name":"Zaugg Malerei Gmbh",
    "wof:placetype":"venue"
},
  "geometry": {"coordinates":[7.6233811378,47.0512771606],"type":"Point"}
}