{
  "type": "Feature",
  "properties": {
    "iso:country":"CH",
    "sg:city":"Basel",
    "sg:orig_category":"Medien, Medienproduktion",
    "sg:postcode":"4058",
    "sg:province":"Basel-Stadt",
    "wof:name":"Red Island",
    "wof:placetype":"venue"
},
  "geometry": {"coordinates":[7.58768,47.54874],"type":"Point"}
}