{
  "type": "Feature",
  "properties": {
    "iso:country":"CH",
    "sg:address":"Holeneich",
    "sg:city":"Tuggen",
    "sg:orig_category":"Gewinnung von Kies U Sand",
    "sg:phone":"+41 55 445 12 53",
    "sg:postcode":"8856",
    "sg:province":"Schwyz",
    "wof:name":"Baggerei Und Kies Ag, Hohleneich, Tuggen",
    "wof:placetype":"venue"
},
  "geometry": {"coordinates":[8.9194850922,47.1917381287],"type":"Point"}
}