{
  "type": "Feature",
  "properties": {
    "iso:country":"CH",
    "sg:address":"Hauptstrasse 18",
    "sg:city":"Riedern",
    "sg:classifiers":[
        {
            "category":"Restaurant",
            "type":"Food & Drink"
        }
    ],
    "sg:phone":"+41 55 640 49 57",
    "sg:postcode":"8750",
    "sg:province":"Glarus",
    "sg:tags":[
        "restaurants",
        "tea-rooms",
        "caterer"
    ],
    "wof:name":"El Local Gmbh Gastst\u00e4tten, Partyservice. Vertrieb Von Produkten U. Dienstleistungen Im Bereiche Gastronomie",
    "wof:placetype":"venue"
},
  "geometry": {"coordinates":[9.053071,47.048664],"type":"Point"}
}