{
  "type": "Feature",
  "properties": {
    "iso:country":"CH",
    "sg:address":"Rellikonstrasse 7",
    "sg:city":"Maur",
    "sg:classifiers":[
        {
            "category":"Government",
            "subcategory":"Fire Station",
            "type":"Public Place"
        }
    ],
    "sg:phone":"+41 18876400",
    "sg:postcode":"8124",
    "sg:province":"Z\u00fcrich",
    "sg:tags":[
        "development",
        "hardware",
        "soft"
    ],
    "wof:name":"Datalink Ag",
    "wof:placetype":"venue"
},
  "geometry": {"coordinates":[8.6707983017,47.3396682739],"type":"Point"}
}