{
  "type": "Feature",
  "properties": {
    "iso:country":"CH",
    "sg:address":"Bahnhofstrasse 14",
    "sg:city":"Chur",
    "sg:orig_category":"Herstellung von sonstigen Nahrungsmitteln",
    "sg:postcode":"7000",
    "sg:province":"Graubunden",
    "wof:name":"Fc Food Company Ag",
    "wof:placetype":"venue"
},
  "geometry": {"coordinates":[9.5310373306,46.8522262573],"type":"Point"}
}