{
  "type": "Feature",
  "properties": {
    "iso:country":"CH",
    "sg:address":"1610",
    "sg:city":"Ch\u00e2tillens",
    "sg:orig_category":"Herstellung von Metallkonstruktionen",
    "sg:phone":"+41 21 908 06 60",
    "sg:postcode":"1610",
    "sg:province":"Vaud",
    "wof:name":"Efsa",
    "wof:placetype":"venue"
},
  "geometry": {"coordinates":[6.8141222,46.5688323975],"type":"Point"}
}