{
  "type": "Feature",
  "properties": {
    "iso:country":"CH",
    "sg:address":"L\u00e4ngweiherstrasse 30",
    "sg:city":"Littau",
    "sg:orig_category":"Unternehmensberatung Wirtschaftspr\u00fcfung, Steuerberatung U Treuhand",
    "sg:phone":"+41 79 444 63 84",
    "sg:postcode":"6014",
    "sg:province":"Luzern",
    "wof:name":"Jm-controlling Johann Meier",
    "wof:placetype":"venue"
},
  "geometry": {"coordinates":[8.2782039642,47.053943634],"type":"Point"}
}