{
  "type": "Feature",
  "properties": {
    "iso:country":"CH",
    "sg:address":"Seestrasse 105",
    "sg:city":"Horn",
    "sg:orig_category":"Grosshandel mit Holz U Baustoffen Herstellung von keramischen Wand U Bodenfliesen U platten",
    "sg:phone":"+41 79 435 04 57",
    "sg:postcode":"9326",
    "sg:province":"Thurgau",
    "wof:name":"Roduit Carrelages S\u00e0rl",
    "wof:placetype":"venue"
},
  "geometry": {"coordinates":[6.9587798119,46.247959137],"type":"Point"}
}