{
  "type": "Feature",
  "properties": {
    "iso:country":"CH",
    "sg:address":"Dorfstrasse 126 8912 Obfelden. Postfach",
    "sg:city":"Obfelden",
    "sg:orig_category":"Grosshandel mit chemischen Erzeugnissen Herstellung von Werkzeugen",
    "sg:phone":"+41 56 633 52 35",
    "sg:postcode":"8912",
    "sg:province":"Z\u00fcrich",
    "wof:name":"Claylith Begr\u00fcnungs Ag",
    "wof:placetype":"venue"
},
  "geometry": {"coordinates":[8.4021253586,47.3476600647],"type":"Point"}
}