{
  "type": "Feature",
  "properties": {
    "addr:full":"Gartenweg 9 Magden Aargau 4312",
    "addr:housenumber":"9",
    "addr:postcode":"4312",
    "addr:street":"Gartenweg",
    "iso:country":"CH",
    "sg:address":"Gartenweg 9",
    "sg:city":"Magden",
    "sg:orig_category":"Buchverlag Verlagsgewerbe",
    "sg:phone":"+41 61 841 14 90",
    "sg:postcode":"4312",
    "sg:province":"Aargau",
    "wof:name":"Amtsblattmappen-verlag Ag",
    "wof:placetype":"venue"
},
  "geometry": {"coordinates":[7.810962,47.525681],"type":"Point"}
}