{
  "type": "Feature",
  "properties": {
    "iso:country":"CH",
    "sg:address":"Eggen",
    "sg:city":"Gurbr\u00fc",
    "sg:orig_category":"Bauschreinerei",
    "sg:phone":"+41 31 755 52 63",
    "sg:postcode":"3208",
    "sg:province":"Bern",
    "wof:name":"Gebr\u00fcder St\u00e4hli Ag Schreinerei",
    "wof:placetype":"venue"
},
  "geometry": {"coordinates":[7.218855,46.963837],"type":"Point"}
}