{
  "type": "Feature",
  "properties": {
    "addr:full":"Les Bossons-audry Arzier Vaud 1273",
    "addr:housenumber":"1273",
    "iso:country":"CH",
    "sg:address":"Les Bossons-audry",
    "sg:city":"Arzier",
    "sg:classifiers":[
        {
            "category":"Banks & Credit Unions",
            "subcategory":"Bank",
            "type":"Services"
        }
    ],
    "sg:phone":"+41 22 366 34 52",
    "sg:postcode":"1273",
    "sg:province":"Vaud",
    "wof:name":"Soci\u00e9t\u00e9 De Banque Suisse",
    "wof:placetype":"venue"
},
  "geometry": {"coordinates":[6.208725,46.460506],"type":"Point"}
}