{
  "type": "Feature",
  "properties": {
    "addr:full":"Dorfgasse 16 Horgen Z\u00fcrich 8810",
    "addr:housenumber":"16",
    "addr:postcode":"8810",
    "addr:street":"Dorfgasse",
    "iso:country":"CH",
    "sg:address":"Dorfgasse 16",
    "sg:city":"Horgen",
    "sg:orig_category":"Detailhandel mit Bekleidung Detailhandel mit Sportartikeln",
    "sg:phone":"+41 17259325",
    "sg:postcode":"8810",
    "sg:province":"Z\u00fcrich",
    "wof:name":"Coll Actions Sport-& Freizeitbekleidung",
    "wof:placetype":"venue"
},
  "geometry": {"coordinates":[8.599071,47.260391],"type":"Point"}
}