{
  "type": "Feature",
  "properties": {
    "iso:country":"CH",
    "sg:address":"Schwandenholzstrasse 182a",
    "sg:city":"Z\u00fcrich",
    "sg:orig_category":"Erbringung von Dienstleistungen f\u00fcr Unternehmen Grafikateliers, Design",
    "sg:phone":"+41 79 417 14 79",
    "sg:postcode":"8046",
    "sg:province":"Z\u00fcrich",
    "wof:name":"Sassine Comic Factory",
    "wof:placetype":"venue"
},
  "geometry": {"coordinates":[8.5241003036,47.424030304],"type":"Point"}
}