{
  "type": "Feature",
  "properties": {
    "iso:country":"CH",
    "sg:address":"Hofnet 24",
    "sg:city":"Obermumpf",
    "sg:orig_category":"Herstellung von pharmazeutischen Grundstoffen",
    "sg:postcode":"4324",
    "sg:province":"Aargau",
    "wof:name":"Germline Biotech Consulting Schr\u00f6der Markus",
    "wof:placetype":"venue"
},
  "geometry": {"coordinates":[7.9333200455,47.5305709839],"type":"Point"}
}