{
  "type": "Feature",
  "properties": {
    "iso:country":"CH",
    "sg:address":"Emmentalstrasse 59",
    "sg:city":"Oberburg",
    "sg:orig_category":"Gartenbau Landschaftsplanungsb\u00fcros U Gartenarchitekturb\u00fcros",
    "sg:phone":"+41 34 422 29 51",
    "sg:postcode":"3414",
    "sg:province":"Bern",
    "wof:name":"Benjamin Riesen Gartengestaltung",
    "wof:placetype":"venue"
},
  "geometry": {"coordinates":[7.6303138733,47.035358429],"type":"Point"}
}