{
  "type": "Feature",
  "properties": {
    "iso:country":"CH",
    "sg:address":"Rue De Praz-palud 2",
    "sg:city":"Echallens",
    "sg:orig_category":"Detailhandel mit Zeitungen U Zeitschriften Kioske",
    "sg:phone":"+41 21 882 21 60",
    "sg:postcode":"1040",
    "sg:province":"Vaud",
    "wof:name":"Carole Ratton Kiosque",
    "wof:placetype":"venue"
},
  "geometry": {"coordinates":[6.6356949806,46.6391983032],"type":"Point"}
}