{
  "type": "Feature",
  "properties": {
    "iso:country":"CH",
    "sg:address":"Bahnhofstrasse 16",
    "sg:city":"Oensingen",
    "sg:orig_category":"Unternehmensberatung",
    "sg:phone":"+41 62 388 18 50",
    "sg:postcode":"4702",
    "sg:province":"Solothurn",
    "wof:name":"Heiniger Unternehmensberatung Ag",
    "wof:placetype":"venue"
},
  "geometry": {"coordinates":[7.7090492249,47.2852935791],"type":"Point"}
}