{
  "type": "Feature",
  "properties": {
    "iso:country":"CH",
    "sg:address":"Grubenstrasse 24-26",
    "sg:city":"Ostermundigen",
    "sg:orig_category":"Softwareentwicklung U beratung",
    "sg:phone":"+41 31 934 49 94",
    "sg:postcode":"3072",
    "sg:province":"Bern",
    "wof:name":"Joseph E. Beer Tellsoft",
    "wof:placetype":"venue"
},
  "geometry": {"coordinates":[7.4888658524,46.9598083496],"type":"Point"}
}