{
  "type": "Feature",
  "properties": {
    "iso:country":"CH",
    "sg:address":"Niederngasse 22",
    "sg:city":"Trogen",
    "sg:orig_category":"Gartenbau",
    "sg:phone":"+41 71 344 27 67",
    "sg:postcode":"9043",
    "sg:province":"Appenzell Ausserrhoden",
    "wof:name":"Wilfried K\u00fcnzler Gartenbau",
    "wof:placetype":"venue"
},
  "geometry": {"coordinates":[9.4645671844,47.4079322815],"type":"Point"}
}