{
  "type": "Feature",
  "properties": {
    "iso:country":"CH",
    "sg:address":"Zugerstrasse 17",
    "sg:city":"Cham",
    "sg:orig_category":"Sonstiger Grosshandel",
    "sg:phone":"+41 55 417 45 45",
    "sg:postcode":"6330",
    "sg:province":"Zug",
    "wof:name":"Contriz Sa",
    "wof:placetype":"venue"
},
  "geometry": {"coordinates":[8.7735757828,46.1541862488],"type":"Point"}
}