{
  "type": "Feature",
  "properties": {
    "iso:country":"CH",
    "sg:address":"Wanderstrasse 131",
    "sg:city":"Basel",
    "sg:orig_category":"Elektroinstallation Herstellung von nachrichtentechnischen Ger\u00e4ten U Einrichtungen",
    "sg:phone":"+41 81 911 55 44",
    "sg:postcode":"4054",
    "sg:province":"Basel-Stadt",
    "wof:name":"Wendi-com Deflorin",
    "wof:placetype":"venue"
},
  "geometry": {"coordinates":[9.2883176804,46.8262405396],"type":"Point"}
}