{
  "type": "Feature",
  "properties": {
    "iso:country":"CH",
    "sg:address":"Via Luigi Lavizzari 6 6830 Chiasso Casella Postale 126",
    "sg:city":"Chiasso",
    "sg:orig_category":"Fachdetailhandel in Verkaufsr\u00e4umen Grosshandel mit Foto U Kinoger\u00e4ten, feinmechanischen U optischen ",
    "sg:phone":"+41 79 620 24 19",
    "sg:postcode":"6830",
    "sg:province":"Ticino",
    "wof:name":"Roy Tower Sa",
    "wof:placetype":"venue"
},
  "geometry": {"coordinates":[9.0313053131,45.8347244263],"type":"Point"}
}