{
  "type": "Feature",
  "properties": {
    "iso:country":"CH",
    "sg:address":"Gottfried Keller-strasse 5",
    "sg:city":"Z\u00fcrich",
    "sg:orig_category":"Vermietung U Verpachtung von eigenen Immobilien",
    "sg:postcode":"8001",
    "sg:province":"Z\u00fcrich",
    "wof:name":"Habeas Ag",
    "wof:placetype":"venue"
},
  "geometry": {"coordinates":[9.4713726044,47.1645126343],"type":"Point"}
}