{
  "type": "Feature",
  "properties": {
    "iso:country":"CH",
    "sg:address":"Wolfsberg",
    "sg:city":"Bauma",
    "sg:orig_category":"Verwertung von Milch",
    "sg:postcode":"8494",
    "sg:province":"Z\u00fcrich",
    "wof:name":"Milchgenossenschaft Bad-wolfensberg",
    "wof:placetype":"venue"
},
  "geometry": {"coordinates":[8.883140564,47.3650817871],"type":"Point"}
}