{
  "type": "Feature",
  "properties": {
    "iso:country":"CH",
    "sg:address":"Rehhalten",
    "sg:city":"Grindelwald",
    "sg:orig_category":"Sportschulen Bergsteiger",
    "sg:phone":"+41 79 600 82 50",
    "sg:postcode":"3818",
    "sg:province":"Bern",
    "wof:name":"Rudolf Kaufmann Bergsteigerschule",
    "wof:placetype":"venue"
},
  "geometry": {"coordinates":[8.0470609665,46.6246109009],"type":"Point"}
}