{
  "type": "Feature",
  "properties": {
    "iso:country":"CH",
    "sg:address":"Scheideggstrasse 10",
    "sg:city":"Winterthur",
    "sg:classifiers":[
        {
            "category":"Restaurant",
            "type":"Food & Drink"
        }
    ],
    "sg:phone":"+41 52 232 46 65",
    "sg:postcode":"8400",
    "sg:province":"Z\u00fcrich",
    "wof:name":"Trattoria Gutschick",
    "wof:placetype":"venue"
},
  "geometry": {"coordinates":[8.7500619888,47.4917678833],"type":"Point"}
}