{
  "type": "Feature",
  "properties": {
    "iso:country":"CH",
    "sg:address":"Hauptstrasse 156",
    "sg:city":"M\u00f6nthal",
    "sg:classifiers":[
        {
            "category":"Restaurant",
            "type":"Food & Drink"
        }
    ],
    "sg:phone":"+41 56 284 13 93",
    "sg:postcode":"5237",
    "sg:province":"Aargau",
    "wof:name":"Restaurant Sternen",
    "wof:placetype":"venue"
},
  "geometry": {"coordinates":[8.1402435303,47.5186882019],"type":"Point"}
}