{
  "type": "Feature",
  "properties": {
    "iso:country":"CH",
    "sg:address":"Avenue De La Gare 45",
    "sg:city":"Rolle",
    "sg:orig_category":"Handels-H\u00e4user U Gesellschaften",
    "sg:phone":"+41 21 825 14 88",
    "sg:postcode":"1180",
    "sg:province":"Vaud",
    "wof:name":"Marcam Sa",
    "wof:placetype":"venue"
},
  "geometry": {"coordinates":[6.3372488022,46.462928772],"type":"Point"}
}