{
  "type": "Feature",
  "properties": {
    "iso:country":"CH",
    "sg:address":"Drusbergstrasse 34",
    "sg:city":"Horgen",
    "sg:orig_category":"Unclassifiable Establishments",
    "sg:postcode":"8810",
    "sg:province":"Z\u00fcrich",
    "wof:name":"Varela Alvarez Renovationen",
    "wof:placetype":"venue"
},
  "geometry": {"coordinates":[8.5976791382,47.2531700134],"type":"Point"}
}