{
  "type": "Feature",
  "properties": {
    "iso:country":"CH",
    "sg:address":"Bruderholzstrasse 60 4053 Basel. Postfach",
    "sg:city":"Basel",
    "sg:orig_category":"Grosshandel mit Holz U Bauelementen aus Holz Holzplattenwerke",
    "sg:phone":"+41 61 361 40 40",
    "sg:postcode":"4018",
    "sg:province":"Basel-Stadt",
    "wof:name":"K.f. Roser Ag Furniere, Schnittholz, Plattenmaterialien Usw; Fabrikation, Handel",
    "wof:placetype":"venue"
},
  "geometry": {"coordinates":[7.5938448906,47.5427360535],"type":"Point"}
}