{
  "type": "Feature",
  "properties": {
    "iso:country":"CH",
    "sg:address":"Chemin De B\u00e9r\u00e9e 10 1010 Lausanne Case Postale 172",
    "sg:city":"Lausanne",
    "sg:orig_category":"Architekturb\u00fcros",
    "sg:phone":"+41 19502029",
    "sg:postcode":"1010",
    "sg:province":"Vaud",
    "wof:name":"R\u00fcegg & Partner Gmbh",
    "wof:placetype":"venue"
},
  "geometry": {"coordinates":[8.796729,47.362259],"type":"Point"}
}