{
  "type": "Feature",
  "properties": {
    "iso:country":"CH",
    "sg:address":"Vazerolgasse 2",
    "sg:city":"Chur",
    "sg:orig_category":"Non-Classified Establishments",
    "sg:postcode":"7000",
    "sg:province":"Graubunden",
    "wof:name":"Olifer Sertissage, Oliveira & Fernandez Rodriguez",
    "wof:placetype":"venue"
},
  "geometry": {"coordinates":[6.8367271423,47.11328125],"type":"Point"}
}