{
  "type": "Feature",
  "properties": {
    "iso:country":"CH",
    "sg:address":"Place De La Gare 1837 Ch\u00e2teau-d'oex. Postfach",
    "sg:city":"Muttenz",
    "sg:orig_category":"Detailhandel mit B\u00fcchern, Zeitungen, Schreib U Papeteriewaren",
    "sg:phone":"+41 26 924 79 92",
    "sg:postcode":"4132",
    "sg:province":"Basel-Landschaft",
    "wof:name":"K Kiosk Ag",
    "wof:placetype":"venue"
},
  "geometry": {"coordinates":[2.9350440502,46.7318763733],"type":"Point"}
}