{
  "type": "Feature",
  "properties": {
    "iso:country":"CH",
    "sg:address":"Grenzacherstrasse 419",
    "sg:city":"Basel",
    "sg:orig_category":"Sportvereine Ballsport Tennis",
    "sg:phone":"+41 61 601 20 70",
    "sg:postcode":"4058",
    "sg:province":"Basel-Stadt",
    "wof:name":"Tennisclub Am Bahndamm",
    "wof:placetype":"venue"
},
  "geometry": {"coordinates":[7.6249299049,47.5620613098],"type":"Point"}
}