{
  "type": "Feature",
  "properties": {
    "iso:country":"CH",
    "sg:address":"Obere Gasse 31",
    "sg:city":"Chur",
    "sg:orig_category":"RESTAURANTS: TEA-ROOMS",
    "sg:phone":"+41 81 252 35 76",
    "sg:postcode":"7000",
    "sg:province":"Graubunden",
    "wof:name":"Caf\u00e9 Zschaler, Silvia Willi + Mirco Massignani",
    "wof:placetype":"venue"
},
  "geometry": {"coordinates":[9.5306491852,46.8479156494],"type":"Point"}
}