{
  "type": "Feature",
  "properties": {
    "iso:country":"CH",
    "sg:address":"Bettenhausenstrasse 4",
    "sg:city":"Herzogenbuchsee",
    "sg:orig_category":"Reparatur von Schuhen U Lederwaren",
    "sg:phone":"+41 62 961 28 28",
    "sg:postcode":"3360",
    "sg:province":"Bern",
    "wof:name":"Walter Lienhard Mech.schuhwerkst\u00e4tte",
    "wof:placetype":"venue"
},
  "geometry": {"coordinates":[7.7059340477,47.1872177124],"type":"Point"}
}