{
  "type": "Feature",
  "properties": {
    "iso:country":"CH",
    "sg:address":"Kirchgasse 4",
    "sg:city":"Lenzburg",
    "sg:orig_category":"RESTAURANTS: TEA-ROOMS",
    "sg:postcode":"5600",
    "sg:province":"Aargau",
    "wof:name":"Ortelli F.",
    "wof:placetype":"venue"
},
  "geometry": {"coordinates":[8.1793060303,47.3871841431],"type":"Point"}
}