{
  "type": "Feature",
  "properties": {
    "iso:country":"CH",
    "sg:address":"Heinrichstrasse 65",
    "sg:city":"Z\u00fcrich",
    "sg:orig_category":"Reiseb\u00fcros",
    "sg:phone":"+41 71 912 46 46",
    "sg:postcode":"8005",
    "sg:province":"Z\u00fcrich",
    "wof:name":"Valentina Reisen Gmbh",
    "wof:placetype":"venue"
},
  "geometry": {"coordinates":[9.0431556702,47.4620552063],"type":"Point"}
}