{
  "type": "Feature",
  "properties": {
    "iso:country":"CH",
    "sg:address":"Einkaufszentrum Telli",
    "sg:city":"Aarau",
    "sg:orig_category":"Detailhandel mit Schuhen",
    "sg:phone":"+41 62 822 30 65",
    "sg:postcode":"5004",
    "sg:province":"Aargau",
    "wof:name":"Karl V\u00f6gele Ag",
    "wof:placetype":"venue"
},
  "geometry": {"coordinates":[8.0499897003,47.3918151855],"type":"Point"}
}