{
  "type": "Feature",
  "properties": {
    "iso:country":"CH",
    "sg:address":"7560 Martina. Postfach",
    "sg:city":"Martina",
    "sg:orig_category":"Detailhandel mit B\u00fcchern, Zeitungen, Schreib U Papeteriewaren",
    "sg:phone":"+41 81 866 36 56",
    "sg:postcode":"7560",
    "sg:province":"Graubunden",
    "wof:name":"Albertini Beatrice",
    "wof:placetype":"venue"
},
  "geometry": {"coordinates":[10.463121,46.88401],"type":"Point"}
}