{
  "type": "Feature",
  "properties": {
    "addr:full":"Uferstrasse 90 Basel Basel-Stadt 4057",
    "addr:housenumber":"90",
    "addr:postcode":"4057",
    "addr:street":"Uferstrasse",
    "iso:country":"CH",
    "sg:address":"Uferstrasse 90",
    "sg:city":"Basel",
    "sg:orig_category":"Binnenschiffahrt",
    "sg:phone":"+41 61 638 82 00",
    "sg:postcode":"4057",
    "sg:province":"Basel-Stadt",
    "wof:name":"Stolt-nielsen Ag Tankschiffahrt",
    "wof:placetype":"venue"
},
  "geometry": {"coordinates":[7.587141,47.582237],"type":"Point"}
}