{
  "type": "Feature",
  "properties": {
    "iso:country":"CH",
    "sg:address":"Rigistrasse 178 6340 Baar. Postfach 532",
    "sg:city":"Baar",
    "sg:orig_category":"Grosshandel mit Eisenwaren sowie Installationsbedarf f\u00fcr Gas, Wasser U Heizung Herstellung von Draht",
    "sg:phone":"+41 41 761 79 26",
    "sg:postcode":"6341",
    "sg:province":"Zug",
    "wof:name":"Taugwalder Wisi Import & Export",
    "wof:placetype":"venue"
},
  "geometry": {"coordinates":[8.5305099487,47.1919517517],"type":"Point"}
}