{
  "type": "Feature",
  "properties": {
    "iso:country":"CH",
    "sg:address":"Werkweg 3",
    "sg:city":"Arch",
    "sg:orig_category":"Herstellung von Metallkonstruktionen Stahl U Leichtmetallbau",
    "sg:phone":"+41 32 679 30 25",
    "sg:postcode":"3296",
    "sg:province":"Bern",
    "wof:name":"Metallbau Herren Ag",
    "wof:placetype":"venue"
},
  "geometry": {"coordinates":[7.4310297966,47.1654243469],"type":"Point"}
}