{
  "type": "Feature",
  "properties": {
    "iso:country":"CH",
    "sg:address":"Lausanne Rue De 53",
    "sg:city":"Gen\u00e8ve",
    "sg:orig_category":"Unclassifiable Establishments",
    "sg:postcode":"1202",
    "sg:province":"Gen\u00e8ve",
    "wof:name":"Tariket El-hanafi",
    "wof:placetype":"venue"
},
  "geometry": {"coordinates":[6.1461648941,46.2146224976],"type":"Point"}
}