{
  "type": "Feature",
  "properties": {
    "iso:country":"CH",
    "sg:address":"Zollstr. 87.",
    "sg:city":"Neuhausen",
    "sg:orig_category":"RESTAURANTS: TEA-ROOMS",
    "sg:postcode":"8212",
    "sg:province":"Schaffhausen",
    "wof:name":"Graf Maria",
    "wof:placetype":"venue"
},
  "geometry": {"coordinates":[8.6041793823,47.6783676147],"type":"Point"}
}