{
  "type": "Feature",
  "properties": {
    "iso:country":"CH",
    "sg:address":"B\u00fcchnerstrasse 28 8006 Z\u00fcrich. Postfach",
    "sg:city":"Z\u00fcrich",
    "sg:orig_category":"Non-Classified Establishments",
    "sg:postcode":"8001",
    "sg:province":"Z\u00fcrich",
    "wof:name":"Roth-production, Foto Und Filmproduktion Foto- U. Filmproduktionen, Locating Scouting U. Casting",
    "wof:placetype":"venue"
},
  "geometry": {"coordinates":[8.5506391525,47.3842658997],"type":"Point"}
}