{
  "type": "Feature",
  "properties": {
    "iso:country":"CH",
    "sg:address":"Rue De Fin-de-praz 26",
    "sg:city":"St-aubin-sauges",
    "sg:classifiers":[
        {
            "category":"Utilities",
            "subcategory":"Water",
            "type":"Services"
        }
    ],
    "sg:phone":"+41 32 835 40 40",
    "sg:postcode":"2024",
    "sg:province":"Neuch\u00e2tel",
    "sg:tags":[
        "treatment",
        "conditioning"
    ],
    "wof:name":"H2eau Concept S\u00e0rl",
    "wof:placetype":"venue"
},
  "geometry": {"coordinates":[6.7799458504,46.8968582153],"type":"Point"}
}