{
  "type": "Feature",
  "properties": {
    "iso:country":"CH",
    "sg:address":"Oberdorfstrasse 1",
    "sg:city":"Bellach",
    "sg:orig_category":"Erschliessung von Grundst\u00fccken",
    "sg:postcode":"4512",
    "sg:province":"Solothurn",
    "wof:name":"Senioren-wohnen Kirchenfeld - Genossenschaft F\u00fcr Preisg\u00fcnstiges Wohnenim Alter",
    "wof:placetype":"venue"
},
  "geometry": {"coordinates":[8.3174819946,47.2825775146],"type":"Point"}
}