{
  "type": "Feature",
  "properties": {
    "iso:country":"CH",
    "sg:address":"M\u00fclhauserstrasse 81",
    "sg:city":"Basel",
    "sg:orig_category":"Detailhandel mit M\u00f6beln Detailhandel mit M\u00f6beln U Haushaltsgegenst\u00e4nden",
    "sg:phone":"+41 61 322 63 33",
    "sg:postcode":"4056",
    "sg:province":"Basel-Stadt",
    "wof:name":"M\u00f6bel Gerstner Heimo, Inhaber M\u00fcller Hanspeter",
    "wof:placetype":"venue"
},
  "geometry": {"coordinates":[7.5784888268,47.5676689148],"type":"Point"}
}