{
  "type": "Feature",
  "properties": {
    "addr:full":"Nelkenstrasse 2 6032 Emmen. Postfach 460 Emmen Luzern 6032",
    "addr:housenumber":"2;460",
    "addr:postcode":"6032 emmen.;6032",
    "addr:street":"Nelkenstrasse;Postfach",
    "iso:country":"CH",
    "sg:address":"Nelkenstrasse 2 6032 Emmen. Postfach 460",
    "sg:city":"Emmen",
    "sg:orig_category":"Architektur U Ingenieurb\u00fcros Hoch U Tiefbau",
    "sg:phone":"+41 41 241 00 80",
    "sg:postcode":"6032",
    "sg:province":"Luzern",
    "wof:name":"Krubau Emmen Gmbh",
    "wof:placetype":"venue"
},
  "geometry": {"coordinates":[8.286231,47.084839],"type":"Point"}
}