{
  "type": "Feature",
  "properties": {
    "addr:full":"Greifengasse 7 Basel Basel-Stadt 4058",
    "addr:housenumber":"7",
    "addr:postcode":"4058",
    "addr:street":"Greifengasse",
    "iso:country":"CH",
    "sg:address":"Greifengasse 7",
    "sg:city":"Basel",
    "sg:classifiers":[
        {
            "category":"Real Estate",
            "subcategory":"Real Estate Operator",
            "type":"Services"
        }
    ],
    "sg:phone":"+41 61 683 34 40",
    "sg:postcode":"4058",
    "sg:province":"Basel-Stadt",
    "sg:tags":[
        "application",
        "asp",
        "provider"
    ],
    "wof:name":"316tn Interaktive Und Klassische Medien Gmbh",
    "wof:placetype":"venue"
},
  "geometry": {"coordinates":[7.591553,47.561104],"type":"Point"}
}