{
  "type": "Feature",
  "properties": {
    "iso:country":"CH",
    "sg:address":"Lindengasse 1",
    "sg:city":"Kaisten",
    "sg:orig_category":"Nationale Postdienste",
    "sg:phone":"+41 62 874 11 51",
    "sg:postcode":"5082",
    "sg:province":"Aargau",
    "wof:name":"Die Schweizerische Post",
    "wof:placetype":"venue"
},
  "geometry": {"coordinates":[8.0461769104,47.5395584106],"type":"Point"}
}