{
  "type": "Feature",
  "properties": {
    "iso:country":"CH",
    "sg:address":"Habich-dietschy-strasse 10",
    "sg:city":"Rheinfelden",
    "sg:orig_category":"Spielsalons",
    "sg:phone":"+41 61 831 13 10",
    "sg:postcode":"4310",
    "sg:province":"Aargau",
    "wof:name":"Ckr Casino-kurbrunnen Rheinfelden Ag",
    "wof:placetype":"venue"
},
  "geometry": {"coordinates":[7.7891788483,47.5532569885],"type":"Point"}
}