{
  "type": "Feature",
  "properties": {
    "iso:country":"CH",
    "sg:address":"Lyssachstrasse 13 3400 Burgdorf. Postfach 468",
    "sg:city":"Burgdorf",
    "sg:classifiers":[
        {
            "category":"Professional",
            "subcategory":"Employment Agencies",
            "type":"Services"
        }
    ],
    "sg:phone":"+41 34 423 23 83",
    "sg:postcode":"3401",
    "sg:province":"Bern",
    "sg:tags":[
        "personal",
        "u",
        "stellenvermittlung"
    ],
    "wof:name":"Bimo Unternehmungen Burgdorf Ag Personalvermittl.",
    "wof:placetype":"venue"
},
  "geometry": {"coordinates":[7.6236810684,47.0584869385],"type":"Point"}
}