{
  "type": "Feature",
  "properties": {
    "iso:country":"CH",
    "sg:address":"Buckstrasse 29",
    "sg:city":"Pfungen",
    "sg:orig_category":"Vereine Vogel-& Naturschutz",
    "sg:phone":"+41 52 315 33 52",
    "sg:postcode":"8422",
    "sg:province":"Z\u00fcrich",
    "wof:name":"Ornitholog.verein Pfungen",
    "wof:placetype":"venue"
},
  "geometry": {"coordinates":[8.6364336014,47.5124435425],"type":"Point"}
}