{
  "type": "Feature",
  "properties": {
    "iso:country":"CH",
    "sg:address":"St\u00e4dtlistrasse 9",
    "sg:city":"Dallenwil",
    "sg:orig_category":"Personal U Stellenvermittlung Unternehmensberatung",
    "sg:phone":"+41 79 208 39 75",
    "sg:postcode":"6383",
    "sg:province":"Nidwalden",
    "wof:name":"Scala Schulung & Beratung",
    "wof:placetype":"venue"
},
  "geometry": {"coordinates":[8.3906335831,46.9323158264],"type":"Point"}
}