{
  "type": "Feature",
  "properties": {
    "iso:country":"CH",
    "sg:address":"Rue Centrale 31",
    "sg:city":"Orbe",
    "sg:orig_category":"Herstellung von Uhren Reparatur von Uhren U Schmuck",
    "sg:phone":"+41 22 781 24 48",
    "sg:postcode":"1350",
    "sg:province":"Vaud",
    "wof:name":"Patek, Philippe Sa",
    "wof:placetype":"venue"
},
  "geometry": {"coordinates":[6.1496648788,46.2038078308],"type":"Point"}
}