{
  "type": "Feature",
  "properties": {
    "iso:country":"CH",
    "sg:address":"Gloriastrasse 31 8006 Z\u00fcrich. Postfach",
    "sg:city":"Z\u00fcrich",
    "sg:orig_category":"Interessenvertretungen",
    "sg:postcode":"8001",
    "sg:province":"Z\u00fcrich",
    "wof:name":"Bloch Prof. Bruno-stiftung F\u00f6rderung Der Wissenschaftlichen Erforschung U. Heilung Des Krebses Usw",
    "wof:placetype":"venue"
},
  "geometry": {"coordinates":[8.5529594421,47.375869751],"type":"Point"}
}