{
  "type": "Feature",
  "properties": {
    "iso:country":"CH",
    "sg:address":"Casa Savius Via Cernesio 3",
    "sg:city":"Figino",
    "sg:orig_category":"Maler U Glasergewerbe Malerei",
    "sg:phone":"+41 81 933 17 90",
    "sg:postcode":"6918",
    "sg:province":"Ticino",
    "wof:name":"Collenberg Maler Und Gipser Ag",
    "wof:placetype":"venue"
},
  "geometry": {"coordinates":[9.1225099564,46.7561416626],"type":"Point"}
}