{
  "type": "Feature",
  "properties": {
    "iso:country":"CH",
    "sg:address":"Bielstrasse 5",
    "sg:city":"Br\u00fcttelen",
    "sg:orig_category":"Maurerarbeiten",
    "sg:phone":"+41 32 313 42 69",
    "sg:postcode":"2578",
    "wof:name":"Marcel J\u00f6rg Maurergesch\u00e4ft",
    "wof:placetype":"venue"
},
  "geometry": {"coordinates":[7.1482157707,47.0223846436],"type":"Point"}
}