{
  "type": "Feature",
  "properties": {
    "iso:country":"CH",
    "sg:address":"Dorfstrasse 24 8834 Schindellegi. Postfach",
    "sg:city":"Schindellegi",
    "sg:orig_category":"Non-Classified Establishments",
    "sg:postcode":"8834",
    "sg:province":"Schwyz",
    "wof:name":"K\u00fchne Holding Ag",
    "wof:placetype":"venue"
},
  "geometry": {"coordinates":[8.7104692459,47.1758460999],"type":"Point"}
}