{
  "type": "Feature",
  "properties": {
    "iso:country":"CH",
    "sg:address":"Chleeacherweg 15 8634 Hombrechtikon. Postfach 210",
    "sg:city":"Hombrechtikon",
    "sg:orig_category":"Grosshandel mit sonstigen Maschinen U Ausr\u00fcstungen f\u00fcr Industrie, Handel U Schiffahrt Herstellung vo",
    "sg:phone":"+41 19365959",
    "sg:postcode":"8634",
    "sg:province":"Z\u00fcrich",
    "wof:name":"Mtp, Mig-tig-plasma Ag",
    "wof:placetype":"venue"
},
  "geometry": {"coordinates":[8.7572603226,47.3070106506],"type":"Point"}
}