{
  "type": "Feature",
  "properties": {
    "iso:country":"CH",
    "sg:address":"1870",
    "sg:city":"Monthey",
    "sg:orig_category":"Dachdeckerei Zimmerei, Dachdeckerei, Bauspenglerei U Abdichtung",
    "sg:phone":"+41 41 670 15 60",
    "sg:postcode":"1870",
    "sg:province":"Valais",
    "wof:name":"Durrer W., Dach Und Wand Ag",
    "wof:placetype":"venue"
},
  "geometry": {"coordinates":[8.275775,46.941643],"type":"Point"}
}