{
  "type": "Feature",
  "properties": {
    "addr:full":"Poststrasse 22 Chur Graubunden 7000",
    "addr:housenumber":"22",
    "addr:postcode":"7000",
    "addr:street":"Poststrasse",
    "iso:country":"CH",
    "sg:address":"Poststrasse 22",
    "sg:city":"Chur",
    "sg:orig_category":"Detailhandel mit B\u00fcchern Versandhandel",
    "sg:phone":"+41 81 353 23 53",
    "sg:postcode":"7000",
    "sg:province":"Graubunden",
    "wof:name":"Strub Buchhandlung Nachf. C. L\u00fctscher & S. Haas",
    "wof:placetype":"venue"
},
  "geometry": {"coordinates":[9.532265,46.849297],"type":"Point"}
}