{
  "type": "Feature",
  "properties": {
    "iso:country":"CH",
    "sg:address":"Rue Du Simplon 52",
    "sg:city":"Martigny",
    "sg:orig_category":"Reparatur von Uhren U Schmuck",
    "sg:phone":"+41 27 722 12 74",
    "sg:postcode":"1920",
    "sg:province":"Valais",
    "wof:name":"Bernard Gallay Horloger",
    "wof:placetype":"venue"
},
  "geometry": {"coordinates":[7.0815320015,46.1043319702],"type":"Point"}
}