{
  "type": "Feature",
  "properties": {
    "iso:country":"CH",
    "sg:address":"Brunnenwisenstrasse 50",
    "sg:city":"Uster",
    "sg:orig_category":"Sportvereine",
    "sg:postcode":"8610",
    "sg:province":"Z\u00fcrich",
    "wof:name":"Z\u00fcrcher Cricket-verein",
    "wof:placetype":"venue"
},
  "geometry": {"coordinates":[8.7164840698,47.3541870117],"type":"Point"}
}