{
  "type": "Feature",
  "properties": {
    "iso:country":"CH",
    "sg:address":"8000 Z\u00fcrich. Postfach 1156",
    "sg:city":"Kloten",
    "sg:orig_category":"Interessenvertretungen Sonstige Institutionen des Sozialwesens ohne Beherbergung",
    "sg:phone":"+41 14912627",
    "sg:postcode":"8302",
    "sg:province":"Z\u00fcrich",
    "wof:name":"Weisser Ring Gemeinn\u00fctz.nationaler Verein",
    "wof:placetype":"venue"
},
  "geometry": {"coordinates":[8.5380096436,47.3690910339],"type":"Point"}
}