{
  "type": "Feature",
  "properties": {
    "iso:country":"CH",
    "sg:address":"L\u00e9man Avenue Du 12 1000 Lausanne. Postfach",
    "sg:city":"Lausanne",
    "sg:orig_category":"Non-Classified Establishments",
    "sg:postcode":"1000",
    "sg:province":"Vaud",
    "wof:name":"L'herboriste Messieurs Cassano Rino Et Wallimann Thomas Droguerie-herboristerie",
    "wof:placetype":"venue"
},
  "geometry": {"coordinates":[6.6947751045,46.5545883179],"type":"Point"}
}