{
  "type": "Feature",
  "properties": {
    "iso:country":"CH",
    "sg:address":"Badenerstrasse 621 8048 Z\u00fcrich. Postfach",
    "sg:city":"Z\u00fcrich",
    "sg:orig_category":"Grosshandel mit Textilien",
    "sg:phone":"+41 71 220 35 75",
    "sg:postcode":"8048",
    "sg:province":"Z\u00fcrich",
    "wof:name":"Dragon Streetwear Minjire & Teixeira",
    "wof:placetype":"venue"
},
  "geometry": {"coordinates":[9.4732599258,47.1659355164],"type":"Point"}
}