{
  "type": "Feature",
  "properties": {
    "iso:country":"CH",
    "sg:address":"6707",
    "sg:city":"Iragna",
    "sg:orig_category":"Verwaltung von Immobilien",
    "sg:phone":"+41 91 862 14 54",
    "sg:postcode":"6707",
    "sg:province":"Ticino",
    "wof:name":"La Botteguccia Di Nigro Angela",
    "wof:placetype":"venue"
},
  "geometry": {"coordinates":[8.9680175781,46.330280304],"type":"Point"}
}