{
  "type": "Feature",
  "properties": {
    "iso:country":"CH",
    "sg:address":"Route Du Moulin-roget 13",
    "sg:city":"Avully",
    "sg:orig_category":"Vermittlungen Wohnungs-Agenturen,",
    "sg:postcode":"1237",
    "sg:province":"Gen\u00e8ve",
    "wof:name":"A1 Relocation Sprenger & Mayor",
    "wof:placetype":"venue"
},
  "geometry": {"coordinates":[6.0004720688,46.1692314148],"type":"Point"}
}