{
  "type": "Feature",
  "properties": {
    "iso:country":"CH",
    "sg:address":"Masanserstrasse 245",
    "sg:city":"Chur",
    "sg:orig_category":"Unclassifiable Establishments",
    "sg:postcode":"7000",
    "sg:province":"Graubunden",
    "wof:name":"Baunova Holding Ag",
    "wof:placetype":"venue"
},
  "geometry": {"coordinates":[8.470454216,47.4502639771],"type":"Point"}
}