{
  "type": "Feature",
  "properties": {
    "iso:country":"CH",
    "sg:address":"Wolfwilerweg 11",
    "sg:city":"H\u00e4rkingen",
    "sg:orig_category":"Sonstige Bauinstallation Sonstiges Reinigungsgewerbe",
    "sg:postcode":"4624",
    "sg:province":"Solothurn",
    "wof:name":"Professional Light A.br\u00e4ndli",
    "wof:placetype":"venue"
},
  "geometry": {"coordinates":[7.8212580681,47.3001785278],"type":"Point"}
}