{
  "type": "Feature",
  "properties": {
    "iso:country":"CH",
    "sg:address":"Oberdorf 23",
    "sg:city":"Zeiningen",
    "sg:orig_category":"Architektur U Ingenieurb\u00fcros",
    "sg:phone":"+41 61 851 18 77",
    "sg:postcode":"4314",
    "sg:province":"Aargau",
    "wof:name":"Maass + Partner",
    "wof:placetype":"venue"
},
  "geometry": {"coordinates":[7.868158,47.541836],"type":"Point"}
}