{
  "type": "Feature",
  "properties": {
    "iso:country":"CH",
    "sg:address":"Mariahilfstrasse 6",
    "sg:city":"Tafers",
    "sg:orig_category":"Instandhaltung U Reparatur von Automobilen",
    "sg:phone":"+41 91 683 16 93",
    "sg:postcode":"1712",
    "sg:province":"Fribourg",
    "wof:name":"Sergio Robbiani Autoelettricit\u00e0",
    "wof:placetype":"venue"
},
  "geometry": {"coordinates":[9.0503702164,45.870098114],"type":"Point"}
}