{
  "type": "Feature",
  "properties": {
    "iso:country":"CH",
    "sg:address":"Aeulistrasse 10",
    "sg:city":"Wangs",
    "sg:classifiers":[
        {
            "category":"Manufacturing",
            "subcategory":"Building Materials",
            "type":"Manufacturing & Wholesale Goods"
        }
    ],
    "sg:phone":"+41 81 720 04 56",
    "sg:postcode":"7323",
    "sg:province":"St. Gallen",
    "sg:tags":[
        "technique",
        "thin-film"
    ],
    "wof:name":"Reinhardt Microtech Ag",
    "wof:placetype":"venue"
},
  "geometry": {"coordinates":[9.4457902908,47.0292816162],"type":"Point"}
}