{
  "type": "Feature",
  "properties": {
    "iso:country":"CH",
    "sg:address":"Quai Jeanrenaud 3 2000 Neuenburg. Postfach",
    "sg:city":"Neuenburg",
    "sg:orig_category":"Grosshandel mit Nahrungsmitteln, Getr\u00e4nken U Tabakwaren ohne ausgepr\u00e4gten Schwerpunkt",
    "sg:postcode":"2000",
    "sg:province":"Neuch\u00e2tel",
    "wof:name":"Philip Morris Vietnam Sa",
    "wof:placetype":"venue"
},
  "geometry": {"coordinates":[6.9002451897,46.9806213379],"type":"Point"}
}