{
  "type": "Feature",
  "properties": {
    "addr:full":"Avenue De Cour 7 Lausanne Vaud 1007",
    "addr:housenumber":"7",
    "addr:postcode":"1007",
    "addr:street":"Avenue De Cour",
    "iso:country":"CH",
    "sg:address":"Avenue De Cour 7",
    "sg:city":"Lausanne",
    "sg:orig_category":"Arztpraxen",
    "sg:phone":"+41 21 617 96 86",
    "sg:postcode":"1007",
    "sg:province":"Vaud",
    "wof:name":"Dr M\u00e9d. Dominique Mottaz M\u00e9decin Sp\u00e9cialiste Fmh",
    "wof:placetype":"venue"
},
  "geometry": {"coordinates":[6.626354,46.511971],"type":"Point"}
}