{
  "type": "Feature",
  "properties": {
    "iso:country":"CH",
    "sg:address":"Rue Du Bourg 51",
    "sg:city":"Martigny",
    "sg:classifiers":[
        {
            "category":"Restaurant",
            "type":"Food & Drink"
        }
    ],
    "sg:phone":"+41 27 722 00 57",
    "sg:postcode":"1920",
    "sg:province":"Valais",
    "wof:name":"Chapiteau Romain Chez Berto Wagon-restaurant",
    "wof:placetype":"venue"
},
  "geometry": {"coordinates":[7.0635538101,46.0900688171],"type":"Point"}
}