{
  "type": "Feature",
  "properties": {
    "iso:country":"CH",
    "sg:address":"Obere Bahnstrasse 3",
    "sg:city":"K\u00f6lliken",
    "sg:orig_category":"Maschinenbau Mechanische Werkst\u00e4tten",
    "sg:phone":"+41 79 330 42 40",
    "sg:postcode":"5742",
    "sg:province":"Aargau",
    "wof:name":"Mauch Ag",
    "wof:placetype":"venue"
},
  "geometry": {"coordinates":[8.0254573822,47.3306236267],"type":"Point"}
}