{
  "type": "Feature",
  "properties": {
    "iso:country":"CH",
    "sg:address":"Matschilsstrasse 23 9495 Triesen. Postfach 555",
    "sg:city":"Triesen",
    "sg:orig_category":"Technische, physikalische U chemische Untersuchung",
    "sg:phone":"+423 392 37 70",
    "sg:postcode":"9495",
    "wof:name":"Fachema Forschungs- Anstalt F\u00fcr Wiederverwertung",
    "wof:placetype":"venue"
},
  "geometry": {"coordinates":[9.5300531387,47.115272522],"type":"Point"}
}