{
  "type": "Feature",
  "properties": {
    "iso:country":"CH",
    "sg:address":"Repfergasse 20",
    "sg:city":"Schaffhausen",
    "sg:orig_category":"Fachdetailhandel in Verkaufsr\u00e4umen",
    "sg:postcode":"8200",
    "sg:province":"Schaffhausen",
    "wof:name":"Silvershop Von Burg Altun",
    "wof:placetype":"venue"
},
  "geometry": {"coordinates":[8.6362419128,47.6978416443],"type":"Point"}
}