{
  "type": "Feature",
  "properties": {
    "iso:country":"CH",
    "sg:address":"Brunngasse 1 S\u00e4riswil 3033 Wohlen B. Bern. Postfach",
    "sg:city":"Innerberg-s\u00e4riswil",
    "sg:orig_category":"Mit dem Versicherungsgewerbe verbundene T\u00e4tigkeiten",
    "sg:postcode":"3044",
    "sg:province":"Bern",
    "wof:name":"Bg Assurances, Bielmann & Gobet Assurances; Gestion Et Conseils",
    "wof:placetype":"venue"
},
  "geometry": {"coordinates":[6.914659977,46.6908187866],"type":"Point"}
}