{
  "type": "Feature",
  "properties": {
    "iso:country":"CH",
    "sg:address":"Hardstrasse 68",
    "sg:city":"Neuenhof",
    "sg:orig_category":"Detailhandel mit Schuhen U Lederwaren Grosshandel mit Lederwaren U Reiseartikeln",
    "sg:postcode":"5432",
    "sg:province":"Aargau",
    "wof:name":"Andrea Napoli",
    "wof:placetype":"venue"
},
  "geometry": {"coordinates":[8.3299970627,47.4512023926],"type":"Point"}
}