{
  "type": "Feature",
  "properties": {
    "iso:country":"CH",
    "sg:address":"6015",
    "sg:city":"Reussb\u00fchl",
    "sg:orig_category":"Kantonalbanken",
    "sg:phone":"+41 41 206 38 80",
    "sg:postcode":"6015",
    "sg:province":"Luzern",
    "wof:name":"Luzerner Kantonalbank",
    "wof:placetype":"venue"
},
  "geometry": {"coordinates":[8.2813673019,47.0650291443],"type":"Point"}
}