{
  "type": "Feature",
  "properties": {
    "iso:country":"CH",
    "sg:address":"Uitikonerstrasse 11",
    "sg:city":"Schlieren",
    "sg:orig_category":"Gold- and Silberschmuck Detailhandel Herstellung von Schmuck, Gold U Silberschmiedwaren",
    "sg:phone":"+41 17308008",
    "sg:postcode":"8952",
    "sg:province":"Z\u00fcrich",
    "wof:name":"Hug Schmuck + Uhren Gmbh Waren, Bes. Schmuck-bijouterieartikel In Gold, Silber; Herst., Vertrieb Usw",
    "wof:placetype":"venue"
},
  "geometry": {"coordinates":[8.4482192993,47.3965759277],"type":"Point"}
}