{
  "type": "Feature",
  "properties": {
    "iso:country":"CH",
    "sg:address":"Dorfstrasse 27",
    "sg:city":"Wolfhalden",
    "sg:orig_category":"Herstellung von sonstigen landwirtschaftlichen Maschinen Schmieden",
    "sg:phone":"+41 71 891 16 89",
    "sg:postcode":"9427",
    "sg:province":"Appenzell Ausserrhoden",
    "wof:name":"Hofstetter & Co Mech.schmiede & Landmaschinen",
    "wof:placetype":"venue"
},
  "geometry": {"coordinates":[9.5489034653,47.4535827637],"type":"Point"}
}