{
  "type": "Feature",
  "properties": {
    "iso:country":"CH",
    "sg:address":"1148",
    "sg:city":"L'isle",
    "sg:orig_category":"Personenbef\u00f6rderung im Linienverkehr zu Land Personenbef\u00f6rderung im Nahverkehr",
    "sg:phone":"+41 79 622 54 20",
    "sg:postcode":"1148",
    "sg:province":"Vaud",
    "wof:name":"Sa Des Auto-transports Du Pied Du Jura Vaudois",
    "wof:placetype":"venue"
},
  "geometry": {"coordinates":[-93.47286224370001,46.1380386353],"type":"Point"}
}