{
  "type": "Feature",
  "properties": {
    "iso:country":"CH",
    "sg:address":"Avenue Ruchonnet 38 1003 Lausanne Case Postale 330",
    "sg:city":"Lausanne",
    "sg:orig_category":"Medizinische Labors",
    "sg:phone":"+41 32 913 79 55",
    "sg:postcode":"1001",
    "sg:province":"Vaud",
    "wof:name":"Laboratoire M\u00e9dical Des Internistes Associ\u00e9s",
    "wof:placetype":"venue"
},
  "geometry": {"coordinates":[6.8264021873,47.1004753113],"type":"Point"}
}