{
  "type": "Feature",
  "properties": {
    "iso:country":"CH",
    "sg:address":"Untergasse 22",
    "sg:city":"Ligerz",
    "sg:orig_category":"Grosshandel mit Getr\u00e4nken Rebbau",
    "sg:phone":"+41 32 315 23 24",
    "sg:postcode":"2514",
    "sg:province":"Bern",
    "wof:name":"Steiner Jun., Charles",
    "wof:placetype":"venue"
},
  "geometry": {"coordinates":[7.1419110298,47.0906524658],"type":"Point"}
}