{
  "type": "Feature",
  "properties": {
    "iso:country":"CH",
    "sg:address":"B\u00f6ltschi",
    "sg:city":"Rothenburg",
    "sg:orig_category":"Interessenvertretungen",
    "sg:phone":"+41 41 280 63 44",
    "sg:postcode":"6023",
    "sg:province":"Luzern",
    "wof:name":"Stiftung F\u00fcr Wohnbauten Im Bertiswilerhof",
    "wof:placetype":"venue"
},
  "geometry": {"coordinates":[8.255944252,47.1025924683],"type":"Point"}
}