{
  "type": "Feature",
  "properties": {
    "iso:country":"CH",
    "sg:address":"Via San Gottardo",
    "sg:city":"Cadenazzo",
    "sg:orig_category":"Hoch U Tiefbau",
    "sg:phone":"+41 91 825 78 18",
    "sg:postcode":"6593",
    "sg:province":"Ticino",
    "wof:name":"Trevisan Mauro",
    "wof:placetype":"venue"
},
  "geometry": {"coordinates":[8.9511346817,46.1518859863],"type":"Point"}
}