{
  "type": "Feature",
  "properties": {
    "iso:country":"CH",
    "sg:address":"Studentenweg 18",
    "sg:city":"Engelberg",
    "sg:orig_category":"Wirtschaftspr\u00fcfung, Steuerberatung U Treuhand",
    "sg:phone":"+41 32892339",
    "sg:postcode":"6390",
    "sg:province":"Obwalden",
    "wof:name":"Tanner Barbara, Buchhaltung Und Sekretariat",
    "wof:placetype":"venue"
},
  "geometry": {"coordinates":[7.3613591194,47.0663986206],"type":"Point"}
}