{
  "type": "Feature",
  "properties": {
    "iso:country":"CH",
    "sg:address":"Baslerstrasse 103a",
    "sg:city":"Allschwil",
    "sg:orig_category":"Satzherstellung U Reproduktion",
    "sg:phone":"+41 56 611 00 70",
    "sg:postcode":"4123",
    "sg:province":"Basel-Landschaft",
    "wof:name":"Media Craft Renaud",
    "wof:placetype":"venue"
},
  "geometry": {"coordinates":[8.2660856247,47.3506774902],"type":"Point"}
}