{
  "type": "Feature",
  "properties": {
    "iso:country":"CH",
    "sg:address":"Langackerstrasse 8",
    "sg:city":"Lausen",
    "sg:orig_category":"Allgemeiner Hoch U Tiefbau",
    "sg:postcode":"4415",
    "sg:province":"Basel-Landschaft",
    "wof:name":"Conar Generalunternehmung Gmbh",
    "wof:placetype":"venue"
},
  "geometry": {"coordinates":[7.75595,47.471615],"type":"Point"}
}