{
  "type": "Feature",
  "properties": {
    "iso:country":"CH",
    "sg:address":"Grimselstrasse 3",
    "sg:city":"Basel",
    "sg:orig_category":"Sonstige Hilfs U Nebent\u00e4tigkeiten f\u00fcr die Luftfahrt",
    "sg:phone":"+41 33 972 22 11",
    "sg:postcode":"4054",
    "sg:province":"Basel-Stadt",
    "wof:name":"Bundesamt F\u00fcr Luftwaffe",
    "wof:placetype":"venue"
},
  "geometry": {"coordinates":[8.1094999313,46.7373313904],"type":"Point"}
}