{
  "type": "Feature",
  "properties": {
    "iso:country":"CH",
    "sg:address":"Landstrasse 19",
    "sg:city":"Kaiseraugst",
    "sg:classifiers":[
        {
            "category":"Communications",
            "subcategory":"Film & Video Production",
            "type":"Services"
        }
    ],
    "sg:phone":"+41 61 971 80 11",
    "sg:postcode":"4303",
    "sg:province":"Aargau",
    "sg:tags":[
        "videofilmherstellung",
        "u"
    ],
    "wof:name":"Thomas Kaufmann Kaufmann Film",
    "wof:placetype":"venue"
},
  "geometry": {"coordinates":[7.7216949463,47.5368080139],"type":"Point"}
}