{
  "type": "Feature",
  "properties": {
    "iso:country":"CH",
    "sg:address":"Geissbergstrasse 22",
    "sg:city":"Kloten",
    "sg:orig_category":"Non-Classified Establishments",
    "sg:postcode":"8302",
    "sg:province":"Z\u00fcrich",
    "wof:name":"Class Taxiservice Gmbh",
    "wof:placetype":"venue"
},
  "geometry": {"coordinates":[8.5915880203,47.4549865723],"type":"Point"}
}