{
  "type": "Feature",
  "properties": {
    "iso:country":"CH",
    "sg:address":"R\u00fcdigerstrasse 15 8045 Z\u00fcrich. Postfach",
    "sg:city":"Z\u00fcrich",
    "sg:orig_category":"Schweizerisch beherrschte Finanzgesellschaften",
    "sg:phone":"+41 71 913 97 77",
    "sg:postcode":"8027",
    "sg:province":"Z\u00fcrich",
    "wof:name":"Dtw Ag F\u00fcr Wohneigentum",
    "wof:placetype":"venue"
},
  "geometry": {"coordinates":[9.0316295624,47.4651184082],"type":"Point"}
}