{
  "type": "Feature",
  "properties": {
    "iso:country":"CH",
    "sg:address":"1544",
    "sg:city":"Gletterens",
    "sg:orig_category":"Herstellung von keramischen Wand U Bodenfliesen U platten",
    "sg:postcode":"1544",
    "sg:province":"Fribourg",
    "wof:name":"Ad Carrelage, Ansermet C\u00e9dric",
    "wof:placetype":"venue"
},
  "geometry": {"coordinates":[6.93708992,46.8953018188],"type":"Point"}
}