{
  "type": "Feature",
  "properties": {
    "iso:country":"CH",
    "sg:address":"Hauptstrasse 63",
    "sg:city":"Binningen",
    "sg:orig_category":"Detailhandel mit M\u00f6beln U Haushaltsgegenst\u00e4nden",
    "sg:phone":"+41 19314343",
    "sg:postcode":"4102",
    "sg:province":"Basel-Landschaft",
    "wof:name":"Messag Messe-service Ag Internationaler Messebau",
    "wof:placetype":"venue"
},
  "geometry": {"coordinates":[8.8015298843,47.3323783875],"type":"Point"}
}