{
  "type": "Feature",
  "properties": {
    "iso:country":"CH",
    "sg:address":"Route D'ambilly 41c",
    "sg:city":"Th\u00f4nex",
    "sg:orig_category":"Sanit\u00e4r, Heizungs U L\u00fcftungsinstallation",
    "sg:phone":"+41 27 934 26 15",
    "sg:postcode":"1226",
    "sg:province":"Gen\u00e8ve",
    "wof:name":"Furrer Theo, Haustechnik",
    "wof:placetype":"venue"
},
  "geometry": {"coordinates":[7.8033881187,46.2830123901],"type":"Point"}
}