{
  "type": "Feature",
  "properties": {
    "iso:country":"CH",
    "sg:address":"Oberer Hobacherweg 461",
    "sg:city":"Zetzwil",
    "sg:orig_category":"Vermietung U Verpachtung von eigenen Immobilien",
    "sg:phone":"+41 62 773 15 70",
    "sg:postcode":"5732",
    "sg:province":"Aargau",
    "wof:name":"Kh Immobilien Ag",
    "wof:placetype":"venue"
},
  "geometry": {"coordinates":[8.1535005569,47.2894325256],"type":"Point"}
}