{
  "type": "Feature",
  "properties": {
    "iso:country":"CH",
    "sg:address":"Elisabethenstrasse 3",
    "sg:city":"Z\u00fcrich",
    "sg:classifiers":[
        {
            "category":"Restaurant",
            "type":"Food & Drink"
        }
    ],
    "sg:phone":"+41 12411191",
    "sg:postcode":"8004",
    "sg:province":"Z\u00fcrich",
    "wof:name":"Restaurant Elisaburg",
    "wof:placetype":"venue"
},
  "geometry": {"coordinates":[8.5230770111,47.3724479675],"type":"Point"}
}