{
  "type": "Feature",
  "properties": {
    "iso:country":"CH",
    "sg:address":"Neunbrunnenstrasse 212",
    "sg:city":"Z\u00fcrich",
    "sg:orig_category":"Detailhandel mit M\u00f6beln U Haushaltsgegenst\u00e4nden",
    "sg:phone":"+41 13718248",
    "sg:postcode":"8046",
    "sg:province":"Z\u00fcrich",
    "wof:name":"Teppich-galerie Wehntaler Gmbh",
    "wof:placetype":"venue"
},
  "geometry": {"coordinates":[8.5291566849,47.4157066345],"type":"Point"}
}