{
  "type": "Feature",
  "properties": {
    "iso:country":"CH",
    "sg:address":"Route Des Ronquoz 41 1950 Sion Case Postale 1117",
    "sg:city":"Sion",
    "sg:orig_category":"Grosshandel mit Erzen U Metallen Grosshandel mit Sportartikeln",
    "sg:phone":"+41 27 329 00 00",
    "sg:postcode":"1951",
    "sg:province":"Valais",
    "wof:name":"Pfefferl\u00e9 & Cie Sa",
    "wof:placetype":"venue"
},
  "geometry": {"coordinates":[7.3615431786,46.2243537903],"type":"Point"}
}