{
  "type": "Feature",
  "properties": {
    "iso:country":"CH",
    "sg:address":"K\u00fcechlimoosstrasse 4",
    "sg:city":"Appenzell",
    "sg:orig_category":"Massagestudios P\u00e9dicure",
    "sg:phone":"+41 61 751 10 65",
    "sg:postcode":"9050",
    "sg:province":"Appenzell Innerhoden",
    "wof:name":"Massagepraxis",
    "wof:placetype":"venue"
},
  "geometry": {"coordinates":[7.5953431129,47.471660614],"type":"Point"}
}