{
  "type": "Feature",
  "properties": {
    "iso:country":"CH",
    "sg:address":"B\u00f6zingenstrasse 165 2500 Biel/bienne. Postfach",
    "sg:city":"Biel/bienne",
    "sg:orig_category":"Herstellung von Mess U Kontrollinstrumenten U vorrichtungen",
    "sg:postcode":"2504",
    "sg:province":"Bern",
    "wof:name":"Sabato L.",
    "wof:placetype":"venue"
},
  "geometry": {"coordinates":[7.2658619881,47.1520996094],"type":"Point"}
}