{
  "type": "Feature",
  "properties": {
    "iso:country":"CH",
    "sg:address":"8307 Effretikon. Postfach 342",
    "sg:city":"Effretikon",
    "sg:orig_category":"Sportvereine Sch\u00fctzen Pistolen-& Gewehr",
    "sg:phone":"+41 19550481",
    "sg:postcode":"8307",
    "sg:province":"Z\u00fcrich",
    "wof:name":"Pistolensch\u00fctzen.ilnau-effr.",
    "wof:placetype":"venue"
},
  "geometry": {"coordinates":[8.7083997726,47.4293899536],"type":"Point"}
}