{
  "type": "Feature",
  "properties": {
    "iso:country":"CH",
    "sg:address":"Burgweg 10 4058 Basel. Postfach",
    "sg:city":"Basel",
    "sg:orig_category":"Mechanik",
    "sg:postcode":"4051",
    "sg:province":"Basel-Stadt",
    "wof:name":"L\u00e9chot Andr\u00e9",
    "wof:placetype":"venue"
},
  "geometry": {"coordinates":[7.2136101723,47.1606483459],"type":"Point"}
}