{
  "type": "Feature",
  "properties": {
    "iso:country":"CH",
    "sg:address":"Staatsstrasse 7",
    "sg:city":"Hilterfingen",
    "sg:classifiers":[
        {
            "category":"Social Services",
            "subcategory":"Retirement Home",
            "type":"Services"
        }
    ],
    "sg:phone":"+41 33 243 16 72",
    "sg:postcode":"3652",
    "sg:province":"Bern",
    "sg:tags":[
        "pflegeheime",
        "u",
        "alters"
    ],
    "wof:name":"Altersheim F\u00fcr Den Amtsbezirk Thun Magda",
    "wof:placetype":"venue"
},
  "geometry": {"coordinates":[7.659647,46.734268],"type":"Point"}
}