{
  "type": "Feature",
  "properties": {
    "iso:country":"CH",
    "sg:address":"Via Verbano 23 6648 Minusio. Postfach Caselle Postale 1371",
    "sg:city":"Minusio",
    "sg:orig_category":"Architekturb\u00fcros",
    "sg:phone":"+41 91 743 52 33",
    "sg:postcode":"6648",
    "sg:province":"Ticino",
    "wof:name":"Fratelli Guscetti Ingegneria & Architettura",
    "wof:placetype":"venue"
},
  "geometry": {"coordinates":[8.818014,46.175629],"type":"Point"}
}