{
  "type": "Feature",
  "properties": {
    "iso:country":"CH",
    "sg:address":"Auf Der H\u00f6he 8 4144 Arlesheim. Postfach 459",
    "sg:city":"Arlesheim",
    "sg:orig_category":"Unternehmensberatung",
    "sg:phone":"+41 61 706 88 44",
    "sg:postcode":"4144",
    "sg:province":"Basel-Landschaft",
    "wof:name":"Hermann F. Kaelin Ag Wirtschaftsberatung",
    "wof:placetype":"venue"
},
  "geometry": {"coordinates":[7.6212468147,47.4892616272],"type":"Point"}
}