{
  "type": "Feature",
  "properties": {
    "addr:full":"Hauptstrasse Auenhofen Hefenhofen Thurgau 8580",
    "addr:postcode":"8580",
    "addr:street":"Hauptstrasse",
    "iso:country":"CH",
    "sg:address":"Hauptstrasse Auenhofen",
    "sg:city":"Hefenhofen",
    "sg:orig_category":"Bauschreinerei Zimmerei",
    "sg:phone":"+41 71 411 17 47",
    "sg:postcode":"8580",
    "sg:province":"Thurgau",
    "wof:name":"Jakob Rempfler Schreinerei & Zimmerei",
    "wof:placetype":"venue"
},
  "geometry": {"coordinates":[9.299568,47.545048],"type":"Point"}
}