{
  "type": "Feature",
  "properties": {
    "iso:country":"CH",
    "sg:address":"Kirchmatte 376",
    "sg:city":"Gontenschwil",
    "sg:orig_category":"Sonstige mit der Informatik verbundene T\u00e4tigkeiten",
    "sg:postcode":"5728",
    "sg:province":"Aargau",
    "wof:name":"Kuhn Informatik",
    "wof:placetype":"venue"
},
  "geometry": {"coordinates":[8.1458015442,47.2705001831],"type":"Point"}
}