{
  "type": "Feature",
  "properties": {
    "iso:country":"CH",
    "sg:address":"Kirchstrasse 61",
    "sg:city":"Vaduz",
    "sg:orig_category":"Bauspenglerei Sanit\u00e4rinstallation U Spenglerei",
    "sg:phone":"+423 232 23 82",
    "sg:postcode":"9490",
    "wof:name":"Biedermann Ag Spenglerei",
    "wof:placetype":"venue"
},
  "geometry": {"coordinates":[9.516487,47.136608],"type":"Point"}
}