{
  "type": "Feature",
  "properties": {
    "iso:country":"CH",
    "sg:address":"Caraa Servetta 54",
    "sg:city":"Losone",
    "sg:orig_category":"Architektur U Ingenieurb\u00fcros",
    "sg:phone":"+41 91 780 50 20",
    "sg:postcode":"6616",
    "sg:province":"Ticino",
    "wof:name":"Bertoli Marco Ing. Dr.",
    "wof:placetype":"venue"
},
  "geometry": {"coordinates":[8.758536,46.162617],"type":"Point"}
}