{
  "type": "Feature",
  "properties": {
    "iso:country":"CH",
    "sg:address":"Dorfstrasse 1",
    "sg:city":"Turtmann",
    "sg:orig_category":"Nationale Postdienste",
    "sg:phone":"+41 27 932 16 91",
    "sg:postcode":"3946",
    "sg:province":"Valais",
    "wof:name":"Die Schweizerische Post",
    "wof:placetype":"venue"
},
  "geometry": {"coordinates":[7.70398283,46.3017272949],"type":"Point"}
}