{
  "type": "Feature",
  "properties": {
    "iso:country":"CH",
    "sg:address":"Hirschmattstrasse 37",
    "sg:city":"Luzern",
    "sg:orig_category":"Architektur U Ingenieurb\u00fcros",
    "sg:phone":"+41 41 210 87 17",
    "sg:postcode":"6003",
    "sg:province":"Luzern",
    "wof:name":"Castilla & Castilla Gmbh",
    "wof:placetype":"venue"
},
  "geometry": {"coordinates":[8.308364,47.046627],"type":"Point"}
}