{
  "type": "Feature",
  "properties": {
    "addr:full":"L\u00e4ngackerstrasse 4 4562 Biberist. Postfach 218 Biberist Solothurn 4562",
    "addr:housenumber":"4;218",
    "addr:postcode":"4562 biberist.;4562",
    "addr:street":"Laengackerstrasse;Postfach",
    "iso:country":"CH",
    "sg:address":"L\u00e4ngackerstrasse 4 4562 Biberist. Postfach 218",
    "sg:city":"Biberist",
    "sg:orig_category":"Allgemeiner Hoch U Tiefbau",
    "sg:phone":"+41 32 672 27 33",
    "sg:postcode":"4562",
    "sg:province":"Solothurn",
    "wof:name":"Desarch Gmbh",
    "wof:placetype":"venue"
},
  "geometry": {"coordinates":[7.553299,47.181168],"type":"Point"}
}