{
  "type": "Feature",
  "properties": {
    "iso:country":"CH",
    "sg:address":"1925",
    "sg:city":"Finhaut",
    "sg:orig_category":"Non-Classified Establishments",
    "sg:postcode":"1925",
    "sg:province":"Valais",
    "wof:name":"Christophe Lugon Transports & Terrassements",
    "wof:placetype":"venue"
},
  "geometry": {"coordinates":[6.9743900299,46.082359314],"type":"Point"}
}