{
  "type": "Feature",
  "properties": {
    "iso:country":"CH",
    "sg:address":"Place Du March\u00e9 1 1260 Nyon. Postfach",
    "sg:city":"Nyon",
    "sg:orig_category":"Dienstleistungen von Beteiligungsgesellschaften",
    "sg:postcode":"1260",
    "sg:province":"Vaud",
    "wof:name":"Accuvest Sa",
    "wof:placetype":"venue"
},
  "geometry": {"coordinates":[6.2385611534,46.381778717],"type":"Point"}
}