{
  "type": "Feature",
  "properties": {
    "iso:country":"CH",
    "sg:address":"Sandbuckstrasse 13",
    "sg:city":"Neerach",
    "sg:orig_category":"Personal U Stellenvermittlung Unternehmensberatung",
    "sg:phone":"+41 21 695 22 09",
    "sg:postcode":"8173",
    "sg:province":"Z\u00fcrich",
    "wof:name":"Oprandi & Partner Sa Conseil En Personnel",
    "wof:placetype":"venue"
},
  "geometry": {"coordinates":[6.1288299561,46.1855583191],"type":"Point"}
}