{
  "type": "Feature",
  "properties": {
    "addr:full":"1070 Puidoux. Postfach Puidoux Vaud 1070",
    "addr:postcode":"1070;postfach;1070",
    "addr:street":"Puidoux.",
    "iso:country":"CH",
    "sg:address":"1070 Puidoux. Postfach",
    "sg:city":"Puidoux",
    "sg:orig_category":"Betrieb U technische Hilfsdienste des Kultur U Unterhaltungswesens",
    "sg:phone":"+41 21 946 22 73",
    "sg:postcode":"1070",
    "sg:province":"Vaud",
    "wof:name":"Lorelei-studio, Ph. Grandjean",
    "wof:placetype":"venue"
},
  "geometry": {"coordinates":[6.78276,46.502048],"type":"Point"}
}