{
  "type": "Feature",
  "properties": {
    "addr:full":"Br\u00fcnnenstrasse 104 Bern Bern 3018",
    "addr:housenumber":"104",
    "addr:postcode":"3018",
    "addr:street":"Bruennenstrasse",
    "iso:country":"CH",
    "sg:address":"Br\u00fcnnenstrasse 104",
    "sg:city":"Bern",
    "sg:orig_category":"Detailhandel mit Bekleidung",
    "sg:postcode":"3018",
    "sg:province":"Bern",
    "wof:name":"Saidra Fashion Trading, Oberholzer M.",
    "wof:placetype":"venue"
},
  "geometry": {"coordinates":[8.483167,47.26778],"type":"Point"}
}