{
  "type": "Feature",
  "properties": {
    "iso:country":"CH",
    "sg:address":"Residenza Alle Betulle 6950 Tesserete. Postfach",
    "sg:city":"Tesserete",
    "sg:orig_category":"Detailhandel mit Computern U Software Hardwareberatung",
    "sg:phone":"+41 91 943 16 04",
    "sg:postcode":"6950",
    "sg:province":"Ticino",
    "wof:name":"Computerpoint Sagl Materiale Elettronico; Vendita, Riparazioni Ecc",
    "wof:placetype":"venue"
},
  "geometry": {"coordinates":[8.96653,46.068443],"type":"Point"}
}