{
  "type": "Feature",
  "properties": {
    "iso:country":"CH",
    "sg:address":"M. Sch\u00fcrer-strasse 16",
    "sg:city":"Grenchen",
    "sg:orig_category":"Herstellung U Zusammensetzung von Uhren",
    "sg:phone":"+41 32 653 35 17",
    "sg:postcode":"2540",
    "sg:province":"Solothurn",
    "wof:name":"Aurema Sa Uhrenmanufaktur",
    "wof:placetype":"venue"
},
  "geometry": {"coordinates":[7.4017329216,47.1989746094],"type":"Point"}
}