{
  "type": "Feature",
  "properties": {
    "iso:country":"CH",
    "sg:address":"Dorfstrasse 30",
    "sg:city":"Bettenhausen",
    "sg:orig_category":"Herstellung von Metallkonstruktionen Mechanik",
    "sg:phone":"+41 62 961 24 17",
    "sg:postcode":"3366",
    "sg:province":"Bern",
    "wof:name":"Aegerter Heinz",
    "wof:placetype":"venue"
},
  "geometry": {"coordinates":[7.7142801285,47.1731071472],"type":"Point"}
}