{
  "type": "Feature",
  "properties": {
    "iso:country":"CH",
    "sg:address":"Dumas Avenue 16bis 1206 Gen\u00e8ve. Postfach",
    "sg:city":"Gen\u00e8ve",
    "sg:classifiers":[
        {
            "category":"Professional",
            "subcategory":"Accounting & Tax Preparation",
            "type":"Services"
        }
    ],
    "sg:postcode":"1206",
    "sg:province":"Gen\u00e8ve",
    "sg:tags":[
        "u",
        "yachtbau",
        "boot"
    ],
    "wof:name":"Nautic Service Nicola\u00ef",
    "wof:placetype":"venue"
},
  "geometry": {"coordinates":[6.155792,46.191654],"type":"Point"}
}