{
  "type": "Feature",
  "properties": {
    "iso:country":"CH",
    "sg:address":"Liebegg 1",
    "sg:city":"Gr\u00e4nichen",
    "sg:orig_category":"Wirtschaftspr\u00fcfung, Steuerberatung U Treuhand",
    "sg:phone":"+41 62 855 86 86",
    "sg:postcode":"5722",
    "sg:province":"Aargau",
    "wof:name":"Agro-treuhand Aargau Lbbz Liebegg",
    "wof:placetype":"venue"
},
  "geometry": {"coordinates":[8.1186199188,47.3382301331],"type":"Point"}
}