{
  "type": "Feature",
  "properties": {
    "iso:country":"CH",
    "sg:address":"Rue De L'ath\u00e9n\u00e9e 32",
    "sg:city":"Gen\u00e8ve",
    "sg:orig_category":"Zahntechnische Laboratorien",
    "sg:phone":"+41 22 346 14 59",
    "sg:postcode":"1206",
    "sg:province":"Gen\u00e8ve",
    "wof:name":"Bernard Schuler Labor.de Proth\u00e8ses Dentaires",
    "wof:placetype":"venue"
},
  "geometry": {"coordinates":[6.1534137726,46.1952323914],"type":"Point"}
}