{
  "type": "Feature",
  "properties": {
    "addr:full":"Parkplatz Br\u00fclisau Appenzell Innerhoden 9058",
    "addr:housenumber":"9058",
    "iso:country":"CH",
    "sg:address":"Parkplatz",
    "sg:city":"Br\u00fclisau",
    "sg:orig_category":"Detailhandel mit Brot, Back U S\u00fcsswaren",
    "sg:phone":"+41 71 799 13 23",
    "sg:postcode":"9058",
    "sg:province":"Appenzell Innerhoden",
    "wof:name":"F\u00e4ssler Hans",
    "wof:placetype":"venue"
},
  "geometry": {"coordinates":[9.454525,47.296616],"type":"Point"}
}