{
  "type": "Feature",
  "properties": {
    "iso:country":"CH",
    "sg:address":"Langfeldstrasse 68",
    "sg:city":"Ittigen",
    "sg:orig_category":"Fotografische Ateliers Grafikateliers, Design",
    "sg:phone":"+41 31 922 08 50",
    "sg:postcode":"3063",
    "sg:province":"Bern",
    "wof:name":"He! Typo + Design Digitale Gestaltung + Medienproduktion",
    "wof:placetype":"venue"
},
  "geometry": {"coordinates":[7.4792551994,46.9857635498],"type":"Point"}
}