{
  "type": "Feature",
  "properties": {
    "iso:country":"CH",
    "sg:address":"Zugerstrasse 51",
    "sg:city":"Baar",
    "sg:orig_category":"Unternehmensberatung",
    "sg:phone":"+41 56 426 41 01",
    "sg:postcode":"6340",
    "sg:province":"Zug",
    "wof:name":"Innopool Aeberhard Dr. Kurt",
    "wof:placetype":"venue"
},
  "geometry": {"coordinates":[8.5210142136,47.1861839294],"type":"Point"}
}