{
  "type": "Feature",
  "properties": {
    "addr:full":"Hohle Gasse 12 Ramlinsburg Basel-Landschaft 4433",
    "addr:housenumber":"12",
    "addr:postcode":"4433",
    "addr:street":"Hohle Gasse",
    "iso:country":"CH",
    "sg:address":"Hohle Gasse 12",
    "sg:city":"Ramlinsburg",
    "sg:orig_category":"Alarm- and Sicherheitsanlagen Grosshandel Herstellung von sonstigen elektrischen Ausr\u00fcstungen",
    "sg:postcode":"4433",
    "sg:province":"Basel-Landschaft",
    "wof:name":"Amea Gmbh Alarm-& Sicherheitsanlagen",
    "wof:placetype":"venue"
},
  "geometry": {"coordinates":[9.183447,47.559231],"type":"Point"}
}