{
  "type": "Feature",
  "properties": {
    "iso:country":"CH",
    "sg:address":"Thunstrasse 4",
    "sg:city":"Konolfingen",
    "sg:orig_category":"Detailhandel mit Radio U Fernsehger\u00e4ten Detailhandel mit elektrischen Haushalts-,Radio U Fernsehger\u00e4",
    "sg:phone":"+41 31 791 01 51",
    "sg:postcode":"3510",
    "sg:province":"Bern",
    "wof:name":"Radio-tv-service H.r. Moser Ag",
    "wof:placetype":"venue"
},
  "geometry": {"coordinates":[7.6204838753,46.8775863647],"type":"Point"}
}