{
  "type": "Feature",
  "properties": {
    "iso:country":"CH",
    "sg:address":"6264",
    "sg:city":"Pfaffnau",
    "sg:orig_category":"Schulpflegen",
    "sg:postcode":"6264",
    "sg:province":"Luzern",
    "wof:name":"Schulpflege Der Gemeinde Pfaffnau",
    "wof:placetype":"venue"
},
  "geometry": {"coordinates":[7.8991041183,47.228553772],"type":"Point"}
}