{
  "type": "Feature",
  "properties": {
    "iso:country":"CH",
    "sg:address":"Rue Johann-renfer 10",
    "sg:city":"Biel/bienne",
    "sg:orig_category":"Non-Classified Establishments",
    "sg:postcode":"2504",
    "sg:province":"Bern",
    "wof:name":"Paulux.finances",
    "wof:placetype":"venue"
},
  "geometry": {"coordinates":[7.2855648994,47.1602210999],"type":"Point"}
}