{
  "type": "Feature",
  "properties": {
    "iso:country":"CH",
    "sg:address":"Moulin-de-la-ratte Route Du 78",
    "sg:city":"Cartigny",
    "sg:orig_category":"Grosshandel mit Holz U Baustoffen",
    "sg:phone":"+41 79 625 57 88",
    "sg:postcode":"1236",
    "sg:province":"Gen\u00e8ve",
    "wof:name":"Bfs Sarl",
    "wof:placetype":"venue"
},
  "geometry": {"coordinates":[6.0341291428,46.1775245667],"type":"Point"}
}