{
  "type": "Feature",
  "properties": {
    "iso:country":"CH",
    "sg:address":"Egnacherstrasse 79",
    "sg:city":"Frasnacht",
    "sg:orig_category":"Detailhandel mit Waren verschiedener Art, Hauptrichtung Nahrungsmittel Grosshandel mit Nahrungsmitte",
    "sg:phone":"+41 71 446 06 45",
    "sg:postcode":"9320",
    "sg:province":"Thurgau",
    "wof:name":"Reinhold Breu Denner-satellit",
    "wof:placetype":"venue"
},
  "geometry": {"coordinates":[9.4014492035,47.5309715271],"type":"Point"}
}