{
  "type": "Feature",
  "properties": {
    "iso:country":"CH",
    "sg:address":"Rue De La Promenade 5",
    "sg:city":"Travers",
    "sg:orig_category":"Institutionen f\u00fcr Behinderte Institutionen f\u00fcr psychosoziale F\u00e4lle",
    "sg:phone":"+41 32 863 22 35",
    "sg:postcode":"2105",
    "sg:province":"Neuch\u00e2tel",
    "wof:name":"Alfaset Ateliers Prot\u00e9g\u00e9s Pour Handicap\u00e9s",
    "wof:placetype":"venue"
},
  "geometry": {"coordinates":[6.6779751778,46.9415435791],"type":"Point"}
}