{
  "type": "Feature",
  "properties": {
    "iso:country":"CH",
    "sg:address":"Bern-z\u00fcrichstrasse 43",
    "sg:city":"Langenthal",
    "sg:orig_category":"Detailhandel mit Getr\u00e4nken",
    "sg:phone":"+41 62 922 63 77",
    "sg:postcode":"4900",
    "sg:province":"Bern",
    "wof:name":"Gedex Ag Getr\u00e4nkehauslieferung",
    "wof:placetype":"venue"
},
  "geometry": {"coordinates":[7.7783741951,47.223815918],"type":"Point"}
}