{
  "type": "Feature",
  "properties": {
    "iso:country":"CH",
    "sg:address":"Schanzenstrasse 1 3008 Bern. Postfach 7918",
    "sg:city":"Bern",
    "sg:orig_category":"Advokaturb\u00fcros",
    "sg:phone":"+41 22 796 33 33",
    "sg:postcode":"3001",
    "sg:province":"Bern",
    "wof:name":"Hans U. Sutter Etude D'avocat",
    "wof:placetype":"venue"
},
  "geometry": {"coordinates":[6.09723,46.202751],"type":"Point"}
}