{
  "type": "Feature",
  "properties": {
    "iso:country":"CH",
    "sg:address":"Aegeristrasse 31a 6340 Baar. Postfach 651",
    "sg:city":"Baar",
    "sg:orig_category":"Grosshandel mit Getr\u00e4nken Grosshandel mit Wein U Spirituosen",
    "sg:phone":"+41 41 761 44 22",
    "sg:postcode":"6341",
    "sg:province":"Zug",
    "wof:name":"Weinhandlung Zum Felsenkeller Sa",
    "wof:placetype":"venue"
},
  "geometry": {"coordinates":[8.5338249207,47.1938972473],"type":"Point"}
}