{
  "type": "Feature",
  "properties": {
    "iso:country":"CH",
    "sg:address":"Rue Du Mont-blanc 20",
    "sg:city":"Gen\u00e8ve",
    "sg:orig_category":"Arztpraxen",
    "sg:phone":"+41 32 913 07 00",
    "sg:postcode":"1201",
    "sg:province":"Gen\u00e8ve",
    "wof:name":"Dr M\u00e9d. Pierre Cibrario M\u00e9decin Sp\u00e9cialiste Fmh",
    "wof:placetype":"venue"
},
  "geometry": {"coordinates":[6.82304,47.098415],"type":"Point"}
}