{
  "type": "Feature",
  "properties": {
    "iso:country":"CH",
    "sg:address":"1922",
    "sg:city":"Salvan",
    "sg:classifiers":[
        {
            "category":"Restaurant",
            "type":"Food & Drink"
        }
    ],
    "sg:phone":"+41 27 761 14 00",
    "sg:postcode":"1922",
    "sg:province":"Valais",
    "wof:name":"Caf\u00e9 Danfieu",
    "wof:placetype":"venue"
},
  "geometry": {"coordinates":[7.020275116,46.1201057434],"type":"Point"}
}