{
  "type": "Feature",
  "properties": {
    "iso:country":"CH",
    "sg:address":"G\u00f6nhardweg 32",
    "sg:city":"Suhr",
    "sg:orig_category":"Fahrschulen, Flugschulen",
    "sg:phone":"+41 79 209 13 14",
    "sg:postcode":"5034",
    "sg:province":"Aargau",
    "wof:name":"Rudolf Schneider City-fahrschule",
    "wof:placetype":"venue"
},
  "geometry": {"coordinates":[8.0643444061,47.3820343018],"type":"Point"}
}