{
  "type": "Feature",
  "properties": {
    "iso:country":"CH",
    "sg:address":"Collex Route De 20 B 1293 Bellevue. Postfach",
    "sg:city":"Bellevue",
    "sg:orig_category":"Berufsbildende weiterf\u00fchrende Schulen",
    "sg:phone":"+41 71 311 38 57",
    "sg:postcode":"1293",
    "sg:province":"Gen\u00e8ve",
    "wof:name":"Werner F\u00fcrer Verkaufsschulungen",
    "wof:placetype":"venue"
},
  "geometry": {"coordinates":[9.323031,47.424328],"type":"Point"}
}