{
  "type": "Feature",
  "properties": {
    "iso:country":"CH",
    "sg:address":"Via A. Tognola 9",
    "sg:city":"Biasca",
    "sg:classifiers":[
        {
            "category":"Building & Trades",
            "subcategory":"Construction",
            "type":"Services"
        }
    ],
    "sg:phone":"+41 91 862 31 54",
    "sg:postcode":"6710",
    "sg:province":"Ticino",
    "sg:tags":[
        "installation",
        "heating"
    ],
    "wof:name":"Saglini Sa",
    "wof:placetype":"venue"
},
  "geometry": {"coordinates":[8.9693431854,46.3608818054],"type":"Point"}
}