{
  "type": "Feature",
  "properties": {
    "iso:country":"CH",
    "sg:address":"Wiesenstrasse 5",
    "sg:city":"Schwerzenbach",
    "sg:orig_category":"Grosshandel mit pharmazeutischen Erzeugnissen, medizinischen U orthop\u00e4dischen Artikeln",
    "sg:phone":"+41 18870000",
    "sg:postcode":"8603",
    "sg:province":"Z\u00fcrich",
    "wof:name":"Padma Ag",
    "wof:placetype":"venue"
},
  "geometry": {"coordinates":[8.6573133469,47.3862571716],"type":"Point"}
}