{
  "type": "Feature",
  "properties": {
    "iso:country":"CH",
    "sg:address":"6805",
    "sg:city":"Mezzovico",
    "sg:orig_category":"Allgemeiner Hoch U Tiefbau",
    "sg:postcode":"6805",
    "sg:province":"Ticino",
    "wof:name":"Rimpark Sa",
    "wof:placetype":"venue"
},
  "geometry": {"coordinates":[8.92073,46.096451],"type":"Point"}
}