{
  "type": "Feature",
  "properties": {
    "iso:country":"CH",
    "sg:address":"Gr\u00fczefeldstrasse 51",
    "sg:city":"Winterthur",
    "sg:classifiers":[
        {
            "category":"Government",
            "subcategory":"Fire Station",
            "type":"Public Place"
        }
    ],
    "sg:phone":"+41 52 234 02 02",
    "sg:postcode":"8404",
    "sg:province":"Z\u00fcrich",
    "sg:tags":[
        "gate",
        "protection"
    ],
    "wof:name":"Ag Stawin Gauger",
    "wof:placetype":"venue"
},
  "geometry": {"coordinates":[8.7567844391,47.4929428101],"type":"Point"}
}