{
  "type": "Feature",
  "properties": {
    "iso:country":"CH",
    "sg:address":"Rue Du Simplon 2",
    "sg:city":"Vevey",
    "sg:orig_category":"Drogerien",
    "sg:phone":"+41 21 921 38 24",
    "sg:postcode":"1800",
    "sg:province":"Vaud",
    "wof:name":"Droguerie St. Jean, Samuel Michel",
    "wof:placetype":"venue"
},
  "geometry": {"coordinates":[6.8472251892,46.4590606689],"type":"Point"}
}