{
  "type": "Feature",
  "properties": {
    "iso:country":"CH",
    "sg:address":"Brandschenkestrasse 47 8000 Z\u00fcrich. Postfach",
    "sg:city":"Z\u00fcrich",
    "sg:orig_category":"Finanzierungsinstitutionen",
    "sg:postcode":"8001",
    "sg:province":"Z\u00fcrich",
    "wof:name":"X-clear Ag",
    "wof:placetype":"venue"
},
  "geometry": {"coordinates":[8.5315437317,47.3689498901],"type":"Point"}
}