{
  "type": "Feature",
  "properties": {
    "addr:full":"Freienwilerstrasse 8 Oberehrendingen 5422",
    "addr:housenumber":"8",
    "addr:postcode":"5422",
    "addr:street":"Freienwilerstrasse;Oberehrendingen",
    "iso:country":"CH",
    "sg:address":"Freienwilerstrasse 8",
    "sg:city":"Oberehrendingen",
    "sg:orig_category":"Abbruch U Sprenggewerbe, Erdbewegungsarbeiten Erdbewegungsarbeiten",
    "sg:phone":"+41 56 222 14 66",
    "sg:postcode":"5422",
    "wof:name":"Spahni Ag",
    "wof:placetype":"venue"
},
  "geometry": {"coordinates":[8.341171,47.497898],"type":"Point"}
}