{
  "type": "Feature",
  "properties": {
    "iso:country":"CH",
    "sg:address":"Schulhaus",
    "sg:city":"Lenzerheide/lai",
    "sg:classifiers":[
        {
            "category":"Education",
            "subcategory":"Library",
            "type":"Public Place"
        }
    ],
    "sg:phone":"+41 17881565",
    "sg:postcode":"7078",
    "sg:province":"Graubunden",
    "sg:tags":[
        "u",
        "bibliotheken",
        "archive"
    ],
    "wof:name":"Schul-& Gemeindebibliothek",
    "wof:placetype":"venue"
},
  "geometry": {"coordinates":[9.057631,46.982082],"type":"Point"}
}