{
  "type": "Feature",
  "properties": {
    "addr:full":"Spitalgasse 37 3011 Bern. Postfach Bern Bern 3001",
    "addr:housenumber":"37",
    "addr:postcode":"3011;postfach;3001",
    "addr:street":"Spitalgasse",
    "iso:country":"CH",
    "sg:address":"Spitalgasse 37 3011 Bern. Postfach",
    "sg:city":"Bern",
    "sg:orig_category":"Arztpraxen",
    "sg:phone":"+41 31 312 33 33",
    "sg:postcode":"3001",
    "sg:province":"Bern",
    "wof:name":"Dr. Med. Tony Kam Spezialarzt F.akupunktur",
    "wof:placetype":"venue"
},
  "geometry": {"coordinates":[7.441596,46.947781],"type":"Point"}
}