{
  "type": "Feature",
  "properties": {
    "iso:country":"CH",
    "sg:address":"7551",
    "sg:city":"Ftan",
    "sg:orig_category":"Pensionskassen",
    "sg:phone":"+41 81 861 22 11",
    "sg:postcode":"7551",
    "sg:province":"Graubunden",
    "wof:name":"Personalf\u00fcrsorgestiftung Des Hochalpinen T\u00f6chterinstitutes Fetan",
    "wof:placetype":"venue"
},
  "geometry": {"coordinates":[10.248667717,46.7940216064],"type":"Point"}
}