{
  "type": "Feature",
  "properties": {
    "iso:country":"CH",
    "sg:address":"Lengghalde 2",
    "sg:city":"Z\u00fcrich",
    "sg:orig_category":"Interessenvertretungen",
    "sg:postcode":"8008",
    "sg:province":"Z\u00fcrich",
    "wof:name":"The International Society For The Study Of The Lumbar Spine",
    "wof:placetype":"venue"
},
  "geometry": {"coordinates":[8.5730934143,47.3527832031],"type":"Point"}
}