{
  "type": "Feature",
  "properties": {
    "iso:country":"CH",
    "sg:address":"Unterstadtg\u00e4ssli 6",
    "sg:city":"Walenstadt",
    "sg:orig_category":"Politische Parteien CVP",
    "sg:phone":"+41 76 226 92 63",
    "sg:postcode":"8880",
    "sg:province":"St. Gallen",
    "wof:name":"Cvp Bonstetten-stallikon-wetts",
    "wof:placetype":"venue"
},
  "geometry": {"coordinates":[8.4532518387,47.2706718445],"type":"Point"}
}