{
  "type": "Feature",
  "properties": {
    "iso:country":"CH",
    "sg:address":"Oberer Haag 350",
    "sg:city":"Wilderswil",
    "sg:orig_category":"Herstellung von konfektionierten Textilwaren ohne Bekleidung",
    "sg:phone":"+41 79 620 35 48",
    "sg:postcode":"3812",
    "sg:province":"Bern",
    "wof:name":"La Filanda Di Perani Angelo",
    "wof:placetype":"venue"
},
  "geometry": {"coordinates":[8.9068098068,46.3802680969],"type":"Point"}
}