{
  "type": "Feature",
  "properties": {
    "iso:country":"CH",
    "sg:address":"Wangenstrasse 113 3018 Bern. Postfach 608",
    "sg:city":"Bern",
    "sg:orig_category":"Grosshandel mit elektrischen Haushaltsger\u00e4ten, Radio U Fernsehger\u00e4ten Herstellung von Werkzeugmaschi",
    "sg:phone":"+41 31 982 11 26",
    "sg:postcode":"3018",
    "sg:province":"Bern",
    "wof:name":"Ag Elektrowerkzeuge",
    "wof:placetype":"venue"
},
  "geometry": {"coordinates":[7.3858361244,46.9320411682],"type":"Point"}
}