{
  "type": "Feature",
  "properties": {
    "iso:country":"CH",
    "sg:address":"Neumattstrasse 2",
    "sg:city":"Arlesheim",
    "sg:orig_category":"Unclassifiable Establishments",
    "sg:postcode":"4144",
    "sg:province":"Basel-Landschaft",
    "wof:name":"Gastrodance Gmbh",
    "wof:placetype":"venue"
},
  "geometry": {"coordinates":[9.4780635834,47.1669311523],"type":"Point"}
}