{
  "type": "Feature",
  "properties": {
    "iso:country":"CH",
    "sg:address":"Hofurlistrasse 1 6373 Ennetb\u00fcrgen. Postfach 265",
    "sg:city":"Ennetb\u00fcrgen",
    "sg:orig_category":"HERSTELLUNG VON GER\u00c4TEN DER ELEKTRIZIT\u00c4TSERZEUGUNG, -VERTEILUNG U.\u00c4 Herstellung von Metallerzeugniss",
    "sg:phone":"+41 41 620 50 64",
    "sg:postcode":"6373",
    "sg:province":"Nidwalden",
    "wof:name":"Sigrist-photometer Ag",
    "wof:placetype":"venue"
},
  "geometry": {"coordinates":[8.4117832184,46.9858474731],"type":"Point"}
}