{
  "type": "Feature",
  "properties": {
    "iso:country":"CH",
    "sg:address":"Via Campagnora Castione 6533 Lumino. Postfach",
    "sg:city":"Bellinzona",
    "sg:orig_category":"Allgemeiner Hoch U Tiefbau",
    "sg:postcode":"6503",
    "sg:province":"Ticino",
    "wof:name":"C. S. Di Ciaponi Luca E Santos Fernando Snc Impresa Di Costruzioni E Riattazioni Ecc",
    "wof:placetype":"venue"
},
  "geometry": {"coordinates":[9.06537,46.230721],"type":"Point"}
}