{
  "type": "Feature",
  "properties": {
    "iso:country":"CH",
    "sg:address":"Postgasse 48",
    "sg:city":"Bern",
    "sg:classifiers":[
        {
            "category":"Restaurant",
            "type":"Food & Drink"
        }
    ],
    "sg:phone":"+41 31 839 55 93",
    "sg:postcode":"3011",
    "sg:province":"Bern",
    "wof:name":"Restaurant Postillion",
    "wof:placetype":"venue"
},
  "geometry": {"coordinates":[7.5307779312,46.9306030273],"type":"Point"}
}