{
  "type": "Feature",
  "properties": {
    "iso:country":"CH",
    "sg:address":"Zugerstrasse 83 6314 Unter\u00e4geri. Postfach 71",
    "sg:city":"Unter\u00e4geri",
    "sg:orig_category":"Grosshandel mit M\u00f6beln, Wohnbedarf, Teppichen U Bodenbel\u00e4gen Grosshandel mit sonstigen Gebrauchs U V",
    "sg:phone":"+41 41 750 44 22",
    "sg:postcode":"6314",
    "sg:province":"Zug",
    "wof:name":"Alberto Sa \u00abmobaco\u00bb",
    "wof:placetype":"venue"
},
  "geometry": {"coordinates":[8.57218647,47.1412734985],"type":"Point"}
}