{
  "type": "Feature",
  "properties": {
    "iso:country":"CH",
    "sg:address":"Schmiedgasse 86 6438 Ibach. Postfach",
    "sg:city":"Ibach",
    "sg:orig_category":"Unclassifiable Establishments",
    "sg:postcode":"6438",
    "sg:province":"Schwyz",
    "wof:name":"Ecolu Holding",
    "wof:placetype":"venue"
},
  "geometry": {"coordinates":[8.3123750687,46.9974212646],"type":"Point"}
}