{
  "type": "Feature",
  "properties": {
    "iso:country":"CH",
    "sg:address":"Dangelstrasse 24 8060 Z\u00fcrich. Postfach 263",
    "sg:city":"Z\u00fcrich",
    "sg:orig_category":"Unternehmensberatung",
    "sg:phone":"+41 14810336",
    "sg:postcode":"8060",
    "sg:province":"Z\u00fcrich",
    "wof:name":"Europe - China Business Development Gmbh Chinesische U. Europ\u00e4ische Firmen, Investoren U. Privatpersonen; Beratung In Wirtschaftlichen Fragen Usw",
    "wof:placetype":"venue"
},
  "geometry": {"coordinates":[8.5286397934,47.3337669373],"type":"Point"}
}