{
  "type": "Feature",
  "properties": {
    "iso:country":"CH",
    "sg:address":"K\u00e4sereistrasse 8",
    "sg:city":"Wigoltingen",
    "sg:orig_category":"Bauschreinerei Innenausbau",
    "sg:phone":"+41 52 763 13 65",
    "sg:postcode":"8556",
    "sg:province":"Thurgau",
    "wof:name":"M\u00fcller M\u00f6bel & Innenausbau",
    "wof:placetype":"venue"
},
  "geometry": {"coordinates":[9.030995,47.596649],"type":"Point"}
}