{
  "type": "Feature",
  "properties": {
    "iso:country":"CH",
    "sg:address":"Benknerstrasse 10",
    "sg:city":"Uznach",
    "sg:orig_category":"Herstellung von Metallkonstruktionen",
    "sg:postcode":"8730",
    "sg:province":"St. Gallen",
    "wof:name":"H\u00fcrlimann Metallbau Ag",
    "wof:placetype":"venue"
},
  "geometry": {"coordinates":[8.9845819473,47.2211380005],"type":"Point"}
}