{
  "type": "Feature",
  "properties": {
    "iso:country":"CH",
    "sg:address":"Gschwendes Steinegg",
    "sg:city":"Appenzell",
    "sg:orig_category":"Politische Parteien CVP",
    "sg:phone":"+41 71 222 31 41",
    "sg:postcode":"9050",
    "sg:province":"Appenzell Innerhoden",
    "wof:name":"Junge Cvp St.gallen",
    "wof:placetype":"venue"
},
  "geometry": {"coordinates":[9.3758268356,47.4229278564],"type":"Point"}
}