{
  "type": "Feature",
  "properties": {
    "iso:country":"CH",
    "sg:address":"Via Giovanni Ferri 25",
    "sg:city":"Lugano",
    "sg:orig_category":"RESTAURANTS: TEA-ROOMS",
    "sg:postcode":"6900",
    "sg:province":"Ticino",
    "wof:name":"Ristobar Serrafiorita Sagl",
    "wof:placetype":"venue"
},
  "geometry": {"coordinates":[8.9596996307,46.014251709],"type":"Point"}
}