{
  "type": "Feature",
  "properties": {
    "iso:country":"CH",
    "sg:address":"6557",
    "sg:city":"Cama",
    "sg:orig_category":"Kaminfeger",
    "sg:phone":"+41 91 830 13 63",
    "sg:postcode":"6557",
    "sg:province":"Graubunden",
    "wof:name":"Martin Christen Spazzacamino",
    "wof:placetype":"venue"
},
  "geometry": {"coordinates":[9.1691150665,46.2709541321],"type":"Point"}
}