{
  "type": "Feature",
  "properties": {
    "iso:country":"CH",
    "sg:address":"Bahnhofstrasse 28 6300 Zug. Postfach",
    "sg:city":"Zug",
    "sg:orig_category":"Wirtschaftspr\u00fcfung, Steuerberatung U Treuhand",
    "sg:phone":"+41 41 729 11 29",
    "sg:postcode":"6300",
    "sg:province":"Zug",
    "wof:name":"Oswald Gebr. Ag",
    "wof:placetype":"venue"
},
  "geometry": {"coordinates":[8.5159921646,47.1701126099],"type":"Point"}
}