{
  "type": "Feature",
  "properties": {
    "iso:country":"CH",
    "sg:address":"Zollstrasse 20",
    "sg:city":"Z\u00fcrich",
    "sg:orig_category":"RESTAURANTS: TEA-ROOMS",
    "sg:phone":"+41 12723044",
    "sg:postcode":"8005",
    "sg:province":"Z\u00fcrich",
    "wof:name":"Zollburg Gastro Gmbh Betriebe Im Bereich Gastronomie, Bes. Herstellung U. Verkauf Von Fertigmahlzeiten Usw",
    "wof:placetype":"venue"
},
  "geometry": {"coordinates":[8.5360908508,47.3800697327],"type":"Point"}
}