{
  "type": "Feature",
  "properties": {
    "iso:country":"CH",
    "sg:address":"Route De Giez 5",
    "sg:city":"Grandson",
    "sg:orig_category":"Bauschreinerei D\u00e4mmung gegen K\u00e4lte, W\u00e4rme, Schall U Ersch\u00fctterung",
    "sg:phone":"+41 24 445 41 45",
    "sg:postcode":"1422",
    "sg:province":"Vaud",
    "wof:name":"Fen\u00eatres De Toitures Service Sa",
    "wof:placetype":"venue"
},
  "geometry": {"coordinates":[6.640405,46.808769],"type":"Point"}
}