{
  "type": "Feature",
  "properties": {
    "iso:country":"CH",
    "sg:address":"Brunngasse 4",
    "sg:city":"Z\u00fcrich",
    "sg:orig_category":"Detailhandel mit Uhren U Schmuck",
    "sg:phone":"+41 12523470",
    "sg:postcode":"8001",
    "sg:province":"Z\u00fcrich",
    "wof:name":"Johanna Dahm Hess Schmuckgestalterin",
    "wof:placetype":"venue"
},
  "geometry": {"coordinates":[8.5440454483,47.3730506897],"type":"Point"}
}