{
  "type": "Feature",
  "properties": {
    "iso:country":"CH",
    "sg:address":"Rue Du Casino 1",
    "sg:city":"Yverdon-les-bains",
    "sg:orig_category":"Reiseb\u00fcros",
    "sg:phone":"+41 24 426 55 90",
    "sg:postcode":"1400",
    "sg:province":"Vaud",
    "wof:name":"Sega Boys Agence De Voyages",
    "wof:placetype":"venue"
},
  "geometry": {"coordinates":[6.6421470642,46.7789764404],"type":"Point"}
}