{
  "type": "Feature",
  "properties": {
    "iso:country":"CH",
    "sg:address":"H\u00fchnerb\u00fchlstrasse 46",
    "sg:city":"Bolligen",
    "sg:orig_category":"Sonstige mit der Informatik verbundene T\u00e4tigkeiten",
    "sg:phone":"+41 31 928 22 81",
    "sg:postcode":"3065",
    "sg:province":"Bern",
    "wof:name":"Brain Sol Gmbh",
    "wof:placetype":"venue"
},
  "geometry": {"coordinates":[7.4994740486,46.9693641663],"type":"Point"}
}