{
  "type": "Feature",
  "properties": {
    "iso:country":"CH",
    "sg:address":"Zeiningerstrasse 20",
    "sg:city":"Maisprach",
    "sg:orig_category":"Maurerarbeiten",
    "sg:phone":"+41 21 691 59 83",
    "sg:postcode":"4464",
    "sg:province":"Basel-Landschaft",
    "wof:name":"Marcel Isoz Ma\u00e7onnerie",
    "wof:placetype":"venue"
},
  "geometry": {"coordinates":[6.5615859032,46.5294952393],"type":"Point"}
}