{
  "type": "Feature",
  "properties": {
    "addr:full":"Largitzenstrasse 74 Basel Basel-Stadt 4056",
    "addr:housenumber":"74",
    "addr:postcode":"4056",
    "addr:street":"Largitzenstrasse",
    "iso:country":"CH",
    "sg:address":"Largitzenstrasse 74",
    "sg:city":"Basel",
    "sg:orig_category":"Arztpraxen",
    "sg:phone":"+41 41 870 15 19",
    "sg:postcode":"4056",
    "sg:province":"Basel-Stadt",
    "wof:name":"Dr.med.hansruedi M\u00fcller Arzt F.allgmeine Medizin Fmh",
    "wof:placetype":"venue"
},
  "geometry": {"coordinates":[8.640261,46.882893],"type":"Point"}
}