{
  "type": "Feature",
  "properties": {
    "iso:country":"CH",
    "sg:address":"6939",
    "sg:city":"Mugena",
    "sg:orig_category":"Hoch U Tiefbau",
    "sg:phone":"+41 91 609 11 10",
    "sg:postcode":"6939",
    "sg:province":"Ticino",
    "wof:name":"Gianni Grignola Impresa Costruzioni",
    "wof:placetype":"venue"
},
  "geometry": {"coordinates":[8.8900499344,46.0489311218],"type":"Point"}
}