{
  "type": "Feature",
  "properties": {
    "iso:country":"CH",
    "sg:address":"Am Ausserberg 22",
    "sg:city":"Riehen",
    "sg:orig_category":"Elektroinstallation",
    "sg:phone":"+41 61 601 64 00",
    "sg:postcode":"4125",
    "sg:province":"Basel-Stadt",
    "wof:name":"Asmussen Ag Industrieautomation",
    "wof:placetype":"venue"
},
  "geometry": {"coordinates":[7.64955616,47.5681762695],"type":"Point"}
}