{
  "type": "Feature",
  "properties": {
    "iso:country":"CH",
    "sg:address":"Ringstrasse 58d",
    "sg:city":"Schattdorf",
    "sg:orig_category":"Verkehrs- and Tourismusb\u00fcros",
    "sg:phone":"+41 41 870 75 70",
    "sg:postcode":"6467",
    "sg:province":"Uri",
    "wof:name":"Verkehrsverein Attinghausen- Brusti,herrn Fritz Imholz",
    "wof:placetype":"venue"
},
  "geometry": {"coordinates":[8.6472530365,46.866443634],"type":"Point"}
}