{
  "type": "Feature",
  "properties": {
    "iso:country":"CH",
    "sg:address":"Hauptstrasse 80",
    "sg:city":"Degersheim",
    "sg:orig_category":"Herstellung von sonstigen elektrischen Ausr\u00fcstungen",
    "sg:postcode":"9113",
    "sg:province":"St. Gallen",
    "wof:name":"Elektro Hans Christoffel",
    "wof:placetype":"venue"
},
  "geometry": {"coordinates":[9.8205451965,46.7932624817],"type":"Point"}
}