{
  "type": "Feature",
  "properties": {
    "iso:country":"CH",
    "sg:address":"8280",
    "sg:city":"Kreuzlingen",
    "sg:classifiers":[
        {
            "category":"Education",
            "subcategory":"Vocational School",
            "type":"Public Place"
        }
    ],
    "sg:postcode":"8280",
    "sg:province":"Thurgau",
    "sg:tags":[
        "koch-",
        "haushaltschulen"
    ],
    "wof:name":"Haushaltungsschule",
    "wof:placetype":"venue"
},
  "geometry": {"coordinates":[9.173210144,47.641368866],"type":"Point"}
}