{
  "type": "Feature",
  "properties": {
    "iso:country":"CH",
    "sg:address":"Wabernstrasse 50",
    "sg:city":"Bern",
    "sg:orig_category":"Unclassifiable Establishments",
    "sg:phone":"+41 31 371 57 66",
    "sg:postcode":"3007",
    "sg:province":"Bern",
    "wof:name":"Vogel Franz Gartenbau Ag Gartenbau, Usw",
    "wof:placetype":"venue"
},
  "geometry": {"coordinates":[7.4384908676,46.9378356934],"type":"Point"}
}