{
  "type": "Feature",
  "properties": {
    "iso:country":"CH",
    "sg:address":"Bahnhofstrasse 11 3770 Zweisimmen. Postfach 314",
    "sg:city":"Zweisimmen",
    "sg:classifiers":[
        {
            "category":"Travel",
            "subcategory":"Hotels & Motels",
            "type":"Entertainment"
        }
    ],
    "sg:phone":"+41 79 422 90 57",
    "sg:postcode":"3770",
    "sg:province":"Bern",
    "sg:tags":[
        "hotels",
        "mit",
        "restaurant"
    ],
    "wof:name":"Hotel Terminus",
    "wof:placetype":"venue"
},
  "geometry": {"coordinates":[7.3743190765,46.5538787842],"type":"Point"}
}