{
  "type": "Feature",
  "properties": {
    "iso:country":"CH",
    "sg:address":"Kantonsstrasse 32",
    "sg:city":"Nottwil",
    "sg:orig_category":"Detailhandel mit Waren verschiedener Art, Hauptrichtung Nahrungsmittel",
    "sg:phone":"+41 41 938 00 01",
    "sg:postcode":"6207",
    "sg:province":"Luzern",
    "wof:name":"Anna Maria V\u00f6lker Denner-satellit",
    "wof:placetype":"venue"
},
  "geometry": {"coordinates":[8.1326370239,47.1373329163],"type":"Point"}
}