{
  "type": "Feature",
  "properties": {
    "iso:country":"CH",
    "sg:address":"Pavillons Rue Des 5-7",
    "sg:city":"Gen\u00e8ve",
    "sg:orig_category":"Instandhaltung U Reparatur von Automobilen",
    "sg:phone":"+41 22 321 03 47",
    "sg:postcode":"1205",
    "sg:province":"Gen\u00e8ve",
    "wof:name":"Garage Stalder Sa",
    "wof:placetype":"venue"
},
  "geometry": {"coordinates":[6.1390271187,46.196975708],"type":"Point"}
}