{
  "type": "Feature",
  "properties": {
    "iso:country":"CH",
    "sg:address":"Vies Sainte-catherine",
    "sg:city":"Del\u00e9mont",
    "sg:orig_category":"Sportvereine Ballsport Tennis",
    "sg:phone":"+41 55 286 81 11",
    "sg:postcode":"2800",
    "sg:province":"Jura",
    "wof:name":"Tennisclub Der Baumann & Cie Ag Sfs",
    "wof:placetype":"venue"
},
  "geometry": {"coordinates":[8.8498697281,47.2590713501],"type":"Point"}
}