{
  "type": "Feature",
  "properties": {
    "iso:country":"CH",
    "sg:address":"Plaz 7554 Sent. Postfach",
    "sg:city":"Sent",
    "sg:orig_category":"Softwareentwicklung U beratung",
    "sg:postcode":"7554",
    "sg:province":"Graubunden",
    "wof:name":"Gertz Consulting",
    "wof:placetype":"venue"
},
  "geometry": {"coordinates":[10.3381700516,46.8173599243],"type":"Point"}
}