{
  "type": "Feature",
  "properties": {
    "iso:country":"CH",
    "sg:address":"Route De Cossonay 14",
    "sg:city":"Penthaz",
    "sg:orig_category":"Malerei Stukkateurgewerbe, Gipserei U Verputzerei",
    "sg:phone":"+41 22 320 10 53",
    "sg:postcode":"1303",
    "sg:province":"Vaud",
    "wof:name":"Patrick Moret Gypserie & Peinture",
    "wof:placetype":"venue"
},
  "geometry": {"coordinates":[6.1451392174,46.1914367676],"type":"Point"}
}