{
  "type": "Feature",
  "properties": {
    "iso:country":"CH",
    "sg:address":"Vogtackerweg 14",
    "sg:city":"Sissach",
    "sg:orig_category":"Interessenvertretungen",
    "sg:postcode":"4450",
    "sg:province":"Basel-Landschaft",
    "wof:name":"Witwen Und Waisenkasse Der Baselbieter-loge Nr. 36",
    "wof:placetype":"venue"
},
  "geometry": {"coordinates":[7.81204319,47.4580230713],"type":"Point"}
}