{
  "type": "Feature",
  "properties": {
    "iso:country":"CH",
    "sg:address":"Milit\u00e4rstrasse 89 8000 Z\u00fcrich. Postfach",
    "sg:city":"Z\u00fcrich",
    "sg:orig_category":"Detailhandel mit Bekleidung",
    "sg:postcode":"8001",
    "sg:province":"Z\u00fcrich",
    "wof:name":"S & B Diffusione Di Scali Giovanni",
    "wof:placetype":"venue"
},
  "geometry": {"coordinates":[8.971225,45.905701],"type":"Point"}
}