{
  "type": "Feature",
  "properties": {
    "iso:country":"CH",
    "sg:address":"Seehaldenstrasse 23b",
    "sg:city":"Rorschacherberg",
    "sg:orig_category":"Herstellung von Nahrungsmitteln undGetr\u00e4nken Sonstiges Textilgewerbe",
    "sg:phone":"+41 71 747 55 11",
    "sg:postcode":"9404",
    "sg:province":"St. Gallen",
    "wof:name":"Rexxam Ag",
    "wof:placetype":"venue"
},
  "geometry": {"coordinates":[9.6320123672,47.4379425049],"type":"Point"}
}