{
  "type": "Feature",
  "properties": {
    "iso:country":"CH",
    "sg:address":"Ibergstrasse 16",
    "sg:city":"Bischofszell",
    "sg:orig_category":"Zimmerei, Dachdeckerei, Bauspenglerei U Abdichtung",
    "sg:phone":"+41 71 422 20 23",
    "sg:postcode":"9220",
    "sg:province":"Thurgau",
    "wof:name":"B\u00fcchler Kurt Ag, Bedachungen",
    "wof:placetype":"venue"
},
  "geometry": {"coordinates":[9.2385959625,47.5003547668],"type":"Point"}
}