{
  "type": "Feature",
  "properties": {
    "iso:country":"CH",
    "sg:address":"Wintersried Ibach 6430 Schwyz. Postfach",
    "sg:city":"Ibach",
    "sg:orig_category":"Non-Classified Establishments",
    "sg:postcode":"6438",
    "sg:province":"Schwyz",
    "wof:name":"Genossenschaft Ril Regionale Indoor-luftdruckanlage Wintersried",
    "wof:placetype":"venue"
},
  "geometry": {"coordinates":[8.6269350052,47.0149536133],"type":"Point"}
}