{
  "type": "Feature",
  "properties": {
    "iso:country":"CH",
    "sg:address":"Kornstrasse 9",
    "sg:city":"Schwerzenbach",
    "sg:orig_category":"Sonstige Institutionen des Sozialwesens ohne Beherbergung",
    "sg:phone":"+41 18260980",
    "sg:postcode":"8603",
    "sg:province":"Z\u00fcrich",
    "wof:name":"Schulpsychologischer Dienst",
    "wof:placetype":"venue"
},
  "geometry": {"coordinates":[8.6571750641,47.3846855164],"type":"Point"}
}