{
  "type": "Feature",
  "properties": {
    "iso:country":"CH",
    "sg:address":"Nidelbadstrasse 21",
    "sg:city":"Z\u00fcrich",
    "sg:orig_category":"Reinigungsgewerbe",
    "sg:postcode":"8038",
    "sg:province":"Z\u00fcrich",
    "wof:name":"Mihailovic Hauswartungen",
    "wof:placetype":"venue"
},
  "geometry": {"coordinates":[8.5333223343,47.3352279663],"type":"Point"}
}