{
  "type": "Feature",
  "properties": {
    "iso:country":"CH",
    "sg:address":"Bottmingerstrasse 74",
    "sg:city":"Binningen",
    "sg:orig_category":"Sonstiger spezialisierter Hoch U Tiefbau",
    "sg:postcode":"4102",
    "sg:province":"Basel-Landschaft",
    "wof:name":"Radovanovic Mika, Baugesch\u00e4ft",
    "wof:placetype":"venue"
},
  "geometry": {"coordinates":[7.5730118752,47.5315132141],"type":"Point"}
}