{
  "type": "Feature",
  "properties": {
    "iso:country":"CH",
    "sg:address":"Kelliweg 3",
    "sg:city":"Horgen",
    "sg:orig_category":"Elektroinstallation Herstellung von Elektromotoren, Generatoren U Transformatoren",
    "sg:phone":"+41 71 333 29 90",
    "sg:postcode":"8810",
    "sg:province":"Z\u00fcrich",
    "wof:name":"Koller Elektro-anlagen Ag",
    "wof:placetype":"venue"
},
  "geometry": {"coordinates":[9.3904714584,47.3862113953],"type":"Point"}
}