{
  "type": "Feature",
  "properties": {
    "iso:country":"CH",
    "sg:address":"Rue Pedro Meylan 1 -",
    "sg:city":"Geneva",
    "sg:classifiers":[
        {
            "category":"Professional",
            "subcategory":"Art Services",
            "type":"Services"
        }
    ],
    "sg:phone":"+41 22 735 73 90",
    "sg:postcode":"1208",
    "sg:province":"Gen\u00e8ve",
    "sg:tags":[
        "export-import"
    ],
    "wof:name":"Greece Consulate",
    "wof:placetype":"venue"
},
  "geometry": {"coordinates":[6.163511,46.195492],"type":"Point"}
}