{
  "type": "Feature",
  "properties": {
    "iso:country":"CH",
    "sg:address":"Hauptstrasse 46",
    "sg:city":"Derendingen",
    "sg:orig_category":"Unternehmensberatung",
    "sg:phone":"+41 32 682 67 87",
    "sg:postcode":"4552",
    "sg:province":"Solothurn",
    "wof:name":"Innova Betriebsberatung Jan Luxik",
    "wof:placetype":"venue"
},
  "geometry": {"coordinates":[7.5861849785,47.1943588257],"type":"Point"}
}