{
  "type": "Feature",
  "properties": {
    "iso:country":"CH",
    "sg:address":"St. Jakobstrasse 63",
    "sg:city":"Pratteln",
    "sg:orig_category":"P\u00e9dicure",
    "sg:phone":"+41 61 821 90 41",
    "sg:postcode":"4133",
    "sg:province":"Basel-Landschaft",
    "wof:name":"Diana Dill P\u00e9dicure",
    "wof:placetype":"venue"
},
  "geometry": {"coordinates":[7.6837620735,47.5200424194],"type":"Point"}
}