{
  "type": "Feature",
  "properties": {
    "iso:country":"CH",
    "sg:address":"Kapfstrasse 227",
    "sg:city":"Aristau",
    "sg:orig_category":"G\u00fcterbef\u00f6rderung im Strassenverkehr",
    "sg:phone":"+41 56 664 49 74",
    "sg:postcode":"5628",
    "sg:province":"Aargau",
    "wof:name":"Lang G\u00fctertransporte Gmbh",
    "wof:placetype":"venue"
},
  "geometry": {"coordinates":[8.3554496765,47.2990608215],"type":"Point"}
}