{
  "type": "Feature",
  "properties": {
    "iso:country":"CH",
    "sg:address":"Limmatwiesenstrasse 2",
    "sg:city":"Oetwil",
    "sg:orig_category":"Grosshandel mit M\u00f6beln, Wohnbedarf, Teppichen U Bodenbel\u00e4gen",
    "sg:phone":"+41 17481140",
    "sg:postcode":"8955",
    "sg:province":"Z\u00fcrich",
    "wof:name":"Schmidt-k\u00fcchen M.b\u00fcrgisser Vertrieb Schweiz",
    "wof:placetype":"venue"
},
  "geometry": {"coordinates":[8.391459465,47.428855896],"type":"Point"}
}