{
  "type": "Feature",
  "properties": {
    "iso:country":"CH",
    "sg:address":"Rue De L'ancien-port 6",
    "sg:city":"Vevey",
    "sg:orig_category":"Notariate",
    "sg:phone":"+41 21 921 90 58",
    "sg:postcode":"1800",
    "sg:province":"Vaud",
    "wof:name":"Bernard Rossetti Etude De Notaire",
    "wof:placetype":"venue"
},
  "geometry": {"coordinates":[6.8445429802,46.4595489502],"type":"Point"}
}