{
  "type": "Feature",
  "properties": {
    "iso:country":"CH",
    "sg:address":"Vorstadt 32",
    "sg:city":"Zug",
    "sg:orig_category":"Non-Classified Establishments",
    "sg:phone":"+41 41 712 05 05",
    "sg:postcode":"6300",
    "sg:province":"Zug",
    "wof:name":"Tridon-r\u00f6sch Ag",
    "wof:placetype":"venue"
},
  "geometry": {"coordinates":[8.5143957138,47.1694755554],"type":"Point"}
}