{
  "type": "Feature",
  "properties": {
    "iso:country":"CH",
    "sg:address":"Arbonerstrasse 45",
    "sg:city":"Kronb\u00fchl",
    "sg:orig_category":"Bauschreinerei S\u00e4gewerke",
    "sg:phone":"+41 56 282 56 37",
    "sg:postcode":"9302",
    "wof:name":"Keller & Co Modellschreinerei & S\u00e4gerei",
    "wof:placetype":"venue"
},
  "geometry": {"coordinates":[8.278076,47.492134],"type":"Point"}
}