{
  "type": "Feature",
  "properties": {
    "iso:country":"CH",
    "sg:address":"Wehntalerstrasse 289",
    "sg:city":"Z\u00fcrich",
    "sg:orig_category":"Detailhandel mit Waren verschiedener Art, Hauptrichtung Nahrungsmittel",
    "sg:postcode":"8046",
    "sg:province":"Z\u00fcrich",
    "wof:name":"Limonella Congia I. Lebensmittel, Bes. Ital. Spezialit\u00e4ten; Handel",
    "wof:placetype":"venue"
},
  "geometry": {"coordinates":[8.5257101059,47.4113998413],"type":"Point"}
}