{
  "type": "Feature",
  "properties": {
    "iso:country":"CH",
    "sg:address":"Brunnmattstr. 13",
    "sg:city":"Th\u00f6rishaus",
    "sg:classifiers":[
        {
            "category":"Utilities",
            "subcategory":"Electric",
            "type":"Services"
        }
    ],
    "sg:phone":"+41 31 889 08 11",
    "sg:postcode":"3174",
    "sg:province":"Bern",
    "sg:tags":[
        "electricity",
        "electronic",
        "electrical",
        "equipment"
    ],
    "wof:name":"Wampfler Ag",
    "wof:placetype":"venue"
},
  "geometry": {"coordinates":[7.3492507935,46.8908805847],"type":"Point"}
}