{
  "type": "Feature",
  "properties": {
    "iso:country":"CH",
    "sg:address":"Industriestrasse 11 6285 Hitzkirch. Postfach",
    "sg:city":"Hitzkirch",
    "sg:orig_category":"Pensionskassen",
    "sg:phone":"+41 41 919 72 72",
    "sg:postcode":"6285",
    "sg:province":"Luzern",
    "wof:name":"Manometer-stiftung",
    "wof:placetype":"venue"
},
  "geometry": {"coordinates":[8.2568397522,47.2262001038],"type":"Point"}
}