{
  "type": "Feature",
  "properties": {
    "iso:country":"CH",
    "sg:address":"Hohlegasse 17",
    "sg:city":"Binningen",
    "sg:orig_category":"Mechanik",
    "sg:phone":"+41 61 423 87 39",
    "sg:postcode":"4102",
    "sg:province":"Basel-Landschaft",
    "wof:name":"Glaser Schlosserei Und Schmiede Gmbh",
    "wof:placetype":"venue"
},
  "geometry": {"coordinates":[7.5722007751,47.5402145386],"type":"Point"}
}