{
  "type": "Feature",
  "properties": {
    "iso:country":"CH",
    "sg:address":"Lindenstrasse 459",
    "sg:city":"Aristau",
    "sg:orig_category":"Unclassifiable Establishments",
    "sg:postcode":"5628",
    "sg:province":"Aargau",
    "wof:name":"Christian Moser, Axa Assurances, Agence G\u00e9n\u00e9rale, La Chaux-de-fonds",
    "wof:placetype":"venue"
},
  "geometry": {"coordinates":[6.8315777779,47.1042976379],"type":"Point"}
}