{
  "type": "Feature",
  "properties": {
    "iso:country":"CH",
    "sg:address":"M\u00fcsgasse 3",
    "sg:city":"Zeiningen",
    "sg:orig_category":"Fotografische Ateliers",
    "sg:phone":"+41 61 851 21 38",
    "sg:postcode":"4314",
    "sg:province":"Aargau",
    "wof:name":"Frank Gersdorf Grafik & Fotografie",
    "wof:placetype":"venue"
},
  "geometry": {"coordinates":[7.8693590164,47.5424003601],"type":"Point"}
}