{
  "type": "Feature",
  "properties": {
    "iso:country":"CH",
    "sg:address":"Chas'alva",
    "sg:city":"Valchava",
    "sg:orig_category":"Sonstiger spezialisierter Hoch U Tiefbau",
    "sg:postcode":"7535",
    "sg:province":"Graubunden",
    "wof:name":"Rosset Didace.",
    "wof:placetype":"venue"
},
  "geometry": {"coordinates":[6.8926100731,46.8147010803],"type":"Point"}
}