{
  "type": "Feature",
  "properties": {
    "iso:country":"CH",
    "sg:address":"Rue Du Temple 8",
    "sg:city":"Payerne",
    "sg:orig_category":"RESTAURANTS: TEA-ROOMS",
    "sg:postcode":"1530",
    "sg:province":"Vaud",
    "wof:name":"Meister Marie-france",
    "wof:placetype":"venue"
},
  "geometry": {"coordinates":[6.9388189316,46.8209953308],"type":"Point"}
}