{
  "type": "Feature",
  "properties": {
    "addr:full":"Obstgartenstrasse 8 Kloten Z\u00fcrich 8302",
    "addr:housenumber":"8",
    "addr:postcode":"8302",
    "addr:street":"Obstgartenstrasse",
    "iso:country":"CH",
    "sg:address":"Obstgartenstrasse 8",
    "sg:city":"Kloten",
    "sg:orig_category":"Bau von Strassen, Sportanlagen U Bahnverkehrsstrecken Strassenbau",
    "sg:phone":"+41 71 911 35 65",
    "sg:postcode":"8302",
    "sg:province":"Z\u00fcrich",
    "wof:name":"F\u00e4h + St\u00e4bler Strassen Und Tiefbau Ag",
    "wof:placetype":"venue"
},
  "geometry": {"coordinates":[9.04506,47.470814],"type":"Point"}
}