{
  "type": "Feature",
  "properties": {
    "iso:country":"CH",
    "sg:address":"6286",
    "sg:city":"Altwis",
    "sg:orig_category":"Wasserversorgung",
    "sg:postcode":"6286",
    "sg:province":"Luzern",
    "wof:name":"Brunnengenossenschaft Bunschen Oberwil I.s.",
    "wof:placetype":"venue"
},
  "geometry": {"coordinates":[7.4573540688,46.6618690491],"type":"Point"}
}