{
  "type": "Feature",
  "properties": {
    "iso:country":"CH",
    "sg:address":"Heidenhubelstrasse 8",
    "sg:city":"Solothurn",
    "sg:orig_category":"Handelsvermittlung U Grosshandel",
    "sg:phone":"+41 61 712 15 18",
    "sg:postcode":"4500",
    "sg:province":"Solothurn",
    "wof:name":"Ren\u00e9 Friedlin Handelsagentur",
    "wof:placetype":"venue"
},
  "geometry": {"coordinates":[7.598528862,47.4995880127],"type":"Point"}
}