{
  "type": "Feature",
  "properties": {
    "iso:country":"CH",
    "sg:address":"St. Gallerstrasse 26/28 8580 Amriswil. Postfach 1671",
    "sg:city":"Amriswil",
    "sg:orig_category":"Autogaragen",
    "sg:phone":"+41 71 414 20 80",
    "sg:postcode":"8580",
    "sg:province":"Thurgau",
    "wof:name":"Diethelm Ag Garage",
    "wof:placetype":"venue"
},
  "geometry": {"coordinates":[9.296868,47.539776],"type":"Point"}
}