{
  "type": "Feature",
  "properties": {
    "iso:country":"CH",
    "sg:address":"Stegmattrain 4",
    "sg:city":"Hinterkappelen",
    "sg:orig_category":"Verwaltung von Immobilien",
    "sg:phone":"+41 31 901 22 33",
    "sg:postcode":"3032",
    "sg:province":"Bern",
    "wof:name":"Fritz Trachsel Immobilienverwaltung",
    "wof:placetype":"venue"
},
  "geometry": {"coordinates":[7.3834462166,46.9677619934],"type":"Point"}
}