{
  "type": "Feature",
  "properties": {
    "iso:country":"CH",
    "sg:address":"Grubenstrasse 19 5070 Frick. Postfach",
    "sg:city":"Frick",
    "sg:orig_category":"Non-Classified Establishments",
    "sg:postcode":"5070",
    "sg:province":"Aargau",
    "wof:name":"Altromondo Sportmarketing Und Management Gmbh",
    "wof:placetype":"venue"
},
  "geometry": {"coordinates":[8.0192899704,47.5106925964],"type":"Point"}
}