{
  "type": "Feature",
  "properties": {
    "iso:country":"CH",
    "sg:address":"Burgerstrasse 5",
    "sg:city":"Luzern",
    "sg:orig_category":"Detailhandel mit Uhren U Schmuck Herstellung von Schmuck, Gold U Silberschmiedwaren",
    "sg:phone":"+41 41 210 11 59",
    "sg:postcode":"6003",
    "sg:province":"Luzern",
    "wof:name":"Laube Harry Goldschmied.",
    "wof:placetype":"venue"
},
  "geometry": {"coordinates":[8.3031864166,47.0506820679],"type":"Point"}
}