{
  "type": "Feature",
  "properties": {
    "iso:country":"CH",
    "sg:address":"Au Village 1436 Treycovagnes. Postfach",
    "sg:city":"Treycovagnes",
    "sg:orig_category":"Detailhandel mit Waren verschiedener Art, Hauptrichtung Nahrungsmittel",
    "sg:postcode":"1436",
    "sg:province":"Vaud",
    "wof:name":"Alimentation Comte Laurence",
    "wof:placetype":"venue"
},
  "geometry": {"coordinates":[6.6039328575,46.7769088745],"type":"Point"}
}