{
  "type": "Feature",
  "properties": {
    "iso:country":"CH",
    "sg:address":"Weiningerstrasse 48",
    "sg:city":"Unterengstringen",
    "sg:orig_category":"Herstellung von medizinischen U chirurgischen Ger\u00e4ten sowie orthop\u00e4dischen Vorrichtungen",
    "sg:postcode":"8103",
    "sg:province":"Z\u00fcrich",
    "wof:name":"Prosantec, Br\u00e4ndli Marco",
    "wof:placetype":"venue"
},
  "geometry": {"coordinates":[8.4491262436,47.4130897522],"type":"Point"}
}