{
  "type": "Feature",
  "properties": {
    "iso:country":"CH",
    "sg:address":"Rue De Morges 1 Ferme En Bettens 1121 Bremblens. Postfach",
    "sg:city":"Bremblens",
    "sg:orig_category":"Fernmeldedienste",
    "sg:phone":"+41 56 484 61 11",
    "sg:postcode":"1121",
    "sg:province":"Vaud",
    "wof:name":"Xentel Ag Dienstleistungen Im Ber. Telekommunikation, Telemarketing Usw",
    "wof:placetype":"venue"
},
  "geometry": {"coordinates":[8.2947158813,47.4468193054],"type":"Point"}
}