{
  "type": "Feature",
  "properties": {
    "iso:country":"CH",
    "sg:address":"Gibelinstrasse 13",
    "sg:city":"Solothurn",
    "sg:orig_category":"Beryllium And Beryllium Alloys",
    "sg:phone":"+41 32 752 32 32",
    "sg:postcode":"4503",
    "sg:province":"Solothurn",
    "wof:name":"Lamineries Matthey S.a.",
    "wof:placetype":"venue"
},
  "geometry": {"coordinates":[7.090176,47.063038],"type":"Point"}
}