{
  "type": "Feature",
  "properties": {
    "iso:country":"CH",
    "sg:address":"Corso San Gottardo 25",
    "sg:city":"Chiasso",
    "sg:orig_category":"Unclassifiable Establishments",
    "sg:postcode":"6830",
    "sg:province":"Ticino",
    "wof:name":"Italmondo Sa",
    "wof:placetype":"venue"
},
  "geometry": {"coordinates":[9.0317249298,45.8330116272],"type":"Point"}
}