{
  "type": "Feature",
  "properties": {
    "iso:country":"CH",
    "sg:address":"1484",
    "sg:city":"Aumont",
    "sg:orig_category":"RESTAURANTS: TEA-ROOMS",
    "sg:phone":"+41 32 968 43 95",
    "sg:postcode":"1484",
    "sg:province":"Fribourg",
    "wof:name":"Restaurant Des Pervenches, Schild & Rogoza",
    "wof:placetype":"venue"
},
  "geometry": {"coordinates":[6.8469409943,47.1312637329],"type":"Point"}
}