{
  "type": "Feature",
  "properties": {
    "addr:full":"9650 Nesslau St. Gallen 9650",
    "addr:housenumber":"9650",
    "addr:postcode":"9650",
    "addr:street":"Nesslau St.",
    "iso:country":"CH",
    "sg:address":"9650",
    "sg:city":"Nesslau",
    "sg:orig_category":"Bezirks, Sekundar, Realschulen, Oberstufe der Primarschulen",
    "sg:phone":"+41 71 994 21 81",
    "sg:postcode":"9650",
    "sg:province":"St. Gallen",
    "wof:name":"Sekundarschule",
    "wof:placetype":"venue"
},
  "geometry": {"coordinates":[9.19936,47.224178],"type":"Point"}
}