{
  "type": "Feature",
  "properties": {
    "iso:country":"CH",
    "sg:address":"Lindenstrasse 3",
    "sg:city":"Buochs",
    "sg:orig_category":"Gelegenheitsflugverkehr",
    "sg:phone":"+41 41 620 80 84",
    "sg:postcode":"6374",
    "sg:province":"Nidwalden",
    "wof:name":"Maranatha Helikopter Gmbh",
    "wof:placetype":"venue"
},
  "geometry": {"coordinates":[8.4284887314,46.9735488892],"type":"Point"}
}