{
  "type": "Feature",
  "properties": {
    "addr:full":"Dorfstrasse 85 Embrach Z\u00fcrich 8424",
    "addr:housenumber":"85",
    "addr:postcode":"8424",
    "addr:street":"Dorfstrasse",
    "iso:country":"CH",
    "sg:address":"Dorfstrasse 85",
    "sg:city":"Embrach",
    "sg:orig_category":"Datenverarbeitungsdienste",
    "sg:phone":"+41 18817137",
    "sg:postcode":"8424",
    "sg:province":"Z\u00fcrich",
    "wof:name":"Eds Information Business Gmbh",
    "wof:placetype":"venue"
},
  "geometry": {"coordinates":[8.593353,47.50647],"type":"Point"}
}