{
  "type": "Feature",
  "properties": {
    "iso:country":"CH",
    "sg:address":"Avenue Soret 2 1200 Genf. Postfach",
    "sg:city":"Gen\u00e8ve",
    "sg:orig_category":"RESTAURANTS: TEA-ROOMS",
    "sg:postcode":"1203",
    "sg:province":"Gen\u00e8ve",
    "wof:name":"Emilio Lloves",
    "wof:placetype":"venue"
},
  "geometry": {"coordinates":[6.1284837723,46.211353302],"type":"Point"}
}