{
  "type": "Feature",
  "properties": {
    "iso:country":"CH",
    "sg:address":"Affolternstrasse 5",
    "sg:city":"Ottenbach",
    "sg:classifiers":[
        {
            "category":"Education",
            "subcategory":"Library",
            "type":"Public Place"
        }
    ],
    "sg:phone":"+41 17611034",
    "sg:postcode":"8913",
    "sg:province":"Z\u00fcrich",
    "sg:tags":[
        "u",
        "bibliotheken",
        "archive"
    ],
    "wof:name":"Gemeinde-& Schulbibliothek",
    "wof:placetype":"venue"
},
  "geometry": {"coordinates":[8.40434,47.280754],"type":"Point"}
}