{
  "type": "Feature",
  "properties": {
    "addr:full":"Romanshornerstrasse 108 Kreuzlingen Thurgau 8280",
    "addr:housenumber":"108",
    "addr:postcode":"8280",
    "addr:street":"Romanshornerstrasse",
    "iso:country":"CH",
    "sg:address":"Romanshornerstrasse 108",
    "sg:city":"Kreuzlingen",
    "sg:orig_category":"Autospenglereien",
    "sg:phone":"+41 71 688 20 40",
    "sg:postcode":"8280",
    "sg:province":"Thurgau",
    "wof:name":"Heinrich Lang Autocarrosserie",
    "wof:placetype":"venue"
},
  "geometry": {"coordinates":[9.19483,47.63961],"type":"Point"}
}