{
  "type": "Feature",
  "properties": {
    "iso:country":"CH",
    "sg:address":"Zentralstrasse 66",
    "sg:city":"Biel/bienne",
    "sg:orig_category":"Sonstiger Fachdetailhandel in Verkaufsr\u00e4umen",
    "sg:phone":"+41 71 279 10 77",
    "sg:postcode":"2503",
    "sg:province":"Bern",
    "wof:name":"Christian Walt Mineralienshop",
    "wof:placetype":"venue"
},
  "geometry": {"coordinates":[9.322766304,47.4045829773],"type":"Point"}
}