{
  "type": "Feature",
  "properties": {
    "iso:country":"CH",
    "sg:address":"M\u00fcnchhaldenstrasse 38",
    "sg:city":"Z\u00fcrich",
    "sg:orig_category":"Werbegrafikateliers",
    "sg:phone":"+41 14229979",
    "sg:postcode":"8008",
    "sg:province":"Z\u00fcrich",
    "wof:name":"Hansruedi Minder Grafisches Atelier",
    "wof:placetype":"venue"
},
  "geometry": {"coordinates":[8.5600919724,47.3553733826],"type":"Point"}
}