{
  "type": "Feature",
  "properties": {
    "addr:full":"Im Gr\u00fcnen Hof 50 Esslingen Z\u00fcrich 8133",
    "addr:housenumber":"50",
    "addr:postcode":"8133",
    "addr:street":"Im Gruenen Hof",
    "iso:country":"CH",
    "sg:address":"Im Gr\u00fcnen Hof 50",
    "sg:city":"Esslingen",
    "sg:orig_category":"Akupunktur Kinesiologie",
    "sg:phone":"+41 19845115",
    "sg:postcode":"8133",
    "sg:province":"Z\u00fcrich",
    "wof:name":"Claudia Hoffmann Gesundheitspraxis",
    "wof:placetype":"venue"
},
  "geometry": {"coordinates":[8.713619,47.285488],"type":"Point"}
}