{
  "type": "Feature",
  "properties": {
    "iso:country":"CH",
    "sg:address":"8882",
    "sg:city":"Unterterzen",
    "sg:orig_category":"Grosshandel mit lebenden Tieren",
    "sg:phone":"+41 81 738 11 21",
    "sg:postcode":"8882",
    "sg:province":"St. Gallen",
    "wof:name":"Ruedi Meyer Viehhandel",
    "wof:placetype":"venue"
},
  "geometry": {"coordinates":[9.2530403137,47.1135101318],"type":"Point"}
}