{
  "type": "Feature",
  "properties": {
    "iso:country":"CH",
    "sg:address":"Rte De Fraternit\u00e9",
    "sg:city":"Sierre",
    "sg:orig_category":"Fotografisches Gewerbe U fotografische Laboratorien",
    "sg:postcode":"3960",
    "sg:province":"Valais",
    "wof:name":"Aero Photo Service Doutrelepont Et Julen",
    "wof:placetype":"venue"
},
  "geometry": {"coordinates":[7.4980401993,46.2770614624],"type":"Point"}
}