{
  "type": "Feature",
  "properties": {
    "iso:country":"CH",
    "sg:address":"Dorfstrasse 12 3084 Wabern. Postfach",
    "sg:city":"Wabern",
    "sg:orig_category":"Unclassifiable Establishments",
    "sg:postcode":"3084",
    "sg:province":"Bern",
    "wof:name":"The Privilegers Ag",
    "wof:placetype":"venue"
},
  "geometry": {"coordinates":[7.4469671249,46.9299736023],"type":"Point"}
}