{
  "type": "Feature",
  "properties": {
    "iso:country":"CH",
    "sg:address":"Via Balcengo",
    "sg:city":"Faido",
    "sg:orig_category":"Arztpraxen",
    "sg:phone":"+41 91 866 28 05",
    "sg:postcode":"6760",
    "sg:province":"Ticino",
    "wof:name":"Dott.med.rossano Sol\u00e8r Specialista Fmh",
    "wof:placetype":"venue"
},
  "geometry": {"coordinates":[8.799678,46.479095],"type":"Point"}
}