{
  "type": "Feature",
  "properties": {
    "iso:country":"CH",
    "sg:address":"Rheinweg 21 Neuhausen Am Rheinfall 8212 Neuhausen. Postfach",
    "sg:city":"Schaffhausen",
    "sg:orig_category":"G\u00fcterbef\u00f6rderung im Strassenverkehr",
    "sg:phone":"+41 55 440 26 93",
    "sg:postcode":"8200",
    "sg:province":"Schaffhausen",
    "wof:name":"Donner Meinrad",
    "wof:placetype":"venue"
},
  "geometry": {"coordinates":[8.8964147568,47.1912956238],"type":"Point"}
}