{
  "type": "Feature",
  "properties": {
    "iso:country":"CH",
    "sg:address":"Via Valdani 9",
    "sg:city":"Chiasso",
    "sg:orig_category":"Elektroinstallation Herstellung von sonstigen elektrischen Ausr\u00fcstungen",
    "sg:phone":"+41 91 683 66 41",
    "sg:postcode":"6830",
    "sg:province":"Ticino",
    "wof:name":"Videocavo Di Mauro Bergomi & Co",
    "wof:placetype":"venue"
},
  "geometry": {"coordinates":[9.0292825699,45.8382568359],"type":"Point"}
}