{
  "type": "Feature",
  "properties": {
    "addr:full":"Hubstrasse 100 Wil St. Gallen 9500",
    "addr:housenumber":"100;st.",
    "addr:postcode":"9500",
    "addr:street":"Hubstrasse;Wil",
    "iso:country":"CH",
    "sg:address":"Hubstrasse 100",
    "sg:city":"Wil",
    "sg:classifiers":[
        {
            "category":"Government",
            "subcategory":"Department Of Motor Vehicles",
            "type":"Public Place"
        }
    ],
    "sg:phone":"+41 71 913 92 90",
    "sg:postcode":"9500",
    "sg:province":"St. Gallen",
    "sg:tags":[
        "saw",
        "attachment"
    ],
    "wof:name":"Stihl & Co",
    "wof:placetype":"venue"
},
  "geometry": {"coordinates":[9.030472,47.459702],"type":"Point"}
}