{
  "type": "Feature",
  "properties": {
    "iso:country":"CH",
    "sg:address":"2572 Sutz. Postfach",
    "sg:city":"Sutz",
    "sg:orig_category":"Pensionskassen",
    "sg:phone":"+41 32 397 00 50",
    "sg:postcode":"2572",
    "sg:province":"Bern",
    "wof:name":"Personalstiftung Der Firma Manigley + Cie",
    "wof:placetype":"venue"
},
  "geometry": {"coordinates":[7.2143712044,47.0965576172],"type":"Point"}
}