{
  "type": "Feature",
  "properties": {
    "iso:country":"CH",
    "sg:address":"Pulverm\u00fchlestrasse 22 7000 Chur. Postfach 51",
    "sg:city":"Chur",
    "sg:orig_category":"Herstellung von Ausbauelementen aus Metall Herstellung von Metallkonstruktionen",
    "sg:phone":"+41 81 285 10 88",
    "sg:postcode":"7007",
    "sg:province":"Graubunden",
    "wof:name":"Mff Ag Metall-,fenster-& Fassadenbau",
    "wof:placetype":"venue"
},
  "geometry": {"coordinates":[9.5162162781,46.8519134521],"type":"Point"}
}