{
  "type": "Feature",
  "properties": {
    "iso:country":"CH",
    "sg:address":"Dorfstrasse 90",
    "sg:city":"Embrach",
    "sg:orig_category":"Malerei",
    "sg:phone":"+41 18650203",
    "sg:postcode":"8424",
    "sg:province":"Z\u00fcrich",
    "wof:name":"Ernst M\u00fcller Malergesch\u00e4ft",
    "wof:placetype":"venue"
},
  "geometry": {"coordinates":[8.593837738,47.5070953369],"type":"Point"}
}