{
  "type": "Feature",
  "properties": {
    "iso:country":"CH",
    "sg:address":"Bifangstrasse 31 5430 Wettingen. Postfach",
    "sg:city":"Wettingen",
    "sg:orig_category":"Sonstiger Fachdetailhandel mit Nahrungsmitteln, Getr\u00e4nken U Tabak in Verkaufsr\u00e4umen",
    "sg:postcode":"5430",
    "sg:province":"Aargau",
    "wof:name":"Milchzentrale Wettingen, Michael Rub",
    "wof:placetype":"venue"
},
  "geometry": {"coordinates":[8.3350658417,47.4644699097],"type":"Point"}
}