{
  "type": "Feature",
  "properties": {
    "iso:country":"CH",
    "sg:address":"General Wille-strasse 40 8706 Feldmeilen. Postfach 67",
    "sg:city":"Feldmeilen",
    "sg:orig_category":"Unternehmensberatung",
    "sg:postcode":"8706",
    "sg:province":"Z\u00fcrich",
    "wof:name":"Bleiker Management Consulting",
    "wof:placetype":"venue"
},
  "geometry": {"coordinates":[8.578379631,47.3256797791],"type":"Point"}
}