{
  "type": "Feature",
  "properties": {
    "iso:country":"CH",
    "sg:address":"Wurmb\u00fchlstrasse 6 8400 Winterthur. Postfach",
    "sg:city":"Winterthur",
    "sg:orig_category":"Herstellung von Sportger\u00e4ten",
    "sg:postcode":"8405",
    "sg:province":"Z\u00fcrich",
    "wof:name":"Reimann Und Constam",
    "wof:placetype":"venue"
},
  "geometry": {"coordinates":[8.7627696991,47.4901885986],"type":"Point"}
}