{
  "type": "Feature",
  "properties": {
    "iso:country":"CH",
    "sg:address":"Av. Chanel 43 1110 Morges Case Postale",
    "sg:city":"Morges",
    "sg:orig_category":"Interessenvertretungen",
    "sg:postcode":"1110",
    "sg:province":"Vaud",
    "wof:name":"Echo Soci\u00e9t\u00e9 Pour Le D\u00e9veloppement Des Activit\u00e9s Culturelles Dans La R\u00e9gion Morgienne.",
    "wof:placetype":"venue"
},
  "geometry": {"coordinates":[6.495593071,46.5161437988],"type":"Point"}
}