{
  "type": "Feature",
  "properties": {
    "iso:country":"CH",
    "sg:address":"Steinenvorstadt 53",
    "sg:city":"Basel",
    "sg:orig_category":"Architektur U Ingenieurb\u00fcros Architekturb\u00fcros",
    "sg:phone":"+41 61 274 00 44",
    "sg:postcode":"4051",
    "sg:province":"Basel-Stadt",
    "wof:name":"Atelier F\u00fcr Architektur Und Cad, Waldmeier Daniel",
    "wof:placetype":"venue"
},
  "geometry": {"coordinates":[7.588644,47.552544],"type":"Point"}
}