{
  "type": "Feature",
  "properties": {
    "iso:country":"CH",
    "sg:address":"Am Stausee 28",
    "sg:city":"Birsfelden",
    "sg:orig_category":"Arbeitnehmerverb\u00e4nde",
    "sg:postcode":"4127",
    "sg:province":"Basel-Landschaft",
    "wof:name":"Ptt-union Sektion Davos",
    "wof:placetype":"venue"
},
  "geometry": {"coordinates":[9.841665,46.809849],"type":"Point"}
}