{
  "type": "Feature",
  "properties": {
    "iso:country":"CH",
    "sg:address":"Viale C. Olgiati 20.2a 6512 Giubiasco. Postfach Caselle Postale 231",
    "sg:city":"Giubiasco",
    "sg:orig_category":"Arztpraxen",
    "sg:phone":"+41 91 857 37 20",
    "sg:postcode":"6512",
    "sg:province":"Ticino",
    "wof:name":"Dott.med.basilio Ostinelli Medico Generico Fmh",
    "wof:placetype":"venue"
},
  "geometry": {"coordinates":[9.014093,46.17617],"type":"Point"}
}