{
  "type": "Feature",
  "properties": {
    "iso:country":"CH",
    "sg:address":"Bischofshusen Goldau 6415 Arth. Postfach",
    "sg:city":"Goldau",
    "sg:orig_category":"Elektroinstallation",
    "sg:phone":"+41 55 284 62 22",
    "sg:postcode":"6410",
    "sg:province":"Schwyz",
    "wof:name":"Rickli Elektro Gmbh",
    "wof:placetype":"venue"
},
  "geometry": {"coordinates":[8.9657840729,47.2446098328],"type":"Point"}
}