{
  "type": "Feature",
  "properties": {
    "iso:country":"CH",
    "sg:address":"Oberdorfstrasse 13 6340 Baar. Postfach 2021",
    "sg:city":"Baar",
    "sg:orig_category":"Baugewerbe Elektroinstallation",
    "sg:phone":"+41 41 761 06 66",
    "sg:postcode":"6342",
    "sg:province":"Zug",
    "wof:name":"Albis Montagen Naef & Co",
    "wof:placetype":"venue"
},
  "geometry": {"coordinates":[8.530436,47.196014],"type":"Point"}
}