{
  "type": "Feature",
  "properties": {
    "iso:country":"CH",
    "sg:address":"Alpenquai 30 6005 Luzern. Postfach",
    "sg:city":"Luzern",
    "sg:orig_category":"Markt U Meinungsforschung",
    "sg:phone":"+41 41 368 18 18",
    "sg:postcode":"6005",
    "sg:province":"Luzern",
    "wof:name":"T.e.a.m. Television Event And Media Marketing Ag",
    "wof:placetype":"venue"
},
  "geometry": {"coordinates":[8.31939888,47.0453262329],"type":"Point"}
}