{
  "type": "Feature",
  "properties": {
    "iso:country":"CH",
    "sg:address":"Habstangenweg 335",
    "sg:city":"M\u00fcmliswil",
    "sg:orig_category":"Wohnheime",
    "sg:phone":"+41 62 391 34 46",
    "sg:postcode":"4717",
    "sg:province":"Solothurn",
    "wof:name":"Bildungs-& Ferienheim Cfb",
    "wof:placetype":"venue"
},
  "geometry": {"coordinates":[7.7003087997,47.3478317261],"type":"Point"}
}