{
  "type": "Feature",
  "properties": {
    "iso:country":"CH",
    "sg:address":"Badenerstrasse 79",
    "sg:city":"Z\u00fcrich",
    "sg:orig_category":"Unternehmensberatung",
    "sg:phone":"+41 13614480",
    "sg:postcode":"8004",
    "sg:province":"Z\u00fcrich",
    "wof:name":"Sc Solutions Gmbh",
    "wof:placetype":"venue"
},
  "geometry": {"coordinates":[8.5263309479,47.3737182617],"type":"Point"}
}