{
  "type": "Feature",
  "properties": {
    "iso:country":"CH",
    "sg:address":"Hauptstrasse 248",
    "sg:city":"Ramsen",
    "sg:orig_category":"Verlegen von Fliesen U Platten",
    "sg:phone":"+41 52 743 13 51",
    "sg:postcode":"8262",
    "sg:province":"Schaffhausen",
    "wof:name":"Hans Neidhart Ofenbau & Plattenbel\u00e4ge",
    "wof:placetype":"venue"
},
  "geometry": {"coordinates":[8.8115282059,47.7071990967],"type":"Point"}
}