{
  "type": "Feature",
  "properties": {
    "iso:country":"CH",
    "sg:address":"Ch. De La Rosaire 5",
    "sg:city":"Aclens",
    "sg:orig_category":"Architektur U Ingenieurb\u00fcros",
    "sg:postcode":"1123",
    "sg:province":"Vaud",
    "wof:name":"Free Lance Architecture Sa \u00ac Technique Aluminium",
    "wof:placetype":"venue"
},
  "geometry": {"coordinates":[6.522831,46.571033],"type":"Point"}
}