{
  "type": "Feature",
  "properties": {
    "iso:country":"CH",
    "sg:address":"Untere Chamm",
    "sg:city":"Bazenheid",
    "sg:orig_category":"Tierheime",
    "sg:phone":"+41 71 931 17 86",
    "sg:postcode":"9602",
    "sg:province":"St. Gallen",
    "wof:name":"Hundeferienheim Sonnenhof",
    "wof:placetype":"venue"
},
  "geometry": {"coordinates":[9.0613527298,47.3796081543],"type":"Point"}
}