{
  "type": "Feature",
  "properties": {
    "addr:full":"Bruggerstrasse 11 Wildegg Aargau 5103",
    "addr:housenumber":"11",
    "addr:postcode":"5103",
    "addr:street":"Bruggerstrasse",
    "iso:country":"CH",
    "sg:address":"Bruggerstrasse 11",
    "sg:city":"Wildegg",
    "sg:orig_category":"Bauingenieurb\u00fcros Heizung L\u00fcftung Klima",
    "sg:phone":"+41 62 893 17 87",
    "sg:postcode":"5103",
    "sg:province":"Aargau",
    "wof:name":"Caltronic Gmbh Planungsb\u00fcro F\u00fcr Haustechnik",
    "wof:placetype":"venue"
},
  "geometry": {"coordinates":[8.16682,47.41658],"type":"Point"}
}