{
  "type": "Feature",
  "properties": {
    "iso:country":"CH",
    "sg:address":"Wolhuserstrasse 1",
    "sg:city":"Menznau",
    "sg:classifiers":[
        {
            "category":"Travel",
            "subcategory":"Hotels & Motels",
            "type":"Entertainment"
        }
    ],
    "sg:phone":"+41 41 493 11 32",
    "sg:postcode":"6122",
    "sg:province":"Luzern",
    "sg:tags":[
        "hotels",
        "mit",
        "restaurant"
    ],
    "wof:name":"Dobmann Fridolin Gasthof Lamm",
    "wof:placetype":"venue"
},
  "geometry": {"coordinates":[8.0392494202,47.0830345154],"type":"Point"}
}