{
  "type": "Feature",
  "properties": {
    "iso:country":"CH",
    "sg:address":"Route De Moncor 2",
    "sg:city":"Villars-sur-gl\u00e2ne",
    "sg:orig_category":"Softwareentwicklung U beratung Sonstige mit der Informatik verbundene T\u00e4tigkeiten",
    "sg:phone":"+41 26 401 31 20",
    "sg:postcode":"1752",
    "sg:province":"Fribourg",
    "wof:name":"Medisys Integra Sa Conseils & D\u00e9veloppem.software",
    "wof:placetype":"venue"
},
  "geometry": {"coordinates":[7.1267280579,46.7985572815],"type":"Point"}
}