{
  "type": "Feature",
  "properties": {
    "iso:country":"CH",
    "sg:address":"Unterdorfstrasse 18",
    "sg:city":"Diepoldsau",
    "sg:orig_category":"Gartenbau",
    "sg:phone":"+41 71 733 32 40",
    "sg:postcode":"9444",
    "sg:province":"St. Gallen",
    "wof:name":"Roland Vorbeck Gartenbau & -pflege",
    "wof:placetype":"venue"
},
  "geometry": {"coordinates":[9.6511087418,47.3853797913],"type":"Point"}
}