{
  "type": "Feature",
  "properties": {
    "iso:country":"CH",
    "sg:address":"Hauptstrasse 46a",
    "sg:city":"Kreuzlingen",
    "sg:orig_category":"Versicherungsagenturen and -broker -Verm\u00f6gensverwaltung",
    "sg:phone":"+41 71 672 22 88",
    "sg:postcode":"8280",
    "sg:province":"Thurgau",
    "wof:name":"Hans-martin Freyer",
    "wof:placetype":"venue"
},
  "geometry": {"coordinates":[9.1743011475,47.6502418518],"type":"Point"}
}