{
  "type": "Feature",
  "properties": {
    "iso:country":"CH",
    "sg:address":"4116",
    "sg:city":"Metzerlen",
    "sg:classifiers":[
        {
            "category":"Travel",
            "subcategory":"Hotels & Motels",
            "type":"Entertainment"
        }
    ],
    "sg:postcode":"4116",
    "sg:province":"Solothurn",
    "sg:tags":[
        "hotels",
        "mit",
        "restaurant"
    ],
    "wof:name":"Riss Ren\u00e9",
    "wof:placetype":"venue"
},
  "geometry": {"coordinates":[7.4650502205,47.4659118652],"type":"Point"}
}