{
  "type": "Feature",
  "properties": {
    "iso:country":"CH",
    "sg:address":"Romont Rue De 12 1700 Fribourg Case Postale 599",
    "sg:city":"Fribourg",
    "sg:classifiers":[
        {
            "category":"Professional",
            "subcategory":"Employment Agencies",
            "type":"Services"
        }
    ],
    "sg:phone":"+41 26 347 40 40",
    "sg:postcode":"1700",
    "sg:province":"Fribourg",
    "sg:tags":[
        "personal",
        "u",
        "stellenvermittlung"
    ],
    "wof:name":"Manpower Sa, Succursale De Fribourg",
    "wof:placetype":"venue"
},
  "geometry": {"coordinates":[7.1550121307,46.8046340942],"type":"Point"}
}