{
  "type": "Feature",
  "properties": {
    "iso:country":"CH",
    "sg:address":"2740 Montagne-moutier. Postfach",
    "sg:city":"Montagne-moutier",
    "sg:orig_category":"Politische Parteien FDP",
    "sg:phone":"+41 32 751 14 26",
    "sg:postcode":"2740",
    "sg:province":"Bern",
    "wof:name":"Prd District De La Neuveville",
    "wof:placetype":"venue"
},
  "geometry": {"coordinates":[7.1061468124,47.0692367554],"type":"Point"}
}