{
  "type": "Feature",
  "properties": {
    "iso:country":"CH",
    "sg:address":"Winterthurerstrasse 190",
    "sg:city":"Z\u00fcrich",
    "sg:orig_category":"Datenverarbeitungsdienste",
    "sg:phone":"+41 12574311",
    "sg:postcode":"8057",
    "sg:province":"Z\u00fcrich",
    "wof:name":"Universit\u00e4t Z\u00fcrich Informatik Dienste Zentrum",
    "wof:placetype":"venue"
},
  "geometry": {"coordinates":[8.546739,47.397598],"type":"Point"}
}