{
  "type": "Feature",
  "properties": {
    "iso:country":"CH",
    "sg:address":"Rue Bonne-de-bourbon 12",
    "sg:city":"Martigny",
    "sg:orig_category":"Bauschreinerei Herstellung von M\u00f6beln verschiedener Art",
    "sg:phone":"+41 31 305 80 60",
    "sg:postcode":"1920",
    "sg:province":"Valais",
    "wof:name":"Le Docteur Des Meubles D.schindler Antikschreinerei",
    "wof:placetype":"venue"
},
  "geometry": {"coordinates":[7.430946,46.975182],"type":"Point"}
}