{
  "type": "Feature",
  "properties": {
    "iso:country":"CH",
    "sg:address":"Avenue Des Alpes 27",
    "sg:city":"Montreux",
    "sg:orig_category":"Detailhandel mit Gebrauchtwaren in Verkaufsr\u00e4umen",
    "sg:phone":"+41 21 963 93 43",
    "sg:postcode":"1820",
    "sg:province":"Vaud",
    "wof:name":"Hiob International Brockenstube",
    "wof:placetype":"venue"
},
  "geometry": {"coordinates":[6.9106287956,46.4341583252],"type":"Point"}
}