{
  "type": "Feature",
  "properties": {
    "iso:country":"CH",
    "sg:address":"6038 Honau. Postfach 172",
    "sg:city":"Ebikon",
    "sg:orig_category":"Gemeindeverwaltungen",
    "sg:phone":"+41 17284111",
    "sg:postcode":"6031",
    "sg:province":"Luzern",
    "wof:name":"Gemeindeverwaltung Horgen",
    "wof:placetype":"venue"
},
  "geometry": {"coordinates":[8.5971317291,47.2611961365],"type":"Point"}
}