{
  "type": "Feature",
  "properties": {
    "iso:country":"CH",
    "sg:address":"M\u00fchleweg 10",
    "sg:city":"Ebikon",
    "sg:orig_category":"Mit dem Versicherungsgewerbe verbundene T\u00e4tigkeiten",
    "sg:phone":"+41 41 440 46 00",
    "sg:postcode":"6030",
    "sg:province":"Luzern",
    "wof:name":"Versicherungs-treuhand Haas Gmbh",
    "wof:placetype":"venue"
},
  "geometry": {"coordinates":[8.3380231857,47.0736198425],"type":"Point"}
}