{
  "type": "Feature",
  "properties": {
    "iso:country":"CH",
    "sg:address":"Im Langstuck 16 8044 Gockhausen. Postfach",
    "sg:city":"Z\u00fcrich",
    "sg:classifiers":[
        {
            "category":"Professional",
            "subcategory":"Employment Agencies",
            "type":"Services"
        }
    ],
    "sg:postcode":"8006",
    "sg:province":"Z\u00fcrich",
    "sg:tags":[
        "personal",
        "u",
        "stellenvermittlung"
    ],
    "wof:name":"Hr Solutions Ag",
    "wof:placetype":"venue"
},
  "geometry": {"coordinates":[8.5799922943,47.3191452026],"type":"Point"}
}