{
  "type": "Feature",
  "properties": {
    "iso:country":"CH",
    "sg:address":"Via Ceresio 13",
    "sg:city":"Ruvigliana",
    "sg:classifiers":[
        {
            "category":"Restaurant",
            "type":"Food & Drink"
        }
    ],
    "sg:phone":"+41 91 971 29 19",
    "sg:postcode":"6977",
    "sg:province":"Ticino",
    "wof:name":"Birreria Ticinese",
    "wof:placetype":"venue"
},
  "geometry": {"coordinates":[8.9738998413,46.0054206848],"type":"Point"}
}