{
  "type": "Feature",
  "properties": {
    "iso:country":"CH",
    "sg:address":"Goldauerstrasse 62",
    "sg:city":"Z\u00fcrich",
    "sg:orig_category":"Markt U Meinungsforschung",
    "sg:phone":"+41 13626410",
    "sg:postcode":"8006",
    "sg:province":"Z\u00fcrich",
    "wof:name":"Andrea Meloni, Beratung F\u00fcr Marketing Und Kommunikation",
    "wof:placetype":"venue"
},
  "geometry": {"coordinates":[8.5494298935,47.3898582458],"type":"Point"}
}