{
  "type": "Feature",
  "properties": {
    "iso:country":"CH",
    "sg:address":"Landstrasse 121",
    "sg:city":"Wettingen",
    "sg:classifiers":[
        {
            "category":"Shopping",
            "subcategory":"Mobile Phones",
            "type":"Retail Goods"
        }
    ],
    "sg:phone":"+41 91 695 51 70",
    "sg:postcode":"5430",
    "sg:province":"Aargau",
    "sg:tags":[
        "trade",
        "accessory"
    ],
    "wof:name":"Technocell Suisse Sa",
    "wof:placetype":"venue"
},
  "geometry": {"coordinates":[9.0203924179,45.8414268494],"type":"Point"}
}