{
  "type": "Feature",
  "properties": {
    "iso:country":"CH",
    "sg:address":"Hauptstrasse 24",
    "sg:city":"Titterten",
    "sg:orig_category":"Erbringung von Dienstleistungen f\u00fcr Unternehmen",
    "sg:phone":"+41 61 945 95 11",
    "sg:postcode":"4425",
    "sg:province":"Basel-Landschaft",
    "wof:name":"Schmutz & Pfister, Grafik + Werbung",
    "wof:placetype":"venue"
},
  "geometry": {"coordinates":[7.7172131538,47.402633667],"type":"Point"}
}