{
  "type": "Feature",
  "properties": {
    "iso:country":"CH",
    "sg:address":"Gustav-kahlenbach-platz",
    "sg:city":"Rheinfelden",
    "sg:orig_category":"Vorschulen, Kinderg\u00e4rten",
    "sg:phone":"+41 31 767 87 95",
    "sg:postcode":"4310",
    "sg:province":"Aargau",
    "wof:name":"Kindergarten",
    "wof:placetype":"venue"
},
  "geometry": {"coordinates":[7.5171599388,47.0950622559],"type":"Point"}
}