{
  "type": "Feature",
  "properties": {
    "iso:country":"CH",
    "sg:address":"Via Dalla Resga",
    "sg:city":"Rh\u00e4z\u00fcns",
    "sg:orig_category":"S\u00e4ge, Hobel U Holzimpr\u00e4gnierwerke S\u00e4gewerke",
    "sg:phone":"+41 81 641 11 40",
    "sg:postcode":"7403",
    "sg:province":"Graubunden",
    "wof:name":"Berger Fritz Ag",
    "wof:placetype":"venue"
},
  "geometry": {"coordinates":[9.3967962265,46.7969779968],"type":"Point"}
}