{
  "type": "Feature",
  "properties": {
    "iso:country":"CH",
    "sg:address":"Kirchstrasse 2",
    "sg:city":"Liebefeld",
    "sg:classifiers":[
        {
            "category":"Government",
            "subcategory":"Post Office",
            "type":"Public Place"
        }
    ],
    "sg:phone":"+41 31 972 17 27",
    "sg:postcode":"3097",
    "sg:province":"Bern",
    "sg:tags":[
        "caf\u00e9s",
        "tea-rooms"
    ],
    "wof:name":"Caf\u00e9 Pause Ag",
    "wof:placetype":"venue"
},
  "geometry": {"coordinates":[7.4280738831,46.9303894043],"type":"Point"}
}