{
  "type": "Feature",
  "properties": {
    "iso:country":"CH",
    "sg:address":"Hasenweid 3 4600 Olten. Postfach",
    "sg:city":"Olten",
    "sg:orig_category":"Technische, physikalische U chemische Untersuchung",
    "sg:phone":"+41 62 213 05 82",
    "sg:postcode":"4600",
    "sg:province":"Solothurn",
    "wof:name":"Menet Dr. Urs Gis- & Umweltberatung Expertisen U. Beratung Im Umweltbereich. Beratung Im Bereich Von Geografischen Informationssystemen",
    "wof:placetype":"venue"
},
  "geometry": {"coordinates":[7.8958649635,47.3552017212],"type":"Point"}
}