{
  "type": "Feature",
  "properties": {
    "iso:country":"CH",
    "sg:address":"Theytaz Ruelle Alo\u00efs 33",
    "sg:city":"Sierre",
    "sg:orig_category":"Bau von Strassen, Sportanlagen U Bahnverkehrsstrecken",
    "sg:phone":"+41 32 637 10 37",
    "sg:postcode":"3960",
    "sg:province":"Valais",
    "wof:name":"Batigroup Sa",
    "wof:placetype":"venue"
},
  "geometry": {"coordinates":[7.532164,46.296577],"type":"Point"}
}