{
  "type": "Feature",
  "properties": {
    "iso:country":"CH",
    "sg:address":"Avenue G\u00e9n\u00e9ral-guisan 21",
    "sg:city":"Vevey",
    "sg:orig_category":"Detailhandel mit Fleisch U Fleischwaren",
    "sg:phone":"+41 21 921 66 51",
    "sg:postcode":"1800",
    "sg:province":"Vaud",
    "wof:name":"Philippe Stuby Boucherie",
    "wof:placetype":"venue"
},
  "geometry": {"coordinates":[6.8404378891,46.4638252258],"type":"Point"}
}