{
  "type": "Feature",
  "properties": {
    "iso:country":"CH",
    "sg:address":"Arcas 21",
    "sg:city":"Chur",
    "sg:orig_category":"Lichtpause U Reprografiebetriebe Satzherstellung U Reproduktion",
    "sg:phone":"+41 41 280 78 15",
    "sg:postcode":"7000",
    "sg:province":"Graubunden",
    "wof:name":"Multi-reflex Ag",
    "wof:placetype":"venue"
},
  "geometry": {"coordinates":[8.3041248322,47.0428657532],"type":"Point"}
}