{
  "type": "Feature",
  "properties": {
    "iso:country":"CH",
    "sg:address":"Luxburgstrasse 9",
    "sg:city":"Egnach",
    "sg:orig_category":"Arztpraxen",
    "sg:phone":"+41 71 477 21 36",
    "sg:postcode":"9322",
    "sg:province":"Thurgau",
    "wof:name":"Dr.med.rolf Streckeisen Arzt F\u00fcr Allgemeine Medizin",
    "wof:placetype":"venue"
},
  "geometry": {"coordinates":[9.380468,47.543575],"type":"Point"}
}