{
  "type": "Feature",
  "properties": {
    "iso:country":"CH",
    "sg:address":"1248",
    "sg:city":"Hermance",
    "sg:orig_category":"Sportvereine Ballsport Fussball",
    "sg:phone":"+41 22 361 22 39",
    "sg:postcode":"1248",
    "sg:province":"Gen\u00e8ve",
    "wof:name":"Fc Hermandad Espagnol",
    "wof:placetype":"venue"
},
  "geometry": {"coordinates":[6.2390799522,46.382358551],"type":"Point"}
}