{
  "type": "Feature",
  "properties": {
    "iso:country":"CH",
    "sg:address":"Ernital",
    "sg:city":"Beckenried",
    "sg:orig_category":"Mechanik",
    "sg:postcode":"6375",
    "sg:province":"Nidwalden",
    "wof:name":"Ernital Allround Gmbh",
    "wof:placetype":"venue"
},
  "geometry": {"coordinates":[8.473195076,46.9684066772],"type":"Point"}
}