{
  "type": "Feature",
  "properties": {
    "iso:country":"CH",
    "sg:address":"Erlenstrasse 14",
    "sg:city":"Steffisburg",
    "sg:orig_category":"Primarschulen",
    "sg:phone":"+41 33 437 63 21",
    "sg:postcode":"3612",
    "sg:province":"Bern",
    "wof:name":"Primarschule Erlen",
    "wof:placetype":"venue"
},
  "geometry": {"coordinates":[7.6352410316,46.7760658264],"type":"Point"}
}