{
  "type": "Feature",
  "properties": {
    "iso:country":"CH",
    "sg:address":"Rufacherstrasse 20",
    "sg:city":"Basel",
    "sg:orig_category":"Unclassifiable Establishments",
    "sg:postcode":"4055",
    "sg:province":"Basel-Stadt",
    "wof:name":"Antiquariat Dr. Karl Ruetz",
    "wof:placetype":"venue"
},
  "geometry": {"coordinates":[7.5722417831,47.5580635071],"type":"Point"}
}