{
  "type": "Feature",
  "properties": {
    "iso:country":"CH",
    "sg:address":"Rosemont Avenue 11 1208 Gen\u00e8ve. Postfach",
    "sg:city":"Gen\u00e8ve",
    "sg:orig_category":"Rechtsberatung",
    "sg:postcode":"1208",
    "sg:province":"Gen\u00e8ve",
    "wof:name":"Yearly Organizing Reunion Of International Civil Services: Yorics",
    "wof:placetype":"venue"
},
  "geometry": {"coordinates":[6.1724081039,46.2020378113],"type":"Point"}
}