{
  "type": "Feature",
  "properties": {
    "iso:country":"CH",
    "sg:address":"Vogesenstrasse 32 4056 Basel. Postfach",
    "sg:city":"Basel",
    "sg:orig_category":"Bauingenieurb\u00fcros Sanit\u00e4r",
    "sg:phone":"+41 61 383 22 22",
    "sg:postcode":"4011",
    "sg:province":"Basel-Stadt",
    "wof:name":"Locher Schwittay Geb\u00e4udetechnik Gmbh",
    "wof:placetype":"venue"
},
  "geometry": {"coordinates":[7.579066,47.565819],"type":"Point"}
}