{
  "type": "Feature",
  "properties": {
    "iso:country":"CH",
    "sg:address":"Rueun",
    "sg:city":"Rueun",
    "sg:classifiers":[
        {
            "category":"Banks & Credit Unions",
            "subcategory":"Bank",
            "type":"Services"
        }
    ],
    "sg:phone":"+41 32 637 11 73",
    "sg:postcode":"7156",
    "sg:province":"Graubunden",
    "wof:name":"Raiffeisenbank Guensberg",
    "wof:placetype":"venue"
},
  "geometry": {"coordinates":[7.54134,47.262203],"type":"Point"}
}