{
  "type": "Feature",
  "properties": {
    "iso:country":"CH",
    "sg:address":"Rue Du Simplon 15",
    "sg:city":"Payerne",
    "sg:orig_category":"Detailhandel mit Sportartikeln Fachdetailhandel in Verkaufsr\u00e4umen",
    "sg:phone":"+41 26 660 35 50",
    "sg:postcode":"1530",
    "sg:province":"Vaud",
    "wof:name":"Surf Machine S\u00e0rl",
    "wof:placetype":"venue"
},
  "geometry": {"coordinates":[6.9357628822,46.8188552856],"type":"Point"}
}