{
  "type": "Feature",
  "properties": {
    "iso:country":"CH",
    "sg:address":"Baselstrasse 28",
    "sg:city":"Zwingen",
    "sg:orig_category":"Dachdeckerei Zimmerei, Dachdeckerei, Bauspenglerei U Abdichtung",
    "sg:phone":"+41 61 761 55 25",
    "sg:postcode":"4222",
    "sg:province":"Basel-Landschaft",
    "wof:name":"Meury Zimmerei-bedachungen Ag",
    "wof:placetype":"venue"
},
  "geometry": {"coordinates":[7.545589,47.442253],"type":"Point"}
}