{
  "type": "Feature",
  "properties": {
    "iso:country":"CH",
    "sg:address":"Dorfstrasse 15",
    "sg:city":"Wuppenau",
    "sg:orig_category":"Bau von Strassen, Sportanlagen U Bahnverkehrsstrecken",
    "sg:postcode":"9514",
    "sg:province":"Thurgau",
    "wof:name":"Egolf Ag Weinfelden",
    "wof:placetype":"venue"
},
  "geometry": {"coordinates":[9.106861,47.495266],"type":"Point"}
}