{
  "type": "Feature",
  "properties": {
    "iso:country":"CH",
    "sg:address":"Fr\u00e9d\u00e9ric-c\u00e9sar-de-la-harpe Av 16",
    "sg:city":"Lausanne",
    "sg:orig_category":"Unternehmensberatung",
    "sg:phone":"+41 31 991 72 84",
    "sg:postcode":"1000",
    "sg:province":"Vaud",
    "wof:name":"Les Consultants Associ\u00e9s, Brunner, Von Beust & Tchicaloff",
    "wof:placetype":"venue"
},
  "geometry": {"coordinates":[6.6947751045,46.5545883179],"type":"Point"}
}