{
  "type": "Feature",
  "properties": {
    "iso:country":"CH",
    "sg:address":"Unterlauelen Eigenthal 6052 Hergiswil Nw. Postfach",
    "sg:city":"Eigenthal",
    "sg:orig_category":"RESTAURANTS: TEA-ROOMS",
    "sg:postcode":"6013",
    "sg:province":"Luzern",
    "wof:name":"Tschopp Urs",
    "wof:placetype":"venue"
},
  "geometry": {"coordinates":[8.3112096786,46.9831390381],"type":"Point"}
}