{
  "type": "Feature",
  "properties": {
    "iso:country":"CH",
    "sg:address":"Bitzistrasse 14",
    "sg:city":"Siebnen",
    "sg:orig_category":"Grosshandel mit B\u00fcromaschinen Grosshandel mit Datenverarbeitungsger\u00e4ten",
    "sg:phone":"+41 55 460 29 00",
    "sg:postcode":"8854",
    "sg:province":"Schwyz",
    "wof:name":"Socomm Gmbh",
    "wof:placetype":"venue"
},
  "geometry": {"coordinates":[8.9034976959,47.1771240234],"type":"Point"}
}