{
  "type": "Feature",
  "properties": {
    "iso:country":"CH",
    "sg:address":"Bernstrasse 99b",
    "sg:city":"Burgdorf",
    "sg:orig_category":"Detailhandel mit Sportartikeln",
    "sg:phone":"+41 34 422 48 87",
    "sg:postcode":"3400",
    "sg:province":"Bern",
    "wof:name":"Hugi-sport",
    "wof:placetype":"venue"
},
  "geometry": {"coordinates":[7.6143898964,47.0535507202],"type":"Point"}
}