{
  "type": "Feature",
  "properties": {
    "iso:country":"CH",
    "sg:address":"Bresteneggstr. 17",
    "sg:city":"Buchs",
    "sg:classifiers":[
        {
            "category":"Manufacturing",
            "subcategory":"Chemicals & Compounds",
            "type":"Manufacturing & Wholesale Goods"
        }
    ],
    "sg:phone":"+41 62 837 93 00",
    "sg:postcode":"5033",
    "sg:province":"Aargau",
    "sg:tags":[
        "pharmaceutical",
        "chemistry",
        "-",
        "by-product"
    ],
    "wof:name":"Basler Lacke Ag",
    "wof:placetype":"venue"
},
  "geometry": {"coordinates":[8.08923,47.385849],"type":"Point"}
}