{
  "type": "Feature",
  "properties": {
    "iso:country":"CH",
    "sg:address":"Baarerstrasse 10",
    "sg:city":"Zug",
    "sg:orig_category":"RESTAURANTS: TEA-ROOMS",
    "sg:phone":"+41 41 711 90 70",
    "sg:postcode":"6300",
    "sg:province":"Zug",
    "wof:name":"Ruckli Xaver Restaurant Braust\u00fcbli.",
    "wof:placetype":"venue"
},
  "geometry": {"coordinates":[8.5164327621,47.1715621948],"type":"Point"}
}