{
  "type": "Feature",
  "properties": {
    "iso:country":"CH",
    "sg:address":"Bernstrasse 79",
    "sg:city":"Ostermundigen",
    "sg:orig_category":"Detailhandel mit Waren verschiedener Art, Hauptrichtung Nahrungsmittel",
    "sg:phone":"+41 31 931 60 55",
    "sg:postcode":"3072",
    "sg:province":"Bern",
    "wof:name":"Volg Detailhandels Ag Volg Markt",
    "wof:placetype":"venue"
},
  "geometry": {"coordinates":[7.4912281036,46.9584121704],"type":"Point"}
}