{
  "type": "Feature",
  "properties": {
    "iso:country":"CH",
    "sg:address":"Baumackerstrasse 24",
    "sg:city":"Z\u00fcrich",
    "sg:classifiers":[
        {
            "category":"Airport",
            "subcategory":"International",
            "type":"Transportation"
        }
    ],
    "sg:phone":"+41 32 925 98 00",
    "sg:postcode":"8050",
    "sg:province":"Z\u00fcrich",
    "sg:tags":[
        "transport"
    ],
    "wof:name":"Air Terre Mer Transports S.a.",
    "wof:placetype":"venue"
},
  "geometry": {"coordinates":[6.8051810265,47.0893974304],"type":"Point"}
}