{
  "type": "Feature",
  "properties": {
    "iso:country":"CH",
    "sg:address":"6285",
    "sg:city":"Hitzkirch",
    "sg:orig_category":"Gesundheitswesen",
    "sg:phone":"+41 41 917 29 29",
    "sg:postcode":"6285",
    "sg:province":"Luzern",
    "wof:name":"Sattler-suter Stiftung",
    "wof:placetype":"venue"
},
  "geometry": {"coordinates":[8.2632598877,47.2249412537],"type":"Point"}
}