{
  "type": "Feature",
  "properties": {
    "iso:country":"CH",
    "sg:address":"Orpundstrasse 31",
    "sg:city":"Biel/bienne",
    "sg:orig_category":"Innendekorationsateliers",
    "sg:phone":"+41 32 341 34 40",
    "sg:postcode":"2504",
    "sg:province":"Bern",
    "wof:name":"Achille Donz\u00e9 Tapezierer-dekorateurgesch\u00e4ft",
    "wof:placetype":"venue"
},
  "geometry": {"coordinates":[7.2766089439,47.1433334351],"type":"Point"}
}