{
  "type": "Feature",
  "properties": {
    "iso:country":"CH",
    "sg:address":"Schulhausstrasse 4",
    "sg:city":"Oberdiessbach",
    "sg:orig_category":"Grosshandel mit lebenden Tieren",
    "sg:phone":"+41 32 396 13 86",
    "sg:postcode":"3672",
    "sg:province":"Bern",
    "wof:name":"Fritz Winkelmann Viehhandel",
    "wof:placetype":"venue"
},
  "geometry": {"coordinates":[7.1874079704,47.0298538208],"type":"Point"}
}