{
  "type": "Feature",
  "properties": {
    "iso:country":"CH",
    "sg:address":"Dorfstrasse 38",
    "sg:city":"Wangs",
    "sg:orig_category":"Nationale Postdienste",
    "sg:phone":"+41 81 723 12 81",
    "sg:postcode":"7323",
    "sg:province":"St. Gallen",
    "wof:name":"Die Schweizerische Post",
    "wof:placetype":"venue"
},
  "geometry": {"coordinates":[9.4310264587,47.0313072205],"type":"Point"}
}