{
  "type": "Feature",
  "properties": {
    "iso:country":"CH",
    "sg:address":"Bahnhofstrasse 3792 Saanen. Postfach 7",
    "sg:city":"Saanen",
    "sg:orig_category":"Regionalbanken U Sparkassen",
    "sg:phone":"+41 33 755 81 86",
    "sg:postcode":"3792",
    "sg:province":"Bern",
    "wof:name":"Saanen Bank",
    "wof:placetype":"venue"
},
  "geometry": {"coordinates":[7.2673168182,46.3836975098],"type":"Point"}
}