{
  "type": "Feature",
  "properties": {
    "iso:country":"CH",
    "sg:address":"Nord Rue Du 4",
    "sg:city":"Martigny",
    "sg:orig_category":"Interessenvertretungen",
    "sg:postcode":"1920",
    "sg:province":"Valais",
    "wof:name":"Fondation Auxiliaire De L'h\u00f4pital Jeanjaquet",
    "wof:placetype":"venue"
},
  "geometry": {"coordinates":[6.9108829498,46.9862289429],"type":"Point"}
}