{
  "type": "Feature",
  "properties": {
    "iso:country":"CH",
    "sg:address":"Frankenstrasse 30 3018 Bern. Postfach",
    "sg:city":"Bern",
    "sg:orig_category":"Grosshandel mit sonstigen Maschinen U Ausr\u00fcstungen f\u00fcr Industrie, Handel U Schiffahrt",
    "sg:postcode":"3018",
    "sg:province":"Bern",
    "wof:name":"Colic & Co. Maschinen Usw; Exp. Imp.",
    "wof:placetype":"venue"
},
  "geometry": {"coordinates":[7.3951611519,46.9402999878],"type":"Point"}
}