{
  "type": "Feature",
  "properties": {
    "addr:full":"Kreuzgasse Fideris Graubunden 7235",
    "addr:postcode":"7235",
    "addr:street":"Kreuzgasse;Graubunden",
    "iso:country":"CH",
    "sg:address":"Kreuzgasse",
    "sg:city":"Fideris",
    "sg:orig_category":"Architekturb\u00fcros Zimmerei, Dachdeckerei, Bauspenglerei U Abdichtung",
    "sg:phone":"+41 81 332 27 24",
    "sg:postcode":"7235",
    "sg:province":"Graubunden",
    "wof:name":"Hans Auer Holzbau",
    "wof:placetype":"venue"
},
  "geometry": {"coordinates":[9.743021,46.915062],"type":"Point"}
}