{
  "type": "Feature",
  "properties": {
    "iso:country":"CH",
    "sg:address":"Burgstrasse 26",
    "sg:city":"Glarus",
    "sg:orig_category":"Advokaturb\u00fcros",
    "sg:phone":"+41 55 640 14 67",
    "sg:postcode":"8750",
    "sg:province":"Glarus",
    "wof:name":"Heer Auer & Meier Advokaturb\u00fcro",
    "wof:placetype":"venue"
},
  "geometry": {"coordinates":[9.068803,47.041115],"type":"Point"}
}