{
  "type": "Feature",
  "properties": {
    "iso:country":"CH",
    "sg:address":"Solothurner Str. 259",
    "sg:city":"Olten",
    "sg:orig_category":"Banking institutions Banking, finance and insurances Metallurgy and Metalworking Miscellaneous Produ",
    "sg:phone":"+41 62 205 96 96",
    "sg:postcode":"4600",
    "sg:province":"Solothurn",
    "wof:name":"Ero Holding Sa",
    "wof:placetype":"venue"
},
  "geometry": {"coordinates":[7.887418,47.347366],"type":"Point"}
}