{
  "type": "Feature",
  "properties": {
    "iso:country":"CH",
    "sg:address":"Lettenstrasse 10",
    "sg:city":"Windisch",
    "sg:orig_category":"Herstellung von Konstruktionsteilen, Fertigbauteilen U Ausbauelementen aus Holz Innenausbau",
    "sg:phone":"+41 32 351 23 36",
    "sg:postcode":"5210",
    "sg:province":"Aargau",
    "wof:name":"Hofer + Burri Ag",
    "wof:placetype":"venue"
},
  "geometry": {"coordinates":[7.3607430458,47.1074867249],"type":"Point"}
}