{
  "type": "Feature",
  "properties": {
    "iso:country":"CH",
    "sg:address":"Rue De Lausanne 35",
    "sg:city":"Sitten",
    "sg:orig_category":"Softwareentwicklung U beratung Sonstige mit der Informatik verbundene T\u00e4tigkeiten",
    "sg:phone":"+41 27 323 78 70",
    "sg:postcode":"1950",
    "sg:province":"Valais",
    "wof:name":"Sopra Informatique",
    "wof:placetype":"venue"
},
  "geometry": {"coordinates":[7.3572230339,46.2318992615],"type":"Point"}
}