{
  "type": "Feature",
  "properties": {
    "iso:country":"CH",
    "sg:address":"Gemeindehaus",
    "sg:city":"R\u00fcdlingen",
    "sg:orig_category":"Grosshandel mit Nahrungsmitteln, Getr\u00e4nken U Tabakwaren ohne ausgepr\u00e4gten Schwerpunkt",
    "sg:postcode":"8455",
    "sg:province":"Schaffhausen",
    "wof:name":"Werner Eigenmann, Spar-markt",
    "wof:placetype":"venue"
},
  "geometry": {"coordinates":[8.5720300674,47.5793533325],"type":"Point"}
}