{
  "type": "Feature",
  "properties": {
    "iso:country":"CH",
    "sg:address":"Wydackerstrasse 12 8152 Glattbrugg. Postfach",
    "sg:city":"Glattbrugg",
    "sg:orig_category":"Sonstige mit der Informatik verbundene T\u00e4tigkeiten Sonstiges Druckgewerbe",
    "sg:phone":"+41 18111401",
    "sg:postcode":"8152",
    "sg:province":"Z\u00fcrich",
    "wof:name":"Sign & Print Glesti Gmbh Vertrieb U. Handel Von Kompletl\u00f6sungen Auf Dem Gebiet Von Sign-making U. Digital-druck Usw",
    "wof:placetype":"venue"
},
  "geometry": {"coordinates":[8.5679693222,47.4284095764],"type":"Point"}
}