{
  "type": "Feature",
  "properties": {
    "iso:country":"CH",
    "sg:address":"Baarerstrasse 79",
    "sg:city":"Zug",
    "sg:orig_category":"Detailhandel mit Metallwaren, Anstrichmitteln, Glaswaren, Bau U Heimwerkerbedarf",
    "sg:phone":"+41 18330279",
    "sg:postcode":"6300",
    "sg:province":"Zug",
    "wof:name":"Unitech Zinsli G.",
    "wof:placetype":"venue"
},
  "geometry": {"coordinates":[8.6429491043,47.4122390747],"type":"Point"}
}