{
  "type": "Feature",
  "properties": {
    "iso:country":"CH",
    "sg:address":"Hochstrasse 182",
    "sg:city":"Schaffhausen",
    "sg:orig_category":"Allgemeiner Hoch U Tiefbau",
    "sg:phone":"+41 52 624 59 12",
    "sg:postcode":"8200",
    "sg:province":"Schaffhausen",
    "wof:name":"Primag Ag, Schaffhausen",
    "wof:placetype":"venue"
},
  "geometry": {"coordinates":[8.641023,47.711403],"type":"Point"}
}