{
  "type": "Feature",
  "properties": {
    "iso:country":"CH",
    "sg:address":"Haselstrasse 17",
    "sg:city":"Oberkulm",
    "sg:orig_category":"Herstellung von Metallkonstruktionen Schlossereien",
    "sg:phone":"+41 19100053",
    "sg:postcode":"5727",
    "sg:province":"Aargau",
    "wof:name":"Willi Fus Schlosserei & Metallbau",
    "wof:placetype":"venue"
},
  "geometry": {"coordinates":[8.585062027,47.318069458],"type":"Point"}
}