{
  "type": "Feature",
  "properties": {
    "iso:country":"CH",
    "sg:address":"Amweg Rue Gustave 21",
    "sg:city":"Porrentruy",
    "sg:orig_category":"Gesundheitswesen",
    "sg:phone":"+41 32 466 73 23",
    "sg:postcode":"2900",
    "sg:province":"Jura",
    "wof:name":"Ppm Physio Philippe Mayeur S\u00e0rl",
    "wof:placetype":"venue"
},
  "geometry": {"coordinates":[7.07787323,47.4193382263],"type":"Point"}
}