{
  "type": "Feature",
  "properties": {
    "iso:country":"CH",
    "sg:address":"Steinauweg 29",
    "sg:city":"Bern",
    "sg:orig_category":"Architekturb\u00fcros",
    "sg:phone":"+41 31 371 42 52",
    "sg:postcode":"3007",
    "sg:province":"Bern",
    "wof:name":"Sandro Eberhart Architekturb\u00fcro",
    "wof:placetype":"venue"
},
  "geometry": {"coordinates":[7.429584,46.937366],"type":"Point"}
}