{
  "type": "Feature",
  "properties": {
    "iso:country":"CH",
    "sg:address":"Kirchstrasse 5a 8280 Kreuzlingen. Postfach 548",
    "sg:city":"Kreuzlingen",
    "sg:orig_category":"Dienstleistungen von Beteiligungsgesellschaften",
    "sg:phone":"+41 71 672 21 39",
    "sg:postcode":"8280",
    "sg:province":"Thurgau",
    "wof:name":"Hager Gebr\u00fcder Ag",
    "wof:placetype":"venue"
},
  "geometry": {"coordinates":[9.173122406,47.646987915],"type":"Point"}
}