{
  "type": "Feature",
  "properties": {
    "addr:full":"Rue De L'ecluse 30 Neuch\u00e2tel Neuch\u00e2tel 2000",
    "addr:housenumber":"30",
    "addr:postcode":"2000",
    "addr:street":"Rue De L'Ecluse",
    "iso:country":"CH",
    "sg:address":"Rue De L'ecluse 30",
    "sg:city":"Neuch\u00e2tel",
    "sg:orig_category":"Detailhandel mit Damenbekleidung",
    "sg:phone":"+41 32 724 10 13",
    "sg:postcode":"2000",
    "sg:province":"Neuch\u00e2tel",
    "wof:name":"Ackermann Shops Ag",
    "wof:placetype":"venue"
},
  "geometry": {"coordinates":[6.925963,46.992886],"type":"Point"}
}