{
  "type": "Feature",
  "properties": {
    "iso:country":"CH",
    "sg:address":"Rue Du Couchant 4 1400 Yverdon-les-bains Case Postale 411",
    "sg:city":"Yverdon-les-bains",
    "sg:orig_category":"Hobel U Holzimpr\u00e4gnierwerke Zimmerei, Dachdeckerei, Bauspenglerei U Abdichtung",
    "sg:phone":"+41 79 418 65 20",
    "sg:postcode":"1400",
    "sg:province":"Vaud",
    "wof:name":"Sani-bois, Overney Andr\u00e9",
    "wof:placetype":"venue"
},
  "geometry": {"coordinates":[6.6260561943,46.7792320251],"type":"Point"}
}