{
  "type": "Feature",
  "properties": {
    "iso:country":"CH",
    "sg:address":"Marktgasse 15",
    "sg:city":"Bern",
    "sg:orig_category":"Detailhandel mit Bekleidung",
    "sg:phone":"+41 81 413 65 05",
    "sg:postcode":"3011",
    "sg:province":"Bern",
    "wof:name":"Lwl Leinen Langenthal Ag",
    "wof:placetype":"venue"
},
  "geometry": {"coordinates":[9.821466,46.7957],"type":"Point"}
}