{
  "type": "Feature",
  "properties": {
    "iso:country":"CH",
    "sg:address":"Rue St-s\u00e9bastien 9 2800 Del\u00e9mont Case Postale 799",
    "sg:city":"Del\u00e9mont",
    "sg:orig_category":"Herstellung von pharmazeutischen Grundstoffen Herstellung von sonstigen organischen Grundstoffen U C",
    "sg:phone":"+41 32 422 42 74",
    "sg:postcode":"2800",
    "sg:province":"Jura",
    "wof:name":"Fettrelet M. Sa",
    "wof:placetype":"venue"
},
  "geometry": {"coordinates":[7.34227705,47.3544578552],"type":"Point"}
}