{
  "type": "Feature",
  "properties": {
    "iso:country":"CH",
    "sg:address":"Sand 8766 Matt. Postfach",
    "sg:city":"Matt",
    "sg:orig_category":"Non-Classified Establishments",
    "sg:postcode":"8766",
    "sg:province":"Glarus",
    "wof:name":"Marti Bauholding Ag",
    "wof:placetype":"venue"
},
  "geometry": {"coordinates":[9.1725101471,46.9570846558],"type":"Point"}
}