{
  "type": "Feature",
  "properties": {
    "iso:country":"CH",
    "sg:address":"Nordstrasse 138",
    "sg:city":"Z\u00fcrich",
    "sg:orig_category":"Wirtschaftspr\u00fcfung, Steuerberatung U Treuhand",
    "sg:phone":"+41 13613000",
    "sg:postcode":"8037",
    "sg:province":"Z\u00fcrich",
    "wof:name":"Tommasi & Partner Treuhandgesellschaft",
    "wof:placetype":"venue"
},
  "geometry": {"coordinates":[8.5336303711,47.3906364441],"type":"Point"}
}