{
  "type": "Feature",
  "properties": {
    "iso:country":"CH",
    "sg:address":"Aeschenvorstadt 48 4002 Basel. Postfach",
    "sg:city":"Basel",
    "sg:orig_category":"Kauf U Verkauf von Immobilien auf eigene Rechnung",
    "sg:phone":"+41 61 691 20 00",
    "sg:postcode":"4002",
    "sg:province":"Basel-Stadt",
    "wof:name":"Kimag Ag",
    "wof:placetype":"venue"
},
  "geometry": {"coordinates":[9.1283597946,46.2375984192],"type":"Point"}
}