{
  "type": "Feature",
  "properties": {
    "iso:country":"CH",
    "sg:address":"Sumpfstrasse 15 6312 Steinhausen. Postfach 227",
    "sg:city":"Steinhausen",
    "sg:orig_category":"Bau von Strassen, Sportanlagen U Bahnverkehrsstrecken Herstellung von Gummi U Kunststoffwaren",
    "sg:phone":"+41 41 741 44 45",
    "sg:postcode":"6312",
    "sg:province":"Zug",
    "wof:name":"Schwimmbad Und Wassertechnik Marlin Ag",
    "wof:placetype":"venue"
},
  "geometry": {"coordinates":[8.488814,47.186714],"type":"Point"}
}