{
  "type": "Feature",
  "properties": {
    "iso:country":"CH",
    "sg:address":"Tramstrasse 99 4132 Muttenz. Postfach",
    "sg:city":"Basel",
    "sg:orig_category":"Herstellung von Drahtwaren",
    "sg:phone":"+41 61 692 45 92",
    "sg:postcode":"4005",
    "sg:province":"Basel-Stadt",
    "wof:name":"Emil Hitz Ag Drahtwaren",
    "wof:placetype":"venue"
},
  "geometry": {"coordinates":[7.6342549324,47.5313949585],"type":"Point"}
}