{
  "type": "Feature",
  "properties": {
    "addr:full":"Luzernerstrasse 82b Adligenswil Luzern 6043",
    "addr:housenumber":"82b",
    "addr:postcode":"6043",
    "addr:street":"Luzernerstrasse",
    "iso:country":"CH",
    "sg:address":"Luzernerstrasse 82b",
    "sg:city":"Adligenswil",
    "sg:classifiers":[
        {
            "category":"Professional",
            "subcategory":"Advertising",
            "type":"Services"
        }
    ],
    "sg:phone":"+41 41 370 35 64",
    "sg:postcode":"6043",
    "sg:province":"Luzern",
    "sg:tags":[
        "film"
    ],
    "wof:name":"Nicolas Video Studio",
    "wof:placetype":"venue"
},
  "geometry": {"coordinates":[8.355991,47.063713],"type":"Point"}
}