{
  "type": "Feature",
  "properties": {
    "iso:country":"CH",
    "sg:address":"La Filature",
    "sg:city":"Ecl\u00e9pens",
    "sg:orig_category":"Herstellung von Holzstoff, Papier, Karton U Pappe",
    "sg:phone":"+41 31 340 88 88",
    "sg:postcode":"1312",
    "sg:province":"Vaud",
    "wof:name":"Mpa Multitec-polygraph Ag",
    "wof:placetype":"venue"
},
  "geometry": {"coordinates":[7.4652099609,46.9662094116],"type":"Point"}
}