{
  "type": "Feature",
  "properties": {
    "addr:full":"Hinterdorfstrasse 25 6430 Schwyz. Postfach 248 Schwyz Schwyz 6431",
    "addr:housenumber":"25;248",
    "addr:postcode":"6430;6431",
    "addr:street":"Hinterdorfstrasse;Postfach",
    "iso:country":"CH",
    "sg:address":"Hinterdorfstrasse 25 6430 Schwyz. Postfach 248",
    "sg:city":"Schwyz",
    "sg:orig_category":"Detailhandel mit Brot, Back U S\u00fcsswaren",
    "sg:phone":"+41 79 414 78 29",
    "sg:postcode":"6431",
    "sg:province":"Schwyz",
    "wof:name":"L\u00fc\u00f6nd Xaver Ag",
    "wof:placetype":"venue"
},
  "geometry": {"coordinates":[8.659312,47.020645],"type":"Point"}
}