{
  "type": "Feature",
  "properties": {
    "iso:country":"CH",
    "sg:address":"6716",
    "sg:city":"Leontica",
    "sg:orig_category":"Verwertung von Milch",
    "sg:postcode":"6716",
    "sg:province":"Ticino",
    "wof:name":"Latteria Sociale Di Leontica.",
    "wof:placetype":"venue"
},
  "geometry": {"coordinates":[8.9245700836,46.4594306946],"type":"Point"}
}