{
  "type": "Feature",
  "properties": {
    "addr:full":"1880 Bex Vaud 1880",
    "addr:postcode":"1880;1880",
    "iso:country":"CH",
    "sg:address":"1880",
    "sg:city":"Bex",
    "sg:orig_category":"Allgemeiner Hoch U Tiefbau",
    "sg:postcode":"1880",
    "sg:province":"Vaud",
    "wof:name":"Putallaz Jean-louis",
    "wof:placetype":"venue"
},
  "geometry": {"coordinates":[7.015681,46.250259],"type":"Point"}
}