{
  "type": "Feature",
  "properties": {
    "iso:country":"CH",
    "sg:address":"Sch\u00fctzenhalde 1070",
    "sg:city":"Wolfhalden",
    "sg:orig_category":"Wohnheime",
    "sg:postcode":"9427",
    "sg:province":"Appenzell Ausserrhoden",
    "wof:name":"Genossenschaft Alterssiedlung Kronenwiese, Wolfhalden",
    "wof:placetype":"venue"
},
  "geometry": {"coordinates":[9.5497522354,47.453414917],"type":"Point"}
}