{
  "type": "Feature",
  "properties": {
    "iso:country":"CH",
    "sg:address":"Poststrasse 9 3400 Burgdorf. Postfach",
    "sg:city":"Burgdorf",
    "sg:orig_category":"Garne U Zwirne",
    "sg:postcode":"3400",
    "sg:province":"Bern",
    "wof:name":"Wollenhof Rascher Frau Rosa.",
    "wof:placetype":"venue"
},
  "geometry": {"coordinates":[7.6237750053,47.0602912903],"type":"Point"}
}