{
  "type": "Feature",
  "properties": {
    "iso:country":"CH",
    "sg:address":"Dorfstrasse 39",
    "sg:city":"Wiesendangen",
    "sg:orig_category":"Zimmerei, Dachdeckerei, Bauspenglerei U Abdichtung",
    "sg:postcode":"8542",
    "sg:province":"Z\u00fcrich",
    "wof:name":"Erne Bedachungs Ag",
    "wof:placetype":"venue"
},
  "geometry": {"coordinates":[8.7890605927,47.5211105347],"type":"Point"}
}