{
  "type": "Feature",
  "properties": {
    "iso:country":"CH",
    "sg:address":"Dorfplatz 4",
    "sg:city":"Knutwil",
    "sg:orig_category":"Detailhandel mit Milcherzeugnissen U Eiern Verarbeitung von Milch",
    "sg:phone":"+41 71 994 11 70",
    "sg:postcode":"6213",
    "sg:province":"Luzern",
    "wof:name":"H. & R. Habegger K\u00e4serei",
    "wof:placetype":"venue"
},
  "geometry": {"coordinates":[9.1944189072,47.2296981812],"type":"Point"}
}