{
  "type": "Feature",
  "properties": {
    "iso:country":"CH",
    "sg:address":"Junkerngasse 34",
    "sg:city":"Bern",
    "sg:orig_category":"Kunsthandel",
    "sg:phone":"+41 31 311 31 91",
    "sg:postcode":"3011",
    "sg:province":"Bern",
    "wof:name":"Art & Vision Galerie Edith Th\u00f6nen",
    "wof:placetype":"venue"
},
  "geometry": {"coordinates":[7.4536161423,46.947807312],"type":"Point"}
}