{
  "type": "Feature",
  "properties": {
    "iso:country":"CH",
    "sg:address":"Industriestrasse 11 5102 Rupperswil. Postfach",
    "sg:city":"Rupperswil",
    "sg:orig_category":"Herstellung von Papier, Karton U Pappe Herstellung von Wellpapier U pappe sowie von Verpackungsmitte",
    "sg:phone":"+41 22 342 31 50",
    "sg:postcode":"5102",
    "sg:province":"Aargau",
    "wof:name":"Losey Jean Sa",
    "wof:placetype":"venue"
},
  "geometry": {"coordinates":[6.1455068588,46.1831054688],"type":"Point"}
}