{
  "type": "Feature",
  "properties": {
    "iso:country":"CH",
    "sg:city":"Beinwil Am See",
    "sg:orig_category":"Industrie, Elektronik U Elektrik",
    "sg:postcode":"5712",
    "sg:province":"Aargau",
    "wof:name":"Rcb Motorenbau Ag",
    "wof:placetype":"venue"
},
  "geometry": {"coordinates":[8.202939,47.266399],"type":"Point"}
}