{
  "type": "Feature",
  "properties": {
    "iso:country":"CH",
    "sg:address":"Kreuzlingerstrasse 37",
    "sg:city":"Amriswil",
    "sg:orig_category":"Bauschreinerei Herstellung von Konstruktionsteilen, Fertigbauteilen U Ausbauelementen aus Holz",
    "sg:phone":"+41 71 411 40 60",
    "sg:postcode":"8580",
    "sg:province":"Thurgau",
    "wof:name":"Schreiner R.",
    "wof:placetype":"venue"
},
  "geometry": {"coordinates":[9.278616,47.547348],"type":"Point"}
}