{
  "type": "Feature",
  "properties": {
    "iso:country":"CH",
    "sg:address":"Wiesenstrasse 18",
    "sg:city":"Langenthal",
    "sg:orig_category":"Arbeitnehmerverb\u00e4nde",
    "sg:phone":"+41 71 223 80 43",
    "sg:postcode":"4900",
    "sg:province":"Bern",
    "wof:name":"Schweiz. Verband Des Personals \u00f6ffentliche Dienste",
    "wof:placetype":"venue"
},
  "geometry": {"coordinates":[9.372148,47.424789],"type":"Point"}
}