{
  "type": "Feature",
  "properties": {
    "iso:country":"CH",
    "sg:address":"Hauptstrasse 106",
    "sg:city":"Rohr",
    "sg:classifiers":[
        {
            "category":"Manufacturing",
            "subcategory":"Tools & Machinery",
            "type":"Manufacturing & Wholesale Goods"
        }
    ],
    "sg:phone":"+41 62 824 24 44",
    "sg:postcode":"5032",
    "sg:province":"Aargau",
    "sg:tags":[
        "metallurgy",
        "metalworking"
    ],
    "wof:name":"Naegeli Maschinencenter Rohr",
    "wof:placetype":"venue"
},
  "geometry": {"coordinates":[8.0943803787,47.404624939],"type":"Point"}
}