{
  "type": "Feature",
  "properties": {
    "iso:country":"CH",
    "sg:address":"Spl\u00fcgenstrasse 18 7000 Chur. Postfach",
    "sg:city":"Chur",
    "sg:orig_category":"Architektur U Ingenieurb\u00fcros Architekturb\u00fcros",
    "sg:phone":"+41 81 253 77 29",
    "sg:postcode":"7000",
    "sg:province":"Graubunden",
    "wof:name":"Geissler Monika Dipl.-ing. (fh) Architektin",
    "wof:placetype":"venue"
},
  "geometry": {"coordinates":[9.537384,46.856262],"type":"Point"}
}