{
  "type": "Feature",
  "properties": {
    "iso:country":"CH",
    "sg:address":"L\u00fctzelstrasse 5 4242 Laufen. Postfach",
    "sg:city":"Laufen",
    "sg:orig_category":"Grosshandel mit landwirtschaftlichen Maschinen U Ger\u00e4ten Instandhaltung U Reparatur von Automobilen",
    "sg:phone":"+41 61 761 51 95",
    "sg:postcode":"4242",
    "sg:province":"Basel-Landschaft",
    "wof:name":"Kaiser Maschinen Und Fahrzeuge Ag",
    "wof:placetype":"venue"
},
  "geometry": {"coordinates":[7.493994236,47.4119415283],"type":"Point"}
}