{
  "type": "Feature",
  "properties": {
    "iso:country":"CH",
    "sg:address":"Worblentalstrasse 97 A 3063 Ittigen. Postfach",
    "sg:city":"Ittigen",
    "sg:orig_category":"Unclassifiable Establishments",
    "sg:postcode":"3063",
    "sg:province":"Bern",
    "wof:name":"Inocar Holding Ag Beteiligungen Usw.",
    "wof:placetype":"venue"
},
  "geometry": {"coordinates":[7.4789958,46.9743156433],"type":"Point"}
}