{
  "type": "Feature",
  "properties": {
    "iso:country":"CH",
    "sg:address":"Loorenstrasse 20c",
    "sg:city":"Niederrohrdorf",
    "sg:orig_category":"Detailhandel mit Radio U Fernsehger\u00e4ten Detailhandel mit elektrischen Haushalts, Radio U Fernsehger\u00e4",
    "sg:phone":"+41 21 657 37 87",
    "sg:postcode":"5443",
    "sg:province":"Aargau",
    "wof:name":"Michel Perret Set 24",
    "wof:placetype":"venue"
},
  "geometry": {"coordinates":[6.6303720474,46.5417251587],"type":"Point"}
}