{
  "type": "Feature",
  "properties": {
    "iso:country":"CH",
    "sg:address":"Rue Du Bourg 14",
    "sg:city":"Sierre",
    "sg:classifiers":[
        {
            "category":"Bars & Pubs",
            "type":"Food & Drink"
        }
    ],
    "sg:phone":"+41 79 221 12 26",
    "sg:postcode":"3960",
    "sg:province":"Valais",
    "wof:name":"Bar Du Bellevue",
    "wof:placetype":"venue"
},
  "geometry": {"coordinates":[7.534132,46.293289],"type":"Point"}
}