{
  "type": "Feature",
  "properties": {
    "iso:country":"CH",
    "sg:address":"1997",
    "sg:city":"Siviez",
    "sg:classifiers":[
        {
            "category":"Government",
            "subcategory":"Post Office",
            "type":"Public Place"
        }
    ],
    "sg:phone":"+41 27 288 13 03",
    "sg:postcode":"1997",
    "sg:province":"Valais",
    "sg:tags":[
        "caf\u00e9s",
        "tea-rooms"
    ],
    "wof:name":"Tea-room Chez Caroline",
    "wof:placetype":"venue"
},
  "geometry": {"coordinates":[7.3158597946,46.136051178],"type":"Point"}
}