{
  "type": "Feature",
  "properties": {
    "iso:country":"CH",
    "sg:address":"Neuenburgstrasse 65",
    "sg:city":"T\u00fcscherz-alferm\u00e9e",
    "sg:orig_category":"Sportvereine Wassersport Motorboot",
    "sg:phone":"+41 71 244 73 48",
    "sg:postcode":"2512",
    "sg:province":"Bern",
    "wof:name":"Schweiz.bodensee-motorbootklub",
    "wof:placetype":"venue"
},
  "geometry": {"coordinates":[9.379617691,47.436000824],"type":"Point"}
}