{
  "type": "Feature",
  "properties": {
    "iso:country":"CH",
    "sg:address":"Grub 773 9052 Niederteufen. Postfach",
    "sg:city":"Niederteufen",
    "sg:orig_category":"Sanit\u00e4r, Heizungs U L\u00fcftungsinstallation",
    "sg:postcode":"9052",
    "sg:province":"Appenzell Ausserrhoden",
    "wof:name":"Nussbaum A. Sanit\u00e4r / Heizung Sanit\u00e4re Installationen",
    "wof:placetype":"venue"
},
  "geometry": {"coordinates":[9.3649778366,47.3906059265],"type":"Point"}
}