{
  "type": "Feature",
  "properties": {
    "iso:country":"CH",
    "sg:address":"Egnacherstrasse 79 9320 Frasnacht. Postfach",
    "sg:city":"Frasnacht",
    "sg:orig_category":"Detailhandel mit M\u00f6beln U Haushaltsgegenst\u00e4nden",
    "sg:postcode":"9320",
    "sg:province":"Thurgau",
    "wof:name":"M\u00f6bel De Solda & Co M\u00f6bel; Handel",
    "wof:placetype":"venue"
},
  "geometry": {"coordinates":[9.4014492035,47.5309715271],"type":"Point"}
}