{
  "type": "Feature",
  "properties": {
    "addr:full":"Blattenstrasse 14 Naters Valais 3904",
    "addr:housenumber":"14",
    "addr:postcode":"3904",
    "addr:street":"Blattenstrasse",
    "iso:country":"CH",
    "sg:address":"Blattenstrasse 14",
    "sg:city":"Naters",
    "sg:orig_category":"Architektur U Ingenieurb\u00fcros",
    "sg:phone":"+41 27 922 09 80",
    "sg:postcode":"3904",
    "sg:province":"Valais",
    "wof:name":"Vwi Ingenieure Ag",
    "wof:placetype":"venue"
},
  "geometry": {"coordinates":[7.98988,46.326508],"type":"Point"}
}