{
  "type": "Feature",
  "properties": {
    "iso:country":"CH",
    "sg:address":"Reism\u00fchlestrasse 11 8400 Winterthur. Postfach",
    "sg:city":"Winterthur",
    "sg:orig_category":"Softwareentwicklung U beratung",
    "sg:phone":"+41 52 242 25 87",
    "sg:postcode":"8409",
    "sg:province":"Z\u00fcrich",
    "wof:name":"Softworker Wegmann Dekhil M.",
    "wof:placetype":"venue"
},
  "geometry": {"coordinates":[8.7685394287,47.5063667297],"type":"Point"}
}