{
  "type": "Feature",
  "properties": {
    "iso:country":"CH",
    "sg:address":"Gare Rue De La 45 1260 Nyon. Postfach",
    "sg:city":"Nyon",
    "sg:orig_category":"Personenbef\u00f6rderung im Linienverkehr zu Land",
    "sg:phone":"+41 39230400",
    "sg:postcode":"1260",
    "sg:province":"Vaud",
    "wof:name":"Soci\u00e9t\u00e9 Des T\u00e9l\u00e9skis La Corbati\u00e8re-la Roche-des-crocs Sa",
    "wof:placetype":"venue"
},
  "geometry": {"coordinates":[6.8280410767,47.1006164551],"type":"Point"}
}