{
  "type": "Feature",
  "properties": {
    "iso:country":"CH",
    "sg:address":"Brauerstrasse 34",
    "sg:city":"Z\u00fcrich",
    "sg:orig_category":"RESTAURANTS: TEA-ROOMS",
    "sg:phone":"+41 12415416",
    "sg:postcode":"8004",
    "sg:province":"Z\u00fcrich",
    "wof:name":"Restaurant Bar-izzi Gmbh",
    "wof:placetype":"venue"
},
  "geometry": {"coordinates":[8.5273237228,47.3778343201],"type":"Point"}
}