{
  "type": "Feature",
  "properties": {
    "iso:country":"CH",
    "sg:address":"Pulverm\u00fchlestrasse 54 7000 Chur. Postfach",
    "sg:city":"Chur",
    "sg:orig_category":"Sonstiger spezialisierter Hoch U Tiefbau",
    "sg:postcode":"7000",
    "sg:province":"Graubunden",
    "wof:name":"Broger Ger\u00fcstbau Ger\u00fcstbau, Bauarbeiten",
    "wof:placetype":"venue"
},
  "geometry": {"coordinates":[9.5139446259,46.8529167175],"type":"Point"}
}