{
  "type": "Feature",
  "properties": {
    "iso:country":"CH",
    "sg:address":"Entre-bois Chemin D' 29 1000 Lausanne. Postfach",
    "sg:city":"Lausanne",
    "sg:orig_category":"Softwareentwicklung U beratung",
    "sg:postcode":"1002",
    "sg:province":"Vaud",
    "wof:name":"Technical & Business Software, Griffin G.b.",
    "wof:placetype":"venue"
},
  "geometry": {"coordinates":[6.1296272278,46.1830863953],"type":"Point"}
}