{
  "type": "Feature",
  "properties": {
    "iso:country":"CH",
    "sg:address":"Archstrasse 36",
    "sg:city":"Grenchen",
    "sg:classifiers":[
        {
            "category":"Manufacturing",
            "subcategory":"Glass & Minerals",
            "type":"Manufacturing & Wholesale Goods"
        }
    ],
    "sg:phone":"+41 31 336 81 81",
    "sg:postcode":"2540",
    "sg:province":"Solothurn",
    "sg:tags":[
        "made",
        "fa\u00e7ade",
        "panel"
    ],
    "wof:name":"Vetrotech Saint-gobain International Ag",
    "wof:placetype":"venue"
},
  "geometry": {"coordinates":[7.464322,46.968609],"type":"Point"}
}