{
  "type": "Feature",
  "properties": {
    "iso:country":"CH",
    "sg:address":"L\u00e4ngfeldstrasse 70",
    "sg:city":"Ittigen",
    "sg:orig_category":"Grosshandel mit Blumen U Pflanzen",
    "sg:postcode":"3063",
    "sg:province":"Bern",
    "wof:name":"Hyplanta M. K\u00fcnzi",
    "wof:placetype":"venue"
},
  "geometry": {"coordinates":[7.479391098,46.9857406616],"type":"Point"}
}