{
  "type": "Feature",
  "properties": {
    "iso:country":"CH",
    "sg:address":"Mattenweg 141 3234 Vinelz. Postfach",
    "sg:city":"Vinelz",
    "sg:orig_category":"Softwareentwicklung U beratung",
    "sg:phone":"+41 32 338 19 17",
    "sg:postcode":"3234",
    "sg:province":"Bern",
    "wof:name":"Netedu Gmbh Projekte Der Informations-technologie Usw",
    "wof:placetype":"venue"
},
  "geometry": {"coordinates":[7.1309499741,47.0351409912],"type":"Point"}
}