{
  "type": "Feature",
  "properties": {
    "iso:country":"CH",
    "sg:address":"Grand-rue 114",
    "sg:city":"Montreux",
    "sg:orig_category":"Unclassifiable Establishments",
    "sg:phone":"+41 21 966 03 66",
    "sg:postcode":"1820",
    "sg:province":"Vaud",
    "wof:name":"Tcm Montreux Sa",
    "wof:placetype":"venue"
},
  "geometry": {"coordinates":[6.9038338661,46.440120697],"type":"Point"}
}