{
  "type": "Feature",
  "properties": {
    "addr:full":"Tieftalweg 2 6405 Immensee. Postfach Immensee Schwyz 6405",
    "addr:housenumber":"2",
    "addr:postcode":"6405 immensee. postfach;6405",
    "addr:street":"Tieftalweg",
    "iso:country":"CH",
    "sg:address":"Tieftalweg 2 6405 Immensee. Postfach",
    "sg:city":"Immensee",
    "sg:orig_category":"Architektur U Ingenieurb\u00fcros",
    "sg:postcode":"6405",
    "sg:province":"Schwyz",
    "wof:name":"Burkardt Peter Ingenieurb\u00fcro.",
    "wof:placetype":"venue"
},
  "geometry": {"coordinates":[8.463745,47.096886],"type":"Point"}
}