{
  "type": "Feature",
  "properties": {
    "iso:country":"CH",
    "sg:address":"Poststrasse 13",
    "sg:city":"Spreitenbach",
    "sg:orig_category":"Landesverteidigung, Sozialversicherung \u00d6ffentliche Verwaltung",
    "sg:phone":"+41 81 833 20 21",
    "sg:postcode":"8957",
    "sg:province":"Aargau",
    "wof:name":"Zivilschutzstelle St. Moritz",
    "wof:placetype":"venue"
},
  "geometry": {"coordinates":[9.8393669128,46.4977531433],"type":"Point"}
}