{
  "type": "Feature",
  "properties": {
    "addr:full":"Bahnhofstrasse 16 Baar Zug 6340",
    "addr:housenumber":"16",
    "addr:postcode":"6340",
    "addr:street":"Bahnhofstrasse;Zug",
    "iso:country":"CH",
    "sg:address":"Bahnhofstrasse 16",
    "sg:city":"Baar",
    "sg:classifiers":[
        {
            "category":"Professional",
            "subcategory":"Computer Services",
            "type":"Services"
        }
    ],
    "sg:phone":"+41 41 761 88 15",
    "sg:postcode":"6340",
    "sg:province":"Zug",
    "sg:tags":[
        "administration",
        "software"
    ],
    "wof:name":"Aals Software Ag",
    "wof:placetype":"venue"
},
  "geometry": {"coordinates":[8.523472,47.193859],"type":"Point"}
}