{
  "type": "Feature",
  "properties": {
    "iso:country":"CH",
    "sg:address":"Rue Francillon 31 2610 St-imier Case Postale",
    "sg:city":"St-imier",
    "sg:orig_category":"Regionalbanken U Sparkassen",
    "sg:phone":"+41 21 845 56 06",
    "sg:postcode":"2610",
    "sg:province":"Bern",
    "wof:name":"Cr\u00e9dit Mutuel De La Vall\u00e9e Sa",
    "wof:placetype":"venue"
},
  "geometry": {"coordinates":[6.2310299873,46.6077919006],"type":"Point"}
}