{
  "type": "Feature",
  "properties": {
    "addr:full":"Industriestrasse 20 Frauenfeld Thurgau 8500",
    "addr:housenumber":"20",
    "addr:postcode":"8500",
    "addr:street":"Industriestrasse",
    "iso:country":"CH",
    "sg:address":"Industriestrasse 20",
    "sg:city":"Frauenfeld",
    "sg:orig_category":"Bezirks, Sekundar, Realschulen, Oberstufe der Primarschulen",
    "sg:phone":"+41 52 722 10 86",
    "sg:postcode":"8500",
    "sg:province":"Thurgau",
    "wof:name":"Zehntes Schuljahr",
    "wof:placetype":"venue"
},
  "geometry": {"coordinates":[8.89403,47.560558],"type":"Point"}
}