{
  "type": "Feature",
  "properties": {
    "iso:country":"CH",
    "sg:address":"Zihlwald 36",
    "sg:city":"Hochdorf",
    "sg:classifiers":[
        {
            "category":"Arena",
            "subcategory":"Sports Club",
            "type":"Entertainment"
        }
    ],
    "sg:postcode":"6280",
    "sg:province":"Luzern",
    "sg:tags":[
        "karate",
        "judo",
        "sportvereine"
    ],
    "wof:name":"Judo Team Innerschweiz",
    "wof:placetype":"venue"
},
  "geometry": {"coordinates":[8.296790123,47.1686706543],"type":"Point"}
}