{
  "type": "Feature",
  "properties": {
    "iso:country":"CH",
    "sg:address":"Elswil 2",
    "sg:city":"W\u00fcnnewil",
    "sg:orig_category":"Detailhandel mit Waren verschiedener Art, Hauptrichtung Nahrungsmittel Sonstiger Fachdetailhandel mi",
    "sg:postcode":"3184",
    "sg:province":"Fribourg",
    "wof:name":"Haymoz Josef",
    "wof:placetype":"venue"
},
  "geometry": {"coordinates":[7.2575101852,46.8701095581],"type":"Point"}
}