{
  "type": "Feature",
  "properties": {
    "iso:country":"CH",
    "sg:address":"Rue De La Clef 13d",
    "sg:city":"St-imier",
    "sg:orig_category":"Gewinnung von Natursteinen f\u00fcr den Bau Herstellung von sonstigen Produkten aus nichtmetallischen Min",
    "sg:phone":"+41 32 941 42 51",
    "sg:postcode":"2610",
    "sg:province":"Bern",
    "wof:name":"Brechb\u00fchler Ulrich, Succursale De St-imier",
    "wof:placetype":"venue"
},
  "geometry": {"coordinates":[6.9865059853,47.1466903687],"type":"Point"}
}