{
  "type": "Feature",
  "properties": {
    "iso:country":"CH",
    "sg:address":"Breisacherstrasse 89 4057 Basel. Postfach",
    "sg:city":"Basel",
    "sg:orig_category":"Herstellung von k\u00e4lte U lufttechnischen Erzeugnissen f\u00fcr gewerbliche Zwecke",
    "sg:postcode":"4051",
    "sg:province":"Basel-Stadt",
    "wof:name":"Bolliger Walter, Wabo-service Reparaturservice F. K\u00fchl, L\u00fcftungs- U. Heizungs-anlagen Usw",
    "wof:placetype":"venue"
},
  "geometry": {"coordinates":[7.5884900093,47.5680656433],"type":"Point"}
}