{
  "type": "Feature",
  "properties": {
    "iso:country":"CH",
    "sg:address":"Schachenstrasse 10",
    "sg:city":"Emmenbr\u00fccke",
    "sg:orig_category":"Unclassifiable Establishments",
    "sg:postcode":"6020",
    "sg:province":"Luzern",
    "wof:name":"Educom,edv-& Sprach- Weiterbildungskurse",
    "wof:placetype":"venue"
},
  "geometry": {"coordinates":[8.2879123688,47.0684547424],"type":"Point"}
}