{
  "type": "Feature",
  "properties": {
    "addr:full":"Maraini Via 23 Pregassona Ticino 6963",
    "addr:housenumber":"23",
    "addr:postcode":"6963",
    "addr:street":"Via",
    "iso:country":"CH",
    "sg:address":"Maraini Via 23",
    "sg:city":"Pregassona",
    "sg:orig_category":"Detailhandel mit B\u00fcchern, Zeitungen, Schreib U Papeteriewaren",
    "sg:phone":"+41 91 941 38 29",
    "sg:postcode":"6963",
    "sg:province":"Ticino",
    "wof:name":"Editions Gastronomie & Tourisme Sa",
    "wof:placetype":"venue"
},
  "geometry": {"coordinates":[8.972781,46.019455],"type":"Point"}
}