{
  "type": "Feature",
  "properties": {
    "iso:country":"CH",
    "sg:address":"Vogelr\u00fcti 111",
    "sg:city":"Niederrohrdorf",
    "sg:orig_category":"Innenausbau Zimmerei, Dachdeckerei, Bauspenglerei U Abdichtung",
    "sg:phone":"+41 79 355 54 15",
    "sg:postcode":"5443",
    "sg:province":"Aargau",
    "wof:name":"Pit Holzbau Dr\u00e4yer Peter",
    "wof:placetype":"venue"
},
  "geometry": {"coordinates":[8.3079214096,47.4175682068],"type":"Point"}
}