{
  "type": "Feature",
  "properties": {
    "iso:country":"CH",
    "sg:address":"3999",
    "sg:city":"Oberwald",
    "sg:orig_category":"S\u00e4ge, Hobel U Holzimpr\u00e4gnierwerke S\u00e4gewerke",
    "sg:phone":"+41 27 973 22 60",
    "sg:postcode":"3999",
    "sg:province":"Valais",
    "wof:name":"Hischier Ag",
    "wof:placetype":"venue"
},
  "geometry": {"coordinates":[8.3459253311,46.5333633423],"type":"Point"}
}