{
  "type": "Feature",
  "properties": {
    "iso:country":"CH",
    "sg:address":"Alter Aargauerstalden 31b",
    "sg:city":"Bern",
    "sg:orig_category":"RESTAURANTS: TEA-ROOMS",
    "sg:phone":"+41 31 331 32 06",
    "sg:postcode":"3006",
    "sg:province":"Bern",
    "wof:name":"Restaurant Rosengarten Grossen H. & I. Und Sohn",
    "wof:placetype":"venue"
},
  "geometry": {"coordinates":[7.4611201286,46.9515457153],"type":"Point"}
}