{
  "type": "Feature",
  "properties": {
    "iso:country":"CH",
    "sg:address":"Oberer Rheinweg 45-47",
    "sg:city":"Basel",
    "sg:orig_category":"Innenarchitekturb\u00fcros Innenausbau",
    "sg:phone":"+41 61 681 80 44",
    "sg:postcode":"4058",
    "sg:province":"Basel-Stadt",
    "wof:name":"Andr\u00e9 Moser & Partner Ag Architektur",
    "wof:placetype":"venue"
},
  "geometry": {"coordinates":[7.5925040245,47.559551239],"type":"Point"}
}