{
  "type": "Feature",
  "properties": {
    "iso:country":"CH",
    "sg:address":"Baarerstrasse 96 6300 Zug. Postfach 2037",
    "sg:city":"Zug",
    "sg:orig_category":"Architektur U Ingenieurb\u00fcros",
    "sg:phone":"+41 41 760 04 44",
    "sg:postcode":"6302",
    "sg:province":"Zug",
    "wof:name":"Trailer Engineering Niederhauser & Co Fahrzeuge, -anh\u00e4nger, Aufliegern; Handel Usw",
    "wof:placetype":"venue"
},
  "geometry": {"coordinates":[8.518467,47.178505],"type":"Point"}
}