{
  "type": "Feature",
  "properties": {
    "iso:country":"CH",
    "sg:address":"Eichmatt",
    "sg:city":"Auswil",
    "sg:classifiers":[
        {
            "category":"Insurance",
            "subcategory":"Insurance Agent",
            "type":"Services"
        }
    ],
    "sg:phone":"+41 62 965 13 09",
    "sg:postcode":"4944",
    "sg:province":"Bern",
    "sg:tags":[
        "versicherungsagenturen",
        "-broker"
    ],
    "wof:name":"Emmentalische Mobiliarversich. Agentur Auswil Fritz Sch\u00e4r",
    "wof:placetype":"venue"
},
  "geometry": {"coordinates":[7.8264021873,47.1346549988],"type":"Point"}
}