{
  "type": "Feature",
  "properties": {
    "iso:country":"CH",
    "sg:address":"F\u00f6hrenweg 359",
    "sg:city":"K\u00fcnten",
    "sg:orig_category":"Wirtschaftspr\u00fcfung, Steuerberatung U Treuhand",
    "sg:phone":"+41 56 496 39 38",
    "sg:postcode":"5444",
    "sg:province":"Aargau",
    "wof:name":"Bader Treuhand Ag Vbt",
    "wof:placetype":"venue"
},
  "geometry": {"coordinates":[8.3310098648,47.3838615417],"type":"Point"}
}