{
  "type": "Feature",
  "properties": {
    "addr:full":"Seetalstrassde 2 Seon Aargau 5703",
    "addr:housenumber":"2",
    "addr:postcode":"5703",
    "addr:street":"Seetalstrassde",
    "iso:country":"CH",
    "sg:address":"Seetalstrassde 2",
    "sg:city":"Seon",
    "sg:orig_category":"Architektur U Ingenieurb\u00fcros",
    "sg:phone":"+41 62 775 06 52",
    "sg:postcode":"5703",
    "sg:province":"Aargau",
    "wof:name":"Schatzmann Engineering",
    "wof:placetype":"venue"
},
  "geometry": {"coordinates":[8.160384,47.346741],"type":"Point"}
}