{
  "type": "Feature",
  "properties": {
    "iso:country":"CH",
    "sg:address":"1641",
    "sg:city":"Vuippens",
    "sg:orig_category":"RESTAURANTS: TEA-ROOMS",
    "sg:postcode":"1641",
    "wof:name":"Bernard Piccand",
    "wof:placetype":"venue"
},
  "geometry": {"coordinates":[7.0738348961,46.6581764221],"type":"Point"}
}