{
  "type": "Feature",
  "properties": {
    "iso:country":"CH",
    "sg:address":"Solothurnstrasse 51",
    "sg:city":"Jegenstorf",
    "sg:orig_category":"Blumen U Zierpflanzenbau Detailhandel mit Blumen U Pflanzen",
    "sg:phone":"+41 31 761 01 50",
    "sg:postcode":"3303",
    "sg:province":"Bern",
    "wof:name":"Bill F. U. H.",
    "wof:placetype":"venue"
},
  "geometry": {"coordinates":[7.511961,47.054977],"type":"Point"}
}