{
  "type": "Feature",
  "properties": {
    "iso:country":"CH",
    "sg:address":"9630",
    "sg:city":"Wattwil",
    "sg:orig_category":"Vereine Abstinenten",
    "sg:postcode":"9630",
    "sg:province":"St. Gallen",
    "wof:name":"Blaues Kreuz",
    "wof:placetype":"venue"
},
  "geometry": {"coordinates":[9.1993598938,47.2241897583],"type":"Point"}
}