{
  "type": "Feature",
  "properties": {
    "addr:full":"Seftigenstrasse 400 3084 Wabern. Postfach Kehrsatz Bern 3122",
    "addr:housenumber":"400",
    "addr:postcode":"3084 wabern. postfach;3122",
    "addr:street":"Seftigenstrasse",
    "iso:country":"CH",
    "sg:address":"Seftigenstrasse 400 3084 Wabern. Postfach",
    "sg:city":"Kehrsatz",
    "sg:orig_category":"Datenverarbeitungsdienste Erbringung von Dienstleistungen f\u00fcr Unternehmen",
    "sg:phone":"+41 71 274 74 05",
    "sg:postcode":"3122",
    "sg:province":"Bern",
    "wof:name":"Business Media Ag",
    "wof:placetype":"venue"
},
  "geometry": {"coordinates":[9.340522,47.41291],"type":"Point"}
}