{
  "type": "Feature",
  "properties": {
    "iso:country":"CH",
    "sg:address":"Lautengartenstrasse 14",
    "sg:city":"Basel",
    "sg:orig_category":"K\u00fcnstlerische U schriftstellerische T\u00e4tigkeiten U Darbietungen",
    "sg:phone":"+41 61 271 25 96",
    "sg:postcode":"4052",
    "sg:province":"Basel-Stadt",
    "wof:name":"Wanap Ag",
    "wof:placetype":"venue"
},
  "geometry": {"coordinates":[7.5967311859,47.5527000427],"type":"Point"}
}