{
  "type": "Feature",
  "properties": {
    "iso:country":"CH",
    "sg:address":"Wildenstichstrasse 1",
    "sg:city":"Turgi",
    "sg:orig_category":"Vorschulen, Kinderg\u00e4rten",
    "sg:phone":"+41 56 223 21 34",
    "sg:postcode":"5300",
    "sg:province":"Aargau",
    "wof:name":"Kindergarten Dorf",
    "wof:placetype":"venue"
},
  "geometry": {"coordinates":[8.2572841644,47.4911308289],"type":"Point"}
}