{
  "type": "Feature",
  "properties": {
    "iso:country":"CH",
    "sg:address":"Niederfeld",
    "sg:city":"Frutigen",
    "sg:orig_category":"Erschliessung von Grundst\u00fccken",
    "sg:postcode":"3714",
    "sg:province":"Bern",
    "wof:name":"Genossenschaft F\u00fcr Landwirtschaftliches Bauen Frutigen Be",
    "wof:placetype":"venue"
},
  "geometry": {"coordinates":[7.6526818275,46.6011886597],"type":"Point"}
}