{
  "type": "Feature",
  "properties": {
    "iso:country":"CH",
    "sg:address":"St. Gallerstrasse 28",
    "sg:city":"Flawil",
    "sg:orig_category":"Architektur U Ingenieurb\u00fcros",
    "sg:phone":"+41 71 393 22 47",
    "sg:postcode":"9230",
    "sg:province":"St. Gallen",
    "wof:name":"Bosco B\u00fceler Gmbh",
    "wof:placetype":"venue"
},
  "geometry": {"coordinates":[9.188604,47.411839],"type":"Point"}
}