{
  "type": "Feature",
  "properties": {
    "iso:country":"CH",
    "sg:address":"Hauptstrasse 63 4313 M\u00f6hlin. Postfach",
    "sg:city":"M\u00f6hlin",
    "sg:orig_category":"Detailhandel mit B\u00fcchern Detailhandel mit B\u00fcchern, Zeitungen, Schreib U Papeteriewaren",
    "sg:phone":"+41 61 851 55 44",
    "sg:postcode":"4313",
    "sg:province":"Aargau",
    "wof:name":"Buechlade Etcetera Bertschinger Rosmarie Buchhandlung",
    "wof:placetype":"venue"
},
  "geometry": {"coordinates":[7.843583,47.558388],"type":"Point"}
}