{
  "type": "Feature",
  "properties": {
    "iso:country":"CH",
    "sg:address":"Rorschacher Strasse 135",
    "sg:city":"L\u00fcchingen",
    "sg:orig_category":"Tankstellen",
    "sg:phone":"+41 81 302 73 23",
    "sg:postcode":"9450",
    "sg:province":"St. Gallen",
    "wof:name":"Coop Tankstelle",
    "wof:placetype":"venue"
},
  "geometry": {"coordinates":[9.4969530106,47.0086555481],"type":"Point"}
}