{
  "type": "Feature",
  "properties": {
    "iso:country":"CH",
    "sg:address":"Josef-frei-weg 1 6210 Sursee. Postfach 3264",
    "sg:city":"Sursee",
    "sg:orig_category":"Detailhandel mit Uhren U Schmuck Reparatur von Uhren U Schmuck",
    "sg:phone":"+41 41 921 21 35",
    "sg:postcode":"6210",
    "sg:province":"Luzern",
    "wof:name":"Georg Tschopp Goldschmied Uhren-bijouterie",
    "wof:placetype":"venue"
},
  "geometry": {"coordinates":[8.1082258224,47.1727333069],"type":"Point"}
}