{
  "type": "Feature",
  "properties": {
    "iso:country":"CH",
    "sg:address":"Lauchenfeld 31 9548 Matzingen. Postfach",
    "sg:city":"Matzingen",
    "sg:orig_category":"Forschung U Entwicklung im Bereich der Naturwissenschaften",
    "sg:postcode":"9548",
    "sg:province":"Thurgau",
    "wof:name":"Medic Tools Ag Forschungs- U. Entwicklungsleistungen. Produkte Im Medizinaltechnik- U. Life-science-bereich; Prod., Handel",
    "wof:placetype":"venue"
},
  "geometry": {"coordinates":[8.9341287613,47.5199813843],"type":"Point"}
}