{
  "type": "Feature",
  "properties": {
    "iso:country":"CH",
    "sg:address":"Genferstrasse 11 8002 Z\u00fcrich. Postfach",
    "sg:city":"Z\u00fcrich",
    "sg:orig_category":"Sonstiges Versicherungsgewerbe",
    "sg:postcode":"8002",
    "sg:province":"Z\u00fcrich",
    "wof:name":"Limmat Versicherungs-gesellschaft",
    "wof:placetype":"venue"
},
  "geometry": {"coordinates":[8.5345182419,47.3643417358],"type":"Point"}
}