{
  "type": "Feature",
  "properties": {
    "iso:country":"CH",
    "sg:address":"8455",
    "sg:city":"R\u00fcdlingen",
    "sg:classifiers":[
        {
            "category":"Restaurant",
            "type":"Food & Drink"
        }
    ],
    "sg:phone":"+41 18670622",
    "sg:postcode":"8455",
    "sg:province":"Schaffhausen",
    "wof:name":"Restaurant Steinenkreuz",
    "wof:placetype":"venue"
},
  "geometry": {"coordinates":[8.5661897659,47.5817985535],"type":"Point"}
}