{
  "type": "Feature",
  "properties": {
    "iso:country":"CH",
    "sg:address":"Franscini Viale 1 6900 Lugano. Postfach",
    "sg:city":"Lugano",
    "sg:orig_category":"Herstellung von Duft U K\u00f6rperpflegemitteln",
    "sg:postcode":"6900",
    "sg:province":"Ticino",
    "wof:name":"H.h.agency International Sa, Hygiene And Health, Luxembourg, Succursale Di Lugano Articoli Per L'igiene Corporale E Per La Pulizia D. Casa; Compravendita, Distribuzione",
    "wof:placetype":"venue"
},
  "geometry": {"coordinates":[8.9525566101,46.0080795288],"type":"Point"}
}