{
  "type": "Feature",
  "properties": {
    "iso:country":"CH",
    "sg:address":"Hofstrasse 3",
    "sg:city":"Ebnat-kappel",
    "sg:orig_category":"Polizei",
    "sg:phone":"+41 71 992 60 20",
    "sg:postcode":"9642",
    "sg:province":"St. Gallen",
    "wof:name":"Kantonale Polizei",
    "wof:placetype":"venue"
},
  "geometry": {"coordinates":[9.1266412735,47.2602996826],"type":"Point"}
}