{
  "type": "Feature",
  "properties": {
    "iso:country":"CH",
    "sg:address":"Alte Landstrasse 36 Postfach 227",
    "sg:city":"Rebstein",
    "sg:classifiers":[
        {
            "category":"Food Court",
            "type":"Food & Drink"
        }
    ],
    "sg:phone":"+41 71 775 81 11",
    "sg:postcode":"9445",
    "sg:province":"St. Gallen",
    "sg:tags":[
        "product",
        "related"
    ],
    "wof:name":"Sonnenbr\u00c4u Ag",
    "wof:placetype":"venue"
},
  "geometry": {"coordinates":[11.4882249832,44.6670303345],"type":"Point"}
}