{
  "type": "Feature",
  "properties": {
    "iso:country":"CH",
    "sg:address":"Wasen Rue Du 32 2502 Biel/bienne. Postfach",
    "sg:city":"Biel/bienne",
    "sg:orig_category":"Pensionskassen",
    "sg:phone":"+41 32 344 99 55",
    "sg:postcode":"2500",
    "sg:province":"Bern",
    "wof:name":"Fondation En Faveur Du Personnel De La Maison Estoppey-addor Sa",
    "wof:placetype":"venue"
},
  "geometry": {"coordinates":[7.2472572327,47.1408882141],"type":"Point"}
}