{
  "type": "Feature",
  "properties": {
    "iso:country":"CH",
    "sg:address":"Langenthalstrasse 21 4912 Aarwangen. Postfach 46",
    "sg:city":"Aarwangen",
    "sg:orig_category":"Grosshandel mit sonstigen Halbwaren Spinnstoffaufbereitung U Spinnerei",
    "sg:phone":"+41 62 922 85 66",
    "sg:postcode":"4912",
    "sg:province":"Bern",
    "wof:name":"H. Ernst + Cie Ag, Aarlan Von H.e.c.",
    "wof:placetype":"venue"
},
  "geometry": {"coordinates":[7.7704091072,47.2388305664],"type":"Point"}
}