{
  "type": "Feature",
  "properties": {
    "iso:country":"CH",
    "sg:address":"Im Himmelrich 19",
    "sg:city":"Widen",
    "sg:orig_category":"Gesundheitswesen",
    "sg:phone":"+41 56 633 18 54",
    "sg:postcode":"8967",
    "sg:province":"Aargau",
    "wof:name":"Frespo Bieri Anton",
    "wof:placetype":"venue"
},
  "geometry": {"coordinates":[8.3625383377,47.3708572388],"type":"Point"}
}