{
  "type": "Feature",
  "properties": {
    "addr:full":"Aux Pruats 26 St-imier Bern 2610",
    "addr:housenumber":"26",
    "addr:postcode":"2610",
    "addr:street":"St-Imier Bern",
    "iso:country":"CH",
    "sg:address":"Aux Pruats 26",
    "sg:city":"St-imier",
    "sg:orig_category":"Architektur U Ingenieurb\u00fcros",
    "sg:phone":"+41 55 260 28 75",
    "sg:postcode":"2610",
    "sg:province":"Bern",
    "wof:name":"Gemag Engineering Ag",
    "wof:placetype":"venue"
},
  "geometry": {"coordinates":[8.869575,47.265926],"type":"Point"}
}