{
  "type": "Feature",
  "properties": {
    "iso:country":"CH",
    "sg:address":"Bergacker",
    "sg:city":"Wattenwil",
    "sg:orig_category":"Bauingenieurb\u00fcros Hochbau Bauingenieurb\u00fcros allgemein",
    "sg:phone":"+41 33 356 20 24",
    "sg:postcode":"3665",
    "sg:province":"Bern",
    "wof:name":"Dieter B\u00f6rlin Ingenieurb\u00fcro",
    "wof:placetype":"venue"
},
  "geometry": {"coordinates":[7.509698,46.769672],"type":"Point"}
}