{
  "type": "Feature",
  "properties": {
    "addr:full":"Schweizergasse 20 Z\u00fcrich Z\u00fcrich 8001",
    "addr:housenumber":"20",
    "addr:postcode":"8001",
    "addr:street":"Schweizergasse",
    "iso:country":"CH",
    "sg:address":"Schweizergasse 20",
    "sg:city":"Z\u00fcrich",
    "sg:orig_category":"Architektur U Ingenieurb\u00fcros Architekturb\u00fcros",
    "sg:phone":"+41 12125312",
    "sg:postcode":"8001",
    "sg:province":"Z\u00fcrich",
    "wof:name":"Ernst & Humbel Gmbh",
    "wof:placetype":"venue"
},
  "geometry": {"coordinates":[8.537325,47.376404],"type":"Point"}
}