{
  "type": "Feature",
  "properties": {
    "iso:country":"CH",
    "sg:address":"Schaffhauserstrasse 6 8500 Frauenfeld. Postfach 21",
    "sg:city":"Frauenfeld",
    "sg:orig_category":"Architektur U Ingenieurb\u00fcros",
    "sg:phone":"+41 71 642 31 81",
    "sg:postcode":"8500",
    "sg:province":"Thurgau",
    "wof:name":"Planag Bauimmobilien Ag",
    "wof:placetype":"venue"
},
  "geometry": {"coordinates":[8.889455,47.5611],"type":"Point"}
}