{
  "type": "Feature",
  "properties": {
    "iso:country":"CH",
    "sg:address":"Chemin Des P\u00e2les 13",
    "sg:city":"Cortaillod",
    "sg:classifiers":[
        {
            "category":"Food & Beverages",
            "subcategory":"Groceries & Convenience Stores",
            "type":"Retail Goods"
        }
    ],
    "sg:phone":"+41 32 842 64 42",
    "sg:postcode":"2016",
    "sg:province":"Neuch\u00e2tel",
    "sg:tags":[
        "dietetic",
        "foodstuff"
    ],
    "wof:name":"Qualidess Sa",
    "wof:placetype":"venue"
},
  "geometry": {"coordinates":[6.845908165,46.9457778931],"type":"Point"}
}