{
  "type": "Feature",
  "properties": {
    "iso:country":"CH",
    "sg:address":"Vogelsangstrasse 21",
    "sg:city":"Esslingen",
    "sg:orig_category":"Interessenvertretungen U sonstige Vereinigungen",
    "sg:phone":"+41 19840854",
    "sg:postcode":"8133",
    "sg:province":"Z\u00fcrich",
    "wof:name":"Z\u00fcrcher Boccia-verband",
    "wof:placetype":"venue"
},
  "geometry": {"coordinates":[8.7119169235,47.2909965515],"type":"Point"}
}