{
  "type": "Feature",
  "properties": {
    "iso:country":"CH",
    "sg:address":"Dorf 23 9107 Urn\u00e4sch. Postfach 30",
    "sg:city":"Urn\u00e4sch",
    "sg:orig_category":"Detailhandel mit Sportartikeln Detailhandel mit Waren verschiedener Art, Hauptrichtung Nahrungsmitte",
    "sg:phone":"+41 71 364 12 09",
    "sg:postcode":"9107",
    "sg:province":"Appenzell Ausserrhoden",
    "wof:name":"Hansueli Schoch Handlung & Sportgesch\u00e4ft",
    "wof:placetype":"venue"
},
  "geometry": {"coordinates":[9.2841997147,47.3178596497],"type":"Point"}
}