{
  "type": "Feature",
  "properties": {
    "iso:country":"CH",
    "sg:address":"Al Ponte Vecchio",
    "sg:city":"Lodrino",
    "sg:orig_category":"Physiotherapie",
    "sg:phone":"+41 91 863 15 33",
    "sg:postcode":"6527",
    "sg:province":"Ticino",
    "wof:name":"Fisiolodrino Marianne Smeele",
    "wof:placetype":"venue"
},
  "geometry": {"coordinates":[8.9811306,46.2996673584],"type":"Point"}
}