{
  "type": "Feature",
  "properties": {
    "iso:country":"CH",
    "sg:address":"Steigstrasse 6 9436 Balgach. Postfach",
    "sg:city":"Balgach",
    "sg:orig_category":"Softwareentwicklung U beratung",
    "sg:postcode":"9436",
    "sg:province":"St. Gallen",
    "wof:name":"Dorner Asp Ag Software; Entwicklung U. Vertrieb Usw.",
    "wof:placetype":"venue"
},
  "geometry": {"coordinates":[9.6068706512,47.4072914124],"type":"Point"}
}