{
  "type": "Feature",
  "properties": {
    "iso:country":"CH",
    "sg:address":"Steinerbr\u00fcggli",
    "sg:city":"Reichenburg",
    "sg:orig_category":"Grosshandel mit Holz U Baustoffen",
    "sg:phone":"+41 56 493 29 66",
    "sg:postcode":"8864",
    "sg:province":"Schwyz",
    "wof:name":"Knecht & Co Ag",
    "wof:placetype":"venue"
},
  "geometry": {"coordinates":[8.2951526642,47.4469490051],"type":"Point"}
}