{
  "type": "Feature",
  "properties": {
    "iso:country":"CH",
    "sg:address":"Zilmattweg 8",
    "sg:city":"Selzach",
    "sg:orig_category":"Herstellung von Elektromotoren, Generatoren U Transformatoren",
    "sg:phone":"+41 32 641 11 83",
    "sg:postcode":"2545",
    "sg:province":"Solothurn",
    "wof:name":"Sch\u00e4li R.",
    "wof:placetype":"venue"
},
  "geometry": {"coordinates":[7.4591178894,47.2001724243],"type":"Point"}
}