{
  "type": "Feature",
  "properties": {
    "iso:country":"CH",
    "sg:address":"Gr\u00fcnenstrasse 6",
    "sg:city":"Gr\u00fcnen",
    "sg:orig_category":"Notariate",
    "sg:phone":"+41 34 431 32 22",
    "sg:postcode":"3455",
    "sg:province":"Bern",
    "wof:name":"Alfred Stirnemann Notariatsb\u00fcro",
    "wof:placetype":"venue"
},
  "geometry": {"coordinates":[7.736893177,47.0250778198],"type":"Point"}
}