{
  "type": "Feature",
  "properties": {
    "iso:country":"CH",
    "sg:address":"Route De L'h\u00f4pital 4",
    "sg:city":"Sierre",
    "sg:orig_category":"Advokaturb\u00fcros Notariate",
    "sg:phone":"+41 81 830 00 80",
    "sg:postcode":"3960",
    "sg:province":"Valais",
    "wof:name":"Mario A. Pfiffner Advokatur-& Notariatsb\u00fcro",
    "wof:placetype":"venue"
},
  "geometry": {"coordinates":[9.838987,46.499233],"type":"Point"}
}