{
  "type": "Feature",
  "properties": {
    "iso:country":"CH",
    "sg:address":"Landstrasse 28",
    "sg:city":"Schaan",
    "sg:orig_category":"Detailhandel mit Brillen U anderen Sehhilfen",
    "sg:phone":"+423 232 58 68",
    "sg:postcode":"9494",
    "wof:name":"Christoph Schmidt Augenoptik Marxer",
    "wof:placetype":"venue"
},
  "geometry": {"coordinates":[9.508815,47.16573],"type":"Point"}
}