{
  "type": "Feature",
  "properties": {
    "iso:country":"CH",
    "sg:address":"Flurstrasse 74",
    "sg:city":"Z\u00fcrich",
    "sg:orig_category":"Markt U Meinungsforschung",
    "sg:phone":"+41 21 616 95 95",
    "sg:postcode":"8048",
    "sg:province":"Z\u00fcrich",
    "wof:name":"Idea Marketing Sa",
    "wof:placetype":"venue"
},
  "geometry": {"coordinates":[6.6385297775,46.5106391907],"type":"Point"}
}