{
  "type": "Feature",
  "properties": {
    "iso:country":"CH",
    "sg:address":"4465",
    "sg:city":"Hemmiken",
    "sg:orig_category":"Schulpflegen",
    "sg:postcode":"4465",
    "sg:province":"Basel-Landschaft",
    "wof:name":"Schulpflege Der Gemeinde Hergiswil",
    "wof:placetype":"venue"
},
  "geometry": {"coordinates":[7.9565200806,47.0838012695],"type":"Point"}
}