{
  "type": "Feature",
  "properties": {
    "iso:country":"CH",
    "sg:address":"Avenue Bois-de-la-chapelle 83",
    "sg:city":"Onex",
    "sg:orig_category":"Restaurants Schwimmb\u00e4der",
    "sg:phone":"+41 22 792 93 57",
    "sg:postcode":"1213",
    "sg:province":"Gen\u00e8ve",
    "wof:name":"Piscine D'onex-parc",
    "wof:placetype":"venue"
},
  "geometry": {"coordinates":[6.1015000343,46.186920166],"type":"Point"}
}