{
  "type": "Feature",
  "properties": {
    "iso:country":"CH",
    "sg:address":"Via Ginevra 4. 6900 Lugano. Postfach Casa Postale",
    "sg:city":"Lugano",
    "sg:orig_category":"Sonstiges Versicherungsgewerbe",
    "sg:postcode":"6900",
    "sg:province":"Ticino",
    "wof:name":"Helvetia-infortuni Societ\u00e0 Svizzera Di Assicurazione Zurigo Agenzia Generale Lugano Boscara Nerio. Agenzia Di Assicurazioni",
    "wof:placetype":"venue"
},
  "geometry": {"coordinates":[8.951880455,46.0083312988],"type":"Point"}
}