{
  "type": "Feature",
  "properties": {
    "addr:full":"Route De La Chassotte 5 Givisiez Fribourg 1762",
    "addr:housenumber":"5",
    "addr:postcode":"1762",
    "addr:street":"Route De La Chassotte",
    "iso:country":"CH",
    "sg:address":"Route De La Chassotte 5",
    "sg:city":"Givisiez",
    "sg:orig_category":"Architektur U Ingenieurb\u00fcros",
    "sg:postcode":"1762",
    "sg:province":"Fribourg",
    "wof:name":"Bureau D'ing\u00e9nieurs Richerzhagen S\u00e0rl",
    "wof:placetype":"venue"
},
  "geometry": {"coordinates":[6.55807,46.510078],"type":"Point"}
}