{
  "type": "Feature",
  "properties": {
    "iso:country":"CH",
    "sg:address":"Chauvet Rue Michel- 3 1208 Gen\u00e8ve. Postfach",
    "sg:city":"Gen\u00e8ve",
    "sg:orig_category":"Unclassifiable Establishments",
    "sg:postcode":"1208",
    "sg:province":"Gen\u00e8ve",
    "wof:name":"Soci\u00e9t\u00e9 Immobili\u00e8re Les Eaux",
    "wof:placetype":"venue"
},
  "geometry": {"coordinates":[6.1582899094,46.1972084045],"type":"Point"}
}