{
  "type": "Feature",
  "properties": {
    "iso:country":"CH",
    "sg:address":"Heilbronnerstrasse 25",
    "sg:city":"Solothurn",
    "sg:orig_category":"Markt U Meinungsforschung",
    "sg:phone":"+41 26 496 38 48",
    "sg:postcode":"4500",
    "sg:province":"Solothurn",
    "wof:name":"Meier Thomas & Partner",
    "wof:placetype":"venue"
},
  "geometry": {"coordinates":[7.2587690353,46.8625068665],"type":"Point"}
}