{
  "type": "Feature",
  "properties": {
    "iso:country":"CH",
    "sg:address":"Praz-paris",
    "sg:city":"Montpreveyres",
    "sg:orig_category":"Malerei Stukkateurgewerbe, Gipserei U Verputzerei",
    "sg:phone":"+41 21 903 23 87",
    "sg:postcode":"1081",
    "sg:province":"Vaud",
    "wof:name":"Jean Keller Gypserie & Peinture",
    "wof:placetype":"venue"
},
  "geometry": {"coordinates":[6.7432851791,46.5820732117],"type":"Point"}
}