{
  "type": "Feature",
  "properties": {
    "iso:country":"CH",
    "sg:address":"Schmalzgrubenstrasse 19",
    "sg:city":"Unteriberg",
    "sg:orig_category":"Instandhaltung U Reparatur von Automobilen",
    "sg:phone":"+41 71 277 81 27",
    "sg:postcode":"8842",
    "sg:province":"Schwyz",
    "wof:name":"Wallner Wolfgang, Rieth\u00fcsli-garage.",
    "wof:placetype":"venue"
},
  "geometry": {"coordinates":[9.3685693741,47.408115387],"type":"Point"}
}