{
  "type": "Feature",
  "properties": {
    "addr:full":"Hauptstrasse 9 Reinach Basel-Landschaft 4153",
    "addr:housenumber":"9",
    "addr:postcode":"4153",
    "addr:street":"Hauptstrasse",
    "iso:country":"CH",
    "sg:address":"Hauptstrasse 9",
    "sg:city":"Reinach",
    "sg:classifiers":[
        {
            "category":"Banks & Credit Unions",
            "subcategory":"Bank",
            "type":"Services"
        }
    ],
    "sg:phone":"+41 62 726 11 64",
    "sg:postcode":"4153",
    "sg:province":"Basel-Landschaft",
    "wof:name":"Raiffeisenbank Reitnau",
    "wof:placetype":"venue"
},
  "geometry": {"coordinates":[8.03848,47.25201],"type":"Point"}
}