{
  "type": "Feature",
  "properties": {
    "iso:country":"CH",
    "sg:address":"Rebrainstrasse 22",
    "sg:city":"Gr\u00fct",
    "sg:classifiers":[
        {
            "category":"Banks & Credit Unions",
            "subcategory":"Investment Brokerage",
            "type":"Services"
        }
    ],
    "sg:phone":"+41 19721800",
    "sg:postcode":"8624",
    "sg:province":"Z\u00fcrich",
    "sg:tags":[
        "erp",
        "software",
        "planning",
        "resource",
        "enterprise"
    ],
    "wof:name":"Basec Software Ag",
    "wof:placetype":"venue"
},
  "geometry": {"coordinates":[8.786611,47.308365],"type":"Point"}
}