{
  "type": "Feature",
  "properties": {
    "iso:country":"CH",
    "sg:address":"Bahnhofstrasse 9",
    "sg:city":"B\u00e4retswil",
    "sg:orig_category":"Allgemeiner Hoch U Tiefbau Strassenbau",
    "sg:phone":"+41 19391764",
    "sg:postcode":"8344",
    "sg:province":"Z\u00fcrich",
    "wof:name":"Wyss Hoch Und Tiefbau Ag",
    "wof:placetype":"venue"
},
  "geometry": {"coordinates":[8.855404,47.335526],"type":"Point"}
}