{
  "type": "Feature",
  "properties": {
    "iso:country":"CH",
    "sg:address":"Rue Du Pr\u00e9fet-comte 28",
    "sg:city":"Court\u00e9telle",
    "sg:orig_category":"RESTAURANTS: TEA-ROOMS",
    "sg:postcode":"2852",
    "sg:province":"Jura",
    "wof:name":"M\u00fcller Liliane",
    "wof:placetype":"venue"
},
  "geometry": {"coordinates":[7.3189749718,47.3389129639],"type":"Point"}
}