{
  "type": "Feature",
  "properties": {
    "iso:country":"CH",
    "sg:address":"Grundrebenstrasse 11 8932 Mettmenstetten. Postfach",
    "sg:city":"Mettmenstetten",
    "sg:orig_category":"W\u00e4scherei U chemische Reinigung",
    "sg:phone":"+41 17682605",
    "sg:postcode":"8932",
    "sg:province":"Z\u00fcrich",
    "wof:name":"Ozosystem Angelino + Co Teppiche; Spezialreinigung Usw",
    "wof:placetype":"venue"
},
  "geometry": {"coordinates":[8.4679536819,47.2476844788],"type":"Point"}
}