{
  "type": "Feature",
  "properties": {
    "iso:country":"CH",
    "sg:address":"Hohlengraben 20",
    "sg:city":"Obererlinsbach",
    "sg:orig_category":"Malerei Tapeziererei",
    "sg:phone":"+41 62 844 27 76",
    "sg:postcode":"5016",
    "wof:name":"Daniel Niederhauser Maler-& Tapezierergesch\u00e4ft",
    "wof:placetype":"venue"
},
  "geometry": {"coordinates":[8.0026569366,47.4075279236],"type":"Point"}
}