{
  "type": "Feature",
  "properties": {
    "iso:country":"CH",
    "sg:address":"Kreuzlinger Strasse 136",
    "sg:city":"Oberaach",
    "sg:orig_category":"Fotografische Ateliers Fotografisches Gewerbe U fotografische Laboratorien",
    "sg:phone":"+41 71 411 74 43",
    "sg:postcode":"8587",
    "sg:province":"Thurgau",
    "wof:name":"Fotostudio Scavini Andrea",
    "wof:placetype":"venue"
},
  "geometry": {"coordinates":[9.2673091888,47.558303833],"type":"Point"}
}