{
  "type": "Feature",
  "properties": {
    "iso:country":"CH",
    "sg:address":"6318",
    "sg:city":"Walchwil",
    "sg:orig_category":"Landw. Genossenschaften Viehzucht",
    "sg:postcode":"6318",
    "sg:province":"Zug",
    "wof:name":"Viehzuchtgenossenschaft",
    "wof:placetype":"venue"
},
  "geometry": {"coordinates":[8.5296697617,47.1140289307],"type":"Point"}
}