{
  "type": "Feature",
  "properties": {
    "iso:country":"CH",
    "sg:address":"Neustadt 9",
    "sg:city":"Schaffhausen",
    "sg:orig_category":"Kauf U Verkauf von Immobilien auf eigene Rechnung Vermietung U Verpachtung von eigenen Immobilien",
    "sg:phone":"+41 52 624 03 30",
    "sg:postcode":"8200",
    "sg:province":"Schaffhausen",
    "wof:name":"Dowa Immobilien Ag",
    "wof:placetype":"venue"
},
  "geometry": {"coordinates":[8.6320419312,47.694103241],"type":"Point"}
}