{
  "type": "Feature",
  "properties": {
    "iso:country":"CH",
    "sg:address":"L\u00f6rracherstrasse 157",
    "sg:city":"Riehen",
    "sg:orig_category":"Herstellung von konfektionierten Textilwaren ohne Bekleidung",
    "sg:phone":"+41 61 641 06 12",
    "sg:postcode":"4125",
    "sg:province":"Basel-Stadt",
    "wof:name":"Reiser Storenbau.",
    "wof:placetype":"venue"
},
  "geometry": {"coordinates":[7.6549348831,47.5945358276],"type":"Point"}
}