{
  "type": "Feature",
  "properties": {
    "iso:country":"CH",
    "sg:address":"Seestrasse 171",
    "sg:city":"Uster",
    "sg:orig_category":"Abwasserreinigung",
    "sg:phone":"+41 19402455",
    "sg:postcode":"8610",
    "sg:province":"Z\u00fcrich",
    "wof:name":"Kl\u00e4ranlage Jungholz",
    "wof:placetype":"venue"
},
  "geometry": {"coordinates":[8.692313,47.351242],"type":"Point"}
}