{
  "type": "Feature",
  "properties": {
    "iso:country":"CH",
    "sg:address":"Hinterdorf",
    "sg:city":"Valens",
    "sg:orig_category":"Detailhandel mit Waren verschiedener Art, Hauptrichtung Nahrungsmittel",
    "sg:phone":"+41 27 957 29 88",
    "sg:postcode":"7317",
    "sg:province":"St. Gallen",
    "wof:name":"Geschwister Andenmatten Lebensmittel",
    "wof:placetype":"venue"
},
  "geometry": {"coordinates":[7.9573631287,46.0964317322],"type":"Point"}
}