{
  "type": "Feature",
  "properties": {
    "iso:country":"CH",
    "sg:address":"Rue De Grands-vergers",
    "sg:city":"Ardon",
    "sg:orig_category":"Malerei",
    "sg:phone":"+41 27 306 48 65",
    "sg:postcode":"1957",
    "sg:province":"Valais",
    "wof:name":"Damiano Cristofaro Entreprise De Peinture",
    "wof:placetype":"venue"
},
  "geometry": {"coordinates":[7.2559390068,46.2109298706],"type":"Point"}
}