{
  "type": "Feature",
  "properties": {
    "iso:country":"CH",
    "sg:address":"Bahnhofstrasse 34 8706 Meilen. Postfach 627",
    "sg:city":"Meilen",
    "sg:orig_category":"Sanit\u00e4r U Heizungsinstallation Sanit\u00e4rinstallation",
    "sg:phone":"+41 19230094",
    "sg:postcode":"8706",
    "sg:province":"Z\u00fcrich",
    "wof:name":"Hollenweger Ag Heizung & Sanit\u00e4r",
    "wof:placetype":"venue"
},
  "geometry": {"coordinates":[8.6444044113,47.2692337036],"type":"Point"}
}