{
  "type": "Feature",
  "properties": {
    "iso:country":"CH",
    "sg:address":"Route Des Plaines-du-loup 74",
    "sg:city":"Lausanne",
    "sg:orig_category":"Detailhandel mit Tabakwaren",
    "sg:phone":"+41 21 647 57 60",
    "sg:postcode":"1018",
    "sg:province":"Vaud",
    "wof:name":"Jean-gabriel Bally Tabacs",
    "wof:placetype":"venue"
},
  "geometry": {"coordinates":[6.6209249496,46.5403747559],"type":"Point"}
}