{
  "type": "Feature",
  "properties": {
    "iso:country":"CH",
    "sg:address":"Br\u00fcderhofweg 29 8057 Z\u00fcrich. Postfach 193",
    "sg:city":"Z\u00fcrich",
    "sg:orig_category":"Sonstige pers\u00f6nliche Dienstleistungen",
    "sg:phone":"+41 13621550",
    "sg:postcode":"8057",
    "sg:province":"Z\u00fcrich",
    "wof:name":"Pro Due, Regionale Informations Und Beratungsstelle F\u00fcr Alleinstehende, Albrecht Margrit",
    "wof:placetype":"venue"
},
  "geometry": {"coordinates":[8.5387954712,47.4001541138],"type":"Point"}
}