{
  "type": "Feature",
  "properties": {
    "iso:country":"CH",
    "sg:address":"Hintergass 19 9490 Vaduz. Postfach 174",
    "sg:city":"Vaduz",
    "sg:orig_category":"Wirtschaftspr\u00fcfung, Steuerberatung U Treuhand",
    "sg:phone":"+423 235 40 50",
    "sg:postcode":"9490",
    "wof:name":"Factum Ag Verm\u00f6gensverwaltung Treuhand",
    "wof:placetype":"venue"
},
  "geometry": {"coordinates":[9.5196342468,47.1440162659],"type":"Point"}
}