{
  "type": "Feature",
  "properties": {
    "iso:country":"CH",
    "sg:address":"Vielmatt 190q",
    "sg:city":"Walkringen",
    "sg:orig_category":"G\u00fcterbef\u00f6rderung im Strassenverkehr",
    "sg:postcode":"3512",
    "sg:province":"Bern",
    "wof:name":"Z\u00fcrcher Transport Gmbh, Walkringen",
    "wof:placetype":"venue"
},
  "geometry": {"coordinates":[7.61687994,46.9431991577],"type":"Point"}
}