{
  "type": "Feature",
  "properties": {
    "iso:country":"CH",
    "sg:address":"Route De Gen\u00e8ve 1 1028 Pr\u00e9verenges. Postfach",
    "sg:city":"Pr\u00e9verenges",
    "sg:orig_category":"Grosshandel mit B\u00fcromaschinen U einrichtungen Softwareentwicklung U beratung",
    "sg:phone":"+41 21 803 21 21",
    "sg:postcode":"1028",
    "sg:province":"Vaud",
    "wof:name":"Infotec Garage S\u00e0rl",
    "wof:placetype":"venue"
},
  "geometry": {"coordinates":[6.5149831772,46.5176582336],"type":"Point"}
}