{
  "type": "Feature",
  "properties": {
    "iso:country":"CH",
    "sg:address":"Route De Lausanne 3",
    "sg:city":"Echallens",
    "sg:classifiers":[
        {
            "category":"Banks & Credit Unions",
            "subcategory":"Bank",
            "type":"Services"
        }
    ],
    "sg:phone":"+41 21 881 44 19",
    "sg:postcode":"1040",
    "sg:province":"Vaud",
    "wof:name":"Banque Raiffeisen",
    "wof:placetype":"venue"
},
  "geometry": {"coordinates":[6.634545,46.640736],"type":"Point"}
}