{
  "type": "Feature",
  "properties": {
    "iso:country":"CH",
    "sg:address":"St. Johanns-vorstadt 58",
    "sg:city":"Basel",
    "sg:orig_category":"Zahnarztpraxen",
    "sg:phone":"+41 71 755 40 33",
    "sg:postcode":"4056",
    "sg:province":"Basel-Stadt",
    "wof:name":"Dr. Med. Dent. Nicolas Viveros Zahnarzt",
    "wof:placetype":"venue"
},
  "geometry": {"coordinates":[9.5411167145,47.3809356689],"type":"Point"}
}