{
  "type": "Feature",
  "properties": {
    "iso:country":"CH",
    "sg:address":"Gewerbestrasse 25",
    "sg:city":"Allschwil",
    "sg:orig_category":"Unternehmensberatung",
    "sg:phone":"+41 79 379 20 14",
    "sg:postcode":"4123",
    "sg:province":"Basel-Landschaft",
    "wof:name":"Daniel Fischer & Partner Marketing Consulting",
    "wof:placetype":"venue"
},
  "geometry": {"coordinates":[7.3814182281,46.9263420105],"type":"Point"}
}