{
  "type": "Feature",
  "properties": {
    "iso:country":"CH",
    "sg:address":"Via Greina 3 6900 Lugano. Postfach",
    "sg:city":"Lugano",
    "sg:classifiers":[
        {
            "category":"Travel",
            "subcategory":"Hotels & Motels",
            "type":"Entertainment"
        }
    ],
    "sg:phone":"+41 91 794 22 23",
    "sg:postcode":"6901",
    "sg:province":"Ticino",
    "sg:tags":[
        "hotels",
        "mit",
        "restaurant"
    ],
    "wof:name":"Albergo La Campagnola",
    "wof:placetype":"venue"
},
  "geometry": {"coordinates":[8.8021802902,46.1322402954],"type":"Point"}
}