{
  "type": "Feature",
  "properties": {
    "addr:full":"Corso Pestalozzi 21a Lugano Ticino 6900",
    "addr:housenumber":"21a",
    "addr:postcode":"6900",
    "addr:street":"Corso Pestalozzi",
    "iso:country":"CH",
    "sg:address":"Corso Pestalozzi 21a",
    "sg:city":"Lugano",
    "sg:orig_category":"Architekturb\u00fcros",
    "sg:phone":"+41 91 923 12 86",
    "sg:postcode":"6900",
    "sg:province":"Ticino",
    "wof:name":"Jacqueline Chimchila Chevili Studio D'architettura",
    "wof:placetype":"venue"
},
  "geometry": {"coordinates":[8.954678,46.005745],"type":"Point"}
}