{
  "type": "Feature",
  "properties": {
    "iso:country":"CH",
    "sg:address":"Helfenbergstrasse 12",
    "sg:city":"Basel",
    "sg:orig_category":"Softwareentwicklung U beratung",
    "sg:phone":"+41 17152247",
    "sg:postcode":"4059",
    "sg:province":"Basel-Stadt",
    "wof:name":"Compugate Gmbh Software-reengineering Werkzeuge; Prod., Verkauf",
    "wof:placetype":"venue"
},
  "geometry": {"coordinates":[7.5894970894,47.53465271],"type":"Point"}
}