{
  "type": "Feature",
  "properties": {
    "iso:country":"CH",
    "sg:address":"Poststrasse 403",
    "sg:city":"Ruggell",
    "sg:orig_category":"Grosshandel mit M\u00f6beln, Wohnbedarf, Teppichen U Bodenbel\u00e4gen Saunas, Solarien, Fitnesszentren U \u00e4hnl",
    "sg:phone":"+41 21 634 39 53",
    "sg:postcode":"9491",
    "wof:name":"Cavin Articles De Jardin Sa",
    "wof:placetype":"venue"
},
  "geometry": {"coordinates":[6.5868420601,46.5444030762],"type":"Point"}
}