{
  "type": "Feature",
  "properties": {
    "iso:country":"CH",
    "sg:address":"Leonhardsgraben 36 4051 Basel. Postfach 206",
    "sg:city":"Basel",
    "sg:orig_category":"Grosshandel mit chemischen Erzeugnissen Grosshandel mit pharmazeutischen Erzeugnissen",
    "sg:phone":"+41 61 264 95 64",
    "sg:postcode":"4003",
    "sg:province":"Basel-Stadt",
    "wof:name":"Chemgo Organica Ag Chem. Rohstoffe, Zwischenprodukte Usw; Handel",
    "wof:placetype":"venue"
},
  "geometry": {"coordinates":[7.5856499672,47.5558395386],"type":"Point"}
}