{
  "type": "Feature",
  "properties": {
    "iso:country":"CH",
    "sg:address":"Schappeweg 1",
    "sg:city":"Kriens",
    "sg:orig_category":"Innenarchitekturb\u00fcros",
    "sg:phone":"+41 41 322 19 60",
    "sg:postcode":"6010",
    "sg:province":"Luzern",
    "wof:name":"Martin Polzer Innenarchitektur",
    "wof:placetype":"venue"
},
  "geometry": {"coordinates":[8.2735500336,47.0348739624],"type":"Point"}
}