{
  "type": "Feature",
  "properties": {
    "iso:country":"CH",
    "sg:address":"Dufourstrasse 30",
    "sg:city":"Bern",
    "sg:orig_category":"Vermietung U Verpachtung von eigenen Immobilien",
    "sg:postcode":"3005",
    "sg:province":"Bern",
    "wof:name":"Bear Trade & Consult Ag",
    "wof:placetype":"venue"
},
  "geometry": {"coordinates":[7.4539318085,46.94140625],"type":"Point"}
}