{
  "type": "Feature",
  "properties": {
    "iso:country":"CH",
    "sg:address":"Zona Industriale",
    "sg:city":"Sigirino",
    "sg:orig_category":"Druckweiterverarbeitung Offsetdruck",
    "sg:phone":"+41 91 945 07 45",
    "sg:postcode":"6806",
    "sg:province":"Ticino",
    "wof:name":"Bettini Sagl",
    "wof:placetype":"venue"
},
  "geometry": {"coordinates":[8.9141702652,46.0810012817],"type":"Point"}
}