{
  "type": "Feature",
  "properties": {
    "iso:country":"CH",
    "sg:address":"Rue Du Vingt-trois Juin 39",
    "sg:city":"Courrendlin",
    "sg:orig_category":"Herstellung von Schrauben, Nieten, Ketten U Federn Mechanische Werkst\u00e4tten",
    "sg:phone":"+41 32 435 58 26",
    "sg:postcode":"2830",
    "sg:province":"Jura",
    "wof:name":"Jean Rickli Samara Atelier De Microm\u00e9can.",
    "wof:placetype":"venue"
},
  "geometry": {"coordinates":[7.3739719391,47.3363990784],"type":"Point"}
}