{
  "type": "Feature",
  "properties": {
    "iso:country":"CH",
    "sg:address":"Sch\u00fctzenstrasse 20",
    "sg:city":"Birsfelden",
    "sg:orig_category":"Bauspenglerei Zimmerei, Dachdeckerei, Bauspenglerei U Abdichtung",
    "sg:phone":"+41 61 311 05 22",
    "sg:postcode":"4127",
    "sg:province":"Basel-Landschaft",
    "wof:name":"Werner L\u00fcthi",
    "wof:placetype":"venue"
},
  "geometry": {"coordinates":[7.625279,47.553532],"type":"Point"}
}