{
  "type": "Feature",
  "properties": {
    "iso:country":"CH",
    "sg:address":"Pasteur Ch. Dr-adolphe- 6",
    "sg:city":"Gen\u00e8ve",
    "sg:orig_category":"Unclassifiable Establishments",
    "sg:phone":"+41 22 733 59 42",
    "sg:postcode":"1209",
    "sg:province":"Gen\u00e8ve",
    "wof:name":"Marrone Claudia",
    "wof:placetype":"venue"
},
  "geometry": {"coordinates":[6.1289482117,46.2211074829],"type":"Point"}
}