{
  "type": "Feature",
  "properties": {
    "addr:full":"Hohlstrasse 545 Z\u00fcrich Z\u00fcrich 8048",
    "addr:housenumber":"545",
    "addr:postcode":"8048",
    "addr:street":"Hohlstrasse",
    "iso:country":"CH",
    "sg:address":"Hohlstrasse 545",
    "sg:city":"Z\u00fcrich",
    "sg:classifiers":[
        {
            "category":"Food & Beverages",
            "subcategory":"Specialty",
            "type":"Retail Goods"
        }
    ],
    "sg:phone":"+41 14303736",
    "sg:postcode":"8048",
    "sg:province":"Z\u00fcrich",
    "sg:tags":[
        "caterer"
    ],
    "wof:name":"Royal Gourmet Express San Z\u00fcrich City Hauslieferdienst",
    "wof:placetype":"venue"
},
  "geometry": {"coordinates":[8.490681,47.39016],"type":"Point"}
}