{
  "type": "Feature",
  "properties": {
    "iso:country":"CH",
    "sg:address":"6674 Someo. Postfach Caselle Postale 135",
    "sg:city":"Someo",
    "sg:orig_category":"Sportvereine Ballsport Fussball",
    "sg:phone":"+41 91 753 19 29",
    "sg:postcode":"6674",
    "sg:province":"Ticino",
    "wof:name":"Fc Someo",
    "wof:placetype":"venue"
},
  "geometry": {"coordinates":[8.6663808823,46.2863388062],"type":"Point"}
}