{
  "type": "Feature",
  "properties": {
    "iso:country":"CH",
    "sg:address":"Tittwiesenstrasse 55 7000 Chur. Postfach",
    "sg:city":"Chur",
    "sg:orig_category":"Gesundheitswesen",
    "sg:postcode":"7000",
    "sg:province":"Graubunden",
    "wof:name":"Beratungen Wielath Josef Anton",
    "wof:placetype":"venue"
},
  "geometry": {"coordinates":[9.5266504288,46.8583259583],"type":"Point"}
}