{
  "type": "Feature",
  "properties": {
    "iso:country":"CH",
    "sg:address":"Feldmatt41",
    "sg:city":"Altishofen",
    "sg:orig_category":"Malerei",
    "sg:phone":"+41 62 756 36 58",
    "sg:postcode":"6246",
    "sg:province":"Luzern",
    "wof:name":"Hodel Maler Ag Malergesch\u00e4ft",
    "wof:placetype":"venue"
},
  "geometry": {"coordinates":[7.967004776,47.2023200989],"type":"Point"}
}