{
  "type": "Feature",
  "properties": {
    "iso:country":"CH",
    "sg:address":"Rue Du Simplon 2",
    "sg:city":"Vevey",
    "sg:orig_category":"Drogerien",
    "sg:phone":"+41 32 466 11 73",
    "sg:postcode":"1800",
    "sg:province":"Vaud",
    "wof:name":"Droguerie-parfumerie-photo Worni Jacques",
    "wof:placetype":"venue"
},
  "geometry": {"coordinates":[7.0761761665,47.4169540405],"type":"Point"}
}