{
  "type": "Feature",
  "properties": {
    "iso:country":"CH",
    "sg:address":"Hintergasse 14",
    "sg:city":"Fehraltorf",
    "sg:classifiers":[
        {
            "category":"Insurance",
            "subcategory":"Insurance Agent",
            "type":"Services"
        }
    ],
    "sg:phone":"+41 19541031",
    "sg:postcode":"8320",
    "sg:province":"Z\u00fcrich",
    "sg:tags":[
        "versicherungsagenturen",
        "-broker"
    ],
    "wof:name":"Basler Versicherungen Agentur Bajram Veseli",
    "wof:placetype":"venue"
},
  "geometry": {"coordinates":[8.7509555817,47.3879318237],"type":"Point"}
}