{
  "type": "Feature",
  "properties": {
    "iso:country":"CH",
    "sg:address":"Rieu Chemin 8 1208 Gen\u00e8ve. Postfach",
    "sg:city":"Gen\u00e8ve",
    "sg:orig_category":"Unclassifiable Establishments",
    "sg:postcode":"1201",
    "sg:province":"Gen\u00e8ve",
    "wof:name":"Epi Bijoux B. Ebstein",
    "wof:placetype":"venue"
},
  "geometry": {"coordinates":[-105.89307403559999,39.3157958984],"type":"Point"}
}