{
  "type": "Feature",
  "properties": {
    "iso:country":"CH",
    "sg:address":"Feldstrasse 144",
    "sg:city":"Z\u00fcrich",
    "sg:orig_category":"HOTELS: MIT RESTAURANT RESTAURANTS: NICHT EIGENST\u00c4NDIG",
    "sg:phone":"+41 12420118",
    "sg:postcode":"8004",
    "sg:province":"Z\u00fcrich",
    "wof:name":"Hotel Contiki",
    "wof:placetype":"venue"
},
  "geometry": {"coordinates":[8.5252170563,47.3804893494],"type":"Point"}
}