{
  "type": "Feature",
  "properties": {
    "iso:country":"CH",
    "sg:address":"R\u00fctimeyerplatz 2",
    "sg:city":"Basel",
    "sg:orig_category":"Grosshandel mit sonstigen Konsumg\u00fctern K\u00fcnstlerische U schriftstellerische T\u00e4tigkeiten U Darbietunge",
    "sg:phone":"+41 61 281 29 29",
    "sg:postcode":"4054",
    "sg:province":"Basel-Stadt",
    "wof:name":"J. L\u00fcber Ag",
    "wof:placetype":"venue"
},
  "geometry": {"coordinates":[7.5759701729,47.5494766235],"type":"Point"}
}