{
  "type": "Feature",
  "properties": {
    "addr:full":"Sonnacker 39 Arni Aargau 8905",
    "addr:housenumber":"39",
    "addr:postcode":"8905",
    "addr:street":"Sonnacker",
    "iso:country":"CH",
    "sg:address":"Sonnacker 39",
    "sg:city":"Arni",
    "sg:classifiers":[
        {
            "category":"Autos & Motor Vehicles",
            "subcategory":"Auto Supplies",
            "type":"Retail Goods"
        }
    ],
    "sg:phone":"+41 56 634 37 57",
    "sg:postcode":"8905",
    "sg:province":"Aargau",
    "sg:tags":[
        "auto-sprays"
    ],
    "wof:name":"Ap-systems",
    "wof:placetype":"venue"
},
  "geometry": {"coordinates":[8.413962,47.321396],"type":"Point"}
}