{
  "type": "Feature",
  "properties": {
    "iso:country":"CH",
    "sg:address":"Im St\u00e4dtchen 13 3235 Erlach. Postfach 21",
    "sg:city":"Erlach",
    "sg:orig_category":"Detailhandel mit Fleisch U Fleischwaren",
    "sg:phone":"+41 21 784 11 44",
    "sg:postcode":"3235",
    "sg:province":"Bern",
    "wof:name":"Cachin O. Sa",
    "wof:placetype":"venue"
},
  "geometry": {"coordinates":[6.6956381798,46.5544815063],"type":"Point"}
}