{
  "type": "Feature",
  "properties": {
    "iso:country":"CH",
    "sg:address":"Pelzgasse 15 5000 Aarau. Postfach",
    "sg:city":"Aarau",
    "sg:orig_category":"Interessenvertretungen",
    "sg:postcode":"5004",
    "sg:province":"Aargau",
    "wof:name":"Corona, Stiftung Zur F\u00f6rderung Des Genussrauchens (cigarren Und Pfeifenrauchen)",
    "wof:placetype":"venue"
},
  "geometry": {"coordinates":[8.0448446274,47.3927001953],"type":"Point"}
}