{
  "type": "Feature",
  "properties": {
    "iso:country":"CH",
    "sg:address":"Oberdorf 12",
    "sg:city":"Beringen",
    "sg:orig_category":"RESTAURANTS: TEA-ROOMS",
    "sg:postcode":"8222",
    "sg:province":"Schaffhausen",
    "wof:name":"Von Euw Albin.",
    "wof:placetype":"venue"
},
  "geometry": {"coordinates":[8.5741605759,47.6986351013],"type":"Point"}
}