{
  "type": "Feature",
  "properties": {
    "iso:country":"CH",
    "sg:address":"Marktplatzstrasse 12",
    "sg:city":"Turtmann",
    "sg:orig_category":"Detailhandel mit elektrischen Haushalts-,Radio U Fernsehger\u00e4ten sowie Musikinstrumenten",
    "sg:phone":"+41 79 213 84 75",
    "sg:postcode":"3946",
    "sg:province":"Valais",
    "wof:name":"Weissbrodt Roger, Haushaltger\u00e4te & K\u00fcchen",
    "wof:placetype":"venue"
},
  "geometry": {"coordinates":[7.7018499374,46.2992362976],"type":"Point"}
}