{
  "type": "Feature",
  "properties": {
    "iso:country":"CH",
    "sg:address":"Olivengasse 11",
    "sg:city":"Z\u00fcrich",
    "sg:orig_category":"Architektur U Ingenieurb\u00fcros Architekturb\u00fcros",
    "sg:phone":"+41 79 344 33 09",
    "sg:postcode":"8032",
    "sg:province":"Z\u00fcrich",
    "wof:name":"R\u00fcegg Walter Ag, Dipl. Architekten Eth/sia",
    "wof:placetype":"venue"
},
  "geometry": {"coordinates":[8.557429,47.363838],"type":"Point"}
}