{
  "type": "Feature",
  "properties": {
    "iso:country":"CH",
    "sg:address":"La Ferme",
    "sg:city":"Rochefort",
    "sg:orig_category":"Sportvereine Sch\u00fctzen",
    "sg:phone":"+41 32 855 14 64",
    "sg:postcode":"2203",
    "wof:name":"St\u00e9 De Tir Armes Rochefort",
    "wof:placetype":"venue"
},
  "geometry": {"coordinates":[-0.9587000012,45.9348182678],"type":"Point"}
}