{
  "type": "Feature",
  "properties": {
    "iso:country":"CH",
    "sg:address":"Bernstr. 253",
    "sg:city":"Berikon",
    "sg:orig_category":"Herstellung von Elektromotoren, Generatoren U Transformatoren",
    "sg:postcode":"8965",
    "sg:province":"Aargau",
    "wof:name":"Elektronet Gmbh",
    "wof:placetype":"venue"
},
  "geometry": {"coordinates":[7.1248178482,46.9302406311],"type":"Point"}
}