{
  "type": "Feature",
  "properties": {
    "iso:country":"CH",
    "sg:address":"Hafenstrasse 28",
    "sg:city":"Kesswil",
    "sg:orig_category":"Unclassifiable Establishments",
    "sg:postcode":"8593",
    "sg:province":"Thurgau",
    "wof:name":"Psk Pro Schiff Kesswil Ag",
    "wof:placetype":"venue"
},
  "geometry": {"coordinates":[9.3220386505,47.5956115723],"type":"Point"}
}