{
  "type": "Feature",
  "properties": {
    "iso:country":"CH",
    "sg:address":"Ziel 382",
    "sg:city":"Wittenbach",
    "sg:orig_category":"G\u00fcterbef\u00f6rderung im Strassenverkehr",
    "sg:phone":"+41 71 298 56 66",
    "sg:postcode":"9303",
    "wof:name":"Josef Eigenmann Transporte & Camionnage",
    "wof:placetype":"venue"
},
  "geometry": {"coordinates":[9.3763399124,47.4625015259],"type":"Point"}
}