{
  "type": "Feature",
  "properties": {
    "iso:country":"CH",
    "sg:address":"St. Alban-anlage 64 4052 Basel. Postfach",
    "sg:city":"Basel",
    "sg:orig_category":"Binnenschiffahrt",
    "sg:postcode":"4051",
    "sg:province":"Basel-Stadt",
    "wof:name":"Hersula Reederei Ag Passagierschiffahrt, Betrieb V. Hotels In Europa, Reiseorganisation Usw.",
    "wof:placetype":"venue"
},
  "geometry": {"coordinates":[7.603028,47.5527],"type":"Point"}
}