{
  "type": "Feature",
  "properties": {
    "iso:country":"CH",
    "sg:address":"Chemin De Chisaz 1",
    "sg:city":"Crissier",
    "sg:orig_category":"RESTAURANTS: TEA-ROOMS",
    "sg:postcode":"1023",
    "sg:province":"Vaud",
    "wof:name":"Schenk No\u00e9mi",
    "wof:placetype":"venue"
},
  "geometry": {"coordinates":[6.5782938004,46.5499267578],"type":"Point"}
}