{
  "type": "Feature",
  "properties": {
    "iso:country":"CH",
    "sg:address":"Landstrasse 8 9496 Balzers. Postfach 163",
    "sg:city":"Balzers",
    "sg:orig_category":"Verwaltung von Immobilien",
    "sg:phone":"+423 388 15 55",
    "sg:postcode":"9496",
    "wof:name":"Trebona-anstalt Verwaltungs-& Treuhandb\u00fcro",
    "wof:placetype":"venue"
},
  "geometry": {"coordinates":[9.5109786987,47.0741081238],"type":"Point"}
}