{
  "type": "Feature",
  "properties": {
    "iso:country":"CH",
    "sg:address":"Bahnhofstrasse 11 Postfach 1632",
    "sg:city":"Amriswil",
    "sg:classifiers":[
        {
            "category":"Manufacturing",
            "subcategory":"Printing",
            "type":"Manufacturing & Wholesale Goods"
        }
    ],
    "sg:phone":"+41 71 414 14 64",
    "sg:postcode":"8580",
    "sg:province":"Thurgau",
    "sg:tags":[
        "publishing"
    ],
    "wof:name":"Grob Druck Ag",
    "wof:placetype":"venue"
},
  "geometry": {"coordinates":[9.1232995987,51.156829834],"type":"Point"}
}