{
  "type": "Feature",
  "properties": {
    "iso:country":"CH",
    "sg:address":"Aeulestrasse 22",
    "sg:city":"Triesen",
    "sg:orig_category":"Schlossereien Stahl U Leichtmetallbau",
    "sg:phone":"+423 392 36 02",
    "sg:postcode":"9495",
    "wof:name":"Peter Eberle Ag Metallbau & Schlosserei",
    "wof:placetype":"venue"
},
  "geometry": {"coordinates":[9.5229291916,47.1163253784],"type":"Point"}
}