{
  "type": "Feature",
  "properties": {
    "iso:country":"CH",
    "sg:address":"Scheuchzerstrasse 68",
    "sg:city":"Z\u00fcrich",
    "sg:orig_category":"Interessenvertretungen",
    "sg:postcode":"8006",
    "sg:province":"Z\u00fcrich",
    "wof:name":"Stiftung J\u00fcdische Zeitgeschichte An Der Eth Z\u00fcrich Zur Sicherung Und Erschliessung Historischer Quellen In Der Schweiz",
    "wof:placetype":"venue"
},
  "geometry": {"coordinates":[8.5453882217,47.3865280151],"type":"Point"}
}