{
  "type": "Feature",
  "properties": {
    "iso:country":"CH",
    "sg:address":"Juchstrasse 27",
    "sg:city":"W\u00fcrenlos",
    "sg:orig_category":"Fotografische Ateliers Technische, physikalische U chemische Untersuchung",
    "sg:phone":"+41 56 424 19 14",
    "sg:postcode":"5436",
    "sg:province":"Aargau",
    "wof:name":"Thomas Pfau, Ing.",
    "wof:placetype":"venue"
},
  "geometry": {"coordinates":[8.3586463928,47.4416732788],"type":"Point"}
}