{
  "type": "Feature",
  "properties": {
    "iso:country":"CH",
    "sg:address":"Trolimatten 544",
    "sg:city":"Zetzwil",
    "sg:orig_category":"Stukkateurgewerbe, Gipserei U Verputzerei",
    "sg:phone":"+41 62 773 19 69",
    "sg:postcode":"5732",
    "sg:province":"Aargau",
    "wof:name":"Orlando Pietro Ag",
    "wof:placetype":"venue"
},
  "geometry": {"coordinates":[8.154586792,47.2856254578],"type":"Point"}
}