{
  "type": "Feature",
  "properties": {
    "iso:country":"CH",
    "sg:address":"Fischerweg 2",
    "sg:city":"Biel/bienne",
    "sg:orig_category":"Wirtschaftspr\u00fcfung, Steuerberatung U Treuhand",
    "sg:phone":"+41 32 331 83 54",
    "sg:postcode":"2502",
    "sg:province":"Bern",
    "wof:name":"Grandjean Peter, Treuhand Und Verwaltung",
    "wof:placetype":"venue"
},
  "geometry": {"coordinates":[7.2380509377,47.1303405762],"type":"Point"}
}