{
  "type": "Feature",
  "properties": {
    "iso:country":"CH",
    "sg:address":"Stegreutistrasse 4 B",
    "sg:city":"M\u00fcnsingen",
    "sg:orig_category":"Detailhandel mit Waren verschiedener Art, Hauptrichtung Nahrungsmittel",
    "sg:postcode":"3110",
    "sg:province":"Bern",
    "wof:name":"Noah Corporation Langenegger & Partner",
    "wof:placetype":"venue"
},
  "geometry": {"coordinates":[9.3509435654,47.4123764038],"type":"Point"}
}