{
  "type": "Feature",
  "properties": {
    "iso:country":"CH",
    "sg:address":"Via Serafino Balestra 17",
    "sg:city":"Lugano",
    "sg:orig_category":"Unclassifiable Establishments",
    "sg:postcode":"6900",
    "sg:province":"Ticino",
    "wof:name":"Amerinter Sa",
    "wof:placetype":"venue"
},
  "geometry": {"coordinates":[8.9561986923,46.0081291199],"type":"Point"}
}