{
  "type": "Feature",
  "properties": {
    "iso:country":"CH",
    "sg:address":"Alte Steinhauserstrasse 1",
    "sg:city":"Cham",
    "sg:classifiers":[
        {
            "category":"Banks & Credit Unions",
            "subcategory":"Bureau De Change",
            "type":"Services"
        }
    ],
    "sg:phone":"+41 41 410 40 21",
    "sg:postcode":"6330",
    "sg:province":"Zug",
    "sg:tags":[
        "revision"
    ],
    "wof:name":"Albert Kuhn Treuhandb\u00fcro",
    "wof:placetype":"venue"
},
  "geometry": {"coordinates":[8.1952953339,47.1163864136],"type":"Point"}
}