{
  "type": "Feature",
  "properties": {
    "iso:country":"CH",
    "sg:address":"Oberwolfhausenstrasse",
    "sg:city":"Wolfhausen",
    "sg:orig_category":"Herstellung von Ger\u00e4ten der Elektrizit\u00e4tserzeugung, -verteilung u.\u00e4. -Herstellung von Elektromotoren",
    "sg:phone":"+41 55 253 26 00",
    "sg:postcode":"8633",
    "sg:province":"Z\u00fcrich",
    "wof:name":"Dynawatt Ag",
    "wof:placetype":"venue"
},
  "geometry": {"coordinates":[8.7929506302,47.260055542],"type":"Point"}
}