{
  "type": "Feature",
  "properties": {
    "iso:country":"CH",
    "sg:address":"F\u00fcrstenlandstrasse 115 9000 St.gallen. Postfach 9014 St. Gallen",
    "sg:city":"Zust",
    "sg:orig_category":"Grosshandel mit Getr\u00e4nken",
    "sg:phone":"+41 71 277 32 44",
    "sg:postcode":"14",
    "wof:name":"Wiederkehr Getr\u00e4nke Ag",
    "wof:placetype":"venue"
},
  "geometry": {"coordinates":[9.3477201462,47.4136199951],"type":"Point"}
}