{
  "type": "Feature",
  "properties": {
    "iso:country":"CH",
    "sg:address":"Eichenstrasse 12",
    "sg:city":"Pf\u00e4ffikon",
    "sg:orig_category":"Anticorrosives",
    "sg:phone":"+41 55 415 50 00",
    "sg:postcode":"8808",
    "sg:province":"Schwyz",
    "wof:name":"Laubscher Korrosions- Und Bautenschutz Ag",
    "wof:placetype":"venue"
},
  "geometry": {"coordinates":[8.762976,47.19759],"type":"Point"}
}