{
  "type": "Feature",
  "properties": {
    "iso:country":"CH",
    "sg:address":"Dorf 9658 Wildhaus. Postfach",
    "sg:city":"Wildhaus",
    "sg:orig_category":"Herstellung von Metallkonstruktionen",
    "sg:postcode":"9658",
    "sg:province":"St. Gallen",
    "wof:name":"K\u00f6pfli Daniel, Delaval-service Melkanlagen, Entmistungen, Komplette Stalleinrichtungen Usw.; Verkauf, Service U. Reparatur",
    "wof:placetype":"venue"
},
  "geometry": {"coordinates":[9.351433754,47.2034492493],"type":"Point"}
}