{
  "type": "Feature",
  "properties": {
    "iso:country":"CH",
    "sg:address":"Via Cantonale 4",
    "sg:city":"Mezzovico",
    "sg:classifiers":[
        {
            "category":"Travel",
            "subcategory":"Hotels & Motels",
            "type":"Entertainment"
        }
    ],
    "sg:phone":"+41 91 946 27 33",
    "sg:postcode":"6805",
    "sg:province":"Ticino",
    "sg:tags":[
        "mit",
        "restaurant"
    ],
    "wof:name":"Albergo Diamante Blu",
    "wof:placetype":"venue"
},
  "geometry": {"coordinates":[8.927652359,46.0981941223],"type":"Point"}
}