{
  "type": "Feature",
  "properties": {
    "addr:full":"Theaterstrasse 2 Z\u00fcrich Z\u00fcrich 8001",
    "addr:housenumber":"2",
    "addr:postcode":"8001",
    "addr:street":"Theaterstrasse",
    "iso:country":"CH",
    "sg:address":"Theaterstrasse 2",
    "sg:city":"Z\u00fcrich",
    "sg:orig_category":"Detailhandel mit Brillen U anderen Sehhilfen Detailhandel mit medizinischen U orthop\u00e4dischen Artikel",
    "sg:phone":"+41 12623877",
    "sg:postcode":"8001",
    "sg:province":"Z\u00fcrich",
    "wof:name":"H\u00f6rberatung Stadelhofen, Schneebeli Maya, Akustikerin",
    "wof:placetype":"venue"
},
  "geometry": {"coordinates":[8.5479,47.365379],"type":"Point"}
}