{
  "type": "Feature",
  "properties": {
    "iso:country":"CH",
    "sg:address":"Escherstrasse 59",
    "sg:city":"Sch\u00e4nis",
    "sg:orig_category":"Verlegen von Fliesen U Platten",
    "sg:phone":"+41 55 615 36 34",
    "sg:postcode":"8718",
    "sg:province":"St. Gallen",
    "wof:name":"Franz Stucki Chemin\u00e9ebau & Plattenbel\u00e4ge",
    "wof:placetype":"venue"
},
  "geometry": {"coordinates":[9.0457820892,47.1550102234],"type":"Point"}
}