{
  "type": "Feature",
  "properties": {
    "iso:country":"CH",
    "sg:address":"Werdstrasse 6",
    "sg:city":"Rottenschwil",
    "sg:orig_category":"Erdbewegungsarbeiten",
    "sg:phone":"+41 79 353 50 14",
    "sg:postcode":"8919",
    "sg:province":"Aargau",
    "wof:name":"Heinz Ritter Bagger-& Traxunternehmung",
    "wof:placetype":"venue"
},
  "geometry": {"coordinates":[9.541352272,47.2190284729],"type":"Point"}
}