{
  "type": "Feature",
  "properties": {
    "iso:country":"CH",
    "sg:address":"Morgartenstrasse 7",
    "sg:city":"Luzern",
    "sg:orig_category":"Advokaturb\u00fcros",
    "sg:phone":"+41 71 622 82 88",
    "sg:postcode":"6003",
    "sg:province":"Luzern",
    "wof:name":"Hangartner & Zweidler Advokaturb\u00fcro",
    "wof:placetype":"venue"
},
  "geometry": {"coordinates":[9.138185,47.566669],"type":"Point"}
}