{
  "type": "Feature",
  "properties": {
    "iso:country":"CH",
    "sg:address":"Meiental",
    "sg:city":"Trimstein",
    "sg:orig_category":"Sportvereine Turnen",
    "sg:postcode":"3083",
    "sg:province":"Bern",
    "wof:name":"M\u00e4nnerriege M\u00fcnsingen",
    "wof:placetype":"venue"
},
  "geometry": {"coordinates":[7.5825619698,46.9012489319],"type":"Point"}
}