{
  "type": "Feature",
  "properties": {
    "iso:country":"CH",
    "sg:address":"St. Gallerstrasse 10 Kronb\u00fchl 9303 Wittenbach. Postfach",
    "sg:city":"Kronb\u00fchl",
    "sg:orig_category":"Fachdetailhandel mit pharmazeutischen Produkten",
    "sg:postcode":"9302",
    "wof:name":"Kronb\u00fchl-apotheke Keller E. Ag",
    "wof:placetype":"venue"
},
  "geometry": {"coordinates":[9.3763399124,47.4625015259],"type":"Point"}
}