{
  "type": "Feature",
  "properties": {
    "iso:country":"CH",
    "sg:address":"Berglistrasse 27",
    "sg:city":"Arbon",
    "sg:orig_category":"Druck ohne Zeitungsdruck Offsetdruck",
    "sg:phone":"+41 62 822 69 55",
    "sg:postcode":"9320",
    "sg:province":"Thurgau",
    "wof:name":"Druckerei M\u00e4der Ag",
    "wof:placetype":"venue"
},
  "geometry": {"coordinates":[8.0645446777,47.3899116516],"type":"Point"}
}