{
  "type": "Feature",
  "properties": {
    "addr:full":"Hohenrainstrasse 40 Pratteln Basel-Landschaft 4133",
    "addr:housenumber":"40",
    "addr:postcode":"4133",
    "addr:street":"Hohenrainstrasse",
    "iso:country":"CH",
    "sg:address":"Hohenrainstrasse 40",
    "sg:city":"Pratteln",
    "sg:orig_category":"Allgemeiner Hoch U Tiefbau",
    "sg:phone":"+41 61 821 31 51",
    "sg:postcode":"4133",
    "sg:province":"Basel-Landschaft",
    "wof:name":"Finnhaus Gmbh",
    "wof:placetype":"venue"
},
  "geometry": {"coordinates":[7.70073,47.525093],"type":"Point"}
}