{
  "type": "Feature",
  "properties": {
    "iso:country":"CH",
    "sg:address":"Via Alla Torre 18",
    "sg:city":"Mendrisio",
    "sg:orig_category":"Gymnastik U Fitnesszentren Saunas, Solarien, Fitnesszentren U \u00e4hnliches",
    "sg:phone":"+41 91 646 74 95",
    "sg:postcode":"6850",
    "sg:province":"Ticino",
    "wof:name":"Athletic Body Sagl Fitness-center",
    "wof:placetype":"venue"
},
  "geometry": {"coordinates":[8.9876899719,45.8675384521],"type":"Point"}
}