{
  "type": "Feature",
  "properties": {
    "iso:country":"CH",
    "sg:address":"Kirchstrasse 20",
    "sg:city":"Dietikon",
    "sg:orig_category":"Unclassifiable Establishments",
    "sg:postcode":"8953",
    "sg:province":"Z\u00fcrich",
    "wof:name":"Mabar Ag.",
    "wof:placetype":"venue"
},
  "geometry": {"coordinates":[8.4034795761,47.4052848816],"type":"Point"}
}