{
  "type": "Feature",
  "properties": {
    "iso:country":"CH",
    "sg:address":"Rue Louis De Savoie 56",
    "sg:city":"Morges",
    "sg:orig_category":"Chemische Reinigung W\u00e4schereien",
    "sg:phone":"+41 21 803 15 60",
    "sg:postcode":"1110",
    "sg:province":"Vaud",
    "wof:name":"Pressing A L'artisan Nettoyeur Nett.\u00e0 Sec Rita Stifani",
    "wof:placetype":"venue"
},
  "geometry": {"coordinates":[6.498594,46.508617],"type":"Point"}
}