{
  "type": "Feature",
  "properties": {
    "addr:full":"Louis Giroud-strasse 37 4600 Olten. Postfach Olten Solothurn 4601",
    "addr:housenumber":"37",
    "addr:postcode":"4600 olten. postfach;4601",
    "iso:country":"CH",
    "sg:address":"Louis Giroud-strasse 37 4600 Olten. Postfach",
    "sg:city":"Olten",
    "sg:orig_category":"Berufsberatungen",
    "sg:phone":"+41 62 287 73 00",
    "sg:postcode":"4601",
    "sg:province":"Solothurn",
    "wof:name":"Berufs-& Studienberatung",
    "wof:placetype":"venue"
},
  "geometry": {"coordinates":[7.91001,47.346336],"type":"Point"}
}