{
  "type": "Feature",
  "properties": {
    "iso:country":"CH",
    "sg:address":"Allmend 2",
    "sg:city":"Widen",
    "sg:orig_category":"Datenverarbeitungsdienste Sonstige mit der Informatik verbundene T\u00e4tigkeiten",
    "sg:phone":"+41 56 648 50 50",
    "sg:postcode":"8967",
    "sg:province":"Aargau",
    "wof:name":"Sika Informationssysteme Ag",
    "wof:placetype":"venue"
},
  "geometry": {"coordinates":[8.365229,47.367645],"type":"Point"}
}