{
  "type": "Feature",
  "properties": {
    "iso:country":"CH",
    "sg:address":"Via Moncucco 7",
    "sg:city":"Lugano",
    "sg:orig_category":"Elektroinstallation Herstellung von Elektromotoren, Generatoren U Transformatoren",
    "sg:phone":"+41 14652111",
    "sg:postcode":"6900",
    "sg:province":"Ticino",
    "wof:name":"Alcatel E-business Distribution Ag",
    "wof:placetype":"venue"
},
  "geometry": {"coordinates":[8.9419031143,46.0051727295],"type":"Point"}
}