{
  "type": "Feature",
  "properties": {
    "iso:country":"CH",
    "sg:address":"Hauptstr. 78",
    "sg:city":"Guntershausen",
    "sg:orig_category":"Zimmerei, Dachdeckerei, Bauspenglerei U Abdichtung",
    "sg:phone":"+41 52 365 39 76",
    "sg:postcode":"8357",
    "sg:province":"Thurgau",
    "wof:name":"M\u00fcller Heinz",
    "wof:placetype":"venue"
},
  "geometry": {"coordinates":[8.921998024,47.4725341797],"type":"Point"}
}