{
  "type": "Feature",
  "properties": {
    "iso:country":"CH",
    "sg:address":"Dorfstrasse 2",
    "sg:city":"Russikon",
    "sg:classifiers":[
        {
            "category":"Restaurant",
            "type":"Food & Drink"
        }
    ],
    "sg:phone":"+41 79 431 99 76",
    "sg:postcode":"8332",
    "sg:province":"Z\u00fcrich",
    "wof:name":"Pizzeria Adria",
    "wof:placetype":"venue"
},
  "geometry": {"coordinates":[8.7762537003,47.3941116333],"type":"Point"}
}