{
  "type": "Feature",
  "properties": {
    "iso:country":"CH",
    "sg:address":"Thunstrasse 15 3612 Steffisburg. Postfach 177",
    "sg:city":"Thun",
    "sg:orig_category":"Herstellung von Werkzeugen Herstellung von sonstigen Werkzeugmaschinen",
    "sg:phone":"+41 32 344 11 52",
    "sg:postcode":"3602",
    "sg:province":"Bern",
    "wof:name":"Htt Hauser Tripet Tschudin Ag",
    "wof:placetype":"venue"
},
  "geometry": {"coordinates":[7.2870998383,47.1544113159],"type":"Point"}
}