{
  "type": "Feature",
  "properties": {
    "iso:country":"CH",
    "sg:address":"Ziegelbr\u00fccke 8867 Niederurnen. Postfach",
    "sg:city":"Ziegelbr\u00fccke",
    "sg:orig_category":"Interessenvertretungen",
    "sg:postcode":"8866",
    "sg:province":"Glarus",
    "wof:name":"Jenny-aebli Caspar Und Elise - Stiftung F\u00fcr Erholungsbed\u00fcrftige",
    "wof:placetype":"venue"
},
  "geometry": {"coordinates":[9.0587711334,47.131401062],"type":"Point"}
}