{
  "type": "Feature",
  "properties": {
    "iso:country":"CH",
    "sg:address":"Friburgstr. 65 1796 Courgevaux. Postfach",
    "sg:city":"Courgevaux",
    "sg:orig_category":"Pensionskassen",
    "sg:postcode":"1796",
    "sg:province":"Fribourg",
    "wof:name":"Personalf\u00fcrsorgestiftung Der Firma Gravograph Ag",
    "wof:placetype":"venue"
},
  "geometry": {"coordinates":[7.1117019653,46.9076766968],"type":"Point"}
}