{
  "type": "Feature",
  "properties": {
    "iso:country":"CH",
    "sg:address":"Hauptstrasse 81 6182 Escholzmatt. Postfach 138",
    "sg:city":"Escholzmatt",
    "sg:orig_category":"Herstellung von Reiseartikeln, Leder U Sattlerwaren Herstellung von Wellpapier U pappe sowie von Ver",
    "sg:phone":"+41 32 913 06 03",
    "sg:postcode":"6182",
    "sg:province":"Luzern",
    "wof:name":"Aubin France-patrice",
    "wof:placetype":"venue"
},
  "geometry": {"coordinates":[6.8212199211,47.1051902771],"type":"Point"}
}