{
  "type": "Feature",
  "properties": {
    "iso:country":"CH",
    "sg:address":"Chemin Du Cr\u00eat 2",
    "sg:city":"Chavannes-de-bogis",
    "sg:orig_category":"Detailhandel mit Waren verschiedener Art, Hauptrichtung Nahrungsmittel",
    "sg:phone":"+41 24 425 14 54",
    "sg:postcode":"1279",
    "sg:province":"Vaud",
    "wof:name":"Perches-import S.a.",
    "wof:placetype":"venue"
},
  "geometry": {"coordinates":[6.1626939774,46.3461685181],"type":"Point"}
}