{
  "type": "Feature",
  "properties": {
    "iso:country":"CH",
    "sg:address":"Aarwangenstrasse 55",
    "sg:city":"Langenthal",
    "sg:orig_category":"Interessenvertretungen",
    "sg:postcode":"4900",
    "sg:province":"Bern",
    "wof:name":"Stiftung Lydia Eymann",
    "wof:placetype":"venue"
},
  "geometry": {"coordinates":[7.7835459709,47.2197265625],"type":"Point"}
}