{
  "type": "Feature",
  "properties": {
    "iso:country":"CH",
    "sg:address":"Centralstrasse 22",
    "sg:city":"Sursee",
    "sg:orig_category":"Detailhandel mit Waren verschiedener Art, Hauptrichtung Nahrungsmittel",
    "sg:phone":"+41 41 920 11 64",
    "sg:postcode":"6210",
    "sg:province":"Luzern",
    "wof:name":"Heinen Eduard",
    "wof:placetype":"venue"
},
  "geometry": {"coordinates":[8.1031503677,47.1708374023],"type":"Point"}
}