{
  "type": "Feature",
  "properties": {
    "iso:country":"CH",
    "sg:address":"Fidmenstrasse 2",
    "sg:city":"Gersau",
    "sg:orig_category":"Innendekorationsateliers",
    "sg:phone":"+41 41 828 12 26",
    "sg:postcode":"6442",
    "sg:province":"Schwyz",
    "wof:name":"Peter M\u00fcller Innendekorationen",
    "wof:placetype":"venue"
},
  "geometry": {"coordinates":[8.5256252289,46.9929351807],"type":"Point"}
}