{
  "type": "Feature",
  "properties": {
    "iso:country":"CH",
    "sg:address":"Via Chantunela 62b",
    "sg:city":"Silvaplana",
    "sg:orig_category":"Tankstellen",
    "sg:phone":"+41 81 828 89 20",
    "sg:postcode":"7513",
    "sg:province":"Graubunden",
    "wof:name":"Esso Muntanella",
    "wof:placetype":"venue"
},
  "geometry": {"coordinates":[9.7905330658,46.4558944702],"type":"Point"}
}