{
  "type": "Feature",
  "properties": {
    "iso:country":"CH",
    "sg:address":"Cornavin Rue De 5 1201 Gen\u00e8ve Case Postale 2255",
    "sg:city":"Gen\u00e8ve",
    "sg:orig_category":"Herstellung von Uhren",
    "sg:phone":"+41 22 732 55 72",
    "sg:postcode":"1201",
    "sg:province":"Gen\u00e8ve",
    "wof:name":"Timetec Sa",
    "wof:placetype":"venue"
},
  "geometry": {"coordinates":[6.1425209045,46.2098770142],"type":"Point"}
}