{
  "type": "Feature",
  "properties": {
    "addr:full":"Br\u00fcnnenstrasse 115 Bern Bern 3018",
    "addr:housenumber":"115",
    "addr:postcode":"3018",
    "addr:street":"Bruennenstrasse",
    "iso:country":"CH",
    "sg:address":"Br\u00fcnnenstrasse 115",
    "sg:city":"Bern",
    "sg:orig_category":"Advokaturb\u00fcros",
    "sg:phone":"+41 31 992 10 77",
    "sg:postcode":"3018",
    "sg:province":"Bern",
    "wof:name":"Gurtner Liechti & Fischer Advokaturb\u00fcro",
    "wof:placetype":"venue"
},
  "geometry": {"coordinates":[7.391606,46.941772],"type":"Point"}
}