{
  "type": "Feature",
  "properties": {
    "iso:country":"CH",
    "sg:address":"Wettingerstrasse 29",
    "sg:city":"Baden",
    "sg:orig_category":"Wirtschaftspr\u00fcfung, Steuerberatung U Treuhand",
    "sg:phone":"+41 56 210 30 90",
    "sg:postcode":"5400",
    "sg:province":"Aargau",
    "wof:name":"L\u00e4gern Treuhand Ag",
    "wof:placetype":"venue"
},
  "geometry": {"coordinates":[8.3165102005,47.4704360962],"type":"Point"}
}