{
  "type": "Feature",
  "properties": {
    "iso:country":"CH",
    "sg:address":"Langstrasse 35",
    "sg:city":"Z\u00fcrich",
    "sg:classifiers":[
        {
            "category":"Restaurant",
            "type":"Food & Drink"
        }
    ],
    "sg:phone":"+41 32 913 13 33",
    "sg:postcode":"8004",
    "sg:province":"Z\u00fcrich",
    "wof:name":"Pizzeria Cercle Italien",
    "wof:placetype":"venue"
},
  "geometry": {"coordinates":[6.8256292343,47.1016120911],"type":"Point"}
}