{
  "type": "Feature",
  "properties": {
    "iso:country":"CH",
    "sg:address":"Gas-str. 8 3000 Bern. Postfach",
    "sg:city":"Bern",
    "sg:orig_category":"RESTAURANTS: TEA-ROOMS",
    "sg:postcode":"3000",
    "sg:province":"Bern",
    "wof:name":"J. Frei Rest. Marzilibr\u00fccke",
    "wof:placetype":"venue"
},
  "geometry": {"coordinates":[7.444381237,46.9450569153],"type":"Point"}
}