{
  "type": "Feature",
  "properties": {
    "iso:country":"CH",
    "sg:address":"Via Cremignone 3",
    "sg:city":"Sorengo",
    "sg:orig_category":"Fachdetailhandel in Verkaufsr\u00e4umen",
    "sg:postcode":"6924",
    "sg:province":"Ticino",
    "wof:name":"Fiorosa Di Braunwalder-derrer Rosa",
    "wof:placetype":"venue"
},
  "geometry": {"coordinates":[8.9337902069,46.0023002625],"type":"Point"}
}