{
  "type": "Feature",
  "properties": {
    "iso:country":"CH",
    "sg:address":"Weinfelder Strasse 1",
    "sg:city":"Mettlen",
    "sg:orig_category":"Werbeagenturen",
    "sg:phone":"+41 71 630 01 02",
    "sg:postcode":"9517",
    "sg:province":"Thurgau",
    "wof:name":"Karrer & St\u00f6ckli Werbung & Promotion",
    "wof:placetype":"venue"
},
  "geometry": {"coordinates":[9.1204586029,47.5332717896],"type":"Point"}
}