{
  "type": "Feature",
  "properties": {
    "iso:country":"CH",
    "sg:address":"Freilagerstrasse 29",
    "sg:city":"Z\u00fcrich",
    "sg:orig_category":"Architekturb\u00fcros",
    "sg:phone":"+41 71 244 63 38",
    "sg:postcode":"8047",
    "sg:province":"Z\u00fcrich",
    "wof:name":"Boris Polasek Architekturb\u00fcro",
    "wof:placetype":"venue"
},
  "geometry": {"coordinates":[9.394195,47.433395],"type":"Point"}
}