{
  "type": "Feature",
  "properties": {
    "iso:country":"CH",
    "sg:address":"1872 Troistorrents Case Postale 60",
    "sg:city":"Troistorrents",
    "sg:orig_category":"Detailhandel mit Radio U Fernsehger\u00e4ten Detailhandel mit elektrischen Haushalts-,Radio U Fernsehger\u00e4",
    "sg:phone":"+41 24 477 42 12",
    "sg:postcode":"1872",
    "sg:province":"Valais",
    "wof:name":"Tv Loisir Bernard D\u00e9fago",
    "wof:placetype":"venue"
},
  "geometry": {"coordinates":[6.9183092117,46.2293548584],"type":"Point"}
}