{
  "type": "Feature",
  "properties": {
    "addr:full":"Oberdorfstrasse 10 Z\u00fcrich Z\u00fcrich 8001",
    "addr:housenumber":"10",
    "addr:postcode":"8001",
    "addr:street":"Oberdorfstrasse",
    "iso:country":"CH",
    "sg:address":"Oberdorfstrasse 10",
    "sg:city":"Z\u00fcrich",
    "sg:orig_category":"Detailhandel mit Antiquit\u00e4ten U Gebrauchtwaren in Verkaufsr\u00e4umen Detailhandel mit B\u00fcchern",
    "sg:phone":"+41 12611920",
    "sg:postcode":"8001",
    "sg:province":"Z\u00fcrich",
    "wof:name":"Altstadt-antiquariat Rita H. Schnellmann",
    "wof:placetype":"venue"
},
  "geometry": {"coordinates":[8.545778,47.368591],"type":"Point"}
}