{
  "type": "Feature",
  "properties": {
    "iso:country":"CH",
    "sg:address":"Blegistrasse 13",
    "sg:city":"Baar",
    "sg:orig_category":"Unternehmensberatung",
    "sg:postcode":"6340",
    "sg:province":"Zug",
    "wof:name":"Kimo Ag",
    "wof:placetype":"venue"
},
  "geometry": {"coordinates":[9.356180191,47.419593811],"type":"Point"}
}