{
  "type": "Feature",
  "properties": {
    "iso:country":"CH",
    "sg:address":"B\u00fcndtenstrasse 576",
    "sg:city":"Kestenholz",
    "sg:orig_category":"Lagerh\u00e4user, G\u00fcterumschlag, Verteilzentren",
    "sg:postcode":"4703",
    "sg:province":"Solothurn",
    "wof:name":"Keha Kestenholz Ag",
    "wof:placetype":"venue"
},
  "geometry": {"coordinates":[7.7499661446,47.2782974243],"type":"Point"}
}