{
  "type": "Feature",
  "properties": {
    "iso:country":"CH",
    "sg:address":"Grellingerstrasse 68",
    "sg:city":"Basel",
    "sg:orig_category":"Arztpraxen",
    "sg:phone":"+41 61 373 25 35",
    "sg:postcode":"4052",
    "sg:province":"Basel-Stadt",
    "wof:name":"Dr.med. C\u00e9cile Ruoss Spezial\u00e4rztin Fmh",
    "wof:placetype":"venue"
},
  "geometry": {"coordinates":[7.605263,47.548878],"type":"Point"}
}