{
  "type": "Feature",
  "properties": {
    "iso:country":"CH",
    "sg:address":"Schulstrasse 1",
    "sg:city":"Sutz",
    "sg:orig_category":"Herstellung von Metallerzeugnissen ohne Maschinenbau Herstellung von sonstigen Maschinen f\u00fcr unspezi",
    "sg:phone":"+41 61 337 96 96",
    "sg:postcode":"2572",
    "sg:province":"Bern",
    "wof:name":"Holzmag Ag",
    "wof:placetype":"venue"
},
  "geometry": {"coordinates":[7.5549287796,47.5092124939],"type":"Point"}
}