{
  "type": "Feature",
  "properties": {
    "iso:country":"CH",
    "sg:address":"Bahnhofstrasse 10",
    "sg:city":"Zug",
    "sg:orig_category":"Fachdetailhandel mit Nahrungsmitteln, Getr\u00e4nken U Tabakwaren in Verkaufsr\u00e4umen",
    "sg:phone":"+41 41 711 03 89",
    "sg:postcode":"6300",
    "sg:province":"Zug",
    "wof:name":"Spar Supermarkt",
    "wof:placetype":"venue"
},
  "geometry": {"coordinates":[8.5159254074,47.1686897278],"type":"Point"}
}