{
  "type": "Feature",
  "properties": {
    "iso:country":"CH",
    "sg:address":"Place Du Premier-ao\u00fbt 2",
    "sg:city":"Grand-lancy",
    "sg:orig_category":"Haushaltartikel Detailhandel",
    "sg:phone":"+41 32 322 29 78",
    "sg:postcode":"1212",
    "sg:province":"Gen\u00e8ve",
    "wof:name":"Gourmet-ware Graziosi Haushaltartikel",
    "wof:placetype":"venue"
},
  "geometry": {"coordinates":[7.2474341393,47.1398849487],"type":"Point"}
}