{
  "type": "Feature",
  "properties": {
    "iso:country":"CH",
    "sg:address":"Nussbaumacker 2",
    "sg:city":"Erlen",
    "sg:orig_category":"Detailhandel mit Geschenkartikeln U Souvenirs",
    "sg:phone":"+41 71 648 10 83",
    "sg:postcode":"8586",
    "sg:province":"Thurgau",
    "wof:name":"Boutique Heidi Geschenkartikel",
    "wof:placetype":"venue"
},
  "geometry": {"coordinates":[9.2272262573,47.5533485413],"type":"Point"}
}