{
  "type": "Feature",
  "properties": {
    "addr:full":"Laupenstrasse 57 3008 Bern. Postfach 7534 Bern Bern 3001",
    "addr:housenumber":"57",
    "addr:postcode":"3008;postfach 7534 bern;3001",
    "addr:street":"Laupenstrasse",
    "iso:country":"CH",
    "sg:address":"Laupenstrasse 57 3008 Bern. Postfach 7534",
    "sg:city":"Bern",
    "sg:orig_category":"Advokaturb\u00fcros",
    "sg:phone":"+41 31 301 19 82",
    "sg:postcode":"3001",
    "sg:province":"Bern",
    "wof:name":"Dr.alexander Plattner Advokaturb\u00fcro",
    "wof:placetype":"venue"
},
  "geometry": {"coordinates":[7.42887,46.947872],"type":"Point"}
}