{
  "type": "Feature",
  "properties": {
    "addr:full":"Dammweg 12 Lyss Bern 3250",
    "addr:housenumber":"12",
    "addr:postcode":"3250",
    "addr:street":"Dammweg;Bern",
    "iso:country":"CH",
    "sg:address":"Dammweg 12",
    "sg:city":"Lyss",
    "sg:orig_category":"Architektur U Ingenieurb\u00fcros",
    "sg:phone":"+41 32 384 10 52",
    "sg:postcode":"3250",
    "sg:province":"Bern",
    "wof:name":"Ingenieurb\u00fcro Gafner",
    "wof:placetype":"venue"
},
  "geometry": {"coordinates":[7.299355,47.082348],"type":"Point"}
}