{
  "type": "Feature",
  "properties": {
    "iso:country":"CH",
    "sg:address":"Obere Wanne 39 5708 Birrwil. Postfach",
    "sg:city":"Birrwil",
    "sg:orig_category":"Instandhaltung U Reparatur von Automobilen",
    "sg:postcode":"5708",
    "sg:province":"Aargau",
    "wof:name":"Sportgarage Hunziker + Trachsler Gebrauchtwagen; An- U. Verkauf Usw",
    "wof:placetype":"venue"
},
  "geometry": {"coordinates":[8.1961755753,47.2883644104],"type":"Point"}
}