{
  "type": "Feature",
  "properties": {
    "addr:full":"Talacker 50 Z\u00fcrich Z\u00fcrich 8001",
    "addr:housenumber":"50",
    "addr:postcode":"8001",
    "addr:street":"Talacker",
    "iso:country":"CH",
    "sg:address":"Talacker 50",
    "sg:city":"Z\u00fcrich",
    "sg:orig_category":"Detailhandel mit Bekleidung",
    "sg:phone":"+41 12118009",
    "sg:postcode":"8001",
    "sg:province":"Z\u00fcrich",
    "wof:name":"Xentor Holding Ag",
    "wof:placetype":"venue"
},
  "geometry": {"coordinates":[8.534805,47.372532],"type":"Point"}
}