{
  "type": "Feature",
  "properties": {
    "iso:country":"CH",
    "sg:address":"Bernstrasse 20",
    "sg:city":"Boll",
    "sg:orig_category":"Bauspenglerei Zimmerei, Dachdeckerei, Bauspenglerei U Abdichtung",
    "sg:phone":"+41 31 781 10 50",
    "sg:postcode":"3067",
    "sg:province":"Bern",
    "wof:name":"Krebs Karl Kirchdorf Ag",
    "wof:placetype":"venue"
},
  "geometry": {"coordinates":[7.549402,46.820587],"type":"Point"}
}