{
  "type": "Feature",
  "properties": {
    "iso:country":"CH",
    "sg:address":"Baarerstrasse 112 6300 Zug. Postfach",
    "sg:city":"Zug",
    "sg:orig_category":"Unclassifiable Establishments",
    "sg:phone":"+41 41 761 86 22",
    "sg:postcode":"6300",
    "sg:province":"Zug",
    "wof:name":"Chemica Ag",
    "wof:placetype":"venue"
},
  "geometry": {"coordinates":[8.5190229416,47.1802215576],"type":"Point"}
}