{
  "type": "Feature",
  "properties": {
    "iso:country":"CH",
    "sg:address":"Muracherstrasse 11",
    "sg:city":"Gr\u00e4nichen",
    "sg:orig_category":"Office, Building, Fa\u00e7ade, Industry, Hospital Cleaning Services",
    "sg:phone":"+41 62 842 92 30",
    "sg:postcode":"5722",
    "sg:province":"Aargau",
    "wof:name":"Brillant Geb\u00e4udereinigungs-team Blanc & Frei",
    "wof:placetype":"venue"
},
  "geometry": {"coordinates":[8.1044502258,47.3543014526],"type":"Point"}
}