{
  "type": "Feature",
  "properties": {
    "iso:country":"CH",
    "sg:address":"Zone Industrielle En Reutet B",
    "sg:city":"Collombey",
    "sg:orig_category":"Technische, physikalische U chemische Untersuchung",
    "sg:postcode":"1868",
    "sg:province":"Valais",
    "wof:name":"R.a. Romandie Assainissement Sa, Succursale De Collombey",
    "wof:placetype":"venue"
},
  "geometry": {"coordinates":[6.945827961,46.2704734802],"type":"Point"}
}