{
  "type": "Feature",
  "properties": {
    "iso:country":"CH",
    "sg:address":"Klotenerstrasse 14",
    "sg:city":"Bassersdorf",
    "sg:orig_category":"Detailhandel mit Radio U Fernsehger\u00e4ten Herstellung von Radio U Fernsehger\u00e4ten sowie phono U videote",
    "sg:phone":"+41 18364243",
    "sg:postcode":"8303",
    "sg:province":"Z\u00fcrich",
    "wof:name":"Bryner Unterhaltungselektronik",
    "wof:placetype":"venue"
},
  "geometry": {"coordinates":[8.6275119781,47.4439697266],"type":"Point"}
}