{
  "type": "Feature",
  "properties": {
    "iso:country":"CH",
    "sg:address":"Hauptstrasse 15",
    "sg:city":"Lausen",
    "sg:classifiers":[
        {
            "category":"Restaurant",
            "type":"Food & Drink"
        }
    ],
    "sg:phone":"+41 19291152",
    "sg:postcode":"4415",
    "sg:province":"Basel-Landschaft",
    "wof:name":"Restaurant Rosenegg",
    "wof:placetype":"venue"
},
  "geometry": {"coordinates":[8.7217645645,47.269908905],"type":"Point"}
}