{
  "type": "Feature",
  "properties": {
    "iso:country":"CH",
    "sg:address":"Rue C\u00f4tes-de-montbenon 16 1003 Lausanne. Postfach",
    "sg:city":"Lausanne",
    "sg:orig_category":"Architektur U Ingenieurb\u00fcros Architekturb\u00fcros",
    "sg:phone":"+41 21 323 01 12",
    "sg:postcode":"1003",
    "sg:province":"Vaud",
    "wof:name":"Concept Consult Architectes S\u00e0rl",
    "wof:placetype":"venue"
},
  "geometry": {"coordinates":[6.626258,46.521385],"type":"Point"}
}