{
  "type": "Feature",
  "properties": {
    "iso:country":"CH",
    "sg:address":"Kapellboden 546",
    "sg:city":"Jaun",
    "sg:orig_category":"RESTAURANTS: TEA-ROOMS",
    "sg:postcode":"1656",
    "sg:province":"Fribourg",
    "wof:name":"Chez Maxim S\u00e0rl",
    "wof:placetype":"venue"
},
  "geometry": {"coordinates":[7.2856559753,46.6103210449],"type":"Point"}
}