{
  "type": "Feature",
  "properties": {
    "iso:country":"CH",
    "sg:address":"Dorfstrasse 34",
    "sg:city":"Tscheppach",
    "sg:orig_category":"Politische Parteien FDP",
    "sg:postcode":"4576",
    "sg:province":"Solothurn",
    "wof:name":"Fdp Ortspartei Tscheppach",
    "wof:placetype":"venue"
},
  "geometry": {"coordinates":[7.4777989388,47.1461219788],"type":"Point"}
}