{
  "type": "Feature",
  "properties": {
    "iso:country":"CH",
    "sg:address":"Arbonerstr. 34 9322 Egnach. Postfach",
    "sg:city":"Egnach",
    "sg:orig_category":"Fachdetailhandel in Verkaufsr\u00e4umen",
    "sg:phone":"+41 71 477 14 14",
    "sg:postcode":"9322",
    "sg:province":"Thurgau",
    "wof:name":"Blumen Gschwend",
    "wof:placetype":"venue"
},
  "geometry": {"coordinates":[9.382349968,47.5261421204],"type":"Point"}
}