{
  "type": "Feature",
  "properties": {
    "addr:full":"Berntorgasse 3-9 3600 Thun. Postfach Thun 3605",
    "addr:housenumber":"3-9",
    "addr:postcode":"3600 thun. postfach;3605",
    "addr:street":"Berntorgasse",
    "iso:country":"CH",
    "sg:address":"Berntorgasse 3-9 3600 Thun. Postfach",
    "sg:city":"Thun",
    "sg:orig_category":"Grosshandel mit Baumaterialien Grosshandel mit Holz U Baustoffen",
    "sg:phone":"+41 33 227 84 84",
    "sg:postcode":"3605",
    "wof:name":"Bagt Baumaterial Ag Thun",
    "wof:placetype":"venue"
},
  "geometry": {"coordinates":[7.628126,46.760948],"type":"Point"}
}