{
  "type": "Feature",
  "properties": {
    "iso:country":"CH",
    "sg:address":"Rue Du Borgeaud 1b",
    "sg:city":"Gland",
    "sg:orig_category":"Detailhandel mit S\u00e4uglings U Kinderbekleidung",
    "sg:phone":"+41 22 364 04 02",
    "sg:postcode":"1196",
    "sg:province":"Vaud",
    "wof:name":"Big & Small V\u00eatements Pour Enfants",
    "wof:placetype":"venue"
},
  "geometry": {"coordinates":[6.2610821724,46.4228172302],"type":"Point"}
}