{
  "type": "Feature",
  "properties": {
    "iso:country":"CH",
    "sg:address":"Brunnenweid 78",
    "sg:city":"Sins",
    "sg:orig_category":"Wasserversorgung",
    "sg:postcode":"5643",
    "sg:province":"Aargau",
    "wof:name":"Wasserversorgungs-genossenschaft Sins Und Umgebung",
    "wof:placetype":"venue"
},
  "geometry": {"coordinates":[8.386598587,47.2001800537],"type":"Point"}
}