{
  "type": "Feature",
  "properties": {
    "iso:country":"CH",
    "sg:address":"Dorfplatz 1",
    "sg:city":"Giffers",
    "sg:orig_category":"Detailhandel mit Milcherzeugnissen U Eiern Verarbeitung von Milch",
    "sg:phone":"+41 19753060",
    "sg:postcode":"1735",
    "sg:province":"Fribourg",
    "wof:name":"Edgar R\u00fcegg K\u00e4serei",
    "wof:placetype":"venue"
},
  "geometry": {"coordinates":[8.8435297012,47.3023300171],"type":"Point"}
}