{
  "type": "Feature",
  "properties": {
    "iso:country":"CH",
    "sg:address":"Seestrasse 6",
    "sg:city":"Beckenried",
    "sg:orig_category":"Nationale Postdienste",
    "sg:phone":"+41 56 661 13 25",
    "sg:postcode":"6375",
    "sg:province":"Nidwalden",
    "wof:name":"Die Schweizerische Post",
    "wof:placetype":"venue"
},
  "geometry": {"coordinates":[8.3174819946,47.2825775146],"type":"Point"}
}