{
  "type": "Feature",
  "properties": {
    "iso:country":"CH",
    "sg:address":"4228",
    "sg:city":"Erschwil",
    "sg:orig_category":"Detailhandel mit Waren verschiedener Art, Hauptrichtung Nahrungsmittel",
    "sg:phone":"+41 61 781 11 24",
    "sg:postcode":"4228",
    "sg:province":"Solothurn",
    "wof:name":"Epa-superdiscount Konsumgenossenschaft",
    "wof:placetype":"venue"
},
  "geometry": {"coordinates":[7.5419621468,47.3722038269],"type":"Point"}
}