{
  "type": "Feature",
  "properties": {
    "iso:country":"CH",
    "sg:address":"Route Du Jura 12a 1700 Fribourg Case Postale",
    "sg:city":"Fribourg",
    "sg:orig_category":"Detailhandel mit Fahrr\u00e4dern Handel mit Motorr\u00e4dern, Teilen U Zubeh\u00f6r Instandhaltung U Reparatur von ",
    "sg:phone":"+41 26 350 67 80",
    "sg:postcode":"1706",
    "wof:name":"Menoud-bike S\u00e0rl Cycles & Scooters",
    "wof:placetype":"venue"
},
  "geometry": {"coordinates":[7.1479840279,46.8093452454],"type":"Point"}
}