{
  "type": "Feature",
  "properties": {
    "iso:country":"CH",
    "sg:address":"Chemin Des Cerisiers 27 1462 Yvonand. Postfach",
    "sg:city":"Yvonand",
    "sg:orig_category":"Maler U Glasergewerbe",
    "sg:postcode":"1462",
    "sg:province":"Vaud",
    "wof:name":"Manu Peinture, Guerreiro Manuel Entreprise De Peinture",
    "wof:placetype":"venue"
},
  "geometry": {"coordinates":[6.752849102,46.7987251282],"type":"Point"}
}