{
  "type": "Feature",
  "properties": {
    "iso:country":"CH",
    "sg:address":"Pilatusstrasse 7",
    "sg:city":"Aarburg",
    "sg:orig_category":"Nationale Postdienste",
    "sg:phone":"+41 62 791 55 53",
    "sg:postcode":"4663",
    "sg:province":"Aargau",
    "wof:name":"Die Schweizerische Post",
    "wof:placetype":"venue"
},
  "geometry": {"coordinates":[7.9006290436,47.3193778992],"type":"Point"}
}