{
  "type": "Feature",
  "properties": {
    "iso:country":"CH",
    "sg:address":"Rue Centrale 52",
    "sg:city":"Moutier",
    "sg:classifiers":[
        {
            "category":"Travel",
            "subcategory":"Hotels & Motels",
            "type":"Entertainment"
        }
    ],
    "sg:phone":"+41 32 493 10 44",
    "sg:postcode":"2740",
    "sg:province":"Bern",
    "sg:tags":[
        "hotels",
        "mit",
        "restaurant"
    ],
    "wof:name":"H\u00f4tel Du Cheval-blanc",
    "wof:placetype":"venue"
},
  "geometry": {"coordinates":[7.3738408089,47.2797050476],"type":"Point"}
}