{
  "type": "Feature",
  "properties": {
    "iso:country":"CH",
    "sg:address":"Soldati Via 6830 Chiasso. Postfach Casa Postale 0",
    "sg:city":"Chiasso",
    "sg:orig_category":"Vermietung U Verpachtung von eigenen Immobilien",
    "sg:postcode":"6830",
    "sg:province":"Ticino",
    "wof:name":"San Paolo Sa Societ\u00e0 Immobiliare",
    "wof:placetype":"venue"
},
  "geometry": {"coordinates":[9.0326147079,45.8358612061],"type":"Point"}
}