{
  "type": "Feature",
  "properties": {
    "iso:country":"CH",
    "sg:address":"Mittelg\u00e4ustrasse 58",
    "sg:city":"Gunzgen",
    "sg:orig_category":"Detailhandel mit Fahrr\u00e4dern Handel mit Motorr\u00e4dern, Teilen U Zubeh\u00f6r Instandhaltung U Reparatur von ",
    "sg:phone":"+41 62 216 41 74",
    "sg:postcode":"4617",
    "sg:province":"Solothurn",
    "wof:name":"Leba Gmbh Treuhandaufgaben U. Beratungen Bes. Im Immobilienbereich U. Gesellschaftsrecht Usw",
    "wof:placetype":"venue"
},
  "geometry": {"coordinates":[7.8271069527,47.3151741028],"type":"Point"}
}