{
  "type": "Feature",
  "properties": {
    "iso:country":"CH",
    "sg:address":"Wilerstrasse 65a 9602 Bazenheid. Postfach",
    "sg:city":"Bazenheid",
    "sg:orig_category":"Reiseb\u00fcros U Reiseveranstalter",
    "sg:phone":"+41 22 798 16 34",
    "sg:postcode":"9602",
    "sg:province":"St. Gallen",
    "wof:name":"Happy Tours Roesner Simone",
    "wof:placetype":"venue"
},
  "geometry": {"coordinates":[6.1194968224,46.229801178],"type":"Point"}
}