{
  "type": "Feature",
  "properties": {
    "iso:country":"CH",
    "sg:address":"Marktgasse 8",
    "sg:city":"Gelterkinden",
    "sg:orig_category":"Gemeindeverwaltungen",
    "sg:phone":"+41 61 985 22 22",
    "sg:postcode":"4460",
    "sg:province":"Basel-Landschaft",
    "wof:name":"Gemeindeverwaltung Gelterkinden",
    "wof:placetype":"venue"
},
  "geometry": {"coordinates":[7.8566470146,47.4640884399],"type":"Point"}
}