{
  "type": "Feature",
  "properties": {
    "iso:country":"CH",
    "sg:address":"7504",
    "sg:city":"Pontresina",
    "sg:orig_category":"Wirtschafts- and Arbeitgeberverb\u00e4nde",
    "sg:postcode":"7504",
    "sg:province":"Graubunden",
    "wof:name":"Hotelierverein Pontresina",
    "wof:placetype":"venue"
},
  "geometry": {"coordinates":[9.9019098282,46.4935150146],"type":"Point"}
}