{
  "type": "Feature",
  "properties": {
    "iso:country":"CH",
    "sg:address":"Rue Du Mont-de-sion 12",
    "sg:city":"Gen\u00e8ve",
    "sg:orig_category":"Advokaturb\u00fcros",
    "sg:phone":"+41 22 347 55 11",
    "sg:postcode":"1206",
    "sg:province":"Gen\u00e8ve",
    "wof:name":"Roland Steiner Etude D'avocat",
    "wof:placetype":"venue"
},
  "geometry": {"coordinates":[6.153932,46.19759],"type":"Point"}
}