{
  "type": "Feature",
  "properties": {
    "iso:country":"CH",
    "sg:address":"Hauptstrasse 127 8574 Lengwil-oberhofen. Postfach",
    "sg:city":"Lengwil-oberhofen",
    "sg:orig_category":"Herstellung von Werkzeugmaschinen",
    "sg:postcode":"8574",
    "sg:province":"Thurgau",
    "wof:name":"Leimer-marti",
    "wof:placetype":"venue"
},
  "geometry": {"coordinates":[9.2098503113,47.6019096375],"type":"Point"}
}