{
  "type": "Feature",
  "properties": {
    "iso:country":"CH",
    "sg:address":"Morgenstrasse 19",
    "sg:city":"Thundorf",
    "sg:orig_category":"Detailhandel mit elektrischen Haushalts-,Radio U Fernsehger\u00e4ten sowie Musikinstrumenten Handelsvermi",
    "sg:phone":"+41 52 376 33 34",
    "sg:postcode":"8512",
    "sg:province":"Thurgau",
    "wof:name":"Aresa Ag",
    "wof:placetype":"venue"
},
  "geometry": {"coordinates":[8.9640550613,47.5487136841],"type":"Point"}
}