{
  "type": "Feature",
  "properties": {
    "iso:country":"CH",
    "sg:address":"Balma C 31",
    "sg:city":"Vals",
    "sg:orig_category":"Webereien, Webwaren",
    "sg:postcode":"7132",
    "sg:province":"Graubunden",
    "wof:name":"Atelier Zameia, Ursula & Alfons J\u00f6rger",
    "wof:placetype":"venue"
},
  "geometry": {"coordinates":[9.1783981323,46.612903595],"type":"Point"}
}