{
  "type": "Feature",
  "properties": {
    "iso:country":"CH",
    "sg:address":"Giblenstrasse 57",
    "sg:city":"Z\u00fcrich",
    "sg:orig_category":"Unclassifiable Establishments",
    "sg:postcode":"8049",
    "sg:province":"Z\u00fcrich",
    "wof:name":"Amat Gmbh",
    "wof:placetype":"venue"
},
  "geometry": {"coordinates":[8.4804611206,47.4123039246],"type":"Point"}
}