{
  "type": "Feature",
  "properties": {
    "iso:country":"CH",
    "sg:address":"Vieux-grenadiers Rue Des 17 1205 Gen\u00e8ve. Postfach",
    "sg:city":"Gen\u00e8ve",
    "sg:classifiers":[
        {
            "category":"Travel",
            "subcategory":"Hotels & Motels",
            "type":"Entertainment"
        }
    ],
    "sg:postcode":"1205",
    "sg:province":"Gen\u00e8ve",
    "sg:tags":[
        "hotels",
        "mit",
        "restaurant"
    ],
    "wof:name":"Jean-robert Guex",
    "wof:placetype":"venue"
},
  "geometry": {"coordinates":[7.6789898872,46.773109436],"type":"Point"}
}