{
  "type": "Feature",
  "properties": {
    "iso:country":"CH",
    "sg:address":"Eichhofweg 5 6318 Walchwil. Postfach 140",
    "sg:city":"Walchwil",
    "sg:orig_category":"Architektur U Ingenieurb\u00fcros",
    "sg:phone":"+41 41 758 17 13",
    "sg:postcode":"6318",
    "sg:province":"Zug",
    "wof:name":"Portmann August Ag",
    "wof:placetype":"venue"
},
  "geometry": {"coordinates":[8.513723,47.101032],"type":"Point"}
}