{
  "type": "Feature",
  "properties": {
    "iso:country":"CH",
    "sg:address":"Niederwil",
    "sg:city":"Cham",
    "sg:orig_category":"Verwertung von Milch",
    "sg:postcode":"6330",
    "sg:province":"Zug",
    "wof:name":"Milchgenossenschaft Niederwil-cham",
    "wof:placetype":"venue"
},
  "geometry": {"coordinates":[8.4490251541,47.2128868103],"type":"Point"}
}