{
  "type": "Feature",
  "properties": {
    "addr:full":"Le Glaney 31 Romont Fribourg 1680",
    "addr:housenumber":"31",
    "addr:postcode":"1680",
    "addr:street":"Romont Fribourg",
    "iso:country":"CH",
    "sg:address":"Le Glaney 31",
    "sg:city":"Romont",
    "sg:classifiers":[
        {
            "category":"Building & Trades",
            "subcategory":"Construction",
            "type":"Services"
        }
    ],
    "sg:phone":"+41 26 652 38 75",
    "sg:postcode":"1680",
    "sg:province":"Fribourg",
    "sg:tags":[
        "central",
        "heating",
        "system"
    ],
    "wof:name":"Oliveira & Suard S\u00e0rl",
    "wof:placetype":"venue"
},
  "geometry": {"coordinates":[6.924316,46.703251],"type":"Point"}
}