{
  "type": "Feature",
  "properties": {
    "iso:country":"CH",
    "sg:address":"Gerbergasse 26 4001 Basel. Postfach",
    "sg:city":"Basel",
    "sg:orig_category":"Arbeitnehmerverb\u00e4nde",
    "sg:phone":"+41 61 261 45 45",
    "sg:postcode":"4001",
    "sg:province":"Basel-Stadt",
    "wof:name":"Bankpersonal-verband Basel Pr\u00e4s.herrn Hans Furer",
    "wof:placetype":"venue"
},
  "geometry": {"coordinates":[7.588206,47.556831],"type":"Point"}
}