{
  "type": "Feature",
  "properties": {
    "iso:country":"CH",
    "sg:address":"Waldeggstrasse 16",
    "sg:city":"Horgen",
    "sg:orig_category":"Herstellung von Gummi U Kunststoffwaren",
    "sg:phone":"+41 14635460",
    "sg:postcode":"8810",
    "sg:province":"Z\u00fcrich",
    "wof:name":"Polyvite Ag",
    "wof:placetype":"venue"
},
  "geometry": {"coordinates":[8.6044836044,47.245677948],"type":"Point"}
}