{
  "type": "Feature",
  "properties": {
    "iso:country":"CH",
    "sg:address":"Rohrstrasse 2 3507 Biglen. Postfach",
    "sg:city":"Biglen",
    "sg:orig_category":"Herstellung von Maschinen f\u00fcr die Textil, Bekleidungsherstellung U die Lederverarbeitung Textilgewer",
    "sg:phone":"+41 55 221 71 11",
    "sg:postcode":"3507",
    "sg:province":"Bern",
    "wof:name":"Graf & Cie Ag",
    "wof:placetype":"venue"
},
  "geometry": {"coordinates":[8.8269090652,47.2294845581],"type":"Point"}
}