{
  "type": "Feature",
  "properties": {
    "iso:country":"CH",
    "sg:address":"La Roujarde 1303 Penthaz. Postfach",
    "sg:city":"Penthaz",
    "sg:orig_category":"Elektroinstallation",
    "sg:postcode":"1303",
    "sg:province":"Vaud",
    "wof:name":"Bureau Technique D'\u00e9lectricit\u00e9, Burkhard H. Bureau D'ing\u00e9nieur-conseil. Etudes Et Projets En Installations \u00e9lectriques Et T\u00e9l\u00e9communications",
    "wof:placetype":"venue"
},
  "geometry": {"coordinates":[6.5384898186,46.5996818542],"type":"Point"}
}