{
  "type": "Feature",
  "properties": {
    "iso:country":"CH",
    "sg:address":"Avenue Du Casino 51",
    "sg:city":"Montreux",
    "sg:orig_category":"Grosshandel mit Parf\u00fcmerieartikeln U K\u00f6rperpflegemitteln Parf\u00fcmerien U sonstiger Detailhandel mit ko",
    "sg:phone":"+41 21 965 13 20",
    "sg:postcode":"1820",
    "sg:province":"Vaud",
    "wof:name":"Alrodo Ag Parfum-& Kosmetikhandel",
    "wof:placetype":"venue"
},
  "geometry": {"coordinates":[6.9107961655,46.430770874],"type":"Point"}
}