{
  "type": "Feature",
  "properties": {
    "iso:country":"CH",
    "sg:address":"Chemin Mont-de-faux",
    "sg:city":"Villars-ste-croix",
    "sg:orig_category":"Herstellung von Metallkonstruktionen Mechanik",
    "sg:phone":"+41 21 634 68 30",
    "sg:postcode":"1029",
    "sg:province":"Vaud",
    "wof:name":"Constructions M\u00e9talliques Mg, Mangione",
    "wof:placetype":"venue"
},
  "geometry": {"coordinates":[6.5820469856,46.534122467],"type":"Point"}
}