{
  "type": "Feature",
  "properties": {
    "iso:country":"CH",
    "sg:address":"Avenue De Thienne 7",
    "sg:city":"Orbe",
    "sg:orig_category":"Detailhandel mit Brot, Back U S\u00fcsswaren Detailhandel mit Waren verschiedener Art, Hauptrichtung Nahr",
    "sg:phone":"+41 24 441 32 46",
    "sg:postcode":"1350",
    "sg:province":"Vaud",
    "wof:name":"Jules Mottaz Boulangerie & P\u00e2tisserie",
    "wof:placetype":"venue"
},
  "geometry": {"coordinates":[6.531983,46.729553],"type":"Point"}
}