{
  "type": "Feature",
  "properties": {
    "iso:country":"CH",
    "sg:address":"Bahnhofstrasse 43a 6048 Horw. Postfach",
    "sg:city":"Horw",
    "sg:orig_category":"Herstellung von Werkzeugen Mechanische Werkst\u00e4tten",
    "sg:phone":"+41 41 340 22 64",
    "sg:postcode":"6048",
    "sg:province":"Luzern",
    "wof:name":"Schmid Mechanik Gmbh Garten, Forst, Hydraulikger\u00e4te, Deichselstapler; Verkauf, Reparatur",
    "wof:placetype":"venue"
},
  "geometry": {"coordinates":[8.3069839478,47.0178108215],"type":"Point"}
}