{
  "type": "Feature",
  "properties": {
    "iso:country":"CH",
    "sg:address":"Belalpstrasse 20",
    "sg:city":"Naters",
    "sg:orig_category":"RESTAURANTS: TEA-ROOMS",
    "sg:phone":"+41 27 923 79 35",
    "sg:postcode":"3904",
    "sg:province":"Valais",
    "wof:name":"Restaurant Caf\u00e9 Naters, Salzmann Richard",
    "wof:placetype":"venue"
},
  "geometry": {"coordinates":[7.9891400337,46.3252944946],"type":"Point"}
}