{
  "type": "Feature",
  "properties": {
    "iso:country":"CH",
    "sg:address":"Besmerstrasse 32a",
    "sg:city":"Kreuzlingen",
    "sg:orig_category":"Non-Classified Establishments",
    "sg:postcode":"8280",
    "sg:province":"Thurgau",
    "wof:name":"Dis Computer Systems Marin",
    "wof:placetype":"venue"
},
  "geometry": {"coordinates":[9.1878013611,47.6400871277],"type":"Point"}
}