{
  "type": "Feature",
  "properties": {
    "iso:country":"CH",
    "sg:address":"Scheibenstrasse 3",
    "sg:city":"Thun",
    "sg:orig_category":"Satzherstellung U Reproduktion",
    "sg:phone":"+41 33 221 51 00",
    "sg:postcode":"3600",
    "sg:province":"Bern",
    "wof:name":"Repro Stucki",
    "wof:placetype":"venue"
},
  "geometry": {"coordinates":[7.6251001358,46.7600402832],"type":"Point"}
}