{
  "type": "Feature",
  "properties": {
    "iso:country":"CH",
    "sg:address":"Gossauer Strasse 59",
    "sg:city":"Herisau",
    "sg:orig_category":"Sonstige Kultur U Unterhaltungseinrichtungen",
    "sg:phone":"+41 71 351 30 96",
    "sg:postcode":"9100",
    "sg:province":"Appenzell Ausserrhoden",
    "wof:name":"Jugendhaus Lindenhof-zentrum Verein F\u00fcr Freizeitgestaltung",
    "wof:placetype":"venue"
},
  "geometry": {"coordinates":[9.2747993469,47.3882102966],"type":"Point"}
}