{
  "type": "Feature",
  "properties": {
    "iso:country":"CH",
    "sg:address":"Schlossstrasse 211 9435 Heerbrugg. Postfach 44",
    "sg:city":"Balgach",
    "sg:orig_category":"Public-Relations-Agenturen",
    "sg:phone":"+41 71 726 10 40",
    "sg:postcode":"9436",
    "sg:province":"St. Gallen",
    "wof:name":"Reinhard Frei & Partner Beziehungsmanagement",
    "wof:placetype":"venue"
},
  "geometry": {"coordinates":[9.622179985,47.4102973938],"type":"Point"}
}