{
  "type": "Feature",
  "properties": {
    "iso:country":"CH",
    "sg:address":"Schulriederstrasse 13",
    "sg:city":"Dotzigen",
    "sg:orig_category":"Fachdetailhandel in Verkaufsr\u00e4umen Grosshandel mit Blumen U Pflanzen",
    "sg:phone":"+41 32 351 36 32",
    "sg:postcode":"3293",
    "sg:province":"Bern",
    "wof:name":"Intertransflor Ag",
    "wof:placetype":"venue"
},
  "geometry": {"coordinates":[7.3335800171,47.1172332764],"type":"Point"}
}