{
  "type": "Feature",
  "properties": {
    "iso:country":"CH",
    "sg:address":"Birkenstrasse 9",
    "sg:city":"Wuppenau",
    "sg:orig_category":"Vermietung U Verpachtung von eigenen Immobilien",
    "sg:phone":"+41 71 940 04 80",
    "sg:postcode":"9514",
    "sg:province":"Thurgau",
    "wof:name":"Thoma Immobilien",
    "wof:placetype":"venue"
},
  "geometry": {"coordinates":[9.108751297,47.4946403503],"type":"Point"}
}