{
  "type": "Feature",
  "properties": {
    "iso:country":"CH",
    "sg:address":"Faubourg Du Lac 67",
    "sg:city":"Biel/bienne",
    "sg:classifiers":[
        {
            "category":"Sports & Exercise",
            "subcategory":"Tennis Court",
            "type":"Entertainment"
        }
    ],
    "sg:phone":"+41 32 322 38 23",
    "sg:postcode":"2502",
    "sg:province":"Bern",
    "sg:tags":[
        "underwater",
        "equipment"
    ],
    "wof:name":"Dan Europe Suisse",
    "wof:placetype":"venue"
},
  "geometry": {"coordinates":[7.2393188477,47.1381187439],"type":"Point"}
}