{
  "type": "Feature",
  "properties": {
    "iso:country":"CH",
    "sg:address":"Langenhagstr. 13",
    "sg:city":"Rheineck",
    "sg:classifiers":[
        {
            "category":"Wholesale",
            "subcategory":"Machinery & Supplies",
            "type":"Manufacturing & Wholesale Goods"
        }
    ],
    "sg:phone":"+41 71 888 08 44",
    "sg:postcode":"9424",
    "sg:province":"St. Gallen",
    "sg:tags":[
        "handling",
        "material",
        "-",
        "machine",
        "equipment",
        "engineering",
        "mechanical"
    ],
    "wof:name":"Peko Rollen P K\u00d6ppel Ag",
    "wof:placetype":"venue"
},
  "geometry": {"coordinates":[9.5870876312,47.4716300964],"type":"Point"}
}