{
  "type": "Feature",
  "properties": {
    "iso:country":"CH",
    "sg:address":"Erlibergstrasse 9",
    "sg:city":"Unter\u00e4geri",
    "sg:orig_category":"Elektroinstallation",
    "sg:phone":"+41 79 250 57 72",
    "sg:postcode":"6314",
    "sg:province":"Zug",
    "wof:name":"Auberson \u00e9lectricit\u00e9 S\u00e0rl",
    "wof:placetype":"venue"
},
  "geometry": {"coordinates":[6.6127300262,46.5202331543],"type":"Point"}
}