{
  "type": "Feature",
  "properties": {
    "addr:full":"Pierre Rue Saint- 3 Freiburg Fribourg 1700",
    "addr:housenumber":"3",
    "addr:postcode":"1700",
    "addr:street":"Rue Saint",
    "iso:country":"CH",
    "sg:address":"Pierre Rue Saint- 3",
    "sg:city":"Freiburg",
    "sg:orig_category":"Architektur U Ingenieurb\u00fcros",
    "sg:postcode":"1700",
    "sg:province":"Fribourg",
    "wof:name":"Bbit Resourcing Sa",
    "wof:placetype":"venue"
},
  "geometry": {"coordinates":[7.154645,46.803822],"type":"Point"}
}