{
  "type": "Feature",
  "properties": {
    "iso:country":"CH",
    "sg:address":"Rue Haldimand 5",
    "sg:city":"Lausanne",
    "sg:orig_category":"Erwachsenenbildung U Unterricht Sprachschulen",
    "sg:phone":"+41 21 320 31 38",
    "sg:postcode":"1003",
    "sg:province":"Vaud",
    "wof:name":"Interlangues Janin Sa",
    "wof:placetype":"venue"
},
  "geometry": {"coordinates":[6.6315698624,46.5226020813],"type":"Point"}
}