{
  "type": "Feature",
  "properties": {
    "iso:country":"CH",
    "sg:address":"Gestadeckplatz 2",
    "sg:city":"Liestal",
    "sg:orig_category":"Herstellung von medizinischen U chirurgischen Ger\u00e4ten sowie orthop\u00e4dischen Vorrichtungen",
    "sg:postcode":"4410",
    "sg:province":"Basel-Landschaft",
    "wof:name":"Nicole P.",
    "wof:placetype":"venue"
},
  "geometry": {"coordinates":[6.8552641869,46.4550933838],"type":"Point"}
}