{
  "type": "Feature",
  "properties": {
    "iso:country":"CH",
    "sg:address":"Mutschellenstrasse 33",
    "sg:city":"Z\u00fcrich",
    "sg:orig_category":"Fotografische Ateliers",
    "sg:phone":"+41 12024541",
    "sg:postcode":"8002",
    "sg:province":"Z\u00fcrich",
    "wof:name":"Martin Beyeler Fotografisches Atelier",
    "wof:placetype":"venue"
},
  "geometry": {"coordinates":[8.5273809433,47.3526916504],"type":"Point"}
}