{
  "type": "Feature",
  "properties": {
    "iso:country":"CH",
    "sg:address":"Steigstrasse 51",
    "sg:city":"Schaffhausen",
    "sg:orig_category":"Architektur U Ingenieurb\u00fcros Architekturb\u00fcros",
    "sg:phone":"+41 52 630 07 90",
    "sg:postcode":"8200",
    "sg:province":"Schaffhausen",
    "wof:name":"Bergamini Manuel Dipl. Arch. Eth/sia",
    "wof:placetype":"venue"
},
  "geometry": {"coordinates":[8.628525,47.696129],"type":"Point"}
}