{
  "type": "Feature",
  "properties": {
    "iso:country":"CH",
    "sg:address":"Chemin Nicolas-bogueret 8",
    "sg:city":"A\u00efre",
    "sg:orig_category":"Herstellung von k\u00e4lte U lufttechnischen Erzeugnissen f\u00fcr gewerbliche Zwecke Sanit\u00e4r U Heizungsinstal",
    "sg:phone":"+41 22 795 75 50",
    "sg:postcode":"1219",
    "sg:province":"Gen\u00e8ve",
    "wof:name":"Scrignari G. Et Pavan G.",
    "wof:placetype":"venue"
},
  "geometry": {"coordinates":[6.0991921425,46.2007408142],"type":"Point"}
}