{
  "type": "Feature",
  "properties": {
    "iso:country":"CH",
    "sg:address":"Sch\u00f6neggstrasse 21",
    "sg:city":"Z\u00fcrich",
    "sg:orig_category":"Grosshandel mit Nahrungsmitteln, Getr\u00e4nken U Tabakwaren ohne ausgepr\u00e4gten Schwerpunkt",
    "sg:postcode":"8004",
    "sg:province":"Z\u00fcrich",
    "wof:name":"V. Zucchetto",
    "wof:placetype":"venue"
},
  "geometry": {"coordinates":[8.5263824463,47.3802070618],"type":"Point"}
}