{
  "type": "Feature",
  "properties": {
    "iso:country":"CH",
    "sg:address":"Rue Du Rh\u00f4ne 46",
    "sg:city":"Gen\u00e8ve",
    "sg:orig_category":"Detailhandel mit Uhren U Schmuck Grosshandel mit Erzen U Metallen",
    "sg:phone":"+41 55 210 44 35",
    "sg:postcode":"1204",
    "sg:province":"Gen\u00e8ve",
    "wof:name":"Domeisen Goldschmiede Ag",
    "wof:placetype":"venue"
},
  "geometry": {"coordinates":[8.8174419403,47.2265968323],"type":"Point"}
}