{
  "type": "Feature",
  "properties": {
    "iso:country":"CH",
    "sg:address":"Fabrikstrasse 3 5444 K\u00fcnten. Postfach",
    "sg:city":"K\u00fcnten",
    "sg:orig_category":"Herstellung von Metallkonstruktionen Maschinenbau",
    "sg:phone":"+41 41 660 26 10",
    "sg:postcode":"5444",
    "sg:province":"Aargau",
    "wof:name":"Mta Montage Technik Gmbh",
    "wof:placetype":"venue"
},
  "geometry": {"coordinates":[8.2109136581,46.8875312805],"type":"Point"}
}