{
  "type": "Feature",
  "properties": {
    "iso:country":"CH",
    "sg:address":"Auf Der Schanz 70",
    "sg:city":"Kaiseraugst",
    "sg:orig_category":"Versicherungsagenturen and -broker -Vermittlung von Immobilien",
    "sg:phone":"+41 61 811 48 08",
    "sg:postcode":"4303",
    "sg:province":"Aargau",
    "wof:name":"Alfred Steingruber Versicherungen",
    "wof:placetype":"venue"
},
  "geometry": {"coordinates":[7.7277679443,47.5372161865],"type":"Point"}
}