{
  "type": "Feature",
  "properties": {
    "iso:country":"CH",
    "sg:address":"Kehrgasse 5 3018 Bern. Postfach",
    "sg:city":"Bern",
    "sg:orig_category":"Grosshandel mit Milch, Milcherzeugnissen, Eiern, Speise\u00f6len U Nahrungsfetten",
    "sg:postcode":"3018",
    "sg:province":"Bern",
    "wof:name":"Albert Guggisberg Eier, Kartoffeln U. Zwiebeln; Handel.",
    "wof:placetype":"venue"
},
  "geometry": {"coordinates":[7.400976181,46.9460449219],"type":"Point"}
}