{
  "type": "Feature",
  "properties": {
    "iso:country":"CH",
    "sg:address":"Zeitglockenlaube 2",
    "sg:city":"Bern",
    "sg:orig_category":"Bau U Wohngenossenschaften",
    "sg:postcode":"3011",
    "sg:province":"Bern",
    "wof:name":"Zweite Wohnbaug.oberhofstetten",
    "wof:placetype":"venue"
},
  "geometry": {"coordinates":[9.31697,47.428329],"type":"Point"}
}