{
  "type": "Feature",
  "properties": {
    "iso:country":"CH",
    "sg:address":"Hardeggweg",
    "sg:city":"Steffisburg",
    "sg:orig_category":"Wasserversorgung",
    "sg:postcode":"3612",
    "sg:province":"Bern",
    "wof:name":"Brunnengenossenschaft Im Unterdorf Zu Steffisburg",
    "wof:placetype":"venue"
},
  "geometry": {"coordinates":[7.6140999794,46.7803993225],"type":"Point"}
}