{
  "type": "Feature",
  "properties": {
    "iso:country":"CH",
    "sg:address":"Thiersteinerrain 132 4059 Basel. Postfach",
    "sg:city":"Basel",
    "sg:orig_category":"Interessenvertretungen",
    "sg:postcode":"4051",
    "sg:province":"Basel-Stadt",
    "wof:name":"Stiftung F\u00fcr Allergie-forschung In Europa",
    "wof:placetype":"venue"
},
  "geometry": {"coordinates":[7.5948767662,47.5356559753],"type":"Point"}
}