{
  "type": "Feature",
  "properties": {
    "iso:country":"CH",
    "sg:address":"Hauptstrasse 1",
    "sg:city":"Arbon",
    "sg:orig_category":"Datenverarbeitungsdienste Fernmeldedienste",
    "sg:phone":"+41 71 440 11 11",
    "sg:postcode":"9320",
    "sg:province":"Thurgau",
    "wof:name":"Netsource Internet Services Gmbh",
    "wof:placetype":"venue"
},
  "geometry": {"coordinates":[9.436204,47.51556],"type":"Point"}
}