{
  "type": "Feature",
  "properties": {
    "iso:country":"CH",
    "sg:address":"Lenggiserstrasse 6",
    "sg:city":"Jona",
    "sg:orig_category":"Hoch U Tiefbau",
    "sg:phone":"+41 55 211 06 17",
    "sg:postcode":"8645",
    "sg:province":"St. Gallen",
    "wof:name":"Gebr. Rocca Gmbh Bauunternehmung",
    "wof:placetype":"venue"
},
  "geometry": {"coordinates":[8.8239583969,47.2395896912],"type":"Point"}
}