{
  "type": "Feature",
  "properties": {
    "iso:country":"CH",
    "sg:address":"Obergass 35",
    "sg:city":"Eglisau",
    "sg:orig_category":"Detailhandel mit Brot, Back U S\u00fcsswaren",
    "sg:phone":"+41 18671700",
    "sg:postcode":"8193",
    "sg:province":"Z\u00fcrich",
    "wof:name":"Markus Schneider B\u00e4ckerei-konditorei",
    "wof:placetype":"venue"
},
  "geometry": {"coordinates":[8.524862,47.57589],"type":"Point"}
}