{
  "type": "Feature",
  "properties": {
    "iso:country":"CH",
    "sg:address":"Heideweg 19",
    "sg:city":"Biel/bienne",
    "sg:orig_category":"Psychotherapie",
    "sg:postcode":"2503",
    "sg:province":"Bern",
    "wof:name":"Paul Debelle Psychotherapie",
    "wof:placetype":"venue"
},
  "geometry": {"coordinates":[7.2548251152,47.1265792847],"type":"Point"}
}