{
  "type": "Feature",
  "properties": {
    "iso:country":"CH",
    "sg:address":"Pont Du Rh\u00f4ne 1950 Sion Case Postale 4187",
    "sg:city":"Sion",
    "sg:orig_category":"Unclassifiable Establishments",
    "sg:phone":"+41 27 203 81 21",
    "sg:postcode":"1950",
    "sg:province":"Valais",
    "wof:name":"Lietti Ferd. Sa, Mat\u00e9riaux De Construction.",
    "wof:placetype":"venue"
},
  "geometry": {"coordinates":[7.3683099747,46.2257843018],"type":"Point"}
}