{
  "type": "Feature",
  "properties": {
    "iso:country":"CH",
    "sg:address":"Gerbergasse 42",
    "sg:city":"Basel",
    "sg:orig_category":"Parf\u00fcmerien U sonstiger Detailhandel mit kosmetischen Artikeln U K\u00f6rperpflegemitteln",
    "sg:phone":"+41 61 263 38 00",
    "sg:postcode":"4001",
    "sg:province":"Basel-Stadt",
    "wof:name":"The Body Shop Levy Ag",
    "wof:placetype":"venue"
},
  "geometry": {"coordinates":[7.5884599686,47.5561523438],"type":"Point"}
}