{
  "type": "Feature",
  "properties": {
    "iso:country":"CH",
    "sg:address":"Hauptstrasse 4",
    "sg:city":"Biberist",
    "sg:orig_category":"Detailhandel mit B\u00fcromaschinen U einrichtungen",
    "sg:phone":"+41 32 623 15 89",
    "sg:postcode":"4562",
    "sg:province":"Solothurn",
    "wof:name":"Felix Lehmann B\u00fcro-organisation",
    "wof:placetype":"venue"
},
  "geometry": {"coordinates":[7.558319,47.181736],"type":"Point"}
}