{
  "type": "Feature",
  "properties": {
    "iso:country":"CH",
    "sg:address":"Vorderberg 11 8044 Z\u00fcrich. Postfach",
    "sg:city":"Z\u00fcrich",
    "sg:orig_category":"Patentanwaltsb\u00fcros, Patentverwertung",
    "sg:phone":"+41 55 266 20 30",
    "sg:postcode":"8044",
    "sg:province":"Z\u00fcrich",
    "wof:name":"Dr. Reinhold C. Salg\u00f2 Patentanwaltsb\u00fcro",
    "wof:placetype":"venue"
},
  "geometry": {"coordinates":[8.9413003922,47.2884101868],"type":"Point"}
}