{
  "type": "Feature",
  "properties": {
    "iso:country":"CH",
    "sg:address":"Schaffhauserstrasse 119",
    "sg:city":"Kloten",
    "sg:orig_category":"Unternehmensberatung",
    "sg:phone":"+41 18141913",
    "sg:postcode":"8302",
    "sg:province":"Z\u00fcrich",
    "wof:name":"Transfer-centrum F\u00fcr Produktions-logistik Und Technologie-management Ag",
    "wof:placetype":"venue"
},
  "geometry": {"coordinates":[8.5809078217,47.4503860474],"type":"Point"}
}