{
  "type": "Feature",
  "properties": {
    "iso:country":"CH",
    "sg:address":"8627",
    "sg:city":"Gr\u00fcningen",
    "sg:orig_category":"Bezirks, Sekundar, Realschulen, Oberstufe der Primarschulen",
    "sg:phone":"+41 81 738 14 10",
    "sg:postcode":"8627",
    "sg:province":"Z\u00fcrich",
    "wof:name":"Oberstufenschule",
    "wof:placetype":"venue"
},
  "geometry": {"coordinates":[8.763625,47.28437],"type":"Point"}
}