{
  "type": "Feature",
  "properties": {
    "iso:country":"CH",
    "sg:address":"Seewadelstrasse 14",
    "sg:city":"Volketswil",
    "sg:orig_category":"Vorschulen, Kinderg\u00e4rten",
    "sg:phone":"+41 34 411 23 63",
    "sg:postcode":"8604",
    "sg:province":"Z\u00fcrich",
    "wof:name":"Kindergarten Walliswil Bei Niederbipp",
    "wof:placetype":"venue"
},
  "geometry": {"coordinates":[7.6727690697,47.2290077209],"type":"Point"}
}