{
  "type": "Feature",
  "properties": {
    "addr:full":"Erspachstrasse 26 Mettmenstetten Z\u00fcrich 8932",
    "addr:housenumber":"26",
    "addr:postcode":"8932",
    "addr:street":"Erspachstrasse",
    "iso:country":"CH",
    "sg:address":"Erspachstrasse 26",
    "sg:city":"Mettmenstetten",
    "sg:classifiers":[
        {
            "category":"Home & Garden",
            "subcategory":"Building Materials",
            "type":"Retail Goods"
        }
    ],
    "sg:phone":"+41 41 850 72 75",
    "sg:postcode":"8932",
    "sg:province":"Z\u00fcrich",
    "sg:tags":[
        "cutting",
        "laser",
        "cnc"
    ],
    "wof:name":"Acquacut Ag",
    "wof:placetype":"venue"
},
  "geometry": {"coordinates":[8.441568,47.081211],"type":"Point"}
}