{
  "type": "Feature",
  "properties": {
    "iso:country":"CH",
    "sg:address":"7415",
    "sg:city":"Pratval",
    "sg:orig_category":"Mechanik",
    "sg:postcode":"7415",
    "sg:province":"Graubunden",
    "wof:name":"Moeckli Jean-luc",
    "wof:placetype":"venue"
},
  "geometry": {"coordinates":[7.0927248001,47.0635795593],"type":"Point"}
}