{
  "type": "Feature",
  "properties": {
    "iso:country":"CH",
    "sg:address":"Via Agostino Maspoli 1",
    "sg:city":"Mendrisio",
    "sg:orig_category":"Fernmeldedienste Unternehmensberatung",
    "sg:phone":"+41 56 619 70 20",
    "sg:postcode":"6850",
    "sg:province":"Ticino",
    "wof:name":"Projekt Support Ludwig Gmbh",
    "wof:placetype":"venue"
},
  "geometry": {"coordinates":[8.2790689468,47.3545379639],"type":"Point"}
}