{
  "type": "Feature",
  "properties": {
    "iso:country":"CH",
    "sg:address":"4 Quai Gal Guisan",
    "sg:city":"Gen\u00e8ve",
    "sg:classifiers":[
        {
            "category":"Banks & Credit Unions",
            "subcategory":"Financial Services",
            "type":"Services"
        }
    ],
    "sg:phone":"+41 22 319 91 91",
    "sg:postcode":"1204",
    "sg:province":"Gen\u00e8ve",
    "sg:tags":[
        "banking",
        "insurance",
        "institution",
        "finance"
    ],
    "wof:name":"Credit Agricole Indosuez Sa",
    "wof:placetype":"venue"
},
  "geometry": {"coordinates":[6.147048,46.204487],"type":"Point"}
}