{
  "type": "Feature",
  "properties": {
    "iso:country":"CH",
    "sg:address":"Grand-rue 46",
    "sg:city":"Montreux",
    "sg:orig_category":"Vermietung U Verpachtung von eigenen Immobilien",
    "sg:phone":"+41 61 703 90 35",
    "sg:postcode":"1820",
    "sg:province":"Vaud",
    "wof:name":"Raisin Invest Sa",
    "wof:placetype":"venue"
},
  "geometry": {"coordinates":[6.9101910591,46.4340248108],"type":"Point"}
}