{
  "type": "Feature",
  "properties": {
    "iso:country":"CH",
    "sg:address":"Tr\u00e9s Le Chatel 1",
    "sg:city":"Prangins",
    "sg:orig_category":"Schlossereien",
    "sg:phone":"+41 22 361 81 52",
    "sg:postcode":"1197",
    "sg:province":"Vaud",
    "wof:name":"Christian Sch\u00fcpbach Serrurerie",
    "wof:placetype":"venue"
},
  "geometry": {"coordinates":[6.2509541512,46.3954620361],"type":"Point"}
}