{
  "type": "Feature",
  "properties": {
    "iso:country":"CH",
    "sg:address":"Kirchb\u00fchl 2",
    "sg:city":"Burgdorf",
    "sg:orig_category":"Institutionen des Sozialwesens ohne Beherbergung",
    "sg:phone":"+41 34 428 80 00",
    "sg:postcode":"3400",
    "sg:province":"Bern",
    "wof:name":"Blauseestiftung Des Rotary Club Burgdorf",
    "wof:placetype":"venue"
},
  "geometry": {"coordinates":[7.6267690659,47.0565109253],"type":"Point"}
}