{
  "type": "Feature",
  "properties": {
    "iso:country":"CH",
    "sg:address":"Freudwilerweg 8",
    "sg:city":"Z\u00fcrich",
    "sg:orig_category":"Architekturb\u00fcros",
    "sg:phone":"+41 12514442",
    "sg:postcode":"8044",
    "sg:province":"Z\u00fcrich",
    "wof:name":"R\u00fcegg + Weber Architekten Ag",
    "wof:placetype":"venue"
},
  "geometry": {"coordinates":[8.554817,47.38113],"type":"Point"}
}