{
  "type": "Feature",
  "properties": {
    "iso:country":"CH",
    "sg:address":"6340",
    "sg:city":"Baar",
    "sg:orig_category":"Vorschulen, Kinderg\u00e4rten",
    "sg:phone":"+41 41 761 34 36",
    "sg:postcode":"6340",
    "sg:province":"Zug",
    "wof:name":"Kindergarten Schutzengel",
    "wof:placetype":"venue"
},
  "geometry": {"coordinates":[8.5406503677,47.1973190308],"type":"Point"}
}