{
  "type": "Feature",
  "properties": {
    "iso:country":"CH",
    "sg:address":"Schulstrasse 63",
    "sg:city":"W\u00fcrenlos",
    "sg:orig_category":"Sonstige mit der Informatik verbundene T\u00e4tigkeiten",
    "sg:phone":"+41 56 450 26 76",
    "sg:postcode":"5436",
    "sg:province":"Aargau",
    "wof:name":"Exa-bit Dipl. El.-ing. Eth Melnikoff Alexandre",
    "wof:placetype":"venue"
},
  "geometry": {"coordinates":[8.1966056824,47.4736671448],"type":"Point"}
}