{
  "type": "Feature",
  "properties": {
    "iso:country":"CH",
    "sg:address":"Schneehof",
    "sg:city":"Laupersdorf",
    "sg:orig_category":"Landwirtschaft, Jagd U damit verbundene Dienstleistungen",
    "sg:phone":"+41 91 872 12 26",
    "sg:postcode":"4712",
    "sg:province":"Solothurn",
    "wof:name":"Gianni & Daniela Martinelli Azienda Agricola",
    "wof:placetype":"venue"
},
  "geometry": {"coordinates":[8.9422903061,46.569644928],"type":"Point"}
}