{
  "type": "Feature",
  "properties": {
    "addr:full":"Rue Fritz-marchand 37 Sonvilier Bern 2615",
    "addr:housenumber":"37",
    "addr:postcode":"2615",
    "addr:street":"Rue Fritz-Marchand",
    "iso:country":"CH",
    "sg:address":"Rue Fritz-marchand 37",
    "sg:city":"Sonvilier",
    "sg:orig_category":"Autogaragen",
    "sg:phone":"+41 32 941 15 38",
    "sg:postcode":"2615",
    "sg:province":"Bern",
    "wof:name":"Johny Roth Garage",
    "wof:placetype":"venue"
},
  "geometry": {"coordinates":[6.957304,47.135605],"type":"Point"}
}