{
  "type": "Feature",
  "properties": {
    "iso:country":"CH",
    "sg:address":"General Wille-strasse 8 8002 Z\u00fcrich. Postfach 588",
    "sg:city":"Z\u00fcrich",
    "sg:classifiers":[
        {
            "category":"Professional",
            "subcategory":"Employment Agencies",
            "type":"Services"
        }
    ],
    "sg:phone":"+41 71 228 44 88",
    "sg:postcode":"8027",
    "sg:province":"Z\u00fcrich",
    "sg:tags":[
        "personal",
        "u",
        "stellenvermittlung"
    ],
    "wof:name":"Transteam Personal Ag St. Gallen",
    "wof:placetype":"venue"
},
  "geometry": {"coordinates":[9.3748435974,47.4250297546],"type":"Point"}
}