{
  "type": "Feature",
  "properties": {
    "iso:country":"CH",
    "sg:address":"Engelstrasse 52 8004 Z\u00fcrich. Postfach 1452",
    "sg:city":"Z\u00fcrich",
    "sg:classifiers":[
        {
            "category":"Communications",
            "subcategory":"Film & Video Production",
            "type":"Services"
        }
    ],
    "sg:phone":"+41 12458660",
    "sg:postcode":"8026",
    "sg:province":"Z\u00fcrich",
    "sg:tags":[
        "videofilmherstellung",
        "u"
    ],
    "wof:name":"Fama Film Ag",
    "wof:placetype":"venue"
},
  "geometry": {"coordinates":[8.5236263275,47.3761405945],"type":"Point"}
}