{
  "type": "Feature",
  "properties": {
    "iso:country":"CH",
    "sg:address":"Nord Place Du 2",
    "sg:city":"Lausanne",
    "sg:orig_category":"Erbringung von Dienstleistungen f\u00fcr Unternehmen",
    "sg:phone":"+41 21 320 58 07",
    "sg:postcode":"1005",
    "sg:province":"Vaud",
    "wof:name":"Cahen & Frossard, Les Ateliers Du Nord",
    "wof:placetype":"venue"
},
  "geometry": {"coordinates":[6.632335186,46.5195960999],"type":"Point"}
}