{
  "type": "Feature",
  "properties": {
    "iso:country":"CH",
    "sg:address":"Erligatterweg 8",
    "sg:city":"Z\u00fcrich",
    "sg:orig_category":"Grosshandel mit Nahrungsmitteln, Getr\u00e4nken U Tabakwaren",
    "sg:phone":"+41 14828681",
    "sg:postcode":"8038",
    "sg:province":"Z\u00fcrich",
    "wof:name":"Alfred Von Escher Artisan En Comestibles",
    "wof:placetype":"venue"
},
  "geometry": {"coordinates":[8.5325813293,47.3345985413],"type":"Point"}
}