{
  "type": "Feature",
  "properties": {
    "iso:country":"CH",
    "sg:address":"Oberzelg 64",
    "sg:city":"Aeschlen",
    "sg:orig_category":"Unternehmensberatung Wirtschaftspr\u00fcfung, Steuerberatung U Treuhand",
    "sg:phone":"+41 31 772 00 35",
    "sg:postcode":"3672",
    "sg:province":"Bern",
    "wof:name":"Advice Concept Gmbh",
    "wof:placetype":"venue"
},
  "geometry": {"coordinates":[7.6453838348,46.837600708],"type":"Point"}
}