{
  "type": "Feature",
  "properties": {
    "iso:country":"CH",
    "sg:address":"T\u00f6sstalstrasse 67",
    "sg:city":"Turbenthal",
    "sg:orig_category":"Detailhandel mit Fleisch U Fleischwaren",
    "sg:phone":"+41 52 385 11 33",
    "sg:postcode":"8488",
    "sg:province":"Z\u00fcrich",
    "wof:name":"Dorfmetzgerei B.& G.brunner",
    "wof:placetype":"venue"
},
  "geometry": {"coordinates":[8.8432512283,47.4408378601],"type":"Point"}
}