{
  "type": "Feature",
  "properties": {
    "iso:country":"CH",
    "sg:address":"Innere G\u00fcterstrasse 4",
    "sg:city":"Zug",
    "sg:orig_category":"Finanzierungsinstitutionen",
    "sg:postcode":"6300",
    "sg:province":"Zug",
    "wof:name":"Hero Finance B.v., Rotterdam, Zweigniederlassung Zug",
    "wof:placetype":"venue"
},
  "geometry": {"coordinates":[8.5169610977,47.1777954102],"type":"Point"}
}