{
  "type": "Feature",
  "properties": {
    "iso:country":"CH",
    "sg:address":"Ammannsmatt 43",
    "sg:city":"Zug",
    "sg:orig_category":"Interessenvertretungen",
    "sg:postcode":"6300",
    "sg:province":"Zug",
    "wof:name":"Stiftung Zugerseemuseum Zug",
    "wof:placetype":"venue"
},
  "geometry": {"coordinates":[8.4970645905,47.187412262],"type":"Point"}
}