{
  "type": "Feature",
  "properties": {
    "addr:full":"Adlerfeldstrasse 2 Frenkendorf Basel-Landschaft 4402",
    "addr:housenumber":"2",
    "addr:postcode":"4402",
    "addr:street":"Adlerfeldstrasse",
    "iso:country":"CH",
    "sg:address":"Adlerfeldstrasse 2",
    "sg:city":"Frenkendorf",
    "sg:orig_category":"Detailhandel mit Blumen U Pflanzen",
    "sg:phone":"+41 61 901 66 80",
    "sg:postcode":"4402",
    "sg:province":"Basel-Landschaft",
    "wof:name":"Urs Berger Blumenhaus",
    "wof:placetype":"venue"
},
  "geometry": {"coordinates":[7.712991,47.503571],"type":"Point"}
}