{
  "type": "Feature",
  "properties": {
    "iso:country":"CH",
    "sg:address":"Sparenmoos 1 3770 Zweisimmen. Postfach 216",
    "sg:city":"Zweisimmen",
    "sg:classifiers":[
        {
            "category":"Travel",
            "subcategory":"Hotels & Motels",
            "type":"Entertainment"
        }
    ],
    "sg:phone":"+41 33 722 22 34",
    "sg:postcode":"3770",
    "sg:province":"Bern",
    "sg:tags":[
        "hotels",
        "mit",
        "restaurant"
    ],
    "wof:name":"Hotel Sparenmoos",
    "wof:placetype":"venue"
},
  "geometry": {"coordinates":[7.3460979462,46.554233551],"type":"Point"}
}