{
  "type": "Feature",
  "properties": {
    "iso:country":"CH",
    "sg:address":"Dullikerstrasse 2",
    "sg:city":"Oberg\u00f6sgen",
    "sg:orig_category":"Diskotheken, Dancings, Night Clubs",
    "sg:phone":"+41 62 295 45 55",
    "sg:postcode":"4653",
    "sg:province":"Solothurn",
    "wof:name":"Landgasthaus F\u00e4hre Ag",
    "wof:placetype":"venue"
},
  "geometry": {"coordinates":[7.9550051689,47.3554344177],"type":"Point"}
}