{
  "type": "Feature",
  "properties": {
    "iso:country":"CH",
    "sg:address":"Via Nassa 68 6900 Lugano. Postfach",
    "sg:city":"Lugano",
    "sg:classifiers":[
        {
            "category":"Travel",
            "subcategory":"Hotels & Motels",
            "type":"Entertainment"
        }
    ],
    "sg:phone":"+41 91 832 11 88",
    "sg:postcode":"6901",
    "sg:province":"Ticino",
    "sg:tags":[
        "hotels",
        "mit",
        "restaurant"
    ],
    "wof:name":"Albergo Internazionale",
    "wof:placetype":"venue"
},
  "geometry": {"coordinates":[9.1906404495,46.4630584717],"type":"Point"}
}