{
  "type": "Feature",
  "properties": {
    "iso:country":"CH",
    "sg:address":"Juchstrasse 18 8500 Frauenfeld. Postfach",
    "sg:city":"Frauenfeld",
    "sg:orig_category":"Instandhaltung U Reparatur von Automobilen",
    "sg:phone":"+41 52 721 24 29",
    "sg:postcode":"8500",
    "sg:province":"Thurgau",
    "wof:name":"Spritzwerk Strupler Ag",
    "wof:placetype":"venue"
},
  "geometry": {"coordinates":[8.9073162079,47.5682945251],"type":"Point"}
}