{
  "type": "Feature",
  "properties": {
    "iso:country":"CH",
    "sg:address":"Gewerbestrasse 4",
    "sg:city":"Deitingen",
    "sg:classifiers":[
        {
            "category":"Manufacturing",
            "subcategory":"Tools & Machinery",
            "type":"Manufacturing & Wholesale Goods"
        }
    ],
    "sg:phone":"+41 21 845 50 66",
    "sg:postcode":"4543",
    "sg:province":"Solothurn",
    "sg:tags":[
        "machine"
    ],
    "wof:name":"Manuel P\u00e9rez Ateliers M\u00e9caniques",
    "wof:placetype":"venue"
},
  "geometry": {"coordinates":[6.222607,46.601387],"type":"Point"}
}