{
  "type": "Feature",
  "properties": {
    "iso:country":"CH",
    "sg:address":"Sternenstrasse 2 8002 Z\u00fcrich. Postfach",
    "sg:city":"Z\u00fcrich",
    "sg:orig_category":"Softwareentwicklung U beratung",
    "sg:phone":"+41 12055700",
    "sg:postcode":"8008",
    "sg:province":"Z\u00fcrich",
    "wof:name":"Voipready Ag",
    "wof:placetype":"venue"
},
  "geometry": {"coordinates":[8.5342702866,47.3602714539],"type":"Point"}
}