{
  "type": "Feature",
  "properties": {
    "addr:full":"Furtbachstr. 16 Buchs Z\u00fcrich 8107",
    "addr:housenumber":"16",
    "addr:postcode":"8107",
    "addr:street":"Furtbachstr.",
    "iso:country":"CH",
    "sg:address":"Furtbachstr. 16",
    "sg:city":"Buchs",
    "sg:classifiers":[
        {
            "category":"Professional",
            "subcategory":"Advertising",
            "type":"Services"
        }
    ],
    "sg:phone":"+41 4118464242",
    "sg:postcode":"8107",
    "sg:province":"Z\u00fcrich",
    "sg:tags":[
        "communication",
        "medium"
    ],
    "wof:name":"Waser Werbeartikel Ag",
    "wof:placetype":"venue"
},
  "geometry": {"coordinates":[8.431973,47.450291],"type":"Point"}
}