{
  "type": "Feature",
  "properties": {
    "iso:country":"CH",
    "sg:address":"Z\u00e4hringerstrasse 23",
    "sg:city":"Luzern",
    "sg:orig_category":"Advokaturb\u00fcros",
    "sg:phone":"+41 41 240 84 52",
    "sg:postcode":"6003",
    "sg:province":"Luzern",
    "wof:name":"Werner B\u00e4r Advokatur-& Notariatsb\u00fcro",
    "wof:placetype":"venue"
},
  "geometry": {"coordinates":[8.301746,47.047016],"type":"Point"}
}