{
  "type": "Feature",
  "properties": {
    "iso:country":"CH",
    "sg:address":"Grand-rue 73 1890 Dailly. Postfach",
    "sg:city":"Dailly",
    "sg:orig_category":"RESTAURANTS: TEA-ROOMS",
    "sg:postcode":"1890",
    "sg:province":"Valais",
    "wof:name":"Pizzeria Napoli S\u00e0rl",
    "wof:placetype":"venue"
},
  "geometry": {"coordinates":[-97.9761123657,46.7137985229],"type":"Point"}
}