{
  "type": "Feature",
  "properties": {
    "iso:country":"CH",
    "sg:address":"Route De Ch\u00eane 129",
    "sg:city":"Ch\u00eane-bougeries",
    "sg:orig_category":"Detailhandel mit Antiquit\u00e4ten U Gebrauchtwaren in Verkaufsr\u00e4umen Detailhandel mit B\u00fcchern",
    "sg:phone":"+41 22 348 77 55",
    "sg:postcode":"1224",
    "sg:province":"Gen\u00e8ve",
    "wof:name":"L'autographe Sa, Librairie Ancienne",
    "wof:placetype":"venue"
},
  "geometry": {"coordinates":[6.183928,46.19862],"type":"Point"}
}