{
  "type": "Feature",
  "properties": {
    "iso:country":"CH",
    "sg:address":"Rte De L'etraz 25",
    "sg:city":"Collex",
    "sg:orig_category":"Fachdetailhandel in Verkaufsr\u00e4umen",
    "sg:phone":"+41 22 774 27 00",
    "sg:postcode":"1239",
    "sg:province":"Gen\u00e8ve",
    "wof:name":"Agro-sanilac, Gaillard Alain",
    "wof:placetype":"venue"
},
  "geometry": {"coordinates":[6.1287651062,46.2724876404],"type":"Point"}
}