{
  "type": "Feature",
  "properties": {
    "iso:country":"CH",
    "sg:address":"6717",
    "sg:city":"Dangio-torre",
    "sg:classifiers":[
        {
            "category":"Restaurant",
            "type":"Food & Drink"
        }
    ],
    "sg:phone":"+41 91 872 16 92",
    "sg:postcode":"6717",
    "sg:province":"Ticino",
    "wof:name":"Caff\u00e9 Della Posta",
    "wof:placetype":"venue"
},
  "geometry": {"coordinates":[8.951918602,46.4869384766],"type":"Point"}
}