{
  "type": "Feature",
  "properties": {
    "iso:country":"CH",
    "sg:address":"Baarerstrasse 95 6301 Zug. Postfach",
    "sg:city":"Zug",
    "sg:orig_category":"Unclassifiable Establishments",
    "sg:postcode":"6301",
    "sg:province":"Zug",
    "wof:name":"N M Rothschild China Holding Ag",
    "wof:placetype":"venue"
},
  "geometry": {"coordinates":[8.5162153244,47.1715087891],"type":"Point"}
}