{
  "type": "Feature",
  "properties": {
    "iso:country":"CH",
    "sg:address":"Bahnhofstrasse 7",
    "sg:city":"Erlen",
    "sg:orig_category":"Herstellung von sonstigen landwirtschaftlichen Maschinen Mechanik",
    "sg:phone":"+41 71 648 19 48",
    "sg:postcode":"8586",
    "sg:province":"Thurgau",
    "wof:name":"Martin Sonderer, Vorm. A. Fisch",
    "wof:placetype":"venue"
},
  "geometry": {"coordinates":[9.2262763977,47.5510826111],"type":"Point"}
}