{
  "type": "Feature",
  "properties": {
    "iso:country":"CH",
    "sg:address":"Wetzikerstrasse 36",
    "sg:city":"Oberhittnau",
    "sg:orig_category":"Hoch U Tiefbau",
    "sg:phone":"+41 19502337",
    "sg:postcode":"8335",
    "sg:province":"Z\u00fcrich",
    "wof:name":"Heinrich Graf Baugesch\u00e4ft",
    "wof:placetype":"venue"
},
  "geometry": {"coordinates":[8.8233852386,47.3593635559],"type":"Point"}
}