{
  "type": "Feature",
  "properties": {
    "iso:country":"CH",
    "sg:address":"Wydenmatten",
    "sg:city":"Breitenbach",
    "sg:orig_category":"Detailhandel mit Damenbekleidung Detailhandel mit Herrenbekleidung",
    "sg:phone":"+41 56 619 79 90",
    "sg:postcode":"4226",
    "sg:province":"Solothurn",
    "wof:name":"Charles V\u00f6gele Mode Ag",
    "wof:placetype":"venue"
},
  "geometry": {"coordinates":[8.2760400772,47.3491096497],"type":"Point"}
}