{
  "type": "Feature",
  "properties": {
    "iso:country":"CH",
    "sg:address":"Hans-huber-strasse 38 4500 Solothurn. Postfach",
    "sg:city":"Solothurn",
    "sg:orig_category":"Grosshandel mit pharmazeutischen Erzeugnissen, medizinischen U orthop\u00e4dischen Artikeln Herstellung v",
    "sg:phone":"+41 32 624 56 60",
    "sg:postcode":"4502",
    "sg:province":"Solothurn",
    "wof:name":"Smith & Nephew Ag",
    "wof:placetype":"venue"
},
  "geometry": {"coordinates":[7.5272870064,47.2011413574],"type":"Point"}
}