{
  "type": "Feature",
  "properties": {
    "iso:country":"CH",
    "sg:address":"Route Principale 50b",
    "sg:city":"Bo\u00e9court",
    "sg:orig_category":"Fahrschulen, Flugschulen",
    "sg:phone":"+41 32 426 60 36",
    "sg:postcode":"2856",
    "sg:province":"Jura",
    "wof:name":"Willy Mahler Auto-\u00e9cole",
    "wof:placetype":"venue"
},
  "geometry": {"coordinates":[7.2126421928,47.349822998],"type":"Point"}
}