{
  "type": "Feature",
  "properties": {
    "iso:country":"CH",
    "sg:address":"Sautter Rue 21 1205 Gen\u00e8ve. Postfach",
    "sg:city":"Gen\u00e8ve",
    "sg:classifiers":[
        {
            "category":"Travel",
            "subcategory":"Hotels & Motels",
            "type":"Entertainment"
        }
    ],
    "sg:postcode":"1201",
    "sg:province":"Gen\u00e8ve",
    "sg:tags":[
        "hotels",
        "mit",
        "restaurant"
    ],
    "wof:name":"Nicor Sa",
    "wof:placetype":"venue"
},
  "geometry": {"coordinates":[6.1500291824,46.1951675415],"type":"Point"}
}