{
  "type": "Feature",
  "properties": {
    "iso:country":"CH",
    "sg:address":"Brusighel Via 6930 Bedano. Postfach",
    "sg:city":"Bedano",
    "sg:orig_category":"Instandhaltung U Reparatur von Automobilen",
    "sg:phone":"+41 27 957 18 57",
    "sg:postcode":"6930",
    "sg:province":"Ticino",
    "wof:name":"Bumann Edgar Autoelektriker",
    "wof:placetype":"venue"
},
  "geometry": {"coordinates":[7.9367241859,46.1232452393],"type":"Point"}
}