{
  "type": "Feature",
  "properties": {
    "iso:country":"CH",
    "sg:address":"Clarastrasse 19",
    "sg:city":"Basel",
    "sg:orig_category":"Unclassifiable Establishments",
    "sg:phone":"+41 61 681 02 20",
    "sg:postcode":"4058",
    "sg:province":"Basel-Stadt",
    "wof:name":"Eclipse Ag Textilreinigung & W\u00e4scherei",
    "wof:placetype":"venue"
},
  "geometry": {"coordinates":[7.5958528519,47.5625534058],"type":"Point"}
}