{
  "type": "Feature",
  "properties": {
    "iso:country":"CH",
    "sg:address":"Klosternhalde 3",
    "sg:city":"Steffisburg",
    "sg:orig_category":"Softwareentwicklung U beratung",
    "sg:postcode":"3612",
    "sg:province":"Bern",
    "wof:name":"Meylan Corinne, Diffusion",
    "wof:placetype":"venue"
},
  "geometry": {"coordinates":[6.3256230354,46.6680374146],"type":"Point"}
}