{
  "type": "Feature",
  "properties": {
    "iso:country":"CH",
    "sg:address":"Bifigweg 20",
    "sg:city":"W\u00fcrenlos",
    "sg:orig_category":"Mechanik Mechanische Werkst\u00e4tten",
    "sg:phone":"+41 33 681 17 51",
    "sg:postcode":"5436",
    "sg:province":"Aargau",
    "wof:name":"Werner Tschabold Mechanische Werkst\u00e4tte",
    "wof:placetype":"venue"
},
  "geometry": {"coordinates":[7.8617801666,49.1125106812],"type":"Point"}
}