{
  "type": "Feature",
  "properties": {
    "iso:country":"CH",
    "sg:address":"Hauptstrasse 43",
    "sg:city":"Sissach",
    "sg:orig_category":"RESTAURANTS: TEA-ROOMS",
    "sg:phone":"+41 41 460 17 15",
    "sg:postcode":"4450",
    "sg:province":"Basel-Landschaft",
    "wof:name":"Restaurant Chang Cheng",
    "wof:placetype":"venue"
},
  "geometry": {"coordinates":[8.2235832214,47.131149292],"type":"Point"}
}