{
  "type": "Feature",
  "properties": {
    "iso:country":"CH",
    "sg:address":"Chemin De La Tuilerie 4",
    "sg:city":"Couvet",
    "sg:orig_category":"Detailhandel mit Getr\u00e4nken Grosshandel mit Getr\u00e4nken",
    "sg:phone":"+41 32 863 19 18",
    "sg:postcode":"2108",
    "sg:province":"Neuch\u00e2tel",
    "wof:name":"Denis Del\u00e9chat Commerce De Vins",
    "wof:placetype":"venue"
},
  "geometry": {"coordinates":[6.6370658875,46.9224815369],"type":"Point"}
}