{
  "type": "Feature",
  "properties": {
    "iso:country":"CH",
    "sg:address":"Gerbergasse 30 4001 Basel. Postfach",
    "sg:city":"Basel",
    "sg:orig_category":"Unternehmensberatung",
    "sg:phone":"+41 61 373 04 85",
    "sg:postcode":"4001",
    "sg:province":"Basel-Stadt",
    "wof:name":"Biemond & Partner",
    "wof:placetype":"venue"
},
  "geometry": {"coordinates":[7.5883879662,47.5565032959],"type":"Point"}
}