{
  "type": "Feature",
  "properties": {
    "iso:country":"CH",
    "sg:address":"Schlossmatt 12",
    "sg:city":"Zufikon",
    "sg:orig_category":"Datenverarbeitungsdienste Softwareentwicklung U beratung",
    "sg:postcode":"5621",
    "sg:province":"Aargau",
    "wof:name":"Infosoft Gmbh",
    "wof:placetype":"venue"
},
  "geometry": {"coordinates":[8.360542,47.345573],"type":"Point"}
}