{
  "type": "Feature",
  "properties": {
    "iso:country":"CH",
    "sg:address":"Chropfacher 4",
    "sg:city":"Schwerzenbach",
    "sg:orig_category":"Non-Classified Establishments",
    "sg:postcode":"8603",
    "sg:province":"Z\u00fcrich",
    "wof:name":"Sonnenstrahl - Reinigungen Araujo Paulo Und Araujo Rui Manuel",
    "wof:placetype":"venue"
},
  "geometry": {"coordinates":[8.6566085815,47.3833732605],"type":"Point"}
}