{
  "type": "Feature",
  "properties": {
    "iso:country":"CH",
    "sg:address":"7000",
    "sg:city":"Chur",
    "sg:orig_category":"Vereine Lions",
    "sg:phone":"+41 81 416 25 01",
    "sg:postcode":"7000",
    "sg:province":"Graubunden",
    "wof:name":"Lions Club Davos",
    "wof:placetype":"venue"
},
  "geometry": {"coordinates":[9.8340272903,46.8032302856],"type":"Point"}
}