{
  "type": "Feature",
  "properties": {
    "iso:country":"CH",
    "sg:address":"Riedstrasse 6 8953 Dietikon. Postfach",
    "sg:city":"R\u00fcdlingen",
    "sg:orig_category":"Reiseb\u00fcros U Reiseveranstalter",
    "sg:postcode":"8455",
    "sg:province":"Schaffhausen",
    "wof:name":"Traxess Ag",
    "wof:placetype":"venue"
},
  "geometry": {"coordinates":[8.3941688538,47.4196548462],"type":"Point"}
}