{
  "type": "Feature",
  "properties": {
    "iso:country":"CH",
    "sg:address":"Dunantstrasse 20 3006 Bern. Postfach",
    "sg:city":"Bern",
    "sg:orig_category":"Wirtschaftspr\u00fcfung, Steuerberatung U Treuhand",
    "sg:phone":"+41 31 352 09 18",
    "sg:postcode":"3005",
    "sg:province":"Bern",
    "wof:name":"L\u00fcthi Bau, Immobilien Und Bautreuhand",
    "wof:placetype":"venue"
},
  "geometry": {"coordinates":[7.4762058258,46.9356994629],"type":"Point"}
}