{
  "type": "Feature",
  "properties": {
    "iso:country":"CH",
    "sg:address":"1055",
    "sg:city":"Froideville",
    "sg:orig_category":"Gemeindeverwaltungen",
    "sg:phone":"+41 21 881 22 27",
    "sg:postcode":"1055",
    "sg:province":"Vaud",
    "wof:name":"Administration Communale Froideville",
    "wof:placetype":"venue"
},
  "geometry": {"coordinates":[6.6880102158,46.5993614197],"type":"Point"}
}