{
  "type": "Feature",
  "properties": {
    "addr:full":"Bahnhofstrasse 67 8001 Z\u00fcrich. Postfach Z\u00fcrich Z\u00fcrich 8023",
    "addr:housenumber":"67",
    "addr:postcode":"8001 zuerich. postfach;8023",
    "addr:street":"Bahnhofstrasse",
    "iso:country":"CH",
    "sg:address":"Bahnhofstrasse 67 8001 Z\u00fcrich. Postfach",
    "sg:city":"Z\u00fcrich",
    "sg:orig_category":"Detailhandel mit Brot, Back U S\u00fcsswaren",
    "sg:phone":"+41 12121702",
    "sg:postcode":"8023",
    "sg:province":"Z\u00fcrich",
    "wof:name":"Confiserie Spr\u00fcngli Ag",
    "wof:placetype":"venue"
},
  "geometry": {"coordinates":[8.5382,47.37389],"type":"Point"}
}