{
  "type": "Feature",
  "properties": {
    "iso:country":"CH",
    "sg:address":"Schafisheimerstrasse 1b",
    "sg:city":"Staufen",
    "sg:orig_category":"Sonstige Kultur U Unterhaltungseinrichtungen",
    "sg:phone":"+41 62 891 25 95",
    "sg:postcode":"5603",
    "sg:province":"Aargau",
    "wof:name":"Islamisches Kulturzentrum",
    "wof:placetype":"venue"
},
  "geometry": {"coordinates":[8.1643371582,47.3867378235],"type":"Point"}
}