{
  "type": "Feature",
  "properties": {
    "iso:country":"CH",
    "sg:address":"Dorfstrasse 50 2076 Bethlehem B. Gals. Postfach",
    "sg:city":"Biel/bienne",
    "sg:orig_category":"Fachdetailhandel in Verkaufsr\u00e4umen",
    "sg:postcode":"2502",
    "sg:province":"Bern",
    "wof:name":"Kys Sa",
    "wof:placetype":"venue"
},
  "geometry": {"coordinates":[7.0426301956,47.0200386047],"type":"Point"}
}