{
  "type": "Feature",
  "properties": {
    "iso:country":"CH",
    "sg:address":"Pflanzerbachstrasse 9",
    "sg:city":"Widen",
    "sg:orig_category":"Herstellung von Kunststoffwaren Herstellung von sonstigen Maschinen f\u00fcr unspezifische Verwendung",
    "sg:phone":"+41 56 633 84 47",
    "sg:postcode":"8967",
    "sg:province":"Aargau",
    "wof:name":"O + M Gmbh",
    "wof:placetype":"venue"
},
  "geometry": {"coordinates":[8.35891819,47.3633613586],"type":"Point"}
}