{
  "type": "Feature",
  "properties": {
    "iso:country":"CH",
    "sg:address":"Ch. Des Evouettes 1",
    "sg:city":"Meinier",
    "sg:orig_category":"Maler U Glasergewerbe",
    "sg:postcode":"1252",
    "sg:province":"Gen\u00e8ve",
    "wof:name":"Entreprise De Peinture, Espinoza",
    "wof:placetype":"venue"
},
  "geometry": {"coordinates":[6.9309201241,46.9920082092],"type":"Point"}
}