{
  "type": "Feature",
  "properties": {
    "iso:country":"CH",
    "sg:address":"Avenue De La Sallaz 54",
    "sg:city":"Lausanne",
    "sg:orig_category":"Detailhandel mit Antiquit\u00e4ten",
    "sg:phone":"+41 21 652 54 93",
    "sg:postcode":"1010",
    "sg:province":"Vaud",
    "wof:name":"Antiquit\u00e9s Au Bibelot Yolande Rapin",
    "wof:placetype":"venue"
},
  "geometry": {"coordinates":[6.647375,46.530796],"type":"Point"}
}