{
  "type": "Feature",
  "properties": {
    "iso:country":"CH",
    "sg:address":"Ch. Sur Villard 9",
    "sg:city":"Echandens",
    "sg:orig_category":"Detailhandel mit B\u00fcchern, Zeitungen, Schreib U Papeteriewaren",
    "sg:phone":"+41 21 802 15 60",
    "sg:postcode":"1026",
    "sg:province":"Vaud",
    "wof:name":"Villard Robert",
    "wof:placetype":"venue"
},
  "geometry": {"coordinates":[6.54083,46.534286],"type":"Point"}
}