{
  "type": "Feature",
  "properties": {
    "iso:country":"CH",
    "sg:address":"Kempttalstrasse 69",
    "sg:city":"Fehraltorf",
    "sg:orig_category":"Detailhandel mit Damenbekleidung",
    "sg:phone":"+41 19541740",
    "sg:postcode":"8320",
    "sg:province":"Z\u00fcrich",
    "wof:name":"Boutique Margrith Margrith Achermann",
    "wof:placetype":"venue"
},
  "geometry": {"coordinates":[8.752709,47.387787],"type":"Point"}
}