{
  "type": "Feature",
  "properties": {
    "addr:full":"D\u00fcnnernstr. 513 Welschenrohr Solothurn 4716",
    "addr:housenumber":"513",
    "addr:postcode":"4716",
    "iso:country":"CH",
    "sg:address":"D\u00fcnnernstr. 513",
    "sg:city":"Welschenrohr",
    "sg:classifiers":[
        {
            "category":"Food & Beverages",
            "subcategory":"Groceries & Convenience Stores",
            "type":"Retail Goods"
        }
    ],
    "sg:phone":"+41 32 639 14 44",
    "sg:postcode":"4716",
    "sg:province":"Solothurn",
    "sg:tags":[
        "product",
        "grain",
        "cereal",
        "related"
    ],
    "wof:name":"Bimbosan Ag",
    "wof:placetype":"venue"
},
  "geometry": {"coordinates":[7.527392,47.279312],"type":"Point"}
}