{
  "type": "Feature",
  "properties": {
    "iso:country":"CH",
    "sg:address":"Bahnhofstrasse 1",
    "sg:city":"Kaltbrunn",
    "sg:orig_category":"K\u00fcnstlerische U schriftstellerische T\u00e4tigkeiten U Darbietungen",
    "sg:phone":"+41 55 283 14 51",
    "sg:postcode":"8722",
    "sg:province":"St. Gallen",
    "wof:name":"Naef Werner, Bildhauer.",
    "wof:placetype":"venue"
},
  "geometry": {"coordinates":[9.0259752274,47.2146568298],"type":"Point"}
}