{
  "type": "Feature",
  "properties": {
    "iso:country":"CH",
    "sg:address":"Dammstrasse 19",
    "sg:city":"Flawil",
    "sg:orig_category":"Grosshandel mit Foto U Kinoger\u00e4ten, feinmechanischen U optischen Erzeugnissen Grosshandel mit elektr",
    "sg:phone":"+41 71 393 31 35",
    "sg:postcode":"9230",
    "sg:province":"St. Gallen",
    "wof:name":"Stage Equipment Wick B\u00fchnentechn.produkte",
    "wof:placetype":"venue"
},
  "geometry": {"coordinates":[9.1930837631,47.4130516052],"type":"Point"}
}