{
  "type": "Feature",
  "properties": {
    "iso:country":"CH",
    "sg:address":"Grammetstrasse 16",
    "sg:city":"Liestal",
    "sg:orig_category":"Tanzschulen, Tanzlehrer",
    "sg:phone":"+41 61 281 49 20",
    "sg:postcode":"4410",
    "sg:province":"Basel-Landschaft",
    "wof:name":"Ballett-& Bewegungsschule Liestal Frau Marlis Stieger",
    "wof:placetype":"venue"
},
  "geometry": {"coordinates":[7.7474498749,47.4789276123],"type":"Point"}
}