{
  "type": "Feature",
  "properties": {
    "iso:country":"CH",
    "sg:address":"Chandieu Chemin De 1",
    "sg:city":"Lausanne",
    "sg:orig_category":"Unternehmensberatung",
    "sg:postcode":"1006",
    "sg:province":"Vaud",
    "wof:name":"Ha Et Consulting Sa",
    "wof:placetype":"venue"
},
  "geometry": {"coordinates":[6.8212080002,47.1004676819],"type":"Point"}
}