{
  "type": "Feature",
  "properties": {
    "iso:country":"CH",
    "sg:address":"Oerlifallstieg 12",
    "sg:city":"Schaffhausen",
    "sg:orig_category":"Grosshandel mit Getreide, Saatgut U Futtermitteln",
    "sg:postcode":"8202",
    "sg:province":"Schaffhausen",
    "wof:name":"United Consumer Electronics International",
    "wof:placetype":"venue"
},
  "geometry": {"coordinates":[8.6140403748,47.7011222839],"type":"Point"}
}