{
  "type": "Feature",
  "properties": {
    "iso:country":"CH",
    "sg:address":"Zur Blumenau",
    "sg:city":"Aadorf",
    "sg:orig_category":"Sportvereine Sch\u00fctzen",
    "sg:phone":"+41 52 365 36 15",
    "sg:postcode":"8355",
    "sg:province":"Thurgau",
    "wof:name":"Sch\u00fctzenges.maischhausen",
    "wof:placetype":"venue"
},
  "geometry": {"coordinates":[8.9210796356,47.4862747192],"type":"Point"}
}