{
  "type": "Feature",
  "properties": {
    "iso:country":"CH",
    "sg:address":"1982 Euseigne. Postfach",
    "sg:city":"Euseigne",
    "sg:orig_category":"Architektur U Ingenieurb\u00fcros",
    "sg:postcode":"1982",
    "sg:province":"Valais",
    "wof:name":"Jean-ren\u00e9 Dayer S\u00e0rl",
    "wof:placetype":"venue"
},
  "geometry": {"coordinates":[7.423947,46.17099],"type":"Point"}
}