{
  "type": "Feature",
  "properties": {
    "iso:country":"CH",
    "sg:address":"Cath\u00e9drale Place De La 5",
    "sg:city":"Lausanne",
    "sg:orig_category":"Architektur U Ingenieurb\u00fcros",
    "sg:phone":"+41 21 312 64 17",
    "sg:postcode":"1005",
    "sg:province":"Vaud",
    "wof:name":"Atelier D'architecture Audergon, Vionnet & Perakis Sa",
    "wof:placetype":"venue"
},
  "geometry": {"coordinates":[6.634997,46.522911],"type":"Point"}
}