{
  "type": "Feature",
  "properties": {
    "iso:country":"CH",
    "sg:address":"Wettiweg 11",
    "sg:city":"Engelberg",
    "sg:orig_category":"Bauschreinerei",
    "sg:phone":"+41 41 637 33 35",
    "sg:postcode":"6390",
    "sg:province":"Obwalden",
    "wof:name":"Heinz B\u00f6ni Schreinerei",
    "wof:placetype":"venue"
},
  "geometry": {"coordinates":[8.410014,46.81855],"type":"Point"}
}