{
  "type": "Feature",
  "properties": {
    "iso:country":"CH",
    "sg:address":"Four Rue Du 31",
    "sg:city":"Yverdon-les-bains",
    "sg:orig_category":"Detailhandel mit Schuhen U Lederwaren",
    "sg:postcode":"1400",
    "sg:province":"Vaud",
    "wof:name":"Boutique Minou, Franziska Gyger",
    "wof:placetype":"venue"
},
  "geometry": {"coordinates":[7.2666568756,47.1203079224],"type":"Point"}
}