{
  "type": "Feature",
  "properties": {
    "iso:country":"CH",
    "sg:address":"Gottstattstrasse 24a",
    "sg:city":"Biel/bienne",
    "sg:classifiers":[
        {
            "category":"Professional",
            "subcategory":"Art Services",
            "type":"Services"
        }
    ],
    "sg:phone":"+41 32 341 00 04",
    "sg:postcode":"2504",
    "sg:province":"Bern",
    "sg:tags":[
        "metalwork"
    ],
    "wof:name":"Adolph Saurer Kunstschmiede Und Leuchten Ag",
    "wof:placetype":"venue"
},
  "geometry": {"coordinates":[7.265728,47.144253],"type":"Point"}
}