{
  "type": "Feature",
  "properties": {
    "iso:country":"CH",
    "sg:address":"Z\u00fcrichstrasse 16",
    "sg:city":"Hinwil",
    "sg:orig_category":"Versicherungen Hauptagenturen",
    "sg:phone":"+41 19371778",
    "sg:postcode":"8340",
    "sg:province":"Z\u00fcrich",
    "wof:name":"Winterthur-versicherungen Hauptagentur Kurt Bayer",
    "wof:placetype":"venue"
},
  "geometry": {"coordinates":[8.8423624039,47.3029899597],"type":"Point"}
}