{
  "type": "Feature",
  "properties": {
    "iso:country":"CH",
    "sg:address":"Gemeindestrasse 26 8032 Z\u00fcrich. Postfach",
    "sg:city":"Z\u00fcrich",
    "sg:orig_category":"Markt U Meinungsforschung",
    "sg:phone":"+41 12528600",
    "sg:postcode":"8032",
    "sg:province":"Z\u00fcrich",
    "wof:name":"Npo Marketing Ag Mittelbeschaffungs-marketing",
    "wof:placetype":"venue"
},
  "geometry": {"coordinates":[8.5533790588,47.3688774109],"type":"Point"}
}