{
  "type": "Feature",
  "properties": {
    "addr:full":"Avenue Du Premier-mars 33 Neuch\u00e2tel Neuch\u00e2tel 2000",
    "addr:housenumber":"33",
    "addr:postcode":"2000",
    "addr:street":"Avenue Du Premier-Mars",
    "iso:country":"CH",
    "sg:address":"Avenue Du Premier-mars 33",
    "sg:city":"Neuch\u00e2tel",
    "sg:orig_category":"Arztpraxen",
    "sg:phone":"+41 32 721 45 75",
    "sg:postcode":"2000",
    "sg:province":"Neuch\u00e2tel",
    "wof:name":"Dr M\u00e9d. F\u00e9lix Gueissaz M\u00e9decin Sp\u00e9cialiste Fmh",
    "wof:placetype":"venue"
},
  "geometry": {"coordinates":[6.939522,46.994663],"type":"Point"}
}