{
  "type": "Feature",
  "properties": {
    "addr:full":"Hauptstrasse 1 Zuckenriet St. Gallen 9526",
    "addr:housenumber":"1",
    "addr:postcode":"9526",
    "addr:street":"Hauptstrasse",
    "iso:country":"CH",
    "sg:address":"Hauptstrasse 1",
    "sg:city":"Zuckenriet",
    "sg:orig_category":"Autogaragen Autospenglereien",
    "sg:phone":"+41 71 947 13 33",
    "sg:postcode":"9526",
    "sg:province":"St. Gallen",
    "wof:name":"Franz Bl\u00e4ttler Garage Carrosserie",
    "wof:placetype":"venue"
},
  "geometry": {"coordinates":[9.157407,47.484035],"type":"Point"}
}