{
  "type": "Feature",
  "properties": {
    "iso:country":"CH",
    "sg:address":"Langfeldweg 6",
    "sg:city":"Zuchwil",
    "sg:orig_category":"Detailhandel mit Waren verschiedener Art, Hauptrichtung Nahrungsmittel",
    "sg:postcode":"4528",
    "sg:province":"Solothurn",
    "wof:name":"S & Q Import-export Gmbh",
    "wof:placetype":"venue"
},
  "geometry": {"coordinates":[7.5751190186,47.2020111084],"type":"Point"}
}