{
  "type": "Feature",
  "properties": {
    "iso:country":"CH",
    "sg:address":"R\u00fcstenschwilerstrasse 8",
    "sg:city":"M\u00fchlau",
    "sg:orig_category":"Elektrizit\u00e4tsversorgung",
    "sg:phone":"+41 56 668 17 91",
    "sg:postcode":"5642",
    "sg:province":"Aargau",
    "wof:name":"Elektra M\u00fchlau",
    "wof:placetype":"venue"
},
  "geometry": {"coordinates":[8.3882904053,47.2300186157],"type":"Point"}
}