{
  "type": "Feature",
  "properties": {
    "iso:country":"CH",
    "sg:address":"Schloss 4912 Aarwangen. Postfach",
    "sg:city":"Aarwangen",
    "sg:orig_category":"Verwaltung der Rechtspflege, Gerichte",
    "sg:phone":"+41 62 919 02 31",
    "sg:postcode":"4912",
    "sg:province":"Bern",
    "wof:name":"Kreisgericht",
    "wof:placetype":"venue"
},
  "geometry": {"coordinates":[7.7689061165,47.2403030396],"type":"Point"}
}