{
  "type": "Feature",
  "properties": {
    "iso:country":"CH",
    "sg:address":"Kirchgasse 1",
    "sg:city":"Triengen",
    "sg:orig_category":"Detailhandel mit Blumen U Pflanzen",
    "sg:phone":"+41 41 933 15 25",
    "sg:postcode":"6234",
    "sg:province":"Luzern",
    "wof:name":"Cornelia Aldrian Blumengesch\u00e4ft",
    "wof:placetype":"venue"
},
  "geometry": {"coordinates":[8.076956,47.234604],"type":"Point"}
}