{
  "type": "Feature",
  "properties": {
    "addr:full":"Chemin Du Raffort 3 Romanel-s-lausanne Vaud 1032",
    "addr:housenumber":"3",
    "addr:postcode":"1032",
    "addr:street":"Chemin Du Raffort",
    "iso:country":"CH",
    "sg:address":"Chemin Du Raffort 3",
    "sg:city":"Romanel-s-lausanne",
    "sg:orig_category":"Bauschreinerei Herstellung von Konstruktionsteilen, Fertigbauteilen U Ausbauelementen aus Holz",
    "sg:phone":"+41 21 781 11 40",
    "sg:postcode":"1032",
    "sg:province":"Vaud",
    "wof:name":"Menuiserie Des Confr\u00e9ries, Richard Jacques Andr\u00e9.",
    "wof:placetype":"venue"
},
  "geometry": {"coordinates":[6.769525,46.541119],"type":"Point"}
}