{
  "type": "Feature",
  "properties": {
    "iso:country":"CH",
    "sg:address":"Hauptstrasse 70",
    "sg:city":"M\u00f6hlin",
    "sg:orig_category":"Unclassifiable Establishments",
    "sg:postcode":"4313",
    "sg:province":"Aargau",
    "wof:name":"Architekturb\u00fcro Heinz Gross Ag",
    "wof:placetype":"venue"
},
  "geometry": {"coordinates":[7.8443908691,47.5574035645],"type":"Point"}
}