{
  "type": "Feature",
  "properties": {
    "iso:country":"CH",
    "sg:address":"Oberwilerstrasse",
    "sg:city":"Br\u00fctten",
    "sg:orig_category":"Gartenbau",
    "sg:phone":"+41 52 345 23 54",
    "sg:postcode":"8311",
    "sg:province":"Z\u00fcrich",
    "wof:name":"Martin Morf Handelsg\u00e4rtnerei",
    "wof:placetype":"venue"
},
  "geometry": {"coordinates":[8.6680459976,47.47108078],"type":"Point"}
}