{
  "type": "Feature",
  "properties": {
    "iso:country":"CH",
    "sg:address":"Santeri Via 7130 Ilanz. Postfach",
    "sg:city":"Ilanz",
    "sg:orig_category":"Mechanik",
    "sg:postcode":"7130",
    "sg:province":"Graubunden",
    "wof:name":"Schlosserei & Stahlbau Jenzer & Co",
    "wof:placetype":"venue"
},
  "geometry": {"coordinates":[9.1938085556,46.7718734741],"type":"Point"}
}