{
  "type": "Feature",
  "properties": {
    "iso:country":"CH",
    "sg:address":"Chemin De L'oiselier 84 2900 Porrentruy Case Postale",
    "sg:city":"Porrentruy",
    "sg:orig_category":"D\u00e4mmung gegen K\u00e4lte, W\u00e4rme, Schall U Ersch\u00fctterung Herstellung von Teppichen",
    "sg:phone":"+41 21 626 04 44",
    "sg:postcode":"2900",
    "sg:province":"Jura",
    "wof:name":"Georges Dentan Sa Etanch\u00e9it\u00e9-asphaltage",
    "wof:placetype":"venue"
},
  "geometry": {"coordinates":[6.5951161385,46.5269317627],"type":"Point"}
}