{
  "type": "Feature",
  "properties": {
    "iso:country":"CH",
    "sg:address":"Nansenstrasse 5 8050 Z\u00fcrich",
    "sg:city":"Zust",
    "sg:orig_category":"Architektur U Ingenieurb\u00fcros",
    "sg:phone":"+41 71 626 51 11",
    "sg:postcode":"50",
    "wof:name":"Meier Und Partner Ag",
    "wof:placetype":"venue"
},
  "geometry": {"coordinates":[9.138185,47.566669],"type":"Point"}
}