{
  "type": "Feature",
  "properties": {
    "iso:country":"CH",
    "sg:address":"Holderbachweg 4",
    "sg:city":"Z\u00fcrich",
    "sg:orig_category":"Unternehmensberatung Wirtschaftspr\u00fcfung, Steuerberatung U Treuhand",
    "sg:phone":"+41 61 643 03 03",
    "sg:postcode":"8046",
    "sg:province":"Z\u00fcrich",
    "wof:name":"Urb-unternehmensberatung & Treuhand Brauchle",
    "wof:placetype":"venue"
},
  "geometry": {"coordinates":[7.6502342224,47.5861778259],"type":"Point"}
}