{
  "type": "Feature",
  "properties": {
    "iso:country":"CH",
    "sg:address":"Im Buechi",
    "sg:city":"Seelisberg",
    "sg:orig_category":"Unternehmensberatung",
    "sg:phone":"+41 61 606 55 00",
    "sg:postcode":"6377",
    "sg:province":"Uri",
    "wof:name":"Hiag Ag",
    "wof:placetype":"venue"
},
  "geometry": {"coordinates":[7.642261982,47.5694160461],"type":"Point"}
}