{
  "type": "Feature",
  "properties": {
    "iso:country":"CH",
    "sg:address":"Dufourstrasse 5 4052 Basel. Postfach",
    "sg:city":"Basel",
    "sg:orig_category":"Unclassifiable Establishments",
    "sg:postcode":"4051",
    "sg:province":"Basel-Stadt",
    "wof:name":"Nolte International Ag",
    "wof:placetype":"venue"
},
  "geometry": {"coordinates":[7.5950632095,47.5540428162],"type":"Point"}
}