{
  "type": "Feature",
  "properties": {
    "iso:country":"CH",
    "sg:address":"Chemin De Flor\u00e9al 11",
    "sg:city":"Orbe",
    "sg:orig_category":"Herstellung von Metallkonstruktionen",
    "sg:phone":"+41 24 441 10 78",
    "sg:postcode":"1350",
    "sg:province":"Vaud",
    "wof:name":"Ammon S\u00e0rl",
    "wof:placetype":"venue"
},
  "geometry": {"coordinates":[6.5327091217,46.7192077637],"type":"Point"}
}