{
  "type": "Feature",
  "properties": {
    "iso:country":"CH",
    "sg:address":"Burgstein",
    "sg:city":"Ennenda",
    "sg:orig_category":"Ingenieurb\u00fcros Vermessung",
    "sg:phone":"+41 55 640 62 38",
    "sg:postcode":"8755",
    "sg:province":"Glarus",
    "wof:name":"Rudolf Loretan Vermessungsb\u00fcro",
    "wof:placetype":"venue"
},
  "geometry": {"coordinates":[9.0737571716,47.0341148376],"type":"Point"}
}