{
  "type": "Feature",
  "properties": {
    "iso:country":"CH",
    "sg:address":"M\u00fchlebachweg 6",
    "sg:city":"Zwingen",
    "sg:orig_category":"Kaminfeger",
    "sg:phone":"+41 79 344 77 50",
    "sg:postcode":"4222",
    "sg:province":"Basel-Landschaft",
    "wof:name":"Wilfried Wolfensberger Kaminfegermeister",
    "wof:placetype":"venue"
},
  "geometry": {"coordinates":[7.531566143,47.4347038269],"type":"Point"}
}