{
  "type": "Feature",
  "properties": {
    "iso:country":"CH",
    "sg:address":"Rue De La Poste 8 1920 Martigny Case Postale 568",
    "sg:city":"Martigny",
    "sg:classifiers":[
        {
            "category":"Travel",
            "subcategory":"Hotels & Motels",
            "type":"Entertainment"
        }
    ],
    "sg:phone":"+41 27 722 14 44",
    "sg:postcode":"1920",
    "sg:province":"Valais",
    "sg:tags":[
        "hotels",
        "mit",
        "restaurant"
    ],
    "wof:name":"Brasserie De La Poste",
    "wof:placetype":"venue"
},
  "geometry": {"coordinates":[7.0759520531,46.1031951904],"type":"Point"}
}