{
  "type": "Feature",
  "properties": {
    "iso:country":"CH",
    "sg:address":"Zwinglistrasse 40",
    "sg:city":"Winterthur",
    "sg:orig_category":"Malerei",
    "sg:phone":"+41 52 233 10 48",
    "sg:postcode":"8400",
    "sg:province":"Z\u00fcrich",
    "wof:name":"G\u00fcnter Gugelmann Malergesch\u00e4ft",
    "wof:placetype":"venue"
},
  "geometry": {"coordinates":[8.7440071106,47.4907913208],"type":"Point"}
}