{
  "type": "Feature",
  "properties": {
    "iso:country":"CH",
    "sg:address":"Rue Pr\u00e9 Borvey 8",
    "sg:city":"Martigny",
    "sg:orig_category":"Malerei",
    "sg:phone":"+41 71 377 10 85",
    "sg:postcode":"1920",
    "sg:province":"Valais",
    "wof:name":"Roland Nef Malergesch\u00e4ft",
    "wof:placetype":"venue"
},
  "geometry": {"coordinates":[9.975394249,48.1765937805],"type":"Point"}
}