{
  "type": "Feature",
  "properties": {
    "iso:country":"CH",
    "sg:address":"Neudietfurt 1 9615 Dietfurt. Postfach",
    "sg:city":"Dietfurt",
    "sg:orig_category":"Grosshandel mit Textilien Grosshandel mit sonstigen Konsumg\u00fctern",
    "sg:phone":"+41 71 980 05 80",
    "sg:postcode":"9615",
    "sg:province":"St. Gallen",
    "wof:name":"Rigotex Handels Ag",
    "wof:placetype":"venue"
},
  "geometry": {"coordinates":[9.0820560455,47.3455924988],"type":"Point"}
}