{
  "type": "Feature",
  "properties": {
    "iso:country":"CH",
    "sg:address":"Berthoudes Rue Des 28 2000 Neuch\u00e2tel. Postfach",
    "sg:city":"Neuch\u00e2tel",
    "sg:orig_category":"Detailhandel mit Waren verschiedener Art, Hauptrichtung Nahrungsmittel",
    "sg:phone":"+41 32 753 36 03",
    "sg:postcode":"2000",
    "sg:province":"Neuch\u00e2tel",
    "wof:name":"D.h. Distribution Hodel Daniel Exploit. D'un D\u00e9p\u00f4t Et Vente De Produits Alimentaires",
    "wof:placetype":"venue"
},
  "geometry": {"coordinates":[6.9634318352,47.0083694458],"type":"Point"}
}