{
  "type": "Feature",
  "properties": {
    "iso:country":"CH",
    "sg:address":"Bremgartenstrasse 119 3012 Bern. Postfach",
    "sg:city":"Bern",
    "sg:orig_category":"Wirtschaftsverb\u00e4nde Versicherungen, Krankenkassen",
    "sg:phone":"+41 31 302 34 34",
    "sg:postcode":"3001",
    "sg:province":"Bern",
    "wof:name":"Verband Bern.krankenh\u00e4user",
    "wof:placetype":"venue"
},
  "geometry": {"coordinates":[7.4274439812,46.9587936401],"type":"Point"}
}