{
  "type": "Feature",
  "properties": {
    "iso:country":"CH",
    "sg:address":"B\u00e4renmatte 24",
    "sg:city":"H\u00f6lstein",
    "sg:orig_category":"Allgemeiner Hoch U Tiefbau Strassenbau",
    "sg:phone":"+41 61 951 13 03",
    "sg:postcode":"4434",
    "sg:province":"Basel-Landschaft",
    "wof:name":"Gysin A. Ag",
    "wof:placetype":"venue"
},
  "geometry": {"coordinates":[7.76489,47.439644],"type":"Point"}
}