{
  "type": "Feature",
  "properties": {
    "iso:country":"CH",
    "sg:address":"Hauptstrasse 25",
    "sg:city":"Zihlschlacht",
    "sg:orig_category":"Detailhandel mit Waren verschiedener Art, Hauptrichtung Nahrungsmittel",
    "sg:phone":"+41 71 422 18 79",
    "sg:postcode":"8588",
    "sg:province":"Thurgau",
    "wof:name":"Mario Graf Dorfl\u00e4deli",
    "wof:placetype":"venue"
},
  "geometry": {"coordinates":[9.2586889267,47.519367218],"type":"Point"}
}