{
  "type": "Feature",
  "properties": {
    "iso:country":"CH",
    "sg:address":"Hofstettenstrasse 14",
    "sg:city":"Ettingen",
    "sg:orig_category":"Werbung",
    "sg:postcode":"4107",
    "sg:province":"Basel-Landschaft",
    "wof:name":"Heyne Werbung",
    "wof:placetype":"venue"
},
  "geometry": {"coordinates":[7.5457911491,47.4763374329],"type":"Point"}
}