{
  "type": "Feature",
  "properties": {
    "iso:country":"CH",
    "sg:address":"Panoramastrasse 354",
    "sg:city":"Bottenwil",
    "sg:orig_category":"Sanit\u00e4r, Heizungs U L\u00fcftungsinstallation Sanit\u00e4rinstallation",
    "sg:phone":"+41 71 311 19 25",
    "sg:postcode":"4814",
    "sg:province":"Aargau",
    "wof:name":"A - Z Sanit\u00e4r Gmbh",
    "wof:placetype":"venue"
},
  "geometry": {"coordinates":[9.3191003799,47.4219245911],"type":"Point"}
}