{
  "type": "Feature",
  "properties": {
    "iso:country":"CH",
    "sg:address":"Juravorstadt 1 2502 Biel/bienne. Postfach",
    "sg:city":"Biel/bienne",
    "sg:orig_category":"Vermietung U Verpachtung von eigenen Immobilien",
    "sg:postcode":"2502",
    "sg:province":"Bern",
    "wof:name":"Immobilien Ag Juravorstadt",
    "wof:placetype":"venue"
},
  "geometry": {"coordinates":[7.2469830513,47.1430091858],"type":"Point"}
}