{
  "type": "Feature",
  "properties": {
    "iso:country":"CH",
    "sg:address":"Rue Du Vieux-coll\u00e8ge 10",
    "sg:city":"Gen\u00e8ve",
    "sg:orig_category":"Finanzierungsinstitutionen",
    "sg:postcode":"1204",
    "sg:province":"Gen\u00e8ve",
    "wof:name":"Venture Vision Schweiz Ag",
    "wof:placetype":"venue"
},
  "geometry": {"coordinates":[9.8168935776,46.7949028015],"type":"Point"}
}