{
  "type": "Feature",
  "properties": {
    "iso:country":"CH",
    "sg:address":"Dorf",
    "sg:city":"Krummenau",
    "sg:orig_category":"RESTAURANTS: TEA-ROOMS",
    "sg:postcode":"9643",
    "sg:province":"St. Gallen",
    "wof:name":"Rest. Sonne Peter B\u00f6sch",
    "wof:placetype":"venue"
},
  "geometry": {"coordinates":[9.1713256836,47.2484703064],"type":"Point"}
}