{
  "type": "Feature",
  "properties": {
    "iso:country":"CH",
    "sg:address":"Talstrasse 56",
    "sg:city":"Altendorf",
    "sg:orig_category":"Detailhandel mit S\u00e4uglings U Kinderbekleidung Sonstiger Fachdetailhandel in Verkaufsr\u00e4umen",
    "sg:phone":"+41 55 442 40 62",
    "sg:postcode":"8852",
    "sg:province":"Schwyz",
    "wof:name":"Kinderwarenb\u00f6rse Erika Knobel",
    "wof:placetype":"venue"
},
  "geometry": {"coordinates":[8.8077392578,47.1943130493],"type":"Point"}
}