{
  "type": "Feature",
  "properties": {
    "iso:country":"CH",
    "sg:address":"6760",
    "sg:city":"Faido",
    "sg:orig_category":"Grosshandel mit festen Brennstoffen U Mineral\u00f6lerzeugnissen",
    "sg:postcode":"6760",
    "sg:province":"Ticino",
    "wof:name":"Gindroz A., Combustibles",
    "wof:placetype":"venue"
},
  "geometry": {"coordinates":[6.5165348053,46.6599502563],"type":"Point"}
}