{
  "type": "Feature",
  "properties": {
    "iso:country":"CH",
    "sg:address":"Ginnasio Via 6982 Agno. Postfach",
    "sg:city":"Agno",
    "sg:orig_category":"Vermietung U Verpachtung von eigenen Immobilien",
    "sg:postcode":"6982",
    "sg:province":"Ticino",
    "wof:name":"Vitulla Sa Immobili Ecc",
    "wof:placetype":"venue"
},
  "geometry": {"coordinates":[8.8993301392,45.9967536926],"type":"Point"}
}