{
  "type": "Feature",
  "properties": {
    "iso:country":"CH",
    "sg:address":"Chemin Des Maladi\u00e8res",
    "sg:city":"Bevaix",
    "sg:classifiers":[
        {
            "category":"Travel",
            "subcategory":"Hotels & Motels",
            "type":"Entertainment"
        }
    ],
    "sg:phone":"+41 34 447 48 48",
    "sg:postcode":"2022",
    "sg:province":"Neuch\u00e2tel",
    "sg:tags":[
        "hotels",
        "mit",
        "restaurant"
    ],
    "wof:name":"Hp Hotel Promotions Ag",
    "wof:placetype":"venue"
},
  "geometry": {"coordinates":[7.5851860046,47.0828590393],"type":"Point"}
}