{
  "type": "Feature",
  "properties": {
    "iso:country":"CH",
    "sg:address":"Hauptstrasse 79",
    "sg:city":"Villigen",
    "sg:orig_category":"Detailhandel mit M\u00f6beln Detailhandel mit M\u00f6beln U Haushaltsgegenst\u00e4nden",
    "sg:phone":"+41 56 284 11 33",
    "sg:postcode":"5234",
    "sg:province":"Aargau",
    "wof:name":"Baumann M\u00f6bel + Co",
    "wof:placetype":"venue"
},
  "geometry": {"coordinates":[8.214676857,47.5285568237],"type":"Point"}
}