{
  "type": "Feature",
  "properties": {
    "iso:country":"CH",
    "sg:address":"Bahnhofstrasse 2",
    "sg:city":"Mettmenstetten",
    "sg:orig_category":"Arztpraxen",
    "sg:phone":"+41 17671550",
    "sg:postcode":"8932",
    "sg:province":"Z\u00fcrich",
    "wof:name":"Dr.med.peter Barben Arzt F.allgemeine Medizin Fmh",
    "wof:placetype":"venue"
},
  "geometry": {"coordinates":[8.462434,47.243755],"type":"Point"}
}