{
  "type": "Feature",
  "properties": {
    "iso:country":"CH",
    "sg:address":"Breitenstrasse 1 5303 W\u00fcrenlingen. Postfach 15",
    "sg:city":"W\u00fcrenlingen",
    "sg:orig_category":"Werbevermittlung Werbung",
    "sg:phone":"+41 56 631 88 31",
    "sg:postcode":"5303",
    "sg:province":"Aargau",
    "wof:name":"Blumer Dieter, Werbeagentur",
    "wof:placetype":"venue"
},
  "geometry": {"coordinates":[8.3470573425,47.3610343933],"type":"Point"}
}