{
  "type": "Feature",
  "properties": {
    "iso:country":"CH",
    "sg:address":"Via Ai Saleggi 14b 6600 Locarno. Postfach",
    "sg:city":"Locarno",
    "sg:orig_category":"Vermietung U Verpachtung von eigenen Immobilien Vermittlung von Immobilien",
    "sg:phone":"+41 91 760 03 80",
    "sg:postcode":"6601",
    "sg:province":"Ticino",
    "wof:name":"Immobiliare Pedrazzini Sagl",
    "wof:placetype":"venue"
},
  "geometry": {"coordinates":[8.7939252853,46.1645889282],"type":"Point"}
}