{
  "type": "Feature",
  "properties": {
    "iso:country":"CH",
    "sg:address":"3763",
    "sg:city":"D\u00e4rstetten",
    "sg:orig_category":"Primarschulen",
    "sg:phone":"+41 33 783 16 44",
    "sg:postcode":"3763",
    "sg:province":"Bern",
    "wof:name":"Primarschule",
    "wof:placetype":"venue"
},
  "geometry": {"coordinates":[7.4962677956,46.658405304],"type":"Point"}
}