{
  "type": "Feature",
  "properties": {
    "iso:country":"CH",
    "sg:address":"Riehenstrasse 250",
    "sg:city":"Basel",
    "sg:orig_category":"Detailhandel mit Blumen U Pflanzen Detailhandel mit Zeitungen U Zeitschriften Kioske",
    "sg:phone":"+41 61 691 71 76",
    "sg:postcode":"4058",
    "sg:province":"Basel-Stadt",
    "wof:name":"Dieter B\u00fcrgin Blumenkiosk Hirzbrunnen",
    "wof:placetype":"venue"
},
  "geometry": {"coordinates":[7.611967,47.56739],"type":"Point"}
}