{
  "type": "Feature",
  "properties": {
    "iso:country":"CH",
    "sg:address":"Tourbillon Avenue De 1950 Sion. Postfach",
    "sg:city":"Sitten",
    "sg:orig_category":"Pensionskassen",
    "sg:postcode":"1950",
    "sg:province":"Valais",
    "wof:name":"Fondation Des Oeuvres Sociales De La F\u00e9d\u00e9ration Des Caves De Producteurs De Vins Du Valais Provins",
    "wof:placetype":"venue"
},
  "geometry": {"coordinates":[7.3653879166,46.238067627],"type":"Point"}
}