{
  "type": "Feature",
  "properties": {
    "iso:country":"CH",
    "sg:address":"Hauptstrasse 6",
    "sg:city":"Ober\u00e4geri",
    "sg:orig_category":"RESTAURANTS: TEA-ROOMS",
    "sg:postcode":"6315",
    "sg:province":"Zug",
    "wof:name":"Heidy Und Peter Gmbh",
    "wof:placetype":"venue"
},
  "geometry": {"coordinates":[8.6136102676,47.1351051331],"type":"Point"}
}