{
  "type": "Feature",
  "properties": {
    "iso:country":"CH",
    "sg:address":"Erlenauweg 15",
    "sg:city":"M\u00fcnsingen",
    "sg:orig_category":"Grosshandel mit sonstigen Konsumg\u00fctern Herstellung von Mess U Kontrollinstrumenten U vorrichtungen",
    "sg:phone":"+41 31 722 05 20",
    "sg:postcode":"3110",
    "sg:province":"Bern",
    "wof:name":"Terraillon-gewako Ag",
    "wof:placetype":"venue"
},
  "geometry": {"coordinates":[7.5605621338,46.8668746948],"type":"Point"}
}