{
  "type": "Feature",
  "properties": {
    "iso:country":"CH",
    "sg:address":"Ackerstrasse 54 8604 Volketswil. Postfach",
    "sg:city":"Volketswil",
    "sg:orig_category":"Grosshandel mit Eisenwaren sowie Installationsbedarf f\u00fcr Gas, Wasser U Heizung Grosshandel mit Masch",
    "sg:phone":"+41 19450306",
    "sg:postcode":"8604",
    "sg:province":"Z\u00fcrich",
    "wof:name":"Wespro, B\u00e4cher Andreas",
    "wof:placetype":"venue"
},
  "geometry": {"coordinates":[8.6687221527,47.3873558044],"type":"Point"}
}