{
  "type": "Feature",
  "properties": {
    "iso:country":"CH",
    "sg:address":"Grundstrasse 11",
    "sg:city":"Ossingen",
    "sg:orig_category":"Detailhandel mit elektrischen Haushalts-,Radio U Fernsehger\u00e4ten sowie Musikinstrumenten",
    "sg:postcode":"8475",
    "sg:province":"Z\u00fcrich",
    "wof:name":"Kerker Arthur, Tontr\u00e4ger-vertrieb",
    "wof:placetype":"venue"
},
  "geometry": {"coordinates":[8.7217178345,47.6142807007],"type":"Point"}
}