{
  "type": "Feature",
  "properties": {
    "addr:full":"Grittweg 9 Niederdorf Basel-Landschaft 4435",
    "addr:housenumber":"9",
    "addr:postcode":"4435",
    "addr:street":"Grittweg",
    "iso:country":"CH",
    "sg:address":"Grittweg 9",
    "sg:city":"Niederdorf",
    "sg:orig_category":"Bestattungswesen",
    "sg:phone":"+41 61 963 16 16",
    "sg:postcode":"4435",
    "sg:province":"Basel-Landschaft",
    "wof:name":"H.p. Dill Bestattungsinstitut",
    "wof:placetype":"venue"
},
  "geometry": {"coordinates":[7.752275,47.403183],"type":"Point"}
}