{
  "type": "Feature",
  "properties": {
    "iso:country":"CH",
    "sg:address":"Via Stazione 78",
    "sg:city":"Caslano",
    "sg:orig_category":"Detailhandel mit Waren verschiedener Art, Hauptrichtung Nahrungsmittel",
    "sg:phone":"+41 91 606 35 03",
    "sg:postcode":"6987",
    "sg:province":"Ticino",
    "wof:name":"Giordano & Brigitte Antonini Negozio Commestibili",
    "wof:placetype":"venue"
},
  "geometry": {"coordinates":[8.8764533997,45.9770812988],"type":"Point"}
}