{
  "type": "Feature",
  "properties": {
    "iso:country":"CH",
    "sg:address":"Shopping Center 11/9/1",
    "sg:city":"Spreitenbach",
    "sg:orig_category":"Handelsvermittlung U Grosshandel Sonstiger Grosshandel",
    "sg:phone":"+41 79 412 91 00",
    "sg:postcode":"8957",
    "sg:province":"Aargau",
    "wof:name":"Matex Import-export M.tejic",
    "wof:placetype":"venue"
},
  "geometry": {"coordinates":[8.3697423935,47.4222488403],"type":"Point"}
}