{
  "type": "Feature",
  "properties": {
    "iso:country":"CH",
    "sg:address":"Vincent Rue Dr-alfred- 10 1201 Gen\u00e8ve. Postfach",
    "sg:city":"Gen\u00e8ve",
    "sg:orig_category":"Betrieb U technische Hilfsdienste des Kultur U Unterhaltungswesens",
    "sg:postcode":"1201",
    "sg:province":"Gen\u00e8ve",
    "wof:name":"Art Diffusion S\u00e0rl",
    "wof:placetype":"venue"
},
  "geometry": {"coordinates":[6.1488,46.210098],"type":"Point"}
}