{
  "type": "Feature",
  "properties": {
    "iso:country":"CH",
    "sg:address":"Dorfstrasse 10",
    "sg:city":"Itingen",
    "sg:orig_category":"Werbeagenturen",
    "sg:phone":"+41 61 971 26 97",
    "sg:postcode":"4452",
    "sg:province":"Basel-Landschaft",
    "wof:name":"Othmar Schmidt Werbung",
    "wof:placetype":"venue"
},
  "geometry": {"coordinates":[7.7848157883,47.4649276733],"type":"Point"}
}