{
  "type": "Feature",
  "properties": {
    "iso:country":"CH",
    "sg:address":"Haus Solaris",
    "sg:city":"Raron",
    "sg:orig_category":"Sanit\u00e4r, Heizungs U L\u00fcftungsinstallation",
    "sg:postcode":"3942",
    "sg:province":"Valais",
    "wof:name":"Fischer & Pomsler",
    "wof:placetype":"venue"
},
  "geometry": {"coordinates":[8.1783828735,47.2373428345],"type":"Point"}
}