{
  "type": "Feature",
  "properties": {
    "iso:country":"CH",
    "sg:address":"Neugutstrasse 933",
    "sg:city":"W\u00e4denswil",
    "sg:orig_category":"RESTAURANTS: TEA-ROOMS",
    "sg:phone":"+41 55 644 12 18",
    "sg:postcode":"8820",
    "sg:province":"Z\u00fcrich",
    "wof:name":"Restaurant Eidgenossen",
    "wof:placetype":"venue"
},
  "geometry": {"coordinates":[9.0734405518,46.9928474426],"type":"Point"}
}