{
  "type": "Feature",
  "properties": {
    "iso:country":"CH",
    "sg:address":"Hinterdorf 12",
    "sg:city":"Trogen",
    "sg:orig_category":"Vorschulen, Kinderg\u00e4rten",
    "sg:phone":"+41 71 344 17 92",
    "sg:postcode":"9043",
    "sg:province":"Appenzell Ausserrhoden",
    "wof:name":"Kindergarten Dorf",
    "wof:placetype":"venue"
},
  "geometry": {"coordinates":[9.4645853043,47.40883255],"type":"Point"}
}