{
  "type": "Feature",
  "properties": {
    "iso:country":"CH",
    "sg:address":"Alpenstrasse 13",
    "sg:city":"B\u00f6nigen",
    "sg:orig_category":"Herstellung von Hebezeugen U F\u00f6rdermitteln Herstellung von Metallerzeugnissen ohne Maschinenbau",
    "sg:phone":"+41 33 822 99 00",
    "sg:postcode":"3806",
    "sg:province":"Bern",
    "wof:name":"Air-hydraulic Martin Tschabold Hydraulik & Pneumatik",
    "wof:placetype":"venue"
},
  "geometry": {"coordinates":[7.8916788101,46.6834335327],"type":"Point"}
}