{
  "type": "Feature",
  "properties": {
    "addr:full":"Speichergasse 6 3000 Bern. Postfach Bern Bern 3005",
    "addr:housenumber":"6",
    "addr:postcode":"3000;postfach;3005",
    "addr:street":"Speichergasse",
    "iso:country":"CH",
    "sg:address":"Speichergasse 6 3000 Bern. Postfach",
    "sg:city":"Bern",
    "sg:orig_category":"Allgemeiner Hoch U Tiefbau",
    "sg:postcode":"3005",
    "sg:province":"Bern",
    "wof:name":"Cablex Ag",
    "wof:placetype":"venue"
},
  "geometry": {"coordinates":[7.442333,46.950535],"type":"Point"}
}