{
  "type": "Feature",
  "properties": {
    "iso:country":"CH",
    "sg:address":"Dorfgasse 16",
    "sg:city":"Arlesheim",
    "sg:orig_category":"Softwareentwicklung U beratung",
    "sg:postcode":"4144",
    "sg:province":"Basel-Landschaft",
    "wof:name":"Heller Informatik Gmbh",
    "wof:placetype":"venue"
},
  "geometry": {"coordinates":[7.6222238541,47.4927597046],"type":"Point"}
}