{
  "type": "Feature",
  "properties": {
    "iso:country":"CH",
    "sg:address":"Chemin De La Culturaz 27",
    "sg:city":"Ch\u00e2telard-lutry",
    "sg:orig_category":"Arztpraxen",
    "sg:phone":"+41 21 791 39 46",
    "sg:postcode":"1095",
    "sg:province":"Vaud",
    "wof:name":"Drs M\u00e9d.p.& M. Robert M\u00e9decins G\u00e9n\u00e9ralistes Fmh",
    "wof:placetype":"venue"
},
  "geometry": {"coordinates":[6.688895,46.502987],"type":"Point"}
}