{
  "type": "Feature",
  "properties": {
    "iso:country":"CH",
    "sg:address":"Rue Goetz-monin 17",
    "sg:city":"Gen\u00e8ve",
    "sg:orig_category":"Arztpraxen",
    "sg:phone":"+41 22 329 78 22",
    "sg:postcode":"1205",
    "sg:province":"Gen\u00e8ve",
    "wof:name":"Dr M\u00e9d. Antonios Frangos M\u00e9decin Sp\u00e9cialiste Fmh",
    "wof:placetype":"venue"
},
  "geometry": {"coordinates":[6.147165,46.194572],"type":"Point"}
}