{
  "type": "Feature",
  "properties": {
    "iso:country":"CH",
    "sg:address":"Chemin Du Levant 157",
    "sg:city":"Lausanne",
    "sg:orig_category":"Bestattungswesen",
    "sg:phone":"+41 21 625 07 77",
    "sg:postcode":"1007",
    "sg:province":"Vaud",
    "wof:name":"Pompes Fun\u00e8bres Cl\u00e9ment Sa",
    "wof:placetype":"venue"
},
  "geometry": {"coordinates":[6.653252,46.515701],"type":"Point"}
}