{
  "type": "Feature",
  "properties": {
    "iso:country":"CH",
    "sg:address":"Schwalbenstrasse 11",
    "sg:city":"Flawil",
    "sg:orig_category":"Sportvereine Wassersport Schwimmen",
    "sg:phone":"+41 71 393 63 53",
    "sg:postcode":"9230",
    "sg:province":"St. Gallen",
    "wof:name":"Ostschweizer Tauchclub Manta",
    "wof:placetype":"venue"
},
  "geometry": {"coordinates":[9.1742610931,47.4173278809],"type":"Point"}
}