{
  "type": "Feature",
  "properties": {
    "iso:country":"CH",
    "sg:address":"Gr\u00fcenaustrasse 11 9424 Rheineck. Postfach 145",
    "sg:city":"Rheineck",
    "sg:orig_category":"Wirtschaftspr\u00fcfung, Steuerberatung U Treuhand",
    "sg:phone":"+41 71 888 49 49",
    "sg:postcode":"9424",
    "sg:province":"St. Gallen",
    "wof:name":"Schwotzer Treuhand",
    "wof:placetype":"venue"
},
  "geometry": {"coordinates":[9.5883893967,47.4691123962],"type":"Point"}
}