{
  "type": "Feature",
  "properties": {
    "iso:country":"CH",
    "sg:address":"R\u00fcchligweg 65",
    "sg:city":"Riehen",
    "sg:orig_category":"Abwasserreinigung, Abfallbeseitigung U sonstige Entsorgung Kanalreinigung",
    "sg:phone":"+41 61 603 30 00",
    "sg:postcode":"4125",
    "sg:province":"Basel-Stadt",
    "wof:name":"Carotec Campinari & Co.",
    "wof:placetype":"venue"
},
  "geometry": {"coordinates":[7.63671,47.571281],"type":"Point"}
}