{
  "type": "Feature",
  "properties": {
    "iso:country":"CH",
    "sg:address":"Rosengasse 14",
    "sg:city":"Schaffhausen",
    "sg:orig_category":"Maler U Glasergewerbe Malerei",
    "sg:phone":"+41 52 625 11 43",
    "sg:postcode":"8200",
    "sg:province":"Schaffhausen",
    "wof:name":"Gilbert Bernath Malergesch\u00e4ft",
    "wof:placetype":"venue"
},
  "geometry": {"coordinates":[8.6342639923,47.694606781],"type":"Point"}
}