{
  "type": "Feature",
  "properties": {
    "iso:country":"CH",
    "sg:address":"Kohlplatz 1",
    "sg:city":"Heiden",
    "sg:orig_category":"G\u00fcterbef\u00f6rderung im Strassenverkehr",
    "sg:phone":"+41 71 891 19 93",
    "sg:postcode":"9410",
    "sg:province":"Appenzell Ausserrhoden",
    "wof:name":"Hans Frischknecht Ag, Transporte Heiden",
    "wof:placetype":"venue"
},
  "geometry": {"coordinates":[9.5345001221,47.4425582886],"type":"Point"}
}