{
  "type": "Feature",
  "properties": {
    "iso:country":"CH",
    "sg:address":"Hauensteinweg 12",
    "sg:city":"Bern",
    "sg:orig_category":"Bauingenieurb\u00fcros Sanit\u00e4r",
    "sg:phone":"+41 31 376 20 90",
    "sg:postcode":"3008",
    "sg:province":"Bern",
    "wof:name":"Linder + Partner Gmbh Fachingenieure + Planer",
    "wof:placetype":"venue"
},
  "geometry": {"coordinates":[7.42061,46.938576],"type":"Point"}
}