{
  "type": "Feature",
  "properties": {
    "iso:country":"CH",
    "sg:address":"Paulihof 1",
    "sg:city":"Vorderthal",
    "sg:orig_category":"Abbruch U Sprenggewerbe, Erdbewegungsarbeiten Erdbewegungsarbeiten",
    "sg:phone":"+41 55 446 12 04",
    "sg:postcode":"8857",
    "sg:province":"Schwyz",
    "wof:name":"Albert M\u00e4chler Aushub Transporte",
    "wof:placetype":"venue"
},
  "geometry": {"coordinates":[8.903406,47.121235],"type":"Point"}
}