{
  "type": "Feature",
  "properties": {
    "iso:country":"CH",
    "sg:address":"Rossfeldstrasse 61",
    "sg:city":"Bern",
    "sg:orig_category":"Vorschulen, Kinderg\u00e4rten",
    "sg:phone":"+41 31 301 22 04",
    "sg:postcode":"3004",
    "sg:province":"Bern",
    "wof:name":"Kindergarten Rossfeld Ii",
    "wof:placetype":"venue"
},
  "geometry": {"coordinates":[7.4446601868,46.9736480713],"type":"Point"}
}