{
  "type": "Feature",
  "properties": {
    "iso:country":"CH",
    "sg:address":"Gerr Via Ai 6807 Taverne. Postfach",
    "sg:city":"Taverne",
    "sg:orig_category":"Sonstiger Grosshandel",
    "sg:postcode":"6807",
    "sg:province":"Ticino",
    "wof:name":"Destille Rheinpark Looser Destillaten; Verkauf",
    "wof:placetype":"venue"
},
  "geometry": {"coordinates":[9.6337099075,47.4550514221],"type":"Point"}
}