{
  "type": "Feature",
  "properties": {
    "iso:country":"CH",
    "sg:address":"Via Giuseppe Motta 20",
    "sg:city":"Mendrisio",
    "sg:orig_category":"Institutionen f\u00fcr Behinderte",
    "sg:phone":"+41 91 648 22 76",
    "sg:postcode":"6850",
    "sg:province":"Ticino",
    "wof:name":"Fondazione Diamante Laboratorio La Linea",
    "wof:placetype":"venue"
},
  "geometry": {"coordinates":[8.971225,45.905701],"type":"Point"}
}