{
  "type": "Feature",
  "properties": {
    "iso:country":"CH",
    "sg:address":"Schl\u00f6sslistrasse 1d",
    "sg:city":"Ebikon",
    "sg:orig_category":"Gesundheitswesen",
    "sg:postcode":"6030",
    "sg:province":"Luzern",
    "wof:name":"Gesundheitspraxis Rossi Maria",
    "wof:placetype":"venue"
},
  "geometry": {"coordinates":[8.3379621506,47.0790634155],"type":"Point"}
}