{
  "type": "Feature",
  "properties": {
    "iso:country":"CH",
    "sg:address":"Via Cantonale",
    "sg:city":"Claro",
    "sg:orig_category":"Bauspenglerei Sanit\u00e4r, Heizungs U L\u00fcftungsinstallation",
    "sg:phone":"+41 79 240 43 67",
    "sg:postcode":"6702",
    "sg:province":"Ticino",
    "wof:name":"Trenta Sa Impianti Sanitari",
    "wof:placetype":"venue"
},
  "geometry": {"coordinates":[9.016418,46.265312],"type":"Point"}
}