{
  "type": "Feature",
  "properties": {
    "iso:country":"CH",
    "sg:address":"Hauptstrasse 4",
    "sg:city":"Pfyn",
    "sg:classifiers":[
        {
            "category":"Military Area",
            "subcategory":"Air Force Base",
            "type":"Public Place"
        }
    ],
    "sg:phone":"+41 52 765 12 33",
    "sg:postcode":"8505",
    "sg:province":"Thurgau",
    "sg:tags":[
        "arrester",
        "system",
        "lightning"
    ],
    "wof:name":"Alessi Gmbh",
    "wof:placetype":"venue"
},
  "geometry": {"coordinates":[8.9483690262,47.5939483643],"type":"Point"}
}