{
  "type": "Feature",
  "properties": {
    "iso:country":"CH",
    "sg:address":"Badenerstrasse 414",
    "sg:city":"Z\u00fcrich",
    "sg:orig_category":"Maler U Glasergewerbe",
    "sg:phone":"+41 18171920",
    "sg:postcode":"8001",
    "sg:province":"Z\u00fcrich",
    "wof:name":"Exakt M\u00fcller",
    "wof:placetype":"venue"
},
  "geometry": {"coordinates":[8.5070924759,47.3798217773],"type":"Point"}
}