{
  "type": "Feature",
  "properties": {
    "iso:country":"CH",
    "sg:address":"Hauptstrasse 31",
    "sg:city":"Hunzenschwil",
    "sg:orig_category":"Sportvereine Ski",
    "sg:phone":"+41 62 897 36 76",
    "sg:postcode":"5502",
    "sg:province":"Aargau",
    "wof:name":"Skiclub Sch\u00f6nenwerd",
    "wof:placetype":"venue"
},
  "geometry": {"coordinates":[8.1201925278,47.3870315552],"type":"Point"}
}