{
  "type": "Feature",
  "properties": {
    "iso:country":"CH",
    "sg:address":"Neumattstrasse 29",
    "sg:city":"Deitingen",
    "sg:orig_category":"Datenverarbeitungsdienste Sonstige mit der Informatik verbundene T\u00e4tigkeiten",
    "sg:phone":"+41 32 614 27 19",
    "sg:postcode":"4543",
    "sg:province":"Solothurn",
    "wof:name":"Ocs Walter Vogt Informatik Edv-beratung",
    "wof:placetype":"venue"
},
  "geometry": {"coordinates":[7.620767,47.2188],"type":"Point"}
}