{
  "type": "Feature",
  "properties": {
    "iso:country":"CH",
    "sg:address":"Klosterzelgstr. 28",
    "sg:city":"Brugg",
    "sg:classifiers":[
        {
            "category":"Utilities",
            "subcategory":"Electric",
            "type":"Services"
        }
    ],
    "sg:phone":"+41 56 460 33 33",
    "sg:postcode":"5201",
    "sg:province":"Aargau",
    "sg:tags":[
        "electricity",
        "electronic",
        "electrical",
        "equipment"
    ],
    "wof:name":"Brugg Kabel Ag",
    "wof:placetype":"venue"
},
  "geometry": {"coordinates":[8.2067642212,47.4841804504],"type":"Point"}
}