{
  "type": "Feature",
  "properties": {
    "iso:country":"CH",
    "sg:address":"Vers La Beuchille",
    "sg:city":"Rossemaison",
    "sg:orig_category":"Betrieb von Taxis",
    "sg:phone":"+41 32 422 13 13",
    "sg:postcode":"2842",
    "sg:province":"Jura",
    "wof:name":"Atd Entreprise De Taxis, Frund Pierre Et Paulette",
    "wof:placetype":"venue"
},
  "geometry": {"coordinates":[7.346602,47.351948],"type":"Point"}
}