{
  "type": "Feature",
  "properties": {
    "iso:country":"CH",
    "sg:address":"3044",
    "sg:city":"Innerberg",
    "sg:classifiers":[
        {
            "category":"Government",
            "subcategory":"Post Office",
            "type":"Public Place"
        }
    ],
    "sg:phone":"+41 31 829 01 03",
    "sg:postcode":"3044",
    "sg:province":"Bern",
    "sg:tags":[
        "die",
        "poststellen"
    ],
    "wof:name":"Die Post",
    "wof:placetype":"venue"
},
  "geometry": {"coordinates":[7.3046097755,46.9948501587],"type":"Point"}
}