{
  "type": "Feature",
  "properties": {
    "iso:country":"CH",
    "sg:address":"8883",
    "sg:city":"Quarten",
    "sg:classifiers":[
        {
            "category":"Travel",
            "subcategory":"Hotels & Motels",
            "type":"Entertainment"
        }
    ],
    "sg:phone":"+41 81 738 23 44",
    "sg:postcode":"8883",
    "sg:province":"St. Gallen",
    "sg:tags":[
        "hotels",
        "mit",
        "restaurant"
    ],
    "wof:name":"Hotel S\u00f6\u00f6gg\u00e4",
    "wof:placetype":"venue"
},
  "geometry": {"coordinates":[9.2411851883,47.1078948975],"type":"Point"}
}