{
  "type": "Feature",
  "properties": {
    "iso:country":"CH",
    "sg:address":"8805",
    "sg:city":"Richterswil",
    "sg:orig_category":"Verwertung von Milch",
    "sg:postcode":"8805",
    "sg:province":"Z\u00fcrich",
    "wof:name":"Sennh\u00fcttengenossenschaft Unterschwanden.",
    "wof:placetype":"venue"
},
  "geometry": {"coordinates":[8.7051200867,47.2075004578],"type":"Point"}
}