{
  "type": "Feature",
  "properties": {
    "iso:country":"CH",
    "sg:address":"1745 Lentigny Case Postale 30",
    "sg:city":"Lentigny",
    "sg:orig_category":"Sportvereine Ballsport Fussball",
    "sg:phone":"+41 26 477 30 52",
    "sg:postcode":"1745",
    "sg:province":"Fribourg",
    "wof:name":"Fc Lentigny",
    "wof:placetype":"venue"
},
  "geometry": {"coordinates":[7.0044398308,46.759059906],"type":"Point"}
}