{
  "type": "Feature",
  "properties": {
    "iso:country":"CH",
    "sg:address":"Sagi 4 3324 Hindelbank. Postfach 56",
    "sg:city":"Hindelbank",
    "sg:orig_category":"Grosshandel mit B\u00fcromaschinen Herstellung von Schreibwaren U B\u00fcrobedarf aus Papier, Karton U Pappe",
    "sg:phone":"+41 34 411 26 51",
    "sg:postcode":"3324",
    "sg:province":"Bern",
    "wof:name":"Marcel Meuwly",
    "wof:placetype":"venue"
},
  "geometry": {"coordinates":[7.5490708351,47.0366592407],"type":"Point"}
}