{
  "type": "Feature",
  "properties": {
    "iso:country":"CH",
    "sg:address":"Rue De Lausanne 140 1950 Sion Case Postale 184",
    "sg:city":"Sion",
    "sg:orig_category":"Instandhaltung U Reparatur von Automobilen",
    "sg:phone":"+41 79 214 01 71",
    "sg:postcode":"1951",
    "sg:province":"Valais",
    "wof:name":"Carrosserie Z\u00e9nith Sa",
    "wof:placetype":"venue"
},
  "geometry": {"coordinates":[7.3390111923,46.2273025513],"type":"Point"}
}