{
  "type": "Feature",
  "properties": {
    "iso:country":"CH",
    "sg:address":"Fischerhof 1",
    "sg:city":"Triengen",
    "sg:classifiers":[
        {
            "category":"Restaurant",
            "type":"Food & Drink"
        }
    ],
    "sg:phone":"+41 41 933 15 18",
    "sg:postcode":"6234",
    "sg:province":"Luzern",
    "wof:name":"Restaurant Fischerhof",
    "wof:placetype":"venue"
},
  "geometry": {"coordinates":[8.0748357773,47.2373199463],"type":"Point"}
}