{
  "type": "Feature",
  "properties": {
    "iso:country":"CH",
    "sg:address":"Schmitterstrasse 5 9444 Diepoldsau. Postfach",
    "sg:city":"Diepoldsau",
    "sg:orig_category":"Herstellung von gewirktem U gestricktem Stoff",
    "sg:phone":"+41 71 733 21 12",
    "sg:postcode":"9444",
    "sg:province":"St. Gallen",
    "wof:name":"E.t.tex, Tagwerker E. Stoff- U. Garnhandel, Bes. Mit Strickwaren",
    "wof:placetype":"venue"
},
  "geometry": {"coordinates":[9.659822464,47.3883056641],"type":"Point"}
}