{
  "type": "Feature",
  "properties": {
    "iso:country":"CH",
    "sg:address":"Unterwies",
    "sg:city":"Grabserberg",
    "sg:orig_category":"Herstellung von Frucht U Gem\u00fcses\u00e4ften",
    "sg:phone":"+41 81 771 32 46",
    "sg:postcode":"9472",
    "sg:province":"St. Gallen",
    "wof:name":"Zogg Gebr. Hans Und Peter, Mosterei Und Brennerei",
    "wof:placetype":"venue"
},
  "geometry": {"coordinates":[9.4268903732,47.1850814819],"type":"Point"}
}