{
  "type": "Feature",
  "properties": {
    "iso:country":"CH",
    "sg:address":"Hintere Oberdorfstrasse 11",
    "sg:city":"Herisau",
    "sg:orig_category":"Sanit\u00e4rinstallation Sanit\u00e4rinstallation U Spenglerei",
    "sg:phone":"+41 71 277 82 30",
    "sg:postcode":"9100",
    "sg:province":"Appenzell Ausserrhoden",
    "wof:name":"Alberto Petrillo Spenglerei/sanit\u00e4rservice",
    "wof:placetype":"venue"
},
  "geometry": {"coordinates":[9.3278436661,47.4038238525],"type":"Point"}
}