{
  "type": "Feature",
  "properties": {
    "iso:country":"CH",
    "sg:address":"Chemin Du Clos \u00e0 Golet 7",
    "sg:city":"Ch\u00e2tel-st-denis",
    "sg:orig_category":"Arztpraxen",
    "sg:phone":"+41 21 948 62 20",
    "sg:postcode":"1618",
    "sg:province":"Fribourg",
    "wof:name":"Dr M\u00e9d. Maria Reiff M\u00e9decin G\u00e9n\u00e9raliste",
    "wof:placetype":"venue"
},
  "geometry": {"coordinates":[6.898364,46.528606],"type":"Point"}
}