{
  "type": "Feature",
  "properties": {
    "iso:country":"CH",
    "sg:address":"Bellariastrasse 51",
    "sg:city":"Z\u00fcrich",
    "sg:orig_category":"Finanzierungsinstitutionen",
    "sg:phone":"+41 14822713",
    "sg:postcode":"8038",
    "sg:province":"Z\u00fcrich",
    "wof:name":"Biberstein Dime Box Petroleum 1985/1 & Co",
    "wof:placetype":"venue"
},
  "geometry": {"coordinates":[8.5303249359,47.3504486084],"type":"Point"}
}