{
  "type": "Feature",
  "properties": {
    "iso:country":"CH",
    "sg:address":"St. Margrethen",
    "sg:city":"St. Margrethen",
    "sg:classifiers":[
        {
            "category":"Banks & Credit Unions",
            "subcategory":"Bank",
            "type":"Services"
        }
    ],
    "sg:phone":"+41 71712013",
    "sg:postcode":"9430",
    "sg:province":"St. Gallen",
    "wof:name":"Sparkassa Berneck",
    "wof:placetype":"venue"
},
  "geometry": {"coordinates":[9.63487,47.451469],"type":"Point"}
}