{
  "type": "Feature",
  "properties": {
    "iso:country":"CH",
    "sg:address":"Bernstrasse 70",
    "sg:city":"Kehrsatz",
    "sg:orig_category":"Einbau von Schreinerwaren Herstellung von K\u00fcchenm\u00f6beln",
    "sg:postcode":"3122",
    "sg:province":"Bern",
    "wof:name":"Veriset K\u00fcchen Ag",
    "wof:placetype":"venue"
},
  "geometry": {"coordinates":[7.4680628777,46.9153671265],"type":"Point"}
}