{
  "type": "Feature",
  "properties": {
    "iso:country":"CH",
    "sg:address":"Sur Les Tilleuls",
    "sg:city":"Grandfontaine",
    "sg:orig_category":"Bauschreinerei Zimmerei, Ingenieurholzbau",
    "sg:phone":"+41 32 476 62 64",
    "sg:postcode":"2908",
    "sg:province":"Jura",
    "wof:name":"Ren\u00e9 Plumez & Fils Sa Menuiserie & Charpente",
    "wof:placetype":"venue"
},
  "geometry": {"coordinates":[6.937975,47.393429],"type":"Point"}
}