{
  "type": "Feature",
  "properties": {
    "iso:country":"CH",
    "sg:address":"F\u00fcrigen",
    "sg:city":"F\u00fcrigen",
    "sg:classifiers":[
        {
            "category":"Travel",
            "subcategory":"Hotels & Motels",
            "type":"Entertainment"
        }
    ],
    "sg:phone":"+41 41 618 69 69",
    "sg:postcode":"6363",
    "sg:province":"Nidwalden",
    "sg:tags":[
        "hotels",
        "business",
        "restaurant"
    ],
    "wof:name":"Hotel F\u00dcrigen Ag",
    "wof:placetype":"venue"
},
  "geometry": {"coordinates":[8.349866,46.982014],"type":"Point"}
}