{
  "type": "Feature",
  "properties": {
    "iso:country":"CH",
    "sg:address":"H\u00f6rnlistrasse 8 8494 Bauma. Postfach 160",
    "sg:city":"Bauma",
    "sg:orig_category":"Grosshandel mit Getreide, Saatgut U Futtermitteln Handelsvermittlung U Grosshandel",
    "sg:phone":"+41 52 386 30 90",
    "sg:postcode":"8494",
    "sg:province":"Z\u00fcrich",
    "wof:name":"Vhzs Vertriebs Und Handelszentrale Seifert",
    "wof:placetype":"venue"
},
  "geometry": {"coordinates":[8.8773498535,47.3676986694],"type":"Point"}
}