{
  "type": "Feature",
  "properties": {
    "iso:country":"CH",
    "sg:address":"Hasenmoosstrasse 49 6023 Rothenburg. Postfach",
    "sg:city":"Rothenburg",
    "sg:orig_category":"Mineral\u00f6lverarbeitung",
    "sg:postcode":"6023",
    "sg:province":"Luzern",
    "wof:name":"Clavad\u00e4tscher Roberto Gmbh",
    "wof:placetype":"venue"
},
  "geometry": {"coordinates":[9.836400032,46.4976921082],"type":"Point"}
}