{
  "type": "Feature",
  "properties": {
    "iso:country":"CH",
    "sg:address":"Malbun",
    "sg:city":"Triesenberg",
    "sg:orig_category":"HOTELS: MIT RESTAURANT Kongress- and Tagungshotels mit Restaurant",
    "sg:phone":"+423 263 29 44",
    "sg:postcode":"9497",
    "wof:name":"Hotel Malbunerhof",
    "wof:placetype":"venue"
},
  "geometry": {"coordinates":[9.6169672012,47.0942840576],"type":"Point"}
}