{
  "type": "Feature",
  "properties": {
    "iso:country":"CH",
    "sg:address":"Kreuzlingerstrasse",
    "sg:city":"Lengwil-oberhofen",
    "sg:orig_category":"Vermietung U Verpachtung von eigenen Immobilien",
    "sg:postcode":"8574",
    "sg:province":"Thurgau",
    "wof:name":"Gpl Immobilien Ag",
    "wof:placetype":"venue"
},
  "geometry": {"coordinates":[9.190164566,47.6278991699],"type":"Point"}
}