{
  "type": "Feature",
  "properties": {
    "iso:country":"CH",
    "sg:address":"Holzh\u00e4usernstrasse 2",
    "sg:city":"Menzingen",
    "sg:orig_category":"RESTAURANTS: TEA-ROOMS",
    "sg:phone":"+41 41 755 11 15",
    "sg:postcode":"6313",
    "sg:province":"Zug",
    "wof:name":"Rest. L\u00f6wen, D\u00f6scher G. & P.",
    "wof:placetype":"venue"
},
  "geometry": {"coordinates":[8.590473175,47.1786384583],"type":"Point"}
}