{
  "type": "Feature",
  "properties": {
    "iso:country":"CH",
    "sg:address":"Auwiesenstrasse 1 8406 Winterthur. Postfach 265",
    "sg:city":"Winterthur",
    "sg:orig_category":"Druck ohne Zeitungsdruck Papier U Kartongewerbe",
    "sg:phone":"+41 52 203 65 26",
    "sg:postcode":"8406",
    "sg:province":"Z\u00fcrich",
    "wof:name":"Weber Ag, Druckverarbeitung Und Versand",
    "wof:placetype":"venue"
},
  "geometry": {"coordinates":[8.710100174,47.4846725464],"type":"Point"}
}