{
  "type": "Feature",
  "properties": {
    "iso:country":"CH",
    "sg:address":"Erzenberg",
    "sg:city":"Schwellbrunn",
    "sg:orig_category":"Haltung von Schweinen",
    "sg:postcode":"9103",
    "sg:province":"Appenzell Ausserrhoden",
    "wof:name":"Delphax Ag.",
    "wof:placetype":"venue"
},
  "geometry": {"coordinates":[9.2144603729,47.3501205444],"type":"Point"}
}