{
  "type": "Feature",
  "properties": {
    "iso:country":"CH",
    "sg:address":"Industrie B\u00fcrerfeld 14",
    "sg:city":"Oberb\u00fcren",
    "sg:orig_category":"Grosshandel mit Uhren Herstellung von Radio U Fernsehger\u00e4ten sowie phono U videotechnischen Ger\u00e4ten",
    "sg:phone":"+41 71 955 90 10",
    "sg:postcode":"9245",
    "sg:province":"St. Gallen",
    "wof:name":"G + M Elektronik Ag",
    "wof:placetype":"venue"
},
  "geometry": {"coordinates":[9.1631736755,47.4511528015],"type":"Point"}
}