{
  "type": "Feature",
  "properties": {
    "iso:country":"CH",
    "sg:address":"Sportzentrum Aegetenstrasse",
    "sg:city":"Widnau",
    "sg:orig_category":"Sportvereine Ballsport Tennis",
    "sg:phone":"+41 26 652 15 08",
    "sg:postcode":"9443",
    "sg:province":"St. Gallen",
    "wof:name":"Tennis-club Romont",
    "wof:placetype":"venue"
},
  "geometry": {"coordinates":[6.9180788994,46.6949501038],"type":"Point"}
}