{
  "type": "Feature",
  "properties": {
    "iso:country":"CH",
    "sg:address":"Oberdorfstrasse 24",
    "sg:city":"R\u00fcmlang",
    "sg:orig_category":"Detailhandel mit Textilien Verlegen von Fussboden",
    "sg:phone":"+41 18171990",
    "sg:postcode":"8153",
    "sg:province":"Z\u00fcrich",
    "wof:name":"Manfred Wenger Innendekorationen",
    "wof:placetype":"venue"
},
  "geometry": {"coordinates":[8.5299949646,47.4507446289],"type":"Point"}
}