{
  "type": "Feature",
  "properties": {
    "iso:country":"CH",
    "sg:address":"Waldeggweg 6",
    "sg:city":"Sch\u00f6ftland",
    "sg:orig_category":"Detailhandel mit elektrischen Haushaltsger\u00e4ten",
    "sg:phone":"+41 62 721 17 85",
    "sg:postcode":"5040",
    "sg:province":"Aargau",
    "wof:name":"Heinz H\u00e4feli Pfaff-n\u00e4hmaschinen",
    "wof:placetype":"venue"
},
  "geometry": {"coordinates":[8.0491313934,47.3006210327],"type":"Point"}
}