{
  "type": "Feature",
  "properties": {
    "iso:country":"CH",
    "sg:address":"Fortunagasse 24",
    "sg:city":"Z\u00fcrich",
    "sg:orig_category":"Unternehmensberatung",
    "sg:phone":"+41 12118960",
    "sg:postcode":"8001",
    "sg:province":"Z\u00fcrich",
    "wof:name":"Ajp Tsch\u00fcmperlin Martin",
    "wof:placetype":"venue"
},
  "geometry": {"coordinates":[8.540140152,47.3733291626],"type":"Point"}
}