{
  "type": "Feature",
  "properties": {
    "iso:country":"CH",
    "sg:address":"1716 Plaffeien. Postfach",
    "sg:city":"Plaffeien",
    "sg:orig_category":"Herstellung von sonstigen landwirtschaftlichen Maschinen Mechanische Werkst\u00e4tten",
    "sg:phone":"+41 77343625",
    "sg:postcode":"1716",
    "sg:province":"Fribourg",
    "wof:name":"Gebr. Rappo Ag",
    "wof:placetype":"venue"
},
  "geometry": {"coordinates":[7.2868709564,46.7410163879],"type":"Point"}
}