{
  "type": "Feature",
  "properties": {
    "iso:country":"CH",
    "sg:address":"Deibergstrasse 19a",
    "sg:city":"Oppligen",
    "sg:orig_category":"Herstellung von Metallkonstruktionen Mechanische Werkst\u00e4tten",
    "sg:phone":"+41 31 781 21 61",
    "sg:postcode":"3629",
    "sg:province":"Bern",
    "wof:name":"Max Huber, Montagen, Mechanik & Tempor\u00e4rservice",
    "wof:placetype":"venue"
},
  "geometry": {"coordinates":[7.5946698189,46.8235702515],"type":"Point"}
}