{
  "type": "Feature",
  "properties": {
    "iso:country":"CH",
    "sg:address":"Romont Rue De 35",
    "sg:city":"Fribourg",
    "sg:orig_category":"Finanzierungsinstitutionen",
    "sg:postcode":"1700",
    "sg:province":"Fribourg",
    "wof:name":"South Western Finance Company Ltd",
    "wof:placetype":"venue"
},
  "geometry": {"coordinates":[7.1539649963,46.8043441772],"type":"Point"}
}