{
  "type": "Feature",
  "properties": {
    "iso:country":"CH",
    "sg:address":"Schulhausstrasse 17",
    "sg:city":"D\u00fcbendorf",
    "sg:orig_category":"Sanit\u00e4r U Heizungsinstallation Sanit\u00e4rinstallation",
    "sg:phone":"+41 52 318 26 26",
    "sg:postcode":"8600",
    "sg:province":"Z\u00fcrich",
    "wof:name":"Meco Haustechnik Ag",
    "wof:placetype":"venue"
},
  "geometry": {"coordinates":[8.6217975616,47.5472602844],"type":"Point"}
}