{
  "type": "Feature",
  "properties": {
    "iso:country":"CH",
    "sg:address":"M\u00fchlebachstrasse 13",
    "sg:city":"Baar",
    "sg:orig_category":"Sonstige Aktivit\u00e4ten der nicht-\u00e4rztlichen Medizinalberufe",
    "sg:phone":"+41 81 302 44 45",
    "sg:postcode":"6340",
    "sg:province":"Zug",
    "wof:name":"Anita Schmidt Kinesiologie",
    "wof:placetype":"venue"
},
  "geometry": {"coordinates":[9.5011463165,47.0130310059],"type":"Point"}
}