{
  "type": "Feature",
  "properties": {
    "iso:country":"CH",
    "sg:address":"Hauptstrasse 16",
    "sg:city":"Hendschiken",
    "sg:orig_category":"Innendekorationsateliers",
    "sg:phone":"+41 62 891 63 10",
    "sg:postcode":"5604",
    "sg:province":"Aargau",
    "wof:name":"Kurt Senn Innenausstattungen",
    "wof:placetype":"venue"
},
  "geometry": {"coordinates":[8.2185382843,47.3862762451],"type":"Point"}
}