{
  "type": "Feature",
  "properties": {
    "iso:country":"CH",
    "sg:address":"Rue Mauborget 7-9 1510 Moudon Case Postale 28",
    "sg:city":"Moudon",
    "sg:orig_category":"Grosshandel mit Erzen U Metallen",
    "sg:phone":"+41 21 905 23 81",
    "sg:postcode":"1510",
    "sg:province":"Vaud",
    "wof:name":"Braillard-fers Sa",
    "wof:placetype":"venue"
},
  "geometry": {"coordinates":[6.797396183,46.6680526733],"type":"Point"}
}