{
  "type": "Feature",
  "properties": {
    "iso:country":"CH",
    "sg:address":"Technikumstrasse 9 8400 Winterthur. Postfach 805",
    "sg:city":"Winterthur",
    "sg:orig_category":"Interessenvertretungen",
    "sg:postcode":"8400",
    "sg:province":"Z\u00fcrich",
    "wof:name":"Fidelio-fonds",
    "wof:placetype":"venue"
},
  "geometry": {"coordinates":[8.7287321091,47.4976158142],"type":"Point"}
}