{
  "type": "Feature",
  "properties": {
    "iso:country":"CH",
    "sg:address":"Pfaffenb\u00fchlweg 32",
    "sg:city":"Thun",
    "sg:orig_category":"Hundesalons",
    "sg:phone":"+41 33 336 93 41",
    "sg:postcode":"3604",
    "sg:province":"Bern",
    "wof:name":"Hundepflege Romy",
    "wof:placetype":"venue"
},
  "geometry": {"coordinates":[7.6298317909,46.7355041504],"type":"Point"}
}