{
  "type": "Feature",
  "properties": {
    "iso:country":"CH",
    "sg:address":"Bahnhofplatz 18 8840 Einsiedeln. Postfach",
    "sg:city":"Einsiedeln",
    "sg:orig_category":"Detailhandel mit Bekleidung Fachdetailhandel in Verkaufsr\u00e4umen",
    "sg:phone":"+41 55 412 21 88",
    "sg:postcode":"8840",
    "sg:province":"Schwyz",
    "wof:name":"Wisel K\u00e4lin-sport",
    "wof:placetype":"venue"
},
  "geometry": {"coordinates":[8.745466,47.128292],"type":"Point"}
}