{
  "type": "Feature",
  "properties": {
    "iso:country":"CH",
    "sg:address":"L\u00e4dergass 28",
    "sg:city":"Sch\u00fcpfheim",
    "sg:orig_category":"Maler U Glasergewerbe Malerei",
    "sg:phone":"+41 41 484 26 33",
    "sg:postcode":"6170",
    "sg:province":"Luzern",
    "wof:name":"Malergesch\u00e4ft Felder Gmbh",
    "wof:placetype":"venue"
},
  "geometry": {"coordinates":[8.0227069855,46.9556884766],"type":"Point"}
}