{
  "type": "Feature",
  "properties": {
    "iso:country":"CH",
    "sg:address":"Winkelriedstrasse 37",
    "sg:city":"St.gallen",
    "sg:orig_category":"Unclassifiable Establishments",
    "sg:phone":"+41 81 723 51 34",
    "sg:postcode":"9000",
    "sg:province":"St. Gallen",
    "wof:name":"Good Edi",
    "wof:placetype":"venue"
},
  "geometry": {"coordinates":[9.4115953445,47.0615463257],"type":"Point"}
}