{
  "type": "Feature",
  "properties": {
    "iso:country":"CH",
    "sg:address":"6110",
    "sg:city":"Wolhusen",
    "sg:orig_category":"Verwertung von Milch",
    "sg:phone":"+41 71 455 12 07",
    "sg:postcode":"6110",
    "sg:province":"Luzern",
    "wof:name":"Milchgenossenschaft Freidorf.",
    "wof:placetype":"venue"
},
  "geometry": {"coordinates":[9.3755149841,47.4928779602],"type":"Point"}
}