{
  "type": "Feature",
  "properties": {
    "iso:country":"CH",
    "sg:address":"Zugerstrasse 195 6314 Unter\u00e4geri. Postfach",
    "sg:city":"Unter\u00e4geri",
    "sg:orig_category":"Oberfl\u00e4chenveredlung U W\u00e4rmebehandlung",
    "sg:postcode":"6314",
    "sg:province":"Zug",
    "wof:name":"H. Achermann",
    "wof:placetype":"venue"
},
  "geometry": {"coordinates":[7.0892109871,46.7579231262],"type":"Point"}
}