{
  "type": "Feature",
  "properties": {
    "addr:full":"Moosstrasse 9 Pieterlen Bern 2542",
    "addr:housenumber":"9",
    "addr:postcode":"2542",
    "addr:street":"Moosstrasse",
    "iso:country":"CH",
    "sg:address":"Moosstrasse 9",
    "sg:city":"Pieterlen",
    "sg:classifiers":[
        {
            "category":"Autos & Motor Vehicles",
            "subcategory":"Fuel & Gas Station",
            "type":"Retail Goods"
        }
    ],
    "sg:phone":"+41 32 376 07 30",
    "sg:postcode":"2542",
    "sg:province":"Bern",
    "sg:tags":[
        "machine",
        "plant",
        "different",
        "special",
        "purpose"
    ],
    "wof:name":"Robert Seckler Ag",
    "wof:placetype":"venue"
},
  "geometry": {"coordinates":[7.318435,47.169952],"type":"Point"}
}