{
  "type": "Feature",
  "properties": {
    "iso:country":"CH",
    "sg:address":"Schulhausstrasse 17",
    "sg:city":"H\u00f6ri",
    "sg:orig_category":"Aktivit\u00e4ten der Krankenschwestern U Hebammen, Hauspflege Organisationen des Gesundheitswesen",
    "sg:phone":"+41 18601504",
    "sg:postcode":"8181",
    "sg:province":"Z\u00fcrich",
    "wof:name":"Spitex-dienste Kranken-& Hauspflege",
    "wof:placetype":"venue"
},
  "geometry": {"coordinates":[8.505016,47.508774],"type":"Point"}
}