{
  "type": "Feature",
  "properties": {
    "iso:country":"CH",
    "sg:address":"Bahnhofstrasse 16",
    "sg:city":"Othmarsingen",
    "sg:orig_category":"Unclassifiable Establishments",
    "sg:postcode":"5504",
    "sg:province":"Aargau",
    "wof:name":"La Macchia Zweirad-shop Ersatzteil-center",
    "wof:placetype":"venue"
},
  "geometry": {"coordinates":[8.2153949738,47.4065818787],"type":"Point"}
}