{
  "type": "Feature",
  "properties": {
    "iso:country":"CH",
    "sg:address":"3920",
    "sg:city":"Zermatt",
    "sg:orig_category":"Detailhandel mit B\u00fcchern Detailhandel mit B\u00fcchern, Zeitungen, Schreib U Papeteriewaren",
    "sg:phone":"+41 79 236 63 22",
    "sg:postcode":"3920",
    "sg:province":"Valais",
    "wof:name":"Juristische Buchhandlung Imperatori Bruno",
    "wof:placetype":"venue"
},
  "geometry": {"coordinates":[8.921343,47.240734],"type":"Point"}
}