{
  "type": "Feature",
  "properties": {
    "iso:country":"CH",
    "sg:address":"Seevorstadt 19 2502 Biel/bienne. Postfach",
    "sg:city":"Biel/bienne",
    "sg:orig_category":"RESTAURANTS: TEA-ROOMS",
    "sg:postcode":"2502",
    "sg:province":"Bern",
    "wof:name":"Klopfenstein Und Jacky Gastro-points",
    "wof:placetype":"venue"
},
  "geometry": {"coordinates":[7.2354669571,47.1360359192],"type":"Point"}
}