{
  "type": "Feature",
  "properties": {
    "iso:country":"CH",
    "sg:address":"Spelterinistrasse 17",
    "sg:city":"Bazenheid",
    "sg:orig_category":"Kinderkrippen U horte",
    "sg:phone":"+41 71 931 35 10",
    "sg:postcode":"9602",
    "sg:province":"St. Gallen",
    "wof:name":"Micarna Sa Kinderhort",
    "wof:placetype":"venue"
},
  "geometry": {"coordinates":[9.0644807816,47.4124069214],"type":"Point"}
}