{
  "type": "Feature",
  "properties": {
    "iso:country":"CH",
    "sg:address":"Route Du Chevalier 6",
    "sg:city":"Marly",
    "sg:orig_category":"Detailhandel mit Brot, Back U S\u00fcsswaren",
    "sg:phone":"+41 26 436 15 44",
    "sg:postcode":"1723",
    "sg:province":"Fribourg",
    "wof:name":"Joseph Wider Boulangerie & P\u00e2tisserie",
    "wof:placetype":"venue"
},
  "geometry": {"coordinates":[7.159979,46.77562],"type":"Point"}
}