{
  "type": "Feature",
  "properties": {
    "iso:country":"CH",
    "sg:address":"Rue De Berne 9",
    "sg:city":"Gen\u00e8ve",
    "sg:classifiers":[
        {
            "category":"Organizations",
            "subcategory":"Professional Association",
            "type":"Services"
        }
    ],
    "sg:phone":"+41 22 716 42 60",
    "sg:postcode":"1201",
    "sg:province":"Gen\u00e8ve",
    "sg:tags":[
        "environmental",
        "protection"
    ],
    "wof:name":"Elsatech Sa",
    "wof:placetype":"venue"
},
  "geometry": {"coordinates":[6.1446180344,46.209022522],"type":"Point"}
}