{
  "type": "Feature",
  "properties": {
    "iso:country":"CH",
    "sg:address":"Landstrasse 39",
    "sg:city":"Andelfingen",
    "sg:orig_category":"Gesundheitswesen Sonstiger Fachdetailhandel mit Nahrungsmitteln, Getr\u00e4nken U Tabak in Verkaufsr\u00e4umen",
    "sg:phone":"+41 52 317 29 33",
    "sg:postcode":"8450",
    "sg:province":"Z\u00fcrich",
    "wof:name":"Genossenschaft Lindenm\u00fchle Andelfingen",
    "wof:placetype":"venue"
},
  "geometry": {"coordinates":[8.6789102554,47.5946388245],"type":"Point"}
}