{
  "type": "Feature",
  "properties": {
    "iso:country":"CH",
    "sg:address":"Habsburgerstrasse 12",
    "sg:city":"Luzern",
    "sg:orig_category":"Pensionskassen",
    "sg:postcode":"6003",
    "sg:province":"Luzern",
    "wof:name":"Emmi-wohlfahrtsfonds",
    "wof:placetype":"venue"
},
  "geometry": {"coordinates":[8.3085699081,47.0474090576],"type":"Point"}
}