{
  "type": "Feature",
  "properties": {
    "iso:country":"CH",
    "sg:address":"Riet-center Wolfriet",
    "sg:city":"Mels",
    "sg:orig_category":"Detailhandel mit Bekleidung Textilveredlung",
    "sg:phone":"+41 81 710 08 40",
    "sg:postcode":"8887",
    "sg:province":"St. Gallen",
    "wof:name":"Switcher-shop Buser Boutique",
    "wof:placetype":"venue"
},
  "geometry": {"coordinates":[9.420965,47.045593],"type":"Point"}
}