{
  "type": "Feature",
  "properties": {
    "addr:full":"Birmensdorferstrasse 70 Urdorf Z\u00fcrich 8902",
    "addr:housenumber":"70",
    "addr:postcode":"8902",
    "addr:street":"Birmensdorferstrasse",
    "iso:country":"CH",
    "sg:address":"Birmensdorferstrasse 70",
    "sg:city":"Urdorf",
    "sg:orig_category":"Chemische Reinigung",
    "sg:phone":"+41 19104008",
    "sg:postcode":"8902",
    "sg:province":"Z\u00fcrich",
    "wof:name":"Terlinden Management Ag",
    "wof:placetype":"venue"
},
  "geometry": {"coordinates":[8.582147,47.317448],"type":"Point"}
}