{
  "type": "Feature",
  "properties": {
    "iso:country":"CH",
    "sg:address":"H\u00f6henstrasse 16a",
    "sg:city":"Wallisellen",
    "sg:orig_category":"Softwareentwicklung U beratung",
    "sg:phone":"+41 13126622",
    "sg:postcode":"8304",
    "sg:province":"Z\u00fcrich",
    "wof:name":"Isb Informatik M. Liechti",
    "wof:placetype":"venue"
},
  "geometry": {"coordinates":[8.5944471359,47.4199066162],"type":"Point"}
}