{
  "type": "Feature",
  "properties": {
    "iso:country":"CH",
    "sg:address":"Bahn 19",
    "sg:city":"Urn\u00e4sch",
    "sg:orig_category":"Nationale Postdienste",
    "sg:phone":"+41 71 364 12 86",
    "sg:postcode":"9107",
    "sg:province":"Appenzell Ausserrhoden",
    "wof:name":"Die Schweizerische Post",
    "wof:placetype":"venue"
},
  "geometry": {"coordinates":[9.285861969,47.3184700012],"type":"Point"}
}