{
  "type": "Feature",
  "properties": {
    "iso:country":"CH",
    "sg:address":"5613",
    "sg:city":"Hilfikon",
    "sg:orig_category":"Sportvereine Sch\u00fctzen",
    "sg:phone":"+41 56 631 78 73",
    "sg:postcode":"5613",
    "sg:province":"Aargau",
    "wof:name":"Sch\u00fctzengesellschaft",
    "wof:placetype":"venue"
},
  "geometry": {"coordinates":[8.2437000275,47.3325195312],"type":"Point"}
}