{
  "type": "Feature",
  "properties": {
    "iso:country":"CH",
    "sg:address":"Hauptstrasse 56a",
    "sg:city":"Kreuzlingen",
    "sg:orig_category":"Detailhandel mit Brillen U anderen Sehhilfen",
    "sg:phone":"+41 71 672 60 22",
    "sg:postcode":"8280",
    "sg:province":"Thurgau",
    "wof:name":"Frauenknecht Ag H\u00f6rberatung",
    "wof:placetype":"venue"
},
  "geometry": {"coordinates":[9.174558,47.649323],"type":"Point"}
}