{
  "type": "Feature",
  "properties": {
    "iso:country":"CH",
    "sg:address":"Hofstrasse 1a",
    "sg:city":"Zug",
    "sg:orig_category":"Kunststoff-Produkte",
    "sg:phone":"+41 41 712 23 62",
    "sg:postcode":"6300",
    "sg:province":"Zug",
    "wof:name":"4 B Recycling Ag",
    "wof:placetype":"venue"
},
  "geometry": {"coordinates":[8.5158700943,47.1615180969],"type":"Point"}
}