{
  "type": "Feature",
  "properties": {
    "iso:country":"CH",
    "sg:address":"Dorfstrasse 1",
    "sg:city":"Wabern",
    "sg:orig_category":"Herstellung von medizinischen U chirurgischen Ger\u00e4ten sowie orthop\u00e4dischen Vorrichtungen",
    "sg:phone":"+41 31 960 43 80",
    "sg:postcode":"3084",
    "sg:province":"Bern",
    "wof:name":"Xentech Ag",
    "wof:placetype":"venue"
},
  "geometry": {"coordinates":[7.4480371475,46.9300804138],"type":"Point"}
}