{
  "type": "Feature",
  "properties": {
    "iso:country":"CH",
    "sg:address":"Selfrangastrasse 40",
    "sg:city":"Klosters",
    "sg:classifiers":[
        {
            "category":"Travel",
            "subcategory":"Hotels & Motels",
            "type":"Entertainment"
        }
    ],
    "sg:phone":"+41 79 437 56 33",
    "sg:postcode":"7250",
    "sg:province":"Graubunden",
    "sg:tags":[
        "hotels",
        "mit",
        "restaurant"
    ],
    "wof:name":"Hotel Chlosterhof",
    "wof:placetype":"venue"
},
  "geometry": {"coordinates":[8.861620903,47.6592025757],"type":"Point"}
}