{
  "type": "Feature",
  "properties": {
    "iso:country":"CH",
    "sg:address":"Entschwil",
    "sg:city":"Diemtigen",
    "sg:classifiers":[
        {
            "category":"Travel",
            "subcategory":"Hotels & Motels",
            "type":"Entertainment"
        }
    ],
    "sg:postcode":"3754",
    "sg:province":"Bern",
    "sg:tags":[
        "hotels",
        "mit",
        "restaurant"
    ],
    "wof:name":"Ernst Erb",
    "wof:placetype":"venue"
},
  "geometry": {"coordinates":[7.5366091728,46.6116676331],"type":"Point"}
}