{
  "type": "Feature",
  "properties": {
    "iso:country":"CH",
    "sg:address":"Langr\u00fctistrasse 45",
    "sg:city":"Einsiedeln",
    "sg:orig_category":"Architektur U Ingenieurb\u00fcros Softwareentwicklung U beratung",
    "sg:phone":"+41 71 944 37 14",
    "sg:postcode":"8840",
    "sg:province":"Schwyz",
    "wof:name":"Arete Design Gmbh",
    "wof:placetype":"venue"
},
  "geometry": {"coordinates":[8.74276,47.121593],"type":"Point"}
}