{
  "type": "Feature",
  "properties": {
    "iso:country":"CH",
    "sg:address":"Hofstrasse 6",
    "sg:city":"Birsfelden",
    "sg:orig_category":"Reiseb\u00fcros U Reiseveranstalter",
    "sg:postcode":"4127",
    "sg:province":"Basel-Landschaft",
    "wof:name":"Rosic Reisen",
    "wof:placetype":"venue"
},
  "geometry": {"coordinates":[7.6256651878,47.5558624268],"type":"Point"}
}