{
  "type": "Feature",
  "properties": {
    "iso:country":"CH",
    "sg:address":"Rainsbergweg 11",
    "sg:city":"Signau",
    "sg:orig_category":"Arztpraxen",
    "sg:phone":"+41 34 497 15 15",
    "sg:postcode":"3534",
    "sg:province":"Bern",
    "wof:name":"Dr.med.lorenz Sommer Arzt F.allgemeine Medizin Fmh",
    "wof:placetype":"venue"
},
  "geometry": {"coordinates":[7.724413,46.922096],"type":"Point"}
}