{
  "type": "Feature",
  "properties": {
    "iso:country":"CH",
    "sg:address":"4704",
    "sg:city":"Wolfisberg",
    "sg:classifiers":[
        {
            "category":"Restaurant",
            "type":"Food & Drink"
        }
    ],
    "sg:phone":"+41 32 636 23 66",
    "sg:postcode":"4704",
    "sg:province":"Bern",
    "wof:name":"Restaurant Buechmatt",
    "wof:placetype":"venue"
},
  "geometry": {"coordinates":[7.6604208946,47.2725944519],"type":"Point"}
}