{
  "type": "Feature",
  "properties": {
    "iso:country":"CH",
    "sg:address":"1470 Estavayer-le-lac Case Postale 5",
    "sg:city":"Estavayer-le-lac",
    "sg:orig_category":"Sportvereine Ballsport Basketball",
    "sg:postcode":"1470",
    "sg:province":"Fribourg",
    "wof:name":"Bbc Estavayer",
    "wof:placetype":"venue"
},
  "geometry": {"coordinates":[6.8482789993,46.8487930298],"type":"Point"}
}