{
  "type": "Feature",
  "properties": {
    "iso:country":"CH",
    "sg:address":"Via Luserte 6 B",
    "sg:city":"Quartino",
    "sg:orig_category":"Sanit\u00e4rinstallation",
    "sg:phone":"+41 91 840 11 25",
    "sg:postcode":"6572",
    "sg:province":"Ticino",
    "wof:name":"Acqua Free Sa",
    "wof:placetype":"venue"
},
  "geometry": {"coordinates":[8.911614418,46.1510429382],"type":"Point"}
}