{
  "type": "Feature",
  "properties": {
    "iso:country":"CH",
    "sg:address":"J\u00f6chlerweg 4",
    "sg:city":"Baar",
    "sg:classifiers":[
        {
            "category":"Structure",
            "subcategory":"Warehouse",
            "type":"Public Place"
        }
    ],
    "sg:phone":"+41 41 761 03 80",
    "sg:postcode":"6340",
    "sg:province":"Zug",
    "sg:tags":[
        "chiller",
        "air-conditioning",
        "system"
    ],
    "wof:name":"Hensler Heizungen Ag",
    "wof:placetype":"venue"
},
  "geometry": {"coordinates":[8.526439,47.200397],"type":"Point"}
}