{
  "type": "Feature",
  "properties": {
    "iso:country":"CH",
    "sg:address":"Kirchfeldstrasse 44",
    "sg:city":"Emmen",
    "sg:orig_category":"Stukkateurgewerbe, Gipserei U Verputzerei",
    "sg:phone":"+41 41 280 15 55",
    "sg:postcode":"6032",
    "sg:province":"Luzern",
    "wof:name":"Vonmoos Oskar Ag, Gipser- & Malergesch\u00e4ft Zweigniederlassung Emmen",
    "wof:placetype":"venue"
},
  "geometry": {"coordinates":[8.2932758331,47.085357666],"type":"Point"}
}