{
  "type": "Feature",
  "properties": {
    "iso:country":"CH",
    "sg:address":"Chemin Charles-gide 6",
    "sg:city":"Lausanne",
    "sg:orig_category":"Physiotherapie",
    "sg:phone":"+41 21 617 45 33",
    "sg:postcode":"1006",
    "sg:province":"Vaud",
    "wof:name":"Joseph Morard Physioth\u00e9rapie",
    "wof:placetype":"venue"
},
  "geometry": {"coordinates":[6.638833046,46.5113792419],"type":"Point"}
}