{
  "type": "Feature",
  "properties": {
    "iso:country":"CH",
    "sg:address":"Grand-rue 26",
    "sg:city":"Nyon",
    "sg:classifiers":[
        {
            "category":"Structure",
            "subcategory":"Office Building",
            "type":"Public Place"
        }
    ],
    "sg:phone":"+41 22 990 09 50",
    "sg:postcode":"1260",
    "sg:province":"Vaud",
    "sg:tags":[
        "equipment",
        "alarm",
        "installation",
        "system"
    ],
    "wof:name":"Prodis Sarl",
    "wof:placetype":"venue"
},
  "geometry": {"coordinates":[6.23879,46.381554],"type":"Point"}
}