{
  "type": "Feature",
  "properties": {
    "iso:country":"CH",
    "sg:address":"Pfad 27",
    "sg:city":"Cham",
    "sg:orig_category":"Fussreflexzonenmassage",
    "sg:phone":"+41 27 456 46 91",
    "sg:postcode":"6330",
    "sg:province":"Zug",
    "wof:name":"Elisabeth Schiesser R\u00e9flexoth\u00e9rapie",
    "wof:placetype":"venue"
},
  "geometry": {"coordinates":[7.5278348923,46.2984352112],"type":"Point"}
}