{
  "type": "Feature",
  "properties": {
    "iso:country":"CH",
    "sg:address":"Holzmattstrasse 7",
    "sg:city":"Dietikon",
    "sg:orig_category":"Sonstige Institutionen des Sozialwesens ohne Beherbergung",
    "sg:phone":"+41 17408342",
    "sg:postcode":"8953",
    "sg:province":"Z\u00fcrich",
    "wof:name":"Liselotte Leuenberger S\u00e4uglingsf\u00fcrsorge",
    "wof:placetype":"venue"
},
  "geometry": {"coordinates":[8.401802063,47.3988838196],"type":"Point"}
}