{
  "type": "Feature",
  "properties": {
    "iso:country":"CH",
    "sg:address":"Retschenweg 3",
    "sg:city":"Titterten",
    "sg:orig_category":"Allgemeiner Hochbau Herstellung von Metallkonstruktionen",
    "sg:phone":"+41 79 644 63 60",
    "sg:postcode":"4425",
    "sg:province":"Basel-Landschaft",
    "wof:name":"Renotech Ag",
    "wof:placetype":"venue"
},
  "geometry": {"coordinates":[7.71364,47.402561],"type":"Point"}
}