{
  "type": "Feature",
  "properties": {
    "iso:country":"CH",
    "sg:address":"Rheinfelderstrasse 27",
    "sg:city":"M\u00f6hlin",
    "sg:orig_category":"Institutionen f\u00fcr psychosoziale F\u00e4lle",
    "sg:phone":"+41 61 851 00 52",
    "sg:postcode":"4313",
    "sg:province":"Aargau",
    "wof:name":"Wohngruppe R\u00fcchi",
    "wof:placetype":"venue"
},
  "geometry": {"coordinates":[7.8332719803,47.5565185547],"type":"Point"}
}