{
  "type": "Feature",
  "properties": {
    "iso:country":"CH",
    "sg:address":"Cormanon 5a.",
    "sg:city":"Villars-sur-gl\u00e2ne",
    "sg:orig_category":"Fachdetailhandel in Verkaufsr\u00e4umen",
    "sg:postcode":"1752",
    "sg:province":"Fribourg",
    "wof:name":"Bim Franz.",
    "wof:placetype":"venue"
},
  "geometry": {"coordinates":[7.1301960945,46.7948532104],"type":"Point"}
}