{
  "type": "Feature",
  "properties": {
    "iso:country":"CH",
    "sg:address":"Thunstrasse 3",
    "sg:city":"Schwarzenburg",
    "sg:orig_category":"Detailhandel mit Musikinstrumenten K\u00fcnstlerische Schulen",
    "sg:phone":"+41 56 441 19 13",
    "sg:postcode":"3150",
    "sg:province":"Bern",
    "wof:name":"Musik Bieri Ag",
    "wof:placetype":"venue"
},
  "geometry": {"coordinates":[8.2074422836,47.4795036316],"type":"Point"}
}