{
  "type": "Feature",
  "properties": {
    "iso:country":"CH",
    "sg:address":"Eisenbahnstrasse 1 3604 Thun. Postfach 8",
    "sg:city":"Thun",
    "sg:classifiers":[
        {
            "category":"Travel",
            "subcategory":"Hotels & Motels",
            "type":"Entertainment"
        }
    ],
    "sg:phone":"+41 33 334 73 47",
    "sg:postcode":"3604",
    "sg:province":"Bern",
    "sg:tags":[
        "hotels",
        "mit",
        "restaurant"
    ],
    "wof:name":"Hotel Alpha Sommerheim",
    "wof:placetype":"venue"
},
  "geometry": {"coordinates":[7.6273021698,46.7407875061],"type":"Point"}
}