{
  "type": "Feature",
  "properties": {
    "addr:full":"Via Delle Aie 1 Lugano Ticino 6900",
    "addr:housenumber":"1",
    "addr:postcode":"6900",
    "addr:street":"Via Delle Aie",
    "iso:country":"CH",
    "sg:address":"Via Delle Aie 1",
    "sg:city":"Lugano",
    "sg:orig_category":"Detailhandel mit Boden U Wandbel\u00e4gen ohne Teppiche Sonstiger Detailhandel mit Metallwaren, Anstrichm",
    "sg:postcode":"6900",
    "sg:province":"Ticino",
    "wof:name":"Zambaiti Traiding B.v. Amsterdam Succ. Di Lugano",
    "wof:placetype":"venue"
},
  "geometry": {"coordinates":[8.957862,46.01577],"type":"Point"}
}