{
  "type": "Feature",
  "properties": {
    "iso:country":"CH",
    "sg:address":"Oberhausenstrasse 47",
    "sg:city":"Wettswil",
    "sg:orig_category":"Herstellung von sonstigen elektrischen Ausr\u00fcstungen",
    "sg:postcode":"8907",
    "sg:province":"Z\u00fcrich",
    "wof:name":"S-access Gmbh",
    "wof:placetype":"venue"
},
  "geometry": {"coordinates":[8.4783334732,47.3373413086],"type":"Point"}
}