{
  "type": "Feature",
  "properties": {
    "iso:country":"CH",
    "sg:address":"Klosterplatz 8 4600 Olten. Postfach",
    "sg:city":"Olten",
    "sg:orig_category":"Bibliotheken U Archive Wohnheime",
    "sg:phone":"+41 62 206 15 50",
    "sg:postcode":"4601",
    "sg:province":"Solothurn",
    "wof:name":"Kapuzinerkloster",
    "wof:placetype":"venue"
},
  "geometry": {"coordinates":[7.903585,47.350567],"type":"Point"}
}