{
  "type": "Feature",
  "properties": {
    "iso:country":"CH",
    "sg:address":"Via Vite 3",
    "sg:city":"Stabio",
    "sg:classifiers":[
        {
            "category":"Shopping",
            "subcategory":"Clothing, Apparel, & Fashions",
            "type":"Retail Goods"
        }
    ],
    "sg:phone":"+41 91 641 76 41",
    "sg:postcode":"6855",
    "sg:province":"Ticino",
    "sg:tags":[
        "clothing",
        "fabric"
    ],
    "wof:name":"Stabio Textil Sa",
    "wof:placetype":"venue"
},
  "geometry": {"coordinates":[8.922579,45.841774],"type":"Point"}
}