{
  "type": "Feature",
  "properties": {
    "addr:full":"Adlerweg 4 B\u00f6nigen Bern 3806",
    "addr:housenumber":"4",
    "addr:postcode":"3806",
    "addr:street":"Adlerweg",
    "iso:country":"CH",
    "sg:address":"Adlerweg 4",
    "sg:city":"B\u00f6nigen",
    "sg:orig_category":"Freizeit, Sport",
    "sg:phone":"+41 33 822 97 82",
    "sg:postcode":"3806",
    "sg:province":"Bern",
    "wof:name":"Brienzerseelauf",
    "wof:placetype":"venue"
},
  "geometry": {"coordinates":[7.89529,46.687935],"type":"Point"}
}