{
  "type": "Feature",
  "properties": {
    "iso:country":"CH",
    "sg:address":"8423 Embrach-embraport. Postfach",
    "sg:city":"Embrach-embraport",
    "sg:orig_category":"G\u00fcterbef\u00f6rderung im Strassenverkehr Unternehmensberatung",
    "sg:phone":"+41 18663131",
    "sg:postcode":"8423",
    "sg:province":"Z\u00fcrich",
    "wof:name":"Cargocare Ag",
    "wof:placetype":"venue"
},
  "geometry": {"coordinates":[8.5941400528,47.5204467773],"type":"Point"}
}