{
  "type": "Feature",
  "properties": {
    "iso:country":"CH",
    "sg:address":"Hauptstrasse 10",
    "sg:city":"Engwilen",
    "sg:orig_category":"Unclassifiable Establishments",
    "sg:postcode":"8564",
    "sg:province":"Thurgau",
    "wof:name":"Pig-shop Gmbh",
    "wof:placetype":"venue"
},
  "geometry": {"coordinates":[9.0944976807,47.6167449951],"type":"Point"}
}