{
  "type": "Feature",
  "properties": {
    "iso:country":"CH",
    "sg:address":"Galgenried",
    "sg:city":"Stans",
    "sg:orig_category":"Einzelhandel mit Automobilteilen U Zubeh\u00f6r",
    "sg:phone":"+41 81 750 50 10",
    "sg:postcode":"6370",
    "sg:province":"Nidwalden",
    "wof:name":"Pneu Matti Ag",
    "wof:placetype":"venue"
},
  "geometry": {"coordinates":[9.4626941681,47.169380188],"type":"Point"}
}