{
  "type": "Feature",
  "properties": {
    "iso:country":"CH",
    "sg:address":"Surlej",
    "sg:city":"Silvaplana",
    "sg:orig_category":"Reiseb\u00fcros U Reiseveranstalter",
    "sg:postcode":"7513",
    "sg:province":"Graubunden",
    "wof:name":"Genossenschaft Auxilium",
    "wof:placetype":"venue"
},
  "geometry": {"coordinates":[9.8103103638,46.4589004517],"type":"Point"}
}