{
  "type": "Feature",
  "properties": {
    "iso:country":"CH",
    "sg:address":"Sch\u00f6ntalstrasse",
    "sg:city":"Engelburg",
    "sg:classifiers":[
        {
            "category":"Building & Trades",
            "subcategory":"Cleaning & Sanitation",
            "type":"Services"
        }
    ],
    "sg:phone":"+41 71 278 26 46",
    "sg:postcode":"9032",
    "sg:province":"St. Gallen",
    "sg:tags":[
        "disposal",
        "hazardous",
        "waste"
    ],
    "wof:name":"Georges Bleiker Gmbh",
    "wof:placetype":"venue"
},
  "geometry": {"coordinates":[9.3408107758,47.4460945129],"type":"Point"}
}