{
  "type": "Feature",
  "properties": {
    "iso:country":"CH",
    "sg:address":"Michel Rue Saint- 5",
    "sg:city":"Fribourg",
    "sg:orig_category":"Vermietung U Verpachtung von eigenen Immobilien",
    "sg:postcode":"1700",
    "sg:province":"Fribourg",
    "wof:name":"Logements Cht S\u00e0rl",
    "wof:placetype":"venue"
},
  "geometry": {"coordinates":[7.1564950943,46.8054771423],"type":"Point"}
}