{
  "type": "Feature",
  "properties": {
    "iso:country":"CH",
    "sg:address":"B\u00fcren 67 5272 Gansingen. Postfach",
    "sg:city":"Gansingen",
    "sg:orig_category":"Fachdetailhandel in Verkaufsr\u00e4umen",
    "sg:postcode":"5272",
    "sg:province":"Aargau",
    "wof:name":"Geisseler Fredy Exklusiv-zweiradzubeh\u00f6r Zweir\u00e4der U. Zweiradzubeh\u00f6r; Verkauf, Handel",
    "wof:placetype":"venue"
},
  "geometry": {"coordinates":[8.1384716034,47.5326423645],"type":"Point"}
}