{
  "type": "Feature",
  "properties": {
    "iso:country":"CH",
    "sg:address":"Weissbadstrasse 14",
    "sg:city":"Appenzell",
    "sg:orig_category":"Unternehmensberatung",
    "sg:phone":"+41 58 858 58 58",
    "sg:postcode":"9050",
    "sg:province":"Appenzell Innerhoden",
    "wof:name":"Holcim Group Support Ltd",
    "wof:placetype":"venue"
},
  "geometry": {"coordinates":[8.1644287109,47.4312133789],"type":"Point"}
}