{
  "type": "Feature",
  "properties": {
    "iso:country":"CH",
    "sg:address":"Aegeristrasse 4 6300 Zug. Postfach 836",
    "sg:city":"Zug",
    "sg:orig_category":"Unternehmensberatung",
    "sg:phone":"+41 41 711 82 22",
    "sg:postcode":"6301",
    "sg:province":"Zug",
    "wof:name":"In Treu Ag Treuhand Gesellschaft Ag",
    "wof:placetype":"venue"
},
  "geometry": {"coordinates":[8.516084671,47.1660346985],"type":"Point"}
}