{
  "type": "Feature",
  "properties": {
    "iso:country":"CH",
    "sg:address":"R\u00e4mistrasse 27",
    "sg:city":"Z\u00fcrich",
    "sg:orig_category":"M\u00f6belschreinereien",
    "sg:phone":"+41 13818696",
    "sg:postcode":"8001",
    "sg:province":"Z\u00fcrich",
    "wof:name":"J\u00fcrg Nutz",
    "wof:placetype":"venue"
},
  "geometry": {"coordinates":[8.547162056,47.3685798645],"type":"Point"}
}