{
  "type": "Feature",
  "properties": {
    "iso:country":"CH",
    "sg:address":"Route De Saint-julien 78",
    "sg:city":"Grand-lancy",
    "sg:orig_category":"Instandhaltung U Reparatur von Automobilen",
    "sg:phone":"+41 22 301 11 11",
    "sg:postcode":"1212",
    "sg:province":"Gen\u00e8ve",
    "wof:name":"B & J Automobiles Sarl",
    "wof:placetype":"venue"
},
  "geometry": {"coordinates":[6.1266708374,46.1729812622],"type":"Point"}
}