{
  "type": "Feature",
  "properties": {
    "iso:country":"CH",
    "sg:address":"Sandacker 154 8112 Otelfingen. Postfach 16",
    "sg:city":"Otelfingen",
    "sg:orig_category":"Herstellung von Werkzeugmaschinen",
    "sg:postcode":"8112",
    "sg:province":"Z\u00fcrich",
    "wof:name":"Vem Tools Sa",
    "wof:placetype":"venue"
},
  "geometry": {"coordinates":[6.6145381927,46.9093551636],"type":"Point"}
}