{
  "type": "Feature",
  "properties": {
    "iso:country":"CH",
    "sg:address":"Binzm\u00fchlestrasse 405/7",
    "sg:city":"Z\u00fcrich",
    "sg:orig_category":"Zahnarztpraxen",
    "sg:phone":"+41 71 222 07 07",
    "sg:postcode":"8046",
    "sg:province":"Z\u00fcrich",
    "wof:name":"Dr. Med. Dent. Erwin T. Egloff Zahnarzt",
    "wof:placetype":"venue"
},
  "geometry": {"coordinates":[9.3727874756,47.4262809753],"type":"Point"}
}