{
  "type": "Feature",
  "properties": {
    "iso:country":"CH",
    "sg:address":"Badenerstrasse 812",
    "sg:city":"Z\u00fcrich",
    "sg:orig_category":"Markt U Meinungsforschung",
    "sg:phone":"+41 62 797 25 89",
    "sg:postcode":"8048",
    "sg:province":"Z\u00fcrich",
    "wof:name":"T-marketing Gmbh",
    "wof:placetype":"venue"
},
  "geometry": {"coordinates":[7.9599142075,47.3240432739],"type":"Point"}
}