{
  "type": "Feature",
  "properties": {
    "iso:country":"CH",
    "sg:address":"S\u00e4ge 2",
    "sg:city":"Altendorf",
    "sg:orig_category":"Grosshandel mit sonstigen Maschinen U Ausr\u00fcstungen f\u00fcr Industrie, Handel U Schiffahrt Handelsvermitt",
    "sg:phone":"+41 21 636 22 36",
    "sg:postcode":"8852",
    "sg:province":"Schwyz",
    "wof:name":"Bt (switzerland) Sa Machines Manutention Palettes",
    "wof:placetype":"venue"
},
  "geometry": {"coordinates":[6.5901060104,46.5287284851],"type":"Point"}
}