{
  "type": "Feature",
  "properties": {
    "iso:country":"CH",
    "sg:address":"Im Bildstei 6",
    "sg:city":"D\u00f6rflingen",
    "sg:orig_category":"Herstellung von industriellen Prozesssteuerungsanlagen",
    "sg:phone":"+41 52 657 46 10",
    "sg:postcode":"8239",
    "sg:province":"Schaffhausen",
    "wof:name":"Keller System-technik",
    "wof:placetype":"venue"
},
  "geometry": {"coordinates":[8.7213029861,47.7089653015],"type":"Point"}
}