{
  "type": "Feature",
  "properties": {
    "iso:country":"CH",
    "sg:address":"Lauetstrasse 33 8112 Otelfingen. Postfach",
    "sg:city":"Otelfingen",
    "sg:orig_category":"Herstellung von Metallkonstruktionen",
    "sg:phone":"+41 18450172",
    "sg:postcode":"8112",
    "sg:province":"Z\u00fcrich",
    "wof:name":"Isoglas Ag Metallbaukomponenten, Verglasungstechnik U. Zubeh\u00f6r; Planung, Herstellung, Montage, Handel",
    "wof:placetype":"venue"
},
  "geometry": {"coordinates":[8.4078330994,47.4568939209],"type":"Point"}
}