{
  "type": "Feature",
  "properties": {
    "iso:country":"CH",
    "sg:address":"Lenzburgerstrasse 2 5702 Niederlenz. Postfach",
    "sg:city":"Niederlenz",
    "sg:orig_category":"Sonstiger Grosshandel",
    "sg:postcode":"5702",
    "sg:province":"Aargau",
    "wof:name":"Fricker J\u00f6rg + Strazzarino Peter, Www.rampenverkauf.ch Onlineshop, Warenhandel",
    "wof:placetype":"venue"
},
  "geometry": {"coordinates":[8.177564621,47.3990745544],"type":"Point"}
}