{
  "type": "Feature",
  "properties": {
    "iso:country":"CH",
    "sg:address":"Baselstrasse 9",
    "sg:city":"Zwingen",
    "sg:orig_category":"Detailhandel mit M\u00f6beln U Haushaltsgegenst\u00e4nden",
    "sg:postcode":"4222",
    "sg:province":"Basel-Landschaft",
    "wof:name":"Bom\u00d6 Zwingen, Novakovic Und Hensler",
    "wof:placetype":"venue"
},
  "geometry": {"coordinates":[7.5329499245,47.4395294189],"type":"Point"}
}