{
  "type": "Feature",
  "properties": {
    "iso:country":"CH",
    "sg:address":"Stigelen 9651 Ennetb\u00fchl. Postfach",
    "sg:city":"Ennetb\u00fchl",
    "sg:orig_category":"Verwaltung von Immobilien",
    "sg:postcode":"9651",
    "sg:province":"St. Gallen",
    "wof:name":"Manerba Gmbh",
    "wof:placetype":"venue"
},
  "geometry": {"coordinates":[9.2110414505,47.2402038574],"type":"Point"}
}