{
  "type": "Feature",
  "properties": {
    "iso:country":"CH",
    "sg:address":"6523 Preonzo. Postfach Caselle Postale 38",
    "sg:city":"Preonzo",
    "sg:orig_category":"Sportvereine Ballsport Fussball",
    "sg:phone":"+41 91 863 19 56",
    "sg:postcode":"6523",
    "sg:province":"Ticino",
    "wof:name":"Fc Preonzo",
    "wof:placetype":"venue"
},
  "geometry": {"coordinates":[8.9998292923,46.2651481628],"type":"Point"}
}