{
  "type": "Feature",
  "properties": {
    "iso:country":"CH",
    "sg:address":"B\u00fc\u00fcndering 1",
    "sg:city":"Fraubrunnen",
    "sg:orig_category":"Gesundheitswesen",
    "sg:phone":"+41 79 652 79 69",
    "sg:postcode":"3312",
    "sg:province":"Bern",
    "wof:name":"Vitagard Gmbh Handelst\u00e4tigkeit U. Dienstleistungen Im Bereich Gesundheit, Ern\u00e4hrung, Kosmetik U. Massage Usw.",
    "wof:placetype":"venue"
},
  "geometry": {"coordinates":[7.5295948982,47.0848999023],"type":"Point"}
}