{
  "type": "Feature",
  "properties": {
    "iso:country":"CH",
    "sg:address":"Dorfstrasse 30",
    "sg:city":"Emmetten",
    "sg:orig_category":"Nationale Postdienste",
    "sg:phone":"+41 41 620 12 22",
    "sg:postcode":"6376",
    "sg:province":"Nidwalden",
    "wof:name":"Die Schweizerische Post",
    "wof:placetype":"venue"
},
  "geometry": {"coordinates":[8.5155935287,46.9562721252],"type":"Point"}
}