{
  "type": "Feature",
  "properties": {
    "iso:country":"CH",
    "sg:address":"Sonnenstrasse 35",
    "sg:city":"Kreuzlingen",
    "sg:orig_category":"Elektroinstallation",
    "sg:phone":"+41 71 677 50 50",
    "sg:postcode":"8280",
    "sg:province":"Thurgau",
    "wof:name":"Peyer R. Ag",
    "wof:placetype":"venue"
},
  "geometry": {"coordinates":[9.1718349457,47.6466712952],"type":"Point"}
}