{
  "type": "Feature",
  "properties": {
    "iso:country":"CH",
    "sg:address":"Hasenmoosstrasse 417",
    "sg:city":"Egliswil",
    "sg:classifiers":[
        {
            "category":"Autos & Motor Vehicles",
            "subcategory":"Auto Supplies",
            "type":"Retail Goods"
        }
    ],
    "sg:phone":"+41 62 775 33 65",
    "sg:postcode":"5704",
    "sg:province":"Aargau",
    "sg:tags":[
        "press",
        "automation"
    ],
    "wof:name":"M. Remund Ag",
    "wof:placetype":"venue"
},
  "geometry": {"coordinates":[8.179803,47.350178],"type":"Point"}
}