{
  "type": "Feature",
  "properties": {
    "iso:country":"CH",
    "sg:address":"Schachenstrasse 24",
    "sg:city":"Oberg\u00f6sgen",
    "sg:orig_category":"G\u00fcterbef\u00f6rderung im Strassenverkehr",
    "sg:phone":"+41 62 295 39 69",
    "sg:postcode":"4653",
    "sg:province":"Solothurn",
    "wof:name":"Ren\u00e9 Greub Transporte",
    "wof:placetype":"venue"
},
  "geometry": {"coordinates":[7.952753067,47.3625183105],"type":"Point"}
}