{
  "type": "Feature",
  "properties": {
    "iso:country":"CH",
    "sg:address":"Landstrasse 65",
    "sg:city":"M\u00f6hlin",
    "sg:orig_category":"RESTAURANTS: TEA-ROOMS",
    "sg:phone":"+41 61 851 11 88",
    "sg:postcode":"4313",
    "sg:province":"Aargau",
    "wof:name":"Gasthaus Sonnenberg Geiger Marcel Restaurant",
    "wof:placetype":"venue"
},
  "geometry": {"coordinates":[7.8498291969,47.5521659851],"type":"Point"}
}