{
  "type": "Feature",
  "properties": {
    "iso:country":"CH",
    "sg:address":"Innere G\u00fcterstrasse 2",
    "sg:city":"Zug",
    "sg:orig_category":"Non-Classified Establishments",
    "sg:postcode":"6300",
    "sg:province":"Zug",
    "wof:name":"Group Interstar Zug Ag",
    "wof:placetype":"venue"
},
  "geometry": {"coordinates":[8.516913414,47.177318573],"type":"Point"}
}