{
  "type": "Feature",
  "properties": {
    "addr:full":"Spitalgasse 34 Bern Bern 3011",
    "addr:housenumber":"34",
    "addr:postcode":"3011",
    "addr:street":"Spitalgasse",
    "iso:country":"CH",
    "sg:address":"Spitalgasse 34",
    "sg:city":"Bern",
    "sg:classifiers":[
        {
            "category":"Bars & Pubs",
            "type":"Food & Drink"
        }
    ],
    "sg:phone":"+41 31 312 14 40",
    "sg:postcode":"3011",
    "sg:province":"Bern",
    "wof:name":"Nelson Pub",
    "wof:placetype":"venue"
},
  "geometry": {"coordinates":[7.441833,46.948002],"type":"Point"}
}