{
  "type": "Feature",
  "properties": {
    "iso:country":"CH",
    "sg:address":"Bahnhofstrasse 145 8957 Spreitenbach. Postfach",
    "sg:city":"Spreitenbach",
    "sg:orig_category":"Werbung",
    "sg:postcode":"8957",
    "sg:province":"Aargau",
    "wof:name":"Tws Taxi Werbung Schweiz Ag Vermarktung Von Taxis Usw",
    "wof:placetype":"venue"
},
  "geometry": {"coordinates":[8.35683918,47.4299964905],"type":"Point"}
}