{
  "type": "Feature",
  "properties": {
    "iso:country":"CH",
    "sg:address":"St\u00e4ngelmatt 6252 Dagmersellen. Postfach",
    "sg:city":"Oberwinterthur",
    "sg:orig_category":"Herstellung von Industriegasen",
    "sg:phone":"+41 52 245 02 02",
    "sg:postcode":"8404",
    "sg:province":"Z\u00fcrich",
    "wof:name":"Propana - Fischer Ag",
    "wof:placetype":"venue"
},
  "geometry": {"coordinates":[7.9799251556,47.2094688416],"type":"Point"}
}