{
  "type": "Feature",
  "properties": {
    "iso:country":"CH",
    "sg:address":"Gotthardstrasse 176",
    "sg:city":"Erstfeld",
    "sg:orig_category":"Sanit\u00e4r, Heizungs U L\u00fcftungsinstallation Sanit\u00e4rinstallation",
    "sg:phone":"+41 41 880 10 69",
    "sg:postcode":"6472",
    "sg:province":"Uri",
    "wof:name":"Marty Walter, Sanit\u00e4re Anlagen, Heizungen Sowie Personalberatung",
    "wof:placetype":"venue"
},
  "geometry": {"coordinates":[8.6474723816,46.8284721375],"type":"Point"}
}