{
  "type": "Feature",
  "properties": {
    "iso:country":"CH",
    "sg:address":"Geissbrunnenweg 21",
    "sg:city":"Itingen",
    "sg:orig_category":"Grosshandel mit sonstigen Gebrauchs U Verbrauchsg\u00fctern",
    "sg:postcode":"4452",
    "sg:province":"Basel-Landschaft",
    "wof:name":"Stricker Automaten-vertrieb",
    "wof:placetype":"venue"
},
  "geometry": {"coordinates":[7.7850232124,47.4724617004],"type":"Point"}
}