{
  "type": "Feature",
  "properties": {
    "iso:country":"CH",
    "sg:address":"Randweg 1",
    "sg:city":"W\u00fcrenlingen",
    "sg:orig_category":"Herstellung von Metallkonstruktionen Mechanik",
    "sg:phone":"+41 56 281 17 82",
    "sg:postcode":"5303",
    "sg:province":"Aargau",
    "wof:name":"Arthur B\u00e4chli Metallbau & Schlosserei",
    "wof:placetype":"venue"
},
  "geometry": {"coordinates":[8.2563085556,47.5380096436],"type":"Point"}
}