{
  "type": "Feature",
  "properties": {
    "iso:country":"CH",
    "sg:address":"Avenue De Rochettaz 2",
    "sg:city":"Pully",
    "sg:orig_category":"Arztpraxen",
    "sg:phone":"+41 21 728 30 40",
    "sg:postcode":"1009",
    "sg:province":"Vaud",
    "wof:name":"Dr M\u00e9d. Annette Leimgruber M\u00e9decin Sp\u00e9cialiste Fmh",
    "wof:placetype":"venue"
},
  "geometry": {"coordinates":[6.66434,46.512749],"type":"Point"}
}