{
  "type": "Feature",
  "properties": {
    "iso:country":"CH",
    "sg:address":"Gemeindehaus",
    "sg:city":"Brittnau",
    "sg:orig_category":"Museen",
    "sg:phone":"+41 61 425 51 51",
    "sg:postcode":"4805",
    "sg:province":"Aargau",
    "wof:name":"Ortsmuseum",
    "wof:placetype":"venue"
},
  "geometry": {"coordinates":[7.5726628304,47.5433044434],"type":"Point"}
}