{
  "type": "Feature",
  "properties": {
    "iso:country":"CH",
    "sg:address":"Ringstrasse 6",
    "sg:city":"Dagmersellen",
    "sg:orig_category":"Unclassifiable Establishments",
    "sg:postcode":"6252",
    "sg:province":"Luzern",
    "wof:name":"Convallis Ag",
    "wof:placetype":"venue"
},
  "geometry": {"coordinates":[9.8209104538,46.7938690186],"type":"Point"}
}