{
  "type": "Feature",
  "properties": {
    "addr:full":"Gygerweg 18 3700 Spiezwiler. Postfach 320 Spiez Bern 3700",
    "addr:housenumber":"18;320",
    "addr:postcode":"3700;3700",
    "addr:street":"Gygerweg;Postfach",
    "iso:country":"CH",
    "sg:address":"Gygerweg 18 3700 Spiezwiler. Postfach 320",
    "sg:city":"Spiez",
    "sg:orig_category":"Bau von Strassen, Sportanlagen U Bahnverkehrsstrecken Br\u00fccken U Tunnelbau",
    "sg:phone":"+41 33 654 26 00",
    "sg:postcode":"3700",
    "sg:province":"Bern",
    "wof:name":"Batigroup Ag",
    "wof:placetype":"venue"
},
  "geometry": {"coordinates":[7.6654,46.683872],"type":"Point"}
}