{
  "type": "Feature",
  "properties": {
    "iso:country":"CH",
    "sg:address":"Burggraben 24",
    "sg:city":"St.gallen",
    "sg:orig_category":"Pensionskassen",
    "sg:postcode":"9000",
    "sg:province":"St. Gallen",
    "wof:name":"Personalf\u00fcrsorgestiftung Der Firma Tsch\u00fcmperlin A. Ag Betonwarenfabriken",
    "wof:placetype":"venue"
},
  "geometry": {"coordinates":[8.4415683746,47.0812110901],"type":"Point"}
}