{
  "type": "Feature",
  "properties": {
    "iso:country":"CH",
    "sg:address":"Place Du Molard 5",
    "sg:city":"Gen\u00e8ve",
    "sg:orig_category":"Effektenvermittlung Broker Finanzierungsinstitutionen",
    "sg:phone":"+41 22 318 30 40",
    "sg:postcode":"1204",
    "sg:province":"Gen\u00e8ve",
    "wof:name":"Financi\u00e8re Gautier & Cie Sa",
    "wof:placetype":"venue"
},
  "geometry": {"coordinates":[6.1481599808,46.2036018372],"type":"Point"}
}