{
  "type": "Feature",
  "properties": {
    "iso:country":"CH",
    "sg:address":"Rue De La Place 2",
    "sg:city":"Tramelan",
    "sg:orig_category":"Zimmerei, Dachdeckerei, Bauspenglerei U Abdichtung",
    "sg:phone":"+41 32 487 49 51",
    "sg:postcode":"2720",
    "sg:province":"Bern",
    "wof:name":"Bory Jean-fran\u00e7ois",
    "wof:placetype":"venue"
},
  "geometry": {"coordinates":[7.1100687981,47.2239456177],"type":"Point"}
}