{
  "type": "Feature",
  "properties": {
    "iso:country":"CH",
    "sg:address":"Im Neusatz 12",
    "sg:city":"Arlesheim",
    "sg:orig_category":"Unclassifiable Establishments",
    "sg:postcode":"4144",
    "sg:province":"Basel-Landschaft",
    "wof:name":"Burger Design Pen Ag",
    "wof:placetype":"venue"
},
  "geometry": {"coordinates":[7.2594342232,46.821472168],"type":"Point"}
}