{
  "type": "Feature",
  "properties": {
    "iso:country":"CH",
    "sg:address":"Bahndammweg 7",
    "sg:city":"Balsthal",
    "sg:orig_category":"Sonstige pers\u00f6nliche Dienstleistungen",
    "sg:postcode":"4710",
    "sg:province":"Solothurn",
    "wof:name":"Ebc European Buying Cooperation Gmbh",
    "wof:placetype":"venue"
},
  "geometry": {"coordinates":[7.692179203,47.3114738464],"type":"Point"}
}