{
  "type": "Feature",
  "properties": {
    "iso:country":"CH",
    "sg:address":"Aeschenvorstadt 57 4051 Basel. Postfach",
    "sg:city":"Basel",
    "sg:orig_category":"Unclassifiable Establishments",
    "sg:phone":"+41 61 206 95 95",
    "sg:postcode":"4010",
    "sg:province":"Basel-Stadt",
    "wof:name":"Gtu Travel Ag Sportreisen & Ticketservice",
    "wof:placetype":"venue"
},
  "geometry": {"coordinates":[7.5938329697,47.5523223877],"type":"Point"}
}