{
  "type": "Feature",
  "properties": {
    "iso:country":"CH",
    "sg:address":"Rosalp 5",
    "sg:city":"Haute-nendaz",
    "sg:classifiers":[
        {
            "category":"Home & Garden",
            "subcategory":"Kitchen Supply",
            "type":"Retail Goods"
        }
    ],
    "sg:phone":"+41 27 288 30 38",
    "sg:postcode":"1997",
    "sg:province":"Valais",
    "sg:tags":[
        "water",
        "filter",
        "household"
    ],
    "wof:name":"Grob Sa",
    "wof:placetype":"venue"
},
  "geometry": {"coordinates":[7.2981119156,46.1841583252],"type":"Point"}
}