{
  "type": "Feature",
  "properties": {
    "iso:country":"CH",
    "sg:address":"Hubel",
    "sg:city":"Plasselb",
    "sg:orig_category":"Herstellung von Metallkonstruktionen",
    "sg:phone":"+41 26 419 34 04",
    "sg:postcode":"1737",
    "sg:province":"Fribourg",
    "wof:name":"Verandas-saillard Winterg\u00e4rten",
    "wof:placetype":"venue"
},
  "geometry": {"coordinates":[7.2540998459,46.7396774292],"type":"Point"}
}