{
  "type": "Feature",
  "properties": {
    "iso:country":"CH",
    "sg:address":"Genuastrasse 15",
    "sg:city":"M\u00fcnchenstein",
    "sg:orig_category":"Detailhandel mit Tabakwaren Grosshandel mit Tabakwaren",
    "sg:phone":"+41 61 331 18 17",
    "sg:postcode":"4142",
    "sg:province":"Basel-Landschaft",
    "wof:name":"Intertabak Ag",
    "wof:placetype":"venue"
},
  "geometry": {"coordinates":[7.6100521088,47.5308189392],"type":"Point"}
}