{
  "type": "Feature",
  "properties": {
    "iso:country":"CH",
    "sg:address":"Blegistrasse 25",
    "sg:city":"Baar",
    "sg:orig_category":"Herstellung von Radio U Fernsehger\u00e4ten sowie phono U videotechnischen Ger\u00e4ten",
    "sg:postcode":"6340",
    "sg:province":"Zug",
    "wof:name":"Somasa Ag",
    "wof:placetype":"venue"
},
  "geometry": {"coordinates":[8.5663824081,47.2145271301],"type":"Point"}
}