{
  "type": "Feature",
  "properties": {
    "iso:country":"CH",
    "sg:address":"Zimikerstrasse 3",
    "sg:city":"Uster",
    "sg:orig_category":"Sonstige mit der Informatik verbundene T\u00e4tigkeiten",
    "sg:postcode":"8610",
    "sg:province":"Z\u00fcrich",
    "wof:name":"Cubes Heizmann Hischier Vogt",
    "wof:placetype":"venue"
},
  "geometry": {"coordinates":[8.7146759033,47.3458061218],"type":"Point"}
}