{
  "type": "Feature",
  "properties": {
    "iso:country":"CH",
    "sg:address":"Vsp Areal Fabrikstrasse 17",
    "sg:city":"Pfyn",
    "sg:orig_category":"Mechanik Mechanische Werkst\u00e4tten",
    "sg:phone":"+41 52 765 28 78",
    "sg:postcode":"8505",
    "sg:province":"Thurgau",
    "wof:name":"Unimech Gmbh",
    "wof:placetype":"venue"
},
  "geometry": {"coordinates":[8.9514503479,47.5952033997],"type":"Point"}
}