{
  "type": "Feature",
  "properties": {
    "iso:country":"CH",
    "sg:address":"Hagnetstrasse 32",
    "sg:city":"W\u00fcnnewil",
    "sg:orig_category":"Sonstige Aktivit\u00e4ten der nicht-\u00e4rztlichen Medizinalberufe",
    "sg:phone":"+41 26 496 31 82",
    "sg:postcode":"3184",
    "sg:province":"Fribourg",
    "wof:name":"Marie-marthe Aebischer Atemtherapie",
    "wof:placetype":"venue"
},
  "geometry": {"coordinates":[7.2584309578,46.8645744324],"type":"Point"}
}