{
  "type": "Feature",
  "properties": {
    "iso:country":"CH",
    "sg:address":"Husacherstr. 321",
    "sg:city":"Unterb\u00f6zberg",
    "sg:orig_category":"Kauf U Verkauf von Immobilien auf eigene Rechnung",
    "sg:phone":"+41 56 441 94 12",
    "sg:postcode":"5224",
    "sg:province":"Aargau",
    "wof:name":"Jakob Staub Ag",
    "wof:placetype":"venue"
},
  "geometry": {"coordinates":[8.1739740372,47.4828186035],"type":"Point"}
}