{
  "type": "Feature",
  "properties": {
    "iso:country":"CH",
    "sg:address":"En Budron H2",
    "sg:city":"Mont-sur-lausanne",
    "sg:orig_category":"Grosshandel mit Holz U Baustoffen",
    "sg:postcode":"1052",
    "sg:province":"Vaud",
    "wof:name":"Cec Trading Gmbh Konsum- U. Investitionsg\u00fcter, Bes. Holzhandel; Internationaler Handel, Export U. Import Usw.",
    "wof:placetype":"venue"
},
  "geometry": {"coordinates":[9.0483894348,47.4553337097],"type":"Point"}
}