{
  "type": "Feature",
  "properties": {
    "iso:country":"CH",
    "sg:address":"Bahnhofstrasse 283",
    "sg:city":"Rohrbach",
    "sg:orig_category":"Architektur U Ingenieurb\u00fcros Architekturb\u00fcros",
    "sg:phone":"+41 79 657 88 28",
    "sg:postcode":"4938",
    "sg:province":"Bern",
    "wof:name":"Architektur M. L\u00fcthi Ag",
    "wof:placetype":"venue"
},
  "geometry": {"coordinates":[7.813272,47.136738],"type":"Point"}
}