{
  "type": "Feature",
  "properties": {
    "iso:country":"CH",
    "sg:address":"Gloriastrasse 78",
    "sg:city":"Z\u00fcrich",
    "sg:orig_category":"Vereine Gemeinn\u00fctzige",
    "sg:phone":"+41 12514790",
    "sg:postcode":"8044",
    "sg:province":"Z\u00fcrich",
    "wof:name":"Israelitisches Rotes Kreuz",
    "wof:placetype":"venue"
},
  "geometry": {"coordinates":[8.5575580597,47.3753662109],"type":"Point"}
}