{
  "type": "Feature",
  "properties": {
    "iso:country":"CH",
    "sg:address":"Berntorgasse 10",
    "sg:city":"Thun",
    "sg:orig_category":"Haltung von Rindern",
    "sg:postcode":"3600",
    "sg:province":"Bern",
    "wof:name":"Braunviehzuchtverband Des Kantons Bern",
    "wof:placetype":"venue"
},
  "geometry": {"coordinates":[7.6276350021,46.7611083984],"type":"Point"}
}