{
  "type": "Feature",
  "properties": {
    "iso:country":"CH",
    "sg:address":"Bahnhofstrasse 9 8001 Z\u00fcrich. Postfach",
    "sg:city":"Z\u00fcrich",
    "sg:orig_category":"Vermietung U Verpachtung von eigenen Immobilien",
    "sg:phone":"+41 12202741",
    "sg:postcode":"8001",
    "sg:province":"Z\u00fcrich",
    "wof:name":"Z\u00fcrcher Immobilien-ag",
    "wof:placetype":"venue"
},
  "geometry": {"coordinates":[8.5396871567,47.3680915833],"type":"Point"}
}