{
  "type": "Feature",
  "properties": {
    "iso:country":"CH",
    "sg:address":"Marktgasse 3",
    "sg:city":"St.gallen",
    "sg:orig_category":"Unclassifiable Establishments",
    "sg:postcode":"9000",
    "sg:province":"St. Gallen",
    "wof:name":"Febu Treuhand Und Immobilien Ag",
    "wof:placetype":"venue"
},
  "geometry": {"coordinates":[9.3763303757,47.4260559082],"type":"Point"}
}