{
  "type": "Feature",
  "properties": {
    "iso:country":"CH",
    "sg:address":"Alte Landstrasse 73",
    "sg:city":"Thalwil",
    "sg:orig_category":"Maler U Glasergewerbe",
    "sg:phone":"+41 17201600",
    "sg:postcode":"8800",
    "sg:province":"Z\u00fcrich",
    "wof:name":"Huggenberger Maler Ag",
    "wof:placetype":"venue"
},
  "geometry": {"coordinates":[8.5693502426,47.2885437012],"type":"Point"}
}