{
  "type": "Feature",
  "properties": {
    "iso:country":"CH",
    "sg:address":"Schreberweg 9",
    "sg:city":"Z\u00fcrich",
    "sg:orig_category":"Interessenvertretungen",
    "sg:postcode":"8044",
    "sg:province":"Z\u00fcrich",
    "wof:name":"Birchler-eberle-stiftung Georg Walter",
    "wof:placetype":"venue"
},
  "geometry": {"coordinates":[8.7771615982,47.2002677917],"type":"Point"}
}