{
  "type": "Feature",
  "properties": {
    "iso:country":"CH",
    "sg:address":"Sch\u00fctzengasse 71d 2502 Biel/bienne. Postfach",
    "sg:city":"Biel/bienne",
    "sg:orig_category":"Interessenvertretungen",
    "sg:phone":"+41 31 352 63 73",
    "sg:postcode":"2502",
    "sg:province":"Bern",
    "wof:name":"Expertenvereinigung Sws Ag Schadenbeurteilung An Fahrzeugen; Erstellen Techn. Gutachten Usw.",
    "wof:placetype":"venue"
},
  "geometry": {"coordinates":[7.2507548332,47.1463928223],"type":"Point"}
}