{
  "type": "Feature",
  "properties": {
    "iso:country":"CH",
    "sg:address":"Albisstrasse 113 8038 Z\u00fcrich. Postfach",
    "sg:city":"Z\u00fcrich",
    "sg:orig_category":"Instandhaltung U Reparatur von Automobilen",
    "sg:postcode":"8038",
    "sg:province":"Z\u00fcrich",
    "wof:name":"Garage Da Riva Baggieri G.+a.",
    "wof:placetype":"venue"
},
  "geometry": {"coordinates":[8.5302658081,47.3375778198],"type":"Point"}
}