{
  "type": "Feature",
  "properties": {
    "iso:country":"CH",
    "sg:address":"Albisriederstrasse 19",
    "sg:city":"Z\u00fcrich",
    "sg:orig_category":"Physiotherapie",
    "sg:phone":"+41 14930602",
    "sg:postcode":"8003",
    "sg:province":"Z\u00fcrich",
    "wof:name":"Jacqueline Mustafic Physiotherapie",
    "wof:placetype":"venue"
},
  "geometry": {"coordinates":[8.5081529617,47.3777313232],"type":"Point"}
}