{
  "type": "Feature",
  "properties": {
    "iso:country":"CH",
    "sg:address":"Plattenstrasse 33 5737 Menziken. Postfach",
    "sg:city":"Menziken",
    "sg:classifiers":[
        {
            "category":"Professional",
            "subcategory":"Employment Agencies",
            "type":"Services"
        }
    ],
    "sg:postcode":"5737",
    "sg:province":"Aargau",
    "sg:tags":[
        "personal",
        "u",
        "stellenvermittlung"
    ],
    "wof:name":"Arnold J.",
    "wof:placetype":"venue"
},
  "geometry": {"coordinates":[8.1809902191,47.2415275574],"type":"Point"}
}