{
  "type": "Feature",
  "properties": {
    "addr:full":"Klosbachstrasse 90 Z\u00fcrich Z\u00fcrich 8032",
    "addr:housenumber":"90",
    "addr:postcode":"8032",
    "addr:street":"Klosbachstrasse",
    "iso:country":"CH",
    "sg:address":"Klosbachstrasse 90",
    "sg:city":"Z\u00fcrich",
    "sg:classifiers":[
        {
            "category":"Banks & Credit Unions",
            "subcategory":"Bank",
            "type":"Services"
        }
    ],
    "sg:phone":"+41 13834202",
    "sg:postcode":"8032",
    "sg:province":"Z\u00fcrich",
    "wof:name":"Schweiz. Mobiliar",
    "wof:placetype":"venue"
},
  "geometry": {"coordinates":[8.56049,47.367626],"type":"Point"}
}