{
  "type": "Feature",
  "properties": {
    "iso:country":"CH",
    "sg:address":"Wehntalerstrasse 11 8165 Oberweningen. Postfach",
    "sg:city":"Oberweningen",
    "sg:orig_category":"Herstellung von Kunststoff in Prim\u00e4rformen Oberfl\u00e4chenveredlung U W\u00e4rmebehandlung",
    "sg:phone":"+41 32 913 17 53",
    "sg:postcode":"8165",
    "sg:province":"Z\u00fcrich",
    "wof:name":"H.e. Finishing Sa",
    "wof:placetype":"venue"
},
  "geometry": {"coordinates":[6.816183,47.09948],"type":"Point"}
}