{
  "type": "Feature",
  "properties": {
    "iso:country":"CH",
    "sg:address":"Baslerstrasse 7",
    "sg:city":"Bottmingen",
    "sg:orig_category":"Detailhandel mit Parf\u00fcmerieartikeln U K\u00f6rperpflegemitteln Detailhandel mit Waren verschiedener Art, ",
    "sg:phone":"+41 34 402 76 35",
    "sg:postcode":"4103",
    "sg:province":"Basel-Landschaft",
    "wof:name":"Bio Stube Gmbh Bio-laden. Bio-produkte; Kauf U. Verkauf Usw.",
    "wof:placetype":"venue"
},
  "geometry": {"coordinates":[7.757589817,46.9491271973],"type":"Point"}
}