{
  "type": "Feature",
  "properties": {
    "iso:country":"CH",
    "sg:address":"Schl\u00fcsselgasse 4 8001 Z\u00fcrich. Postfach",
    "sg:city":"Z\u00fcrich",
    "sg:orig_category":"Fachdetailhandel in Verkaufsr\u00e4umen Grosshandel mit Baumaterialien",
    "sg:phone":"+41 17777626",
    "sg:postcode":"8001",
    "sg:province":"Z\u00fcrich",
    "wof:name":"Rusag Ag",
    "wof:placetype":"venue"
},
  "geometry": {"coordinates":[8.435008049,47.3528213501],"type":"Point"}
}