{
  "type": "Feature",
  "properties": {
    "iso:country":"CH",
    "sg:address":"Avenue De France 23",
    "sg:city":"Sierre",
    "sg:orig_category":"G\u00fcterbef\u00f6rderung im Strassenverkehr",
    "sg:postcode":"3960",
    "sg:province":"Valais",
    "wof:name":"Siegfried Michel",
    "wof:placetype":"venue"
},
  "geometry": {"coordinates":[7.5238628387,46.2901916504],"type":"Point"}
}