{
  "type": "Feature",
  "properties": {
    "iso:country":"CH",
    "sg:address":"Gr\u00fctweg 385",
    "sg:city":"T\u00e4gerig",
    "sg:orig_category":"Unternehmensberatung",
    "sg:postcode":"5522",
    "sg:province":"Aargau",
    "wof:name":"Egloff Unternehmensberatung",
    "wof:placetype":"venue"
},
  "geometry": {"coordinates":[8.2793540955,47.406665802],"type":"Point"}
}