{
  "type": "Feature",
  "properties": {
    "addr:full":"2108 Couvet Neuch\u00e2tel 2108",
    "addr:housenumber":"2108",
    "addr:postcode":"2108",
    "addr:street":"Neucha\u0302Tel",
    "iso:country":"CH",
    "sg:address":"2108",
    "sg:city":"Couvet",
    "sg:classifiers":[
        {
            "category":"Education",
            "subcategory":"Library",
            "type":"Public Place"
        }
    ],
    "sg:postcode":"2108",
    "sg:province":"Neuch\u00e2tel",
    "sg:tags":[
        "u",
        "bibliotheken",
        "archive"
    ],
    "wof:name":"Biblioth\u00e8que Populaire",
    "wof:placetype":"venue"
},
  "geometry": {"coordinates":[6.55847,46.912842],"type":"Point"}
}