{
  "type": "Feature",
  "properties": {
    "iso:country":"CH",
    "sg:address":"Rosengasse 6",
    "sg:city":"Liestal",
    "sg:orig_category":"Detailhandel mit fotografischen Artikeln Fotografisches Gewerbe U fotografische Laboratorien",
    "sg:phone":"+41 56 631 85 58",
    "sg:postcode":"4410",
    "sg:province":"Basel-Landschaft",
    "wof:name":"Foto Dubler Ag",
    "wof:placetype":"venue"
},
  "geometry": {"coordinates":[8.3488235474,47.3519325256],"type":"Point"}
}