{
  "type": "Feature",
  "properties": {
    "iso:country":"CH",
    "sg:address":"Industrie Rue De L' 5",
    "sg:city":"Ste-croix",
    "sg:orig_category":"Interessenvertretungen",
    "sg:phone":"+41 24 454 16 48",
    "sg:postcode":"1450",
    "sg:province":"Vaud",
    "wof:name":"Coop\u00e9rative Textura",
    "wof:placetype":"venue"
},
  "geometry": {"coordinates":[6.5032429695,46.8211708069],"type":"Point"}
}