{
  "type": "Feature",
  "properties": {
    "iso:country":"CH",
    "sg:address":"Ottenbacherstrasse 25",
    "sg:city":"Obfelden",
    "sg:orig_category":"Gesundheitswesen Medizinische Labors",
    "sg:phone":"+41 17618033",
    "sg:postcode":"8912",
    "sg:province":"Z\u00fcrich",
    "wof:name":"Allergielabor W\u00e4lti Dr. M., Immunologisch-allergologische Analytik Ag",
    "wof:placetype":"venue"
},
  "geometry": {"coordinates":[8.4249486923,47.2668800354],"type":"Point"}
}