{
  "type": "Feature",
  "properties": {
    "iso:country":"CH",
    "sg:address":"Bernstrasse-ost 49",
    "sg:city":"Suhr",
    "sg:orig_category":"Unclassifiable Establishments",
    "sg:phone":"+41 62 855 80 30",
    "sg:postcode":"5034",
    "sg:province":"Aargau",
    "wof:name":"Pfister Arco Holding Ag",
    "wof:placetype":"venue"
},
  "geometry": {"coordinates":[8.0845899582,47.3741378784],"type":"Point"}
}