{
  "type": "Feature",
  "properties": {
    "addr:full":"Risi 47 N\u00e4fels Glarus 8752",
    "addr:housenumber":"47",
    "addr:postcode":"8752",
    "addr:street":"Risi;Naefels Glarus",
    "iso:country":"CH",
    "sg:address":"Risi 47",
    "sg:city":"N\u00e4fels",
    "sg:orig_category":"Abfallbeseitigung R\u00fcckgewinnung U Vorbereitung f\u00fcr die Wiederverwertung Recycling",
    "sg:phone":"+41 32 365 71 71",
    "sg:postcode":"8752",
    "sg:province":"Glarus",
    "wof:name":"Sonderabfallverwertungs-ag, Sovag",
    "wof:placetype":"venue"
},
  "geometry": {"coordinates":[7.259953,47.120277],"type":"Point"}
}