{
  "type": "Feature",
  "properties": {
    "addr:full":"Dorfstrasse 53 B\u00fcttenhardt Schaffhausen 8236",
    "addr:housenumber":"53",
    "addr:postcode":"8236",
    "addr:street":"Dorfstrasse",
    "iso:country":"CH",
    "sg:address":"Dorfstrasse 53",
    "sg:city":"B\u00fcttenhardt",
    "sg:orig_category":"Autogaragen",
    "sg:phone":"+41 52 649 33 23",
    "sg:postcode":"8236",
    "sg:province":"Schaffhausen",
    "wof:name":"Reiat-garage Armin Maier",
    "wof:placetype":"venue"
},
  "geometry": {"coordinates":[8.65448,47.758411],"type":"Point"}
}