{
  "type": "Feature",
  "properties": {
    "iso:country":"CH",
    "sg:address":"Piazza Brocchi 5",
    "sg:city":"Montagnola",
    "sg:orig_category":"Physiotherapie",
    "sg:phone":"+41 91 994 43 15",
    "sg:postcode":"6926",
    "sg:province":"Ticino",
    "wof:name":"Stefano Isolini Fisioterapia",
    "wof:placetype":"venue"
},
  "geometry": {"coordinates":[8.9177780151,45.9824562073],"type":"Point"}
}