{
  "type": "Feature",
  "properties": {
    "iso:country":"CH",
    "sg:address":"Bundesplatz 1 6003 Luzern. Postfach",
    "sg:city":"Luzern",
    "sg:orig_category":"Interessenvertretungen",
    "sg:postcode":"6003",
    "sg:province":"Luzern",
    "wof:name":"Dreifuss Jakob Salomon Stiftung Beisteuer An J\u00fcdische M\u00e4dchen Usw.",
    "wof:placetype":"venue"
},
  "geometry": {"coordinates":[8.3097238541,47.0459365845],"type":"Point"}
}