{
  "type": "Feature",
  "properties": {
    "iso:country":"CH",
    "sg:address":"Bodenfeldstrasse 10",
    "sg:city":"Bonstetten",
    "sg:orig_category":"Unternehmensberatung",
    "sg:postcode":"8906",
    "sg:province":"Z\u00fcrich",
    "wof:name":"Fcs Financial Consultancy Services Kilcoyne",
    "wof:placetype":"venue"
},
  "geometry": {"coordinates":[8.4650144577,47.3141098022],"type":"Point"}
}