{
  "type": "Feature",
  "properties": {
    "iso:country":"CH",
    "sg:address":"M\u00fchlemattweg 11",
    "sg:city":"K\u00fcnten",
    "sg:orig_category":"Vorschulen, Kinderg\u00e4rten",
    "sg:phone":"+41 56 496 66 56",
    "sg:postcode":"5444",
    "sg:province":"Aargau",
    "wof:name":"Kindergarten Stube 1",
    "wof:placetype":"venue"
},
  "geometry": {"coordinates":[8.3266401291,47.3875083923],"type":"Point"}
}