{
  "type": "Feature",
  "properties": {
    "iso:country":"CH",
    "sg:address":"Astrastrasse 13",
    "sg:city":"Steffisburg",
    "sg:orig_category":"Non-Classified Establishments",
    "sg:phone":"+41 31 972 81 00",
    "sg:postcode":"3613",
    "sg:province":"Bern",
    "wof:name":"Discover-it Michels Hajo",
    "wof:placetype":"venue"
},
  "geometry": {"coordinates":[7.6299910545,46.7729072571],"type":"Point"}
}