{
  "type": "Feature",
  "properties": {
    "iso:country":"CH",
    "sg:address":"Chemin Des Cornillons 4",
    "sg:city":"Chamb\u00e9sy",
    "sg:classifiers":[
        {
            "category":"Restaurant",
            "type":"Food & Drink"
        }
    ],
    "sg:phone":"+41 22 758 45 66",
    "sg:postcode":"1292",
    "sg:province":"Gen\u00e8ve",
    "wof:name":"Restaurant Kor\u00e9a Garden",
    "wof:placetype":"venue"
},
  "geometry": {"coordinates":[6.1463718414,46.2430534363],"type":"Point"}
}