{
  "type": "Feature",
  "properties": {
    "iso:country":"CH",
    "sg:address":"1921",
    "sg:city":"Martigny-croix",
    "sg:orig_category":"Interessenvertretungen",
    "sg:postcode":"1921",
    "sg:province":"Valais",
    "wof:name":"Fondation Sos Village D'enfants Martigny-combe",
    "wof:placetype":"venue"
},
  "geometry": {"coordinates":[7.0548000336,46.0870895386],"type":"Point"}
}