{
  "type": "Feature",
  "properties": {
    "iso:country":"CH",
    "sg:address":"Erlachstrasse 44",
    "sg:city":"Z\u00fcrich",
    "sg:orig_category":"Kunsthandel",
    "sg:phone":"+41 14617610",
    "sg:postcode":"8003",
    "sg:province":"Z\u00fcrich",
    "wof:name":"Galerie Kayoko Frey",
    "wof:placetype":"venue"
},
  "geometry": {"coordinates":[8.5200738907,47.3674430847],"type":"Point"}
}