{
  "type": "Feature",
  "properties": {
    "iso:country":"CH",
    "sg:address":"Po Box 38",
    "sg:city":"Schleitheim",
    "sg:classifiers":[
        {
            "category":"Banks & Credit Unions",
            "subcategory":"Bank",
            "type":"Services"
        }
    ],
    "sg:phone":"+41 52 680 10 25",
    "sg:postcode":"8226",
    "sg:province":"Schaffhausen",
    "wof:name":"Spar- + Leihkasse, Des Bezirks Schleitheim",
    "wof:placetype":"venue"
},
  "geometry": {"coordinates":[8.488014,47.750401],"type":"Point"}
}