{
  "type": "Feature",
  "properties": {
    "iso:country":"CH",
    "sg:address":"Bordinette Route De La 4 1094 Paudex. Postfach",
    "sg:city":"Paudex",
    "sg:orig_category":"Fernmeldedienste",
    "sg:phone":"+41 21 791 30 92",
    "sg:postcode":"1094",
    "sg:province":"Vaud",
    "wof:name":"Tell Cell S\u00e0rl Service Dans Le Dom. Des T\u00e9l\u00e9communications Et Des Syst\u00e8mes D'information",
    "wof:placetype":"venue"
},
  "geometry": {"coordinates":[6.6718449593,46.5055656433],"type":"Point"}
}