{
  "type": "Feature",
  "properties": {
    "iso:country":"CH",
    "sg:address":"Curval Rue Louis- 1 1206 Gen\u00e8ve. Postfach",
    "sg:city":"Gen\u00e8ve",
    "sg:orig_category":"Reiseb\u00fcros U Reiseveranstalter",
    "sg:postcode":"1206",
    "sg:province":"Gen\u00e8ve",
    "wof:name":"E.c. Way S\u00e0rl",
    "wof:placetype":"venue"
},
  "geometry": {"coordinates":[6.1543569565,46.1907539368],"type":"Point"}
}