{
  "type": "Feature",
  "properties": {
    "iso:country":"CH",
    "sg:address":"Dorfplatz 7",
    "sg:city":"Horgen",
    "sg:orig_category":"Fachdetailhandel in Verkaufsr\u00e4umen Grosshandel mit Schmuck",
    "sg:phone":"+41 17261014",
    "sg:postcode":"8810",
    "sg:province":"Z\u00fcrich",
    "wof:name":"Obelisk Gmbh",
    "wof:placetype":"venue"
},
  "geometry": {"coordinates":[8.5983409882,47.260181427],"type":"Point"}
}