{
  "type": "Feature",
  "properties": {
    "iso:country":"CH",
    "sg:address":"Ancien Sierre Route De 6",
    "sg:city":"Sierre",
    "sg:orig_category":"Unclassifiable Establishments",
    "sg:postcode":"3960",
    "sg:province":"Valais",
    "wof:name":"Byse S\u00e0rl",
    "wof:placetype":"venue"
},
  "geometry": {"coordinates":[7.528427124,46.2848701477],"type":"Point"}
}