{
  "type": "Feature",
  "properties": {
    "iso:country":"CH",
    "sg:address":"Werdstrasse 8 8001 Z\u00fcrich. Postfach",
    "sg:city":"Z\u00fcrich",
    "sg:orig_category":"Sonstige mit der Informatik verbundene T\u00e4tigkeiten",
    "sg:phone":"+41 12913419",
    "sg:postcode":"8004",
    "sg:province":"Z\u00fcrich",
    "wof:name":"Berguna Gmbh Beratungsdienstleistungen In Bezug Auf Den Einsatz Von Technologien In Finanzm\u00e4rkten",
    "wof:placetype":"venue"
},
  "geometry": {"coordinates":[8.531001091,47.3731002808],"type":"Point"}
}