{
  "type": "Feature",
  "properties": {
    "addr:full":"Mittelfeldstrasse 10 Diepoldsau St. Gallen 9444",
    "addr:housenumber":"10",
    "addr:postcode":"9444",
    "addr:street":"Mittelfeldstrasse",
    "iso:country":"CH",
    "sg:address":"Mittelfeldstrasse 10",
    "sg:city":"Diepoldsau",
    "sg:orig_category":"Arbeitnehmerverb\u00e4nde",
    "sg:phone":"+41 71 733 23 42",
    "sg:postcode":"9444",
    "sg:province":"St. Gallen",
    "wof:name":"Ges.schw.lebensmittelinspekt. Pr\u00e4s.herrn Marcel Baumgarten",
    "wof:placetype":"venue"
},
  "geometry": {"coordinates":[9.666256,47.382084],"type":"Point"}
}