{
  "type": "Feature",
  "properties": {
    "iso:country":"CH",
    "sg:address":"Wiese 25",
    "sg:city":"Mitl\u00f6di",
    "sg:orig_category":"Satzherstellung U Reproduktion",
    "sg:postcode":"8756",
    "sg:province":"Glarus",
    "wof:name":"Office Support Gmbh",
    "wof:placetype":"venue"
},
  "geometry": {"coordinates":[9.0780172348,47.0095596313],"type":"Point"}
}