{
  "type": "Feature",
  "properties": {
    "iso:country":"CH",
    "sg:address":"Route De Cugy 136",
    "sg:city":"Mont-sur-lausanne",
    "sg:orig_category":"Hobel U Holzimpr\u00e4gnierwerke S\u00e4ge, Hobel U Holzimpr\u00e4gnierwerke",
    "sg:postcode":"1052",
    "sg:province":"Vaud",
    "wof:name":"Cortinas Jos\u00e9",
    "wof:placetype":"venue"
},
  "geometry": {"coordinates":[6.8173499107,47.097984314],"type":"Point"}
}