{
  "type": "Feature",
  "properties": {
    "iso:country":"CH",
    "sg:city":"Niederbipp",
    "sg:orig_category":"Immobilien U Baugewerbe, Baugewerbe",
    "sg:postcode":"4704",
    "sg:province":"Bern",
    "wof:name":"Ms Bedachungen Ag",
    "wof:placetype":"venue"
},
  "geometry": {"coordinates":[7.692255,47.270695],"type":"Point"}
}