{
  "type": "Feature",
  "properties": {
    "iso:country":"CH",
    "sg:address":"In Der Ballota 3",
    "sg:city":"Schaan",
    "sg:orig_category":"HOTELS: MIT RESTAURANT Kongress- and Tagungshotels mit Restaurant",
    "sg:phone":"+423 232 18 77",
    "sg:postcode":"9494",
    "wof:name":"Hotel Schaanerhof",
    "wof:placetype":"venue"
},
  "geometry": {"coordinates":[9.513338089,47.1641693115],"type":"Point"}
}