{
  "type": "Feature",
  "properties": {
    "iso:country":"CH",
    "sg:address":"Rebenweg 9",
    "sg:city":"H\u00fcnenberg",
    "sg:orig_category":"Non-Classified Establishments",
    "sg:postcode":"6331",
    "sg:province":"Zug",
    "wof:name":"Rainbow Travel Entreprises Holding Limited",
    "wof:placetype":"venue"
},
  "geometry": {"coordinates":[8.423787117,47.1762313843],"type":"Point"}
}