{
  "type": "Feature",
  "properties": {
    "iso:country":"CH",
    "sg:address":"Zone Industrielle La Gu\u00e9rite",
    "sg:city":"S\u00e9vaz",
    "sg:orig_category":"Mechanische Werkst\u00e4tten",
    "sg:phone":"+41 26 663 26 63",
    "sg:postcode":"1541",
    "sg:province":"Fribourg",
    "wof:name":"Pierre Blaser M\u00e9canique Navale",
    "wof:placetype":"venue"
},
  "geometry": {"coordinates":[6.8753180504,46.8386802673],"type":"Point"}
}