{
  "type": "Feature",
  "properties": {
    "iso:country":"CH",
    "sg:address":"9614",
    "sg:city":"Libingen",
    "sg:orig_category":"Vereine Musik/Blasmusik",
    "sg:postcode":"9614",
    "sg:province":"St. Gallen",
    "wof:name":"Musikgesellschaft",
    "wof:placetype":"venue"
},
  "geometry": {"coordinates":[9.0228996277,47.3287506104],"type":"Point"}
}