{
  "type": "Feature",
  "properties": {
    "iso:country":"CH",
    "sg:address":"1696",
    "sg:city":"Vuisternens-ogoz",
    "sg:orig_category":"S\u00e4ge, Hobel U Holzimpr\u00e4gnierwerke S\u00e4gewerke",
    "sg:phone":"+41 81 651 41 30",
    "sg:postcode":"1696",
    "sg:province":"Fribourg",
    "wof:name":"Romi's Mobils\u00e4gewerk Gmbh",
    "wof:placetype":"venue"
},
  "geometry": {"coordinates":[9.4555253983,46.7018165588],"type":"Point"}
}