{
  "type": "Feature",
  "properties": {
    "iso:country":"CH",
    "sg:address":"Hofwiesenstrasse 4",
    "sg:city":"Volketswil",
    "sg:orig_category":"Handel mit Automobilen",
    "sg:postcode":"8604",
    "sg:province":"Z\u00fcrich",
    "wof:name":"Cartrade Reust",
    "wof:placetype":"venue"
},
  "geometry": {"coordinates":[8.6732463837,47.3819465637],"type":"Point"}
}