{
  "type": "Feature",
  "properties": {
    "iso:country":"CH",
    "sg:address":"Chemin De Bonlieu 14",
    "sg:city":"Fribourg",
    "sg:classifiers":[
        {
            "category":"Social Services",
            "subcategory":"Retirement Home",
            "type":"Services"
        }
    ],
    "sg:phone":"+41 32 932 15 21",
    "sg:postcode":"1700",
    "sg:province":"Fribourg",
    "sg:tags":[
        "pflegeheime",
        "u",
        "alters"
    ],
    "wof:name":"La Gentilhommi\u00e8re Maison De Retraite",
    "wof:placetype":"venue"
},
  "geometry": {"coordinates":[6.724278,47.049686],"type":"Point"}
}