{
  "type": "Feature",
  "properties": {
    "iso:country":"CH",
    "sg:address":"Fuhrenstr. 31",
    "sg:city":"Adelboden",
    "sg:orig_category":"Interessenvertretungen",
    "sg:phone":"+41 33 673 32 48",
    "sg:postcode":"3715",
    "sg:province":"Bern",
    "wof:name":"L\u00fcthi-br\u00fcnnich Walter - Stiftung",
    "wof:placetype":"venue"
},
  "geometry": {"coordinates":[7.5576162338,46.4837837219],"type":"Point"}
}