{
  "type": "Feature",
  "properties": {
    "iso:country":"CH",
    "sg:address":"Via Rinaldo Simen 3",
    "sg:city":"Lugano",
    "sg:orig_category":"Sonstige mit Sport verbundene T\u00e4tigkeiten",
    "sg:postcode":"6900",
    "sg:province":"Ticino",
    "wof:name":"Curling Club Baden Regio",
    "wof:placetype":"venue"
},
  "geometry": {"coordinates":[8.2833662033,47.4561538696],"type":"Point"}
}