{
  "type": "Feature",
  "properties": {
    "iso:country":"CH",
    "sg:address":"Talackerstrasse 18",
    "sg:city":"H\u00e4gglingen",
    "sg:orig_category":"Allgemeiner Hoch U Tiefbau Hoch U Tiefbau",
    "sg:phone":"+41 32 968 64 20",
    "sg:postcode":"5607",
    "sg:province":"Aargau",
    "wof:name":"Tripet Fr\u00e8res.",
    "wof:placetype":"venue"
},
  "geometry": {"coordinates":[6.828638,47.106117],"type":"Point"}
}