{
  "type": "Feature",
  "properties": {
    "iso:country":"CH",
    "sg:address":"Hirschengraben 1",
    "sg:city":"Z\u00fcrich",
    "sg:classifiers":[
        {
            "category":"Banks & Credit Unions",
            "subcategory":"Bank",
            "type":"Services"
        }
    ],
    "sg:phone":"+41 12521900",
    "sg:postcode":"8024",
    "sg:province":"Z\u00fcrich",
    "wof:name":"Banque Mulit Commerciale",
    "wof:placetype":"venue"
},
  "geometry": {"coordinates":[8.547664,47.369358],"type":"Point"}
}