{
  "type": "Feature",
  "properties": {
    "iso:country":"CH",
    "sg:address":"Heckenweg 29 3270 Aarberg. Postfach",
    "sg:city":"Aarberg",
    "sg:orig_category":"Allgemeiner Hoch U Tiefbau Erdbewegungsarbeiten",
    "sg:phone":"+41 32 392 55 66",
    "sg:postcode":"3270",
    "sg:province":"Bern",
    "wof:name":"K\u00e4stli Ag Bauunternehmung",
    "wof:placetype":"venue"
},
  "geometry": {"coordinates":[7.28631,47.051121],"type":"Point"}
}