{
  "type": "Feature",
  "properties": {
    "iso:country":"CH",
    "sg:address":"Winkelstrasse 212",
    "sg:city":"Brunegg",
    "sg:orig_category":"Allgemeiner Hoch U Tiefbau Hoch U Tiefbau",
    "sg:phone":"+41 55 240 10 07",
    "sg:postcode":"5505",
    "sg:province":"Aargau",
    "wof:name":"Usseglio Baugesch\u00e4ft Ag",
    "wof:placetype":"venue"
},
  "geometry": {"coordinates":[8.867862,47.267864],"type":"Point"}
}