{
  "type": "Feature",
  "properties": {
    "iso:country":"CH",
    "sg:address":"Br\u00fchlstrasse 10a",
    "sg:city":"Arbon",
    "sg:orig_category":"RESTAURANTS: TEA-ROOMS",
    "sg:postcode":"9320",
    "sg:province":"Thurgau",
    "wof:name":"Ravag Ag",
    "wof:placetype":"venue"
},
  "geometry": {"coordinates":[9.4303636551,47.5128479004],"type":"Point"}
}