{
  "type": "Feature",
  "properties": {
    "iso:country":"CH",
    "sg:address":"Luzernerstrasse 30",
    "sg:city":"Kriens",
    "sg:orig_category":"Reiseb\u00fcros",
    "sg:phone":"+41 41 329 01 01",
    "sg:postcode":"6010",
    "sg:province":"Luzern",
    "wof:name":"Hotelplan Internationale Reiseorganisation Ag Einkaufszentrum Hofmatt",
    "wof:placetype":"venue"
},
  "geometry": {"coordinates":[8.2832307816,47.034034729],"type":"Point"}
}