{
  "type": "Feature",
  "properties": {
    "iso:country":"CH",
    "sg:address":"Missionsstrasse 67 4055 Basel. Postfach",
    "sg:city":"Basel",
    "sg:orig_category":"Fachdetailhandel in Verkaufsr\u00e4umen",
    "sg:postcode":"4012",
    "sg:province":"Basel-Stadt",
    "wof:name":"Erica's Erotic-shop, Schoenauer E.",
    "wof:placetype":"venue"
},
  "geometry": {"coordinates":[7.5741701126,47.5615768433],"type":"Point"}
}