{
  "type": "Feature",
  "properties": {
    "iso:country":"CH",
    "sg:address":"Kirchgasse 25",
    "sg:city":"Bischofszell",
    "sg:orig_category":"Sonstiges Gesundheitswesen",
    "sg:phone":"+41 61 721 41 51",
    "sg:postcode":"9220",
    "sg:province":"Thurgau",
    "wof:name":"Krankenmobilien",
    "wof:placetype":"venue"
},
  "geometry": {"coordinates":[7.5153198242,47.5054702759],"type":"Point"}
}