{
  "type": "Feature",
  "properties": {
    "iso:country":"CH",
    "sg:address":"Rheinfelsstrasse 5",
    "sg:city":"Chur",
    "sg:orig_category":"Detailhandel mit Schuhen",
    "sg:phone":"+41 81 250 34 20",
    "sg:postcode":"7000",
    "sg:province":"Graubunden",
    "wof:name":"Karl V\u00f6gele Ag",
    "wof:placetype":"venue"
},
  "geometry": {"coordinates":[9.5120372772,46.8507270813],"type":"Point"}
}