{
  "type": "Feature",
  "properties": {
    "iso:country":"CH",
    "sg:address":"Rheinecker Strasse 5",
    "sg:city":"Thal",
    "sg:orig_category":"Primarschulen",
    "sg:phone":"+41 71 888 35 06",
    "sg:postcode":"9425",
    "sg:province":"St. Gallen",
    "wof:name":"Primarschule Bild",
    "wof:placetype":"venue"
},
  "geometry": {"coordinates":[9.5708036423,47.4648323059],"type":"Point"}
}