{
  "type": "Feature",
  "properties": {
    "iso:country":"CH",
    "sg:address":"Ulrich-ochsenbein-weg 1 2503 Biel/bienne Case Postale 634",
    "sg:city":"Biel/bienne",
    "sg:orig_category":"Wirtschaftspr\u00fcfung, Steuerberatung U Treuhand",
    "sg:phone":"+41 71 245 78 15",
    "sg:postcode":"2501",
    "sg:province":"Bern",
    "wof:name":"Leo Metzger Treuhandb\u00fcro",
    "wof:placetype":"venue"
},
  "geometry": {"coordinates":[9.3658628464,47.4243278503],"type":"Point"}
}