{
  "type": "Feature",
  "properties": {
    "iso:country":"CH",
    "sg:address":"Rue Du Coll\u00e8ge 20 1400 Yverdon-les-bains Case Postale 63",
    "sg:city":"Yverdon",
    "sg:orig_category":"Detailhandel mit Uhren U Schmuck Fachdetailhandel in Verkaufsr\u00e4umen",
    "sg:phone":"+41 24 425 64 64",
    "sg:postcode":"1401",
    "sg:province":"Vaud",
    "wof:name":"Allemann F., Montres Et Bijoux.",
    "wof:placetype":"venue"
},
  "geometry": {"coordinates":[6.6379299164,46.7791786194],"type":"Point"}
}