{
  "type": "Feature",
  "properties": {
    "iso:country":"CH",
    "sg:address":"Unterdorfstrasse 19",
    "sg:city":"Flawil",
    "sg:orig_category":"Grosshandel mit Getreide, Saatgut U Futtermitteln",
    "sg:phone":"+41 71 393 10 10",
    "sg:postcode":"9230",
    "sg:province":"St. Gallen",
    "wof:name":"Wero D\u00e4mmstoffe Gmbh",
    "wof:placetype":"venue"
},
  "geometry": {"coordinates":[9.1889390945,47.4140853882],"type":"Point"}
}