{
  "type": "Feature",
  "properties": {
    "addr:full":"Dorneckstrasse 99 Dornach Solothurn 4143",
    "addr:housenumber":"99",
    "addr:postcode":"4143",
    "addr:street":"Dorneckstrasse",
    "iso:country":"CH",
    "sg:address":"Dorneckstrasse 99",
    "sg:city":"Dornach",
    "sg:orig_category":"Allgemeiner Hoch U Tiefbau",
    "sg:phone":"+41 61 701 50 48",
    "sg:postcode":"4143",
    "sg:province":"Solothurn",
    "wof:name":"Bte Bautechnik Ag",
    "wof:placetype":"venue"
},
  "geometry": {"coordinates":[7.622926,47.483414],"type":"Point"}
}