{
  "type": "Feature",
  "properties": {
    "iso:country":"CH",
    "sg:address":"La Lovettaz 5",
    "sg:city":"Sullens",
    "sg:orig_category":"Sanit\u00e4rinstallation",
    "sg:phone":"+41 21 731 58 65",
    "sg:postcode":"1036",
    "sg:province":"Vaud",
    "wof:name":"Ren\u00e9 Jaccaud Installations Sanitaires",
    "wof:placetype":"venue"
},
  "geometry": {"coordinates":[6.5707740784,46.5962028503],"type":"Point"}
}