{
  "type": "Feature",
  "properties": {
    "iso:country":"CH",
    "sg:address":"L\u00f6wenplatz 3",
    "sg:city":"Jegenstorf",
    "sg:orig_category":"Detailhandel mit Milcherzeugnissen U Eiern Verarbeitung von Milch",
    "sg:phone":"+41 31 762 00 38",
    "sg:postcode":"3303",
    "sg:province":"Bern",
    "wof:name":"Gottfried Frey K\u00e4serei",
    "wof:placetype":"venue"
},
  "geometry": {"coordinates":[7.5064730644,47.0486755371],"type":"Point"}
}