{
  "type": "Feature",
  "properties": {
    "iso:country":"CH",
    "sg:address":"Daillet",
    "sg:city":"Gr\u00f4ne",
    "sg:orig_category":"Technische B\u00fcros Heizung, L\u00fcftung, Klima Technische B\u00fcros Sanit\u00e4r",
    "sg:phone":"+41 79 220 34 49",
    "sg:postcode":"3979",
    "sg:province":"Valais",
    "wof:name":"Freddy Bruttin Bureau Technique",
    "wof:placetype":"venue"
},
  "geometry": {"coordinates":[7.4628000259,46.239566803],"type":"Point"}
}