{
  "type": "Feature",
  "properties": {
    "iso:country":"CH",
    "sg:address":"L\u00e4gernstrasse 31",
    "sg:city":"Z\u00fcrich",
    "sg:orig_category":"Detailhandel mit elektrischen Haushalts-,Radio U Fernsehger\u00e4ten sowie Musikinstrumenten",
    "sg:postcode":"8037",
    "sg:province":"Z\u00fcrich",
    "wof:name":"Masaeli Nadja Musikinstrumente, Zubeh\u00f6r; Handel U. Reparatur",
    "wof:placetype":"venue"
},
  "geometry": {"coordinates":[8.5315303802,47.3951263428],"type":"Point"}
}