{
  "type": "Feature",
  "properties": {
    "iso:country":"CH",
    "sg:address":"Landis+gyr-strasse 1 6300 Zug. Postfach 4262",
    "sg:city":"Zug",
    "sg:orig_category":"Grosshandel mit chemischen Erzeugnissen Grosshandel mit pharmazeutischen Erzeugnissen",
    "sg:phone":"+41 41 748 38 38",
    "sg:postcode":"6304",
    "sg:province":"Zug",
    "wof:name":"Cilag Ag International",
    "wof:placetype":"venue"
},
  "geometry": {"coordinates":[8.5122509003,47.1759338379],"type":"Point"}
}