{
  "type": "Feature",
  "properties": {
    "iso:country":"CH",
    "sg:address":"Gonda",
    "sg:city":"Disentis/must\u00e9r",
    "sg:orig_category":"Malerei",
    "sg:phone":"+41 71 744 26 06",
    "sg:postcode":"7180",
    "sg:province":"Graubunden",
    "wof:name":"Werner Brauchli Malerei",
    "wof:placetype":"venue"
},
  "geometry": {"coordinates":[9.6437206268,47.4248580933],"type":"Point"}
}