{
  "type": "Feature",
  "properties": {
    "iso:country":"CH",
    "sg:address":"Linseb\u00fchlstrasse 97",
    "sg:city":"St.gallen",
    "sg:orig_category":"Detailhandel mit B\u00fcchern, Zeitungen, Schreib U Papeteriewaren Detailhandel mit Zeitungen U Zeitschri",
    "sg:phone":"+41 71 223 36 65",
    "sg:postcode":"9000",
    "sg:province":"St. Gallen",
    "wof:name":"Quartierkiosk Quak Locher & Tognati",
    "wof:placetype":"venue"
},
  "geometry": {"coordinates":[9.385087,47.425888],"type":"Point"}
}