{
  "type": "Feature",
  "properties": {
    "addr:full":"Hauptstrasse H\u00f6rhausen Thurgau 8507",
    "addr:postcode":"8507",
    "addr:street":"Hauptstrasse;Thurgau",
    "iso:country":"CH",
    "sg:address":"Hauptstrasse",
    "sg:city":"H\u00f6rhausen",
    "sg:classifiers":[
        {
            "category":"Banks & Credit Unions",
            "subcategory":"Bank",
            "type":"Services"
        }
    ],
    "sg:phone":"+41 4154632420",
    "sg:postcode":"8507",
    "sg:province":"Thurgau",
    "wof:name":"Raiffeisenbank, G\u00fcndelhart-h\u00f6rhausen",
    "wof:placetype":"venue"
},
  "geometry": {"coordinates":[8.971179,47.632641],"type":"Point"}
}