{
  "type": "Feature",
  "properties": {
    "iso:country":"CH",
    "sg:address":"Hauptstrasse 24",
    "sg:city":"Kreuzlingen",
    "sg:orig_category":"Sonstige Kultur U Unterhaltungseinrichtungen Spielsalons",
    "sg:phone":"+41 71 672 35 70",
    "sg:postcode":"8280",
    "sg:province":"Thurgau",
    "wof:name":"Spielsalon Lucky Play",
    "wof:placetype":"venue"
},
  "geometry": {"coordinates":[9.1736631393,47.6522865295],"type":"Point"}
}