{
  "type": "Feature",
  "properties": {
    "iso:country":"CH",
    "sg:address":"Saint-honor\u00e9 Rue 3 2000 Neuch\u00e2tel. Postfach",
    "sg:city":"Neuenburg",
    "sg:orig_category":"Unclassifiable Establishments",
    "sg:phone":"+41 32 721 21 37",
    "sg:postcode":"2000",
    "sg:province":"Neuch\u00e2tel",
    "wof:name":"Si Jafab Sa",
    "wof:placetype":"venue"
},
  "geometry": {"coordinates":[6.9312009811,46.9907722473],"type":"Point"}
}