{
  "type": "Feature",
  "properties": {
    "iso:country":"CH",
    "sg:address":"Hauptstr. 405 Pf 7",
    "sg:city":"Rohrbach",
    "sg:classifiers":[
        {
            "category":"Manufacturing",
            "subcategory":"Rubber & Plastics",
            "type":"Manufacturing & Wholesale Goods"
        }
    ],
    "sg:phone":"+41 62 965 38 78",
    "sg:postcode":"4938",
    "sg:province":"Bern",
    "wof:name":"Ac Profil Ag",
    "wof:placetype":"venue"
},
  "geometry": {"coordinates":[7.8123750687,47.1359062195],"type":"Point"}
}