{
  "type": "Feature",
  "properties": {
    "iso:country":"CH",
    "sg:address":"Haglistrasse 17b 6315 Ober\u00e4geri. Postfach",
    "sg:city":"Ober\u00e4geri",
    "sg:orig_category":"Unclassifiable Establishments",
    "sg:postcode":"6315",
    "sg:province":"Zug",
    "wof:name":"V+h Beteiligungen Gmbh Consulting Und Management Dienstleistungen Im Ber. Finanzierung, Beteiligungen",
    "wof:placetype":"venue"
},
  "geometry": {"coordinates":[8.6019849777,47.1420211792],"type":"Point"}
}