{
  "type": "Feature",
  "properties": {
    "iso:country":"CH",
    "sg:address":"Comercialstrasse 19",
    "sg:city":"Chur",
    "sg:classifiers":[
        {
            "category":"Professional",
            "subcategory":"Advertising",
            "type":"Services"
        }
    ],
    "sg:phone":"+41 81 250 10 51",
    "sg:postcode":"7000",
    "sg:province":"Graubunden",
    "sg:tags":[
        "agency"
    ],
    "wof:name":"S\u00fcsskind Grafik Design Und Kommunikation Ag",
    "wof:placetype":"venue"
},
  "geometry": {"coordinates":[9.509939,46.847237],"type":"Point"}
}