{
  "type": "Feature",
  "properties": {
    "iso:country":"CH",
    "sg:address":"Kasernenstrasse 9a",
    "sg:city":"Herisau",
    "sg:orig_category":"Ingenieurb\u00fcros Elektro",
    "sg:phone":"+41 71 351 22 63",
    "sg:postcode":"9100",
    "sg:province":"Appenzell Ausserrhoden",
    "wof:name":"Otto Graf Elektro-ingenieur Ag",
    "wof:placetype":"venue"
},
  "geometry": {"coordinates":[9.2813158035,47.3860168457],"type":"Point"}
}