{
  "type": "Feature",
  "properties": {
    "iso:country":"CH",
    "sg:address":"Oberlandstrasse 6",
    "sg:city":"Spiez",
    "sg:orig_category":"Detailhandel mit Uhren U Schmuck Herstellung von Schmuck, Gold U Silberschmiedwaren",
    "sg:phone":"+41 33 654 64 74",
    "sg:postcode":"3700",
    "sg:province":"Bern",
    "wof:name":"G\u00fcnter Krauss Goldschmiede-atelier",
    "wof:placetype":"venue"
},
  "geometry": {"coordinates":[7.6758508682,46.6894378662],"type":"Point"}
}