{
  "type": "Feature",
  "properties": {
    "iso:country":"CH",
    "sg:address":"Oberdorf 20 A",
    "sg:city":"Oberhof",
    "sg:orig_category":"Softwareentwicklung U beratung",
    "sg:phone":"+41 62 877 14 18",
    "sg:postcode":"5062",
    "sg:province":"Aargau",
    "wof:name":"Gab, Gestaltungsatelier-druckstufe, Blattner Gmbh",
    "wof:placetype":"venue"
},
  "geometry": {"coordinates":[8.005689621,47.4516601562],"type":"Point"}
}