{
  "type": "Feature",
  "properties": {
    "iso:country":"CH",
    "sg:address":"Leimgr\u00fcbelstrasse 22a 8052 Seebach. Postfach 26",
    "sg:city":"Z\u00fcrich",
    "sg:orig_category":"Erbringung von Dienstleistungen f\u00fcr Unternehmen",
    "sg:phone":"+41 13711007",
    "sg:postcode":"8046",
    "sg:province":"Z\u00fcrich",
    "wof:name":"Delphinara, Baldi Jordana Ariela",
    "wof:placetype":"venue"
},
  "geometry": {"coordinates":[8.5402402878,47.4224815369],"type":"Point"}
}