{
  "type": "Feature",
  "properties": {
    "iso:country":"CH",
    "sg:address":"2532",
    "sg:city":"Magglingen/macolin",
    "sg:classifiers":[
        {
            "category":"Government",
            "subcategory":"Post Office",
            "type":"Public Place"
        }
    ],
    "sg:phone":"+41 32 322 28 05",
    "sg:postcode":"2532",
    "sg:province":"Bern",
    "sg:tags":[
        "die",
        "poststellen"
    ],
    "wof:name":"Die Post",
    "wof:placetype":"venue"
},
  "geometry": {"coordinates":[7.2113099098,47.1423492432],"type":"Point"}
}