{
  "type": "Feature",
  "properties": {
    "iso:country":"CH",
    "sg:address":"Via Carona 6",
    "sg:city":"Melide",
    "sg:orig_category":"Non-Classified Establishments",
    "sg:postcode":"6815",
    "sg:province":"Ticino",
    "wof:name":"Tele Ticino Sa",
    "wof:placetype":"venue"
},
  "geometry": {"coordinates":[8.9467906952,45.9557991028],"type":"Point"}
}