{
  "type": "Feature",
  "properties": {
    "iso:country":"CH",
    "sg:address":"Sandstrasse 67",
    "sg:city":"Moosseedorf",
    "sg:orig_category":"Informatikdienste Sonstige mit der Informatik verbundene T\u00e4tigkeiten",
    "sg:phone":"+41 31 859 90 34",
    "sg:postcode":"3302",
    "sg:province":"Bern",
    "wof:name":"Ph-webdesign Weil Qualit\u00e4t Einen Namen Hat",
    "wof:placetype":"venue"
},
  "geometry": {"coordinates":[7.4943451881,47.0116004944],"type":"Point"}
}