{
  "type": "Feature",
  "properties": {
    "addr:full":"Falkenstrasse 11 Z\u00fcrich Z\u00fcrich 8008",
    "addr:housenumber":"11",
    "addr:postcode":"8008",
    "addr:street":"Falkenstrasse",
    "iso:country":"CH",
    "sg:address":"Falkenstrasse 11",
    "sg:city":"Z\u00fcrich",
    "sg:classifiers":[
        {
            "category":"Professional",
            "subcategory":"Advertising",
            "type":"Services"
        }
    ],
    "sg:phone":"+41 12581111",
    "sg:postcode":"8008",
    "sg:province":"Z\u00fcrich",
    "sg:tags":[
        "job",
        "employment"
    ],
    "wof:name":"Ag F\u00fcr Die Neue Z\u00fcrcher Zeitung",
    "wof:placetype":"venue"
},
  "geometry": {"coordinates":[8.54739,47.364918],"type":"Point"}
}