{
  "type": "Feature",
  "properties": {
    "iso:country":"CH",
    "sg:address":"Furlenstrasse 66 4415 Lausen. Postfach",
    "sg:city":"Lausen",
    "sg:orig_category":"Herstellung von k\u00e4lte U lufttechnischen Erzeugnissen f\u00fcr gewerbliche Zwecke",
    "sg:phone":"+41 61 921 08 88",
    "sg:postcode":"4415",
    "sg:province":"Basel-Landschaft",
    "wof:name":"Eisgr\u00fcn Ag",
    "wof:placetype":"venue"
},
  "geometry": {"coordinates":[7.7586131096,47.466129303],"type":"Point"}
}