{
  "type": "Feature",
  "properties": {
    "iso:country":"CH",
    "sg:address":"Eschenstrasse 8",
    "sg:city":"Emmenbr\u00fccke",
    "sg:orig_category":"Detailhandel mit Fleisch U Fleischwaren",
    "sg:phone":"+41 41 260 22 22",
    "sg:postcode":"6020",
    "sg:province":"Luzern",
    "wof:name":"Vital & Esther Kopp",
    "wof:placetype":"venue"
},
  "geometry": {"coordinates":[8.2883892059,47.0724639893],"type":"Point"}
}