{
  "type": "Feature",
  "properties": {
    "iso:country":"CH",
    "sg:address":"Feld",
    "sg:city":"Gurtnellen",
    "sg:classifiers":[
        {
            "category":"Restaurant",
            "type":"Food & Drink"
        }
    ],
    "sg:phone":"+41 41 885 17 23",
    "sg:postcode":"6482",
    "sg:province":"Uri",
    "wof:name":"Restaurant Feld",
    "wof:placetype":"venue"
},
  "geometry": {"coordinates":[8.6282100677,46.7381362915],"type":"Point"}
}