{
  "type": "Feature",
  "properties": {
    "iso:country":"CH",
    "sg:address":"3973",
    "sg:city":"Venth\u00f4ne",
    "sg:orig_category":"Landesverteidigung, Sozialversicherung \u00d6ffentliche Verwaltung",
    "sg:phone":"+41 27 455 76 33",
    "sg:postcode":"3973",
    "sg:province":"Valais",
    "wof:name":"Centre De Protection Civile",
    "wof:placetype":"venue"
},
  "geometry": {"coordinates":[7.5217700005,46.3066291809],"type":"Point"}
}