{
  "type": "Feature",
  "properties": {
    "iso:country":"CH",
    "sg:address":"Rue De La Cour 2",
    "sg:city":"Gorgier",
    "sg:orig_category":"Gemeindeverwaltungen",
    "sg:phone":"+41 32 836 25 25",
    "sg:postcode":"2023",
    "sg:province":"Neuch\u00e2tel",
    "wof:name":"Administration Communale De Gorgier",
    "wof:placetype":"venue"
},
  "geometry": {"coordinates":[6.7802190781,46.9028778076],"type":"Point"}
}