{
  "type": "Feature",
  "properties": {
    "iso:country":"CH",
    "sg:address":"Rosenfeldweg 10",
    "sg:city":"Horw",
    "sg:orig_category":"Reparatur von Uhren U Schmuck",
    "sg:phone":"+41 41 340 75 43",
    "sg:postcode":"6048",
    "sg:province":"Luzern",
    "wof:name":"Herbert Gruber Uhrmacher",
    "wof:placetype":"venue"
},
  "geometry": {"coordinates":[8.3099069595,47.0231132507],"type":"Point"}
}