{
  "type": "Feature",
  "properties": {
    "iso:country":"CH",
    "sg:address":"F\u00f6hrenweg 9 4856 Glash\u00fctten. Postfach",
    "sg:city":"Glash\u00fctten",
    "sg:orig_category":"Unclassifiable Establishments",
    "sg:postcode":"4856",
    "sg:province":"Aargau",
    "wof:name":"J. Bohli Gmbh",
    "wof:placetype":"venue"
},
  "geometry": {"coordinates":[7.9699888229,47.3260192871],"type":"Point"}
}