{
  "type": "Feature",
  "properties": {
    "iso:country":"CH",
    "sg:address":"Maranerstrasse",
    "sg:city":"Arosa",
    "sg:orig_category":"Sportschulen Ski-& Snowboardschulen Sportvereine Ski",
    "sg:phone":"+41 22 797 38 25",
    "sg:postcode":"7050",
    "sg:province":"Graubunden",
    "wof:name":"Ski Club International & Ecole De Ski",
    "wof:placetype":"venue"
},
  "geometry": {"coordinates":[6.095459938,46.2035598755],"type":"Point"}
}