{
  "type": "Feature",
  "properties": {
    "iso:country":"CH",
    "sg:address":"Neuscheuer 2",
    "sg:city":"Jaun",
    "sg:orig_category":"Bauschreinerei",
    "sg:phone":"+41 79 230 64 94",
    "sg:postcode":"1656",
    "sg:province":"Fribourg",
    "wof:name":"Beat Buchs Schreinerei",
    "wof:placetype":"venue"
},
  "geometry": {"coordinates":[7.294595,46.611057],"type":"Point"}
}