{
  "type": "Feature",
  "properties": {
    "iso:country":"CH",
    "sg:address":"Sternhalde 7",
    "sg:city":"Luzern",
    "sg:orig_category":"Hardwareberatung",
    "sg:postcode":"6005",
    "sg:province":"Luzern",
    "wof:name":"Bricom Briker Communication",
    "wof:placetype":"venue"
},
  "geometry": {"coordinates":[8.3094005585,47.0386505127],"type":"Point"}
}