{
  "type": "Feature",
  "properties": {
    "iso:country":"CH",
    "sg:address":"Terreaux Rue Des 5 1003 Lausanne. Postfach",
    "sg:city":"Lausanne",
    "sg:orig_category":"Allgemeiner Hoch U Tiefbau",
    "sg:postcode":"1003",
    "sg:province":"Vaud",
    "wof:name":"Ettore Conti & Cie Sa",
    "wof:placetype":"venue"
},
  "geometry": {"coordinates":[6.145882,46.183704],"type":"Point"}
}