{
  "type": "Feature",
  "properties": {
    "iso:country":"CH",
    "sg:address":"Schl\u00f6sslerstrasse 60 8964 Rudolfstetten. Postfach 13",
    "sg:city":"Rudolfstetten",
    "sg:orig_category":"Sportvereine Ballsport Fussball",
    "sg:phone":"+41 56 633 88 26",
    "sg:postcode":"8964",
    "sg:province":"Aargau",
    "wof:name":"Fc Rudolfstetten",
    "wof:placetype":"venue"
},
  "geometry": {"coordinates":[8.3760623932,47.3667106628],"type":"Point"}
}