{
  "type": "Feature",
  "properties": {
    "iso:country":"CH",
    "sg:address":"Sous-raimeux 26",
    "sg:city":"Moutier",
    "sg:orig_category":"Religi\u00f6se Vereinigungen divers",
    "sg:phone":"+41 32 493 11 63",
    "sg:postcode":"2740",
    "sg:province":"Bern",
    "wof:name":"Cercle Catholique De Moutier",
    "wof:placetype":"venue"
},
  "geometry": {"coordinates":[7.3908782005,47.2805938721],"type":"Point"}
}