{
  "type": "Feature",
  "properties": {
    "iso:country":"CH",
    "sg:address":"Rue Cherbuliez 3",
    "sg:city":"Gen\u00e8ve",
    "sg:orig_category":"Grosshandel mit Datenverarbeitungsger\u00e4ten Herstellung von elektronischen Bauelementen",
    "sg:phone":"+41 22 840 05 42",
    "sg:postcode":"1207",
    "sg:province":"Gen\u00e8ve",
    "wof:name":"Abcd Electronique Tward",
    "wof:placetype":"venue"
},
  "geometry": {"coordinates":[6.1584968567,46.2039718628],"type":"Point"}
}