{
  "type": "Feature",
  "properties": {
    "iso:country":"CH",
    "sg:address":"Sonnenpl\u00e4tzli 5c",
    "sg:city":"Schwyz",
    "sg:orig_category":"Herstellung von sonstigen elektrischen Ausr\u00fcstungen Softwareentwicklung U beratung",
    "sg:phone":"+41 41 720 00 85",
    "sg:postcode":"6430",
    "sg:province":"Schwyz",
    "wof:name":"Primafin Software Ag",
    "wof:placetype":"venue"
},
  "geometry": {"coordinates":[8.6571149826,47.020450592],"type":"Point"}
}