{
  "type": "Feature",
  "properties": {
    "iso:country":"CH",
    "sg:address":"F\u00fcllerichstrasse 41",
    "sg:city":"G\u00fcmligen",
    "sg:orig_category":"Betrieb von Taxis",
    "sg:phone":"+41 31 951 74 51",
    "sg:postcode":"3073",
    "sg:province":"Bern",
    "wof:name":"Messerli & Hunziker Kombi-taxi Bern",
    "wof:placetype":"venue"
},
  "geometry": {"coordinates":[7.502222,46.932251],"type":"Point"}
}