{
  "type": "Feature",
  "properties": {
    "iso:country":"CH",
    "sg:address":"Schulstrasse 7",
    "sg:city":"Turbenthal",
    "sg:orig_category":"Institutionen f\u00fcr Behinderte Sonderschulen",
    "sg:phone":"+41 52 385 28 40",
    "sg:postcode":"8488",
    "sg:province":"Z\u00fcrich",
    "wof:name":"Heilp\u00e4dag.sonderschule Hst",
    "wof:placetype":"venue"
},
  "geometry": {"coordinates":[8.8464994431,47.438533783],"type":"Point"}
}