{
  "type": "Feature",
  "properties": {
    "iso:country":"CH",
    "sg:address":"Schwellm\u00fchlestrasse 5",
    "sg:city":"Oberegg",
    "sg:orig_category":"Massagestudios",
    "sg:phone":"+41 71 891 42 28",
    "sg:postcode":"9413",
    "sg:province":"Appenzell Innerhoden",
    "wof:name":"Karin Sp\u00f6rri Massagen",
    "wof:placetype":"venue"
},
  "geometry": {"coordinates":[9.5556764603,47.4219398499],"type":"Point"}
}