{
  "type": "Feature",
  "properties": {
    "iso:country":"CH",
    "sg:address":"Langstrasse 95-97",
    "sg:city":"Z\u00fcrich",
    "sg:orig_category":"Unclassifiable Establishments",
    "sg:postcode":"8004",
    "sg:province":"Z\u00fcrich",
    "wof:name":"Bistro-pub Aladin Yeter",
    "wof:placetype":"venue"
},
  "geometry": {"coordinates":[8.5266819,47.378276825],"type":"Point"}
}