{
  "type": "Feature",
  "properties": {
    "iso:country":"CH",
    "sg:address":"Y\u00e8res Chemin Des 4",
    "sg:city":"Bevaix",
    "sg:orig_category":"Herstellung von K\u00fcchenm\u00f6beln",
    "sg:phone":"+41 32 846 11 48",
    "sg:postcode":"2022",
    "sg:province":"Neuch\u00e2tel",
    "wof:name":"Steiner Jacqueline",
    "wof:placetype":"venue"
},
  "geometry": {"coordinates":[6.8152251244,46.9300765991],"type":"Point"}
}