{
  "type": "Feature",
  "properties": {
    "iso:country":"CH",
    "sg:address":"Neuwiesenstrasse 8",
    "sg:city":"Winterthur",
    "sg:orig_category":"Vermietung U Verpachtung von eigenen Immobilien",
    "sg:postcode":"8400",
    "sg:province":"Z\u00fcrich",
    "wof:name":"Elimar Immobilien Ag",
    "wof:placetype":"venue"
},
  "geometry": {"coordinates":[8.7203817368,47.5010108948],"type":"Point"}
}