{
  "type": "Feature",
  "properties": {
    "iso:country":"CH",
    "sg:address":"Kehlhofh\u00f6he 20",
    "sg:city":"Adligenswil",
    "sg:orig_category":"Architekturb\u00fcros",
    "sg:phone":"+41 41 370 20 16",
    "sg:postcode":"6043",
    "sg:province":"Luzern",
    "wof:name":"Herbert Kaufmann Architekturb\u00fcro",
    "wof:placetype":"venue"
},
  "geometry": {"coordinates":[8.363687,47.077084],"type":"Point"}
}