{
  "type": "Feature",
  "properties": {
    "iso:country":"CH",
    "sg:address":"Gagoz 75 9496 Balzers. Postfach 146",
    "sg:city":"Balzers",
    "sg:orig_category":"Verwaltung von Immobilien Wirtschaftspr\u00fcfung, Steuerberatung U Treuhand",
    "sg:phone":"+41 81 844 09 37",
    "sg:postcode":"9496",
    "wof:name":"Marchesi Edgaro",
    "wof:placetype":"venue"
},
  "geometry": {"coordinates":[10.0633115768,46.3106536865],"type":"Point"}
}