{
  "type": "Feature",
  "properties": {
    "iso:country":"CH",
    "sg:address":"Ringstrasse 15 4600 Olten. Postfach",
    "sg:city":"Olten",
    "sg:orig_category":"Grossbanken",
    "sg:phone":"+41 62 205 44 44",
    "sg:postcode":"4603",
    "sg:province":"Solothurn",
    "wof:name":"Ubs Ag",
    "wof:placetype":"venue"
},
  "geometry": {"coordinates":[7.9012880325,47.3517837524],"type":"Point"}
}