{
  "type": "Feature",
  "properties": {
    "iso:country":"CH",
    "sg:address":"Dorfstrasse 17 6454 Fl\u00fcelen. Postfach",
    "sg:city":"Fl\u00fcelen",
    "sg:orig_category":"Sanit\u00e4r U Heizungsinstallation Sanit\u00e4rinstallation",
    "sg:phone":"+41 41 870 21 79",
    "sg:postcode":"6454",
    "sg:province":"Uri",
    "wof:name":"Arndt & Schuler Gmbh Sanit\u00e4re Anlagen & Heizungen",
    "wof:placetype":"venue"
},
  "geometry": {"coordinates":[8.6258802414,46.9021263123],"type":"Point"}
}