{
  "type": "Feature",
  "properties": {
    "iso:country":"CH",
    "sg:address":"Bernstr. 3 3184 W\u00fcnnewil. Postfach",
    "sg:city":"Flamatt",
    "sg:orig_category":"Mit dem Versicherungsgewerbe verbundene T\u00e4tigkeiten",
    "sg:postcode":"3175",
    "sg:province":"Fribourg",
    "wof:name":"Versicherungstreuhand Staub D.",
    "wof:placetype":"venue"
},
  "geometry": {"coordinates":[7.2761421204,46.8746261597],"type":"Point"}
}