{
  "type": "Feature",
  "properties": {
    "iso:country":"CH",
    "sg:address":"Avenue Louis Edouard Junod 7",
    "sg:city":"Lucens",
    "sg:orig_category":"Grosshandel mit Nahrungsmitteln, Getr\u00e4nken U Tabakwaren Herstellung von medizinischen U chirurgische",
    "sg:phone":"+41 21 906 12 35",
    "sg:postcode":"1522",
    "sg:province":"Vaud",
    "wof:name":"Amicot Trade & Consult S\u00e0rl",
    "wof:placetype":"venue"
},
  "geometry": {"coordinates":[6.8370761871,46.7083587646],"type":"Point"}
}