{
  "type": "Feature",
  "properties": {
    "iso:country":"CH",
    "sg:address":"Therwilerstrasse 11",
    "sg:city":"M\u00fcnchenstein",
    "sg:orig_category":"Vereine Fasnacht",
    "sg:postcode":"4142",
    "sg:province":"Basel-Landschaft",
    "wof:name":"D\u00e4filutscher",
    "wof:placetype":"venue"
},
  "geometry": {"coordinates":[7.6060090065,47.5246086121],"type":"Point"}
}