{
  "type": "Feature",
  "properties": {
    "iso:country":"CH",
    "sg:address":"Birkenweg 6 4528 Zuchwil. Postfach",
    "sg:city":"Zuchwil",
    "sg:orig_category":"Sonstige mit der Informatik verbundene T\u00e4tigkeiten",
    "sg:postcode":"4528",
    "sg:province":"Solothurn",
    "wof:name":"Abc All Bennett Consulting Beratung U. Dienstleistung Im Bereich Informatik",
    "wof:placetype":"venue"
},
  "geometry": {"coordinates":[7.5524020195,47.1962852478],"type":"Point"}
}