{
  "type": "Feature",
  "properties": {
    "iso:country":"CH",
    "sg:address":"Hotel Riederfurka 3986 Ried-m\u00f6rel. Postfach",
    "sg:city":"Riederalp",
    "sg:orig_category":"Grosshandel mit Getr\u00e4nken",
    "sg:postcode":"3987",
    "sg:province":"Valais",
    "wof:name":"Bwp Gmbh",
    "wof:placetype":"venue"
},
  "geometry": {"coordinates":[8.3039693832,46.9915542603],"type":"Point"}
}