{
  "type": "Feature",
  "properties": {
    "addr:full":"Via Dei Solari 4 Lugano Ticino 6900",
    "addr:housenumber":"4",
    "addr:postcode":"6900",
    "addr:street":"Via Dei Solari",
    "iso:country":"CH",
    "sg:address":"Via Dei Solari 4",
    "sg:city":"Lugano",
    "sg:orig_category":"Detailhandel mit Bekleidung",
    "sg:phone":"+41 91 922 64 64",
    "sg:postcode":"6900",
    "sg:province":"Ticino",
    "wof:name":"Gruppo Immagine Marketing Ltd, Wilmington, Succursale Di Lugano",
    "wof:placetype":"venue"
},
  "geometry": {"coordinates":[8.950166,46.003716],"type":"Point"}
}