{
  "type": "Feature",
  "properties": {
    "iso:country":"CH",
    "sg:address":"Passage Zum Stein",
    "sg:city":"Luzern",
    "sg:orig_category":"Pensionskassen",
    "sg:phone":"+41 41 310 20 56",
    "sg:postcode":"6004",
    "sg:province":"Luzern",
    "wof:name":"Personalf\u00fcrsorgestiftung Der Twerenbold Ag",
    "wof:placetype":"venue"
},
  "geometry": {"coordinates":[8.3083496094,47.0538864136],"type":"Point"}
}