{
  "type": "Feature",
  "properties": {
    "iso:country":"CH",
    "sg:address":"Rebmattli 23",
    "sg:city":"Baar",
    "sg:orig_category":"Rechtsberatung",
    "sg:phone":"+41 41 761 44 89",
    "sg:postcode":"6340",
    "sg:province":"Zug",
    "wof:name":"Geapag Ag",
    "wof:placetype":"venue"
},
  "geometry": {"coordinates":[8.5144376755,47.2038993835],"type":"Point"}
}