{
  "type": "Feature",
  "properties": {
    "addr:full":"Friberig Weissenburg Bern 3764",
    "addr:postcode":"3764",
    "iso:country":"CH",
    "sg:address":"Friberig",
    "sg:city":"Weissenburg",
    "sg:classifiers":[
        {
            "category":"Manufacturing",
            "subcategory":"Wood Products",
            "type":"Manufacturing & Wholesale Goods"
        }
    ],
    "sg:phone":"+41 33 783 12 36",
    "sg:postcode":"3764",
    "sg:province":"Bern",
    "sg:tags":[
        "solid",
        "ceiling",
        "made",
        "panel"
    ],
    "wof:name":"Bieri Ag M\u00f6bel Und Innenausbau",
    "wof:placetype":"venue"
},
  "geometry": {"coordinates":[7.47795,46.663574],"type":"Point"}
}