{
  "type": "Feature",
  "properties": {
    "iso:country":"CH",
    "sg:address":"Hauptstrasse 550",
    "sg:city":"Welschenrohr",
    "sg:orig_category":"Detailhandel mit Brot, Back U S\u00fcsswaren",
    "sg:phone":"+41 56 622 23 23",
    "sg:postcode":"4716",
    "sg:province":"Solothurn",
    "wof:name":"Bruno Kuhn B\u00e4ckerei-konditorei",
    "wof:placetype":"venue"
},
  "geometry": {"coordinates":[8.281285,47.350178],"type":"Point"}
}