{
  "type": "Feature",
  "properties": {
    "iso:country":"CH",
    "sg:address":"Neugr\u00fct 21",
    "sg:city":"Balzers",
    "sg:classifiers":[
        {
            "category":"Manufacturing",
            "subcategory":"Metals",
            "type":"Manufacturing & Wholesale Goods"
        }
    ],
    "sg:phone":"+41 41 850 70 92",
    "sg:postcode":"9496",
    "sg:tags":[
        "u",
        "leichtmetallbau",
        "stahl"
    ],
    "wof:name":"Bruggmann & Co., Edelstahl",
    "wof:placetype":"venue"
},
  "geometry": {"coordinates":[8.435631752,47.0841751099],"type":"Point"}
}