{
  "type": "Feature",
  "properties": {
    "iso:country":"CH",
    "sg:address":"Blumenbergplatz 5",
    "sg:city":"St.gallen",
    "sg:orig_category":"Institutionen f\u00fcr Behinderte",
    "sg:phone":"+41 71 223 33 53",
    "sg:postcode":"9000",
    "sg:province":"St. Gallen",
    "wof:name":"Wohntrainingsgruppe F\u00fcr Geistigbehinderte",
    "wof:placetype":"venue"
},
  "geometry": {"coordinates":[9.3734941483,47.4266433716],"type":"Point"}
}