{
  "type": "Feature",
  "properties": {
    "iso:country":"CH",
    "sg:address":"Hotel Cresta Palace",
    "sg:city":"Schlarigna",
    "sg:orig_category":"Wirtschafts- and Arbeitgeberverb\u00e4nde",
    "sg:phone":"+41 81 416 17 88",
    "sg:postcode":"7505",
    "sg:province":"Graubunden",
    "wof:name":"Hotelier-verein Davos Sporthotel Meierhof",
    "wof:placetype":"venue"
},
  "geometry": {"coordinates":[9.8370513916,46.8057327271],"type":"Point"}
}