{
  "type": "Feature",
  "properties": {
    "iso:country":"CH",
    "sg:address":"La Fortune",
    "sg:city":"Donneloye",
    "sg:orig_category":"Schreib U \u00dcbersetzungsb\u00fcros",
    "sg:phone":"+41 24 433 15 48",
    "sg:postcode":"1407",
    "sg:province":"Vaud",
    "wof:name":"Objectif Communication, Gabrielle Desarzens",
    "wof:placetype":"venue"
},
  "geometry": {"coordinates":[6.7153749466,46.7413291931],"type":"Point"}
}