{
  "type": "Feature",
  "properties": {
    "iso:country":"CH",
    "sg:address":"Freiburgstrasse 394 3018 Bern. Postfach",
    "sg:city":"Bern",
    "sg:orig_category":"Verwaltung von Immobilien",
    "sg:phone":"+41 800 553 162",
    "sg:postcode":"3018",
    "sg:province":"Bern",
    "wof:name":"Schneider H. & Co Verwaltg. V. Immobilien",
    "wof:placetype":"venue"
},
  "geometry": {"coordinates":[7.3923039436,46.9348182678],"type":"Point"}
}