{
  "type": "Feature",
  "properties": {
    "iso:country":"CH",
    "sg:address":"Rte De La Grangette 46",
    "sg:city":"Marly",
    "sg:orig_category":"Herstellung von k\u00e4lte U lufttechnischen Erzeugnissen f\u00fcr gewerbliche Zwecke",
    "sg:phone":"+41 26 436 16 28",
    "sg:postcode":"1723",
    "sg:province":"Fribourg",
    "wof:name":"Ksm Klima-service-marly S\u00e0rl",
    "wof:placetype":"venue"
},
  "geometry": {"coordinates":[7.1583480835,46.7814750671],"type":"Point"}
}