{
  "type": "Feature",
  "properties": {
    "iso:country":"CH",
    "sg:address":"1997",
    "sg:city":"Haute-nendaz",
    "sg:orig_category":"Arztpraxen",
    "sg:phone":"+41 27 288 15 34",
    "sg:postcode":"1997",
    "sg:province":"Valais",
    "wof:name":"Dr M\u00e9d.sylviane Boissard M\u00e9decin G\u00e9n\u00e9raliste",
    "wof:placetype":"venue"
},
  "geometry": {"coordinates":[7.29811,46.184151],"type":"Point"}
}