{
  "type": "Feature",
  "properties": {
    "addr:full":"Rossau Mettmenstetten Z\u00fcrich 8932",
    "addr:postcode":"8932",
    "addr:street":"Zuerich",
    "iso:country":"CH",
    "sg:address":"Rossau",
    "sg:city":"Mettmenstetten",
    "sg:orig_category":"Berufsorganisationen",
    "sg:postcode":"8932",
    "sg:province":"Z\u00fcrich",
    "wof:name":"Verein G\u00e4stehaus Und Gutsbetrieb G\u00fcetli",
    "wof:placetype":"venue"
},
  "geometry": {"coordinates":[8.48312,47.226768],"type":"Point"}
}