{
  "type": "Feature",
  "properties": {
    "iso:country":"CH",
    "sg:address":"Alfred-aebi-strasse 92",
    "sg:city":"Biel/bienne",
    "sg:orig_category":"Detailhandel mit Waren verschiedener Art, Hauptrichtung Nahrungsmittel",
    "sg:phone":"+41 32 322 00 66",
    "sg:postcode":"2503",
    "sg:province":"Bern",
    "wof:name":"Denner Top Superdiscount",
    "wof:placetype":"venue"
},
  "geometry": {"coordinates":[7.251352787,47.1319541931],"type":"Point"}
}