{
  "type": "Feature",
  "properties": {
    "iso:country":"CH",
    "sg:address":"Via Tesserete 46",
    "sg:city":"Lugano",
    "sg:orig_category":"Universit\u00e4tsspit\u00e4ler, Spit\u00e4ler f\u00fcr allgemeine Pflege",
    "sg:phone":"+41 91 805 61 11",
    "sg:postcode":"6900",
    "sg:province":"Ticino",
    "wof:name":"Ospedale Civico",
    "wof:placetype":"venue"
},
  "geometry": {"coordinates":[8.9521255493,46.0178527832],"type":"Point"}
}