{
  "type": "Feature",
  "properties": {
    "iso:country":"CH",
    "sg:address":"P\u00fcndtstrasse 11",
    "sg:city":"Uster",
    "sg:orig_category":"Detailhandel mit elektrischen Haushalts-,Radio U Fernsehger\u00e4ten sowie Musikinstrumenten Reparatur vo",
    "sg:phone":"+41 19420501",
    "sg:postcode":"8610",
    "sg:province":"Z\u00fcrich",
    "wof:name":"Zoia Engineering",
    "wof:placetype":"venue"
},
  "geometry": {"coordinates":[8.7103309631,47.3494720459],"type":"Point"}
}