{
  "type": "Feature",
  "properties": {
    "iso:country":"CH",
    "sg:address":"Rampe De La Gare 7 1290 Versoix. Postfach",
    "sg:city":"Versoix",
    "sg:orig_category":"Detailhandel mit S\u00e4uglings U Kinderbekleidung Herstellung von W\u00e4sche",
    "sg:phone":"+41 22 779 31 39",
    "sg:postcode":"1290",
    "sg:province":"Gen\u00e8ve",
    "wof:name":"Pain D'\u00e9pices, Mode Enfantine S\u00e0rl Boutique De Mode Enfantine",
    "wof:placetype":"venue"
},
  "geometry": {"coordinates":[6.1669659615,46.2793922424],"type":"Point"}
}