{
  "type": "Feature",
  "properties": {
    "addr:full":"Frohmattrain 433 Kleinl\u00fctzel Solothurn 4245",
    "addr:housenumber":"433;4245",
    "addr:street":"Frohmattrain;Solothurn",
    "iso:country":"CH",
    "sg:address":"Frohmattrain 433",
    "sg:city":"Kleinl\u00fctzel",
    "sg:orig_category":"Bauspenglerei Sanit\u00e4rinstallation",
    "sg:phone":"+41 41 460 19 39",
    "sg:postcode":"4245",
    "sg:province":"Solothurn",
    "wof:name":"Alexander Duss San.anlagen & Bauspenglerei",
    "wof:placetype":"venue"
},
  "geometry": {"coordinates":[8.223583,47.131149],"type":"Point"}
}