{
  "type": "Feature",
  "properties": {
    "iso:country":"CH",
    "sg:address":"Neugasse 33",
    "sg:city":"Widnau",
    "sg:orig_category":"Physiotherapie",
    "sg:phone":"+41 71 722 62 92",
    "sg:postcode":"9443",
    "sg:province":"St. Gallen",
    "wof:name":"Medical Fitness Widnau/heerbrugg Und Physiotherapiezentrum Delgrosso Physiotherapie",
    "wof:placetype":"venue"
},
  "geometry": {"coordinates":[9.6416912079,47.4050331116],"type":"Point"}
}