{
  "type": "Feature",
  "properties": {
    "iso:country":"CH",
    "sg:address":"Chemin Des Tuileries 33",
    "sg:city":"Bellevue",
    "sg:orig_category":"Gem\u00fcsebau",
    "sg:phone":"+41 22 774 12 06",
    "sg:postcode":"1293",
    "sg:province":"Gen\u00e8ve",
    "wof:name":"Andr\u00e9 Tschudin Maraicher",
    "wof:placetype":"venue"
},
  "geometry": {"coordinates":[6.1405291557,46.2557945251],"type":"Point"}
}