{
  "type": "Feature",
  "properties": {
    "iso:country":"CH",
    "sg:address":"Claridenstrasse 23 8305 Dietlikon. Postfach",
    "sg:city":"Dietlikon",
    "sg:orig_category":"Unternehmensberatung",
    "sg:phone":"+41 18335415",
    "sg:postcode":"8305",
    "sg:province":"Z\u00fcrich",
    "wof:name":"Alana Gmbh Bereitstellung Von Dienstleistungen In Den Bereichen Management, Management Support Usw",
    "wof:placetype":"venue"
},
  "geometry": {"coordinates":[8.6183586121,47.4174613953],"type":"Point"}
}