{
  "type": "Feature",
  "properties": {
    "iso:country":"CH",
    "sg:address":"Schottengasse 12",
    "sg:city":"Bischofszell",
    "sg:orig_category":"Vereine Gesang",
    "sg:phone":"+41 81 416 25 58",
    "sg:postcode":"9220",
    "sg:province":"Thurgau",
    "wof:name":"Singkreis Davos",
    "wof:placetype":"venue"
},
  "geometry": {"coordinates":[9.8537597656,46.8327331543],"type":"Point"}
}