{
  "type": "Feature",
  "properties": {
    "iso:country":"CH",
    "sg:address":"Freiburgstrasse 41",
    "sg:city":"B\u00f6singen",
    "sg:orig_category":"Unclassifiable Establishments",
    "sg:postcode":"3178",
    "sg:province":"Fribourg",
    "wof:name":"Fireprof Peter Balsiger",
    "wof:placetype":"venue"
},
  "geometry": {"coordinates":[7.2252879143,46.8897514343],"type":"Point"}
}