{
  "type": "Feature",
  "properties": {
    "iso:country":"CH",
    "sg:address":"Marcacci Via 10",
    "sg:city":"Locarno",
    "sg:orig_category":"Verwaltung von Immobilien",
    "sg:postcode":"6600",
    "sg:province":"Ticino",
    "wof:name":"P\u00e9n\u00f3 Sagl",
    "wof:placetype":"venue"
},
  "geometry": {"coordinates":[8.7950973511,46.1705589294],"type":"Point"}
}