{
  "type": "Feature",
  "properties": {
    "iso:country":"CH",
    "sg:address":"Winznauerstrasse 101",
    "sg:city":"Trimbach",
    "sg:orig_category":"Detailhandel mit M\u00f6beln U Haushaltsgegenst\u00e4nden Grosshandel mit M\u00f6beln, Wohnbedarf, Teppichen U Bode",
    "sg:phone":"+41 55 240 93 06",
    "sg:postcode":"4632",
    "sg:province":"Solothurn",
    "wof:name":"Schmidt Hans Orientteppichimport Ag",
    "wof:placetype":"venue"
},
  "geometry": {"coordinates":[8.8678617477,47.2678642273],"type":"Point"}
}