{
  "type": "Feature",
  "properties": {
    "iso:country":"CH",
    "sg:address":"Hirschengraben 3 3011 Bern. Postfach",
    "sg:city":"Bern",
    "sg:orig_category":"Finanzierungsinstitutionen",
    "sg:phone":"+41 31 666 10 88",
    "sg:postcode":"3001",
    "sg:province":"Bern",
    "wof:name":"Dezennium-finanz Ag Finanzierung V Jurist. U Nat\u00fcrlichen Personen Usw",
    "wof:placetype":"venue"
},
  "geometry": {"coordinates":[7.4381828308,46.9467887878],"type":"Point"}
}