{
  "type": "Feature",
  "properties": {
    "addr:full":"Strandboden Murg St. Gallen 8877",
    "addr:postcode":"8877",
    "addr:street":"Murg",
    "iso:country":"CH",
    "sg:address":"Strandboden",
    "sg:city":"Murg",
    "sg:orig_category":"Campingpl\u00e4tze",
    "sg:phone":"+41 81 738 15 30",
    "sg:postcode":"8877",
    "sg:province":"St. Gallen",
    "wof:name":"Camping-platz",
    "wof:placetype":"venue"
},
  "geometry": {"coordinates":[9.215042,47.114334],"type":"Point"}
}