{
  "type": "Feature",
  "properties": {
    "iso:country":"CH",
    "sg:address":"Gr\u00fcnaustrasse 14a 8370 Sirnach. Postfach",
    "sg:city":"Sirnach",
    "sg:orig_category":"Interessenvertretungen",
    "sg:postcode":"8370",
    "sg:province":"Thurgau",
    "wof:name":"Mackeben Theo Foundation (tmf)",
    "wof:placetype":"venue"
},
  "geometry": {"coordinates":[8.9971323013,47.4638137817],"type":"Point"}
}