{
  "type": "Feature",
  "properties": {
    "iso:country":"CH",
    "sg:address":"Vorderbergstrasse 41",
    "sg:city":"Walchwil",
    "sg:orig_category":"Autogaragen",
    "sg:phone":"+41 41 758 10 50",
    "sg:postcode":"6318",
    "sg:province":"Zug",
    "wof:name":"Fritz Zeindler Autoservice",
    "wof:placetype":"venue"
},
  "geometry": {"coordinates":[8.513042,47.106609],"type":"Point"}
}