{
  "type": "Feature",
  "properties": {
    "iso:country":"CH",
    "sg:address":"Lerchenb\u00fchlh\u00f6he 3",
    "sg:city":"Meggen",
    "sg:orig_category":"Vorschulen, Kinderg\u00e4rten",
    "sg:phone":"+41 41 377 25 82",
    "sg:postcode":"6045",
    "sg:province":"Luzern",
    "wof:name":"Kindergarten Lerchenb\u00fchl",
    "wof:placetype":"venue"
},
  "geometry": {"coordinates":[8.3614320755,47.0416297913],"type":"Point"}
}