{
  "type": "Feature",
  "properties": {
    "iso:country":"CH",
    "sg:address":"Unterdorfstrasse 25 3072 Ostermundigen. Postfach",
    "sg:city":"Ostermundigen",
    "sg:orig_category":"G\u00fcterbef\u00f6rderung im Strassenverkehr Sonstige Kurierdienste",
    "sg:phone":"+41 31 931 32 54",
    "sg:postcode":"3072",
    "sg:province":"Bern",
    "wof:name":"Vipa Trans Gmbh Kurierdienste U. Transporte",
    "wof:placetype":"venue"
},
  "geometry": {"coordinates":[7.4913358688,46.9609489441],"type":"Point"}
}