{
  "type": "Feature",
  "properties": {
    "iso:country":"CH",
    "sg:address":"Winkelweg 7",
    "sg:city":"Niederdorf",
    "sg:orig_category":"Sportvereine Sch\u00fctzen Pistolen-& Gewehr",
    "sg:postcode":"4435",
    "sg:province":"Basel-Landschaft",
    "wof:name":"Pistolensekt.oberdorf & Umg.",
    "wof:placetype":"venue"
},
  "geometry": {"coordinates":[7.7500109673,47.4069747925],"type":"Point"}
}