{
  "type": "Feature",
  "properties": {
    "iso:country":"CH",
    "sg:address":"Hansbrunnen 3",
    "sg:city":"Rudolfstetten",
    "sg:orig_category":"Politische Parteien SVP",
    "sg:phone":"+41 56 633 10 77",
    "sg:postcode":"8964",
    "sg:province":"Aargau",
    "wof:name":"Svp Ortspartei Rudolfstetten",
    "wof:placetype":"venue"
},
  "geometry": {"coordinates":[8.3759632111,47.3656616211],"type":"Point"}
}