{
  "type": "Feature",
  "properties": {
    "iso:country":"CH",
    "sg:address":"Felseggweg 1c",
    "sg:city":"Henau",
    "sg:orig_category":"Innendekorationsateliers",
    "sg:phone":"+41 79 353 55 23",
    "sg:postcode":"9247",
    "sg:province":"St. Gallen",
    "wof:name":"Tema Form",
    "wof:placetype":"venue"
},
  "geometry": {"coordinates":[9.1203069687,47.4608917236],"type":"Point"}
}