{
  "type": "Feature",
  "properties": {
    "iso:country":"CH",
    "sg:address":"Au Village",
    "sg:city":"Epagny",
    "sg:orig_category":"Geb\u00e4ude, Wohnungsreinigung",
    "sg:postcode":"1664",
    "wof:name":"Sergio Coduri Cc-reinigungen",
    "wof:placetype":"venue"
},
  "geometry": {"coordinates":[8.3837757111,47.3345947266],"type":"Point"}
}