{
  "type": "Feature",
  "properties": {
    "iso:country":"CH",
    "sg:address":"Dammstrasse 38",
    "sg:city":"Opfikon",
    "sg:orig_category":"Elektroinstallation",
    "sg:phone":"+41 18102233",
    "sg:postcode":"8152",
    "sg:province":"Z\u00fcrich",
    "wof:name":"Ets Telecom Gmbh",
    "wof:placetype":"venue"
},
  "geometry": {"coordinates":[8.5655708313,47.4371795654],"type":"Point"}
}