{
  "type": "Feature",
  "properties": {
    "iso:country":"CH",
    "sg:address":"Impasse Du Nouveau-march\u00e9 1",
    "sg:city":"Marly",
    "sg:orig_category":"Detailhandel mit Blumen U Pflanzen Fachdetailhandel in Verkaufsr\u00e4umen",
    "sg:phone":"+41 52 233 60 00",
    "sg:postcode":"1723",
    "sg:province":"Fribourg",
    "wof:name":"La Terra Floristik, M\u00fchlethaler Urs",
    "wof:placetype":"venue"
},
  "geometry": {"coordinates":[8.760722,47.483559],"type":"Point"}
}