{
  "type": "Feature",
  "properties": {
    "addr:full":"Chemin Louis-d\u00e9gallier 8 Versoix Gen\u00e8ve 1290",
    "addr:housenumber":"8",
    "addr:postcode":"1290",
    "addr:street":"Chemin Louis-De\u0301Gallier",
    "iso:country":"CH",
    "sg:address":"Chemin Louis-d\u00e9gallier 8",
    "sg:city":"Versoix",
    "sg:orig_category":"Bauschreinerei Forstwirtschaft ohne Dienstleistungen in der Forstwirtschaft",
    "sg:phone":"+41 22 755 13 92",
    "sg:postcode":"1290",
    "sg:province":"Gen\u00e8ve",
    "wof:name":"Maurice Bianchetti Menuiserie",
    "wof:placetype":"venue"
},
  "geometry": {"coordinates":[6.163649,46.28212],"type":"Point"}
}