{
  "type": "Feature",
  "properties": {
    "iso:country":"CH",
    "sg:address":"Via Loco Coste",
    "sg:city":"Gordola",
    "sg:orig_category":"Unternehmensberatung",
    "sg:phone":"+41 91 745 32 33",
    "sg:postcode":"6596",
    "sg:province":"Ticino",
    "wof:name":"Karl Werner M\u00fcller Consigliere Industriale",
    "wof:placetype":"venue"
},
  "geometry": {"coordinates":[8.8596429825,46.1857032776],"type":"Point"}
}