{
  "type": "Feature",
  "properties": {
    "iso:country":"CH",
    "sg:address":"Fliederweg 14",
    "sg:city":"Schwadernau",
    "sg:orig_category":"Unternehmensberatung",
    "sg:phone":"+41 32 373 48 56",
    "sg:postcode":"2556",
    "sg:province":"Bern",
    "wof:name":"Thoma Josef Consulting",
    "wof:placetype":"venue"
},
  "geometry": {"coordinates":[7.301527977,47.1260757446],"type":"Point"}
}