{
  "type": "Feature",
  "properties": {
    "iso:country":"CH",
    "sg:address":"Rue Du Puits-godet 20",
    "sg:city":"Neuch\u00e2tel",
    "sg:orig_category":"Gymnastik U Fitnesszentren Saunas, Solarien, Fitnesszentren U \u00e4hnliches",
    "sg:phone":"+41 32 724 25 60",
    "sg:postcode":"2000",
    "sg:province":"Neuch\u00e2tel",
    "wof:name":"Body Tonic, Locatelli",
    "wof:placetype":"venue"
},
  "geometry": {"coordinates":[6.9117689133,46.9982261658],"type":"Point"}
}