{
  "type": "Feature",
  "properties": {
    "iso:country":"CH",
    "sg:address":"Chemin Du Fief-de-chapitre",
    "sg:city":"Petit-lancy",
    "sg:orig_category":"Vorschulen, Kinderg\u00e4rten",
    "sg:phone":"+41 22 342 80 42",
    "sg:postcode":"1213",
    "sg:province":"Gen\u00e8ve",
    "wof:name":"Ecole Enfantine Tours I-iii",
    "wof:placetype":"venue"
},
  "geometry": {"coordinates":[6.1360731125,46.183467865],"type":"Point"}
}