{
  "type": "Feature",
  "properties": {
    "iso:country":"CH",
    "sg:address":"Bodenacker 56",
    "sg:city":"Liedertswil",
    "sg:orig_category":"Vereine Musik/Blasmusik",
    "sg:phone":"+41 61 961 10 04",
    "sg:postcode":"4436",
    "sg:province":"Basel-Landschaft",
    "wof:name":"Musikverein Oberdorf/bl",
    "wof:placetype":"venue"
},
  "geometry": {"coordinates":[7.7162852287,47.3911781311],"type":"Point"}
}