{
  "type": "Feature",
  "properties": {
    "iso:country":"CH",
    "sg:address":"Parkallee Grabenstrasse",
    "sg:city":"Bachenb\u00fclach",
    "sg:orig_category":"Detailhandel mit Blumen U Pflanzen Fachdetailhandel in Verkaufsr\u00e4umen",
    "sg:phone":"+41 18626180",
    "sg:postcode":"8184",
    "sg:province":"Z\u00fcrich",
    "wof:name":"Les Fleurs, Van Heuveln M.",
    "wof:placetype":"venue"
},
  "geometry": {"coordinates":[8.54821,47.502731],"type":"Point"}
}