{
  "type": "Feature",
  "properties": {
    "addr:full":"Avenue Du Coll\u00e8ge 22 Boudry Neuch\u00e2tel 2017",
    "addr:housenumber":"22",
    "addr:postcode":"2017",
    "addr:street":"Avenue Du Colle\u0300Ge;Neucha\u0302Tel",
    "iso:country":"CH",
    "sg:address":"Avenue Du Coll\u00e8ge 22",
    "sg:city":"Boudry",
    "sg:classifiers":[
        {
            "category":"Education",
            "subcategory":"Library",
            "type":"Public Place"
        }
    ],
    "sg:phone":"+41 32 842 32 82",
    "sg:postcode":"2017",
    "sg:province":"Neuch\u00e2tel",
    "sg:tags":[
        "u",
        "bibliotheken",
        "archive"
    ],
    "wof:name":"Biblioth\u00e8que Communale",
    "wof:placetype":"venue"
},
  "geometry": {"coordinates":[6.839602,46.95018],"type":"Point"}
}