{
  "type": "Feature",
  "properties": {
    "iso:country":"CH",
    "sg:address":"Uttigenstrasse 62 3661 Uetendorf. Postfach",
    "sg:city":"Uetendorf",
    "sg:orig_category":"W\u00e4scherei U chemische Reinigung",
    "sg:postcode":"3661",
    "sg:province":"Bern",
    "wof:name":"Mister Clean Teppich Und Polsterreinigungen, H\u00e4fliger Franz",
    "wof:placetype":"venue"
},
  "geometry": {"coordinates":[7.5904169083,46.77891922],"type":"Point"}
}