{
  "type": "Feature",
  "properties": {
    "iso:country":"CH",
    "sg:address":"Ai Campisc",
    "sg:city":"Camorino",
    "sg:orig_category":"Mechanische Werkst\u00e4tten",
    "sg:phone":"+41 55 251 58 58",
    "sg:postcode":"6528",
    "sg:province":"Ticino",
    "wof:name":"Kanya Ag",
    "wof:placetype":"venue"
},
  "geometry": {"coordinates":[8.8668546677,47.2671203613],"type":"Point"}
}