{
  "type": "Feature",
  "properties": {
    "addr:full":"Via Vallemaggia 1 Locarno Ticino 6600",
    "addr:housenumber":"1",
    "addr:postcode":"6600",
    "addr:street":"Via Vallemaggia;Ticino",
    "iso:country":"CH",
    "sg:address":"Via Vallemaggia 1",
    "sg:city":"Locarno",
    "sg:orig_category":"Bestattungswesen",
    "sg:phone":"+41 79 332 33 55",
    "sg:postcode":"6600",
    "sg:province":"Ticino",
    "wof:name":"Guignard Fromont Et Roulet, Pompes Fun\u00e8bres",
    "wof:placetype":"venue"
},
  "geometry": {"coordinates":[6.829905,47.10281],"type":"Point"}
}