{
  "type": "Feature",
  "properties": {
    "iso:country":"CH",
    "sg:address":"Telmoos 14",
    "sg:city":"Plaffeien",
    "sg:orig_category":"Erbringung von Dienstleistungen f\u00fcr Unternehmen Verlegen von Fussboden",
    "sg:phone":"+41 26 419 26 22",
    "sg:postcode":"1716",
    "sg:province":"Fribourg",
    "wof:name":"Zbinden Josef, Jun., Eidg. Dipl. Bodenleger",
    "wof:placetype":"venue"
},
  "geometry": {"coordinates":[7.2920241356,46.7368583679],"type":"Point"}
}