{
  "type": "Feature",
  "properties": {
    "iso:country":"CH",
    "sg:address":"3215",
    "sg:city":"Lurtigen",
    "sg:orig_category":"Maler U Glasergewerbe Malerei",
    "sg:phone":"+41 61 811 12 95",
    "sg:postcode":"3215",
    "sg:province":"Fribourg",
    "wof:name":"Moritz Ag Malergesch\u00e4ft",
    "wof:placetype":"venue"
},
  "geometry": {"coordinates":[7.7272701263,47.5312538147],"type":"Point"}
}