{
  "type": "Feature",
  "properties": {
    "iso:country":"CH",
    "sg:address":"Rosenb\u00f6hleli 8",
    "sg:city":"Appenzell",
    "sg:orig_category":"Unternehmensberatung",
    "sg:phone":"+41 71 787 45 80",
    "sg:postcode":"9050",
    "sg:province":"Appenzell Innerhoden",
    "wof:name":"R\u00fcsch Dr. & Partner Holding Ag",
    "wof:placetype":"venue"
},
  "geometry": {"coordinates":[9.4303064346,47.3461532593],"type":"Point"}
}