{
  "type": "Feature",
  "properties": {
    "iso:country":"CH",
    "sg:address":"1196",
    "sg:city":"Gland",
    "sg:orig_category":"Verkehrs- and Tourismusb\u00fcros",
    "sg:postcode":"1196",
    "sg:province":"Vaud",
    "wof:name":"St\u00e9 De D\u00e9veloppement De Gland",
    "wof:placetype":"venue"
},
  "geometry": {"coordinates":[6.2614498138,46.4224014282],"type":"Point"}
}