{
  "type": "Feature",
  "properties": {
    "iso:country":"CH",
    "sg:address":"Untere Br\u00fchlstrasse 4",
    "sg:city":"Zofingen",
    "sg:orig_category":"Herstellung von D\u00fcngemitteln U Stickstoffverbindungen Herstellung von sonstigen organischen Grundsto",
    "sg:phone":"+41 62 746 11 11",
    "sg:postcode":"4800",
    "sg:province":"Aargau",
    "wof:name":"Siegfried Agro Ag",
    "wof:placetype":"venue"
},
  "geometry": {"coordinates":[7.9391918182,47.2885551453],"type":"Point"}
}