{
  "type": "Feature",
  "properties": {
    "addr:full":"B\u00fcsserachstrasse 148 Fehren Solothurn 4232",
    "addr:housenumber":"148",
    "addr:postcode":"4232",
    "addr:street":"Buesserachstrasse",
    "iso:country":"CH",
    "sg:address":"B\u00fcsserachstrasse 148",
    "sg:city":"Fehren",
    "sg:orig_category":"Autogaragen",
    "sg:phone":"+41 55 283 14 48",
    "sg:postcode":"4232",
    "sg:province":"Solothurn",
    "wof:name":"Franz Inglin Autogarage",
    "wof:placetype":"venue"
},
  "geometry": {"coordinates":[9.005025,47.199047],"type":"Point"}
}