{
  "type": "Feature",
  "properties": {
    "iso:country":"CH",
    "sg:address":"Steinmatt",
    "sg:city":"Alpthal",
    "sg:orig_category":"Abbruch U Sprenggewerbe, Erdbewegungsarbeiten Erdbewegungsarbeiten",
    "sg:phone":"+41 41 660 66 50",
    "sg:postcode":"8849",
    "sg:province":"Schwyz",
    "wof:name":"Josef Von Moos-imesch Ag Bagger-& Traxbetrieb",
    "wof:placetype":"venue"
},
  "geometry": {"coordinates":[8.211209,46.886616],"type":"Point"}
}