{
  "type": "Feature",
  "properties": {
    "iso:country":"CH",
    "sg:address":"Im Oberen Boden 144",
    "sg:city":"Z\u00fcrich",
    "sg:orig_category":"Kauf U Verkauf von Immobilien auf eigene Rechnung Vermittlung von Immobilien",
    "sg:phone":"+41 13419794",
    "sg:postcode":"8049",
    "sg:province":"Z\u00fcrich",
    "wof:name":"Besseag Immobilien, Defrancesco-besse Gladys",
    "wof:placetype":"venue"
},
  "geometry": {"coordinates":[8.4766769409,47.4159240723],"type":"Point"}
}