{
  "type": "Feature",
  "properties": {
    "addr:full":"Niederb\u00fcrerstrasse 22 Bischofszell Thurgau 9220",
    "addr:housenumber":"22",
    "addr:postcode":"9220",
    "addr:street":"Niederbuererstrasse",
    "iso:country":"CH",
    "sg:address":"Niederb\u00fcrerstrasse 22",
    "sg:city":"Bischofszell",
    "sg:orig_category":"Betrieb von Taxis Fahrschulen, Flugschulen",
    "sg:phone":"+41 71 422 25 73",
    "sg:postcode":"9220",
    "sg:province":"Thurgau",
    "wof:name":"Albert Nobel Funk-taxi & Fahrschule",
    "wof:placetype":"venue"
},
  "geometry": {"coordinates":[9.234394,47.489456],"type":"Point"}
}