{
  "type": "Feature",
  "properties": {
    "iso:country":"CH",
    "sg:address":"Kirchgasse 1",
    "sg:city":"Flumenthal",
    "sg:orig_category":"Sonstiger Fachdetailhandel mit Nahrungsmitteln, Getr\u00e4nken U Tabak in Verkaufsr\u00e4umen Verarbeitung von",
    "sg:phone":"+41 32 637 27 48",
    "sg:postcode":"4534",
    "sg:province":"Solothurn",
    "wof:name":"Ch\u00e4si Vis-\u00e0-vis Correia S.",
    "wof:placetype":"venue"
},
  "geometry": {"coordinates":[7.5955371857,47.2386131287],"type":"Point"}
}