{
  "type": "Feature",
  "properties": {
    "addr:full":"Gotthardstr Gurtnellen Uri 6482",
    "addr:postcode":"6482",
    "iso:country":"CH",
    "sg:address":"Gotthardstr",
    "sg:city":"Gurtnellen",
    "sg:orig_category":"Detailhandel mit Brot, Back U S\u00fcsswaren",
    "sg:postcode":"6482",
    "sg:province":"Uri",
    "wof:name":"Widmer-indergand, Martin",
    "wof:placetype":"venue"
},
  "geometry": {"coordinates":[8.618477,46.722054],"type":"Point"}
}