{
  "type": "Feature",
  "properties": {
    "iso:country":"CH",
    "sg:address":"Zeisenberg 194",
    "sg:city":"Rifferswil",
    "sg:orig_category":"Allgemeinbildende weiterf\u00fchrende Schulen",
    "sg:phone":"+41 17642510",
    "sg:postcode":"8911",
    "sg:province":"Z\u00fcrich",
    "wof:name":"Harald R\u00fcegg, Lernberatung Und Ausbildung",
    "wof:placetype":"venue"
},
  "geometry": {"coordinates":[8.491804,47.244144],"type":"Point"}
}