{
  "type": "Feature",
  "properties": {
    "iso:country":"CH",
    "sg:address":"Bangerten 209 5063 W\u00f6lflinswil. Postfach",
    "sg:city":"W\u00f6lflinswil",
    "sg:orig_category":"Wirtschaftspr\u00fcfung, Steuerberatung U Treuhand",
    "sg:postcode":"5063",
    "sg:province":"Aargau",
    "wof:name":"Treuhand- U. Inkasso-bureau R. B\u00f6hringer",
    "wof:placetype":"venue"
},
  "geometry": {"coordinates":[7.9997859001,47.4625396729],"type":"Point"}
}