{
  "type": "Feature",
  "properties": {
    "iso:country":"CH",
    "sg:address":"Limmatquai 2",
    "sg:city":"Z\u00fcrich",
    "sg:orig_category":"Interessenvertretungen",
    "sg:phone":"+41 12514760",
    "sg:postcode":"8001",
    "sg:province":"Z\u00fcrich",
    "wof:name":"Tschanz Fred - Stiftung Bezweckt Bar. O. Naturalspenden Auszurichten An; Bed\u00fcrftige, Geistig U./o. K\u00f6rperlich Behinderte Kinder Usw",
    "wof:placetype":"venue"
},
  "geometry": {"coordinates":[8.5452203751,47.3677444458],"type":"Point"}
}