{
  "type": "Feature",
  "properties": {
    "iso:country":"CH",
    "sg:address":"Am See",
    "sg:city":"Murg",
    "sg:orig_category":"Fussboden, Fliesen U Plattenlegerei, Tapeziererei Verlegen von Fliesen U Platten",
    "sg:phone":"+41 81 738 17 80",
    "sg:postcode":"8877",
    "sg:province":"St. Gallen",
    "wof:name":"Titus Gm\u00fcr Ag Ofenbau & Plattenbel\u00e4ge",
    "wof:placetype":"venue"
},
  "geometry": {"coordinates":[9.2161121368,47.1130218506],"type":"Point"}
}