{
  "type": "Feature",
  "properties": {
    "iso:country":"CH",
    "sg:address":"Neuheim 6018 Buttisholz. Postfach 143",
    "sg:city":"Buttisholz",
    "sg:orig_category":"Grosshandel mit sonstigen Maschinen U Ausr\u00fcstungen f\u00fcr Industrie, Handel U Schiffahrt Handelsvermitt",
    "sg:phone":"+41 41 928 17 57",
    "sg:postcode":"6018",
    "sg:province":"Luzern",
    "wof:name":"Marti A. Ag",
    "wof:placetype":"venue"
},
  "geometry": {"coordinates":[8.0937595367,47.1144142151],"type":"Point"}
}