{
  "type": "Feature",
  "properties": {
    "iso:country":"CH",
    "sg:address":"7423",
    "sg:city":"Sarn",
    "sg:orig_category":"Primarschulen",
    "sg:phone":"+41 81 651 27 13",
    "sg:postcode":"7423",
    "sg:province":"Graubunden",
    "wof:name":"Primarschule",
    "wof:placetype":"venue"
},
  "geometry": {"coordinates":[9.4099559784,46.7195892334],"type":"Point"}
}