{
  "type": "Feature",
  "properties": {
    "iso:country":"CH",
    "sg:address":"Riva Paradiso 32a 6900 Paradiso. Postfach",
    "sg:city":"Paradiso",
    "sg:orig_category":"Softwareentwicklung U beratung",
    "sg:postcode":"6900",
    "sg:province":"Ticino",
    "wof:name":"Nwconsulting Sagl Consulenza Nel Campo Di Sistemi Informativi, Logistica Ecc",
    "wof:placetype":"venue"
},
  "geometry": {"coordinates":[8.952009201,45.9898071289],"type":"Point"}
}