{
  "type": "Feature",
  "properties": {
    "iso:country":"CH",
    "sg:address":"Rue Du 23-juin 3",
    "sg:city":"Porrentruy",
    "sg:orig_category":"Softwareentwicklung U beratung",
    "sg:postcode":"2900",
    "sg:province":"Jura",
    "wof:name":"Nussbaumer Pierre-andr\u00e9",
    "wof:placetype":"venue"
},
  "geometry": {"coordinates":[7.0747270584,47.416759491],"type":"Point"}
}