{
  "type": "Feature",
  "properties": {
    "iso:country":"CH",
    "sg:address":"Spitalstrasse 24 8180 B\u00fclach. Postfach",
    "sg:city":"B\u00fclach",
    "sg:orig_category":"Non-Classified Establishments",
    "sg:phone":"+41 18632211",
    "sg:postcode":"8180",
    "sg:province":"Z\u00fcrich",
    "wof:name":"Spital B\u00fclach",
    "wof:placetype":"venue"
},
  "geometry": {"coordinates":[8.5338068008,47.5215034485],"type":"Point"}
}