{
  "type": "Feature",
  "properties": {
    "iso:country":"CH",
    "sg:address":"Neuch\u00e2tel Route De 4 Bis 1008 Prilly. Postfach",
    "sg:city":"Prilly",
    "sg:orig_category":"Fachdetailhandel in Verkaufsr\u00e4umen",
    "sg:postcode":"1008",
    "sg:province":"Vaud",
    "wof:name":"Sonic Jet, Dupuis & Morellon",
    "wof:placetype":"venue"
},
  "geometry": {"coordinates":[6.6106982231,46.5339050293],"type":"Point"}
}