{
  "type": "Feature",
  "properties": {
    "iso:country":"CH",
    "sg:address":"Rue Du Rh\u00f4ne 30",
    "sg:city":"Gen\u00e8ve",
    "sg:orig_category":"Detailhandel mit Damenbekleidung",
    "sg:phone":"+41 22 310 70 60",
    "sg:postcode":"1204",
    "sg:province":"Gen\u00e8ve",
    "wof:name":"Boutique Georges Rech Pr\u00eat-\u00e0-porter F\u00e9minin",
    "wof:placetype":"venue"
},
  "geometry": {"coordinates":[6.145966,46.204414],"type":"Point"}
}