{
  "type": "Feature",
  "properties": {
    "iso:country":"CH",
    "sg:address":"Saint-randoald Rue 12a",
    "sg:city":"Del\u00e9mont",
    "sg:orig_category":"Softwareentwicklung U beratung",
    "sg:postcode":"2800",
    "sg:province":"Jura",
    "wof:name":"Magiks Services Informatique S\u00e0rl",
    "wof:placetype":"venue"
},
  "geometry": {"coordinates":[7.344244957,47.355342865],"type":"Point"}
}