{
  "type": "Feature",
  "properties": {
    "iso:country":"CH",
    "sg:address":"Huttwilstrasse 11",
    "sg:city":"Lotzwil",
    "sg:orig_category":"Sonstiger Fachdetailhandel mit Nahrungsmitteln, Getr\u00e4nken U Tabak in Verkaufsr\u00e4umen",
    "sg:postcode":"4932",
    "sg:province":"Bern",
    "wof:name":"Ch\u00e4s-loube Lotzwil, Joost Peter",
    "wof:placetype":"venue"
},
  "geometry": {"coordinates":[7.7920460701,47.1898841858],"type":"Point"}
}