{
  "type": "Feature",
  "properties": {
    "iso:country":"CH",
    "sg:address":"Industriestrasse 3",
    "sg:city":"Bazenheid",
    "sg:classifiers":[
        {
            "category":"Government",
            "subcategory":"Court House",
            "type":"Public Place"
        }
    ],
    "sg:phone":"+41 71 930 03 90",
    "sg:postcode":"9602",
    "sg:province":"St. Gallen",
    "sg:tags":[
        "vice",
        "bench"
    ],
    "wof:name":"Pamatool Ag Werkzeugbau Und Spannsysteme",
    "wof:placetype":"venue"
},
  "geometry": {"coordinates":[9.071038,47.411476],"type":"Point"}
}