{
  "type": "Feature",
  "properties": {
    "iso:country":"CH",
    "sg:address":"Ancien Coll\u00e8ge Horloge Rue D",
    "sg:city":"Buchillon",
    "sg:orig_category":"Non-Classified Establishments",
    "sg:postcode":"1164",
    "sg:province":"Vaud",
    "wof:name":"Fragrance Finance Sa",
    "wof:placetype":"venue"
},
  "geometry": {"coordinates":[6.4212551117,46.4699859619],"type":"Point"}
}