{
  "type": "Feature",
  "properties": {
    "iso:country":"CH",
    "sg:address":"Berninastrasse 46 8057 Z\u00fcrich. Postfach",
    "sg:city":"Z\u00fcrich",
    "sg:orig_category":"Elektroinstallation Herstellung von Elektrizit\u00e4tsverteilungs U schalteinrichtungen",
    "sg:phone":"+41 13113888",
    "sg:postcode":"8042",
    "sg:province":"Z\u00fcrich",
    "wof:name":"Hensel Ag Elektrotechn.unternehmungen",
    "wof:placetype":"venue"
},
  "geometry": {"coordinates":[8.5471134186,47.4038162231],"type":"Point"}
}