{
  "type": "Feature",
  "properties": {
    "addr:full":"Rue Du Torrent 23 Vevey Vaud 1800",
    "addr:housenumber":"23",
    "addr:postcode":"1800",
    "addr:street":"Rue Du Torrent",
    "iso:country":"CH",
    "sg:address":"Rue Du Torrent 23",
    "sg:city":"Vevey",
    "sg:orig_category":"Arztpraxen",
    "sg:phone":"+41 32 913 07 73",
    "sg:postcode":"1800",
    "sg:province":"Vaud",
    "wof:name":"Dr M\u00e9d. Philippe Schoeni M\u00e9decin Sp\u00e9cialiste Fmh",
    "wof:placetype":"venue"
},
  "geometry": {"coordinates":[6.825532,47.102524],"type":"Point"}
}