{
  "type": "Feature",
  "properties": {
    "iso:country":"CH",
    "sg:address":"Schmiedgasse 7",
    "sg:city":"Schwyz",
    "sg:orig_category":"Non-Classified Establishments",
    "sg:postcode":"6430",
    "sg:province":"Schwyz",
    "wof:name":"Bote Der Urschweiz Ag",
    "wof:placetype":"venue"
},
  "geometry": {"coordinates":[8.6520118713,47.0195732117],"type":"Point"}
}