{
  "type": "Feature",
  "properties": {
    "iso:country":"CH",
    "sg:address":"Hintere Bahnhofstrasse 92",
    "sg:city":"Aarau",
    "sg:orig_category":"Geb\u00e4ude, Wohnungsreinigung",
    "sg:phone":"+41 52 238 20 80",
    "sg:postcode":"5000",
    "sg:province":"Aargau",
    "wof:name":"Aida-reinigungsservice",
    "wof:placetype":"venue"
},
  "geometry": {"coordinates":[8.7607221603,47.4835586548],"type":"Point"}
}