{
  "type": "Feature",
  "properties": {
    "iso:country":"CH",
    "sg:address":"Kolinplatz 2",
    "sg:city":"Zug",
    "sg:orig_category":"Wirtschaftspr\u00fcfung, Steuerberatung U Treuhand",
    "sg:phone":"+41 41 727 52 10",
    "sg:postcode":"6300",
    "sg:province":"Zug",
    "wof:name":"Meier Bruno Treuhand",
    "wof:placetype":"venue"
},
  "geometry": {"coordinates":[8.515376091,47.1663856506],"type":"Point"}
}