{
  "type": "Feature",
  "properties": {
    "iso:country":"CH",
    "sg:address":"Waldmannstrasse 35",
    "sg:city":"Bern",
    "sg:orig_category":"Vorschulen, Kinderg\u00e4rten",
    "sg:phone":"+41 31 992 65 76",
    "sg:postcode":"3027",
    "sg:province":"Bern",
    "wof:name":"Kindergarten Tscharnergut I",
    "wof:placetype":"venue"
},
  "geometry": {"coordinates":[7.3881568909,46.9487380981],"type":"Point"}
}