{
  "type": "Feature",
  "properties": {
    "iso:country":"CH",
    "sg:address":"Feldstrasse 100",
    "sg:city":"B\u00fclach",
    "sg:orig_category":"Unclassifiable Establishments",
    "sg:postcode":"8180",
    "sg:province":"Z\u00fcrich",
    "wof:name":"Caravan M\u00fcller Gmbh",
    "wof:placetype":"venue"
},
  "geometry": {"coordinates":[8.5410900116,47.5076065063],"type":"Point"}
}