{
  "type": "Feature",
  "properties": {
    "iso:country":"CH",
    "sg:address":"Im Winkel 3.",
    "sg:city":"D\u00fcbendorf",
    "sg:orig_category":"Beherbergungsgewerbe",
    "sg:postcode":"8600",
    "sg:province":"Z\u00fcrich",
    "wof:name":"Ferienhausgenossenschaft Hirschweid",
    "wof:placetype":"venue"
},
  "geometry": {"coordinates":[8.620326,47.38937],"type":"Point"}
}