{
  "type": "Feature",
  "properties": {
    "iso:country":"CH",
    "sg:address":"1727",
    "sg:city":"Corpataux-magneden",
    "sg:orig_category":"Landesverteidigung, Sozialversicherung \u00d6ffentliche Verwaltung",
    "sg:phone":"+41 26 411 32 39",
    "sg:postcode":"1727",
    "sg:province":"Fribourg",
    "wof:name":"Centre De Protection Civile",
    "wof:placetype":"venue"
},
  "geometry": {"coordinates":[7.0983800888,46.7445411682],"type":"Point"}
}