{
  "type": "Feature",
  "properties": {
    "iso:country":"CH",
    "sg:address":"Alberich Zwyssigstrasse 81",
    "sg:city":"Wettingen",
    "sg:orig_category":"Interessenvertretungen",
    "sg:phone":"+41 56 426 23 85",
    "sg:postcode":"5430",
    "sg:province":"Aargau",
    "wof:name":"Schweizerische Gesellschaft F\u00fcr Milit\u00e4rhistorische Studienreisen Gms",
    "wof:placetype":"venue"
},
  "geometry": {"coordinates":[8.3256092072,47.4652786255],"type":"Point"}
}