{
  "type": "Feature",
  "properties": {
    "iso:country":"CH",
    "sg:address":"Hauptstrasse 48",
    "sg:city":"Kreuzlingen",
    "sg:orig_category":"Unclassifiable Establishments",
    "sg:postcode":"8280",
    "sg:province":"Thurgau",
    "wof:name":"S+s Holding Ag",
    "wof:placetype":"venue"
},
  "geometry": {"coordinates":[9.1744232178,47.6501693726],"type":"Point"}
}