{
  "type": "Feature",
  "properties": {
    "iso:country":"CH",
    "sg:address":"Schweinbrunnen",
    "sg:city":"Huttwil",
    "sg:orig_category":"Herstellung von Futtermitteln f\u00fcr Nutztiere",
    "sg:phone":"+41 62 962 16 60",
    "sg:postcode":"4950",
    "sg:province":"Bern",
    "wof:name":"Grastrocknerei Huttwil, Fritz Spichiger",
    "wof:placetype":"venue"
},
  "geometry": {"coordinates":[7.8096737862,47.1009101868],"type":"Point"}
}