{
  "type": "Feature",
  "properties": {
    "iso:country":"CH",
    "sg:address":"Bergstrasse 40",
    "sg:city":"Goldau",
    "sg:classifiers":[
        {
            "category":"Restaurant",
            "type":"Food & Drink"
        }
    ],
    "sg:phone":"+41 41 855 13 51",
    "sg:postcode":"6410",
    "sg:province":"Schwyz",
    "wof:name":"Restaurant Kreuzstrasse & Pizzeria Bacco",
    "wof:placetype":"venue"
},
  "geometry": {"coordinates":[8.5542469025,47.052192688],"type":"Point"}
}