{
  "type": "Feature",
  "properties": {
    "iso:country":"CH",
    "sg:address":"Franscini Viale 1",
    "sg:city":"Lugano",
    "sg:orig_category":"Handelsvermittlung von Textilien, Bekleidung, Schuhen U Lederwaren",
    "sg:postcode":"6900",
    "sg:province":"Ticino",
    "wof:name":"Gay Riccardo International Ltd, Londra, Succursale Di Lugano",
    "wof:placetype":"venue"
},
  "geometry": {"coordinates":[8.9525566101,46.0080795288],"type":"Point"}
}