{
  "type": "Feature",
  "properties": {
    "iso:country":"CH",
    "sg:address":"Bahnhofstrasse 37 8320 Fehraltorf. Postfach 329",
    "sg:city":"Fehraltorf",
    "sg:classifiers":[
        {
            "category":"Restaurant",
            "type":"Food & Drink"
        }
    ],
    "sg:phone":"+41 26 673 14 02",
    "sg:postcode":"8320",
    "sg:province":"Z\u00fcrich",
    "sg:tags":[
        "caterer"
    ],
    "wof:name":"Caf\u00e9 Port",
    "wof:placetype":"venue"
},
  "geometry": {"coordinates":[7.083548,46.948147],"type":"Point"}
}