{
  "type": "Feature",
  "properties": {
    "iso:country":"CH",
    "sg:address":"Thurtalstrasse 40",
    "sg:city":"Andelfingen",
    "sg:orig_category":"Grosshandel mit sonstigen Maschinen U Ausr\u00fcstungen f\u00fcr Industrie, Handel U Schiffahrt",
    "sg:phone":"+41 52 317 09 82",
    "sg:postcode":"8450",
    "sg:province":"Z\u00fcrich",
    "wof:name":"Imtag",
    "wof:placetype":"venue"
},
  "geometry": {"coordinates":[8.686340332,47.5948410034],"type":"Point"}
}