{
  "type": "Feature",
  "properties": {
    "iso:country":"CH",
    "sg:address":"Florastrasse 10",
    "sg:city":"Birsfelden",
    "sg:orig_category":"Herstellung von k\u00e4lte U lufttechnischen Erzeugnissen f\u00fcr gewerbliche Zwecke",
    "sg:postcode":"4127",
    "sg:province":"Basel-Landschaft",
    "wof:name":"Popair Gmbh",
    "wof:placetype":"venue"
},
  "geometry": {"coordinates":[7.6280498505,47.5475158691],"type":"Point"}
}