{
  "type": "Feature",
  "properties": {
    "iso:country":"CH",
    "sg:address":"Rue Du Midi 13",
    "sg:city":"Yverdon-les-bains",
    "sg:orig_category":"Grosshandel mit Werkzeugmaschinen Herstellung von Werkzeugen",
    "sg:phone":"+41 24 425 21 85",
    "sg:postcode":"1400",
    "sg:province":"Vaud",
    "wof:name":"Pittet Jardin Et F\u00f4ret Sa",
    "wof:placetype":"venue"
},
  "geometry": {"coordinates":[6.6371397972,46.7763786316],"type":"Point"}
}