{
  "type": "Feature",
  "properties": {
    "iso:country":"CH",
    "sg:address":"Bahnhofstrasse 33 6210 Sursee. Postfach 64",
    "sg:city":"Sursee",
    "sg:orig_category":"Autogaragen Lastwagen and Nutzfahrzeuge",
    "sg:phone":"+41 844 857 575",
    "sg:postcode":"6210",
    "sg:province":"Luzern",
    "wof:name":"Autoverkehr Aarberg",
    "wof:placetype":"venue"
},
  "geometry": {"coordinates":[7.265182,47.119682],"type":"Point"}
}