{
  "type": "Feature",
  "properties": {
    "iso:country":"CH",
    "sg:address":"Schaffhauserstrasse 127",
    "sg:city":"Kloten",
    "sg:orig_category":"Detailhandel mit Spielwaren Detailhandel mit S\u00e4uglings U Kinderbekleidung",
    "sg:phone":"+41 18137359",
    "sg:postcode":"8302",
    "sg:province":"Z\u00fcrich",
    "wof:name":"Bambi Spielwaren Gmbh",
    "wof:placetype":"venue"
},
  "geometry": {"coordinates":[8.580909729,47.4512252808],"type":"Point"}
}