{
  "type": "Feature",
  "properties": {
    "addr:full":"Engelbergstrasse 19 Niederg\u00f6sgen Solothurn 5013",
    "addr:housenumber":"19",
    "addr:postcode":"5013",
    "addr:street":"Engelbergstrasse;Solothurn",
    "iso:country":"CH",
    "sg:address":"Engelbergstrasse 19",
    "sg:city":"Niederg\u00f6sgen",
    "sg:classifiers":[
        {
            "category":"Building & Trades",
            "subcategory":"Pest Control",
            "type":"Services"
        }
    ],
    "sg:phone":"+41 62 849 21 45",
    "sg:postcode":"5013",
    "sg:province":"Solothurn",
    "sg:tags":[
        "automation"
    ],
    "wof:name":"Schopfer Msre Gmbh",
    "wof:placetype":"venue"
},
  "geometry": {"coordinates":[7.990718,47.371067],"type":"Point"}
}