{
  "type": "Feature",
  "properties": {
    "iso:country":"CH",
    "sg:address":"Am Stadtgatter 11",
    "sg:city":"Berikon",
    "sg:orig_category":"Sportvereine Sch\u00fctzen",
    "sg:phone":"+41 56 633 11 74",
    "sg:postcode":"8965",
    "sg:province":"Aargau",
    "wof:name":"Feldsch\u00fctzen Berikon",
    "wof:placetype":"venue"
},
  "geometry": {"coordinates":[8.3701238632,47.3518104553],"type":"Point"}
}