{
  "type": "Feature",
  "properties": {
    "iso:country":"CH",
    "sg:address":"Zugerstrasse 15 6330 Cham. Postfach 168",
    "sg:city":"Cham",
    "sg:orig_category":"Wirtschaftspr\u00fcfung, Steuerberatung U Treuhand",
    "sg:phone":"+41 41 780 40 88",
    "sg:postcode":"6330",
    "sg:province":"Zug",
    "wof:name":"Degrandi Beat Treuhand",
    "wof:placetype":"venue"
},
  "geometry": {"coordinates":[8.4615259171,47.1817016602],"type":"Point"}
}