{
  "type": "Feature",
  "properties": {
    "iso:country":"CH",
    "sg:address":"Mara\u00eechers Rue Des 36",
    "sg:city":"Gen\u00e8ve",
    "sg:orig_category":"Sonstige pers\u00f6nliche Dienstleistungen",
    "sg:postcode":"1205",
    "sg:province":"Gen\u00e8ve",
    "wof:name":"Vincent Vega Llc, Dover, Succursale De Gen\u00e8ve",
    "wof:placetype":"venue"
},
  "geometry": {"coordinates":[6.1357288361,46.1987266541],"type":"Point"}
}