{
  "type": "Feature",
  "properties": {
    "iso:country":"CH",
    "sg:address":"Plattenstrasse 45",
    "sg:city":"Z\u00fcrich",
    "sg:orig_category":"Kinderkrippen U horte Vorschulen, Kinderg\u00e4rten",
    "sg:phone":"+41 12515777",
    "sg:postcode":"8032",
    "sg:province":"Z\u00fcrich",
    "wof:name":"Kindergarten Platte Tagesst\u00e4tte Universit\u00e4t",
    "wof:placetype":"venue"
},
  "geometry": {"coordinates":[8.5547323227,47.37241745],"type":"Point"}
}