{
  "type": "Feature",
  "properties": {
    "addr:full":"Luzernerstrasse 186 Merlischachen Schwyz 6402",
    "addr:housenumber":"186",
    "addr:postcode":"6402",
    "addr:street":"Luzernerstrasse;Schwyz",
    "iso:country":"CH",
    "sg:address":"Luzernerstrasse 186",
    "sg:city":"Merlischachen",
    "sg:classifiers":[
        {
            "category":"Social Services",
            "subcategory":"Job Training",
            "type":"Services"
        }
    ],
    "sg:phone":"+41 41 852 02 95",
    "sg:postcode":"6402",
    "sg:province":"Schwyz",
    "sg:tags":[
        "software",
        "database"
    ],
    "wof:name":"Gabor Borb\u00e9ly Reltech Software",
    "wof:placetype":"venue"
},
  "geometry": {"coordinates":[8.410061,47.066978],"type":"Point"}
}