{
  "type": "Feature",
  "properties": {
    "iso:country":"CH",
    "sg:address":"Chemin Du L\u00e9vrioux 1263 Crassier Case Postale 23",
    "sg:city":"Crassier",
    "sg:orig_category":"Unternehmensberatung",
    "sg:phone":"+41 22 367 10 93",
    "sg:postcode":"1263",
    "sg:province":"Vaud",
    "wof:name":"Gmg Richard Polis",
    "wof:placetype":"venue"
},
  "geometry": {"coordinates":[6.166864872,46.3724746704],"type":"Point"}
}