{
  "type": "Feature",
  "properties": {
    "iso:country":"CH",
    "sg:address":"Les Ilettes",
    "sg:city":"Monthey",
    "sg:orig_category":"Einzelhandel mit Automobilteilen U Zubeh\u00f6r",
    "sg:phone":"+41 24 471 91 59",
    "sg:postcode":"1870",
    "sg:province":"Valais",
    "wof:name":"Adam Touring Gmbh",
    "wof:placetype":"venue"
},
  "geometry": {"coordinates":[6.9609351158,46.2472343445],"type":"Point"}
}