{
  "type": "Feature",
  "properties": {
    "iso:country":"CH",
    "sg:address":"St\u00fcsslingerstrasse 93",
    "sg:city":"Niedererlinsbach",
    "sg:orig_category":"Grosshandel mit Holz U Baustoffen",
    "sg:postcode":"5015",
    "sg:province":"Solothurn",
    "wof:name":"Buser Hans Zementwaren",
    "wof:placetype":"venue"
},
  "geometry": {"coordinates":[7.996737957,47.3982620239],"type":"Point"}
}