{
  "type": "Feature",
  "properties": {
    "iso:country":"CH",
    "sg:address":"B\u00f6zingenstrasse 184",
    "sg:city":"Biel/bienne",
    "sg:orig_category":"Architektur U Ingenieurb\u00fcros Architekturb\u00fcros",
    "sg:phone":"+41 32 344 70 40",
    "sg:postcode":"2504",
    "sg:province":"Bern",
    "wof:name":"Werkhof-architekten Gmbh",
    "wof:placetype":"venue"
},
  "geometry": {"coordinates":[7.267344,47.152882],"type":"Point"}
}