{
  "type": "Feature",
  "properties": {
    "iso:country":"CH",
    "sg:address":"Bahnh\u00f6heweg 34 3000 Bern. Postfach",
    "sg:city":"Bern",
    "sg:orig_category":"Herstellung von Schmuck, Gold U Silberschmiedwaren",
    "sg:postcode":"3003",
    "sg:province":"Bern",
    "wof:name":"Atelier La Bicicleta Peppino Tony",
    "wof:placetype":"venue"
},
  "geometry": {"coordinates":[7.3997511864,46.9404945374],"type":"Point"}
}