{
  "type": "Feature",
  "properties": {
    "iso:country":"CH",
    "sg:address":"Dorfstrasse 59",
    "sg:city":"Oetwil",
    "sg:orig_category":"Sportvereine Sch\u00fctzen",
    "sg:phone":"+41 17481120",
    "sg:postcode":"8955",
    "sg:province":"Z\u00fcrich",
    "wof:name":"Standsch\u00fctzenges.dietikon",
    "wof:placetype":"venue"
},
  "geometry": {"coordinates":[8.3995580673,47.4262619019],"type":"Point"}
}