{
  "type": "Feature",
  "properties": {
    "iso:country":"CH",
    "sg:address":"Tsch\u00e4ppel",
    "sg:city":"Huttwil",
    "sg:orig_category":"Verwertung von Milch",
    "sg:postcode":"4950",
    "sg:province":"Bern",
    "wof:name":"K\u00e4sereigenossenschaft Tsch\u00e4ppel-gommen",
    "wof:placetype":"venue"
},
  "geometry": {"coordinates":[7.8497819901,47.0965614319],"type":"Point"}
}