{
  "type": "Feature",
  "properties": {
    "iso:country":"CH",
    "sg:address":"Anz\u00e8re 1966 Argnoud (ayent). Postfach",
    "sg:city":"Anz\u00e8re",
    "sg:classifiers":[
        {
            "category":"Travel",
            "subcategory":"Hotels & Motels",
            "type":"Entertainment"
        }
    ],
    "sg:phone":"+41 27 398 34 94",
    "sg:postcode":"1972",
    "sg:province":"Valais",
    "sg:tags":[
        "hotels",
        "mit",
        "restaurant"
    ],
    "wof:name":"Moos R\u00e9gis",
    "wof:placetype":"venue"
},
  "geometry": {"coordinates":[7.4068250656,46.2767829895],"type":"Point"}
}