{
  "type": "Feature",
  "properties": {
    "addr:full":"Rheinstrasse 10 7302 Landquart. Postfach Landquart Graubunden 7302",
    "addr:housenumber":"10",
    "addr:postcode":"7302 landquart. postfach;7302",
    "addr:street":"Rheinstrasse",
    "iso:country":"CH",
    "sg:address":"Rheinstrasse 10 7302 Landquart. Postfach",
    "sg:city":"Landquart",
    "sg:orig_category":"Allgemeiner Hoch U Tiefbau",
    "sg:phone":"+41 81 322 69 70",
    "sg:postcode":"7302",
    "sg:province":"Graubunden",
    "wof:name":"Schmid Richard Ag",
    "wof:placetype":"venue"
},
  "geometry": {"coordinates":[9.558521,46.962166],"type":"Point"}
}