{
  "type": "Feature",
  "properties": {
    "iso:country":"CH",
    "sg:address":"Attinghausenstrasse 20",
    "sg:city":"Bern",
    "sg:orig_category":"Detailhandel mit Waren verschiedener Art, Hauptrichtung Nahrungsmittel",
    "sg:phone":"+41 31 332 10 10",
    "sg:postcode":"3014",
    "sg:province":"Bern",
    "wof:name":"Vergiss Mein Nicht Lebensmittelgesch\u00e4ft",
    "wof:placetype":"venue"
},
  "geometry": {"coordinates":[7.4560399055,46.9611663818],"type":"Point"}
}