{
  "type": "Feature",
  "properties": {
    "iso:country":"CH",
    "sg:address":"H\u00f6ngen 128",
    "sg:city":"Laupersdorf",
    "sg:orig_category":"RESTAURANTS: TEA-ROOMS",
    "sg:phone":"+41 62 391 55 22",
    "sg:postcode":"4712",
    "sg:province":"Solothurn",
    "wof:name":"Schmid Josef",
    "wof:placetype":"venue"
},
  "geometry": {"coordinates":[7.6737351418,47.3230133057],"type":"Point"}
}