{
  "type": "Feature",
  "properties": {
    "iso:country":"CH",
    "sg:address":"Westringstrasse 4",
    "sg:city":"Solothurn",
    "sg:orig_category":"Interessenvertretungen",
    "sg:postcode":"4500",
    "sg:province":"Solothurn",
    "wof:name":"Sunrise-stiftung F\u00fcr Umweltfreundliche Energieformen",
    "wof:placetype":"venue"
},
  "geometry": {"coordinates":[7.5348081589,47.2075195312],"type":"Point"}
}