{
  "type": "Feature",
  "properties": {
    "iso:country":"CH",
    "sg:address":"6005 Luzern. Postfach 2918",
    "sg:city":"Luzern",
    "sg:orig_category":"Sportvereine Ballsport Fussball",
    "sg:phone":"+41 41 250 13 40",
    "sg:postcode":"6002",
    "sg:province":"Luzern",
    "wof:name":"Fc Luzern",
    "wof:placetype":"venue"
},
  "geometry": {"coordinates":[8.3351602554,47.0335617065],"type":"Point"}
}