{
  "type": "Feature",
  "properties": {
    "iso:country":"CH",
    "sg:address":"Seestrasse 160 8002 Z\u00fcrich. Postfach",
    "sg:city":"Z\u00fcrich",
    "sg:orig_category":"Dienstleistungen von Beteiligungsgesellschaften",
    "sg:phone":"+41 17122222",
    "sg:postcode":"8001",
    "sg:province":"Z\u00fcrich",
    "wof:name":"M\u00f6venpick - Holding Beteiligungen Usw",
    "wof:placetype":"venue"
},
  "geometry": {"coordinates":[8.5321102142,47.3557815552],"type":"Point"}
}