{
  "type": "Feature",
  "properties": {
    "iso:country":"CH",
    "sg:address":"8404 Winterthur. Postfach 42",
    "sg:city":"Winterthur",
    "sg:orig_category":"Vereine Musik/Blasmusik",
    "sg:phone":"+41 52 242 67 77",
    "sg:postcode":"8404",
    "sg:province":"Z\u00fcrich",
    "wof:name":"Musikverein Harmonie Oberwinterthur",
    "wof:placetype":"venue"
},
  "geometry": {"coordinates":[8.7606601715,47.5198402405],"type":"Point"}
}