{
  "type": "Feature",
  "properties": {
    "iso:country":"CH",
    "sg:address":"Benediktinerinnenkloster",
    "sg:city":"Melchtal",
    "sg:orig_category":"Freizeit, Kunst U Kultur",
    "sg:postcode":"6067",
    "sg:province":"Obwalden",
    "wof:name":"Sr. Chantal Hug Melchtal",
    "wof:placetype":"venue"
},
  "geometry": {"coordinates":[8.278651,46.802223],"type":"Point"}
}