{
  "type": "Feature",
  "properties": {
    "iso:country":"CH",
    "sg:address":"Rue De Soleure 60",
    "sg:city":"Montagne-moutier",
    "sg:orig_category":"Instandhaltung U Reparatur von Automobilen",
    "sg:phone":"+41 32 493 44 68",
    "sg:postcode":"2740",
    "sg:province":"Bern",
    "wof:name":"Kipfer Automobiles Sa",
    "wof:placetype":"venue"
},
  "geometry": {"coordinates":[7.3890299797,47.2803535461],"type":"Point"}
}