{
  "type": "Feature",
  "properties": {
    "iso:country":"CH",
    "sg:address":"Lyssachstrasse 83",
    "sg:city":"Burgdorf",
    "sg:orig_category":"Pensionskassen",
    "sg:phone":"+41 34 422 74 74",
    "sg:postcode":"3400",
    "sg:province":"Bern",
    "wof:name":"Personalf\u00fcrsorgestiftung Der Simon Keller Ag",
    "wof:placetype":"venue"
},
  "geometry": {"coordinates":[7.6185998917,47.059753418],"type":"Point"}
}