{
  "type": "Feature",
  "properties": {
    "iso:country":"CH",
    "sg:address":"L\u00e4ngfeldstrasse 28",
    "sg:city":"Ittigen",
    "sg:orig_category":"Handelsvermittlung U Grosshandel",
    "sg:phone":"+41 31 921 31 72",
    "sg:postcode":"3063",
    "sg:province":"Bern",
    "wof:name":"Minh Vun Choy Warenhandel",
    "wof:placetype":"venue"
},
  "geometry": {"coordinates":[7.4783091545,46.9843559265],"type":"Point"}
}