{
  "type": "Feature",
  "properties": {
    "iso:country":"CH",
    "sg:address":"Dorfleuteweg 14",
    "sg:city":"Buochs",
    "sg:orig_category":"Architektur U Ingenieurb\u00fcros",
    "sg:phone":"+41 41 340 10 24",
    "sg:postcode":"6374",
    "sg:province":"Nidwalden",
    "wof:name":"Geotest Ag",
    "wof:placetype":"venue"
},
  "geometry": {"coordinates":[8.422175,46.975224],"type":"Point"}
}