{
  "type": "Feature",
  "properties": {
    "iso:country":"CH",
    "sg:address":"R\u00f6hliberg 8",
    "sg:city":"Cham",
    "sg:orig_category":"Erschliessung von Grundst\u00fccken",
    "sg:postcode":"6330",
    "sg:province":"Zug",
    "wof:name":"Genossenschaft Eigenheim",
    "wof:placetype":"venue"
},
  "geometry": {"coordinates":[8.4540710449,47.1852455139],"type":"Point"}
}