{
  "type": "Feature",
  "properties": {
    "iso:country":"CH",
    "sg:address":"Arova-areal",
    "sg:city":"Flurlingen",
    "sg:orig_category":"Herstellung von industriellen Prozesssteuerungsanlagen",
    "sg:phone":"+41 52 659 64 65",
    "sg:postcode":"8247",
    "sg:province":"Z\u00fcrich",
    "wof:name":"Meister Peter Ag",
    "wof:placetype":"venue"
},
  "geometry": {"coordinates":[8.6309671402,47.6889839172],"type":"Point"}
}