{
  "type": "Feature",
  "properties": {
    "iso:country":"CH",
    "sg:address":"Poststrasse 14",
    "sg:city":"Dietikon",
    "sg:orig_category":"Sonstige Institutionen des Sozialwesens ohne Beherbergung",
    "sg:phone":"+41 17408674",
    "sg:postcode":"8953",
    "sg:province":"Z\u00fcrich",
    "wof:name":"Jugendsekretariat Des Bezirks Dietikon",
    "wof:placetype":"venue"
},
  "geometry": {"coordinates":[8.4050102234,47.4033737183],"type":"Point"}
}