{
  "type": "Feature",
  "properties": {
    "iso:country":"CH",
    "sg:address":"Rue Du Closillon 17",
    "sg:city":"Monthey",
    "sg:orig_category":"Maler U Glasergewerbe",
    "sg:phone":"+41 31 747 70 86",
    "sg:postcode":"1870",
    "sg:province":"Valais",
    "wof:name":"Herren Fritz",
    "wof:placetype":"venue"
},
  "geometry": {"coordinates":[7.2403931618,46.9001235962],"type":"Point"}
}