{
  "type": "Feature",
  "properties": {
    "iso:country":"CH",
    "sg:address":"Dubsstrasse 45 8003 Z\u00fcrich. Postfach",
    "sg:city":"Z\u00fcrich",
    "sg:orig_category":"Detailhandel mit Textilien",
    "sg:postcode":"8001",
    "sg:province":"Z\u00fcrich",
    "wof:name":"Str\u00e4ssle Hans Fabrikation Von Posamenten",
    "wof:placetype":"venue"
},
  "geometry": {"coordinates":[8.5208539963,47.3667488098],"type":"Point"}
}