{
  "type": "Feature",
  "properties": {
    "iso:country":"CH",
    "sg:address":"Weingartenstrasse 41",
    "sg:city":"Olten",
    "sg:orig_category":"Herstellung von sonstigen elektrischen Ausr\u00fcstungen",
    "sg:phone":"+41 62 212 70 41",
    "sg:postcode":"4600",
    "sg:province":"Solothurn",
    "wof:name":"Msu-electronic Eggenschwiler Beat",
    "wof:placetype":"venue"
},
  "geometry": {"coordinates":[7.8896741867,47.352432251],"type":"Point"}
}