{
  "type": "Feature",
  "properties": {
    "iso:country":"CH",
    "sg:address":"Heissgl\u00e4ndstrasse 40",
    "sg:city":"Muttenz",
    "sg:orig_category":"Handel mit Automobilteilen U Zubeh\u00f6r",
    "sg:postcode":"4132",
    "sg:province":"Basel-Landschaft",
    "wof:name":"Karimbo Autodesign Bouaouiche",
    "wof:placetype":"venue"
},
  "geometry": {"coordinates":[7.6534099579,47.5266609192],"type":"Point"}
}