{
  "type": "Feature",
  "properties": {
    "iso:country":"CH",
    "sg:address":"Kasernenplatz 1 6003 Luzern. Postfach",
    "sg:city":"Luzern",
    "sg:orig_category":"Pensionskassen",
    "sg:phone":"+41 41 240 13 13",
    "sg:postcode":"6003",
    "sg:province":"Luzern",
    "wof:name":"Forstwirtschaftliche Familienstiftung Von Moos In Luzern",
    "wof:placetype":"venue"
},
  "geometry": {"coordinates":[8.3007087708,47.0513153076],"type":"Point"}
}