{
  "type": "Feature",
  "properties": {
    "iso:country":"CH",
    "sg:address":"3256",
    "sg:city":"Dieterswil",
    "sg:orig_category":"Grosshandel mit lebenden Tieren",
    "sg:phone":"+41 31 879 05 80",
    "sg:postcode":"3256",
    "sg:province":"Bern",
    "wof:name":"Ernst Schneider",
    "wof:placetype":"venue"
},
  "geometry": {"coordinates":[7.4086999893,47.0657196045],"type":"Point"}
}