{
  "type": "Feature",
  "properties": {
    "iso:country":"CH",
    "sg:address":"Romont Rue De 35",
    "sg:city":"Fribourg",
    "sg:orig_category":"Binnenschiffahrt",
    "sg:postcode":"1700",
    "sg:province":"Fribourg",
    "wof:name":"Masstrader Sa",
    "wof:placetype":"venue"
},
  "geometry": {"coordinates":[7.153965,46.804344],"type":"Point"}
}