{
  "type": "Feature",
  "properties": {
    "iso:country":"CH",
    "sg:address":"Rue Haute 13",
    "sg:city":"Grandson",
    "sg:orig_category":"Grosshandel mit Getr\u00e4nken Rebbau",
    "sg:phone":"+41 24 436 04 36",
    "sg:postcode":"1422",
    "sg:province":"Vaud",
    "wof:name":"Caveau Des Viticulteurs Le Vigneron Sa",
    "wof:placetype":"venue"
},
  "geometry": {"coordinates":[6.6442728043,46.80859375],"type":"Point"}
}