{
  "type": "Feature",
  "properties": {
    "iso:country":"CH",
    "sg:address":"Rue Cardelay",
    "sg:city":"Bassins",
    "sg:orig_category":"Gesundheitswesen Grosshandel mit medizinischen U orthop\u00e4dischen Artikeln",
    "sg:phone":"+41 22 366 25 00",
    "sg:postcode":"1269",
    "sg:province":"Vaud",
    "wof:name":"Tonneau Fournitures M\u00e9dicales",
    "wof:placetype":"venue"
},
  "geometry": {"coordinates":[6.2338271141,46.4636573792],"type":"Point"}
}