{
  "type": "Feature",
  "properties": {
    "iso:country":"CH",
    "sg:address":"B\u00fcmplizstrasse 165 3018 Bern. Postfach",
    "sg:city":"Bern",
    "sg:orig_category":"Herstellung von elektronischen Bauelementen",
    "sg:postcode":"3003",
    "sg:province":"Bern",
    "wof:name":"Blumenauer Electronics Gmbh Elektronische U. Nicht Elektronische Elemente; Produktion, Verkauf U. Organisation Usw",
    "wof:placetype":"venue"
},
  "geometry": {"coordinates":[7.3930001259,46.9392204285],"type":"Point"}
}