{
  "type": "Feature",
  "properties": {
    "iso:country":"CH",
    "sg:address":"Landstrasse 1d 3664 Burgistein. Postfach",
    "sg:city":"Burgistein",
    "sg:orig_category":"Bau von Strassen, Sportanlagen U Bahnverkehrsstrecken",
    "sg:postcode":"3664",
    "sg:province":"Bern",
    "wof:name":"Spedibau Ag Strassen, Hoch, Tiefbau. Baumaterialien; Herstellung, Handel",
    "wof:placetype":"venue"
},
  "geometry": {"coordinates":[7.518337,46.793293],"type":"Point"}
}