{
  "type": "Feature",
  "properties": {
    "iso:country":"CH",
    "sg:address":"Jenatschstrasse 1 8002 Z\u00fcrich. Postfach",
    "sg:city":"Z\u00fcrich",
    "sg:orig_category":"Textilgewerbe",
    "sg:phone":"+41 12016260",
    "sg:postcode":"8022",
    "sg:province":"Z\u00fcrich",
    "wof:name":"Mayer Ferd. Ag",
    "wof:placetype":"venue"
},
  "geometry": {"coordinates":[8.5341739655,47.3635063171],"type":"Point"}
}