{
  "type": "Feature",
  "properties": {
    "iso:country":"CH",
    "sg:address":"Suisse Route 11 1295 Mies. Postfach",
    "sg:city":"Mies",
    "sg:orig_category":"Unclassifiable Establishments",
    "sg:postcode":"1295",
    "sg:province":"Vaud",
    "wof:name":"F\u00e9d\u00e9ration Internationale De Motocyclisme",
    "wof:placetype":"venue"
},
  "geometry": {"coordinates":[6.1681838036,46.2973136902],"type":"Point"}
}