{
  "type": "Feature",
  "properties": {
    "iso:country":"CH",
    "sg:address":"Hummelstrasse 17 8500 Frauenfeld. Postfach",
    "sg:city":"Frauenfeld",
    "sg:orig_category":"Unclassifiable Establishments",
    "sg:phone":"+41 52 728 11 22",
    "sg:postcode":"8500",
    "sg:province":"Thurgau",
    "wof:name":"Baumer Holding Ag",
    "wof:placetype":"venue"
},
  "geometry": {"coordinates":[8.8832092285,47.5646324158],"type":"Point"}
}