{
  "type": "Feature",
  "properties": {
    "iso:country":"CH",
    "sg:address":"Aarburgerstrasse",
    "sg:city":"Zofingen",
    "sg:orig_category":"Herstellung von Fenstern U T\u00fcren aus Holz Innenausbau",
    "sg:phone":"+41 71 385 70 88",
    "sg:postcode":"4800",
    "sg:province":"Aargau",
    "wof:name":"Hans K\u00fcnzle Innenausbau T\u00fcren M\u00f6bel K\u00fcchen",
    "wof:placetype":"venue"
},
  "geometry": {"coordinates":[9.2537031174,47.4162902832],"type":"Point"}
}