{
  "type": "Feature",
  "properties": {
    "addr:full":"Rue Du Centre 2b Crissier Vaud 1023",
    "addr:housenumber":"2b",
    "addr:postcode":"1023",
    "addr:street":"Rue Du Centre",
    "iso:country":"CH",
    "sg:address":"Rue Du Centre 2b",
    "sg:city":"Crissier",
    "sg:orig_category":"Arztpraxen",
    "sg:phone":"+41 21 633 07 11",
    "sg:postcode":"1023",
    "sg:province":"Vaud",
    "wof:name":"Dr M\u00e9d. Daniel Blanc M\u00e9decin G\u00e9n\u00e9raliste",
    "wof:placetype":"venue"
},
  "geometry": {"coordinates":[6.576679,46.553776],"type":"Point"}
}