{
  "type": "Feature",
  "properties": {
    "iso:country":"CH",
    "sg:address":"Simplon Avenue Du 32",
    "sg:city":"Monthey",
    "sg:orig_category":"G\u00fcterbef\u00f6rderung im Strassenverkehr",
    "sg:phone":"+41 24 471 18 68",
    "sg:postcode":"1870",
    "sg:province":"Valais",
    "wof:name":"Techni Services (suisse) S\u00e0rl",
    "wof:placetype":"venue"
},
  "geometry": {"coordinates":[6.9471468925,46.2516288757],"type":"Point"}
}