{
  "type": "Feature",
  "properties": {
    "iso:country":"CH",
    "sg:address":"1442",
    "sg:city":"Montagny-yverdon",
    "sg:orig_category":"Elektroinstallation Mechanische Werkst\u00e4tten",
    "sg:phone":"+41 24 445 47 68",
    "sg:postcode":"1442",
    "sg:province":"Vaud",
    "wof:name":"Groux, Georges.",
    "wof:placetype":"venue"
},
  "geometry": {"coordinates":[6.609389782,46.7890090942],"type":"Point"}
}