{
  "type": "Feature",
  "properties": {
    "iso:country":"CH",
    "sg:address":"St. Sulpice",
    "sg:city":"St. Sulpice",
    "sg:classifiers":[
        {
            "category":"Banks & Credit Unions",
            "subcategory":"Bank",
            "type":"Services"
        }
    ],
    "sg:phone":"+41 26 917 83 73",
    "sg:postcode":"2123",
    "sg:province":"Neuch\u00e2tel",
    "wof:name":"Banque Raiffeisen S\u00e2les/st-martin",
    "wof:placetype":"venue"
},
  "geometry": {"coordinates":[6.974406,46.63554],"type":"Point"}
}