{
  "type": "Feature",
  "properties": {
    "addr:full":"Hofibachstrasse 18 Zwillikon Z\u00fcrich 8909",
    "addr:housenumber":"18",
    "addr:postcode":"8909",
    "addr:street":"Hofibachstrasse",
    "iso:country":"CH",
    "sg:address":"Hofibachstrasse 18",
    "sg:city":"Zwillikon",
    "sg:orig_category":"Bauschreinerei Herstellung von M\u00f6beln verschiedener Art",
    "sg:phone":"+41 17410101",
    "sg:postcode":"8909",
    "sg:province":"Z\u00fcrich",
    "wof:name":"Instar Staub Rudolf",
    "wof:placetype":"venue"
},
  "geometry": {"coordinates":[8.438614,47.289406],"type":"Point"}
}