{
  "type": "Feature",
  "properties": {
    "iso:country":"CH",
    "sg:address":"Z\u00fcrcherstrasse 47",
    "sg:city":"Baden",
    "sg:orig_category":"Druck ohne Zeitungsdruck Siebdruck",
    "sg:phone":"+41 56 222 24 34",
    "sg:postcode":"5400",
    "sg:province":"Aargau",
    "wof:name":"Fiba Baden, Siebdruck & Beschriftungen",
    "wof:placetype":"venue"
},
  "geometry": {"coordinates":[8.3064928055,47.4670410156],"type":"Point"}
}