{
  "type": "Feature",
  "properties": {
    "addr:full":"Windeggli Siebeneich Kerns Obwalden 6064",
    "addr:postcode":"6064",
    "iso:country":"CH",
    "sg:address":"Windeggli Siebeneich",
    "sg:city":"Kerns",
    "sg:orig_category":"Blumen U Zierpflanzenbau Detailhandel mit Blumen U Pflanzen",
    "sg:phone":"+41 41 660 16 49",
    "sg:postcode":"6064",
    "sg:province":"Obwalden",
    "wof:name":"Willy Durrer G\u00e4rtnerei & Blumengesch\u00e4ft",
    "wof:placetype":"venue"
},
  "geometry": {"coordinates":[8.275,46.900822],"type":"Point"}
}