{
  "type": "Feature",
  "properties": {
    "addr:full":"Lange Gasse 78 Basel Basel-Stadt 4052",
    "addr:housenumber":"78",
    "addr:postcode":"4052",
    "addr:street":"Lange Gasse",
    "iso:country":"CH",
    "sg:address":"Lange Gasse 78",
    "sg:city":"Basel",
    "sg:orig_category":"Arztpraxen",
    "sg:phone":"+41 61 271 98 88",
    "sg:postcode":"4052",
    "sg:province":"Basel-Stadt",
    "wof:name":"Dr.med.urs Leibundgut Spezialarzt Fmh",
    "wof:placetype":"venue"
},
  "geometry": {"coordinates":[7.60087,47.551617],"type":"Point"}
}