{
  "type": "Feature",
  "properties": {
    "iso:country":"CH",
    "sg:address":"Place Chauderon 32",
    "sg:city":"Lausanne",
    "sg:orig_category":"Fachdetailhandel mit pharmazeutischen Produkten",
    "sg:phone":"+41 21 624 75 22",
    "sg:postcode":"1003",
    "sg:province":"Vaud",
    "wof:name":"Sghaier Isabelle Pharmacie De Chauderon Etc",
    "wof:placetype":"venue"
},
  "geometry": {"coordinates":[6.6241168976,46.5237731934],"type":"Point"}
}