{
  "type": "Feature",
  "properties": {
    "iso:country":"CH",
    "sg:address":"Route De Villeneuve 16",
    "sg:city":"Lucens",
    "sg:orig_category":"G\u00fcterbef\u00f6rderung im Strassenverkehr",
    "sg:phone":"+41 21 906 73 15",
    "sg:postcode":"1522",
    "sg:province":"Vaud",
    "wof:name":"Antonio Pugliese Transports",
    "wof:placetype":"venue"
},
  "geometry": {"coordinates":[6.8416500092,46.7110176086],"type":"Point"}
}