{
  "type": "Feature",
  "properties": {
    "addr:full":"Pulverm\u00fchlestrasse 23 Chur Graubunden 7000",
    "addr:housenumber":"23",
    "addr:postcode":"7000",
    "addr:street":"Pulvermuehlestrasse",
    "iso:country":"CH",
    "sg:address":"Pulverm\u00fchlestrasse 23",
    "sg:city":"Chur",
    "sg:orig_category":"Arbeitnehmerverb\u00e4nde",
    "sg:phone":"+41 81 284 65 63",
    "sg:postcode":"7000",
    "sg:province":"Graubunden",
    "wof:name":"Schweiz.typograph.vereinigung Sekt.chur,herrn Alfred Cerjak",
    "wof:placetype":"venue"
},
  "geometry": {"coordinates":[9.516117,46.85194],"type":"Point"}
}