{
  "type": "Feature",
  "properties": {
    "iso:country":"CH",
    "sg:address":"Rabius",
    "sg:city":"Rabius",
    "sg:classifiers":[
        {
            "category":"Banks & Credit Unions",
            "subcategory":"Bank",
            "type":"Services"
        }
    ],
    "sg:phone":"+41 81 943 19 17",
    "sg:postcode":"7172",
    "sg:province":"Graubunden",
    "wof:name":"Graub\u00fcndner Kantonalbank",
    "wof:placetype":"venue"
},
  "geometry": {"coordinates":[8.95336,46.738708],"type":"Point"}
}