{
  "type": "Feature",
  "properties": {
    "iso:country":"CH",
    "sg:address":"Ch. Du Ch\u00e2teau-bloc 12",
    "sg:city":"Vernier",
    "sg:orig_category":"Pensionskassen",
    "sg:postcode":"1214",
    "sg:province":"Gen\u00e8ve",
    "wof:name":"Fondation De Pr\u00e9voyance En Faveur Du Personnel Administratif Et Des Cadres Techniques De La Ferronnerie Genevoise Sa",
    "wof:placetype":"venue"
},
  "geometry": {"coordinates":[6.0990657806,46.2075195312],"type":"Point"}
}