{
  "type": "Feature",
  "properties": {
    "iso:country":"CH",
    "sg:address":"Rue Am\u00e9lie-munier-romilly 2",
    "sg:city":"Gen\u00e8ve",
    "sg:orig_category":"Primarschulen Religi\u00f6se Vereinigungen",
    "sg:phone":"+41 22 346 38 19",
    "sg:postcode":"1206",
    "sg:province":"Gen\u00e8ve",
    "wof:name":"Externat Catholique Des Glacis",
    "wof:placetype":"venue"
},
  "geometry": {"coordinates":[6.1529979706,46.197883606],"type":"Point"}
}