{
  "type": "Feature",
  "properties": {
    "iso:country":"CH",
    "sg:address":"Rue Du Temple 2",
    "sg:city":"Rolle",
    "sg:orig_category":"Zahnarztpraxen",
    "sg:phone":"+41 21 825 15 33",
    "sg:postcode":"1180",
    "sg:province":"Vaud",
    "wof:name":"Drs M\u00e9d.dent. Th.& Ch. Monnier M\u00e9decins-dentistes",
    "wof:placetype":"venue"
},
  "geometry": {"coordinates":[6.3382291794,46.4581298828],"type":"Point"}
}