{
  "type": "Feature",
  "properties": {
    "iso:country":"CH",
    "sg:address":"Parkstrasse",
    "sg:city":"Gstaad",
    "sg:orig_category":"Detailhandel mit Uhren U Schmuck Kunsthandel",
    "sg:phone":"+41 33 744 66 80",
    "sg:postcode":"3780",
    "sg:province":"Bern",
    "wof:name":"Adler Sa Bijouterie",
    "wof:placetype":"venue"
},
  "geometry": {"coordinates":[7.2882428169,46.4719810486],"type":"Point"}
}