{
  "type": "Feature",
  "properties": {
    "iso:country":"CH",
    "sg:address":"G\u00fcterstrasse 150",
    "sg:city":"Basel",
    "sg:orig_category":"Fachdetailhandel in Verkaufsr\u00e4umen",
    "sg:phone":"+41 61 363 28 28",
    "sg:postcode":"4053",
    "sg:province":"Basel-Stadt",
    "wof:name":"Palm Beach Peter Freymond",
    "wof:placetype":"venue"
},
  "geometry": {"coordinates":[7.5898251534,47.5444831848],"type":"Point"}
}