{
  "type": "Feature",
  "properties": {
    "addr:full":"Bahnhofplatz 6 Belp Bern 3123",
    "addr:housenumber":"6",
    "addr:postcode":"3123",
    "addr:street":"Bahnhofplatz",
    "iso:country":"CH",
    "sg:address":"Bahnhofplatz 6",
    "sg:city":"Belp",
    "sg:orig_category":"Buchverlag Verlagsgewerbe",
    "sg:phone":"+41 31 819 42 09",
    "sg:postcode":"3123",
    "sg:province":"Bern",
    "wof:name":"Tve Teaterverlag Elgg Gmbh In Belp",
    "wof:placetype":"venue"
},
  "geometry": {"coordinates":[7.498615,46.889023],"type":"Point"}
}