{
  "type": "Feature",
  "properties": {
    "iso:country":"CH",
    "sg:address":"Bergstrasse 4",
    "sg:city":"St\u00e4fa",
    "sg:orig_category":"Wirtschafts- and Arbeitgeberverb\u00e4nde",
    "sg:phone":"+41 81 413 16 68",
    "sg:postcode":"8712",
    "sg:province":"Z\u00fcrich",
    "wof:name":"Spenglermeister-& Installat.- Verband,hrn Walter Schwager",
    "wof:placetype":"venue"
},
  "geometry": {"coordinates":[9.8243083954,46.7969741821],"type":"Point"}
}