{
  "type": "Feature",
  "properties": {
    "iso:country":"CH",
    "sg:address":"Ri.nova Impulszentrum",
    "sg:city":"Rebstein",
    "sg:orig_category":"Allgemeiner Hoch U Tiefbau",
    "sg:phone":"+41 71 777 65 65",
    "sg:postcode":"9445",
    "sg:province":"St. Gallen",
    "wof:name":"Feierabend Victor Bau-supporting Gmbh",
    "wof:placetype":"venue"
},
  "geometry": {"coordinates":[9.584665,47.398724],"type":"Point"}
}