{
  "type": "Feature",
  "properties": {
    "iso:country":"CH",
    "sg:address":"D\u00e4hlenh\u00fcsli",
    "sg:city":"Gampelen",
    "sg:orig_category":"Schreib U \u00dcbersetzungsb\u00fcros",
    "sg:postcode":"3236",
    "sg:province":"Bern",
    "wof:name":"Gastrolingua Springbrunn A.",
    "wof:placetype":"venue"
},
  "geometry": {"coordinates":[7.0584812164,47.0145874023],"type":"Point"}
}