{
  "type": "Feature",
  "properties": {
    "iso:country":"CH",
    "sg:address":"8907 Wettswil. Postfach 277",
    "sg:city":"Wettswil",
    "sg:orig_category":"Sportvereine Ballsport Tennis",
    "sg:phone":"+41 19326303",
    "sg:postcode":"8907",
    "sg:province":"Z\u00fcrich",
    "wof:name":"Tennisclub Wetzikon",
    "wof:placetype":"venue"
},
  "geometry": {"coordinates":[8.8227109909,47.3280296326],"type":"Point"}
}