{
  "type": "Feature",
  "properties": {
    "iso:country":"CH",
    "sg:address":"Landstrasse 66",
    "sg:city":"Wettingen",
    "sg:orig_category":"Vermietung U Verpachtung von eigenen Immobilien",
    "sg:postcode":"5430",
    "sg:province":"Aargau",
    "wof:name":"Romo-immobilien Ag",
    "wof:placetype":"venue"
},
  "geometry": {"coordinates":[8.3233213425,47.4671401978],"type":"Point"}
}