{
  "type": "Feature",
  "properties": {
    "iso:country":"CH",
    "sg:address":"Schafh\u00fcbelstutz 3",
    "sg:city":"Balsthal",
    "sg:orig_category":"Unternehmensberatung",
    "sg:phone":"+41 62 391 22 44",
    "sg:postcode":"4710",
    "sg:province":"Solothurn",
    "wof:name":"Freiermuth R. Kunststoff-management-services",
    "wof:placetype":"venue"
},
  "geometry": {"coordinates":[7.6922450066,47.318157196],"type":"Point"}
}