{
  "type": "Feature",
  "properties": {
    "iso:country":"CH",
    "sg:address":"S\u00e4ntisstrasse 48",
    "sg:city":"Br\u00fctten",
    "sg:orig_category":"Luft U Raumfahrzeugbau Werbeberatung",
    "sg:phone":"+41 13020767",
    "sg:postcode":"8311",
    "sg:province":"Z\u00fcrich",
    "wof:name":"Business Jet Associates Gmbh Technische Erzeugnisse Der Flugzeugbranche; Beratung, Kaug, Verkauf Usw",
    "wof:placetype":"venue"
},
  "geometry": {"coordinates":[8.6809148788,47.4753608704],"type":"Point"}
}