{
  "type": "Feature",
  "properties": {
    "addr:full":"Breiteichli 5 Udligenswil Luzern 6044",
    "addr:housenumber":"5",
    "addr:postcode":"6044",
    "addr:street":"Breiteichli",
    "iso:country":"CH",
    "sg:address":"Breiteichli 5",
    "sg:city":"Udligenswil",
    "sg:orig_category":"Architekturb\u00fcros",
    "sg:phone":"+41 41 260 51 77",
    "sg:postcode":"6044",
    "sg:province":"Luzern",
    "wof:name":"Werner Dommann Architekturb\u00fcro",
    "wof:placetype":"venue"
},
  "geometry": {"coordinates":[8.403048,47.089115],"type":"Point"}
}