{
  "type": "Feature",
  "properties": {
    "iso:country":"CH",
    "sg:address":"Scharfrichtergasse 11",
    "sg:city":"Chur",
    "sg:orig_category":"Sonstiger Grosshandel",
    "sg:phone":"+41 81 252 30 35",
    "sg:postcode":"7000",
    "sg:province":"Graubunden",
    "wof:name":"Hemp Factory Gmbh",
    "wof:placetype":"venue"
},
  "geometry": {"coordinates":[9.5332927704,46.8509063721],"type":"Point"}
}