{
  "type": "Feature",
  "properties": {
    "iso:country":"CH",
    "sg:address":"Welsikerstrasse 35",
    "sg:city":"Dinhard",
    "sg:orig_category":"Wirtschaftsverb\u00e4nde Gewerbeverb\u00e4nde/-vereine",
    "sg:phone":"+41 52 384 14 60",
    "sg:postcode":"8474",
    "sg:province":"Z\u00fcrich",
    "wof:name":"Gewerbeverein Dinhard/thurtal Pr\u00e4s.herrn Erwin Peter",
    "wof:placetype":"venue"
},
  "geometry": {"coordinates":[8.7665691376,47.5550994873],"type":"Point"}
}