{
  "type": "Feature",
  "properties": {
    "iso:country":"CH",
    "sg:address":"Schulanlage Selhofen",
    "sg:city":"Kehrsatz",
    "sg:classifiers":[
        {
            "category":"Education",
            "subcategory":"Library",
            "type":"Public Place"
        }
    ],
    "sg:postcode":"3122",
    "sg:province":"Bern",
    "sg:tags":[
        "u",
        "bibliotheken",
        "archive"
    ],
    "wof:name":"Jugend-& Arbeitsbibliothek",
    "wof:placetype":"venue"
},
  "geometry": {"coordinates":[7.470869,46.910843],"type":"Point"}
}