{
  "type": "Feature",
  "properties": {
    "iso:country":"CH",
    "sg:address":"Holiweg 41",
    "sg:city":"Schnottwil",
    "sg:orig_category":"Landw. Genossenschaften Dresch",
    "sg:phone":"+41 56 496 18 89",
    "sg:postcode":"3253",
    "sg:province":"Solothurn",
    "wof:name":"Alois Huber Drescherei",
    "wof:placetype":"venue"
},
  "geometry": {"coordinates":[8.306353569,47.4003677368],"type":"Point"}
}