{
  "type": "Feature",
  "properties": {
    "iso:country":"CH",
    "sg:address":"Bernstrasse 139 3627 Heimberg. Postfach",
    "sg:city":"Heimberg",
    "sg:orig_category":"Geschenk- and Werbeartikel Grosshandel Grosshandel mit Spielwaren",
    "sg:phone":"+41 33 439 90 30",
    "sg:postcode":"3627",
    "sg:province":"Bern",
    "wof:name":"Ballon-m\u00fcller Gmbh Ballone & Geschenke",
    "wof:placetype":"venue"
},
  "geometry": {"coordinates":[7.6117119789,46.779548645],"type":"Point"}
}