{
  "type": "Feature",
  "properties": {
    "iso:country":"CH",
    "sg:address":"Voltastrasse 10",
    "sg:city":"Luzern",
    "sg:orig_category":"Fotografische Ateliers",
    "sg:phone":"+41 41 360 70 72",
    "sg:postcode":"6005",
    "sg:province":"Luzern",
    "wof:name":"Christina Niederer Atelier F\u00fcr Fotografik",
    "wof:placetype":"venue"
},
  "geometry": {"coordinates":[8.3070926666,47.0405158997],"type":"Point"}
}