{
  "type": "Feature",
  "properties": {
    "iso:country":"CH",
    "sg:address":"Nassa Via 38",
    "sg:city":"Lugano",
    "sg:orig_category":"Unternehmensberatung",
    "sg:postcode":"6900",
    "sg:province":"Ticino",
    "wof:name":"Industrial Polimers Sa, Lussemburgo, Succursale Di Lugano",
    "wof:placetype":"venue"
},
  "geometry": {"coordinates":[8.9494762421,46.0021896362],"type":"Point"}
}