{
  "type": "Feature",
  "properties": {
    "iso:country":"CH",
    "sg:address":"2813",
    "sg:city":"Ederswiler",
    "sg:orig_category":"S\u00e4gewerke",
    "sg:phone":"+41 32 431 12 68",
    "sg:postcode":"2813",
    "sg:province":"Jura",
    "wof:name":"M. Schmidlin Sa Industrie Du Bois",
    "wof:placetype":"venue"
},
  "geometry": {"coordinates":[7.3357849121,47.425743103],"type":"Point"}
}