{
  "type": "Feature",
  "properties": {
    "iso:country":"CH",
    "sg:address":"Bernstrasse 34 3303 Jegenstorf. Postfach",
    "sg:city":"Jegenstorf",
    "sg:orig_category":"Elektroinstallation",
    "sg:phone":"+41 31 761 22 04",
    "sg:postcode":"3303",
    "sg:province":"Bern",
    "wof:name":"Elektro Sch\u00e4r Ag",
    "wof:placetype":"venue"
},
  "geometry": {"coordinates":[7.5051188469,47.0464401245],"type":"Point"}
}