{
  "type": "Feature",
  "properties": {
    "addr:full":"La Stampa Canobbio Ticino 6952",
    "addr:postcode":"6952",
    "iso:country":"CH",
    "sg:address":"La Stampa",
    "sg:city":"Canobbio",
    "sg:orig_category":"Autogaragen",
    "sg:phone":"+41 91 942 59 41",
    "sg:postcode":"6952",
    "sg:province":"Ticino",
    "wof:name":"Mauro Bissolotti Garage",
    "wof:placetype":"venue"
},
  "geometry": {"coordinates":[8.965891,46.035343],"type":"Point"}
}