{
  "type": "Feature",
  "properties": {
    "iso:country":"CH",
    "sg:address":"Neufeldstrasse 15a",
    "sg:city":"Wettingen",
    "sg:orig_category":"Herstellung von sonstigen Maschinen f\u00fcr unspezifische Verwendung Maschinen and Apparate divers Gross",
    "sg:phone":"+41 56 426 81 51",
    "sg:postcode":"5430",
    "sg:province":"Aargau",
    "wof:name":"Barth Technik Gmbh",
    "wof:placetype":"venue"
},
  "geometry": {"coordinates":[8.3390130997,47.4597854614],"type":"Point"}
}