{
  "type": "Feature",
  "properties": {
    "iso:country":"CH",
    "sg:address":"Hinterbergstrasse 11 6330 Cham. Postfach 5034",
    "sg:city":"Cham",
    "sg:orig_category":"Herstellung von sonstigen Maschinen f\u00fcr bestimmte Verwendung",
    "sg:phone":"+41 41 748 71 11",
    "sg:postcode":"6330",
    "sg:province":"Zug",
    "wof:name":"Am Digital Ag",
    "wof:placetype":"venue"
},
  "geometry": {"coordinates":[8.4765262604,47.1871566772],"type":"Point"}
}