{
  "type": "Feature",
  "properties": {
    "iso:country":"CH",
    "sg:address":"En Bitternaz 9 1562 Corcelles-payerne. Postfach",
    "sg:city":"Corcelles-payerne",
    "sg:orig_category":"Non-Classified Establishments",
    "sg:postcode":"1562",
    "sg:province":"Vaud",
    "wof:name":"Schneider Location & Vaisselle De Fete S\u00e0rl Mat\u00e9riel Et Infrastructure N\u00e9cessaires \u00e0 L'organisation De Manifestations Publiques Ou Priv\u00e9es; Commerce, Location Etc",
    "wof:placetype":"venue"
},
  "geometry": {"coordinates":[6.9615449905,46.8308105469],"type":"Point"}
}