{
  "type": "Feature",
  "properties": {
    "iso:country":"CH",
    "sg:address":"Freigutstrasse 27 8002 Z\u00fcrich. Postfach 452",
    "sg:city":"Z\u00fcrich",
    "sg:orig_category":"Finanzierungsinstitutionen",
    "sg:phone":"+41 12014710",
    "sg:postcode":"8027",
    "sg:province":"Z\u00fcrich",
    "wof:name":"Orbitex Finanz Ag",
    "wof:placetype":"venue"
},
  "geometry": {"coordinates":[8.5307626724,47.3683013916],"type":"Point"}
}