{
  "type": "Feature",
  "properties": {
    "iso:country":"CH",
    "sg:address":"Br\u00fcggmatte",
    "sg:city":"Boltigen",
    "sg:orig_category":"Non-Classified Establishments",
    "sg:postcode":"3766",
    "sg:province":"Bern",
    "wof:name":"Teuscher Hans Carrosserie & Abschleppdienst",
    "wof:placetype":"venue"
},
  "geometry": {"coordinates":[7.3924641609,46.6294898987],"type":"Point"}
}