{
  "type": "Feature",
  "properties": {
    "iso:country":"CH",
    "sg:address":"Bifangstrasse 6",
    "sg:city":"Neuenhof",
    "sg:orig_category":"Architektur U Ingenieurb\u00fcros",
    "sg:phone":"+41 56 406 48 03",
    "sg:postcode":"5432",
    "sg:province":"Aargau",
    "wof:name":"Efcon Ag Verm\u00f6gensverwaltung",
    "wof:placetype":"venue"
},
  "geometry": {"coordinates":[8.327826,47.446102],"type":"Point"}
}