{
  "type": "Feature",
  "properties": {
    "iso:country":"CH",
    "sg:address":"Steingasse 12",
    "sg:city":"Niederbipp",
    "sg:orig_category":"Detailhandel mit M\u00f6beln U Haushaltsgegenst\u00e4nden Innendekorationsateliers",
    "sg:phone":"+41 32 633 15 17",
    "sg:postcode":"4704",
    "sg:province":"Bern",
    "wof:name":"Sch\u00f6nmann Inneneinrichtungen Ag",
    "wof:placetype":"venue"
},
  "geometry": {"coordinates":[7.6916260719,47.2698020935],"type":"Point"}
}