{
  "type": "Feature",
  "properties": {
    "addr:full":"Christoph-schnyder-str. 18 Sursee Luzern 6210",
    "addr:housenumber":"18",
    "addr:postcode":"6210",
    "addr:street":"Christoph-Schnyder-Str.",
    "iso:country":"CH",
    "sg:address":"Christoph-schnyder-str. 18",
    "sg:city":"Sursee",
    "sg:orig_category":"Architektur U Ingenieurb\u00fcros",
    "sg:phone":"+41 41 921 04 04",
    "sg:postcode":"6210",
    "sg:province":"Luzern",
    "wof:name":"Roesch Gerhard B\u00fcro F\u00fcr Architektur & Raumplanung",
    "wof:placetype":"venue"
},
  "geometry": {"coordinates":[8.103529,47.168549],"type":"Point"}
}