{
  "type": "Feature",
  "properties": {
    "iso:country":"CH",
    "sg:address":"Feldstrasse 55",
    "sg:city":"Sarnen",
    "sg:orig_category":"Herstellung von k\u00e4lte U lufttechnischen Erzeugnissen f\u00fcr gewerbliche Zwecke",
    "sg:postcode":"6060",
    "sg:province":"Obwalden",
    "wof:name":"Sanotherm Ag",
    "wof:placetype":"venue"
},
  "geometry": {"coordinates":[8.2525148392,46.9004745483],"type":"Point"}
}