{
  "type": "Feature",
  "properties": {
    "addr:full":"Blegistrasse 3 6340 Baar. Postfach Baar Zug 6340",
    "addr:housenumber":"3",
    "addr:postcode":"6340 baar. postfach;6340",
    "addr:street":"Blegistrasse;Zug",
    "iso:country":"CH",
    "sg:address":"Blegistrasse 3 6340 Baar. Postfach",
    "sg:city":"Baar",
    "sg:orig_category":"Architektur U Ingenieurb\u00fcros",
    "sg:postcode":"6340",
    "sg:province":"Zug",
    "wof:name":"L\u00fcem Thomas Partner Baar Ag",
    "wof:placetype":"venue"
},
  "geometry": {"coordinates":[8.572193,47.216106],"type":"Point"}
}