{
  "type": "Feature",
  "properties": {
    "iso:country":"CH",
    "sg:address":"Hauptstrasse 93",
    "sg:city":"Sissach",
    "sg:classifiers":[
        {
            "category":"Banks & Credit Unions",
            "subcategory":"Bank",
            "type":"Services"
        }
    ],
    "sg:phone":"+41 61 971 40 04",
    "sg:postcode":"4450",
    "sg:province":"Basel-Landschaft",
    "wof:name":"Regiobank Beider Basel",
    "wof:placetype":"venue"
},
  "geometry": {"coordinates":[7.809072,47.464638],"type":"Point"}
}