{
  "type": "Feature",
  "properties": {
    "iso:country":"CH",
    "sg:address":"Fleury Rue 20",
    "sg:city":"Neuch\u00e2tel",
    "sg:orig_category":"Detailhandel mit Fleisch U Fleischwaren",
    "sg:phone":"+41 32 725 10 50",
    "sg:postcode":"2000",
    "sg:province":"Neuch\u00e2tel",
    "wof:name":"Boucherie-charcuterie-traiteur Andr\u00e9 Munnier.",
    "wof:placetype":"venue"
},
  "geometry": {"coordinates":[6.9280338287,46.9910087585],"type":"Point"}
}