{
  "type": "Feature",
  "properties": {
    "iso:country":"CH",
    "sg:address":"Grand-rue 4",
    "sg:city":"Montreux",
    "sg:orig_category":"Kauf U Verkauf von Immobilien auf eigene Rechnung",
    "sg:phone":"+41 21 963 15 22",
    "sg:postcode":"1820",
    "sg:province":"Vaud",
    "wof:name":"Soci\u00e9t\u00e9 D'hauterive \u00e0 Montreux",
    "wof:placetype":"venue"
},
  "geometry": {"coordinates":[6.9106588364,46.4318695068],"type":"Point"}
}