{
  "type": "Feature",
  "properties": {
    "iso:country":"CH",
    "sg:address":"Zieglerstrasse 20",
    "sg:city":"Bern",
    "sg:orig_category":"RESTAURANTS: TEA-ROOMS",
    "sg:postcode":"3007",
    "sg:province":"Bern",
    "wof:name":"Don Camillo Bern Gmbh",
    "wof:placetype":"venue"
},
  "geometry": {"coordinates":[7.4290328026,46.9464263916],"type":"Point"}
}