{
  "type": "Feature",
  "properties": {
    "iso:country":"CH",
    "sg:address":"Feldstrasse 20",
    "sg:city":"Thal",
    "sg:orig_category":"Herstellung von sonstigen Maschinen f\u00fcr unspezifische Verwendung",
    "sg:phone":"+41 71 888 06 56",
    "sg:postcode":"9425",
    "sg:province":"St. Gallen",
    "wof:name":"R\u00fcmmelin Engineering Gmbh",
    "wof:placetype":"venue"
},
  "geometry": {"coordinates":[9.5613193512,47.4648971558],"type":"Point"}
}