{
  "type": "Feature",
  "properties": {
    "iso:country":"CH",
    "sg:address":"Route Chocolati\u00e8re 11",
    "sg:city":"Echandens",
    "sg:orig_category":"Satzherstellung U Reproduktion",
    "sg:phone":"+41 21 701 26 26",
    "sg:postcode":"1026",
    "sg:province":"Vaud",
    "wof:name":"Promotext Sa",
    "wof:placetype":"venue"
},
  "geometry": {"coordinates":[6.5466470718,46.5379524231],"type":"Point"}
}