{
  "type": "Feature",
  "properties": {
    "iso:country":"CH",
    "sg:address":"Bahnhofstrasse 67 5000 Aarau. Postfach",
    "sg:city":"Aarau",
    "sg:orig_category":"Nationale Postdienste",
    "sg:phone":"+41 61 821 10 75",
    "sg:postcode":"5001",
    "sg:province":"Aargau",
    "wof:name":"Die Schweizerische Post Pratteln 2 Stockmatt",
    "wof:placetype":"venue"
},
  "geometry": {"coordinates":[7.6811709404,47.5199584961],"type":"Point"}
}