{
  "type": "Feature",
  "properties": {
    "iso:country":"CH",
    "sg:address":"P\u00fcndtstrasse",
    "sg:city":"Arbon",
    "sg:orig_category":"Instandhaltung U Reparatur von Automobilen",
    "sg:phone":"+41 71 411 11 57",
    "sg:postcode":"9320",
    "sg:province":"Thurgau",
    "wof:name":"Autowaschzentrum Baumann H.",
    "wof:placetype":"venue"
},
  "geometry": {"coordinates":[9.4205722809,47.4983444214],"type":"Point"}
}