{
  "type": "Feature",
  "properties": {
    "iso:country":"CH",
    "sg:address":"4116",
    "sg:city":"Metzerlen",
    "sg:classifiers":[
        {
            "category":"Travel",
            "subcategory":"Hotels & Motels",
            "type":"Entertainment"
        }
    ],
    "sg:postcode":"4116",
    "sg:province":"Solothurn",
    "sg:tags":[
        "hotels",
        "mit",
        "restaurant"
    ],
    "wof:name":"Risse Mme Charlotte",
    "wof:placetype":"venue"
},
  "geometry": {"coordinates":[7.1380701065,46.6968002319],"type":"Point"}
}