{
  "type": "Feature",
  "properties": {
    "iso:country":"CH",
    "sg:address":"Schaffhauserstr. 200",
    "sg:city":"Frauenfeld",
    "sg:classifiers":[
        {
            "category":"Farming",
            "subcategory":"Crops",
            "type":"Manufacturing & Wholesale Goods"
        }
    ],
    "sg:phone":"+41 52 728 09 09",
    "sg:postcode":"8500",
    "sg:province":"Thurgau",
    "sg:tags":[
        "vegetable",
        "fruit",
        "agriculture",
        "livestock"
    ],
    "wof:name":"Giovanelli Fruchtimport Ag",
    "wof:placetype":"venue"
},
  "geometry": {"coordinates":[8.87739,47.563335],"type":"Point"}
}