{
  "type": "Feature",
  "properties": {
    "iso:country":"CH",
    "sg:address":"8052",
    "sg:city":"Seebach",
    "sg:orig_category":"Lagerh\u00e4user, G\u00fcterumschlag, Verteilzentren",
    "sg:postcode":"8052",
    "sg:province":"Z\u00fcrich",
    "wof:name":"Genossenschaft F\u00fcr Brennstoff-lagerhaltung Z\u00fcrich",
    "wof:placetype":"venue"
},
  "geometry": {"coordinates":[8.5402402878,47.4224815369],"type":"Point"}
}