{
  "type": "Feature",
  "properties": {
    "iso:country":"CH",
    "sg:address":"Rastberg",
    "sg:city":"Sarnen",
    "sg:orig_category":"Grosshandel mit lebenden Tieren",
    "sg:phone":"+41 41 660 22 93",
    "sg:postcode":"6060",
    "sg:province":"Obwalden",
    "wof:name":"Alois Krummenacher Viehhandel",
    "wof:placetype":"venue"
},
  "geometry": {"coordinates":[8.2448596954,46.8933639526],"type":"Point"}
}