{
  "type": "Feature",
  "properties": {
    "iso:country":"CH",
    "sg:address":"Schmelzbergstrasse 57",
    "sg:city":"Z\u00fcrich",
    "sg:orig_category":"Unternehmensberatung",
    "sg:phone":"+41 19153949",
    "sg:postcode":"8044",
    "sg:province":"Z\u00fcrich",
    "wof:name":"Gwb Gesellschaft F\u00fcr Wirtschafts Und Bauberatung Ag",
    "wof:placetype":"venue"
},
  "geometry": {"coordinates":[8.5982656479,47.2977790833],"type":"Point"}
}