{
  "type": "Feature",
  "properties": {
    "iso:country":"CH",
    "sg:address":"Neugutstrasse 15",
    "sg:city":"Oberengstringen",
    "sg:orig_category":"Instandhaltung U Reparatur von Automobilen",
    "sg:phone":"+41 17504641",
    "sg:postcode":"8102",
    "sg:province":"Z\u00fcrich",
    "wof:name":"Garage Thomas Haas Ag",
    "wof:placetype":"venue"
},
  "geometry": {"coordinates":[8.457324028,47.4072799683],"type":"Point"}
}