{
  "type": "Feature",
  "properties": {
    "iso:country":"CH",
    "sg:address":"T\u00f6beli 4",
    "sg:city":"Speicher",
    "sg:orig_category":"Vermietung U Verpachtung von eigenen Immobilien",
    "sg:phone":"+41 19109608",
    "sg:postcode":"9042",
    "sg:province":"Appenzell Ausserrhoden",
    "wof:name":"Gewerbehaus Binz Ag",
    "wof:placetype":"venue"
},
  "geometry": {"coordinates":[8.5958995819,47.3122024536],"type":"Point"}
}