{
  "type": "Feature",
  "properties": {
    "iso:country":"CH",
    "sg:address":"Schulhausweg 4",
    "sg:city":"Ganterschwil",
    "sg:orig_category":"Instandhaltung U Reparatur von Automobilen",
    "sg:phone":"+41 71 983 11 80",
    "sg:postcode":"9608",
    "sg:province":"St. Gallen",
    "wof:name":"Manser & Co",
    "wof:placetype":"venue"
},
  "geometry": {"coordinates":[9.0890007019,47.3802566528],"type":"Point"}
}