{
  "type": "Feature",
  "properties": {
    "iso:country":"CH",
    "sg:address":"Mitteldorfstrasse 29",
    "sg:city":"Ostermundigen",
    "sg:orig_category":"Satzherstellung U Reproduktion",
    "sg:postcode":"3072",
    "sg:province":"Bern",
    "wof:name":"Giger's Belichtungsservice",
    "wof:placetype":"venue"
},
  "geometry": {"coordinates":[7.4914479256,46.9557876587],"type":"Point"}
}