{
  "type": "Feature",
  "properties": {
    "iso:country":"CH",
    "sg:address":"Unterdorfweg 3",
    "sg:city":"Hindelbank",
    "sg:orig_category":"Zahnarztpraxen",
    "sg:phone":"+41 31 332 35 19",
    "sg:postcode":"3324",
    "sg:province":"Bern",
    "wof:name":"Dr. Med. Dent. Ivan Sokol Zahnarzt",
    "wof:placetype":"venue"
},
  "geometry": {"coordinates":[7.5406160355,47.0450973511],"type":"Point"}
}