{
  "type": "Feature",
  "properties": {
    "iso:country":"CH",
    "sg:address":"Gr\u00fcnweg 3",
    "sg:city":"Scheuren",
    "sg:orig_category":"Fernmeldedienste",
    "sg:phone":"+41 79 300 45 27",
    "sg:postcode":"2556",
    "sg:province":"Bern",
    "wof:name":"Web D-sign",
    "wof:placetype":"venue"
},
  "geometry": {"coordinates":[7.3161478043,47.1345367432],"type":"Point"}
}