{
  "type": "Feature",
  "properties": {
    "iso:country":"CH",
    "sg:address":"Salavaux",
    "sg:city":"Salavaux",
    "sg:orig_category":"Herstellung von Oberbekleidung",
    "sg:phone":"+41 19201203",
    "sg:postcode":"1585",
    "sg:province":"Vaud",
    "wof:name":"Fantaisy Mode Rochdi",
    "wof:placetype":"venue"
},
  "geometry": {"coordinates":[8.6742801666,47.267162323],"type":"Point"}
}