{
  "type": "Feature",
  "properties": {
    "iso:country":"CH",
    "sg:address":"Rotwaldstrasse 10",
    "sg:city":"Bazenheid",
    "sg:orig_category":"Einbau von Schreinerwaren",
    "sg:phone":"+41 71 931 25 60",
    "sg:postcode":"9602",
    "sg:province":"St. Gallen",
    "wof:name":"Secoba Gmbh K\u00fcchenmontagen",
    "wof:placetype":"venue"
},
  "geometry": {"coordinates":[9.072508812,47.4085884094],"type":"Point"}
}