{
  "type": "Feature",
  "properties": {
    "iso:country":"CH",
    "sg:address":"Spielmatte 3",
    "sg:city":"Unterseen",
    "sg:classifiers":[
        {
            "category":"Professional",
            "subcategory":"Employment Agencies",
            "type":"Services"
        }
    ],
    "sg:phone":"+41 33 823 75 75",
    "sg:postcode":"3800",
    "sg:province":"Bern",
    "sg:tags":[
        "personal",
        "u",
        "stellenvermittlung"
    ],
    "wof:name":"Rav Berner Oberland Regionales Arbeitsvermittlungszentrum",
    "wof:placetype":"venue"
},
  "geometry": {"coordinates":[7.851293087,46.687084198],"type":"Point"}
}