{
  "type": "Feature",
  "properties": {
    "iso:country":"CH",
    "sg:address":"Brunnenh\u00f6fli 5 Obernau 6010 Kriens. Postfach",
    "sg:city":"Obernau",
    "sg:orig_category":"Sonstige pers\u00f6nliche Dienstleistungen",
    "sg:postcode":"6012",
    "sg:province":"Luzern",
    "wof:name":"Beratung.l\u00f6i.mettauer",
    "wof:placetype":"venue"
},
  "geometry": {"coordinates":[8.2792053223,47.0338058472],"type":"Point"}
}