{
  "type": "Feature",
  "properties": {
    "iso:country":"CH",
    "sg:address":"Kantonsstrasse 34",
    "sg:city":"Geuensee",
    "sg:orig_category":"Instandhaltung U Reparatur von Automobilen Tankstellen",
    "sg:phone":"+41 41 921 97 37",
    "sg:postcode":"6232",
    "sg:province":"Luzern",
    "wof:name":"Garage Peter",
    "wof:placetype":"venue"
},
  "geometry": {"coordinates":[8.1084098816,47.1986999512],"type":"Point"}
}