{
  "type": "Feature",
  "properties": {
    "iso:country":"CH",
    "sg:address":"Rh\u00f4ne Du 3",
    "sg:city":"Aigle",
    "sg:orig_category":"Wirtschaftspr\u00fcfung, Steuerberatung U Treuhand",
    "sg:postcode":"1860",
    "sg:province":"Vaud",
    "wof:name":"Fiduciaire Rochat C.",
    "wof:placetype":"venue"
},
  "geometry": {"coordinates":[6.9673709869,46.3168334961],"type":"Point"}
}