{
  "type": "Feature",
  "properties": {
    "iso:country":"CH",
    "sg:address":"K\u00f6llikerstrasse 84",
    "sg:city":"Gretzenbach",
    "sg:orig_category":"Handelsvermittlung U Grosshandel R\u00fcckgewinnung U Vorbereitung f\u00fcr die Wiederverwertung Recycling",
    "sg:phone":"+41 71 288 34 94",
    "sg:postcode":"5014",
    "sg:province":"Solothurn",
    "wof:name":"Ren\u00e9 Huber Altmetallhandel",
    "wof:placetype":"venue"
},
  "geometry": {"coordinates":[9.4045495987,47.4355354309],"type":"Point"}
}