{
  "type": "Feature",
  "properties": {
    "iso:country":"CH",
    "sg:address":"Aubrigstrasse 14",
    "sg:city":"Horgen",
    "sg:orig_category":"Vereine Vogel-& Naturschutz",
    "sg:postcode":"8810",
    "sg:province":"Z\u00fcrich",
    "wof:name":"Naturschutzverein Oberglatt",
    "wof:placetype":"venue"
},
  "geometry": {"coordinates":[8.5188398361,47.4763717651],"type":"Point"}
}