{
  "type": "Feature",
  "properties": {
    "iso:country":"CH",
    "sg:address":"Rickenstrasse 9",
    "sg:city":"Hombrechtikon",
    "sg:orig_category":"Kauf U Verkauf von Immobilien auf eigene Rechnung",
    "sg:postcode":"8634",
    "sg:province":"Z\u00fcrich",
    "wof:name":"Tucan Ag",
    "wof:placetype":"venue"
},
  "geometry": {"coordinates":[8.7810297012,47.2522735596],"type":"Point"}
}