{
  "type": "Feature",
  "properties": {
    "iso:country":"CH",
    "sg:address":"Zugerstrasse 53",
    "sg:city":"Cham",
    "sg:orig_category":"Herstellung von Mess U Kontrollinstrumenten U vorrichtungen",
    "sg:postcode":"6330",
    "sg:province":"Zug",
    "wof:name":"Arma Sa",
    "wof:placetype":"venue"
},
  "geometry": {"coordinates":[7.019343853,47.0383148193],"type":"Point"}
}