{
  "type": "Feature",
  "properties": {
    "iso:country":"CH",
    "sg:address":"G\u00fcterstrasse 213 4053 Basel. Postfach",
    "sg:city":"Basel",
    "sg:orig_category":"Versicherungen Generalagenturen",
    "sg:phone":"+41 31 302 41 71",
    "sg:postcode":"4018",
    "sg:province":"Basel-Stadt",
    "wof:name":"Fortuna Versicherungen Generalagentur",
    "wof:placetype":"venue"
},
  "geometry": {"coordinates":[7.4370679855,46.9544792175],"type":"Point"}
}