{
  "type": "Feature",
  "properties": {
    "iso:country":"CH",
    "sg:address":"Sch\u00e4rweg 32",
    "sg:city":"Therwil",
    "sg:orig_category":"Bauspenglerei Dachdeckerei",
    "sg:phone":"+41 61 721 39 33",
    "sg:postcode":"4106",
    "sg:province":"Basel-Landschaft",
    "wof:name":"Abax F.gutzwiller",
    "wof:placetype":"venue"
},
  "geometry": {"coordinates":[7.553015,47.492451],"type":"Point"}
}