{
  "type": "Feature",
  "properties": {
    "iso:country":"CH",
    "sg:address":"Langensandstrasse 23",
    "sg:city":"Luzern",
    "sg:orig_category":"Detailhandel mit Damenbekleidung Detailhandel mit Herrenbekleidung",
    "sg:phone":"+41 41 360 24 24",
    "sg:postcode":"6005",
    "sg:province":"Luzern",
    "wof:name":"Charles V\u00f6gele Mode Ag",
    "wof:placetype":"venue"
},
  "geometry": {"coordinates":[8.3275680542,47.0372085571],"type":"Point"}
}