{
  "type": "Feature",
  "properties": {
    "iso:country":"CH",
    "sg:address":"Im Muchried 4",
    "sg:city":"Wettswil",
    "sg:orig_category":"Vereine Gesang",
    "sg:phone":"+41 52 741 32 06",
    "sg:postcode":"8907",
    "sg:province":"Z\u00fcrich",
    "wof:name":"Kirchenchor Stein Am Rhein",
    "wof:placetype":"venue"
},
  "geometry": {"coordinates":[8.8598861694,47.6590652466],"type":"Point"}
}