{
  "type": "Feature",
  "properties": {
    "iso:country":"CH",
    "sg:address":"Via Violino 1",
    "sg:city":"Manno",
    "sg:orig_category":"Grosshandel mit elektrischen Haushaltsger\u00e4ten Herstellung von sonstigen elektrischen Ausr\u00fcstungen",
    "sg:phone":"+41 41 210 68 00",
    "sg:postcode":"6928",
    "sg:province":"Ticino",
    "wof:name":"Electronova Luzern Gmbh",
    "wof:placetype":"venue"
},
  "geometry": {"coordinates":[8.3055391312,47.0446128845],"type":"Point"}
}