{
  "type": "Feature",
  "properties": {
    "iso:country":"CH",
    "sg:address":"Unterdorf",
    "sg:city":"Lauperswil",
    "sg:classifiers":[
        {
            "category":"Professional",
            "subcategory":"Advertising",
            "type":"Services"
        }
    ],
    "sg:phone":"+41 34 496 98 98",
    "sg:postcode":"3438",
    "sg:province":"Bern",
    "sg:tags":[
        "information",
        "medium",
        "communication"
    ],
    "wof:name":"Frama Ag",
    "wof:placetype":"venue"
},
  "geometry": {"coordinates":[7.743105,46.966965],"type":"Point"}
}