{
  "type": "Feature",
  "properties": {
    "iso:country":"CH",
    "sg:address":"Quellenstrasse 2",
    "sg:city":"Uster",
    "sg:orig_category":"Mit dem Versicherungsgewerbe verbundene T\u00e4tigkeiten",
    "sg:phone":"+41 19405444",
    "sg:postcode":"8610",
    "sg:province":"Z\u00fcrich",
    "wof:name":"Refinanz, Finanzplanungen",
    "wof:placetype":"venue"
},
  "geometry": {"coordinates":[8.7081203461,47.3484268188],"type":"Point"}
}