{
  "type": "Feature",
  "properties": {
    "iso:country":"CH",
    "sg:address":"Zypressenstrasse 60 8001 Z\u00fcrich. Postfach",
    "sg:city":"Z\u00fcrich",
    "sg:orig_category":"Unclassifiable Establishments",
    "sg:postcode":"8004",
    "sg:province":"Z\u00fcrich",
    "wof:name":"Finanzgesellschaft F\u00fcr B\u00f6rsenwerte Sa",
    "wof:placetype":"venue"
},
  "geometry": {"coordinates":[8.9564599991,46.0654716492],"type":"Point"}
}