{
  "type": "Feature",
  "properties": {
    "iso:country":"CH",
    "sg:address":"Cart Rue Jean-jacques- 8",
    "sg:city":"Lausanne",
    "sg:orig_category":"Unclassifiable Establishments",
    "sg:postcode":"1006",
    "sg:province":"Vaud",
    "wof:name":"Fondation Saint-pierre Pour La Diffusion Du Message Chr\u00e9tien",
    "wof:placetype":"venue"
},
  "geometry": {"coordinates":[6.6257939339,46.5142478943],"type":"Point"}
}