{
  "type": "Feature",
  "properties": {
    "iso:country":"CH",
    "sg:address":"Sumpf 3 3324 Hindelbank. Postfach",
    "sg:city":"Hindelbank",
    "sg:orig_category":"Ackerbau",
    "sg:postcode":"3324",
    "sg:province":"Bern",
    "wof:name":"Agrones Gmbh",
    "wof:placetype":"venue"
},
  "geometry": {"coordinates":[7.557687,47.055351],"type":"Point"}
}