{
  "type": "Feature",
  "properties": {
    "addr:full":"Hauptstrasse 66 Pfeffingen Basel-Landschaft 4148",
    "addr:housenumber":"66",
    "addr:postcode":"4148",
    "addr:street":"Hauptstrasse",
    "iso:country":"CH",
    "sg:address":"Hauptstrasse 66",
    "sg:city":"Pfeffingen",
    "sg:orig_category":"Bauspenglerei Zimmerei, Dachdeckerei, Bauspenglerei U Abdichtung",
    "sg:phone":"+41 61 751 13 42",
    "sg:postcode":"4148",
    "sg:province":"Basel-Landschaft",
    "wof:name":"Schibig Josef",
    "wof:placetype":"venue"
},
  "geometry": {"coordinates":[7.589945,47.458427],"type":"Point"}
}