{
  "type": "Feature",
  "properties": {
    "iso:country":"CH",
    "sg:address":"Th\u00e9\u00e2tre Bvd Du 4-6 1204 Gen\u00e8ve. Postfach",
    "sg:city":"Gen\u00e8ve",
    "sg:orig_category":"Interessenvertretungen",
    "sg:postcode":"1201",
    "sg:province":"Gen\u00e8ve",
    "wof:name":"Fondation Ineichen Emmy",
    "wof:placetype":"venue"
},
  "geometry": {"coordinates":[8.3174819946,47.2825775146],"type":"Point"}
}