{
  "type": "Feature",
  "properties": {
    "iso:country":"CH",
    "sg:address":"Allmendweg 13 6330 Cham. Postfach",
    "sg:city":"Baar",
    "sg:orig_category":"Unternehmensberatung",
    "sg:phone":"+41 41 760 99 09",
    "sg:postcode":"6340",
    "sg:province":"Zug",
    "wof:name":"Arpos Gmbh Beratung Und Coaching F\u00fcr Prozess, Organisations Und Systemengineering Usw",
    "wof:placetype":"venue"
},
  "geometry": {"coordinates":[8.4533891678,47.1803741455],"type":"Point"}
}