{
  "type": "Feature",
  "properties": {
    "iso:country":"CH",
    "sg:address":"Dornhaldestrasse 51",
    "sg:city":"Heimberg",
    "sg:orig_category":"Sonstiger Grosshandel",
    "sg:phone":"+41 26 436 58 50",
    "sg:postcode":"3627",
    "sg:province":"Bern",
    "wof:name":"Schaer Paul Sa",
    "wof:placetype":"venue"
},
  "geometry": {"coordinates":[7.1459388733,46.7542304993],"type":"Point"}
}