{
  "type": "Feature",
  "properties": {
    "iso:country":"CH",
    "sg:address":"Rue De La Plaine 44",
    "sg:city":"Yverdon-les-bains",
    "sg:orig_category":"Bauspenglerei Zimmerei, Dachdeckerei, Bauspenglerei U Abdichtung",
    "sg:phone":"+41 32 961 10 34",
    "sg:postcode":"1400",
    "sg:province":"Vaud",
    "wof:name":"Jobin F. Et J.-m. Sa",
    "wof:placetype":"venue"
},
  "geometry": {"coordinates":[6.914563,47.183838],"type":"Point"}
}