{
  "type": "Feature",
  "properties": {
    "iso:country":"CH",
    "sg:address":"Hauptstrasse 82",
    "sg:city":"Rorschach",
    "sg:orig_category":"Arztpraxen",
    "sg:phone":"+41 71 845 52 52",
    "sg:postcode":"9400",
    "sg:province":"St. Gallen",
    "wof:name":"Dr.med. Yvonne Breitenmoser Spezial\u00e4rztin Fmh",
    "wof:placetype":"venue"
},
  "geometry": {"coordinates":[9.490789,47.479137],"type":"Point"}
}