{
  "type": "Feature",
  "properties": {
    "iso:country":"CH",
    "sg:address":"Glattalstrasse 138",
    "sg:city":"Z\u00fcrich",
    "sg:orig_category":"Autogaragen",
    "sg:phone":"+41 13010890",
    "sg:postcode":"8052",
    "sg:province":"Z\u00fcrich",
    "wof:name":"Walter Zimmermann Garage",
    "wof:placetype":"venue"
},
  "geometry": {"coordinates":[8.544221,47.430988],"type":"Point"}
}