{
  "type": "Feature",
  "properties": {
    "addr:full":"Glattalstrasse 138 Z\u00fcrich Z\u00fcrich 8052",
    "addr:housenumber":"138",
    "addr:postcode":"8052",
    "addr:street":"Glattalstrasse",
    "iso:country":"CH",
    "sg:address":"Glattalstrasse 138",
    "sg:city":"Z\u00fcrich",
    "sg:orig_category":"Autogaragen",
    "sg:phone":"+41 13010890",
    "sg:postcode":"8052",
    "sg:province":"Z\u00fcrich",
    "wof:name":"Walter Zimmermann Garage",
    "wof:placetype":"venue"
},
  "geometry": {"coordinates":[8.544221,47.430988],"type":"Point"}
}