{
  "type": "Feature",
  "properties": {
    "iso:country":"CH",
    "sg:address":"M\u00fchlegutstrasse 10",
    "sg:city":"Steinach",
    "sg:orig_category":"Vereine Musik/Blasmusik",
    "sg:phone":"+41 71 446 84 74",
    "sg:postcode":"9323",
    "sg:province":"St. Gallen",
    "wof:name":"Milit\u00e4rveteranen",
    "wof:placetype":"venue"
},
  "geometry": {"coordinates":[9.4406909943,47.5015335083],"type":"Point"}
}