{
  "type": "Feature",
  "properties": {
    "iso:country":"CH",
    "sg:address":"Birkenstrasse 9/102",
    "sg:city":"Luzern",
    "sg:orig_category":"Non-Classified Establishments",
    "sg:postcode":"6003",
    "sg:province":"Luzern",
    "wof:name":"R\u00fcegg Montageblitz",
    "wof:placetype":"venue"
},
  "geometry": {"coordinates":[8.3043384552,47.0421104431],"type":"Point"}
}