{
  "type": "Feature",
  "properties": {
    "iso:country":"CH",
    "sg:address":"7075",
    "sg:city":"Churwalden",
    "sg:classifiers":[
        {
            "category":"Travel",
            "subcategory":"Hotels & Motels",
            "type":"Entertainment"
        }
    ],
    "sg:phone":"+41 27 957 12 52",
    "sg:postcode":"7075",
    "sg:province":"Graubunden",
    "sg:tags":[
        "hotels",
        "mit",
        "restaurant"
    ],
    "wof:name":"Hotel Condor, Bumann Cornelia",
    "wof:placetype":"venue"
},
  "geometry": {"coordinates":[7.933672905,46.1117172241],"type":"Point"}
}