{
  "type": "Feature",
  "properties": {
    "iso:country":"CH",
    "sg:address":"Bodenackerstrasse 14d",
    "sg:city":"Liestal",
    "sg:orig_category":"Unternehmensberatung",
    "sg:postcode":"4410",
    "sg:province":"Basel-Landschaft",
    "wof:name":"Jaggi Consulting Gmbh",
    "wof:placetype":"venue"
},
  "geometry": {"coordinates":[7.7262129784,47.4832458496],"type":"Point"}
}