{
  "type": "Feature",
  "properties": {
    "addr:full":"Dorfstr. 81 Schuepfheim Luzern 6170",
    "addr:housenumber":"81",
    "addr:postcode":"6170",
    "addr:street":"Dorfstr.",
    "iso:country":"CH",
    "sg:address":"Dorfstr. 81",
    "sg:city":"Schuepfheim",
    "sg:classifiers":[
        {
            "category":"Banks & Credit Unions",
            "subcategory":"Bank",
            "type":"Services"
        }
    ],
    "sg:postcode":"6170",
    "sg:province":"Luzern",
    "wof:name":"Volksbank Neuenkirch-reiden",
    "wof:placetype":"venue"
},
  "geometry": {"coordinates":[8.19442,47.11565],"type":"Point"}
}