{
  "type": "Feature",
  "properties": {
    "iso:country":"CH",
    "sg:address":"Fr\u00e4schelsgasse 258 3210 Kerzers. Postfach",
    "sg:city":"Kerzers",
    "sg:orig_category":"Herstellung von Elektromotoren, Generatoren U Transformatoren",
    "sg:phone":"+41 31 750 50 50",
    "sg:postcode":"3210",
    "sg:province":"Fribourg",
    "wof:name":"Gfeller Elektro Ag",
    "wof:placetype":"venue"
},
  "geometry": {"coordinates":[7.1992001534,46.9815483093],"type":"Point"}
}