{
  "type": "Feature",
  "properties": {
    "iso:country":"CH",
    "sg:address":"Rossbergstrasse 9",
    "sg:city":"Goldau",
    "sg:orig_category":"Sanit\u00e4r U Heizungsinstallation Sanit\u00e4rinstallation",
    "sg:phone":"+41 41 855 25 70",
    "sg:postcode":"6410",
    "sg:province":"Schwyz",
    "wof:name":"Werner Kenel Heizungs-& Sanit\u00e4rarbeiten",
    "wof:placetype":"venue"
},
  "geometry": {"coordinates":[8.5499162674,47.0515327454],"type":"Point"}
}