{
  "type": "Feature",
  "properties": {
    "iso:country":"CH",
    "sg:address":"Neukirch An Der Thur 8578 Neukirch. Postfach",
    "sg:city":"Neukirch",
    "sg:orig_category":"Verwertung von Milch",
    "sg:postcode":"8578",
    "wof:name":"K\u00e4sereigenossenschaft Neukirch An Der Thur",
    "wof:placetype":"venue"
},
  "geometry": {"coordinates":[9.7031955719,47.6581077576],"type":"Point"}
}