{
  "type": "Feature",
  "properties": {
    "addr:full":"Auf Der Mauer 4 Z\u00fcrich Z\u00fcrich 8001",
    "addr:housenumber":"4",
    "addr:postcode":"8001",
    "addr:street":"Auf Der Mauer",
    "iso:country":"CH",
    "sg:address":"Auf Der Mauer 4",
    "sg:city":"Z\u00fcrich",
    "sg:orig_category":"Buchverlag Detailhandel mit B\u00fcchern, Zeitungen, Schreib U Papeteriewaren",
    "sg:phone":"+41 17464280",
    "sg:postcode":"8001",
    "sg:province":"Z\u00fcrich",
    "wof:name":"Baumgartner B\u00fccher Ag",
    "wof:placetype":"venue"
},
  "geometry": {"coordinates":[8.450316,47.277439],"type":"Point"}
}