{
  "type": "Feature",
  "properties": {
    "iso:country":"CH",
    "sg:address":"Chemin Cr\u00eat-du-ch\u00eane",
    "sg:city":"Neuch\u00e2tel",
    "sg:orig_category":"Primarschulen",
    "sg:phone":"+41 32 717 78 80",
    "sg:postcode":"2000",
    "sg:province":"Neuch\u00e2tel",
    "wof:name":"Ecole Primaire Coll\u00e8ge De La Coudre",
    "wof:placetype":"venue"
},
  "geometry": {"coordinates":[6.9598321915,47.0074157715],"type":"Point"}
}