{
  "type": "Feature",
  "properties": {
    "iso:country":"CH",
    "sg:address":"Chemin Des Cond\u00e9mines",
    "sg:city":"Sierre",
    "sg:orig_category":"S\u00e4ge, Hobel U Holzimpr\u00e4gnierwerke",
    "sg:postcode":"3960",
    "sg:province":"Valais",
    "wof:name":"Devanth\u00e9ry Nicolas",
    "wof:placetype":"venue"
},
  "geometry": {"coordinates":[7.5285429955,46.2874565125],"type":"Point"}
}