{
  "type": "Feature",
  "properties": {
    "iso:country":"CH",
    "sg:address":"Klosterweg 7",
    "sg:city":"N\u00e4fels",
    "sg:orig_category":"Herstellung von Musikinstrumenten",
    "sg:phone":"+41 55 612 33 60",
    "sg:postcode":"8752",
    "sg:province":"Glarus",
    "wof:name":"Orgelplanungen M. Leipold",
    "wof:placetype":"venue"
},
  "geometry": {"coordinates":[9.0618801117,47.0980644226],"type":"Point"}
}