{
  "type": "Feature",
  "properties": {
    "iso:country":"CH",
    "sg:address":"Hauptstrasse 141",
    "sg:city":"Ursenbach",
    "sg:orig_category":"Herstellung von Maschinen f\u00fcr das Druckgewerbe Mechanische Werkst\u00e4tten",
    "sg:phone":"+41 62 965 34 34",
    "sg:postcode":"4937",
    "sg:province":"Bern",
    "wof:name":"Mdc D\u00e4twyler Max Ag Ursenbach",
    "wof:placetype":"venue"
},
  "geometry": {"coordinates":[7.7768192291,47.1423721313],"type":"Point"}
}