{
  "type": "Feature",
  "properties": {
    "iso:country":"CH",
    "sg:address":"Veronikaweg 8",
    "sg:city":"Aarau",
    "sg:orig_category":"Bauingenieurb\u00fcros Hochbau Bauingenieurb\u00fcros allgemein",
    "sg:phone":"+41 62 824 33 85",
    "sg:postcode":"5000",
    "sg:province":"Aargau",
    "wof:name":"Ren\u00e9 Wernli Ingenieurb\u00fcro",
    "wof:placetype":"venue"
},
  "geometry": {"coordinates":[8.041854,47.383698],"type":"Point"}
}