{
  "type": "Feature",
  "properties": {
    "iso:country":"CH",
    "sg:address":"Poststrasse 5",
    "sg:city":"Gelterkinden",
    "sg:orig_category":"RESTAURANTS: TEA-ROOMS",
    "sg:postcode":"4460",
    "sg:province":"Basel-Landschaft",
    "wof:name":"Kurt Muhmenthaler",
    "wof:placetype":"venue"
},
  "geometry": {"coordinates":[7.853140831,47.4656105042],"type":"Point"}
}