{
  "type": "Feature",
  "properties": {
    "iso:country":"CH",
    "sg:address":"Kasinostrasse 32",
    "sg:city":"Aarau",
    "sg:orig_category":"Detailhandel mit Bekleidung Detailhandel mit Damenbekleidung",
    "sg:phone":"+41 62 822 42 65",
    "sg:postcode":"5000",
    "sg:province":"Aargau",
    "wof:name":"Modehaus & Boutique M\u00fcller Ag",
    "wof:placetype":"venue"
},
  "geometry": {"coordinates":[8.047051,47.391693],"type":"Point"}
}