{
  "type": "Feature",
  "properties": {
    "iso:country":"CH",
    "sg:address":"Route Du Rawyl 38",
    "sg:city":"Sierre",
    "sg:classifiers":[
        {
            "category":"Wholesale",
            "subcategory":"Petroleum",
            "type":"Manufacturing & Wholesale Goods"
        }
    ],
    "sg:phone":"+41 27 455 12 63",
    "sg:postcode":"3960",
    "sg:province":"Valais",
    "sg:tags":[
        "swiss",
        "wine"
    ],
    "wof:name":"Riondaz S.a.",
    "wof:placetype":"venue"
},
  "geometry": {"coordinates":[7.5360031128,46.2986984253],"type":"Point"}
}