{
  "type": "Feature",
  "properties": {
    "iso:country":"CH",
    "sg:address":"Pelikanweg 6 4054 Basel. Postfach",
    "sg:city":"Basel",
    "sg:orig_category":"Wheelchair Accessories",
    "sg:phone":"+41 41 850 40 50",
    "sg:postcode":"4051",
    "sg:province":"Basel-Stadt",
    "wof:name":"Atec Ingenieurb\u00fcro Ag",
    "wof:placetype":"venue"
},
  "geometry": {"coordinates":[8.437951088,47.0710525513],"type":"Point"}
}