{
  "type": "Feature",
  "properties": {
    "iso:country":"CH",
    "sg:address":"Schulhaus Kirchb\u00fchl Ost",
    "sg:city":"St\u00e4fa",
    "sg:orig_category":"K\u00fcnstlerische Schulen",
    "sg:phone":"+41 19262422",
    "sg:postcode":"8712",
    "sg:province":"Z\u00fcrich",
    "wof:name":"Jugendmusikschule St\u00e4fa Sekretariat",
    "wof:placetype":"venue"
},
  "geometry": {"coordinates":[8.7229890823,47.2414932251],"type":"Point"}
}