{
  "type": "Feature",
  "properties": {
    "iso:country":"CH",
    "sg:address":"Schifflaube 46",
    "sg:city":"Bern",
    "sg:orig_category":"Unclassifiable Establishments",
    "sg:postcode":"3011",
    "sg:province":"Bern",
    "wof:name":"Wohnbaugenossenschaft Modell Schifflaube",
    "wof:placetype":"venue"
},
  "geometry": {"coordinates":[7.453567028,46.9463272095],"type":"Point"}
}