{
  "type": "Feature",
  "properties": {
    "iso:country":"CH",
    "sg:address":"Werkhofstrasse 9 4500 Solothurn. Postfach",
    "sg:city":"Solothurn",
    "sg:orig_category":"Werbung",
    "sg:phone":"+41 32 624 47 00",
    "sg:postcode":"4500",
    "sg:province":"Solothurn",
    "wof:name":"Ibl Und Partner Ag Werbeagentur",
    "wof:placetype":"venue"
},
  "geometry": {"coordinates":[7.5343852043,47.209728241],"type":"Point"}
}