{
  "type": "Feature",
  "properties": {
    "iso:country":"CH",
    "sg:address":"Im D\u00f6rfli 69",
    "sg:city":"Dietikon",
    "sg:orig_category":"Fahrschulen, Flugschulen",
    "sg:phone":"+41 79 407 48 64",
    "sg:postcode":"8953",
    "sg:province":"Z\u00fcrich",
    "wof:name":"Markus Alder Autofahrschule",
    "wof:placetype":"venue"
},
  "geometry": {"coordinates":[8.4059762955,47.400062561],"type":"Point"}
}