{
  "type": "Feature",
  "properties": {
    "iso:country":"CH",
    "sg:address":"St.-antons-gasse 4a",
    "sg:city":"Zug",
    "sg:orig_category":"Unternehmensberatung",
    "sg:postcode":"6300",
    "sg:province":"Zug",
    "wof:name":"Agite!, Gesellschaft F\u00fcr Beratung Und Training Mbh",
    "wof:placetype":"venue"
},
  "geometry": {"coordinates":[8.7577753067,47.2063064575],"type":"Point"}
}