{
  "type": "Feature",
  "properties": {
    "iso:country":"CH",
    "sg:address":"Rte De S\u00e9prais. 24l Case Postale 23",
    "sg:city":"Bo\u00e9court",
    "sg:classifiers":[
        {
            "category":"Wholesale",
            "subcategory":"Machinery & Supplies",
            "type":"Manufacturing & Wholesale Goods"
        }
    ],
    "sg:phone":"+41 32 426 74 56",
    "sg:postcode":"2856",
    "sg:province":"Jura",
    "sg:tags":[
        "equipment",
        "equipement",
        "precision",
        "timekeeping"
    ],
    "wof:name":"Erma Bo\u00c9court Sa",
    "wof:placetype":"venue"
},
  "geometry": {"coordinates":[7.227039814,47.3660697937],"type":"Point"}
}