{
  "type": "Feature",
  "properties": {
    "iso:country":"CH",
    "sg:address":"Valegia Via 19 6926 Montagnola. Postfach",
    "sg:city":"Montagnola",
    "sg:orig_category":"Vermietung U Verpachtung von eigenen Immobilien",
    "sg:postcode":"6926",
    "sg:province":"Ticino",
    "wof:name":"Orbisana Sa Immobili Ecc",
    "wof:placetype":"venue"
},
  "geometry": {"coordinates":[8.9150333405,45.9833717346],"type":"Point"}
}