{
  "type": "Feature",
  "properties": {
    "iso:country":"CH",
    "sg:address":"Steigstrasse 4",
    "sg:city":"Winterthur",
    "sg:orig_category":"Autospenglereien",
    "sg:phone":"+41 52 202 91 20",
    "sg:postcode":"8406",
    "sg:province":"Z\u00fcrich",
    "wof:name":"Hans Heider Karosserie-werkst\u00e4tte",
    "wof:placetype":"venue"
},
  "geometry": {"coordinates":[8.703869,47.479656],"type":"Point"}
}