{
  "type": "Feature",
  "properties": {
    "iso:country":"CH",
    "sg:address":"Weiherweidstrasse 5",
    "sg:city":"St.gallen",
    "sg:orig_category":"Vereine Gemeinn\u00fctzige",
    "sg:phone":"+41 71 223 13 74",
    "sg:postcode":"9000",
    "sg:province":"St. Gallen",
    "wof:name":"Oekum.arbeitskr.friedenswoche",
    "wof:placetype":"venue"
},
  "geometry": {"coordinates":[9.3798666,47.4177131653],"type":"Point"}
}