{
  "type": "Feature",
  "properties": {
    "iso:country":"CH",
    "sg:address":"Maison Rouge 30",
    "sg:city":"Sierre",
    "sg:orig_category":"Stukkateurgewerbe, Gipserei U Verputzerei",
    "sg:phone":"+41 27 455 81 33",
    "sg:postcode":"3960",
    "sg:province":"Valais",
    "wof:name":"Lettieri Matteo",
    "wof:placetype":"venue"
},
  "geometry": {"coordinates":[7.5227527618,46.2854042053],"type":"Point"}
}