{
  "type": "Feature",
  "properties": {
    "iso:country":"CH",
    "sg:address":"De-grenus Rue 14 1201 Gen\u00e8ve. Postfach",
    "sg:city":"Gen\u00e8ve",
    "sg:orig_category":"RESTAURANTS: TEA-ROOMS",
    "sg:postcode":"1201",
    "sg:province":"Gen\u00e8ve",
    "wof:name":"Kollegger Erwin.",
    "wof:placetype":"venue"
},
  "geometry": {"coordinates":[9.5531616211,47.3865661621],"type":"Point"}
}