{
  "type": "Feature",
  "properties": {
    "iso:country":"CH",
    "sg:address":"8164",
    "sg:city":"Bachs",
    "sg:orig_category":"Haltung von Rindern",
    "sg:postcode":"8164",
    "sg:province":"Z\u00fcrich",
    "wof:name":"Viehzuchtgenossenschaft Bad Ragaz",
    "wof:placetype":"venue"
},
  "geometry": {"coordinates":[9.5019950867,47.0127792358],"type":"Point"}
}