{
  "type": "Feature",
  "properties": {
    "iso:country":"CH",
    "sg:address":"Avenue Du Petit-lancy 10",
    "sg:city":"Petit-lancy",
    "sg:orig_category":"Institutionen f\u00fcr Behinderte",
    "sg:phone":"+41 22 792 04 92",
    "sg:postcode":"1213",
    "sg:province":"Gen\u00e8ve",
    "wof:name":"R\u00e9sidence Du Petit-lancy",
    "wof:placetype":"venue"
},
  "geometry": {"coordinates":[6.1176629066,46.1910743713],"type":"Point"}
}