{
  "type": "Feature",
  "properties": {
    "iso:country":"CH",
    "sg:address":"Ettiswilerstrasse 1",
    "sg:city":"Entlebuch",
    "sg:orig_category":"Fahrschulen, Flugschulen",
    "sg:phone":"+41 79 414 77 44",
    "sg:postcode":"6162",
    "sg:province":"Luzern",
    "wof:name":"Anton Schaller Lastwagenfahrschule",
    "wof:placetype":"venue"
},
  "geometry": {"coordinates":[8.0649986267,46.9928016663],"type":"Point"}
}