{
  "type": "Feature",
  "properties": {
    "iso:country":"CH",
    "sg:address":"Bahnhofstrasse 19",
    "sg:city":"Arbon",
    "sg:orig_category":"Vereine Orchester",
    "sg:phone":"+41 71 446 38 86",
    "sg:postcode":"9320",
    "sg:province":"Thurgau",
    "wof:name":"Stadt-orchester",
    "wof:placetype":"venue"
},
  "geometry": {"coordinates":[9.4352807999,47.5138473511],"type":"Point"}
}