{
  "type": "Feature",
  "properties": {
    "iso:country":"CH",
    "sg:address":"7013 Domat/ems. Postfach 157",
    "sg:city":"Domat/ems",
    "sg:orig_category":"Sportvereine Ballsport Fussball",
    "sg:postcode":"7013",
    "sg:province":"Graubunden",
    "wof:name":"Milan-club",
    "wof:placetype":"venue"
},
  "geometry": {"coordinates":[9.450969696,46.8354187012],"type":"Point"}
}