{
  "type": "Feature",
  "properties": {
    "addr:full":"Grendelstrasse 6 Luzern Luzern 6004",
    "addr:housenumber":"6",
    "addr:postcode":"6004",
    "addr:street":"Grendelstrasse",
    "iso:country":"CH",
    "sg:address":"Grendelstrasse 6",
    "sg:city":"Luzern",
    "sg:orig_category":"Arztpraxen",
    "sg:phone":"+41 31 311 69 08",
    "sg:postcode":"6004",
    "sg:province":"Luzern",
    "wof:name":"Dr.med.arnold Durrer Spezialarzt Fmh",
    "wof:placetype":"venue"
},
  "geometry": {"coordinates":[7.454744,46.946674],"type":"Point"}
}