{
  "type": "Feature",
  "properties": {
    "iso:country":"CH",
    "sg:address":"Gerbestrasse 1",
    "sg:city":"Uster",
    "sg:orig_category":"Detailhandel mit Teppichen Detailhandel mit Textilien",
    "sg:phone":"+41 19414371",
    "sg:postcode":"8610",
    "sg:province":"Z\u00fcrich",
    "wof:name":"Helen Michel Teppich-& Handwerkladen",
    "wof:placetype":"venue"
},
  "geometry": {"coordinates":[8.7169675827,47.3468818665],"type":"Point"}
}