{
  "type": "Feature",
  "properties": {
    "iso:country":"CH",
    "sg:address":"Feldbergstrasse 100",
    "sg:city":"Basel",
    "sg:orig_category":"Non-Classified Establishments",
    "sg:postcode":"4057",
    "sg:province":"Basel-Stadt",
    "wof:name":"Kobivasan & Co.",
    "wof:placetype":"venue"
},
  "geometry": {"coordinates":[7.5945448875,47.5667648315],"type":"Point"}
}