{
  "type": "Feature",
  "properties": {
    "iso:country":"CH",
    "sg:address":"Grabenwiese 82b",
    "sg:city":"Weisslingen",
    "sg:orig_category":"Unternehmensberatung",
    "sg:phone":"+41 52 384 17 72",
    "sg:postcode":"8484",
    "sg:province":"Z\u00fcrich",
    "wof:name":"Berger Control Ag",
    "wof:placetype":"venue"
},
  "geometry": {"coordinates":[8.7711286545,47.4273834229],"type":"Point"}
}