{
  "type": "Feature",
  "properties": {
    "iso:country":"CH",
    "sg:address":"Burggasse 10",
    "sg:city":"Muttenz",
    "sg:orig_category":"Herstellung von Metallkonstruktionen",
    "sg:phone":"+41 55 240 88 76",
    "sg:postcode":"4132",
    "sg:province":"Basel-Landschaft",
    "wof:name":"Jamont Gmbh Inh.j.kilchenmann",
    "wof:placetype":"venue"
},
  "geometry": {"coordinates":[8.8432855606,47.2767753601],"type":"Point"}
}