{
  "type": "Feature",
  "properties": {
    "iso:country":"CH",
    "sg:address":"Zubastr. 12",
    "sg:city":"Neuhausen",
    "sg:orig_category":"Stukkateurgewerbe, Gipserei U Verputzerei",
    "sg:phone":"+41 52 672 55 84",
    "sg:postcode":"8212",
    "sg:province":"Schaffhausen",
    "wof:name":"Weltin Ren\u00e9",
    "wof:placetype":"venue"
},
  "geometry": {"coordinates":[8.6181087494,47.686668396],"type":"Point"}
}