{
  "type": "Feature",
  "properties": {
    "iso:country":"CH",
    "sg:address":"Hauptstrasse 34 6283 Baldegg. Postfach",
    "sg:city":"Baldegg",
    "sg:orig_category":"Fachdetailhandel in Verkaufsr\u00e4umen",
    "sg:postcode":"6283",
    "sg:province":"Luzern",
    "wof:name":"Abt Susanne Blumenhandel",
    "wof:placetype":"venue"
},
  "geometry": {"coordinates":[8.2805118561,47.1878967285],"type":"Point"}
}