{
  "type": "Feature",
  "properties": {
    "iso:country":"CH",
    "sg:address":"Ulmenweg 24a",
    "sg:city":"Biberist",
    "sg:orig_category":"Arztpraxen",
    "sg:phone":"+41 32 675 68 25",
    "sg:postcode":"4562",
    "sg:province":"Solothurn",
    "wof:name":"Dr.med.peter Oehen Spezialarzt Fmh",
    "wof:placetype":"venue"
},
  "geometry": {"coordinates":[7.55354,47.17461],"type":"Point"}
}