{
  "type": "Feature",
  "properties": {
    "iso:country":"CH",
    "sg:address":"Chemin Du Gors 1",
    "sg:city":"Sugiez",
    "sg:orig_category":"Binnenschiffahrt",
    "sg:postcode":"1786",
    "sg:province":"Fribourg",
    "wof:name":"Schifffahrtsgesellschaft Drei Seen Gmbh",
    "wof:placetype":"venue"
},
  "geometry": {"coordinates":[7.107928,46.957409],"type":"Point"}
}