{
  "type": "Feature",
  "properties": {
    "iso:country":"CH",
    "sg:address":"Haldenstrasse 26b 8306 Br\u00fcttisellen. Postfach",
    "sg:city":"Br\u00fcttisellen",
    "sg:orig_category":"Grosshandel mit sonstigen Maschinen U Ausr\u00fcstungen f\u00fcr Industrie, Handel U Schiffahrt",
    "sg:phone":"+41 31 859 36 05",
    "sg:postcode":"8306",
    "sg:province":"Z\u00fcrich",
    "wof:name":"Hans-peter Schnegg Handel Mit Industrieg\u00fctern",
    "wof:placetype":"venue"
},
  "geometry": {"coordinates":[7.5241189003,47.0206184387],"type":"Point"}
}