{
  "type": "Feature",
  "properties": {
    "iso:country":"CH",
    "sg:address":"Cholrain",
    "sg:city":"Menzingen",
    "sg:orig_category":"Non-Classified Establishments",
    "sg:postcode":"6313",
    "sg:province":"Zug",
    "wof:name":"Mediaco Gmbh",
    "wof:placetype":"venue"
},
  "geometry": {"coordinates":[8.5669622421,47.1571960449],"type":"Point"}
}