{
  "type": "Feature",
  "properties": {
    "iso:country":"CH",
    "sg:address":"Baselstrasse 23",
    "sg:city":"Riehen",
    "sg:orig_category":"Herstellung von Kakao, Schokoladeerzeugnissen U Zuckerwaren",
    "sg:postcode":"4125",
    "sg:province":"Basel-Stadt",
    "wof:name":"Patrizia's Schoggi-paradies, P. Dammann",
    "wof:placetype":"venue"
},
  "geometry": {"coordinates":[7.6485748291,47.5837593079],"type":"Point"}
}