{
  "type": "Feature",
  "properties": {
    "iso:country":"CH",
    "sg:address":"9113",
    "sg:city":"Degersheim",
    "sg:orig_category":"Vereine Abstinenten",
    "sg:phone":"+41 71 371 15 48",
    "sg:postcode":"9113",
    "sg:province":"St. Gallen",
    "wof:name":"Blaues Kreuz",
    "wof:placetype":"venue"
},
  "geometry": {"coordinates":[9.200012207,47.3739433289],"type":"Point"}
}