{
  "type": "Feature",
  "properties": {
    "iso:country":"CH",
    "sg:address":"Via Alle Scuole",
    "sg:city":"Taverne",
    "sg:orig_category":"Rolladen- and Storenmontage",
    "sg:phone":"+41 91 945 14 89",
    "sg:postcode":"6807",
    "sg:province":"Ticino",
    "wof:name":"Salvatore Grande Fornitura E Posa Rolladen",
    "wof:placetype":"venue"
},
  "geometry": {"coordinates":[8.9333286285,46.0671730042],"type":"Point"}
}