{
  "type": "Feature",
  "properties": {
    "iso:country":"CH",
    "sg:address":"Bergstrasse 56",
    "sg:city":"Embrach",
    "sg:orig_category":"Bauingenieurb\u00fcros allgemein",
    "sg:phone":"+41 18650913",
    "sg:postcode":"8424",
    "sg:province":"Z\u00fcrich",
    "wof:name":"H.h. Sallenbach & H.p. Widmer Ingenieurb\u00fcro",
    "wof:placetype":"venue"
},
  "geometry": {"coordinates":[8.5993,47.50156],"type":"Point"}
}