{
  "type": "Feature",
  "properties": {
    "iso:country":"CH",
    "sg:address":"Luegislandstrasse 45c",
    "sg:city":"Z\u00fcrich",
    "sg:orig_category":"Sonstiger Grosshandel",
    "sg:phone":"+41 13213791",
    "sg:postcode":"8051",
    "sg:province":"Z\u00fcrich",
    "wof:name":"Fu-long, Stefaniak-kang Su-wang Import, Export, Warenhandel; Filmproduktion Usw.",
    "wof:placetype":"venue"
},
  "geometry": {"coordinates":[8.5662031174,47.406036377],"type":"Point"}
}