{
  "type": "Feature",
  "properties": {
    "iso:country":"CH",
    "sg:address":"Melchnaustrasse 57d 4900 Langenthal. Postfach",
    "sg:city":"Langenthal",
    "sg:orig_category":"Verlagsgewerbe",
    "sg:phone":"+41 22 321 13 21",
    "sg:postcode":"4900",
    "sg:province":"Bern",
    "wof:name":"Plaidoyer Revue Juridique & Politique",
    "wof:placetype":"venue"
},
  "geometry": {"coordinates":[6.1419730186,46.1845817566],"type":"Point"}
}