{
  "type": "Feature",
  "properties": {
    "iso:country":"CH",
    "sg:address":"Rue Du Bois Carrien 2",
    "sg:city":"Onex",
    "sg:classifiers":[
        {
            "category":"Arena",
            "subcategory":"Sports Club",
            "type":"Entertainment"
        }
    ],
    "sg:phone":"+41 22 349 94 07",
    "sg:postcode":"1213",
    "sg:province":"Gen\u00e8ve",
    "sg:tags":[
        "karate",
        "judo",
        "sportvereine"
    ],
    "wof:name":"Karate-club Sankukai Onex",
    "wof:placetype":"venue"
},
  "geometry": {"coordinates":[6.1011309624,46.1911354065],"type":"Point"}
}