{
  "type": "Feature",
  "properties": {
    "addr:full":"Buchholzstrasse 13 Stettlen Bern 3066",
    "addr:housenumber":"13",
    "addr:postcode":"3066",
    "addr:street":"Buchholzstrasse;Bern",
    "iso:country":"CH",
    "sg:address":"Buchholzstrasse 13",
    "sg:city":"Stettlen",
    "sg:orig_category":"Datenverarbeitungsdienste",
    "sg:phone":"+41 31 332 74 44",
    "sg:postcode":"3066",
    "sg:province":"Bern",
    "wof:name":"Exprog-h\u00fcgli Edv; Organisation, Analyse, Programmierung U. Ausbildung.",
    "wof:placetype":"venue"
},
  "geometry": {"coordinates":[8.44777,47.436958],"type":"Point"}
}