{
  "type": "Feature",
  "properties": {
    "iso:country":"CH",
    "sg:address":"Bahnhofplatz 70-72",
    "sg:city":"Frauenfeld",
    "sg:orig_category":"Detailhandel mit Schuhen Detailhandel mit Sportartikeln",
    "sg:phone":"+41 33 676 22 05",
    "sg:postcode":"8500",
    "sg:province":"Thurgau",
    "wof:name":"Othmar Bircher Schuhe & Sport",
    "wof:placetype":"venue"
},
  "geometry": {"coordinates":[7.6927351952,46.6255302429],"type":"Point"}
}