{
  "type": "Feature",
  "properties": {
    "iso:country":"CH",
    "sg:address":"Luisenstrasse 46 3013 Bern. Postfach 268",
    "sg:city":"Bern",
    "sg:orig_category":"Sonstige mit der Informatik verbundene T\u00e4tigkeiten",
    "sg:phone":"+41 31 332 00 05",
    "sg:postcode":"3013",
    "sg:province":"Bern",
    "wof:name":"K-link Gmbh",
    "wof:placetype":"venue"
},
  "geometry": {"coordinates":[7.4530391693,46.9404335022],"type":"Point"}
}