{
  "type": "Feature",
  "properties": {
    "addr:full":"Eth Zentrum Z\u00fcrich Z\u00fcrich 8092",
    "addr:postcode":"8092",
    "addr:street":"Zuerich",
    "iso:country":"CH",
    "sg:address":"Eth Zentrum",
    "sg:city":"Z\u00fcrich",
    "sg:orig_category":"Dienstleistungen, Telekommunikation",
    "sg:postcode":"8092",
    "sg:province":"Z\u00fcrich",
    "wof:name":"Umweltnaturwissenschaften Eth Z\u00fcrich",
    "wof:placetype":"venue"
},
  "geometry": {"coordinates":[8.53801,47.369091],"type":"Point"}
}