{
  "type": "Feature",
  "properties": {
    "iso:country":"CH",
    "sg:address":"Chemin Des Briffods 11",
    "sg:city":"Choulex",
    "sg:orig_category":"Vorschulen, Kinderg\u00e4rten",
    "sg:phone":"+41 22 750 21 12",
    "sg:postcode":"1244",
    "sg:province":"Gen\u00e8ve",
    "wof:name":"Ecole Enfantine Choulex",
    "wof:placetype":"venue"
},
  "geometry": {"coordinates":[6.2235379219,46.2256622314],"type":"Point"}
}