{
  "type": "Feature",
  "properties": {
    "iso:country":"CH",
    "sg:address":"Schulhausstrasse 21",
    "sg:city":"D\u00fcbendorf",
    "sg:orig_category":"Herstellung von Elektrizit\u00e4tsverteilungs U schalteinrichtungen",
    "sg:phone":"+41 18513640",
    "sg:postcode":"8600",
    "sg:province":"Z\u00fcrich",
    "wof:name":"Berli Schaltanlagen Ag",
    "wof:placetype":"venue"
},
  "geometry": {"coordinates":[8.5090360641,47.4707107544],"type":"Point"}
}