{
  "type": "Feature",
  "properties": {
    "iso:country":"CH",
    "sg:address":"Laupen 8637 Laupen Zh. Postfach",
    "sg:city":"Urnerboden",
    "sg:orig_category":"Detailhandel mit Brot, Back U S\u00fcsswaren",
    "sg:postcode":"8751",
    "sg:province":"Uri",
    "wof:name":"Roli's Und Fr\u00e4nzi's B\u00e4ckerst\u00fcbli, Inhaber R\u00fcegg Roland",
    "wof:placetype":"venue"
},
  "geometry": {"coordinates":[8.93136,47.267639],"type":"Point"}
}