{
  "type": "Feature",
  "properties": {
    "addr:full":"6547 Augio Graubunden 6547",
    "addr:housenumber":"6547;6547",
    "addr:street":"Augio Graubunden",
    "iso:country":"CH",
    "sg:address":"6547",
    "sg:city":"Augio",
    "sg:orig_category":"Bauschreinerei",
    "sg:phone":"+41 91 828 11 41",
    "sg:postcode":"6547",
    "sg:province":"Graubunden",
    "wof:name":"Graziano Papa Falegnameria",
    "wof:placetype":"venue"
},
  "geometry": {"coordinates":[9.12699,46.364719],"type":"Point"}
}