{
  "type": "Feature",
  "properties": {
    "iso:country":"CH",
    "sg:address":"Murgenthalerstrasse 46 4628 Wolfwil. Postfach",
    "sg:city":"Murgenthal",
    "sg:orig_category":"Herstellung von Kunststoff in Prim\u00e4rformen Herstellung von Kunststoffwaren",
    "sg:phone":"+41 19371433",
    "sg:postcode":"4853",
    "sg:province":"Aargau",
    "wof:name":"Hans Kn\u00f6pfel Glasfaserverst.kunststoffe",
    "wof:placetype":"venue"
},
  "geometry": {"coordinates":[8.8202762604,47.2919082642],"type":"Point"}
}