{
  "type": "Feature",
  "properties": {
    "iso:country":"CH",
    "sg:address":"Grendelstrasse 15",
    "sg:city":"Luzern",
    "sg:orig_category":"Arztpraxen",
    "sg:phone":"+41 41 410 30 35",
    "sg:postcode":"6004",
    "sg:province":"Luzern",
    "wof:name":"Dr.med.hans Schenk Spezialarzt Fmh",
    "wof:placetype":"venue"
},
  "geometry": {"coordinates":[8.307372,47.053284],"type":"Point"}
}