{
  "type": "Feature",
  "properties": {
    "iso:country":"CH",
    "sg:address":"Chemin Des Semilles",
    "sg:city":"Monthey",
    "sg:orig_category":"Fussboden, Fliesen U Plattenlegerei, Tapeziererei",
    "sg:postcode":"1870",
    "sg:province":"Valais",
    "wof:name":"Ceram Monthey Sa",
    "wof:placetype":"venue"
},
  "geometry": {"coordinates":[6.9534320831,46.2466773987],"type":"Point"}
}