{
  "type": "Feature",
  "properties": {
    "iso:country":"CH",
    "sg:address":"G\u00fcterstrasse 137",
    "sg:city":"Basel",
    "sg:classifiers":[
        {
            "category":"Professional",
            "subcategory":"Employment Agencies",
            "type":"Services"
        }
    ],
    "sg:phone":"+41 61 366 86 21",
    "sg:postcode":"4053",
    "sg:province":"Basel-Stadt",
    "sg:tags":[
        "personal",
        "u",
        "stellenvermittlung"
    ],
    "wof:name":"Transwork Ag",
    "wof:placetype":"venue"
},
  "geometry": {"coordinates":[7.5895819664,47.5448875427],"type":"Point"}
}