{
  "type": "Feature",
  "properties": {
    "iso:country":"CH",
    "sg:address":"Vordere Hauptgasse 18",
    "sg:city":"Zofingen",
    "sg:orig_category":"Unternehmensberatung",
    "sg:phone":"+41 62 752 52 52",
    "sg:postcode":"4800",
    "sg:province":"Aargau",
    "wof:name":"Via Mobile Strahm-waller Sabina",
    "wof:placetype":"venue"
},
  "geometry": {"coordinates":[7.9441027641,47.289981842],"type":"Point"}
}