{
  "type": "Feature",
  "properties": {
    "iso:country":"CH",
    "sg:address":"Unterdorf 6 3800 Unterseen. Postfach 105",
    "sg:city":"Unterseen",
    "sg:orig_category":"Architekturb\u00fcros",
    "sg:phone":"+41 33 822 61 57",
    "sg:postcode":"3800",
    "sg:province":"Bern",
    "wof:name":"Andreas Fuchs Architekturb\u00fcro",
    "wof:placetype":"venue"
},
  "geometry": {"coordinates":[7.84772,46.684811],"type":"Point"}
}