{
  "type": "Feature",
  "properties": {
    "iso:country":"CH",
    "sg:address":"Sch\u00e4nzlistrasse 10",
    "sg:city":"Solothurn",
    "sg:orig_category":"Softwareentwicklung U beratung Sonstige mit der Informatik verbundene T\u00e4tigkeiten",
    "sg:phone":"+41 32 621 11 01",
    "sg:postcode":"4500",
    "sg:province":"Solothurn",
    "wof:name":"Archenova Consulting Gmbh Informatik-beratung",
    "wof:placetype":"venue"
},
  "geometry": {"coordinates":[7.5415859222,47.2054176331],"type":"Point"}
}