{
  "type": "Feature",
  "properties": {
    "iso:country":"CH",
    "sg:address":"Route De Ch\u00eane 104 1224 Ch\u00eane-bougeries Case Postale 256",
    "sg:city":"Ch\u00eane-bougeries",
    "sg:orig_category":"Wohnheime",
    "sg:phone":"+41 22 349 13 04",
    "sg:postcode":"1224",
    "sg:province":"Gen\u00e8ve",
    "wof:name":"Home Hautefeuilles-ermitage Maison De Repos",
    "wof:placetype":"venue"
},
  "geometry": {"coordinates":[6.1812400818,46.1987915039],"type":"Point"}
}