{
  "type": "Feature",
  "properties": {
    "iso:country":"CH",
    "sg:address":"Nidertistrasse 16",
    "sg:city":"Beckenried",
    "sg:orig_category":"Instandhaltung U Reparatur von Automobilen",
    "sg:phone":"+41 41 620 24 59",
    "sg:postcode":"6375",
    "sg:province":"Nidwalden",
    "wof:name":"Garage Gander Adolf",
    "wof:placetype":"venue"
},
  "geometry": {"coordinates":[8.4602775574,46.9662513733],"type":"Point"}
}