{
  "type": "Feature",
  "properties": {
    "iso:country":"CH",
    "sg:address":"Stadtturmstrasse 10 5400 Baden. Postfach",
    "sg:city":"Baden",
    "sg:orig_category":"Vermietung U Verpachtung von eigenen Immobilien Vermittlung von Immobilien",
    "sg:phone":"+41 56 299 44 88",
    "sg:postcode":"5401",
    "sg:province":"Aargau",
    "wof:name":"Mib Ag Property & Facility Management",
    "wof:placetype":"venue"
},
  "geometry": {"coordinates":[8.3057947159,47.4759101868],"type":"Point"}
}