{
  "type": "Feature",
  "properties": {
    "iso:country":"CH",
    "sg:address":"Allmendstrasse 6 Postfach 66",
    "sg:city":"Villmergen",
    "sg:classifiers":[
        {
            "category":"Park",
            "type":"Public Place"
        }
    ],
    "sg:phone":"+41 56 622 94 30",
    "sg:postcode":"5612",
    "sg:province":"Aargau",
    "sg:tags":[
        "work",
        "construction",
        "sport"
    ],
    "wof:name":"Rosconi Ag",
    "wof:placetype":"venue"
},
  "geometry": {"coordinates":[-6.273169,53.359447],"type":"Point"}
}