{
  "type": "Feature",
  "properties": {
    "iso:country":"CH",
    "sg:address":"Eggstrasse 5 6232 Geuensee. Postfach",
    "sg:city":"Sursee",
    "sg:orig_category":"Verarbeitung von Tee U Kaffee",
    "sg:postcode":"6210",
    "sg:province":"Luzern",
    "wof:name":"Kdh Gottfried Muster",
    "wof:placetype":"venue"
},
  "geometry": {"coordinates":[8.4425601959,47.2891807556],"type":"Point"}
}