{
  "type": "Feature",
  "properties": {
    "iso:country":"CH",
    "sg:address":"Thurgauerstrasse 66",
    "sg:city":"Z\u00fcrich",
    "sg:orig_category":"Softwareentwicklung U beratung",
    "sg:phone":"+41 13086030",
    "sg:postcode":"8050",
    "sg:province":"Z\u00fcrich",
    "wof:name":"Mensch & Maschine Software Ag",
    "wof:placetype":"venue"
},
  "geometry": {"coordinates":[8.5538063049,47.4169044495],"type":"Point"}
}