{
  "type": "Feature",
  "properties": {
    "iso:country":"CH",
    "sg:address":"Chemin Frank-thomas 22bis",
    "sg:city":"Gen\u00e8ve",
    "sg:orig_category":"Grosshandel mit Sportartikeln Grosshandel mit sonstigen Gebrauchs U Verbrauchsg\u00fctern",
    "sg:postcode":"1208",
    "sg:province":"Gen\u00e8ve",
    "wof:name":"Xxl Trading Gmbh Distribution Articles De Sport",
    "wof:placetype":"venue"
},
  "geometry": {"coordinates":[6.1716279984,46.2033157349],"type":"Point"}
}