{
  "type": "Feature",
  "properties": {
    "addr:full":"Untere Rheingasse 9 4058 Basel. Postfach Basel Basel-Stadt 4005",
    "addr:housenumber":"9",
    "addr:postcode":"4058;4005",
    "addr:street":"Untere Rheingasse;Postfach",
    "iso:country":"CH",
    "sg:address":"Untere Rheingasse 9 4058 Basel. Postfach",
    "sg:city":"Basel",
    "sg:orig_category":"Bars Diskotheken, Dancings, Night Clubs",
    "sg:phone":"+41 61 681 12 70",
    "sg:postcode":"4005",
    "sg:province":"Basel-Stadt",
    "wof:name":"Bar/cabaret Tiffany/negresco",
    "wof:placetype":"venue"
},
  "geometry": {"coordinates":[7.591036,47.560879],"type":"Point"}
}