{
  "type": "Feature",
  "properties": {
    "iso:country":"CH",
    "sg:address":"Rheinstrasse 81 4133 Pratteln. Postfach",
    "sg:city":"Pratteln",
    "sg:orig_category":"Pensionskassen",
    "sg:phone":"+41 61 816 61 61",
    "sg:postcode":"4133",
    "sg:province":"Basel-Landschaft",
    "wof:name":"Vorsorgestiftung Der Promena Ag",
    "wof:placetype":"venue"
},
  "geometry": {"coordinates":[7.710791111,47.5346908569],"type":"Point"}
}