{
  "type": "Feature",
  "properties": {
    "iso:country":"CH",
    "sg:address":"Pradafenz",
    "sg:city":"Churwalden",
    "sg:orig_category":"Physiotherapie",
    "sg:phone":"+41 81 382 18 17",
    "sg:postcode":"7075",
    "sg:province":"Graubunden",
    "wof:name":"Frank Schieman Physiotherapie",
    "wof:placetype":"venue"
},
  "geometry": {"coordinates":[9.5434303284,46.7792053223],"type":"Point"}
}