{
  "type": "Feature",
  "properties": {
    "iso:country":"CH",
    "sg:address":"Via Bossi 9 6900 Lugano Caselle Postale Casella Postale 2678",
    "sg:city":"Lugano",
    "sg:orig_category":"Kauf U Verkauf von Immobilien auf eigene Rechnung Wirtschaftspr\u00fcfung, Steuerberatung U Treuhand",
    "sg:phone":"+41 91 923 15 72",
    "sg:postcode":"6900",
    "sg:province":"Ticino",
    "wof:name":"Iii - Intermediazioni Immobiliari Internazionali Sa",
    "wof:placetype":"venue"
},
  "geometry": {"coordinates":[8.9513053894,46.0029754639],"type":"Point"}
}