{
  "type": "Feature",
  "properties": {
    "iso:country":"CH",
    "sg:address":"Chemin Des Catons 5",
    "sg:city":"Perly",
    "sg:orig_category":"Blumen U Zierpflanzenbau Gem\u00fcsebau",
    "sg:phone":"+41 22 771 14 65",
    "sg:postcode":"1258",
    "sg:province":"Gen\u00e8ve",
    "wof:name":"Raoul Ethenoz Horticulture",
    "wof:placetype":"venue"
},
  "geometry": {"coordinates":[6.081262,46.156471],"type":"Point"}
}