{
  "type": "Feature",
  "properties": {
    "iso:country":"CH",
    "sg:address":"Voa Son Schon 14",
    "sg:city":"Vaz/obervaz",
    "sg:orig_category":"Architekturb\u00fcros",
    "sg:phone":"+41 81 384 44 43",
    "sg:postcode":"7082",
    "sg:province":"Graubunden",
    "wof:name":"Michael Hartmann Architekturb\u00fcro",
    "wof:placetype":"venue"
},
  "geometry": {"coordinates":[9.524327,46.69273],"type":"Point"}
}