{
  "type": "Feature",
  "properties": {
    "iso:country":"CH",
    "sg:address":"Kaselfeldstrasse 27",
    "sg:city":"Bellach",
    "sg:orig_category":"Organisationen des Gesundheitswesen",
    "sg:phone":"+41 32 618 07 60",
    "sg:postcode":"4512",
    "sg:province":"Solothurn",
    "wof:name":"Haus-& Krankenpflegeverein Herr Urs Walliser",
    "wof:placetype":"venue"
},
  "geometry": {"coordinates":[7.4958062172,47.2137756348],"type":"Point"}
}