{
  "type": "Feature",
  "properties": {
    "addr:full":"Robinsonweg 61 Bern Bern 3006",
    "addr:housenumber":"61",
    "addr:postcode":"3006",
    "addr:street":"Robinsonweg",
    "iso:country":"CH",
    "sg:address":"Robinsonweg 61",
    "sg:city":"Bern",
    "sg:classifiers":[
        {
            "category":"Manufacturing",
            "subcategory":"Glass & Minerals",
            "type":"Manufacturing & Wholesale Goods"
        }
    ],
    "sg:phone":"+41 31 941 30 49",
    "sg:postcode":"3006",
    "sg:province":"Bern",
    "sg:tags":[
        "decorative",
        "artistic"
    ],
    "wof:name":"Glas-design Reich Heidi",
    "wof:placetype":"venue"
},
  "geometry": {"coordinates":[7.482135,46.946877],"type":"Point"}
}