{
  "type": "Feature",
  "properties": {
    "iso:country":"CH",
    "sg:address":"Dorfstrasse 44",
    "sg:city":"Bettlach",
    "sg:orig_category":"Architektur U Ingenieurb\u00fcros Architekturb\u00fcros",
    "sg:phone":"+41 32 645 25 88",
    "sg:postcode":"2544",
    "sg:province":"Solothurn",
    "wof:name":"W. Heiri Architekturb\u00fcro Ag",
    "wof:placetype":"venue"
},
  "geometry": {"coordinates":[7.423855,47.203442],"type":"Point"}
}