{
  "type": "Feature",
  "properties": {
    "iso:country":"CH",
    "sg:address":"R\u00f6sslimatt 6",
    "sg:city":"Neuenkirch",
    "sg:orig_category":"Sonstige mit der Informatik verbundene T\u00e4tigkeiten",
    "sg:phone":"+41 41 467 00 43",
    "sg:postcode":"6206",
    "sg:province":"Luzern",
    "wof:name":"Creative Web Studio B\u00e4der",
    "wof:placetype":"venue"
},
  "geometry": {"coordinates":[8.196393013,47.1060905457],"type":"Point"}
}