{
  "type": "Feature",
  "properties": {
    "iso:country":"CH",
    "sg:address":"Solothurnerstrasse 59",
    "sg:city":"Basel",
    "sg:orig_category":"G\u00fcterbef\u00f6rderung im Strassenverkehr",
    "sg:postcode":"4053",
    "sg:province":"Basel-Stadt",
    "wof:name":"Abc Transport & Warentaxi Andreas Schneider",
    "wof:placetype":"venue"
},
  "geometry": {"coordinates":[7.5899238586,47.5433387756],"type":"Point"}
}