{
  "type": "Feature",
  "properties": {
    "iso:country":"CH",
    "sg:address":"Cousset-centre",
    "sg:city":"Cousset",
    "sg:orig_category":"Fachdetailhandel mit pharmazeutischen Produkten",
    "sg:phone":"+41 26 660 52 11",
    "sg:postcode":"1774",
    "sg:province":"Fribourg",
    "wof:name":"Droguerie Agostinelli Pascalino",
    "wof:placetype":"venue"
},
  "geometry": {"coordinates":[6.9768500328,46.8182106018],"type":"Point"}
}