{
  "type": "Feature",
  "properties": {
    "iso:country":"CH",
    "sg:address":"Im Sesselacker 60 4059 Basel. Postfach",
    "sg:city":"Basel",
    "sg:orig_category":"Handels-H\u00e4user U Gesellschaften",
    "sg:postcode":"4051",
    "sg:province":"Basel-Stadt",
    "wof:name":"Traderopa Ag Transithandels, Import Und Exportgesch\u00e4fte Mit Waren Usw",
    "wof:placetype":"venue"
},
  "geometry": {"coordinates":[7.6009922028,47.5356140137],"type":"Point"}
}