{
  "type": "Feature",
  "properties": {
    "iso:country":"CH",
    "sg:address":"Via Dunant 13",
    "sg:city":"Massagno",
    "sg:orig_category":"Unclassifiable Establishments",
    "sg:phone":"+41 91 966 31 55",
    "sg:postcode":"6900",
    "sg:province":"Ticino",
    "wof:name":"Tabra Sa",
    "wof:placetype":"venue"
},
  "geometry": {"coordinates":[8.9387674332,46.010055542],"type":"Point"}
}