{
  "type": "Feature",
  "properties": {
    "iso:country":"CH",
    "sg:address":"La Fayettaz",
    "sg:city":"Remaufens",
    "sg:orig_category":"Detailhandel mit Metallwaren, Anstrichmitteln, Glaswaren, Bau U Heimwerkerbedarf",
    "sg:postcode":"1617",
    "sg:province":"Fribourg",
    "wof:name":"Vmv Keller Et Jan",
    "wof:placetype":"venue"
},
  "geometry": {"coordinates":[6.8788499832,46.5283584595],"type":"Point"}
}