{
  "type": "Feature",
  "properties": {
    "iso:country":"CH",
    "sg:address":"Marktgasse 35",
    "sg:city":"Bern",
    "sg:orig_category":"Detailhandel mit Damenbekleidung Grosshandel mit Textilien",
    "sg:phone":"+41 31 311 05 66",
    "sg:postcode":"3011",
    "sg:province":"Bern",
    "wof:name":"Moditalia Rasim Taninmis",
    "wof:placetype":"venue"
},
  "geometry": {"coordinates":[7.4455609322,46.9479217529],"type":"Point"}
}