{
  "type": "Feature",
  "properties": {
    "iso:country":"CH",
    "sg:address":"Weiermattstrasse 22 3027 Bern. Postfach",
    "sg:city":"Bern",
    "sg:orig_category":"Fachdetailhandel in Verkaufsr\u00e4umen",
    "sg:postcode":"3027",
    "sg:province":"Bern",
    "wof:name":"A-pro Sport, Joss + Wyss Sportbekleidung, -artikel; Verkauf",
    "wof:placetype":"venue"
},
  "geometry": {"coordinates":[7.3788199425,46.9485702515],"type":"Point"}
}