{
  "type": "Feature",
  "properties": {
    "iso:country":"CH",
    "sg:address":"Im Ochsengarten 1",
    "sg:city":"Blauen",
    "sg:orig_category":"Detailhandel mit Antiquit\u00e4ten",
    "sg:phone":"+41 76 378 78 23",
    "sg:postcode":"4223",
    "sg:province":"Basel-Landschaft",
    "wof:name":"Erich Saladin Antik Style Saladin",
    "wof:placetype":"venue"
},
  "geometry": {"coordinates":[7.518243,47.449936],"type":"Point"}
}