{
  "type": "Feature",
  "properties": {
    "iso:country":"CH",
    "sg:address":"Wehntalerstrasse 6",
    "sg:city":"Oberglatt",
    "sg:classifiers":[
        {
            "category":"Sports & Exercise",
            "subcategory":"Playing Field",
            "type":"Entertainment"
        }
    ],
    "sg:phone":"+41 18522020",
    "sg:postcode":"8154",
    "sg:province":"Z\u00fcrich",
    "sg:tags":[
        "encoders",
        "angle"
    ],
    "wof:name":"Aip Wild Ag",
    "wof:placetype":"venue"
},
  "geometry": {"coordinates":[8.503327,47.48082],"type":"Point"}
}