{
  "type": "Feature",
  "properties": {
    "iso:country":"CH",
    "sg:address":"Neue Hard 16",
    "sg:city":"Z\u00fcrich",
    "sg:orig_category":"Mini-Disc\u00ae Players",
    "sg:phone":"+41 43 534 57 25",
    "sg:postcode":"8005",
    "sg:province":"Z\u00fcrich",
    "wof:name":"Green & Co Kg",
    "wof:placetype":"venue"
},
  "geometry": {"coordinates":[8.5195064545,47.3872070312],"type":"Point"}
}