{
  "type": "Feature",
  "properties": {
    "iso:country":"CH",
    "sg:address":"Route De Chancy 28",
    "sg:city":"Petit-lancy",
    "sg:orig_category":"Zahntechnische Laboratorien",
    "sg:phone":"+41 22 793 39 30",
    "sg:postcode":"1213",
    "sg:province":"Gen\u00e8ve",
    "wof:name":"Georges Morand Laboratoire Dentaire",
    "wof:placetype":"venue"
},
  "geometry": {"coordinates":[6.1190571785,46.1903877258],"type":"Point"}
}