{
  "type": "Feature",
  "properties": {
    "iso:country":"CH",
    "sg:address":"Rue De Gen\u00e8ve 88",
    "sg:city":"Ch\u00eane-bourg",
    "sg:orig_category":"Detailhandel mit Tabakwaren",
    "sg:phone":"+41 22 348 38 30",
    "sg:postcode":"1225",
    "sg:province":"Gen\u00e8ve",
    "wof:name":"V. & C. Franchina Shop Tip Top Tabacs",
    "wof:placetype":"venue"
},
  "geometry": {"coordinates":[6.19871521,46.1933784485],"type":"Point"}
}