{
  "type": "Feature",
  "properties": {
    "iso:country":"CH",
    "sg:address":"Grand-rue 17",
    "sg:city":"Rolle",
    "sg:orig_category":"Detailhandel mit Geschenkartikeln U Souvenirs",
    "sg:phone":"+41 21 825 20 33",
    "sg:postcode":"1180",
    "sg:province":"Vaud",
    "wof:name":"Boutique Elisabeth Antoine Gasparetto",
    "wof:placetype":"venue"
},
  "geometry": {"coordinates":[6.3393721581,46.4585189819],"type":"Point"}
}