{
  "type": "Feature",
  "properties": {
    "iso:country":"CH",
    "sg:address":"Rte Du Bois 31",
    "sg:city":"Ecublens",
    "sg:classifiers":[
        {
            "category":"Banks & Credit Unions",
            "subcategory":"Bank",
            "type":"Services"
        }
    ],
    "sg:phone":"+41 21 691 97 11",
    "sg:postcode":"1503",
    "wof:name":"Banque Vaudoise De Credit",
    "wof:placetype":"venue"
},
  "geometry": {"coordinates":[6.808428,46.609589],"type":"Point"}
}