{
  "type": "Feature",
  "properties": {
    "iso:country":"CH",
    "sg:address":"Birmensdorferstrasse 122",
    "sg:city":"Urdorf",
    "sg:orig_category":"Reiseb\u00fcros U Reiseveranstalter Wirtschaftspr\u00fcfung, Steuerberatung U Treuhand",
    "sg:phone":"+41 17353040",
    "sg:postcode":"8902",
    "sg:province":"Z\u00fcrich",
    "wof:name":"Tanner Treuhand & Touristik Ag",
    "wof:placetype":"venue"
},
  "geometry": {"coordinates":[8.4226951599,47.3811454773],"type":"Point"}
}