{
  "type": "Feature",
  "properties": {
    "addr:full":"Im Unteren Baumgarten 15 W\u00e4denswil Z\u00fcrich 8820",
    "addr:housenumber":"15",
    "addr:postcode":"8820",
    "addr:street":"Im Unteren Baumgarten;Zuerich",
    "iso:country":"CH",
    "sg:address":"Im Unteren Baumgarten 15",
    "sg:city":"W\u00e4denswil",
    "sg:orig_category":"Arbeitnehmerverb\u00e4nde",
    "sg:phone":"+41 17801040",
    "sg:postcode":"8820",
    "sg:province":"Z\u00fcrich",
    "wof:name":"Kaufm\u00e4mmischer Verein",
    "wof:placetype":"venue"
},
  "geometry": {"coordinates":[8.672213,47.222168],"type":"Point"}
}