{
  "type": "Feature",
  "properties": {
    "iso:country":"CH",
    "sg:address":"Lavertezzo Piano",
    "sg:city":"Riazzino",
    "sg:orig_category":"Selbst\u00e4ndige bildende K\u00fcnstler",
    "sg:phone":"+41 33 822 87 31",
    "sg:postcode":"6595",
    "sg:province":"Ticino",
    "wof:name":"Peter Abegglen Holz-& Steingrabmale",
    "wof:placetype":"venue"
},
  "geometry": {"coordinates":[7.8952298164,46.7016448975],"type":"Point"}
}