{
  "type": "Feature",
  "properties": {
    "addr:full":"Rue Des Tunnels 38 Neuch\u00e2tel Neuch\u00e2tel 2000",
    "addr:housenumber":"38",
    "addr:postcode":"2000",
    "addr:street":"Rue Des Tunnels",
    "iso:country":"CH",
    "sg:address":"Rue Des Tunnels 38",
    "sg:city":"Neuch\u00e2tel",
    "sg:classifiers":[
        {
            "category":"Home & Garden",
            "subcategory":"Household Appliances",
            "type":"Retail Goods"
        }
    ],
    "sg:phone":"+41 32 737 74 74",
    "sg:postcode":"2000",
    "sg:province":"Neuch\u00e2tel",
    "sg:tags":[
        "stove",
        "chimney"
    ],
    "wof:name":"Tiba Sa",
    "wof:placetype":"venue"
},
  "geometry": {"coordinates":[6.914906,46.990257],"type":"Point"}
}