{
  "type": "Feature",
  "properties": {
    "iso:country":"CH",
    "sg:address":"Sur La C\u00f4te 224",
    "sg:city":"Courtedoux",
    "sg:orig_category":"Wasserversorgung",
    "sg:phone":"+41 32 466 35 50",
    "sg:postcode":"2905",
    "sg:province":"Jura",
    "wof:name":"Convers Francine",
    "wof:placetype":"venue"
},
  "geometry": {"coordinates":[7.0391011238,47.4065208435],"type":"Point"}
}