{
  "type": "Feature",
  "properties": {
    "iso:country":"CH",
    "sg:address":"Rue De Savoie 23",
    "sg:city":"Payerne",
    "sg:orig_category":"Sanit\u00e4r, Heizungs U L\u00fcftungsinstallation",
    "sg:phone":"+41 26 660 10 10",
    "sg:postcode":"1530",
    "sg:province":"Vaud",
    "wof:name":"Dousse Emile, Fribourg Sa.",
    "wof:placetype":"venue"
},
  "geometry": {"coordinates":[6.9393601418,46.8202476501],"type":"Point"}
}