{
  "type": "Feature",
  "properties": {
    "iso:country":"CH",
    "sg:address":"Im R\u00f6tel 7",
    "sg:city":"Zug",
    "sg:orig_category":"Non-Classified Establishments",
    "sg:postcode":"6300",
    "sg:province":"Zug",
    "wof:name":"Kannewischer Holding Ag",
    "wof:placetype":"venue"
},
  "geometry": {"coordinates":[8.5252418518,47.1654167175],"type":"Point"}
}