{
  "type": "Feature",
  "properties": {
    "iso:country":"CH",
    "sg:address":"T\u00e4gerhardstrasse 120",
    "sg:city":"Wettingen",
    "sg:orig_category":"Instandhaltung U Reparatur von Automobilen",
    "sg:postcode":"5430",
    "sg:province":"Aargau",
    "wof:name":"Luigi Cerrato",
    "wof:placetype":"venue"
},
  "geometry": {"coordinates":[8.3340101242,47.4563026428],"type":"Point"}
}