{
  "type": "Feature",
  "properties": {
    "iso:country":"CH",
    "sg:address":"Chemin De Montaux",
    "sg:city":"Lonay",
    "sg:orig_category":"Herstellung von W\u00e4sche",
    "sg:postcode":"1027",
    "sg:province":"Vaud",
    "wof:name":"Rohrer Ruth",
    "wof:placetype":"venue"
},
  "geometry": {"coordinates":[6.5254049301,46.5306091309],"type":"Point"}
}