{
  "type": "Feature",
  "properties": {
    "iso:country":"CH",
    "sg:address":"Binningerstrasse 117",
    "sg:city":"Allschwil",
    "sg:orig_category":"Unclassifiable Establishments",
    "sg:phone":"+41 61 482 34 67",
    "sg:postcode":"4123",
    "sg:province":"Basel-Landschaft",
    "wof:name":"Kleintransporte S. Jasari",
    "wof:placetype":"venue"
},
  "geometry": {"coordinates":[7.5493869781,47.5478057861],"type":"Point"}
}