{
  "type": "Feature",
  "properties": {
    "iso:country":"CH",
    "sg:address":"Untereichli 18",
    "sg:city":"Immensee",
    "sg:orig_category":"Bauspenglerei Dachdeckerei",
    "sg:phone":"+41 41 850 01 60",
    "sg:postcode":"6405",
    "sg:province":"Schwyz",
    "wof:name":"Bucher Dach Ag Bedachungen & Bauspenglerei",
    "wof:placetype":"venue"
},
  "geometry": {"coordinates":[8.461027,47.094746],"type":"Point"}
}