{
  "type": "Feature",
  "properties": {
    "iso:country":"CH",
    "sg:address":"Neugasse 6 9400 Rorschach. Postfach",
    "sg:city":"Rorschach",
    "sg:orig_category":"Verwaltung von Immobilien",
    "sg:postcode":"9400",
    "sg:province":"St. Gallen",
    "wof:name":"Hh Meeting Lounge Gmbh",
    "wof:placetype":"venue"
},
  "geometry": {"coordinates":[9.4919204712,47.4784812927],"type":"Point"}
}