{
  "type": "Feature",
  "properties": {
    "iso:country":"CH",
    "sg:address":"Schlattstrasse 16",
    "sg:city":"Herrliberg",
    "sg:orig_category":"Sonstiger Grosshandel",
    "sg:postcode":"8704",
    "sg:province":"Z\u00fcrich",
    "wof:name":"Tradeg\u00e9rance Ag",
    "wof:placetype":"venue"
},
  "geometry": {"coordinates":[8.6227998734,47.2871170044],"type":"Point"}
}