{
  "type": "Feature",
  "properties": {
    "iso:country":"CH",
    "sg:address":"Kellerswiesenstrasse 33",
    "sg:city":"Eggersriet",
    "sg:orig_category":"Fahrschulen, Flugschulen",
    "sg:phone":"+41 55 240 24 44",
    "sg:postcode":"9034",
    "sg:province":"St. Gallen",
    "wof:name":"Werner Rothenb\u00fchler Autofahrschule",
    "wof:placetype":"venue"
},
  "geometry": {"coordinates":[8.8544054031,47.2505722046],"type":"Point"}
}