{
  "type": "Feature",
  "properties": {
    "iso:country":"CH",
    "sg:address":"M\u00fchlegasse 1",
    "sg:city":"Balsthal",
    "sg:orig_category":"Interessenvertretungen",
    "sg:phone":"+41 62 386 12 12",
    "sg:postcode":"4710",
    "sg:province":"Solothurn",
    "wof:name":"Verein Gr\u00fcnderzentrum Kanton Solothurn",
    "wof:placetype":"venue"
},
  "geometry": {"coordinates":[7.6972742081,47.3155593872],"type":"Point"}
}