{
  "type": "Feature",
  "properties": {
    "iso:country":"CH",
    "sg:address":"H\u00e4ldelistrasse 27",
    "sg:city":"Neerach",
    "sg:orig_category":"Detailhandel mit Teppichen Verlegen von Fussboden",
    "sg:phone":"+41 18581797",
    "sg:postcode":"8173",
    "sg:province":"Z\u00fcrich",
    "wof:name":"Fritz Ryser Teppiche",
    "wof:placetype":"venue"
},
  "geometry": {"coordinates":[8.4655714035,47.5125312805],"type":"Point"}
}