{
  "type": "Feature",
  "properties": {
    "iso:country":"CH",
    "sg:address":"Grenzacherstrasse 97 4058 Basel. Postfach",
    "sg:city":"Basel",
    "sg:orig_category":"Erbringung von Dienstleistungen f\u00fcr Unternehmen",
    "sg:phone":"+41 61 691 32 89",
    "sg:postcode":"4051",
    "sg:province":"Basel-Stadt",
    "wof:name":"S & P Innenarchitektur, Steiger & Partner Raumgestaltung, Wohndesign",
    "wof:placetype":"venue"
},
  "geometry": {"coordinates":[7.6035208702,47.5589485168],"type":"Point"}
}