{
  "type": "Feature",
  "properties": {
    "iso:country":"CH",
    "sg:address":"Fronwagplatz 7",
    "sg:city":"Schaffhausen",
    "sg:orig_category":"Unclassifiable Establishments",
    "sg:postcode":"8200",
    "sg:province":"Schaffhausen",
    "wof:name":"Bbf Schaffhausen Gmbh",
    "wof:placetype":"venue"
},
  "geometry": {"coordinates":[8.6331949234,47.6966819763],"type":"Point"}
}