{
  "type": "Feature",
  "properties": {
    "iso:country":"CH",
    "sg:address":"Rosengartenstrasse 71",
    "sg:city":"Z\u00fcrich",
    "sg:orig_category":"Unclassifiable Establishments",
    "sg:postcode":"8037",
    "sg:province":"Z\u00fcrich",
    "wof:name":"Conventure Gmbh",
    "wof:placetype":"venue"
},
  "geometry": {"coordinates":[8.530424118,47.3959236145],"type":"Point"}
}