{
  "type": "Feature",
  "properties": {
    "iso:country":"CH",
    "sg:address":"Hauptstrasse 38",
    "sg:city":"Zurzach",
    "sg:classifiers":[
        {
            "category":"Restaurant",
            "type":"Food & Drink"
        }
    ],
    "sg:phone":"+41 56 249 32 05",
    "sg:postcode":"5330",
    "sg:province":"Aargau",
    "wof:name":"Restaurant Arlecchino",
    "wof:placetype":"venue"
},
  "geometry": {"coordinates":[8.2926044464,47.586025238],"type":"Point"}
}