{
  "type": "Feature",
  "properties": {
    "addr:full":"Via Cantonale 6527 Lodrino. Postfach Lodrino Ticino 6527",
    "addr:postcode":"6527;6527",
    "addr:street":"Via Cantonale;Postfach;Ticino",
    "iso:country":"CH",
    "sg:address":"Via Cantonale 6527 Lodrino. Postfach",
    "sg:city":"Lodrino",
    "sg:orig_category":"Allgemeiner Hoch U Tiefbau",
    "sg:postcode":"6527",
    "sg:province":"Ticino",
    "wof:name":"Nbk Neutrale Baukonzepte, M\u00fcller Hans Baumanagement, Neutrale Bauberatungen, Expertisen, Bauprojekte, Projektleitungen",
    "wof:placetype":"venue"
},
  "geometry": {"coordinates":[8.303848,46.989426],"type":"Point"}
}