{
  "type": "Feature",
  "properties": {
    "iso:country":"CH",
    "sg:address":"Neue Aarburgerstrasse 2",
    "sg:city":"Rothrist",
    "sg:orig_category":"Detailhandel mit M\u00f6beln U Haushaltsgegenst\u00e4nden Grosshandel mit M\u00f6beln, Wohnbedarf, Teppichen U Bode",
    "sg:phone":"+41 41 794 34 34",
    "sg:postcode":"4852",
    "sg:province":"Aargau",
    "wof:name":"Rutina - K\u00fcchen Ag",
    "wof:placetype":"venue"
},
  "geometry": {"coordinates":[7.8797698021,47.3070716858],"type":"Point"}
}