{
  "type": "Feature",
  "properties": {
    "iso:country":"CH",
    "sg:address":"Schloss Ursellen",
    "sg:city":"Konolfingen",
    "sg:orig_category":"Non-Classified Establishments",
    "sg:postcode":"3510",
    "sg:province":"Bern",
    "wof:name":"Berakom Ag",
    "wof:placetype":"venue"
},
  "geometry": {"coordinates":[7.6025319099,46.8789558411],"type":"Point"}
}