{
  "type": "Feature",
  "properties": {
    "iso:country":"CH",
    "sg:address":"Bahnhofstrasse 4",
    "sg:city":"Sachseln",
    "sg:orig_category":"Handel mit Motorr\u00e4dern, Teilen U Zubeh\u00f6r Instandhaltung U Reparatur von Motorr\u00e4dern",
    "sg:phone":"+41 41 662 16 16",
    "sg:postcode":"6072",
    "sg:province":"Obwalden",
    "wof:name":"Country Road Burri Martin Motorrad-werkstatt",
    "wof:placetype":"venue"
},
  "geometry": {"coordinates":[8.2392950058,46.8696594238],"type":"Point"}
}