{
  "type": "Feature",
  "properties": {
    "iso:country":"CH",
    "sg:address":"5417",
    "sg:city":"Untersiggenthal",
    "sg:orig_category":"Sportvereine Turnen",
    "sg:postcode":"5417",
    "sg:province":"Aargau",
    "wof:name":"Turnverein Etv",
    "wof:placetype":"venue"
},
  "geometry": {"coordinates":[8.2633457184,47.4998207092],"type":"Point"}
}