{
  "type": "Feature",
  "properties": {
    "iso:country":"CH",
    "sg:address":"Rue Pierre-p\u00e9quignat 23",
    "sg:city":"Courgenay",
    "sg:orig_category":"Notariate",
    "sg:phone":"+41 32 471 20 09",
    "sg:postcode":"2950",
    "sg:province":"Jura",
    "wof:name":"Jean-fran\u00e7ois Kohler Etude De Notaire",
    "wof:placetype":"venue"
},
  "geometry": {"coordinates":[7.1238150597,47.4040718079],"type":"Point"}
}