{
  "type": "Feature",
  "properties": {
    "addr:full":"Bankstrasse 24 Embrach Z\u00fcrich 8424",
    "addr:housenumber":"24",
    "addr:postcode":"8424",
    "addr:street":"Bankstrasse",
    "iso:country":"CH",
    "sg:address":"Bankstrasse 24",
    "sg:city":"Embrach",
    "sg:orig_category":"Architektur U Ingenieurb\u00fcros Hoch U Tiefbau",
    "sg:phone":"+41 18654422",
    "sg:postcode":"8424",
    "sg:province":"Z\u00fcrich",
    "wof:name":"Gebr. Hunziker Ag Ingenieurunternehmung Sia / Usic",
    "wof:placetype":"venue"
},
  "geometry": {"coordinates":[8.593801,47.502781],"type":"Point"}
}