{
  "type": "Feature",
  "properties": {
    "iso:country":"CH",
    "sg:address":"Dorfstrasse 38",
    "sg:city":"W\u00fcnnewil",
    "sg:orig_category":"Wein Detailhandel",
    "sg:phone":"+41 26 496 14 85",
    "sg:postcode":"3184",
    "sg:province":"Fribourg",
    "wof:name":"Weinkiste St. Jakob",
    "wof:placetype":"venue"
},
  "geometry": {"coordinates":[7.2742609978,46.8748855591],"type":"Point"}
}