{
  "type": "Feature",
  "properties": {
    "addr:full":"Dunantstrasse 27 3006 Bern. Postfach Bern Bern 3005",
    "addr:housenumber":"27",
    "addr:postcode":"3006;postfach;3005",
    "addr:street":"Dunantstrasse",
    "iso:country":"CH",
    "sg:address":"Dunantstrasse 27 3006 Bern. Postfach",
    "sg:city":"Bern",
    "sg:orig_category":"Allgemeiner Hoch U Tiefbau",
    "sg:postcode":"3005",
    "sg:province":"Bern",
    "wof:name":"Gebr. Merz Ag G\u00fcmligen Baugesch\u00e4ft",
    "wof:placetype":"venue"
},
  "geometry": {"coordinates":[7.476895,46.935394],"type":"Point"}
}