{
  "type": "Feature",
  "properties": {
    "iso:country":"CH",
    "sg:address":"Grendelstrasse 7",
    "sg:city":"Ennetbaden",
    "sg:orig_category":"Vorschulen, Kinderg\u00e4rten",
    "sg:postcode":"5408",
    "sg:province":"Aargau",
    "wof:name":"Kindergarten Grendel",
    "wof:placetype":"venue"
},
  "geometry": {"coordinates":[8.3142757416,47.4782028198],"type":"Point"}
}