{
  "type": "Feature",
  "properties": {
    "iso:country":"CH",
    "sg:address":"Albricci Via Degli 6",
    "sg:city":"Chiasso",
    "sg:orig_category":"Unclassifiable Establishments",
    "sg:postcode":"6830",
    "sg:province":"Ticino",
    "wof:name":"Refinvest Sa",
    "wof:placetype":"venue"
},
  "geometry": {"coordinates":[9.034113884,45.834197998],"type":"Point"}
}