{
  "type": "Feature",
  "properties": {
    "iso:country":"CH",
    "sg:address":"Dorf",
    "sg:city":"R\u00fceggisberg",
    "sg:orig_category":"Advokaturb\u00fcros Notariate",
    "sg:phone":"+41 31 802 05 25",
    "sg:postcode":"3088",
    "sg:province":"Bern",
    "wof:name":"Peter B\u00e4riswyl Notariat Advokatur Verwaltung",
    "wof:placetype":"venue"
},
  "geometry": {"coordinates":[7.438045,46.822205],"type":"Point"}
}