{
  "type": "Feature",
  "properties": {
    "iso:country":"CH",
    "sg:address":"Weissbadstrasse 14 9050 Appenzell. Postfach",
    "sg:city":"Appenzell",
    "sg:orig_category":"Grosshandel mit Erzen U Metallen Handelsvermittlung von Brennstoffen, Erzen, Metallen U Chemikalien",
    "sg:phone":"+41 71 788 18 20",
    "sg:postcode":"9050",
    "sg:province":"Appenzell Innerhoden",
    "wof:name":"A & M Resources Sa",
    "wof:placetype":"venue"
},
  "geometry": {"coordinates":[9.412115097,47.3291473389],"type":"Point"}
}