{
  "type": "Feature",
  "properties": {
    "addr:full":"St\u00e4dtle 7 9490 Vaduz. Postfach 70 Vaduz 9490",
    "addr:housenumber":"7;70",
    "addr:postcode":"9490 vaduz.;9490",
    "addr:street":"Staedtle;Postfach",
    "iso:country":"CH",
    "sg:address":"St\u00e4dtle 7 9490 Vaduz. Postfach 70",
    "sg:city":"Vaduz",
    "sg:orig_category":"Advokaturb\u00fcros",
    "sg:phone":"+41 75 236 14 44",
    "sg:postcode":"9490",
    "wof:name":"Dr.alexander Abfalterer Advokaturb\u00fcro",
    "wof:placetype":"venue"
},
  "geometry": {"coordinates":[9.521681,47.141144],"type":"Point"}
}