{
  "type": "Feature",
  "properties": {
    "iso:country":"CH",
    "sg:address":"Chemin Des Vignes 2bis 1209 Gen\u00e8ve. Postfach",
    "sg:city":"Gen\u00e8ve",
    "sg:orig_category":"Finanzierungsinstitutionen Verm\u00f6gensverwaltung",
    "sg:phone":"+41 22 733 28 28",
    "sg:postcode":"1209",
    "sg:province":"Gen\u00e8ve",
    "wof:name":"Kairos Investments",
    "wof:placetype":"venue"
},
  "geometry": {"coordinates":[6.1306290627,46.2213058472],"type":"Point"}
}