{
  "type": "Feature",
  "properties": {
    "iso:country":"CH",
    "sg:address":"Via Aldesago 142",
    "sg:city":"Lugano",
    "sg:orig_category":"Vermietung U Verpachtung von eigenen Immobilien",
    "sg:postcode":"6900",
    "sg:province":"Ticino",
    "wof:name":"Furgiati Sa",
    "wof:placetype":"venue"
},
  "geometry": {"coordinates":[8.984041214,46.0063896179],"type":"Point"}
}