{
  "type": "Feature",
  "properties": {
    "iso:country":"CH",
    "sg:address":"Place Grenus 4",
    "sg:city":"Gen\u00e8ve",
    "sg:orig_category":"Grosshandel mit Eisenwaren sowie Installationsbedarf f\u00fcr Gas, Wasser U Heizung Grosshandel mit Erzen",
    "sg:phone":"+41 22 732 40 67",
    "sg:postcode":"1201",
    "sg:province":"Gen\u00e8ve",
    "wof:name":"Henri Reymond Sa",
    "wof:placetype":"venue"
},
  "geometry": {"coordinates":[6.1434969902,46.2067985535],"type":"Point"}
}