{
  "type": "Feature",
  "properties": {
    "iso:country":"CH",
    "sg:address":"Adetswilerstrasse 52",
    "sg:city":"Adetswil",
    "sg:orig_category":"Detailhandel mit Waren verschiedener Art, Hauptrichtung Nahrungsmittel",
    "sg:phone":"+41 19391244",
    "sg:postcode":"8345",
    "sg:province":"Z\u00fcrich",
    "wof:name":"Volg Adetswil Landi B\u00e4retswil",
    "wof:placetype":"venue"
},
  "geometry": {"coordinates":[8.8388366699,47.3392524719],"type":"Point"}
}