{
  "type": "Feature",
  "properties": {
    "iso:country":"CH",
    "sg:address":"Lindhofstrasse 94",
    "sg:city":"Windisch",
    "sg:orig_category":"Fachdetailhandel in Verkaufsr\u00e4umen Grosshandel mit sonstigen Gebrauchs U Verbrauchsg\u00fctern",
    "sg:phone":"+41 56 441 43 77",
    "sg:postcode":"5210",
    "sg:province":"Aargau",
    "wof:name":"Camporesi Fashion Inh.alois Saxer",
    "wof:placetype":"venue"
},
  "geometry": {"coordinates":[8.2210693359,47.4711914062],"type":"Point"}
}