{
  "type": "Feature",
  "properties": {
    "iso:country":"CH",
    "sg:address":"Cossonay Route De 66 1008 Prilly. Postfach",
    "sg:city":"Prilly",
    "sg:orig_category":"Tankstellen",
    "sg:postcode":"1008",
    "sg:province":"Vaud",
    "wof:name":"Migrol Service Hugonnet St\u00e9phane Station-service Et Shop",
    "wof:placetype":"venue"
},
  "geometry": {"coordinates":[6.6014060974,46.5376243591],"type":"Point"}
}