{
  "type": "Feature",
  "properties": {
    "iso:country":"CH",
    "sg:address":"Sagenbungert",
    "sg:city":"Haldenstein",
    "sg:orig_category":"Instandhaltung U Reparatur von Automobilen",
    "sg:postcode":"7023",
    "sg:province":"Graubunden",
    "wof:name":"Panier Hans",
    "wof:placetype":"venue"
},
  "geometry": {"coordinates":[9.5266046524,46.8787574768],"type":"Point"}
}