{
  "type": "Feature",
  "properties": {
    "iso:country":"CH",
    "sg:address":"Hauptstrasse 31",
    "sg:city":"Arbon",
    "sg:orig_category":"Unclassifiable Establishments",
    "sg:postcode":"9320",
    "sg:province":"Thurgau",
    "wof:name":"Erat Design Group Ag",
    "wof:placetype":"venue"
},
  "geometry": {"coordinates":[9.4335479736,47.5161056519],"type":"Point"}
}