{
  "type": "Feature",
  "properties": {
    "iso:country":"CH",
    "sg:address":"Sporgasse 1",
    "sg:city":"Grabs",
    "sg:orig_category":"Grosshandel mit sonstigen Halbwaren Herstellung von Bettwaren",
    "sg:phone":"+41 81 771 42 12",
    "sg:postcode":"9472",
    "sg:province":"St. Gallen",
    "wof:name":"Ettlin-frei Hans, Wollkarderei",
    "wof:placetype":"venue"
},
  "geometry": {"coordinates":[9.4446411133,47.1818962097],"type":"Point"}
}