{
  "type": "Feature",
  "properties": {
    "iso:country":"CH",
    "sg:address":"F\u00f6hrenweg 7",
    "sg:city":"Rupperswil",
    "sg:orig_category":"Handelsvermittlung U Grosshandel Wasserversorgung",
    "sg:phone":"+41 62 897 58 30",
    "sg:postcode":"5102",
    "sg:province":"Aargau",
    "wof:name":"Wild Hans, Wasseraufbereitung",
    "wof:placetype":"venue"
},
  "geometry": {"coordinates":[8.1227989197,47.4046592712],"type":"Point"}
}