{
  "type": "Feature",
  "properties": {
    "iso:country":"CH",
    "sg:address":"Constant Place Benjamin- 2",
    "sg:city":"Lausanne",
    "sg:orig_category":"RESTAURANTS: TEA-ROOMS",
    "sg:phone":"+41 32 753 25 93",
    "sg:postcode":"1003",
    "sg:province":"Vaud",
    "wof:name":"Pinocchio - Pizzeria - Restaurant, Capaldi S.",
    "wof:placetype":"venue"
},
  "geometry": {"coordinates":[6.9616589546,47.0087471008],"type":"Point"}
}