{
  "type": "Feature",
  "properties": {
    "addr:full":"Hauptstrasse 30 Wolfertswil St. Gallen 9116",
    "addr:housenumber":"30",
    "addr:postcode":"9116",
    "addr:street":"Hauptstrasse",
    "iso:country":"CH",
    "sg:address":"Hauptstrasse 30",
    "sg:city":"Wolfertswil",
    "sg:classifiers":[
        {
            "category":"Banks & Credit Unions",
            "subcategory":"Bank",
            "type":"Services"
        }
    ],
    "sg:phone":"+41 4171831116",
    "sg:postcode":"9116",
    "sg:province":"St. Gallen",
    "wof:name":"Raiffeisenbank",
    "wof:placetype":"venue"
},
  "geometry": {"coordinates":[9.18221,47.395027],"type":"Point"}
}