{
  "type": "Feature",
  "properties": {
    "iso:country":"CH",
    "sg:address":"Verbier 1936 Verbier. Postfach",
    "sg:city":"Verbier",
    "sg:orig_category":"Architektur U Ingenieurb\u00fcros",
    "sg:postcode":"1936",
    "sg:province":"Valais",
    "wof:name":"Gaillard Robert",
    "wof:placetype":"venue"
},
  "geometry": {"coordinates":[7.219276,46.096146],"type":"Point"}
}