{
  "type": "Feature",
  "properties": {
    "iso:country":"CH",
    "sg:address":"Obernauerstrasse 9",
    "sg:city":"Kriens",
    "sg:orig_category":"Sonstige mit der Informatik verbundene T\u00e4tigkeiten",
    "sg:phone":"+41 41 320 78 94",
    "sg:postcode":"6010",
    "sg:province":"Luzern",
    "wof:name":"Colangelo Antonio",
    "wof:placetype":"venue"
},
  "geometry": {"coordinates":[8.2723379135,47.0338745117],"type":"Point"}
}