{
  "type": "Feature",
  "properties": {
    "iso:country":"CH",
    "sg:address":"Baselstrasse 160",
    "sg:city":"Laufen",
    "sg:orig_category":"Detailhandel mit Metallwaren, Anstrichmitteln, Glaswaren, Bau U Heimwerkerbedarf",
    "sg:postcode":"4242",
    "sg:province":"Basel-Landschaft",
    "wof:name":"Edmv Ag F\u00fcr Entwicklung, Design, Marketing Und Vertrieb.",
    "wof:placetype":"venue"
},
  "geometry": {"coordinates":[8.3084011078,46.9914245605],"type":"Point"}
}