{
  "type": "Feature",
  "properties": {
    "iso:country":"CH",
    "sg:address":"Seestrasse 39",
    "sg:city":"Salmsach",
    "sg:orig_category":"Grosshandel mit Erzen U Metallen",
    "sg:postcode":"8599",
    "sg:province":"Thurgau",
    "wof:name":"Hunziker Frau Renate",
    "wof:placetype":"venue"
},
  "geometry": {"coordinates":[9.3758611679,47.5551223755],"type":"Point"}
}