{
  "type": "Feature",
  "properties": {
    "iso:country":"CH",
    "sg:address":"Aux Partiers 156",
    "sg:city":"Corm\u00e9rod",
    "sg:orig_category":"G\u00fcterbef\u00f6rderung im Strassenverkehr",
    "sg:phone":"+41 26 684 17 77",
    "sg:postcode":"1721",
    "sg:province":"Fribourg",
    "wof:name":"Bjedov Zarko",
    "wof:placetype":"venue"
},
  "geometry": {"coordinates":[7.0656499863,46.8526954651],"type":"Point"}
}