{
  "type": "Feature",
  "properties": {
    "iso:country":"CH",
    "sg:address":"Pr\u00e9-fleuri Chemin Du 25c 1228 Plan-les-ouates Case Postale 157",
    "sg:city":"Plan-les-ouates",
    "sg:orig_category":"Herstellung von Maschinen f\u00fcr die Nahrungsmittel, Getr\u00e4nkeherstellung U die Tabakverarbeitung",
    "sg:phone":"+41 22 706 10 20",
    "sg:postcode":"1228",
    "sg:province":"Gen\u00e8ve",
    "wof:name":"Hukki-import Dreher & Cie",
    "wof:placetype":"venue"
},
  "geometry": {"coordinates":[6.108178,46.165359],"type":"Point"}
}