{
  "type": "Feature",
  "properties": {
    "iso:country":"CH",
    "sg:address":"Unterdorf 55",
    "sg:city":"Sils",
    "sg:classifiers":[
        {
            "category":"Banks & Credit Unions",
            "subcategory":"Bank",
            "type":"Services"
        }
    ],
    "sg:phone":"+41 41 789 60 30",
    "sg:postcode":"7411",
    "sg:province":"Graubunden",
    "wof:name":"Raiffeisenbank Sins-oberr\u00fcti",
    "wof:placetype":"venue"
},
  "geometry": {"coordinates":[8.39609,47.188679],"type":"Point"}
}