{
  "type": "Feature",
  "properties": {
    "iso:country":"CH",
    "sg:address":"Holenackerstrasse 33 3027 Bern. Postfach",
    "sg:city":"Bern",
    "sg:orig_category":"Ger\u00fcstbau Sonstiger spezialisierter Hoch U Tiefbau",
    "sg:phone":"+41 31 991 20 67",
    "sg:postcode":"3027",
    "sg:province":"Bern",
    "wof:name":"Emini Ger\u00fcstbau Gmbh Ger\u00fcstbauunternehmens Usw.",
    "wof:placetype":"venue"
},
  "geometry": {"coordinates":[7.3807439804,46.9500694275],"type":"Point"}
}