{
  "type": "Feature",
  "properties": {
    "iso:country":"CH",
    "sg:address":"Chemin De La Fontaine 8 1224 Ch\u00eane-bougeries. Postfach",
    "sg:city":"Ch\u00eane-bougeries",
    "sg:orig_category":"Sonstige Finanzierungsinstitutionen",
    "sg:phone":"+41 22 349 46 94",
    "sg:postcode":"1224",
    "sg:province":"Gen\u00e8ve",
    "wof:name":"Ipp Telecommunications Sa Participations Etc",
    "wof:placetype":"venue"
},
  "geometry": {"coordinates":[6.1908898354,46.196849823],"type":"Point"}
}