{
  "type": "Feature",
  "properties": {
    "iso:country":"CH",
    "sg:address":"Route Petite-caroline 3 A",
    "sg:city":"Tolochenaz",
    "sg:orig_category":"Wirtschaftspr\u00fcfung, Steuerberatung U Treuhand",
    "sg:phone":"+41 21 801 68 51",
    "sg:postcode":"1131",
    "sg:province":"Vaud",
    "wof:name":"Pl Gestion Patrick Luquiens Bureau Fiduciaire",
    "wof:placetype":"venue"
},
  "geometry": {"coordinates":[6.4757518768,46.498336792],"type":"Point"}
}