{
  "type": "Feature",
  "properties": {
    "iso:country":"CH",
    "sg:address":"Zweierstr. 169/1",
    "sg:city":"Z\u00fcrich",
    "sg:classifiers":[
        {
            "category":"Banks & Credit Unions",
            "subcategory":"Bank",
            "type":"Services"
        }
    ],
    "sg:phone":"+41 12285747",
    "sg:postcode":"8003",
    "sg:province":"Z\u00fcrich",
    "wof:name":"Julius Baer Holding Ltd",
    "wof:placetype":"venue"
},
  "geometry": {"coordinates":[8.538864,47.371246],"type":"Point"}
}