{
  "type": "Feature",
  "properties": {
    "addr:full":"Fontaine Chemin De La 3 Ch\u00eane-bougeries Gen\u00e8ve 1224",
    "addr:housenumber":"3",
    "addr:postcode":"1224",
    "addr:street":"Chemin De La",
    "iso:country":"CH",
    "sg:address":"Fontaine Chemin De La 3",
    "sg:city":"Ch\u00eane-bougeries",
    "sg:orig_category":"Betrieb von Sportanlagen",
    "sg:phone":"+41 22 349 21 66",
    "sg:postcode":"1224",
    "sg:province":"Gen\u00e8ve",
    "wof:name":"Point Bleu Service, Grandgirard F.",
    "wof:placetype":"venue"
},
  "geometry": {"coordinates":[6.187205,46.197926],"type":"Point"}
}