{
  "type": "Feature",
  "properties": {
    "iso:country":"CH",
    "sg:address":"4938",
    "sg:city":"Rohrbach",
    "sg:orig_category":"Detailhandel mit Fleisch U Fleischwaren",
    "sg:postcode":"4938",
    "sg:province":"Bern",
    "wof:name":"Werner Lanz",
    "wof:placetype":"venue"
},
  "geometry": {"coordinates":[7.8123750687,47.1359062195],"type":"Point"}
}