{
  "type": "Feature",
  "properties": {
    "iso:country":"CH",
    "sg:address":"Dr\u00e8ra Riva Dal",
    "sg:city":"Morcote",
    "sg:orig_category":"RESTAURANTS: TEA-ROOMS",
    "sg:postcode":"6922",
    "sg:province":"Ticino",
    "wof:name":"Sarensol Sagl",
    "wof:placetype":"venue"
},
  "geometry": {"coordinates":[8.916970253,45.9229011536],"type":"Point"}
}