{
  "type": "Feature",
  "properties": {
    "iso:country":"CH",
    "sg:address":"Vordere Gasse 16",
    "sg:city":"Kerzers",
    "sg:orig_category":"Detailhandel mit Textilien Detailhandel mit elektrischen Haushaltsger\u00e4ten",
    "sg:phone":"+41 19302629",
    "sg:postcode":"3210",
    "sg:province":"Fribourg",
    "wof:name":"Gabriel Turke Bernina-n\u00e4hmaschinen",
    "wof:placetype":"venue"
},
  "geometry": {"coordinates":[8.7984170914,47.3254585266],"type":"Point"}
}