{
  "type": "Feature",
  "properties": {
    "iso:country":"CH",
    "sg:address":"Marktplatz 18",
    "sg:city":"Rorschach",
    "sg:orig_category":"Detailhandel mit Textilien",
    "sg:phone":"+41 71 841 63 44",
    "sg:postcode":"9400",
    "sg:province":"St. Gallen",
    "wof:name":"Notburga Studer Wolle & Handarbeiten",
    "wof:placetype":"venue"
},
  "geometry": {"coordinates":[9.4909677505,47.477558136],"type":"Point"}
}