{
  "type": "Feature",
  "properties": {
    "iso:country":"CH",
    "sg:address":"Via Cantonale 34a",
    "sg:city":"Manno",
    "sg:orig_category":"Vermittlung von Immobilien Wirtschaftspr\u00fcfung, Steuerberatung U Treuhand",
    "sg:phone":"+41 41 420 01 23",
    "sg:postcode":"6928",
    "sg:province":"Ticino",
    "wof:name":"Glanzmann Treuhand Ag",
    "wof:placetype":"venue"
},
  "geometry": {"coordinates":[8.3103380203,47.0626144409],"type":"Point"}
}