{
  "type": "Feature",
  "properties": {
    "iso:country":"CH",
    "sg:address":"Via San Gottardo 118a 6648 Minusio. Postfach Caselle Postale 1040",
    "sg:city":"Minusio",
    "sg:orig_category":"Architekturb\u00fcros",
    "sg:phone":"+41 91 743 42 51",
    "sg:postcode":"6648",
    "sg:province":"Ticino",
    "wof:name":"Studio Rizzi Arch. M. Sa Impresa Generale Di Costruzioni Spec. Lavori Edili, Ufficio Tecnico E Fiduciario Ecc",
    "wof:placetype":"venue"
},
  "geometry": {"coordinates":[8.819979,46.178272],"type":"Point"}
}