{
  "type": "Feature",
  "properties": {
    "iso:country":"CH",
    "sg:address":"1354",
    "sg:city":"Montcherand",
    "sg:orig_category":"Haltung von Rindern",
    "sg:postcode":"1354",
    "sg:province":"Vaud",
    "wof:name":"Synd.d'\u00e9levage De La Race Tachet\u00e9e Noire De Romont",
    "wof:placetype":"venue"
},
  "geometry": {"coordinates":[6.9131121635,46.6952056885],"type":"Point"}
}