{
  "type": "Feature",
  "properties": {
    "iso:country":"CH",
    "sg:address":"Bohlstrasse 9a",
    "sg:city":"Zug",
    "sg:orig_category":"Unclassifiable Establishments",
    "sg:postcode":"6300",
    "sg:province":"Zug",
    "wof:name":"Sassum Holding Ag",
    "wof:placetype":"venue"
},
  "geometry": {"coordinates":[8.5183954239,47.1647834778],"type":"Point"}
}