{
  "type": "Feature",
  "properties": {
    "iso:country":"CH",
    "sg:address":"Birseckstrasse 4",
    "sg:city":"M\u00fcnchenstein",
    "sg:orig_category":"Detailhandel mit Bekleidung",
    "sg:phone":"+41 61 411 06 29",
    "sg:postcode":"4142",
    "sg:province":"Basel-Landschaft",
    "wof:name":"Josef Gasser Textilien",
    "wof:placetype":"venue"
},
  "geometry": {"coordinates":[7.614411,47.528023],"type":"Point"}
}