{
  "type": "Feature",
  "properties": {
    "iso:country":"CH",
    "sg:address":"8585",
    "sg:city":"Zuben",
    "sg:orig_category":"Gartenbau",
    "sg:phone":"+41 71 695 18 83",
    "sg:postcode":"8585",
    "sg:province":"Thurgau",
    "wof:name":"Hugo Kramer G\u00e4rtnerei",
    "wof:placetype":"venue"
},
  "geometry": {"coordinates":[9.2376098633,47.6083488464],"type":"Point"}
}