{
  "type": "Feature",
  "properties": {
    "iso:country":"CH",
    "sg:address":"Kieswerkstrasse 8 8355 Aadorf. Postfach 179",
    "sg:city":"Aadorf",
    "sg:orig_category":"Gewinnung von Kies U Sand",
    "sg:phone":"+41 52 365 14 84",
    "sg:postcode":"8355",
    "sg:province":"Thurgau",
    "wof:name":"Kies Und Sandwerk Aadorf Ag",
    "wof:placetype":"venue"
},
  "geometry": {"coordinates":[8.8950786591,47.4996109009],"type":"Point"}
}