{
  "type": "Feature",
  "properties": {
    "iso:country":"CH",
    "sg:address":"Hirschmattstrasse 29 6000 Luzern. Postfach",
    "sg:city":"Luzern",
    "sg:orig_category":"Unternehmensberatung",
    "sg:postcode":"6003",
    "sg:province":"Luzern",
    "wof:name":"Unternehmensberatung Imbach Rolf",
    "wof:placetype":"venue"
},
  "geometry": {"coordinates":[8.3080120087,47.0470314026],"type":"Point"}
}