{
  "type": "Feature",
  "properties": {
    "iso:country":"CH",
    "sg:address":"Zugerstrasse 56",
    "sg:city":"Horgen",
    "sg:classifiers":[
        {
            "category":"Wholesale",
            "subcategory":"Construction Materials",
            "type":"Manufacturing & Wholesale Goods"
        }
    ],
    "sg:phone":"+41 71 223 17 90",
    "sg:postcode":"8810",
    "sg:province":"Z\u00fcrich",
    "sg:tags":[
        "bridge",
        "temporary",
        "materials",
        "crown"
    ],
    "wof:name":"Zahntechnik B\u00fcttner & Abderhalden",
    "wof:placetype":"venue"
},
  "geometry": {"coordinates":[9.3760881424,47.4254989624],"type":"Point"}
}