{
  "type": "Feature",
  "properties": {
    "iso:country":"CH",
    "sg:address":"Dornacherstrasse 10 4600 Olten. Postfach",
    "sg:city":"Olten",
    "sg:orig_category":"Verwaltung von Immobilien Wirtschaftspr\u00fcfung, Steuerberatung U Treuhand",
    "sg:phone":"+41 62 205 70 40",
    "sg:postcode":"4603",
    "sg:province":"Solothurn",
    "wof:name":"Acta-treuhand Ag",
    "wof:placetype":"venue"
},
  "geometry": {"coordinates":[7.9015188217,47.3517456055],"type":"Point"}
}