{
  "type": "Feature",
  "properties": {
    "iso:country":"CH",
    "sg:address":"Oberdorfstrasse 3",
    "sg:city":"Stettlen",
    "sg:orig_category":"Bauschreinerei Herstellung von Konstruktionsteilen, Fertigbauteilen U Ausbauelementen aus Holz",
    "sg:phone":"+41 71 245 84 48",
    "sg:postcode":"3066",
    "sg:province":"Bern",
    "wof:name":"Steiner Alfred, Schreinerei",
    "wof:placetype":"venue"
},
  "geometry": {"coordinates":[9.389843,47.428875],"type":"Point"}
}