{
  "type": "Feature",
  "properties": {
    "addr:full":"Bernstrasse 18 Meikirch Bern 3045",
    "addr:housenumber":"18",
    "addr:postcode":"3045",
    "addr:street":"Bernstrasse",
    "iso:country":"CH",
    "sg:address":"Bernstrasse 18",
    "sg:city":"Meikirch",
    "sg:orig_category":"Arztpraxen",
    "sg:phone":"+41 31 829 20 11",
    "sg:postcode":"3045",
    "sg:province":"Bern",
    "wof:name":"Dr.med.johannes Sieber Arzt F.allgemeine Medizin Fmh",
    "wof:placetype":"venue"
},
  "geometry": {"coordinates":[7.366475,47.009098],"type":"Point"}
}