{
  "type": "Feature",
  "properties": {
    "iso:country":"CH",
    "sg:address":"Route De Saint-julien 147",
    "sg:city":"Plan-les-ouates",
    "sg:orig_category":"Elektroinstallation",
    "sg:postcode":"1228",
    "sg:province":"Gen\u00e8ve",
    "wof:name":"Wespi Willi Elektroinstallationen",
    "wof:placetype":"venue"
},
  "geometry": {"coordinates":[8.0486307144,46.9768791199],"type":"Point"}
}