{
  "type": "Feature",
  "properties": {
    "iso:country":"CH",
    "sg:address":"Surlej",
    "sg:city":"Silvaplana",
    "sg:classifiers":[
        {
            "category":"Travel",
            "subcategory":"Hotels & Motels",
            "type":"Entertainment"
        }
    ],
    "sg:postcode":"7513",
    "sg:province":"Graubunden",
    "sg:tags":[
        "hotels",
        "mit",
        "restaurant"
    ],
    "wof:name":"Ni\u00e9to Jos\u00e9",
    "wof:placetype":"venue"
},
  "geometry": {"coordinates":[6.8312358856,47.1047554016],"type":"Point"}
}