{
  "type": "Feature",
  "properties": {
    "iso:country":"CH",
    "sg:address":"Oberdorf 34",
    "sg:city":"Tschugg",
    "sg:orig_category":"Innenausbau",
    "sg:phone":"+41 62 923 03 52",
    "sg:postcode":"3233",
    "sg:province":"Bern",
    "wof:name":"Max Meyer Innenausbau",
    "wof:placetype":"venue"
},
  "geometry": {"coordinates":[7.8298978806,47.2345314026],"type":"Point"}
}