{
  "type": "Feature",
  "properties": {
    "iso:country":"CH",
    "sg:address":"Brunngrabenstrasse 12",
    "sg:city":"Solothurn",
    "sg:orig_category":"Maler U Glasergewerbe",
    "sg:phone":"+41 32 623 37 49",
    "sg:postcode":"4500",
    "sg:province":"Solothurn",
    "wof:name":"Flury Heinz Ag",
    "wof:placetype":"venue"
},
  "geometry": {"coordinates":[7.5162100792,47.2068862915],"type":"Point"}
}