{
  "type": "Feature",
  "properties": {
    "iso:country":"CH",
    "sg:address":"Seestrasse 1-3 8712 St\u00e4fa. Postfach 180",
    "sg:city":"St\u00e4fa",
    "sg:orig_category":"Instandhaltung U Reparatur von Automobilen Tankstellen",
    "sg:phone":"+41 61 401 13 35",
    "sg:postcode":"8712",
    "sg:province":"Z\u00fcrich",
    "wof:name":"Touring-garage St\u00f6ckli",
    "wof:placetype":"venue"
},
  "geometry": {"coordinates":[7.5630378723,47.5155487061],"type":"Point"}
}