{
  "type": "Feature",
  "properties": {
    "iso:country":"CH",
    "sg:address":"Kirchstrasse 7 3097 Liebefeld. Postfach",
    "sg:city":"Liebefeld",
    "sg:orig_category":"Betrieb U technische Hilfsdienste des Kultur U Unterhaltungswesens",
    "sg:postcode":"3097",
    "sg:province":"Bern",
    "wof:name":"Braun Electronic",
    "wof:placetype":"venue"
},
  "geometry": {"coordinates":[8.82279,47.271988],"type":"Point"}
}