{
  "type": "Feature",
  "properties": {
    "iso:country":"CH",
    "sg:address":"Europe Avenue De L'",
    "sg:city":"Monthey",
    "sg:orig_category":"Non-Classified Establishments",
    "sg:postcode":"1870",
    "sg:province":"Valais",
    "wof:name":"Patricia Lugon",
    "wof:placetype":"venue"
},
  "geometry": {"coordinates":[6.9471402168,46.2516212463],"type":"Point"}
}