{
  "type": "Feature",
  "properties": {
    "addr:full":"Giessenstrasse 15 Schlieren Z\u00fcrich 8952",
    "addr:housenumber":"15",
    "addr:postcode":"8952",
    "addr:street":"Giessenstrasse",
    "iso:country":"CH",
    "sg:address":"Giessenstrasse 15",
    "sg:city":"Schlieren",
    "sg:orig_category":"Datenverarbeitungsdienste Herstellung von industriellen Prozesssteuerungsanlagen",
    "sg:phone":"+41 17745566",
    "sg:postcode":"8952",
    "sg:province":"Z\u00fcrich",
    "wof:name":"Flexfactory Ag",
    "wof:placetype":"venue"
},
  "geometry": {"coordinates":[8.45142,47.398212],"type":"Point"}
}