{
  "type": "Feature",
  "properties": {
    "iso:country":"CH",
    "sg:address":"Francesca Via 1 6596 Gordola. Postfach",
    "sg:city":"Gordola",
    "sg:orig_category":"Stukkateurgewerbe, Gipserei U Verputzerei",
    "sg:phone":"+41 91 745 14 26",
    "sg:postcode":"6596",
    "sg:province":"Ticino",
    "wof:name":"Tecnogesso Di Lot\u00e0 Giuseppe Impresa Di Gessatura",
    "wof:placetype":"venue"
},
  "geometry": {"coordinates":[8.8604202271,46.180934906],"type":"Point"}
}