{
  "type": "Feature",
  "properties": {
    "iso:country":"CH",
    "sg:address":"Sustenstrasse 8a",
    "sg:city":"Z\u00fcrich",
    "sg:orig_category":"Sonstige pers\u00f6nliche Dienstleistungen",
    "sg:phone":"+41 14319760",
    "sg:postcode":"8048",
    "sg:province":"Z\u00fcrich",
    "wof:name":"Ammann Oskar Haus U. Garten; Dienstleistungen",
    "wof:placetype":"venue"
},
  "geometry": {"coordinates":[8.4784002304,47.3879203796],"type":"Point"}
}