{
  "type": "Feature",
  "properties": {
    "iso:country":"CH",
    "sg:address":"Seengerstrasse 1",
    "sg:city":"Tennwil",
    "sg:orig_category":"Kaminfeger",
    "sg:phone":"+41 71 944 19 41",
    "sg:postcode":"5617",
    "sg:province":"Aargau",
    "wof:name":"Thomas Holenstein Kaminfegergesch\u00e4ft",
    "wof:placetype":"venue"
},
  "geometry": {"coordinates":[9.1161050797,47.4755783081],"type":"Point"}
}