{
  "type": "Feature",
  "properties": {
    "iso:country":"CH",
    "sg:address":"Ebnetstrasse 64",
    "sg:city":"Horgen",
    "sg:classifiers":[
        {
            "category":"Manufacturing",
            "subcategory":"Glass & Minerals",
            "type":"Manufacturing & Wholesale Goods"
        }
    ],
    "sg:phone":"+41 17256217",
    "sg:postcode":"8810",
    "sg:province":"Z\u00fcrich",
    "sg:tags":[
        "machine",
        "tool",
        "working"
    ],
    "wof:name":"Glasfix Ag",
    "wof:placetype":"venue"
},
  "geometry": {"coordinates":[8.5902957916,47.25623703],"type":"Point"}
}