{
  "type": "Feature",
  "properties": {
    "iso:country":"CH",
    "sg:address":"Mitteldorfstrasse 21 6315 Ober\u00e4geri. Postfach 170",
    "sg:city":"Ober\u00e4geri",
    "sg:orig_category":"Sonderschulen Wohnheime f\u00fcr Kinder U Jugendliche",
    "sg:phone":"+41 41 750 16 35",
    "sg:postcode":"6315",
    "sg:province":"Zug",
    "wof:name":"Stiftung Tagesschule Erika",
    "wof:placetype":"venue"
},
  "geometry": {"coordinates":[8.6098833084,47.1364936829],"type":"Point"}
}