{
  "type": "Feature",
  "properties": {
    "iso:country":"CH",
    "sg:address":"Hubring 29 8303 Bassersdorf. Postfach",
    "sg:city":"Bassersdorf",
    "sg:orig_category":"Allgemeiner Hoch U Tiefbau",
    "sg:postcode":"8303",
    "sg:province":"Z\u00fcrich",
    "wof:name":"Sp\u00f6rri Dr. H., Generalunternehmung.",
    "wof:placetype":"venue"
},
  "geometry": {"coordinates":[8.635472,47.443336],"type":"Point"}
}