{
  "type": "Feature",
  "properties": {
    "iso:country":"CH",
    "sg:address":"1325",
    "sg:city":"Vaulion",
    "sg:orig_category":"Sessellifte and Skilifte",
    "sg:phone":"+41 32 926 70 84",
    "sg:postcode":"1325",
    "sg:province":"Vaud",
    "wof:name":"T\u00e9l\u00e9ski Du Chapeau-r\u00e2bl\u00e9",
    "wof:placetype":"venue"
},
  "geometry": {"coordinates":[6.8074121475,47.0981063843],"type":"Point"}
}