{
  "type": "Feature",
  "properties": {
    "iso:country":"CH",
    "sg:address":"Affolternstrasse 102 8050 Z\u00fcrich",
    "sg:city":"Zust",
    "sg:orig_category":"Finanzierungsinstitutionen",
    "sg:phone":"+41 22 310 52 06",
    "sg:postcode":"50",
    "wof:name":"Cb Capital Management Sa",
    "wof:placetype":"venue"
},
  "geometry": {"coordinates":[6.1496767998,46.2023887634],"type":"Point"}
}