{
  "type": "Feature",
  "properties": {
    "iso:country":"CH",
    "sg:address":"1914",
    "sg:city":"Is\u00e9rables",
    "sg:orig_category":"Herstellung von Konstruktionsteilen, Fertigbauteilen U Ausbauelementen aus Holz",
    "sg:phone":"+41 21 960 23 00",
    "sg:postcode":"1914",
    "sg:province":"Valais",
    "wof:name":"Gilli\u00e9ron Jean-claude",
    "wof:placetype":"venue"
},
  "geometry": {"coordinates":[6.9261350632,46.39818573],"type":"Point"}
}