{
  "type": "Feature",
  "properties": {
    "iso:country":"CH",
    "sg:address":"Unterdorfstrasse 7",
    "sg:city":"Utzenstorf",
    "sg:orig_category":"Nationale Postdienste",
    "sg:phone":"+41 32 665 38 05",
    "sg:postcode":"3427",
    "sg:province":"Bern",
    "wof:name":"Die Schweizerische Post",
    "wof:placetype":"venue"
},
  "geometry": {"coordinates":[7.5567498207,47.1371307373],"type":"Point"}
}