{
  "type": "Feature",
  "properties": {
    "iso:country":"CH",
    "sg:address":"Tiguelet Chemin Du 16",
    "sg:city":"Givisiez",
    "sg:orig_category":"Unclassifiable Establishments",
    "sg:postcode":"1762",
    "sg:province":"Fribourg",
    "wof:name":"A 3 Nature-power Gmbh",
    "wof:placetype":"venue"
},
  "geometry": {"coordinates":[7.6560149193,46.758140564],"type":"Point"}
}