{
  "type": "Feature",
  "properties": {
    "iso:country":"CH",
    "sg:address":"Viale Cattaneo 21",
    "sg:city":"Lugano",
    "sg:orig_category":"Unternehmensberatung",
    "sg:phone":"+41 91 912 22 22",
    "sg:postcode":"6900",
    "sg:province":"Ticino",
    "wof:name":"Arner Consulting Sa",
    "wof:placetype":"venue"
},
  "geometry": {"coordinates":[8.9595661163,46.0059242249],"type":"Point"}
}