{
  "type": "Feature",
  "properties": {
    "iso:country":"CH",
    "sg:address":"W\u00fcrzenbachhalde 14",
    "sg:city":"Luzern",
    "sg:orig_category":"Herstellung von Konstruktionsteilen, Fertigbauteilen U Ausbauelementen aus Holz",
    "sg:phone":"+41 41 370 31 86",
    "sg:postcode":"6006",
    "sg:province":"Luzern",
    "wof:name":"Fischer Anton Ag Luzern",
    "wof:placetype":"venue"
},
  "geometry": {"coordinates":[8.3511457443,47.0579414368],"type":"Point"}
}