{
  "type": "Feature",
  "properties": {
    "iso:country":"CH",
    "sg:address":"Dorfstrasse 14",
    "sg:city":"Basel",
    "sg:orig_category":"Detailhandel mit Zeitungen U Zeitschriften Kioske",
    "sg:phone":"+41 32 913 00 62",
    "sg:postcode":"4057",
    "sg:province":"Basel-Stadt",
    "wof:name":"Marcel Huguenin Kiosque Bois Du Petit Ch\u00e2teau",
    "wof:placetype":"venue"
},
  "geometry": {"coordinates":[6.8234767914,47.105178833],"type":"Point"}
}