{
  "type": "Feature",
  "properties": {
    "iso:country":"CH",
    "sg:address":"Blinzernfeldweg 17",
    "sg:city":"K\u00f6niz",
    "sg:orig_category":"Herstellung von Schmuck, Gold U Silberschmiedwaren Herstellung von sonstigen Metallwaren",
    "sg:phone":"+41 32 730 34 34",
    "sg:postcode":"3098",
    "sg:province":"Bern",
    "wof:name":"Huguenin & Kramer M\u00e9dailleurs Sa",
    "wof:placetype":"venue"
},
  "geometry": {"coordinates":[6.9081687927,46.9862136841],"type":"Point"}
}