{
  "type": "Feature",
  "properties": {
    "iso:country":"CH",
    "sg:address":"Oberfeld 6 6037 Root. Postfach 355",
    "sg:city":"Root",
    "sg:orig_category":"Herstellung von Automobilen",
    "sg:phone":"+41 41 455 00 40",
    "sg:postcode":"6037",
    "sg:province":"Luzern",
    "wof:name":"Krieger Tankfahrzeuge Ag",
    "wof:placetype":"venue"
},
  "geometry": {"coordinates":[8.3873319626,47.1118659973],"type":"Point"}
}