{
  "type": "Feature",
  "properties": {
    "iso:country":"CH",
    "sg:address":"En Segrin 1",
    "sg:city":"Cortaillod",
    "sg:orig_category":"Herstellung von Nahrungsmitteln undGetr\u00e4nken Herstellung von sonstigen Nahrungsmitteln",
    "sg:phone":"+41 32 842 64 42",
    "sg:postcode":"2016",
    "sg:province":"Neuch\u00e2tel",
    "wof:name":"Qualidess Sa",
    "wof:placetype":"venue"
},
  "geometry": {"coordinates":[6.8395881653,46.9406738281],"type":"Point"}
}