{
  "type": "Feature",
  "properties": {
    "iso:country":"CH",
    "sg:address":"Mutschellenstrasse 102",
    "sg:city":"Z\u00fcrich",
    "sg:orig_category":"Institutionen f\u00fcr Behinderte Sonderschulen",
    "sg:phone":"+41 14910747",
    "sg:postcode":"8038",
    "sg:province":"Z\u00fcrich",
    "wof:name":"Sonderschule Ringlikon Der Stadt Z\u00fcrich",
    "wof:placetype":"venue"
},
  "geometry": {"coordinates":[8.4740114212,47.3597335815],"type":"Point"}
}