{
  "type": "Feature",
  "properties": {
    "iso:country":"CH",
    "sg:address":"Sumpfstrasse 1",
    "sg:city":"Zug",
    "sg:classifiers":[
        {
            "category":"Wholesale",
            "subcategory":"Motor Vehicles",
            "type":"Manufacturing & Wholesale Goods"
        }
    ],
    "sg:phone":"+41 41 740 07 44",
    "sg:postcode":"6300",
    "sg:province":"Zug",
    "sg:tags":[
        "scooter"
    ],
    "wof:name":"Langenegger Italo-motos",
    "wof:placetype":"venue"
},
  "geometry": {"coordinates":[8.4909925461,47.186000824],"type":"Point"}
}