{
  "type": "Feature",
  "properties": {
    "iso:country":"CH",
    "sg:address":"Eigerplatz 3 3000 Bern. Postfach",
    "sg:city":"Bern",
    "sg:orig_category":"Unternehmensberatung",
    "sg:phone":"+41 31 321 87 87",
    "sg:postcode":"3007",
    "sg:province":"Bern",
    "wof:name":"Bahn + Bus Beratung Ag 3b Beratungsdienstleistungen F\u00fcr Den \u00f6ffentlichen Verkehr Usw",
    "wof:placetype":"venue"
},
  "geometry": {"coordinates":[7.4312901497,46.9412117004],"type":"Point"}
}