{
  "type": "Feature",
  "properties": {
    "iso:country":"CH",
    "sg:address":"Bahnhofstrasse 49",
    "sg:city":"Arbon",
    "sg:orig_category":"Drogerien Parf\u00fcmerien U sonstiger Detailhandel mit kosmetischen Artikeln U K\u00f6rperpflegemitteln",
    "sg:phone":"+41 71 446 40 90",
    "sg:postcode":"9320",
    "sg:province":"Thurgau",
    "wof:name":"Drogerie Suremann",
    "wof:placetype":"venue"
},
  "geometry": {"coordinates":[9.4338340759,47.5113601685],"type":"Point"}
}