{
  "type": "Feature",
  "properties": {
    "iso:country":"CH",
    "sg:address":"Kirchgasse 2 3860 Meiringen. Postfach 285",
    "sg:city":"Meiringen",
    "sg:orig_category":"Detailhandel mit Textilien",
    "sg:phone":"+41 33 971 15 08",
    "sg:postcode":"3860",
    "sg:province":"Bern",
    "wof:name":"Abplanalp & Frutiger Egglade",
    "wof:placetype":"venue"
},
  "geometry": {"coordinates":[8.1873931885,46.7275390625],"type":"Point"}
}