{
  "type": "Feature",
  "properties": {
    "iso:country":"CH",
    "sg:address":"Gr\u00fcntalstrasse 46",
    "sg:city":"Arbon",
    "sg:orig_category":"Unclassifiable Establishments",
    "sg:postcode":"9320",
    "sg:province":"Thurgau",
    "wof:name":"Arboner Taxi Gmbh",
    "wof:placetype":"venue"
},
  "geometry": {"coordinates":[9.4158372879,47.5055274963],"type":"Point"}
}