{
  "type": "Feature",
  "properties": {
    "addr:full":"Rue De Glarey 17 Sierre Valais 3960",
    "addr:housenumber":"17",
    "addr:postcode":"3960",
    "addr:street":"Rue De Glarey",
    "iso:country":"CH",
    "sg:address":"Rue De Glarey 17",
    "sg:city":"Sierre",
    "sg:orig_category":"Architektur U Ingenieurb\u00fcros",
    "sg:postcode":"3960",
    "sg:province":"Valais",
    "wof:name":"B\u00fctzberger Et Warpelin Bureaux D\u00ecng\u00e9nieurs Civils Et G\u00e9om\u00e8tres Offi-ciels",
    "wof:placetype":"venue"
},
  "geometry": {"coordinates":[7.541058,46.297768],"type":"Point"}
}