{
  "type": "Feature",
  "properties": {
    "iso:country":"CH",
    "sg:address":"Grossmatte-ost 24 6014 Littau. Postfach",
    "sg:city":"Littau",
    "sg:orig_category":"Herstellung von Schmuck, Gold U Silberschmiedwaren Herstellung von Schneidwaren U Bestecken",
    "sg:phone":"+41 41 259 21 21",
    "sg:postcode":"6014",
    "sg:province":"Luzern",
    "wof:name":"Berndorf Luzern Ag",
    "wof:placetype":"venue"
},
  "geometry": {"coordinates":[8.2703199387,47.0493774414],"type":"Point"}
}