{
  "type": "Feature",
  "properties": {
    "iso:country":"CH",
    "sg:address":"Fulenbacherstrasse 114",
    "sg:city":"Neuendorf",
    "sg:orig_category":"Detailhandel mit elektrischen Haushalts-,Radio U Fernsehger\u00e4ten sowie Musikinstrumenten",
    "sg:phone":"+41 62 398 16 61",
    "sg:postcode":"4623",
    "sg:province":"Solothurn",
    "wof:name":"Schaub Kuno Geigenbauer",
    "wof:placetype":"venue"
},
  "geometry": {"coordinates":[7.8010001183,47.2967681885],"type":"Point"}
}