{
  "type": "Feature",
  "properties": {
    "iso:country":"CH",
    "sg:address":"Via Campagna",
    "sg:city":"Bioggio",
    "sg:classifiers":[
        {
            "category":"Restaurant",
            "type":"Food & Drink"
        }
    ],
    "sg:phone":"+41 91 604 60 96",
    "sg:postcode":"6934",
    "sg:province":"Ticino",
    "wof:name":"Ristorante Centro Nord-sud",
    "wof:placetype":"venue"
},
  "geometry": {"coordinates":[8.9113054276,46.0094184875],"type":"Point"}
}