{
  "type": "Feature",
  "properties": {
    "iso:country":"CH",
    "sg:address":"St\u00e4blistrasse 9-11",
    "sg:city":"Z\u00fcrich",
    "sg:orig_category":"Kauf U Verkauf von Immobilien auf eigene Rechnung Verwaltung von Immobilien",
    "sg:phone":"+41 13630046",
    "sg:postcode":"8000",
    "sg:province":"Z\u00fcrich",
    "wof:name":"Fluri Immobilien- & Verwaltungs Ag, Zweigniederlassung Z\u00fcrich",
    "wof:placetype":"venue"
},
  "geometry": {"coordinates":[8.5493602753,47.3837661743],"type":"Point"}
}