{
  "type": "Feature",
  "properties": {
    "iso:country":"CH",
    "sg:address":"Marktgass-passage 3 3011 Bern. Postfach",
    "sg:city":"Bern",
    "sg:orig_category":"Interessenvertretungen",
    "sg:postcode":"3005",
    "sg:province":"Bern",
    "wof:name":"Wartmann-stiftung F\u00fcr Die Kinderheilst\u00e4tte Bad Sonder",
    "wof:placetype":"venue"
},
  "geometry": {"coordinates":[9.3938531876,47.4461021423],"type":"Point"}
}