{
  "type": "Feature",
  "properties": {
    "addr:full":"Kirchstrasse 3 Horgen Z\u00fcrich 8810",
    "addr:housenumber":"3",
    "addr:postcode":"8810",
    "addr:street":"Kirchstrasse",
    "iso:country":"CH",
    "sg:address":"Kirchstrasse 3",
    "sg:city":"Horgen",
    "sg:classifiers":[
        {
            "category":"Home & Garden",
            "subcategory":"Household Appliances",
            "type":"Retail Goods"
        }
    ],
    "sg:phone":"+41 17257581",
    "sg:postcode":"8810",
    "sg:province":"Z\u00fcrich",
    "sg:tags":[
        "sanitary",
        "fitting"
    ],
    "wof:name":"Hauser Instaplan Gmbh",
    "wof:placetype":"venue"
},
  "geometry": {"coordinates":[8.598529,47.260986],"type":"Point"}
}