{
  "type": "Feature",
  "properties": {
    "iso:country":"CH",
    "sg:address":"Bachstrasse 6",
    "sg:city":"M\u00f6hlin",
    "sg:orig_category":"Nationale Postdienste",
    "sg:phone":"+41 61 851 21 51",
    "sg:postcode":"4313",
    "sg:province":"Aargau",
    "wof:name":"Die Schweizerische Post",
    "wof:placetype":"venue"
},
  "geometry": {"coordinates":[7.8423581123,47.5600585938],"type":"Point"}
}