{
  "type": "Feature",
  "properties": {
    "iso:country":"CH",
    "sg:address":"Freiestrasse 14",
    "sg:city":"Amriswil",
    "sg:orig_category":"Unternehmensberatung Wirtschaftspr\u00fcfung, Steuerberatung U Treuhand",
    "sg:postcode":"8580",
    "sg:province":"Thurgau",
    "wof:name":"Kleeb & Partner Wirtschaftstr. & Unternehmensberatung Ag",
    "wof:placetype":"venue"
},
  "geometry": {"coordinates":[9.3006296158,47.5484619141],"type":"Point"}
}