{
  "type": "Feature",
  "properties": {
    "iso:country":"CH",
    "sg:address":"Ruhtalstrasse 12 8400 Winterthur. Postfach 418",
    "sg:city":"Winterthur",
    "sg:orig_category":"Detailhandel mit Damenbekleidung",
    "sg:phone":"+41 52 213 19 28",
    "sg:postcode":"8402",
    "sg:province":"Z\u00fcrich",
    "wof:name":"Alois & Trudy Klein Dirndl-mode",
    "wof:placetype":"venue"
},
  "geometry": {"coordinates":[8.724401,47.504345],"type":"Point"}
}