{
  "type": "Feature",
  "properties": {
    "addr:full":"D\u00e4ttnauerstrasse 22 Winterthur Z\u00fcrich 8406",
    "addr:housenumber":"22",
    "addr:postcode":"8406",
    "addr:street":"Daettnauerstrasse",
    "iso:country":"CH",
    "sg:address":"D\u00e4ttnauerstrasse 22",
    "sg:city":"Winterthur",
    "sg:orig_category":"Autogaragen",
    "sg:phone":"+41 81 410 13 10",
    "sg:postcode":"8406",
    "sg:province":"Z\u00fcrich",
    "wof:name":"Walter Gruber Garage",
    "wof:placetype":"venue"
},
  "geometry": {"coordinates":[9.853965,46.825134],"type":"Point"}
}