{
  "type": "Feature",
  "properties": {
    "iso:country":"CH",
    "sg:address":"M\u00fchlestr. 25",
    "sg:city":"B\u00e4ttwil",
    "sg:orig_category":"Ausbaugewerbe",
    "sg:postcode":"4112",
    "sg:province":"Solothurn",
    "wof:name":"Bernasconi Arno.",
    "wof:placetype":"venue"
},
  "geometry": {"coordinates":[7.50817,47.489658],"type":"Point"}
}