{
  "type": "Feature",
  "properties": {
    "iso:country":"CH",
    "sg:address":"Obere B\u00fcschenstrasse 4 9000 St.gallen. Postfach",
    "sg:city":"Oberwinterthur",
    "sg:orig_category":"Finanzierungsinstitutionen Sonstiges Versicherungsgewerbe",
    "sg:phone":"+41 52 320 90 80",
    "sg:postcode":"8404",
    "sg:province":"Z\u00fcrich",
    "wof:name":"Home Promotion Ag Versicherungs- U. Finanzgesch\u00e4fte; Vermittlung Usw",
    "wof:placetype":"venue"
},
  "geometry": {"coordinates":[9.379907608,47.4245681763],"type":"Point"}
}