{
  "type": "Feature",
  "properties": {
    "iso:country":"CH",
    "sg:address":"Weberm\u00fchle 11",
    "sg:city":"Neuenhof",
    "sg:orig_category":"Detailhandel mit Waren verschiedener Art, Hauptrichtung Nahrungsmittel Grosshandel mit Nahrungsmitte",
    "sg:phone":"+41 56 406 60 11",
    "sg:postcode":"5432",
    "sg:province":"Aargau",
    "wof:name":"Jawad Ali Lebensmittel",
    "wof:placetype":"venue"
},
  "geometry": {"coordinates":[8.3268165588,47.4499435425],"type":"Point"}
}