{
  "type": "Feature",
  "properties": {
    "iso:country":"CH",
    "sg:address":"Bergstrasse 6",
    "sg:city":"Herisau",
    "sg:orig_category":"Vereine Radio, Film and Foto",
    "sg:phone":"+41 71 352 29 61",
    "sg:postcode":"9100",
    "sg:province":"Appenzell Ausserrhoden",
    "wof:name":"Photo-klub St.gallen",
    "wof:placetype":"venue"
},
  "geometry": {"coordinates":[9.2809333801,47.3841667175],"type":"Point"}
}