{
  "type": "Feature",
  "properties": {
    "iso:country":"CH",
    "sg:address":"H\u00f6henweg 2",
    "sg:city":"Schindellegi",
    "sg:orig_category":"Herstellung von Betonerzeugnissen f\u00fcr den Bau Herstellung von Transportbeton",
    "sg:phone":"+41 17840147",
    "sg:postcode":"8834",
    "sg:province":"Schwyz",
    "wof:name":"Minder Beton Ag",
    "wof:placetype":"venue"
},
  "geometry": {"coordinates":[8.7130908966,47.1739807129],"type":"Point"}
}