{
  "type": "Feature",
  "properties": {
    "iso:country":"CH",
    "sg:address":"Prieur\u00e9 Rue Du 32 1202 Gen\u00e8ve. Postfach",
    "sg:city":"Gen\u00e8ve",
    "sg:orig_category":"Herstellung von sonstigen elektrischen Ausr\u00fcstungen",
    "sg:postcode":"1202",
    "sg:province":"Gen\u00e8ve",
    "wof:name":"Electro Radical Ag",
    "wof:placetype":"venue"
},
  "geometry": {"coordinates":[7.3597769737,47.1806221008],"type":"Point"}
}