{
  "type": "Feature",
  "properties": {
    "iso:country":"CH",
    "sg:address":"Freimettigenstrasse 1",
    "sg:city":"Oberdiessbach",
    "sg:orig_category":"Handel mit Motorr\u00e4dern, Teilen U Zubeh\u00f6r Instandhaltung U Reparatur von Motorr\u00e4dern",
    "sg:phone":"+41 31 771 17 75",
    "sg:postcode":"3672",
    "sg:province":"Bern",
    "wof:name":"Erich Segessenmann Velos-motos",
    "wof:placetype":"venue"
},
  "geometry": {"coordinates":[7.6193399429,46.8408355713],"type":"Point"}
}