{
  "type": "Feature",
  "properties": {
    "iso:country":"CH",
    "sg:address":"Ackerweg 6",
    "sg:city":"Vilters",
    "sg:orig_category":"Reinigungsgewerbe",
    "sg:phone":"+41 81 723 69 93",
    "sg:postcode":"7324",
    "sg:province":"St. Gallen",
    "wof:name":"Guntli-kunz Emma",
    "wof:placetype":"venue"
},
  "geometry": {"coordinates":[9.4516687393,47.0246124268],"type":"Point"}
}