{
  "type": "Feature",
  "properties": {
    "iso:country":"CH",
    "sg:address":"Maggio Via 1 6900 Lugano. Postfach",
    "sg:city":"Calprino",
    "sg:orig_category":"Werbung",
    "sg:phone":"+41 61 713 11 90",
    "sg:postcode":"6900",
    "sg:province":"Ticino",
    "wof:name":"Conmedia Ag",
    "wof:placetype":"venue"
},
  "geometry": {"coordinates":[7.5160589218,47.4011383057],"type":"Point"}
}