{
  "type": "Feature",
  "properties": {
    "iso:country":"CH",
    "sg:address":"1742",
    "sg:city":"Autigny",
    "sg:orig_category":"Haltung von Rindern",
    "sg:postcode":"1742",
    "sg:province":"Fribourg",
    "wof:name":"Syndicat D'\u00e9levage De La Race Tachet\u00e9e Rouge D'autigny-ch\u00e9nens",
    "wof:placetype":"venue"
},
  "geometry": {"coordinates":[7.0183601379,46.7365837097],"type":"Point"}
}