{
  "type": "Feature",
  "properties": {
    "iso:country":"CH",
    "sg:address":"Hofj\u00fcngerstrasse 24 9630 Wattwil. Postfach",
    "sg:city":"Wattwil",
    "sg:orig_category":"Erdbewegungsarbeiten Vermietung U Verpachtung von eigenen Immobilien",
    "sg:phone":"+41 71 988 39 22",
    "sg:postcode":"9630",
    "sg:province":"St. Gallen",
    "wof:name":"Weber E. & Co",
    "wof:placetype":"venue"
},
  "geometry": {"coordinates":[9.0863075256,47.3059272766],"type":"Point"}
}