{
  "type": "Feature",
  "properties": {
    "iso:country":"CH",
    "sg:address":"Schweinbrunnen",
    "sg:city":"Huttwil",
    "sg:orig_category":"Maschinen-Fabrikation",
    "sg:postcode":"4950",
    "sg:province":"Bern",
    "wof:name":"W. Baumann",
    "wof:placetype":"venue"
},
  "geometry": {"coordinates":[7.8096737862,47.1009101868],"type":"Point"}
}