{
  "type": "Feature",
  "properties": {
    "iso:country":"CH",
    "sg:address":"Rue De Gravelone 47",
    "sg:city":"Sion",
    "sg:orig_category":"Architekturb\u00fcros",
    "sg:phone":"+41 27 322 41 52",
    "sg:postcode":"1950",
    "sg:province":"Valais",
    "wof:name":"Renaud Rouvinez Bureau D'architecture",
    "wof:placetype":"venue"
},
  "geometry": {"coordinates":[7.352744,46.234722],"type":"Point"}
}