{
  "type": "Feature",
  "properties": {
    "iso:country":"CH",
    "sg:address":"Rue Du Cardinal-journet 43 1217 Meyrin. Postfach",
    "sg:city":"Meyrin",
    "sg:orig_category":"RESTAURANTS: TEA-ROOMS",
    "sg:postcode":"1217",
    "sg:province":"Gen\u00e8ve",
    "wof:name":"Spirito G. & De Nuccio M.",
    "wof:placetype":"venue"
},
  "geometry": {"coordinates":[6.0806450844,46.2259101868],"type":"Point"}
}