{
  "type": "Feature",
  "properties": {
    "iso:country":"CH",
    "sg:address":"Sonnhaldenstrasse 16",
    "sg:city":"Balterswil",
    "sg:classifiers":[
        {
            "category":"Home & Garden",
            "subcategory":"Carpets & Floor Coverings",
            "type":"Retail Goods"
        }
    ],
    "sg:phone":"+41 71 970 01 48",
    "sg:postcode":"8362",
    "sg:province":"Thurgau",
    "wof:name":"Riwatech Gmbh",
    "wof:placetype":"venue"
},
  "geometry": {"coordinates":[8.9337110519,47.4519615173],"type":"Point"}
}