{
  "type": "Feature",
  "properties": {
    "addr:full":"Dorfstrasse 18 Wauwil Luzern 6242",
    "addr:housenumber":"18",
    "addr:postcode":"6242",
    "addr:street":"Dorfstrasse",
    "iso:country":"CH",
    "sg:address":"Dorfstrasse 18",
    "sg:city":"Wauwil",
    "sg:orig_category":"Arztpraxen Physiotherapie",
    "sg:phone":"+41 41 980 55 55",
    "sg:postcode":"6242",
    "sg:province":"Luzern",
    "wof:name":"Dr.med.gerhard Klein Arzt F.allgemeine Medizin Fmh",
    "wof:placetype":"venue"
},
  "geometry": {"coordinates":[8.01751,47.185036],"type":"Point"}
}