{
  "type": "Feature",
  "properties": {
    "iso:country":"CH",
    "sg:address":"6830 Chiasso. Postfach Caselle Postale 234",
    "sg:city":"Chiasso",
    "sg:orig_category":"Sportvereine Eissport Eishockey",
    "sg:phone":"+41 91 683 77 29",
    "sg:postcode":"6830",
    "sg:province":"Ticino",
    "wof:name":"Hockey-club Chiasso",
    "wof:placetype":"venue"
},
  "geometry": {"coordinates":[9.0249595642,45.8330001831],"type":"Point"}
}