{
  "type": "Feature",
  "properties": {
    "iso:country":"CH",
    "sg:address":"Sandrainstrasse 2",
    "sg:city":"Bern",
    "sg:orig_category":"Maurerarbeiten Sonstiger spezialisierter Hoch U Tiefbau",
    "sg:phone":"+41 31 372 60 60",
    "sg:postcode":"3007",
    "sg:province":"Bern",
    "wof:name":"Maurergesch\u00e4ft Pauli & Co",
    "wof:placetype":"venue"
},
  "geometry": {"coordinates":[7.4414730072,46.940536499],"type":"Point"}
}