{
  "type": "Feature",
  "properties": {
    "iso:country":"CH",
    "sg:address":"Friedbergstrasse 17",
    "sg:city":"Thundorf",
    "sg:orig_category":"Fahrschulen, Flugschulen",
    "sg:phone":"+41 52 376 33 17",
    "sg:postcode":"8512",
    "sg:province":"Thurgau",
    "wof:name":"Ursula Zurlinden Autofahrschule",
    "wof:placetype":"venue"
},
  "geometry": {"coordinates":[8.9643554688,47.5487632751],"type":"Point"}
}