{
  "type": "Feature",
  "properties": {
    "iso:country":"CH",
    "sg:address":"Bahnhofstrasse 6 8302 Kloten. Postfach",
    "sg:city":"Kloten",
    "sg:orig_category":"W\u00e4scherei U chemische Reinigung",
    "sg:postcode":"8302",
    "sg:province":"Z\u00fcrich",
    "wof:name":"Cleanothek Gmbh Textilien; Reinigung. Reinigungsmittel, Waren; Handel",
    "wof:placetype":"venue"
},
  "geometry": {"coordinates":[8.5826787949,47.4490737915],"type":"Point"}
}