{
  "type": "Feature",
  "properties": {
    "iso:country":"CH",
    "sg:address":"Amp\u00e8restrasse 3",
    "sg:city":"Steinach",
    "sg:orig_category":"Markt U Meinungsforschung",
    "sg:postcode":"9323",
    "sg:province":"St. Gallen",
    "wof:name":"Amp International Enterprises Ltd, Wilmington, Zweigniederlassung Steinach",
    "wof:placetype":"venue"
},
  "geometry": {"coordinates":[9.4477910995,47.4996490479],"type":"Point"}
}