{
  "type": "Feature",
  "properties": {
    "iso:country":"CH",
    "sg:address":"Pr\u00e9 Laurent 167",
    "sg:city":"Plagne",
    "sg:orig_category":"Stukkateurgewerbe, Gipserei U Verputzerei Tapeziererei",
    "sg:phone":"+41 79 209 32 21",
    "sg:postcode":"2536",
    "sg:province":"Bern",
    "wof:name":"Theo Sterk Peinture & Gypserie",
    "wof:placetype":"venue"
},
  "geometry": {"coordinates":[7.2781338692,47.1922798157],"type":"Point"}
}