{
  "type": "Feature",
  "properties": {
    "iso:country":"CH",
    "sg:address":"Ennetb\u00fcrgerstrasse 12",
    "sg:city":"Buochs",
    "sg:orig_category":"Fernmeldedienste",
    "sg:postcode":"6374",
    "sg:province":"Nidwalden",
    "wof:name":"Frey + Cie. Telecom Ag",
    "wof:placetype":"venue"
},
  "geometry": {"coordinates":[8.4197778702,46.9752998352],"type":"Point"}
}