{
  "type": "Feature",
  "properties": {
    "iso:country":"CH",
    "sg:address":"9214 Kradolf. Postfach 156",
    "sg:city":"Kradolf",
    "sg:orig_category":"Sportvereine Ballsport Fussball",
    "sg:postcode":"9214",
    "sg:province":"Thurgau",
    "wof:name":"Fc Kradolf-sch\u00f6nenberg",
    "wof:placetype":"venue"
},
  "geometry": {"coordinates":[9.2017002106,47.5242195129],"type":"Point"}
}