{
  "type": "Feature",
  "properties": {
    "iso:country":"CH",
    "sg:address":"Rosenstrasse 6 9240 Uzwil. Postfach",
    "sg:city":"Henau",
    "sg:orig_category":"Architektur U Ingenieurb\u00fcros Architekturb\u00fcros",
    "sg:phone":"+41 31 932 52 52",
    "sg:postcode":"9247",
    "sg:province":"St. Gallen",
    "wof:name":"Donum Architekten Ag",
    "wof:placetype":"venue"
},
  "geometry": {"coordinates":[7.478002,46.955467],"type":"Point"}
}