{
  "type": "Feature",
  "properties": {
    "iso:country":"CH",
    "sg:address":"Aarauerstrasse 34",
    "sg:city":"Biberstein",
    "sg:orig_category":"Sportvereine Ballsport Handball",
    "sg:postcode":"5023",
    "sg:province":"Aargau",
    "wof:name":"Sc Damm Aarau",
    "wof:placetype":"venue"
},
  "geometry": {"coordinates":[8.0732946396,47.4119720459],"type":"Point"}
}