{
  "type": "Feature",
  "properties": {
    "iso:country":"CH",
    "sg:address":"Rue De L'oyonne 6",
    "sg:city":"Vevey",
    "sg:orig_category":"Physiotherapie",
    "sg:phone":"+41 21 944 35 40",
    "sg:postcode":"1800",
    "sg:province":"Vaud",
    "wof:name":"Annemarie Mussitelli Physioth\u00e9rapie",
    "wof:placetype":"venue"
},
  "geometry": {"coordinates":[6.8387122154,46.4650115967],"type":"Point"}
}