{
  "type": "Feature",
  "properties": {
    "iso:country":"CH",
    "sg:address":"3618",
    "sg:city":"S\u00fcderen",
    "sg:orig_category":"Schulpflegen",
    "sg:phone":"+41 61 766 17 17",
    "sg:postcode":"3618",
    "sg:province":"Bern",
    "wof:name":"Primarschulkommission Der Gemeinde Wahlen Bei Laufen",
    "wof:placetype":"venue"
},
  "geometry": {"coordinates":[7.5154800415,47.4013595581],"type":"Point"}
}