{
  "type": "Feature",
  "properties": {
    "iso:country":"CH",
    "sg:address":"Avenue A.-m.-mirany 19",
    "sg:city":"Ch\u00eane-bourg",
    "sg:orig_category":"Grosshandel mit Radio U Fernsehger\u00e4ten Herstellung von elektronischen Bauelementen",
    "sg:phone":"+41 57229022",
    "sg:postcode":"1225",
    "sg:province":"Gen\u00e8ve",
    "wof:name":"Paniz Adriano A & C Electronic",
    "wof:placetype":"venue"
},
  "geometry": {"coordinates":[8.2990245819,47.3741455078],"type":"Point"}
}