{
  "type": "Feature",
  "properties": {
    "addr:full":"Dorfmattenstrasse 3 Escholzmatt Luzern 6182",
    "addr:housenumber":"3",
    "addr:postcode":"6182",
    "addr:street":"Dorfmattenstrasse",
    "iso:country":"CH",
    "sg:address":"Dorfmattenstrasse 3",
    "sg:city":"Escholzmatt",
    "sg:orig_category":"Bau U Wohngenossenschaften",
    "sg:postcode":"6182",
    "sg:province":"Luzern",
    "wof:name":"Genossenschaft F\u00fcr Wohnungsbau Escholzmatt Gwe",
    "wof:placetype":"venue"
},
  "geometry": {"coordinates":[7.934199,46.915035],"type":"Point"}
}