{
  "type": "Feature",
  "properties": {
    "iso:country":"CH",
    "sg:address":"Flurstrasse 41",
    "sg:city":"Hagendorn",
    "sg:orig_category":"Bauschreinerei Herstellung von Konstruktionsteilen, Fertigbauteilen U Ausbauelementen aus Holz",
    "sg:phone":"+41 41 785 85 85",
    "sg:postcode":"6332",
    "sg:province":"Zug",
    "wof:name":"Baumgartner G. Ag",
    "wof:placetype":"venue"
},
  "geometry": {"coordinates":[8.429201,47.202351],"type":"Point"}
}