{
  "type": "Feature",
  "properties": {
    "iso:country":"CH",
    "sg:address":"Hauptstrasse 61 2560 Nidau. Postfach 413",
    "sg:city":"Nidau",
    "sg:orig_category":"Detailhandel mit medizinischen U orthop\u00e4dischen Artikeln Herstellung von medizinischen U chirurgisch",
    "sg:phone":"+41 32 331 61 21",
    "sg:postcode":"2560",
    "sg:province":"Bern",
    "wof:name":"Rindlisbacher Kurt Ag, Schuhreparatur Und Orthop\u00e4die",
    "wof:placetype":"venue"
},
  "geometry": {"coordinates":[7.2409682274,47.1249198914],"type":"Point"}
}