{
  "type": "Feature",
  "properties": {
    "iso:country":"CH",
    "sg:address":"Grellingerstrasse 48",
    "sg:city":"Basel",
    "sg:orig_category":"Chemische Reinigung",
    "sg:phone":"+41 61 311 20 81",
    "sg:postcode":"4052",
    "sg:province":"Basel-Stadt",
    "wof:name":"Yvonne Bennewitz Chem.reinigung Pressing",
    "wof:placetype":"venue"
},
  "geometry": {"coordinates":[7.606003,47.549435],"type":"Point"}
}