{
  "type": "Feature",
  "properties": {
    "iso:country":"CH",
    "sg:address":"Untere Grabenstrasse 32",
    "sg:city":"Zofingen",
    "sg:orig_category":"Nationale Postdienste",
    "sg:phone":"+41 62 751 18 83",
    "sg:postcode":"4800",
    "sg:province":"Aargau",
    "wof:name":"Die Schweizerische Post",
    "wof:placetype":"venue"
},
  "geometry": {"coordinates":[7.9435801506,47.2874984741],"type":"Point"}
}