{
  "type": "Feature",
  "properties": {
    "iso:country":"CH",
    "sg:address":"Baslerstrasse 9 4710 Balsthal. Postfach 243",
    "sg:city":"Balsthal",
    "sg:orig_category":"Instandhaltung U Reparatur von Automobilen",
    "sg:phone":"+41 62 391 34 44",
    "sg:postcode":"4710",
    "sg:province":"Solothurn",
    "wof:name":"Garage Kreuchi Ag",
    "wof:placetype":"venue"
},
  "geometry": {"coordinates":[7.7024722099,47.3161773682],"type":"Point"}
}