{
  "type": "Feature",
  "properties": {
    "iso:country":"CH",
    "sg:address":"Worblentalstrasse 58",
    "sg:city":"Ittigen",
    "sg:orig_category":"Detailhandel mit Fahrr\u00e4dern Handel mit Motorr\u00e4dern, Teilen U Zubeh\u00f6r Instandhaltung U Reparatur von ",
    "sg:phone":"+41 31 921 00 92",
    "sg:postcode":"3063",
    "sg:province":"Bern",
    "wof:name":"Christian Hubacher Velos-motos",
    "wof:placetype":"venue"
},
  "geometry": {"coordinates":[7.4775238037,46.9744491577],"type":"Point"}
}