{
  "type": "Feature",
  "properties": {
    "iso:country":"CH",
    "sg:address":"Metallstrasse 18",
    "sg:city":"St.gallen",
    "sg:orig_category":"Grosshandel mit Wasch U Reinigungsmitteln Grosshandel mit elektrischen Haushaltsger\u00e4ten",
    "sg:phone":"+41 71 277 28 32",
    "sg:postcode":"9000",
    "sg:province":"St. Gallen",
    "wof:name":"Diverseylever Ag",
    "wof:placetype":"venue"
},
  "geometry": {"coordinates":[9.3547420502,47.42004776],"type":"Point"}
}