{
  "type": "Feature",
  "properties": {
    "iso:country":"CH",
    "sg:address":"Hauptstrasse 212",
    "sg:city":"Orpund",
    "sg:orig_category":"Drogerien Sonstiger Fachdetailhandel mit Nahrungsmitteln, Getr\u00e4nken U Tabak in Verkaufsr\u00e4umen",
    "sg:phone":"+41 71 278 26 23",
    "sg:postcode":"2552",
    "sg:province":"Bern",
    "wof:name":"Lachen Drogerie Linsi Mathias",
    "wof:placetype":"venue"
},
  "geometry": {"coordinates":[9.355307579,47.4197273254],"type":"Point"}
}