{
  "type": "Feature",
  "properties": {
    "iso:country":"CH",
    "sg:address":"Rue De L'h\u00f4tel-de-ville 12 1470 Estavayer-le-lac. Postfach",
    "sg:city":"Estavayer-le-lac",
    "sg:orig_category":"Herstellung von elektrischen Ausr\u00fcstungen f\u00fcr Motoren U Fahrzeuge",
    "sg:phone":"+41 52 741 41 70",
    "sg:postcode":"1470",
    "sg:province":"Fribourg",
    "wof:name":"Bomot-boothandels Ag",
    "wof:placetype":"venue"
},
  "geometry": {"coordinates":[8.8545799255,47.6536598206],"type":"Point"}
}