{
  "type": "Feature",
  "properties": {
    "iso:country":"CH",
    "sg:address":"Landstrasse 81 5430 Wettingen. Postfach 21",
    "sg:city":"Wettingen",
    "sg:orig_category":"Technische, physikalische U chemische Untersuchung",
    "sg:postcode":"5430",
    "sg:province":"Aargau",
    "wof:name":"Zenteco Ag",
    "wof:placetype":"venue"
},
  "geometry": {"coordinates":[8.3254585266,47.4665222168],"type":"Point"}
}