{
  "type": "Feature",
  "properties": {
    "iso:country":"CH",
    "sg:address":"Forchstrasse 50 8008 Z\u00fcrich. Postfach",
    "sg:city":"Z\u00fcrich",
    "sg:orig_category":"Non-Classified Establishments",
    "sg:postcode":"8001",
    "sg:province":"Z\u00fcrich",
    "wof:name":"Multimedia, Louvrier G. Et Cie.",
    "wof:placetype":"venue"
},
  "geometry": {"coordinates":[6.1387882233,46.1829071045],"type":"Point"}
}