{
  "type": "Feature",
  "properties": {
    "iso:country":"CH",
    "sg:address":"Bahnhofstrasse 3a",
    "sg:city":"Sevelen",
    "sg:orig_category":"P\u00e9dicure",
    "sg:phone":"+41 81 785 27 14",
    "sg:postcode":"9475",
    "sg:province":"St. Gallen",
    "wof:name":"Mona Donatz",
    "wof:placetype":"venue"
},
  "geometry": {"coordinates":[9.4931726456,47.1241569519],"type":"Point"}
}