{
  "type": "Feature",
  "properties": {
    "iso:country":"CH",
    "sg:address":"Stegreutiweg 2a",
    "sg:city":"M\u00fcnsingen",
    "sg:orig_category":"Unclassifiable Establishments",
    "sg:postcode":"3110",
    "sg:province":"Bern",
    "wof:name":"Tschanz Public Relations",
    "wof:placetype":"venue"
},
  "geometry": {"coordinates":[7.5490179062,46.8705253601],"type":"Point"}
}