{
  "type": "Feature",
  "properties": {
    "iso:country":"CH",
    "sg:address":"Heideweg 19 2500 Biel/bienne. Postfach",
    "sg:city":"Biel/bienne",
    "sg:orig_category":"Herstellung von Uhren",
    "sg:postcode":"2503",
    "sg:province":"Bern",
    "wof:name":"Roth Thomas",
    "wof:placetype":"venue"
},
  "geometry": {"coordinates":[7.2548251152,47.1265792847],"type":"Point"}
}