{
  "type": "Feature",
  "properties": {
    "iso:country":"CH",
    "sg:address":"Kirschgartenstrasse 9",
    "sg:city":"Muttenz",
    "sg:orig_category":"Sonstige mit der Informatik verbundene T\u00e4tigkeiten",
    "sg:postcode":"4132",
    "sg:province":"Basel-Landschaft",
    "wof:name":"Ineco C. Pinto",
    "wof:placetype":"venue"
},
  "geometry": {"coordinates":[7.6481127739,47.5303535461],"type":"Point"}
}