{
  "type": "Feature",
  "properties": {
    "iso:country":"CH",
    "sg:address":"M\u00fchlebachstrasse 2 8008 Z\u00fcrich. Postfach 22",
    "sg:city":"Z\u00fcrich",
    "sg:orig_category":"Wirtschaftspr\u00fcfung, Steuerberatung U Treuhand",
    "sg:phone":"+41 12682525",
    "sg:postcode":"8024",
    "sg:province":"Z\u00fcrich",
    "wof:name":"Weber, Schaub & Partner Steuer, Rechtsberatung",
    "wof:placetype":"venue"
},
  "geometry": {"coordinates":[8.5490970612,47.3659286499],"type":"Point"}
}