{
  "type": "Feature",
  "properties": {
    "iso:country":"CH",
    "sg:address":"Schaffhauserstrasse 11",
    "sg:city":"Glattbrugg",
    "sg:orig_category":"Softwareentwicklung U beratung",
    "sg:postcode":"8152",
    "sg:province":"Z\u00fcrich",
    "wof:name":"Originate Software Gmbh",
    "wof:placetype":"venue"
},
  "geometry": {"coordinates":[8.5579786301,47.4286613464],"type":"Point"}
}