{
  "type": "Feature",
  "properties": {
    "iso:country":"CH",
    "sg:address":"Chemin Edouard-tavan 7",
    "sg:city":"Gen\u00e8ve",
    "sg:orig_category":"Sportvereine Ballsport Tennis",
    "sg:postcode":"1206",
    "sg:province":"Gen\u00e8ve",
    "wof:name":"Tennis-club Universitaire",
    "wof:placetype":"venue"
},
  "geometry": {"coordinates":[6.1584200859,46.1854400635],"type":"Point"}
}