{
  "type": "Feature",
  "properties": {
    "iso:country":"CH",
    "sg:address":"Rue Du Four 8",
    "sg:city":"Estavayer-le-lac",
    "sg:orig_category":"Detailhandel mit Getr\u00e4nken Grosshandel mit Wein U Spirituosen",
    "sg:phone":"+41 79 635 14 03",
    "sg:postcode":"1470",
    "sg:province":"Fribourg",
    "wof:name":"Gabriel Dettwiler",
    "wof:placetype":"venue"
},
  "geometry": {"coordinates":[6.8479628563,46.8500709534],"type":"Point"}
}