{
  "type": "Feature",
  "properties": {
    "iso:country":"CH",
    "sg:address":"Viaduc Chemin Du 10 1008 Prilly. Postfach",
    "sg:city":"Prilly",
    "sg:orig_category":"Grosshandel mit Nahrungsmitteln, Getr\u00e4nken U Tabakwaren ohne ausgepr\u00e4gten Schwerpunkt",
    "sg:postcode":"1008",
    "sg:province":"Vaud",
    "wof:name":"Jesus Carmona",
    "wof:placetype":"venue"
},
  "geometry": {"coordinates":[6.6061439514,46.5340614319],"type":"Point"}
}