{
  "type": "Feature",
  "properties": {
    "iso:country":"CH",
    "sg:address":"Route De Peney 48",
    "sg:city":"Vernier",
    "sg:orig_category":"Autospenglereien",
    "sg:phone":"+41 22 930 01 00",
    "sg:postcode":"1214",
    "sg:province":"Gen\u00e8ve",
    "wof:name":"Cars Line Carosserie",
    "wof:placetype":"venue"
},
  "geometry": {"coordinates":[6.07603,46.210846],"type":"Point"}
}