{
  "type": "Feature",
  "properties": {
    "iso:country":"CH",
    "sg:address":"Sierenzerstrasse 77",
    "sg:city":"Basel",
    "sg:orig_category":"Malerei",
    "sg:phone":"+41 61 302 65 22",
    "sg:postcode":"4055",
    "sg:province":"Basel-Stadt",
    "wof:name":"Anton Sacher Malergesch\u00e4ft",
    "wof:placetype":"venue"
},
  "geometry": {"coordinates":[7.5681881905,47.5578651428],"type":"Point"}
}