{
  "type": "Feature",
  "properties": {
    "iso:country":"CH",
    "sg:address":"4410",
    "sg:city":"Liestal",
    "sg:orig_category":"Vorschulen, Kinderg\u00e4rten",
    "sg:postcode":"4410",
    "sg:province":"Basel-Landschaft",
    "wof:name":"Kindergarten Weihermatt I & Ii",
    "wof:placetype":"venue"
},
  "geometry": {"coordinates":[8.2035999298,47.4864692688],"type":"Point"}
}