{
  "type": "Feature",
  "properties": {
    "addr:full":"Coulouvreni\u00e8re Rue De La 23 1200 Genf. Postfach Gen\u00e8ve Gen\u00e8ve 1201",
    "addr:housenumber":"coulouvrenie\u0300re;23",
    "addr:postcode":"1200 genf. postfach;1201",
    "addr:street":"Rue De La",
    "iso:country":"CH",
    "sg:address":"Coulouvreni\u00e8re Rue De La 23 1200 Genf. Postfach",
    "sg:city":"Gen\u00e8ve",
    "sg:orig_category":"Detailhandel mit B\u00fcchern, Zeitungen, Schreib U Papeteriewaren",
    "sg:phone":"+41 22 321 45 82",
    "sg:postcode":"1201",
    "sg:province":"Gen\u00e8ve",
    "wof:name":"Rooarr Kiosque S\u00e0rl",
    "wof:placetype":"venue"
},
  "geometry": {"coordinates":[6.142701,46.208359],"type":"Point"}
}