{
  "type": "Feature",
  "properties": {
    "iso:country":"CH",
    "sg:address":"Seestrasse 77",
    "sg:city":"Horn",
    "sg:orig_category":"Detailhandel mit Brot, Back U S\u00fcsswaren",
    "sg:phone":"+41 71 841 22 29",
    "sg:postcode":"9326",
    "sg:province":"Thurgau",
    "wof:name":"K\u00f6lbener Stefan, B\u00e4ckerei, Konditorei, Confiserie",
    "wof:placetype":"venue"
},
  "geometry": {"coordinates":[9.463687,47.49559],"type":"Point"}
}