{
  "type": "Feature",
  "properties": {
    "iso:country":"CH",
    "sg:address":"Maihuserstrasse 2a 5737 Menziken. Postfach",
    "sg:city":"Menziken",
    "sg:orig_category":"Erbringung von sonstigen Dienstleistungen f\u00fcr Unterhaltung, Erholung U Freizeit Sonstige Hilfsdienst",
    "sg:phone":"+41 62 772 28 28",
    "sg:postcode":"5737",
    "sg:province":"Aargau",
    "wof:name":"Rock Star Promotion, Aeschbach",
    "wof:placetype":"venue"
},
  "geometry": {"coordinates":[8.1928882599,47.2328720093],"type":"Point"}
}