{
  "type": "Feature",
  "properties": {
    "iso:country":"CH",
    "sg:address":"Bellot Rue Fran\u00e7ois- 2 1206 Gen\u00e8ve. Postfach",
    "sg:city":"Gen\u00e8ve",
    "sg:orig_category":"Unclassifiable Establishments",
    "sg:postcode":"1206",
    "sg:province":"Gen\u00e8ve",
    "wof:name":"Fuegotel S\u00e0rl",
    "wof:placetype":"venue"
},
  "geometry": {"coordinates":[6.6639499664,46.5902061462],"type":"Point"}
}