{
  "type": "Feature",
  "properties": {
    "iso:country":"CH",
    "sg:address":"Adlergasse 1",
    "sg:city":"Solothurn",
    "sg:orig_category":"Detailhandel mit Waren verschiedener Art, Hauptrichtung Nahrungsmittel Grosshandel mit Nahrungsmitte",
    "sg:phone":"+41 32 623 80 70",
    "sg:postcode":"4500",
    "sg:province":"Solothurn",
    "wof:name":"La Gustosa Gmbh",
    "wof:placetype":"venue"
},
  "geometry": {"coordinates":[7.5362119675,47.2046012878],"type":"Point"}
}