{
  "type": "Feature",
  "properties": {
    "iso:country":"CH",
    "sg:address":"Industriestrasse 25",
    "sg:city":"Buchs",
    "sg:classifiers":[
        {
            "category":"Manufacturing",
            "subcategory":"Chemicals & Compounds",
            "type":"Manufacturing & Wholesale Goods"
        }
    ],
    "sg:phone":"+41 81 755 28 28",
    "sg:postcode":"9470",
    "sg:province":"St. Gallen",
    "sg:tags":[
        "fine"
    ],
    "wof:name":"Sigma-aldrich Ag",
    "wof:placetype":"venue"
},
  "geometry": {"coordinates":[9.4789209366,47.1735115051],"type":"Point"}
}