{
  "type": "Feature",
  "properties": {
    "iso:country":"CH",
    "sg:address":"Gotthardstrasse 41",
    "sg:city":"Andermatt",
    "sg:orig_category":"Sonstige mit Sport verbundene T\u00e4tigkeiten",
    "sg:phone":"+41 41 887 06 14",
    "sg:postcode":"6490",
    "sg:province":"Uri",
    "wof:name":"Snowlimit, B. Simmen Und M. Boog",
    "wof:placetype":"venue"
},
  "geometry": {"coordinates":[8.5961427689,46.635307312],"type":"Point"}
}