{
  "type": "Feature",
  "properties": {
    "iso:country":"CH",
    "sg:address":"Elisabethenanlage 11 4051 Basel. Postfach 631",
    "sg:city":"Basel",
    "sg:orig_category":"Grosshandel mit Holz U Bauelementen aus Holz",
    "sg:phone":"+41 61 205 52 52",
    "sg:postcode":"4010",
    "sg:province":"Basel-Stadt",
    "wof:name":"Tt Timber International Ag H\u00f6lzer, Holzprodukte; Organisation, Finanzierung, Verkauf",
    "wof:placetype":"venue"
},
  "geometry": {"coordinates":[7.5885748863,47.5489883423],"type":"Point"}
}