{
  "type": "Feature",
  "properties": {
    "iso:country":"CH",
    "sg:address":"Bel-air Place De 2 1204 Gen\u00e8ve. Postfach",
    "sg:city":"Gen\u00e8ve",
    "sg:orig_category":"Interessenvertretungen",
    "sg:postcode":"1204",
    "sg:province":"Gen\u00e8ve",
    "wof:name":"Fondation Maurice Favre",
    "wof:placetype":"venue"
},
  "geometry": {"coordinates":[6.8304381371,47.1011161804],"type":"Point"}
}