{
  "type": "Feature",
  "properties": {
    "iso:country":"CH",
    "sg:address":"Via Alpsu 61",
    "sg:city":"Sedrun",
    "sg:orig_category":"Detailhandel mit Waren verschiedener Art, Hauptrichtung Nahrungsmittel",
    "sg:phone":"+41 81 949 11 10",
    "sg:postcode":"7188",
    "sg:province":"Graubunden",
    "wof:name":"Werner Curschellas Denner-satellit",
    "wof:placetype":"venue"
},
  "geometry": {"coordinates":[8.7751913071,46.6805915833],"type":"Point"}
}