{
  "type": "Feature",
  "properties": {
    "iso:country":"CH",
    "sg:address":"Neue Hard 7 8005 Z\u00fcrich. Postfach",
    "sg:city":"Z\u00fcrich-m\u00fclligen",
    "sg:orig_category":"Unclassifiable Establishments",
    "sg:phone":"+41 12774444",
    "sg:postcode":"8010",
    "sg:province":"Z\u00fcrich",
    "wof:name":"Kuoni Reisen Holding Ag",
    "wof:placetype":"venue"
},
  "geometry": {"coordinates":[8.5204248428,47.3864784241],"type":"Point"}
}