{
  "type": "Feature",
  "properties": {
    "iso:country":"CH",
    "sg:address":"Atenb\u00fcelweg 1",
    "sg:city":"Hinwil",
    "sg:orig_category":"Schwimmb\u00e4der",
    "sg:phone":"+41 19373922",
    "sg:postcode":"8340",
    "sg:province":"Z\u00fcrich",
    "wof:name":"Schwimmbad",
    "wof:placetype":"venue"
},
  "geometry": {"coordinates":[8.8367528915,47.3070526123],"type":"Point"}
}