{
  "type": "Feature",
  "properties": {
    "iso:country":"CH",
    "sg:address":"Mittelstrasse 16",
    "sg:city":"Langenthal",
    "sg:orig_category":"Non-Classified Establishments",
    "sg:phone":"+41 62 922 84 44",
    "sg:postcode":"4900",
    "sg:province":"Bern",
    "wof:name":"Sch\u00fctz-bracher P., Drogerie",
    "wof:placetype":"venue"
},
  "geometry": {"coordinates":[7.786400795,47.2086029053],"type":"Point"}
}