{
  "type": "Feature",
  "properties": {
    "iso:country":"CH",
    "sg:address":"Amselweg 2",
    "sg:city":"Riggisberg",
    "sg:orig_category":"Sportvereine Turnen Vereine Damen",
    "sg:phone":"+41 52 383 21 03",
    "sg:postcode":"3132",
    "sg:province":"Bern",
    "wof:name":"Damenriege Stv Rikon",
    "wof:placetype":"venue"
},
  "geometry": {"coordinates":[8.7991695404,47.4472541809],"type":"Point"}
}