{
  "type": "Feature",
  "properties": {
    "iso:country":"CH",
    "sg:address":"Im Schloss",
    "sg:city":"Zwingen",
    "sg:orig_category":"Grosshandel mit sonstigen Gebrauchs U Verbrauchsg\u00fctern Grosshandel mit sonstigen Halbwaren",
    "sg:phone":"+41 71 744 78 11",
    "sg:postcode":"4222",
    "sg:province":"Basel-Landschaft",
    "wof:name":"Reni-papier W.hasler",
    "wof:placetype":"venue"
},
  "geometry": {"coordinates":[9.6466550827,47.45079422],"type":"Point"}
}