{
  "type": "Feature",
  "properties": {
    "iso:country":"CH",
    "sg:address":"Bettengasse 70",
    "sg:city":"Wilchingen",
    "sg:orig_category":"Zimmerei, Ingenieurholzbau",
    "sg:phone":"+41 52 681 23 43",
    "sg:postcode":"8217",
    "sg:province":"Schaffhausen",
    "wof:name":"Roth Robert Holzbau",
    "wof:placetype":"venue"
},
  "geometry": {"coordinates":[8.4715633392,47.6663017273],"type":"Point"}
}