{
  "type": "Feature",
  "properties": {
    "iso:country":"CH",
    "sg:address":"Bruggerstrasse 171",
    "sg:city":"Baden",
    "sg:orig_category":"RESTAURANTS: TEA-ROOMS",
    "sg:postcode":"5400",
    "sg:province":"Aargau",
    "wof:name":"Speiserestaurant Quelle R\u00f6schli R. + A.",
    "wof:placetype":"venue"
},
  "geometry": {"coordinates":[8.2843942642,47.4834060669],"type":"Point"}
}