{
  "type": "Feature",
  "properties": {
    "iso:country":"CH",
    "sg:address":"Oberennetlinth 8783 Linthal. Postfach 22",
    "sg:city":"Linthal",
    "sg:orig_category":"Betrieb von Taxis G\u00fcterbef\u00f6rderung im Strassenverkehr",
    "sg:phone":"+41 55 643 12 60",
    "sg:postcode":"8783",
    "sg:province":"Glarus",
    "wof:name":"Wichser Thomas Klausengarage.",
    "wof:placetype":"venue"
},
  "geometry": {"coordinates":[8.994584,46.920727],"type":"Point"}
}