{
  "type": "Feature",
  "properties": {
    "iso:country":"CH",
    "sg:address":"H\u00f6lzliwisenstrasse 5",
    "sg:city":"Volketswil",
    "sg:orig_category":"Sonstiger Detailhandel nicht in Verkaufsr\u00e4umen",
    "sg:phone":"+41 19083020",
    "sg:postcode":"8604",
    "sg:province":"Z\u00fcrich",
    "wof:name":"Evis Ag",
    "wof:placetype":"venue"
},
  "geometry": {"coordinates":[8.6792039871,47.3781166077],"type":"Point"}
}