{
  "type": "Feature",
  "properties": {
    "iso:country":"CH",
    "sg:address":"Brunnenweid 78",
    "sg:city":"Sins",
    "sg:orig_category":"Wasserversorgung",
    "sg:postcode":"5643",
    "sg:province":"Aargau",
    "wof:name":"Wasserversorgungs-genossenschaft S\u00f6renberg",
    "wof:placetype":"venue"
},
  "geometry": {"coordinates":[8.0187387466,46.8324432373],"type":"Point"}
}