{
  "type": "Feature",
  "properties": {
    "iso:country":"CH",
    "sg:address":"Oberlindach",
    "sg:city":"Kirchlindach",
    "sg:classifiers":[
        {
            "category":"Restaurant",
            "type":"Food & Drink"
        }
    ],
    "sg:phone":"+41 31 829 03 20",
    "sg:postcode":"3038",
    "sg:province":"Bern",
    "wof:name":"Restaurant Zur Waage",
    "wof:placetype":"venue"
},
  "geometry": {"coordinates":[7.4259500504,47.0032691956],"type":"Point"}
}