{
  "type": "Feature",
  "properties": {
    "iso:country":"CH",
    "sg:address":"Kasernenstrasse 19 3013 Bern. Postfach",
    "sg:city":"Bern",
    "sg:orig_category":"Landesverteidigung",
    "sg:phone":"+41 31 324 57 01",
    "sg:postcode":"3003",
    "sg:province":"Bern",
    "wof:name":"Gruppe R\u00fcstung",
    "wof:placetype":"venue"
},
  "geometry": {"coordinates":[7.4579191208,46.9560012817],"type":"Point"}
}