{
  "type": "Feature",
  "properties": {
    "iso:country":"CH",
    "sg:address":"Trabandan Chemin Du 43",
    "sg:city":"Lausanne",
    "sg:orig_category":"Unclassifiable Establishments",
    "sg:postcode":"1006",
    "sg:province":"Vaud",
    "wof:name":"Fa Montages S\u00e0rl",
    "wof:placetype":"venue"
},
  "geometry": {"coordinates":[6.6458268166,46.5128440857],"type":"Point"}
}