{
  "type": "Feature",
  "properties": {
    "iso:country":"CH",
    "sg:address":"Rohrerstrasse 3 5000 Aarau. Postfach",
    "sg:city":"Aarau",
    "sg:orig_category":"Architektur U Ingenieurb\u00fcros",
    "sg:phone":"+41 79 332 98 10",
    "sg:postcode":"5001",
    "sg:province":"Aargau",
    "wof:name":"Ces Bauingenieur Ag Burgherr U. Partner",
    "wof:placetype":"venue"
},
  "geometry": {"coordinates":[8.055457,47.393501],"type":"Point"}
}