{
  "type": "Feature",
  "properties": {
    "iso:country":"CH",
    "sg:address":"Kantonsstrasse 60 6234 Triengen. Postfach 162",
    "sg:city":"Triengen",
    "sg:orig_category":"Regionalbanken U Sparkassen",
    "sg:phone":"+41 41 935 10 10",
    "sg:postcode":"6234",
    "sg:province":"Luzern",
    "wof:name":"Triba Partner Bank",
    "wof:placetype":"venue"
},
  "geometry": {"coordinates":[8.0761938095,47.2357330322],"type":"Point"}
}