{
  "type": "Feature",
  "properties": {
    "iso:country":"CH",
    "sg:address":"Bahnhofstrasse 46 8001 Z\u00fcrich. Postfach",
    "sg:city":"Z\u00fcrich",
    "sg:orig_category":"Finanzierungsinstitutionen",
    "sg:phone":"+41 12127474",
    "sg:postcode":"8021",
    "sg:province":"Z\u00fcrich",
    "wof:name":"Eps Finanz Ag Verm\u00f6gensverwaltung Usw",
    "wof:placetype":"venue"
},
  "geometry": {"coordinates":[8.5385284424,47.372215271],"type":"Point"}
}