{
  "type": "Feature",
  "properties": {
    "iso:country":"CH",
    "sg:address":"Industriestrasse 13b",
    "sg:city":"Zug",
    "sg:orig_category":"Markt U Meinungsforschung",
    "sg:phone":"+41 22 300 19 50",
    "sg:postcode":"6300",
    "sg:province":"Zug",
    "wof:name":"Acamedia, Baldi P.",
    "wof:placetype":"venue"
},
  "geometry": {"coordinates":[6.1423988342,46.1862945557],"type":"Point"}
}