{
  "type": "Feature",
  "properties": {
    "addr:full":"Belpstrasse 11 Bern Bern 3007",
    "addr:housenumber":"11",
    "addr:postcode":"3007",
    "addr:street":"Belpstrasse",
    "iso:country":"CH",
    "sg:address":"Belpstrasse 11",
    "sg:city":"Bern",
    "sg:orig_category":"Arztpraxen",
    "sg:phone":"+41 31 381 20 40",
    "sg:postcode":"3007",
    "sg:province":"Bern",
    "wof:name":"Dr.med. Judit Koller \u00c4rztin F\u00fcr Allg.medizin Fmh",
    "wof:placetype":"venue"
},
  "geometry": {"coordinates":[7.433632,46.945671],"type":"Point"}
}