{
  "type": "Feature",
  "properties": {
    "iso:country":"CH",
    "sg:address":"Loorenstrasse 43",
    "sg:city":"Z\u00fcrich",
    "sg:orig_category":"Softwareentwicklung U beratung",
    "sg:postcode":"8053",
    "sg:province":"Z\u00fcrich",
    "wof:name":"Haslinger R., Elektronik & Software Techn. Soft, Hardware; Entwicklung, Vertrieb",
    "wof:placetype":"venue"
},
  "geometry": {"coordinates":[8.5941286087,47.3602600098],"type":"Point"}
}