{
  "type": "Feature",
  "properties": {
    "iso:country":"CH",
    "sg:address":"Sch\u00fctzemur 13",
    "sg:city":"Rafz",
    "sg:orig_category":"Verlegen von Fliesen U Platten",
    "sg:phone":"+41 18690182",
    "sg:postcode":"8197",
    "sg:province":"Z\u00fcrich",
    "wof:name":"Heinz B\u00e4chi Chemin\u00e9ebau & Plattenbel\u00e4ge",
    "wof:placetype":"venue"
},
  "geometry": {"coordinates":[8.5461187363,47.6139602661],"type":"Point"}
}