{
  "type": "Feature",
  "properties": {
    "iso:country":"CH",
    "sg:address":"Rainstrasse 8",
    "sg:city":"Horriwil",
    "sg:orig_category":"Softwareentwicklung U beratung Sonstige mit der Informatik verbundene T\u00e4tigkeiten",
    "sg:phone":"+41 79 250 35 60",
    "sg:postcode":"4557",
    "sg:province":"Solothurn",
    "wof:name":"Studer Edv-beratung.",
    "wof:placetype":"venue"
},
  "geometry": {"coordinates":[7.6204061508,47.1819610596],"type":"Point"}
}