{
  "type": "Feature",
  "properties": {
    "iso:country":"CH",
    "sg:address":"Hauptgassse 22a",
    "sg:city":"Appenzell",
    "sg:classifiers":[
        {
            "category":"Shopping",
            "subcategory":"Pharmacy",
            "type":"Retail Goods"
        }
    ],
    "sg:phone":"+41 4117147272",
    "sg:postcode":"9050",
    "sg:province":"Appenzell Innerhoden",
    "sg:tags":[
        "chemical",
        "pharmaceutical",
        "cosmetic"
    ],
    "wof:name":"Blidor Ag",
    "wof:placetype":"venue"
},
  "geometry": {"coordinates":[8.5366,47.28756],"type":"Point"}
}