{
  "type": "Feature",
  "properties": {
    "iso:country":"CH",
    "sg:address":"Angelrainstrasse 3 5600 Lenzburg. Postfach",
    "sg:city":"Lenzburg",
    "sg:orig_category":"Sonstige mit der Informatik verbundene T\u00e4tigkeiten",
    "sg:phone":"+41 62 892 08 60",
    "sg:postcode":"5600",
    "sg:province":"Aargau",
    "wof:name":"Pmr Consulting, Reber Priska Edv-dienstleistungen Usw",
    "wof:placetype":"venue"
},
  "geometry": {"coordinates":[8.175075531,47.3884468079],"type":"Point"}
}