{
  "type": "Feature",
  "properties": {
    "iso:country":"CH",
    "sg:address":"Winzerhalde 28",
    "sg:city":"Z\u00fcrich",
    "sg:orig_category":"Kauf U Verkauf von Immobilien auf eigene Rechnung Vermietung U Verpachtung von eigenen Immobilien",
    "sg:phone":"+41 13400055",
    "sg:postcode":"8045",
    "sg:province":"Z\u00fcrich",
    "wof:name":"Z\u00fcriwohn Ag",
    "wof:placetype":"venue"
},
  "geometry": {"coordinates":[8.4916276932,47.399848938],"type":"Point"}
}