{
  "type": "Feature",
  "properties": {
    "iso:country":"CH",
    "sg:address":"H\u00f6fle 44",
    "sg:city":"Balzers",
    "sg:orig_category":"Detailhandel mit Fleisch U Fleischwaren",
    "sg:phone":"+41 79 608 19 55",
    "sg:postcode":"9496",
    "wof:name":"Metzgerei Brunhart Ag",
    "wof:placetype":"venue"
},
  "geometry": {"coordinates":[9.5072717667,47.0686683655],"type":"Point"}
}