{
  "type": "Feature",
  "properties": {
    "iso:country":"CH",
    "sg:address":"Schmalzgrube",
    "sg:city":"Unteriberg",
    "sg:orig_category":"Bauschreinerei",
    "sg:phone":"+41 55 414 19 45",
    "sg:postcode":"8842",
    "sg:province":"Schwyz",
    "wof:name":"Karl Bellmont Schreinerei",
    "wof:placetype":"venue"
},
  "geometry": {"coordinates":[8.806374,47.069702],"type":"Point"}
}