{
  "type": "Feature",
  "properties": {
    "iso:country":"CH",
    "sg:address":"Champ-bosson 354",
    "sg:city":"Riaz",
    "sg:orig_category":"Detailhandel mit Bekleidung Detailhandel mit Damenbekleidung",
    "sg:phone":"+41 26 912 33 23",
    "sg:postcode":"1632",
    "sg:province":"Fribourg",
    "wof:name":"Au Paradis De La Mari\u00e9e Patricia Michel",
    "wof:placetype":"venue"
},
  "geometry": {"coordinates":[7.058593,46.635525],"type":"Point"}
}