{
  "type": "Feature",
  "properties": {
    "iso:country":"CH",
    "sg:address":"Fluhstrasse 18",
    "sg:city":"Jona",
    "sg:orig_category":"RESTAURANTS: TEA-ROOMS",
    "sg:postcode":"8645",
    "sg:province":"St. Gallen",
    "wof:name":"Zellhof Ag",
    "wof:placetype":"venue"
},
  "geometry": {"coordinates":[8.8192777634,47.2374458313],"type":"Point"}
}