{
  "type": "Feature",
  "properties": {
    "iso:country":"CH",
    "sg:address":"Ostb\u00fchlstrasse 15",
    "sg:city":"Z\u00fcrich",
    "sg:orig_category":"Werbegrafikateliers",
    "sg:phone":"+41 19842121",
    "sg:postcode":"8038",
    "sg:province":"Z\u00fcrich",
    "wof:name":"Augustinus Bingesser Grafisches Atelier",
    "wof:placetype":"venue"
},
  "geometry": {"coordinates":[8.6900548935,47.3005561829],"type":"Point"}
}