{
  "type": "Feature",
  "properties": {
    "iso:country":"CH",
    "sg:address":"Im Zentrum 15 8604 Volketswil. Postfach",
    "sg:city":"Volketswil",
    "sg:orig_category":"Sonstiger Grosshandel",
    "sg:postcode":"8604",
    "sg:province":"Z\u00fcrich",
    "wof:name":"Impex Sk Gmbh Waren; Handel. Im, Export. Vermittlung U. Beratung In Produktionsfragen",
    "wof:placetype":"venue"
},
  "geometry": {"coordinates":[8.6816883087,47.3878555298],"type":"Point"}
}