{
  "type": "Feature",
  "properties": {
    "iso:country":"CH",
    "sg:address":"Route De Tramelan 1 2710 Tavannes Case Postale 58",
    "sg:city":"Tavannes",
    "sg:orig_category":"Drogerien Fachdetailhandel mit pharmazeutischen Produkten",
    "sg:phone":"+41 32 481 22 54",
    "sg:postcode":"2710",
    "sg:province":"Bern",
    "wof:name":"Droguerie Pharmacie Gasser, Tavannes Droguerie, Pharmcie Ect",
    "wof:placetype":"venue"
},
  "geometry": {"coordinates":[7.1981058121,47.2203483582],"type":"Point"}
}