{
  "type": "Feature",
  "properties": {
    "addr:full":"Tellistrasse 67 Aarau Aargau 5004",
    "addr:housenumber":"67",
    "addr:postcode":"5004",
    "addr:street":"Tellistrasse",
    "iso:country":"CH",
    "sg:address":"Tellistrasse 67",
    "sg:city":"Aarau",
    "sg:orig_category":"Detailhandel mit Damenbekleidung",
    "sg:phone":"+41 62 822 99 68",
    "sg:postcode":"5004",
    "sg:province":"Aargau",
    "wof:name":"Rafael-mode Feridun Gayret Damen-& Lederbekleidung",
    "wof:placetype":"venue"
},
  "geometry": {"coordinates":[8.058141,47.397804],"type":"Point"}
}