{
  "type": "Feature",
  "properties": {
    "iso:country":"CH",
    "sg:address":"Haldengasse 8",
    "sg:city":"Zeiningen",
    "sg:orig_category":"Dienstleistungen von Beteiligungsgesellschaften",
    "sg:phone":"+41 61 853 95 80",
    "sg:postcode":"4314",
    "sg:province":"Aargau",
    "wof:name":"Bsc Gmbh Unternehmens Und Personalberatung",
    "wof:placetype":"venue"
},
  "geometry": {"coordinates":[7.8715319633,47.5442848206],"type":"Point"}
}