{
  "type": "Feature",
  "properties": {
    "iso:country":"CH",
    "sg:address":"Pr\u00e9-yonnet 77 1860 Aigle. Postfach",
    "sg:city":"Aigle",
    "sg:orig_category":"K\u00fcnstlerische U schriftstellerische T\u00e4tigkeiten U Darbietungen",
    "sg:postcode":"1860",
    "sg:province":"Vaud",
    "wof:name":"Zumbrunnen Michel, Atelier Absis",
    "wof:placetype":"venue"
},
  "geometry": {"coordinates":[6.9611778259,46.3212509155],"type":"Point"}
}