{
  "type": "Feature",
  "properties": {
    "iso:country":"CH",
    "sg:address":"Aernihof",
    "sg:city":"Wolhusen",
    "sg:orig_category":"Schulpflegen",
    "sg:postcode":"6110",
    "sg:province":"Luzern",
    "wof:name":"Schulpflege Der Gemeinde Werthenstein,herrn H.amb\u00fchl",
    "wof:placetype":"venue"
},
  "geometry": {"coordinates":[8.0732545853,47.0589408875],"type":"Point"}
}