{
  "type": "Feature",
  "properties": {
    "iso:country":"CH",
    "sg:address":"Paulus-weg 10 2500 Biel/bienne. Postfach",
    "sg:city":"Biel/bienne",
    "sg:orig_category":"Oberfl\u00e4chenveredlung U W\u00e4rmebehandlung",
    "sg:phone":"+41 32 365 08 25",
    "sg:postcode":"2503",
    "sg:province":"Bern",
    "wof:name":"Helbling Rolf, Metallveredlung",
    "wof:placetype":"venue"
},
  "geometry": {"coordinates":[7.2547440529,47.1313476562],"type":"Point"}
}