{
  "type": "Feature",
  "properties": {
    "iso:country":"CH",
    "sg:address":"S\u00fcdstrasse 7",
    "sg:city":"M\u00fcnsingen",
    "sg:orig_category":"Autogaragen",
    "sg:phone":"+41 31 721 48 88",
    "sg:postcode":"3110",
    "sg:province":"Bern",
    "wof:name":"Ring Garage",
    "wof:placetype":"venue"
},
  "geometry": {"coordinates":[7.563433,46.867908],"type":"Point"}
}