{
  "type": "Feature",
  "properties": {
    "iso:country":"CH",
    "sg:address":"Rue De L'evole 8a",
    "sg:city":"Neuch\u00e2tel",
    "sg:orig_category":"Handel mit Automobilteilen U Zubeh\u00f6r Handelsvermittlung U Grosshandel mit Automobilteilen U Zubeh\u00f6r",
    "sg:phone":"+41 79 447 53 90",
    "sg:postcode":"2000",
    "sg:province":"Neuch\u00e2tel",
    "wof:name":"Tout Pour L'auto S\u00e0rl",
    "wof:placetype":"venue"
},
  "geometry": {"coordinates":[6.941450119,46.9826812744],"type":"Point"}
}