{
  "type": "Feature",
  "properties": {
    "iso:country":"CH",
    "sg:address":"Viale Franscini 17",
    "sg:city":"Lugano",
    "sg:orig_category":"Effektenvermittlung Broker Finanzierungsinstitutionen",
    "sg:postcode":"6900",
    "sg:province":"Ticino",
    "wof:name":"Ebcapital (europe) Ag",
    "wof:placetype":"venue"
},
  "geometry": {"coordinates":[8.7901973724,47.2036628723],"type":"Point"}
}