{
  "type": "Feature",
  "properties": {
    "iso:country":"CH",
    "sg:address":"B\u00e2timent Le Grand Pont 1884 Villars-sur-ollon. Postfach",
    "sg:city":"Villars-sur-ollon",
    "sg:orig_category":"Finanzierungsinstitutionen",
    "sg:phone":"+41 19386000",
    "sg:postcode":"1884",
    "sg:province":"Vaud",
    "wof:name":"Wrh Corporate Services Ag",
    "wof:placetype":"venue"
},
  "geometry": {"coordinates":[8.8286581039,47.3039398193],"type":"Point"}
}