{
  "type": "Feature",
  "properties": {
    "iso:country":"CH",
    "sg:address":"Dorfstrasse 575",
    "sg:city":"Gontenschwil",
    "sg:orig_category":"Sportvereine Turnen",
    "sg:phone":"+41 71 385 55 92",
    "sg:postcode":"5728",
    "sg:province":"Aargau",
    "wof:name":"Turnverein Stv Gossau Sg",
    "wof:placetype":"venue"
},
  "geometry": {"coordinates":[9.2602329254,47.4181594849],"type":"Point"}
}