{
  "type": "Feature",
  "properties": {
    "iso:country":"CH",
    "sg:address":"Neuhus 6",
    "sg:city":"Forch",
    "sg:orig_category":"Vereine Geselligkeit",
    "sg:phone":"+41 19180174",
    "sg:postcode":"8127",
    "sg:province":"Z\u00fcrich",
    "wof:name":"Altersverein Berg-k\u00fcsnacht",
    "wof:placetype":"venue"
},
  "geometry": {"coordinates":[8.6550750732,47.3287506104],"type":"Point"}
}