{
  "type": "Feature",
  "properties": {
    "iso:country":"CH",
    "sg:address":"B\u00e4umlihofstrasse 154",
    "sg:city":"Basel",
    "sg:orig_category":"Chemische Reinigung",
    "sg:phone":"+41 61 601 12 20",
    "sg:postcode":"4058",
    "sg:province":"Basel-Stadt",
    "wof:name":"N\u00e4f-express-reinigung",
    "wof:placetype":"venue"
},
  "geometry": {"coordinates":[7.619815,47.566082],"type":"Point"}
}