{
  "type": "Feature",
  "properties": {
    "iso:country":"CH",
    "sg:address":"Bruggerstrasse 37 5400 Baden. Postfach",
    "sg:city":"Baden",
    "sg:orig_category":"Werbung",
    "sg:phone":"+41 56 200 10 20",
    "sg:postcode":"5400",
    "sg:province":"Aargau",
    "wof:name":"Bdwhs Werbeagentur Ag",
    "wof:placetype":"venue"
},
  "geometry": {"coordinates":[8.3047838211,47.4764022827],"type":"Point"}
}