{
  "type": "Feature",
  "properties": {
    "addr:full":"Chrummatt 40 Flamatt Fribourg 3175",
    "addr:housenumber":"40",
    "addr:postcode":"3175",
    "addr:street":"Chrummatt",
    "iso:country":"CH",
    "sg:address":"Chrummatt 40",
    "sg:city":"Flamatt",
    "sg:classifiers":[
        {
            "category":"Organizations",
            "subcategory":"Labor Organization",
            "type":"Services"
        }
    ],
    "sg:phone":"+41 31 741 23 55",
    "sg:postcode":"3175",
    "sg:province":"Fribourg",
    "sg:tags":[
        "work",
        "assembling",
        "assembly",
        "contract"
    ],
    "wof:name":"Nydegger Storen",
    "wof:placetype":"venue"
},
  "geometry": {"coordinates":[7.302631,46.882488],"type":"Point"}
}