{
  "type": "Feature",
  "properties": {
    "iso:country":"CH",
    "sg:address":"Rue De L'h\u00f4pital 24 2800 Del\u00e9mont Case Postale 2232",
    "sg:city":"Delsberg",
    "sg:orig_category":"Reiseb\u00fcros U Reiseveranstalter",
    "sg:phone":"+41 22 346 95 83",
    "sg:postcode":"2800",
    "sg:province":"Jura",
    "wof:name":"Odyss\u00e9e Sa",
    "wof:placetype":"venue"
},
  "geometry": {"coordinates":[6.1522421837,46.1945877075],"type":"Point"}
}