{
  "type": "Feature",
  "properties": {
    "iso:country":"CH",
    "sg:address":"Seuzachstr. 26",
    "sg:city":"Neftenbach",
    "sg:classifiers":[
        {
            "category":"Professional",
            "subcategory":"Engineering",
            "type":"Services"
        }
    ],
    "sg:phone":"+41 52 315 12 21",
    "sg:postcode":"8413",
    "sg:province":"Z\u00fcrich",
    "sg:tags":[
        "machine",
        "-",
        "mechanical"
    ],
    "wof:name":"Idis International Distributor Group Ag",
    "wof:placetype":"venue"
},
  "geometry": {"coordinates":[8.671829,47.52951],"type":"Point"}
}