{
  "type": "Feature",
  "properties": {
    "iso:country":"CH",
    "sg:address":"Kriegstettenstrasse 1",
    "sg:city":"Gerlafingen",
    "sg:orig_category":"Detailhandel mit Waren verschiedener Art, Hauptrichtung Nahrungsmittel",
    "sg:phone":"+41 32 675 18 11",
    "sg:postcode":"4563",
    "sg:province":"Solothurn",
    "wof:name":"Coop Center",
    "wof:placetype":"venue"
},
  "geometry": {"coordinates":[7.5731902122,47.1707992554],"type":"Point"}
}