{
  "type": "Feature",
  "properties": {
    "iso:country":"CH",
    "sg:address":"Luzernerstrasse",
    "sg:city":"Mosen",
    "sg:orig_category":"Herstellung von Schl\u00f6ssern U Beschl\u00e4gen",
    "sg:phone":"+41 41 919 90 80",
    "sg:postcode":"6295",
    "sg:province":"Luzern",
    "wof:name":"Peka System Ag",
    "wof:placetype":"venue"
},
  "geometry": {"coordinates":[8.2257852554,47.2420539856],"type":"Point"}
}