{
  "type": "Feature",
  "properties": {
    "iso:country":"CH",
    "sg:address":"Lange Gasse 47 4052 Basel. Postfach",
    "sg:city":"Basel",
    "sg:orig_category":"Vermietung U Verpachtung von eigenen Immobilien",
    "sg:postcode":"4051",
    "sg:province":"Basel-Stadt",
    "wof:name":"Carimmo Finanz Ag Grundst\u00fccke, Liegenschaften; Kauf, Verkauf, Verwaltung, Vermittl",
    "wof:placetype":"venue"
},
  "geometry": {"coordinates":[7.6006379128,47.5518493652],"type":"Point"}
}