{
  "type": "Feature",
  "properties": {
    "iso:country":"CH",
    "sg:address":"Bernstrasse 16",
    "sg:city":"Lyss",
    "sg:orig_category":"Instandhaltung U Reparatur von Automobilen",
    "sg:phone":"+41 32 384 44 44",
    "sg:postcode":"3250",
    "sg:province":"Bern",
    "wof:name":"Marti Heinz",
    "wof:placetype":"venue"
},
  "geometry": {"coordinates":[7.3113460541,47.0695953369],"type":"Point"}
}