{
  "type": "Feature",
  "properties": {
    "iso:country":"CH",
    "sg:address":"S\u00fcdstrasse 1 3110 M\u00fcnsingen. Postfach",
    "sg:city":"M\u00fcnsingen",
    "sg:orig_category":"Architektur U Ingenieurb\u00fcros",
    "sg:phone":"+41 81 750 00 75",
    "sg:postcode":"3110",
    "sg:province":"Bern",
    "wof:name":"Gabathuler Ag, Dipl. Bauingenieure Eth",
    "wof:placetype":"venue"
},
  "geometry": {"coordinates":[9.482451,47.166],"type":"Point"}
}