{
  "type": "Feature",
  "properties": {
    "iso:country":"CH",
    "sg:address":"Rotenwies 1559",
    "sg:city":"Gais",
    "sg:orig_category":"Detailhandel mit M\u00f6beln U Haushaltsgegenst\u00e4nden",
    "sg:phone":"+41 71 793 28 40",
    "sg:postcode":"9056",
    "sg:province":"Appenzell Ausserrhoden",
    "wof:name":"Geba Innenarchitektur, Weber M.",
    "wof:placetype":"venue"
},
  "geometry": {"coordinates":[9.4733104706,47.3707618713],"type":"Point"}
}