{
  "type": "Feature",
  "properties": {
    "iso:country":"CH",
    "sg:address":"G\u00fcterstrasse 126",
    "sg:city":"Basel",
    "sg:orig_category":"Detailhandel mit Bekleidung",
    "sg:postcode":"4053",
    "sg:province":"Basel-Stadt",
    "wof:name":"Samanyolu-wagner Recep",
    "wof:placetype":"venue"
},
  "geometry": {"coordinates":[7.588343,47.545048],"type":"Point"}
}