{
  "type": "Feature",
  "properties": {
    "iso:country":"CH",
    "sg:address":"Ringgeliweg 3",
    "sg:city":"Wynigen",
    "sg:orig_category":"Gartenbau",
    "sg:phone":"+41 55 410 67 65",
    "sg:postcode":"3472",
    "sg:province":"Bern",
    "wof:name":"Heinrich Hiestand Gartenbau",
    "wof:placetype":"venue"
},
  "geometry": {"coordinates":[8.7856559753,47.2003364563],"type":"Point"}
}