{
  "type": "Feature",
  "properties": {
    "iso:country":"CH",
    "sg:address":"Rue De Lausanne 61",
    "sg:city":"Fribourg",
    "sg:classifiers":[
        {
            "category":"Government",
            "subcategory":"Post Office",
            "type":"Public Place"
        }
    ],
    "sg:phone":"+41 26 322 34 89",
    "sg:postcode":"1700",
    "sg:province":"Fribourg",
    "sg:tags":[
        "caf\u00e9s",
        "tea-rooms"
    ],
    "wof:name":"Tea-room B\u00fcrgisser",
    "wof:placetype":"venue"
},
  "geometry": {"coordinates":[7.1580848694,46.8056526184],"type":"Point"}
}