{
  "type": "Feature",
  "properties": {
    "iso:country":"CH",
    "sg:address":"3661",
    "sg:city":"Uetendorf",
    "sg:orig_category":"Markt U Meinungsforschung",
    "sg:postcode":"3661",
    "sg:province":"Bern",
    "wof:name":"B-p's Lodge, Tschanz Peter",
    "wof:placetype":"venue"
},
  "geometry": {"coordinates":[7.5716490746,46.7742767334],"type":"Point"}
}