{
  "type": "Feature",
  "properties": {
    "iso:country":"CH",
    "sg:address":"Haueti",
    "sg:city":"Giswil",
    "sg:orig_category":"Dachdeckerei Zimmerei, Dachdeckerei, Bauspenglerei U Abdichtung",
    "sg:phone":"+41 41 675 23 67",
    "sg:postcode":"6074",
    "sg:province":"Obwalden",
    "wof:name":"Anderegg Georg, Bedachungen",
    "wof:placetype":"venue"
},
  "geometry": {"coordinates":[8.161564,46.848045],"type":"Point"}
}