{
  "type": "Feature",
  "properties": {
    "iso:country":"CH",
    "sg:address":"Rue Du Cropt 20",
    "sg:city":"Bex",
    "sg:classifiers":[
        {
            "category":"Bars & Pubs",
            "type":"Food & Drink"
        }
    ],
    "sg:phone":"+41 24 463 23 97",
    "sg:postcode":"1880",
    "sg:province":"Vaud",
    "wof:name":"Bar Cam\u00e9o",
    "wof:placetype":"venue"
},
  "geometry": {"coordinates":[7.014095,46.249889],"type":"Point"}
}