{
  "type": "Feature",
  "properties": {
    "iso:country":"CH",
    "sg:address":"Acla Davosora",
    "sg:city":"Valbella",
    "sg:orig_category":"Personenbef\u00f6rderung im Linienverkehr zu Land",
    "sg:phone":"+41 81 325 19 53",
    "sg:postcode":"7077",
    "sg:province":"Graubunden",
    "wof:name":"Skilift Flensa Ag",
    "wof:placetype":"venue"
},
  "geometry": {"coordinates":[9.6389751434,46.9900741577],"type":"Point"}
}