{
  "type": "Feature",
  "properties": {
    "iso:country":"CH",
    "sg:address":"In Der Au 6",
    "sg:city":"Gachnang",
    "sg:orig_category":"Kauf U Verkauf von Immobilien auf eigene Rechnung",
    "sg:phone":"+41 52 375 13 70",
    "sg:postcode":"8547",
    "sg:province":"Thurgau",
    "wof:name":"Wepega Immobilien Gmbh",
    "wof:placetype":"venue"
},
  "geometry": {"coordinates":[8.8472471237,47.5415306091],"type":"Point"}
}