{
  "type": "Feature",
  "properties": {
    "iso:country":"CH",
    "sg:address":"Ernst Z\u00f6beli-strasse 8",
    "sg:city":"Z\u00fcrich",
    "sg:orig_category":"G\u00fcterbef\u00f6rderung im Strassenverkehr",
    "sg:phone":"+41 14314303",
    "sg:postcode":"8048",
    "sg:province":"Z\u00fcrich",
    "wof:name":"Roland Blatti Transporte",
    "wof:placetype":"venue"
},
  "geometry": {"coordinates":[8.4742050171,47.3920555115],"type":"Point"}
}