{
  "type": "Feature",
  "properties": {
    "iso:country":"CH",
    "sg:address":"Gstipfstrasse 9",
    "sg:city":"Glis",
    "sg:orig_category":"Mechanische Werkst\u00e4tten",
    "sg:phone":"+41 27 923 44 44",
    "sg:postcode":"3902",
    "sg:province":"Valais",
    "wof:name":"Leitz Gmbh Sch\u00e4rf-service",
    "wof:placetype":"venue"
},
  "geometry": {"coordinates":[7.9734539986,46.3090858459],"type":"Point"}
}