{
  "type": "Feature",
  "properties": {
    "iso:country":"CH",
    "sg:address":"Burgholz",
    "sg:city":"Oey",
    "sg:orig_category":"Strassenbau",
    "sg:phone":"+41 21 691 29 00",
    "sg:postcode":"3753",
    "sg:province":"Bern",
    "wof:name":"Reproad Sa Saint-sulpice",
    "wof:placetype":"venue"
},
  "geometry": {"coordinates":[6.5424780846,46.5132637024],"type":"Point"}
}