{
  "type": "Feature",
  "properties": {
    "addr:full":"Laufenstrasse 36 Basel Basel-Stadt 4053",
    "addr:housenumber":"36",
    "addr:postcode":"4053",
    "addr:street":"Laufenstrasse",
    "iso:country":"CH",
    "sg:address":"Laufenstrasse 36",
    "sg:city":"Basel",
    "sg:orig_category":"Datenverarbeitungsdienste Sonstige mit der Informatik verbundene T\u00e4tigkeiten",
    "sg:phone":"+41 61 331 08 05",
    "sg:postcode":"4053",
    "sg:province":"Basel-Stadt",
    "wof:name":"Roka-data Ag",
    "wof:placetype":"venue"
},
  "geometry": {"coordinates":[7.598775,47.541359],"type":"Point"}
}