{
  "type": "Feature",
  "properties": {
    "iso:country":"CH",
    "sg:address":"Im Dorf 3",
    "sg:city":"Rechthalten",
    "sg:orig_category":"Instandhaltung U Reparatur von Automobilen",
    "sg:phone":"+41 26 418 22 14",
    "sg:postcode":"1718",
    "sg:province":"Fribourg",
    "wof:name":"Bielmann Lorenz",
    "wof:placetype":"venue"
},
  "geometry": {"coordinates":[7.2402639389,46.7678375244],"type":"Point"}
}