{
  "type": "Feature",
  "properties": {
    "iso:country":"CH",
    "sg:address":"Beethoven Str. 24",
    "sg:city":"Z\u00fcrich",
    "sg:classifiers":[
        {
            "category":"Banks & Credit Unions",
            "subcategory":"Bank",
            "type":"Services"
        }
    ],
    "sg:phone":"+41 12810101",
    "sg:postcode":"8002",
    "sg:province":"Z\u00fcrich",
    "wof:name":"Confederacion, Espanola De Cajas De Ahorros",
    "wof:placetype":"venue"
},
  "geometry": {"coordinates":[8.536526,47.36681],"type":"Point"}
}