{
  "type": "Feature",
  "properties": {
    "iso:country":"CH",
    "sg:address":"Mollens",
    "sg:city":"Mollens",
    "sg:classifiers":[
        {
            "category":"Banks & Credit Unions",
            "subcategory":"Bank",
            "type":"Services"
        }
    ],
    "sg:phone":"+41 27414220",
    "sg:postcode":"3974",
    "sg:province":"Valais",
    "wof:name":"National Suisse",
    "wof:placetype":"venue"
},
  "geometry": {"coordinates":[7.520036,46.316448],"type":"Point"}
}