{
  "type": "Feature",
  "properties": {
    "iso:country":"CH",
    "sg:address":"6672",
    "sg:city":"Gordevio",
    "sg:orig_category":"Herstellung von industriellen Prozesssteuerungsanlagen",
    "sg:phone":"+41 19843155",
    "sg:postcode":"6672",
    "sg:province":"Ticino",
    "wof:name":"Markus Artho Elektronische Steuerungen Und Ger\u00e4te",
    "wof:placetype":"venue"
},
  "geometry": {"coordinates":[8.6900548935,47.3005561829],"type":"Point"}
}