{
  "type": "Feature",
  "properties": {
    "iso:country":"CH",
    "sg:address":"Dufour Rue Du G\u00e9n\u00e9ral- 15 1204 Gen\u00e8ve. Postfach",
    "sg:city":"Gen\u00e8ve",
    "sg:orig_category":"Vermietung U Verpachtung von eigenen Immobilien",
    "sg:postcode":"1204",
    "sg:province":"Gen\u00e8ve",
    "wof:name":"Jofa Immobilien Ag",
    "wof:placetype":"venue"
},
  "geometry": {"coordinates":[8.8798389435,47.1942825317],"type":"Point"}
}