{
  "type": "Feature",
  "properties": {
    "iso:country":"CH",
    "sg:address":"Bahnhofstrasse 5 3800 Interlaken. Postfach 243",
    "sg:city":"Interlaken",
    "sg:orig_category":"Vereine Mieter",
    "sg:phone":"+41 17409555",
    "sg:postcode":"3800",
    "sg:province":"Bern",
    "wof:name":"Mieterverband Limmattal",
    "wof:placetype":"venue"
},
  "geometry": {"coordinates":[8.4036903381,47.4038887024],"type":"Point"}
}