{
  "type": "Feature",
  "properties": {
    "iso:country":"CH",
    "sg:address":"Rue Des Alpes 58",
    "sg:city":"Fribourg",
    "sg:orig_category":"Interessenvertretungen",
    "sg:postcode":"1700",
    "sg:province":"Fribourg",
    "wof:name":"Fondation Gabriel E. Thurler",
    "wof:placetype":"venue"
},
  "geometry": {"coordinates":[7.1592001915,46.8053207397],"type":"Point"}
}