{
  "type": "Feature",
  "properties": {
    "iso:country":"CH",
    "sg:address":"Jurastrasse 48",
    "sg:city":"Biel/bienne",
    "sg:orig_category":"Vereine Musik/Blasmusik",
    "sg:postcode":"2503",
    "sg:province":"Bern",
    "wof:name":"Arbeitermusik Biel",
    "wof:placetype":"venue"
},
  "geometry": {"coordinates":[7.2530012131,47.1389007568],"type":"Point"}
}