{
  "type": "Feature",
  "properties": {
    "iso:country":"CH",
    "sg:address":"Bederstrasse 119",
    "sg:city":"Z\u00fcrich",
    "sg:orig_category":"Interessenvertretungen",
    "sg:postcode":"8001",
    "sg:province":"Z\u00fcrich",
    "wof:name":"M\u00fcller-meier Lina Stiftung",
    "wof:placetype":"venue"
},
  "geometry": {"coordinates":[8.5243473053,47.360458374],"type":"Point"}
}