{
  "type": "Feature",
  "properties": {
    "iso:country":"CH",
    "sg:address":"B\u00e4ndlistrasse 23 8064 Z\u00fcrich. Postfach",
    "sg:city":"Z\u00fcrich",
    "sg:orig_category":"Grosshandel mit Nahrungsmitteln, Getr\u00e4nken U Tabakwaren ohne ausgepr\u00e4gten Schwerpunkt",
    "sg:postcode":"8064",
    "sg:province":"Z\u00fcrich",
    "wof:name":"L'economica Alimentare, Adriana Akhavan Safa-berardi",
    "wof:placetype":"venue"
},
  "geometry": {"coordinates":[8.4880428314,47.3953208923],"type":"Point"}
}