{
  "type": "Feature",
  "properties": {
    "iso:country":"CH",
    "sg:address":"Universit\u00e4tstrasse 94 8006 Z\u00fcrich. Postfach",
    "sg:city":"Z\u00fcrich",
    "sg:orig_category":"Patentverwertung",
    "sg:phone":"+41 27 473 47 25",
    "sg:postcode":"8033",
    "sg:province":"Z\u00fcrich",
    "wof:name":"Refim Ag Alpinfire",
    "wof:placetype":"venue"
},
  "geometry": {"coordinates":[7.6518630981,46.3238334656],"type":"Point"}
}