{
  "type": "Feature",
  "properties": {
    "iso:country":"CH",
    "sg:address":"Industriestrasse 44 5000 Aarau. Postfach",
    "sg:city":"Aarau",
    "sg:orig_category":"Herstellung von Metallerzeugnissen ohne Maschinenbau Maschinenbau",
    "sg:phone":"+41 71 761 21 21",
    "sg:postcode":"5001",
    "sg:province":"Aargau",
    "wof:name":"Mattle Walter Ag, Maschinenfabrik",
    "wof:placetype":"venue"
},
  "geometry": {"coordinates":[9.5739545822,47.3270149231],"type":"Point"}
}