{
  "type": "Feature",
  "properties": {
    "iso:country":"CH",
    "sg:address":"Zehntenhausstrasse 15 8046 Z\u00fcrich. Postfach",
    "sg:city":"Z\u00fcrich",
    "sg:orig_category":"Detailhandel mit Metallwaren, Anstrichmitteln, Glaswaren, Bau U Heimwerkerbedarf Handelsvermittlung ",
    "sg:phone":"+41 13716600",
    "sg:postcode":"8046",
    "sg:province":"Z\u00fcrich",
    "wof:name":"Gertsch H. & Co Ag",
    "wof:placetype":"venue"
},
  "geometry": {"coordinates":[8.50663,47.420242],"type":"Point"}
}