{
  "type": "Feature",
  "properties": {
    "iso:country":"CH",
    "sg:address":"Bogenstrasse 17",
    "sg:city":"Horn",
    "sg:orig_category":"Non-Classified Establishments",
    "sg:postcode":"9326",
    "sg:province":"Thurgau",
    "wof:name":"Crazy World Guhl",
    "wof:placetype":"venue"
},
  "geometry": {"coordinates":[8.6885499954,47.678024292],"type":"Point"}
}