{
  "type": "Feature",
  "properties": {
    "iso:country":"CH",
    "sg:address":"Dufour Rue Du G\u00e9n\u00e9ral- 11 1204 Gen\u00e8ve. Postfach",
    "sg:city":"Gen\u00e8ve",
    "sg:orig_category":"Sonstige mit Sport verbundene T\u00e4tigkeiten",
    "sg:phone":"+41 31 982 15 16",
    "sg:postcode":"1204",
    "sg:province":"Gen\u00e8ve",
    "wof:name":"Magnet Trainingszentrum F\u00fcr Sportkletterer Sigrist Gmbh",
    "wof:placetype":"venue"
},
  "geometry": {"coordinates":[7.3701472282,46.9210319519],"type":"Point"}
}