{
  "type": "Feature",
  "properties": {
    "iso:country":"CH",
    "sg:address":"Bleiche 335b",
    "sg:city":"Trogen",
    "sg:orig_category":"Architektur U Ingenieurb\u00fcros",
    "sg:phone":"+41 71 340 02 05",
    "sg:postcode":"9043",
    "sg:province":"Appenzell Ausserrhoden",
    "wof:name":"Lgb Gmbh Liegenschaftentreuhand & Bauberatungs-gesellschaft",
    "wof:placetype":"venue"
},
  "geometry": {"coordinates":[9.473372,47.408035],"type":"Point"}
}