{
  "type": "Feature",
  "properties": {
    "iso:country":"CH",
    "sg:address":"Caro Route Du",
    "sg:city":"Chandolin-savi\u00e8se",
    "sg:orig_category":"Erbringung von Dienstleistungen f\u00fcr Unternehmen",
    "sg:phone":"+41 27 395 24 86",
    "sg:postcode":"1965",
    "sg:province":"Valais",
    "wof:name":"L\u00e9ger Stephen",
    "wof:placetype":"venue"
},
  "geometry": {"coordinates":[7.3385391235,46.2504730225],"type":"Point"}
}