{
  "type": "Feature",
  "properties": {
    "iso:country":"CH",
    "sg:address":"Moosacherstr. 7",
    "sg:city":"W\u00e4denswil",
    "sg:orig_category":"Mechanik",
    "sg:phone":"+41 32 925 90 26",
    "sg:postcode":"8820",
    "sg:province":"Z\u00fcrich",
    "wof:name":"Orbag, J.-j. Hippenmeyer",
    "wof:placetype":"venue"
},
  "geometry": {"coordinates":[6.8174419403,47.0959968567],"type":"Point"}
}