{
  "type": "Feature",
  "properties": {
    "iso:country":"CH",
    "sg:address":"Bodenackerstrasse 69",
    "sg:city":"Dulliken",
    "sg:orig_category":"RESTAURANTS: TEA-ROOMS",
    "sg:phone":"+41 26 470 23 15",
    "sg:postcode":"4657",
    "sg:province":"Solothurn",
    "wof:name":"Corallo Gastro Gmbh",
    "wof:placetype":"venue"
},
  "geometry": {"coordinates":[2.4079089165,44.1636695862],"type":"Point"}
}