{
  "type": "Feature",
  "properties": {
    "iso:country":"CH",
    "sg:address":"Via Cantonale",
    "sg:city":"Tegna",
    "sg:orig_category":"Mechanische Werkst\u00e4tten",
    "sg:phone":"+41 79 207 14 32",
    "sg:postcode":"6652",
    "sg:province":"Ticino",
    "wof:name":"Giulio Bazzana Officina Meccanica & Garage",
    "wof:placetype":"venue"
},
  "geometry": {"coordinates":[8.7470493317,46.1871185303],"type":"Point"}
}