{
  "type": "Feature",
  "properties": {
    "iso:country":"CH",
    "sg:address":"Chemin De Giziaux 3 1066 Epalinges. Postfach",
    "sg:city":"Epalinges",
    "sg:orig_category":"Herstellung von medizinischen U chirurgischen Ger\u00e4ten sowie orthop\u00e4dischen Vorrichtungen",
    "sg:postcode":"1066",
    "sg:province":"Vaud",
    "wof:name":"Oxystar S\u00e0rl",
    "wof:placetype":"venue"
},
  "geometry": {"coordinates":[6.6759529114,46.5484848022],"type":"Point"}
}