{
  "type": "Feature",
  "properties": {
    "iso:country":"CH",
    "sg:address":"Winterthurerstrasse 534",
    "sg:city":"Z\u00fcrich",
    "sg:orig_category":"RESTAURANTS: TEA-ROOMS",
    "sg:phone":"+41 13223514",
    "sg:postcode":"8051",
    "sg:province":"Z\u00fcrich",
    "wof:name":"Blume Schwamendingen Gmbh",
    "wof:placetype":"venue"
},
  "geometry": {"coordinates":[8.5729017258,47.4040641785],"type":"Point"}
}