{
  "type": "Feature",
  "properties": {
    "iso:country":"CH",
    "sg:address":"3423 Ersigen. Postfach 107",
    "sg:city":"Ersigen",
    "sg:orig_category":"Sportvereine Ballsport Fussball",
    "sg:phone":"+41 34 445 74 89",
    "sg:postcode":"3423",
    "sg:province":"Bern",
    "wof:name":"Sc Ersigen",
    "wof:placetype":"venue"
},
  "geometry": {"coordinates":[7.5955348015,47.0935783386],"type":"Point"}
}