{
  "type": "Feature",
  "properties": {
    "iso:country":"CH",
    "sg:address":"Steinhofhalde 21",
    "sg:city":"Luzern",
    "sg:orig_category":"Vereine Musik/Blasmusik",
    "sg:phone":"+41 41 310 07 22",
    "sg:postcode":"6005",
    "sg:province":"Luzern",
    "wof:name":"Harmonie-musik Kriens",
    "wof:placetype":"venue"
},
  "geometry": {"coordinates":[8.294719696,47.042011261],"type":"Point"}
}