{
  "type": "Feature",
  "properties": {
    "iso:country":"CH",
    "sg:address":"Terreaux Rue Des 21",
    "sg:city":"Lausanne",
    "sg:orig_category":"Detailhandel mit Bekleidung",
    "sg:postcode":"1003",
    "sg:province":"Vaud",
    "wof:name":"Molho Simon",
    "wof:placetype":"venue"
},
  "geometry": {"coordinates":[6.627736,46.522682],"type":"Point"}
}