{
  "type": "Feature",
  "properties": {
    "iso:country":"CH",
    "sg:address":"Besson Avenue Fran\u00e7ois- 1",
    "sg:city":"Meyrin",
    "sg:orig_category":"Sonstiger Grosshandel",
    "sg:phone":"+41 22 785 46 75",
    "sg:postcode":"1217",
    "sg:province":"Gen\u00e8ve",
    "wof:name":"Aquatec, Garcia Jos\u00e9 Maria",
    "wof:placetype":"venue"
},
  "geometry": {"coordinates":[6.0790200233,46.2333908081],"type":"Point"}
}