{
  "type": "Feature",
  "properties": {
    "addr:full":"Route D'oron 4 1010 Lausanne Case Postale 154 Lausanne Vaud 1010",
    "addr:housenumber":"4;154",
    "addr:postcode":"1010;1010",
    "addr:street":"Route D'Oron;Postale",
    "iso:country":"CH",
    "sg:address":"Route D'oron 4 1010 Lausanne Case Postale 154",
    "sg:city":"Lausanne",
    "sg:orig_category":"Detailhandel mit Blumen U Pflanzen Fachdetailhandel in Verkaufsr\u00e4umen",
    "sg:phone":"+41 21 652 57 83",
    "sg:postcode":"1010",
    "sg:province":"Vaud",
    "wof:name":"Julien Fleurs, Pilloud J. Et L.",
    "wof:placetype":"venue"
},
  "geometry": {"coordinates":[6.666006,46.506939],"type":"Point"}
}