{
  "type": "Feature",
  "properties": {
    "iso:country":"CH",
    "sg:address":"Furkastrasse",
    "sg:city":"Realp",
    "sg:orig_category":"HOTELS: OHNE RESTAURANT",
    "sg:phone":"+41 32 487 69 70",
    "sg:postcode":"6491",
    "sg:province":"Uri",
    "wof:name":"Garni Zur Alten K\u00e4serei",
    "wof:placetype":"venue"
},
  "geometry": {"coordinates":[7.08335495,47.2246208191],"type":"Point"}
}