{
  "type": "Feature",
  "properties": {
    "iso:country":"CH",
    "sg:address":"M\u00fclibachweg 5",
    "sg:city":"Oberrohrdorf",
    "sg:orig_category":"Unternehmensberatung",
    "sg:postcode":"5452",
    "sg:province":"Aargau",
    "wof:name":"Active Steps Gmbh",
    "wof:placetype":"venue"
},
  "geometry": {"coordinates":[8.3104305267,47.4210166931],"type":"Point"}
}