{
  "type": "Feature",
  "properties": {
    "iso:country":"CH",
    "sg:address":"1897",
    "sg:city":"Bouveret",
    "sg:orig_category":"Landesverteidigung, Sozialversicherung \u00d6ffentliche Verwaltung",
    "sg:phone":"+41 24 481 27 26",
    "sg:postcode":"1897",
    "sg:province":"Valais",
    "wof:name":"Centre De Protection Civile",
    "wof:placetype":"venue"
},
  "geometry": {"coordinates":[6.8527798653,46.3853187561],"type":"Point"}
}