{
  "type": "Feature",
  "properties": {
    "iso:country":"CH",
    "sg:address":"M\u00fchlebachweg 4 8867 Niederurnen. Postfach",
    "sg:city":"Niederurnen",
    "sg:orig_category":"Architektur U Ingenieurb\u00fcros",
    "sg:phone":"+41 55 610 15 19",
    "sg:postcode":"8867",
    "sg:province":"Glarus",
    "wof:name":"Ingenieurb\u00fcro Wickli Und H\u00f6sli Ag",
    "wof:placetype":"venue"
},
  "geometry": {"coordinates":[9.058349,47.123455],"type":"Point"}
}