{
  "type": "Feature",
  "properties": {
    "iso:country":"CH",
    "sg:address":"Rue De Lausanne 121",
    "sg:city":"Gen\u00e8ve",
    "sg:orig_category":"Detektivb\u00fcros U \u00dcberwachung Herstellung von sonstigen elektrischen Ausr\u00fcstungen",
    "sg:phone":"+41 22 349 48 58",
    "sg:postcode":"1202",
    "sg:province":"Gen\u00e8ve",
    "wof:name":"Adsi Fonti Sa",
    "wof:placetype":"venue"
},
  "geometry": {"coordinates":[6.149846077,46.2207946777],"type":"Point"}
}