{
  "type": "Feature",
  "properties": {
    "iso:country":"CH",
    "sg:address":"Guillemin Avenue 14",
    "sg:city":"Pully",
    "sg:orig_category":"Fachdetailhandel in Verkaufsr\u00e4umen",
    "sg:postcode":"1009",
    "sg:province":"Vaud",
    "wof:name":"Randowest, S. Cabat",
    "wof:placetype":"venue"
},
  "geometry": {"coordinates":[6.655559063,46.51379776],"type":"Point"}
}