{
  "type": "Feature",
  "properties": {
    "iso:country":"CH",
    "sg:address":"Rue Pierre-fatio 8",
    "sg:city":"Gen\u00e8ve",
    "sg:orig_category":"Detailhandel mit Bekleidung Detailhandel mit Pelzwaren",
    "sg:phone":"+41 22 310 07 70",
    "sg:postcode":"1204",
    "sg:province":"Gen\u00e8ve",
    "wof:name":"Vermorel J.-c., Fourrures",
    "wof:placetype":"venue"
},
  "geometry": {"coordinates":[6.153408,46.202354],"type":"Point"}
}