{
  "type": "Feature",
  "properties": {
    "iso:country":"CH",
    "sg:address":"Kappelenring 56b",
    "sg:city":"Hinterkappelen",
    "sg:orig_category":"Elektroinstallation Herstellung von Elektromotoren, Generatoren U Transformatoren",
    "sg:phone":"+41 31 901 18 53",
    "sg:postcode":"3032",
    "sg:province":"Bern",
    "wof:name":"Orell Und Ramseier Ag",
    "wof:placetype":"venue"
},
  "geometry": {"coordinates":[7.3766131401,46.9676856995],"type":"Point"}
}