{
  "type": "Feature",
  "properties": {
    "iso:country":"CH",
    "sg:address":"Grabackerstrasse 3",
    "sg:city":"Kriegstetten",
    "sg:orig_category":"Naturheil\u00e4rzte and Heilpraktiker",
    "sg:phone":"+41 32 675 25 08",
    "sg:postcode":"4566",
    "sg:province":"Solothurn",
    "wof:name":"Hilma Naturheilpraxis",
    "wof:placetype":"venue"
},
  "geometry": {"coordinates":[7.5985879898,47.1806488037],"type":"Point"}
}