{
  "type": "Feature",
  "properties": {
    "iso:country":"CH",
    "sg:address":"K\u00e4sereistrasse 7 3145 Niederscherli. Postfach 68",
    "sg:city":"Niederscherli",
    "sg:orig_category":"Herstellung von Metallerzeugnissen ohne Maschinenbau Herstellung von sonstigen Maschinen f\u00fcr unspezi",
    "sg:phone":"+41 31 849 10 47",
    "sg:postcode":"3145",
    "sg:province":"Bern",
    "wof:name":"Setaga Krebs & Co.",
    "wof:placetype":"venue"
},
  "geometry": {"coordinates":[7.3879990578,46.8857040405],"type":"Point"}
}