{
  "type": "Feature",
  "properties": {
    "iso:country":"CH",
    "sg:address":"R\u00fcmelinsplatz 7 4001 Basel. Postfach",
    "sg:city":"Basel",
    "sg:orig_category":"Non-Classified Establishments",
    "sg:postcode":"4001",
    "sg:province":"Basel-Stadt",
    "wof:name":"Applaus! Gmbh Herausgabe Von Publikationen U. Dienstleistungen In Den Bereichen Veranstaltungen, Internet U. Public Relation Usw",
    "wof:placetype":"venue"
},
  "geometry": {"coordinates":[7.5873880386,47.5565643311],"type":"Point"}
}