{
  "type": "Feature",
  "properties": {
    "iso:country":"CH",
    "sg:address":"Marktgasse 5",
    "sg:city":"Bern",
    "sg:orig_category":"Detailhandel mit Bekleidung",
    "sg:phone":"+41 31 311 86 00",
    "sg:postcode":"3011",
    "sg:province":"Bern",
    "wof:name":"Comeback Hauser",
    "wof:placetype":"venue"
},
  "geometry": {"coordinates":[7.447084,46.9478],"type":"Point"}
}