{
  "type": "Feature",
  "properties": {
    "iso:country":"CH",
    "sg:address":"Eisenbahnstrasse 41 9400 Rorschach. Postfach 228",
    "sg:city":"Rorschach",
    "sg:orig_category":"Advokaturb\u00fcros",
    "sg:phone":"+41 71 841 01 41",
    "sg:postcode":"9401",
    "sg:province":"St. Gallen",
    "wof:name":"Peter Dietsche Advokaturb\u00fcro",
    "wof:placetype":"venue"
},
  "geometry": {"coordinates":[9.49259,47.475754],"type":"Point"}
}