{
  "type": "Feature",
  "properties": {
    "iso:country":"CH",
    "sg:city":"Wasen",
    "sg:classifiers":[
        {
            "category":"Banks & Credit Unions",
            "subcategory":"Bank",
            "type":"Services"
        }
    ],
    "sg:phone":"+41 4134771554",
    "sg:postcode":"3457",
    "sg:province":"Bern",
    "wof:name":"Amtsersparniskasse Sumiswald",
    "wof:placetype":"venue"
},
  "geometry": {"coordinates":[7.797653,47.043568],"type":"Point"}
}