{
  "type": "Feature",
  "properties": {
    "iso:country":"CH",
    "sg:address":"Pierre Rue Saint- 4",
    "sg:city":"Fribourg",
    "sg:orig_category":"Non-Classified Establishments",
    "sg:phone":"+41 22 321 45 80",
    "sg:postcode":"1700",
    "sg:province":"Fribourg",
    "wof:name":"Eca Holdings Sa",
    "wof:placetype":"venue"
},
  "geometry": {"coordinates":[7.1546912193,46.8035240173],"type":"Point"}
}