{
  "type": "Feature",
  "properties": {
    "iso:country":"CH",
    "sg:address":"Ch. De La Rochelle 24",
    "sg:city":"Prilly",
    "sg:orig_category":"Sanit\u00e4r, Heizungs U L\u00fcftungsinstallation",
    "sg:phone":"+41 21 634 34 33",
    "sg:postcode":"1008",
    "sg:province":"Vaud",
    "wof:name":"Sanitec Sa",
    "wof:placetype":"venue"
},
  "geometry": {"coordinates":[6.586206913,46.5302238464],"type":"Point"}
}