{
  "type": "Feature",
  "properties": {
    "iso:country":"CH",
    "sg:address":"Chemin Du Barillet 1926 Fully Case Postale 142",
    "sg:city":"Fully",
    "sg:orig_category":"Rebbau",
    "sg:phone":"+41 27 746 10 58",
    "sg:postcode":"1926",
    "sg:province":"Valais",
    "wof:name":"Laurent Roduit P\u00e9pini\u00e9riste-viticulteur",
    "wof:placetype":"venue"
},
  "geometry": {"coordinates":[7.103913784,46.130859375],"type":"Point"}
}