{
  "type": "Feature",
  "properties": {
    "iso:country":"CH",
    "sg:address":"Spielmatte",
    "sg:city":"Gunzwil",
    "sg:orig_category":"Wirtschafts- and Arbeitgeberverb\u00e4nde",
    "sg:phone":"+41 41 930 28 46",
    "sg:postcode":"6222",
    "sg:province":"Luzern",
    "wof:name":"Schweiz.kaminfegermeister- Verband Herrn Hans Weibel",
    "wof:placetype":"venue"
},
  "geometry": {"coordinates":[8.1826896667,47.2092132568],"type":"Point"}
}