{
  "type": "Feature",
  "properties": {
    "iso:country":"CH",
    "sg:address":"Route De Villette 15",
    "sg:city":"Th\u00f4nex",
    "sg:orig_category":"Detailhandel mit M\u00f6beln U Haushaltsgegenst\u00e4nden Grosshandel mit M\u00f6beln, Wohnbedarf, Teppichen U Bode",
    "sg:phone":"+41 22 347 02 79",
    "sg:postcode":"1226",
    "sg:province":"Gen\u00e8ve",
    "wof:name":"Mobilier M\u00e9tallique Moderne Sa",
    "wof:placetype":"venue"
},
  "geometry": {"coordinates":[6.1872720718,46.1841392517],"type":"Point"}
}