{
  "type": "Feature",
  "properties": {
    "iso:country":"CH",
    "sg:address":"Portstrasse 38 2503 Biel/bienne. Postfach 427",
    "sg:city":"Biel/bienne",
    "sg:orig_category":"HERSTELLUNG VON GER\u00c4TEN DER ELEKTRIZIT\u00c4TSERZEUGUNG, -VERTEILUNG U.\u00c4 Herstellung von Metallerzeugniss",
    "sg:phone":"+41 32 366 56 00",
    "sg:postcode":"2501",
    "sg:province":"Bern",
    "wof:name":"Contelec Sa",
    "wof:placetype":"venue"
},
  "geometry": {"coordinates":[7.25961,47.124821],"type":"Point"}
}