{
  "type": "Feature",
  "properties": {
    "iso:country":"CH",
    "sg:address":"Thunstrasse 1",
    "sg:city":"Biglen",
    "sg:orig_category":"Grosshandel mit Schuhen",
    "sg:phone":"+41 31 701 14 93",
    "sg:postcode":"3507",
    "sg:province":"Bern",
    "wof:name":"Rolf Schneider Schuhagentur",
    "wof:placetype":"venue"
},
  "geometry": {"coordinates":[7.6304779053,46.9246559143],"type":"Point"}
}