{
  "type": "Feature",
  "properties": {
    "iso:country":"CH",
    "sg:address":"Fribourg Rue De 5 1201 Gen\u00e8ve. Postfach",
    "sg:city":"Gen\u00e8ve",
    "sg:orig_category":"Vermietung von Gebrauchsg\u00fctern",
    "sg:postcode":"1201",
    "sg:province":"Gen\u00e8ve",
    "wof:name":"Sabi Vid\u00e9o Sa",
    "wof:placetype":"venue"
},
  "geometry": {"coordinates":[6.1449217796,46.2106437683],"type":"Point"}
}