{
  "type": "Feature",
  "properties": {
    "iso:country":"CH",
    "sg:address":"R\u00fcdigerstrasse 17 8000 Z\u00fcrich. Postfach 8045 Z\u00fcrich",
    "sg:city":"Zust",
    "sg:orig_category":"Sonstiger Grosshandel",
    "sg:postcode":"45",
    "wof:name":"Titex Ag",
    "wof:placetype":"venue"
},
  "geometry": {"coordinates":[8.5217609406,47.3600234985],"type":"Point"}
}