{
  "type": "Feature",
  "properties": {
    "iso:country":"CH",
    "sg:address":"Wieshaldenstrasse 7",
    "sg:city":"Stettfurt",
    "sg:orig_category":"Erbringung von Dienstleistungen f\u00fcr Unternehmen",
    "sg:phone":"+41 52 376 34 64",
    "sg:postcode":"9507",
    "sg:province":"Thurgau",
    "wof:name":"Credecco, Individuelle Dekorationen, Kuster Marion",
    "wof:placetype":"venue"
},
  "geometry": {"coordinates":[8.9508399963,47.5272903442],"type":"Point"}
}