{
  "type": "Feature",
  "properties": {
    "iso:country":"CH",
    "sg:address":"G\u00e4mpi 61",
    "sg:city":"Adligenswil",
    "sg:orig_category":"Fachdetailhandel mit pharmazeutischen Produkten",
    "sg:postcode":"6043",
    "sg:province":"Luzern",
    "wof:name":"Kep Trade Sohi Elisabeth M.",
    "wof:placetype":"venue"
},
  "geometry": {"coordinates":[8.3662853241,47.0670433044],"type":"Point"}
}