{
  "type": "Feature",
  "properties": {
    "addr:full":"R\u00e9sidence Jeanne D'arc 3962 Montana-vermala Case Postale 152 Montana-vermala 3962",
    "addr:housenumber":"3962;152",
    "addr:postcode":"3962",
    "addr:street":"Montana-Vermala Case Postale",
    "iso:country":"CH",
    "sg:address":"R\u00e9sidence Jeanne D'arc 3962 Montana-vermala Case Postale 152",
    "sg:city":"Montana-vermala",
    "sg:orig_category":"Architekturb\u00fcros",
    "sg:phone":"+41 79 408 39 31",
    "sg:postcode":"3962",
    "wof:name":"Alfred M. Gysin Bureau D'architecture",
    "wof:placetype":"venue"
},
  "geometry": {"coordinates":[7.483332,46.311977],"type":"Point"}
}