{
  "type": "Feature",
  "properties": {
    "iso:country":"CH",
    "sg:address":"Rue Saint-laurent 8",
    "sg:city":"Lausanne",
    "sg:orig_category":"Herstellung von sonstigen M\u00f6beln",
    "sg:phone":"+41 21 312 64 82",
    "sg:postcode":"1003",
    "sg:province":"Vaud",
    "wof:name":"Fontannaz Serge",
    "wof:placetype":"venue"
},
  "geometry": {"coordinates":[6.6315069199,46.5224609375],"type":"Point"}
}