{
  "type": "Feature",
  "properties": {
    "iso:country":"CH",
    "sg:address":"Stampfenbachstrasse 117 8006 Z\u00fcrich. Postfach",
    "sg:city":"Z\u00fcrich",
    "sg:orig_category":"Erbringung von Dienstleistungen f\u00fcr Unternehmen",
    "sg:phone":"+41 13659595",
    "sg:postcode":"8035",
    "sg:province":"Z\u00fcrich",
    "wof:name":"Weco Inkasso Ag",
    "wof:placetype":"venue"
},
  "geometry": {"coordinates":[8.5399608612,47.3842658997],"type":"Point"}
}