{
  "type": "Feature",
  "properties": {
    "addr:full":"Via Emilio Bossi 15 Chiasso Ticino 6830",
    "addr:housenumber":"15",
    "addr:postcode":"6830",
    "addr:street":"Via Emilio Bossi;Ticino",
    "iso:country":"CH",
    "sg:address":"Via Emilio Bossi 15",
    "sg:city":"Chiasso",
    "sg:classifiers":[
        {
            "category":"Bars & Pubs",
            "type":"Food & Drink"
        }
    ],
    "sg:phone":"+41 91 682 75 81",
    "sg:postcode":"6830",
    "sg:province":"Ticino",
    "wof:name":"Bar Bortolo",
    "wof:placetype":"venue"
},
  "geometry": {"coordinates":[9.030996,45.834419],"type":"Point"}
}