{
  "type": "Feature",
  "properties": {
    "iso:country":"CH",
    "sg:address":"Route De Neuch\u00e2tel 61",
    "sg:city":"Cudrefin",
    "sg:orig_category":"Malerei Tapeziererei",
    "sg:phone":"+41 26 677 17 91",
    "sg:postcode":"1588",
    "sg:province":"Vaud",
    "wof:name":"Daniel Claude Peinture & Papier-peints",
    "wof:placetype":"venue"
},
  "geometry": {"coordinates":[7.0249509811,46.9588623047],"type":"Point"}
}