{
  "type": "Feature",
  "properties": {
    "iso:country":"CH",
    "sg:address":"Bkw-strasse",
    "sg:city":"Kandergrund",
    "sg:orig_category":"Allgemeiner Hochbau Dachdeckerei",
    "sg:phone":"+41 79 445 07 26",
    "sg:postcode":"3716",
    "sg:province":"Bern",
    "wof:name":"Anton Zurbr\u00fcgg Bedachungen & Fassadenbau",
    "wof:placetype":"venue"
},
  "geometry": {"coordinates":[7.659216,46.543274],"type":"Point"}
}