{
  "type": "Feature",
  "properties": {
    "iso:country":"CH",
    "sg:address":"Obere Hauptgasse 46",
    "sg:city":"Thun",
    "sg:classifiers":[
        {
            "category":"Restaurant",
            "type":"Food & Drink"
        }
    ],
    "sg:phone":"+41 33 222 24 20",
    "sg:postcode":"3600",
    "sg:province":"Bern",
    "wof:name":"Restaurant Primavera",
    "wof:placetype":"venue"
},
  "geometry": {"coordinates":[7.630136013,46.7585449219],"type":"Point"}
}