{
  "type": "Feature",
  "properties": {
    "iso:country":"CH",
    "sg:address":"Schinhalten 9",
    "sg:city":"Stans",
    "sg:orig_category":"Sonstiger Grosshandel",
    "sg:phone":"+41 41 612 15 44",
    "sg:postcode":"6370",
    "sg:province":"Nidwalden",
    "wof:name":"Christen & Co Schalung & Mauerwerk",
    "wof:placetype":"venue"
},
  "geometry": {"coordinates":[8.365904808,46.9572486877],"type":"Point"}
}