{
  "type": "Feature",
  "properties": {
    "iso:country":"CH",
    "sg:address":"Zimmerberg 20",
    "sg:city":"Beringen",
    "sg:orig_category":"Detailhandel mit M\u00f6beln Innenausbau",
    "sg:phone":"+41 52 685 25 14",
    "sg:postcode":"8222",
    "sg:province":"Schaffhausen",
    "wof:name":"Adolf Thalmann M\u00f6bel & Innenausbau",
    "wof:placetype":"venue"
},
  "geometry": {"coordinates":[8.5743455887,47.7022323608],"type":"Point"}
}