{
  "type": "Feature",
  "properties": {
    "iso:country":"CH",
    "sg:address":"Via San Gottardo 50",
    "sg:city":"Biasca",
    "sg:orig_category":"Mechanische Werkst\u00e4tten",
    "sg:phone":"+41 91 862 26 74",
    "sg:postcode":"6710",
    "sg:province":"Ticino",
    "wof:name":"Vittorio Gennaro Affilature Attrezzi",
    "wof:placetype":"venue"
},
  "geometry": {"coordinates":[8.9636611938,46.3599205017],"type":"Point"}
}