{
  "type": "Feature",
  "properties": {
    "iso:country":"CH",
    "sg:address":"Ueberlandstrasse 351",
    "sg:city":"Z\u00fcrich",
    "sg:orig_category":"Stukkateurgewerbe, Gipserei U Verputzerei",
    "sg:phone":"+41 13229974",
    "sg:postcode":"8051",
    "sg:province":"Z\u00fcrich",
    "wof:name":"Stanco Gipsergesch\u00e4ft Gmbh",
    "wof:placetype":"venue"
},
  "geometry": {"coordinates":[8.5825443268,47.4082870483],"type":"Point"}
}