{
  "type": "Feature",
  "properties": {
    "addr:full":"Laufenstrasse 4 Breitenbach Solothurn 4226",
    "addr:housenumber":"4",
    "addr:postcode":"4226",
    "addr:street":"Laufenstrasse",
    "iso:country":"CH",
    "sg:address":"Laufenstrasse 4",
    "sg:city":"Breitenbach",
    "sg:orig_category":"Arztpraxen",
    "sg:phone":"+41 61 781 33 88",
    "sg:postcode":"4226",
    "sg:province":"Solothurn",
    "wof:name":"Dres Med. Huber & Mateos Wick Spezial\u00e4rzte Fmh",
    "wof:placetype":"venue"
},
  "geometry": {"coordinates":[7.542829,47.408154],"type":"Point"}
}