{
  "type": "Feature",
  "properties": {
    "iso:country":"CH",
    "sg:address":"Rilke Rue Rainer Maria 1",
    "sg:city":"Sierre",
    "sg:orig_category":"Fachdetailhandel in Verkaufsr\u00e4umen",
    "sg:phone":"+41 79 352 03 05",
    "sg:postcode":"3960",
    "sg:province":"Valais",
    "wof:name":"Lunetterie Junior Enfants Et Adultes Hansen Sven",
    "wof:placetype":"venue"
},
  "geometry": {"coordinates":[7.530875206,46.2927627563],"type":"Point"}
}