{
  "type": "Feature",
  "properties": {
    "iso:country":"CH",
    "sg:address":"Hauptstrasse 81 4853 Murgenthal. Postfach",
    "sg:city":"Murgenthal",
    "sg:orig_category":"Non-Classified Establishments",
    "sg:postcode":"4853",
    "sg:province":"Aargau",
    "wof:name":"Bueckle Holding Gmbh, Lauffen A.n. (d), Zweigniederlassung Murgenthal Beteiligungen Usw",
    "wof:placetype":"venue"
},
  "geometry": {"coordinates":[7.840692997,47.2716941833],"type":"Point"}
}