{
  "type": "Feature",
  "properties": {
    "iso:country":"CH",
    "sg:address":"Obere Plessurstrasse 39",
    "sg:city":"Chur",
    "sg:orig_category":"Kauf U Verkauf von Immobilien auf eigene Rechnung",
    "sg:postcode":"7000",
    "sg:province":"Graubunden",
    "wof:name":"Indom Ag",
    "wof:placetype":"venue"
},
  "geometry": {"coordinates":[9.5266304016,46.8496780396],"type":"Point"}
}