{
  "type": "Feature",
  "properties": {
    "iso:country":"CH",
    "sg:address":"Dorf 31",
    "sg:city":"Krummenau",
    "sg:orig_category":"Sanit\u00e4rinstallation U Spenglerei Zimmerei, Dachdeckerei, Bauspenglerei U Abdichtung",
    "sg:phone":"+41 71 994 36 73",
    "sg:postcode":"9643",
    "sg:province":"St. Gallen",
    "wof:name":"B\u00f6sch Josef",
    "wof:placetype":"venue"
},
  "geometry": {"coordinates":[9.1713256836,47.2484703064],"type":"Point"}
}