{
  "type": "Feature",
  "properties": {
    "iso:country":"CH",
    "sg:address":"Burghaldenweg 10",
    "sg:city":"Zurzach",
    "sg:orig_category":"Sportvereine Alpinismus",
    "sg:phone":"+41 56 249 26 68",
    "sg:postcode":"5330",
    "sg:province":"Aargau",
    "wof:name":"Sac Sektion L\u00e4gern Zurzach",
    "wof:placetype":"venue"
},
  "geometry": {"coordinates":[8.3008747101,47.5856628418],"type":"Point"}
}