{
  "type": "Feature",
  "properties": {
    "iso:country":"CH",
    "sg:address":"Chameilles Chemin Des 1",
    "sg:city":"Blonay",
    "sg:orig_category":"Unclassifiable Establishments",
    "sg:postcode":"1807",
    "sg:province":"Vaud",
    "wof:name":"Fmanagement Sa",
    "wof:placetype":"venue"
},
  "geometry": {"coordinates":[6.8968000412,46.4690704346],"type":"Point"}
}