{
  "type": "Feature",
  "properties": {
    "iso:country":"CH",
    "sg:address":"Baarerstrasse 34",
    "sg:city":"Zug",
    "sg:orig_category":"Wirtschaftspr\u00fcfung, Steuerberatung U Treuhand",
    "sg:postcode":"6300",
    "sg:province":"Zug",
    "wof:name":"Serves Ag Zug",
    "wof:placetype":"venue"
},
  "geometry": {"coordinates":[8.5170812607,47.1742134094],"type":"Point"}
}