{
  "type": "Feature",
  "properties": {
    "iso:country":"CH",
    "sg:address":"Montalinstrass 14",
    "sg:city":"Trimmis",
    "sg:orig_category":"Unclassifiable Establishments",
    "sg:phone":"+41 81 353 49 19",
    "sg:postcode":"7203",
    "sg:province":"Graubunden",
    "wof:name":"Onlain Ag",
    "wof:placetype":"venue"
},
  "geometry": {"coordinates":[9.5614376068,46.901134491],"type":"Point"}
}