{
  "type": "Feature",
  "properties": {
    "iso:country":"CH",
    "sg:address":"Viaduktstrasse 44 4051 Basel. Postfach",
    "sg:city":"Basel",
    "sg:orig_category":"Arbeitslosenkassen ALV",
    "sg:phone":"+41 61 264 22 22",
    "sg:postcode":"4002",
    "sg:province":"Basel-Stadt",
    "wof:name":"Allg. Arbeitslosenkasse In Basel",
    "wof:placetype":"venue"
},
  "geometry": {"coordinates":[7.58608,47.548969],"type":"Point"}
}