{
  "type": "Feature",
  "properties": {
    "iso:country":"CH",
    "sg:address":"Ziegelbr\u00fcckstrasse 82 8867 Niederurnen. Postfach",
    "sg:city":"Niederurnen",
    "sg:orig_category":"Unternehmensberatung",
    "sg:phone":"+41 19141212",
    "sg:postcode":"8867",
    "sg:province":"Glarus",
    "wof:name":"Mab Management Beratung Ag",
    "wof:placetype":"venue"
},
  "geometry": {"coordinates":[8.5808334351,47.3172569275],"type":"Point"}
}