{
  "type": "Feature",
  "properties": {
    "iso:country":"CH",
    "sg:address":"8867",
    "sg:city":"Niederurnen",
    "sg:orig_category":"Vereine Damen Vereine Gesang",
    "sg:postcode":"8867",
    "sg:province":"Glarus",
    "wof:name":"T\u00f6chterchor Niederurnen",
    "wof:placetype":"venue"
},
  "geometry": {"coordinates":[9.052895546,47.1254081726],"type":"Point"}
}