{
  "type": "Feature",
  "properties": {
    "iso:country":"CH",
    "sg:address":"Route De Chantemerle 18",
    "sg:city":"Granges-paccot",
    "sg:orig_category":"Pensionskassen",
    "sg:postcode":"1763",
    "sg:province":"Fribourg",
    "wof:name":"Fonds De Pr\u00e9voyance En Faveur Du Personnel De La Maison Antoine Marchon Sa",
    "wof:placetype":"venue"
},
  "geometry": {"coordinates":[7.1453700066,46.8208007812],"type":"Point"}
}