{
  "type": "Feature",
  "properties": {
    "iso:country":"CH",
    "sg:address":"Chemin Pontverre 12",
    "sg:city":"Confignon",
    "sg:orig_category":"Reiseb\u00fcros U Reiseveranstalter",
    "sg:postcode":"1232",
    "sg:province":"Gen\u00e8ve",
    "wof:name":"Voyages Concept, Roehrich Jean-daniel Et Cadoux Steve & Cie",
    "wof:placetype":"venue"
},
  "geometry": {"coordinates":[6.0815329552,46.1734809875],"type":"Point"}
}