{
  "type": "Feature",
  "properties": {
    "iso:country":"CH",
    "sg:address":"Rue De La Raisse 2",
    "sg:city":"Glovelier",
    "sg:orig_category":"Instandhaltung U Reparatur von Automobilen",
    "sg:phone":"+41 32 426 72 68",
    "sg:postcode":"2855",
    "sg:province":"Jura",
    "wof:name":"Jean Hertzeisen Voyages En Autocars",
    "wof:placetype":"venue"
},
  "geometry": {"coordinates":[7.2054038048,47.33411026],"type":"Point"}
}