{
  "type": "Feature",
  "properties": {
    "iso:country":"CH",
    "sg:address":"Borgo Via 24",
    "sg:city":"Ascona",
    "sg:orig_category":"Grosshandel mit sonstigen Gebrauchs U Verbrauchsg\u00fctern",
    "sg:postcode":"6612",
    "sg:province":"Ticino",
    "wof:name":"Sia Color Sa",
    "wof:placetype":"venue"
},
  "geometry": {"coordinates":[8.7677602768,46.1561355591],"type":"Point"}
}