{
  "type": "Feature",
  "properties": {
    "iso:country":"CH",
    "sg:address":"5210",
    "sg:city":"Windisch",
    "sg:orig_category":"Politische Parteien SVP",
    "sg:phone":"+41 55 644 13 07",
    "sg:postcode":"5210",
    "sg:province":"Aargau",
    "wof:name":"Dvp/svp Sektion Glarus",
    "wof:placetype":"venue"
},
  "geometry": {"coordinates":[9.0683546066,47.0044021606],"type":"Point"}
}