{
  "type": "Feature",
  "properties": {
    "iso:country":"CH",
    "sg:address":"Route De Sion 14",
    "sg:city":"Sierre",
    "sg:orig_category":"Arztpraxen",
    "sg:phone":"+41 27 455 07 44",
    "sg:postcode":"3960",
    "sg:province":"Valais",
    "wof:name":"Dr M\u00e9d. Gabriella Rossier M\u00e9decin G\u00e9n\u00e9raliste",
    "wof:placetype":"venue"
},
  "geometry": {"coordinates":[7.52514,46.290474],"type":"Point"}
}