{
  "type": "Feature",
  "properties": {
    "iso:country":"CH",
    "sg:address":"Bahnhofplatz 1",
    "sg:city":"Frick",
    "sg:orig_category":"Advokaturb\u00fcros Notariate",
    "sg:phone":"+41 62 871 34 33",
    "sg:postcode":"5070",
    "sg:province":"Aargau",
    "wof:name":"Dr. Benno Studer Advokatur-& Notariatsb\u00fcro",
    "wof:placetype":"venue"
},
  "geometry": {"coordinates":[8.01853,47.508369],"type":"Point"}
}