{
  "type": "Feature",
  "properties": {
    "iso:country":"CH",
    "sg:address":"Nordheimstrasse 6",
    "sg:city":"Z\u00fcrich",
    "sg:orig_category":"Vorschulen, Kinderg\u00e4rten",
    "sg:phone":"+41 71 278 22 74",
    "sg:postcode":"8057",
    "sg:province":"Z\u00fcrich",
    "wof:name":"St\u00e4dtischer Kindergarten",
    "wof:placetype":"venue"
},
  "geometry": {"coordinates":[9.3666505814,47.4125595093],"type":"Point"}
}