{
  "type": "Feature",
  "properties": {
    "iso:country":"CH",
    "sg:address":"Im Moos 24",
    "sg:city":"Urdorf",
    "sg:orig_category":"Primarschulen",
    "sg:phone":"+41 17343337",
    "sg:postcode":"8902",
    "sg:province":"Z\u00fcrich",
    "wof:name":"Primarschule Moosmatt",
    "wof:placetype":"venue"
},
  "geometry": {"coordinates":[8.4253454208,47.3883285522],"type":"Point"}
}