{
  "type": "Feature",
  "properties": {
    "iso:country":"CH",
    "sg:address":"Poststrasse 3 8212 Neuhausen. Postfach 521",
    "sg:city":"Neuhausen",
    "sg:orig_category":"Elektroinstallation",
    "sg:phone":"+41 52 672 27 07",
    "sg:postcode":"8212",
    "sg:province":"Schaffhausen",
    "wof:name":"R. Auf Der Maur, Elektroinstallationen",
    "wof:placetype":"venue"
},
  "geometry": {"coordinates":[8.6204051971,47.6826057434],"type":"Point"}
}