{
  "type": "Feature",
  "properties": {
    "iso:country":"CH",
    "sg:address":"6810 Isone. Postfach 30",
    "sg:city":"Isone",
    "sg:orig_category":"Sportvereine Ballsport Fussball",
    "sg:phone":"+41 91 814 26 18",
    "sg:postcode":"6810",
    "sg:province":"Ticino",
    "wof:name":"As Isone",
    "wof:placetype":"venue"
},
  "geometry": {"coordinates":[8.9871416092,46.1296043396],"type":"Point"}
}