{
  "type": "Feature",
  "properties": {
    "iso:country":"CH",
    "sg:address":"Rancate",
    "sg:city":"Rancate",
    "sg:classifiers":[
        {
            "category":"Banks & Credit Unions",
            "subcategory":"Bank",
            "type":"Services"
        }
    ],
    "sg:phone":"+41 4191462666",
    "sg:postcode":"6862",
    "sg:province":"Ticino",
    "wof:name":"Cassa Raiffeisen Di Rancate",
    "wof:placetype":"venue"
},
  "geometry": {"coordinates":[8.97055,45.874519],"type":"Point"}
}