{
  "type": "Feature",
  "properties": {
    "iso:country":"CH",
    "sg:address":"6716",
    "sg:city":"Leontica",
    "sg:orig_category":"Primarschulen",
    "sg:phone":"+41 91 754 21 94",
    "sg:postcode":"6716",
    "sg:province":"Ticino",
    "wof:name":"Scuola Elementare",
    "wof:placetype":"venue"
},
  "geometry": {"coordinates":[8.9245700836,46.4594306946],"type":"Point"}
}