{
  "type": "Feature",
  "properties": {
    "iso:country":"CH",
    "sg:address":"Badstrasse 78",
    "sg:city":"Zurzach",
    "sg:orig_category":"Kaminfeger",
    "sg:phone":"+41 56 249 30 63",
    "sg:postcode":"5330",
    "sg:province":"Aargau",
    "wof:name":"Andreas Gersbach Kaminfegermeister",
    "wof:placetype":"venue"
},
  "geometry": {"coordinates":[8.2836561203,47.5938453674],"type":"Point"}
}