{
  "type": "Feature",
  "properties": {
    "iso:country":"CH",
    "sg:address":"Bahnhofstrasse 2",
    "sg:city":"Oberuzwil",
    "sg:orig_category":"Herstellung von Radio U Fernsehger\u00e4ten sowie phono U videotechnischen Ger\u00e4ten",
    "sg:postcode":"9242",
    "sg:province":"St. Gallen",
    "wof:name":"Edv Consulting L\u00fctscher",
    "wof:placetype":"venue"
},
  "geometry": {"coordinates":[9.1227626801,47.4308662415],"type":"Point"}
}