{
  "type": "Feature",
  "properties": {
    "iso:country":"CH",
    "sg:address":"8222",
    "sg:city":"Beringen",
    "sg:orig_category":"Vereine Abstinenten",
    "sg:postcode":"8222",
    "sg:province":"Schaffhausen",
    "wof:name":"Blaues Kreuz",
    "wof:placetype":"venue"
},
  "geometry": {"coordinates":[8.5766687393,47.6964035034],"type":"Point"}
}