{
  "type": "Feature",
  "properties": {
    "iso:country":"CH",
    "sg:address":"Herrmoos 78",
    "sg:city":"B\u00fchler",
    "sg:orig_category":"Maler U Glasergewerbe Malerei",
    "sg:phone":"+41 71 793 17 70",
    "sg:postcode":"9055",
    "sg:province":"Appenzell Ausserrhoden",
    "wof:name":"Marco Sutter, Malergesch\u00e4ft",
    "wof:placetype":"venue"
},
  "geometry": {"coordinates":[9.4251928329,47.3722686768],"type":"Point"}
}