{
  "type": "Feature",
  "properties": {
    "iso:country":"CH",
    "sg:address":"Ehrli",
    "sg:city":"Sattel",
    "sg:orig_category":"Herstellung von sonstigen elektrischen Ausr\u00fcstungen Mechanische Werkst\u00e4tten",
    "sg:phone":"+41 41 835 17 70",
    "sg:postcode":"6417",
    "sg:province":"Schwyz",
    "wof:name":"Kkv Ag",
    "wof:placetype":"venue"
},
  "geometry": {"coordinates":[8.6224336624,47.0715408325],"type":"Point"}
}