{
  "type": "Feature",
  "properties": {
    "iso:country":"CH",
    "sg:address":"Schmiedgasse 16",
    "sg:city":"Diessenhofen",
    "sg:orig_category":"Aktivit\u00e4ten der Krankenschwestern U Hebammen, Hauspflege Organisationen des Gesundheitswesen",
    "sg:phone":"+41 52 657 24 34",
    "sg:postcode":"8253",
    "sg:province":"Thurgau",
    "wof:name":"Spitex Kranken-& Hauspflege",
    "wof:placetype":"venue"
},
  "geometry": {"coordinates":[8.750272,47.688972],"type":"Point"}
}