{
  "type": "Feature",
  "properties": {
    "iso:country":"CH",
    "sg:address":"Oberwilerstrasse 30",
    "sg:city":"Bottmingen",
    "sg:orig_category":"Sportvereine Turnen",
    "sg:phone":"+41 61 421 86 08",
    "sg:postcode":"4103",
    "sg:province":"Basel-Landschaft",
    "wof:name":"Turnverein Stv Bottmingen",
    "wof:placetype":"venue"
},
  "geometry": {"coordinates":[7.5662918091,47.5242271423],"type":"Point"}
}