{
  "type": "Feature",
  "properties": {
    "addr:full":"Rieden 3 Stans Nidwalden 6370",
    "addr:housenumber":"3",
    "addr:postcode":"6370",
    "addr:street":"Rieden",
    "iso:country":"CH",
    "sg:address":"Rieden 3",
    "sg:city":"Stans",
    "sg:classifiers":[
        {
            "category":"Autos & Motor Vehicles",
            "subcategory":"Auto Supplies",
            "type":"Retail Goods"
        }
    ],
    "sg:phone":"+41 848 840 898",
    "sg:postcode":"6370",
    "sg:province":"Nidwalden",
    "sg:tags":[
        "automobile",
        "accessory"
    ],
    "wof:name":"Pansport Autos Sa",
    "wof:placetype":"venue"
},
  "geometry": {"coordinates":[6.758681,47.06303],"type":"Point"}
}