{
  "type": "Feature",
  "properties": {
    "iso:country":"CH",
    "sg:address":"Rue Du Cr\u00eat 4 2740 Montagne-moutier. Postfach",
    "sg:city":"Montagne-moutier",
    "sg:orig_category":"Erschliessung von Grundst\u00fccken",
    "sg:postcode":"2740",
    "sg:province":"Bern",
    "wof:name":"Soci\u00e9t\u00e9 Coop\u00e9rative D'habitation Azur\u00e9a Logements Pr\u00e9v\u00f4tois",
    "wof:placetype":"venue"
},
  "geometry": {"coordinates":[7.3833498955,47.2825317383],"type":"Point"}
}