{
  "type": "Feature",
  "properties": {
    "iso:country":"CH",
    "sg:address":"1762 Givisiez. Postfach",
    "sg:city":"Daillettes",
    "sg:orig_category":"Haltung von Rindern",
    "sg:postcode":"1700",
    "sg:province":"Fribourg",
    "wof:name":"Viehzuchtgenossenschaft R\u00f6thenbach I.e.",
    "wof:placetype":"venue"
},
  "geometry": {"coordinates":[7.7429900169,46.8556518555],"type":"Point"}
}