{
  "type": "Feature",
  "properties": {
    "iso:country":"CH",
    "sg:address":"Rehwiesenstrasse 4",
    "sg:city":"Zurzach",
    "sg:orig_category":"Fahrschulen, Flugschulen",
    "sg:phone":"+41 56 249 26 45",
    "sg:postcode":"5330",
    "sg:province":"Aargau",
    "wof:name":"Walter Frehner Autofahrschule",
    "wof:placetype":"venue"
},
  "geometry": {"coordinates":[8.2945671082,47.5832443237],"type":"Point"}
}