{
  "type": "Feature",
  "properties": {
    "iso:country":"CH",
    "sg:address":"Avenue Du Grand-champsec 86",
    "sg:city":"Sion",
    "sg:orig_category":"Interessenvertretungen",
    "sg:phone":"+41 27 603 47 00",
    "sg:postcode":"1950",
    "sg:province":"Valais",
    "wof:name":"Institut Central Des H\u00f4pitaux Valaisans",
    "wof:placetype":"venue"
},
  "geometry": {"coordinates":[7.3858389854,46.235710144],"type":"Point"}
}