{
  "type": "Feature",
  "properties": {
    "iso:country":"CH",
    "sg:address":"Mattackerstrasse 61",
    "sg:city":"Z\u00fcrich",
    "sg:classifiers":[
        {
            "category":"Communications",
            "subcategory":"Film & Video Production",
            "type":"Services"
        }
    ],
    "sg:phone":"+41 79 239 13 47",
    "sg:postcode":"8052",
    "sg:province":"Z\u00fcrich",
    "sg:tags":[
        "videofilmherstellung",
        "u"
    ],
    "wof:name":"Magic Camera Productions Benno M\u00fcessli",
    "wof:placetype":"venue"
},
  "geometry": {"coordinates":[8.5527038574,47.4259262085],"type":"Point"}
}