{
  "type": "Feature",
  "properties": {
    "iso:country":"CH",
    "sg:address":"Chemin De Chantefleur 17",
    "sg:city":"Vessy",
    "sg:orig_category":"Kosmetikinstitute",
    "sg:phone":"+41 22 784 27 55",
    "sg:postcode":"1234",
    "sg:province":"Gen\u00e8ve",
    "wof:name":"Dominique Cots Institut De Beaut\u00e9",
    "wof:placetype":"venue"
},
  "geometry": {"coordinates":[6.1606669426,46.1690444946],"type":"Point"}
}