{
  "type": "Feature",
  "properties": {
    "addr:full":"Rehb\u00fchlstrasse 30 Uster Z\u00fcrich 8610",
    "addr:housenumber":"30",
    "addr:postcode":"8610",
    "addr:street":"Rehbuehlstrasse",
    "iso:country":"CH",
    "sg:address":"Rehb\u00fchlstrasse 30",
    "sg:city":"Uster",
    "sg:orig_category":"Bezirks, Sekundar, Realschulen, Oberstufe der Primarschulen",
    "sg:postcode":"8610",
    "sg:province":"Z\u00fcrich",
    "wof:name":"Oberstufenschule Weidli",
    "wof:placetype":"venue"
},
  "geometry": {"coordinates":[8.730186,47.354504],"type":"Point"}
}