{
  "type": "Feature",
  "properties": {
    "addr:full":"Grand-rue 40 Reconvilier Bern 2732",
    "addr:housenumber":"40",
    "addr:postcode":"2732",
    "addr:street":"Grand-Rue",
    "iso:country":"CH",
    "sg:address":"Grand-rue 40",
    "sg:city":"Reconvilier",
    "sg:orig_category":"Bauschreinerei Bestattungswesen",
    "sg:phone":"+41 34 402 34 44",
    "sg:postcode":"2732",
    "sg:province":"Bern",
    "wof:name":"Rudolf Stalder Schreinerei Bestattungen",
    "wof:placetype":"venue"
},
  "geometry": {"coordinates":[7.75759,46.949127],"type":"Point"}
}