{
  "type": "Feature",
  "properties": {
    "iso:country":"CH",
    "sg:address":"G\u00fcterstrasse 250 4053 Basel. Postfach",
    "sg:city":"Basel",
    "sg:classifiers":[
        {
            "category":"Government",
            "subcategory":"Post Office",
            "type":"Public Place"
        }
    ],
    "sg:phone":"+41 61 275 75 75",
    "sg:postcode":"4021",
    "sg:tags":[
        "caf\u00e9s",
        "tea-rooms"
    ],
    "wof:name":"Caf\u00e9 Sutter Ag",
    "wof:placetype":"venue"
},
  "geometry": {"coordinates":[7.5976428986,47.5417785645],"type":"Point"}
}