{
  "type": "Feature",
  "properties": {
    "iso:country":"CH",
    "sg:address":"Mont-soleil 19",
    "sg:city":"Mont-soleil",
    "sg:classifiers":[
        {
            "category":"Travel",
            "subcategory":"Hotels & Motels",
            "type":"Entertainment"
        }
    ],
    "sg:postcode":"2610",
    "sg:province":"Bern",
    "sg:tags":[
        "hotels",
        "mit",
        "restaurant"
    ],
    "wof:name":"Spielmann Erika",
    "wof:placetype":"venue"
},
  "geometry": {"coordinates":[6.9843301773,47.1547889709],"type":"Point"}
}