{
  "type": "Feature",
  "properties": {
    "iso:country":"CH",
    "sg:address":"Hinterbergstrasse 19-21",
    "sg:city":"Cham",
    "sg:orig_category":"Non-Classified Establishments",
    "sg:postcode":"6330",
    "sg:province":"Zug",
    "wof:name":"Mathis Treuhand",
    "wof:placetype":"venue"
},
  "geometry": {"coordinates":[8.4777965546,47.1876678467],"type":"Point"}
}