{
  "type": "Feature",
  "properties": {
    "iso:country":"CH",
    "sg:address":"Sole Piazza Del 6500 Bellinzona Casella Postale 2848",
    "sg:city":"Bellinzona",
    "sg:orig_category":"Allgemeiner Hoch U Tiefbau",
    "sg:phone":"+41 91 835 55 10",
    "sg:postcode":"6500",
    "sg:province":"Ticino",
    "wof:name":"Zschokke Entreprise G\u00e9n\u00e9rale Sa Costruzioni; Studio, Direzione E Esecuzione Ecc. Immobili",
    "wof:placetype":"venue"
},
  "geometry": {"coordinates":[9.024119,46.194462],"type":"Point"}
}