{
  "type": "Feature",
  "properties": {
    "iso:country":"CH",
    "sg:address":"Grand-rue 66",
    "sg:city":"Fribourg",
    "sg:orig_category":"Grosshandel mit Nahrungsmitteln, Getr\u00e4nken U Tabakwaren ohne ausgepr\u00e4gten Schwerpunkt Wein Detailhan",
    "sg:phone":"+41 79 214 22 04",
    "sg:postcode":"1700",
    "sg:province":"Fribourg",
    "wof:name":"Cantina Del Mulino Ag",
    "wof:placetype":"venue"
},
  "geometry": {"coordinates":[7.1622328758,46.8057174683],"type":"Point"}
}