{
  "type": "Feature",
  "properties": {
    "iso:country":"CH",
    "sg:address":"Schmiedenstrasse 21",
    "sg:city":"Einsiedeln",
    "sg:classifiers":[
        {
            "category":"Restaurant",
            "type":"Food & Drink"
        }
    ],
    "sg:phone":"+41 55 412 24 21",
    "sg:postcode":"8840",
    "sg:province":"Schwyz",
    "wof:name":"Restaurant Biergarten",
    "wof:placetype":"venue"
},
  "geometry": {"coordinates":[8.7479887009,47.1280212402],"type":"Point"}
}