{
  "type": "Feature",
  "properties": {
    "iso:country":"CH",
    "sg:address":"Jurastrasse 8",
    "sg:city":"Olten",
    "sg:orig_category":"Druckweiterverarbeitung",
    "sg:phone":"+41 62 212 35 30",
    "sg:postcode":"4600",
    "sg:province":"Solothurn",
    "wof:name":"Atelier Martin Flury",
    "wof:placetype":"venue"
},
  "geometry": {"coordinates":[7.9043598175,47.3529281616],"type":"Point"}
}