{
  "type": "Feature",
  "properties": {
    "iso:country":"CH",
    "sg:address":"Quellenstrasse 42 8000 Z\u00fcrich. Postfach",
    "sg:city":"Z\u00fcrich",
    "sg:orig_category":"Markt U Meinungsforschung",
    "sg:postcode":"8001",
    "sg:province":"Z\u00fcrich",
    "wof:name":"Publisprint Eschler Romer Associates",
    "wof:placetype":"venue"
},
  "geometry": {"coordinates":[8.5289936066,47.3861312866],"type":"Point"}
}