{
  "type": "Feature",
  "properties": {
    "iso:country":"CH",
    "sg:address":"Hauptstrasse 37",
    "sg:city":"Niederdorf",
    "sg:orig_category":"Detailhandel mit Fleisch U Fleischwaren",
    "sg:phone":"+41 61 961 01 13",
    "sg:postcode":"4435",
    "sg:province":"Basel-Landschaft",
    "wof:name":"Metzgerei P. Beyeler",
    "wof:placetype":"venue"
},
  "geometry": {"coordinates":[7.751475811,47.40417099],"type":"Point"}
}