{
  "type": "Feature",
  "properties": {
    "addr:full":"St. Jodernstrasse 12 Visp Valais 3930",
    "addr:housenumber":"12",
    "addr:postcode":"3930",
    "addr:street":"Jodernstrasse",
    "iso:country":"CH",
    "sg:address":"St. Jodernstrasse 12",
    "sg:city":"Visp",
    "sg:orig_category":"Architektur U Ingenieurb\u00fcros",
    "sg:phone":"+41 27 946 27 21",
    "sg:postcode":"3930",
    "sg:province":"Valais",
    "wof:name":"Architecum Gmbh",
    "wof:placetype":"venue"
},
  "geometry": {"coordinates":[7.88438,46.28595],"type":"Point"}
}