{
  "type": "Feature",
  "properties": {
    "iso:country":"CH",
    "sg:address":"Sch\u00f6negg 74",
    "sg:city":"Mirchel",
    "sg:orig_category":"Herstellung von Metallkonstruktionen Maurerarbeiten",
    "sg:phone":"+41 32 358 17 15",
    "sg:postcode":"3532",
    "sg:province":"Bern",
    "wof:name":"M\u00f6ri Andr\u00e9-michel.",
    "wof:placetype":"venue"
},
  "geometry": {"coordinates":[-112.009475708,43.5343589783],"type":"Point"}
}