{
  "type": "Feature",
  "properties": {
    "iso:country":"CH",
    "sg:address":"Ch\u00eanes Chemin Des 1967 Bramois. Postfach",
    "sg:city":"Bramois",
    "sg:orig_category":"Unclassifiable Establishments",
    "sg:phone":"+41 27 203 78 78",
    "sg:postcode":"1967",
    "sg:province":"Valais",
    "wof:name":"A-z Electricit\u00e9 S\u00e0rl",
    "wof:placetype":"venue"
},
  "geometry": {"coordinates":[7.4026799202,46.2301216125],"type":"Point"}
}