{
  "type": "Feature",
  "properties": {
    "iso:country":"CH",
    "sg:address":"Grabenring 31",
    "sg:city":"Allschwil",
    "sg:orig_category":"Handelsvermittlung von Maschinen, technischem Bedarf, Wasser U Luftfahrzeugen",
    "sg:postcode":"4123",
    "sg:province":"Basel-Landschaft",
    "wof:name":"Hummel Technik Gmbh",
    "wof:placetype":"venue"
},
  "geometry": {"coordinates":[7.5372447968,47.5549621582],"type":"Point"}
}