{
  "type": "Feature",
  "properties": {
    "iso:country":"CH",
    "sg:address":"Luzernstrasse 20",
    "sg:city":"Neuenkirch",
    "sg:orig_category":"Handel mit Motorr\u00e4dern, Teilen U Zubeh\u00f6r Instandhaltung U Reparatur von Motorr\u00e4dern",
    "sg:phone":"+41 41 467 21 22",
    "sg:postcode":"6206",
    "sg:province":"Luzern",
    "wof:name":"Velos, Motos Wicki Gmbh",
    "wof:placetype":"venue"
},
  "geometry": {"coordinates":[8.2062950134,47.0978317261],"type":"Point"}
}