{
  "type": "Feature",
  "properties": {
    "iso:country":"CH",
    "sg:address":"La Filature",
    "sg:city":"Ecl\u00e9pens",
    "sg:orig_category":"Herstellung von Holzstoff, Papier, Karton U Pappe",
    "sg:phone":"+41 17255335",
    "sg:postcode":"1312",
    "sg:province":"Vaud",
    "wof:name":"Pfh Holding",
    "wof:placetype":"venue"
},
  "geometry": {"coordinates":[8.5894126892,47.2665328979],"type":"Point"}
}