{
  "type": "Feature",
  "properties": {
    "iso:country":"CH",
    "sg:address":"Lorrainestrasse 22 3013 Bern. Postfach",
    "sg:city":"Bern",
    "sg:orig_category":"RESTAURANTS: TEA-ROOMS",
    "sg:phone":"+41 31 331 36 69",
    "sg:postcode":"3005",
    "sg:province":"Bern",
    "wof:name":"C. A. Rebmann Restaurant Feldschl\u00f6sschen",
    "wof:placetype":"venue"
},
  "geometry": {"coordinates":[7.4450001717,46.9564933777],"type":"Point"}
}