{
  "type": "Feature",
  "properties": {
    "iso:country":"CH",
    "sg:address":"Hauptstrasse 30",
    "sg:city":"Arlesheim",
    "sg:orig_category":"Non-Classified Establishments",
    "sg:phone":"+41 61 701 19 60",
    "sg:postcode":"4144",
    "sg:province":"Basel-Landschaft",
    "wof:name":"St\u00f6cklin Malergesch\u00e4ft Gmbh",
    "wof:placetype":"venue"
},
  "geometry": {"coordinates":[7.6200618744,47.4933891296],"type":"Point"}
}