{
  "type": "Feature",
  "properties": {
    "iso:country":"CH",
    "sg:address":"Sonnenb\u00f6hl 3692",
    "sg:city":"Herisau",
    "sg:orig_category":"Herstellung von sonstigen landwirtschaftlichen Maschinen",
    "sg:phone":"+41 71 351 63 90",
    "sg:postcode":"9100",
    "sg:province":"Appenzell Ausserrhoden",
    "wof:name":"Emil Anderegg Landmaschinenservice",
    "wof:placetype":"venue"
},
  "geometry": {"coordinates":[9.2733764648,47.3940086365],"type":"Point"}
}