{
  "type": "Feature",
  "properties": {
    "iso:country":"CH",
    "sg:address":"Pilatusstrasse 2",
    "sg:city":"Dierikon",
    "sg:orig_category":"Einbau von Schreinerwaren",
    "sg:phone":"+41 41 455 52 52",
    "sg:postcode":"6036",
    "sg:province":"Luzern",
    "wof:name":"Alpnach K\u00fcchen Ag",
    "wof:placetype":"venue"
},
  "geometry": {"coordinates":[8.3643636703,47.0951576233],"type":"Point"}
}