{
  "type": "Feature",
  "properties": {
    "addr:full":"Spalenvorstadt 25 Basel Basel-Stadt 4051",
    "addr:housenumber":"25",
    "addr:postcode":"4051",
    "addr:street":"Spalenvorstadt",
    "iso:country":"CH",
    "sg:address":"Spalenvorstadt 25",
    "sg:city":"Basel",
    "sg:orig_category":"Detailhandel mit Antiquit\u00e4ten Kunsthandel",
    "sg:phone":"+41 61 261 31 10",
    "sg:postcode":"4051",
    "sg:province":"Basel-Stadt",
    "wof:name":"Sandro Damioli Jugendstil-galerie-artdeco",
    "wof:placetype":"venue"
},
  "geometry": {"coordinates":[7.582271,47.557434],"type":"Point"}
}