{
  "type": "Feature",
  "properties": {
    "iso:country":"CH",
    "sg:address":"Allmendstrasse 26a",
    "sg:city":"Ennetb\u00fcrgen",
    "sg:orig_category":"Herstellung von keramischen Wand U Bodenfliesen U platten",
    "sg:phone":"+41 41 620 48 89",
    "sg:postcode":"6373",
    "sg:province":"Nidwalden",
    "wof:name":"Kaiser Werner Gmbh",
    "wof:placetype":"venue"
},
  "geometry": {"coordinates":[8.408987999,46.9823112488],"type":"Point"}
}