{
  "type": "Feature",
  "properties": {
    "iso:country":"CH",
    "sg:address":"Fallbach 1106",
    "sg:city":"Oberegg",
    "sg:orig_category":"Bauschreinerei Herstellung von Konstruktionsteilen, Fertigbauteilen U Ausbauelementen aus Holz",
    "sg:phone":"+41 71 891 52 19",
    "sg:postcode":"9413",
    "sg:province":"Appenzell Innerhoden",
    "wof:name":"Sonderegger & Breu Ag Schreinerei-zimmerei",
    "wof:placetype":"venue"
},
  "geometry": {"coordinates":[9.549387,47.421474],"type":"Point"}
}