{
  "type": "Feature",
  "properties": {
    "iso:country":"CH",
    "sg:address":"Bahnhofstrasse 19 8753 Mollis. Postfach 139",
    "sg:city":"Mollis",
    "sg:orig_category":"Betrieb von Taxis RESTAURANTS: TEA-ROOMS",
    "sg:phone":"+41 55 612 16 36",
    "sg:postcode":"8753",
    "sg:province":"Glarus",
    "wof:name":"Hauenstein Urs Restaurant Heidi's & Hauis B\u00fcndnerst\u00fcbli",
    "wof:placetype":"venue"
},
  "geometry": {"coordinates":[9.071857,47.095951],"type":"Point"}
}