{
  "type": "Feature",
  "properties": {
    "iso:country":"CH",
    "sg:address":"Es Planches 123a 2842 Rossemaison. Postfach",
    "sg:city":"Rossemaison",
    "sg:orig_category":"Gesundheitswesen",
    "sg:phone":"+41 32 422 86 12",
    "sg:postcode":"2842",
    "sg:province":"Jura",
    "wof:name":"Mg Consulting Co, De Gasparo Marc Pharmacologie, M\u00e9decine; Consultance",
    "wof:placetype":"venue"
},
  "geometry": {"coordinates":[7.3472270966,47.3444213867],"type":"Point"}
}