{
  "type": "Feature",
  "properties": {
    "iso:country":"CH",
    "sg:address":"Hardstrasse 43",
    "sg:city":"Neuenhof",
    "sg:orig_category":"Sportvereine Ballsport Handball",
    "sg:phone":"+41 41 711 41 08",
    "sg:postcode":"5432",
    "sg:province":"Aargau",
    "wof:name":"Handball-club Lk Zug",
    "wof:placetype":"venue"
},
  "geometry": {"coordinates":[8.5057401657,47.1456604004],"type":"Point"}
}