{
  "type": "Feature",
  "properties": {
    "iso:country":"CH",
    "sg:address":"Alleestrasse 31",
    "sg:city":"Romanshorn",
    "sg:orig_category":"Unclassifiable Establishments",
    "sg:postcode":"8590",
    "sg:province":"Thurgau",
    "wof:name":"Suba Susanne St\u00e4uble-b\u00e4chli",
    "wof:placetype":"venue"
},
  "geometry": {"coordinates":[9.3773031235,47.56457901],"type":"Point"}
}