{
  "type": "Feature",
  "properties": {
    "iso:country":"CH",
    "sg:address":"Zeughausgasse 20 3011 Bern. Postfach",
    "sg:city":"Bern",
    "sg:orig_category":"Detailhandel mit Bekleidung",
    "sg:phone":"+41 31 311 28 69",
    "sg:postcode":"3005",
    "sg:province":"Bern",
    "wof:name":"La Luna Bern Ag Textilien, Schuhe, Mode-artikel Usw; Handel",
    "wof:placetype":"venue"
},
  "geometry": {"coordinates":[7.445069,46.949123],"type":"Point"}
}