{
  "type": "Feature",
  "properties": {
    "iso:country":"CH",
    "sg:address":"Chemin De La Poya 5",
    "sg:city":"Oron-la-ville",
    "sg:orig_category":"Bauschreinerei Herstellung von Konstruktionsteilen, Fertigbauteilen U Ausbauelementen aus Holz",
    "sg:phone":"+41 21 907 70 32",
    "sg:postcode":"1610",
    "sg:province":"Vaud",
    "wof:name":"Komposch Bois S\u00e0rl",
    "wof:placetype":"venue"
},
  "geometry": {"coordinates":[6.827422,46.572235],"type":"Point"}
}