{
  "type": "Feature",
  "properties": {
    "iso:country":"CH",
    "sg:address":"Vermont Chemin De 20",
    "sg:city":"Yverdon-les-bains",
    "sg:orig_category":"Vermietung von Automobilen",
    "sg:phone":"+41 24 426 48 48",
    "sg:postcode":"1400",
    "sg:province":"Vaud",
    "wof:name":"Taxi Moderne, Barraud Thierry",
    "wof:placetype":"venue"
},
  "geometry": {"coordinates":[6.6414198875,46.7786331177],"type":"Point"}
}