{
  "type": "Feature",
  "properties": {
    "iso:country":"CH",
    "sg:address":"Neue Industriestr. 6",
    "sg:city":"Rothrist",
    "sg:classifiers":[
        {
            "category":"Professional",
            "subcategory":"Engineering",
            "type":"Services"
        }
    ],
    "sg:phone":"+41 62 794 42 22",
    "sg:postcode":"4852",
    "sg:province":"Aargau",
    "sg:tags":[
        "electric",
        "-",
        "component",
        "machine",
        "mechanical",
        "electronic"
    ],
    "wof:name":"M\u00dcller Martini Electronic Ag",
    "wof:placetype":"venue"
},
  "geometry": {"coordinates":[7.8683009148,47.3044586182],"type":"Point"}
}