{
  "type": "Feature",
  "properties": {
    "iso:country":"CH",
    "sg:address":"Chemin De Pesay 4",
    "sg:city":"Grand-lancy",
    "sg:orig_category":"Vereine Hundedressur",
    "sg:phone":"+41 22 342 80 14",
    "sg:postcode":"1212",
    "sg:province":"Gen\u00e8ve",
    "wof:name":"St\u00e9 Canine De Gen\u00e8ve",
    "wof:placetype":"venue"
},
  "geometry": {"coordinates":[6.127322197,46.1741943359],"type":"Point"}
}