{
  "type": "Feature",
  "properties": {
    "iso:country":"CH",
    "sg:address":"Ch. De Chamblandes 45",
    "sg:city":"Pully",
    "sg:classifiers":[
        {
            "category":"Travel",
            "subcategory":"Hotels & Motels",
            "type":"Entertainment"
        }
    ],
    "sg:postcode":"1009",
    "sg:province":"Vaud",
    "sg:tags":[
        "hotels",
        "mit",
        "restaurant"
    ],
    "wof:name":"Favre Andr\u00e9",
    "wof:placetype":"venue"
},
  "geometry": {"coordinates":[6.6462440491,46.5079536438],"type":"Point"}
}