{
  "type": "Feature",
  "properties": {
    "addr:full":"Scheidmatte Aeschiried Bern 3703",
    "addr:postcode":"3703",
    "addr:street":"Scheidmatte",
    "iso:country":"CH",
    "sg:address":"Scheidmatte",
    "sg:city":"Aeschiried",
    "sg:orig_category":"Dachdeckerei Zimmerei, Ingenieurholzbau",
    "sg:phone":"+41 79 335 96 49",
    "sg:postcode":"3703",
    "sg:province":"Bern",
    "wof:name":"Christian D\u00e4pp Bedachungen & Zimmerei",
    "wof:placetype":"venue"
},
  "geometry": {"coordinates":[7.726344,46.643478],"type":"Point"}
}