{
  "type": "Feature",
  "properties": {
    "iso:country":"CH",
    "sg:address":"Bahnhofstrasse 1 3177 Laupen Be. Postfach",
    "sg:city":"Rizenbach",
    "sg:orig_category":"Detailhandel mit Waren verschiedener Art, Hauptrichtung Nahrungsmittel",
    "sg:phone":"+41 31 931 03 18",
    "sg:postcode":"3206",
    "sg:province":"Bern",
    "wof:name":"Landi Laupen",
    "wof:placetype":"venue"
},
  "geometry": {"coordinates":[7.2381310463,46.9025382996],"type":"Point"}
}