{
  "type": "Feature",
  "properties": {
    "iso:country":"CH",
    "sg:address":"Fabrikstrasse",
    "sg:city":"Grabs",
    "sg:classifiers":[
        {
            "category":"Shopping",
            "subcategory":"Stationery & Office Supplies",
            "type":"Retail Goods"
        }
    ],
    "sg:phone":"+41 81 750 34 34",
    "sg:postcode":"9472",
    "sg:province":"St. Gallen",
    "sg:tags":[
        "adhesive",
        "label"
    ],
    "wof:name":"Etimark Ag",
    "wof:placetype":"venue"
},
  "geometry": {"coordinates":[9.452115,47.179417],"type":"Point"}
}