{
  "type": "Feature",
  "properties": {
    "iso:country":"CH",
    "sg:address":"Oberdorf Merligen.",
    "sg:city":"Sigriswil",
    "sg:orig_category":"Maler U Glasergewerbe",
    "sg:postcode":"3655",
    "sg:province":"Bern",
    "wof:name":"Von Gunten H.u.",
    "wof:placetype":"venue"
},
  "geometry": {"coordinates":[7.6979141235,46.7354698181],"type":"Point"}
}