{
  "type": "Feature",
  "properties": {
    "iso:country":"CH",
    "sg:address":"8455",
    "sg:city":"R\u00fcdlingen",
    "sg:classifiers":[
        {
            "category":"Restaurant",
            "type":"Food & Drink"
        }
    ],
    "sg:phone":"+41 52 375 14 71",
    "sg:postcode":"8455",
    "sg:province":"Schaffhausen",
    "wof:name":"Restaurant Steinfels",
    "wof:placetype":"venue"
},
  "geometry": {"coordinates":[8.8500299454,47.5623283386],"type":"Point"}
}