{
  "type": "Feature",
  "properties": {
    "iso:country":"CH",
    "sg:address":"Ribigasse 1",
    "sg:city":"H\u00f6lstein",
    "sg:orig_category":"Grosshandel mit Uhren Herstellung U Zusammensetzung von Uhren",
    "sg:phone":"+41 61 482 26 60",
    "sg:postcode":"4434",
    "sg:province":"Basel-Landschaft",
    "wof:name":"Sunvision-artwatches, Rapold Philipp",
    "wof:placetype":"venue"
},
  "geometry": {"coordinates":[7.4360589981,47.4575691223],"type":"Point"}
}