{
  "type": "Feature",
  "properties": {
    "iso:country":"CH",
    "sg:address":"Rue Caroline 5",
    "sg:city":"Lausanne",
    "sg:orig_category":"HOTELS: MIT RESTAURANT Kongress- and Tagungshotels mit Restaurant",
    "sg:phone":"+41 32 721 21 21",
    "sg:postcode":"1003",
    "sg:province":"Vaud",
    "wof:name":"Eurotel Neuch\u00e2tel",
    "wof:placetype":"venue"
},
  "geometry": {"coordinates":[6.9309840202,46.9933319092],"type":"Point"}
}