{
  "type": "Feature",
  "properties": {
    "iso:country":"CH",
    "sg:address":"Galliweg 34a",
    "sg:city":"Rothrist",
    "sg:orig_category":"Vorschulen, Kinderg\u00e4rten",
    "sg:phone":"+41 62 794 31 04",
    "sg:postcode":"4852",
    "sg:province":"Aargau",
    "wof:name":"Kindergarten Gr\u00fcebli",
    "wof:placetype":"venue"
},
  "geometry": {"coordinates":[7.8773331642,47.3012886047],"type":"Point"}
}