{
  "type": "Feature",
  "properties": {
    "iso:country":"CH",
    "sg:address":"Br\u00fcckfeldstrasse 20",
    "sg:city":"Bern",
    "sg:orig_category":"Berufsbildende weiterf\u00fchrende Schulen Hochschulen U h\u00f6here Ausbildung",
    "sg:phone":"+41 31 301 94 44",
    "sg:postcode":"3012",
    "sg:province":"Bern",
    "wof:name":"Kosmetik-fachschule Bern Kfb Luginb\u00fchl Claudia",
    "wof:placetype":"venue"
},
  "geometry": {"coordinates":[7.435931,46.95636],"type":"Point"}
}