{
  "type": "Feature",
  "properties": {
    "iso:country":"CH",
    "sg:address":"Rue Du Lion-d'or 2 1003 Lausanne Case Postale 3312",
    "sg:city":"Lausanne",
    "sg:orig_category":"Advokaturb\u00fcros",
    "sg:phone":"+41 21 312 18 44",
    "sg:postcode":"1002",
    "sg:province":"Vaud",
    "wof:name":"Mercier Marmier & Berthoud Etude D'avocat",
    "wof:placetype":"venue"
},
  "geometry": {"coordinates":[6.63045,46.519989],"type":"Point"}
}