{
  "type": "Feature",
  "properties": {
    "iso:country":"CH",
    "sg:address":"Neugutstrasse 65",
    "sg:city":"D\u00fcbendorf",
    "sg:orig_category":"Herstellung von Drahtwaren Herstellung von Schrauben, Nieten, Ketten U Federn",
    "sg:phone":"+41 18213743",
    "sg:postcode":"8600",
    "sg:province":"Z\u00fcrich",
    "wof:name":"Egli Federnfabrik Ag",
    "wof:placetype":"venue"
},
  "geometry": {"coordinates":[8.60638237,47.4002838135],"type":"Point"}
}