{
  "type": "Feature",
  "properties": {
    "iso:country":"CH",
    "sg:address":"Bruch",
    "sg:city":"Kandersteg",
    "sg:orig_category":"RESTAURANTS: TEA-ROOMS",
    "sg:postcode":"3718",
    "sg:province":"Bern",
    "wof:name":"Motiv Aktion Ag",
    "wof:placetype":"venue"
},
  "geometry": {"coordinates":[7.6812720299,46.5031547546],"type":"Point"}
}