{
  "type": "Feature",
  "properties": {
    "iso:country":"CH",
    "sg:address":"Dorfstrasse 34",
    "sg:city":"Kaisten",
    "sg:orig_category":"Institutionen f\u00fcr Suchtkranke",
    "sg:phone":"+41 61 791 01 31",
    "sg:postcode":"5082",
    "sg:province":"Aargau",
    "wof:name":"Therapeutische Gemeinschaft",
    "wof:placetype":"venue"
},
  "geometry": {"coordinates":[7.5872797966,47.3625450134],"type":"Point"}
}