{
  "type": "Feature",
  "properties": {
    "iso:country":"CH",
    "sg:address":"P\u00e9rolles Boulevard De 3",
    "sg:city":"Fribourg",
    "sg:orig_category":"Schreib U \u00dcbersetzungsb\u00fcros",
    "sg:postcode":"1700",
    "sg:province":"Fribourg",
    "wof:name":"Ordi-compta-suppleance, Golliard-fontaine M.-th.",
    "wof:placetype":"venue"
},
  "geometry": {"coordinates":[7.1154899597,46.839263916],"type":"Point"}
}