{
  "type": "Feature",
  "properties": {
    "iso:country":"CH",
    "sg:address":"Les Il\u00f4ts",
    "sg:city":"Martigny",
    "sg:orig_category":"Grosshandel mit lebenden Tieren",
    "sg:phone":"+41 27 722 85 07",
    "sg:postcode":"1920",
    "sg:province":"Valais",
    "wof:name":"Michel Darioly Commerce De B\u00e9tail",
    "wof:placetype":"venue"
},
  "geometry": {"coordinates":[7.0593352318,46.1238212585],"type":"Point"}
}