{
  "type": "Feature",
  "properties": {
    "iso:country":"CH",
    "sg:address":"Corso San Gottardo 54 6830 Chiasso Casella Postale 2616",
    "sg:city":"Chiasso",
    "sg:orig_category":"Handelsvermittlung U Grosshandel Sonstiger Grosshandel",
    "sg:phone":"+41 91 682 58 61",
    "sg:postcode":"6830",
    "sg:province":"Ticino",
    "wof:name":"Cotrans Sa Import-export",
    "wof:placetype":"venue"
},
  "geometry": {"coordinates":[9.0313053131,45.8347244263],"type":"Point"}
}