{
  "type": "Feature",
  "properties": {
    "iso:country":"CH",
    "sg:address":"Englischer Viertel 19 3920 Zermatt. Postfach 80",
    "sg:city":"Zermatt",
    "sg:orig_category":"Allgemeiner Hoch U Tiefbau Strassenbau",
    "sg:phone":"+41 27 967 12 64",
    "sg:postcode":"3920",
    "sg:province":"Valais",
    "wof:name":"Adolf Schaller Ag",
    "wof:placetype":"venue"
},
  "geometry": {"coordinates":[7.748212,46.020535],"type":"Point"}
}