{
  "type": "Feature",
  "properties": {
    "iso:country":"CH",
    "sg:address":"Avenue De La Gare 36",
    "sg:city":"Monthey",
    "sg:orig_category":"Arztpraxen",
    "sg:phone":"+41 24 471 27 33",
    "sg:postcode":"1870",
    "sg:province":"Valais",
    "wof:name":"Dr M\u00e9d. Fran\u00e7ois Kuntschen M\u00e9decin Sp\u00e9cialiste Fmh",
    "wof:placetype":"venue"
},
  "geometry": {"coordinates":[6.951796,46.254036],"type":"Point"}
}