{
  "type": "Feature",
  "properties": {
    "iso:country":"CH",
    "sg:address":"8332 Russikon. Postfach 67",
    "sg:city":"Russikon",
    "sg:orig_category":"Sportvereine Ballsport Tennis",
    "sg:phone":"+41 19550311",
    "sg:postcode":"8332",
    "sg:province":"Z\u00fcrich",
    "wof:name":"Tennisclub Russikon",
    "wof:placetype":"venue"
},
  "geometry": {"coordinates":[8.7759141922,47.3938407898],"type":"Point"}
}