{
  "type": "Feature",
  "properties": {
    "iso:country":"CH",
    "sg:address":"Villa Waldegg",
    "sg:city":"Mitl\u00f6di",
    "sg:orig_category":"Herstellung von Medikamenten U sonstigen pharmazeutischen Erzeugnissen",
    "sg:postcode":"8756",
    "sg:province":"Glarus",
    "wof:name":"Rapura Ag",
    "wof:placetype":"venue"
},
  "geometry": {"coordinates":[8.5812511444,47.3129882812],"type":"Point"}
}