{
  "type": "Feature",
  "properties": {
    "iso:country":"CH",
    "sg:address":"Airport Business Center 60 3123 Belp. Postfach",
    "sg:city":"Belp",
    "sg:orig_category":"Grosshandel mit Eisenwaren sowie Installationsbedarf f\u00fcr Gas, Wasser U Heizung Grosshandel mit sonst",
    "sg:phone":"+41 22 782 84 50",
    "sg:postcode":"3123",
    "sg:province":"Bern",
    "wof:name":"Johnson Controls Systems Sa, Succursale De Meyrin",
    "wof:placetype":"venue"
},
  "geometry": {"coordinates":[6.0751681328,46.2254486084],"type":"Point"}
}