{
  "type": "Feature",
  "properties": {
    "iso:country":"CH",
    "sg:address":"Polenl\u00f6serweg",
    "sg:city":"Untervaz",
    "sg:orig_category":"Allgemeiner Hoch U Tiefbau",
    "sg:phone":"+41 81 322 71 38",
    "sg:postcode":"7204",
    "sg:province":"Graubunden",
    "wof:name":"Reprojet Ag",
    "wof:placetype":"venue"
},
  "geometry": {"coordinates":[9.553862,46.915588],"type":"Point"}
}