{
  "type": "Feature",
  "properties": {
    "iso:country":"CH",
    "sg:address":"G\u00e4rtnerstrasse 21",
    "sg:city":"Solothurn",
    "sg:classifiers":[
        {
            "category":"Education",
            "subcategory":"Library",
            "type":"Public Place"
        }
    ],
    "sg:phone":"+41 32 625 37 37",
    "sg:postcode":"4500",
    "sg:province":"Solothurn",
    "sg:tags":[
        "u",
        "bibliotheken",
        "archive"
    ],
    "wof:name":"Seraphisches Liebeswerk So Studien-& Bildungsbibliothek",
    "wof:placetype":"venue"
},
  "geometry": {"coordinates":[7.534771,47.211273],"type":"Point"}
}