{
  "type": "Feature",
  "properties": {
    "iso:country":"CH",
    "sg:address":"Rte De Claie-aux-moines 28",
    "sg:city":"Savigny",
    "sg:orig_category":"Maler U Glasergewerbe",
    "sg:postcode":"1073",
    "sg:province":"Vaud",
    "wof:name":"Tundo Lorenzo",
    "wof:placetype":"venue"
},
  "geometry": {"coordinates":[6.7110900879,46.5415496826],"type":"Point"}
}