{
  "type": "Feature",
  "properties": {
    "iso:country":"CH",
    "sg:address":"Neugasse 22",
    "sg:city":"Zug",
    "sg:orig_category":"Erwachsenenbildung U Unterricht Wirtschaftspr\u00fcfung, Steuerberatung U Treuhand",
    "sg:phone":"+41 41 728 76 10",
    "sg:postcode":"6300",
    "sg:province":"Zug",
    "wof:name":"Wild Group Management Ag",
    "wof:placetype":"venue"
},
  "geometry": {"coordinates":[8.5153312683,47.166469574],"type":"Point"}
}