{
  "type": "Feature",
  "properties": {
    "iso:country":"CH",
    "sg:address":"H\u00e4rtestrasse 10",
    "sg:city":"Fislisbach",
    "sg:orig_category":"Betrieb von Taxis",
    "sg:phone":"+41 56 493 79 59",
    "sg:postcode":"5442",
    "sg:province":"Aargau",
    "wof:name":"Koller J., Taxi, Klein-busse, Limousinen Gewerbem\u00e4ssiger Personentransport",
    "wof:placetype":"venue"
},
  "geometry": {"coordinates":[8.29972,47.436306],"type":"Point"}
}