{
  "type": "Feature",
  "properties": {
    "iso:country":"CH",
    "sg:address":"Gallus\u00e4ckerstrasse 22",
    "sg:city":"M\u00f6rschwil",
    "sg:orig_category":"Reinigungsgewerbe",
    "sg:phone":"+41 71 866 26 31",
    "sg:postcode":"9402",
    "sg:province":"St. Gallen",
    "wof:name":"Solazzo Wyland-reinigung Ag",
    "wof:placetype":"venue"
},
  "geometry": {"coordinates":[9.4237031937,47.4717330933],"type":"Point"}
}