{
  "type": "Feature",
  "properties": {
    "iso:country":"CH",
    "sg:address":"6170 Sch\u00fcpfheim. Postfach",
    "sg:city":"Sch\u00fcpfheim",
    "sg:orig_category":"Grosshandel mit Eisenwaren sowie Installationsbedarf f\u00fcr Gas, Wasser U Heizung",
    "sg:postcode":"6170",
    "sg:province":"Luzern",
    "wof:name":"Ewag Eisenwaren Ag",
    "wof:placetype":"venue"
},
  "geometry": {"coordinates":[8.0194749832,46.9536094666],"type":"Point"}
}