{
  "type": "Feature",
  "properties": {
    "iso:country":"CH",
    "sg:address":"Via Catenazzi 25",
    "sg:city":"Mendrisio",
    "sg:orig_category":"Bauschreinerei Herstellung von M\u00f6beln verschiedener Art",
    "sg:phone":"+41 91 683 97 47",
    "sg:postcode":"6850",
    "sg:province":"Ticino",
    "wof:name":"I. Cereghetti & D. Fontana Falegnameria",
    "wof:placetype":"venue"
},
  "geometry": {"coordinates":[8.980099,45.871208],"type":"Point"}
}