{
  "type": "Feature",
  "properties": {
    "iso:country":"CH",
    "sg:address":"Rieterstrasse 35",
    "sg:city":"Z\u00fcrich",
    "sg:orig_category":"Druck ohne Zeitungsdruck",
    "sg:postcode":"8002",
    "sg:province":"Z\u00fcrich",
    "wof:name":"Fink Medien Ag",
    "wof:placetype":"venue"
},
  "geometry": {"coordinates":[8.5262174606,47.3585968018],"type":"Point"}
}