{
  "type": "Feature",
  "properties": {
    "iso:country":"CH",
    "sg:address":"Letzigraben 120 8047 Z\u00fcrich. Postfach",
    "sg:city":"Z\u00fcrich",
    "sg:orig_category":"Detailhandel mit Metallwaren, Anstrichmitteln, Glaswaren, Bau U Heimwerkerbedarf Handelsvermittlung ",
    "sg:phone":"+41 12424210",
    "sg:postcode":"8047",
    "sg:province":"Z\u00fcrich",
    "wof:name":"Techno-flex Sa Produits Industriels, Informatiques Etc.; Conception, Ing\u00e9nierie, Production, Commercialisation",
    "wof:placetype":"venue"
},
  "geometry": {"coordinates":[8.4974994659,47.3766670227],"type":"Point"}
}