{
  "type": "Feature",
  "properties": {
    "iso:country":"CH",
    "sg:address":"Krippenstrasse 23",
    "sg:city":"Langenthal",
    "sg:orig_category":"Kinderkrippen U horte",
    "sg:phone":"+41 62 922 19 88",
    "sg:postcode":"4900",
    "sg:province":"Bern",
    "wof:name":"Kinderkrippe",
    "wof:placetype":"venue"
},
  "geometry": {"coordinates":[7.7824602127,47.2101593018],"type":"Point"}
}