{
  "type": "Feature",
  "properties": {
    "iso:country":"CH",
    "sg:address":"Zweierstrasse 35",
    "sg:city":"Z\u00fcrich",
    "sg:orig_category":"Vermietung U Verpachtung von eigenen Immobilien",
    "sg:postcode":"8004",
    "sg:province":"Z\u00fcrich",
    "wof:name":"Retus Immobilien Ag",
    "wof:placetype":"venue"
},
  "geometry": {"coordinates":[8.3059358597,46.9953384399],"type":"Point"}
}