{
  "type": "Feature",
  "properties": {
    "iso:country":"CH",
    "sg:address":"Rue Louis-favre 43",
    "sg:city":"Gen\u00e8ve",
    "sg:orig_category":"D\u00e4mmung gegen K\u00e4lte, W\u00e4rme, Schall U Ersch\u00fctterung Oberfl\u00e4chenveredlung U W\u00e4rmebehandlung",
    "sg:phone":"+41 22 733 53 54",
    "sg:postcode":"1201",
    "sg:province":"Gen\u00e8ve",
    "wof:name":"Renov\u00e9mail",
    "wof:placetype":"venue"
},
  "geometry": {"coordinates":[6.137819767,46.2116012573],"type":"Point"}
}