{
  "type": "Feature",
  "properties": {
    "iso:country":"CH",
    "sg:address":"Seeburgstrasse 26",
    "sg:city":"Luzern",
    "sg:orig_category":"Personal U Stellenvermittlung Unternehmensberatung",
    "sg:phone":"+41 41 370 95 23",
    "sg:postcode":"6006",
    "sg:province":"Luzern",
    "wof:name":"Persona Ag",
    "wof:placetype":"venue"
},
  "geometry": {"coordinates":[8.3396749496,47.0514717102],"type":"Point"}
}