{
  "type": "Feature",
  "properties": {
    "iso:country":"CH",
    "sg:address":"Kirchgasse 8",
    "sg:city":"Walenstadt",
    "sg:orig_category":"Detailhandel mit Bekleidung",
    "sg:phone":"+41 81 735 28 06",
    "sg:postcode":"8880",
    "sg:province":"St. Gallen",
    "wof:name":"Carite Gymnastikbekleidungen",
    "wof:placetype":"venue"
},
  "geometry": {"coordinates":[9.317446,47.125015],"type":"Point"}
}