{
  "type": "Feature",
  "properties": {
    "iso:country":"CH",
    "sg:address":"Amriswiler Strasse 49",
    "sg:city":"Steinebrunn",
    "sg:orig_category":"Landwirtschaftliche Maschinen Wartung and Reparatur",
    "sg:phone":"+41 71 477 28 28",
    "sg:postcode":"9314",
    "sg:province":"Thurgau",
    "wof:name":"Aggeler Ag Forsttechnik F\u00f6rdertechnik",
    "wof:placetype":"venue"
},
  "geometry": {"coordinates":[9.3498868942,47.5334281921],"type":"Point"}
}