{
  "type": "Feature",
  "properties": {
    "iso:country":"CH",
    "sg:address":"Arvenweg 3",
    "sg:city":"Uetendorf",
    "sg:orig_category":"Sportvereine Turnen Vereine Damen",
    "sg:phone":"+41 33 345 40 19",
    "sg:postcode":"3661",
    "sg:province":"Bern",
    "wof:name":"Frauenturnverein Stv Uetendorf",
    "wof:placetype":"venue"
},
  "geometry": {"coordinates":[7.5680031776,46.7718238831],"type":"Point"}
}