{
  "type": "Feature",
  "properties": {
    "iso:country":"CH",
    "sg:address":"Z\u00fcrcher Strasse 27",
    "sg:city":"St.gallen",
    "sg:orig_category":"Grosshandel mit Holz U Baustoffen",
    "sg:postcode":"9000",
    "sg:province":"St. Gallen",
    "wof:name":"Merotto-calonder Sergio",
    "wof:placetype":"venue"
},
  "geometry": {"coordinates":[9.0641136169,46.0894584656],"type":"Point"}
}