{
  "type": "Feature",
  "properties": {
    "iso:country":"CH",
    "sg:address":"Albisstrasse 8",
    "sg:city":"Mettmenstetten",
    "sg:orig_category":"Architektur U Ingenieurb\u00fcros",
    "sg:phone":"+41 31 351 28 72",
    "sg:postcode":"8932",
    "sg:province":"Z\u00fcrich",
    "wof:name":"Eichenberger, M\u00fcller Ag, Bern, Ingenieurb\u00fcro F\u00fcr Hoch Und Tiefbau",
    "wof:placetype":"venue"
},
  "geometry": {"coordinates":[7.45102,46.940159],"type":"Point"}
}