{
  "type": "Feature",
  "properties": {
    "addr:full":"Hofwiesenstrasse 135 Zurich Z\u00fcrich 8057",
    "addr:housenumber":"135",
    "addr:postcode":"8057",
    "addr:street":"Hofwiesenstrasse",
    "iso:country":"CH",
    "sg:address":"Hofwiesenstrasse 135",
    "sg:city":"Zurich",
    "sg:classifiers":[
        {
            "category":"Banks & Credit Unions",
            "subcategory":"Financial Services",
            "type":"Services"
        }
    ],
    "sg:phone":"+41 21 921 03 32",
    "sg:postcode":"8057",
    "sg:province":"Z\u00fcrich",
    "sg:tags":[
        "banking",
        "finance",
        "insurance"
    ],
    "wof:name":"Orior Holding Sa",
    "wof:placetype":"venue"
},
  "geometry": {"coordinates":[6.850067,46.458496],"type":"Point"}
}