{
  "type": "Feature",
  "properties": {
    "iso:country":"CH",
    "sg:address":"Im Ochsengarten 1",
    "sg:city":"Blauen",
    "sg:orig_category":"Detailhandel mit Antiquit\u00e4ten",
    "sg:phone":"+41 71 223 38 88",
    "sg:postcode":"4223",
    "sg:province":"Basel-Landschaft",
    "wof:name":"Erika Hartmann Opus Zwei Antiquit\u00e4ten",
    "wof:placetype":"venue"
},
  "geometry": {"coordinates":[9.375067,47.427261],"type":"Point"}
}