{
  "type": "Feature",
  "properties": {
    "iso:country":"CH",
    "sg:address":"Heuberg 16",
    "sg:city":"Basel",
    "sg:orig_category":"Non-Classified Establishments",
    "sg:postcode":"4051",
    "sg:province":"Basel-Stadt",
    "wof:name":"Ritter Giger Schmid Architekten Sia Ag",
    "wof:placetype":"venue"
},
  "geometry": {"coordinates":[7.5855197906,47.5562744141],"type":"Point"}
}