{
  "type": "Feature",
  "properties": {
    "iso:country":"CH",
    "sg:address":"F\u00f6hrenweg 19",
    "sg:city":"Frick",
    "sg:orig_category":"Erbringung von Dienstleistungen f\u00fcr Unternehmen",
    "sg:phone":"+41 62 871 25 11",
    "sg:postcode":"5070",
    "sg:province":"Aargau",
    "wof:name":"Paf Design-center Gmbh",
    "wof:placetype":"venue"
},
  "geometry": {"coordinates":[8.0279808044,47.5127067566],"type":"Point"}
}