{
  "type": "Feature",
  "properties": {
    "addr:full":"Sagne Chemin De La 17 St-aubin-sauges Neuch\u00e2tel 2024",
    "addr:housenumber":"17",
    "addr:postcode":"2024",
    "addr:street":"Chemin De La;St-Aubin-Sauges Neucha\u0302Tel",
    "iso:country":"CH",
    "sg:address":"Sagne Chemin De La 17",
    "sg:city":"St-aubin-sauges",
    "sg:orig_category":"Allgemeiner Hoch U Tiefbau",
    "sg:phone":"+41 32 835 15 55",
    "sg:postcode":"2024",
    "sg:province":"Neuch\u00e2tel",
    "wof:name":"Albati Sa",
    "wof:placetype":"venue"
},
  "geometry": {"coordinates":[6.76328,46.887115],"type":"Point"}
}