{
  "type": "Feature",
  "properties": {
    "iso:country":"CH",
    "sg:address":"Gr\u00fcnaustrasse 53",
    "sg:city":"Wabern",
    "sg:orig_category":"Institutionen f\u00fcr Behinderte Wohnheime",
    "sg:phone":"+41 31 961 01 99",
    "sg:postcode":"3084",
    "sg:province":"Bern",
    "wof:name":"Stiftung B\u00e4chtelen",
    "wof:placetype":"venue"
},
  "geometry": {"coordinates":[7.4536070824,46.9249763489],"type":"Point"}
}