{
  "type": "Feature",
  "properties": {
    "iso:country":"CH",
    "sg:address":"6864",
    "sg:city":"Arzo",
    "sg:orig_category":"RESTAURANTS: TEA-ROOMS",
    "sg:phone":"+41 91464226",
    "sg:postcode":"6864",
    "sg:province":"Ticino",
    "wof:name":"Tobar Sa",
    "wof:placetype":"venue"
},
  "geometry": {"coordinates":[8.9395303726,45.8800201416],"type":"Point"}
}