{
  "type": "Feature",
  "properties": {
    "iso:country":"CH",
    "sg:address":"Route Du Centre 4",
    "sg:city":"Belfaux",
    "sg:orig_category":"Detailhandel mit M\u00f6beln Innendekorationsateliers",
    "sg:phone":"+41 32 931 36 07",
    "sg:postcode":"1782",
    "sg:province":"Fribourg",
    "wof:name":"Marcel P\u00e9ter-contesse Ameublement",
    "wof:placetype":"venue"
},
  "geometry": {"coordinates":[6.8001561165,47.0393943787],"type":"Point"}
}