{
  "type": "Feature",
  "properties": {
    "iso:country":"CH",
    "sg:address":"Chemin Du Terreau 3",
    "sg:city":"Biel/bienne",
    "sg:orig_category":"Engravings, Technical",
    "sg:phone":"+41 32 322 50 25",
    "sg:postcode":"2502",
    "sg:province":"Bern",
    "wof:name":"S\u00e9d\u00e9cal Sa",
    "wof:placetype":"venue"
},
  "geometry": {"coordinates":[7.2377681732,47.136051178],"type":"Point"}
}