{
  "type": "Feature",
  "properties": {
    "iso:country":"CH",
    "sg:address":"Leuenweg 3",
    "sg:city":"Rombach",
    "sg:orig_category":"Unclassifiable Establishments",
    "sg:postcode":"5022",
    "sg:province":"Aargau",
    "wof:name":"Kugelrund Gmbh",
    "wof:placetype":"venue"
},
  "geometry": {"coordinates":[8.0470972061,47.4034423828],"type":"Point"}
}