{
  "type": "Feature",
  "properties": {
    "iso:country":"CH",
    "sg:address":"Kronengasse 2",
    "sg:city":"Baden",
    "sg:orig_category":"RESTAURANTS: TEA-ROOMS",
    "sg:phone":"+41 56 222 57 62",
    "sg:postcode":"5400",
    "sg:province":"Aargau",
    "wof:name":"Ranko Acimovic Restaurant Krone",
    "wof:placetype":"venue"
},
  "geometry": {"coordinates":[8.309926033,47.472568512],"type":"Point"}
}