{
  "type": "Feature",
  "properties": {
    "iso:country":"CH",
    "sg:address":"Bankstrasse 21",
    "sg:city":"Glarus",
    "sg:orig_category":"Allgemeiner Hoch U Tiefbau",
    "sg:postcode":"8750",
    "sg:province":"Glarus",
    "wof:name":"Bauteam Ag",
    "wof:placetype":"venue"
},
  "geometry": {"coordinates":[9.06875,47.040379],"type":"Point"}
}