{
  "type": "Feature",
  "properties": {
    "iso:country":"CH",
    "sg:address":"Hauptstrasse 30",
    "sg:city":"St\u00fcsslingen",
    "sg:classifiers":[
        {
            "category":"Banks & Credit Unions",
            "subcategory":"Bank",
            "type":"Services"
        }
    ],
    "sg:phone":"+41 4162482233",
    "sg:postcode":"4655",
    "sg:province":"Solothurn",
    "wof:name":"Raiffeisenbank, St\u00fcsslingen-rohr",
    "wof:placetype":"venue"
},
  "geometry": {"coordinates":[7.970739,47.391266],"type":"Point"}
}