{
  "type": "Feature",
  "properties": {
    "iso:country":"CH",
    "sg:address":"Dorfstrasse 9",
    "sg:city":"Leukerbad",
    "sg:orig_category":"RESTAURANTS: TEA-ROOMS",
    "sg:phone":"+41 27 470 24 13",
    "sg:postcode":"3954",
    "sg:province":"Valais",
    "wof:name":"Pizzeria Choucas",
    "wof:placetype":"venue"
},
  "geometry": {"coordinates":[7.6284527779,46.3801002502],"type":"Point"}
}