{
  "type": "Feature",
  "properties": {
    "addr:full":"Rainstrasse 76 St\u00e4fa Z\u00fcrich 8712",
    "addr:housenumber":"76",
    "addr:postcode":"8712",
    "addr:street":"Rainstrasse;Zuerich",
    "iso:country":"CH",
    "sg:address":"Rainstrasse 76",
    "sg:city":"St\u00e4fa",
    "sg:orig_category":"Blumen U Zierpflanzenbau",
    "sg:phone":"+41 21 466 51 11",
    "sg:postcode":"8712",
    "sg:province":"Z\u00fcrich",
    "wof:name":"Horisberger Yvorne Sa",
    "wof:placetype":"venue"
},
  "geometry": {"coordinates":[6.93579,46.34396],"type":"Point"}
}