{
  "type": "Feature",
  "properties": {
    "iso:country":"CH",
    "sg:address":"Ecluse Rue De L' 33",
    "sg:city":"Neuch\u00e2tel",
    "sg:orig_category":"Grosshandel mit Nahrungsmitteln, Getr\u00e4nken U Tabakwaren ohne ausgepr\u00e4gten Schwerpunkt",
    "sg:postcode":"2000",
    "sg:province":"Neuch\u00e2tel",
    "wof:name":"Tschanz Mme G., Alimentation Magasin D'alimentation",
    "wof:placetype":"venue"
},
  "geometry": {"coordinates":[6.9272999763,46.9934310913],"type":"Point"}
}