{
  "type": "Feature",
  "properties": {
    "iso:country":"CH",
    "sg:address":"Neum\u00fchlestrasse 27b 9403 Goldach. Postfach",
    "sg:city":"Rorschach",
    "sg:classifiers":[
        {
            "category":"Mining & Drilling",
            "type":"Manufacturing & Wholesale Goods"
        }
    ],
    "sg:phone":"+41 71 845 30 90",
    "sg:postcode":"9400",
    "sg:province":"St. Gallen",
    "sg:tags":[
        "test",
        "sondierbohrungen",
        "u"
    ],
    "wof:name":"Z\u00fcllig Baubohrungen Gmbh Arbeiten Im Ber. Von Diamant-bohrungen Bzw. Baubohrungen; Planung Usw.",
    "wof:placetype":"venue"
},
  "geometry": {"coordinates":[9.466591835,47.4714393616],"type":"Point"}
}