{
  "type": "Feature",
  "properties": {
    "iso:country":"CH",
    "sg:address":"Romanshornerstrasse 11",
    "sg:city":"Kronb\u00fchl",
    "sg:orig_category":"Verarbeitung von Milch Verwertung von Milch",
    "sg:phone":"+41 81 413 51 42",
    "sg:postcode":"9302",
    "wof:name":"Molkerei Davos",
    "wof:placetype":"venue"
},
  "geometry": {"coordinates":[9.8245372772,46.7962341309],"type":"Point"}
}