{
  "type": "Feature",
  "properties": {
    "iso:country":"CH",
    "sg:address":"Strandweg 22",
    "sg:city":"Muntelier",
    "sg:orig_category":"Grosshandel mit Bekleidung Maschinen and Apparate divers Grosshandel",
    "sg:phone":"+41 71 245 25 25",
    "sg:postcode":"3286",
    "sg:province":"Fribourg",
    "wof:name":"Vincenzo Scuderi Stahlmeier",
    "wof:placetype":"venue"
},
  "geometry": {"coordinates":[9.3957328796,47.437046051],"type":"Point"}
}