{
  "type": "Feature",
  "properties": {
    "iso:country":"CH",
    "sg:address":"B\u00e4reggstrasse 20",
    "sg:city":"Langenthal",
    "sg:orig_category":"Primarschulen",
    "sg:phone":"+41 62 922 27 76",
    "sg:postcode":"4900",
    "sg:province":"Bern",
    "wof:name":"Primarschule Hard",
    "wof:placetype":"venue"
},
  "geometry": {"coordinates":[7.7798409462,47.2198562622],"type":"Point"}
}