{
  "type": "Feature",
  "properties": {
    "iso:country":"CH",
    "sg:address":"Faubourg Du Jura 44",
    "sg:city":"Biel/bienne",
    "sg:classifiers":[
        {
            "category":"Professional",
            "subcategory":"Business Services",
            "type":"Services"
        }
    ],
    "sg:phone":"+41 32 751 52 79",
    "sg:postcode":"2502",
    "sg:province":"Bern",
    "sg:tags":[
        "high-precision",
        "mechanic"
    ],
    "wof:name":"Francis Cr\u00e9chard",
    "wof:placetype":"venue"
},
  "geometry": {"coordinates":[7.0923781395,47.0639915466],"type":"Point"}
}