{
  "type": "Feature",
  "properties": {
    "iso:country":"CH",
    "sg:address":"8856 Tuggen. Postfach 49",
    "sg:city":"Tuggen",
    "sg:orig_category":"Sportvereine Ballsport Fussball",
    "sg:phone":"+41 55 445 18 00",
    "sg:postcode":"8856",
    "sg:province":"Schwyz",
    "wof:name":"Fc Tuggen",
    "wof:placetype":"venue"
},
  "geometry": {"coordinates":[8.9418878555,47.202922821],"type":"Point"}
}