{
  "type": "Feature",
  "properties": {
    "iso:country":"CH",
    "sg:address":"Moosstrasse 5",
    "sg:city":"Ebertswil",
    "sg:orig_category":"Architektur U Ingenieurb\u00fcros",
    "sg:phone":"+41 17111777",
    "sg:postcode":"8925",
    "sg:province":"Z\u00fcrich",
    "wof:name":"Sz Creativ Conzept Gmbh",
    "wof:placetype":"venue"
},
  "geometry": {"coordinates":[8.54652,47.226646],"type":"Point"}
}