{
  "type": "Feature",
  "properties": {
    "iso:country":"CH",
    "sg:address":"1667",
    "sg:city":"Enney",
    "sg:orig_category":"RESTAURANTS: TEA-ROOMS",
    "sg:phone":"+41 26 921 32 47",
    "sg:postcode":"1667",
    "sg:province":"Fribourg",
    "wof:name":"Moret Ren\u00e9.",
    "wof:placetype":"venue"
},
  "geometry": {"coordinates":[7.0839400291,46.5667800903],"type":"Point"}
}