{
  "type": "Feature",
  "properties": {
    "iso:country":"CH",
    "sg:address":"Winkelb\u00fcel 3 6043 Adligenswil. Postfach",
    "sg:city":"Adligenswil",
    "sg:orig_category":"Herstellung von Schmuck, Gold U Silberschmiedwaren",
    "sg:phone":"+41 71 911 37 89",
    "sg:postcode":"6043",
    "sg:province":"Luzern",
    "wof:name":"Ars Et Aurum Silberschmiedatelier Ferigutti Bruno",
    "wof:placetype":"venue"
},
  "geometry": {"coordinates":[9.0373411179,47.4647369385],"type":"Point"}
}