{
  "type": "Feature",
  "properties": {
    "iso:country":"CH",
    "sg:address":"Hodler Rue Ferdinand- 23 1207 Gen\u00e8ve. Postfach",
    "sg:city":"Gen\u00e8ve",
    "sg:orig_category":"Non-Classified Establishments",
    "sg:postcode":"1207",
    "sg:province":"Gen\u00e8ve",
    "wof:name":"Soci\u00e9t\u00e9 Immobili\u00e8re Fontanivas",
    "wof:placetype":"venue"
},
  "geometry": {"coordinates":[6.1553339958,46.1990966797],"type":"Point"}
}