{
  "type": "Feature",
  "properties": {
    "iso:country":"CH",
    "sg:address":"1897",
    "sg:city":"Bouveret",
    "sg:orig_category":"Sanit\u00e4r, Heizungs U L\u00fcftungsinstallation",
    "sg:postcode":"1897",
    "sg:province":"Valais",
    "wof:name":"Fornay Eric Ferblanterie-couverture S\u00e0rl",
    "wof:placetype":"venue"
},
  "geometry": {"coordinates":[6.8527798653,46.3853187561],"type":"Point"}
}