{
  "type": "Feature",
  "properties": {
    "iso:country":"CH",
    "sg:address":"T\u00f6sstalstrasse 6",
    "sg:city":"Wallenwil",
    "sg:orig_category":"Einzelhandel mit Automobilen Instandhaltung U Reparatur von Automobilen",
    "sg:phone":"+41 71 971 37 37",
    "sg:postcode":"8360",
    "sg:province":"Thurgau",
    "wof:name":"Stations-garage Ag Carosserie",
    "wof:placetype":"venue"
},
  "geometry": {"coordinates":[8.954117775,47.4610328674],"type":"Point"}
}