{
  "type": "Feature",
  "properties": {
    "addr:full":"Steinengraben 14 Basel Basel-Stadt 4051",
    "addr:housenumber":"14",
    "addr:postcode":"4051",
    "addr:street":"Steinengraben",
    "iso:country":"CH",
    "sg:address":"Steinengraben 14",
    "sg:city":"Basel",
    "sg:orig_category":"Architekturb\u00fcros",
    "sg:phone":"+41 61 270 92 00",
    "sg:postcode":"4051",
    "sg:province":"Basel-Stadt",
    "wof:name":"M\u00fcller Mathis & M\u00fcller Ueli Architekten",
    "wof:placetype":"venue"
},
  "geometry": {"coordinates":[7.585073,47.554676],"type":"Point"}
}