{
  "type": "Feature",
  "properties": {
    "iso:country":"CH",
    "sg:address":"H\u00e4ngertstrasse 3 3114 Oberwichtrach. Postfach 154",
    "sg:city":"Oberwichtrach",
    "sg:orig_category":"Bauspenglerei Sanit\u00e4rinstallation",
    "sg:phone":"+41 31 781 25 25",
    "sg:postcode":"3114",
    "sg:province":"Bern",
    "wof:name":"Steiner Wichtrach Haustechnik Ag",
    "wof:placetype":"venue"
},
  "geometry": {"coordinates":[7.576897,46.842991],"type":"Point"}
}