{
  "type": "Feature",
  "properties": {
    "iso:country":"CH",
    "sg:address":"Unterdorf 20",
    "sg:city":"Mosnang",
    "sg:classifiers":[
        {
            "category":"Restaurant",
            "type":"Food & Drink"
        }
    ],
    "sg:phone":"+41 41 850 13 50",
    "sg:postcode":"9607",
    "sg:province":"St. Gallen",
    "wof:name":"Restaurant Krone",
    "wof:placetype":"venue"
},
  "geometry": {"coordinates":[8.4399671555,47.0805854797],"type":"Point"}
}