{
  "type": "Feature",
  "properties": {
    "iso:country":"CH",
    "sg:address":"Hauptstr.",
    "sg:city":"Rabius",
    "sg:classifiers":[
        {
            "category":"Home & Garden",
            "subcategory":"Furniture",
            "type":"Retail Goods"
        }
    ],
    "sg:phone":"+41 81 943 12 81",
    "sg:postcode":"7172",
    "sg:province":"Graubunden",
    "sg:tags":[
        "household",
        "wood"
    ],
    "wof:name":"Gabriel Lutz Kochen U. Wohnen",
    "wof:placetype":"venue"
},
  "geometry": {"coordinates":[8.9598093033,46.7340736389],"type":"Point"}
}