{
  "type": "Feature",
  "properties": {
    "iso:country":"CH",
    "sg:address":"B\u00fchl",
    "sg:city":"Wimmis",
    "sg:orig_category":"Detailhandel mit elektrischen Haushalts-,Radio U Fernsehger\u00e4ten sowie Musikinstrumenten",
    "sg:postcode":"3752",
    "sg:province":"Bern",
    "wof:name":"Radio-tv H. Meier",
    "wof:placetype":"venue"
},
  "geometry": {"coordinates":[7.6407032013,46.6749267578],"type":"Point"}
}