{
  "type": "Feature",
  "properties": {
    "iso:country":"CH",
    "sg:address":"Rebgasse 15",
    "sg:city":"Binningen",
    "sg:orig_category":"Sonstige Aktivit\u00e4ten der nicht-\u00e4rztlichen Medizinalberufe",
    "sg:phone":"+41 61 421 37 82",
    "sg:postcode":"4102",
    "sg:province":"Basel-Landschaft",
    "wof:name":"Balance Bruce Erika, Institut F\u00fcr Kinesiologie, Familienaufstellungen, Familien Und Paarbegleitung",
    "wof:placetype":"venue"
},
  "geometry": {"coordinates":[7.5699009895,47.5405464172],"type":"Point"}
}