{
  "type": "Feature",
  "properties": {
    "iso:country":"CH",
    "sg:address":"Bachtelen 36b",
    "sg:city":"Pohlern",
    "sg:orig_category":"Assembling, Disassembling",
    "sg:phone":"+41 79 334 00 54",
    "sg:postcode":"3638",
    "sg:province":"Bern",
    "wof:name":"Beat Wenger Montage",
    "wof:placetype":"venue"
},
  "geometry": {"coordinates":[7.528054,46.730118],"type":"Point"}
}