{
  "type": "Feature",
  "properties": {
    "iso:country":"CH",
    "sg:address":"Seestrasse 270",
    "sg:city":"Horgen",
    "sg:orig_category":"Grosshandel mit sonstigen Maschinen U Ausr\u00fcstungen f\u00fcr Industrie, Handel U Schiffahrt Maschinenbau",
    "sg:postcode":"8810",
    "sg:province":"Z\u00fcrich",
    "wof:name":"Famec Ag",
    "wof:placetype":"venue"
},
  "geometry": {"coordinates":[8.6078329086,47.2568054199],"type":"Point"}
}