{
  "type": "Feature",
  "properties": {
    "iso:country":"CH",
    "sg:address":"Sangenstrasse 2",
    "sg:city":"Weinfelden",
    "sg:orig_category":"Versicherungen Generalagenturen",
    "sg:phone":"+41 71 626 57 77",
    "sg:postcode":"8570",
    "sg:province":"Thurgau",
    "wof:name":"La Suisse Versicherungen Generalagentur",
    "wof:placetype":"venue"
},
  "geometry": {"coordinates":[9.1084184647,47.5626373291],"type":"Point"}
}