{
  "type": "Feature",
  "properties": {
    "iso:country":"CH",
    "sg:address":"Ch. Des Rosiers 6",
    "sg:city":"Veyrier",
    "sg:orig_category":"Non-Classified Establishments",
    "sg:postcode":"1255",
    "sg:province":"Gen\u00e8ve",
    "wof:name":"Cotinus, Gillig",
    "wof:placetype":"venue"
},
  "geometry": {"coordinates":[6.1429319382,46.1728553772],"type":"Point"}
}