{
  "type": "Feature",
  "properties": {
    "iso:country":"CH",
    "sg:address":"Pr\u00e9s-beudin Avenue Des 20",
    "sg:city":"Martigny",
    "sg:orig_category":"Unclassifiable Establishments",
    "sg:postcode":"1920",
    "sg:province":"Valais",
    "wof:name":"Vistafinance Sa",
    "wof:placetype":"venue"
},
  "geometry": {"coordinates":[7.0847167969,46.1091461182],"type":"Point"}
}