{
  "type": "Feature",
  "properties": {
    "iso:country":"CH",
    "sg:address":"Platz",
    "sg:city":"Mels",
    "sg:orig_category":"S\u00e4ge, Hobel U Holzimpr\u00e4gnierwerke",
    "sg:postcode":"8887",
    "sg:province":"St. Gallen",
    "wof:name":"Britt Gebr\u00fcder Eduard Und Adolf",
    "wof:placetype":"venue"
},
  "geometry": {"coordinates":[9.4190750122,47.0468406677],"type":"Point"}
}