{
  "type": "Feature",
  "properties": {
    "iso:country":"CH",
    "sg:address":"3512",
    "sg:city":"Walkringen",
    "sg:orig_category":"Sonstiges Versicherungsgewerbe",
    "sg:postcode":"3512",
    "sg:province":"Bern",
    "wof:name":"Pferdeversicherungs-genossenschaft Laupen",
    "wof:placetype":"venue"
},
  "geometry": {"coordinates":[7.2639498711,46.9152984619],"type":"Point"}
}