{
  "type": "Feature",
  "properties": {
    "iso:country":"CH",
    "sg:address":"Schloss 8820 W\u00e4denswil. Postfach 185",
    "sg:city":"W\u00e4denswil",
    "sg:orig_category":"Obstbau Rebbau",
    "sg:phone":"+41 17805670",
    "sg:postcode":"8820",
    "sg:province":"Z\u00fcrich",
    "wof:name":"Eidg. Forschungsanstalt F\u00fcr Obst-,wein-& Gartenbau",
    "wof:placetype":"venue"
},
  "geometry": {"coordinates":[8.6775541306,47.2247886658],"type":"Point"}
}