{
  "type": "Feature",
  "properties": {
    "iso:country":"CH",
    "sg:address":"Mockenwies 38b",
    "sg:city":"Uerikon",
    "sg:orig_category":"Kaminfeger",
    "sg:phone":"+41 55 282 12 42",
    "sg:postcode":"8713",
    "sg:province":"Z\u00fcrich",
    "wof:name":"Roland Lieberherr Kaminfegermeister",
    "wof:placetype":"venue"
},
  "geometry": {"coordinates":[8.9186820984,47.2403526306],"type":"Point"}
}