{
  "type": "Feature",
  "properties": {
    "iso:country":"CH",
    "sg:address":"Contrada S. Marco",
    "sg:city":"Agno",
    "sg:orig_category":"Handel mit Automobilen",
    "sg:postcode":"6982",
    "sg:province":"Ticino",
    "wof:name":"Auto Hall Sa",
    "wof:placetype":"venue"
},
  "geometry": {"coordinates":[8.8992099762,45.9960479736],"type":"Point"}
}