{
  "type": "Feature",
  "properties": {
    "iso:country":"CH",
    "sg:address":"Voa Principala 23",
    "sg:city":"Lenzerheide/lai",
    "sg:orig_category":"Kosmetikinstitute",
    "sg:phone":"+41 19323288",
    "sg:postcode":"7078",
    "sg:province":"Graubunden",
    "wof:name":"Carmen M. Meier Kosmetikinstitut Viva",
    "wof:placetype":"venue"
},
  "geometry": {"coordinates":[8.7927446365,47.3198013306],"type":"Point"}
}