{
  "type": "Feature",
  "properties": {
    "iso:country":"CH",
    "sg:address":"Grand-rue 33",
    "sg:city":"Ch\u00e2tel-st-denis",
    "sg:orig_category":"Detailhandel mit Fleisch U Fleischwaren",
    "sg:phone":"+41 32 392 58 87",
    "sg:postcode":"1618",
    "sg:province":"Fribourg",
    "wof:name":"Gerber Bargen Ag",
    "wof:placetype":"venue"
},
  "geometry": {"coordinates":[7.2645668983,47.0394172668],"type":"Point"}
}