{
  "type": "Feature",
  "properties": {
    "iso:country":"CH",
    "sg:address":"Giassa Travers 196",
    "sg:city":"Zuoz",
    "sg:orig_category":"Herstellung von Heizk\u00f6rpern U kesseln f\u00fcr die Zentralheizung Sanit\u00e4rinstallation",
    "sg:phone":"+41 81 854 04 70",
    "sg:postcode":"7524",
    "sg:province":"Graubunden",
    "wof:name":"Stuppan Robert",
    "wof:placetype":"venue"
},
  "geometry": {"coordinates":[9.9607973099,46.6025009155],"type":"Point"}
}