{
  "type": "Feature",
  "properties": {
    "iso:country":"CH",
    "sg:address":"Rebbergstrasse 27",
    "sg:city":"Rudolfstetten",
    "sg:orig_category":"Betrieb von Taxis",
    "sg:phone":"+41 56 648 48 48",
    "sg:postcode":"8964",
    "sg:province":"Aargau",
    "wof:name":"Taxi Lehmann",
    "wof:placetype":"venue"
},
  "geometry": {"coordinates":[8.378275,47.373089],"type":"Point"}
}