{
  "type": "Feature",
  "properties": {
    "iso:country":"CH",
    "sg:address":"Imm. Genziana A 3962 Montana. Postfach",
    "sg:city":"Montana",
    "sg:orig_category":"Vermietung U Verpachtung von eigenen Immobilien",
    "sg:postcode":"3962",
    "wof:name":"Domag Ag, Buchs Sg",
    "wof:placetype":"venue"
},
  "geometry": {"coordinates":[9.4716854095,47.1721076965],"type":"Point"}
}