{
  "type": "Feature",
  "properties": {
    "iso:country":"CH",
    "sg:address":"8353 Elgg. Postfach 131",
    "sg:city":"Elgg",
    "sg:classifiers":[
        {
            "category":"Education",
            "subcategory":"Library",
            "type":"Public Place"
        }
    ],
    "sg:postcode":"8353",
    "sg:province":"Z\u00fcrich",
    "sg:tags":[
        "u",
        "bibliotheken",
        "archive"
    ],
    "wof:name":"Gemeindebibliothek",
    "wof:placetype":"venue"
},
  "geometry": {"coordinates":[8.869225,47.490253],"type":"Point"}
}