{
  "type": "Feature",
  "properties": {
    "iso:country":"CH",
    "sg:address":"Bahnhofstrasse 2",
    "sg:city":"Siegershausen",
    "sg:orig_category":"Herstellung von K\u00e4se Verwertung von Milch",
    "sg:phone":"+41 34 408 11 10",
    "sg:postcode":"8573",
    "sg:province":"Thurgau",
    "wof:name":"Tiger K\u00e4se Ag",
    "wof:placetype":"venue"
},
  "geometry": {"coordinates":[7.757589817,46.9491271973],"type":"Point"}
}