{
  "type": "Feature",
  "properties": {
    "iso:country":"CH",
    "sg:address":"Gewerbestrasse 5 6330 Cham. Postfach",
    "sg:city":"Cham",
    "sg:orig_category":"Unternehmensberatung",
    "sg:phone":"+41 41 740 34 80",
    "sg:postcode":"6330",
    "sg:province":"Zug",
    "wof:name":"Globconvest Ag Unternehmensberatung Usw",
    "wof:placetype":"venue"
},
  "geometry": {"coordinates":[8.4734659195,47.1885452271],"type":"Point"}
}