{
  "type": "Feature",
  "properties": {
    "iso:country":"CH",
    "sg:address":"Olgiati Viale C. 20.4",
    "sg:city":"Giubiasco",
    "sg:orig_category":"Detailhandel mit Waren verschiedener Art, Hauptrichtung Nahrungsmittel",
    "sg:phone":"+41 26 927 11 44",
    "sg:postcode":"6512",
    "sg:province":"Ticino",
    "wof:name":"Nelly Overney Alimentation",
    "wof:placetype":"venue"
},
  "geometry": {"coordinates":[7.157790184,46.6337089539],"type":"Point"}
}