{
  "type": "Feature",
  "properties": {
    "iso:country":"CH",
    "sg:address":"Via Onorio Longhi",
    "sg:city":"Arzo",
    "sg:orig_category":"Flachsaufbereitung U spinnerei Handelsvermittlung U Grosshandel",
    "sg:phone":"+41 41 498 08 88",
    "sg:postcode":"6864",
    "sg:province":"Ticino",
    "wof:name":"Freak-inn Basel Gmbh",
    "wof:placetype":"venue"
},
  "geometry": {"coordinates":[8.1827249527,47.0368156433],"type":"Point"}
}