{
  "type": "Feature",
  "properties": {
    "iso:country":"CH",
    "sg:address":"Strada Principale",
    "sg:city":"Poschiavo",
    "sg:orig_category":"Zimmerei, Dachdeckerei, Bauspenglerei U Abdichtung",
    "sg:phone":"+41 17371277",
    "sg:postcode":"7742",
    "sg:province":"Graubunden",
    "wof:name":"Zanini A. & S. Ag",
    "wof:placetype":"venue"
},
  "geometry": {"coordinates":[8.4587945938,47.3600730896],"type":"Point"}
}