{
  "type": "Feature",
  "properties": {
    "iso:country":"CH",
    "sg:address":"Dorfstrasse 13 8332 Russikon. Postfach 25",
    "sg:city":"Russikon",
    "sg:orig_category":"Detailhandel mit Beleuchtungs U Haushaltsgegenst\u00e4nden Detailhandel mit elektrischen Haushalts-,Radio",
    "sg:phone":"+41 19542071",
    "sg:postcode":"8332",
    "sg:province":"Z\u00fcrich",
    "wof:name":"Nenz Haushalt-apparate Ag",
    "wof:placetype":"venue"
},
  "geometry": {"coordinates":[8.775859,47.393665],"type":"Point"}
}