{
  "type": "Feature",
  "properties": {
    "addr:full":"Unterfeld W\u00e4denswil Z\u00fcrich 8820",
    "addr:postcode":"8820",
    "addr:street":"Zuerich",
    "iso:country":"CH",
    "sg:address":"Unterfeld",
    "sg:city":"W\u00e4denswil",
    "sg:orig_category":"Bauschreinerei Herstellung von M\u00f6beln verschiedener Art",
    "sg:phone":"+41 17802436",
    "sg:postcode":"8820",
    "sg:province":"Z\u00fcrich",
    "wof:name":"Ernst Rusterholz Bau-& Antikschreinerei",
    "wof:placetype":"venue"
},
  "geometry": {"coordinates":[8.669204,47.213978],"type":"Point"}
}