{
  "type": "Feature",
  "properties": {
    "iso:country":"CH",
    "sg:address":"Gerechtigkeitsgasse 1 3011 Bern. Postfach",
    "sg:city":"Bern",
    "sg:orig_category":"RESTAURANTS: TEA-ROOMS",
    "sg:phone":"+41 31 981 21 15",
    "sg:postcode":"3005",
    "sg:province":"Bern",
    "wof:name":"Hans Kobel Tea-room Nydegg.",
    "wof:placetype":"venue"
},
  "geometry": {"coordinates":[7.4556670189,46.9485435486],"type":"Point"}
}