{
  "type": "Feature",
  "properties": {
    "addr:full":"Dorfstrasse 22a Baar Zug 6340",
    "addr:housenumber":"22a",
    "addr:postcode":"6340",
    "addr:street":"Dorfstrasse;Zug",
    "iso:country":"CH",
    "sg:address":"Dorfstrasse 22a",
    "sg:city":"Baar",
    "sg:orig_category":"Architektur U Ingenieurb\u00fcros",
    "sg:phone":"+41 41 210 05 51",
    "sg:postcode":"6340",
    "sg:province":"Zug",
    "wof:name":"Luno Bauingenieure Gmbh",
    "wof:placetype":"venue"
},
  "geometry": {"coordinates":[8.524609,47.194069],"type":"Point"}
}