{
  "type": "Feature",
  "properties": {
    "iso:country":"CH",
    "sg:address":"Rue De Lo\u00e8che 45",
    "sg:city":"Sion",
    "sg:orig_category":"G\u00fcterbef\u00f6rderung im Strassenverkehr",
    "sg:postcode":"1950",
    "sg:province":"Valais",
    "wof:name":"Fournier Roland, Camionnages-exp\u00e9ditions",
    "wof:placetype":"venue"
},
  "geometry": {"coordinates":[7.3660669327,46.2391166687],"type":"Point"}
}