{
  "type": "Feature",
  "properties": {
    "iso:country":"CH",
    "sg:address":"1657",
    "sg:city":"Abl\u00e4ndschen",
    "sg:classifiers":[
        {
            "category":"Travel",
            "subcategory":"Hotels & Motels",
            "type":"Entertainment"
        }
    ],
    "sg:phone":"+41 26 929 85 50",
    "sg:postcode":"1657",
    "sg:province":"Bern",
    "sg:tags":[
        "hotels",
        "mit",
        "restaurant"
    ],
    "wof:name":"Berghotel Zum Weissen Kreuz",
    "wof:placetype":"venue"
},
  "geometry": {"coordinates":[7.2908358574,46.5750083923],"type":"Point"}
}