{
  "type": "Feature",
  "properties": {
    "iso:country":"CH",
    "sg:address":"R\u00f6ssligasse 10",
    "sg:city":"Seen",
    "sg:orig_category":"Sanit\u00e4r, Heizungs U L\u00fcftungsinstallation",
    "sg:postcode":"8405",
    "sg:province":"Z\u00fcrich",
    "wof:name":"Berber T. H.",
    "wof:placetype":"venue"
},
  "geometry": {"coordinates":[8.2780704498,47.3505363464],"type":"Point"}
}