{
  "type": "Feature",
  "properties": {
    "iso:country":"CH",
    "sg:address":"Wydenmatten 1a",
    "sg:city":"Breitenbach",
    "sg:orig_category":"Sportvereine Ballsport Tennis",
    "sg:postcode":"4226",
    "sg:province":"Solothurn",
    "wof:name":"Tc Brienz",
    "wof:placetype":"venue"
},
  "geometry": {"coordinates":[8.0255346298,46.7567100525],"type":"Point"}
}