{
  "type": "Feature",
  "properties": {
    "iso:country":"CH",
    "sg:address":"Grubplatz 12 9220 Bischofszell. Postfach",
    "sg:city":"Bischofszell",
    "sg:orig_category":"Detailhandel mit Bekleidung Detailhandel mit Damenbekleidung",
    "sg:phone":"+41 71 422 12 66",
    "sg:postcode":"9220",
    "sg:province":"Thurgau",
    "wof:name":"Doris W\u00fcst-graf Mode Dorelle & Mode Bagatelle",
    "wof:placetype":"venue"
},
  "geometry": {"coordinates":[9.241374,47.494003],"type":"Point"}
}