{
  "type": "Feature",
  "properties": {
    "addr:full":"Muristrasse 15 Ottenbach Z\u00fcrich 8913",
    "addr:housenumber":"15",
    "addr:postcode":"8913",
    "addr:street":"Muristrasse",
    "iso:country":"CH",
    "sg:address":"Muristrasse 15",
    "sg:city":"Ottenbach",
    "sg:orig_category":"Detailhandel mit Brot, Back U S\u00fcsswaren",
    "sg:phone":"+41 17611525",
    "sg:postcode":"8913",
    "sg:province":"Z\u00fcrich",
    "wof:name":"Rolf Rimann B\u00e4ckerei-konditorei",
    "wof:placetype":"venue"
},
  "geometry": {"coordinates":[8.402575,47.280724],"type":"Point"}
}