{
  "type": "Feature",
  "properties": {
    "iso:country":"CH",
    "sg:address":"1355",
    "sg:city":"L'abergement",
    "sg:orig_category":"Verwertung von Milch",
    "sg:postcode":"1355",
    "sg:province":"Vaud",
    "wof:name":"Soci\u00e9t\u00e9 De Fromagerie De La Br\u00e9vine",
    "wof:placetype":"venue"
},
  "geometry": {"coordinates":[6.6068201065,46.9808044434],"type":"Point"}
}