{
  "type": "Feature",
  "properties": {
    "iso:country":"CH",
    "sg:address":"Fabrikstrasse 6",
    "sg:city":"Hinwil",
    "sg:orig_category":"G\u00fcterbef\u00f6rderung im Strassenverkehr",
    "sg:phone":"+41 19371441",
    "sg:postcode":"8340",
    "sg:province":"Z\u00fcrich",
    "wof:name":"Confima Internationale Transporte",
    "wof:placetype":"venue"
},
  "geometry": {"coordinates":[8.8376350403,47.3005714417],"type":"Point"}
}