{
  "type": "Feature",
  "properties": {
    "iso:country":"CH",
    "sg:address":"1678",
    "sg:city":"Siviriez",
    "sg:orig_category":"Verwertung von Milch",
    "sg:postcode":"1678",
    "sg:province":"Fribourg",
    "wof:name":"Soci\u00e9t\u00e9 De Laiterie Du S\u00e9pey",
    "wof:placetype":"venue"
},
  "geometry": {"coordinates":[7.0534849167,46.3616447449],"type":"Point"}
}