{
  "type": "Feature",
  "properties": {
    "addr:full":"Purgira Stierva Graubunden 7459",
    "addr:housenumber":"7459",
    "iso:country":"CH",
    "sg:address":"Purgira",
    "sg:city":"Stierva",
    "sg:orig_category":"Aktivit\u00e4ten der Generalunternehmen im Baugewerbe Allgemeiner Hoch U Tiefbau",
    "sg:phone":"+41 81 637 01 06",
    "sg:postcode":"7459",
    "sg:province":"Graubunden",
    "wof:name":"Bafa Gu Gmbh",
    "wof:placetype":"venue"
},
  "geometry": {"coordinates":[9.542105,46.662601],"type":"Point"}
}