{
  "type": "Feature",
  "properties": {
    "iso:country":"CH",
    "sg:address":"Im Holderbaum 29",
    "sg:city":"Bauma",
    "sg:orig_category":"Kaminfeger",
    "sg:phone":"+41 21 624 86 10",
    "sg:postcode":"8494",
    "sg:province":"Z\u00fcrich",
    "wof:name":"Claude Lambelet Maitre Ramoneur",
    "wof:placetype":"venue"
},
  "geometry": {"coordinates":[6.596683979,46.5312423706],"type":"Point"}
}