{
  "type": "Feature",
  "properties": {
    "iso:country":"CH",
    "sg:address":"Chemin Vers-chez-cottier 19",
    "sg:city":"Blonay",
    "sg:orig_category":"Wirtschaftspr\u00fcfung, Steuerberatung U Treuhand",
    "sg:phone":"+41 21 943 46 23",
    "sg:postcode":"1807",
    "sg:province":"Vaud",
    "wof:name":"Fiduciaire Borloz Maurice",
    "wof:placetype":"venue"
},
  "geometry": {"coordinates":[6.8965411186,46.4758644104],"type":"Point"}
}