{
  "type": "Feature",
  "properties": {
    "iso:country":"CH",
    "sg:address":"Avenue Louis-casa\u00ef 71 1217 Meyrin. Postfach",
    "sg:city":"Meyrin",
    "sg:orig_category":"Herstellung von elektronischen Bauelementen",
    "sg:postcode":"1217",
    "sg:province":"Gen\u00e8ve",
    "wof:name":"Myspares.com Sa Vente De Mat\u00e9riel \u00e9lectronique, Notammm. De Pi\u00e8ces D\u00e9tach\u00e9es",
    "wof:placetype":"venue"
},
  "geometry": {"coordinates":[6.1082839966,46.2240638733],"type":"Point"}
}