{
  "type": "Feature",
  "properties": {
    "iso:country":"CH",
    "sg:address":"Milit\u00e4rstrasse 52 8000 Z\u00fcrich. Postfach",
    "sg:city":"Z\u00fcrich",
    "sg:orig_category":"Sonstiger Grosshandel",
    "sg:postcode":"8046",
    "sg:province":"Z\u00fcrich",
    "wof:name":"My Place Gmbh",
    "wof:placetype":"venue"
},
  "geometry": {"coordinates":[8.5314359665,47.377658844],"type":"Point"}
}