{
  "type": "Feature",
  "properties": {
    "iso:country":"CH",
    "sg:address":"Lindenplatz 5",
    "sg:city":"Gr\u00e4nichen",
    "sg:orig_category":"RESTAURANTS: TEA-ROOMS",
    "sg:phone":"+41 62 216 12 61",
    "sg:postcode":"5722",
    "sg:province":"Aargau",
    "wof:name":"Restaurant Linde Lack Franziska Und Marius",
    "wof:placetype":"venue"
},
  "geometry": {"coordinates":[7.8545498848,47.3280143738],"type":"Point"}
}