{
  "type": "Feature",
  "properties": {
    "iso:country":"CH",
    "sg:address":"Breitestrasse 11 8451 Kleinandelfingen. Postfach 34",
    "sg:city":"Kleinandelfingen",
    "sg:orig_category":"Wirtschaftspr\u00fcfung, Steuerberatung U Treuhand",
    "sg:phone":"+41 52 317 26 73",
    "sg:postcode":"8451",
    "sg:province":"Z\u00fcrich",
    "wof:name":"Kempf Verwaltung",
    "wof:placetype":"venue"
},
  "geometry": {"coordinates":[8.681473732,47.6000900269],"type":"Point"}
}