{
  "type": "Feature",
  "properties": {
    "iso:country":"CH",
    "sg:address":"Unterdorf 6",
    "sg:city":"Beringen",
    "sg:orig_category":"Offsetdruck",
    "sg:phone":"+41 52 680 11 23",
    "sg:postcode":"8222",
    "sg:province":"Schaffhausen",
    "wof:name":"Stamm & Co Grafisches Unternehmen",
    "wof:placetype":"venue"
},
  "geometry": {"coordinates":[8.5750236511,47.696849823],"type":"Point"}
}