{
  "type": "Feature",
  "properties": {
    "iso:country":"CH",
    "sg:address":"Distelbergstrasse 12",
    "sg:city":"Aarau",
    "sg:orig_category":"Gesundheitswesen",
    "sg:phone":"+41 62 822 95 65",
    "sg:postcode":"5000",
    "sg:province":"Aargau",
    "wof:name":"Institut F\u00fcr Beratungen Im Gesundheitswesen Ibg",
    "wof:placetype":"venue"
},
  "geometry": {"coordinates":[8.0509090424,47.3802146912],"type":"Point"}
}