{
  "type": "Feature",
  "properties": {
    "iso:country":"CH",
    "sg:address":"Egnacher Strasse 11",
    "sg:city":"Frasnacht",
    "sg:orig_category":"Vereine Musik/Blasmusik",
    "sg:phone":"+41 71 446 15 91",
    "sg:postcode":"9320",
    "sg:province":"Thurgau",
    "wof:name":"Stadtmusik Arbon",
    "wof:placetype":"venue"
},
  "geometry": {"coordinates":[9.4082956314,47.5252799988],"type":"Point"}
}