{
  "type": "Feature",
  "properties": {
    "iso:country":"CH",
    "sg:address":"Lerchenplatz 1",
    "sg:city":"Meggen",
    "sg:orig_category":"RESTAURANTS: TEA-ROOMS",
    "sg:phone":"+41 71 277 96 06",
    "sg:postcode":"6045",
    "sg:province":"Luzern",
    "wof:name":"Restaurant Lerchenfeld Kunsteisbahn & Schwimmbad",
    "wof:placetype":"venue"
},
  "geometry": {"coordinates":[9.3415660858,47.4152908325],"type":"Point"}
}