{
  "type": "Feature",
  "properties": {
    "iso:country":"CH",
    "sg:address":"Bundesgasse 32 3011 Bern. Postfach",
    "sg:city":"Bern",
    "sg:orig_category":"Alters U Hinterlassenenversicherung AHV, Invalidenversicherung IV, Arbeitslosenversicherung ALV",
    "sg:phone":"+41 31 322 64 25",
    "sg:postcode":"3003",
    "sg:province":"Bern",
    "wof:name":"Eidg. Ausgleichskasse",
    "wof:placetype":"venue"
},
  "geometry": {"coordinates":[7.438846,46.946224],"type":"Point"}
}