{
  "type": "Feature",
  "properties": {
    "iso:country":"CH",
    "sg:address":"Sihlquai 107",
    "sg:city":"Z\u00fcrich",
    "sg:orig_category":"Vermietung U Verpachtung von eigenen Immobilien Vermittlung von Immobilien",
    "sg:phone":"+41 12725859",
    "sg:postcode":"8005",
    "sg:province":"Z\u00fcrich",
    "wof:name":"Tanimag Immobiliengesellschaft Ag",
    "wof:placetype":"venue"
},
  "geometry": {"coordinates":[8.534989357,47.3842468262],"type":"Point"}
}