{
  "type": "Feature",
  "properties": {
    "iso:country":"CH",
    "sg:address":"Riedhofstrasse 360 8049 Z\u00fcrich. Postfach",
    "sg:city":"Z\u00fcrich",
    "sg:orig_category":"Sonstige mit der Informatik verbundene T\u00e4tigkeiten",
    "sg:postcode":"8049",
    "sg:province":"Z\u00fcrich",
    "wof:name":"Informatik Services Pazinski Jack Informatikdienstleistungen Usw",
    "wof:placetype":"venue"
},
  "geometry": {"coordinates":[8.4830932617,47.4093399048],"type":"Point"}
}