{
  "type": "Feature",
  "properties": {
    "iso:country":"CH",
    "sg:address":"Kindergartenweg 3 5105 Auenstein. Postfach",
    "sg:city":"Auenstein",
    "sg:orig_category":"Allgemeiner Hoch U Tiefbau",
    "sg:phone":"+41 62 897 56 00",
    "sg:postcode":"5105",
    "sg:province":"Aargau",
    "wof:name":"S\u00fcess Bau Und Immobilien Dienstleistungen Gmbh",
    "wof:placetype":"venue"
},
  "geometry": {"coordinates":[8.138031,47.418362],"type":"Point"}
}