{
  "type": "Feature",
  "properties": {
    "iso:country":"CH",
    "sg:address":"L'abbaye",
    "sg:city":"Collonges",
    "sg:orig_category":"Architektur U Ingenieurb\u00fcros",
    "sg:postcode":"1903",
    "sg:province":"Valais",
    "wof:name":"Lavigne Christian",
    "wof:placetype":"venue"
},
  "geometry": {"coordinates":[6.9993,46.297764],"type":"Point"}
}