{
  "type": "Feature",
  "properties": {
    "iso:country":"CH",
    "sg:address":"Garwidenstr. 21",
    "sg:city":"Oensingen",
    "sg:classifiers":[
        {
            "category":"Manufacturing",
            "subcategory":"Chemicals & Compounds",
            "type":"Manufacturing & Wholesale Goods"
        }
    ],
    "sg:phone":"+41 62 396 26 60",
    "sg:postcode":"4702",
    "sg:province":"Solothurn",
    "sg:tags":[
        "pharmaceutical",
        "chemistry",
        "-",
        "by-product"
    ],
    "wof:name":"Lederer Ag",
    "wof:placetype":"venue"
},
  "geometry": {"coordinates":[7.708489,47.281376],"type":"Point"}
}