{
  "type": "Feature",
  "properties": {
    "iso:country":"CH",
    "sg:address":"Aprikosenstrasse 5",
    "sg:city":"Z\u00fcrich",
    "sg:orig_category":"Vereine Abstinenten",
    "sg:phone":"+41 13223950",
    "sg:postcode":"8051",
    "sg:province":"Z\u00fcrich",
    "wof:name":"Blaues Kreuz Schwamendingen",
    "wof:placetype":"venue"
},
  "geometry": {"coordinates":[8.5706853867,47.4057350159],"type":"Point"}
}