{
  "type": "Feature",
  "properties": {
    "iso:country":"CH",
    "sg:address":"Pr\u00e9-j\u00e9r\u00f4me Rue Du 22 1205 Gen\u00e8ve. Postfach",
    "sg:city":"Gen\u00e8ve",
    "sg:orig_category":"Vermietung U Verpachtung von eigenen Immobilien",
    "sg:postcode":"1201",
    "sg:province":"Gen\u00e8ve",
    "wof:name":"Med Gestion Sa",
    "wof:placetype":"venue"
},
  "geometry": {"coordinates":[6.1465182304,46.1924972534],"type":"Point"}
}