{
  "type": "Feature",
  "properties": {
    "iso:country":"CH",
    "sg:address":"Gewerbestrasse 16",
    "sg:city":"Egg",
    "sg:classifiers":[
        {
            "category":"Organizations",
            "subcategory":"Political Organization",
            "type":"Services"
        }
    ],
    "sg:phone":"+41 19862400",
    "sg:postcode":"8132",
    "sg:province":"Z\u00fcrich",
    "sg:tags":[
        "cabling",
        "system"
    ],
    "wof:name":"Kontakt Systeme",
    "wof:placetype":"venue"
},
  "geometry": {"coordinates":[8.693547,47.303864],"type":"Point"}
}