{
  "type": "Feature",
  "properties": {
    "iso:country":"CH",
    "sg:address":"Im Haufland 20",
    "sg:city":"Gr\u00fcningen",
    "sg:orig_category":"Softwareentwicklung U beratung",
    "sg:postcode":"8627",
    "sg:province":"Z\u00fcrich",
    "wof:name":"Computer Grafik Sound Reimann Thomas U.",
    "wof:placetype":"venue"
},
  "geometry": {"coordinates":[8.7673578262,47.283908844],"type":"Point"}
}