{
  "type": "Feature",
  "properties": {
    "addr:full":"Schulhausstrasse 16 8887 Mels. Postfach Mels St. Gallen 8887",
    "addr:housenumber":"16",
    "addr:postcode":"8887 mels. postfach;8887",
    "addr:street":"Schulhausstrasse",
    "iso:country":"CH",
    "sg:address":"Schulhausstrasse 16 8887 Mels. Postfach",
    "sg:city":"Mels",
    "sg:orig_category":"Bauspenglerei Zimmerei, Dachdeckerei, Bauspenglerei U Abdichtung",
    "sg:phone":"+41 81 723 12 75",
    "sg:postcode":"8887",
    "sg:province":"St. Gallen",
    "wof:name":"Gm\u00fcnder E. & Co",
    "wof:placetype":"venue"
},
  "geometry": {"coordinates":[9.421547,47.049351],"type":"Point"}
}