{
  "type": "Feature",
  "properties": {
    "iso:country":"CH",
    "sg:address":"L\u00e4nggasse 5",
    "sg:city":"Thun",
    "sg:orig_category":"Detailhandel mit Beleuchtungs U Haushaltsgegenst\u00e4nden Detailhandel mit elektrischen Haushalts-,Radio",
    "sg:phone":"+41 26 652 41 26",
    "sg:postcode":"3600",
    "sg:province":"Bern",
    "wof:name":"Maillard \u00e9lectro-m\u00e9nager S\u00e0rl",
    "wof:placetype":"venue"
},
  "geometry": {"coordinates":[6.92757,46.679989],"type":"Point"}
}