{
  "type": "Feature",
  "properties": {
    "iso:country":"CH",
    "sg:address":"Z\u00fcrcherstrasse 29a",
    "sg:city":"Sargans",
    "sg:orig_category":"Geb\u00e4ude, Wohnungsreinigung",
    "sg:phone":"+41 81 723 42 43",
    "sg:postcode":"7320",
    "sg:province":"St. Gallen",
    "wof:name":"Paula Frehner Baureinigungen",
    "wof:placetype":"venue"
},
  "geometry": {"coordinates":[9.4360780716,47.0484695435],"type":"Point"}
}