{
  "type": "Feature",
  "properties": {
    "iso:country":"CH",
    "sg:address":"Bromeggstrasse 6",
    "sg:city":"Biberist",
    "sg:orig_category":"Non-Classified Establishments",
    "sg:phone":"+41 77317727",
    "sg:postcode":"4562",
    "sg:province":"Solothurn",
    "wof:name":"Hasler & Co",
    "wof:placetype":"venue"
},
  "geometry": {"coordinates":[7.5651078224,47.1880607605],"type":"Point"}
}