{
  "type": "Feature",
  "properties": {
    "iso:country":"CH",
    "sg:address":"La Crusch",
    "sg:city":"Ramosch",
    "sg:orig_category":"G\u00fcterbef\u00f6rderung im Strassenverkehr",
    "sg:phone":"+41 81 866 31 30",
    "sg:postcode":"7556",
    "sg:province":"Graubunden",
    "wof:name":"Alois Laurent Transporte",
    "wof:placetype":"venue"
},
  "geometry": {"coordinates":[10.3815145493,46.8347015381],"type":"Point"}
}