{
  "type": "Feature",
  "properties": {
    "iso:country":"CH",
    "sg:address":"Pichard Rue 8",
    "sg:city":"Lausanne",
    "sg:orig_category":"RESTAURANTS: TEA-ROOMS",
    "sg:postcode":"1003",
    "sg:province":"Vaud",
    "wof:name":"Rod Philippe",
    "wof:placetype":"venue"
},
  "geometry": {"coordinates":[6.630382061,46.5220718384],"type":"Point"}
}