{
  "type": "Feature",
  "properties": {
    "iso:country":"CH",
    "sg:address":"Malerweg 2 3600 Thun. Postfach",
    "sg:city":"Thun",
    "sg:orig_category":"Herstellung von medizinischen U chirurgischen Ger\u00e4ten sowie orthop\u00e4dischen Vorrichtungen",
    "sg:postcode":"3600",
    "sg:province":"Bern",
    "wof:name":"Gerardo Ventre",
    "wof:placetype":"venue"
},
  "geometry": {"coordinates":[7.6278810501,46.7565879822],"type":"Point"}
}