{
  "type": "Feature",
  "properties": {
    "iso:country":"CH",
    "sg:address":"Zona Industriale",
    "sg:city":"Quartino",
    "sg:classifiers":[
        {
            "category":"Wholesale",
            "subcategory":"Vending Machines",
            "type":"Manufacturing & Wholesale Goods"
        }
    ],
    "sg:phone":"+41 91 858 24 64",
    "sg:postcode":"6572",
    "sg:province":"Ticino",
    "sg:tags":[
        "erosive",
        "cutting"
    ],
    "wof:name":"Agema Sa",
    "wof:placetype":"venue"
},
  "geometry": {"coordinates":[8.8953781128,46.1506347656],"type":"Point"}
}