{
  "type": "Feature",
  "properties": {
    "iso:country":"CH",
    "sg:address":"Bassin Route De 12",
    "sg:city":"Conthey",
    "sg:orig_category":"RESTAURANTS: TEA-ROOMS",
    "sg:postcode":"1964",
    "sg:province":"Valais",
    "wof:name":"Le Pacha, Pertew Zaki",
    "wof:placetype":"venue"
},
  "geometry": {"coordinates":[6.826113224,47.1013717651],"type":"Point"}
}