{
  "type": "Feature",
  "properties": {
    "iso:country":"CH",
    "sg:address":"Zugerstrasse 4 6330 Cham. Postfach",
    "sg:city":"Cham",
    "sg:orig_category":"RESTAURANTS: TEA-ROOMS",
    "sg:postcode":"6330",
    "sg:province":"Zug",
    "wof:name":"Mawag Restaurations Gmbh, Zweigniederlassung Wirtschaft Zur Milchs\u00fcdi",
    "wof:placetype":"venue"
},
  "geometry": {"coordinates":[8.4604520798,47.1811637878],"type":"Point"}
}