{
  "type": "Feature",
  "properties": {
    "iso:country":"CH",
    "sg:address":"Spitalgasse 33 3011 Bern. Postfach",
    "sg:city":"Bern",
    "sg:orig_category":"Pensionskassen",
    "sg:phone":"+41 31 950 81 11",
    "sg:postcode":"3005",
    "sg:province":"Bern",
    "wof:name":"F\u00fcrsorgestiftung Des Schweizerischen Fussball-verbandes Und Seiner Abteilungen",
    "wof:placetype":"venue"
},
  "geometry": {"coordinates":[7.4845919609,46.9362754822],"type":"Point"}
}