{
  "type": "Feature",
  "properties": {
    "iso:country":"CH",
    "sg:address":"K\u00fcchengasse 3",
    "sg:city":"Basel",
    "sg:classifiers":[
        {
            "category":"Restaurant",
            "type":"Food & Drink"
        }
    ],
    "sg:phone":"+41 71 911 10 78",
    "sg:postcode":"4051",
    "sg:province":"Basel-Stadt",
    "wof:name":"Restaurant Da Vinci",
    "wof:placetype":"venue"
},
  "geometry": {"coordinates":[9.0502700806,47.4664573669],"type":"Point"}
}