{
  "type": "Feature",
  "properties": {
    "iso:country":"CH",
    "sg:address":"Route De Taillepied 125",
    "sg:city":"Lutry",
    "sg:classifiers":[
        {
            "category":"Building & Trades",
            "subcategory":"Electrical",
            "type":"Services"
        }
    ],
    "sg:phone":"+41 21 793 12 12",
    "sg:postcode":"1095",
    "sg:province":"Vaud",
    "sg:tags":[
        "engineering",
        "construction",
        "architectural",
        "software"
    ],
    "wof:name":"Baucad",
    "wof:placetype":"venue"
},
  "geometry": {"coordinates":[6.68407,46.504967],"type":"Point"}
}