{
  "type": "Feature",
  "properties": {
    "iso:country":"CH",
    "sg:address":"4316",
    "sg:city":"Hellikon",
    "sg:orig_category":"Vereine Frauen",
    "sg:postcode":"4316",
    "sg:province":"Aargau",
    "wof:name":"Allg.frauenverein",
    "wof:placetype":"venue"
},
  "geometry": {"coordinates":[7.9253678322,47.5085830688],"type":"Point"}
}