{
  "type": "Feature",
  "properties": {
    "iso:country":"CH",
    "sg:address":"Schulweg 2 3014 Bern. Postfach 243",
    "sg:city":"Bern",
    "sg:orig_category":"Herstellung von Sitzm\u00f6beln",
    "sg:phone":"+41 31 333 94 94",
    "sg:postcode":"3014",
    "sg:province":"Bern",
    "wof:name":"Villa Collection Valavanis-grimm",
    "wof:placetype":"venue"
},
  "geometry": {"coordinates":[7.4467668533,46.9563674927],"type":"Point"}
}