{
  "type": "Feature",
  "properties": {
    "iso:country":"CH",
    "sg:address":"Junkerngasse 33",
    "sg:city":"Bern",
    "sg:orig_category":"Fotografische Ateliers",
    "sg:phone":"+41 31 311 85 04",
    "sg:postcode":"3011",
    "sg:province":"Bern",
    "wof:name":"Michael Von Graffenried Fotografisches Atelier",
    "wof:placetype":"venue"
},
  "geometry": {"coordinates":[7.4546380043,46.9478378296],"type":"Point"}
}