{
  "type": "Feature",
  "properties": {
    "iso:country":"CH",
    "sg:address":"Reinacherstr. 101 Pf 4018",
    "sg:city":"Basel",
    "sg:classifiers":[
        {
            "category":"Manufacturing",
            "subcategory":"Paper Products",
            "type":"Manufacturing & Wholesale Goods"
        }
    ],
    "sg:phone":"+41 61 337 89 89",
    "sg:postcode":"4053",
    "sg:province":"Basel-Stadt",
    "sg:tags":[
        "packaging",
        "material",
        "-",
        "cardboard"
    ],
    "wof:name":"Textil-emballagen Ag",
    "wof:placetype":"venue"
},
  "geometry": {"coordinates":[7.587679863,47.548740387],"type":"Point"}
}