{
  "type": "Feature",
  "properties": {
    "iso:country":"CH",
    "sg:address":"Seefeldstrasse 255 8008 Z\u00fcrich. Postfach",
    "sg:city":"Z\u00fcrich",
    "sg:orig_category":"Reiseb\u00fcros U Reiseveranstalter",
    "sg:phone":"+41 14222017",
    "sg:postcode":"8034",
    "sg:province":"Z\u00fcrich",
    "wof:name":"Inter Frei Travel Reiseveranstalter, Touristikberatung, Pauschalreisenvermittlung",
    "wof:placetype":"venue"
},
  "geometry": {"coordinates":[8.5624580383,47.3498268127],"type":"Point"}
}