{
  "type": "Feature",
  "properties": {
    "addr:full":"Buchholzstrasse 119 Z\u00fcrich Z\u00fcrich 8053",
    "addr:housenumber":"119",
    "addr:postcode":"8053",
    "addr:street":"Buchholzstrasse",
    "iso:country":"CH",
    "sg:address":"Buchholzstrasse 119",
    "sg:city":"Z\u00fcrich",
    "sg:orig_category":"Architektur U Ingenieurb\u00fcros",
    "sg:postcode":"8053",
    "sg:province":"Z\u00fcrich",
    "wof:name":"Geba, Ernst Gerber & Co Technisches B\u00fcro, Hoch- U. Tiefbauunternehmung.",
    "wof:placetype":"venue"
},
  "geometry": {"coordinates":[8.588862,47.36105],"type":"Point"}
}