{
  "type": "Feature",
  "properties": {
    "iso:country":"CH",
    "sg:address":"Bibersteinerstrasse 4",
    "sg:city":"Rombach",
    "sg:orig_category":"Nationale Postdienste",
    "sg:phone":"+41 62 827 22 12",
    "sg:postcode":"5022",
    "sg:province":"Aargau",
    "wof:name":"Die Schweizerische Post",
    "wof:placetype":"venue"
},
  "geometry": {"coordinates":[8.0446195602,47.4017982483],"type":"Point"}
}