{
  "type": "Feature",
  "properties": {
    "iso:country":"CH",
    "sg:address":"Stauffacherstr. 60 Postfach 2248",
    "sg:city":"Bern",
    "sg:classifiers":[
        {
            "category":"Professional",
            "subcategory":"Engineering",
            "type":"Services"
        }
    ],
    "sg:phone":"+41 71 288 33 44",
    "sg:postcode":"3001",
    "sg:province":"Bern",
    "sg:tags":[
        "machine",
        "-",
        "mechanical"
    ],
    "wof:name":"Schiffner Ag",
    "wof:placetype":"venue"
},
  "geometry": {"coordinates":[9.4171895981,47.4447937012],"type":"Point"}
}