{
  "type": "Feature",
  "properties": {
    "addr:full":"Im Rigi 1 Wald Z\u00fcrich 8636",
    "addr:housenumber":"1",
    "addr:postcode":"8636",
    "addr:street":"Im Rigi",
    "iso:country":"CH",
    "sg:address":"Im Rigi 1",
    "sg:city":"Wald",
    "sg:classifiers":[
        {
            "category":"Organizations",
            "subcategory":"Labor Organization",
            "type":"Services"
        }
    ],
    "sg:phone":"+41 55 246 18 14",
    "sg:postcode":"8636",
    "sg:province":"Z\u00fcrich",
    "sg:tags":[
        "work",
        "assembling",
        "assembly",
        "contract"
    ],
    "wof:name":"Artho Pan Ag",
    "wof:placetype":"venue"
},
  "geometry": {"coordinates":[-69.00396000000001,44.434299],"type":"Point"}
}