{
  "type": "Feature",
  "properties": {
    "iso:country":"CH",
    "sg:address":"Herrenacker 18",
    "sg:city":"Schaffhausen",
    "sg:orig_category":"RESTAURANTS: TEA-ROOMS",
    "sg:postcode":"8200",
    "sg:province":"Schaffhausen",
    "wof:name":"Duck Ida",
    "wof:placetype":"venue"
},
  "geometry": {"coordinates":[8.6325407028,47.6956100464],"type":"Point"}
}