{
  "type": "Feature",
  "properties": {
    "addr:full":"Rue Ancien-lavoir 2 Ani\u00e8res Gen\u00e8ve 1247",
    "addr:housenumber":"2",
    "addr:postcode":"1247",
    "addr:street":"Rue Ancien-Lavoir",
    "iso:country":"CH",
    "sg:address":"Rue Ancien-lavoir 2",
    "sg:city":"Ani\u00e8res",
    "sg:orig_category":"Bauschreinerei",
    "sg:phone":"+41 79 626 56 06",
    "sg:postcode":"1247",
    "sg:province":"Gen\u00e8ve",
    "wof:name":"Bernard Fluckiger Menuiserie",
    "wof:placetype":"venue"
},
  "geometry": {"coordinates":[6.221495,46.273991],"type":"Point"}
}