{
  "type": "Feature",
  "properties": {
    "iso:country":"CH",
    "sg:address":"Im Moos Ebersol 9114 Hoffeld. Postfach",
    "sg:city":"Hoffeld",
    "sg:orig_category":"Betrieb U technische Hilfsdienste des Kultur U Unterhaltungswesens",
    "sg:phone":"+41 71 375 60 77",
    "sg:postcode":"9114",
    "sg:province":"St. Gallen",
    "wof:name":"Balik Farm Gmbh",
    "wof:placetype":"venue"
},
  "geometry": {"coordinates":[9.175026,47.362423],"type":"Point"}
}