{
  "type": "Feature",
  "properties": {
    "iso:country":"CH",
    "sg:address":"Rathausplatz 1",
    "sg:city":"Glarus",
    "sg:orig_category":"Elektroinstallation Herstellung von elektrischen Lampen U Leuchten",
    "sg:phone":"+41 55 640 72 04",
    "sg:postcode":"8750",
    "sg:province":"Glarus",
    "wof:name":"Stefan Freuler Leuchtenbau & Elektroanlagen",
    "wof:placetype":"venue"
},
  "geometry": {"coordinates":[9.0683555603,47.0400276184],"type":"Point"}
}