{
  "type": "Feature",
  "properties": {
    "iso:country":"CH",
    "sg:address":"Marktgasse 25",
    "sg:city":"Winterthur",
    "sg:classifiers":[
        {
            "category":"Education",
            "subcategory":"Library",
            "type":"Public Place"
        }
    ],
    "sg:phone":"+41 52 267 51 33",
    "sg:postcode":"8400",
    "sg:province":"Z\u00fcrich",
    "sg:tags":[
        "u",
        "bibliotheken",
        "archive"
    ],
    "wof:name":"Kreisbibliothek Altstadt",
    "wof:placetype":"venue"
},
  "geometry": {"coordinates":[8.729109,47.49955],"type":"Point"}
}