{
  "type": "Feature",
  "properties": {
    "iso:country":"CH",
    "sg:address":"Via Cattaneo 5",
    "sg:city":"Chiasso",
    "sg:orig_category":"Autotransporte international Pensionskassen",
    "sg:phone":"+41 17335111",
    "sg:postcode":"6830",
    "sg:province":"Ticino",
    "wof:name":"Personalf\u00fcrsorgestiftung Der Firma M\u00f6bel-transport Ag",
    "wof:placetype":"venue"
},
  "geometry": {"coordinates":[9.026355,45.831242],"type":"Point"}
}