{
  "type": "Feature",
  "properties": {
    "iso:country":"CH",
    "sg:address":"Via Orselina 6",
    "sg:city":"Muralto",
    "sg:classifiers":[
        {
            "category":"Restaurant",
            "type":"Food & Drink"
        }
    ],
    "sg:phone":"+41 26 652 31 07",
    "sg:postcode":"6600",
    "sg:province":"Ticino",
    "wof:name":"Pause Caf\u00e9",
    "wof:placetype":"venue"
},
  "geometry": {"coordinates":[6.9142532349,46.6929855347],"type":"Point"}
}