{
  "type": "Feature",
  "properties": {
    "iso:country":"CH",
    "sg:address":"Friedhofweg 4",
    "sg:city":"Otelfingen",
    "sg:orig_category":"Wirtschaftspr\u00fcfung, Steuerberatung U Treuhand",
    "sg:phone":"+41 18444371",
    "sg:postcode":"8112",
    "sg:province":"Z\u00fcrich",
    "wof:name":"Furttal Treuhand Ag",
    "wof:placetype":"venue"
},
  "geometry": {"coordinates":[8.3893136978,47.4616851807],"type":"Point"}
}