{
  "type": "Feature",
  "properties": {
    "iso:country":"CH",
    "sg:address":"Baldismoosstrasse 39 6043 Adligenswil. Postfach 375",
    "sg:city":"Adligenswil",
    "sg:orig_category":"G\u00fcterbef\u00f6rderung im Strassenverkehr",
    "sg:phone":"+41 41 370 31 45",
    "sg:postcode":"6043",
    "sg:province":"Luzern",
    "wof:name":"Reinhard Grund Transporte",
    "wof:placetype":"venue"
},
  "geometry": {"coordinates":[8.3763179779,47.0723953247],"type":"Point"}
}