{
  "type": "Feature",
  "properties": {
    "iso:country":"CH",
    "sg:address":"R\u00f6ssligasse 15",
    "sg:city":"Gelterkinden",
    "sg:orig_category":"Detailhandel mit Brillen U anderen Sehhilfen Fachdetailhandel in Verkaufsr\u00e4umen",
    "sg:phone":"+41 61 985 94 00",
    "sg:postcode":"4460",
    "sg:province":"Basel-Landschaft",
    "wof:name":"Optic Clavadetscher",
    "wof:placetype":"venue"
},
  "geometry": {"coordinates":[7.854139,47.465191],"type":"Point"}
}