{
  "type": "Feature",
  "properties": {
    "iso:country":"CH",
    "sg:address":"3115 Gerzensee. Postfach 12",
    "sg:city":"Gerzensee",
    "sg:orig_category":"Vereine Musik/Blasmusik",
    "sg:postcode":"3115",
    "sg:province":"Bern",
    "wof:name":"Musikgesellschaft",
    "wof:placetype":"venue"
},
  "geometry": {"coordinates":[7.5467591286,46.8397903442],"type":"Point"}
}