{
  "type": "Feature",
  "properties": {
    "iso:country":"CH",
    "sg:address":"Via Rodari 22",
    "sg:city":"Lugano",
    "sg:orig_category":"Architekturb\u00fcros",
    "sg:phone":"+41 91 966 11 40",
    "sg:postcode":"6900",
    "sg:province":"Ticino",
    "wof:name":"Carlo Cocco Studio D'architettura",
    "wof:placetype":"venue"
},
  "geometry": {"coordinates":[8.943877,46.004436],"type":"Point"}
}