{
  "type": "Feature",
  "properties": {
    "iso:country":"CH",
    "sg:address":"Widderfeld 3",
    "sg:city":"Wolfenschiessen",
    "sg:orig_category":"Dachdeckerei Zimmerei, Dachdeckerei, Bauspenglerei U Abdichtung",
    "sg:phone":"+41 41 628 10 50",
    "sg:postcode":"6386",
    "sg:province":"Nidwalden",
    "wof:name":"Kopp Hans.",
    "wof:placetype":"venue"
},
  "geometry": {"coordinates":[8.3938,46.90226],"type":"Point"}
}