{
  "type": "Feature",
  "properties": {
    "iso:country":"CH",
    "sg:address":"Ringstr. 7",
    "sg:city":"Oberrohrdorf",
    "sg:classifiers":[
        {
            "category":"Banks & Credit Unions",
            "subcategory":"Bank",
            "type":"Services"
        }
    ],
    "sg:phone":"+41 4156962168",
    "sg:postcode":"5452",
    "sg:province":"Aargau",
    "wof:name":"Raiffeisenkasse",
    "wof:placetype":"venue"
},
  "geometry": {"coordinates":[8.316812,47.418442],"type":"Point"}
}