{
  "type": "Feature",
  "properties": {
    "addr:full":"Bahnhofstrasse 3 Rothrist Aargau 4852",
    "addr:housenumber":"3",
    "addr:postcode":"4852",
    "addr:street":"Bahnhofstrasse",
    "iso:country":"CH",
    "sg:address":"Bahnhofstrasse 3",
    "sg:city":"Rothrist",
    "sg:orig_category":"Architektur U Ingenieurb\u00fcros",
    "sg:phone":"+41 62 794 15 75",
    "sg:postcode":"4852",
    "sg:province":"Aargau",
    "wof:name":"Weber & Christen, Architekten",
    "wof:placetype":"venue"
},
  "geometry": {"coordinates":[7.879285,47.305813],"type":"Point"}
}