{
  "type": "Feature",
  "properties": {
    "iso:country":"CH",
    "sg:address":"1912",
    "sg:city":"Leytron",
    "sg:classifiers":[
        {
            "category":"Restaurant",
            "type":"Food & Drink"
        }
    ],
    "sg:phone":"+41 27 306 47 22",
    "sg:postcode":"1912",
    "sg:province":"Valais",
    "wof:name":"Caf\u00e9 Refuge De Farinet",
    "wof:placetype":"venue"
},
  "geometry": {"coordinates":[7.2003498077,46.1885681152],"type":"Point"}
}