{
  "type": "Feature",
  "properties": {
    "iso:country":"CH",
    "sg:address":"Villa An-jo",
    "sg:city":"Tolochenaz",
    "sg:orig_category":"Rebbau",
    "sg:phone":"+41 21 801 18 34",
    "sg:postcode":"1131",
    "sg:province":"Vaud",
    "wof:name":"Andr\u00e9 Jacot Viticulteur-p\u00e9pini\u00e9riste",
    "wof:placetype":"venue"
},
  "geometry": {"coordinates":[6.4742050171,46.5053062439],"type":"Point"}
}