{
  "type": "Feature",
  "properties": {
    "addr:full":"Hellb\u00fcchel 249 Lutzenberg Appenzell Ausserrhoden 9426",
    "addr:housenumber":"249",
    "addr:postcode":"9426",
    "addr:street":"Lutzenberg Appenzell Ausserrhoden",
    "iso:country":"CH",
    "sg:address":"Hellb\u00fcchel 249",
    "sg:city":"Lutzenberg",
    "sg:orig_category":"Bauspenglerei Zimmerei, Dachdeckerei, Bauspenglerei U Abdichtung",
    "sg:phone":"+41 71 888 15 19",
    "sg:postcode":"9426",
    "sg:province":"Appenzell Ausserrhoden",
    "wof:name":"Loppacher E., Inhaber K\u00e4ch K.",
    "wof:placetype":"venue"
},
  "geometry": {"coordinates":[9.563258,47.458195],"type":"Point"}
}