{
  "type": "Feature",
  "properties": {
    "iso:country":"CH",
    "sg:address":"Rue Dr-schwab 20b",
    "sg:city":"St-imier",
    "sg:orig_category":"Handel mit Motorr\u00e4dern, Teilen U Zubeh\u00f6r Instandhaltung U Reparatur von Motorr\u00e4dern",
    "sg:phone":"+41 32 941 40 61",
    "sg:postcode":"2610",
    "sg:province":"Bern",
    "wof:name":"Val-motos Constant Widmer",
    "wof:placetype":"venue"
},
  "geometry": {"coordinates":[7.0029292107,47.1538772583],"type":"Point"}
}