{
  "type": "Feature",
  "properties": {
    "iso:country":"CH",
    "sg:address":"Bundesstrasse 3 6300 Zug. Postfach 4523",
    "sg:city":"Zug",
    "sg:orig_category":"Wirtschaftspr\u00fcfung, Steuerberatung U Treuhand",
    "sg:postcode":"6300",
    "sg:province":"Zug",
    "wof:name":"Neutra Treuhand Ag",
    "wof:placetype":"venue"
},
  "geometry": {"coordinates":[9.3718414307,47.4210281372],"type":"Point"}
}