{
  "type": "Feature",
  "properties": {
    "iso:country":"CH",
    "sg:address":"Kiesweid 16",
    "sg:city":"Hinwil",
    "sg:classifiers":[
        {
            "category":"Professional",
            "subcategory":"Computer Services",
            "type":"Services"
        }
    ],
    "sg:phone":"+41 19306602",
    "sg:postcode":"8340",
    "sg:province":"Z\u00fcrich",
    "sg:tags":[
        "development",
        "software"
    ],
    "wof:name":"Zo Informatik Ag",
    "wof:placetype":"venue"
},
  "geometry": {"coordinates":[8.8584890366,47.2898101807],"type":"Point"}
}