{
  "type": "Feature",
  "properties": {
    "addr:full":"Gibelstrasse 45 Grenchen Solothurn 2540",
    "addr:housenumber":"45",
    "addr:postcode":"2540",
    "addr:street":"Gibelstrasse",
    "iso:country":"CH",
    "sg:address":"Gibelstrasse 45",
    "sg:city":"Grenchen",
    "sg:classifiers":[
        {
            "category":"Banks & Credit Unions",
            "subcategory":"Investment Brokerage",
            "type":"Services"
        }
    ],
    "sg:phone":"+41 32 652 10 82",
    "sg:postcode":"2540",
    "sg:province":"Solothurn",
    "sg:tags":[
        "grinder",
        "cutter"
    ],
    "wof:name":"Prexa Ag",
    "wof:placetype":"venue"
},
  "geometry": {"coordinates":[7.392909,47.189823],"type":"Point"}
}