{
  "type": "Feature",
  "properties": {
    "iso:country":"CH",
    "sg:address":"Schulhausstrasse 2",
    "sg:city":"Wynau",
    "sg:orig_category":"Fachdetailhandel mit Nahrungsmitteln, Getr\u00e4nken U Tabakwaren in Verkaufsr\u00e4umen",
    "sg:phone":"+41 62 929 11 81",
    "sg:postcode":"4923",
    "sg:province":"Bern",
    "wof:name":"Spar Supermarkt",
    "wof:placetype":"venue"
},
  "geometry": {"coordinates":[7.8153362274,47.2564048767],"type":"Point"}
}