{
  "type": "Feature",
  "properties": {
    "iso:country":"CH",
    "sg:address":"Rue Baptiste-savoye 65",
    "sg:city":"St-imier",
    "sg:orig_category":"Finanzierungsinstitutionen",
    "sg:phone":"+41 32 941 21 66",
    "sg:postcode":"2610",
    "sg:province":"Bern",
    "wof:name":"Fontana & Giovannoni Sa",
    "wof:placetype":"venue"
},
  "geometry": {"coordinates":[6.9950151443,47.1517753601],"type":"Point"}
}