{
  "type": "Feature",
  "properties": {
    "iso:country":"CH",
    "sg:address":"Obernauerstrasse 11",
    "sg:city":"Kriens",
    "sg:orig_category":"Wirtschaftspr\u00fcfung, Steuerberatung U Treuhand",
    "sg:phone":"+41 41 320 84 44",
    "sg:postcode":"6010",
    "sg:province":"Luzern",
    "wof:name":"Walter Noser Treuhand-& Revisionsb\u00fcro",
    "wof:placetype":"venue"
},
  "geometry": {"coordinates":[8.2720022202,47.0338592529],"type":"Point"}
}