{
  "type": "Feature",
  "properties": {
    "iso:country":"CH",
    "sg:address":"1543",
    "sg:city":"Grandcour",
    "sg:orig_category":"Drogerien",
    "sg:phone":"+41 26 667 11 73",
    "sg:postcode":"1543",
    "sg:province":"Vaud",
    "wof:name":"Bernard Combremont Droguerie",
    "wof:placetype":"venue"
},
  "geometry": {"coordinates":[6.9286150932,46.8717956543],"type":"Point"}
}