{
  "type": "Feature",
  "properties": {
    "iso:country":"CH",
    "sg:address":"Landstrasse 8",
    "sg:city":"Balzers",
    "sg:orig_category":"Versicherungen Generalagenturen",
    "sg:phone":"+423 384 15 44",
    "sg:postcode":"9496",
    "wof:name":"Z\u00fcrich Leben Generalagentur Lorenz Maier",
    "wof:placetype":"venue"
},
  "geometry": {"coordinates":[9.5109786987,47.0741081238],"type":"Point"}
}