{
  "type": "Feature",
  "properties": {
    "iso:country":"CH",
    "sg:address":"Gewerbestrasse 10",
    "sg:city":"Subingen",
    "sg:orig_category":"Grosshandel mit sonstigen Maschinen U Ausr\u00fcstungen f\u00fcr Industrie, Handel U Schiffahrt",
    "sg:phone":"+41 32 614 45 35",
    "sg:postcode":"4553",
    "sg:province":"Solothurn",
    "wof:name":"Boegli Wagatex Engineering Ag",
    "wof:placetype":"venue"
},
  "geometry": {"coordinates":[7.6040649414,47.197227478],"type":"Point"}
}