{
  "type": "Feature",
  "properties": {
    "iso:country":"CH",
    "sg:address":"La Campagnarde E. 1070 Puidoux. Postfach",
    "sg:city":"Puidoux",
    "sg:orig_category":"Vermietung U Verpachtung von eigenen Immobilien",
    "sg:postcode":"1070",
    "sg:province":"Vaud",
    "wof:name":"Pv Constructions S\u00e0rl Affaires Immobili\u00e8res Etc",
    "wof:placetype":"venue"
},
  "geometry": {"coordinates":[6.7830929756,46.5027084351],"type":"Point"}
}