{
  "type": "Feature",
  "properties": {
    "iso:country":"CH",
    "sg:address":"Place De La Riponne 1",
    "sg:city":"Lausanne",
    "sg:classifiers":[
        {
            "category":"Professional",
            "subcategory":"Business Services",
            "type":"Services"
        }
    ],
    "sg:phone":"+41 21 317 07 07",
    "sg:postcode":"1005",
    "sg:province":"Vaud",
    "sg:tags":[
        "marketing",
        "agency"
    ],
    "wof:name":"Phone Marketing Business Sa",
    "wof:placetype":"venue"
},
  "geometry": {"coordinates":[6.6318898201,46.5232009888],"type":"Point"}
}