{
  "type": "Feature",
  "properties": {
    "addr:full":"Sch\u00f6nenwerderstrasse 6 Aarau Aargau 5000",
    "addr:housenumber":"6",
    "addr:postcode":"5000",
    "addr:street":"Schoenenwerderstrasse",
    "iso:country":"CH",
    "sg:address":"Sch\u00f6nenwerderstrasse 6",
    "sg:city":"Aarau",
    "sg:orig_category":"Allgemeiner Hoch U Tiefbau",
    "sg:postcode":"5000",
    "sg:province":"Aargau",
    "wof:name":"Bruno Rusconi Sa",
    "wof:placetype":"venue"
},
  "geometry": {"coordinates":[8.040822,47.388378],"type":"Point"}
}