{
  "type": "Feature",
  "properties": {
    "iso:country":"CH",
    "sg:address":"Noville",
    "sg:city":"Noville",
    "sg:classifiers":[
        {
            "category":"Banks & Credit Unions",
            "subcategory":"Bank",
            "type":"Services"
        }
    ],
    "sg:phone":"+41 21 960 39 12",
    "sg:postcode":"1845",
    "sg:province":"Vaud",
    "wof:name":"Banque Raiffeisen De Noville",
    "wof:placetype":"venue"
},
  "geometry": {"coordinates":[6.899166,46.381565],"type":"Point"}
}