{
  "type": "Feature",
  "properties": {
    "iso:country":"CH",
    "sg:address":"Rigistrasse 68",
    "sg:city":"Luzern",
    "sg:orig_category":"Vereine Radio, Film and Foto",
    "sg:postcode":"6006",
    "sg:province":"Luzern",
    "wof:name":"Filmclub Luzern",
    "wof:placetype":"venue"
},
  "geometry": {"coordinates":[8.3296375275,47.0581474304],"type":"Point"}
}