{
  "type": "Feature",
  "properties": {
    "iso:country":"CH",
    "sg:address":"Morgentalstrasse 2",
    "sg:city":"Aadorf",
    "sg:orig_category":"Detailhandel mit S\u00e4uglings U Kinderbekleidung Herstellung von W\u00e4sche",
    "sg:phone":"+41 17370611",
    "sg:postcode":"8355",
    "sg:province":"Thurgau",
    "wof:name":"R\u00e4ggi-rebmann, Thee",
    "wof:placetype":"venue"
},
  "geometry": {"coordinates":[8.4363794327,47.3531341553],"type":"Point"}
}