{
  "type": "Feature",
  "properties": {
    "iso:country":"CH",
    "sg:address":"Clos Sur Les Laves 117",
    "sg:city":"Plagne",
    "sg:orig_category":"Fahrschulen, Flugschulen",
    "sg:phone":"+41 79 250 27 68",
    "sg:postcode":"2536",
    "sg:province":"Bern",
    "wof:name":"Ariste Grandjean Auto-\u00e9cole",
    "wof:placetype":"venue"
},
  "geometry": {"coordinates":[7.2864580154,47.1881065369],"type":"Point"}
}