{
  "type": "Feature",
  "properties": {
    "iso:country":"CH",
    "sg:address":"Birkenstrasse 4 8708 M\u00e4nnedorf. Postfach",
    "sg:city":"M\u00e4nnedorf",
    "sg:orig_category":"Non-Classified Establishments",
    "sg:phone":"+41 19221232",
    "sg:postcode":"8708",
    "sg:province":"Z\u00fcrich",
    "wof:name":"Weiss Robert Consulting Kommanditgesellschaft",
    "wof:placetype":"venue"
},
  "geometry": {"coordinates":[8.7048845291,47.2563743591],"type":"Point"}
}