{
  "type": "Feature",
  "properties": {
    "iso:country":"CH",
    "sg:address":"Hauptstrasse 26",
    "sg:city":"Muhen",
    "sg:orig_category":"RESTAURANTS: TEA-ROOMS",
    "sg:phone":"+41 62 723 24 42",
    "sg:postcode":"5037",
    "sg:province":"Aargau",
    "wof:name":"L\u00fcscher W. Restaurant Bahnhof",
    "wof:placetype":"venue"
},
  "geometry": {"coordinates":[8.0535202026,47.3396720886],"type":"Point"}
}