{
  "type": "Feature",
  "properties": {
    "iso:country":"CH",
    "sg:address":"Belmontstrasse 1 7000 Chur. Postfach",
    "sg:city":"Chur",
    "sg:orig_category":"Nationale Postdienste",
    "sg:phone":"+41 81 256 32 96",
    "sg:postcode":"7006",
    "sg:province":"Graubunden",
    "wof:name":"Die Schweizerische Post Chur 6 Lacuna",
    "wof:placetype":"venue"
},
  "geometry": {"coordinates":[9.52617836,46.8617095947],"type":"Point"}
}