{
  "type": "Feature",
  "properties": {
    "addr:full":"Schulstrasse 31 Z\u00fcrich Z\u00fcrich 8050",
    "addr:housenumber":"31",
    "addr:postcode":"8050",
    "addr:street":"Schulstrasse",
    "iso:country":"CH",
    "sg:address":"Schulstrasse 31",
    "sg:city":"Z\u00fcrich",
    "sg:orig_category":"Architekturb\u00fcros",
    "sg:phone":"+41 13132211",
    "sg:postcode":"8050",
    "sg:province":"Z\u00fcrich",
    "wof:name":"Hans-j\u00fcrg B\u00fchler Architekturb\u00fcro",
    "wof:placetype":"venue"
},
  "geometry": {"coordinates":[8.543937,47.409309],"type":"Point"}
}