{
  "type": "Feature",
  "properties": {
    "iso:country":"CH",
    "sg:address":"Charmey",
    "sg:city":"Charmey",
    "sg:classifiers":[
        {
            "category":"Banks & Credit Unions",
            "subcategory":"Bank",
            "type":"Services"
        }
    ],
    "sg:phone":"+41 2971153",
    "sg:postcode":"1637",
    "sg:province":"Fribourg",
    "wof:name":"Banque Raiffeisen De Charmey",
    "wof:placetype":"venue"
},
  "geometry": {"coordinates":[7.164164,46.619221],"type":"Point"}
}