{
  "type": "Feature",
  "properties": {
    "iso:country":"CH",
    "sg:address":"Via Bellinzona 6",
    "sg:city":"Giubiasco",
    "sg:orig_category":"Nationale Postdienste",
    "sg:phone":"+41 91 857 26 74",
    "sg:postcode":"6512",
    "sg:province":"Ticino",
    "wof:name":"La Posta Svizzera",
    "wof:placetype":"venue"
},
  "geometry": {"coordinates":[9.0117511749,46.1749153137],"type":"Point"}
}