{
  "type": "Feature",
  "properties": {
    "iso:country":"CH",
    "sg:address":"Moulins De Granges",
    "sg:city":"Granges-marnand",
    "sg:orig_category":"G\u00fcterbef\u00f6rderung im Strassenverkehr",
    "sg:postcode":"1523",
    "sg:province":"Vaud",
    "wof:name":"Andelic Juro",
    "wof:placetype":"venue"
},
  "geometry": {"coordinates":[6.8875250816,46.7635803223],"type":"Point"}
}