{
  "type": "Feature",
  "properties": {
    "iso:country":"CH",
    "sg:address":"Chatzenr\u00fcti",
    "sg:city":"Amriswil",
    "sg:orig_category":"Allgemeiner Hoch U Tiefbau",
    "sg:phone":"+41 71 411 36 58",
    "sg:postcode":"8580",
    "sg:province":"Thurgau",
    "wof:name":"Heitz Paul",
    "wof:placetype":"venue"
},
  "geometry": {"coordinates":[9.299568,47.545048],"type":"Point"}
}