{
  "type": "Feature",
  "properties": {
    "iso:country":"CH",
    "sg:address":"Grand-rue 7",
    "sg:city":"Fleurier",
    "sg:orig_category":"Organisationen der Wohlfahrtspflege Sonstige Kultur U Unterhaltungseinrichtungen",
    "sg:phone":"+41 32 861 35 05",
    "sg:postcode":"2114",
    "sg:province":"Neuch\u00e2tel",
    "wof:name":"Centre Oecum\u00e9nique De Rencontre & D'animation Cora",
    "wof:placetype":"venue"
},
  "geometry": {"coordinates":[6.5829591751,46.90209198],"type":"Point"}
}