{
  "type": "Feature",
  "properties": {
    "iso:country":"CH",
    "sg:address":"Route D'alle 58 2900 Porrentruy Case Postale 206",
    "sg:city":"Pruntrut",
    "sg:orig_category":"Fernmeldedienste",
    "sg:phone":"+41 32 466 61 88",
    "sg:postcode":"2900",
    "sg:province":"Jura",
    "wof:name":"T\u00e9l\u00e9r\u00e9seau Porrentruy Sa",
    "wof:placetype":"venue"
},
  "geometry": {"coordinates":[7.0852150917,47.4187850952],"type":"Point"}
}