{
  "type": "Feature",
  "properties": {
    "iso:country":"CH",
    "sg:address":"Dufourstrasse 5 4051 Basel. Postfach",
    "sg:city":"Basel",
    "sg:orig_category":"Interessenvertretungen",
    "sg:phone":"+41 91 791 75 47",
    "sg:postcode":"4051",
    "sg:province":"Basel-Stadt",
    "wof:name":"Sherpa Association Switzerland Mantenere L'integrit\u00e0 Nazionale, Territoriale Ecc. D. Comunit\u00e0 Sherpa",
    "wof:placetype":"venue"
},
  "geometry": {"coordinates":[8.7262001038,46.1440429688],"type":"Point"}
}