{
  "type": "Feature",
  "properties": {
    "addr:full":"Am Wasser 161 8049 Z\u00fcrich. Postfach Z\u00fcrich Z\u00fcrich 8049",
    "addr:housenumber":"161",
    "addr:postcode":"8049 zuerich. postfach;8049",
    "addr:street":"Am Wasser",
    "iso:country":"CH",
    "sg:address":"Am Wasser 161 8049 Z\u00fcrich. Postfach",
    "sg:city":"Z\u00fcrich",
    "sg:orig_category":"Betrieb U technische Hilfsdienste des Kultur U Unterhaltungswesens",
    "sg:phone":"+41 13414455",
    "sg:postcode":"8049",
    "sg:province":"Z\u00fcrich",
    "wof:name":"Z\u00f6beli Events & Artists Veranstaltungen; Organisation. K\u00fcnstlervermittlungen",
    "wof:placetype":"venue"
},
  "geometry": {"coordinates":[8.495811,47.39959],"type":"Point"}
}