{
  "type": "Feature",
  "properties": {
    "iso:country":"CH",
    "sg:address":"St\u00e4dtli 21",
    "sg:city":"Werdenberg",
    "sg:orig_category":"Unclassifiable Establishments",
    "sg:postcode":"9470",
    "sg:province":"St. Gallen",
    "wof:name":"Gugg Faserpelz Gmbh",
    "wof:placetype":"venue"
},
  "geometry": {"coordinates":[9.1543264389,47.5649108887],"type":"Point"}
}