{
  "type": "Feature",
  "properties": {
    "iso:country":"CH",
    "sg:address":"Premploz",
    "sg:city":"Erde",
    "sg:orig_category":"Grosshandel mit lebenden Tieren",
    "sg:phone":"+41 32 866 14 18",
    "sg:postcode":"1976",
    "sg:province":"Valais",
    "wof:name":"Jean-fran\u00e7ois Sancey Commerce De B\u00e9tail",
    "wof:placetype":"venue"
},
  "geometry": {"coordinates":[6.4648928642,46.9011192322],"type":"Point"}
}