{
  "type": "Feature",
  "properties": {
    "iso:country":"CH",
    "sg:address":"Route De Bottens 1041 Poliez-le-grand Case Postale 16",
    "sg:city":"Poliez-le-grand",
    "sg:orig_category":"Instandhaltung U Reparatur von Automobilen Mechanische Werkst\u00e4tten",
    "sg:phone":"+41 21 881 13 29",
    "sg:postcode":"1041",
    "sg:province":"Vaud",
    "wof:name":"Freymond Et Fils Sa",
    "wof:placetype":"venue"
},
  "geometry": {"coordinates":[6.6641349792,46.6369094849],"type":"Point"}
}