{
  "type": "Feature",
  "properties": {
    "iso:country":"CH",
    "sg:address":"Alpenstrasse 12 6300 Zug. Postfach",
    "sg:city":"Zug",
    "sg:orig_category":"Handelsvermittlung U Grosshandel Handelsvermittlung von Brennstoffen, Erzen, Metallen U Chemikalien",
    "sg:phone":"+41 41 711 35 10",
    "sg:postcode":"6304",
    "sg:province":"Zug",
    "wof:name":"Carrington Ag",
    "wof:placetype":"venue"
},
  "geometry": {"coordinates":[8.5149440765,47.1725082397],"type":"Point"}
}