{
  "type": "Feature",
  "properties": {
    "iso:country":"CH",
    "sg:address":"Baselstrasse 47",
    "sg:city":"Solothurn",
    "sg:orig_category":"Non-Classified Establishments",
    "sg:postcode":"4500",
    "sg:province":"Solothurn",
    "wof:name":"Yvonne Bernasconi",
    "wof:placetype":"venue"
},
  "geometry": {"coordinates":[7.5451478958,47.2121658325],"type":"Point"}
}