{
  "type": "Feature",
  "properties": {
    "iso:country":"CH",
    "sg:address":"Dienerstrasse 30 8004 Z\u00fcrich. Postfach",
    "sg:city":"Z\u00fcrich",
    "sg:orig_category":"Pensionskassen",
    "sg:phone":"+41 12428592",
    "sg:postcode":"8001",
    "sg:province":"Z\u00fcrich",
    "wof:name":"Personalstiftung Der Genossenschaft F\u00fcr Glas Und Geb\u00e4udereinigung",
    "wof:placetype":"venue"
},
  "geometry": {"coordinates":[8.52780056,47.3782463074],"type":"Point"}
}