{
  "type": "Feature",
  "properties": {
    "iso:country":"CH",
    "sg:address":"Quai Du Haut 8",
    "sg:city":"Biel/bienne",
    "sg:orig_category":"Non-Classified Establishments",
    "sg:postcode":"2503",
    "sg:province":"Bern",
    "wof:name":"Fernandez + Cie",
    "wof:placetype":"venue"
},
  "geometry": {"coordinates":[7.2478427887,47.1372413635],"type":"Point"}
}