{
  "type": "Feature",
  "properties": {
    "iso:country":"CH",
    "sg:address":"In B\u00e4chlere 6",
    "sg:city":"D\u00e4llikon",
    "sg:orig_category":"Unternehmensberatung",
    "sg:postcode":"8108",
    "sg:province":"Z\u00fcrich",
    "wof:name":"Biaggi Richard",
    "wof:placetype":"venue"
},
  "geometry": {"coordinates":[8.4409208298,47.4366188049],"type":"Point"}
}