{
  "type": "Feature",
  "properties": {
    "iso:country":"CH",
    "sg:address":"7050",
    "sg:city":"Arosa",
    "sg:orig_category":"Reiseb\u00fcros U Reiseveranstalter",
    "sg:postcode":"7050",
    "sg:province":"Graubunden",
    "wof:name":"Doctors Travel Club By Max\u00e9n Lars",
    "wof:placetype":"venue"
},
  "geometry": {"coordinates":[9.6765518188,46.7778625488],"type":"Point"}
}