{
  "type": "Feature",
  "properties": {
    "iso:country":"CH",
    "sg:address":"Birchmattstrasse 25",
    "sg:city":"Seon",
    "sg:orig_category":"Vermittlung von Immobilien",
    "sg:phone":"+41 52 763 17 84",
    "sg:postcode":"5703",
    "sg:province":"Aargau",
    "wof:name":"Max Baumann Liegenschaftenvermittlung",
    "wof:placetype":"venue"
},
  "geometry": {"coordinates":[9.0048332214,47.5971603394],"type":"Point"}
}