{
  "type": "Feature",
  "properties": {
    "iso:country":"CH",
    "sg:address":"B\u00fcrerfeld 2",
    "sg:city":"Oberb\u00fcren",
    "sg:orig_category":"Herstellung von nachrichtentechnischen Ger\u00e4ten U Einrichtungen",
    "sg:phone":"+41 79 697 35 55",
    "sg:postcode":"9245",
    "sg:province":"St. Gallen",
    "wof:name":"G\u00e4mperle Veranstaltungstechnik",
    "wof:placetype":"venue"
},
  "geometry": {"coordinates":[9.1602687836,47.4458503723],"type":"Point"}
}