{
  "type": "Feature",
  "properties": {
    "iso:country":"CH",
    "sg:address":"1700",
    "sg:city":"Fribourg",
    "sg:orig_category":"Schulpflegen",
    "sg:phone":"+41 32 841 18 77",
    "sg:postcode":"1700",
    "sg:province":"Fribourg",
    "wof:name":"Commission Scolaire Du Centre Scolaire Secondaire",
    "wof:placetype":"venue"
},
  "geometry": {"coordinates":[6.8579797745,46.9656105042],"type":"Point"}
}