{
  "type": "Feature",
  "properties": {
    "iso:country":"CH",
    "sg:address":"4224",
    "sg:city":"Nenzlingen",
    "sg:orig_category":"Primarschulen",
    "sg:phone":"+41 61 761 44 58",
    "sg:postcode":"4224",
    "sg:province":"Basel-Landschaft",
    "wof:name":"Primarschule",
    "wof:placetype":"venue"
},
  "geometry": {"coordinates":[7.5619401932,47.4488716125],"type":"Point"}
}