{
  "type": "Feature",
  "properties": {
    "iso:country":"CH",
    "sg:address":"R\u00e4chholderstrasse 46",
    "sg:city":"D\u00fcdingen",
    "sg:orig_category":"Allgemeiner Hoch U Tiefbau Allgemeiner Hochbau",
    "sg:phone":"+41 26 493 27 49",
    "sg:postcode":"3186",
    "sg:province":"Fribourg",
    "wof:name":"Kuriger R. Ag",
    "wof:placetype":"venue"
},
  "geometry": {"coordinates":[7.184166,46.848991],"type":"Point"}
}