{
  "type": "Feature",
  "properties": {
    "iso:country":"CH",
    "sg:address":"Altgass 5",
    "sg:city":"Hitzkirch",
    "sg:orig_category":"Grosshandel mit Eisenwaren sowie Installationsbedarf f\u00fcr Gas, Wasser U Heizung",
    "sg:phone":"+41 41 917 12 52",
    "sg:postcode":"6285",
    "sg:province":"Luzern",
    "wof:name":"Meier Heinrich Eisenhandlung",
    "wof:placetype":"venue"
},
  "geometry": {"coordinates":[8.2635860443,47.2255859375],"type":"Point"}
}