{
  "type": "Feature",
  "properties": {
    "iso:country":"CH",
    "sg:address":"Via Soave 6",
    "sg:city":"Lugano",
    "sg:orig_category":"Aktivit\u00e4t der Bankinstitute",
    "sg:phone":"+41 91 912 69 69",
    "sg:postcode":"6900",
    "sg:province":"Ticino",
    "wof:name":"Lgt Bank In Liechtenstein Ag",
    "wof:placetype":"venue"
},
  "geometry": {"coordinates":[8.950783,46.004467],"type":"Point"}
}