{
  "type": "Feature",
  "properties": {
    "iso:country":"CH",
    "sg:address":"Strada Cantonale 18 Casella Postale 202",
    "sg:city":"Lamone-cadempino",
    "sg:classifiers":[
        {
            "category":"Food Court",
            "type":"Food & Drink"
        }
    ],
    "sg:phone":"+41 91 935 75 45",
    "sg:postcode":"6814",
    "sg:province":"Ticino",
    "sg:tags":[
        "product",
        "related"
    ],
    "wof:name":"Tamborini Carlo Eredi Sa",
    "wof:placetype":"venue"
},
  "geometry": {"coordinates":[8.93151474,46.0453643799],"type":"Point"}
}