{
  "type": "Feature",
  "properties": {
    "iso:country":"CH",
    "sg:address":"Eichfeldstrasse 3 3612 Steffisburg. Postfach",
    "sg:city":"Steffisburg",
    "sg:orig_category":"Reiseb\u00fcros U Reiseveranstalter",
    "sg:phone":"+41 33 437 98 47",
    "sg:postcode":"3612",
    "sg:province":"Bern",
    "wof:name":"Smyrna Reisen Gmbh",
    "wof:placetype":"venue"
},
  "geometry": {"coordinates":[7.6335430145,46.7789039612],"type":"Point"}
}