{
  "type": "Feature",
  "properties": {
    "iso:country":"CH",
    "sg:address":"Vela Via Vincenzo 21",
    "sg:city":"Mendrisio",
    "sg:orig_category":"Filmverleih U Videoprogrammanbieter",
    "sg:phone":"+41 14011819",
    "sg:postcode":"6850",
    "sg:province":"Ticino",
    "wof:name":"M.f.d. Morandini Film Distribution",
    "wof:placetype":"venue"
},
  "geometry": {"coordinates":[8.9864006042,45.8722648621],"type":"Point"}
}