{
  "type": "Feature",
  "properties": {
    "iso:country":"CH",
    "sg:address":"Via Cantonale",
    "sg:city":"Orselina",
    "sg:orig_category":"RESTAURANTS: TEA-ROOMS",
    "sg:postcode":"6644",
    "sg:province":"Ticino",
    "wof:name":"Cavicchiolo Ardolino",
    "wof:placetype":"venue"
},
  "geometry": {"coordinates":[8.7986249924,46.1787261963],"type":"Point"}
}