{
  "type": "Feature",
  "properties": {
    "iso:country":"CH",
    "sg:address":"Viale Papio",
    "sg:city":"Ascona",
    "sg:orig_category":"Detailhandel mit Waren verschiedener Art, Hauptrichtung Nahrungsmittel",
    "sg:phone":"+41 91 791 06 90",
    "sg:postcode":"6612",
    "sg:province":"Ticino",
    "wof:name":"Coop",
    "wof:placetype":"venue"
},
  "geometry": {"coordinates":[8.7708053589,46.15574646],"type":"Point"}
}