{
  "type": "Feature",
  "properties": {
    "iso:country":"CH",
    "sg:address":"Route De Chaulin",
    "sg:city":"Brent",
    "sg:orig_category":"Grosshandel mit Uhren",
    "sg:phone":"+41 21 964 45 22",
    "sg:postcode":"1817",
    "sg:province":"Vaud",
    "wof:name":"Carl A. Wirz Sa Import-export",
    "wof:placetype":"venue"
},
  "geometry": {"coordinates":[6.9011001587,46.4577255249],"type":"Point"}
}