{
  "type": "Feature",
  "properties": {
    "iso:country":"CH",
    "sg:address":"Kaufplatz 7 3930 Visp. Postfach",
    "sg:city":"Visp",
    "sg:orig_category":"Herstellung von sonstigen Metallwaren",
    "sg:phone":"+41 27 946 11 33",
    "sg:postcode":"3930",
    "sg:province":"Valais",
    "wof:name":"Della Bianca Daniel, Zinngiesserei",
    "wof:placetype":"venue"
},
  "geometry": {"coordinates":[7.8814911842,46.2907981873],"type":"Point"}
}