{
  "type": "Feature",
  "properties": {
    "iso:country":"CH",
    "sg:address":"Hauptstrasse 192",
    "sg:city":"Herbetswil",
    "sg:orig_category":"Herstellung von Uhren",
    "sg:postcode":"4715",
    "sg:province":"Solothurn",
    "wof:name":"Galvado Ag",
    "wof:placetype":"venue"
},
  "geometry": {"coordinates":[7.5928587914,47.2937469482],"type":"Point"}
}