{
  "type": "Feature",
  "properties": {
    "iso:country":"CH",
    "sg:address":"Reverdil Avenue 14",
    "sg:city":"Nyon",
    "sg:orig_category":"Dienstleistungen von Beteiligungsgesellschaften",
    "sg:phone":"+41 22 994 28 80",
    "sg:postcode":"1260",
    "sg:province":"Vaud",
    "wof:name":"Diy Tech Ltd, Tortola, British Virgin Islands, Succursale De Nyon",
    "wof:placetype":"venue"
},
  "geometry": {"coordinates":[6.2321338654,46.3808479309],"type":"Point"}
}