{
  "type": "Feature",
  "properties": {
    "addr:full":"Industriestrasse Maienfeld Graubunden 7304",
    "addr:postcode":"7304",
    "addr:street":"Industriestrasse;Graubunden",
    "iso:country":"CH",
    "sg:address":"Industriestrasse",
    "sg:city":"Maienfeld",
    "sg:orig_category":"Allgemeiner Hoch U Tiefbau",
    "sg:phone":"+41 21 922 72 69",
    "sg:postcode":"7304",
    "sg:province":"Graubunden",
    "wof:name":"Karok S\u00e0rl",
    "wof:placetype":"venue"
},
  "geometry": {"coordinates":[5.18087,45.897339],"type":"Point"}
}