{
  "type": "Feature",
  "properties": {
    "iso:country":"CH",
    "sg:address":"Amsler-laffon-strasse 9",
    "sg:city":"Schaffhausen",
    "sg:orig_category":"Unternehmensberatung",
    "sg:postcode":"8200",
    "sg:province":"Schaffhausen",
    "wof:name":"Jubil\u00e4umsstiftung Fischer Georg",
    "wof:placetype":"venue"
},
  "geometry": {"coordinates":[8.64407444,47.7082977295],"type":"Point"}
}