{
  "type": "Feature",
  "properties": {
    "iso:country":"CH",
    "sg:address":"Oslo-strasse 1 4142 M\u00fcnchenstein. Postfach",
    "sg:city":"M\u00fcnchenstein",
    "sg:orig_category":"Finanzierungsinstitutionen Logistikberatung",
    "sg:phone":"+41 61 333 17 77",
    "sg:postcode":"4142",
    "sg:province":"Basel-Landschaft",
    "wof:name":"Proserve Logistics Gmbh Dienstl. Im Finanz, Logistikbereich Usw",
    "wof:placetype":"venue"
},
  "geometry": {"coordinates":[7.6098217964,47.5342903137],"type":"Point"}
}