{
  "type": "Feature",
  "properties": {
    "iso:country":"CH",
    "sg:address":"Bethlehemstrasse 105",
    "sg:city":"Bern",
    "sg:orig_category":"Detailhandel mit Waren verschiedener Art, Hauptrichtung Nahrungsmittel",
    "sg:phone":"+41 31 992 01 12",
    "sg:postcode":"3018",
    "sg:province":"Bern",
    "wof:name":"Coop Meienegg",
    "wof:placetype":"venue"
},
  "geometry": {"coordinates":[7.3997101784,46.9443359375],"type":"Point"}
}