{
  "type": "Feature",
  "properties": {
    "iso:country":"CH",
    "sg:address":"Fin-de-la-croix Route 1",
    "sg:city":"Givisiez",
    "sg:orig_category":"Stukkateurgewerbe, Gipserei U Verputzerei",
    "sg:phone":"+41 79 436 52 03",
    "sg:postcode":"1762",
    "sg:province":"Fribourg",
    "wof:name":"Entreprise De Peinture, Kolly & Neuhaus",
    "wof:placetype":"venue"
},
  "geometry": {"coordinates":[7.1326379776,46.8146743774],"type":"Point"}
}