{
  "type": "Feature",
  "properties": {
    "iso:country":"CH",
    "sg:address":"Sainte-c\u00e9cile Avenue 7",
    "sg:city":"Meyrin",
    "sg:orig_category":"RESTAURANTS: TEA-ROOMS",
    "sg:postcode":"1217",
    "sg:province":"Gen\u00e8ve",
    "wof:name":"Fasila Servir S\u00e0rl",
    "wof:placetype":"venue"
},
  "geometry": {"coordinates":[6.0845890045,46.2340202332],"type":"Point"}
}