{
  "type": "Feature",
  "properties": {
    "iso:country":"CH",
    "sg:address":"Chemin De Nant 4",
    "sg:city":"Jongny",
    "sg:orig_category":"Grosshandel mit Eisenwaren sowie Installationsbedarf f\u00fcr Gas, Wasser U Heizung Herstellung von Heizk",
    "sg:phone":"+41 21 921 64 73",
    "sg:postcode":"1805",
    "sg:province":"Vaud",
    "wof:name":"Ren\u00e9 Selinger Syst\u00e8mes Et Mat. De Chauffages",
    "wof:placetype":"venue"
},
  "geometry": {"coordinates":[6.8470277786,46.4798126221],"type":"Point"}
}