{
  "type": "Feature",
  "properties": {
    "iso:country":"CH",
    "sg:address":"Witikonerstrasse 264",
    "sg:city":"Z\u00fcrich",
    "sg:orig_category":"Herstellung von Lederbekleidung",
    "sg:postcode":"8053",
    "sg:province":"Z\u00fcrich",
    "wof:name":"Hotskin + Plastic, Prcin + Schlegel",
    "wof:placetype":"venue"
},
  "geometry": {"coordinates":[8.5842466354,47.3582191467],"type":"Point"}
}