{
  "type": "Feature",
  "properties": {
    "iso:country":"CH",
    "sg:address":"Im Gartenfl\u00fcgel 8866 Ziegelbr\u00fccke. Postfach",
    "sg:city":"Ziegelbr\u00fccke",
    "sg:orig_category":"Interessenvertretungen",
    "sg:phone":"+41 55 610 16 13",
    "sg:postcode":"8866",
    "sg:province":"Glarus",
    "wof:name":"Stiftung Gartenfl\u00fcgel",
    "wof:placetype":"venue"
},
  "geometry": {"coordinates":[9.067150116,47.1351509094],"type":"Point"}
}