{
  "type": "Feature",
  "properties": {
    "iso:country":"CH",
    "sg:address":"Mathilde Paravicini-strasse 9 4052 Basel. Postfach",
    "sg:city":"Basel",
    "sg:orig_category":"Wirtschaftspr\u00fcfung, Steuerberatung U Treuhand",
    "sg:phone":"+41 61 311 20 00",
    "sg:postcode":"4020",
    "sg:province":"Basel-Stadt",
    "wof:name":"Treuhand F\u00fcr Senioren Henseler Ag",
    "wof:placetype":"venue"
},
  "geometry": {"coordinates":[7.6041221619,47.5487174988],"type":"Point"}
}