{
  "type": "Feature",
  "properties": {
    "iso:country":"CH",
    "sg:address":"Lindenheimweg 1",
    "sg:city":"Emmen",
    "sg:orig_category":"Handel mit Automobilteilen U Zubeh\u00f6r Handelsvermittlung U Grosshandel mit Automobilteilen U Zubeh\u00f6r",
    "sg:phone":"+41 41 268 80 40",
    "sg:postcode":"6032",
    "sg:province":"Luzern",
    "wof:name":"B & S Automobiltechnik Ag",
    "wof:placetype":"venue"
},
  "geometry": {"coordinates":[8.2921533585,47.0762825012],"type":"Point"}
}