{
  "type": "Feature",
  "properties": {
    "iso:country":"CH",
    "sg:address":"Weiherweg 3",
    "sg:city":"Oberwil",
    "sg:classifiers":[
        {
            "category":"Professional",
            "subcategory":"Computer Services",
            "type":"Services"
        }
    ],
    "sg:phone":"+41 61 403 19 00",
    "sg:postcode":"4104",
    "sg:province":"Basel-Landschaft",
    "sg:tags":[
        "development",
        "software"
    ],
    "wof:name":"Assist Ag",
    "wof:placetype":"venue"
},
  "geometry": {"coordinates":[7.558839798,47.5137062073],"type":"Point"}
}