{
  "type": "Feature",
  "properties": {
    "iso:country":"CH",
    "sg:address":"En Felezin",
    "sg:city":"Romanel-s-lausanne",
    "sg:orig_category":"Detailhandel mit Waren verschiedener Art, Hauptrichtung Nahrungsmittel",
    "sg:phone":"+41 21 646 13 31",
    "sg:postcode":"1032",
    "sg:province":"Vaud",
    "wof:name":"Migros Vaud",
    "wof:placetype":"venue"
},
  "geometry": {"coordinates":[6.6112809181,46.5597114563],"type":"Point"}
}