{
  "type": "Feature",
  "properties": {
    "iso:country":"CH",
    "sg:address":"Industriestrasse",
    "sg:city":"Inwil",
    "sg:orig_category":"Herstellung von Metallkonstruktionen Stahl U Leichtmetallbau",
    "sg:phone":"+41 41 448 25 65",
    "sg:postcode":"6034",
    "sg:province":"Luzern",
    "wof:name":"Mebal Ag",
    "wof:placetype":"venue"
},
  "geometry": {"coordinates":[8.3493375778,47.1181678772],"type":"Point"}
}