{
  "type": "Feature",
  "properties": {
    "iso:country":"CH",
    "sg:address":"5512",
    "sg:city":"Wohlenschwil",
    "sg:orig_category":"Primarschulen",
    "sg:postcode":"5512",
    "sg:province":"Aargau",
    "wof:name":"Primarschule",
    "wof:placetype":"venue"
},
  "geometry": {"coordinates":[8.2549600601,47.4160804749],"type":"Point"}
}