{
  "type": "Feature",
  "properties": {
    "iso:country":"CH",
    "sg:address":"De-luserna Avenue 13 1203 Gen\u00e8ve Case Postale 2226",
    "sg:city":"Gen\u00e8ve",
    "sg:orig_category":"Elektroinstallation",
    "sg:phone":"+41 22 345 77 20",
    "sg:postcode":"1203",
    "sg:province":"Gen\u00e8ve",
    "wof:name":"Cauderay Electrotecnic Cit\u00e9 Sa",
    "wof:placetype":"venue"
},
  "geometry": {"coordinates":[6.1261739731,46.2128105164],"type":"Point"}
}