{
  "type": "Feature",
  "properties": {
    "iso:country":"CH",
    "sg:address":"Dorf 44",
    "sg:city":"Peterzell",
    "sg:orig_category":"G\u00fcterbef\u00f6rderung im Strassenverkehr Reiseb\u00fcros U Reiseveranstalter",
    "sg:phone":"+41 71 377 11 66",
    "sg:postcode":"9127",
    "sg:province":"St. Gallen",
    "wof:name":"B\u00f6sch Hermann Ag",
    "wof:placetype":"venue"
},
  "geometry": {"coordinates":[8.4667129517,48.3240394592],"type":"Point"}
}