{
  "type": "Feature",
  "properties": {
    "iso:country":"CH",
    "sg:address":"Schachen",
    "sg:city":"Buchrain",
    "sg:orig_category":"Abwasserreinigung, Abfallbeseitigung U sonstige Entsorgung Grosshandel mit chemischen Erzeugnissen",
    "sg:phone":"+41 41 240 00 61",
    "sg:postcode":"6033",
    "sg:province":"Luzern",
    "wof:name":"Ebiox Ag",
    "wof:placetype":"venue"
},
  "geometry": {"coordinates":[8.286808,47.054344],"type":"Point"}
}