{
  "type": "Feature",
  "properties": {
    "iso:country":"CH",
    "sg:address":"Obere Wart 8",
    "sg:city":"Thun",
    "sg:orig_category":"Fotografische Ateliers Korrespondenz U Nachrichtenb\u00fcros",
    "sg:phone":"+41 26 670 10 40",
    "sg:postcode":"3600",
    "sg:province":"Bern",
    "wof:name":"Siegfried Kuhn Pressefotograf",
    "wof:placetype":"venue"
},
  "geometry": {"coordinates":[7.1084527969,46.9252319336],"type":"Point"}
}