{
  "type": "Feature",
  "properties": {
    "iso:country":"CH",
    "sg:address":"Lindenstrasse 2",
    "sg:city":"Orpund",
    "sg:orig_category":"Herstellung von elektrischen Lampen U Leuchten",
    "sg:postcode":"2552",
    "sg:province":"Bern",
    "wof:name":"High-light Boder",
    "wof:placetype":"venue"
},
  "geometry": {"coordinates":[7.3082299232,47.1389122009],"type":"Point"}
}