{
  "type": "Feature",
  "properties": {
    "iso:country":"CH",
    "sg:address":"In Der Breiti 13",
    "sg:city":"Z\u00fcrich",
    "sg:orig_category":"Fahrschulen, Flugschulen",
    "sg:phone":"+41 14913130",
    "sg:postcode":"8047",
    "sg:province":"Z\u00fcrich",
    "wof:name":"Frieda Hanselmann Autofahrschule",
    "wof:placetype":"venue"
},
  "geometry": {"coordinates":[8.4847097397,47.3775558472],"type":"Point"}
}