{
  "type": "Feature",
  "properties": {
    "iso:country":"CH",
    "sg:address":"Bahnhofplatz 13 2500 Biel/bienne. Postfach",
    "sg:city":"Biel/bienne",
    "sg:orig_category":"Gesundheitswesen",
    "sg:postcode":"2502",
    "sg:province":"Bern",
    "wof:name":"Massage - Therapie Barbara Peko Sport- U. Klassische-massagetherapie",
    "wof:placetype":"venue"
},
  "geometry": {"coordinates":[7.3941378593,46.9489555359],"type":"Point"}
}