{
  "type": "Feature",
  "properties": {
    "iso:country":"CH",
    "sg:address":"Gerichtshausstrasse 14",
    "sg:city":"Glarus",
    "sg:orig_category":"P\u00e9dicure",
    "sg:phone":"+41 55 650 13 00",
    "sg:postcode":"8750",
    "sg:province":"Glarus",
    "wof:name":"Margrith Eichenberger Fusspflege",
    "wof:placetype":"venue"
},
  "geometry": {"coordinates":[9.0678367615,47.0420608521],"type":"Point"}
}