{
  "type": "Feature",
  "properties": {
    "iso:country":"CH",
    "sg:address":"Les Mazots-de-gryon",
    "sg:city":"Gryon",
    "sg:orig_category":"Schiffsbau ohne Boots U Yachtbau",
    "sg:phone":"+41 24 498 00 68",
    "sg:postcode":"1882",
    "sg:province":"Vaud",
    "wof:name":"Kasha Maritime Sa",
    "wof:placetype":"venue"
},
  "geometry": {"coordinates":[7.0617899895,46.2738685608],"type":"Point"}
}