{
  "type": "Feature",
  "properties": {
    "iso:country":"CH",
    "sg:address":"En Mont\u00e9vaux",
    "sg:city":"Farvagny",
    "sg:orig_category":"Malerei",
    "sg:phone":"+41 18410185",
    "sg:postcode":"1726",
    "sg:province":"Fribourg",
    "wof:name":"Michel Zwald Malergesch\u00e4ft",
    "wof:placetype":"venue"
},
  "geometry": {"coordinates":[8.4650964737,47.453754425],"type":"Point"}
}