{
  "type": "Feature",
  "properties": {
    "iso:country":"CH",
    "sg:address":"1747",
    "sg:city":"Corserey",
    "sg:orig_category":"Kaminfeger",
    "sg:phone":"+41 26 470 14 58",
    "sg:postcode":"1747",
    "sg:province":"Fribourg",
    "wof:name":"Jean-marc B\u00e4chler Maitre Ramoneur",
    "wof:placetype":"venue"
},
  "geometry": {"coordinates":[6.9889202118,46.7712287903],"type":"Point"}
}