{
  "type": "Feature",
  "properties": {
    "iso:country":"CH",
    "sg:address":"Eschenring 5 6300 Zug. Postfach",
    "sg:city":"Zug",
    "sg:orig_category":"Vermietung U Verpachtung von eigenen Immobilien",
    "sg:postcode":"6300",
    "sg:province":"Zug",
    "wof:name":"Hs Projekt Consulting Ag Immobilien, Kapital; Vermittlung. Finanzprodukte; Vertrieb",
    "wof:placetype":"venue"
},
  "geometry": {"coordinates":[8.5180444717,47.1818389893],"type":"Point"}
}