{
  "type": "Feature",
  "properties": {
    "iso:country":"CH",
    "sg:address":"Hulfteggstrasse 39",
    "sg:city":"Winterthur",
    "sg:orig_category":"Erschliessung von Grundst\u00fccken",
    "sg:phone":"+41 52 232 39 25",
    "sg:postcode":"8400",
    "sg:province":"Z\u00fcrich",
    "wof:name":"Baugen.sunnigi Heimet",
    "wof:placetype":"venue"
},
  "geometry": {"coordinates":[8.7536411285,47.4927978516],"type":"Point"}
}