{
  "type": "Feature",
  "properties": {
    "iso:country":"CH",
    "sg:address":"M\u00fchlestrasse 6 5702 Niederlenz. Postfach 62",
    "sg:city":"Niederlenz",
    "sg:orig_category":"Druck ohne Zeitungsdruck Offsetdruck",
    "sg:phone":"+41 56 463 61 11",
    "sg:postcode":"5702",
    "sg:province":"Aargau",
    "wof:name":"Lerchm\u00fcller Ag Forms & Labels",
    "wof:placetype":"venue"
},
  "geometry": {"coordinates":[8.1428003311,47.4453468323],"type":"Point"}
}