{
  "type": "Feature",
  "properties": {
    "iso:country":"CH",
    "sg:address":"Scheideggstrasse 6",
    "sg:city":"Winterthur",
    "sg:orig_category":"Wein Detailhandel",
    "sg:phone":"+41 52 238 27 36",
    "sg:postcode":"8400",
    "sg:province":"Z\u00fcrich",
    "wof:name":"Giorgio Lurati Weinkiste St. Jakob",
    "wof:placetype":"venue"
},
  "geometry": {"coordinates":[8.7497158051,47.4914245605],"type":"Point"}
}