{
  "type": "Feature",
  "properties": {
    "iso:country":"CH",
    "sg:address":"Bielstrasse 77 4500 Solothurn. Postfach 122",
    "sg:city":"Solothurn",
    "sg:orig_category":"Erbringung von sonstigen Dienstleistungen f\u00fcr Unterhaltung, Erholung U Freizeit",
    "sg:phone":"+41 32 622 73 04",
    "sg:postcode":"4500",
    "sg:province":"Solothurn",
    "wof:name":"Entertainment Consulting Baumann",
    "wof:placetype":"venue"
},
  "geometry": {"coordinates":[7.5251960754,47.2111473083],"type":"Point"}
}