{
  "type": "Feature",
  "properties": {
    "addr:full":"Froschaugasse 7 Z\u00fcrich Z\u00fcrich 8001",
    "addr:housenumber":"7",
    "addr:postcode":"8001",
    "addr:street":"Froschaugasse",
    "iso:country":"CH",
    "sg:address":"Froschaugasse 7",
    "sg:city":"Z\u00fcrich",
    "sg:orig_category":"Detailhandel mit B\u00fcchern Detailhandel mit B\u00fcchern, Zeitungen, Schreib U Papeteriewaren",
    "sg:phone":"+41 12532222",
    "sg:postcode":"8001",
    "sg:province":"Z\u00fcrich",
    "wof:name":"Comics-shop Keller",
    "wof:placetype":"venue"
},
  "geometry": {"coordinates":[8.545002,47.37286],"type":"Point"}
}