{
  "type": "Feature",
  "properties": {
    "iso:country":"CH",
    "sg:address":"Route De Chantemerle 58 1763 Granges-paccot. Postfach",
    "sg:city":"Granges-paccot",
    "sg:orig_category":"Non-Classified Establishments",
    "sg:postcode":"1763",
    "sg:province":"Fribourg",
    "wof:name":"Sw Technology Holding Sa",
    "wof:placetype":"venue"
},
  "geometry": {"coordinates":[7.140182972,46.820224762],"type":"Point"}
}