{
  "type": "Feature",
  "properties": {
    "iso:country":"CH",
    "sg:address":"Pr\u00e9a 6992 Vernate. Postfach",
    "sg:city":"Vernate",
    "sg:orig_category":"Werbung",
    "sg:postcode":"6992",
    "sg:province":"Ticino",
    "wof:name":"Artcake K\u00fcste H. Pubblicit\u00e0",
    "wof:placetype":"venue"
},
  "geometry": {"coordinates":[8.8831157684,45.9932594299],"type":"Point"}
}