{
  "type": "Feature",
  "properties": {
    "iso:country":"CH",
    "sg:address":"R\u00fcmikerstrasse 5a",
    "sg:city":"R\u00e4terschen",
    "sg:orig_category":"Betrieb von Sportanlagen",
    "sg:phone":"+41 52 366 08 08",
    "sg:postcode":"8352",
    "sg:province":"Z\u00fcrich",
    "wof:name":"Beseco Gmbh",
    "wof:placetype":"venue"
},
  "geometry": {"coordinates":[8.78409,47.50388],"type":"Point"}
}