{
  "type": "Feature",
  "properties": {
    "iso:country":"CH",
    "sg:address":"Lac-de-br\u00eat Chemin Du",
    "sg:city":"Puidoux",
    "sg:orig_category":"RESTAURANTS: TEA-ROOMS",
    "sg:phone":"+41 24 492 34 81",
    "sg:postcode":"1070",
    "sg:province":"Vaud",
    "wof:name":"Jrg S\u00e0rl",
    "wof:placetype":"venue"
},
  "geometry": {"coordinates":[7.1587119102,46.3500404358],"type":"Point"}
}