{
  "type": "Feature",
  "properties": {
    "addr:full":"Rue Du Rh\u00f4ne 12 1950 Sitten. Postfach Sion Valais 1951",
    "addr:housenumber":"12",
    "addr:postcode":"1950 sitten. postfach;1951",
    "addr:street":"Rue Du Rho\u0302Ne",
    "iso:country":"CH",
    "sg:address":"Rue Du Rh\u00f4ne 12 1950 Sitten. Postfach",
    "sg:city":"Sion",
    "sg:orig_category":"Allgemeiner Hoch U Tiefbau",
    "sg:postcode":"1951",
    "sg:province":"Valais",
    "wof:name":"Sovalco, Jacquod & Aymon",
    "wof:placetype":"venue"
},
  "geometry": {"coordinates":[7.360897,46.232689],"type":"Point"}
}