{
  "type": "Feature",
  "properties": {
    "iso:country":"CH",
    "sg:address":"1638",
    "sg:city":"Morlon",
    "sg:orig_category":"Gemeindeverwaltungen",
    "sg:phone":"+41 21 731 24 47",
    "sg:postcode":"1638",
    "sg:province":"Fribourg",
    "wof:name":"Administration Communale De Morrens",
    "wof:placetype":"venue"
},
  "geometry": {"coordinates":[6.6260838509,46.5913772583],"type":"Point"}
}