{
  "type": "Feature",
  "properties": {
    "iso:country":"CH",
    "sg:address":"Gotthardstr. 51 6415 Arth. Postfach",
    "sg:city":"Goldau",
    "sg:orig_category":"Herstellung von Schmuck, Gold U Silberschmiedwaren",
    "sg:phone":"+41 41 855 51 70",
    "sg:postcode":"6410",
    "sg:province":"Schwyz",
    "wof:name":"Susi's Goldstudio, Willimann Susi",
    "wof:placetype":"venue"
},
  "geometry": {"coordinates":[8.5259132385,47.0613288879],"type":"Point"}
}