{
  "type": "Feature",
  "properties": {
    "iso:country":"CH",
    "sg:address":"Croix Rue De La 32",
    "sg:city":"Bassecourt",
    "sg:orig_category":"Hardwareberatung",
    "sg:phone":"+41 32 426 66 76",
    "sg:postcode":"2854",
    "sg:province":"Jura",
    "wof:name":"Froment Jacques, Megaccossoires-computer",
    "wof:placetype":"venue"
},
  "geometry": {"coordinates":[7.2450351715,47.3370552063],"type":"Point"}
}