{
  "type": "Feature",
  "properties": {
    "iso:country":"CH",
    "sg:address":"Platanenweg 5 8555 M\u00fcllheim Dorf. Postfach",
    "sg:city":"M\u00fcllheim-wigoltgn",
    "sg:orig_category":"Sonstiges Versicherungsgewerbe",
    "sg:postcode":"8554",
    "sg:province":"Thurgau",
    "wof:name":"Yabloko, Epple Erich",
    "wof:placetype":"venue"
},
  "geometry": {"coordinates":[8.9939899445,47.5974731445],"type":"Point"}
}