{
  "type": "Feature",
  "properties": {
    "iso:country":"CH",
    "sg:address":"Buristrasse 8 3000 Bern. Postfach",
    "sg:city":"Bern",
    "sg:orig_category":"Sonstige Kurierdienste",
    "sg:postcode":"3005",
    "sg:province":"Bern",
    "wof:name":"Gourmet Express Aliu",
    "wof:placetype":"venue"
},
  "geometry": {"coordinates":[7.4745001793,46.9453163147],"type":"Point"}
}