{
  "type": "Feature",
  "properties": {
    "iso:country":"CH",
    "sg:address":"Br\u00fcnigstrasse 109",
    "sg:city":"Sachseln",
    "sg:orig_category":"Physiotherapie",
    "sg:phone":"+41 41 661 01 77",
    "sg:postcode":"6072",
    "sg:province":"Obwalden",
    "wof:name":"Dagmar Hirner Physiotherapie",
    "wof:placetype":"venue"
},
  "geometry": {"coordinates":[8.2376031876,46.8680877686],"type":"Point"}
}