{
  "type": "Feature",
  "properties": {
    "iso:country":"CH",
    "sg:address":"Rundstrasse 36",
    "sg:city":"Winterthur",
    "sg:orig_category":"Allgemeiner Hoch U Tiefbau",
    "sg:phone":"+41 52 212 44 23",
    "sg:postcode":"8400",
    "sg:province":"Z\u00fcrich",
    "wof:name":"Zingg Consultants Ag",
    "wof:placetype":"venue"
},
  "geometry": {"coordinates":[8.722391,47.506298],"type":"Point"}
}