{
  "type": "Feature",
  "properties": {
    "iso:country":"CH",
    "sg:address":"Petits Champs Rue Des",
    "sg:city":"Yverdon-les-bains",
    "sg:orig_category":"Oberfl\u00e4chenveredlung U W\u00e4rmebehandlung",
    "sg:phone":"+41 24 425 63 19",
    "sg:postcode":"1400",
    "sg:province":"Vaud",
    "wof:name":"Wegm\u00fcller E. Sa",
    "wof:placetype":"venue"
},
  "geometry": {"coordinates":[6.6421508789,46.7595901489],"type":"Point"}
}