{
  "type": "Feature",
  "properties": {
    "iso:country":"CH",
    "sg:address":"Ringstrasse 7",
    "sg:city":"Neuenhof",
    "sg:orig_category":"Elektroinstallation Herstellung von Elektrizit\u00e4tsverteilungs U schalteinrichtungen",
    "sg:phone":"+41 56 406 15 67",
    "sg:postcode":"5432",
    "sg:province":"Aargau",
    "wof:name":"Almi-elektrobau Ag",
    "wof:placetype":"venue"
},
  "geometry": {"coordinates":[8.328207016,47.4540786743],"type":"Point"}
}