{
  "type": "Feature",
  "properties": {
    "iso:country":"CH",
    "sg:address":"Mattenhofstrasse 10",
    "sg:city":"Bern",
    "sg:orig_category":"Markt U Meinungsforschung",
    "sg:postcode":"3007",
    "sg:province":"Bern",
    "wof:name":"L\u00fcthi Marc Marketing + Medien",
    "wof:placetype":"venue"
},
  "geometry": {"coordinates":[7.4319119453,46.9429130554],"type":"Point"}
}