{
  "type": "Feature",
  "properties": {
    "addr:full":"3917 Kippel Valais 3917",
    "addr:postcode":"3917;3917",
    "iso:country":"CH",
    "sg:address":"3917",
    "sg:city":"Kippel",
    "sg:classifiers":[
        {
            "category":"Social Services",
            "subcategory":"Retirement Home",
            "type":"Services"
        }
    ],
    "sg:phone":"+41 41 979 11 49",
    "sg:postcode":"3917",
    "sg:province":"Valais",
    "sg:tags":[
        "pflegeheime",
        "u",
        "alters"
    ],
    "wof:name":"Altersheim St.johann",
    "wof:placetype":"venue"
},
  "geometry": {"coordinates":[7.96201,47.119591],"type":"Point"}
}