{
  "type": "Feature",
  "properties": {
    "addr:full":"Gartenstrasse 7 4552 Derendingen. Postfach Derendingen Solothurn 4552",
    "addr:housenumber":"7",
    "addr:postcode":"4552 derendingen. postfach;4552",
    "addr:street":"Gartenstrasse",
    "iso:country":"CH",
    "sg:address":"Gartenstrasse 7 4552 Derendingen. Postfach",
    "sg:city":"Derendingen",
    "sg:orig_category":"Architekturb\u00fcros RESTAURANTS: TEA-ROOMS",
    "sg:phone":"+41 32 682 24 37",
    "sg:postcode":"4552",
    "sg:province":"Solothurn",
    "wof:name":"Stuber Rudolf",
    "wof:placetype":"venue"
},
  "geometry": {"coordinates":[7.583364,47.198757],"type":"Point"}
}