{
  "type": "Feature",
  "properties": {
    "iso:country":"CH",
    "sg:address":"T\u00f6distrasse 63 8002 Z\u00fcrich. Postfach",
    "sg:city":"Z\u00fcrich",
    "sg:orig_category":"Verm\u00f6gensverwaltung",
    "sg:phone":"+41 12099900",
    "sg:postcode":"8039",
    "wof:name":"Atag Asset Management Ag",
    "wof:placetype":"venue"
},
  "geometry": {"coordinates":[8.5327959061,47.3685150146],"type":"Point"}
}