{
  "type": "Feature",
  "properties": {
    "iso:country":"CH",
    "sg:address":"Lehngasse 72",
    "sg:city":"Wilderswil",
    "sg:orig_category":"RESTAURANTS: TEA-ROOMS",
    "sg:phone":"+41 31 781 17 58",
    "sg:postcode":"3812",
    "sg:province":"Bern",
    "wof:name":"Nelly Zysset-b\u00fchlmann",
    "wof:placetype":"venue"
},
  "geometry": {"coordinates":[7.5464158058,46.8056945801],"type":"Point"}
}