{
  "type": "Feature",
  "properties": {
    "iso:country":"CH",
    "sg:address":"Rhonesandstrasse 13",
    "sg:city":"Brig",
    "sg:orig_category":"Detailhandel mit Brillen U anderen Sehhilfen Detailhandel mit medizinischen U orthop\u00e4dischen Artikel",
    "sg:phone":"+41 27 923 36 56",
    "sg:postcode":"3900",
    "sg:province":"Valais",
    "wof:name":"Oberholzer K\u00e4thi Imesch, H\u00f6rakustikerin, Maico H\u00f6rger\u00e4te",
    "wof:placetype":"venue"
},
  "geometry": {"coordinates":[7.989634,46.317848],"type":"Point"}
}