{
  "type": "Feature",
  "properties": {
    "iso:country":"CH",
    "sg:address":"Schulstrasse 20",
    "sg:city":"M\u00e4nnedorf",
    "sg:orig_category":"Primarschulen",
    "sg:phone":"+41 19200170",
    "sg:postcode":"8708",
    "sg:province":"Z\u00fcrich",
    "wof:name":"Primarschule",
    "wof:placetype":"venue"
},
  "geometry": {"coordinates":[8.6960926056,47.2539215088],"type":"Point"}
}