{
  "type": "Feature",
  "properties": {
    "iso:country":"CH",
    "sg:address":"Othmarsingerstrasse 3",
    "sg:city":"Dottikon",
    "sg:orig_category":"Non-Classified Establishments",
    "sg:phone":"+41 56 610 15 88",
    "sg:postcode":"5605",
    "sg:province":"Aargau",
    "wof:name":"Smc Schwab Mediaconsulting",
    "wof:placetype":"venue"
},
  "geometry": {"coordinates":[8.2404499054,47.3844337463],"type":"Point"}
}