{
  "type": "Feature",
  "properties": {
    "iso:country":"CH",
    "sg:address":"Herblingerstrasse 54",
    "sg:city":"Schaffhausen",
    "sg:orig_category":"Unclassifiable Establishments",
    "sg:phone":"+41 43 888 08 08",
    "sg:postcode":"8207",
    "sg:province":"Schaffhausen",
    "wof:name":"Davidshofer Trading",
    "wof:placetype":"venue"
},
  "geometry": {"coordinates":[8.7341480255,47.1973953247],"type":"Point"}
}