{
  "type": "Feature",
  "properties": {
    "addr:full":"Weidstrasse 28 Wegenstetten Aargau 4317",
    "addr:housenumber":"28",
    "addr:postcode":"4317",
    "addr:street":"Weidstrasse",
    "iso:country":"CH",
    "sg:address":"Weidstrasse 28",
    "sg:city":"Wegenstetten",
    "sg:orig_category":"Bauschreinerei Herstellung von Konstruktionsteilen, Fertigbauteilen U Ausbauelementen aus Holz",
    "sg:phone":"+41 61 871 00 58",
    "sg:postcode":"4317",
    "sg:province":"Aargau",
    "wof:name":"M\u00fcller Peter, Schreinerei",
    "wof:placetype":"venue"
},
  "geometry": {"coordinates":[7.925602,47.494072],"type":"Point"}
}