{
  "type": "Feature",
  "properties": {
    "iso:country":"CH",
    "sg:address":"Landenbergstrasse 35 6005 Luzern. Postfach",
    "sg:city":"Luzern",
    "sg:orig_category":"Pensionskassen",
    "sg:postcode":"6005",
    "sg:province":"Luzern",
    "wof:name":"Patronaler Vorsorgefonds Der Sch\u00e4tzle-betriebe",
    "wof:placetype":"venue"
},
  "geometry": {"coordinates":[8.3165903091,47.0457954407],"type":"Point"}
}