{
  "type": "Feature",
  "properties": {
    "iso:country":"CH",
    "sg:address":"Rainstrasse 20",
    "sg:city":"Grenchen",
    "sg:orig_category":"Grosshandel mit Textilien",
    "sg:postcode":"2540",
    "sg:province":"Solothurn",
    "wof:name":"Schneider Mode & Co",
    "wof:placetype":"venue"
},
  "geometry": {"coordinates":[7.4122600555,47.1956748962],"type":"Point"}
}