{
  "type": "Feature",
  "properties": {
    "iso:country":"CH",
    "sg:address":"Einschlagweg 67",
    "sg:city":"Burgdorf",
    "sg:orig_category":"D\u00e4mmung gegen K\u00e4lte, W\u00e4rme, Schall U Ersch\u00fctterung Zimmerei, Dachdeckerei, Bauspenglerei U Abdichtun",
    "sg:phone":"+41 32 730 50 50",
    "sg:postcode":"3400",
    "sg:province":"Bern",
    "wof:name":"Setimac Gilbert Bernasconi Sa Asphaltage & \u00e9tanch\u00e9it\u00e9",
    "wof:placetype":"venue"
},
  "geometry": {"coordinates":[6.8307452202,47.0933380127],"type":"Point"}
}