{
  "type": "Feature",
  "properties": {
    "addr:full":"Bossi\u00e8re Route De La 14 Prangins Vaud 1197",
    "addr:housenumber":"14",
    "addr:postcode":"1197",
    "addr:street":"Route De La",
    "iso:country":"CH",
    "sg:address":"Bossi\u00e8re Route De La 14",
    "sg:city":"Prangins",
    "sg:orig_category":"Architektur U Ingenieurb\u00fcros",
    "sg:postcode":"1197",
    "sg:province":"Vaud",
    "wof:name":"Niculescu A. Et D. Sa",
    "wof:placetype":"venue"
},
  "geometry": {"coordinates":[6.249,46.394325],"type":"Point"}
}