{
  "type": "Feature",
  "properties": {
    "iso:country":"CH",
    "sg:address":"Oberkaien 1",
    "sg:city":"Rehetobel",
    "sg:orig_category":"Handel mit Automobilen",
    "sg:phone":"+41 71 877 13 14",
    "sg:postcode":"9038",
    "sg:province":"Appenzell Ausserrhoden",
    "wof:name":"As-automobile Schneider A.",
    "wof:placetype":"venue"
},
  "geometry": {"coordinates":[9.4952230453,47.429599762],"type":"Point"}
}