{
  "type": "Feature",
  "properties": {
    "iso:country":"CH",
    "sg:address":"Schaffhauserstrasse 130",
    "sg:city":"Kloten",
    "sg:orig_category":"Wirtschafts- and Arbeitgeberverb\u00e4nde",
    "sg:phone":"+41 18007766",
    "sg:postcode":"8302",
    "sg:province":"Z\u00fcrich",
    "wof:name":"Vereinigung Z\u00fcrcher Reiseb\u00fcro C/o Passage Reisen Ag",
    "wof:placetype":"venue"
},
  "geometry": {"coordinates":[8.5808696747,47.4516792297],"type":"Point"}
}