{
  "type": "Feature",
  "properties": {
    "iso:country":"CH",
    "sg:address":"Lausanne Rue De 57 1700 Fribourg. Postfach",
    "sg:city":"Fribourg",
    "sg:orig_category":"Herstellung von W\u00e4sche",
    "sg:postcode":"1700",
    "sg:province":"Fribourg",
    "wof:name":"Gavroche Krattinger-ecoffey Myriam Magasin De Mode Enfantine",
    "wof:placetype":"venue"
},
  "geometry": {"coordinates":[7.1582508087,46.8056907654],"type":"Point"}
}