{
  "type": "Feature",
  "properties": {
    "iso:country":"CH",
    "sg:address":"Altwingerten 1",
    "sg:city":"Dinhard",
    "sg:orig_category":"Softwareentwicklung U beratung",
    "sg:postcode":"8474",
    "sg:province":"Z\u00fcrich",
    "wof:name":"Habegger Software",
    "wof:placetype":"venue"
},
  "geometry": {"coordinates":[8.7486228943,47.5544700623],"type":"Point"}
}