{
  "type": "Feature",
  "properties": {
    "iso:country":"CH",
    "sg:address":"Le Camp",
    "sg:city":"Bi\u00e8re",
    "sg:orig_category":"Mechanik Schlossereien",
    "sg:phone":"+41 21 809 58 08",
    "sg:postcode":"1145",
    "sg:province":"Vaud",
    "wof:name":"Forge Serrurerie Tschantz Pierre-andr\u00e9",
    "wof:placetype":"venue"
},
  "geometry": {"coordinates":[6.3344750404,46.5325698853],"type":"Point"}
}