{
  "type": "Feature",
  "properties": {
    "iso:country":"CH",
    "sg:address":"Eggeli 2",
    "sg:city":"Sattel",
    "sg:orig_category":"Polizei",
    "sg:phone":"+41 41 835 13 17",
    "sg:postcode":"6417",
    "sg:province":"Schwyz",
    "wof:name":"Polizeiposten Sattel",
    "wof:placetype":"venue"
},
  "geometry": {"coordinates":[8.6355037689,47.0824928284],"type":"Point"}
}