{
  "type": "Feature",
  "properties": {
    "iso:country":"CH",
    "sg:address":"Rue Du Voisinand 10",
    "sg:city":"Lutry",
    "sg:orig_category":"Microtechnology Products Made Of Metal",
    "sg:phone":"+41 21 791 16 90",
    "sg:postcode":"1095",
    "sg:province":"Vaud",
    "wof:name":"Blc Produits Microtechniques Sa",
    "wof:placetype":"venue"
},
  "geometry": {"coordinates":[6.6870121956,46.5038032532],"type":"Point"}
}