{
  "type": "Feature",
  "properties": {
    "iso:country":"CH",
    "sg:address":"Via Lambertenghi 5",
    "sg:city":"Lugano",
    "sg:orig_category":"Herstellung von Bergwerks U Baumaschinen",
    "sg:phone":"+41 32 731 34 89",
    "sg:postcode":"6900",
    "sg:province":"Ticino",
    "wof:name":"De Oliveira Aurelio J. Machines De Chantiers Et Industriells D'occasion; Achat, Vente Etc",
    "wof:placetype":"venue"
},
  "geometry": {"coordinates":[6.9026479721,46.9829177856],"type":"Point"}
}