{
  "type": "Feature",
  "properties": {
    "iso:country":"CH",
    "sg:city":"Kriens (lu)",
    "sg:orig_category":"Industrie, Industrieorganisationen",
    "sg:postcode":"6010",
    "sg:province":"Luzern",
    "wof:name":"Geiger Cytec Systems Ag",
    "wof:placetype":"venue"
},
  "geometry": {"coordinates":[8.279205,47.033806],"type":"Point"}
}