{
  "type": "Feature",
  "properties": {
    "iso:country":"CH",
    "sg:address":"Rue De La Prulay 30",
    "sg:city":"Meyrin",
    "sg:orig_category":"Bauspenglerei Fassadenbau",
    "sg:phone":"+41 71 633 16 33",
    "sg:postcode":"1217",
    "sg:province":"Gen\u00e8ve",
    "wof:name":"Peter Walker",
    "wof:placetype":"venue"
},
  "geometry": {"coordinates":[9.150692,47.554638],"type":"Point"}
}