{
  "type": "Feature",
  "properties": {
    "addr:full":"Stutz 23 3700 Spiezwiler. Postfach 228 Spiez Bern 3700",
    "addr:housenumber":"23;228",
    "addr:postcode":"3700;3700",
    "addr:street":"Stutz;Postfach",
    "iso:country":"CH",
    "sg:address":"Stutz 23 3700 Spiezwiler. Postfach 228",
    "sg:city":"Spiez",
    "sg:orig_category":"Autoreiseunternehmen",
    "sg:phone":"+41 33 654 80 80",
    "sg:postcode":"3700",
    "sg:province":"Bern",
    "wof:name":"Erwin Maurer Carreisen",
    "wof:placetype":"venue"
},
  "geometry": {"coordinates":[7.665888,46.683041],"type":"Point"}
}