{
  "type": "Feature",
  "properties": {
    "iso:country":"CH",
    "sg:address":"Geerenweg 2",
    "sg:city":"Z\u00fcrich",
    "sg:orig_category":"Sanit\u00e4r, Heizungs U L\u00fcftungsinstallation Sanit\u00e4rinstallation",
    "sg:phone":"+41 91 646 44 20",
    "sg:postcode":"8048",
    "sg:province":"Z\u00fcrich",
    "wof:name":"Rilav Sa",
    "wof:placetype":"venue"
},
  "geometry": {"coordinates":[9.0076999664,45.8654785156],"type":"Point"}
}