{
  "type": "Feature",
  "properties": {
    "iso:country":"CH",
    "sg:address":"6866",
    "sg:city":"Meride",
    "sg:orig_category":"Architektur U Ingenieurb\u00fcros",
    "sg:postcode":"6866",
    "sg:province":"Ticino",
    "wof:name":"Archicasa Sa",
    "wof:placetype":"venue"
},
  "geometry": {"coordinates":[8.955031,45.890236],"type":"Point"}
}