{
  "type": "Feature",
  "properties": {
    "addr:full":"Rue Emile-yung 6 Gen\u00e8ve Gen\u00e8ve 1205",
    "addr:housenumber":"6",
    "addr:postcode":"1205",
    "addr:street":"Rue Emile-Yung",
    "iso:country":"CH",
    "sg:address":"Rue Emile-yung 6",
    "sg:city":"Gen\u00e8ve",
    "sg:orig_category":"Arztpraxen",
    "sg:phone":"+41 22 346 08 95",
    "sg:postcode":"1205",
    "sg:province":"Gen\u00e8ve",
    "wof:name":"Dr M\u00e9d.fran\u00e7oise R. Posternak M\u00e9decin Sp\u00e9cialiste Fmh",
    "wof:placetype":"venue"
},
  "geometry": {"coordinates":[6.149415,46.195675],"type":"Point"}
}