{
  "type": "Feature",
  "properties": {
    "iso:country":"CH",
    "sg:address":"Sonnmattgrund 7 6206 Neuenkirch. Postfach",
    "sg:city":"Neuenkirch",
    "sg:orig_category":"HERSTELLUNG VON GER\u00c4TEN DER ELEKTRIZIT\u00c4TSERZEUGUNG, -VERTEILUNG U.\u00c4 Mechanische Werkst\u00e4tten",
    "sg:phone":"+41 41 670 27 88",
    "sg:postcode":"6206",
    "sg:province":"Luzern",
    "wof:name":"Zietromec Ag",
    "wof:placetype":"venue"
},
  "geometry": {"coordinates":[8.2716178894,46.9414558411],"type":"Point"}
}