{
  "type": "Feature",
  "properties": {
    "iso:country":"CH",
    "sg:address":"Route De L'a\u00e9roport 5 1215 Gen\u00e8ve. Postfach 1215 Gen\u00e8ve",
    "sg:city":"D\u00e9p\u00f4t",
    "sg:orig_category":"Architekturb\u00fcros",
    "sg:phone":"+41 17371445",
    "sg:postcode":"15",
    "wof:name":"Furler Integrale Beratung Umwelt Bau Energie",
    "wof:placetype":"venue"
},
  "geometry": {"coordinates":[8.448877,47.356224],"type":"Point"}
}