{
  "type": "Feature",
  "properties": {
    "iso:country":"CH",
    "sg:address":"Zollstrasse 5",
    "sg:city":"Vaduz",
    "sg:orig_category":"Versicherungen Generalagenturen",
    "sg:phone":"+423 76540",
    "sg:postcode":"9490",
    "wof:name":"Die Mobiliar Versicherungen & Vorsorge",
    "wof:placetype":"venue"
},
  "geometry": {"coordinates":[9.5212287903,47.1325378418],"type":"Point"}
}