{
  "type": "Feature",
  "properties": {
    "iso:country":"CH",
    "sg:address":"Flecken 9",
    "sg:city":"Rothenburg",
    "sg:orig_category":"Detailhandel mit Brot, Back U S\u00fcsswaren",
    "sg:phone":"+41 41 280 11 50",
    "sg:postcode":"6023",
    "sg:province":"Luzern",
    "wof:name":"Holzofenbeck Ruedi Wicki",
    "wof:placetype":"venue"
},
  "geometry": {"coordinates":[8.271659,47.093487],"type":"Point"}
}