{
  "type": "Feature",
  "properties": {
    "addr:full":"Route De Corsinge 48 Meinier Gen\u00e8ve 1252",
    "addr:housenumber":"48",
    "addr:postcode":"1252",
    "addr:street":"Route De Corsinge",
    "iso:country":"CH",
    "sg:address":"Route De Corsinge 48",
    "sg:city":"Meinier",
    "sg:orig_category":"Bauschreinerei Herstellung von M\u00f6beln verschiedener Art",
    "sg:phone":"+41 22 759 18 63",
    "sg:postcode":"1252",
    "sg:province":"Gen\u00e8ve",
    "wof:name":"Patrick Vidonne Menuiserie & \u00e9b\u00e9nisterie",
    "wof:placetype":"venue"
},
  "geometry": {"coordinates":[6.242448,46.237438],"type":"Point"}
}