{
  "type": "Feature",
  "properties": {
    "iso:country":"CH",
    "sg:address":"Haldenstrasse 3",
    "sg:city":"Embrach",
    "sg:orig_category":"Detailhandel mit Radio U Fernsehger\u00e4ten Detailhandel mit elektrischen Haushalts-,Radio U Fernsehger\u00e4",
    "sg:phone":"+41 18655344",
    "sg:postcode":"8424",
    "sg:province":"Z\u00fcrich",
    "wof:name":"Hifi Studio Sigrist",
    "wof:placetype":"venue"
},
  "geometry": {"coordinates":[8.5932073593,47.5047721863],"type":"Point"}
}