{
  "type": "Feature",
  "properties": {
    "iso:country":"CH",
    "sg:address":"Hauptstrasse 68",
    "sg:city":"B\u00f6zen",
    "sg:classifiers":[
        {
            "category":"Restaurant",
            "type":"Food & Drink"
        }
    ],
    "sg:phone":"+41 62 876 11 37",
    "sg:postcode":"5076",
    "sg:province":"Aargau",
    "wof:name":"Gasthaus B\u00e4ren",
    "wof:placetype":"venue"
},
  "geometry": {"coordinates":[8.0827770233,47.4950904846],"type":"Point"}
}