{
  "type": "Feature",
  "properties": {
    "iso:country":"CH",
    "sg:address":"Rue Du Midi 2",
    "sg:city":"Lausanne",
    "sg:orig_category":"Unternehmensberatung",
    "sg:phone":"+41 79 212 50 77",
    "sg:postcode":"1003",
    "sg:province":"Vaud",
    "wof:name":"Dimension Corporate Finance Sa",
    "wof:placetype":"venue"
},
  "geometry": {"coordinates":[6.6316862106,46.5187034607],"type":"Point"}
}