{
  "type": "Feature",
  "properties": {
    "iso:country":"CH",
    "sg:address":"Untere Zollgasse 22",
    "sg:city":"Ostermundigen",
    "sg:classifiers":[
        {
            "category":"Communications",
            "subcategory":"Radio Station",
            "type":"Services"
        }
    ],
    "sg:phone":"+41 31 931 82 78",
    "sg:postcode":"3072",
    "sg:province":"Bern",
    "sg:tags":[
        "circuitry"
    ],
    "wof:name":"Elstar Bruderer",
    "wof:placetype":"venue"
},
  "geometry": {"coordinates":[7.488352,46.960335],"type":"Point"}
}