{
  "type": "Feature",
  "properties": {
    "addr:full":"Spitalgasse 5 Z\u00fcrich Z\u00fcrich 8001",
    "addr:housenumber":"5",
    "addr:postcode":"8001",
    "addr:street":"Spitalgasse",
    "iso:country":"CH",
    "sg:address":"Spitalgasse 5",
    "sg:city":"Z\u00fcrich",
    "sg:orig_category":"Detailhandel mit Bekleidung Detailhandel mit Schuhen",
    "sg:phone":"+41 12103840",
    "sg:postcode":"8001",
    "sg:province":"Z\u00fcrich",
    "wof:name":"Soho Ag Store",
    "wof:placetype":"venue"
},
  "geometry": {"coordinates":[8.54415,47.37365],"type":"Point"}
}