{
  "type": "Feature",
  "properties": {
    "iso:country":"CH",
    "sg:address":"Via Nobili Rusca 6",
    "sg:city":"Mendrisio",
    "sg:orig_category":"Selbst\u00e4ndige bildende K\u00fcnstler",
    "sg:phone":"+41 91 646 51 70",
    "sg:postcode":"6850",
    "sg:province":"Ticino",
    "wof:name":"Pierino Selmoni Scultore",
    "wof:placetype":"venue"
},
  "geometry": {"coordinates":[8.9895477295,45.8715515137],"type":"Point"}
}