{
  "type": "Feature",
  "properties": {
    "iso:country":"CH",
    "sg:address":"1950",
    "sg:city":"Sion",
    "sg:orig_category":"Detailhandel mit Brot, Back U S\u00fcsswaren",
    "sg:postcode":"1950",
    "sg:province":"Valais",
    "wof:name":"D\u00e9l\u00e8ze Pierre-gilbert",
    "wof:placetype":"venue"
},
  "geometry": {"coordinates":[7.3634,46.236698],"type":"Point"}
}