{
  "type": "Feature",
  "properties": {
    "iso:country":"CH",
    "sg:address":"Werdenbergerweg 11",
    "sg:city":"Vaduz",
    "sg:orig_category":"\u00dcbersetzungsb\u00fcros",
    "sg:phone":"+41 75 232 45 75",
    "sg:postcode":"9490",
    "wof:name":"Angela Matt Uebersetzungen",
    "wof:placetype":"venue"
},
  "geometry": {"coordinates":[9.516125679,47.1463546753],"type":"Point"}
}