{
  "type": "Feature",
  "properties": {
    "iso:country":"CH",
    "sg:address":"Heinrichstrasse 147 8005 Z\u00fcrich. Postfach",
    "sg:city":"Z\u00fcrich",
    "sg:orig_category":"Grosshandel mit sonstigen Maschinen U Ausr\u00fcstungen f\u00fcr Industrie, Handel U Schiffahrt",
    "sg:phone":"+41 12718222",
    "sg:postcode":"8001",
    "sg:province":"Z\u00fcrich",
    "wof:name":"Rohromatic Rohrreinigungsdienst, Hans Schoch Reinigung V. Rohren Aller Art",
    "wof:placetype":"venue"
},
  "geometry": {"coordinates":[8.5259838104,47.3871040344],"type":"Point"}
}