{
  "type": "Feature",
  "properties": {
    "iso:country":"CH",
    "sg:address":"Eggasse 20",
    "sg:city":"Worb",
    "sg:orig_category":"Detailhandel mit Haustieren U zoologischem Bedarf",
    "sg:phone":"+41 31 839 24 69",
    "sg:postcode":"3076",
    "sg:province":"Bern",
    "wof:name":"Ernst W\u00e4spe Heimtier Zoo",
    "wof:placetype":"venue"
},
  "geometry": {"coordinates":[7.5644378662,46.9319190979],"type":"Point"}
}