{
  "type": "Feature",
  "properties": {
    "addr:full":"Steinenvorstadt 32 Basel Basel-Stadt 4051",
    "addr:housenumber":"32",
    "addr:postcode":"4051",
    "addr:street":"Steinenvorstadt",
    "iso:country":"CH",
    "sg:address":"Steinenvorstadt 32",
    "sg:city":"Basel",
    "sg:classifiers":[
        {
            "category":"Bars & Pubs",
            "type":"Food & Drink"
        }
    ],
    "sg:phone":"+41 61 281 68 28",
    "sg:postcode":"4051",
    "sg:province":"Basel-Stadt",
    "sg:tags":[
        "restaurant"
    ],
    "wof:name":"Restaurant-bar Movie",
    "wof:placetype":"venue"
},
  "geometry": {"coordinates":[7.588361,47.552746],"type":"Point"}
}