{
  "type": "Feature",
  "properties": {
    "iso:country":"CH",
    "sg:address":"Krauchthalstrasse 2 3324 Hindelbank. Postfach",
    "sg:city":"Hindelbank",
    "sg:orig_category":"Herstellung von Metallkonstruktionen",
    "sg:postcode":"3324",
    "sg:province":"Bern",
    "wof:name":"Covertec Fassadentechnik Ag",
    "wof:placetype":"venue"
},
  "geometry": {"coordinates":[7.54773283,47.0363273621],"type":"Point"}
}