{
  "type": "Feature",
  "properties": {
    "iso:country":"CH",
    "sg:address":"Industrie West 40/42 4614 H\u00e4gendorf. Postfach",
    "sg:city":"Olten",
    "sg:orig_category":"Detailhandel mit M\u00f6beln Verlegen von Fussboden",
    "sg:phone":"+41 304610",
    "sg:postcode":"4601",
    "sg:province":"Solothurn",
    "wof:name":"M\u00f6belhaus St\u00f6rchli Gmbh",
    "wof:placetype":"venue"
},
  "geometry": {"coordinates":[8.7823114395,47.3674240112],"type":"Point"}
}