{
  "type": "Feature",
  "properties": {
    "iso:country":"CH",
    "sg:address":"Prisongasse 4",
    "sg:city":"Solothurn",
    "sg:orig_category":"RESTAURANTS: TEA-ROOMS",
    "sg:postcode":"4500",
    "sg:province":"Solothurn",
    "wof:name":"Misteli Joseph",
    "wof:placetype":"venue"
},
  "geometry": {"coordinates":[7.5367279053,47.2050819397],"type":"Point"}
}