{
  "type": "Feature",
  "properties": {
    "iso:country":"CH",
    "sg:address":"Tribschenstrasse 7 6005 Luzern. Postfach 2770",
    "sg:city":"Luzern",
    "sg:orig_category":"Rechtsberatung Verwaltung von Immobilien",
    "sg:phone":"+41 58 286 77 11",
    "sg:postcode":"6002",
    "sg:province":"Luzern",
    "wof:name":"Ernst & Young Ag",
    "wof:placetype":"venue"
},
  "geometry": {"coordinates":[8.3125286102,47.044052124],"type":"Point"}
}