{
  "type": "Feature",
  "properties": {
    "addr:full":"Erni Via Hans 15 Ilanz Graubunden 7130",
    "addr:housenumber":"15",
    "addr:postcode":"7130",
    "addr:street":"Via Hans;Graubunden",
    "iso:country":"CH",
    "sg:address":"Erni Via Hans 15",
    "sg:city":"Ilanz",
    "sg:orig_category":"Architektur U Ingenieurb\u00fcros",
    "sg:phone":"+41 56 281 31 16",
    "sg:postcode":"7130",
    "sg:province":"Graubunden",
    "wof:name":"Architekturb\u00fcro Christen Marcel",
    "wof:placetype":"venue"
},
  "geometry": {"coordinates":[8.24502,47.524662],"type":"Point"}
}