{
  "type": "Feature",
  "properties": {
    "iso:country":"CH",
    "sg:address":"Romanshornerstrasse 27",
    "sg:city":"Arbon",
    "sg:orig_category":"Softwareentwicklung U beratung",
    "sg:postcode":"9320",
    "sg:province":"Thurgau",
    "wof:name":"Schneider & Stofer, Edv-systeme Und Beratung",
    "wof:placetype":"venue"
},
  "geometry": {"coordinates":[9.4284124374,47.5177154541],"type":"Point"}
}