{
  "type": "Feature",
  "properties": {
    "iso:country":"CH",
    "sg:address":"1595",
    "sg:city":"Faoug",
    "sg:orig_category":"Schulpflegen",
    "sg:postcode":"1595",
    "sg:province":"Bern",
    "wof:name":"Commission Scolaire De L'ecole Primaire",
    "wof:placetype":"venue"
},
  "geometry": {"coordinates":[7.0785198212,46.908531189],"type":"Point"}
}