{
  "type": "Feature",
  "properties": {
    "iso:country":"CH",
    "sg:address":"Chrischonaw\u00e4g 12",
    "sg:city":"Rafz",
    "sg:orig_category":"Detailhandel mit elektrischen Haushalts-,Radio U Fernsehger\u00e4ten sowie Musikinstrumenten",
    "sg:postcode":"8197",
    "sg:province":"Z\u00fcrich",
    "wof:name":"Sound Am Albis, Daniel Z\u00fcrcher",
    "wof:placetype":"venue"
},
  "geometry": {"coordinates":[8.4494762421,47.2787590027],"type":"Point"}
}