{
  "type": "Feature",
  "properties": {
    "iso:country":"CH",
    "sg:address":"Wiesackerstrasse 135",
    "sg:city":"Regensdorf",
    "sg:orig_category":"Herstellung von Verbrennungsmotoren U Turbinen ohne Motoren f\u00fcr Luft U Strassenfahrzeuge Mechanische",
    "sg:phone":"+41 18400544",
    "sg:postcode":"8105",
    "sg:province":"Z\u00fcrich",
    "wof:name":"Hollenstein Und Zoelly",
    "wof:placetype":"venue"
},
  "geometry": {"coordinates":[8.4582414627,47.4405326843],"type":"Point"}
}