{
  "type": "Feature",
  "properties": {
    "addr:full":"Avenue De Florimont 2bis Lausanne Vaud 1006",
    "addr:housenumber":"2bis",
    "addr:postcode":"1006",
    "addr:street":"Avenue De Florimont",
    "iso:country":"CH",
    "sg:address":"Avenue De Florimont 2bis",
    "sg:city":"Lausanne",
    "sg:orig_category":"B\u00e4ckereien Detailhandel mit Waren verschiedener Art, Hauptrichtung Nahrungsmittel",
    "sg:postcode":"1006",
    "sg:province":"Vaud",
    "wof:name":"Silvana Cavadini Nives Boulangerie Chez Sissi",
    "wof:placetype":"venue"
},
  "geometry": {"coordinates":[6.637914,46.516102],"type":"Point"}
}