{
  "type": "Feature",
  "properties": {
    "iso:country":"CH",
    "sg:address":"Dorfstrasse 52 3123 Belp. Postfach 12",
    "sg:city":"Belp",
    "sg:orig_category":"Detailhandel mit M\u00f6beln Verlegen von Fussboden",
    "sg:phone":"+41 31 818 80 80",
    "sg:postcode":"3123",
    "sg:province":"Bern",
    "wof:name":"Probst + Eggimann Ag",
    "wof:placetype":"venue"
},
  "geometry": {"coordinates":[7.5009469986,46.8897972107],"type":"Point"}
}