{
  "type": "Feature",
  "properties": {
    "iso:country":"CH",
    "sg:address":"Tribschenstrasse 7 6005 Luzern. Postfach",
    "sg:city":"Luzern",
    "sg:orig_category":"Pensionskassen",
    "sg:postcode":"6003",
    "sg:province":"Luzern",
    "wof:name":"Personalf\u00fcrsorgestiftung Des Acs Luzern",
    "wof:placetype":"venue"
},
  "geometry": {"coordinates":[8.3125286102,47.044052124],"type":"Point"}
}