{
  "type": "Feature",
  "properties": {
    "iso:country":"CH",
    "sg:address":"M\u00fchlebachstrasse 82",
    "sg:city":"Z\u00fcrich",
    "sg:orig_category":"Patentverwertung Rechtsberatung",
    "sg:phone":"+41 81 420 11 95",
    "sg:postcode":"8008",
    "sg:province":"Z\u00fcrich",
    "wof:name":"Ecofin Data Model Ag",
    "wof:placetype":"venue"
},
  "geometry": {"coordinates":[9.8372573853,46.8050575256],"type":"Point"}
}