{
  "type": "Feature",
  "properties": {
    "iso:country":"CH",
    "sg:address":"Rorikerhof",
    "sg:city":"Niederrohrdorf",
    "sg:orig_category":"Verwertung von Milch",
    "sg:postcode":"5443",
    "sg:province":"Aargau",
    "wof:name":"Milchgenossenschaft Niederrohrdorf",
    "wof:placetype":"venue"
},
  "geometry": {"coordinates":[8.2938261032,47.4219284058],"type":"Point"}
}