{
  "type": "Feature",
  "properties": {
    "iso:country":"CH",
    "sg:address":"Christoph-schnyder-str. 1c",
    "sg:city":"Sursee",
    "sg:orig_category":"Herstellung von medizinischen U chirurgischen Ger\u00e4ten sowie orthop\u00e4dischen Vorrichtungen",
    "sg:postcode":"6210",
    "sg:province":"Luzern",
    "wof:name":"Trans-eye Ag",
    "wof:placetype":"venue"
},
  "geometry": {"coordinates":[8.1021928787,47.1717567444],"type":"Point"}
}