{
  "type": "Feature",
  "properties": {
    "iso:country":"CH",
    "sg:address":"Au Village 1041 Naz. Postfach",
    "sg:city":"Etoy",
    "sg:orig_category":"G\u00fcterbef\u00f6rderung im Strassenverkehr",
    "sg:phone":"+41 21 807 10 66",
    "sg:postcode":"1163",
    "sg:province":"Vaud",
    "wof:name":"Denatrans, Jean-claude Dessauges",
    "wof:placetype":"venue"
},
  "geometry": {"coordinates":[6.6988630295,46.6573143005],"type":"Point"}
}