{
  "type": "Feature",
  "properties": {
    "iso:country":"CH",
    "sg:address":"Plantahofstrasse 7302 Landquart. Postfach 185",
    "sg:city":"Landquart",
    "sg:orig_category":"Sanit\u00e4r, Heizungs U L\u00fcftungsinstallation Sanit\u00e4rinstallation",
    "sg:phone":"+41 81 322 47 73",
    "sg:postcode":"7302",
    "sg:province":"Graubunden",
    "wof:name":"Holzinger Dieter Ag",
    "wof:placetype":"venue"
},
  "geometry": {"coordinates":[9.5585203171,46.963848114],"type":"Point"}
}