{
  "type": "Feature",
  "properties": {
    "iso:country":"CH",
    "sg:address":"Weissensteinstrasse 24",
    "sg:city":"Burgdorf",
    "sg:orig_category":"Fachdetailhandel mit pharmazeutischen Produkten",
    "sg:phone":"+41 34 420 27 27",
    "sg:postcode":"3400",
    "sg:province":"Bern",
    "wof:name":"Pharma Consulting Senn Marion Gmbh",
    "wof:placetype":"venue"
},
  "geometry": {"coordinates":[7.6146068573,47.056930542],"type":"Point"}
}