{
  "type": "Feature",
  "properties": {
    "iso:country":"CH",
    "sg:address":"R\u00f6hrliberg 26",
    "sg:city":"Cham",
    "sg:orig_category":"Vorschulen, Kinderg\u00e4rten",
    "sg:phone":"+41 41 780 50 71",
    "sg:postcode":"6330",
    "sg:province":"Zug",
    "wof:name":"Kindergarten R\u00f6hrliberg",
    "wof:placetype":"venue"
},
  "geometry": {"coordinates":[8.4520196915,47.1867408752],"type":"Point"}
}