{
  "type": "Feature",
  "properties": {
    "iso:country":"CH",
    "sg:address":"S\u00e4gestrasse 10 8157 Dielsdorf. Postfach",
    "sg:city":"Dielsdorf",
    "sg:orig_category":"Wohnheime",
    "sg:postcode":"8157",
    "sg:province":"Z\u00fcrich",
    "wof:name":"Baugenossenschaft Seniorenwohnraum Dielsdorf",
    "wof:placetype":"venue"
},
  "geometry": {"coordinates":[8.451540947,47.4836463928],"type":"Point"}
}