{
  "type": "Feature",
  "properties": {
    "iso:country":"CH",
    "sg:address":"Rue Du 1er-mars 6",
    "sg:city":"Geneveys-coffrane",
    "sg:classifiers":[
        {
            "category":"Food & Beverages",
            "subcategory":"Specialty",
            "type":"Retail Goods"
        }
    ],
    "sg:phone":"+41 32 857 30 05",
    "sg:postcode":"2206",
    "sg:province":"Neuch\u00e2tel",
    "sg:tags":[
        "caterer"
    ],
    "wof:name":"Pizza'fun Livraison \u00e0 Domicile",
    "wof:placetype":"venue"
},
  "geometry": {"coordinates":[6.851742,47.016617],"type":"Point"}
}