{
  "type": "Feature",
  "properties": {
    "iso:country":"CH",
    "sg:address":"Br\u00fchlstrasse 48b",
    "sg:city":"Klingnau",
    "sg:orig_category":"Sportvereine Billard",
    "sg:phone":"+41 56 245 75 70",
    "sg:postcode":"5313",
    "sg:province":"Aargau",
    "wof:name":"Club 90 Billardclub",
    "wof:placetype":"venue"
},
  "geometry": {"coordinates":[8.2513399124,47.5786590576],"type":"Point"}
}