{
  "type": "Feature",
  "properties": {
    "iso:country":"CH",
    "sg:address":"Rotzbergstrasse 7",
    "sg:city":"Stansstad",
    "sg:orig_category":"Herstellung von Metallkonstruktionen",
    "sg:phone":"+41 27 722 23 42",
    "sg:postcode":"6362",
    "sg:province":"Nidwalden",
    "wof:name":"Righini Charles",
    "wof:placetype":"venue"
},
  "geometry": {"coordinates":[7.0742988586,46.1036071777],"type":"Point"}
}