{
  "type": "Feature",
  "properties": {
    "iso:country":"CH",
    "sg:address":"Allschwilerstrasse 81",
    "sg:city":"Basel",
    "sg:orig_category":"Sonstige pers\u00f6nliche Dienstleistungen",
    "sg:phone":"+41 61 332 21 50",
    "sg:postcode":"4055",
    "sg:province":"Basel-Stadt",
    "wof:name":"Be.st Beutter + Stephenson",
    "wof:placetype":"venue"
},
  "geometry": {"coordinates":[7.5695037842,47.5572090149],"type":"Point"}
}