{
  "type": "Feature",
  "properties": {
    "iso:country":"CH",
    "sg:address":"Zentrumsplatz 10",
    "sg:city":"Sch\u00f6nb\u00fchl-urtenen",
    "sg:orig_category":"Versicherungen Hauptagenturen",
    "sg:phone":"+41 31 859 40 00",
    "sg:postcode":"3322",
    "sg:province":"Bern",
    "wof:name":"Winterthur-versicherungen Hauptagentur",
    "wof:placetype":"venue"
},
  "geometry": {"coordinates":[7.4982981682,47.0207672119],"type":"Point"}
}