{
  "type": "Feature",
  "properties": {
    "iso:country":"CH",
    "sg:address":"Le Coin",
    "sg:city":"Lussery-villars",
    "sg:orig_category":"Sonstige pers\u00f6nliche Dienstleistungen",
    "sg:phone":"+41 21 861 08 62",
    "sg:postcode":"1307",
    "sg:province":"Vaud",
    "wof:name":"Georges Kobel Www.surdoue.net",
    "wof:placetype":"venue"
},
  "geometry": {"coordinates":[6.5240530968,46.6356201172],"type":"Point"}
}