{
  "type": "Feature",
  "properties": {
    "iso:country":"CH",
    "sg:address":"1692",
    "sg:city":"Massonnens",
    "sg:orig_category":"RESTAURANTS: TEA-ROOMS",
    "sg:phone":"+41 26 653 11 56",
    "sg:postcode":"1692",
    "sg:province":"Fribourg",
    "wof:name":"Auberge De L'union, Thierry Jean-gabriel",
    "wof:placetype":"venue"
},
  "geometry": {"coordinates":[6.9777002335,46.6972312927],"type":"Point"}
}