{
  "type": "Feature",
  "properties": {
    "iso:country":"CH",
    "sg:address":"Route De Scie 13",
    "sg:city":"Estavayer-le-lac",
    "sg:orig_category":"Herstellung von k\u00e4lte U lufttechnischen Erzeugnissen f\u00fcr gewerbliche Zwecke Sanit\u00e4r U Heizungsinstal",
    "sg:phone":"+41 26 663 33 69",
    "sg:postcode":"1470",
    "sg:province":"Fribourg",
    "wof:name":"Sautaux R. Chauffages Centraux Sa",
    "wof:placetype":"venue"
},
  "geometry": {"coordinates":[6.8467597961,46.8427047729],"type":"Point"}
}