{
  "type": "Feature",
  "properties": {
    "iso:country":"CH",
    "sg:address":"Wydenstrasse 4",
    "sg:city":"Worb",
    "sg:orig_category":"Architekturb\u00fcros",
    "sg:phone":"+41 34 402 50 72",
    "sg:postcode":"3076",
    "sg:province":"Bern",
    "wof:name":"Grossenbacher & Glauser Ag Architekturb\u00fcro",
    "wof:placetype":"venue"
},
  "geometry": {"coordinates":[7.564464,46.927624],"type":"Point"}
}