{
  "type": "Feature",
  "properties": {
    "iso:country":"CH",
    "sg:address":"Alexander-sch\u00f6ni-strasse 40 2500 Biel/bienne. Postfach",
    "sg:city":"Biel/bienne",
    "sg:orig_category":"Architektur U Ingenieurb\u00fcros",
    "sg:phone":"+41 32 325 47 25",
    "sg:postcode":"2502",
    "sg:province":"Bern",
    "wof:name":"Hadorn Patrick + Kocher Hans-peter Bauleitung Gmbh",
    "wof:placetype":"venue"
},
  "geometry": {"coordinates":[7.250675,47.137516],"type":"Point"}
}