{
  "type": "Feature",
  "properties": {
    "iso:country":"CH",
    "sg:address":"Route D'a\u00efre 158",
    "sg:city":"A\u00efre",
    "sg:orig_category":"Softwareentwicklung U beratung Wirtschaftspr\u00fcfung, Steuerberatung U Treuhand",
    "sg:phone":"+41 22 970 00 83",
    "sg:postcode":"1219",
    "sg:province":"Gen\u00e8ve",
    "wof:name":"Jean Pfyffer Conseil & Comptabilit\u00e9",
    "wof:placetype":"venue"
},
  "geometry": {"coordinates":[6.1003398895,46.1972198486],"type":"Point"}
}