{
  "type": "Feature",
  "properties": {
    "iso:country":"CH",
    "sg:address":"Hauptstrasse 35 4127 Birsfelden. Postfach",
    "sg:city":"Birsfelden",
    "sg:orig_category":"Detailhandel mit Waren verschiedener Art, Hauptrichtung Nahrungsmittel Grosshandel mit Nahrungsmitte",
    "sg:phone":"+41 61 313 00 80",
    "sg:postcode":"4127",
    "sg:province":"Basel-Landschaft",
    "wof:name":"Mini Market Gmbh",
    "wof:placetype":"venue"
},
  "geometry": {"coordinates":[7.620554924,47.5540161133],"type":"Point"}
}