{
  "type": "Feature",
  "properties": {
    "iso:country":"CH",
    "sg:address":"Tour-ma\u00eetresse Rue De La 12 1204 Gen\u00e8ve. Postfach",
    "sg:city":"Gen\u00e8ve",
    "sg:orig_category":"Fachdetailhandel in Verkaufsr\u00e4umen",
    "sg:postcode":"1204",
    "sg:province":"Gen\u00e8ve",
    "wof:name":"Fougue S\u00e0rl",
    "wof:placetype":"venue"
},
  "geometry": {"coordinates":[6.1574859619,46.2039604187],"type":"Point"}
}