{
  "type": "Feature",
  "properties": {
    "iso:country":"CH",
    "sg:address":"Schlossg\u00e4ssli 21",
    "sg:city":"Burgdorf",
    "sg:orig_category":"Arztpraxen",
    "sg:phone":"+41 56 641 19 19",
    "sg:postcode":"3400",
    "sg:province":"Bern",
    "wof:name":"Dr.med.rolf K\u00f6ster Spezialarzt Fmh",
    "wof:placetype":"venue"
},
  "geometry": {"coordinates":[8.348824,47.351933],"type":"Point"}
}