{
  "type": "Feature",
  "properties": {
    "iso:country":"CH",
    "sg:address":"Hauptstrasse 69",
    "sg:city":"Muttenz",
    "sg:orig_category":"Laboratoriums-Chemikalien",
    "sg:phone":"+41 61 461 11 33",
    "sg:postcode":"4132",
    "sg:province":"Basel-Landschaft",
    "wof:name":"Volgochim Ag",
    "wof:placetype":"venue"
},
  "geometry": {"coordinates":[7.6467728615,47.5258331299],"type":"Point"}
}