{
  "type": "Feature",
  "properties": {
    "iso:country":"CH",
    "sg:address":"Via Cantonale 19 6900 Lugano. Postfach Caselle Postale 2418",
    "sg:city":"Lugano",
    "sg:orig_category":"Detailhandel mit M\u00f6beln U Haushaltsgegenst\u00e4nden",
    "sg:phone":"+41 91 924 90 60",
    "sg:postcode":"6901",
    "sg:province":"Ticino",
    "wof:name":"Mobinfina Sagl",
    "wof:placetype":"venue"
},
  "geometry": {"coordinates":[8.9502239227,46.0093307495],"type":"Point"}
}