{
  "type": "Feature",
  "properties": {
    "iso:country":"CH",
    "sg:address":"St\u00e4dtchen 33",
    "sg:city":"Uznach",
    "sg:orig_category":"Detailhandel mit Fahrr\u00e4dern Handel mit Motorr\u00e4dern, Teilen U Zubeh\u00f6r Instandhaltung U Reparatur von ",
    "sg:postcode":"8730",
    "sg:province":"St. Gallen",
    "wof:name":"Peter Brunner Brunner's 2-rad-egg\u00e4",
    "wof:placetype":"venue"
},
  "geometry": {"coordinates":[8.9872217178,47.2254981995],"type":"Point"}
}