{
  "type": "Feature",
  "properties": {
    "iso:country":"CH",
    "sg:address":"9425",
    "sg:city":"Thal",
    "sg:orig_category":"Sportvereine Velo Rad-& Motorfahrer-Bund SRB",
    "sg:postcode":"9425",
    "sg:province":"St. Gallen",
    "wof:name":"Arbeiter-touring-bund Atb Solidarit\u00e4t",
    "wof:placetype":"venue"
},
  "geometry": {"coordinates":[8.2029390335,47.2663993835],"type":"Point"}
}