{
  "type": "Feature",
  "properties": {
    "iso:country":"CH",
    "sg:address":"P\u00fcntstrasse 1",
    "sg:city":"Wila",
    "sg:orig_category":"G\u00fcterbef\u00f6rderung im Strassenverkehr",
    "sg:phone":"+41 52 385 16 33",
    "sg:postcode":"8492",
    "sg:province":"Z\u00fcrich",
    "wof:name":"A. Waldvogel Ag Transporte",
    "wof:placetype":"venue"
},
  "geometry": {"coordinates":[8.8437976837,47.4216804504],"type":"Point"}
}