{
  "type": "Feature",
  "properties": {
    "iso:country":"CH",
    "sg:address":"B\u00e4renbohlstrasse 19",
    "sg:city":"Z\u00fcrich",
    "sg:orig_category":"Sportvereine Eissport Eishockey",
    "sg:phone":"+41 13715202",
    "sg:postcode":"8046",
    "sg:province":"Z\u00fcrich",
    "wof:name":"Hockey-club Grischun Kniggers",
    "wof:placetype":"venue"
},
  "geometry": {"coordinates":[8.5099658966,47.4265785217],"type":"Point"}
}