{
  "type": "Feature",
  "properties": {
    "iso:country":"CH",
    "sg:address":"Falkenstrasse 2a",
    "sg:city":"Langenthal",
    "sg:orig_category":"Vorschulen, Kinderg\u00e4rten",
    "sg:phone":"+41 62 922 68 76",
    "sg:postcode":"4900",
    "sg:province":"Bern",
    "wof:name":"Kindergarten B\u00e4regg Ii",
    "wof:placetype":"venue"
},
  "geometry": {"coordinates":[7.7840929031,47.2221794128],"type":"Point"}
}