{
  "type": "Feature",
  "properties": {
    "iso:country":"CH",
    "sg:address":"9622",
    "sg:city":"Krinau",
    "sg:orig_category":"Vereine Gesang",
    "sg:postcode":"9622",
    "sg:province":"St. Gallen",
    "wof:name":"M\u00e4nnerchor Krinau",
    "wof:placetype":"venue"
},
  "geometry": {"coordinates":[9.0497646332,47.3174209595],"type":"Point"}
}