{
  "type": "Feature",
  "properties": {
    "iso:country":"CH",
    "sg:address":"Regensbergstrasse 96",
    "sg:city":"Z\u00fcrich",
    "sg:orig_category":"Handel mit Automobilen Instandhaltung U Reparatur von Automobilen",
    "sg:phone":"+41 79 429 29 04",
    "sg:postcode":"8050",
    "sg:province":"Z\u00fcrich",
    "wof:name":"Z\u00fcri Zw\u00f6lf Autohandels Ag",
    "wof:placetype":"venue"
},
  "geometry": {"coordinates":[8.5476560593,47.4059867859],"type":"Point"}
}