{
  "type": "Feature",
  "properties": {
    "iso:country":"CH",
    "sg:address":"Flugplatzstrasse",
    "sg:city":"Grenchen",
    "sg:orig_category":"Verkehrsmittel, Bahnverkehr",
    "sg:postcode":"2540",
    "sg:province":"Solothurn",
    "wof:name":"Regionalflughafen Jura Grenchen Ag",
    "wof:placetype":"venue"
},
  "geometry": {"coordinates":[7.399401,47.192886],"type":"Point"}
}