{
  "type": "Feature",
  "properties": {
    "iso:country":"CH",
    "sg:address":"Haslistrasse 8",
    "sg:city":"Windlach",
    "sg:orig_category":"Hochschulen U h\u00f6here Ausbildung Informatikschulen",
    "sg:phone":"+41 18581005",
    "sg:postcode":"8175",
    "sg:province":"Z\u00fcrich",
    "wof:name":"Zero One",
    "wof:placetype":"venue"
},
  "geometry": {"coordinates":[8.4753084183,47.5389404297],"type":"Point"}
}