{
  "type": "Feature",
  "properties": {
    "addr:full":"Tiefenmattweg 4 Biel/bienne Bern 2503",
    "addr:housenumber":"4",
    "addr:postcode":"2503",
    "addr:street":"Tiefenmattweg",
    "iso:country":"CH",
    "sg:address":"Tiefenmattweg 4",
    "sg:city":"Biel/bienne",
    "sg:orig_category":"Cutting Machines For Diamonds",
    "sg:phone":"+41 32 365 07 77",
    "sg:postcode":"2503",
    "sg:province":"Bern",
    "wof:name":"Dianding",
    "wof:placetype":"venue"
},
  "geometry": {"coordinates":[7.25138,47.12767],"type":"Point"}
}