{
  "type": "Feature",
  "properties": {
    "iso:country":"CH",
    "sg:address":"Schaffhauserstrasse 34",
    "sg:city":"Kleinandelfingen",
    "sg:classifiers":[
        {
            "category":"Government",
            "subcategory":"Fire Station",
            "type":"Public Place"
        }
    ],
    "sg:phone":"+41 52 317 27 23",
    "sg:postcode":"8451",
    "sg:province":"Z\u00fcrich",
    "sg:tags":[
        "development",
        "hardware",
        "soft"
    ],
    "wof:name":"Wyland Elektronik Gmbh",
    "wof:placetype":"venue"
},
  "geometry": {"coordinates":[8.684132576,47.5999450684],"type":"Point"}
}