{
  "type": "Feature",
  "properties": {
    "iso:country":"CH",
    "sg:address":"Moosgasse 56",
    "sg:city":"Limpach",
    "sg:orig_category":"Gesundheitswesen",
    "sg:phone":"+41 79 321 97 39",
    "sg:postcode":"3317",
    "sg:province":"Bern",
    "wof:name":"Cos, Chain Of Survive Meuwly Alexandra Und Schrepfer Sabina",
    "wof:placetype":"venue"
},
  "geometry": {"coordinates":[7.491300106,47.1092414856],"type":"Point"}
}