{
  "type": "Feature",
  "properties": {
    "iso:country":"CH",
    "sg:address":"La Cibe",
    "sg:city":"Concise",
    "sg:orig_category":"Sanit\u00e4r, Heizungs U L\u00fcftungsinstallation Sanit\u00e4rinstallation",
    "sg:phone":"+41 24 434 15 53",
    "sg:postcode":"1426",
    "sg:province":"Vaud",
    "wof:name":"Jos\u00e9 Borges Installations Sanitaires",
    "wof:placetype":"venue"
},
  "geometry": {"coordinates":[6.7170248032,46.8502502441],"type":"Point"}
}