{
  "type": "Feature",
  "properties": {
    "iso:country":"CH",
    "sg:address":"Schwalbenweg 1",
    "sg:city":"Z\u00fcrich",
    "sg:orig_category":"Detailhandel mit Fahrr\u00e4dern",
    "sg:phone":"+41 13121550",
    "sg:postcode":"8050",
    "sg:province":"Z\u00fcrich",
    "wof:name":"Werner Fl\u00fcckiger Werni's Veloshop",
    "wof:placetype":"venue"
},
  "geometry": {"coordinates":[8.5355205536,47.4102516174],"type":"Point"}
}