{
  "type": "Feature",
  "properties": {
    "iso:country":"CH",
    "sg:address":"M\u00fchlenstrasse 50",
    "sg:city":"Schaffhausen",
    "sg:orig_category":"Sonstige Kurierdienste Vermietung von Automobilen",
    "sg:phone":"+41 52 624 11 70",
    "sg:postcode":"8200",
    "sg:province":"Schaffhausen",
    "wof:name":"Diego Reinau Ace Limousine-service",
    "wof:placetype":"venue"
},
  "geometry": {"coordinates":[8.6273698807,47.6932411194],"type":"Point"}
}