{
  "type": "Feature",
  "properties": {
    "addr:full":"Avenue Alexandre Vinet 11 Clarens Vaud 1815",
    "addr:housenumber":"11",
    "addr:postcode":"1815",
    "addr:street":"Avenue Alexandre Vinet",
    "iso:country":"CH",
    "sg:address":"Avenue Alexandre Vinet 11",
    "sg:city":"Clarens",
    "sg:orig_category":"Arztpraxen",
    "sg:phone":"+41 21 964 16 36",
    "sg:postcode":"1815",
    "sg:province":"Vaud",
    "wof:name":"Dr M\u00e9d. Roland Sthioul M\u00e9decin G\u00e9n\u00e9raliste",
    "wof:placetype":"venue"
},
  "geometry": {"coordinates":[6.894168,46.4412],"type":"Point"}
}