{
  "type": "Feature",
  "properties": {
    "iso:country":"CH",
    "sg:address":"Im Obere Binder",
    "sg:city":"T\u00e4gerwilen",
    "sg:orig_category":"Sportvereine Turnen Vereine Damen",
    "sg:phone":"+41 71 669 20 37",
    "sg:postcode":"8274",
    "sg:province":"Thurgau",
    "wof:name":"Damenturnv.stv Alterswilen",
    "wof:placetype":"venue"
},
  "geometry": {"coordinates":[9.1400003433,47.648563385],"type":"Point"}
}