{
  "type": "Feature",
  "properties": {
    "iso:country":"CH",
    "sg:address":"Dorfstrasse 65",
    "sg:city":"Beckenried",
    "sg:orig_category":"Detailhandel mit Antiquit\u00e4ten Reparatur von Uhren U Schmuck",
    "sg:phone":"+41 41 620 66 32",
    "sg:postcode":"6375",
    "sg:province":"Nidwalden",
    "wof:name":"Kamber Martin Gmbh Bad- U. Tuschtrennw\u00e4nde Usw; Handel, Montage",
    "wof:placetype":"venue"
},
  "geometry": {"coordinates":[8.470042,46.969463],"type":"Point"}
}