{
  "type": "Feature",
  "properties": {
    "iso:country":"CH",
    "sg:address":"Stadthausstr. 2",
    "sg:city":"Luzern",
    "sg:orig_category":"Detailhandel mit Fleisch U Fleischwaren",
    "sg:phone":"+41 41 210 99 33",
    "sg:postcode":"6003",
    "sg:province":"Luzern",
    "wof:name":"Kauffmann Ag",
    "wof:placetype":"venue"
},
  "geometry": {"coordinates":[8.3055047989,47.0494117737],"type":"Point"}
}