{
  "type": "Feature",
  "properties": {
    "addr:full":"Passage Des Lions 6bis Gen\u00e8ve Gen\u00e8ve 1204",
    "addr:housenumber":"6bis",
    "addr:postcode":"1204",
    "addr:street":"Passage Des Lions",
    "iso:country":"CH",
    "sg:address":"Passage Des Lions 6bis",
    "sg:city":"Gen\u00e8ve",
    "sg:orig_category":"Detailhandel mit Damenbekleidung",
    "sg:phone":"+41 22 781 50 02",
    "sg:postcode":"1204",
    "sg:province":"Gen\u00e8ve",
    "wof:name":"La Maison Du Tricot Sa Confection Dames",
    "wof:placetype":"venue"
},
  "geometry": {"coordinates":[6.144186,46.204037],"type":"Point"}
}