{
  "type": "Feature",
  "properties": {
    "addr:full":"Obergasse 13 Bischofszell Thurgau 9220",
    "addr:housenumber":"13",
    "addr:postcode":"9220",
    "addr:street":"Obergasse",
    "iso:country":"CH",
    "sg:address":"Obergasse 13",
    "sg:city":"Bischofszell",
    "sg:classifiers":[
        {
            "category":"Bars & Pubs",
            "type":"Food & Drink"
        }
    ],
    "sg:postcode":"9220",
    "sg:province":"Thurgau",
    "wof:name":"Ledergerber Birgitta",
    "wof:placetype":"venue"
},
  "geometry": {"coordinates":[9.242485,47.494076],"type":"Point"}
}