{
  "type": "Feature",
  "properties": {
    "addr:full":"Wilhofstrasse 8 8332 Russikon. Postfach 87 Russikon Z\u00fcrich 8332",
    "addr:housenumber":"8;87",
    "addr:postcode":"8332;8332",
    "addr:street":"Wilhofstrasse;Postfach",
    "iso:country":"CH",
    "sg:address":"Wilhofstrasse 8 8332 Russikon. Postfach 87",
    "sg:city":"Russikon",
    "sg:orig_category":"Bauschreinerei Herstellung von Konstruktionsteilen, Fertigbauteilen U Ausbauelementen aus Holz",
    "sg:phone":"+41 19540766",
    "sg:postcode":"8332",
    "sg:province":"Z\u00fcrich",
    "wof:name":"Schreinerei Maag Und Takacs",
    "wof:placetype":"venue"
},
  "geometry": {"coordinates":[8.776015,47.39159],"type":"Point"}
}