{
  "type": "Feature",
  "properties": {
    "iso:country":"CH",
    "sg:address":"Schl\u00f6sslistrasse 9a 3008 Bern. Postfach 8915",
    "sg:city":"Bern",
    "sg:orig_category":"Vermittlung von Immobilien",
    "sg:phone":"+41 27 322 30 56",
    "sg:postcode":"3001",
    "sg:province":"Bern",
    "wof:name":"Xavier Favre Agence Immobili\u00e8re",
    "wof:placetype":"venue"
},
  "geometry": {"coordinates":[7.3603811264,46.2345085144],"type":"Point"}
}