{
  "type": "Feature",
  "properties": {
    "iso:country":"CH",
    "sg:address":"6986",
    "sg:city":"Curio",
    "sg:orig_category":"Herstellung von sonstigen Maschinen f\u00fcr bestimmte Verwendung",
    "sg:postcode":"6986",
    "sg:province":"Ticino",
    "wof:name":"Mtn Immo Contrade Sa",
    "wof:placetype":"venue"
},
  "geometry": {"coordinates":[8.8608150482,46.0023155212],"type":"Point"}
}