{
  "type": "Feature",
  "properties": {
    "iso:country":"CH",
    "sg:address":"Dorfstrasse 52",
    "sg:city":"Hagendorn",
    "sg:orig_category":"Verlegen von Fliesen U Platten",
    "sg:phone":"+41 41 780 41 74",
    "sg:postcode":"6332",
    "sg:province":"Zug",
    "wof:name":"Oskar Schwager Bodenbel\u00e4ge",
    "wof:placetype":"venue"
},
  "geometry": {"coordinates":[8.4325551987,47.2038230896],"type":"Point"}
}