{
  "type": "Feature",
  "properties": {
    "iso:country":"CH",
    "sg:address":"Eulerstrasse 68",
    "sg:city":"Basel",
    "sg:orig_category":"Ingenieurb\u00fcros Umwelttechnik and \u00d6kologie",
    "sg:phone":"+41 61 271 73 44",
    "sg:postcode":"4051",
    "sg:province":"Basel-Stadt",
    "wof:name":"Carbotech Ag",
    "wof:placetype":"venue"
},
  "geometry": {"coordinates":[7.5783481598,47.5568618774],"type":"Point"}
}