{
  "type": "Feature",
  "properties": {
    "iso:country":"CH",
    "sg:address":"Rue Saint-pierre 18 1700 Fribourg. Postfach",
    "sg:city":"Fribourg",
    "sg:orig_category":"Notariate",
    "sg:phone":"+41 26 323 10 08",
    "sg:postcode":"1701",
    "sg:province":"Fribourg",
    "wof:name":"Philippe Uldry Etude De Notaire",
    "wof:placetype":"venue"
},
  "geometry": {"coordinates":[7.1558661461,46.8040313721],"type":"Point"}
}