{
  "type": "Feature",
  "properties": {
    "iso:country":"CH",
    "sg:address":"Bruggerstrasse 44 5400 Baden. Postfach 1414",
    "sg:city":"Baden",
    "sg:orig_category":"Wirtschaftspr\u00fcfung, Steuerberatung U Treuhand",
    "sg:phone":"+41 56 222 77 84",
    "sg:postcode":"5401",
    "sg:province":"Aargau",
    "wof:name":"Tolotos Ag",
    "wof:placetype":"venue"
},
  "geometry": {"coordinates":[8.3049678802,47.4768829346],"type":"Point"}
}