{
  "type": "Feature",
  "properties": {
    "iso:country":"CH",
    "sg:address":"1040",
    "sg:city":"Echallens",
    "sg:orig_category":"Grosshandel mit lebenden Tieren",
    "sg:postcode":"1040",
    "sg:province":"Vaud",
    "wof:name":"Pittet H.",
    "wof:placetype":"venue"
},
  "geometry": {"coordinates":[6.6343631744,46.6408653259],"type":"Point"}
}