{
  "type": "Feature",
  "properties": {
    "iso:country":"CH",
    "sg:address":"Palazzo Peri Via Ariosto 6",
    "sg:city":"Lugano",
    "sg:orig_category":"Erschliessung von Grundst\u00fccken Kauf U Verkauf von Immobilien auf eigene Rechnung",
    "sg:phone":"+41 32 338 88 99",
    "sg:postcode":"6900",
    "sg:province":"Ticino",
    "wof:name":"Massi Ag",
    "wof:placetype":"venue"
},
  "geometry": {"coordinates":[7.0426301956,47.0200386047],"type":"Point"}
}