{
  "type": "Feature",
  "properties": {
    "iso:country":"CH",
    "sg:address":"Rue Des Casernes 2",
    "sg:city":"Yverdon-les-bains",
    "sg:orig_category":"Museen",
    "sg:phone":"+41 24 426 31 64",
    "sg:postcode":"1400",
    "sg:province":"Vaud",
    "wof:name":"Mus\u00e9e Suisse De La Mode",
    "wof:placetype":"venue"
},
  "geometry": {"coordinates":[6.6373147964,46.7796554565],"type":"Point"}
}