{
  "type": "Feature",
  "properties": {
    "iso:country":"CH",
    "sg:address":"Kolinplatz 8",
    "sg:city":"Zug",
    "sg:classifiers":[
        {
            "category":"Professional",
            "subcategory":"Detective & Security Services",
            "type":"Services"
        }
    ],
    "sg:phone":"+41 41 729 88 77",
    "sg:postcode":"6300",
    "sg:province":"Zug",
    "sg:tags":[
        "customer",
        "information"
    ],
    "wof:name":"Alabusnow Ag",
    "wof:placetype":"venue"
},
  "geometry": {"coordinates":[8.515206,47.166115],"type":"Point"}
}