{
  "type": "Feature",
  "properties": {
    "addr:full":"Campagna Via Alla 2a Lugano Ticino 6900",
    "addr:housenumber":"2a",
    "addr:postcode":"6900",
    "addr:street":"Via Alla",
    "iso:country":"CH",
    "sg:address":"Campagna Via Alla 2a",
    "sg:city":"Lugano",
    "sg:orig_category":"Architektur U Ingenieurb\u00fcros",
    "sg:phone":"+41 18250290",
    "sg:postcode":"6900",
    "sg:province":"Ticino",
    "wof:name":"Gossweiler Ingenieure Ag",
    "wof:placetype":"venue"
},
  "geometry": {"coordinates":[8.622259,47.398727],"type":"Point"}
}