{
  "type": "Feature",
  "properties": {
    "iso:country":"CH",
    "sg:address":"Seestr. 117. 8800 Thalwil. Postfach 3015",
    "sg:city":"Thalwil",
    "sg:orig_category":"Interessenvertretungen",
    "sg:postcode":"8800",
    "sg:province":"Z\u00fcrich",
    "wof:name":"Kreditschutzverein Am Z\u00fcrichsee Und Umgebung.",
    "wof:placetype":"venue"
},
  "geometry": {"coordinates":[8.5688667297,47.2950210571],"type":"Point"}
}