{
  "type": "Feature",
  "properties": {
    "iso:country":"CH",
    "sg:address":"Wydenstrasse 7 5242 Birr-lupfig. Postfach Postfach",
    "sg:city":"Birr",
    "sg:orig_category":"Architektur U Ingenieurb\u00fcros Architekturb\u00fcros",
    "sg:phone":"+41 56 464 40 60",
    "sg:postcode":"5242",
    "sg:province":"Aargau",
    "wof:name":"M\u00fcller Meinrad Architektur Und Bauleitung Ag",
    "wof:placetype":"venue"
},
  "geometry": {"coordinates":[8.202725,47.436172],"type":"Point"}
}