{
  "type": "Feature",
  "properties": {
    "iso:country":"CH",
    "sg:address":"Ch Du Parc 6",
    "sg:city":"Bussigny",
    "sg:classifiers":[
        {
            "category":"Banks & Credit Unions",
            "subcategory":"Bank",
            "type":"Services"
        }
    ],
    "sg:phone":"+41 21 701 17 77",
    "sg:postcode":"1030",
    "sg:province":"Vaud",
    "wof:name":"Banque Vaudoise De Cr\u00e9dit",
    "wof:placetype":"venue"
},
  "geometry": {"coordinates":[6.553318,46.549362],"type":"Point"}
}