{
  "type": "Feature",
  "properties": {
    "iso:country":"CH",
    "sg:address":"Bahnhofstrasse 26",
    "sg:city":"Widnau",
    "sg:orig_category":"Fahrschulen, Flugschulen",
    "sg:phone":"+41 79 697 78 01",
    "sg:postcode":"9443",
    "sg:province":"St. Gallen",
    "wof:name":"Erol Uenveren Autofahrschule",
    "wof:placetype":"venue"
},
  "geometry": {"coordinates":[9.6340513229,47.4059638977],"type":"Point"}
}