{
  "type": "Feature",
  "properties": {
    "iso:country":"CH",
    "sg:address":"6951",
    "sg:city":"Scareglia",
    "sg:orig_category":"Sanit\u00e4rinstallation",
    "sg:phone":"+41 32 913 72 79",
    "sg:postcode":"6951",
    "sg:province":"Ticino",
    "wof:name":"Pierre Sautaux Installation Sanitaire",
    "wof:placetype":"venue"
},
  "geometry": {"coordinates":[6.8179531097,47.0975036621],"type":"Point"}
}