{
  "type": "Feature",
  "properties": {
    "iso:country":"CH",
    "sg:address":"Ambassadorenhof 4500 Solothurn. Postfach",
    "sg:city":"Solothurn",
    "sg:orig_category":"Polizei",
    "sg:phone":"+41 32 627 71 11",
    "sg:postcode":"4502",
    "sg:province":"Solothurn",
    "wof:name":"Polizeikommando Des Kantons Solothurn",
    "wof:placetype":"venue"
},
  "geometry": {"coordinates":[7.5369272232,47.2105407715],"type":"Point"}
}