{
  "type": "Feature",
  "properties": {
    "iso:country":"CH",
    "sg:address":"Mythenquai 386",
    "sg:city":"Z\u00fcrich",
    "sg:orig_category":"Non-Classified Establishments",
    "sg:phone":"+41 32 968 98 48",
    "sg:postcode":"8038",
    "sg:province":"Z\u00fcrich",
    "wof:name":"Panzera Ottavio",
    "wof:placetype":"venue"
},
  "geometry": {"coordinates":[6.8940219879,47.1224403381],"type":"Point"}
}