{
  "type": "Feature",
  "properties": {
    "iso:country":"CH",
    "sg:address":"Rubiana Via 6a",
    "sg:city":"Gentilino",
    "sg:orig_category":"Architektur U Ingenieurb\u00fcros",
    "sg:phone":"+41 91 994 40 78",
    "sg:postcode":"6925",
    "sg:province":"Ticino",
    "wof:name":"Gt Industrial Consulting Di Gosteli Walter",
    "wof:placetype":"venue"
},
  "geometry": {"coordinates":[8.932384,45.991913],"type":"Point"}
}