{
  "type": "Feature",
  "properties": {
    "iso:country":"CH",
    "sg:address":"1185",
    "sg:city":"Mont-sur-rolle",
    "sg:orig_category":"Schulpflegen",
    "sg:postcode":"1185",
    "sg:province":"Vaud",
    "wof:name":"Commission Scolaire De L'\u00e9cole Primaire De Mont-sur-rolle",
    "wof:placetype":"venue"
},
  "geometry": {"coordinates":[6.3379797935,46.4727897644],"type":"Point"}
}