{
  "type": "Feature",
  "properties": {
    "iso:country":"CH",
    "sg:address":"Menn Rue Barth\u00e9lemy- 4",
    "sg:city":"Gen\u00e8ve",
    "sg:orig_category":"Sanit\u00e4r, Heizungs U L\u00fcftungsinstallation",
    "sg:phone":"+41 79 229 48 81",
    "sg:postcode":"1205",
    "sg:province":"Gen\u00e8ve",
    "wof:name":"Sanfer Sa",
    "wof:placetype":"venue"
},
  "geometry": {"coordinates":[6.1440701485,46.1907348633],"type":"Point"}
}