{
  "type": "Feature",
  "properties": {
    "iso:country":"CH",
    "sg:address":"Frutigenstrasse 8",
    "sg:city":"Thun",
    "sg:orig_category":"Sanit\u00e4r U Heizungsinstallation Sanit\u00e4rinstallation",
    "sg:phone":"+41 33 222 67 22",
    "sg:postcode":"3600",
    "sg:province":"Bern",
    "wof:name":"Axima Westschweiz Ag",
    "wof:placetype":"venue"
},
  "geometry": {"coordinates":[7.6289768219,46.7560157776],"type":"Point"}
}