{
  "type": "Feature",
  "properties": {
    "iso:country":"CH",
    "sg:address":"Entenweidstrasse 74",
    "sg:city":"Basel",
    "sg:orig_category":"Antennenbau",
    "sg:phone":"+41 61 383 06 42",
    "sg:postcode":"4056",
    "sg:province":"Basel-Stadt",
    "wof:name":"Dieter Gr\u00fctz Gr\u00fctz Antennentechnik",
    "wof:placetype":"venue"
},
  "geometry": {"coordinates":[7.573946,47.568314],"type":"Point"}
}