{
  "type": "Feature",
  "properties": {
    "iso:country":"CH",
    "sg:address":"Avenue Nestl\u00e9 2",
    "sg:city":"Montreux",
    "sg:orig_category":"Detailhandel mit Waren verschiedener Art, Hauptrichtung Nahrungsmittel Fachdetailhandel mit Nahrungs",
    "sg:phone":"+41 21 963 00 72",
    "sg:postcode":"1820",
    "sg:province":"Vaud",
    "wof:name":"Lina Fuoco Sp\u00e9cialit\u00e9s Italiennes",
    "wof:placetype":"venue"
},
  "geometry": {"coordinates":[6.9125108719,46.4316902161],"type":"Point"}
}