{
  "type": "Feature",
  "properties": {
    "iso:country":"CH",
    "sg:address":"Holzh\u00e4usernstrasse 1",
    "sg:city":"Risch",
    "sg:orig_category":"Unternehmensberatung Wirtschaftspr\u00fcfung, Steuerberatung U Treuhand",
    "sg:phone":"+41 41 790 49 88",
    "sg:postcode":"6343",
    "sg:province":"Zug",
    "wof:name":"Datomar Sp\u00f6rri-treuhand Ag",
    "wof:placetype":"venue"
},
  "geometry": {"coordinates":[8.4425897598,47.1478004456],"type":"Point"}
}