{
  "type": "Feature",
  "properties": {
    "addr:full":"Klybeckstrasse 40 4057 Basel. Postfach Basel Basel-Stadt 4051",
    "addr:housenumber":"40",
    "addr:postcode":"4057;4051",
    "addr:street":"Klybeckstrasse;Postfach",
    "iso:country":"CH",
    "sg:address":"Klybeckstrasse 40 4057 Basel. Postfach",
    "sg:city":"Basel",
    "sg:orig_category":"Detailhandel mit B\u00fcchern, Zeitungen, Schreib U Papeteriewaren",
    "sg:postcode":"4051",
    "sg:province":"Basel-Stadt",
    "wof:name":"Schlup Roland Convenience-store",
    "wof:placetype":"venue"
},
  "geometry": {"coordinates":[7.277455,47.123856],"type":"Point"}
}