{
  "type": "Feature",
  "properties": {
    "iso:country":"CH",
    "sg:address":"Hallerstrasse 23 3012 Bern. Postfach",
    "sg:city":"Bern",
    "sg:orig_category":"Elektroinstallation",
    "sg:phone":"+41 31 302 44 10",
    "sg:postcode":"3001",
    "sg:province":"Bern",
    "wof:name":"Huggenberger E., Elektr. Installationen",
    "wof:placetype":"venue"
},
  "geometry": {"coordinates":[7.4361300468,46.9532241821],"type":"Point"}
}