{
  "type": "Feature",
  "properties": {
    "iso:country":"CH",
    "sg:address":"Hauptstrasse 4 9214 Kradolf. Postfach 11",
    "sg:city":"Kradolf",
    "sg:orig_category":"Galvanische Betriebe",
    "sg:phone":"+41 71 644 90 10",
    "sg:postcode":"9214",
    "sg:province":"Thurgau",
    "wof:name":"Interpars Ag Beschichtungen",
    "wof:placetype":"venue"
},
  "geometry": {"coordinates":[9.2003726959,47.5247802734],"type":"Point"}
}