{
  "type": "Feature",
  "properties": {
    "iso:country":"CH",
    "sg:address":"5732",
    "sg:city":"Zetzwil",
    "sg:orig_category":"Primarschulen",
    "sg:phone":"+41 62 773 26 13",
    "sg:postcode":"5732",
    "sg:province":"Aargau",
    "wof:name":"Primarschule",
    "wof:placetype":"venue"
},
  "geometry": {"coordinates":[8.1611099243,47.2888412476],"type":"Point"}
}