{
  "type": "Feature",
  "properties": {
    "iso:country":"CH",
    "sg:address":"La Pergola",
    "sg:city":"Brusio",
    "sg:orig_category":"Autogaragen",
    "sg:phone":"+41 81 846 52 80",
    "sg:postcode":"7743",
    "sg:province":"Graubunden",
    "wof:name":"Rino Zala Garage",
    "wof:placetype":"venue"
},
  "geometry": {"coordinates":[10.128052,46.251087],"type":"Point"}
}