{
  "type": "Feature",
  "properties": {
    "iso:country":"CH",
    "sg:address":"Grenzstrasse 11",
    "sg:city":"Winterthur",
    "sg:orig_category":"Bauspenglerei Zimmerei, Dachdeckerei, Bauspenglerei U Abdichtung",
    "sg:phone":"+41 79 422 93 77",
    "sg:postcode":"8406",
    "sg:province":"Z\u00fcrich",
    "wof:name":"Schranz Ag, Spenglerei, Heizungen, Sanit\u00e4re Anlagen",
    "wof:placetype":"venue"
},
  "geometry": {"coordinates":[7.26741,46.386864],"type":"Point"}
}