{
  "type": "Feature",
  "properties": {
    "iso:country":"CH",
    "sg:address":"Talstrasse 5",
    "sg:city":"Visp",
    "sg:orig_category":"Landw. Genossenschaften Dresch",
    "sg:postcode":"3930",
    "sg:province":"Valais",
    "wof:name":"Dreschereigenossenschaft Visp & Umgebung",
    "wof:placetype":"venue"
},
  "geometry": {"coordinates":[7.8810601234,46.2856903076],"type":"Point"}
}