{
  "type": "Feature",
  "properties": {
    "iso:country":"CH",
    "sg:address":"6776",
    "sg:city":"Piotta",
    "sg:orig_category":"Herstellung von M\u00f6beln",
    "sg:phone":"+41 91 868 15 89",
    "sg:postcode":"6776",
    "sg:province":"Ticino",
    "wof:name":"Fratelli Gut Sa Fabbrica Serramenti & Mobili",
    "wof:placetype":"venue"
},
  "geometry": {"coordinates":[8.6774301529,46.5127983093],"type":"Point"}
}