{
  "type": "Feature",
  "properties": {
    "iso:country":"CH",
    "sg:address":"Buchserstrasse",
    "sg:city":"Sennwald",
    "sg:orig_category":"Unternehmensberatung",
    "sg:phone":"+41 81 740 31 31",
    "sg:postcode":"9466",
    "sg:province":"St. Gallen",
    "wof:name":"Rms Ag",
    "wof:placetype":"venue"
},
  "geometry": {"coordinates":[9.48554039,47.2047958374],"type":"Point"}
}