{
  "type": "Feature",
  "properties": {
    "iso:country":"CH",
    "sg:address":"Oberdorfstrasse 69",
    "sg:city":"Herisau",
    "sg:orig_category":"Fotografische Ateliers",
    "sg:phone":"+41 71 351 32 44",
    "sg:postcode":"9100",
    "sg:province":"Appenzell Ausserrhoden",
    "wof:name":"Toni K\u00fcng Fotografisches Atelier",
    "wof:placetype":"venue"
},
  "geometry": {"coordinates":[9.2846479416,47.3862571716],"type":"Point"}
}