{
  "type": "Feature",
  "properties": {
    "iso:country":"CH",
    "sg:address":"Pommernweg 7a 8608 Bubikon. Postfach 101",
    "sg:city":"Bubikon",
    "sg:orig_category":"Datenverarbeitungsdienste Wirtschaftspr\u00fcfung, Steuerberatung U Treuhand",
    "sg:phone":"+41 21 960 10 19",
    "sg:postcode":"8608",
    "sg:province":"Z\u00fcrich",
    "wof:name":"Cds Conseils & Gestion Sa",
    "wof:placetype":"venue"
},
  "geometry": {"coordinates":[6.929865,46.393436],"type":"Point"}
}