{
  "type": "Feature",
  "properties": {
    "iso:country":"CH",
    "sg:address":"Egerta 53",
    "sg:city":"Balzers",
    "sg:orig_category":"Zahnarztpraxen",
    "sg:phone":"+41 71 923 13 70",
    "sg:postcode":"9496",
    "wof:name":"Dr. Med. Dent. Stefan Marcec Zahnarzt",
    "wof:placetype":"venue"
},
  "geometry": {"coordinates":[9.0501203537,47.4460296631],"type":"Point"}
}