{
  "type": "Feature",
  "properties": {
    "iso:country":"CH",
    "sg:address":"Libernstrasse 24",
    "sg:city":"Otelfingen",
    "sg:orig_category":"Markt U Meinungsforschung Werbeagenturen",
    "sg:phone":"+41 18473131",
    "sg:postcode":"8112",
    "sg:province":"Z\u00fcrich",
    "wof:name":"Freddy Z\u00e4hner Pms Public Marketing Service",
    "wof:placetype":"venue"
},
  "geometry": {"coordinates":[8.4009981155,47.4587898254],"type":"Point"}
}