{
  "type": "Feature",
  "properties": {
    "iso:country":"CH",
    "sg:address":"Rue Daniel-dardel 13",
    "sg:city":"St-blaise",
    "sg:orig_category":"Wirtschafts- and Arbeitgeberverb\u00e4nde",
    "sg:phone":"+41 22 793 04 67",
    "sg:postcode":"2072",
    "sg:province":"Neuch\u00e2tel",
    "wof:name":"St\u00e9 Suisse De P\u00e9dagogie Musicale,madame Monique Buunk",
    "wof:placetype":"venue"
},
  "geometry": {"coordinates":[6.1152038574,46.1903572083],"type":"Point"}
}