{
  "type": "Feature",
  "properties": {
    "iso:country":"CH",
    "sg:address":"9436 Balgach. Postfach 44",
    "sg:city":"Balgach",
    "sg:orig_category":"Messeorganisationen",
    "sg:phone":"+41 111",
    "sg:postcode":"9436",
    "sg:province":"St. Gallen",
    "wof:name":"Vms Vereinigung Messen Schweiz C/o Olma Messen St. Gallen",
    "wof:placetype":"venue"
},
  "geometry": {"coordinates":[9.3935003281,47.4436607361],"type":"Point"}
}