{
  "type": "Feature",
  "properties": {
    "iso:country":"CH",
    "sg:address":"Untere Hinterlohstrasse 13",
    "sg:city":"Romanshorn",
    "sg:orig_category":"Wohnheime",
    "sg:phone":"+41 71 463 35 66",
    "sg:postcode":"8590",
    "sg:province":"Thurgau",
    "wof:name":"Genossenschaft Alterssiedlung Und Altersheim Romanshorn",
    "wof:placetype":"venue"
},
  "geometry": {"coordinates":[9.3720760345,47.5728569031],"type":"Point"}
}