{
  "type": "Feature",
  "properties": {
    "iso:country":"CH",
    "sg:address":"Im Tal 116",
    "sg:city":"Unterendingen",
    "sg:orig_category":"Sportvereine Motorrad",
    "sg:phone":"+41 56 633 22 22",
    "sg:postcode":"5305",
    "sg:province":"Aargau",
    "wof:name":"Moto-club Reusstal Restaurant Stadtkeller",
    "wof:placetype":"venue"
},
  "geometry": {"coordinates":[8.3425598145,47.3519210815],"type":"Point"}
}