{
  "type": "Feature",
  "properties": {
    "iso:country":"CH",
    "sg:address":"La Tuili\u00e8re 2 1163 Etoy. Postfach",
    "sg:city":"Etoy",
    "sg:orig_category":"Instandhaltung U Reparatur von Automobilen",
    "sg:phone":"+41 21 807 43 95",
    "sg:postcode":"1163",
    "sg:province":"Vaud",
    "wof:name":"Garage Ferreira Batista Garage, Carrosserie",
    "wof:placetype":"venue"
},
  "geometry": {"coordinates":[6.4269108772,46.4763870239],"type":"Point"}
}