{
  "type": "Feature",
  "properties": {
    "iso:country":"CH",
    "sg:address":"Aarbergstrasse 41",
    "sg:city":"Lyss",
    "sg:orig_category":"Grosshandel mit Nahrungsmitteln, Getr\u00e4nken U Tabakwaren ohne ausgepr\u00e4gten Schwerpunkt",
    "sg:phone":"+41 32 384 88 80",
    "sg:postcode":"3250",
    "sg:province":"Bern",
    "wof:name":"Baguette Buffet, Gafner Peter",
    "wof:placetype":"venue"
},
  "geometry": {"coordinates":[7.3031139374,47.0713195801],"type":"Point"}
}