{
  "type": "Feature",
  "properties": {
    "iso:country":"CH",
    "sg:address":"Vieux-moulin Rue Du 14",
    "sg:city":"Onex",
    "sg:orig_category":"Detailhandel mit B\u00fcchern, Zeitungen, Schreib U Papeteriewaren",
    "sg:postcode":"1213",
    "sg:province":"Gen\u00e8ve",
    "wof:name":"Tabacs-journaux, Marino",
    "wof:placetype":"venue"
},
  "geometry": {"coordinates":[6.098979,46.190163],"type":"Point"}
}