{
  "type": "Feature",
  "properties": {
    "iso:country":"CH",
    "sg:address":"G\u00f6thestrasse 22",
    "sg:city":"St\u00e4fa",
    "sg:orig_category":"Detailhandel mit Brot, Back U S\u00fcsswaren",
    "sg:phone":"+41 32 751 22 72",
    "sg:postcode":"8712",
    "sg:province":"Z\u00fcrich",
    "wof:name":"Bruno R\u00fcegger Boulangerie & P\u00e2tisserie",
    "wof:placetype":"venue"
},
  "geometry": {"coordinates":[7.092886,47.063236],"type":"Point"}
}