{
  "type": "Feature",
  "properties": {
    "iso:country":"CH",
    "sg:address":"2612 Cormoret Case Postale 2",
    "sg:city":"Cormoret",
    "sg:orig_category":"Herstellung von Uhren",
    "sg:phone":"+41 32 944 11 14",
    "sg:postcode":"2612",
    "sg:province":"Bern",
    "wof:name":"Nioles Sa",
    "wof:placetype":"venue"
},
  "geometry": {"coordinates":[7.0454897881,47.1705703735],"type":"Point"}
}