{
  "type": "Feature",
  "properties": {
    "iso:country":"CH",
    "sg:address":"Wiesenstrasse 29",
    "sg:city":"Port",
    "sg:orig_category":"Fahrschulen, Flugschulen",
    "sg:phone":"+41 79 301 96 86",
    "sg:postcode":"2562",
    "sg:province":"Bern",
    "wof:name":"Ren\u00e9 Sprecher Autofahrschule",
    "wof:placetype":"venue"
},
  "geometry": {"coordinates":[7.568983078,47.0876655579],"type":"Point"}
}