{
  "type": "Feature",
  "properties": {
    "iso:country":"CH",
    "sg:address":"Hauptstrasse 24",
    "sg:city":"K\u00f6lliken",
    "sg:orig_category":"Detailhandel mit Waren verschiedener Art, Hauptrichtung Nahrungsmittel",
    "sg:phone":"+41 79 633 38 44",
    "sg:postcode":"5742",
    "sg:province":"Aargau",
    "wof:name":"Paul L\u00fcscher Lebensmittel",
    "wof:placetype":"venue"
},
  "geometry": {"coordinates":[8.0243701935,47.3367767334],"type":"Point"}
}