{
  "type": "Feature",
  "properties": {
    "iso:country":"CH",
    "sg:address":"Monnin Rue Abb\u00e9- 15 2854 Bassecourt. Postfach",
    "sg:city":"Bassecourt",
    "sg:orig_category":"Non-Classified Establishments",
    "sg:postcode":"2854",
    "sg:province":"Jura",
    "wof:name":"Electricit\u00e9 Tabourat Sa Entreprise G\u00e9n\u00e9rale D'\u00e9lectricit\u00e9",
    "wof:placetype":"venue"
},
  "geometry": {"coordinates":[7.2463350296,47.3374900818],"type":"Point"}
}