{
  "type": "Feature",
  "properties": {
    "iso:country":"CH",
    "sg:address":"Via Teatro 1",
    "sg:city":"Bellinzona",
    "sg:orig_category":"Detailhandel mit Bekleidung Detailhandel mit Herrenbekleidung",
    "sg:phone":"+41 81 833 18 39",
    "sg:postcode":"6500",
    "sg:province":"Ticino",
    "wof:name":"Caviezel Felicitas",
    "wof:placetype":"venue"
},
  "geometry": {"coordinates":[9.819665,46.485081],"type":"Point"}
}