{
  "type": "Feature",
  "properties": {
    "iso:country":"CH",
    "sg:address":"Gfillweg 2",
    "sg:city":"Rothrist",
    "sg:orig_category":"Gem\u00fcsebau",
    "sg:phone":"+41 62 794 25 55",
    "sg:postcode":"4852",
    "sg:province":"Aargau",
    "wof:name":"Ch. Steffen Gartenbau 4852 Rothrist",
    "wof:placetype":"venue"
},
  "geometry": {"coordinates":[7.8970661163,47.294380188],"type":"Point"}
}