{
  "type": "Feature",
  "properties": {
    "iso:country":"CH",
    "sg:address":"Passwangstrasse 15",
    "sg:city":"Breitenbach",
    "sg:orig_category":"Allgemeiner Hoch U Tiefbau Architekturb\u00fcros",
    "sg:phone":"+41 61 789 98 99",
    "sg:postcode":"4226",
    "sg:province":"Solothurn",
    "wof:name":"Pophaus Ag",
    "wof:placetype":"venue"
},
  "geometry": {"coordinates":[7.543405,47.406849],"type":"Point"}
}