{
  "type": "Feature",
  "properties": {
    "iso:country":"CH",
    "sg:address":"Route Du Pr\u00e9 De L'etang 5",
    "sg:city":"Cormanon",
    "sg:orig_category":"Non-Classified Establishments",
    "sg:postcode":"1752",
    "sg:province":"Fribourg",
    "wof:name":"Karakas & Fran\u00e7ais Sa Bureau D'ing\u00e9nieurs",
    "wof:placetype":"venue"
},
  "geometry": {"coordinates":[7.1141648293,46.7900733948],"type":"Point"}
}