{
  "type": "Feature",
  "properties": {
    "iso:country":"CH",
    "sg:address":"Waldhofstrasse 8",
    "sg:city":"Romanshorn",
    "sg:orig_category":"Landwirtschaft, Jagd U damit verbundene Dienstleistungen",
    "sg:phone":"+41 71 461 19 32",
    "sg:postcode":"8590",
    "sg:province":"Thurgau",
    "wof:name":"Gutsbetrieb Waldhof Ag",
    "wof:placetype":"venue"
},
  "geometry": {"coordinates":[9.3588647842,47.5660133362],"type":"Point"}
}