{
  "type": "Feature",
  "properties": {
    "iso:country":"CH",
    "sg:address":"Weissenaustrasse 72",
    "sg:city":"Unterseen",
    "sg:orig_category":"Zimmerei, Ingenieurholzbau",
    "sg:phone":"+41 55 444 14 25",
    "sg:postcode":"3800",
    "sg:province":"Bern",
    "wof:name":"Alois Ruoss Holzbau",
    "wof:placetype":"venue"
},
  "geometry": {"coordinates":[8.9527902603,47.1751785278],"type":"Point"}
}