{
  "type": "Feature",
  "properties": {
    "iso:country":"CH",
    "sg:address":"Schaffhauserstrasse 56",
    "sg:city":"Winterthur",
    "sg:classifiers":[
        {
            "category":"Restaurant",
            "type":"Food & Drink"
        }
    ],
    "sg:phone":"+41 52 212 25 00",
    "sg:postcode":"8400",
    "sg:province":"Z\u00fcrich",
    "wof:name":"Restaurant Furetto",
    "wof:placetype":"venue"
},
  "geometry": {"coordinates":[8.7216320038,47.5118751526],"type":"Point"}
}