{
  "type": "Feature",
  "properties": {
    "iso:country":"CH",
    "sg:address":"Stuhlegg",
    "sg:city":"Krattigen",
    "sg:orig_category":"Detailhandel mit M\u00f6beln U Haushaltsgegenst\u00e4nden",
    "sg:postcode":"3704",
    "sg:province":"Bern",
    "wof:name":"Kuhnen Margaretha",
    "wof:placetype":"venue"
},
  "geometry": {"coordinates":[7.7185549736,46.6577835083],"type":"Point"}
}