{
  "type": "Feature",
  "properties": {
    "iso:country":"CH",
    "sg:address":"Avenue De Lavaux 50 1009 Pully. Postfach",
    "sg:city":"Pully",
    "sg:orig_category":"Stukkateurgewerbe, Gipserei U Verputzerei Tapeziererei",
    "sg:phone":"+41 21 728 50 51",
    "sg:postcode":"1009",
    "sg:province":"Vaud",
    "wof:name":"Vittorio Scuderi Pl\u00e2trerie & Peinture",
    "wof:placetype":"venue"
},
  "geometry": {"coordinates":[6.6628441811,46.5105667114],"type":"Point"}
}