{
  "type": "Feature",
  "properties": {
    "iso:country":"CH",
    "sg:address":"Landhausstrasse 4d",
    "sg:city":"Baar",
    "sg:orig_category":"Bauschreinerei Herstellung von Konstruktionsteilen, Fertigbauteilen U Ausbauelementen aus Holz",
    "sg:phone":"+41 18440151",
    "sg:postcode":"6340",
    "sg:province":"Zug",
    "wof:name":"Langmeier Ag",
    "wof:placetype":"venue"
},
  "geometry": {"coordinates":[8.428442,47.45858],"type":"Point"}
}