{
  "type": "Feature",
  "properties": {
    "iso:country":"CH",
    "sg:address":"Schulstr. 1",
    "sg:city":"Root",
    "sg:classifiers":[
        {
            "category":"Banks & Credit Unions",
            "subcategory":"Bank",
            "type":"Services"
        }
    ],
    "sg:phone":"+41 41 289 11 11",
    "sg:postcode":"6037",
    "sg:province":"Luzern",
    "wof:name":"Raiffeisenbank Rothenburg",
    "wof:placetype":"venue"
},
  "geometry": {"coordinates":[8.304375,47.049545],"type":"Point"}
}