{
  "type": "Feature",
  "properties": {
    "iso:country":"CH",
    "sg:address":"Wiesenstrasse 17 8008 Z\u00fcrich. Postfach",
    "sg:city":"Z\u00fcrich",
    "sg:orig_category":"Grosshandel mit sonstigen Gebrauchs U Verbrauchsg\u00fctern Grosshandel mit sonstigen Halbwaren",
    "sg:phone":"+41 13819092",
    "sg:postcode":"8034",
    "sg:province":"Z\u00fcrich",
    "wof:name":"Sappi Schweiz Ag",
    "wof:placetype":"venue"
},
  "geometry": {"coordinates":[8.5529594421,47.3625717163],"type":"Point"}
}