{
  "type": "Feature",
  "properties": {
    "iso:country":"CH",
    "sg:address":"Bannholzstrasse 17 9490 Vaduz. Postfach 730",
    "sg:city":"Vaduz",
    "sg:orig_category":"Unternehmensberatung",
    "sg:phone":"+41 61 826 60 60",
    "sg:postcode":"9490",
    "wof:name":"Ramseier Treuhand Ag",
    "wof:placetype":"venue"
},
  "geometry": {"coordinates":[7.705177784,47.5235137939],"type":"Point"}
}