{
  "type": "Feature",
  "properties": {
    "iso:country":"CH",
    "sg:address":"Thunstrasse 24",
    "sg:city":"Bern",
    "sg:orig_category":"Massagestudios",
    "sg:phone":"+41 31 351 63 64",
    "sg:postcode":"3005",
    "sg:province":"Bern",
    "wof:name":"Rolf Henggi Massagen",
    "wof:placetype":"venue"
},
  "geometry": {"coordinates":[7.4541859627,46.9419364929],"type":"Point"}
}