{
  "type": "Feature",
  "properties": {
    "iso:country":"CH",
    "sg:address":"Scherrerstrasse 3",
    "sg:city":"Winterthur",
    "sg:orig_category":"Autospenglereien",
    "sg:phone":"+41 52 233 15 05",
    "sg:postcode":"8400",
    "sg:province":"Z\u00fcrich",
    "wof:name":"Jakob Weder Autok\u00fchler-spenglerei",
    "wof:placetype":"venue"
},
  "geometry": {"coordinates":[8.74208,47.497105],"type":"Point"}
}