{
  "type": "Feature",
  "properties": {
    "iso:country":"CH",
    "sg:address":"Neustadtstrasse 34",
    "sg:city":"Root",
    "sg:orig_category":"Pensionskassen",
    "sg:postcode":"6037",
    "sg:province":"Luzern",
    "wof:name":"Personal-f\u00fcrsorgestiftung Der Fa. Emilio Stecher A.g. Root",
    "wof:placetype":"venue"
},
  "geometry": {"coordinates":[8.3901052475,47.1151390076],"type":"Point"}
}