{
  "type": "Feature",
  "properties": {
    "iso:country":"CH",
    "sg:address":"Rheinstrasse 173",
    "sg:city":"Chur",
    "sg:orig_category":"Grosshandel mit Baumaterialien Grosshandel mit Holz U Baustoffen",
    "sg:phone":"+41 81 253 55 27",
    "sg:postcode":"7000",
    "sg:province":"Graubunden",
    "wof:name":"Bauagentur Gmbh",
    "wof:placetype":"venue"
},
  "geometry": {"coordinates":[9.5145940781,46.8610267639],"type":"Point"}
}