{
  "type": "Feature",
  "properties": {
    "iso:country":"CH",
    "sg:address":"Tschuepis",
    "sg:city":"Zwischenfl\u00fch",
    "sg:orig_category":"G\u00fcterbef\u00f6rderung im Strassenverkehr",
    "sg:phone":"+41 79 311 14 82",
    "sg:postcode":"3756",
    "sg:province":"Bern",
    "wof:name":"Ernst Kneub\u00fchl Transporte",
    "wof:placetype":"venue"
},
  "geometry": {"coordinates":[7.5133800507,46.6063117981],"type":"Point"}
}