{
  "type": "Feature",
  "properties": {
    "iso:country":"CH",
    "sg:address":"Hauptstrasse 33",
    "sg:city":"Unterkulm",
    "sg:orig_category":"Architektur U Ingenieurb\u00fcros",
    "sg:phone":"+41 62 776 23 26",
    "sg:postcode":"5726",
    "sg:province":"Aargau",
    "wof:name":"Ingenieurb\u00fcro Schneiter U. Ibs",
    "wof:placetype":"venue"
},
  "geometry": {"coordinates":[8.114154,47.311127],"type":"Point"}
}