{
  "type": "Feature",
  "properties": {
    "iso:country":"CH",
    "sg:address":"Boulevard Carl-vogt 39 1200 Genf. Postfach",
    "sg:city":"Gen\u00e8ve",
    "sg:orig_category":"RESTAURANTS: TEA-ROOMS",
    "sg:postcode":"1201",
    "sg:province":"Gen\u00e8ve",
    "wof:name":"Zhou S\u00e0rl",
    "wof:placetype":"venue"
},
  "geometry": {"coordinates":[6.1339201927,46.1992721558],"type":"Point"}
}