{
  "type": "Feature",
  "properties": {
    "iso:country":"CH",
    "sg:address":"Ribimattweg 6",
    "sg:city":"Biberist",
    "sg:orig_category":"Maler U Glasergewerbe Malerei",
    "sg:phone":"+41 32 672 35 84",
    "sg:postcode":"4562",
    "sg:province":"Solothurn",
    "wof:name":"Malerei Hubler Gmbh",
    "wof:placetype":"venue"
},
  "geometry": {"coordinates":[7.557079792,47.1797561646],"type":"Point"}
}