{
  "type": "Feature",
  "properties": {
    "addr:full":"Lindenhofstrasse 12 Worblaufen Bern 3048",
    "addr:housenumber":"12",
    "addr:postcode":"3048",
    "addr:street":"Lindenhofstrasse",
    "iso:country":"CH",
    "sg:address":"Lindenhofstrasse 12",
    "sg:city":"Worblaufen",
    "sg:orig_category":"Arztpraxen",
    "sg:phone":"+41 56 225 22 22",
    "sg:postcode":"3048",
    "sg:province":"Bern",
    "wof:name":"Dr.med.urs Sch\u00e4rer Arzt F.allgemeine Medizin Fmh",
    "wof:placetype":"venue"
},
  "geometry": {"coordinates":[8.248344,47.463066],"type":"Point"}
}