{
  "type": "Feature",
  "properties": {
    "iso:country":"CH",
    "sg:address":"Feld",
    "sg:city":"Altb\u00fcron",
    "sg:orig_category":"Sportvereine Turnen Vereine Damen",
    "sg:phone":"+41 62 927 20 55",
    "sg:postcode":"6147",
    "sg:province":"Luzern",
    "wof:name":"Damenriege Stv Altb\u00fcron",
    "wof:placetype":"venue"
},
  "geometry": {"coordinates":[7.8698348999,47.1902923584],"type":"Point"}
}