{
  "type": "Feature",
  "properties": {
    "iso:country":"CH",
    "sg:address":"B\u00fchl",
    "sg:city":"M\u00fcswangen",
    "sg:orig_category":"Haltung von Schweinen",
    "sg:phone":"+41 41 917 27 04",
    "sg:postcode":"6289",
    "sg:province":"Luzern",
    "wof:name":"Albert Koch Schweinezucht",
    "wof:placetype":"venue"
},
  "geometry": {"coordinates":[8.2877197266,47.2399406433],"type":"Point"}
}