{
  "type": "Feature",
  "properties": {
    "iso:country":"CH",
    "sg:address":"Lichterswil",
    "sg:city":"Bowil",
    "sg:orig_category":"Non-Classified Establishments",
    "sg:postcode":"3533",
    "sg:province":"Bern",
    "wof:name":"Hanspeter W\u00fcthrich Hpwtec",
    "wof:placetype":"venue"
},
  "geometry": {"coordinates":[7.706964016,46.9046287537],"type":"Point"}
}