{
  "type": "Feature",
  "properties": {
    "iso:country":"CH",
    "sg:address":"Villereuse Rue De 6 1207 Gen\u00e8ve. Postfach",
    "sg:city":"Gen\u00e8ve",
    "sg:orig_category":"Detailhandel mit M\u00f6beln U Haushaltsgegenst\u00e4nden",
    "sg:postcode":"1207",
    "sg:province":"Gen\u00e8ve",
    "wof:name":"Mar\u00e9chal Claude",
    "wof:placetype":"venue"
},
  "geometry": {"coordinates":[6.1579680443,46.2001190186],"type":"Point"}
}