{
  "type": "Feature",
  "properties": {
    "iso:country":"CH",
    "sg:address":"Favre Via 8",
    "sg:city":"Balerna",
    "sg:orig_category":"Grosshandel mit Getreide, Saatgut U Futtermitteln",
    "sg:phone":"+41 71 311 11 85",
    "sg:postcode":"6828",
    "sg:province":"Ticino",
    "wof:name":"Roos Gmbh",
    "wof:placetype":"venue"
},
  "geometry": {"coordinates":[9.303440094,47.404624939],"type":"Point"}
}