{
  "type": "Feature",
  "properties": {
    "iso:country":"CH",
    "sg:address":"Birmensdorferstrasse 586",
    "sg:city":"Z\u00fcrich",
    "sg:orig_category":"Stukkateurgewerbe, Gipserei U Verputzerei",
    "sg:phone":"+41 14512240",
    "sg:postcode":"8055",
    "sg:province":"Z\u00fcrich",
    "wof:name":"Longa + Sohn Ag",
    "wof:placetype":"venue"
},
  "geometry": {"coordinates":[8.4899921417,47.3675346375],"type":"Point"}
}