{
  "type": "Feature",
  "properties": {
    "iso:country":"CH",
    "sg:address":"Itzikon",
    "sg:city":"Gr\u00fcningen",
    "sg:orig_category":"Non-Classified Establishments",
    "sg:phone":"+41 19352226",
    "sg:postcode":"8627",
    "sg:province":"Z\u00fcrich",
    "wof:name":"Gadola Holding Ag",
    "wof:placetype":"venue"
},
  "geometry": {"coordinates":[8.7636547089,47.2795066833],"type":"Point"}
}