{
  "type": "Feature",
  "properties": {
    "iso:country":"CH",
    "sg:address":"Eptingerstrasse 41",
    "sg:city":"Muttenz",
    "sg:orig_category":"Architektur U Ingenieurb\u00fcros",
    "sg:phone":"+41 61 465 15 15",
    "sg:postcode":"4132",
    "sg:province":"Basel-Landschaft",
    "wof:name":"Hans Meyer Engineering Ag Industrieautomation",
    "wof:placetype":"venue"
},
  "geometry": {"coordinates":[7.653292,47.527931],"type":"Point"}
}