{
  "type": "Feature",
  "properties": {
    "iso:country":"CH",
    "sg:address":"Aarauerstrasse 1",
    "sg:city":"Reinach",
    "sg:orig_category":"Sheet Metal Testing Machines",
    "sg:phone":"+41 62 771 17 16",
    "sg:postcode":"5734",
    "sg:province":"Aargau",
    "wof:name":"Paul Haessig & Co",
    "wof:placetype":"venue"
},
  "geometry": {"coordinates":[8.1795721054,47.2582473755],"type":"Point"}
}