{
  "type": "Feature",
  "properties": {
    "addr:full":"Emmerstrasse 21 Glattfelden Z\u00fcrich 8192",
    "addr:housenumber":"21",
    "addr:postcode":"8192",
    "addr:street":"Emmerstrasse",
    "iso:country":"CH",
    "sg:address":"Emmerstrasse 21",
    "sg:city":"Glattfelden",
    "sg:orig_category":"Datenverarbeitungsdienste",
    "sg:phone":"+41 18673488",
    "sg:postcode":"8192",
    "sg:province":"Z\u00fcrich",
    "wof:name":"Ataris Ag Dienstl. Im Informatiksektor Usw",
    "wof:placetype":"venue"
},
  "geometry": {"coordinates":[8.503307,47.556793],"type":"Point"}
}