{
  "type": "Feature",
  "properties": {
    "iso:country":"CH",
    "sg:address":"9606",
    "sg:city":"B\u00fctschwil",
    "sg:orig_category":"Schulpflegen",
    "sg:phone":"+41 18443384",
    "sg:postcode":"9606",
    "sg:province":"St. Gallen",
    "wof:name":"Schulpflege Der Gemeinden D\u00e4nikon & H\u00fcttikon",
    "wof:placetype":"venue"
},
  "geometry": {"coordinates":[8.4047002792,47.4435386658],"type":"Point"}
}