{
  "type": "Feature",
  "properties": {
    "iso:country":"CH",
    "sg:address":"Badstubenstrasse 9",
    "sg:city":"Walenstadt",
    "sg:orig_category":"Architektur U Ingenieurb\u00fcros",
    "sg:postcode":"8880",
    "sg:province":"St. Gallen",
    "wof:name":"Kurath Bauberatung Gmbh",
    "wof:placetype":"venue"
},
  "geometry": {"coordinates":[9.313285,47.123558],"type":"Point"}
}