{
  "type": "Feature",
  "properties": {
    "iso:country":"CH",
    "sg:address":"Eschikon 22",
    "sg:city":"Lindau",
    "sg:orig_category":"Vereine Gesang",
    "sg:phone":"+41 71 931 32 51",
    "sg:postcode":"8315",
    "sg:province":"Z\u00fcrich",
    "wof:name":"M\u00e4nnerchor Kirchberg",
    "wof:placetype":"venue"
},
  "geometry": {"coordinates":[7.5844497681,47.0851783752],"type":"Point"}
}