{
  "type": "Feature",
  "properties": {
    "iso:country":"CH",
    "sg:address":"Chemin Des Polonais 30",
    "sg:city":"Cortaillod",
    "sg:orig_category":"Allgemeiner Hoch U Tiefbau Maurerarbeiten",
    "sg:phone":"+41 32 842 13 58",
    "sg:postcode":"2016",
    "sg:province":"Neuch\u00e2tel",
    "wof:name":"Spinedi Sa",
    "wof:placetype":"venue"
},
  "geometry": {"coordinates":[6.846274,46.947136],"type":"Point"}
}