{
  "type": "Feature",
  "properties": {
    "iso:country":"CH",
    "sg:address":"Simplon Rue Du 14",
    "sg:city":"Martigny",
    "sg:orig_category":"Non-Classified Establishments",
    "sg:phone":"+41 27 722 38 22",
    "sg:postcode":"1920",
    "sg:province":"Valais",
    "wof:name":"Tina Sa",
    "wof:placetype":"venue"
},
  "geometry": {"coordinates":[7.0771479607,46.1022529602],"type":"Point"}
}