{
  "type": "Feature",
  "properties": {
    "iso:country":"CH",
    "sg:address":"1666",
    "sg:city":"Grandvillard",
    "sg:orig_category":"Detailhandel mit Waren verschiedener Art, Hauptrichtung Nahrungsmittel",
    "sg:postcode":"1666",
    "sg:province":"Fribourg",
    "wof:name":"Soci\u00e9t\u00e9 Coop\u00e9rative De Consommation De Grandvillard",
    "wof:placetype":"venue"
},
  "geometry": {"coordinates":[7.0855789185,46.5394859314],"type":"Point"}
}