{
  "type": "Feature",
  "properties": {
    "addr:full":"Steinacker Str. 47 Urdorf Z\u00fcrich 8902",
    "addr:housenumber":"47",
    "addr:postcode":"8902",
    "addr:street":"Steinacker Str.",
    "iso:country":"CH",
    "sg:address":"Steinacker Str. 47",
    "sg:city":"Urdorf",
    "sg:classifiers":[
        {
            "category":"Professional",
            "subcategory":"Business Services",
            "type":"Services"
        }
    ],
    "sg:phone":"+41 4117641048",
    "sg:postcode":"8902",
    "sg:province":"Z\u00fcrich",
    "sg:tags":[
        "information",
        "advice",
        "technology",
        "software"
    ],
    "wof:name":"Up Trend Ag",
    "wof:placetype":"venue"
},
  "geometry": {"coordinates":[8.531481,47.226246],"type":"Point"}
}