{
  "type": "Feature",
  "properties": {
    "iso:country":"CH",
    "sg:address":"Funkstrasse 122/601 3084 Wabern. Postfach",
    "sg:city":"Wabern",
    "sg:orig_category":"Fernmeldedienste",
    "sg:phone":"+41 31 961 70 58",
    "sg:postcode":"3084",
    "sg:province":"Bern",
    "wof:name":"Nettach Telekommunikation Smith",
    "wof:placetype":"venue"
},
  "geometry": {"coordinates":[7.4437708855,46.9306259155],"type":"Point"}
}