{
  "type": "Feature",
  "properties": {
    "iso:country":"CH",
    "sg:address":"Aubrigstrasse 21",
    "sg:city":"Thalwil",
    "sg:orig_category":"Sonstige mit der Informatik verbundene T\u00e4tigkeiten",
    "sg:postcode":"8800",
    "sg:province":"Z\u00fcrich",
    "wof:name":"Edv-beratung Kraushofer",
    "wof:placetype":"venue"
},
  "geometry": {"coordinates":[8.5675859451,47.2866744995],"type":"Point"}
}