{
  "type": "Feature",
  "properties": {
    "iso:country":"CH",
    "sg:address":"Froburgstrasse 9 4600 Olten. Postfach",
    "sg:city":"Olten",
    "sg:classifiers":[
        {
            "category":"Professional",
            "subcategory":"Employment Agencies",
            "type":"Services"
        }
    ],
    "sg:phone":"+41 62 207 06 06",
    "sg:postcode":"4600",
    "sg:province":"Solothurn",
    "sg:tags":[
        "personal",
        "u",
        "stellenvermittlung"
    ],
    "wof:name":"Planova Human Capital Ag Personal; Ausleihen, Vermitteln",
    "wof:placetype":"venue"
},
  "geometry": {"coordinates":[7.9039731026,47.351978302],"type":"Point"}
}