{
  "type": "Feature",
  "properties": {
    "iso:country":"CH",
    "sg:address":"Dorf",
    "sg:city":"Oey",
    "sg:orig_category":"G\u00fcterbef\u00f6rderung im Strassenverkehr",
    "sg:phone":"+41 79 340 95 26",
    "sg:postcode":"3753",
    "sg:province":"Bern",
    "wof:name":"Jakob Kernen",
    "wof:placetype":"venue"
},
  "geometry": {"coordinates":[7.5777101517,46.6608657837],"type":"Point"}
}