{
  "type": "Feature",
  "properties": {
    "iso:country":"CH",
    "sg:address":"Dorfstr. 3",
    "sg:city":"Leukerbad",
    "sg:classifiers":[
        {
            "category":"Banks & Credit Unions",
            "subcategory":"Bank",
            "type":"Services"
        }
    ],
    "sg:phone":"+41 27 472 78 00",
    "sg:postcode":"3954",
    "sg:province":"Valais",
    "wof:name":"Schweiz. Bankgesellschaft",
    "wof:placetype":"venue"
},
  "geometry": {"coordinates":[7.628073,46.380013],"type":"Point"}
}