{
  "type": "Feature",
  "properties": {
    "iso:country":"CH",
    "sg:address":"Lindackerweg 5 4411 Seltisberg. Postfach",
    "sg:city":"Seltisberg",
    "sg:orig_category":"Grosshandel mit Erzen U Metallen",
    "sg:phone":"+41 79 311 99 49",
    "sg:postcode":"4411",
    "sg:province":"Basel-Landschaft",
    "wof:name":"Ajb Trading Ag",
    "wof:placetype":"venue"
},
  "geometry": {"coordinates":[7.7215538025,47.4632339478],"type":"Point"}
}