{
  "type": "Feature",
  "properties": {
    "iso:country":"CH",
    "sg:address":"Perr\u00e9ard Rue Fran\u00e7ois 18",
    "sg:city":"Ch\u00eane-bourg",
    "sg:orig_category":"Detailhandel mit elektrischen Haushalts-,Radio U Fernsehger\u00e4ten sowie Musikinstrumenten",
    "sg:phone":"+41 22 348 87 26",
    "sg:postcode":"1225",
    "sg:province":"Gen\u00e8ve",
    "wof:name":"Corrado S\u00e0rl",
    "wof:placetype":"venue"
},
  "geometry": {"coordinates":[6.1933951378,46.1949615479],"type":"Point"}
}