{
  "type": "Feature",
  "properties": {
    "iso:country":"CH",
    "sg:address":"Itingerstrasse 4",
    "sg:city":"Sissach",
    "sg:orig_category":"Zahnarztpraxen",
    "sg:phone":"+41 61 971 48 90",
    "sg:postcode":"4450",
    "sg:province":"Basel-Landschaft",
    "wof:name":"Dr.med.dent.christian G\u00fcrtler Zahnarzt",
    "wof:placetype":"venue"
},
  "geometry": {"coordinates":[7.8085608482,47.4624977112],"type":"Point"}
}