{
  "type": "Feature",
  "properties": {
    "iso:country":"CH",
    "sg:address":"Grafenau 12",
    "sg:city":"Zug",
    "sg:classifiers":[
        {
            "category":"Manufacturing",
            "subcategory":"Chemicals & Compounds",
            "type":"Manufacturing & Wholesale Goods"
        }
    ],
    "sg:phone":"+41 41 729 25 11",
    "sg:postcode":"6301",
    "sg:province":"Zug",
    "sg:tags":[
        "pharmaceutical",
        "-",
        "cosmetic",
        "pharmacy",
        "chemistry",
        "by-product"
    ],
    "wof:name":"Lever Faberge Gmbh",
    "wof:placetype":"venue"
},
  "geometry": {"coordinates":[8.51193,47.174255],"type":"Point"}
}