{
  "type": "Feature",
  "properties": {
    "iso:country":"CH",
    "sg:address":"Bettlachstrasse 20",
    "sg:city":"Grenchen",
    "sg:orig_category":"Non-Classified Establishments",
    "sg:postcode":"2540",
    "sg:province":"Solothurn",
    "wof:name":"Familia Eigenheimbau Architektur + Generalbau Gmbh",
    "wof:placetype":"venue"
},
  "geometry": {"coordinates":[7.3974637985,47.1928710938],"type":"Point"}
}