{
  "type": "Feature",
  "properties": {
    "iso:country":"CH",
    "sg:address":"Via Soldini 37a",
    "sg:city":"Chiasso",
    "sg:orig_category":"Detailhandel mit Schreib U Papeteriewaren Grosshandel mit B\u00fcromaschinen U einrichtungen",
    "sg:phone":"+41 55 410 26 12",
    "sg:postcode":"6830",
    "sg:province":"Ticino",
    "wof:name":"B\u00fcro Adam, Inhaber Nydegger Ernst",
    "wof:placetype":"venue"
},
  "geometry": {"coordinates":[8.7962093353,47.2026023865],"type":"Point"}
}