{
  "type": "Feature",
  "properties": {
    "iso:country":"CH",
    "sg:address":"Birmensdorferstrasse 511",
    "sg:city":"Z\u00fcrich",
    "sg:orig_category":"Softwareentwicklung U beratung",
    "sg:postcode":"8055",
    "sg:province":"Z\u00fcrich",
    "wof:name":"Wahl Financial Software Consulting Finanz-software; Beratung",
    "wof:placetype":"venue"
},
  "geometry": {"coordinates":[8.4947843552,47.3675422668],"type":"Point"}
}