{
  "type": "Feature",
  "properties": {
    "iso:country":"CH",
    "sg:address":"Marktstrasse 14",
    "sg:city":"Frauenfeld",
    "sg:orig_category":"Bezirks, Sekundar, Realschulen, Oberstufe der Primarschulen",
    "sg:phone":"+41 71 277 34 15",
    "sg:postcode":"8500",
    "sg:province":"Thurgau",
    "wof:name":"Oberstufenzentrum Sch\u00f6nau",
    "wof:placetype":"venue"
},
  "geometry": {"coordinates":[9.347791,47.417107],"type":"Point"}
}