{
  "type": "Feature",
  "properties": {
    "iso:country":"CH",
    "sg:address":"Kiesweg 10 3904 Naters. Postfach 731",
    "sg:city":"Brig",
    "sg:orig_category":"Grosshandel mit Eisenwaren sowie Installationsbedarf f\u00fcr Gas, Wasser U Heizung Grosshandel mit Holz ",
    "sg:phone":"+41 27 922 20 41",
    "sg:postcode":"3900",
    "sg:province":"Valais",
    "wof:name":"Zen-ruffinen & Co Baumaterialien-sanit.apparate",
    "wof:placetype":"venue"
},
  "geometry": {"coordinates":[7.9799418449,46.3190727234],"type":"Point"}
}