{
  "type": "Feature",
  "properties": {
    "iso:country":"CH",
    "sg:address":"Stadtbachstrasse 5",
    "sg:city":"Baden",
    "sg:orig_category":"Maler U Glasergewerbe",
    "sg:phone":"+41 56 222 74 85",
    "sg:postcode":"5400",
    "sg:province":"Aargau",
    "wof:name":"Max Berger",
    "wof:placetype":"venue"
},
  "geometry": {"coordinates":[8.2991638184,47.4693641663],"type":"Point"}
}