{
  "type": "Feature",
  "properties": {
    "iso:country":"CH",
    "sg:address":"Via Al Ronchetto 3b",
    "sg:city":"Lugano",
    "sg:orig_category":"Technische, physikalische U chemische Untersuchung",
    "sg:postcode":"6900",
    "sg:province":"Ticino",
    "wof:name":"Poma Marcon & Bernasconi Societ\u00e0 Di Controllo Case",
    "wof:placetype":"venue"
},
  "geometry": {"coordinates":[8.9556713104,46.0181465149],"type":"Point"}
}