{
  "type": "Feature",
  "properties": {
    "iso:country":"CH",
    "sg:address":"St\u00fcdliweg 8",
    "sg:city":"Z\u00fcrich",
    "sg:orig_category":"Sonstige mit der Informatik verbundene T\u00e4tigkeiten",
    "sg:phone":"+41 12411981",
    "sg:postcode":"8004",
    "sg:province":"Z\u00fcrich",
    "wof:name":"Datakob Gmbh Edv-dienstleistungen",
    "wof:placetype":"venue"
},
  "geometry": {"coordinates":[8.5183124542,47.3803749084],"type":"Point"}
}