{
  "type": "Feature",
  "properties": {
    "iso:country":"CH",
    "sg:address":"Fusion Avenue De La 64",
    "sg:city":"Martigny",
    "sg:orig_category":"RESTAURANTS: TEA-ROOMS",
    "sg:postcode":"1920",
    "sg:province":"Valais",
    "wof:name":"H\u00f4tel Suisse, Ch\u00e2telard (valais) Sa",
    "wof:placetype":"venue"
},
  "geometry": {"coordinates":[7.0729198456,46.1013793945],"type":"Point"}
}