{
  "type": "Feature",
  "properties": {
    "addr:full":"Hauptstrasse 28 Guntershausen Thurgau 8357",
    "addr:housenumber":"28",
    "addr:postcode":"8357",
    "addr:street":"Hauptstrasse",
    "iso:country":"CH",
    "sg:address":"Hauptstrasse 28",
    "sg:city":"Guntershausen",
    "sg:orig_category":"Allgemeiner Hoch U Tiefbau Hoch U Tiefbau",
    "sg:phone":"+41 52 365 14 10",
    "sg:postcode":"8357",
    "sg:province":"Thurgau",
    "wof:name":"Hasler Hans & Cie",
    "wof:placetype":"venue"
},
  "geometry": {"coordinates":[8.913971,47.476524],"type":"Point"}
}