{
  "type": "Feature",
  "properties": {
    "iso:country":"CH",
    "sg:address":"Klosbachstrasse 5",
    "sg:city":"Z\u00fcrich",
    "sg:orig_category":"Innendekorationsateliers",
    "sg:phone":"+41 32 751 45 79",
    "sg:postcode":"8032",
    "sg:province":"Z\u00fcrich",
    "wof:name":"C\u00e9dric Zanini D\u00e9corateur D'int\u00e9rieur",
    "wof:placetype":"venue"
},
  "geometry": {"coordinates":[7.0626749992,47.0553092957],"type":"Point"}
}