{
  "type": "Feature",
  "properties": {
    "iso:country":"CH",
    "sg:address":"Seetalstrasse 1",
    "sg:city":"Schafisheim",
    "sg:orig_category":"Instandhaltung U Reparatur von Automobilen",
    "sg:phone":"+41 52 315 19 40",
    "sg:postcode":"5503",
    "sg:province":"Aargau",
    "wof:name":"G\u00fclle Autospritzwerk",
    "wof:placetype":"venue"
},
  "geometry": {"coordinates":[8.6812343597,47.5417976379],"type":"Point"}
}