{
  "type": "Feature",
  "properties": {
    "iso:country":"CH",
    "sg:address":"Pavillonweg 14",
    "sg:city":"Bern",
    "sg:orig_category":"Grosshandel mit Altmaterial U Reststoffen Grosshandel mit Erzen U Metallen",
    "sg:phone":"+41 31 308 03 09",
    "sg:postcode":"3012",
    "sg:province":"Bern",
    "wof:name":"Cemetal Sa Waren, Bes. Rohstoffe, Metalle, Schrotte Usw.; Handel",
    "wof:placetype":"venue"
},
  "geometry": {"coordinates":[7.4332408905,46.9494552612],"type":"Point"}
}