{
  "type": "Feature",
  "properties": {
    "iso:country":"CH",
    "sg:address":"Chemin Des Pralets 37",
    "sg:city":"Belmont-lausanne",
    "sg:orig_category":"Non-Classified Establishments",
    "sg:postcode":"1092",
    "sg:province":"Vaud",
    "wof:name":"Moltan Holding Ag Beteiligungen Usw.",
    "wof:placetype":"venue"
},
  "geometry": {"coordinates":[7.7882928848,47.2176361084],"type":"Point"}
}