{
  "type": "Feature",
  "properties": {
    "iso:country":"CH",
    "sg:address":"Zelglistrasse 62 8122 Binz. Postfach",
    "sg:city":"Binz",
    "sg:orig_category":"Interessenvertretungen",
    "sg:postcode":"8122",
    "sg:province":"Z\u00fcrich",
    "wof:name":"Attinger Ursula-stiftung Krippen, Ostereiersammlung Von Hilke Ehlers Usw.; Finanzierung",
    "wof:placetype":"venue"
},
  "geometry": {"coordinates":[8.6238918304,47.357421875],"type":"Point"}
}