{
  "type": "Feature",
  "properties": {
    "iso:country":"CH",
    "sg:address":"Badenerstrasse 329",
    "sg:city":"Z\u00fcrich",
    "sg:classifiers":[
        {
            "category":"Autos & Motor Vehicles",
            "subcategory":"Fuel & Gas Station",
            "type":"Retail Goods"
        }
    ],
    "sg:phone":"+41 14981616",
    "sg:postcode":"8003",
    "sg:province":"Z\u00fcrich",
    "sg:tags":[
        "engine",
        "petrol",
        "turbine",
        "diesel"
    ],
    "wof:name":"B\u00fcrke Ag",
    "wof:placetype":"venue"
},
  "geometry": {"coordinates":[8.5116081238,47.3776473999],"type":"Point"}
}