{
  "type": "Feature",
  "properties": {
    "iso:country":"CH",
    "sg:address":"Neulandweg 3",
    "sg:city":"Hunzenschwil",
    "sg:orig_category":"Softwareentwicklung U beratung",
    "sg:phone":"+41 81 834 87 00",
    "sg:postcode":"5502",
    "sg:province":"Aargau",
    "wof:name":"Multimedia Touristik Design Gmbh",
    "wof:placetype":"venue"
},
  "geometry": {"coordinates":[9.8368577957,46.4951477051],"type":"Point"}
}