{
  "type": "Feature",
  "properties": {
    "iso:country":"CH",
    "sg:address":"5632",
    "sg:city":"Buttwil",
    "sg:classifiers":[
        {
            "category":"Restaurant",
            "type":"Food & Drink"
        }
    ],
    "sg:phone":"+41 56 664 43 80",
    "sg:postcode":"5632",
    "sg:province":"Aargau",
    "wof:name":"Restaurant Flugplatz",
    "wof:placetype":"venue"
},
  "geometry": {"coordinates":[8.2976503372,47.2720603943],"type":"Point"}
}