{
  "type": "Feature",
  "properties": {
    "iso:country":"CH",
    "sg:address":"Albisriederstrasse 96",
    "sg:city":"Z\u00fcrich",
    "sg:orig_category":"Kinderkrippen U horte",
    "sg:postcode":"8003",
    "sg:province":"Z\u00fcrich",
    "wof:name":"Hort Des Schulamtes Der Stadt Z\u00fcrich",
    "wof:placetype":"venue"
},
  "geometry": {"coordinates":[8.5037250519,47.3783607483],"type":"Point"}
}