{
  "type": "Feature",
  "properties": {
    "iso:country":"CH",
    "sg:address":"Berntorstrasse 10 4500 Solothurn. Postfach 227",
    "sg:city":"Solothurn",
    "sg:orig_category":"Interessenvertretungen U sonstige Vereinigungen Organisationen der Wohlfahrtspflege",
    "sg:phone":"+41 32 622 30 80",
    "sg:postcode":"4501",
    "sg:province":"Solothurn",
    "wof:name":"Caritas Solothurn",
    "wof:placetype":"venue"
},
  "geometry": {"coordinates":[7.5361499786,47.2047996521],"type":"Point"}
}