{
  "type": "Feature",
  "properties": {
    "iso:country":"CH",
    "sg:address":"Lindenweg 1",
    "sg:city":"Vilters",
    "sg:orig_category":"Stukkateurgewerbe, Gipserei U Verputzerei",
    "sg:postcode":"7324",
    "sg:province":"St. Gallen",
    "wof:name":"Mantello Cosimo",
    "wof:placetype":"venue"
},
  "geometry": {"coordinates":[9.4499902725,47.0245742798],"type":"Point"}
}