{
  "type": "Feature",
  "properties": {
    "iso:country":"CH",
    "sg:address":"Bleicherweg 45",
    "sg:city":"Z\u00fcrich",
    "sg:orig_category":"Unclassifiable Establishments",
    "sg:phone":"+41 12017600",
    "sg:postcode":"8002",
    "sg:province":"Z\u00fcrich",
    "wof:name":"Globix Ag",
    "wof:placetype":"venue"
},
  "geometry": {"coordinates":[8.5327377319,47.3660202026],"type":"Point"}
}