{
  "type": "Feature",
  "properties": {
    "iso:country":"CH",
    "sg:address":"Bahnhofstrasse 43",
    "sg:city":"G\u00fcmligen",
    "sg:orig_category":"Alters U Pflegeheime Wohnheime",
    "sg:phone":"+41 31 951 09 53",
    "sg:postcode":"3073",
    "sg:province":"Bern",
    "wof:name":"Alterswohnheim G\u00fcmligen",
    "wof:placetype":"venue"
},
  "geometry": {"coordinates":[7.505785,46.935013],"type":"Point"}
}