{
  "type": "Feature",
  "properties": {
    "iso:country":"CH",
    "sg:address":"Bernstr. 16",
    "sg:city":"Fraubrunnen",
    "sg:classifiers":[
        {
            "category":"Banks & Credit Unions",
            "subcategory":"Bank",
            "type":"Services"
        }
    ],
    "sg:phone":"+41 31 760 17 17",
    "sg:postcode":"3312",
    "sg:province":"Bern",
    "wof:name":"Raiffeisenbank Fraubrunnen",
    "wof:placetype":"venue"
},
  "geometry": {"coordinates":[7.524559,47.084892],"type":"Point"}
}