{
  "type": "Feature",
  "properties": {
    "iso:country":"CH",
    "sg:address":"Olivier Avenue Juste- 5",
    "sg:city":"Lausanne",
    "sg:orig_category":"Fachdetailhandel mit pharmazeutischen Produkten",
    "sg:phone":"+41 27 722 20 05",
    "sg:postcode":"1006",
    "sg:province":"Vaud",
    "wof:name":"Pharmacie Lauber, Lauber Philippe Lauber Successeur",
    "wof:placetype":"venue"
},
  "geometry": {"coordinates":[7.0741028786,46.102432251],"type":"Point"}
}