{
  "type": "Feature",
  "properties": {
    "iso:country":"CH",
    "sg:address":"Chemin Du Muveran 7 1000 Lausanne. Postfach",
    "sg:city":"Lausanne",
    "sg:orig_category":"Softwareentwicklung U beratung",
    "sg:postcode":"1002",
    "sg:province":"Vaud",
    "wof:name":"Spice Tech Leroy",
    "wof:placetype":"venue"
},
  "geometry": {"coordinates":[6.6467700005,46.5237350464],"type":"Point"}
}