{
  "type": "Feature",
  "properties": {
    "iso:country":"CH",
    "sg:address":"Rue Du Patinage 21",
    "sg:city":"Fleurier",
    "sg:orig_category":"Zahnarztpraxen",
    "sg:phone":"+41 21 922 84 60",
    "sg:postcode":"2114",
    "sg:province":"Neuch\u00e2tel",
    "wof:name":"Drs M\u00e9d. Dent. B. & I. Holtz M\u00e9decins-dentistes",
    "wof:placetype":"venue"
},
  "geometry": {"coordinates":[5.1808700562,45.8973388672],"type":"Point"}
}