{
  "type": "Feature",
  "properties": {
    "iso:country":"CH",
    "sg:address":"Rue Du Valentin 2",
    "sg:city":"Yverdon-les-bains",
    "sg:classifiers":[
        {
            "category":"Bars & Pubs",
            "type":"Food & Drink"
        }
    ],
    "sg:phone":"+41 24 425 30 42",
    "sg:postcode":"1400",
    "sg:province":"Vaud",
    "sg:tags":[
        "restaurant"
    ],
    "wof:name":"Restaurant & Bar Le Coq D'or",
    "wof:placetype":"venue"
},
  "geometry": {"coordinates":[6.641943,46.777725],"type":"Point"}
}