{
  "type": "Feature",
  "properties": {
    "iso:country":"CH",
    "sg:address":"Hardrain 34 4052 Basel. Postfach",
    "sg:city":"Basel",
    "sg:orig_category":"Fussboden, Fliesen U Plattenlegerei, Tapeziererei Verlegen von Fussboden",
    "sg:postcode":"4028",
    "wof:name":"Parkett Nufer Ag Bodenbel\u00e4ge",
    "wof:placetype":"venue"
},
  "geometry": {"coordinates":[7.6167039871,47.5451011658],"type":"Point"}
}