{
  "type": "Feature",
  "properties": {
    "iso:country":"CH",
    "sg:address":"Industrie Rue De L' 58",
    "sg:city":"Bussigny-lausanne",
    "sg:orig_category":"Unternehmensberatung",
    "sg:phone":"+41 21 701 40 50",
    "sg:postcode":"1030",
    "sg:province":"Vaud",
    "wof:name":"Chemservices, Spiliadis S.",
    "wof:placetype":"venue"
},
  "geometry": {"coordinates":[6.5542078018,46.5480651855],"type":"Point"}
}