{
  "type": "Feature",
  "properties": {
    "iso:country":"CH",
    "sg:address":"Via Maraini 4b",
    "sg:city":"Massagno",
    "sg:orig_category":"Sportvereine Ballsport Fussball",
    "sg:postcode":"6900",
    "sg:province":"Ticino",
    "wof:name":"Fc Croatia Ticino",
    "wof:placetype":"venue"
},
  "geometry": {"coordinates":[8.9421510696,46.0148963928],"type":"Point"}
}