{
  "type": "Feature",
  "properties": {
    "iso:country":"CH",
    "sg:address":"Via Antonio Vanoni 6 6900 Lugano. Postfach",
    "sg:city":"Lugano",
    "sg:orig_category":"Wirtschaftspr\u00fcfung, Steuerberatung U Treuhand",
    "sg:postcode":"6900",
    "sg:province":"Ticino",
    "wof:name":"Prati Associati Sa Attivit\u00e0 Fiduciaria E Finanziaria Ecc",
    "wof:placetype":"venue"
},
  "geometry": {"coordinates":[8.9536848068,46.0111961365],"type":"Point"}
}