{
  "type": "Feature",
  "properties": {
    "iso:country":"CH",
    "sg:address":"Gaiserau 42a",
    "sg:city":"Gais",
    "sg:orig_category":"Hoch U Tiefbau",
    "sg:phone":"+41 71 793 31 74",
    "sg:postcode":"9056",
    "sg:province":"Appenzell Ausserrhoden",
    "wof:name":"Hans Heinrich Fuchs Baugesch\u00e4ft",
    "wof:placetype":"venue"
},
  "geometry": {"coordinates":[9.4510126114,47.3594055176],"type":"Point"}
}