{
  "type": "Feature",
  "properties": {
    "iso:country":"CH",
    "sg:address":"Bahnhofstrasse 14",
    "sg:city":"Chur",
    "sg:orig_category":"Herstellung von k\u00e4lte U lufttechnischen Erzeugnissen f\u00fcr gewerbliche Zwecke Installation von Heizung",
    "sg:phone":"+41 81 250 74 00",
    "sg:postcode":"7000",
    "sg:province":"Graubunden",
    "wof:name":"Casparis Lufttechnik L\u00fcftungs Und Klimaanlagen; Planung Usw",
    "wof:placetype":"venue"
},
  "geometry": {"coordinates":[9.5310373306,46.8522262573],"type":"Point"}
}