{
  "type": "Feature",
  "properties": {
    "iso:country":"CH",
    "sg:address":"Hauptstrasse 9",
    "sg:city":"Arbon",
    "sg:classifiers":[
        {
            "category":"Bars & Pubs",
            "type":"Food & Drink"
        }
    ],
    "sg:phone":"+41 71 446 35 60",
    "sg:postcode":"9320",
    "sg:province":"Thurgau",
    "wof:name":"St\u00e4dtli-bar",
    "wof:placetype":"venue"
},
  "geometry": {"coordinates":[9.435818,47.515873],"type":"Point"}
}