{
  "type": "Feature",
  "properties": {
    "iso:country":"CH",
    "sg:address":"4617 Gunzgen. Postfach 201",
    "sg:city":"Gunzgen",
    "sg:orig_category":"Tankstellen",
    "sg:phone":"+41 62 216 26 71",
    "sg:postcode":"4617",
    "sg:province":"Solothurn",
    "wof:name":"Jadi Ag",
    "wof:placetype":"venue"
},
  "geometry": {"coordinates":[7.8343100548,47.310710907],"type":"Point"}
}