{
  "type": "Feature",
  "properties": {
    "iso:country":"CH",
    "sg:address":"Wigartenstrasse 5",
    "sg:city":"F\u00e4llanden",
    "sg:orig_category":"Nationale Postdienste",
    "sg:phone":"+41 71 923 10 77",
    "sg:postcode":"8117",
    "sg:province":"Z\u00fcrich",
    "wof:name":"Die Schweizerische Post",
    "wof:placetype":"venue"
},
  "geometry": {"coordinates":[9.0740423203,47.4426345825],"type":"Point"}
}