{
  "type": "Feature",
  "properties": {
    "iso:country":"CH",
    "sg:address":"Postplatz 3 8303 Bassersdorf. Postfach 551",
    "sg:city":"Bassersdorf",
    "sg:orig_category":"Kantonalbanken",
    "sg:phone":"+41 18381717",
    "sg:postcode":"8303",
    "sg:province":"Z\u00fcrich",
    "wof:name":"Z\u00fcrcher Kantonalbank",
    "wof:placetype":"venue"
},
  "geometry": {"coordinates":[8.6306123734,47.4429740906],"type":"Point"}
}