{
  "type": "Feature",
  "properties": {
    "iso:country":"CH",
    "sg:address":"Bahnweg 57",
    "sg:city":"Mels",
    "sg:orig_category":"Verwaltung von Immobilien",
    "sg:phone":"+41 81 723 61 50",
    "sg:postcode":"8887",
    "sg:province":"St. Gallen",
    "wof:name":"Othmar Kurath Liegenschaftenverwaltung",
    "wof:placetype":"venue"
},
  "geometry": {"coordinates":[9.421628952,47.052192688],"type":"Point"}
}