{
  "type": "Feature",
  "properties": {
    "iso:country":"CH",
    "sg:address":"Foulques Rue Des 11",
    "sg:city":"Yverdon-les-bains",
    "sg:orig_category":"Bau von Strassen, Sportanlagen U Bahnverkehrsstrecken",
    "sg:phone":"+41 24 445 46 94",
    "sg:postcode":"1400",
    "sg:province":"Vaud",
    "wof:name":"Batigroup Sa",
    "wof:placetype":"venue"
},
  "geometry": {"coordinates":[6.63413,46.791828],"type":"Point"}
}