{
  "type": "Feature",
  "properties": {
    "iso:country":"CH",
    "sg:address":"Kurplatz 3",
    "sg:city":"Baden",
    "sg:classifiers":[
        {
            "category":"Travel",
            "subcategory":"Hotels & Motels",
            "type":"Entertainment"
        }
    ],
    "sg:postcode":"5400",
    "sg:province":"Aargau",
    "sg:tags":[
        "hotels",
        "mit",
        "restaurant"
    ],
    "wof:name":"Badhotel Tamina Ag",
    "wof:placetype":"venue"
},
  "geometry": {"coordinates":[9.5013246536,47.0036811829],"type":"Point"}
}