{
  "type": "Feature",
  "properties": {
    "iso:country":"CH",
    "sg:address":"Dorfstrasse 17",
    "sg:city":"Winkel",
    "sg:orig_category":"Werbung",
    "sg:postcode":"8185",
    "sg:province":"Z\u00fcrich",
    "wof:name":"Display Shop Ulrich N. Steinegger & Co.",
    "wof:placetype":"venue"
},
  "geometry": {"coordinates":[8.5549154282,47.4924163818],"type":"Point"}
}