{
  "type": "Feature",
  "properties": {
    "iso:country":"CH",
    "sg:address":"Rue Du Lignolat 8 1170 Aubonne Case Postale 30",
    "sg:city":"Aubonne",
    "sg:classifiers":[
        {
            "category":"Restaurant",
            "type":"Food & Drink"
        }
    ],
    "sg:phone":"+41 79 210 20 71",
    "sg:postcode":"1170",
    "sg:province":"Vaud",
    "wof:name":"Caf\u00e9 Du Cercle",
    "wof:placetype":"venue"
},
  "geometry": {"coordinates":[6.3923249245,46.4953613281],"type":"Point"}
}