{
  "type": "Feature",
  "properties": {
    "iso:country":"CH",
    "sg:address":"Ch. Des Cr\u00eats-de-champel 23",
    "sg:city":"Gen\u00e8ve",
    "sg:orig_category":"Vermietung U Verpachtung von eigenen Immobilien",
    "sg:postcode":"1206",
    "sg:province":"Gen\u00e8ve",
    "wof:name":"Cmp Carrelage, Ma\u00e7onnerie, Peinture Sa",
    "wof:placetype":"venue"
},
  "geometry": {"coordinates":[6.1553220749,46.1877403259],"type":"Point"}
}