{
  "type": "Feature",
  "properties": {
    "iso:country":"CH",
    "sg:address":"Ruhsitzstrasse 28",
    "sg:city":"St.gallen",
    "sg:orig_category":"Sportvereine Wassersport Schwimmen",
    "sg:phone":"+41 19101127",
    "sg:postcode":"9000",
    "sg:province":"St. Gallen",
    "wof:name":"K\u00fcsnachter Schwimmverein",
    "wof:placetype":"venue"
},
  "geometry": {"coordinates":[8.5845861435,47.319065094],"type":"Point"}
}