{
  "type": "Feature",
  "properties": {
    "addr:full":"Neugutstrasse 4 8304 Wallisellen. Postfach Wallisellen Z\u00fcrich 8304",
    "addr:housenumber":"4",
    "addr:postcode":"8304;8304",
    "addr:street":"Neugutstrasse",
    "iso:country":"CH",
    "sg:address":"Neugutstrasse 4 8304 Wallisellen. Postfach",
    "sg:city":"Wallisellen",
    "sg:orig_category":"Datenverarbeitungsdienste Softwareentwicklung U beratung",
    "sg:phone":"+41 71 855 77 11",
    "sg:postcode":"8304",
    "sg:province":"Z\u00fcrich",
    "wof:name":"Bruderer Informatik",
    "wof:placetype":"venue"
},
  "geometry": {"coordinates":[9.4952,47.47794],"type":"Point"}
}