{
  "type": "Feature",
  "properties": {
    "iso:country":"CH",
    "sg:address":"R\u00fcchligstrasse 20",
    "sg:city":"Dietikon",
    "sg:orig_category":"Grosshandel mit medizinischen U orthop\u00e4dischen Artikeln Grosshandel mit pharmazeutischen Erzeugnisse",
    "sg:phone":"+41 21 728 00 22",
    "sg:postcode":"8953",
    "sg:province":"Z\u00fcrich",
    "wof:name":"Niakan S\u00e0rl",
    "wof:placetype":"venue"
},
  "geometry": {"coordinates":[6.6527929306,46.5179901123],"type":"Point"}
}