{
  "type": "Feature",
  "properties": {
    "iso:country":"CH",
    "sg:address":"Industriestr. 2 6060 Sarnen. Postfach",
    "sg:city":"Sarnen",
    "sg:orig_category":"Pensionskassen",
    "sg:postcode":"6060",
    "sg:province":"Obwalden",
    "wof:name":"Patronale Wohlfahrtsstiftung Ab\u00e4cherli Druck Ag",
    "wof:placetype":"venue"
},
  "geometry": {"coordinates":[8.2488737106,46.8990287781],"type":"Point"}
}