{
  "type": "Feature",
  "properties": {
    "iso:country":"CH",
    "sg:address":"Offenburgerstrasse 37 4057 Basel. Postfach",
    "sg:city":"Basel",
    "sg:orig_category":"RESTAURANTS: TEA-ROOMS",
    "sg:phone":"+41 61 692 94 41",
    "sg:postcode":"4051",
    "sg:province":"Basel-Stadt",
    "wof:name":"Teehaus Zum Buddha, Sutter R. Fern\u00f6stliche Teesorten; Imp., Verkauf. Tea-room",
    "wof:placetype":"venue"
},
  "geometry": {"coordinates":[7.5884637833,47.5692634583],"type":"Point"}
}