{
  "type": "Feature",
  "properties": {
    "iso:country":"CH",
    "sg:address":"Carl Sprecherstrasse 1",
    "sg:city":"Oberentfelden",
    "sg:classifiers":[
        {
            "category":"Industrial Area",
            "type":"Public Place"
        }
    ],
    "sg:phone":"+41 62 737 33 33",
    "sg:postcode":"5036",
    "sg:province":"Aargau",
    "sg:tags":[
        "energy",
        "distribution",
        "system"
    ],
    "wof:name":"Alstom T&d Ag",
    "wof:placetype":"venue"
},
  "geometry": {"coordinates":[8.0540866852,47.3571662903],"type":"Point"}
}