{
  "type": "Feature",
  "properties": {
    "iso:country":"CH",
    "sg:address":"M\u00fchlematte 14",
    "sg:city":"W\u00fcnnewil",
    "sg:orig_category":"Elektroinstallation",
    "sg:postcode":"3184",
    "sg:province":"Fribourg",
    "wof:name":"Ssw Gmbh",
    "wof:placetype":"venue"
},
  "geometry": {"coordinates":[7.2844409943,46.8732414246],"type":"Point"}
}