{
  "type": "Feature",
  "properties": {
    "iso:country":"CH",
    "sg:address":"Bahnhofstrasse 23a 3800 Interlaken. Postfach 353",
    "sg:city":"Interlaken",
    "sg:orig_category":"Detailhandel mit Geschenkartikeln U Souvenirs Herstellung von Radio U Fernsehger\u00e4ten sowie phono U v",
    "sg:phone":"+41 33 823 80 63",
    "sg:postcode":"3800",
    "sg:province":"Bern",
    "wof:name":"Music Box Plaza, Schneider Silvia.",
    "wof:placetype":"venue"
},
  "geometry": {"coordinates":[7.8529782295,46.6840705872],"type":"Point"}
}