{
  "type": "Feature",
  "properties": {
    "iso:country":"CH",
    "sg:address":"Villigerstrasse 370",
    "sg:city":"Remigen",
    "sg:orig_category":"Herstellung von Ger\u00e4ten der Elektrizit\u00e4tserzeugung, -verteilung u.\u00e4. -Herstellung von sonstigen elek",
    "sg:phone":"+41 56 284 15 55",
    "sg:postcode":"5236",
    "sg:province":"Aargau",
    "wof:name":"Dipl.-ing. Kramert Gmbh",
    "wof:placetype":"venue"
},
  "geometry": {"coordinates":[8.1894330978,47.514793396],"type":"Point"}
}