{
  "type": "Feature",
  "properties": {
    "iso:country":"CH",
    "sg:address":"Allenbergstrasse 70a",
    "sg:city":"St\u00e4fa",
    "sg:orig_category":"Lichtpause U Reprografiebetriebe Satzherstellung U Reproduktion",
    "sg:phone":"+41 19263030",
    "sg:postcode":"8712",
    "sg:province":"Z\u00fcrich",
    "wof:name":"Peter Astfalck",
    "wof:placetype":"venue"
},
  "geometry": {"coordinates":[8.714846611,47.2500305176],"type":"Point"}
}