{
  "type": "Feature",
  "properties": {
    "iso:country":"CH",
    "sg:address":"Sihlquai 75",
    "sg:city":"Z\u00fcrich",
    "sg:classifiers":[
        {
            "category":"Wholesale",
            "subcategory":"Machinery & Supplies",
            "type":"Manufacturing & Wholesale Goods"
        }
    ],
    "sg:phone":"+41 4112717722",
    "sg:postcode":"8021",
    "sg:province":"Z\u00fcrich",
    "sg:tags":[
        "equipment",
        "optical",
        "precision",
        "instrument"
    ],
    "wof:name":"Picture Service Gwerder Ag",
    "wof:placetype":"venue"
},
  "geometry": {"coordinates":[8.5372610092,47.3826293945],"type":"Point"}
}