{
  "type": "Feature",
  "properties": {
    "iso:country":"CH",
    "sg:address":"M\u00fchlbergweg 21c",
    "sg:city":"Baden",
    "sg:orig_category":"Kauf U Verkauf von Immobilien auf eigene Rechnung",
    "sg:postcode":"5400",
    "sg:province":"Aargau",
    "wof:name":"Chesa Alpina Ag",
    "wof:placetype":"venue"
},
  "geometry": {"coordinates":[9.8377103806,46.4975395203],"type":"Point"}
}