{
  "type": "Feature",
  "properties": {
    "iso:country":"CH",
    "sg:address":"Avenue Marc-dufour 19 1000 Lausanne. Postfach",
    "sg:city":"Lausanne",
    "sg:orig_category":"Grosshandel mit Nahrungsmitteln, Getr\u00e4nken U Tabakwaren ohne ausgepr\u00e4gten Schwerpunkt",
    "sg:postcode":"1003",
    "sg:province":"Vaud",
    "wof:name":"Montefusco Raffaele",
    "wof:placetype":"venue"
},
  "geometry": {"coordinates":[6.6164178848,46.5185050964],"type":"Point"}
}