{
  "type": "Feature",
  "properties": {
    "iso:country":"CH",
    "sg:address":"Chalet N\u00e9miaz",
    "sg:city":"Chamoson",
    "sg:orig_category":"Rebbau",
    "sg:phone":"+41 27 306 20 75",
    "sg:postcode":"1955",
    "sg:province":"Valais",
    "wof:name":"Martial Putallaz Propri\u00e9taire Encaveur",
    "wof:placetype":"venue"
},
  "geometry": {"coordinates":[7.2253789902,46.2008628845],"type":"Point"}
}