{
  "type": "Feature",
  "properties": {
    "iso:country":"CH",
    "sg:address":"Alpenweg 10",
    "sg:city":"Seon",
    "sg:orig_category":"Religi\u00f6se Vereinigungen divers",
    "sg:postcode":"5703",
    "sg:province":"Aargau",
    "wof:name":"Cvjm",
    "wof:placetype":"venue"
},
  "geometry": {"coordinates":[8.1668138504,47.353767395],"type":"Point"}
}