{
  "type": "Feature",
  "properties": {
    "iso:country":"CH",
    "sg:address":"Schwabachstrasse 32",
    "sg:city":"Meilen",
    "sg:orig_category":"Herstellung von Verbrennungsmotoren U Turbinen ohne Motoren f\u00fcr Luft U Strassenfahrzeuge Mechanische",
    "sg:phone":"+41 19232914",
    "sg:postcode":"8706",
    "sg:province":"Z\u00fcrich",
    "wof:name":"Sennhauser Motorger\u00e4te Ag",
    "wof:placetype":"venue"
},
  "geometry": {"coordinates":[8.6343822479,47.2797088623],"type":"Point"}
}