{
  "type": "Feature",
  "properties": {
    "iso:country":"CH",
    "sg:address":"Luegislandstrasse 392",
    "sg:city":"Z\u00fcrich",
    "sg:orig_category":"Autogaragen",
    "sg:phone":"+41 13229933",
    "sg:postcode":"8051",
    "sg:province":"Z\u00fcrich",
    "wof:name":"Bruno Derrer Garage",
    "wof:placetype":"venue"
},
  "geometry": {"coordinates":[8.57664,47.408173],"type":"Point"}
}