{
  "type": "Feature",
  "properties": {
    "iso:country":"CH",
    "sg:address":"Eichmattstrasse 2",
    "sg:city":"Luzern",
    "sg:orig_category":"Fachdetailhandel in Verkaufsr\u00e4umen Herstellung von medizinischen Ger\u00e4ten, Pr\u00e4zisionsinstrumenten opt",
    "sg:phone":"+41 41 240 07 33",
    "sg:postcode":"6005",
    "sg:province":"Luzern",
    "wof:name":"Meyer Urs Schmuck + Ger\u00e4t Gmbh",
    "wof:placetype":"venue"
},
  "geometry": {"coordinates":[8.3044185638,47.0386695862],"type":"Point"}
}