{
  "type": "Feature",
  "properties": {
    "iso:country":"CH",
    "sg:address":"Bois-de-la-chapelle Av. Du 7",
    "sg:city":"Onex",
    "sg:orig_category":"Sanit\u00e4r, Heizungs U L\u00fcftungsinstallation",
    "sg:phone":"+41 79 626 29 45",
    "sg:postcode":"1213",
    "sg:province":"Gen\u00e8ve",
    "wof:name":"Mercier Patrick",
    "wof:placetype":"venue"
},
  "geometry": {"coordinates":[6.1072697639,46.1909408569],"type":"Point"}
}