{
  "type": "Feature",
  "properties": {
    "iso:country":"CH",
    "sg:address":"Waldeggweg 17",
    "sg:city":"Kloten",
    "sg:orig_category":"Sonstige Verkehrsvermittlung",
    "sg:postcode":"8302",
    "sg:province":"Z\u00fcrich",
    "wof:name":"Wm Spedition- & Transportberatung, Walter Misteli",
    "wof:placetype":"venue"
},
  "geometry": {"coordinates":[8.5777416229,47.4427032471],"type":"Point"}
}