{
  "type": "Feature",
  "properties": {
    "iso:country":"CH",
    "sg:address":"Poste B\u00e2t. 1936 Verbier. Postfach",
    "sg:city":"Verbier",
    "sg:orig_category":"RESTAURANTS: TEA-ROOMS",
    "sg:postcode":"1936",
    "sg:province":"Valais",
    "wof:name":"Kassam Ahal-nasir",
    "wof:placetype":"venue"
},
  "geometry": {"coordinates":[7.2247400284,46.0970802307],"type":"Point"}
}