{
  "type": "Feature",
  "properties": {
    "iso:country":"CH",
    "sg:address":"3716",
    "sg:city":"Kandergrund",
    "sg:orig_category":"Primarschulen",
    "sg:phone":"+41 33 671 38 48",
    "sg:postcode":"3716",
    "sg:province":"Bern",
    "wof:name":"Primarschule Reckental",
    "wof:placetype":"venue"
},
  "geometry": {"coordinates":[7.6618871689,46.5452346802],"type":"Point"}
}