{
  "type": "Feature",
  "properties": {
    "iso:country":"CH",
    "sg:address":"Kronengasse 5",
    "sg:city":"Gottlieben",
    "sg:orig_category":"Vereine Frauen Vereine Gemeinn\u00fctzige",
    "sg:phone":"+41 71 669 14 21",
    "sg:postcode":"8274",
    "sg:province":"Thurgau",
    "wof:name":"Thurg.gemeinn.frauenverein Tgf",
    "wof:placetype":"venue"
},
  "geometry": {"coordinates":[9.1336193085,47.6647911072],"type":"Point"}
}