{
  "type": "Feature",
  "properties": {
    "iso:country":"CH",
    "sg:address":"Chiboz D'en Bas",
    "sg:city":"Fully",
    "sg:classifiers":[
        {
            "category":"Restaurant",
            "type":"Food & Drink"
        }
    ],
    "sg:phone":"+41 27 746 26 20",
    "sg:postcode":"1926",
    "sg:province":"Valais",
    "wof:name":"Caf\u00e9 Chez Les Anglais",
    "wof:placetype":"venue"
},
  "geometry": {"coordinates":[7.1384840012,46.1665077209],"type":"Point"}
}