{
  "type": "Feature",
  "properties": {
    "iso:country":"CH",
    "sg:address":"Oberreinach",
    "sg:city":"Herlisberg",
    "sg:orig_category":"Markt U Meinungsforschung",
    "sg:phone":"+41 41 930 36 86",
    "sg:postcode":"6028",
    "sg:province":"Luzern",
    "wof:name":"Osiris Seminar Ag",
    "wof:placetype":"venue"
},
  "geometry": {"coordinates":[8.2364654541,47.1882209778],"type":"Point"}
}