{
  "type": "Feature",
  "properties": {
    "iso:country":"CH",
    "sg:address":"Clos-dessous",
    "sg:city":"Vich",
    "sg:orig_category":"Erbringung von Dienstleistungen f\u00fcr Unternehmen",
    "sg:postcode":"1267",
    "sg:province":"Vaud",
    "wof:name":"F.m. De Mestral",
    "wof:placetype":"venue"
},
  "geometry": {"coordinates":[6.2500171661,46.4310722351],"type":"Point"}
}