{
  "type": "Feature",
  "properties": {
    "iso:country":"CH",
    "sg:address":"Spitalackerstrasse 59",
    "sg:city":"Bern",
    "sg:orig_category":"Detailhandel mit Zeitungen U Zeitschriften Kioske",
    "sg:phone":"+41 31 332 62 35",
    "sg:postcode":"3013",
    "sg:province":"Bern",
    "wof:name":"Gertrud Friedli Kiosk",
    "wof:placetype":"venue"
},
  "geometry": {"coordinates":[7.4518518448,46.9566383362],"type":"Point"}
}