{
  "type": "Feature",
  "properties": {
    "iso:country":"CH",
    "sg:address":"Vergers-de-la-gottaz 19",
    "sg:city":"Morges",
    "sg:orig_category":"Markt U Meinungsforschung",
    "sg:postcode":"1110",
    "sg:province":"Vaud",
    "wof:name":"Mst Marketing-secr\u00e9tariat-traductions A. Jaccard",
    "wof:placetype":"venue"
},
  "geometry": {"coordinates":[6.4855208397,46.5078277588],"type":"Point"}
}