{
  "type": "Feature",
  "properties": {
    "iso:country":"CH",
    "sg:address":"Grossmattrain 2",
    "sg:city":"Rudolfstetten",
    "sg:orig_category":"Autogaragen",
    "sg:phone":"+41 56 631 14 49",
    "sg:postcode":"8964",
    "sg:province":"Aargau",
    "wof:name":"Lazar Jankovic Garage",
    "wof:placetype":"venue"
},
  "geometry": {"coordinates":[8.38734,47.374226],"type":"Point"}
}