{
  "type": "Feature",
  "properties": {
    "iso:country":"CH",
    "sg:address":"Furkastrasse 28",
    "sg:city":"Naters",
    "sg:orig_category":"Herstellung von medizinischen U chirurgischen Ger\u00e4ten sowie orthop\u00e4dischen Vorrichtungen Zahntechnis",
    "sg:phone":"+41 62 875 13 13",
    "sg:postcode":"3904",
    "sg:province":"Valais",
    "wof:name":"Zahntechnisches Labor Zellweger Robert",
    "wof:placetype":"venue"
},
  "geometry": {"coordinates":[8.1332521439,47.5541534424],"type":"Point"}
}