{
  "type": "Feature",
  "properties": {
    "iso:country":"CH",
    "sg:address":"Rue De Gravelone 76",
    "sg:city":"Sion",
    "sg:orig_category":"Arztpraxen",
    "sg:phone":"+41 27 322 10 10",
    "sg:postcode":"1950",
    "sg:province":"Valais",
    "wof:name":"Dr M\u00e9d. Walter Zen Ruffinen M\u00e9decin Sp\u00e9cialiste Fmh",
    "wof:placetype":"venue"
},
  "geometry": {"coordinates":[7.347745,46.233856],"type":"Point"}
}