{
  "type": "Feature",
  "properties": {
    "iso:country":"CH",
    "sg:address":"R\u00fcegerholzstrasse 38",
    "sg:city":"Frauenfeld",
    "sg:orig_category":"Grosshandel mit medizinischen U orthop\u00e4dischen Artikeln Softwareentwicklung U beratung",
    "sg:phone":"+41 22 309 08 10",
    "sg:postcode":"8500",
    "sg:province":"Thurgau",
    "wof:name":"S\u00e9lectif Dk S\u00e0rl Commerce \u00e9quipements M\u00e9dicaux",
    "wof:placetype":"venue"
},
  "geometry": {"coordinates":[6.12774086,46.1870918274],"type":"Point"}
}