{
  "type": "Feature",
  "properties": {
    "iso:country":"CH",
    "sg:address":"Obertor 12",
    "sg:city":"Winterthur",
    "sg:orig_category":"Arztpraxen",
    "sg:phone":"+41 52 213 99 20",
    "sg:postcode":"8400",
    "sg:province":"Z\u00fcrich",
    "wof:name":"Dr.med.ursula Baumberger Spezial\u00e4rztin Fmh",
    "wof:placetype":"venue"
},
  "geometry": {"coordinates":[8.730524,47.498669],"type":"Point"}
}