{
  "type": "Feature",
  "properties": {
    "iso:country":"CH",
    "sg:address":"Steinhaldenring 10 8954 Geroldswil. Postfach 28",
    "sg:city":"Geroldswil",
    "sg:orig_category":"Detailhandel Detailhandel mit B\u00fcromaschinen U einrichtungen Reparatur von Gebrauchsg\u00fctern",
    "sg:phone":"+41 17484088",
    "sg:postcode":"8954",
    "sg:province":"Z\u00fcrich",
    "wof:name":"Fiba Schulbedarf Ag",
    "wof:placetype":"venue"
},
  "geometry": {"coordinates":[8.4129991531,47.4195556641],"type":"Point"}
}