{
  "type": "Feature",
  "properties": {
    "iso:country":"CH",
    "sg:address":"9479",
    "sg:city":"Oberschan",
    "sg:orig_category":"Sportvereine Turnen",
    "sg:postcode":"9479",
    "sg:province":"St. Gallen",
    "wof:name":"Turnverein Obersiggenthal",
    "wof:placetype":"venue"
},
  "geometry": {"coordinates":[8.2896528244,47.4883422852],"type":"Point"}
}