{
  "type": "Feature",
  "properties": {
    "iso:country":"CH",
    "sg:address":"Baeumleingasse 4",
    "sg:city":"Basel",
    "sg:orig_category":"Medizin, Pharmaprodukte",
    "sg:phone":"+41 61 272 70 07",
    "sg:postcode":"4051",
    "sg:province":"Basel-Stadt",
    "wof:name":"Engel-apotheke Ag",
    "wof:placetype":"venue"
},
  "geometry": {"coordinates":[7.591905,47.554703],"type":"Point"}
}