{
  "type": "Feature",
  "properties": {
    "iso:country":"CH",
    "sg:address":"Wiesenstrasse 3",
    "sg:city":"K\u00f6lliken",
    "sg:orig_category":"Politische Parteien SVP",
    "sg:phone":"+41 62 723 27 39",
    "sg:postcode":"5742",
    "sg:province":"Aargau",
    "wof:name":"Svp Ortspartei K\u00f6lliken",
    "wof:placetype":"venue"
},
  "geometry": {"coordinates":[8.0270280838,47.3341789246],"type":"Point"}
}