{
  "type": "Feature",
  "properties": {
    "iso:country":"CH",
    "sg:address":"Leutholdstrasse 12 8037 Z\u00fcrich. Postfach",
    "sg:city":"Z\u00fcrich",
    "sg:orig_category":"D\u00e4mmung gegen K\u00e4lte, W\u00e4rme, Schall U Ersch\u00fctterung Innenausbau",
    "sg:phone":"+41 12726260",
    "sg:postcode":"8037",
    "sg:province":"Z\u00fcrich",
    "wof:name":"I-be-tex F.j.ziegler Innenausbau",
    "wof:placetype":"venue"
},
  "geometry": {"coordinates":[8.5264205933,47.3922958374],"type":"Point"}
}