{
  "type": "Feature",
  "properties": {
    "addr:full":"Benknerstrasse Kaltbrunn St. Gallen 8722",
    "addr:postcode":"8722",
    "addr:street":"Benknerstrasse Kaltbrunn",
    "iso:country":"CH",
    "sg:address":"Benknerstrasse",
    "sg:city":"Kaltbrunn",
    "sg:orig_category":"Betrieb von Sportanlagen",
    "sg:phone":"+41 55 293 24 94",
    "sg:postcode":"8722",
    "sg:province":"St. Gallen",
    "wof:name":"Linth Indoor Niederer Helmut",
    "wof:placetype":"venue"
},
  "geometry": {"coordinates":[9.021285,47.208183],"type":"Point"}
}