{
  "type": "Feature",
  "properties": {
    "iso:country":"CH",
    "sg:address":"St. Alban-vorstadt 25 4052 Basel. Postfach",
    "sg:city":"Basel",
    "sg:orig_category":"Gesundheits\u00e4mter",
    "sg:phone":"+41 61 267 81 81",
    "sg:postcode":"4006",
    "wof:name":"Sanit\u00e4tsdepartement Des Kantons Basel-stadt",
    "wof:placetype":"venue"
},
  "geometry": {"coordinates":[7.5962700844,47.5547180176],"type":"Point"}
}