{
  "type": "Feature",
  "properties": {
    "iso:country":"CH",
    "sg:address":"Tiergartenstrasse 1",
    "sg:city":"Altendorf",
    "sg:orig_category":"Architektur U Ingenieurb\u00fcros",
    "sg:phone":"+41 14062020",
    "sg:postcode":"8852",
    "sg:province":"Schwyz",
    "wof:name":"All-tec Ag",
    "wof:placetype":"venue"
},
  "geometry": {"coordinates":[8.45591,47.360161],"type":"Point"}
}