{
  "type": "Feature",
  "properties": {
    "iso:country":"CH",
    "sg:address":"Place De La Gare 6",
    "sg:city":"Cully",
    "sg:classifiers":[
        {
            "category":"Wholesale",
            "subcategory":"Petroleum",
            "type":"Manufacturing & Wholesale Goods"
        }
    ],
    "sg:phone":"+41 21 799 11 17",
    "sg:postcode":"1096",
    "sg:province":"Vaud",
    "sg:tags":[
        "swiss",
        "wine"
    ],
    "wof:name":"Henri Contesse S.a.",
    "wof:placetype":"venue"
},
  "geometry": {"coordinates":[6.726593,46.488716],"type":"Point"}
}