{
  "type": "Feature",
  "properties": {
    "addr:full":"Hofuhrenstrasse 10 Deitingen Solothurn 4543",
    "addr:housenumber":"10",
    "addr:postcode":"4543",
    "addr:street":"Hofuhrenstrasse",
    "iso:country":"CH",
    "sg:address":"Hofuhrenstrasse 10",
    "sg:city":"Deitingen",
    "sg:orig_category":"Bauschreinerei Innenausbau",
    "sg:phone":"+41 32 613 33 70",
    "sg:postcode":"4543",
    "sg:province":"Solothurn",
    "wof:name":"Gebr. Frei Ag M\u00f6belschreinerei Innenausbau",
    "wof:placetype":"venue"
},
  "geometry": {"coordinates":[7.616281,47.223686],"type":"Point"}
}