{
  "type": "Feature",
  "properties": {
    "iso:country":"CH",
    "sg:address":"3963",
    "sg:city":"Crans-sur-sierre",
    "sg:orig_category":"Unclassifiable Establishments",
    "sg:postcode":"3963",
    "sg:province":"Valais",
    "wof:name":"Si T\u00e9l\u00e9r\u00e9sidence Holidays Crans No 23 A Sa",
    "wof:placetype":"venue"
},
  "geometry": {"coordinates":[7.4617700577,46.3076210022],"type":"Point"}
}