{
  "type": "Feature",
  "properties": {
    "iso:country":"CH",
    "sg:address":"Ruestel",
    "sg:city":"Amden",
    "sg:orig_category":"Wirtschaftspr\u00fcfung, Steuerberatung U Treuhand",
    "sg:postcode":"8873",
    "sg:province":"St. Gallen",
    "wof:name":"Mallal Rasheed Johnz Enterprise",
    "wof:placetype":"venue"
},
  "geometry": {"coordinates":[9.1439914703,47.149646759],"type":"Point"}
}