{
  "type": "Feature",
  "properties": {
    "iso:country":"CH",
    "sg:address":"Oberg\u00fctschhalde 9",
    "sg:city":"Luzern",
    "sg:orig_category":"Grosshandel mit B\u00fcromaschinen Grosshandel mit Datenverarbeitungsger\u00e4ten",
    "sg:phone":"+41 41 310 65 65",
    "sg:postcode":"6003",
    "sg:province":"Luzern",
    "wof:name":"Compco Informatik Ag Edv-dienstleistungen",
    "wof:placetype":"venue"
},
  "geometry": {"coordinates":[8.2875432968,47.0449867249],"type":"Point"}
}