{
  "type": "Feature",
  "properties": {
    "iso:country":"CH",
    "sg:address":"Baselstr. 32",
    "sg:city":"Wiedlisbach",
    "sg:classifiers":[
        {
            "category":"Professional",
            "subcategory":"Printing & Photocopies",
            "type":"Services"
        }
    ],
    "sg:phone":"+41 41 854 40 60",
    "sg:postcode":"4537",
    "sg:province":"Bern",
    "sg:tags":[
        "machine",
        "engineering",
        "-",
        "mechanical"
    ],
    "wof:name":"Durrer Spezialmaschinen Ag",
    "wof:placetype":"venue"
},
  "geometry": {"coordinates":[8.4377317429,47.0754089355],"type":"Point"}
}