{
  "type": "Feature",
  "properties": {
    "iso:country":"CH",
    "sg:address":"Reichenbachstr. 69 3000 Bern. Postfach",
    "sg:city":"Bern",
    "sg:classifiers":[
        {
            "category":"Communications",
            "subcategory":"Radio Station",
            "type":"Services"
        }
    ],
    "sg:phone":"+41 31 305 97 47",
    "sg:postcode":"3004",
    "sg:province":"Bern",
    "sg:tags":[
        "fernsehanstalten",
        "u"
    ],
    "wof:name":"Audioplan Andr\u00e9 C. Pappa Studio F. Audiovision U. Raumplanung",
    "wof:placetype":"venue"
},
  "geometry": {"coordinates":[7.4457168579,46.9713478088],"type":"Point"}
}