{
  "type": "Feature",
  "properties": {
    "iso:country":"CH",
    "sg:address":"Wildbrunnstrasse 3",
    "sg:city":"Kaltbrunn",
    "sg:orig_category":"Herstellung von Metallerzeugnissen ohne Maschinenbau Herstellung von k\u00e4lte U lufttechnischen Erzeugn",
    "sg:phone":"+41 55 283 29 29",
    "sg:postcode":"8722",
    "sg:province":"St. Gallen",
    "wof:name":"Rrw Riesen Reinlufttechnik Und W\u00e4rmer\u00fcckgewinnung, Apparate F\u00fcr Kontrollierte L\u00fcftung Und Klimatechnik.",
    "wof:placetype":"venue"
},
  "geometry": {"coordinates":[9.0088062286,47.2167015076],"type":"Point"}
}