{
  "type": "Feature",
  "properties": {
    "iso:country":"CH",
    "sg:address":"Rosenbergh\u00f6he 6",
    "sg:city":"Luzern",
    "sg:orig_category":"Vereine Gesang",
    "sg:postcode":"6004",
    "sg:province":"Luzern",
    "wof:name":"M\u00e4nnerchor Staad",
    "wof:placetype":"venue"
},
  "geometry": {"coordinates":[9.5341300964,47.4807701111],"type":"Point"}
}