{
  "type": "Feature",
  "properties": {
    "iso:country":"CH",
    "sg:address":"Z\u00fcrichstrasse 14",
    "sg:city":"D\u00fcbendorf",
    "sg:orig_category":"Autogaragen",
    "sg:phone":"+41 18210911",
    "sg:postcode":"8600",
    "sg:province":"Z\u00fcrich",
    "wof:name":"Andreas Weber Garage",
    "wof:placetype":"venue"
},
  "geometry": {"coordinates":[8.61569,47.397041],"type":"Point"}
}