{
  "type": "Feature",
  "properties": {
    "iso:country":"CH",
    "sg:address":"Chemin Du Cr\u00eat 14",
    "sg:city":"Evilard",
    "sg:orig_category":"Instandhaltung U Reparatur von Automobilen",
    "sg:phone":"+41 32 322 78 65",
    "sg:postcode":"2533",
    "sg:province":"Bern",
    "wof:name":"Atz Racing-development Sa",
    "wof:placetype":"venue"
},
  "geometry": {"coordinates":[7.2399191856,47.1523590088],"type":"Point"}
}