{
  "type": "Feature",
  "properties": {
    "iso:country":"CH",
    "sg:address":"Oberer Deutweg 27",
    "sg:city":"Winterthur",
    "sg:orig_category":"Handelsvermittlung U Grosshandel R\u00fcckgewinnung U Vorbereitung f\u00fcr die Wiederverwertung Recycling",
    "sg:phone":"+41 52 233 13 17",
    "sg:postcode":"8400",
    "sg:province":"Z\u00fcrich",
    "wof:name":"Ernst Schneider Industrieabf\u00e4lle",
    "wof:placetype":"venue"
},
  "geometry": {"coordinates":[8.7448472977,47.4954528809],"type":"Point"}
}