{
  "type": "Feature",
  "properties": {
    "iso:country":"CH",
    "sg:address":"Z\u00fcrcherstrasse 197",
    "sg:city":"Frauenfeld",
    "sg:orig_category":"Reparatur von Schuhen U Lederwaren",
    "sg:phone":"+41 52 721 63 66",
    "sg:postcode":"8500",
    "sg:province":"Thurgau",
    "wof:name":"Max Peter Schuhservice",
    "wof:placetype":"venue"
},
  "geometry": {"coordinates":[8.8992490768,47.5578842163],"type":"Point"}
}