{
  "type": "Feature",
  "properties": {
    "iso:country":"CH",
    "sg:address":"Mittskirchweg 7",
    "sg:city":"Zurzach",
    "sg:orig_category":"Einbau von Schreinerwaren",
    "sg:phone":"+41 56 249 28 40",
    "sg:postcode":"5330",
    "sg:province":"Aargau",
    "wof:name":"Rd Planung & Handels Ag Ladenbau",
    "wof:placetype":"venue"
},
  "geometry": {"coordinates":[8.2968730927,47.5882644653],"type":"Point"}
}