{
  "type": "Feature",
  "properties": {
    "iso:country":"CH",
    "sg:address":"Campi Via Ai 6",
    "sg:city":"Agno",
    "sg:orig_category":"Architektur U Ingenieurb\u00fcros",
    "sg:phone":"+41 91 604 52 34",
    "sg:postcode":"6982",
    "sg:province":"Ticino",
    "wof:name":"Dr. Architetto Mauro Del Maschio",
    "wof:placetype":"venue"
},
  "geometry": {"coordinates":[8.899663,45.998795],"type":"Point"}
}