{
  "type": "Feature",
  "properties": {
    "iso:country":"CH",
    "sg:address":"Margarethenstrasse 19 4053 Basel. Postfach",
    "sg:city":"Basel",
    "sg:orig_category":"Maler U Glasergewerbe",
    "sg:phone":"+41 61 271 99 45",
    "sg:postcode":"4008",
    "sg:province":"Basel-Stadt",
    "wof:name":"W. Nissl\u00e9 & Sohn Ag",
    "wof:placetype":"venue"
},
  "geometry": {"coordinates":[7.5855689049,47.5471076965],"type":"Point"}
}