{
  "type": "Feature",
  "properties": {
    "iso:country":"CH",
    "sg:address":"Sch\u00f6nb\u00fchlstrasse",
    "sg:city":"Chur",
    "sg:orig_category":"Instandhaltung U Reparatur von Automobilen",
    "sg:postcode":"7000",
    "sg:province":"Graubunden",
    "wof:name":"Garage Misini",
    "wof:placetype":"venue"
},
  "geometry": {"coordinates":[9.5122013092,46.8492927551],"type":"Point"}
}