{
  "type": "Feature",
  "properties": {
    "iso:country":"CH",
    "sg:address":"Dorfstrasse 1",
    "sg:city":"Leuzigen",
    "sg:orig_category":"Verwertung von Milch",
    "sg:phone":"+41 32 679 36 50",
    "sg:postcode":"3297",
    "sg:province":"Bern",
    "wof:name":"K\u00e4serei Leuzigen, Stoll Veronika",
    "wof:placetype":"venue"
},
  "geometry": {"coordinates":[7.4585399628,47.1737594604],"type":"Point"}
}