{
  "type": "Feature",
  "properties": {
    "iso:country":"CH",
    "sg:address":"Obergasse 2",
    "sg:city":"Uznach",
    "sg:orig_category":"Installation von Heizungs, L\u00fcftungs U Klimaanlagen Sanit\u00e4r U Heizungsinstallation",
    "sg:phone":"+41 22 342 64 00",
    "sg:postcode":"8730",
    "sg:province":"St. Gallen",
    "wof:name":"H\u00e4lg & Co Ag",
    "wof:placetype":"venue"
},
  "geometry": {"coordinates":[6.1414251328,46.1833114624],"type":"Point"}
}