{
  "type": "Feature",
  "properties": {
    "iso:country":"CH",
    "sg:address":"St. Gallerstrasse 4",
    "sg:city":"Elgg",
    "sg:orig_category":"Instandhaltung U Reparatur von Automobilen",
    "sg:phone":"+41 52 364 38 87",
    "sg:postcode":"8353",
    "sg:province":"Z\u00fcrich",
    "wof:name":"Steinemann Ueberlandgarage Ag",
    "wof:placetype":"venue"
},
  "geometry": {"coordinates":[8.8592910767,47.4988670349],"type":"Point"}
}