{
  "type": "Feature",
  "properties": {
    "iso:country":"CH",
    "sg:address":"Rue Du March\u00e9 23",
    "sg:city":"Montreux",
    "sg:orig_category":"Sonstiges Versicherungsgewerbe",
    "sg:postcode":"1820",
    "sg:province":"Vaud",
    "wof:name":"Aeschbacher Marc",
    "wof:placetype":"venue"
},
  "geometry": {"coordinates":[6.9131789207,46.4336357117],"type":"Point"}
}