{
  "type": "Feature",
  "properties": {
    "iso:country":"CH",
    "sg:address":"Mattstrasse 7a",
    "sg:city":"Ennenda",
    "sg:orig_category":"Vermietung U Verpachtung von eigenen Immobilien",
    "sg:postcode":"8755",
    "sg:province":"Glarus",
    "wof:name":"J 83 Projekt-partner Ag",
    "wof:placetype":"venue"
},
  "geometry": {"coordinates":[9.0806312561,47.0307121277],"type":"Point"}
}