{
  "type": "Feature",
  "properties": {
    "iso:country":"CH",
    "sg:address":"R\u00f6merstrasse 22",
    "sg:city":"Baden",
    "sg:orig_category":"Unternehmensberatung",
    "sg:postcode":"5400",
    "sg:province":"Aargau",
    "wof:name":"Elida Gmbh",
    "wof:placetype":"venue"
},
  "geometry": {"coordinates":[8.3090200424,47.4809532166],"type":"Point"}
}