{
  "type": "Feature",
  "properties": {
    "iso:country":"CH",
    "sg:address":"N\u00e4fenackerstrasse 7",
    "sg:city":"St.gallen",
    "sg:orig_category":"Grosshandel mit Getr\u00e4nken",
    "sg:postcode":"9000",
    "sg:province":"St. Gallen",
    "wof:name":"Valvins Gmbh",
    "wof:placetype":"venue"
},
  "geometry": {"coordinates":[9.3908157349,47.4263801575],"type":"Point"}
}