{
  "type": "Feature",
  "properties": {
    "iso:country":"CH",
    "sg:address":"San Michele Salita 2",
    "sg:city":"Bellinzona",
    "sg:orig_category":"RESTAURANTS: TEA-ROOMS",
    "sg:phone":"+41 91 826 25 53",
    "sg:postcode":"6500",
    "sg:province":"Ticino",
    "wof:name":"Moncisa Sa",
    "wof:placetype":"venue"
},
  "geometry": {"coordinates":[9.0225715637,46.1918296814],"type":"Point"}
}