{
  "type": "Feature",
  "properties": {
    "iso:country":"CH",
    "sg:address":"Bahnstrasse 102",
    "sg:city":"Regensdorf",
    "sg:orig_category":"Hardwareberatung",
    "sg:phone":"+41 18452770",
    "sg:postcode":"8105",
    "sg:province":"Z\u00fcrich",
    "wof:name":"Dokumenzi, Facility-management, Menzi B.",
    "wof:placetype":"venue"
},
  "geometry": {"coordinates":[8.4584140778,47.4442024231],"type":"Point"}
}