{
  "type": "Feature",
  "properties": {
    "iso:country":"CH",
    "sg:address":"Rue Du Brise-vent 17",
    "sg:city":"Del\u00e9mont",
    "sg:orig_category":"Herstellung von medizinischen U chirurgischen Ger\u00e4ten sowie orthop\u00e4dischen Vorrichtungen Zahntechnis",
    "sg:phone":"+41 32 422 98 34",
    "sg:postcode":"2800",
    "sg:province":"Jura",
    "wof:name":"Jeannottat Cl\u00e9ment Sa",
    "wof:placetype":"venue"
},
  "geometry": {"coordinates":[7.33086586,47.3671188354],"type":"Point"}
}