{
  "type": "Feature",
  "properties": {
    "iso:country":"CH",
    "sg:address":"Seebestrasse 3",
    "sg:city":"Marthalen",
    "sg:orig_category":"Sonstiger spezialisierter Hoch U Tiefbau",
    "sg:phone":"+41 71 747 45 45",
    "sg:postcode":"8460",
    "sg:province":"Z\u00fcrich",
    "wof:name":"Schwalm Ag",
    "wof:placetype":"venue"
},
  "geometry": {"coordinates":[9.6348695755,47.4514694214],"type":"Point"}
}