{
  "type": "Feature",
  "properties": {
    "iso:country":"CH",
    "sg:address":"Charmettes Chemin Des 9",
    "sg:city":"Lausanne",
    "sg:orig_category":"Handels-H\u00e4user U Gesellschaften",
    "sg:postcode":"1003",
    "sg:province":"Vaud",
    "wof:name":"Alexandra Sa",
    "wof:placetype":"venue"
},
  "geometry": {"coordinates":[6.6284508705,46.5191917419],"type":"Point"}
}