{
  "type": "Feature",
  "properties": {
    "iso:country":"CH",
    "sg:address":"Pictet Avenue Ernest- 5 1203 Gen\u00e8ve. Postfach",
    "sg:city":"Genf",
    "sg:orig_category":"Fernmeldedienste",
    "sg:postcode":"1200",
    "sg:province":"Gen\u00e8ve",
    "wof:name":"Fanac & Robas Sa T\u00e9l\u00e9communications; Engineering, C\u00e2blage, Installations",
    "wof:placetype":"venue"
},
  "geometry": {"coordinates":[6.1267409325,46.2115898132],"type":"Point"}
}