{
  "type": "Feature",
  "properties": {
    "iso:country":"CH",
    "sg:address":"St. Jakobs-strasse 200 4052 Basel. Postfach 3202",
    "sg:city":"Basel",
    "sg:orig_category":"Frachtumschlag U Lagerung",
    "sg:phone":"+41 61 319 92 22",
    "sg:postcode":"4002",
    "sg:province":"Basel-Stadt",
    "wof:name":"Hupac Intermodal Sa",
    "wof:placetype":"venue"
},
  "geometry": {"coordinates":[7.6071028709,47.5438766479],"type":"Point"}
}