{
  "type": "Feature",
  "properties": {
    "iso:country":"CH",
    "sg:address":"Hauptstrasse 12 6222 Gunzwil. Postfach 85",
    "sg:city":"Gunzwil",
    "sg:orig_category":"Dachdeckerei",
    "sg:phone":"+41 41 930 22 31",
    "sg:postcode":"6222",
    "sg:province":"Luzern",
    "wof:name":"Erwin Bucher Bedachungen",
    "wof:placetype":"venue"
},
  "geometry": {"coordinates":[8.179368,47.21143],"type":"Point"}
}