{
  "type": "Feature",
  "properties": {
    "iso:country":"CH",
    "sg:address":"Am Sientalweg 6 6343 Rotkreuz. Postfach 37",
    "sg:city":"Rotkreuz",
    "sg:orig_category":"Grosshandel mit Flachglas, Sanit\u00e4rkeramik U Anstrichmitteln Handelsvermittlung U Grosshandel mit Aut",
    "sg:phone":"+41 62 749 50 70",
    "sg:postcode":"6343",
    "sg:province":"Zug",
    "wof:name":"Exachem Ag Lacke & Zubeh\u00f6r",
    "wof:placetype":"venue"
},
  "geometry": {"coordinates":[8.4339542389,47.1395683289],"type":"Point"}
}