{
  "type": "Feature",
  "properties": {
    "iso:country":"CH",
    "sg:address":"T\u00f6tzliweg 8",
    "sg:city":"M\u00e4nnedorf",
    "sg:orig_category":"Gartenbau",
    "sg:phone":"+41 19202140",
    "sg:postcode":"8708",
    "sg:province":"Z\u00fcrich",
    "wof:name":"K\u00e4ser Gartenbau Ag",
    "wof:placetype":"venue"
},
  "geometry": {"coordinates":[8.6950817108,47.2555923462],"type":"Point"}
}