{
  "type": "Feature",
  "properties": {
    "addr:full":"Steighalde 11 Rorschacherberg St. Gallen 9404",
    "addr:housenumber":"11",
    "addr:postcode":"9404",
    "addr:street":"Steighalde",
    "iso:country":"CH",
    "sg:address":"Steighalde 11",
    "sg:city":"Rorschacherberg",
    "sg:orig_category":"Bauschreinerei Herstellung von Konstruktionsteilen, Fertigbauteilen U Ausbauelementen aus Holz",
    "sg:phone":"+41 71 841 13 26",
    "sg:postcode":"9404",
    "sg:province":"St. Gallen",
    "wof:name":"Hafner + Locher",
    "wof:placetype":"venue"
},
  "geometry": {"coordinates":[9.507789,47.471973],"type":"Point"}
}