{
  "type": "Feature",
  "properties": {
    "iso:country":"CH",
    "sg:address":"Rue De Lausanne 141",
    "sg:city":"Gen\u00e8ve",
    "sg:orig_category":"Einbau von Schreinerwaren Herstellung von K\u00fcchenm\u00f6beln",
    "sg:phone":"+41 22 738 11 50",
    "sg:postcode":"1202",
    "sg:province":"Gen\u00e8ve",
    "wof:name":"Prodival Sa, Succursale De Gen\u00e8ve",
    "wof:placetype":"venue"
},
  "geometry": {"coordinates":[6.1487178802,46.2227783203],"type":"Point"}
}