{
  "type": "Feature",
  "properties": {
    "iso:country":"CH",
    "sg:address":"1682",
    "sg:city":"Lovatens",
    "sg:orig_category":"Maurerarbeiten",
    "sg:phone":"+41 26 652 37 58",
    "sg:postcode":"1682",
    "sg:province":"Vaud",
    "wof:name":"Guido Righetti Entreprise De Ma\u00e7onnerie",
    "wof:placetype":"venue"
},
  "geometry": {"coordinates":[6.8639497757,46.6918258667],"type":"Point"}
}