{
  "type": "Feature",
  "properties": {
    "addr:full":"Eichenweg 37 3052 Zollikofen. Postfach 733 Zollikofen Bern 3052",
    "addr:housenumber":"37;733",
    "addr:postcode":"3052 zollikofen.;3052",
    "addr:street":"Eichenweg;Postfach",
    "iso:country":"CH",
    "sg:address":"Eichenweg 37 3052 Zollikofen. Postfach 733",
    "sg:city":"Zollikofen",
    "sg:orig_category":"D\u00e4mmung gegen K\u00e4lte, W\u00e4rme, Schall U Ersch\u00fctterung Herstellung von sonstigen Metallwaren",
    "sg:phone":"+41 31 910 83 60",
    "sg:postcode":"3052",
    "sg:province":"Bern",
    "wof:name":"Watep Ag",
    "wof:placetype":"venue"
},
  "geometry": {"coordinates":[7.464175,46.998779],"type":"Point"}
}