{
  "type": "Feature",
  "properties": {
    "iso:country":"CH",
    "sg:address":"Route Des H\u00f4tels",
    "sg:city":"Villars-sur-ollon",
    "sg:orig_category":"Zahnarztpraxen",
    "sg:phone":"+41 24 495 33 94",
    "sg:postcode":"1884",
    "sg:province":"Vaud",
    "wof:name":"Dr M\u00e9d. Dent. Wolfgang Teumer M\u00e9decin-dentiste",
    "wof:placetype":"venue"
},
  "geometry": {"coordinates":[7.0569009781,46.2975578308],"type":"Point"}
}