{
  "type": "Feature",
  "properties": {
    "iso:country":"CH",
    "sg:address":"St. Gallerstrasse 112",
    "sg:city":"Arbon",
    "sg:orig_category":"RESTAURANTS: TEA-ROOMS",
    "sg:postcode":"9320",
    "sg:province":"Thurgau",
    "wof:name":"Carrillo A.",
    "wof:placetype":"venue"
},
  "geometry": {"coordinates":[9.0096073151,47.6044197083],"type":"Point"}
}