{
  "type": "Feature",
  "properties": {
    "iso:country":"CH",
    "sg:address":"Bahnhofstrasse 25",
    "sg:city":"Huttwil",
    "sg:orig_category":"Instandhaltung U Reparatur von Automobilen",
    "sg:phone":"+41 62 962 23 23",
    "sg:postcode":"4950",
    "sg:province":"Bern",
    "wof:name":"Marcel Rupli Autogarage",
    "wof:placetype":"venue"
},
  "geometry": {"coordinates":[7.8449859619,47.1138076782],"type":"Point"}
}