{
  "type": "Feature",
  "properties": {
    "iso:country":"CH",
    "sg:address":"Hauptstrasse 25",
    "sg:city":"Muttenz",
    "sg:orig_category":"G\u00fcterbef\u00f6rderung im Strassenverkehr",
    "sg:phone":"+41 61 461 46 83",
    "sg:postcode":"4132",
    "sg:province":"Basel-Landschaft",
    "wof:name":"Herzog Kurt & S\u00f6hne Ag",
    "wof:placetype":"venue"
},
  "geometry": {"coordinates":[7.6455760002,47.5238800049],"type":"Point"}
}