{
  "type": "Feature",
  "properties": {
    "iso:country":"CH",
    "sg:address":"La Fayollaz",
    "sg:city":"Villarepos",
    "sg:orig_category":"Rebbau",
    "sg:phone":"+41 26 675 20 67",
    "sg:postcode":"1583",
    "sg:province":"Fribourg",
    "wof:name":"Paul Wyss Viticulteur",
    "wof:placetype":"venue"
},
  "geometry": {"coordinates":[7.0695848465,46.8831977844],"type":"Point"}
}