{
  "type": "Feature",
  "properties": {
    "iso:country":"CH",
    "sg:address":"La Perla",
    "sg:city":"Weggis",
    "sg:orig_category":"Unclassifiable Establishments",
    "sg:postcode":"6353",
    "sg:province":"Luzern",
    "wof:name":"Bachmann Gastst\u00e4tten Ag",
    "wof:placetype":"venue"
},
  "geometry": {"coordinates":[8.4343938828,47.0322952271],"type":"Point"}
}