{
  "type": "Feature",
  "properties": {
    "iso:country":"CH",
    "sg:address":"Sonnenbergstrasse 13",
    "sg:city":"Oberengstringen",
    "sg:orig_category":"Grosshandel mit chemischen Erzeugnissen Herstellung von Seifen, Wasch U Reinigungsmitteln",
    "sg:phone":"+41 17502121",
    "sg:postcode":"8102",
    "sg:province":"Z\u00fcrich",
    "wof:name":"Gastro - Line - Toni Sp\u00e4ni",
    "wof:placetype":"venue"
},
  "geometry": {"coordinates":[8.4611167908,47.4120330811],"type":"Point"}
}