{
  "type": "Feature",
  "properties": {
    "iso:country":"CH",
    "sg:address":"Ettenbergstrasse 24",
    "sg:city":"Wettswil",
    "sg:orig_category":"Herstellung von sonstigen landwirtschaftlichen Maschinen Mechanische Werkst\u00e4tten",
    "sg:phone":"+41 17001456",
    "sg:postcode":"8907",
    "sg:province":"Z\u00fcrich",
    "wof:name":"Hermann Forst Jun. Forst-& Gartenger\u00e4te",
    "wof:placetype":"venue"
},
  "geometry": {"coordinates":[8.4717197418,47.3412437439],"type":"Point"}
}