{
  "type": "Feature",
  "properties": {
    "iso:country":"CH",
    "sg:address":"Via Zurigo",
    "sg:city":"Lugano",
    "sg:orig_category":"Arztpraxen",
    "sg:phone":"+41 91 923 49 36",
    "sg:postcode":"6900",
    "sg:province":"Ticino",
    "wof:name":"Dott.med.giuseppe Paltenghi Medico Generico Fmh",
    "wof:placetype":"venue"
},
  "geometry": {"coordinates":[8.95282,46.012344],"type":"Point"}
}