{
  "type": "Feature",
  "properties": {
    "iso:country":"CH",
    "sg:address":"Engelgasse 5",
    "sg:city":"St.gallen",
    "sg:orig_category":"Gesundheitswesen",
    "sg:postcode":"9000",
    "sg:province":"St. Gallen",
    "wof:name":"Physiotherapie Schildknecht Rudolf",
    "wof:placetype":"venue"
},
  "geometry": {"coordinates":[9.3746795654,47.4264640808],"type":"Point"}
}