{
  "type": "Feature",
  "properties": {
    "iso:country":"CH",
    "sg:address":"Chemin Des Bourratoilles 2 1630 Bulle. Postfach",
    "sg:city":"Bulle",
    "sg:orig_category":"Stukkateurgewerbe, Gipserei U Verputzerei",
    "sg:phone":"+41 26 912 07 51",
    "sg:postcode":"1630",
    "sg:province":"Fribourg",
    "wof:name":"Saklican Aziz Gypserie-peinture Etc",
    "wof:placetype":"venue"
},
  "geometry": {"coordinates":[7.0573811531,46.6186027527],"type":"Point"}
}