{
  "type": "Feature",
  "properties": {
    "iso:country":"CH",
    "sg:address":"S\u00e4listrasse 4",
    "sg:city":"Dulliken",
    "sg:orig_category":"Sportvereine Ballsport Tennis",
    "sg:phone":"+41 62 295 14 66",
    "sg:postcode":"4657",
    "sg:province":"Solothurn",
    "wof:name":"Tc Dulliken",
    "wof:placetype":"venue"
},
  "geometry": {"coordinates":[7.9392848015,47.347454071],"type":"Point"}
}