{
  "type": "Feature",
  "properties": {
    "iso:country":"CH",
    "sg:address":"8835",
    "sg:city":"Feusisberg",
    "sg:orig_category":"Herstellung von Kork, Flecht U Korbwaren",
    "sg:postcode":"8835",
    "sg:province":"Schwyz",
    "wof:name":"Korba Korbwaren En Gros Fr. Achermann & Co.",
    "wof:placetype":"venue"
},
  "geometry": {"coordinates":[8.747595787,47.187297821],"type":"Point"}
}