{
  "type": "Feature",
  "properties": {
    "addr:full":"Ischlagweg 26 Frutigen Bern 3714",
    "addr:housenumber":"26",
    "addr:postcode":"3714",
    "addr:street":"Ischlagweg",
    "iso:country":"CH",
    "sg:address":"Ischlagweg 26",
    "sg:city":"Frutigen",
    "sg:classifiers":[
        {
            "category":"Education",
            "subcategory":"Library",
            "type":"Public Place"
        }
    ],
    "sg:phone":"+41 33 671 28 80",
    "sg:postcode":"3714",
    "sg:province":"Bern",
    "sg:tags":[
        "u",
        "bibliotheken",
        "archive"
    ],
    "wof:name":"Ludothek Frutigen Frau Elisabeth Schmid",
    "wof:placetype":"venue"
},
  "geometry": {"coordinates":[7.649964,46.591274],"type":"Point"}
}