{
  "type": "Feature",
  "properties": {
    "iso:country":"CH",
    "sg:address":"Hessstrasse 27d Liebefeld 3098 K\u00f6niz. Postfach",
    "sg:city":"Liebefeld",
    "sg:orig_category":"Herstellung von Platten, Folien, Schl\u00e4uchen U Profilen aus Kunststoff",
    "sg:postcode":"3097",
    "sg:province":"Bern",
    "wof:name":"J.poltera Industriespritzwerk",
    "wof:placetype":"venue"
},
  "geometry": {"coordinates":[8.7835569382,47.3263511658],"type":"Point"}
}