{
  "type": "Feature",
  "properties": {
    "iso:country":"CH",
    "sg:address":"Marktstrasse 20",
    "sg:city":"Niederuzwil",
    "sg:classifiers":[
        {
            "category":"Professional",
            "subcategory":"Advertising",
            "type":"Services"
        }
    ],
    "sg:phone":"+41 71 952 65 55",
    "sg:postcode":"9244",
    "sg:province":"St. Gallen",
    "sg:tags":[
        "video"
    ],
    "wof:name":"Dvc Digital Video Company Aero Bild",
    "wof:placetype":"venue"
},
  "geometry": {"coordinates":[9.142754,47.447681],"type":"Point"}
}