{
  "type": "Feature",
  "properties": {
    "iso:country":"CH",
    "sg:address":"Schwertstrasse 8",
    "sg:city":"Zug",
    "sg:orig_category":"Markt U Meinungsforschung",
    "sg:postcode":"6300",
    "sg:province":"Zug",
    "wof:name":"Hauri Mario Marketing Und Beratung",
    "wof:placetype":"venue"
},
  "geometry": {"coordinates":[8.5202713013,47.1613540649],"type":"Point"}
}