{
  "type": "Feature",
  "properties": {
    "iso:country":"CH",
    "sg:address":"B\u00e4renwil 193",
    "sg:city":"Langenbruck",
    "sg:orig_category":"RESTAURANTS: TEA-ROOMS",
    "sg:phone":"+41 62 390 11 13",
    "sg:postcode":"4438",
    "sg:province":"Basel-Landschaft",
    "wof:name":"Restaurant Chilchli",
    "wof:placetype":"venue"
},
  "geometry": {"coordinates":[7.7887997627,47.3392028809],"type":"Point"}
}