{
  "type": "Feature",
  "properties": {
    "iso:country":"CH",
    "sg:address":"Frohsinnweg",
    "sg:city":"Gommiswald",
    "sg:orig_category":"Kaminfeger",
    "sg:phone":"+41 55 280 33 54",
    "sg:postcode":"8737",
    "sg:province":"St. Gallen",
    "wof:name":"Martin Imper Kaminfegergesch\u00e4ft",
    "wof:placetype":"venue"
},
  "geometry": {"coordinates":[9.0217952728,47.2328834534],"type":"Point"}
}