{
  "type": "Feature",
  "properties": {
    "iso:country":"CH",
    "sg:address":"Aarauerstr. 37",
    "sg:city":"Sch\u00f6nenwerd",
    "sg:orig_category":"Herstellung von Automobilen",
    "sg:postcode":"5012",
    "sg:province":"Solothurn",
    "wof:name":"Humm Otto Nutzfahrzeuge",
    "wof:placetype":"venue"
},
  "geometry": {"coordinates":[8.0091524124,47.3739089966],"type":"Point"}
}