{
  "type": "Feature",
  "properties": {
    "iso:country":"CH",
    "sg:address":"Place De La Fontaine 4",
    "sg:city":"Peseux",
    "sg:classifiers":[
        {
            "category":"Bars & Pubs",
            "type":"Food & Drink"
        }
    ],
    "sg:phone":"+41 26 652 06 08",
    "sg:postcode":"2034",
    "sg:province":"Neuch\u00e2tel",
    "sg:tags":[
        "restaurant"
    ],
    "wof:name":"Bar-pizzeria Le Z\u00e9nith",
    "wof:placetype":"venue"
},
  "geometry": {"coordinates":[6.915029,46.692497],"type":"Point"}
}