{
  "type": "Feature",
  "properties": {
    "iso:country":"CH",
    "sg:address":"Oberdorf",
    "sg:city":"Raperswilen",
    "sg:orig_category":"Handelsvermittlung U Grosshandel Sonstiger Grosshandel",
    "sg:phone":"+41 52 763 26 00",
    "sg:postcode":"8558",
    "sg:province":"Thurgau",
    "wof:name":"H\u00fcga B. Garzotto & V. H\u00fcrzeler Import & Handel",
    "wof:placetype":"venue"
},
  "geometry": {"coordinates":[9.0653276443,47.6416549683],"type":"Point"}
}