{
  "type": "Feature",
  "properties": {
    "addr:full":"4312 Magden Aargau 4312",
    "addr:postcode":"4312;4312",
    "iso:country":"CH",
    "sg:address":"4312",
    "sg:city":"Magden",
    "sg:classifiers":[
        {
            "category":"Education",
            "subcategory":"Library",
            "type":"Public Place"
        }
    ],
    "sg:phone":"+41 61 841 29 33",
    "sg:postcode":"4312",
    "sg:province":"Aargau",
    "sg:tags":[
        "u",
        "bibliotheken",
        "archive"
    ],
    "wof:name":"Gemeinde-& Volksbibliothek",
    "wof:placetype":"venue"
},
  "geometry": {"coordinates":[7.813089,47.528419],"type":"Point"}
}