{
  "type": "Feature",
  "properties": {
    "iso:country":"CH",
    "sg:address":"Voa Nova 28",
    "sg:city":"Vaz/obervaz",
    "sg:classifiers":[
        {
            "category":"Restaurant",
            "type":"Food & Drink"
        }
    ],
    "sg:phone":"+41 81 384 11 44",
    "sg:postcode":"7082",
    "sg:province":"Graubunden",
    "wof:name":"Restaurant Junkerhaus",
    "wof:placetype":"venue"
},
  "geometry": {"coordinates":[9.5544900894,46.713809967],"type":"Point"}
}