{
  "type": "Feature",
  "properties": {
    "iso:country":"CH",
    "sg:address":"Fr\u00f6schmattstrasse 4",
    "sg:city":"Pratteln",
    "sg:orig_category":"Zahnarztpraxen",
    "sg:phone":"+41 61 821 20 60",
    "sg:postcode":"4133",
    "sg:province":"Basel-Landschaft",
    "wof:name":"Dr. Med. Dent. Vera Wyss Zahn\u00e4rztin",
    "wof:placetype":"venue"
},
  "geometry": {"coordinates":[7.6995611191,47.5221633911],"type":"Point"}
}