{
  "type": "Feature",
  "properties": {
    "iso:country":"CH",
    "sg:address":"Moosstr. 12 Abtwil",
    "sg:city":"Gaiserwald",
    "sg:orig_category":"Reiseb\u00fcros U Reiseveranstalter",
    "sg:phone":"+41 71 313 99 00",
    "sg:postcode":"9030",
    "sg:province":"St. Gallen",
    "wof:name":"D\u00e4hler, Karl, Reisen Und Transporte",
    "wof:placetype":"venue"
},
  "geometry": {"coordinates":[9.3191003799,47.4219245911],"type":"Point"}
}