{
  "type": "Feature",
  "properties": {
    "iso:country":"CH",
    "sg:address":"Via Cantonale 18",
    "sg:city":"Caslano",
    "sg:orig_category":"Unclassifiable Establishments",
    "sg:postcode":"6987",
    "sg:province":"Ticino",
    "wof:name":"Golden Island Sa",
    "wof:placetype":"venue"
},
  "geometry": {"coordinates":[8.8775882721,45.9795799255],"type":"Point"}
}