{
  "type": "Feature",
  "properties": {
    "addr:full":"Baumgartiweg 4 Wimmis Bern 3752",
    "addr:housenumber":"4",
    "addr:postcode":"3752",
    "addr:street":"Baumgartiweg;Bern",
    "iso:country":"CH",
    "sg:address":"Baumgartiweg 4",
    "sg:city":"Wimmis",
    "sg:orig_category":"Betrieb von Taxis",
    "sg:phone":"+41 33 657 17 17",
    "sg:postcode":"3752",
    "sg:province":"Bern",
    "wof:name":"Roland Zaugg Taxi",
    "wof:placetype":"venue"
},
  "geometry": {"coordinates":[7.638852,46.681816],"type":"Point"}
}