{
  "type": "Feature",
  "properties": {
    "iso:country":"CH",
    "sg:address":"Mittlere Strasse 79",
    "sg:city":"Basel",
    "sg:orig_category":"Kinderkrippen U horte",
    "sg:phone":"+41 61 381 75 34",
    "sg:postcode":"4056",
    "sg:province":"Basel-Stadt",
    "wof:name":"Kinderkrippe St.peter",
    "wof:placetype":"venue"
},
  "geometry": {"coordinates":[7.577009201,47.5623817444],"type":"Point"}
}