{
  "type": "Feature",
  "properties": {
    "iso:country":"CH",
    "sg:address":"Jakob-st\u00e4mpfli-strasse 94",
    "sg:city":"Biel/bienne",
    "sg:orig_category":"Grosshandel mit Uhren Herstellung von Uhren",
    "sg:phone":"+41 26 439 92 44",
    "sg:postcode":"2502",
    "sg:province":"Bern",
    "wof:name":"Fournitures Et Outils D'horlogerie Furka Sa",
    "wof:placetype":"venue"
},
  "geometry": {"coordinates":[7.1612091064,46.7757720947],"type":"Point"}
}