{
  "type": "Feature",
  "properties": {
    "iso:country":"CH",
    "sg:address":"4581",
    "sg:city":"K\u00fcttigkofen",
    "sg:classifiers":[
        {
            "category":"Restaurant",
            "type":"Food & Drink"
        }
    ],
    "sg:phone":"+41 32 677 10 07",
    "sg:postcode":"4581",
    "sg:province":"Solothurn",
    "wof:name":"Restaurant Bismarck",
    "wof:placetype":"venue"
},
  "geometry": {"coordinates":[7.5138602257,47.1498794556],"type":"Point"}
}