{
  "type": "Feature",
  "properties": {
    "iso:country":"CH",
    "sg:address":"Werkstrasse 36",
    "sg:city":"Lyss",
    "sg:classifiers":[
        {
            "category":"Wholesale",
            "subcategory":"Medical Equipment & Supplies",
            "type":"Manufacturing & Wholesale Goods"
        }
    ],
    "sg:phone":"+41 32 386 15 05",
    "sg:postcode":"3250",
    "sg:province":"Bern",
    "sg:tags":[
        "measuring",
        "physiotherapy",
        "diagnostic"
    ],
    "wof:name":"Map Medizintechnik F\u00fcr Arzt Und Patient (schweiz) Gmbh",
    "wof:placetype":"venue"
},
  "geometry": {"coordinates":[7.2951288223,47.0709762573],"type":"Point"}
}