{
  "type": "Feature",
  "properties": {
    "iso:country":"CH",
    "sg:address":"Langensandstrasse 78 6005 Luzern. Postfach",
    "sg:city":"Luzern",
    "sg:orig_category":"Vermietung U Verpachtung von eigenen Immobilien",
    "sg:phone":"+41 41 361 00 44",
    "sg:postcode":"6003",
    "sg:province":"Luzern",
    "wof:name":"Brunner Immobilien Und Treuhand Immobilien U. Treuhandunternehmen",
    "wof:placetype":"venue"
},
  "geometry": {"coordinates":[8.3293104172,47.034538269],"type":"Point"}
}