{
  "type": "Feature",
  "properties": {
    "iso:country":"CH",
    "sg:address":"Schipferstrasse 6",
    "sg:city":"Thalwil",
    "sg:orig_category":"Kauf U Verkauf von Immobilien auf eigene Rechnung Vermittlung von Immobilien",
    "sg:phone":"+41 17222600",
    "sg:postcode":"8800",
    "sg:province":"Z\u00fcrich",
    "wof:name":"Br\u00e4ndli Verwaltungen Und Immobilien",
    "wof:placetype":"venue"
},
  "geometry": {"coordinates":[8.5751247406,47.2834854126],"type":"Point"}
}