{
  "type": "Feature",
  "properties": {
    "iso:country":"CH",
    "sg:address":"Rue Baudit 2",
    "sg:city":"Gen\u00e8ve",
    "sg:orig_category":"Detailhandel mit Schuhen",
    "sg:phone":"+41 22 733 00 10",
    "sg:postcode":"1201",
    "sg:province":"Gen\u00e8ve",
    "wof:name":"Dansko-helvesko Chaussures Confort",
    "wof:placetype":"venue"
},
  "geometry": {"coordinates":[6.1388220787,46.2100372314],"type":"Point"}
}