{
  "type": "Feature",
  "properties": {
    "iso:country":"CH",
    "sg:address":"S\u00fcdstrasse 115 8000 Z\u00fcrich. Postfach",
    "sg:city":"Z\u00fcrich",
    "sg:orig_category":"Hochschulen U h\u00f6here Ausbildung",
    "sg:phone":"+41 13816120",
    "sg:postcode":"8001",
    "sg:province":"Z\u00fcrich",
    "wof:name":"S\u00fcdhalde Berufschule F. Psychiatrische Krankenpflege; Bau, Unterhalt",
    "wof:placetype":"venue"
},
  "geometry": {"coordinates":[8.568116188,47.3497276306],"type":"Point"}
}