{
  "type": "Feature",
  "properties": {
    "iso:country":"CH",
    "sg:address":"Baarerstrasse 110a 6300 Zug. Postfach 2648",
    "sg:city":"Zug",
    "sg:orig_category":"Grosshandel mit B\u00fcromaschinen Grosshandel mit Datenverarbeitungsger\u00e4ten",
    "sg:phone":"+41 41 769 77 99",
    "sg:postcode":"6302",
    "sg:province":"Zug",
    "wof:name":"Wut Edv-support, Utzinger Walter",
    "wof:placetype":"venue"
},
  "geometry": {"coordinates":[8.5189380646,47.1798820496],"type":"Point"}
}