{
  "type": "Feature",
  "properties": {
    "iso:country":"CH",
    "sg:address":"Adlerplatz 1",
    "sg:city":"Sch\u00fcbelbach",
    "sg:orig_category":"RESTAURANTS: TEA-ROOMS",
    "sg:postcode":"8862",
    "sg:province":"Schwyz",
    "wof:name":"Habermacher Ren\u00e9",
    "wof:placetype":"venue"
},
  "geometry": {"coordinates":[8.9290103912,47.1731338501],"type":"Point"}
}