{
  "type": "Feature",
  "properties": {
    "iso:country":"CH",
    "sg:address":"Au Village",
    "sg:city":"Seiry",
    "sg:classifiers":[
        {
            "category":"Professional",
            "subcategory":"Advertising",
            "type":"Services"
        }
    ],
    "sg:phone":"+41 26 665 29 20",
    "sg:postcode":"1474",
    "sg:province":"Fribourg",
    "sg:tags":[
        "processing",
        "data",
        "agency",
        "provider"
    ],
    "wof:name":"Informatique-help",
    "wof:placetype":"venue"
},
  "geometry": {"coordinates":[6.829932,46.812237],"type":"Point"}
}