{
  "type": "Feature",
  "properties": {
    "iso:country":"CH",
    "sg:address":"Rheinstrasse 64 7000 Chur. Postfach",
    "sg:city":"Chur",
    "sg:orig_category":"Detailhandel mit Fleisch U Fleischwaren",
    "sg:postcode":"7000",
    "sg:province":"Graubunden",
    "wof:name":"Pferdemetzgerei Torri Jrene",
    "wof:placetype":"venue"
},
  "geometry": {"coordinates":[9.5219669342,46.854850769],"type":"Point"}
}