{
  "type": "Feature",
  "properties": {
    "iso:country":"CH",
    "sg:address":"Trisnera Via 47",
    "sg:city":"Losone",
    "sg:orig_category":"Herstellung von Teppichen",
    "sg:phone":"+41 91 791 00 51",
    "sg:postcode":"6616",
    "sg:province":"Ticino",
    "wof:name":"Pfyffer Von Altishofen Urs",
    "wof:placetype":"venue"
},
  "geometry": {"coordinates":[8.7587738037,46.1731758118],"type":"Point"}
}