{
  "type": "Feature",
  "properties": {
    "iso:country":"CH",
    "sg:address":"Hotzestrasse 29 8006 Z\u00fcrich. Postfach",
    "sg:city":"Z\u00fcrich",
    "sg:orig_category":"Pensionskassen",
    "sg:postcode":"8006",
    "sg:province":"Z\u00fcrich",
    "wof:name":"Altersf\u00fcrsorgestiftung Der Firma Zahn Ag",
    "wof:placetype":"venue"
},
  "geometry": {"coordinates":[7.5580430031,46.9397926331],"type":"Point"}
}