{
  "type": "Feature",
  "properties": {
    "iso:country":"CH",
    "sg:address":"Wiesen 2479",
    "sg:city":"Herisau",
    "sg:orig_category":"Sonderschulen Wohnheime f\u00fcr Kinder U Jugendliche",
    "sg:phone":"+41 71 351 16 02",
    "sg:postcode":"9100",
    "sg:province":"Appenzell Ausserrhoden",
    "wof:name":"Kinderheim Gott Hilft",
    "wof:placetype":"venue"
},
  "geometry": {"coordinates":[9.2782888412,47.3871612549],"type":"Point"}
}