{
  "type": "Feature",
  "properties": {
    "iso:country":"CH",
    "sg:address":"Via Mercoli 2",
    "sg:city":"Lugano",
    "sg:orig_category":"Sonstige Kultur U Unterhaltungseinrichtungen",
    "sg:postcode":"6900",
    "sg:province":"Ticino",
    "wof:name":"L'angelo Rosa Di Portaluri Giorgio",
    "wof:placetype":"venue"
},
  "geometry": {"coordinates":[8.9556922913,46.0157394409],"type":"Point"}
}