{
  "type": "Feature",
  "properties": {
    "iso:country":"CH",
    "sg:address":"Gotthardstrasse 19 8800 Thalwil. Postfach 1428",
    "sg:city":"Thalwil",
    "sg:orig_category":"Drogerien Parf\u00fcmerien U sonstiger Detailhandel mit kosmetischen Artikeln U K\u00f6rperpflegemitteln",
    "sg:phone":"+41 17200618",
    "sg:postcode":"8801",
    "sg:province":"Z\u00fcrich",
    "wof:name":"Impuls Drogerie Hirsig",
    "wof:placetype":"venue"
},
  "geometry": {"coordinates":[8.5639314651,47.2952384949],"type":"Point"}
}