{
  "type": "Feature",
  "properties": {
    "iso:country":"CH",
    "sg:address":"Walkestrasse 31 8400 Winterthur. Postfach",
    "sg:city":"Winterthur",
    "sg:orig_category":"Grosshandel mit Textilien",
    "sg:postcode":"8400",
    "sg:province":"Z\u00fcrich",
    "wof:name":"Keller + Fontanez Im Und Export",
    "wof:placetype":"venue"
},
  "geometry": {"coordinates":[8.5448770523,47.3288841248],"type":"Point"}
}