{
  "type": "Feature",
  "properties": {
    "iso:country":"CH",
    "sg:address":"G\u00fctli 1136",
    "sg:city":"Walzenhausen",
    "sg:orig_category":"Arztpraxen",
    "sg:phone":"+41 71 888 52 52",
    "sg:postcode":"9428",
    "sg:province":"Appenzell Ausserrhoden",
    "wof:name":"Dr.med.inigo G\u00f6tz Arzt F\u00fcr Allgemeine Medizin",
    "wof:placetype":"venue"
},
  "geometry": {"coordinates":[9.608002,47.447456],"type":"Point"}
}