{
  "type": "Feature",
  "properties": {
    "iso:country":"CH",
    "sg:address":"Hasel",
    "sg:city":"B\u00fcrchen",
    "sg:orig_category":"Organisationen des Gesundheitswesen",
    "sg:phone":"+41 27 934 13 69",
    "sg:postcode":"3935",
    "sg:province":"Valais",
    "wof:name":"Samariterverein B\u00fcrchen",
    "wof:placetype":"venue"
},
  "geometry": {"coordinates":[7.8162169456,46.2855949402],"type":"Point"}
}