{
  "type": "Feature",
  "properties": {
    "iso:country":"CH",
    "sg:address":"Seetalstrasse 2",
    "sg:city":"Seon",
    "sg:orig_category":"Allgemeiner Hoch U Tiefbau Innenausbau",
    "sg:phone":"+41 62 775 00 27",
    "sg:postcode":"5703",
    "sg:province":"Aargau",
    "wof:name":"Architektur + Ausf\u00fchrung Von Umbauten + Sanierungen Rinova Bock D.",
    "wof:placetype":"venue"
},
  "geometry": {"coordinates":[8.15976,47.352352],"type":"Point"}
}