{
  "type": "Feature",
  "properties": {
    "iso:country":"CH",
    "sg:address":"Hirschengraben 33 B 6000 Luzern. Postfach",
    "sg:city":"Luzern",
    "sg:orig_category":"Softwareentwicklung U beratung",
    "sg:postcode":"6003",
    "sg:province":"Luzern",
    "wof:name":"Starchem Gmbh",
    "wof:placetype":"venue"
},
  "geometry": {"coordinates":[8.3019132614,47.0495109558],"type":"Point"}
}