{
  "type": "Feature",
  "properties": {
    "iso:country":"CH",
    "sg:address":"Therwilerstrasse 7",
    "sg:city":"Basel",
    "sg:orig_category":"Wohnheime",
    "sg:phone":"+41 61 206 97 60",
    "sg:postcode":"4054",
    "sg:province":"Basel-Stadt",
    "wof:name":"Stiftung Melchior",
    "wof:placetype":"venue"
},
  "geometry": {"coordinates":[7.577673912,47.5508804321],"type":"Point"}
}