{
  "type": "Feature",
  "properties": {
    "iso:country":"CH",
    "sg:address":"Neuengasse 39",
    "sg:city":"Biel/bienne",
    "sg:orig_category":"Grosshandel mit B\u00fcromaschinen Grosshandel mit Datenverarbeitungsger\u00e4ten",
    "sg:phone":"+41 32 325 35 53",
    "sg:postcode":"2502",
    "sg:province":"Bern",
    "wof:name":"Omnitron Zankl Peter",
    "wof:placetype":"venue"
},
  "geometry": {"coordinates":[7.2452859879,47.1385612488],"type":"Point"}
}