{
  "type": "Feature",
  "properties": {
    "iso:country":"CH",
    "sg:address":"Rieden 3",
    "sg:city":"Stans",
    "sg:classifiers":[
        {
            "category":"Autos & Motor Vehicles",
            "subcategory":"Auto Supplies",
            "type":"Retail Goods"
        }
    ],
    "sg:phone":"+41 848 840 890",
    "sg:postcode":"6370",
    "sg:province":"Nidwalden",
    "sg:tags":[
        "automobile",
        "accessory"
    ],
    "wof:name":"Pansport Autos Sa",
    "wof:placetype":"venue"
},
  "geometry": {"coordinates":[6.821551,47.094254],"type":"Point"}
}