{
  "type": "Feature",
  "properties": {
    "iso:country":"CH",
    "sg:address":"Alte Landstrasse 7",
    "sg:city":"Balsthal",
    "sg:orig_category":"Unclassifiable Establishments",
    "sg:phone":"+41 79 210 41 83",
    "sg:postcode":"4710",
    "sg:province":"Solothurn",
    "wof:name":"S-dienst Julmy B.",
    "wof:placetype":"venue"
},
  "geometry": {"coordinates":[7.6817159653,47.3124084473],"type":"Point"}
}