{
  "type": "Feature",
  "properties": {
    "iso:country":"CH",
    "sg:address":"Steinengraben 79 4051 Basel. Postfach",
    "sg:city":"Basel",
    "sg:orig_category":"Wirtschaftspr\u00fcfung, Steuerberatung U Treuhand",
    "sg:postcode":"4051",
    "sg:province":"Basel-Stadt",
    "wof:name":"Alltax Ag Treuhandgesellschaft",
    "wof:placetype":"venue"
},
  "geometry": {"coordinates":[7.5344901085,47.545539856],"type":"Point"}
}