{
  "type": "Feature",
  "properties": {
    "iso:country":"CH",
    "sg:address":"Loretostrasse 42",
    "sg:city":"Lichtensteig",
    "sg:orig_category":"Werbung",
    "sg:phone":"+41 71 988 49 65",
    "sg:postcode":"9620",
    "sg:province":"St. Gallen",
    "wof:name":"Tuttosprint Di Guerra Graziano",
    "wof:placetype":"venue"
},
  "geometry": {"coordinates":[9.0858297348,47.3270301819],"type":"Point"}
}