{
  "type": "Feature",
  "properties": {
    "iso:country":"CH",
    "sg:address":"Br\u00fcgglerweg 9",
    "sg:city":"Bern",
    "sg:orig_category":"Unternehmensberatung",
    "sg:postcode":"3000",
    "sg:province":"Bern",
    "wof:name":"Artemis Management Ag",
    "wof:placetype":"venue"
},
  "geometry": {"coordinates":[7.4613070488,46.9481315613],"type":"Point"}
}