{
  "type": "Feature",
  "properties": {
    "iso:country":"CH",
    "sg:address":"Erlenstrasse 9",
    "sg:city":"Ennetaach",
    "sg:orig_category":"Sportvereine Turnen Vereine Damen",
    "sg:phone":"+41 71 648 34 69",
    "sg:postcode":"8586",
    "sg:province":"Thurgau",
    "wof:name":"Turnerinnenverein Oberaach",
    "wof:placetype":"venue"
},
  "geometry": {"coordinates":[9.217713356,47.5491981506],"type":"Point"}
}