{
  "type": "Feature",
  "properties": {
    "iso:country":"CH",
    "sg:address":"Untereichli 6 6405 Immensee. Postfach",
    "sg:city":"Immensee",
    "sg:orig_category":"Eisenbahnverkehr",
    "sg:phone":"+41 41 850 66 70",
    "sg:postcode":"6405",
    "sg:province":"Schwyz",
    "wof:name":"Oberholzer Werner",
    "wof:placetype":"venue"
},
  "geometry": {"coordinates":[8.4608488083,47.0945854187],"type":"Point"}
}