{
  "type": "Feature",
  "properties": {
    "iso:country":"CH",
    "sg:address":"Schwelliseestrasse",
    "sg:city":"Innerarosa",
    "sg:orig_category":"HOTELS: OHNE RESTAURANT",
    "sg:phone":"+41 81 377 12 97",
    "sg:postcode":"7050",
    "sg:province":"Graubunden",
    "wof:name":"Hotel Belri",
    "wof:placetype":"venue"
},
  "geometry": {"coordinates":[9.6588115692,46.7753295898],"type":"Point"}
}