{
  "type": "Feature",
  "properties": {
    "iso:country":"CH",
    "sg:address":"Schulweg 3",
    "sg:city":"Ebertswil",
    "sg:orig_category":"Grosshandel mit Foto U Kinoger\u00e4ten, feinmechanischen U optischen Erzeugnissen Maschinen and Apparate",
    "sg:phone":"+41 17641019",
    "sg:postcode":"8925",
    "sg:province":"Z\u00fcrich",
    "wof:name":"Copyphot Sa",
    "wof:placetype":"venue"
},
  "geometry": {"coordinates":[8.5483608246,47.2269363403],"type":"Point"}
}