{
  "type": "Feature",
  "properties": {
    "addr:full":"Hauptgasse 32 6130 Willisau. Postfach Willisau Luzern 6130",
    "addr:housenumber":"32",
    "addr:postcode":"6130 willisau. postfach;6130",
    "addr:street":"Hauptgasse",
    "iso:country":"CH",
    "sg:address":"Hauptgasse 32 6130 Willisau. Postfach",
    "sg:city":"Willisau",
    "sg:orig_category":"Detailhandel mit Beleuchtungs U Haushaltsgegenst\u00e4nden Detailhandel mit elektrischen Haushalts-,Radio",
    "sg:phone":"+41 41 970 17 18",
    "sg:postcode":"6130",
    "sg:province":"Luzern",
    "wof:name":"Gisler Ag, Haushaltartikel Und Eisenwaren, Willisau",
    "wof:placetype":"venue"
},
  "geometry": {"coordinates":[7.990137,47.120636],"type":"Point"}
}