{
  "type": "Feature",
  "properties": {
    "iso:country":"CH",
    "sg:address":"Bischofszellerstrasse 343",
    "sg:city":"Arnegg",
    "sg:orig_category":"Detailhandel mit Blumen U Pflanzen",
    "sg:phone":"+41 71 385 84 84",
    "sg:postcode":"9212",
    "sg:province":"St. Gallen",
    "wof:name":"Kurt & Beatrice H\u00e4ssig Blumenhaus",
    "wof:placetype":"venue"
},
  "geometry": {"coordinates":[9.255398,47.443504],"type":"Point"}
}