{
  "type": "Feature",
  "properties": {
    "iso:country":"CH",
    "sg:address":"Hardstrasse 24",
    "sg:city":"Strengelbach",
    "sg:orig_category":"Unclassifiable Establishments",
    "sg:postcode":"4802",
    "sg:province":"Aargau",
    "wof:name":"Planet'choc Sa",
    "wof:placetype":"venue"
},
  "geometry": {"coordinates":[6.1105661392,46.2317199707],"type":"Point"}
}