{
  "type": "Feature",
  "properties": {
    "iso:country":"CH",
    "sg:address":"Dammstrasse D",
    "sg:city":"Landquart",
    "sg:orig_category":"Bau U Wohngenossenschaften",
    "sg:phone":"+41 81 322 25 93",
    "sg:postcode":"7302",
    "sg:province":"Graubunden",
    "wof:name":"Eisenbahner-wohnbaugen.",
    "wof:placetype":"venue"
},
  "geometry": {"coordinates":[9.56266,46.967781],"type":"Point"}
}