{
  "type": "Feature",
  "properties": {
    "iso:country":"CH",
    "sg:address":"Melchtalstrasse 11",
    "sg:city":"Bern",
    "sg:orig_category":"Organisationen des Gesundheitswesen",
    "sg:phone":"+41 31 961 27 27",
    "sg:postcode":"3014",
    "sg:province":"Bern",
    "wof:name":"Samariterverein Wabern-spiegel",
    "wof:placetype":"venue"
},
  "geometry": {"coordinates":[7.4570541382,46.9613647461],"type":"Point"}
}