{
  "type": "Feature",
  "properties": {
    "iso:country":"CH",
    "sg:address":"8645 Jona. Postfach 2132",
    "sg:city":"Jona",
    "sg:orig_category":"Schulpflegen",
    "sg:phone":"+41 55 210 54 32",
    "sg:postcode":"8645",
    "sg:province":"St. Gallen",
    "wof:name":"Primarschulgemeinde Jona",
    "wof:placetype":"venue"
},
  "geometry": {"coordinates":[8.8452396393,47.2296905518],"type":"Point"}
}