{
  "type": "Feature",
  "properties": {
    "iso:country":"CH",
    "sg:address":"Kolinplatz 1",
    "sg:city":"Zug",
    "sg:orig_category":"Sonstige mit der Informatik verbundene T\u00e4tigkeiten",
    "sg:postcode":"6300",
    "sg:province":"Zug",
    "wof:name":"Sai - Scuola E Assistenza Informatica Di Tedeschi Raffaele Apparecchiature Informatiche; Vendita, Installazione Ecc",
    "wof:placetype":"venue"
},
  "geometry": {"coordinates":[8.9068098068,46.3802680969],"type":"Point"}
}