{
  "type": "Feature",
  "properties": {
    "iso:country":"CH",
    "sg:address":"Dufourstrasse 7",
    "sg:city":"Kreuzlingen",
    "sg:orig_category":"Sonstige Kultur U Unterhaltungseinrichtungen",
    "sg:phone":"+41 19105689",
    "sg:postcode":"8280",
    "sg:province":"Thurgau",
    "wof:name":"Centro Ricreativo Stranieri",
    "wof:placetype":"venue"
},
  "geometry": {"coordinates":[8.6030521393,47.3055725098],"type":"Point"}
}