{
  "type": "Feature",
  "properties": {
    "iso:country":"CH",
    "sg:address":"Fontaines Chemin Des 2 1297 Founex. Postfach",
    "sg:city":"Founex",
    "sg:orig_category":"Finanzierungsinstitutionen",
    "sg:phone":"+41 21 960 41 45",
    "sg:postcode":"1297",
    "sg:province":"Vaud",
    "wof:name":"Livorina Sa",
    "wof:placetype":"venue"
},
  "geometry": {"coordinates":[6.924407959,46.3974494934],"type":"Point"}
}