{
  "type": "Feature",
  "properties": {
    "iso:country":"CH",
    "sg:address":"Neufeldstrasse 12a 3604 Thun. Postfach",
    "sg:city":"Thun",
    "sg:orig_category":"Non-Classified Establishments",
    "sg:postcode":"3604",
    "sg:province":"Bern",
    "wof:name":"B\u00fcko Webdesign Gmbh",
    "wof:placetype":"venue"
},
  "geometry": {"coordinates":[7.6119170189,46.7392158508],"type":"Point"}
}