{
  "type": "Feature",
  "properties": {
    "iso:country":"CH",
    "sg:address":"Eichenweg 8",
    "sg:city":"Embrach",
    "sg:orig_category":"Herstellung von elektronischen Bauelementen",
    "sg:phone":"+41 18656151",
    "sg:postcode":"8424",
    "sg:province":"Z\u00fcrich",
    "wof:name":"Fischer I. Service Elektronische Artikel; Import, Service. Bewaffneter Personenschutz Usw",
    "wof:placetype":"venue"
},
  "geometry": {"coordinates":[8.5948553085,47.5086784363],"type":"Point"}
}