{
  "type": "Feature",
  "properties": {
    "iso:country":"CH",
    "sg:address":"6654",
    "sg:city":"Cavigliano",
    "sg:orig_category":"Sonstiger Fachdetailhandel mit Nahrungsmitteln, Getr\u00e4nken U Tabak in Verkaufsr\u00e4umen",
    "sg:phone":"+41 91 796 25 34",
    "sg:postcode":"6654",
    "sg:province":"Ticino",
    "wof:name":"Negozio Al Centro Sagl Negozio Usego",
    "wof:placetype":"venue"
},
  "geometry": {"coordinates":[8.7089300156,46.1919212341],"type":"Point"}
}