{
  "type": "Feature",
  "properties": {
    "iso:country":"CH",
    "sg:address":"Hauptstrasse 63",
    "sg:city":"Reiden",
    "sg:orig_category":"Detailhandel mit Waren verschiedener Art, Hauptrichtung Nahrungsmittel",
    "sg:phone":"+41 62 749 10 70",
    "sg:postcode":"6260",
    "sg:province":"Luzern",
    "wof:name":"Coop Laden Reiden",
    "wof:placetype":"venue"
},
  "geometry": {"coordinates":[7.9707732201,47.248298645],"type":"Point"}
}