{
  "type": "Feature",
  "properties": {
    "iso:country":"CH",
    "sg:address":"Place Du Midi 36",
    "sg:city":"Sion",
    "sg:orig_category":"Physiotherapie",
    "sg:phone":"+41 22 731 21 20",
    "sg:postcode":"1950",
    "sg:province":"Valais",
    "wof:name":"Jean-b\u00e9n\u00e9dict Bonjour Physioth\u00e9rapie",
    "wof:placetype":"venue"
},
  "geometry": {"coordinates":[6.1414251328,46.1833114624],"type":"Point"}
}