{
  "type": "Feature",
  "properties": {
    "iso:country":"CH",
    "sg:address":"Buchenweg 20",
    "sg:city":"B\u00fcetigen",
    "sg:orig_category":"Sportvereine Velo Rad-& Motorfahrer-Bund SRB",
    "sg:postcode":"3263",
    "sg:province":"Bern",
    "wof:name":"Rrc Jeunesse Br\u00fcgg-aegerten",
    "wof:placetype":"venue"
},
  "geometry": {"coordinates":[7.339389801,47.1036529541],"type":"Point"}
}