{
  "type": "Feature",
  "properties": {
    "addr:full":"B\u00fcrgerheimstrasse 10/12 W\u00e4denswil Z\u00fcrich 8820",
    "addr:housenumber":"10 / 12",
    "addr:postcode":"8820",
    "addr:street":"Buergerheimstrasse;Waedenswil Zuerich",
    "iso:country":"CH",
    "sg:address":"B\u00fcrgerheimstrasse 10/12",
    "sg:city":"W\u00e4denswil",
    "sg:classifiers":[
        {
            "category":"Social Services",
            "subcategory":"Retirement Home",
            "type":"Services"
        }
    ],
    "sg:phone":"+41 17801620",
    "sg:postcode":"8820",
    "sg:province":"Z\u00fcrich",
    "sg:tags":[
        "pflegeheime",
        "u",
        "alters"
    ],
    "wof:name":"Altersheim Frohmatt",
    "wof:placetype":"venue"
},
  "geometry": {"coordinates":[8.661991,47.230095],"type":"Point"}
}