{
  "type": "Feature",
  "properties": {
    "iso:country":"CH",
    "sg:address":"Beckenhofstrasse 61",
    "sg:city":"Z\u00fcrich",
    "sg:orig_category":"Softwareentwicklung U beratung",
    "sg:phone":"+41 13634589",
    "sg:postcode":"8006",
    "sg:province":"Z\u00fcrich",
    "wof:name":"Treibauf Nicolas Schwotzer Software",
    "wof:placetype":"venue"
},
  "geometry": {"coordinates":[8.5400533676,47.3866500854],"type":"Point"}
}