{
  "type": "Feature",
  "properties": {
    "addr:full":"Glattalstrasse 207 8153 R\u00fcmlang. Postfach R\u00fcmlang Z\u00fcrich 8153",
    "addr:housenumber":"207",
    "addr:postcode":"8153;8153",
    "addr:street":"Glattalstrasse;Postfach Ruemlang Zuerich",
    "iso:country":"CH",
    "sg:address":"Glattalstrasse 207 8153 R\u00fcmlang. Postfach",
    "sg:city":"R\u00fcmlang",
    "sg:orig_category":"Aufz\u00fcge and Rolltreppen Herstellung",
    "sg:phone":"+41 18170808",
    "sg:postcode":"8153",
    "sg:province":"Z\u00fcrich",
    "wof:name":"Thyssen Aufz\u00fcge Ag",
    "wof:placetype":"venue"
},
  "geometry": {"coordinates":[8.530143,47.44936],"type":"Point"}
}