{
  "type": "Feature",
  "properties": {
    "iso:country":"CH",
    "sg:address":"Chemin Des L\u00e9ch\u00e8res 10 1217 Meyrin. Postfach",
    "sg:city":"Meyrin",
    "sg:orig_category":"Instandhaltung U Reparatur von Automobilen",
    "sg:phone":"+41 27 979 11 68",
    "sg:postcode":"1217",
    "sg:province":"Gen\u00e8ve",
    "wof:name":"Garage Doveria",
    "wof:placetype":"venue"
},
  "geometry": {"coordinates":[8.0550851822,46.195930481],"type":"Point"}
}