{
  "type": "Feature",
  "properties": {
    "iso:country":"CH",
    "sg:address":"Champ-pamont Chemin De 22",
    "sg:city":"Cheseaux-lausanne",
    "sg:orig_category":"Fachdetailhandel in Verkaufsr\u00e4umen",
    "sg:phone":"+41 21 731 51 92",
    "sg:postcode":"1033",
    "sg:province":"Vaud",
    "wof:name":"Torsade, Sophie Maret Chabloz",
    "wof:placetype":"venue"
},
  "geometry": {"coordinates":[6.6048598289,46.5855407715],"type":"Point"}
}