{
  "type": "Feature",
  "properties": {
    "iso:country":"CH",
    "sg:address":"Via Dei Pioppi 6593 Cadenazzo. Postfach Caselle Postale 219",
    "sg:city":"Cadenazzo",
    "sg:orig_category":"Herstellung U Zusammensetzung von Uhren Herstellung von Uhren",
    "sg:phone":"+41 22 884 00 55",
    "sg:postcode":"6593",
    "sg:province":"Ticino",
    "wof:name":"Weil Raymond Sa",
    "wof:placetype":"venue"
},
  "geometry": {"coordinates":[6.1240720749,46.1784210205],"type":"Point"}
}