{
  "type": "Feature",
  "properties": {
    "iso:country":"CH",
    "sg:address":"Marktgasse 41",
    "sg:city":"Winterthur",
    "sg:orig_category":"Detailhandel mit Brillen U anderen Sehhilfen Detailhandel mit medizinischen U orthop\u00e4dischen Artikel",
    "sg:phone":"+41 12210557",
    "sg:postcode":"8400",
    "sg:province":"Z\u00fcrich",
    "wof:name":"H\u00f6rservice Ag",
    "wof:placetype":"venue"
},
  "geometry": {"coordinates":[8.855785,47.190304],"type":"Point"}
}