{
  "type": "Feature",
  "properties": {
    "iso:country":"CH",
    "sg:address":"Delsbergstrasse 13",
    "sg:city":"Grellingen",
    "sg:orig_category":"G\u00fcterbef\u00f6rderung im Strassenverkehr",
    "sg:phone":"+41 61 741 21 43",
    "sg:postcode":"4203",
    "sg:province":"Basel-Landschaft",
    "wof:name":"Andr\u00e9 Kaiser-lay, Transporte",
    "wof:placetype":"venue"
},
  "geometry": {"coordinates":[7.5870909691,47.4413223267],"type":"Point"}
}