{
  "type": "Feature",
  "properties": {
    "iso:country":"CH",
    "sg:address":"Churer Strasse 6",
    "sg:city":"Nendeln",
    "sg:classifiers":[
        {
            "category":"Bars & Pubs",
            "type":"Food & Drink"
        }
    ],
    "sg:phone":"+41 71 744 18 98",
    "sg:postcode":"9485",
    "sg:tags":[
        "restaurant"
    ],
    "wof:name":"Restaurant & Bar L\u00f6wen",
    "wof:placetype":"venue"
},
  "geometry": {"coordinates":[9.635192,47.431007],"type":"Point"}
}