{
  "type": "Feature",
  "properties": {
    "iso:country":"CH",
    "sg:address":"Trottenstrasse 38",
    "sg:city":"Weiach",
    "sg:orig_category":"Eisenbahnverkehr",
    "sg:postcode":"8187",
    "sg:province":"Z\u00fcrich",
    "wof:name":"Tvg Ag Transportmittel - Vermietungs - Gesellschaft",
    "wof:placetype":"venue"
},
  "geometry": {"coordinates":[8.4395523071,47.5571594238],"type":"Point"}
}