{
  "type": "Feature",
  "properties": {
    "iso:country":"CH",
    "sg:address":"Ruelle De L'ecluse 8",
    "sg:city":"Del\u00e9mont",
    "sg:orig_category":"Erwachsenenbildung U Unterricht K\u00fcnstlerische Schulen",
    "sg:phone":"+41 32 422 78 28",
    "sg:postcode":"2800",
    "sg:province":"Jura",
    "wof:name":"Institut D'\u00e9ducation Musicale Edgar Willems, M. Ragni Et F. Ragni Cr\u00e9tin",
    "wof:placetype":"venue"
},
  "geometry": {"coordinates":[7.3504118919,47.3633575439],"type":"Point"}
}