{
  "type": "Feature",
  "properties": {
    "iso:country":"CH",
    "sg:address":"Niedergr\u00e4chen",
    "sg:city":"Gr\u00e4chen",
    "sg:orig_category":"Detailhandel mit Waren verschiedener Art, Hauptrichtung Nahrungsmittel",
    "sg:phone":"+41 27 956 18 38",
    "sg:postcode":"3925",
    "sg:province":"Valais",
    "wof:name":"Theodul Walter Lebensmittelgesch\u00e4ft",
    "wof:placetype":"venue"
},
  "geometry": {"coordinates":[7.8294630051,46.1909637451],"type":"Point"}
}