{
  "type": "Feature",
  "properties": {
    "iso:country":"CH",
    "sg:address":"Hauptstrasse 20",
    "sg:city":"Kradolf",
    "sg:orig_category":"Instandhaltung U Reparatur von Automobilen",
    "sg:phone":"+41 71 642 17 13",
    "sg:postcode":"9214",
    "sg:province":"Thurgau",
    "wof:name":"Spurtgarage Pfenninger Ag",
    "wof:placetype":"venue"
},
  "geometry": {"coordinates":[9.1985359192,47.5258483887],"type":"Point"}
}