{
  "type": "Feature",
  "properties": {
    "iso:country":"CH",
    "sg:address":"B\u00fcelholz 10",
    "sg:city":"Winterthur",
    "sg:orig_category":"Mit dem Versicherungsgewerbe verbundene T\u00e4tigkeiten",
    "sg:postcode":"8400",
    "sg:province":"Z\u00fcrich",
    "wof:name":"Richner Interdisziplin\u00e4re Beratungen Im Gesundheitswesen",
    "wof:placetype":"venue"
},
  "geometry": {"coordinates":[8.7270116806,47.4920425415],"type":"Point"}
}