{
  "type": "Feature",
  "properties": {
    "iso:country":"CH",
    "sg:address":"Adam-friedrich-molz-gasse 10 2502 Biel/bienne Case Postale 3131",
    "sg:city":"Biel/bienne",
    "sg:orig_category":"Reiseb\u00fcros",
    "sg:phone":"+41 32 322 11 66",
    "sg:postcode":"2501",
    "sg:province":"Bern",
    "wof:name":"Imholz Reisen",
    "wof:placetype":"venue"
},
  "geometry": {"coordinates":[7.2451710701,47.1393890381],"type":"Point"}
}