{
  "type": "Feature",
  "properties": {
    "iso:country":"CH",
    "sg:address":"Place De Cornavin 7",
    "sg:city":"Gen\u00e8ve",
    "sg:orig_category":"Pers\u00f6nliche Dienstleistungen",
    "sg:phone":"+41 22 731 39 39",
    "sg:postcode":"1201",
    "sg:province":"Gen\u00e8ve",
    "wof:name":"Mc Clean Ag Hygienecenter",
    "wof:placetype":"venue"
},
  "geometry": {"coordinates":[6.1427979469,46.2102088928],"type":"Point"}
}