{
  "type": "Feature",
  "properties": {
    "iso:country":"CH",
    "sg:address":"Weissenb\u00fchlweg 8 3007 Bern. Postfach",
    "sg:city":"Bern",
    "sg:orig_category":"Sonstige mit der Informatik verbundene T\u00e4tigkeiten",
    "sg:postcode":"3005",
    "sg:province":"Bern",
    "wof:name":"Powersoft Burri Armin Edv-dienstleistungen",
    "wof:placetype":"venue"
},
  "geometry": {"coordinates":[7.4330391884,46.9379196167],"type":"Point"}
}