{
  "type": "Feature",
  "properties": {
    "iso:country":"CH",
    "sg:address":"Maria Via St. 68",
    "sg:city":"Gordola",
    "sg:orig_category":"Architektur U Ingenieurb\u00fcros",
    "sg:phone":"+41 79 423 73 37",
    "sg:postcode":"6596",
    "sg:province":"Ticino",
    "wof:name":"D.g.r. Sagl",
    "wof:placetype":"venue"
},
  "geometry": {"coordinates":[8.865398,46.170498],"type":"Point"}
}