{
  "type": "Feature",
  "properties": {
    "addr:full":"Freienhofgasse 20 3600 Thun. Postfach Thun Bern 3600",
    "addr:housenumber":"20",
    "addr:postcode":"3600 thun. postfach;3600",
    "addr:street":"Freienhofgasse",
    "iso:country":"CH",
    "sg:address":"Freienhofgasse 20 3600 Thun. Postfach",
    "sg:city":"Thun",
    "sg:orig_category":"Betrieb U technische Hilfsdienste des Kultur U Unterhaltungswesens",
    "sg:phone":"+41 33 823 48 48",
    "sg:postcode":"3600",
    "sg:province":"Bern",
    "wof:name":"Spot On Gmbh",
    "wof:placetype":"venue"
},
  "geometry": {"coordinates":[7.863109,46.681244],"type":"Point"}
}