{
  "type": "Feature",
  "properties": {
    "addr:full":"Keller\u00e4ckerstrasse 48 Widen Aargau 8967",
    "addr:housenumber":"48",
    "addr:postcode":"8967",
    "addr:street":"Kelleraeckerstrasse",
    "iso:country":"CH",
    "sg:address":"Keller\u00e4ckerstrasse 48",
    "sg:city":"Widen",
    "sg:orig_category":"Arztpraxen",
    "sg:phone":"+41 81 756 36 16",
    "sg:postcode":"8967",
    "sg:province":"Aargau",
    "wof:name":"Dr.med.guido Truniger Arzt F.allgemeine Medizin Fmh",
    "wof:placetype":"venue"
},
  "geometry": {"coordinates":[9.476932,47.166973],"type":"Point"}
}