{
  "type": "Feature",
  "properties": {
    "iso:country":"CH",
    "sg:address":"Passwangstrasse 84",
    "sg:city":"M\u00fcmliswil",
    "sg:orig_category":"RESTAURANTS: TEA-ROOMS",
    "sg:phone":"+41 21 921 94 64",
    "sg:postcode":"4717",
    "sg:province":"Solothurn",
    "wof:name":"Meylan Doris",
    "wof:placetype":"venue"
},
  "geometry": {"coordinates":[5.1808700562,45.8973388672],"type":"Point"}
}