{
  "type": "Feature",
  "properties": {
    "iso:country":"CH",
    "sg:address":"Ohne Domizil 2108 Couvet Case Postale 129",
    "sg:city":"Couvet",
    "sg:orig_category":"Fachdetailhandel in Verkaufsr\u00e4umen",
    "sg:phone":"+41 32 869 12 12",
    "sg:postcode":"2108",
    "sg:province":"Neuch\u00e2tel",
    "wof:name":"Vigio Cr\u00e9ation S\u00e0rl",
    "wof:placetype":"venue"
},
  "geometry": {"coordinates":[6.6301870346,46.9247665405],"type":"Point"}
}