{
  "type": "Feature",
  "properties": {
    "iso:country":"CH",
    "sg:address":"Rue De La Dent-blanche 8",
    "sg:city":"Sion",
    "sg:orig_category":"Physiotherapie",
    "sg:phone":"+41 27 323 83 02",
    "sg:postcode":"1950",
    "sg:province":"Valais",
    "wof:name":"Pablo Ferrada Physioth\u00e9rapie",
    "wof:placetype":"venue"
},
  "geometry": {"coordinates":[7.3589529991,46.2314872742],"type":"Point"}
}