{
  "type": "Feature",
  "properties": {
    "iso:country":"CH",
    "sg:address":"Rue Du 31-d\u00e9cembre 47",
    "sg:city":"Gen\u00e8ve",
    "sg:orig_category":"Grosshandel mit chemischen Erzeugnissen Herstellung von Akkumulatoren U Batterien",
    "sg:phone":"+41 22 929 94 11",
    "sg:postcode":"1207",
    "sg:province":"Gen\u00e8ve",
    "wof:name":"Energizer Sa",
    "wof:placetype":"venue"
},
  "geometry": {"coordinates":[6.1225810051,46.2355957031],"type":"Point"}
}