{
  "type": "Feature",
  "properties": {
    "addr:full":"Haus Satellit Susten Valais 3952",
    "addr:postcode":"3952",
    "iso:country":"CH",
    "sg:address":"Haus Satellit",
    "sg:city":"Susten",
    "sg:orig_category":"Allgemeiner Hochbau Strassenbau",
    "sg:phone":"+41 27 473 15 30",
    "sg:postcode":"3952",
    "sg:province":"Valais",
    "wof:name":"Josef Meyer Baugesch\u00e4ft",
    "wof:placetype":"venue"
},
  "geometry": {"coordinates":[7.642022,46.311512],"type":"Point"}
}