{
  "type": "Feature",
  "properties": {
    "iso:country":"CH",
    "sg:address":"8765",
    "sg:city":"Engi",
    "sg:orig_category":"Pensionskassen",
    "sg:phone":"+41 55 642 25 42",
    "sg:postcode":"8765",
    "sg:province":"Glarus",
    "wof:name":"Patronale Stiftung Der Weseta Kraftwerke Ag",
    "wof:placetype":"venue"
},
  "geometry": {"coordinates":[9.1517906189,46.9848136902],"type":"Point"}
}