{
  "type": "Feature",
  "properties": {
    "iso:country":"CH",
    "sg:address":"Im Hubel 14",
    "sg:city":"Sursee",
    "sg:orig_category":"Erschliessung von Grundst\u00fccken",
    "sg:postcode":"6210",
    "sg:province":"Luzern",
    "wof:name":"Wohnbaugenossenschaft F\u00fcr Die Familie Wil",
    "wof:placetype":"venue"
},
  "geometry": {"coordinates":[9.0406303406,47.4697875977],"type":"Point"}
}