{
  "type": "Feature",
  "properties": {
    "iso:country":"CH",
    "sg:address":"H\u00f6ckleri 8",
    "sg:city":"Widen",
    "sg:orig_category":"Unternehmensberatung",
    "sg:phone":"+41 56 633 91 10",
    "sg:postcode":"8967",
    "sg:province":"Aargau",
    "wof:name":"Pm Consult, Project Management Consulting & Training, Buhl Reinhold",
    "wof:placetype":"venue"
},
  "geometry": {"coordinates":[8.3573112488,47.3719406128],"type":"Point"}
}