{
  "type": "Feature",
  "properties": {
    "iso:country":"CH",
    "sg:address":"Avenue De La Gare 6",
    "sg:city":"Fleurier",
    "sg:orig_category":"Handel mit Automobilteilen U Zubeh\u00f6r",
    "sg:phone":"+41 32 861 32 60",
    "sg:postcode":"2114",
    "sg:province":"Neuch\u00e2tel",
    "wof:name":"Couleurs Brobst Guy",
    "wof:placetype":"venue"
},
  "geometry": {"coordinates":[6.5818591118,46.9028892517],"type":"Point"}
}