{
  "type": "Feature",
  "properties": {
    "iso:country":"CH",
    "sg:address":"Langendorfstrasse 46",
    "sg:city":"Solothurn",
    "sg:orig_category":"Unclassifiable Establishments",
    "sg:phone":"+41 32 621 77 77",
    "sg:postcode":"4500",
    "sg:province":"Solothurn",
    "wof:name":"Radio-tv Tr\u00f6sch Solothurn Ag",
    "wof:placetype":"venue"
},
  "geometry": {"coordinates":[7.5155739784,47.2166061401],"type":"Point"}
}