{
  "type": "Feature",
  "properties": {
    "iso:country":"CH",
    "sg:address":"F\u00f6hrenweg 19",
    "sg:city":"Ormalingen",
    "sg:orig_category":"Dachdeckerei Zimmerei, Ingenieurholzbau",
    "sg:phone":"+41 61 991 05 26",
    "sg:postcode":"4466",
    "sg:province":"Basel-Landschaft",
    "wof:name":"Franz R. Hugentobler Holzbau & Bedachungen",
    "wof:placetype":"venue"
},
  "geometry": {"coordinates":[7.866567,47.470993],"type":"Point"}
}