{
  "type": "Feature",
  "properties": {
    "iso:country":"CH",
    "sg:address":"Kanalstrasse 20",
    "sg:city":"Vaduz",
    "sg:orig_category":"Sonstige Kultur U Unterhaltungseinrichtungen",
    "sg:phone":"+423 230 02 10",
    "sg:postcode":"9490",
    "wof:name":"Jugendtreffpunkt Cam\u00e4leon",
    "wof:placetype":"venue"
},
  "geometry": {"coordinates":[9.5211725235,47.1248931885],"type":"Point"}
}