{
  "type": "Feature",
  "properties": {
    "iso:country":"CH",
    "sg:address":"Seebergstr. 1 8103 Unterengstringen. Postfach",
    "sg:city":"Schlieren",
    "sg:orig_category":"Erbringung von Dienstleistungen f\u00fcr Unternehmen",
    "sg:phone":"+41 17304477",
    "sg:postcode":"8952",
    "sg:province":"Z\u00fcrich",
    "wof:name":"Egli & Giger, Gestaltung Beschriftung Siebdruck",
    "wof:placetype":"venue"
},
  "geometry": {"coordinates":[8.4279737473,47.4026794434],"type":"Point"}
}