{
  "type": "Feature",
  "properties": {
    "iso:country":"CH",
    "sg:address":"Rigistrasse 11 6210 Sursee. Postfach",
    "sg:city":"Sursee",
    "sg:orig_category":"Herstellung von Fenstern U T\u00fcren aus Holz Herstellung von Konstruktionsteilen, Fertigbauteilen U Aus",
    "sg:phone":"+41 41 925 11 50",
    "sg:postcode":"6210",
    "sg:province":"Luzern",
    "wof:name":"Bs Fenster Und T\u00fcrenbau Ag",
    "wof:placetype":"venue"
},
  "geometry": {"coordinates":[8.101354599,47.1685028076],"type":"Point"}
}