{
  "type": "Feature",
  "properties": {
    "iso:country":"CH",
    "sg:address":"Ensingerstrasse 16a",
    "sg:city":"Bern",
    "sg:orig_category":"Sportvereine Sch\u00fctzen Pistolen-& Gewehr",
    "sg:phone":"+41 31 829 19 63",
    "sg:postcode":"3006",
    "sg:province":"Bern",
    "wof:name":"Sch\u00fctzen 3 Bern",
    "wof:placetype":"venue"
},
  "geometry": {"coordinates":[7.4626641273,46.9426460266],"type":"Point"}
}