{
  "type": "Feature",
  "properties": {
    "iso:country":"CH",
    "sg:address":"Vogelsangstrasse 24",
    "sg:city":"Effretikon",
    "sg:orig_category":"Herstellung von Pumpen U Kompressoren Mechanische Werkst\u00e4tten",
    "sg:phone":"+41 61 961 05 77",
    "sg:postcode":"8307",
    "sg:province":"Z\u00fcrich",
    "wof:name":"Paul Krattiger Ag",
    "wof:placetype":"venue"
},
  "geometry": {"coordinates":[7.7574510574,47.3902664185],"type":"Point"}
}