{
  "type": "Feature",
  "properties": {
    "iso:country":"CH",
    "sg:address":"Strehlgasse 29",
    "sg:city":"Z\u00fcrich",
    "sg:orig_category":"Detailhandel mit Bekleidung",
    "sg:phone":"+41 12213104",
    "sg:postcode":"8001",
    "sg:province":"Z\u00fcrich",
    "wof:name":"Lwl Leinen Langenthal Ag",
    "wof:placetype":"venue"
},
  "geometry": {"coordinates":[8.540575,47.372154],"type":"Point"}
}