{
  "type": "Feature",
  "properties": {
    "iso:country":"CH",
    "sg:address":"Ruvria 336",
    "sg:city":"Thusis",
    "sg:orig_category":"Verwaltung der Rechtspflege, Gerichte",
    "sg:phone":"+41 81 651 18 43",
    "sg:postcode":"7430",
    "sg:province":"Graubunden",
    "wof:name":"Bezirksgericht Heinzerberg",
    "wof:placetype":"venue"
},
  "geometry": {"coordinates":[9.4359903336,46.7007293701],"type":"Point"}
}