{
  "type": "Feature",
  "properties": {
    "iso:country":"CH",
    "sg:address":"Weiermattweg 3",
    "sg:city":"D\u00fcdingen",
    "sg:orig_category":"Werbung",
    "sg:phone":"+41 26 493 26 35",
    "sg:postcode":"3186",
    "sg:province":"Fribourg",
    "wof:name":"Mws-werbung Und Kommunikation Perroulaz Marco",
    "wof:placetype":"venue"
},
  "geometry": {"coordinates":[7.1915621758,46.842086792],"type":"Point"}
}