{
  "type": "Feature",
  "properties": {
    "iso:country":"CH",
    "sg:address":"Rue Des Eaux-vives 6",
    "sg:city":"Gen\u00e8ve",
    "sg:orig_category":"Psychotherapie",
    "sg:phone":"+41 22 700 09 59",
    "sg:postcode":"1207",
    "sg:province":"Gen\u00e8ve",
    "wof:name":"Sabine Azarmsa Psychoth\u00e9rapie",
    "wof:placetype":"venue"
},
  "geometry": {"coordinates":[6.1572670937,46.2029342651],"type":"Point"}
}