{
  "type": "Feature",
  "properties": {
    "iso:country":"CH",
    "sg:address":"Gersauerstrasse 86 6440 Ingenbohl. Postfach",
    "sg:city":"Brunnen",
    "sg:orig_category":"Detailhandel mit Waren verschiedener Art, Hauptrichtung Nahrungsmittel",
    "sg:postcode":"6440",
    "sg:province":"Schwyz",
    "wof:name":"Promarkt Ag",
    "wof:placetype":"venue"
},
  "geometry": {"coordinates":[8.5954198837,46.9993286133],"type":"Point"}
}