{
  "type": "Feature",
  "properties": {
    "iso:country":"CH",
    "sg:address":"6710",
    "sg:city":"Biasca",
    "sg:orig_category":"Maler U Glasergewerbe Malerei",
    "sg:phone":"+41 71 311 55 10",
    "sg:postcode":"6710",
    "sg:province":"Ticino",
    "wof:name":"Parente Paolo",
    "wof:placetype":"venue"
},
  "geometry": {"coordinates":[9.3181266785,47.4053573608],"type":"Point"}
}