{
  "type": "Feature",
  "properties": {
    "iso:country":"CH",
    "sg:address":"Chlosterb\u00fcel 28",
    "sg:city":"Sch\u00fcpfheim",
    "sg:orig_category":"Landwirtschaftliche Schulen",
    "sg:phone":"+41 41 484 25 25",
    "sg:postcode":"6170",
    "sg:province":"Luzern",
    "wof:name":"Landwirtschafts-& B\u00e4uerinnenschule",
    "wof:placetype":"venue"
},
  "geometry": {"coordinates":[8.0256528854,46.9592628479],"type":"Point"}
}