{
  "type": "Feature",
  "properties": {
    "iso:country":"CH",
    "sg:address":"Brunngasse 9",
    "sg:city":"Z\u00fcrich",
    "sg:orig_category":"Herstellung von sonstigen Produkten aus nichtmetallischen Mineralien",
    "sg:phone":"+41 55 240 14 09",
    "sg:postcode":"8001",
    "sg:province":"Z\u00fcrich",
    "wof:name":"Rowa Ag",
    "wof:placetype":"venue"
},
  "geometry": {"coordinates":[8.8474340439,47.2592124939],"type":"Point"}
}