{
  "type": "Feature",
  "properties": {
    "addr:full":"Weinfelder Strasse 16 Amriswil Thurgau 8580",
    "addr:housenumber":"16",
    "addr:postcode":"8580",
    "addr:street":"Weinfelder Strasse",
    "iso:country":"CH",
    "sg:address":"Weinfelder Strasse 16",
    "sg:city":"Amriswil",
    "sg:orig_category":"Ansichtskartenverlage Druckgewerbe",
    "sg:phone":"+41 71 411 90 10",
    "sg:postcode":"8580",
    "sg:province":"Thurgau",
    "wof:name":"Markus D\u00e4pp Art Take Away Markus D\u00e4pp",
    "wof:placetype":"venue"
},
  "geometry": {"coordinates":[9.296048,47.545475],"type":"Point"}
}