{
  "type": "Feature",
  "properties": {
    "iso:country":"CH",
    "sg:address":"Feldstrasse 2b",
    "sg:city":"Langenthal",
    "sg:orig_category":"Herstellung von Teppichen",
    "sg:phone":"+41 71 633 15 10",
    "sg:postcode":"4900",
    "sg:province":"Bern",
    "wof:name":"Isa Fazli Plattenleger",
    "wof:placetype":"venue"
},
  "geometry": {"coordinates":[9.1524839401,47.5499153137],"type":"Point"}
}