{
  "type": "Feature",
  "properties": {
    "addr:full":"Chemin Du Verger 6 Ros\u00e9 Fribourg 1754",
    "addr:housenumber":"6",
    "addr:postcode":"1754",
    "addr:street":"Chemin Du Verger",
    "iso:country":"CH",
    "sg:address":"Chemin Du Verger 6",
    "sg:city":"Ros\u00e9",
    "sg:orig_category":"Architektur U Ingenieurb\u00fcros",
    "sg:postcode":"1754",
    "sg:province":"Fribourg",
    "wof:name":"Lutz & Partenaires Sa",
    "wof:placetype":"venue"
},
  "geometry": {"coordinates":[7.072196,46.788326],"type":"Point"}
}