{
  "type": "Feature",
  "properties": {
    "iso:country":"CH",
    "sg:address":"Alfons Aeby-strasse 24",
    "sg:city":"D\u00fcdingen",
    "sg:orig_category":"Primarschulen",
    "sg:phone":"+41 79 227 47 61",
    "sg:postcode":"3186",
    "sg:province":"Fribourg",
    "wof:name":"Primarschule Wolfacker",
    "wof:placetype":"venue"
},
  "geometry": {"coordinates":[7.1939339638,46.8474578857],"type":"Point"}
}