{
  "type": "Feature",
  "properties": {
    "iso:country":"CH",
    "sg:address":"Laurenzentorgasse 2 5000 Aarau. Postfach",
    "sg:city":"Aarau",
    "sg:orig_category":"Wirtschaftspr\u00fcfung, Steuerberatung U Treuhand",
    "sg:phone":"+41 62 822 97 22",
    "sg:postcode":"5001",
    "sg:province":"Aargau",
    "wof:name":"Erni & Co Treuhandgesellschaft Aarau",
    "wof:placetype":"venue"
},
  "geometry": {"coordinates":[8.044500351,47.3930358887],"type":"Point"}
}