{
  "type": "Feature",
  "properties": {
    "iso:country":"CH",
    "sg:address":"Urn\u00e4scher Strasse",
    "sg:city":"Hundwil",
    "sg:orig_category":"Primarschulen",
    "sg:phone":"+41 71 367 17 66",
    "sg:postcode":"9064",
    "sg:province":"Appenzell Ausserrhoden",
    "wof:name":"Primarschule Mitledi",
    "wof:placetype":"venue"
},
  "geometry": {"coordinates":[9.3157901764,47.3615264893],"type":"Point"}
}