{
  "type": "Feature",
  "properties": {
    "iso:country":"CH",
    "sg:address":"Eaux-vives Place Des 6 1207 Gen\u00e8ve. Postfach",
    "sg:city":"Gen\u00e8ve",
    "sg:orig_category":"Non-Classified Establishments",
    "sg:postcode":"1207",
    "sg:province":"Gen\u00e8ve",
    "wof:name":"Si La C\u00f4ti\u00e8re Bleue",
    "wof:placetype":"venue"
},
  "geometry": {"coordinates":[6.1663861275,46.2004928589],"type":"Point"}
}