{
  "type": "Feature",
  "properties": {
    "iso:country":"CH",
    "sg:address":"Hegibergstrasse 96",
    "sg:city":"Trimbach",
    "sg:orig_category":"Architektur U Ingenieurb\u00fcros",
    "sg:phone":"+41 62 293 13 30",
    "sg:postcode":"4632",
    "sg:province":"Solothurn",
    "wof:name":"Gerhard Hagmann Ingenieurb\u00fcro",
    "wof:placetype":"venue"
},
  "geometry": {"coordinates":[7.901604,47.368118],"type":"Point"}
}