{
  "type": "Feature",
  "properties": {
    "iso:country":"CH",
    "sg:address":"Stadthausgasse 27",
    "sg:city":"Schaffhausen",
    "sg:orig_category":"Unclassifiable Establishments",
    "sg:postcode":"8200",
    "sg:province":"Schaffhausen",
    "wof:name":"Mosburger Beteiligungs Gmbh, Wien, Zweigniederlassung Schaffhausen",
    "wof:placetype":"venue"
},
  "geometry": {"coordinates":[8.6337537766,47.6967735291],"type":"Point"}
}