{
  "type": "Feature",
  "properties": {
    "iso:country":"CH",
    "sg:address":"Flughofstrasse 71",
    "sg:city":"R\u00fcmlang",
    "sg:orig_category":"G\u00fcterbef\u00f6rderung im Strassenverkehr",
    "sg:phone":"+41 91 646 34 59",
    "sg:postcode":"8153",
    "sg:province":"Z\u00fcrich",
    "wof:name":"Bruno Mantegazzi Trasporti",
    "wof:placetype":"venue"
},
  "geometry": {"coordinates":[8.9725999832,45.8892059326],"type":"Point"}
}