{
  "type": "Feature",
  "properties": {
    "iso:country":"CH",
    "sg:address":"Zi",
    "sg:city":"Villaz-st-pierre",
    "sg:classifiers":[
        {
            "category":"Professional",
            "subcategory":"Engineering",
            "type":"Services"
        }
    ],
    "sg:phone":"+41 26 653 92 00",
    "sg:postcode":"1690",
    "sg:province":"Fribourg",
    "sg:tags":[
        "machine",
        "-",
        "mechanical"
    ],
    "wof:name":"Iscar-metaldur Sa",
    "wof:placetype":"venue"
},
  "geometry": {"coordinates":[6.9565711021,46.7209243774],"type":"Point"}
}