{
  "type": "Feature",
  "properties": {
    "iso:country":"CH",
    "sg:address":"Z\u00fcrcherstrasse 212",
    "sg:city":"Frauenfeld",
    "sg:orig_category":"Detailhandel mit elektrischen Haushalts-,Radio U Fernsehger\u00e4ten sowie Musikinstrumenten",
    "sg:postcode":"8500",
    "sg:province":"Thurgau",
    "wof:name":"Cd-handel Und Vertrieb Baumann",
    "wof:placetype":"venue"
},
  "geometry": {"coordinates":[8.9001054764,47.5581092834],"type":"Point"}
}