{
  "type": "Feature",
  "properties": {
    "iso:country":"CH",
    "sg:address":"Haslenstrasse 1",
    "sg:city":"Teufen",
    "sg:classifiers":[
        {
            "category":"Professional",
            "subcategory":"Computer Services",
            "type":"Services"
        }
    ],
    "sg:phone":"+41 71 335 77 57",
    "sg:postcode":"9053",
    "sg:province":"Appenzell Ausserrhoden",
    "sg:tags":[
        "administration",
        "software"
    ],
    "wof:name":"Ercomp Gmbh",
    "wof:placetype":"venue"
},
  "geometry": {"coordinates":[9.388795,47.385742],"type":"Point"}
}