{
  "type": "Feature",
  "properties": {
    "iso:country":"CH",
    "sg:address":"Fabrikstrasse 3 5444 K\u00fcnten. Postfach",
    "sg:city":"K\u00fcnten",
    "sg:orig_category":"Sonstiges Druckgewerbe",
    "sg:postcode":"5444",
    "sg:province":"Aargau",
    "wof:name":"Copy Shop - Ds-service, Hiltbrand",
    "wof:placetype":"venue"
},
  "geometry": {"coordinates":[8.3318424225,47.3893547058],"type":"Point"}
}