{
  "type": "Feature",
  "properties": {
    "iso:country":"CH",
    "sg:address":"G\u00f6nhardweg 6",
    "sg:city":"Aarau",
    "sg:orig_category":"Arztpraxen",
    "sg:phone":"+41 56 664 16 34",
    "sg:postcode":"5000",
    "sg:province":"Aargau",
    "wof:name":"Dr.med.verena Gantner Aerztin F\u00fcr Allg.medizin Fmh",
    "wof:placetype":"venue"
},
  "geometry": {"coordinates":[8.317482,47.282578],"type":"Point"}
}