{
  "type": "Feature",
  "properties": {
    "iso:country":"CH",
    "sg:city":"Saas",
    "sg:classifiers":[
        {
            "category":"Banks & Credit Unions",
            "subcategory":"Bank",
            "type":"Services"
        }
    ],
    "sg:phone":"+41 27 957 16 12",
    "sg:postcode":"3906",
    "sg:province":"Valais",
    "wof:name":"Walliser Kantonalbank",
    "wof:placetype":"venue"
},
  "geometry": {"coordinates":[7.90173,46.085499],"type":"Point"}
}