{
  "type": "Feature",
  "properties": {
    "iso:country":"CH",
    "sg:address":"Eisenbahnstrasse 41",
    "sg:city":"Thun",
    "sg:orig_category":"Werbung",
    "sg:phone":"+41 33 335 37 02",
    "sg:postcode":"3600",
    "sg:province":"Bern",
    "wof:name":"Iws Interwerbes\u00e4ulen, Roger Bylang",
    "wof:placetype":"venue"
},
  "geometry": {"coordinates":[7.6243047714,46.7353668213],"type":"Point"}
}