{
  "type": "Feature",
  "properties": {
    "iso:country":"CH",
    "sg:address":"Ch\u00e9serex Route De",
    "sg:city":"Gingins",
    "sg:orig_category":"Herstellung von k\u00e4lte U lufttechnischen Erzeugnissen f\u00fcr gewerbliche Zwecke Herstellung von sonstige",
    "sg:phone":"+41 41 666 32 32",
    "sg:postcode":"1276",
    "sg:province":"Vaud",
    "wof:name":"Sarna-granol Ag",
    "wof:placetype":"venue"
},
  "geometry": {"coordinates":[8.246049881,46.9038887024],"type":"Point"}
}