{
  "type": "Feature",
  "properties": {
    "iso:country":"CH",
    "sg:address":"Hardturmstrasse 261 8000 Z\u00fcrich. Postfach",
    "sg:city":"Z\u00fcrich",
    "sg:orig_category":"RESTAURANTS: TEA-ROOMS",
    "sg:phone":"+41 22 343 32 24",
    "sg:postcode":"8001",
    "sg:province":"Z\u00fcrich",
    "wof:name":"Brasserie Des Tours S\u00e0rl",
    "wof:placetype":"venue"
},
  "geometry": {"coordinates":[6.1366539001,46.183757782],"type":"Point"}
}