{
  "type": "Feature",
  "properties": {
    "iso:country":"CH",
    "sg:address":"Arbenzstrasse 8 8008 Z\u00fcrich. Postfach",
    "sg:city":"Z\u00fcrich",
    "sg:orig_category":"Detailhandel mit Bekleidung",
    "sg:phone":"+41 14228554",
    "sg:postcode":"8001",
    "sg:province":"Z\u00fcrich",
    "wof:name":"Beltext Import, Bellucci Daniele Textilien Bes. Brautkleider; Import, Verkauf An Detailisten",
    "wof:placetype":"venue"
},
  "geometry": {"coordinates":[8.556003,47.358742],"type":"Point"}
}