{
  "type": "Feature",
  "properties": {
    "iso:country":"CH",
    "sg:address":"Casa Reviva 7159 Andiast. Postfach",
    "sg:city":"Andiast",
    "sg:orig_category":"Erwachsenenbildung U Unterricht",
    "sg:postcode":"7159",
    "sg:province":"Graubunden",
    "wof:name":"Rosina Vincenz",
    "wof:placetype":"venue"
},
  "geometry": {"coordinates":[9.1143198013,46.7845954895],"type":"Point"}
}