{
  "type": "Feature",
  "properties": {
    "iso:country":"CH",
    "sg:address":"Pestalozzistrasse 2 3400 Burgdorf. Postfach",
    "sg:city":"Burgdorf",
    "sg:orig_category":"Herstellung von Anstrichmitteln, Druckfarben U Kitten",
    "sg:phone":"+41 71 929 52 82",
    "sg:postcode":"3402",
    "sg:province":"Bern",
    "wof:name":"Votteler Ag",
    "wof:placetype":"venue"
},
  "geometry": {"coordinates":[9.085729599,47.4239006042],"type":"Point"}
}