{
  "type": "Feature",
  "properties": {
    "iso:country":"CH",
    "sg:address":"Rankstrasse 30",
    "sg:city":"Neftenbach",
    "sg:orig_category":"Unclassifiable Establishments",
    "sg:postcode":"8413",
    "sg:province":"Z\u00fcrich",
    "wof:name":"Alterswohnheim Bethlehem Gmbh",
    "wof:placetype":"venue"
},
  "geometry": {"coordinates":[7.2296447754,46.8515205383],"type":"Point"}
}