{
  "type": "Feature",
  "properties": {
    "iso:country":"CH",
    "sg:address":"D\u00fcrrenweid",
    "sg:city":"Schwarzenegg",
    "sg:orig_category":"Bauschreinerei",
    "sg:phone":"+41 33 453 19 94",
    "sg:postcode":"3616",
    "sg:province":"Bern",
    "wof:name":"Walter Wyttenbach Schreinerei",
    "wof:placetype":"venue"
},
  "geometry": {"coordinates":[7.72441,46.793495],"type":"Point"}
}