{
  "type": "Feature",
  "properties": {
    "iso:country":"CH",
    "sg:address":"Neuhofstrasse 7",
    "sg:city":"Baar",
    "sg:orig_category":"Unternehmensberatung",
    "sg:phone":"+41 61 301 58 80",
    "sg:postcode":"6340",
    "sg:province":"Zug",
    "wof:name":"Wtb Worldtradebusinesscenter Gmbh",
    "wof:placetype":"venue"
},
  "geometry": {"coordinates":[8.515329361,47.1909408569],"type":"Point"}
}