{
  "type": "Feature",
  "properties": {
    "iso:country":"CH",
    "sg:address":"Birchli 1",
    "sg:city":"Einsiedeln",
    "sg:orig_category":"Grosshandel mit lebenden Tieren",
    "sg:phone":"+41 41 917 14 34",
    "sg:postcode":"8840",
    "sg:province":"Schwyz",
    "wof:name":"Anton Brunner Viehhandel",
    "wof:placetype":"venue"
},
  "geometry": {"coordinates":[8.2363138199,47.2583999634],"type":"Point"}
}