{
  "type": "Feature",
  "properties": {
    "iso:country":"CH",
    "sg:address":"8572",
    "sg:city":"Graltshausen",
    "sg:classifiers":[
        {
            "category":"Restaurant",
            "type":"Food & Drink"
        }
    ],
    "sg:phone":"+41 71 636 11 80",
    "sg:postcode":"8572",
    "sg:province":"Thurgau",
    "wof:name":"Restaurant Frohsinn",
    "wof:placetype":"venue"
},
  "geometry": {"coordinates":[9.1819200516,47.5958404541],"type":"Point"}
}