{
  "type": "Feature",
  "properties": {
    "iso:country":"CH",
    "sg:address":"Badenerstrasse 1 8952 Schlieren. Postfach",
    "sg:city":"Schlieren",
    "sg:orig_category":"Detailhandel mit Bekleidung",
    "sg:postcode":"8952",
    "sg:province":"Z\u00fcrich",
    "wof:name":"Boutique Carmen, Ruth Stahel-gretler",
    "wof:placetype":"venue"
},
  "geometry": {"coordinates":[8.447769,47.397247],"type":"Point"}
}