{
  "type": "Feature",
  "properties": {
    "iso:country":"CH",
    "sg:address":"Sonnrain 3",
    "sg:city":"Z\u00e4ziwil",
    "sg:orig_category":"Herstellung von sonstigen chemischen Erzeugnissen",
    "sg:phone":"+41 31 711 05 33",
    "sg:postcode":"3532",
    "sg:province":"Bern",
    "wof:name":"Cem-floor-system Ag",
    "wof:placetype":"venue"
},
  "geometry": {"coordinates":[7.6768250465,46.885925293],"type":"Point"}
}