{
  "type": "Feature",
  "properties": {
    "iso:country":"CH",
    "sg:address":"Route De La Gare 68",
    "sg:city":"Satigny",
    "sg:orig_category":"Unclassifiable Establishments",
    "sg:phone":"+41 22 753 12 11",
    "sg:postcode":"1242",
    "sg:province":"Gen\u00e8ve",
    "wof:name":"Magnin Thierry",
    "wof:placetype":"venue"
},
  "geometry": {"coordinates":[6.0566010475,46.2170753479],"type":"Point"}
}