{
  "type": "Feature",
  "properties": {
    "iso:country":"CH",
    "sg:address":"Rohrstrasse 2",
    "sg:city":"Glattbrugg",
    "sg:orig_category":"Detailhandel mit Spielwaren Versandhandel",
    "sg:phone":"+41 33 733 10 71",
    "sg:postcode":"8152",
    "sg:province":"Z\u00fcrich",
    "wof:name":"Alfred Friedli Friho Modellbahn-versand",
    "wof:placetype":"venue"
},
  "geometry": {"coordinates":[7.4413700104,46.4569587708],"type":"Point"}
}