{
  "type": "Feature",
  "properties": {
    "iso:country":"CH",
    "sg:address":"Pfrundweg 11",
    "sg:city":"Aarau",
    "sg:orig_category":"Stukkateurgewerbe, Gipserei U Verputzerei",
    "sg:phone":"+41 71 244 06 71",
    "sg:postcode":"5000",
    "sg:province":"Aargau",
    "wof:name":"Haag Josef Ag",
    "wof:placetype":"venue"
},
  "geometry": {"coordinates":[9.419418335,47.438747406],"type":"Point"}
}