{
  "type": "Feature",
  "properties": {
    "iso:country":"CH",
    "sg:address":"L\u00f6berenstrasse 17",
    "sg:city":"Zug",
    "sg:orig_category":"Vereine Gemeinn\u00fctzige",
    "sg:phone":"+41 41 711 89 86",
    "sg:postcode":"6300",
    "sg:province":"Zug",
    "wof:name":"M\u00fctter-& V\u00e4terzentren Zg",
    "wof:placetype":"venue"
},
  "geometry": {"coordinates":[8.5198812485,47.1680107117],"type":"Point"}
}