{
  "type": "Feature",
  "properties": {
    "iso:country":"CH",
    "sg:address":"Unterer Einschlag",
    "sg:city":"Bettlach",
    "sg:classifiers":[
        {
            "category":"Community Center",
            "type":"Public Place"
        }
    ],
    "sg:phone":"+41 32 644 33 11",
    "sg:postcode":"2544",
    "sg:province":"Solothurn",
    "sg:tags":[
        "part",
        "stamped"
    ],
    "wof:name":"H\u00e4nggi Ag Stanztechnik",
    "wof:placetype":"venue"
},
  "geometry": {"coordinates":[7.4263401031,47.1950645447],"type":"Point"}
}