{
  "type": "Feature",
  "properties": {
    "iso:country":"CH",
    "sg:address":"Sonnenhofweg 19 3006 Bern. Postfach",
    "sg:city":"Bern",
    "sg:orig_category":"Grosshandel mit Getreide, Saatgut U Futtermitteln",
    "sg:postcode":"3005",
    "sg:province":"Bern",
    "wof:name":"Zryd Jean, Miroga Verkaufsorganisation F. Neuheiten",
    "wof:placetype":"venue"
},
  "geometry": {"coordinates":[7.4716868401,46.9439201355],"type":"Point"}
}