{
  "type": "Feature",
  "properties": {
    "iso:country":"CH",
    "sg:address":"Rue Oscar-huguenin 6",
    "sg:city":"Boudry",
    "sg:orig_category":"Kosmetikinstitute",
    "sg:phone":"+41 32 842 43 00",
    "sg:postcode":"2017",
    "sg:province":"Neuch\u00e2tel",
    "wof:name":"Nicole Porret Institut De Beaut\u00e9 Cybel",
    "wof:placetype":"venue"
},
  "geometry": {"coordinates":[6.8376231194,46.9499092102],"type":"Point"}
}