{
  "type": "Feature",
  "properties": {
    "iso:country":"CH",
    "sg:address":"Gasstrasse 20",
    "sg:city":"Liestal",
    "sg:orig_category":"Detailhandel Reparatur von Gebrauchsg\u00fctern Vermietung von Gebrauchsg\u00fctern",
    "sg:phone":"+41 61 921 68 85",
    "sg:postcode":"4410",
    "sg:province":"Basel-Landschaft",
    "wof:name":"Gennaro D'avolio Videoteca G.r.c",
    "wof:placetype":"venue"
},
  "geometry": {"coordinates":[7.7339468002,47.4868850708],"type":"Point"}
}