{
  "type": "Feature",
  "properties": {
    "iso:country":"CH",
    "sg:address":"Montana-vermala",
    "sg:city":"Montana-vermala",
    "sg:orig_category":"Non-Classified Establishments",
    "sg:postcode":"3962",
    "wof:name":"Si Vacances \u00e0 Montana-vermala No 13 Sa",
    "wof:placetype":"venue"
},
  "geometry": {"coordinates":[7.4924340248,46.3144187927],"type":"Point"}
}