{
  "type": "Feature",
  "properties": {
    "iso:country":"CH",
    "sg:address":"Klosterplatz 7",
    "sg:city":"Solothurn",
    "sg:orig_category":"K\u00fcnstlerische U schriftstellerische T\u00e4tigkeiten U Darbietungen",
    "sg:postcode":"4500",
    "sg:province":"Solothurn",
    "wof:name":"Kaboud Fran\u00e7oise",
    "wof:placetype":"venue"
},
  "geometry": {"coordinates":[5.1808700562,45.8973388672],"type":"Point"}
}