{
  "type": "Feature",
  "properties": {
    "iso:country":"CH",
    "sg:address":"Alte Bruggerstrasse 24",
    "sg:city":"Dottikon",
    "sg:orig_category":"Fahrschulen, Flugschulen",
    "sg:phone":"+41 56 624 13 89",
    "sg:postcode":"5605",
    "sg:province":"Aargau",
    "wof:name":"Ruedi Brunner Autofahrschule",
    "wof:placetype":"venue"
},
  "geometry": {"coordinates":[8.2337970734,47.3764266968],"type":"Point"}
}