{
  "type": "Feature",
  "properties": {
    "iso:country":"CH",
    "sg:address":"Hauptstrasse 53",
    "sg:city":"Oensingen",
    "sg:orig_category":"Handel mit Motorr\u00e4dern, Teilen U Zubeh\u00f6r Instandhaltung U Reparatur von Motorr\u00e4dern",
    "sg:phone":"+41 62 396 35 35",
    "sg:postcode":"4702",
    "sg:province":"Solothurn",
    "wof:name":"Moto-shop Obrist & Rellstab Gmbh",
    "wof:placetype":"venue"
},
  "geometry": {"coordinates":[7.720266819,47.2903862],"type":"Point"}
}