{
  "type": "Feature",
  "properties": {
    "iso:country":"CH",
    "sg:address":"Alpenstrasse 2",
    "sg:city":"Wallisellen",
    "sg:orig_category":"Sprachschulen \u00dcbersetzungsb\u00fcros",
    "sg:phone":"+41 18307363",
    "sg:postcode":"8304",
    "sg:province":"Z\u00fcrich",
    "wof:name":"Ronny Scott",
    "wof:placetype":"venue"
},
  "geometry": {"coordinates":[8.5911922455,47.4170265198],"type":"Point"}
}