{
  "type": "Feature",
  "properties": {
    "iso:country":"CH",
    "sg:address":"Bristenweg 9",
    "sg:city":"Basel",
    "sg:orig_category":"Arztpraxen",
    "sg:phone":"+41 61 301 74 60",
    "sg:postcode":"4054",
    "sg:province":"Basel-Stadt",
    "wof:name":"Dr.med.irene Metz Spezial\u00e4rztin",
    "wof:placetype":"venue"
},
  "geometry": {"coordinates":[7.568031,47.54969],"type":"Point"}
}