{
  "type": "Feature",
  "properties": {
    "iso:country":"CH",
    "sg:address":"Rinkenbach 13 9050 Appenzell. Postfach",
    "sg:city":"Appenzell",
    "sg:orig_category":"Architektur U Ingenieurb\u00fcros",
    "sg:phone":"+41 71 787 25 83",
    "sg:postcode":"9050",
    "sg:province":"Appenzell Innerhoden",
    "wof:name":"Hd-plan Gmbh Holzbauplanung",
    "wof:placetype":"venue"
},
  "geometry": {"coordinates":[9.402674,47.331703],"type":"Point"}
}