{
  "type": "Feature",
  "properties": {
    "iso:country":"CH",
    "sg:address":"Wehntalerstrasse 98",
    "sg:city":"Z\u00fcrich",
    "sg:orig_category":"Herstellung von Spielwaren",
    "sg:phone":"+41 13643066",
    "sg:postcode":"8057",
    "sg:province":"Z\u00fcrich",
    "wof:name":"Peter J\u00e4ggi Modellspielwaren",
    "wof:placetype":"venue"
},
  "geometry": {"coordinates":[8.535490036,47.4025001526],"type":"Point"}
}