{
  "type": "Feature",
  "properties": {
    "iso:country":"CH",
    "sg:address":"Crans-sur-sierre 3963 Crans-sur-sierre. Postfach",
    "sg:city":"Crans-sur-sierre",
    "sg:orig_category":"Non-Classified Establishments",
    "sg:postcode":"3963",
    "sg:province":"Valais",
    "wof:name":"Le Panetier S.a.",
    "wof:placetype":"venue"
},
  "geometry": {"coordinates":[6.83162117,47.1025161743],"type":"Point"}
}