{
  "type": "Feature",
  "properties": {
    "iso:country":"CH",
    "sg:address":"Neufeldweg 4",
    "sg:city":"Hindelbank",
    "sg:orig_category":"Entkalkung, Entrostung, Kalkschutz, Rostschutz",
    "sg:phone":"+41 34 411 22 34",
    "sg:postcode":"3324",
    "sg:province":"Bern",
    "wof:name":"Robert Danz",
    "wof:placetype":"venue"
},
  "geometry": {"coordinates":[7.5444760323,47.0479164124],"type":"Point"}
}