{
  "type": "Feature",
  "properties": {
    "addr:full":"Via San Gottardo 15 Lugano Ticino 6900",
    "addr:housenumber":"15",
    "addr:postcode":"6900",
    "addr:street":"Via San Gottardo",
    "iso:country":"CH",
    "sg:address":"Via San Gottardo 15",
    "sg:city":"Lugano",
    "sg:orig_category":"Bearbeitung von Edel U Schmucksteinen Grosshandel mit Uhren",
    "sg:phone":"+41 91 924 29 03",
    "sg:postcode":"6900",
    "sg:province":"Ticino",
    "wof:name":"Plus Group Sa",
    "wof:placetype":"venue"
},
  "geometry": {"coordinates":[8.947214,46.007229],"type":"Point"}
}