{
  "type": "Feature",
  "properties": {
    "iso:country":"CH",
    "sg:address":"Jostenstrasse 4",
    "sg:city":"Galgenen",
    "sg:orig_category":"Gesundheitswesen",
    "sg:phone":"+41 81 833 31 97",
    "sg:postcode":"8854",
    "sg:province":"Schwyz",
    "wof:name":"Drogerie-parf\u00fcmerie Beyeler Ag",
    "wof:placetype":"venue"
},
  "geometry": {"coordinates":[9.8401603699,46.4987487793],"type":"Point"}
}