{
  "type": "Feature",
  "properties": {
    "iso:country":"CH",
    "sg:address":"Alte Badenerstrasse 30",
    "sg:city":"Neerach",
    "sg:orig_category":"Organisationen des Gesundheitswesen Personal U Stellenvermittlung",
    "sg:phone":"+41 18580783",
    "sg:postcode":"8173",
    "sg:province":"Z\u00fcrich",
    "wof:name":"Kranken-& Hauspflegeverein Steinmaur-neerach",
    "wof:placetype":"venue"
},
  "geometry": {"coordinates":[8.4656419754,47.5100021362],"type":"Point"}
}