{
  "type": "Feature",
  "properties": {
    "iso:country":"CH",
    "sg:address":"4614",
    "sg:city":"H\u00e4gendorf",
    "sg:orig_category":"Sportvereine Ski",
    "sg:phone":"+41 62 216 38 62",
    "sg:postcode":"4614",
    "sg:province":"Solothurn",
    "wof:name":"Skiclub H\u00e4gendorf",
    "wof:placetype":"venue"
},
  "geometry": {"coordinates":[7.8448348045,47.3368263245],"type":"Point"}
}