{
  "type": "Feature",
  "properties": {
    "addr:full":"Europe Avenue De L' 91 Monthey Valais 1870",
    "addr:housenumber":"91",
    "addr:postcode":"1870",
    "addr:street":"Europe Avenue De L '",
    "iso:country":"CH",
    "sg:address":"Europe Avenue De L' 91",
    "sg:city":"Monthey",
    "sg:orig_category":"Architektur U Ingenieurb\u00fcros",
    "sg:phone":"+41 24 471 84 10",
    "sg:postcode":"1870",
    "sg:province":"Valais",
    "wof:name":"Btm, Bureau Technique S\u00e0rl",
    "wof:placetype":"venue"
},
  "geometry": {"coordinates":[6.94714,46.251621],"type":"Point"}
}