{
  "type": "Feature",
  "properties": {
    "iso:country":"CH",
    "sg:address":"Unterdorfstrasse 46",
    "sg:city":"Stettfurt",
    "sg:orig_category":"Allgemeiner Hoch U Tiefbau Strassenbau",
    "sg:phone":"+41 52 376 14 42",
    "sg:postcode":"9507",
    "sg:province":"Thurgau",
    "wof:name":"Pfeiffer Hans.",
    "wof:placetype":"venue"
},
  "geometry": {"coordinates":[8.955485,47.520538],"type":"Point"}
}