{
  "type": "Feature",
  "properties": {
    "iso:country":"CH",
    "sg:address":"Dufourstrasse 7",
    "sg:city":"Rorschach",
    "sg:orig_category":"Herstellung von Schl\u00f6ssern U Beschl\u00e4gen",
    "sg:phone":"+41 71 841 12 24",
    "sg:postcode":"9400",
    "sg:province":"St. Gallen",
    "wof:name":"Schl\u00fcssel Schneider, Nachfolger Hutter Othmar",
    "wof:placetype":"venue"
},
  "geometry": {"coordinates":[9.4877758026,47.4751663208],"type":"Point"}
}