{
  "type": "Feature",
  "properties": {
    "iso:country":"CH",
    "sg:address":"S\u00e4giweg 7",
    "sg:city":"Hauptwil",
    "sg:orig_category":"Allgemeiner Gartenbau Dienstleistungen im Gartenbau",
    "sg:phone":"+41 71 278 29 30",
    "sg:postcode":"9213",
    "sg:province":"Thurgau",
    "wof:name":"Hofst\u00e4dter Gartenbau",
    "wof:placetype":"venue"
},
  "geometry": {"coordinates":[9.256289,47.477825],"type":"Point"}
}