{
  "type": "Feature",
  "properties": {
    "iso:country":"CH",
    "sg:address":"Rue De La Gare 11",
    "sg:city":"Nyon",
    "sg:orig_category":"Zahnarztpraxen",
    "sg:phone":"+41 22 361 64 21",
    "sg:postcode":"1260",
    "sg:province":"Vaud",
    "wof:name":"Dr M\u00e9d. Dent. Jean Monney M\u00e9decin-dentiste",
    "wof:placetype":"venue"
},
  "geometry": {"coordinates":[6.2381367683,46.3825073242],"type":"Point"}
}