{
  "type": "Feature",
  "properties": {
    "iso:country":"CH",
    "sg:address":"Dorfstrasse 39",
    "sg:city":"Embrach",
    "sg:orig_category":"Detailhandel mit Radio U Fernsehger\u00e4ten Detailhandel mit fotografischen Artikeln",
    "sg:phone":"+41 18651670",
    "sg:postcode":"8424",
    "sg:province":"Z\u00fcrich",
    "wof:name":"Rolf Bosshard Expert Bosshard Radio/tv Foto",
    "wof:placetype":"venue"
},
  "geometry": {"coordinates":[8.594291687,47.5037574768],"type":"Point"}
}