{
  "type": "Feature",
  "properties": {
    "iso:country":"CH",
    "sg:address":"Dorfstrasse 7 6340 Baar. Postfach 1262",
    "sg:city":"Baar",
    "sg:orig_category":"Mit dem Versicherungsgewerbe verbundene T\u00e4tigkeiten",
    "sg:phone":"+41 14810304",
    "sg:postcode":"6340",
    "sg:province":"Zug",
    "wof:name":"Bs Bruno Suligoi, Finanztreuhand",
    "wof:placetype":"venue"
},
  "geometry": {"coordinates":[8.5257787704,47.1942024231],"type":"Point"}
}