{
  "type": "Feature",
  "properties": {
    "iso:country":"CH",
    "sg:address":"Seltisbergerstrasse 46",
    "sg:city":"Liestal",
    "sg:orig_category":"Detailhandel mit Metallwaren, Anstrichmitteln, Glaswaren, Bau U Heimwerkerbedarf",
    "sg:phone":"+41 61 923 05 70",
    "sg:postcode":"4410",
    "sg:province":"Basel-Landschaft",
    "wof:name":"Glasbedarf + Montagen Germann Rolf",
    "wof:placetype":"venue"
},
  "geometry": {"coordinates":[7.7339057922,47.4774131775],"type":"Point"}
}