{
  "type": "Feature",
  "properties": {
    "iso:country":"CH",
    "sg:address":"Binningerstrasse 9",
    "sg:city":"Allschwil",
    "sg:orig_category":"Herstellung von Konstruktionsteilen, Fertigbauteilen U Ausbauelementen aus Holz",
    "sg:phone":"+41 61 482 02 78",
    "sg:postcode":"4123",
    "sg:province":"Basel-Landschaft",
    "wof:name":"Sywadec Giess Roland",
    "wof:placetype":"venue"
},
  "geometry": {"coordinates":[7.540459156,47.5515327454],"type":"Point"}
}