{
  "type": "Feature",
  "properties": {
    "iso:country":"CH",
    "sg:address":"Rigiblickstrasse",
    "sg:city":"Weggis",
    "sg:orig_category":"Herstellung von Metallkonstruktionen",
    "sg:postcode":"6353",
    "sg:province":"Luzern",
    "wof:name":"Spiess Montagen",
    "wof:placetype":"venue"
},
  "geometry": {"coordinates":[8.4347648621,47.0362243652],"type":"Point"}
}