{
  "type": "Feature",
  "properties": {
    "iso:country":"CH",
    "sg:address":"Sonnhaldestrasse 30",
    "sg:city":"Emmen",
    "sg:orig_category":"Interessenvertretungen",
    "sg:postcode":"6032",
    "sg:province":"Luzern",
    "wof:name":"Kunstturnhalle Schwarz",
    "wof:placetype":"venue"
},
  "geometry": {"coordinates":[8.8588428497,47.2597961426],"type":"Point"}
}