{
  "type": "Feature",
  "properties": {
    "iso:country":"CH",
    "sg:address":"Jargonnant Rue De 2 1207 Gen\u00e8ve. Postfach",
    "sg:city":"Gen\u00e8ve",
    "sg:orig_category":"Markt U Meinungsforschung",
    "sg:postcode":"1207",
    "sg:province":"Gen\u00e8ve",
    "wof:name":"Pms P\u00f6ll Dieter Marketing Services",
    "wof:placetype":"venue"
},
  "geometry": {"coordinates":[7.4755010605,46.9268569946],"type":"Point"}
}