{
  "type": "Feature",
  "properties": {
    "iso:country":"CH",
    "sg:address":"Schorenweg 19",
    "sg:city":"Basel",
    "sg:orig_category":"Detailhandel mit Waren verschiedener Art, Hauptrichtung Nahrungsmittel",
    "sg:phone":"+41 91 692 14 12",
    "sg:postcode":"4058",
    "sg:province":"Basel-Stadt",
    "wof:name":"Coop Basel",
    "wof:placetype":"venue"
},
  "geometry": {"coordinates":[7.6103401184,47.5707817078],"type":"Point"}
}