{
  "type": "Feature",
  "properties": {
    "iso:country":"CH",
    "sg:address":"Ziegelbr\u00fcckstrasse 22a",
    "sg:city":"Niederurnen",
    "sg:orig_category":"Fachdetailhandel in Verkaufsr\u00e4umen",
    "sg:phone":"+41 55 610 35 33",
    "sg:postcode":"8867",
    "sg:province":"Glarus",
    "wof:name":"Ncy Navy Club Yachts",
    "wof:placetype":"venue"
},
  "geometry": {"coordinates":[9.0556774139,47.1275749207],"type":"Point"}
}