{
  "type": "Feature",
  "properties": {
    "iso:country":"CH",
    "sg:address":"Chemin Du Closelet 6",
    "sg:city":"Lausanne",
    "sg:orig_category":"HOTELS: OHNE RESTAURANT Instandhaltung U Reparatur von Automobilen",
    "sg:phone":"+41 21 616 84 51",
    "sg:postcode":"1006",
    "sg:province":"Vaud",
    "wof:name":"Garage-h\u00f4tel Excelsior Sa",
    "wof:placetype":"venue"
},
  "geometry": {"coordinates":[6.6325531006,46.5144233704],"type":"Point"}
}