{
  "type": "Feature",
  "properties": {
    "iso:country":"CH",
    "sg:address":"Bahnhofstrasse 11",
    "sg:city":"Lyssach",
    "sg:orig_category":"Detailhandel mit Brot, Back U S\u00fcsswaren",
    "sg:phone":"+41 41 921 13 67",
    "sg:postcode":"3421",
    "sg:province":"Bern",
    "wof:name":"L\u00fctolf-m\u00fcller Friedrich",
    "wof:placetype":"venue"
},
  "geometry": {"coordinates":[8.072201,47.199047],"type":"Point"}
}