{
  "type": "Feature",
  "properties": {
    "iso:country":"CH",
    "sg:address":"Altst\u00e4tterstrasse 1 9451 Kriessern. Postfach",
    "sg:city":"Kriessern",
    "sg:orig_category":"RESTAURANTS: TEA-ROOMS",
    "sg:phone":"+41 71 722 23 40",
    "sg:postcode":"9451",
    "sg:province":"St. Gallen",
    "wof:name":"Restaurant Sonne, R\u00fcscher",
    "wof:placetype":"venue"
},
  "geometry": {"coordinates":[9.6059656143,47.3651809692],"type":"Point"}
}