{
  "type": "Feature",
  "properties": {
    "iso:country":"CH",
    "sg:address":"Warpelstrasse 10 3186 D\u00fcdingen. Postfach 12",
    "sg:city":"D\u00fcdingen",
    "sg:orig_category":"Patentverwertung",
    "sg:phone":"+41 26 492 96 60",
    "sg:postcode":"3186",
    "sg:province":"Fribourg",
    "wof:name":"Allper Ag",
    "wof:placetype":"venue"
},
  "geometry": {"coordinates":[7.2029771805,46.8610496521],"type":"Point"}
}