{
  "type": "Feature",
  "properties": {
    "iso:country":"CH",
    "sg:address":"Im Chapf 253",
    "sg:city":"R\u00fcdlingen",
    "sg:orig_category":"Saunas Solarien",
    "sg:phone":"+41 18671767",
    "sg:postcode":"8455",
    "sg:province":"Schaffhausen",
    "wof:name":"Marcel Quiblier Solarium Chapf",
    "wof:placetype":"venue"
},
  "geometry": {"coordinates":[8.5667591095,47.5773696899],"type":"Point"}
}