{
  "type": "Feature",
  "properties": {
    "iso:country":"CH",
    "sg:address":"1628",
    "sg:city":"Vuadens",
    "sg:orig_category":"Sportvereine Sch\u00fctzen",
    "sg:postcode":"1628",
    "sg:province":"Fribourg",
    "wof:name":"St\u00e9 De Tir",
    "wof:placetype":"venue"
},
  "geometry": {"coordinates":[7.0663948059,46.6079711914],"type":"Point"}
}