{
  "type": "Feature",
  "properties": {
    "iso:country":"CH",
    "sg:address":"Schwelli",
    "sg:city":"Pragg-jenaz",
    "sg:orig_category":"Autospenglereien",
    "sg:phone":"+41 81 332 21 01",
    "sg:postcode":"7231",
    "sg:province":"Graubunden",
    "wof:name":"Hans-jakob Val\u00e4r Autospenglerei",
    "wof:placetype":"venue"
},
  "geometry": {"coordinates":[9.708731,46.940033],"type":"Point"}
}