{
  "type": "Feature",
  "properties": {
    "iso:country":"CH",
    "sg:address":"5 Chemin Des Aulx",
    "sg:city":"Plan-les-ouates",
    "sg:classifiers":[
        {
            "category":"Wholesale",
            "subcategory":"Medical Equipment & Supplies",
            "type":"Manufacturing & Wholesale Goods"
        }
    ],
    "sg:phone":"+41 4119346060",
    "sg:postcode":"1228",
    "sg:province":"Gen\u00e8ve",
    "sg:tags":[
        "instrument",
        "health",
        "-",
        "precision"
    ],
    "wof:name":"Sun World Ag",
    "wof:placetype":"venue"
},
  "geometry": {"coordinates":[8.7938747406,47.3109474182],"type":"Point"}
}