{
  "type": "Feature",
  "properties": {
    "addr:full":"Nordstrasse 44 8006 Z\u00fcrich. Postfach 2911 Z\u00fcrich Z\u00fcrich 8021",
    "addr:housenumber":"44",
    "addr:postcode":"8006 zuerich. postfach 2911;8021",
    "addr:street":"Nordstrasse",
    "iso:country":"CH",
    "sg:address":"Nordstrasse 44 8006 Z\u00fcrich. Postfach 2911",
    "sg:city":"Z\u00fcrich",
    "sg:orig_category":"Allgemeiner Hoch U Tiefbau ohne ausgepr\u00e4gten Schwerpunkt",
    "sg:phone":"+41 12472211",
    "sg:postcode":"8021",
    "sg:province":"Z\u00fcrich",
    "wof:name":"Kantonspolizei Z\u00fcrich Organisationsabteilung",
    "wof:placetype":"venue"
},
  "geometry": {"coordinates":[8.538078,47.38607],"type":"Point"}
}