{
  "type": "Feature",
  "properties": {
    "iso:country":"CH",
    "sg:address":"Arbonerstrasse 6 9302 Kronb\u00fchl. Postfach",
    "sg:city":"Kronb\u00fchl",
    "sg:orig_category":"Fachdetailhandel in Verkaufsr\u00e4umen",
    "sg:phone":"+41 71 298 18 58",
    "sg:postcode":"9302",
    "wof:name":"Xix Gmbh",
    "wof:placetype":"venue"
},
  "geometry": {"coordinates":[9.3949985504,47.460395813],"type":"Point"}
}