{
  "type": "Feature",
  "properties": {
    "iso:country":"CH",
    "sg:address":"Rue De Zurich 24",
    "sg:city":"Gen\u00e8ve",
    "sg:orig_category":"Detailhandel mit Herrenbekleidung Herstellung von konfektionierten Textilwaren ohne Bekleidung",
    "sg:phone":"+41 22 738 63 21",
    "sg:postcode":"1201",
    "sg:province":"Gen\u00e8ve",
    "wof:name":"Boutique Milione Battista",
    "wof:placetype":"venue"
},
  "geometry": {"coordinates":[6.1471362114,46.211730957],"type":"Point"}
}