{
  "type": "Feature",
  "properties": {
    "iso:country":"CH",
    "sg:address":"Faisswiesen",
    "sg:city":"Dietlikon",
    "sg:classifiers":[
        {
            "category":"Restaurant",
            "type":"Food & Drink"
        }
    ],
    "sg:phone":"+41 18331844",
    "sg:postcode":"8305",
    "sg:province":"Z\u00fcrich",
    "wof:name":"Hallenbad Restaurant",
    "wof:placetype":"venue"
},
  "geometry": {"coordinates":[8.6212673187,47.4219169617],"type":"Point"}
}