{
  "type": "Feature",
  "properties": {
    "iso:country":"CH",
    "sg:address":"Isla",
    "sg:city":"Mastrils",
    "sg:orig_category":"Stukkateurgewerbe, Gipserei U Verputzerei",
    "sg:phone":"+41 71 920 10 54",
    "sg:postcode":"7303",
    "sg:province":"Graubunden",
    "wof:name":"Gips- & Mal-fix Gmbh Gipser, Maler, Aussenisolations- Arbeiten. Handel Mit Waren, Bes. Baumaterialien Usw",
    "wof:placetype":"venue"
},
  "geometry": {"coordinates":[9.0411367416,47.4615478516],"type":"Point"}
}