{
  "type": "Feature",
  "properties": {
    "iso:country":"CH",
    "sg:address":"Gitterlistrasse 8",
    "sg:city":"Liestal",
    "sg:orig_category":"Fachdetailhandel in Verkaufsr\u00e4umen",
    "sg:phone":"+41 61 922 01 02",
    "sg:postcode":"4410",
    "sg:province":"Basel-Landschaft",
    "wof:name":"Emma Martin, Handel Mit Geschenkartikeln",
    "wof:placetype":"venue"
},
  "geometry": {"coordinates":[7.7406020164,47.4793739319],"type":"Point"}
}