{
  "type": "Feature",
  "properties": {
    "iso:country":"CH",
    "sg:address":"Faubourg Du Lac 2",
    "sg:city":"Neuch\u00e2tel",
    "sg:classifiers":[
        {
            "category":"Bars & Pubs",
            "type":"Food & Drink"
        }
    ],
    "sg:phone":"+41 32 725 18 86",
    "sg:postcode":"2000",
    "sg:province":"Neuch\u00e2tel",
    "wof:name":"Moscato Paolo",
    "wof:placetype":"venue"
},
  "geometry": {"coordinates":[6.93162,46.991283],"type":"Point"}
}