{
  "type": "Feature",
  "properties": {
    "iso:country":"CH",
    "sg:address":"F\u00e4hrstrasse 37",
    "sg:city":"Bern",
    "sg:orig_category":"Herstellung von Konstruktionsteilen, Fertigbauteilen U Ausbauelementen aus Holz",
    "sg:postcode":"3004",
    "sg:province":"Bern",
    "wof:name":"H. Dubach",
    "wof:placetype":"venue"
},
  "geometry": {"coordinates":[7.4417471886,46.97498703],"type":"Point"}
}