{
  "type": "Feature",
  "properties": {
    "iso:country":"CH",
    "sg:address":"Seestrasse 37",
    "sg:city":"Sutz",
    "sg:classifiers":[
        {
            "category":"Restaurant",
            "type":"Food & Drink"
        }
    ],
    "sg:phone":"+41 32 397 20 49",
    "sg:postcode":"2572",
    "sg:province":"Bern",
    "wof:name":"Restaurant Seepintli Gmbh",
    "wof:placetype":"venue"
},
  "geometry": {"coordinates":[7.209980011,47.0970726013],"type":"Point"}
}