{
  "type": "Feature",
  "properties": {
    "iso:country":"CH",
    "sg:address":"Seestrasse 32",
    "sg:city":"R\u00fcschlikon",
    "sg:orig_category":"Unternehmensberatung",
    "sg:phone":"+41 61 711 71 41",
    "sg:postcode":"8803",
    "sg:province":"Z\u00fcrich",
    "wof:name":"Alliancat Gmbh Beratungsunternehmen Mit Beratung, Coaching Und Verhandlung Von Lizenzen, Technologie-transfer Usw",
    "wof:placetype":"venue"
},
  "geometry": {"coordinates":[7.6021399498,47.4791412354],"type":"Point"}
}