{
  "type": "Feature",
  "properties": {
    "addr:full":"Nordstrasse 110 Z\u00fcrich Z\u00fcrich 8037",
    "addr:housenumber":"110",
    "addr:postcode":"8037",
    "addr:street":"Nordstrasse",
    "iso:country":"CH",
    "sg:address":"Nordstrasse 110",
    "sg:city":"Z\u00fcrich",
    "sg:orig_category":"Architektur U Ingenieurb\u00fcros Architekturb\u00fcros",
    "sg:phone":"+41 13640546",
    "sg:postcode":"8037",
    "sg:province":"Z\u00fcrich",
    "wof:name":"Team 4 Franz + Schneider Architekten Eth/sia",
    "wof:placetype":"venue"
},
  "geometry": {"coordinates":[8.534893,47.389565],"type":"Point"}
}