{
  "type": "Feature",
  "properties": {
    "iso:country":"CH",
    "sg:address":"Chemin De La Prairie 10",
    "sg:city":"Corminboeuf",
    "sg:orig_category":"Softwareentwicklung U beratung",
    "sg:phone":"+41 26 475 20 50",
    "sg:postcode":"1720",
    "sg:province":"Fribourg",
    "wof:name":"Nobs Anne-elisabeth",
    "wof:placetype":"venue"
},
  "geometry": {"coordinates":[7.100851059,46.8131866455],"type":"Point"}
}