{
  "type": "Feature",
  "properties": {
    "iso:country":"CH",
    "sg:address":"Malerweg 2 3600 Thun. Postfach 1341",
    "sg:city":"Thun",
    "sg:orig_category":"Organisationen der Wohlfahrtspflege",
    "sg:phone":"+41 33 226 60 60",
    "sg:postcode":"3601",
    "sg:province":"Bern",
    "wof:name":"Pro Senectute Oberland-west",
    "wof:placetype":"venue"
},
  "geometry": {"coordinates":[7.6278810501,46.7565879822],"type":"Point"}
}