{
  "type": "Feature",
  "properties": {
    "addr:full":"6674 Someo Ticino 6674",
    "addr:housenumber":"6674;6674",
    "addr:street":"Someo Ticino",
    "iso:country":"CH",
    "sg:address":"6674",
    "sg:city":"Someo",
    "sg:classifiers":[
        {
            "category":"Social Services",
            "subcategory":"Retirement Home",
            "type":"Services"
        }
    ],
    "sg:phone":"+41 91 753 27 75",
    "sg:postcode":"6674",
    "sg:province":"Ticino",
    "sg:tags":[
        "pflegeheime",
        "u",
        "alters"
    ],
    "wof:name":"Valmaggese Casa Per Anziani",
    "wof:placetype":"venue"
},
  "geometry": {"coordinates":[8.66638,46.286331],"type":"Point"}
}