{
  "type": "Feature",
  "properties": {
    "iso:country":"CH",
    "sg:address":"Le Vieux-pressoir",
    "sg:city":"Epesses",
    "sg:orig_category":"Rebbau",
    "sg:phone":"+41 21 799 14 00",
    "sg:postcode":"1098",
    "sg:province":"Vaud",
    "wof:name":"Gaston Dubois Vigneron-encaveur",
    "wof:placetype":"venue"
},
  "geometry": {"coordinates":[6.7467498779,46.491771698],"type":"Point"}
}