{
  "type": "Feature",
  "properties": {
    "iso:country":"CH",
    "sg:address":"Rue Du Lac 41",
    "sg:city":"Yverdon-les-bains",
    "sg:classifiers":[
        {
            "category":"Utilities",
            "subcategory":"Water",
            "type":"Services"
        }
    ],
    "sg:phone":"+41 24 425 66 14",
    "sg:postcode":"1400",
    "sg:province":"Vaud",
    "sg:tags":[
        "tea-rooms",
        "bar",
        "restaurants"
    ],
    "wof:name":"Brasserie-pub Le Silver, Signorello Eva Et Giacchino",
    "wof:placetype":"venue"
},
  "geometry": {"coordinates":[6.638591,46.779884],"type":"Point"}
}