{
  "type": "Feature",
  "properties": {
    "iso:country":"CH",
    "sg:address":"Riehenring 45",
    "sg:city":"Basel",
    "sg:classifiers":[
        {
            "category":"Banks & Credit Unions",
            "subcategory":"Bank",
            "type":"Services"
        }
    ],
    "sg:phone":"+41 61 266 26 66",
    "sg:postcode":"4058",
    "sg:province":"Basel-Stadt",
    "wof:name":"Basler Kantonalbank",
    "wof:placetype":"venue"
},
  "geometry": {"coordinates":[7.599882,47.562401],"type":"Point"}
}