{
  "type": "Feature",
  "properties": {
    "iso:country":"CH",
    "sg:address":"Via Beltramina 15",
    "sg:city":"Lugano",
    "sg:orig_category":"Religi\u00f6se Vereinigungen",
    "sg:postcode":"6900",
    "sg:province":"Ticino",
    "wof:name":"Comunit\u00e0 Israelita Di Lugano",
    "wof:placetype":"venue"
},
  "geometry": {"coordinates":[8.9600639343,46.0168380737],"type":"Point"}
}