{
  "type": "Feature",
  "properties": {
    "iso:country":"CH",
    "sg:address":"Poststrasse 109",
    "sg:city":"Spreitenbach",
    "sg:orig_category":"Gartenbau",
    "sg:phone":"+41 56 402 10 69",
    "sg:postcode":"8957",
    "sg:province":"Aargau",
    "wof:name":"Kalt Daniel - Gartenbau, Gartenpflege",
    "wof:placetype":"venue"
},
  "geometry": {"coordinates":[8.3597755432,47.4249382019],"type":"Point"}
}