{
  "type": "Feature",
  "properties": {
    "iso:country":"CH",
    "sg:address":"2068",
    "sg:city":"Hauterive",
    "sg:orig_category":"Sportvereine Ballsport Volleyball Vereine Damen",
    "sg:postcode":"2068",
    "sg:province":"Neuch\u00e2tel",
    "wof:name":"Group Volleyb.berne-b\u00fcmpliz",
    "wof:placetype":"venue"
},
  "geometry": {"coordinates":[6.9759001732,47.0046806335],"type":"Point"}
}