{
  "type": "Feature",
  "properties": {
    "iso:country":"CH",
    "sg:address":"Staubergasse 3",
    "sg:city":"Maur",
    "sg:orig_category":"Mit Sport verbundene T\u00e4tigkeiten Unterhaltung, Kultur U Sport",
    "sg:phone":"+41 19806383",
    "sg:postcode":"8124",
    "sg:province":"Z\u00fcrich",
    "wof:name":"Mandate Management Ag Sportmarketing",
    "wof:placetype":"venue"
},
  "geometry": {"coordinates":[8.6703472137,47.3390235901],"type":"Point"}
}