{
  "type": "Feature",
  "properties": {
    "iso:country":"CH",
    "sg:address":"Schlossergasse 3 6247 Sch\u00f6tz. Postfach",
    "sg:city":"Sch\u00f6tz",
    "sg:orig_category":"Sanit\u00e4r, Heizungs U L\u00fcftungsinstallation Sanit\u00e4rinstallation",
    "sg:phone":"+41 41 980 13 34",
    "sg:postcode":"6247",
    "sg:province":"Luzern",
    "wof:name":"Graf Josef, Heizung, L\u00fcftung, Sanit\u00e4r",
    "wof:placetype":"venue"
},
  "geometry": {"coordinates":[7.9870991707,47.1703948975],"type":"Point"}
}