{
  "type": "Feature",
  "properties": {
    "iso:country":"CH",
    "sg:address":"4313",
    "sg:city":"M\u00f6hlin",
    "sg:orig_category":"Vorschulen, Kinderg\u00e4rten",
    "sg:phone":"+41 52 741 17 31",
    "sg:postcode":"4313",
    "sg:province":"Aargau",
    "wof:name":"Kindergarten Schanz",
    "wof:placetype":"venue"
},
  "geometry": {"coordinates":[8.8609972,47.6600379944],"type":"Point"}
}