{
  "type": "Feature",
  "properties": {
    "iso:country":"CH",
    "sg:address":"L\u00e4ngackerstrasse 32",
    "sg:city":"Riedholz",
    "sg:orig_category":"Hardwareberatung",
    "sg:postcode":"4533",
    "sg:province":"Solothurn",
    "wof:name":"Comdata Informatik Wipfli Computer; Handel, Unterhalt",
    "wof:placetype":"venue"
},
  "geometry": {"coordinates":[8.6077957153,46.8810882568],"type":"Point"}
}