{
  "type": "Feature",
  "properties": {
    "iso:country":"CH",
    "sg:address":"Alte Bernstrasse 32 2558 Aegerten. Postfach",
    "sg:city":"Aegerten",
    "sg:orig_category":"Handel mit Automobilen",
    "sg:phone":"+41 32 373 60 70",
    "sg:postcode":"2558",
    "sg:province":"Bern",
    "wof:name":"Rattinbus International Gmbh Fahrzeuge, Bes. Omnibusse; Handel Usw.",
    "wof:placetype":"venue"
},
  "geometry": {"coordinates":[7.2916998863,47.1187591553],"type":"Point"}
}