{
  "type": "Feature",
  "properties": {
    "iso:country":"CH",
    "sg:address":"Piano La Stampa",
    "sg:city":"Davesco-soragno",
    "sg:orig_category":"Erzeugung U Erstbearbeitung von Aluminium Herstellung von Metallerzeugnissen ohne Maschinenbau",
    "sg:phone":"+41 91 940 44 88",
    "sg:postcode":"6964",
    "sg:province":"Ticino",
    "wof:name":"Sala Alu Sagl Costr.in Alluminio & Metallo",
    "wof:placetype":"venue"
},
  "geometry": {"coordinates":[8.9895296097,46.0325584412],"type":"Point"}
}