{
  "type": "Feature",
  "properties": {
    "iso:country":"CH",
    "sg:address":"Paleu Sura 7013 Domat/ems. Postfach 46",
    "sg:city":"Domat/ems",
    "sg:orig_category":"Druck ohne Zeitungsdruck Offsetdruck",
    "sg:phone":"+41 81 250 05 55",
    "sg:postcode":"7013",
    "sg:province":"Graubunden",
    "wof:name":"Amedes Druck Ag",
    "wof:placetype":"venue"
},
  "geometry": {"coordinates":[9.4798402786,46.8416366577],"type":"Point"}
}