{
  "type": "Feature",
  "properties": {
    "iso:country":"CH",
    "sg:address":"Wiesenstrasse 19",
    "sg:city":"Langenthal",
    "sg:orig_category":"Sanit\u00e4r U Heizungsinstallation Sanit\u00e4rinstallation",
    "sg:phone":"+41 62 922 45 85",
    "sg:postcode":"4900",
    "sg:province":"Bern",
    "wof:name":"Hans-rudolf Hofer Heizung L\u00fcftung Sanit\u00e4r",
    "wof:placetype":"venue"
},
  "geometry": {"coordinates":[7.7862801552,47.2122840881],"type":"Point"}
}