{
  "type": "Feature",
  "properties": {
    "iso:country":"CH",
    "sg:address":"Carmenstrasse 39 8032 Z\u00fcrich. Postfach 39",
    "sg:city":"Z\u00fcrich",
    "sg:orig_category":"Grosshandel mit Getr\u00e4nken Grosshandel mit Wein U Spirituosen",
    "sg:phone":"+41 12543300",
    "sg:postcode":"8030",
    "wof:name":"Bols-cynar-ballantine's Ag",
    "wof:placetype":"venue"
},
  "geometry": {"coordinates":[8.563202858,47.3679962158],"type":"Point"}
}