{
  "type": "Feature",
  "properties": {
    "addr:full":"Breisacherstrasse 10 Basel Basel-Stadt 4057",
    "addr:housenumber":"10",
    "addr:postcode":"4057",
    "addr:street":"Breisacherstrasse",
    "iso:country":"CH",
    "sg:address":"Breisacherstrasse 10",
    "sg:city":"Basel",
    "sg:orig_category":"Betrieb von Theatern, Opern, Schauspielh\u00e4usern U Konzerthallen",
    "sg:phone":"+41 61 691 24 23",
    "sg:postcode":"4057",
    "sg:province":"Basel-Stadt",
    "wof:name":"Theater Klara",
    "wof:placetype":"venue"
},
  "geometry": {"coordinates":[7.589845,47.564198],"type":"Point"}
}