{
  "type": "Feature",
  "properties": {
    "iso:country":"CH",
    "sg:address":"Via C. Ghiringhelli 57d",
    "sg:city":"Bellinzona",
    "sg:classifiers":[
        {
            "category":"Arts & Performance",
            "subcategory":"Art Gallery",
            "type":"Entertainment"
        }
    ],
    "sg:phone":"+41 79 655 61 04",
    "sg:postcode":"6500",
    "sg:province":"Ticino",
    "sg:tags":[
        "painting"
    ],
    "wof:name":"Francesca Rossi Restauro Di Dipinti E Ceramiche",
    "wof:placetype":"venue"
},
  "geometry": {"coordinates":[9.01457,46.183449],"type":"Point"}
}