{
  "type": "Feature",
  "properties": {
    "iso:country":"CH",
    "sg:address":"Belchenstrasse 12",
    "sg:city":"Rheinfelden",
    "sg:orig_category":"Bauspenglerei Zimmerei, Dachdeckerei, Bauspenglerei U Abdichtung",
    "sg:phone":"+41 61 831 51 89",
    "sg:postcode":"4310",
    "sg:province":"Aargau",
    "wof:name":"Greiner Ag",
    "wof:placetype":"venue"
},
  "geometry": {"coordinates":[7.787944,47.550819],"type":"Point"}
}