{
  "type": "Feature",
  "properties": {
    "iso:country":"CH",
    "sg:address":"Avenue Guillemin 14",
    "sg:city":"Pully",
    "sg:orig_category":"Detailhandel mit Metallwaren, Anstrichmitteln, Glaswaren, Bau U Heimwerkerbedarf",
    "sg:phone":"+41 21 729 47 71",
    "sg:postcode":"1009",
    "sg:province":"Vaud",
    "wof:name":"Protec, Dufour G.",
    "wof:placetype":"venue"
},
  "geometry": {"coordinates":[6.655559063,46.51379776],"type":"Point"}
}