{
  "type": "Feature",
  "properties": {
    "iso:country":"CH",
    "sg:address":"S\u00e4ntisblickstrasse 7",
    "sg:city":"Amriswil",
    "sg:orig_category":"Sonstiger spezialisierter Hoch U Tiefbau",
    "sg:phone":"+41 71 411 39 28",
    "sg:postcode":"8580",
    "sg:province":"Thurgau",
    "wof:name":"Ferrobau Armierungs Ag",
    "wof:placetype":"venue"
},
  "geometry": {"coordinates":[9.3069877625,47.5493659973],"type":"Point"}
}