{
  "type": "Feature",
  "properties": {
    "addr:full":"Aspstrasse 59 Seuzach Z\u00fcrich 8472",
    "addr:housenumber":"59",
    "addr:postcode":"8472",
    "addr:street":"Aspstrasse",
    "iso:country":"CH",
    "sg:address":"Aspstrasse 59",
    "sg:city":"Seuzach",
    "sg:orig_category":"Bauingenieurb\u00fcros Eisenbetonbau Bauingenieurb\u00fcros allgemein",
    "sg:postcode":"8472",
    "sg:province":"Z\u00fcrich",
    "wof:name":"B\u00e4nziger Bacchetta Fehlmann & Partner Ingenieure & Planer",
    "wof:placetype":"venue"
},
  "geometry": {"coordinates":[8.724452,47.274078],"type":"Point"}
}