{
  "type": "Feature",
  "properties": {
    "iso:country":"CH",
    "sg:address":"Hofacker 1",
    "sg:city":"Marthalen",
    "sg:orig_category":"Bauschreinerei Glaserei",
    "sg:phone":"+41 52 319 16 92",
    "sg:postcode":"8460",
    "sg:province":"Z\u00fcrich",
    "wof:name":"Gottlieb Hug Bauschreinerei & Glaserei",
    "wof:placetype":"venue"
},
  "geometry": {"coordinates":[8.649847,47.62318],"type":"Point"}
}