{
  "type": "Feature",
  "properties": {
    "iso:country":"CH",
    "sg:address":"1948",
    "sg:city":"Lourtier",
    "sg:orig_category":"Instandhaltung U Reparatur von Automobilen",
    "sg:phone":"+41 27 778 14 55",
    "sg:postcode":"1948",
    "sg:province":"Valais",
    "wof:name":"Maret Vincent",
    "wof:placetype":"venue"
},
  "geometry": {"coordinates":[7.3359398842,46.0026512146],"type":"Point"}
}