{
  "type": "Feature",
  "properties": {
    "iso:country":"CH",
    "sg:address":"Casa Clarida",
    "sg:city":"Contra",
    "sg:orig_category":"Pensionskassen",
    "sg:phone":"+41 91 745 22 59",
    "sg:postcode":"6646",
    "sg:province":"Ticino",
    "wof:name":"Jakob Lerchm\u00fcller Fondazione Per Il Personale",
    "wof:placetype":"venue"
},
  "geometry": {"coordinates":[8.8394403458,46.1885643005],"type":"Point"}
}