{
  "type": "Feature",
  "properties": {
    "iso:country":"CH",
    "sg:address":"Sch\u00f6neggstrasse",
    "sg:city":"W\u00e4denswil",
    "sg:classifiers":[
        {
            "category":"Restaurant",
            "type":"Food & Drink"
        }
    ],
    "sg:phone":"+41 17898960",
    "sg:postcode":"8820",
    "sg:province":"Z\u00fcrich",
    "wof:name":"Restaurant Sch\u00f6negg",
    "wof:placetype":"venue"
},
  "geometry": {"coordinates":[8.6480998993,47.2348899841],"type":"Point"}
}