{
  "type": "Feature",
  "properties": {
    "iso:country":"CH",
    "sg:address":"Oberdorfstr. 123",
    "sg:city":"Leibstadt",
    "sg:classifiers":[
        {
            "category":"Food & Beverages",
            "subcategory":"Groceries & Convenience Stores",
            "type":"Retail Goods"
        }
    ],
    "sg:phone":"+41 56 247 11 44",
    "sg:postcode":"5325",
    "sg:province":"Aargau",
    "sg:tags":[
        "product",
        "related"
    ],
    "wof:name":"Knecht M\u00dchle Ag Leibstadt",
    "wof:placetype":"venue"
},
  "geometry": {"coordinates":[8.1759443283,47.5872955322],"type":"Point"}
}