{
  "type": "Feature",
  "properties": {
    "iso:country":"CH",
    "sg:address":"Nant-d'avril Route Du 40 1217 Meyrin. Postfach",
    "sg:city":"Meyrin",
    "sg:orig_category":"Handel mit Automobilen",
    "sg:postcode":"1217",
    "sg:province":"Gen\u00e8ve",
    "wof:name":"Perez Automobiles Commerce De Voitures",
    "wof:placetype":"venue"
},
  "geometry": {"coordinates":[6.0841169357,46.247303009],"type":"Point"}
}