{
  "type": "Feature",
  "properties": {
    "iso:country":"CH",
    "sg:address":"Orbe Rue D' 38",
    "sg:city":"Yverdon-les-bains",
    "sg:classifiers":[
        {
            "category":"Bars & Pubs",
            "type":"Food & Drink"
        }
    ],
    "sg:phone":"+41 24 426 56 10",
    "sg:postcode":"1400",
    "sg:province":"Vaud",
    "wof:name":"L'aurore, Filipe Ferreira Joao",
    "wof:placetype":"venue"
},
  "geometry": {"coordinates":[6.628979,46.754066],"type":"Point"}
}