{
  "type": "Feature",
  "properties": {
    "iso:country":"CH",
    "sg:address":"Benzburweg 18",
    "sg:city":"Liestal",
    "sg:orig_category":"Wirtschaftspr\u00fcfung, Steuerberatung U Treuhand",
    "sg:phone":"+41 61 423 08 30",
    "sg:postcode":"4410",
    "sg:province":"Basel-Landschaft",
    "wof:name":"Treuhand Hehlen Ursula",
    "wof:placetype":"venue"
},
  "geometry": {"coordinates":[7.741150856,47.4751548767],"type":"Point"}
}