{
  "type": "Feature",
  "properties": {
    "iso:country":"CH",
    "sg:address":"Bahnhofstrasse 2",
    "sg:city":"Pieterlen",
    "sg:orig_category":"Detailhandel mit Radio U Fernsehger\u00e4ten Detailhandel mit elektrischen Haushalts-,Radio U Fernsehger\u00e4",
    "sg:phone":"+41 32 377 17 43",
    "sg:postcode":"2542",
    "sg:province":"Bern",
    "wof:name":"Reber Martin, Radio-tv",
    "wof:placetype":"venue"
},
  "geometry": {"coordinates":[7.3380331993,47.174785614],"type":"Point"}
}