{
  "type": "Feature",
  "properties": {
    "iso:country":"CH",
    "sg:address":"Heidenlochstrasse 31",
    "sg:city":"Liestal",
    "sg:classifiers":[
        {
            "category":"Personal",
            "subcategory":"Sauna",
            "type":"Services"
        }
    ],
    "sg:phone":"+41 61 921 95 59",
    "sg:postcode":"4410",
    "sg:province":"Basel-Landschaft",
    "wof:name":"Claire Spreyermann Sauna",
    "wof:placetype":"venue"
},
  "geometry": {"coordinates":[7.7490148544,47.4821472168],"type":"Point"}
}