{
  "type": "Feature",
  "properties": {
    "iso:country":"CH",
    "sg:address":"Badenerstrasse 18",
    "sg:city":"Oberrohrdorf",
    "sg:classifiers":[
        {
            "category":"Government",
            "subcategory":"Fire Station",
            "type":"Public Place"
        }
    ],
    "sg:phone":"+41 56 496 45 12",
    "sg:postcode":"5452",
    "sg:province":"Aargau",
    "sg:tags":[
        "steel",
        "processing",
        "chromium-nickel"
    ],
    "wof:name":"Noser-inox Ag",
    "wof:placetype":"venue"
},
  "geometry": {"coordinates":[8.314968,47.420967],"type":"Point"}
}