{
  "type": "Feature",
  "properties": {
    "iso:country":"CH",
    "sg:address":"6285",
    "sg:city":"Hitzkirch",
    "sg:orig_category":"Sportvereine Sch\u00fctzen",
    "sg:postcode":"6285",
    "sg:province":"Luzern",
    "wof:name":"Schiessverein",
    "wof:placetype":"venue"
},
  "geometry": {"coordinates":[8.2632598877,47.2249412537],"type":"Point"}
}