{
  "type": "Feature",
  "properties": {
    "iso:country":"CH",
    "sg:address":"M\u00fchlehof",
    "sg:city":"Dagmersellen",
    "sg:orig_category":"Detailhandel mit Textilien Innenausbau",
    "sg:phone":"+41 62 756 12 36",
    "sg:postcode":"6252",
    "sg:province":"Luzern",
    "wof:name":"Josef Stocker",
    "wof:placetype":"venue"
},
  "geometry": {"coordinates":[7.9890551567,47.213054657],"type":"Point"}
}