{
  "type": "Feature",
  "properties": {
    "iso:country":"CH",
    "sg:address":"Allmeindstrasse 15",
    "sg:city":"Einsiedeln",
    "sg:orig_category":"Detailhandel mit M\u00f6beln U Haushaltsgegenst\u00e4nden",
    "sg:phone":"+41 55 216 19 44",
    "sg:postcode":"8840",
    "sg:province":"Schwyz",
    "wof:name":"Kurt Bisig Ag",
    "wof:placetype":"venue"
},
  "geometry": {"coordinates":[8.8380699158,47.2958831787],"type":"Point"}
}