{
  "type": "Feature",
  "properties": {
    "iso:country":"CH",
    "sg:address":"Route De Rolle 48",
    "sg:city":"St-prex",
    "sg:classifiers":[
        {
            "category":"Home & Garden",
            "subcategory":"Furniture",
            "type":"Retail Goods"
        }
    ],
    "sg:phone":"+41 52 762 77 77",
    "sg:postcode":"1162",
    "sg:province":"Vaud",
    "wof:name":"Schaffner Ag",
    "wof:placetype":"venue"
},
  "geometry": {"coordinates":[8.9897918701,47.5979385376],"type":"Point"}
}