{
  "type": "Feature",
  "properties": {
    "iso:country":"CH",
    "sg:address":"Martin-distelistr. 26",
    "sg:city":"Olten",
    "sg:classifiers":[
        {
            "category":"Real Estate",
            "subcategory":"Real Estate Agent",
            "type":"Services"
        }
    ],
    "sg:phone":"+41 62 286 81 11",
    "sg:postcode":"4601",
    "sg:province":"Solothurn",
    "sg:tags":[
        "precis",
        "good",
        "instrument",
        "-",
        "metalworking",
        "metallic",
        "metallurgy",
        "equipment",
        "finished",
        "measurement"
    ],
    "wof:name":"R Nussbaum Ag",
    "wof:placetype":"venue"
},
  "geometry": {"coordinates":[7.9102468491,47.3510475159],"type":"Point"}
}