{
  "type": "Feature",
  "properties": {
    "iso:country":"CH",
    "sg:address":"F\u00fcnflindenstrasse 2",
    "sg:city":"Lenzburg",
    "sg:orig_category":"Vermietung von Automobilen",
    "sg:phone":"+41 79 332 75 00",
    "sg:postcode":"5600",
    "sg:province":"Aargau",
    "wof:name":"Lincoln Limousine Service, Tellenbach Urs",
    "wof:placetype":"venue"
},
  "geometry": {"coordinates":[8.1613636017,47.3878211975],"type":"Point"}
}