{
  "type": "Feature",
  "properties": {
    "iso:country":"CH",
    "sg:address":"Ankerstrasse 10 8400 Winterthur. Postfach",
    "sg:city":"Winterthur",
    "sg:orig_category":"Maschinen-Fabrikation",
    "sg:postcode":"8406",
    "sg:province":"Z\u00fcrich",
    "wof:name":"Weilenmann Peter Mechanische Bearbeitung & Prototypenbau",
    "wof:placetype":"venue"
},
  "geometry": {"coordinates":[8.7098779678,47.4905776978],"type":"Point"}
}