{
  "type": "Feature",
  "properties": {
    "iso:country":"CH",
    "sg:address":"Ch\u00f6renmattstrasse 63",
    "sg:city":"Berikon",
    "sg:orig_category":"Drag\u00e9es Sweets",
    "sg:phone":"+41 56 633 95 61",
    "sg:postcode":"8965",
    "sg:province":"Aargau",
    "wof:name":"Mini Fruits Trading",
    "wof:placetype":"venue"
},
  "geometry": {"coordinates":[8.3680677414,47.3575057983],"type":"Point"}
}