{
  "type": "Feature",
  "properties": {
    "iso:country":"CH",
    "sg:address":"Rheinstrasse 16",
    "sg:city":"Liestal",
    "sg:orig_category":"Detailhandel mit Brillen U anderen Sehhilfen Detailhandel mit medizinischen U orthop\u00e4dischen Artikel",
    "sg:phone":"+41 61 923 10 15",
    "sg:postcode":"4410",
    "sg:province":"Basel-Landschaft",
    "wof:name":"Brunner H\u00f6r-akustik, Institut F\u00fcr H\u00f6rger\u00e4te Gmbh",
    "wof:placetype":"venue"
},
  "geometry": {"coordinates":[7.732315,47.486214],"type":"Point"}
}