{
  "type": "Feature",
  "properties": {
    "iso:country":"CH",
    "sg:address":"B\u00fcmpliz",
    "sg:city":"Bern",
    "sg:classifiers":[
        {
            "category":"Banks & Credit Unions",
            "subcategory":"Bank",
            "type":"Services"
        }
    ],
    "sg:phone":"+41 31 991 30 55",
    "sg:postcode":"3018",
    "sg:province":"Bern",
    "wof:name":"Swiss Bank Corporation",
    "wof:placetype":"venue"
},
  "geometry": {"coordinates":[7.39115,46.945999],"type":"Point"}
}