{
  "type": "Feature",
  "properties": {
    "iso:country":"CH",
    "sg:address":"Neubr\u00fcckstrasse 80",
    "sg:city":"Bern",
    "sg:orig_category":"Detailhandel mit Radio U Fernsehger\u00e4ten Herstellung von Radio U Fernsehger\u00e4ten sowie phono U videote",
    "sg:phone":"+41 31 301 21 01",
    "sg:postcode":"3012",
    "sg:province":"Bern",
    "wof:name":"Montesi Radio Tv Multimedia",
    "wof:placetype":"venue"
},
  "geometry": {"coordinates":[7.4370698929,46.9575691223],"type":"Point"}
}