{
  "type": "Feature",
  "properties": {
    "iso:country":"CH",
    "sg:address":"Innere Margarethenstrasse 19",
    "sg:city":"Basel",
    "sg:orig_category":"Massagestudios",
    "sg:phone":"+41 91 743 67 39",
    "sg:postcode":"4051",
    "sg:province":"Basel-Stadt",
    "wof:name":"Hedy L\u00e4nzlinger Massaggi",
    "wof:placetype":"venue"
},
  "geometry": {"coordinates":[8.8300590515,46.1852149963],"type":"Point"}
}