{
  "type": "Feature",
  "properties": {
    "iso:country":"CH",
    "sg:address":"Dorf",
    "sg:city":"Kleinwangen",
    "sg:orig_category":"Handelsvermittlung U Grosshandel mit Automobilen Herstellung von sonstigen landwirtschaftlichen Masc",
    "sg:phone":"+41 41 910 11 63",
    "sg:postcode":"6277",
    "sg:province":"Luzern",
    "wof:name":"Rogger Ag",
    "wof:placetype":"venue"
},
  "geometry": {"coordinates":[8.2919988632,47.1954154968],"type":"Point"}
}