{
  "type": "Feature",
  "properties": {
    "iso:country":"CH",
    "sg:address":"Stationsstrasse 26 8606 Greifensee. Postfach 34",
    "sg:city":"Greifensee",
    "sg:orig_category":"Kantonalbanken",
    "sg:phone":"+41 19056040",
    "sg:postcode":"8606",
    "sg:province":"Z\u00fcrich",
    "wof:name":"Z\u00fcrcher Kantonalbank",
    "wof:placetype":"venue"
},
  "geometry": {"coordinates":[8.6810855865,47.3678588867],"type":"Point"}
}