{
  "type": "Feature",
  "properties": {
    "iso:country":"CH",
    "sg:address":"Stadtweg 56 4310 Rheinfelden. Postfach",
    "sg:city":"Rheinfelden",
    "sg:orig_category":"Herstellung von elektronischen Bauelementen",
    "sg:postcode":"4310",
    "sg:province":"Aargau",
    "wof:name":"Dg Electronics Ag",
    "wof:placetype":"venue"
},
  "geometry": {"coordinates":[7.7964367867,47.5476341248],"type":"Point"}
}