{
  "type": "Feature",
  "properties": {
    "iso:country":"CH",
    "sg:address":"5726",
    "sg:city":"Unterkulm",
    "sg:orig_category":"Verarbeitung von Milch Verwertung von Milch",
    "sg:postcode":"5726",
    "sg:province":"Aargau",
    "wof:name":"Milchgenossenschaft Wannenhof",
    "wof:placetype":"venue"
},
  "geometry": {"coordinates":[8.1150026321,47.3104400635],"type":"Point"}
}