{
  "type": "Feature",
  "properties": {
    "iso:country":"CH",
    "sg:address":"S\u00fcls 21",
    "sg:city":"Selzach",
    "sg:orig_category":"Verwertung von Milch",
    "sg:postcode":"2545",
    "sg:province":"Solothurn",
    "wof:name":"Milchverwertungsgenossenschaft Hasliberg",
    "wof:placetype":"venue"
},
  "geometry": {"coordinates":[8.2025403976,46.7372512817],"type":"Point"}
}