{
  "type": "Feature",
  "properties": {
    "iso:country":"CH",
    "sg:address":"Stuben 6030 Ebikon. Postfach 12",
    "sg:city":"Ebikon",
    "sg:orig_category":"Schiffs U Bootsbau",
    "sg:phone":"+41 79 250 57 75",
    "sg:postcode":"6030",
    "sg:province":"Luzern",
    "wof:name":"Vincent-louis Blanco R\u00e9paration De Bateaux",
    "wof:placetype":"venue"
},
  "geometry": {"coordinates":[6.9365301132,46.991191864],"type":"Point"}
}