{
  "type": "Feature",
  "properties": {
    "iso:country":"CH",
    "sg:address":"Forchstrasse 10",
    "sg:city":"Uster",
    "sg:orig_category":"Maler U Glasergewerbe Malerei",
    "sg:phone":"+41 19402197",
    "sg:postcode":"8610",
    "sg:province":"Z\u00fcrich",
    "wof:name":"B\u00fchlmann A. + Partner Ag",
    "wof:placetype":"venue"
},
  "geometry": {"coordinates":[8.7124300003,47.3473396301],"type":"Point"}
}