{
  "type": "Feature",
  "properties": {
    "iso:country":"CH",
    "sg:address":"La Bergerie Route De Suisse 1196 Gland. Postfach",
    "sg:city":"Gland",
    "sg:orig_category":"Architektur U Ingenieurb\u00fcros",
    "sg:postcode":"1196",
    "sg:province":"Vaud",
    "wof:name":"Les Deux Rivi\u00e8res (verbier) Sa Projets, Construction De B\u00e2timents Etc",
    "wof:placetype":"venue"
},
  "geometry": {"coordinates":[6.26145,46.422401],"type":"Point"}
}