{
  "type": "Feature",
  "properties": {
    "iso:country":"CH",
    "sg:address":"Wettsteinallee 123 4058 Basel. Postfach",
    "sg:city":"Basel",
    "sg:orig_category":"Sanit\u00e4r, Heizungs U L\u00fcftungsinstallation",
    "sg:phone":"+41 61 691 19 73",
    "sg:postcode":"4058",
    "sg:province":"Basel-Stadt",
    "wof:name":"Steinegger Service \u00d6l-u. Gasheizungen; Installationen, Service. Boilerentkalkungen",
    "wof:placetype":"venue"
},
  "geometry": {"coordinates":[7.607448101,47.561630249],"type":"Point"}
}