{
  "type": "Feature",
  "properties": {
    "iso:country":"CH",
    "sg:address":"Eggiwilstrasse 87",
    "sg:city":"Sch\u00fcpbach",
    "sg:orig_category":"Kaminfeger",
    "sg:phone":"+41 34 497 10 88",
    "sg:postcode":"3535",
    "sg:province":"Bern",
    "wof:name":"Alfred Salzmann Kaminfegergesch\u00e4ft",
    "wof:placetype":"venue"
},
  "geometry": {"coordinates":[7.7462701797,46.9219818115],"type":"Point"}
}