{
  "type": "Feature",
  "properties": {
    "iso:country":"CH",
    "sg:address":"Vorstadt 63",
    "sg:city":"Schaffhausen",
    "sg:orig_category":"Interessenvertretungen",
    "sg:phone":"+41 52 672 66 66",
    "sg:postcode":"8200",
    "sg:province":"Schaffhausen",
    "wof:name":"Interessengemeinschaft Altstadt Schaffhausen",
    "wof:placetype":"venue"
},
  "geometry": {"coordinates":[8.6351146698,47.6995506287],"type":"Point"}
}