{
  "type": "Feature",
  "properties": {
    "iso:country":"CH",
    "sg:address":"Str\u00e4hlgasse 64",
    "sg:city":"Brittnau",
    "sg:orig_category":"Interessenvertretungen",
    "sg:postcode":"4805",
    "sg:province":"Aargau",
    "wof:name":"Friedrich W\u00e4chter-stiftung",
    "wof:placetype":"venue"
},
  "geometry": {"coordinates":[7.948800087,47.2598609924],"type":"Point"}
}