{
  "type": "Feature",
  "properties": {
    "iso:country":"CH",
    "sg:address":"Primev\u00e8res Chemin Des 45 1700 Fribourg. Postfach",
    "sg:city":"Fribourg",
    "sg:orig_category":"Detailhandel mit Bekleidung",
    "sg:phone":"+41 81 420 71 07",
    "sg:postcode":"1700",
    "sg:province":"Fribourg",
    "wof:name":"Babaloo Kids Gmbh",
    "wof:placetype":"venue"
},
  "geometry": {"coordinates":[9.83779,46.806873],"type":"Point"}
}