{
  "type": "Feature",
  "properties": {
    "iso:country":"CH",
    "sg:address":"Satteleggstrasse 8846 Willerzell. Postfach 30",
    "sg:city":"Willerzell",
    "sg:classifiers":[
        {
            "category":"Restaurant",
            "type":"Food & Drink"
        }
    ],
    "sg:phone":"+41 55 412 51 55",
    "sg:postcode":"8846",
    "sg:province":"Schwyz",
    "wof:name":"Bergrestaurant Sattelegg",
    "wof:placetype":"venue"
},
  "geometry": {"coordinates":[8.7952651978,47.129863739],"type":"Point"}
}