{
  "type": "Feature",
  "properties": {
    "iso:country":"CH",
    "sg:address":"Stafflerstrasse 20b",
    "sg:city":"Hermetschwil-staff",
    "sg:orig_category":"Berufliche Weiterbildung, Erwachsenenbildung",
    "sg:phone":"+41 56 631 70 80",
    "sg:postcode":"5626",
    "sg:province":"Aargau",
    "wof:name":"Volkshochschule Wohlen",
    "wof:placetype":"venue"
},
  "geometry": {"coordinates":[8.339659,47.33197],"type":"Point"}
}