{
  "type": "Feature",
  "properties": {
    "iso:country":"CH",
    "sg:address":"Gerbegasse 10",
    "sg:city":"Kloten",
    "sg:orig_category":"Fachdetailhandel mit pharmazeutischen Produkten",
    "sg:phone":"+41 18135151",
    "sg:postcode":"8302",
    "sg:province":"Z\u00fcrich",
    "wof:name":"Gerbegasse-apotheke, B\u00fchrer Silvia",
    "wof:placetype":"venue"
},
  "geometry": {"coordinates":[8.5816507339,47.452747345],"type":"Point"}
}