{
  "type": "Feature",
  "properties": {
    "iso:country":"CH",
    "sg:address":"Marais Chemin Du 8",
    "sg:city":"Romanel-s-lausanne",
    "sg:orig_category":"Herstellung von Teppichen",
    "sg:postcode":"1032",
    "sg:province":"Vaud",
    "wof:name":"Jud R., Teppich Und Bodenbel\u00e4ge",
    "wof:placetype":"venue"
},
  "geometry": {"coordinates":[8.8084897995,47.3316688538],"type":"Point"}
}