{
  "type": "Feature",
  "properties": {
    "iso:country":"CH",
    "sg:address":"Rue Aim\u00e9 Charpilloz 4",
    "sg:city":"B\u00e9vilard",
    "sg:orig_category":"Architektur U Ingenieurb\u00fcros Architekturb\u00fcros",
    "sg:phone":"+41 32 492 22 11",
    "sg:postcode":"2735",
    "sg:province":"Bern",
    "wof:name":"M.-h. Heimann Sa Bureau D'architecture",
    "wof:placetype":"venue"
},
  "geometry": {"coordinates":[7.284268,47.236889],"type":"Point"}
}