{
  "type": "Feature",
  "properties": {
    "iso:country":"CH",
    "sg:address":"Glendweg 184",
    "sg:city":"Schellenberg",
    "sg:orig_category":"Verlegen von Fliesen U Platten",
    "sg:phone":"+423 373 35 83",
    "sg:postcode":"9488",
    "wof:name":"Hans M\u00fcller Est. Keramische Wand-& Bodenbel\u00e4ge",
    "wof:placetype":"venue"
},
  "geometry": {"coordinates":[9.5410852432,47.2306213379],"type":"Point"}
}