{
  "type": "Feature",
  "properties": {
    "iso:country":"CH",
    "sg:address":"Gigering 67",
    "sg:city":"Neunkirch",
    "sg:orig_category":"Handelsvermittlung von Brennstoffen, Erzen, Metallen U Chemikalien",
    "sg:phone":"+41 52 681 32 21",
    "sg:postcode":"8213",
    "sg:province":"Schaffhausen",
    "wof:name":"Masayoshi Nakamura, Eis- & Konditoreirohstoffe",
    "wof:placetype":"venue"
},
  "geometry": {"coordinates":[8.4929361343,47.686466217],"type":"Point"}
}