{
  "type": "Feature",
  "properties": {
    "iso:country":"CH",
    "sg:address":"Rue De La Gare",
    "sg:city":"Pal\u00e9zieux-gare",
    "sg:orig_category":"Architekturb\u00fcros",
    "sg:phone":"+41 21 907 92 13",
    "sg:postcode":"1607",
    "sg:province":"Vaud",
    "wof:name":"Jacques Amiquet Bureau D'architecture",
    "wof:placetype":"venue"
},
  "geometry": {"coordinates":[6.837913,46.542622],"type":"Point"}
}