{
  "type": "Feature",
  "properties": {
    "iso:country":"CH",
    "sg:address":"Oberer Festiweg 23",
    "sg:city":"Ligerz",
    "sg:orig_category":"Malerei",
    "sg:phone":"+41 32 315 15 55",
    "sg:postcode":"2514",
    "sg:province":"Bern",
    "wof:name":"Edi Martin Malergesch\u00e4ft",
    "wof:placetype":"venue"
},
  "geometry": {"coordinates":[7.1366682053,47.0900917053],"type":"Point"}
}