{
  "type": "Feature",
  "properties": {
    "iso:country":"CH",
    "sg:address":"Chemin Des Bourdons 7",
    "sg:city":"Evilard",
    "sg:orig_category":"Herstellung von sonstigen Maschinen f\u00fcr unspezifische Verwendung",
    "sg:postcode":"2533",
    "sg:province":"Bern",
    "wof:name":"Tp Hartmann Ag Hartmann Packaging",
    "wof:placetype":"venue"
},
  "geometry": {"coordinates":[7.2383542061,47.1524467468],"type":"Point"}
}