{
  "type": "Feature",
  "properties": {
    "iso:country":"CH",
    "sg:address":"Z\u00fcrcherstrasse 115",
    "sg:city":"Neuenhof",
    "sg:orig_category":"Grosshandel mit sonstigen Gebrauchs U Verbrauchsg\u00fctern",
    "sg:postcode":"5432",
    "sg:province":"Aargau",
    "wof:name":"Vessaz Roland",
    "wof:placetype":"venue"
},
  "geometry": {"coordinates":[6.5847787857,46.5399398804],"type":"Point"}
}