{
  "type": "Feature",
  "properties": {
    "iso:country":"CH",
    "sg:address":"Emmentalstrasse 15",
    "sg:city":"Konolfingen",
    "sg:orig_category":"B\u00e4ckereien Konditoreien",
    "sg:phone":"+41 71 311 24 32",
    "sg:postcode":"3510",
    "sg:province":"Bern",
    "wof:name":"H. & M. Gm\u00fcr B\u00e4ckerei-konditorei",
    "wof:placetype":"venue"
},
  "geometry": {"coordinates":[9.318016,47.421703],"type":"Point"}
}