{
  "type": "Feature",
  "properties": {
    "iso:country":"CH",
    "sg:address":"Kohlbruck 1",
    "sg:city":"Balzers",
    "sg:orig_category":"Bauingenieurb\u00fcros Heizung L\u00fcftung Klima",
    "sg:phone":"+423 384 12 22",
    "sg:postcode":"9496",
    "wof:name":"Karl Kaufmann Ingenieurb\u00fcro",
    "wof:placetype":"venue"
},
  "geometry": {"coordinates":[9.501349,47.070377],"type":"Point"}
}