{
  "type": "Feature",
  "properties": {
    "iso:country":"CH",
    "sg:address":"Rue De La Poste 9",
    "sg:city":"Echallens",
    "sg:orig_category":"Detailhandel mit B\u00fcchern",
    "sg:phone":"+41 21 881 51 00",
    "sg:postcode":"1040",
    "sg:province":"Vaud",
    "wof:name":"Colette Micello Librairie A La Page",
    "wof:placetype":"venue"
},
  "geometry": {"coordinates":[6.635937,46.641014],"type":"Point"}
}