{
  "type": "Feature",
  "properties": {
    "iso:country":"CH",
    "sg:address":"Riedstrasse 7",
    "sg:city":"Dietikon",
    "sg:classifiers":[
        {
            "category":"Professional",
            "subcategory":"Accounting & Tax Preparation",
            "type":"Services"
        }
    ],
    "sg:phone":"+41 41 921 90 19",
    "sg:postcode":"8953",
    "sg:province":"Z\u00fcrich",
    "sg:tags":[
        "book-keeping"
    ],
    "wof:name":"Comatic Ag",
    "wof:placetype":"venue"
},
  "geometry": {"coordinates":[8.07447,47.182919],"type":"Point"}
}