{
  "type": "Feature",
  "properties": {
    "iso:country":"CH",
    "sg:address":"Mittelg\u00e4ssli",
    "sg:city":"Saanen",
    "sg:orig_category":"Betrieb von Taxis",
    "sg:phone":"+41 33 744 99 90",
    "sg:postcode":"3792",
    "sg:province":"Bern",
    "wof:name":"Josef Prinz Taxi",
    "wof:placetype":"venue"
},
  "geometry": {"coordinates":[7.259483,46.488831],"type":"Point"}
}