{
  "type": "Feature",
  "properties": {
    "addr:full":"Muristrasse 18 Bern Bern 3006",
    "addr:housenumber":"18",
    "addr:postcode":"3006",
    "addr:street":"Muristrasse",
    "iso:country":"CH",
    "sg:address":"Muristrasse 18",
    "sg:city":"Bern",
    "sg:orig_category":"Arztpraxen",
    "sg:phone":"+41 31 337 60 00",
    "sg:postcode":"3006",
    "sg:province":"Bern",
    "wof:name":"Dr.med.hans Peter Burki Spezialarzt Fmh",
    "wof:placetype":"venue"
},
  "geometry": {"coordinates":[7.461528,46.944351],"type":"Point"}
}