{
  "type": "Feature",
  "properties": {
    "iso:country":"CH",
    "sg:address":"Kalkofenstrasse 17",
    "sg:city":"Horgen",
    "sg:orig_category":"Geb\u00e4ude, Wohnungsreinigung Reinigungsgewerbe",
    "sg:phone":"+41 17260016",
    "sg:postcode":"8810",
    "sg:province":"Z\u00fcrich",
    "wof:name":"W\u00e4lchli Reinigungen Gmbh",
    "wof:placetype":"venue"
},
  "geometry": {"coordinates":[8.6079397202,47.2464637756],"type":"Point"}
}