{
  "type": "Feature",
  "properties": {
    "iso:country":"CH",
    "sg:address":"Eichbergstrasse 35",
    "sg:city":"Eichberg",
    "sg:orig_category":"Technische B\u00fcros Hoch-& Tiefbau",
    "sg:phone":"+41 71 755 31 19",
    "sg:postcode":"9453",
    "sg:province":"St. Gallen",
    "wof:name":"Fritz Laich Planungsb\u00fcro",
    "wof:placetype":"venue"
},
  "geometry": {"coordinates":[9.5322294235,47.3439369202],"type":"Point"}
}