{
  "type": "Feature",
  "properties": {
    "iso:country":"CH",
    "sg:address":"Luzernerstrasse 25c",
    "sg:city":"Ebikon",
    "sg:orig_category":"Physiotherapie",
    "sg:phone":"+41 41 440 60 88",
    "sg:postcode":"6030",
    "sg:province":"Luzern",
    "wof:name":"Physiotherapie Schmiedhof",
    "wof:placetype":"venue"
},
  "geometry": {"coordinates":[8.3324804306,47.0765609741],"type":"Point"}
}