{
  "type": "Feature",
  "properties": {
    "iso:country":"CH",
    "sg:address":"Fiechtenhof 6154 Hofstatt. Postfach",
    "sg:city":"Hofstatt",
    "sg:orig_category":"Gewinnung von Kies U Sand",
    "sg:postcode":"6154",
    "sg:province":"Luzern",
    "wof:name":"Napf Kies Ag",
    "wof:placetype":"venue"
},
  "geometry": {"coordinates":[7.9148750305,47.0844955444],"type":"Point"}
}