{
  "type": "Feature",
  "properties": {
    "addr:full":"Stadtturmstrasse 20 Baden Aargau 5400",
    "addr:housenumber":"20",
    "addr:postcode":"5400",
    "addr:street":"Stadtturmstrasse",
    "iso:country":"CH",
    "sg:address":"Stadtturmstrasse 20",
    "sg:city":"Baden",
    "sg:orig_category":"Detailhandel mit Blumen U Pflanzen Fachdetailhandel in Verkaufsr\u00e4umen",
    "sg:phone":"+41 56 221 80 63",
    "sg:postcode":"5400",
    "sg:province":"Aargau",
    "wof:name":"Blumen - Kunst - Design, Haller Doris",
    "wof:placetype":"venue"
},
  "geometry": {"coordinates":[8.305217,47.476566],"type":"Point"}
}