{
  "type": "Feature",
  "properties": {
    "iso:country":"CH",
    "sg:address":"Rosenb\u00fchlstrasse 37",
    "sg:city":"Z\u00fcrich",
    "sg:orig_category":"Betrieb von Taxis",
    "sg:phone":"+41 79 624 10 71",
    "sg:postcode":"8044",
    "sg:province":"Z\u00fcrich",
    "wof:name":"Hubert Pannatier Taxis",
    "wof:placetype":"venue"
},
  "geometry": {"coordinates":[6.125059,46.232517],"type":"Point"}
}