{
  "type": "Feature",
  "properties": {
    "iso:country":"CH",
    "sg:address":"R\u00e4bacher 7",
    "sg:city":"Bettlach",
    "sg:orig_category":"Zahntechnische Laboratorien",
    "sg:phone":"+41 32 645 36 38",
    "sg:postcode":"2544",
    "sg:province":"Solothurn",
    "wof:name":"Hans Peter Suter Zahntechnisches Labor",
    "wof:placetype":"venue"
},
  "geometry": {"coordinates":[7.4243788719,47.207611084],"type":"Point"}
}