{
  "type": "Feature",
  "properties": {
    "iso:country":"CH",
    "sg:address":"Zugerstrasse 51 6340 Baar. Postfach",
    "sg:city":"Baar",
    "sg:orig_category":"Reinigungsgewerbe",
    "sg:postcode":"6340",
    "sg:province":"Zug",
    "wof:name":"Th Hauswartungen, Bozhajaj I.",
    "wof:placetype":"venue"
},
  "geometry": {"coordinates":[8.5210142136,47.1861839294],"type":"Point"}
}