{
  "type": "Feature",
  "properties": {
    "iso:country":"CH",
    "sg:address":"Bahnhofstrasse 30",
    "sg:city":"Wolhusen",
    "sg:orig_category":"Vermittlung von Immobilien Wirtschaftspr\u00fcfung, Steuerberatung U Treuhand",
    "sg:phone":"+41 79 456 57 50",
    "sg:postcode":"6110",
    "sg:province":"Luzern",
    "wof:name":"B\u00fchlmann Treuhand Ag",
    "wof:placetype":"venue"
},
  "geometry": {"coordinates":[8.075633049,47.0571556091],"type":"Point"}
}