{
  "type": "Feature",
  "properties": {
    "iso:country":"CH",
    "sg:address":"Prayoud Route De 106 1618 Ch\u00e2tel-st-denis. Postfach",
    "sg:city":"Ch\u00e2tel-st-denis",
    "sg:orig_category":"Elektroinstallation",
    "sg:postcode":"1618",
    "sg:province":"Fribourg",
    "wof:name":"Cordonier Electricit\u00e9 S\u00e0rl Entreprise De Fournitures, D'installations \u00e9lectriques, T\u00e9l\u00e9phoniques Etc",
    "wof:placetype":"venue"
},
  "geometry": {"coordinates":[6.8834300041,46.4704742432],"type":"Point"}
}