{
  "type": "Feature",
  "properties": {
    "iso:country":"CH",
    "sg:address":"Technologiestrasse 11",
    "sg:city":"Winterthur",
    "sg:orig_category":"Aircraft Parts, Components, Modules, And Construction Supplies",
    "sg:phone":"+41 71 744 44 62",
    "sg:postcode":"8404",
    "sg:province":"Z\u00fcrich",
    "wof:name":"F. Kriftner Konstruktionsb\u00fcro",
    "wof:placetype":"venue"
},
  "geometry": {"coordinates":[9.629172,47.453259],"type":"Point"}
}