{
  "type": "Feature",
  "properties": {
    "iso:country":"CH",
    "sg:address":"Chemin Des Villarets 16a",
    "sg:city":"Cormondr\u00e8che",
    "sg:orig_category":"Wirtschaftspr\u00fcfung, Steuerberatung U Treuhand",
    "sg:phone":"+41 32 730 40 20",
    "sg:postcode":"2036",
    "sg:province":"Neuch\u00e2tel",
    "wof:name":"Mcp Management, Conseils & Promotion Sa",
    "wof:placetype":"venue"
},
  "geometry": {"coordinates":[6.8626999855,46.9821510315],"type":"Point"}
}