{
  "type": "Feature",
  "properties": {
    "iso:country":"CH",
    "sg:address":"Schluckmattstrasse 4",
    "sg:city":"Itingen",
    "sg:classifiers":[
        {
            "category":"Education",
            "subcategory":"Library",
            "type":"Public Place"
        }
    ],
    "sg:phone":"+41 61 971 25 25",
    "sg:postcode":"4452",
    "sg:province":"Basel-Landschaft",
    "sg:tags":[
        "u",
        "bibliotheken",
        "archive"
    ],
    "wof:name":"Jugend-& Volksbibliothek Herrn Karl Jost",
    "wof:placetype":"venue"
},
  "geometry": {"coordinates":[7.78363,47.464001],"type":"Point"}
}