{
  "type": "Feature",
  "properties": {
    "iso:country":"CH",
    "sg:address":"Waldeggstrasse 27",
    "sg:city":"Liebefeld",
    "sg:orig_category":"Oberfl\u00e4chenveredlung U W\u00e4rmebehandlung",
    "sg:phone":"+41 31 971 46 72",
    "sg:postcode":"3097",
    "sg:province":"Bern",
    "wof:name":"Emaillierwerk Ag Liebefeld",
    "wof:placetype":"venue"
},
  "geometry": {"coordinates":[7.4199838638,46.9331436157],"type":"Point"}
}