{
  "type": "Feature",
  "properties": {
    "iso:country":"CH",
    "sg:address":"Thorenbergbr\u00fccke",
    "sg:city":"Littau",
    "sg:orig_category":"Unclassifiable Establishments",
    "sg:postcode":"6014",
    "sg:province":"Luzern",
    "wof:name":"Hess Fenster Ag",
    "wof:placetype":"venue"
},
  "geometry": {"coordinates":[8.2537183762,47.0546836853],"type":"Point"}
}