{
  "type": "Feature",
  "properties": {
    "iso:country":"CH",
    "sg:address":"Schwarzseestrasse 12",
    "sg:city":"Tafers",
    "sg:orig_category":"Elektroinstallation",
    "sg:phone":"+41 26 494 10 10",
    "sg:postcode":"1712",
    "sg:province":"Fribourg",
    "wof:name":"Hertli & Bertschy Ag",
    "wof:placetype":"venue"
},
  "geometry": {"coordinates":[7.2157878876,46.8133583069],"type":"Point"}
}