{
  "type": "Feature",
  "properties": {
    "iso:country":"CH",
    "sg:address":"Via Pietro Peri 4",
    "sg:city":"Lugano",
    "sg:orig_category":"Massagestudios",
    "sg:phone":"+41 91 922 09 07",
    "sg:postcode":"6900",
    "sg:province":"Ticino",
    "wof:name":"Centro Aldebaran Massaggi",
    "wof:placetype":"venue"
},
  "geometry": {"coordinates":[8.9509334564,46.0054359436],"type":"Point"}
}