{
  "type": "Feature",
  "properties": {
    "iso:country":"CH",
    "sg:address":"Amstutzstrasse 3a",
    "sg:city":"Kriens",
    "sg:orig_category":"Architektur U Ingenieurb\u00fcros Architekturb\u00fcros",
    "sg:phone":"+41 41 342 09 79",
    "sg:postcode":"6010",
    "sg:province":"Luzern",
    "wof:name":"Schnieper + Keller Architekten",
    "wof:placetype":"venue"
},
  "geometry": {"coordinates":[8.290996,47.037853],"type":"Point"}
}