{
  "type": "Feature",
  "properties": {
    "iso:country":"CH",
    "sg:address":"Schmiedengasse 19",
    "sg:city":"Burgdorf",
    "sg:orig_category":"Detailhandel mit Schuhen U Lederwaren",
    "sg:phone":"+41 34 422 13 19",
    "sg:postcode":"3400",
    "sg:province":"Bern",
    "wof:name":"Wyss Lederwaren Gmbh",
    "wof:placetype":"venue"
},
  "geometry": {"coordinates":[7.6256427765,47.0554084778],"type":"Point"}
}