{
  "type": "Feature",
  "properties": {
    "iso:country":"CH",
    "sg:address":"Churfirstenstrasse 54",
    "sg:city":"Wil",
    "sg:classifiers":[
        {
            "category":"Professional",
            "subcategory":"Management & Consulting",
            "type":"Services"
        }
    ],
    "sg:phone":"+41 71 912 31 32",
    "sg:postcode":"9500",
    "sg:province":"St. Gallen",
    "sg:tags":[
        "seminar"
    ],
    "wof:name":"Erfolgs Impuls",
    "wof:placetype":"venue"
},
  "geometry": {"coordinates":[9.0469903946,47.4559783936],"type":"Point"}
}