{
  "type": "Feature",
  "properties": {
    "iso:country":"CH",
    "sg:address":"Rainstrasse 7",
    "sg:city":"Oetwil",
    "sg:orig_category":"Sportvereine Sch\u00fctzen Pistolen-& Gewehr",
    "sg:phone":"+41 17482085",
    "sg:postcode":"8955",
    "sg:province":"Z\u00fcrich",
    "wof:name":"Feldsch\u00fctzenv.o'engstringen",
    "wof:placetype":"venue"
},
  "geometry": {"coordinates":[8.3990478516,47.4284133911],"type":"Point"}
}