{
  "type": "Feature",
  "properties": {
    "iso:country":"CH",
    "sg:address":"Dahliastrasse 8",
    "sg:city":"Z\u00fcrich",
    "sg:orig_category":"Sonstiger Grosshandel",
    "sg:postcode":"8008",
    "sg:province":"Z\u00fcrich",
    "wof:name":"Import-export - Liava M.",
    "wof:placetype":"venue"
},
  "geometry": {"coordinates":[8.5539178848,47.3568954468],"type":"Point"}
}