{
  "type": "Feature",
  "properties": {
    "iso:country":"CH",
    "sg:address":"Scheidbach",
    "sg:city":"Turbach",
    "sg:orig_category":"Dienstleistungen in der Forstwirtschaft Forstwirtschaft ohne Dienstleistungen in der Forstwirtschaft",
    "sg:phone":"+41 33 744 50 78",
    "sg:postcode":"3781",
    "sg:province":"Bern",
    "wof:name":"Ueli Hefti Gmbh Forstuntern.& Holztransporte",
    "wof:placetype":"venue"
},
  "geometry": {"coordinates":[7.3304600716,46.4784355164],"type":"Point"}
}