{
  "type": "Feature",
  "properties": {
    "iso:country":"CH",
    "sg:address":"Bernastrasse 4",
    "sg:city":"Interlaken",
    "sg:orig_category":"RESTAURANTS: TEA-ROOMS",
    "sg:postcode":"3800",
    "sg:province":"Bern",
    "wof:name":"Antikschreinerei Gn\u00e4gi",
    "wof:placetype":"venue"
},
  "geometry": {"coordinates":[7.8527178764,46.6820755005],"type":"Point"}
}