{
  "type": "Feature",
  "properties": {
    "iso:country":"CH",
    "sg:address":"1846",
    "sg:city":"Chessel",
    "sg:orig_category":"Primarschulen",
    "sg:phone":"+41 26 915 27 16",
    "sg:postcode":"1846",
    "sg:province":"Vaud",
    "wof:name":"Ecole Primaire",
    "wof:placetype":"venue"
},
  "geometry": {"coordinates":[6.8965501785,46.3527793884],"type":"Point"}
}