{
  "type": "Feature",
  "properties": {
    "iso:country":"CH",
    "sg:address":"Avenue De Lavaux 35",
    "sg:city":"Pully",
    "sg:orig_category":"Zahnarztpraxen",
    "sg:phone":"+41 21 728 05 55",
    "sg:postcode":"1009",
    "sg:province":"Vaud",
    "wof:name":"Dr M\u00e9d. Dent. Yves Revaz M\u00e9decin-dentiste",
    "wof:placetype":"venue"
},
  "geometry": {"coordinates":[6.6586899757,46.5125389099],"type":"Point"}
}