{
  "type": "Feature",
  "properties": {
    "iso:country":"CH",
    "sg:address":"Chemin De M\u00e9zery 2",
    "sg:city":"Jouxtens-m\u00e9zery",
    "sg:orig_category":"Unternehmensberatung Werbung",
    "sg:phone":"+41 21 634 34 68",
    "sg:postcode":"1008",
    "sg:province":"Vaud",
    "wof:name":"Advimark Sa",
    "wof:placetype":"venue"
},
  "geometry": {"coordinates":[6.5979390144,46.5547027588],"type":"Point"}
}