{
  "type": "Feature",
  "properties": {
    "iso:country":"CH",
    "sg:address":"K\u00e4giswilerstrasse",
    "sg:city":"Sarnen",
    "sg:orig_category":"Herstellung von sonstigen Nahrungsmitteln",
    "sg:postcode":"6060",
    "sg:province":"Obwalden",
    "wof:name":"Arnold Bruno",
    "wof:placetype":"venue"
},
  "geometry": {"coordinates":[8.2587308884,46.9083213806],"type":"Point"}
}