{
  "type": "Feature",
  "properties": {
    "iso:country":"CH",
    "sg:address":"L\u00f6wenstrasse 21",
    "sg:city":"Dietikon",
    "sg:orig_category":"Unternehmensberatung",
    "sg:phone":"+41 56 451 10 55",
    "sg:postcode":"8953",
    "sg:province":"Z\u00fcrich",
    "wof:name":"Schneider B. & Partner Gmbh",
    "wof:placetype":"venue"
},
  "geometry": {"coordinates":[8.2068004608,47.4854507446],"type":"Point"}
}