{
  "type": "Feature",
  "properties": {
    "iso:country":"CH",
    "sg:address":"5645",
    "sg:city":"Aettenschwil",
    "sg:orig_category":"Schulpflegen",
    "sg:phone":"+41 79 356 75 71",
    "sg:postcode":"5645",
    "sg:province":"Aargau",
    "wof:name":"Primarschulpflege Der Gemeinde Aeugst Am Albis",
    "wof:placetype":"venue"
},
  "geometry": {"coordinates":[8.4854745865,47.2676887512],"type":"Point"}
}