{
  "type": "Feature",
  "properties": {
    "iso:country":"CH",
    "sg:address":"Lindenhof 8",
    "sg:city":"Wettingen",
    "sg:orig_category":"Herstellung von elektronischen Bauelementen",
    "sg:phone":"+41 56 426 75 83",
    "sg:postcode":"5430",
    "sg:province":"Aargau",
    "wof:name":"Electronics Bures Zdenka",
    "wof:placetype":"venue"
},
  "geometry": {"coordinates":[8.3203220367,47.4645805359],"type":"Point"}
}