{
  "type": "Feature",
  "properties": {
    "iso:country":"CH",
    "sg:address":"B\u00e4ndlistrasse 58",
    "sg:city":"Z\u00fcrich",
    "sg:orig_category":"G\u00fcterbef\u00f6rderung im Strassenverkehr",
    "sg:postcode":"8064",
    "sg:province":"Z\u00fcrich",
    "wof:name":"Sturgeon Schnell-industrie-transport Gmbh",
    "wof:placetype":"venue"
},
  "geometry": {"coordinates":[8.4842739105,47.3967475891],"type":"Point"}
}