{
  "type": "Feature",
  "properties": {
    "iso:country":"CH",
    "sg:address":"Hardstrasse 8",
    "sg:city":"Volketswil",
    "sg:orig_category":"Bauspenglerei Zimmerei, Dachdeckerei, Bauspenglerei U Abdichtung",
    "sg:phone":"+41 19454550",
    "sg:postcode":"8604",
    "sg:province":"Z\u00fcrich",
    "wof:name":"Schneebeli Spenglerei Und Installationen Ag",
    "wof:placetype":"venue"
},
  "geometry": {"coordinates":[8.691811,47.387737],"type":"Point"}
}