{
  "type": "Feature",
  "properties": {
    "iso:country":"CH",
    "sg:address":"Staffelenweg 16 4460 Gelterkinden. Postfach",
    "sg:city":"Gelterkinden",
    "sg:orig_category":"Unclassifiable Establishments",
    "sg:phone":"+41 61 981 26 38",
    "sg:postcode":"4460",
    "sg:province":"Basel-Landschaft",
    "wof:name":"Gartenbau G\u00fcl & Schnitzler",
    "wof:placetype":"venue"
},
  "geometry": {"coordinates":[7.851170063,47.4689674377],"type":"Point"}
}