{
  "type": "Feature",
  "properties": {
    "iso:country":"CH",
    "sg:address":"9565",
    "sg:city":"Bussnang",
    "sg:orig_category":"Schulpflegen",
    "sg:postcode":"9565",
    "sg:province":"Thurgau",
    "wof:name":"Primarschulkommission Der Gemeinde Busswil Bei B\u00fcren",
    "wof:placetype":"venue"
},
  "geometry": {"coordinates":[7.3292989731,47.0991363525],"type":"Point"}
}