{
  "type": "Feature",
  "properties": {
    "iso:country":"CH",
    "sg:address":"Moulin-du-choc 1122 Romanel-sur-morges. Postfach",
    "sg:city":"Romanel-sur-morges",
    "sg:orig_category":"Detailhandel mit Metallwaren, Anstrichmitteln, Glaswaren, Bau U Heimwerkerbedarf",
    "sg:phone":"+41 21 869 90 33",
    "sg:postcode":"1122",
    "sg:province":"Vaud",
    "wof:name":"L. O. T.-oriel (suisse) S\u00e0rl Produits Techniques; D\u00e9velopp., Fabrication, Commerce",
    "wof:placetype":"venue"
},
  "geometry": {"coordinates":[6.5264410973,46.561340332],"type":"Point"}
}