{
  "type": "Feature",
  "properties": {
    "iso:country":"CH",
    "sg:address":"Chemin Du Grand'clos 1",
    "sg:city":"Vouvry",
    "sg:orig_category":"Detailhandel mit Waren verschiedener Art, Hauptrichtung Nahrungsmittel",
    "sg:phone":"+41 24 481 52 66",
    "sg:postcode":"1896",
    "sg:province":"Valais",
    "wof:name":"Coop Vaud Chablais Valaisan",
    "wof:placetype":"venue"
},
  "geometry": {"coordinates":[6.8874511719,46.3340797424],"type":"Point"}
}