{
  "type": "Feature",
  "properties": {
    "iso:country":"CH",
    "sg:address":"Bruggereggstrasse 16",
    "sg:city":"Herisau",
    "sg:orig_category":"Vereine Haus- and Grundeigent\u00fcmer",
    "sg:phone":"+41 71 351 71 54",
    "sg:postcode":"9100",
    "sg:province":"Appenzell Ausserrhoden",
    "wof:name":"Hauseigent\u00fcmerverband Ar",
    "wof:placetype":"venue"
},
  "geometry": {"coordinates":[9.2654714584,47.3778915405],"type":"Point"}
}