{
  "type": "Feature",
  "properties": {
    "iso:country":"CH",
    "sg:address":"Kreuzbuchstrasse 27 6006 Luzern. Postfach",
    "sg:city":"Luzern",
    "sg:orig_category":"Erbringung von Dienstleistungen f\u00fcr Unternehmen",
    "sg:postcode":"6003",
    "sg:province":"Luzern",
    "wof:name":"Messenorganisation Luzern Koch Josef Messenorganisationen, Ausstellungs- U. Standbau",
    "wof:placetype":"venue"
},
  "geometry": {"coordinates":[8.332654953,47.0549125671],"type":"Point"}
}