{
  "type": "Feature",
  "properties": {
    "iso:country":"CH",
    "sg:address":"Bireggstrasse 31",
    "sg:city":"Luzern",
    "sg:orig_category":"Sonstige mit der Informatik verbundene T\u00e4tigkeiten",
    "sg:phone":"+41 41 311 05 30",
    "sg:postcode":"6003",
    "sg:province":"Luzern",
    "wof:name":"Cps Gmbh",
    "wof:placetype":"venue"
},
  "geometry": {"coordinates":[8.3068037033,47.0417404175],"type":"Point"}
}