{
  "type": "Feature",
  "properties": {
    "iso:country":"CH",
    "sg:address":"Schulstrasse 48",
    "sg:city":"Schlieren",
    "sg:orig_category":"Gesundheitswesen Verwaltung im Bereich des Gesundheitswesens, der Bildung, der Kultur, des Sports U ",
    "sg:phone":"+41 17308131",
    "sg:postcode":"8952",
    "sg:province":"Z\u00fcrich",
    "wof:name":"Schwimmbad Im Moos Stadtverwaltung",
    "wof:placetype":"venue"
},
  "geometry": {"coordinates":[8.4573631287,47.396987915],"type":"Point"}
}