{
  "type": "Feature",
  "properties": {
    "iso:country":"CH",
    "sg:address":"Cotterd",
    "sg:city":"Salavaux",
    "sg:classifiers":[
        {
            "category":"Restaurant",
            "type":"Food & Drink"
        }
    ],
    "sg:phone":"+41 26 677 13 14",
    "sg:postcode":"1585",
    "sg:province":"Vaud",
    "wof:name":"Caf\u00e9 Vignerons",
    "wof:placetype":"venue"
},
  "geometry": {"coordinates":[7.0202159882,46.9188575745],"type":"Point"}
}