{
  "type": "Feature",
  "properties": {
    "addr:full":"Route Du Nant-d'avril 12 Vernier Gen\u00e8ve 1214",
    "addr:housenumber":"12",
    "addr:postcode":"1214",
    "addr:street":"Route Du Nant-D'Avril",
    "iso:country":"CH",
    "sg:address":"Route Du Nant-d'avril 12",
    "sg:city":"Vernier",
    "sg:orig_category":"Bauschreinerei Herstellung von M\u00f6beln verschiedener Art",
    "sg:phone":"+41 22 341 37 16",
    "sg:postcode":"1214",
    "sg:province":"Gen\u00e8ve",
    "wof:name":"Meyer Charles Eug\u00e8ne, Menuiserie-eb\u00e9nisterie",
    "wof:placetype":"venue"
},
  "geometry": {"coordinates":[6.08047,46.212341],"type":"Point"}
}