{
  "type": "Feature",
  "properties": {
    "iso:country":"CH",
    "sg:address":"1963",
    "sg:city":"V\u00e9troz",
    "sg:orig_category":"Haltung von Rindern",
    "sg:postcode":"1963",
    "sg:province":"Valais",
    "wof:name":"Etable Communautaire La Goletaz",
    "wof:placetype":"venue"
},
  "geometry": {"coordinates":[7.3364601135,46.1857681274],"type":"Point"}
}