{
  "type": "Feature",
  "properties": {
    "iso:country":"CH",
    "sg:address":"Waisenhausstrasse 8",
    "sg:city":"Solothurn",
    "sg:classifiers":[
        {
            "category":"Education",
            "subcategory":"Vocational School",
            "type":"Public Place"
        }
    ],
    "sg:phone":"+41 32 622 93 80",
    "sg:postcode":"4500",
    "sg:province":"Solothurn",
    "sg:tags":[
        "koch-",
        "haushaltschulen"
    ],
    "wof:name":"Kant. Hauswirtschaftsschule",
    "wof:placetype":"venue"
},
  "geometry": {"coordinates":[7.531692028,47.218624115],"type":"Point"}
}