{
  "type": "Feature",
  "properties": {
    "iso:country":"CH",
    "sg:address":"Gotthardstrasse 88",
    "sg:city":"Erstfeld",
    "sg:orig_category":"Betrieb von Taxis",
    "sg:postcode":"6472",
    "sg:province":"Uri",
    "wof:name":"Alpen-taxi",
    "wof:placetype":"venue"
},
  "geometry": {"coordinates":[8.651185,46.820194],"type":"Point"}
}