{
  "type": "Feature",
  "properties": {
    "iso:country":"CH",
    "sg:address":"Neuenburgstrasse 18 2505 Biel/bienne. Postfach",
    "sg:city":"Biel/bienne",
    "sg:orig_category":"RESTAURANTS: TEA-ROOMS",
    "sg:phone":"+41 32 322 59 32",
    "sg:postcode":"2505",
    "sg:province":"Bern",
    "wof:name":"R\u00f6mer Marianne",
    "wof:placetype":"venue"
},
  "geometry": {"coordinates":[7.2238898277,47.1324501038],"type":"Point"}
}