{
  "type": "Feature",
  "properties": {
    "iso:country":"CH",
    "sg:address":"C\u00e4cilienstrasse 21",
    "sg:city":"Bern",
    "sg:orig_category":"Elektroinstallation",
    "sg:phone":"+41 31 371 76 76",
    "sg:postcode":"3007",
    "sg:province":"Bern",
    "wof:name":"Roth Marcel, Elektro & Telefon Elektr. Installationen, Elektr. Apparate U Telefone",
    "wof:placetype":"venue"
},
  "geometry": {"coordinates":[7.4276227951,46.9408493042],"type":"Point"}
}