{
  "type": "Feature",
  "properties": {
    "iso:country":"CH",
    "sg:address":"Ulmenstrasse 14",
    "sg:city":"Luzern",
    "sg:orig_category":"Unclassifiable Establishments",
    "sg:phone":"+41 41 360 34 13",
    "sg:postcode":"6003",
    "sg:province":"Luzern",
    "wof:name":"Imbiss Kostgeberei",
    "wof:placetype":"venue"
},
  "geometry": {"coordinates":[8.3048658371,47.0419502258],"type":"Point"}
}