{
  "type": "Feature",
  "properties": {
    "iso:country":"CH",
    "sg:address":"Tschalunstrasse 11",
    "sg:city":"Oberiberg",
    "sg:orig_category":"G\u00fcterbef\u00f6rderung im Strassenverkehr",
    "sg:phone":"+41 55 414 12 20",
    "sg:postcode":"8843",
    "sg:province":"Schwyz",
    "wof:name":"Albert Holdener Transporte",
    "wof:placetype":"venue"
},
  "geometry": {"coordinates":[8.7808847427,47.0386009216],"type":"Point"}
}