{
  "type": "Feature",
  "properties": {
    "iso:country":"CH",
    "sg:address":"Ferradina Via 4",
    "sg:city":"Giubiasco",
    "sg:orig_category":"Verwaltung von Immobilien",
    "sg:postcode":"6512",
    "sg:province":"Ticino",
    "wof:name":"Tectum Ag",
    "wof:placetype":"venue"
},
  "geometry": {"coordinates":[8.2926168442,47.4872055054],"type":"Point"}
}