{
  "type": "Feature",
  "properties": {
    "iso:country":"CH",
    "sg:address":"Sennhofstrasse 86",
    "sg:city":"Zollikerberg",
    "sg:orig_category":"Bauschreinerei Herstellung von Konstruktionsteilen, Fertigbauteilen U Ausbauelementen aus Holz",
    "sg:phone":"+41 13917740",
    "sg:postcode":"8125",
    "sg:province":"Z\u00fcrich",
    "wof:name":"Greiter Schreinerei Ag",
    "wof:placetype":"venue"
},
  "geometry": {"coordinates":[8.618443,47.344421],"type":"Point"}
}