{
  "type": "Feature",
  "properties": {
    "iso:country":"CH",
    "sg:address":"Effingerstrasse 14",
    "sg:city":"Bern",
    "sg:classifiers":[
        {
            "category":"Restaurant",
            "type":"Food & Drink"
        }
    ],
    "sg:phone":"+41 31 381 18 18",
    "sg:postcode":"3011",
    "sg:province":"Bern",
    "wof:name":"Restaurant-pizzeria Da Carlo",
    "wof:placetype":"venue"
},
  "geometry": {"coordinates":[7.4352369308,46.9460144043],"type":"Point"}
}