{
  "type": "Feature",
  "properties": {
    "iso:country":"CH",
    "sg:address":"Gottardo Via San 29",
    "sg:city":"Muralto",
    "sg:orig_category":"Unclassifiable Establishments",
    "sg:postcode":"6600",
    "sg:province":"Ticino",
    "wof:name":"S.p. Fina Holding Sa",
    "wof:placetype":"venue"
},
  "geometry": {"coordinates":[8.8053121567,46.1742744446],"type":"Point"}
}