{
  "type": "Feature",
  "properties": {
    "iso:country":"CH",
    "sg:address":"Gessnerallee 32 8001 Z\u00fcrich. Postfach",
    "sg:city":"Z\u00fcrich",
    "sg:orig_category":"Advokaturb\u00fcros",
    "sg:phone":"+41 12125353",
    "sg:postcode":"8023",
    "sg:province":"Z\u00fcrich",
    "wof:name":"Bernasconi & Bernasconi Advokaturb\u00fcro",
    "wof:placetype":"venue"
},
  "geometry": {"coordinates":[8.536624,47.376369],"type":"Point"}
}