{
  "type": "Feature",
  "properties": {
    "iso:country":"CH",
    "sg:address":"Dorfstrasse 9",
    "sg:city":"Leuzigen",
    "sg:orig_category":"Vorschulen, Kinderg\u00e4rten",
    "sg:phone":"+41 32 679 32 20",
    "sg:postcode":"3297",
    "sg:province":"Bern",
    "wof:name":"Kindergarten Alte Post",
    "wof:placetype":"venue"
},
  "geometry": {"coordinates":[7.4596858025,47.1738624573],"type":"Point"}
}