{
  "type": "Feature",
  "properties": {
    "iso:country":"CH",
    "sg:address":"Dorneckstrasse 31",
    "sg:city":"Dornach",
    "sg:orig_category":"Wohnheime",
    "sg:postcode":"4143",
    "sg:province":"Solothurn",
    "wof:name":"Stiftung Haus Miranda",
    "wof:placetype":"venue"
},
  "geometry": {"coordinates":[9.1885662079,47.5608634949],"type":"Point"}
}