{
  "type": "Feature",
  "properties": {
    "iso:country":"CH",
    "sg:address":"Haltenstrasse 39 3715 Adelboden. Postfach",
    "sg:city":"Biel/bienne",
    "sg:orig_category":"Softwareentwicklung U beratung",
    "sg:postcode":"2502",
    "sg:province":"Bern",
    "wof:name":"D\u00e4pp Electronics",
    "wof:placetype":"venue"
},
  "geometry": {"coordinates":[7.5572710037,46.4938964844],"type":"Point"}
}