{
  "type": "Feature",
  "properties": {
    "iso:country":"CH",
    "sg:address":"Zollrain 4",
    "sg:city":"Aarau",
    "sg:classifiers":[
        {
            "category":"Restaurant",
            "type":"Food & Drink"
        }
    ],
    "sg:phone":"+41 55 210 16 07",
    "sg:postcode":"5000",
    "sg:province":"Aargau",
    "wof:name":"Restaurant Liz",
    "wof:placetype":"venue"
},
  "geometry": {"coordinates":[8.8199977875,47.2285652161],"type":"Point"}
}