{
  "type": "Feature",
  "properties": {
    "iso:country":"CH",
    "sg:address":"Place Du Midi 36 1950 Sion Case Postale 1017",
    "sg:city":"Sion",
    "sg:orig_category":"Versicherungen Generalagenturen",
    "sg:phone":"+41 27 329 04 70",
    "sg:postcode":"1951",
    "sg:province":"Valais",
    "wof:name":"Vaudoise Assurances Agence G\u00e9n\u00e9rale",
    "wof:placetype":"venue"
},
  "geometry": {"coordinates":[7.3617019653,46.2314338684],"type":"Point"}
}