{
  "type": "Feature",
  "properties": {
    "addr:full":"1112 Echichens Vaud 1112",
    "addr:housenumber":"1112",
    "addr:postcode":"1112",
    "addr:street":"Echichens",
    "iso:country":"CH",
    "sg:address":"1112",
    "sg:city":"Echichens",
    "sg:classifiers":[
        {
            "category":"Education",
            "subcategory":"Library",
            "type":"Public Place"
        }
    ],
    "sg:postcode":"1112",
    "sg:province":"Vaud",
    "sg:tags":[
        "u",
        "bibliotheken",
        "archive"
    ],
    "wof:name":"Biblioth\u00e8que Populaire",
    "wof:placetype":"venue"
},
  "geometry": {"coordinates":[6.4943,46.530849],"type":"Point"}
}