{
  "type": "Feature",
  "properties": {
    "addr:full":"Bahnhofzentrum 3186 D\u00fcdingen. Postfach 227 D\u00fcdingen Fribourg 3186",
    "addr:housenumber":"227",
    "addr:postcode":"3186;3186",
    "addr:street":"Duedingen. Postfach;Fribourg",
    "iso:country":"CH",
    "sg:address":"Bahnhofzentrum 3186 D\u00fcdingen. Postfach 227",
    "sg:city":"D\u00fcdingen",
    "sg:orig_category":"Arztpraxen",
    "sg:phone":"+41 19203268",
    "sg:postcode":"3186",
    "sg:province":"Fribourg",
    "wof:name":"Dr.med.erich Unterrassner Arzt F.allgemeine Medizin Fmh",
    "wof:placetype":"venue"
},
  "geometry": {"coordinates":[8.720788,47.271069],"type":"Point"}
}