{
  "type": "Feature",
  "properties": {
    "iso:country":"CH",
    "sg:address":"Motto Via 6",
    "sg:city":"Cureglia",
    "sg:orig_category":"Unternehmensberatung",
    "sg:postcode":"6944",
    "sg:province":"Ticino",
    "wof:name":"Fcd Consulting Sa",
    "wof:placetype":"venue"
},
  "geometry": {"coordinates":[8.9422235489,46.0334777832],"type":"Point"}
}