{
  "type": "Feature",
  "properties": {
    "iso:country":"CH",
    "sg:address":"Talackerstr. 17 8152 Glattbrugg. Postfach",
    "sg:city":"Z\u00fcrich",
    "sg:orig_category":"Herstellung von Oberbekleidung",
    "sg:phone":"+41 12123091",
    "sg:postcode":"8065",
    "sg:province":"Z\u00fcrich",
    "wof:name":"Lataa Style Ag",
    "wof:placetype":"venue"
},
  "geometry": {"coordinates":[8.5820579529,47.3126373291],"type":"Point"}
}