{
  "type": "Feature",
  "properties": {
    "addr:full":"Weinplatz 4/5 8001 Z\u00fcrich. Postfach Z\u00fcrich Z\u00fcrich 8021",
    "addr:housenumber":"4 / 5",
    "addr:postcode":"8001 zuerich. postfach;8021",
    "addr:street":"Weinplatz",
    "iso:country":"CH",
    "sg:address":"Weinplatz 4/5 8001 Z\u00fcrich. Postfach",
    "sg:city":"Z\u00fcrich",
    "sg:orig_category":"Detailhandel mit B\u00fcchern Detailhandel mit B\u00fcchern, Zeitungen, Schreib U Papeteriewaren",
    "sg:phone":"+41 12099111",
    "sg:postcode":"8021",
    "sg:province":"Z\u00fcrich",
    "wof:name":"Buchhandlung St\u00e4heli Ag",
    "wof:placetype":"venue"
},
  "geometry": {"coordinates":[8.541452,47.371384],"type":"Point"}
}