{
  "type": "Feature",
  "properties": {
    "iso:country":"CH",
    "sg:address":"C.f. Meyer-strasse 14",
    "sg:city":"Basel",
    "sg:orig_category":"Sonstiger Grosshandel",
    "sg:postcode":"4059",
    "sg:province":"Basel-Stadt",
    "wof:name":"Karicom Gmbh",
    "wof:placetype":"venue"
},
  "geometry": {"coordinates":[7.5872950554,47.5311584473],"type":"Point"}
}