{
  "type": "Feature",
  "properties": {
    "iso:country":"CH",
    "sg:address":"Haus Chilchweg",
    "sg:city":"Sachseln",
    "sg:orig_category":"Allgemeiner Hoch U Tiefbau",
    "sg:postcode":"6072",
    "sg:province":"Obwalden",
    "wof:name":"Gasser Felstechnik Ag Lungern, Zweigniederlassung Sachseln Bauunternehmung, Felsabbau. Baumaterialien-handel",
    "wof:placetype":"venue"
},
  "geometry": {"coordinates":[8.250006,46.870609],"type":"Point"}
}