{
  "type": "Feature",
  "properties": {
    "iso:country":"CH",
    "sg:address":"Bl\u00fcmlisalpstrasse 33c",
    "sg:city":"Thun",
    "sg:orig_category":"Malerei-Gipserei Stukkateurgewerbe, Gipserei U Verputzerei",
    "sg:phone":"+41 79 422 56 50",
    "sg:postcode":"3600",
    "sg:province":"Bern",
    "wof:name":"Peter Sch\u00e4ren Gipsergesch\u00e4ft",
    "wof:placetype":"venue"
},
  "geometry": {"coordinates":[7.988255024,47.5544052124],"type":"Point"}
}