{
  "type": "Feature",
  "properties": {
    "iso:country":"CH",
    "sg:address":"Dornwydenweg 9",
    "sg:city":"Arlesheim",
    "sg:orig_category":"Lagerung",
    "sg:phone":"+41 32 913 94 24",
    "sg:postcode":"4144",
    "sg:province":"Basel-Landschaft",
    "wof:name":"Natural Ag",
    "wof:placetype":"venue"
},
  "geometry": {"coordinates":[6.8264021873,47.1004753113],"type":"Point"}
}