{
  "type": "Feature",
  "properties": {
    "iso:country":"CH",
    "sg:address":"Schaffhauserstrasse 24 8400 Winterthur. Postfach 522",
    "sg:city":"Winterthur",
    "sg:orig_category":"Bauspenglerei Sanit\u00e4r, Heizungs U L\u00fcftungsinstallation",
    "sg:postcode":"8401",
    "sg:province":"Z\u00fcrich",
    "wof:name":"Schellenberg Robert Ag",
    "wof:placetype":"venue"
},
  "geometry": {"coordinates":[8.723818,47.506306],"type":"Point"}
}