{
  "type": "Feature",
  "properties": {
    "iso:country":"CH",
    "sg:address":"Schw\u00e4rzere 3",
    "sg:city":"Koppigen",
    "sg:orig_category":"Sportvereine Turnen",
    "sg:phone":"+41 34 413 21 39",
    "sg:postcode":"3425",
    "sg:province":"Bern",
    "wof:name":"Turnverein Stv Koppigen",
    "wof:placetype":"venue"
},
  "geometry": {"coordinates":[7.6062788963,47.1329727173],"type":"Point"}
}