{
  "type": "Feature",
  "properties": {
    "iso:country":"CH",
    "sg:address":"En Budron 14",
    "sg:city":"Mont-sur-lausanne",
    "sg:orig_category":"Unternehmensberatung",
    "sg:postcode":"1052",
    "sg:province":"Vaud",
    "wof:name":"Tech'firm Sa",
    "wof:placetype":"venue"
},
  "geometry": {"coordinates":[6.5580701828,46.5100784302],"type":"Point"}
}