{
  "type": "Feature",
  "properties": {
    "iso:country":"CH",
    "sg:address":"Unterfeldstrasse 7b",
    "sg:city":"Frauenfeld",
    "sg:orig_category":"Architektur U Ingenieurb\u00fcros",
    "sg:phone":"+41 52 721 70 69",
    "sg:postcode":"8500",
    "sg:province":"Thurgau",
    "wof:name":"Bachmann Walter",
    "wof:placetype":"venue"
},
  "geometry": {"coordinates":[8.906093,47.555828],"type":"Point"}
}