{
  "type": "Feature",
  "properties": {
    "iso:country":"CH",
    "sg:address":"Via Da La Pesa",
    "sg:city":"Poschiavo",
    "sg:orig_category":"Detailhandel mit Fleisch U Fleischwaren",
    "sg:phone":"+41 81 844 01 16",
    "sg:postcode":"7742",
    "sg:province":"Graubunden",
    "wof:name":"Urbano Luminati Macelleria",
    "wof:placetype":"venue"
},
  "geometry": {"coordinates":[10.057674408,46.3271255493],"type":"Point"}
}