{
  "type": "Feature",
  "properties": {
    "iso:country":"CH",
    "sg:address":"Friedheimstrasse 11",
    "sg:city":"Erstfeld",
    "sg:orig_category":"Erschliessung von Grundst\u00fccken",
    "sg:postcode":"6472",
    "sg:province":"Uri",
    "wof:name":"Baugenossenschaft Eigenhaus",
    "wof:placetype":"venue"
},
  "geometry": {"coordinates":[8.6514120102,46.8225822449],"type":"Point"}
}