{
  "type": "Feature",
  "properties": {
    "iso:country":"CH",
    "sg:address":"Suedstrasse 8 A 3110 M\u00fcnsingen. Postfach",
    "sg:city":"M\u00fcnsingen",
    "sg:orig_category":"Herstellung von keramischen Wand U Bodenfliesen U platten",
    "sg:phone":"+41 31 721 94 92",
    "sg:postcode":"3110",
    "sg:province":"Bern",
    "wof:name":"Princess Laszlo Keramische Wand U. Bodenbel\u00e4ge",
    "wof:placetype":"venue"
},
  "geometry": {"coordinates":[7.5630888939,46.8677597046],"type":"Point"}
}