{
  "type": "Feature",
  "properties": {
    "iso:country":"CH",
    "sg:address":"Byfangweg 40 4000 Basel. Postfach",
    "sg:city":"Basel",
    "sg:orig_category":"Vermietung U Verpachtung von eigenen Immobilien",
    "sg:postcode":"4051",
    "sg:province":"Basel-Stadt",
    "wof:name":"Byfang-immobilien Gmbh",
    "wof:placetype":"venue"
},
  "geometry": {"coordinates":[7.5807609558,47.5510635376],"type":"Point"}
}