{
  "type": "Feature",
  "properties": {
    "addr:full":"Hauptstrasse 39 2560 Nidau. Postfach Nidau Bern 2560",
    "addr:housenumber":"39",
    "addr:postcode":"2560 nidau. postfach;2560",
    "addr:street":"Hauptstrasse",
    "iso:country":"CH",
    "sg:address":"Hauptstrasse 39 2560 Nidau. Postfach",
    "sg:city":"Nidau",
    "sg:orig_category":"Detailhandel mit Bekleidung Detailhandel mit Geschenkartikeln U Souvenirs",
    "sg:phone":"+41 32 331 52 91",
    "sg:postcode":"2560",
    "sg:province":"Bern",
    "wof:name":"Lydia Br\u00f6nnimann Boutique Black Cat",
    "wof:placetype":"venue"
},
  "geometry": {"coordinates":[7.240692,47.125435],"type":"Point"}
}