{
  "type": "Feature",
  "properties": {
    "iso:country":"CH",
    "sg:address":"Via Angelo Maspoli 24",
    "sg:city":"Mendrisio",
    "sg:orig_category":"Sonstige Kurierdienste",
    "sg:postcode":"6850",
    "sg:province":"Ticino",
    "wof:name":"Dhl Sa Worldwide Express Courrier",
    "wof:placetype":"venue"
},
  "geometry": {"coordinates":[8.9810523987,45.8748321533],"type":"Point"}
}