{
  "type": "Feature",
  "properties": {
    "iso:country":"CH",
    "sg:address":"Allmeindlistrasse 5",
    "sg:city":"Reichenburg",
    "sg:orig_category":"RESTAURANTS: TEA-ROOMS",
    "sg:postcode":"8864",
    "sg:province":"Schwyz",
    "wof:name":"Pk Restaurant Hahn Reichenburg Betriebs Gmbh",
    "wof:placetype":"venue"
},
  "geometry": {"coordinates":[8.9814710617,47.1683807373],"type":"Point"}
}