{
  "type": "Feature",
  "properties": {
    "iso:country":"CH",
    "sg:address":"Klosterweg 36",
    "sg:city":"Z\u00fcrich",
    "sg:orig_category":"RESTAURANTS: TEA-ROOMS",
    "sg:phone":"+41 12512500",
    "sg:postcode":"8044",
    "sg:province":"Z\u00fcrich",
    "wof:name":"Zoo Restaurants Gmbh",
    "wof:placetype":"venue"
},
  "geometry": {"coordinates":[8.5753498077,47.386631012],"type":"Point"}
}