{
  "type": "Feature",
  "properties": {
    "iso:country":"CH",
    "sg:address":"K\u00e4sereistrasse 9",
    "sg:city":"Kesswil",
    "sg:orig_category":"Herstellung von Fenstern U T\u00fcren aus Holz Herstellung von Konstruktionsteilen, Fertigbauteilen U Aus",
    "sg:phone":"+41 71 463 26 45",
    "sg:postcode":"8593",
    "sg:province":"Thurgau",
    "wof:name":"Roth W. Fensterbau",
    "wof:placetype":"venue"
},
  "geometry": {"coordinates":[9.314081192,47.592540741],"type":"Point"}
}