{
  "type": "Feature",
  "properties": {
    "iso:country":"CH",
    "sg:address":"Fr\u00fceblistrasse 9",
    "sg:city":"Dielsdorf",
    "sg:orig_category":"Vorschulen, Kinderg\u00e4rten",
    "sg:phone":"+41 56 633 32 71",
    "sg:postcode":"8157",
    "sg:province":"Z\u00fcrich",
    "wof:name":"Kindergarten Fuchs\u00e4cker",
    "wof:placetype":"venue"
},
  "geometry": {"coordinates":[8.3469753265,47.3468971252],"type":"Point"}
}