{
  "type": "Feature",
  "properties": {
    "iso:country":"CH",
    "sg:address":"Dorf 79",
    "sg:city":"Schwellbrunn",
    "sg:orig_category":"HOTELS: MIT RESTAURANT HOTELS: OHNE RESTAURANT",
    "sg:phone":"+41 71 351 71 43",
    "sg:postcode":"9103",
    "sg:province":"Appenzell Ausserrhoden",
    "wof:name":"G\u00e4stehaus Kreuz Gmbh",
    "wof:placetype":"venue"
},
  "geometry": {"coordinates":[9.248790741,47.3517227173],"type":"Point"}
}