{
  "type": "Feature",
  "properties": {
    "iso:country":"CH",
    "sg:address":"Wibachstrasse 17 8153 R\u00fcmlang. Postfach",
    "sg:city":"R\u00fcmlang",
    "sg:orig_category":"G\u00fcterbef\u00f6rderung im Strassenverkehr",
    "sg:phone":"+41 18173366",
    "sg:postcode":"8153",
    "sg:province":"Z\u00fcrich",
    "wof:name":"Camion-transport Ag Wil Ct Filiale",
    "wof:placetype":"venue"
},
  "geometry": {"coordinates":[8.5214672089,47.459980011],"type":"Point"}
}