{
  "type": "Feature",
  "properties": {
    "addr:full":"Austrasse 2 Oberwichtrach Bern 3114",
    "addr:housenumber":"2",
    "addr:postcode":"3114",
    "addr:street":"Austrasse",
    "iso:country":"CH",
    "sg:address":"Austrasse 2",
    "sg:city":"Oberwichtrach",
    "sg:orig_category":"Autogaragen",
    "sg:phone":"+41 31 781 08 08",
    "sg:postcode":"3114",
    "sg:province":"Bern",
    "wof:name":"Martin Diener Au-garage",
    "wof:placetype":"venue"
},
  "geometry": {"coordinates":[7.576506,46.843365],"type":"Point"}
}