{
  "type": "Feature",
  "properties": {
    "iso:country":"CH",
    "sg:address":"Baselstrasse 11",
    "sg:city":"Riehen",
    "sg:orig_category":"Herstellung von homogenisierten U di\u00e4tetischen Nahrungsmitteln",
    "sg:phone":"+41 61 645 96 00",
    "sg:postcode":"4125",
    "sg:province":"Basel-Stadt",
    "wof:name":"Holle Baby Food Gmbh",
    "wof:placetype":"venue"
},
  "geometry": {"coordinates":[7.6481199265,47.5833435059],"type":"Point"}
}