{
  "type": "Feature",
  "properties": {
    "iso:country":"CH",
    "sg:address":"Vorderer Schallenberg",
    "sg:city":"S\u00fcderen",
    "sg:orig_category":"Mechanische Werkst\u00e4tten",
    "sg:phone":"+41 34 491 20 71",
    "sg:postcode":"3618",
    "sg:province":"Bern",
    "wof:name":"Urs Wittwer Mechanische Werkstatt",
    "wof:placetype":"venue"
},
  "geometry": {"coordinates":[7.7245750427,46.8177490234],"type":"Point"}
}