{
  "type": "Feature",
  "properties": {
    "iso:country":"CH",
    "sg:address":"Poste Rue De La 3 1920 Martigny. Postfach",
    "sg:city":"Martigny",
    "sg:orig_category":"Softwareentwicklung U beratung",
    "sg:phone":"+41 27 723 59 40",
    "sg:postcode":"1920",
    "sg:province":"Valais",
    "wof:name":"Thales Informations Systems Sa, Succursale De Martigny",
    "wof:placetype":"venue"
},
  "geometry": {"coordinates":[7.0729198456,46.1013793945],"type":"Point"}
}