{
  "type": "Feature",
  "properties": {
    "iso:country":"CH",
    "sg:address":"Rue Fritz Oppliger 18 2500 Biel/bienne. Postfach",
    "sg:city":"Biel/bienne",
    "sg:orig_category":"Pensionskassen",
    "sg:postcode":"2500",
    "sg:province":"Bern",
    "wof:name":"Fonds De Pr\u00e9voyance En Faveur Du Personnel De La Maison Posalux Sa",
    "wof:placetype":"venue"
},
  "geometry": {"coordinates":[7.283249855,47.1602554321],"type":"Point"}
}