{
  "type": "Feature",
  "properties": {
    "iso:country":"CH",
    "sg:address":"Wylerringstrasse 36 3014 Bern. Postfach 2750",
    "sg:city":"Bern",
    "sg:orig_category":"Pensionskassen",
    "sg:postcode":"3005",
    "sg:province":"Bern",
    "wof:name":"Allgemeine F\u00fcrsorgestiftung Wifag/polytype",
    "wof:placetype":"venue"
},
  "geometry": {"coordinates":[7.4489121437,46.9626808167],"type":"Point"}
}