{
  "type": "Feature",
  "properties": {
    "iso:country":"CH",
    "sg:address":"Weidstrasse 6",
    "sg:city":"D\u00fcdingen",
    "sg:classifiers":[
        {
            "category":"Ice Cream",
            "type":"Food & Drink"
        }
    ],
    "sg:phone":"+41 79 435 00 56",
    "sg:postcode":"3186",
    "sg:province":"Fribourg",
    "sg:tags":[
        "ice-cream"
    ],
    "wof:name":"Jungo Hanspeter",
    "wof:placetype":"venue"
},
  "geometry": {"coordinates":[7.1805458069,46.8490562439],"type":"Point"}
}