{
  "type": "Feature",
  "properties": {
    "iso:country":"CH",
    "sg:address":"Via Moretto 4",
    "sg:city":"Sorengo",
    "sg:orig_category":"Non-Classified Establishments",
    "sg:postcode":"6924",
    "sg:province":"Ticino",
    "wof:name":"Chiesa Evangelica Ravvivamento Della Fede",
    "wof:placetype":"venue"
},
  "geometry": {"coordinates":[8.934633255,46.0052947998],"type":"Point"}
}