{
  "type": "Feature",
  "properties": {
    "iso:country":"CH",
    "sg:address":"Belairstrasse 20",
    "sg:city":"Schaffhausen",
    "sg:orig_category":"Unclassifiable Establishments",
    "sg:postcode":"8200",
    "sg:province":"Schaffhausen",
    "wof:name":"Partyorganisation Modularis",
    "wof:placetype":"venue"
},
  "geometry": {"coordinates":[8.6212472916,47.7028617859],"type":"Point"}
}