{
  "type": "Feature",
  "properties": {
    "iso:country":"CH",
    "sg:address":"1291 Commugny. Postfach",
    "sg:city":"Commugny",
    "sg:orig_category":"Sportvereine Ballsport Fussball",
    "sg:phone":"+41 22 776 05 22",
    "sg:postcode":"1291",
    "sg:province":"Vaud",
    "wof:name":"Us Terre Sainte",
    "wof:placetype":"venue"
},
  "geometry": {"coordinates":[6.1738519669,46.3194656372],"type":"Point"}
}