{
  "type": "Feature",
  "properties": {
    "iso:country":"CH",
    "sg:address":"Via Privata Delle Scuole",
    "sg:city":"Pregassona",
    "sg:orig_category":"Herstellung von elektrischen Lampen U Leuchten",
    "sg:postcode":"6963",
    "sg:province":"Ticino",
    "wof:name":"Scenotecnica Barbieri",
    "wof:placetype":"venue"
},
  "geometry": {"coordinates":[8.9703798294,46.021987915],"type":"Point"}
}