{
  "type": "Feature",
  "properties": {
    "iso:country":"CH",
    "sg:address":"Masanserstrasse 19 7000 Chur. Postfach",
    "sg:city":"Chur",
    "sg:orig_category":"Wirtschaftspr\u00fcfung, Steuerberatung U Treuhand",
    "sg:postcode":"7000",
    "sg:province":"Graubunden",
    "wof:name":"Prohn Company Ag, Christian M",
    "wof:placetype":"venue"
},
  "geometry": {"coordinates":[9.5342407227,46.8532028198],"type":"Point"}
}