{
  "type": "Feature",
  "properties": {
    "iso:country":"CH",
    "sg:address":"4315",
    "sg:city":"Zuzgen",
    "sg:orig_category":"Mahl U Sch\u00e4lm\u00fchlen",
    "sg:phone":"+41 61 871 04 54",
    "sg:postcode":"4315",
    "sg:province":"Aargau",
    "wof:name":"Hans Schaffner M\u00fchle",
    "wof:placetype":"venue"
},
  "geometry": {"coordinates":[7.9023170471,47.5239143372],"type":"Point"}
}