{
  "type": "Feature",
  "properties": {
    "iso:country":"CH",
    "sg:address":"2947",
    "sg:city":"Charmoille",
    "sg:orig_category":"Forstwirtschaft ohne Dienstleistungen in der Forstwirtschaft",
    "sg:phone":"+41 32 462 26 74",
    "sg:postcode":"2947",
    "sg:province":"Jura",
    "wof:name":"Chaignat Gilles",
    "wof:placetype":"venue"
},
  "geometry": {"coordinates":[7.2043571472,47.4232330322],"type":"Point"}
}