{
  "type": "Feature",
  "properties": {
    "addr:full":"Paulistrasse 26 8834 Schindellegi. Postfach Schindellegi Schwyz 8834",
    "addr:housenumber":"26",
    "addr:postcode":"8834 schindellegi. postfach;8834",
    "addr:street":"Paulistrasse",
    "iso:country":"CH",
    "sg:address":"Paulistrasse 26 8834 Schindellegi. Postfach",
    "sg:city":"Schindellegi",
    "sg:orig_category":"Dauerkulturbau",
    "sg:phone":"+41 17840015",
    "sg:postcode":"8834",
    "sg:province":"Schwyz",
    "wof:name":"Rellstab Vino-cave Consulting",
    "wof:placetype":"venue"
},
  "geometry": {"coordinates":[8.714955,47.181831],"type":"Point"}
}