{
  "type": "Feature",
  "properties": {
    "iso:country":"CH",
    "sg:address":"Hungerb\u00fcelstrasse 10 8500 Frauenfeld. Postfach",
    "sg:city":"Frauenfeld",
    "sg:orig_category":"Satzherstellung U Reproduktion",
    "sg:phone":"+41 52 720 76 67",
    "sg:postcode":"8501",
    "sg:province":"Thurgau",
    "wof:name":"Ren\u00e9 Meier Visuellsatz",
    "wof:placetype":"venue"
},
  "geometry": {"coordinates":[8.8733463287,47.5624771118],"type":"Point"}
}