{
  "type": "Feature",
  "properties": {
    "iso:country":"CH",
    "sg:address":"Oberestrasse 1a",
    "sg:city":"Davos",
    "sg:classifiers":[
        {
            "category":"Banks & Credit Unions",
            "subcategory":"Bank",
            "type":"Services"
        }
    ],
    "sg:phone":"+41 4181436685",
    "sg:postcode":"7270",
    "sg:province":"Graubunden",
    "wof:name":"Schweiz. Mobiliar",
    "wof:placetype":"venue"
},
  "geometry": {"coordinates":[9.816715,46.79044],"type":"Point"}
}