{
  "type": "Feature",
  "properties": {
    "addr:full":"Rue De La Thiolleyres 1 Estavayer-le-lac Fribourg 1470",
    "addr:housenumber":"1",
    "addr:postcode":"1470",
    "addr:street":"Rue De La Thiolleyres;Fribourg",
    "iso:country":"CH",
    "sg:address":"Rue De La Thiolleyres 1",
    "sg:city":"Estavayer-le-lac",
    "sg:orig_category":"Architektur U Ingenieurb\u00fcros",
    "sg:phone":"+41 26 663 34 55",
    "sg:postcode":"1470",
    "sg:province":"Fribourg",
    "wof:name":"Bureau D'ing\u00e9nieurs Michel Etudes Sa",
    "wof:placetype":"venue"
},
  "geometry": {"coordinates":[6.845057,46.849415],"type":"Point"}
}