{
  "type": "Feature",
  "properties": {
    "iso:country":"CH",
    "sg:address":"Frohbergstrasse 11c",
    "sg:city":"Samstagern",
    "sg:orig_category":"Softwareentwicklung U beratung",
    "sg:phone":"+41 17861630",
    "sg:postcode":"8833",
    "sg:province":"Z\u00fcrich",
    "wof:name":"E-cos Informatik Ag Edv-dienstleistungen",
    "wof:placetype":"venue"
},
  "geometry": {"coordinates":[8.6890697479,47.1992034912],"type":"Point"}
}