{
  "type": "Feature",
  "properties": {
    "iso:country":"CH",
    "sg:address":"Nussbaumweg 15",
    "sg:city":"Binningen",
    "sg:orig_category":"Geb\u00e4ude, Wohnungsreinigung Reinigungsgewerbe",
    "sg:phone":"+41 61 422 04 66",
    "sg:postcode":"4102",
    "sg:province":"Basel-Landschaft",
    "wof:name":"Reinigungsinstitut M.gerber",
    "wof:placetype":"venue"
},
  "geometry": {"coordinates":[7.5598039627,47.5379295349],"type":"Point"}
}