{
  "type": "Feature",
  "properties": {
    "iso:country":"CH",
    "sg:address":"Via Lisano 3 6900 Massagno. Postfach",
    "sg:city":"Lugano",
    "sg:orig_category":"Inkassob\u00fcros",
    "sg:phone":"+41 91 966 49 51",
    "sg:postcode":"6903",
    "sg:province":"Ticino",
    "wof:name":"Justitia Sa Servizi Per Gli Incassi",
    "wof:placetype":"venue"
},
  "geometry": {"coordinates":[8.9428453445,46.0092735291],"type":"Point"}
}