{
  "type": "Feature",
  "properties": {
    "iso:country":"CH",
    "sg:address":"Grundhofstrasse 71 8404 Stadel(winterthur). Postfach",
    "sg:city":"Stadel(winterthur)",
    "sg:orig_category":"Grosshandel mit Textilien",
    "sg:phone":"+41 71 755 22 44",
    "sg:postcode":"8404",
    "sg:province":"Z\u00fcrich",
    "wof:name":"Wico-textil Handels Ag",
    "wof:placetype":"venue"
},
  "geometry": {"coordinates":[9.55809021,47.3807945251],"type":"Point"}
}