{
  "type": "Feature",
  "properties": {
    "iso:country":"CH",
    "sg:address":"Rue De La Paix 10",
    "sg:city":"Court",
    "sg:orig_category":"Sportvereine Ballsport Tischtennis",
    "sg:phone":"+41 32 497 95 78",
    "sg:postcode":"2738",
    "sg:province":"Bern",
    "wof:name":"Ctt Moutier",
    "wof:placetype":"venue"
},
  "geometry": {"coordinates":[7.3394908905,47.2420349121],"type":"Point"}
}