{
  "type": "Feature",
  "properties": {
    "iso:country":"CH",
    "sg:address":"Schmidweg 10 8634 Hombrechtikon. Postfach 112",
    "sg:city":"Hombrechtikon",
    "sg:orig_category":"Schulpflegen",
    "sg:phone":"+41 55 244 35 45",
    "sg:postcode":"8634",
    "sg:province":"Z\u00fcrich",
    "wof:name":"Schulpflege Der Gemeinde Hombrechtikon",
    "wof:placetype":"venue"
},
  "geometry": {"coordinates":[8.7665185928,47.2511367798],"type":"Point"}
}