{
  "type": "Feature",
  "properties": {
    "iso:country":"CH",
    "sg:address":"Adlikerstrasse 255 8105 Regensdorf. Postfach",
    "sg:city":"Regensdorf",
    "sg:orig_category":"Pensionskassen",
    "sg:phone":"+41 18402040",
    "sg:postcode":"8105",
    "sg:province":"Z\u00fcrich",
    "wof:name":"Wohlfahrtsstiftung Der Drawag Ag",
    "wof:placetype":"venue"
},
  "geometry": {"coordinates":[8.4653816223,47.4430465698],"type":"Point"}
}