{
  "type": "Feature",
  "properties": {
    "iso:country":"CH",
    "sg:address":"Laufenstrasse 20 A",
    "sg:city":"Zwingen",
    "sg:orig_category":"Verwaltung von Immobilien",
    "sg:postcode":"4222",
    "sg:province":"Basel-Landschaft",
    "wof:name":"Vargas-preuss + Co",
    "wof:placetype":"venue"
},
  "geometry": {"coordinates":[7.523750782,47.4377403259],"type":"Point"}
}