{
  "type": "Feature",
  "properties": {
    "iso:country":"CH",
    "sg:address":"Rue De Lyon 114",
    "sg:city":"Gen\u00e8ve",
    "sg:orig_category":"Innenarchitekturb\u00fcros",
    "sg:phone":"+41 31 971 32 32",
    "sg:postcode":"1201",
    "sg:province":"Gen\u00e8ve",
    "wof:name":"Eric Montandon Idea-crea Innenarchitektur",
    "wof:placetype":"venue"
},
  "geometry": {"coordinates":[7.4154338837,46.909614563],"type":"Point"}
}