{
  "type": "Feature",
  "properties": {
    "iso:country":"CH",
    "sg:address":"Neeracherstrasse 20",
    "sg:city":"Dielsdorf",
    "sg:orig_category":"Grosshandel mit Textilien",
    "sg:postcode":"8157",
    "sg:province":"Z\u00fcrich",
    "wof:name":"Hja Equitex, Hans Jakob Altherr",
    "wof:placetype":"venue"
},
  "geometry": {"coordinates":[8.4690189362,47.4870300293],"type":"Point"}
}