{
  "type": "Feature",
  "properties": {
    "iso:country":"CH",
    "sg:address":"Gruebi",
    "sg:city":"Habkern",
    "sg:classifiers":[
        {
            "category":"Insurance",
            "subcategory":"Insurance Agent",
            "type":"Services"
        }
    ],
    "sg:phone":"+41 33 843 12 14",
    "sg:postcode":"3804",
    "sg:province":"Bern",
    "sg:tags":[
        "versicherungsagenturen",
        "-broker"
    ],
    "wof:name":"Winterthur-versicherungen Agentur",
    "wof:placetype":"venue"
},
  "geometry": {"coordinates":[7.8640518188,46.7258834839],"type":"Point"}
}