{
  "type": "Feature",
  "properties": {
    "addr:full":"Hohlandstrasse 1 Winterthur Z\u00fcrich 8404",
    "addr:housenumber":"1",
    "addr:postcode":"8404",
    "addr:street":"Hohlandstrasse",
    "iso:country":"CH",
    "sg:address":"Hohlandstrasse 1",
    "sg:city":"Winterthur",
    "sg:orig_category":"Detailhandel mit Beleuchtungs U Haushaltsgegenst\u00e4nden Innendekorationsateliers",
    "sg:phone":"+41 52 242 33 30",
    "sg:postcode":"8404",
    "sg:province":"Z\u00fcrich",
    "wof:name":"Vorhang Sch\u00f6n M.sch\u00f6n",
    "wof:placetype":"venue"
},
  "geometry": {"coordinates":[8.754887,47.507275],"type":"Point"}
}