{
  "type": "Feature",
  "properties": {
    "iso:country":"CH",
    "sg:address":"Bahnhofstrasse 53",
    "sg:city":"Aarau",
    "sg:classifiers":[
        {
            "category":"Travel",
            "subcategory":"Hotels & Motels",
            "type":"Entertainment"
        }
    ],
    "sg:phone":"+41 27 952 13 38",
    "sg:postcode":"5000",
    "sg:province":"Aargau",
    "sg:tags":[
        "hotels",
        "mit",
        "restaurant"
    ],
    "wof:name":"Hotel Killerhof",
    "wof:placetype":"venue"
},
  "geometry": {"coordinates":[7.8920350075,46.2011413574],"type":"Point"}
}