{
  "type": "Feature",
  "properties": {
    "iso:country":"CH",
    "sg:address":"Glattalstrasse 507",
    "sg:city":"R\u00fcmlang",
    "sg:orig_category":"Instandhaltung U Reparatur von Automobilen",
    "sg:phone":"+41 61 701 97 11",
    "sg:postcode":"8153",
    "sg:province":"Z\u00fcrich",
    "wof:name":"Str\u00e4uli Kurt",
    "wof:placetype":"venue"
},
  "geometry": {"coordinates":[7.620059967,47.4760169983],"type":"Point"}
}