{
  "type": "Feature",
  "properties": {
    "iso:country":"CH",
    "sg:address":"Holzwiesstrasse 11",
    "sg:city":"Herrliberg",
    "sg:orig_category":"Verm\u00f6gensverwaltung",
    "sg:phone":"+41 19153693",
    "sg:postcode":"8704",
    "sg:province":"Z\u00fcrich",
    "wof:name":"Peter A. Grollimund",
    "wof:placetype":"venue"
},
  "geometry": {"coordinates":[8.6079864502,47.2943229675],"type":"Point"}
}