{
  "type": "Feature",
  "properties": {
    "iso:country":"CH",
    "sg:address":"Gemeindekanzlei",
    "sg:city":"Spiringen",
    "sg:orig_category":"Interessenvertretungen",
    "sg:phone":"+41 41 879 11 34",
    "sg:postcode":"6464",
    "sg:province":"Uri",
    "wof:name":"Stiftung D\u00f6rfli-haus",
    "wof:placetype":"venue"
},
  "geometry": {"coordinates":[8.734708786,46.8717422485],"type":"Point"}
}