{
  "type": "Feature",
  "properties": {
    "iso:country":"CH",
    "sg:address":"Dorfstrasse 33",
    "sg:city":"Sch\u00f6ftland",
    "sg:orig_category":"RESTAURANTS: TEA-ROOMS",
    "sg:postcode":"5040",
    "sg:province":"Aargau",
    "wof:name":"B\u00fcttiker S. + Sinske G.",
    "wof:placetype":"venue"
},
  "geometry": {"coordinates":[8.0513715744,47.3089256287],"type":"Point"}
}