{
  "type": "Feature",
  "properties": {
    "iso:country":"CH",
    "sg:address":"Gewerbestrasse 5 4450 Sissach. Postfach 373",
    "sg:city":"Sissach",
    "sg:orig_category":"Grosshandel mit Eisenwaren sowie Installationsbedarf f\u00fcr Gas, Wasser U Heizung Grosshandel mit sonst",
    "sg:phone":"+41 61 971 57 55",
    "sg:postcode":"4450",
    "sg:province":"Basel-Landschaft",
    "wof:name":"Spowema-tec Ag",
    "wof:placetype":"venue"
},
  "geometry": {"coordinates":[7.8020739555,47.467540741],"type":"Point"}
}