{
  "type": "Feature",
  "properties": {
    "iso:country":"CH",
    "sg:address":"Neugasse 7 6300 Zug. Postfach 519",
    "sg:city":"Zug",
    "sg:orig_category":"Fachdetailhandel in Verkaufsr\u00e4umen Grosshandel mit Sportartikeln",
    "sg:phone":"+41 41 710 22 93",
    "sg:postcode":"6301",
    "sg:province":"Zug",
    "wof:name":"Zacharias Sportleasure Ag, Succursale D'estavayer-le-lac Articles De Sport Etc.; Commerce Et Distribution",
    "wof:placetype":"venue"
},
  "geometry": {"coordinates":[8.5157108307,47.1673927307],"type":"Point"}
}