{
  "type": "Feature",
  "properties": {
    "iso:country":"CH",
    "sg:address":"Rousseaustrasse 43",
    "sg:city":"Z\u00fcrich",
    "sg:orig_category":"Schwimmb\u00e4der",
    "sg:phone":"+41 13612670",
    "sg:postcode":"8037",
    "sg:province":"Z\u00fcrich",
    "wof:name":"Schulhaus Letten Betriebsleitung Hallenbad",
    "wof:placetype":"venue"
},
  "geometry": {"coordinates":[8.533706665,47.3889007568],"type":"Point"}
}