{
  "type": "Feature",
  "properties": {
    "iso:country":"CH",
    "sg:address":"Faselrain 327",
    "sg:city":"Ramsen",
    "sg:orig_category":"Detailhandel mit Fleisch U Fleischwaren",
    "sg:phone":"+41 52 743 14 14",
    "sg:postcode":"8262",
    "sg:province":"Schaffhausen",
    "wof:name":"Jung Jos.",
    "wof:placetype":"venue"
},
  "geometry": {"coordinates":[8.8136997223,47.7057762146],"type":"Point"}
}