{
  "type": "Feature",
  "properties": {
    "iso:country":"CH",
    "sg:address":"Avry-centre Route Matran 9",
    "sg:city":"Avry-sur-matran",
    "sg:orig_category":"Tankstellen Vermietung von Automobilen",
    "sg:phone":"+41 26 470 19 87",
    "sg:postcode":"1754",
    "sg:province":"Fribourg",
    "wof:name":"Migrol Service Station D'essence & Budget",
    "wof:placetype":"venue"
},
  "geometry": {"coordinates":[7.0721960068,46.7883262634],"type":"Point"}
}