{
  "type": "Feature",
  "properties": {
    "iso:country":"CH",
    "sg:address":"Quellenstr. 29",
    "sg:city":"Rheinfelden",
    "sg:classifiers":[
        {
            "category":"Home & Garden",
            "subcategory":"Furniture",
            "type":"Retail Goods"
        }
    ],
    "sg:phone":"+41 61 831 54 34",
    "sg:postcode":"4310",
    "sg:province":"Aargau",
    "sg:tags":[
        "wood"
    ],
    "wof:name":"Sg Furnierwerk Ag Rheinfelden",
    "wof:placetype":"venue"
},
  "geometry": {"coordinates":[7.787569046,47.5504150391],"type":"Point"}
}