{
  "type": "Feature",
  "properties": {
    "iso:country":"CH",
    "sg:address":"Hauptstrasse 10 5726 Unterkulm. Postfach",
    "sg:city":"Unterkulm",
    "sg:orig_category":"Detailhandel mit Blumen U Pflanzen Fachdetailhandel in Verkaufsr\u00e4umen",
    "sg:phone":"+41 62 776 42 52",
    "sg:postcode":"5726",
    "sg:province":"Aargau",
    "wof:name":"Blueme-style Wirz Sandra Blumengesch\u00e4ft. Blumen; Handel. Pflanzen, Vasen Usw.; Verkauf",
    "wof:placetype":"venue"
},
  "geometry": {"coordinates":[8.115972,47.308773],"type":"Point"}
}