{
  "type": "Feature",
  "properties": {
    "iso:country":"CH",
    "sg:address":"Kalchb\u00fchlstrasse 40 7000 Chur. Postfach",
    "sg:city":"Magden",
    "sg:orig_category":"Unclassifiable Establishments",
    "sg:phone":"+41 61 845 96 96",
    "sg:postcode":"4312",
    "sg:province":"Aargau",
    "wof:name":"Vta Schweiz Gmbh Engineering Und Umwelttechnik Chemische Erzeugnisse, Bes. Wasser, Trinkwasser- U. Abwasseraufbereitungs- U. -reinigungsmittel Usw",
    "wof:placetype":"venue"
},
  "geometry": {"coordinates":[9.5068750381,46.8466873169],"type":"Point"}
}