{
  "type": "Feature",
  "properties": {
    "addr:full":"Schrotm\u00e4ttli 2 Littau Luzern 6014",
    "addr:housenumber":"2",
    "addr:postcode":"6014",
    "addr:street":"Schrotmaettli",
    "iso:country":"CH",
    "sg:address":"Schrotm\u00e4ttli 2",
    "sg:city":"Littau",
    "sg:orig_category":"Autospenglereien",
    "sg:phone":"+41 62 771 48 07",
    "sg:postcode":"6014",
    "sg:province":"Luzern",
    "wof:name":"Rolf L\u00fcthi Carrosserie",
    "wof:placetype":"venue"
},
  "geometry": {"coordinates":[8.201195,47.275517],"type":"Point"}
}