{
  "type": "Feature",
  "properties": {
    "iso:country":"CH",
    "sg:address":"Waldeggrain 11",
    "sg:city":"Hellb\u00fchl",
    "sg:orig_category":"Non-Classified Establishments",
    "sg:postcode":"6016",
    "sg:province":"Luzern",
    "wof:name":"Thomas Breitenstein",
    "wof:placetype":"venue"
},
  "geometry": {"coordinates":[8.1997308731,47.0730361938],"type":"Point"}
}