{
  "type": "Feature",
  "properties": {
    "iso:country":"CH",
    "sg:address":"Rigistrasse 4",
    "sg:city":"Brunnen",
    "sg:orig_category":"Elektroinstallation",
    "sg:phone":"+41 79 642 66 37",
    "sg:postcode":"6440",
    "sg:province":"Schwyz",
    "wof:name":"Elektro Betschart.",
    "wof:placetype":"venue"
},
  "geometry": {"coordinates":[8.6021413803,46.9951095581],"type":"Point"}
}