{
  "type": "Feature",
  "properties": {
    "iso:country":"CH",
    "sg:address":"K\u00e4sereistrasse 6 8722 Kaltbrunn. Postfach 122",
    "sg:city":"Kaltbrunn",
    "sg:orig_category":"Schulpflegen",
    "sg:phone":"+41 55 283 28 54",
    "sg:postcode":"8722",
    "sg:province":"St. Gallen",
    "wof:name":"Schulverwaltung Der Gemeinde Kaltbrunn",
    "wof:placetype":"venue"
},
  "geometry": {"coordinates":[9.0269937515,47.2140235901],"type":"Point"}
}