{
  "type": "Feature",
  "properties": {
    "iso:country":"CH",
    "sg:address":"Obernauerstrasse 38",
    "sg:city":"Kriens",
    "sg:orig_category":"Grosshandel mit Getr\u00e4nken",
    "sg:phone":"+41 41 320 63 70",
    "sg:postcode":"6010",
    "sg:province":"Luzern",
    "wof:name":"Weinhandlung Stalder Philipp",
    "wof:placetype":"venue"
},
  "geometry": {"coordinates":[8.2670202255,47.0339813232],"type":"Point"}
}