{
  "type": "Feature",
  "properties": {
    "iso:country":"CH",
    "sg:address":"6078",
    "sg:city":"Lungern",
    "sg:orig_category":"Personenbef\u00f6rderung im Linienverkehr zu Land",
    "sg:phone":"+41 41 678 15 55",
    "sg:postcode":"6078",
    "sg:province":"Obwalden",
    "wof:name":"Genossenschaft Skilift Bannholz",
    "wof:placetype":"venue"
},
  "geometry": {"coordinates":[8.1595687866,46.7853965759],"type":"Point"}
}