{
  "type": "Feature",
  "properties": {
    "iso:country":"CH",
    "sg:address":"Hirzbodenweg 47",
    "sg:city":"Basel",
    "sg:orig_category":"RESTAURANTS: TEA-ROOMS",
    "sg:postcode":"4052",
    "sg:province":"Basel-Stadt",
    "wof:name":"Feo Gmbh",
    "wof:placetype":"venue"
},
  "geometry": {"coordinates":[7.6082210541,47.5496139526],"type":"Point"}
}