{
  "type": "Feature",
  "properties": {
    "iso:country":"CH",
    "sg:address":"Dorfstrasse",
    "sg:city":"Wengen",
    "sg:orig_category":"Kantonalbanken",
    "sg:phone":"+41 31 376 45 10",
    "sg:postcode":"3823",
    "sg:province":"Bern",
    "wof:name":"Berner Kantonalbank Bekb/bcbe",
    "wof:placetype":"venue"
},
  "geometry": {"coordinates":[7.4314570427,46.9408226013],"type":"Point"}
}