{
  "type": "Feature",
  "properties": {
    "iso:country":"CH",
    "sg:address":"Untere Hauptstrasse 12a",
    "sg:city":"Niederwichtrach",
    "sg:orig_category":"Detailhandel mit Schuhen Detailhandel mit Sportartikeln",
    "sg:phone":"+41 31 781 37 30",
    "sg:postcode":"3114",
    "sg:province":"Bern",
    "wof:name":"Berger Schuhe & Sport",
    "wof:placetype":"venue"
},
  "geometry": {"coordinates":[7.5756530762,46.8502464294],"type":"Point"}
}