{
  "type": "Feature",
  "properties": {
    "addr:full":"Birmannsgasse 11 Basel Basel-Stadt 4055",
    "addr:housenumber":"11",
    "addr:postcode":"4055",
    "addr:street":"Birmannsgasse",
    "iso:country":"CH",
    "sg:address":"Birmannsgasse 11",
    "sg:city":"Basel",
    "sg:orig_category":"Arztpraxen",
    "sg:phone":"+41 61 261 03 22",
    "sg:postcode":"4055",
    "sg:province":"Basel-Stadt",
    "wof:name":"Dr.med.gian Clo Serena Arzt F.allgemeine Medizin Fmh",
    "wof:placetype":"venue"
},
  "geometry": {"coordinates":[7.5786,47.557949],"type":"Point"}
}