{
  "type": "Feature",
  "properties": {
    "iso:country":"CH",
    "sg:address":"Allmendstrasse 13 8102 Oberengstringen. Postfach",
    "sg:city":"Oberengstringen",
    "sg:orig_category":"Fachdetailhandel in Verkaufsr\u00e4umen Grosshandel mit Blumen U Pflanzen",
    "sg:phone":"+41 81 307 21 31",
    "sg:postcode":"8102",
    "sg:province":"Z\u00fcrich",
    "wof:name":"Gensetter Topfpflanzen Ag",
    "wof:placetype":"venue"
},
  "geometry": {"coordinates":[9.5694198608,46.9554290771],"type":"Point"}
}