{
  "type": "Feature",
  "properties": {
    "iso:country":"CH",
    "sg:address":"Mythen-centerstrasse 15",
    "sg:city":"Ibach",
    "sg:orig_category":"Non-Classified Establishments",
    "sg:postcode":"6438",
    "sg:province":"Schwyz",
    "wof:name":"Cbe Marmor U. Handels Ag",
    "wof:placetype":"venue"
},
  "geometry": {"coordinates":[8.6458873749,47.0148544312],"type":"Point"}
}