{
  "type": "Feature",
  "properties": {
    "iso:country":"CH",
    "sg:address":"Le Pontet",
    "sg:city":"Concise",
    "sg:classifiers":[
        {
            "category":"Banks & Credit Unions",
            "subcategory":"Bank",
            "type":"Services"
        }
    ],
    "sg:phone":"+41 24731320",
    "sg:postcode":"1426",
    "sg:province":"Vaud",
    "wof:name":"Banque Raiffeisen, Du Mont-aubert",
    "wof:placetype":"venue"
},
  "geometry": {"coordinates":[6.7181,46.850109],"type":"Point"}
}