{
  "type": "Feature",
  "properties": {
    "iso:country":"CH",
    "sg:address":"Im Zelgli 11",
    "sg:city":"Habsburg",
    "sg:orig_category":"Grosshandel mit sonstigen Konsumg\u00fctern Sonstiger Grosshandel",
    "sg:phone":"+41 56 450 29 09",
    "sg:postcode":"5245",
    "sg:province":"Aargau",
    "wof:name":"Texis Sa",
    "wof:placetype":"venue"
},
  "geometry": {"coordinates":[8.189368248,47.4618873596],"type":"Point"}
}