{
  "type": "Feature",
  "properties": {
    "iso:country":"CH",
    "sg:address":"Bahnhofstrasse 36",
    "sg:city":"Schwerzenbach",
    "sg:orig_category":"Grossbanken",
    "sg:phone":"+41 12281111",
    "sg:postcode":"8603",
    "sg:province":"Z\u00fcrich",
    "wof:name":"Credit Suisse",
    "wof:placetype":"venue"
},
  "geometry": {"coordinates":[8.5380973816,47.3725090027],"type":"Point"}
}