{
  "type": "Feature",
  "properties": {
    "iso:country":"CH",
    "sg:address":"Hochr\u00fctistrasse 14",
    "sg:city":"Luzern",
    "sg:orig_category":"Erbringung von Dienstleistungen f\u00fcr Unternehmen",
    "sg:postcode":"6005",
    "sg:province":"Luzern",
    "wof:name":"Excess Management Cisotta",
    "wof:placetype":"venue"
},
  "geometry": {"coordinates":[8.3086099625,47.0361061096],"type":"Point"}
}