{
  "type": "Feature",
  "properties": {
    "iso:country":"CH",
    "sg:address":"Rue Du Centre 12",
    "sg:city":"Gorgier",
    "sg:orig_category":"Elektroinstallation",
    "sg:phone":"+41 32 835 26 66",
    "sg:postcode":"2023",
    "sg:province":"Neuch\u00e2tel",
    "wof:name":"Electropro Sa",
    "wof:placetype":"venue"
},
  "geometry": {"coordinates":[6.7805042267,46.9028549194],"type":"Point"}
}