{
  "type": "Feature",
  "properties": {
    "iso:country":"CH",
    "sg:address":"Langenthalerstrasse 421 4803 Vordemwald. Postfach",
    "sg:city":"Vordemwald",
    "sg:orig_category":"Herstellung von Karosserien U Anh\u00e4ngern",
    "sg:phone":"+41 56 282 12 12",
    "sg:postcode":"4803",
    "sg:province":"Aargau",
    "wof:name":"Erwin L\u00fcthi",
    "wof:placetype":"venue"
},
  "geometry": {"coordinates":[8.2826013565,47.4986915588],"type":"Point"}
}