{
  "type": "Feature",
  "properties": {
    "iso:country":"CH",
    "sg:address":"4618 Boningen. Postfach",
    "sg:city":"Boningen",
    "sg:orig_category":"Sportvereine Unihockey",
    "sg:postcode":"4618",
    "sg:province":"Solothurn",
    "wof:name":"Uhc Hurricane Boningen",
    "wof:placetype":"venue"
},
  "geometry": {"coordinates":[7.8518800735,47.3009414673],"type":"Point"}
}