{
  "type": "Feature",
  "properties": {
    "iso:country":"CH",
    "sg:address":"Zollstrasse 33",
    "sg:city":"Thayngen",
    "sg:orig_category":"Instandhaltung U Reparatur von Automobilen",
    "sg:postcode":"8240",
    "sg:province":"Schaffhausen",
    "wof:name":"Auto Center B\u00dchrer Ag",
    "wof:placetype":"venue"
},
  "geometry": {"coordinates":[8.710650444,47.7412605286],"type":"Point"}
}