{
  "type": "Feature",
  "properties": {
    "iso:country":"CH",
    "sg:address":"Z\u00fcrcherstrasse 106 8102 Oberengstringen. Postfach",
    "sg:city":"Oberengstringen",
    "sg:orig_category":"Geb\u00e4ude, Wohnungsreinigung Reinigungsgewerbe",
    "sg:phone":"+41 17511527",
    "sg:postcode":"8102",
    "sg:province":"Z\u00fcrich",
    "wof:name":"Diaz Reinigungen",
    "wof:placetype":"venue"
},
  "geometry": {"coordinates":[8.4655714035,47.4082870483],"type":"Point"}
}