{
  "type": "Feature",
  "properties": {
    "iso:country":"CH",
    "sg:address":"Lettenstrasse 9 6343 Rotkreuz. Postfach",
    "sg:city":"Dietikon",
    "sg:orig_category":"Sonstige mit der Informatik verbundene T\u00e4tigkeiten",
    "sg:postcode":"8953",
    "sg:province":"Z\u00fcrich",
    "wof:name":"Refractionswiss Gmbh",
    "wof:placetype":"venue"
},
  "geometry": {"coordinates":[8.3074617386,46.9880447388],"type":"Point"}
}