{
  "type": "Feature",
  "properties": {
    "iso:country":"CH",
    "sg:address":"Br\u00fcnnenstrasse 62",
    "sg:city":"Bern",
    "sg:orig_category":"Dachdeckerei",
    "sg:phone":"+41 31 991 56 13",
    "sg:postcode":"3018",
    "sg:province":"Bern",
    "wof:name":"Hans Weyermann Dachdeckergesch\u00e4ft",
    "wof:placetype":"venue"
},
  "geometry": {"coordinates":[7.385719,46.943459],"type":"Point"}
}