{
  "type": "Feature",
  "properties": {
    "iso:country":"CH",
    "sg:address":"Wiggiswilweg 9",
    "sg:city":"Jegenstorf",
    "sg:orig_category":"Fachdetailhandel mit pharmazeutischen, medizinischen U kosmetischen Artikeln in Verkaufsr\u00e4umen",
    "sg:phone":"+41 81 416 26 24",
    "sg:postcode":"3303",
    "sg:province":"Bern",
    "wof:name":"Rosmarie Casutt Tiroler Stein\u00f6lprodukte",
    "wof:placetype":"venue"
},
  "geometry": {"coordinates":[9.8374900818,46.807346344],"type":"Point"}
}