{
  "type": "Feature",
  "properties": {
    "iso:country":"CH",
    "sg:address":"Am Bachweg 8 3628 Uttigen. Postfach",
    "sg:city":"Uttigen",
    "sg:orig_category":"Reinigungsgewerbe",
    "sg:phone":"+41 33 345 40 94",
    "sg:postcode":"3628",
    "sg:province":"Bern",
    "wof:name":"Z\u00fcrcher Hans Gmbh Liegenschaftsdienstleistungen, Reinigungen, R\u00e4umungen Usw",
    "wof:placetype":"venue"
},
  "geometry": {"coordinates":[7.574034214,46.7938690186],"type":"Point"}
}