{
  "type": "Feature",
  "properties": {
    "iso:country":"CH",
    "sg:address":"Hashofweg 1",
    "sg:city":"Balsthal",
    "sg:orig_category":"Allgemeiner Hoch U Tiefbau",
    "sg:phone":"+41 62 391 34 32",
    "sg:postcode":"4710",
    "sg:province":"Solothurn",
    "wof:name":"Ziegler-latscha Ag",
    "wof:placetype":"venue"
},
  "geometry": {"coordinates":[7.688437,47.316498],"type":"Point"}
}