{
  "type": "Feature",
  "properties": {
    "addr:full":"Murtenstrasse 28 3210 Kerzers. Postfach 218 Kerzers Fribourg 3210",
    "addr:housenumber":"28;218",
    "addr:postcode":"3210;3210",
    "addr:street":"Murtenstrasse;Postfach",
    "iso:country":"CH",
    "sg:address":"Murtenstrasse 28 3210 Kerzers. Postfach 218",
    "sg:city":"Kerzers",
    "sg:orig_category":"Allgemeiner Hoch U Tiefbau Strassenbau",
    "sg:phone":"+41 31 755 62 34",
    "sg:postcode":"3210",
    "sg:province":"Fribourg",
    "wof:name":"Hans Weibel Ag Bauunternehmung",
    "wof:placetype":"venue"
},
  "geometry": {"coordinates":[7.192123,46.970829],"type":"Point"}
}