{
  "type": "Feature",
  "properties": {
    "iso:country":"CH",
    "sg:address":"3989",
    "sg:city":"Ritzingen",
    "sg:orig_category":"Landwirtschaftliche Genossenschaften",
    "sg:postcode":"3989",
    "sg:province":"Valais",
    "wof:name":"Saatzuchtproduzenten- Genossenschaft Obergoms",
    "wof:placetype":"venue"
},
  "geometry": {"coordinates":[8.2226200104,46.4570388794],"type":"Point"}
}