{
  "type": "Feature",
  "properties": {
    "iso:country":"CH",
    "sg:address":"G\u00f6nhardweg 4",
    "sg:city":"Suhr",
    "sg:orig_category":"Fahrschulen, Flugschulen",
    "sg:phone":"+41 79 420 75 61",
    "sg:postcode":"5034",
    "sg:province":"Aargau",
    "wof:name":"Hansruedi Z\u00fcger Autofahrschule",
    "wof:placetype":"venue"
},
  "geometry": {"coordinates":[8.7878322601,47.32787323],"type":"Point"}
}