{
  "type": "Feature",
  "properties": {
    "iso:country":"CH",
    "sg:address":"Holzgasse 19",
    "sg:city":"Oberrieden",
    "sg:orig_category":"Fotografisches Gewerbe U fotografische Laboratorien",
    "sg:phone":"+41 17209671",
    "sg:postcode":"8942",
    "sg:province":"Z\u00fcrich",
    "wof:name":"Tapprich J\u00fcrgen, Fotoatelier",
    "wof:placetype":"venue"
},
  "geometry": {"coordinates":[8.5697202682,47.2761764526],"type":"Point"}
}