{
  "type": "Feature",
  "properties": {
    "iso:country":"CH",
    "sg:address":"B\u00fchlstrasse 70",
    "sg:city":"Sulgen",
    "sg:orig_category":"RESTAURANTS: TEA-ROOMS",
    "sg:postcode":"8583",
    "sg:province":"Thurgau",
    "wof:name":"Immo Invest Ag",
    "wof:placetype":"venue"
},
  "geometry": {"coordinates":[9.1734676361,47.5421829224],"type":"Point"}
}