{
  "type": "Feature",
  "properties": {
    "iso:country":"CH",
    "sg:address":"Rothausstrasse 61",
    "sg:city":"Muttenz",
    "sg:orig_category":"Interessenvertretungen",
    "sg:phone":"+41 71 747 61 61",
    "sg:postcode":"4132",
    "sg:province":"Basel-Landschaft",
    "wof:name":"Wohlfahrtsstiftung Der Firma Merz-meyer Ag",
    "wof:placetype":"venue"
},
  "geometry": {"coordinates":[9.6488103867,47.4482536316],"type":"Point"}
}