{
  "type": "Feature",
  "properties": {
    "iso:country":"CH",
    "sg:address":"Route De Chardonne 1 1070 Puidoux. Postfach",
    "sg:city":"Puidoux",
    "sg:orig_category":"Wirtschaftsverb\u00e4nde Landwirtschaft",
    "sg:phone":"+41 24 471 25 78",
    "sg:postcode":"1070",
    "sg:province":"Vaud",
    "wof:name":"F\u00e9d.d.st\u00e9s D'horticulture D.l. Suisse Rom.,jean Frachebourg",
    "wof:placetype":"venue"
},
  "geometry": {"coordinates":[6.9586148262,46.2496566772],"type":"Point"}
}