{
  "type": "Feature",
  "properties": {
    "iso:country":"CH",
    "sg:address":"2740",
    "sg:city":"Montagne-moutier",
    "sg:orig_category":"RESTAURANTS: TEA-ROOMS",
    "sg:postcode":"2740",
    "sg:province":"Bern",
    "wof:name":"Geissmann, Bruno",
    "wof:placetype":"venue"
},
  "geometry": {"coordinates":[7.3724632263,47.2787246704],"type":"Point"}
}