{
  "type": "Feature",
  "properties": {
    "iso:country":"CH",
    "sg:address":"Wybergliweg 82",
    "sg:city":"Arth",
    "sg:orig_category":"Handelsvermittlung U Grosshandel Wirtschaftspr\u00fcfung, Steuerberatung U Treuhand",
    "sg:phone":"+41 41 855 59 59",
    "sg:postcode":"6415",
    "sg:province":"Schwyz",
    "wof:name":"Gasser Beat, Dienstleistungen, Beratungen Und Handel",
    "wof:placetype":"venue"
},
  "geometry": {"coordinates":[8.530497551,47.0683937073],"type":"Point"}
}