{
  "type": "Feature",
  "properties": {
    "iso:country":"CH",
    "sg:address":"K\u00f6llikerstrasse 29 5036 Oberentfelden. Postfach",
    "sg:city":"Oberentfelden",
    "sg:orig_category":"D\u00e4mmung gegen K\u00e4lte, W\u00e4rme, Schall U Ersch\u00fctterung Herstellung von sonstigen Metallwaren",
    "sg:phone":"+41 62 723 67 89",
    "sg:postcode":"5036",
    "sg:province":"Aargau",
    "wof:name":"Eubo D\u00e4mmtechnik Ag",
    "wof:placetype":"venue"
},
  "geometry": {"coordinates":[8.043800354,47.353553772],"type":"Point"}
}