{
  "type": "Feature",
  "properties": {
    "iso:country":"CH",
    "sg:address":"Weidstrasse 16 9220 Bischofszell. Postfach",
    "sg:city":"Bischofszell",
    "sg:orig_category":"Non-Classified Establishments",
    "sg:postcode":"9220",
    "sg:province":"Thurgau",
    "wof:name":"Haus + Herd Typenhaus Ag, Zweigniederlassung Wil",
    "wof:placetype":"venue"
},
  "geometry": {"coordinates":[9.0610332489,47.4635124207],"type":"Point"}
}