{
  "type": "Feature",
  "properties": {
    "iso:country":"CH",
    "sg:address":"March\u00e9 Place Du 3",
    "sg:city":"Echallens",
    "sg:orig_category":"Sonstiges Verlagsgewerbe",
    "sg:phone":"+41 21 881 50 69",
    "sg:postcode":"1040",
    "sg:province":"Vaud",
    "wof:name":"D\u00e9tour, Jaccard Sylvie",
    "wof:placetype":"venue"
},
  "geometry": {"coordinates":[6.6343631744,46.6408653259],"type":"Point"}
}