{
  "type": "Feature",
  "properties": {
    "iso:country":"CH",
    "sg:address":"Kirchstrasse 9",
    "sg:city":"M\u00f6hlin",
    "sg:orig_category":"Detailhandel mit Beleuchtungs U Haushaltsgegenst\u00e4nden Detailhandel mit Metallwaren, Anstrichmitteln,",
    "sg:phone":"+41 61 851 36 46",
    "sg:postcode":"4313",
    "sg:province":"Aargau",
    "wof:name":"Schmid Kurt",
    "wof:placetype":"venue"
},
  "geometry": {"coordinates":[7.841971,47.55714],"type":"Point"}
}