{
  "type": "Feature",
  "properties": {
    "iso:country":"CH",
    "sg:address":"Route D'evian 1845 Noville Case Postale 67",
    "sg:city":"Noville",
    "sg:orig_category":"Grosshandel mit Kaffee, Tee, Kakao U Gew\u00fcrzen",
    "sg:phone":"+41 21 960 14 84",
    "sg:postcode":"1845",
    "sg:province":"Vaud",
    "wof:name":"Milliquet J.a. Sa Th\u00e9s Et Herboristerie En Gros",
    "wof:placetype":"venue"
},
  "geometry": {"coordinates":[6.900081,46.381886],"type":"Point"}
}