{
  "type": "Feature",
  "properties": {
    "iso:country":"CH",
    "sg:address":"Tribschenstrasse 64 6005 Luzern. Postfach",
    "sg:city":"Luzern",
    "sg:orig_category":"Handel mit Automobilen",
    "sg:phone":"+41 41 360 66 77",
    "sg:postcode":"6005",
    "sg:province":"Luzern",
    "wof:name":"Galliker Handels Ag, Luzern Fahrzeuge, Autozubeh\u00f6r Usw; Handel",
    "wof:placetype":"venue"
},
  "geometry": {"coordinates":[8.3174858093,47.0422554016],"type":"Point"}
}