{
  "type": "Feature",
  "properties": {
    "iso:country":"CH",
    "sg:address":"Stauberbergstrasse 24",
    "sg:city":"Uster",
    "sg:orig_category":"Sportvereine Ballsport Volleyball",
    "sg:phone":"+41 19414637",
    "sg:postcode":"8610",
    "sg:province":"Z\u00fcrich",
    "wof:name":"Volleyball-club Volketswil",
    "wof:placetype":"venue"
},
  "geometry": {"coordinates":[8.7151899338,47.3495101929],"type":"Point"}
}