{
  "type": "Feature",
  "properties": {
    "iso:country":"CH",
    "sg:address":"Seftigenstrasse 302",
    "sg:city":"Wabern",
    "sg:orig_category":"Detailhandel mit Milcherzeugnissen U Eiern Sonstiger Fachdetailhandel mit Nahrungsmitteln, Getr\u00e4nken",
    "sg:phone":"+41 31 961 12 47",
    "sg:postcode":"3084",
    "sg:province":"Bern",
    "wof:name":"Fritz & Therese Walther K\u00e4sespezialit\u00e4ten",
    "wof:placetype":"venue"
},
  "geometry": {"coordinates":[7.4545049667,46.9270820618],"type":"Point"}
}