{
  "type": "Feature",
  "properties": {
    "iso:country":"CH",
    "sg:address":"Via Trevano 61",
    "sg:city":"Lugano",
    "sg:orig_category":"Bauingenieurb\u00fcros allgemein",
    "sg:phone":"+41 91 967 35 45",
    "sg:postcode":"6900",
    "sg:province":"Ticino",
    "wof:name":"Alfio Casanova Studio D'ingegneria",
    "wof:placetype":"venue"
},
  "geometry": {"coordinates":[8.956361,46.017883],"type":"Point"}
}