{
  "type": "Feature",
  "properties": {
    "iso:country":"CH",
    "sg:address":"Buchserstrasse 25",
    "sg:city":"D\u00e4llikon",
    "sg:orig_category":"Grosshandel mit Baumaschinen Vermietung von Baumaschinen U ger\u00e4ten",
    "sg:postcode":"8108",
    "sg:province":"Z\u00fcrich",
    "wof:name":"Wolffkran Schweiz Ag",
    "wof:placetype":"venue"
},
  "geometry": {"coordinates":[8.4384679794,47.4459152222],"type":"Point"}
}