{
  "type": "Feature",
  "properties": {
    "iso:country":"CH",
    "sg:address":"Sommeristr. 37 A",
    "sg:city":"Amriswil",
    "sg:classifiers":[
        {
            "category":"Food & Beverages",
            "subcategory":"Fruits & Vegetables",
            "type":"Retail Goods"
        }
    ],
    "sg:phone":"+41 71 744 32 33",
    "sg:postcode":"8580",
    "sg:province":"Thurgau",
    "sg:tags":[
        "frozen",
        "product",
        "related"
    ],
    "wof:name":"Frigaliment Import Gmbh",
    "wof:placetype":"venue"
},
  "geometry": {"coordinates":[9.6407613754,47.4516792297],"type":"Point"}
}