{
  "type": "Feature",
  "properties": {
    "iso:country":"CH",
    "sg:address":"Gertrudstrasse 37",
    "sg:city":"Z\u00fcrich",
    "sg:orig_category":"RESTAURANTS: TEA-ROOMS",
    "sg:phone":"+41 14513231",
    "sg:postcode":"8003",
    "sg:province":"Z\u00fcrich",
    "wof:name":"Restaurant Da Michelangelo R. Morelli Cerullo",
    "wof:placetype":"venue"
},
  "geometry": {"coordinates":[8.5151767731,47.3733215332],"type":"Point"}
}