{
  "type": "Feature",
  "properties": {
    "iso:country":"CH",
    "sg:address":"Chemin Bois-de-ban 56",
    "sg:city":"Epalinges",
    "sg:orig_category":"Allgemeiner Hoch U Tiefbau Maurerarbeiten",
    "sg:phone":"+41 21 784 35 35",
    "sg:postcode":"1066",
    "sg:province":"Vaud",
    "wof:name":"Talloru Alfio Sa",
    "wof:placetype":"venue"
},
  "geometry": {"coordinates":[6.663705,46.558792],"type":"Point"}
}