{
  "type": "Feature",
  "properties": {
    "iso:country":"CH",
    "sg:address":"Silbernstrasse 12 8953 Dietikon. Postfach",
    "sg:city":"Dietikon",
    "sg:orig_category":"Non-Classified Establishments",
    "sg:postcode":"8953",
    "sg:province":"Z\u00fcrich",
    "wof:name":"Smrqi Asllan Transport Transporte Von Kies U. Sand",
    "wof:placetype":"venue"
},
  "geometry": {"coordinates":[8.3954229355,47.4169120789],"type":"Point"}
}