{
  "type": "Feature",
  "properties": {
    "iso:country":"CH",
    "sg:address":"Luzernerstrasse 50 6014 Littau. Postfach",
    "sg:city":"Littau",
    "sg:orig_category":"Fachdetailhandel in Verkaufsr\u00e4umen Grosshandel mit B\u00fcromaschinen",
    "sg:phone":"+41 41 250 46 33",
    "sg:postcode":"6014",
    "sg:province":"Luzern",
    "wof:name":"Aregger Kassensysteme Gmbh Registrierkassen; Handel, Reparaturen, Revisionen Usw",
    "wof:placetype":"venue"
},
  "geometry": {"coordinates":[8.2778301239,47.0520401001],"type":"Point"}
}