{
  "type": "Feature",
  "properties": {
    "iso:country":"CH",
    "sg:address":"Oberdorf 185",
    "sg:city":"Ramsen",
    "sg:classifiers":[
        {
            "category":"Social Services",
            "subcategory":"Retirement Home",
            "type":"Services"
        }
    ],
    "sg:phone":"+41 41 670 25 22",
    "sg:postcode":"8262",
    "sg:province":"Schaffhausen",
    "sg:tags":[
        "pflegeheime",
        "u",
        "alters"
    ],
    "wof:name":"Alterszentrum Allmend",
    "wof:placetype":"venue"
},
  "geometry": {"coordinates":[8.276644,46.943516],"type":"Point"}
}