{
  "type": "Feature",
  "properties": {
    "iso:country":"CH",
    "sg:address":"Wydenstrasse 28",
    "sg:city":"Winterthur",
    "sg:orig_category":"Detailhandel mit Teppichen Verlegen von Fussboden",
    "sg:phone":"+41 79 607 31 51",
    "sg:postcode":"8408",
    "sg:province":"Z\u00fcrich",
    "wof:name":"Andreas Burkhard Innendekorationen",
    "wof:placetype":"venue"
},
  "geometry": {"coordinates":[7.5272288322,46.9313926697],"type":"Point"}
}