{
  "type": "Feature",
  "properties": {
    "iso:country":"CH",
    "sg:address":"\u00d6ltrotte 14",
    "sg:city":"Ennetb\u00fcrgen",
    "sg:orig_category":"Architektur U Ingenieurb\u00fcros",
    "sg:postcode":"6373",
    "sg:province":"Nidwalden",
    "wof:name":"Ingesic Gmbh",
    "wof:placetype":"venue"
},
  "geometry": {"coordinates":[8.407441,46.984657],"type":"Point"}
}