{
  "type": "Feature",
  "properties": {
    "iso:country":"CH",
    "sg:address":"Ziegelmatt 41",
    "sg:city":"Diegten",
    "sg:orig_category":"Non-Classified Establishments",
    "sg:postcode":"4457",
    "sg:province":"Basel-Landschaft",
    "wof:name":"Kompaktbau Gmbh",
    "wof:placetype":"venue"
},
  "geometry": {"coordinates":[7.8088989258,47.4061660767],"type":"Point"}
}