{
  "type": "Feature",
  "properties": {
    "iso:country":"CH",
    "sg:address":"Wengistrasse 13",
    "sg:city":"Solothurn",
    "sg:classifiers":[
        {
            "category":"Travel",
            "subcategory":"Hotels & Motels",
            "type":"Entertainment"
        }
    ],
    "sg:phone":"+41 32 622 75 71",
    "sg:postcode":"4500",
    "sg:province":"Solothurn",
    "sg:tags":[
        "hotels",
        "mit",
        "restaurant"
    ],
    "wof:name":"Hotel Astoria",
    "wof:placetype":"venue"
},
  "geometry": {"coordinates":[7.5333871841,47.2067909241],"type":"Point"}
}