{
  "type": "Feature",
  "properties": {
    "iso:country":"CH",
    "sg:address":"Hofackerstrasse 3a",
    "sg:city":"Muttenz",
    "sg:orig_category":"Wirtschaftspr\u00fcfung, Steuerberatung U Treuhand",
    "sg:phone":"+41 32 721 44 01",
    "sg:postcode":"4132",
    "sg:province":"Basel-Landschaft",
    "wof:name":"Agence De Service Fiduciaire Et G\u00e9rance Afg Sa",
    "wof:placetype":"venue"
},
  "geometry": {"coordinates":[6.9320201874,46.9905128479],"type":"Point"}
}