{
  "type": "Feature",
  "properties": {
    "iso:country":"CH",
    "sg:address":"K\u00e4tzigen",
    "sg:city":"Dagmersellen",
    "sg:orig_category":"Grosshandel mit lebenden Tieren",
    "sg:phone":"+41 62 756 15 20",
    "sg:postcode":"6252",
    "sg:province":"Luzern",
    "wof:name":"Troxler Anton",
    "wof:placetype":"venue"
},
  "geometry": {"coordinates":[8.0185556412,47.1977920532],"type":"Point"}
}