{
  "type": "Feature",
  "properties": {
    "iso:country":"CH",
    "sg:address":"Gubelstrasse 2",
    "sg:city":"Z\u00fcrich",
    "sg:orig_category":"Detailhandel mit Musikinstrumenten K\u00fcnstlerische Schulen",
    "sg:phone":"+41 13119745",
    "sg:postcode":"8050",
    "sg:province":"Z\u00fcrich",
    "wof:name":"Roger Enzler",
    "wof:placetype":"venue"
},
  "geometry": {"coordinates":[8.5465698242,47.4077796936],"type":"Point"}
}