{
  "type": "Feature",
  "properties": {
    "addr:full":"Via Vanoni 6 Lugano Ticino 6900",
    "addr:housenumber":"6",
    "addr:postcode":"6900",
    "addr:street":"Via Vanoni",
    "iso:country":"CH",
    "sg:address":"Via Vanoni 6",
    "sg:city":"Lugano",
    "sg:orig_category":"Advokaturb\u00fcros",
    "sg:phone":"+41 91 923 96 79",
    "sg:postcode":"6900",
    "sg:province":"Ticino",
    "wof:name":"Luisa Biaggini Studio Legale",
    "wof:placetype":"venue"
},
  "geometry": {"coordinates":[8.953685,46.011196],"type":"Point"}
}