{
  "type": "Feature",
  "properties": {
    "iso:country":"CH",
    "sg:address":"Avenue Des Alpes 70",
    "sg:city":"Montreux",
    "sg:orig_category":"Fachdetailhandel in Verkaufsr\u00e4umen",
    "sg:postcode":"1820",
    "sg:province":"Vaud",
    "wof:name":"Hofer Sports, Mme",
    "wof:placetype":"venue"
},
  "geometry": {"coordinates":[6.9105529785,46.4352836609],"type":"Point"}
}