{
  "type": "Feature",
  "properties": {
    "iso:country":"CH",
    "sg:address":"Ackerstrasse 2 8180 B\u00fclach. Postfach",
    "sg:city":"B\u00fclach",
    "sg:orig_category":"Grosshandel mit sonstigen Maschinen U Ausr\u00fcstungen f\u00fcr Industrie, Handel U Schiffahrt",
    "sg:postcode":"8180",
    "sg:province":"Z\u00fcrich",
    "wof:name":"Cleansystems Ag Reinigungsger\u00e4te; Entwicklung, Produktion, Handel. Lizenzen; Vergabe Usw",
    "wof:placetype":"venue"
},
  "geometry": {"coordinates":[8.5423431396,47.5085754395],"type":"Point"}
}