{
  "type": "Feature",
  "properties": {
    "addr:full":"Bahnhofstrasse 22 3800 Interlaken. Postfach 611 Interlaken Bern 3800",
    "addr:housenumber":"22;611",
    "addr:postcode":"3800;3800",
    "addr:street":"Bahnhofstrasse;Postfach",
    "iso:country":"CH",
    "sg:address":"Bahnhofstrasse 22 3800 Interlaken. Postfach 611",
    "sg:city":"Interlaken",
    "sg:orig_category":"Architektur U Ingenieurb\u00fcros Innenarchitekturb\u00fcros",
    "sg:phone":"+41 33 823 15 50",
    "sg:postcode":"3800",
    "sg:province":"Bern",
    "wof:name":"Forum 4 Ag F\u00fcr Architektur",
    "wof:placetype":"venue"
},
  "geometry": {"coordinates":[7.8517,46.68317],"type":"Point"}
}