{
  "type": "Feature",
  "properties": {
    "iso:country":"CH",
    "sg:address":"Teufener Strasse 25a",
    "sg:city":"Speicher",
    "sg:orig_category":"Physiotherapie",
    "sg:phone":"+41 71 344 30 34",
    "sg:postcode":"9042",
    "sg:province":"Appenzell Ausserrhoden",
    "wof:name":"Martina Schmidheini Physiotherapie",
    "wof:placetype":"venue"
},
  "geometry": {"coordinates":[9.4418001175,47.4061050415],"type":"Point"}
}