{
  "type": "Feature",
  "properties": {
    "iso:country":"CH",
    "sg:address":"Oetwilerstrasse 27",
    "sg:city":"Dietikon",
    "sg:orig_category":"Herstellung von konfektionierten Textilwaren ohne Bekleidung",
    "sg:postcode":"8953",
    "sg:province":"Z\u00fcrich",
    "wof:name":"Moser Storen",
    "wof:placetype":"venue"
},
  "geometry": {"coordinates":[8.3974475861,47.40832901],"type":"Point"}
}