{
  "type": "Feature",
  "properties": {
    "iso:country":"CH",
    "sg:address":"R\u00fctistrasse 38",
    "sg:city":"Gockhausen",
    "sg:orig_category":"Interessenvertretungen",
    "sg:postcode":"8044",
    "sg:province":"Z\u00fcrich",
    "wof:name":"Stiftung Baukultur",
    "wof:placetype":"venue"
},
  "geometry": {"coordinates":[8.5953874588,47.3834571838],"type":"Point"}
}