{
  "type": "Feature",
  "properties": {
    "iso:country":"CH",
    "sg:address":"Bahnhofstrasse 9",
    "sg:city":"Jegenstorf",
    "sg:orig_category":"Grosshandel mit B\u00fcromaschinen Grosshandel mit Datenverarbeitungsger\u00e4ten",
    "sg:phone":"+41 31 761 11 91",
    "sg:postcode":"3303",
    "sg:province":"Bern",
    "wof:name":"Wehren Emcom",
    "wof:placetype":"venue"
},
  "geometry": {"coordinates":[7.5075531006,47.0481071472],"type":"Point"}
}