{
  "type": "Feature",
  "properties": {
    "iso:country":"CH",
    "sg:address":"Fliederweg 29",
    "sg:city":"Chur",
    "sg:orig_category":"Finanzierungsinstitutionen",
    "sg:postcode":"7000",
    "sg:province":"Graubunden",
    "wof:name":"Coninvest Chur Gmbh",
    "wof:placetype":"venue"
},
  "geometry": {"coordinates":[9.5181188583,46.8539123535],"type":"Point"}
}