{
  "type": "Feature",
  "properties": {
    "iso:country":"CH",
    "sg:address":"Buchens\u00e4ge",
    "sg:city":"Menzberg",
    "sg:orig_category":"S\u00e4ge, Hobel U Holzimpr\u00e4gnierwerke S\u00e4gewerke",
    "sg:phone":"+41 41 493 12 64",
    "sg:postcode":"6125",
    "sg:province":"Luzern",
    "wof:name":"S\u00e4gewerk H\u00e4fliger Ag",
    "wof:placetype":"venue"
},
  "geometry": {"coordinates":[7.9971408844,47.0369300842],"type":"Point"}
}