{
  "type": "Feature",
  "properties": {
    "iso:country":"CH",
    "sg:address":"Gutenbergstrasse 1",
    "sg:city":"Bern",
    "sg:classifiers":[
        {
            "category":"Education",
            "subcategory":"Library",
            "type":"Public Place"
        }
    ],
    "sg:phone":"+41 71 227 33 63",
    "sg:postcode":"3011",
    "sg:province":"Bern",
    "sg:tags":[
        "u",
        "bibliotheken",
        "archive"
    ],
    "wof:name":"Bibliothek Der Bisch\u00f6flichen Kanzlei",
    "wof:placetype":"venue"
},
  "geometry": {"coordinates":[9.377725,47.423374],"type":"Point"}
}