{
  "type": "Feature",
  "properties": {
    "iso:country":"CH",
    "sg:address":"Grand-mont Route Du 25",
    "sg:city":"Mont-sur-lausanne",
    "sg:orig_category":"Detailhandel mit Metallwaren, Anstrichmitteln, Glaswaren, Bau U Heimwerkerbedarf",
    "sg:phone":"+41 19103232",
    "sg:postcode":"1052",
    "sg:province":"Vaud",
    "wof:name":"Colores Decor Ag",
    "wof:placetype":"venue"
},
  "geometry": {"coordinates":[8.5914077759,47.3199501038],"type":"Point"}
}