{
  "type": "Feature",
  "properties": {
    "iso:country":"CH",
    "sg:address":"St. Florinsgasse 1",
    "sg:city":"Vaduz",
    "sg:orig_category":"K\u00fcnstlerische Schulen",
    "sg:postcode":"9490",
    "wof:name":"Liechtensteinische Musikschule",
    "wof:placetype":"venue"
},
  "geometry": {"coordinates":[9.5227804184,47.1368293762],"type":"Point"}
}