{
  "type": "Feature",
  "properties": {
    "iso:country":"CH",
    "sg:address":"Oberdorfgasse 13",
    "sg:city":"Frutigen",
    "sg:orig_category":"Reinigungsgewerbe",
    "sg:phone":"+41 33711188",
    "sg:postcode":"3714",
    "sg:province":"Bern",
    "wof:name":"Egger & Co., Vormals Trachsel Tankrevisionen",
    "wof:placetype":"venue"
},
  "geometry": {"coordinates":[7.6464519501,46.5897827148],"type":"Point"}
}