{
  "type": "Feature",
  "properties": {
    "addr:full":"Oberstufenschulhaus Wattwil St. Gallen 9630",
    "addr:postcode":"9630",
    "iso:country":"CH",
    "sg:address":"Oberstufenschulhaus",
    "sg:city":"Wattwil",
    "sg:orig_category":"Bezirks, Sekundar, Realschulen, Oberstufe der Primarschulen",
    "sg:postcode":"9630",
    "sg:province":"St. Gallen",
    "wof:name":"Real-& Sekundarschule Risi",
    "wof:placetype":"venue"
},
  "geometry": {"coordinates":[9.086835,47.299656],"type":"Point"}
}