{
  "type": "Feature",
  "properties": {
    "iso:country":"CH",
    "sg:address":"Bahnhofstrasse 54",
    "sg:city":"D\u00fcbendorf",
    "sg:orig_category":"RESTAURANTS: TEA-ROOMS",
    "sg:postcode":"8600",
    "sg:province":"Z\u00fcrich",
    "wof:name":"Restaurant, Neuhof, Rutishauser Lilo",
    "wof:placetype":"venue"
},
  "geometry": {"coordinates":[8.6218910217,47.3994483948],"type":"Point"}
}