{
  "type": "Feature",
  "properties": {
    "iso:country":"CH",
    "sg:address":"En Budron C7 1052 Mont-sur-lausanne Case Postale",
    "sg:city":"Mont-sur-lausanne",
    "sg:orig_category":"Grosshandel mit chemischen Erzeugnissen Rechtsberatung",
    "sg:phone":"+41 41 610 55 02",
    "sg:postcode":"1052",
    "sg:province":"Vaud",
    "wof:name":"Cadisa Cleaning Systems Meyer W. & Co",
    "wof:placetype":"venue"
},
  "geometry": {"coordinates":[8.3111009598,46.9864387512],"type":"Point"}
}