{
  "type": "Feature",
  "properties": {
    "iso:country":"CH",
    "sg:address":"Libernstrasse 24",
    "sg:city":"Otelfingen",
    "sg:orig_category":"Grosshandel mit Datenverarbeitungsger\u00e4ten",
    "sg:phone":"+41 18474545",
    "sg:postcode":"8112",
    "sg:province":"Z\u00fcrich",
    "wof:name":"Dolphins Network Systems Ag",
    "wof:placetype":"venue"
},
  "geometry": {"coordinates":[8.4009981155,47.4587898254],"type":"Point"}
}