{
  "type": "Feature",
  "properties": {
    "iso:country":"CH",
    "sg:address":"Bernstrasse 40",
    "sg:city":"Ostermundigen",
    "sg:orig_category":"Kosmetikinstitute",
    "sg:phone":"+41 31 931 59 57",
    "sg:postcode":"3072",
    "sg:province":"Bern",
    "wof:name":"Martha Keller Kosmetikinstitut",
    "wof:placetype":"venue"
},
  "geometry": {"coordinates":[7.4846739769,46.9566764832],"type":"Point"}
}