{
  "type": "Feature",
  "properties": {
    "iso:country":"CH",
    "sg:address":"Dorfstrasse 2",
    "sg:city":"Mogelsberg",
    "sg:orig_category":"Einzelhandel mit Automobilen Instandhaltung U Reparatur von Automobilen",
    "sg:phone":"+41 71 374 24 24",
    "sg:postcode":"9122",
    "sg:province":"St. Gallen",
    "wof:name":"Sonnenberg-garage Mogelsberg Ag",
    "wof:placetype":"venue"
},
  "geometry": {"coordinates":[9.1340761185,47.3625411987],"type":"Point"}
}