{
  "type": "Feature",
  "properties": {
    "iso:country":"CH",
    "sg:address":"Luegetenstrasse 30",
    "sg:city":"Menzingen",
    "sg:orig_category":"Unternehmensberatung",
    "sg:phone":"+41 41 755 19 14",
    "sg:postcode":"6313",
    "sg:province":"Zug",
    "wof:name":"Hjb Consultants Gmbh",
    "wof:placetype":"venue"
},
  "geometry": {"coordinates":[8.5960197449,47.177066803],"type":"Point"}
}