{
  "type": "Feature",
  "properties": {
    "iso:country":"CH",
    "sg:address":"Allmendstrasse 7",
    "sg:city":"Liestal",
    "sg:orig_category":"Handelsvermittlung U Grosshandel Sonstiger Grosshandel",
    "sg:phone":"+41 61 921 39 36",
    "sg:postcode":"4410",
    "sg:province":"Basel-Landschaft",
    "wof:name":"Niclas Ag",
    "wof:placetype":"venue"
},
  "geometry": {"coordinates":[7.7407717705,47.481628418],"type":"Point"}
}