{
  "type": "Feature",
  "properties": {
    "iso:country":"CH",
    "sg:address":"Bergstrasse 8 8712 St\u00e4fa. Postfach",
    "sg:city":"St\u00e4fa",
    "sg:orig_category":"Grosshandel mit sonstigen Maschinen U Ausr\u00fcstungen f\u00fcr Industrie, Handel U Schiffahrt",
    "sg:phone":"+41 19263400",
    "sg:postcode":"8712",
    "sg:province":"Z\u00fcrich",
    "wof:name":"Heinz E. Weber Industrievertretungen",
    "wof:placetype":"venue"
},
  "geometry": {"coordinates":[8.720911026,47.2415313721],"type":"Point"}
}