{
  "type": "Feature",
  "properties": {
    "iso:country":"CH",
    "sg:address":"Chanel Via Dal",
    "sg:city":"Silvaplana",
    "sg:orig_category":"Softwareentwicklung U beratung",
    "sg:postcode":"7513",
    "sg:province":"Graubunden",
    "wof:name":"Heinz Vogel Maschinen Ag",
    "wof:placetype":"venue"
},
  "geometry": {"coordinates":[8.2055673599,47.1153373718],"type":"Point"}
}