{
  "type": "Feature",
  "properties": {
    "iso:country":"CH",
    "sg:address":"Sch\u00f6ngrund 9",
    "sg:city":"Rotkreuz",
    "sg:orig_category":"Unclassifiable Establishments",
    "sg:postcode":"6343",
    "sg:province":"Zug",
    "wof:name":"Solar Und Sicherheitstechnik Pius Sturzenegger",
    "wof:placetype":"venue"
},
  "geometry": {"coordinates":[8.4275913239,47.1440887451],"type":"Point"}
}