{
  "type": "Feature",
  "properties": {
    "iso:country":"CH",
    "sg:address":"Neugasse 27 6300 Zug. Postfach 339",
    "sg:city":"Zug",
    "sg:orig_category":"Detailhandel mit Uhren U Schmuck Fachdetailhandel in Verkaufsr\u00e4umen",
    "sg:phone":"+41 41 710 72 72",
    "sg:postcode":"6301",
    "sg:province":"Zug",
    "wof:name":"Atelier Wassmann",
    "wof:placetype":"venue"
},
  "geometry": {"coordinates":[8.5155410767,47.1662597656],"type":"Point"}
}