{
  "type": "Feature",
  "properties": {
    "iso:country":"CH",
    "sg:address":"Witikonerstrasse 409",
    "sg:city":"Z\u00fcrich",
    "sg:orig_category":"Physiotherapie",
    "sg:phone":"+41 14222260",
    "sg:postcode":"8053",
    "sg:province":"Z\u00fcrich",
    "wof:name":"Patricia Schori Physiotherapie & Akupunktur",
    "wof:placetype":"venue"
},
  "geometry": {"coordinates":[8.5947008133,47.3599967957],"type":"Point"}
}