{
  "type": "Feature",
  "properties": {
    "iso:country":"CH",
    "sg:address":"Gare Avenue De La 2",
    "sg:city":"Montagne-moutier",
    "sg:orig_category":"Elektroinstallation",
    "sg:phone":"+41 17370448",
    "sg:postcode":"2740",
    "sg:province":"Bern",
    "wof:name":"Ren\u00e9 Cesaro Elektro-techn.unternehmungen",
    "wof:placetype":"venue"
},
  "geometry": {"coordinates":[8.4597501755,47.3625984192],"type":"Point"}
}