{
  "type": "Feature",
  "properties": {
    "iso:country":"CH",
    "sg:address":"Grange-canal Chemin De 21 1208 Gen\u00e8ve. Postfach",
    "sg:city":"Gen\u00e8ve",
    "sg:orig_category":"Non-Classified Establishments",
    "sg:postcode":"1208",
    "sg:province":"Gen\u00e8ve",
    "wof:name":"Si Etoile-palettes N",
    "wof:placetype":"venue"
},
  "geometry": {"coordinates":[6.1399769783,46.185333252],"type":"Point"}
}