{
  "type": "Feature",
  "properties": {
    "iso:country":"CH",
    "sg:address":"Bahnhofstrasse 4",
    "sg:city":"R\u00fcmlang",
    "sg:orig_category":"Korrespondenz U Nachrichtenb\u00fcros, selbst\u00e4ndige Journalisten",
    "sg:postcode":"8153",
    "sg:province":"Z\u00fcrich",
    "wof:name":"Press-office Sturzenegger",
    "wof:placetype":"venue"
},
  "geometry": {"coordinates":[8.5286235809,47.4522819519],"type":"Point"}
}