{
  "type": "Feature",
  "properties": {
    "iso:country":"CH",
    "sg:address":"Oberdorfstrasse 32",
    "sg:city":"Steffisburg",
    "sg:classifiers":[
        {
            "category":"Travel",
            "subcategory":"Hotels & Motels",
            "type":"Entertainment"
        }
    ],
    "sg:phone":"+41 33 437 24 37",
    "sg:postcode":"3612",
    "sg:province":"Bern",
    "sg:tags":[
        "hotels",
        "mit",
        "restaurant"
    ],
    "wof:name":"Iseli H.",
    "wof:placetype":"venue"
},
  "geometry": {"coordinates":[7.634016037,46.780582428],"type":"Point"}
}