{
  "type": "Feature",
  "properties": {
    "iso:country":"CH",
    "sg:address":"Quatre-communes Rte Des",
    "sg:city":"Rolle",
    "sg:orig_category":"Softwareentwicklung U beratung",
    "sg:postcode":"1180",
    "sg:province":"Vaud",
    "wof:name":"Si Facile - Morel",
    "wof:placetype":"venue"
},
  "geometry": {"coordinates":[6.3335299492,46.4593467712],"type":"Point"}
}