{
  "type": "Feature",
  "properties": {
    "iso:country":"CH",
    "sg:address":"Industriestrasse",
    "sg:city":"Reiden",
    "sg:orig_category":"Herstellung von Metallkonstruktionen Zimmerei, Ingenieurholzbau",
    "sg:phone":"+41 62 758 19 80",
    "sg:postcode":"6260",
    "sg:province":"Luzern",
    "wof:name":"Stallbau Nirox Ag",
    "wof:placetype":"venue"
},
  "geometry": {"coordinates":[7.9653100967,47.2532463074],"type":"Point"}
}