{
  "type": "Feature",
  "properties": {
    "iso:country":"CH",
    "sg:address":"K\u00f6nizstrasse 269 3097 Liebefeld. Postfach",
    "sg:city":"Liebefeld",
    "sg:orig_category":"Detailhandel mit Getr\u00e4nken Grosshandel mit Getr\u00e4nken",
    "sg:phone":"+41 31 971 11 55",
    "sg:postcode":"3097",
    "sg:province":"Bern",
    "wof:name":"Wein- & Geschenkboutique Geiser",
    "wof:placetype":"venue"
},
  "geometry": {"coordinates":[7.4167327881,46.9278869629],"type":"Point"}
}