{
  "type": "Feature",
  "properties": {
    "iso:country":"CH",
    "sg:address":"Wiesholzerstrasse 396",
    "sg:city":"Ramsen",
    "sg:orig_category":"Softwareentwicklung U beratung",
    "sg:postcode":"8262",
    "sg:province":"Schaffhausen",
    "wof:name":"Camedia Gmbh",
    "wof:placetype":"venue"
},
  "geometry": {"coordinates":[8.8225164413,47.7086791992],"type":"Point"}
}