{
  "type": "Feature",
  "properties": {
    "iso:country":"CH",
    "sg:address":"Englischviertelstrasse 56 8032 Z\u00fcrich 32 Zust. Postfach 1328 8032 Z\u00fcrich",
    "sg:city":"Zust",
    "sg:orig_category":"Sonstiger Grosshandel",
    "sg:phone":"+41 13830343",
    "sg:postcode":"32",
    "wof:name":"Promotop Gmbh",
    "wof:placetype":"venue"
},
  "geometry": {"coordinates":[8.5679702759,47.3668403625],"type":"Point"}
}