{
  "type": "Feature",
  "properties": {
    "iso:country":"CH",
    "sg:address":"Wallisellenstrasse 11",
    "sg:city":"Z\u00fcrich",
    "sg:classifiers":[
        {
            "category":"Restaurant",
            "type":"Food & Drink"
        }
    ],
    "sg:phone":"+41 13113117",
    "sg:postcode":"8050",
    "sg:province":"Z\u00fcrich",
    "wof:name":"Osteria Pizzeria Il Pappagallo",
    "wof:placetype":"venue"
},
  "geometry": {"coordinates":[8.5484867096,47.4105186462],"type":"Point"}
}