{
  "type": "Feature",
  "properties": {
    "iso:country":"CH",
    "sg:address":"Corso San Gottardo 10",
    "sg:city":"Chiasso",
    "sg:classifiers":[
        {
            "category":"Professional",
            "subcategory":"Employment Agencies",
            "type":"Services"
        }
    ],
    "sg:phone":"+41 31 372 60 20",
    "sg:postcode":"6830",
    "sg:province":"Ticino",
    "sg:tags":[
        "personal",
        "u",
        "stellenvermittlung"
    ],
    "wof:name":"Swing Personal Ag",
    "wof:placetype":"venue"
},
  "geometry": {"coordinates":[7.4305739403,46.9415054321],"type":"Point"}
}