{
  "type": "Feature",
  "properties": {
    "iso:country":"CH",
    "sg:address":"Weiermattstrasse 2",
    "sg:city":"Sch\u00f6nenwerd",
    "sg:orig_category":"Vorschulen, Kinderg\u00e4rten",
    "sg:phone":"+41 61 791 90 62",
    "sg:postcode":"5012",
    "sg:province":"Solothurn",
    "wof:name":"Kindergarten Weihermatt",
    "wof:placetype":"venue"
},
  "geometry": {"coordinates":[7.5914649963,47.4976997375],"type":"Point"}
}