{
  "type": "Feature",
  "properties": {
    "iso:country":"CH",
    "sg:address":"Incella",
    "sg:city":"Brissago",
    "sg:orig_category":"Sportvereine Velo Rad-& Motorfahrer-Bund SRB",
    "sg:phone":"+41 91 793 10 84",
    "sg:postcode":"6614",
    "sg:province":"Ticino",
    "wof:name":"Velo-club Brissago",
    "wof:placetype":"venue"
},
  "geometry": {"coordinates":[8.7016801834,46.1166000366],"type":"Point"}
}