{
  "type": "Feature",
  "properties": {
    "iso:country":"CH",
    "sg:address":"Industriestr. 38",
    "sg:city":"Kleind\u00f6ttingen",
    "sg:classifiers":[
        {
            "category":"Home & Garden",
            "subcategory":"Furniture",
            "type":"Retail Goods"
        }
    ],
    "sg:phone":"+41 56 268 82 11",
    "sg:postcode":"5314",
    "sg:province":"Aargau",
    "sg:tags":[
        "wood"
    ],
    "wof:name":"Hpm Sortimente",
    "wof:placetype":"venue"
},
  "geometry": {"coordinates":[8.237695694,47.575969696],"type":"Point"}
}