{
  "type": "Feature",
  "properties": {
    "addr:full":"Chemin Des Comtoises 8 Vernier Gen\u00e8ve 1214",
    "addr:housenumber":"8",
    "addr:postcode":"1214",
    "addr:street":"Chemin Des Comtoises",
    "iso:country":"CH",
    "sg:address":"Chemin Des Comtoises 8",
    "sg:city":"Vernier",
    "sg:orig_category":"Alters U Pflegeheime Wohnheime",
    "sg:phone":"+41 19325636",
    "sg:postcode":"1214",
    "sg:province":"Gen\u00e8ve",
    "wof:name":"Pfister E., Wohn Und Pflegeheim Uf Em W\u00e4g",
    "wof:placetype":"venue"
},
  "geometry": {"coordinates":[8.788067,47.324673],"type":"Point"}
}