{
  "type": "Feature",
  "properties": {
    "iso:country":"CH",
    "sg:address":"Waldrand",
    "sg:city":"Grindelwald",
    "sg:orig_category":"Architektur U Ingenieurb\u00fcros",
    "sg:postcode":"3818",
    "sg:province":"Bern",
    "wof:name":"Plandoku Gmbh",
    "wof:placetype":"venue"
},
  "geometry": {"coordinates":[9.358394,47.417568],"type":"Point"}
}