{
  "type": "Feature",
  "properties": {
    "iso:country":"CH",
    "sg:address":"Baarerstrasse 65",
    "sg:city":"Zug",
    "sg:orig_category":"RESTAURANTS: TEA-ROOMS",
    "sg:postcode":"6300",
    "sg:province":"Zug",
    "wof:name":"Bantli Josef",
    "wof:placetype":"venue"
},
  "geometry": {"coordinates":[8.5174379349,47.1763916016],"type":"Point"}
}