{
  "type": "Feature",
  "properties": {
    "addr:full":"Z\u00fcrcherstrasse 169 Frauenfeld Thurgau 8500",
    "addr:housenumber":"169",
    "addr:postcode":"8500",
    "addr:street":"Zuercherstrasse",
    "iso:country":"CH",
    "sg:address":"Z\u00fcrcherstrasse 169",
    "sg:city":"Frauenfeld",
    "sg:orig_category":"Bijouterien Reparatur von Uhren U Schmuck",
    "sg:phone":"+41 52 721 25 61",
    "sg:postcode":"8500",
    "sg:province":"Thurgau",
    "wof:name":"Max Lauener Uhren-bijouterie",
    "wof:placetype":"venue"
},
  "geometry": {"coordinates":[8.89744,47.556561],"type":"Point"}
}