{
  "type": "Feature",
  "properties": {
    "iso:country":"CH",
    "sg:address":"Bickelstrasse 15",
    "sg:city":"Oberrieden",
    "sg:orig_category":"Fachdetailhandel in Verkaufsr\u00e4umen Grosshandel mit Foto U Kinoger\u00e4ten, feinmechanischen U optischen ",
    "sg:phone":"+41 17204413",
    "sg:postcode":"8942",
    "sg:province":"Z\u00fcrich",
    "wof:name":"Gfeller Werner",
    "wof:placetype":"venue"
},
  "geometry": {"coordinates":[8.5769262314,47.2790222168],"type":"Point"}
}