{
  "type": "Feature",
  "properties": {
    "iso:country":"CH",
    "sg:address":"Bahnhofstr. 16",
    "sg:city":"Eschlikon",
    "sg:classifiers":[
        {
            "category":"Banks & Credit Unions",
            "subcategory":"Bank",
            "type":"Services"
        }
    ],
    "sg:phone":"+41 4173432727",
    "sg:postcode":"8370",
    "sg:province":"Thurgau",
    "wof:name":"Thurgauer Kantonalbank",
    "wof:placetype":"venue"
},
  "geometry": {"coordinates":[8.961945,47.462708],"type":"Point"}
}