{
  "type": "Feature",
  "properties": {
    "iso:country":"CH",
    "sg:address":"Place Du Molard 6",
    "sg:city":"Gen\u00e8ve",
    "sg:classifiers":[
        {
            "category":"Restaurant",
            "type":"Food & Drink"
        }
    ],
    "sg:phone":"+41 71 244 88 52",
    "sg:postcode":"1204",
    "sg:province":"Gen\u00e8ve",
    "wof:name":"Jakobstal Scheffelstrasse Restaurant",
    "wof:placetype":"venue"
},
  "geometry": {"coordinates":[9.3799676895,47.4301109314],"type":"Point"}
}