{
  "type": "Feature",
  "properties": {
    "addr:full":"1241 Puplinge Gen\u00e8ve 1241",
    "addr:postcode":"1241;1241",
    "addr:street":"Puplinge",
    "iso:country":"CH",
    "sg:address":"1241",
    "sg:city":"Puplinge",
    "sg:classifiers":[
        {
            "category":"Education",
            "subcategory":"Library",
            "type":"Public Place"
        }
    ],
    "sg:phone":"+41 22 321 07 32",
    "sg:postcode":"1241",
    "sg:province":"Gen\u00e8ve",
    "sg:tags":[
        "u",
        "bibliotheken",
        "archive"
    ],
    "wof:name":"Biblioth\u00e8que Communale",
    "wof:placetype":"venue"
},
  "geometry": {"coordinates":[6.23503,46.21032],"type":"Point"}
}