{
  "type": "Feature",
  "properties": {
    "iso:country":"CH",
    "sg:address":"Avenue Du Ch\u00e2telard 5",
    "sg:city":"Clarens",
    "sg:classifiers":[
        {
            "category":"Restaurant",
            "type":"Food & Drink"
        }
    ],
    "sg:phone":"+41 21 964 36 50",
    "sg:postcode":"1815",
    "sg:province":"Vaud",
    "wof:name":"Caf\u00e9 Des Bray\u00e8res",
    "wof:placetype":"venue"
},
  "geometry": {"coordinates":[6.8938817978,46.4442749023],"type":"Point"}
}