{
  "type": "Feature",
  "properties": {
    "iso:country":"CH",
    "sg:address":"Attisholz",
    "sg:city":"Riedholz",
    "sg:orig_category":"Pensionskassen",
    "sg:phone":"+41 32 626 81 11",
    "sg:postcode":"4533",
    "sg:province":"Solothurn",
    "wof:name":"Stiftung F\u00fcr Arbeitslosenf\u00fcrsorge Der Cellulose Attisholz Ag.",
    "wof:placetype":"venue"
},
  "geometry": {"coordinates":[7.5756897926,47.2282791138],"type":"Point"}
}