{
  "type": "Feature",
  "properties": {
    "iso:country":"CH",
    "sg:address":"Davo R\u00f6ven 7530 Zernez. Postfach",
    "sg:city":"Zernez",
    "sg:orig_category":"Herstellung von elektrischen Haushaltsger\u00e4ten",
    "sg:phone":"+41 18452161",
    "sg:postcode":"7530",
    "sg:province":"Graubunden",
    "wof:name":"Sch\u00f6n M. Kaffeekonzepte",
    "wof:placetype":"venue"
},
  "geometry": {"coordinates":[8.4416046143,47.4548377991],"type":"Point"}
}