{
  "type": "Feature",
  "properties": {
    "iso:country":"CH",
    "sg:address":"Strandbadstrasse 3 3800 Interlaken. Postfach 22",
    "sg:city":"Interlaken",
    "sg:orig_category":"Zahnarztpraxen",
    "sg:phone":"+41 33 822 24 14",
    "sg:postcode":"3800",
    "sg:province":"Bern",
    "wof:name":"Dr. Med. Dent. Guido Willa Zahnarzt",
    "wof:placetype":"venue"
},
  "geometry": {"coordinates":[7.8547120094,46.6870117188],"type":"Point"}
}