{
  "type": "Feature",
  "properties": {
    "iso:country":"CH",
    "sg:address":"Chemin Des Primev\u00e8res 15",
    "sg:city":"Saignel\u00e9gier",
    "sg:orig_category":"Bezirks, Sekundar, Realschulen, Oberstufe der Primarschulen",
    "sg:phone":"+41 32 951 10 93",
    "sg:postcode":"2350",
    "sg:province":"Jura",
    "wof:name":"Ecole Secondaire",
    "wof:placetype":"venue"
},
  "geometry": {"coordinates":[6.994804,47.257545],"type":"Point"}
}