{
  "type": "Feature",
  "properties": {
    "iso:country":"CH",
    "sg:address":"Kienastenwiesweg 31",
    "sg:city":"Z\u00fcrich",
    "sg:orig_category":"Sonstiger Grosshandel",
    "sg:postcode":"8053",
    "sg:province":"Z\u00fcrich",
    "wof:name":"Peoplefox Gmbh",
    "wof:placetype":"venue"
},
  "geometry": {"coordinates":[8.6030931473,47.3556861877],"type":"Point"}
}