{
  "type": "Feature",
  "properties": {
    "iso:country":"CH",
    "sg:address":"Berninastrasse 9",
    "sg:city":"Z\u00fcrich",
    "sg:orig_category":"Sonstiger Fachdetailhandel mit Nahrungsmitteln, Getr\u00e4nken U Tabak in Verkaufsr\u00e4umen",
    "sg:phone":"+41 13117874",
    "sg:postcode":"8057",
    "sg:province":"Z\u00fcrich",
    "wof:name":"Naturviva Ag",
    "wof:placetype":"venue"
},
  "geometry": {"coordinates":[8.552406311,47.4024658203],"type":"Point"}
}