{
  "type": "Feature",
  "properties": {
    "iso:country":"CH",
    "sg:address":"Engstringerstrasse 12",
    "sg:city":"Schlieren",
    "sg:orig_category":"Detailhandel mit Milcherzeugnissen U Eiern Detailhandel mit Waren verschiedener Art, Hauptrichtung N",
    "sg:phone":"+41 17307170",
    "sg:postcode":"8952",
    "sg:province":"Z\u00fcrich",
    "wof:name":"Peter Welti Lebensmittelgesch\u00e4ft",
    "wof:placetype":"venue"
},
  "geometry": {"coordinates":[8.4480962753,47.4034309387],"type":"Point"}
}