{
  "type": "Feature",
  "properties": {
    "iso:country":"CH",
    "sg:address":"Route D'englisberg 17 1763 Granges-paccot Case Postale 126",
    "sg:city":"Granges-paccot",
    "sg:orig_category":"Herstellung von Damen U M\u00e4dchenoberbekleidung Herstellung von Herren U Knabenoberbekleidung",
    "sg:phone":"+41 26 460 79 79",
    "sg:postcode":"1763",
    "sg:province":"Fribourg",
    "wof:name":"Oa Textile & Articles Promotionnels Sa",
    "wof:placetype":"venue"
},
  "geometry": {"coordinates":[7.1482000351,46.8223991394],"type":"Point"}
}