{
  "type": "Feature",
  "properties": {
    "iso:country":"CH",
    "sg:address":"Hauptgasse 28 3280 Burg B. Murten. Postfach 107",
    "sg:city":"Sargans",
    "sg:orig_category":"Reiseb\u00fcros U Reiseveranstalter",
    "sg:phone":"+41 26 672 20 22",
    "sg:postcode":"7320",
    "sg:province":"St. Gallen",
    "wof:name":"Destour Reiseb\u00fcro Gmbh",
    "wof:placetype":"venue"
},
  "geometry": {"coordinates":[7.1084527969,46.9252319336],"type":"Point"}
}