{
  "type": "Feature",
  "properties": {
    "iso:country":"CH",
    "sg:address":"R\u00fceggisingerstrasse 74",
    "sg:city":"Emmen",
    "sg:orig_category":"Malerei Tapeziererei",
    "sg:phone":"+41 52 657 42 43",
    "sg:postcode":"6032",
    "sg:province":"Luzern",
    "wof:name":"Hanspeter Richner Maler-& Tapezierergesch\u00e4ft",
    "wof:placetype":"venue"
},
  "geometry": {"coordinates":[8.7035932541,47.661075592],"type":"Point"}
}