{
  "type": "Feature",
  "properties": {
    "iso:country":"CH",
    "sg:address":"H\u00f6htalstrasse 23 5408 Ennetbaden. Postfach",
    "sg:city":"Ennetbaden",
    "sg:orig_category":"Erbringung von Dienstleistungen f\u00fcr Unternehmen",
    "sg:phone":"+41 56 222 81 56",
    "sg:postcode":"5408",
    "sg:province":"Aargau",
    "wof:name":"Monteca Arkuszewski Wissenschaftsberatung. Nukleartechnik, Dosimetrie, Strahlungshygiene; Expertisen Und Software",
    "wof:placetype":"venue"
},
  "geometry": {"coordinates":[8.3173885345,47.4783973694],"type":"Point"}
}