{
  "type": "Feature",
  "properties": {
    "iso:country":"CH",
    "sg:address":"Grand-rue 64",
    "sg:city":"Ch\u00e2tel-st-denis",
    "sg:orig_category":"Detailhandel mit Fleisch U Fleischwaren",
    "sg:phone":"+41 21 948 73 77",
    "sg:postcode":"1618",
    "sg:province":"Fribourg",
    "wof:name":"Fran\u00e7ois Blanc Boucherie-charcuterie",
    "wof:placetype":"venue"
},
  "geometry": {"coordinates":[6.9024691582,46.5283737183],"type":"Point"}
}