{
  "type": "Feature",
  "properties": {
    "iso:country":"CH",
    "sg:address":"Zugerstrasse 76b 6340 Baar. Postfach",
    "sg:city":"Baar",
    "sg:orig_category":"Verwaltung von Immobilien",
    "sg:phone":"+41 41 767 28 32",
    "sg:postcode":"6341",
    "sg:province":"Zug",
    "wof:name":"Mb Verwaltungs Ag",
    "wof:placetype":"venue"
},
  "geometry": {"coordinates":[8.519613266,47.1831130981],"type":"Point"}
}