{
  "type": "Feature",
  "properties": {
    "iso:country":"CH",
    "sg:address":"Brunnhofweg 47",
    "sg:city":"Bern",
    "sg:orig_category":"Detailhandel mit B\u00fcchern, Zeitungen, Schreib U Papeteriewaren",
    "sg:phone":"+41 31 381 70 20",
    "sg:postcode":"3007",
    "sg:province":"Bern",
    "wof:name":"Kiosk Brunnhofweg 47, Graber",
    "wof:placetype":"venue"
},
  "geometry": {"coordinates":[7.42751,46.94352],"type":"Point"}
}