{
  "type": "Feature",
  "properties": {
    "iso:country":"CH",
    "sg:address":"Milchg\u00e4ssli 12",
    "sg:city":"Schwarzenburg",
    "sg:orig_category":"Detailhandel mit Lederwaren U Reiseartikeln Detailhandel mit Schuhen U Lederwaren",
    "sg:phone":"+41 31 731 14 93",
    "sg:postcode":"3150",
    "sg:province":"Bern",
    "wof:name":"Zico Lederwaren Daniel Zimmermann",
    "wof:placetype":"venue"
},
  "geometry": {"coordinates":[7.3397879601,46.8164215088],"type":"Point"}
}