{
  "type": "Feature",
  "properties": {
    "addr:full":"Rue Saint-pierre 6 Fribourg Fribourg 1700",
    "addr:housenumber":"6",
    "addr:postcode":"1700",
    "addr:street":"Rue Saint-Pierre",
    "iso:country":"CH",
    "sg:address":"Rue Saint-pierre 6",
    "sg:city":"Fribourg",
    "sg:orig_category":"Detailhandel mit Bekleidung Detailhandel mit Damenbekleidung",
    "sg:phone":"+41 26 322 28 28",
    "sg:postcode":"1700",
    "sg:province":"Fribourg",
    "wof:name":"Boutique Tendresse B.andrey & M.-f.aeby",
    "wof:placetype":"venue"
},
  "geometry": {"coordinates":[7.154884,46.803627],"type":"Point"}
}