{
  "type": "Feature",
  "properties": {
    "iso:country":"CH",
    "sg:address":"4536",
    "sg:city":"Attiswil",
    "sg:orig_category":"Vereine Gesang",
    "sg:phone":"+41 32 637 26 26",
    "sg:postcode":"4536",
    "sg:province":"Bern",
    "wof:name":"Gemischter Chor",
    "wof:placetype":"venue"
},
  "geometry": {"coordinates":[7.6126790047,47.246887207],"type":"Point"}
}