{
  "type": "Feature",
  "properties": {
    "iso:country":"CH",
    "sg:address":"9467",
    "sg:city":"Fr\u00fcmsen",
    "sg:classifiers":[
        {
            "category":"Travel",
            "subcategory":"Hotels & Motels",
            "type":"Entertainment"
        }
    ],
    "sg:phone":"+41 71 799 11 77",
    "sg:postcode":"9467",
    "sg:province":"St. Gallen",
    "sg:tags":[
        "hotels",
        "mit",
        "restaurant"
    ],
    "wof:name":"Bergrestaurant Staubern",
    "wof:placetype":"venue"
},
  "geometry": {"coordinates":[9.4734773636,47.245136261],"type":"Point"}
}