{
  "type": "Feature",
  "properties": {
    "iso:country":"CH",
    "sg:address":"Rue Pr\u00e9vost-martin 25",
    "sg:city":"Gen\u00e8ve",
    "sg:orig_category":"Detailhandel mit Geschenkartikeln U Souvenirs Detailhandel mit M\u00f6beln U Haushaltsgegenst\u00e4nden",
    "sg:phone":"+41 61 601 58 91",
    "sg:postcode":"1205",
    "sg:province":"Gen\u00e8ve",
    "wof:name":"Maja Marti Geschenkboutique",
    "wof:placetype":"venue"
},
  "geometry": {"coordinates":[7.6319861412,47.5725517273],"type":"Point"}
}