{
  "type": "Feature",
  "properties": {
    "addr:full":"Ch. De Sous-cherre 6 D 1245 Collonge-bellerive. Postfach Collonge-bellerive Gen\u00e8ve 1245",
    "addr:housenumber":"6 d",
    "addr:postcode":"1245 collonge-bellerive. postfach collonge-bellerive;1245",
    "addr:street":"Ch. De Sous-Cherre",
    "iso:country":"CH",
    "sg:address":"Ch. De Sous-cherre 6 D 1245 Collonge-bellerive. Postfach",
    "sg:city":"Collonge-bellerive",
    "sg:orig_category":"Architektur U Ingenieurb\u00fcros",
    "sg:postcode":"1245",
    "sg:province":"Gen\u00e8ve",
    "wof:name":"Sorefa Sarl",
    "wof:placetype":"venue"
},
  "geometry": {"coordinates":[6.204528,46.260731],"type":"Point"}
}