{
  "type": "Feature",
  "properties": {
    "iso:country":"CH",
    "sg:address":"Rue Des Alpes 44",
    "sg:city":"Crissier",
    "sg:orig_category":"Detailhandel mit Fleisch U Fleischwaren",
    "sg:phone":"+41 21 634 27 90",
    "sg:postcode":"1023",
    "sg:province":"Vaud",
    "wof:name":"Bernard Friederich Boucherie-charcuterie",
    "wof:placetype":"venue"
},
  "geometry": {"coordinates":[6.5795941353,46.5424118042],"type":"Point"}
}