{
  "type": "Feature",
  "properties": {
    "addr:full":"Maiens\u00e4ss Moos Vals Graubunden 7132",
    "addr:postcode":"7132",
    "addr:street":"Moos;Graubunden",
    "iso:country":"CH",
    "sg:address":"Maiens\u00e4ss Moos",
    "sg:city":"Vals",
    "sg:orig_category":"Allgemeiner Hoch U Tiefbau",
    "sg:phone":"+41 81 935 15 90",
    "sg:postcode":"7132",
    "sg:province":"Graubunden",
    "wof:name":"Schmid Richard",
    "wof:placetype":"venue"
},
  "geometry": {"coordinates":[9.180222,46.617252],"type":"Point"}
}