{
  "type": "Feature",
  "properties": {
    "iso:country":"CH",
    "sg:address":"Avenue Reverdil 6",
    "sg:city":"Nyon",
    "sg:orig_category":"Sonstige Aktivit\u00e4ten der nicht-\u00e4rztlichen Medizinalberufe",
    "sg:phone":"+41 22 364 04 84",
    "sg:postcode":"1260",
    "sg:province":"Vaud",
    "wof:name":"Patrick Drapel Kin\u00e9siologie & Massage",
    "wof:placetype":"venue"
},
  "geometry": {"coordinates":[6.2335338593,46.3820266724],"type":"Point"}
}