{
  "type": "Feature",
  "properties": {
    "iso:country":"CH",
    "sg:address":"Franzosenstrasse",
    "sg:city":"Seewen",
    "sg:orig_category":"Basketware",
    "sg:phone":"+41 41 818 60 60",
    "sg:postcode":"6423",
    "sg:province":"Schwyz",
    "wof:name":"Schlittler & Co Ag",
    "wof:placetype":"venue"
},
  "geometry": {"coordinates":[8.6311,47.019852],"type":"Point"}
}