{
  "type": "Feature",
  "properties": {
    "iso:country":"CH",
    "sg:address":"Rosenhaldenstrasse 19",
    "sg:city":"Meggen",
    "sg:orig_category":"Architekturb\u00fcros",
    "sg:phone":"+41 41 377 19 30",
    "sg:postcode":"6045",
    "sg:province":"Luzern",
    "wof:name":"Siegfried Fuhrimann Architekturb\u00fcro",
    "wof:placetype":"venue"
},
  "geometry": {"coordinates":[8.363377,47.042583],"type":"Point"}
}