{
  "type": "Feature",
  "properties": {
    "iso:country":"CH",
    "sg:address":"1515",
    "sg:city":"Neyruz-sur-moudon",
    "sg:classifiers":[
        {
            "category":"Restaurant",
            "type":"Food & Drink"
        }
    ],
    "sg:phone":"+41 21 905 30 28",
    "sg:postcode":"1515",
    "sg:province":"Vaud",
    "wof:name":"Restaurant Les Rutannes",
    "wof:placetype":"venue"
},
  "geometry": {"coordinates":[6.7885122299,46.6984825134],"type":"Point"}
}