{
  "type": "Feature",
  "properties": {
    "addr:full":"Baslerstrasse 76 Olten Solothurn 4600",
    "addr:housenumber":"76",
    "addr:postcode":"4600",
    "addr:street":"Baslerstrasse",
    "iso:country":"CH",
    "sg:address":"Baslerstrasse 76",
    "sg:city":"Olten",
    "sg:classifiers":[
        {
            "category":"Bars & Pubs",
            "type":"Food & Drink"
        }
    ],
    "sg:postcode":"4600",
    "sg:province":"Solothurn",
    "wof:name":"Primavera-bar Lushi Hasan",
    "wof:placetype":"venue"
},
  "geometry": {"coordinates":[7.902588,47.353149],"type":"Point"}
}