{
  "type": "Feature",
  "properties": {
    "iso:country":"CH",
    "sg:address":"Sch\u00f6nblickh\u00f6he 12",
    "sg:city":"Meggen",
    "sg:orig_category":"Vermittlung von Immobilien Verwaltung von Immobilien",
    "sg:phone":"+41 41 311 24 35",
    "sg:postcode":"6045",
    "sg:province":"Luzern",
    "wof:name":"Ueli M. Eggstein Ingenieurunternehmung Ag",
    "wof:placetype":"venue"
},
  "geometry": {"coordinates":[8.3697872162,47.0443496704],"type":"Point"}
}