{
  "type": "Feature",
  "properties": {
    "iso:country":"CH",
    "sg:address":"Quaderstrasse 17",
    "sg:city":"Chur",
    "sg:orig_category":"Detailhandel mit Uhren U Schmuck Reparatur von Uhren U Schmuck",
    "sg:phone":"+41 81 252 23 92",
    "sg:postcode":"7000",
    "sg:province":"Graubunden",
    "wof:name":"Werner Kircher Uhren & Bijouterie",
    "wof:placetype":"venue"
},
  "geometry": {"coordinates":[9.533115387,46.8525161743],"type":"Point"}
}