{
  "type": "Feature",
  "properties": {
    "iso:country":"CH",
    "sg:address":"Boole 4 2542 Pieterlen. Postfach",
    "sg:city":"Pieterlen",
    "sg:orig_category":"Herstellung von Mess U Kontrollinstrumenten U vorrichtungen",
    "sg:postcode":"2542",
    "sg:province":"Bern",
    "wof:name":"Cutline Ag Feinmechanik U. Metallbearbeitung. Werkzeuge, Komponenten Usw.; Produktion, Montage",
    "wof:placetype":"venue"
},
  "geometry": {"coordinates":[7.3374509811,47.1693878174],"type":"Point"}
}