{
  "type": "Feature",
  "properties": {
    "iso:country":"CH",
    "sg:address":"K\u00f6llikerstrasse 35",
    "sg:city":"Gretzenbach",
    "sg:orig_category":"Nationale Postdienste",
    "sg:phone":"+41 62 849 14 30",
    "sg:postcode":"5014",
    "sg:province":"Solothurn",
    "wof:name":"Die Schweizerische Post",
    "wof:placetype":"venue"
},
  "geometry": {"coordinates":[7.9955201149,47.3597145081],"type":"Point"}
}