{
  "type": "Feature",
  "properties": {
    "iso:country":"CH",
    "sg:address":"Grancy Boulevard De 31 1006 Lausanne. Postfach",
    "sg:city":"Lausanne",
    "sg:orig_category":"Interessenvertretungen",
    "sg:postcode":"1003",
    "sg:province":"Vaud",
    "wof:name":"Fondation De La Piscine Du Landeron",
    "wof:placetype":"venue"
},
  "geometry": {"coordinates":[7.0628671646,47.0604782104],"type":"Point"}
}