{
  "type": "Feature",
  "properties": {
    "addr:full":"Theaterstrasse 22 Basel Basel-Stadt 4051",
    "addr:housenumber":"22",
    "addr:postcode":"4051",
    "addr:street":"Theaterstrasse",
    "iso:country":"CH",
    "sg:address":"Theaterstrasse 22",
    "sg:city":"Basel",
    "sg:orig_category":"Detailhandel mit Bekleidung Detailhandel mit Damenbekleidung",
    "sg:phone":"+41 61 281 89 85",
    "sg:postcode":"4051",
    "sg:province":"Basel-Stadt",
    "wof:name":"Schatzk\u00e4schtli Ag",
    "wof:placetype":"venue"
},
  "geometry": {"coordinates":[7.589496,47.552589],"type":"Point"}
}