{
  "type": "Feature",
  "properties": {
    "iso:country":"CH",
    "sg:address":"Publoz",
    "sg:city":"Puidoux",
    "sg:orig_category":"Detailhandel mit Waren verschiedener Art, Hauptrichtung Nahrungsmittel Grosshandel mit Nahrungsmitte",
    "sg:phone":"+41 81 413 24 45",
    "sg:postcode":"1070",
    "sg:province":"Vaud",
    "wof:name":"Konsum Davos Ag",
    "wof:placetype":"venue"
},
  "geometry": {"coordinates":[9.8232135773,46.7939529419],"type":"Point"}
}