{
  "type": "Feature",
  "properties": {
    "iso:country":"CH",
    "sg:address":"Avenue Haldimand 81 1400 Yverdon-les-bains Case Postale 3036",
    "sg:city":"Yverdon",
    "sg:orig_category":"Detailhandel mit Brennstoffen U Heizmaterial Grosshandel mit festen Brennstoffen U Mineral\u00f6lerzeugni",
    "sg:phone":"+41 24 471 22 62",
    "sg:postcode":"1401",
    "sg:province":"Vaud",
    "wof:name":"Dubosson M. Sa",
    "wof:placetype":"venue"
},
  "geometry": {"coordinates":[6.948625,46.25317],"type":"Point"}
}