{
  "type": "Feature",
  "properties": {
    "iso:country":"CH",
    "sg:address":"Rue Des Draizes 71",
    "sg:city":"Neuch\u00e2tel",
    "sg:orig_category":"Herstellung von Metallkonstruktionen",
    "sg:phone":"+41 32 731 14 00",
    "sg:postcode":"2000",
    "sg:province":"Neuch\u00e2tel",
    "wof:name":"Serrurerie Des Draizes, Vernier Laurent",
    "wof:placetype":"venue"
},
  "geometry": {"coordinates":[6.8995299339,46.9887466431],"type":"Point"}
}