{
  "type": "Feature",
  "properties": {
    "iso:country":"CH",
    "sg:address":"S\u00e4gebachstrasse",
    "sg:city":"Lenggenwil",
    "sg:orig_category":"Alarm- and Sicherheitsanlagen Grosshandel Elektroinstallation",
    "sg:phone":"+41 71 949 00 70",
    "sg:postcode":"9525",
    "sg:province":"St. Gallen",
    "wof:name":"Bell Security (schweiz) Ag",
    "wof:placetype":"venue"
},
  "geometry": {"coordinates":[9.148861,47.476112],"type":"Point"}
}