{
  "type": "Feature",
  "properties": {
    "iso:country":"CH",
    "sg:address":"Nationalquai 6000 Luzern. Postfach",
    "sg:city":"Luzern",
    "sg:orig_category":"Boots U Yachtbau Vermietung von Wasserfahrzeugen",
    "sg:phone":"+41 41 410 43 33",
    "sg:postcode":"6002",
    "sg:province":"Luzern",
    "wof:name":"Herzog Werft Ag",
    "wof:placetype":"venue"
},
  "geometry": {"coordinates":[8.315159,47.054581],"type":"Point"}
}