{
  "type": "Feature",
  "properties": {
    "iso:country":"CH",
    "sg:address":"Badenerstrasse 281",
    "sg:city":"Z\u00fcrich",
    "sg:orig_category":"Non-Classified Establishments",
    "sg:postcode":"8003",
    "sg:province":"Z\u00fcrich",
    "wof:name":"Acad Record, Anderegg",
    "wof:placetype":"venue"
},
  "geometry": {"coordinates":[8.5142936707,47.3762969971],"type":"Point"}
}