{
  "type": "Feature",
  "properties": {
    "iso:country":"CH",
    "sg:address":"Wehntalerstrasse 48 8157 Dielsdorf. Postfach",
    "sg:city":"Dielsdorf",
    "sg:orig_category":"Grosshandel mit sonstigen Maschinen U Ausr\u00fcstungen f\u00fcr Industrie, Handel U Schiffahrt Schaustellerge",
    "sg:phone":"+41 52 238 23 93",
    "sg:postcode":"8157",
    "sg:province":"Z\u00fcrich",
    "wof:name":"Karussellbetrieb Bichler Und Maier Ag",
    "wof:placetype":"venue"
},
  "geometry": {"coordinates":[8.7607221603,47.4835586548],"type":"Point"}
}