{
  "type": "Feature",
  "properties": {
    "iso:country":"CH",
    "sg:address":"R\u00fcegerholzstrasse 3",
    "sg:city":"Frauenfeld",
    "sg:orig_category":"Arztpraxen",
    "sg:phone":"+41 52 720 44 72",
    "sg:postcode":"8500",
    "sg:province":"Thurgau",
    "wof:name":"Dr.med.frank Schumacher Spezialarzt Fmh",
    "wof:placetype":"venue"
},
  "geometry": {"coordinates":[8.897961,47.550884],"type":"Point"}
}