{
  "type": "Feature",
  "properties": {
    "iso:country":"CH",
    "sg:address":"Zollikerstrasse 214 8008 Z\u00fcrich. Postfach",
    "sg:city":"Z\u00fcrich",
    "sg:orig_category":"Kauf U Verkauf von Immobilien auf eigene Rechnung",
    "sg:postcode":"8001",
    "sg:province":"Z\u00fcrich",
    "wof:name":"Wirverkaufenihrhaus St\u00f6hr Daniel",
    "wof:placetype":"venue"
},
  "geometry": {"coordinates":[8.8226995468,47.446521759],"type":"Point"}
}