{
  "type": "Feature",
  "properties": {
    "iso:country":"CH",
    "sg:address":"Im St\u00e4dtchen 13",
    "sg:city":"Erlach",
    "sg:orig_category":"Detailhandel mit Fleisch U Fleischwaren",
    "sg:phone":"+41 32 338 11 07",
    "sg:postcode":"3235",
    "sg:province":"Bern",
    "wof:name":"Robert B\u00fcrki Metzgerei-wursterei",
    "wof:placetype":"venue"
},
  "geometry": {"coordinates":[7.0968651772,47.0431480408],"type":"Point"}
}