{
  "type": "Feature",
  "properties": {
    "iso:country":"CH",
    "sg:address":"Hinterstadt",
    "sg:city":"Uznach",
    "sg:classifiers":[
        {
            "category":"Home & Garden",
            "subcategory":"Carpets & Floor Coverings",
            "type":"Retail Goods"
        }
    ],
    "sg:phone":"+41 55 280 28 44",
    "sg:postcode":"8730",
    "sg:province":"St. Gallen",
    "sg:tags":[
        "stone",
        "natural",
        "panel"
    ],
    "wof:name":"P. De Zanet & Co Ag",
    "wof:placetype":"venue"
},
  "geometry": {"coordinates":[8.9890775681,47.2250747681],"type":"Point"}
}