{
  "type": "Feature",
  "properties": {
    "iso:country":"CH",
    "sg:address":"In Der S\u00e4nti 16 6130 Willisau. Postfach",
    "sg:city":"Willisau",
    "sg:orig_category":"Zimmerei, Dachdeckerei, Bauspenglerei U Abdichtung",
    "sg:phone":"+41 41 970 16 07",
    "sg:postcode":"6130",
    "sg:province":"Luzern",
    "wof:name":"H\u00e4fliger Konrad Holz & Systemarbeiten Ag F\u00fcr Holzbauplanung",
    "wof:placetype":"venue"
},
  "geometry": {"coordinates":[8.0049581528,47.1195869446],"type":"Point"}
}