{
  "type": "Feature",
  "properties": {
    "iso:country":"CH",
    "sg:address":"Untere M\u00fchle",
    "sg:city":"Schwellbrunn",
    "sg:classifiers":[
        {
            "category":"Restaurant",
            "type":"Food & Drink"
        }
    ],
    "sg:phone":"+41 71 371 13 51",
    "sg:postcode":"9103",
    "sg:province":"Appenzell Ausserrhoden",
    "sg:tags":[
        "tea-rooms",
        "restaurants"
    ],
    "wof:name":"Restaurant Untere M\u00fchle, Kaufmann J\u00fcrg Und Monika",
    "wof:placetype":"venue"
},
  "geometry": {"coordinates":[9.222237587,47.3662261963],"type":"Point"}
}