{
  "type": "Feature",
  "properties": {
    "iso:country":"CH",
    "sg:address":"Eigerstrasse 2",
    "sg:city":"Unterseen",
    "sg:orig_category":"Sportvereine Turnen",
    "sg:phone":"+41 33 822 64 26",
    "sg:postcode":"3800",
    "sg:province":"Bern",
    "wof:name":"Turnverein Stv Unterseen",
    "wof:placetype":"venue"
},
  "geometry": {"coordinates":[7.8443660736,46.6835823059],"type":"Point"}
}