{
  "type": "Feature",
  "properties": {
    "iso:country":"CH",
    "sg:address":"Dorfstrasse 8 6072 Sachseln. Postfach 237",
    "sg:city":"Sachseln",
    "sg:orig_category":"Elektroinstallation Herstellung von Elektromotoren, Generatoren U Transformatoren",
    "sg:phone":"+41 79 642 61 20",
    "sg:postcode":"6072",
    "sg:province":"Obwalden",
    "wof:name":"Elektro-kaiser Ag Sachseln",
    "wof:placetype":"venue"
},
  "geometry": {"coordinates":[8.2392148972,46.8680038452],"type":"Point"}
}