{
  "type": "Feature",
  "properties": {
    "iso:country":"CH",
    "sg:address":"Bahnhofstrasse 27 5012 Sch\u00f6nenwerd. Postfach",
    "sg:city":"Sch\u00f6nenwerd",
    "sg:orig_category":"Softwareentwicklung U beratung",
    "sg:postcode":"5012",
    "sg:province":"Solothurn",
    "wof:name":"Mhm, Annika Boverio",
    "wof:placetype":"venue"
},
  "geometry": {"coordinates":[6.5488681793,46.8069915771],"type":"Point"}
}