{
  "type": "Feature",
  "properties": {
    "iso:country":"CH",
    "sg:address":"Verdaine Rue 9",
    "sg:city":"Gen\u00e8ve",
    "sg:orig_category":"RESTAURANTS: TEA-ROOMS",
    "sg:postcode":"1204",
    "sg:province":"Gen\u00e8ve",
    "wof:name":"Kal'vin, Th. Von Ballmoos",
    "wof:placetype":"venue"
},
  "geometry": {"coordinates":[6.1503748894,46.2012863159],"type":"Point"}
}