{
  "type": "Feature",
  "properties": {
    "iso:country":"CH",
    "sg:address":"Sonnenblick Dorf",
    "sg:city":"Hofstatt",
    "sg:orig_category":"Detailhandel mit Brot, Back U S\u00fcsswaren Detailhandel mit Waren verschiedener Art, Hauptrichtung Nahr",
    "sg:phone":"+41 41 978 11 24",
    "sg:postcode":"6154",
    "sg:province":"Luzern",
    "wof:name":"Kaspar Hodel",
    "wof:placetype":"venue"
},
  "geometry": {"coordinates":[7.914875,47.084496],"type":"Point"}
}