{
  "type": "Feature",
  "properties": {
    "iso:country":"CH",
    "sg:address":"Kilchb\u00fchlstrasse 2 6390 Engelberg. Postfach 324",
    "sg:city":"Engelberg",
    "sg:orig_category":"Unternehmensberatung",
    "sg:phone":"+41 41 639 53 43",
    "sg:postcode":"6390",
    "sg:province":"Obwalden",
    "wof:name":"Thomas Meierhofer Unternehmensberatung",
    "wof:placetype":"venue"
},
  "geometry": {"coordinates":[8.4185762405,46.8202476501],"type":"Point"}
}