{
  "type": "Feature",
  "properties": {
    "iso:country":"CH",
    "sg:address":"Bahnhofstrasse 14 2502 Biel/bienne Case Postale 509",
    "sg:city":"Biel/bienne",
    "sg:orig_category":"Reiseb\u00fcros U Reiseveranstalter Vermietung von Automobilen",
    "sg:phone":"+41 32 329 90 10",
    "sg:postcode":"2501",
    "sg:province":"Bern",
    "wof:name":"Ernst Marti Ag",
    "wof:placetype":"venue"
},
  "geometry": {"coordinates":[7.2425208092,47.1330947876],"type":"Point"}
}