{
  "type": "Feature",
  "properties": {
    "iso:country":"CH",
    "sg:address":"Baarerstrasse 19",
    "sg:city":"Zug",
    "sg:orig_category":"Berufsbildende weiterf\u00fchrende Schulen Fahrschulen, Flugschulen",
    "sg:phone":"+41 41 711 40 10",
    "sg:postcode":"6300",
    "sg:province":"Zug",
    "wof:name":"Afv Verkehrsschule Zug",
    "wof:placetype":"venue"
},
  "geometry": {"coordinates":[8.516126,47.172092],"type":"Point"}
}