{
  "type": "Feature",
  "properties": {
    "iso:country":"CH",
    "sg:address":"Rieterstrasse 52 8002 Z\u00fcrich. Postfach",
    "sg:city":"Z\u00fcrich",
    "sg:orig_category":"Sonstiges Versicherungsgewerbe",
    "sg:phone":"+41 12213838",
    "sg:postcode":"8027",
    "sg:province":"Z\u00fcrich",
    "wof:name":"Meier Ren\u00e9",
    "wof:placetype":"venue"
},
  "geometry": {"coordinates":[8.5259170532,47.3574981689],"type":"Point"}
}