{
  "type": "Feature",
  "properties": {
    "iso:country":"CH",
    "sg:address":"Rue Du Dr-lerch 3",
    "sg:city":"Couvet",
    "sg:orig_category":"Sportvereine Wassersport Schwimmen",
    "sg:phone":"+41 32 863 20 83",
    "sg:postcode":"2108",
    "sg:province":"Neuch\u00e2tel",
    "wof:name":"Club Natation Val-de-travers",
    "wof:placetype":"venue"
},
  "geometry": {"coordinates":[6.6289548874,46.9252929688],"type":"Point"}
}