{
  "type": "Feature",
  "properties": {
    "iso:country":"CH",
    "sg:address":"La Rougearde",
    "sg:city":"Penthaz",
    "sg:orig_category":"Elektroinstallation",
    "sg:phone":"+41 21628090",
    "sg:postcode":"1303",
    "sg:province":"Vaud",
    "wof:name":"E.t.s. Electricit\u00e9, T\u00e9l\u00e9communication Et S\u00e9curit\u00e9 S\u00e0rl",
    "wof:placetype":"venue"
},
  "geometry": {"coordinates":[6.5384898186,46.5996818542],"type":"Point"}
}