{
  "type": "Feature",
  "properties": {
    "addr:full":"Stampfenbachstr. 85 Z\u00fcrich Z\u00fcrich 8035",
    "addr:housenumber":"85",
    "addr:postcode":"8035",
    "addr:street":"Stampfenbachstr.",
    "iso:country":"CH",
    "sg:address":"Stampfenbachstr. 85",
    "sg:city":"Z\u00fcrich",
    "sg:classifiers":[
        {
            "category":"Professional",
            "subcategory":"Advertising",
            "type":"Services"
        }
    ],
    "sg:phone":"+41 4113655454",
    "sg:postcode":"8035",
    "sg:province":"Z\u00fcrich",
    "sg:tags":[
        "information",
        "medium",
        "communication"
    ],
    "wof:name":"Osec Buisness Network Switzerland",
    "wof:placetype":"venue"
},
  "geometry": {"coordinates":[8.541534,47.382359],"type":"Point"}
}