{
  "type": "Feature",
  "properties": {
    "iso:country":"CH",
    "sg:address":"Schwaderhof 5708 Birrwil. Postfach",
    "sg:city":"Birrwil",
    "sg:orig_category":"Non-Classified Establishments",
    "sg:postcode":"5708",
    "sg:province":"Aargau",
    "wof:name":"Bodymind Ag",
    "wof:placetype":"venue"
},
  "geometry": {"coordinates":[8.1979436874,47.3013572693],"type":"Point"}
}