{
  "type": "Feature",
  "properties": {
    "iso:country":"CH",
    "sg:address":"Progr\u00e8s Rue Du 3",
    "sg:city":"Fribourg",
    "sg:orig_category":"Unclassifiable Establishments",
    "sg:postcode":"1700",
    "sg:province":"Fribourg",
    "wof:name":"Si Rue Du Progr\u00e8s 3 Et 5 Sa",
    "wof:placetype":"venue"
},
  "geometry": {"coordinates":[7.1449279785,46.8022193909],"type":"Point"}
}