{
  "type": "Feature",
  "properties": {
    "iso:country":"CH",
    "sg:address":"Gotettes Chemin Des 60b",
    "sg:city":"Collonge-bellerive",
    "sg:orig_category":"Unternehmensberatung",
    "sg:phone":"+41 22 707 14 70",
    "sg:postcode":"1245",
    "sg:province":"Gen\u00e8ve",
    "wof:name":"Qualia Consulting S\u00e0rl",
    "wof:placetype":"venue"
},
  "geometry": {"coordinates":[6.2042441368,46.2535629272],"type":"Point"}
}