{
  "type": "Feature",
  "properties": {
    "iso:country":"CH",
    "sg:address":"Deutsche Kirchgasse 25",
    "sg:city":"Murten",
    "sg:orig_category":"Zahnarztpraxen",
    "sg:phone":"+41 26 670 25 52",
    "sg:postcode":"3280",
    "sg:province":"Fribourg",
    "wof:name":"Dr. Med. Dent. Oliver Zeyer Zahnarzt",
    "wof:placetype":"venue"
},
  "geometry": {"coordinates":[7.1186070442,46.9286346436],"type":"Point"}
}