{
  "type": "Feature",
  "properties": {
    "iso:country":"CH",
    "sg:address":"Hertensteinstrasse 43",
    "sg:city":"Luzern",
    "sg:orig_category":"P\u00e9dicure",
    "sg:phone":"+41 41 410 90 10",
    "sg:postcode":"6004",
    "sg:province":"Luzern",
    "wof:name":"Marianne Pauli P\u00e9dicure",
    "wof:placetype":"venue"
},
  "geometry": {"coordinates":[8.3075714111,47.0538330078],"type":"Point"}
}