{
  "type": "Feature",
  "properties": {
    "iso:country":"CH",
    "sg:address":"Grand-rue 4",
    "sg:city":"Corcelles",
    "sg:classifiers":[
        {
            "category":"Home & Garden",
            "subcategory":"Building Materials",
            "type":"Retail Goods"
        }
    ],
    "sg:phone":"+41 32 731 44 53",
    "sg:postcode":"2035",
    "sg:province":"Neuch\u00e2tel",
    "sg:tags":[
        "garage",
        "door"
    ],
    "wof:name":"Hartmann + Co S.a.",
    "wof:placetype":"venue"
},
  "geometry": {"coordinates":[6.8832159042,46.985244751],"type":"Point"}
}