{
  "type": "Feature",
  "properties": {
    "iso:country":"CH",
    "sg:address":"Fulenbacherstrasse 34",
    "sg:city":"Wolfwil",
    "sg:classifiers":[
        {
            "category":"Insurance",
            "subcategory":"Insurance Agent",
            "type":"Services"
        }
    ],
    "sg:phone":"+41 62 386 22 22",
    "sg:postcode":"4628",
    "sg:province":"Solothurn",
    "sg:tags":[
        "versicherungsagenturen",
        "-broker"
    ],
    "wof:name":"Die Mobiliar Versicherungen & Vorsorge",
    "wof:placetype":"venue"
},
  "geometry": {"coordinates":[7.8096561432,47.2705307007],"type":"Point"}
}