{
  "type": "Feature",
  "properties": {
    "addr:full":"Eichstrasse 44 Glattbrugg Z\u00fcrich 8152",
    "addr:housenumber":"44",
    "addr:postcode":"8152",
    "addr:street":"Eichstrasse",
    "iso:country":"CH",
    "sg:address":"Eichstrasse 44",
    "sg:city":"Glattbrugg",
    "sg:orig_category":"Betrieb U technische Hilfsdienste des Kultur U Unterhaltungswesens",
    "sg:phone":"+41 18802203",
    "sg:postcode":"8152",
    "sg:province":"Z\u00fcrich",
    "wof:name":"Opera Veranstaltungen Gmbh",
    "wof:placetype":"venue"
},
  "geometry": {"coordinates":[8.556444,47.431412],"type":"Point"}
}