{
  "type": "Feature",
  "properties": {
    "iso:country":"CH",
    "sg:address":"Bahnhofstrasse 11",
    "sg:city":"Zug",
    "sg:orig_category":"Handelsvermittlung von Waren ohne ausgepr\u00e4gten Schwerpunkt Markt U Meinungsforschung",
    "sg:phone":"+41 41 720 42 63",
    "sg:postcode":"6300",
    "sg:province":"Zug",
    "wof:name":"Caprixor Gmbh",
    "wof:placetype":"venue"
},
  "geometry": {"coordinates":[8.2710876465,46.9404907227],"type":"Point"}
}