{
  "type": "Feature",
  "properties": {
    "iso:country":"CH",
    "sg:address":"M\u00fchlerainstrasse 17",
    "sg:city":"F\u00fcllinsdorf",
    "sg:orig_category":"Kantonalbanken",
    "sg:phone":"+41 61 906 92 11",
    "sg:postcode":"4414",
    "sg:province":"Basel-Landschaft",
    "wof:name":"Basellandschaftliche Kantonalbank",
    "wof:placetype":"venue"
},
  "geometry": {"coordinates":[7.7257900238,47.5022125244],"type":"Point"}
}