{
  "type": "Feature",
  "properties": {
    "iso:country":"CH",
    "sg:address":"Les T\u00eates 1875 Morgins. Postfach",
    "sg:city":"Morgins",
    "sg:classifiers":[
        {
            "category":"Travel",
            "subcategory":"Hotels & Motels",
            "type":"Entertainment"
        }
    ],
    "sg:postcode":"1875",
    "sg:province":"Valais",
    "sg:tags":[
        "hotels",
        "mit",
        "restaurant"
    ],
    "wof:name":"La Rosablanche Verbier Sa",
    "wof:placetype":"venue"
},
  "geometry": {"coordinates":[7.2124481201,46.0804595947],"type":"Point"}
}