{
  "type": "Feature",
  "properties": {
    "iso:country":"CH",
    "sg:address":"Haus Elias",
    "sg:city":"Zermatt",
    "sg:orig_category":"Herstellung von k\u00e4lte U lufttechnischen Erzeugnissen f\u00fcr gewerbliche Zwecke",
    "sg:postcode":"3920",
    "sg:province":"Valais",
    "wof:name":"Sanitherm, Perren Raoul, Tech. B\u00fcro Sanit\u00e4r-heizungen",
    "wof:placetype":"venue"
},
  "geometry": {"coordinates":[7.7484002113,46.024143219],"type":"Point"}
}