{
  "type": "Feature",
  "properties": {
    "iso:country":"CH",
    "sg:address":"Route De Soleure 14",
    "sg:city":"St-blaise",
    "sg:classifiers":[
        {
            "category":"Government",
            "subcategory":"Fire Station",
            "type":"Public Place"
        }
    ],
    "sg:phone":"+41 32 756 96 20",
    "sg:postcode":"2072",
    "sg:province":"Neuch\u00e2tel",
    "sg:tags":[
        "copier",
        "digital"
    ],
    "wof:name":"P&g Solutions Sa",
    "wof:placetype":"venue"
},
  "geometry": {"coordinates":[6.9935421944,47.0147514343],"type":"Point"}
}