{
  "type": "Feature",
  "properties": {
    "addr:full":"Mettlenstrasse 1 Eschenz Thurgau 8264",
    "addr:housenumber":"1",
    "addr:postcode":"8264",
    "addr:street":"Mettlenstrasse",
    "iso:country":"CH",
    "sg:address":"Mettlenstrasse 1",
    "sg:city":"Eschenz",
    "sg:orig_category":"Arztpraxen",
    "sg:phone":"+41 52 742 02 02",
    "sg:postcode":"8264",
    "sg:province":"Thurgau",
    "wof:name":"Dres Med.h. Lang & H. Spycher Aerzte F\u00fcr Allg.medizin Fmh",
    "wof:placetype":"venue"
},
  "geometry": {"coordinates":[8.861994,47.653805],"type":"Point"}
}