{
  "type": "Feature",
  "properties": {
    "iso:country":"CH",
    "sg:address":"Hauptstrasse 43a",
    "sg:city":"Bronschhofen",
    "sg:orig_category":"Grosshandel mit Nahrungsmitteln, Getr\u00e4nken U Tabakwaren ohne ausgepr\u00e4gten Schwerpunkt",
    "sg:phone":"+41 71 877 13 53",
    "sg:postcode":"9552",
    "sg:province":"St. Gallen",
    "wof:name":"Spar Supermarkt",
    "wof:placetype":"venue"
},
  "geometry": {"coordinates":[9.4905719757,47.4157562256],"type":"Point"}
}