{
  "type": "Feature",
  "properties": {
    "iso:country":"CH",
    "sg:address":"Unter Altstadt 40",
    "sg:city":"Zug",
    "sg:orig_category":"Unclassifiable Establishments",
    "sg:phone":"+41 19110296",
    "sg:postcode":"6300",
    "sg:province":"Zug",
    "wof:name":"Kommunikation & Kultur, H\u00f6chli",
    "wof:placetype":"venue"
},
  "geometry": {"coordinates":[8.5136871338,47.1649932861],"type":"Point"}
}