{
  "type": "Feature",
  "properties": {
    "iso:country":"CH",
    "sg:address":"Unterbiel 21",
    "sg:city":"Reigoldswil",
    "sg:orig_category":"Architekturb\u00fcros",
    "sg:phone":"+41 61 941 16 10",
    "sg:postcode":"4418",
    "sg:province":"Basel-Landschaft",
    "wof:name":"Kurt Roth Architekturb\u00fcro",
    "wof:placetype":"venue"
},
  "geometry": {"coordinates":[7.6906337738,47.3992538452],"type":"Point"}
}