{
  "type": "Feature",
  "properties": {
    "iso:country":"CH",
    "sg:address":"1374",
    "sg:city":"Corcelles-chavorn",
    "sg:classifiers":[
        {
            "category":"Social Services",
            "subcategory":"Retirement Home",
            "type":"Services"
        }
    ],
    "sg:phone":"+41 24 441 41 19",
    "sg:postcode":"1374",
    "sg:province":"Vaud",
    "sg:tags":[
        "pflegeheime",
        "u",
        "alters"
    ],
    "wof:name":"Etablissement M\u00e9dico-social Le Pr\u00e9-carr\u00e9",
    "wof:placetype":"venue"
},
  "geometry": {"coordinates":[6.57381,46.708019],"type":"Point"}
}