{
  "type": "Feature",
  "properties": {
    "iso:country":"CH",
    "sg:address":"Delsbergerallee 81",
    "sg:city":"Basel",
    "sg:orig_category":"Detailhandel mit Musikinstrumenten Detailhandel mit elektrischen Haushalts-,Radio U Fernsehger\u00e4ten s",
    "sg:phone":"+41 71 911 34 44",
    "sg:postcode":"4053",
    "sg:province":"Basel-Stadt",
    "wof:name":"Musikhaus Aerne",
    "wof:placetype":"venue"
},
  "geometry": {"coordinates":[9.0446405411,47.4630508423],"type":"Point"}
}