{
  "type": "Feature",
  "properties": {
    "iso:country":"CH",
    "sg:address":"Europastrasse 2 8152 Opfikon. Postfach",
    "sg:city":"Opfikon",
    "sg:orig_category":"Vermietung U Verpachtung von eigenen Immobilien",
    "sg:phone":"+41 12341111",
    "sg:postcode":"8152",
    "sg:province":"Z\u00fcrich",
    "wof:name":"Il Immobilien-leasing Ag",
    "wof:placetype":"venue"
},
  "geometry": {"coordinates":[8.5596761703,47.435749054],"type":"Point"}
}