{
  "type": "Feature",
  "properties": {
    "iso:country":"CH",
    "sg:address":"Listrighalde 16",
    "sg:city":"Emmenbr\u00fccke",
    "sg:orig_category":"Unclassifiable Establishments",
    "sg:postcode":"6020",
    "sg:province":"Luzern",
    "wof:name":"Roger B\u00fcchel Rco Veranstaltungstechnik",
    "wof:placetype":"venue"
},
  "geometry": {"coordinates":[9.5634069443,47.3186531067],"type":"Point"}
}