{
  "type": "Feature",
  "properties": {
    "addr:full":"Morgenstrasse 136 Bern Bern 3018",
    "addr:housenumber":"136",
    "addr:postcode":"3018",
    "addr:street":"Morgenstrasse",
    "iso:country":"CH",
    "sg:address":"Morgenstrasse 136",
    "sg:city":"Bern",
    "sg:orig_category":"Datenverarbeitungsdienste Softwareentwicklung U beratung",
    "sg:phone":"+41 31 990 11 11",
    "sg:postcode":"3018",
    "sg:province":"Bern",
    "wof:name":"Wistar Informatik Ag",
    "wof:placetype":"venue"
},
  "geometry": {"coordinates":[7.3883,46.934265],"type":"Point"}
}