{
  "type": "Feature",
  "properties": {
    "iso:country":"CH",
    "sg:address":"Hauptstrasse 98 9052 Niederteufen. Postfach",
    "sg:city":"Niederteufen",
    "sg:orig_category":"Herstellung von Duft U K\u00f6rperpflegemitteln",
    "sg:phone":"+41 71 333 11 82",
    "sg:postcode":"9052",
    "sg:province":"Appenzell Ausserrhoden",
    "wof:name":"Suhner Stephan",
    "wof:placetype":"venue"
},
  "geometry": {"coordinates":[9.3681087494,47.3921279907],"type":"Point"}
}