{
  "type": "Feature",
  "properties": {
    "iso:country":"CH",
    "sg:address":"Trachslauerstrasse 68",
    "sg:city":"Einsiedeln",
    "sg:orig_category":"Detailhandel mit Metallwaren, Anstrichmitteln, Glaswaren, Bau U Heimwerkerbedarf Grosshandel mit Eis",
    "sg:phone":"+41 55 422 18 03",
    "sg:postcode":"8840",
    "sg:province":"Schwyz",
    "wof:name":"Menerga Ag",
    "wof:placetype":"venue"
},
  "geometry": {"coordinates":[8.7395420074,47.1182518005],"type":"Point"}
}