{
  "type": "Feature",
  "properties": {
    "iso:country":"CH",
    "sg:address":"Ryf 56",
    "sg:city":"Morat",
    "sg:classifiers":[
        {
            "category":"Professional",
            "subcategory":"Employment Agencies",
            "type":"Services"
        }
    ],
    "sg:phone":"+41 26 672 32 32",
    "sg:postcode":"3280",
    "sg:province":"Fribourg",
    "sg:tags":[
        "personal",
        "u",
        "stellenvermittlung"
    ],
    "wof:name":"Adecco Ressources Humaines Sa",
    "wof:placetype":"venue"
},
  "geometry": {"coordinates":[7.1170539856,46.9296684265],"type":"Point"}
}