{
  "type": "Feature",
  "properties": {
    "iso:country":"CH",
    "sg:address":"Bahnhofstrasse 44 4303 Kaiseraugst. Postfach 62",
    "sg:city":"Kaiseraugst",
    "sg:orig_category":"Grosshandel mit Erzen U Metallen Herstellung von Metallerzeugnissen ohne Maschinenbau",
    "sg:phone":"+41 62 866 32 32",
    "sg:postcode":"4303",
    "sg:province":"Aargau",
    "wof:name":"Wetzel Ag Sisseln",
    "wof:placetype":"venue"
},
  "geometry": {"coordinates":[7.9860110283,47.5497398376],"type":"Point"}
}