{
  "type": "Feature",
  "properties": {
    "iso:country":"CH",
    "sg:address":"Eichwatt 1 8105 Watt. Postfach 32",
    "sg:city":"Watt",
    "sg:orig_category":"Architektur U Ingenieurb\u00fcros",
    "sg:phone":"+41 21 943 48 34",
    "sg:postcode":"8105",
    "sg:province":"Z\u00fcrich",
    "wof:name":"Hagin Roger",
    "wof:placetype":"venue"
},
  "geometry": {"coordinates":[6.877618,46.471401],"type":"Point"}
}