{
  "type": "Feature",
  "properties": {
    "addr:full":"Voa Princiapla 54 7082 Vaz/obervaz. Postfach Lenzerheide/lai Graubunden 7078",
    "addr:housenumber":"54",
    "addr:postcode":"7082;7078",
    "addr:street":"Voa Princiapla;Vaz / Obervaz. Postfach",
    "iso:country":"CH",
    "sg:address":"Voa Princiapla 54 7082 Vaz/obervaz. Postfach",
    "sg:city":"Lenzerheide/lai",
    "sg:orig_category":"Detailhandel mit Bekleidung",
    "sg:postcode":"7078",
    "sg:province":"Graubunden",
    "wof:name":"Sebregondi-z\u00e4ch Theresia",
    "wof:placetype":"venue"
},
  "geometry": {"coordinates":[9.55963,46.75502],"type":"Point"}
}