{
  "type": "Feature",
  "properties": {
    "iso:country":"CH",
    "sg:address":"Amthausstrasse 21a",
    "sg:city":"Dornach",
    "sg:orig_category":"Gesundheitswesen",
    "sg:phone":"+41 61 702 03 09",
    "sg:postcode":"4143",
    "sg:province":"Solothurn",
    "wof:name":"Th\u00fcring H.p. Sporttherapie Und Massage",
    "wof:placetype":"venue"
},
  "geometry": {"coordinates":[7.6082978249,47.4883308411],"type":"Point"}
}