{
  "type": "Feature",
  "properties": {
    "iso:country":"CH",
    "sg:address":"Incella",
    "sg:city":"Brissago",
    "sg:orig_category":"Vereine Musik/Blasmusik",
    "sg:postcode":"6614",
    "sg:province":"Ticino",
    "wof:name":"Filarmonica Brissaghese",
    "wof:placetype":"venue"
},
  "geometry": {"coordinates":[8.7016801834,46.1166000366],"type":"Point"}
}