{
  "type": "Feature",
  "properties": {
    "iso:country":"CH",
    "sg:address":"Menznauerstrasse 8",
    "sg:city":"Wolhusen",
    "sg:orig_category":"Unclassifiable Establishments",
    "sg:postcode":"6110",
    "sg:province":"Luzern",
    "wof:name":"Zum Bastelb\u00e4r Kehrli",
    "wof:placetype":"venue"
},
  "geometry": {"coordinates":[8.0735464096,47.0594825745],"type":"Point"}
}