{
  "type": "Feature",
  "properties": {
    "addr:full":"Carouge Rue De 28 1205 Gen\u00e8ve. Postfach Gen\u00e8ve Gen\u00e8ve 1205",
    "addr:housenumber":"28",
    "addr:postcode":"1205;postfach;1205",
    "addr:street":"Rue De",
    "iso:country":"CH",
    "sg:address":"Carouge Rue De 28 1205 Gen\u00e8ve. Postfach",
    "sg:city":"Gen\u00e8ve",
    "sg:orig_category":"Detailhandel mit Bekleidung",
    "sg:postcode":"1205",
    "sg:province":"Gen\u00e8ve",
    "wof:name":"Sarolf Import Mohamed Ridha Ouena",
    "wof:placetype":"venue"
},
  "geometry": {"coordinates":[6.143083,46.195728],"type":"Point"}
}