{
  "type": "Feature",
  "properties": {
    "iso:country":"CH",
    "sg:address":"Winterthurerstrasse 667",
    "sg:city":"Z\u00fcrich",
    "sg:orig_category":"Grosshandel mit Eisenwaren sowie Installationsbedarf f\u00fcr Gas, Wasser U Heizung",
    "sg:phone":"+41 41553510",
    "sg:postcode":"8051",
    "sg:province":"Z\u00fcrich",
    "wof:name":"Fridon Ag",
    "wof:placetype":"venue"
},
  "geometry": {"coordinates":[8.310426712,46.9898681641],"type":"Point"}
}