{
  "type": "Feature",
  "properties": {
    "addr:full":"D\u00f6rrmattweg 25 Frick Aargau 5070",
    "addr:housenumber":"25",
    "addr:postcode":"5070",
    "addr:street":"Doerrmattweg",
    "iso:country":"CH",
    "sg:address":"D\u00f6rrmattweg 25",
    "sg:city":"Frick",
    "sg:classifiers":[
        {
            "category":"Manufacturing",
            "subcategory":"Glass & Minerals",
            "type":"Manufacturing & Wholesale Goods"
        }
    ],
    "sg:phone":"+41 62 865 10 40",
    "sg:postcode":"5070",
    "sg:province":"Aargau",
    "sg:tags":[
        "melamine",
        "coated",
        "resin",
        "chipboard"
    ],
    "wof:name":"Hobak Frick Ag",
    "wof:placetype":"venue"
},
  "geometry": {"coordinates":[8.012458,47.505901],"type":"Point"}
}