{
  "type": "Feature",
  "properties": {
    "iso:country":"CH",
    "sg:address":"Aarauerstrasse 1",
    "sg:city":"Sch\u00f6ftland",
    "sg:orig_category":"Non-Classified Establishments",
    "sg:postcode":"5040",
    "sg:province":"Aargau",
    "wof:name":"Hair Creativ Daniel",
    "wof:placetype":"venue"
},
  "geometry": {"coordinates":[9.3780899048,47.4254989624],"type":"Point"}
}