{
  "type": "Feature",
  "properties": {
    "addr:full":"Gr\u00fcndenstrasse 58 Flurlingen Z\u00fcrich 8247",
    "addr:housenumber":"58",
    "addr:postcode":"8247",
    "addr:street":"Gruendenstrasse",
    "iso:country":"CH",
    "sg:address":"Gr\u00fcndenstrasse 58",
    "sg:city":"Flurlingen",
    "sg:orig_category":"Architektur U Ingenieurb\u00fcros Architekturb\u00fcros",
    "sg:phone":"+41 52 659 37 15",
    "sg:postcode":"8247",
    "sg:province":"Z\u00fcrich",
    "wof:name":"Architekturb\u00fcro Meisterhans Max",
    "wof:placetype":"venue"
},
  "geometry": {"coordinates":[8.626506,47.687901],"type":"Point"}
}