{
  "type": "Feature",
  "properties": {
    "iso:country":"CH",
    "sg:address":"Mittelg\u00e4ustrasse 63",
    "sg:city":"Gunzgen",
    "sg:orig_category":"Ger\u00fcstbau Sonstiger spezialisierter Hoch U Tiefbau",
    "sg:phone":"+41 61 411 16 00",
    "sg:postcode":"4617",
    "sg:province":"Solothurn",
    "wof:name":"Kapulica Ag Ger\u00fcstbau & Montagen",
    "wof:placetype":"venue"
},
  "geometry": {"coordinates":[7.5955438614,47.4882736206],"type":"Point"}
}