{
  "type": "Feature",
  "properties": {
    "iso:country":"CH",
    "sg:city":"Magadino",
    "sg:classifiers":[
        {
            "category":"Banks & Credit Unions",
            "subcategory":"Bank",
            "type":"Services"
        }
    ],
    "sg:phone":"+41 4193611744",
    "sg:postcode":"6573",
    "sg:province":"Ticino",
    "wof:name":"Cassa Raiffeisen",
    "wof:placetype":"venue"
},
  "geometry": {"coordinates":[8.85611,46.148571],"type":"Point"}
}