{
  "type": "Feature",
  "properties": {
    "iso:country":"CH",
    "sg:address":"Bahnhofplatz 2",
    "sg:city":"Trubschachen",
    "sg:classifiers":[
        {
            "category":"Travel",
            "subcategory":"Hotels & Motels",
            "type":"Entertainment"
        }
    ],
    "sg:phone":"+41 34 495 51 22",
    "sg:postcode":"3555",
    "sg:province":"Bern",
    "sg:tags":[
        "hotels",
        "mit",
        "restaurant"
    ],
    "wof:name":"Hotel Bahnhof",
    "wof:placetype":"venue"
},
  "geometry": {"coordinates":[7.8461899757,46.9223976135],"type":"Point"}
}