{
  "type": "Feature",
  "properties": {
    "iso:country":"CH",
    "sg:address":"Br\u00fcnigstrasse 142",
    "sg:city":"Sarnen",
    "sg:orig_category":"Detailhandel mit Schuhen Detailhandel mit Schuhen U Lederwaren",
    "sg:phone":"+41 41 660 37 00",
    "sg:postcode":"6060",
    "sg:province":"Obwalden",
    "wof:name":"Schuhhaus Odermatt.",
    "wof:placetype":"venue"
},
  "geometry": {"coordinates":[8.2460622787,46.8968086243],"type":"Point"}
}