{
  "type": "Feature",
  "properties": {
    "iso:country":"CH",
    "sg:address":"La Cour 65a",
    "sg:city":"Chevenez",
    "sg:orig_category":"Allgemeiner Hoch U Tiefbau Allgemeiner Hochbau",
    "sg:phone":"+41 79 251 27 82",
    "sg:postcode":"2906",
    "sg:province":"Jura",
    "wof:name":"Charles Comment Entreprise De Construction",
    "wof:placetype":"venue"
},
  "geometry": {"coordinates":[6.9993,47.391541],"type":"Point"}
}