{
  "type": "Feature",
  "properties": {
    "iso:country":"CH",
    "sg:address":"Crans 1978 Lens. Postfach",
    "sg:city":"Crans-sur-sierre",
    "sg:orig_category":"G\u00fcterbef\u00f6rderung im Strassenverkehr",
    "sg:postcode":"3963",
    "sg:province":"Valais",
    "wof:name":"Emery Marcel, Entreprise De Transport",
    "wof:placetype":"venue"
},
  "geometry": {"coordinates":[7.4502239227,46.2898712158],"type":"Point"}
}