{
  "type": "Feature",
  "properties": {
    "iso:country":"CH",
    "sg:address":"Alte Simplonstrasse 23",
    "sg:city":"Brig",
    "sg:orig_category":"Vermietung U Verpachtung von eigenen Immobilien",
    "sg:phone":"+41 56 622 88 66",
    "sg:postcode":"3900",
    "sg:province":"Valais",
    "wof:name":"Heimbau-genossenschaft Bachmattli",
    "wof:placetype":"venue"
},
  "geometry": {"coordinates":[8.2703018188,47.3499259949],"type":"Point"}
}