{
  "type": "Feature",
  "properties": {
    "iso:country":"CH",
    "sg:address":"Klosterzelgstrasse 16",
    "sg:city":"Windisch",
    "sg:orig_category":"Vereine Diverse",
    "sg:phone":"+41 56 442 09 80",
    "sg:postcode":"5210",
    "sg:province":"Aargau",
    "wof:name":"Federblatt Verein",
    "wof:placetype":"venue"
},
  "geometry": {"coordinates":[8.2122859955,47.478515625],"type":"Point"}
}