{
  "type": "Feature",
  "properties": {
    "iso:country":"CH",
    "sg:address":"B\u00f6sch 43a",
    "sg:city":"H\u00fcnenberg",
    "sg:orig_category":"Detailhandel mit S\u00e4uglings U Kinderbekleidung Herstellung von W\u00e4sche",
    "sg:phone":"+41 41 760 60 47",
    "sg:postcode":"6331",
    "sg:province":"Zug",
    "wof:name":"Kids Gmbh",
    "wof:placetype":"venue"
},
  "geometry": {"coordinates":[8.4376420975,47.1618881226],"type":"Point"}
}