{
  "type": "Feature",
  "properties": {
    "iso:country":"CH",
    "sg:address":"Suisse Route De 140",
    "sg:city":"Versoix",
    "sg:orig_category":"Detailhandel mit elektrischen Haushalts-,Radio U Fernsehger\u00e4ten sowie Musikinstrumenten",
    "sg:phone":"+41 22552060",
    "sg:postcode":"1290",
    "sg:province":"Gen\u00e8ve",
    "wof:name":"Synthetic Records S\u00e0rl",
    "wof:placetype":"venue"
},
  "geometry": {"coordinates":[6.1671500206,46.280292511],"type":"Point"}
}