{
  "type": "Feature",
  "properties": {
    "iso:country":"CH",
    "sg:address":"Place De La Poste 1",
    "sg:city":"Del\u00e9mont",
    "sg:orig_category":"Detailhandel mit Radio U Fernsehger\u00e4ten",
    "sg:phone":"+41 32 422 14 55",
    "sg:postcode":"2800",
    "sg:province":"Jura",
    "wof:name":"Swisscom-shop",
    "wof:placetype":"venue"
},
  "geometry": {"coordinates":[7.3485980034,47.3621063232],"type":"Point"}
}