{
  "type": "Feature",
  "properties": {
    "addr:full":"Henric Petri-strasse 35 4051 Basel. Postfach 164 Basel Basel-Stadt 4051",
    "addr:housenumber":"35;164",
    "addr:postcode":"4051;4051",
    "addr:street":"Henric Petri-Strasse;Postfach",
    "iso:country":"CH",
    "sg:address":"Henric Petri-strasse 35 4051 Basel. Postfach 164",
    "sg:city":"Basel",
    "sg:orig_category":"Aktivit\u00e4t der Bankinstitute",
    "sg:phone":"+41 61 205 12 12",
    "sg:postcode":"4051",
    "sg:province":"Basel-Stadt",
    "wof:name":"Scobag Ag Verm\u00f6gensverwaltungsbank, Wertpapierhandel Usw.",
    "wof:placetype":"venue"
},
  "geometry": {"coordinates":[7.594192,47.551277],"type":"Point"}
}