{
  "type": "Feature",
  "properties": {
    "iso:country":"CH",
    "sg:address":"Rheinfallstrasse 9",
    "sg:city":"Neuhausen",
    "sg:classifiers":[
        {
            "category":"Personal",
            "subcategory":"Nail Salon",
            "type":"Services"
        }
    ],
    "sg:phone":"+41 52 672 50 22",
    "sg:postcode":"8212",
    "sg:province":"Schaffhausen",
    "sg:tags":[
        "manicure"
    ],
    "wof:name":"Maria Kozak Nail-kosmetik",
    "wof:placetype":"venue"
},
  "geometry": {"coordinates":[8.6166763306,47.6806945801],"type":"Point"}
}