{
  "type": "Feature",
  "properties": {
    "iso:country":"CH",
    "sg:address":"Halen 60",
    "sg:city":"Herrenschwanden",
    "sg:orig_category":"Werbegrafikateliers",
    "sg:phone":"+41 31 302 98 78",
    "sg:postcode":"3037",
    "sg:province":"Bern",
    "wof:name":"J\u00fcrg Peter Grafisches Atelier",
    "wof:placetype":"venue"
},
  "geometry": {"coordinates":[7.4180898666,46.9780311584],"type":"Point"}
}