{
  "type": "Feature",
  "properties": {
    "iso:country":"CH",
    "sg:address":"L\u00e4nggassstrasse 34a",
    "sg:city":"Bern",
    "sg:orig_category":"Detailhandel mit Bekleidung",
    "sg:phone":"+41 31 302 50 44",
    "sg:postcode":"3012",
    "sg:province":"Bern",
    "wof:name":"Wizo Bern Second Hand Shop",
    "wof:placetype":"venue"
},
  "geometry": {"coordinates":[7.432164,46.953594],"type":"Point"}
}