{
  "type": "Feature",
  "properties": {
    "iso:country":"CH",
    "sg:address":"Dorfplatz 15",
    "sg:city":"Zumikon",
    "sg:orig_category":"Detailhandel mit Damenbekleidung Detailhandel mit S\u00e4uglings U Kinderbekleidung",
    "sg:phone":"+41 19190452",
    "sg:postcode":"8126",
    "sg:province":"Z\u00fcrich",
    "wof:name":"Heidi Hefti Domino Fashion Corner",
    "wof:placetype":"venue"
},
  "geometry": {"coordinates":[8.6237363815,47.3321037292],"type":"Point"}
}