{
  "type": "Feature",
  "properties": {
    "iso:country":"CH",
    "sg:address":"Talhofweg 20",
    "sg:city":"Winterthur",
    "sg:orig_category":"Arztpraxen",
    "sg:phone":"+41 55 282 39 33",
    "sg:postcode":"8408",
    "sg:province":"Z\u00fcrich",
    "wof:name":"Dr.med.hans Schwarz Arzt F.allgemeine Medizin Fmh",
    "wof:placetype":"venue"
},
  "geometry": {"coordinates":[8.922377,47.241066],"type":"Point"}
}