{
  "type": "Feature",
  "properties": {
    "iso:country":"CH",
    "sg:address":"Gasstrasse 14",
    "sg:city":"Liestal",
    "sg:orig_category":"Chemin\u00e9e- and Ofenbau",
    "sg:phone":"+41 61 922 11 41",
    "sg:postcode":"4410",
    "sg:province":"Basel-Landschaft",
    "wof:name":"Pablo Wennberg Ofenbau",
    "wof:placetype":"venue"
},
  "geometry": {"coordinates":[7.733564,47.486591],"type":"Point"}
}