{
  "type": "Feature",
  "properties": {
    "iso:country":"CH",
    "sg:address":"Ziegelackerstr. 11",
    "sg:city":"Bern",
    "sg:orig_category":"Health - equipments and instruments Mechanical Engineering - machines Metals - machinery and equipme",
    "sg:phone":"+41 32 373 33 64",
    "sg:postcode":"3027",
    "sg:province":"Bern",
    "wof:name":"Amg Studen Sa",
    "wof:placetype":"venue"
},
  "geometry": {"coordinates":[7.307079792,47.108833313],"type":"Point"}
}