{
  "type": "Feature",
  "properties": {
    "iso:country":"CH",
    "sg:address":"Alte Steinhauserstrasse 19",
    "sg:city":"Cham",
    "sg:orig_category":"Chemische Industrie Grosshandel mit chemischen Erzeugnissen",
    "sg:phone":"+41 32 724 45 75",
    "sg:postcode":"6330",
    "sg:province":"Zug",
    "wof:name":"Prochimac Sa",
    "wof:placetype":"venue"
},
  "geometry": {"coordinates":[6.92799,46.991726],"type":"Point"}
}