{
  "type": "Feature",
  "properties": {
    "iso:country":"CH",
    "sg:address":"Maygutstr. 20 3098 K\u00f6niz. Postfach",
    "sg:city":"Wabern",
    "sg:orig_category":"Sonstige Kultur U Unterhaltungseinrichtungen",
    "sg:postcode":"3084",
    "sg:province":"Bern",
    "wof:name":"Wenger Irene + Beck Ursula.",
    "wof:placetype":"venue"
},
  "geometry": {"coordinates":[7.4605798721,46.9264373779],"type":"Point"}
}