{
  "type": "Feature",
  "properties": {
    "iso:country":"CH",
    "sg:address":"Mitteldorfstr. 272",
    "sg:city":"Oeschgen",
    "sg:orig_category":"Herstellung von Konstruktionsteilen, Fertigbauteilen U Ausbauelementen aus Holz",
    "sg:postcode":"5072",
    "sg:province":"Aargau",
    "wof:name":"Keiser-stutz Stefan",
    "wof:placetype":"venue"
},
  "geometry": {"coordinates":[8.0192165375,47.5179367065],"type":"Point"}
}