{
  "type": "Feature",
  "properties": {
    "iso:country":"CH",
    "sg:address":"Florastrasse 26",
    "sg:city":"Uster",
    "sg:orig_category":"Kinderkrippen U horte",
    "sg:phone":"+41 19401162",
    "sg:postcode":"8610",
    "sg:province":"Z\u00fcrich",
    "wof:name":"Kinderkrippe",
    "wof:placetype":"venue"
},
  "geometry": {"coordinates":[8.7216281891,47.3471031189],"type":"Point"}
}