{
  "type": "Feature",
  "properties": {
    "iso:country":"CH",
    "sg:address":"Zihlgasse 11 8880 Walenstadt. Postfach 102",
    "sg:city":"Walenstadt",
    "sg:orig_category":"Unclassifiable Establishments",
    "sg:phone":"+41 81 710 20 81",
    "sg:postcode":"8880",
    "sg:province":"St. Gallen",
    "wof:name":"Finanzplanung G. Pischel",
    "wof:placetype":"venue"
},
  "geometry": {"coordinates":[9.3184099197,47.1251449585],"type":"Point"}
}