{
  "type": "Feature",
  "properties": {
    "iso:country":"CH",
    "sg:address":"Oltnerstrasse 6",
    "sg:city":"Sch\u00f6nenwerd",
    "sg:orig_category":"Museen",
    "sg:phone":"+41 62 858 26 41",
    "sg:postcode":"5012",
    "sg:province":"Solothurn",
    "wof:name":"Bally Schuhfabriken Ag",
    "wof:placetype":"venue"
},
  "geometry": {"coordinates":[8.0021400452,47.3718986511],"type":"Point"}
}