{
  "type": "Feature",
  "properties": {
    "addr:full":"Batteriestrasse 19 Bottmingen Basel-Landschaft 4103",
    "addr:housenumber":"19",
    "addr:postcode":"4103",
    "addr:street":"Batteriestrasse",
    "iso:country":"CH",
    "sg:address":"Batteriestrasse 19",
    "sg:city":"Bottmingen",
    "sg:classifiers":[
        {
            "category":"Banks & Credit Unions",
            "subcategory":"Bank",
            "type":"Services"
        }
    ],
    "sg:phone":"+41 61 421 86 30",
    "sg:postcode":"4103",
    "sg:province":"Basel-Landschaft",
    "wof:name":"Schweiz. Mobiliar",
    "wof:placetype":"venue"
},
  "geometry": {"coordinates":[7.576467,47.527069],"type":"Point"}
}