{
  "type": "Feature",
  "properties": {
    "iso:country":"CH",
    "sg:address":"Route De La Jeurna 19",
    "sg:city":"Cho\u00ebx",
    "sg:orig_category":"Fahrschulen, Flugschulen",
    "sg:phone":"+41 24 471 45 67",
    "sg:postcode":"1871",
    "sg:province":"Valais",
    "wof:name":"Ren\u00e9 Germanier Auto-\u00e9cole",
    "wof:placetype":"venue"
},
  "geometry": {"coordinates":[6.9605960846,46.2403297424],"type":"Point"}
}