{
  "type": "Feature",
  "properties": {
    "addr:full":"Sandstrasse 42 Glarus Glarus 8750",
    "addr:housenumber":"42",
    "addr:postcode":"8750",
    "addr:street":"Sandstrasse",
    "iso:country":"CH",
    "sg:address":"Sandstrasse 42",
    "sg:city":"Glarus",
    "sg:orig_category":"Allgemeiner Hoch U Tiefbau",
    "sg:postcode":"8750",
    "sg:province":"Glarus",
    "wof:name":"Schluep + Schori Ag, Zweigniederlassung",
    "wof:placetype":"venue"
},
  "geometry": {"coordinates":[7.363415,47.108486],"type":"Point"}
}