{
  "type": "Feature",
  "properties": {
    "iso:country":"CH",
    "sg:address":"Solothurnerstrasse 101 4600 Olten. Postfach",
    "sg:city":"Olten",
    "sg:orig_category":"Versicherungen Generalagenturen",
    "sg:phone":"+41 62 205 15 88",
    "sg:postcode":"4603",
    "sg:province":"Solothurn",
    "wof:name":"Winterthur-versicherungen Generalagentur Olten",
    "wof:placetype":"venue"
},
  "geometry": {"coordinates":[7.895840168,47.3501167297],"type":"Point"}
}