{
  "type": "Feature",
  "properties": {
    "iso:country":"CH",
    "sg:address":"Roggenweg 3",
    "sg:city":"Oensingen",
    "sg:orig_category":"Maler U Glasergewerbe Malerei",
    "sg:phone":"+41 62 396 35 25",
    "sg:postcode":"4702",
    "sg:province":"Solothurn",
    "wof:name":"J\u00fcrg & Brigitte Perren Malergesch\u00e4ft",
    "wof:placetype":"venue"
},
  "geometry": {"coordinates":[7.7235350609,47.29164505],"type":"Point"}
}