{
  "type": "Feature",
  "properties": {
    "iso:country":"CH",
    "sg:address":"Saltinisstrasse 15",
    "sg:city":"Trimmis",
    "sg:orig_category":"Arztpraxen",
    "sg:phone":"+41 81 354 99 66",
    "sg:postcode":"7203",
    "sg:province":"Graubunden",
    "wof:name":"Dr.med. Stefan Erhart Spezialarzt Fmh",
    "wof:placetype":"venue"
},
  "geometry": {"coordinates":[9.561514,46.900684],"type":"Point"}
}