{
  "type": "Feature",
  "properties": {
    "iso:country":"CH",
    "sg:address":"Birkenstrasse 25",
    "sg:city":"Neuenhof",
    "sg:orig_category":"Fahrschulen, Flugschulen",
    "sg:phone":"+41 56 406 18 75",
    "sg:postcode":"5432",
    "sg:province":"Aargau",
    "wof:name":"Autofahrschule Josef Setz",
    "wof:placetype":"venue"
},
  "geometry": {"coordinates":[8.3235902786,47.4505767822],"type":"Point"}
}