{
  "type": "Feature",
  "properties": {
    "iso:country":"CH",
    "sg:address":"Via Vignalunga 13",
    "sg:city":"Mendrisio",
    "sg:orig_category":"Druckweiterverarbeitung Offsetdruck",
    "sg:phone":"+41 91 646 41 87",
    "sg:postcode":"6850",
    "sg:province":"Ticino",
    "wof:name":"Tipo Print Di Roncoroni & Sulmini & Co",
    "wof:placetype":"venue"
},
  "geometry": {"coordinates":[8.9835519791,45.8790435791],"type":"Point"}
}