{
  "type": "Feature",
  "properties": {
    "iso:country":"CH",
    "sg:address":"Gartenstrasse 2 9038 Rehetobel. Postfach",
    "sg:city":"Rehetobel",
    "sg:orig_category":"Detailhandel mit Geschenkartikeln U Souvenirs",
    "sg:phone":"+41 71 877 22 82",
    "sg:postcode":"9038",
    "sg:province":"Appenzell Ausserrhoden",
    "wof:name":"R + S Presents Gmbh Geschenkartikel; En Gros Handel. Liegenschaften Usw",
    "wof:placetype":"venue"
},
  "geometry": {"coordinates":[9.4809541702,47.4258918762],"type":"Point"}
}