{
  "type": "Feature",
  "properties": {
    "iso:country":"CH",
    "sg:address":"Les Isles",
    "sg:city":"St-prex",
    "sg:orig_category":"Verwertung von Milch",
    "sg:postcode":"1162",
    "sg:province":"Vaud",
    "wof:name":"Soci\u00e9t\u00e9 De Laiterie Et D'agriculture De Saint-prex",
    "wof:placetype":"venue"
},
  "geometry": {"coordinates":[6.4576702118,46.4821166992],"type":"Point"}
}