{
  "type": "Feature",
  "properties": {
    "iso:country":"CH",
    "sg:address":"Oron Route D' 47 1010 Lausanne. Postfach",
    "sg:city":"Lausanne",
    "sg:orig_category":"Allgemeinbildende weiterf\u00fchrende Schulen",
    "sg:phone":"+41 21 652 37 33",
    "sg:postcode":"1010",
    "sg:province":"Vaud",
    "wof:name":"Institut International Ste Marceline Education Des Jeunes Filles, \u00e9tablissem. D'instituts D'\u00e9ducation Et D'autres Oeuvres",
    "wof:placetype":"venue"
},
  "geometry": {"coordinates":[6.808139,46.566658],"type":"Point"}
}