{
  "type": "Feature",
  "properties": {
    "addr:full":"Claridenstrasse 36 Z\u00fcrich Z\u00fcrich 8002",
    "addr:housenumber":"36",
    "addr:postcode":"8002",
    "addr:street":"Claridenstrasse",
    "iso:country":"CH",
    "sg:address":"Claridenstrasse 36",
    "sg:city":"Z\u00fcrich",
    "sg:orig_category":"Bauingenieurb\u00fcros allgemein",
    "sg:phone":"+41 12878180",
    "sg:postcode":"8002",
    "sg:province":"Z\u00fcrich",
    "wof:name":"Gsg Projekt Partner Ag Investitionsberatung",
    "wof:placetype":"venue"
},
  "geometry": {"coordinates":[8.53711,47.367985],"type":"Point"}
}