{
  "type": "Feature",
  "properties": {
    "iso:country":"CH",
    "sg:address":"Rue Du Bruye 52",
    "sg:city":"Reconvilier",
    "sg:orig_category":"Maler U Glasergewerbe",
    "sg:phone":"+41 32 724 01 01",
    "sg:postcode":"2732",
    "sg:province":"Bern",
    "wof:name":"Francesco Caruso",
    "wof:placetype":"venue"
},
  "geometry": {"coordinates":[6.8797159195,46.9831008911],"type":"Point"}
}