{
  "type": "Feature",
  "properties": {
    "iso:country":"CH",
    "sg:address":"Rue St-fran\u00e7ois 10",
    "sg:city":"St-maurice",
    "sg:classifiers":[
        {
            "category":"Education",
            "subcategory":"Library",
            "type":"Public Place"
        }
    ],
    "sg:phone":"+41 27 329 06 60",
    "sg:postcode":"1890",
    "sg:province":"Valais",
    "sg:tags":[
        "u",
        "bibliotheken",
        "archive"
    ],
    "wof:name":"Biblioth\u00e8que Du Couvent Des Capucins",
    "wof:placetype":"venue"
},
  "geometry": {"coordinates":[7.005502,46.219482],"type":"Point"}
}