{
  "type": "Feature",
  "properties": {
    "iso:country":"CH",
    "sg:address":"Rue Du Vingt-trois Juin 20",
    "sg:city":"Courroux",
    "sg:classifiers":[
        {
            "category":"Restaurant",
            "type":"Food & Drink"
        }
    ],
    "sg:phone":"+41 32 422 16 61",
    "sg:postcode":"2822",
    "sg:province":"Jura",
    "wof:name":"Caf\u00e9 De L' Etoile",
    "wof:placetype":"venue"
},
  "geometry": {"coordinates":[7.3717880249,47.362121582],"type":"Point"}
}