{
  "type": "Feature",
  "properties": {
    "iso:country":"CH",
    "sg:address":"Stahlermatten 3",
    "sg:city":"Grossdietwil",
    "sg:orig_category":"Allgemeiner Hoch U Tiefbau",
    "sg:phone":"+41 62 927 22 31",
    "sg:postcode":"6146",
    "sg:province":"Luzern",
    "wof:name":"Werner Knupp Ag Bauunternehmung",
    "wof:placetype":"venue"
},
  "geometry": {"coordinates":[7.88263,47.169907],"type":"Point"}
}