{
  "type": "Feature",
  "properties": {
    "iso:country":"CH",
    "sg:address":"Badenerstrasse 767",
    "sg:city":"Z\u00fcrich",
    "sg:orig_category":"Instandhaltung U Reparatur von Automobilen",
    "sg:phone":"+41 14314069",
    "sg:postcode":"8048",
    "sg:province":"Z\u00fcrich",
    "wof:name":"Garage Z\u00f6llig",
    "wof:placetype":"venue"
},
  "geometry": {"coordinates":[8.4778528214,47.3916511536],"type":"Point"}
}