{
  "type": "Feature",
  "properties": {
    "addr:full":"Scherzinger Strasse 2 Bottighofen Thurgau 8598",
    "addr:housenumber":"2",
    "addr:postcode":"8598",
    "addr:street":"Scherzinger Strasse",
    "iso:country":"CH",
    "sg:address":"Scherzinger Strasse 2",
    "sg:city":"Bottighofen",
    "sg:orig_category":"Arztpraxen",
    "sg:phone":"+41 71 688 44 75",
    "sg:postcode":"8598",
    "sg:province":"Thurgau",
    "wof:name":"Dr.med.elsbeth Bornhauser Aerztin F\u00fcr Allg.medizin Fmh",
    "wof:placetype":"venue"
},
  "geometry": {"coordinates":[9.209963,47.637173],"type":"Point"}
}