{
  "type": "Feature",
  "properties": {
    "iso:country":"CH",
    "sg:address":"Buzibachring 1+3",
    "sg:city":"Rothenburg",
    "sg:classifiers":[
        {
            "category":"Communications",
            "subcategory":"Film & Video Production",
            "type":"Services"
        }
    ],
    "sg:phone":"+41 41 289 01 01",
    "sg:postcode":"6023",
    "sg:province":"Luzern",
    "sg:tags":[
        "attendance",
        "working",
        "recording",
        "time",
        "flexitime",
        "software"
    ],
    "wof:name":"Hr Management Ag",
    "wof:placetype":"venue"
},
  "geometry": {"coordinates":[8.2546796799,47.0914802551],"type":"Point"}
}