{
  "type": "Feature",
  "properties": {
    "iso:country":"CH",
    "sg:address":"Hauptstrasse 43",
    "sg:city":"Welschenrohr",
    "sg:orig_category":"Gasth\u00f6fe/Gasth\u00e4user mit Restaurant Kongress- and Tagungshotels mit Restaurant",
    "sg:phone":"+41 32 639 12 91",
    "sg:postcode":"4716",
    "sg:province":"Solothurn",
    "wof:name":"Gasthof Kreuz",
    "wof:placetype":"venue"
},
  "geometry": {"coordinates":[7.5299448967,47.2809791565],"type":"Point"}
}