{
  "type": "Feature",
  "properties": {
    "iso:country":"CH",
    "sg:address":"Unterm\u00fcli 9",
    "sg:city":"Zug",
    "sg:orig_category":"Mineral\u00f6lverarbeitung",
    "sg:phone":"+41 62 827 33 38",
    "sg:postcode":"6300",
    "sg:province":"Zug",
    "wof:name":"Ade Advanced Development Enterprises Ag",
    "wof:placetype":"venue"
},
  "geometry": {"coordinates":[8.5177631378,47.1804656982],"type":"Point"}
}