{
  "type": "Feature",
  "properties": {
    "iso:country":"CH",
    "sg:address":"L\u00f6wenstrasse 16",
    "sg:city":"Kreuzlingen",
    "sg:orig_category":"Arztpraxen",
    "sg:phone":"+41 71 672 15 15",
    "sg:postcode":"8280",
    "sg:province":"Thurgau",
    "wof:name":"Dr.med.christoph L. Hofer Spezialarzt Fmh",
    "wof:placetype":"venue"
},
  "geometry": {"coordinates":[9.17179,47.647884],"type":"Point"}
}