{
  "type": "Feature",
  "properties": {
    "iso:country":"CH",
    "sg:address":"Rietli 9403 Goldach. Postfach",
    "sg:city":"Rorschach",
    "sg:orig_category":"Elektroinstallation Mechanische Werkst\u00e4tten",
    "sg:phone":"+41 71 845 30 10",
    "sg:postcode":"9401",
    "sg:province":"St. Gallen",
    "wof:name":"Sigra Ag, Rorschach",
    "wof:placetype":"venue"
},
  "geometry": {"coordinates":[9.4656553268,47.4742546082],"type":"Point"}
}