{
  "type": "Feature",
  "properties": {
    "iso:country":"CH",
    "sg:address":"Maiengasse 58",
    "sg:city":"Basel",
    "sg:orig_category":"Kinderkrippen U horte",
    "sg:phone":"+41 61 381 84 58",
    "sg:postcode":"4056",
    "sg:province":"Basel-Stadt",
    "wof:name":"Tagesheim & Kinderkrippe Des Basler Frauenvereins",
    "wof:placetype":"venue"
},
  "geometry": {"coordinates":[7.5770730972,47.5608673096],"type":"Point"}
}