{
  "type": "Feature",
  "properties": {
    "addr:full":"Industrie Rue De L' 4 Bussigny-lausanne Vaud 1030",
    "addr:housenumber":"4",
    "addr:postcode":"1030",
    "addr:street":"Rue De L '",
    "iso:country":"CH",
    "sg:address":"Industrie Rue De L' 4",
    "sg:city":"Bussigny-lausanne",
    "sg:orig_category":"Bau von Strassen, Sportanlagen U Bahnverkehrsstrecken",
    "sg:phone":"+41 21 702 52 36",
    "sg:postcode":"1030",
    "sg:province":"Vaud",
    "wof:name":"Orca Diffusion S\u00e0rl",
    "wof:placetype":"venue"
},
  "geometry": {"coordinates":[6.554208,46.548065],"type":"Point"}
}