{
  "type": "Feature",
  "properties": {
    "addr:full":"Seetalstrasse 16 Boniswil Aargau 5706",
    "addr:housenumber":"16",
    "addr:postcode":"5706",
    "addr:street":"Seetalstrasse",
    "iso:country":"CH",
    "sg:address":"Seetalstrasse 16",
    "sg:city":"Boniswil",
    "sg:classifiers":[
        {
            "category":"Bus Stop",
            "subcategory":"None",
            "type":"Transportation"
        }
    ],
    "sg:phone":"+41 62 777 13 57",
    "sg:postcode":"5706",
    "sg:province":"Aargau",
    "sg:tags":[
        "valve",
        "aerosol"
    ],
    "wof:name":"Vervaline Ag",
    "wof:placetype":"venue"
},
  "geometry": {"coordinates":[8.186293,47.314796],"type":"Point"}
}