{
  "type": "Feature",
  "properties": {
    "iso:country":"CH",
    "sg:address":"En Brit 9",
    "sg:city":"Savigny",
    "sg:orig_category":"Herstellung von Elektrizit\u00e4tsverteilungs U schalteinrichtungen",
    "sg:phone":"+41 21 781 34 00",
    "sg:postcode":"1073",
    "sg:province":"Vaud",
    "wof:name":"Artega, Luchino Samuel",
    "wof:placetype":"venue"
},
  "geometry": {"coordinates":[6.7360630035,46.5356788635],"type":"Point"}
}