{
  "type": "Feature",
  "properties": {
    "iso:country":"CH",
    "sg:address":"Rue Des Bats 3",
    "sg:city":"Del\u00e9mont",
    "sg:orig_category":"Detailhandel mit Fleisch U Fleischwaren",
    "sg:phone":"+41 32 422 11 89",
    "sg:postcode":"2800",
    "sg:province":"Jura",
    "wof:name":"Boucherie-charcuterie Br\u00e4ndli Sa",
    "wof:placetype":"venue"
},
  "geometry": {"coordinates":[7.3463401794,47.3651275635],"type":"Point"}
}