{
  "type": "Feature",
  "properties": {
    "iso:country":"CH",
    "sg:address":"Rossweidweg 13",
    "sg:city":"Zollikofen",
    "sg:orig_category":"Wirtschaftspr\u00fcfung, Steuerberatung U Treuhand",
    "sg:postcode":"3052",
    "sg:province":"Bern",
    "wof:name":"Cmw Data Consult Ag",
    "wof:placetype":"venue"
},
  "geometry": {"coordinates":[7.453458786,46.9947814941],"type":"Point"}
}