{
  "type": "Feature",
  "properties": {
    "iso:country":"CH",
    "sg:address":"Solothurnstrasse 51",
    "sg:city":"Oensingen",
    "sg:orig_category":"Grosshandel mit Textilien",
    "sg:postcode":"4702",
    "sg:province":"Solothurn",
    "wof:name":"Schwab Hansruedi",
    "wof:placetype":"venue"
},
  "geometry": {"coordinates":[7.7118082047,47.2882003784],"type":"Point"}
}