{
  "type": "Feature",
  "properties": {
    "iso:country":"CH",
    "sg:address":"Rickenstrasse 48 8737 Gommiswald. Postfach",
    "sg:city":"Gommiswald",
    "sg:orig_category":"Herstellung von Mess U Kontrollinstrumenten U vorrichtungen",
    "sg:postcode":"8737",
    "sg:province":"St. Gallen",
    "wof:name":"Pr\u00e4zisionsschleiferei Fanton Und Drongdey",
    "wof:placetype":"venue"
},
  "geometry": {"coordinates":[9.0222511292,47.2351303101],"type":"Point"}
}