{
  "type": "Feature",
  "properties": {
    "iso:country":"CH",
    "sg:address":"Z\u00fcrcherstrasse 109",
    "sg:city":"Basel",
    "sg:orig_category":"Non-Classified Establishments",
    "sg:postcode":"4052",
    "sg:province":"Basel-Stadt",
    "wof:name":"Richard Schaub",
    "wof:placetype":"venue"
},
  "geometry": {"coordinates":[7.611823082,47.5549888611],"type":"Point"}
}