{
  "type": "Feature",
  "properties": {
    "iso:country":"CH",
    "sg:address":"Zugerstrasse 16",
    "sg:city":"Unterlunkhofen",
    "sg:orig_category":"Vereine Dramatische and Theater",
    "sg:phone":"+41 52 316 21 50",
    "sg:postcode":"8918",
    "sg:province":"Aargau",
    "wof:name":"Freie B\u00fchne Uster",
    "wof:placetype":"venue"
},
  "geometry": {"coordinates":[8.790594101,47.3164138794],"type":"Point"}
}