{
  "type": "Feature",
  "properties": {
    "iso:country":"CH",
    "sg:address":"Bruggerstrasse 171 5400 Baden. Postfach",
    "sg:city":"Baden",
    "sg:orig_category":"Nationale Postdienste",
    "sg:phone":"+41 56 222 24 57",
    "sg:postcode":"5403",
    "wof:name":"Die Schweizerische Post Baden 3 Kappelerhof",
    "wof:placetype":"venue"
},
  "geometry": {"coordinates":[8.2843942642,47.4834060669],"type":"Point"}
}