{
  "type": "Feature",
  "properties": {
    "iso:country":"CH",
    "sg:address":"Busslingerstr. 354",
    "sg:city":"Stetten",
    "sg:classifiers":[
        {
            "category":"Banks & Credit Unions",
            "subcategory":"Bank",
            "type":"Services"
        }
    ],
    "sg:phone":"+41 4156963940",
    "sg:postcode":"5608",
    "sg:province":"Aargau",
    "wof:name":"Raiffeisenkasse",
    "wof:placetype":"venue"
},
  "geometry": {"coordinates":[8.315323,47.407108],"type":"Point"}
}