{
  "type": "Feature",
  "properties": {
    "iso:country":"CH",
    "sg:address":"Les Zittes",
    "sg:city":"Chalais",
    "sg:orig_category":"Autogaragen",
    "sg:phone":"+41 27 458 57 58",
    "sg:postcode":"3966",
    "sg:province":"Valais",
    "wof:name":"Jean-pierre Hetzel Garage",
    "wof:placetype":"venue"
},
  "geometry": {"coordinates":[7.51536,46.270603],"type":"Point"}
}