{
  "type": "Feature",
  "properties": {
    "iso:country":"CH",
    "sg:address":"Spitalstrasse 68",
    "sg:city":"Schlieren",
    "sg:orig_category":"Detailhandel mit Metallwaren, Anstrichmitteln, Glaswaren, Bau U Heimwerkerbedarf",
    "sg:phone":"+41 17309165",
    "sg:postcode":"8952",
    "sg:province":"Z\u00fcrich",
    "wof:name":"Erb Walter, Comimpex",
    "wof:placetype":"venue"
},
  "geometry": {"coordinates":[8.4263286591,47.3952407837],"type":"Point"}
}