{
  "type": "Feature",
  "properties": {
    "iso:country":"CH",
    "sg:address":"8881",
    "sg:city":"Walenstadtberg",
    "sg:orig_category":"Landw. Genossenschaften Viehzucht",
    "sg:postcode":"8881",
    "sg:province":"St. Gallen",
    "wof:name":"Viehzuchtgenossenschaft",
    "wof:placetype":"venue"
},
  "geometry": {"coordinates":[9.2976503372,47.1335105896],"type":"Point"}
}