{
  "type": "Feature",
  "properties": {
    "iso:country":"CH",
    "sg:address":"Tiergartenstrasse 8852 Altendorf. Postfach 81",
    "sg:city":"Altendorf",
    "sg:orig_category":"Pensionskassen",
    "sg:phone":"+41 55 442 37 38",
    "sg:postcode":"8852",
    "sg:province":"Schwyz",
    "wof:name":"Personalf\u00fcrsorgestiftung Julius M\u00fcller Ag",
    "wof:placetype":"venue"
},
  "geometry": {"coordinates":[8.8415927887,47.1877059937],"type":"Point"}
}