{
  "type": "Feature",
  "properties": {
    "iso:country":"CH",
    "sg:address":"Piazza Statione 6600 Muralto. Postfach",
    "sg:city":"Muralto",
    "sg:orig_category":"RESTAURANTS: TEA-ROOMS",
    "sg:phone":"+41 91 744 60 98",
    "sg:postcode":"6602",
    "sg:province":"Ticino",
    "wof:name":"Bar Silo Sa",
    "wof:placetype":"venue"
},
  "geometry": {"coordinates":[8.8003940582,46.1705741882],"type":"Point"}
}