{
  "type": "Feature",
  "properties": {
    "iso:country":"CH",
    "sg:address":"Mittlere Dorfstrasse 7",
    "sg:city":"Suhr",
    "sg:orig_category":"Detailhandel mit Waren verschiedener Art, Hauptrichtung Nahrungsmittel",
    "sg:phone":"+41 62 842 43 15",
    "sg:postcode":"5034",
    "sg:province":"Aargau",
    "wof:name":"Denner Top Superdiscount",
    "wof:placetype":"venue"
},
  "geometry": {"coordinates":[8.0777406693,47.3746337891],"type":"Point"}
}