{
  "type": "Feature",
  "properties": {
    "iso:country":"CH",
    "sg:address":"3654",
    "sg:city":"Gunten",
    "sg:orig_category":"Sportvereine Turnen Vereine Damen",
    "sg:phone":"+41 31 771 18 92",
    "sg:postcode":"3654",
    "sg:province":"Bern",
    "wof:name":"Frauenturnriege",
    "wof:placetype":"venue"
},
  "geometry": {"coordinates":[7.7014298439,46.7128295898],"type":"Point"}
}