{
  "type": "Feature",
  "properties": {
    "iso:country":"CH",
    "sg:address":"Hauptstrasse 40",
    "sg:city":"K\u00fcttigen",
    "sg:orig_category":"Arztpraxen",
    "sg:phone":"+41 62 827 42 62",
    "sg:postcode":"5024",
    "sg:province":"Aargau",
    "wof:name":"Dr.med.rosanna Wernli Spezial\u00e4rztin Fmh",
    "wof:placetype":"venue"
},
  "geometry": {"coordinates":[8.048453,47.415352],"type":"Point"}
}