{
  "type": "Feature",
  "properties": {
    "iso:country":"CH",
    "sg:address":"Untermattweg 22",
    "sg:city":"Bern",
    "sg:orig_category":"Elektroinstallation Technische B\u00fcros Elektro",
    "sg:phone":"+41 19752333",
    "sg:postcode":"3027",
    "sg:province":"Bern",
    "wof:name":"Markus Knappe, Innovative Elektrotechnik",
    "wof:placetype":"venue"
},
  "geometry": {"coordinates":[8.7591590881,47.3043899536],"type":"Point"}
}