{
  "type": "Feature",
  "properties": {
    "iso:country":"CH",
    "sg:address":"Route De Lavaux 285",
    "sg:city":"Ch\u00e2telard-lutry",
    "sg:orig_category":"Saunas, Solarien, Fitnesszentren U \u00e4hnliches",
    "sg:postcode":"1095",
    "sg:province":"Vaud",
    "wof:name":"J\u00f6rge Jos\u00e9.",
    "wof:placetype":"venue"
},
  "geometry": {"coordinates":[6.6925778389,46.5009689331],"type":"Point"}
}