{
  "type": "Feature",
  "properties": {
    "iso:country":"CH",
    "sg:address":"Bach 26",
    "sg:city":"L\u00e4ngenb\u00fchl",
    "sg:orig_category":"Zimmerei, Dachdeckerei, Bauspenglerei U Abdichtung",
    "sg:postcode":"3636",
    "sg:province":"Bern",
    "wof:name":"Zysset Holzbau Gmbh",
    "wof:placetype":"venue"
},
  "geometry": {"coordinates":[7.5287408829,46.7565383911],"type":"Point"}
}