{
  "type": "Feature",
  "properties": {
    "iso:country":"CH",
    "sg:address":"Dorfplatz 13",
    "sg:city":"W\u00f6lflinswil",
    "sg:orig_category":"Herstellung von Arbeits U Berufsbekleidung",
    "sg:phone":"+41 62 865 80 60",
    "sg:postcode":"5063",
    "sg:province":"Aargau",
    "wof:name":"Techbau Arbeitssicherheit Niklaus Keel",
    "wof:placetype":"venue"
},
  "geometry": {"coordinates":[7.9981608391,47.4606399536],"type":"Point"}
}