{
  "type": "Feature",
  "properties": {
    "iso:country":"CH",
    "sg:address":"Eichlistrasse 28 6405 Immensee. Postfach",
    "sg:city":"Immensee",
    "sg:orig_category":"Verkehrs- and Tourismusb\u00fcros",
    "sg:phone":"+41 41 850 54 24",
    "sg:postcode":"6405",
    "sg:province":"Schwyz",
    "wof:name":"Verkehrsb\u00fcro",
    "wof:placetype":"venue"
},
  "geometry": {"coordinates":[8.4602603912,47.0946006775],"type":"Point"}
}