{
  "type": "Feature",
  "properties": {
    "iso:country":"CH",
    "sg:address":"Gerechtigkeitsgasse 12",
    "sg:city":"Bern",
    "sg:orig_category":"Arztpraxen",
    "sg:phone":"+41 31 311 68 88",
    "sg:postcode":"3011",
    "sg:province":"Bern",
    "wof:name":"Dr.med. Rosmarie Fey Spezial\u00e4rztin Fmh",
    "wof:placetype":"venue"
},
  "geometry": {"coordinates":[7.455591,46.94873],"type":"Point"}
}