{
  "type": "Feature",
  "properties": {
    "iso:country":"CH",
    "sg:address":"Elisabethenstrasse 16 8000 Z\u00fcrich. Postfach",
    "sg:city":"Z\u00fcrich",
    "sg:orig_category":"Softwareentwicklung U beratung",
    "sg:postcode":"8001",
    "sg:province":"Z\u00fcrich",
    "wof:name":"Escape-hosting Gmbh",
    "wof:placetype":"venue"
},
  "geometry": {"coordinates":[8.5227661133,47.3730583191],"type":"Point"}
}