{
  "type": "Feature",
  "properties": {
    "iso:country":"CH",
    "sg:address":"Burgfelderstrasse 211",
    "sg:city":"Basel",
    "sg:orig_category":"Vermietung U Verpachtung von eigenen Immobilien",
    "sg:phone":"+41 61 326 35 00",
    "sg:postcode":"4055",
    "sg:province":"Basel-Stadt",
    "wof:name":"Ifm Infrastruktur Und Facility Management Ag",
    "wof:placetype":"venue"
},
  "geometry": {"coordinates":[7.562874794,47.5673141479],"type":"Point"}
}