{
  "type": "Feature",
  "properties": {
    "iso:country":"CH",
    "sg:address":"Bahnhofstrasse 32 6300 Zug. Postfach",
    "sg:city":"Zug",
    "sg:orig_category":"Unternehmensberatung",
    "sg:phone":"+41 41 729 46 96",
    "sg:postcode":"6300",
    "sg:province":"Zug",
    "wof:name":"Idesearch Gmbh Unternehmensberatung. F\u00fchrungskr\u00e4fte; Vermittlung",
    "wof:placetype":"venue"
},
  "geometry": {"coordinates":[8.5160121918,47.1704101562],"type":"Point"}
}