{
  "type": "Feature",
  "properties": {
    "iso:country":"CH",
    "sg:address":"Kratzstrasse 6",
    "sg:city":"R\u00fcmlang",
    "sg:orig_category":"P\u00e9dicure Solarien",
    "sg:phone":"+41 18505098",
    "sg:postcode":"8153",
    "sg:province":"Z\u00fcrich",
    "wof:name":"Janet Strupler Dipl. Masseurin",
    "wof:placetype":"venue"
},
  "geometry": {"coordinates":[8.5308132172,47.4523773193],"type":"Point"}
}