{
  "type": "Feature",
  "properties": {
    "iso:country":"CH",
    "sg:address":"Dattenmattstrasse 15",
    "sg:city":"Kriens",
    "sg:orig_category":"Erzeugung U Erstbearbeitung von Blei, Zink U Zinn Glas- and Porzellanwaren Grosshandel",
    "sg:postcode":"6010",
    "sg:province":"Luzern",
    "wof:name":"Zgg Zinn Glas Gravuren Ag",
    "wof:placetype":"venue"
},
  "geometry": {"coordinates":[8.3011217117,47.0198020935],"type":"Point"}
}