{
  "type": "Feature",
  "properties": {
    "iso:country":"CH",
    "sg:address":"Bvd Helv\u00e9tique 16",
    "sg:city":"Gen\u00e8ve",
    "sg:orig_category":"Physiotherapie Sonstige Aktivit\u00e4ten der nicht-\u00e4rztlichen Medizinalberufe",
    "sg:phone":"+41 22 342 79 33",
    "sg:postcode":"1207",
    "sg:province":"Gen\u00e8ve",
    "wof:name":"Philippe Monnier Physioth\u00e9rapie",
    "wof:placetype":"venue"
},
  "geometry": {"coordinates":[6.1538667679,46.2000846863],"type":"Point"}
}