{
  "type": "Feature",
  "properties": {
    "iso:country":"CH",
    "sg:address":"Oberdorfstrasse 4",
    "sg:city":"Baar",
    "sg:orig_category":"Sportvereine Billard",
    "sg:phone":"+41 41 761 20 18",
    "sg:postcode":"6340",
    "sg:province":"Zug",
    "wof:name":"Billard Eight-ball",
    "wof:placetype":"venue"
},
  "geometry": {"coordinates":[8.5298042297,47.1960067749],"type":"Point"}
}