{
  "type": "Feature",
  "properties": {
    "iso:country":"CH",
    "sg:address":"Hertizentrum 6",
    "sg:city":"Zug",
    "sg:orig_category":"Herstellung von Kakao, Schokoladeerzeugnissen U Zuckerwaren",
    "sg:phone":"+41 31 372 27 55",
    "sg:postcode":"6300",
    "sg:province":"Zug",
    "wof:name":"Interdandy Ag",
    "wof:placetype":"venue"
},
  "geometry": {"coordinates":[8.5061779022,47.1779022217],"type":"Point"}
}