{
  "type": "Feature",
  "properties": {
    "iso:country":"CH",
    "sg:address":"Bahnhofstrasse 4",
    "sg:city":"Egerkingen",
    "sg:orig_category":"Unternehmensberatung",
    "sg:phone":"+41 62 398 01 31",
    "sg:postcode":"4622",
    "sg:province":"Solothurn",
    "wof:name":"Arconet Gmbh",
    "wof:placetype":"venue"
},
  "geometry": {"coordinates":[7.7945189476,47.3211936951],"type":"Point"}
}