{
  "type": "Feature",
  "properties": {
    "iso:country":"CH",
    "sg:address":"Kronenstrasse 6",
    "sg:city":"St\u00e4fa",
    "sg:orig_category":"Architekturb\u00fcros",
    "sg:phone":"+41 71 222 18 40",
    "sg:postcode":"8712",
    "sg:province":"Z\u00fcrich",
    "wof:name":"Risse Ralf Dipl. Architekt Htl Architekt, Planung, Projektierung Usw",
    "wof:placetype":"venue"
},
  "geometry": {"coordinates":[9.373715,47.426392],"type":"Point"}
}