{
  "type": "Feature",
  "properties": {
    "iso:country":"CH",
    "sg:address":"Abl\u00e4schstr. 80",
    "sg:city":"Glarus",
    "sg:orig_category":"Institutionen des Sozialwesens ohne Beherbergung",
    "sg:postcode":"8750",
    "sg:province":"Glarus",
    "wof:name":"Stiftung Pukllasunchis",
    "wof:placetype":"venue"
},
  "geometry": {"coordinates":[8.4654111862,47.363407135],"type":"Point"}
}