{
  "type": "Feature",
  "properties": {
    "iso:country":"CH",
    "sg:address":"Heinrich Gujer-strasse 1",
    "sg:city":"Bauma",
    "sg:orig_category":"Non-Classified Establishments",
    "sg:postcode":"8494",
    "sg:province":"Z\u00fcrich",
    "wof:name":"Heinz Schwarz Herrensalon",
    "wof:placetype":"venue"
},
  "geometry": {"coordinates":[8.8767738342,47.3684005737],"type":"Point"}
}