{
  "type": "Feature",
  "properties": {
    "iso:country":"CH",
    "sg:address":"Chemin De La Lionne",
    "sg:city":"Savigny",
    "sg:orig_category":"Betrieb von Taxis",
    "sg:postcode":"1073",
    "sg:province":"Vaud",
    "wof:name":"Taxi-t\u00e9l\u00e9phone, Porchet Michel",
    "wof:placetype":"venue"
},
  "geometry": {"coordinates":[6.710569,46.543179],"type":"Point"}
}