{
  "type": "Feature",
  "properties": {
    "addr:full":"Technoramastrasse 10 Winterthur Z\u00fcrich 8404",
    "addr:housenumber":"10",
    "addr:postcode":"8404",
    "addr:street":"Technoramastrasse",
    "iso:country":"CH",
    "sg:address":"Technoramastrasse 10",
    "sg:city":"Winterthur",
    "sg:classifiers":[
        {
            "category":"Structure",
            "subcategory":"Bridge",
            "type":"Public Place"
        }
    ],
    "sg:phone":"+41 41 670 11 51",
    "sg:postcode":"8404",
    "sg:province":"Z\u00fcrich",
    "sg:tags":[
        "construction"
    ],
    "wof:name":"Imfeld & Camenzind Ag",
    "wof:placetype":"venue"
},
  "geometry": {"coordinates":[8.270502,46.939758],"type":"Point"}
}