{
  "type": "Feature",
  "properties": {
    "iso:country":"CH",
    "sg:address":"Bahnhof-park 1",
    "sg:city":"Baar",
    "sg:orig_category":"Arztpraxen",
    "sg:phone":"+41 41 763 19 19",
    "sg:postcode":"6340",
    "sg:province":"Zug",
    "wof:name":"Dr.med.beat Ineichen Spezialarzt Fmh",
    "wof:placetype":"venue"
},
  "geometry": {"coordinates":[8.525329,47.19545],"type":"Point"}
}