{
  "type": "Feature",
  "properties": {
    "iso:country":"CH",
    "sg:address":"Kolinplatz 8",
    "sg:city":"Zug",
    "sg:orig_category":"Public-Relations-Agenturen Werbeberatung",
    "sg:phone":"+41 61 753 13 52",
    "sg:postcode":"6300",
    "sg:province":"Zug",
    "wof:name":"Dominique Hiltbrunnger Hiltbrunner Projektmanagement",
    "wof:placetype":"venue"
},
  "geometry": {"coordinates":[7.5941038132,47.4668006897],"type":"Point"}
}