{
  "type": "Feature",
  "properties": {
    "iso:country":"CH",
    "sg:address":"Talgut-zentrum 7",
    "sg:city":"Ittigen",
    "sg:classifiers":[
        {
            "category":"Restaurant",
            "type":"Food & Drink"
        }
    ],
    "sg:phone":"+41 31 921 47 17",
    "sg:postcode":"3063",
    "sg:province":"Bern",
    "wof:name":"Restaurant Badhaus",
    "wof:placetype":"venue"
},
  "geometry": {"coordinates":[7.4832038879,46.9742355347],"type":"Point"}
}