{
  "type": "Feature",
  "properties": {
    "iso:country":"CH",
    "sg:address":"Hauptstrasse 61",
    "sg:city":"M\u00f6hlin",
    "sg:orig_category":"Detailhandel mit Milcherzeugnissen U Eiern Detailhandel mit Waren verschiedener Art, Hauptrichtung N",
    "sg:postcode":"4313",
    "sg:province":"Aargau",
    "wof:name":"Ch\u00e4si M\u00f6hlin/rh-partyservice",
    "wof:placetype":"venue"
},
  "geometry": {"coordinates":[7.8435511589,47.5584564209],"type":"Point"}
}