{
  "type": "Feature",
  "properties": {
    "iso:country":"CH",
    "sg:address":"Klausstrasse 43 8008 Z\u00fcrich. Postfach 754",
    "sg:city":"Z\u00fcrich",
    "sg:classifiers":[
        {
            "category":"Professional",
            "subcategory":"Employment Agencies",
            "type":"Services"
        }
    ],
    "sg:phone":"+41 13889555",
    "sg:postcode":"8008",
    "sg:province":"Z\u00fcrich",
    "sg:tags":[
        "personal",
        "u",
        "stellenvermittlung"
    ],
    "wof:name":"Intramanagement Ag",
    "wof:placetype":"venue"
},
  "geometry": {"coordinates":[8.5516319275,47.359336853],"type":"Point"}
}