{
  "type": "Feature",
  "properties": {
    "addr:full":"Via Geretta 6 Paradiso Ticino 6900",
    "addr:housenumber":"6",
    "addr:postcode":"6900",
    "addr:street":"Via Geretta",
    "iso:country":"CH",
    "sg:address":"Via Geretta 6",
    "sg:city":"Paradiso",
    "sg:classifiers":[
        {
            "category":"Bars & Pubs",
            "type":"Food & Drink"
        }
    ],
    "sg:phone":"+41 71 222 55 54",
    "sg:postcode":"6900",
    "sg:province":"Ticino",
    "wof:name":"Keferbar",
    "wof:placetype":"venue"
},
  "geometry": {"coordinates":[9.376258,47.427341],"type":"Point"}
}