{
  "type": "Feature",
  "properties": {
    "iso:country":"CH",
    "sg:address":"Rue De La Gare 1",
    "sg:city":"Prangins",
    "sg:orig_category":"Grosshandel mit lebenden Tieren",
    "sg:phone":"+41 32 961 11 05",
    "sg:postcode":"1197",
    "sg:province":"Vaud",
    "wof:name":"Fernand Donz\u00e9 Commerce De B\u00e9tail",
    "wof:placetype":"venue"
},
  "geometry": {"coordinates":[6.9006972313,47.1846542358],"type":"Point"}
}