{
  "type": "Feature",
  "properties": {
    "iso:country":"CH",
    "sg:address":"Felsenstrasse 79",
    "sg:city":"St.gallen",
    "sg:orig_category":"Unclassifiable Establishments",
    "sg:phone":"+41 71 223 81 53",
    "sg:postcode":"9000",
    "sg:province":"St. Gallen",
    "wof:name":"Go Claude Andr\u00e9 Ribaux",
    "wof:placetype":"venue"
},
  "geometry": {"coordinates":[9.3719825745,47.4193687439],"type":"Point"}
}