{
  "type": "Feature",
  "properties": {
    "iso:country":"CH",
    "sg:address":"Unterdorf",
    "sg:city":"Oey",
    "sg:orig_category":"Detailhandel mit Fahrr\u00e4dern",
    "sg:phone":"+41 33 823 69 60",
    "sg:postcode":"3753",
    "sg:province":"Bern",
    "wof:name":"Huber Zweirad Ag",
    "wof:placetype":"venue"
},
  "geometry": {"coordinates":[7.8572101593,46.6804428101],"type":"Point"}
}