{
  "type": "Feature",
  "properties": {
    "iso:country":"CH",
    "sg:address":"Ziegeleistrasse 32c",
    "sg:city":"Steffisburg",
    "sg:orig_category":"Herstellung von Maschinen f\u00fcr die Nahrungsmittel, Getr\u00e4nkeherstellung U die Tabakverarbeitung",
    "sg:phone":"+41 33 437 33 07",
    "sg:postcode":"3612",
    "sg:province":"Bern",
    "wof:name":"Imbaumgarten",
    "wof:placetype":"venue"
},
  "geometry": {"coordinates":[7.6349320412,46.7727432251],"type":"Point"}
}