{
  "type": "Feature",
  "properties": {
    "iso:country":"CH",
    "sg:address":"Grand-rue 63",
    "sg:city":"Gland",
    "sg:orig_category":"Architektur U Ingenieurb\u00fcros",
    "sg:phone":"+41 22 364 21 35",
    "sg:postcode":"1196",
    "sg:province":"Vaud",
    "wof:name":"Christen Architectes Sa",
    "wof:placetype":"venue"
},
  "geometry": {"coordinates":[6.265333,46.424152],"type":"Point"}
}