{
  "type": "Feature",
  "properties": {
    "iso:country":"CH",
    "sg:address":"Sch\u00fctzenstrasse 19",
    "sg:city":"Herisau",
    "sg:orig_category":"Herstellung von Konstruktionsteilen, Fertigbauteilen U Ausbauelementen aus Holz",
    "sg:phone":"+41 71 351 60 87",
    "sg:postcode":"9100",
    "sg:province":"Appenzell Ausserrhoden",
    "wof:name":"Alder Robert",
    "wof:placetype":"venue"
},
  "geometry": {"coordinates":[9.2833919525,47.3909721375],"type":"Point"}
}