{
  "type": "Feature",
  "properties": {
    "iso:country":"CH",
    "sg:address":"Z\u00fcrichstrasse 13 8840 Einsiedeln. Postfach",
    "sg:city":"Einsiedeln",
    "sg:orig_category":"Feuerwehr",
    "sg:postcode":"8840",
    "sg:province":"Schwyz",
    "wof:name":"Brawass Gmbh Sanierung Von Brand- U. Wassersch\u00e4den Usw",
    "wof:placetype":"venue"
},
  "geometry": {"coordinates":[8.7433958054,47.1294593811],"type":"Point"}
}