{
  "type": "Feature",
  "properties": {
    "iso:country":"CH",
    "sg:address":"Sandstrasse 90",
    "sg:city":"Gebenstorf",
    "sg:orig_category":"Organisationen des Gesundheitswesen",
    "sg:phone":"+41 17154630",
    "sg:postcode":"5412",
    "sg:province":"Aargau",
    "wof:name":"Samariterverein",
    "wof:placetype":"venue"
},
  "geometry": {"coordinates":[8.5389976501,47.3174476624],"type":"Point"}
}