{
  "type": "Feature",
  "properties": {
    "iso:country":"CH",
    "sg:address":"Rathausplatz 4",
    "sg:city":"Sch\u00e4nis",
    "sg:orig_category":"Detailhandel mit Fleisch U Fleischwaren",
    "sg:phone":"+41 27 957 28 18",
    "sg:postcode":"8718",
    "sg:province":"St. Gallen",
    "wof:name":"Raymund Manz & Sohn Metzgerei",
    "wof:placetype":"venue"
},
  "geometry": {"coordinates":[7.9573631287,46.0964317322],"type":"Point"}
}