{
  "type": "Feature",
  "properties": {
    "iso:country":"CH",
    "sg:address":"Im Grossacher 8 8125 Zollikerberg. Postfach",
    "sg:city":"Zollikerberg",
    "sg:orig_category":"Erbringung von Dienstleistungen f\u00fcr Unternehmen",
    "sg:phone":"+41 13917862",
    "sg:postcode":"8125",
    "sg:province":"Z\u00fcrich",
    "wof:name":"Bencor Gmbh",
    "wof:placetype":"venue"
},
  "geometry": {"coordinates":[8.6005935669,47.3497085571],"type":"Point"}
}