{
  "type": "Feature",
  "properties": {
    "iso:country":"CH",
    "sg:address":"Englische Anlagen 8",
    "sg:city":"Bern",
    "sg:orig_category":"Non-Classified Establishments",
    "sg:postcode":"3005",
    "sg:province":"Bern",
    "wof:name":"Paradies G\u00e4rten Meier",
    "wof:placetype":"venue"
},
  "geometry": {"coordinates":[7.4508891106,46.9441566467],"type":"Point"}
}