{
  "type": "Feature",
  "properties": {
    "iso:country":"CH",
    "sg:address":"Untere Bahnhofstrasse 16",
    "sg:city":"Frutigen",
    "sg:orig_category":"RESTAURANTS: TEA-ROOMS",
    "sg:phone":"+41 33 671 16 61",
    "sg:postcode":"3714",
    "sg:province":"Bern",
    "wof:name":"Express-buffet Beetschen Jacques",
    "wof:placetype":"venue"
},
  "geometry": {"coordinates":[7.6512432098,46.5887794495],"type":"Point"}
}