{
  "type": "Feature",
  "properties": {
    "iso:country":"CH",
    "sg:address":"Indutriestrasse 34",
    "sg:city":"Dietlikon",
    "sg:orig_category":"Fachdetailhandel in Verkaufsr\u00e4umen",
    "sg:postcode":"8305",
    "sg:province":"Z\u00fcrich",
    "wof:name":"Lorica Ag",
    "wof:placetype":"venue"
},
  "geometry": {"coordinates":[8.6162128448,47.4122200012],"type":"Point"}
}