{
  "type": "Feature",
  "properties": {
    "iso:country":"CH",
    "sg:address":"Buochserstrasse 2",
    "sg:city":"Stans",
    "sg:orig_category":"Vermittlung von Immobilien Verwaltung von Immobilien",
    "sg:phone":"+41 41 228 11 11",
    "sg:postcode":"6370",
    "sg:province":"Nidwalden",
    "wof:name":"Balmer-etienne Treuhand Ag",
    "wof:placetype":"venue"
},
  "geometry": {"coordinates":[8.3678941727,46.9580497742],"type":"Point"}
}