{
  "type": "Feature",
  "properties": {
    "addr:full":"Route De Chandoline 1950 Sion Case Postale 51 Sion Valais 1951",
    "addr:postcode":"1950;51;1951",
    "addr:street":"Route De Chandoline;Postale",
    "iso:country":"CH",
    "sg:address":"Route De Chandoline 1950 Sion Case Postale 51",
    "sg:city":"Sion",
    "sg:orig_category":"Mechanik Stahl U Leichtmetallbau",
    "sg:phone":"+41 27 203 30 47",
    "sg:postcode":"1951",
    "sg:province":"Valais",
    "wof:name":"Ateliers De Chandoline Sa",
    "wof:placetype":"venue"
},
  "geometry": {"coordinates":[7.367769,46.223862],"type":"Point"}
}