{
  "type": "Feature",
  "properties": {
    "iso:country":"CH",
    "sg:address":"Witiweg 2",
    "sg:city":"Bettlach",
    "sg:orig_category":"Verwertung von Milch",
    "sg:postcode":"2544",
    "sg:province":"Solothurn",
    "wof:name":"K\u00e4sereigenossenschaft Bibern.",
    "wof:placetype":"venue"
},
  "geometry": {"coordinates":[7.4537668228,47.1463432312],"type":"Point"}
}