{
  "type": "Feature",
  "properties": {
    "iso:country":"CH",
    "sg:address":"Ecluse Rue De L' 21",
    "sg:city":"Neuch\u00e2tel",
    "sg:orig_category":"Markt U Meinungsforschung",
    "sg:postcode":"2000",
    "sg:province":"Neuch\u00e2tel",
    "wof:name":"Uhc Habegger Consulting",
    "wof:placetype":"venue"
},
  "geometry": {"coordinates":[8.4967756271,47.4962730408],"type":"Point"}
}