{
  "type": "Feature",
  "properties": {
    "iso:country":"CH",
    "sg:address":"Altkircherstrasse 8 4054 Basel. Postfach",
    "sg:city":"Basel",
    "sg:orig_category":"Sonstige mit der Informatik verbundene T\u00e4tigkeiten",
    "sg:phone":"+41 61 303 01 40",
    "sg:postcode":"4051",
    "sg:province":"Basel-Stadt",
    "wof:name":"Itp On Request Gmbh Beratung, Projektleitung, Qualit\u00e4tsmanagement, Programmierung, Schulung Im Informatikbereich. Personal; Vermittlung U. Unterst\u00fctzung Bei Selektion",
    "wof:placetype":"venue"
},
  "geometry": {"coordinates":[7.5705962181,47.5532264709],"type":"Point"}
}