{
  "type": "Feature",
  "properties": {
    "iso:country":"CH",
    "sg:address":"Reusstrasse 1 6038 Gisikon. Postfach",
    "sg:city":"Gisikon",
    "sg:orig_category":"Grosshandel mit Textilien",
    "sg:postcode":"6038",
    "sg:province":"Luzern",
    "wof:name":"Pm Collection Gmbh",
    "wof:placetype":"venue"
},
  "geometry": {"coordinates":[8.3977499008,47.1266746521],"type":"Point"}
}