{
  "type": "Feature",
  "properties": {
    "iso:country":"CH",
    "sg:address":"Bachtalen 20",
    "sg:city":"Hagendorn",
    "sg:orig_category":"Grosshandel mit Spielwaren Softwareentwicklung U beratung",
    "sg:phone":"+41 31 376 14 45",
    "sg:postcode":"6332",
    "sg:province":"Zug",
    "wof:name":"Polymasa Ag",
    "wof:placetype":"venue"
},
  "geometry": {"coordinates":[7.4179668427,46.9401931763],"type":"Point"}
}