{
  "type": "Feature",
  "properties": {
    "iso:country":"CH",
    "sg:address":"Route De Sorvilier 6",
    "sg:city":"B\u00e9vilard",
    "sg:orig_category":"Herstellung von Schrauben, Nieten, Ketten U Federn",
    "sg:phone":"+41 32 961 17 17",
    "sg:postcode":"2735",
    "sg:province":"Bern",
    "wof:name":"Z\u00fcrcher Fr\u00e8res Sa",
    "wof:placetype":"venue"
},
  "geometry": {"coordinates":[6.904610157,47.1760635376],"type":"Point"}
}