{
  "type": "Feature",
  "properties": {
    "iso:country":"CH",
    "sg:address":"Via Pioda 4",
    "sg:city":"Lugano",
    "sg:orig_category":"Ausl\u00e4ndisch beherrschte Finanzgesellschaften Rechtsberatung",
    "sg:phone":"+41 91 923 11 17",
    "sg:postcode":"6900",
    "sg:province":"Ticino",
    "wof:name":"Nottington Holding Bv, Amsterdam, Succursale Di Lugano",
    "wof:placetype":"venue"
},
  "geometry": {"coordinates":[8.951305,46.002975],"type":"Point"}
}