{
  "type": "Feature",
  "properties": {
    "iso:country":"CH",
    "sg:address":"Unterdorfstrasse 7",
    "sg:city":"Z\u00fcberwangen",
    "sg:orig_category":"Sportvereine Velo Rad-& Motorfahrer-Bund SRB",
    "sg:phone":"+41 71 944 35 67",
    "sg:postcode":"9523",
    "sg:province":"St. Gallen",
    "wof:name":"Fit-bike-team Wil",
    "wof:placetype":"venue"
},
  "geometry": {"coordinates":[9.0872106552,47.465877533],"type":"Point"}
}