{
  "type": "Feature",
  "properties": {
    "iso:country":"CH",
    "sg:address":"R\u00fctti",
    "sg:city":"Stechelberg",
    "sg:orig_category":"Betrieb von Taxis Instandhaltung U Reparatur von Automobilen",
    "sg:phone":"+41 33 855 12 64",
    "sg:postcode":"3824",
    "sg:province":"Bern",
    "wof:name":"Gerhard Gertsch Garage & Transporte",
    "wof:placetype":"venue"
},
  "geometry": {"coordinates":[7.90255,46.545395],"type":"Point"}
}