{
  "type": "Feature",
  "properties": {
    "iso:country":"CH",
    "sg:address":"T\u00fcrgass 12a",
    "sg:city":"W\u00e4denswil",
    "sg:orig_category":"Herstellung von Metallkonstruktionen Stahl U Leichtmetallbau",
    "sg:phone":"+41 71 973 90 84",
    "sg:postcode":"8820",
    "sg:province":"Z\u00fcrich",
    "wof:name":"Burag Kabinenbau Ag Aluminiumkabinen Und Verteilerk\u00e4sten",
    "wof:placetype":"venue"
},
  "geometry": {"coordinates":[8.9630451202,47.4618492126],"type":"Point"}
}