{
  "type": "Feature",
  "properties": {
    "iso:country":"CH",
    "sg:address":"Route De Gy 28b",
    "sg:city":"Meinier",
    "sg:orig_category":"Nationale Postdienste",
    "sg:phone":"+41 22 752 15 50",
    "sg:postcode":"1252",
    "sg:province":"Gen\u00e8ve",
    "wof:name":"La Poste Suisse",
    "wof:placetype":"venue"
},
  "geometry": {"coordinates":[6.2314548492,46.2456054688],"type":"Point"}
}