{
  "type": "Feature",
  "properties": {
    "addr:full":"Aermelgasse 49 Birr Aargau 5242",
    "addr:housenumber":"49",
    "addr:postcode":"5242",
    "addr:street":"Aermelgasse",
    "iso:country":"CH",
    "sg:address":"Aermelgasse 49",
    "sg:city":"Birr",
    "sg:classifiers":[
        {
            "category":"Manufacturing",
            "subcategory":"Electronics",
            "type":"Manufacturing & Wholesale Goods"
        }
    ],
    "sg:phone":"+41 56 444 88 46",
    "sg:postcode":"5242",
    "sg:province":"Aargau",
    "sg:tags":[
        "industrial",
        "cable"
    ],
    "wof:name":"Cda Elektronik",
    "wof:placetype":"venue"
},
  "geometry": {"coordinates":[8.196473,47.437641],"type":"Point"}
}