{
  "type": "Feature",
  "properties": {
    "iso:country":"CH",
    "sg:address":"Im Bifang 4a",
    "sg:city":"Rupperswil",
    "sg:orig_category":"Softwareentwicklung U beratung",
    "sg:phone":"+41 62 897 55 55",
    "sg:postcode":"5102",
    "sg:province":"Aargau",
    "wof:name":"Navware Baumgartner Adam",
    "wof:placetype":"venue"
},
  "geometry": {"coordinates":[8.1280508041,47.3987617493],"type":"Point"}
}