{
  "type": "Feature",
  "properties": {
    "iso:country":"CH",
    "sg:address":"Riehenstrasse 157",
    "sg:city":"Basel",
    "sg:orig_category":"Bau U Wohngenossenschaften",
    "sg:postcode":"4058",
    "sg:province":"Basel-Stadt",
    "wof:name":"Bau-& Verw.-gen.mittelfeld",
    "wof:placetype":"venue"
},
  "geometry": {"coordinates":[7.605988,47.565235],"type":"Point"}
}