{
  "type": "Feature",
  "properties": {
    "iso:country":"CH",
    "sg:address":"Im Oberen Boden 31",
    "sg:city":"Z\u00fcrich",
    "sg:orig_category":"Sportvereine Ballsport Tennis",
    "sg:phone":"+41 71 688 33 98",
    "sg:postcode":"8049",
    "sg:province":"Z\u00fcrich",
    "wof:name":"Tennisclub H\u00f6rnli Kreuzlingen",
    "wof:placetype":"venue"
},
  "geometry": {"coordinates":[9.1948261261,47.6403160095],"type":"Point"}
}