{
  "type": "Feature",
  "properties": {
    "iso:country":"CH",
    "sg:address":"Halles Place Des 4",
    "sg:city":"Neuch\u00e2tel",
    "sg:classifiers":[
        {
            "category":"Travel",
            "subcategory":"Hotels & Motels",
            "type":"Entertainment"
        }
    ],
    "sg:postcode":"2000",
    "sg:province":"Neuch\u00e2tel",
    "sg:tags":[
        "hotels",
        "mit",
        "restaurant"
    ],
    "wof:name":"Mimosa Neuch\u00e2tel Sa",
    "wof:placetype":"venue"
},
  "geometry": {"coordinates":[6.9310851097,46.9903335571],"type":"Point"}
}