{
  "type": "Feature",
  "properties": {
    "iso:country":"CH",
    "sg:address":"Riegelweidstrasse 28 8841 Gross. Postfach",
    "sg:city":"Geroldswil",
    "sg:orig_category":"Vereine Fasnacht",
    "sg:phone":"+41 55 412 14 46",
    "sg:postcode":"8954",
    "sg:province":"Z\u00fcrich",
    "wof:name":"Guggenmusik Pseudophoniker",
    "wof:placetype":"venue"
},
  "geometry": {"coordinates":[8.7718801498,47.1211967468],"type":"Point"}
}