{
  "type": "Feature",
  "properties": {
    "iso:country":"CH",
    "sg:address":"Hauptstrasse 43",
    "sg:city":"Bronschhofen",
    "sg:orig_category":"Zahnarztpraxen",
    "sg:phone":"+41 71 911 54 85",
    "sg:postcode":"9552",
    "sg:province":"St. Gallen",
    "wof:name":"Dr.med.dent.dragomir Dabetic Zahnarzt",
    "wof:placetype":"venue"
},
  "geometry": {"coordinates":[9.0338134766,47.4800262451],"type":"Point"}
}