{
  "type": "Feature",
  "properties": {
    "iso:country":"CH",
    "sg:address":"En Borny",
    "sg:city":"Tr\u00e9lex",
    "sg:orig_category":"Architektur U Ingenieurb\u00fcros",
    "sg:phone":"+41 71 311 21 93",
    "sg:postcode":"1270",
    "sg:province":"Vaud",
    "wof:name":"Walter Peter Ingenieurb\u00fcro",
    "wof:placetype":"venue"
},
  "geometry": {"coordinates":[9.324348,47.430553],"type":"Point"}
}