{
  "type": "Feature",
  "properties": {
    "iso:country":"CH",
    "sg:address":"Chemin Delay 9",
    "sg:city":"Vernier",
    "sg:classifiers":[
        {
            "category":"Retail",
            "subcategory":"Repair Shop",
            "type":"Services"
        }
    ],
    "sg:phone":"+41 32 914 16 82",
    "sg:postcode":"1214",
    "sg:province":"Gen\u00e8ve",
    "sg:tags":[
        "workshop",
        "mechanical"
    ],
    "wof:name":"Franco Longo",
    "wof:placetype":"venue"
},
  "geometry": {"coordinates":[6.8148899078,47.1020011902],"type":"Point"}
}