{
  "type": "Feature",
  "properties": {
    "addr:full":"1453 Bullet Vaud 1453",
    "addr:postcode":"1453;1453",
    "iso:country":"CH",
    "sg:address":"1453",
    "sg:city":"Bullet",
    "sg:orig_category":"Architektur U Ingenieurb\u00fcros",
    "sg:postcode":"1453",
    "sg:province":"Vaud",
    "wof:name":"Guex Andr\u00e9",
    "wof:placetype":"venue"
},
  "geometry": {"coordinates":[6.554786,46.831249],"type":"Point"}
}