{
  "type": "Feature",
  "properties": {
    "iso:country":"CH",
    "sg:address":"Wegm\u00fchleg\u00e4ssli 57/b 3072 Ostermundigen. Postfach",
    "sg:city":"Ostermundigen",
    "sg:orig_category":"Unclassifiable Establishments",
    "sg:postcode":"3072",
    "sg:province":"Bern",
    "wof:name":"Hyseni",
    "wof:placetype":"venue"
},
  "geometry": {"coordinates":[7.494538784,46.9626312256],"type":"Point"}
}