{
  "type": "Feature",
  "properties": {
    "iso:country":"CH",
    "sg:address":"6215",
    "sg:city":"Berom\u00fcnster",
    "sg:orig_category":"Schwimmb\u00e4der",
    "sg:phone":"+41 52 649 14 06",
    "sg:postcode":"6215",
    "sg:province":"Luzern",
    "wof:name":"Schwimmbad Bibern Sh",
    "wof:placetype":"venue"
},
  "geometry": {"coordinates":[8.676779747,47.782459259],"type":"Point"}
}