{
  "type": "Feature",
  "properties": {
    "iso:country":"CH",
    "sg:address":"Rue De Tr\u00e9velin 5 1170 Aubonne Case Postale 43",
    "sg:city":"Aubonne",
    "sg:classifiers":[
        {
            "category":"Travel",
            "subcategory":"Hotels & Motels",
            "type":"Entertainment"
        }
    ],
    "sg:phone":"+41 32 841 24 29",
    "sg:postcode":"1170",
    "sg:province":"Vaud",
    "sg:tags":[
        "hotels",
        "mit",
        "restaurant"
    ],
    "wof:name":"H\u00f4tel Du Commerce, Di Giuseppe A.",
    "wof:placetype":"venue"
},
  "geometry": {"coordinates":[6.856692791,46.9664382935],"type":"Point"}
}