{
  "type": "Feature",
  "properties": {
    "iso:country":"CH",
    "sg:address":"Traverse Chemin De La 12",
    "sg:city":"Aubonne",
    "sg:orig_category":"Interessenvertretungen",
    "sg:phone":"+41 21 808 88 77",
    "sg:postcode":"1170",
    "sg:province":"Vaud",
    "wof:name":"Fondation T\u00e9l\u00e9thon Action Suisse",
    "wof:placetype":"venue"
},
  "geometry": {"coordinates":[6.391699791,46.4952468872],"type":"Point"}
}