{
  "type": "Feature",
  "properties": {
    "iso:country":"CH",
    "sg:address":"Industriestrasse 17",
    "sg:city":"Frauenfeld",
    "sg:orig_category":"Patentverwertung",
    "sg:phone":"+41 52 720 69 75",
    "sg:postcode":"8500",
    "sg:province":"Thurgau",
    "wof:name":"Abatron-patentb\u00fcro Ag",
    "wof:placetype":"venue"
},
  "geometry": {"coordinates":[8.8938570023,47.5603561401],"type":"Point"}
}