{
  "type": "Feature",
  "properties": {
    "iso:country":"CH",
    "sg:address":"3926",
    "sg:city":"Embd",
    "sg:classifiers":[
        {
            "category":"Restaurant",
            "type":"Food & Drink"
        }
    ],
    "sg:phone":"+41 52 745 12 33",
    "sg:postcode":"3926",
    "sg:province":"Valais",
    "wof:name":"Restaurant Morgensonne",
    "wof:placetype":"venue"
},
  "geometry": {"coordinates":[8.7991743088,47.6019287109],"type":"Point"}
}