{
  "type": "Feature",
  "properties": {
    "iso:country":"CH",
    "sg:address":"Seeblick 1",
    "sg:city":"Meierskappel",
    "sg:orig_category":"Grosshandel mit sonstigen Maschinen U Ausr\u00fcstungen f\u00fcr Industrie, Handel U Schiffahrt",
    "sg:phone":"+41 41 790 20 26",
    "sg:postcode":"6344",
    "sg:province":"Luzern",
    "wof:name":"Scantrade Kugler Karl John",
    "wof:placetype":"venue"
},
  "geometry": {"coordinates":[8.4440612793,47.1263999939],"type":"Point"}
}