{
  "type": "Feature",
  "properties": {
    "iso:country":"CH",
    "sg:address":"Im Gartenhof 1",
    "sg:city":"Allschwil",
    "sg:orig_category":"Sonstige Aktivit\u00e4ten der nicht-\u00e4rztlichen Medizinalberufe",
    "sg:phone":"+41 61 482 06 07",
    "sg:postcode":"4123",
    "sg:province":"Basel-Landschaft",
    "wof:name":"F\u00e9licie De Roche Atemtherapie",
    "wof:placetype":"venue"
},
  "geometry": {"coordinates":[7.5439558029,47.5487174988],"type":"Point"}
}