{
  "type": "Feature",
  "properties": {
    "iso:country":"CH",
    "sg:address":"Kilchgrundstrasse 33",
    "sg:city":"Ostermundigen",
    "sg:orig_category":"Elektroinstallation",
    "sg:phone":"+41 31 932 10 70",
    "sg:postcode":"3072",
    "sg:province":"Bern",
    "wof:name":"Scherler Ag, Elektro Und Telematik",
    "wof:placetype":"venue"
},
  "geometry": {"coordinates":[7.4860210419,46.959564209],"type":"Point"}
}