{
  "type": "Feature",
  "properties": {
    "iso:country":"CH",
    "sg:address":"Hauptstrasse 49",
    "sg:city":"Schmerikon",
    "sg:orig_category":"Fachdetailhandel in Verkaufsr\u00e4umen",
    "sg:phone":"+41 55 282 41 41",
    "sg:postcode":"8716",
    "sg:province":"St. Gallen",
    "wof:name":"Pd-handels Ag",
    "wof:placetype":"venue"
},
  "geometry": {"coordinates":[8.9436721802,47.2259521484],"type":"Point"}
}