{
  "type": "Feature",
  "properties": {
    "iso:country":"CH",
    "sg:address":"Untere Dorfstrasse 45",
    "sg:city":"Rudolfstetten",
    "sg:orig_category":"Handels-H\u00e4user U Gesellschaften",
    "sg:postcode":"8964",
    "sg:province":"Aargau",
    "wof:name":"Leonard's Trading Sa Trading Di Valori Mobiliari, Consulenza Nel Sett. Finanziario Ecc",
    "wof:placetype":"venue"
},
  "geometry": {"coordinates":[9.128364563,46.2376060486],"type":"Point"}
}