{
  "type": "Feature",
  "properties": {
    "iso:country":"CH",
    "sg:address":"Spierstrasse 2a",
    "sg:city":"Horw",
    "sg:classifiers":[
        {
            "category":"Military Area",
            "subcategory":"Air Force Base",
            "type":"Public Place"
        }
    ],
    "sg:phone":"+41 41 340 58 87",
    "sg:postcode":"6048",
    "sg:province":"Luzern",
    "sg:tags":[
        "instrument",
        "aircraft",
        "navigation"
    ],
    "wof:name":"Aircotec Gmbh",
    "wof:placetype":"venue"
},
  "geometry": {"coordinates":[8.306299,47.010693],"type":"Point"}
}