{
  "type": "Feature",
  "properties": {
    "iso:country":"CH",
    "sg:address":"Wahlackerstrasse 2",
    "sg:city":"Zollikofen",
    "sg:orig_category":"Elektroinstallation",
    "sg:phone":"+41 31 911 31 21",
    "sg:postcode":"3052",
    "sg:province":"Bern",
    "wof:name":"Urs Walther Ag",
    "wof:placetype":"venue"
},
  "geometry": {"coordinates":[7.4566040039,46.9929046631],"type":"Point"}
}