{
  "type": "Feature",
  "properties": {
    "iso:country":"CH",
    "sg:address":"Schulstrasse 2",
    "sg:city":"Gipf-oberfrick",
    "sg:orig_category":"Grosshandel mit lebenden Tieren",
    "sg:phone":"+41 62 871 13 21",
    "sg:postcode":"5073",
    "sg:province":"Aargau",
    "wof:name":"Alfred Hasler Pferdehandel",
    "wof:placetype":"venue"
},
  "geometry": {"coordinates":[8.0024871826,47.4983520508],"type":"Point"}
}