{
  "type": "Feature",
  "properties": {
    "iso:country":"CH",
    "sg:address":"Delphinstrasse 5",
    "sg:city":"Z\u00fcrich",
    "sg:orig_category":"Advokaturb\u00fcros",
    "sg:phone":"+41 12518010",
    "sg:postcode":"8008",
    "sg:province":"Z\u00fcrich",
    "wof:name":"Dr.georg Lechleiter Advokaturb\u00fcro",
    "wof:placetype":"venue"
},
  "geometry": {"coordinates":[8.552349,47.363995],"type":"Point"}
}