{
  "type": "Feature",
  "properties": {
    "addr:full":"Gehrenstrasse 16 Muhen Aargau 5037",
    "addr:housenumber":"16",
    "addr:postcode":"5037",
    "addr:street":"Gehrenstrasse",
    "iso:country":"CH",
    "sg:address":"Gehrenstrasse 16",
    "sg:city":"Muhen",
    "sg:orig_category":"Allgemeiner Hoch U Tiefbau Allgemeiner Hochbau",
    "sg:phone":"+41 26 496 00 40",
    "sg:postcode":"5037",
    "sg:province":"Aargau",
    "wof:name":"Otto Zumwald Ag",
    "wof:placetype":"venue"
},
  "geometry": {"coordinates":[7.248416,46.863247],"type":"Point"}
}