{
  "type": "Feature",
  "properties": {
    "iso:country":"CH",
    "sg:address":"Boulevard Des Philosophes 28",
    "sg:city":"Gen\u00e8ve",
    "sg:orig_category":"Werbevermittlung",
    "sg:phone":"+41 22 346 24 30",
    "sg:postcode":"1205",
    "sg:province":"Gen\u00e8ve",
    "wof:name":"Jacques Notari Agence De Publicit\u00e9",
    "wof:placetype":"venue"
},
  "geometry": {"coordinates":[6.1493887901,46.1962776184],"type":"Point"}
}