{
  "type": "Feature",
  "properties": {
    "iso:country":"CH",
    "sg:address":"Sonnmatt 25",
    "sg:city":"Landquart",
    "sg:orig_category":"Malerei-Gipserei Stukkateurgewerbe, Gipserei U Verputzerei",
    "sg:phone":"+41 81 756 17 27",
    "sg:postcode":"7302",
    "sg:province":"Graubunden",
    "wof:name":"Gustav Zogg Ag Gipsergesch\u00e4ft",
    "wof:placetype":"venue"
},
  "geometry": {"coordinates":[9.4626941681,47.169380188],"type":"Point"}
}