{
  "type": "Feature",
  "properties": {
    "iso:country":"CH",
    "sg:address":"Rue Du Moulin 10",
    "sg:city":"Moutier",
    "sg:orig_category":"Advokaturb\u00fcros",
    "sg:phone":"+41 32 493 28 37",
    "sg:postcode":"2740",
    "sg:province":"Bern",
    "wof:name":"Dominique Charmillot Etude D'avocat",
    "wof:placetype":"venue"
},
  "geometry": {"coordinates":[7.369755,47.278336],"type":"Point"}
}