{
  "type": "Feature",
  "properties": {
    "iso:country":"CH",
    "sg:address":"Soleure Route De 12 2072 St-blaise. Postfach",
    "sg:city":"St-blaise",
    "sg:orig_category":"Sonstiges Textilgewerbe",
    "sg:postcode":"2072",
    "sg:province":"Neuch\u00e2tel",
    "wof:name":"Alpine Spunmelt Nonwovens Sa Produits Et Compos\u00e9s Li\u00e9s Dir. Ou Indirectement Aux Tissus Non Tiss\u00e9s Et Non-nou\u00e9s Etc.; Conception, Ing\u00e9nierie, Production, Commercial., Distr.",
    "wof:placetype":"venue"
},
  "geometry": {"coordinates":[6.9901638031,47.0149078369],"type":"Point"}
}