{
  "type": "Feature",
  "properties": {
    "iso:country":"CH",
    "sg:address":"Rue Des Alpes 21",
    "sg:city":"Gen\u00e8ve",
    "sg:classifiers":[
        {
            "category":"Bars & Pubs",
            "type":"Food & Drink"
        }
    ],
    "sg:phone":"+41 22 731 21 24",
    "sg:postcode":"1201",
    "sg:province":"Gen\u00e8ve",
    "sg:tags":[
        "restaurant"
    ],
    "wof:name":"Bar Rest. Dancing Black Jack 1900",
    "wof:placetype":"venue"
},
  "geometry": {"coordinates":[6.145206,46.209877],"type":"Point"}
}