{
  "type": "Feature",
  "properties": {
    "iso:country":"CH",
    "sg:address":"Rue Pierre-pertuis 12a",
    "sg:city":"Sonceboz-sombeval",
    "sg:orig_category":"Mit dem Versicherungsgewerbe verbundene T\u00e4tigkeiten",
    "sg:postcode":"2605",
    "sg:province":"Bern",
    "wof:name":"Cocchi Consulting Gmbh",
    "wof:placetype":"venue"
},
  "geometry": {"coordinates":[8.6343660355,46.8743934631],"type":"Point"}
}