{
  "type": "Feature",
  "properties": {
    "iso:country":"CH",
    "sg:address":"Place Du Tunnel 13-14",
    "sg:city":"Lausanne",
    "sg:orig_category":"Detailhandel Reparatur von Gebrauchsg\u00fctern Vermietung von Gebrauchsg\u00fctern",
    "sg:phone":"+41 21 351 12 91",
    "sg:postcode":"1005",
    "sg:province":"Vaud",
    "wof:name":"Vid\u00e9o Folies Carlos & Sandrine Uzal",
    "wof:placetype":"venue"
},
  "geometry": {"coordinates":[6.6345901489,46.5262718201],"type":"Point"}
}