{
  "type": "Feature",
  "properties": {
    "iso:country":"CH",
    "sg:address":"General Guisanstrasse 10",
    "sg:city":"Jegenstorf",
    "sg:orig_category":"Non-Classified Establishments",
    "sg:phone":"+41 55 442 45 89",
    "sg:postcode":"3303",
    "sg:province":"Bern",
    "wof:name":"Kr\u00e4henmann Urs",
    "wof:placetype":"venue"
},
  "geometry": {"coordinates":[8.8518838882,47.1923904419],"type":"Point"}
}