{
  "type": "Feature",
  "properties": {
    "iso:country":"CH",
    "sg:address":"Lindhofstrasse 16",
    "sg:city":"M\u00f6nchaltorf",
    "sg:orig_category":"Bauspenglerei Sanit\u00e4rinstallation U Spenglerei",
    "sg:phone":"+41 19481220",
    "sg:postcode":"8617",
    "sg:province":"Z\u00fcrich",
    "wof:name":"Walter Vogler Isolationsspenglerei",
    "wof:placetype":"venue"
},
  "geometry": {"coordinates":[8.724071,47.312489],"type":"Point"}
}