{
  "type": "Feature",
  "properties": {
    "iso:country":"CH",
    "sg:address":"Boulevard De P\u00e9rolles 21a",
    "sg:city":"Fribourg",
    "sg:orig_category":"Detailhandel mit Waren verschiedener Art, Hauptrichtung Nahrungsmittel",
    "sg:phone":"+41 61 711 77 60",
    "sg:postcode":"1700",
    "sg:province":"Fribourg",
    "wof:name":"Pick Pay Betriebs Ag",
    "wof:placetype":"venue"
},
  "geometry": {"coordinates":[7.5894579887,47.4934310913],"type":"Point"}
}