{
  "type": "Feature",
  "properties": {
    "iso:country":"CH",
    "sg:address":"Suhrerstrasse 14",
    "sg:city":"Oberentfelden",
    "sg:orig_category":"Interessenvertretungen",
    "sg:postcode":"5036",
    "sg:province":"Aargau",
    "wof:name":"Stiftung Zur Unterst\u00fctzung Der Arbeiter-turnvereine Von Oberentfelden",
    "wof:placetype":"venue"
},
  "geometry": {"coordinates":[8.0479812622,47.3572006226],"type":"Point"}
}