{
  "type": "Feature",
  "properties": {
    "iso:country":"CH",
    "sg:address":"Unter-rieten",
    "sg:city":"Morschach",
    "sg:orig_category":"Architektur U Ingenieurb\u00fcros",
    "sg:postcode":"6443",
    "sg:province":"Schwyz",
    "wof:name":"Walker Architekten Ag",
    "wof:placetype":"venue"
},
  "geometry": {"coordinates":[8.207595,47.483032],"type":"Point"}
}