{
  "type": "Feature",
  "properties": {
    "iso:country":"CH",
    "sg:address":"Herrengasse 34",
    "sg:city":"Schwyz",
    "sg:orig_category":"Zimmerei, Dachdeckerei, Bauspenglerei U Abdichtung",
    "sg:postcode":"6430",
    "sg:province":"Schwyz",
    "wof:name":"Spenglerei Fenk",
    "wof:placetype":"venue"
},
  "geometry": {"coordinates":[8.948554039,47.1755104065],"type":"Point"}
}