{
  "type": "Feature",
  "properties": {
    "iso:country":"CH",
    "sg:address":"Baarerstrasse 43 6300 Zug. Postfach",
    "sg:city":"Luzern",
    "sg:orig_category":"Grosshandel mit Nahrungsmitteln, Getr\u00e4nken U Tabakwaren ohne ausgepr\u00e4gten Schwerpunkt",
    "sg:postcode":"6003",
    "sg:province":"Luzern",
    "wof:name":"Gastro Italia Management Ag Liegenschaften Usw",
    "wof:placetype":"venue"
},
  "geometry": {"coordinates":[8.516579628,47.1738433838],"type":"Point"}
}