{
  "type": "Feature",
  "properties": {
    "iso:country":"CH",
    "sg:address":"Rue Des Noirettes 32-34",
    "sg:city":"Carouge",
    "sg:classifiers":[
        {
            "category":"Shopping",
            "subcategory":"Beauty & Cosmetics",
            "type":"Retail Goods"
        }
    ],
    "sg:phone":"+41 22 300 50 60",
    "sg:postcode":"1227",
    "sg:province":"Gen\u00e8ve",
    "sg:tags":[
        "perfume"
    ],
    "wof:name":"Ac & M. Parfums Sa",
    "wof:placetype":"venue"
},
  "geometry": {"coordinates":[6.1323451996,46.1880149841],"type":"Point"}
}