{
  "type": "Feature",
  "properties": {
    "iso:country":"CH",
    "sg:address":"Tiergarten 43",
    "sg:city":"Burgdorf",
    "sg:orig_category":"Verwaltung von Immobilien",
    "sg:phone":"+41 34 422 15 42",
    "sg:postcode":"3400",
    "sg:province":"Bern",
    "wof:name":"Casa X Gmbh",
    "wof:placetype":"venue"
},
  "geometry": {"coordinates":[7.6154618263,47.0624732971],"type":"Point"}
}