{
  "type": "Feature",
  "properties": {
    "iso:country":"CH",
    "sg:address":"Kreuzfeldweg 1",
    "sg:city":"Biberist",
    "sg:orig_category":"Grosshandel mit B\u00fcromaschinen Grosshandel mit Datenverarbeitungsger\u00e4ten",
    "sg:phone":"+41 32 672 07 70",
    "sg:postcode":"4562",
    "sg:province":"Solothurn",
    "wof:name":"Hasotronic Gmbh Elektronik & Software",
    "wof:placetype":"venue"
},
  "geometry": {"coordinates":[7.5569939613,47.1813812256],"type":"Point"}
}