{
  "type": "Feature",
  "properties": {
    "iso:country":"CH",
    "sg:address":"Wallisellenstrasse 241",
    "sg:city":"Z\u00fcrich",
    "sg:orig_category":"Einzelhandel mit Automobilteilen U Zubeh\u00f6r Herstellung von Bereifungen",
    "sg:phone":"+41 81 740 00 88",
    "sg:postcode":"8050",
    "sg:province":"Z\u00fcrich",
    "wof:name":"Pneu Moreschi Ag",
    "wof:placetype":"venue"
},
  "geometry": {"coordinates":[9.4842071533,47.1728286743],"type":"Point"}
}