{
  "type": "Feature",
  "properties": {
    "iso:country":"CH",
    "sg:address":"1991",
    "sg:city":"Salins",
    "sg:orig_category":"Wirtschaftspr\u00fcfung, Steuerberatung U Treuhand",
    "sg:phone":"+41 27 207 33 34",
    "sg:postcode":"1991",
    "sg:province":"Valais",
    "wof:name":"Fiduciaire Pcl",
    "wof:placetype":"venue"
},
  "geometry": {"coordinates":[7.3580350876,46.2108764648],"type":"Point"}
}