{
  "type": "Feature",
  "properties": {
    "iso:country":"CH",
    "sg:address":"C\u00e9ard Rue Robert- 9 1204 Gen\u00e8ve. Postfach",
    "sg:city":"Gen\u00e8ve",
    "sg:orig_category":"Fachdetailhandel in Verkaufsr\u00e4umen",
    "sg:postcode":"1204",
    "sg:province":"Gen\u00e8ve",
    "wof:name":"J.loichot Et Cie",
    "wof:placetype":"venue"
},
  "geometry": {"coordinates":[6.1489200592,46.203338623],"type":"Point"}
}