{
  "type": "Feature",
  "properties": {
    "iso:country":"CH",
    "sg:address":"Fola Via 13 6963 Pregassona. Postfach",
    "sg:city":"Pregassona",
    "sg:orig_category":"Instandhaltung U Reparatur von Automobilen",
    "sg:postcode":"6963",
    "sg:province":"Ticino",
    "wof:name":"Pomaf Sa Automobili, Accessori, Prodotti; Manutenzione, Compravendita Ecc",
    "wof:placetype":"venue"
},
  "geometry": {"coordinates":[8.9628305435,46.0170097351],"type":"Point"}
}