{
  "type": "Feature",
  "properties": {
    "iso:country":"CH",
    "sg:address":"Feldstrasse 109",
    "sg:city":"Z\u00fcrich",
    "sg:orig_category":"Religi\u00f6se Vereinigungen divers Vereine Gemeinn\u00fctzige",
    "sg:postcode":"8004",
    "sg:province":"Z\u00fcrich",
    "wof:name":"Figlie Di Maria Missione Cattolica Italiana",
    "wof:placetype":"venue"
},
  "geometry": {"coordinates":[8.5232105255,47.3789863586],"type":"Point"}
}