{
  "type": "Feature",
  "properties": {
    "iso:country":"CH",
    "sg:address":"R\u00f6sslistr. 10",
    "sg:city":"N\u00e4fels",
    "sg:classifiers":[
        {
            "category":"Banks & Credit Unions",
            "subcategory":"Bank",
            "type":"Services"
        }
    ],
    "sg:phone":"+41 61 981 54 52",
    "sg:postcode":"8752",
    "sg:province":"Glarus",
    "wof:name":"Raiffeisenbank Oberbaselbiet",
    "wof:placetype":"venue"
},
  "geometry": {"coordinates":[7.88765,47.490471],"type":"Point"}
}