{
  "type": "Feature",
  "properties": {
    "iso:country":"CH",
    "sg:address":"Haus Siena B",
    "sg:city":"Susten",
    "sg:orig_category":"Detailhandel mit medizinischen U orthop\u00e4dischen Artikeln Herstellung von medizinischen U chirurgisch",
    "sg:phone":"+41 27 473 12 00",
    "sg:postcode":"3952",
    "sg:province":"Valais",
    "wof:name":"Detlef Loretan",
    "wof:placetype":"venue"
},
  "geometry": {"coordinates":[7.6420221329,46.3115119934],"type":"Point"}
}