{
  "type": "Feature",
  "properties": {
    "iso:country":"CH",
    "sg:address":"Wibichstrasse 35",
    "sg:city":"Z\u00fcrich",
    "sg:orig_category":"Werbung",
    "sg:postcode":"8037",
    "sg:province":"Z\u00fcrich",
    "wof:name":"G. Janett, Akquisiteurin",
    "wof:placetype":"venue"
},
  "geometry": {"coordinates":[8.5288143158,47.3970870972],"type":"Point"}
}