{
  "type": "Feature",
  "properties": {
    "addr:full":"Sternmattstrasse 69 Luzern Luzern 6005",
    "addr:housenumber":"69",
    "addr:postcode":"6005",
    "addr:street":"Sternmattstrasse",
    "iso:country":"CH",
    "sg:address":"Sternmattstrasse 69",
    "sg:city":"Luzern",
    "sg:orig_category":"Architekturb\u00fcros",
    "sg:phone":"+41 41 360 53 75",
    "sg:postcode":"6005",
    "sg:province":"Luzern",
    "wof:name":"Hans Rudolf Stillhardt Architekturb\u00fcro",
    "wof:placetype":"venue"
},
  "geometry": {"coordinates":[8.312829,47.036476],"type":"Point"}
}