{
  "type": "Feature",
  "properties": {
    "iso:country":"CH",
    "sg:address":"Marktgasse 6a",
    "sg:city":"Thun",
    "sg:orig_category":"Fachdetailhandel in Verkaufsr\u00e4umen",
    "sg:phone":"+41 55 442 12 92",
    "sg:postcode":"3600",
    "sg:province":"Bern",
    "wof:name":"Kispa Ag",
    "wof:placetype":"venue"
},
  "geometry": {"coordinates":[8.8533697128,47.193321228],"type":"Point"}
}