{
  "type": "Feature",
  "properties": {
    "iso:country":"CH",
    "sg:address":"Haus Fleckstein 3928 Randa. Postfach 7",
    "sg:city":"Randa",
    "sg:orig_category":"Wirtschaftspr\u00fcfung, Steuerberatung U Treuhand",
    "sg:phone":"+41 27 967 58 00",
    "sg:postcode":"3928",
    "sg:province":"Valais",
    "wof:name":"Brantschen Albin, Treuhandb\u00fcro",
    "wof:placetype":"venue"
},
  "geometry": {"coordinates":[7.7803549767,46.0985984802],"type":"Point"}
}