{
  "type": "Feature",
  "properties": {
    "iso:country":"CH",
    "sg:address":"Rebstrasse 59",
    "sg:city":"Oberhasli",
    "sg:orig_category":"Herstellung von Elektrizit\u00e4tsverteilungs U schalteinrichtungen",
    "sg:phone":"+41 18505075",
    "sg:postcode":"8156",
    "sg:province":"Z\u00fcrich",
    "wof:name":"Pancontrol A Marca D.",
    "wof:placetype":"venue"
},
  "geometry": {"coordinates":[8.5000619888,47.465511322],"type":"Point"}
}