{
  "type": "Feature",
  "properties": {
    "iso:country":"CH",
    "sg:address":"Dettighofer Strasse 6",
    "sg:city":"Lengwil-oberhofen",
    "sg:orig_category":"Herstellung von Gummi U Kunststoffwaren",
    "sg:phone":"+41 71 688 99 30",
    "sg:postcode":"8574",
    "sg:province":"Thurgau",
    "wof:name":"Tegometall (international) Consulting Gmbh",
    "wof:placetype":"venue"
},
  "geometry": {"coordinates":[9.1946458817,47.6239547729],"type":"Point"}
}