{
  "type": "Feature",
  "properties": {
    "iso:country":"CH",
    "sg:address":"G\u00e4uggelistrasse 25",
    "sg:city":"Chur",
    "sg:orig_category":"Non-Classified Establishments",
    "sg:postcode":"7000",
    "sg:province":"Graubunden",
    "wof:name":"Intermetec Holding Ag",
    "wof:placetype":"venue"
},
  "geometry": {"coordinates":[9.5277013779,46.8511772156],"type":"Point"}
}