{
  "type": "Feature",
  "properties": {
    "iso:country":"CH",
    "sg:address":"Bahnhofstrasse 18",
    "sg:city":"Zug",
    "sg:orig_category":"Grosshandel mit festen Brennstoffen U Mineral\u00f6lerzeugnissen",
    "sg:phone":"+41 41 710 24 55",
    "sg:postcode":"6300",
    "sg:province":"Zug",
    "wof:name":"Gutamo Ag",
    "wof:placetype":"venue"
},
  "geometry": {"coordinates":[8.5158376694,47.1692504883],"type":"Point"}
}