{
  "type": "Feature",
  "properties": {
    "addr:full":"Schartenstrasse 95 Wettingen Aargau 5430",
    "addr:housenumber":"95",
    "addr:postcode":"5430",
    "addr:street":"Schartenstrasse",
    "iso:country":"CH",
    "sg:address":"Schartenstrasse 95",
    "sg:city":"Wettingen",
    "sg:orig_category":"Blumen U Zierpflanzenbau Detailhandel mit Blumen U Pflanzen",
    "sg:phone":"+41 56 426 74 49",
    "sg:postcode":"5430",
    "sg:province":"Aargau",
    "wof:name":"Erni Blumen & Gartenbau Ag",
    "wof:placetype":"venue"
},
  "geometry": {"coordinates":[8.322362,47.470142],"type":"Point"}
}