{
  "type": "Feature",
  "properties": {
    "iso:country":"CH",
    "sg:address":"Gare Rue De La 7",
    "sg:city":"Aigle",
    "sg:orig_category":"Verwaltung von Immobilien",
    "sg:phone":"+41 27 746 22 14",
    "sg:postcode":"1860",
    "sg:province":"Vaud",
    "wof:name":"Chamary Sa",
    "wof:placetype":"venue"
},
  "geometry": {"coordinates":[6.9701099396,46.3175544739],"type":"Point"}
}