{
  "type": "Feature",
  "properties": {
    "iso:country":"CH",
    "sg:address":"Langenhagstr. 6",
    "sg:city":"Rheineck",
    "sg:classifiers":[
        {
            "category":"Farming",
            "subcategory":"Farm & Veterinary Services",
            "type":"Manufacturing & Wholesale Goods"
        }
    ],
    "sg:phone":"+41 71 888 27 27",
    "sg:postcode":"9424",
    "sg:province":"St. Gallen",
    "sg:tags":[
        "food",
        "product",
        "breeding",
        "animal",
        "related"
    ],
    "wof:name":"Meyerhans Hotz Ag M\u00dchlen",
    "wof:placetype":"venue"
},
  "geometry": {"coordinates":[9.588326,47.470715],"type":"Point"}
}