{
  "type": "Feature",
  "properties": {
    "iso:country":"CH",
    "sg:address":"Axenstrasse 4 6454 Fl\u00fcelen. Postfach",
    "sg:city":"Fl\u00fcelen",
    "sg:orig_category":"Diskotheken, Dancings, Night Clubs",
    "sg:phone":"+41 41 874 30 20",
    "sg:postcode":"6454",
    "sg:province":"Uri",
    "wof:name":"Restaurant Urnerhof & Chu\u00e4flad\u00e4 Bar-dancing",
    "wof:placetype":"venue"
},
  "geometry": {"coordinates":[8.6252765656,46.903213501],"type":"Point"}
}