{
  "type": "Feature",
  "properties": {
    "iso:country":"CH",
    "sg:address":"Z\u00fcrichstrasse 2",
    "sg:city":"Oftringen",
    "sg:orig_category":"Detailhandel mit Schuhen",
    "sg:phone":"+41 62 797 43 30",
    "sg:postcode":"4665",
    "sg:province":"Aargau",
    "wof:name":"Gysin Schuhmode",
    "wof:placetype":"venue"
},
  "geometry": {"coordinates":[7.9223828316,47.3127365112],"type":"Point"}
}