{
  "type": "Feature",
  "properties": {
    "addr:full":"Hauptstrasse 64 Speicher Appenzell Ausserrhoden 9042",
    "addr:housenumber":"64",
    "addr:postcode":"9042",
    "addr:street":"Hauptstrasse;Ausserrhoden",
    "iso:country":"CH",
    "sg:address":"Hauptstrasse 64",
    "sg:city":"Speicher",
    "sg:orig_category":"Bauschreinerei Herstellung von M\u00f6beln verschiedener Art",
    "sg:phone":"+41 71 344 14 63",
    "sg:postcode":"9042",
    "sg:province":"Appenzell Ausserrhoden",
    "wof:name":"Erich Zellweger Ag",
    "wof:placetype":"venue"
},
  "geometry": {"coordinates":[9.439051,47.412891],"type":"Point"}
}