{
  "type": "Feature",
  "properties": {
    "iso:country":"CH",
    "sg:address":"T\u00f6berstrasse 1 9425 Thal. Postfach 149",
    "sg:city":"Thal",
    "sg:classifiers":[
        {
            "category":"Restaurant",
            "type":"Food & Drink"
        }
    ],
    "sg:phone":"+41 52 383 13 23",
    "sg:postcode":"9425",
    "sg:province":"St. Gallen",
    "wof:name":"Restaurant L\u00f6wen",
    "wof:placetype":"venue"
},
  "geometry": {"coordinates":[8.799741745,47.4433326721],"type":"Point"}
}