{
  "type": "Feature",
  "properties": {
    "iso:country":"CH",
    "sg:address":"Mittelstrasse 14 8000 Z\u00fcrich. Postfach",
    "sg:city":"Z\u00fcrich",
    "sg:orig_category":"Finanzierungsinstitutionen",
    "sg:postcode":"8008",
    "sg:province":"Z\u00fcrich",
    "wof:name":"Dominick Capital Ag",
    "wof:placetype":"venue"
},
  "geometry": {"coordinates":[8.5517139435,47.3574638367],"type":"Point"}
}