{
  "type": "Feature",
  "properties": {
    "iso:country":"CH",
    "sg:city":"Gonten",
    "sg:classifiers":[
        {
            "category":"Banks & Credit Unions",
            "subcategory":"Bank",
            "type":"Services"
        }
    ],
    "sg:phone":"+41 71 794 12 25",
    "sg:postcode":"9108",
    "sg:province":"Appenzell Innerhoden",
    "wof:name":"Appenzell-innerrhodische, Kantonalbank",
    "wof:placetype":"venue"
},
  "geometry": {"coordinates":[9.343704,47.32608],"type":"Point"}
}