{
  "type": "Feature",
  "properties": {
    "iso:country":"CH",
    "sg:address":"Bollwerk 35",
    "sg:city":"Bern",
    "sg:orig_category":"Berufliche Weiterbildung, Erwachsenenbildung",
    "sg:phone":"+41 31 312 12 62",
    "sg:postcode":"3011",
    "sg:province":"Bern",
    "wof:name":"Bildungszentrum Wwf",
    "wof:placetype":"venue"
},
  "geometry": {"coordinates":[7.44145,46.951572],"type":"Point"}
}