{
  "type": "Feature",
  "properties": {
    "iso:country":"CH",
    "sg:address":"Rue De La Samaritaine 11",
    "sg:city":"Fribourg",
    "sg:orig_category":"Detailhandel mit Zeitungen U Zeitschriften Kioske",
    "sg:phone":"+41 26 322 07 15",
    "sg:postcode":"1700",
    "sg:province":"Fribourg",
    "wof:name":"Kiosque De La Samaritaine",
    "wof:placetype":"venue"
},
  "geometry": {"coordinates":[7.1668601036,46.8040351868],"type":"Point"}
}