{
  "type": "Feature",
  "properties": {
    "iso:country":"CH",
    "sg:address":"Untere Zollgasse 24",
    "sg:city":"Ostermundigen",
    "sg:orig_category":"Tierarztpraxis",
    "sg:phone":"+41 31 931 60 20",
    "sg:postcode":"3072",
    "sg:province":"Bern",
    "wof:name":"Dr. Med. Vet. Willi H\u00e4feli Tierarzt",
    "wof:placetype":"venue"
},
  "geometry": {"coordinates":[7.4882907867,46.9606742859],"type":"Point"}
}