{
  "type": "Feature",
  "properties": {
    "iso:country":"CH",
    "sg:address":"T\u00fcrkheimerstrasse 5 4055 Basel. Postfach",
    "sg:city":"Basel",
    "sg:orig_category":"Warenh\u00e4user",
    "sg:phone":"+41 61 301 19 68",
    "sg:postcode":"4009",
    "sg:province":"Basel-Stadt",
    "wof:name":"Abm Au Bon March\u00e9",
    "wof:placetype":"venue"
},
  "geometry": {"coordinates":[7.5746788979,47.5576171875],"type":"Point"}
}