{
  "type": "Feature",
  "properties": {
    "iso:country":"CH",
    "sg:address":"Molkenstrasse 6 8004 Z\u00fcrich. Postfach",
    "sg:city":"Z\u00fcrich",
    "sg:orig_category":"Wohnheime",
    "sg:phone":"+41 12989000",
    "sg:postcode":"8026",
    "sg:province":"Z\u00fcrich",
    "wof:name":"Heilsarmee Wohnheim F.frauen & M\u00e4nner",
    "wof:placetype":"venue"
},
  "geometry": {"coordinates":[8.5276079178,47.3764457703],"type":"Point"}
}