{
  "type": "Feature",
  "properties": {
    "iso:country":"CH",
    "sg:address":"Faubourg De L'h\u00f4pital 9",
    "sg:city":"Neuenburg",
    "sg:orig_category":"Unclassifiable Establishments",
    "sg:postcode":"2000",
    "sg:province":"Neuch\u00e2tel",
    "wof:name":"Copyquick Laser & Digital Printing Sa",
    "wof:placetype":"venue"
},
  "geometry": {"coordinates":[6.9363808632,46.9942970276],"type":"Point"}
}