{
  "type": "Feature",
  "properties": {
    "iso:country":"CH",
    "sg:address":"Lindenstrasse 34",
    "sg:city":"Dietikon",
    "sg:orig_category":"Architektur U Ingenieurb\u00fcros",
    "sg:postcode":"8953",
    "sg:province":"Z\u00fcrich",
    "wof:name":"Vetsch Peter Ag",
    "wof:placetype":"venue"
},
  "geometry": {"coordinates":[8.38576,47.39967],"type":"Point"}
}