{
  "type": "Feature",
  "properties": {
    "iso:country":"CH",
    "sg:address":"Im Monplaisir 4",
    "sg:city":"Rheineck",
    "sg:orig_category":"Wirtschaftspr\u00fcfung, Steuerberatung U Treuhand",
    "sg:phone":"+41 71 383 22 11",
    "sg:postcode":"9424",
    "sg:province":"St. Gallen",
    "wof:name":"Trevitas Treuhand Ag",
    "wof:placetype":"venue"
},
  "geometry": {"coordinates":[9.3142166138,47.4091873169],"type":"Point"}
}