{
  "type": "Feature",
  "properties": {
    "iso:country":"CH",
    "sg:address":"Via Del Segnale",
    "sg:city":"Ascona",
    "sg:classifiers":[
        {
            "category":"Travel",
            "subcategory":"Hotels & Motels",
            "type":"Entertainment"
        }
    ],
    "sg:phone":"+41 800 333 313",
    "sg:postcode":"6612",
    "sg:province":"Ticino",
    "sg:tags":[
        "hotels",
        "mit",
        "restaurant"
    ],
    "wof:name":"Albergo Giardino",
    "wof:placetype":"venue"
},
  "geometry": {"coordinates":[8.7903079987,46.1495780945],"type":"Point"}
}