{
  "type": "Feature",
  "properties": {
    "iso:country":"CH",
    "sg:address":"Hauptstrasse 59",
    "sg:city":"Hauptwil",
    "sg:orig_category":"Herstellung von Konstruktionsteilen, Fertigbauteilen U Ausbauelementen aus Holz Herstellung von sons",
    "sg:phone":"+41 71 422 16 41",
    "sg:postcode":"9213",
    "sg:province":"Thurgau",
    "wof:name":"Rohr Rudolf",
    "wof:placetype":"venue"
},
  "geometry": {"coordinates":[9.2569303513,47.4827651978],"type":"Point"}
}