{
  "type": "Feature",
  "properties": {
    "iso:country":"CH",
    "sg:address":"Wermatswilerstrasse 4",
    "sg:city":"Uster",
    "sg:orig_category":"Psychotherapie",
    "sg:phone":"+41 19416422",
    "sg:postcode":"8610",
    "sg:province":"Z\u00fcrich",
    "wof:name":"Sibyl-cornelia Kamm Psychotherapie",
    "wof:placetype":"venue"
},
  "geometry": {"coordinates":[8.7273292542,47.3476104736],"type":"Point"}
}