{
  "type": "Feature",
  "properties": {
    "iso:country":"CH",
    "sg:address":"3943",
    "sg:city":"Eischoll",
    "sg:orig_category":"G\u00fcterbef\u00f6rderung im Strassenverkehr",
    "sg:phone":"+41 27 934 30 31",
    "sg:postcode":"3943",
    "sg:province":"Valais",
    "wof:name":"Transporte Bayard Landolt",
    "wof:placetype":"venue"
},
  "geometry": {"coordinates":[7.7804951668,46.2933311462],"type":"Point"}
}