{
  "type": "Feature",
  "properties": {
    "iso:country":"CH",
    "sg:address":"Holeestrasse 145 4054 Basel. Postfach",
    "sg:city":"Basel",
    "sg:orig_category":"Herstellung von k\u00e4lte U lufttechnischen Erzeugnissen f\u00fcr gewerbliche Zwecke Sanit\u00e4r U Heizungsinstal",
    "sg:phone":"+41 61 308 91 91",
    "sg:postcode":"4015",
    "sg:province":"Basel-Stadt",
    "wof:name":"Markus Egli Ag",
    "wof:placetype":"venue"
},
  "geometry": {"coordinates":[7.5661301613,47.5461997986],"type":"Point"}
}