{
  "type": "Feature",
  "properties": {
    "iso:country":"CH",
    "sg:address":"L\u00e4ngenbold 3 6037 Root. Postfach 242",
    "sg:city":"Root",
    "sg:orig_category":"Erzeugung U Erstbearbeitung von Aluminium Grosshandel mit Erzen U Metallen",
    "sg:phone":"+41 41 455 50 50",
    "sg:postcode":"6037",
    "sg:province":"Luzern",
    "wof:name":"Hunter Douglas Ag Alum.bauprodukte Luxalon",
    "wof:placetype":"venue"
},
  "geometry": {"coordinates":[8.3757476807,47.1049842834],"type":"Point"}
}