{
  "type": "Feature",
  "properties": {
    "iso:country":"CH",
    "sg:address":"Turbistrasse 21",
    "sg:city":"Hochdorf",
    "sg:orig_category":"HERSTELLUNG VON GER\u00c4TEN DER ELEKTRIZIT\u00c4TSERZEUGUNG, -VERTEILUNG U.\u00c4 Softwareentwicklung U beratung",
    "sg:phone":"+41 32 731 63 31",
    "sg:postcode":"6280",
    "sg:province":"Luzern",
    "wof:name":"Crivelli Data Sa",
    "wof:placetype":"venue"
},
  "geometry": {"coordinates":[6.882352829,46.9846763611],"type":"Point"}
}