{
  "type": "Feature",
  "properties": {
    "iso:country":"CH",
    "sg:address":"Winkelriedstrasse 43",
    "sg:city":"Schaffhausen",
    "sg:orig_category":"Grosshandel mit Eisenwaren sowie Installationsbedarf f\u00fcr Gas, Wasser U Heizung",
    "sg:phone":"+41 52 625 68 35",
    "sg:postcode":"8200",
    "sg:province":"Schaffhausen",
    "wof:name":"Group Az Gmbh",
    "wof:placetype":"venue"
},
  "geometry": {"coordinates":[8.6522035599,47.7011413574],"type":"Point"}
}