{
  "type": "Feature",
  "properties": {
    "addr:full":"Sternmattweg 4b 6010 Kriens. Postfach 2459 Luzern Luzern 6002",
    "addr:housenumber":"4b",
    "addr:postcode":"6010 kriens. postfach 2459;6002",
    "addr:street":"Sternmattweg",
    "iso:country":"CH",
    "sg:address":"Sternmattweg 4b 6010 Kriens. Postfach 2459",
    "sg:city":"Luzern",
    "sg:orig_category":"Architektur U Ingenieurb\u00fcros",
    "sg:phone":"+41 41 312 18 80",
    "sg:postcode":"6002",
    "sg:province":"Luzern",
    "wof:name":"Basis Team Gmbh Planung & Baumanagement",
    "wof:placetype":"venue"
},
  "geometry": {"coordinates":[8.297329,47.028706],"type":"Point"}
}