{
  "type": "Feature",
  "properties": {
    "iso:country":"CH",
    "sg:address":"Glaserstrasse 12",
    "sg:city":"T\u00e4gerwilen",
    "sg:classifiers":[
        {
            "category":"Wholesale",
            "subcategory":"Plants",
            "type":"Manufacturing & Wholesale Goods"
        }
    ],
    "sg:phone":"+41 71 669 23 47",
    "sg:postcode":"8274",
    "sg:province":"Thurgau",
    "sg:tags":[
        "machine",
        "industrial",
        "automation"
    ],
    "wof:name":"Cintex Ag",
    "wof:placetype":"venue"
},
  "geometry": {"coordinates":[9.144358,47.652058],"type":"Point"}
}