{
  "type": "Feature",
  "properties": {
    "iso:country":"CH",
    "sg:address":"Furrengasse 6",
    "sg:city":"Luzern",
    "sg:orig_category":"Arztpraxen",
    "sg:phone":"+41 41 410 34 00",
    "sg:postcode":"6004",
    "sg:province":"Luzern",
    "wof:name":"Dr. Med.christoph Merlo Spezialarzt Fmh",
    "wof:placetype":"venue"
},
  "geometry": {"coordinates":[8.307337,47.052429],"type":"Point"}
}