{
  "type": "Feature",
  "properties": {
    "addr:full":"Neugass 1 Berneck St. Gallen 9442",
    "addr:housenumber":"1;st.",
    "addr:postcode":"9442",
    "addr:street":"Neugass;Berneck",
    "iso:country":"CH",
    "sg:address":"Neugass 1",
    "sg:city":"Berneck",
    "sg:orig_category":"Detailhandel mit Brot, Back U S\u00fcsswaren",
    "sg:phone":"+41 71 722 21 79",
    "sg:postcode":"9442",
    "sg:province":"St. Gallen",
    "wof:name":"Hugo Eschenmoser B\u00e4ckerei-konditorei",
    "wof:placetype":"venue"
},
  "geometry": {"coordinates":[9.61016,47.425354],"type":"Point"}
}