{
  "type": "Feature",
  "properties": {
    "iso:country":"CH",
    "sg:address":"Via Lugano 37",
    "sg:city":"Bellinzona",
    "sg:orig_category":"Detailhandel mit elektrischen Haushalts, Radio U Fernsehger\u00e4ten ohne ausgepr\u00e4gten Schwerpunkt",
    "sg:phone":"+41 91 825 25 15",
    "sg:postcode":"6500",
    "sg:province":"Ticino",
    "wof:name":"Pasteris Sa ..fus.m.751'404",
    "wof:placetype":"venue"
},
  "geometry": {"coordinates":[9.0195798874,46.1855583191],"type":"Point"}
}