{
  "type": "Feature",
  "properties": {
    "iso:country":"CH",
    "sg:address":"Rue Du Closillon 2",
    "sg:city":"Monthey",
    "sg:orig_category":"Bauschreinerei Herstellung von Konstruktionsteilen, Fertigbauteilen U Ausbauelementen aus Holz",
    "sg:phone":"+41 24 471 23 78",
    "sg:postcode":"1870",
    "sg:province":"Valais",
    "wof:name":"Multone Et Cie Menuiserie Sa",
    "wof:placetype":"venue"
},
  "geometry": {"coordinates":[6.956275,46.255573],"type":"Point"}
}