{
  "type": "Feature",
  "properties": {
    "iso:country":"CH",
    "sg:address":"Unter Ziel 28",
    "sg:city":"Appenzell",
    "sg:orig_category":"Massagestudios",
    "sg:phone":"+41 71 799 16 13",
    "sg:postcode":"9050",
    "sg:province":"Appenzell Innerhoden",
    "wof:name":"Monika Reut Massagen",
    "wof:placetype":"venue"
},
  "geometry": {"coordinates":[9.4096670151,47.3346290588],"type":"Point"}
}