{
  "type": "Feature",
  "properties": {
    "iso:country":"CH",
    "sg:address":"Poststrasse 29",
    "sg:city":"Wattwil",
    "sg:orig_category":"Unclassifiable Establishments",
    "sg:phone":"+41 61 965 61 11",
    "sg:postcode":"9630",
    "sg:province":"St. Gallen",
    "wof:name":"Smp Ag",
    "wof:placetype":"venue"
},
  "geometry": {"coordinates":[7.749949,47.390182],"type":"Point"}
}