{
  "type": "Feature",
  "properties": {
    "iso:country":"CH",
    "sg:address":"Amriswiler Strasse 44",
    "sg:city":"Steinebrunn",
    "sg:orig_category":"Detailhandel mit Fleisch U Fleischwaren",
    "sg:phone":"+41 71 477 14 12",
    "sg:postcode":"9314",
    "sg:province":"Thurgau",
    "wof:name":"Albert Weibel Metzgerei",
    "wof:placetype":"venue"
},
  "geometry": {"coordinates":[9.3481330872,47.5338287354],"type":"Point"}
}