{
  "type": "Feature",
  "properties": {
    "iso:country":"CH",
    "sg:address":"Erachfeldstrasse 22",
    "sg:city":"B\u00fclach",
    "sg:orig_category":"Ingenieurb\u00fcros Elektro",
    "sg:phone":"+41 18610307",
    "sg:postcode":"8180",
    "sg:province":"Z\u00fcrich",
    "wof:name":"Hans-j\u00f6rg Streuli Ingenieurb\u00fcro",
    "wof:placetype":"venue"
},
  "geometry": {"coordinates":[8.5397481918,47.5143661499],"type":"Point"}
}