{
  "type": "Feature",
  "properties": {
    "addr:full":"B\u00fcnte 39 Tegerfelden Aargau 5306",
    "addr:housenumber":"39",
    "addr:postcode":"5306",
    "addr:street":"Buente",
    "iso:country":"CH",
    "sg:address":"B\u00fcnte 39",
    "sg:city":"Tegerfelden",
    "sg:classifiers":[
        {
            "category":"Professional",
            "subcategory":"Advertising",
            "type":"Services"
        }
    ],
    "sg:phone":"+41 56 268 62 22",
    "sg:postcode":"5306",
    "sg:province":"Aargau",
    "sg:tags":[
        "gift"
    ],
    "wof:name":"Zollinger Beschriftungen Und Werbeprodukte Ag",
    "wof:placetype":"venue"
},
  "geometry": {"coordinates":[8.289742,47.565144],"type":"Point"}
}