{
  "type": "Feature",
  "properties": {
    "iso:country":"CH",
    "sg:address":"L\u00e4ndtestrasse 15",
    "sg:city":"Schwarzh\u00e4usern",
    "sg:orig_category":"Detailhandel mit Milcherzeugnissen U Eiern Verarbeitung von Milch",
    "sg:phone":"+41 62 922 58 27",
    "sg:postcode":"4911",
    "sg:province":"Bern",
    "wof:name":"Armin Kl\u00e4figer K\u00e4serei",
    "wof:placetype":"venue"
},
  "geometry": {"coordinates":[7.7668170929,47.2507972717],"type":"Point"}
}