{
  "type": "Feature",
  "properties": {
    "iso:country":"CH",
    "sg:address":"Gibelstrasse 58 2540 Grenchen. Postfach",
    "sg:city":"Grenchen",
    "sg:orig_category":"Werbung",
    "sg:postcode":"2540",
    "sg:province":"Solothurn",
    "wof:name":"G\u00f6de Marketing Und Werbung Gmbh Werbemassnahmen; Konzeption, Entwicklung, Gestaltung Usw",
    "wof:placetype":"venue"
},
  "geometry": {"coordinates":[7.3915548325,47.1897735596],"type":"Point"}
}