{
  "type": "Feature",
  "properties": {
    "addr:full":"Turnerstrasse 26 8006 Z\u00fcrich. Postfach Z\u00fcrich Z\u00fcrich 8001",
    "addr:housenumber":"26",
    "addr:postcode":"8006 zuerich. postfach;8001",
    "addr:street":"Turnerstrasse",
    "iso:country":"CH",
    "sg:address":"Turnerstrasse 26 8006 Z\u00fcrich. Postfach",
    "sg:city":"Z\u00fcrich",
    "sg:orig_category":"Datenverarbeitungsdienste Sonstige mit der Informatik verbundene T\u00e4tigkeiten",
    "sg:phone":"+41 13503901",
    "sg:postcode":"8001",
    "sg:province":"Z\u00fcrich",
    "wof:name":"Asmak Services Gmbh Edv Services",
    "wof:placetype":"venue"
},
  "geometry": {"coordinates":[8.544016,47.385529],"type":"Point"}
}