{
  "type": "Feature",
  "properties": {
    "iso:country":"CH",
    "sg:address":"Dorfstr. 30",
    "sg:city":"Adelboden",
    "sg:classifiers":[
        {
            "category":"Banks & Credit Unions",
            "subcategory":"Bank",
            "type":"Services"
        }
    ],
    "sg:postcode":"3715",
    "sg:province":"Bern",
    "wof:name":"Spar- Und Leihkasse Hallau",
    "wof:placetype":"venue"
},
  "geometry": {"coordinates":[8.458765,47.697426],"type":"Point"}
}