{
  "type": "Feature",
  "properties": {
    "iso:country":"CH",
    "sg:address":"Riedmattstrasse 5",
    "sg:city":"R\u00fcmlang",
    "sg:orig_category":"Instandhaltung U Reparatur von Automobilen",
    "sg:phone":"+41 32 757 15 56",
    "sg:postcode":"8153",
    "sg:province":"Z\u00fcrich",
    "wof:name":"Storrer G\u00e9rald.",
    "wof:placetype":"venue"
},
  "geometry": {"coordinates":[7.0239601135,47.0374145508],"type":"Point"}
}