{
  "type": "Feature",
  "properties": {
    "iso:country":"CH",
    "sg:address":"K\u00fcfergasse 3",
    "sg:city":"Jens",
    "sg:orig_category":"Bauschreinerei Herstellung von Konstruktionsteilen, Fertigbauteilen U Ausbauelementen aus Holz",
    "sg:phone":"+41 32 331 64 59",
    "sg:postcode":"2565",
    "sg:province":"Bern",
    "wof:name":"Lehmann Heinz, Schreinerei, Innenausbau",
    "wof:placetype":"venue"
},
  "geometry": {"coordinates":[7.262347,47.099804],"type":"Point"}
}