{
  "type": "Feature",
  "properties": {
    "addr:full":"Sch\u00fctzenstrasse 3 9404 Rorschacherberg. Postfach Rorschacherberg St. Gallen 9404",
    "addr:housenumber":"3",
    "addr:postcode":"9404 rorschacherberg. postfach;9404",
    "addr:street":"Schuetzenstrasse",
    "iso:country":"CH",
    "sg:address":"Sch\u00fctzenstrasse 3 9404 Rorschacherberg. Postfach",
    "sg:city":"Rorschacherberg",
    "sg:orig_category":"Architekturb\u00fcros",
    "sg:phone":"+41 71 855 10 80",
    "sg:postcode":"9404",
    "sg:province":"St. Gallen",
    "wof:name":"Guido K\u00f6ppel Ingenieur-& Architekturb\u00fcro",
    "wof:placetype":"venue"
},
  "geometry": {"coordinates":[9.493688,47.469902],"type":"Point"}
}