{
  "type": "Feature",
  "properties": {
    "iso:country":"CH",
    "sg:address":"Rue Coll\u00e8ge 40",
    "sg:city":"Clarens",
    "sg:orig_category":"Detailhandel mit Fleisch U Fleischwaren Grosshandel mit Fleisch U Fleischwaren",
    "sg:phone":"+41 21 964 10 02",
    "sg:postcode":"1815",
    "sg:province":"Vaud",
    "wof:name":"Viandes Riviera - Lipka Fr\u00e8res Sa",
    "wof:placetype":"venue"
},
  "geometry": {"coordinates":[6.8935799599,46.4435043335],"type":"Point"}
}