{
  "type": "Feature",
  "properties": {
    "iso:country":"CH",
    "sg:address":"Heiligkreuz 19",
    "sg:city":"Vaduz",
    "sg:orig_category":"Offsetdruck",
    "sg:phone":"+423 232 19 90",
    "sg:postcode":"9490",
    "wof:name":"Gustav Jehle Buch-& Offsetdruck Ag",
    "wof:placetype":"venue"
},
  "geometry": {"coordinates":[9.5222120285,47.1349105835],"type":"Point"}
}