{
  "type": "Feature",
  "properties": {
    "iso:country":"CH",
    "sg:address":"Sch\u00fctzenstrasse 10 3770 Zweisimmen. Postfach 433",
    "sg:city":"Zweisimmen",
    "sg:orig_category":"Sanit\u00e4r, Heizungs U L\u00fcftungsinstallation Schlossereien",
    "sg:phone":"+41 71 923 40 70",
    "sg:postcode":"3770",
    "sg:province":"Bern",
    "wof:name":"Gubser Werner",
    "wof:placetype":"venue"
},
  "geometry": {"coordinates":[-77.13302612299999,40.4769287109],"type":"Point"}
}