{
  "type": "Feature",
  "properties": {
    "iso:country":"CH",
    "sg:address":"Officina Viale 17",
    "sg:city":"Bellinzona",
    "sg:classifiers":[
        {
            "category":"Travel",
            "subcategory":"Hotels & Motels",
            "type":"Entertainment"
        }
    ],
    "sg:postcode":"6500",
    "sg:province":"Ticino",
    "sg:tags":[
        "hotels",
        "mit",
        "restaurant"
    ],
    "wof:name":"Osman Mohamed Detto Mimmo",
    "wof:placetype":"venue"
},
  "geometry": {"coordinates":[9.0285711288,46.1982116699],"type":"Point"}
}