{
  "type": "Feature",
  "properties": {
    "iso:country":"CH",
    "sg:address":"Untere Br\u00fchlstrasse 21",
    "sg:city":"Zofingen",
    "sg:orig_category":"Softwareentwicklung U beratung",
    "sg:phone":"+41 62 745 30 61",
    "sg:postcode":"4800",
    "sg:province":"Aargau",
    "wof:name":"Kummer Werner",
    "wof:placetype":"venue"
},
  "geometry": {"coordinates":[7.933257103,47.2933654785],"type":"Point"}
}