{
  "type": "Feature",
  "properties": {
    "iso:country":"CH",
    "sg:address":"Webereistrasse 66 8134 Adliswil. Postfach",
    "sg:city":"Adliswil",
    "sg:orig_category":"Grosshandel mit Baumaschinen Herstellung von Bergwerks U Baumaschinen",
    "sg:phone":"+41 17104800",
    "sg:postcode":"8134",
    "sg:province":"Z\u00fcrich",
    "wof:name":"Aretor Bauger\u00e4te Ag",
    "wof:placetype":"venue"
},
  "geometry": {"coordinates":[8.5250873566,47.3049736023],"type":"Point"}
}