{
  "type": "Feature",
  "properties": {
    "iso:country":"CH",
    "sg:address":"Chemin De La Sallaz",
    "sg:city":"Yverdon-les-bains",
    "sg:orig_category":"Sonstige pers\u00f6nliche Dienstleistungen",
    "sg:phone":"+41 31 950 95 85",
    "sg:postcode":"1400",
    "sg:province":"Vaud",
    "wof:name":"Geoline",
    "wof:placetype":"venue"
},
  "geometry": {"coordinates":[7.4921388626,46.9354972839],"type":"Point"}
}