{
  "type": "Feature",
  "properties": {
    "iso:country":"CH",
    "sg:address":"Rathausenstrasse 1",
    "sg:city":"Emmen",
    "sg:orig_category":"Unclassifiable Establishments",
    "sg:postcode":"6032",
    "sg:province":"Luzern",
    "wof:name":"Informax Gmbh",
    "wof:placetype":"venue"
},
  "geometry": {"coordinates":[8.3075876236,47.0818481445],"type":"Point"}
}