{
  "type": "Feature",
  "properties": {
    "addr:full":"Avenue De La Gare 68 V\u00e9troz Valais 1963",
    "addr:housenumber":"68",
    "addr:postcode":"1963",
    "addr:street":"Avenue De La Gare",
    "iso:country":"CH",
    "sg:address":"Avenue De La Gare 68",
    "sg:city":"V\u00e9troz",
    "sg:orig_category":"Bauschreinerei Zimmerei, Dachdeckerei, Bauspenglerei U Abdichtung",
    "sg:phone":"+41 27 346 12 82",
    "sg:postcode":"1963",
    "sg:province":"Valais",
    "wof:name":"Udry Joseph",
    "wof:placetype":"venue"
},
  "geometry": {"coordinates":[7.272535,46.219532],"type":"Point"}
}