{
  "type": "Feature",
  "properties": {
    "iso:country":"CH",
    "sg:address":"Loorenrank 24",
    "sg:city":"Z\u00fcrich",
    "sg:orig_category":"Organisationen des Gesundheitswesen",
    "sg:phone":"+41 13835087",
    "sg:postcode":"8053",
    "sg:province":"Z\u00fcrich",
    "wof:name":"Danica Bibic Privat-krankenpflege Unas",
    "wof:placetype":"venue"
},
  "geometry": {"coordinates":[8.5953979492,47.3591575623],"type":"Point"}
}