{
  "type": "Feature",
  "properties": {
    "iso:country":"CH",
    "sg:address":"Bahnhofstrasse 9 3900 Brig. Postfach 697",
    "sg:city":"Brig",
    "sg:classifiers":[
        {
            "category":"Restaurant",
            "type":"Food & Drink"
        }
    ],
    "sg:phone":"+41 27 957 18 16",
    "sg:postcode":"3900",
    "sg:province":"Valais",
    "wof:name":"Restaurant Walliserkanne",
    "wof:placetype":"venue"
},
  "geometry": {"coordinates":[7.933672905,46.1117172241],"type":"Point"}
}