{
  "type": "Feature",
  "properties": {
    "iso:country":"CH",
    "sg:address":"Via Dante Alighieri 12",
    "sg:city":"Chiasso",
    "sg:orig_category":"Grosshandel mit chemischen Erzeugnissen Sonstiger Grosshandel",
    "sg:phone":"+41 22 809 40 80",
    "sg:postcode":"6830",
    "sg:province":"Ticino",
    "wof:name":"Stragen Pharma Sa",
    "wof:placetype":"venue"
},
  "geometry": {"coordinates":[6.1411190033,46.1940040588],"type":"Point"}
}