{
  "type": "Feature",
  "properties": {
    "iso:country":"CH",
    "sg:address":"Ai Campisc 8",
    "sg:city":"Camorino",
    "sg:orig_category":"Sonstige mit Sport verbundene T\u00e4tigkeiten",
    "sg:phone":"+41 91 857 60 40",
    "sg:postcode":"6528",
    "sg:province":"Ticino",
    "wof:name":"Tennis-club Flamingo Camorino Sa",
    "wof:placetype":"venue"
},
  "geometry": {"coordinates":[8.9866380692,46.1599197388],"type":"Point"}
}