{
  "type": "Feature",
  "properties": {
    "iso:country":"CH",
    "sg:address":"Scheideggstrasse 55",
    "sg:city":"Z\u00fcrich",
    "sg:orig_category":"Wasserversorgung",
    "sg:postcode":"8002",
    "sg:province":"Z\u00fcrich",
    "wof:name":"Aqua-detox Ag",
    "wof:placetype":"venue"
},
  "geometry": {"coordinates":[8.529540062,47.355178833],"type":"Point"}
}