{
  "type": "Feature",
  "properties": {
    "iso:country":"CH",
    "sg:address":"7504 Pontresina. Postfach 16",
    "sg:city":"Pontresina",
    "sg:orig_category":"Sportvereine Ballsport Tennis",
    "sg:phone":"+41 32 466 28 35",
    "sg:postcode":"7504",
    "sg:province":"Graubunden",
    "wof:name":"Tennisclub Porrentruy",
    "wof:placetype":"venue"
},
  "geometry": {"coordinates":[7.0860209465,47.4164390564],"type":"Point"}
}