{
  "type": "Feature",
  "properties": {
    "iso:country":"CH",
    "sg:address":"Via Cortivallo 21",
    "sg:city":"Lugano",
    "sg:orig_category":"Reinigungsgewerbe",
    "sg:phone":"+41 91 966 68 66",
    "sg:postcode":"6900",
    "sg:province":"Ticino",
    "wof:name":"Lodi Giorgio",
    "wof:placetype":"venue"
},
  "geometry": {"coordinates":[8.9389486313,46.0061645508],"type":"Point"}
}