{
  "type": "Feature",
  "properties": {
    "iso:country":"CH",
    "sg:address":"St. Anna",
    "sg:city":"Oberstammheim",
    "sg:orig_category":"Grosshandel mit Getr\u00e4nken",
    "sg:phone":"+41 52 745 28 58",
    "sg:postcode":"8477",
    "sg:province":"Z\u00fcrich",
    "wof:name":"K\u00e4gi & Meier, Weine",
    "wof:placetype":"venue"
},
  "geometry": {"coordinates":[8.7969150543,47.633430481],"type":"Point"}
}