{
  "type": "Feature",
  "properties": {
    "iso:country":"CH",
    "sg:address":"Waldhofstrasse 54",
    "sg:city":"Langenthal",
    "sg:orig_category":"P\u00e9dicure",
    "sg:phone":"+41 62 922 52 29",
    "sg:postcode":"4900",
    "sg:province":"Bern",
    "wof:name":"Doris Zurkirchen P\u00e9dicure",
    "wof:placetype":"venue"
},
  "geometry": {"coordinates":[7.7977128029,47.2157287598],"type":"Point"}
}