{
  "type": "Feature",
  "properties": {
    "addr:full":"Kantonsstrasse Vitznau Luzern 6354",
    "addr:postcode":"6354",
    "addr:street":"Kantonsstrasse",
    "iso:country":"CH",
    "sg:address":"Kantonsstrasse",
    "sg:city":"Vitznau",
    "sg:orig_category":"Clay For Tennis Courts",
    "sg:phone":"+41 41 399 60 60",
    "sg:postcode":"6354",
    "sg:province":"Luzern",
    "wof:name":"Park Hotel Vitznau Ag",
    "wof:placetype":"venue"
},
  "geometry": {"coordinates":[8.48331,47.010342],"type":"Point"}
}