{
  "type": "Feature",
  "properties": {
    "iso:country":"CH",
    "sg:address":"Feldenstrasse",
    "sg:city":"Sigriswil",
    "sg:orig_category":"Sonstiger Grosshandel",
    "sg:phone":"+41 41 630 42 46",
    "sg:postcode":"3655",
    "sg:province":"Bern",
    "wof:name":"Vitec Trade Company Ag",
    "wof:placetype":"venue"
},
  "geometry": {"coordinates":[8.3102197647,46.9972305298],"type":"Point"}
}