{
  "type": "Feature",
  "properties": {
    "iso:country":"CH",
    "sg:address":"Oberfeldstrasse 37",
    "sg:city":"Pratteln",
    "sg:orig_category":"Elektrizit\u00e4tsversorgung",
    "sg:postcode":"4133",
    "sg:province":"Basel-Landschaft",
    "wof:name":"Solargenossenschaft Pratteln Sopra",
    "wof:placetype":"venue"
},
  "geometry": {"coordinates":[7.705532074,47.5216140747],"type":"Point"}
}