{
  "type": "Feature",
  "properties": {
    "addr:full":"Schwabistalstrasse 4 Muhen Aargau 5037",
    "addr:housenumber":"4",
    "addr:postcode":"5037",
    "addr:street":"Schwabistalstrasse",
    "iso:country":"CH",
    "sg:address":"Schwabistalstrasse 4",
    "sg:city":"Muhen",
    "sg:orig_category":"Allgemeiner Hoch U Tiefbau",
    "sg:postcode":"5037",
    "sg:province":"Aargau",
    "wof:name":"Matter Baugesch\u00e4ft Ag",
    "wof:placetype":"venue"
},
  "geometry": {"coordinates":[8.054522,47.340252],"type":"Point"}
}