{
  "type": "Feature",
  "properties": {
    "iso:country":"CH",
    "sg:address":"R\u00fcdli",
    "sg:city":"Amsoldingen",
    "sg:classifiers":[
        {
            "category":"Personal",
            "subcategory":"Nail Salon",
            "type":"Services"
        }
    ],
    "sg:phone":"+41 33 341 18 14",
    "sg:postcode":"3633",
    "sg:province":"Bern",
    "sg:tags":[
        "manicure"
    ],
    "wof:name":"Marianne Joss Nail-kosmetik",
    "wof:placetype":"venue"
},
  "geometry": {"coordinates":[7.5872740746,46.7253761292],"type":"Point"}
}