{
  "type": "Feature",
  "properties": {
    "iso:country":"CH",
    "sg:address":"Rue De Lausanne 16",
    "sg:city":"Vallorbe",
    "sg:orig_category":"Instandhaltung U Reparatur von Automobilen",
    "sg:phone":"+41 21 843 11 13",
    "sg:postcode":"1337",
    "sg:province":"Vaud",
    "wof:name":"Garage Gasch Eric",
    "wof:placetype":"venue"
},
  "geometry": {"coordinates":[6.3808789253,46.7110786438],"type":"Point"}
}