{
  "type": "Feature",
  "properties": {
    "iso:country":"CH",
    "sg:address":"Grienbachstrasse 34",
    "sg:city":"Zug",
    "sg:orig_category":"Instandhaltung U Reparatur von Automobilen",
    "sg:phone":"+41 41 761 66 60",
    "sg:postcode":"6300",
    "sg:province":"Zug",
    "wof:name":"Schicker Automobile Ag",
    "wof:placetype":"venue"
},
  "geometry": {"coordinates":[8.5255413055,47.1822738647],"type":"Point"}
}