{
  "type": "Feature",
  "properties": {
    "iso:country":"CH",
    "sg:address":"Erligatterweg 14",
    "sg:city":"Z\u00fcrich",
    "sg:orig_category":"Grosshandel mit Nahrungsmitteln, Getr\u00e4nken U Tabakwaren ohne ausgepr\u00e4gten Schwerpunkt",
    "sg:phone":"+41 14618810",
    "sg:postcode":"8038",
    "sg:province":"Z\u00fcrich",
    "wof:name":"Import Von Delikatessen Claudia Messina",
    "wof:placetype":"venue"
},
  "geometry": {"coordinates":[8.5322914124,47.334072113],"type":"Point"}
}