{
  "type": "Feature",
  "properties": {
    "addr:full":"Erlenstrasse 6 4058 Basel. Postfach Basel Basel-Stadt 4051",
    "addr:housenumber":"6",
    "addr:postcode":"4058;4051",
    "addr:street":"Erlenstrasse;Postfach",
    "iso:country":"CH",
    "sg:address":"Erlenstrasse 6 4058 Basel. Postfach",
    "sg:city":"Basel",
    "sg:orig_category":"Betrieb von Taxis",
    "sg:postcode":"4051",
    "sg:province":"Basel-Stadt",
    "wof:name":"Rickenbacher Max Taxiunternehmen.",
    "wof:placetype":"venue"
},
  "geometry": {"coordinates":[7.598561,47.567963],"type":"Point"}
}