{
  "type": "Feature",
  "properties": {
    "addr:full":"Route Suisse 7 Mies Vaud 1295",
    "addr:housenumber":"7",
    "addr:postcode":"1295",
    "addr:street":"Route Suisse",
    "iso:country":"CH",
    "sg:address":"Route Suisse 7",
    "sg:city":"Mies",
    "sg:orig_category":"Autogaragen",
    "sg:phone":"+41 22 755 24 66",
    "sg:postcode":"1295",
    "sg:province":"Vaud",
    "wof:name":"Pierre Keller Garage Du Port",
    "wof:placetype":"venue"
},
  "geometry": {"coordinates":[6.16765,46.296635],"type":"Point"}
}