{
  "type": "Feature",
  "properties": {
    "iso:country":"CH",
    "sg:address":"Untere Br\u00fchlstrasse 28",
    "sg:city":"Zofingen",
    "sg:orig_category":"Grosshandel mit Holz U Bauelementen aus Holz Herstellung von Werkzeugen",
    "sg:phone":"+41 62 751 02 63",
    "sg:postcode":"4800",
    "sg:province":"Aargau",
    "wof:name":"Eichenberger & L\u00fcscher Ag",
    "wof:placetype":"venue"
},
  "geometry": {"coordinates":[7.9342141151,47.2925300598],"type":"Point"}
}