{
  "type": "Feature",
  "properties": {
    "iso:country":"CH",
    "sg:address":"Marktgasse 165 5080 Laufenburg. Postfach",
    "sg:city":"Laufenburg",
    "sg:orig_category":"Architektur U Ingenieurb\u00fcros",
    "sg:postcode":"5080",
    "sg:province":"Aargau",
    "wof:name":"Consab Gmbh Architektur + Baudienstleistungen",
    "wof:placetype":"venue"
},
  "geometry": {"coordinates":[8.060229,47.562599],"type":"Point"}
}