{
  "type": "Feature",
  "properties": {
    "iso:country":"CH",
    "sg:address":"Feldblumenweg 20",
    "sg:city":"Z\u00fcrich",
    "sg:orig_category":"Sonstiger Grosshandel",
    "sg:phone":"+41 14303550",
    "sg:postcode":"8048",
    "sg:province":"Z\u00fcrich",
    "wof:name":"Maxsoft Raschle R.",
    "wof:placetype":"venue"
},
  "geometry": {"coordinates":[8.484512,47.381317],"type":"Point"}
}