{
  "type": "Feature",
  "properties": {
    "iso:country":"CH",
    "sg:address":"Neuengass-passage 2 3011 Bern. Postfach",
    "sg:city":"Bern",
    "sg:orig_category":"Grosshandel mit Schuhen Grosshandel mit Sportartikeln",
    "sg:phone":"+41 31 326 21 11",
    "sg:postcode":"3001",
    "sg:province":"Bern",
    "wof:name":"Maikler Ag Schuhhandel Usw",
    "wof:placetype":"venue"
},
  "geometry": {"coordinates":[7.4429430962,46.9492034912],"type":"Point"}
}