{
  "type": "Feature",
  "properties": {
    "iso:country":"CH",
    "sg:address":"Unterm\u00fcli 11",
    "sg:city":"Zug",
    "sg:orig_category":"Non-Classified Establishments",
    "sg:postcode":"6300",
    "sg:province":"Zug",
    "wof:name":"Avuton Gmbh",
    "wof:placetype":"venue"
},
  "geometry": {"coordinates":[8.5173511505,47.1806297302],"type":"Point"}
}