{
  "type": "Feature",
  "properties": {
    "iso:country":"CH",
    "sg:address":"Talstrasse 8",
    "sg:city":"Seon",
    "sg:orig_category":"Herstellung von Platten, Folien, Schl\u00e4uchen U Profilen aus Kunststoff",
    "sg:phone":"+41 62 775 26 70",
    "sg:postcode":"5703",
    "sg:province":"Aargau",
    "wof:name":"Addiplast Martin Ziegler",
    "wof:placetype":"venue"
},
  "geometry": {"coordinates":[8.158162117,47.349281311],"type":"Point"}
}