{
  "type": "Feature",
  "properties": {
    "iso:country":"CH",
    "sg:address":"Mareestrasse 29",
    "sg:city":"Vaduz",
    "sg:classifiers":[
        {
            "category":"Travel",
            "subcategory":"Hotels & Motels",
            "type":"Entertainment"
        }
    ],
    "sg:phone":"+423 232 11 92",
    "sg:postcode":"9490",
    "sg:tags":[
        "hotels",
        "mit",
        "restaurant"
    ],
    "wof:name":"Parkhotel Sonnenhof",
    "wof:placetype":"venue"
},
  "geometry": {"coordinates":[9.524271965,47.1470603943],"type":"Point"}
}