{
  "type": "Feature",
  "properties": {
    "iso:country":"CH",
    "sg:address":"Saint-laurent Rue 14",
    "sg:city":"Lausanne",
    "sg:orig_category":"RESTAURANTS: TEA-ROOMS",
    "sg:phone":"+41 21 323 63 88",
    "sg:postcode":"1003",
    "sg:province":"Vaud",
    "wof:name":"Le Farinet-lausanne Sa",
    "wof:placetype":"venue"
},
  "geometry": {"coordinates":[6.6311430931,46.5224838257],"type":"Point"}
}