{
  "type": "Feature",
  "properties": {
    "addr:full":"Liestalerstrasse 29 4052 Basel. Postfach Basel Basel-Stadt 4051",
    "addr:housenumber":"29",
    "addr:postcode":"4052;4051",
    "addr:street":"Liestalerstrasse;Postfach",
    "iso:country":"CH",
    "sg:address":"Liestalerstrasse 29 4052 Basel. Postfach",
    "sg:city":"Basel",
    "sg:orig_category":"Allgemeiner Hoch U Tiefbau",
    "sg:postcode":"4051",
    "sg:province":"Basel-Stadt",
    "wof:name":"Baugesch\u00e4ft E. Berger",
    "wof:placetype":"venue"
},
  "geometry": {"coordinates":[7.614739,47.554798],"type":"Point"}
}