{
  "type": "Feature",
  "properties": {
    "iso:country":"CH",
    "sg:address":"Limmatstrasse 264",
    "sg:city":"Z\u00fcrich",
    "sg:orig_category":"Grosshandel mit Getr\u00e4nken Grosshandel mit sonstigen Getr\u00e4nken",
    "sg:phone":"+41 12733130",
    "sg:postcode":"8005",
    "sg:province":"Z\u00fcrich",
    "wof:name":"Steinfels Weinauktionen Und Weinhandels Ag",
    "wof:placetype":"venue"
},
  "geometry": {"coordinates":[8.5261411667,47.3886184692],"type":"Point"}
}