{
  "type": "Feature",
  "properties": {
    "iso:country":"CH",
    "sg:address":"Route Des Iles 22",
    "sg:city":"Sion",
    "sg:classifiers":[
        {
            "category":"Manufacturing",
            "subcategory":"Printing",
            "type":"Manufacturing & Wholesale Goods"
        }
    ],
    "sg:phone":"+41 27 203 77 00",
    "sg:postcode":"1950",
    "sg:province":"Valais",
    "sg:tags":[
        "house",
        "book"
    ],
    "wof:name":"Sirius Print S\u00e0rl",
    "wof:placetype":"venue"
},
  "geometry": {"coordinates":[7.342168,46.217754],"type":"Point"}
}