{
  "type": "Feature",
  "properties": {
    "addr:full":"Seebahnstrasse 113 Z\u00fcrich Z\u00fcrich 8003",
    "addr:housenumber":"113",
    "addr:postcode":"8003",
    "addr:street":"Seebahnstrasse",
    "iso:country":"CH",
    "sg:address":"Seebahnstrasse 113",
    "sg:city":"Z\u00fcrich",
    "sg:classifiers":[
        {
            "category":"Manufacturing",
            "subcategory":"Furniture",
            "type":"Manufacturing & Wholesale Goods"
        }
    ],
    "sg:phone":"+41 14627168",
    "sg:postcode":"8003",
    "sg:province":"Z\u00fcrich",
    "sg:tags":[
        "children's"
    ],
    "wof:name":"K. Brack & Co",
    "wof:placetype":"venue"
},
  "geometry": {"coordinates":[8.520495,47.37281],"type":"Point"}
}