{
  "type": "Feature",
  "properties": {
    "iso:country":"CH",
    "sg:address":"Bahnhofstrasse",
    "sg:city":"Schiers",
    "sg:classifiers":[
        {
            "category":"Banks & Credit Unions",
            "subcategory":"Bank",
            "type":"Services"
        }
    ],
    "sg:phone":"+41 56 443 29 76",
    "sg:postcode":"7220",
    "sg:province":"Graubunden",
    "wof:name":"Raiffeisenbank Schinznach-villnachern",
    "wof:placetype":"venue"
},
  "geometry": {"coordinates":[8.14182,47.44709],"type":"Point"}
}