{
  "type": "Feature",
  "properties": {
    "iso:country":"CH",
    "sg:address":"Rue Alcide-jentzer 11",
    "sg:city":"Gen\u00e8ve",
    "sg:orig_category":"Autogaragen Autospenglereien",
    "sg:phone":"+41 22 320 16 28",
    "sg:postcode":"1205",
    "sg:province":"Gen\u00e8ve",
    "wof:name":"Andr\u00e9 Galera Carrosserie & Garage De La Cluse Sa",
    "wof:placetype":"venue"
},
  "geometry": {"coordinates":[6.145778,46.192188],"type":"Point"}
}