{
  "type": "Feature",
  "properties": {
    "iso:country":"CH",
    "sg:address":"R\u00fctib\u00fchl 1582 8704 Herrliberg. Postfach",
    "sg:city":"Herrliberg",
    "sg:classifiers":[
        {
            "category":"Travel",
            "subcategory":"Hotels & Motels",
            "type":"Entertainment"
        }
    ],
    "sg:postcode":"8704",
    "sg:province":"Z\u00fcrich",
    "sg:tags":[
        "hotels",
        "mit",
        "restaurant"
    ],
    "wof:name":"Avita Ag Geophatologie, Seminare Im Bereich Des Gesundheitswesens Usw",
    "wof:placetype":"venue"
},
  "geometry": {"coordinates":[8.6135377884,47.2861976624],"type":"Point"}
}