{
  "type": "Feature",
  "properties": {
    "iso:country":"CH",
    "sg:address":"Rebweg 185",
    "sg:city":"Trasadingen",
    "sg:orig_category":"G\u00fcterbef\u00f6rderung im Strassenverkehr",
    "sg:phone":"+41 52 681 25 07",
    "sg:postcode":"8219",
    "sg:province":"Schaffhausen",
    "wof:name":"R\u00fceger Alex Gmbh",
    "wof:placetype":"venue"
},
  "geometry": {"coordinates":[8.431096077,47.6706886292],"type":"Point"}
}