{
  "type": "Feature",
  "properties": {
    "iso:country":"CH",
    "sg:address":"Im Bruggen 16",
    "sg:city":"Bonstetten",
    "sg:orig_category":"Vereine Gesang",
    "sg:postcode":"8906",
    "sg:province":"Z\u00fcrich",
    "wof:name":"S\u00e4ngerbund Am Albis",
    "wof:placetype":"venue"
},
  "geometry": {"coordinates":[8.4742660522,47.3247680664],"type":"Point"}
}