{
  "type": "Feature",
  "properties": {
    "addr:full":"Kirchhalde 9 Uttwil Thurgau 8592",
    "addr:housenumber":"9",
    "addr:postcode":"8592",
    "addr:street":"Kirchhalde",
    "iso:country":"CH",
    "sg:address":"Kirchhalde 9",
    "sg:city":"Uttwil",
    "sg:orig_category":"Arztpraxen",
    "sg:phone":"+41 71 461 25 25",
    "sg:postcode":"8592",
    "sg:province":"Thurgau",
    "wof:name":"Dr.med.martin Kl\u00e4usler Arzt F.allgemeine Medizin Fmh",
    "wof:placetype":"venue"
},
  "geometry": {"coordinates":[9.342285,47.583839],"type":"Point"}
}