{
  "type": "Feature",
  "properties": {
    "iso:country":"CH",
    "sg:address":"Avenue Des Alpes 13",
    "sg:city":"Sierre",
    "sg:orig_category":"Handels-H\u00e4user U Gesellschaften",
    "sg:postcode":"3960",
    "sg:province":"Valais",
    "wof:name":"Snc Proxima Wyss N. Kuster D. Vianin F.",
    "wof:placetype":"venue"
},
  "geometry": {"coordinates":[7.5288658142,46.2930183411],"type":"Point"}
}