{
  "type": "Feature",
  "properties": {
    "iso:country":"CH",
    "sg:address":"Rue Du Milieu 3",
    "sg:city":"Buttes",
    "sg:orig_category":"Non-Classified Establishments",
    "sg:postcode":"2115",
    "sg:province":"Neuch\u00e2tel",
    "wof:name":"Buffet De La Gare Chaudet Et Cie",
    "wof:placetype":"venue"
},
  "geometry": {"coordinates":[6.5520429611,46.8880348206],"type":"Point"}
}