{
  "type": "Feature",
  "properties": {
    "iso:country":"CH",
    "sg:address":"Chemin Des Lovi\u00e8res 4",
    "sg:city":"Tramelan",
    "sg:orig_category":"Sprachschulen",
    "sg:phone":"+41 32 487 47 84",
    "sg:postcode":"2720",
    "sg:province":"Bern",
    "wof:name":"Ecole Commerciale & Professionnelle",
    "wof:placetype":"venue"
},
  "geometry": {"coordinates":[7.1059231758,47.2218513489],"type":"Point"}
}