{
  "type": "Feature",
  "properties": {
    "iso:country":"CH",
    "sg:address":"Rietwisstrasse 40 9100 Herisau. Postfach",
    "sg:city":"Herisau",
    "sg:orig_category":"Herstellung von \u00d6fen U Brennern",
    "sg:phone":"+41 79 697 64 92",
    "sg:postcode":"9101",
    "sg:province":"Appenzell Ausserrhoden",
    "wof:name":"Hans Weishaupt",
    "wof:placetype":"venue"
},
  "geometry": {"coordinates":[9.262881279,47.39868927],"type":"Point"}
}