{
  "type": "Feature",
  "properties": {
    "iso:country":"CH",
    "sg:address":"Leimackerstrasse",
    "sg:city":"Sulgen",
    "sg:orig_category":"Dachdeckerei Zimmerei, Dachdeckerei, Bauspenglerei U Abdichtung",
    "sg:phone":"+41 61 713 10 25",
    "sg:postcode":"8583",
    "sg:province":"Thurgau",
    "wof:name":"Sch\u00fcepp Paul Spenglerei Und Bedachungen",
    "wof:placetype":"venue"
},
  "geometry": {"coordinates":[7.594515,47.486919],"type":"Point"}
}