{
  "type": "Feature",
  "properties": {
    "iso:country":"CH",
    "sg:address":"Sch\u00fctzenstrasse 8",
    "sg:city":"Birsfelden",
    "sg:orig_category":"Tanzschulen, Tanzlehrer",
    "sg:phone":"+41 61 312 97 30",
    "sg:postcode":"4127",
    "sg:province":"Basel-Landschaft",
    "wof:name":"Clarice Wiedemann Tanzschule Dos Santos",
    "wof:placetype":"venue"
},
  "geometry": {"coordinates":[7.6246361732,47.5537147522],"type":"Point"}
}