{
  "type": "Feature",
  "properties": {
    "iso:country":"CH",
    "sg:address":"Lenzburgerstrasse 40 5507 Mellingen. Postfach",
    "sg:city":"Mellingen",
    "sg:orig_category":"Sonstige Personenbef\u00f6rderung im Landverkehr",
    "sg:phone":"+41 56 491 11 44",
    "sg:postcode":"5507",
    "sg:province":"Aargau",
    "wof:name":"Geissmann Reisen Ag",
    "wof:placetype":"venue"
},
  "geometry": {"coordinates":[8.2694330215,47.4141616821],"type":"Point"}
}