{
  "type": "Feature",
  "properties": {
    "addr:full":"Rheinstrasse 79 9443 Widnau. Postfach 48 Widnau St. Gallen 9443",
    "addr:housenumber":"79;48",
    "addr:postcode":"9443;9443",
    "addr:street":"Rheinstrasse;Postfach;Widnau",
    "iso:country":"CH",
    "sg:address":"Rheinstrasse 79 9443 Widnau. Postfach 48",
    "sg:city":"Widnau",
    "sg:orig_category":"Architektur U Ingenieurb\u00fcros",
    "sg:phone":"+41 41 871 14 37",
    "sg:postcode":"9443",
    "sg:province":"St. Gallen",
    "wof:name":"Cadmold Gmbh",
    "wof:placetype":"venue"
},
  "geometry": {"coordinates":[9.64687,47.408905],"type":"Point"}
}