{
  "type": "Feature",
  "properties": {
    "iso:country":"CH",
    "sg:address":"Wasserweg",
    "sg:city":"Filisur",
    "sg:orig_category":"Non-Classified Establishments",
    "sg:postcode":"7477",
    "sg:province":"Graubunden",
    "wof:name":"Stella - Flor Nobs",
    "wof:placetype":"venue"
},
  "geometry": {"coordinates":[9.687505722,46.6718864441],"type":"Point"}
}