{
  "type": "Feature",
  "properties": {
    "iso:country":"CH",
    "sg:address":"Z\u00fcrichstrasse 14 8306 Br\u00fcttisellen. Postfach",
    "sg:city":"M\u00e4nnedorf",
    "sg:orig_category":"Elektroinstallation",
    "sg:postcode":"8708",
    "sg:province":"Z\u00fcrich",
    "wof:name":"Techno Gubler",
    "wof:placetype":"venue"
},
  "geometry": {"coordinates":[8.6324682236,47.4249076843],"type":"Point"}
}