{
  "type": "Feature",
  "properties": {
    "iso:country":"CH",
    "sg:address":"Kirchweg 19 6375 Beckenried. Postfach 19",
    "sg:city":"Beckenried",
    "sg:orig_category":"Detailhandel mit Sportartikeln Fachdetailhandel in Verkaufsr\u00e4umen",
    "sg:phone":"+41 41 620 12 65",
    "sg:postcode":"6375",
    "sg:province":"Nidwalden",
    "wof:name":"Murer Sport Gmbh",
    "wof:placetype":"venue"
},
  "geometry": {"coordinates":[8.4737091064,46.9666442871],"type":"Point"}
}