{
  "type": "Feature",
  "properties": {
    "iso:country":"CH",
    "sg:address":"Cit\u00e9-des-jardins Rte De 15",
    "sg:city":"Fribourg",
    "sg:orig_category":"Sonstiger spezialisierter Hoch U Tiefbau",
    "sg:phone":"+41 26 481 39 04",
    "sg:postcode":"1700",
    "sg:province":"Fribourg",
    "wof:name":"Genoud Jean-louis",
    "wof:placetype":"venue"
},
  "geometry": {"coordinates":[7.171227932,46.8090782166],"type":"Point"}
}