{
  "type": "Feature",
  "properties": {
    "iso:country":"CH",
    "sg:address":"Lindenhof",
    "sg:city":"Gunzwil",
    "sg:orig_category":"Abbruch U Sprenggewerbe, Erdbewegungsarbeiten",
    "sg:phone":"+41 41 930 14 51",
    "sg:postcode":"6222",
    "sg:province":"Luzern",
    "wof:name":"Frischkopf Ag",
    "wof:placetype":"venue"
},
  "geometry": {"coordinates":[8.186275,47.20892],"type":"Point"}
}