{
  "type": "Feature",
  "properties": {
    "addr:full":"Marktstrasse 1 Grenchen Solothurn 2540",
    "addr:housenumber":"1",
    "addr:postcode":"2540",
    "addr:street":"Marktstrasse",
    "iso:country":"CH",
    "sg:address":"Marktstrasse 1",
    "sg:city":"Grenchen",
    "sg:orig_category":"Arztpraxen",
    "sg:phone":"+41 56 633 22 24",
    "sg:postcode":"2540",
    "sg:province":"Solothurn",
    "wof:name":"Dres Med. Ch. & H. Karli Aerzte F\u00fcr Allg.medizin",
    "wof:placetype":"venue"
},
  "geometry": {"coordinates":[8.344641,47.35165],"type":"Point"}
}