{
  "type": "Feature",
  "properties": {
    "iso:country":"CH",
    "sg:address":"Hauptstrasse 18 9042 Speicher. Postfach",
    "sg:city":"Speicher",
    "sg:orig_category":"Druck ohne Zeitungsdruck Offsetdruck",
    "sg:phone":"+41 31 331 61 26",
    "sg:postcode":"9042",
    "sg:province":"Appenzell Ausserrhoden",
    "wof:name":"Druckerei L\u00e4derach Ag",
    "wof:placetype":"venue"
},
  "geometry": {"coordinates":[7.453371048,46.9561042786],"type":"Point"}
}