{
  "type": "Feature",
  "properties": {
    "iso:country":"CH",
    "sg:address":"Route De Lausanne",
    "sg:city":"Prangins",
    "sg:classifiers":[
        {
            "category":"Restaurant",
            "type":"Food & Drink"
        }
    ],
    "sg:phone":"+41 22 361 86 01",
    "sg:postcode":"1197",
    "sg:province":"Vaud",
    "wof:name":"Caf\u00e9 Les Ab\u00e9riaux",
    "wof:placetype":"venue"
},
  "geometry": {"coordinates":[6.2556052208,46.3940849304],"type":"Point"}
}