{
  "type": "Feature",
  "properties": {
    "iso:country":"CH",
    "sg:address":"Industriestrasse 13c 6300 Zug. Postfach",
    "sg:city":"Zug",
    "sg:orig_category":"Unternehmensberatung",
    "sg:phone":"+41 71 228 09 11",
    "sg:postcode":"6300",
    "sg:province":"Zug",
    "wof:name":"R.f. Fleischmann & Partner Gmbh",
    "wof:placetype":"venue"
},
  "geometry": {"coordinates":[9.3709163666,47.4205780029],"type":"Point"}
}