{
  "type": "Feature",
  "properties": {
    "iso:country":"CH",
    "sg:address":"Rue Ernest-roulet 7 2034 Peseux Case Postale 73",
    "sg:city":"Peseux",
    "sg:orig_category":"Detailhandel mit Radio U Fernsehger\u00e4ten Elektroinstallation",
    "sg:phone":"+41 32 731 91 91",
    "sg:postcode":"2034",
    "sg:province":"Neuch\u00e2tel",
    "wof:name":"T\u00e9l\u00e9 R\u00e9pa M.-j. Rohner Radios, T\u00e9l\u00e9visions, Hi-fi; Achat, Vente, Location Etc",
    "wof:placetype":"venue"
},
  "geometry": {"coordinates":[6.8880991936,46.9855651855],"type":"Point"}
}