{
  "type": "Feature",
  "properties": {
    "iso:country":"CH",
    "sg:address":"Hauptstrasse 5",
    "sg:city":"Kleind\u00f6ttingen",
    "sg:orig_category":"Lichtpause U Reprografiebetriebe Satzherstellung U Reproduktion",
    "sg:phone":"+41 56 245 57 59",
    "sg:postcode":"5314",
    "sg:province":"Aargau",
    "wof:name":"Meier-druck Ag",
    "wof:placetype":"venue"
},
  "geometry": {"coordinates":[8.2493610382,47.5718383789],"type":"Point"}
}