{
  "type": "Feature",
  "properties": {
    "iso:country":"CH",
    "sg:address":"Rue De Maillefer 29",
    "sg:city":"Neuch\u00e2tel",
    "sg:orig_category":"Detailhandel mit Parf\u00fcmerieartikeln U K\u00f6rperpflegemitteln Herstellung von Duft U K\u00f6rperpflegemitteln",
    "sg:phone":"+41 22 365 44 00",
    "sg:postcode":"2000",
    "sg:province":"Neuch\u00e2tel",
    "wof:name":"Renessence Ifg Sa Fabr.de Parfums",
    "wof:placetype":"venue"
},
  "geometry": {"coordinates":[6.2220640182,46.3839073181],"type":"Point"}
}