{
  "type": "Feature",
  "properties": {
    "iso:country":"CH",
    "sg:address":"F\u00fcrigenrain",
    "sg:city":"F\u00fcrigen",
    "sg:orig_category":"Unternehmensberatung",
    "sg:phone":"+41 61 711 05 50",
    "sg:postcode":"6363",
    "sg:province":"Nidwalden",
    "wof:name":"J\u00e4ggi Consulting Beratung, Unterst\u00fctzung U. Mediation Von Unternehmen, Teams U. Einzelpersonen Im Personalbereich",
    "wof:placetype":"venue"
},
  "geometry": {"coordinates":[8.3498659134,46.9820137024],"type":"Point"}
}