{
  "type": "Feature",
  "properties": {
    "iso:country":"CH",
    "sg:address":"Gewerbestrasse 23 4512 Bellach. Postfach 309",
    "sg:city":"Bellach",
    "sg:orig_category":"Instandhaltung U Reparatur von Automobilen",
    "sg:phone":"+41 32 618 14 34",
    "sg:postcode":"4512",
    "sg:province":"Solothurn",
    "wof:name":"Autogarage Fluri Kurt",
    "wof:placetype":"venue"
},
  "geometry": {"coordinates":[7.494617939,47.2100067139],"type":"Point"}
}