{
  "type": "Feature",
  "properties": {
    "iso:country":"CH",
    "sg:address":"Via Ai Chiabi 16",
    "sg:city":"Biasca",
    "sg:classifiers":[
        {
            "category":"Bars & Pubs",
            "type":"Food & Drink"
        }
    ],
    "sg:phone":"+41 91 862 38 96",
    "sg:postcode":"6710",
    "sg:province":"Ticino",
    "wof:name":"Bar Mondo",
    "wof:placetype":"venue"
},
  "geometry": {"coordinates":[8.958556,46.357132],"type":"Point"}
}