{
  "type": "Feature",
  "properties": {
    "iso:country":"CH",
    "sg:address":"Rue Des Granges 1200 Gen\u00e8ve. Postfach",
    "sg:city":"Gen\u00e8ve",
    "sg:orig_category":"Beherbergungsgewerbe",
    "sg:phone":"+41 21 903 10 72",
    "sg:postcode":"1204",
    "sg:province":"Gen\u00e8ve",
    "wof:name":"Fondation Les Chardouilles",
    "wof:placetype":"venue"
},
  "geometry": {"coordinates":[6.770595,46.593719],"type":"Point"}
}