{
  "type": "Feature",
  "properties": {
    "addr:full":"Seestrasse 360 Z\u00fcrich Z\u00fcrich 8038",
    "addr:housenumber":"360",
    "addr:postcode":"8038",
    "addr:street":"Seestrasse",
    "iso:country":"CH",
    "sg:address":"Seestrasse 360",
    "sg:city":"Z\u00fcrich",
    "sg:orig_category":"Detailhandel mit Blumen U Pflanzen Fachdetailhandel in Verkaufsr\u00e4umen",
    "sg:phone":"+41 14812020",
    "sg:postcode":"8038",
    "sg:province":"Z\u00fcrich",
    "wof:name":"Blumen Bajazzo, Saladin",
    "wof:placetype":"venue"
},
  "geometry": {"coordinates":[8.533542,47.344772],"type":"Point"}
}