{
  "type": "Feature",
  "properties": {
    "iso:country":"CH",
    "sg:address":"Waisenhausstrasse 10",
    "sg:city":"Herisau",
    "sg:orig_category":"Schulpflegen",
    "sg:phone":"+41 71 354 54 54",
    "sg:postcode":"9100",
    "sg:province":"Appenzell Ausserrhoden",
    "wof:name":"Schulverwaltung",
    "wof:placetype":"venue"
},
  "geometry": {"coordinates":[9.2811279297,47.3905944824],"type":"Point"}
}