{
  "type": "Feature",
  "properties": {
    "iso:country":"CH",
    "sg:address":"Via Del Tiglio 3 6900 Lugano. Postfach",
    "sg:city":"Lugano",
    "sg:orig_category":"Detektivb\u00fcros U \u00dcberwachung",
    "sg:postcode":"6900",
    "sg:province":"Ticino",
    "wof:name":"P.s. Private Service Security Sa",
    "wof:placetype":"venue"
},
  "geometry": {"coordinates":[8.9614286423,46.0073471069],"type":"Point"}
}