{
  "type": "Feature",
  "properties": {
    "iso:country":"CH",
    "sg:address":"1180",
    "sg:city":"Tartegnin",
    "sg:orig_category":"RESTAURANTS: TEA-ROOMS",
    "sg:phone":"+41 21 826 08 16",
    "sg:postcode":"1180",
    "sg:province":"Vaud",
    "wof:name":"Caf\u00e9-restaurant Le Serpolet, Ducret Jo\u00eblle",
    "wof:placetype":"venue"
},
  "geometry": {"coordinates":[6.316699028,46.4661178589],"type":"Point"}
}