{
  "type": "Feature",
  "properties": {
    "iso:country":"CH",
    "sg:address":"Kieselgasse 12",
    "sg:city":"Z\u00fcrich",
    "sg:orig_category":"Finanzierungsinstitutionen",
    "sg:phone":"+41 16872700",
    "sg:postcode":"8008",
    "sg:province":"Z\u00fcrich",
    "wof:name":"Rtm Financial Coaching Ag",
    "wof:placetype":"venue"
},
  "geometry": {"coordinates":[8.5573730469,47.3561439514],"type":"Point"}
}