{
  "type": "Feature",
  "properties": {
    "iso:country":"CH",
    "sg:address":"Pictet-de-rochemont Av.",
    "sg:city":"Gen\u00e8ve",
    "sg:orig_category":"Sonstiger Grosshandel",
    "sg:postcode":"1207",
    "sg:province":"Gen\u00e8ve",
    "wof:name":"Rochemont Industries Sa",
    "wof:placetype":"venue"
},
  "geometry": {"coordinates":[6.1570501328,46.2024993896],"type":"Point"}
}