{
  "type": "Feature",
  "properties": {
    "iso:country":"CH",
    "sg:address":"1095 Ch\u00e2telard-lutry Case Postale 190",
    "sg:city":"Ch\u00e2telard-lutry",
    "sg:orig_category":"Elektrizit\u00e4tsversorgung Gasversorgung",
    "sg:phone":"+41 21 791 11 31",
    "sg:postcode":"1095",
    "sg:province":"Vaud",
    "wof:name":"Services Industriels Administration Communale",
    "wof:placetype":"venue"
},
  "geometry": {"coordinates":[6.6857571602,46.5032806396],"type":"Point"}
}