{
  "type": "Feature",
  "properties": {
    "iso:country":"CH",
    "sg:address":"Beckenhofstrasse 30",
    "sg:city":"Z\u00fcrich",
    "sg:orig_category":"Herstellung von Schreinerwaren ohne ausgepr\u00e4gten Schwerpunkt Innenausbau",
    "sg:phone":"+41 13617474",
    "sg:postcode":"8006",
    "sg:province":"Z\u00fcrich",
    "wof:name":"Schreineria Straube Michael",
    "wof:placetype":"venue"
},
  "geometry": {"coordinates":[8.5413427353,47.3854560852],"type":"Point"}
}