{
  "type": "Feature",
  "properties": {
    "iso:country":"CH",
    "sg:address":"D\u00e4llikerstrasse 44",
    "sg:city":"Regensdorf",
    "sg:orig_category":"Arztpraxen",
    "sg:phone":"+41 56 442 00 86",
    "sg:postcode":"8105",
    "sg:province":"Z\u00fcrich",
    "wof:name":"Dr.med.felix Horn Arzt F\u00fcr Allgemeine Medizin",
    "wof:placetype":"venue"
},
  "geometry": {"coordinates":[8.207449,47.480824],"type":"Point"}
}