{
  "type": "Feature",
  "properties": {
    "iso:country":"CH",
    "sg:address":"Liesbergerstrasse 35",
    "sg:city":"Liesberg",
    "sg:orig_category":"Non-Classified Establishments",
    "sg:phone":"+41 61 771 01 29",
    "sg:postcode":"4253",
    "sg:province":"Basel-Landschaft",
    "wof:name":"Jermann Charles, Naturstein-import",
    "wof:placetype":"venue"
},
  "geometry": {"coordinates":[7.4343252182,47.3999404907],"type":"Point"}
}