{
  "type": "Feature",
  "properties": {
    "iso:country":"CH",
    "sg:address":"Grellingerstrasse 23",
    "sg:city":"Nunningen",
    "sg:orig_category":"Forschung U Entwicklung im Bereich der Naturwissenschaften Technische, physikalische U chemische Unt",
    "sg:phone":"+41 61 795 96 18",
    "sg:postcode":"4208",
    "sg:province":"Solothurn",
    "wof:name":"Laboratorium F.oekotoxikologie Dr.silvio Leonardi",
    "wof:placetype":"venue"
},
  "geometry": {"coordinates":[7.614107132,47.3968582153],"type":"Point"}
}