{
  "type": "Feature",
  "properties": {
    "iso:country":"CH",
    "sg:address":"Worblaufenstr. 159 3063 Ittigen. Postfach",
    "sg:city":"Worblaufen",
    "sg:orig_category":"Detailhandel mit Antiquit\u00e4ten U Gebrauchtwaren in Verkaufsr\u00e4umen",
    "sg:postcode":"3048",
    "sg:province":"Bern",
    "wof:name":"Hiob-stiftung",
    "wof:placetype":"venue"
},
  "geometry": {"coordinates":[7.461787,46.977802],"type":"Point"}
}