{
  "type": "Feature",
  "properties": {
    "iso:country":"CH",
    "sg:address":"Chemin Des Grands-pins 13",
    "sg:city":"Neuch\u00e2tel",
    "sg:orig_category":"Religi\u00f6se Vereinigungen divers Vereine Gemeinn\u00fctzige",
    "sg:phone":"+41 32 724 06 31",
    "sg:postcode":"2000",
    "sg:province":"Neuch\u00e2tel",
    "wof:name":"Entraide Cath.-chr\u00e9t.suisse Ne",
    "wof:placetype":"venue"
},
  "geometry": {"coordinates":[6.9331479073,46.997543335],"type":"Point"}
}