{
  "type": "Feature",
  "properties": {
    "iso:country":"CH",
    "sg:address":"Via Alla Ramogna 4",
    "sg:city":"Locarno",
    "sg:orig_category":"Interessenvertretungen",
    "sg:postcode":"6600",
    "sg:province":"Ticino",
    "wof:name":"Fondazione Parroco Erborista K\u00fcnzle",
    "wof:placetype":"venue"
},
  "geometry": {"coordinates":[8.7995786667,46.1711425781],"type":"Point"}
}