{
  "type": "Feature",
  "properties": {
    "iso:country":"CH",
    "sg:address":"Pr\u00e9-bois Route Des 20",
    "sg:city":"Meyrin",
    "sg:orig_category":"Hardwareberatung",
    "sg:postcode":"1217",
    "sg:province":"Gen\u00e8ve",
    "wof:name":"Concert Global Networks Ltd, Londres, Succursale De Meyrin Grossiste De Services En T\u00e9l\u00e9communication",
    "wof:placetype":"venue"
},
  "geometry": {"coordinates":[6.0722160339,46.2284431458],"type":"Point"}
}