{
  "type": "Feature",
  "properties": {
    "iso:country":"CH",
    "sg:address":"Weissenb\u00fchlweg 45",
    "sg:city":"Bern",
    "sg:orig_category":"Herstellung von Reiseartikeln, Leder U Sattlerwaren Innendekorationsateliers",
    "sg:phone":"+41 31 371 20 19",
    "sg:postcode":"3007",
    "sg:province":"Bern",
    "wof:name":"Kurt G\u00fcdel Sattlerei Antikpolsterei",
    "wof:placetype":"venue"
},
  "geometry": {"coordinates":[7.4371900558,46.937171936],"type":"Point"}
}