{
  "type": "Feature",
  "properties": {
    "iso:country":"CH",
    "sg:address":"Aewilerstrasse 1 9608 Ganterschwil. Postfach 31",
    "sg:city":"Ganterschwil",
    "sg:orig_category":"Detailhandel mit Fleisch U Fleischwaren HOTELS: MIT RESTAURANT",
    "sg:phone":"+41 71 983 16 81",
    "sg:postcode":"9608",
    "sg:province":"St. Gallen",
    "wof:name":"Hotel-restaurant L\u00f6wen Thoma Pius",
    "wof:placetype":"venue"
},
  "geometry": {"coordinates":[9.0901184082,47.3808021545],"type":"Point"}
}