{
  "type": "Feature",
  "properties": {
    "iso:country":"CH",
    "sg:address":"Via Al Ticino",
    "sg:city":"Sementina",
    "sg:orig_category":"Detailhandel mit Bekleidung Detailhandel mit Geschenkartikeln U Souvenirs",
    "sg:phone":"+41 91 857 61 26",
    "sg:postcode":"6514",
    "sg:province":"Ticino",
    "wof:name":"Tocade Sagl",
    "wof:placetype":"venue"
},
  "geometry": {"coordinates":[8.992004,46.182693],"type":"Point"}
}