{
  "type": "Feature",
  "properties": {
    "iso:country":"CH",
    "sg:address":"Unionstrasse 17",
    "sg:city":"Goldach",
    "sg:classifiers":[
        {
            "category":"Professional",
            "subcategory":"Art Services",
            "type":"Services"
        }
    ],
    "sg:phone":"+41 71 840 08 60",
    "sg:postcode":"9403",
    "sg:province":"St. Gallen",
    "sg:tags":[
        "homepage",
        "designing"
    ],
    "wof:name":"Tedoc",
    "wof:placetype":"venue"
},
  "geometry": {"coordinates":[9.463137,47.471806],"type":"Point"}
}