{
  "type": "Feature",
  "properties": {
    "iso:country":"CH",
    "sg:address":"Clos-du-boux",
    "sg:city":"Epesses",
    "sg:orig_category":"Grosshandel mit Getr\u00e4nken Rebbau",
    "sg:phone":"+41 21 799 21 47",
    "sg:postcode":"1098",
    "sg:province":"Vaud",
    "wof:name":"Massy Luc",
    "wof:placetype":"venue"
},
  "geometry": {"coordinates":[6.745704174,46.4925041199],"type":"Point"}
}