{
  "type": "Feature",
  "properties": {
    "iso:country":"CH",
    "sg:address":"Rue Du Bourg",
    "sg:city":"Martigny",
    "sg:orig_category":"Herstellung von Teppichen",
    "sg:postcode":"1920",
    "sg:province":"Valais",
    "wof:name":"Sarrasin Herv\u00e9",
    "wof:placetype":"venue"
},
  "geometry": {"coordinates":[7.0613689423,46.0888595581],"type":"Point"}
}