{
  "type": "Feature",
  "properties": {
    "iso:country":"CH",
    "sg:address":"Sch\u00fctzengraben 13",
    "sg:city":"Basel",
    "sg:orig_category":"Gymnastikschulen",
    "sg:phone":"+41 61 261 68 17",
    "sg:postcode":"4051",
    "sg:province":"Basel-Stadt",
    "wof:name":"Sibylle Ossendorf Gymnastikstudio Faesch",
    "wof:placetype":"venue"
},
  "geometry": {"coordinates":[7.5825281143,47.555721283],"type":"Point"}
}