{
  "type": "Feature",
  "properties": {
    "iso:country":"CH",
    "sg:address":"Hauptstrasse",
    "sg:city":"Rohrbach",
    "sg:orig_category":"RESTAURANTS: TEA-ROOMS",
    "sg:postcode":"4938",
    "sg:province":"Bern",
    "wof:name":"Herrmann Walter",
    "wof:placetype":"venue"
},
  "geometry": {"coordinates":[7.8223772049,47.130405426],"type":"Point"}
}