{
  "type": "Feature",
  "properties": {
    "iso:country":"CH",
    "sg:address":"Steinenstrasse 14",
    "sg:city":"Sachseln",
    "sg:orig_category":"Maler U Glasergewerbe Malerei",
    "sg:postcode":"6072",
    "sg:province":"Obwalden",
    "wof:name":"Erwin R\u00f6thlin Kundenmalerei",
    "wof:placetype":"venue"
},
  "geometry": {"coordinates":[8.2384653091,46.8657531738],"type":"Point"}
}