{
  "type": "Feature",
  "properties": {
    "iso:country":"CH",
    "sg:address":"J.c. Rosenburger-strasse 8",
    "sg:city":"M\u00fcnchenstein",
    "sg:orig_category":"Sonstige mit der Informatik verbundene T\u00e4tigkeiten",
    "sg:postcode":"4142",
    "sg:province":"Basel-Landschaft",
    "wof:name":"Multi Consulting, Patrizia Egli-montani",
    "wof:placetype":"venue"
},
  "geometry": {"coordinates":[8.4065322876,47.4446983337],"type":"Point"}
}