{
  "type": "Feature",
  "properties": {
    "addr:full":"Lagerstrasse 55 Z\u00fcrich Z\u00fcrich 8090",
    "addr:housenumber":"55",
    "addr:postcode":"8090",
    "addr:street":"Lagerstrasse",
    "iso:country":"CH",
    "sg:address":"Lagerstrasse 55",
    "sg:city":"Z\u00fcrich",
    "sg:orig_category":"Berufsbildende weiterf\u00fchrende Schulen",
    "sg:phone":"+41 31 331 14 73",
    "sg:postcode":"8090",
    "sg:province":"Z\u00fcrich",
    "wof:name":"Baumeisterverband Bern Az Maurer-lehrhalle Bern",
    "wof:placetype":"venue"
},
  "geometry": {"coordinates":[7.443938,46.954929],"type":"Point"}
}