{
  "type": "Feature",
  "properties": {
    "iso:country":"CH",
    "sg:address":"Sandackerstrasse 7",
    "sg:city":"Oberb\u00fcren",
    "sg:orig_category":"Vorschulen, Kinderg\u00e4rten",
    "sg:phone":"+41 71 951 78 07",
    "sg:postcode":"9245",
    "sg:province":"St. Gallen",
    "wof:name":"Kindergarten Schlossgarten",
    "wof:placetype":"venue"
},
  "geometry": {"coordinates":[9.1577596664,47.4517097473],"type":"Point"}
}