{
  "type": "Feature",
  "properties": {
    "iso:country":"CH",
    "sg:address":"Wilerstrasse 1",
    "sg:city":"Eglisau",
    "sg:orig_category":"Vereine Literarische and Lese",
    "sg:phone":"+41 18673315",
    "sg:postcode":"8193",
    "sg:province":"Z\u00fcrich",
    "wof:name":"Lesegesellschaft Eglisau",
    "wof:placetype":"venue"
},
  "geometry": {"coordinates":[8.5291004181,47.5770606995],"type":"Point"}
}