{
  "type": "Feature",
  "properties": {
    "iso:country":"CH",
    "sg:address":"Route Cantonale",
    "sg:city":"Avry-devant-pont",
    "sg:orig_category":"Grosshandel mit Wasch U Reinigungsmitteln HOTELS: MIT RESTAURANT",
    "sg:phone":"+41 26 915 34 39",
    "sg:postcode":"1644",
    "sg:province":"Fribourg",
    "wof:name":"Soci\u00e9t\u00e9 Seydoux Olivier S\u00e0rl",
    "wof:placetype":"venue"
},
  "geometry": {"coordinates":[7.086250782,46.6852798462],"type":"Point"}
}