{
  "type": "Feature",
  "properties": {
    "iso:country":"CH",
    "sg:address":"Les Grandes-planches 7",
    "sg:city":"Geneveys-coffrane",
    "sg:orig_category":"Vermittlung von Immobilien Verwaltung von Immobilien",
    "sg:phone":"+41 32 857 16 92",
    "sg:postcode":"2206",
    "sg:province":"Neuch\u00e2tel",
    "wof:name":"Ray Fiduciaire & R\u00e9visions Sa",
    "wof:placetype":"venue"
},
  "geometry": {"coordinates":[6.8459448814,47.0122261047],"type":"Point"}
}