{
  "type": "Feature",
  "properties": {
    "iso:country":"CH",
    "sg:address":"Saurenbachstrasse 51",
    "sg:city":"M\u00e4nnedorf",
    "sg:orig_category":"RESTAURANTS: TEA-ROOMS",
    "sg:postcode":"8708",
    "sg:province":"Z\u00fcrich",
    "wof:name":"Rawe Gastro Gmbh",
    "wof:placetype":"venue"
},
  "geometry": {"coordinates":[8.7000989914,47.252696991],"type":"Point"}
}