{
  "type": "Feature",
  "properties": {
    "iso:country":"CH",
    "sg:address":"Nobsstrasse 5",
    "sg:city":"Ostermundigen",
    "sg:orig_category":"Sonstiger Grosshandel",
    "sg:phone":"+41 31 931 68 89",
    "sg:postcode":"3072",
    "sg:province":"Bern",
    "wof:name":"Lanka Shan Enterprise Shanmugalingam Sasikala",
    "wof:placetype":"venue"
},
  "geometry": {"coordinates":[7.4933099747,46.9592247009],"type":"Point"}
}