{
  "type": "Feature",
  "properties": {
    "iso:country":"CH",
    "sg:address":"Klein-schoenberg 49",
    "sg:city":"Fribourg",
    "sg:orig_category":"Malerei Stukkateurgewerbe, Gipserei U Verputzerei",
    "sg:phone":"+41 26 481 29 61",
    "sg:postcode":"1700",
    "sg:province":"Fribourg",
    "wof:name":"Piero Calasso Pl\u00e2trerie-peinture",
    "wof:placetype":"venue"
},
  "geometry": {"coordinates":[7.1820988655,46.8050727844],"type":"Point"}
}