{
  "type": "Feature",
  "properties": {
    "iso:country":"CH",
    "sg:address":"Route De La P\u00e2le 14",
    "sg:city":"Denges",
    "sg:orig_category":"Fotografische Laboratorien",
    "sg:phone":"+41 21 804 60 20",
    "sg:postcode":"1026",
    "sg:province":"Vaud",
    "wof:name":"Kodak Sa Centre De Distribution",
    "wof:placetype":"venue"
},
  "geometry": {"coordinates":[6.5417881012,46.5184669495],"type":"Point"}
}