{
  "type": "Feature",
  "properties": {
    "iso:country":"CH",
    "sg:address":"Tiergarten 11 8000 Z\u00fcrich. Postfach",
    "sg:city":"Z\u00fcrich",
    "sg:orig_category":"Wirtschaftspr\u00fcfung, Steuerberatung U Treuhand",
    "sg:postcode":"8055",
    "sg:province":"Z\u00fcrich",
    "wof:name":"Meier Martin Treuhand",
    "wof:placetype":"venue"
},
  "geometry": {"coordinates":[8.512597084,47.3665351868],"type":"Point"}
}