{
  "type": "Feature",
  "properties": {
    "iso:country":"CH",
    "sg:address":"Hefenhoferstrasse 7",
    "sg:city":"Sommeri",
    "sg:classifiers":[
        {
            "category":"Home & Garden",
            "subcategory":"Building Materials",
            "type":"Retail Goods"
        }
    ],
    "sg:phone":"+41 71 411 16 87",
    "sg:postcode":"8580",
    "sg:province":"Thurgau",
    "sg:tags":[
        "steel",
        "metal",
        "made",
        "door",
        "gate"
    ],
    "wof:name":"Schneggenburger Gmbh",
    "wof:placetype":"venue"
},
  "geometry": {"coordinates":[9.292016983,47.5662193298],"type":"Point"}
}