{
  "type": "Feature",
  "properties": {
    "iso:country":"CH",
    "sg:address":"Seestrasse 25",
    "sg:city":"Z\u00fcrich",
    "sg:orig_category":"Detailhandel mit fotografischen Artikeln Fotografische Ateliers",
    "sg:phone":"+41 56 664 19 44",
    "sg:postcode":"8002",
    "sg:province":"Z\u00fcrich",
    "wof:name":"Foto Studio Gioia Fotostudio, Fotoartikelverkauf",
    "wof:placetype":"venue"
},
  "geometry": {"coordinates":[8.3174819946,47.2825775146],"type":"Point"}
}