{
  "type": "Feature",
  "properties": {
    "iso:country":"CH",
    "sg:address":"Kirch 14",
    "sg:city":"Bleiken",
    "sg:orig_category":"Sportvereine Behindertensport",
    "sg:phone":"+41 31 771 22 12",
    "sg:postcode":"3674",
    "sg:province":"Bern",
    "wof:name":"Svbs Bern Rc",
    "wof:placetype":"venue"
},
  "geometry": {"coordinates":[7.6455440521,46.8145027161],"type":"Point"}
}