{
  "type": "Feature",
  "properties": {
    "iso:country":"CH",
    "sg:address":"Faubourg Du Lac 22 2500 Biel/bienne. Postfach",
    "sg:city":"Biel/bienne",
    "sg:orig_category":"RESTAURANTS: TEA-ROOMS",
    "sg:phone":"+41 32 322 37 75",
    "sg:postcode":"2502",
    "sg:province":"Bern",
    "wof:name":"Coderey Esther & Patrick",
    "wof:placetype":"venue"
},
  "geometry": {"coordinates":[7.2382102013,47.1371040344],"type":"Point"}
}