{
  "type": "Feature",
  "properties": {
    "iso:country":"CH",
    "sg:address":"Lindenstrasse 159",
    "sg:city":"St.gallen",
    "sg:orig_category":"Herstellung von Heizk\u00f6rpern U kesseln f\u00fcr die Zentralheizung Sanit\u00e4r, Heizungs U L\u00fcftungsinstallatio",
    "sg:phone":"+41 71 288 26 10",
    "sg:postcode":"9000",
    "sg:province":"St. Gallen",
    "wof:name":"M\u00fcller Oelbrenner-service",
    "wof:placetype":"venue"
},
  "geometry": {"coordinates":[9.398399353,47.4349441528],"type":"Point"}
}