{
  "type": "Feature",
  "properties": {
    "iso:country":"CH",
    "sg:address":"Zelgstr. 1",
    "sg:city":"Kreuzlingen",
    "sg:classifiers":[
        {
            "category":"Professional",
            "subcategory":"Printing & Photocopies",
            "type":"Services"
        }
    ],
    "sg:phone":"+41 32 365 53 30",
    "sg:postcode":"8280",
    "sg:province":"Thurgau",
    "sg:tags":[
        "publishing"
    ],
    "wof:name":"Brm Design Sa",
    "wof:placetype":"venue"
},
  "geometry": {"coordinates":[7.265137,47.121002],"type":"Point"}
}