{
  "type": "Feature",
  "properties": {
    "iso:country":"CH",
    "sg:address":"B\u00fcntelistr. 15",
    "sg:city":"Widnau",
    "sg:classifiers":[
        {
            "category":"Professional",
            "subcategory":"Business Services",
            "type":"Services"
        }
    ],
    "sg:phone":"+41 71 727 81 11",
    "sg:postcode":"9443",
    "sg:province":"St. Gallen",
    "sg:tags":[
        "servi",
        "rubber",
        "advice",
        "material",
        "-",
        "plastic",
        "packaging",
        "transport"
    ],
    "wof:name":"Plaston Ag",
    "wof:placetype":"venue"
},
  "geometry": {"coordinates":[9.647485,47.405056],"type":"Point"}
}