{
  "type": "Feature",
  "properties": {
    "iso:country":"CH",
    "sg:address":"Grand'rue 6",
    "sg:city":"Couvet",
    "sg:orig_category":"Herstellung von Duft U K\u00f6rperpflegemitteln",
    "sg:postcode":"2108",
    "sg:province":"Neuch\u00e2tel",
    "wof:name":"Bio-conseils, V. Merlotti",
    "wof:placetype":"venue"
},
  "geometry": {"coordinates":[6.6306781769,46.9261779785],"type":"Point"}
}