{
  "type": "Feature",
  "properties": {
    "iso:country":"CH",
    "sg:address":"Kanalstrasse 23",
    "sg:city":"Glattbrugg",
    "sg:orig_category":"Autotransporte international",
    "sg:phone":"+41 18094343",
    "sg:postcode":"8152",
    "sg:province":"Z\u00fcrich",
    "wof:name":"Dachser Spedition Ag",
    "wof:placetype":"venue"
},
  "geometry": {"coordinates":[8.57401,47.429298],"type":"Point"}
}