{
  "type": "Feature",
  "properties": {
    "iso:country":"CH",
    "sg:address":"Kempttalstrasse 31",
    "sg:city":"Illnau",
    "sg:orig_category":"Detailhandel mit Fahrr\u00e4dern Handel mit Motorr\u00e4dern, Teilen U Zubeh\u00f6r Instandhaltung U Reparatur von ",
    "sg:phone":"+41 55 283 16 07",
    "sg:postcode":"8308",
    "sg:province":"Z\u00fcrich",
    "wof:name":"Werner Kamer Velos-motos",
    "wof:placetype":"venue"
},
  "geometry": {"coordinates":[9.0054197311,47.19764328],"type":"Point"}
}