{
  "type": "Feature",
  "properties": {
    "iso:country":"CH",
    "sg:address":"Fontnas 9478 Azmoos. Postfach",
    "sg:city":"Weite",
    "sg:orig_category":"Sonstige mit der Informatik verbundene T\u00e4tigkeiten",
    "sg:postcode":"9476",
    "sg:province":"St. Gallen",
    "wof:name":"Ebs Edv-beratung Schol",
    "wof:placetype":"venue"
},
  "geometry": {"coordinates":[9.4766893387,47.0802955627],"type":"Point"}
}