{
  "type": "Feature",
  "properties": {
    "iso:country":"CH",
    "sg:address":"Tulpenweg 17",
    "sg:city":"Madiswil",
    "sg:orig_category":"Markt U Meinungsforschung",
    "sg:postcode":"4934",
    "sg:province":"Bern",
    "wof:name":"Masgo, Marketing-services & Sales, Gomez",
    "wof:placetype":"venue"
},
  "geometry": {"coordinates":[7.800951004,47.1709899902],"type":"Point"}
}