{
  "type": "Feature",
  "properties": {
    "iso:country":"CH",
    "sg:address":"R. De La Boverie 36 Case Postale 429",
    "sg:city":"Payerne",
    "sg:classifiers":[
        {
            "category":"Shopping",
            "subcategory":"Gifts & Souvenirs",
            "type":"Retail Goods"
        }
    ],
    "sg:phone":"+41 26 662 43 21",
    "sg:postcode":"1530",
    "sg:province":"Vaud",
    "sg:tags":[
        "product",
        "miscellaneous"
    ],
    "wof:name":"Fermenta Sa",
    "wof:placetype":"venue"
},
  "geometry": {"coordinates":[6.0272297859,46.2078781128],"type":"Point"}
}