{
  "type": "Feature",
  "properties": {
    "iso:country":"CH",
    "sg:address":"Schleifetobelweg 6 8810 Horgen. Postfach",
    "sg:city":"Horgen",
    "sg:orig_category":"Fotografische Ateliers Fotografisches Gewerbe U fotografische Laboratorien",
    "sg:phone":"+41 17254879",
    "sg:postcode":"8812",
    "sg:province":"Z\u00fcrich",
    "wof:name":"Microphot - Sch\u00fcpbach Peter Wissenschaftliche Fotografien",
    "wof:placetype":"venue"
},
  "geometry": {"coordinates":[8.596988678,47.2568893433],"type":"Point"}
}