{
  "type": "Feature",
  "properties": {
    "iso:country":"CH",
    "sg:address":"Pilatusstrasse 53",
    "sg:city":"Luzern",
    "sg:orig_category":"RESTAURANTS: TEA-ROOMS",
    "sg:phone":"+41 81 413 09 92",
    "sg:postcode":"6003",
    "sg:province":"Luzern",
    "wof:name":"Parasole Vincenzo",
    "wof:placetype":"venue"
},
  "geometry": {"coordinates":[9.8297605515,46.8014640808],"type":"Point"}
}