{
  "type": "Feature",
  "properties": {
    "iso:country":"CH",
    "sg:address":"6216",
    "sg:city":"Mauensee",
    "sg:orig_category":"Landesverteidigung, Sozialversicherung \u00d6ffentliche Verwaltung",
    "sg:phone":"+41 41 921 14 84",
    "sg:postcode":"6216",
    "sg:province":"Luzern",
    "wof:name":"Zivilschutzstelle Mauensee",
    "wof:placetype":"venue"
},
  "geometry": {"coordinates":[8.0768995285,47.1682395935],"type":"Point"}
}