{
  "type": "Feature",
  "properties": {
    "iso:country":"CH",
    "sg:address":"H\u00f6heweg 92",
    "sg:city":"Interlaken",
    "sg:classifiers":[
        {
            "category":"Bars & Pubs",
            "type":"Food & Drink"
        }
    ],
    "sg:phone":"+41 33 823 09 66",
    "sg:postcode":"3800",
    "sg:province":"Bern",
    "sg:tags":[
        "restaurant"
    ],
    "wof:name":"Restaurant & Bar Chez Pierre's",
    "wof:placetype":"venue"
},
  "geometry": {"coordinates":[7.865743,46.689514],"type":"Point"}
}