{
  "type": "Feature",
  "properties": {
    "addr:full":"Hauelen 88a Gondiswil Bern 4955",
    "addr:housenumber":"88a",
    "addr:postcode":"4955",
    "addr:street":"Hauelen",
    "iso:country":"CH",
    "sg:address":"Hauelen 88a",
    "sg:city":"Gondiswil",
    "sg:orig_category":"Autogaragen",
    "sg:phone":"+41 79 434 43 67",
    "sg:postcode":"4955",
    "sg:province":"Bern",
    "wof:name":"Garage Alternativ Auto",
    "wof:placetype":"venue"
},
  "geometry": {"coordinates":[7.866454,47.146019],"type":"Point"}
}