{
  "type": "Feature",
  "properties": {
    "iso:country":"CH",
    "sg:address":"Schachenhof 4 6014 Littau. Postfach 6014",
    "sg:city":"Littau",
    "sg:orig_category":"Herstellung von Metallerzeugnissen ohne Maschinenbau Herstellung von sonstigen Metallwaren",
    "sg:phone":"+41 56 297 10 30",
    "sg:postcode":"6014",
    "sg:province":"Luzern",
    "wof:name":"Merki + Hitz Ag Metallwarenfabrik",
    "wof:placetype":"venue"
},
  "geometry": {"coordinates":[8.2409944534,47.5221748352],"type":"Point"}
}