{
  "type": "Feature",
  "properties": {
    "iso:country":"CH",
    "sg:address":"1138",
    "sg:city":"Villars-sous-yens",
    "sg:orig_category":"Schulpflegen",
    "sg:postcode":"1138",
    "wof:name":"Commission Scolaire De L'ecole Secondaire",
    "wof:placetype":"venue"
},
  "geometry": {"coordinates":[6.4161701202,46.5183753967],"type":"Point"}
}