{
  "type": "Feature",
  "properties": {
    "iso:country":"CH",
    "sg:address":"Heidwiesen 14",
    "sg:city":"Z\u00fcrich",
    "sg:orig_category":"Sonstige pers\u00f6nliche Dienstleistungen",
    "sg:postcode":"8051",
    "sg:province":"Z\u00fcrich",
    "wof:name":"Sg Service Gestion Michel Gross",
    "wof:placetype":"venue"
},
  "geometry": {"coordinates":[7.5153589249,46.0982971191],"type":"Point"}
}