{
  "type": "Feature",
  "properties": {
    "iso:country":"CH",
    "sg:address":"Habsburgerstrasse 33",
    "sg:city":"Luzern",
    "sg:orig_category":"Non-Classified Establishments",
    "sg:postcode":"6003",
    "sg:province":"Luzern",
    "wof:name":"Boutique Rif, A. + P. Bikti",
    "wof:placetype":"venue"
},
  "geometry": {"coordinates":[9.0477733612,47.4662628174],"type":"Point"}
}