{
  "type": "Feature",
  "properties": {
    "addr:full":"Zentralstrasse 30 Boswil Aargau 5623",
    "addr:housenumber":"30",
    "addr:postcode":"5623",
    "addr:street":"Zentralstrasse",
    "iso:country":"CH",
    "sg:address":"Zentralstrasse 30",
    "sg:city":"Boswil",
    "sg:orig_category":"Detailhandel mit Brot, Back U S\u00fcsswaren Detailhandel mit Waren verschiedener Art, Hauptrichtung Nahr",
    "sg:phone":"+41 56 666 14 34",
    "sg:postcode":"5623",
    "sg:province":"Aargau",
    "wof:name":"Werner Hilfiker B\u00e4ckerei & Lebensmittel",
    "wof:placetype":"venue"
},
  "geometry": {"coordinates":[8.314149,47.299603],"type":"Point"}
}