{
  "type": "Feature",
  "properties": {
    "iso:country":"CH",
    "sg:address":"Feldbergstrasse 113 4057 Basel. Postfach",
    "sg:city":"Basel",
    "sg:orig_category":"Flachsaufbereitung U spinnerei",
    "sg:phone":"+41 61 683 56 86",
    "sg:postcode":"4051",
    "sg:province":"Basel-Stadt",
    "wof:name":"Futureworld Gmbh Waren, Bes. Hanfprodukte, Musikinstrumente, Tontr\u00e4ger; Handel Usw",
    "wof:placetype":"venue"
},
  "geometry": {"coordinates":[7.5952892303,47.5671539307],"type":"Point"}
}