{
  "type": "Feature",
  "properties": {
    "iso:country":"CH",
    "sg:address":"Via Maistra",
    "sg:city":"S-chanf",
    "sg:classifiers":[
        {
            "category":"Travel",
            "subcategory":"Hotels & Motels",
            "type":"Entertainment"
        }
    ],
    "sg:phone":"+41 81 854 12 64",
    "sg:postcode":"7525",
    "sg:province":"Graubunden",
    "sg:tags":[
        "hotels",
        "mit",
        "restaurant"
    ],
    "wof:name":"Langen-zingre Dora.",
    "wof:placetype":"venue"
},
  "geometry": {"coordinates":[9.9836778641,46.6118049622],"type":"Point"}
}