{
  "type": "Feature",
  "properties": {
    "iso:country":"CH",
    "sg:address":"Rue Des Foss\u00e9s 4",
    "sg:city":"Morges",
    "sg:orig_category":"Detailhandel mit Damenbekleidung",
    "sg:phone":"+41 21 803 00 32",
    "sg:postcode":"1110",
    "sg:province":"Vaud",
    "wof:name":"Kurer Modes Confection Pour Dames",
    "wof:placetype":"venue"
},
  "geometry": {"coordinates":[6.4981689453,46.5106239319],"type":"Point"}
}