{
  "type": "Feature",
  "properties": {
    "iso:country":"CH",
    "sg:address":"Rue De La Place 4",
    "sg:city":"Chippis",
    "sg:orig_category":"Non-Classified Establishments",
    "sg:postcode":"3965",
    "sg:province":"Valais",
    "wof:name":"Z.e.p. S\u00e0rl",
    "wof:placetype":"venue"
},
  "geometry": {"coordinates":[7.5422539711,46.27942276],"type":"Point"}
}