{
  "type": "Feature",
  "properties": {
    "addr:full":"Hofstrasse 31 4127 Birsfelden. Postfach Birsfelden Basel-Landschaft 4127",
    "addr:housenumber":"31",
    "addr:postcode":"4127 birsfelden. postfach;4127",
    "addr:street":"Hofstrasse",
    "iso:country":"CH",
    "sg:address":"Hofstrasse 31 4127 Birsfelden. Postfach",
    "sg:city":"Birsfelden",
    "sg:orig_category":"Architektur U Ingenieurb\u00fcros Architekturb\u00fcros",
    "sg:phone":"+41 61 313 66 10",
    "sg:postcode":"4127",
    "sg:province":"Basel-Landschaft",
    "wof:name":"Gs Architekten Ag",
    "wof:placetype":"venue"
},
  "geometry": {"coordinates":[7.626254,47.557236],"type":"Point"}
}