{
  "type": "Feature",
  "properties": {
    "iso:country":"CH",
    "sg:address":"Industriestrasse 24",
    "sg:city":"Kronb\u00fchl",
    "sg:orig_category":"Wirtschaftspr\u00fcfung, Steuerberatung U Treuhand",
    "sg:phone":"+41 71 298 20 73",
    "sg:postcode":"9302",
    "wof:name":"Keller H. Revision Und Treuhand Ag",
    "wof:placetype":"venue"
},
  "geometry": {"coordinates":[9.394865036,47.4597816467],"type":"Point"}
}