{
  "type": "Feature",
  "properties": {
    "iso:country":"CH",
    "sg:address":"Winkelweg 8 8124 Maur. Postfach",
    "sg:city":"Forch",
    "sg:orig_category":"Erschliessung von Grundst\u00fccken",
    "sg:postcode":"8127",
    "sg:province":"Z\u00fcrich",
    "wof:name":"Wohngenossenschaft Juventus Aesch-maur",
    "wof:placetype":"venue"
},
  "geometry": {"coordinates":[8.655254364,47.3320274353],"type":"Point"}
}