{
  "type": "Feature",
  "properties": {
    "addr:full":"Hauptstrasse 7 D\u00f6ttingen Aargau 5312",
    "addr:housenumber":"7",
    "addr:postcode":"5312",
    "addr:street":"Hauptstrasse",
    "iso:country":"CH",
    "sg:address":"Hauptstrasse 7",
    "sg:city":"D\u00f6ttingen",
    "sg:orig_category":"Bauingenieurb\u00fcros Tiefbau Bauingenieurb\u00fcros allgemein",
    "sg:phone":"+41 56 245 66 65",
    "sg:postcode":"5312",
    "sg:province":"Aargau",
    "wof:name":"Ingenieurb\u00fcro Senn Planung & Tiefbau",
    "wof:placetype":"venue"
},
  "geometry": {"coordinates":[8.255564,47.576599],"type":"Point"}
}