{
  "type": "Feature",
  "properties": {
    "iso:country":"CH",
    "sg:address":"Luegislandstrasse 245",
    "sg:city":"Z\u00fcrich",
    "sg:orig_category":"Herstellung von Konstruktionsteilen, Fertigbauteilen U Ausbauelementen aus Holz",
    "sg:postcode":"8051",
    "sg:province":"Z\u00fcrich",
    "wof:name":"Inbau & Plan, Noger Marcel",
    "wof:placetype":"venue"
},
  "geometry": {"coordinates":[8.5736436844,47.4094085693],"type":"Point"}
}