{
  "type": "Feature",
  "properties": {
    "iso:country":"CH",
    "sg:address":"Route De Saint-julien 263",
    "sg:city":"Perly",
    "sg:orig_category":"Physiotherapie",
    "sg:phone":"+41 22 771 10 20",
    "sg:postcode":"1258",
    "sg:province":"Gen\u00e8ve",
    "wof:name":"Physioth\u00e9rapie Perly",
    "wof:placetype":"venue"
},
  "geometry": {"coordinates":[6.0974888802,46.1569862366],"type":"Point"}
}