{
  "type": "Feature",
  "properties": {
    "iso:country":"CH",
    "sg:city":"Niederhasli",
    "sg:orig_category":"Internet, Webseiten U -systeme",
    "sg:postcode":"8155",
    "sg:province":"Z\u00fcrich",
    "wof:name":"Cybergate Corporation",
    "wof:placetype":"venue"
},
  "geometry": {"coordinates":[8.483948,47.481236],"type":"Point"}
}