{
  "type": "Feature",
  "properties": {
    "addr:full":"Niederhasli Z\u00fcrich 8155",
    "addr:postcode":"8155",
    "iso:country":"CH",
    "sg:city":"Niederhasli",
    "sg:orig_category":"Internet, Webseiten U -systeme",
    "sg:postcode":"8155",
    "sg:province":"Z\u00fcrich",
    "wof:name":"Cybergate Corporation",
    "wof:placetype":"venue"
},
  "geometry": {"coordinates":[8.483948,47.481236],"type":"Point"}
}