{
  "type": "Feature",
  "properties": {
    "iso:country":"CH",
    "sg:address":"Milit\u00e4rstrasse 6",
    "sg:city":"Thun",
    "sg:orig_category":"Erbringung von sonstigen Dienstleistungen f\u00fcr Unternehmen",
    "sg:phone":"+41 33 221 50 88",
    "sg:postcode":"3600",
    "sg:province":"Bern",
    "wof:name":"Dellsperger Rolf Bauberatungen",
    "wof:placetype":"venue"
},
  "geometry": {"coordinates":[7.6161141396,46.7567672729],"type":"Point"}
}