{
  "type": "Feature",
  "properties": {
    "iso:country":"CH",
    "sg:address":"Wangenstrasse 10",
    "sg:city":"Herzogenbuchsee",
    "sg:orig_category":"Physiotherapie",
    "sg:phone":"+41 62 961 57 28",
    "sg:postcode":"3360",
    "sg:province":"Bern",
    "wof:name":"Bruno Misteli Physiotherapie",
    "wof:placetype":"venue"
},
  "geometry": {"coordinates":[7.705892086,47.1885414124],"type":"Point"}
}