{
  "type": "Feature",
  "properties": {
    "iso:country":"CH",
    "sg:address":"Rheinweg 7",
    "sg:city":"Schaffhausen",
    "sg:orig_category":"Grosshandel mit Holz U Baustoffen Herstellung von Erzeugnissen aus Beton, Gips U Zement",
    "sg:phone":"+41 52 624 81 00",
    "sg:postcode":"8200",
    "sg:province":"Schaffhausen",
    "wof:name":"Inba Innovative Bauprodukte Ag",
    "wof:placetype":"venue"
},
  "geometry": {"coordinates":[8.6349506378,47.6937446594],"type":"Point"}
}