{
  "type": "Feature",
  "properties": {
    "addr:full":"Bellariarain 12 Z\u00fcrich Z\u00fcrich 8038",
    "addr:housenumber":"12",
    "addr:postcode":"8038",
    "addr:street":"Bellariarain",
    "iso:country":"CH",
    "sg:address":"Bellariarain 12",
    "sg:city":"Z\u00fcrich",
    "sg:classifiers":[
        {
            "category":"Shopping",
            "subcategory":"Books",
            "type":"Retail Goods"
        }
    ],
    "sg:phone":"+41 14823026",
    "sg:postcode":"8038",
    "sg:province":"Z\u00fcrich",
    "wof:name":"Sistabooks Gmbh",
    "wof:placetype":"venue"
},
  "geometry": {"coordinates":[8.530818,47.349098],"type":"Point"}
}