{
  "type": "Feature",
  "properties": {
    "iso:country":"CH",
    "sg:address":"3979",
    "sg:city":"Gr\u00f4ne",
    "sg:orig_category":"Unclassifiable Establishments",
    "sg:phone":"+41 19374289",
    "sg:postcode":"3979",
    "sg:province":"Valais",
    "wof:name":"Zimmermann Finanz Holding Ag",
    "wof:placetype":"venue"
},
  "geometry": {"coordinates":[8.841173172,47.2980041504],"type":"Point"}
}