{
  "type": "Feature",
  "properties": {
    "iso:country":"CH",
    "sg:address":"7605",
    "sg:city":"Stampa",
    "sg:orig_category":"Sonstige mit Sport verbundene T\u00e4tigkeiten",
    "sg:phone":"+41 32 863 15 55",
    "sg:postcode":"7605",
    "sg:province":"Graubunden",
    "wof:name":"Aero-club Du Val-de-travers",
    "wof:placetype":"venue"
},
  "geometry": {"coordinates":[6.6211700439,46.9019889832],"type":"Point"}
}