{
  "type": "Feature",
  "properties": {
    "iso:country":"CH",
    "sg:address":"3715 Adelboden. Postfach 118",
    "sg:city":"Adelboden",
    "sg:classifiers":[
        {
            "category":"Travel",
            "subcategory":"Hotels & Motels",
            "type":"Entertainment"
        }
    ],
    "sg:phone":"+41 33 673 22 91",
    "sg:postcode":"3715",
    "sg:province":"Bern",
    "sg:tags":[
        "hotels",
        "mit",
        "restaurant"
    ],
    "wof:name":"Berghotel Engstligenalp",
    "wof:placetype":"venue"
},
  "geometry": {"coordinates":[7.5602669716,46.4932365417],"type":"Point"}
}