{
  "type": "Feature",
  "properties": {
    "iso:country":"CH",
    "sg:address":"Via Cantoni 8",
    "sg:city":"Chiasso",
    "sg:orig_category":"Malerei",
    "sg:phone":"+41 79 444 11 56",
    "sg:postcode":"6830",
    "sg:province":"Ticino",
    "wof:name":"Furio Bortolomiol Impresa Colorado",
    "wof:placetype":"venue"
},
  "geometry": {"coordinates":[9.0328330994,45.8348960876],"type":"Point"}
}