{
  "type": "Feature",
  "properties": {
    "iso:country":"CH",
    "sg:address":"Neuhofstrasse 91",
    "sg:city":"Romanshorn",
    "sg:orig_category":"Herstellung von sonstigen Maschinen f\u00fcr bestimmte Verwendung",
    "sg:phone":"+41 71 463 59 75",
    "sg:postcode":"8590",
    "sg:province":"Thurgau",
    "wof:name":"Theodor Von B\u00fcren, Handel Mit Techn. Produkten",
    "wof:placetype":"venue"
},
  "geometry": {"coordinates":[9.371547699,47.559425354],"type":"Point"}
}