{
  "type": "Feature",
  "properties": {
    "iso:country":"CH",
    "sg:address":"Chemin De La Perche 20a",
    "sg:city":"Porrentruy",
    "sg:orig_category":"Herstellung von Teppichen Verlegen von Fliesen U Platten",
    "sg:phone":"+41 32 466 33 48",
    "sg:postcode":"2900",
    "sg:province":"Jura",
    "wof:name":"Biedermann Carrelages Sa",
    "wof:placetype":"venue"
},
  "geometry": {"coordinates":[7.0820469856,47.4140853882],"type":"Point"}
}