{
  "type": "Feature",
  "properties": {
    "iso:country":"CH",
    "sg:address":"Sporrengasse 6 8200 Schaffhausen. Postfach",
    "sg:city":"Schaffhausen",
    "sg:orig_category":"Detailhandel mit Spielwaren Fachdetailhandel in Verkaufsr\u00e4umen",
    "sg:phone":"+41 62 822 35 50",
    "sg:postcode":"8201",
    "sg:province":"Schaffhausen",
    "wof:name":"Bieri Spielwaren",
    "wof:placetype":"venue"
},
  "geometry": {"coordinates":[8.0693798065,47.3904380798],"type":"Point"}
}