{
  "type": "Feature",
  "properties": {
    "iso:country":"CH",
    "sg:address":"Wettingerstrasse 29",
    "sg:city":"Baden",
    "sg:orig_category":"Architektur U Ingenieurb\u00fcros",
    "sg:phone":"+41 56 221 62 21",
    "sg:postcode":"5400",
    "sg:province":"Aargau",
    "wof:name":"B\u00e4nziger+bacchetta+fehlmann+partner Ingenieure + Planer Sia Usic",
    "wof:placetype":"venue"
},
  "geometry": {"coordinates":[8.31651,47.470436],"type":"Point"}
}