{
  "type": "Feature",
  "properties": {
    "iso:country":"CH",
    "sg:address":"Route De Chantemerle 58 1763 Granges-paccot Case Postale 30",
    "sg:city":"Granges-paccot",
    "sg:orig_category":"Unclassifiable Establishments",
    "sg:phone":"+41 26 466 45 04",
    "sg:postcode":"1763",
    "sg:province":"Fribourg",
    "wof:name":"Buchheim Communications Sa",
    "wof:placetype":"venue"
},
  "geometry": {"coordinates":[7.140182972,46.820224762],"type":"Point"}
}