{
  "type": "Feature",
  "properties": {
    "iso:country":"CH",
    "sg:address":"Grabenstrasse 35 7000 Chur. Postfach",
    "sg:city":"Chur",
    "sg:orig_category":"Kaufm\u00e4nnische Berufsschulen",
    "sg:phone":"+41 81 252 45 90",
    "sg:postcode":"7002",
    "sg:province":"Graubunden",
    "wof:name":"Kaufm\u00e4nnische Berufsschule",
    "wof:placetype":"venue"
},
  "geometry": {"coordinates":[9.5304956436,46.8494567871],"type":"Point"}
}