{
  "type": "Feature",
  "properties": {
    "iso:country":"CH",
    "sg:address":"Av Du Grand Pr\u00e9",
    "sg:city":"Moudon",
    "sg:classifiers":[
        {
            "category":"Farming",
            "subcategory":"Farm",
            "type":"Manufacturing & Wholesale Goods"
        }
    ],
    "sg:phone":"+41 21 905 06 07",
    "sg:postcode":"1510",
    "sg:province":"Vaud",
    "sg:tags":[
        "horticulture",
        "agriculture",
        "livestock"
    ],
    "wof:name":"Famaco Sa",
    "wof:placetype":"venue"
},
  "geometry": {"coordinates":[6.796468,46.669319],"type":"Point"}
}