{
  "type": "Feature",
  "properties": {
    "iso:country":"CH",
    "sg:address":"Claragraben 38 4058 Basel. Postfach",
    "sg:city":"Basel",
    "sg:orig_category":"Selbst\u00e4ndige bildende K\u00fcnstler",
    "sg:phone":"+41 61 681 23 40",
    "sg:postcode":"4005",
    "sg:province":"Basel-Stadt",
    "wof:name":"Josef Bossart Bildhaueratelier",
    "wof:placetype":"venue"
},
  "geometry": {"coordinates":[7.5967421532,47.5602073669],"type":"Point"}
}