{
  "type": "Feature",
  "properties": {
    "iso:country":"CH",
    "sg:address":"Etangs Route Des Binii",
    "sg:city":"Chandolin-savi\u00e8se",
    "sg:orig_category":"Detailhandel mit B\u00fcchern, Zeitungen, Schreib U Papeteriewaren",
    "sg:postcode":"1965",
    "sg:province":"Valais",
    "wof:name":"Alwa Services & Products, Alfred M. Walder",
    "wof:placetype":"venue"
},
  "geometry": {"coordinates":[7.338539,46.250473],"type":"Point"}
}