{
  "type": "Feature",
  "properties": {
    "iso:country":"CH",
    "sg:address":"Tr\u00fcmlerstrasse 22 3126 Kaufdorf. Postfach",
    "sg:city":"Kaufdorf",
    "sg:orig_category":"Mit dem Versicherungsgewerbe verbundene T\u00e4tigkeiten",
    "sg:phone":"+41 31 802 19 67",
    "sg:postcode":"3126",
    "sg:province":"Bern",
    "wof:name":"Version Versicherungs Service Usta-aeberhard C. Dienstleistungen In Den Bereichen Versicherungen, Krediten, Reisen Usw.",
    "wof:placetype":"venue"
},
  "geometry": {"coordinates":[7.4953050613,46.837436676],"type":"Point"}
}