{
  "type": "Feature",
  "properties": {
    "iso:country":"CH",
    "sg:address":"Hauptstrasse",
    "sg:city":"Conters",
    "sg:orig_category":"Instandhaltung U Reparatur von Automobilen",
    "sg:postcode":"7241",
    "sg:province":"Graubunden",
    "wof:name":"Hartmann Arno",
    "wof:placetype":"venue"
},
  "geometry": {"coordinates":[9.7985095978,46.9016914368],"type":"Point"}
}