{
  "type": "Feature",
  "properties": {
    "iso:country":"CH",
    "sg:address":"W\u00fcrzgrabenstr. 6",
    "sg:city":"Z\u00fcrich",
    "sg:classifiers":[
        {
            "category":"Social Services",
            "subcategory":"Job Training",
            "type":"Services"
        }
    ],
    "sg:phone":"+41 4114315060",
    "sg:postcode":"8048",
    "sg:province":"Z\u00fcrich",
    "sg:tags":[
        "information",
        "peripheral",
        "-",
        "technology",
        "software"
    ],
    "wof:name":"Wht-software Ag",
    "wof:placetype":"venue"
},
  "geometry": {"coordinates":[8.493897438,47.3930435181],"type":"Point"}
}