{
  "type": "Feature",
  "properties": {
    "iso:country":"CH",
    "sg:address":"G\u00fcterstrasse 158 4053 Basel. Postfach",
    "sg:city":"Basel",
    "sg:orig_category":"Fachdetailhandel in Verkaufsr\u00e4umen",
    "sg:postcode":"4051",
    "sg:province":"Basel-Stadt",
    "wof:name":"Kunsthandlung Einrahmungen Jakob",
    "wof:placetype":"venue"
},
  "geometry": {"coordinates":[7.5902338028,47.5443267822],"type":"Point"}
}