{
  "type": "Feature",
  "properties": {
    "iso:country":"CH",
    "sg:address":"Kreuzplatz 9",
    "sg:city":"Z\u00fcrich",
    "sg:classifiers":[
        {
            "category":"Restaurant",
            "type":"Food & Drink"
        }
    ],
    "sg:phone":"+41 12516868",
    "sg:postcode":"8032",
    "sg:province":"Z\u00fcrich",
    "wof:name":"Restaurant Schmiede",
    "wof:placetype":"venue"
},
  "geometry": {"coordinates":[8.5543909073,47.3647994995],"type":"Point"}
}