{
  "type": "Feature",
  "properties": {
    "iso:country":"CH",
    "sg:address":"T\u00f6distrasse 52 8039 Z\u00fcrich. Postfach 1071",
    "sg:city":"Z\u00fcrich",
    "sg:orig_category":"Unternehmensberatung",
    "sg:postcode":"8039",
    "wof:name":"Zmg Zurich Management Group",
    "wof:placetype":"venue"
},
  "geometry": {"coordinates":[8.5335140228,47.3680992126],"type":"Point"}
}