{
  "type": "Feature",
  "properties": {
    "iso:country":"CH",
    "sg:address":"Signalstrasse 25",
    "sg:city":"Rorschach",
    "sg:classifiers":[
        {
            "category":"Restaurant",
            "type":"Food & Drink"
        }
    ],
    "sg:phone":"+41 71 841 31 98",
    "sg:postcode":"9400",
    "sg:province":"St. Gallen",
    "wof:name":"Restaurant Haifisch",
    "wof:placetype":"venue"
},
  "geometry": {"coordinates":[9.4915800095,47.4758644104],"type":"Point"}
}