{
  "type": "Feature",
  "properties": {
    "iso:country":"CH",
    "sg:address":"Clos-belmont 2 1208 Gen\u00e8ve. Postfach",
    "sg:city":"Gen\u00e8ve",
    "sg:orig_category":"Softwareentwicklung U beratung",
    "sg:postcode":"1208",
    "sg:province":"Gen\u00e8ve",
    "wof:name":"Hatt Robert, Informatique-infratect Consultant En Informatique. Conception, R\u00e9alisation Etc",
    "wof:placetype":"venue"
},
  "geometry": {"coordinates":[6.1638140678,46.1996841431],"type":"Point"}
}