{
  "type": "Feature",
  "properties": {
    "iso:country":"CH",
    "sg:address":"Hauptstr. 50 6276 Hohenrain. Postfach",
    "sg:city":"Kleinwangen",
    "sg:orig_category":"Grosshandel mit Kaffee, Tee, Kakao U Gew\u00fcrzen",
    "sg:postcode":"6277",
    "sg:province":"Luzern",
    "wof:name":"Kessler Werner",
    "wof:placetype":"venue"
},
  "geometry": {"coordinates":[8.2958898544,47.1958007812],"type":"Point"}
}