{
  "type": "Feature",
  "properties": {
    "iso:country":"CH",
    "sg:address":"Aegeristrasse 66",
    "sg:city":"Zug",
    "sg:orig_category":"Wirtschaftspr\u00fcfung, Steuerberatung U Treuhand",
    "sg:postcode":"6300",
    "sg:province":"Zug",
    "wof:name":"Deloitte Goldby Pim Gmbh",
    "wof:placetype":"venue"
},
  "geometry": {"coordinates":[8.521774292,47.1679840088],"type":"Point"}
}