{
  "type": "Feature",
  "properties": {
    "iso:country":"CH",
    "sg:address":"Hohlstrasse 694 8048 Z\u00fcrich. Postfach",
    "sg:city":"Z\u00fcrich",
    "sg:orig_category":"Sanit\u00e4r, Heizungs U L\u00fcftungsinstallation",
    "sg:phone":"+41 71 931 11 11",
    "sg:postcode":"8048",
    "sg:province":"Z\u00fcrich",
    "wof:name":"Seiz G. Ag",
    "wof:placetype":"venue"
},
  "geometry": {"coordinates":[9.0369977951,47.4112815857],"type":"Point"}
}