{
  "type": "Feature",
  "properties": {
    "iso:country":"CH",
    "sg:address":"Pictet Avenue Ernest- 15 1203 Gen\u00e8ve. Postfach",
    "sg:city":"Gen\u00e8ve",
    "sg:orig_category":"Zimmerei, Dachdeckerei, Bauspenglerei U Abdichtung",
    "sg:phone":"+41 22 345 92 53",
    "sg:postcode":"1203",
    "sg:province":"Gen\u00e8ve",
    "wof:name":"Joseph Kaufmann",
    "wof:placetype":"venue"
},
  "geometry": {"coordinates":[6.1258068085,46.212020874],"type":"Point"}
}