{
  "type": "Feature",
  "properties": {
    "iso:country":"CH",
    "sg:address":"Vordergasse 63.",
    "sg:city":"Neunkirch",
    "sg:orig_category":"Grosshandel mit Eisenwaren sowie Installationsbedarf f\u00fcr Gas, Wasser U Heizung",
    "sg:postcode":"8213",
    "sg:province":"Schaffhausen",
    "wof:name":"Wildberger Joh., Inhaber Walter F\u00e4h",
    "wof:placetype":"venue"
},
  "geometry": {"coordinates":[8.4991960526,47.690196991],"type":"Point"}
}