{
  "type": "Feature",
  "properties": {
    "iso:country":"CH",
    "sg:address":"5083",
    "sg:city":"Ittenthal",
    "sg:orig_category":"Gemeindeverwaltungen",
    "sg:phone":"+41 62 871 24 59",
    "sg:postcode":"5083",
    "sg:province":"Aargau",
    "wof:name":"Gemeindeverwaltung Ittenthal",
    "wof:placetype":"venue"
},
  "geometry": {"coordinates":[8.0610599518,47.5178413391],"type":"Point"}
}