{
  "type": "Feature",
  "properties": {
    "iso:country":"CH",
    "sg:address":"Chlupfgasse 2 8303 Bassersdorf. Postfach",
    "sg:city":"Bassersdorf",
    "sg:orig_category":"Wirtschaftspr\u00fcfung, Steuerberatung U Treuhand",
    "sg:phone":"+41 18381919",
    "sg:postcode":"8303",
    "sg:province":"Z\u00fcrich",
    "wof:name":"Buff Hugo & Co Treuhand",
    "wof:placetype":"venue"
},
  "geometry": {"coordinates":[8.6238241196,47.4446678162],"type":"Point"}
}