{
  "type": "Feature",
  "properties": {
    "addr:full":"Obergasse 2 Zizers Graubunden 7205",
    "addr:housenumber":"2",
    "addr:postcode":"7205",
    "addr:street":"Obergasse",
    "iso:country":"CH",
    "sg:address":"Obergasse 2",
    "sg:city":"Zizers",
    "sg:orig_category":"Arztpraxen",
    "sg:phone":"+41 81 330 06 66",
    "sg:postcode":"7205",
    "sg:province":"Graubunden",
    "wof:name":"Dr.med.christoph Peng Arzt F.allgemeine Medizin Fmh",
    "wof:placetype":"venue"
},
  "geometry": {"coordinates":[9.566414,46.93502],"type":"Point"}
}