{
  "type": "Feature",
  "properties": {
    "iso:country":"CH",
    "sg:address":"Seftigenstrasse 303",
    "sg:city":"Wabern",
    "sg:orig_category":"Tanzschulen, Tanzlehrer",
    "sg:phone":"+41 31 961 29 83",
    "sg:postcode":"3084",
    "sg:province":"Bern",
    "wof:name":"Hedd Perll-zaugg Bewegungsschule Gr\u00fcnau",
    "wof:placetype":"venue"
},
  "geometry": {"coordinates":[7.4558291435,46.9267883301],"type":"Point"}
}