{
  "type": "Feature",
  "properties": {
    "iso:country":"CH",
    "sg:address":"Brunnenwiesstrasse 2",
    "sg:city":"Wigoltingen",
    "sg:orig_category":"Mechanische Werkst\u00e4tten",
    "sg:phone":"+41 79 358 10 76",
    "sg:postcode":"8556",
    "sg:province":"Thurgau",
    "wof:name":"Gerhard Tr\u00fcb Mechanische Werkstatt",
    "wof:placetype":"venue"
},
  "geometry": {"coordinates":[9.0280151367,47.5975914001],"type":"Point"}
}