{
  "type": "Feature",
  "properties": {
    "iso:country":"CH",
    "sg:address":"Kleinwilstrasse 1a",
    "sg:city":"Horw",
    "sg:orig_category":"Herstellung von keramischen Wand U Bodenfliesen U platten",
    "sg:postcode":"6048",
    "sg:province":"Luzern",
    "wof:name":"Wespi Josef Plattenbel\u00e4ge",
    "wof:placetype":"venue"
},
  "geometry": {"coordinates":[8.1941146851,47.1193084717],"type":"Point"}
}