{
  "type": "Feature",
  "properties": {
    "iso:country":"CH",
    "sg:address":"Schlossackerstrasse 20",
    "sg:city":"Winterthur",
    "sg:classifiers":[
        {
            "category":"Wholesale",
            "subcategory":"Auto Parts",
            "type":"Manufacturing & Wholesale Goods"
        }
    ],
    "sg:phone":"+41 17611760",
    "sg:postcode":"8404",
    "sg:province":"Z\u00fcrich",
    "sg:tags":[
        "automobile",
        "accessory",
        "equipment"
    ],
    "wof:name":"Elmega Ag",
    "wof:placetype":"venue"
},
  "geometry": {"coordinates":[8.439768,47.274265],"type":"Point"}
}