{
  "type": "Feature",
  "properties": {
    "iso:country":"CH",
    "sg:address":"Geissensteinring 12",
    "sg:city":"Luzern",
    "sg:orig_category":"Werbegrafikateliers",
    "sg:phone":"+41 55 210 80 25",
    "sg:postcode":"6005",
    "sg:province":"Luzern",
    "wof:name":"Stefan Imper Grafisches Atelier",
    "wof:placetype":"venue"
},
  "geometry": {"coordinates":[8.8316926956,47.2311439514],"type":"Point"}
}