{
  "type": "Feature",
  "properties": {
    "iso:country":"CH",
    "sg:address":"Wasserwerkgassse 5",
    "sg:city":"Bern",
    "sg:orig_category":"Unclassifiable Establishments",
    "sg:phone":"+41 19531333",
    "sg:postcode":"3011",
    "sg:province":"Bern",
    "wof:name":"Baltec Holding Ag",
    "wof:placetype":"venue"
},
  "geometry": {"coordinates":[8.7804412842,47.3700637817],"type":"Point"}
}