{
  "type": "Feature",
  "properties": {
    "iso:country":"CH",
    "sg:address":"St. Gallerstrasse 18b",
    "sg:city":"Arbon",
    "sg:orig_category":"Physiotherapie",
    "sg:phone":"+41 71 446 22 25",
    "sg:postcode":"9320",
    "sg:province":"Thurgau",
    "wof:name":"Roman Neuber Physiotherapie",
    "wof:placetype":"venue"
},
  "geometry": {"coordinates":[9.430267334,47.5117912292],"type":"Point"}
}