{
  "type": "Feature",
  "properties": {
    "iso:country":"CH",
    "sg:address":"Via Mistroni",
    "sg:city":"Pura",
    "sg:orig_category":"Unclassifiable Establishments",
    "sg:postcode":"6984",
    "sg:province":"Ticino",
    "wof:name":"Martin Strobel Sa",
    "wof:placetype":"venue"
},
  "geometry": {"coordinates":[8.8667440414,45.9771614075],"type":"Point"}
}