{
  "type": "Feature",
  "properties": {
    "iso:country":"CH",
    "sg:address":"Lindenstrasse 16",
    "sg:city":"Th\u00f6rigen",
    "sg:orig_category":"Herstellung von keramischen Wand U Bodenfliesen U platten Verlegen von Fliesen U Platten",
    "sg:phone":"+41 79 332 82 64",
    "sg:postcode":"3367",
    "sg:province":"Bern",
    "wof:name":"Keramische Wand Und Bodenbel\u00e4ge W\u00e4chli",
    "wof:placetype":"venue"
},
  "geometry": {"coordinates":[7.7290811539,47.1706314087],"type":"Point"}
}