{
  "type": "Feature",
  "properties": {
    "iso:country":"CH",
    "sg:address":"Founex Route De 46",
    "sg:city":"Coppet",
    "sg:orig_category":"Grosshandel mit sonstigen Maschinen U Ausr\u00fcstungen f\u00fcr Industrie, Handel U Schiffahrt",
    "sg:phone":"+41 22 960 03 80",
    "sg:postcode":"1296",
    "sg:province":"Vaud",
    "wof:name":"Famas Technology S\u00e0rl",
    "wof:placetype":"venue"
},
  "geometry": {"coordinates":[6.1932439804,46.3162384033],"type":"Point"}
}