{
  "type": "Feature",
  "properties": {
    "iso:country":"CH",
    "sg:address":"Rainacker 5",
    "sg:city":"Obererlinsbach",
    "sg:orig_category":"Grosshandel mit H\u00e4uten, Fellen U Leder",
    "sg:phone":"+41 62 844 10 18",
    "sg:postcode":"5016",
    "wof:name":"Werner Br\u00f6nnimann Handel M.h\u00e4uten & Fellen",
    "wof:placetype":"venue"
},
  "geometry": {"coordinates":[8.0037059784,47.4046363831],"type":"Point"}
}