{
  "type": "Feature",
  "properties": {
    "iso:country":"CH",
    "sg:address":"Dorfstrasse 68",
    "sg:city":"Zumikon",
    "sg:orig_category":"Hardwareberatung",
    "sg:phone":"+41 19918630",
    "sg:postcode":"8126",
    "sg:province":"Z\u00fcrich",
    "wof:name":"A-net Gmbh",
    "wof:placetype":"venue"
},
  "geometry": {"coordinates":[8.6256399155,47.3303756714],"type":"Point"}
}