{
  "type": "Feature",
  "properties": {
    "iso:country":"CH",
    "sg:address":"Poststrasse 1",
    "sg:city":"Oetwil",
    "sg:orig_category":"Verlagsgewerbe Werbung",
    "sg:phone":"+41 71 929 58 21",
    "sg:postcode":"8955",
    "sg:province":"Z\u00fcrich",
    "wof:name":"Wir Public Relations Ag Wagenleitner Wolfgang M.",
    "wof:placetype":"venue"
},
  "geometry": {"coordinates":[9.0442562103,47.458896637],"type":"Point"}
}