{
  "type": "Feature",
  "properties": {
    "iso:country":"CH",
    "sg:address":"Aliothstrasse 62",
    "sg:city":"M\u00fcnchenstein",
    "sg:orig_category":"Detailhandel mit Haustieren U zoologischem Bedarf",
    "sg:phone":"+41 32 325 38 70",
    "sg:postcode":"4142",
    "sg:province":"Basel-Landschaft",
    "wof:name":"Tierfreund Ag Basel Zentralverwaltung",
    "wof:placetype":"venue"
},
  "geometry": {"coordinates":[7.6132521629,47.5094833374],"type":"Point"}
}