{
  "type": "Feature",
  "properties": {
    "iso:country":"CH",
    "sg:address":"Gartenstrasse 101 4000 Basel. Postfach",
    "sg:city":"Basel",
    "sg:orig_category":"Offsetdruck Sonstige pers\u00f6nliche Dienstleistungen",
    "sg:phone":"+41 14372737",
    "sg:postcode":"4051",
    "sg:province":"Basel-Stadt",
    "wof:name":"Ecp Gmbh",
    "wof:placetype":"venue"
},
  "geometry": {"coordinates":[7.5933561325,47.548034668],"type":"Point"}
}