{
  "type": "Feature",
  "properties": {
    "iso:country":"CH",
    "sg:address":"Gewerbestrasse 5",
    "sg:city":"Cham",
    "sg:orig_category":"Grosshandel mit sonstigen Halbwaren Sonstige mit der Informatik verbundene T\u00e4tigkeiten",
    "sg:phone":"+41 41 740 10 70",
    "sg:postcode":"6330",
    "sg:province":"Zug",
    "wof:name":"Publicity Cards Ag",
    "wof:placetype":"venue"
},
  "geometry": {"coordinates":[8.4734659195,47.1885452271],"type":"Point"}
}