{
  "type": "Feature",
  "properties": {
    "iso:country":"CH",
    "sg:address":"Aarauerstrasse 2",
    "sg:city":"Wildegg",
    "sg:orig_category":"Sanit\u00e4r U Heizungsinstallation Sanit\u00e4rinstallation",
    "sg:phone":"+41 62 893 22 58",
    "sg:postcode":"5103",
    "sg:province":"Aargau",
    "wof:name":"Willi Hollenstein San.installationen Heizungen",
    "wof:placetype":"venue"
},
  "geometry": {"coordinates":[8.1640224457,47.4147033691],"type":"Point"}
}