{
  "type": "Feature",
  "properties": {
    "iso:country":"CH",
    "sg:address":"Lindenhofstrasse 20",
    "sg:city":"Worblaufen",
    "sg:orig_category":"Grosshandel mit Geschenkartikeln U Souvenirs Werbung",
    "sg:phone":"+41 31 921 77 08",
    "sg:postcode":"3048",
    "sg:province":"Bern",
    "wof:name":"Branco Werbesysteme",
    "wof:placetype":"venue"
},
  "geometry": {"coordinates":[7.4610290527,46.9793319702],"type":"Point"}
}