{
  "type": "Feature",
  "properties": {
    "iso:country":"CH",
    "sg:address":"Route De Soral 125",
    "sg:city":"Bernex",
    "sg:orig_category":"G\u00fcterbef\u00f6rderung im Strassenverkehr",
    "sg:phone":"+41 22 757 50 39",
    "sg:postcode":"1233",
    "sg:province":"Gen\u00e8ve",
    "wof:name":"Pierre-louis Chevalley Entreprise De Transports",
    "wof:placetype":"venue"
},
  "geometry": {"coordinates":[6.0727639198,46.1641159058],"type":"Point"}
}