{
  "type": "Feature",
  "properties": {
    "iso:country":"CH",
    "sg:address":"Chemin Du Chauderon 1",
    "sg:city":"Chexbres",
    "sg:classifiers":[
        {
            "category":"Government",
            "subcategory":"Post Office",
            "type":"Public Place"
        }
    ],
    "sg:phone":"+41 21 946 10 35",
    "sg:postcode":"1071",
    "sg:province":"Vaud",
    "sg:tags":[
        "die",
        "poststellen"
    ],
    "wof:name":"La Poste Suisse",
    "wof:placetype":"venue"
},
  "geometry": {"coordinates":[6.7767238617,46.4821166992],"type":"Point"}
}