{
  "type": "Feature",
  "properties": {
    "iso:country":"CH",
    "sg:address":"Hauptstrasse 81",
    "sg:city":"Rorschach",
    "sg:orig_category":"Detailhandel mit Damenbekleidung Detailhandel mit Herrenbekleidung",
    "sg:phone":"+41 71 845 45 35",
    "sg:postcode":"9400",
    "sg:province":"St. Gallen",
    "wof:name":"Modehaus Rudolf",
    "wof:placetype":"venue"
},
  "geometry": {"coordinates":[9.4908742905,47.4787406921],"type":"Point"}
}