{
  "type": "Feature",
  "properties": {
    "iso:country":"CH",
    "sg:address":"Grellingerstrasse 95",
    "sg:city":"Nunningen",
    "sg:orig_category":"Detailhandel mit Haustieren U zoologischem Bedarf Personal U Stellenvermittlung",
    "sg:phone":"+41 61 791 06 59",
    "sg:postcode":"4208",
    "sg:province":"Solothurn",
    "wof:name":"Wechsler Thomas",
    "wof:placetype":"venue"
},
  "geometry": {"coordinates":[7.5978860855,47.4075698853],"type":"Point"}
}