{
  "type": "Feature",
  "properties": {
    "iso:country":"CH",
    "sg:address":"S\u00e4gegasse 22 8702 Zollikon. Postfach 118",
    "sg:city":"Zollikon",
    "sg:orig_category":"Werbevermittlung",
    "sg:phone":"+41 13902025",
    "sg:postcode":"8702",
    "sg:province":"Z\u00fcrich",
    "wof:name":"Rolf D. Baumgarten Werbeagentur",
    "wof:placetype":"venue"
},
  "geometry": {"coordinates":[8.5733127594,47.336933136],"type":"Point"}
}