{
  "type": "Feature",
  "properties": {
    "iso:country":"CH",
    "sg:address":"Marterey Rue 1",
    "sg:city":"Lausanne",
    "sg:orig_category":"Herstellung von Elektromotoren, Generatoren U Transformatoren",
    "sg:postcode":"1005",
    "sg:province":"Vaud",
    "wof:name":"Aps Advanced Power Systems, J.-c. Mathieu",
    "wof:placetype":"venue"
},
  "geometry": {"coordinates":[6.6373720169,46.5197219849],"type":"Point"}
}