{
  "type": "Feature",
  "properties": {
    "iso:country":"CH",
    "sg:address":"Gehrrebenstrasse 3",
    "sg:city":"Hedingen",
    "sg:orig_category":"Baugewerbe",
    "sg:phone":"+41 17617709",
    "sg:postcode":"8908",
    "sg:province":"Z\u00fcrich",
    "wof:name":"Nova Baumanagement",
    "wof:placetype":"venue"
},
  "geometry": {"coordinates":[8.451407,47.299953],"type":"Point"}
}