{
  "type": "Feature",
  "properties": {
    "iso:country":"CH",
    "sg:address":"Rue De La Poste 47 1926 Fully. Postfach",
    "sg:city":"Fully",
    "sg:orig_category":"Offsetdruck Schnelldruck U Kopierservice",
    "sg:phone":"+41 79 412 83 74",
    "sg:postcode":"1926",
    "sg:province":"Valais",
    "wof:name":"Flash Copy Dorsaz Sa Imprimerie",
    "wof:placetype":"venue"
},
  "geometry": {"coordinates":[7.1132459641,46.1367454529],"type":"Point"}
}