{
  "type": "Feature",
  "properties": {
    "iso:country":"CH",
    "sg:address":"Pr\u00e9 Du Martinet",
    "sg:city":"Gingins",
    "sg:orig_category":"Sonstiger Grosshandel",
    "sg:postcode":"1276",
    "sg:province":"Vaud",
    "wof:name":"Jeandiffuse, St\u00e9phane Jean-mairet",
    "wof:placetype":"venue"
},
  "geometry": {"coordinates":[6.183426857,46.403717041],"type":"Point"}
}