{
  "type": "Feature",
  "properties": {
    "iso:country":"CH",
    "sg:address":"Dorfbachstrasse 60",
    "sg:city":"K\u00f6niz",
    "sg:orig_category":"Wirtschaftspr\u00fcfung, Steuerberatung U Treuhand",
    "sg:phone":"+41 31 972 04 02",
    "sg:postcode":"3098",
    "sg:province":"Bern",
    "wof:name":"Phs Treuhand Gmbh",
    "wof:placetype":"venue"
},
  "geometry": {"coordinates":[7.4070038795,46.9196662903],"type":"Point"}
}