{
  "type": "Feature",
  "properties": {
    "iso:country":"CH",
    "sg:address":"Emmentalstrasse 49",
    "sg:city":"Oberburg",
    "sg:orig_category":"Mechanik Mechanische Werkst\u00e4tten",
    "sg:postcode":"3414",
    "sg:province":"Bern",
    "wof:name":"Rudolf K\u00fchni",
    "wof:placetype":"venue"
},
  "geometry": {"coordinates":[7.6297249794,47.0357971191],"type":"Point"}
}