{
  "type": "Feature",
  "properties": {
    "iso:country":"CH",
    "sg:address":"Champoussin",
    "sg:city":"Val-d'illiez",
    "sg:orig_category":"HOTELS: MIT RESTAURANT Kongress- and Tagungshotels mit Restaurant",
    "sg:phone":"+41 24 476 83 00",
    "sg:postcode":"1873",
    "sg:province":"Valais",
    "wof:name":"H\u00f4tel Royal Alpage Club",
    "wof:placetype":"venue"
},
  "geometry": {"coordinates":[6.8638601303,46.2090797424],"type":"Point"}
}