{
  "type": "Feature",
  "properties": {
    "iso:country":"CH",
    "sg:address":"Chemin Des Publes 6",
    "sg:city":"Penthaz",
    "sg:orig_category":"Primarschulen",
    "sg:phone":"+41 21 861 10 88",
    "sg:postcode":"1303",
    "sg:province":"Vaud",
    "wof:name":"Ecole Primaire Coll\u00e8ge La L\u00e9chire",
    "wof:placetype":"venue"
},
  "geometry": {"coordinates":[6.5355482101,46.6047592163],"type":"Point"}
}