{
  "type": "Feature",
  "properties": {
    "iso:country":"CH",
    "sg:address":"Alte Steinhauserstrasse 19",
    "sg:city":"Cham",
    "sg:orig_category":"Handelsvermittlung U Grosshandel Sonstiger Grosshandel",
    "sg:phone":"+41 55 420 15 30",
    "sg:postcode":"6330",
    "sg:province":"Zug",
    "wof:name":"Newchem Ag Waren; Handel. Bautechnische Technologien Und Produkte; Entwicklung",
    "wof:placetype":"venue"
},
  "geometry": {"coordinates":[8.7764577866,47.1998558044],"type":"Point"}
}