{
  "type": "Feature",
  "properties": {
    "iso:country":"CH",
    "sg:address":"Plaz",
    "sg:city":"Sent",
    "sg:orig_category":"Herstellung von sonstigen landwirtschaftlichen Maschinen Instandhaltung U Reparatur von Automobilen",
    "sg:phone":"+41 79 669 12 02",
    "sg:postcode":"7554",
    "sg:province":"Graubunden",
    "wof:name":"Valentin & Krebs",
    "wof:placetype":"venue"
},
  "geometry": {"coordinates":[10.3381700516,46.8173599243],"type":"Point"}
}