{
  "type": "Feature",
  "properties": {
    "iso:country":"CH",
    "sg:address":"Triststrasse 8 7000 Chur. Postfach 204",
    "sg:city":"Chur",
    "sg:orig_category":"Herstellung von Ger\u00e4ten der Elektrizit\u00e4tserzeugung, -verteilung u.\u00e4. -Herstellung von Elektrizit\u00e4tsv",
    "sg:phone":"+41 81 254 25 11",
    "sg:postcode":"7007",
    "sg:province":"Graubunden",
    "wof:name":"Tem Ag F\u00fcr Elektronik",
    "wof:placetype":"venue"
},
  "geometry": {"coordinates":[9.507024765,46.8450775146],"type":"Point"}
}