{
  "type": "Feature",
  "properties": {
    "iso:country":"CH",
    "sg:address":"Freidorf 151",
    "sg:city":"Muttenz",
    "sg:orig_category":"Erschliessung von Grundst\u00fccken",
    "sg:phone":"+41 17808093",
    "sg:postcode":"4132",
    "sg:province":"Basel-Landschaft",
    "wof:name":"Siedlungsgenossenschaft Gwad",
    "wof:placetype":"venue"
},
  "geometry": {"coordinates":[8.6534738541,47.2387657166],"type":"Point"}
}