{
  "type": "Feature",
  "properties": {
    "iso:country":"CH",
    "sg:address":"Weidenpark 3",
    "sg:city":"M\u00f6hlin",
    "sg:orig_category":"Abdichtung Ausbaugewerbe",
    "sg:phone":"+41 79 350 17 31",
    "sg:postcode":"4313",
    "sg:province":"Aargau",
    "wof:name":"Mohler Gmbh Abdichtungen Bautenschutz",
    "wof:placetype":"venue"
},
  "geometry": {"coordinates":[7.840251,47.560318],"type":"Point"}
}