{
  "type": "Feature",
  "properties": {
    "iso:country":"CH",
    "sg:address":"Kalchengasse 9 8302 Kloten. Postfach",
    "sg:city":"Kloten",
    "sg:orig_category":"Herstellung von Konstruktionsteilen, Fertigbauteilen U Ausbauelementen aus Holz",
    "sg:postcode":"8302",
    "sg:province":"Z\u00fcrich",
    "wof:name":"Neue Holzarchitektur Ag Schreinerei, Bes. Raumgestaltung U. Innenausbau Usw",
    "wof:placetype":"venue"
},
  "geometry": {"coordinates":[8.582201004,47.4525222778],"type":"Point"}
}