{
  "type": "Feature",
  "properties": {
    "addr:full":"Quai Du Mont-blanc 31 1200 Genf. Postfach Gen\u00e8ve Gen\u00e8ve 1201",
    "addr:housenumber":"31",
    "addr:postcode":"1200 genf. postfach;1201",
    "addr:street":"Quai Du Mont-Blanc",
    "iso:country":"CH",
    "sg:address":"Quai Du Mont-blanc 31 1200 Genf. Postfach",
    "sg:city":"Gen\u00e8ve",
    "sg:orig_category":"Allgemeinbildende weiterf\u00fchrende Schulen",
    "sg:postcode":"1201",
    "sg:province":"Gen\u00e8ve",
    "wof:name":"Piccolo Studio S\u00e0rl",
    "wof:placetype":"venue"
},
  "geometry": {"coordinates":[6.152384,46.211308],"type":"Point"}
}