{
  "type": "Feature",
  "properties": {
    "iso:country":"CH",
    "sg:address":"Gewerbestrasse 14",
    "sg:city":"Suhr",
    "sg:orig_category":"Sanit\u00e4r, Heizungs U L\u00fcftungsinstallation Sanit\u00e4rinstallation",
    "sg:phone":"+41 62 842 60 13",
    "sg:postcode":"5034",
    "sg:province":"Aargau",
    "wof:name":"L. Hitz Ag Suhr",
    "wof:placetype":"venue"
},
  "geometry": {"coordinates":[8.0849018097,47.366569519],"type":"Point"}
}