{
  "type": "Feature",
  "properties": {
    "iso:country":"CH",
    "sg:address":"Fazy Boulevard James- 4 1201 Gen\u00e8ve. Postfach",
    "sg:city":"Gen\u00e8ve",
    "sg:orig_category":"Wirtschaftspr\u00fcfung, Steuerberatung U Treuhand",
    "sg:phone":"+41 32 720 92 84",
    "sg:postcode":"1201",
    "sg:province":"Gen\u00e8ve",
    "wof:name":"Orfigest Sa",
    "wof:placetype":"venue"
},
  "geometry": {"coordinates":[6.9989829063,47.255279541],"type":"Point"}
}