{
  "type": "Feature",
  "properties": {
    "iso:country":"CH",
    "sg:address":"Rue De St-bonnet",
    "sg:city":"Dully",
    "sg:orig_category":"Rebbau",
    "sg:phone":"+41 21 824 16 08",
    "sg:postcode":"1195",
    "sg:province":"Vaud",
    "wof:name":"Bernard Steiner Viticulteur-encaveur",
    "wof:placetype":"venue"
},
  "geometry": {"coordinates":[6.3020720482,46.4363937378],"type":"Point"}
}