{
  "type": "Feature",
  "properties": {
    "iso:country":"CH",
    "sg:address":"Molaires Les",
    "sg:city":"St-gingolph",
    "sg:orig_category":"Maschinen-Fabrikation",
    "sg:phone":"+41 24 481 53 24",
    "sg:postcode":"1898",
    "sg:province":"Valais",
    "wof:name":"Rdc Construction Ltd",
    "wof:placetype":"venue"
},
  "geometry": {"coordinates":[6.8345160484,46.3854103088],"type":"Point"}
}