{
  "type": "Feature",
  "properties": {
    "iso:country":"CH",
    "sg:address":"Neugutstrasse 45",
    "sg:city":"D\u00fcbendorf",
    "sg:orig_category":"Hardwareberatung",
    "sg:phone":"+41 61 401 50 83",
    "sg:postcode":"8600",
    "sg:province":"Z\u00fcrich",
    "wof:name":"Kreis Martin",
    "wof:placetype":"venue"
},
  "geometry": {"coordinates":[7.5545377731,47.514957428],"type":"Point"}
}