{
  "type": "Feature",
  "properties": {
    "iso:country":"CH",
    "sg:address":"Oltnerstrasse 3",
    "sg:city":"Sch\u00f6nenwerd",
    "sg:orig_category":"Bau U Wohngenossenschaften",
    "sg:phone":"+41 71 455 12 07",
    "sg:postcode":"5012",
    "sg:province":"Solothurn",
    "wof:name":"Genossenschaft Alterswohnungen Roggwil / Freidorf",
    "wof:placetype":"venue"
},
  "geometry": {"coordinates":[9.394352,47.499794],"type":"Point"}
}