{
  "type": "Feature",
  "properties": {
    "iso:country":"CH",
    "sg:address":"Gerre Via Alle 11",
    "sg:city":"Gordola",
    "sg:orig_category":"Herstellung von sonstigen keramischen Erzeugnissen f\u00fcr technische Zwecke",
    "sg:postcode":"6596",
    "sg:province":"Ticino",
    "wof:name":"G\u00fcller Danilo",
    "wof:placetype":"venue"
},
  "geometry": {"coordinates":[8.8604202271,46.180934906],"type":"Point"}
}