{
  "type": "Feature",
  "properties": {
    "iso:country":"CH",
    "sg:address":"Sumpfstrasse 30 6300 Zug. Postfach 1550",
    "sg:city":"Zug",
    "sg:orig_category":"Allgemeiner Hoch U Tiefbau Verlegen von Fliesen U Platten",
    "sg:phone":"+41 41 726 41 41",
    "sg:postcode":"6301",
    "sg:province":"Zug",
    "wof:name":"Peikert Bau Ag",
    "wof:placetype":"venue"
},
  "geometry": {"coordinates":[8.485151,47.177853],"type":"Point"}
}