{
  "type": "Feature",
  "properties": {
    "iso:country":"CH",
    "sg:address":"6865",
    "sg:city":"Tremona",
    "sg:orig_category":"Allgemeiner Hoch U Tiefbau",
    "sg:postcode":"6865",
    "sg:province":"Ticino",
    "wof:name":"Ircr Istituto Regionale Per La Conservazione E Il Restauro Sa",
    "wof:placetype":"venue"
},
  "geometry": {"coordinates":[8.95838,45.881371],"type":"Point"}
}