{
  "type": "Feature",
  "properties": {
    "iso:country":"CH",
    "sg:address":"Reggenschwilerstrasse 28",
    "sg:city":"M\u00f6rschwil",
    "sg:orig_category":"Herstellung von medizinischen U chirurgischen Ger\u00e4ten sowie orthop\u00e4dischen Vorrichtungen",
    "sg:phone":"+41 79 438 02 51",
    "sg:postcode":"9402",
    "sg:province":"St. Gallen",
    "wof:name":"Med-service Ag",
    "wof:placetype":"venue"
},
  "geometry": {"coordinates":[9.4119462967,47.4666862488],"type":"Point"}
}