{
  "type": "Feature",
  "properties": {
    "iso:country":"CH",
    "sg:address":"5647",
    "sg:city":"Oberr\u00fcti",
    "sg:orig_category":"Sportvereine Sch\u00fctzen",
    "sg:phone":"+41 26 418 34 01",
    "sg:postcode":"5647",
    "sg:province":"Aargau",
    "wof:name":"Feldsch\u00fctzengesellschaft",
    "wof:placetype":"venue"
},
  "geometry": {"coordinates":[8.1618499756,47.247089386],"type":"Point"}
}