{
  "type": "Feature",
  "properties": {
    "iso:country":"CH",
    "sg:address":"Zentralstrasse 115",
    "sg:city":"Biel/bienne",
    "sg:orig_category":"Werbegrafikateliers",
    "sg:phone":"+41 32 365 15 35",
    "sg:postcode":"2503",
    "sg:province":"Bern",
    "wof:name":"Isabelle Kuhn Grafisches Atelier",
    "wof:placetype":"venue"
},
  "geometry": {"coordinates":[7.2506461143,47.1331443787],"type":"Point"}
}