{
  "type": "Feature",
  "properties": {
    "addr:full":"Stadio Piazzale Bellinzona Ticino 6500",
    "addr:postcode":"6500",
    "addr:street":"Piazzale",
    "iso:country":"CH",
    "sg:address":"Stadio Piazzale",
    "sg:city":"Bellinzona",
    "sg:orig_category":"Architektur U Ingenieurb\u00fcros",
    "sg:postcode":"6500",
    "sg:province":"Ticino",
    "wof:name":"Habitat Costruzioni 2000 Sa",
    "wof:placetype":"venue"
},
  "geometry": {"coordinates":[9.024119,46.194462],"type":"Point"}
}