{
  "type": "Feature",
  "properties": {
    "iso:country":"CH",
    "sg:address":"Fl\u00fchgasse 35 8008 Z\u00fcrich. Postfach",
    "sg:city":"Z\u00fcrich",
    "sg:orig_category":"Gesundheitswesen",
    "sg:phone":"+41 12527520",
    "sg:postcode":"8001",
    "sg:province":"Z\u00fcrich",
    "wof:name":"Feldenkrais Institut Wurm-zgraggen & Co Bewusstseinsf\u00f6rderung Durch Bewegung. Funktionale Integration Usw",
    "wof:placetype":"venue"
},
  "geometry": {"coordinates":[8.565820694,47.3500862122],"type":"Point"}
}