{
  "type": "Feature",
  "properties": {
    "iso:country":"CH",
    "sg:address":"Diepoldsauerstrasse 8",
    "sg:city":"Widnau",
    "sg:orig_category":"Manicure P\u00e9dicure",
    "sg:phone":"+41 71 722 18 88",
    "sg:postcode":"9443",
    "sg:province":"St. Gallen",
    "wof:name":"Salon Menzi Silvia",
    "wof:placetype":"venue"
},
  "geometry": {"coordinates":[9.6370649338,47.4002075195],"type":"Point"}
}