{
  "type": "Feature",
  "properties": {
    "iso:country":"CH",
    "sg:address":"Moosweg 2",
    "sg:city":"H\u00e4gglingen",
    "sg:orig_category":"Vereine Bienenz\u00fcchter",
    "sg:phone":"+41 56 624 22 79",
    "sg:postcode":"5607",
    "sg:province":"Aargau",
    "wof:name":"Bienenz\u00fcchterver.bremgarten",
    "wof:placetype":"venue"
},
  "geometry": {"coordinates":[8.2502470016,47.3894386292],"type":"Point"}
}