{
  "type": "Feature",
  "properties": {
    "iso:country":"CH",
    "sg:address":"Avenue Communes-r\u00e9unies 86bis",
    "sg:city":"Grand-lancy",
    "sg:orig_category":"Installation von Heizungs, L\u00fcftungs U Klimaanlagen Sanit\u00e4r U Heizungsinstallation",
    "sg:phone":"+41 22 880 08 48",
    "sg:postcode":"1212",
    "sg:province":"Gen\u00e8ve",
    "wof:name":"Olivier Aschiero Aac Aschiero Assist. Chauffage",
    "wof:placetype":"venue"
},
  "geometry": {"coordinates":[6.1232647896,46.1722984314],"type":"Point"}
}