{
  "type": "Feature",
  "properties": {
    "iso:country":"CH",
    "sg:address":"Moselenweg 7a",
    "sg:city":"Wiedlisbach",
    "sg:orig_category":"Herstellung von Kunststoff in Prim\u00e4rformen",
    "sg:phone":"+41 32 636 20 88",
    "sg:postcode":"4537",
    "sg:province":"Bern",
    "wof:name":"Polymere Compound Ag",
    "wof:placetype":"venue"
},
  "geometry": {"coordinates":[7.6523499489,47.2469711304],"type":"Point"}
}