{
  "type": "Feature",
  "properties": {
    "iso:country":"CH",
    "sg:address":"Fahys Rue Des 129",
    "sg:city":"Neuch\u00e2tel",
    "sg:orig_category":"Handel mit Automobilteilen U Zubeh\u00f6r",
    "sg:postcode":"2000",
    "sg:province":"Neuch\u00e2tel",
    "wof:name":"Bg Rep-rapid Ltd, \u00e0 Londres, Succursale De Neuch\u00e2tel",
    "wof:placetype":"venue"
},
  "geometry": {"coordinates":[6.9310851097,46.9903335571],"type":"Point"}
}