{
  "type": "Feature",
  "properties": {
    "iso:country":"CH",
    "sg:address":"1964 Conthey. Postfach",
    "sg:city":"Conthey",
    "sg:orig_category":"Grosshandel mit Getr\u00e4nken",
    "sg:postcode":"1964",
    "sg:province":"Valais",
    "wof:name":"Taverne Contheysanne Sa",
    "wof:placetype":"venue"
},
  "geometry": {"coordinates":[7.302670002,46.2224006653],"type":"Point"}
}