{
  "type": "Feature",
  "properties": {
    "iso:country":"CH",
    "sg:address":"Obere Eichholz 24",
    "sg:city":"Koppigen",
    "sg:orig_category":"Sportvereine Ballsport Tennis",
    "sg:phone":"+41 34 413 22 35",
    "sg:postcode":"3425",
    "sg:province":"Bern",
    "wof:name":"Tennisclub Koppigen",
    "wof:placetype":"venue"
},
  "geometry": {"coordinates":[7.5929732323,47.1322975159],"type":"Point"}
}