{
  "type": "Feature",
  "properties": {
    "iso:country":"CH",
    "sg:address":"Avenue Centrale",
    "sg:city":"Villars-sur-ollon",
    "sg:orig_category":"Nationale Postdienste",
    "sg:phone":"+41 24 495 29 35",
    "sg:postcode":"1884",
    "sg:province":"Vaud",
    "wof:name":"La Poste Suisse",
    "wof:placetype":"venue"
},
  "geometry": {"coordinates":[7.0550079346,46.2969665527],"type":"Point"}
}