{
  "type": "Feature",
  "properties": {
    "iso:country":"CH",
    "sg:address":"Alpenau 9404 Rorschacherberg. Postfach",
    "sg:city":"Rorschacherberg",
    "sg:orig_category":"RESTAURANTS: TEA-ROOMS",
    "sg:postcode":"9404",
    "sg:province":"St. Gallen",
    "wof:name":"Paul U. Margot Ridolfi",
    "wof:placetype":"venue"
},
  "geometry": {"coordinates":[9.4864778519,47.4554443359],"type":"Point"}
}