{
  "type": "Feature",
  "properties": {
    "iso:country":"CH",
    "sg:address":"Hauptstrasse 50",
    "sg:city":"Frick",
    "sg:orig_category":"Detailhandel mit Spielwaren Herstellung von sonstiger Bekleidung U Bekleidungszubeh\u00f6r",
    "sg:phone":"+41 62 871 48 47",
    "sg:postcode":"5070",
    "sg:province":"Aargau",
    "wof:name":"Binkert Ag Frick",
    "wof:placetype":"venue"
},
  "geometry": {"coordinates":[8.0205898285,47.5073661804],"type":"Point"}
}