{
  "type": "Feature",
  "properties": {
    "addr:full":"Fl\u00fch 3096 Oberbalm. Postfach Oberbalm Bern 3096",
    "addr:postcode":"3096;postfach;3096",
    "addr:street":"Oberbalm.",
    "iso:country":"CH",
    "sg:address":"Fl\u00fch 3096 Oberbalm. Postfach",
    "sg:city":"Oberbalm",
    "sg:orig_category":"Allgemeiner Hoch U Tiefbau",
    "sg:postcode":"3096",
    "sg:province":"Bern",
    "wof:name":"Hostettler Daniel Baugesch\u00e4ft",
    "wof:placetype":"venue"
},
  "geometry": {"coordinates":[7.425672,46.859325],"type":"Point"}
}