{
  "type": "Feature",
  "properties": {
    "iso:country":"CH",
    "sg:address":"Beckenriederstrasse 9 6374 Buochs. Postfach 144",
    "sg:city":"Buochs",
    "sg:orig_category":"Landesverteidigung, Sozialversicherung \u00d6ffentliche Verwaltung",
    "sg:phone":"+41 41 620 05 19",
    "sg:postcode":"6374",
    "sg:province":"Nidwalden",
    "wof:name":"Zivilschutzstelle Buochs",
    "wof:placetype":"venue"
},
  "geometry": {"coordinates":[8.4227628708,46.9740028381],"type":"Point"}
}