{
  "type": "Feature",
  "properties": {
    "addr:full":"Heerengarten 350 Hallau Schaffhausen 8215",
    "addr:housenumber":"350",
    "addr:postcode":"8215",
    "addr:street":"Heerengarten",
    "iso:country":"CH",
    "sg:address":"Heerengarten 350",
    "sg:city":"Hallau",
    "sg:classifiers":[
        {
            "category":"Banks & Credit Unions",
            "subcategory":"Bank",
            "type":"Services"
        }
    ],
    "sg:phone":"+41 91 809 31 11",
    "sg:postcode":"8215",
    "sg:province":"Schaffhausen",
    "wof:name":"Bsi Sa",
    "wof:placetype":"venue"
},
  "geometry": {"coordinates":[8.94513,46.013046],"type":"Point"}
}