{
  "type": "Feature",
  "properties": {
    "iso:country":"CH",
    "sg:address":"Schwertgasse 14",
    "sg:city":"Zurzach",
    "sg:orig_category":"Erbringung von sonstigen Dienstleistungen f\u00fcr Unternehmen",
    "sg:phone":"+41 71 383 30 80",
    "sg:postcode":"5330",
    "sg:province":"Aargau",
    "wof:name":"Claro Weltladen",
    "wof:placetype":"venue"
},
  "geometry": {"coordinates":[9.2534332275,47.4168586731],"type":"Point"}
}