{
  "type": "Feature",
  "properties": {
    "iso:country":"CH",
    "sg:address":"Blumenweg 3",
    "sg:city":"K\u00f6lliken",
    "sg:orig_category":"Markt U Meinungsforschung Unternehmensberatung",
    "sg:phone":"+41 62 723 05 74",
    "sg:postcode":"5742",
    "sg:province":"Aargau",
    "wof:name":"Teamconsult Ag",
    "wof:placetype":"venue"
},
  "geometry": {"coordinates":[8.0165634155,47.3339309692],"type":"Point"}
}