{
  "type": "Feature",
  "properties": {
    "iso:country":"CH",
    "sg:address":"Fischmarkt 19",
    "sg:city":"Liestal",
    "sg:orig_category":"Herstellung von medizinischen U chirurgischen Ger\u00e4ten sowie orthop\u00e4dischen Vorrichtungen",
    "sg:phone":"+41 61 921 40 29",
    "sg:postcode":"4410",
    "sg:province":"Basel-Landschaft",
    "wof:name":"Roma Birth Ag",
    "wof:placetype":"venue"
},
  "geometry": {"coordinates":[7.734869957,47.4834785461],"type":"Point"}
}