{
  "type": "Feature",
  "properties": {
    "iso:country":"CH",
    "sg:address":"Rundbuckstrasse 6",
    "sg:city":"Neuhausen",
    "sg:orig_category":"Unternehmensberatung",
    "sg:postcode":"8212",
    "sg:province":"Schaffhausen",
    "wof:name":"Bausback Consulting & Management",
    "wof:placetype":"venue"
},
  "geometry": {"coordinates":[8.5825986862,47.3295211792],"type":"Point"}
}