{
  "type": "Feature",
  "properties": {
    "iso:country":"CH",
    "sg:address":"Terbinerstrasse 21",
    "sg:city":"Visp",
    "sg:orig_category":"HOTELS: OHNE RESTAURANT",
    "sg:phone":"+41 32 751 33 38",
    "sg:postcode":"3930",
    "sg:province":"Valais",
    "wof:name":"Pension Iris Garni",
    "wof:placetype":"venue"
},
  "geometry": {"coordinates":[7.0914211273,47.0633964539],"type":"Point"}
}