{
  "type": "Feature",
  "properties": {
    "iso:country":"CH",
    "sg:address":"Via Massagno 26",
    "sg:city":"Lugano",
    "sg:orig_category":"Grosshandel mit chemischen Erzeugnissen Handelsvermittlung von Brennstoffen, Erzen, Metallen U Chemi",
    "sg:phone":"+41 91 910 18 50",
    "sg:postcode":"6900",
    "sg:province":"Ticino",
    "wof:name":"Pansoinco Trading Ltd, Dublino, Succursale Di Lugano",
    "wof:placetype":"venue"
},
  "geometry": {"coordinates":[8.9474172592,46.0102119446],"type":"Point"}
}