{
  "type": "Feature",
  "properties": {
    "iso:country":"CH",
    "sg:address":"Chemin Du Pr\u00e9-fleuri 14 1228 Plan-les-ouates Case Postale 899",
    "sg:city":"Grand-lancy",
    "sg:orig_category":"Herstellung von Duft U K\u00f6rperpflegemitteln",
    "sg:phone":"+41 22 884 33 60",
    "sg:postcode":"1212",
    "sg:province":"Gen\u00e8ve",
    "wof:name":"Scerri Paul Sa",
    "wof:placetype":"venue"
},
  "geometry": {"coordinates":[6.1079540253,46.1655807495],"type":"Point"}
}