{
  "type": "Feature",
  "properties": {
    "addr:full":"Weinhaldenstrasse 39c Jona St. Gallen 8645",
    "addr:housenumber":"39c;st.",
    "addr:postcode":"8645",
    "addr:street":"Weinhaldenstrasse;Jona",
    "iso:country":"CH",
    "sg:address":"Weinhaldenstrasse 39c",
    "sg:city":"Jona",
    "sg:orig_category":"Architektur U Ingenieurb\u00fcros",
    "sg:phone":"+41 55 214 20 11",
    "sg:postcode":"8645",
    "sg:province":"St. Gallen",
    "wof:name":"Urs Iten Beratung + Planung",
    "wof:placetype":"venue"
},
  "geometry": {"coordinates":[8.814268,47.239128],"type":"Point"}
}