{
  "type": "Feature",
  "properties": {
    "iso:country":"CH",
    "sg:address":"Bolacker 7",
    "sg:city":"Gerlafingen",
    "sg:orig_category":"Druck ohne Zeitungsdruck Offsetdruck",
    "sg:phone":"+41 32 675 15 86",
    "sg:postcode":"4563",
    "sg:province":"Solothurn",
    "wof:name":"W\u00fcthrich Druck",
    "wof:placetype":"venue"
},
  "geometry": {"coordinates":[7.5687971115,47.1716690063],"type":"Point"}
}