{
  "type": "Feature",
  "properties": {
    "iso:country":"CH",
    "sg:address":"Rue De Lo\u00e8che 26",
    "sg:city":"Sion",
    "sg:orig_category":"Verlegen von Fliesen U Platten",
    "sg:phone":"+41 27 322 29 04",
    "sg:postcode":"1950",
    "sg:province":"Valais",
    "wof:name":"M\u00e9dard Barras Entreprise De Carrelage",
    "wof:placetype":"venue"
},
  "geometry": {"coordinates":[7.363506794,46.2380180359],"type":"Point"}
}