{
  "type": "Feature",
  "properties": {
    "iso:country":"CH",
    "sg:address":"Minervastrasse 13",
    "sg:city":"Z\u00fcrich",
    "sg:orig_category":"Arztpraxen",
    "sg:phone":"+41 12612742",
    "sg:postcode":"8032",
    "sg:province":"Z\u00fcrich",
    "wof:name":"Dr. Med. Beat Keller Spezialarzt Fmh",
    "wof:placetype":"venue"
},
  "geometry": {"coordinates":[8.553362,47.368851],"type":"Point"}
}