{
  "type": "Feature",
  "properties": {
    "iso:country":"CH",
    "sg:address":"Schmelzistrasse 63",
    "sg:city":"Erschwil",
    "sg:orig_category":"Sportvereine Sch\u00fctzen",
    "sg:phone":"+41 61 781 19 57",
    "sg:postcode":"4228",
    "sg:province":"Solothurn",
    "wof:name":"Freisch\u00fctzengesellschaft",
    "wof:placetype":"venue"
},
  "geometry": {"coordinates":[7.5414409637,47.3726615906],"type":"Point"}
}