{
  "type": "Feature",
  "properties": {
    "iso:country":"CH",
    "sg:address":"Devant Le Village",
    "sg:city":"Rossini\u00e8re",
    "sg:orig_category":"G\u00fcterbef\u00f6rderung im Strassenverkehr",
    "sg:phone":"+41 79 436 60 37",
    "sg:postcode":"1836",
    "wof:name":"Denis Pilet Transports",
    "wof:placetype":"venue"
},
  "geometry": {"coordinates":[7.0834870338,46.4673881531],"type":"Point"}
}