{
  "type": "Feature",
  "properties": {
    "iso:country":"CH",
    "sg:address":"Rosenstrasse 37",
    "sg:city":"Liestal",
    "sg:orig_category":"Politische Parteien FDP",
    "sg:phone":"+41 61 921 98 28",
    "sg:postcode":"4410",
    "sg:province":"Basel-Landschaft",
    "wof:name":"Fdp Des Kantons Baselland",
    "wof:placetype":"venue"
},
  "geometry": {"coordinates":[7.7427401543,47.4828567505],"type":"Point"}
}