{
  "type": "Feature",
  "properties": {
    "iso:country":"CH",
    "sg:address":"Waldheimstrasse 4",
    "sg:city":"Zug",
    "sg:orig_category":"Wirtschaftspr\u00fcfung, Steuerberatung U Treuhand",
    "sg:postcode":"6300",
    "sg:province":"Zug",
    "wof:name":"Schuler Treuhand",
    "wof:placetype":"venue"
},
  "geometry": {"coordinates":[8.5227537155,47.1642417908],"type":"Point"}
}