{
  "type": "Feature",
  "properties": {
    "iso:country":"CH",
    "sg:address":"Renggerstrasse 74",
    "sg:city":"Z\u00fcrich",
    "sg:orig_category":"Sonstige mit der Informatik verbundene T\u00e4tigkeiten",
    "sg:phone":"+41 14810012",
    "sg:postcode":"8038",
    "sg:province":"Z\u00fcrich",
    "wof:name":"Jw Support Ag",
    "wof:placetype":"venue"
},
  "geometry": {"coordinates":[8.5331640244,47.3439331055],"type":"Point"}
}