{
  "type": "Feature",
  "properties": {
    "iso:country":"CH",
    "sg:address":"Chemin Du Pont-de-ville 13",
    "sg:city":"Ch\u00eane-bougeries",
    "sg:orig_category":"Fotografische Ateliers Fotografisches Gewerbe U fotografische Laboratorien",
    "sg:phone":"+41 22 349 70 62",
    "sg:postcode":"1224",
    "sg:province":"Gen\u00e8ve",
    "wof:name":"Monique Bernaz Atelier De Photographie",
    "wof:placetype":"venue"
},
  "geometry": {"coordinates":[6.1917519569,46.1973495483],"type":"Point"}
}