{
  "type": "Feature",
  "properties": {
    "iso:country":"CH",
    "sg:address":"Hohengasse 17",
    "sg:city":"Burgdorf",
    "sg:orig_category":"Grosshandel mit elektrischen Haushaltsger\u00e4ten, Radio U Fernsehger\u00e4ten Handelsvermittlung U Grosshand",
    "sg:phone":"+41 34 423 34 50",
    "sg:postcode":"3400",
    "sg:province":"Bern",
    "wof:name":"Ascom Systec Ag",
    "wof:placetype":"venue"
},
  "geometry": {"coordinates":[7.6270980835,47.056438446],"type":"Point"}
}