{
  "type": "Feature",
  "properties": {
    "iso:country":"CH",
    "sg:address":"Mittlere Strasse 26 4056 Basel. Postfach",
    "sg:city":"Basel",
    "sg:orig_category":"RESTAURANTS: TEA-ROOMS",
    "sg:postcode":"4051",
    "sg:province":"Basel-Stadt",
    "wof:name":"Saladin Elsa Caf\u00e9",
    "wof:placetype":"venue"
},
  "geometry": {"coordinates":[7.5789089203,47.5610694885],"type":"Point"}
}