{
  "type": "Feature",
  "properties": {
    "iso:country":"CH",
    "sg:address":"Dorfstrasse 70",
    "sg:city":"Wiesendangen",
    "sg:orig_category":"Sonstige mit der Informatik verbundene T\u00e4tigkeiten",
    "sg:postcode":"8542",
    "sg:province":"Z\u00fcrich",
    "wof:name":"Smart Support Lehmann",
    "wof:placetype":"venue"
},
  "geometry": {"coordinates":[8.7915058136,47.5210838318],"type":"Point"}
}