{
  "type": "Feature",
  "properties": {
    "addr:full":"Luberzenstrasse 6 Dietikon Z\u00fcrich 8953",
    "addr:housenumber":"6",
    "addr:postcode":"8953",
    "addr:street":"Luberzenstrasse",
    "iso:country":"CH",
    "sg:address":"Luberzenstrasse 6",
    "sg:city":"Dietikon",
    "sg:orig_category":"Autogaragen",
    "sg:phone":"+41 17409905",
    "sg:postcode":"8953",
    "sg:province":"Z\u00fcrich",
    "wof:name":"Wolfgang Merten Luberzengarage",
    "wof:placetype":"venue"
},
  "geometry": {"coordinates":[8.419443,47.398151],"type":"Point"}
}