{
  "type": "Feature",
  "properties": {
    "addr:full":"Via Rompada 36 6987 Caslano. Postfach Caselle Postale 147 Caslano Ticino 6987",
    "addr:housenumber":"36",
    "addr:postcode":"6987 caslano. postfach caselle postale 147;6987",
    "addr:street":"Via Rompada",
    "iso:country":"CH",
    "sg:address":"Via Rompada 36 6987 Caslano. Postfach Caselle Postale 147",
    "sg:city":"Caslano",
    "sg:orig_category":"Grosshandel mit Zucker, Schokolade U S\u00fcsswaren Herstellung von Kakao U Schokoladeerzeugnissen",
    "sg:phone":"+41 91 606 66 66",
    "sg:postcode":"6987",
    "sg:province":"Ticino",
    "wof:name":"Cioccolata Alprose Sa",
    "wof:placetype":"venue"
},
  "geometry": {"coordinates":[8.873225,45.973995],"type":"Point"}
}