{
  "type": "Feature",
  "properties": {
    "iso:country":"CH",
    "sg:address":"7015",
    "sg:city":"Tamins",
    "sg:orig_category":"Primarschulen",
    "sg:phone":"+41 81 641 16 10",
    "sg:postcode":"7015",
    "sg:province":"Graubunden",
    "wof:name":"Primarschule Neues Schulhaus",
    "wof:placetype":"venue"
},
  "geometry": {"coordinates":[9.4072446823,46.8299407959],"type":"Point"}
}