{
  "type": "Feature",
  "properties": {
    "iso:country":"CH",
    "sg:address":"Erlenstrasse 5",
    "sg:city":"Liestal",
    "sg:orig_category":"Buchf\u00fchrung Wirtschaftspr\u00fcfung, Steuerberatung U Treuhand",
    "sg:phone":"+41 79 209 39 15",
    "sg:postcode":"4410",
    "sg:province":"Basel-Landschaft",
    "wof:name":"Bt-treuhand Balordi Peter",
    "wof:placetype":"venue"
},
  "geometry": {"coordinates":[7.722265,47.494476],"type":"Point"}
}