{
  "type": "Feature",
  "properties": {
    "iso:country":"CH",
    "sg:address":"6002 Luzern. Postfach 4411",
    "sg:city":"Luzern",
    "sg:orig_category":"Sportvereine Ballsport Basketball Sportvereine Turnen",
    "sg:phone":"+41 41 440 05 40",
    "sg:postcode":"6002",
    "sg:province":"Luzern",
    "wof:name":"Stadtturnverein Luzern",
    "wof:placetype":"venue"
},
  "geometry": {"coordinates":[8.3082399368,47.0456581116],"type":"Point"}
}