{
  "type": "Feature",
  "properties": {
    "iso:country":"CH",
    "sg:address":"Rue De La Terrassi\u00e8re 58 1200 Genf. Postfach",
    "sg:city":"Gen\u00e8ve",
    "sg:orig_category":"Technische, physikalische U chemische Untersuchung",
    "sg:phone":"+41 32 353 15 05",
    "sg:postcode":"1207",
    "sg:province":"Gen\u00e8ve",
    "wof:name":"Covanis Gmbh",
    "wof:placetype":"venue"
},
  "geometry": {"coordinates":[7.4047012329,47.1289176941],"type":"Point"}
}