{
  "type": "Feature",
  "properties": {
    "iso:country":"CH",
    "sg:address":"Rue Du Village 31",
    "sg:city":"Chardonne",
    "sg:orig_category":"Detailhandel mit Getr\u00e4nken",
    "sg:phone":"+41 21 921 28 56",
    "sg:postcode":"1803",
    "sg:province":"Vaud",
    "wof:name":"Jacques Neyroud Vins La Championne",
    "wof:placetype":"venue"
},
  "geometry": {"coordinates":[6.8279118538,46.4766693115],"type":"Point"}
}