{
  "type": "Feature",
  "properties": {
    "iso:country":"CH",
    "sg:address":"Hauptstrasse 406",
    "sg:city":"Hallau",
    "sg:orig_category":"Detailhandel mit Damenbekleidung Detailhandel mit Herrenbekleidung",
    "sg:phone":"+41 52 681 30 50",
    "sg:postcode":"8215",
    "sg:province":"Schaffhausen",
    "wof:name":"Lexa-textil Zum Merkur A.leutenegger & Co",
    "wof:placetype":"venue"
},
  "geometry": {"coordinates":[8.4573936462,47.6965904236],"type":"Point"}
}