{
  "type": "Feature",
  "properties": {
    "iso:country":"CH",
    "sg:address":"Hauptstrasse 82",
    "sg:city":"Rorschach",
    "sg:orig_category":"Architektur U Ingenieurb\u00fcros Architekturb\u00fcros",
    "sg:phone":"+41 71 841 42 18",
    "sg:postcode":"9400",
    "sg:province":"St. Gallen",
    "wof:name":"Biehle Bruno Ag",
    "wof:placetype":"venue"
},
  "geometry": {"coordinates":[9.490789,47.479137],"type":"Point"}
}