{
  "type": "Feature",
  "properties": {
    "iso:country":"CH",
    "sg:address":"Ruvigliana Via 16 6962 Viganello. Postfach",
    "sg:city":"Viganello",
    "sg:orig_category":"Unclassifiable Establishments",
    "sg:postcode":"6962",
    "sg:province":"Ticino",
    "wof:name":"G.a.n.v. Soci\u00e9t\u00e9 Europ\u00e9enne Industrielle Et Financi\u00e8re Sa Partecipazione In Societ\u00e0 Industriali Ecc",
    "wof:placetype":"venue"
},
  "geometry": {"coordinates":[8.9712972641,46.0134086609],"type":"Point"}
}