{
  "type": "Feature",
  "properties": {
    "iso:country":"CH",
    "sg:address":"Ferdinand Hodler-strasse 5",
    "sg:city":"Z\u00fcrich",
    "sg:orig_category":"Grosshandel mit Nahrungsmitteln, Getr\u00e4nken U Tabakwaren Grosshandel mit Wein U Spirituosen",
    "sg:phone":"+41 13414067",
    "sg:postcode":"8049",
    "sg:province":"Z\u00fcrich",
    "wof:name":"Rudolf Polak Delikatessen & Weine",
    "wof:placetype":"venue"
},
  "geometry": {"coordinates":[8.5017776489,47.4034996033],"type":"Point"}
}