{
  "type": "Feature",
  "properties": {
    "iso:country":"CH",
    "sg:address":"Quellmattstrasse 25",
    "sg:city":"Ipsach",
    "sg:orig_category":"Sonstige mit der Informatik verbundene T\u00e4tigkeiten",
    "sg:phone":"+41 32 333 12 27",
    "sg:postcode":"2563",
    "sg:province":"Bern",
    "wof:name":"Creinfo Rossier",
    "wof:placetype":"venue"
},
  "geometry": {"coordinates":[7.2378430367,47.1159095764],"type":"Point"}
}