{
  "type": "Feature",
  "properties": {
    "addr:full":"Von Roll-strasse 22 Olten Solothurn 4600",
    "addr:housenumber":"22",
    "addr:postcode":"4600",
    "addr:street":"Von Roll-Strasse",
    "iso:country":"CH",
    "sg:address":"Von Roll-strasse 22",
    "sg:city":"Olten",
    "sg:orig_category":"Betrieb U technische Hilfsdienste des Kultur U Unterhaltungswesens",
    "sg:postcode":"4600",
    "sg:province":"Solothurn",
    "wof:name":"Eastend Company Gmbh",
    "wof:placetype":"venue"
},
  "geometry": {"coordinates":[7.908121,47.347477],"type":"Point"}
}