{
  "type": "Feature",
  "properties": {
    "iso:country":"CH",
    "sg:address":"Route De Del\u00e9ment 50",
    "sg:city":"Rossemaison",
    "sg:orig_category":"Herstellung von Maschinen f\u00fcr die Nahrungsmittel, Getr\u00e4nkeherstellung U die Tabakverarbeitung Herste",
    "sg:phone":"+41 62 824 93 15",
    "sg:postcode":"2842",
    "sg:province":"Jura",
    "wof:name":"Geider E. Ag",
    "wof:placetype":"venue"
},
  "geometry": {"coordinates":[8.0724620819,47.3967781067],"type":"Point"}
}