{
  "type": "Feature",
  "properties": {
    "iso:country":"CH",
    "sg:address":"Marktgasse 11",
    "sg:city":"B\u00fclach",
    "sg:orig_category":"Reiseb\u00fcros",
    "sg:phone":"+41 18603050",
    "sg:postcode":"8180",
    "sg:province":"Z\u00fcrich",
    "wof:name":"Bti Kuoni Switzerland Kuoni Reisen Ag",
    "wof:placetype":"venue"
},
  "geometry": {"coordinates":[8.5409584045,47.5185508728],"type":"Point"}
}