{
  "type": "Feature",
  "properties": {
    "iso:country":"CH",
    "sg:address":"Chemin De La Criblette 1",
    "sg:city":"Grandvaux",
    "sg:orig_category":"Rechtsberatung Steuerberatung",
    "sg:phone":"+41 21 799 57 11",
    "sg:postcode":"1091",
    "sg:province":"Vaud",
    "wof:name":"Euroexpert.net S\u00e0rl",
    "wof:placetype":"venue"
},
  "geometry": {"coordinates":[6.7245850563,46.4986038208],"type":"Point"}
}