{
  "type": "Feature",
  "properties": {
    "iso:country":"CH",
    "sg:address":"Bahnhofstrasse 26",
    "sg:city":"Arbon",
    "sg:orig_category":"Unclassifiable Establishments",
    "sg:postcode":"9320",
    "sg:province":"Thurgau",
    "wof:name":"Hoga-service Gmbh",
    "wof:placetype":"venue"
},
  "geometry": {"coordinates":[9.0515136719,47.4669494629],"type":"Point"}
}