{
  "type": "Feature",
  "properties": {
    "iso:country":"CH",
    "sg:address":"Guglerstrasse 27",
    "sg:city":"Bellach",
    "sg:orig_category":"Sportvereine Ski",
    "sg:phone":"+41 32 618 28 84",
    "sg:postcode":"4512",
    "sg:province":"Solothurn",
    "wof:name":"Skiclub Alth\u00fcsli Solothurn",
    "wof:placetype":"venue"
},
  "geometry": {"coordinates":[7.5074381828,47.2139091492],"type":"Point"}
}