{
  "type": "Feature",
  "properties": {
    "iso:country":"CH",
    "sg:address":"Furkastrasse 28",
    "sg:city":"M\u00f6rel",
    "sg:orig_category":"Nationale Postdienste",
    "sg:phone":"+41 27 973 11 34",
    "sg:postcode":"3983",
    "sg:province":"Valais",
    "wof:name":"Die Schweizerische Post",
    "wof:placetype":"venue"
},
  "geometry": {"coordinates":[8.2595663071,46.4833641052],"type":"Point"}
}