{
  "type": "Feature",
  "properties": {
    "iso:country":"CH",
    "sg:address":"Feld",
    "sg:city":"Grabs",
    "sg:classifiers":[
        {
            "category":"Restaurant",
            "type":"Food & Drink"
        }
    ],
    "sg:phone":"+41 81 771 32 16",
    "sg:postcode":"9472",
    "sg:province":"St. Gallen",
    "wof:name":"Gasthaus Krone",
    "wof:placetype":"venue"
},
  "geometry": {"coordinates":[9.4420785904,47.1857185364],"type":"Point"}
}