{
  "type": "Feature",
  "properties": {
    "iso:country":"CH",
    "sg:address":"Im B\u00fcel 1",
    "sg:city":"Matzingen",
    "sg:orig_category":"Grosshandel mit sonstigen Maschinen U Ausr\u00fcstungen f\u00fcr Industrie, Handel U Schiffahrt Strassenbau",
    "sg:postcode":"9548",
    "sg:province":"Thurgau",
    "wof:name":"Peter Neuweiler Schachtfix",
    "wof:placetype":"venue"
},
  "geometry": {"coordinates":[8.9266519547,47.5164718628],"type":"Point"}
}