{
  "type": "Feature",
  "properties": {
    "iso:country":"CH",
    "sg:address":"Tribschenstrasse 57",
    "sg:city":"Luzern",
    "sg:orig_category":"Bauschreinerei Zimmerei, Dachdeckerei, Bauspenglerei U Abdichtung",
    "sg:phone":"+41 41 361 02 40",
    "sg:postcode":"6005",
    "sg:province":"Luzern",
    "wof:name":"Eggstein Holz Ag",
    "wof:placetype":"venue"
},
  "geometry": {"coordinates":[8.316265,47.04285],"type":"Point"}
}