{
  "type": "Feature",
  "properties": {
    "iso:country":"CH",
    "sg:address":"Jungfraustrasse 34",
    "sg:city":"Biberist",
    "sg:orig_category":"Grosshandel mit chemischen Erzeugnissen Herstellung von Seifen, Wasch U Reinigungsmitteln",
    "sg:phone":"+41 32 672 35 45",
    "sg:postcode":"4562",
    "sg:province":"Solothurn",
    "wof:name":"Biber-reinigungstechnik Kn\u00f6rr Mario",
    "wof:placetype":"venue"
},
  "geometry": {"coordinates":[7.5495500565,47.1852912903],"type":"Point"}
}