{
  "type": "Feature",
  "properties": {
    "iso:country":"CH",
    "sg:address":"Hegenheimerstrasse 24 4055 Basel. Postfach",
    "sg:city":"Basel",
    "sg:orig_category":"Pensionskassen",
    "sg:postcode":"4051",
    "sg:province":"Basel-Stadt",
    "wof:name":"Personalf\u00fcrsorgestiftung Der Firma K\u00fcenzi Druck, Inhaber Graf W.",
    "wof:placetype":"venue"
},
  "geometry": {"coordinates":[7.573143959,47.5605316162],"type":"Point"}
}