{
  "type": "Feature",
  "properties": {
    "iso:country":"CH",
    "sg:address":"2542 Pieterlen. Postfach",
    "sg:city":"Pieterlen",
    "sg:orig_category":"Detailhandel mit Waren verschiedener Art, Hauptrichtung Nahrungsmittel",
    "sg:phone":"+41 62 771 14 66",
    "sg:postcode":"2542",
    "sg:province":"Bern",
    "wof:name":"Landwirtschaftliche Genossenschaft Reinach-menziken Und Umgebung",
    "wof:placetype":"venue"
},
  "geometry": {"coordinates":[8.1819820404,47.2584457397],"type":"Point"}
}