{
  "type": "Feature",
  "properties": {
    "iso:country":"CH",
    "sg:address":"Bruderwies 27",
    "sg:city":"Z\u00fcrich",
    "sg:orig_category":"Grosshandel mit Nahrungsmitteln, Getr\u00e4nken U Tabakwaren ohne ausgepr\u00e4gten Schwerpunkt",
    "sg:postcode":"8041",
    "sg:province":"Z\u00fcrich",
    "wof:name":"Simply Crazy Gmbh",
    "wof:placetype":"venue"
},
  "geometry": {"coordinates":[8.5185213089,47.3341903687],"type":"Point"}
}