{
  "type": "Feature",
  "properties": {
    "iso:country":"CH",
    "sg:address":"Hohlstrasse 150 8004 Z\u00fcrich. Postfach",
    "sg:city":"Z\u00fcrich",
    "sg:orig_category":"Lagerung",
    "sg:phone":"+41 71 911 32 22",
    "sg:postcode":"8023",
    "sg:province":"Z\u00fcrich",
    "wof:name":"Sbb Lagerhausverwaltung",
    "wof:placetype":"venue"
},
  "geometry": {"coordinates":[9.0534296036,47.4628791809],"type":"Point"}
}