{
  "type": "Feature",
  "properties": {
    "iso:country":"CH",
    "sg:address":"Via Del Passetto 8 6600 Solduno. Postfach",
    "sg:city":"Locarno",
    "sg:orig_category":"Elektroinstallation",
    "sg:phone":"+41 91 751 49 65",
    "sg:postcode":"6604",
    "sg:province":"Ticino",
    "wof:name":"Eros Pedrioli Sa Impianti Elettrici",
    "wof:placetype":"venue"
},
  "geometry": {"coordinates":[8.7808618546,46.1677284241],"type":"Point"}
}