{
  "type": "Feature",
  "properties": {
    "iso:country":"CH",
    "sg:address":"Rue Edouard-rod 6 1200 Gen\u00e8ve. Postfach",
    "sg:city":"Gen\u00e8ve",
    "sg:orig_category":"Erbringung von Dienstleistungen f\u00fcr Unternehmen",
    "sg:phone":"+41 71 244 24 70",
    "sg:postcode":"1203",
    "sg:province":"Gen\u00e8ve",
    "wof:name":"Keller Ren\u00e9",
    "wof:placetype":"venue"
},
  "geometry": {"coordinates":[9.3904857635,47.4388198853],"type":"Point"}
}