{
  "type": "Feature",
  "properties": {
    "addr:full":"Seilerbahnweg 8 Chur Graubunden 7000",
    "addr:housenumber":"8",
    "addr:postcode":"7000",
    "addr:street":"Seilerbahnweg",
    "iso:country":"CH",
    "sg:address":"Seilerbahnweg 8",
    "sg:city":"Chur",
    "sg:orig_category":"Arbeitnehmerverb\u00e4nde",
    "sg:phone":"+41 81 252 65 65",
    "sg:postcode":"7000",
    "sg:province":"Graubunden",
    "wof:name":"Kaufm\u00e4nnischer Verein Chur",
    "wof:placetype":"venue"
},
  "geometry": {"coordinates":[9.526812,46.846951],"type":"Point"}
}