{
  "type": "Feature",
  "properties": {
    "iso:country":"CH",
    "sg:address":"Falkenstrasse 1",
    "sg:city":"Tagelswangen",
    "sg:orig_category":"Primarschulen",
    "sg:phone":"+41 71 855 31 51",
    "sg:postcode":"8317",
    "sg:province":"Z\u00fcrich",
    "wof:name":"Primarschule Buechen",
    "wof:placetype":"venue"
},
  "geometry": {"coordinates":[9.5429334641,47.4775428772],"type":"Point"}
}