{
  "type": "Feature",
  "properties": {
    "iso:country":"CH",
    "sg:address":"5612",
    "sg:city":"Villmergen",
    "sg:orig_category":"Fotografisches Gewerbe U fotografische Laboratorien",
    "sg:postcode":"5612",
    "sg:province":"Aargau",
    "wof:name":"Foto Willi",
    "wof:placetype":"venue"
},
  "geometry": {"coordinates":[8.244600296,47.3474121094],"type":"Point"}
}