{
  "type": "Feature",
  "properties": {
    "iso:country":"CH",
    "sg:address":"D\u00fcnnernstrasse 15",
    "sg:city":"H\u00e4gendorf",
    "sg:orig_category":"Kosmetikinstitute",
    "sg:phone":"+41 62 216 46 54",
    "sg:postcode":"4614",
    "sg:province":"Solothurn",
    "wof:name":"Rose Gerber Kosmetikinstitut",
    "wof:placetype":"venue"
},
  "geometry": {"coordinates":[7.8448939323,47.3288192749],"type":"Point"}
}