{
  "type": "Feature",
  "properties": {
    "iso:country":"CH",
    "sg:address":"Herrengasse 5",
    "sg:city":"Schwyz",
    "sg:orig_category":"Grosshandel mit Eisenwaren sowie Installationsbedarf f\u00fcr Gas, Wasser U Heizung Grosshandel mit elekt",
    "sg:phone":"+41 41 811 20 64",
    "sg:postcode":"6430",
    "sg:province":"Schwyz",
    "wof:name":"Weber Marcel",
    "wof:placetype":"venue"
},
  "geometry": {"coordinates":[8.6527061462,47.0214385986],"type":"Point"}
}