{
  "type": "Feature",
  "properties": {
    "iso:country":"CH",
    "sg:address":"7126",
    "sg:city":"Castrisch",
    "sg:classifiers":[
        {
            "category":"Restaurant",
            "type":"Food & Drink"
        }
    ],
    "sg:phone":"+41 81 925 19 16",
    "sg:postcode":"7126",
    "sg:province":"Graubunden",
    "wof:name":"Ustria Mundaun",
    "wof:placetype":"venue"
},
  "geometry": {"coordinates":[9.2309818268,46.7760124207],"type":"Point"}
}