{
  "type": "Feature",
  "properties": {
    "iso:country":"CH",
    "sg:address":"Rue Du March\u00e9 37",
    "sg:city":"Montreux",
    "sg:classifiers":[
        {
            "category":"Professional",
            "subcategory":"Management & Consulting",
            "type":"Services"
        }
    ],
    "sg:phone":"+41 21 961 36 36",
    "sg:postcode":"1820",
    "sg:province":"Vaud",
    "sg:tags":[
        "consultancy"
    ],
    "wof:name":"Wagner & Partner Sa",
    "wof:placetype":"venue"
},
  "geometry": {"coordinates":[6.9138331413,46.4340744019],"type":"Point"}
}