{
  "type": "Feature",
  "properties": {
    "iso:country":"CH",
    "sg:address":"Seestrasse 1 6300 Zug. Postfach",
    "sg:city":"Zug",
    "sg:orig_category":"Sonstige Kurierdienste",
    "sg:phone":"+41 41 711 64 64",
    "sg:postcode":"6300",
    "sg:province":"Zug",
    "wof:name":"Pizza Point Gmbh",
    "wof:placetype":"venue"
},
  "geometry": {"coordinates":[8.5150718689,47.1674499512],"type":"Point"}
}