{
  "type": "Feature",
  "properties": {
    "iso:country":"CH",
    "sg:address":"Im Gjuch 21",
    "sg:city":"Mettmenstetten",
    "sg:orig_category":"Non-Classified Establishments",
    "sg:phone":"+41 17682070",
    "sg:postcode":"8932",
    "sg:province":"Z\u00fcrich",
    "wof:name":"Crazy Events Wolf",
    "wof:placetype":"venue"
},
  "geometry": {"coordinates":[8.4675111771,47.2516212463],"type":"Point"}
}