{
  "type": "Feature",
  "properties": {
    "iso:country":"CH",
    "sg:address":"Taaholzstrasse 2",
    "sg:city":"Uzwil",
    "sg:orig_category":"Bau von Strassen, Sportanlagen U Bahnverkehrsstrecken Grafikateliers, Design",
    "sg:phone":"+41 71 951 14 32",
    "sg:postcode":"9240",
    "sg:province":"St. Gallen",
    "wof:name":"Alois P\u00fcntener Ag",
    "wof:placetype":"venue"
},
  "geometry": {"coordinates":[9.129985,47.442024],"type":"Point"}
}