{
  "type": "Feature",
  "properties": {
    "iso:country":"CH",
    "sg:address":"R\u00fctistrasse 22",
    "sg:city":"Schlieren",
    "sg:orig_category":"Bauingenieurb\u00fcros Heizung L\u00fcftung Klima Planer f\u00fcr Energiekonzepte",
    "sg:phone":"+41 17324646",
    "sg:postcode":"8952",
    "sg:province":"Z\u00fcrich",
    "wof:name":"Frigo-consulting Ag Ingenieurb\u00fcro",
    "wof:placetype":"venue"
},
  "geometry": {"coordinates":[8.45206,47.400688],"type":"Point"}
}