{
  "type": "Feature",
  "properties": {
    "iso:country":"CH",
    "sg:address":"S\u00e4gestrasse 47",
    "sg:city":"Lenzburg",
    "sg:orig_category":"Hobel U Holzimpr\u00e4gnierwerke Oberfl\u00e4chenveredlung U W\u00e4rmebehandlung",
    "sg:phone":"+41 79 353 24 64",
    "sg:postcode":"5600",
    "sg:province":"Aargau",
    "wof:name":"Easy Finish Gmbh Montagearbeiten",
    "wof:placetype":"venue"
},
  "geometry": {"coordinates":[8.1775484085,47.3928031921],"type":"Point"}
}