{
  "type": "Feature",
  "properties": {
    "iso:country":"CH",
    "sg:address":"Sch\u00f6neichstrasse 7",
    "sg:city":"Z\u00fcrich",
    "sg:orig_category":"Saunas, Solarien, Fitnesszentren U \u00e4hnliches",
    "sg:phone":"+41 13115303",
    "sg:postcode":"8051",
    "sg:province":"Z\u00fcrich",
    "wof:name":"Lucky Sun Z\u00fcrich Gmbh",
    "wof:placetype":"venue"
},
  "geometry": {"coordinates":[8.5573368073,47.4043235779],"type":"Point"}
}