{
  "type": "Feature",
  "properties": {
    "iso:country":"CH",
    "sg:address":"Neumattweg 4",
    "sg:city":"Schafisheim",
    "sg:orig_category":"Autogaragen",
    "sg:phone":"+41 18440855",
    "sg:postcode":"5503",
    "sg:province":"Aargau",
    "wof:name":"Georg Monjoye Autoreparaturwerkst\u00e4tte",
    "wof:placetype":"venue"
},
  "geometry": {"coordinates":[8.139347,47.379795],"type":"Point"}
}