{
  "type": "Feature",
  "properties": {
    "iso:country":"CH",
    "sg:address":"Ladhuebstrasse 1 9303 Wittenbach. Postfach",
    "sg:city":"Wittenbach",
    "sg:orig_category":"Elektroinstallation",
    "sg:phone":"+41 71 292 30 60",
    "sg:postcode":"9303",
    "wof:name":"Netrag Ag Wittenbach",
    "wof:placetype":"venue"
},
  "geometry": {"coordinates":[9.3726625443,47.4631843567],"type":"Point"}
}