{
  "type": "Feature",
  "properties": {
    "iso:country":"CH",
    "sg:address":"Lottenweg 9",
    "sg:city":"Staufen",
    "sg:orig_category":"Handels-H\u00e4user U Gesellschaften",
    "sg:postcode":"5603",
    "sg:province":"Aargau",
    "wof:name":"Hofinag Ag",
    "wof:placetype":"venue"
},
  "geometry": {"coordinates":[8.1602344513,47.3836746216],"type":"Point"}
}