{
  "type": "Feature",
  "properties": {
    "addr:full":"Via Landriani 2a Lugano Ticino 6900",
    "addr:housenumber":"2a",
    "addr:postcode":"6900",
    "addr:street":"Via Landriani",
    "iso:country":"CH",
    "sg:address":"Via Landriani 2a",
    "sg:city":"Lugano",
    "sg:classifiers":[
        {
            "category":"Banks & Credit Unions",
            "subcategory":"Bank",
            "type":"Services"
        }
    ],
    "sg:postcode":"6900",
    "sg:province":"Ticino",
    "wof:name":"Arquebuse Sa",
    "wof:placetype":"venue"
},
  "geometry": {"coordinates":[6.142701,46.208359],"type":"Point"}
}