{
  "type": "Feature",
  "properties": {
    "addr:full":"Alpenstrasse 17 Illnau Z\u00fcrich 8308",
    "addr:housenumber":"17",
    "addr:postcode":"8308",
    "addr:street":"Alpenstrasse",
    "iso:country":"CH",
    "sg:address":"Alpenstrasse 17",
    "sg:city":"Illnau",
    "sg:orig_category":"Baugewerbe Sonstige pers\u00f6nliche Dienstleistungen",
    "sg:phone":"+41 52 347 20 11",
    "sg:postcode":"8308",
    "sg:province":"Z\u00fcrich",
    "wof:name":"Marcel Fiocchi Fio Tec",
    "wof:placetype":"venue"
},
  "geometry": {"coordinates":[8.712645,47.411797],"type":"Point"}
}