{
  "type": "Feature",
  "properties": {
    "iso:country":"CH",
    "sg:address":"Frohb\u00fchlstrasse 3 8052 Z\u00fcrich. Postfach",
    "sg:city":"Z\u00fcrich",
    "sg:orig_category":"Reiseb\u00fcros",
    "sg:phone":"+41 13030433",
    "sg:postcode":"8052",
    "sg:province":"Z\u00fcrich",
    "wof:name":"Last-minute Swiss Am Holidays",
    "wof:placetype":"venue"
},
  "geometry": {"coordinates":[8.5515604019,47.4274406433],"type":"Point"}
}