{
  "type": "Feature",
  "properties": {
    "iso:country":"CH",
    "sg:address":"Bodenfeldstrasse 27",
    "sg:city":"Bonstetten",
    "sg:orig_category":"Unclassifiable Establishments",
    "sg:postcode":"8906",
    "sg:province":"Z\u00fcrich",
    "wof:name":"Appella Bau Gmbh",
    "wof:placetype":"venue"
},
  "geometry": {"coordinates":[8.4656190872,47.3140182495],"type":"Point"}
}