{
  "type": "Feature",
  "properties": {
    "addr:full":"Hauptbahnhof Z\u00fcrich Z\u00fcrich 8001",
    "addr:postcode":"8001",
    "addr:street":"Zuerich",
    "iso:country":"CH",
    "sg:address":"Hauptbahnhof",
    "sg:city":"Z\u00fcrich",
    "sg:orig_category":"Coiffeursalons Damen Parf\u00fcmerien U sonstiger Detailhandel mit kosmetischen Artikeln U K\u00f6rperpflegemi",
    "sg:phone":"+41 12121966",
    "sg:postcode":"8001",
    "sg:province":"Z\u00fcrich",
    "wof:name":"Andr\u00e9 Tresch Coiffure Andr\u00e9 Joe",
    "wof:placetype":"venue"
},
  "geometry": {"coordinates":[8.53955,47.37706],"type":"Point"}
}