{
  "type": "Feature",
  "properties": {
    "iso:country":"CH",
    "sg:address":"Weinbergstrasse 5",
    "sg:city":"Zug",
    "sg:orig_category":"Finanzierungsinstitutionen",
    "sg:postcode":"6300",
    "sg:province":"Zug",
    "wof:name":"Thomson P\u00e9nz\u00fcgyi Szolg\u00e1ltat\u00f3 Korl\u00e1tolt Felel\u00f6ss\u00e9g\u00fc T\u00e1rsas\u00e1g, Budapest, Branch Office Zug",
    "wof:placetype":"venue"
},
  "geometry": {"coordinates":[8.5264606476,47.1707267761],"type":"Point"}
}