{
  "type": "Feature",
  "properties": {
    "iso:country":"CH",
    "sg:address":"Route De La Grangette 12",
    "sg:city":"Marly",
    "sg:orig_category":"Maurerarbeiten",
    "sg:phone":"+41 26 436 17 06",
    "sg:postcode":"1723",
    "sg:province":"Fribourg",
    "wof:name":"Maurice Donzallaz Ma\u00e7onnerie",
    "wof:placetype":"venue"
},
  "geometry": {"coordinates":[7.1531000137,46.781036377],"type":"Point"}
}