{
  "type": "Feature",
  "properties": {
    "iso:country":"CH",
    "sg:address":"Amselweg 4",
    "sg:city":"Alchenfl\u00fch",
    "sg:orig_category":"Grosshandel mit Sportartikeln",
    "sg:phone":"+41 34 445 07 55",
    "sg:postcode":"3422",
    "sg:province":"Bern",
    "wof:name":"Delgada Ag",
    "wof:placetype":"venue"
},
  "geometry": {"coordinates":[7.5809640884,47.0840873718],"type":"Point"}
}