{
  "type": "Feature",
  "properties": {
    "iso:country":"CH",
    "sg:address":"Rosengasse 4",
    "sg:city":"Liestal",
    "sg:orig_category":"Detailhandel mit Ton U Bildtr\u00e4gern Detailhandel mit elektrischen Haushalts-,Radio U Fernsehger\u00e4ten s",
    "sg:phone":"+41 61 921 19 69",
    "sg:postcode":"4410",
    "sg:province":"Basel-Landschaft",
    "wof:name":"Decade Wenger Ueli",
    "wof:placetype":"venue"
},
  "geometry": {"coordinates":[7.7354168892,47.4845733643],"type":"Point"}
}