{
  "type": "Feature",
  "properties": {
    "iso:country":"CH",
    "sg:address":"Z\u00fcrcherstrasse 7",
    "sg:city":"Rheinfelden",
    "sg:orig_category":"G\u00fcterbef\u00f6rderung im Strassenverkehr Luftfahrt",
    "sg:phone":"+41 61 325 39 33",
    "sg:postcode":"4310",
    "sg:province":"Aargau",
    "wof:name":"Helitrans Ag",
    "wof:placetype":"venue"
},
  "geometry": {"coordinates":[7.7966389656,47.5528411865],"type":"Point"}
}