{
  "type": "Feature",
  "properties": {
    "iso:country":"CH",
    "sg:address":"1981 Vex. Postfach",
    "sg:city":"Vex",
    "sg:orig_category":"Unternehmensberatung",
    "sg:postcode":"1981",
    "sg:province":"Valais",
    "wof:name":"Givr S\u00e0rl",
    "wof:placetype":"venue"
},
  "geometry": {"coordinates":[7.3954100609,46.2054786682],"type":"Point"}
}