{
  "type": "Feature",
  "properties": {
    "iso:country":"CH",
    "sg:address":"Bielstrasse 9 4500 Solothurn. Postfach",
    "sg:city":"Solothurn",
    "sg:orig_category":"Softwareentwicklung U beratung Sonstige mit der Informatik verbundene T\u00e4tigkeiten",
    "sg:phone":"+41 19344433",
    "sg:postcode":"4500",
    "sg:province":"Solothurn",
    "wof:name":"Opus Software Gmbh",
    "wof:placetype":"venue"
},
  "geometry": {"coordinates":[8.7912721634,47.3162841797],"type":"Point"}
}