{
  "type": "Feature",
  "properties": {
    "iso:country":"CH",
    "sg:address":"Salici Via Ai",
    "sg:city":"Bedano",
    "sg:orig_category":"Gesundheitswesen",
    "sg:postcode":"6930",
    "sg:province":"Ticino",
    "wof:name":"Salusan Studio Sagl",
    "wof:placetype":"venue"
},
  "geometry": {"coordinates":[8.9181346893,46.0484466553],"type":"Point"}
}