{
  "type": "Feature",
  "properties": {
    "iso:country":"CH",
    "sg:address":"Hauptstrasse 89",
    "sg:city":"Berg\u00fcn/bravuogn",
    "sg:orig_category":"Seilbahnen Verkehrs- and Tourismusb\u00fcros",
    "sg:phone":"+41 81 407 11 52",
    "sg:postcode":"7482",
    "sg:province":"Graubunden",
    "wof:name":"Berg\u00fcn Ferien",
    "wof:placetype":"venue"
},
  "geometry": {"coordinates":[9.7460184097,46.6284370422],"type":"Point"}
}