{
  "type": "Feature",
  "properties": {
    "iso:country":"CH",
    "sg:address":"Badstrasse 6 6210 Sursee. Postfach 3197",
    "sg:city":"Sursee",
    "sg:orig_category":"Einbau von Schreinerwaren Herstellung von sonstigen Maschinen f\u00fcr unspezifische Verwendung",
    "sg:phone":"+41 41 921 31 55",
    "sg:postcode":"6210",
    "sg:province":"Luzern",
    "wof:name":"Zust Adriano Ag",
    "wof:placetype":"venue"
},
  "geometry": {"coordinates":[8.1107530594,47.1705703735],"type":"Point"}
}