{
  "type": "Feature",
  "properties": {
    "iso:country":"CH",
    "sg:address":"Ruedswilerstr. 39.",
    "sg:city":"Ersigen",
    "sg:orig_category":"Detailhandel mit Tabakwaren",
    "sg:phone":"+41 34453703",
    "sg:postcode":"3423",
    "sg:province":"Bern",
    "wof:name":"G. Frankenstein",
    "wof:placetype":"venue"
},
  "geometry": {"coordinates":[7.6078262329,47.092956543],"type":"Point"}
}