{
  "type": "Feature",
  "properties": {
    "iso:country":"CH",
    "sg:address":"Bahnweg S\u00fcd 2",
    "sg:city":"Sevelen",
    "sg:orig_category":"Unclassifiable Establishments",
    "sg:postcode":"9475",
    "sg:province":"St. Gallen",
    "wof:name":"Schreinerei Christian Bisang",
    "wof:placetype":"venue"
},
  "geometry": {"coordinates":[9.4964265823,47.1248931885],"type":"Point"}
}