{
  "type": "Feature",
  "properties": {
    "iso:country":"CH",
    "sg:address":"6 Cs De Rive",
    "sg:city":"Gen\u00e8ve",
    "sg:classifiers":[
        {
            "category":"Utilities",
            "subcategory":"Natural Gas",
            "type":"Services"
        }
    ],
    "sg:phone":"+41 32 351 55 41",
    "sg:postcode":"1204",
    "sg:province":"Gen\u00e8ve",
    "sg:tags":[
        "rohrfernleitungen",
        "transport"
    ],
    "wof:name":"Aerocom Gmbh & Co. Rohrpostsysteme",
    "wof:placetype":"venue"
},
  "geometry": {"coordinates":[7.362639904,47.1395149231],"type":"Point"}
}