{
  "type": "Feature",
  "properties": {
    "iso:country":"CH",
    "sg:address":"Chemin Des Grandes-vies 5",
    "sg:city":"Porrentruy",
    "sg:orig_category":"Herstellung von Metallkonstruktionen",
    "sg:phone":"+41 32 466 47 79",
    "sg:postcode":"2900",
    "sg:province":"Jura",
    "wof:name":"Crevoisier & Rerat Sa",
    "wof:placetype":"venue"
},
  "geometry": {"coordinates":[7.0819897652,47.4266853333],"type":"Point"}
}