{
  "type": "Feature",
  "properties": {
    "iso:country":"CH",
    "sg:address":"M\u00fchlebachstrasse 86 8008 Z\u00fcrich. Postfach",
    "sg:city":"Z\u00fcrich",
    "sg:orig_category":"RESTAURANTS: TEA-ROOMS",
    "sg:phone":"+41 13883535",
    "sg:postcode":"8032",
    "sg:province":"Z\u00fcrich",
    "wof:name":"Zfv-unternehmungen/z\u00fcrcher Frauenverein F\u00fcr Alkoholfreie Wirtschaften",
    "wof:placetype":"venue"
},
  "geometry": {"coordinates":[8.5538768768,47.3617362976],"type":"Point"}
}