{
  "type": "Feature",
  "properties": {
    "iso:country":"CH",
    "sg:address":"Dorfstrasse 31a",
    "sg:city":"Wattenwil",
    "sg:orig_category":"Drogerien",
    "sg:phone":"+41 33 356 26 26",
    "sg:postcode":"3665",
    "sg:province":"Bern",
    "wof:name":"Roland H\u00e4usler Drogerie",
    "wof:placetype":"venue"
},
  "geometry": {"coordinates":[7.5093970299,46.7700538635],"type":"Point"}
}