{
  "type": "Feature",
  "properties": {
    "iso:country":"CH",
    "sg:address":"Hauptstrasse 22 7413 F\u00fcrstenaubruck. Postfach",
    "sg:city":"F\u00fcrstenaubruck",
    "sg:orig_category":"Non-Classified Establishments",
    "sg:postcode":"7413",
    "sg:province":"Graubunden",
    "wof:name":"Aneka Rasa, Asian Catering, Sani Salzmann",
    "wof:placetype":"venue"
},
  "geometry": {"coordinates":[8.5396108627,47.2886581421],"type":"Point"}
}