{
  "type": "Feature",
  "properties": {
    "iso:country":"CH",
    "sg:address":"Hauptstrasse 23a 4944 Auswil. Postfach 1",
    "sg:city":"Auswil",
    "sg:orig_category":"Laboratorien biologisch",
    "sg:phone":"+41 62 965 07 00",
    "sg:postcode":"4944",
    "sg:province":"Bern",
    "wof:name":"Meier & Co Institut Ilh",
    "wof:placetype":"venue"
},
  "geometry": {"coordinates":[7.8315148354,47.1361351013],"type":"Point"}
}