{
  "type": "Feature",
  "properties": {
    "iso:country":"CH",
    "sg:address":"Cattaneo Viale 3",
    "sg:city":"Lugano",
    "sg:orig_category":"R\u00fcckgewinnung U Vorbereitung f\u00fcr die Wiederverwertung Recycling von Schrott",
    "sg:postcode":"6900",
    "sg:province":"Ticino",
    "wof:name":"Darc, Associazione Ticinese Demolitori Di Auto E Recuperatori Di Cascami",
    "wof:placetype":"venue"
},
  "geometry": {"coordinates":[8.9564399719,46.0057830811],"type":"Point"}
}