{
  "type": "Feature",
  "properties": {
    "iso:country":"CH",
    "sg:address":"Rue De La Grenade",
    "sg:city":"Aubonne",
    "sg:orig_category":"Sportvereine Ballsport Tischtennis",
    "sg:phone":"+41 32 757 16 75",
    "sg:postcode":"1170",
    "sg:province":"Vaud",
    "wof:name":"Ctt Brunette",
    "wof:placetype":"venue"
},
  "geometry": {"coordinates":[7.043366909,47.0549087524],"type":"Point"}
}