{
  "type": "Feature",
  "properties": {
    "iso:country":"CH",
    "sg:address":"Fraumattstrasse 13",
    "sg:city":"Liestal",
    "sg:orig_category":"Sanit\u00e4rinstallation",
    "sg:phone":"+41 61 921 69 69",
    "sg:postcode":"4410",
    "sg:province":"Basel-Landschaft",
    "wof:name":"Peter Ehrsam Installationen & Montagen",
    "wof:placetype":"venue"
},
  "geometry": {"coordinates":[7.7272582054,47.4937324524],"type":"Point"}
}