{
  "type": "Feature",
  "properties": {
    "iso:country":"CH",
    "sg:address":"Langholzstrasse 27",
    "sg:city":"Cham",
    "sg:orig_category":"Sportvereine Ballsport Tischtennis",
    "sg:phone":"+41 79 406 90 65",
    "sg:postcode":"6330",
    "sg:province":"Zug",
    "wof:name":"Ttc H\u00fcnenberg",
    "wof:placetype":"venue"
},
  "geometry": {"coordinates":[8.4473905563,47.1722335815],"type":"Point"}
}