{
  "type": "Feature",
  "properties": {
    "iso:country":"CH",
    "sg:address":"H\u00f6nggerstrasse 1-3 8102 Oberengstringen. Postfach",
    "sg:city":"Oberengstringen",
    "sg:orig_category":"Sonstiger Grosshandel",
    "sg:phone":"+41 41 630 42 46",
    "sg:postcode":"8102",
    "sg:province":"Z\u00fcrich",
    "wof:name":"Trade Connection Ag",
    "wof:placetype":"venue"
},
  "geometry": {"coordinates":[8.3102197647,46.9972305298],"type":"Point"}
}