{
  "type": "Feature",
  "properties": {
    "iso:country":"CH",
    "sg:address":"Allmendweg 6 4528 Zuchwil. Postfach 116",
    "sg:city":"Solothurn",
    "sg:classifiers":[
        {
            "category":"Insurance",
            "subcategory":"Insurance Agent",
            "type":"Services"
        }
    ],
    "sg:phone":"+41 22 342 12 12",
    "sg:postcode":"4501",
    "sg:province":"Solothurn",
    "sg:tags":[
        "versicherungsagenturen",
        "-broker"
    ],
    "wof:name":"Iosi Pellegrini Acc Assur. Conseil Courtage",
    "wof:placetype":"venue"
},
  "geometry": {"coordinates":[6.12774086,46.1870918274],"type":"Point"}
}