{
  "type": "Feature",
  "properties": {
    "iso:country":"CH",
    "sg:address":"Corso San Gottardo 35",
    "sg:city":"Chiasso",
    "sg:orig_category":"Detailhandel mit Bekleidung",
    "sg:phone":"+41 71 912 24 24",
    "sg:postcode":"6830",
    "sg:province":"Ticino",
    "wof:name":"Switch Factory Gmbh",
    "wof:placetype":"venue"
},
  "geometry": {"coordinates":[9.040483,47.464771],"type":"Point"}
}