{
  "type": "Feature",
  "properties": {
    "iso:country":"CH",
    "sg:address":"1196 Gland Case Postale 233",
    "sg:city":"Gland",
    "sg:orig_category":"Sportvereine Sch\u00fctzen Bogen",
    "sg:postcode":"1196",
    "sg:province":"Vaud",
    "wof:name":"Compagnie Des Archers",
    "wof:placetype":"venue"
},
  "geometry": {"coordinates":[6.2614498138,46.4224014282],"type":"Point"}
}