{
  "type": "Feature",
  "properties": {
    "iso:country":"CH",
    "sg:address":"3967",
    "sg:city":"Vercorin",
    "sg:orig_category":"Kunsthandel",
    "sg:phone":"+41 27 455 82 82",
    "sg:postcode":"3967",
    "sg:province":"Valais",
    "wof:name":"Galerie Fontany V\u00e9r\u00e8ne Corvasce",
    "wof:placetype":"venue"
},
  "geometry": {"coordinates":[7.5315098763,46.2563400269],"type":"Point"}
}