{
  "type": "Feature",
  "properties": {
    "iso:country":"CH",
    "sg:address":"Schwerzgruebstrasse 3",
    "sg:city":"B\u00fclach",
    "sg:orig_category":"Maler U Glasergewerbe",
    "sg:postcode":"8180",
    "sg:province":"Z\u00fcrich",
    "wof:name":"Maler Und Gipsergesch\u00e4ft Colacicco",
    "wof:placetype":"venue"
},
  "geometry": {"coordinates":[8.5429992676,47.5148963928],"type":"Point"}
}