{
  "type": "Feature",
  "properties": {
    "iso:country":"CH",
    "sg:address":"Via Costa Di Fuori 2 6614 Brissago. Postfach Caselle Postale 645",
    "sg:city":"Brissago",
    "sg:orig_category":"Maler U Glasergewerbe Verlegen von Fliesen U Platten",
    "sg:phone":"+41 91 793 14 63",
    "sg:postcode":"6614",
    "sg:province":"Ticino",
    "wof:name":"Pozzorini Maurizio",
    "wof:placetype":"venue"
},
  "geometry": {"coordinates":[8.7052307129,46.1125106812],"type":"Point"}
}