{
  "type": "Feature",
  "properties": {
    "addr:full":"Ancien-port Rue De L' 14 1201 Gen\u00e8ve. Postfach Gen\u00e8ve Gen\u00e8ve 1201",
    "addr:housenumber":"14",
    "addr:postcode":"1201;postfach;1201",
    "addr:street":"Rue De L '",
    "iso:country":"CH",
    "sg:address":"Ancien-port Rue De L' 14 1201 Gen\u00e8ve. Postfach",
    "sg:city":"Gen\u00e8ve",
    "sg:orig_category":"Betrieb U technische Hilfsdienste des Kultur U Unterhaltungswesens",
    "sg:postcode":"1201",
    "sg:province":"Gen\u00e8ve",
    "wof:name":"Latin Integration And Specials Gmbh",
    "wof:placetype":"venue"
},
  "geometry": {"coordinates":[8.438205,47.155849],"type":"Point"}
}