{
  "type": "Feature",
  "properties": {
    "iso:country":"CH",
    "sg:address":"Kantonsstrasse 49 6234 Triengen. Postfach 430",
    "sg:city":"Triengen",
    "sg:orig_category":"Sanit\u00e4rinstallation Schlossereien",
    "sg:phone":"+41 41 933 19 30",
    "sg:postcode":"6234",
    "sg:province":"Luzern",
    "wof:name":"Fritz Fischer San.anlagen & Schlosserei",
    "wof:placetype":"venue"
},
  "geometry": {"coordinates":[8.0762748718,47.2347717285],"type":"Point"}
}