{
  "type": "Feature",
  "properties": {
    "iso:country":"CH",
    "sg:address":"Pfingstweidstrasse 31a",
    "sg:city":"Z\u00fcrich",
    "sg:orig_category":"Markt U Meinungsforschung",
    "sg:phone":"+41 21 944 19 22",
    "sg:postcode":"8005",
    "sg:province":"Z\u00fcrich",
    "wof:name":"Francisco Batalla Etude De March\u00e9",
    "wof:placetype":"venue"
},
  "geometry": {"coordinates":[6.8605880737,46.4541015625],"type":"Point"}
}