{
  "type": "Feature",
  "properties": {
    "iso:country":"CH",
    "sg:address":"Chalbisau",
    "sg:city":"Hirzel",
    "sg:orig_category":"Bauschreinerei Innenausbau",
    "sg:phone":"+41 17299147",
    "sg:postcode":"8816",
    "sg:province":"Z\u00fcrich",
    "wof:name":"Willy Kleiner Schreinerei & Innenausbau",
    "wof:placetype":"venue"
},
  "geometry": {"coordinates":[8.59548,47.218018],"type":"Point"}
}