{
  "type": "Feature",
  "properties": {
    "iso:country":"CH",
    "sg:address":"Martinsbergstrasse 38",
    "sg:city":"Baden",
    "sg:orig_category":"Kauf U Verkauf von Immobilien auf eigene Rechnung",
    "sg:phone":"+41 22 343 22 57",
    "sg:postcode":"5400",
    "sg:province":"Aargau",
    "wof:name":"Mbb Sa",
    "wof:placetype":"venue"
},
  "geometry": {"coordinates":[6.1347222328,46.1774711609],"type":"Point"}
}