{
  "type": "Feature",
  "properties": {
    "iso:country":"CH",
    "sg:address":"Les Gr\u00e8ves 112",
    "sg:city":"Font",
    "sg:orig_category":"Kauf U Verkauf von Immobilien auf eigene Rechnung Vermittlung von Immobilien",
    "sg:phone":"+41 26 663 29 77",
    "sg:postcode":"1473",
    "sg:province":"Fribourg",
    "wof:name":"Brigitte Brand Agence Immobili\u00e8re Malibu",
    "wof:placetype":"venue"
},
  "geometry": {"coordinates":[6.8203530312,46.8407478333],"type":"Point"}
}