{
  "type": "Feature",
  "properties": {
    "iso:country":"CH",
    "sg:address":"Tillierstrasse 36",
    "sg:city":"Bern",
    "sg:classifiers":[
        {
            "category":"Building & Trades",
            "subcategory":"Cleaning & Sanitation",
            "type":"Services"
        }
    ],
    "sg:phone":"+41 52 674 08 80",
    "sg:postcode":"3005",
    "sg:province":"Bern",
    "sg:tags":[
        "disposal",
        "hazardous",
        "waste"
    ],
    "wof:name":"Rethmann Recycling Ag",
    "wof:placetype":"venue"
},
  "geometry": {"coordinates":[8.6021766663,47.6761627197],"type":"Point"}
}