{
  "type": "Feature",
  "properties": {
    "iso:country":"CH",
    "sg:address":"B\u00fchlstrasse 70 8583 Sulgen. Postfach",
    "sg:city":"Luzern",
    "sg:orig_category":"Allgemeiner Hoch U Tiefbau",
    "sg:phone":"+41 27 957 21 55",
    "sg:postcode":"6003",
    "sg:province":"Luzern",
    "wof:name":"Burgener H. & Sohn Ag",
    "wof:placetype":"venue"
},
  "geometry": {"coordinates":[7.928501,46.152824],"type":"Point"}
}