{
  "type": "Feature",
  "properties": {
    "iso:country":"CH",
    "sg:address":"Baer Haus 3818 Grindelwald. Postfach 140",
    "sg:city":"Grindelwald",
    "sg:orig_category":"Advokaturb\u00fcros Notariate",
    "sg:phone":"+41 33 853 23 66",
    "sg:postcode":"3818",
    "sg:province":"Bern",
    "wof:name":"Kaspar Sterchi Advokatur-& Notariatsb\u00fcro",
    "wof:placetype":"venue"
},
  "geometry": {"coordinates":[8.057785,46.628681],"type":"Point"}
}