{
  "type": "Feature",
  "properties": {
    "iso:country":"CH",
    "sg:address":"Kehrsitenstrasse 7",
    "sg:city":"Stansstad",
    "sg:orig_category":"Verlegen von Fliesen U Platten",
    "sg:phone":"+41 41 610 83 21",
    "sg:postcode":"6362",
    "sg:province":"Nidwalden",
    "wof:name":"Klein Josef",
    "wof:placetype":"venue"
},
  "geometry": {"coordinates":[8.338850975,46.9797554016],"type":"Point"}
}