{
  "type": "Feature",
  "properties": {
    "iso:country":"CH",
    "sg:address":"Waldweg 16",
    "sg:city":"Aarwangen",
    "sg:orig_category":"Vorschulen, Kinderg\u00e4rten",
    "sg:phone":"+41 62 922 06 43",
    "sg:postcode":"4912",
    "sg:province":"Bern",
    "wof:name":"Kindergarten Mumenthal",
    "wof:placetype":"venue"
},
  "geometry": {"coordinates":[7.7822341919,47.2338409424],"type":"Point"}
}