{
  "type": "Feature",
  "properties": {
    "iso:country":"CH",
    "sg:address":"Marchbachstrasse 9",
    "sg:city":"Ettingen",
    "sg:orig_category":"Sportvereine Eissport Curling",
    "sg:phone":"+41 61 721 46 59",
    "sg:postcode":"4107",
    "sg:province":"Basel-Landschaft",
    "wof:name":"C.c.basel-ice-fleas",
    "wof:placetype":"venue"
},
  "geometry": {"coordinates":[7.5499401093,47.4870605469],"type":"Point"}
}