{
  "type": "Feature",
  "properties": {
    "addr:full":"Marktplatz 6 Laufenburg Aargau 5080",
    "addr:housenumber":"6",
    "addr:postcode":"5080",
    "addr:street":"Marktplatz",
    "iso:country":"CH",
    "sg:address":"Marktplatz 6",
    "sg:city":"Laufenburg",
    "sg:orig_category":"Arztpraxen",
    "sg:phone":"+41 62 874 10 59",
    "sg:postcode":"5080",
    "sg:province":"Aargau",
    "wof:name":"Dr.med.josef Untern\u00e4hrer Arzt F.allgemeine Medizin Fmh",
    "wof:placetype":"venue"
},
  "geometry": {"coordinates":[8.061528,47.562672],"type":"Point"}
}