{
  "type": "Feature",
  "properties": {
    "iso:country":"CH",
    "sg:address":"Beethovenstrasse 5",
    "sg:city":"Z\u00fcrich",
    "sg:orig_category":"Reiseb\u00fcros U Reiseveranstalter",
    "sg:postcode":"8002",
    "sg:province":"Z\u00fcrich",
    "wof:name":"Hrg Hotel Representation Gmbh",
    "wof:placetype":"venue"
},
  "geometry": {"coordinates":[8.5372972488,47.3652038574],"type":"Point"}
}