{
  "type": "Feature",
  "properties": {
    "iso:country":"CH",
    "sg:address":"1063",
    "sg:city":"Chapelle-s-moudon",
    "sg:orig_category":"Mechanische Werkst\u00e4tten",
    "sg:phone":"+41 21 905 17 11",
    "sg:postcode":"1063",
    "sg:province":"Vaud",
    "wof:name":"R\u00e9my Vulliens Atelier M\u00e9canique",
    "wof:placetype":"venue"
},
  "geometry": {"coordinates":[6.737195015,46.6686592102],"type":"Point"}
}