{
  "type": "Feature",
  "properties": {
    "iso:country":"CH",
    "sg:address":"Rue Du Grand-verger 9",
    "sg:city":"Martigny",
    "sg:classifiers":[
        {
            "category":"Bars & Pubs",
            "type":"Food & Drink"
        }
    ],
    "sg:phone":"+41 27 722 87 98",
    "sg:postcode":"1920",
    "sg:province":"Valais",
    "wof:name":"Regis Bar",
    "wof:placetype":"venue"
},
  "geometry": {"coordinates":[7.076647,46.101688],"type":"Point"}
}