{
  "type": "Feature",
  "properties": {
    "iso:country":"CH",
    "sg:address":"Via San Martino 20 6850 Mendrisio. Postfach Caselle Postale 275",
    "sg:city":"Mendrisio",
    "sg:orig_category":"Herstellung von Elektromotoren, Generatoren U Transformatoren Herstellung von sonstigen Kunststoffwa",
    "sg:phone":"+41 55 221 41 05",
    "sg:postcode":"6850",
    "sg:province":"Ticino",
    "wof:name":"Weidmann Transformerboard Systems Ag",
    "wof:placetype":"venue"
},
  "geometry": {"coordinates":[8.8242368698,47.2275047302],"type":"Point"}
}