{
  "type": "Feature",
  "properties": {
    "iso:country":"CH",
    "sg:address":"Cit\u00e9 Vieusseux 8 1203 Gen\u00e8ve. Postfach",
    "sg:city":"Gen\u00e8ve",
    "sg:orig_category":"Erschliessung von Grundst\u00fccken",
    "sg:postcode":"1201",
    "sg:province":"Gen\u00e8ve",
    "wof:name":"Soci\u00e9t\u00e9 Coop\u00e9rative Les Ch\u00eanes Verts",
    "wof:placetype":"venue"
},
  "geometry": {"coordinates":[6.1197271347,46.213394165],"type":"Point"}
}