{
  "type": "Feature",
  "properties": {
    "iso:country":"CH",
    "sg:address":"Haldensteig 581",
    "sg:city":"Leuggern",
    "sg:orig_category":"Wirtschaftspr\u00fcfung, Steuerberatung U Treuhand",
    "sg:postcode":"5316",
    "sg:province":"Aargau",
    "wof:name":"Sht Schweizerische Hotel Treuhand Ag, Zweigniederlassung St. Moritz",
    "wof:placetype":"venue"
},
  "geometry": {"coordinates":[9.8381900787,46.4970588684],"type":"Point"}
}