{
  "type": "Feature",
  "properties": {
    "iso:country":"CH",
    "sg:address":"Weidenweg 215",
    "sg:city":"Glis",
    "sg:orig_category":"Unternehmensberatung",
    "sg:phone":"+41 27 922 47 11",
    "sg:postcode":"3902",
    "sg:province":"Valais",
    "wof:name":"Fib Freizeit Gmbh",
    "wof:placetype":"venue"
},
  "geometry": {"coordinates":[7.9668960571,46.3104515076],"type":"Point"}
}