{
  "type": "Feature",
  "properties": {
    "iso:country":"CH",
    "sg:address":"Wehntalerstrasse 502 8046 Z\u00fcrich. Postfach",
    "sg:city":"Z\u00fcrich",
    "sg:orig_category":"Herstellung von sonstigen keramischen Erzeugnissen f\u00fcr technische Zwecke",
    "sg:phone":"+41 13711369",
    "sg:postcode":"8046",
    "sg:province":"Z\u00fcrich",
    "wof:name":"Baukeramik Pantovic",
    "wof:placetype":"venue"
},
  "geometry": {"coordinates":[8.5098781586,47.4178581238],"type":"Point"}
}