{
  "type": "Feature",
  "properties": {
    "iso:country":"CH",
    "sg:address":"Beundengasse 9",
    "sg:city":"Lyss",
    "sg:orig_category":"Herstellung von Tanks U Sammelbeh\u00e4ltern aus Metall Schlossereien",
    "sg:phone":"+41 32 385 22 02",
    "sg:postcode":"3250",
    "sg:province":"Bern",
    "wof:name":"Alfred Hirter Tankrevisionen Schlosserei",
    "wof:placetype":"venue"
},
  "geometry": {"coordinates":[7.3008599281,47.0729904175],"type":"Point"}
}