{
  "type": "Feature",
  "properties": {
    "iso:country":"CH",
    "sg:address":"Talacker 50",
    "sg:city":"Z\u00fcrich",
    "sg:orig_category":"Herstellung von Duft U K\u00f6rperpflegemitteln",
    "sg:postcode":"8001",
    "sg:province":"Z\u00fcrich",
    "wof:name":"Take Off Hair And Beauty Ag",
    "wof:placetype":"venue"
},
  "geometry": {"coordinates":[8.3142662048,46.9925308228],"type":"Point"}
}