{
  "type": "Feature",
  "properties": {
    "iso:country":"CH",
    "sg:address":"Untertor 39 8401 Winterthur. Postfach 1241",
    "sg:city":"Winterthur",
    "sg:orig_category":"Fachdetailhandel mit pharmazeutischen Produkten",
    "sg:phone":"+41 52 269 08 51",
    "sg:postcode":"8401",
    "sg:province":"Z\u00fcrich",
    "wof:name":"Dr. U. Reinhard Ag",
    "wof:placetype":"venue"
},
  "geometry": {"coordinates":[8.7240457535,47.4990272522],"type":"Point"}
}