{
  "type": "Feature",
  "properties": {
    "iso:country":"CH",
    "sg:address":"Schmidgasse 10 6300 Zug. Postfach 305",
    "sg:city":"Zug",
    "sg:orig_category":"Sonstiger Fachdetailhandel mit Nahrungsmitteln, Getr\u00e4nken U Tabak in Verkaufsr\u00e4umen",
    "sg:phone":"+41 41 711 08 69",
    "sg:postcode":"6301",
    "sg:province":"Zug",
    "wof:name":"M\u00fcller Reformhaus Ag",
    "wof:placetype":"venue"
},
  "geometry": {"coordinates":[8.5146570206,47.1692085266],"type":"Point"}
}