{
  "type": "Feature",
  "properties": {
    "addr:full":"Enzbergh\u00f6he 14 Gipf-oberfrick Aargau 5073",
    "addr:housenumber":"14",
    "addr:postcode":"5073",
    "addr:street":"Enzberghoehe",
    "iso:country":"CH",
    "sg:address":"Enzbergh\u00f6he 14",
    "sg:city":"Gipf-oberfrick",
    "sg:orig_category":"Architekturb\u00fcros",
    "sg:phone":"+41 55 240 12 29",
    "sg:postcode":"5073",
    "sg:province":"Aargau",
    "wof:name":"Peter Gutersohn Architekturb\u00fcro",
    "wof:placetype":"venue"
},
  "geometry": {"coordinates":[8.84042,47.255711],"type":"Point"}
}