{
  "type": "Feature",
  "properties": {
    "iso:country":"CH",
    "sg:address":"Rue Du Tilleul 2",
    "sg:city":"St-blaise",
    "sg:classifiers":[
        {
            "category":"Restaurant",
            "type":"Food & Drink"
        }
    ],
    "sg:phone":"+41 32 753 34 05",
    "sg:postcode":"2072",
    "sg:province":"Neuch\u00e2tel",
    "wof:name":"Restaurant Le Montagnard",
    "wof:placetype":"venue"
},
  "geometry": {"coordinates":[6.9905190468,47.0155525208],"type":"Point"}
}