{
  "type": "Feature",
  "properties": {
    "iso:country":"CH",
    "sg:address":"Hauptstrasse 44",
    "sg:city":"Niedererlinsbach",
    "sg:orig_category":"Herstellung von konfektionierten Textilwaren ohne Bekleidung",
    "sg:phone":"+41 62 844 22 29",
    "sg:postcode":"5015",
    "sg:province":"Solothurn",
    "wof:name":"Villiger Willy",
    "wof:placetype":"venue"
},
  "geometry": {"coordinates":[8.0084552765,47.4001083374],"type":"Point"}
}