{
  "type": "Feature",
  "properties": {
    "iso:country":"CH",
    "sg:address":"Kantonsstrasse 81",
    "sg:city":"Reichenburg",
    "sg:orig_category":"G\u00fcterbef\u00f6rderung im Strassenverkehr",
    "sg:postcode":"8864",
    "sg:province":"Schwyz",
    "wof:name":"Senn & Riedi, Transporte Und Kanalisationsreinigung.",
    "wof:placetype":"venue"
},
  "geometry": {"coordinates":[8.6629972458,46.874671936],"type":"Point"}
}