{
  "type": "Feature",
  "properties": {
    "iso:country":"CH",
    "sg:address":"Bachstrasse 20",
    "sg:city":"Kreuzlingen",
    "sg:orig_category":"Physiotherapie",
    "sg:phone":"+41 71 385 45 67",
    "sg:postcode":"8280",
    "sg:province":"Thurgau",
    "wof:name":"Physiomed Gossau J.j. Wammes & I. Forster",
    "wof:placetype":"venue"
},
  "geometry": {"coordinates":[9.2520866394,47.4167671204],"type":"Point"}
}