{
  "type": "Feature",
  "properties": {
    "iso:country":"CH",
    "sg:address":"Gundeldinger Str.",
    "sg:city":"Basel",
    "sg:orig_category":"Medizin, Medizinische Beratung",
    "sg:phone":"+41 61 367 93 67",
    "sg:postcode":"4050",
    "wof:name":"Precon",
    "wof:placetype":"venue"
},
  "geometry": {"coordinates":[7.582315,47.543625],"type":"Point"}
}