{
  "type": "Feature",
  "properties": {
    "addr:full":"Route Du Lavapesson 1 Granges-paccot Fribourg 1763",
    "addr:housenumber":"1",
    "addr:postcode":"1763",
    "addr:street":"Route Du Lavapesson",
    "iso:country":"CH",
    "sg:address":"Route Du Lavapesson 1",
    "sg:city":"Granges-paccot",
    "sg:orig_category":"Architektur U Ingenieurb\u00fcros",
    "sg:phone":"+41 26 466 64 40",
    "sg:postcode":"1763",
    "sg:province":"Fribourg",
    "wof:name":"Hans Krieg Bureau D'ing\u00e9nieurs",
    "wof:placetype":"venue"
},
  "geometry": {"coordinates":[7.149897,46.821884],"type":"Point"}
}