{
  "type": "Feature",
  "properties": {
    "iso:country":"CH",
    "sg:address":"Rue Du Patinage 4 2114 Fleurier. Postfach",
    "sg:city":"Fleurier",
    "sg:orig_category":"Vermietung U Verpachtung von eigenen Immobilien",
    "sg:postcode":"2114",
    "sg:province":"Neuch\u00e2tel",
    "wof:name":"Patinvest S\u00e0rl",
    "wof:placetype":"venue"
},
  "geometry": {"coordinates":[6.5769047737,46.9047012329],"type":"Point"}
}