{
  "type": "Feature",
  "properties": {
    "iso:country":"CH",
    "sg:address":"Somplatz Via 63 7512 Champf\u00e8r. Postfach",
    "sg:city":"Champf\u00e8r",
    "sg:orig_category":"Vermietung U Verpachtung von eigenen Immobilien",
    "sg:postcode":"7512",
    "sg:province":"Graubunden",
    "wof:name":"Immobiliengesellschaft Va\u00fcglia Ag",
    "wof:placetype":"venue"
},
  "geometry": {"coordinates":[9.8129501343,46.4796867371],"type":"Point"}
}