{
  "type": "Feature",
  "properties": {
    "iso:country":"CH",
    "sg:address":"Sihlquai 253 8005 Z\u00fcrich. Postfach",
    "sg:city":"Z\u00fcrich",
    "sg:orig_category":"Allgemeiner Hoch U Tiefbau",
    "sg:postcode":"8001",
    "sg:province":"Z\u00fcrich",
    "wof:name":"Concept 3000 S\u00e0rl",
    "wof:placetype":"venue"
},
  "geometry": {"coordinates":[7.58311,46.21003],"type":"Point"}
}