{
  "type": "Feature",
  "properties": {
    "iso:country":"CH",
    "sg:address":"Pfefferg\u00e4sslein 12 4051 Basel. Postfach",
    "sg:city":"Basel",
    "sg:orig_category":"Vermietung U Verpachtung von eigenen Immobilien",
    "sg:postcode":"4051",
    "sg:province":"Basel-Stadt",
    "wof:name":"Pegase Stifruz Sa",
    "wof:placetype":"venue"
},
  "geometry": {"coordinates":[6.857986927,46.9656143188],"type":"Point"}
}