{
  "type": "Feature",
  "properties": {
    "addr:full":"Alte Kantonsstrasse 45 B\u00fcron Luzern 6233",
    "addr:housenumber":"45",
    "addr:postcode":"6233",
    "addr:street":"Alte Kantonsstrasse",
    "iso:country":"CH",
    "sg:address":"Alte Kantonsstrasse 45",
    "sg:city":"B\u00fcron",
    "sg:orig_category":"Autotransporte M\u00f6bel Autotransporte international",
    "sg:phone":"+41 41 933 20 10",
    "sg:postcode":"6233",
    "sg:province":"Luzern",
    "wof:name":"Urs Fischer Transporte & Umz\u00fcge",
    "wof:placetype":"venue"
},
  "geometry": {"coordinates":[8.101767,47.206821],"type":"Point"}
}