{
  "type": "Feature",
  "properties": {
    "iso:country":"CH",
    "sg:address":"Winkelb\u00fchl 4",
    "sg:city":"Adligenswil",
    "sg:orig_category":"Sonstige Kultur U Unterhaltungseinrichtungen",
    "sg:postcode":"6043",
    "sg:province":"Luzern",
    "wof:name":"Rodenhausen-haldimann Ruth Mobile Raum F\u00fcr Bewegung Und Begegnung",
    "wof:placetype":"venue"
},
  "geometry": {"coordinates":[8.3792352676,47.0725250244],"type":"Point"}
}