{
  "type": "Feature",
  "properties": {
    "iso:country":"CH",
    "sg:address":"Sommergasse 6",
    "sg:city":"Witterswil",
    "sg:orig_category":"Vermietung von Gebrauchsg\u00fctern",
    "sg:postcode":"4108",
    "sg:province":"Solothurn",
    "wof:name":"Mepro, Endrass & Co",
    "wof:placetype":"venue"
},
  "geometry": {"coordinates":[7.5298500061,47.485118866],"type":"Point"}
}