{
  "type": "Feature",
  "properties": {
    "iso:country":"CH",
    "sg:address":"St\u00e4dtle 33",
    "sg:city":"Vaduz",
    "sg:orig_category":"Detailhandel mit Schuhen",
    "sg:phone":"+423 232 12 17",
    "sg:postcode":"9490",
    "wof:name":"Rechsteiner Ag Schuhe & Sport",
    "wof:placetype":"venue"
},
  "geometry": {"coordinates":[9.5228013992,47.1393203735],"type":"Point"}
}