{
  "type": "Feature",
  "properties": {
    "iso:country":"CH",
    "sg:address":"Fachstrasse 68",
    "sg:city":"Oberrieden",
    "sg:orig_category":"Gartenbau",
    "sg:phone":"+41 17208240",
    "sg:postcode":"8942",
    "sg:province":"Z\u00fcrich",
    "wof:name":"Ursula Schmocker Gartenarchitektin",
    "wof:placetype":"venue"
},
  "geometry": {"coordinates":[8.5812110901,47.2733001709],"type":"Point"}
}