{
  "type": "Feature",
  "properties": {
    "iso:country":"CH",
    "sg:address":"Schlossweg 1",
    "sg:city":"Uster",
    "sg:orig_category":"Hochschulen U h\u00f6here Ausbildung Primarschulen",
    "sg:phone":"+41 19420704",
    "sg:postcode":"8610",
    "sg:province":"Z\u00fcrich",
    "wof:name":"Schloss-schule Uster",
    "wof:placetype":"venue"
},
  "geometry": {"coordinates":[8.7182531357,47.3452415466],"type":"Point"}
}