{
  "type": "Feature",
  "properties": {
    "iso:country":"CH",
    "sg:address":"Reussinsel 52",
    "sg:city":"Luzern",
    "sg:orig_category":"Offsetdruck",
    "sg:phone":"+41 41 240 68 22",
    "sg:postcode":"6003",
    "sg:province":"Luzern",
    "wof:name":"Josef Theiler Druckerei",
    "wof:placetype":"venue"
},
  "geometry": {"coordinates":[8.2881803513,47.055480957],"type":"Point"}
}