{
  "type": "Feature",
  "properties": {
    "iso:country":"CH",
    "sg:address":"Galgenried 4",
    "sg:city":"Stans",
    "sg:classifiers":[
        {
            "category":"Shopping",
            "subcategory":"Computers & Home Electronics",
            "type":"Retail Goods"
        }
    ],
    "sg:phone":"+41 41 612 11 88",
    "sg:postcode":"6370",
    "sg:province":"Nidwalden",
    "sg:tags":[
        "caravan",
        "vehicles",
        "motor",
        "camping",
        "homes"
    ],
    "wof:name":"Jakober Usa-wohnmobile Ag",
    "wof:placetype":"venue"
},
  "geometry": {"coordinates":[8.3450098038,46.9685554504],"type":"Point"}
}