{
  "type": "Feature",
  "properties": {
    "iso:country":"CH",
    "sg:address":"Rorschacher Strasse 13",
    "sg:city":"St.gallen",
    "sg:orig_category":"Grosshandel mit Textilien",
    "sg:phone":"+41 71 245 16 51",
    "sg:postcode":"9000",
    "sg:province":"St. Gallen",
    "wof:name":"Filadoro-tanner R. & A.",
    "wof:placetype":"venue"
},
  "geometry": {"coordinates":[9.3793611526,47.4264564514],"type":"Point"}
}