{
  "type": "Feature",
  "properties": {
    "iso:country":"CH",
    "sg:address":"M\u00fchlenplatz 1",
    "sg:city":"Luzern",
    "sg:orig_category":"Detailhandel mit Brillen U anderen Sehhilfen Fachdetailhandel in Verkaufsr\u00e4umen",
    "sg:phone":"+41 41 410 38 38",
    "sg:postcode":"6004",
    "sg:province":"Luzern",
    "wof:name":"G\u00f6tti & Niederer Ag",
    "wof:placetype":"venue"
},
  "geometry": {"coordinates":[8.303635,47.05191],"type":"Point"}
}