{
  "type": "Feature",
  "properties": {
    "iso:country":"CH",
    "sg:address":"Chemin De L'arzelier 14",
    "sg:city":"Chexbres",
    "sg:orig_category":"Sportvereine Ski",
    "sg:postcode":"1071",
    "sg:province":"Vaud",
    "wof:name":"Ski-club St-saphorin-rivaz",
    "wof:placetype":"venue"
},
  "geometry": {"coordinates":[6.7762298584,46.4821090698],"type":"Point"}
}