{
  "type": "Feature",
  "properties": {
    "iso:country":"CH",
    "sg:address":"Zentrumsweg 10",
    "sg:city":"Rothrist",
    "sg:orig_category":"G\u00fcterbef\u00f6rderung im Strassenverkehr",
    "sg:phone":"+41 62 794 39 89",
    "sg:postcode":"4852",
    "sg:province":"Aargau",
    "wof:name":"Charles Reinhard Transporte",
    "wof:placetype":"venue"
},
  "geometry": {"coordinates":[7.890296936,47.3065986633],"type":"Point"}
}