{
  "type": "Feature",
  "properties": {
    "iso:country":"CH",
    "sg:address":"Aproz 1997 Haute-nendaz. Postfach",
    "sg:city":"Aproz",
    "sg:orig_category":"Grosshandel mit Obst U Gem\u00fcse",
    "sg:postcode":"1994",
    "sg:province":"Valais",
    "wof:name":"Clerc Louis, Fruits",
    "wof:placetype":"venue"
},
  "geometry": {"coordinates":[7.2981119156,46.1841583252],"type":"Point"}
}