{
  "type": "Feature",
  "properties": {
    "iso:country":"CH",
    "sg:address":"Bahnhofstrasse 54 8001 Z\u00fcrich. Postfach",
    "sg:city":"Z\u00fcrich",
    "sg:orig_category":"Personal U Stellenvermittlung Unternehmensberatung",
    "sg:phone":"+41 19054000",
    "sg:postcode":"8001",
    "sg:province":"Z\u00fcrich",
    "wof:name":"B\u00fcchi Personal",
    "wof:placetype":"venue"
},
  "geometry": {"coordinates":[8.7225141525,47.3526268005],"type":"Point"}
}