{
  "type": "Feature",
  "properties": {
    "iso:country":"CH",
    "sg:address":"Gerichtshausstrasse 14",
    "sg:city":"Glarus",
    "sg:orig_category":"Herstellung von Teppichen",
    "sg:phone":"+41 55 610 39 04",
    "sg:postcode":"8750",
    "sg:province":"Glarus",
    "wof:name":"Urs Seliner, Teppiche Bodenbel\u00e4ge Parkett",
    "wof:placetype":"venue"
},
  "geometry": {"coordinates":[9.0678367615,47.0420608521],"type":"Point"}
}