{
  "type": "Feature",
  "properties": {
    "iso:country":"CH",
    "sg:address":"Mittlerfeld Stanserstrasse",
    "sg:city":"Stansstad",
    "sg:orig_category":"Haltung von Schweinen",
    "sg:phone":"+41 41 610 11 34",
    "sg:postcode":"6362",
    "sg:province":"Nidwalden",
    "wof:name":"Julius Zemp Schweinezucht",
    "wof:placetype":"venue"
},
  "geometry": {"coordinates":[8.3469295502,46.9725265503],"type":"Point"}
}