{
  "type": "Feature",
  "properties": {
    "iso:country":"CH",
    "sg:address":"Carra Dei Nasi 18",
    "sg:city":"Ascona",
    "sg:orig_category":"Vereine K\u00fcnstler",
    "sg:phone":"+41 31 311 09 44",
    "sg:postcode":"6612",
    "sg:province":"Ticino",
    "wof:name":"Bernische Kunstgesellschaft",
    "wof:placetype":"venue"
},
  "geometry": {"coordinates":[7.4429159164,46.9512062073],"type":"Point"}
}