{
  "type": "Feature",
  "properties": {
    "iso:country":"CH",
    "sg:address":"M\u00fchlfangstrasse 16 8583 Sulgen. Postfach",
    "sg:city":"Sulgen",
    "sg:orig_category":"Grosshandel mit B\u00fcromaschinen Grosshandel mit Datenverarbeitungsger\u00e4ten",
    "sg:phone":"+41 71 622 84 77",
    "sg:postcode":"8583",
    "sg:province":"Thurgau",
    "wof:name":"Informa Maasl M.",
    "wof:placetype":"venue"
},
  "geometry": {"coordinates":[9.1835622787,47.5399246216],"type":"Point"}
}