{
  "type": "Feature",
  "properties": {
    "iso:country":"CH",
    "sg:address":"Schachenstrasse 6",
    "sg:city":"Gretzenbach",
    "sg:orig_category":"Instandhaltung U Reparatur von Automobilen",
    "sg:phone":"+41 62 291 10 09",
    "sg:postcode":"5014",
    "sg:province":"Solothurn",
    "wof:name":"Stern-garage Achermann",
    "wof:placetype":"venue"
},
  "geometry": {"coordinates":[7.9832181931,47.3603210449],"type":"Point"}
}