{
  "type": "Feature",
  "properties": {
    "iso:country":"CH",
    "sg:address":"Holzwiesstrasse 37",
    "sg:city":"Jona",
    "sg:orig_category":"Grosshandel mit Software Softwareentwicklung U beratung",
    "sg:phone":"+41 55 225 39 00",
    "sg:postcode":"8645",
    "sg:province":"St. Gallen",
    "wof:name":"De Simone & Osswald Ag Software-architekten",
    "wof:placetype":"venue"
},
  "geometry": {"coordinates":[8.8376207352,47.2355575562],"type":"Point"}
}