{
  "type": "Feature",
  "properties": {
    "iso:country":"CH",
    "sg:address":"Sihlstrasse 61",
    "sg:city":"Z\u00fcrich",
    "sg:orig_category":"Berufsorganisationen Wirtschafts U Arbeitgeberverb\u00e4nde",
    "sg:postcode":"8001",
    "sg:province":"Z\u00fcrich",
    "wof:name":"Schweizerischer Berufsverband F\u00fcr Craniosacral-therapie",
    "wof:placetype":"venue"
},
  "geometry": {"coordinates":[8.533288,47.372414],"type":"Point"}
}