{
  "type": "Feature",
  "properties": {
    "iso:country":"CH",
    "sg:address":"Dorf",
    "sg:city":"R\u00fcegsau",
    "sg:orig_category":"Herstellung von Frischmilchprodukten Verwertung von Milch",
    "sg:phone":"+41 34 461 66 39",
    "sg:postcode":"3417",
    "sg:province":"Bern",
    "wof:name":"Milch-land Ag",
    "wof:placetype":"venue"
},
  "geometry": {"coordinates":[7.6723399162,47.0248985291],"type":"Point"}
}