{
  "type": "Feature",
  "properties": {
    "iso:country":"CH",
    "sg:address":"Ringstrasse 37",
    "sg:city":"Chur",
    "sg:orig_category":"Non-Classified Establishments",
    "sg:postcode":"7000",
    "sg:province":"Graubunden",
    "wof:name":"B\u00e4nziger + K\u00f6ppel + Br\u00e4ndli + Partner, Ingenieure + Planer Sia Usic, Diplomingenieure Eth",
    "wof:placetype":"venue"
},
  "geometry": {"coordinates":[9.5151882172,46.8547096252],"type":"Point"}
}