{
  "type": "Feature",
  "properties": {
    "addr:full":"Route De Jussy 4b Th\u00f4nex Gen\u00e8ve 1226",
    "addr:housenumber":"4b",
    "addr:postcode":"1226",
    "addr:street":"Route De Jussy",
    "iso:country":"CH",
    "sg:address":"Route De Jussy 4b",
    "sg:city":"Th\u00f4nex",
    "sg:orig_category":"Arztpraxen",
    "sg:phone":"+41 79 213 89 47",
    "sg:postcode":"1226",
    "sg:province":"Gen\u00e8ve",
    "wof:name":"Dr M\u00e9d. Guy Mi\u00e9ville M\u00e9decin G\u00e9n\u00e9raliste",
    "wof:placetype":"venue"
},
  "geometry": {"coordinates":[6.856335,46.453423],"type":"Point"}
}