{
  "type": "Feature",
  "properties": {
    "iso:country":"CH",
    "sg:address":"Hintergasse 6 8335 Hittnau. Postfach",
    "sg:city":"Hittnau",
    "sg:orig_category":"Herstellung von elektrischen Lampen U Leuchten",
    "sg:postcode":"8335",
    "sg:province":"Z\u00fcrich",
    "wof:name":"Preid Eventtechnik",
    "wof:placetype":"venue"
},
  "geometry": {"coordinates":[8.8205499649,47.36951828],"type":"Point"}
}