{
  "type": "Feature",
  "properties": {
    "iso:country":"CH",
    "sg:address":"Baslerstrasse 4",
    "sg:city":"Allschwil",
    "sg:orig_category":"Non-Classified Establishments",
    "sg:postcode":"4123",
    "sg:province":"Basel-Landschaft",
    "wof:name":"Restaurant Landhus, Myrta Leopold",
    "wof:placetype":"venue"
},
  "geometry": {"coordinates":[7.5370121002,47.5511207581],"type":"Point"}
}