{
  "type": "Feature",
  "properties": {
    "iso:country":"CH",
    "sg:address":"Witikonerstrasse 289 8053 Z\u00fcrich. Postfach 265",
    "sg:city":"Z\u00fcrich",
    "sg:orig_category":"Mit dem Versicherungsgewerbe verbundene T\u00e4tigkeiten",
    "sg:phone":"+41 31 984 10 15",
    "sg:postcode":"8053",
    "sg:province":"Z\u00fcrich",
    "wof:name":"Nva Planungs Gmbh",
    "wof:placetype":"venue"
},
  "geometry": {"coordinates":[7.375688076,46.9228172302],"type":"Point"}
}