{
  "type": "Feature",
  "properties": {
    "iso:country":"CH",
    "sg:address":"Rue De-grenus 1",
    "sg:city":"Gen\u00e8ve",
    "sg:orig_category":"Grosshandel mit medizinischen U orthop\u00e4dischen Artikeln Herstellung von medizinischen U chirurgische",
    "sg:phone":"+41 22 731 81 31",
    "sg:postcode":"1201",
    "sg:province":"Gen\u00e8ve",
    "wof:name":"Arteromed Sa",
    "wof:placetype":"venue"
},
  "geometry": {"coordinates":[6.1415538788,46.2061004639],"type":"Point"}
}