{
  "type": "Feature",
  "properties": {
    "iso:country":"CH",
    "sg:address":"Route De Berne 26",
    "sg:city":"Lausanne",
    "sg:orig_category":"HOTELS: OHNE RESTAURANT",
    "sg:phone":"+41 21 652 17 98",
    "sg:postcode":"1010",
    "sg:province":"Vaud",
    "wof:name":"Pension Delaunay Yolande",
    "wof:placetype":"venue"
},
  "geometry": {"coordinates":[6.6488370895,46.536315918],"type":"Point"}
}