{
  "type": "Feature",
  "properties": {
    "iso:country":"CH",
    "sg:address":"Weinbergstrasse 24",
    "sg:city":"Z\u00fcrich",
    "sg:orig_category":"Herstellung von medizinischen U chirurgischen Ger\u00e4ten sowie orthop\u00e4dischen Vorrichtungen",
    "sg:phone":"+41 12521544",
    "sg:postcode":"8001",
    "sg:province":"Z\u00fcrich",
    "wof:name":"Yanku Erol Zahntechniker",
    "wof:placetype":"venue"
},
  "geometry": {"coordinates":[8.5444946289,47.3783416748],"type":"Point"}
}