{
  "type": "Feature",
  "properties": {
    "iso:country":"CH",
    "sg:address":"Gostel",
    "sg:city":"Vinelz",
    "sg:classifiers":[
        {
            "category":"Travel",
            "subcategory":"Hotels & Motels",
            "type":"Entertainment"
        }
    ],
    "sg:phone":"+41 32 338 11 24",
    "sg:postcode":"3234",
    "sg:province":"Bern",
    "sg:tags":[
        "hotels",
        "mit",
        "restaurant"
    ],
    "wof:name":"Ramseier Roger",
    "wof:placetype":"venue"
},
  "geometry": {"coordinates":[7.1061201096,47.0344238281],"type":"Point"}
}