{
  "type": "Feature",
  "properties": {
    "iso:country":"CH",
    "sg:address":"Balierestrasse 6",
    "sg:city":"Frauenfeld",
    "sg:orig_category":"RESTAURANTS: TEA-ROOMS",
    "sg:phone":"+41 52 720 17 17",
    "sg:postcode":"8500",
    "sg:province":"Thurgau",
    "wof:name":"Sasso Carlo",
    "wof:placetype":"venue"
},
  "geometry": {"coordinates":[8.8957357407,47.5550537109],"type":"Point"}
}