{
  "type": "Feature",
  "properties": {
    "iso:country":"CH",
    "sg:address":"1041",
    "sg:city":"Bettens",
    "sg:orig_category":"Grosshandel mit Getreide, Saatgut U Futtermitteln",
    "sg:phone":"+41 19947227",
    "sg:postcode":"1041",
    "sg:province":"Vaud",
    "wof:name":"Rovagro Sa Landwirtschaftliche Artikel",
    "wof:placetype":"venue"
},
  "geometry": {"coordinates":[6.5762720108,46.6268310547],"type":"Point"}
}