{
  "type": "Feature",
  "properties": {
    "iso:country":"CH",
    "sg:address":"Avenue De Pratifori 8",
    "sg:city":"Sion",
    "sg:orig_category":"Allgemeiner Hoch U Tiefbau",
    "sg:phone":"+41 27 322 17 75",
    "sg:postcode":"1950",
    "sg:province":"Valais",
    "wof:name":"Fasanino Jean",
    "wof:placetype":"venue"
},
  "geometry": {"coordinates":[7.357297,46.231312],"type":"Point"}
}