{
  "type": "Feature",
  "properties": {
    "iso:country":"CH",
    "sg:address":"Weberstrasse 11a",
    "sg:city":"Aarburg",
    "sg:orig_category":"Herstellung von Textilbekleidung Herstellung von konfektionierten Textilwaren ohne Bekleidung",
    "sg:phone":"+41 71 672 48 38",
    "sg:postcode":"4663",
    "sg:province":"Aargau",
    "wof:name":"Schiesser Schweiz Ag",
    "wof:placetype":"venue"
},
  "geometry": {"coordinates":[9.1749706268,47.6517753601],"type":"Point"}
}