{
  "type": "Feature",
  "properties": {
    "iso:country":"CH",
    "sg:address":"Champy Rue De 41 1632 Riaz. Postfach",
    "sg:city":"Riaz",
    "sg:orig_category":"Allgemeiner Hoch U Tiefbau",
    "sg:postcode":"1632",
    "sg:province":"Fribourg",
    "wof:name":"D & D Constructions S\u00e0rl",
    "wof:placetype":"venue"
},
  "geometry": {"coordinates":[7.056412,46.636642],"type":"Point"}
}