{
  "type": "Feature",
  "properties": {
    "iso:country":"CH",
    "sg:address":"Planches Avenue Des 22",
    "sg:city":"Montreux",
    "sg:orig_category":"Pensionskassen",
    "sg:postcode":"1820",
    "sg:province":"Vaud",
    "wof:name":"Fonds De Pr\u00e9voyance En Faveur Du Personnel De La Sa Efap Sa",
    "wof:placetype":"venue"
},
  "geometry": {"coordinates":[6.8840880394,46.9836235046],"type":"Point"}
}