{
  "type": "Feature",
  "properties": {
    "iso:country":"CH",
    "sg:address":"Dreilindenstrasse 35",
    "sg:city":"Meggen",
    "sg:orig_category":"Non-Classified Establishments",
    "sg:phone":"+41 62 765 55 55",
    "sg:postcode":"6045",
    "sg:province":"Luzern",
    "wof:name":"Villiger S\u00f6hne Holding Ag",
    "wof:placetype":"venue"
},
  "geometry": {"coordinates":[8.1618499756,47.247089386],"type":"Point"}
}