{
  "type": "Feature",
  "properties": {
    "iso:country":"CH",
    "sg:address":"Chemin Du Champ-des-filles 35",
    "sg:city":"Plan-les-ouates",
    "sg:orig_category":"Instandhaltung U Reparatur von Automobilen",
    "sg:phone":"+41 71 923 44 22",
    "sg:postcode":"1228",
    "sg:province":"Gen\u00e8ve",
    "wof:name":"Carrosserie Kugler",
    "wof:placetype":"venue"
},
  "geometry": {"coordinates":[9.0461845398,47.4605751038],"type":"Point"}
}