{
  "type": "Feature",
  "properties": {
    "iso:country":"CH",
    "sg:address":"Ottenhausen",
    "sg:city":"Aathal-seegr\u00e4ben",
    "sg:orig_category":"Landw. Genossenschaften Alpgenossenschaften",
    "sg:phone":"+41 19321412",
    "sg:postcode":"8607",
    "sg:province":"Z\u00fcrich",
    "wof:name":"Weidengenossenschaft Gadenst\u00e4tt Martin Guyer",
    "wof:placetype":"venue"
},
  "geometry": {"coordinates":[8.7684850693,47.3358840942],"type":"Point"}
}