{
  "type": "Feature",
  "properties": {
    "iso:country":"CH",
    "sg:address":"3805",
    "sg:city":"Goldswil",
    "sg:orig_category":"Schwimmb\u00e4der",
    "sg:phone":"+41 17848429",
    "sg:postcode":"3805",
    "sg:province":"Bern",
    "wof:name":"Strandbad B\u00e4ch",
    "wof:placetype":"venue"
},
  "geometry": {"coordinates":[8.7346868515,47.2044754028],"type":"Point"}
}