{
  "type": "Feature",
  "properties": {
    "iso:country":"CH",
    "sg:address":"Dorfstrasse 11",
    "sg:city":"Grafenried",
    "sg:orig_category":"Bauschreinerei",
    "sg:phone":"+41 71 744 12 43",
    "sg:postcode":"3308",
    "sg:province":"Bern",
    "wof:name":"Nady Steiner Schreinerei",
    "wof:placetype":"venue"
},
  "geometry": {"coordinates":[9.630715,47.454006],"type":"Point"}
}