{
  "type": "Feature",
  "properties": {
    "iso:country":"CH",
    "sg:address":"Feldstrasse 6",
    "sg:city":"Herzogenbuchsee",
    "sg:orig_category":"Grosshandel mit sonstigen Halbwaren",
    "sg:phone":"+41 91 683 66 14",
    "sg:postcode":"3360",
    "sg:province":"Bern",
    "wof:name":"Ferdinando Pedrazzini Rappresentanze Cartarie",
    "wof:placetype":"venue"
},
  "geometry": {"coordinates":[9.0212497711,45.8606987],"type":"Point"}
}