{
  "type": "Feature",
  "properties": {
    "iso:country":"CH",
    "sg:address":"Karl-neuhaus-strasse 11",
    "sg:city":"Biel/bienne",
    "sg:orig_category":"Zahntechnische Laboratorien",
    "sg:phone":"+41 32 322 95 29",
    "sg:postcode":"2502",
    "sg:province":"Bern",
    "wof:name":"G\u00fcnter Metzig Zahntechnisches Labor",
    "wof:placetype":"venue"
},
  "geometry": {"coordinates":[7.2433547974,47.1381034851],"type":"Point"}
}