{
  "type": "Feature",
  "properties": {
    "iso:country":"CH",
    "sg:address":"Dorfstr. 2",
    "sg:city":"Walchwil",
    "sg:classifiers":[
        {
            "category":"Banks & Credit Unions",
            "subcategory":"Bank",
            "type":"Services"
        }
    ],
    "sg:phone":"+41 4142771376",
    "sg:postcode":"6318",
    "sg:province":"Zug",
    "wof:name":"Zuger Kantonalbank",
    "wof:placetype":"venue"
},
  "geometry": {"coordinates":[8.513305,47.100082],"type":"Point"}
}