{
  "type": "Feature",
  "properties": {
    "iso:country":"CH",
    "sg:address":"Les Epineys",
    "sg:city":"Saillon",
    "sg:orig_category":"Grosshandel mit Getr\u00e4nken Rebbau",
    "sg:phone":"+41 79 220 31 20",
    "sg:postcode":"1913",
    "sg:province":"Valais",
    "wof:name":"Pierre-antoine Crettenand Cave",
    "wof:placetype":"venue"
},
  "geometry": {"coordinates":[7.1778478622,46.1586074829],"type":"Point"}
}