{
  "type": "Feature",
  "properties": {
    "iso:country":"CH",
    "sg:address":"G\u00f6sgerstrasse 6 5012 Sch\u00f6nenwerd. Postfach",
    "sg:city":"Sch\u00f6nenwerd",
    "sg:orig_category":"Detailhandel mit Schuhen U Lederwaren",
    "sg:postcode":"5012",
    "sg:province":"Solothurn",
    "wof:name":"P.i.m.u. Kinderschuh-laden Wetter",
    "wof:placetype":"venue"
},
  "geometry": {"coordinates":[8.0018053055,47.3723945618],"type":"Point"}
}