{
  "type": "Feature",
  "properties": {
    "iso:country":"CH",
    "sg:address":"Hohlstrasse 561",
    "sg:city":"Z\u00fcrich",
    "sg:orig_category":"Detailhandel mit Waren verschiedener Art, Hauptrichtung Nahrungsmittel",
    "sg:phone":"+41 14331128",
    "sg:postcode":"8048",
    "sg:province":"Z\u00fcrich",
    "wof:name":"Ital-food Gmbh Lebensmittel-vertrieb",
    "wof:placetype":"venue"
},
  "geometry": {"coordinates":[8.4890727997,47.3906173706],"type":"Point"}
}