{
  "type": "Feature",
  "properties": {
    "addr:full":"Tell Rue Guillaume- 6 1201 Gen\u00e8ve Case Postale Gen\u00e8ve Gen\u00e8ve 1201",
    "addr:housenumber":"6",
    "addr:postcode":"1201;postale;1201",
    "addr:street":"Rue Guillaume",
    "iso:country":"CH",
    "sg:address":"Tell Rue Guillaume- 6 1201 Gen\u00e8ve Case Postale",
    "sg:city":"Gen\u00e8ve",
    "sg:orig_category":"Detailhandel mit B\u00fcchern, Zeitungen, Schreib U Papeteriewaren",
    "sg:phone":"+41 22 785 24 85",
    "sg:postcode":"1201",
    "sg:province":"Gen\u00e8ve",
    "wof:name":"Petrin, Office Shopper",
    "wof:placetype":"venue"
},
  "geometry": {"coordinates":[6.145392,46.20652],"type":"Point"}
}