{
  "type": "Feature",
  "properties": {
    "iso:country":"CH",
    "sg:address":"Breiten",
    "sg:city":"M\u00f6rel",
    "sg:orig_category":"Interessenvertretungen U sonstige Vereinigungen",
    "sg:phone":"+41 27 928 42 00",
    "sg:postcode":"3983",
    "sg:province":"Valais",
    "wof:name":"Walliser Schwingerverband",
    "wof:placetype":"venue"
},
  "geometry": {"coordinates":[8.0443487167,46.3578681946],"type":"Point"}
}