{
  "type": "Feature",
  "properties": {
    "iso:country":"CH",
    "sg:address":"Rainstrasse 13",
    "sg:city":"Riedholz",
    "sg:orig_category":"Fachdetailhandel in Verkaufsr\u00e4umen",
    "sg:postcode":"4533",
    "sg:province":"Solothurn",
    "wof:name":"Marlies Stoop",
    "wof:placetype":"venue"
},
  "geometry": {"coordinates":[9.8358945847,46.8024406433],"type":"Point"}
}