{
  "type": "Feature",
  "properties": {
    "iso:country":"CH",
    "sg:address":"8716",
    "sg:city":"Schmerikon",
    "sg:orig_category":"Vereine Gesang",
    "sg:postcode":"8716",
    "sg:province":"St. Gallen",
    "wof:name":"M\u00e4nnerchor Schmerikon",
    "wof:placetype":"venue"
},
  "geometry": {"coordinates":[8.9420604706,47.2247886658],"type":"Point"}
}