{
  "type": "Feature",
  "properties": {
    "addr:full":"1427 Bonvillars Vaud 1427",
    "addr:postcode":"1427;1427",
    "iso:country":"CH",
    "sg:address":"1427",
    "sg:city":"Bonvillars",
    "sg:orig_category":"Arztpraxen",
    "sg:phone":"+41 21 801 49 71",
    "sg:postcode":"1427",
    "sg:province":"Vaud",
    "wof:name":"Dr M\u00e9d. Jean-f. Savary M\u00e9decin Sp\u00e9cialiste Fmh",
    "wof:placetype":"venue"
},
  "geometry": {"coordinates":[6.492472,46.512012],"type":"Point"}
}