{
  "type": "Feature",
  "properties": {
    "iso:country":"CH",
    "sg:address":"Gerbergasse 9",
    "sg:city":"Luzern",
    "sg:orig_category":"Detailhandel mit Bekleidung Detailhandel mit Schuhen",
    "sg:phone":"+41 41 410 98 56",
    "sg:postcode":"6004",
    "sg:province":"Luzern",
    "wof:name":"Brunello Ag Handelswaren, Bes. Schuhe, Accessoires, Kleider; Handel, Verkauf Usw",
    "wof:placetype":"venue"
},
  "geometry": {"coordinates":[8.308052,47.053028],"type":"Point"}
}