{
  "type": "Feature",
  "properties": {
    "iso:country":"CH",
    "sg:address":"Rue De La Musini\u00e8re 6",
    "sg:city":"St-blaise",
    "sg:orig_category":"Detailhandel mit Zeitungen U Zeitschriften Einzelhandel mit Automobilteilen U Zubeh\u00f6r Kioske",
    "sg:phone":"+41 32 753 07 70",
    "sg:postcode":"2072",
    "sg:province":"Neuch\u00e2tel",
    "wof:name":"New Shop Denis Dubois Kiosque",
    "wof:placetype":"venue"
},
  "geometry": {"coordinates":[6.9904441833,47.0116004944],"type":"Point"}
}