{
  "type": "Feature",
  "properties": {
    "iso:country":"CH",
    "sg:address":"Chemin De La Mousse 117",
    "sg:city":"Th\u00f4nex",
    "sg:orig_category":"Gem\u00fcsebau Landschaftsplanungsb\u00fcros U Gartenarchitekturb\u00fcros",
    "sg:phone":"+41 79 353 90 09",
    "sg:postcode":"1226",
    "sg:province":"Gen\u00e8ve",
    "wof:name":"Entreprise Parini S. Parcs Et Jardins Sa",
    "wof:placetype":"venue"
},
  "geometry": {"coordinates":[6.2257671356,46.2575683594],"type":"Point"}
}