{
  "type": "Feature",
  "properties": {
    "iso:country":"CH",
    "sg:address":"Oberrietstrasse",
    "sg:city":"Uster",
    "sg:orig_category":"G\u00fcterbef\u00f6rderung im Strassenverkehr",
    "sg:phone":"+41 19411585",
    "sg:postcode":"8610",
    "sg:province":"Z\u00fcrich",
    "wof:name":"Welte Leo Ag",
    "wof:placetype":"venue"
},
  "geometry": {"coordinates":[8.7215442657,47.3297538757],"type":"Point"}
}