{
  "type": "Feature",
  "properties": {
    "iso:country":"CH",
    "sg:address":"Kaufplatz 10",
    "sg:city":"Visp",
    "sg:orig_category":"Herstellung von Armaturen",
    "sg:phone":"+41 27 945 13 13",
    "sg:postcode":"3930",
    "sg:province":"Valais",
    "wof:name":"Acqua - Rubin Star Ag",
    "wof:placetype":"venue"
},
  "geometry": {"coordinates":[7.8813848495,46.2908935547],"type":"Point"}
}