{
  "type": "Feature",
  "properties": {
    "iso:country":"CH",
    "sg:address":"R\u00e9sidence Au Village",
    "sg:city":"Duillier",
    "sg:orig_category":"Grosshandel mit Textilien",
    "sg:postcode":"1266",
    "sg:province":"Vaud",
    "wof:name":"Von Arx Anita",
    "wof:placetype":"venue"
},
  "geometry": {"coordinates":[6.2369141579,46.4099502563],"type":"Point"}
}