{
  "type": "Feature",
  "properties": {
    "iso:country":"CH",
    "sg:address":"Ruelle Dubl\u00e9 1",
    "sg:city":"Neuch\u00e2tel",
    "sg:orig_category":"Kosmetikinstitute",
    "sg:phone":"+41 32 725 09 79",
    "sg:postcode":"2000",
    "sg:province":"Neuch\u00e2tel",
    "wof:name":"Catherine Giostra Institut Scarlett Beaut\u00e9",
    "wof:placetype":"venue"
},
  "geometry": {"coordinates":[6.9296870232,46.9909973145],"type":"Point"}
}