{
  "type": "Feature",
  "properties": {
    "iso:country":"CH",
    "sg:address":"Morgins 1872 Troistorrents. Postfach",
    "sg:city":"Morgins",
    "sg:orig_category":"RESTAURANTS: TEA-ROOMS",
    "sg:postcode":"1875",
    "sg:province":"Valais",
    "wof:name":"Pedetti Daniel",
    "wof:placetype":"venue"
},
  "geometry": {"coordinates":[6.9395551682,46.2492294312],"type":"Point"}
}