{
  "type": "Feature",
  "properties": {
    "iso:country":"CH",
    "sg:address":"Schlachthofstrasse 19a 8400 Winterthur. Postfach",
    "sg:city":"Winterthur",
    "sg:orig_category":"Herstellung von Duft U K\u00f6rperpflegemitteln",
    "sg:postcode":"8406",
    "sg:province":"Z\u00fcrich",
    "wof:name":"Tolei Beauty Concept Ag",
    "wof:placetype":"venue"
},
  "geometry": {"coordinates":[8.6984434128,47.4965324402],"type":"Point"}
}