{
  "type": "Feature",
  "properties": {
    "iso:country":"CH",
    "sg:address":"1774",
    "sg:city":"Montagny-les-monts",
    "sg:orig_category":"Zimmerei, Dachdeckerei, Bauspenglerei U Abdichtung",
    "sg:postcode":"1774",
    "sg:province":"Fribourg",
    "wof:name":"Zanetta Construction",
    "wof:placetype":"venue"
},
  "geometry": {"coordinates":[6.9902901649,46.808921814],"type":"Point"}
}