{
  "type": "Feature",
  "properties": {
    "iso:country":"CH",
    "sg:address":"Kirchb\u00fchlweg 48 3007 Bern. Postfach",
    "sg:city":"Bern",
    "sg:orig_category":"Herstellung von elektronischen Bauelementen",
    "sg:postcode":"3005",
    "sg:province":"Bern",
    "wof:name":"M\u00fcller Technik Industrieelektronik, Maschinenbau; Fabrikation, Service, Handel",
    "wof:placetype":"venue"
},
  "geometry": {"coordinates":[7.4219150543,46.9433784485],"type":"Point"}
}