{
  "type": "Feature",
  "properties": {
    "iso:country":"CH",
    "sg:address":"Via Angelo Maspoli 18",
    "sg:city":"Mendrisio",
    "sg:orig_category":"Herstellung von Damen U M\u00e4dchenoberbekleidung Herstellung von Herren U Knabenoberbekleidung",
    "sg:phone":"+41 91 630 07 55",
    "sg:postcode":"6850",
    "sg:province":"Ticino",
    "wof:name":"Ittierre Suisse Gmbh",
    "wof:placetype":"venue"
},
  "geometry": {"coordinates":[8.978729248,45.8752593994],"type":"Point"}
}