{
  "type": "Feature",
  "properties": {
    "iso:country":"CH",
    "sg:address":"H\u00e4nib\u00fchl 8 6300 Zug. Postfach 457",
    "sg:city":"Zug",
    "sg:orig_category":"Advokaturb\u00fcros Notariate",
    "sg:phone":"+41 41 711 67 21",
    "sg:postcode":"6301",
    "sg:province":"Zug",
    "wof:name":"Dr.christoph Straub Advokatur-& Notariatsb\u00fcro",
    "wof:placetype":"venue"
},
  "geometry": {"coordinates":[8.517233,47.158157],"type":"Point"}
}