{
  "type": "Feature",
  "properties": {
    "iso:country":"CH",
    "sg:address":"La Chaumi\u00e8re",
    "sg:city":"Ecl\u00e9pens",
    "sg:orig_category":"Fachdetailhandel in Verkaufsr\u00e4umen",
    "sg:postcode":"1312",
    "sg:province":"Vaud",
    "wof:name":"Emeri R., Dino Diffusion",
    "wof:placetype":"venue"
},
  "geometry": {"coordinates":[6.5289797783,46.6511039734],"type":"Point"}
}