{
  "type": "Feature",
  "properties": {
    "iso:country":"CH",
    "sg:address":"Hardstrasse 65 4052 Basel. Postfach",
    "sg:city":"Basel",
    "sg:orig_category":"Museen",
    "sg:postcode":"4051",
    "sg:province":"Basel-Stadt",
    "wof:name":"Galerie Azimut Ag Kunsthandel Usw",
    "wof:placetype":"venue"
},
  "geometry": {"coordinates":[7.6050868034,47.550453186],"type":"Point"}
}