{
  "type": "Feature",
  "properties": {
    "iso:country":"CH",
    "sg:address":"Via St. Maria 66",
    "sg:city":"Gordola",
    "sg:orig_category":"Ingenieurb\u00fcros Vermessung",
    "sg:phone":"+41 91 745 13 77",
    "sg:postcode":"6596",
    "sg:province":"Ticino",
    "wof:name":"Claudio Terribilini Studio D'ingegneria",
    "wof:placetype":"venue"
},
  "geometry": {"coordinates":[8.865398407,46.1704978943],"type":"Point"}
}