{
  "type": "Feature",
  "properties": {
    "iso:country":"CH",
    "sg:address":"Rue De Bouleyres 24",
    "sg:city":"Bulle",
    "sg:orig_category":"Maler U Glasergewerbe",
    "sg:phone":"+41 26 919 82 30",
    "sg:postcode":"1630",
    "sg:province":"Fribourg",
    "wof:name":"Ruffieux Charly",
    "wof:placetype":"venue"
},
  "geometry": {"coordinates":[7.0603208542,46.6162872314],"type":"Point"}
}