{
  "type": "Feature",
  "properties": {
    "iso:country":"CH",
    "sg:address":"Zugerstrasse 20",
    "sg:city":"Zufikon",
    "sg:orig_category":"Autogaragen",
    "sg:phone":"+41 56 631 24 04",
    "sg:postcode":"5621",
    "sg:province":"Aargau",
    "wof:name":"Rudolf Wasser Garage",
    "wof:placetype":"venue"
},
  "geometry": {"coordinates":[8.353807,47.342651],"type":"Point"}
}