{
  "type": "Feature",
  "properties": {
    "iso:country":"CH",
    "sg:address":"Bahnhofstrasse 9 4553 Subingen. Postfach 210",
    "sg:city":"Subingen",
    "sg:orig_category":"Vermittlung von Immobilien",
    "sg:phone":"+41 32 614 27 27",
    "sg:postcode":"4553",
    "sg:province":"Solothurn",
    "wof:name":"Erich Ingold Treuhandb\u00fcro",
    "wof:placetype":"venue"
},
  "geometry": {"coordinates":[7.6135787964,47.1944084167],"type":"Point"}
}