{
  "type": "Feature",
  "properties": {
    "iso:country":"CH",
    "sg:address":"Le Tiguelet.",
    "sg:city":"Belfaux",
    "sg:orig_category":"Instandhaltung U Reparatur von Automobilen",
    "sg:phone":"+41 26 475 40 26",
    "sg:postcode":"1782",
    "sg:province":"Fribourg",
    "wof:name":"Yerly Romain.",
    "wof:placetype":"venue"
},
  "geometry": {"coordinates":[7.1102380753,46.8195457458],"type":"Point"}
}