{
  "type": "Feature",
  "properties": {
    "iso:country":"CH",
    "sg:address":"Rigistrasse 7",
    "sg:city":"Dierikon",
    "sg:orig_category":"G\u00fcterbef\u00f6rderung im Strassenverkehr",
    "sg:phone":"+41 41 451 03 96",
    "sg:postcode":"6036",
    "sg:province":"Luzern",
    "wof:name":"Ht Retex Gmbh",
    "wof:placetype":"venue"
},
  "geometry": {"coordinates":[8.3682174683,47.0973243713],"type":"Point"}
}