{
  "type": "Feature",
  "properties": {
    "iso:country":"CH",
    "sg:address":"Stapfen 3862 Innertkirchen. Postfach",
    "sg:city":"Innertkirchen",
    "sg:classifiers":[
        {
            "category":"Travel",
            "subcategory":"Hotels & Motels",
            "type":"Entertainment"
        }
    ],
    "sg:postcode":"3862",
    "sg:province":"Bern",
    "sg:tags":[
        "hotels",
        "mit",
        "restaurant"
    ],
    "wof:name":"Kottelat-braichet Marie-jeanne.",
    "wof:placetype":"venue"
},
  "geometry": {"coordinates":[6.9842767715,47.2712631226],"type":"Point"}
}