{
  "type": "Feature",
  "properties": {
    "iso:country":"CH",
    "sg:address":"Hinterm\u00fchlenstr. 6",
    "sg:city":"Winterthur",
    "sg:classifiers":[
        {
            "category":"Professional",
            "subcategory":"Engineering",
            "type":"Services"
        }
    ],
    "sg:phone":"+41 52 242 85 27",
    "sg:postcode":"8409",
    "sg:province":"Z\u00fcrich",
    "sg:tags":[
        "machine",
        "-",
        "mechanical"
    ],
    "wof:name":"Ultramatic Ag",
    "wof:placetype":"venue"
},
  "geometry": {"coordinates":[8.7736988068,47.5038948059],"type":"Point"}
}