{
  "type": "Feature",
  "properties": {
    "iso:country":"CH",
    "sg:address":"Hauptstr.",
    "sg:city":"Rabius",
    "sg:classifiers":[
        {
            "category":"Home & Garden",
            "subcategory":"Furniture",
            "type":"Retail Goods"
        }
    ],
    "sg:phone":"+41 22 818 39 99",
    "sg:postcode":"7172",
    "sg:province":"Graubunden",
    "sg:tags":[
        "household",
        "wood"
    ],
    "wof:name":"Galli D\u00c9coration Sa",
    "wof:placetype":"venue"
},
  "geometry": {"coordinates":[4.3227248192,46.0998497009],"type":"Point"}
}