{
  "type": "Feature",
  "properties": {
    "iso:country":"CH",
    "sg:address":"Ravecchia Via 50 6500 Bellinzona. Postfach Casa Postale",
    "sg:city":"Bellinzona",
    "sg:orig_category":"Herstellung von Metallkonstruktionen",
    "sg:postcode":"6500",
    "sg:province":"Ticino",
    "wof:name":"Edilmetallica Sa Costruzioni Metalliche. Fabbricazione E Vendita Di Elementi Ecc",
    "wof:placetype":"venue"
},
  "geometry": {"coordinates":[9.0239200592,46.1943397522],"type":"Point"}
}