{
  "type": "Feature",
  "properties": {
    "iso:country":"CH",
    "sg:address":"Kanalstrasse 19",
    "sg:city":"Opfikon",
    "sg:orig_category":"Softwareentwicklung U beratung",
    "sg:phone":"+41 18104044",
    "sg:postcode":"8152",
    "sg:province":"Z\u00fcrich",
    "wof:name":"B\u00fcroelektronik Bel Ag",
    "wof:placetype":"venue"
},
  "geometry": {"coordinates":[8.5740098953,47.4292984009],"type":"Point"}
}