{
  "type": "Feature",
  "properties": {
    "iso:country":"CH",
    "sg:address":"Kirchackerweg 4",
    "sg:city":"Villmergen",
    "sg:orig_category":"Verlegen von Fliesen U Platten",
    "sg:phone":"+41 79 420 68 39",
    "sg:postcode":"5612",
    "sg:province":"Aargau",
    "wof:name":"Otto Gsell Keramische Wand-& Bodenbel\u00e4ge",
    "wof:placetype":"venue"
},
  "geometry": {"coordinates":[8.2408790588,47.3472862244],"type":"Point"}
}