{
  "type": "Feature",
  "properties": {
    "iso:country":"CH",
    "sg:address":"Clos-bottey 128",
    "sg:city":"Orsonnens",
    "sg:orig_category":"Datenbanken",
    "sg:phone":"+41 26 653 03 04",
    "sg:postcode":"1693",
    "wof:name":"Captel, Roch Jean-fran\u00e7ois",
    "wof:placetype":"venue"
},
  "geometry": {"coordinates":[6.995251,46.716404],"type":"Point"}
}