{
  "type": "Feature",
  "properties": {
    "iso:country":"CH",
    "sg:address":"Etzelstrasse 70",
    "sg:city":"St\u00e4fa",
    "sg:orig_category":"Herstellung von sonstigen elektrischen Ausr\u00fcstungen",
    "sg:postcode":"8712",
    "sg:province":"Z\u00fcrich",
    "wof:name":"Pmb Projekt-management Bauert",
    "wof:placetype":"venue"
},
  "geometry": {"coordinates":[8.7196407318,47.2451591492],"type":"Point"}
}