{
  "type": "Feature",
  "properties": {
    "iso:country":"CH",
    "sg:address":"Rue Beau-s\u00e9jour 7",
    "sg:city":"Lausanne",
    "sg:orig_category":"Detailhandel mit Lederwaren U Reiseartikeln Herstellung von Reiseartikeln, Leder U Sattlerwaren",
    "sg:phone":"+41 21 323 88 15",
    "sg:postcode":"1003",
    "sg:province":"Vaud",
    "wof:name":"Mohamed Hamouche Sellerie-maroquinerie",
    "wof:placetype":"venue"
},
  "geometry": {"coordinates":[6.6349101067,46.5181846619],"type":"Point"}
}