{
  "type": "Feature",
  "properties": {
    "iso:country":"CH",
    "sg:address":"Le Cornat 22 2946 Mi\u00e9court. Postfach",
    "sg:city":"Mi\u00e9court",
    "sg:orig_category":"Sonstige mit Sport verbundene T\u00e4tigkeiten",
    "sg:phone":"+41 32 462 28 53",
    "sg:postcode":"2946",
    "sg:province":"Jura",
    "wof:name":"Loisirs Et Sant\u00e9 S\u00e0rl Prestations De Services Dans Le Secteur Hippomobile",
    "wof:placetype":"venue"
},
  "geometry": {"coordinates":[7.1764850616,47.4285697937],"type":"Point"}
}