{
  "type": "Feature",
  "properties": {
    "iso:country":"CH",
    "sg:address":"Ringstrasse 6",
    "sg:city":"Dagmersellen",
    "sg:orig_category":"Unclassifiable Establishments",
    "sg:postcode":"6252",
    "sg:province":"Luzern",
    "wof:name":"Contsihp Transporte Daniel Baumann",
    "wof:placetype":"venue"
},
  "geometry": {"coordinates":[7.9806251526,47.2166023254],"type":"Point"}
}