{
  "type": "Feature",
  "properties": {
    "iso:country":"CH",
    "sg:address":"Langackerstrasse 73",
    "sg:city":"Herrliberg",
    "sg:orig_category":"Non-Classified Establishments",
    "sg:postcode":"8704",
    "sg:province":"Z\u00fcrich",
    "wof:name":"Robert Haas Vermietung Von Werbefl\u00e4chen Und Immobilien",
    "wof:placetype":"venue"
},
  "geometry": {"coordinates":[8.6189842224,47.2888832092],"type":"Point"}
}