{
  "type": "Feature",
  "properties": {
    "iso:country":"CH",
    "sg:address":"Seminarstrasse 102",
    "sg:city":"Wettingen",
    "sg:classifiers":[
        {
            "category":"Communications",
            "subcategory":"Television Station",
            "type":"Services"
        }
    ],
    "sg:phone":"+41 56 426 80 81",
    "sg:postcode":"5430",
    "sg:province":"Aargau",
    "sg:tags":[
        "generator",
        "high-frequency"
    ],
    "wof:name":"Plustherm Point Gmbh",
    "wof:placetype":"venue"
},
  "geometry": {"coordinates":[8.3151416779,47.4610443115],"type":"Point"}
}