{
  "type": "Feature",
  "properties": {
    "iso:country":"CH",
    "sg:address":"Fluhweg 5",
    "sg:city":"Pieterlen",
    "sg:orig_category":"Architekturb\u00fcros",
    "sg:phone":"+41 32 384 28 21",
    "sg:postcode":"2542",
    "sg:province":"Bern",
    "wof:name":"Iseli & Von Lerber Bauberatung",
    "wof:placetype":"venue"
},
  "geometry": {"coordinates":[7.317004,47.09547],"type":"Point"}
}