{
  "type": "Feature",
  "properties": {
    "iso:country":"CH",
    "sg:address":"Eurorest Autobahn N1/n2",
    "sg:city":"Gunzgen",
    "sg:orig_category":"RESTAURANTS: TEA-ROOMS Tankstellen",
    "sg:phone":"+41 62 216 25 65",
    "sg:postcode":"4617",
    "sg:province":"Solothurn",
    "wof:name":"Z'graggen Paul",
    "wof:placetype":"venue"
},
  "geometry": {"coordinates":[7.8295850754,47.3174552917],"type":"Point"}
}