{
  "type": "Feature",
  "properties": {
    "iso:country":"CH",
    "sg:address":"Croissant Chemin Du 16",
    "sg:city":"Ch\u00e2telaine",
    "sg:orig_category":"Non-Classified Establishments",
    "sg:postcode":"1219",
    "sg:province":"Gen\u00e8ve",
    "wof:name":"Pink Films, Jaquenod Fran\u00e7ois Et Christian",
    "wof:placetype":"venue"
},
  "geometry": {"coordinates":[6.1109509468,46.2091445923],"type":"Point"}
}