{
  "type": "Feature",
  "properties": {
    "iso:country":"CH",
    "sg:address":"Kugelgasse 7",
    "sg:city":"St.gallen",
    "sg:orig_category":"RESTAURANTS: TEA-ROOMS",
    "sg:postcode":"9000",
    "sg:province":"St. Gallen",
    "wof:name":"San Marco Rapperswil Ag",
    "wof:placetype":"venue"
},
  "geometry": {"coordinates":[8.8146944046,47.2261352539],"type":"Point"}
}