{
  "type": "Feature",
  "properties": {
    "iso:country":"CH",
    "sg:address":"6233",
    "sg:city":"B\u00fcron",
    "sg:classifiers":[
        {
            "category":"Education",
            "subcategory":"Vocational School",
            "type":"Public Place"
        }
    ],
    "sg:postcode":"6233",
    "sg:province":"Luzern",
    "sg:tags":[
        "koch-",
        "haushaltschulen"
    ],
    "wof:name":"Haushaltungsschule",
    "wof:placetype":"venue"
},
  "geometry": {"coordinates":[8.0951595306,47.2130813599],"type":"Point"}
}