{
  "type": "Feature",
  "properties": {
    "iso:country":"CH",
    "sg:address":"Tamaro Via 3",
    "sg:city":"Bellinzona",
    "sg:orig_category":"Allgemeiner Hoch U Tiefbau",
    "sg:phone":"+41 91 825 43 46",
    "sg:postcode":"6500",
    "sg:province":"Ticino",
    "wof:name":"Casanova Mario Ing. Sts Impresa Construzioni",
    "wof:placetype":"venue"
},
  "geometry": {"coordinates":[9.033097,46.203869],"type":"Point"}
}