{
  "type": "Feature",
  "properties": {
    "iso:country":"CH",
    "sg:address":"St. Johanns-vorstadt 13 4056 Basel. Postfach",
    "sg:city":"Basel",
    "sg:orig_category":"Pensionskassen",
    "sg:postcode":"4051",
    "sg:province":"Basel-Stadt",
    "wof:name":"Europ\u00e4ischer Landfonds Beitr\u00e4ge Zur Verhinderung Der Abwanderung Der Bev\u00f6lkerung Usw",
    "wof:placetype":"venue"
},
  "geometry": {"coordinates":[7.5846118927,47.5630645752],"type":"Point"}
}