{
  "type": "Feature",
  "properties": {
    "iso:country":"CH",
    "sg:address":"2875",
    "sg:city":"Montfaucon",
    "sg:orig_category":"Unclassifiable Establishments",
    "sg:postcode":"2875",
    "sg:province":"Jura",
    "wof:name":"Toutacarien, Philippe Jeannotat",
    "wof:placetype":"venue"
},
  "geometry": {"coordinates":[7.0542049408,47.2841796875],"type":"Point"}
}