{
  "type": "Feature",
  "properties": {
    "iso:country":"CH",
    "sg:address":"Altwiesenstrasse 346",
    "sg:city":"Z\u00fcrich",
    "sg:orig_category":"Unternehmensberatung Wirtschaftspr\u00fcfung, Steuerberatung U Treuhand",
    "sg:phone":"+41 13201415",
    "sg:postcode":"8051",
    "sg:province":"Z\u00fcrich",
    "wof:name":"Hierholzer & Partner Ag Treuhand & Unternehmensb.",
    "wof:placetype":"venue"
},
  "geometry": {"coordinates":[8.5905380249,47.3999824524],"type":"Point"}
}