{
  "type": "Feature",
  "properties": {
    "iso:country":"CH",
    "sg:address":"Emil Frey-strasse 70 4142 M\u00fcnchenstein. Postfach",
    "sg:city":"Basel",
    "sg:orig_category":"Personenbef\u00f6rderung im Linienverkehr zu Land",
    "sg:phone":"+41 61 332 18 18",
    "sg:postcode":"4002",
    "sg:province":"Basel-Stadt",
    "wof:name":"Dfb-dampfbahn Furka-bergstrecke",
    "wof:placetype":"venue"
},
  "geometry": {"coordinates":[7.610929966,47.5289382935],"type":"Point"}
}