{
  "type": "Feature",
  "properties": {
    "iso:country":"CH",
    "sg:address":"Chemin D'archessus 6",
    "sg:city":"Bevaix",
    "sg:orig_category":"G\u00fcterbef\u00f6rderung im Strassenverkehr",
    "sg:postcode":"2022",
    "sg:province":"Neuch\u00e2tel",
    "wof:name":"Ducommun Jacques",
    "wof:placetype":"venue"
},
  "geometry": {"coordinates":[6.8152198792,46.9300689697],"type":"Point"}
}