{
  "type": "Feature",
  "properties": {
    "iso:country":"CH",
    "sg:address":"Rietwisstrasse 25",
    "sg:city":"Herisau",
    "sg:orig_category":"Vorschulen, Kinderg\u00e4rten",
    "sg:phone":"+41 71 352 49 93",
    "sg:postcode":"9100",
    "sg:province":"Appenzell Ausserrhoden",
    "wof:name":"Kindergarten Rietwis",
    "wof:placetype":"venue"
},
  "geometry": {"coordinates":[9.2632017136,47.3988494873],"type":"Point"}
}