{
  "type": "Feature",
  "properties": {
    "iso:country":"CH",
    "sg:address":"Melchr\u00fctistrasse 19 8304 Wallisellen. Postfach 1449",
    "sg:city":"Glattzentrum",
    "sg:orig_category":"Ingenieurb\u00fcros Elektro",
    "sg:phone":"+41 71 244 22 56",
    "sg:postcode":"8301",
    "sg:province":"Z\u00fcrich",
    "wof:name":"Thomas Camenisch Ingenieurb\u00fcro",
    "wof:placetype":"venue"
},
  "geometry": {"coordinates":[9.3797540665,47.4369773865],"type":"Point"}
}