{
  "type": "Feature",
  "properties": {
    "iso:country":"CH",
    "sg:address":"Aarestrasse 30a",
    "sg:city":"Thun",
    "sg:orig_category":"Bijouterien",
    "sg:phone":"+41 31 832 48 10",
    "sg:postcode":"3600",
    "sg:province":"Bern",
    "wof:name":"Rhomberg Schmuck Ag B\u00e4ren Zentrum",
    "wof:placetype":"venue"
},
  "geometry": {"coordinates":[7.561202,46.929184],"type":"Point"}
}