{
  "type": "Feature",
  "properties": {
    "iso:country":"CH",
    "sg:address":"Universit\u00e4tstrasse 118",
    "sg:city":"Z\u00fcrich",
    "sg:orig_category":"Reiseb\u00fcros U Reiseveranstalter",
    "sg:postcode":"8000",
    "sg:province":"Z\u00fcrich",
    "wof:name":"Reisen Ohne Grenzen Rog - Travel, J. Bollhalder",
    "wof:placetype":"venue"
},
  "geometry": {"coordinates":[8.5487003326,47.385433197],"type":"Point"}
}