{
  "type": "Feature",
  "properties": {
    "iso:country":"CH",
    "sg:address":"Granges-paccot Av. De 2 1700 Fribourg. Postfach",
    "sg:city":"Freiburg",
    "sg:orig_category":"Fachdetailhandel in Verkaufsr\u00e4umen",
    "sg:postcode":"1700",
    "sg:province":"Fribourg",
    "wof:name":"\u00able Nautilus\u00bb Roche C. Magasin D'animaux",
    "wof:placetype":"venue"
},
  "geometry": {"coordinates":[7.1528320312,46.8124008179],"type":"Point"}
}