{
  "type": "Feature",
  "properties": {
    "iso:country":"CH",
    "sg:address":"L\u00f6wengartenstrasse 4",
    "sg:city":"Rorschach",
    "sg:orig_category":"Herstellung von Karosserien U Anh\u00e4ngern",
    "sg:phone":"+41 71 841 74 80",
    "sg:postcode":"9400",
    "sg:province":"St. Gallen",
    "wof:name":"Carrosserie Batliner",
    "wof:placetype":"venue"
},
  "geometry": {"coordinates":[9.4841880798,47.4772567749],"type":"Point"}
}