{
  "type": "Feature",
  "properties": {
    "addr:full":"Rue Des Voisins 15 Gen\u00e8ve Gen\u00e8ve 1205",
    "addr:housenumber":"15",
    "addr:postcode":"1205",
    "addr:street":"Rue Des Voisins",
    "iso:country":"CH",
    "sg:address":"Rue Des Voisins 15",
    "sg:city":"Gen\u00e8ve",
    "sg:orig_category":"Architekturb\u00fcros",
    "sg:phone":"+41 22 320 24 20",
    "sg:postcode":"1205",
    "sg:province":"Gen\u00e8ve",
    "wof:name":"Pierre-a.& Philippe Staehli Bureau D'architecture",
    "wof:placetype":"venue"
},
  "geometry": {"coordinates":[6.144637,46.195415],"type":"Point"}
}