{
  "type": "Feature",
  "properties": {
    "iso:country":"CH",
    "sg:address":"Schmiedgasse 121",
    "sg:city":"Eschen",
    "sg:orig_category":"Werbegrafikateliers",
    "sg:phone":"+41 75 232 00 48",
    "sg:postcode":"9492",
    "wof:name":"Cornelia Eberle Grafisches Atelier",
    "wof:placetype":"venue"
},
  "geometry": {"coordinates":[9.5209197998,47.210559845],"type":"Point"}
}