{
  "type": "Feature",
  "properties": {
    "iso:country":"CH",
    "sg:address":"Grand-rue 61",
    "sg:city":"Tramelan",
    "sg:orig_category":"Detailhandel mit Brot, Back U S\u00fcsswaren",
    "sg:phone":"+41 32 487 42 56",
    "sg:postcode":"2720",
    "sg:province":"Bern",
    "wof:name":"Albert, Ernest.",
    "wof:placetype":"venue"
},
  "geometry": {"coordinates":[7.111634,47.223118],"type":"Point"}
}