{
  "type": "Feature",
  "properties": {
    "iso:country":"CH",
    "sg:address":"Place De La Gare 1",
    "sg:city":"Corcelles",
    "sg:classifiers":[
        {
            "category":"Professional",
            "subcategory":"Business Services",
            "type":"Services"
        }
    ],
    "sg:phone":"+41 32 731 67 77",
    "sg:postcode":"2035",
    "sg:province":"Neuch\u00e2tel",
    "sg:tags":[
        "high-precision",
        "mechanic"
    ],
    "wof:name":"Efap S.a.",
    "wof:placetype":"venue"
},
  "geometry": {"coordinates":[6.8840880394,46.9836235046],"type":"Point"}
}