{
  "type": "Feature",
  "properties": {
    "iso:country":"CH",
    "sg:address":"Boulevard De Saint-georges 10",
    "sg:city":"Gen\u00e8ve",
    "sg:classifiers":[
        {
            "category":"Restaurant",
            "type":"Food & Drink"
        }
    ],
    "sg:phone":"+41 22 321 75 38",
    "sg:postcode":"1205",
    "sg:province":"Gen\u00e8ve",
    "wof:name":"Caf\u00e9 Le Scotch",
    "wof:placetype":"venue"
},
  "geometry": {"coordinates":[6.1318078041,46.2011795044],"type":"Point"}
}