{
  "type": "Feature",
  "properties": {
    "iso:country":"CH",
    "sg:address":"Reuenthalerstrasse 308",
    "sg:city":"Leuggern",
    "sg:orig_category":"Elektroinstallation",
    "sg:phone":"+41 56 450 10 61",
    "sg:postcode":"5316",
    "sg:province":"Aargau",
    "wof:name":"Thut Elektro Ag",
    "wof:placetype":"venue"
},
  "geometry": {"coordinates":[8.1358127594,47.4439277649],"type":"Point"}
}