{
  "type": "Feature",
  "properties": {
    "iso:country":"CH",
    "sg:address":"Julierweg 11 7000 Chur. Postfach",
    "sg:city":"Chur",
    "sg:orig_category":"Handel mit Automobilen",
    "sg:postcode":"7000",
    "sg:province":"Graubunden",
    "wof:name":"Makhlouf Autohandel",
    "wof:placetype":"venue"
},
  "geometry": {"coordinates":[9.5215406418,46.8562240601],"type":"Point"}
}