{
  "type": "Feature",
  "properties": {
    "iso:country":"CH",
    "sg:address":"Im Pardiel 61",
    "sg:city":"Schaan",
    "sg:orig_category":"Vorschulen, Kinderg\u00e4rten",
    "sg:phone":"+423 232 09 43",
    "sg:postcode":"9494",
    "wof:name":"Kindergarten Pardiel I",
    "wof:placetype":"venue"
},
  "geometry": {"coordinates":[9.505865097,47.1643638611],"type":"Point"}
}