{
  "type": "Feature",
  "properties": {
    "iso:country":"CH",
    "sg:address":"Rue Du Milieu 44",
    "sg:city":"Yverdon-les-bains",
    "sg:orig_category":"Detailhandel mit Geschenkartikeln U Souvenirs Herstellung von Oberbekleidung",
    "sg:phone":"+41 24 425 74 41",
    "sg:postcode":"1400",
    "sg:province":"Vaud",
    "wof:name":"Christine Maffini Boutique Black Jack",
    "wof:placetype":"venue"
},
  "geometry": {"coordinates":[6.6373701096,46.7793083191],"type":"Point"}
}