{
  "type": "Feature",
  "properties": {
    "iso:country":"CH",
    "sg:address":"Pilettes Rue Des 1",
    "sg:city":"Freiburg",
    "sg:orig_category":"Detailhandel mit Waren verschiedener Art, Hauptrichtung Nahrungsmittel",
    "sg:postcode":"1700",
    "sg:province":"Fribourg",
    "wof:name":"Man-koso International Ag",
    "wof:placetype":"venue"
},
  "geometry": {"coordinates":[7.1516737938,46.80078125],"type":"Point"}
}