{
  "type": "Feature",
  "properties": {
    "iso:country":"CH",
    "sg:address":"Glarnerstrasse 43 8854 Siebnen. Postfach",
    "sg:city":"Siebnen",
    "sg:orig_category":"Detailhandel mit elektrischen Haushalts-,Radio U Fernsehger\u00e4ten sowie Musikinstrumenten",
    "sg:phone":"+41 55 450 21 80",
    "sg:postcode":"8854",
    "sg:province":"Schwyz",
    "wof:name":"Schmid Arnold Ag",
    "wof:placetype":"venue"
},
  "geometry": {"coordinates":[8.9020385742,47.1759338379],"type":"Point"}
}