{
  "type": "Feature",
  "properties": {
    "iso:country":"CH",
    "sg:address":"Schlossbrugg",
    "sg:city":"Berneck",
    "sg:orig_category":"Pensionskassen",
    "sg:postcode":"9442",
    "sg:province":"St. Gallen",
    "wof:name":"Personal-f\u00fcrsorgestiftung Der Firma Mobil-werke Frei U., Berneck",
    "wof:placetype":"venue"
},
  "geometry": {"coordinates":[9.6164646149,47.4231491089],"type":"Point"}
}