{
  "type": "Feature",
  "properties": {
    "iso:country":"CH",
    "sg:address":"Chemin De L'etang 46 1214 Vernier. Postfach",
    "sg:city":"Vernier",
    "sg:orig_category":"Kauf U Verkauf von Immobilien auf eigene Rechnung",
    "sg:phone":"+41 22 979 37 00",
    "sg:postcode":"1214",
    "sg:province":"Gen\u00e8ve",
    "wof:name":"Sa Falaises-p\u00eacheries Immeubles Etc",
    "wof:placetype":"venue"
},
  "geometry": {"coordinates":[6.1026492119,46.218788147],"type":"Point"}
}