{
  "type": "Feature",
  "properties": {
    "iso:country":"CH",
    "sg:address":"St. Gallerstrasse 16",
    "sg:city":"Arbon",
    "sg:classifiers":[
        {
            "category":"Professional",
            "subcategory":"Employment Agencies",
            "type":"Services"
        }
    ],
    "sg:postcode":"9320",
    "sg:province":"Thurgau",
    "sg:tags":[
        "personal",
        "u",
        "stellenvermittlung"
    ],
    "wof:name":"Qmc Gmbh",
    "wof:placetype":"venue"
},
  "geometry": {"coordinates":[9.4305391312,47.5118637085],"type":"Point"}
}