{
  "type": "Feature",
  "properties": {
    "iso:country":"CH",
    "sg:address":"Suisse Route 9",
    "sg:city":"Mies",
    "sg:orig_category":"Non-Classified Establishments",
    "sg:postcode":"1295",
    "sg:province":"Vaud",
    "wof:name":"Golden Sands Sa",
    "wof:placetype":"venue"
},
  "geometry": {"coordinates":[6.1678080559,46.2968559265],"type":"Point"}
}