{
  "type": "Feature",
  "properties": {
    "iso:country":"CH",
    "sg:address":"Avry-top",
    "sg:city":"Avry-sur-matran",
    "sg:orig_category":"Detailhandel mit Beleuchtungs U Haushaltsgegenst\u00e4nden Detailhandel mit Radio U Fernsehger\u00e4ten",
    "sg:phone":"+41 26 470 29 49",
    "sg:postcode":"1754",
    "sg:province":"Fribourg",
    "wof:name":"Fust Sa",
    "wof:placetype":"venue"
},
  "geometry": {"coordinates":[7.072196,46.788326],"type":"Point"}
}