{
  "type": "Feature",
  "properties": {
    "iso:country":"CH",
    "sg:address":"Place Du March\u00e9 6",
    "sg:city":"Leysin",
    "sg:orig_category":"Vermittlung von Immobilien Verwaltung von Immobilien",
    "sg:phone":"+41 24 494 15 00",
    "sg:postcode":"1854",
    "sg:province":"Vaud",
    "wof:name":"Groupe Geco Sa Agence Immobili\u00e8re",
    "wof:placetype":"venue"
},
  "geometry": {"coordinates":[7.0130829811,46.3435630798],"type":"Point"}
}