{
  "type": "Feature",
  "properties": {
    "iso:country":"CH",
    "sg:address":"Im Isisb\u00fcel 6",
    "sg:city":"Thalwil",
    "sg:orig_category":"Sanit\u00e4r, Heizungs U L\u00fcftungsinstallation Sanit\u00e4rinstallation",
    "sg:phone":"+41 17203280",
    "sg:postcode":"8800",
    "sg:province":"Z\u00fcrich",
    "wof:name":"Christen U. Partner",
    "wof:placetype":"venue"
},
  "geometry": {"coordinates":[8.5677928925,47.2926635742],"type":"Point"}
}