{
  "type": "Feature",
  "properties": {
    "iso:country":"CH",
    "sg:address":"Hinterdorf",
    "sg:city":"Sax",
    "sg:orig_category":"K\u00fcnstlerische U schriftstellerische T\u00e4tigkeiten U Darbietungen Selbst\u00e4ndige bildende K\u00fcnstler",
    "sg:phone":"+41 81 756 01 17",
    "sg:postcode":"9468",
    "sg:province":"St. Gallen",
    "wof:name":"Rohrer Bildhauer Ag",
    "wof:placetype":"venue"
},
  "geometry": {"coordinates":[9.4626941681,47.169380188],"type":"Point"}
}