{
  "type": "Feature",
  "properties": {
    "addr:full":"Emmentalstrasse 29 Konolfingen Bern 3510",
    "addr:housenumber":"29",
    "addr:postcode":"3510",
    "addr:street":"Emmentalstrasse;Bern",
    "iso:country":"CH",
    "sg:address":"Emmentalstrasse 29",
    "sg:city":"Konolfingen",
    "sg:orig_category":"Armierungen Herstellung",
    "sg:phone":"+41 55 444 27 09",
    "sg:postcode":"3510",
    "sg:province":"Bern",
    "wof:name":"Marcel Z\u00fcger Gmbh Armierungen",
    "wof:placetype":"venue"
},
  "geometry": {"coordinates":[8.95279,47.175179],"type":"Point"}
}