{
  "type": "Feature",
  "properties": {
    "iso:country":"CH",
    "sg:address":"Ch. Des Alpes 9",
    "sg:city":"Mont-sur-rolle",
    "sg:orig_category":"Sanit\u00e4r, Heizungs U L\u00fcftungsinstallation",
    "sg:phone":"+41 21 625 49 58",
    "sg:postcode":"1185",
    "sg:province":"Vaud",
    "wof:name":"Renaud Pascal, Commerce D'importation",
    "wof:placetype":"venue"
},
  "geometry": {"coordinates":[6.3281650543,46.475151062],"type":"Point"}
}