{
  "type": "Feature",
  "properties": {
    "iso:country":"CH",
    "sg:address":"Wildensteinerstrasse 26",
    "sg:city":"Bubendorf",
    "sg:orig_category":"Alters U Pflegeheime Wohnheime f\u00fcr Kinder U Jugendliche",
    "sg:phone":"+41 61 931 18 75",
    "sg:postcode":"4416",
    "sg:province":"Basel-Landschaft",
    "wof:name":"Wohnheim Am Weiher",
    "wof:placetype":"venue"
},
  "geometry": {"coordinates":[7.735726,47.44331],"type":"Point"}
}