{
  "type": "Feature",
  "properties": {
    "iso:country":"CH",
    "sg:address":"Bahnhofstrasse 74",
    "sg:city":"Mels",
    "sg:orig_category":"Unclassifiable Establishments",
    "sg:postcode":"8887",
    "sg:province":"St. Gallen",
    "wof:name":"Hotel Melserhof - Hauser",
    "wof:placetype":"venue"
},
  "geometry": {"coordinates":[9.4173250198,47.0534477234],"type":"Point"}
}