{
  "type": "Feature",
  "properties": {
    "iso:country":"CH",
    "sg:address":"Emmentalstrasse 67",
    "sg:city":"Konolfingen",
    "sg:orig_category":"Bauschreinerei Herstellung von Konstruktionsteilen, Fertigbauteilen U Ausbauelementen aus Holz",
    "sg:phone":"+41 31 791 09 83",
    "sg:postcode":"3510",
    "sg:province":"Bern",
    "wof:name":"Andreas Eichenberger",
    "wof:placetype":"venue"
},
  "geometry": {"coordinates":[7.632041,46.884888],"type":"Point"}
}