{
  "type": "Feature",
  "properties": {
    "iso:country":"CH",
    "sg:address":"Solothurnstrasse 6",
    "sg:city":"Jegenstorf",
    "sg:orig_category":"Bauschreinerei Innenausbau",
    "sg:phone":"+41 71 777 10 90",
    "sg:postcode":"3303",
    "sg:province":"Bern",
    "wof:name":"Hans Inauen Schreinerei & Innenausbau",
    "wof:placetype":"venue"
},
  "geometry": {"coordinates":[9.568735,47.391918],"type":"Point"}
}