{
  "type": "Feature",
  "properties": {
    "iso:country":"CH",
    "sg:address":"Hauptstrasse 53a",
    "sg:city":"Lommis",
    "sg:orig_category":"Fahrschulen, Flugschulen",
    "sg:phone":"+41 52 376 29 55",
    "sg:postcode":"9506",
    "sg:province":"Thurgau",
    "wof:name":"Peter H\u00f6gger Autofahrschule",
    "wof:placetype":"venue"
},
  "geometry": {"coordinates":[8.9954538345,47.5174484253],"type":"Point"}
}