{
  "type": "Feature",
  "properties": {
    "iso:country":"CH",
    "sg:address":"Dachlissen",
    "sg:city":"Mettmenstetten",
    "sg:orig_category":"Allgemeiner Hoch U Tiefbau",
    "sg:postcode":"8932",
    "sg:province":"Z\u00fcrich",
    "wof:name":"Frick Martin, Hoch Und Tiefbau",
    "wof:placetype":"venue"
},
  "geometry": {"coordinates":[7.323109,46.41655],"type":"Point"}
}