{
  "type": "Feature",
  "properties": {
    "iso:country":"CH",
    "sg:address":"Oberalpstrasse 35",
    "sg:city":"Chur",
    "sg:orig_category":"Architekturb\u00fcros Bauingenieurb\u00fcros",
    "sg:phone":"+41 81 250 63 63",
    "sg:postcode":"7000",
    "sg:province":"Graubunden",
    "wof:name":"Architektur Und Bauberatung Luzius U. Graf",
    "wof:placetype":"venue"
},
  "geometry": {"coordinates":[9.523283,46.854549],"type":"Point"}
}