{
  "type": "Feature",
  "properties": {
    "iso:country":"CH",
    "sg:address":"Sch\u00fctzengartenstrasse 3",
    "sg:city":"Oberuzwil",
    "sg:orig_category":"Erbringung von Dienstleistungen f\u00fcr Unternehmen Grafikateliers, Design",
    "sg:phone":"+41 71 951 95 06",
    "sg:postcode":"9242",
    "sg:province":"St. Gallen",
    "wof:name":"B\u00e4tschmann Beschriftungen Ag",
    "wof:placetype":"venue"
},
  "geometry": {"coordinates":[9.1221618652,47.4301300049],"type":"Point"}
}