{
  "type": "Feature",
  "properties": {
    "iso:country":"CH",
    "sg:address":"Kirchstrasse 14a",
    "sg:city":"Amriswil",
    "sg:orig_category":"Kinderkrippen U horte",
    "sg:phone":"+41 71 411 16 14",
    "sg:postcode":"8580",
    "sg:province":"Thurgau",
    "wof:name":"Kinderkrippe Amriswil",
    "wof:placetype":"venue"
},
  "geometry": {"coordinates":[9.298740387,47.5470085144],"type":"Point"}
}