{
  "type": "Feature",
  "properties": {
    "addr:full":"Zugerstrasse 70 6340 Baar. Postfach 559 Baar Zug 6341",
    "addr:housenumber":"70;559",
    "addr:postcode":"6340 baar.;6341",
    "addr:street":"Zugerstrasse;Postfach;Zug",
    "iso:country":"CH",
    "sg:address":"Zugerstrasse 70 6340 Baar. Postfach 559",
    "sg:city":"Baar",
    "sg:orig_category":"Architektur U Ingenieurb\u00fcros",
    "sg:phone":"+41 79 414 61 01",
    "sg:postcode":"6341",
    "sg:province":"Zug",
    "wof:name":"Scepan Ag",
    "wof:placetype":"venue"
},
  "geometry": {"coordinates":[8.520032,47.184406],"type":"Point"}
}