{
  "type": "Feature",
  "properties": {
    "iso:country":"CH",
    "sg:address":"6821",
    "sg:city":"Rovio",
    "sg:classifiers":[
        {
            "category":"Travel",
            "subcategory":"Hotels & Motels",
            "type":"Entertainment"
        }
    ],
    "sg:phone":"+41 91 611 27 00",
    "sg:postcode":"6821",
    "sg:province":"Ticino",
    "sg:tags":[
        "hotels",
        "mit",
        "restaurant"
    ],
    "wof:name":"Albergo Del Pesce Di Iseli Andreas, Sandro E Simona",
    "wof:placetype":"venue"
},
  "geometry": {"coordinates":[8.862950325,45.9702606201],"type":"Point"}
}