{
  "type": "Feature",
  "properties": {
    "iso:country":"CH",
    "sg:address":"Bellefontaine Rue 2",
    "sg:city":"Lausanne",
    "sg:orig_category":"RESTAURANTS: TEA-ROOMS",
    "sg:phone":"+41 21 323 41 61",
    "sg:postcode":"1003",
    "sg:province":"Vaud",
    "wof:name":"Toscaflor Sa",
    "wof:placetype":"venue"
},
  "geometry": {"coordinates":[6.6379709244,46.5165214539],"type":"Point"}
}