{
  "type": "Feature",
  "properties": {
    "iso:country":"CH",
    "sg:address":"B\u00fchlstrasse 36",
    "sg:city":"Unter\u00e4geri",
    "sg:orig_category":"Sanit\u00e4r, Heizungs U L\u00fcftungsinstallation Sanit\u00e4rinstallation",
    "sg:phone":"+41 41 750 18 36",
    "sg:postcode":"6314",
    "sg:province":"Zug",
    "wof:name":"Iten-marty Ag",
    "wof:placetype":"venue"
},
  "geometry": {"coordinates":[8.5767745972,47.1332168579],"type":"Point"}
}