{
  "type": "Feature",
  "properties": {
    "iso:country":"CH",
    "sg:address":"Prulay Rue De La 29",
    "sg:city":"Meyrin",
    "sg:orig_category":"Unclassifiable Establishments",
    "sg:postcode":"1217",
    "sg:province":"Gen\u00e8ve",
    "wof:name":"Arts-antiquit\u00e9s, Hugentobler Denis",
    "wof:placetype":"venue"
},
  "geometry": {"coordinates":[6.0722160339,46.2284431458],"type":"Point"}
}