{
  "type": "Feature",
  "properties": {
    "iso:country":"CH",
    "sg:address":"Untere L\u00e4ttenstrasse 2",
    "sg:city":"Geroldswil",
    "sg:orig_category":"Detailhandel mit Beleuchtungs U Haushaltsgegenst\u00e4nden Herstellung von elektrischen Lampen U Leuchten",
    "sg:phone":"+41 17484347",
    "sg:postcode":"8954",
    "sg:province":"Z\u00fcrich",
    "wof:name":"Hugo Spadacini Glas Keramik",
    "wof:placetype":"venue"
},
  "geometry": {"coordinates":[8.406423,47.425396],"type":"Point"}
}