{
  "type": "Feature",
  "properties": {
    "iso:country":"CH",
    "sg:address":"R\u00e9sidence De La C\u00f4te 50",
    "sg:city":"Morges",
    "sg:orig_category":"Sportvereine Eissport Curling",
    "sg:postcode":"1110",
    "sg:province":"Vaud",
    "wof:name":"Curling-club Ls-beau-rivage",
    "wof:placetype":"venue"
},
  "geometry": {"coordinates":[6.4956870079,46.5186653137],"type":"Point"}
}