{
  "type": "Feature",
  "properties": {
    "iso:country":"CH",
    "sg:address":"Winterthurerstrasse 534",
    "sg:city":"Z\u00fcrich",
    "sg:orig_category":"Sonstige pers\u00f6nliche Dienstleistungen",
    "sg:postcode":"8051",
    "sg:province":"Z\u00fcrich",
    "wof:name":"H\u00e4fliger`s Peter Beizli-f\u00fc\u00fcrwehr",
    "wof:placetype":"venue"
},
  "geometry": {"coordinates":[8.5729017258,47.4040641785],"type":"Point"}
}