{
  "type": "Feature",
  "properties": {
    "addr:full":"3993 Grengiols Valais 3993",
    "addr:housenumber":"3993",
    "addr:postcode":"3993",
    "iso:country":"CH",
    "sg:address":"3993",
    "sg:city":"Grengiols",
    "sg:orig_category":"Architektur U Ingenieurb\u00fcros Architekturb\u00fcros",
    "sg:phone":"+41 61 771 03 96",
    "sg:postcode":"3993",
    "sg:province":"Valais",
    "wof:name":"Architekturb\u00fcro Roland M\u00fcller Gmbh Liesberg",
    "wof:placetype":"venue"
},
  "geometry": {"coordinates":[7.42539,47.403381],"type":"Point"}
}