{
  "type": "Feature",
  "properties": {
    "iso:country":"CH",
    "sg:address":"Industriestrasse 6 4227 B\u00fcsserach. Postfach 24",
    "sg:city":"B\u00fcsserach",
    "sg:orig_category":"Detailhandel mit M\u00f6beln U Haushaltsgegenst\u00e4nden",
    "sg:phone":"+41 61 781 16 50",
    "sg:postcode":"4227",
    "sg:province":"Solothurn",
    "wof:name":"Saner Guido Ag",
    "wof:placetype":"venue"
},
  "geometry": {"coordinates":[7.5351719856,47.3955345154],"type":"Point"}
}