{
  "type": "Feature",
  "properties": {
    "iso:country":"CH",
    "sg:address":"Magglingen 2533 Evilard. Postfach",
    "sg:city":"Magglingen/macolin",
    "sg:orig_category":"Verwertung von Milch",
    "sg:postcode":"2532",
    "sg:province":"Bern",
    "wof:name":"Milchverwertungsgenossenschaft Magglingen-leubringen",
    "wof:placetype":"venue"
},
  "geometry": {"coordinates":[7.2355899811,47.1496696472],"type":"Point"}
}