{
  "type": "Feature",
  "properties": {
    "iso:country":"CH",
    "sg:address":"Waldmannstrasse 10a",
    "sg:city":"Z\u00fcrich",
    "sg:orig_category":"Detailhandel mit Geschenkartikeln U Souvenirs Sonstiger Grosshandel",
    "sg:phone":"+41 12620939",
    "sg:postcode":"8001",
    "sg:province":"Z\u00fcrich",
    "wof:name":"Entre Deux Ag",
    "wof:placetype":"venue"
},
  "geometry": {"coordinates":[8.5465583801,47.3687133789],"type":"Point"}
}