{
  "type": "Feature",
  "properties": {
    "iso:country":"CH",
    "sg:address":"6647",
    "sg:city":"Mergoscia",
    "sg:orig_category":"Vereine Fasnacht",
    "sg:postcode":"6647",
    "sg:province":"Ticino",
    "wof:name":"Comitato Carnevale",
    "wof:placetype":"venue"
},
  "geometry": {"coordinates":[8.8461208344,46.2087402344],"type":"Point"}
}