{
  "type": "Feature",
  "properties": {
    "iso:country":"CH",
    "sg:address":"Walcheplatz 12",
    "sg:city":"Z\u00fcrich",
    "sg:orig_category":"Kosmetikinstitute",
    "sg:phone":"+41 32 853 54 60",
    "sg:postcode":"8001",
    "sg:province":"Z\u00fcrich",
    "wof:name":"Heidi Bachmann Institut De Beaut\u00e9 Flora",
    "wof:placetype":"venue"
},
  "geometry": {"coordinates":[6.9187231064,47.0202217102],"type":"Point"}
}