{
  "type": "Feature",
  "properties": {
    "iso:country":"CH",
    "sg:address":"Gubelstrasse 28 8050 Z\u00fcrich. Postfach",
    "sg:city":"Z\u00fcrich",
    "sg:orig_category":"Herstellung von elektronischen Bauelementen",
    "sg:phone":"+41 13131001",
    "sg:postcode":"8050",
    "sg:province":"Z\u00fcrich",
    "wof:name":"Litton Precision Products International, Inc, Wilmington (delaware), Zurich Branch",
    "wof:placetype":"venue"
},
  "geometry": {"coordinates":[8.5443525314,47.4083557129],"type":"Point"}
}