{
  "type": "Feature",
  "properties": {
    "iso:country":"CH",
    "sg:address":"Arbonerstrasse 64",
    "sg:city":"Amriswil",
    "sg:orig_category":"Herstellung von Konstruktionsteilen, Fertigbauteilen U Ausbauelementen aus Holz",
    "sg:phone":"+41 71 411 60 40",
    "sg:postcode":"8580",
    "sg:province":"Thurgau",
    "wof:name":"K\u00fcnzle Herbert",
    "wof:placetype":"venue"
},
  "geometry": {"coordinates":[9.3185949326,47.5411300659],"type":"Point"}
}