{
  "type": "Feature",
  "properties": {
    "iso:country":"CH",
    "sg:address":"K\u00e4genstrasse 7",
    "sg:city":"Reinach",
    "sg:classifiers":[
        {
            "category":"Utilities",
            "subcategory":"Water",
            "type":"Services"
        }
    ],
    "sg:phone":"+41 61 715 61 11",
    "sg:postcode":"4153",
    "sg:province":"Basel-Landschaft",
    "sg:tags":[
        "flow",
        "sewage",
        "meter"
    ],
    "wof:name":"Endress + Hauser Flowtec Ag",
    "wof:placetype":"venue"
},
  "geometry": {"coordinates":[7.598033905,47.4883499146],"type":"Point"}
}