{
  "type": "Feature",
  "properties": {
    "iso:country":"CH",
    "sg:address":"Grand'rue 10 1071 Chexbres Case Postale 60",
    "sg:city":"Chexbres",
    "sg:classifiers":[
        {
            "category":"Travel",
            "subcategory":"Hotels & Motels",
            "type":"Entertainment"
        }
    ],
    "sg:phone":"+41 21 946 11 51",
    "sg:postcode":"1071",
    "sg:province":"Vaud",
    "sg:tags":[
        "hotels",
        "mit",
        "restaurant"
    ],
    "wof:name":"H\u00f4tel Du Lion-d'or",
    "wof:placetype":"venue"
},
  "geometry": {"coordinates":[6.7762470245,46.4821128845],"type":"Point"}
}