{
  "type": "Feature",
  "properties": {
    "iso:country":"CH",
    "sg:address":"Dorfstrasse 13",
    "sg:city":"Schindellegi",
    "sg:orig_category":"Erzeugung U Erstbearbeitung von Aluminium Herstellung von Ausbauelementen aus Metall",
    "sg:phone":"+41 17840989",
    "sg:postcode":"8834",
    "sg:province":"Schwyz",
    "wof:name":"Nova-trend Hansj\u00f6rg Bachmann",
    "wof:placetype":"venue"
},
  "geometry": {"coordinates":[8.7111301422,47.1748962402],"type":"Point"}
}