{
  "type": "Feature",
  "properties": {
    "iso:country":"CH",
    "sg:address":"Dorf 103",
    "sg:city":"Walzenhausen",
    "sg:orig_category":"Detailhandel mit Waren verschiedener Art, Hauptrichtung Nahrungsmittel",
    "sg:phone":"+41 71 888 11 29",
    "sg:postcode":"9428",
    "sg:province":"Appenzell Ausserrhoden",
    "wof:name":"J\u00fcrg & Uschi Frei Fr\u00fcchte Gem\u00fcse",
    "wof:placetype":"venue"
},
  "geometry": {"coordinates":[9.6039190292,47.4505996704],"type":"Point"}
}