{
  "type": "Feature",
  "properties": {
    "iso:country":"CH",
    "sg:address":"Bahnhofstrasse 1",
    "sg:city":"Zurzach",
    "sg:orig_category":"Interessenvertretungen",
    "sg:postcode":"5330",
    "sg:province":"Aargau",
    "wof:name":"Stiftung Kirchlibuck-burgkapelle",
    "wof:placetype":"venue"
},
  "geometry": {"coordinates":[8.2940406799,47.5888824463],"type":"Point"}
}