{
  "type": "Feature",
  "properties": {
    "iso:country":"CH",
    "sg:address":"Lyssstrasse 14",
    "sg:city":"Dotzigen",
    "sg:orig_category":"Sonstige Milchverwertung",
    "sg:phone":"+41 32 351 12 13",
    "sg:postcode":"3293",
    "sg:province":"Bern",
    "wof:name":"Boncas Ag Spezialit\u00e4tenk\u00e4serei",
    "wof:placetype":"venue"
},
  "geometry": {"coordinates":[7.3442769051,47.1188087463],"type":"Point"}
}