{
  "type": "Feature",
  "properties": {
    "iso:country":"CH",
    "sg:address":"Gersauerstrasse 17 6440 Brunnen. Postfach 329",
    "sg:city":"Brunnen",
    "sg:orig_category":"Instandhaltung U Reparatur von Automobilen",
    "sg:phone":"+41 71 744 14 70",
    "sg:postcode":"6440",
    "sg:province":"Schwyz",
    "wof:name":"Inderwildi & Fink Ag",
    "wof:placetype":"venue"
},
  "geometry": {"coordinates":[9.6490335464,47.4477233887],"type":"Point"}
}