{
  "type": "Feature",
  "properties": {
    "addr:full":"R\u00e4tscheng\u00e4ssli 49 Kloten Z\u00fcrich 8302",
    "addr:housenumber":"49",
    "addr:postcode":"8302",
    "addr:street":"Raetschengaessli",
    "iso:country":"CH",
    "sg:address":"R\u00e4tscheng\u00e4ssli 49",
    "sg:city":"Kloten",
    "sg:orig_category":"Detailhandel mit B\u00fcchern, Zeitungen, Schreib U Papeteriewaren",
    "sg:postcode":"8302",
    "sg:province":"Z\u00fcrich",
    "wof:name":"Tutto Comics M. Di Rocco",
    "wof:placetype":"venue"
},
  "geometry": {"coordinates":[8.587532,47.453419],"type":"Point"}
}