{
  "type": "Feature",
  "properties": {
    "iso:country":"CH",
    "sg:address":"Via Gen. Guisan 10 Casella Postale 1150",
    "sg:city":"Biasca",
    "sg:classifiers":[
        {
            "category":"Utilities",
            "subcategory":"Electric",
            "type":"Services"
        }
    ],
    "sg:phone":"+41 91 756 91 91",
    "sg:postcode":"6710",
    "sg:province":"Ticino",
    "sg:tags":[
        "electricity",
        "raw",
        "energy",
        "material"
    ],
    "wof:name":"Societ\u00c0 Elettrica Sopracenerina Ses",
    "wof:placetype":"venue"
},
  "geometry": {"coordinates":[8.9698448181,46.3577651978],"type":"Point"}
}