{
  "type": "Feature",
  "properties": {
    "iso:country":"CH",
    "sg:address":"Bernstrasse 97 3612 Steffisburg. Postfach",
    "sg:city":"Steffisburg",
    "sg:orig_category":"Interessenvertretungen",
    "sg:postcode":"3612",
    "sg:province":"Bern",
    "wof:name":"Verein Kleingewerbe-verbund Schaffung Von Rahmenvertr\u00e4ge Mit Versicherungsgesellschaften Usw",
    "wof:placetype":"venue"
},
  "geometry": {"coordinates":[7.618309021,46.7705764771],"type":"Point"}
}