{
  "type": "Feature",
  "properties": {
    "iso:country":"CH",
    "sg:address":"Avenue De Tivoli 8",
    "sg:city":"Lausanne",
    "sg:orig_category":"Non-Classified Establishments",
    "sg:postcode":"1007",
    "sg:province":"Vaud",
    "wof:name":"Transversal Sa",
    "wof:placetype":"venue"
},
  "geometry": {"coordinates":[6.6216239929,46.5213775635],"type":"Point"}
}