{
  "type": "Feature",
  "properties": {
    "iso:country":"CH",
    "sg:address":"Kornplatz 12",
    "sg:city":"Chur",
    "sg:orig_category":"Detailhandel mit Bekleidung",
    "sg:postcode":"7000",
    "sg:province":"Graubunden",
    "wof:name":"Gasche Hedwig",
    "wof:placetype":"venue"
},
  "geometry": {"coordinates":[9.530893,46.849018],"type":"Point"}
}