{
  "type": "Feature",
  "properties": {
    "iso:country":"CH",
    "sg:address":"Tr\u00fc",
    "sg:city":"Scuol",
    "sg:orig_category":"Sportvereine Turnen Vereine Damen",
    "sg:phone":"+41 81 864 15 09",
    "sg:postcode":"7550",
    "sg:province":"Graubunden",
    "wof:name":"Gruppa Gimnastas",
    "wof:placetype":"venue"
},
  "geometry": {"coordinates":[10.293381691,46.7965927124],"type":"Point"}
}