{
  "type": "Feature",
  "properties": {
    "iso:country":"CH",
    "sg:address":"Dorfstrasse 14",
    "sg:city":"Dachsen",
    "sg:orig_category":"Sportvereine Orientierungslauf",
    "sg:postcode":"8447",
    "sg:province":"Z\u00fcrich",
    "wof:name":"Olg Flims",
    "wof:placetype":"venue"
},
  "geometry": {"coordinates":[9.2852306366,46.8366928101],"type":"Point"}
}