{
  "type": "Feature",
  "properties": {
    "iso:country":"CH",
    "sg:address":"Neherstieg 41",
    "sg:city":"Schaffhausen",
    "sg:orig_category":"Detailhandel mit Damenbekleidung",
    "sg:phone":"+41 52 625 50 86",
    "sg:postcode":"8200",
    "sg:province":"Schaffhausen",
    "wof:name":"Evelyne Plieninger Couture",
    "wof:placetype":"venue"
},
  "geometry": {"coordinates":[8.615549,47.700546],"type":"Point"}
}