{
  "type": "Feature",
  "properties": {
    "iso:country":"CH",
    "sg:address":"Glattalstrasse 561",
    "sg:city":"Z\u00fcrich",
    "sg:classifiers":[
        {
            "category":"Restaurant",
            "type":"Food & Drink"
        }
    ],
    "sg:phone":"+41 19373282",
    "sg:postcode":"8052",
    "sg:province":"Z\u00fcrich",
    "wof:name":"Restaurant Waldegg",
    "wof:placetype":"venue"
},
  "geometry": {"coordinates":[8.8722162247,47.3087615967],"type":"Point"}
}