{
  "type": "Feature",
  "properties": {
    "iso:country":"CH",
    "sg:address":"Tiefenackerstrasse 52",
    "sg:city":"Altst\u00e4tten",
    "sg:classifiers":[
        {
            "category":"Retail",
            "subcategory":"Laundry & Dry Cleaning",
            "type":"Services"
        }
    ],
    "sg:phone":"+41 71 757 64 11",
    "sg:postcode":"9450",
    "sg:province":"St. Gallen",
    "sg:tags":[
        "insulating",
        "accessory"
    ],
    "wof:name":"Polypag Ag",
    "wof:placetype":"venue"
},
  "geometry": {"coordinates":[9.5607843399,47.3796577454],"type":"Point"}
}