{
  "type": "Feature",
  "properties": {
    "iso:country":"CH",
    "sg:address":"St. Martinistrasse 1 3930 Visp. Postfach",
    "sg:city":"Visp",
    "sg:orig_category":"RESTAURANTS: TEA-ROOMS",
    "sg:phone":"+41 27 946 35 75",
    "sg:postcode":"3930",
    "sg:province":"Valais",
    "wof:name":"Restaurant Martinikeller, De Almeida Sousa Liliana",
    "wof:placetype":"venue"
},
  "geometry": {"coordinates":[7.881746769,46.2904243469],"type":"Point"}
}