{
  "type": "Feature",
  "properties": {
    "iso:country":"CH",
    "sg:address":"Hauptstrasse 35",
    "sg:city":"Ziefen",
    "sg:orig_category":"Autogaragen",
    "sg:phone":"+41 61 931 22 68",
    "sg:postcode":"4417",
    "sg:province":"Basel-Landschaft",
    "wof:name":"Andreas Gisin Garage",
    "wof:placetype":"venue"
},
  "geometry": {"coordinates":[7.715117,47.433262],"type":"Point"}
}