{
  "type": "Feature",
  "properties": {
    "iso:country":"CH",
    "sg:address":"Elswil 4",
    "sg:city":"W\u00fcnnewil",
    "sg:orig_category":"Technische, physikalische U chemische Untersuchung",
    "sg:phone":"+41 26 496 36 15",
    "sg:postcode":"3184",
    "sg:province":"Fribourg",
    "wof:name":"Fritest Ag",
    "wof:placetype":"venue"
},
  "geometry": {"coordinates":[7.2582731247,46.8680152893],"type":"Point"}
}