{
  "type": "Feature",
  "properties": {
    "iso:country":"CH",
    "sg:address":"Bahnhofstrasse 10",
    "sg:city":"Worb",
    "sg:orig_category":"Zahnarztpraxen",
    "sg:phone":"+41 31 839 14 07",
    "sg:postcode":"3076",
    "sg:province":"Bern",
    "wof:name":"Dr. Med. Dent. Robert Lukacs Zahnarzt",
    "wof:placetype":"venue"
},
  "geometry": {"coordinates":[7.564125061,46.9287986755],"type":"Point"}
}