{
  "type": "Feature",
  "properties": {
    "iso:country":"CH",
    "sg:address":"Brunnmatt 201/a",
    "sg:city":"Pfaffnau",
    "sg:orig_category":"Herstellung von Teilen U Zubeh\u00f6r f\u00fcr Automobile",
    "sg:phone":"+41 62 754 00 45",
    "sg:postcode":"6264",
    "sg:province":"Luzern",
    "wof:name":"Apd Pl\u00fcss Gmbh",
    "wof:placetype":"venue"
},
  "geometry": {"coordinates":[7.908686161,47.2328147888],"type":"Point"}
}