{
  "type": "Feature",
  "properties": {
    "iso:country":"CH",
    "sg:address":"Route De La P\u00e2le 7 1026 Denges. Postfach",
    "sg:city":"Denges",
    "sg:orig_category":"Instandhaltung U Reparatur von Automobilen",
    "sg:postcode":"1026",
    "sg:province":"Vaud",
    "wof:name":"Garage De La Pale, Vionnet Jean-fran\u00e7ois",
    "wof:placetype":"venue"
},
  "geometry": {"coordinates":[6.5425810814,46.5164451599],"type":"Point"}
}