{
  "type": "Feature",
  "properties": {
    "iso:country":"CH",
    "sg:address":"Bernstrasse 25 3400 Burgdorf. Postfach",
    "sg:city":"Burgdorf",
    "sg:orig_category":"Druckweiterverarbeitung",
    "sg:phone":"+41 34 422 25 21",
    "sg:postcode":"3402",
    "sg:province":"Bern",
    "wof:name":"W\u00e4lchli Hans Peter",
    "wof:placetype":"venue"
},
  "geometry": {"coordinates":[7.6212458611,47.0535697937],"type":"Point"}
}