{
  "type": "Feature",
  "properties": {
    "iso:country":"CH",
    "sg:address":"Reckholder 31",
    "sg:city":"Niederhelfenschwil",
    "sg:orig_category":"Vermittlung von Immobilien Verwaltung von Immobilien",
    "sg:phone":"+41 71 311 24 31",
    "sg:postcode":"9527",
    "sg:province":"St. Gallen",
    "wof:name":"K\u00fcnzle Immobilien-treuhand",
    "wof:placetype":"venue"
},
  "geometry": {"coordinates":[9.3242616653,47.4246368408],"type":"Point"}
}