{
  "type": "Feature",
  "properties": {
    "iso:country":"CH",
    "sg:address":"Hauptstrasse 28",
    "sg:city":"Pfyn",
    "sg:orig_category":"Schlossereien Schmieden",
    "sg:phone":"+41 52 765 17 24",
    "sg:postcode":"8505",
    "sg:province":"Thurgau",
    "wof:name":"Ueli Stump Kunstschmiede & Schlosserei",
    "wof:placetype":"venue"
},
  "geometry": {"coordinates":[8.9544630051,47.5957641602],"type":"Point"}
}