{
  "type": "Feature",
  "properties": {
    "iso:country":"CH",
    "sg:address":"Bas Du Village 11",
    "sg:city":"Plagne",
    "sg:orig_category":"Bauschreinerei Zimmerei, Ingenieurholzbau",
    "sg:phone":"+41 32 358 12 10",
    "sg:postcode":"2536",
    "sg:province":"Bern",
    "wof:name":"Noverraz Menuiserie S\u00e0rl",
    "wof:placetype":"venue"
},
  "geometry": {"coordinates":[7.288775,47.189163],"type":"Point"}
}