{
  "type": "Feature",
  "properties": {
    "iso:country":"CH",
    "sg:address":"Gewerbeweg 1",
    "sg:city":"Seftigen",
    "sg:orig_category":"Technische, physikalische U chemische Untersuchung",
    "sg:phone":"+41 33 356 27 25",
    "sg:postcode":"3662",
    "sg:province":"Bern",
    "wof:name":"Kern Peter",
    "wof:placetype":"venue"
},
  "geometry": {"coordinates":[7.5269560814,46.7882843018],"type":"Point"}
}