{
  "type": "Feature",
  "properties": {
    "addr:full":"Ischlag 7 Buckten Basel-Landschaft 4446",
    "addr:housenumber":"7",
    "addr:postcode":"4446",
    "addr:street":"Ischlag",
    "iso:country":"CH",
    "sg:address":"Ischlag 7",
    "sg:city":"Buckten",
    "sg:orig_category":"Architektur U Ingenieurb\u00fcros Architekturb\u00fcros",
    "sg:phone":"+41 62 299 28 23",
    "sg:postcode":"4446",
    "sg:province":"Basel-Landschaft",
    "wof:name":"Fankhauser Architekturb\u00fcro",
    "wof:placetype":"venue"
},
  "geometry": {"coordinates":[7.84744,47.40781],"type":"Point"}
}