{
  "type": "Feature",
  "properties": {
    "iso:country":"CH",
    "sg:address":"Bernstrasse",
    "sg:city":"Lyssach",
    "sg:classifiers":[
        {
            "category":"Travel",
            "subcategory":"Hotels & Motels",
            "type":"Entertainment"
        }
    ],
    "sg:postcode":"3421",
    "sg:province":"Bern",
    "sg:tags":[
        "hotels",
        "mit",
        "restaurant"
    ],
    "wof:name":"Blue Motel Ag",
    "wof:placetype":"venue"
},
  "geometry": {"coordinates":[8.7972450256,47.3216514587],"type":"Point"}
}