{
  "type": "Feature",
  "properties": {
    "iso:country":"CH",
    "sg:address":"Habsburgerstrasse 22",
    "sg:city":"Luzern",
    "sg:orig_category":"Pensionskassen",
    "sg:phone":"+41 41103422",
    "sg:postcode":"6003",
    "sg:province":"Luzern",
    "wof:name":"Personalf\u00fcrsorgestiftung Gamag Management Ag",
    "wof:placetype":"venue"
},
  "geometry": {"coordinates":[8.3071346283,47.0469894409],"type":"Point"}
}