{
  "type": "Feature",
  "properties": {
    "iso:country":"CH",
    "sg:address":"Lindenpk. 1",
    "sg:city":"Bern",
    "sg:classifiers":[
        {
            "category":"Utilities",
            "subcategory":"Telephone",
            "type":"Services"
        }
    ],
    "sg:phone":"+41 31 342 11 11",
    "sg:postcode":"3050",
    "sg:province":"Bern",
    "sg:tags":[
        "telecommunication"
    ],
    "wof:name":"Swisscom International Ag",
    "wof:placetype":"venue"
},
  "geometry": {"coordinates":[7.4449810982,46.9342308044],"type":"Point"}
}