{
  "type": "Feature",
  "properties": {
    "iso:country":"CH",
    "sg:address":"5401 Baden. Postfach",
    "sg:city":"Baden",
    "sg:orig_category":"Vereine Musik/Blasmusik",
    "sg:phone":"+41 56 241 16 12",
    "sg:postcode":"5401",
    "sg:province":"Aargau",
    "wof:name":"Musikgesellschaft Badenia",
    "wof:placetype":"venue"
},
  "geometry": {"coordinates":[8.3076000214,47.4735183716],"type":"Point"}
}