{
  "type": "Feature",
  "properties": {
    "iso:country":"CH",
    "sg:address":"Lindenb\u00fchl 45 6330 Cham. Postfach",
    "sg:city":"Cham",
    "sg:orig_category":"Softwareentwicklung U beratung",
    "sg:postcode":"6330",
    "sg:province":"Zug",
    "wof:name":"Buholzer Communication Dienstleistungen Im Bereich Informations-technologie Usw",
    "wof:placetype":"venue"
},
  "geometry": {"coordinates":[8.4473562241,47.1940422058],"type":"Point"}
}