{
  "type": "Feature",
  "properties": {
    "iso:country":"CH",
    "sg:address":"Oltnerstrasse 3",
    "sg:city":"Sch\u00f6nenwerd",
    "sg:orig_category":"Bau U Wohngenossenschaften",
    "sg:postcode":"5012",
    "sg:province":"Solothurn",
    "wof:name":"Genossenschaft Alterssiedlung",
    "wof:placetype":"venue"
},
  "geometry": {"coordinates":[8.859149,47.258293],"type":"Point"}
}