{
  "type": "Feature",
  "properties": {
    "iso:country":"CH",
    "sg:address":"L\u00e4ngackerstrasse 7",
    "sg:city":"Selzach",
    "sg:orig_category":"Landw. Genossenschaften Viehzucht",
    "sg:postcode":"2545",
    "sg:province":"Solothurn",
    "wof:name":"Braunviehzuchtgenossenschaft St.gallen",
    "wof:placetype":"venue"
},
  "geometry": {"coordinates":[9.3187265396,47.4020996094],"type":"Point"}
}