{
  "type": "Feature",
  "properties": {
    "iso:country":"CH",
    "sg:address":"Staffelstrasse 17",
    "sg:city":"Jegenstorf",
    "sg:orig_category":"Arztpraxen",
    "sg:phone":"+41 31 761 00 55",
    "sg:postcode":"3303",
    "sg:province":"Bern",
    "wof:name":"Dr.med.ernst Wyss Spezialarzt Fmh",
    "wof:placetype":"venue"
},
  "geometry": {"coordinates":[7.508593,47.054817],"type":"Point"}
}