{
  "type": "Feature",
  "properties": {
    "iso:country":"CH",
    "sg:address":"Route De Cit\u00e9-ouest 1 1196 Gland. Postfach",
    "sg:city":"Gland",
    "sg:orig_category":"Elektroinstallation",
    "sg:phone":"+41 22 364 26 78",
    "sg:postcode":"1196",
    "sg:province":"Vaud",
    "wof:name":"Claude-alain Zehnder Installations \u00e9lectriques",
    "wof:placetype":"venue"
},
  "geometry": {"coordinates":[6.2584462166,46.423210144],"type":"Point"}
}