{
  "type": "Feature",
  "properties": {
    "iso:country":"CH",
    "sg:address":"Rue Des Esserts 4",
    "sg:city":"Cernier",
    "sg:orig_category":"Herstellung von Konstruktionsteilen, Fertigbauteilen U Ausbauelementen aus Holz",
    "sg:phone":"+41 22 343 22 23",
    "sg:postcode":"2053",
    "sg:province":"Neuch\u00e2tel",
    "wof:name":"Menuiserie Hiltpold F.",
    "wof:placetype":"venue"
},
  "geometry": {"coordinates":[6.1440839767,46.1844329834],"type":"Point"}
}