{
  "type": "Feature",
  "properties": {
    "iso:country":"CH",
    "sg:address":"Sattelstrasse 10",
    "sg:city":"Steinerberg",
    "sg:orig_category":"RESTAURANTS: TEA-ROOMS",
    "sg:phone":"+41 41 832 22 66",
    "sg:postcode":"6416",
    "sg:province":"Schwyz",
    "wof:name":"Restaurant Hirschen, Krummenacher Max",
    "wof:placetype":"venue"
},
  "geometry": {"coordinates":[8.5853805542,47.0538368225],"type":"Point"}
}