{
  "type": "Feature",
  "properties": {
    "iso:country":"CH",
    "sg:address":"Rue Haldimand 6",
    "sg:city":"Lausanne",
    "sg:orig_category":"Detailhandel mit Uhren U Schmuck",
    "sg:phone":"+41 21 323 47 01",
    "sg:postcode":"1003",
    "sg:province":"Vaud",
    "wof:name":"Michel Collaud Bijouterie",
    "wof:placetype":"venue"
},
  "geometry": {"coordinates":[6.63129282,46.5227928162],"type":"Point"}
}