{
  "type": "Feature",
  "properties": {
    "iso:country":"CH",
    "sg:address":"Fliederweg 6",
    "sg:city":"Menziken",
    "sg:orig_category":"Grosshandel mit keramischen Erzeugnissen, Glaswaren U Reinigungsmitteln",
    "sg:phone":"+41 62 771 49 36",
    "sg:postcode":"5737",
    "sg:province":"Aargau",
    "wof:name":"Glas- + Metallbautechnik Walter Jurt Ing. Htl",
    "wof:placetype":"venue"
},
  "geometry": {"coordinates":[8.1964759827,47.2463798523],"type":"Point"}
}