{
  "type": "Feature",
  "properties": {
    "iso:country":"CH",
    "sg:address":"Rickenbachstrasse 52 6430 Schwyz. Postfach 15",
    "sg:city":"Schwyz",
    "sg:orig_category":"Herstellung von k\u00e4lte U lufttechnischen Erzeugnissen f\u00fcr gewerbliche Zwecke Installation von Heizung",
    "sg:phone":"+41 41 811 47 57",
    "sg:postcode":"6431",
    "sg:province":"Schwyz",
    "wof:name":"Beeler K\u00e4lte-/klimatechnik Ag",
    "wof:placetype":"venue"
},
  "geometry": {"coordinates":[8.6598711014,47.0217704773],"type":"Point"}
}