{
  "type": "Feature",
  "properties": {
    "iso:country":"CH",
    "sg:address":"R\u00f6merbrunnenweg 7",
    "sg:city":"Grenchen",
    "sg:orig_category":"Sportvereine Turnen Vereine Damen",
    "sg:phone":"+41 71 912 16 54",
    "sg:postcode":"2540",
    "sg:province":"Solothurn",
    "wof:name":"Satus Frauenriege Wil",
    "wof:placetype":"venue"
},
  "geometry": {"coordinates":[9.054473877,47.4714927673],"type":"Point"}
}