{
  "type": "Feature",
  "properties": {
    "iso:country":"CH",
    "sg:address":"Granges Rue Des 13",
    "sg:city":"Payerne",
    "sg:orig_category":"Werbung",
    "sg:phone":"+41 26 660 85 25",
    "sg:postcode":"1530",
    "sg:province":"Vaud",
    "wof:name":"Advertising Import. Z\u00fcger Anita",
    "wof:placetype":"venue"
},
  "geometry": {"coordinates":[6.9387660027,46.8213653564],"type":"Point"}
}