{
  "type": "Feature",
  "properties": {
    "iso:country":"CH",
    "sg:address":"Milit\u00e4rstrasse 76",
    "sg:city":"Z\u00fcrich",
    "sg:classifiers":[
        {
            "category":"Professional",
            "subcategory":"Advertising",
            "type":"Services"
        }
    ],
    "sg:phone":"+41 81 302 81 00",
    "sg:postcode":"8004",
    "sg:province":"Z\u00fcrich",
    "sg:tags":[
        "article",
        "plastic"
    ],
    "wof:name":"Plastic Ag",
    "wof:placetype":"venue"
},
  "geometry": {"coordinates":[9.50294,47.01112],"type":"Point"}
}