{
  "type": "Feature",
  "properties": {
    "iso:country":"CH",
    "sg:address":"Mitteldorfstrasse 5 5612 Villmergen. Postfach 184",
    "sg:city":"Villmergen",
    "sg:orig_category":"Elektroinstallation Herstellung von Elektromotoren, Generatoren U Transformatoren",
    "sg:phone":"+41 56 622 80 80",
    "sg:postcode":"5612",
    "sg:province":"Aargau",
    "wof:name":"Notter Elektro- + Telefonanlagen",
    "wof:placetype":"venue"
},
  "geometry": {"coordinates":[8.2447099686,47.3464698792],"type":"Point"}
}