{
  "type": "Feature",
  "properties": {
    "iso:country":"CH",
    "sg:address":"Chemin De Pr\u00e9laz 18",
    "sg:city":"Nyon",
    "sg:orig_category":"Werbeagenturen",
    "sg:phone":"+41 61 751 14 66",
    "sg:postcode":"1260",
    "sg:province":"Vaud",
    "wof:name":"Pege Hug & Th\u00fcring Werbung",
    "wof:placetype":"venue"
},
  "geometry": {"coordinates":[7.5900158882,47.4771575928],"type":"Point"}
}