{
  "type": "Feature",
  "properties": {
    "iso:country":"CH",
    "sg:address":"Schwerzenbachstrasse 3",
    "sg:city":"F\u00e4llanden",
    "sg:orig_category":"Fotografische Laboratorien",
    "sg:phone":"+41 18254659",
    "sg:postcode":"8117",
    "sg:province":"Z\u00fcrich",
    "wof:name":"Pietro Ruffini Farblabor",
    "wof:placetype":"venue"
},
  "geometry": {"coordinates":[8.6394691467,47.3712425232],"type":"Point"}
}