{
  "type": "Feature",
  "properties": {
    "iso:country":"CH",
    "sg:address":"Malzstrasse 17",
    "sg:city":"Z\u00fcrich",
    "sg:orig_category":"Satzherstellung U Reproduktion",
    "sg:postcode":"8045",
    "sg:province":"Z\u00fcrich",
    "wof:name":"Discovery Girardin & Sch\u00f6ni",
    "wof:placetype":"venue"
},
  "geometry": {"coordinates":[6.8299050331,47.102809906],"type":"Point"}
}