{
  "type": "Feature",
  "properties": {
    "addr:full":"Birkenstrasse 13 Luzern Luzern 6003",
    "addr:housenumber":"13",
    "addr:postcode":"6003",
    "addr:street":"Birkenstrasse",
    "iso:country":"CH",
    "sg:address":"Birkenstrasse 13",
    "sg:city":"Luzern",
    "sg:orig_category":"Arbeitnehmerverb\u00e4nde",
    "sg:phone":"+41 41 310 02 41",
    "sg:postcode":"6003",
    "sg:province":"Luzern",
    "wof:name":"Schweiz.polierverband Sekt.lu Herrn Anton Regli",
    "wof:placetype":"venue"
},
  "geometry": {"coordinates":[8.303999,47.041664],"type":"Point"}
}