{
  "type": "Feature",
  "properties": {
    "iso:country":"CH",
    "sg:address":"Bachweg 28",
    "sg:city":"Olten",
    "sg:orig_category":"Chemin\u00e9e- and Ofenbau",
    "sg:phone":"+41 62 296 73 70",
    "sg:postcode":"4600",
    "sg:province":"Solothurn",
    "wof:name":"Willi Wyss Chemin\u00e9e-& Ofenbau",
    "wof:placetype":"venue"
},
  "geometry": {"coordinates":[7.916698,47.348545],"type":"Point"}
}