{
  "type": "Feature",
  "properties": {
    "iso:country":"CH",
    "sg:address":"Bremgartenstrasse 160",
    "sg:city":"Aristau",
    "sg:orig_category":"Abbruch U Sprenggewerbe, Erdbewegungsarbeiten",
    "sg:postcode":"5628",
    "sg:province":"Aargau",
    "wof:name":"Stocker Tiefbau",
    "wof:placetype":"venue"
},
  "geometry": {"coordinates":[8.671449,47.441353],"type":"Point"}
}