{
  "type": "Feature",
  "properties": {
    "iso:country":"CH",
    "sg:address":"Oetlingerstrasse 81 4000 Basel. Postfach",
    "sg:city":"Basel",
    "sg:orig_category":"Interessenvertretungen",
    "sg:postcode":"4051",
    "sg:province":"Basel-Stadt",
    "wof:name":"Stiftung Job Training",
    "wof:placetype":"venue"
},
  "geometry": {"coordinates":[7.5919809341,47.5679016113],"type":"Point"}
}