{
  "type": "Feature",
  "properties": {
    "iso:country":"CH",
    "sg:address":"Baselstrasse 71 4142 M\u00fcnchenstein. Postfach",
    "sg:city":"M\u00fcnchenstein",
    "sg:orig_category":"Herstellung von sonstiger Bekleidung U Bekleidungszubeh\u00f6r",
    "sg:postcode":"4142",
    "sg:province":"Basel-Landschaft",
    "wof:name":"Kinder-lagune Weil",
    "wof:placetype":"venue"
},
  "geometry": {"coordinates":[7.6176700592,47.5229187012],"type":"Point"}
}