{
  "type": "Feature",
  "properties": {
    "iso:country":"CH",
    "sg:address":"Dorfstrasse 58",
    "sg:city":"Oberengstringen",
    "sg:orig_category":"Zahntechnische Laboratorien",
    "sg:phone":"+41 17503947",
    "sg:postcode":"8102",
    "sg:province":"Z\u00fcrich",
    "wof:name":"Vratislav Prevor Zahntechnisches Labor",
    "wof:placetype":"venue"
},
  "geometry": {"coordinates":[8.4623584747,47.4091720581],"type":"Point"}
}