{
  "type": "Feature",
  "properties": {
    "iso:country":"CH",
    "sg:address":"Bahnhofstrasse 42",
    "sg:city":"Grenchen",
    "sg:orig_category":"Cad/Cam Software",
    "sg:phone":"+41 32 654 97 40",
    "sg:postcode":"2540",
    "sg:province":"Solothurn",
    "wof:name":"Dacom Ag",
    "wof:placetype":"venue"
},
  "geometry": {"coordinates":[7.396262,47.189064],"type":"Point"}
}