{
  "type": "Feature",
  "properties": {
    "iso:country":"CH",
    "sg:address":"Rue Dufour 16",
    "sg:city":"Biel/bienne",
    "sg:orig_category":"Vermietung U Verpachtung von eigenen Immobilien",
    "sg:phone":"+41 32 322 16 19",
    "sg:postcode":"2500",
    "sg:province":"Bern",
    "wof:name":"Vabim Biel Ag",
    "wof:placetype":"venue"
},
  "geometry": {"coordinates":[7.2899799347,47.1467399597],"type":"Point"}
}