{
  "type": "Feature",
  "properties": {
    "iso:country":"CH",
    "sg:address":"Ludretikonerstrasse 15 8800 Thalwil. Postfach",
    "sg:city":"Thalwil",
    "sg:orig_category":"Werbegrafikateliers",
    "sg:phone":"+41 17209611",
    "sg:postcode":"8800",
    "sg:province":"Z\u00fcrich",
    "wof:name":"Hanspeter Stutz Grafiker",
    "wof:placetype":"venue"
},
  "geometry": {"coordinates":[8.5625047684,47.2998085022],"type":"Point"}
}