{
  "type": "Feature",
  "properties": {
    "iso:country":"CH",
    "sg:address":"Mitteldorfstrasse 21",
    "sg:city":"Ossingen",
    "sg:orig_category":"Detailhandel mit Waren verschiedener Art, Hauptrichtung Nahrungsmittel",
    "sg:phone":"+41 52 317 16 51",
    "sg:postcode":"8475",
    "sg:province":"Z\u00fcrich",
    "wof:name":"Patricia Kerker Volg-laden Ossingen",
    "wof:placetype":"venue"
},
  "geometry": {"coordinates":[8.7260103226,47.6111488342],"type":"Point"}
}