{
  "type": "Feature",
  "properties": {
    "iso:country":"CH",
    "sg:address":"Rue Du Scex 38",
    "sg:city":"Sion",
    "sg:classifiers":[
        {
            "category":"Travel",
            "subcategory":"Hotels & Motels",
            "type":"Entertainment"
        }
    ],
    "sg:phone":"+41 27 322 91 71",
    "sg:postcode":"1950",
    "sg:province":"Valais",
    "sg:tags":[
        "hotels",
        "mit",
        "restaurant"
    ],
    "wof:name":"Gaillet Marianne",
    "wof:placetype":"venue"
},
  "geometry": {"coordinates":[7.3682618141,46.2324066162],"type":"Point"}
}