{
  "type": "Feature",
  "properties": {
    "iso:country":"CH",
    "sg:address":"Bahnhofstrasse 21",
    "sg:city":"Toffen",
    "sg:classifiers":[
        {
            "category":"Restaurant",
            "type":"Food & Drink"
        }
    ],
    "sg:phone":"+41 31 819 83 93",
    "sg:postcode":"3125",
    "sg:province":"Bern",
    "wof:name":"Caf\u00e9-bar 21",
    "wof:placetype":"venue"
},
  "geometry": {"coordinates":[7.4943737984,46.8601608276],"type":"Point"}
}