{
  "type": "Feature",
  "properties": {
    "iso:country":"CH",
    "sg:address":"Zugerstrasse 15",
    "sg:city":"Cham",
    "sg:orig_category":"Unclassifiable Establishments",
    "sg:postcode":"6330",
    "sg:province":"Zug",
    "wof:name":"Wyrsch Holding Ag",
    "wof:placetype":"venue"
},
  "geometry": {"coordinates":[8.4615259171,47.1817016602],"type":"Point"}
}