{
  "type": "Feature",
  "properties": {
    "iso:country":"CH",
    "sg:address":"Chemin Cr\u00e9bolaz",
    "sg:city":"Noville",
    "sg:orig_category":"Fussreflexzonenmassage",
    "sg:phone":"+41 21 960 26 35",
    "sg:postcode":"1845",
    "sg:province":"Vaud",
    "wof:name":"Institut Energy Massage-r\u00e9flexologie",
    "wof:placetype":"venue"
},
  "geometry": {"coordinates":[6.9008450508,46.3815460205],"type":"Point"}
}