{
  "type": "Feature",
  "properties": {
    "iso:country":"CH",
    "sg:address":"St. Gallerstrasse 14 8589 Sitterdorf. Postfach",
    "sg:city":"Sitterdorf",
    "sg:orig_category":"Grosshandel mit Holz U Baustoffen",
    "sg:postcode":"8589",
    "sg:province":"Thurgau",
    "wof:name":"Stierli - Holz, Inh. E. Walser",
    "wof:placetype":"venue"
},
  "geometry": {"coordinates":[9.2539634705,47.5052490234],"type":"Point"}
}