{
  "type": "Feature",
  "properties": {
    "iso:country":"CH",
    "sg:address":"Stadtplatz 22",
    "sg:city":"Aarberg",
    "sg:orig_category":"G\u00fcterbef\u00f6rderung im Strassenverkehr",
    "sg:phone":"+41 26 670 51 60",
    "sg:postcode":"3270",
    "sg:province":"Bern",
    "wof:name":"Marti Ernst Ag, Zweigniederlassung Murten Zweigniederlassung Murten",
    "wof:placetype":"venue"
},
  "geometry": {"coordinates":[7.1084527969,46.9252319336],"type":"Point"}
}