{
  "type": "Feature",
  "properties": {
    "iso:country":"CH",
    "sg:address":"Wengistrasse 18",
    "sg:city":"Solothurn",
    "sg:classifiers":[
        {
            "category":"Professional",
            "subcategory":"Employment Agencies",
            "type":"Services"
        }
    ],
    "sg:phone":"+41 32 621 60 80",
    "sg:postcode":"4500",
    "sg:province":"Solothurn",
    "sg:tags":[
        "personal",
        "u",
        "stellenvermittlung"
    ],
    "wof:name":"Kofmehl Und Partner Gmbh",
    "wof:placetype":"venue"
},
  "geometry": {"coordinates":[7.5331869125,47.2072868347],"type":"Point"}
}