{
  "type": "Feature",
  "properties": {
    "iso:country":"CH",
    "sg:address":"Hirschengraben 1",
    "sg:city":"Z\u00fcrich",
    "sg:classifiers":[
        {
            "category":"Banks & Credit Unions",
            "subcategory":"Bank",
            "type":"Services"
        }
    ],
    "sg:phone":"+41 22 817 88 33",
    "sg:postcode":"8024",
    "sg:province":"Z\u00fcrich",
    "wof:name":"Banque Multi Commerciale",
    "wof:placetype":"venue"
},
  "geometry": {"coordinates":[6.141838,46.204739],"type":"Point"}
}