{
  "type": "Feature",
  "properties": {
    "iso:country":"CH",
    "sg:address":"Chemin Eug\u00e8ne-grasset 2 1000 Lausanne. Postfach",
    "sg:city":"Lausanne",
    "sg:orig_category":"Fachdetailhandel in Verkaufsr\u00e4umen Sonstiger Fachdetailhandel in Verkaufsr\u00e4umen",
    "sg:phone":"+41 71 755 80 40",
    "sg:postcode":"1001",
    "sg:province":"Vaud",
    "wof:name":"Jumag Ag",
    "wof:placetype":"venue"
},
  "geometry": {"coordinates":[9.5336313248,47.3815574646],"type":"Point"}
}