{
  "type": "Feature",
  "properties": {
    "iso:country":"CH",
    "sg:address":"Tal 599",
    "sg:city":"Urn\u00e4sch",
    "sg:classifiers":[
        {
            "category":"Restaurant",
            "type":"Food & Drink"
        }
    ],
    "sg:phone":"+41 71 364 12 32",
    "sg:postcode":"9107",
    "sg:province":"Appenzell Ausserrhoden",
    "wof:name":"Restaurant Sternen",
    "wof:placetype":"venue"
},
  "geometry": {"coordinates":[9.2753152847,47.306728363],"type":"Point"}
}