{
  "type": "Feature",
  "properties": {
    "iso:country":"CH",
    "sg:address":"Eichwaldstrasse 27a 6005 Luzern. Postfach",
    "sg:city":"Luzern",
    "sg:orig_category":"Kunsthandel",
    "sg:phone":"+41 41 311 22 01",
    "sg:postcode":"6002",
    "sg:province":"Luzern",
    "wof:name":"Raum F.aktuelle Kunst Prosart Galerie",
    "wof:placetype":"venue"
},
  "geometry": {"coordinates":[8.3011388779,47.0370559692],"type":"Point"}
}