{
  "type": "Feature",
  "properties": {
    "iso:country":"CH",
    "sg:address":"Unterdorfstrasse 17",
    "sg:city":"Lausen",
    "sg:orig_category":"Herstellung von Konstruktionsteilen, Fertigbauteilen U Ausbauelementen aus Holz",
    "sg:phone":"+41 61 922 08 26",
    "sg:postcode":"4415",
    "sg:province":"Basel-Landschaft",
    "wof:name":"Max Peter-kaufmann",
    "wof:placetype":"venue"
},
  "geometry": {"coordinates":[7.7600879669,47.4726600647],"type":"Point"}
}