{
  "type": "Feature",
  "properties": {
    "iso:country":"CH",
    "sg:address":"Bahnhofstrasse 2",
    "sg:city":"M\u00e4nnedorf",
    "sg:orig_category":"Detailhandel mit Radio U Fernsehger\u00e4ten Elektroinstallation",
    "sg:postcode":"8708",
    "sg:province":"Z\u00fcrich",
    "wof:name":"Gigaline Gmbh Computersysteme",
    "wof:placetype":"venue"
},
  "geometry": {"coordinates":[8.6909227371,47.2539405823],"type":"Point"}
}