{
  "type": "Feature",
  "properties": {
    "iso:country":"CH",
    "sg:address":"Rue Du Chasseral 7",
    "sg:city":"Pr\u00eales",
    "sg:orig_category":"Elektroinstallation Technische B\u00fcros Elektro",
    "sg:postcode":"2515",
    "sg:province":"Bern",
    "wof:name":"Alexander Weigel Av Coach",
    "wof:placetype":"venue"
},
  "geometry": {"coordinates":[8.5245847702,47.4780578613],"type":"Point"}
}