{
  "type": "Feature",
  "properties": {
    "iso:country":"CH",
    "sg:address":"Kasernenstrasse 56",
    "sg:city":"Liestal",
    "sg:classifiers":[
        {
            "category":"Insurance",
            "subcategory":"Insurance Agent",
            "type":"Services"
        }
    ],
    "sg:phone":"+41 61 921 39 80",
    "sg:postcode":"4410",
    "sg:province":"Basel-Landschaft",
    "sg:tags":[
        "versicherungsagenturen",
        "-broker"
    ],
    "wof:name":"Vtb Versicherung-treuhand Beider Basel Gmbh",
    "wof:placetype":"venue"
},
  "geometry": {"coordinates":[7.740913868,47.4802322388],"type":"Point"}
}