{
  "type": "Feature",
  "properties": {
    "iso:country":"CH",
    "sg:address":"Rosenweg",
    "sg:city":"Sennwald",
    "sg:orig_category":"Wirtschaftspr\u00fcfung, Steuerberatung U Treuhand",
    "sg:phone":"+41 81 757 18 25",
    "sg:postcode":"9466",
    "sg:province":"St. Gallen",
    "wof:name":"Revin Gmbh",
    "wof:placetype":"venue"
},
  "geometry": {"coordinates":[9.4906053543,47.2529449463],"type":"Point"}
}