{
  "type": "Feature",
  "properties": {
    "iso:country":"CH",
    "sg:address":"La Grange-d'enhaut",
    "sg:city":"Sassel",
    "sg:orig_category":"Mit Sport verbundene T\u00e4tigkeiten",
    "sg:phone":"+41 24 492 37 78",
    "sg:postcode":"1534",
    "sg:province":"Fribourg",
    "wof:name":"Robert Urweider Man\u00e8ge & \u00e9cole D'\u00e9quitation",
    "wof:placetype":"venue"
},
  "geometry": {"coordinates":[7.1570019722,46.3499794006],"type":"Point"}
}