{
  "type": "Feature",
  "properties": {
    "iso:country":"CH",
    "sg:address":"Dorfstrasse 35 3652 Hilterfingen. Postfach 60",
    "sg:city":"Hilterfingen",
    "sg:orig_category":"Architektur U Ingenieurb\u00fcros Architekturb\u00fcros",
    "sg:phone":"+41 33 243 43 36",
    "sg:postcode":"3652",
    "sg:province":"Bern",
    "wof:name":"Pierre Baeriswyl Ag",
    "wof:placetype":"venue"
},
  "geometry": {"coordinates":[7.658631,46.737007],"type":"Point"}
}