{
  "type": "Feature",
  "properties": {
    "iso:country":"CH",
    "sg:address":"Industriestr. 21",
    "sg:city":"Mellingen",
    "sg:classifiers":[
        {
            "category":"Shopping",
            "subcategory":"Computers & Home Electronics",
            "type":"Retail Goods"
        }
    ],
    "sg:phone":"+41 56 491 01 81",
    "sg:postcode":"5507",
    "sg:province":"Aargau",
    "sg:tags":[
        "equipment",
        "electrical",
        "component",
        "electric",
        "electronic"
    ],
    "wof:name":"Vibratec Ag",
    "wof:placetype":"venue"
},
  "geometry": {"coordinates":[8.275718689,47.4102859497],"type":"Point"}
}