{
  "type": "Feature",
  "properties": {
    "iso:country":"CH",
    "sg:address":"Kantonsstrasse 58",
    "sg:city":"Glis",
    "sg:orig_category":"Detailhandel mit Waren verschiedener Art, Hauptrichtung Nahrungsmittel Sonstiger Detailhandel mit Me",
    "sg:phone":"+41 27 922 46 22",
    "sg:postcode":"3902",
    "sg:province":"Valais",
    "wof:name":"Migros-markt",
    "wof:placetype":"venue"
},
  "geometry": {"coordinates":[7.9702692032,46.3086700439],"type":"Point"}
}