{
  "type": "Feature",
  "properties": {
    "iso:country":"CH",
    "sg:address":"Oberdorfstrasse 21 8810 Horgen. Postfach 632-c",
    "sg:city":"Horgen",
    "sg:orig_category":"Herstellung von Metallerzeugnissen ohne Maschinenbau Herstellung von sonstigen Werkzeugmaschinen",
    "sg:phone":"+41 17285555",
    "sg:postcode":"8812",
    "sg:province":"Z\u00fcrich",
    "wof:name":"Hans Oetiker Ag, Maschinen Und Apparatefabrik",
    "wof:placetype":"venue"
},
  "geometry": {"coordinates":[8.5884475708,47.2608032227],"type":"Point"}
}