{
  "type": "Feature",
  "properties": {
    "iso:country":"CH",
    "sg:address":"Hauptstrasse 38",
    "sg:city":"Ober\u00e4geri",
    "sg:orig_category":"Nahrungsmittel-Industrie: Rohstoffe",
    "sg:phone":"+41 41 750 75 17",
    "sg:postcode":"6315",
    "sg:province":"Zug",
    "wof:name":"Essig & Oel R\u00f6sch Matthias",
    "wof:placetype":"venue"
},
  "geometry": {"coordinates":[8.6093540192,47.1358718872],"type":"Point"}
}