{
  "type": "Feature",
  "properties": {
    "iso:country":"CH",
    "sg:address":"Moncor 1",
    "sg:city":"Villars-sur-gl\u00e2ne",
    "sg:orig_category":"RESTAURANTS: TEA-ROOMS",
    "sg:phone":"+41 22 342 31 09",
    "sg:postcode":"1752",
    "sg:province":"Fribourg",
    "wof:name":"Bouchon \u00e0 Tonio Sa",
    "wof:placetype":"venue"
},
  "geometry": {"coordinates":[6.1394929886,46.1797866821],"type":"Point"}
}