{
  "type": "Feature",
  "properties": {
    "iso:country":"CH",
    "sg:address":"B\u00e4rengand 8",
    "sg:city":"Schattdorf",
    "sg:orig_category":"G\u00fcterbef\u00f6rderung im Strassenverkehr",
    "sg:phone":"+41 41 870 63 39",
    "sg:postcode":"6467",
    "sg:province":"Uri",
    "wof:name":"Arnold Alois",
    "wof:placetype":"venue"
},
  "geometry": {"coordinates":[8.6511487961,46.8609848022],"type":"Point"}
}