{
  "type": "Feature",
  "properties": {
    "iso:country":"CH",
    "sg:address":"Route De Riddes 21 1950 Sitten. Postfach",
    "sg:city":"Sion",
    "sg:orig_category":"G\u00fcterbef\u00f6rderung im Strassenverkehr",
    "sg:postcode":"1951",
    "sg:province":"Valais",
    "wof:name":"Aymon Sa, Succursale De Sion",
    "wof:placetype":"venue"
},
  "geometry": {"coordinates":[7.3743038177,46.2273712158],"type":"Point"}
}