{
  "type": "Feature",
  "properties": {
    "addr:full":"Karlihof 4 Malans Graubunden 7208",
    "addr:housenumber":"4",
    "addr:postcode":"7208",
    "addr:street":"Karlihof",
    "iso:country":"CH",
    "sg:address":"Karlihof 4",
    "sg:city":"Malans",
    "sg:classifiers":[
        {
            "category":"Wholesale",
            "subcategory":"Wine & Distilled Alcoholic Beverages",
            "type":"Manufacturing & Wholesale Goods"
        }
    ],
    "sg:phone":"+41 81 300 00 30",
    "sg:postcode":"7208",
    "sg:province":"Graubunden",
    "sg:tags":[
        "australian"
    ],
    "wof:name":"Cottinelli Ag",
    "wof:placetype":"venue"
},
  "geometry": {"coordinates":[9.560423,46.971886],"type":"Point"}
}