{
  "type": "Feature",
  "properties": {
    "iso:country":"CH",
    "sg:address":"Siewerdtstrasse 7 8050 Z\u00fcrich. Postfach 8050 Z\u00fcrich",
    "sg:city":"Zust",
    "sg:orig_category":"Grosshandel mit sonstigen Nahrungsmitteln",
    "sg:postcode":"50",
    "wof:name":"Alaska Import Keel A.",
    "wof:placetype":"venue"
},
  "geometry": {"coordinates":[8.6855363846,47.2635192871],"type":"Point"}
}