{
  "type": "Feature",
  "properties": {
    "iso:country":"CH",
    "sg:address":"Jussy Route De 14b",
    "sg:city":"Th\u00f4nex",
    "sg:orig_category":"K\u00fcnstlerische U schriftstellerische T\u00e4tigkeiten U Darbietungen",
    "sg:postcode":"1226",
    "sg:province":"Gen\u00e8ve",
    "wof:name":"J.-m. Ottet",
    "wof:placetype":"venue"
},
  "geometry": {"coordinates":[6.1982450485,46.1879501343],"type":"Point"}
}