{
  "type": "Feature",
  "properties": {
    "iso:country":"CH",
    "sg:address":"Ohne Domizil 6318 Walchwil. Postfach",
    "sg:city":"Werthenstein",
    "sg:orig_category":"Vermietung U Verpachtung von eigenen Immobilien",
    "sg:postcode":"6106",
    "sg:province":"Luzern",
    "wof:name":"A + B Immobilien Ag",
    "wof:placetype":"venue"
},
  "geometry": {"coordinates":[8.5119657516,47.1009902954],"type":"Point"}
}