{
  "type": "Feature",
  "properties": {
    "iso:country":"CH",
    "sg:address":"Po Box 171 Direktion Kochergasse 6",
    "sg:city":"Bern",
    "sg:classifiers":[
        {
            "category":"Banks & Credit Unions",
            "subcategory":"Bank",
            "type":"Services"
        }
    ],
    "sg:postcode":"3011",
    "sg:province":"Bern",
    "wof:name":"Ansbacher (switzerland) Limited",
    "wof:placetype":"venue"
},
  "geometry": {"coordinates":[8.53955,47.37706],"type":"Point"}
}