{
  "type": "Feature",
  "properties": {
    "iso:country":"CH",
    "sg:address":"3673",
    "sg:city":"Linden",
    "sg:orig_category":"Sportvereine Sch\u00fctzen Pistolen-& Gewehr",
    "sg:postcode":"3673",
    "sg:province":"Bern",
    "wof:name":"Feldsch\u00fctzenges.kurzenberg",
    "wof:placetype":"venue"
},
  "geometry": {"coordinates":[7.6791849136,46.8479537964],"type":"Point"}
}