{
  "type": "Feature",
  "properties": {
    "iso:country":"CH",
    "sg:address":"3930",
    "sg:city":"Visp",
    "sg:orig_category":"Unclassifiable Establishments",
    "sg:phone":"+41 27 946 44 66",
    "sg:postcode":"3930",
    "sg:province":"Valais",
    "wof:name":"Zerzuben Touristik Ag",
    "wof:placetype":"venue"
},
  "geometry": {"coordinates":[7.8827300072,46.2922286987],"type":"Point"}
}