{
  "type": "Feature",
  "properties": {
    "iso:country":"CH",
    "sg:address":"Freie Strasse 103",
    "sg:city":"Basel",
    "sg:orig_category":"Detailhandel mit Damenbekleidung",
    "sg:phone":"+41 61 273 11 70",
    "sg:postcode":"4051",
    "sg:province":"Basel-Stadt",
    "wof:name":"Beldona Ag",
    "wof:placetype":"venue"
},
  "geometry": {"coordinates":[7.591784,47.554405],"type":"Point"}
}