{
  "type": "Feature",
  "properties": {
    "iso:country":"CH",
    "sg:address":"Aegerte",
    "sg:city":"Feschel-guttet",
    "sg:orig_category":"Einzelhandel mit Automobilteilen U Zubeh\u00f6r Herstellung von Bereifungen",
    "sg:phone":"+41 27 473 40 40",
    "sg:postcode":"3956",
    "sg:province":"Valais",
    "wof:name":"Abr Pneu Ag",
    "wof:placetype":"venue"
},
  "geometry": {"coordinates":[7.6607561111,46.3219223022],"type":"Point"}
}