{
  "type": "Feature",
  "properties": {
    "iso:country":"CH",
    "sg:address":"Gare 1",
    "sg:city":"Fribourg",
    "sg:orig_category":"Sonstiger Fachdetailhandel mit Nahrungsmitteln, Getr\u00e4nken U Tabak in Verkaufsr\u00e4umen",
    "sg:phone":"+41 26 322 55 85",
    "sg:postcode":"1700",
    "sg:province":"Fribourg",
    "wof:name":"Trudy Tinguely Produits Di\u00e9t\u00e9tiques",
    "wof:placetype":"venue"
},
  "geometry": {"coordinates":[7.1512551308,46.8025474548],"type":"Point"}
}