{
  "type": "Feature",
  "properties": {
    "iso:country":"CH",
    "sg:address":"Marterey Rue 38 1005 Lausanne. Postfach",
    "sg:city":"Lausanne",
    "sg:orig_category":"Sonstiger Grosshandel",
    "sg:phone":"+41 21 784 30 97",
    "sg:postcode":"1003",
    "sg:province":"Vaud",
    "wof:name":"Trexa Sa Repr\u00e9sentation, Comm. Et Fabricat. De Produits Manufactur\u00e9s",
    "wof:placetype":"venue"
},
  "geometry": {"coordinates":[6.6390318871,46.5207824707],"type":"Point"}
}