{
  "type": "Feature",
  "properties": {
    "iso:country":"CH",
    "sg:address":"Route De Reculan",
    "sg:city":"Ecublens",
    "sg:classifiers":[
        {
            "category":"Professional",
            "subcategory":"Management & Consulting",
            "type":"Services"
        }
    ],
    "sg:phone":"+41 21 701 42 61",
    "sg:postcode":"1024",
    "sg:province":"Vaud",
    "sg:tags":[
        "hazardous",
        "waste"
    ],
    "wof:name":"Matthey Transports S.a.",
    "wof:placetype":"venue"
},
  "geometry": {"coordinates":[6.5548272133,46.5405387878],"type":"Point"}
}