{
  "type": "Feature",
  "properties": {
    "iso:country":"CH",
    "sg:address":"Schaffhauserstrasse 158",
    "sg:city":"Kloten",
    "sg:orig_category":"Kosmetikinstitute",
    "sg:phone":"+41 18136969",
    "sg:postcode":"8302",
    "sg:province":"Z\u00fcrich",
    "wof:name":"Rike Eigenmann Coiffure & Kosmetik Piccolina",
    "wof:placetype":"venue"
},
  "geometry": {"coordinates":[8.5798187256,47.453830719],"type":"Point"}
}