{
  "type": "Feature",
  "properties": {
    "iso:country":"CH",
    "sg:address":"Ch\u00e8vre Chemin De La",
    "sg:city":"Yverdon-les-bains",
    "sg:orig_category":"Vermietung U Verpachtung von eigenen Immobilien",
    "sg:postcode":"1400",
    "sg:province":"Vaud",
    "wof:name":"Carri\u00e8res Du Ch\u00e2telard Sa",
    "wof:placetype":"venue"
},
  "geometry": {"coordinates":[6.6414198875,46.7786331177],"type":"Point"}
}