{
  "type": "Feature",
  "properties": {
    "iso:country":"CH",
    "sg:address":"Bahnhofstrasse 11",
    "sg:city":"Brig",
    "sg:orig_category":"Detailhandel mit Uhren U Schmuck Reparatur von Uhren U Schmuck",
    "sg:phone":"+41 27 923 36 31",
    "sg:postcode":"3900",
    "sg:province":"Valais",
    "wof:name":"Christ Uhren & Schmuck Ag",
    "wof:placetype":"venue"
},
  "geometry": {"coordinates":[7.9883818626,46.317237854],"type":"Point"}
}