{
  "type": "Feature",
  "properties": {
    "addr:full":"Fliederweg 12 Zug Zug 6300",
    "addr:housenumber":"12",
    "addr:postcode":"6300",
    "addr:street":"Fliederweg;Zug",
    "iso:country":"CH",
    "sg:address":"Fliederweg 12",
    "sg:city":"Zug",
    "sg:orig_category":"Betrieb von Taxis",
    "sg:phone":"+41 41 711 11 66",
    "sg:postcode":"6300",
    "sg:province":"Zug",
    "wof:name":"Zuger Taxi V.kunter",
    "wof:placetype":"venue"
},
  "geometry": {"coordinates":[8.51102,47.179089],"type":"Point"}
}