{
  "type": "Feature",
  "properties": {
    "iso:country":"CH",
    "sg:address":"Archstrasse 6",
    "sg:city":"Winterthur",
    "sg:orig_category":"Werbeagenturen",
    "sg:phone":"+41 52 209 09 20",
    "sg:postcode":"8400",
    "sg:province":"Z\u00fcrich",
    "wof:name":"Deep River Images",
    "wof:placetype":"venue"
},
  "geometry": {"coordinates":[8.7235956192,47.4982452393],"type":"Point"}
}