{
  "type": "Feature",
  "properties": {
    "iso:country":"CH",
    "sg:address":"Grienbachstrasse 17",
    "sg:city":"Zug",
    "sg:orig_category":"Herstellung von sonstigen organischen Grundstoffen U Chemikalien",
    "sg:postcode":"6300",
    "sg:province":"Zug",
    "wof:name":"Gypsum Research Sa",
    "wof:placetype":"venue"
},
  "geometry": {"coordinates":[8.523443222,47.1832809448],"type":"Point"}
}