{
  "type": "Feature",
  "properties": {
    "iso:country":"CH",
    "sg:address":"Lee-g\u00e4ssli Grubenwald 3770 Zweisimmen. Postfach 440",
    "sg:city":"Zweisimmen",
    "sg:orig_category":"Sportschulen Ski-& Snowboardschulen",
    "sg:phone":"+41 33 733 13 33",
    "sg:postcode":"3770",
    "sg:province":"Bern",
    "wof:name":"Langlaufschule Herrn Werner Tschanz",
    "wof:placetype":"venue"
},
  "geometry": {"coordinates":[7.3827462196,46.5823860168],"type":"Point"}
}