{
  "type": "Feature",
  "properties": {
    "iso:country":"CH",
    "sg:address":"Baselstrasse 70",
    "sg:city":"Laufen",
    "sg:orig_category":"Zimmerei, Ingenieurholzbau",
    "sg:phone":"+41 61 761 66 58",
    "sg:postcode":"4242",
    "sg:province":"Basel-Landschaft",
    "wof:name":"Alfred Meyer Zimmerei",
    "wof:placetype":"venue"
},
  "geometry": {"coordinates":[7.5059671402,47.4236755371],"type":"Point"}
}