{
  "type": "Feature",
  "properties": {
    "iso:country":"CH",
    "sg:address":"Schaffhauserstrasse 1",
    "sg:city":"Schleitheim",
    "sg:orig_category":"RESTAURANTS: TEA-ROOMS",
    "sg:postcode":"8226",
    "sg:province":"Schaffhausen",
    "wof:name":"Avogaro Reto + Co",
    "wof:placetype":"venue"
},
  "geometry": {"coordinates":[8.4805421829,47.7468109131],"type":"Point"}
}