{
  "type": "Feature",
  "properties": {
    "iso:country":"CH",
    "sg:address":"Neubr\u00fcckstrasse 76",
    "sg:city":"Bern",
    "sg:orig_category":"Handels-H\u00e4user U Gesellschaften",
    "sg:postcode":"3012",
    "sg:province":"Bern",
    "wof:name":"Solsens Gmbh",
    "wof:placetype":"venue"
},
  "geometry": {"coordinates":[7.4373588562,46.9573936462],"type":"Point"}
}