{
  "type": "Feature",
  "properties": {
    "iso:country":"CH",
    "sg:address":"Lux 3",
    "sg:city":"Landquart",
    "sg:orig_category":"Sportvereine Turnen",
    "sg:phone":"+41 81 322 53 06",
    "sg:postcode":"7302",
    "sg:province":"Graubunden",
    "wof:name":"Gymnastische Gesellschaft",
    "wof:placetype":"venue"
},
  "geometry": {"coordinates":[9.5626602173,46.9677810669],"type":"Point"}
}