{
  "type": "Feature",
  "properties": {
    "iso:country":"CH",
    "sg:address":"Aspacherstrasse 58 8413 Neftenbach. Postfach",
    "sg:city":"Winterthur",
    "sg:orig_category":"Non-Classified Establishments",
    "sg:postcode":"8404",
    "sg:province":"Z\u00fcrich",
    "wof:name":"Mano A Mano Mode Design Boutique",
    "wof:placetype":"venue"
},
  "geometry": {"coordinates":[139.2158203125,37.8366394043],"type":"Point"}
}