{
  "type": "Feature",
  "properties": {
    "iso:country":"CH",
    "sg:address":"Holbeinstrasse 18",
    "sg:city":"Basel",
    "sg:orig_category":"Interessenvertretungen",
    "sg:phone":"+41 61 267 31 11",
    "sg:postcode":"4051",
    "sg:province":"Basel-Stadt",
    "wof:name":"Universit\u00e4t Philisophisch-historische Faktult\u00e4t Aepyptologisches Seminar",
    "wof:placetype":"venue"
},
  "geometry": {"coordinates":[7.5841169357,47.554233551],"type":"Point"}
}