{
  "type": "Feature",
  "properties": {
    "iso:country":"CH",
    "sg:address":"Zone Industrielle Pr\u00e8s-bersot",
    "sg:city":"Cornaux",
    "sg:classifiers":[
        {
            "category":"Autos & Motor Vehicles",
            "subcategory":"Fuel & Gas Station",
            "type":"Retail Goods"
        }
    ],
    "sg:phone":"+41 32 758 72 00",
    "sg:postcode":"2087",
    "sg:province":"Neuch\u00e2tel",
    "sg:tags":[
        "pump",
        "high-pressure"
    ],
    "wof:name":"Vogel - Rocano S.a.",
    "wof:placetype":"venue"
},
  "geometry": {"coordinates":[7.019343853,47.0383148193],"type":"Point"}
}