{
  "type": "Feature",
  "properties": {
    "iso:country":"CH",
    "sg:address":"Petit-lancy Avenue Du 7 1213 Petit-lancy. Postfach",
    "sg:city":"Petit-lancy",
    "sg:orig_category":"Interessenvertretungen",
    "sg:phone":"+41 22 793 33 22",
    "sg:postcode":"1213",
    "sg:province":"Gen\u00e8ve",
    "wof:name":"Fondation Clair Bois",
    "wof:placetype":"venue"
},
  "geometry": {"coordinates":[6.1169581413,46.1915054321],"type":"Point"}
}