{
  "type": "Feature",
  "properties": {
    "iso:country":"CH",
    "sg:address":"Konstanzer Strasse 31",
    "sg:city":"Rossr\u00fcti",
    "sg:orig_category":"Grosshandel mit Spielwaren Grosshandel mit Textilien",
    "sg:phone":"+41 71 222 77 40",
    "sg:postcode":"9512",
    "sg:province":"St. Gallen",
    "wof:name":"Filafil Ag Textilien Engros",
    "wof:placetype":"venue"
},
  "geometry": {"coordinates":[9.3725337982,47.4216957092],"type":"Point"}
}