{
  "type": "Feature",
  "properties": {
    "iso:country":"CH",
    "sg:address":"Dorfstrasse 4",
    "sg:city":"Guntalingen",
    "sg:orig_category":"Innenausbau",
    "sg:phone":"+41 79 671 53 22",
    "sg:postcode":"8468",
    "sg:province":"Z\u00fcrich",
    "wof:name":"Heinz Windler Innenausbau",
    "wof:placetype":"venue"
},
  "geometry": {"coordinates":[8.7676239014,47.6300621033],"type":"Point"}
}