{
  "type": "Feature",
  "properties": {
    "iso:country":"CH",
    "sg:address":"Gehrenackerweg 2",
    "sg:city":"Grellingen",
    "sg:classifiers":[
        {
            "category":"Structure",
            "subcategory":"Warehouse",
            "type":"Public Place"
        }
    ],
    "sg:phone":"+41 61 741 18 00",
    "sg:postcode":"4203",
    "sg:province":"Basel-Landschaft",
    "sg:tags":[
        "air-conditioning",
        "system"
    ],
    "wof:name":"Badertscher Service Ag",
    "wof:placetype":"venue"
},
  "geometry": {"coordinates":[7.581032,47.440182],"type":"Point"}
}