{
  "type": "Feature",
  "properties": {
    "iso:country":"CH",
    "sg:address":"R\u00e4ffelstrasse 25 8045 Z\u00fcrich",
    "sg:city":"Zust",
    "sg:orig_category":"Herstellung von sonstigen M\u00f6beln",
    "sg:postcode":"45",
    "wof:name":"Gwm Agency Garten- U. Wohnm\u00f6bel A. Treglia",
    "wof:placetype":"venue"
},
  "geometry": {"coordinates":[8.5118503571,47.3567810059],"type":"Point"}
}