{
  "type": "Feature",
  "properties": {
    "iso:country":"CH",
    "sg:address":"Pont Rue Du 2",
    "sg:city":"Tavannes",
    "sg:classifiers":[
        {
            "category":"Bars & Pubs",
            "type":"Food & Drink"
        }
    ],
    "sg:postcode":"2710",
    "sg:province":"Bern",
    "wof:name":"Savoldelli & Cie",
    "wof:placetype":"venue"
},
  "geometry": {"coordinates":[7.199656,47.220047],"type":"Point"}
}