{
  "type": "Feature",
  "properties": {
    "iso:country":"CH",
    "sg:address":"8376",
    "sg:city":"Fischingen",
    "sg:orig_category":"Kauf U Verkauf von Immobilien auf eigene Rechnung",
    "sg:postcode":"8376",
    "sg:province":"Thurgau",
    "wof:name":"Br\u00fcndeltobel Ag",
    "wof:placetype":"venue"
},
  "geometry": {"coordinates":[8.9690742493,47.4147911072],"type":"Point"}
}