{
  "type": "Feature",
  "properties": {
    "iso:country":"CH",
    "sg:address":"Friedhofstrasse 13",
    "sg:city":"Schwyz",
    "sg:orig_category":"Blumen U Zierpflanzenbau Detailhandel mit Blumen U Pflanzen",
    "sg:phone":"+41 71 755 49 71",
    "sg:postcode":"6430",
    "sg:province":"Schwyz",
    "wof:name":"M\u00fcller-blumen Ag",
    "wof:placetype":"venue"
},
  "geometry": {"coordinates":[9.542464,47.378216],"type":"Point"}
}