{
  "type": "Feature",
  "properties": {
    "iso:country":"CH",
    "sg:address":"Gr\u00fctstrasse 28 8134 Adliswil. Postfach",
    "sg:city":"Adliswil",
    "sg:orig_category":"Pensionskassen",
    "sg:postcode":"8134",
    "sg:province":"Z\u00fcrich",
    "wof:name":"Personalf\u00fcrsorgestiftung Der Firma Eggenberger Hans Ag Central-garage Und Der Ihr Angeschlossenen Firmen",
    "wof:placetype":"venue"
},
  "geometry": {"coordinates":[9.6351900101,47.4310188293],"type":"Point"}
}