{
  "type": "Feature",
  "properties": {
    "iso:country":"CH",
    "sg:address":"La P\u00e2le",
    "sg:city":"Echandens",
    "sg:orig_category":"Vermietung U Verpachtung von eigenen Immobilien",
    "sg:phone":"+41 21 801 33 83",
    "sg:postcode":"1026",
    "sg:province":"Vaud",
    "wof:name":"Rochat Edouard Sa",
    "wof:placetype":"venue"
},
  "geometry": {"coordinates":[6.5408301353,46.534286499],"type":"Point"}
}