{
  "type": "Feature",
  "properties": {
    "iso:country":"CH",
    "sg:address":"Seestrasse 557",
    "sg:city":"Z\u00fcrich",
    "sg:orig_category":"Campingpl\u00e4tze Detailhandel mit Zeitungen U Zeitschriften Kioske",
    "sg:phone":"+41 14821612",
    "sg:postcode":"8038",
    "sg:province":"Z\u00fcrich",
    "wof:name":"Camping Seebucht Gmbh",
    "wof:placetype":"venue"
},
  "geometry": {"coordinates":[8.540714,47.335403],"type":"Point"}
}