{
  "type": "Feature",
  "properties": {
    "iso:country":"CH",
    "sg:address":"Rigiblickstrasse 92",
    "sg:city":"Weggis",
    "sg:classifiers":[
        {
            "category":"Insurance",
            "subcategory":"Insurance Agent",
            "type":"Services"
        }
    ],
    "sg:phone":"+41 41 390 10 01",
    "sg:postcode":"6353",
    "sg:province":"Luzern",
    "sg:tags":[
        "versicherungsagenturen",
        "-broker"
    ],
    "wof:name":"Basler Versicherungen Agentur Steve Erni",
    "wof:placetype":"venue"
},
  "geometry": {"coordinates":[8.4321308136,47.0360488892],"type":"Point"}
}