{
  "type": "Feature",
  "properties": {
    "addr:full":"Avenue De Montchoisi 35 1006 Lausanne. Postfach Lausanne Vaud 1001",
    "addr:housenumber":"35",
    "addr:postcode":"1006;postfach;1001",
    "addr:street":"Avenue De Montchoisi",
    "iso:country":"CH",
    "sg:address":"Avenue De Montchoisi 35 1006 Lausanne. Postfach",
    "sg:city":"Lausanne",
    "sg:orig_category":"Aktivit\u00e4ten der Generalunternehmen im Baugewerbe Vermittlung von Immobilien",
    "sg:phone":"+41 21 613 15 00",
    "sg:postcode":"1001",
    "sg:province":"Vaud",
    "wof:name":"G\u00f6hner Merkur Sa Entreprise G\u00e9n\u00e9rale",
    "wof:placetype":"venue"
},
  "geometry": {"coordinates":[6.634657,46.512459],"type":"Point"}
}