{
  "type": "Feature",
  "properties": {
    "iso:country":"CH",
    "sg:address":"Klotenerstrasse 21",
    "sg:city":"Bassersdorf",
    "sg:orig_category":"RESTAURANTS: TEA-ROOMS",
    "sg:postcode":"8303",
    "sg:province":"Z\u00fcrich",
    "wof:name":"Topaloglu Imbiss",
    "wof:placetype":"venue"
},
  "geometry": {"coordinates":[8.6268615723,47.4439239502],"type":"Point"}
}