{
  "type": "Feature",
  "properties": {
    "iso:country":"CH",
    "sg:address":"H\u00f6fnerstrasse 15",
    "sg:city":"Unter\u00e4geri",
    "sg:orig_category":"Wasserversorgung",
    "sg:phone":"+41 41 750 13 34",
    "sg:postcode":"6314",
    "sg:province":"Zug",
    "wof:name":"Wasserversorgung Wilbrunnen Ag",
    "wof:placetype":"venue"
},
  "geometry": {"coordinates":[8.5847949982,47.1357498169],"type":"Point"}
}