{
  "type": "Feature",
  "properties": {
    "addr:full":"Bahnhofplatz 3 Herisau Appenzell Ausserrhoden 9100",
    "addr:housenumber":"3",
    "addr:postcode":"9100",
    "addr:street":"Bahnhofplatz;Ausserrhoden",
    "iso:country":"CH",
    "sg:address":"Bahnhofplatz 3",
    "sg:city":"Herisau",
    "sg:orig_category":"Bahnhofbuffets Restaurants",
    "sg:phone":"+41 21 921 09 95",
    "sg:postcode":"9100",
    "sg:province":"Appenzell Ausserrhoden",
    "wof:name":"Buffet De La Gare Du Mont-p\u00e9lerin",
    "wof:placetype":"venue"
},
  "geometry": {"coordinates":[6.831296,46.482079],"type":"Point"}
}