{
  "type": "Feature",
  "properties": {
    "iso:country":"CH",
    "sg:address":"Forst 100",
    "sg:city":"Thunstetten",
    "sg:orig_category":"Detailhandel mit Brot, Back U S\u00fcsswaren",
    "sg:phone":"+41 62 963 12 85",
    "sg:postcode":"4922",
    "sg:province":"Bern",
    "wof:name":"Rudolf Rickli B\u00e4ckerei",
    "wof:placetype":"venue"
},
  "geometry": {"coordinates":[7.73995,47.200508],"type":"Point"}
}