{
  "type": "Feature",
  "properties": {
    "iso:country":"CH",
    "sg:address":"Via Beltramina 10",
    "sg:city":"Lugano",
    "sg:classifiers":[
        {
            "category":"Restaurant",
            "type":"Food & Drink"
        }
    ],
    "sg:phone":"+41 91 972 95 98",
    "sg:postcode":"6900",
    "sg:province":"Ticino",
    "wof:name":"Ristorante Grigionese",
    "wof:placetype":"venue"
},
  "geometry": {"coordinates":[8.9576120377,46.0170326233],"type":"Point"}
}