{
  "type": "Feature",
  "properties": {
    "iso:country":"CH",
    "sg:address":"Feldmoos 5",
    "sg:city":"Richterswil",
    "sg:orig_category":"Instandhaltung U Reparatur von Automobilen",
    "sg:postcode":"8805",
    "sg:province":"Z\u00fcrich",
    "wof:name":"Automobile Scherer Res",
    "wof:placetype":"venue"
},
  "geometry": {"coordinates":[8.7051200867,47.2075004578],"type":"Point"}
}