{
  "type": "Feature",
  "properties": {
    "iso:country":"CH",
    "sg:address":"Uitikonerstrasse 23",
    "sg:city":"Schlieren",
    "sg:orig_category":"Kauf U Verkauf von Immobilien auf eigene Rechnung",
    "sg:postcode":"8952",
    "sg:province":"Z\u00fcrich",
    "wof:name":"Immowir Immobilien Bewirtschaftung Ag",
    "wof:placetype":"venue"
},
  "geometry": {"coordinates":[8.4483880997,47.3956031799],"type":"Point"}
}