{
  "type": "Feature",
  "properties": {
    "iso:country":"CH",
    "sg:address":"Aroserstrasse",
    "sg:city":"Maladers",
    "sg:classifiers":[
        {
            "category":"Restaurant",
            "type":"Food & Drink"
        }
    ],
    "sg:phone":"+41 19321074",
    "sg:postcode":"7026",
    "sg:province":"Graubunden",
    "wof:name":"Restaurant Post",
    "wof:placetype":"venue"
},
  "geometry": {"coordinates":[8.7921962738,47.3190307617],"type":"Point"}
}