{
  "type": "Feature",
  "properties": {
    "iso:country":"CH",
    "sg:address":"H\u00f6heweg 2",
    "sg:city":"M\u00fcnchenbuchsee",
    "sg:orig_category":"Detailhandel mit S\u00e4uglings U Kinderbekleidung Fachdetailhandel in Verkaufsr\u00e4umen",
    "sg:phone":"+41 31 869 11 77",
    "sg:postcode":"3053",
    "sg:province":"Bern",
    "wof:name":"Merlin, Franziska Schild",
    "wof:placetype":"venue"
},
  "geometry": {"coordinates":[7.4475059509,47.0205535889],"type":"Point"}
}