{
  "type": "Feature",
  "properties": {
    "iso:country":"CH",
    "sg:address":"Burgstrasse 71",
    "sg:city":"Ennenda",
    "sg:orig_category":"Malerei",
    "sg:phone":"+41 55 640 22 75",
    "sg:postcode":"8755",
    "sg:province":"Glarus",
    "wof:name":"Kurt Hauser Ag Malergesch\u00e4ft",
    "wof:placetype":"venue"
},
  "geometry": {"coordinates":[9.078795433,47.0329093933],"type":"Point"}
}