{
  "type": "Feature",
  "properties": {
    "iso:country":"CH",
    "sg:address":"Guggig\u00e4ssli 10",
    "sg:city":"Frutigen",
    "sg:orig_category":"Grosshandel mit Datenverarbeitungsger\u00e4ten Softwareentwicklung U beratung",
    "sg:phone":"+41 33 671 33 66",
    "sg:postcode":"3714",
    "sg:province":"Bern",
    "wof:name":"Informaticon",
    "wof:placetype":"venue"
},
  "geometry": {"coordinates":[7.6538619995,46.5799179077],"type":"Point"}
}