{
  "type": "Feature",
  "properties": {
    "iso:country":"CH",
    "sg:address":"Oberdorf 320",
    "sg:city":"Plasselb",
    "sg:orig_category":"Detailhandel mit elektrischen Haushalts-,Radio U Fernsehger\u00e4ten sowie Musikinstrumenten",
    "sg:phone":"+41 26 419 20 88",
    "sg:postcode":"1737",
    "sg:province":"Fribourg",
    "wof:name":"Rtv R\u00fcffieux",
    "wof:placetype":"venue"
},
  "geometry": {"coordinates":[7.2522602081,46.7323989868],"type":"Point"}
}