{
  "type": "Feature",
  "properties": {
    "addr:full":"Webereistrasse 47 Adliswil Z\u00fcrich 8134",
    "addr:housenumber":"47",
    "addr:postcode":"8134",
    "addr:street":"Webereistrasse",
    "iso:country":"CH",
    "sg:address":"Webereistrasse 47",
    "sg:city":"Adliswil",
    "sg:orig_category":"Datenbanken",
    "sg:phone":"+41 17107020",
    "sg:postcode":"8134",
    "sg:province":"Z\u00fcrich",
    "wof:name":"Ex-press Fotoagentur",
    "wof:placetype":"venue"
},
  "geometry": {"coordinates":[8.525591,47.306751],"type":"Point"}
}