{
  "type": "Feature",
  "properties": {
    "iso:country":"CH",
    "sg:address":"Sur Le Lavoir 186",
    "sg:city":"Courcelon",
    "sg:orig_category":"Architektur U Ingenieurb\u00fcros Herstellung von sonstigen Maschinen f\u00fcr unspezifische Verwendung",
    "sg:phone":"+41 32 422 07 16",
    "sg:postcode":"2823",
    "sg:province":"Jura",
    "wof:name":"Mesh Ag",
    "wof:placetype":"venue"
},
  "geometry": {"coordinates":[7.390955,47.36166],"type":"Point"}
}