{
  "type": "Feature",
  "properties": {
    "iso:country":"CH",
    "sg:address":"Dietersmattstrasse 6",
    "sg:city":"Giswil",
    "sg:orig_category":"Detailhandel mit Brot, Back U S\u00fcsswaren",
    "sg:phone":"+41 41 675 11 77",
    "sg:postcode":"6074",
    "sg:province":"Obwalden",
    "wof:name":"Bruno Vogler B\u00e4ckerei-konditorei",
    "wof:placetype":"venue"
},
  "geometry": {"coordinates":[8.187235,46.838852],"type":"Point"}
}