{
  "type": "Feature",
  "properties": {
    "iso:country":"CH",
    "sg:address":"Irchelstrasse 13 8427 Rorbas. Postfach",
    "sg:city":"Rorbas",
    "sg:orig_category":"Grosshandel mit Nahrungsmitteln, Getr\u00e4nken U Tabakwaren ohne ausgepr\u00e4gten Schwerpunkt",
    "sg:postcode":"8427",
    "sg:province":"Z\u00fcrich",
    "wof:name":"Asian Concepts Management Gmbh",
    "wof:placetype":"venue"
},
  "geometry": {"coordinates":[8.5812120438,47.531463623],"type":"Point"}
}