{
  "type": "Feature",
  "properties": {
    "iso:country":"CH",
    "sg:address":"Deutsche Strasse 35 7000 Chur. Postfach",
    "sg:city":"Chur",
    "sg:classifiers":[
        {
            "category":"Restaurant",
            "type":"Food & Drink"
        }
    ],
    "sg:phone":"+41 81 353 33 69",
    "sg:postcode":"7005",
    "wof:name":"Restaurant Oldtimer",
    "wof:placetype":"venue"
},
  "geometry": {"coordinates":[9.5401802063,46.8862686157],"type":"Point"}
}