{
  "type": "Feature",
  "properties": {
    "iso:country":"CH",
    "sg:address":"Station",
    "sg:city":"Rothenburg",
    "sg:orig_category":"Non-Classified Establishments",
    "sg:phone":"+41 41 280 11 87",
    "sg:postcode":"6023",
    "sg:province":"Luzern",
    "wof:name":"Restaurant Bahnhof",
    "wof:placetype":"venue"
},
  "geometry": {"coordinates":[8.2537822723,47.0861740112],"type":"Point"}
}