{
  "type": "Feature",
  "properties": {
    "iso:country":"CH",
    "sg:address":"Via Bosciarina",
    "sg:city":"Arbedo",
    "sg:orig_category":"Elektroinstallation Herstellung von sonstigen elektrischen Ausr\u00fcstungen",
    "sg:phone":"+41 17132424",
    "sg:postcode":"6517",
    "sg:province":"Ticino",
    "wof:name":"Elsener & Co Ag F\u00fcr Elektrotechnische Anlagen",
    "wof:placetype":"venue"
},
  "geometry": {"coordinates":[8.5437078476,47.2856483459],"type":"Point"}
}