{
  "type": "Feature",
  "properties": {
    "iso:country":"CH",
    "sg:address":"Bahnhofstrasse 21",
    "sg:city":"Zug",
    "sg:orig_category":"Sonstiger Grosshandel",
    "sg:phone":"+41 41 710 66 44",
    "sg:postcode":"6300",
    "sg:province":"Zug",
    "wof:name":"Centrotrade Investment Ag",
    "wof:placetype":"venue"
},
  "geometry": {"coordinates":[8.5156917572,47.1697540283],"type":"Point"}
}