{
  "type": "Feature",
  "properties": {
    "iso:country":"CH",
    "sg:address":"Route Des Carres 34",
    "sg:city":"Meinier",
    "sg:orig_category":"Rebbau",
    "sg:phone":"+41 27 458 36 57",
    "sg:postcode":"1252",
    "sg:province":"Gen\u00e8ve",
    "wof:name":"Gabriel Duc Vigneron-encaveur",
    "wof:placetype":"venue"
},
  "geometry": {"coordinates":[7.4784898758,46.2839508057],"type":"Point"}
}