{
  "type": "Feature",
  "properties": {
    "addr:full":"H\u00f6heweg 72 Interlaken Bern 3800",
    "addr:housenumber":"72",
    "addr:postcode":"3800",
    "addr:street":"Hoeheweg",
    "iso:country":"CH",
    "sg:address":"H\u00f6heweg 72",
    "sg:city":"Interlaken",
    "sg:orig_category":"Detailhandel mit B\u00fcchern, Zeitungen, Schreib U Papeteriewaren",
    "sg:postcode":"3800",
    "sg:province":"Bern",
    "wof:name":"Presse + Kiosk H\u00f6heweg Ag",
    "wof:placetype":"venue"
},
  "geometry": {"coordinates":[7.862903,46.688442],"type":"Point"}
}