{
  "type": "Feature",
  "properties": {
    "addr:full":"Winterthurerstrasse 25 Z\u00fcrich Z\u00fcrich 8006",
    "addr:housenumber":"25",
    "addr:postcode":"8006",
    "addr:street":"Winterthurerstrasse",
    "iso:country":"CH",
    "sg:address":"Winterthurerstrasse 25",
    "sg:city":"Z\u00fcrich",
    "sg:orig_category":"Aktivit\u00e4ten der Krankenschwestern U Hebammen, Hauspflege Organisationen des Gesundheitswesen",
    "sg:phone":"+41 13611440",
    "sg:postcode":"8006",
    "sg:province":"Z\u00fcrich",
    "wof:name":"Spitex-zentrum Oberstrass Gemeindekrankenpflege",
    "wof:placetype":"venue"
},
  "geometry": {"coordinates":[8.547613,47.386406],"type":"Point"}
}