{
  "type": "Feature",
  "properties": {
    "addr:full":"Ferrenweg 4 Baldegg Luzern 6283",
    "addr:housenumber":"4",
    "addr:postcode":"6283",
    "addr:street":"Ferrenweg",
    "iso:country":"CH",
    "sg:address":"Ferrenweg 4",
    "sg:city":"Baldegg",
    "sg:orig_category":"Detailhandel mit Antiquit\u00e4ten Detailhandel mit M\u00f6beln",
    "sg:phone":"+41 71 223 12 10",
    "sg:postcode":"6283",
    "sg:province":"Luzern",
    "wof:name":"Alfred Nenning Polsterm\u00f6bel Antiquit\u00e4ten",
    "wof:placetype":"venue"
},
  "geometry": {"coordinates":[9.375038,47.426971],"type":"Point"}
}