{
  "type": "Feature",
  "properties": {
    "iso:country":"CH",
    "sg:address":"Dufourstrasse 55",
    "sg:city":"Zollikon",
    "sg:orig_category":"Herstellung von Herren U Knabenoberbekleidung Sonstiges Textilgewerbe",
    "sg:phone":"+41 13902715",
    "sg:postcode":"8702",
    "sg:province":"Z\u00fcrich",
    "wof:name":"Ittierre Suisse Gmbh",
    "wof:placetype":"venue"
},
  "geometry": {"coordinates":[8.5710353851,47.3419494629],"type":"Point"}
}