{
  "type": "Feature",
  "properties": {
    "iso:country":"CH",
    "sg:address":"Kirchweg 20 5444 K\u00fcnten. Postfach",
    "sg:city":"K\u00fcnten",
    "sg:orig_category":"Mineral\u00f6lverarbeitung",
    "sg:postcode":"5444",
    "sg:province":"Aargau",
    "wof:name":"Paweg Gmbh Mineral\u00f6lprodukte; Handel Usw",
    "wof:placetype":"venue"
},
  "geometry": {"coordinates":[8.328204155,47.3905296326],"type":"Point"}
}