{
  "type": "Feature",
  "properties": {
    "iso:country":"CH",
    "sg:address":"Landstrasse 7",
    "sg:city":"Schaan",
    "sg:orig_category":"Detailhandel mit S\u00e4uglings U Kinderbekleidung Detailhandel mit Textilien",
    "sg:phone":"+423 233 34 40",
    "sg:postcode":"9494",
    "wof:name":"Helen Hilti Kinderbekleidung Wolle",
    "wof:placetype":"venue"
},
  "geometry": {"coordinates":[9.5100135803,47.1668395996],"type":"Point"}
}