{
  "type": "Feature",
  "properties": {
    "iso:country":"CH",
    "sg:address":"Laurenzenvorstadt 129",
    "sg:city":"Aarau",
    "sg:orig_category":"Arbeitnehmerverb\u00e4nde",
    "sg:phone":"+41 62 822 33 60",
    "sg:postcode":"5000",
    "sg:province":"Aargau",
    "wof:name":"Schweiz.berufsverband Der Krankenschwestern & -pfleger",
    "wof:placetype":"venue"
},
  "geometry": {"coordinates":[8.054467,47.393486],"type":"Point"}
}