{
  "type": "Feature",
  "properties": {
    "iso:country":"CH",
    "sg:address":"Mohrhaldenstrasse 22",
    "sg:city":"Riehen",
    "sg:orig_category":"Gesundheitswesen",
    "sg:postcode":"4125",
    "sg:province":"Basel-Stadt",
    "wof:name":"Isabelle Andr\u00e9e Stump",
    "wof:placetype":"venue"
},
  "geometry": {"coordinates":[7.6531801224,47.5834541321],"type":"Point"}
}