{
  "type": "Feature",
  "properties": {
    "iso:country":"CH",
    "sg:address":"Brauerstrasse 45 8000 Z\u00fcrich. Postfach 2223",
    "sg:city":"Z\u00fcrich",
    "sg:orig_category":"Detailhandel mit Getr\u00e4nken",
    "sg:phone":"+41 12410607",
    "sg:postcode":"8026",
    "sg:province":"Z\u00fcrich",
    "wof:name":"Black Death Switzerland Gmbh Import Und Vertrieb",
    "wof:placetype":"venue"
},
  "geometry": {"coordinates":[8.5263586044,47.3779945374],"type":"Point"}
}