{
  "type": "Feature",
  "properties": {
    "addr:full":"Gl\u00e4rnischstrasse 56 St\u00e4fa Z\u00fcrich 8712",
    "addr:housenumber":"56",
    "addr:postcode":"8712",
    "addr:street":"Glaernischstrasse;Zuerich",
    "iso:country":"CH",
    "sg:address":"Gl\u00e4rnischstrasse 56",
    "sg:city":"St\u00e4fa",
    "sg:orig_category":"Detailhandel mit Blumen U Pflanzen Detailhandel mit Waren verschiedener Art, Hauptrichtung Nahrungsm",
    "sg:phone":"+41 31 308 91 11",
    "sg:postcode":"8712",
    "sg:province":"Z\u00fcrich",
    "wof:name":"Landi Chaux-de-fonds",
    "wof:placetype":"venue"
},
  "geometry": {"coordinates":[6.816753,47.093891],"type":"Point"}
}