{
  "type": "Feature",
  "properties": {
    "iso:country":"CH",
    "sg:address":"Alte Gasse 8 5034 Suhr. Postfach",
    "sg:city":"Suhr",
    "sg:orig_category":"Herstellung von Werkzeugmaschinen Landwirtschaftliche Maschinen Grosshandel",
    "sg:phone":"+41 62 855 20 17",
    "sg:postcode":"5034",
    "sg:province":"Aargau",
    "wof:name":"Batcon-maschinen Attula J\u00fcrgen Handelsunternehmen F\u00fcr Holzbearbeitunsmaschinen U. -anlagen Usw",
    "wof:placetype":"venue"
},
  "geometry": {"coordinates":[8.0811595917,47.3739967346],"type":"Point"}
}