{
  "type": "Feature",
  "properties": {
    "iso:country":"CH",
    "sg:address":"Rue De La Gare 24 1860 Aigle. Postfach",
    "sg:city":"Aigle",
    "sg:orig_category":"Gesundheitswesen",
    "sg:postcode":"1860",
    "sg:province":"Vaud",
    "wof:name":"Laboratoires Du Chablais Sa, Succursale D'aigle",
    "wof:placetype":"venue"
},
  "geometry": {"coordinates":[6.9656062126,46.3174552917],"type":"Point"}
}