{
  "type": "Feature",
  "properties": {
    "iso:country":"CH",
    "sg:address":"Hinterdorfstr. 26",
    "sg:city":"Villigen",
    "sg:orig_category":"Sonstiger spezialisierter Hoch U Tiefbau",
    "sg:phone":"+41 56 284 10 70",
    "sg:postcode":"5234",
    "sg:province":"Aargau",
    "wof:name":"Baumann + M\u00fcller Ger\u00fcstmontagen",
    "wof:placetype":"venue"
},
  "geometry": {"coordinates":[8.2166452408,47.5269432068],"type":"Point"}
}