{
  "type": "Feature",
  "properties": {
    "iso:country":"CH",
    "sg:address":"Grabenstrasse 5",
    "sg:city":"Schlieren",
    "sg:orig_category":"Unclassifiable Establishments",
    "sg:postcode":"8952",
    "sg:province":"Z\u00fcrich",
    "wof:name":"Friedrich B\u00fcchler",
    "wof:placetype":"venue"
},
  "geometry": {"coordinates":[9.8581809998,46.9966583252],"type":"Point"}
}