{
  "type": "Feature",
  "properties": {
    "iso:country":"CH",
    "sg:address":"Via Pasquale Lucchini 1",
    "sg:city":"Lugano",
    "sg:orig_category":"Non-Classified Establishments",
    "sg:postcode":"6900",
    "sg:province":"Ticino",
    "wof:name":"Oxinvest Sa",
    "wof:placetype":"venue"
},
  "geometry": {"coordinates":[8.9571819305,46.0059127808],"type":"Point"}
}