{
  "type": "Feature",
  "properties": {
    "iso:country":"CH",
    "sg:address":"2738",
    "sg:city":"Court",
    "sg:classifiers":[
        {
            "category":"Restaurant",
            "type":"Food & Drink"
        }
    ],
    "sg:phone":"+41 32 497 90 73",
    "sg:postcode":"2738",
    "sg:province":"Bern",
    "wof:name":"Restaurant Chez Ponte",
    "wof:placetype":"venue"
},
  "geometry": {"coordinates":[7.3414521217,47.2410430908],"type":"Point"}
}