{
  "type": "Feature",
  "properties": {
    "iso:country":"CH",
    "sg:address":"Route De Cossonay 100",
    "sg:city":"Prilly",
    "sg:orig_category":"Herstellung von Metallerzeugnissen ohne Maschinenbau Herstellung von elektrischen Lampen U Leuchten",
    "sg:phone":"+41 21 635 66 56",
    "sg:postcode":"1008",
    "sg:province":"Vaud",
    "wof:name":"Neuco Ag Succursale De Prilly",
    "wof:placetype":"venue"
},
  "geometry": {"coordinates":[6.596807003,46.5397033691],"type":"Point"}
}