{
  "type": "Feature",
  "properties": {
    "iso:country":"CH",
    "sg:address":"Faguillon Chemin De 1 1223 Cologny. Postfach",
    "sg:city":"Cologny",
    "sg:orig_category":"Reiseb\u00fcros U Reiseveranstalter",
    "sg:postcode":"1223",
    "sg:province":"Gen\u00e8ve",
    "wof:name":"Intracom General Machinery Sa Analyses Des Projets D'investissment Etc",
    "wof:placetype":"venue"
},
  "geometry": {"coordinates":[6.1858448982,46.2192382812],"type":"Point"}
}