{
  "type": "Feature",
  "properties": {
    "iso:country":"CH",
    "sg:address":"Merzenberg 6017 Ruswil. Postfach",
    "sg:city":"Ruswil",
    "sg:orig_category":"Kalb U Schweine-M\u00e4sterei U Zucht",
    "sg:postcode":"6017",
    "sg:province":"Luzern",
    "wof:name":"Remporc Ag Zuchtschweine U. Schlachtschweiner; Produktion, Handel Usw",
    "wof:placetype":"venue"
},
  "geometry": {"coordinates":[8.1506004333,47.1093978882],"type":"Point"}
}