{
  "type": "Feature",
  "properties": {
    "iso:country":"CH",
    "sg:address":"Grabackerstrasse 48 4441 Th\u00fcrnen. Postfach",
    "sg:city":"Th\u00fcrnen",
    "sg:orig_category":"Grosshandel mit sonstigen Maschinen U Ausr\u00fcstungen f\u00fcr Industrie, Handel U Schiffahrt Ingenieurb\u00fcros",
    "sg:phone":"+41 61 971 50 11",
    "sg:postcode":"4441",
    "sg:province":"Basel-Landschaft",
    "wof:name":"M. Bachmann Ag, Industriebedarf",
    "wof:placetype":"venue"
},
  "geometry": {"coordinates":[7.8235468864,47.4594039917],"type":"Point"}
}