{
  "type": "Feature",
  "properties": {
    "iso:country":"CH",
    "sg:address":"Chemin Des Etournelles 4",
    "sg:city":"Veyrier",
    "sg:orig_category":"Sportvereine Wassersport Segeln",
    "sg:phone":"+41 41 850 32 41",
    "sg:postcode":"1255",
    "sg:province":"Gen\u00e8ve",
    "wof:name":"Yachtklub Rigi Ycri",
    "wof:placetype":"venue"
},
  "geometry": {"coordinates":[8.4326095581,47.0853805542],"type":"Point"}
}