{
  "type": "Feature",
  "properties": {
    "iso:country":"CH",
    "sg:address":"Baslerstrasse 343 4123 Allschwil. Postfach",
    "sg:city":"Allschwil",
    "sg:orig_category":"Herstellung von Klebstoffen U Gelatinen",
    "sg:phone":"+41 61 483 19 90",
    "sg:postcode":"4123",
    "sg:province":"Basel-Landschaft",
    "wof:name":"Atp Alltape Klebetechnik (schweiz) Ag Produkte Der Klebetechnik; Herstellung, Vertrieb Usw",
    "wof:placetype":"venue"
},
  "geometry": {"coordinates":[7.5627551079,47.5575714111],"type":"Point"}
}