{
  "type": "Feature",
  "properties": {
    "iso:country":"CH",
    "sg:address":"Bahnhofstrasse 26",
    "sg:city":"Beringen",
    "sg:orig_category":"Erschliessung von Grundst\u00fccken",
    "sg:phone":"+41 52 685 31 36",
    "sg:postcode":"8222",
    "sg:province":"Schaffhausen",
    "wof:name":"W + M Tech Gmbh",
    "wof:placetype":"venue"
},
  "geometry": {"coordinates":[8.5716209412,47.6951560974],"type":"Point"}
}