{
  "type": "Feature",
  "properties": {
    "iso:country":"CH",
    "sg:address":"Nideltobel",
    "sg:city":"Bauma",
    "sg:orig_category":"Detailhandel mit Antiquit\u00e4ten U Gebrauchtwaren in Verkaufsr\u00e4umen",
    "sg:phone":"+41 12714245",
    "sg:postcode":"8494",
    "sg:province":"Z\u00fcrich",
    "wof:name":"Antiquariat A. Rihm",
    "wof:placetype":"venue"
},
  "geometry": {"coordinates":[8.921471,47.360569],"type":"Point"}
}