{
  "type": "Feature",
  "properties": {
    "addr:full":"H\u00f6hefeldstrasse 73 Sch\u00f6nenwerd Solothurn 5012",
    "addr:housenumber":"73",
    "addr:postcode":"5012",
    "addr:street":"Hoehefeldstrasse;Schoenenwerd Solothurn",
    "iso:country":"CH",
    "sg:address":"H\u00f6hefeldstrasse 73",
    "sg:city":"Sch\u00f6nenwerd",
    "sg:orig_category":"Abwasserreinigung",
    "sg:phone":"+41 62 295 27 55",
    "sg:postcode":"5012",
    "sg:province":"Solothurn",
    "wof:name":"Kl\u00e4ranalage",
    "wof:placetype":"venue"
},
  "geometry": {"coordinates":[8.007472,47.380535],"type":"Point"}
}