{
  "type": "Feature",
  "properties": {
    "iso:country":"CH",
    "sg:address":"Via Pravender 88 D",
    "sg:city":"M\u00fcstair",
    "sg:orig_category":"Sonstige pers\u00f6nliche Dienstleistungen",
    "sg:postcode":"7537",
    "sg:province":"Graubunden",
    "wof:name":"Zwick Distribution Gmbh",
    "wof:placetype":"venue"
},
  "geometry": {"coordinates":[10.4447469711,46.6233062744],"type":"Point"}
}