{
  "type": "Feature",
  "properties": {
    "iso:country":"CH",
    "sg:address":"Rathausstrasse 32",
    "sg:city":"Leukerbad",
    "sg:orig_category":"Medizinische Anstalten",
    "sg:postcode":"3954",
    "sg:province":"Valais",
    "wof:name":"Venenzentrum Im Medizinischen Zentrum",
    "wof:placetype":"venue"
},
  "geometry": {"coordinates":[9.5013246536,47.0036811829],"type":"Point"}
}