{
  "type": "Feature",
  "properties": {
    "addr:full":"Toblerstrasse 51 8044 Z\u00fcrich. Postfach Z\u00fcrich Z\u00fcrich 8044",
    "addr:housenumber":"51",
    "addr:postcode":"8044 zuerich. postfach;8044",
    "addr:street":"Toblerstrasse",
    "iso:country":"CH",
    "sg:address":"Toblerstrasse 51 8044 Z\u00fcrich. Postfach",
    "sg:city":"Z\u00fcrich",
    "sg:classifiers":[
        {
            "category":"Education",
            "subcategory":"Library",
            "type":"Public Place"
        }
    ],
    "sg:phone":"+41 71 344 12 64",
    "sg:postcode":"8044",
    "sg:province":"Z\u00fcrich",
    "sg:tags":[
        "u",
        "bibliotheken",
        "archive"
    ],
    "wof:name":"Pro Juventute",
    "wof:placetype":"venue"
},
  "geometry": {"coordinates":[9.38846,47.39056],"type":"Point"}
}