{
  "type": "Feature",
  "properties": {
    "iso:country":"CH",
    "sg:address":"Obergasse 5",
    "sg:city":"Elgg",
    "sg:orig_category":"Kauf U Verkauf von Immobilien auf eigene Rechnung",
    "sg:phone":"+41 52 364 00 34",
    "sg:postcode":"8353",
    "sg:province":"Z\u00fcrich",
    "wof:name":"Obergass Liegenschaften Ag Liegenschaften; Verwaltung",
    "wof:placetype":"venue"
},
  "geometry": {"coordinates":[8.8687572479,47.4903945923],"type":"Point"}
}