{
  "type": "Feature",
  "properties": {
    "iso:country":"CH",
    "sg:address":"Schulstrasse 335",
    "sg:city":"Hornussen",
    "sg:orig_category":"Malerei",
    "sg:phone":"+41 62 871 31 41",
    "sg:postcode":"5075",
    "sg:province":"Aargau",
    "wof:name":"Roland Frey Malergesch\u00e4ft",
    "wof:placetype":"venue"
},
  "geometry": {"coordinates":[8.0648031235,47.4991455078],"type":"Point"}
}