{
  "type": "Feature",
  "properties": {
    "iso:country":"CH",
    "sg:address":"Wigartenstrasse 9",
    "sg:city":"F\u00e4llanden",
    "sg:orig_category":"Elektroinstallation",
    "sg:phone":"+41 79 358 83 05",
    "sg:postcode":"8117",
    "sg:province":"Z\u00fcrich",
    "wof:name":"Manser Elektroanlagen Ag",
    "wof:placetype":"venue"
},
  "geometry": {"coordinates":[8.6900548935,47.3005561829],"type":"Point"}
}