{
  "type": "Feature",
  "properties": {
    "iso:country":"CH",
    "sg:address":"Lommiserstrasse 25",
    "sg:city":"W\u00e4ngi",
    "sg:orig_category":"Non-Classified Establishments",
    "sg:postcode":"9545",
    "sg:province":"Thurgau",
    "wof:name":"Me Reifenimport Gmbh",
    "wof:placetype":"venue"
},
  "geometry": {"coordinates":[8.9590215683,47.5022926331],"type":"Point"}
}