{
  "type": "Feature",
  "properties": {
    "iso:country":"CH",
    "sg:address":"Kaiserstrasse 4 4310 Rheinfelden. Postfach",
    "sg:city":"Rheinfelden",
    "sg:orig_category":"Grossbanken",
    "sg:phone":"+41 844 800 888",
    "sg:postcode":"4310",
    "sg:province":"Aargau",
    "wof:name":"Credit Suisse",
    "wof:placetype":"venue"
},
  "geometry": {"coordinates":[7.7952032089,47.5532951355],"type":"Point"}
}