{
  "type": "Feature",
  "properties": {
    "iso:country":"CH",
    "sg:address":"Winzenried 3086 Zimmerwald. Postfach",
    "sg:city":"Zimmerwald",
    "sg:classifiers":[
        {
            "category":"Travel",
            "subcategory":"Hotels & Motels",
            "type":"Entertainment"
        }
    ],
    "sg:postcode":"3086",
    "sg:province":"Bern",
    "sg:tags":[
        "hotels",
        "mit",
        "restaurant"
    ],
    "wof:name":"Tomec Gmbh Seminare, Beratung U. Schulung Usw.; Entwicklung, Anbietung U. Erteilung",
    "wof:placetype":"venue"
},
  "geometry": {"coordinates":[7.4773001671,46.8834114075],"type":"Point"}
}