{
  "type": "Feature",
  "properties": {
    "iso:country":"CH",
    "sg:address":"Sulzbacherstrasse 3729",
    "sg:city":"Uster",
    "sg:orig_category":"G\u00fcterbef\u00f6rderung im Strassenverkehr Herstellung von sonstigen landwirtschaftlichen Maschinen",
    "sg:phone":"+41 19401738",
    "sg:postcode":"8610",
    "sg:province":"Z\u00fcrich",
    "wof:name":"H\u00fcrlimann & Sohn Transporte & Landmaschinen",
    "wof:placetype":"venue"
},
  "geometry": {"coordinates":[8.7422552109,47.3320884705],"type":"Point"}
}