{
  "type": "Feature",
  "properties": {
    "iso:country":"CH",
    "sg:address":"Rue De Lausanne 25",
    "sg:city":"Sion",
    "sg:orig_category":"Sonstiges Versicherungsgewerbe",
    "sg:phone":"+41 27 322 49 81",
    "sg:postcode":"1950",
    "sg:province":"Valais",
    "wof:name":"Orega Sa",
    "wof:placetype":"venue"
},
  "geometry": {"coordinates":[7.358438015,46.232257843],"type":"Point"}
}