{
  "type": "Feature",
  "properties": {
    "iso:country":"CH",
    "sg:address":"Liestalerstrasse 52",
    "sg:city":"Seltisberg",
    "sg:orig_category":"Softwareentwicklung U beratung",
    "sg:postcode":"4411",
    "sg:province":"Basel-Landschaft",
    "wof:name":"A-r-t Gmbh",
    "wof:placetype":"venue"
},
  "geometry": {"coordinates":[7.3786091805,47.1381835938],"type":"Point"}
}