{
  "type": "Feature",
  "properties": {
    "iso:country":"CH",
    "sg:address":"M\u00fcnchensteinerstrasse 270",
    "sg:city":"Basel",
    "sg:orig_category":"Grosshandel mit Geschenkartikeln U Souvenirs Grosshandel mit sonstigen Gebrauchs U Verbrauchsg\u00fctern",
    "sg:phone":"+41 61 332 07 66",
    "sg:postcode":"4053",
    "sg:province":"Basel-Stadt",
    "wof:name":"Simcla Ag",
    "wof:placetype":"venue"
},
  "geometry": {"coordinates":[7.6086001396,47.5367736816],"type":"Point"}
}