{
  "type": "Feature",
  "properties": {
    "iso:country":"CH",
    "sg:address":"2042",
    "sg:city":"Valangin",
    "sg:orig_category":"Detailhandel mit Brot, Back U S\u00fcsswaren",
    "sg:postcode":"2042",
    "sg:province":"Neuch\u00e2tel",
    "wof:name":"Weber & Cie",
    "wof:placetype":"venue"
},
  "geometry": {"coordinates":[6.89775,47.017681],"type":"Point"}
}