{
  "type": "Feature",
  "properties": {
    "iso:country":"CH",
    "sg:address":"Nelkenweg 7",
    "sg:city":"Heiden",
    "sg:orig_category":"Grosshandel mit Getreide, Saatgut U Futtermitteln",
    "sg:phone":"+41 22 702 07 02",
    "sg:postcode":"9410",
    "sg:province":"Appenzell Ausserrhoden",
    "wof:name":"Finagrain Compagnie Commerciale Agricole Et Financi\u00e8re",
    "wof:placetype":"venue"
},
  "geometry": {"coordinates":[6.156662941,46.1911964417],"type":"Point"}
}