{
  "type": "Feature",
  "properties": {
    "iso:country":"CH",
    "sg:city":"Campocologno",
    "sg:classifiers":[
        {
            "category":"Banks & Credit Unions",
            "subcategory":"Bank",
            "type":"Services"
        }
    ],
    "sg:phone":"+41 41 825 54 15",
    "sg:postcode":"7744",
    "sg:province":"Graubunden",
    "wof:name":"Graub\u00fcndner, Kantonalbank",
    "wof:placetype":"venue"
},
  "geometry": {"coordinates":[10.141491,46.234035],"type":"Point"}
}