{
  "type": "Feature",
  "properties": {
    "iso:country":"CH",
    "sg:address":"Zentralstrasse 11",
    "sg:city":"Boswil",
    "sg:orig_category":"Offsetdruck Verlagsgewerbe",
    "sg:phone":"+41 56 666 11 66",
    "sg:postcode":"5623",
    "sg:province":"Aargau",
    "wof:name":"Alois Huber Druckerei",
    "wof:placetype":"venue"
},
  "geometry": {"coordinates":[8.313000679,47.3013076782],"type":"Point"}
}