{
  "type": "Feature",
  "properties": {
    "addr:full":"Alpenweg 7 3506 Grossh\u00f6chstetten. Postfach Grossh\u00f6chstetten Bern 3506",
    "addr:housenumber":"7",
    "addr:postcode":"3506;3506",
    "addr:street":"Alpenweg;Postfach",
    "iso:country":"CH",
    "sg:address":"Alpenweg 7 3506 Grossh\u00f6chstetten. Postfach",
    "sg:city":"Grossh\u00f6chstetten",
    "sg:orig_category":"Beleuchtungsk\u00f6rper Detailhandel Elektroinstallation",
    "sg:phone":"+41 31 711 28 28",
    "sg:postcode":"3506",
    "sg:province":"Bern",
    "wof:name":"H\u00e4usler & Partner Gmbh Elektrische Anlagen",
    "wof:placetype":"venue"
},
  "geometry": {"coordinates":[7.640945,46.90741],"type":"Point"}
}