{
  "type": "Feature",
  "properties": {
    "iso:country":"CH",
    "sg:address":"3970",
    "sg:city":"Salgesch",
    "sg:orig_category":"Detailhandel mit Getr\u00e4nken",
    "sg:phone":"+41 27 455 50 43",
    "sg:postcode":"3970",
    "sg:province":"Valais",
    "wof:name":"Raoul Cina Weinhandlung",
    "wof:placetype":"venue"
},
  "geometry": {"coordinates":[7.5696148872,46.3114013672],"type":"Point"}
}