{
  "type": "Feature",
  "properties": {
    "iso:country":"CH",
    "sg:address":"Badenerstrasse 329 8003 Z\u00fcrich. Postfach 2372",
    "sg:city":"Z\u00fcrich",
    "sg:orig_category":"Grosshandel mit festen Brennstoffen U Mineral\u00f6lerzeugnissen Interessenvertretungen",
    "sg:phone":"+41 14059010",
    "sg:postcode":"8040",
    "sg:province":"Z\u00fcrich",
    "wof:name":"Avia International Mineral\u00f6l, -produkte-importeure Usw.; Interessenwahrnehmung",
    "wof:placetype":"venue"
},
  "geometry": {"coordinates":[8.5116081238,47.3776473999],"type":"Point"}
}