{
  "type": "Feature",
  "properties": {
    "iso:country":"CH",
    "sg:address":"4552 Derendingen. Postfach 255",
    "sg:city":"Derendingen",
    "sg:orig_category":"Sportvereine Ballsport Fussball",
    "sg:postcode":"4552",
    "sg:province":"Solothurn",
    "wof:name":"Sc Derendingen",
    "wof:placetype":"venue"
},
  "geometry": {"coordinates":[7.5903201103,47.1920318604],"type":"Point"}
}