{
  "type": "Feature",
  "properties": {
    "iso:country":"CH",
    "sg:address":"Sissacherstrasse 40",
    "sg:city":"Gelterkinden",
    "sg:orig_category":"Grosshandel mit Obst U Gem\u00fcse",
    "sg:phone":"+41 61 331 42 45",
    "sg:postcode":"4460",
    "sg:province":"Basel-Landschaft",
    "wof:name":"Frunoba Ag Lebensmittel, Bes. Fr\u00fcchte, Gem\u00fcse Usw; Handel",
    "wof:placetype":"venue"
},
  "geometry": {"coordinates":[7.8438868523,47.4644355774],"type":"Point"}
}