{
  "type": "Feature",
  "properties": {
    "iso:country":"CH",
    "sg:address":"3008",
    "sg:city":"Bern",
    "sg:orig_category":"Berufsbildende weiterf\u00fchrende Schulen",
    "sg:phone":"+41 31 386 45 22",
    "sg:postcode":"3008",
    "sg:province":"Bern",
    "wof:name":"Die Post Ausbildung (trainingsz.bern)",
    "wof:placetype":"venue"
},
  "geometry": {"coordinates":[7.41822,46.94363],"type":"Point"}
}