{
  "type": "Feature",
  "properties": {
    "addr:full":"Plainpalaisrond-point De 6 Gen\u00e8ve Gen\u00e8ve 1205",
    "addr:housenumber":"6",
    "addr:postcode":"1205",
    "iso:country":"CH",
    "sg:address":"Plainpalaisrond-point De 6",
    "sg:city":"Gen\u00e8ve",
    "sg:orig_category":"Detailhandel mit Bekleidung",
    "sg:phone":"+41 22 320 21 09",
    "sg:postcode":"1205",
    "sg:province":"Gen\u00e8ve",
    "wof:name":"E. Bettan",
    "wof:placetype":"venue"
},
  "geometry": {"coordinates":[6.142701,46.208359],"type":"Point"}
}