{
  "type": "Feature",
  "properties": {
    "iso:country":"CH",
    "sg:address":"Ruelle Du March\u00e9 8",
    "sg:city":"Bex",
    "sg:orig_category":"Zahnarztpraxen",
    "sg:phone":"+41 24 463 22 61",
    "sg:postcode":"1880",
    "sg:province":"Vaud",
    "wof:name":"Dr M\u00e9d. Dent. Wolfgang Teumer M\u00e9decin-dentiste",
    "wof:placetype":"venue"
},
  "geometry": {"coordinates":[7.0139307976,46.2503318787],"type":"Point"}
}