{
  "type": "Feature",
  "properties": {
    "iso:country":"CH",
    "sg:address":"Schulstrasse 2 8153 R\u00fcmlang. Postfach 177",
    "sg:city":"R\u00fcmlang",
    "sg:orig_category":"Detailhandel mit M\u00f6beln U Haushaltsgegenst\u00e4nden Detailhandel mit Teppichen",
    "sg:phone":"+41 56 241 19 33",
    "sg:postcode":"8153",
    "sg:province":"Z\u00fcrich",
    "wof:name":"Roth Innendekorationen",
    "wof:placetype":"venue"
},
  "geometry": {"coordinates":[8.3286542892,47.5206184387],"type":"Point"}
}