{
  "type": "Feature",
  "properties": {
    "iso:country":"CH",
    "sg:address":"Via Borghetto 9",
    "sg:city":"Giubiasco",
    "sg:orig_category":"Chemische Reinigung W\u00e4schereien",
    "sg:phone":"+41 91 857 16 46",
    "sg:postcode":"6512",
    "sg:province":"Ticino",
    "wof:name":"Intercolor Sa Lavanderia Chimica Linda",
    "wof:placetype":"venue"
},
  "geometry": {"coordinates":[9.012224,46.173824],"type":"Point"}
}