{
  "type": "Feature",
  "properties": {
    "iso:country":"CH",
    "sg:address":"Fritz Honegger-weg 6",
    "sg:city":"R\u00fcschlikon",
    "sg:orig_category":"Non-Classified Establishments",
    "sg:phone":"+41 17243363",
    "sg:postcode":"8803",
    "sg:province":"Z\u00fcrich",
    "wof:name":"Ansico Gmbh",
    "wof:placetype":"venue"
},
  "geometry": {"coordinates":[8.548833847,47.3076782227],"type":"Point"}
}