{
  "type": "Feature",
  "properties": {
    "iso:country":"CH",
    "sg:address":"Cinque Vie Piazza 1 6932 Breganzona. Postfach",
    "sg:city":"Breganzona",
    "sg:orig_category":"Softwareentwicklung U beratung",
    "sg:postcode":"6932",
    "sg:province":"Ticino",
    "wof:name":"Agent Automation Sa Sistemi Informatici; Sviluppo, Comm.",
    "wof:placetype":"venue"
},
  "geometry": {"coordinates":[8.9361848831,46.0109138489],"type":"Point"}
}