{
  "type": "Feature",
  "properties": {
    "iso:country":"CH",
    "sg:address":"Gare Avenue De La 1180 Rolle. Postfach",
    "sg:city":"Rolle",
    "sg:orig_category":"Grosshandel mit Nahrungsmitteln, Getr\u00e4nken U Tabakwaren ohne ausgepr\u00e4gten Schwerpunkt",
    "sg:phone":"+41 21 825 32 47",
    "sg:postcode":"1180",
    "sg:province":"Vaud",
    "wof:name":"Pick Pay Partenaire, Blagojevic Borivoje Produits Alimentaires, Notamm. Alcooliques Ou Alcoolis\u00e9es, Tabacs Etc.; Commerce",
    "wof:placetype":"venue"
},
  "geometry": {"coordinates":[6.3380351067,46.4575614929],"type":"Point"}
}