{
  "type": "Feature",
  "properties": {
    "iso:country":"CH",
    "sg:address":"Marktgasse 15",
    "sg:city":"Rheinfelden",
    "sg:orig_category":"Gymnastik U Fitnesszentren Saunas, Solarien, Fitnesszentren U \u00e4hnliches",
    "sg:postcode":"4310",
    "sg:province":"Aargau",
    "wof:name":"City One Fit & Well, Schwarb Andreas",
    "wof:placetype":"venue"
},
  "geometry": {"coordinates":[7.7932729721,47.5551757812],"type":"Point"}
}