{
  "type": "Feature",
  "properties": {
    "iso:country":"CH",
    "sg:address":"Zimmerwaldstr. 91 3122 Kehrsatz. Postfach",
    "sg:city":"Kehrsatz",
    "sg:orig_category":"Maler U Glasergewerbe",
    "sg:phone":"+41 31 961 38 32",
    "sg:postcode":"3122",
    "sg:province":"Bern",
    "wof:name":"H\u00e4nni Ren\u00e9 Malergesch\u00e4ft",
    "wof:placetype":"venue"
},
  "geometry": {"coordinates":[7.4720010757,46.9036979675],"type":"Point"}
}