{
  "type": "Feature",
  "properties": {
    "iso:country":"CH",
    "sg:address":"6162",
    "sg:city":"Rengg",
    "sg:orig_category":"Primarschulen",
    "sg:phone":"+41 41 480 01 25",
    "sg:postcode":"6162",
    "sg:province":"Luzern",
    "wof:name":"Primarschule",
    "wof:placetype":"venue"
},
  "geometry": {"coordinates":[8.0906200409,47.0034294128],"type":"Point"}
}