{
  "type": "Feature",
  "properties": {
    "iso:country":"CH",
    "sg:address":"Route D'yverdon 1",
    "sg:city":"Chavornay",
    "sg:orig_category":"Physiotherapie",
    "sg:phone":"+41 24 441 57 57",
    "sg:postcode":"1373",
    "sg:province":"Vaud",
    "wof:name":"Jean-paul Montet Physioth\u00e9rapie & Massage",
    "wof:placetype":"venue"
},
  "geometry": {"coordinates":[6.5751829147,46.7156524658],"type":"Point"}
}