{
  "type": "Feature",
  "properties": {
    "iso:country":"CH",
    "sg:address":"Basteiplatz 7",
    "sg:city":"Z\u00fcrich",
    "sg:orig_category":"Datenverarbeitungsdienste Softwareentwicklung U beratung",
    "sg:phone":"+41 12131195",
    "sg:postcode":"8001",
    "sg:province":"Z\u00fcrich",
    "wof:name":"Kontex Informatik Ag",
    "wof:placetype":"venue"
},
  "geometry": {"coordinates":[8.53574,47.369724],"type":"Point"}
}