{
  "type": "Feature",
  "properties": {
    "iso:country":"CH",
    "sg:address":"Tessenbergstrasse 64 2505 Biel/bienne. Postfach",
    "sg:city":"Biel/bienne",
    "sg:orig_category":"Sonstige mit der Informatik verbundene T\u00e4tigkeiten",
    "sg:postcode":"2505",
    "sg:province":"Bern",
    "wof:name":"Batschelet Edv-beratung",
    "wof:placetype":"venue"
},
  "geometry": {"coordinates":[7.2199001312,47.1311569214],"type":"Point"}
}