{
  "type": "Feature",
  "properties": {
    "iso:country":"CH",
    "sg:address":"4950",
    "sg:city":"Huttwil",
    "sg:orig_category":"Spinnstoffaufbereitung U Spinnerei Textilveredlung",
    "sg:phone":"+41 62 959 90 30",
    "sg:postcode":"4950",
    "sg:province":"Bern",
    "wof:name":"Wollspinnerei Huttwil Ag",
    "wof:placetype":"venue"
},
  "geometry": {"coordinates":[7.8472599983,47.1139984131],"type":"Point"}
}