{
  "type": "Feature",
  "properties": {
    "iso:country":"CH",
    "sg:address":"F\u00f6rrlibuckstrasse 109 8005 Z\u00fcrich. Postfach",
    "sg:city":"Z\u00fcrich",
    "sg:orig_category":"Futtermittel, Heu and Stroh Grosshandel Grosshandel mit Milch, Milcherzeugnissen, Eiern, Speise\u00f6len ",
    "sg:phone":"+41 12755511",
    "sg:postcode":"8037",
    "sg:province":"Z\u00fcrich",
    "wof:name":"Lacto Prosp\u00e9rit\u00e9 Ag",
    "wof:placetype":"venue"
},
  "geometry": {"coordinates":[8.5125083923,47.3918876648],"type":"Point"}
}