{
  "type": "Feature",
  "properties": {
    "iso:country":"CH",
    "sg:address":"Landstrasse 43",
    "sg:city":"Andelfingen",
    "sg:orig_category":"Architektur U Ingenieurb\u00fcros Herstellung von \u00d6fen U Brennern",
    "sg:phone":"+41 52 305 24 00",
    "sg:postcode":"8450",
    "sg:province":"Z\u00fcrich",
    "wof:name":"Consolidated Engineering Company Sand Lion Ag",
    "wof:placetype":"venue"
},
  "geometry": {"coordinates":[8.678839,47.594688],"type":"Point"}
}