{
  "type": "Feature",
  "properties": {
    "iso:country":"CH",
    "sg:address":"Hochstrasse 4",
    "sg:city":"Pf\u00e4ffikon",
    "sg:classifiers":[
        {
            "category":"Organizations",
            "subcategory":"Labor Organization",
            "type":"Services"
        }
    ],
    "sg:phone":"+41 19951850",
    "sg:postcode":"8330",
    "sg:province":"Z\u00fcrich",
    "sg:tags":[
        "work",
        "assembling",
        "assembly",
        "contract"
    ],
    "wof:name":"R. Schmid",
    "wof:placetype":"venue"
},
  "geometry": {"coordinates":[8.782729,47.366829],"type":"Point"}
}