{
  "type": "Feature",
  "properties": {
    "addr:full":"Leimatt Eriswil Bern 4952",
    "addr:postcode":"4952",
    "addr:street":"Leimatt;Bern",
    "iso:country":"CH",
    "sg:address":"Leimatt",
    "sg:city":"Eriswil",
    "sg:classifiers":[
        {
            "category":"Social Services",
            "subcategory":"Retirement Home",
            "type":"Services"
        }
    ],
    "sg:phone":"+41 62 966 18 57",
    "sg:postcode":"4952",
    "sg:province":"Bern",
    "sg:tags":[
        "pflegeheime",
        "u",
        "alters"
    ],
    "wof:name":"Altersheim Der Gemeinde Eriswil",
    "wof:placetype":"venue"
},
  "geometry": {"coordinates":[7.849085,47.072979],"type":"Point"}
}