{
  "type": "Feature",
  "properties": {
    "iso:country":"CH",
    "sg:address":"Cirque Place Du 2",
    "sg:city":"Genf",
    "sg:orig_category":"Grosshandel mit Parf\u00fcmerieartikeln U K\u00f6rperpflegemitteln Sonstiger Grosshandel",
    "sg:phone":"+41 31 372 32 35",
    "sg:postcode":"1200",
    "sg:province":"Gen\u00e8ve",
    "wof:name":"Zimac Handels Gmbh",
    "wof:placetype":"venue"
},
  "geometry": {"coordinates":[7.4164757729,46.9356040955],"type":"Point"}
}