{
  "type": "Feature",
  "properties": {
    "iso:country":"CH",
    "sg:address":"Hauptstrasse 47 6418 Rothenthurm. Postfach 23",
    "sg:city":"Rothenthurm",
    "sg:orig_category":"Erbringung von sonstigen Dienstleistungen f\u00fcr Unterhaltung, Erholung U Freizeit Reiseb\u00fcros U Reiseve",
    "sg:phone":"+41 79 234 15 61",
    "sg:postcode":"6418",
    "sg:province":"Schwyz",
    "wof:name":"Rafters Outdoor & Events Organisation Von Abenteuer Und Erlebnisausfl\u00fcgen, Teambildung",
    "wof:placetype":"venue"
},
  "geometry": {"coordinates":[8.6744937897,47.1014862061],"type":"Point"}
}