{
  "type": "Feature",
  "properties": {
    "iso:country":"CH",
    "sg:address":"7166",
    "sg:city":"Trun",
    "sg:orig_category":"Bezirks, Sekundar, Realschulen, Oberstufe der Primarschulen",
    "sg:postcode":"7166",
    "sg:province":"Graubunden",
    "wof:name":"Sekundarschule",
    "wof:placetype":"venue"
},
  "geometry": {"coordinates":[8.990615,46.743107],"type":"Point"}
}