{
  "type": "Feature",
  "properties": {
    "iso:country":"CH",
    "sg:address":"Fortstrasse 20",
    "sg:city":"Solothurn",
    "sg:orig_category":"Sportvereine Ballsport Basketball",
    "sg:postcode":"4500",
    "sg:province":"Solothurn",
    "wof:name":"Bc Solothurn",
    "wof:placetype":"venue"
},
  "geometry": {"coordinates":[7.5469741821,47.2100563049],"type":"Point"}
}