{
  "type": "Feature",
  "properties": {
    "iso:country":"CH",
    "sg:address":"Eigerweg 7 Sch\u00f6nb\u00fchl.",
    "sg:city":"Sch\u00f6nb\u00fchl-urtenen",
    "sg:orig_category":"Detailhandel mit elektrischen Haushalts-,Radio U Fernsehger\u00e4ten sowie Musikinstrumenten",
    "sg:postcode":"3322",
    "sg:province":"Bern",
    "wof:name":"K\u00e4gi R. + Partner Ag",
    "wof:placetype":"venue"
},
  "geometry": {"coordinates":[9.0476093292,47.4658126831],"type":"Point"}
}