{
  "type": "Feature",
  "properties": {
    "iso:country":"CH",
    "sg:address":"Place De La Gare 7 2500 Biel/bienne. Postfach",
    "sg:city":"Biel/bienne",
    "sg:orig_category":"Vermietung U Verpachtung von eigenen Immobilien",
    "sg:postcode":"2501",
    "sg:province":"Bern",
    "wof:name":"Dr. Krattiger & Cie",
    "wof:placetype":"venue"
},
  "geometry": {"coordinates":[7.2428531647,47.1337509155],"type":"Point"}
}