{
  "type": "Feature",
  "properties": {
    "iso:country":"CH",
    "sg:address":"Via Pauzella",
    "sg:city":"Novazzano",
    "sg:orig_category":"Mit Sport verbundene T\u00e4tigkeiten",
    "sg:phone":"+41 91 647 24 21",
    "sg:postcode":"6883",
    "sg:province":"Ticino",
    "wof:name":"Scuola D'equitazione Pauzzella",
    "wof:placetype":"venue"
},
  "geometry": {"coordinates":[8.9687690735,45.8369865417],"type":"Point"}
}