{
  "type": "Feature",
  "properties": {
    "iso:country":"CH",
    "sg:address":"Buchserstr. 34",
    "sg:city":"D\u00e4llikon",
    "sg:classifiers":[
        {
            "category":"Manufacturing",
            "subcategory":"Textiles",
            "type":"Manufacturing & Wholesale Goods"
        }
    ],
    "sg:phone":"+41 4118444400",
    "sg:postcode":"8108",
    "sg:province":"Z\u00fcrich",
    "sg:tags":[
        "linen",
        "clothing",
        "fabric"
    ],
    "wof:name":"Tapisano Ag",
    "wof:placetype":"venue"
},
  "geometry": {"coordinates":[8.4388141632,47.4465065002],"type":"Point"}
}