{
  "type": "Feature",
  "properties": {
    "addr:full":"Gr\u00fcttbachstrasse 16 Luterbach Solothurn 4542",
    "addr:housenumber":"16",
    "addr:postcode":"4542",
    "addr:street":"Gruettbachstrasse",
    "iso:country":"CH",
    "sg:address":"Gr\u00fcttbachstrasse 16",
    "sg:city":"Luterbach",
    "sg:orig_category":"Architektur U Ingenieurb\u00fcros",
    "sg:phone":"+41 32 682 58 93",
    "sg:postcode":"4542",
    "sg:province":"Solothurn",
    "wof:name":"Manfred Hubacher Konstruktionsb\u00fcro",
    "wof:placetype":"venue"
},
  "geometry": {"coordinates":[7.588266,47.217945],"type":"Point"}
}