{
  "type": "Feature",
  "properties": {
    "iso:country":"CH",
    "sg:address":"Madonna D'arla",
    "sg:city":"Sonvico",
    "sg:classifiers":[
        {
            "category":"Restaurant",
            "type":"Food & Drink"
        }
    ],
    "sg:phone":"+41 91 943 21 37",
    "sg:postcode":"6968",
    "sg:province":"Ticino",
    "wof:name":"Grotto Arla",
    "wof:placetype":"venue"
},
  "geometry": {"coordinates":[9.0164575577,46.0741767883],"type":"Point"}
}