{
  "type": "Feature",
  "properties": {
    "iso:country":"CH",
    "sg:address":"Rohracker",
    "sg:city":"Thundorf",
    "sg:orig_category":"Verwertung von Milch",
    "sg:postcode":"8512",
    "sg:province":"Thurgau",
    "wof:name":"K\u00e4sereigesellschaft Thundorf",
    "wof:placetype":"venue"
},
  "geometry": {"coordinates":[8.9647703171,47.5523986816],"type":"Point"}
}