{
  "type": "Feature",
  "properties": {
    "iso:country":"CH",
    "sg:address":"Dorfstrasse 36",
    "sg:city":"Matzendorf",
    "sg:orig_category":"Regionalbanken U Sparkassen",
    "sg:phone":"+41 62 386 26 26",
    "sg:postcode":"4713",
    "sg:province":"Solothurn",
    "wof:name":"Bank Im Thal Zweigstelle Matzendorf",
    "wof:placetype":"venue"
},
  "geometry": {"coordinates":[7.6296420097,47.3059272766],"type":"Point"}
}