{
  "type": "Feature",
  "properties": {
    "iso:country":"CH",
    "sg:address":"Grenzacherweg 190",
    "sg:city":"Riehen",
    "sg:orig_category":"Berufsorganisationen",
    "sg:postcode":"4125",
    "sg:province":"Basel-Stadt",
    "wof:name":"Ghr Gewerbehaus Riehen Ag",
    "wof:placetype":"venue"
},
  "geometry": {"coordinates":[7.645556,47.571949],"type":"Point"}
}