{
  "type": "Feature",
  "properties": {
    "iso:country":"CH",
    "sg:address":"Viale S. Franscini 11",
    "sg:city":"Bellinzona",
    "sg:orig_category":"Innendekorationsateliers Maler U Glasergewerbe",
    "sg:phone":"+41 91 825 86 49",
    "sg:postcode":"6500",
    "sg:province":"Ticino",
    "wof:name":"Zanchin Giuseppe",
    "wof:placetype":"venue"
},
  "geometry": {"coordinates":[9.0186090469,46.1904792786],"type":"Point"}
}