{
  "type": "Feature",
  "properties": {
    "iso:country":"CH",
    "sg:address":"M\u00fchlewiesestrasse 7",
    "sg:city":"Aadorf",
    "sg:orig_category":"Wirtschaftspr\u00fcfung, Steuerberatung U Treuhand",
    "sg:phone":"+41 52 365 02 58",
    "sg:postcode":"8355",
    "sg:province":"Thurgau",
    "wof:name":"Tkd M\u00e4chler Treuhandgesellschaft",
    "wof:placetype":"venue"
},
  "geometry": {"coordinates":[8.9060316086,47.490272522],"type":"Point"}
}