{
  "type": "Feature",
  "properties": {
    "iso:country":"CH",
    "sg:address":"Schwarztorstrasse 22",
    "sg:city":"Bern",
    "sg:orig_category":"Arbeitnehmerverb\u00e4nde",
    "sg:phone":"+41 31 381 39 39",
    "sg:postcode":"3007",
    "sg:province":"Bern",
    "wof:name":"Verband Schweiz.assistenz-& Ober\u00e4rzte,sekt.bern",
    "wof:placetype":"venue"
},
  "geometry": {"coordinates":[7.434776,46.943611],"type":"Point"}
}