{
  "type": "Feature",
  "properties": {
    "iso:country":"CH",
    "sg:address":"Sulzbacherstrasse 1399",
    "sg:city":"Uster",
    "sg:orig_category":"Sanit\u00e4r U Heizungsinstallation Schlossereien",
    "sg:phone":"+41 19401144",
    "sg:postcode":"8610",
    "sg:province":"Z\u00fcrich",
    "wof:name":"Josef Pr\u00e4auer Heizungen & Schlosserei",
    "wof:placetype":"venue"
},
  "geometry": {"coordinates":[8.7422552109,47.3320884705],"type":"Point"}
}