{
  "type": "Feature",
  "properties": {
    "addr:full":"Dornacherstrasse 114 Aesch Basel-Landschaft 4147",
    "addr:housenumber":"114",
    "addr:postcode":"4147",
    "addr:street":"Dornacherstrasse",
    "iso:country":"CH",
    "sg:address":"Dornacherstrasse 114",
    "sg:city":"Aesch",
    "sg:classifiers":[
        {
            "category":"Wholesale",
            "subcategory":"Drugs",
            "type":"Manufacturing & Wholesale Goods"
        }
    ],
    "sg:phone":"+41 61 705 43 43",
    "sg:postcode":"4147",
    "sg:province":"Basel-Landschaft",
    "sg:tags":[
        "generic"
    ],
    "wof:name":"Mepha Pharma Ag",
    "wof:placetype":"venue"
},
  "geometry": {"coordinates":[7.60461,47.481674],"type":"Point"}
}