{
  "type": "Feature",
  "properties": {
    "iso:country":"CH",
    "sg:address":"Chemin Des Croisettes 26",
    "sg:city":"Epalinges",
    "sg:orig_category":"H\u00f6here Fachschulen",
    "sg:phone":"+41 21 654 01 50",
    "sg:postcode":"1066",
    "sg:province":"Vaud",
    "wof:name":"Swissmem Ecole De Cadres",
    "wof:placetype":"venue"
},
  "geometry": {"coordinates":[6.6591029167,46.5440979004],"type":"Point"}
}