{
  "type": "Feature",
  "properties": {
    "iso:country":"CH",
    "sg:address":"Wernischwand",
    "sg:city":"Sch\u00fcpfheim",
    "sg:orig_category":"Verarbeitung von Milch Verwertung von Milch",
    "sg:postcode":"6170",
    "sg:province":"Luzern",
    "wof:name":"K\u00e4sereigenossenschaft Oberberg",
    "wof:placetype":"venue"
},
  "geometry": {"coordinates":[8.0194749832,46.9536094666],"type":"Point"}
}