{
  "type": "Feature",
  "properties": {
    "iso:country":"CH",
    "sg:address":"Innerer Giessenweg 29. 3110 M\u00fcnsingen. Postfach",
    "sg:city":"M\u00fcnsingen",
    "sg:orig_category":"Satzherstellung U Reproduktion",
    "sg:phone":"+41 31 721 33 74",
    "sg:postcode":"3110",
    "sg:province":"Bern",
    "wof:name":"Pauli, Martin",
    "wof:placetype":"venue"
},
  "geometry": {"coordinates":[7.5497250557,46.8725280762],"type":"Point"}
}