{
  "type": "Feature",
  "properties": {
    "iso:country":"CH",
    "sg:address":"Alte Lyss-strasse 12",
    "sg:city":"Aarberg",
    "sg:orig_category":"Handel mit Motorr\u00e4dern, Teilen U Zubeh\u00f6r Instandhaltung U Reparatur von Motorr\u00e4dern",
    "sg:phone":"+41 32 392 28 22",
    "sg:postcode":"3270",
    "sg:province":"Bern",
    "wof:name":"M\u00f6ri Sport Ag Moto-center-seeland",
    "wof:placetype":"venue"
},
  "geometry": {"coordinates":[7.2749400139,47.0393333435],"type":"Point"}
}