{
  "type": "Feature",
  "properties": {
    "iso:country":"CH",
    "sg:address":"Hinterbundstrasse 12",
    "sg:city":"Dietlikon",
    "sg:orig_category":"Markt U Meinungsforschung Sonstige Aktivit\u00e4ten der nicht-\u00e4rztlichen Medizinalberufe",
    "sg:phone":"+41 55 462 26 02",
    "sg:postcode":"8305",
    "sg:province":"Z\u00fcrich",
    "wof:name":"Meier Silvia Marisa, Praxismarketing",
    "wof:placetype":"venue"
},
  "geometry": {"coordinates":[8.853112,47.190441],"type":"Point"}
}