{
  "type": "Feature",
  "properties": {
    "iso:country":"CH",
    "sg:address":"Gl\u00e4ndstrasse 24",
    "sg:city":"Rothrist",
    "sg:orig_category":"Herstellung von Besen U B\u00fcrsten Wohnheime",
    "sg:phone":"+41 62 785 01 01",
    "sg:postcode":"4852",
    "sg:province":"Aargau",
    "wof:name":"Borna Blinden Und Invalidenheim Rothrist",
    "wof:placetype":"venue"
},
  "geometry": {"coordinates":[7.9020810127,47.2991485596],"type":"Point"}
}