{
  "type": "Feature",
  "properties": {
    "iso:country":"CH",
    "sg:address":"Kreuzlingerstrasse 38",
    "sg:city":"Amriswil",
    "sg:orig_category":"Instandhaltung U Reparatur von Automobilen",
    "sg:phone":"+41 71 411 70 30",
    "sg:postcode":"8580",
    "sg:province":"Thurgau",
    "wof:name":"Sportgarage Roman Walther",
    "wof:placetype":"venue"
},
  "geometry": {"coordinates":[9.2776908875,47.5484695435],"type":"Point"}
}