{
  "type": "Feature",
  "properties": {
    "iso:country":"CH",
    "sg:address":"Neuquartierstrasse 25",
    "sg:city":"Biberist",
    "sg:orig_category":"Grosshandel mit sonstigen Gebrauchs U Verbrauchsg\u00fctern",
    "sg:phone":"+41 32 672 23 36",
    "sg:postcode":"4562",
    "sg:province":"Solothurn",
    "wof:name":"Informa-grafik Vogel Werner",
    "wof:placetype":"venue"
},
  "geometry": {"coordinates":[7.5661978722,47.18359375],"type":"Point"}
}