{
  "type": "Feature",
  "properties": {
    "iso:country":"CH",
    "sg:address":"Valentin Rue Du 16",
    "sg:city":"Lausanne",
    "sg:orig_category":"Detailhandel mit Waren verschiedener Art, Hauptrichtung Nahrungsmittel",
    "sg:phone":"+41 22 771 10 13",
    "sg:postcode":"1004",
    "sg:province":"Vaud",
    "wof:name":"Epicerie Poste",
    "wof:placetype":"venue"
},
  "geometry": {"coordinates":[6.1360998154,46.1454849243],"type":"Point"}
}