{
  "type": "Feature",
  "properties": {
    "iso:country":"CH",
    "sg:address":"Porte-neuve Rue De La 20",
    "sg:city":"Sion",
    "sg:orig_category":"Pensionskassen",
    "sg:postcode":"1950",
    "sg:province":"Valais",
    "wof:name":"Fondation De Pr\u00e9voyance En Faveur Du Personnel Du Secr\u00e9tariat Des Syndicats Chr\u00e9tiens Du Valais Central",
    "wof:placetype":"venue"
},
  "geometry": {"coordinates":[7.3588571548,46.2280921936],"type":"Point"}
}