{
  "type": "Feature",
  "properties": {
    "iso:country":"CH",
    "sg:address":"Rue Du Bourg 33",
    "sg:city":"Chailly-montreux",
    "sg:orig_category":"Sonstige pers\u00f6nliche Dienstleistungen Wirtschaftspr\u00fcfung, Steuerberatung U Treuhand",
    "sg:phone":"+41 21 964 14 72",
    "sg:postcode":"1816",
    "sg:province":"Vaud",
    "wof:name":"Itark Sa",
    "wof:placetype":"venue"
},
  "geometry": {"coordinates":[6.8911938667,46.4546165466],"type":"Point"}
}