{
  "type": "Feature",
  "properties": {
    "iso:country":"CH",
    "sg:address":"Ch. Du Foron 19 1226 Th\u00f4nex. Postfach",
    "sg:city":"Th\u00f4nex",
    "sg:orig_category":"Pensionskassen",
    "sg:postcode":"1226",
    "sg:province":"Gen\u00e8ve",
    "wof:name":"Fondation De Pr\u00e9voyance En Faveur Du Personnel De Caran D'ache Sa",
    "wof:placetype":"venue"
},
  "geometry": {"coordinates":[6.2106781006,46.1935195923],"type":"Point"}
}