{
  "type": "Feature",
  "properties": {
    "iso:country":"CH",
    "sg:address":"Haldenstrasse 5",
    "sg:city":"Baar",
    "sg:orig_category":"Vermietung U Verpachtung von eigenen Immobilien",
    "sg:phone":"+41 41 760 00 25",
    "sg:postcode":"6340",
    "sg:province":"Zug",
    "wof:name":"Mbc Immobau Ag",
    "wof:placetype":"venue"
},
  "geometry": {"coordinates":[8.5383815765,47.1966171265],"type":"Point"}
}