{
  "type": "Feature",
  "properties": {
    "iso:country":"CH",
    "sg:address":"8564",
    "sg:city":"W\u00e4ldi",
    "sg:orig_category":"Vereine Gesang",
    "sg:phone":"+41 71 891 45 87",
    "sg:postcode":"8564",
    "sg:province":"Thurgau",
    "wof:name":"M\u00e4nnerchor Heiden",
    "wof:placetype":"venue"
},
  "geometry": {"coordinates":[9.5220088959,47.4489135742],"type":"Point"}
}