{
  "type": "Feature",
  "properties": {
    "iso:country":"CH",
    "sg:address":"Leemattenweg 6",
    "sg:city":"Fislisbach",
    "sg:orig_category":"Wirtschaftspr\u00fcfung, Steuerberatung U Treuhand",
    "sg:phone":"+41 56 493 10 42",
    "sg:postcode":"5442",
    "sg:province":"Aargau",
    "wof:name":"Tetrachord Ag",
    "wof:placetype":"venue"
},
  "geometry": {"coordinates":[8.2879209518,47.4366836548],"type":"Point"}
}