{
  "type": "Feature",
  "properties": {
    "iso:country":"CH",
    "sg:address":"Strassburgerallee 68 4055 Basel. Postfach",
    "sg:city":"Basel",
    "sg:orig_category":"Herstellung von sonstigen Maschinen f\u00fcr unspezifische Verwendung",
    "sg:phone":"+41 79 311 55 55",
    "sg:postcode":"4051",
    "sg:province":"Basel-Stadt",
    "wof:name":"Niro Gastro Service Niederer Robert Grossk\u00fcchen Bes. Gastgewerbe; Beratung, Service, Verkauf",
    "wof:placetype":"venue"
},
  "geometry": {"coordinates":[7.5698652267,47.5626411438],"type":"Point"}
}