{
  "type": "Feature",
  "properties": {
    "iso:country":"CH",
    "sg:address":"S\u00e4gestr. 22",
    "sg:city":"Sch\u00fcpfen",
    "sg:classifiers":[
        {
            "category":"Home & Garden",
            "subcategory":"Furniture",
            "type":"Retail Goods"
        }
    ],
    "sg:phone":"+41 31 808 06 06",
    "sg:postcode":"3054",
    "sg:province":"Bern",
    "sg:tags":[
        "wood"
    ],
    "wof:name":"S\u00c4gerei Trachsel Ag",
    "wof:placetype":"venue"
},
  "geometry": {"coordinates":[7.4485859871,46.7816314697],"type":"Point"}
}