{
  "type": "Feature",
  "properties": {
    "iso:country":"CH",
    "sg:address":"Haltingerstrasse 92/94 4057 Basel. Postfach",
    "sg:city":"Basel",
    "sg:orig_category":"Detailhandel mit Milcherzeugnissen U Eiern Grosshandel mit Milch, Milcherzeugnissen, Eiern, Speise\u00f6l",
    "sg:phone":"+41 61 311 27 01",
    "sg:postcode":"4005",
    "sg:province":"Basel-Stadt",
    "wof:name":"F. + E. Zimmermann Ag Milch, Milchprodukte, Lebensmittel Usw; Handel",
    "wof:placetype":"venue"
},
  "geometry": {"coordinates":[7.5966877937,47.5663337708],"type":"Point"}
}