{
  "type": "Feature",
  "properties": {
    "iso:country":"CH",
    "sg:address":"Kapuzinerstrasse 32 3902 Glis. Postfach 117",
    "sg:city":"Glis",
    "sg:orig_category":"Verwaltung von Immobilien Wirtschaftspr\u00fcfung, Steuerberatung U Treuhand",
    "sg:phone":"+41 27 923 51 24",
    "sg:postcode":"3902",
    "sg:province":"Valais",
    "wof:name":"Treuhandb\u00fcro Valsecchi",
    "wof:placetype":"venue"
},
  "geometry": {"coordinates":[7.9871549606,46.3133888245],"type":"Point"}
}