{
  "type": "Feature",
  "properties": {
    "iso:country":"CH",
    "sg:address":"Porrentruy Route De 74",
    "sg:city":"Del\u00e9mont",
    "sg:orig_category":"Pensionskassen",
    "sg:postcode":"2800",
    "sg:province":"Jura",
    "wof:name":"Fondation De Pr\u00e9voyance Paritaire De Pr\u00e9ci-dip Durtal Sa",
    "wof:placetype":"venue"
},
  "geometry": {"coordinates":[7.3354110718,47.3606529236],"type":"Point"}
}