{
  "type": "Feature",
  "properties": {
    "iso:country":"CH",
    "sg:address":"8580 Amriswil. Postfach 283",
    "sg:city":"Amriswil",
    "sg:orig_category":"Detailhandel mit Metallwaren, Anstrichmitteln, Glaswaren, Bau U Heimwerkerbedarf",
    "sg:phone":"+41 71 411 21 74",
    "sg:postcode":"8580",
    "sg:province":"Thurgau",
    "wof:name":"Hauert Alfred.",
    "wof:placetype":"venue"
},
  "geometry": {"coordinates":[9.2995681763,47.54504776],"type":"Point"}
}