{
  "type": "Feature",
  "properties": {
    "iso:country":"CH",
    "sg:address":"Albulastrasse 55",
    "sg:city":"Z\u00fcrich",
    "sg:classifiers":[
        {
            "category":"Banks & Credit Unions",
            "subcategory":"Investment Brokerage",
            "type":"Services"
        }
    ],
    "sg:phone":"+41 14346666",
    "sg:postcode":"8048",
    "sg:province":"Z\u00fcrich",
    "sg:tags":[
        "telecommunication",
        "isdn",
        "system"
    ],
    "wof:name":"Egtel Ag",
    "wof:placetype":"venue"
},
  "geometry": {"coordinates":[8.4921560287,47.3885154724],"type":"Point"}
}