{
  "type": "Feature",
  "properties": {
    "iso:country":"CH",
    "sg:address":"Letziwiesstrasse 8 9604 L\u00fctisburg. Postfach",
    "sg:city":"L\u00fctisburg",
    "sg:orig_category":"Herstellung von Maschinen f\u00fcr die Nahrungsmittel, Getr\u00e4nkeherstellung U die Tabakverarbeitung Stahl ",
    "sg:phone":"+41 71 385 31 11",
    "sg:postcode":"9604",
    "sg:province":"St. Gallen",
    "wof:name":"Maier J. & E. Ag",
    "wof:placetype":"venue"
},
  "geometry": {"coordinates":[9.2595090866,47.4130706787],"type":"Point"}
}