{
  "type": "Feature",
  "properties": {
    "iso:country":"CH",
    "sg:address":"Chemin Des Conches 64",
    "sg:city":"Conches",
    "sg:orig_category":"Unternehmensberatung",
    "sg:phone":"+41 22 789 55 00",
    "sg:postcode":"1231",
    "sg:province":"Gen\u00e8ve",
    "wof:name":"Bernard Taramarcaz Conseils D'entreprises",
    "wof:placetype":"venue"
},
  "geometry": {"coordinates":[6.175868988,46.178276062],"type":"Point"}
}