{
  "type": "Feature",
  "properties": {
    "iso:country":"CH",
    "sg:address":"Waaghausgasse 5 3011 Bern. Postfach",
    "sg:city":"Bern",
    "sg:orig_category":"Fachdetailhandel in Verkaufsr\u00e4umen",
    "sg:postcode":"3005",
    "sg:province":"Bern",
    "wof:name":"Photo Heinzelmann Fotogesch\u00e4ft.",
    "wof:placetype":"venue"
},
  "geometry": {"coordinates":[7.4443759918,46.9487113953],"type":"Point"}
}