{
  "type": "Feature",
  "properties": {
    "iso:country":"CH",
    "sg:address":"Niesenweg 21",
    "sg:city":"Toffen",
    "sg:orig_category":"Elektroinstallation",
    "sg:phone":"+41 31 819 22 31",
    "sg:postcode":"3125",
    "sg:province":"Bern",
    "wof:name":"Kurt Krebs Ag",
    "wof:placetype":"venue"
},
  "geometry": {"coordinates":[7.4913749695,46.8617210388],"type":"Point"}
}