{
  "type": "Feature",
  "properties": {
    "iso:country":"CH",
    "sg:address":"Hauptstrasse 31 9214 Kradolf. Postfach 71",
    "sg:city":"Kradolf",
    "sg:orig_category":"Diskotheken, Dancings, Night Clubs",
    "sg:phone":"+41 71 642 49 49",
    "sg:postcode":"9214",
    "sg:province":"Thurgau",
    "wof:name":"Taverne-dancing Klein Rigi",
    "wof:placetype":"venue"
},
  "geometry": {"coordinates":[9.1987743378,47.5260620117],"type":"Point"}
}