{
  "type": "Feature",
  "properties": {
    "iso:country":"CH",
    "sg:address":"Hondrichstrasse",
    "sg:city":"Spiez",
    "sg:orig_category":"Herstellung von sonstigen M\u00f6beln",
    "sg:postcode":"3700",
    "sg:province":"Bern",
    "wof:name":"Friedrich Maurer",
    "wof:placetype":"venue"
},
  "geometry": {"coordinates":[7.6819648743,46.6810531616],"type":"Point"}
}