{
  "type": "Feature",
  "properties": {
    "addr:full":"Schulhausg\u00e4ssli 4 K\u00f6niz Bern 3098",
    "addr:housenumber":"4",
    "addr:postcode":"3098",
    "addr:street":"Schulhausgaessli",
    "iso:country":"CH",
    "sg:address":"Schulhausg\u00e4ssli 4",
    "sg:city":"K\u00f6niz",
    "sg:orig_category":"Architektur U Ingenieurb\u00fcros Architekturb\u00fcros",
    "sg:phone":"+41 31 971 52 84",
    "sg:postcode":"3098",
    "sg:province":"Bern",
    "wof:name":"Architekturb\u00fcro Reust Ag",
    "wof:placetype":"venue"
},
  "geometry": {"coordinates":[7.412769,46.921139],"type":"Point"}
}