{
  "type": "Feature",
  "properties": {
    "iso:country":"CH",
    "sg:address":"Bahnhofstrasse 3",
    "sg:city":"Romanshorn",
    "sg:orig_category":"Zahnarztpraxen",
    "sg:phone":"+41 71 463 10 41",
    "sg:postcode":"8590",
    "sg:province":"Thurgau",
    "wof:name":"Dr.med.dent.j\u00fcrg Breitenmoser Zahnarzt",
    "wof:placetype":"venue"
},
  "geometry": {"coordinates":[9.3779754639,47.5659179688],"type":"Point"}
}