{
  "type": "Feature",
  "properties": {
    "iso:country":"CH",
    "sg:address":"Wangenstrasse 100a",
    "sg:city":"Herzogenbuchsee",
    "sg:orig_category":"Allgemeiner Hoch U Tiefbau Handelsvermittlung U Grosshandel",
    "sg:phone":"+41 62 961 86 65",
    "sg:postcode":"3360",
    "sg:province":"Bern",
    "wof:name":"Thierstein Ag Festwirtschaft-vermietungen",
    "wof:placetype":"venue"
},
  "geometry": {"coordinates":[7.70005,47.196533],"type":"Point"}
}