{
  "type": "Feature",
  "properties": {
    "iso:country":"CH",
    "sg:address":"Neugass 23",
    "sg:city":"Berneck",
    "sg:orig_category":"Nationale Postdienste",
    "sg:phone":"+41 71 744 10 45",
    "sg:postcode":"9442",
    "sg:province":"St. Gallen",
    "wof:name":"Die Schweizerische Post",
    "wof:placetype":"venue"
},
  "geometry": {"coordinates":[9.6131267548,47.4256401062],"type":"Point"}
}