{
  "type": "Feature",
  "properties": {
    "iso:country":"CH",
    "sg:address":"Breitenaustrasse 139 8200 Schaffhausen. Postfach",
    "sg:city":"Schaffhausen",
    "sg:orig_category":"Sonstiger Grosshandel",
    "sg:postcode":"8202",
    "sg:province":"Schaffhausen",
    "wof:name":"Wittwer Urs Cons. & Trad",
    "wof:placetype":"venue"
},
  "geometry": {"coordinates":[8.6222829819,47.7067108154],"type":"Point"}
}