{
  "type": "Feature",
  "properties": {
    "iso:country":"CH",
    "sg:address":"Chemin De La Chocolati\u00e8re 2",
    "sg:city":"Bussigny-lausanne",
    "sg:orig_category":"Bauspenglerei Herstellung von Mess U Kontrollinstrumenten U vorrichtungen",
    "sg:phone":"+41 21 701 36 31",
    "sg:postcode":"1030",
    "sg:province":"Vaud",
    "wof:name":"Aubort Alfred Sa",
    "wof:placetype":"venue"
},
  "geometry": {"coordinates":[6.55026,46.545635],"type":"Point"}
}