{
  "type": "Feature",
  "properties": {
    "iso:country":"CH",
    "sg:address":"Friedbergstrasse 9 8820 W\u00e4denswil. Postfach",
    "sg:city":"W\u00e4denswil",
    "sg:orig_category":"Erschliessung von Grundst\u00fccken",
    "sg:postcode":"8820",
    "sg:province":"Z\u00fcrich",
    "wof:name":"Baugenossenschaft Eichweid",
    "wof:placetype":"venue"
},
  "geometry": {"coordinates":[8.6738567352,47.2291755676],"type":"Point"}
}