{
  "type": "Feature",
  "properties": {
    "iso:country":"CH",
    "sg:address":"Christoph Merian-strasse 6",
    "sg:city":"M\u00fcnchenstein",
    "sg:orig_category":"Detailhandel mit Gebrauchtwaren in Verkaufsr\u00e4umen",
    "sg:phone":"+41 19501291",
    "sg:postcode":"4142",
    "sg:province":"Basel-Landschaft",
    "wof:name":"Hilde Kuster Brockenstube Denk An Mich",
    "wof:placetype":"venue"
},
  "geometry": {"coordinates":[8.7839918137,47.3674468994],"type":"Point"}
}