{
  "type": "Feature",
  "properties": {
    "iso:country":"CH",
    "sg:address":"1583",
    "sg:city":"Villarepos",
    "sg:orig_category":"Sportvereine Ballsport Fussball",
    "sg:postcode":"1583",
    "sg:province":"Fribourg",
    "wof:name":"Fc Villarepos",
    "wof:placetype":"venue"
},
  "geometry": {"coordinates":[7.0848898888,46.8821983337],"type":"Point"}
}