{
  "type": "Feature",
  "properties": {
    "iso:country":"CH",
    "sg:address":"H\u00f6he 14 3312 Fraubrunnen. Postfach 223",
    "sg:city":"Sch\u00f6nb\u00fchl-urtenen",
    "sg:orig_category":"Geb\u00e4ude, Wohnungsreinigung",
    "sg:phone":"+41 18451858",
    "sg:postcode":"3322",
    "sg:province":"Bern",
    "wof:name":"Fancelli-geb\u00e4udereinigungen",
    "wof:placetype":"venue"
},
  "geometry": {"coordinates":[8.4397106171,47.4540672302],"type":"Point"}
}