{
  "type": "Feature",
  "properties": {
    "iso:country":"CH",
    "sg:address":"Industriestrasse 13",
    "sg:city":"B\u00f6singen",
    "sg:orig_category":"Allgemeiner Hoch U Tiefbau Allgemeiner Hochbau",
    "sg:phone":"+41 79 222 76 86",
    "sg:postcode":"3178",
    "sg:province":"Fribourg",
    "wof:name":"Neustrag Ag Bauunternehmung",
    "wof:placetype":"venue"
},
  "geometry": {"coordinates":[7.229587,46.900921],"type":"Point"}
}