{
  "type": "Feature",
  "properties": {
    "iso:country":"CH",
    "sg:address":"Hauptstrasse 85",
    "sg:city":"T\u00e4gerwilen",
    "sg:orig_category":"RESTAURANTS: TEA-ROOMS",
    "sg:postcode":"8274",
    "sg:province":"Thurgau",
    "wof:name":"Sistek M.",
    "wof:placetype":"venue"
},
  "geometry": {"coordinates":[9.1340780258,47.6550979614],"type":"Point"}
}