{
  "type": "Feature",
  "properties": {
    "iso:country":"CH",
    "sg:address":"Ringstrasse 37",
    "sg:city":"Frauenfeld",
    "sg:orig_category":"Maler U Glasergewerbe Malerei",
    "sg:phone":"+41 41 630 46 56",
    "sg:postcode":"8500",
    "sg:province":"Thurgau",
    "wof:name":"Malergesch\u00e4ft Niederberger & Achermann Gmbh",
    "wof:placetype":"venue"
},
  "geometry": {"coordinates":[8.311841011,46.986164093],"type":"Point"}
}