{
  "type": "Feature",
  "properties": {
    "iso:country":"CH",
    "sg:address":"Hauptstrasse 29",
    "sg:city":"R\u00fcttenen",
    "sg:orig_category":"Bau von Strassen, Sportanlagen U Bahnverkehrsstrecken Strassenbau",
    "sg:postcode":"4522",
    "sg:province":"Solothurn",
    "wof:name":"Ruetsch Harry",
    "wof:placetype":"venue"
},
  "geometry": {"coordinates":[7.528683,47.229683],"type":"Point"}
}