{
  "type": "Feature",
  "properties": {
    "iso:country":"CH",
    "sg:address":"Kirchweg 2 3510 Konolfingen. Postfach",
    "sg:city":"Konolfingen",
    "sg:orig_category":"Softwareentwicklung U beratung Sonstige mit der Informatik verbundene T\u00e4tigkeiten",
    "sg:phone":"+41 31 792 00 40",
    "sg:postcode":"3510",
    "sg:province":"Bern",
    "wof:name":"Nbit Informatik Gmbh Dienstleistungen Im Bereich Der Informatik Usw.",
    "wof:placetype":"venue"
},
  "geometry": {"coordinates":[7.6202769279,46.8787117004],"type":"Point"}
}