{
  "type": "Feature",
  "properties": {
    "iso:country":"CH",
    "sg:address":"Z\u00fcrcherstrasse 240 8406 Winterthur. Postfach 289",
    "sg:city":"Winterthur",
    "sg:orig_category":"Autogaragen",
    "sg:phone":"+41 52 202 72 28",
    "sg:postcode":"8406",
    "sg:province":"Z\u00fcrich",
    "wof:name":"Auvag Automobil-verkauf Ag Garage",
    "wof:placetype":"venue"
},
  "geometry": {"coordinates":[8.70775,47.460693],"type":"Point"}
}