{
  "type": "Feature",
  "properties": {
    "iso:country":"CH",
    "sg:address":"Unterworbenstrasse 51 3252 Worben. Postfach 115",
    "sg:city":"Worben",
    "sg:orig_category":"Herstellung von Werkzeugen Mechanische Werkst\u00e4tten",
    "sg:phone":"+41 32 384 75 54",
    "sg:postcode":"3252",
    "sg:province":"Bern",
    "wof:name":"Safrima Ag",
    "wof:placetype":"venue"
},
  "geometry": {"coordinates":[7.3018221855,47.1044311523],"type":"Point"}
}