{
  "type": "Feature",
  "properties": {
    "iso:country":"CH",
    "sg:address":"Rudolf Diesel-strasse 1",
    "sg:city":"Winterthur",
    "sg:classifiers":[
        {
            "category":"Professional",
            "subcategory":"Art Services",
            "type":"Services"
        }
    ],
    "sg:phone":"+41 52 232 11 11",
    "sg:postcode":"8404",
    "sg:province":"Z\u00fcrich",
    "sg:tags":[
        "graphic",
        "designer"
    ],
    "wof:name":"Carpage Internet Design",
    "wof:placetype":"venue"
},
  "geometry": {"coordinates":[8.7531089783,47.4957122803],"type":"Point"}
}