{
  "type": "Feature",
  "properties": {
    "iso:country":"CH",
    "sg:address":"6999",
    "sg:city":"Astano",
    "sg:orig_category":"Vorschulen, Kinderg\u00e4rten",
    "sg:postcode":"6999",
    "sg:province":"Ticino",
    "wof:name":"Scuola Materna",
    "wof:placetype":"venue"
},
  "geometry": {"coordinates":[8.8151702881,46.0153694153],"type":"Point"}
}