{
  "type": "Feature",
  "properties": {
    "iso:country":"CH",
    "sg:address":"Hauptstrasse 17",
    "sg:city":"Staufen",
    "sg:orig_category":"Kosmetikinstitute",
    "sg:phone":"+41 62 891 50 68",
    "sg:postcode":"5603",
    "sg:province":"Aargau",
    "wof:name":"Carla Bellot Schlankheit & Sch\u00f6nheit",
    "wof:placetype":"venue"
},
  "geometry": {"coordinates":[8.1683645248,47.3864517212],"type":"Point"}
}