{
  "type": "Feature",
  "properties": {
    "iso:country":"CH",
    "sg:address":"Nelkenweg 3",
    "sg:city":"Langenthal",
    "sg:orig_category":"Unclassifiable Establishments",
    "sg:postcode":"4900",
    "sg:province":"Bern",
    "wof:name":"Schlossfabrik Heusser Holding Ag",
    "wof:placetype":"venue"
},
  "geometry": {"coordinates":[7.7900910378,47.2151031494],"type":"Point"}
}