{
  "type": "Feature",
  "properties": {
    "iso:country":"CH",
    "sg:address":"Gartenhofstrasse 15 8004 Z\u00fcrich. Postfach 1633",
    "sg:city":"Z\u00fcrich",
    "sg:orig_category":"Interessenvertretungen",
    "sg:postcode":"8001",
    "sg:province":"Z\u00fcrich",
    "wof:name":"Genossenschaft-montecolla",
    "wof:placetype":"venue"
},
  "geometry": {"coordinates":[8.5253334045,47.3723144531],"type":"Point"}
}