{
  "type": "Feature",
  "properties": {
    "iso:country":"CH",
    "sg:address":"Chapfstrasse 26b",
    "sg:city":"Bonstetten",
    "sg:orig_category":"Unternehmensberatung Wirtschaftspr\u00fcfung, Steuerberatung U Treuhand",
    "sg:phone":"+41 41 630 25 35",
    "sg:postcode":"8906",
    "sg:province":"Z\u00fcrich",
    "wof:name":"Titanus Treuhand Ag",
    "wof:placetype":"venue"
},
  "geometry": {"coordinates":[8.3105077744,46.9956893921],"type":"Point"}
}