{
  "type": "Feature",
  "properties": {
    "iso:country":"CH",
    "sg:address":"Sch\u00fctzengasse 19",
    "sg:city":"Heiden",
    "sg:orig_category":"Allgemeiner Hochbau Zimmerei, Dachdeckerei, Bauspenglerei U Abdichtung",
    "sg:phone":"+41 79 605 21 27",
    "sg:postcode":"9410",
    "sg:province":"Appenzell Ausserrhoden",
    "wof:name":"Alder J\u00fcrg",
    "wof:placetype":"venue"
},
  "geometry": {"coordinates":[9.529544,47.440151],"type":"Point"}
}