{
  "type": "Feature",
  "properties": {
    "iso:country":"CH",
    "sg:address":"Rue Basse 6",
    "sg:city":"Grandson",
    "sg:orig_category":"Detailhandel mit Brot, Back U S\u00fcsswaren",
    "sg:phone":"+41 24 445 33 43",
    "sg:postcode":"1422",
    "sg:province":"Vaud",
    "wof:name":"Nelly Leuenberger Boulangerie & P\u00e2tisserie",
    "wof:placetype":"venue"
},
  "geometry": {"coordinates":[6.645091,46.808403],"type":"Point"}
}