{
  "type": "Feature",
  "properties": {
    "iso:country":"CH",
    "sg:address":"Grubenstrasse 104 8200 Schaffhausen. Postfach 557",
    "sg:city":"Schaffhausen",
    "sg:orig_category":"G\u00fcterbef\u00f6rderung im Strassenverkehr",
    "sg:phone":"+41 52 624 52 52",
    "sg:postcode":"8201",
    "sg:province":"Schaffhausen",
    "wof:name":"Gebr\u00fcder Gonzalez Int. M\u00f6beltransporte",
    "wof:placetype":"venue"
},
  "geometry": {"coordinates":[8.6481380463,47.7027359009],"type":"Point"}
}