{
  "type": "Feature",
  "properties": {
    "iso:country":"CH",
    "sg:address":"Jeukenweg 2",
    "sg:city":"Zeiningen",
    "sg:orig_category":"Grafikateliers, Design",
    "sg:phone":"+41 61 421 32 61",
    "sg:postcode":"4314",
    "sg:province":"Aargau",
    "wof:name":"Josef Wittlin Schriftenmalerei",
    "wof:placetype":"venue"
},
  "geometry": {"coordinates":[7.8758368492,47.5390205383],"type":"Point"}
}