{
  "type": "Feature",
  "properties": {
    "iso:country":"CH",
    "sg:address":"Chamerstrasse 24",
    "sg:city":"H\u00fcnenberg",
    "sg:orig_category":"Grosshandel mit Geschenkartikeln U Souvenirs Grosshandel mit sonstigen Gebrauchs U Verbrauchsg\u00fctern",
    "sg:phone":"+41 41 780 61 63",
    "sg:postcode":"6331",
    "sg:province":"Zug",
    "wof:name":"B\u00fctler D. Werbeartikel + Beschriftungen",
    "wof:placetype":"venue"
},
  "geometry": {"coordinates":[8.42735672,47.1768951416],"type":"Point"}
}