{
  "type": "Feature",
  "properties": {
    "iso:country":"CH",
    "sg:address":"Kornweg 8",
    "sg:city":"Staufen",
    "sg:orig_category":"Kosmetikinstitute",
    "sg:phone":"+41 62 891 81 31",
    "sg:postcode":"5603",
    "sg:province":"Aargau",
    "wof:name":"Brigitta Schlosser Kosmetikinstitut Brigitta",
    "wof:placetype":"venue"
},
  "geometry": {"coordinates":[8.1636514664,47.3850402832],"type":"Point"}
}