{
  "type": "Feature",
  "properties": {
    "iso:country":"CH",
    "sg:address":"Unterdorfstrasse 21",
    "sg:city":"Dornach",
    "sg:orig_category":"Unternehmensberatung",
    "sg:phone":"+41 18444074",
    "sg:postcode":"4143",
    "sg:province":"Solothurn",
    "wof:name":"Institut F\u00fcr Gesellschaftsbe- Zogenes Management (igm)",
    "wof:placetype":"venue"
},
  "geometry": {"coordinates":[8.4416189194,47.4601707458],"type":"Point"}
}