{
  "type": "Feature",
  "properties": {
    "iso:country":"CH",
    "sg:address":"Gewerbestrasse 16 8800 Thalwil. Postfach",
    "sg:city":"Thalwil",
    "sg:orig_category":"Non-Classified Establishments",
    "sg:postcode":"8800",
    "sg:province":"Z\u00fcrich",
    "wof:name":"Epc-holding Ag",
    "wof:placetype":"venue"
},
  "geometry": {"coordinates":[8.565993309,47.2857284546],"type":"Point"}
}