{
  "type": "Feature",
  "properties": {
    "iso:country":"CH",
    "sg:address":"Kantonsstrasse 39b",
    "sg:city":"Nottwil",
    "sg:orig_category":"Grosshandel mit Datenverarbeitungsger\u00e4ten Sonstige mit der Informatik verbundene T\u00e4tigkeiten",
    "sg:phone":"+41 41 938 02 35",
    "sg:postcode":"6207",
    "sg:province":"Luzern",
    "wof:name":"Esofttec Gmbh",
    "wof:placetype":"venue"
},
  "geometry": {"coordinates":[8.1311693192,47.1381072998],"type":"Point"}
}