{
  "type": "Feature",
  "properties": {
    "iso:country":"CH",
    "sg:address":"Grande Rue 7",
    "sg:city":"Morges",
    "sg:classifiers":[
        {
            "category":"Travel",
            "subcategory":"Hotels & Motels",
            "type":"Entertainment"
        }
    ],
    "sg:postcode":"1110",
    "sg:province":"Vaud",
    "sg:tags":[
        "hotels",
        "mit",
        "restaurant"
    ],
    "wof:name":"Buso Pierre",
    "wof:placetype":"venue"
},
  "geometry": {"coordinates":[6.4997320175,46.5102310181],"type":"Point"}
}