{
  "type": "Feature",
  "properties": {
    "iso:country":"CH",
    "sg:address":"Brunngasse 1",
    "sg:city":"Innerberg-s\u00e4riswil",
    "sg:orig_category":"Non-Classified Establishments",
    "sg:postcode":"3044",
    "sg:province":"Bern",
    "wof:name":"Bersana Gmbh",
    "wof:placetype":"venue"
},
  "geometry": {"coordinates":[7.3331999779,46.9912338257],"type":"Point"}
}