{
  "type": "Feature",
  "properties": {
    "iso:country":"CH",
    "sg:address":"Urdorferstrasse 43",
    "sg:city":"Dietikon",
    "sg:orig_category":"Zimmerei, Dachdeckerei, Bauspenglerei U Abdichtung",
    "sg:phone":"+41 17403025",
    "sg:postcode":"8953",
    "sg:province":"Z\u00fcrich",
    "wof:name":"Spenglerei Meier E.",
    "wof:placetype":"venue"
},
  "geometry": {"coordinates":[8.4161367416,47.3963394165],"type":"Point"}
}