{
  "type": "Feature",
  "properties": {
    "iso:country":"CH",
    "sg:address":"Envers 27g 2605 Sonceboz-sombeval. Postfach",
    "sg:city":"Sombeval",
    "sg:orig_category":"Non-Classified Establishments",
    "sg:postcode":"2605",
    "sg:province":"Bern",
    "wof:name":"44 Technics Chatelain Henri Et Chatelain Cedric",
    "wof:placetype":"venue"
},
  "geometry": {"coordinates":[7.1684827805,47.194568634],"type":"Point"}
}