{
  "type": "Feature",
  "properties": {
    "iso:country":"CH",
    "sg:address":"B\u00fctzbergstrasse 15",
    "sg:city":"Aarwangen",
    "sg:orig_category":"Autogaragen",
    "sg:phone":"+41 62 922 83 73",
    "sg:postcode":"4912",
    "sg:province":"Bern",
    "wof:name":"Ernst K\u00e4ser & Peter Jufer Dorf-garage",
    "wof:placetype":"venue"
},
  "geometry": {"coordinates":[7.773089,47.233639],"type":"Point"}
}