{
  "type": "Feature",
  "properties": {
    "iso:country":"CH",
    "sg:address":"Baselstrasse 57 4125 Riehen. Postfach",
    "sg:city":"Riehen",
    "sg:orig_category":"Werbeagenturen Werbevermittlung",
    "sg:phone":"+41 13914020",
    "sg:postcode":"4125",
    "sg:province":"Basel-Stadt",
    "wof:name":"Grob & Co Werbeagentur",
    "wof:placetype":"venue"
},
  "geometry": {"coordinates":[8.5765066147,47.3456077576],"type":"Point"}
}