{
  "type": "Feature",
  "properties": {
    "iso:country":"CH",
    "sg:address":"Florastrasse 11",
    "sg:city":"Z\u00fcrich",
    "sg:orig_category":"Satzherstellung U Reproduktion",
    "sg:phone":"+41 13883646",
    "sg:postcode":"8000",
    "sg:province":"Z\u00fcrich",
    "wof:name":"Graf, Wilhelm Ag",
    "wof:placetype":"venue"
},
  "geometry": {"coordinates":[8.5491695404,47.3610801697],"type":"Point"}
}