{
  "type": "Feature",
  "properties": {
    "iso:country":"CH",
    "sg:address":"Sonnmatt 41",
    "sg:city":"Mogelsberg",
    "sg:orig_category":"Markt U Meinungsforschung",
    "sg:phone":"+41 71 374 26 24",
    "sg:postcode":"9122",
    "sg:province":"St. Gallen",
    "wof:name":"Mobiles Marketing B\u00fcro Meyer-b\u00f6hm Maja",
    "wof:placetype":"venue"
},
  "geometry": {"coordinates":[9.136592865,47.3573226929],"type":"Point"}
}