{
  "type": "Feature",
  "properties": {
    "iso:country":"CH",
    "sg:address":"Rue De Lausanne 19",
    "sg:city":"Fribourg",
    "sg:orig_category":"Fachdetailhandel in Verkaufsr\u00e4umen",
    "sg:postcode":"1700",
    "sg:province":"Fribourg",
    "wof:name":"Antenen F.",
    "wof:placetype":"venue"
},
  "geometry": {"coordinates":[7.1601338387,46.8061027527],"type":"Point"}
}