{
  "type": "Feature",
  "properties": {
    "iso:country":"CH",
    "sg:address":"Obere Haldenstrasse 16 9327 T\u00fcbach. Postfach",
    "sg:city":"T\u00fcbach",
    "sg:orig_category":"Grosshandel mit Bekleidung Grosshandel mit Sportartikeln",
    "sg:phone":"+41 79 207 64 94",
    "sg:postcode":"9327",
    "sg:province":"St. Gallen",
    "wof:name":"Fennotex Ag",
    "wof:placetype":"venue"
},
  "geometry": {"coordinates":[9.4490299225,47.4835510254],"type":"Point"}
}