{
  "type": "Feature",
  "properties": {
    "iso:country":"CH",
    "sg:address":"Grand-rue 12 2900 Pruntrut. Postfach",
    "sg:city":"Pruntrut",
    "sg:orig_category":"RESTAURANTS: TEA-ROOMS",
    "sg:postcode":"2900",
    "sg:province":"Jura",
    "wof:name":"Lachat-desboeufs Bernadette",
    "wof:placetype":"venue"
},
  "geometry": {"coordinates":[7.075065136,47.4161720276],"type":"Point"}
}