{
  "type": "Feature",
  "properties": {
    "iso:country":"CH",
    "sg:address":"Renggerstrasse 61 8038 Z\u00fcrich. Postfach",
    "sg:city":"Z\u00fcrich",
    "sg:orig_category":"Maler U Glasergewerbe Tapeziererei",
    "sg:phone":"+41 14828620",
    "sg:postcode":"8038",
    "sg:province":"Z\u00fcrich",
    "wof:name":"Bertschi Und W\u00fcrmli Malergesch\u00e4ft",
    "wof:placetype":"venue"
},
  "geometry": {"coordinates":[8.5331811905,47.3443946838],"type":"Point"}
}