{
  "type": "Feature",
  "properties": {
    "iso:country":"CH",
    "sg:address":"Route De Courtavon",
    "sg:city":"Mi\u00e9court",
    "sg:orig_category":"Bauschreinerei",
    "sg:phone":"+41 32 462 26 73",
    "sg:postcode":"2946",
    "sg:province":"Jura",
    "wof:name":"Joseph Petignat Menuiserie",
    "wof:placetype":"venue"
},
  "geometry": {"coordinates":[7.179493,47.429909],"type":"Point"}
}