{
  "type": "Feature",
  "properties": {
    "iso:country":"CH",
    "sg:address":"Vignascia Via Alla 5",
    "sg:city":"Gordola",
    "sg:classifiers":[
        {
            "category":"Travel",
            "subcategory":"Hotels & Motels",
            "type":"Entertainment"
        }
    ],
    "sg:phone":"+41 27 771 61 21",
    "sg:postcode":"6596",
    "sg:province":"Ticino",
    "sg:tags":[
        "hotels",
        "mit",
        "restaurant"
    ],
    "wof:name":"Cdm Rhodania Sa",
    "wof:placetype":"venue"
},
  "geometry": {"coordinates":[7.2124481201,46.0804595947],"type":"Point"}
}