{
  "type": "Feature",
  "properties": {
    "iso:country":"CH",
    "sg:address":"Rue Du Vieux-ch\u00e2teau 25",
    "sg:city":"Delsberg",
    "sg:orig_category":"Instandhaltung U Reparatur von Automobilen",
    "sg:postcode":"2800",
    "sg:province":"Jura",
    "wof:name":"Jean-pierre Sauvain",
    "wof:placetype":"venue"
},
  "geometry": {"coordinates":[7.3535408974,47.3708534241],"type":"Point"}
}