{
  "type": "Feature",
  "properties": {
    "iso:country":"CH",
    "sg:address":"Rue De La Loge 29a",
    "sg:city":"Biel/bienne",
    "sg:orig_category":"Instandhaltung U Reparatur von Automobilen",
    "sg:phone":"+41 32423220",
    "sg:postcode":"2500",
    "sg:province":"Bern",
    "wof:name":"Carrosserie Zimmermann Sa",
    "wof:placetype":"venue"
},
  "geometry": {"coordinates":[7.2517051697,47.1405410767],"type":"Point"}
}