{
  "type": "Feature",
  "properties": {
    "iso:country":"CH",
    "sg:address":"Rue Des Scies",
    "sg:city":"Baulmes",
    "sg:classifiers":[
        {
            "category":"Professional",
            "subcategory":"Employment Agencies",
            "type":"Services"
        }
    ],
    "sg:phone":"+41 24 459 14 00",
    "sg:postcode":"1446",
    "sg:province":"Vaud",
    "sg:tags":[
        "personal",
        "u",
        "stellenvermittlung"
    ],
    "wof:name":"Agence Matter Anne-lise",
    "wof:placetype":"venue"
},
  "geometry": {"coordinates":[6.5196771622,46.7927322388],"type":"Point"}
}