{
  "type": "Feature",
  "properties": {
    "iso:country":"CH",
    "sg:address":"Lohrihof 13",
    "sg:city":"Greppen",
    "sg:orig_category":"Datenverarbeitungsdienste Softwareentwicklung U beratung",
    "sg:phone":"+41 41 390 01 66",
    "sg:postcode":"6404",
    "sg:province":"Luzern",
    "wof:name":"Writeware Ag",
    "wof:placetype":"venue"
},
  "geometry": {"coordinates":[8.42942,47.057178],"type":"Point"}
}