{
  "type": "Feature",
  "properties": {
    "iso:country":"CH",
    "sg:address":"Clochettes Chemin Des 16 1206 Gen\u00e8ve. Postfach",
    "sg:city":"Gen\u00e8ve",
    "sg:orig_category":"Sonstiger Grosshandel",
    "sg:phone":"+41 79 310 02 86",
    "sg:postcode":"1201",
    "sg:province":"Gen\u00e8ve",
    "wof:name":"Challand Ren\u00e9 Commercialisation De G\u00e9n\u00e9rateurs D'ambiance Olfactive",
    "wof:placetype":"venue"
},
  "geometry": {"coordinates":[6.158768177,46.1886672974],"type":"Point"}
}