{
  "type": "Feature",
  "properties": {
    "iso:country":"CH",
    "sg:address":"Blattenstrasse 1 8634 Hombrechtikon. Postfach 171",
    "sg:city":"Hombrechtikon",
    "sg:orig_category":"Architektur U Ingenieurb\u00fcros",
    "sg:phone":"+41 52 343 13 18",
    "sg:postcode":"8634",
    "sg:province":"Z\u00fcrich",
    "wof:name":"Weruko-konstruktionen, Rutschmann Werner",
    "wof:placetype":"venue"
},
  "geometry": {"coordinates":[8.77367,47.252991],"type":"Point"}
}