{
  "type": "Feature",
  "properties": {
    "iso:country":"CH",
    "sg:address":"Alfons-aebystrasse 15",
    "sg:city":"D\u00fcdingen",
    "sg:orig_category":"Organisationen des Gesundheitswesen",
    "sg:phone":"+41 26 493 14 33",
    "sg:postcode":"3186",
    "sg:province":"Fribourg",
    "wof:name":"Spitex-zentrum D\u00fcdingen/ Schmitten",
    "wof:placetype":"venue"
},
  "geometry": {"coordinates":[7.1961407661,46.8495445251],"type":"Point"}
}