{
  "type": "Feature",
  "properties": {
    "iso:country":"CH",
    "sg:address":"Morystrasse 34",
    "sg:city":"Riehen",
    "sg:orig_category":"Zeitungsverlag",
    "sg:phone":"+41 61 601 01 34",
    "sg:postcode":"4125",
    "sg:province":"Basel-Stadt",
    "wof:name":"D\u00fcrr & Co Verlags-kg",
    "wof:placetype":"venue"
},
  "geometry": {"coordinates":[7.6428790092,47.5728759766],"type":"Point"}
}