{
  "type": "Feature",
  "properties": {
    "iso:country":"CH",
    "sg:address":"Kulmerhof 572",
    "sg:city":"Oberkulm",
    "sg:orig_category":"Detailhandel mit Fleisch U Fleischwaren",
    "sg:phone":"+41 62 776 15 65",
    "sg:postcode":"5727",
    "sg:province":"Aargau",
    "wof:name":"Kyburz Roland Metzgerei",
    "wof:placetype":"venue"
},
  "geometry": {"coordinates":[8.1229047775,47.2992668152],"type":"Point"}
}