{
  "type": "Feature",
  "properties": {
    "iso:country":"CH",
    "sg:address":"Eichholzstrasse 1",
    "sg:city":"Sumiswald",
    "sg:orig_category":"Detailhandel mit elektrischen Haushaltsger\u00e4ten Herstellung von konfektionierten Textilwaren ohne Bek",
    "sg:postcode":"3454",
    "sg:province":"Bern",
    "wof:name":"Heinz Kohler",
    "wof:placetype":"venue"
},
  "geometry": {"coordinates":[7.7472262383,47.0276832581],"type":"Point"}
}