{
  "type": "Feature",
  "properties": {
    "iso:country":"CH",
    "sg:address":"Kapplerstrasse 10",
    "sg:city":"Ebnat",
    "sg:orig_category":"Kauf U Verkauf von Immobilien auf eigene Rechnung",
    "sg:postcode":"9642",
    "sg:province":"St. Gallen",
    "wof:name":"Zimmermann-k\u00e4ser Ag",
    "wof:placetype":"venue"
},
  "geometry": {"coordinates":[9.0856952667,47.0004196167],"type":"Point"}
}