{
  "type": "Feature",
  "properties": {
    "iso:country":"CH",
    "sg:address":"Langackerstrasse 22",
    "sg:city":"Cham",
    "sg:orig_category":"Non-Classified Establishments",
    "sg:postcode":"6330",
    "sg:province":"Zug",
    "wof:name":"Martin K\u00f6ppel Treuhand + Unternehmensberatung",
    "wof:placetype":"venue"
},
  "geometry": {"coordinates":[9.6351919174,47.4310073853],"type":"Point"}
}