{
  "type": "Feature",
  "properties": {
    "iso:country":"CH",
    "sg:address":"B\u00e4umlihofstrasse 449 4125 Riehen. Postfach",
    "sg:city":"Riehen",
    "sg:orig_category":"Finanzierungsinstitutionen",
    "sg:postcode":"4125",
    "sg:province":"Basel-Stadt",
    "wof:name":"Mercury Financial Services, Brecelj M. Unabh\u00e4ngige Allfinanzberatung. Vermittlung Von Versicherungs- U. Bankprodukten",
    "wof:placetype":"venue"
},
  "geometry": {"coordinates":[7.6320319176,47.5726928711],"type":"Point"}
}