{
  "type": "Feature",
  "properties": {
    "iso:country":"CH",
    "sg:address":"Sonnengasse 52",
    "sg:city":"Klingnau",
    "sg:orig_category":"Herstellung von Wein Rebbau",
    "sg:phone":"+41 56 463 60 20",
    "sg:postcode":"5313",
    "sg:province":"Aargau",
    "wof:name":"Weinbaugenossenschaft Schinznach-dorf",
    "wof:placetype":"venue"
},
  "geometry": {"coordinates":[8.1429290771,47.4467315674],"type":"Point"}
}