{
  "type": "Feature",
  "properties": {
    "iso:country":"CH",
    "sg:address":"Chemin De La Valerette 1 1860 Aigle Case Postale 489",
    "sg:city":"Aigle",
    "sg:orig_category":"Grosshandel mit B\u00fcromaschinen Grosshandel mit Datenverarbeitungsger\u00e4ten",
    "sg:phone":"+41 24 467 00 91",
    "sg:postcode":"1860",
    "sg:province":"Vaud",
    "wof:name":"Abc Computers Sa",
    "wof:placetype":"venue"
},
  "geometry": {"coordinates":[6.9664587975,46.3104324341],"type":"Point"}
}