{
  "type": "Feature",
  "properties": {
    "iso:country":"CH",
    "sg:address":"Via Enrico Guisan 15",
    "sg:city":"Chiasso",
    "sg:orig_category":"Detailhandel mit Waren verschiedener Art, Hauptrichtung Nahrungsmittel",
    "sg:phone":"+41 91 683 79 04",
    "sg:postcode":"6830",
    "sg:province":"Ticino",
    "wof:name":"Marco Ferrazzini Negozio Commestibili",
    "wof:placetype":"venue"
},
  "geometry": {"coordinates":[9.0221672058,45.8327789307],"type":"Point"}
}