{
  "type": "Feature",
  "properties": {
    "iso:country":"CH",
    "sg:address":"8858",
    "sg:city":"Innerthal",
    "sg:orig_category":"Sportvereine Sch\u00fctzen",
    "sg:phone":"+41 34 402 12 70",
    "sg:postcode":"8858",
    "sg:province":"Schwyz",
    "wof:name":"Feldsch\u00fctzengesellschaft",
    "wof:placetype":"venue"
},
  "geometry": {"coordinates":[8.9160404205,47.1063041687],"type":"Point"}
}