{
  "type": "Feature",
  "properties": {
    "iso:country":"CH",
    "sg:address":"St. Alban-graben 5",
    "sg:city":"Basel",
    "sg:orig_category":"Pensionskassen",
    "sg:phone":"+41 61 271 22 02",
    "sg:postcode":"4051",
    "sg:province":"Basel-Stadt",
    "wof:name":"Stiftung Zur F\u00f6rderung Des Antikenmuseums Basel",
    "wof:placetype":"venue"
},
  "geometry": {"coordinates":[7.5931429863,47.5543708801],"type":"Point"}
}