{
  "type": "Feature",
  "properties": {
    "iso:country":"CH",
    "sg:address":"Sackstrasse 23 8342 Wernetshausen. Postfach",
    "sg:city":"Wernetshausen",
    "sg:orig_category":"Softwareentwicklung U beratung",
    "sg:postcode":"8342",
    "sg:province":"Z\u00fcrich",
    "wof:name":"G\u00e4chter Andr\u00e9 Gmbh",
    "wof:placetype":"venue"
},
  "geometry": {"coordinates":[8.8611536026,47.2996864319],"type":"Point"}
}