{
  "type": "Feature",
  "properties": {
    "iso:country":"CH",
    "sg:address":"St. Gallerstrasse 53",
    "sg:city":"Jona",
    "sg:orig_category":"Detailhandel mit Waren verschiedener Art, Hauptrichtung Nahrungsmittel",
    "sg:postcode":"8645",
    "sg:province":"St. Gallen",
    "wof:name":"Landwirtschaftliche Genossenschaft Jona-rapperswil",
    "wof:placetype":"venue"
},
  "geometry": {"coordinates":[8.8387012482,47.2301101685],"type":"Point"}
}