{
  "type": "Feature",
  "properties": {
    "iso:country":"CH",
    "sg:address":"Hauptstrasse 107",
    "sg:city":"Aesch",
    "sg:classifiers":[
        {
            "category":"Banks & Credit Unions",
            "subcategory":"Bank",
            "type":"Services"
        }
    ],
    "sg:phone":"+41 61 751 15 22",
    "sg:postcode":"4147",
    "sg:province":"Basel-Landschaft",
    "wof:name":"Raiffeisenbank, Aesch-pfeffingen",
    "wof:placetype":"venue"
},
  "geometry": {"coordinates":[7.596589,47.470295],"type":"Point"}
}