{
  "type": "Feature",
  "properties": {
    "iso:country":"CH",
    "sg:address":"Seehaldenstrasse 21b 9404 Rorschacherberg. Postfach",
    "sg:city":"Rorschacherberg",
    "sg:orig_category":"Softwareentwicklung U beratung",
    "sg:phone":"+41 71 855 40 09",
    "sg:postcode":"9404",
    "sg:province":"St. Gallen",
    "wof:name":"Anso Consulting Ag",
    "wof:placetype":"venue"
},
  "geometry": {"coordinates":[9.5202007294,47.4767837524],"type":"Point"}
}