{
  "type": "Feature",
  "properties": {
    "iso:country":"CH",
    "sg:address":"Bielstrasse 22",
    "sg:city":"Lyss",
    "sg:orig_category":"Herstellung von medizinischen U chirurgischen Ger\u00e4ten sowie orthop\u00e4dischen Vorrichtungen Reparatur v",
    "sg:phone":"+41 32 384 64 62",
    "sg:postcode":"3250",
    "sg:province":"Bern",
    "wof:name":"Hermes Gmbh",
    "wof:placetype":"venue"
},
  "geometry": {"coordinates":[7.3049588203,47.0761413574],"type":"Point"}
}