{
  "type": "Feature",
  "properties": {
    "iso:country":"CH",
    "sg:address":"Romanshornstrasse 8",
    "sg:city":"Sulgen",
    "sg:orig_category":"Grosshandel mit Holz U Bauelementen aus Holz Herstellung von sonstigen Holzwaren",
    "sg:phone":"+41 71 642 44 46",
    "sg:postcode":"8583",
    "sg:province":"Thurgau",
    "wof:name":"Holzmarkt Plus Ag",
    "wof:placetype":"venue"
},
  "geometry": {"coordinates":[9.1839208603,47.5451660156],"type":"Point"}
}