{
  "type": "Feature",
  "properties": {
    "iso:country":"CH",
    "sg:address":"St\u00e4nzlergasse 3",
    "sg:city":"Basel",
    "sg:classifiers":[
        {
            "category":"Professional",
            "subcategory":"Employment Agencies",
            "type":"Services"
        }
    ],
    "sg:phone":"+41 81 750 00 50",
    "sg:postcode":"4051",
    "sg:province":"Basel-Stadt",
    "sg:tags":[
        "personal",
        "u",
        "stellenvermittlung"
    ],
    "wof:name":"Transteam Personal Ag Buchs",
    "wof:placetype":"venue"
},
  "geometry": {"coordinates":[9.4740543365,47.1661109924],"type":"Point"}
}