{
  "type": "Feature",
  "properties": {
    "iso:country":"CH",
    "sg:address":"Rehgasse 430",
    "sg:city":"Matzendorf",
    "sg:orig_category":"Non-Classified Establishments",
    "sg:postcode":"4713",
    "sg:province":"Solothurn",
    "wof:name":"Haefeli Montagen Gmbh",
    "wof:placetype":"venue"
},
  "geometry": {"coordinates":[7.6326918602,47.3079109192],"type":"Point"}
}