{
  "type": "Feature",
  "properties": {
    "iso:country":"CH",
    "sg:address":"Bei Der Post",
    "sg:city":"H\u00fctten",
    "sg:orig_category":"Instandhaltung U Reparatur von Automobilen",
    "sg:phone":"+41 17881912",
    "sg:postcode":"8825",
    "sg:province":"Z\u00fcrich",
    "wof:name":"Baer Martin Gmbh",
    "wof:placetype":"venue"
},
  "geometry": {"coordinates":[8.6656112671,47.1753997803],"type":"Point"}
}