{
  "type": "Feature",
  "properties": {
    "iso:country":"CH",
    "sg:address":"Rue Charles-sturm 20",
    "sg:city":"Gen\u00e8ve",
    "sg:orig_category":"Wirtschaftspr\u00fcfung, Steuerberatung U Treuhand",
    "sg:phone":"+41 22 703 51 40",
    "sg:postcode":"1206",
    "sg:province":"Gen\u00e8ve",
    "wof:name":"Equinom",
    "wof:placetype":"venue"
},
  "geometry": {"coordinates":[6.1549720764,46.1982192993],"type":"Point"}
}