{
  "type": "Feature",
  "properties": {
    "iso:country":"CH",
    "sg:address":"Sihlbruggstrasse 105",
    "sg:city":"Baar",
    "sg:orig_category":"Unternehmensberatung Wirtschaftspr\u00fcfung, Steuerberatung U Treuhand",
    "sg:phone":"+41 71 911 69 46",
    "sg:postcode":"6340",
    "sg:province":"Zug",
    "wof:name":"Geiger J\u00fcrg Treuhand Ag",
    "wof:placetype":"venue"
},
  "geometry": {"coordinates":[9.0311660767,47.4650688171],"type":"Point"}
}