{
  "type": "Feature",
  "properties": {
    "iso:country":"CH",
    "sg:address":"6573",
    "sg:city":"Magadino",
    "sg:orig_category":"Wasserversorgung",
    "sg:postcode":"6573",
    "sg:province":"Ticino",
    "wof:name":"Azienda Acqua Potabile Comune Di Magadino",
    "wof:placetype":"venue"
},
  "geometry": {"coordinates":[8.8637800217,46.145778656],"type":"Point"}
}