{
  "type": "Feature",
  "properties": {
    "iso:country":"CH",
    "sg:address":"Rebwiesstrasse 38",
    "sg:city":"Zollikon",
    "sg:orig_category":"Datenverarbeitungsdienste",
    "sg:phone":"+41 31 382 47 47",
    "sg:postcode":"8702",
    "sg:province":"Z\u00fcrich",
    "wof:name":"Pharmatic Ag Offizin- U Spitalapotheken; Erbringung V Dienstleistungen",
    "wof:placetype":"venue"
},
  "geometry": {"coordinates":[7.420286,46.942562],"type":"Point"}
}