{
  "type": "Feature",
  "properties": {
    "iso:country":"CH",
    "sg:address":"Figuiers Avenue Des 17 1007 Lausanne. Postfach",
    "sg:city":"Lausanne",
    "sg:orig_category":"Fachdetailhandel in Verkaufsr\u00e4umen",
    "sg:postcode":"1007",
    "sg:province":"Vaud",
    "wof:name":"Reymond",
    "wof:placetype":"venue"
},
  "geometry": {"coordinates":[6.579390049,46.5390815735],"type":"Point"}
}