{
  "type": "Feature",
  "properties": {
    "iso:country":"CH",
    "sg:address":"Feldmoos",
    "sg:city":"Huttwil",
    "sg:orig_category":"Bauschreinerei Innenausbau",
    "sg:phone":"+41 27 956 19 07",
    "sg:postcode":"4950",
    "sg:province":"Bern",
    "wof:name":"Heinz Gruber Schreinerei & Holzbildhauerei",
    "wof:placetype":"venue"
},
  "geometry": {"coordinates":[7.807089,46.180622],"type":"Point"}
}