{
  "type": "Feature",
  "properties": {
    "iso:country":"CH",
    "sg:address":"Herrenwaldstrasse 2",
    "sg:city":"Menznau",
    "sg:orig_category":"Bauingenieurb\u00fcros allgemein",
    "sg:phone":"+41 81 854 18 52",
    "sg:postcode":"6122",
    "sg:province":"Luzern",
    "wof:name":"Petrin Niggli Ingenieurb\u00fcro",
    "wof:placetype":"venue"
},
  "geometry": {"coordinates":[9.927915,46.5779],"type":"Point"}
}