{
  "type": "Feature",
  "properties": {
    "iso:country":"CH",
    "sg:address":"Gartenstrasse 3",
    "sg:city":"D\u00fcbendorf",
    "sg:orig_category":"Mechanische Werkst\u00e4tten",
    "sg:phone":"+41 18212412",
    "sg:postcode":"8600",
    "sg:province":"Z\u00fcrich",
    "wof:name":"Pietro Tonon Werkzeugsch\u00e4rferei",
    "wof:placetype":"venue"
},
  "geometry": {"coordinates":[8.6079759598,47.3981246948],"type":"Point"}
}