{
  "type": "Feature",
  "properties": {
    "iso:country":"CH",
    "sg:address":"Riggenbachstrasse 30",
    "sg:city":"Olten",
    "sg:orig_category":"Fotografische Ateliers",
    "sg:phone":"+41 62 296 58 10",
    "sg:postcode":"4600",
    "sg:province":"Solothurn",
    "wof:name":"Thomas Ledergerber Fotografisches Atelier",
    "wof:placetype":"venue"
},
  "geometry": {"coordinates":[7.9128007889,47.3459968567],"type":"Point"}
}