{
  "type": "Feature",
  "properties": {
    "iso:country":"CH",
    "sg:address":"Via Maggio 13 6900 Lugano. Postfach",
    "sg:city":"Lugano",
    "sg:orig_category":"Fachdetailhandel in Verkaufsr\u00e4umen",
    "sg:postcode":"6900",
    "sg:province":"Ticino",
    "wof:name":"Jeux Du Monde - Jean-marc Lagger",
    "wof:placetype":"venue"
},
  "geometry": {"coordinates":[6.9731612206,46.2920532227],"type":"Point"}
}