{
  "type": "Feature",
  "properties": {
    "iso:country":"CH",
    "sg:address":"S\u00fcdstrasse 5",
    "sg:city":"Dielsdorf",
    "sg:orig_category":"Wirtschaftspr\u00fcfung, Steuerberatung U Treuhand",
    "sg:postcode":"8157",
    "sg:province":"Z\u00fcrich",
    "wof:name":"Kuhn Andrea, Treuhand & B\u00fcroservice",
    "wof:placetype":"venue"
},
  "geometry": {"coordinates":[8.4538068771,47.4733581543],"type":"Point"}
}