{
  "type": "Feature",
  "properties": {
    "iso:country":"CH",
    "sg:address":"Avenue De Cour 15",
    "sg:city":"Lausanne",
    "sg:classifiers":[
        {
            "category":"Restaurant",
            "type":"Food & Drink"
        }
    ],
    "sg:phone":"+41 21 616 55 11",
    "sg:postcode":"1007",
    "sg:province":"Vaud",
    "wof:name":"Caf\u00e9 La Jonque",
    "wof:placetype":"venue"
},
  "geometry": {"coordinates":[6.6251878738,46.5121536255],"type":"Point"}
}