{
  "type": "Feature",
  "properties": {
    "addr:full":"1123 Aclens Vaud 1123",
    "addr:housenumber":"1123",
    "addr:postcode":"1123",
    "addr:street":"Aclens",
    "iso:country":"CH",
    "sg:address":"1123",
    "sg:city":"Aclens",
    "sg:classifiers":[
        {
            "category":"Education",
            "subcategory":"Library",
            "type":"Public Place"
        }
    ],
    "sg:postcode":"1123",
    "sg:province":"Vaud",
    "sg:tags":[
        "u",
        "bibliotheken",
        "archive"
    ],
    "wof:name":"Biblioth\u00e8que Populaire",
    "wof:placetype":"venue"
},
  "geometry": {"coordinates":[6.51096,46.5686],"type":"Point"}
}