{
  "type": "Feature",
  "properties": {
    "iso:country":"CH",
    "sg:address":"Bahnhofstrasse 11",
    "sg:city":"Wollerau",
    "sg:orig_category":"Herstellung von Seifen, Wasch U Reinigungsmitteln",
    "sg:phone":"+41 17840031",
    "sg:postcode":"8832",
    "sg:province":"Schwyz",
    "wof:name":"Vok Ag",
    "wof:placetype":"venue"
},
  "geometry": {"coordinates":[8.7212953568,47.1956596375],"type":"Point"}
}