{
  "type": "Feature",
  "properties": {
    "addr:full":"Poststr. 38 Schleitheim Schaffhausen 8226",
    "addr:housenumber":"38",
    "addr:postcode":"8226",
    "addr:street":"Poststr.",
    "iso:country":"CH",
    "sg:address":"Poststr. 38",
    "sg:city":"Schleitheim",
    "sg:classifiers":[
        {
            "category":"Banks & Credit Unions",
            "subcategory":"Bank",
            "type":"Services"
        }
    ],
    "sg:phone":"+41 52 680 20 50",
    "sg:postcode":"8226",
    "sg:province":"Schaffhausen",
    "wof:name":"Bs Bank Schaffhausen",
    "wof:placetype":"venue"
},
  "geometry": {"coordinates":[8.482881,47.748959],"type":"Point"}
}