{
  "type": "Feature",
  "properties": {
    "iso:country":"CH",
    "sg:address":"Ausserfeldstrasse 22",
    "sg:city":"Rohr",
    "sg:classifiers":[
        {
            "category":"Banks & Credit Unions",
            "subcategory":"Bank",
            "type":"Services"
        }
    ],
    "sg:phone":"+41 4164221272",
    "sg:postcode":"5032",
    "sg:province":"Aargau",
    "wof:name":"Rentenanstalt Swiss Life",
    "wof:placetype":"venue"
},
  "geometry": {"coordinates":[8.080765,47.400345],"type":"Point"}
}