{
  "type": "Feature",
  "properties": {
    "iso:country":"CH",
    "sg:address":"Langackerstrasse 37",
    "sg:city":"Cham",
    "sg:orig_category":"Detailhandel mit Metallwaren, Anstrichmitteln, Glaswaren, Bau U Heimwerkerbedarf",
    "sg:phone":"+41 41 670 25 25",
    "sg:postcode":"6330",
    "sg:province":"Zug",
    "wof:name":"Temelec Ag",
    "wof:placetype":"venue"
},
  "geometry": {"coordinates":[8.4554510117,47.1979827881],"type":"Point"}
}