{
  "type": "Feature",
  "properties": {
    "iso:country":"CH",
    "sg:address":"Leimgrubenweg 32",
    "sg:city":"Binningen",
    "sg:orig_category":"Mit Sport verbundene T\u00e4tigkeiten Sonstige mit Sport verbundene T\u00e4tigkeiten",
    "sg:phone":"+41 61 421 09 43",
    "sg:postcode":"4102",
    "sg:province":"Basel-Landschaft",
    "wof:name":"Psz Pferdesportzentrum Binningen Ag",
    "wof:placetype":"venue"
},
  "geometry": {"coordinates":[7.5598549843,47.5354537964],"type":"Point"}
}