{
  "type": "Feature",
  "properties": {
    "iso:country":"CH",
    "sg:address":"J. J. Balmer-strasse 7 4053 Basel. Postfach",
    "sg:city":"Basel",
    "sg:orig_category":"Wirtschaftspr\u00fcfung, Steuerberatung U Treuhand",
    "sg:phone":"+41 61 331 40 85",
    "sg:postcode":"4051",
    "sg:province":"Basel-Stadt",
    "wof:name":"B\u00e4chler Treuhand Treuhandb\u00fcro",
    "wof:placetype":"venue"
},
  "geometry": {"coordinates":[7.5951337814,47.5411186218],"type":"Point"}
}