{
  "type": "Feature",
  "properties": {
    "iso:country":"CH",
    "sg:address":"Platanes Chemin Des 4 1700 Fribourg. Postfach",
    "sg:city":"Freiburg",
    "sg:orig_category":"Herstellung von sonstigen Produkten aus nichtmetallischen Mineralien",
    "sg:phone":"+41 26 466 84 36",
    "sg:postcode":"1700",
    "sg:province":"Fribourg",
    "wof:name":"Or Etanch\u00e9iti\u00e9 S\u00e0rl Entreprise D'\u00e9tanch\u00e9it\u00e9 Et D'isolations",
    "wof:placetype":"venue"
},
  "geometry": {"coordinates":[7.1536831856,46.8037452698],"type":"Point"}
}