{
  "type": "Feature",
  "properties": {
    "iso:country":"CH",
    "sg:address":"M\u00fcnchwilen",
    "sg:city":"M\u00fcnchwilen",
    "sg:classifiers":[
        {
            "category":"Banks & Credit Unions",
            "subcategory":"Bank",
            "type":"Services"
        }
    ],
    "sg:phone":"+41 4173262744",
    "sg:postcode":"9542",
    "sg:province":"Thurgau",
    "wof:name":"Raiffeisenbank M\u00fcnchwilen",
    "wof:placetype":"venue"
},
  "geometry": {"coordinates":[8.99612,47.479542],"type":"Point"}
}