{
  "type": "Feature",
  "properties": {
    "iso:country":"CH",
    "sg:address":"Lindenstrasse 20",
    "sg:city":"Winterthur",
    "sg:orig_category":"Fussreflexzonenmassage P\u00e9dicure",
    "sg:phone":"+41 52 222 06 41",
    "sg:postcode":"8400",
    "sg:province":"Z\u00fcrich",
    "wof:name":"Rosemarie H\u00e4ussler Praxis F\u00fcr Fusspflege/-massage",
    "wof:placetype":"venue"
},
  "geometry": {"coordinates":[8.7165470123,47.5054702759],"type":"Point"}
}