{
  "type": "Feature",
  "properties": {
    "iso:country":"CH",
    "sg:address":"Metallstrasse 9",
    "sg:city":"Zug",
    "sg:orig_category":"Zeitungsverlag",
    "sg:postcode":"6300",
    "sg:province":"Zug",
    "wof:name":"Ediko Ag",
    "wof:placetype":"venue"
},
  "geometry": {"coordinates":[8.5183458328,47.1736183167],"type":"Point"}
}