{
  "type": "Feature",
  "properties": {
    "addr:full":"Magdalenenstrasse 49 8050 Z\u00fcrich Zust 50",
    "addr:housenumber":"49;50",
    "addr:postcode":"8050",
    "addr:street":"Magdalenenstrasse;Zust",
    "iso:country":"CH",
    "sg:address":"Magdalenenstrasse 49 8050 Z\u00fcrich",
    "sg:city":"Zust",
    "sg:orig_category":"Allgemeiner Hoch U Tiefbau",
    "sg:postcode":"50",
    "wof:name":"B\u00e4hler Bau Gmbh",
    "wof:placetype":"venue"
},
  "geometry": {"coordinates":[7.80442,47.044598],"type":"Point"}
}