{
  "type": "Feature",
  "properties": {
    "iso:country":"CH",
    "sg:address":"1144",
    "sg:city":"Ballens",
    "sg:orig_category":"Landw. Genossenschaften Alpgenossenschaften Landw. Genossenschaften Viehzucht",
    "sg:phone":"+41 26 496 13 47",
    "sg:postcode":"1144",
    "sg:province":"Vaud",
    "wof:name":"Viehzucht-& Alpgenossenschaft H.rudaz",
    "wof:placetype":"venue"
},
  "geometry": {"coordinates":[7.2488670349,46.8629646301],"type":"Point"}
}