{
  "type": "Feature",
  "properties": {
    "iso:country":"CH",
    "sg:address":"Schneidergasse 24",
    "sg:city":"Basel",
    "sg:orig_category":"Detailhandel mit Ton U Bildtr\u00e4gern Detailhandel mit elektrischen Haushalts-,Radio U Fernsehger\u00e4ten s",
    "sg:phone":"+41 61 261 90 25",
    "sg:postcode":"4051",
    "sg:province":"Basel-Stadt",
    "wof:name":"Musik Wyler, Vormals Lothar L\u00f6ffler",
    "wof:placetype":"venue"
},
  "geometry": {"coordinates":[7.5865697861,47.5578727722],"type":"Point"}
}