{
  "type": "Feature",
  "properties": {
    "iso:country":"CH",
    "sg:address":"Arbonerstrasse 6 9302 Kronb\u00fchl. Postfach 204",
    "sg:city":"Kronb\u00fchl",
    "sg:orig_category":"Fotografisches Gewerbe U fotografische Laboratorien",
    "sg:phone":"+41 71 298 39 68",
    "sg:postcode":"9302",
    "wof:name":"Graficad.ch Werbeagentur",
    "wof:placetype":"venue"
},
  "geometry": {"coordinates":[9.3949985504,47.460395813],"type":"Point"}
}