{
  "type": "Feature",
  "properties": {
    "iso:country":"CH",
    "sg:address":"Chemin De Marcelly 10",
    "sg:city":"Th\u00f4nex",
    "sg:orig_category":"Primarschulen",
    "sg:phone":"+41 22 348 70 69",
    "sg:postcode":"1226",
    "sg:province":"Gen\u00e8ve",
    "wof:name":"Ecole Primaire Marcelly",
    "wof:placetype":"venue"
},
  "geometry": {"coordinates":[6.2038259506,46.1945838928],"type":"Point"}
}