{
  "type": "Feature",
  "properties": {
    "iso:country":"CH",
    "sg:address":"Refentalstrasse 2 5722 Gr\u00e4nichen. Postfach 89",
    "sg:city":"Gr\u00e4nichen",
    "sg:orig_category":"Detailhandel mit elektrischen Haushalts-,Radio U Fernsehger\u00e4ten sowie Musikinstrumenten Instandhaltu",
    "sg:phone":"+41 62 842 20 10",
    "sg:postcode":"5722",
    "sg:province":"Aargau",
    "wof:name":"Auto-elektro Freddy W\u00fcrgler Ag",
    "wof:placetype":"venue"
},
  "geometry": {"coordinates":[8.1137943268,47.3445396423],"type":"Point"}
}