{
  "type": "Feature",
  "properties": {
    "iso:country":"CH",
    "sg:address":"Adlikon",
    "sg:city":"Adlikon",
    "sg:classifiers":[
        {
            "category":"Organizations",
            "subcategory":"Labor Organization",
            "type":"Services"
        }
    ],
    "sg:phone":"+41 18404082",
    "sg:postcode":"8106",
    "sg:province":"Z\u00fcrich",
    "sg:tags":[
        "electromagnetic",
        "shielding",
        "system",
        "emc",
        "compatibility"
    ],
    "wof:name":"Donato Roder Technische Produkte",
    "wof:placetype":"venue"
},
  "geometry": {"coordinates":[8.463809967,47.4514694214],"type":"Point"}
}