{
  "type": "Feature",
  "properties": {
    "iso:country":"CH",
    "sg:address":"Lindenstrasse 4",
    "sg:city":"Glattbrugg",
    "sg:orig_category":"Herstellung von K\u00fcchenm\u00f6beln",
    "sg:phone":"+41 18101313",
    "sg:postcode":"8152",
    "sg:province":"Z\u00fcrich",
    "wof:name":"K\u00fccheneinrichtungen, Frei Eduard",
    "wof:placetype":"venue"
},
  "geometry": {"coordinates":[8.5624465942,47.4308586121],"type":"Point"}
}