{
  "type": "Feature",
  "properties": {
    "iso:country":"CH",
    "sg:address":"Allmendstrasse 140",
    "sg:city":"Z\u00fcrich",
    "sg:classifiers":[
        {
            "category":"Organizations",
            "subcategory":"Professional Association",
            "type":"Services"
        }
    ],
    "sg:phone":"+41 14886888",
    "sg:postcode":"8041",
    "sg:province":"Z\u00fcrich",
    "sg:tags":[
        "customer",
        "software",
        "management",
        "relationship",
        "crm"
    ],
    "wof:name":"Avaloq Evolution Ag",
    "wof:placetype":"venue"
},
  "geometry": {"coordinates":[8.518615,47.338524],"type":"Point"}
}