{
  "type": "Feature",
  "properties": {
    "addr:full":"Untere Sternengasse 2 4500 Solothurn. Postfach 16 Solothurn 4504",
    "addr:housenumber":"2;16",
    "addr:postcode":"4500 solothurn.;4504",
    "addr:street":"Untere Sternengasse;Postfach",
    "iso:country":"CH",
    "sg:address":"Untere Sternengasse 2 4500 Solothurn. Postfach 16",
    "sg:city":"Solothurn",
    "sg:orig_category":"Arbeits\u00e4mter",
    "sg:phone":"+41 32 627 94 11",
    "sg:postcode":"4504",
    "wof:name":"Kantonales Amt F\u00fcr Wirtschaft & Arbeit",
    "wof:placetype":"venue"
},
  "geometry": {"coordinates":[7.54517,47.211605],"type":"Point"}
}