{
  "type": "Feature",
  "properties": {
    "iso:country":"CH",
    "sg:address":"Chilenholzstrasse 33",
    "sg:city":"Sulzbach",
    "sg:orig_category":"Detailhandel mit Getr\u00e4nken",
    "sg:phone":"+41 19400663",
    "sg:postcode":"8614",
    "sg:province":"Z\u00fcrich",
    "wof:name":"Eugen & Elisabeth Gloor Weine & Zubeh\u00f6r",
    "wof:placetype":"venue"
},
  "geometry": {"coordinates":[8.7424230576,47.3284492493],"type":"Point"}
}