{
  "type": "Feature",
  "properties": {
    "iso:country":"CH",
    "sg:address":"Pelzgasse 1",
    "sg:city":"Aarau",
    "sg:orig_category":"Detailhandel mit Blumen U Pflanzen",
    "sg:phone":"+41 62 822 14 54",
    "sg:postcode":"5000",
    "sg:province":"Aargau",
    "wof:name":"Cr\u00e9afleur Blumengesch\u00e4ft",
    "wof:placetype":"venue"
},
  "geometry": {"coordinates":[8.044577,47.392982],"type":"Point"}
}