{
  "type": "Feature",
  "properties": {
    "iso:country":"CH",
    "sg:address":"Bleichistrasse 10",
    "sg:city":"Zug",
    "sg:classifiers":[
        {
            "category":"Landmark",
            "subcategory":"Unesco World Heritage Site",
            "type":"Public Place"
        }
    ],
    "sg:phone":"+41 41 711 07 44",
    "sg:postcode":"6300",
    "sg:province":"Zug",
    "sg:tags":[
        "programming",
        "database"
    ],
    "wof:name":"Orap Software Ag",
    "wof:placetype":"venue"
},
  "geometry": {"coordinates":[8.5195798874,47.1746025085],"type":"Point"}
}