{
  "type": "Feature",
  "properties": {
    "iso:country":"CH",
    "sg:address":"Via Beltramina 7a",
    "sg:city":"Lugano",
    "sg:orig_category":"Arztpraxen",
    "sg:phone":"+41 91 971 11 89",
    "sg:postcode":"6900",
    "sg:province":"Ticino",
    "wof:name":"Prof.dott.med. Eugen Beck Specialista Fmh",
    "wof:placetype":"venue"
},
  "geometry": {"coordinates":[8.958925,46.017002],"type":"Point"}
}