{
  "type": "Feature",
  "properties": {
    "addr:full":"Gartenweg 7 Niederrohrdorf Aargau 5443",
    "addr:housenumber":"7",
    "addr:postcode":"5443",
    "addr:street":"Gartenweg",
    "iso:country":"CH",
    "sg:address":"Gartenweg 7",
    "sg:city":"Niederrohrdorf",
    "sg:orig_category":"Datenverarbeitungsdienste",
    "sg:phone":"+41 56 496 22 09",
    "sg:postcode":"5443",
    "sg:province":"Aargau",
    "wof:name":"Schickli Kommunikation & Werbung",
    "wof:placetype":"venue"
},
  "geometry": {"coordinates":[8.309483,47.423939],"type":"Point"}
}