{
  "type": "Feature",
  "properties": {
    "iso:country":"CH",
    "sg:address":"Route De Florissant 78",
    "sg:city":"Gen\u00e8ve",
    "sg:orig_category":"Detailhandel mit Getr\u00e4nken Grosshandel mit Getr\u00e4nken",
    "sg:phone":"+41 22 347 62 92",
    "sg:postcode":"1206",
    "sg:province":"Gen\u00e8ve",
    "wof:name":"Vinoth\u00e8que Sa",
    "wof:placetype":"venue"
},
  "geometry": {"coordinates":[6.1633238792,46.1923522949],"type":"Point"}
}