{
  "type": "Feature",
  "properties": {
    "iso:country":"CH",
    "sg:address":"Schweizerhofquai 4",
    "sg:city":"Luzern",
    "sg:orig_category":"Detailhandel mit Geschenkartikeln U Souvenirs",
    "sg:phone":"+41 41 410 81 01",
    "sg:postcode":"6004",
    "sg:province":"Luzern",
    "wof:name":"Boutique Comme \u00e7a Gabriel Hanin & Tanja Gauch",
    "wof:placetype":"venue"
},
  "geometry": {"coordinates":[8.3108119965,47.0544242859],"type":"Point"}
}