{
  "type": "Feature",
  "properties": {
    "iso:country":"CH",
    "sg:address":"Plattenstrasse 19",
    "sg:city":"Dottikon",
    "sg:orig_category":"Vermietung U Verpachtung von eigenen Immobilien",
    "sg:postcode":"5605",
    "sg:province":"Aargau",
    "wof:name":"Schw\u00e4nberg Gmbh",
    "wof:placetype":"venue"
},
  "geometry": {"coordinates":[8.2337970734,47.3784599304],"type":"Point"}
}