{
  "type": "Feature",
  "properties": {
    "iso:country":"CH",
    "sg:address":"3186",
    "sg:city":"D\u00fcdingen",
    "sg:orig_category":"RESTAURANTS: TEA-ROOMS",
    "sg:postcode":"3186",
    "sg:province":"Fribourg",
    "wof:name":"Krattinger Markus, Sport-caf\u00e9 D\u00fcdingen",
    "wof:placetype":"venue"
},
  "geometry": {"coordinates":[7.1900749207,46.8504104614],"type":"Point"}
}