{
  "type": "Feature",
  "properties": {
    "iso:country":"CH",
    "sg:address":"Obere Plessurstrasse 36",
    "sg:city":"Chur",
    "sg:orig_category":"Interessenvertretungen",
    "sg:phone":"+41 81 252 44 82",
    "sg:postcode":"7000",
    "sg:province":"Graubunden",
    "wof:name":"Duncan Sir Oliver Stiftung",
    "wof:placetype":"venue"
},
  "geometry": {"coordinates":[9.5269432068,46.8498497009],"type":"Point"}
}