{
  "type": "Feature",
  "properties": {
    "iso:country":"CH",
    "sg:address":"Kesselstrasse 11",
    "sg:city":"Spreitenbach",
    "sg:orig_category":"Glaserei",
    "sg:phone":"+41 56 401 15 25",
    "sg:postcode":"8957",
    "sg:province":"Aargau",
    "wof:name":"Werner Matti Glaserei",
    "wof:placetype":"venue"
},
  "geometry": {"coordinates":[8.3724946976,47.4330024719],"type":"Point"}
}