{
  "type": "Feature",
  "properties": {
    "iso:country":"CH",
    "sg:address":"Bachweg 3 3400 Burgdorf. Postfach",
    "sg:city":"Burgdorf",
    "sg:orig_category":"Herstellung von Armaturen Herstellung von sonstigen Maschinen f\u00fcr unspezifische Verwendung",
    "sg:phone":"+41 79 665 45 75",
    "sg:postcode":"3401",
    "sg:province":"Bern",
    "wof:name":"Rosenbauer Ag Feuerwehrfahrzeuge, -l\u00f6schger\u00e4te, Hydraulische Arbeitsger\u00e4te; Fabrikation, Handel",
    "wof:placetype":"venue"
},
  "geometry": {"coordinates":[8.5080776215,47.4741477966],"type":"Point"}
}