{
  "type": "Feature",
  "properties": {
    "iso:country":"CH",
    "sg:address":"R\u00fctistr. 28",
    "sg:city":"Schlieren",
    "sg:classifiers":[
        {
            "category":"Professional",
            "type":"Services"
        }
    ],
    "sg:phone":"+41 4117322111",
    "sg:postcode":"8952",
    "sg:province":"Z\u00fcrich",
    "sg:tags":[
        "transport",
        "road"
    ],
    "wof:name":"Atlantic Speditions Ag",
    "wof:placetype":"venue"
},
  "geometry": {"coordinates":[8.4534187317,47.4006576538],"type":"Point"}
}