{
  "type": "Feature",
  "properties": {
    "iso:country":"CH",
    "sg:address":"Michelbacherstrasse 6",
    "sg:city":"Basel",
    "sg:orig_category":"Vereine Musik/Blasmusik",
    "sg:phone":"+41 61 301 61 42",
    "sg:postcode":"4055",
    "sg:province":"Basel-Stadt",
    "wof:name":"Alphorn-bl\u00e4ser Basler-dybli C/o Hofstetter",
    "wof:placetype":"venue"
},
  "geometry": {"coordinates":[7.5624427795,47.565826416],"type":"Point"}
}