{
  "type": "Feature",
  "properties": {
    "iso:country":"CH",
    "sg:address":"Eichackerstrasse 24 8600 D\u00fcbendorf. Postfach",
    "sg:city":"D\u00fcbendorf",
    "sg:orig_category":"Gesundheitswesen",
    "sg:postcode":"8600",
    "sg:province":"Z\u00fcrich",
    "wof:name":"Medical Technology & Consulting Gmbh Medizinische Therapien. Medizinische Ger\u00e4te; Vertrieb, Verleih Usw",
    "wof:placetype":"venue"
},
  "geometry": {"coordinates":[8.6292161942,47.3895721436],"type":"Point"}
}