{
  "type": "Feature",
  "properties": {
    "iso:country":"CH",
    "sg:address":"Via San Carlo 22",
    "sg:city":"Breganzona",
    "sg:orig_category":"Vorschulen, Kinderg\u00e4rten",
    "sg:phone":"+41 91 966 17 26",
    "sg:postcode":"6932",
    "sg:province":"Ticino",
    "wof:name":"Scuola Materna Sezione Vi",
    "wof:placetype":"venue"
},
  "geometry": {"coordinates":[8.9302864075,46.0138893127],"type":"Point"}
}