{
  "type": "Feature",
  "properties": {
    "iso:country":"CH",
    "sg:address":"1484",
    "sg:city":"Aumont",
    "sg:orig_category":"Sportvereine Sch\u00fctzen",
    "sg:phone":"+41 61 751 83 81",
    "sg:postcode":"1484",
    "sg:province":"Fribourg",
    "wof:name":"St\u00e9 De Tir Belprahon-grandval",
    "wof:placetype":"venue"
},
  "geometry": {"coordinates":[7.5982289314,47.4793395996],"type":"Point"}
}