{
  "type": "Feature",
  "properties": {
    "iso:country":"CH",
    "sg:address":"Wiesenstrasse 26",
    "sg:city":"Felben",
    "sg:orig_category":"Sportvereine Motorrad",
    "sg:phone":"+41 52 765 18 43",
    "sg:postcode":"8552",
    "sg:province":"Thurgau",
    "wof:name":"Auto-moto-club Andelfingen",
    "wof:placetype":"venue"
},
  "geometry": {"coordinates":[8.9385099411,47.5795173645],"type":"Point"}
}