{
  "type": "Feature",
  "properties": {
    "iso:country":"CH",
    "sg:address":"Chemin Des Places 20",
    "sg:city":"Del\u00e9mont",
    "sg:orig_category":"Organisationen des Gesundheitswesen",
    "sg:phone":"+41 32 422 77 04",
    "sg:postcode":"2800",
    "sg:province":"Jura",
    "wof:name":"St\u00e9 Des Samaritains Del\u00e9mont",
    "wof:placetype":"venue"
},
  "geometry": {"coordinates":[7.3435268402,47.3622970581],"type":"Point"}
}