{
  "type": "Feature",
  "properties": {
    "iso:country":"CH",
    "sg:address":"Bahnhofstrasse 4 7000 Chur. Postfach",
    "sg:city":"Chur",
    "sg:orig_category":"Architektur U Ingenieurb\u00fcros",
    "sg:phone":"+41 81 252 07 50",
    "sg:postcode":"7001",
    "sg:province":"Graubunden",
    "wof:name":"Hegland & Partner Ag",
    "wof:placetype":"venue"
},
  "geometry": {"coordinates":[9.530085,46.85294],"type":"Point"}
}