{
  "type": "Feature",
  "properties": {
    "iso:country":"CH",
    "sg:address":"6644",
    "sg:city":"Orselina",
    "sg:orig_category":"Sportvereine Sch\u00fctzen",
    "sg:postcode":"6644",
    "sg:province":"Ticino",
    "wof:name":"Tiratori Orselinesi",
    "wof:placetype":"venue"
},
  "geometry": {"coordinates":[8.7967700958,46.1801109314],"type":"Point"}
}