{
  "type": "Feature",
  "properties": {
    "iso:country":"CH",
    "sg:address":"Grand-rue 2",
    "sg:city":"Thielle-wavre",
    "sg:orig_category":"Primarschulen",
    "sg:phone":"+41 32 753 23 77",
    "sg:postcode":"2075",
    "sg:province":"Neuch\u00e2tel",
    "wof:name":"Coll\u00e8ge Ecole Primaire",
    "wof:placetype":"venue"
},
  "geometry": {"coordinates":[7.0216789246,47.0259208679],"type":"Point"}
}