{
  "type": "Feature",
  "properties": {
    "iso:country":"CH",
    "sg:address":"Rietstrasse 80 8200 Schaffhausen. Postfach 409",
    "sg:city":"Schaffhausen",
    "sg:orig_category":"Politische Parteien Evangelische Volkspartei",
    "sg:phone":"+41 62 212 46 18",
    "sg:postcode":"8201",
    "sg:province":"Schaffhausen",
    "wof:name":"Evp Des Kantons Solothurn",
    "wof:placetype":"venue"
},
  "geometry": {"coordinates":[7.8792300224,47.3468399048],"type":"Point"}
}