{
  "type": "Feature",
  "properties": {
    "iso:country":"CH",
    "sg:address":"Surtour 1",
    "sg:city":"Samedan",
    "sg:orig_category":"Drogerien Sonstiger Fachdetailhandel mit Nahrungsmitteln, Getr\u00e4nken U Tabak in Verkaufsr\u00e4umen",
    "sg:phone":"+41 81 852 48 95",
    "sg:postcode":"7503",
    "sg:province":"Graubunden",
    "wof:name":"Drogerie-parf\u00fcmerie Beyeler Ag",
    "wof:placetype":"venue"
},
  "geometry": {"coordinates":[9.8701696396,46.5340156555],"type":"Point"}
}