{
  "type": "Feature",
  "properties": {
    "iso:country":"CH",
    "sg:address":"Messeplatz 5 4058 Basel. Postfach",
    "sg:city":"Basel",
    "sg:orig_category":"Nationale Postdienste",
    "sg:phone":"+41 61 681 09 09",
    "sg:postcode":"4021",
    "wof:name":"Die Schweizerische Post Basel 21 Mustermesse",
    "wof:placetype":"venue"
},
  "geometry": {"coordinates":[7.6006650925,47.5639533997],"type":"Point"}
}