{
  "type": "Feature",
  "properties": {
    "iso:country":"CH",
    "sg:address":"Sonnhaldenstrasse 14",
    "sg:city":"Jona",
    "sg:orig_category":"Bauingenieurb\u00fcros Heizung L\u00fcftung Klima Bauingenieurb\u00fcros Sanit\u00e4r",
    "sg:phone":"+41 56 282 40 05",
    "sg:postcode":"8645",
    "sg:province":"St. Gallen",
    "wof:name":"Heco Engineering Gmbh",
    "wof:placetype":"venue"
},
  "geometry": {"coordinates":[8.276855,47.493313],"type":"Point"}
}