{
  "type": "Feature",
  "properties": {
    "iso:country":"CH",
    "sg:address":"Bahnhofplatz 1 3110 M\u00fcnsingen. Postfach",
    "sg:city":"M\u00fcnsingen",
    "sg:orig_category":"Druck ohne Zeitungsdruck",
    "sg:phone":"+41 31 720 51 11",
    "sg:postcode":"3110",
    "sg:province":"Bern",
    "wof:name":"Fischer Management Ag",
    "wof:placetype":"venue"
},
  "geometry": {"coordinates":[7.559729,46.873959],"type":"Point"}
}