{
  "type": "Feature",
  "properties": {
    "iso:country":"CH",
    "sg:address":"Chamerstrasse 56",
    "sg:city":"Zug",
    "sg:orig_category":"Informatikdienste Softwareentwicklung U beratung",
    "sg:phone":"+41 41 712 36 54",
    "sg:postcode":"6300",
    "sg:province":"Zug",
    "wof:name":"Amazing Technologies",
    "wof:placetype":"venue"
},
  "geometry": {"coordinates":[8.5037937164,47.1752433777],"type":"Point"}
}