{
  "type": "Feature",
  "properties": {
    "iso:country":"CH",
    "sg:address":"Altes Schulhaus",
    "sg:city":"Heimenhausen",
    "sg:orig_category":"Vorschulen, Kinderg\u00e4rten",
    "sg:phone":"+41 62 961 41 44",
    "sg:postcode":"3373",
    "sg:province":"Bern",
    "wof:name":"Kindergarten Aare-oenz",
    "wof:placetype":"venue"
},
  "geometry": {"coordinates":[7.6832289696,47.2046699524],"type":"Point"}
}