{
  "type": "Feature",
  "properties": {
    "iso:country":"CH",
    "sg:address":"Maurstrasse 42 8117 F\u00e4llanden. Postfach 570",
    "sg:city":"F\u00e4llanden",
    "sg:orig_category":"Sonstiger Grosshandel",
    "sg:postcode":"8117",
    "sg:province":"Z\u00fcrich",
    "wof:name":"Interlink Trading Ag",
    "wof:placetype":"venue"
},
  "geometry": {"coordinates":[8.6455202103,47.3683204651],"type":"Point"}
}