{
  "type": "Feature",
  "properties": {
    "iso:country":"CH",
    "sg:address":"B\u00fcrerfeld 1",
    "sg:city":"Oberb\u00fcren",
    "sg:orig_category":"Grosshandel mit Eisenwaren sowie Installationsbedarf f\u00fcr Gas, Wasser U Heizung Handel mit Motorr\u00e4der",
    "sg:phone":"+41 21 691 52 11",
    "sg:postcode":"9245",
    "sg:province":"St. Gallen",
    "wof:name":"Solo Kleinmotoren Ag",
    "wof:placetype":"venue"
},
  "geometry": {"coordinates":[6.5583810806,46.5141448975],"type":"Point"}
}