{
  "type": "Feature",
  "properties": {
    "iso:country":"CH",
    "sg:address":"Buechschwendistrasse 4 9038 Rehetobel. Postfach",
    "sg:city":"Rehetobel",
    "sg:orig_category":"Detailhandel mit elektrischen Haushalts-,Radio U Fernsehger\u00e4ten sowie Musikinstrumenten Herstellung ",
    "sg:phone":"+41 71 877 22 30",
    "sg:postcode":"9038",
    "sg:province":"Appenzell Ausserrhoden",
    "wof:name":"Reinhardt N\u00e4htechnologie Gmbh Maschinen, Ger\u00e4te, Zubeh\u00f6r Im Bereich N\u00e4htechnologie; Herstellung, Handel. Patente, Lizenzen; Erwerb, Vermittlung Usw",
    "wof:placetype":"venue"
},
  "geometry": {"coordinates":[9.4817657471,47.4237289429],"type":"Point"}
}