{
  "type": "Feature",
  "properties": {
    "iso:country":"CH",
    "sg:address":"Fraum\u00fcnsterstrasse 13",
    "sg:city":"Z\u00fcrich",
    "sg:orig_category":"Detailhandel mit Radio U Fernsehger\u00e4ten Herstellung von Radio U Fernsehger\u00e4ten sowie phono U videote",
    "sg:phone":"+41 12119560",
    "sg:postcode":"8001",
    "sg:province":"Z\u00fcrich",
    "wof:name":"Adi Wyss Audio Digital Installationen",
    "wof:placetype":"venue"
},
  "geometry": {"coordinates":[8.5407876968,47.368637085],"type":"Point"}
}