{
  "type": "Feature",
  "properties": {
    "iso:country":"CH",
    "sg:address":"Alter Z\u00fcrichweg 35",
    "sg:city":"Niederlenz",
    "sg:orig_category":"Unclassifiable Establishments",
    "sg:postcode":"5702",
    "sg:province":"Aargau",
    "wof:name":"Lukas Suter Cafe / Restaurant Max Und Moritz",
    "wof:placetype":"venue"
},
  "geometry": {"coordinates":[8.2118167877,47.4619102478],"type":"Point"}
}