{
  "type": "Feature",
  "properties": {
    "iso:country":"CH",
    "sg:address":"1838",
    "sg:city":"Rougemont",
    "sg:orig_category":"Sonstiger Fachdetailhandel mit Nahrungsmitteln, Getr\u00e4nken U Tabak in Verkaufsr\u00e4umen Verarbeitung von",
    "sg:phone":"+41 26 925 82 34",
    "sg:postcode":"1838",
    "wof:name":"Beroud Michel",
    "wof:placetype":"venue"
},
  "geometry": {"coordinates":[-78.9260559082,36.2178535461],"type":"Point"}
}