{
  "type": "Feature",
  "properties": {
    "iso:country":"CH",
    "sg:address":"Rietstrasse 6",
    "sg:city":"D\u00e4llikon",
    "sg:orig_category":"Mechanische Werkst\u00e4tten",
    "sg:phone":"+41 71 277 35 38",
    "sg:postcode":"8108",
    "sg:province":"Z\u00fcrich",
    "wof:name":"Rolf Vetsch Reparaturen & Service",
    "wof:placetype":"venue"
},
  "geometry": {"coordinates":[9.337184906,47.402759552],"type":"Point"}
}