{
  "type": "Feature",
  "properties": {
    "iso:country":"CH",
    "sg:address":"Falkenplatz 1 3012 Bern. Postfach",
    "sg:city":"Bern",
    "sg:orig_category":"Unternehmensberatung Wirtschaftspr\u00fcfung, Steuerberatung U Treuhand",
    "sg:phone":"+41 81 252 33 94",
    "sg:postcode":"3001",
    "sg:province":"Bern",
    "wof:name":"Vertigo Sa Caf\u00e9s, Bars, Restaurants Etc",
    "wof:placetype":"venue"
},
  "geometry": {"coordinates":[7.4358210564,46.9504814148],"type":"Point"}
}