{
  "type": "Feature",
  "properties": {
    "iso:country":"CH",
    "sg:address":"Ueberlandstrasse 423 8051 Z\u00fcrich. Postfach 88",
    "sg:city":"Z\u00fcrich",
    "sg:orig_category":"Detailhandel mit M\u00f6beln Detailhandel mit M\u00f6beln U Haushaltsgegenst\u00e4nden",
    "sg:phone":"+41 13252550",
    "sg:postcode":"8051",
    "sg:province":"Z\u00fcrich",
    "wof:name":"M\u00f6bel Schubiger Ag",
    "wof:placetype":"venue"
},
  "geometry": {"coordinates":[8.5927314758,47.4056243896],"type":"Point"}
}