{
  "type": "Feature",
  "properties": {
    "addr:full":"Parkstrasse 9 F\u00fcllinsdorf Basel-Landschaft 4414",
    "addr:housenumber":"9",
    "addr:postcode":"4414",
    "addr:street":"Parkstrasse",
    "iso:country":"CH",
    "sg:address":"Parkstrasse 9",
    "sg:city":"F\u00fcllinsdorf",
    "sg:orig_category":"Aktivit\u00e4ten der Krankenschwestern U Hebammen, Hauspflege Organisationen des Gesundheitswesen",
    "sg:phone":"+41 71 229 40 74",
    "sg:postcode":"4414",
    "sg:province":"Basel-Landschaft",
    "wof:name":"Spitex Beratungsstelle F\u00fcr Kranken-& Gesundheitspflege",
    "wof:placetype":"venue"
},
  "geometry": {"coordinates":[9.379582,47.423721],"type":"Point"}
}