{
  "type": "Feature",
  "properties": {
    "iso:country":"CH",
    "sg:address":"Im Br\u00e4chli 33",
    "sg:city":"Z\u00fcrich",
    "sg:orig_category":"Lichtpause U Reprografiebetriebe Satzherstellung U Reproduktion",
    "sg:phone":"+41 13819626",
    "sg:postcode":"8053",
    "sg:province":"Z\u00fcrich",
    "wof:name":"Tri-lith Ag Fotolithos U. Filme F. Offset- U. Siebbruckverfahren Usw.",
    "wof:placetype":"venue"
},
  "geometry": {"coordinates":[8.5808458328,47.3602218628],"type":"Point"}
}