{
  "type": "Feature",
  "properties": {
    "iso:country":"CH",
    "sg:address":"Rossweid 10",
    "sg:city":"Guntershausen",
    "sg:orig_category":"Sanit\u00e4r U Heizungsinstallation Sanit\u00e4rinstallation",
    "sg:phone":"+41 52 365 17 62",
    "sg:postcode":"8357",
    "sg:province":"Thurgau",
    "wof:name":"Peter Beusch San.installationen & Heizungen",
    "wof:placetype":"venue"
},
  "geometry": {"coordinates":[8.9216251373,47.4731826782],"type":"Point"}
}