{
  "type": "Feature",
  "properties": {
    "iso:country":"CH",
    "sg:address":"W\u00fcrzenbachmatte 33",
    "sg:city":"Luzern",
    "sg:orig_category":"Vorschulen, Kinderg\u00e4rten",
    "sg:postcode":"6006",
    "sg:province":"Luzern",
    "wof:name":"St\u00e4dtischer Kindergarten W\u00fcrzenbachmatte I & Ii",
    "wof:placetype":"venue"
},
  "geometry": {"coordinates":[8.3487453461,47.0566177368],"type":"Point"}
}