{
  "type": "Feature",
  "properties": {
    "iso:country":"CH",
    "sg:address":"Kleinzelgli 2 5623 Boswil. Postfach",
    "sg:city":"Z\u00fcrich",
    "sg:orig_category":"Sonstige mit der Informatik verbundene T\u00e4tigkeiten",
    "sg:phone":"+41 56 442 48 92",
    "sg:postcode":"8002",
    "sg:province":"Z\u00fcrich",
    "wof:name":"Navo Gmbh Informatik Consulting",
    "wof:placetype":"venue"
},
  "geometry": {"coordinates":[8.2068767548,47.4855384827],"type":"Point"}
}