{
  "type": "Feature",
  "properties": {
    "iso:country":"CH",
    "sg:address":"Vordergasse 31",
    "sg:city":"Neunkirch",
    "sg:orig_category":"Malerei",
    "sg:phone":"+41 52 383 20 52",
    "sg:postcode":"8213",
    "sg:province":"Schaffhausen",
    "wof:name":"Rudolf Kosin Malergesch\u00e4ft",
    "wof:placetype":"venue"
},
  "geometry": {"coordinates":[8.8200960159,47.4419784546],"type":"Point"}
}