{
  "type": "Feature",
  "properties": {
    "iso:country":"CH",
    "sg:address":"Rue Fran\u00e7ois-dussaud 19 1200 Genf. Postfach",
    "sg:city":"Gen\u00e8ve",
    "sg:orig_category":"Sonstige mit der Informatik verbundene T\u00e4tigkeiten",
    "sg:postcode":"1207",
    "sg:province":"Gen\u00e8ve",
    "wof:name":"Devillard Services S\u00e0rl",
    "wof:placetype":"venue"
},
  "geometry": {"coordinates":[6.1291031837,46.1957168579],"type":"Point"}
}