{
  "type": "Feature",
  "properties": {
    "iso:country":"CH",
    "sg:address":"Erlenbach 589 9100 Herisau. Postfach 1442",
    "sg:city":"Herisau",
    "sg:orig_category":"Stukkateurgewerbe, Gipserei U Verputzerei",
    "sg:phone":"+41 71 351 39 40",
    "sg:postcode":"9102",
    "sg:province":"Appenzell Ausserrhoden",
    "wof:name":"H. Solenthaler Ag",
    "wof:placetype":"venue"
},
  "geometry": {"coordinates":[9.2775096893,47.3783798218],"type":"Point"}
}