{
  "type": "Feature",
  "properties": {
    "iso:country":"CH",
    "sg:address":"Kirchstrasse 18 9327 T\u00fcbach. Postfach",
    "sg:city":"T\u00fcbach",
    "sg:orig_category":"Verwaltung der Rechtspflege, Gerichte",
    "sg:phone":"+41 71 744 02 10",
    "sg:postcode":"9327",
    "sg:province":"St. Gallen",
    "wof:name":"Grundbuchamt",
    "wof:placetype":"venue"
},
  "geometry": {"coordinates":[9.6351919174,47.4310073853],"type":"Point"}
}