{
  "type": "Feature",
  "properties": {
    "iso:country":"CH",
    "sg:address":"Piazzale Roncaa 2",
    "sg:city":"Mendrisio",
    "sg:orig_category":"Pensionskassen",
    "sg:postcode":"6850",
    "sg:province":"Ticino",
    "wof:name":"Fondazione Di Previdenza Professionale Per Il Personale Della Plastifil Sa",
    "wof:placetype":"venue"
},
  "geometry": {"coordinates":[8.974603653,45.8647193909],"type":"Point"}
}