{
  "type": "Feature",
  "properties": {
    "iso:country":"CH",
    "sg:address":"Thuraustrasse 9",
    "sg:city":"Henau",
    "sg:orig_category":"Bauschreinerei Herstellung von Konstruktionsteilen, Fertigbauteilen U Ausbauelementen aus Holz",
    "sg:phone":"+41 71 951 86 84",
    "sg:postcode":"9247",
    "sg:province":"St. Gallen",
    "wof:name":"Kunz Niklaus",
    "wof:placetype":"venue"
},
  "geometry": {"coordinates":[9.119912,47.454079],"type":"Point"}
}