{
  "type": "Feature",
  "properties": {
    "iso:country":"CH",
    "sg:address":"Clarahofweg 34 4058 Basel. Postfach",
    "sg:city":"Basel",
    "sg:orig_category":"Vermittlungen Wohnungs-Agenturen,",
    "sg:postcode":"4051",
    "sg:province":"Basel-Stadt",
    "wof:name":"Sadiku Kredit Wohnungen U. Kleinkredite; Vermittlung. Videokassetten; Verleih",
    "wof:placetype":"venue"
},
  "geometry": {"coordinates":[7.5977139473,47.5621261597],"type":"Point"}
}