{
  "type": "Feature",
  "properties": {
    "iso:country":"CH",
    "sg:address":"Via Industria 1",
    "sg:city":"Lugano",
    "sg:orig_category":"Grosshandel mit festen Brennstoffen U Mineral\u00f6lerzeugnissen",
    "sg:postcode":"6900",
    "sg:province":"Ticino",
    "wof:name":"Oilgamma S.a",
    "wof:placetype":"venue"
},
  "geometry": {"coordinates":[8.9748706818,46.0397033691],"type":"Point"}
}