{
  "type": "Feature",
  "properties": {
    "iso:country":"CH",
    "sg:address":"Salvatorenstrasse 66",
    "sg:city":"Chur",
    "sg:orig_category":"Werbeagenturen Werbegrafikateliers",
    "sg:phone":"+41 81 250 41 05",
    "sg:postcode":"7000",
    "sg:province":"Graubunden",
    "wof:name":"Clus Gmbh Kommunikationsagentur",
    "wof:placetype":"venue"
},
  "geometry": {"coordinates":[9.5176973343,46.8497848511],"type":"Point"}
}