{
  "type": "Feature",
  "properties": {
    "iso:country":"CH",
    "sg:address":"Obgassweg 3",
    "sg:city":"Buochs",
    "sg:orig_category":"Kosmetikinstitute",
    "sg:phone":"+41 56 622 65 84",
    "sg:postcode":"6374",
    "sg:province":"Nidwalden",
    "wof:name":"Edith Gratwohl Kosmetikinstitut",
    "wof:placetype":"venue"
},
  "geometry": {"coordinates":[8.2976255417,47.373714447],"type":"Point"}
}