{
  "type": "Feature",
  "properties": {
    "iso:country":"CH",
    "sg:address":"Heckenweg 5",
    "sg:city":"Schwarzenburg",
    "sg:orig_category":"Abwasserreinigung",
    "sg:phone":"+41 79 370 93 60",
    "sg:postcode":"3150",
    "sg:province":"Bern",
    "wof:name":"K\u00e4mpf & Haldemann Syphon-clean & Rohrreinigungen",
    "wof:placetype":"venue"
},
  "geometry": {"coordinates":[7.345087,46.821381],"type":"Point"}
}