{
  "type": "Feature",
  "properties": {
    "addr:full":"Via Borgo 36 Ascona Ticino 6612",
    "addr:housenumber":"36",
    "addr:postcode":"6612",
    "addr:street":"Via Borgo",
    "iso:country":"CH",
    "sg:address":"Via Borgo 36",
    "sg:city":"Ascona",
    "sg:orig_category":"Detailhandel mit Bekleidung",
    "sg:postcode":"6612",
    "sg:province":"Ticino",
    "wof:name":"Borgonovo Locarno Sa",
    "wof:placetype":"venue"
},
  "geometry": {"coordinates":[8.76751,46.155815],"type":"Point"}
}