{
  "type": "Feature",
  "properties": {
    "iso:country":"CH",
    "sg:address":"Burgunderweg 38a 2505 Biel/bienne. Postfach",
    "sg:city":"Biel/bienne",
    "sg:orig_category":"Architektur U Ingenieurb\u00fcros",
    "sg:phone":"+41 32 322 80 88",
    "sg:postcode":"2505",
    "sg:province":"Bern",
    "wof:name":"Bolliger Markus A.p.r. Architektur Projekt Realisation",
    "wof:placetype":"venue"
},
  "geometry": {"coordinates":[7.217544,47.130547],"type":"Point"}
}