{
  "type": "Feature",
  "properties": {
    "iso:country":"CH",
    "sg:address":"G\u00fcttinger Strasse 36",
    "sg:city":"Altnau",
    "sg:classifiers":[
        {
            "category":"Restaurant",
            "type":"Food & Drink"
        }
    ],
    "sg:phone":"+41 71 695 19 23",
    "sg:postcode":"8595",
    "sg:province":"Thurgau",
    "wof:name":"Restaurant Walhalla",
    "wof:placetype":"venue"
},
  "geometry": {"coordinates":[9.2614850998,47.6090888977],"type":"Point"}
}