{
  "type": "Feature",
  "properties": {
    "iso:country":"CH",
    "sg:address":"Klosterparkg\u00e4ssli 2",
    "sg:city":"Wettingen",
    "sg:orig_category":"Vermietung U Verpachtung von eigenen Immobilien",
    "sg:postcode":"5430",
    "sg:province":"Aargau",
    "wof:name":"Rempro Ag",
    "wof:placetype":"venue"
},
  "geometry": {"coordinates":[8.3148851395,47.4566955566],"type":"Point"}
}