{
  "type": "Feature",
  "properties": {
    "iso:country":"CH",
    "sg:address":"Baslerstrasse 10",
    "sg:city":"Zurzach",
    "sg:orig_category":"Elektroinstallation",
    "sg:phone":"+41 41 917 20 70",
    "sg:postcode":"5330",
    "sg:province":"Aargau",
    "wof:name":"Schnyder Elektro Ag Aesch",
    "wof:placetype":"venue"
},
  "geometry": {"coordinates":[8.2413196564,47.2566490173],"type":"Point"}
}