{
  "type": "Feature",
  "properties": {
    "iso:country":"CH",
    "sg:address":"Palazzo Darani 2",
    "sg:city":"Faido",
    "sg:orig_category":"Herstellung von Werkzeugmaschinen Mechanische Werkst\u00e4tten",
    "sg:phone":"+41 91 866 00 56",
    "sg:postcode":"6760",
    "sg:province":"Ticino",
    "wof:name":"Untermek Sa",
    "wof:placetype":"venue"
},
  "geometry": {"coordinates":[8.7949810028,46.4794502258],"type":"Point"}
}