{
  "type": "Feature",
  "properties": {
    "iso:country":"CH",
    "sg:address":"Im Noll 24",
    "sg:city":"Pfeffingen",
    "sg:orig_category":"Detailhandel mit Fahrr\u00e4dern Handel mit Motorr\u00e4dern, Teilen U Zubeh\u00f6r Instandhaltung U Reparatur von ",
    "sg:phone":"+41 61 751 47 78",
    "sg:postcode":"4148",
    "sg:province":"Basel-Landschaft",
    "wof:name":"Ttc Twin Techno Center",
    "wof:placetype":"venue"
},
  "geometry": {"coordinates":[7.5897011757,47.4589424133],"type":"Point"}
}