{
  "type": "Feature",
  "properties": {
    "iso:country":"CH",
    "sg:address":"Gempenstrasse 52",
    "sg:city":"Pratteln",
    "sg:orig_category":"Unclassifiable Establishments",
    "sg:postcode":"4133",
    "sg:province":"Basel-Landschaft",
    "wof:name":"Home Modulation Gmbh",
    "wof:placetype":"venue"
},
  "geometry": {"coordinates":[7.6854610443,47.5175971985],"type":"Point"}
}