{
  "type": "Feature",
  "properties": {
    "iso:country":"CH",
    "sg:address":"Gotthardstrasse 42 8800 Thalwil. Postfach 1174",
    "sg:city":"Thalwil",
    "sg:orig_category":"Unclassifiable Establishments",
    "sg:phone":"+41 17201362",
    "sg:postcode":"8800",
    "sg:province":"Z\u00fcrich",
    "wof:name":"Radio-television Staeger Ag",
    "wof:placetype":"venue"
},
  "geometry": {"coordinates":[8.5626325607,47.2970619202],"type":"Point"}
}