{
  "type": "Feature",
  "properties": {
    "iso:country":"CH",
    "sg:address":"Zollstrasse 95",
    "sg:city":"Neuhausen",
    "sg:orig_category":"Unclassifiable Establishments",
    "sg:postcode":"8212",
    "sg:province":"Schaffhausen",
    "wof:name":"A.k.s M\u00f6bel Gmbh",
    "wof:placetype":"venue"
},
  "geometry": {"coordinates":[8.5997533798,47.6750297546],"type":"Point"}
}