{
  "type": "Feature",
  "properties": {
    "iso:country":"CH",
    "sg:address":"Tribunal-f\u00e9d\u00e9ral Av. Du 11",
    "sg:city":"Lausanne",
    "sg:orig_category":"Wirtschaftspr\u00fcfung, Steuerberatung U Treuhand",
    "sg:postcode":"1005",
    "sg:province":"Vaud",
    "wof:name":"Criphil S\u00e0rl",
    "wof:placetype":"venue"
},
  "geometry": {"coordinates":[6.6396799088,46.5203971863],"type":"Point"}
}