{
  "type": "Feature",
  "properties": {
    "iso:country":"CH",
    "sg:address":"Wuhrmattstrasse 4 4800 Zofingen. Postfach",
    "sg:city":"Zofingen",
    "sg:orig_category":"Stukkateurgewerbe, Gipserei U Verputzerei",
    "sg:phone":"+41 62 771 88 00",
    "sg:postcode":"4800",
    "sg:province":"Aargau",
    "wof:name":"Gipsergesch\u00e4ft B\u00fchler Franz",
    "wof:placetype":"venue"
},
  "geometry": {"coordinates":[8.1736316681,47.255027771],"type":"Point"}
}