{
  "type": "Feature",
  "properties": {
    "iso:country":"CH",
    "sg:address":"Schulhausplatz",
    "sg:city":"Meilen",
    "sg:classifiers":[
        {
            "category":"Government",
            "subcategory":"Post Office",
            "type":"Public Place"
        }
    ],
    "sg:phone":"+41 19233388",
    "sg:postcode":"8706",
    "sg:province":"Z\u00fcrich",
    "sg:tags":[
        "caf\u00e9s",
        "tea-rooms"
    ],
    "wof:name":"Caf\u00e9 Centro Ricreativo",
    "wof:placetype":"venue"
},
  "geometry": {"coordinates":[8.642829895,47.2681541443],"type":"Point"}
}