{
  "type": "Feature",
  "properties": {
    "addr:full":"Loretostrasse 31 4500 Solothurn. Postfach Solothurn Solothurn 4503",
    "addr:housenumber":"31",
    "addr:postcode":"4500 solothurn. postfach;4503",
    "addr:street":"Loretostrasse",
    "iso:country":"CH",
    "sg:address":"Loretostrasse 31 4500 Solothurn. Postfach",
    "sg:city":"Solothurn",
    "sg:orig_category":"Architektur U Ingenieurb\u00fcros Architekturb\u00fcros",
    "sg:phone":"+41 52 741 31 63",
    "sg:postcode":"4503",
    "sg:province":"Solothurn",
    "wof:name":"Frei Andreas Bauplanung-bauf\u00fchrung Architekturdienstleistungen",
    "wof:placetype":"venue"
},
  "geometry": {"coordinates":[8.852502,47.65789],"type":"Point"}
}