{
  "type": "Feature",
  "properties": {
    "iso:country":"CH",
    "sg:address":"Route D'echallens 2",
    "sg:city":"Romanel-s-lausanne",
    "sg:orig_category":"Wirtschaftspr\u00fcfung, Steuerberatung U Treuhand",
    "sg:phone":"+41 21 648 60 44",
    "sg:postcode":"1032",
    "sg:province":"Vaud",
    "wof:name":"Fiduciaire Staub Maurice",
    "wof:placetype":"venue"
},
  "geometry": {"coordinates":[6.6049871445,46.5690307617],"type":"Point"}
}