{
  "type": "Feature",
  "properties": {
    "iso:country":"CH",
    "sg:address":"Lufingerstrasse 9",
    "sg:city":"Winkel",
    "sg:orig_category":"Bauschreinerei",
    "sg:phone":"+41 33 336 48 48",
    "sg:postcode":"8185",
    "sg:province":"Z\u00fcrich",
    "wof:name":"Fritz Linder Schreinerei",
    "wof:placetype":"venue"
},
  "geometry": {"coordinates":[7.620159,46.732552],"type":"Point"}
}