{
  "type": "Feature",
  "properties": {
    "iso:country":"CH",
    "sg:address":"Abb\u00e9-bovet Rue De L' 5",
    "sg:city":"Fribourg",
    "sg:orig_category":"Detailhandel mit Fleisch U Fleischwaren",
    "sg:phone":"+41 22 796 43 40",
    "sg:postcode":"1700",
    "sg:province":"Fribourg",
    "wof:name":"Boucherie Chevaline Caprioni Domenico",
    "wof:placetype":"venue"
},
  "geometry": {"coordinates":[6.0956997871,46.203666687],"type":"Point"}
}