{
  "type": "Feature",
  "properties": {
    "iso:country":"CH",
    "sg:address":"Tulpenweg 6 6005 Luzern. Postfach",
    "sg:city":"Luzern",
    "sg:orig_category":"Interessenvertretungen",
    "sg:postcode":"6003",
    "sg:province":"Luzern",
    "wof:name":"Z\u00fclly-stiftung Hermine Unterst\u00fctzung Bed\u00fcrftiger Familien Usw",
    "wof:placetype":"venue"
},
  "geometry": {"coordinates":[8.2982320786,47.0433692932],"type":"Point"}
}