{
  "type": "Feature",
  "properties": {
    "iso:country":"CH",
    "sg:address":"Sandackerweg 1",
    "sg:city":"St\u00fcsslingen",
    "sg:orig_category":"Detailhandel mit Radio U Fernsehger\u00e4ten Herstellung von Radio U Fernsehger\u00e4ten sowie phono U videote",
    "sg:phone":"+41 79 415 01 20",
    "sg:postcode":"4655",
    "sg:province":"Solothurn",
    "wof:name":"Electronic-service Eugster M.",
    "wof:placetype":"venue"
},
  "geometry": {"coordinates":[7.9664258957,47.3882904053],"type":"Point"}
}