{
  "type": "Feature",
  "properties": {
    "iso:country":"CH",
    "sg:address":"Sporthaus Ems",
    "sg:city":"Schiers",
    "sg:orig_category":"Schwimmb\u00e4der",
    "sg:phone":"+41 81 328 15 49",
    "sg:postcode":"7220",
    "sg:province":"Graubunden",
    "wof:name":"Schwimmbad Herrn David Hartmann",
    "wof:placetype":"venue"
},
  "geometry": {"coordinates":[9.6870222092,46.9697189331],"type":"Point"}
}