{
  "type": "Feature",
  "properties": {
    "iso:country":"CH",
    "sg:address":"Crastuoglia",
    "sg:city":"Scuol",
    "sg:orig_category":"Zahnarztpraxen",
    "sg:phone":"+41 81 864 13 28",
    "sg:postcode":"7550",
    "sg:province":"Graubunden",
    "wof:name":"Dr. Med. Dent. Giacomo Dolfi Zahnarzt",
    "wof:placetype":"venue"
},
  "geometry": {"coordinates":[10.2985124588,46.7990264893],"type":"Point"}
}