{
  "type": "Feature",
  "properties": {
    "addr:full":"Seetalstrasse 28 6020 Emmenbr\u00fccke. Postfach Emmenbr\u00fccke Luzern 6020",
    "addr:housenumber":"28",
    "addr:postcode":"6020;6020",
    "addr:street":"Seetalstrasse;Postfach Emmenbruecke",
    "iso:country":"CH",
    "sg:address":"Seetalstrasse 28 6020 Emmenbr\u00fccke. Postfach",
    "sg:city":"Emmenbr\u00fccke",
    "sg:orig_category":"Betrieb von Taxis",
    "sg:postcode":"6020",
    "sg:province":"Luzern",
    "wof:name":"Schmid & Cie Taxis R\u00e9unis",
    "wof:placetype":"venue"
},
  "geometry": {"coordinates":[6.745269,47.052227],"type":"Point"}
}