{
  "type": "Feature",
  "properties": {
    "iso:country":"CH",
    "sg:address":"Fauggersweg 14",
    "sg:city":"Ins",
    "sg:orig_category":"Reinigungsgewerbe",
    "sg:phone":"+41 17843852",
    "sg:postcode":"3232",
    "sg:province":"Bern",
    "wof:name":"H\u00f6fner-geb\u00e4udereinigung Kurt Vigorelli",
    "wof:placetype":"venue"
},
  "geometry": {"coordinates":[8.7341480255,47.1973953247],"type":"Point"}
}