{
  "type": "Feature",
  "properties": {
    "iso:country":"CH",
    "sg:address":"Moosstrasse 7 2542 Pieterlen. Postfach 324",
    "sg:city":"Pieterlen",
    "sg:orig_category":"Grosshandel mit H\u00e4uten, Fellen U Leder Grosshandel mit Textilien",
    "sg:phone":"+41 32 377 38 77",
    "sg:postcode":"2542",
    "sg:province":"Bern",
    "wof:name":"Hans Zbinden Ag",
    "wof:placetype":"venue"
},
  "geometry": {"coordinates":[7.3178300858,47.1698036194],"type":"Point"}
}