{
  "type": "Feature",
  "properties": {
    "iso:country":"CH",
    "sg:address":"Bettlachstrasse 17",
    "sg:city":"Grenchen",
    "sg:orig_category":"Detailhandel mit Geschenkartikeln U Souvenirs",
    "sg:phone":"+41 32 652 41 44",
    "sg:postcode":"2540",
    "sg:province":"Solothurn",
    "wof:name":"Boutique Fabi",
    "wof:placetype":"venue"
},
  "geometry": {"coordinates":[7.397371769,47.1931266785],"type":"Point"}
}