{
  "type": "Feature",
  "properties": {
    "iso:country":"CH",
    "sg:address":"Langgasse 3",
    "sg:city":"Visp",
    "sg:orig_category":"Grosshandel mit Getreide, Saatgut U Futtermitteln Handelsvermittlung U Grosshandel",
    "sg:phone":"+41 27 946 20 49",
    "sg:postcode":"3930",
    "sg:province":"Valais",
    "wof:name":"Lareida, Landesprodukte En Gros, Depot Provimi",
    "wof:placetype":"venue"
},
  "geometry": {"coordinates":[7.8809990883,46.2909011841],"type":"Point"}
}