{
  "type": "Feature",
  "properties": {
    "iso:country":"CH",
    "sg:address":"Schaffhauserstrasse 75",
    "sg:city":"Z\u00fcrich",
    "sg:orig_category":"Detailhandel mit Waren verschiedener Art, Hauptrichtung Nahrungsmittel",
    "sg:phone":"+41 13611540",
    "sg:postcode":"8057",
    "sg:province":"Z\u00fcrich",
    "wof:name":"Migros-markt Schaffhauserplatz",
    "wof:placetype":"venue"
},
  "geometry": {"coordinates":[8.5385951996,47.3925247192],"type":"Point"}
}