{
  "type": "Feature",
  "properties": {
    "iso:country":"CH",
    "sg:address":"Sternenstrasse 11",
    "sg:city":"Herzogenbuchsee",
    "sg:orig_category":"G\u00fcterbef\u00f6rderung im Strassenverkehr",
    "sg:phone":"+41 62 961 20 13",
    "sg:postcode":"3360",
    "sg:province":"Bern",
    "wof:name":"Jau Hans Ulrich",
    "wof:placetype":"venue"
},
  "geometry": {"coordinates":[7.7061328888,47.190788269],"type":"Point"}
}