{
  "type": "Feature",
  "properties": {
    "addr:full":"Dorfstrasse 16 Kaltbrunn St. Gallen 8722",
    "addr:housenumber":"16",
    "addr:postcode":"8722",
    "addr:street":"Dorfstrasse",
    "iso:country":"CH",
    "sg:address":"Dorfstrasse 16",
    "sg:city":"Kaltbrunn",
    "sg:orig_category":"Detailhandel mit Bekleidung Detailhandel mit Damenbekleidung",
    "sg:phone":"+41 91 683 69 86",
    "sg:postcode":"8722",
    "sg:province":"St. Gallen",
    "wof:name":"Griffe 133 Sa",
    "wof:placetype":"venue"
},
  "geometry": {"coordinates":[8.995126,45.858536],"type":"Point"}
}