{
  "type": "Feature",
  "properties": {
    "iso:country":"CH",
    "sg:address":"Quadras",
    "sg:city":"Sumvitg",
    "sg:orig_category":"Instandhaltung U Reparatur von Automobilen",
    "sg:postcode":"7175",
    "sg:province":"Graubunden",
    "wof:name":"Basuki Ag",
    "wof:placetype":"venue"
},
  "geometry": {"coordinates":[9.4729719162,47.1673698425],"type":"Point"}
}