{
  "type": "Feature",
  "properties": {
    "iso:country":"CH",
    "sg:address":"Langsamstig 1",
    "sg:city":"Lenzburg",
    "sg:orig_category":"Wirtschaftspr\u00fcfung, Steuerberatung U Treuhand",
    "sg:phone":"+41 61 726 66 88",
    "sg:postcode":"5600",
    "sg:province":"Aargau",
    "wof:name":"Bf Treuhand Ag",
    "wof:placetype":"venue"
},
  "geometry": {"coordinates":[7.5253500938,47.5052108765],"type":"Point"}
}