{
  "type": "Feature",
  "properties": {
    "addr:full":"Grand-rue 19 Payerne Vaud 1530",
    "addr:housenumber":"19",
    "addr:postcode":"1530",
    "addr:street":"Grand-Rue",
    "iso:country":"CH",
    "sg:address":"Grand-rue 19",
    "sg:city":"Payerne",
    "sg:classifiers":[
        {
            "category":"Banks & Credit Unions",
            "subcategory":"Bank",
            "type":"Services"
        }
    ],
    "sg:phone":"+41 26 661 75 11",
    "sg:postcode":"1530",
    "sg:province":"Vaud",
    "wof:name":"Swiss Bank Corp.",
    "wof:placetype":"venue"
},
  "geometry": {"coordinates":[6.938278,46.821274],"type":"Point"}
}