{
  "type": "Feature",
  "properties": {
    "iso:country":"CH",
    "sg:address":"Seestrasse 111",
    "sg:city":"Steckborn",
    "sg:orig_category":"Detailhandel mit Beleuchtungs U Haushaltsgegenst\u00e4nden",
    "sg:phone":"+41 52 761 11 46",
    "sg:postcode":"8266",
    "sg:province":"Thurgau",
    "wof:name":"Fredy Rudolf Eisenwaren & Haushaltartikel",
    "wof:placetype":"venue"
},
  "geometry": {"coordinates":[8.981778,47.667473],"type":"Point"}
}