{
  "type": "Feature",
  "properties": {
    "iso:country":"CH",
    "sg:address":"Reichenbachstrasse 22",
    "sg:city":"Zollikofen",
    "sg:orig_category":"Sportvereine Ballsport Volleyball",
    "sg:phone":"+41 31 911 40 53",
    "sg:postcode":"3052",
    "sg:province":"Bern",
    "wof:name":"Volleyball-club Bern",
    "wof:placetype":"venue"
},
  "geometry": {"coordinates":[7.4540557861,46.9914131165],"type":"Point"}
}