{
  "type": "Feature",
  "properties": {
    "iso:country":"CH",
    "sg:address":"Baslerstrasse 191",
    "sg:city":"Allschwil",
    "sg:orig_category":"Detailhandel mit Waren verschiedener Art, Hauptrichtung Nahrungsmittel",
    "sg:phone":"+41 61 481 44 61",
    "sg:postcode":"4123",
    "sg:province":"Basel-Landschaft",
    "wof:name":"Coop Center Betten",
    "wof:placetype":"venue"
},
  "geometry": {"coordinates":[7.5506768227,47.5531311035],"type":"Point"}
}