{
  "type": "Feature",
  "properties": {
    "iso:country":"CH",
    "sg:address":"Via Cantonale 11c",
    "sg:city":"Stabio",
    "sg:orig_category":"Handelsvermittlung U Grosshandel Verarbeitung von Tee U Kaffee",
    "sg:phone":"+41 91 640 70 15",
    "sg:postcode":"6855",
    "sg:province":"Ticino",
    "wof:name":"Moretto Sa Torrefazione Di Caff\u00e8",
    "wof:placetype":"venue"
},
  "geometry": {"coordinates":[8.9425983429,45.8493843079],"type":"Point"}
}