{
  "type": "Feature",
  "properties": {
    "iso:country":"CH",
    "sg:address":"Stampfenbachstrasse 48",
    "sg:city":"Z\u00fcrich",
    "sg:classifiers":[
        {
            "category":"Restaurant",
            "type":"Food & Drink"
        }
    ],
    "sg:phone":"+41 13614326",
    "sg:postcode":"8006",
    "sg:province":"Z\u00fcrich",
    "wof:name":"Restaurant Silberkugel",
    "wof:placetype":"venue"
},
  "geometry": {"coordinates":[8.5428533554,47.3806533813],"type":"Point"}
}