{
  "type": "Feature",
  "properties": {
    "iso:country":"CH",
    "sg:address":"B\u00fcrgenstockstrasse 12 6362 Stansstad. Postfach 414",
    "sg:city":"Stansstad",
    "sg:orig_category":"Instandhaltung U Reparatur von Automobilen",
    "sg:phone":"+41 41 610 46 52",
    "sg:postcode":"6362",
    "sg:province":"Nidwalden",
    "wof:name":"Garage Holecek",
    "wof:placetype":"venue"
},
  "geometry": {"coordinates":[8.3418226242,46.9778594971],"type":"Point"}
}