{
  "type": "Feature",
  "properties": {
    "iso:country":"CH",
    "sg:address":"Steinackerstrasse 8",
    "sg:city":"Leuzigen",
    "sg:orig_category":"Detailhandel mit Metallwaren, Anstrichmitteln, Glaswaren, Bau U Heimwerkerbedarf Grosshandel mit lan",
    "sg:phone":"+41 32 679 55 55",
    "sg:postcode":"3297",
    "sg:province":"Bern",
    "wof:name":"Wattinger, Inhaber M. Neuenschwander",
    "wof:placetype":"venue"
},
  "geometry": {"coordinates":[7.4452939034,47.1763687134],"type":"Point"}
}