{
  "type": "Feature",
  "properties": {
    "iso:country":"CH",
    "sg:address":"S\u00e4gemattstrasse 82/41",
    "sg:city":"K\u00f6niz",
    "sg:orig_category":"Interessenvertretungen",
    "sg:postcode":"3098",
    "sg:province":"Bern",
    "wof:name":"Carnot Pater Maurus Stiftung",
    "wof:placetype":"venue"
},
  "geometry": {"coordinates":[10.3710098267,46.9443283081],"type":"Point"}
}