{
  "type": "Feature",
  "properties": {
    "iso:country":"CH",
    "sg:address":"Langackerstrasse 127",
    "sg:city":"Herrliberg",
    "sg:orig_category":"Non-Classified Establishments",
    "sg:postcode":"8704",
    "sg:province":"Z\u00fcrich",
    "wof:name":"Fug Ag",
    "wof:placetype":"venue"
},
  "geometry": {"coordinates":[8.6154193878,47.2904014587],"type":"Point"}
}