{
  "type": "Feature",
  "properties": {
    "iso:country":"CH",
    "sg:address":"Fr\u00fceblistrasse 4",
    "sg:city":"Dielsdorf",
    "sg:orig_category":"Schwimmb\u00e4der",
    "sg:phone":"+41 79 276 76 81",
    "sg:postcode":"8157",
    "sg:province":"Z\u00fcrich",
    "wof:name":"Oberstufenschulhaus Betriebsleitung Hallenbad",
    "wof:placetype":"venue"
},
  "geometry": {"coordinates":[8.4549922943,47.4807891846],"type":"Point"}
}