{
  "type": "Feature",
  "properties": {
    "iso:country":"CH",
    "sg:address":"Breitenstrasse 8",
    "sg:city":"Uznach",
    "sg:orig_category":"Interessenvertretungen",
    "sg:phone":"+41 55 280 29 71",
    "sg:postcode":"8730",
    "sg:province":"St. Gallen",
    "wof:name":"Rosa Mystica",
    "wof:placetype":"venue"
},
  "geometry": {"coordinates":[8.9936437607,47.2223777771],"type":"Point"}
}