{
  "type": "Feature",
  "properties": {
    "iso:country":"CH",
    "sg:address":"Rossens",
    "sg:city":"Rossens",
    "sg:classifiers":[
        {
            "category":"Banks & Credit Unions",
            "subcategory":"Bank",
            "type":"Services"
        }
    ],
    "sg:phone":"+41 26 411 23 63",
    "sg:postcode":"1728",
    "sg:province":"Fribourg",
    "wof:name":"Raiffeisen",
    "wof:placetype":"venue"
},
  "geometry": {"coordinates":[7.09953,46.72419],"type":"Point"}
}