{
  "type": "Feature",
  "properties": {
    "iso:country":"CH",
    "sg:address":"Fluxstrasse 290",
    "sg:city":"Eschen",
    "sg:orig_category":"Politische Vereinigungen",
    "sg:phone":"+41 75 232 08 08",
    "sg:postcode":"9492",
    "wof:name":"Fortschrittliche B\u00fcrgerpartei",
    "wof:placetype":"venue"
},
  "geometry": {"coordinates":[9.520190239,47.2049484253],"type":"Point"}
}