{
  "type": "Feature",
  "properties": {
    "iso:country":"CH",
    "sg:address":"Circusstr. 22",
    "sg:city":"Oeschgen",
    "sg:classifiers":[
        {
            "category":"Sports & Exercise",
            "subcategory":"Sports Center",
            "type":"Entertainment"
        }
    ],
    "sg:phone":"+41 62 871 22 59",
    "sg:postcode":"5072",
    "sg:province":"Aargau",
    "sg:tags":[
        "game"
    ],
    "wof:name":"Circus Nock Ag",
    "wof:placetype":"venue"
},
  "geometry": {"coordinates":[8.0103216171,47.5180587769],"type":"Point"}
}