{
  "type": "Feature",
  "properties": {
    "iso:country":"CH",
    "sg:address":"Bahnhofstrasse 28",
    "sg:city":"Schwyz",
    "sg:orig_category":"Unclassifiable Establishments",
    "sg:postcode":"6430",
    "sg:province":"Schwyz",
    "wof:name":"Dehoco Ag",
    "wof:placetype":"venue"
},
  "geometry": {"coordinates":[8.6468133926,47.0222358704],"type":"Point"}
}