{
  "type": "Feature",
  "properties": {
    "addr:full":"Salvemattweg 5c Baar Zug 6340",
    "addr:housenumber":"5c",
    "addr:postcode":"6340",
    "addr:street":"Salvemattweg;Zug",
    "iso:country":"CH",
    "sg:address":"Salvemattweg 5c",
    "sg:city":"Baar",
    "sg:orig_category":"Allgemeiner Hoch U Tiefbau",
    "sg:postcode":"6340",
    "sg:province":"Zug",
    "wof:name":"Sch\u00e4tti Karl Ag",
    "wof:placetype":"venue"
},
  "geometry": {"coordinates":[8.523429,47.197754],"type":"Point"}
}