{
  "type": "Feature",
  "properties": {
    "iso:country":"CH",
    "sg:address":"Auhafenstrasse 2",
    "sg:city":"Muttenz",
    "sg:orig_category":"Tankstellen",
    "sg:phone":"+41 61 377 94 75",
    "sg:postcode":"4132",
    "sg:province":"Basel-Landschaft",
    "wof:name":"Bp (switzerland)",
    "wof:placetype":"venue"
},
  "geometry": {"coordinates":[7.6452732086,47.5230712891],"type":"Point"}
}