{
  "type": "Feature",
  "properties": {
    "iso:country":"CH",
    "sg:address":"6930",
    "sg:city":"Bedano",
    "sg:orig_category":"Elektrizit\u00e4tsversorgung Sanit\u00e4r, Heizungs U L\u00fcftungsinstallation",
    "sg:phone":"+41 91 857 22 32",
    "sg:postcode":"6930",
    "sg:province":"Ticino",
    "wof:name":"Servodomo Sa",
    "wof:placetype":"venue"
},
  "geometry": {"coordinates":[8.917090416,46.0536994934],"type":"Point"}
}