{
  "type": "Feature",
  "properties": {
    "iso:country":"CH",
    "sg:address":"Grand Rue 40",
    "sg:city":"Montreux",
    "sg:orig_category":"Arztpraxen",
    "sg:phone":"+41 21 963 77 63",
    "sg:postcode":"1820",
    "sg:province":"Vaud",
    "wof:name":"Dr M\u00e9d. Jean-marie Monney M\u00e9decin Sp\u00e9cialiste Fmh",
    "wof:placetype":"venue"
},
  "geometry": {"coordinates":[6.910311,46.433773],"type":"Point"}
}