{
  "type": "Feature",
  "properties": {
    "iso:country":"CH",
    "sg:address":"Alte Bernstrasse 4",
    "sg:city":"G\u00fcmmenen",
    "sg:orig_category":"Gartenbau",
    "sg:phone":"+41 31 751 00 18",
    "sg:postcode":"3205",
    "sg:province":"Bern",
    "wof:name":"Samuel Remund Hydrog\u00e4rtnerei",
    "wof:placetype":"venue"
},
  "geometry": {"coordinates":[7.2457618713,46.9452018738],"type":"Point"}
}