{
  "type": "Feature",
  "properties": {
    "iso:country":"CH",
    "sg:address":"Route De B\u00e2le 13",
    "sg:city":"Soyhi\u00e8res",
    "sg:orig_category":"Tabakverarbeitung",
    "sg:phone":"+41 32 423 50 08",
    "sg:postcode":"2805",
    "sg:province":"Jura",
    "wof:name":"Jt International Ag Dagmersellen",
    "wof:placetype":"venue"
},
  "geometry": {"coordinates":[7.3711872101,47.3902893066],"type":"Point"}
}