{
  "type": "Feature",
  "properties": {
    "iso:country":"CH",
    "sg:address":"Birrfeldstrasse 8",
    "sg:city":"Birrhard",
    "sg:orig_category":"Instandhaltung U Reparatur von Automobilen",
    "sg:phone":"+41 27 776 23 23",
    "sg:postcode":"5244",
    "sg:province":"Aargau",
    "wof:name":"Garage St-christophe Bagnes Sa.",
    "wof:placetype":"venue"
},
  "geometry": {"coordinates":[7.2124481201,46.0804595947],"type":"Point"}
}