{
  "type": "Feature",
  "properties": {
    "iso:country":"CH",
    "sg:address":"Rue De Corbi\u00e8res 37 1630 Bulle. Postfach",
    "sg:city":"Bulle",
    "sg:orig_category":"Herstellung von Metallkonstruktionen",
    "sg:postcode":"1630",
    "sg:province":"Fribourg",
    "wof:name":"Natma S\u00e0rl",
    "wof:placetype":"venue"
},
  "geometry": {"coordinates":[7.0621809959,46.6240730286],"type":"Point"}
}