{
  "type": "Feature",
  "properties": {
    "iso:country":"CH",
    "sg:address":"8532",
    "sg:city":"Warth",
    "sg:orig_category":"Gartenbau",
    "sg:phone":"+41 55 246 47 68",
    "sg:postcode":"8532",
    "sg:province":"Thurgau",
    "wof:name":"Gartenbau Thoma Gmbh",
    "wof:placetype":"venue"
},
  "geometry": {"coordinates":[8.932062149,47.2614402771],"type":"Point"}
}