{
  "type": "Feature",
  "properties": {
    "iso:country":"CH",
    "sg:address":"K\u00f6chlistrasse 28 8004 Z\u00fcrich. Postfach 2118",
    "sg:city":"Z\u00fcrich",
    "sg:orig_category":"Sonstiger Grosshandel Verlag von bespielten Tontr\u00e4gern",
    "sg:phone":"+41 12428040",
    "sg:postcode":"8026",
    "sg:province":"Z\u00fcrich",
    "wof:name":"Ramiy Records Gmbh",
    "wof:placetype":"venue"
},
  "geometry": {"coordinates":[8.5226325989,47.3740196228],"type":"Point"}
}