{
  "type": "Feature",
  "properties": {
    "iso:country":"CH",
    "sg:address":"Ebnaterstrasse 61",
    "sg:city":"Wattwil",
    "sg:orig_category":"G\u00fcterbef\u00f6rderung im Strassenverkehr Vermietung von Automobilen",
    "sg:phone":"+41 71 987 10 55",
    "sg:postcode":"9630",
    "sg:province":"St. Gallen",
    "wof:name":"Heberlein & Co Ag Transporte & Autovermietung",
    "wof:placetype":"venue"
},
  "geometry": {"coordinates":[9.0917568207,47.2979812622],"type":"Point"}
}