{
  "type": "Feature",
  "properties": {
    "iso:country":"CH",
    "sg:address":"Schulhausstrasse 24",
    "sg:city":"Langenthal",
    "sg:orig_category":"Handel mit Automobilen",
    "sg:phone":"+41 62 922 55 55",
    "sg:postcode":"4900",
    "sg:province":"Bern",
    "wof:name":"Schulhausgarage Ag",
    "wof:placetype":"venue"
},
  "geometry": {"coordinates":[7.7838730812,47.2120285034],"type":"Point"}
}