{
  "type": "Feature",
  "properties": {
    "iso:country":"CH",
    "sg:address":"Blumenweg 6",
    "sg:city":"Arlesheim",
    "sg:orig_category":"Non-Classified Establishments",
    "sg:postcode":"4144",
    "sg:province":"Basel-Landschaft",
    "wof:name":"Bahag Holding Gmbh",
    "wof:placetype":"venue"
},
  "geometry": {"coordinates":[7.6189308167,47.507106781],"type":"Point"}
}