{
  "type": "Feature",
  "properties": {
    "addr:full":"Feldstrasse 20 Winterthur Z\u00fcrich 8400",
    "addr:housenumber":"20",
    "addr:postcode":"8400",
    "addr:street":"Feldstrasse",
    "iso:country":"CH",
    "sg:address":"Feldstrasse 20",
    "sg:city":"Winterthur",
    "sg:orig_category":"Detailhandel mit Antiquit\u00e4ten Malerei",
    "sg:phone":"+41 52 222 09 89",
    "sg:postcode":"8400",
    "sg:province":"Z\u00fcrich",
    "wof:name":"Walter Steiger",
    "wof:placetype":"venue"
},
  "geometry": {"coordinates":[8.719066,47.506248],"type":"Point"}
}