{
  "type": "Feature",
  "properties": {
    "addr:full":"Les Hauts-de-nendaz Haute-nendaz Valais 1997",
    "addr:postcode":"1997",
    "iso:country":"CH",
    "sg:address":"Les Hauts-de-nendaz",
    "sg:city":"Haute-nendaz",
    "sg:orig_category":"Allgemeiner Hoch U Tiefbau",
    "sg:postcode":"1997",
    "sg:province":"Valais",
    "wof:name":"Fondation Pour La Halle 6",
    "wof:placetype":"venue"
},
  "geometry": {"coordinates":[6.121724,46.232517],"type":"Point"}
}