{
  "type": "Feature",
  "properties": {
    "iso:country":"CH",
    "sg:address":"Hafenstrasse 20",
    "sg:city":"Kreuzlingen",
    "sg:orig_category":"Zeitungsverlag",
    "sg:postcode":"8280",
    "sg:province":"Thurgau",
    "wof:name":"Gut Medien Ag",
    "wof:placetype":"venue"
},
  "geometry": {"coordinates":[9.1776790619,47.6516227722],"type":"Point"}
}