{
  "type": "Feature",
  "properties": {
    "addr:full":"Thunstrasse 2 3700 Spiez. Postfach 158 Spiez Bern 3700",
    "addr:housenumber":"2;158",
    "addr:postcode":"3700 spiez.;3700",
    "addr:street":"Thunstrasse;Postfach",
    "iso:country":"CH",
    "sg:address":"Thunstrasse 2 3700 Spiez. Postfach 158",
    "sg:city":"Spiez",
    "sg:orig_category":"Arztpraxen",
    "sg:phone":"+41 33 654 70 20",
    "sg:postcode":"3700",
    "sg:province":"Bern",
    "wof:name":"Dres Med. Kopp, Stump & W\u00e4lti Spezial\u00e4rzte Fmh",
    "wof:placetype":"venue"
},
  "geometry": {"coordinates":[7.674948,46.689919],"type":"Point"}
}