{
  "type": "Feature",
  "properties": {
    "iso:country":"CH",
    "sg:address":"Hohlstrasse 615a",
    "sg:city":"Z\u00fcrich",
    "sg:orig_category":"Satzherstellung U Reproduktion",
    "sg:phone":"+41 14313565",
    "sg:postcode":"8048",
    "sg:province":"Z\u00fcrich",
    "wof:name":"Ls Litho Service Ag",
    "wof:placetype":"venue"
},
  "geometry": {"coordinates":[8.4854402542,47.391544342],"type":"Point"}
}