{
  "type": "Feature",
  "properties": {
    "iso:country":"CH",
    "sg:address":"Alte Winterthurerstrasse 14",
    "sg:city":"Wallisellen",
    "sg:classifiers":[
        {
            "category":"Professional",
            "subcategory":"Advertising",
            "type":"Services"
        }
    ],
    "sg:phone":"+41 71 313 27 27",
    "sg:postcode":"8304",
    "sg:province":"Z\u00fcrich",
    "sg:tags":[
        "marketing",
        "direct"
    ],
    "wof:name":"Dm-plus Direktmarketing Ag",
    "wof:placetype":"venue"
},
  "geometry": {"coordinates":[9.314658165,47.4089584351],"type":"Point"}
}