{
  "type": "Feature",
  "properties": {
    "iso:country":"CH",
    "sg:address":"Wiesen 2488",
    "sg:city":"Herisau",
    "sg:orig_category":"Erbringung von Dienstleistungen f\u00fcr Unternehmen Schreib U \u00dcbersetzungsb\u00fcros",
    "sg:phone":"+41 71 352 39 65",
    "sg:postcode":"9100",
    "sg:province":"Appenzell Ausserrhoden",
    "wof:name":"Knoeag B\u00fcrosupport & \u00dcbersetzungen",
    "wof:placetype":"venue"
},
  "geometry": {"coordinates":[9.2522182465,47.3671913147],"type":"Point"}
}