{
  "type": "Feature",
  "properties": {
    "iso:country":"CH",
    "sg:address":"Chiss 8",
    "sg:city":"Samedan",
    "sg:orig_category":"Unternehmensberatung",
    "sg:phone":"+41 81 852 18 51",
    "sg:postcode":"7503",
    "sg:province":"Graubunden",
    "wof:name":"Peter Schubert, Unternehmensberatung",
    "wof:placetype":"venue"
},
  "geometry": {"coordinates":[9.8695201874,46.5345611572],"type":"Point"}
}