{
  "type": "Feature",
  "properties": {
    "iso:country":"CH",
    "sg:address":"Spalenberg 37",
    "sg:city":"Basel",
    "sg:orig_category":"Kunsthandel",
    "sg:phone":"+41 61 261 38 05",
    "sg:postcode":"4051",
    "sg:province":"Basel-Stadt",
    "wof:name":"Helgestuube & Atelier Zum Kirschbaum",
    "wof:placetype":"venue"
},
  "geometry": {"coordinates":[7.5855031013,47.5567932129],"type":"Point"}
}