{
  "type": "Feature",
  "properties": {
    "iso:country":"CH",
    "sg:address":"Rue De La Poste",
    "sg:city":"Verbier",
    "sg:orig_category":"Reiseb\u00fcros U Reiseveranstalter",
    "sg:phone":"+41 27 771 62 67",
    "sg:postcode":"1936",
    "sg:province":"Valais",
    "wof:name":"Horizons Nouveaux Jaques & Kennes,voyages",
    "wof:placetype":"venue"
},
  "geometry": {"coordinates":[7.2247400284,46.0970802307],"type":"Point"}
}