{
  "type": "Feature",
  "properties": {
    "iso:country":"CH",
    "sg:address":"Luzernstrasse 38 4553 Subingen. Postfach 242",
    "sg:city":"Subingen",
    "sg:orig_category":"Drogerien",
    "sg:phone":"+41 32 614 15 01",
    "sg:postcode":"4553",
    "sg:province":"Solothurn",
    "wof:name":"Drogerie P. Leu",
    "wof:placetype":"venue"
},
  "geometry": {"coordinates":[7.6149587631,47.1953697205],"type":"Point"}
}