{
  "type": "Feature",
  "properties": {
    "iso:country":"CH",
    "sg:address":"Rugenstrasse 31",
    "sg:city":"Matten",
    "sg:classifiers":[
        {
            "category":"Military Area",
            "subcategory":"Air Force Base",
            "type":"Public Place"
        }
    ],
    "sg:phone":"+41 33 822 88 28",
    "sg:postcode":"3800",
    "sg:province":"Bern",
    "sg:tags":[
        "conservatory",
        "aluminium",
        "construction",
        "system"
    ],
    "wof:name":"Albert Zwahlen Metallbau",
    "wof:placetype":"venue"
},
  "geometry": {"coordinates":[7.863166,46.675526],"type":"Point"}
}