{
  "type": "Feature",
  "properties": {
    "addr:full":"Haldenhut Pf 131 Mollis Glarus 8753",
    "addr:housenumber":"131",
    "addr:postcode":"8753",
    "iso:country":"CH",
    "sg:address":"Haldenhut Pf 131",
    "sg:city":"Mollis",
    "sg:classifiers":[
        {
            "category":"Airport",
            "type":"Transportation"
        }
    ],
    "sg:phone":"+41 55 612 33 33",
    "sg:postcode":"8753",
    "sg:province":"Glarus",
    "sg:tags":[
        "transport",
        "air"
    ],
    "wof:name":"Heli-linth Ag",
    "wof:placetype":"venue"
},
  "geometry": {"coordinates":[9.074525,47.091438],"type":"Point"}
}