{
  "type": "Feature",
  "properties": {
    "iso:country":"CH",
    "sg:address":"Hirzenbachstrasse 70",
    "sg:city":"Z\u00fcrich",
    "sg:orig_category":"Mechanik Mechanische Werkst\u00e4tten",
    "sg:phone":"+41 13224013",
    "sg:postcode":"8051",
    "sg:province":"Z\u00fcrich",
    "wof:name":"Thomas Ochs Mechanische Werkstatt",
    "wof:placetype":"venue"
},
  "geometry": {"coordinates":[8.5883903503,47.4053421021],"type":"Point"}
}