{
  "type": "Feature",
  "properties": {
    "iso:country":"CH",
    "sg:address":"Dorfstrasse 32",
    "sg:city":"Thal",
    "sg:orig_category":"Detailhandel mit Waren verschiedener Art, Hauptrichtung Nichtnahrungsmittel",
    "sg:phone":"+41 71 888 18 87",
    "sg:postcode":"9425",
    "sg:province":"St. Gallen",
    "wof:name":"Epa Superdiscount, Grab S. + G.",
    "wof:placetype":"venue"
},
  "geometry": {"coordinates":[9.5656280518,47.4681434631],"type":"Point"}
}