{
  "type": "Feature",
  "properties": {
    "iso:country":"CH",
    "sg:address":"Viale Verbano 31",
    "sg:city":"Muralto",
    "sg:classifiers":[
        {
            "category":"Travel",
            "subcategory":"Hotels & Motels",
            "type":"Entertainment"
        }
    ],
    "sg:phone":"+41 91 743 13 55",
    "sg:postcode":"6600",
    "sg:province":"Ticino",
    "sg:tags":[
        "hotels",
        "mit",
        "restaurant"
    ],
    "wof:name":"Albergo Beau-rivage Treff Hotel Oasis Sa",
    "wof:placetype":"venue"
},
  "geometry": {"coordinates":[8.8049507141,46.1716308594],"type":"Point"}
}