{
  "type": "Feature",
  "properties": {
    "iso:country":"CH",
    "sg:address":"Rue De L'industrie 11 2114 Fleurier. Postfach",
    "sg:city":"Fleurier",
    "sg:orig_category":"Handels-H\u00e4user U Gesellschaften Immobilienwesen",
    "sg:phone":"+41 32 860 10 55",
    "sg:postcode":"2114",
    "sg:province":"Neuch\u00e2tel",
    "wof:name":"Valimmob Corrado Di Meo Bureau De Courtage En Immobilier Et Assurances",
    "wof:placetype":"venue"
},
  "geometry": {"coordinates":[6.5786561966,46.9013442993],"type":"Point"}
}