{
  "type": "Feature",
  "properties": {
    "iso:country":"CH",
    "sg:address":"Bahnhofstrasse 19",
    "sg:city":"Sissach",
    "sg:orig_category":"Fachdetailhandel in Verkaufsr\u00e4umen",
    "sg:phone":"+41 61 973 08 35",
    "sg:postcode":"4450",
    "sg:province":"Basel-Landschaft",
    "wof:name":"Tierfutter-haus Sissach, Bolliger E. + Langer D.",
    "wof:placetype":"venue"
},
  "geometry": {"coordinates":[7.8130669594,47.4628372192],"type":"Point"}
}