{
  "type": "Feature",
  "properties": {
    "iso:country":"CH",
    "sg:address":"Im Glockengut 31 8200 Schaffhausen. Postfach",
    "sg:city":"Schaffhausen",
    "sg:orig_category":"Sanit\u00e4r, Heizungs U L\u00fcftungsinstallation",
    "sg:postcode":"8207",
    "sg:province":"Schaffhausen",
    "wof:name":"Luginb\u00fchl Heinz Sanit\u00e4rservice",
    "wof:placetype":"venue"
},
  "geometry": {"coordinates":[8.6535825729,47.7190284729],"type":"Point"}
}