{
  "type": "Feature",
  "properties": {
    "iso:country":"CH",
    "sg:address":"Loretostrasse 6",
    "sg:city":"Lichtensteig",
    "sg:orig_category":"Finanzierungsinstitutionen",
    "sg:postcode":"9620",
    "sg:province":"St. Gallen",
    "wof:name":"Finanz Und Immobilienberatung Widmer H\u00fcberli Claudia",
    "wof:placetype":"venue"
},
  "geometry": {"coordinates":[9.0873794556,47.3246612549],"type":"Point"}
}