{
  "type": "Feature",
  "properties": {
    "iso:country":"CH",
    "sg:address":"Corso San Gottardo 14",
    "sg:city":"Chiasso",
    "sg:orig_category":"Non-Classified Establishments",
    "sg:postcode":"6830",
    "sg:province":"Ticino",
    "wof:name":"Vickers Sa Atelier M\u00e9canique",
    "wof:placetype":"venue"
},
  "geometry": {"coordinates":[7.0246648788,47.0372657776],"type":"Point"}
}