{
  "type": "Feature",
  "properties": {
    "iso:country":"CH",
    "sg:address":"Landstrasse 15",
    "sg:city":"Schaan",
    "sg:orig_category":"Detailhandel mit Schreib U Papeteriewaren Erbringung von Dienstleistungen f\u00fcr Unternehmen",
    "sg:phone":"+41 55 293 50 41",
    "sg:postcode":"9494",
    "wof:name":"Paperfashion, Schmid J\u00f6rg & Co",
    "wof:placetype":"venue"
},
  "geometry": {"coordinates":[9.0052719116,47.1983261108],"type":"Point"}
}