{
  "type": "Feature",
  "properties": {
    "iso:country":"CH",
    "sg:address":"Forchstrasse 2 8008 Z\u00fcrich. Postfach 1957",
    "sg:city":"Z\u00fcrich",
    "sg:orig_category":"Detailhandel mit Bekleidung Detailhandel mit Textilien",
    "sg:phone":"+41 12111344",
    "sg:postcode":"8032",
    "sg:province":"Z\u00fcrich",
    "wof:name":"B\u00f6hny-handschuhe Ag",
    "wof:placetype":"venue"
},
  "geometry": {"coordinates":[8.554772,47.364464],"type":"Point"}
}