{
  "type": "Feature",
  "properties": {
    "iso:country":"CH",
    "sg:address":"Clarastrasse 51 4058 Basel. Postfach",
    "sg:city":"Basel",
    "sg:orig_category":"Institutionen f\u00fcr Finanzierungsleasing Sonstiger Grosshandel",
    "sg:phone":"+41 71 220 11 88",
    "sg:postcode":"4005",
    "sg:province":"Basel-Stadt",
    "wof:name":"Lisca Ag",
    "wof:placetype":"venue"
},
  "geometry": {"coordinates":[9.3720808029,47.4237632751],"type":"Point"}
}