{
  "type": "Feature",
  "properties": {
    "iso:country":"CH",
    "sg:address":"Tagungszentrum Landegg",
    "sg:city":"Eggersriet",
    "sg:orig_category":"Religi\u00f6se Vereinigungen",
    "sg:phone":"+41 71 891 91 31",
    "sg:postcode":"9034",
    "sg:province":"St. Gallen",
    "wof:name":"Internationale Baha'i Stiftung Landegg",
    "wof:placetype":"venue"
},
  "geometry": {"coordinates":[9.4722900391,47.4425544739],"type":"Point"}
}