{
  "type": "Feature",
  "properties": {
    "iso:country":"CH",
    "sg:address":"Bahnhofstrasse 86",
    "sg:city":"Aarau",
    "sg:orig_category":"Zahnarztpraxen",
    "sg:phone":"+41 62 824 91 14",
    "sg:postcode":"5000",
    "sg:province":"Aargau",
    "wof:name":"Dr. Med. Dent. Christian Eicke Zahnarzt",
    "wof:placetype":"venue"
},
  "geometry": {"coordinates":[8.0526533127,47.3923988342],"type":"Point"}
}