{
  "type": "Feature",
  "properties": {
    "iso:country":"CH",
    "sg:address":"Pavement Route Du 12 1018 Lausanne. Postfach",
    "sg:city":"Lausanne",
    "sg:orig_category":"Grosshandel mit Nahrungsmitteln, Getr\u00e4nken U Tabakwaren ohne ausgepr\u00e4gten Schwerpunkt",
    "sg:phone":"+41 71 744 18 83",
    "sg:postcode":"1018",
    "sg:province":"Vaud",
    "wof:name":"Kuhn Dora Frau, Lebensmittel.",
    "wof:placetype":"venue"
},
  "geometry": {"coordinates":[9.6367607117,47.4546127319],"type":"Point"}
}