{
  "type": "Feature",
  "properties": {
    "iso:country":"CH",
    "sg:address":"Route De Malagnou 39",
    "sg:city":"Gen\u00e8ve",
    "sg:orig_category":"Physiotherapie",
    "sg:phone":"+41 22 735 58 20",
    "sg:postcode":"1208",
    "sg:province":"Gen\u00e8ve",
    "wof:name":"Damien Mar\u00e9chal Physioth\u00e9rapie",
    "wof:placetype":"venue"
},
  "geometry": {"coordinates":[6.1629929543,46.1970367432],"type":"Point"}
}