{
  "type": "Feature",
  "properties": {
    "iso:country":"CH",
    "sg:address":"Via Pedevilla 10",
    "sg:city":"Bellinzona",
    "sg:orig_category":"Tierarztpraxis",
    "sg:phone":"+41 91 825 25 58",
    "sg:postcode":"6500",
    "sg:province":"Ticino",
    "wof:name":"Dott.med.vet.sergio Postizzi Veterinario",
    "wof:placetype":"venue"
},
  "geometry": {"coordinates":[9.0218420029,46.18359375],"type":"Point"}
}