{
  "type": "Feature",
  "properties": {
    "iso:country":"CH",
    "sg:address":"Vo\u00ebns 2072 St-blaise. Postfach",
    "sg:city":"St-blaise",
    "sg:orig_category":"Detailhandel mit Sportartikeln Fachdetailhandel in Verkaufsr\u00e4umen",
    "sg:phone":"+41 32 753 70 84",
    "sg:postcode":"2072",
    "sg:province":"Neuch\u00e2tel",
    "wof:name":"Golf Et Country Shop De Vo\u00ebns S\u00e0rl Magasin Pour Le Golf, Vente De Mat\u00e9riel, Produits Pour Le Golf Etc",
    "wof:placetype":"venue"
},
  "geometry": {"coordinates":[6.9915142059,47.0317573547],"type":"Point"}
}