{
  "type": "Feature",
  "properties": {
    "iso:country":"CH",
    "sg:address":"Car\u00e0 Via 18b 6932 Breganzona. Postfach",
    "sg:city":"Breganzona",
    "sg:orig_category":"Schiffsbau ohne Boots U Yachtbau",
    "sg:phone":"+41 91 604 66 17",
    "sg:postcode":"6932",
    "sg:province":"Ticino",
    "wof:name":"Medservices & Partners Ltd, Londra, Succursale Di Manno",
    "wof:placetype":"venue"
},
  "geometry": {"coordinates":[8.9248876572,46.0064048767],"type":"Point"}
}