{
  "type": "Feature",
  "properties": {
    "iso:country":"CH",
    "sg:address":"Lehenstrasse 35",
    "sg:city":"Z\u00fcrich",
    "sg:orig_category":"Non-Classified Establishments",
    "sg:postcode":"8037",
    "sg:province":"Z\u00fcrich",
    "wof:name":"Deflorin + Bahnsen Garten Und Sportanlagen Ag",
    "wof:placetype":"venue"
},
  "geometry": {"coordinates":[9.8381910324,46.4970664978],"type":"Point"}
}