{
  "type": "Feature",
  "properties": {
    "addr:full":"Ciossi Via Ai 8 Losone Ticino 6616",
    "addr:housenumber":"8",
    "addr:postcode":"6616",
    "addr:street":"Via Ai",
    "iso:country":"CH",
    "sg:address":"Ciossi Via Ai 8",
    "sg:city":"Losone",
    "sg:orig_category":"Allgemeiner Hoch U Tiefbau",
    "sg:postcode":"6616",
    "sg:province":"Ticino",
    "wof:name":"Bigoni Giovanni Sagl",
    "wof:placetype":"venue"
},
  "geometry": {"coordinates":[8.7608,46.1628],"type":"Point"}
}