{
  "type": "Feature",
  "properties": {
    "iso:country":"CH",
    "sg:address":"Rathausgasse 3 4500 Solothurn. Postfach 943",
    "sg:city":"Solothurn",
    "sg:orig_category":"Politische Parteien SP",
    "sg:phone":"+41 71 622 25 62",
    "sg:postcode":"4502",
    "sg:province":"Solothurn",
    "wof:name":"Sp Des Kantons Thurgau",
    "wof:placetype":"venue"
},
  "geometry": {"coordinates":[9.1381845474,47.5666694641],"type":"Point"}
}