{
  "type": "Feature",
  "properties": {
    "iso:country":"CH",
    "sg:address":"1686",
    "sg:city":"Grangettes-romont",
    "sg:orig_category":"Sonstiger Fachdetailhandel mit Nahrungsmitteln, Getr\u00e4nken U Tabak in Verkaufsr\u00e4umen",
    "sg:phone":"+41 26 652 11 45",
    "sg:postcode":"1686",
    "sg:province":"Fribourg",
    "wof:name":"Laiterie-fromagerie Lauper Joseph",
    "wof:placetype":"venue"
},
  "geometry": {"coordinates":[6.9610900879,46.6757888794],"type":"Point"}
}