{
  "type": "Feature",
  "properties": {
    "iso:country":"CH",
    "sg:address":"6712",
    "sg:orig_category":"Mechanik",
    "sg:postcode":"6712",
    "wof:name":"Latzer Emil.",
    "wof:placetype":"venue"
},
  "geometry": {"coordinates":[9.2546291351,47.4166107178],"type":"Point"}
}