{
  "type": "Feature",
  "properties": {
    "iso:country":"CH",
    "sg:address":"Rh\u00f4ne Rue Du 50 1204 Gen\u00e8ve. Postfach",
    "sg:city":"Gen\u00e8ve",
    "sg:orig_category":"Vermietung U Verpachtung von eigenen Immobilien",
    "sg:postcode":"1204",
    "sg:province":"Gen\u00e8ve",
    "wof:name":"La Prairie Tallan Sa",
    "wof:placetype":"venue"
},
  "geometry": {"coordinates":[6.8612399101,46.98828125],"type":"Point"}
}