{
  "type": "Feature",
  "properties": {
    "iso:country":"CH",
    "sg:address":"Paradiesstrasse 1 8425 Oberembrach. Postfach",
    "sg:city":"Winterthur",
    "sg:orig_category":"Allgemeiner Hoch U Tiefbau",
    "sg:phone":"+41 52 222 38 55",
    "sg:postcode":"8408",
    "sg:province":"Z\u00fcrich",
    "wof:name":"Berna Allround Gmbh Arbeiten Im Baubereich",
    "wof:placetype":"venue"
},
  "geometry": {"coordinates":[8.621402,47.488491],"type":"Point"}
}