{
  "type": "Feature",
  "properties": {
    "iso:country":"CH",
    "sg:address":"Restelbergstrasse 79",
    "sg:city":"Z\u00fcrich",
    "sg:orig_category":"Markt U Meinungsforschung",
    "sg:postcode":"8044",
    "sg:province":"Z\u00fcrich",
    "wof:name":"Bender Hermann. Verkaufsorganisation.",
    "wof:placetype":"venue"
},
  "geometry": {"coordinates":[8.5550394058,47.3837623596],"type":"Point"}
}