{
  "type": "Feature",
  "properties": {
    "iso:country":"CH",
    "sg:address":"Portone Viale 10",
    "sg:city":"Bellinzona",
    "sg:orig_category":"Unclassifiable Establishments",
    "sg:postcode":"6500",
    "sg:province":"Ticino",
    "wof:name":"Balascio Pasquale - Compra-vendita Autoveicoli D'occasione",
    "wof:placetype":"venue"
},
  "geometry": {"coordinates":[9.0186052322,46.1935844421],"type":"Point"}
}