{
  "type": "Feature",
  "properties": {
    "iso:country":"CH",
    "sg:address":"Kirchweg 6",
    "sg:city":"Waltenschwil",
    "sg:orig_category":"Grosshandel mit Geschenkartikeln U Souvenirs Grosshandel mit sonstigen Gebrauchs U Verbrauchsg\u00fctern",
    "sg:phone":"+41 31 381 57 71",
    "sg:postcode":"5622",
    "sg:province":"Aargau",
    "wof:name":"Polydono Ag",
    "wof:placetype":"venue"
},
  "geometry": {"coordinates":[7.4193148613,46.9469032288],"type":"Point"}
}