{
  "type": "Feature",
  "properties": {
    "iso:country":"CH",
    "sg:address":"Lavaterstrasse 7",
    "sg:city":"Z\u00fcrich",
    "sg:orig_category":"Religi\u00f6se Vereinigungen",
    "sg:postcode":"8002",
    "sg:province":"Z\u00fcrich",
    "wof:name":"Stiftung Zur Erhaltung Und Pflege Der Friedh\u00f6fe Der Isrealitischen Cultusgemeinde",
    "wof:placetype":"venue"
},
  "geometry": {"coordinates":[8.5320796967,47.3637199402],"type":"Point"}
}