{
  "type": "Feature",
  "properties": {
    "iso:country":"CH",
    "sg:address":"En Rosset 5",
    "sg:city":"Echallens",
    "sg:orig_category":"Interessenvertretungen",
    "sg:postcode":"1040",
    "sg:province":"Vaud",
    "wof:name":"Arts & Paix",
    "wof:placetype":"venue"
},
  "geometry": {"coordinates":[6.6394639015,46.6448860168],"type":"Point"}
}