{
  "type": "Feature",
  "properties": {
    "iso:country":"CH",
    "sg:address":"Herrenrebenweg 16 8408 Winterthur. Postfach",
    "sg:city":"Winterthur",
    "sg:orig_category":"Handelsvermittlung U Grosshandel",
    "sg:phone":"+41 52 202 93 51",
    "sg:postcode":"8408",
    "sg:province":"Z\u00fcrich",
    "wof:name":"Remco Gmbh Techn. Anlagen Usw.; Handel, Dienstl.",
    "wof:placetype":"venue"
},
  "geometry": {"coordinates":[8.6920223236,47.5027923584],"type":"Point"}
}