{
  "type": "Feature",
  "properties": {
    "iso:country":"CH",
    "sg:address":"Gaswerkstrasse 15",
    "sg:city":"Weinfelden",
    "sg:orig_category":"Grosshandel mit Nahrungsmitteln, Getr\u00e4nken U Tabakwaren Grosshandel mit Nahrungsmitteln, Getr\u00e4nken U",
    "sg:phone":"+41 71 626 81 31",
    "sg:postcode":"8570",
    "sg:province":"Thurgau",
    "wof:name":"Frigemo Ag",
    "wof:placetype":"venue"
},
  "geometry": {"coordinates":[9.099486351,47.5690193176],"type":"Point"}
}