{
  "type": "Feature",
  "properties": {
    "iso:country":"CH",
    "sg:address":"Ober Altstadt 4",
    "sg:city":"Zug",
    "sg:orig_category":"Detailhandel mit elektrischen Haushalts-,Radio U Fernsehger\u00e4ten sowie Musikinstrumenten",
    "sg:postcode":"6300",
    "sg:province":"Zug",
    "wof:name":"Vhf-technologies Sa",
    "wof:placetype":"venue"
},
  "geometry": {"coordinates":[6.7467451096,47.056476593],"type":"Point"}
}