{
  "type": "Feature",
  "properties": {
    "iso:country":"CH",
    "sg:address":"Mittelbach",
    "sg:city":"Heimisbach",
    "sg:orig_category":"Massagestudios",
    "sg:phone":"+41 34 431 43 65",
    "sg:postcode":"3453",
    "sg:province":"Bern",
    "wof:name":"Samuel Erhard Massagen",
    "wof:placetype":"venue"
},
  "geometry": {"coordinates":[7.7603111267,47.011756897],"type":"Point"}
}