{
  "type": "Feature",
  "properties": {
    "iso:country":"CH",
    "sg:address":"R\u00fctistrasse 16",
    "sg:city":"Hombrechtikon",
    "sg:orig_category":"Zahntechnische Laboratorien",
    "sg:phone":"+41 55 244 46 25",
    "sg:postcode":"8634",
    "sg:province":"Z\u00fcrich",
    "wof:name":"Elisabeth Szeg\u00f6-bajka Zahnprothetik",
    "wof:placetype":"venue"
},
  "geometry": {"coordinates":[8.7693853378,47.2518692017],"type":"Point"}
}