{
  "type": "Feature",
  "properties": {
    "addr:full":"Mettlenstrasse 26 Winterthur Z\u00fcrich 8409",
    "addr:housenumber":"26",
    "addr:postcode":"8409",
    "addr:street":"Mettlenstrasse",
    "iso:country":"CH",
    "sg:address":"Mettlenstrasse 26",
    "sg:city":"Winterthur",
    "sg:classifiers":[
        {
            "category":"Farming",
            "subcategory":"Crops",
            "type":"Manufacturing & Wholesale Goods"
        }
    ],
    "sg:phone":"+41 31 750 55 22",
    "sg:postcode":"8409",
    "sg:province":"Z\u00fcrich",
    "sg:tags":[
        "vegetable",
        "fruit",
        "agriculture",
        "livestock"
    ],
    "wof:name":"Etter + Berno Ag",
    "wof:placetype":"venue"
},
  "geometry": {"coordinates":[7.186681,46.953812],"type":"Point"}
}