{
  "type": "Feature",
  "properties": {
    "iso:country":"CH",
    "sg:address":"Sappetenstrasse 6",
    "sg:city":"Bubendorf",
    "sg:orig_category":"Grosshandel mit Software Softwareentwicklung U beratung",
    "sg:phone":"+41 61 933 10 33",
    "sg:postcode":"4416",
    "sg:province":"Basel-Landschaft",
    "wof:name":"Digisoft Ag",
    "wof:placetype":"venue"
},
  "geometry": {"coordinates":[7.737279892,47.4511604309],"type":"Point"}
}