{
  "type": "Feature",
  "properties": {
    "iso:country":"CH",
    "sg:address":"Pradafant 11 9490 Vaduz. Postfach 1508",
    "sg:city":"Vaduz",
    "sg:orig_category":"Fotografische Ateliers Korrespondenz U Nachrichtenb\u00fcros",
    "sg:phone":"+423 232 65 73",
    "sg:postcode":"9490",
    "wof:name":"Wbw & Partner-presse &",
    "wof:placetype":"venue"
},
  "geometry": {"coordinates":[9.5135173798,47.1450996399],"type":"Point"}
}