{
  "type": "Feature",
  "properties": {
    "iso:country":"CH",
    "sg:address":"Via Geretta 9a",
    "sg:city":"Bellinzona",
    "sg:orig_category":"Interessenvertretungen Jugendherbergen U H\u00fctten",
    "sg:phone":"+41 91 825 90 98",
    "sg:postcode":"6500",
    "sg:province":"Ticino",
    "wof:name":"Jugendherberge Spazio Aperto",
    "wof:placetype":"venue"
},
  "geometry": {"coordinates":[9.0303926468,46.2007980347],"type":"Point"}
}