{
  "type": "Feature",
  "properties": {
    "iso:country":"CH",
    "sg:address":"Centre Du Village",
    "sg:city":"Sullens",
    "sg:orig_category":"Regionalbanken U Sparkassen",
    "sg:phone":"+41 21 732 18 32",
    "sg:postcode":"1036",
    "sg:province":"Vaud",
    "wof:name":"Caisse D'epargne Du District De Cossonay",
    "wof:placetype":"venue"
},
  "geometry": {"coordinates":[6.5663352013,46.5934906006],"type":"Point"}
}