{
  "type": "Feature",
  "properties": {
    "iso:country":"CH",
    "sg:address":"8640 Kempraten. Postfach 122",
    "sg:city":"Kempraten",
    "sg:orig_category":"Sportvereine Ballsport Tennis",
    "sg:phone":"+41 55 210 60 54",
    "sg:postcode":"8640",
    "sg:province":"Schwyz",
    "wof:name":"Tc Sport K\u00fcng",
    "wof:placetype":"venue"
},
  "geometry": {"coordinates":[8.8209552765,47.2339515686],"type":"Point"}
}