{
  "type": "Feature",
  "properties": {
    "addr:full":"Hauptstrasse 72 Muttenz Basel-Landschaft 4132",
    "addr:housenumber":"72",
    "addr:postcode":"4132",
    "addr:street":"Hauptstrasse",
    "iso:country":"CH",
    "sg:address":"Hauptstrasse 72",
    "sg:city":"Muttenz",
    "sg:orig_category":"Detailhandel mit Bekleidung Detailhandel mit Herrenbekleidung",
    "sg:postcode":"4132",
    "sg:province":"Basel-Landschaft",
    "wof:name":"Wirth Mode Ag",
    "wof:placetype":"venue"
},
  "geometry": {"coordinates":[9.249733,47.41589],"type":"Point"}
}