{
  "type": "Feature",
  "properties": {
    "iso:country":"CH",
    "sg:address":"1608",
    "sg:city":"Oron-le-ch\u00e2tel",
    "sg:orig_category":"Forstwirtschaft ohne Dienstleistungen in der Forstwirtschaft",
    "sg:phone":"+41 21 907 98 66",
    "sg:postcode":"1608",
    "sg:province":"Fribourg",
    "wof:name":"Quittner De Vagfalvi Thierry",
    "wof:placetype":"venue"
},
  "geometry": {"coordinates":[6.8395252228,46.5752868652],"type":"Point"}
}