{
  "type": "Feature",
  "properties": {
    "iso:country":"CH",
    "sg:address":"Rosenbergstrasse 1",
    "sg:city":"Wallisellen",
    "sg:classifiers":[
        {
            "category":"Professional",
            "subcategory":"Computer Services",
            "type":"Services"
        }
    ],
    "sg:phone":"+41 71 260 28 60",
    "sg:postcode":"8304",
    "sg:province":"Z\u00fcrich",
    "sg:tags":[
        "development",
        "software"
    ],
    "wof:name":"Karl Kalberer Kaa Software Engineering",
    "wof:placetype":"venue"
},
  "geometry": {"coordinates":[9.3529586792,47.4119262695],"type":"Point"}
}