{
  "type": "Feature",
  "properties": {
    "iso:country":"CH",
    "sg:address":"Via Trevano 7a",
    "sg:city":"Lugano",
    "sg:orig_category":"Datenverarbeitungsdienste",
    "sg:phone":"+41 19701555",
    "sg:postcode":"6900",
    "sg:province":"Ticino",
    "wof:name":"Domig Informatik Ag",
    "wof:placetype":"venue"
},
  "geometry": {"coordinates":[8.814889,47.337116],"type":"Point"}
}