{
  "type": "Feature",
  "properties": {
    "iso:country":"CH",
    "sg:address":"Weidstrasse 4 6038 Honau. Postfach 16",
    "sg:city":"Gisikon",
    "sg:orig_category":"Immobilienwesen",
    "sg:phone":"+41 41 451 05 87",
    "sg:postcode":"6038",
    "sg:province":"Luzern",
    "wof:name":"Busch & Partner Immobilien",
    "wof:placetype":"venue"
},
  "geometry": {"coordinates":[8.4071025848,47.1303634644],"type":"Point"}
}