{
  "type": "Feature",
  "properties": {
    "iso:country":"CH",
    "sg:address":"Untere Steig 15",
    "sg:city":"Rheinau",
    "sg:classifiers":[
        {
            "category":"Restaurant",
            "type":"Food & Drink"
        }
    ],
    "sg:phone":"+41 71 222 15 43",
    "sg:postcode":"8462",
    "sg:province":"Z\u00fcrich",
    "wof:name":"Restaurant Augustinerhalle",
    "wof:placetype":"venue"
},
  "geometry": {"coordinates":[9.3746995926,47.4273796082],"type":"Point"}
}