{
  "type": "Feature",
  "properties": {
    "addr:full":"M\u00fcnchensteinerstrasse 2 Basel Basel-Stadt 4052",
    "addr:housenumber":"2",
    "addr:postcode":"4052",
    "addr:street":"Muenchensteinerstrasse",
    "iso:country":"CH",
    "sg:address":"M\u00fcnchensteinerstrasse 2",
    "sg:city":"Basel",
    "sg:classifiers":[
        {
            "category":"Food & Beverages",
            "subcategory":"Specialty",
            "type":"Retail Goods"
        }
    ],
    "sg:phone":"+41 18803404",
    "sg:postcode":"4052",
    "sg:province":"Basel-Stadt",
    "sg:tags":[
        "caterer"
    ],
    "wof:name":"Baggenstos Ag Partyservice Event Organisatio",
    "wof:placetype":"venue"
},
  "geometry": {"coordinates":[8.440954,47.415848],"type":"Point"}
}