{
  "type": "Feature",
  "properties": {
    "iso:country":"CH",
    "sg:address":"Via Moree 8",
    "sg:city":"Mendrisio",
    "sg:orig_category":"Markt U Meinungsforschung Werbevermittlung",
    "sg:phone":"+41 79 444 02 32",
    "sg:postcode":"6850",
    "sg:province":"Ticino",
    "wof:name":"Falko & Friends",
    "wof:placetype":"venue"
},
  "geometry": {"coordinates":[8.9809274673,45.8732185364],"type":"Point"}
}