{
  "type": "Feature",
  "properties": {
    "iso:country":"CH",
    "sg:address":"Chemin Pralies 15",
    "sg:city":"Bogis-bossey",
    "sg:orig_category":"Grosshandel mit B\u00fcromaschinen Grosshandel mit Datenverarbeitungsger\u00e4ten",
    "sg:phone":"+41 17844272",
    "sg:postcode":"1279",
    "sg:province":"Vaud",
    "wof:name":"Inactweb Gmbh",
    "wof:placetype":"venue"
},
  "geometry": {"coordinates":[8.7278995514,47.2013206482],"type":"Point"}
}