{
  "type": "Feature",
  "properties": {
    "iso:country":"CH",
    "sg:address":"Villars-vert Route De 2 1752 Villars-sur-gl\u00e2ne Case Postale",
    "sg:city":"Villars-sur-gl\u00e2ne",
    "sg:orig_category":"Herstellung von nachrichtentechnischen Ger\u00e4ten U Einrichtungen",
    "sg:phone":"+41 26 409 74 09",
    "sg:postcode":"1752",
    "sg:province":"Fribourg",
    "wof:name":"Fran\u00e7ois Molliet Sa",
    "wof:placetype":"venue"
},
  "geometry": {"coordinates":[7.1299967766,46.7990570068],"type":"Point"}
}