{
  "type": "Feature",
  "properties": {
    "iso:country":"CH",
    "sg:address":"Stationsstrasse 2",
    "sg:city":"Niederhasli",
    "sg:orig_category":"Organisationen des Gesundheitswesen",
    "sg:phone":"+41 18504022",
    "sg:postcode":"8155",
    "sg:province":"Z\u00fcrich",
    "wof:name":"Samariterverein Dielsdorf",
    "wof:placetype":"venue"
},
  "geometry": {"coordinates":[8.4883842468,47.4793624878],"type":"Point"}
}