{
  "type": "Feature",
  "properties": {
    "iso:country":"CH",
    "sg:address":"Lorrainestrasse 14",
    "sg:city":"Bern",
    "sg:orig_category":"Detailhandel mit Schreib U Papeteriewaren Sonstiger Fachdetailhandel in Verkaufsr\u00e4umen",
    "sg:phone":"+41 31 333 44 34",
    "sg:postcode":"3013",
    "sg:province":"Bern",
    "wof:name":"Xanadu & Leisure Gmbh Multi Mega Store",
    "wof:placetype":"venue"
},
  "geometry": {"coordinates":[7.4452800751,46.9557533264],"type":"Point"}
}