{
  "type": "Feature",
  "properties": {
    "iso:country":"CH",
    "sg:address":"Im Moos 23a",
    "sg:city":"Nufenen",
    "sg:orig_category":"Architektur U Ingenieurb\u00fcros",
    "sg:phone":"+41 81 664 14 14",
    "sg:postcode":"7437",
    "sg:province":"Graubunden",
    "wof:name":"Tschopp Consult",
    "wof:placetype":"venue"
},
  "geometry": {"coordinates":[9.248228,46.540634],"type":"Point"}
}