{
  "type": "Feature",
  "properties": {
    "iso:country":"CH",
    "sg:address":"Sonnhaldenweg 24 4450 Sissach. Postfach",
    "sg:city":"Sissach",
    "sg:orig_category":"Fachdetailhandel in Verkaufsr\u00e4umen Herstellung U Zusammensetzung von Uhren",
    "sg:phone":"+41 61 971 41 83",
    "sg:postcode":"4450",
    "sg:province":"Basel-Landschaft",
    "wof:name":"Montres Charmex",
    "wof:placetype":"venue"
},
  "geometry": {"coordinates":[7.8106942177,47.4710388184],"type":"Point"}
}