{
  "type": "Feature",
  "properties": {
    "iso:country":"CH",
    "sg:address":"Th\u00e9\u00e2tre Bvd Du 12 1204 Gen\u00e8ve. Postfach",
    "sg:city":"Gen\u00e8ve",
    "sg:orig_category":"Non-Classified Establishments",
    "sg:postcode":"1204",
    "sg:province":"Gen\u00e8ve",
    "wof:name":"Soci\u00e9t\u00e9 Immobili\u00e8re De La Rue Des Granges No 5",
    "wof:placetype":"venue"
},
  "geometry": {"coordinates":[6.142206192,46.2013053894],"type":"Point"}
}