{
  "type": "Feature",
  "properties": {
    "iso:country":"CH",
    "sg:address":"Village Rue Du 11",
    "sg:city":"Aran",
    "sg:orig_category":"Grosshandel mit Getr\u00e4nken",
    "sg:postcode":"1091",
    "sg:province":"Vaud",
    "wof:name":"Cave Beau R\u00e9veil, Testuz B\u00e9atrice",
    "wof:placetype":"venue"
},
  "geometry": {"coordinates":[6.7108769417,46.4980812073],"type":"Point"}
}