{
  "type": "Feature",
  "properties": {
    "iso:country":"CH",
    "sg:address":"1853 Yvorne Case Postale 0",
    "sg:city":"Yvorne",
    "sg:orig_category":"Grosshandel mit Getr\u00e4nken",
    "sg:phone":"+41 55 246 32 43",
    "sg:postcode":"1853",
    "sg:province":"Vaud",
    "wof:name":"Istvanic Franjo, Weinimport",
    "wof:placetype":"venue"
},
  "geometry": {"coordinates":[8.9413003922,47.2884101868],"type":"Point"}
}