{
  "type": "Feature",
  "properties": {
    "iso:country":"CH",
    "sg:address":"Centralstrasse 28",
    "sg:city":"Interlaken",
    "sg:classifiers":[
        {
            "category":"Travel",
            "subcategory":"Hotels & Motels",
            "type":"Entertainment"
        }
    ],
    "sg:postcode":"3800",
    "sg:province":"Bern",
    "sg:tags":[
        "hotels",
        "mit",
        "restaurant"
    ],
    "wof:name":"Input Finance Gmbh",
    "wof:placetype":"venue"
},
  "geometry": {"coordinates":[7.8565139771,46.6839790344],"type":"Point"}
}