{
  "type": "Feature",
  "properties": {
    "iso:country":"CH",
    "sg:address":"Dorf",
    "sg:city":"Wiggen",
    "sg:orig_category":"RESTAURANTS: TEA-ROOMS",
    "sg:phone":"+41 79 222 51 44",
    "sg:postcode":"6192",
    "sg:province":"Luzern",
    "wof:name":"B. & E. Glanzmann Rest. Rosengarten",
    "wof:placetype":"venue"
},
  "geometry": {"coordinates":[7.9097008705,46.8958778381],"type":"Point"}
}