{
  "type": "Feature",
  "properties": {
    "iso:country":"CH",
    "sg:address":"Creusets Rue Des 32",
    "sg:city":"Sion",
    "sg:orig_category":"Vermietung von Luftfahrzeugen",
    "sg:postcode":"1950",
    "sg:province":"Valais",
    "wof:name":"Gsa Groupe De Services A\u00e9ronautiques (suisse) Sa",
    "wof:placetype":"venue"
},
  "geometry": {"coordinates":[7.356921196,46.2280921936],"type":"Point"}
}