{
  "type": "Feature",
  "properties": {
    "addr:full":"R\u00f6ntgenstrasse 32a Z\u00fcrich Z\u00fcrich 8005",
    "addr:housenumber":"32a",
    "addr:postcode":"8005",
    "addr:street":"Roentgenstrasse",
    "iso:country":"CH",
    "sg:address":"R\u00f6ntgenstrasse 32a",
    "sg:city":"Z\u00fcrich",
    "sg:orig_category":"Betrieb U technische Hilfsdienste des Kultur U Unterhaltungswesens Film U Videofilmherstellung",
    "sg:phone":"+41 12734545",
    "sg:postcode":"8005",
    "sg:province":"Z\u00fcrich",
    "wof:name":"Digiton Von Allmen J\u00fcrg",
    "wof:placetype":"venue"
},
  "geometry": {"coordinates":[8.527364,47.383904],"type":"Point"}
}