{
  "type": "Feature",
  "properties": {
    "iso:country":"CH",
    "sg:address":"Fliederweg 10",
    "sg:city":"Zuchwil",
    "sg:orig_category":"Sportvereine Ballsport Basketball Sportvereine Ballsport Fussball",
    "sg:phone":"+41 71 245 38 74",
    "sg:postcode":"4528",
    "sg:province":"Solothurn",
    "wof:name":"Firmensport",
    "wof:placetype":"venue"
},
  "geometry": {"coordinates":[9.3889560699,47.4381446838],"type":"Point"}
}