{
  "type": "Feature",
  "properties": {
    "iso:country":"CH",
    "sg:address":"Rte De La Gl\u00e2ne 26",
    "sg:city":"Fribourg",
    "sg:classifiers":[
        {
            "category":"Manufacturing",
            "subcategory":"Building Materials",
            "type":"Manufacturing & Wholesale Goods"
        }
    ],
    "sg:phone":"+41 26 426 11 11",
    "sg:postcode":"1701",
    "sg:province":"Fribourg",
    "sg:tags":[
        "-",
        "machine",
        "raw",
        "engineering",
        "paper",
        "mechanical",
        "cardboard"
    ],
    "wof:name":"Polytype Ag",
    "wof:placetype":"venue"
},
  "geometry": {"coordinates":[7.143575,46.792866],"type":"Point"}
}