{
  "type": "Feature",
  "properties": {
    "iso:country":"CH",
    "sg:address":"E. Meili Frohmoos",
    "sg:city":"Hedingen",
    "sg:orig_category":"Verwertung von Milch",
    "sg:postcode":"8908",
    "sg:province":"Z\u00fcrich",
    "wof:name":"Milchproduzenten-genossenschaft Hedingen",
    "wof:placetype":"venue"
},
  "geometry": {"coordinates":[8.4537534714,47.3006286621],"type":"Point"}
}