{
  "type": "Feature",
  "properties": {
    "iso:country":"CH",
    "sg:address":"Zugerbergstrasse 33 B",
    "sg:city":"Zug",
    "sg:orig_category":"Interessenvertretungen",
    "sg:postcode":"6300",
    "sg:province":"Zug",
    "wof:name":"Stiftung Liebfrauenhof",
    "wof:placetype":"venue"
},
  "geometry": {"coordinates":[8.5210733414,47.1583213806],"type":"Point"}
}