{
  "type": "Feature",
  "properties": {
    "iso:country":"CH",
    "sg:address":"Schreinereiweg 8",
    "sg:city":"Steffisburg",
    "sg:orig_category":"Detailhandel mit Metallwaren, Anstrichmitteln, Glaswaren, Bau U Heimwerkerbedarf",
    "sg:postcode":"3612",
    "sg:province":"Bern",
    "wof:name":"Haus Der 100 Angebote Gmbh",
    "wof:placetype":"venue"
},
  "geometry": {"coordinates":[7.6328668594,46.7760353088],"type":"Point"}
}