{
  "type": "Feature",
  "properties": {
    "iso:country":"CH",
    "sg:address":"Bissen",
    "sg:city":"Gstaad",
    "sg:orig_category":"Sonstige Institutionen des Sozialwesens ohne Beherbergung",
    "sg:phone":"+41 33 744 13 42",
    "sg:postcode":"3780",
    "sg:province":"Bern",
    "wof:name":"Marlene Von Siebenthal M\u00fctterberatung",
    "wof:placetype":"venue"
},
  "geometry": {"coordinates":[7.2978401184,46.4697685242],"type":"Point"}
}