{
  "type": "Feature",
  "properties": {
    "iso:country":"CH",
    "sg:address":"Leoncavallo Via 20",
    "sg:city":"Brissago",
    "sg:orig_category":"Detailhandel mit Fleisch U Fleischwaren",
    "sg:postcode":"6614",
    "sg:province":"Ticino",
    "wof:name":"Macelleria Da Dodo Di Furger Arnoldo",
    "wof:placetype":"venue"
},
  "geometry": {"coordinates":[9.1073904037,46.2385597229],"type":"Point"}
}