{
  "type": "Feature",
  "properties": {
    "iso:country":"CH",
    "sg:address":"Constant Galeries B.- 1 1003 Lausanne. Postfach",
    "sg:city":"Lausanne",
    "sg:orig_category":"Non-Classified Establishments",
    "sg:postcode":"1003",
    "sg:province":"Vaud",
    "wof:name":"Si Le Mousquetaire, La Tour-de-peilz",
    "wof:placetype":"venue"
},
  "geometry": {"coordinates":[6.8613700867,46.4520492554],"type":"Point"}
}