{
  "type": "Feature",
  "properties": {
    "addr:full":"Marktgasse 57 8400 Winterthur. Postfach Winterthur Z\u00fcrich 8400",
    "addr:housenumber":"57",
    "addr:postcode":"8400;8400",
    "addr:street":"Marktgasse;Postfach",
    "iso:country":"CH",
    "sg:address":"Marktgasse 57 8400 Winterthur. Postfach",
    "sg:city":"Winterthur",
    "sg:orig_category":"Detailhandel mit B\u00fcchern, Zeitungen, Schreib U Papeteriewaren",
    "sg:phone":"+41 52 212 57 22",
    "sg:postcode":"8400",
    "sg:province":"Z\u00fcrich",
    "wof:name":"Buchhandlung Hoster Ag",
    "wof:placetype":"venue"
},
  "geometry": {"coordinates":[8.726861,47.499271],"type":"Point"}
}