{
  "type": "Feature",
  "properties": {
    "iso:country":"CH",
    "sg:address":"Wilerstrasse 82 9230 Flawil. Postfach",
    "sg:city":"Flawil",
    "sg:orig_category":"Allgemeiner Hoch U Tiefbau",
    "sg:postcode":"9230",
    "sg:province":"St. Gallen",
    "wof:name":"Carciola + Flury Bau Gmbh",
    "wof:placetype":"venue"
},
  "geometry": {"coordinates":[9.182377,47.415573],"type":"Point"}
}