{
  "type": "Feature",
  "properties": {
    "iso:country":"CH",
    "sg:address":"Alpbachstrasse 9-11",
    "sg:city":"Meiringen",
    "sg:orig_category":"Diskotheken, Dancings, Night Clubs Sonstige mit Sport verbundene T\u00e4tigkeiten",
    "sg:phone":"+41 33 971 18 25",
    "sg:postcode":"3860",
    "sg:province":"Bern",
    "wof:name":"Dancing Sherlock Alpenclub & Biergarten Restaurant",
    "wof:placetype":"venue"
},
  "geometry": {"coordinates":[8.1903896332,46.7255706787],"type":"Point"}
}