{
  "type": "Feature",
  "properties": {
    "iso:country":"CH",
    "sg:address":"7424",
    "sg:city":"Pr\u00e4z",
    "sg:orig_category":"Vorschulen, Kinderg\u00e4rten",
    "sg:phone":"+41 81 651 51 93",
    "sg:postcode":"7424",
    "sg:province":"Graubunden",
    "wof:name":"Kindergarten Ausserheinzenberg",
    "wof:placetype":"venue"
},
  "geometry": {"coordinates":[9.4044589996,46.7410583496],"type":"Point"}
}