{
  "type": "Feature",
  "properties": {
    "iso:country":"CH",
    "sg:address":"Haldenstrasse 3 6340 Baar. Postfach",
    "sg:city":"Baar",
    "sg:orig_category":"Herstellung von sonstigen Maschinen f\u00fcr bestimmte Verwendung",
    "sg:postcode":"6340",
    "sg:province":"Zug",
    "wof:name":"Rotograf Ag Servicearbeiten U. Dienstleistungen F\u00fcr D. Grafische- U. Papierindustrie Usw",
    "wof:placetype":"venue"
},
  "geometry": {"coordinates":[8.5370826721,47.1956443787],"type":"Point"}
}