{
  "type": "Feature",
  "properties": {
    "iso:country":"CH",
    "sg:address":"Boulevard De P\u00e9rolles 42 1700 Fribourg Case Postale 98",
    "sg:city":"Fribourg",
    "sg:orig_category":"Organisationen der Wohlfahrtspflege",
    "sg:phone":"+41 26 422 13 41",
    "sg:postcode":"1705",
    "sg:province":"Fribourg",
    "wof:name":"Pro Infirmis",
    "wof:placetype":"venue"
},
  "geometry": {"coordinates":[7.1548099518,46.7970466614],"type":"Point"}
}