{
  "type": "Feature",
  "properties": {
    "iso:country":"CH",
    "sg:address":"Maspoli Via Angelo 18",
    "sg:city":"Mendrisio",
    "sg:orig_category":"Unclassifiable Establishments",
    "sg:phone":"+41 91 630 08 26",
    "sg:postcode":"6850",
    "sg:province":"Ticino",
    "wof:name":"Holding Misa Sa",
    "wof:placetype":"venue"
},
  "geometry": {"coordinates":[8.978729248,45.8752593994],"type":"Point"}
}