{
  "type": "Feature",
  "properties": {
    "iso:country":"CH",
    "sg:address":"Dennigkofenweg 46",
    "sg:city":"Ostermundigen",
    "sg:orig_category":"Verarbeitung von Milch Verwertung von Milch",
    "sg:postcode":"3072",
    "sg:province":"Bern",
    "wof:name":"Milchverwertungsgenossenschaft Ostermundigen",
    "wof:placetype":"venue"
},
  "geometry": {"coordinates":[7.4963078499,46.942691803],"type":"Point"}
}