{
  "type": "Feature",
  "properties": {
    "iso:country":"CH",
    "sg:address":"Cantonale Via 8 6983 Magliaso. Postfach",
    "sg:city":"Magliaso",
    "sg:orig_category":"Tankstellen",
    "sg:phone":"+41 14913644",
    "sg:postcode":"6983",
    "sg:province":"Ticino",
    "wof:name":"Delio Gentile Garage",
    "wof:placetype":"venue"
},
  "geometry": {"coordinates":[8.4625597,47.3676185608],"type":"Point"}
}