{
  "type": "Feature",
  "properties": {
    "iso:country":"CH",
    "sg:address":"Winterthurerstrasse 514",
    "sg:city":"Z\u00fcrich",
    "sg:orig_category":"Arztpraxen",
    "sg:phone":"+41 13222444",
    "sg:postcode":"8051",
    "sg:province":"Z\u00fcrich",
    "wof:name":"Dr.med.gianmario Ferrazzini Spezialarzt Fmh",
    "wof:placetype":"venue"
},
  "geometry": {"coordinates":[8.571723,47.403599],"type":"Point"}
}