{
  "type": "Feature",
  "properties": {
    "iso:country":"CH",
    "sg:address":"Bernstrasse-west 58",
    "sg:city":"Suhr",
    "sg:orig_category":"Herstellung von K\u00fcchenm\u00f6beln",
    "sg:phone":"+41 62 842 71 86",
    "sg:postcode":"5034",
    "sg:province":"Aargau",
    "wof:name":"Richner K\u00fcchen + B\u00e4der",
    "wof:placetype":"venue"
},
  "geometry": {"coordinates":[8.0792255402,47.3705406189],"type":"Point"}
}