{
  "type": "Feature",
  "properties": {
    "iso:country":"CH",
    "sg:address":"Luzernerstrasse 21",
    "sg:city":"Oftringen",
    "sg:orig_category":"Handels-H\u00e4user U Gesellschaften",
    "sg:phone":"+41 62 751 83 72",
    "sg:postcode":"4665",
    "sg:province":"Aargau",
    "wof:name":"Wahli Mc Trading Gmbh",
    "wof:placetype":"venue"
},
  "geometry": {"coordinates":[7.9241838455,47.3102874756],"type":"Point"}
}