{
  "type": "Feature",
  "properties": {
    "iso:country":"CH",
    "sg:address":"Avenue Des Communes-r\u00e9unies 78",
    "sg:city":"Grand-lancy",
    "sg:orig_category":"Wirtschaftspr\u00fcfung, Steuerberatung U Treuhand",
    "sg:phone":"+41 22 794 57 57",
    "sg:postcode":"1212",
    "sg:province":"Gen\u00e8ve",
    "wof:name":"Telecompta Sa",
    "wof:placetype":"venue"
},
  "geometry": {"coordinates":[6.1225337982,46.1729736328],"type":"Point"}
}