{
  "type": "Feature",
  "properties": {
    "iso:country":"CH",
    "sg:address":"Minervastrasse 126 8032 Z\u00fcrich 32 Zust. Postfach",
    "sg:city":"Z\u00fcrich",
    "sg:orig_category":"Wohnheime",
    "sg:phone":"+41 33 251 12 25",
    "sg:postcode":"8032",
    "sg:province":"Z\u00fcrich",
    "wof:name":"Rhi Betreuungs Ag",
    "wof:placetype":"venue"
},
  "geometry": {"coordinates":[7.6972298622,46.7259750366],"type":"Point"}
}