{
  "type": "Feature",
  "properties": {
    "addr:full":"Voltastrasse 65 Z\u00fcrich Z\u00fcrich 8044",
    "addr:housenumber":"65",
    "addr:postcode":"8044",
    "addr:street":"Voltastrasse",
    "iso:country":"CH",
    "sg:address":"Voltastrasse 65",
    "sg:city":"Z\u00fcrich",
    "sg:orig_category":"Architekturb\u00fcros",
    "sg:phone":"+41 12623932",
    "sg:postcode":"8044",
    "sg:province":"Z\u00fcrich",
    "wof:name":"Nikolaus M. Hajnos Architekturb\u00fcro",
    "wof:placetype":"venue"
},
  "geometry": {"coordinates":[8.554472,47.379822],"type":"Point"}
}