{
  "type": "Feature",
  "properties": {
    "iso:country":"CH",
    "sg:address":"Neugasse 6",
    "sg:city":"Zug",
    "sg:orig_category":"RESTAURANTS: TEA-ROOMS",
    "sg:postcode":"6300",
    "sg:province":"Zug",
    "wof:name":"Ebneter W. + M. Ag",
    "wof:placetype":"venue"
},
  "geometry": {"coordinates":[8.5154285431,47.1673583984],"type":"Point"}
}