{
  "type": "Feature",
  "properties": {
    "iso:country":"CH",
    "sg:address":"Dorfstrasse 140",
    "sg:city":"Meilen",
    "sg:orig_category":"Detailhandel mit Waren verschiedener Art, Hauptrichtung Nahrungsmittel",
    "sg:phone":"+41 17931013",
    "sg:postcode":"8706",
    "sg:province":"Z\u00fcrich",
    "wof:name":"Denner Top Superdiscount",
    "wof:placetype":"venue"
},
  "geometry": {"coordinates":[8.6463489532,47.2687606812],"type":"Point"}
}