{
  "type": "Feature",
  "properties": {
    "iso:country":"CH",
    "sg:address":"M\u00fchlestrasse 16",
    "sg:city":"Kreuzlingen",
    "sg:orig_category":"Wohnheime f\u00fcr Kinder U Jugendliche",
    "sg:phone":"+41 71 671 20 86",
    "sg:postcode":"8280",
    "sg:province":"Thurgau",
    "wof:name":"Pfadiheim Alte M\u00fchle",
    "wof:placetype":"venue"
},
  "geometry": {"coordinates":[9.1568899155,47.6439628601],"type":"Point"}
}