{
  "type": "Feature",
  "properties": {
    "iso:country":"CH",
    "sg:address":"Gyrhaldenstrasse 7",
    "sg:city":"Dietikon",
    "sg:orig_category":"Grosshandel mit Erzen U Metallen",
    "sg:phone":"+41 17402525",
    "sg:postcode":"8953",
    "sg:province":"Z\u00fcrich",
    "wof:name":"Hess Metalle Ag",
    "wof:placetype":"venue"
},
  "geometry": {"coordinates":[8.3948926926,47.4021377563],"type":"Point"}
}