{
  "type": "Feature",
  "properties": {
    "iso:country":"CH",
    "sg:address":"Ryf 16",
    "sg:city":"Murten",
    "sg:orig_category":"Chemin\u00e9e- and Ofenbau",
    "sg:phone":"+41 26 670 28 48",
    "sg:postcode":"3280",
    "sg:province":"Fribourg",
    "wof:name":"C\u00e9cile D\u00fcrr Ofenbau",
    "wof:placetype":"venue"
},
  "geometry": {"coordinates":[7.114709,46.928299],"type":"Point"}
}