{
  "type": "Feature",
  "properties": {
    "iso:country":"CH",
    "sg:address":"1712",
    "sg:city":"Tafers",
    "sg:orig_category":"Landw. Genossenschaften Viehzucht",
    "sg:postcode":"1712",
    "sg:province":"Fribourg",
    "wof:name":"Viehzuchtgenossenschaft",
    "wof:placetype":"venue"
},
  "geometry": {"coordinates":[7.2608799934,46.8221817017],"type":"Point"}
}