{
  "type": "Feature",
  "properties": {
    "iso:country":"CH",
    "sg:address":"Unterdorf 321",
    "sg:city":"Wallbach",
    "sg:orig_category":"Malerei",
    "sg:phone":"+41 79 350 17 38",
    "sg:postcode":"4323",
    "sg:province":"Aargau",
    "wof:name":"Ren\u00e9 Herzog Malergesch\u00e4ft Bimbo",
    "wof:placetype":"venue"
},
  "geometry": {"coordinates":[7.9058899879,47.560131073],"type":"Point"}
}