{
  "type": "Feature",
  "properties": {
    "addr:full":"Rue De Parcouret 30 Conthey Valais 1964",
    "addr:housenumber":"30",
    "addr:postcode":"1964",
    "addr:street":"Rue De Parcouret",
    "iso:country":"CH",
    "sg:address":"Rue De Parcouret 30",
    "sg:city":"Conthey",
    "sg:orig_category":"Chemico-Technical Articles",
    "sg:phone":"+41 27 346 14 72",
    "sg:postcode":"1964",
    "sg:province":"Valais",
    "wof:name":"Oeno-tech Chimicoval",
    "wof:placetype":"venue"
},
  "geometry": {"coordinates":[7.308683,46.232445],"type":"Point"}
}