{
  "type": "Feature",
  "properties": {
    "iso:country":"CH",
    "sg:address":"Traubenweg 52",
    "sg:city":"Winterthur",
    "sg:orig_category":"Unternehmensberatung",
    "sg:postcode":"8408",
    "sg:province":"Z\u00fcrich",
    "wof:name":"Von Der Marwitz Consulting Gmbh",
    "wof:placetype":"venue"
},
  "geometry": {"coordinates":[8.5390338898,47.2808418274],"type":"Point"}
}