{
  "type": "Feature",
  "properties": {
    "iso:country":"CH",
    "sg:address":"Ch\u00e4simatte 6214 Schenkon. Postfach",
    "sg:city":"Schenkon",
    "sg:orig_category":"Herstellung von Elektromotoren, Generatoren U Transformatoren Planer f\u00fcr Energiekonzepte",
    "sg:phone":"+41 33 951 33 51",
    "sg:postcode":"6214",
    "sg:province":"Luzern",
    "wof:name":"Etron Gmbh Technische Probleml\u00f6sungen In Den Bereichen Energietechnik Usw.; Erarbeitung U. Verwirklichung",
    "wof:placetype":"venue"
},
  "geometry": {"coordinates":[8.0323543549,46.7545394897],"type":"Point"}
}