{
  "type": "Feature",
  "properties": {
    "iso:country":"CH",
    "sg:address":"Marjovet Chemin Du A7",
    "sg:city":"Echallens",
    "sg:orig_category":"Werbung",
    "sg:phone":"+41 21 881 24 19",
    "sg:postcode":"1040",
    "sg:province":"Vaud",
    "wof:name":"Buchs Jean, Promotion Et Publicit\u00e9",
    "wof:placetype":"venue"
},
  "geometry": {"coordinates":[6.6343631744,46.6408653259],"type":"Point"}
}