{
  "type": "Feature",
  "properties": {
    "iso:country":"CH",
    "sg:address":"Gr\u00fcnaustrasse 50",
    "sg:city":"Wabern",
    "sg:orig_category":"Herstellung von Konstruktionsteilen, Fertigbauteilen U Ausbauelementen aus Holz",
    "sg:postcode":"3084",
    "sg:province":"Bern",
    "wof:name":"Gsp Spanndecken Ag",
    "wof:placetype":"venue"
},
  "geometry": {"coordinates":[7.4511108398,46.9263916016],"type":"Point"}
}