{
  "type": "Feature",
  "properties": {
    "iso:country":"CH",
    "sg:address":"Gundeldingerstrasse 315 4000 Basel. Postfach",
    "sg:city":"Basel",
    "sg:orig_category":"Grosshandel mit Nahrungsmitteln, Getr\u00e4nken U Tabakwaren ohne ausgepr\u00e4gten Schwerpunkt",
    "sg:postcode":"4051",
    "sg:province":"Basel-Stadt",
    "wof:name":"Ibrahimi Nehat, Springreka",
    "wof:placetype":"venue"
},
  "geometry": {"coordinates":[7.5944190025,47.5398330688],"type":"Point"}
}