{
  "type": "Feature",
  "properties": {
    "iso:country":"CH",
    "sg:address":"Bvd Carl-vogt 43 1200 Genf. Postfach",
    "sg:city":"Gen\u00e8ve",
    "sg:orig_category":"RESTAURANTS: TEA-ROOMS",
    "sg:postcode":"1201",
    "sg:province":"Gen\u00e8ve",
    "wof:name":"Casal Sende Miguel",
    "wof:placetype":"venue"
},
  "geometry": {"coordinates":[6.1342840195,46.1990623474],"type":"Point"}
}