{
  "type": "Feature",
  "properties": {
    "iso:country":"CH",
    "sg:address":"Place Grenus 3",
    "sg:city":"Gen\u00e8ve",
    "sg:orig_category":"Detailhandel mit Antiquit\u00e4ten",
    "sg:phone":"+41 21 944 28 31",
    "sg:postcode":"1201",
    "sg:province":"Gen\u00e8ve",
    "wof:name":"Nicolas Wieland Antiquit\u00e9s",
    "wof:placetype":"venue"
},
  "geometry": {"coordinates":[6.861257,46.456055],"type":"Point"}
}