{
  "type": "Feature",
  "properties": {
    "iso:country":"CH",
    "sg:address":"Badenerstrasse 255",
    "sg:city":"Z\u00fcrich",
    "sg:orig_category":"Aktivit\u00e4t der Bankinstitute",
    "sg:phone":"+41 14510535",
    "sg:postcode":"8003",
    "sg:province":"Z\u00fcrich",
    "wof:name":"Banco Popular Espanol",
    "wof:placetype":"venue"
},
  "geometry": {"coordinates":[8.515735,47.375694],"type":"Point"}
}