{
  "type": "Feature",
  "properties": {
    "iso:country":"CH",
    "sg:address":"Kirchstrasse 6",
    "sg:city":"Oberrieden",
    "sg:orig_category":"Kunsthandel",
    "sg:phone":"+41 17201925",
    "sg:postcode":"8942",
    "sg:province":"Z\u00fcrich",
    "wof:name":"Galerie Zum Baffo Johannes K\u00e4gi",
    "wof:placetype":"venue"
},
  "geometry": {"coordinates":[8.5767936707,47.2761878967],"type":"Point"}
}