{
  "type": "Feature",
  "properties": {
    "iso:country":"CH",
    "sg:address":"3923",
    "sg:city":"T\u00f6rbel",
    "sg:orig_category":"Bauschreinerei Herstellung von Konstruktionsteilen, Fertigbauteilen U Ausbauelementen aus Holz",
    "sg:phone":"+41 27 952 18 72",
    "sg:postcode":"3923",
    "sg:province":"Valais",
    "wof:name":"Schreinerei Hosennen Vinzenz",
    "wof:placetype":"venue"
},
  "geometry": {"coordinates":[7.84998,46.23737],"type":"Point"}
}