{
  "type": "Feature",
  "properties": {
    "iso:country":"CH",
    "sg:address":"Bachtobelstrasse 3",
    "sg:city":"Horgen",
    "sg:classifiers":[
        {
            "category":"Manufacturing",
            "subcategory":"Chemicals & Compounds",
            "type":"Manufacturing & Wholesale Goods"
        }
    ],
    "sg:phone":"+41 32 913 17 53",
    "sg:postcode":"8810",
    "sg:province":"Z\u00fcrich",
    "sg:tags":[
        "industrial"
    ],
    "wof:name":"H. E. Finishing Sa",
    "wof:placetype":"venue"
},
  "geometry": {"coordinates":[6.816183,47.09948],"type":"Point"}
}