{
  "type": "Feature",
  "properties": {
    "addr:full":"B\u00fcrglenstrasse 5 3000 Bern. Postfach Bern Bern 3005",
    "addr:housenumber":"5",
    "addr:postcode":"3000;postfach;3005",
    "addr:street":"Buerglenstrasse",
    "iso:country":"CH",
    "sg:address":"B\u00fcrglenstrasse 5 3000 Bern. Postfach",
    "sg:city":"Bern",
    "sg:orig_category":"Abwasserreinigung, Abfallbeseitigung U sonstige Entsorgung",
    "sg:postcode":"3005",
    "sg:province":"Bern",
    "wof:name":"Mtb Entsorgungs Und Verwertungs Ag",
    "wof:placetype":"venue"
},
  "geometry": {"coordinates":[9.462694,47.16938],"type":"Point"}
}