{
  "type": "Feature",
  "properties": {
    "iso:country":"CH",
    "sg:address":"Grosszaun",
    "sg:city":"Netstal",
    "sg:orig_category":"Herstellung von Werkzeugen",
    "sg:phone":"+41 33 437 51 48",
    "sg:postcode":"8754",
    "sg:province":"Glarus",
    "wof:name":"Hans Berger",
    "wof:placetype":"venue"
},
  "geometry": {"coordinates":[7.6687598228,46.7968711853],"type":"Point"}
}