{
  "type": "Feature",
  "properties": {
    "iso:country":"CH",
    "sg:address":"Rue De Lausanne 64",
    "sg:city":"Renens",
    "sg:classifiers":[
        {
            "category":"Professional",
            "subcategory":"Business Services",
            "type":"Services"
        }
    ],
    "sg:phone":"+41 21 644 37 44",
    "sg:postcode":"1020",
    "sg:province":"Vaud",
    "sg:tags":[
        "industrial",
        "bookbinding"
    ],
    "wof:name":"Olbis",
    "wof:placetype":"venue"
},
  "geometry": {"coordinates":[6.6313247681,46.5420646667],"type":"Point"}
}