{
  "type": "Feature",
  "properties": {
    "iso:country":"CH",
    "sg:address":"Av. Pictet-de-rochemont 28 1200 Gen\u00e8ve. Postfach",
    "sg:city":"Gen\u00e8ve",
    "sg:orig_category":"Sonstige pers\u00f6nliche Dienstleistungen",
    "sg:phone":"+41 22 700 52 65",
    "sg:postcode":"1207",
    "sg:province":"Gen\u00e8ve",
    "wof:name":"Placibat, A. Furrer",
    "wof:placetype":"venue"
},
  "geometry": {"coordinates":[6.1627268791,46.2000617981],"type":"Point"}
}