{
  "type": "Feature",
  "properties": {
    "iso:country":"CH",
    "sg:address":"1325",
    "sg:city":"Vaulion",
    "sg:classifiers":[
        {
            "category":"Restaurant",
            "type":"Food & Drink"
        }
    ],
    "sg:phone":"+41 21 843 28 16",
    "sg:postcode":"1325",
    "sg:province":"Vaud",
    "wof:name":"Caf\u00e9 Restaurant Du Nord",
    "wof:placetype":"venue"
},
  "geometry": {"coordinates":[6.3902349472,46.6893463135],"type":"Point"}
}