{
  "type": "Feature",
  "properties": {
    "iso:country":"CH",
    "sg:address":"Lampenbergerstrasse 10",
    "sg:city":"Niederdorf",
    "sg:orig_category":"Wohnheime",
    "sg:phone":"+41 61 961 01 11",
    "sg:postcode":"4435",
    "sg:province":"Basel-Landschaft",
    "wof:name":"Wohnheim Niederdorf",
    "wof:placetype":"venue"
},
  "geometry": {"coordinates":[7.7535238266,47.4095497131],"type":"Point"}
}