{
  "type": "Feature",
  "properties": {
    "iso:country":"CH",
    "sg:address":"Fischeracherstrasse 10",
    "sg:city":"Lindau",
    "sg:orig_category":"Grosshandel mit B\u00fcromaschinen Grosshandel mit Datenverarbeitungsger\u00e4ten",
    "sg:phone":"+41 52 347 14 10",
    "sg:postcode":"8315",
    "sg:province":"Z\u00fcrich",
    "wof:name":"Nik New Informatics Know-how Ag",
    "wof:placetype":"venue"
},
  "geometry": {"coordinates":[8.6734685898,47.4416732788],"type":"Point"}
}