{
  "type": "Feature",
  "properties": {
    "iso:country":"CH",
    "sg:address":"Br\u00fcnigstrasse 100",
    "sg:city":"Meiringen",
    "sg:orig_category":"Glaserei Mechanische Werkst\u00e4tten",
    "sg:phone":"+41 33 971 68 62",
    "sg:postcode":"3860",
    "sg:province":"Bern",
    "wof:name":"Otto Willi Messersch\u00e4rferei & Glaserei",
    "wof:placetype":"venue"
},
  "geometry": {"coordinates":[8.1751298904,46.733127594],"type":"Point"}
}