{
  "type": "Feature",
  "properties": {
    "iso:country":"CH",
    "sg:address":"Rte De Gambach 13",
    "sg:city":"Fribourg",
    "sg:orig_category":"Wirtschaftspr\u00fcfung, Steuerberatung U Treuhand",
    "sg:phone":"+41 22 310 80 20",
    "sg:postcode":"1700",
    "sg:province":"Fribourg",
    "wof:name":"Macphail & Co",
    "wof:placetype":"venue"
},
  "geometry": {"coordinates":[6.1533498764,46.2022247314],"type":"Point"}
}