{
  "type": "Feature",
  "properties": {
    "iso:country":"CH",
    "sg:address":"R\u00fcnenbergerstrasse 13",
    "sg:city":"Gelterkinden",
    "sg:orig_category":"Herstellung von sonstigen elektrischen Ausr\u00fcstungen",
    "sg:phone":"+41 61 981 55 44",
    "sg:postcode":"4460",
    "sg:province":"Basel-Landschaft",
    "wof:name":"Bose Ag",
    "wof:placetype":"venue"
},
  "geometry": {"coordinates":[7.8594579697,47.4621009827],"type":"Point"}
}