{
  "type": "Feature",
  "properties": {
    "iso:country":"CH",
    "sg:address":"Sonnhalde 46b",
    "sg:city":"Wileroltigen",
    "sg:orig_category":"Sanit\u00e4r U Heizungsinstallation",
    "sg:phone":"+41 31 755 65 21",
    "sg:postcode":"3207",
    "sg:province":"Bern",
    "wof:name":"Hans-peter B\u00fchlmann Heizungen",
    "wof:placetype":"venue"
},
  "geometry": {"coordinates":[7.2387590408,46.9714736938],"type":"Point"}
}