{
  "type": "Feature",
  "properties": {
    "iso:country":"CH",
    "sg:address":"Dorfstrasse 13",
    "sg:city":"Algetshausen",
    "sg:classifiers":[
        {
            "category":"Banks & Credit Unions",
            "subcategory":"Bank",
            "type":"Services"
        }
    ],
    "sg:phone":"+41 4173518908",
    "sg:postcode":"9249",
    "sg:province":"St. Gallen",
    "wof:name":"Bank In Niederuzwil",
    "wof:placetype":"venue"
},
  "geometry": {"coordinates":[9.106844,47.447571],"type":"Point"}
}