{
  "type": "Feature",
  "properties": {
    "iso:country":"CH",
    "sg:address":"Haselgasse 40",
    "sg:city":"R\u00fcdlingen",
    "sg:classifiers":[
        {
            "category":"Restaurant",
            "type":"Food & Drink"
        }
    ],
    "sg:phone":"+41 18670141",
    "sg:postcode":"8455",
    "sg:province":"Schaffhausen",
    "wof:name":"Restaurant Sternen",
    "wof:placetype":"venue"
},
  "geometry": {"coordinates":[8.5724420547,47.5792541504],"type":"Point"}
}