{
  "type": "Feature",
  "properties": {
    "iso:country":"CH",
    "sg:address":"Hohlstrasse 219",
    "sg:city":"Z\u00fcrich",
    "sg:orig_category":"Geb\u00e4ude, Wohnungsreinigung Reinigungsgewerbe",
    "sg:phone":"+41 12910954",
    "sg:postcode":"8004",
    "sg:province":"Z\u00fcrich",
    "wof:name":"Frischknecht & Co",
    "wof:placetype":"venue"
},
  "geometry": {"coordinates":[8.5162935257,47.3817024231],"type":"Point"}
}