{
  "type": "Feature",
  "properties": {
    "iso:country":"CH",
    "sg:address":"L\u00f6berenstrasse 35",
    "sg:city":"Zug",
    "sg:orig_category":"Non-Classified Establishments",
    "sg:postcode":"6300",
    "sg:province":"Zug",
    "wof:name":"Techno-finanz-holding Ag",
    "wof:placetype":"venue"
},
  "geometry": {"coordinates":[8.5215578079,47.1705780029],"type":"Point"}
}