{
  "type": "Feature",
  "properties": {
    "iso:country":"CH",
    "sg:address":"Kreuzgasse 8",
    "sg:city":"M\u00fcnchenbuchsee",
    "sg:orig_category":"Fotografische Ateliers",
    "sg:phone":"+41 31 869 53 53",
    "sg:postcode":"3053",
    "sg:province":"Bern",
    "wof:name":"Markus Niederhauser Atelier F\u00fcr Werbefoto",
    "wof:placetype":"venue"
},
  "geometry": {"coordinates":[7.4527521133,47.018497467],"type":"Point"}
}