{
  "type": "Feature",
  "properties": {
    "iso:country":"CH",
    "sg:address":"M\u00fcnchhaldenstrasse 19",
    "sg:city":"Z\u00fcrich",
    "sg:orig_category":"Architekturb\u00fcros",
    "sg:phone":"+41 31 352 90 66",
    "sg:postcode":"8008",
    "sg:province":"Z\u00fcrich",
    "wof:name":"Franz Rutishauser Architekturb\u00fcro",
    "wof:placetype":"venue"
},
  "geometry": {"coordinates":[7.456179,46.947399],"type":"Point"}
}