{
  "type": "Feature",
  "properties": {
    "iso:country":"CH",
    "sg:address":"1978",
    "sg:city":"Lens",
    "sg:orig_category":"Instandhaltung U Reparatur von Automobilen",
    "sg:phone":"+41 27 483 43 00",
    "sg:postcode":"1978",
    "sg:province":"Valais",
    "wof:name":"Garage Et Carrosserie De La D\u00e9l\u00e8ge, J.-c. Et J.-l. Mabillard.",
    "wof:placetype":"venue"
},
  "geometry": {"coordinates":[7.4485402107,46.2786102295],"type":"Point"}
}