{
  "type": "Feature",
  "properties": {
    "iso:country":"CH",
    "sg:address":"Chasa 9",
    "sg:city":"Tschlin",
    "sg:orig_category":"Reiseb\u00fcros U Reiseveranstalter",
    "sg:phone":"+41 81 866 32 44",
    "sg:postcode":"7559",
    "sg:province":"Graubunden",
    "wof:name":"Gustin Annina",
    "wof:placetype":"venue"
},
  "geometry": {"coordinates":[10.4237651825,46.8686981201],"type":"Point"}
}