{
  "type": "Feature",
  "properties": {
    "iso:country":"CH",
    "sg:address":"Rue De Martheray 8",
    "sg:city":"Begnins",
    "sg:orig_category":"Kosmetikinstitute",
    "sg:phone":"+41 22 366 24 41",
    "sg:postcode":"1268",
    "sg:province":"Vaud",
    "wof:name":"Hannelore Horvath Institut De Beaut\u00e9 F\u00e9mina",
    "wof:placetype":"venue"
},
  "geometry": {"coordinates":[6.2502551079,46.4408988953],"type":"Point"}
}