{
  "type": "Feature",
  "properties": {
    "iso:country":"CH",
    "sg:address":"St\u00e4dtlistrasse 25 7130 Ilanz. Postfach",
    "sg:city":"Ilanz",
    "sg:classifiers":[
        {
            "category":"Restaurant",
            "type":"Food & Drink"
        }
    ],
    "sg:phone":"+41 81 925 35 90",
    "sg:postcode":"7130",
    "sg:province":"Graubunden",
    "wof:name":"Pizzeria Obertor",
    "wof:placetype":"venue"
},
  "geometry": {"coordinates":[9.2036008835,46.7727432251],"type":"Point"}
}