{
  "type": "Feature",
  "properties": {
    "iso:country":"CH",
    "sg:address":"Gschwaderstrasse 70",
    "sg:city":"Uster",
    "sg:orig_category":"Primarschulen",
    "sg:phone":"+41 19413573",
    "sg:postcode":"8610",
    "sg:province":"Z\u00fcrich",
    "wof:name":"Primarschule Gschwader",
    "wof:placetype":"venue"
},
  "geometry": {"coordinates":[8.7172489166,47.361000061],"type":"Point"}
}