{
  "type": "Feature",
  "properties": {
    "iso:country":"CH",
    "sg:address":"Wasserturmplatz 9",
    "sg:city":"Liestal",
    "sg:orig_category":"Unclassifiable Establishments",
    "sg:postcode":"4410",
    "sg:province":"Basel-Landschaft",
    "wof:name":"Str\u00fcbin Ag, Drogerie Liestal",
    "wof:placetype":"venue"
},
  "geometry": {"coordinates":[7.7345280647,47.482635498],"type":"Point"}
}