{
  "type": "Feature",
  "properties": {
    "iso:country":"CH",
    "sg:address":"Kasinostrasse 17",
    "sg:city":"Aarau",
    "sg:orig_category":"Detailhandel mit Bekleidung Grosshandel mit Textilien",
    "sg:phone":"+41 62 823 02 02",
    "sg:postcode":"5000",
    "sg:province":"Aargau",
    "wof:name":"Von D\u00e4niken Mode",
    "wof:placetype":"venue"
},
  "geometry": {"coordinates":[8.046782,47.392822],"type":"Point"}
}