{
  "type": "Feature",
  "properties": {
    "iso:country":"CH",
    "sg:address":"Ebnatstrasse 145 8207 Schaffhausen. Postfach 1139",
    "sg:city":"Schaffhausen",
    "sg:orig_category":"Personenbef\u00f6rderung im Linienverkehr zu Land",
    "sg:phone":"+41 52 644 20 20",
    "sg:postcode":"8207",
    "sg:province":"Schaffhausen",
    "wof:name":"Regionale Verkehrsbetriebe Schaffhausen Rvsh",
    "wof:placetype":"venue"
},
  "geometry": {"coordinates":[8.6555652618,47.7126998901],"type":"Point"}
}