{
  "type": "Feature",
  "properties": {
    "iso:country":"CH",
    "sg:address":"Via Cantonale",
    "sg:city":"Mezzovico",
    "sg:orig_category":"Sicherheitsdienste",
    "sg:phone":"+41 32 913 70 30",
    "sg:postcode":"6805",
    "sg:province":"Ticino",
    "wof:name":"Securitas Ag Schweiz. Bewachungsgesellschaft Agence De La Chaux-de-fonds",
    "wof:placetype":"venue"
},
  "geometry": {"coordinates":[6.8220567703,47.1016960144],"type":"Point"}
}