{
  "type": "Feature",
  "properties": {
    "iso:country":"CH",
    "sg:address":"Seestrasse 120 8266 Steckborn. Postfach",
    "sg:city":"Steckborn",
    "sg:orig_category":"Sonstiger Grosshandel",
    "sg:postcode":"8266",
    "sg:province":"Thurgau",
    "wof:name":"Artocelli Accessoires Gmbh",
    "wof:placetype":"venue"
},
  "geometry": {"coordinates":[8.3484458923,47.3471107483],"type":"Point"}
}