{
  "type": "Feature",
  "properties": {
    "iso:country":"CH",
    "sg:address":"Horben",
    "sg:city":"Eggiwil",
    "sg:orig_category":"Wohnheime",
    "sg:postcode":"3537",
    "sg:province":"Bern",
    "wof:name":"Alterswohnungen Eggiwil",
    "wof:placetype":"venue"
},
  "geometry": {"coordinates":[7.7732467651,46.8993186951],"type":"Point"}
}