{
  "type": "Feature",
  "properties": {
    "addr:full":"Route De Courgenay 37 Alle Jura 2942",
    "addr:housenumber":"37",
    "addr:postcode":"2942",
    "addr:street":"Route De Courgenay;Jura",
    "iso:country":"CH",
    "sg:address":"Route De Courgenay 37",
    "sg:city":"Alle",
    "sg:classifiers":[
        {
            "category":"Shopping Center",
            "type":"Public Place"
        }
    ],
    "sg:phone":"+41 32 471 14 14",
    "sg:postcode":"2942",
    "sg:province":"Jura",
    "sg:tags":[
        "case",
        "clock"
    ],
    "wof:name":"Mrp S.a.",
    "wof:placetype":"venue"
},
  "geometry": {"coordinates":[7.124342,47.421486],"type":"Point"}
}