{
  "type": "Feature",
  "properties": {
    "iso:country":"CH",
    "sg:address":"Brauerstrasse 29 8004 Z\u00fcrich. Postfach",
    "sg:city":"Z\u00fcrich",
    "sg:orig_category":"Erbringung von Dienstleistungen f\u00fcr Unternehmen",
    "sg:postcode":"8001",
    "sg:province":"Z\u00fcrich",
    "wof:name":"Annunziata Ag Generaldienstleistungsunternehmen Im Bereich Des Modedesigns. Trends Im Bezug Auf Kleider Usw.; Abkl\u00e4rung",
    "wof:placetype":"venue"
},
  "geometry": {"coordinates":[8.5272502899,47.3775863647],"type":"Point"}
}