{
  "type": "Feature",
  "properties": {
    "iso:country":"CH",
    "sg:address":"R\u00f6schenzerstrasse 19 4053 Basel. Postfach 3353",
    "sg:city":"Basel",
    "sg:orig_category":"Grosshandel mit Kaffee, Tee, Kakao U Gew\u00fcrzen",
    "sg:phone":"+41 22 906 48 86",
    "sg:postcode":"4002",
    "sg:province":"Basel-Stadt",
    "wof:name":"Kaenzig Pierre & Co",
    "wof:placetype":"venue"
},
  "geometry": {"coordinates":[6.1453919411,46.2065200806],"type":"Point"}
}