{
  "type": "Feature",
  "properties": {
    "iso:country":"CH",
    "sg:address":"Riet 9651 Ennetb\u00fchl. Postfach",
    "sg:city":"Ennetb\u00fchl",
    "sg:orig_category":"Wirtschaftspr\u00fcfung, Steuerberatung U Treuhand",
    "sg:postcode":"9651",
    "sg:province":"St. Gallen",
    "wof:name":"Kamber - Fibu Treuhandunternehmung",
    "wof:placetype":"venue"
},
  "geometry": {"coordinates":[9.2110414505,47.2402038574],"type":"Point"}
}