{
  "type": "Feature",
  "properties": {
    "iso:country":"CH",
    "sg:address":"Via Pretorio 1",
    "sg:city":"Lugano",
    "sg:orig_category":"Sonstiger Grosshandel",
    "sg:phone":"+41 91 923 32 42",
    "sg:postcode":"6900",
    "sg:province":"Ticino",
    "wof:name":"La Brianzola Sa",
    "wof:placetype":"venue"
},
  "geometry": {"coordinates":[8.951335907,46.0052375793],"type":"Point"}
}