{
  "type": "Feature",
  "properties": {
    "addr:full":"Rebgasse 28 Basel Basel-Stadt 4058",
    "addr:housenumber":"28",
    "addr:postcode":"4058",
    "addr:street":"Rebgasse",
    "iso:country":"CH",
    "sg:address":"Rebgasse 28",
    "sg:city":"Basel",
    "sg:orig_category":"Arztpraxen",
    "sg:phone":"+41 61 690 98 68",
    "sg:postcode":"4058",
    "sg:province":"Basel-Stadt",
    "wof:name":"Dr.med.reto Planta Spezialarzt",
    "wof:placetype":"venue"
},
  "geometry": {"coordinates":[7.594569,47.560318],"type":"Point"}
}