{
  "type": "Feature",
  "properties": {
    "iso:country":"CH",
    "sg:address":"Bundesplatz 14",
    "sg:city":"Luzern",
    "sg:orig_category":"Gesundheitswesen",
    "sg:postcode":"6003",
    "sg:province":"Luzern",
    "wof:name":"Voegelin Dr. Med. Roger, Allgemeine Medizin Fmh",
    "wof:placetype":"venue"
},
  "geometry": {"coordinates":[9.3889255524,47.3908195496],"type":"Point"}
}