{
  "type": "Feature",
  "properties": {
    "iso:country":"CH",
    "sg:address":"Glatthaldestrasse 9230 Flawil. Postfach",
    "sg:city":"Flawil",
    "sg:orig_category":"Detailhandel mit Fahrr\u00e4dern",
    "sg:phone":"+41 71 393 63 63",
    "sg:postcode":"9230",
    "sg:province":"St. Gallen",
    "wof:name":"Jakob Holenstein Velos",
    "wof:placetype":"venue"
},
  "geometry": {"coordinates":[9.2029075623,47.4109535217],"type":"Point"}
}