{
  "type": "Feature",
  "properties": {
    "iso:country":"CH",
    "sg:address":"Geisshof.",
    "sg:city":"Unterlunkhofen",
    "sg:orig_category":"Grosshandel mit lebenden Tieren",
    "sg:postcode":"8918",
    "sg:province":"Aargau",
    "wof:name":"R\u00fcttimann Johann.",
    "wof:placetype":"venue"
},
  "geometry": {"coordinates":[8.3569450378,47.3318977356],"type":"Point"}
}