{
  "type": "Feature",
  "properties": {
    "iso:country":"CH",
    "sg:address":"Salmenweg 9",
    "sg:city":"Basel",
    "sg:orig_category":"G\u00fcterbef\u00f6rderung im Strassenverkehr",
    "sg:postcode":"4019",
    "sg:province":"Basel-Stadt",
    "wof:name":"Khd Transporte, Dombrowski K.-h.",
    "wof:placetype":"venue"
},
  "geometry": {"coordinates":[7.5941958427,47.5814247131],"type":"Point"}
}