{
  "type": "Feature",
  "properties": {
    "iso:country":"CH",
    "sg:address":"Gutstrasse 73 8055 Z\u00fcrich. Postfach 880",
    "sg:city":"Z\u00fcrich",
    "sg:orig_category":"Markt U Meinungsforschung",
    "sg:phone":"+41 14666768",
    "sg:postcode":"8055",
    "sg:province":"Z\u00fcrich",
    "wof:name":"Catapult Ag",
    "wof:placetype":"venue"
},
  "geometry": {"coordinates":[8.5072793961,47.3712768555],"type":"Point"}
}