{
  "type": "Feature",
  "properties": {
    "iso:country":"CH",
    "sg:address":"Tivoli",
    "sg:city":"Spreitenbach",
    "sg:orig_category":"Versicherungsgewerbe",
    "sg:phone":"+41 56 417 90 40",
    "sg:postcode":"8957",
    "sg:province":"Aargau",
    "wof:name":"Coop Versicherung",
    "wof:placetype":"venue"
},
  "geometry": {"coordinates":[8.3656835556,47.4180450439],"type":"Point"}
}