{
  "type": "Feature",
  "properties": {
    "iso:country":"CH",
    "sg:address":"Route Du Village 40 1807 Blonay Case Postale 50",
    "sg:city":"Blonay",
    "sg:orig_category":"Instandhaltung U Reparatur von Automobilen",
    "sg:phone":"+41 79 621 91 32",
    "sg:postcode":"1807",
    "sg:province":"Vaud",
    "wof:name":"Garage De L'avenir Blonay, Pedrini Christian",
    "wof:placetype":"venue"
},
  "geometry": {"coordinates":[6.8946580887,46.4653396606],"type":"Point"}
}