{
  "type": "Feature",
  "properties": {
    "iso:country":"CH",
    "sg:address":"Rue Des Sugiez 20",
    "sg:city":"Marin-centre",
    "sg:orig_category":"Sportvereine Ballsport Tischtennis",
    "sg:phone":"+41 32 753 72 25",
    "sg:postcode":"2074",
    "sg:province":"Neuch\u00e2tel",
    "wof:name":"Ctt Suchard",
    "wof:placetype":"venue"
},
  "geometry": {"coordinates":[7.0171442032,47.0089950562],"type":"Point"}
}