{
  "type": "Feature",
  "properties": {
    "iso:country":"CH",
    "sg:address":"Lotzwilstrasse 14",
    "sg:city":"Langenthal",
    "sg:orig_category":"Versicherungen Generalagenturen",
    "sg:phone":"+41 62 922 02 36",
    "sg:postcode":"4900",
    "sg:province":"Bern",
    "wof:name":"National-versicherungen Generalagentur",
    "wof:placetype":"venue"
},
  "geometry": {"coordinates":[7.7858982086,47.2100067139],"type":"Point"}
}