{
  "type": "Feature",
  "properties": {
    "iso:country":"CH",
    "sg:address":"Aehrenweg 14 8405 Seen. Postfach",
    "sg:city":"Seen",
    "sg:orig_category":"Wirtschaftspr\u00fcfung, Steuerberatung U Treuhand",
    "sg:postcode":"8405",
    "sg:province":"Z\u00fcrich",
    "wof:name":"Hochholdinger J., Treuhand Und Edv Buchhaltungen, Bes. Abschl\u00fcsse U. Beratung. Edv-beratung",
    "wof:placetype":"venue"
},
  "geometry": {"coordinates":[8.7607898712,47.4797210693],"type":"Point"}
}