{
  "type": "Feature",
  "properties": {
    "iso:country":"CH",
    "sg:address":"Risi 1",
    "sg:city":"Netstal",
    "sg:classifiers":[
        {
            "category":"Restaurant",
            "type":"Food & Drink"
        }
    ],
    "sg:phone":"+41 55 640 11 66",
    "sg:postcode":"8754",
    "sg:province":"Glarus",
    "wof:name":"St.fridolin's Pub",
    "wof:placetype":"venue"
},
  "geometry": {"coordinates":[9.051856041,47.0587997437],"type":"Point"}
}