{
  "type": "Feature",
  "properties": {
    "iso:country":"CH",
    "sg:address":"3537",
    "sg:city":"Eggiwil",
    "sg:classifiers":[
        {
            "category":"Education",
            "subcategory":"Vocational School",
            "type":"Public Place"
        }
    ],
    "sg:postcode":"3537",
    "sg:province":"Bern",
    "sg:tags":[
        "koch-",
        "haushaltschulen"
    ],
    "wof:name":"Haushaltungsschule",
    "wof:placetype":"venue"
},
  "geometry": {"coordinates":[7.7429900169,46.8556518555],"type":"Point"}
}