{
  "type": "Feature",
  "properties": {
    "iso:country":"CH",
    "sg:address":"Nidaugasse 54 2500 Biel/bienne. Postfach",
    "sg:city":"Biel/bienne",
    "sg:orig_category":"Herstellung von Kakao, Schokoladeerzeugnissen U Zuckerwaren",
    "sg:phone":"+41 32 323 26 50",
    "sg:postcode":"2502",
    "sg:province":"Bern",
    "wof:name":"Schneider-kr\u00e4henb\u00fchl, Hans",
    "wof:placetype":"venue"
},
  "geometry": {"coordinates":[7.2465519905,47.138381958],"type":"Point"}
}