{
  "type": "Feature",
  "properties": {
    "iso:country":"CH",
    "sg:address":"Moserstrasse 24",
    "sg:city":"Bern",
    "sg:classifiers":[
        {
            "category":"Internet Cafe",
            "subcategory":"None",
            "type":"Food & Drink"
        }
    ],
    "sg:postcode":"3014",
    "sg:province":"Bern",
    "sg:tags":[
        "webdesign",
        "provider"
    ],
    "wof:name":"Akkurat Gmbh Kommunikation & Design",
    "wof:placetype":"venue"
},
  "geometry": {"coordinates":[8.8210954666,47.2270126343],"type":"Point"}
}