{
  "type": "Feature",
  "properties": {
    "iso:country":"CH",
    "sg:address":"Ebringerstrasse",
    "sg:city":"Thayngen",
    "sg:orig_category":"Zoll- and Grenzb\u00fcros",
    "sg:phone":"+41 52 649 31 79",
    "sg:postcode":"8240",
    "sg:province":"Schaffhausen",
    "wof:name":"Eidg. Zollverwaltung Zollamt",
    "wof:placetype":"venue"
},
  "geometry": {"coordinates":[8.7195310593,47.7473373413],"type":"Point"}
}