{
  "type": "Feature",
  "properties": {
    "iso:country":"CH",
    "sg:address":"Lindenstrasse 7",
    "sg:city":"R\u00fcmlang",
    "sg:orig_category":"Detailhandel mit Brillen U anderen Sehhilfen Fachdetailhandel in Verkaufsr\u00e4umen",
    "sg:phone":"+41 18173064",
    "sg:postcode":"8153",
    "sg:province":"Z\u00fcrich",
    "wof:name":"Reva Optik Gmbh",
    "wof:placetype":"venue"
},
  "geometry": {"coordinates":[8.531472,47.450562],"type":"Point"}
}