{
  "type": "Feature",
  "properties": {
    "addr:full":"K\u00fcfergasse 3 Jens Bern 2565",
    "addr:housenumber":"3",
    "addr:postcode":"2565",
    "addr:street":"Kuefergasse",
    "iso:country":"CH",
    "sg:address":"K\u00fcfergasse 3",
    "sg:city":"Jens",
    "sg:orig_category":"Bauschreinerei Herstellung von Konstruktionsteilen, Fertigbauteilen U Ausbauelementen aus Holz",
    "sg:phone":"+41 71 385 98 88",
    "sg:postcode":"2565",
    "sg:province":"Bern",
    "wof:name":"Lehmann Niklaus",
    "wof:placetype":"venue"
},
  "geometry": {"coordinates":[9.261285,47.416988],"type":"Point"}
}