{
  "type": "Feature",
  "properties": {
    "iso:country":"CH",
    "sg:address":"Le Jeanbrenin",
    "sg:city":"Corg\u00e9mont",
    "sg:orig_category":"Haltung von Rindern",
    "sg:postcode":"2606",
    "sg:province":"Bern",
    "wof:name":"Association Coop\u00e9rative Pour L'\u00e9levage Du B\u00e9tail De La Race Tachet\u00e9e, Jeanbrenin-la Tanne",
    "wof:placetype":"venue"
},
  "geometry": {"coordinates":[7.1435952187,47.2124176025],"type":"Point"}
}