{
  "type": "Feature",
  "properties": {
    "iso:country":"CH",
    "sg:address":"Eichenstrasse 30",
    "sg:city":"Reussb\u00fchl",
    "sg:orig_category":"Rechtsberatung",
    "sg:postcode":"6015",
    "sg:province":"Luzern",
    "wof:name":"Edita Rechts Und Treuhandpraxis Melliger",
    "wof:placetype":"venue"
},
  "geometry": {"coordinates":[8.2759065628,47.0598373413],"type":"Point"}
}