{
  "type": "Feature",
  "properties": {
    "iso:country":"CH",
    "sg:address":"Corso Elvezia 4",
    "sg:city":"Lugano",
    "sg:orig_category":"Advokaturb\u00fcros",
    "sg:phone":"+41 91 924 21 85",
    "sg:postcode":"6900",
    "sg:province":"Ticino",
    "wof:name":"Roberto Badaracco Studio Legale",
    "wof:placetype":"venue"
},
  "geometry": {"coordinates":[8.955799,46.006458],"type":"Point"}
}