{
  "type": "Feature",
  "properties": {
    "iso:country":"CH",
    "sg:address":"Badenerstrasse 668",
    "sg:city":"Z\u00fcrich",
    "sg:orig_category":"Detailhandel mit Waren verschiedener Art, Hauptrichtung Nahrungsmittel Fachdetailhandel mit Nahrungs",
    "sg:phone":"+41 14311506",
    "sg:postcode":"8048",
    "sg:province":"Z\u00fcrich",
    "wof:name":"Vincenzo Serratore Delikatessen & Teigwaren",
    "wof:placetype":"venue"
},
  "geometry": {"coordinates":[8.4871711731,47.3876991272],"type":"Point"}
}