{
  "type": "Feature",
  "properties": {
    "iso:country":"CH",
    "sg:address":"Vorstadt 3a",
    "sg:city":"Boswil",
    "sg:orig_category":"Unclassifiable Establishments",
    "sg:postcode":"5623",
    "sg:province":"Aargau",
    "wof:name":"Jorge Gmbh",
    "wof:placetype":"venue"
},
  "geometry": {"coordinates":[8.3155736923,47.2987556458],"type":"Point"}
}