{
  "type": "Feature",
  "properties": {
    "iso:country":"CH",
    "sg:address":"Vevey Rue De 27",
    "sg:city":"Bulle",
    "sg:orig_category":"RESTAURANTS: TEA-ROOMS",
    "sg:postcode":"1630",
    "sg:province":"Fribourg",
    "wof:name":"Le Triangle D'or, Charri\u00e8re Herv\u00e9",
    "wof:placetype":"venue"
},
  "geometry": {"coordinates":[7.0573811531,46.6186027527],"type":"Point"}
}