{
  "type": "Feature",
  "properties": {
    "iso:country":"CH",
    "sg:address":"Planche-sup\u00e9rieure 18",
    "sg:city":"Fribourg",
    "sg:orig_category":"Grosshandel mit sonstigen Maschinen U Ausr\u00fcstungen f\u00fcr Industrie, Handel U Schiffahrt",
    "sg:phone":"+41 26 322 30 48",
    "sg:postcode":"1700",
    "sg:province":"Fribourg",
    "wof:name":"Gobet Michel",
    "wof:placetype":"venue"
},
  "geometry": {"coordinates":[7.1624932289,46.8028411865],"type":"Point"}
}