{
  "type": "Feature",
  "properties": {
    "iso:country":"CH",
    "sg:address":"1978",
    "sg:city":"Lens",
    "sg:orig_category":"Unclassifiable Establishments",
    "sg:postcode":"1978",
    "sg:province":"Valais",
    "wof:name":"Si T\u00e9l\u00e9r\u00e9sidence Holidays Crans No 2 C Sa",
    "wof:placetype":"venue"
},
  "geometry": {"coordinates":[7.4485402107,46.2786102295],"type":"Point"}
}