{
  "type": "Feature",
  "properties": {
    "iso:country":"CH",
    "sg:address":"Riedstrasse 6",
    "sg:city":"Dietikon",
    "sg:orig_category":"Detailhandel mit Bekleidung Grosshandel mit Bekleidung",
    "sg:phone":"+41 56 430 12 61",
    "sg:postcode":"8953",
    "sg:province":"Z\u00fcrich",
    "wof:name":"Cocoon Meier A.",
    "wof:placetype":"venue"
},
  "geometry": {"coordinates":[8.394169,47.419655],"type":"Point"}
}