{
  "type": "Feature",
  "properties": {
    "iso:country":"CH",
    "sg:address":"B\u00e4lliz 52",
    "sg:city":"Thun",
    "sg:orig_category":"Chiropraktik",
    "sg:phone":"+41 33 223 38 34",
    "sg:postcode":"3600",
    "sg:province":"Bern",
    "wof:name":"Dr.daniel Caron Chiropraktor",
    "wof:placetype":"venue"
},
  "geometry": {"coordinates":[7.628051,46.757812],"type":"Point"}
}