{
  "type": "Feature",
  "properties": {
    "iso:country":"CH",
    "sg:address":"Bankgasse 10",
    "sg:city":"St.gallen",
    "sg:classifiers":[
        {
            "category":"Restaurant",
            "type":"Food & Drink"
        }
    ],
    "sg:phone":"+41 71 230 09 83",
    "sg:postcode":"9000",
    "sg:province":"St. Gallen",
    "sg:tags":[
        "tea-rooms",
        "restaurants"
    ],
    "wof:name":"Restaurant, Weinstube & Bistro Neubad, Robert Burri & Maria Lutz Burri",
    "wof:placetype":"venue"
},
  "geometry": {"coordinates":[9.3753623962,47.4232749939],"type":"Point"}
}