{
  "type": "Feature",
  "properties": {
    "iso:country":"CH",
    "sg:address":"Lehenstrasse 11",
    "sg:city":"Egerkingen",
    "sg:orig_category":"Grosshandel mit Eisenwaren sowie Installationsbedarf f\u00fcr Gas, Wasser U Heizung Herstellung von \u00d6fen ",
    "sg:phone":"+41 62 398 26 81",
    "sg:postcode":"4622",
    "sg:province":"Solothurn",
    "wof:name":"Studer Feuerungstechnik Ag",
    "wof:placetype":"venue"
},
  "geometry": {"coordinates":[7.8018159866,47.3264160156],"type":"Point"}
}