{
  "type": "Feature",
  "properties": {
    "iso:country":"CH",
    "sg:address":"1945",
    "sg:city":"Liddes",
    "sg:classifiers":[
        {
            "category":"Travel",
            "subcategory":"Hotels & Motels",
            "type":"Entertainment"
        }
    ],
    "sg:phone":"+41 27 783 13 02",
    "sg:postcode":"1945",
    "sg:province":"Valais",
    "sg:tags":[
        "hotels",
        "mit",
        "restaurant"
    ],
    "wof:name":"H\u00f4tel Grand-st-bernard",
    "wof:placetype":"venue"
},
  "geometry": {"coordinates":[7.1862039566,45.9914665222],"type":"Point"}
}