{
  "type": "Feature",
  "properties": {
    "iso:country":"CH",
    "sg:address":"Industriestrasse 31 6300 Zug. Postfach 420",
    "sg:city":"Zug",
    "sg:orig_category":"Grosshandel mit chemischen Erzeugnissen Sonstiger Grosshandel",
    "sg:phone":"+41 41 711 38 21",
    "sg:postcode":"6301",
    "sg:province":"Zug",
    "wof:name":"Chrisenta Ag",
    "wof:placetype":"venue"
},
  "geometry": {"coordinates":[8.5194377899,47.1763191223],"type":"Point"}
}