{
  "type": "Feature",
  "properties": {
    "iso:country":"CH",
    "sg:address":"Eschenring 3 6300 Zug. Postfach 2407",
    "sg:city":"Zug",
    "sg:orig_category":"Handelsvermittlung U Grosshandel",
    "sg:phone":"+41 71 455 27 44",
    "sg:postcode":"6304",
    "sg:province":"Zug",
    "wof:name":"Agrosan Gottfried Sittner Import-export",
    "wof:placetype":"venue"
},
  "geometry": {"coordinates":[9.4044294357,47.4864997864],"type":"Point"}
}