{
  "type": "Feature",
  "properties": {
    "iso:country":"CH",
    "sg:address":"Route De Denges 27 1027 Lonay. Postfach",
    "sg:city":"Lonay",
    "sg:orig_category":"Grosshandel mit Obst U Gem\u00fcse",
    "sg:postcode":"1027",
    "sg:province":"Vaud",
    "wof:name":"Soleil D'italie, Tlili",
    "wof:placetype":"venue"
},
  "geometry": {"coordinates":[6.5286979675,46.5278892517],"type":"Point"}
}