{
  "type": "Feature",
  "properties": {
    "addr:full":"Route Du Signal 2 Orbe Vaud 1350",
    "addr:housenumber":"2",
    "addr:postcode":"1350",
    "addr:street":"Route Du Signal",
    "iso:country":"CH",
    "sg:address":"Route Du Signal 2",
    "sg:city":"Orbe",
    "sg:orig_category":"Autospenglereien",
    "sg:phone":"+41 17252761",
    "sg:postcode":"1350",
    "sg:province":"Vaud",
    "wof:name":"Armin Grob Autospenglerei",
    "wof:placetype":"venue"
},
  "geometry": {"coordinates":[8.601075,47.257687],"type":"Point"}
}