{
  "type": "Feature",
  "properties": {
    "iso:country":"CH",
    "sg:address":"Sonnenbergstrasse 3",
    "sg:city":"Schwerzenbach",
    "sg:orig_category":"Hardwareberatung Softwareentwicklung U beratung",
    "sg:phone":"+41 18254275",
    "sg:postcode":"8603",
    "sg:province":"Z\u00fcrich",
    "wof:name":"Emmel It Gmbh",
    "wof:placetype":"venue"
},
  "geometry": {"coordinates":[8.6498355865,47.3836975098],"type":"Point"}
}