{
  "type": "Feature",
  "properties": {
    "iso:country":"CH",
    "sg:address":"Hauptstrasse 32",
    "sg:city":"Wagenhausen",
    "sg:classifiers":[
        {
            "category":"Manufacturing",
            "subcategory":"Rubber & Plastics",
            "type":"Manufacturing & Wholesale Goods"
        }
    ],
    "sg:phone":"+41 91 608 19 51",
    "sg:postcode":"8259",
    "sg:province":"Thurgau",
    "sg:tags":[
        "injection",
        "part",
        "moulded"
    ],
    "wof:name":"Repo Sa Croglio",
    "wof:placetype":"venue"
},
  "geometry": {"coordinates":[8.8205404282,45.990020752],"type":"Point"}
}