{
  "type": "Feature",
  "properties": {
    "iso:country":"CH",
    "sg:address":"Romanshorner Strasse 117",
    "sg:city":"Kreuzlingen",
    "sg:orig_category":"Unternehmensberatung",
    "sg:phone":"+41 55 210 71 63",
    "sg:postcode":"8280",
    "sg:province":"Thurgau",
    "wof:name":"Amesa Ag Unternehmensberatung",
    "wof:placetype":"venue"
},
  "geometry": {"coordinates":[9.1942596436,47.6400909424],"type":"Point"}
}