{
  "type": "Feature",
  "properties": {
    "iso:country":"CH",
    "sg:address":"Luegstrasse 2",
    "sg:city":"Wynigen",
    "sg:orig_category":"Gasth\u00f6fe/Gasth\u00e4user mit Restaurant",
    "sg:phone":"+41 34 415 12 80",
    "sg:postcode":"3472",
    "sg:province":"Bern",
    "wof:name":"Landgasthof Z. Linde",
    "wof:placetype":"venue"
},
  "geometry": {"coordinates":[7.6677589417,47.1059188843],"type":"Point"}
}