{
  "type": "Feature",
  "properties": {
    "iso:country":"CH",
    "sg:address":"Kiesgrube 74b 7231 Pragg-jenaz. Postfach",
    "sg:city":"Pragg-jenaz",
    "sg:orig_category":"Unclassifiable Establishments",
    "sg:phone":"+41 18333063",
    "sg:postcode":"7231",
    "sg:province":"Graubunden",
    "wof:name":"Wirth Haustechnik Sanit\u00e4r + Heizungen",
    "wof:placetype":"venue"
},
  "geometry": {"coordinates":[8.6441774368,47.4108924866],"type":"Point"}
}