{
  "type": "Feature",
  "properties": {
    "iso:country":"CH",
    "sg:address":"Winterthurerstrasse 684",
    "sg:city":"Z\u00fcrich",
    "sg:orig_category":"Sportvereine Turnen",
    "sg:postcode":"8051",
    "sg:province":"Z\u00fcrich",
    "wof:name":"Arb.touring-bund Atb Oerlikon",
    "wof:placetype":"venue"
},
  "geometry": {"coordinates":[8.582780838,47.4061546326],"type":"Point"}
}