{
  "type": "Feature",
  "properties": {
    "iso:country":"CH",
    "sg:address":"Fontaine Chemin De La",
    "sg:city":"Bremblens",
    "sg:orig_category":"Markt U Meinungsforschung",
    "sg:phone":"+41 21 801 55 37",
    "sg:postcode":"1121",
    "sg:province":"Vaud",
    "wof:name":"Agence Commerciale Wsa, Weigand S.",
    "wof:placetype":"venue"
},
  "geometry": {"coordinates":[6.5147027969,46.5446891785],"type":"Point"}
}