{
  "type": "Feature",
  "properties": {
    "iso:country":"CH",
    "sg:address":"Kurvenstrasse",
    "sg:city":"Lustm\u00fchle",
    "sg:orig_category":"Naturheil\u00e4rzte and Heilpraktiker",
    "sg:phone":"+41 71 333 16 22",
    "sg:postcode":"9062",
    "sg:province":"Appenzell Ausserrhoden",
    "wof:name":"Paul Michel Magnetopath",
    "wof:placetype":"venue"
},
  "geometry": {"coordinates":[9.3584270477,47.3985671997],"type":"Point"}
}