{
  "type": "Feature",
  "properties": {
    "iso:country":"CH",
    "sg:address":"Angensteinerstrasse 25",
    "sg:city":"Basel",
    "sg:orig_category":"Architekturb\u00fcros",
    "sg:phone":"+41 61 312 66 20",
    "sg:postcode":"4052",
    "sg:province":"Basel-Stadt",
    "wof:name":"Peter Laederach Architekturb\u00fcro",
    "wof:placetype":"venue"
},
  "geometry": {"coordinates":[7.604029,47.54969],"type":"Point"}
}