{
  "type": "Feature",
  "properties": {
    "addr:full":"P\u00fcntenstrasse 2 Winterthur Z\u00fcrich 8404",
    "addr:housenumber":"2",
    "addr:postcode":"8404",
    "addr:street":"Puentenstrasse",
    "iso:country":"CH",
    "sg:address":"P\u00fcntenstrasse 2",
    "sg:city":"Winterthur",
    "sg:classifiers":[
        {
            "category":"Arts & Performance",
            "subcategory":"Dance",
            "type":"Entertainment"
        }
    ],
    "sg:phone":"+41 52 242 41 81",
    "sg:postcode":"8404",
    "sg:province":"Z\u00fcrich",
    "sg:tags":[
        "casting"
    ],
    "wof:name":"Kunstgiesserei Br\u00fcndler Gmbh",
    "wof:placetype":"venue"
},
  "geometry": {"coordinates":[8.757978,47.508663],"type":"Point"}
}