{
  "type": "Feature",
  "properties": {
    "iso:country":"CH",
    "sg:address":"Loostrasse 11 8451 Kleinandelfingen. Postfach",
    "sg:city":"R\u00fcschlikon",
    "sg:orig_category":"Unternehmensberatung",
    "sg:phone":"+41 71 288 03 01",
    "sg:postcode":"8803",
    "sg:province":"Z\u00fcrich",
    "wof:name":"Zahner Public",
    "wof:placetype":"venue"
},
  "geometry": {"coordinates":[9.404127121,47.4476394653],"type":"Point"}
}