{
  "type": "Feature",
  "properties": {
    "iso:country":"CH",
    "sg:address":"6994",
    "sg:city":"Aranno",
    "sg:orig_category":"Gartenbau",
    "sg:phone":"+41 91 609 21 16",
    "sg:postcode":"6994",
    "sg:province":"Ticino",
    "wof:name":"Magini Sagl Manutenzione Terreni-giardini",
    "wof:placetype":"venue"
},
  "geometry": {"coordinates":[8.8729295731,46.0192718506],"type":"Point"}
}