{
  "type": "Feature",
  "properties": {
    "iso:country":"CH",
    "sg:address":"Seestrasse 157",
    "sg:city":"W\u00e4denswil",
    "sg:classifiers":[
        {
            "category":"Food & Beverages",
            "subcategory":"Specialty",
            "type":"Retail Goods"
        }
    ],
    "sg:phone":"+41 16802525",
    "sg:postcode":"8820",
    "sg:province":"Z\u00fcrich",
    "sg:tags":[
        "caterer"
    ],
    "wof:name":"Pizza-kurier Tasty",
    "wof:placetype":"venue"
},
  "geometry": {"coordinates":[8.669432,47.232349],"type":"Point"}
}