{
  "type": "Feature",
  "properties": {
    "iso:country":"CH",
    "sg:address":"Wiggispark 8754 Netstal. Postfach",
    "sg:city":"Netstal",
    "sg:orig_category":"M\u00f6belschreinereien",
    "sg:postcode":"8754",
    "sg:province":"Glarus",
    "wof:name":"Visus Project Ag Qualitativ Hochwertige M\u00f6bel U. M\u00f6belsysteme; Entwicklung, Planung, Fertigung Usw.",
    "wof:placetype":"venue"
},
  "geometry": {"coordinates":[9.057393074,47.0656394958],"type":"Point"}
}