{
  "type": "Feature",
  "properties": {
    "iso:country":"CH",
    "sg:address":"Luzernstrasse 19 6206 Neuenkirch. Postfach",
    "sg:city":"Neuenkirch",
    "sg:orig_category":"Instandhaltung U Reparatur von Automobilen",
    "sg:postcode":"6206",
    "sg:province":"Luzern",
    "wof:name":"W\u00fcest Autospritzwerk",
    "wof:placetype":"venue"
},
  "geometry": {"coordinates":[8.2066421509,47.0979728699],"type":"Point"}
}