{
  "type": "Feature",
  "properties": {
    "iso:country":"CH",
    "sg:address":"7250",
    "sg:city":"Klosters",
    "sg:orig_category":"Erschliessung von Grundst\u00fccken",
    "sg:postcode":"7250",
    "sg:province":"Graubunden",
    "wof:name":"Wohnbau Ag Muri Bei Bern",
    "wof:placetype":"venue"
},
  "geometry": {"coordinates":[7.4764070511,46.9279251099],"type":"Point"}
}