{
  "type": "Feature",
  "properties": {
    "iso:country":"CH",
    "sg:address":"Schutzengelstrasse 36 6340 Baar. Postfach 2154",
    "sg:city":"Baar",
    "sg:orig_category":"Aktivit\u00e4ten der Generalunternehmen im Baugewerbe Allgemeiner Hoch U Tiefbau",
    "sg:phone":"+41 41 619 00 30",
    "sg:postcode":"6342",
    "sg:province":"Zug",
    "wof:name":"Nimasa Ag",
    "wof:placetype":"venue"
},
  "geometry": {"coordinates":[8.536715,47.197521],"type":"Point"}
}