{
  "type": "Feature",
  "properties": {
    "iso:country":"CH",
    "sg:address":"Seestrasse 677",
    "sg:city":"Meilen",
    "sg:orig_category":"Sanit\u00e4r, Heizungs U L\u00fcftungsinstallation Sanit\u00e4rinstallation",
    "sg:phone":"+41 19230880",
    "sg:postcode":"8706",
    "sg:province":"Z\u00fcrich",
    "wof:name":"Lehmann & Billeter Ag Heizung Sanit\u00e4r Energie",
    "wof:placetype":"venue"
},
  "geometry": {"coordinates":[8.6463575363,47.2679862976],"type":"Point"}
}