{
  "type": "Feature",
  "properties": {
    "iso:country":"CH",
    "sg:address":"Hauptstrasse 12",
    "sg:city":"Glarus",
    "sg:orig_category":"Unclassifiable Establishments",
    "sg:postcode":"8750",
    "sg:province":"Glarus",
    "wof:name":"Geka Spielwaren Gmbh",
    "wof:placetype":"venue"
},
  "geometry": {"coordinates":[9.068936348,47.0388793945],"type":"Point"}
}