{
  "type": "Feature",
  "properties": {
    "iso:country":"CH",
    "sg:address":"Sch\u00f6nenbergstrasse 3 8820 W\u00e4denswil. Postfach 201",
    "sg:city":"W\u00e4denswil",
    "sg:orig_category":"Architektur U Ingenieurb\u00fcros",
    "sg:phone":"+41 55 210 15 58",
    "sg:postcode":"8820",
    "sg:province":"Z\u00fcrich",
    "wof:name":"Frei + Krauer Ag",
    "wof:placetype":"venue"
},
  "geometry": {"coordinates":[8.8243350983,47.2305793762],"type":"Point"}
}