{
  "type": "Feature",
  "properties": {
    "iso:country":"CH",
    "sg:address":"Hauptstrasse 108 6182 Escholzmatt. Postfach 108",
    "sg:city":"Escholzmatt",
    "sg:orig_category":"Detailhandel mit Sportartikeln",
    "sg:phone":"+41 41 486 12 47",
    "sg:postcode":"6182",
    "sg:province":"Luzern",
    "wof:name":"Hans Jun. Abb\u00fchl Abb\u00fchl-sport",
    "wof:placetype":"venue"
},
  "geometry": {"coordinates":[7.9339227676,46.9137382507],"type":"Point"}
}