{
  "type": "Feature",
  "properties": {
    "iso:country":"CH",
    "sg:address":"Rue Du Chalet 1",
    "sg:city":"Tavannes",
    "sg:orig_category":"Instandhaltung U Reparatur von Automobilen",
    "sg:phone":"+41 32 481 48 83",
    "sg:postcode":"2710",
    "sg:province":"Bern",
    "wof:name":"Giorgio Longo Garage De L'avenir",
    "wof:placetype":"venue"
},
  "geometry": {"coordinates":[7.2028059959,47.2253570557],"type":"Point"}
}