{
  "type": "Feature",
  "properties": {
    "addr:full":"Rue De Lausanne 23 Pr\u00e9verenges Vaud 1028",
    "addr:housenumber":"23",
    "addr:postcode":"1028",
    "addr:street":"Rue De Lausanne",
    "iso:country":"CH",
    "sg:address":"Rue De Lausanne 23",
    "sg:city":"Pr\u00e9verenges",
    "sg:orig_category":"Abwasserreinigung",
    "sg:phone":"+41 79 656 53 38",
    "sg:postcode":"1028",
    "sg:province":"Vaud",
    "wof:name":"Eugen Schl\u00e4pfer Kanal-& Rohrreinigungen",
    "wof:placetype":"venue"
},
  "geometry": {"coordinates":[7.562833,46.717854],"type":"Point"}
}