{
  "type": "Feature",
  "properties": {
    "iso:country":"CH",
    "sg:address":"Landstrasse 62",
    "sg:city":"M\u00f6hlin",
    "sg:classifiers":[
        {
            "category":"Travel",
            "subcategory":"Hotels & Motels",
            "type":"Entertainment"
        }
    ],
    "sg:phone":"+41 61 851 20 37",
    "sg:postcode":"4313",
    "sg:province":"Aargau",
    "sg:tags":[
        "hotels",
        "mit",
        "restaurant"
    ],
    "wof:name":"Lardi Angelo Ag",
    "wof:placetype":"venue"
},
  "geometry": {"coordinates":[7.852686882,47.5529518127],"type":"Point"}
}