{
  "type": "Feature",
  "properties": {
    "iso:country":"CH",
    "sg:address":"Hammerstrasse 112",
    "sg:city":"Z\u00fcrich",
    "sg:orig_category":"P\u00e9dicure",
    "sg:phone":"+41 52 765 29 37",
    "sg:postcode":"8032",
    "sg:province":"Z\u00fcrich",
    "wof:name":"Liselotte Oesch P\u00e9dicure",
    "wof:placetype":"venue"
},
  "geometry": {"coordinates":[8.9763698578,47.5778617859],"type":"Point"}
}