{
  "type": "Feature",
  "properties": {
    "iso:country":"CH",
    "sg:address":"Rue Des Vergers 4",
    "sg:city":"Sion",
    "sg:orig_category":"Detailhandel mit medizinischen U orthop\u00e4dischen Artikeln Herstellung von medizinischen U chirurgisch",
    "sg:phone":"+41 41 360 25 44",
    "sg:postcode":"1950",
    "sg:province":"Valais",
    "wof:name":"Ortho Medica Hutter Gregor",
    "wof:placetype":"venue"
},
  "geometry": {"coordinates":[8.3067178726,47.0427284241],"type":"Point"}
}