{
  "type": "Feature",
  "properties": {
    "iso:country":"CH",
    "sg:address":"M\u00fchlefeldstrasse 57 4702 Oensingen. Postfach",
    "sg:city":"Oensingen",
    "sg:orig_category":"Detailhandel mit Damenbekleidung Detailhandel mit Herrenbekleidung",
    "sg:phone":"+41 62 396 12 22",
    "sg:postcode":"4702",
    "sg:province":"Solothurn",
    "wof:name":"Boutique Graffiti",
    "wof:placetype":"venue"
},
  "geometry": {"coordinates":[7.720245,47.288738],"type":"Point"}
}