{
  "type": "Feature",
  "properties": {
    "iso:country":"CH",
    "sg:address":"Schulstrasse 2 6440 Brunnen. Postfach",
    "sg:city":"Ibach",
    "sg:orig_category":"Maler U Glasergewerbe",
    "sg:postcode":"6438",
    "sg:province":"Schwyz",
    "wof:name":"Kunden-maler Christen Pepi",
    "wof:placetype":"venue"
},
  "geometry": {"coordinates":[8.6139593124,47.0006523132],"type":"Point"}
}