{
  "type": "Feature",
  "properties": {
    "iso:country":"CH",
    "sg:address":"Pumpwerkstrasse 23",
    "sg:city":"Regensdorf",
    "sg:orig_category":"Handelsvermittlung U Grosshandel",
    "sg:phone":"+41 61 913 95 47",
    "sg:postcode":"8105",
    "sg:province":"Z\u00fcrich",
    "wof:name":"Pro-v Gmbh Handel- & Dienstleistungen",
    "wof:placetype":"venue"
},
  "geometry": {"coordinates":[7.6889209747,47.4589538574],"type":"Point"}
}