{
  "type": "Feature",
  "properties": {
    "iso:country":"CH",
    "sg:address":"Gerechtigkeitsgasse 16 3011 Bern. Postfach",
    "sg:city":"Bern",
    "sg:orig_category":"RESTAURANTS: TEA-ROOMS",
    "sg:postcode":"3005",
    "sg:province":"Bern",
    "wof:name":"Werner B\u00f6siger Restaurant Nydeggstube.",
    "wof:placetype":"venue"
},
  "geometry": {"coordinates":[7.4554347992,46.9487380981],"type":"Point"}
}