{
  "type": "Feature",
  "properties": {
    "iso:country":"CH",
    "sg:address":"Bernstrasse 210 3613 Steffisburg. Postfach 34",
    "sg:city":"Steffisburg",
    "sg:orig_category":"Autogaragen",
    "sg:phone":"+41 33 437 45 57",
    "sg:postcode":"3613",
    "sg:province":"Bern",
    "wof:name":"Gebr.ernst & Kurt Schneiter Garage",
    "wof:placetype":"venue"
},
  "geometry": {"coordinates":[7.611206,46.780949],"type":"Point"}
}