{
  "type": "Feature",
  "properties": {
    "iso:country":"CH",
    "sg:address":"Rue Du Simplon 13",
    "sg:city":"Martigny",
    "sg:orig_category":"Kosmetikinstitute",
    "sg:phone":"+41 27 722 22 51",
    "sg:postcode":"1920",
    "sg:province":"Valais",
    "wof:name":"Gis\u00e8le Vuistiner Institut De Beaut\u00e9 Alexandra",
    "wof:placetype":"venue"
},
  "geometry": {"coordinates":[7.0789971352,46.1035881042],"type":"Point"}
}