{
  "type": "Feature",
  "properties": {
    "iso:country":"CH",
    "sg:address":"T\u00fcfiwis 9 8332 Russikon. Postfach",
    "sg:city":"Russikon",
    "sg:orig_category":"Fachdetailhandel in Verkaufsr\u00e4umen",
    "sg:phone":"+41 19543458",
    "sg:postcode":"8332",
    "sg:province":"Z\u00fcrich",
    "wof:name":"Team Sport Jost Sportartikel; Handel, Verkauf",
    "wof:placetype":"venue"
},
  "geometry": {"coordinates":[8.7732439041,47.3913841248],"type":"Point"}
}