{
  "type": "Feature",
  "properties": {
    "iso:country":"CH",
    "sg:address":"Universit\u00e4tstrasse 6 8006 Z\u00fcrich. Postfach",
    "sg:city":"Z\u00fcrich",
    "sg:classifiers":[
        {
            "category":"Education",
            "subcategory":"Library",
            "type":"Public Place"
        }
    ],
    "sg:phone":"+41 16326247",
    "sg:postcode":"8092",
    "sg:province":"Z\u00fcrich",
    "sg:tags":[
        "u",
        "bibliotheken",
        "archive"
    ],
    "wof:name":"Chemie-bibliothek Ethz",
    "wof:placetype":"venue"
},
  "geometry": {"coordinates":[8.548321,47.37833],"type":"Point"}
}