{
  "type": "Feature",
  "properties": {
    "iso:country":"CH",
    "sg:address":"Aecherligasse 2",
    "sg:city":"Oftringen",
    "sg:orig_category":"Instandhaltung U Reparatur von Automobilen",
    "sg:phone":"+41 81 422 29 26",
    "sg:postcode":"4665",
    "sg:province":"Aargau",
    "wof:name":"Carrosserie Martin Fetz",
    "wof:placetype":"venue"
},
  "geometry": {"coordinates":[9.8742961884,46.8846511841],"type":"Point"}
}