{
  "type": "Feature",
  "properties": {
    "iso:country":"CH",
    "sg:address":"Rue John-grasset 5",
    "sg:city":"Gen\u00e8ve",
    "sg:orig_category":"Detailhandel mit Uhren U Schmuck",
    "sg:phone":"+41 22 320 70 61",
    "sg:postcode":"1205",
    "sg:province":"Gen\u00e8ve",
    "wof:name":"Michel Gaschen Atelier De Bijouterie",
    "wof:placetype":"venue"
},
  "geometry": {"coordinates":[6.1450829506,46.1912345886],"type":"Point"}
}