{
  "type": "Feature",
  "properties": {
    "iso:country":"CH",
    "sg:address":"S\u00fcdstrasse 1 3110 M\u00fcnsingen. Postfach 1245",
    "sg:city":"M\u00fcnsingen",
    "sg:orig_category":"Grosshandel mit Datenverarbeitungsger\u00e4ten Softwareentwicklung U beratung",
    "sg:phone":"+41 31 720 14 14",
    "sg:postcode":"3110",
    "sg:province":"Bern",
    "wof:name":"Itag Information Technology Ag",
    "wof:placetype":"venue"
},
  "geometry": {"coordinates":[7.5633740425,46.868724823],"type":"Point"}
}