{
  "type": "Feature",
  "properties": {
    "iso:country":"CH",
    "sg:address":"8458",
    "sg:city":"Dorf",
    "sg:orig_category":"G\u00fcterbef\u00f6rderung im Strassenverkehr",
    "sg:phone":"+41 71 633 12 02",
    "sg:postcode":"8458",
    "sg:province":"Z\u00fcrich",
    "wof:name":"Schallenberg Christian",
    "wof:placetype":"venue"
},
  "geometry": {"coordinates":[9.154961586,47.5498390198],"type":"Point"}
}