{
  "type": "Feature",
  "properties": {
    "iso:country":"CH",
    "sg:address":"Thuraustrasse 31 9642 Ebnat. Postfach 177",
    "sg:city":"Ebnat",
    "sg:orig_category":"Bauschreinerei Hoch U Tiefbau",
    "sg:phone":"+41 81 854 22 64",
    "sg:postcode":"9642",
    "sg:province":"St. Gallen",
    "wof:name":"Laudenbacher Bau Ag",
    "wof:placetype":"venue"
},
  "geometry": {"coordinates":[9.924975,46.57967],"type":"Point"}
}