{
  "type": "Feature",
  "properties": {
    "addr:full":"H\u00fcbelistrasse 1 Olten Solothurn 4600",
    "addr:housenumber":"1",
    "addr:postcode":"4600",
    "addr:street":"Huebelistrasse",
    "iso:country":"CH",
    "sg:address":"H\u00fcbelistrasse 1",
    "sg:city":"Olten",
    "sg:orig_category":"Detailhandel mit Bekleidung",
    "sg:phone":"+41 62 293 17 33",
    "sg:postcode":"4600",
    "sg:province":"Solothurn",
    "wof:name":"Boutique Casa Gloor Franziska",
    "wof:placetype":"venue"
},
  "geometry": {"coordinates":[7.90038,47.35004],"type":"Point"}
}