{
  "type": "Feature",
  "properties": {
    "iso:country":"CH",
    "sg:address":"Pessina Via 5",
    "sg:city":"Lugano",
    "sg:orig_category":"Grosshandel mit Eisenwaren sowie Installationsbedarf f\u00fcr Gas, Wasser U Heizung",
    "sg:phone":"+41 91 921 02 09",
    "sg:postcode":"6900",
    "sg:province":"Ticino",
    "wof:name":"P.p.c. Participation Partnership Consulting Ltd, Dublino, Succursale Di Lugano",
    "wof:placetype":"venue"
},
  "geometry": {"coordinates":[8.9502897263,46.0038719177],"type":"Point"}
}