{
  "type": "Feature",
  "properties": {
    "iso:country":"CH",
    "sg:address":"6776",
    "sg:city":"Piotta",
    "sg:orig_category":"Detailhandel mit Fleisch U Fleischwaren",
    "sg:phone":"+41 91 868 11 19",
    "sg:postcode":"6776",
    "sg:province":"Ticino",
    "wof:name":"Fratelli Piccoli Macelleria",
    "wof:placetype":"venue"
},
  "geometry": {"coordinates":[8.6774301529,46.5127983093],"type":"Point"}
}