{
  "type": "Feature",
  "properties": {
    "iso:country":"CH",
    "sg:address":"Via Mola 6877 Coldrerio Casella Postale 79",
    "sg:city":"Coldrerio",
    "sg:orig_category":"Herstellung von sonstigen elektrischen Ausr\u00fcstungen",
    "sg:phone":"+41 91 646 55 72",
    "sg:postcode":"6877",
    "sg:province":"Ticino",
    "wof:name":"Telecondor Di Mezzanzanica Angelo",
    "wof:placetype":"venue"
},
  "geometry": {"coordinates":[8.987575531,45.8543815613],"type":"Point"}
}