{
  "type": "Feature",
  "properties": {
    "iso:country":"CH",
    "sg:address":"Avenue De Chailly 44",
    "sg:city":"Lausanne",
    "sg:orig_category":"Architektur U Ingenieurb\u00fcros",
    "sg:phone":"+41 21 729 86 21",
    "sg:postcode":"1012",
    "sg:province":"Vaud",
    "wof:name":"Chevalley Christian Bureau D'ing\u00e9nieurs Civils Sa",
    "wof:placetype":"venue"
},
  "geometry": {"coordinates":[6.654706,46.523346],"type":"Point"}
}