{
  "type": "Feature",
  "properties": {
    "iso:country":"CH",
    "sg:address":"Solothurnstrasse 31 3315 B\u00e4tterkinden. Postfach",
    "sg:city":"B\u00e4tterkinden",
    "sg:orig_category":"Herstellung von Metallkonstruktionen Stahl U Leichtmetallbau",
    "sg:phone":"+41 32 665 45 68",
    "sg:postcode":"3315",
    "sg:province":"Bern",
    "wof:name":"Stoller Metallbau Ag",
    "wof:placetype":"venue"
},
  "geometry": {"coordinates":[7.5371961594,47.1369857788],"type":"Point"}
}