{
  "type": "Feature",
  "properties": {
    "iso:country":"CH",
    "sg:address":"Lausanne Rue De 30",
    "sg:city":"Meyriez",
    "sg:orig_category":"Maschinen-Fabrikation",
    "sg:phone":"+41 26 672 99 11",
    "sg:postcode":"3280",
    "sg:province":"Fribourg",
    "wof:name":"Romag Geb\u00e4udeautomation Roulin & Gilgen",
    "wof:placetype":"venue"
},
  "geometry": {"coordinates":[7.1053638458,46.9223327637],"type":"Point"}
}