{
  "type": "Feature",
  "properties": {
    "iso:country":"CH",
    "sg:address":"Hardstrasse 95",
    "sg:city":"Neuenhof",
    "sg:orig_category":"Zimmerei, Dachdeckerei, Bauspenglerei U Abdichtung",
    "sg:phone":"+41 56 406 05 04",
    "sg:postcode":"5432",
    "sg:province":"Aargau",
    "wof:name":"Bauspenglerei Irena & Oliver Gmbh",
    "wof:placetype":"venue"
},
  "geometry": {"coordinates":[8.3263225555,47.4529647827],"type":"Point"}
}