{
  "type": "Feature",
  "properties": {
    "addr:full":"Bahnhofstrasse 12 6072 Sachseln. Postfach 64 Sachseln Obwalden 6072",
    "addr:housenumber":"12;64",
    "addr:postcode":"6072 sachseln.;6072",
    "addr:street":"Bahnhofstrasse;Postfach",
    "iso:country":"CH",
    "sg:address":"Bahnhofstrasse 12 6072 Sachseln. Postfach 64",
    "sg:city":"Sachseln",
    "sg:orig_category":"Bauschreinerei Herstellung von Konstruktionsteilen, Fertigbauteilen U Ausbauelementen aus Holz",
    "sg:phone":"+41 41 666 75 45",
    "sg:postcode":"6072",
    "sg:province":"Obwalden",
    "wof:name":"Von Ah Theo S\u00f6hne Ag.",
    "wof:placetype":"venue"
},
  "geometry": {"coordinates":[8.2387,46.870567],"type":"Point"}
}