{
  "type": "Feature",
  "properties": {
    "iso:country":"CH",
    "sg:address":"M\u00fchlegasse 1 6314 Unter\u00e4geri. Postfach",
    "sg:city":"Unter\u00e4geri",
    "sg:orig_category":"Handelsvermittlung von Textilien, Bekleidung, Schuhen U Lederwaren",
    "sg:phone":"+41 41 752 08 20",
    "sg:postcode":"6314",
    "sg:province":"Zug",
    "wof:name":"Innovazione Di Maglia Gmbh Modebranche; Beratung, Warenlieferung. Pferdezucht",
    "wof:placetype":"venue"
},
  "geometry": {"coordinates":[8.5841398239,47.1354370117],"type":"Point"}
}