{
  "type": "Feature",
  "properties": {
    "iso:country":"CH",
    "sg:address":"Harderstrasse 14",
    "sg:city":"Interlaken",
    "sg:orig_category":"Personenbef\u00f6rderung im Linienverkehr zu Land",
    "sg:phone":"+41 33 828 71 11",
    "sg:postcode":"3800",
    "sg:province":"Bern",
    "wof:name":"Wengernalpbahn Ag",
    "wof:placetype":"venue"
},
  "geometry": {"coordinates":[7.8555231094,46.6864204407],"type":"Point"}
}