{
  "type": "Feature",
  "properties": {
    "iso:country":"CH",
    "sg:address":"Route D'hermance 106",
    "sg:city":"Collonge-bellerive",
    "sg:orig_category":"Herstellung von Phantasieschmuck",
    "sg:phone":"+41 32 931 51 61",
    "sg:postcode":"1245",
    "sg:province":"Gen\u00e8ve",
    "wof:name":"Borel Fulvio",
    "wof:placetype":"venue"
},
  "geometry": {"coordinates":[6.7549009323,47.057182312],"type":"Point"}
}