{
  "type": "Feature",
  "properties": {
    "iso:country":"CH",
    "sg:address":"R\u00fcegsaustrasse 69",
    "sg:city":"R\u00fcegsauschachen",
    "sg:orig_category":"Wasserversorgung",
    "sg:phone":"+41 34 461 27 70",
    "sg:postcode":"3415",
    "sg:province":"Bern",
    "wof:name":"Genossensch.wasserversorgung R\u00fcegsauschachen & Umgebung",
    "wof:placetype":"venue"
},
  "geometry": {"coordinates":[7.66370821,47.0200271606],"type":"Point"}
}