{
  "type": "Feature",
  "properties": {
    "iso:country":"CH",
    "sg:address":"Chemin Du Chalet Rouge 2",
    "sg:city":"Moudon",
    "sg:orig_category":"Herstellung von sonstigen elektrischen Ausr\u00fcstungen",
    "sg:phone":"+41 21 905 17 35",
    "sg:postcode":"1510",
    "sg:province":"Vaud",
    "wof:name":"Rudaz Electronique.",
    "wof:placetype":"venue"
},
  "geometry": {"coordinates":[6.7896571159,46.6667976379],"type":"Point"}
}