{
  "type": "Feature",
  "properties": {
    "iso:country":"CH",
    "sg:address":"Ginevra Via 4 6900 Lugano. Postfach",
    "sg:city":"Lugano",
    "sg:orig_category":"Interessenvertretungen",
    "sg:postcode":"6900",
    "sg:province":"Ticino",
    "wof:name":"Fondazione Godlewski Dr. Julian",
    "wof:placetype":"venue"
},
  "geometry": {"coordinates":[8.951880455,46.0083312988],"type":"Point"}
}