{
  "type": "Feature",
  "properties": {
    "iso:country":"CH",
    "sg:address":"Englisch-gruss-strasse 9",
    "sg:city":"Glis",
    "sg:classifiers":[
        {
            "category":"Government",
            "subcategory":"Post Office",
            "type":"Public Place"
        }
    ],
    "sg:phone":"+41 27 924 25 00",
    "sg:postcode":"3902",
    "sg:province":"Valais",
    "sg:tags":[
        "caf\u00e9s",
        "tea-rooms"
    ],
    "wof:name":"Tea-room Glismatta",
    "wof:placetype":"venue"
},
  "geometry": {"coordinates":[7.9857459068,46.315826416],"type":"Point"}
}