{
  "type": "Feature",
  "properties": {
    "iso:country":"CH",
    "sg:address":"Avenue De Richelien 39 1290 Versoix Case Postale 664",
    "sg:city":"Versoix",
    "sg:orig_category":"Herstellung von Metallerzeugnissen ohne Maschinenbau Herstellung von Werkzeugen",
    "sg:phone":"+41 22 775 33 33",
    "sg:postcode":"1290",
    "sg:province":"Gen\u00e8ve",
    "wof:name":"B\u00fcnter Sa",
    "wof:placetype":"venue"
},
  "geometry": {"coordinates":[6.1388168335,46.2833824158],"type":"Point"}
}