{
  "type": "Feature",
  "properties": {
    "iso:country":"CH",
    "sg:address":"Pr\u00e9-de-la-fontaine Rue 15",
    "sg:city":"Meyrin",
    "sg:orig_category":"Detailhandel mit Metallwaren, Anstrichmitteln, Glaswaren, Bau U Heimwerkerbedarf",
    "sg:postcode":"1217",
    "sg:province":"Gen\u00e8ve",
    "wof:name":"Bpz Outillages, Zlatiew & Cie",
    "wof:placetype":"venue"
},
  "geometry": {"coordinates":[6.0722160339,46.2284431458],"type":"Point"}
}