{
  "type": "Feature",
  "properties": {
    "iso:country":"CH",
    "sg:address":"Gotenstrasse 4",
    "sg:city":"Bern",
    "sg:orig_category":"Detailhandel mit Waren verschiedener Art, Hauptrichtung Nahrungsmittel Grosshandel mit Nahrungsmitte",
    "sg:phone":"+41 31 991 03 07",
    "sg:postcode":"3018",
    "sg:province":"Bern",
    "wof:name":"Sheba Allenbach, Eve S Shop",
    "wof:placetype":"venue"
},
  "geometry": {"coordinates":[7.3983168602,46.9439086914],"type":"Point"}
}