{
  "type": "Feature",
  "properties": {
    "iso:country":"CH",
    "sg:address":"Riva Via Antonio 14",
    "sg:city":"Lugano",
    "sg:orig_category":"Herstellung von elektronischen Bauelementen",
    "sg:phone":"+41 91 994 80 21",
    "sg:postcode":"6900",
    "sg:province":"Ticino",
    "wof:name":"Eloico Sa",
    "wof:placetype":"venue"
},
  "geometry": {"coordinates":[8.9421195984,45.9967384338],"type":"Point"}
}