{
  "type": "Feature",
  "properties": {
    "iso:country":"CH",
    "sg:address":"Sternenstrasse 15 8002 Z\u00fcrich. Postfach",
    "sg:city":"Z\u00fcrich",
    "sg:orig_category":"Sonstige mit der Informatik verbundene T\u00e4tigkeiten",
    "sg:phone":"+41 12018306",
    "sg:postcode":"8001",
    "sg:province":"Z\u00fcrich",
    "wof:name":"Affentranger Fernando, Jad & Rad Solutions Dienstleistungen Im Informatikbereich, Bes. Softwarem\u00e4ssige Umsetzung Von Modellen Aus Der Angewandten Mathematik",
    "wof:placetype":"venue"
},
  "geometry": {"coordinates":[8.533539772,47.3600196838],"type":"Point"}
}