{
  "type": "Feature",
  "properties": {
    "iso:country":"CH",
    "sg:address":"Hauptstrasse 449",
    "sg:city":"Meisterschwanden",
    "sg:orig_category":"RESTAURANTS: TEA-ROOMS",
    "sg:phone":"+41 56 667 39 00",
    "sg:postcode":"5616",
    "sg:province":"Aargau",
    "wof:name":"Restaurant R\u00fctli & Pfyfe Bar",
    "wof:placetype":"venue"
},
  "geometry": {"coordinates":[8.2248687744,47.2992553711],"type":"Point"}
}