{
  "type": "Feature",
  "properties": {
    "iso:country":"CH",
    "sg:address":"Ch. De La Rippaz 21",
    "sg:city":"Vandoeuvres",
    "sg:orig_category":"Non-Classified Establishments",
    "sg:postcode":"1253",
    "sg:province":"Gen\u00e8ve",
    "wof:name":"Si Rue Des Eaux-vives 102",
    "wof:placetype":"venue"
},
  "geometry": {"coordinates":[6.1999521255,46.2279396057],"type":"Point"}
}