{
  "type": "Feature",
  "properties": {
    "iso:country":"CH",
    "sg:address":"Hauptstrasse 12",
    "sg:city":"Zihlschlacht",
    "sg:orig_category":"Elektroinstallation",
    "sg:phone":"+41 71 422 17 29",
    "sg:postcode":"8588",
    "sg:province":"Thurgau",
    "wof:name":"Fritz M\u00fcller Elektrische Installationen",
    "wof:placetype":"venue"
},
  "geometry": {"coordinates":[9.2571973801,47.5182151794],"type":"Point"}
}