{
  "type": "Feature",
  "properties": {
    "iso:country":"CH",
    "sg:address":"Talackerweg 14",
    "sg:city":"Grossh\u00f6chstetten",
    "sg:orig_category":"Sportvereine Sch\u00fctzen",
    "sg:phone":"+41 31 711 04 39",
    "sg:postcode":"3506",
    "sg:province":"Bern",
    "wof:name":"Milit\u00e4rsch\u00fctzengesellschaft",
    "wof:placetype":"venue"
},
  "geometry": {"coordinates":[7.6317939758,46.9105224609],"type":"Point"}
}