{
  "type": "Feature",
  "properties": {
    "addr:full":"Schlosserstrasse 28 Winterthur Z\u00fcrich 8400",
    "addr:housenumber":"28",
    "addr:postcode":"8400",
    "addr:street":"Schlosserstrasse",
    "iso:country":"CH",
    "sg:address":"Schlosserstrasse 28",
    "sg:city":"Winterthur",
    "sg:orig_category":"Detailhandel mit Damenbekleidung",
    "sg:phone":"+41 52 222 12 16",
    "sg:postcode":"8400",
    "sg:province":"Z\u00fcrich",
    "wof:name":"Conzetta Valenti Damenkonfektion",
    "wof:placetype":"venue"
},
  "geometry": {"coordinates":[8.711632,47.504749],"type":"Point"}
}