{
  "type": "Feature",
  "properties": {
    "iso:country":"CH",
    "sg:address":"Holbeinstrasse 36-38 4051 Basel. Postfach 160",
    "sg:city":"Basel",
    "sg:orig_category":"Patentanwaltsb\u00fcros, Patentverwertung Rechtsberatung",
    "sg:phone":"+41 71 911 58 66",
    "sg:postcode":"4003",
    "sg:province":"Basel-Stadt",
    "wof:name":"B\u00fcchel, Von R\u00e9vy & Partner",
    "wof:placetype":"venue"
},
  "geometry": {"coordinates":[9.042429924,47.4672279358],"type":"Point"}
}