{
  "type": "Feature",
  "properties": {
    "iso:country":"CH",
    "sg:address":"Bremgartenstrasse 6",
    "sg:city":"Niederrohrdorf",
    "sg:orig_category":"RESTAURANTS: TEA-ROOMS",
    "sg:phone":"+41 31 747 73 22",
    "sg:postcode":"5443",
    "sg:province":"Aargau",
    "wof:name":"Hans Ruprecht",
    "wof:placetype":"venue"
},
  "geometry": {"coordinates":[7.2395119667,46.9029693604],"type":"Point"}
}