{
  "type": "Feature",
  "properties": {
    "iso:country":"CH",
    "sg:address":"Via Fola 2",
    "sg:city":"Pregassona",
    "sg:orig_category":"Instandhaltung U Reparatur von Automobilen",
    "sg:phone":"+41 79 621 87 70",
    "sg:postcode":"6963",
    "sg:province":"Ticino",
    "wof:name":"Rencar Sa",
    "wof:placetype":"venue"
},
  "geometry": {"coordinates":[8.9641141891,46.017616272],"type":"Point"}
}