{
  "type": "Feature",
  "properties": {
    "iso:country":"CH",
    "sg:address":"Via G. Motta 24",
    "sg:city":"Chiasso",
    "sg:orig_category":"Non-Classified Establishments",
    "sg:postcode":"6830",
    "sg:province":"Ticino",
    "wof:name":"Corega International Sa",
    "wof:placetype":"venue"
},
  "geometry": {"coordinates":[9.0299282074,45.8331604004],"type":"Point"}
}