{
  "type": "Feature",
  "properties": {
    "iso:country":"CH",
    "sg:address":"Obere Bahnhofstrasse 13",
    "sg:city":"Mellingen",
    "sg:orig_category":"Softwareentwicklung U beratung",
    "sg:phone":"+41 56 481 80 44",
    "sg:postcode":"5507",
    "sg:province":"Aargau",
    "wof:name":"Samac Vertriebs Ag",
    "wof:placetype":"venue"
},
  "geometry": {"coordinates":[8.2721204758,47.4292144775],"type":"Point"}
}