{
  "type": "Feature",
  "properties": {
    "iso:country":"CH",
    "sg:address":"Alte Kantonsstrasse 12",
    "sg:city":"Brunnen",
    "sg:orig_category":"Grosshandel mit lebenden Tieren",
    "sg:postcode":"6440",
    "sg:province":"Schwyz",
    "wof:name":"Schwyzer Viehvermarktungs Ag (sviag)",
    "wof:placetype":"venue"
},
  "geometry": {"coordinates":[8.6139593124,47.0006523132],"type":"Point"}
}