{
  "type": "Feature",
  "properties": {
    "iso:country":"CH",
    "sg:address":"Auenwiesenstrasse 8",
    "sg:city":"Bichelsee",
    "sg:orig_category":"Detailhandel mit Teppichen Herstellung von Teppichen",
    "sg:phone":"+41 71 971 37 50",
    "sg:postcode":"8363",
    "sg:province":"Thurgau",
    "wof:name":"Bosch Gmbh",
    "wof:placetype":"venue"
},
  "geometry": {"coordinates":[8.9252080917,47.4490089417],"type":"Point"}
}