{
  "type": "Feature",
  "properties": {
    "addr:full":"All\u00e9e Des Marronniers 1 Fontainemelon Neuch\u00e2tel 2052",
    "addr:housenumber":"1",
    "addr:postcode":"2052",
    "addr:street":"Alle\u0301E Des Marronniers;Neucha\u0302Tel",
    "iso:country":"CH",
    "sg:address":"All\u00e9e Des Marronniers 1",
    "sg:city":"Fontainemelon",
    "sg:orig_category":"Alters U Pflegeheime Institutionen f\u00fcr Behinderte",
    "sg:phone":"+41 32 853 41 38",
    "sg:postcode":"2052",
    "sg:province":"Neuch\u00e2tel",
    "wof:name":"Home M\u00e9dicalis\u00e9 Vert-bois Pension Pour Personnes \u00e2g\u00e9es",
    "wof:placetype":"venue"
},
  "geometry": {"coordinates":[6.892049,47.057663],"type":"Point"}
}