{
  "type": "Feature",
  "properties": {
    "iso:country":"CH",
    "sg:address":"3999",
    "sg:city":"Oberwald",
    "sg:orig_category":"Sportvereine Sch\u00fctzen",
    "sg:postcode":"3999",
    "sg:province":"Valais",
    "wof:name":"Milit\u00e4rschiessverein",
    "wof:placetype":"venue"
},
  "geometry": {"coordinates":[8.2035999298,47.4864692688],"type":"Point"}
}