{
  "type": "Feature",
  "properties": {
    "iso:country":"CH",
    "sg:address":"Comercialstrasse 19",
    "sg:city":"Chur",
    "sg:orig_category":"Pensionskassen",
    "sg:phone":"+41 81 650 00 10",
    "sg:postcode":"7000",
    "sg:province":"Graubunden",
    "wof:name":"Personalf\u00fcrsorgestiftung Der Hotel Und Touristik-management Htm Ag",
    "wof:placetype":"venue"
},
  "geometry": {"coordinates":[9.5099391937,46.8472366333],"type":"Point"}
}