{
  "type": "Feature",
  "properties": {
    "iso:country":"CH",
    "sg:address":"Neuve Place De 2 1204 Gen\u00e8ve. Postfach",
    "sg:city":"Gen\u00e8ve",
    "sg:orig_category":"Interessenvertretungen",
    "sg:postcode":"1204",
    "sg:province":"Gen\u00e8ve",
    "wof:name":"International Industrial Development Agency",
    "wof:placetype":"venue"
},
  "geometry": {"coordinates":[6.1480460167,46.2033691406],"type":"Point"}
}