{
  "type": "Feature",
  "properties": {
    "iso:country":"CH",
    "sg:address":"Birkenstrasse 12",
    "sg:city":"Tuggen",
    "sg:orig_category":"Softwareentwicklung U beratung",
    "sg:phone":"+41 55 445 20 22",
    "sg:postcode":"8856",
    "sg:province":"Schwyz",
    "wof:name":"Gisi Consult",
    "wof:placetype":"venue"
},
  "geometry": {"coordinates":[8.9471158981,47.2058296204],"type":"Point"}
}