{
  "type": "Feature",
  "properties": {
    "iso:country":"CH",
    "sg:address":"Baslerstrasse 9 4600 Olten. Postfach",
    "sg:city":"Olten",
    "sg:orig_category":"Arztpraxen",
    "sg:phone":"+41 62 212 85 32",
    "sg:postcode":"4603",
    "sg:province":"Solothurn",
    "wof:name":"Dr.med.christoph Fink Spezialarzt Fmh",
    "wof:placetype":"venue"
},
  "geometry": {"coordinates":[7.902548,47.350956],"type":"Point"}
}