{
  "type": "Feature",
  "properties": {
    "iso:country":"CH",
    "sg:address":"Seedorfweg 32",
    "sg:city":"M\u00fcnchenbuchsee",
    "sg:orig_category":"Elektroinstallation",
    "sg:phone":"+41 79 421 42 28",
    "sg:postcode":"3053",
    "sg:province":"Bern",
    "wof:name":"Elektro Schwegler Gmbh",
    "wof:placetype":"venue"
},
  "geometry": {"coordinates":[9.1522407532,47.5501747131],"type":"Point"}
}