{
  "type": "Feature",
  "properties": {
    "iso:country":"CH",
    "sg:address":"Pfistermatte",
    "sg:city":"Eggiwil",
    "sg:classifiers":[
        {
            "category":"Retail",
            "subcategory":"Repair Shop",
            "type":"Services"
        }
    ],
    "sg:phone":"+41 34 491 11 13",
    "sg:postcode":"3537",
    "sg:province":"Bern",
    "sg:tags":[
        "agricultural",
        "machinery"
    ],
    "wof:name":"Hans Arm Landw. Ger\u00e4te Und Maschinen",
    "wof:placetype":"venue"
},
  "geometry": {"coordinates":[7.792144,46.878468],"type":"Point"}
}