{
  "type": "Feature",
  "properties": {
    "iso:country":"CH",
    "sg:address":"Nordstrasse 48",
    "sg:city":"Chur",
    "sg:orig_category":"Shiatsu-Therapie",
    "sg:phone":"+41 81 284 09 28",
    "sg:postcode":"7000",
    "sg:province":"Graubunden",
    "wof:name":"Annalis Fischer Shiatsu Therapie",
    "wof:placetype":"venue"
},
  "geometry": {"coordinates":[9.5249872208,46.8580436707],"type":"Point"}
}