{
  "type": "Feature",
  "properties": {
    "iso:country":"CH",
    "sg:address":"Ador Quai Gustave- 62 1207 Gen\u00e8ve. Postfach",
    "sg:city":"Gen\u00e8ve",
    "sg:orig_category":"Softwareentwicklung U beratung",
    "sg:postcode":"1207",
    "sg:province":"Gen\u00e8ve",
    "wof:name":"Basf It Services Bv, Arnhem (nl), Zweigniederlassung W\u00e4denswil Dienstleistungen U. Ausf\u00fchren Von T\u00e4tigkeiten Im Bereich Der Informationstechnologie Usw",
    "wof:placetype":"venue"
},
  "geometry": {"coordinates":[8.6480903625,47.2410545349],"type":"Point"}
}