{
  "type": "Feature",
  "properties": {
    "iso:country":"CH",
    "sg:address":"Bahnhofstr. 12",
    "sg:city":"Amriswil",
    "sg:classifiers":[
        {
            "category":"Banks & Credit Unions",
            "subcategory":"Bank",
            "type":"Services"
        }
    ],
    "sg:phone":"+41 4171671859",
    "sg:postcode":"8580",
    "sg:province":"Thurgau",
    "wof:name":"Roth August Ag",
    "wof:placetype":"venue"
},
  "geometry": {"coordinates":[9.30114,47.546696],"type":"Point"}
}