{
  "type": "Feature",
  "properties": {
    "iso:country":"CH",
    "sg:address":"8825",
    "sg:city":"H\u00fctten",
    "sg:orig_category":"Sportvereine Sch\u00fctzen",
    "sg:phone":"+41 32 373 55 61",
    "sg:postcode":"8825",
    "sg:province":"Z\u00fcrich",
    "wof:name":"Feldsch\u00fctzenverein",
    "wof:placetype":"venue"
},
  "geometry": {"coordinates":[8.8399801254,47.0724411011],"type":"Point"}
}