{
  "type": "Feature",
  "properties": {
    "iso:country":"CH",
    "sg:address":"Hauptstrasse 16",
    "sg:city":"Degersheim",
    "sg:orig_category":"Organisationen des Gesundheitswesen",
    "sg:phone":"+41 71 371 11 36",
    "sg:postcode":"9113",
    "sg:province":"St. Gallen",
    "wof:name":"Samariterverein Degersheim",
    "wof:placetype":"venue"
},
  "geometry": {"coordinates":[9.2025299072,47.3754997253],"type":"Point"}
}