{
  "type": "Feature",
  "properties": {
    "iso:country":"CH",
    "sg:address":"Wassergrabe 10",
    "sg:city":"Sursee",
    "sg:orig_category":"Non-Classified Establishments",
    "sg:postcode":"6210",
    "sg:province":"Luzern",
    "wof:name":"R + O Removals & Storage S\u00e0rl D\u00e9m\u00e9nagements, Op\u00e9rations Transitaires Et De Douane",
    "wof:placetype":"venue"
},
  "geometry": {"coordinates":[6.1414251328,46.1833114624],"type":"Point"}
}