{
  "type": "Feature",
  "properties": {
    "iso:country":"CH",
    "sg:address":"Rue Des Indiennes 11",
    "sg:city":"Marin-epagnier",
    "sg:classifiers":[
        {
            "category":"Food & Beverages",
            "subcategory":"Fruits & Vegetables",
            "type":"Retail Goods"
        }
    ],
    "sg:phone":"+41 32 753 38 66",
    "sg:postcode":"2074",
    "sg:province":"Neuch\u00e2tel",
    "sg:tags":[
        "frozen",
        "product",
        "related"
    ],
    "wof:name":"Intergel Multifood",
    "wof:placetype":"venue"
},
  "geometry": {"coordinates":[6.9969658852,47.0108261108],"type":"Point"}
}