{
  "type": "Feature",
  "properties": {
    "iso:country":"CH",
    "sg:address":"Bergstrasse 2 8712 St\u00e4fa. Postfach 535",
    "sg:city":"St\u00e4fa",
    "sg:orig_category":"Bau\u00e4mter",
    "sg:postcode":"8712",
    "sg:province":"Z\u00fcrich",
    "wof:name":"Baukommission Des Bezirks Schlatt-haslen",
    "wof:placetype":"venue"
},
  "geometry": {"coordinates":[9.36713,47.36948],"type":"Point"}
}