{
  "type": "Feature",
  "properties": {
    "iso:country":"CH",
    "sg:address":"Wolserstrasse 72",
    "sg:city":"Obfelden",
    "sg:orig_category":"Malerei",
    "sg:phone":"+41 17614161",
    "sg:postcode":"8912",
    "sg:province":"Z\u00fcrich",
    "wof:name":"Alfred Launer Malergesch\u00e4ft",
    "wof:placetype":"venue"
},
  "geometry": {"coordinates":[8.4260702133,47.2600212097],"type":"Point"}
}