{
  "type": "Feature",
  "properties": {
    "addr:full":"Im Ried 16 Eggersriet St. Gallen 9034",
    "addr:housenumber":"16",
    "addr:postcode":"9034",
    "addr:street":"Im Ried",
    "iso:country":"CH",
    "sg:address":"Im Ried 16",
    "sg:city":"Eggersriet",
    "sg:orig_category":"Betrieb U technische Hilfsdienste des Kultur U Unterhaltungswesens",
    "sg:postcode":"9034",
    "sg:province":"St. Gallen",
    "wof:name":"Chrisal Christina Alder",
    "wof:placetype":"venue"
},
  "geometry": {"coordinates":[9.46852,47.442291],"type":"Point"}
}