{
  "type": "Feature",
  "properties": {
    "iso:country":"CH",
    "sg:address":"Im Schilf 6",
    "sg:city":"Herrliberg",
    "sg:orig_category":"Vermietung U Verpachtung von eigenen Immobilien",
    "sg:phone":"+41 19153770",
    "sg:postcode":"8704",
    "sg:province":"Z\u00fcrich",
    "wof:name":"Immoconsulta Ag",
    "wof:placetype":"venue"
},
  "geometry": {"coordinates":[8.6135377884,47.2861976624],"type":"Point"}
}