{
  "type": "Feature",
  "properties": {
    "iso:country":"CH",
    "sg:address":"Schwadernaustr. 61",
    "sg:city":"Aegerten",
    "sg:classifiers":[
        {
            "category":"Manufacturing",
            "subcategory":"Metals",
            "type":"Manufacturing & Wholesale Goods"
        }
    ],
    "sg:phone":"+41 32 373 53 14",
    "sg:postcode":"2558",
    "sg:province":"Bern",
    "sg:tags":[
        "metallurgy",
        "metalworking",
        "processing"
    ],
    "wof:name":"Estoppey-reber Sa",
    "wof:placetype":"venue"
},
  "geometry": {"coordinates":[7.2958869934,47.1244544983],"type":"Point"}
}