{
  "type": "Feature",
  "properties": {
    "addr:full":"Leukerbad Leukerbad Valais 3953",
    "addr:postcode":"3953",
    "iso:country":"CH",
    "sg:address":"Leukerbad",
    "sg:city":"Leukerbad",
    "sg:classifiers":[
        {
            "category":"Banks & Credit Unions",
            "subcategory":"Bank",
            "type":"Services"
        }
    ],
    "sg:phone":"+41 27 473 25 39",
    "sg:postcode":"3953",
    "sg:province":"Valais",
    "wof:name":"Spar- Und Leihkasse, Leuk Und Umgebung",
    "wof:placetype":"venue"
},
  "geometry": {"coordinates":[7.59498,46.346088],"type":"Point"}
}