{
  "type": "Feature",
  "properties": {
    "iso:country":"CH",
    "sg:address":"L\u00f6wenhaus",
    "sg:city":"K\u00fcmmertshausen",
    "sg:orig_category":"Bauschreinerei Herstellung von M\u00f6beln verschiedener Art",
    "sg:phone":"+41 71 411 67 33",
    "sg:postcode":"8586",
    "sg:province":"Thurgau",
    "wof:name":"Paul Gsell M\u00f6belschreinerei",
    "wof:placetype":"venue"
},
  "geometry": {"coordinates":[9.24117,47.565632],"type":"Point"}
}