{
  "type": "Feature",
  "properties": {
    "iso:country":"CH",
    "sg:address":"3805",
    "sg:city":"Goldswil",
    "sg:orig_category":"Vereine Gesang",
    "sg:postcode":"3805",
    "sg:province":"Bern",
    "wof:name":"Gemischter Chor Goldswil",
    "wof:placetype":"venue"
},
  "geometry": {"coordinates":[7.876349926,46.7023506165],"type":"Point"}
}