{
  "type": "Feature",
  "properties": {
    "iso:country":"CH",
    "sg:address":"Yverdon Route D' 8",
    "sg:city":"Estavayer-le-lac",
    "sg:orig_category":"Sonstiger Fachdetailhandel mit Nahrungsmitteln, Getr\u00e4nken U Tabak in Verkaufsr\u00e4umen",
    "sg:postcode":"1470",
    "sg:province":"Fribourg",
    "wof:name":"Damalp Sa",
    "wof:placetype":"venue"
},
  "geometry": {"coordinates":[6.8482699394,46.8487892151],"type":"Point"}
}