{
  "type": "Feature",
  "properties": {
    "iso:country":"CH",
    "sg:address":"2803",
    "sg:city":"Bourrignon",
    "sg:classifiers":[
        {
            "category":"Restaurant",
            "type":"Food & Drink"
        }
    ],
    "sg:phone":"+41 32 431 18 38",
    "sg:postcode":"2803",
    "sg:province":"Jura",
    "wof:name":"Restaurant Le Grenier",
    "wof:placetype":"venue"
},
  "geometry": {"coordinates":[7.244243145,47.3972358704],"type":"Point"}
}