{
  "type": "Feature",
  "properties": {
    "iso:country":"CH",
    "sg:address":"Vordere Hauptgasse 74",
    "sg:city":"Zofingen",
    "sg:orig_category":"Konkurs- and Betreibungs\u00e4mter",
    "sg:phone":"+41 62 751 15 49",
    "sg:postcode":"4800",
    "sg:province":"Aargau",
    "wof:name":"Betreibungsamt",
    "wof:placetype":"venue"
},
  "geometry": {"coordinates":[7.9450712204,47.288192749],"type":"Point"}
}