{
  "type": "Feature",
  "properties": {
    "iso:country":"CH",
    "sg:address":"W\u00e4sserwiesenstrasse 95 Hinter Volvo Auto H\u00e4rti Ag",
    "sg:city":"Winterthur",
    "sg:orig_category":"Detailhandel Handel mit Motorr\u00e4dern, Teilen U Zubeh\u00f6r Instandhaltung U Reparatur von Motorr\u00e4dern Rep",
    "sg:phone":"+41 52 222 78 58",
    "sg:postcode":"8408",
    "sg:province":"Z\u00fcrich",
    "wof:name":"Schlatter Motorr\u00e4der Ag I Exklusiv Honda Vertretung",
    "wof:placetype":"venue"
},
  "geometry": {"coordinates":[8.6934547424,47.5105857849],"type":"Point"}
}