{
  "type": "Feature",
  "properties": {
    "iso:country":"CH",
    "sg:address":"Kirchstrasse 24",
    "sg:city":"Glarus",
    "sg:orig_category":"Detailhandel mit elektrischen Haushalts-,Radio U Fernsehger\u00e4ten sowie Musikinstrumenten",
    "sg:postcode":"8750",
    "sg:province":"Glarus",
    "wof:name":"Heiz Theo, Inhaberin Frau Heiz-sp\u00f6rri L.",
    "wof:placetype":"venue"
},
  "geometry": {"coordinates":[9.066491127,47.0407104492],"type":"Point"}
}