{
  "type": "Feature",
  "properties": {
    "iso:country":"CH",
    "sg:address":"Ohne Domizil 6330 Cham. Postfach",
    "sg:city":"Cham",
    "sg:classifiers":[
        {
            "category":"Bars & Pubs",
            "type":"Food & Drink"
        }
    ],
    "sg:phone":"+41 41 781 03 81",
    "sg:postcode":"6330",
    "sg:province":"Zug",
    "wof:name":"Gma Gastro Management Ag",
    "wof:placetype":"venue"
},
  "geometry": {"coordinates":[8.458923,47.18079],"type":"Point"}
}