{
  "type": "Feature",
  "properties": {
    "iso:country":"CH",
    "sg:address":"Route D'allaman",
    "sg:city":"Etoy",
    "sg:orig_category":"Instandhaltung U Reparatur von Automobilen",
    "sg:phone":"+41 21 807 41 41",
    "sg:postcode":"1163",
    "sg:province":"Vaud",
    "wof:name":"Iassogna Fernando",
    "wof:placetype":"venue"
},
  "geometry": {"coordinates":[6.4129710197,46.475025177],"type":"Point"}
}