{
  "type": "Feature",
  "properties": {
    "iso:country":"CH",
    "sg:address":"Kugelgasse 6",
    "sg:city":"St.gallen",
    "sg:orig_category":"RESTAURANTS: TEA-ROOMS",
    "sg:phone":"+41 71 223 66 60",
    "sg:postcode":"9000",
    "sg:province":"St. Gallen",
    "wof:name":"La Boule, Caf\u00e9 Conditorei Schedler-kern Barbara",
    "wof:placetype":"venue"
},
  "geometry": {"coordinates":[9.3773698807,47.4254264832],"type":"Point"}
}