{
  "type": "Feature",
  "properties": {
    "iso:country":"CH",
    "sg:address":"Straussweg 8",
    "sg:city":"Meierskappel",
    "sg:classifiers":[
        {
            "category":"Travel",
            "subcategory":"Hotels & Motels",
            "type":"Entertainment"
        }
    ],
    "sg:phone":"+41 41 790 11 65",
    "sg:postcode":"6344",
    "sg:province":"Luzern",
    "sg:tags":[
        "hotels",
        "mit",
        "restaurant"
    ],
    "wof:name":"Landgasthaus Strauss St\u00f6ckli Ruedi",
    "wof:placetype":"venue"
},
  "geometry": {"coordinates":[8.4439764023,47.1247024536],"type":"Point"}
}