{
  "type": "Feature",
  "properties": {
    "iso:country":"CH",
    "sg:address":"Rue De Lausanne 63",
    "sg:city":"Gen\u00e8ve",
    "sg:orig_category":"Detailhandel mit M\u00f6beln U Haushaltsgegenst\u00e4nden Grosshandel mit M\u00f6beln, Wohnbedarf, Teppichen U Bode",
    "sg:phone":"+41 22 738 74 54",
    "sg:postcode":"1202",
    "sg:province":"Gen\u00e8ve",
    "wof:name":"Sa Pour La Diffusion Des Produits Mondialmoquette",
    "wof:placetype":"venue"
},
  "geometry": {"coordinates":[6.1467909813,46.2154846191],"type":"Point"}
}