{
  "type": "Feature",
  "properties": {
    "iso:country":"CH",
    "sg:address":"Bruderholzallee 167",
    "sg:city":"Basel",
    "sg:orig_category":"Gesundheitswesen",
    "sg:postcode":"4059",
    "sg:province":"Basel-Stadt",
    "wof:name":"Verein Tele-hilfe Basel",
    "wof:placetype":"venue"
},
  "geometry": {"coordinates":[7.5942101479,47.5327568054],"type":"Point"}
}