{
  "type": "Feature",
  "properties": {
    "iso:country":"CH",
    "sg:address":"Bahnhofplatz 8 7000 Chur. Postfach",
    "sg:city":"Chur",
    "sg:orig_category":"Architektur U Ingenieurb\u00fcros",
    "sg:phone":"+41 71 388 80 90",
    "sg:postcode":"7000",
    "sg:province":"Graubunden",
    "wof:name":"Bauline Gmbh",
    "wof:placetype":"venue"
},
  "geometry": {"coordinates":[9.263152,47.412975],"type":"Point"}
}