{
  "type": "Feature",
  "properties": {
    "iso:country":"CH",
    "sg:address":"Hauptstrasse 30 4416 Bubendorf. Postfach",
    "sg:city":"Bubendorf",
    "sg:orig_category":"G\u00fcterbef\u00f6rderung im Strassenverkehr Herstellung von Schmuck, Gold U Silberschmiedwaren",
    "sg:phone":"+41 61 931 27 95",
    "sg:postcode":"4416",
    "sg:province":"Basel-Landschaft",
    "wof:name":"Rizmann Kata's Transporte Goldschmiedatelier. Warenhandel, Bes. Lebensmittel U. Alkoholische Getr\u00e4nke. Transporte",
    "wof:placetype":"venue"
},
  "geometry": {"coordinates":[7.7374119759,47.4527702332],"type":"Point"}
}