{
  "type": "Feature",
  "properties": {
    "iso:country":"CH",
    "sg:address":"Via Rongia 6596 Gordola. Postfach",
    "sg:city":"Gordola",
    "sg:orig_category":"Sonstiger Grosshandel",
    "sg:postcode":"6596",
    "sg:province":"Ticino",
    "wof:name":"Wezid Handelsagentur, B. Salina",
    "wof:placetype":"venue"
},
  "geometry": {"coordinates":[8.8673191071,46.1817169189],"type":"Point"}
}