{
  "type": "Feature",
  "properties": {
    "iso:country":"CH",
    "sg:address":"Dorfstrasse 23 3715 Adelboden. Postfach 310",
    "sg:city":"Adelboden",
    "sg:orig_category":"Verkehrs- and Tourismusb\u00fcros",
    "sg:phone":"+41 27 958 18 58",
    "sg:postcode":"3715",
    "sg:province":"Bern",
    "wof:name":"Tourist Office",
    "wof:placetype":"venue"
},
  "geometry": {"coordinates":[7.933672905,46.1117172241],"type":"Point"}
}