{
  "type": "Feature",
  "properties": {
    "iso:country":"CH",
    "sg:address":"6253",
    "sg:city":"Uffikon",
    "sg:orig_category":"Erschliessung von Grundst\u00fccken",
    "sg:postcode":"6253",
    "sg:province":"Luzern",
    "wof:name":"Baugenossenschaft \u00absonnig-hus, St. Gallen\u00bb",
    "wof:placetype":"venue"
},
  "geometry": {"coordinates":[9.3799314499,47.4420547485],"type":"Point"}
}