{
  "type": "Feature",
  "properties": {
    "iso:country":"CH",
    "sg:address":"Via Del Tiglio 23",
    "sg:city":"Lugano",
    "sg:classifiers":[
        {
            "category":"Bars & Pubs",
            "type":"Food & Drink"
        }
    ],
    "sg:phone":"+41 91 971 41 98",
    "sg:postcode":"6900",
    "sg:province":"Ticino",
    "wof:name":"Lilly Bar Propr. Causo Silvio",
    "wof:placetype":"venue"
},
  "geometry": {"coordinates":[8.964517,46.00787],"type":"Point"}
}