{
  "type": "Feature",
  "properties": {
    "iso:country":"CH",
    "sg:address":"Algierstrasse 1",
    "sg:city":"Z\u00fcrich",
    "sg:orig_category":"Sonstiges Versicherungsgewerbe",
    "sg:phone":"+41 33 442 22 00",
    "sg:postcode":"8048",
    "sg:province":"Z\u00fcrich",
    "wof:name":"Krankenkasse Assura Agentur",
    "wof:placetype":"venue"
},
  "geometry": {"coordinates":[7.6560149193,46.758140564],"type":"Point"}
}