{
  "type": "Feature",
  "properties": {
    "iso:country":"CH",
    "sg:address":"Cho D'punt 64/66",
    "sg:city":"Samedan",
    "sg:orig_category":"Zimmerei, Ingenieurholzbau",
    "sg:phone":"+41 81 852 37 66",
    "sg:postcode":"7503",
    "sg:province":"Graubunden",
    "wof:name":"A. Freund Holzbau Gmbh Zimmerei",
    "wof:placetype":"venue"
},
  "geometry": {"coordinates":[9.8728303909,46.5353507996],"type":"Point"}
}