{
  "type": "Feature",
  "properties": {
    "iso:country":"CH",
    "sg:address":"Bernerweg 11 6003 Luzern. Postfach",
    "sg:city":"Luzern",
    "sg:orig_category":"Grosshandel mit sonstigen Gebrauchs U Verbrauchsg\u00fctern",
    "sg:phone":"+41 41 252 09 09",
    "sg:postcode":"6003",
    "sg:province":"Luzern",
    "wof:name":"Schumacher Roland Edelsteinhandel",
    "wof:placetype":"venue"
},
  "geometry": {"coordinates":[8.2832841873,47.052230835],"type":"Point"}
}