{
  "type": "Feature",
  "properties": {
    "iso:country":"CH",
    "sg:address":"Niederglatterstrasse 10",
    "sg:city":"Niederhasli",
    "sg:orig_category":"Malerei-Gipserei Stukkateurgewerbe, Gipserei U Verputzerei",
    "sg:phone":"+41 79 401 17 08",
    "sg:postcode":"8155",
    "sg:province":"Z\u00fcrich",
    "wof:name":"Di Pascuale Gipsergesch\u00e4ft",
    "wof:placetype":"venue"
},
  "geometry": {"coordinates":[8.4858007431,47.4811019897],"type":"Point"}
}