{
  "type": "Feature",
  "properties": {
    "iso:country":"CH",
    "sg:address":"4813",
    "sg:city":"Uerkheim",
    "sg:orig_category":"Primarschulen",
    "sg:phone":"+41 62 721 30 12",
    "sg:postcode":"4813",
    "sg:province":"Aargau",
    "wof:name":"Primarschule Schulhaus H\u00fcbeli",
    "wof:placetype":"venue"
},
  "geometry": {"coordinates":[8.0247764587,47.3047218323],"type":"Point"}
}