{
  "type": "Feature",
  "properties": {
    "iso:country":"CH",
    "sg:address":"Schachenweg 4c",
    "sg:city":"Windisch",
    "sg:classifiers":[
        {
            "category":"Professional",
            "subcategory":"Engineering",
            "type":"Services"
        }
    ],
    "sg:phone":"+41 56 450 33 71",
    "sg:postcode":"5210",
    "sg:province":"Aargau",
    "wof:name":"Armafluid Gmbh",
    "wof:placetype":"venue"
},
  "geometry": {"coordinates":[8.2292900085,47.4836196899],"type":"Point"}
}