{
  "type": "Feature",
  "properties": {
    "iso:country":"CH",
    "sg:address":"Schl\u00f6sslirain 5 6006 Luzern. Postfach",
    "sg:city":"Luzern",
    "sg:orig_category":"Grosshandel mit Textilien",
    "sg:postcode":"6006",
    "sg:province":"Luzern",
    "wof:name":"E-socks Wespi Adrian Textilien; Handel",
    "wof:placetype":"venue"
},
  "geometry": {"coordinates":[8.3380146027,47.0558776855],"type":"Point"}
}