{
  "type": "Feature",
  "properties": {
    "iso:country":"CH",
    "sg:address":"Grand-rue 7",
    "sg:city":"Sorvilier",
    "sg:orig_category":"Architekturb\u00fcros",
    "sg:phone":"+41 32 492 21 62",
    "sg:postcode":"2736",
    "sg:province":"Bern",
    "wof:name":"Jean-paul Romy Bureau D'architecture",
    "wof:placetype":"venue"
},
  "geometry": {"coordinates":[7.30534,47.239479],"type":"Point"}
}