{
  "type": "Feature",
  "properties": {
    "addr:full":"Route Des Iles 88 Bouveret Valais 1897",
    "addr:housenumber":"88",
    "addr:postcode":"1897",
    "addr:street":"Route Des Iles",
    "iso:country":"CH",
    "sg:address":"Route Des Iles 88",
    "sg:city":"Bouveret",
    "sg:classifiers":[
        {
            "category":"Organizations",
            "subcategory":"Community Association",
            "type":"Services"
        }
    ],
    "sg:phone":"+41 24 481 24 21",
    "sg:postcode":"1897",
    "sg:province":"Valais",
    "sg:tags":[
        "oils",
        "oil",
        "composition",
        "perfume"
    ],
    "wof:name":"Symrise",
    "wof:placetype":"venue"
},
  "geometry": {"coordinates":[6.864928,46.379108],"type":"Point"}
}