{
  "type": "Feature",
  "properties": {
    "addr:full":"Seestrasse 227 8810 Horgen. Postfach Horgen Z\u00fcrich 8810",
    "addr:housenumber":"227",
    "addr:postcode":"8810;8810",
    "addr:street":"Seestrasse",
    "iso:country":"CH",
    "sg:address":"Seestrasse 227 8810 Horgen. Postfach",
    "sg:city":"Horgen",
    "sg:orig_category":"Architektur U Ingenieurb\u00fcros",
    "sg:phone":"+41 17276464",
    "sg:postcode":"8810",
    "sg:province":"Z\u00fcrich",
    "wof:name":"Dachtler Partner Ag Architekturb\u00fcro, Dienstleistungen Im Baugewerbe Usw",
    "wof:placetype":"venue"
},
  "geometry": {"coordinates":[8.605592,47.258018],"type":"Point"}
}