{
  "type": "Feature",
  "properties": {
    "iso:country":"CH",
    "sg:address":"Holderenweg 7",
    "sg:city":"Weinfelden",
    "sg:orig_category":"Vermittlung von Immobilien",
    "sg:phone":"+41 71 622 22 66",
    "sg:postcode":"8570",
    "sg:province":"Thurgau",
    "wof:name":"Alfred Diethelm Liegenschaften",
    "wof:placetype":"venue"
},
  "geometry": {"coordinates":[9.1018381119,47.5711631775],"type":"Point"}
}