{
  "type": "Feature",
  "properties": {
    "iso:country":"CH",
    "sg:address":"Ch\u00eane-bougeries Rue De 20 1224 Ch\u00eane-bougeries. Postfach",
    "sg:city":"Ch\u00eane-bougeries",
    "sg:orig_category":"Zimmerei, Dachdeckerei, Bauspenglerei U Abdichtung",
    "sg:postcode":"1224",
    "sg:province":"Gen\u00e8ve",
    "wof:name":"Von Siebenthal Holzbau Ag",
    "wof:placetype":"venue"
},
  "geometry": {"coordinates":[9.170425415,47.589553833],"type":"Point"}
}