{
  "type": "Feature",
  "properties": {
    "iso:country":"CH",
    "sg:address":"Fleurettes Chemin Des 41 1007 Lausanne Case Postale",
    "sg:city":"Lausanne",
    "sg:orig_category":"Fotografisches Gewerbe U fotografische Laboratorien",
    "sg:phone":"+41 21 616 33 22",
    "sg:postcode":"1003",
    "sg:province":"Vaud",
    "wof:name":"Saxod J. Atelier De Travaux Photographiques",
    "wof:placetype":"venue"
},
  "geometry": {"coordinates":[6.619743824,46.5171928406],"type":"Point"}
}