{
  "type": "Feature",
  "properties": {
    "iso:country":"CH",
    "sg:address":"Sch\u00f6nmaieng\u00e4sschen 1 8200 Schaffhausen. Postfach 232",
    "sg:city":"Schaffhausen",
    "sg:orig_category":"Advokaturb\u00fcros",
    "sg:phone":"+41 79 344 29 62",
    "sg:postcode":"8201",
    "sg:province":"Schaffhausen",
    "wof:name":"Eva Cerny Advokaturb\u00fcro",
    "wof:placetype":"venue"
},
  "geometry": {"coordinates":[8.63552,47.695702],"type":"Point"}
}