{
  "type": "Feature",
  "properties": {
    "addr:full":"Bleicherweg 66 Z\u00fcrich Z\u00fcrich 8002",
    "addr:housenumber":"66",
    "addr:postcode":"8002",
    "addr:street":"Bleicherweg",
    "iso:country":"CH",
    "sg:address":"Bleicherweg 66",
    "sg:city":"Z\u00fcrich",
    "sg:orig_category":"Arztpraxen",
    "sg:phone":"+41 12062200",
    "sg:postcode":"8002",
    "sg:province":"Z\u00fcrich",
    "wof:name":"Dr.med.thomas Dan Blasbalg Spezialarzt Fmh",
    "wof:placetype":"venue"
},
  "geometry": {"coordinates":[8.533197,47.366882],"type":"Point"}
}