{
  "type": "Feature",
  "properties": {
    "iso:country":"CH",
    "sg:address":"Idastrasse 28",
    "sg:city":"Z\u00fcrich",
    "sg:orig_category":"Physiotherapie",
    "sg:phone":"+41 14625835",
    "sg:postcode":"8003",
    "sg:province":"Z\u00fcrich",
    "wof:name":"Sibylla Jaeger Physiotherapie",
    "wof:placetype":"venue"
},
  "geometry": {"coordinates":[8.5152359009,47.3732681274],"type":"Point"}
}