{
  "type": "Feature",
  "properties": {
    "iso:country":"CH",
    "sg:address":"Rueteli 254",
    "sg:city":"Unterb\u00f6zberg",
    "sg:orig_category":"Detailhandel mit Getr\u00e4nken Detailhandel mit Waren verschiedener Art, Hauptrichtung Nahrungsmittel",
    "sg:phone":"+41 56 441 40 00",
    "sg:postcode":"5224",
    "sg:province":"Aargau",
    "wof:name":"Lorenz Eschbach Dorfladen & Getr\u00e4nke",
    "wof:placetype":"venue"
},
  "geometry": {"coordinates":[8.1733417511,47.4836807251],"type":"Point"}
}