{
  "type": "Feature",
  "properties": {
    "iso:country":"CH",
    "sg:address":"Boulevard De P\u00e9rolles 31 1700 Fribourg. Postfach",
    "sg:city":"Fribourg",
    "sg:orig_category":"Detailhandel mit Musikinstrumenten Detailhandel mit elektrischen Haushalts-,Radio U Fernsehger\u00e4ten s",
    "sg:postcode":"1705",
    "sg:province":"Fribourg",
    "wof:name":"Jaccoud Elise",
    "wof:placetype":"venue"
},
  "geometry": {"coordinates":[7.1529722214,46.7985343933],"type":"Point"}
}