{
  "type": "Feature",
  "properties": {
    "iso:country":"CH",
    "sg:address":"Via Trevano 73",
    "sg:city":"Lugano",
    "sg:orig_category":"Grosshandel mit Holz U Baustoffen",
    "sg:phone":"+41 91 971 06 16",
    "sg:postcode":"6900",
    "sg:province":"Ticino",
    "wof:name":"Gesslibe Sagl",
    "wof:placetype":"venue"
},
  "geometry": {"coordinates":[8.9570446014,46.0190963745],"type":"Point"}
}