{
  "type": "Feature",
  "properties": {
    "iso:country":"CH",
    "sg:address":"Gurnigelstrasse 12",
    "sg:city":"Thun",
    "sg:orig_category":"Hundesalons",
    "sg:phone":"+41 33 223 47 04",
    "sg:postcode":"3600",
    "sg:province":"Bern",
    "wof:name":"Katrin Stucki Hundesalon Bobby",
    "wof:placetype":"venue"
},
  "geometry": {"coordinates":[7.6217827797,46.7557296753],"type":"Point"}
}