{
  "type": "Feature",
  "properties": {
    "iso:country":"CH",
    "sg:address":"Bernstrasse 74",
    "sg:city":"Ostermundigen",
    "sg:orig_category":"Non-Classified Establishments",
    "sg:postcode":"3072",
    "sg:province":"Bern",
    "wof:name":"Delmarkt Gmbh",
    "wof:placetype":"venue"
},
  "geometry": {"coordinates":[7.4906039238,46.9581451416],"type":"Point"}
}