{
  "type": "Feature",
  "properties": {
    "iso:country":"CH",
    "sg:address":"Neufeldstrasse 5 A 3076 Bangerten B. Worb. Postfach 321",
    "sg:city":"Worb",
    "sg:orig_category":"Unclassifiable Establishments",
    "sg:phone":"+41 31 838 16 16",
    "sg:postcode":"3076",
    "sg:province":"Bern",
    "wof:name":"Sanit\u00e4r Rupp Ag",
    "wof:placetype":"venue"
},
  "geometry": {"coordinates":[7.5602049828,46.9346809387],"type":"Point"}
}