{
  "type": "Feature",
  "properties": {
    "iso:country":"CH",
    "sg:address":"Streulistrasse 11",
    "sg:city":"Z\u00fcrich",
    "sg:orig_category":"Werbung",
    "sg:phone":"+41 13818384",
    "sg:postcode":"8032",
    "sg:province":"Z\u00fcrich",
    "wof:name":"Schiller Verena, Werbe Und Produktionsberatung Werbe, Produktionsberatung. Werbemittel, Bes. Inserate Usw; Herst",
    "wof:placetype":"venue"
},
  "geometry": {"coordinates":[8.5610809326,47.366443634],"type":"Point"}
}