{
  "type": "Feature",
  "properties": {
    "iso:country":"CH",
    "sg:address":"Langgr\u00fctstrasse 37",
    "sg:city":"Z\u00fcrich",
    "sg:orig_category":"Grosshandel mit sonstigen Gebrauchs U Verbrauchsg\u00fctern",
    "sg:phone":"+41 41 926 71 71",
    "sg:postcode":"8047",
    "sg:province":"Z\u00fcrich",
    "wof:name":"Escor Automaten Ag",
    "wof:placetype":"venue"
},
  "geometry": {"coordinates":[8.0744695663,47.1829185486],"type":"Point"}
}