{
  "type": "Feature",
  "properties": {
    "iso:country":"CH",
    "sg:address":"Chesa Cum\u00fcnela",
    "sg:city":"Pontresina",
    "sg:orig_category":"Reiseb\u00fcros U Reiseveranstalter",
    "sg:phone":"+41 81 838 83 00",
    "sg:postcode":"7504",
    "sg:province":"Graubunden",
    "wof:name":"Verein Ferienregion Engadin",
    "wof:placetype":"venue"
},
  "geometry": {"coordinates":[9.9048089981,46.4893798828],"type":"Point"}
}