{
  "type": "Feature",
  "properties": {
    "iso:country":"CH",
    "sg:address":"Hinterbergstrasse 28",
    "sg:city":"Zug",
    "sg:orig_category":"Wirtschaftspr\u00fcfung, Steuerberatung U Treuhand",
    "sg:postcode":"6300",
    "sg:province":"Zug",
    "wof:name":"Ais Ivanov A., Administration & Management Service",
    "wof:placetype":"venue"
},
  "geometry": {"coordinates":[8.5162153244,47.1715087891],"type":"Point"}
}