{
  "type": "Feature",
  "properties": {
    "iso:country":"CH",
    "sg:address":"Wolserstrasse 4",
    "sg:city":"Obfelden",
    "sg:orig_category":"Mechanik Stahl U Leichtmetallbau",
    "sg:phone":"+41 17613608",
    "sg:postcode":"8912",
    "sg:province":"Z\u00fcrich",
    "wof:name":"Remo Plozza Schlosserei Metallbau",
    "wof:placetype":"venue"
},
  "geometry": {"coordinates":[8.4289484024,47.2632408142],"type":"Point"}
}