{
  "type": "Feature",
  "properties": {
    "iso:country":"CH",
    "sg:address":"Auberge 155",
    "sg:city":"Bellelay",
    "sg:classifiers":[
        {
            "category":"Travel",
            "subcategory":"Hotels & Motels",
            "type":"Entertainment"
        }
    ],
    "sg:phone":"+41 32 484 97 27",
    "sg:postcode":"2713",
    "sg:province":"Bern",
    "sg:tags":[
        "hotels",
        "mit",
        "restaurant"
    ],
    "wof:name":"Krebs Jean-robert",
    "wof:placetype":"venue"
},
  "geometry": {"coordinates":[7.1666350365,47.2626724243],"type":"Point"}
}