{
  "type": "Feature",
  "properties": {
    "iso:country":"CH",
    "sg:address":"Niffel 6280 Hochdorf. Postfach 953",
    "sg:city":"Hochdorf",
    "sg:orig_category":"Grosshandel mit Wein U Spirituosen Mineralquellen, Herstellung von alkoholfreien Getr\u00e4nken",
    "sg:phone":"+41 41 910 10 79",
    "sg:postcode":"6281",
    "sg:province":"Luzern",
    "wof:name":"Lupo-getr\u00e4nke",
    "wof:placetype":"venue"
},
  "geometry": {"coordinates":[8.2893247604,47.1669769287],"type":"Point"}
}