{
  "type": "Feature",
  "properties": {
    "iso:country":"CH",
    "sg:address":"B\u00fcelmattweg 6",
    "sg:city":"Baar",
    "sg:orig_category":"Sonstige mit der Informatik verbundene T\u00e4tigkeiten",
    "sg:phone":"+41 41 852 10 10",
    "sg:postcode":"6340",
    "sg:province":"Zug",
    "wof:name":"Acn Matthias Baier",
    "wof:placetype":"venue"
},
  "geometry": {"coordinates":[8.4372529984,47.0865402222],"type":"Point"}
}