{
  "type": "Feature",
  "properties": {
    "iso:country":"CH",
    "sg:address":"Werkstrasse 31",
    "sg:city":"Lyss",
    "sg:orig_category":"Bauspenglerei Sanit\u00e4r, Heizungs U L\u00fcftungsinstallation",
    "sg:phone":"+41 32 751 22 39",
    "sg:postcode":"3250",
    "sg:province":"Bern",
    "wof:name":"Muttner Robert",
    "wof:placetype":"venue"
},
  "geometry": {"coordinates":[7.064404,47.05434],"type":"Point"}
}