{
  "type": "Feature",
  "properties": {
    "iso:country":"CH",
    "sg:address":"Weizenstrasse 12",
    "sg:city":"Wettingen",
    "sg:orig_category":"Herstellung von sonstigen Metallwaren",
    "sg:phone":"+41 56 426 29 04",
    "sg:postcode":"5430",
    "sg:province":"Aargau",
    "wof:name":"Mcs Magnet Consulting Services Berkes Dipl. Ing. Branko",
    "wof:placetype":"venue"
},
  "geometry": {"coordinates":[8.3320503235,47.468788147],"type":"Point"}
}