{
  "type": "Feature",
  "properties": {
    "iso:country":"CH",
    "sg:address":"Fabrikweg 12",
    "sg:city":"Rickenbach",
    "sg:classifiers":[
        {
            "category":"Utilities",
            "subcategory":"Cable",
            "type":"Services"
        }
    ],
    "sg:phone":"+41 41 930 21 05",
    "sg:postcode":"6221",
    "sg:province":"Luzern",
    "sg:tags":[
        "ready",
        "use",
        "cables",
        "finished"
    ],
    "wof:name":"Alomac Fabrikationen Ag",
    "wof:placetype":"venue"
},
  "geometry": {"coordinates":[8.150257,47.223736],"type":"Point"}
}