{
  "type": "Feature",
  "properties": {
    "iso:country":"CH",
    "sg:address":"Vuaracaux Chemin En 3",
    "sg:city":"Founex",
    "sg:orig_category":"Sonstiger Grosshandel",
    "sg:phone":"+41 22 776 18 14",
    "sg:postcode":"1297",
    "sg:province":"Vaud",
    "wof:name":"Sevilon Sa",
    "wof:placetype":"venue"
},
  "geometry": {"coordinates":[6.1657400131,46.3367919922],"type":"Point"}
}