{
  "type": "Feature",
  "properties": {
    "iso:country":"CH",
    "sg:address":"Im Zentrum 19",
    "sg:city":"Volketswil",
    "sg:orig_category":"Erbringung von Dienstleistungen f\u00fcr Unternehmen",
    "sg:postcode":"8604",
    "sg:province":"Z\u00fcrich",
    "wof:name":"Musikagentur Niederberger Theo",
    "wof:placetype":"venue"
},
  "geometry": {"coordinates":[8.6813526154,47.3875846863],"type":"Point"}
}