{
  "type": "Feature",
  "properties": {
    "iso:country":"CH",
    "sg:address":"Lindenthalstrasse 7",
    "sg:city":"Boll",
    "sg:orig_category":"Wohnheime",
    "sg:postcode":"3067",
    "sg:province":"Bern",
    "wof:name":"Stiftung Alterswohnungen Vechigen",
    "wof:placetype":"venue"
},
  "geometry": {"coordinates":[7.5491728783,46.9551963806],"type":"Point"}
}