{
  "type": "Feature",
  "properties": {
    "iso:country":"CH",
    "sg:address":"Alte Tannerstrasse 20",
    "sg:city":"Tann",
    "sg:orig_category":"Nationale Postdienste",
    "sg:phone":"+41 52 240 25 05",
    "sg:postcode":"8632",
    "sg:province":"Z\u00fcrich",
    "wof:name":"Die Schweizerische Post",
    "wof:placetype":"venue"
},
  "geometry": {"coordinates":[8.8523187637,47.2685394287],"type":"Point"}
}