{
  "type": "Feature",
  "properties": {
    "iso:country":"CH",
    "sg:address":"7551",
    "sg:city":"Ftan",
    "sg:classifiers":[
        {
            "category":"Education",
            "subcategory":"Library",
            "type":"Public Place"
        }
    ],
    "sg:phone":"+41 81 864 08 20",
    "sg:postcode":"7551",
    "sg:province":"Graubunden",
    "sg:tags":[
        "u",
        "bibliotheken",
        "archive"
    ],
    "wof:name":"Gemeindebibliothek",
    "wof:placetype":"venue"
},
  "geometry": {"coordinates":[10.248668,46.794022],"type":"Point"}
}