{
  "type": "Feature",
  "properties": {
    "iso:country":"CH",
    "sg:address":"Talstrasse 2",
    "sg:city":"Zollikon",
    "sg:orig_category":"Pensionskassen",
    "sg:phone":"+41 81 416 42 42",
    "sg:postcode":"8702",
    "sg:province":"Z\u00fcrich",
    "wof:name":"Personalf\u00fcrsorgestiftung Der Firma Gebr. D\u00fcrst Ag Davos",
    "wof:placetype":"venue"
},
  "geometry": {"coordinates":[9.8319244385,46.7988395691],"type":"Point"}
}