{
  "type": "Feature",
  "properties": {
    "iso:country":"CH",
    "sg:address":"Birren 6",
    "sg:city":"Seon",
    "sg:orig_category":"Einzelhandel mit Automobilteilen U Zubeh\u00f6r Herstellung von Bereifungen",
    "sg:phone":"+41 79 330 39 40",
    "sg:postcode":"5703",
    "sg:province":"Aargau",
    "wof:name":"Pneu Prall Br\u00e4ndli",
    "wof:placetype":"venue"
},
  "geometry": {"coordinates":[8.1645202637,47.3617286682],"type":"Point"}
}