{
  "type": "Feature",
  "properties": {
    "iso:country":"CH",
    "sg:address":"Route De L'etraz 164",
    "sg:city":"Aubonne",
    "sg:orig_category":"Bauingenieurb\u00fcros allgemein",
    "sg:phone":"+41 56 622 31 71",
    "sg:postcode":"1170",
    "sg:province":"Vaud",
    "wof:name":"L\u00fcthi & H\u00e4fliger Ingenieurb\u00fcro",
    "wof:placetype":"venue"
},
  "geometry": {"coordinates":[8.27791,47.350857],"type":"Point"}
}