{
  "type": "Feature",
  "properties": {
    "iso:country":"CH",
    "sg:address":"Reibestrasse 4",
    "sg:city":"Uster",
    "sg:orig_category":"P\u00e9dicure",
    "sg:phone":"+41 19403455",
    "sg:postcode":"8610",
    "sg:province":"Z\u00fcrich",
    "wof:name":"Lotte Engeler P\u00e9dicure",
    "wof:placetype":"venue"
},
  "geometry": {"coordinates":[8.7199344635,47.3473815918],"type":"Point"}
}