{
  "type": "Feature",
  "properties": {
    "iso:country":"CH",
    "sg:address":"Rue Du Perron 11",
    "sg:city":"Gland",
    "sg:orig_category":"Blumen U Zierpflanzenbau Landschaftsplanungsb\u00fcros U Gartenarchitekturb\u00fcros",
    "sg:phone":"+41 22 364 12 16",
    "sg:postcode":"1196",
    "sg:province":"Vaud",
    "wof:name":"Jean Rindlisbacher Horticulteur-paysagiste",
    "wof:placetype":"venue"
},
  "geometry": {"coordinates":[6.273816,46.419949],"type":"Point"}
}