{
  "type": "Feature",
  "properties": {
    "iso:country":"CH",
    "sg:address":"St. Gallerstrasse 5",
    "sg:city":"Rorschach",
    "sg:orig_category":"Detailhandel mit Waren verschiedener Art, Hauptrichtung Nahrungsmittel",
    "sg:phone":"+41 71 840 06 08",
    "sg:postcode":"9400",
    "sg:province":"St. Gallen",
    "wof:name":"Denner Top Superdiscount",
    "wof:placetype":"venue"
},
  "geometry": {"coordinates":[9.4881448746,47.4788131714],"type":"Point"}
}