{
  "type": "Feature",
  "properties": {
    "iso:country":"CH",
    "sg:address":"Rue Centrale 11",
    "sg:city":"Orient",
    "sg:orig_category":"Detailhandel mit Brot, Back U S\u00fcsswaren",
    "sg:phone":"+41 21 845 43 35",
    "sg:postcode":"1341",
    "sg:province":"Vaud",
    "wof:name":"Christian Defferrard Boulangerie De Chez Le Maitre",
    "wof:placetype":"venue"
},
  "geometry": {"coordinates":[6.240719,46.602356],"type":"Point"}
}