{
  "type": "Feature",
  "properties": {
    "iso:country":"CH",
    "sg:address":"Josefstrasse 59 8004 Z\u00fcrich. Postfach",
    "sg:city":"Z\u00fcrich",
    "sg:orig_category":"Pensionskassen",
    "sg:postcode":"8001",
    "sg:province":"Z\u00fcrich",
    "wof:name":"F\u00fcrsorge Und Ferienkasse Des Christlichen Holz Und Bauarbeiterverbandes",
    "wof:placetype":"venue"
},
  "geometry": {"coordinates":[8.5318098068,47.3821487427],"type":"Point"}
}