{
  "type": "Feature",
  "properties": {
    "iso:country":"CH",
    "sg:address":"Siewerdtstrasse 75 8000 Z\u00fcrich. Postfach 8050 Z\u00fcrich",
    "sg:city":"Zust",
    "sg:orig_category":"Sonstiger spezialisierter Hoch U Tiefbau",
    "sg:postcode":"50",
    "wof:name":"Wss Ag",
    "wof:placetype":"venue"
},
  "geometry": {"coordinates":[8.55493927,47.4123535156],"type":"Point"}
}