{
  "type": "Feature",
  "properties": {
    "iso:country":"CH",
    "sg:address":"Zelgweg 4a",
    "sg:city":"Grenchen",
    "sg:orig_category":"Physiotherapie",
    "sg:phone":"+41 32 652 68 07",
    "sg:postcode":"2540",
    "sg:province":"Solothurn",
    "wof:name":"Trudy Wermelinger Physiotherapie",
    "wof:placetype":"venue"
},
  "geometry": {"coordinates":[7.3809762001,47.1926498413],"type":"Point"}
}