{
  "type": "Feature",
  "properties": {
    "iso:country":"CH",
    "sg:address":"Via Lische Zona Industriale 3",
    "sg:city":"Stabio",
    "sg:classifiers":[
        {
            "category":"Personal",
            "subcategory":"Skin Care",
            "type":"Services"
        }
    ],
    "sg:phone":"+41 91 641 62 50",
    "sg:postcode":"6855",
    "sg:province":"Ticino",
    "sg:tags":[
        "nail",
        "nipper"
    ],
    "wof:name":"Outils Rubis Sa",
    "wof:placetype":"venue"
},
  "geometry": {"coordinates":[8.9393825531,45.8523521423],"type":"Point"}
}