{
  "type": "Feature",
  "properties": {
    "iso:country":"CH",
    "sg:address":"Court-chemin Esc. Du 19",
    "sg:city":"Fribourg",
    "sg:orig_category":"Wirtschaftspr\u00fcfung, Steuerberatung U Treuhand",
    "sg:postcode":"1700",
    "sg:province":"Fribourg",
    "wof:name":"Bat Training & Partners Sa",
    "wof:placetype":"venue"
},
  "geometry": {"coordinates":[7.1609559059,46.8045806885],"type":"Point"}
}