{
  "type": "Feature",
  "properties": {
    "iso:country":"CH",
    "sg:address":"Twerenegg",
    "sg:city":"Menznau",
    "sg:orig_category":"Wasserversorgung",
    "sg:postcode":"6122",
    "sg:province":"Luzern",
    "wof:name":"Wasserversorgungsgenossenschaft Uerzlikon",
    "wof:placetype":"venue"
},
  "geometry": {"coordinates":[8.49629879,47.2230758667],"type":"Point"}
}