{
  "type": "Feature",
  "properties": {
    "addr:full":"Alte Steinhauserstrasse 23 6330 Cham. Postfach 5257 Cham Zug 6330",
    "addr:housenumber":"23",
    "addr:postcode":"6330;5257;6330",
    "addr:street":"Alte Steinhauserstrasse;Postfach;Zug",
    "iso:country":"CH",
    "sg:address":"Alte Steinhauserstrasse 23 6330 Cham. Postfach 5257",
    "sg:city":"Cham",
    "sg:orig_category":"Handelsvermittlung U Grosshandel mit Automobilen Herstellung von Bergwerks U Baumaschinen",
    "sg:phone":"+41 41 741 77 00",
    "sg:postcode":"6330",
    "sg:province":"Zug",
    "wof:name":"Heusser Carl Ag",
    "wof:placetype":"venue"
},
  "geometry": {"coordinates":[8.474537,47.188942],"type":"Point"}
}