{
  "type": "Feature",
  "properties": {
    "iso:country":"CH",
    "sg:address":"Rue De La Promenade 34",
    "sg:city":"Ponts-de-martel",
    "sg:orig_category":"Mahl U Sch\u00e4lm\u00fchlen",
    "sg:phone":"+41 32 937 10 91",
    "sg:postcode":"2316",
    "sg:province":"Neuch\u00e2tel",
    "wof:name":"Moulin Agricole Des Ponts-de-martel S\u00e0rl",
    "wof:placetype":"venue"
},
  "geometry": {"coordinates":[6.7275319099,46.9964294434],"type":"Point"}
}