{
  "type": "Feature",
  "properties": {
    "iso:country":"CH",
    "sg:address":"Oberdorfstrasse 2",
    "sg:city":"Freienbach",
    "sg:orig_category":"Kauf U Verkauf von Immobilien auf eigene Rechnung",
    "sg:phone":"+41 55483655",
    "sg:postcode":"8807",
    "sg:province":"Schwyz",
    "wof:name":"Westgrund-liegenschaften Ag.",
    "wof:placetype":"venue"
},
  "geometry": {"coordinates":[8.7784986496,47.2003517151],"type":"Point"}
}