{
  "type": "Feature",
  "properties": {
    "iso:country":"CH",
    "sg:address":"Eustrasse 5",
    "sg:city":"Menzingen",
    "sg:orig_category":"Fachdetailhandel in Verkaufsr\u00e4umen",
    "sg:postcode":"6313",
    "sg:province":"Zug",
    "wof:name":"Benz Tiernahrung Import Und Handel",
    "wof:placetype":"venue"
},
  "geometry": {"coordinates":[8.5910253525,47.1769523621],"type":"Point"}
}