{
  "type": "Feature",
  "properties": {
    "iso:country":"CH",
    "sg:address":"Rue De La Borde 77",
    "sg:city":"Lausanne",
    "sg:orig_category":"Maschinenbau",
    "sg:phone":"+41 17844045",
    "sg:postcode":"1018",
    "sg:province":"Vaud",
    "wof:name":"Empac Ag",
    "wof:placetype":"venue"
},
  "geometry": {"coordinates":[8.7252006531,47.2008781433],"type":"Point"}
}