{
  "type": "Feature",
  "properties": {
    "iso:country":"CH",
    "sg:address":"Riva Paradiso 16",
    "sg:city":"Lugano",
    "sg:orig_category":"Architekturb\u00fcros",
    "sg:phone":"+41 21 634 70 63",
    "sg:postcode":"6900",
    "sg:province":"Ticino",
    "wof:name":"Delta 7 Architecture Sa Maisons; Planification, \u00e9dification, Achat, Vente, Am\u00e9nagement",
    "wof:placetype":"venue"
},
  "geometry": {"coordinates":[6.5916519165,46.5299682617],"type":"Point"}
}