{
  "type": "Feature",
  "properties": {
    "addr:full":"Wingreis 272 Twann Bern 2513",
    "addr:housenumber":"272",
    "addr:postcode":"2513",
    "addr:street":"Twann Bern",
    "iso:country":"CH",
    "sg:address":"Wingreis 272",
    "sg:city":"Twann",
    "sg:orig_category":"Dauerkulturbau",
    "sg:phone":"+41 32 315 12 63",
    "sg:postcode":"2513",
    "sg:province":"Bern",
    "wof:name":"Feitknecht Urs.",
    "wof:placetype":"venue"
},
  "geometry": {"coordinates":[7.177143,47.102493],"type":"Point"}
}