{
  "type": "Feature",
  "properties": {
    "iso:country":"CH",
    "sg:address":"Neuenschwandstrasse 883c 3536 Aeschau. Postfach",
    "sg:city":"Aeschau",
    "sg:orig_category":"Grosshandel mit Getreide, Saatgut U Futtermitteln",
    "sg:postcode":"3536",
    "sg:province":"Bern",
    "wof:name":"Stufi Tierbedarf Gmbh",
    "wof:placetype":"venue"
},
  "geometry": {"coordinates":[7.7649149895,46.9097061157],"type":"Point"}
}