{
  "type": "Feature",
  "properties": {
    "iso:country":"CH",
    "sg:address":"Petersgasse 36",
    "sg:city":"Basel",
    "sg:orig_category":"Sonstiger Grosshandel",
    "sg:phone":"+41 61 266 44 66",
    "sg:postcode":"4051",
    "sg:province":"Basel-Stadt",
    "wof:name":"Weitnauer Distribution Ltd",
    "wof:placetype":"venue"
},
  "geometry": {"coordinates":[7.5860562325,47.5601768494],"type":"Point"}
}