{
  "type": "Feature",
  "properties": {
    "iso:country":"CH",
    "sg:address":"Viale Cattaneo 3",
    "sg:city":"Lugano",
    "sg:orig_category":"Vermietung U Verpachtung von eigenen Immobilien",
    "sg:postcode":"6900",
    "sg:province":"Ticino",
    "wof:name":"Lisander Sa",
    "wof:placetype":"venue"
},
  "geometry": {"coordinates":[8.9564399719,46.0057830811],"type":"Point"}
}