{
  "type": "Feature",
  "properties": {
    "iso:country":"CH",
    "sg:address":"Simplemont Chemin 12",
    "sg:city":"Lausanne",
    "sg:orig_category":"Unclassifiable Establishments",
    "sg:postcode":"1005",
    "sg:province":"Vaud",
    "wof:name":"Audioconcept Sa",
    "wof:placetype":"venue"
},
  "geometry": {"coordinates":[6.6504349709,46.5192871094],"type":"Point"}
}