{
  "type": "Feature",
  "properties": {
    "iso:country":"CH",
    "sg:address":"Scuole Via Delle 16 6918 Figino. Postfach",
    "sg:city":"Figino",
    "sg:orig_category":"Grosshandel mit Holz U Baustoffen",
    "sg:phone":"+41 91 995 12 54",
    "sg:postcode":"6918",
    "sg:province":"Ticino",
    "wof:name":"Combertaldi Herbert",
    "wof:placetype":"venue"
},
  "geometry": {"coordinates":[8.9069690704,45.9528579712],"type":"Point"}
}