{
  "type": "Feature",
  "properties": {
    "iso:country":"CH",
    "sg:address":"Allmendstrasse 48",
    "sg:city":"Meiringen",
    "sg:orig_category":"Unclassifiable Establishments",
    "sg:phone":"+41 33 971 07 15",
    "sg:postcode":"3860",
    "sg:province":"Bern",
    "wof:name":"Mimmo Gmbh",
    "wof:placetype":"venue"
},
  "geometry": {"coordinates":[8.1831130981,46.7263069153],"type":"Point"}
}