{
  "type": "Feature",
  "properties": {
    "iso:country":"CH",
    "sg:address":"Schochenm\u00fchlestrasse",
    "sg:city":"Baar",
    "sg:orig_category":"Instandhaltung U Reparatur von Automobilen",
    "sg:phone":"+41 55 246 52 75",
    "sg:postcode":"6340",
    "sg:province":"Zug",
    "wof:name":"Zentral Garage, Simonet Remo",
    "wof:placetype":"venue"
},
  "geometry": {"coordinates":[8.9277486801,47.2651481628],"type":"Point"}
}