{
  "type": "Feature",
  "properties": {
    "addr:full":"Im Ehrmerk 2 Wallenwil Thurgau 8360",
    "addr:housenumber":"2",
    "addr:postcode":"8360",
    "addr:street":"Im Ehrmerk",
    "iso:country":"CH",
    "sg:address":"Im Ehrmerk 2",
    "sg:city":"Wallenwil",
    "sg:orig_category":"Autospenglereien",
    "sg:phone":"+41 71 971 13 83",
    "sg:postcode":"8360",
    "sg:province":"Thurgau",
    "wof:name":"Fritz Heer Carrosserie",
    "wof:placetype":"venue"
},
  "geometry": {"coordinates":[8.97053,47.464867],"type":"Point"}
}