{
  "type": "Feature",
  "properties": {
    "iso:country":"CH",
    "sg:address":"Corso San Gottardo 4",
    "sg:city":"Chiasso",
    "sg:classifiers":[
        {
            "category":"Banks & Credit Unions",
            "subcategory":"Bank",
            "type":"Services"
        }
    ],
    "sg:phone":"+41 4191446521",
    "sg:postcode":"6830",
    "sg:province":"Ticino",
    "wof:name":"Banca Dello Stato, Del Cantone Ticino",
    "wof:placetype":"venue"
},
  "geometry": {"coordinates":[9.033349,45.832661],"type":"Point"}
}