{
  "type": "Feature",
  "properties": {
    "iso:country":"CH",
    "sg:address":"M\u00f6sli 82 Industriegebiet",
    "sg:city":"Schwaderloch",
    "sg:orig_category":"Pensionskassen",
    "sg:postcode":"5326",
    "sg:province":"Aargau",
    "wof:name":"Personalf\u00fcrsorgestiftung Fixtr\u00e4ger Ag",
    "wof:placetype":"venue"
},
  "geometry": {"coordinates":[8.1468353271,47.586769104],"type":"Point"}
}