{
  "type": "Feature",
  "properties": {
    "iso:country":"CH",
    "sg:address":"Rankstrasse 15",
    "sg:city":"Wettingen",
    "sg:orig_category":"Abdichtung Allgemeiner Hoch U Tiefbau",
    "sg:phone":"+41 79 205 57 49",
    "sg:postcode":"5430",
    "sg:province":"Aargau",
    "wof:name":"Sockelmontage & Kittfugen Bartucca Gmbh",
    "wof:placetype":"venue"
},
  "geometry": {"coordinates":[8.326472,47.464668],"type":"Point"}
}