{
  "type": "Feature",
  "properties": {
    "iso:country":"CH",
    "sg:address":"Uttigenstrasse 125",
    "sg:city":"Thun",
    "sg:orig_category":"Technische B\u00fcros Heizung, L\u00fcftung, Klima",
    "sg:phone":"+41 22 342 72 96",
    "sg:postcode":"3603",
    "sg:province":"Bern",
    "wof:name":"Jean-claude Charvoz Bureau Technique",
    "wof:placetype":"venue"
},
  "geometry": {"coordinates":[6.1323451996,46.1880149841],"type":"Point"}
}