{
  "type": "Feature",
  "properties": {
    "iso:country":"CH",
    "sg:address":"1906",
    "sg:city":"Charrat",
    "sg:orig_category":"Allgemeiner Hoch U Tiefbau ohne ausgepr\u00e4gten Schwerpunkt",
    "sg:phone":"+41 27 747 61 00",
    "sg:postcode":"1906",
    "sg:province":"Valais",
    "wof:name":"Police De L'autoroute Centre Indivis",
    "wof:placetype":"venue"
},
  "geometry": {"coordinates":[7.129689,46.124989],"type":"Point"}
}