{
  "type": "Feature",
  "properties": {
    "iso:country":"CH",
    "sg:address":"Langgstr. 1042",
    "sg:city":"Gais",
    "sg:orig_category":"Allgemeiner Hoch U Tiefbau",
    "sg:postcode":"9056",
    "sg:province":"Appenzell Ausserrhoden",
    "wof:name":"Sutter Ag, Appenzell",
    "wof:placetype":"venue"
},
  "geometry": {"coordinates":[9.44698,47.359928],"type":"Point"}
}