{
  "type": "Feature",
  "properties": {
    "iso:country":"CH",
    "sg:address":"R\u00fctistrasse 1",
    "sg:city":"Baden",
    "sg:orig_category":"Detailhandel mit M\u00f6beln Herstellung von sonstigen M\u00f6beln",
    "sg:phone":"+41 62 771 45 71",
    "sg:postcode":"5400",
    "sg:province":"Aargau",
    "wof:name":"Gabotex Ag",
    "wof:placetype":"venue"
},
  "geometry": {"coordinates":[8.1772727966,47.2633399963],"type":"Point"}
}