{
  "type": "Feature",
  "properties": {
    "iso:country":"CH",
    "sg:address":"Terbinerstrasse 51",
    "sg:city":"Visp",
    "sg:orig_category":"Herstellung von sonstigen Produkten aus nichtmetallischen Mineralien",
    "sg:phone":"+41 27 946 51 94",
    "sg:postcode":"3930",
    "sg:province":"Valais",
    "wof:name":"Bauberatung Gattlen Ren\u00e9",
    "wof:placetype":"venue"
},
  "geometry": {"coordinates":[7.8872790337,46.2894058228],"type":"Point"}
}