{
  "type": "Feature",
  "properties": {
    "addr:full":"Lottenweg 22 Muhen Aargau 5037",
    "addr:housenumber":"22",
    "addr:postcode":"5037",
    "addr:street":"Lottenweg",
    "iso:country":"CH",
    "sg:address":"Lottenweg 22",
    "sg:city":"Muhen",
    "sg:classifiers":[
        {
            "category":"Shopping",
            "subcategory":"Stationery & Office Supplies",
            "type":"Retail Goods"
        }
    ],
    "sg:phone":"+41 62 737 20 40",
    "sg:postcode":"5037",
    "sg:province":"Aargau",
    "sg:tags":[
        "adhesive",
        "label"
    ],
    "wof:name":"Tr\u00fcmpy Ag",
    "wof:placetype":"venue"
},
  "geometry": {"coordinates":[8.061076,47.338985],"type":"Point"}
}