{
  "type": "Feature",
  "properties": {
    "iso:country":"CH",
    "sg:address":"Industriestrasse 13c",
    "sg:city":"Zug",
    "sg:orig_category":"Unclassifiable Establishments",
    "sg:postcode":"6300",
    "sg:province":"Zug",
    "wof:name":"Mibore Ag",
    "wof:placetype":"venue"
},
  "geometry": {"coordinates":[8.5183839798,47.1725463867],"type":"Point"}
}