{
  "type": "Feature",
  "properties": {
    "iso:country":"CH",
    "sg:address":"Spitalgasse 4",
    "sg:city":"Bern",
    "sg:orig_category":"Detailhandel mit Schuhen",
    "sg:phone":"+41 22 301 59 80",
    "sg:postcode":"3011",
    "sg:province":"Bern",
    "wof:name":"Millepattes Sa",
    "wof:placetype":"venue"
},
  "geometry": {"coordinates":[6.1421937943,46.1865196228],"type":"Point"}
}