{
  "type": "Feature",
  "properties": {
    "iso:country":"CH",
    "sg:address":"Cioss Mezz 4 6776 Piotta. Postfach",
    "sg:city":"Piotta",
    "sg:orig_category":"Vermietung U Verpachtung von eigenen Immobilien",
    "sg:postcode":"6776",
    "sg:province":"Ticino",
    "wof:name":"Provalle Sa",
    "wof:placetype":"venue"
},
  "geometry": {"coordinates":[8.6699676514,46.5149726868],"type":"Point"}
}