{
  "type": "Feature",
  "properties": {
    "iso:country":"CH",
    "sg:address":"St. Urbangasse 27 4500 Solothurn. Postfach",
    "sg:city":"Solothurn",
    "sg:orig_category":"Architektur U Ingenieurb\u00fcros Architekturb\u00fcros",
    "sg:phone":"+41 32 622 23 73",
    "sg:postcode":"4502",
    "sg:province":"Solothurn",
    "wof:name":"Meier Eugen, Architekt Htl",
    "wof:placetype":"venue"
},
  "geometry": {"coordinates":[7.535387,47.208698],"type":"Point"}
}