{
  "type": "Feature",
  "properties": {
    "addr:full":"B\u00fcelstrasse 15 8910 Affoltern Am Albis. Postfach 564 Z\u00fcrich Z\u00fcrich 8005",
    "addr:housenumber":"15;564",
    "addr:postcode":"8910;8005",
    "addr:street":"Bueelstrasse;Postfach",
    "iso:country":"CH",
    "sg:address":"B\u00fcelstrasse 15 8910 Affoltern Am Albis. Postfach 564",
    "sg:city":"Z\u00fcrich",
    "sg:orig_category":"Bijouterien Reparatur von Uhren U Schmuck",
    "sg:phone":"+41 14472626",
    "sg:postcode":"8005",
    "sg:province":"Z\u00fcrich",
    "wof:name":"Christ Uhren Und Schmuck Ag Uhren, Schmuck, Diamanten, Edelsteine Usw; Handel, Vertrieb",
    "wof:placetype":"venue"
},
  "geometry": {"coordinates":[8.446813,47.274178],"type":"Point"}
}