{
  "type": "Feature",
  "properties": {
    "iso:country":"CH",
    "sg:address":"Piazza Indipendenza 4. 6830 Chiasso. Postfach Casa Postale",
    "sg:city":"Chiasso",
    "sg:orig_category":"Vermietung U Verpachtung von eigenen Immobilien",
    "sg:postcode":"6830",
    "sg:province":"Ticino",
    "wof:name":"Lariana Sa Immobiliare Ecc",
    "wof:placetype":"venue"
},
  "geometry": {"coordinates":[9.0308475494,45.8336181641],"type":"Point"}
}