{
  "type": "Feature",
  "properties": {
    "iso:country":"CH",
    "sg:address":"Bahnhofstrasse 53",
    "sg:city":"Aarau",
    "sg:orig_category":"Unclassifiable Establishments",
    "sg:postcode":"5000",
    "sg:province":"Aargau",
    "wof:name":"Orso Ag",
    "wof:placetype":"venue"
},
  "geometry": {"coordinates":[8.049030304,47.3915863037],"type":"Point"}
}