{
  "type": "Feature",
  "properties": {
    "iso:country":"CH",
    "sg:address":"Ziegelfeldstrasse 18",
    "sg:city":"Olten",
    "sg:orig_category":"D\u00e4mmung gegen K\u00e4lte, W\u00e4rme, Schall U Ersch\u00fctterung Reinigungsgewerbe",
    "sg:phone":"+41 62 212 18 32",
    "sg:postcode":"4600",
    "sg:province":"Solothurn",
    "wof:name":"Az-reinigungen Und Dichtungstechnik Ag",
    "wof:placetype":"venue"
},
  "geometry": {"coordinates":[7.8998570442,47.3522224426],"type":"Point"}
}