{
  "type": "Feature",
  "properties": {
    "iso:country":"CH",
    "sg:address":"Heidenlochstrasse 16",
    "sg:city":"Liestal",
    "sg:orig_category":"Interessenvertretungen",
    "sg:postcode":"4410",
    "sg:province":"Basel-Landschaft",
    "wof:name":"Martin-eschbach-stiftung Paul Und Frieda",
    "wof:placetype":"venue"
},
  "geometry": {"coordinates":[7.7420368195,47.4853630066],"type":"Point"}
}