{
  "type": "Feature",
  "properties": {
    "iso:country":"CH",
    "sg:address":"2923",
    "sg:city":"Courtema\u00eeche",
    "sg:orig_category":"Herstellung von Uhren",
    "sg:phone":"+41 32 466 24 53",
    "sg:postcode":"2923",
    "sg:province":"Jura",
    "wof:name":"Soci\u00e9t\u00e9 Maillard Fr\u00e8res & Cie",
    "wof:placetype":"venue"
},
  "geometry": {"coordinates":[7.0438098907,47.4589500427],"type":"Point"}
}