{
  "type": "Feature",
  "properties": {
    "iso:country":"CH",
    "sg:address":"Zentralstrasse 80",
    "sg:city":"Neuhausen",
    "sg:classifiers":[
        {
            "category":"Professional",
            "subcategory":"Employment Agencies",
            "type":"Services"
        }
    ],
    "sg:phone":"+41 52 672 44 26",
    "sg:postcode":"8212",
    "sg:province":"Schaffhausen",
    "sg:tags":[
        "personal",
        "u",
        "stellenvermittlung"
    ],
    "wof:name":"Zentrum F\u00fcr Angewandte Psychologie Imhof Markus",
    "wof:placetype":"venue"
},
  "geometry": {"coordinates":[8.6212215424,47.6828994751],"type":"Point"}
}