{
  "type": "Feature",
  "properties": {
    "iso:country":"CH",
    "sg:address":"Isenrietstrasse 5a",
    "sg:city":"M\u00f6nchaltorf",
    "sg:orig_category":"Non-Classified Establishments",
    "sg:postcode":"8617",
    "sg:province":"Z\u00fcrich",
    "wof:name":"Garage D. Eugster Gmbh",
    "wof:placetype":"venue"
},
  "geometry": {"coordinates":[8.7180957794,47.3009872437],"type":"Point"}
}