{
  "type": "Feature",
  "properties": {
    "iso:country":"CH",
    "sg:address":"Stockerstrasse 17",
    "sg:city":"Z\u00fcrich",
    "sg:classifiers":[
        {
            "category":"Travel",
            "subcategory":"Hotels & Motels",
            "type":"Entertainment"
        }
    ],
    "sg:phone":"+41 81 416 81 31",
    "sg:postcode":"8002",
    "sg:province":"Z\u00fcrich",
    "sg:tags":[
        "hotels",
        "mit",
        "restaurant"
    ],
    "wof:name":"Arabellasheraton Golfhotel Waldhuus",
    "wof:placetype":"venue"
},
  "geometry": {"coordinates":[9.8347005844,46.7973518372],"type":"Point"}
}