{
  "type": "Feature",
  "properties": {
    "iso:country":"CH",
    "sg:address":"Landstrasse 1",
    "sg:city":"Naters",
    "sg:orig_category":"RESTAURANTS: TEA-ROOMS",
    "sg:postcode":"3904",
    "sg:province":"Valais",
    "wof:name":"Restaurant Belalp, Eyer & Co",
    "wof:placetype":"venue"
},
  "geometry": {"coordinates":[7.989836216,46.3256187439],"type":"Point"}
}