{
  "type": "Feature",
  "properties": {
    "iso:country":"CH",
    "sg:address":"Place De La Croix-blanche 7",
    "sg:city":"Epalinges",
    "sg:orig_category":"Detailhandel mit Waren verschiedener Art, Hauptrichtung Nahrungsmittel",
    "sg:phone":"+41 21 784 00 75",
    "sg:postcode":"1066",
    "sg:province":"Vaud",
    "wof:name":"Pick Pay Betriebs Ag",
    "wof:placetype":"venue"
},
  "geometry": {"coordinates":[6.6714901924,46.5484466553],"type":"Point"}
}