{
  "type": "Feature",
  "properties": {
    "iso:country":"CH",
    "sg:address":"Ebnetstrasse 75",
    "sg:city":"Horgen",
    "sg:orig_category":"Non-Classified Establishments",
    "sg:phone":"+41 79 608 26 36",
    "sg:postcode":"8810",
    "sg:province":"Z\u00fcrich",
    "wof:name":"Katzenpension Zur Ebnet D\u00fcrst B.",
    "wof:placetype":"venue"
},
  "geometry": {"coordinates":[8.5898723602,47.2560958862],"type":"Point"}
}