{
  "type": "Feature",
  "properties": {
    "iso:country":"CH",
    "sg:address":"Riedstrasse 14",
    "sg:city":"Tamins",
    "sg:orig_category":"D\u00e4mmung gegen K\u00e4lte, W\u00e4rme, Schall U Ersch\u00fctterung Herstellung von Konstruktionsteilen, Fertigbautei",
    "sg:phone":"+41 81 641 10 40",
    "sg:postcode":"7015",
    "sg:province":"Graubunden",
    "wof:name":"Montalta Ag",
    "wof:placetype":"venue"
},
  "geometry": {"coordinates":[9.4065103531,46.8325462341],"type":"Point"}
}