{
  "type": "Feature",
  "properties": {
    "iso:country":"CH",
    "sg:address":"Oberneuhofstrasse 13 6340 Baar. Postfach",
    "sg:city":"Baar",
    "sg:orig_category":"Handelsvermittlung von Brennstoffen, Erzen, Metallen U Chemikalien",
    "sg:phone":"+41 41 760 02 78",
    "sg:postcode":"6340",
    "sg:province":"Zug",
    "wof:name":"Hudson Corporation Ag Waren, Bes. Rohstoffe Im Ber. Stahl, Metall Und Erd\u00f6l; Handel",
    "wof:placetype":"venue"
},
  "geometry": {"coordinates":[8.5165224075,47.1867828369],"type":"Point"}
}