{
  "type": "Feature",
  "properties": {
    "iso:country":"CH",
    "sg:address":"Kirchgasse 18 3053 M\u00fcnchenbuchsee. Postfach",
    "sg:city":"M\u00fcnchenbuchsee",
    "sg:orig_category":"Herstellung von medizinischen U chirurgischen Ger\u00e4ten sowie orthop\u00e4dischen Vorrichtungen",
    "sg:phone":"+41 31 869 56 11",
    "sg:postcode":"3053",
    "sg:province":"Bern",
    "wof:name":"Schmid Daniel Contactlinsen Optikergesch\u00e4ft, Bes. F. Kontaktlinsen",
    "wof:placetype":"venue"
},
  "geometry": {"coordinates":[7.4498848915,47.0194664001],"type":"Point"}
}