{
  "type": "Feature",
  "properties": {
    "iso:country":"CH",
    "sg:address":"Sch\u00fctzenmatte 19",
    "sg:city":"Sch\u00f6tz",
    "sg:orig_category":"Vermietung U Verpachtung von eigenen Immobilien",
    "sg:postcode":"6247",
    "sg:province":"Luzern",
    "wof:name":"Beho Ag",
    "wof:placetype":"venue"
},
  "geometry": {"coordinates":[7.9821829796,47.1714782715],"type":"Point"}
}