{
  "type": "Feature",
  "properties": {
    "iso:country":"CH",
    "sg:address":"Fischerweg 2",
    "sg:city":"Biel/bienne",
    "sg:orig_category":"Verwaltung von Immobilien Wirtschaftspr\u00fcfung, Steuerberatung U Treuhand",
    "sg:phone":"+41 32 322 58 68",
    "sg:postcode":"2503",
    "sg:province":"Bern",
    "wof:name":"G & C Partner Gmbh",
    "wof:placetype":"venue"
},
  "geometry": {"coordinates":[7.2380509377,47.1303405762],"type":"Point"}
}