{
  "type": "Feature",
  "properties": {
    "iso:country":"CH",
    "sg:address":"Hochstrasse 32",
    "sg:city":"Schaffhausen",
    "sg:orig_category":"Instandhaltung U Reparatur von Automobilen",
    "sg:phone":"+41 52 625 52 20",
    "sg:postcode":"8200",
    "sg:province":"Schaffhausen",
    "wof:name":"Autospenglerei Elan Gmbh",
    "wof:placetype":"venue"
},
  "geometry": {"coordinates":[8.6355524063,47.7029571533],"type":"Point"}
}