{
  "type": "Feature",
  "properties": {
    "iso:country":"CH",
    "sg:address":"Hauptgasse 34",
    "sg:city":"Olten",
    "sg:orig_category":"Detailhandel mit Damenbekleidung Grosshandel mit Textilien",
    "sg:phone":"+41 71 911 13 20",
    "sg:postcode":"4600",
    "sg:province":"Solothurn",
    "wof:name":"Donna Pi\u00f9 Moda Gmbh",
    "wof:placetype":"venue"
},
  "geometry": {"coordinates":[9.0491189957,47.466506958],"type":"Point"}
}