{
  "type": "Feature",
  "properties": {
    "iso:country":"CH",
    "sg:address":"Bahnhofstrasse 16",
    "sg:city":"Herzogenbuchsee",
    "sg:classifiers":[
        {
            "category":"Travel",
            "subcategory":"Hotels & Motels",
            "type":"Entertainment"
        }
    ],
    "sg:phone":"+41 62 961 23 83",
    "sg:postcode":"3360",
    "sg:province":"Bern",
    "sg:tags":[
        "hotels",
        "mit",
        "restaurant"
    ],
    "wof:name":"Frau G. Thommen",
    "wof:placetype":"venue"
},
  "geometry": {"coordinates":[7.7018008232,47.1880722046],"type":"Point"}
}