{
  "type": "Feature",
  "properties": {
    "iso:country":"CH",
    "sg:address":"Kornfeldweg 5",
    "sg:city":"Baden",
    "sg:orig_category":"Allgemeiner Hoch U Tiefbau",
    "sg:phone":"+41 56 222 68 21",
    "sg:postcode":"5400",
    "sg:province":"Aargau",
    "wof:name":"Diener Paul Aviation-service Ag",
    "wof:placetype":"venue"
},
  "geometry": {"coordinates":[8.289695,47.482891],"type":"Point"}
}