{
  "type": "Feature",
  "properties": {
    "iso:country":"CH",
    "sg:address":"Oberwiesstrasse 50",
    "sg:city":"Jona",
    "sg:classifiers":[
        {
            "category":"Wholesale",
            "subcategory":"Vending Machines",
            "type":"Manufacturing & Wholesale Goods"
        }
    ],
    "sg:phone":"+41 55 212 40 32",
    "sg:postcode":"8645",
    "sg:province":"St. Gallen",
    "sg:tags":[
        "bending",
        "profile",
        "iron",
        "structural"
    ],
    "wof:name":"Bmg Blechbearbeitungsmaschinen Gubler",
    "wof:placetype":"venue"
},
  "geometry": {"coordinates":[8.843248,47.231693],"type":"Point"}
}