{
  "type": "Feature",
  "properties": {
    "iso:country":"CH",
    "sg:address":"L\u00f6wengraben 24",
    "sg:city":"Luzern",
    "sg:orig_category":"Vereine Z\u00fcnfte",
    "sg:phone":"+41 41 410 10 91",
    "sg:postcode":"6004",
    "sg:province":"Luzern",
    "wof:name":"Ges.der Herren Zu Sch\u00fctzen",
    "wof:placetype":"venue"
},
  "geometry": {"coordinates":[8.3028364182,47.0523986816],"type":"Point"}
}