{
  "type": "Feature",
  "properties": {
    "iso:country":"CH",
    "sg:address":"Via Lucino 42",
    "sg:city":"Breganzona",
    "sg:orig_category":"Handelsvermittlung von Brennstoffen, Erzen, Metallen U Chemikalien",
    "sg:postcode":"6932",
    "sg:province":"Ticino",
    "wof:name":"Fidimport De-bernardis",
    "wof:placetype":"venue"
},
  "geometry": {"coordinates":[8.9319839478,46.0066757202],"type":"Point"}
}