{
  "type": "Feature",
  "properties": {
    "iso:country":"CH",
    "sg:address":"Steinemoos",
    "sg:city":"Besenb\u00fcren",
    "sg:classifiers":[
        {
            "category":"Autos & Motor Vehicles",
            "subcategory":"Automobile Sales",
            "type":"Retail Goods"
        }
    ],
    "sg:phone":"+41 56 677 80 11",
    "sg:postcode":"5627",
    "sg:province":"Aargau",
    "sg:tags":[
        "equipment",
        "motor-cars",
        "transport"
    ],
    "wof:name":"Rudolf Senn Ag Autocenter",
    "wof:placetype":"venue"
},
  "geometry": {"coordinates":[8.3433551788,47.3178367615],"type":"Point"}
}