{
  "type": "Feature",
  "properties": {
    "iso:country":"CH",
    "sg:address":"Mellingerstrasse 126",
    "sg:city":"Baden",
    "sg:classifiers":[
        {
            "category":"Professional",
            "subcategory":"Employment Agencies",
            "type":"Services"
        }
    ],
    "sg:phone":"+41 56 210 33 00",
    "sg:postcode":"5400",
    "sg:province":"Aargau",
    "sg:tags":[
        "personal",
        "u",
        "stellenvermittlung"
    ],
    "wof:name":"Dieter Probst Db Treuhand & Beratung",
    "wof:placetype":"venue"
},
  "geometry": {"coordinates":[8.2953624725,47.4680595398],"type":"Point"}
}