{
  "type": "Feature",
  "properties": {
    "iso:country":"CH",
    "sg:address":"Steinlen Chemin Aim\u00e9- 9 1004 Lausanne. Postfach",
    "sg:city":"Lausanne",
    "sg:orig_category":"RESTAURANTS: TEA-ROOMS",
    "sg:phone":"+41 71 222 43 44",
    "sg:postcode":"1003",
    "sg:province":"Vaud",
    "wof:name":"Fondue-beizli Neueck",
    "wof:placetype":"venue"
},
  "geometry": {"coordinates":[9.3780965805,47.4253196716],"type":"Point"}
}