{
  "type": "Feature",
  "properties": {
    "iso:country":"CH",
    "sg:address":"Rue Du Pr\u00e9-bouvier 31 1242 Satigny Case Postale 56",
    "sg:city":"Satigny",
    "sg:orig_category":"Detailhandel mit Brot, Back U S\u00fcsswaren",
    "sg:phone":"+41 22 783 22 00",
    "sg:postcode":"1242",
    "sg:province":"Gen\u00e8ve",
    "wof:name":"Pouly Tradition Sa",
    "wof:placetype":"venue"
},
  "geometry": {"coordinates":[6.051999,46.220535],"type":"Point"}
}