{
  "type": "Feature",
  "properties": {
    "iso:country":"CH",
    "sg:address":"Stockerstrasse 41",
    "sg:city":"Z\u00fcrich",
    "sg:orig_category":"Unternehmensberatung",
    "sg:postcode":"8002",
    "sg:province":"Z\u00fcrich",
    "wof:name":"Gurbee Limited",
    "wof:placetype":"venue"
},
  "geometry": {"coordinates":[8.5344953537,47.3674812317],"type":"Point"}
}