{
  "type": "Feature",
  "properties": {
    "iso:country":"CH",
    "sg:address":"Avenue Des Planches 22",
    "sg:city":"Montreux",
    "sg:orig_category":"F\u00fcrsorge\u00e4mter Gesundheits U Sozialwesen",
    "sg:phone":"+41 21 963 51 11",
    "sg:postcode":"1820",
    "sg:province":"Vaud",
    "wof:name":"Centre M\u00e9dico-social Croix-rouge Suisse",
    "wof:placetype":"venue"
},
  "geometry": {"coordinates":[6.9138450623,46.4307861328],"type":"Point"}
}