{
  "type": "Feature",
  "properties": {
    "iso:country":"CH",
    "sg:address":"D\u00fcrrenb\u00fchl 4954 Wyssachen. Postfach",
    "sg:city":"Wyssachen",
    "sg:classifiers":[
        {
            "category":"Travel",
            "subcategory":"Hotels & Motels",
            "type":"Entertainment"
        }
    ],
    "sg:postcode":"4954",
    "sg:province":"Bern",
    "sg:tags":[
        "hotels",
        "mit",
        "restaurant"
    ],
    "wof:name":"Niederhauser-f\u00e4ssler",
    "wof:placetype":"venue"
},
  "geometry": {"coordinates":[7.8243517876,47.0866622925],"type":"Point"}
}