{
  "type": "Feature",
  "properties": {
    "iso:country":"CH",
    "sg:address":"H\u00f6heweg 9",
    "sg:city":"Oberdiessbach",
    "sg:orig_category":"Wirtschaftspr\u00fcfung, Steuerberatung U Treuhand",
    "sg:phone":"+41 31 747 97 27",
    "sg:postcode":"3672",
    "sg:province":"Bern",
    "wof:name":"Glauser + Roth",
    "wof:placetype":"venue"
},
  "geometry": {"coordinates":[7.2380242348,46.9045982361],"type":"Point"}
}