{
  "type": "Feature",
  "properties": {
    "iso:country":"CH",
    "sg:address":"Rhonesandstrasse 7",
    "sg:city":"Brig",
    "sg:orig_category":"Detailhandel mit Damenbekleidung Herstellung von W\u00e4sche",
    "sg:phone":"+41 27 923 54 00",
    "sg:postcode":"3900",
    "sg:province":"Valais",
    "wof:name":"Boutique San Francisco Ag",
    "wof:placetype":"venue"
},
  "geometry": {"coordinates":[7.989153862,46.3176994324],"type":"Point"}
}