{
  "type": "Feature",
  "properties": {
    "iso:country":"CH",
    "sg:address":"Oberr\u00fcttenenstrasse 53",
    "sg:city":"R\u00fcttenen",
    "sg:classifiers":[
        {
            "category":"Restaurant",
            "type":"Food & Drink"
        }
    ],
    "sg:phone":"+41 32 622 93 88",
    "sg:postcode":"4522",
    "sg:province":"Solothurn",
    "wof:name":"Restaurant Oberr\u00fcttenen",
    "wof:placetype":"venue"
},
  "geometry": {"coordinates":[7.5309348106,47.2378578186],"type":"Point"}
}