{
  "type": "Feature",
  "properties": {
    "iso:country":"CH",
    "sg:address":"Sonnenstrasse 16",
    "sg:city":"Kreuzlingen",
    "sg:orig_category":"Detailhandel mit Radio U Fernsehger\u00e4ten",
    "sg:phone":"+41 32 916 10 21",
    "sg:postcode":"8280",
    "sg:province":"Thurgau",
    "wof:name":"Interdiscount Sa Hi-fi Video Photo Radio",
    "wof:placetype":"venue"
},
  "geometry": {"coordinates":[6.8291797638,47.1021652222],"type":"Point"}
}