{
  "type": "Feature",
  "properties": {
    "iso:country":"CH",
    "sg:address":"Chalet La Vigne",
    "sg:city":"Verbier",
    "sg:orig_category":"Non-Classified Establishments",
    "sg:postcode":"1936",
    "sg:province":"Valais",
    "wof:name":"Britannia Traductions S.\u00e0 R.l.",
    "wof:placetype":"venue"
},
  "geometry": {"coordinates":[7.2229619026,46.0967292786],"type":"Point"}
}