{
  "type": "Feature",
  "properties": {
    "iso:country":"CH",
    "sg:address":"Kirchstrasse 60 9400 Rorschach. Postfach",
    "sg:city":"Rorschach",
    "sg:classifiers":[
        {
            "category":"Restaurant",
            "type":"Food & Drink"
        }
    ],
    "sg:phone":"+41 71 931 12 55",
    "sg:postcode":"9401",
    "sg:province":"St. Gallen",
    "wof:name":"Restaurant Toggenburg",
    "wof:placetype":"venue"
},
  "geometry": {"coordinates":[9.0261001587,47.4062538147],"type":"Point"}
}