{
  "type": "Feature",
  "properties": {
    "iso:country":"CH",
    "sg:address":"B\u00fcchelstrasse 6",
    "sg:city":"Widnau",
    "sg:orig_category":"Detailhandel mit Fleisch U Fleischwaren",
    "sg:phone":"+41 71 720 03 33",
    "sg:postcode":"9443",
    "sg:province":"St. Gallen",
    "wof:name":"Sonderegger Paul",
    "wof:placetype":"venue"
},
  "geometry": {"coordinates":[9.6385087967,47.4017906189],"type":"Point"}
}