{
  "type": "Feature",
  "properties": {
    "iso:country":"CH",
    "sg:address":"Sigmundstrasse 1",
    "sg:city":"Liestal",
    "sg:orig_category":"Architekturb\u00fcros",
    "sg:phone":"+41 61 927 96 88",
    "sg:postcode":"4410",
    "sg:province":"Basel-Landschaft",
    "wof:name":"Architeam Design Ag",
    "wof:placetype":"venue"
},
  "geometry": {"coordinates":[7.743348,47.478859],"type":"Point"}
}