{
  "type": "Feature",
  "properties": {
    "iso:country":"CH",
    "sg:address":"Via Alle Vigne 31",
    "sg:city":"Locarno",
    "sg:orig_category":"Detailhandel mit elektrischen Haushaltsger\u00e4ten",
    "sg:phone":"+41 91 751 20 05",
    "sg:postcode":"6600",
    "sg:province":"Ticino",
    "wof:name":"Rita Biaggi Macchine Per Cucire Pfaff",
    "wof:placetype":"venue"
},
  "geometry": {"coordinates":[8.7720403671,46.1717529297],"type":"Point"}
}