{
  "type": "Feature",
  "properties": {
    "iso:country":"CH",
    "sg:address":"Husmattstrasse 7",
    "sg:city":"Belp",
    "sg:orig_category":"Grosshandel mit Textilien",
    "sg:phone":"+41 31 819 45 64",
    "sg:postcode":"3123",
    "sg:province":"Bern",
    "wof:name":"Blunier Textil",
    "wof:placetype":"venue"
},
  "geometry": {"coordinates":[7.5027308464,46.8864822388],"type":"Point"}
}