{
  "type": "Feature",
  "properties": {
    "iso:country":"CH",
    "sg:address":"Murbacherstrasse 38 4056 Basel. Postfach",
    "sg:city":"Basel",
    "sg:orig_category":"Fachdetailhandel in Verkaufsr\u00e4umen",
    "sg:postcode":"4051",
    "sg:province":"Basel-Stadt",
    "wof:name":"Winter Jean Velo, Motorr\u00e4der; Handel, Rep.",
    "wof:placetype":"venue"
},
  "geometry": {"coordinates":[7.5767970085,47.5692825317],"type":"Point"}
}