{
  "type": "Feature",
  "properties": {
    "addr:full":"M\u00fcnsterplatz 4 Basel Basel-Stadt 4051",
    "addr:housenumber":"4",
    "addr:postcode":"4051",
    "addr:street":"Muensterplatz",
    "iso:country":"CH",
    "sg:address":"M\u00fcnsterplatz 4",
    "sg:city":"Basel",
    "sg:orig_category":"Bibliotheken U Archive Pensionskassen",
    "sg:phone":"+41 61 269 66 44",
    "sg:postcode":"4051",
    "sg:province":"Basel-Stadt",
    "wof:name":"Paul Sacher Stiftung",
    "wof:placetype":"venue"
},
  "geometry": {"coordinates":[7.592107,47.55706],"type":"Point"}
}