{
  "type": "Feature",
  "properties": {
    "iso:country":"CH",
    "sg:address":"Mattenweg 5",
    "sg:city":"Frick",
    "sg:orig_category":"Museen",
    "sg:phone":"+41 62 865 28 06",
    "sg:postcode":"5070",
    "sg:province":"Aargau",
    "wof:name":"Sauriermuseum Frick",
    "wof:placetype":"venue"
},
  "geometry": {"coordinates":[8.0142030716,47.5057373047],"type":"Point"}
}