{
  "type": "Feature",
  "properties": {
    "iso:country":"CH",
    "sg:address":"Alter Z\u00fcrichweg 32 5702 Niederlenz. Postfach",
    "sg:city":"Niederlenz",
    "sg:orig_category":"Maler U Glasergewerbe",
    "sg:phone":"+41 56 622 34 88",
    "sg:postcode":"5702",
    "sg:province":"Aargau",
    "wof:name":"Malergesch\u00e4ft Buri Erwin.",
    "wof:placetype":"venue"
},
  "geometry": {"coordinates":[8.2677268982,47.3240203857],"type":"Point"}
}