{
  "type": "Feature",
  "properties": {
    "iso:country":"CH",
    "sg:address":"Marktgasse 41",
    "sg:city":"Winterthur",
    "sg:orig_category":"Detailhandel mit B\u00fcchern Detailhandel mit B\u00fcchern, Zeitungen, Schreib U Papeteriewaren",
    "sg:phone":"+41 52 212 65 88",
    "sg:postcode":"8400",
    "sg:province":"Z\u00fcrich",
    "wof:name":"Buchhandlung Vogel Ag",
    "wof:placetype":"venue"
},
  "geometry": {"coordinates":[8.727981,47.499416],"type":"Point"}
}