{
  "type": "Feature",
  "properties": {
    "iso:country":"CH",
    "sg:address":"Industrie Nord 6210 Sursee. Postfach 273",
    "sg:city":"Sursee",
    "sg:orig_category":"Sonstiger Grosshandel",
    "sg:phone":"+41 41 921 27 70",
    "sg:postcode":"6210",
    "sg:province":"Luzern",
    "wof:name":"Muri Ag",
    "wof:placetype":"venue"
},
  "geometry": {"coordinates":[8.097360611,47.1749610901],"type":"Point"}
}