{
  "type": "Feature",
  "properties": {
    "iso:country":"CH",
    "sg:address":"Trittligasse 2",
    "sg:city":"Z\u00fcrich",
    "sg:orig_category":"Druck ohne Zeitungsdruck",
    "sg:postcode":"8001",
    "sg:province":"Z\u00fcrich",
    "wof:name":"Druckerei Kalbermatten E. & J.-p.",
    "wof:placetype":"venue"
},
  "geometry": {"coordinates":[7.933672905,46.1117172241],"type":"Point"}
}