{
  "type": "Feature",
  "properties": {
    "iso:country":"CH",
    "sg:address":"Waagtalstrasse 23",
    "sg:city":"Unteriberg",
    "sg:orig_category":"Autolackierereien Autospenglereien",
    "sg:phone":"+41 34 402 11 51",
    "sg:postcode":"8842",
    "sg:province":"Schwyz",
    "wof:name":"Klaus Reusser Autospritzwerk Schriften",
    "wof:placetype":"venue"
},
  "geometry": {"coordinates":[7.75759,46.949127],"type":"Point"}
}