{
  "type": "Feature",
  "properties": {
    "iso:country":"CH",
    "sg:address":"Route De Nyon 2a",
    "sg:city":"Gland",
    "sg:orig_category":"Handelsvermittlung U Grosshandel Sonstiger Grosshandel",
    "sg:phone":"+41 22 364 60 60",
    "sg:postcode":"1196",
    "sg:province":"Vaud",
    "wof:name":"Provic Sa",
    "wof:placetype":"venue"
},
  "geometry": {"coordinates":[6.2677612305,46.4195022583],"type":"Point"}
}