{
  "type": "Feature",
  "properties": {
    "iso:country":"CH",
    "sg:address":"Pretorio Via 7",
    "sg:city":"Lugano",
    "sg:orig_category":"Grosshandel mit Textilien",
    "sg:phone":"+41 18292523",
    "sg:postcode":"6900",
    "sg:province":"Ticino",
    "wof:name":"Tex-life Ag",
    "wof:placetype":"venue"
},
  "geometry": {"coordinates":[8.8610420227,47.1878356934],"type":"Point"}
}