{
  "type": "Feature",
  "properties": {
    "iso:country":"CH",
    "sg:address":"Chemin De La Meuni\u00e8re 12",
    "sg:city":"Prilly",
    "sg:classifiers":[
        {
            "category":"Ferry Terminal",
            "type":"Transportation"
        }
    ],
    "sg:phone":"+41 21 624 45 33",
    "sg:postcode":"1008",
    "sg:province":"Vaud",
    "sg:tags":[
        "trolley",
        "hoist",
        "electric"
    ],
    "wof:name":"W. Burri S.a.",
    "wof:placetype":"venue"
},
  "geometry": {"coordinates":[6.602369,46.529968],"type":"Point"}
}