{
  "type": "Feature",
  "properties": {
    "iso:country":"CH",
    "sg:address":"Luc",
    "sg:city":"Ayent",
    "sg:orig_category":"Mechanik Schlossereien",
    "sg:phone":"+41 71 655 11 26",
    "sg:postcode":"1966",
    "sg:province":"Valais",
    "wof:name":"Bissegger Ag",
    "wof:placetype":"venue"
},
  "geometry": {"coordinates":[9.0563354492,47.5365982056],"type":"Point"}
}