{
  "type": "Feature",
  "properties": {
    "addr:full":"Schachenstrasse 7 Hedingen Z\u00fcrich 8908",
    "addr:housenumber":"7",
    "addr:postcode":"8908",
    "addr:street":"Schachenstrasse",
    "iso:country":"CH",
    "sg:address":"Schachenstrasse 7",
    "sg:city":"Hedingen",
    "sg:classifiers":[
        {
            "category":"Education",
            "subcategory":"Library",
            "type":"Public Place"
        }
    ],
    "sg:phone":"+41 17002477",
    "sg:postcode":"8908",
    "sg:province":"Z\u00fcrich",
    "sg:tags":[
        "u",
        "bibliotheken",
        "archive"
    ],
    "wof:name":"Gemeindebibliothek",
    "wof:placetype":"venue"
},
  "geometry": {"coordinates":[8.444852,47.297249],"type":"Point"}
}