{
  "type": "Feature",
  "properties": {
    "iso:country":"CH",
    "sg:address":"Gerbeg\u00e4sslein 5",
    "sg:city":"Sissach",
    "sg:orig_category":"HERSTELLUNG VON GER\u00c4TEN DER ELEKTRIZIT\u00c4TSERZEUGUNG, -VERTEILUNG U.\u00c4 Herstellung von sonstigen elektr",
    "sg:phone":"+41 61 971 49 01",
    "sg:postcode":"4450",
    "sg:province":"Basel-Landschaft",
    "wof:name":"Grieder Electronic",
    "wof:placetype":"venue"
},
  "geometry": {"coordinates":[7.8125758171,47.4660301208],"type":"Point"}
}