{
  "type": "Feature",
  "properties": {
    "iso:country":"CH",
    "sg:address":"Schwanden 324",
    "sg:city":"Oberhelfenschwil",
    "sg:orig_category":"Architektur U Ingenieurb\u00fcros",
    "sg:phone":"+41 71 376 00 76",
    "sg:postcode":"9621",
    "sg:province":"St. Gallen",
    "wof:name":"Bl\u00f6chinger Holzbautechnik",
    "wof:placetype":"venue"
},
  "geometry": {"coordinates":[9.105724,47.341862],"type":"Point"}
}