{
  "type": "Feature",
  "properties": {
    "iso:country":"CH",
    "sg:address":"S\u00e4ntisstrasse 14",
    "sg:city":"Siebnen",
    "sg:orig_category":"Allgemeiner Hoch U Tiefbau",
    "sg:postcode":"8854",
    "sg:province":"Schwyz",
    "wof:name":"Krieg Hanspeter",
    "wof:placetype":"venue"
},
  "geometry": {"coordinates":[8.902316,47.181702],"type":"Point"}
}