{
  "type": "Feature",
  "properties": {
    "iso:country":"CH",
    "sg:address":"Via Collina D'oro 98 6926 Montagnola. Postfach",
    "sg:city":"Lugano",
    "sg:orig_category":"Finanzierungsinstitutionen Wirtschaftspr\u00fcfung, Steuerberatung U Treuhand",
    "sg:phone":"+41 91 994 31 21",
    "sg:postcode":"6900",
    "sg:province":"Ticino",
    "wof:name":"Km International Financial Consulting Sa Consulenza Finanziaria, Commerciale Ecc",
    "wof:placetype":"venue"
},
  "geometry": {"coordinates":[8.9169044495,45.9813270569],"type":"Point"}
}