{
  "type": "Feature",
  "properties": {
    "iso:country":"CH",
    "sg:address":"Rue Erhard-borel 24",
    "sg:city":"Neuch\u00e2tel",
    "sg:orig_category":"RESTAURANTS: TEA-ROOMS",
    "sg:phone":"+41 32 731 50 20",
    "sg:postcode":"2000",
    "sg:province":"Neuch\u00e2tel",
    "wof:name":"Caf\u00e9-restaurant Du Pont, Eliane Gallet",
    "wof:placetype":"venue"
},
  "geometry": {"coordinates":[6.9038410187,46.9827537537],"type":"Point"}
}