{
  "type": "Feature",
  "properties": {
    "iso:country":"CH",
    "sg:address":"Via Al Doyro 1b",
    "sg:city":"Melide",
    "sg:orig_category":"Allgemeiner Hoch U Tiefbau Allgemeiner Hochbau",
    "sg:phone":"+41 91 649 45 40",
    "sg:postcode":"6815",
    "sg:province":"Ticino",
    "wof:name":"Gimotecno Sa",
    "wof:placetype":"venue"
},
  "geometry": {"coordinates":[8.944894,45.95274],"type":"Point"}
}