{
  "type": "Feature",
  "properties": {
    "iso:country":"CH",
    "sg:address":"Bahnhofstrasse 1",
    "sg:city":"Oberaach",
    "sg:orig_category":"Herstellung von D\u00fcngemitteln U Stickstoffverbindungen Herstellung von pharmazeutischen Grundstoffen",
    "sg:phone":"+41 71 414 04 14",
    "sg:postcode":"8587",
    "sg:province":"Thurgau",
    "wof:name":"K\u00fcnzle Farma Ag",
    "wof:placetype":"venue"
},
  "geometry": {"coordinates":[9.2670021057,47.5541915894],"type":"Point"}
}