{
  "type": "Feature",
  "properties": {
    "iso:country":"CH",
    "sg:address":"Simplon Rue Du 148",
    "sg:city":"Martigny",
    "sg:orig_category":"Nahrungsmittel-Industrie: Rohstoffe",
    "sg:phone":"+41 27 723 24 22",
    "sg:postcode":"1920",
    "sg:province":"Valais",
    "wof:name":"Dos Reis Anibal Manuel Da Surrei\u00e7ao",
    "wof:placetype":"venue"
},
  "geometry": {"coordinates":[7.0896887779,46.1082763672],"type":"Point"}
}