{
  "type": "Feature",
  "properties": {
    "iso:country":"CH",
    "sg:address":"Via Guisan 14",
    "sg:city":"Paradiso",
    "sg:orig_category":"Detailhandel mit Geschenkartikeln U Souvenirs",
    "sg:phone":"+41 91 994 22 30",
    "sg:postcode":"6900",
    "sg:province":"Ticino",
    "wof:name":"Luigi Taborelli Confezioni-maglieria Sayonara",
    "wof:placetype":"venue"
},
  "geometry": {"coordinates":[8.9467811584,45.9910125732],"type":"Point"}
}