{
  "type": "Feature",
  "properties": {
    "iso:country":"CH",
    "sg:address":"Im Baumgarten 1",
    "sg:city":"Dietwil",
    "sg:orig_category":"Grafikateliers, Design",
    "sg:phone":"+41 52 347 19 91",
    "sg:postcode":"6042",
    "sg:province":"Aargau",
    "wof:name":"Nicole Morf Grafic Creative Design",
    "wof:placetype":"venue"
},
  "geometry": {"coordinates":[8.7150764465,47.433391571],"type":"Point"}
}