{
  "type": "Feature",
  "properties": {
    "iso:country":"CH",
    "sg:address":"Merkurstrasse 3",
    "sg:city":"W\u00e4denswil",
    "sg:orig_category":"Allgemeiner Hoch U Tiefbau",
    "sg:phone":"+41 79 404 16 48",
    "sg:postcode":"8820",
    "sg:province":"Z\u00fcrich",
    "wof:name":"Hauser Umbauten",
    "wof:placetype":"venue"
},
  "geometry": {"coordinates":[8.756313,47.306744],"type":"Point"}
}