{
  "type": "Feature",
  "properties": {
    "iso:country":"CH",
    "sg:address":"Gempenstrasse 60",
    "sg:city":"Dornach",
    "sg:orig_category":"Mechanik Mechanische Werkst\u00e4tten",
    "sg:postcode":"4143",
    "sg:province":"Solothurn",
    "wof:name":"Zimmermann Peter",
    "wof:placetype":"venue"
},
  "geometry": {"coordinates":[7.622988224,47.4752807617],"type":"Point"}
}