{
  "type": "Feature",
  "properties": {
    "iso:country":"CH",
    "sg:address":"D\u00f6rflistrasse 28",
    "sg:city":"Z\u00fcrich",
    "sg:orig_category":"Sonstiger Grosshandel",
    "sg:postcode":"8057",
    "sg:province":"Z\u00fcrich",
    "wof:name":"B\u00e4ni Trading & Co",
    "wof:placetype":"venue"
},
  "geometry": {"coordinates":[8.5497941971,47.4048423767],"type":"Point"}
}