{
  "type": "Feature",
  "properties": {
    "iso:country":"CH",
    "sg:address":"St.martinsplatz 8",
    "sg:city":"Chur",
    "sg:orig_category":"Advokaturb\u00fcros Notariate",
    "sg:phone":"+41 79 238 97 82",
    "sg:postcode":"7000",
    "sg:province":"Graubunden",
    "wof:name":"Bieder & Ineichen Advokatur- & Notariatsb\u00fcro",
    "wof:placetype":"venue"
},
  "geometry": {"coordinates":[8.305527,47.052639],"type":"Point"}
}