{
  "type": "Feature",
  "properties": {
    "iso:country":"CH",
    "sg:address":"Chemin De La Golaz",
    "sg:city":"Yvonand",
    "sg:orig_category":"Handel mit Automobilteilen U Zubeh\u00f6r",
    "sg:postcode":"1462",
    "sg:province":"Vaud",
    "wof:name":"Graf Roland",
    "wof:placetype":"venue"
},
  "geometry": {"coordinates":[6.7541527748,46.7922325134],"type":"Point"}
}