{
  "type": "Feature",
  "properties": {
    "addr:full":"7412 Scharans Graubunden 7412",
    "addr:housenumber":"7412",
    "addr:postcode":"7412",
    "addr:street":"Scharans Graubunden",
    "iso:country":"CH",
    "sg:address":"7412",
    "sg:city":"Scharans",
    "sg:orig_category":"Architekturb\u00fcros",
    "sg:phone":"+41 81 651 17 66",
    "sg:postcode":"7412",
    "sg:province":"Graubunden",
    "wof:name":"Hansruedi Meuli Architekturb\u00fcro",
    "wof:placetype":"venue"
},
  "geometry": {"coordinates":[9.457932,46.717026],"type":"Point"}
}