{
  "type": "Feature",
  "properties": {
    "iso:country":"CH",
    "sg:address":"Eigerplatz 8",
    "sg:city":"Bern",
    "sg:orig_category":"Caterer Sonstiger Fachdetailhandel mit Nahrungsmitteln, Getr\u00e4nken U Tabak in Verkaufsr\u00e4umen",
    "sg:phone":"+41 31 372 05 18",
    "sg:postcode":"3007",
    "sg:province":"Bern",
    "wof:name":"Mu Tong Gmbh",
    "wof:placetype":"venue"
},
  "geometry": {"coordinates":[7.4308,46.941074],"type":"Point"}
}