{
  "type": "Feature",
  "properties": {
    "iso:country":"CH",
    "sg:address":"Rue Abb\u00e9-bovet 1",
    "sg:city":"Fribourg",
    "sg:orig_category":"Zahnarztpraxen",
    "sg:phone":"+41 26 322 31 24",
    "sg:postcode":"1700",
    "sg:province":"Fribourg",
    "wof:name":"Dr M\u00e9d. Dent. Jean-luc Faller M\u00e9decin-dentiste",
    "wof:placetype":"venue"
},
  "geometry": {"coordinates":[7.1553640366,46.8045196533],"type":"Point"}
}