{
  "type": "Feature",
  "properties": {
    "iso:country":"CH",
    "sg:address":"Riedmattenstrasse 48 2562 Port. Postfach",
    "sg:city":"Port",
    "sg:orig_category":"Markt U Meinungsforschung",
    "sg:phone":"+41 21 634 44 24",
    "sg:postcode":"2562",
    "sg:province":"Bern",
    "wof:name":"Gb Marketing D'espaces Publicitaires, Gabrielle Burnand",
    "wof:placetype":"venue"
},
  "geometry": {"coordinates":[6.5819392204,46.5396499634],"type":"Point"}
}