{
  "type": "Feature",
  "properties": {
    "iso:country":"CH",
    "sg:address":"Monbijoustrasse 10",
    "sg:city":"Bern",
    "sg:classifiers":[
        {
            "category":"Government",
            "subcategory":"Post Office",
            "type":"Public Place"
        }
    ],
    "sg:phone":"+41 31 381 28 10",
    "sg:postcode":"3011",
    "sg:province":"Bern",
    "sg:tags":[
        "caf\u00e9s",
        "tea-rooms"
    ],
    "wof:name":"Caf\u00e9 Cappuccino",
    "wof:placetype":"venue"
},
  "geometry": {"coordinates":[7.4367051125,46.945350647],"type":"Point"}
}