{
  "type": "Feature",
  "properties": {
    "iso:country":"CH",
    "sg:address":"Birmensdorferstrasse 535 8055 Z\u00fcrich. Postfach",
    "sg:city":"Z\u00fcrich",
    "sg:orig_category":"Innenarchitekturb\u00fcros",
    "sg:phone":"+41 14625100",
    "sg:postcode":"8055",
    "sg:province":"Z\u00fcrich",
    "wof:name":"Christian Bleuer Innenarchitektur",
    "wof:placetype":"venue"
},
  "geometry": {"coordinates":[8.4930839539,47.3669242859],"type":"Point"}
}