{
  "type": "Feature",
  "properties": {
    "iso:country":"CH",
    "sg:address":"Br\u00fchlstrasse 2",
    "sg:city":"Wettingen",
    "sg:orig_category":"Vermietung U Verpachtung von eigenen Immobilien",
    "sg:postcode":"5430",
    "sg:province":"Aargau",
    "wof:name":"Otto B\u00fchler's Erben",
    "wof:placetype":"venue"
},
  "geometry": {"coordinates":[8.3232803345,47.4678001404],"type":"Point"}
}