{
  "type": "Feature",
  "properties": {
    "iso:country":"CH",
    "sg:address":"Industriestrasse 18",
    "sg:city":"Embrach",
    "sg:orig_category":"Grosshandel mit Baumaschinen Grosshandel mit Holz U Baustoffen",
    "sg:phone":"+41 61 401 05 73",
    "sg:postcode":"8424",
    "sg:province":"Z\u00fcrich",
    "wof:name":"Richard Degen Trax & Pneuladeschaufeln",
    "wof:placetype":"venue"
},
  "geometry": {"coordinates":[7.5525860786,47.5133743286],"type":"Point"}
}