{
  "type": "Feature",
  "properties": {
    "iso:country":"CH",
    "sg:address":"Altstetterstrasse 159",
    "sg:city":"Z\u00fcrich",
    "sg:orig_category":"Zahnarztpraxen",
    "sg:phone":"+41 14311140",
    "sg:postcode":"8048",
    "sg:province":"Z\u00fcrich",
    "wof:name":"Dr.med.dent.arthur Rutishauser Zahnarzt",
    "wof:placetype":"venue"
},
  "geometry": {"coordinates":[8.4863424301,47.3868484497],"type":"Point"}
}