{
  "type": "Feature",
  "properties": {
    "iso:country":"CH",
    "sg:address":"Vollikerstrasse 22",
    "sg:city":"Esslingen",
    "sg:orig_category":"Architektur U Ingenieurb\u00fcros Herstellung von sonstigen elektrischen Ausr\u00fcstungen",
    "sg:phone":"+41 32 913 54 49",
    "sg:postcode":"8133",
    "sg:province":"Z\u00fcrich",
    "wof:name":"Onda Developments, D\u00e9nervaud P.",
    "wof:placetype":"venue"
},
  "geometry": {"coordinates":[6.827686,47.104458],"type":"Point"}
}