{
  "type": "Feature",
  "properties": {
    "iso:country":"CH",
    "sg:address":"Beim Bahnhof",
    "sg:city":"Rafz",
    "sg:orig_category":"Schlossereien Stahl U Leichtmetallbau",
    "sg:postcode":"8197",
    "sg:province":"Z\u00fcrich",
    "wof:name":"Gebr. Kranz Metallbauschlosserei Ag",
    "wof:placetype":"venue"
},
  "geometry": {"coordinates":[9.5510749817,47.2096252441],"type":"Point"}
}