{
  "type": "Feature",
  "properties": {
    "iso:country":"CH",
    "sg:address":"Seeblickstrasse 26a 9327 T\u00fcbach. Postfach",
    "sg:city":"T\u00fcbach",
    "sg:orig_category":"Herstellung von Konstruktionsteilen, Fertigbauteilen U Ausbauelementen aus Holz",
    "sg:phone":"+41 62 771 28 46",
    "sg:postcode":"9327",
    "sg:province":"St. Gallen",
    "wof:name":"Bieri St\u00e4ge Und Schreinerei Ag",
    "wof:placetype":"venue"
},
  "geometry": {"coordinates":[8.1727924347,47.2621192932],"type":"Point"}
}