{
  "type": "Feature",
  "properties": {
    "iso:country":"CH",
    "sg:address":"Boulevard De P\u00e9rolles 17 1700 Fribourg Case Postale 238",
    "sg:city":"Freiburg",
    "sg:orig_category":"Grosshandel mit chemischen Erzeugnissen",
    "sg:phone":"+41 26 402 40 58",
    "sg:postcode":"1700",
    "sg:province":"Fribourg",
    "wof:name":"Schlatter J.p. Sa",
    "wof:placetype":"venue"
},
  "geometry": {"coordinates":[7.1521830559,46.8002433777],"type":"Point"}
}