{
  "type": "Feature",
  "properties": {
    "iso:country":"CH",
    "sg:address":"Industriestrasse 15",
    "sg:city":"Gossau",
    "sg:classifiers":[
        {
            "category":"Building & Trades",
            "subcategory":"Construction",
            "type":"Services"
        }
    ],
    "sg:phone":"+41 71 388 82 82",
    "sg:postcode":"9200",
    "sg:province":"St. Gallen",
    "sg:tags":[
        "steel",
        "bridge"
    ],
    "wof:name":"Aepli & Co Metallbau",
    "wof:placetype":"venue"
},
  "geometry": {"coordinates":[9.2683639526,47.4136009216],"type":"Point"}
}