{
  "type": "Feature",
  "properties": {
    "iso:country":"CH",
    "sg:address":"Sur-les-planches 15",
    "sg:city":"Ballaigues",
    "sg:orig_category":"Sportvereine Ski",
    "sg:phone":"+41 21 843 19 29",
    "sg:postcode":"1338",
    "sg:province":"Vaud",
    "wof:name":"Ski-club Ballaigues",
    "wof:placetype":"venue"
},
  "geometry": {"coordinates":[6.4132351875,46.7299232483],"type":"Point"}
}