{
  "type": "Feature",
  "properties": {
    "iso:country":"CH",
    "sg:address":"Combe Chemin De La 12 1197 Prangins. Postfach",
    "sg:city":"Mont-sur-rolle",
    "sg:orig_category":"Finanzierungsinstitutionen",
    "sg:postcode":"1185",
    "sg:province":"Vaud",
    "wof:name":"Traprofin Sa",
    "wof:placetype":"venue"
},
  "geometry": {"coordinates":[6.2490000725,46.3943252563],"type":"Point"}
}