{
  "type": "Feature",
  "properties": {
    "iso:country":"CH",
    "sg:address":"Bossi Via Emilio 1",
    "sg:city":"Chiasso",
    "sg:orig_category":"Detailhandel mit elektrischen Haushalts-,Radio U Fernsehger\u00e4ten sowie Musikinstrumenten",
    "sg:postcode":"6830",
    "sg:province":"Ticino",
    "wof:name":"Etam Gmbh",
    "wof:placetype":"venue"
},
  "geometry": {"coordinates":[9.6401453018,46.9913635254],"type":"Point"}
}