{
  "type": "Feature",
  "properties": {
    "iso:country":"CH",
    "sg:address":"Rue Rothschild 50",
    "sg:city":"Gen\u00e8ve",
    "sg:orig_category":"Datenverarbeitungsdienste Softwareentwicklung U beratung",
    "sg:phone":"+41 22 307 15 11",
    "sg:postcode":"1202",
    "sg:province":"Gen\u00e8ve",
    "wof:name":"Elca Informatique Sa Succursale De Gen\u00e8ve",
    "wof:placetype":"venue"
},
  "geometry": {"coordinates":[6.14752,46.215649],"type":"Point"}
}