{
  "type": "Feature",
  "properties": {
    "iso:country":"CH",
    "sg:address":"Chemin De Champittet 1009 Pully Case Postale 622",
    "sg:city":"Pully",
    "sg:orig_category":"Allgemeinbildende weiterf\u00fchrende Schulen Bezirks, Sekundar, Realschulen, Oberstufe der Primarschulen",
    "sg:phone":"+41 21 728 66 44",
    "sg:postcode":"1009",
    "sg:province":"Vaud",
    "wof:name":"Coll\u00e8ge Champittet Sa",
    "wof:placetype":"venue"
},
  "geometry": {"coordinates":[6.643384,46.507889],"type":"Point"}
}