{
  "type": "Feature",
  "properties": {
    "iso:country":"CH",
    "sg:address":"Via Bongio",
    "sg:city":"Coldrerio",
    "sg:orig_category":"Grosshandel mit sonstigen Halbwaren",
    "sg:phone":"+41 91 646 19 15",
    "sg:postcode":"6877",
    "sg:province":"Ticino",
    "wof:name":"Armando Kessler Commercio Carta All'ingrosso",
    "wof:placetype":"venue"
},
  "geometry": {"coordinates":[8.989616394,45.8527297974],"type":"Point"}
}