{
  "type": "Feature",
  "properties": {
    "addr:full":"Talstrasse 19 Seon Aargau 5703",
    "addr:housenumber":"19",
    "addr:postcode":"5703",
    "addr:street":"Talstrasse",
    "iso:country":"CH",
    "sg:address":"Talstrasse 19",
    "sg:city":"Seon",
    "sg:orig_category":"Detailhandel mit Brennstoffen U Heizmaterial G\u00fcterbef\u00f6rderung im Strassenverkehr",
    "sg:phone":"+41 79 402 04 21",
    "sg:postcode":"5703",
    "sg:province":"Aargau",
    "wof:name":"Ernst H\u00e4rri",
    "wof:placetype":"venue"
},
  "geometry": {"coordinates":[8.158083,47.350746],"type":"Point"}
}