{
  "type": "Feature",
  "properties": {
    "iso:country":"CH",
    "sg:address":"5330",
    "sg:city":"Zurzach",
    "sg:orig_category":"Vereine Damen Vereine Gesang",
    "sg:postcode":"5330",
    "sg:province":"Aargau",
    "wof:name":"T\u00f6chterchor",
    "wof:placetype":"venue"
},
  "geometry": {"coordinates":[7.5253500938,47.5052108765],"type":"Point"}
}