{
  "type": "Feature",
  "properties": {
    "addr:full":"Rue De L'epervier 9 Cernier Neuch\u00e2tel 2053",
    "addr:housenumber":"9",
    "addr:postcode":"2053",
    "addr:street":"Rue De L'Epervier;Neucha\u0302Tel",
    "iso:country":"CH",
    "sg:address":"Rue De L'epervier 9",
    "sg:city":"Cernier",
    "sg:orig_category":"Detailhandel mit Bekleidung Detailhandel mit Textilien",
    "sg:phone":"+41 32 751 23 30",
    "sg:postcode":"2053",
    "sg:province":"Neuch\u00e2tel",
    "wof:name":"Boutique Au Griffon Lingerie Confection Mercerie",
    "wof:placetype":"venue"
},
  "geometry": {"coordinates":[7.067525,47.055859],"type":"Point"}
}