{
  "type": "Feature",
  "properties": {
    "iso:country":"CH",
    "sg:address":"Hasleren",
    "sg:city":"Schweizersholz",
    "sg:orig_category":"Gartenbau",
    "sg:phone":"+41 71 642 35 40",
    "sg:postcode":"9223",
    "sg:province":"Thurgau",
    "wof:name":"Gartenbau-team Knill + Bieri",
    "wof:placetype":"venue"
},
  "geometry": {"coordinates":[9.193939209,47.5027694702],"type":"Point"}
}