{
  "type": "Feature",
  "properties": {
    "iso:country":"CH",
    "sg:address":"Aeschenvorstadt 24",
    "sg:city":"Basel",
    "sg:orig_category":"Unterhaltung, Kultur U Sport Unterrichtswesen",
    "sg:phone":"+41 76 330 15 99",
    "sg:postcode":"4051",
    "sg:province":"Basel-Stadt",
    "wof:name":"Step On Stage Stepptanzgruppe",
    "wof:placetype":"venue"
},
  "geometry": {"coordinates":[7.5927171707,47.5528831482],"type":"Point"}
}