{
  "type": "Feature",
  "properties": {
    "iso:country":"CH",
    "sg:address":"Eichlistrasse 5",
    "sg:city":"M\u00e4genwil",
    "sg:orig_category":"Haltung von Gefl\u00fcgel Schlachten von Gefl\u00fcgel",
    "sg:postcode":"5506",
    "sg:province":"Aargau",
    "wof:name":"Werner L\u00e4tt Goldfarm Produkte",
    "wof:placetype":"venue"
},
  "geometry": {"coordinates":[7.4800739288,47.1393699646],"type":"Point"}
}