{
  "type": "Feature",
  "properties": {
    "iso:country":"CH",
    "sg:address":"Alpenweg 9",
    "sg:city":"Oberbipp",
    "sg:orig_category":"Unternehmensberatung",
    "sg:phone":"+41 79 251 11 90",
    "sg:postcode":"4538",
    "sg:province":"Bern",
    "wof:name":"Korff Consult",
    "wof:placetype":"venue"
},
  "geometry": {"coordinates":[7.6626329422,47.2649269104],"type":"Point"}
}