{
  "type": "Feature",
  "properties": {
    "iso:country":"CH",
    "sg:address":"Hauptstrasse",
    "sg:city":"Baltschieder",
    "sg:orig_category":"Instandhaltung U Reparatur von Automobilen",
    "sg:phone":"+41 17616871",
    "sg:postcode":"3937",
    "sg:province":"Valais",
    "wof:name":"Carrosserie Estermann H.",
    "wof:placetype":"venue"
},
  "geometry": {"coordinates":[8.4402770996,47.2766151428],"type":"Point"}
}