{
  "type": "Feature",
  "properties": {
    "iso:country":"CH",
    "sg:address":"Moosstrasse 1",
    "sg:city":"Luzern",
    "sg:orig_category":"Zahnarztpraxen",
    "sg:phone":"+41 56 443 02 08",
    "sg:postcode":"6003",
    "sg:province":"Luzern",
    "wof:name":"Dr. Med. Dent. Dominik Burkart Zahnarzt",
    "wof:placetype":"venue"
},
  "geometry": {"coordinates":[8.1430702209,47.4475212097],"type":"Point"}
}