{
  "type": "Feature",
  "properties": {
    "iso:country":"CH",
    "sg:address":"4522",
    "sg:city":"R\u00fcttenen",
    "sg:classifiers":[
        {
            "category":"Restaurant",
            "type":"Food & Drink"
        }
    ],
    "sg:phone":"+41 62 756 48 35",
    "sg:postcode":"4522",
    "sg:province":"Solothurn",
    "wof:name":"Restaurant Eintracht",
    "wof:placetype":"venue"
},
  "geometry": {"coordinates":[8.0369100571,47.2019081116],"type":"Point"}
}