{
  "type": "Feature",
  "properties": {
    "iso:country":"CH",
    "sg:address":"Zielstrasse 38 9050 Appenzell. Postfach",
    "sg:city":"Appenzell",
    "sg:orig_category":"Grosshandel mit Textilien",
    "sg:phone":"+41 55 210 96 10",
    "sg:postcode":"9050",
    "sg:province":"Appenzell Innerhoden",
    "wof:name":"Alberto T-shirt-shop Lendenmann Christa",
    "wof:placetype":"venue"
},
  "geometry": {"coordinates":[8.8146791458,47.2264022827],"type":"Point"}
}