{
  "type": "Feature",
  "properties": {
    "iso:country":"CH",
    "sg:address":"Culmannstrasse 64",
    "sg:city":"Z\u00fcrich",
    "sg:orig_category":"Allgemeiner Hoch U Tiefbau",
    "sg:postcode":"8006",
    "sg:province":"Z\u00fcrich",
    "wof:name":"Hovadik Bauberatung",
    "wof:placetype":"venue"
},
  "geometry": {"coordinates":[8.547536,47.383419],"type":"Point"}
}