{
  "type": "Feature",
  "properties": {
    "iso:country":"CH",
    "sg:address":"Postfach",
    "sg:city":"M\u00fchleberg",
    "sg:classifiers":[
        {
            "category":"Utilities",
            "subcategory":"Electric",
            "type":"Services"
        }
    ],
    "sg:phone":"+41 32 631 43 43",
    "sg:postcode":"3203",
    "sg:province":"Bern",
    "sg:tags":[
        "electricity",
        "electronic",
        "electrical",
        "equipment"
    ],
    "wof:name":"Bkw Fmb Energie Ag",
    "wof:placetype":"venue"
},
  "geometry": {"coordinates":[7.9403700829,47.260269165],"type":"Point"}
}