{
  "type": "Feature",
  "properties": {
    "iso:country":"CH",
    "sg:address":"Dammstrasse 21 4500 Solothurn. Postfach",
    "sg:city":"Solothurn",
    "sg:orig_category":"Schiffsbau ohne Boots U Yachtbau",
    "sg:postcode":"4500",
    "sg:province":"Solothurn",
    "wof:name":"Solocruise Ag Binnen- U. Hochseeschiffe; Ankauf, Chartern Usw",
    "wof:placetype":"venue"
},
  "geometry": {"coordinates":[7.5324511528,47.205871582],"type":"Point"}
}