{
  "type": "Feature",
  "properties": {
    "iso:country":"CH",
    "sg:address":"M\u00fchledorfstrasse 58",
    "sg:city":"Niederg\u00f6sgen",
    "sg:classifiers":[
        {
            "category":"Organizations",
            "subcategory":"Non-profit Organization",
            "type":"Services"
        }
    ],
    "sg:phone":"+41 62 849 14 14",
    "sg:postcode":"5013",
    "sg:province":"Solothurn",
    "sg:tags":[
        "feeding",
        "dairy",
        "system",
        "cattle"
    ],
    "wof:name":"Gb Silo System Ag",
    "wof:placetype":"venue"
},
  "geometry": {"coordinates":[7.9704499245,47.3686714172],"type":"Point"}
}