{
  "type": "Feature",
  "properties": {
    "iso:country":"CH",
    "sg:address":"3210",
    "sg:city":"Kerzers",
    "sg:orig_category":"Politische Parteien CVP",
    "sg:phone":"+41 26 424 47 30",
    "sg:postcode":"3210",
    "sg:province":"Fribourg",
    "wof:name":"Cvp Ortspartei See",
    "wof:placetype":"venue"
},
  "geometry": {"coordinates":[7.1956620216,46.9756240845],"type":"Point"}
}