{
  "type": "Feature",
  "properties": {
    "iso:country":"CH",
    "sg:address":"Hasenb\u00fcelweg 34",
    "sg:city":"Zug",
    "sg:orig_category":"Unclassifiable Establishments",
    "sg:phone":"+41 41 720 35 83",
    "sg:postcode":"6300",
    "sg:province":"Zug",
    "wof:name":"Tanson Medical Ag",
    "wof:placetype":"venue"
},
  "geometry": {"coordinates":[8.5164690018,47.1527366638],"type":"Point"}
}