{
  "type": "Feature",
  "properties": {
    "iso:country":"CH",
    "sg:address":"Place H.-c.dubois 1",
    "sg:city":"Buttes",
    "sg:orig_category":"Gemeindeverwaltungen",
    "sg:phone":"+41 32 861 13 75",
    "sg:postcode":"2115",
    "sg:province":"Neuch\u00e2tel",
    "wof:name":"Administration Communale De Buttes",
    "wof:placetype":"venue"
},
  "geometry": {"coordinates":[6.5518298149,46.88829422],"type":"Point"}
}