{
  "type": "Feature",
  "properties": {
    "iso:country":"CH",
    "sg:address":"Montolivet Chemin De 35 1006 Lausanne. Postfach",
    "sg:city":"Lausanne",
    "sg:orig_category":"Finanzierungsinstitutionen",
    "sg:phone":"+41 22 731 10 13",
    "sg:postcode":"1003",
    "sg:province":"Vaud",
    "wof:name":"G & R Finance Sa Soci\u00e9t\u00e9 Financi\u00e8re",
    "wof:placetype":"venue"
},
  "geometry": {"coordinates":[6.1519899368,46.2136878967],"type":"Point"}
}