{
  "type": "Feature",
  "properties": {
    "iso:country":"CH",
    "sg:address":"Av. Jean-j. Rousseau 19",
    "sg:city":"Clarens",
    "sg:classifiers":[
        {
            "category":"Travel",
            "subcategory":"Hotels & Motels",
            "type":"Entertainment"
        }
    ],
    "sg:phone":"+41 21 989 98 98",
    "sg:postcode":"1815",
    "sg:province":"Vaud",
    "sg:tags":[
        "equipment",
        "hotels",
        "restaurant"
    ],
    "wof:name":"B\u00e9ard S.a.",
    "wof:placetype":"venue"
},
  "geometry": {"coordinates":[6.8917179108,46.4430427551],"type":"Point"}
}