{
  "type": "Feature",
  "properties": {
    "iso:country":"CH",
    "sg:address":"Sigensee",
    "sg:city":"M\u00fcnchwilen",
    "sg:classifiers":[
        {
            "category":"Manufacturing",
            "subcategory":"Food",
            "type":"Manufacturing & Wholesale Goods"
        }
    ],
    "sg:phone":"+41 71 969 40 10",
    "sg:postcode":"9542",
    "sg:province":"Thurgau",
    "sg:tags":[
        "recycling"
    ],
    "wof:name":"Hunziker Food Recycling Ag",
    "wof:placetype":"venue"
},
  "geometry": {"coordinates":[9.0075702667,47.4766845703],"type":"Point"}
}