{
  "type": "Feature",
  "properties": {
    "iso:country":"CH",
    "sg:address":"Zugerstrasse 46 6340 Baar. Postfach",
    "sg:city":"Zug",
    "sg:orig_category":"Handelsvermittlung U Grosshandel",
    "sg:phone":"+41 41 761 03 70",
    "sg:postcode":"6302",
    "sg:province":"Zug",
    "wof:name":"Isa Zug Ag Int.handelsgesellschaft",
    "wof:placetype":"venue"
},
  "geometry": {"coordinates":[8.521150589,47.1875648499],"type":"Point"}
}