{
  "type": "Feature",
  "properties": {
    "iso:country":"CH",
    "sg:address":"1473",
    "sg:city":"Font",
    "sg:classifiers":[
        {
            "category":"Travel",
            "subcategory":"Hotels & Motels",
            "type":"Entertainment"
        }
    ],
    "sg:postcode":"1473",
    "sg:province":"Fribourg",
    "sg:tags":[
        "hotels",
        "mit",
        "restaurant"
    ],
    "wof:name":"Brasey Antoine.",
    "wof:placetype":"venue"
},
  "geometry": {"coordinates":[6.8206748962,46.8364982605],"type":"Point"}
}