{
  "type": "Feature",
  "properties": {
    "iso:country":"CH",
    "sg:address":"Greifengasse 14",
    "sg:city":"Basel",
    "sg:orig_category":"Fachdetailhandel mit pharmazeutischen Produkten",
    "sg:phone":"+41 55 415 63 33",
    "sg:postcode":"4058",
    "sg:province":"Basel-Stadt",
    "wof:name":"L\u00f6wenapotheke Krummenacher B.",
    "wof:placetype":"venue"
},
  "geometry": {"coordinates":[8.7781352997,47.2013778687],"type":"Point"}
}