{
  "type": "Feature",
  "properties": {
    "iso:country":"CH",
    "sg:address":"Prisongasse 4",
    "sg:city":"Solothurn",
    "sg:orig_category":"Grosshandel mit Getr\u00e4nken",
    "sg:phone":"+41 32 623 55 45",
    "sg:postcode":"4500",
    "sg:province":"Solothurn",
    "wof:name":"Restaurant Vini-al Grappolo",
    "wof:placetype":"venue"
},
  "geometry": {"coordinates":[7.5367279053,47.2050819397],"type":"Point"}
}