{
  "type": "Feature",
  "properties": {
    "iso:country":"CH",
    "sg:address":"Einsiedlerstrasse 31",
    "sg:city":"W\u00e4denswil",
    "sg:orig_category":"Gymnastik U Fitnesszentren Saunas, Solarien, Fitnesszentren U \u00e4hnliches",
    "sg:phone":"+41 17802091",
    "sg:postcode":"8820",
    "sg:province":"Z\u00fcrich",
    "wof:name":"Ernst Schmucki Fitness-& Sportstudio",
    "wof:placetype":"venue"
},
  "geometry": {"coordinates":[8.6873531342,47.218914032],"type":"Point"}
}