{
  "type": "Feature",
  "properties": {
    "iso:country":"CH",
    "sg:address":"Allmendstrasse 6",
    "sg:city":"Sursee",
    "sg:orig_category":"Gymnastik U Fitnesszentren Saunas, Solarien, Fitnesszentren U \u00e4hnliches",
    "sg:phone":"+41 41 920 30 40",
    "sg:postcode":"6210",
    "sg:province":"Luzern",
    "wof:name":"Tc Training Center Sursee Ag",
    "wof:placetype":"venue"
},
  "geometry": {"coordinates":[8.1089773178,47.1804199219],"type":"Point"}
}