{
  "type": "Feature",
  "properties": {
    "iso:country":"CH",
    "sg:address":"Bahnhofstrasse 11 6300 Zug. Postfach",
    "sg:city":"Zug",
    "sg:orig_category":"Grosshandel mit Holz U Baustoffen Herstellung von sonstigen elektrischen Ausr\u00fcstungen",
    "sg:phone":"+41 41 711 55 65",
    "sg:postcode":"6301",
    "sg:province":"Zug",
    "wof:name":"Rinotec Gmbh",
    "wof:placetype":"venue"
},
  "geometry": {"coordinates":[8.5155363083,47.1688194275],"type":"Point"}
}