{
  "type": "Feature",
  "properties": {
    "iso:country":"CH",
    "sg:address":"Via Sasselli",
    "sg:city":"Agno",
    "sg:orig_category":"Grosshandel mit Getr\u00e4nken",
    "sg:postcode":"6982",
    "sg:province":"Ticino",
    "wof:name":"Vini Cecchin",
    "wof:placetype":"venue"
},
  "geometry": {"coordinates":[8.8986873627,45.997013092],"type":"Point"}
}