{
  "type": "Feature",
  "properties": {
    "addr:full":"Chemin De Chandieu 1 Lausanne Vaud 1000",
    "addr:housenumber":"1",
    "addr:postcode":"1000",
    "addr:street":"Chemin De Chandieu",
    "iso:country":"CH",
    "sg:address":"Chemin De Chandieu 1",
    "sg:city":"Lausanne",
    "sg:orig_category":"Allgemeiner Hoch U Tiefbau",
    "sg:postcode":"1000",
    "sg:province":"Vaud",
    "wof:name":"Ribatec Sa, Port-louis, Succursale De Lausanne",
    "wof:placetype":"venue"
},
  "geometry": {"coordinates":[6.636867,46.512943],"type":"Point"}
}