{
  "type": "Feature",
  "properties": {
    "iso:country":"CH",
    "sg:address":"Gewerbestrasse 1",
    "sg:city":"Lyssach",
    "sg:orig_category":"Grosshandel mit pharmazeutischen Erzeugnissen Herstellung von medizinischen U chirurgischen Ger\u00e4ten ",
    "sg:phone":"+41 19911772",
    "sg:postcode":"3421",
    "sg:province":"Bern",
    "wof:name":"Isar Pharm Ag",
    "wof:placetype":"venue"
},
  "geometry": {"coordinates":[8.5925827026,47.3144493103],"type":"Point"}
}