{
  "type": "Feature",
  "properties": {
    "iso:country":"CH",
    "sg:address":"Seefeldstrasse 32/34 8008 Z\u00fcrich. Postfach",
    "sg:city":"Z\u00fcrich",
    "sg:orig_category":"Detailhandel mit fotografischen Artikeln Fachdetailhandel in Verkaufsr\u00e4umen",
    "sg:phone":"+41 12519408",
    "sg:postcode":"8034",
    "sg:province":"Z\u00fcrich",
    "wof:name":"Schorno Foto-video-radio-elektronik",
    "wof:placetype":"venue"
},
  "geometry": {"coordinates":[8.5492544174,47.3634529114],"type":"Point"}
}