{
  "type": "Feature",
  "properties": {
    "iso:country":"CH",
    "sg:address":"Gotthardstrasse 3",
    "sg:city":"Zug",
    "sg:orig_category":"Herstellung von sonstigen Nahrungsmitteln",
    "sg:postcode":"6300",
    "sg:province":"Zug",
    "wof:name":"Nutra Produkte Ag",
    "wof:placetype":"venue"
},
  "geometry": {"coordinates":[8.5175666809,47.171585083],"type":"Point"}
}