{
  "type": "Feature",
  "properties": {
    "iso:country":"CH",
    "sg:address":"Icogne 1977 Icogne. Postfach",
    "sg:city":"Icogne",
    "sg:orig_category":"Detailhandel mit Textilien",
    "sg:postcode":"1977",
    "sg:province":"Valais",
    "wof:name":"Bagnoud Mme Jeanine",
    "wof:placetype":"venue"
},
  "geometry": {"coordinates":[7.438272953,46.2908935547],"type":"Point"}
}