{
  "type": "Feature",
  "properties": {
    "iso:country":"CH",
    "sg:address":"Wartenbergstr. 40a",
    "sg:city":"Pratteln",
    "sg:orig_category":"Unternehmensberatung",
    "sg:phone":"+41 56 634 36 56",
    "sg:postcode":"4133",
    "sg:province":"Basel-Landschaft",
    "wof:name":"Schindler Consulto",
    "wof:placetype":"venue"
},
  "geometry": {"coordinates":[8.4385242462,47.3228569031],"type":"Point"}
}