{
  "type": "Feature",
  "properties": {
    "iso:country":"CH",
    "sg:address":"Besenrainstrasse 26",
    "sg:city":"Z\u00fcrich",
    "sg:orig_category":"Gartenbau",
    "sg:phone":"+41 14829045",
    "sg:postcode":"8038",
    "sg:province":"Z\u00fcrich",
    "wof:name":"Bernhard Oesch Gartenbau & Gartenpflege",
    "wof:placetype":"venue"
},
  "geometry": {"coordinates":[8.5272197723,47.3454055786],"type":"Point"}
}