{
  "type": "Feature",
  "properties": {
    "iso:country":"CH",
    "sg:address":"Gare Avenue De La 37",
    "sg:city":"Del\u00e9mont",
    "sg:orig_category":"Architektur U Ingenieurb\u00fcros",
    "sg:phone":"+41 79 687 24 85",
    "sg:postcode":"2800",
    "sg:province":"Jura",
    "wof:name":"Hulmann Marc",
    "wof:placetype":"venue"
},
  "geometry": {"coordinates":[7.34397,47.365356],"type":"Point"}
}