{
  "type": "Feature",
  "properties": {
    "iso:country":"CH",
    "sg:address":"Paradieslistrasse 33",
    "sg:city":"Unteriberg",
    "sg:orig_category":"Architektur U Ingenieurb\u00fcros",
    "sg:phone":"+41 55 414 52 33",
    "sg:postcode":"8842",
    "sg:province":"Schwyz",
    "wof:name":"Gyr Baudienstleistungen",
    "wof:placetype":"venue"
},
  "geometry": {"coordinates":[8.795425,47.059837],"type":"Point"}
}