{
  "type": "Feature",
  "properties": {
    "iso:country":"CH",
    "sg:address":"Dorfstrasse 12",
    "sg:city":"Belp",
    "sg:orig_category":"R\u00fcckgewinnung U Vorbereitung f\u00fcr die Wiederverwertung Recycling",
    "sg:phone":"+41 79 227 44 13",
    "sg:postcode":"3123",
    "sg:province":"Bern",
    "wof:name":"Hans B\u00f6hlen Entsorgung & Recycling",
    "wof:placetype":"venue"
},
  "geometry": {"coordinates":[7.4981122017,46.8928108215],"type":"Point"}
}