{
  "type": "Feature",
  "properties": {
    "iso:country":"CH",
    "sg:address":"Avenue De L'ariana 2",
    "sg:city":"Gen\u00e8ve",
    "sg:orig_category":"Konsulate",
    "sg:phone":"+41 22 710 72 72",
    "sg:postcode":"1202",
    "sg:province":"Gen\u00e8ve",
    "wof:name":"Consulat G\u00e9n\u00e9ral De L'etat Du Koweit",
    "wof:placetype":"venue"
},
  "geometry": {"coordinates":[6.1555218697,46.1997489929],"type":"Point"}
}