{
  "type": "Feature",
  "properties": {
    "addr:full":"Zugerstrasse 11 W\u00e4denswil Z\u00fcrich 8820",
    "addr:housenumber":"11",
    "addr:postcode":"8820",
    "addr:street":"Zugerstrasse;Zuerich",
    "iso:country":"CH",
    "sg:address":"Zugerstrasse 11",
    "sg:city":"W\u00e4denswil",
    "sg:orig_category":"Detailhandel mit Brot, Back U S\u00fcsswaren",
    "sg:phone":"+41 17801020",
    "sg:postcode":"8820",
    "sg:province":"Z\u00fcrich",
    "wof:name":"Hirschen Holzofenb\u00e4ckerei Ag",
    "wof:placetype":"venue"
},
  "geometry": {"coordinates":[8.671421,47.22958],"type":"Point"}
}