{
  "type": "Feature",
  "properties": {
    "iso:country":"CH",
    "sg:address":"B\u00fcndtenweg 24",
    "sg:city":"R\u00f6schenz",
    "sg:orig_category":"Herstellung von K\u00fcchenm\u00f6beln Innenausbau",
    "sg:phone":"+41 61 761 65 64",
    "sg:postcode":"4244",
    "sg:province":"Basel-Landschaft",
    "wof:name":"Karrer K\u00fcchen, K\u00fcchen Und Innenausbau",
    "wof:placetype":"venue"
},
  "geometry": {"coordinates":[7.4767680168,47.4228553772],"type":"Point"}
}