{
  "type": "Feature",
  "properties": {
    "iso:country":"CH",
    "sg:address":"Gloriastrasse 18",
    "sg:city":"Z\u00fcrich",
    "sg:orig_category":"Interessenvertretungen",
    "sg:phone":"+41 12524201",
    "sg:postcode":"8006",
    "sg:province":"Z\u00fcrich",
    "wof:name":"Dialog Ethik Verein F\u00fcr Interdisziplin\u00e4re Ethik",
    "wof:placetype":"venue"
},
  "geometry": {"coordinates":[8.5534095764,47.3759689331],"type":"Point"}
}