{
  "type": "Feature",
  "properties": {
    "iso:country":"CH",
    "sg:address":"Einschlagstrasse 2",
    "sg:city":"Wynau",
    "sg:orig_category":"Detailhandel mit Waren verschiedener Art in Verkaufsr\u00e4umen Fachdetailhandel mit Nahrungsmitteln, Get",
    "sg:phone":"+41 71 777 16 12",
    "sg:postcode":"4923",
    "sg:province":"Bern",
    "wof:name":"Otto's Ag",
    "wof:placetype":"venue"
},
  "geometry": {"coordinates":[9.5658607483,47.3902206421],"type":"Point"}
}