{
  "type": "Feature",
  "properties": {
    "iso:country":"CH",
    "sg:address":"Frontenex Route De 62 1207 Gen\u00e8ve Case Postale",
    "sg:city":"Gen\u00e8ve",
    "sg:orig_category":"Unternehmensberatung",
    "sg:phone":"+41 22000000",
    "sg:postcode":"1207",
    "sg:province":"Gen\u00e8ve",
    "wof:name":"Rh\u00f4ne Trust Sa",
    "wof:placetype":"venue"
},
  "geometry": {"coordinates":[6.1671380997,46.203338623],"type":"Point"}
}