{
  "type": "Feature",
  "properties": {
    "iso:country":"CH",
    "sg:address":"5036 Oberentfelden. Postfach",
    "sg:city":"Oberentfelden",
    "sg:orig_category":"Vereine Musik/Blasmusik",
    "sg:phone":"+41 62 723 19 79",
    "sg:postcode":"5036",
    "sg:province":"Aargau",
    "wof:name":"Musikgesellschaft",
    "wof:placetype":"venue"
},
  "geometry": {"coordinates":[8.0466556549,47.3560371399],"type":"Point"}
}