{
  "type": "Feature",
  "properties": {
    "iso:country":"CH",
    "sg:address":"Im B\u00f6hler 9",
    "sg:city":"Untereggen",
    "sg:classifiers":[
        {
            "category":"Wholesale",
            "subcategory":"Vending Machines",
            "type":"Manufacturing & Wholesale Goods"
        }
    ],
    "sg:phone":"+41 71 866 18 38",
    "sg:postcode":"9033",
    "sg:province":"St. Gallen",
    "sg:tags":[
        "debarking"
    ],
    "wof:name":"Silvio Kuratli Maschinenbau",
    "wof:placetype":"venue"
},
  "geometry": {"coordinates":[9.440992,47.449429],"type":"Point"}
}