{
  "type": "Feature",
  "properties": {
    "addr:full":"Dorfstrasse 62 Spreitenbach Aargau 8957",
    "addr:housenumber":"62",
    "addr:postcode":"8957",
    "addr:street":"Dorfstrasse",
    "iso:country":"CH",
    "sg:address":"Dorfstrasse 62",
    "sg:city":"Spreitenbach",
    "sg:orig_category":"Darlehenskassen U Raiffeisenbanken",
    "sg:phone":"+41 56 401 12 59",
    "sg:postcode":"8957",
    "sg:province":"Aargau",
    "wof:name":"Raiffeisenbank",
    "wof:placetype":"venue"
},
  "geometry": {"coordinates":[8.365218,47.418064],"type":"Point"}
}