{
  "type": "Feature",
  "properties": {
    "iso:country":"CH",
    "sg:address":"Montagne-du-droit",
    "sg:city":"Mont-soleil",
    "sg:classifiers":[
        {
            "category":"Travel",
            "subcategory":"Hotels & Motels",
            "type":"Entertainment"
        }
    ],
    "sg:phone":"+41 32 941 23 60",
    "sg:postcode":"2610",
    "sg:province":"Bern",
    "sg:tags":[
        "hotels",
        "mit",
        "restaurant"
    ],
    "wof:name":"Auberge De L'assesseur S\u00e0rl",
    "wof:placetype":"venue"
},
  "geometry": {"coordinates":[6.9958171844,47.1520423889],"type":"Point"}
}