{
  "type": "Feature",
  "properties": {
    "iso:country":"CH",
    "sg:address":"W\u00fclflingerstrasse 29 8400 Winterthur. Postfach",
    "sg:city":"Winterthur",
    "sg:orig_category":"Sonstiger Grosshandel",
    "sg:postcode":"8400",
    "sg:province":"Z\u00fcrich",
    "wof:name":"Strzelecki Edward Handel Und Transporte Waren; Im- U. Export, Handel",
    "wof:placetype":"venue"
},
  "geometry": {"coordinates":[8.7176904678,47.5050506592],"type":"Point"}
}