{
  "type": "Feature",
  "properties": {
    "iso:country":"CH",
    "sg:address":"Rainacherstrasse 11",
    "sg:city":"Z\u00fcrich",
    "sg:orig_category":"Interessenvertretungen U sonstige Vereinigungen",
    "sg:phone":"+41 13832152",
    "sg:postcode":"8032",
    "sg:province":"Z\u00fcrich",
    "wof:name":"Stadtz\u00fcrch.tennisvereinigung",
    "wof:placetype":"venue"
},
  "geometry": {"coordinates":[8.5605707169,47.3660354614],"type":"Point"}
}