{
  "type": "Feature",
  "properties": {
    "iso:country":"CH",
    "sg:address":"Theodorshofweg 31",
    "sg:city":"Rheinfelden",
    "sg:orig_category":"Non-Classified Establishments",
    "sg:postcode":"4310",
    "sg:province":"Aargau",
    "wof:name":"Bischof Management Gmbh",
    "wof:placetype":"venue"
},
  "geometry": {"coordinates":[7.8048028946,47.5625648499],"type":"Point"}
}