{
  "type": "Feature",
  "properties": {
    "iso:country":"CH",
    "sg:address":"Lyssachstrasse 17 3400 Burgdorf. Postfach",
    "sg:city":"Burgdorf",
    "sg:orig_category":"Versicherungen Hauptagenturen",
    "sg:phone":"+41 34 420 75 75",
    "sg:postcode":"3401",
    "sg:province":"Bern",
    "wof:name":"Waadt-versicherungen Hauptagentur",
    "wof:placetype":"venue"
},
  "geometry": {"coordinates":[7.6226730347,47.0586967468],"type":"Point"}
}