{
  "type": "Feature",
  "properties": {
    "iso:country":"CH",
    "sg:address":"T\u00e4gernaustrasse 153",
    "sg:city":"Jona",
    "sg:orig_category":"Malerei-Gipserei Parkettleger",
    "sg:postcode":"8645",
    "sg:province":"St. Gallen",
    "wof:name":"Josef Gubelmann Bodenbel\u00e4ge",
    "wof:placetype":"venue"
},
  "geometry": {"coordinates":[8.8474197388,47.2354316711],"type":"Point"}
}