{
  "type": "Feature",
  "properties": {
    "iso:country":"CH",
    "sg:address":"Steinmatt",
    "sg:city":"Willisau",
    "sg:orig_category":"Unclassifiable Establishments",
    "sg:phone":"+41 41 970 20 02",
    "sg:postcode":"6130",
    "sg:province":"Luzern",
    "wof:name":"Betonelemente J. Schmidiger",
    "wof:placetype":"venue"
},
  "geometry": {"coordinates":[7.9928841591,47.1222229004],"type":"Point"}
}