{
  "type": "Feature",
  "properties": {
    "iso:country":"CH",
    "sg:address":"Rosenweg 2802",
    "sg:city":"Sennwald",
    "sg:orig_category":"Detektivb\u00fcros U \u00dcberwachung",
    "sg:postcode":"9466",
    "sg:province":"St. Gallen",
    "wof:name":"Security-jussel Bewachungen",
    "wof:placetype":"venue"
},
  "geometry": {"coordinates":[9.4904432297,47.2532424927],"type":"Point"}
}