{
  "type": "Feature",
  "properties": {
    "iso:country":"CH",
    "sg:address":"Lindenhof",
    "sg:city":"G\u00fcttingen",
    "sg:orig_category":"Sportvereine Turnen Vereine Damen",
    "sg:phone":"+41 52 242 03 19",
    "sg:postcode":"8594",
    "sg:province":"Thurgau",
    "wof:name":"Damenriege Hegi",
    "wof:placetype":"venue"
},
  "geometry": {"coordinates":[8.7708511353,47.5054740906],"type":"Point"}
}