{
  "type": "Feature",
  "properties": {
    "iso:country":"CH",
    "sg:address":"Rte Verdel 6",
    "sg:city":"Bulle",
    "sg:classifiers":[
        {
            "category":"Manufacturing",
            "subcategory":"Metals",
            "type":"Manufacturing & Wholesale Goods"
        }
    ],
    "sg:phone":"+41 26 913 95 15",
    "sg:postcode":"1630",
    "sg:province":"Fribourg",
    "sg:tags":[
        "metallurgy",
        "metalworking",
        "processing"
    ],
    "wof:name":"Px Usiprosil Sa",
    "wof:placetype":"venue"
},
  "geometry": {"coordinates":[7.0662851334,46.623664856],"type":"Point"}
}