{
  "type": "Feature",
  "properties": {
    "addr:full":"Poststrasse 11 Richterswil Z\u00fcrich 8805",
    "addr:housenumber":"11",
    "addr:postcode":"8805",
    "addr:street":"Poststrasse",
    "iso:country":"CH",
    "sg:address":"Poststrasse 11",
    "sg:city":"Richterswil",
    "sg:orig_category":"Detailhandel mit Bekleidung Detailhandel mit Herrenbekleidung",
    "sg:phone":"+41 17846020",
    "sg:postcode":"8805",
    "sg:province":"Z\u00fcrich",
    "wof:name":"Hans Wyler, Herren-bekleidung",
    "wof:placetype":"venue"
},
  "geometry": {"coordinates":[8.706323,47.208328],"type":"Point"}
}