{
  "type": "Feature",
  "properties": {
    "iso:country":"CH",
    "sg:address":"Zehntenhausstrasse 19",
    "sg:city":"Z\u00fcrich",
    "sg:classifiers":[
        {
            "category":"Home & Garden",
            "subcategory":"Building Materials",
            "type":"Retail Goods"
        }
    ],
    "sg:phone":"+41 13777777",
    "sg:postcode":"8046",
    "sg:province":"Z\u00fcrich",
    "sg:tags":[
        "installation",
        "electric"
    ],
    "wof:name":"R. Meuli Elektro Ag",
    "wof:placetype":"venue"
},
  "geometry": {"coordinates":[8.5068922043,47.4206314087],"type":"Point"}
}