{
  "type": "Feature",
  "properties": {
    "iso:country":"CH",
    "sg:address":"Forelstrasse 42",
    "sg:city":"Ostermundigen",
    "sg:orig_category":"Kunsthandel",
    "sg:phone":"+41 31 931 26 72",
    "sg:postcode":"3072",
    "sg:province":"Bern",
    "wof:name":"Hilda Leuenberger Atelier & Galerie",
    "wof:placetype":"venue"
},
  "geometry": {"coordinates":[7.4851121902,46.9604301453],"type":"Point"}
}