{
  "type": "Feature",
  "properties": {
    "iso:country":"CH",
    "sg:address":"Ancienne Poste",
    "sg:city":"Crans-sur-sierre",
    "sg:orig_category":"Vermietung U Verpachtung von eigenen Immobilien Vermittlung von Immobilien",
    "sg:phone":"+41 81 833 69 06",
    "sg:postcode":"3963",
    "sg:province":"Valais",
    "wof:name":"Adelheid Ag Silvaplana Immobiliengesellschaft",
    "wof:placetype":"venue"
},
  "geometry": {"coordinates":[9.8329877853,46.4877738953],"type":"Point"}
}