{
  "type": "Feature",
  "properties": {
    "addr:full":"Unterstrasse 4 Herzogenbuchsee Bern 3360",
    "addr:housenumber":"4",
    "addr:postcode":"3360",
    "addr:street":"Unterstrasse;Bern",
    "iso:country":"CH",
    "sg:address":"Unterstrasse 4",
    "sg:city":"Herzogenbuchsee",
    "sg:classifiers":[
        {
            "category":"Bars & Pubs",
            "type":"Food & Drink"
        }
    ],
    "sg:phone":"+41 62 961 04 98",
    "sg:postcode":"3360",
    "sg:province":"Bern",
    "wof:name":"Bar Treffpunkt",
    "wof:placetype":"venue"
},
  "geometry": {"coordinates":[7.702808,47.188187],"type":"Point"}
}