{
  "type": "Feature",
  "properties": {
    "iso:country":"CH",
    "sg:address":"Moosmatthalde 21",
    "sg:city":"Meggen",
    "sg:orig_category":"Kinesiologie",
    "sg:phone":"+41 41 377 41 68",
    "sg:postcode":"6045",
    "sg:province":"Luzern",
    "wof:name":"Marisa Janser Kinesiologie",
    "wof:placetype":"venue"
},
  "geometry": {"coordinates":[8.3641242981,47.0422897339],"type":"Point"}
}