{
  "type": "Feature",
  "properties": {
    "iso:country":"CH",
    "sg:address":"Schachenstrasse 35b",
    "sg:city":"Wolfhausen",
    "sg:orig_category":"Innenausbau Zimmerei, Ingenieurholzbau",
    "sg:phone":"+41 55 263 13 92",
    "sg:postcode":"8633",
    "sg:province":"Z\u00fcrich",
    "wof:name":"Werner D\u00e4ndliker Zimmerei Innenausbau",
    "wof:placetype":"venue"
},
  "geometry": {"coordinates":[8.7959260941,47.2540092468],"type":"Point"}
}