{
  "type": "Feature",
  "properties": {
    "iso:country":"CH",
    "sg:address":"Ischlagweg 15",
    "sg:city":"Reigoldswil",
    "sg:orig_category":"Interessenvertretungen",
    "sg:postcode":"4418",
    "sg:province":"Basel-Landschaft",
    "wof:name":"Dettwiler-stiftung Erwin Und Anna",
    "wof:placetype":"venue"
},
  "geometry": {"coordinates":[7.6852278709,47.3978538513],"type":"Point"}
}