{
  "type": "Feature",
  "properties": {
    "iso:country":"CH",
    "sg:address":"Rue De La Servette 1",
    "sg:city":"Gen\u00e8ve",
    "sg:orig_category":"Detailhandel mit Spielwaren",
    "sg:phone":"+41 22 734 25 76",
    "sg:postcode":"1201",
    "sg:province":"Gen\u00e8ve",
    "wof:name":"Henri Zwicky Jouets Au Vieux Paris",
    "wof:placetype":"venue"
},
  "geometry": {"coordinates":[6.1397461891,46.2089157104],"type":"Point"}
}