{
  "type": "Feature",
  "properties": {
    "iso:country":"CH",
    "sg:address":"H\u00e9rens Rue Du Val D'",
    "sg:city":"Vex",
    "sg:orig_category":"RESTAURANTS: TEA-ROOMS",
    "sg:phone":"+41 24 471 37 06",
    "sg:postcode":"1981",
    "sg:province":"Valais",
    "wof:name":"Guerlavais Daniel Et Anita",
    "wof:placetype":"venue"
},
  "geometry": {"coordinates":[7.3954100609,46.2054786682],"type":"Point"}
}