{
  "type": "Feature",
  "properties": {
    "iso:country":"CH",
    "sg:address":"Piller Route Andr\u00e9 33g 1762 Givisiez Case Postale",
    "sg:city":"Givisiez",
    "sg:orig_category":"Herstellung von Maschinen f\u00fcr die Nahrungsmittel, Getr\u00e4nkeherstellung U die Tabakverarbeitung",
    "sg:phone":"+41 26 466 81 26",
    "sg:postcode":"1762",
    "sg:province":"Fribourg",
    "wof:name":"Romeco 2000 Sa",
    "wof:placetype":"venue"
},
  "geometry": {"coordinates":[7.117128849,46.811794281],"type":"Point"}
}