{
  "type": "Feature",
  "properties": {
    "iso:country":"CH",
    "sg:address":"Muristrasse 41",
    "sg:city":"Bern",
    "sg:orig_category":"Gartenbau",
    "sg:phone":"+41 79 647 59 85",
    "sg:postcode":"3006",
    "sg:province":"Bern",
    "wof:name":"Horst Meyer Gartenunterhalt",
    "wof:placetype":"venue"
},
  "geometry": {"coordinates":[8.100235939,47.5395355225],"type":"Point"}
}