{
  "type": "Feature",
  "properties": {
    "iso:country":"CH",
    "sg:address":"Unterdorf 21",
    "sg:city":"N\u00e4fels",
    "sg:orig_category":"M\u00f6belveredelung U restaurierung",
    "sg:phone":"+41 55 612 41 69",
    "sg:postcode":"8752",
    "sg:province":"Glarus",
    "wof:name":"Severin Kinkelin Antikschreinerei",
    "wof:placetype":"venue"
},
  "geometry": {"coordinates":[9.0632047653,47.1022377014],"type":"Point"}
}