{
  "type": "Feature",
  "properties": {
    "iso:country":"CH",
    "sg:address":"Weissensteinstrasse 20",
    "sg:city":"Wolfwil",
    "sg:classifiers":[
        {
            "category":"Insurance",
            "subcategory":"Insurance Agent",
            "type":"Services"
        }
    ],
    "sg:phone":"+41 41 670 13 56",
    "sg:postcode":"4628",
    "sg:province":"Solothurn",
    "sg:tags":[
        "versicherungsagenturen",
        "-broker"
    ],
    "wof:name":"Karl Langensand Versicherungen",
    "wof:placetype":"venue"
},
  "geometry": {"coordinates":[8.2635192871,46.9350128174],"type":"Point"}
}