{
  "type": "Feature",
  "properties": {
    "iso:country":"CH",
    "sg:address":"Reussstrasse 17",
    "sg:city":"Gisikon",
    "sg:orig_category":"Detailhandel mit Uhren U Schmuck Fachdetailhandel in Verkaufsr\u00e4umen",
    "sg:phone":"+41 41 429 15 15",
    "sg:postcode":"6038",
    "sg:province":"Luzern",
    "wof:name":"G\u00fcbelin Ag",
    "wof:placetype":"venue"
},
  "geometry": {"coordinates":[9.8397750854,46.497215271],"type":"Point"}
}