{
  "type": "Feature",
  "properties": {
    "iso:country":"CH",
    "sg:address":"Rigiweg 13",
    "sg:city":"Arth",
    "sg:orig_category":"Architektur U Ingenieurb\u00fcros",
    "sg:phone":"+41 41 855 20 80",
    "sg:postcode":"6415",
    "sg:province":"Schwyz",
    "wof:name":"Hsk Ingenieur Ag K\u00fcssnacht, Zweigniederlassung Arth",
    "wof:placetype":"venue"
},
  "geometry": {"coordinates":[8.521846,47.061436],"type":"Point"}
}