{
  "type": "Feature",
  "properties": {
    "iso:country":"CH",
    "sg:address":"Neugasse 16",
    "sg:city":"Zug",
    "sg:classifiers":[
        {
            "category":"Restaurant",
            "type":"Food & Drink"
        }
    ],
    "sg:phone":"+41 41 711 09 60",
    "sg:postcode":"6300",
    "sg:province":"Zug",
    "wof:name":"Caf\u00e9-restaurant Ritz",
    "wof:placetype":"venue"
},
  "geometry": {"coordinates":[8.515378952,47.1668891907],"type":"Point"}
}