{
  "type": "Feature",
  "properties": {
    "iso:country":"CH",
    "sg:address":"Obere Jungfraustrasse 52 3800 Interlaken. Postfach 338",
    "sg:city":"Interlaken",
    "sg:orig_category":"Reiseb\u00fcros U Reiseveranstalter",
    "sg:phone":"+41 33 822 17 33",
    "sg:postcode":"3800",
    "sg:province":"Bern",
    "wof:name":"Rtw Round The World Travel & Touristik Gmbh",
    "wof:placetype":"venue"
},
  "geometry": {"coordinates":[7.8579058647,46.6836891174],"type":"Point"}
}