{
  "type": "Feature",
  "properties": {
    "iso:country":"CH",
    "sg:address":"Centralstrasse 29",
    "sg:city":"Grenchen",
    "sg:orig_category":"Detailhandel mit Fleisch U Fleischwaren",
    "sg:phone":"+41 32 652 17 31",
    "sg:postcode":"2540",
    "sg:province":"Solothurn",
    "wof:name":"Guex-t\u00fcscher Roland",
    "wof:placetype":"venue"
},
  "geometry": {"coordinates":[7.3952240944,47.1940574646],"type":"Point"}
}