{
  "type": "Feature",
  "properties": {
    "iso:country":"CH",
    "sg:address":"Haus Domino B",
    "sg:city":"Susten",
    "sg:orig_category":"Organisationen der Wohlfahrtspflege",
    "sg:phone":"+41 31 972 40 30",
    "sg:postcode":"3952",
    "sg:province":"Valais",
    "wof:name":"Pro Senectute Bern-land",
    "wof:placetype":"venue"
},
  "geometry": {"coordinates":[7.4350328445,46.9247398376],"type":"Point"}
}