{
  "type": "Feature",
  "properties": {
    "iso:country":"CH",
    "sg:address":"Lehmattstrasse 187",
    "sg:city":"Zeglingen",
    "sg:orig_category":"Herstellung von sonstigen landwirtschaftlichen Maschinen",
    "sg:phone":"+41 32 381 10 88",
    "sg:postcode":"4495",
    "sg:province":"Basel-Landschaft",
    "wof:name":"Nikles Walter Ag",
    "wof:placetype":"venue"
},
  "geometry": {"coordinates":[7.2438988686,47.0813140869],"type":"Point"}
}