{
  "type": "Feature",
  "properties": {
    "iso:country":"CH",
    "sg:address":"Weidgasse 10",
    "sg:city":"Bern",
    "sg:orig_category":"Malerei",
    "sg:phone":"+41 31 992 01 18",
    "sg:postcode":"3018",
    "sg:province":"Bern",
    "wof:name":"Heinz Kl\u00e4y Malergesch\u00e4ft",
    "wof:placetype":"venue"
},
  "geometry": {"coordinates":[7.3900737762,46.935546875],"type":"Point"}
}