{
  "type": "Feature",
  "properties": {
    "iso:country":"CH",
    "sg:address":"Rue Du Simplon 25",
    "sg:city":"Lausanne",
    "sg:orig_category":"Architekturb\u00fcros",
    "sg:phone":"+41 26 652 40 75",
    "sg:postcode":"1006",
    "sg:province":"Vaud",
    "wof:name":"Achille Deillon Bureau D'architecture",
    "wof:placetype":"venue"
},
  "geometry": {"coordinates":[6.916774,46.692211],"type":"Point"}
}