{
  "type": "Feature",
  "properties": {
    "iso:country":"CH",
    "sg:address":"Zugerstrasse 60",
    "sg:city":"Baar",
    "sg:orig_category":"Tankstellen",
    "sg:phone":"+41 41 761 93 46",
    "sg:postcode":"6340",
    "sg:province":"Zug",
    "wof:name":"Bp Service Baar Brander H.-p.",
    "wof:placetype":"venue"
},
  "geometry": {"coordinates":[8.5202970505,47.1851806641],"type":"Point"}
}