{
  "type": "Feature",
  "properties": {
    "iso:country":"CH",
    "sg:address":"Barf\u00fcsserplatz 17",
    "sg:city":"Basel",
    "sg:orig_category":"Unclassifiable Establishments",
    "sg:postcode":"4051",
    "sg:province":"Basel-Stadt",
    "wof:name":"El Qirinawi & Cie. - Trockenblumen",
    "wof:placetype":"venue"
},
  "geometry": {"coordinates":[7.5886287689,47.5547065735],"type":"Point"}
}