{
  "type": "Feature",
  "properties": {
    "iso:country":"CH",
    "sg:address":"Kirchbergstrasse 211 3400 Burgdorf. Postfach 704",
    "sg:city":"Burgdorf",
    "sg:orig_category":"Non-Classified Establishments",
    "sg:phone":"+41 34 426 70 71",
    "sg:postcode":"3400",
    "sg:province":"Bern",
    "wof:name":"Alimarca Holding Ag",
    "wof:placetype":"venue"
},
  "geometry": {"coordinates":[7.6045489311,47.067325592],"type":"Point"}
}