{
  "type": "Feature",
  "properties": {
    "iso:country":"CH",
    "sg:address":"6182 Escholzmatt. Postfach 55",
    "sg:city":"Escholzmatt",
    "sg:orig_category":"Sportvereine Ballsport Fussball",
    "sg:phone":"+41 21 981 21 21",
    "sg:postcode":"6182",
    "sg:province":"Luzern",
    "wof:name":"Fc Espagnol-montreux",
    "wof:placetype":"venue"
},
  "geometry": {"coordinates":[6.9105000496,46.4316902161],"type":"Point"}
}