{
  "type": "Feature",
  "properties": {
    "iso:country":"CH",
    "sg:address":"Chemin Dent-d'oche 1",
    "sg:city":"Morges",
    "sg:classifiers":[
        {
            "category":"Professional",
            "subcategory":"Employment Agencies",
            "type":"Services"
        }
    ],
    "sg:phone":"+41 21 802 39 84",
    "sg:postcode":"1110",
    "sg:province":"Vaud",
    "sg:tags":[
        "personal",
        "u",
        "stellenvermittlung"
    ],
    "wof:name":"Place-lab Martine Pahud Placement De Laborantines",
    "wof:placetype":"venue"
},
  "geometry": {"coordinates":[6.5017781258,46.5221786499],"type":"Point"}
}