{
  "type": "Feature",
  "properties": {
    "iso:country":"CH",
    "sg:address":"Rue Pr\u00e9-landry 20 2017 Boudry. Postfach",
    "sg:city":"Boudry",
    "sg:orig_category":"Architektur U Ingenieurb\u00fcros Grosshandel mit elektrischen Haushaltsger\u00e4ten, Radio U Fernsehger\u00e4ten",
    "sg:phone":"+41 32 843 47 10",
    "sg:postcode":"2017",
    "sg:province":"Neuch\u00e2tel",
    "wof:name":"Sysa Engineering Sa Produits \u00e9lectriques, \u00e9lectroniques, Technique Solaire; \u00e9laboration, Fabrication, Repr\u00e9s. Etc",
    "wof:placetype":"venue"
},
  "geometry": {"coordinates":[6.8405,46.951195],"type":"Point"}
}