{
  "type": "Feature",
  "properties": {
    "iso:country":"CH",
    "sg:address":"Route Des Alpes",
    "sg:city":"Pampigny",
    "sg:orig_category":"Mechanische Werkst\u00e4tten",
    "sg:phone":"+41 21 800 33 93",
    "sg:postcode":"1142",
    "sg:province":"Vaud",
    "wof:name":"Roger Baumgartner Atelier M\u00e9canique",
    "wof:placetype":"venue"
},
  "geometry": {"coordinates":[6.4331898689,46.5737304688],"type":"Point"}
}