{
  "type": "Feature",
  "properties": {
    "iso:country":"CH",
    "sg:address":"Aegertstrasse 11",
    "sg:city":"Dietlikon",
    "sg:orig_category":"Herstellung von Metallerzeugnissen ohne Maschinenbau Maschinenbau",
    "sg:phone":"+41 18332822",
    "sg:postcode":"8305",
    "sg:province":"Z\u00fcrich",
    "wof:name":"Seda Gebr.freund Maschinenfabrikation",
    "wof:placetype":"venue"
},
  "geometry": {"coordinates":[8.627497673,47.4120445251],"type":"Point"}
}