{
  "type": "Feature",
  "properties": {
    "iso:country":"CH",
    "sg:address":"Flurweg 11",
    "sg:city":"Emmenbr\u00fccke",
    "sg:orig_category":"Allgemeiner Hoch U Tiefbau ohne ausgepr\u00e4gten Schwerpunkt",
    "sg:phone":"+41 41 288 91 63",
    "sg:postcode":"6020",
    "sg:province":"Luzern",
    "wof:name":"Kant.strasseninspektorat",
    "wof:placetype":"venue"
},
  "geometry": {"coordinates":[8.270245,47.082745],"type":"Point"}
}