{
  "type": "Feature",
  "properties": {
    "iso:country":"CH",
    "sg:address":"Oberruntigen",
    "sg:city":"Detligen",
    "sg:orig_category":"Herstellung von Mess U Kontrollinstrumenten U vorrichtungen",
    "sg:phone":"+41 32 652 38 09",
    "sg:postcode":"3036",
    "sg:province":"Bern",
    "wof:name":"R\u00fcfli, E.",
    "wof:placetype":"venue"
},
  "geometry": {"coordinates":[7.3610811234,47.181892395],"type":"Point"}
}