{
  "type": "Feature",
  "properties": {
    "iso:country":"CH",
    "sg:address":"Dornacherstrasse 307",
    "sg:city":"Basel",
    "sg:orig_category":"Dachdeckerei Zimmerei, Dachdeckerei, Bauspenglerei U Abdichtung",
    "sg:postcode":"4053",
    "sg:province":"Basel-Stadt",
    "wof:name":"Fritz D\u00e4llenbach",
    "wof:placetype":"venue"
},
  "geometry": {"coordinates":[7.60094,47.53973],"type":"Point"}
}