{
  "type": "Feature",
  "properties": {
    "iso:country":"CH",
    "sg:address":"Bucheggstrasse 122",
    "sg:city":"Z\u00fcrich",
    "sg:orig_category":"Erschliessung von Grundst\u00fccken",
    "sg:phone":"+41 13628558",
    "sg:postcode":"8057",
    "sg:province":"Z\u00fcrich",
    "wof:name":"Gemeinn\u00fctzige Baugenossenschaft Wiedinghof Z\u00fcrich",
    "wof:placetype":"venue"
},
  "geometry": {"coordinates":[8.537730217,47.3981781006],"type":"Point"}
}