{
  "type": "Feature",
  "properties": {
    "iso:country":"CH",
    "sg:address":"Lochgasse 12",
    "sg:city":"L\u00fcsslingen",
    "sg:orig_category":"Sonstige mit Sport verbundene T\u00e4tigkeiten",
    "sg:phone":"+41 32 622 77 39",
    "sg:postcode":"4574",
    "sg:province":"Solothurn",
    "wof:name":"Agaso Kohler",
    "wof:placetype":"venue"
},
  "geometry": {"coordinates":[7.5032219887,47.1929206848],"type":"Point"}
}