{
  "type": "Feature",
  "properties": {
    "iso:country":"CH",
    "sg:address":"Hegenheimerstrasse 311",
    "sg:city":"Basel",
    "sg:orig_category":"Gewinnung von Kies U Sand Herstellung von Betonerzeugnissen f\u00fcr den Bau",
    "sg:phone":"+41 61 481 10 13",
    "sg:postcode":"4055",
    "sg:province":"Basel-Stadt",
    "wof:name":"Kies Ag Basel",
    "wof:placetype":"venue"
},
  "geometry": {"coordinates":[7.5579648018,47.5651245117],"type":"Point"}
}