{
  "type": "Feature",
  "properties": {
    "iso:country":"CH",
    "sg:address":"Via Somplaz 70/julierhof 7512 Champf\u00e8r. Postfach",
    "sg:city":"Champf\u00e8r",
    "sg:orig_category":"Kauf U Verkauf von Immobilien auf eigene Rechnung",
    "sg:phone":"+41 81 834 92 22",
    "sg:postcode":"7512",
    "sg:province":"Graubunden",
    "wof:name":"Intercity Engiadina",
    "wof:placetype":"venue"
},
  "geometry": {"coordinates":[9.8110704422,46.4780006409],"type":"Point"}
}