{
  "type": "Feature",
  "properties": {
    "addr:full":"Ringstrasse Stelz 15 Wil St. Gallen 9500",
    "addr:housenumber":"15;st.",
    "addr:postcode":"9500",
    "addr:street":"Ringstrasse Stelz;Wil",
    "iso:country":"CH",
    "sg:address":"Ringstrasse Stelz 15",
    "sg:city":"Wil",
    "sg:classifiers":[
        {
            "category":"Home & Garden",
            "subcategory":"Building Materials",
            "type":"Retail Goods"
        }
    ],
    "sg:phone":"+41 71 929 59 69",
    "sg:postcode":"9500",
    "sg:province":"St. Gallen",
    "sg:tags":[
        "rebuilding",
        "chimney"
    ],
    "wof:name":"H. Schlegel Ag",
    "wof:placetype":"venue"
},
  "geometry": {"coordinates":[9.05087,47.466225],"type":"Point"}
}