{
  "type": "Feature",
  "properties": {
    "iso:country":"CH",
    "sg:address":"Althardstrasse 120",
    "sg:city":"Regensdorf",
    "sg:orig_category":"Sonstiger Grosshandel",
    "sg:phone":"+41 18702480",
    "sg:postcode":"8105",
    "sg:province":"Z\u00fcrich",
    "wof:name":"Levincha Gmbh",
    "wof:placetype":"venue"
},
  "geometry": {"coordinates":[8.4684877396,47.4397544861],"type":"Point"}
}