{
  "type": "Feature",
  "properties": {
    "iso:country":"CH",
    "sg:address":"Nollenstrasse 1d",
    "sg:city":"Appenzell",
    "sg:orig_category":"Bau von Strassen, Sportanlagen U Bahnverkehrsstrecken",
    "sg:phone":"+41 71 787 48 12",
    "sg:postcode":"9050",
    "sg:province":"Appenzell Innerhoden",
    "wof:name":"Albert K\u00f6ppel Ag, Zweigniederlassung In Appenzell",
    "wof:placetype":"venue"
},
  "geometry": {"coordinates":[9.415851,47.324551],"type":"Point"}
}