{
  "type": "Feature",
  "properties": {
    "addr:full":"M\u00fchlenplatz 2 6004 Luzern. Postfach Luzern Luzern 6003",
    "addr:housenumber":"2",
    "addr:postcode":"6004;postfach;6003",
    "addr:street":"Muehlenplatz",
    "iso:country":"CH",
    "sg:address":"M\u00fchlenplatz 2 6004 Luzern. Postfach",
    "sg:city":"Luzern",
    "sg:orig_category":"Pensionskassen",
    "sg:phone":"+41 41 410 25 51",
    "sg:postcode":"6003",
    "sg:province":"Luzern",
    "wof:name":"Personalf\u00fcrsorgestiftung Der Fa. Buchwalder-linder Ag Luzern",
    "wof:placetype":"venue"
},
  "geometry": {"coordinates":[8.303514,47.051876],"type":"Point"}
}