{
  "type": "Feature",
  "properties": {
    "iso:country":"CH",
    "sg:address":"Alte Dorfemerstrasse 10",
    "sg:city":"Henggart",
    "sg:orig_category":"Arztpraxen",
    "sg:phone":"+41 52 316 23 23",
    "sg:postcode":"8444",
    "sg:province":"Z\u00fcrich",
    "wof:name":"Dres Med. H.-r. & K. Etter Aerzte F\u00fcr Allg.medizin Fmh",
    "wof:placetype":"venue"
},
  "geometry": {"coordinates":[8.681086,47.563847],"type":"Point"}
}