{
  "type": "Feature",
  "properties": {
    "iso:country":"CH",
    "sg:address":"Hermannswisstr. 9",
    "sg:city":"Widnau",
    "sg:orig_category":"Herstellung von Metallerzeugnissen ohne Maschinenbau Maschinenbau",
    "sg:phone":"+41 71 722 72 63",
    "sg:postcode":"9443",
    "sg:province":"St. Gallen",
    "wof:name":"G\u00e4chter Ag",
    "wof:placetype":"venue"
},
  "geometry": {"coordinates":[9.6376953125,47.4132957458],"type":"Point"}
}