{
  "type": "Feature",
  "properties": {
    "iso:country":"CH",
    "sg:address":"Chemin De La Blanche 6",
    "sg:city":"Ch\u00eane-bourg",
    "sg:orig_category":"Softwareentwicklung U beratung",
    "sg:postcode":"1225",
    "sg:province":"Gen\u00e8ve",
    "wof:name":"Denkzone Gmbh",
    "wof:placetype":"venue"
},
  "geometry": {"coordinates":[7.414276123,46.9228744507],"type":"Point"}
}