{
  "type": "Feature",
  "properties": {
    "iso:country":"CH",
    "sg:address":"Chemin De Rennier 4",
    "sg:city":"Pully",
    "sg:orig_category":"Arztpraxen",
    "sg:phone":"+41 21 711 22 01",
    "sg:postcode":"1009",
    "sg:province":"Vaud",
    "wof:name":"Dr M\u00e9d. Isabelle De Lorme M\u00e9decin Sp\u00e9cialiste Fmh",
    "wof:placetype":"venue"
},
  "geometry": {"coordinates":[6.664053,46.51358],"type":"Point"}
}