{
  "type": "Feature",
  "properties": {
    "iso:country":"CH",
    "sg:address":"H\u00fcttenberg",
    "sg:city":"Braunwald",
    "sg:orig_category":"Sonstige mit Sport verbundene T\u00e4tigkeiten",
    "sg:postcode":"8784",
    "sg:province":"Glarus",
    "wof:name":"Genossenschaft Schweizer Skischule Und Schweizer Snowboardschule Braunwald",
    "wof:placetype":"venue"
},
  "geometry": {"coordinates":[8.9896039963,46.9373626709],"type":"Point"}
}