{
  "type": "Feature",
  "properties": {
    "iso:country":"CH",
    "sg:address":"Rue Du Seyon 15",
    "sg:city":"Neuch\u00e2tel",
    "sg:orig_category":"Unclassifiable Establishments",
    "sg:postcode":"2000",
    "sg:province":"Neuch\u00e2tel",
    "wof:name":"Jeanne Lampert Naturopathe",
    "wof:placetype":"venue"
},
  "geometry": {"coordinates":[6.9281058311,46.9927597046],"type":"Point"}
}