{
  "type": "Feature",
  "properties": {
    "iso:country":"CH",
    "sg:address":"Industriestrasse 26",
    "sg:city":"Wittenbach",
    "sg:orig_category":"Instandhaltung U Reparatur von Automobilen",
    "sg:phone":"+41 19912127",
    "sg:postcode":"9303",
    "wof:name":"Getcar Ag",
    "wof:placetype":"venue"
},
  "geometry": {"coordinates":[8.5984249115,47.323059082],"type":"Point"}
}