{
  "type": "Feature",
  "properties": {
    "iso:country":"CH",
    "sg:address":"Rue Du Beulet 7-9",
    "sg:city":"Gen\u00e8ve",
    "sg:orig_category":"W\u00e4scherei U chemische Reinigung",
    "sg:postcode":"1203",
    "sg:province":"Gen\u00e8ve",
    "wof:name":"Sie Und Er Chemische Reinigung",
    "wof:placetype":"venue"
},
  "geometry": {"coordinates":[17.6500301361,43.0537185669],"type":"Point"}
}