{
  "type": "Feature",
  "properties": {
    "addr:full":"Sch\u00fctzenstrasse 5 Derendingen Solothurn 4552",
    "addr:housenumber":"5",
    "addr:postcode":"4552",
    "addr:street":"Schuetzenstrasse",
    "iso:country":"CH",
    "sg:address":"Sch\u00fctzenstrasse 5",
    "sg:city":"Derendingen",
    "sg:classifiers":[
        {
            "category":"Education",
            "subcategory":"Library",
            "type":"Public Place"
        }
    ],
    "sg:phone":"+41 32 682 20 85",
    "sg:postcode":"4552",
    "sg:province":"Solothurn",
    "sg:tags":[
        "u",
        "bibliotheken",
        "archive"
    ],
    "wof:name":"Reformierte Pfarrbibliothek",
    "wof:placetype":"venue"
},
  "geometry": {"coordinates":[7.584371,47.194229],"type":"Point"}
}