{
  "type": "Feature",
  "properties": {
    "iso:country":"CH",
    "sg:address":"Landhausweg 27",
    "sg:city":"Bern",
    "sg:orig_category":"Fahrschulen, Flugschulen",
    "sg:phone":"+41 31 372 59 59",
    "sg:postcode":"3007",
    "sg:province":"Bern",
    "wof:name":"Franz Furrer Autofahrschule",
    "wof:placetype":"venue"
},
  "geometry": {"coordinates":[7.4324808121,46.9355697632],"type":"Point"}
}