{
  "type": "Feature",
  "properties": {
    "iso:country":"CH",
    "sg:address":"Hubertus 1",
    "sg:city":"Gr\u00fcsch",
    "sg:orig_category":"Sportvereine Eissport Eishockey",
    "sg:phone":"+41 81 325 12 34",
    "sg:postcode":"7214",
    "sg:province":"Graubunden",
    "wof:name":"Eishockey-club Gr\u00fcsch-danusa",
    "wof:placetype":"venue"
},
  "geometry": {"coordinates":[9.6467075348,46.9807434082],"type":"Point"}
}