{
  "type": "Feature",
  "properties": {
    "iso:country":"CH",
    "sg:address":"Sentiero Dei Castagni 3",
    "sg:city":"Viganello",
    "sg:orig_category":"Vermittlung von Immobilien",
    "sg:phone":"+41 91 972 72 40",
    "sg:postcode":"6962",
    "sg:province":"Ticino",
    "wof:name":"Ab Aldo Balestra Ufficio Fiduciario",
    "wof:placetype":"venue"
},
  "geometry": {"coordinates":[8.9749660492,46.0138626099],"type":"Point"}
}