{
  "type": "Feature",
  "properties": {
    "iso:country":"CH",
    "sg:address":"Thiolleyres Rue De La 3",
    "sg:city":"Estavayer-le-lac",
    "sg:orig_category":"Herstellung von sonstigen landwirtschaftlichen Maschinen",
    "sg:postcode":"1470",
    "sg:province":"Fribourg",
    "wof:name":"F. Et K. Tours, Koleski Mile",
    "wof:placetype":"venue"
},
  "geometry": {"coordinates":[6.8449778557,46.8493156433],"type":"Point"}
}