{
  "type": "Feature",
  "properties": {
    "iso:country":"CH",
    "sg:address":"Karmaad",
    "sg:city":"Gams",
    "sg:orig_category":"Herstellung von sonstigen Metallwaren",
    "sg:postcode":"9473",
    "sg:province":"St. Gallen",
    "wof:name":"Karoblech Gmbh",
    "wof:placetype":"venue"
},
  "geometry": {"coordinates":[9.4550199509,47.2044906616],"type":"Point"}
}