{
  "type": "Feature",
  "properties": {
    "iso:country":"CH",
    "sg:address":"Langr\u00fctistrasse 33",
    "sg:city":"Einsiedeln",
    "sg:classifiers":[
        {
            "category":"Communications",
            "subcategory":"Film & Video Production",
            "type":"Services"
        }
    ],
    "sg:phone":"+41 55 412 79 73",
    "sg:postcode":"8840",
    "sg:province":"Schwyz",
    "sg:tags":[
        "videofilmherstellung",
        "u"
    ],
    "wof:name":"Franz K\u00e4lin Filmproduktion",
    "wof:placetype":"venue"
},
  "geometry": {"coordinates":[8.7434558868,47.1246376038],"type":"Point"}
}