{
  "type": "Feature",
  "properties": {
    "iso:country":"CH",
    "sg:address":"1586",
    "sg:city":"Vallamand",
    "sg:classifiers":[
        {
            "category":"Travel",
            "subcategory":"Hotels & Motels",
            "type":"Entertainment"
        }
    ],
    "sg:phone":"+41 26 677 45 77",
    "sg:postcode":"1586",
    "sg:province":"Vaud",
    "sg:tags":[
        "hotels",
        "mit",
        "restaurant"
    ],
    "wof:name":"H\u00f4tel La R\u00e9sidence",
    "wof:placetype":"venue"
},
  "geometry": {"coordinates":[7.0417699814,46.929599762],"type":"Point"}
}