{
  "type": "Feature",
  "properties": {
    "iso:country":"CH",
    "sg:address":"Bahnhofstrasse 42",
    "sg:city":"Flums",
    "sg:orig_category":"Detailhandel mit Textilien",
    "sg:phone":"+41 81 733 19 70",
    "sg:postcode":"8890",
    "sg:province":"St. Gallen",
    "wof:name":"Traugott Brotzer Elvira's Stoff-& N\u00e4hshop",
    "wof:placetype":"venue"
},
  "geometry": {"coordinates":[9.3432502747,47.092414856],"type":"Point"}
}