{
  "type": "Feature",
  "properties": {
    "iso:country":"CH",
    "sg:address":"Rue Du Bourg 1",
    "sg:city":"Ch\u00e2telard-lutry",
    "sg:orig_category":"Einbau von Schreinerwaren Haushaltartikel Detailhandel",
    "sg:phone":"+41 21 791 62 80",
    "sg:postcode":"1095",
    "sg:province":"Vaud",
    "wof:name":"Cuisinissima Agencement De Cuisines",
    "wof:placetype":"venue"
},
  "geometry": {"coordinates":[6.6858110428,46.5023002625],"type":"Point"}
}