{
  "type": "Feature",
  "properties": {
    "iso:country":"CH",
    "sg:address":"Wyerweg 6",
    "sg:city":"Rothenthurm",
    "sg:classifiers":[
        {
            "category":"Insurance",
            "subcategory":"Insurance Agent",
            "type":"Services"
        }
    ],
    "sg:phone":"+41 41 838 13 36",
    "sg:postcode":"6418",
    "sg:province":"Schwyz",
    "sg:tags":[
        "versicherungsagenturen",
        "-broker"
    ],
    "wof:name":"Winterthur-versicherungen Agentur Herrn Robert Moser",
    "wof:placetype":"venue"
},
  "geometry": {"coordinates":[8.6730451584,47.1043205261],"type":"Point"}
}