{
  "type": "Feature",
  "properties": {
    "addr:full":"Route De La Croix-blanche 40 1066 Epalinges Case Postale 167 Epalinges Vaud 1066",
    "addr:housenumber":"40;167",
    "addr:postcode":"1066;1066",
    "addr:street":"Route De La Croix-Blanche;Postale",
    "iso:country":"CH",
    "sg:address":"Route De La Croix-blanche 40 1066 Epalinges Case Postale 167",
    "sg:city":"Epalinges",
    "sg:orig_category":"Architektur U Ingenieurb\u00fcros",
    "sg:postcode":"1066",
    "sg:province":"Vaud",
    "wof:name":"Alain Muriset D\u00e9veloppement Amd",
    "wof:placetype":"venue"
},
  "geometry": {"coordinates":[6.770595,46.593719],"type":"Point"}
}