{
  "type": "Feature",
  "properties": {
    "iso:country":"CH",
    "sg:address":"Ammerswilerstrasse 55",
    "sg:city":"Egliswil",
    "sg:orig_category":"Non-Classified Establishments",
    "sg:postcode":"5704",
    "sg:province":"Aargau",
    "wof:name":"Hpc Feuer Produkte Karl Matter",
    "wof:placetype":"venue"
},
  "geometry": {"coordinates":[8.1884899139,47.3494567871],"type":"Point"}
}