{
  "type": "Feature",
  "properties": {
    "iso:country":"CH",
    "sg:address":"Grand-rue 128",
    "sg:city":"Tramelan",
    "sg:orig_category":"Druck ohne Zeitungsdruck",
    "sg:postcode":"2720",
    "sg:province":"Bern",
    "wof:name":"Choffat & Vuilleumier, Imprimerie Du Progr\u00e8s, L'echo Du Jura",
    "wof:placetype":"venue"
},
  "geometry": {"coordinates":[7.0995697975,47.2231864929],"type":"Point"}
}