{
  "type": "Feature",
  "properties": {
    "iso:country":"CH",
    "sg:address":"Rue Louis-favre 37",
    "sg:city":"Boudry",
    "sg:orig_category":"Gemeindeverwaltungen",
    "sg:phone":"+41 32 842 30 32",
    "sg:postcode":"2017",
    "sg:province":"Neuch\u00e2tel",
    "wof:name":"Administration Communale De Boudry,h\u00f4tel De Ville",
    "wof:placetype":"venue"
},
  "geometry": {"coordinates":[6.8356571198,46.9486503601],"type":"Point"}
}