{
  "type": "Feature",
  "properties": {
    "iso:country":"CH",
    "sg:address":"M\u00fchleli 650",
    "sg:city":"Urn\u00e4sch",
    "sg:orig_category":"Zimmerei, Ingenieurholzbau",
    "sg:phone":"+41 71 364 13 62",
    "sg:postcode":"9107",
    "sg:province":"Appenzell Ausserrhoden",
    "wof:name":"Werner Kn\u00f6pfel Holzbau",
    "wof:placetype":"venue"
},
  "geometry": {"coordinates":[9.2835702896,47.3174514771],"type":"Point"}
}