{
  "type": "Feature",
  "properties": {
    "iso:country":"CH",
    "sg:address":"3780",
    "sg:city":"Gstaad",
    "sg:orig_category":"Gymnastik U Fitnesszentren",
    "sg:phone":"+41 33 748 98 00",
    "sg:postcode":"3780",
    "sg:province":"Bern",
    "wof:name":"Fitness-center Grand Hotel Park",
    "wof:placetype":"venue"
},
  "geometry": {"coordinates":[7.283949852,46.4762382507],"type":"Point"}
}