{
  "type": "Feature",
  "properties": {
    "iso:country":"CH",
    "sg:address":"Ebnatstrasse 72",
    "sg:city":"Schaffhausen",
    "sg:orig_category":"RESTAURANTS: TEA-ROOMS",
    "sg:postcode":"8200",
    "sg:province":"Schaffhausen",
    "wof:name":"Klecka-bartonik Miroslava.",
    "wof:placetype":"venue"
},
  "geometry": {"coordinates":[8.644826889,47.7074279785],"type":"Point"}
}