{
  "type": "Feature",
  "properties": {
    "iso:country":"CH",
    "sg:address":"Hornstrasse 6",
    "sg:city":"Feldbach",
    "sg:orig_category":"Obstbau",
    "sg:phone":"+41 55 244 27 58",
    "sg:postcode":"8714",
    "sg:province":"Z\u00fcrich",
    "wof:name":"Konrad Hunziker Obstbau Sunneblick",
    "wof:placetype":"venue"
},
  "geometry": {"coordinates":[8.7872982025,47.2382965088],"type":"Point"}
}