{
  "type": "Feature",
  "properties": {
    "iso:country":"CH",
    "sg:address":"Poststrasse 2",
    "sg:city":"Bischofszell",
    "sg:orig_category":"Detailhandel mit Bekleidung",
    "sg:phone":"+41 71 422 52 51",
    "sg:postcode":"9220",
    "sg:province":"Thurgau",
    "wof:name":"Boutique S Christian Steiner Textilverkauf",
    "wof:placetype":"venue"
},
  "geometry": {"coordinates":[9.242414,47.493088],"type":"Point"}
}