{
  "type": "Feature",
  "properties": {
    "iso:country":"CH",
    "sg:address":"Adlerstrasse 30",
    "sg:city":"Magden",
    "sg:orig_category":"Zimmerei, Dachdeckerei, Bauspenglerei U Abdichtung",
    "sg:phone":"+41 79 302 50 35",
    "sg:postcode":"4312",
    "sg:province":"Aargau",
    "wof:name":"H\u00e4nni Eduard Holzbau Nachfolger H\u00fcrbin P.",
    "wof:placetype":"venue"
},
  "geometry": {"coordinates":[7.8131089211,47.5253410339],"type":"Point"}
}