{
  "type": "Feature",
  "properties": {
    "addr:full":"Ammerswil Aargau 5600",
    "addr:postcode":"5600",
    "iso:country":"CH",
    "sg:city":"Ammerswil",
    "sg:classifiers":[
        {
            "category":"Banks & Credit Unions",
            "subcategory":"Bank",
            "type":"Services"
        }
    ],
    "sg:phone":"+41 4164515903",
    "sg:postcode":"5600",
    "sg:province":"Aargau",
    "wof:name":"Raiffeisenbank",
    "wof:placetype":"venue"
},
  "geometry": {"coordinates":[8.207187,47.369488],"type":"Point"}
}