{
  "type": "Feature",
  "properties": {
    "iso:country":"CH",
    "sg:address":"Werstr. 65. 2575 Hagneck. Postfach",
    "sg:city":"Hagneck",
    "sg:orig_category":"Zimmerei, Dachdeckerei, Bauspenglerei U Abdichtung",
    "sg:phone":"+41 32 396 41 57",
    "sg:postcode":"2575",
    "sg:province":"Bern",
    "wof:name":"Kopp Rudolf.",
    "wof:placetype":"venue"
},
  "geometry": {"coordinates":[7.2002248764,47.0695991516],"type":"Point"}
}