{
  "type": "Feature",
  "properties": {
    "iso:country":"CH",
    "sg:address":"Erlenstrasse 4a Rotkreuz 6343 Risch. Postfach",
    "sg:city":"Rotkreuz",
    "sg:orig_category":"Softwareentwicklung U beratung",
    "sg:postcode":"6343",
    "sg:province":"Zug",
    "wof:name":"Art On Cd (schweiz) Gmbh",
    "wof:placetype":"venue"
},
  "geometry": {"coordinates":[8.4660310745,47.1341400146],"type":"Point"}
}