{
  "type": "Feature",
  "properties": {
    "iso:country":"CH",
    "sg:address":"Route De L'a\u00e9roport 10 1215 Gen\u00e8ve Case Postale 1215 Gen\u00e8ve",
    "sg:city":"D\u00e9p\u00f4t",
    "sg:orig_category":"Baumwollaufbereitung U spinnerei Grosshandel mit Textilien",
    "sg:phone":"+41 22 929 81 00",
    "sg:postcode":"15",
    "wof:name":"Dunavant Sa",
    "wof:placetype":"venue"
},
  "geometry": {"coordinates":[6.105718,46.229107],"type":"Point"}
}