{
  "type": "Feature",
  "properties": {
    "iso:country":"CH",
    "sg:address":"Wiesgasse 1",
    "sg:city":"Diepoldsau",
    "sg:orig_category":"Farben and Lacke Grosshandel Grosshandel mit chemischen Erzeugnissen",
    "sg:phone":"+41 71 944 18 38",
    "sg:postcode":"9444",
    "sg:province":"St. Gallen",
    "wof:name":"Paul Rotzinger Holzlacke & Beizen",
    "wof:placetype":"venue"
},
  "geometry": {"coordinates":[9.1076726913,47.4747848511],"type":"Point"}
}