{
  "type": "Feature",
  "properties": {
    "iso:country":"CH",
    "sg:address":"Speerstrasse 16",
    "sg:city":"Schaffhausen",
    "sg:orig_category":"Fotografisches Gewerbe U fotografische Laboratorien",
    "sg:phone":"+41 52 624 06 29",
    "sg:postcode":"8200",
    "sg:province":"Schaffhausen",
    "wof:name":"Gerhard Merzeder Fotograph",
    "wof:placetype":"venue"
},
  "geometry": {"coordinates":[8.6448993683,47.6979408264],"type":"Point"}
}