{
  "type": "Feature",
  "properties": {
    "iso:country":"CH",
    "sg:address":"\u00dcberlandstrasse",
    "sg:city":"D\u00fcbendorf",
    "sg:orig_category":"D\u00e4mmung gegen K\u00e4lte, W\u00e4rme, Schall U Ersch\u00fctterung",
    "sg:phone":"+41 79 436 04 56",
    "sg:postcode":"8600",
    "sg:province":"Z\u00fcrich",
    "wof:name":"St\u00e4deli Isolierungen",
    "wof:placetype":"venue"
},
  "geometry": {"coordinates":[8.607624054,47.4029388428],"type":"Point"}
}