{
  "type": "Feature",
  "properties": {
    "iso:country":"CH",
    "sg:address":"Russikerstrasse 12",
    "sg:city":"Fehraltorf",
    "sg:orig_category":"Detailhandel mit Waren verschiedener Art, Hauptrichtung Nahrungsmittel Grosshandel mit Nahrungsmitte",
    "sg:phone":"+41 19550160",
    "sg:postcode":"8320",
    "sg:province":"Z\u00fcrich",
    "wof:name":"Epa Superdiscount, A. Bortolas",
    "wof:placetype":"venue"
},
  "geometry": {"coordinates":[8.758482933,47.3852233887],"type":"Point"}
}