{
  "type": "Feature",
  "properties": {
    "iso:country":"CH",
    "sg:address":"Speerstrasse 4",
    "sg:city":"Kloten",
    "sg:orig_category":"Erschliessung von Grundst\u00fccken",
    "sg:postcode":"8302",
    "sg:province":"Z\u00fcrich",
    "wof:name":"Baugenossenschaft Eidg. Beamter Z\u00fcrich-flugplatz",
    "wof:placetype":"venue"
},
  "geometry": {"coordinates":[8.5929298401,47.4527168274],"type":"Point"}
}