{
  "type": "Feature",
  "properties": {
    "iso:country":"CH",
    "sg:address":"Chemin De Pierrefleur 32",
    "sg:city":"Lausanne",
    "sg:orig_category":"Detailhandel mit Waren verschiedener Art, Hauptrichtung Nahrungsmittel",
    "sg:phone":"+41 21 646 01 71",
    "sg:postcode":"1004",
    "sg:province":"Vaud",
    "wof:name":"Denner Satellite",
    "wof:placetype":"venue"
},
  "geometry": {"coordinates":[6.6164999008,46.5350914001],"type":"Point"}
}