{
  "type": "Feature",
  "properties": {
    "iso:country":"CH",
    "sg:address":"Badenerstrasse 558",
    "sg:city":"Z\u00fcrich",
    "sg:orig_category":"Vereine Gesang Vereine Gesang and Jodler",
    "sg:phone":"+41 14929294",
    "sg:postcode":"8048",
    "sg:province":"Z\u00fcrich",
    "wof:name":"Jodler-sextett Tv Alte Sektion",
    "wof:placetype":"venue"
},
  "geometry": {"coordinates":[8.4977712631,47.3842811584],"type":"Point"}
}