{
  "type": "Feature",
  "properties": {
    "iso:country":"CH",
    "sg:address":"Aemmenmattstr. 2",
    "sg:city":"Belp",
    "sg:classifiers":[
        {
            "category":"Health Services",
            "subcategory":"Medical Lab",
            "type":"Services"
        }
    ],
    "sg:phone":"+41 71 272 84 84",
    "sg:postcode":"3123",
    "sg:province":"Bern",
    "sg:tags":[
        "chemical",
        "pharmaceutical",
        "pharmacy"
    ],
    "wof:name":"Vifor International Ag",
    "wof:placetype":"venue"
},
  "geometry": {"coordinates":[9.336512,47.418179],"type":"Point"}
}