{
  "type": "Feature",
  "properties": {
    "addr:full":"Parkstrasse 6 Wabern Bern 3084",
    "addr:housenumber":"6",
    "addr:postcode":"3084",
    "addr:street":"Parkstrasse",
    "iso:country":"CH",
    "sg:address":"Parkstrasse 6",
    "sg:city":"Wabern",
    "sg:orig_category":"Bauspenglerei Sanit\u00e4rinstallation",
    "sg:phone":"+41 31 333 00 03",
    "sg:postcode":"3084",
    "sg:province":"Bern",
    "wof:name":"Schiess & Co Sanit\u00e4re Anlagen & Spenglerei",
    "wof:placetype":"venue"
},
  "geometry": {"coordinates":[7.448401,46.961948],"type":"Point"}
}