{
  "type": "Feature",
  "properties": {
    "iso:country":"CH",
    "sg:address":"Chemin De Riant-mont 14 1804 Corsier-sur-vevey. Postfach",
    "sg:city":"Corsier-sur-vevey",
    "sg:orig_category":"Grosshandel mit sonstigen Nahrungsmitteln",
    "sg:postcode":"1804",
    "sg:province":"Vaud",
    "wof:name":"Produits Surgel\u00e9s De Laurentiis Nicola",
    "wof:placetype":"venue"
},
  "geometry": {"coordinates":[6.850039959,46.4721794128],"type":"Point"}
}