{
  "type": "Feature",
  "properties": {
    "iso:country":"CH",
    "sg:address":"Froschaugasse 16",
    "sg:city":"Z\u00fcrich",
    "sg:orig_category":"Detailhandel mit Spielwaren",
    "sg:phone":"+41 12528814",
    "sg:postcode":"8001",
    "sg:province":"Z\u00fcrich",
    "wof:name":"Hanne W\u00e4schle Puppenladen",
    "wof:placetype":"venue"
},
  "geometry": {"coordinates":[8.5450162888,47.3730926514],"type":"Point"}
}