{
  "type": "Feature",
  "properties": {
    "iso:country":"CH",
    "sg:address":"Via Brogeda 2",
    "sg:city":"Chiasso",
    "sg:orig_category":"Sonstige Verkehrsvermittlung",
    "sg:phone":"+41 91 682 24 36",
    "sg:postcode":"6830",
    "sg:province":"Ticino",
    "wof:name":"Lastra Sagl",
    "wof:placetype":"venue"
},
  "geometry": {"coordinates":[9.0355806351,45.8370170593],"type":"Point"}
}