{
  "type": "Feature",
  "properties": {
    "iso:country":"CH",
    "sg:address":"Via San Gottardo 51",
    "sg:city":"Chiasso",
    "sg:orig_category":"Detailhandel mit Damenbekleidung Detailhandel mit Textilien",
    "sg:phone":"+41 91 682 85 36",
    "sg:postcode":"6830",
    "sg:province":"Ticino",
    "wof:name":"Franca Presti Merceria",
    "wof:placetype":"venue"
},
  "geometry": {"coordinates":[9.0289173126,45.8344650269],"type":"Point"}
}