{
  "type": "Feature",
  "properties": {
    "iso:country":"CH",
    "sg:address":"Feldstrasse 32c",
    "sg:city":"Grosswangen",
    "sg:orig_category":"Aktivit\u00e4ten der Generalunternehmen im Baugewerbe Vermittlung von Immobilien",
    "sg:phone":"+41 41 497 26 40",
    "sg:postcode":"6022",
    "sg:province":"Luzern",
    "wof:name":"Cerutti Partner Architekten Ag Architekturb\u00fcro Filiale Malters",
    "wof:placetype":"venue"
},
  "geometry": {"coordinates":[8.182725,47.036816],"type":"Point"}
}