{
  "type": "Feature",
  "properties": {
    "iso:country":"CH",
    "sg:address":"Luzernerstrasse 18",
    "sg:city":"Kriens",
    "sg:classifiers":[
        {
            "category":"Restaurant",
            "type":"Food & Drink"
        }
    ],
    "sg:phone":"+41 41 320 53 88",
    "sg:postcode":"6010",
    "sg:province":"Luzern",
    "wof:name":"Caf\u00e9-restaurant Ambrosia",
    "wof:placetype":"venue"
},
  "geometry": {"coordinates":[8.2802686691,47.0337867737],"type":"Point"}
}