{
  "type": "Feature",
  "properties": {
    "iso:country":"CH",
    "sg:address":"P\u00e9rolles Boulevard De 55",
    "sg:city":"Freiburg",
    "sg:orig_category":"Unclassifiable Establishments",
    "sg:postcode":"1700",
    "sg:province":"Fribourg",
    "wof:name":"Redyw Ag",
    "wof:placetype":"venue"
},
  "geometry": {"coordinates":[9.8381900787,46.4970588684],"type":"Point"}
}