{
  "type": "Feature",
  "properties": {
    "iso:country":"CH",
    "sg:address":"Bahnhofstrasse 4",
    "sg:city":"Ostermundigen",
    "sg:orig_category":"Grosshandel mit Getreide, Saatgut U Futtermitteln",
    "sg:postcode":"3072",
    "sg:province":"Bern",
    "wof:name":"Petland Brunner Kurt",
    "wof:placetype":"venue"
},
  "geometry": {"coordinates":[7.483191967,46.9554443359],"type":"Point"}
}