{
  "type": "Feature",
  "properties": {
    "iso:country":"CH",
    "sg:address":"H\u00fcbeli",
    "sg:city":"Sch\u00f6tz",
    "sg:orig_category":"Erschliessung von Grundst\u00fccken",
    "sg:postcode":"6247",
    "sg:province":"Luzern",
    "wof:name":"Wohnbaugenossenschaft Sch\u00f6tz",
    "wof:placetype":"venue"
},
  "geometry": {"coordinates":[7.9863381386,47.1674575806],"type":"Point"}
}