{
  "type": "Feature",
  "properties": {
    "iso:country":"CH",
    "sg:address":"Florastrasse 38",
    "sg:city":"Z\u00fcrich",
    "sg:orig_category":"Betrieb von Taxis",
    "sg:postcode":"8008",
    "sg:province":"Z\u00fcrich",
    "wof:name":"Kunterbunt Gmbh",
    "wof:placetype":"venue"
},
  "geometry": {"coordinates":[8.551552,47.361362],"type":"Point"}
}