{
  "type": "Feature",
  "properties": {
    "iso:country":"CH",
    "sg:address":"M\u00fcnchstrasse 3",
    "sg:city":"M\u00fcnchenstein",
    "sg:orig_category":"Architektur U Ingenieurb\u00fcros Architekturb\u00fcros",
    "sg:phone":"+41 61 413 20 30",
    "sg:postcode":"4142",
    "sg:province":"Basel-Landschaft",
    "wof:name":"Haab Hans-peter, Schneider Pascal Architekten",
    "wof:placetype":"venue"
},
  "geometry": {"coordinates":[7.621516,47.512203],"type":"Point"}
}