{
  "type": "Feature",
  "properties": {
    "iso:country":"CH",
    "sg:address":"8588",
    "sg:city":"Zihlschlacht",
    "sg:orig_category":"Primarschulen",
    "sg:phone":"+41 71 642 21 55",
    "sg:postcode":"8588",
    "sg:province":"Thurgau",
    "wof:name":"Primarschule",
    "wof:placetype":"venue"
},
  "geometry": {"coordinates":[9.2587299347,47.5190887451],"type":"Point"}
}