{
  "type": "Feature",
  "properties": {
    "iso:country":"CH",
    "sg:address":"Alfons-aeby-strasse 43 3186 D\u00fcdingen. Postfach 202",
    "sg:city":"D\u00fcdingen",
    "sg:orig_category":"Detailhandel mit Getreide, Futtermitteln U Landesprodukten Grosshandel mit Getreide, Saatgut U Futte",
    "sg:phone":"+41 26 493 51 80",
    "sg:postcode":"3186",
    "sg:province":"Fribourg",
    "wof:name":"Vivasol Gmbh",
    "wof:placetype":"venue"
},
  "geometry": {"coordinates":[7.1964550018,46.8486213684],"type":"Point"}
}