{
  "type": "Feature",
  "properties": {
    "iso:country":"CH",
    "sg:address":"Promenadenstrasse 11",
    "sg:city":"Zurzach",
    "sg:orig_category":"Kinderkrippen U horte",
    "sg:phone":"+41 56 249 25 65",
    "sg:postcode":"5330",
    "sg:province":"Aargau",
    "wof:name":"Kinderhort Zurzach Des Gemeinn\u00fctzigen Frauenvereins",
    "wof:placetype":"venue"
},
  "geometry": {"coordinates":[8.2978200912,47.5857582092],"type":"Point"}
}