{
  "type": "Feature",
  "properties": {
    "iso:country":"CH",
    "sg:address":"8355",
    "sg:city":"Aadorf",
    "sg:orig_category":"Erschliessung von Grundst\u00fccken",
    "sg:postcode":"8355",
    "sg:province":"Thurgau",
    "wof:name":"Hausgen.kosthaus Aadorf",
    "wof:placetype":"venue"
},
  "geometry": {"coordinates":[8.9033498764,47.4896583557],"type":"Point"}
}