{
  "type": "Feature",
  "properties": {
    "iso:country":"CH",
    "sg:address":"Rue De L'eglise 1926 Fully. Postfach",
    "sg:city":"Fully",
    "sg:orig_category":"Detailhandel mit Uhren U Schmuck Fachdetailhandel in Verkaufsr\u00e4umen",
    "sg:phone":"+41 27 746 24 04",
    "sg:postcode":"1926",
    "sg:province":"Valais",
    "wof:name":"Maret, G\u00e9rard",
    "wof:placetype":"venue"
},
  "geometry": {"coordinates":[7.1151638031,46.1387557983],"type":"Point"}
}