{
  "type": "Feature",
  "properties": {
    "iso:country":"CH",
    "sg:address":"Industriestrasse 3 4543 Deitingen. Postfach",
    "sg:city":"Deitingen",
    "sg:orig_category":"Herstellung von Verbrennungsmotoren U Turbinen ohne Motoren f\u00fcr Luft U Strassenfahrzeuge",
    "sg:phone":"+41 32 613 20 30",
    "sg:postcode":"4543",
    "sg:province":"Solothurn",
    "wof:name":"Abb Turbo Systems Ag",
    "wof:placetype":"venue"
},
  "geometry": {"coordinates":[7.62332201,47.2171936035],"type":"Point"}
}