{
  "type": "Feature",
  "properties": {
    "iso:country":"CH",
    "sg:address":"Grubenstrasse 4",
    "sg:city":"Urdorf",
    "sg:orig_category":"Werbevermittlung Werbung",
    "sg:phone":"+41 17340472",
    "sg:postcode":"8902",
    "sg:province":"Z\u00fcrich",
    "wof:name":"Isler Annoncen Ag",
    "wof:placetype":"venue"
},
  "geometry": {"coordinates":[8.4201202393,47.3921966553],"type":"Point"}
}