{
  "type": "Feature",
  "properties": {
    "iso:country":"CH",
    "sg:address":"Zehntenhausstrasse 15",
    "sg:city":"Z\u00fcrich",
    "sg:orig_category":"Bau von Strassen, Sportanlagen U Bahnverkehrsstrecken",
    "sg:postcode":"8046",
    "sg:province":"Z\u00fcrich",
    "wof:name":"Oceano Gmbh",
    "wof:placetype":"venue"
},
  "geometry": {"coordinates":[8.074811,47.40012],"type":"Point"}
}