{
  "type": "Feature",
  "properties": {
    "iso:country":"CH",
    "sg:address":"Invau",
    "sg:city":"Mossel",
    "sg:orig_category":"Fotografische Ateliers Fotografisches Gewerbe U fotografische Laboratorien",
    "sg:phone":"+41 26 652 52 70",
    "sg:postcode":"1675",
    "sg:province":"Fribourg",
    "wof:name":"Philippe Blanc Photographe",
    "wof:placetype":"venue"
},
  "geometry": {"coordinates":[6.850810051,46.6225357056],"type":"Point"}
}