{
  "type": "Feature",
  "properties": {
    "iso:country":"CH",
    "sg:address":"S\u00e4ntisstrasse 10",
    "sg:city":"Sulgen",
    "sg:orig_category":"Malerei",
    "sg:phone":"+41 71 642 17 65",
    "sg:postcode":"8583",
    "sg:province":"Thurgau",
    "wof:name":"Paul Sennhauser Malergesch\u00e4ft",
    "wof:placetype":"venue"
},
  "geometry": {"coordinates":[9.1892948151,47.5334129333],"type":"Point"}
}