{
  "type": "Feature",
  "properties": {
    "iso:country":"CH",
    "sg:address":"Guggenmoos",
    "sg:city":"K\u00e4giswil",
    "sg:orig_category":"Abbruch U Sprenggewerbe, Erdbewegungsarbeiten Erdbewegungsarbeiten",
    "sg:phone":"+41 41 660 45 88",
    "sg:postcode":"6056",
    "sg:province":"Obwalden",
    "wof:name":"Bucher Albert Produits De Protection De B\u00e9ton, De Murs Et De Sols; Diffusion",
    "wof:placetype":"venue"
},
  "geometry": {"coordinates":[8.26272,46.921661],"type":"Point"}
}