{
  "type": "Feature",
  "properties": {
    "iso:country":"CH",
    "sg:address":"Entrep\u00f4ts Rue Des 1950 Sion Case Postale 176",
    "sg:city":"Sitten",
    "sg:orig_category":"Grosshandel mit festen Brennstoffen U Mineral\u00f6lerzeugnissen",
    "sg:phone":"+41 27 203 36 14",
    "sg:postcode":"1950",
    "sg:province":"Valais",
    "wof:name":"Raf Sa",
    "wof:placetype":"venue"
},
  "geometry": {"coordinates":[7.3582339287,46.2266960144],"type":"Point"}
}