{
  "type": "Feature",
  "properties": {
    "iso:country":"CH",
    "sg:address":"Bogn Engiadina",
    "sg:city":"Scuol",
    "sg:orig_category":"Arztpraxen",
    "sg:phone":"+41 81 861 20 40",
    "sg:postcode":"7550",
    "sg:province":"Graubunden",
    "wof:name":"Dres Med.c. & U. Casanova Spezial\u00e4rzte Fmh",
    "wof:placetype":"venue"
},
  "geometry": {"coordinates":[10.302828,46.798767],"type":"Point"}
}