{
  "type": "Feature",
  "properties": {
    "addr:full":"Coula Route De La 5 Ch\u00e2tel-st-denis Fribourg 1618",
    "addr:housenumber":"5",
    "addr:postcode":"1618",
    "addr:street":"Route De La",
    "iso:country":"CH",
    "sg:address":"Coula Route De La 5",
    "sg:city":"Ch\u00e2tel-st-denis",
    "sg:orig_category":"Allgemeiner Hoch U Tiefbau",
    "sg:phone":"+41 21 948 91 91",
    "sg:postcode":"1618",
    "sg:province":"Fribourg",
    "wof:name":"Allseas Construction Contractors Sa",
    "wof:placetype":"venue"
},
  "geometry": {"coordinates":[6.90154,46.527534],"type":"Point"}
}