{
  "type": "Feature",
  "properties": {
    "iso:country":"CH",
    "sg:address":"Muntschi",
    "sg:city":"Andeer",
    "sg:orig_category":"Tierarztpraxis",
    "sg:phone":"+41 81 661 21 41",
    "sg:postcode":"7440",
    "sg:province":"Graubunden",
    "wof:name":"Dr. Med. Vet. Bernard Semadeni Tierarzt",
    "wof:placetype":"venue"
},
  "geometry": {"coordinates":[9.4262599945,46.6029052734],"type":"Point"}
}