{
  "type": "Feature",
  "properties": {
    "iso:country":"CH",
    "sg:address":"Via Medere 14",
    "sg:city":"Ascona",
    "sg:orig_category":"Sanit\u00e4r, Heizungs U L\u00fcftungsinstallation Sanit\u00e4rinstallation",
    "sg:phone":"+41 91 791 11 80",
    "sg:postcode":"6612",
    "sg:province":"Ticino",
    "wof:name":"Bai Angelo E Figlio",
    "wof:placetype":"venue"
},
  "geometry": {"coordinates":[8.7763309479,46.1579055786],"type":"Point"}
}