{
  "type": "Feature",
  "properties": {
    "iso:country":"CH",
    "sg:address":"Gl\u00e4rnischstrasse 121",
    "sg:city":"M\u00e4nnedorf",
    "sg:orig_category":"Interessenvertretungen",
    "sg:postcode":"8708",
    "sg:province":"Z\u00fcrich",
    "wof:name":"Genossenschaft Klubhaus Der Fischer-vereinigung M\u00e4nnedorf-st\u00e4fa-uetikon",
    "wof:placetype":"venue"
},
  "geometry": {"coordinates":[8.6900691986,47.2595291138],"type":"Point"}
}