{
  "type": "Feature",
  "properties": {
    "addr:full":"Bernstrasse 7 Schlieren Z\u00fcrich 8952",
    "addr:housenumber":"7",
    "addr:postcode":"8952",
    "addr:street":"Bernstrasse",
    "iso:country":"CH",
    "sg:address":"Bernstrasse 7",
    "sg:city":"Schlieren",
    "sg:orig_category":"Architektur U Ingenieurb\u00fcros Unternehmensberatung",
    "sg:phone":"+41 32 913 83 39",
    "sg:postcode":"8952",
    "sg:province":"Z\u00fcrich",
    "wof:name":"Conseilray Sa",
    "wof:placetype":"venue"
},
  "geometry": {"coordinates":[6.824122,47.099598],"type":"Point"}
}