{
  "type": "Feature",
  "properties": {
    "iso:country":"CH",
    "sg:address":"Vallamand-dessous",
    "sg:city":"Salavaux",
    "sg:orig_category":"RESTAURANTS: TEA-ROOMS",
    "sg:postcode":"1585",
    "sg:province":"Vaud",
    "wof:name":"Restaurant Du Lac Vallamand-dessous Sa",
    "wof:placetype":"venue"
},
  "geometry": {"coordinates":[7.0237250328,46.9194107056],"type":"Point"}
}