{
  "type": "Feature",
  "properties": {
    "iso:country":"CH",
    "sg:address":"Altstattstrasse",
    "sg:city":"Sattel",
    "sg:orig_category":"Instandhaltung U Reparatur von Automobilen",
    "sg:postcode":"6417",
    "sg:province":"Schwyz",
    "wof:name":"Paul Mathis",
    "wof:placetype":"venue"
},
  "geometry": {"coordinates":[8.6453742981,47.0912017822],"type":"Point"}
}