{
  "type": "Feature",
  "properties": {
    "iso:country":"CH",
    "sg:address":"Reichenbachstrasse 54",
    "sg:city":"Zollikofen",
    "sg:orig_category":"Fahrschulen, Flugschulen",
    "sg:phone":"+41 31 911 02 10",
    "sg:postcode":"3052",
    "sg:province":"Bern",
    "wof:name":"Ernst Hug Autofahrlehrer",
    "wof:placetype":"venue"
},
  "geometry": {"coordinates":[7.4497947693,46.9923591614],"type":"Point"}
}