{
  "type": "Feature",
  "properties": {
    "iso:country":"CH",
    "sg:address":"R\u00fctti Riedern",
    "sg:city":"Ueberstorf",
    "sg:orig_category":"Herstellung von sonstigen Holzwaren",
    "sg:phone":"+41 31 889 02 79",
    "sg:postcode":"3182",
    "sg:province":"Fribourg",
    "wof:name":"Kaufmann Walter",
    "wof:placetype":"venue"
},
  "geometry": {"coordinates":[7.3485980034,46.8861465454],"type":"Point"}
}