{
  "type": "Feature",
  "properties": {
    "iso:country":"CH",
    "sg:address":"7554",
    "sg:city":"Sent",
    "sg:orig_category":"Malerei",
    "sg:phone":"+41 71 636 14 21",
    "sg:postcode":"7554",
    "sg:province":"Graubunden",
    "wof:name":"Basil Frick Malergesch\u00e4ft",
    "wof:placetype":"venue"
},
  "geometry": {"coordinates":[9.1711006165,47.5798530579],"type":"Point"}
}