{
  "type": "Feature",
  "properties": {
    "iso:country":"CH",
    "sg:address":"Bahnhofstrasse 2 6370 Stans. Postfach 971",
    "sg:city":"Stans",
    "sg:orig_category":"Grossbanken",
    "sg:phone":"+41 41 618 68 68",
    "sg:postcode":"6371",
    "sg:province":"Nidwalden",
    "wof:name":"Credit Suisse",
    "wof:placetype":"venue"
},
  "geometry": {"coordinates":[8.3665876389,46.957408905],"type":"Point"}
}