{
  "type": "Feature",
  "properties": {
    "iso:country":"CH",
    "sg:address":"Poststr. 300",
    "sg:city":"Krinau",
    "sg:classifiers":[
        {
            "category":"Banks & Credit Unions",
            "subcategory":"Bank",
            "type":"Services"
        }
    ],
    "sg:phone":"+41 71 988 40 40",
    "sg:postcode":"9622",
    "sg:province":"St. Gallen",
    "wof:name":"Raiffeisenkasse",
    "wof:placetype":"venue"
},
  "geometry": {"coordinates":[9.05165,47.317715],"type":"Point"}
}