{
  "type": "Feature",
  "properties": {
    "iso:country":"CH",
    "sg:address":"Rue Samuel-constant 1",
    "sg:city":"Gen\u00e8ve",
    "sg:orig_category":"Wirtschaftspr\u00fcfung, Steuerberatung U Treuhand",
    "sg:phone":"+41 22 340 43 44",
    "sg:postcode":"1201",
    "sg:province":"Gen\u00e8ve",
    "wof:name":"Jean-claude Fran\u00e7ois Bureau Fiduciaire",
    "wof:placetype":"venue"
},
  "geometry": {"coordinates":[6.1347570419,46.2067375183],"type":"Point"}
}