{
  "type": "Feature",
  "properties": {
    "iso:country":"CH",
    "sg:address":"Kirchstrasse 88",
    "sg:city":"Grenchen",
    "sg:orig_category":"Detailhandel mit Brot, Back U S\u00fcsswaren",
    "sg:phone":"+41 32 652 17 56",
    "sg:postcode":"2540",
    "sg:province":"Solothurn",
    "wof:name":"B\u00e4ckerei Badoglu Z.",
    "wof:placetype":"venue"
},
  "geometry": {"coordinates":[7.39197,47.19635],"type":"Point"}
}