{
  "type": "Feature",
  "properties": {
    "iso:country":"CH",
    "sg:address":"H\u00f6heweg 2",
    "sg:city":"Glarus",
    "sg:orig_category":"Detailhandel mit B\u00fcchern, Zeitungen, Schreib U Papeteriewaren Druckweiterverarbeitung",
    "sg:phone":"+41 55 640 20 88",
    "sg:postcode":"8750",
    "sg:province":"Glarus",
    "wof:name":"W. M\u00fcller-moor",
    "wof:placetype":"venue"
},
  "geometry": {"coordinates":[9.058873,47.045811],"type":"Point"}
}