{
  "type": "Feature",
  "properties": {
    "iso:country":"CH",
    "sg:address":"Strada Da La Vall Da Fi\u00fcm",
    "sg:city":"Morcote",
    "sg:orig_category":"Erbringung von Dienstleistungen f\u00fcr Unternehmen Kunsthandel",
    "sg:phone":"+41 19913060",
    "sg:postcode":"6922",
    "sg:province":"Ticino",
    "wof:name":"Z\u00fcrichsee Auktionen Belart Ag",
    "wof:placetype":"venue"
},
  "geometry": {"coordinates":[8.5914516449,47.3026123047],"type":"Point"}
}