{
  "type": "Feature",
  "properties": {
    "iso:country":"CH",
    "sg:address":"Forchstrasse 152",
    "sg:city":"Z\u00fcrich",
    "sg:orig_category":"Architekturb\u00fcros",
    "sg:phone":"+41 13815830",
    "sg:postcode":"8032",
    "sg:province":"Z\u00fcrich",
    "wof:name":"Manfred & Helen Heuss Architekten Sia",
    "wof:placetype":"venue"
},
  "geometry": {"coordinates":[8.564058,47.360321],"type":"Point"}
}