{
  "type": "Feature",
  "properties": {
    "iso:country":"CH",
    "sg:address":"Seestrasse 86 8610 Uster. Postfach",
    "sg:city":"Uster",
    "sg:orig_category":"Sanit\u00e4r, Heizungs U L\u00fcftungsinstallation",
    "sg:postcode":"8610",
    "sg:province":"Z\u00fcrich",
    "wof:name":"Max Heizungen Gmbh",
    "wof:placetype":"venue"
},
  "geometry": {"coordinates":[8.7090778351,47.3452835083],"type":"Point"}
}