{
  "type": "Feature",
  "properties": {
    "iso:country":"CH",
    "sg:address":"Restaurant Fuschena.",
    "sg:city":"Berg\u00fcn/bravuogn",
    "sg:orig_category":"RESTAURANTS: TEA-ROOMS",
    "sg:phone":"+41 81 862 28 91",
    "sg:postcode":"7482",
    "sg:province":"Graubunden",
    "wof:name":"Ragaz Gastro Ag",
    "wof:placetype":"venue"
},
  "geometry": {"coordinates":[9.496805191,47.0083847046],"type":"Point"}
}