{
  "type": "Feature",
  "properties": {
    "iso:country":"CH",
    "sg:address":"Nidaugasse 42",
    "sg:city":"Biel/bienne",
    "sg:orig_category":"Parf\u00fcmerien U sonstiger Detailhandel mit kosmetischen Artikeln U K\u00f6rperpflegemitteln",
    "sg:phone":"+41 32 322 91 91",
    "sg:postcode":"2502",
    "sg:province":"Bern",
    "wof:name":"Parfumerie Yves Rocher",
    "wof:placetype":"venue"
},
  "geometry": {"coordinates":[7.2461481094,47.1391029358],"type":"Point"}
}