{
  "type": "Feature",
  "properties": {
    "iso:country":"CH",
    "sg:address":"R\u00fctihofstrasse 19",
    "sg:city":"Z\u00fcrich",
    "sg:classifiers":[
        {
            "category":"Restaurant",
            "type":"Food & Drink"
        }
    ],
    "sg:phone":"+41 13413100",
    "sg:postcode":"8049",
    "sg:province":"Z\u00fcrich",
    "wof:name":"Restaurant R\u00fctihof",
    "wof:placetype":"venue"
},
  "geometry": {"coordinates":[8.4791622162,47.4139823914],"type":"Point"}
}