{
  "type": "Feature",
  "properties": {
    "iso:country":"CH",
    "sg:address":"Sennweidstrasse 46 6312 Steinhausen. Postfach 462",
    "sg:city":"Steinhausen",
    "sg:orig_category":"Markt U Meinungsforschung",
    "sg:phone":"+41 41 748 76 00",
    "sg:postcode":"6312",
    "sg:province":"Zug",
    "wof:name":"Schlegel Dr., Pharmamarketing Ag",
    "wof:placetype":"venue"
},
  "geometry": {"coordinates":[8.4835071564,47.1889610291],"type":"Point"}
}