{
  "type": "Feature",
  "properties": {
    "iso:country":"CH",
    "sg:address":"Oberlandstr. 9",
    "sg:city":"Spiez",
    "sg:classifiers":[
        {
            "category":"Banks & Credit Unions",
            "subcategory":"Bank",
            "type":"Services"
        }
    ],
    "sg:phone":"+41 33 654 23 77",
    "sg:postcode":"3700",
    "sg:province":"Bern",
    "wof:name":"Amtsersparniskasse Thun, Gesch\u00e4ftsstelle",
    "wof:placetype":"venue"
},
  "geometry": {"coordinates":[7.67634,46.689537],"type":"Point"}
}