{
  "type": "Feature",
  "properties": {
    "iso:country":"CH",
    "sg:address":"3754 Diemtigen. Postfach",
    "sg:city":"Schwenden",
    "sg:classifiers":[
        {
            "category":"Travel",
            "subcategory":"Hotels & Motels",
            "type":"Entertainment"
        }
    ],
    "sg:phone":"+41 41 850 82 50",
    "sg:postcode":"3757",
    "sg:province":"Bern",
    "sg:tags":[
        "hotels",
        "mit",
        "restaurant"
    ],
    "wof:name":"Ulrich Hans.",
    "wof:placetype":"venue"
},
  "geometry": {"coordinates":[8.4411153793,47.0812721252],"type":"Point"}
}