{
  "type": "Feature",
  "properties": {
    "iso:country":"CH",
    "sg:address":"Rue De La Source 18",
    "sg:city":"Vallorbe",
    "sg:orig_category":"Sanit\u00e4r, Heizungs U L\u00fcftungsinstallation",
    "sg:phone":"+41 21 843 11 14",
    "sg:postcode":"1337",
    "sg:province":"Vaud",
    "wof:name":"Cunin Roland",
    "wof:placetype":"venue"
},
  "geometry": {"coordinates":[6.3559741974,46.7062339783],"type":"Point"}
}