{
  "type": "Feature",
  "properties": {
    "iso:country":"CH",
    "sg:address":"Sportplatzweg 6 3672 Oberdiessbach. Postfach 143",
    "sg:city":"Oberdiessbach",
    "sg:orig_category":"Druck ohne Zeitungsdruck Offsetdruck",
    "sg:phone":"+41 31 771 01 57",
    "sg:postcode":"3672",
    "sg:province":"Bern",
    "wof:name":"Gerber Bernhard, Buch Und Offsetdruckerei, Filmsatz",
    "wof:placetype":"venue"
},
  "geometry": {"coordinates":[7.6217861176,46.8398895264],"type":"Point"}
}