{
  "type": "Feature",
  "properties": {
    "iso:country":"CH",
    "sg:address":"Aeschenstrasse 11",
    "sg:city":"Amden",
    "sg:orig_category":"Architektur U Ingenieurb\u00fcros",
    "sg:phone":"+41 55 611 53 53",
    "sg:postcode":"8873",
    "sg:province":"St. Gallen",
    "wof:name":"Magma Ag F\u00fcr Geologie, Umwelt Und Planung",
    "wof:placetype":"venue"
},
  "geometry": {"coordinates":[9.137376,47.148994],"type":"Point"}
}