{
  "type": "Feature",
  "properties": {
    "iso:country":"CH",
    "sg:address":"St\u00e4hlistrasse 33",
    "sg:city":"Kreuzlingen",
    "sg:orig_category":"Unternehmensberatung",
    "sg:postcode":"8280",
    "sg:province":"Thurgau",
    "wof:name":"Unjc Schenkel-w\u00fcger Marianne",
    "wof:placetype":"venue"
},
  "geometry": {"coordinates":[9.1642990112,47.6437988281],"type":"Point"}
}