{
  "type": "Feature",
  "properties": {
    "iso:country":"CH",
    "sg:address":"Niederfeldstrasse 24",
    "sg:city":"Mettmenstetten",
    "sg:orig_category":"Konkurs- and Betreibungs\u00e4mter",
    "sg:phone":"+41 17671485",
    "sg:postcode":"8932",
    "sg:province":"Z\u00fcrich",
    "wof:name":"Betreibungsamt",
    "wof:placetype":"venue"
},
  "geometry": {"coordinates":[8.4655685425,47.247127533],"type":"Point"}
}