{
  "type": "Feature",
  "properties": {
    "iso:country":"CH",
    "sg:address":"Magnoliastrasse 1 3600 Thun. Postfach",
    "sg:city":"Thun",
    "sg:orig_category":"Sonstige mit der Informatik verbundene T\u00e4tigkeiten",
    "sg:phone":"+41 33 222 12 85",
    "sg:postcode":"3600",
    "sg:province":"Bern",
    "wof:name":"Riedel Computing Informatik-schulungen, -beratungen",
    "wof:placetype":"venue"
},
  "geometry": {"coordinates":[7.6339111328,46.7596206665],"type":"Point"}
}