{
  "type": "Feature",
  "properties": {
    "iso:country":"CH",
    "sg:address":"Efringerstrasse 5",
    "sg:city":"Basel",
    "sg:orig_category":"Maler U Glasergewerbe Tapeziererei",
    "sg:phone":"+41 41 660 54 77",
    "sg:postcode":"4057",
    "sg:province":"Basel-Stadt",
    "wof:name":"Hess Anton",
    "wof:placetype":"venue"
},
  "geometry": {"coordinates":[8.222943306,46.8815612793],"type":"Point"}
}