{
  "type": "Feature",
  "properties": {
    "iso:country":"CH",
    "sg:address":"Burgunderstrasse 14",
    "sg:city":"Bellach",
    "sg:orig_category":"Sonstige mit der Informatik verbundene T\u00e4tigkeiten",
    "sg:phone":"+41 32 618 15 83",
    "sg:postcode":"4512",
    "sg:province":"Solothurn",
    "wof:name":"Josch Johner Daniel Schulungen",
    "wof:placetype":"venue"
},
  "geometry": {"coordinates":[7.5097618103,47.2144851685],"type":"Point"}
}