{
  "type": "Feature",
  "properties": {
    "iso:country":"CH",
    "sg:address":"Rue Alexander-sch\u00f6ni 30a 2500 Biel/bienne. Postfach",
    "sg:city":"Biel/bienne",
    "sg:orig_category":"Detailhandel mit elektrischen Haushalts-,Radio U Fernsehger\u00e4ten sowie Musikinstrumenten",
    "sg:postcode":"2503",
    "sg:province":"Bern",
    "wof:name":"Giant Music, Vincent Baettig.",
    "wof:placetype":"venue"
},
  "geometry": {"coordinates":[7.2499451637,47.1371650696],"type":"Point"}
}