{
  "type": "Feature",
  "properties": {
    "iso:country":"CH",
    "sg:address":"Rue Pr\u00e9-fleuri 2a",
    "sg:city":"Sion",
    "sg:orig_category":"Grosshandel mit Textilien",
    "sg:phone":"+41 21 943 38 38",
    "sg:postcode":"1950",
    "sg:province":"Valais",
    "wof:name":"Amiguet Philippe Sa",
    "wof:placetype":"venue"
},
  "geometry": {"coordinates":[6.8644599915,46.4657783508],"type":"Point"}
}