{
  "type": "Feature",
  "properties": {
    "iso:country":"CH",
    "sg:address":"Kirchstrasse 6",
    "sg:city":"Freienbach",
    "sg:orig_category":"Kauf U Verkauf von Immobilien auf eigene Rechnung",
    "sg:phone":"+41 12915450",
    "sg:postcode":"8807",
    "sg:province":"Schwyz",
    "wof:name":"Bacom & T Engineering Ag",
    "wof:placetype":"venue"
},
  "geometry": {"coordinates":[8.7264680862,47.1954345703],"type":"Point"}
}