{
  "type": "Feature",
  "properties": {
    "iso:country":"CH",
    "sg:address":"Rasses Chemin Des 92",
    "sg:city":"Veyrier",
    "sg:orig_category":"Wohnheime",
    "sg:phone":"+41 22 784 33 00",
    "sg:postcode":"1255",
    "sg:province":"Gen\u00e8ve",
    "wof:name":"Fondation Communale Pour Le Logement Des Personnes \u00e2g\u00e9es.",
    "wof:placetype":"venue"
},
  "geometry": {"coordinates":[6.185324192,46.1668891907],"type":"Point"}
}