{
  "type": "Feature",
  "properties": {
    "iso:country":"CH",
    "sg:address":"Oberer Graben 44 8400 Winterthur. Postfach",
    "sg:city":"Winterthur",
    "sg:orig_category":"Detailhandel mit fotografischen Artikeln Fachdetailhandel in Verkaufsr\u00e4umen",
    "sg:phone":"+41 52 213 37 85",
    "sg:postcode":"8402",
    "sg:province":"Z\u00fcrich",
    "wof:name":"Steiner Hugo, Fotogesch\u00e4ft",
    "wof:placetype":"venue"
},
  "geometry": {"coordinates":[8.73133564,47.4997444153],"type":"Point"}
}