{
  "type": "Feature",
  "properties": {
    "iso:country":"CH",
    "sg:address":"Aelpli 4",
    "sg:city":"St\u00fcsslingen",
    "sg:orig_category":"Erbringung von Dienstleistungen f\u00fcr Unternehmen Satzherstellung U Reproduktion",
    "sg:phone":"+41 62 298 24 16",
    "sg:postcode":"4655",
    "sg:province":"Solothurn",
    "wof:name":"Agi Atelier F\u00fcr Die Graphische Industrie Ag",
    "wof:placetype":"venue"
},
  "geometry": {"coordinates":[7.9697041512,47.3976325989],"type":"Point"}
}