{
  "type": "Feature",
  "properties": {
    "iso:country":"CH",
    "sg:address":"Route De Florissant 57",
    "sg:city":"Gen\u00e8ve",
    "sg:orig_category":"Detailhandel Reparatur von Gebrauchsg\u00fctern Vermietung von Gebrauchsg\u00fctern",
    "sg:phone":"+41 22 346 27 47",
    "sg:postcode":"1206",
    "sg:province":"Gen\u00e8ve",
    "wof:name":"Playtime Video Sa",
    "wof:placetype":"venue"
},
  "geometry": {"coordinates":[6.1620731354,46.193397522],"type":"Point"}
}