{
  "type": "Feature",
  "properties": {
    "iso:country":"CH",
    "sg:address":"Stauffenbach",
    "sg:city":"Ochlenberg",
    "sg:orig_category":"Detailhandel mit Milcherzeugnissen U Eiern Verarbeitung von Milch",
    "sg:phone":"+41 79 335 91 49",
    "sg:postcode":"3367",
    "sg:province":"Bern",
    "wof:name":"Karl Geissb\u00fchler K\u00e4serei",
    "wof:placetype":"venue"
},
  "geometry": {"coordinates":[7.7330498695,47.1495094299],"type":"Point"}
}