{
  "type": "Feature",
  "properties": {
    "addr:full":"6482 Gurtnellen. Postfach Gurtnellen Uri 6482",
    "addr:housenumber":"6482",
    "addr:postcode":"6482",
    "addr:street":"Gurtnellen. Postfach",
    "iso:country":"CH",
    "sg:address":"6482 Gurtnellen. Postfach",
    "sg:city":"Gurtnellen",
    "sg:orig_category":"Allgemeinbildende weiterf\u00fchrende Schulen RESTAURANTS: TEA-ROOMS",
    "sg:phone":"+41 41 885 11 22",
    "sg:postcode":"6482",
    "sg:province":"Uri",
    "wof:name":"Kurs Und Seminarzentrum Gurtnellen, Beatrice Epp-iseli Restaurant",
    "wof:placetype":"venue"
},
  "geometry": {"coordinates":[8.62147,46.727879],"type":"Point"}
}