{
  "type": "Feature",
  "properties": {
    "iso:country":"CH",
    "sg:address":"Place Des Anciens-bains 10",
    "sg:city":"Rolle",
    "sg:orig_category":"Autogaragen",
    "sg:phone":"+41 21 825 25 28",
    "sg:postcode":"1180",
    "sg:province":"Vaud",
    "wof:name":"Serge Lincio Garage",
    "wof:placetype":"venue"
},
  "geometry": {"coordinates":[6.33987,46.459885],"type":"Point"}
}