{
  "type": "Feature",
  "properties": {
    "iso:country":"CH",
    "sg:address":"Allschwilerstrasse 123",
    "sg:city":"Basel",
    "sg:orig_category":"Detailhandel mit B\u00fcchern, Zeitungen, Schreib U Papeteriewaren",
    "sg:phone":"+41 61 302 80 70",
    "sg:postcode":"4055",
    "sg:province":"Basel-Stadt",
    "wof:name":"Kiosk Morgartenring Sahin",
    "wof:placetype":"venue"
},
  "geometry": {"coordinates":[7.565424,47.556999],"type":"Point"}
}