{
  "type": "Feature",
  "properties": {
    "iso:country":"CH",
    "sg:address":"Via Della Pace 16",
    "sg:city":"Locarno",
    "sg:orig_category":"Herstellung von sonstigen Fahrzeugen Schiffsbau ohne Boots U Yachtbau",
    "sg:phone":"+41 91 751 66 18",
    "sg:postcode":"6600",
    "sg:province":"Ticino",
    "wof:name":"Marjan Shipping Services Ltd",
    "wof:placetype":"venue"
},
  "geometry": {"coordinates":[8.7991876602,46.1662750244],"type":"Point"}
}