{
  "type": "Feature",
  "properties": {
    "iso:country":"CH",
    "sg:address":"1712",
    "sg:city":"Tafers",
    "sg:orig_category":"Zimmerei, Dachdeckerei, Bauspenglerei U Abdichtung",
    "sg:phone":"+41 26 494 14 16",
    "sg:postcode":"1712",
    "sg:province":"Fribourg",
    "wof:name":"P. Zbinden Ag",
    "wof:placetype":"venue"
},
  "geometry": {"coordinates":[7.2158999443,46.8150558472],"type":"Point"}
}