{
  "type": "Feature",
  "properties": {
    "iso:country":"CH",
    "sg:address":"Via Bagutti 39",
    "sg:city":"Lugano",
    "sg:orig_category":"Allgemeiner Hoch U Tiefbau",
    "sg:postcode":"6900",
    "sg:province":"Ticino",
    "wof:name":"Grassi Alberto",
    "wof:placetype":"venue"
},
  "geometry": {"coordinates":[8.95641,46.01561],"type":"Point"}
}