{
  "type": "Feature",
  "properties": {
    "iso:country":"CH",
    "sg:address":"Seestrasse 14",
    "sg:city":"Horn",
    "sg:orig_category":"Non-Classified Establishments",
    "sg:phone":"+41 71 845 19 45",
    "sg:postcode":"9326",
    "sg:province":"Thurgau",
    "wof:name":"Raduner Gartenbau Ag",
    "wof:placetype":"venue"
},
  "geometry": {"coordinates":[9.4740047455,47.4906005859],"type":"Point"}
}