{
  "type": "Feature",
  "properties": {
    "iso:country":"CH",
    "sg:address":"1324",
    "sg:city":"Premier",
    "sg:orig_category":"Unclassifiable Establishments",
    "sg:phone":"+41 24 453 16 47",
    "sg:postcode":"1324",
    "sg:province":"Vaud",
    "wof:name":"Cst Chauvie Francis",
    "wof:placetype":"venue"
},
  "geometry": {"coordinates":[6.4468917847,46.7038993835],"type":"Point"}
}