{
  "type": "Feature",
  "properties": {
    "iso:country":"CH",
    "sg:address":"Via Calprino 7",
    "sg:city":"Paradiso",
    "sg:orig_category":"Unclassifiable Establishments",
    "sg:postcode":"6900",
    "sg:province":"Ticino",
    "wof:name":"Macaluso Marco Trasporti Sagl",
    "wof:placetype":"venue"
},
  "geometry": {"coordinates":[8.9408912659,45.9886894226],"type":"Point"}
}