{
  "type": "Feature",
  "properties": {
    "iso:country":"CH",
    "sg:address":"Kanzleistrasse 80",
    "sg:city":"Z\u00fcrich",
    "sg:orig_category":"Vermittlungen Wohnungs-Agenturen,",
    "sg:postcode":"8004",
    "sg:province":"Z\u00fcrich",
    "wof:name":"Stiftung Domicil, Gemeinn\u00fctzige Wohnungsvermittlung Und Verwaltung Z\u00fcrich",
    "wof:placetype":"venue"
},
  "geometry": {"coordinates":[8.5242462158,47.3757095337],"type":"Point"}
}