{
  "type": "Feature",
  "properties": {
    "iso:country":"CH",
    "sg:address":"Wannengut 9",
    "sg:city":"M\u00fchlethal",
    "sg:orig_category":"Werbeagenturen Werbung",
    "sg:phone":"+41 62 752 85 60",
    "sg:postcode":"4812",
    "sg:province":"Aargau",
    "wof:name":"Taudien Manfred Mt-werbeagentur",
    "wof:placetype":"venue"
},
  "geometry": {"coordinates":[7.9710822105,47.3026351929],"type":"Point"}
}