{
  "type": "Feature",
  "properties": {
    "iso:country":"CH",
    "sg:address":"Rte De La Piscine 1934 Le Ch\u00e2ble Vs. Postfach",
    "sg:city":"Verbier",
    "sg:orig_category":"Wirtschaftspr\u00fcfung, Steuerberatung U Treuhand",
    "sg:postcode":"1936",
    "sg:province":"Valais",
    "wof:name":"Chapuis Pierre",
    "wof:placetype":"venue"
},
  "geometry": {"coordinates":[7.2124481201,46.0804595947],"type":"Point"}
}