{
  "type": "Feature",
  "properties": {
    "iso:country":"CH",
    "sg:address":"Roule Route Du 47 1723 Marly. Postfach",
    "sg:city":"Marly",
    "sg:orig_category":"Schreib U \u00dcbersetzungsb\u00fcros",
    "sg:phone":"+41 26 670 44 38",
    "sg:postcode":"1723",
    "sg:province":"Fribourg",
    "wof:name":"Lamia-m\u00e4der Charlotte",
    "wof:placetype":"venue"
},
  "geometry": {"coordinates":[7.1084527969,46.9252319336],"type":"Point"}
}