{
  "type": "Feature",
  "properties": {
    "iso:country":"CH",
    "sg:address":"Industriestrasse",
    "sg:city":"Inwil",
    "sg:classifiers":[
        {
            "category":"Wholesale",
            "subcategory":"Plants",
            "type":"Manufacturing & Wholesale Goods"
        }
    ],
    "sg:phone":"+41 41 449 06 06",
    "sg:postcode":"6034",
    "sg:province":"Luzern",
    "sg:tags":[
        "decoration",
        "potted",
        "premise"
    ],
    "wof:name":"Waller Begr\u00fcnungssysteme Ag",
    "wof:placetype":"venue"
},
  "geometry": {"coordinates":[8.349338,47.118168],"type":"Point"}
}