{
  "type": "Feature",
  "properties": {
    "iso:country":"CH",
    "sg:address":"Grundstrasse 12",
    "sg:city":"Rotkreuz",
    "sg:orig_category":"Unclassifiable Establishments",
    "sg:postcode":"6343",
    "sg:province":"Zug",
    "wof:name":"Maiba Ag",
    "wof:placetype":"venue"
},
  "geometry": {"coordinates":[8.4302759171,47.145690918],"type":"Point"}
}