{
  "type": "Feature",
  "properties": {
    "iso:country":"CH",
    "sg:address":"Holenackerstrasse 5",
    "sg:city":"Bern",
    "sg:orig_category":"Stukkateurgewerbe, Gipserei U Verputzerei",
    "sg:phone":"+41 79 607 21 41",
    "sg:postcode":"3027",
    "sg:province":"Bern",
    "wof:name":"Tekari Ag",
    "wof:placetype":"venue"
},
  "geometry": {"coordinates":[7.380628109,46.9492111206],"type":"Point"}
}