{
  "type": "Feature",
  "properties": {
    "iso:country":"CH",
    "sg:address":"Vigne Via Delle 8",
    "sg:city":"Minusio",
    "sg:orig_category":"Interessenvertretungen",
    "sg:postcode":"6648",
    "sg:province":"Ticino",
    "wof:name":"Fondazione Joro",
    "wof:placetype":"venue"
},
  "geometry": {"coordinates":[8.8105106354,46.1786155701],"type":"Point"}
}