{
  "type": "Feature",
  "properties": {
    "iso:country":"CH",
    "sg:address":"Via Rivapiana 20a",
    "sg:city":"Minusio",
    "sg:orig_category":"Sonstige mit der Informatik verbundene T\u00e4tigkeiten",
    "sg:postcode":"6648",
    "sg:province":"Ticino",
    "wof:name":"Djm Consulting M\u00fcller Daniel J.",
    "wof:placetype":"venue"
},
  "geometry": {"coordinates":[8.8118066788,46.1726074219],"type":"Point"}
}