{
  "type": "Feature",
  "properties": {
    "iso:country":"CH",
    "sg:address":"Colline Chemin De La 24",
    "sg:city":"Yverdon-les-bains",
    "sg:orig_category":"Softwareentwicklung U beratung",
    "sg:phone":"+41 62 836 35 25",
    "sg:postcode":"1400",
    "sg:province":"Vaud",
    "wof:name":"Restorage Gmbh",
    "wof:placetype":"venue"
},
  "geometry": {"coordinates":[8.0689182281,47.3918495178],"type":"Point"}
}