{
  "type": "Feature",
  "properties": {
    "iso:country":"CH",
    "sg:address":"Corso San Gottardo 14",
    "sg:city":"Chiasso",
    "sg:orig_category":"Gartenbau Grosshandel mit Obst U Gem\u00fcse",
    "sg:phone":"+41 21 944 27 42",
    "sg:postcode":"6830",
    "sg:province":"Ticino",
    "wof:name":"Angelo L. Angeli Champignons",
    "wof:placetype":"venue"
},
  "geometry": {"coordinates":[6.8606348038,46.4539299011],"type":"Point"}
}