{
  "type": "Feature",
  "properties": {
    "iso:country":"CH",
    "sg:address":"Pilatusstrasse 19",
    "sg:city":"Muri",
    "sg:classifiers":[
        {
            "category":"Government",
            "subcategory":"Post Office",
            "type":"Public Place"
        }
    ],
    "sg:phone":"+41 56 675 44 55",
    "sg:postcode":"5630",
    "sg:province":"Aargau",
    "sg:tags":[
        "packaging",
        "cd"
    ],
    "wof:name":"Awm Plastpack Ag",
    "wof:placetype":"venue"
},
  "geometry": {"coordinates":[8.3519077301,47.2617607117],"type":"Point"}
}