{
  "type": "Feature",
  "properties": {
    "iso:country":"CH",
    "sg:address":"Feldeggstrasse 49",
    "sg:city":"Z\u00fcrich",
    "sg:orig_category":"Grosshandel mit Textilien Grosshandel mit sonstigen Konsumg\u00fctern",
    "sg:postcode":"8008",
    "sg:province":"Z\u00fcrich",
    "wof:name":"Jegen Textilien Ag",
    "wof:placetype":"venue"
},
  "geometry": {"coordinates":[8.5446939468,47.2871627808],"type":"Point"}
}