{
  "type": "Feature",
  "properties": {
    "iso:country":"CH",
    "sg:address":"Pl. De La R\u00e9unification",
    "sg:city":"Saignel\u00e9gier",
    "sg:orig_category":"Fachdetailhandel in Verkaufsr\u00e4umen",
    "sg:phone":"+41 71 744 70 10",
    "sg:postcode":"2350",
    "sg:province":"Jura",
    "wof:name":"Frommenwiler Roman",
    "wof:placetype":"venue"
},
  "geometry": {"coordinates":[9.6223802567,47.4521408081],"type":"Point"}
}