{
  "type": "Feature",
  "properties": {
    "iso:country":"CH",
    "sg:address":"Buchzopfen 14",
    "sg:city":"Lyss",
    "sg:orig_category":"Sportvereine Velo Rad-& Motorfahrer-Bund SRB",
    "sg:phone":"+41 32 384 49 69",
    "sg:postcode":"3250",
    "sg:province":"Bern",
    "wof:name":"Velo-club Lyss",
    "wof:placetype":"venue"
},
  "geometry": {"coordinates":[7.3026499748,47.080909729],"type":"Point"}
}