{
  "type": "Feature",
  "properties": {
    "iso:country":"CH",
    "sg:address":"Rheinweg 25. 8212 Neuhausen. Postfach",
    "sg:city":"Schaffhausen",
    "sg:orig_category":"Sonstiges Versicherungsgewerbe",
    "sg:phone":"+41 22 321 91 02",
    "sg:postcode":"8201",
    "sg:province":"Schaffhausen",
    "wof:name":"Bureau D'assistances Marc Leuba Sa",
    "wof:placetype":"venue"
},
  "geometry": {"coordinates":[6.1381139755,46.1986579895],"type":"Point"}
}