{
  "type": "Feature",
  "properties": {
    "iso:country":"CH",
    "sg:address":"Lac Rue Du 29",
    "sg:city":"B\u00f4le",
    "sg:orig_category":"Herstellung von elektronischen Bauelementen",
    "sg:postcode":"2014",
    "sg:province":"Neuch\u00e2tel",
    "wof:name":"Ads Technologies S\u00e0rl",
    "wof:placetype":"venue"
},
  "geometry": {"coordinates":[6.841509819,46.9673309326],"type":"Point"}
}