{
  "type": "Feature",
  "properties": {
    "addr:full":"Industriestrasse 5 Effretikon Z\u00fcrich 8307",
    "addr:housenumber":"5",
    "addr:postcode":"8307",
    "addr:street":"Industriestrasse",
    "iso:country":"CH",
    "sg:address":"Industriestrasse 5",
    "sg:city":"Effretikon",
    "sg:orig_category":"Architektur U Ingenieurb\u00fcros",
    "sg:phone":"+41 52 343 16 95",
    "sg:postcode":"8307",
    "sg:province":"Z\u00fcrich",
    "wof:name":"Ingenieurb\u00fcro Ernst Hug",
    "wof:placetype":"venue"
},
  "geometry": {"coordinates":[8.683087,47.419247],"type":"Point"}
}