{
  "type": "Feature",
  "properties": {
    "iso:country":"CH",
    "sg:address":"Via Da Sotsassa 41a",
    "sg:city":"Poschiavo",
    "sg:orig_category":"Vorschulen, Kinderg\u00e4rten",
    "sg:postcode":"7742",
    "sg:province":"Graubunden",
    "wof:name":"Scuola Dell'infanzia",
    "wof:placetype":"venue"
},
  "geometry": {"coordinates":[10.0588884354,46.3261070251],"type":"Point"}
}