{
  "type": "Feature",
  "properties": {
    "iso:country":"CH",
    "sg:address":"2113",
    "sg:city":"Boveresse",
    "sg:orig_category":"G\u00fcterbef\u00f6rderung im Strassenverkehr",
    "sg:phone":"+41 32 861 12 12",
    "sg:postcode":"2113",
    "sg:province":"Neuch\u00e2tel",
    "wof:name":"Roger Erb Petits D\u00e9m\u00e9nagements",
    "wof:placetype":"venue"
},
  "geometry": {"coordinates":[6.5982999802,46.9174690247],"type":"Point"}
}