{
  "type": "Feature",
  "properties": {
    "iso:country":"CH",
    "sg:address":"Truttikerstrasse 6",
    "sg:city":"Ossingen",
    "sg:orig_category":"Herstellung von Elektromotoren, Generatoren U Transformatoren",
    "sg:phone":"+41 52 317 42 51",
    "sg:postcode":"8475",
    "sg:province":"Z\u00fcrich",
    "wof:name":"\u00e0 Porta Allround Montagen",
    "wof:placetype":"venue"
},
  "geometry": {"coordinates":[8.7263965607,47.612159729],"type":"Point"}
}