{
  "type": "Feature",
  "properties": {
    "iso:country":"CH",
    "sg:address":"Chemin De Rov\u00e9r\u00e9az 60",
    "sg:city":"Lausanne",
    "sg:orig_category":"Arztpraxen",
    "sg:phone":"+41 21 622 89 77",
    "sg:postcode":"1012",
    "sg:province":"Vaud",
    "wof:name":"Dr M\u00e9d. Michael Sturzenegger M\u00e9decin Sp\u00e9cialiste Fmh",
    "wof:placetype":"venue"
},
  "geometry": {"coordinates":[6.600932,46.518311],"type":"Point"}
}