{
  "type": "Feature",
  "properties": {
    "iso:country":"CH",
    "sg:address":"Hauptstrasse",
    "sg:city":"Mitl\u00f6di",
    "sg:orig_category":"Detailhandel mit Fleisch U Fleischwaren",
    "sg:phone":"+41 55 644 12 31",
    "sg:postcode":"8756",
    "sg:province":"Glarus",
    "wof:name":"Peter Menzi Metzgerei",
    "wof:placetype":"venue"
},
  "geometry": {"coordinates":[9.0813398361,47.0123405457],"type":"Point"}
}