{
  "type": "Feature",
  "properties": {
    "iso:country":"CH",
    "sg:address":"Rue Des M\u00e9sanges 11",
    "sg:city":"Reconvilier",
    "sg:classifiers":[
        {
            "category":"Insurance",
            "subcategory":"Insurance Agent",
            "type":"Services"
        }
    ],
    "sg:phone":"+41 32 481 42 57",
    "sg:postcode":"2732",
    "sg:province":"Bern",
    "sg:tags":[
        "versicherungsagenturen",
        "-broker"
    ],
    "wof:name":"Winterthur-assurances Agence",
    "wof:placetype":"venue"
},
  "geometry": {"coordinates":[7.2208042145,47.2375679016],"type":"Point"}
}