{
  "type": "Feature",
  "properties": {
    "iso:country":"CH",
    "sg:address":"Levant Rue Du 22",
    "sg:city":"Ste-croix",
    "sg:orig_category":"Stukkateurgewerbe, Gipserei U Verputzerei",
    "sg:phone":"+41 21 841 12 53",
    "sg:postcode":"1450",
    "sg:province":"Vaud",
    "wof:name":"Juriens Marc-henri",
    "wof:placetype":"venue"
},
  "geometry": {"coordinates":[6.3256230354,46.6680374146],"type":"Point"}
}