{
  "type": "Feature",
  "properties": {
    "iso:country":"CH",
    "sg:address":"Riedernstrasse 10",
    "sg:city":"Glarus",
    "sg:orig_category":"Unternehmensberatung",
    "sg:phone":"+41 12020072",
    "sg:postcode":"8750",
    "sg:province":"Glarus",
    "wof:name":"Hnw Family Office Ag",
    "wof:placetype":"venue"
},
  "geometry": {"coordinates":[8.5917100906,47.3025398254],"type":"Point"}
}