{
  "type": "Feature",
  "properties": {
    "iso:country":"CH",
    "sg:address":"9033",
    "sg:city":"Untereggen",
    "sg:orig_category":"Sportvereine Sch\u00fctzen",
    "sg:phone":"+41 81 738 25 83",
    "sg:postcode":"9033",
    "sg:province":"St. Gallen",
    "wof:name":"Milit\u00e4rsch\u00fctzenverein",
    "wof:placetype":"venue"
},
  "geometry": {"coordinates":[9.4515609741,47.4548149109],"type":"Point"}
}