{
  "type": "Feature",
  "properties": {
    "iso:country":"CH",
    "sg:address":"Wallstrasse 22 4051 Basel. Postfach",
    "sg:city":"Basel",
    "sg:orig_category":"Fernmeldedienste",
    "sg:phone":"+41 61 285 51 11",
    "sg:postcode":"4002",
    "sg:province":"Basel-Stadt",
    "wof:name":"Swisscom Directories Ag",
    "wof:placetype":"venue"
},
  "geometry": {"coordinates":[7.5888729095,47.5503959656],"type":"Point"}
}