{
  "type": "Feature",
  "properties": {
    "iso:country":"CH",
    "sg:address":"Bittertenstrasse 12 4702 Oensingen. Postfach",
    "sg:city":"Oensingen",
    "sg:orig_category":"Abfallbeseitigung Bau von Strassen, Sportanlagen U Bahnverkehrsstrecken",
    "sg:phone":"+41 18506677",
    "sg:postcode":"4702",
    "sg:province":"Solothurn",
    "wof:name":"Entsorga Ag",
    "wof:placetype":"venue"
},
  "geometry": {"coordinates":[8.502137,47.481888],"type":"Point"}
}