{
  "type": "Feature",
  "properties": {
    "addr:full":"Aarburgerstrasse 21 Zofingen Aargau 4800",
    "addr:housenumber":"21",
    "addr:postcode":"4800",
    "addr:street":"Aarburgerstrasse",
    "iso:country":"CH",
    "sg:address":"Aarburgerstrasse 21",
    "sg:city":"Zofingen",
    "sg:orig_category":"Architektur U Ingenieurb\u00fcros",
    "sg:phone":"+41 62 745 88 00",
    "sg:postcode":"4800",
    "sg:province":"Aargau",
    "wof:name":"Plast Competence Center Ag",
    "wof:placetype":"venue"
},
  "geometry": {"coordinates":[7.939527,47.293518],"type":"Point"}
}