{
  "type": "Feature",
  "properties": {
    "iso:country":"CH",
    "sg:address":"Wolfgrubenstrasse 22b",
    "sg:city":"K\u00f6lliken",
    "sg:orig_category":"Sportvereine Eissport Eishockey",
    "sg:phone":"+41 27 473 40 44",
    "sg:postcode":"5742",
    "sg:province":"Aargau",
    "wof:name":"Hc Sierre Fan Club,sekt.leuk",
    "wof:placetype":"venue"
},
  "geometry": {"coordinates":[8.0248775482,47.3410072327],"type":"Point"}
}