{
  "type": "Feature",
  "properties": {
    "iso:country":"CH",
    "sg:address":"Linerhofweg",
    "sg:city":"Engelburg",
    "sg:orig_category":"Selbst\u00e4ndige bildende K\u00fcnstler",
    "sg:phone":"+41 71 278 28 33",
    "sg:postcode":"9032",
    "sg:province":"St. Gallen",
    "wof:name":"Heinrich St\u00e4ubli Glasmalerei",
    "wof:placetype":"venue"
},
  "geometry": {"coordinates":[9.3441648483,47.4431838989],"type":"Point"}
}