{
  "type": "Feature",
  "properties": {
    "iso:country":"CH",
    "sg:address":"Seestrasse 36",
    "sg:city":"Horn",
    "sg:classifiers":[
        {
            "category":"Travel",
            "subcategory":"Hotels & Motels",
            "type":"Entertainment"
        }
    ],
    "sg:phone":"+41 71 841 55 11",
    "sg:postcode":"9326",
    "sg:province":"Thurgau",
    "sg:tags":[
        "hotels",
        "mit",
        "restaurant"
    ],
    "wof:name":"Hotel Bad Horn",
    "wof:placetype":"venue"
},
  "geometry": {"coordinates":[9.4682035446,47.4945335388],"type":"Point"}
}