{
  "type": "Feature",
  "properties": {
    "iso:country":"CH",
    "sg:address":"Fl\u00fcelastrasse 47",
    "sg:city":"Z\u00fcrich",
    "sg:orig_category":"Sprachschulen",
    "sg:phone":"+41 14013901",
    "sg:postcode":"8047",
    "sg:province":"Z\u00fcrich",
    "wof:name":"Dialogica Z\u00fcrich, Schirmer J.-p.",
    "wof:placetype":"venue"
},
  "geometry": {"coordinates":[8.4944829941,47.3810195923],"type":"Point"}
}