{
  "type": "Feature",
  "properties": {
    "iso:country":"CH",
    "sg:address":"Via Camminata 5",
    "sg:city":"Bellinzona",
    "sg:orig_category":"Zahntechnische Laboratorien",
    "sg:phone":"+41 62 771 10 32",
    "sg:postcode":"6500",
    "sg:province":"Ticino",
    "wof:name":"Arnold Graf Dental Labor",
    "wof:placetype":"venue"
},
  "geometry": {"coordinates":[8.2070140839,47.2685546875],"type":"Point"}
}