{
  "type": "Feature",
  "properties": {
    "iso:country":"CH",
    "sg:address":"Place De Rome 5",
    "sg:city":"Martigny",
    "sg:orig_category":"Mechanik",
    "sg:phone":"+41 79 406 38 36",
    "sg:postcode":"1920",
    "sg:province":"Valais",
    "wof:name":"Vascom, M. Vasic",
    "wof:placetype":"venue"
},
  "geometry": {"coordinates":[9.3948173523,47.5010681152],"type":"Point"}
}