{
  "type": "Feature",
  "properties": {
    "iso:country":"CH",
    "sg:address":"Bernstrasse 75 4852 Rothrist. Postfach 175",
    "sg:city":"Rothrist",
    "sg:orig_category":"Fachdetailhandel mit pharmazeutischen Produkten",
    "sg:phone":"+41 79 647 77 77",
    "sg:postcode":"4852",
    "sg:province":"Aargau",
    "wof:name":"Apotheke Rothrist J\u00f6rg Fidel",
    "wof:placetype":"venue"
},
  "geometry": {"coordinates":[7.8960371017,47.3046226501],"type":"Point"}
}