{
  "type": "Feature",
  "properties": {
    "iso:country":"CH",
    "sg:address":"Chemin Du Fau-blanc 20e",
    "sg:city":"Pully",
    "sg:orig_category":"Vermietung U Verpachtung von eigenen Immobilien",
    "sg:postcode":"1009",
    "sg:province":"Vaud",
    "wof:name":"Au Planoz C Sa",
    "wof:placetype":"venue"
},
  "geometry": {"coordinates":[6.6610951424,46.513923645],"type":"Point"}
}