{
  "type": "Feature",
  "properties": {
    "iso:country":"CH",
    "sg:address":"Route De La Clochatte 88",
    "sg:city":"Mont-sur-lausanne",
    "sg:orig_category":"Institutionen f\u00fcr Suchtkranke",
    "sg:phone":"+41 21 651 99 51",
    "sg:postcode":"1052",
    "sg:province":"Vaud",
    "wof:name":"Centre D'alcoologie Fondation Les Oliviers",
    "wof:placetype":"venue"
},
  "geometry": {"coordinates":[6.6401901245,46.5457305908],"type":"Point"}
}