{
  "type": "Feature",
  "properties": {
    "iso:country":"CH",
    "sg:address":"Kirchgasse 1",
    "sg:city":"Weinfelden",
    "sg:orig_category":"Kosmetikinstitute",
    "sg:phone":"+41 71 622 71 90",
    "sg:postcode":"8570",
    "sg:province":"Thurgau",
    "wof:name":"Elisabeth F\u00fcllemann Pendzic Institut New Cosmetics",
    "wof:placetype":"venue"
},
  "geometry": {"coordinates":[9.1105003357,47.5684738159],"type":"Point"}
}