{
  "type": "Feature",
  "properties": {
    "iso:country":"CH",
    "sg:address":"Chemin Du Bosquet 1 1030 Bussigny-lausanne Case Postale 161",
    "sg:city":"Bussigny-lausanne",
    "sg:orig_category":"Wirtschaftspr\u00fcfung, Steuerberatung U Treuhand",
    "sg:postcode":"1030",
    "sg:province":"Vaud",
    "wof:name":"Fiduciaire Chevalier St\u00e9phane",
    "wof:placetype":"venue"
},
  "geometry": {"coordinates":[6.9295902252,46.3618087769],"type":"Point"}
}