{
  "type": "Feature",
  "properties": {
    "iso:country":"CH",
    "sg:address":"Avenue Agassiz 2",
    "sg:city":"Lausanne",
    "sg:orig_category":"Arbeitnehmerverb\u00e4nde",
    "sg:phone":"+41 21 319 71 11",
    "sg:postcode":"1003",
    "sg:province":"Vaud",
    "wof:name":"Groupement Vaudois Des Professions De La Sant\u00e9",
    "wof:placetype":"venue"
},
  "geometry": {"coordinates":[6.631735,46.51812],"type":"Point"}
}