{
  "type": "Feature",
  "properties": {
    "iso:country":"CH",
    "sg:address":"Altishoferstrasse 2 6252 Dagmersellen. Postfach",
    "sg:city":"Dagmersellen",
    "sg:orig_category":"Veterin\u00e4rwesen",
    "sg:postcode":"6252",
    "sg:province":"Luzern",
    "wof:name":"Tierarztpraxis Am R\u00f6ssliplatz Ag Kleintier, Grosstierpraxis. Dienstleistungen In Der Tierseuchenbek\u00e4mpfung Und Fleischkontrolle Usw",
    "wof:placetype":"venue"
},
  "geometry": {"coordinates":[7.9889378548,47.2127304077],"type":"Point"}
}