{
  "type": "Feature",
  "properties": {
    "addr:full":"Bahnhofstrasse 6 6410 Goldau. Postfach Goldau Schwyz 6410",
    "addr:housenumber":"6",
    "addr:postcode":"6410 goldau. postfach;6410",
    "addr:street":"Bahnhofstrasse",
    "iso:country":"CH",
    "sg:address":"Bahnhofstrasse 6 6410 Goldau. Postfach",
    "sg:city":"Goldau",
    "sg:orig_category":"Detailhandel mit B\u00fcchern, Zeitungen, Schreib U Papeteriewaren",
    "sg:phone":"+41 41 855 55 80",
    "sg:postcode":"6410",
    "sg:province":"Schwyz",
    "wof:name":"Spichtig + Tsch\u00fcmperlin Maria + Adalbert, B\u00fcecherlade Goldau",
    "wof:placetype":"venue"
},
  "geometry": {"coordinates":[8.546839,47.049629],"type":"Point"}
}