{
  "type": "Feature",
  "properties": {
    "iso:country":"CH",
    "sg:address":"Buchserh\u00fcbeli 5",
    "sg:city":"Seengen",
    "sg:orig_category":"Detailhandel mit Brot, Back U S\u00fcsswaren",
    "sg:phone":"+41 62 777 22 09",
    "sg:postcode":"5707",
    "sg:province":"Aargau",
    "wof:name":"B\u00e4ckerei-konditorei Studler Ag",
    "wof:placetype":"venue"
},
  "geometry": {"coordinates":[8.203227,47.325424],"type":"Point"}
}