{
  "type": "Feature",
  "properties": {
    "iso:country":"CH",
    "sg:address":"Rehhagstrasse 55 3018 Bern. Postfach",
    "sg:city":"Bern",
    "sg:orig_category":"Fachdetailhandel in Verkaufsr\u00e4umen",
    "sg:phone":"+41 31 981 34 94",
    "sg:postcode":"3018",
    "sg:province":"Bern",
    "wof:name":"Impression Kohout Thomas + Co Blumendekorationen",
    "wof:placetype":"venue"
},
  "geometry": {"coordinates":[7.3865470886,46.9357948303],"type":"Point"}
}