{
  "type": "Feature",
  "properties": {
    "iso:country":"CH",
    "sg:address":"Hauptstrasse 30 6387 Oberrickenbach. Postfach",
    "sg:city":"Oberrickenbach",
    "sg:orig_category":"Zimmerei, Dachdeckerei, Bauspenglerei U Abdichtung",
    "sg:postcode":"6387",
    "sg:province":"Nidwalden",
    "wof:name":"Holzbearbeitung Schmitter",
    "wof:placetype":"venue"
},
  "geometry": {"coordinates":[8.3898601532,46.8960189819],"type":"Point"}
}