{
  "type": "Feature",
  "properties": {
    "iso:country":"CH",
    "sg:address":"Avenue Louis-casa\u00ef 54",
    "sg:city":"Cointrin",
    "sg:classifiers":[
        {
            "category":"Restaurant",
            "type":"Food & Drink"
        }
    ],
    "sg:phone":"+41 17153830",
    "sg:postcode":"1216",
    "sg:province":"Gen\u00e8ve",
    "wof:name":"Bendliker Trotte Restaurant Zur",
    "wof:placetype":"venue"
},
  "geometry": {"coordinates":[8.5500421524,47.3225135803],"type":"Point"}
}