{
  "type": "Feature",
  "properties": {
    "iso:country":"CH",
    "sg:address":"Im Zelgli 12a",
    "sg:city":"Hettlingen",
    "sg:orig_category":"Maler U Glasergewerbe Malerei",
    "sg:phone":"+41 52 316 18 41",
    "sg:postcode":"8442",
    "sg:province":"Z\u00fcrich",
    "wof:name":"Malergesch\u00e4ft Khangsar",
    "wof:placetype":"venue"
},
  "geometry": {"coordinates":[8.7108240128,47.5452651978],"type":"Point"}
}