{
  "type": "Feature",
  "properties": {
    "addr:full":"Route De Montreux 7 Ch\u00e2tel-st-denis Fribourg 1618",
    "addr:housenumber":"7",
    "addr:postcode":"1618",
    "addr:street":"Route De Montreux",
    "iso:country":"CH",
    "sg:address":"Route De Montreux 7",
    "sg:city":"Ch\u00e2tel-st-denis",
    "sg:classifiers":[
        {
            "category":"Bars & Pubs",
            "type":"Food & Drink"
        }
    ],
    "sg:phone":"+41 21 948 82 95",
    "sg:postcode":"1618",
    "sg:province":"Fribourg",
    "wof:name":"Bar Havana",
    "wof:placetype":"venue"
},
  "geometry": {"coordinates":[6.901692,46.527012],"type":"Point"}
}