{
  "type": "Feature",
  "properties": {
    "iso:country":"CH",
    "sg:address":"Islisbergstrasse 21",
    "sg:city":"Bonstetten",
    "sg:orig_category":"Kunsthandel",
    "sg:phone":"+41 17001919",
    "sg:postcode":"8906",
    "sg:province":"Z\u00fcrich",
    "wof:name":"Anton Seiler Galerie",
    "wof:placetype":"venue"
},
  "geometry": {"coordinates":[8.4521665573,47.3181343079],"type":"Point"}
}