{
  "type": "Feature",
  "properties": {
    "iso:country":"CH",
    "sg:address":"Lindenstrasse 11",
    "sg:city":"Oekingen",
    "sg:orig_category":"Sonstige mit der Informatik verbundene T\u00e4tigkeiten",
    "sg:phone":"+41 32 675 01 10",
    "sg:postcode":"4566",
    "sg:province":"Solothurn",
    "wof:name":"Cpn Informatik R. W\u00e4lchli",
    "wof:placetype":"venue"
},
  "geometry": {"coordinates":[7.6025819778,47.1780471802],"type":"Point"}
}