{
  "type": "Feature",
  "properties": {
    "iso:country":"CH",
    "sg:address":"Wasenstrasse 27",
    "sg:city":"Kreuzlingen",
    "sg:classifiers":[
        {
            "category":"Social Services",
            "subcategory":"Retirement Home",
            "type":"Services"
        }
    ],
    "sg:phone":"+41 71 688 54 55",
    "sg:postcode":"8280",
    "sg:province":"Thurgau",
    "sg:tags":[
        "pflegeheime",
        "u",
        "alters"
    ],
    "wof:name":"Alterspension & Pflegeheim Meeresstern",
    "wof:placetype":"venue"
},
  "geometry": {"coordinates":[9.182802,47.645508],"type":"Point"}
}