{
  "type": "Feature",
  "properties": {
    "iso:country":"CH",
    "sg:address":"Gerliswilstrasse 37",
    "sg:city":"Emmenbr\u00fccke",
    "sg:orig_category":"Unclassifiable Establishments",
    "sg:postcode":"6020",
    "sg:province":"Luzern",
    "wof:name":"Digital Druck Shop Lustenberger",
    "wof:placetype":"venue"
},
  "geometry": {"coordinates":[8.2775564194,47.0733451843],"type":"Point"}
}