{
  "type": "Feature",
  "properties": {
    "iso:country":"CH",
    "sg:address":"K\u00e4ppelibodenweg 38",
    "sg:city":"Muttenz",
    "sg:orig_category":"Kosmetikinstitute",
    "sg:phone":"+41 61 461 46 10",
    "sg:postcode":"4132",
    "sg:province":"Basel-Landschaft",
    "wof:name":"Ratana Keller Kosmetikinstitut",
    "wof:placetype":"venue"
},
  "geometry": {"coordinates":[7.6289768219,47.5333786011],"type":"Point"}
}