{
  "type": "Feature",
  "properties": {
    "iso:country":"CH",
    "sg:address":"Webergutstrasse 5",
    "sg:city":"Zollikofen",
    "sg:orig_category":"Fernmeldedienste Herstellung von Radio U Fernsehger\u00e4ten sowie phono U videotechnischen Ger\u00e4ten",
    "sg:phone":"+41 71 310 06 10",
    "sg:postcode":"3052",
    "sg:province":"Bern",
    "wof:name":"Telecom Mettler",
    "wof:placetype":"venue"
},
  "geometry": {"coordinates":[9.3182907104,47.4217071533],"type":"Point"}
}