{
  "type": "Feature",
  "properties": {
    "iso:country":"CH",
    "sg:address":"Rue Neuve 7 1260 Nyon Case Postale 114",
    "sg:city":"Nyon",
    "sg:orig_category":"Versicherungen Generalagenturen",
    "sg:phone":"+41 22 361 44 30",
    "sg:postcode":"1260",
    "sg:province":"Vaud",
    "wof:name":"Generali Assurances",
    "wof:placetype":"venue"
},
  "geometry": {"coordinates":[6.2378821373,46.3830795288],"type":"Point"}
}