{
  "type": "Feature",
  "properties": {
    "iso:country":"CH",
    "sg:address":"Route De Vissigen 72",
    "sg:city":"Sion",
    "sg:classifiers":[
        {
            "category":"Restaurant",
            "type":"Food & Drink"
        }
    ],
    "sg:phone":"+41 27 203 21 20",
    "sg:postcode":"1950",
    "sg:province":"Valais",
    "wof:name":"Restaurant Parc",
    "wof:placetype":"venue"
},
  "geometry": {"coordinates":[7.3725018501,46.2349967957],"type":"Point"}
}