{
  "type": "Feature",
  "properties": {
    "addr:full":"Kr\u00e4hholzweg 3 3324 Hindelbank. Postfach Hindelbank Bern 3324",
    "addr:housenumber":"3",
    "addr:postcode":"3324;3324",
    "addr:street":"Kraehholzweg;Postfach",
    "iso:country":"CH",
    "sg:address":"Kr\u00e4hholzweg 3 3324 Hindelbank. Postfach",
    "sg:city":"Hindelbank",
    "sg:orig_category":"Architektur U Ingenieurb\u00fcros",
    "sg:postcode":"3324",
    "sg:province":"Bern",
    "wof:name":"Processus Immobilier Sa",
    "wof:placetype":"venue"
},
  "geometry": {"coordinates":[6.141425,46.183311],"type":"Point"}
}