{
  "type": "Feature",
  "properties": {
    "iso:country":"CH",
    "sg:address":"Chne-berchtold Rue Du 43",
    "sg:city":"Sion",
    "sg:orig_category":"Erbringung von sonstigen Dienstleistungen f\u00fcr Unterhaltung, Erholung U Freizeit",
    "sg:phone":"+41 41 922 14 57",
    "sg:postcode":"1950",
    "sg:province":"Valais",
    "wof:name":"General Look Management Ldt",
    "wof:placetype":"venue"
},
  "geometry": {"coordinates":[8.0722904205,47.2124214172],"type":"Point"}
}