{
  "type": "Feature",
  "properties": {
    "iso:country":"CH",
    "sg:address":"Fl\u00fcelistrasse 4a",
    "sg:city":"Kerns",
    "sg:orig_category":"Softwareentwicklung U beratung Sonstige mit der Informatik verbundene T\u00e4tigkeiten",
    "sg:phone":"+41 41 410 02 92",
    "sg:postcode":"6064",
    "sg:province":"Obwalden",
    "wof:name":"Sowi Gmbh",
    "wof:placetype":"venue"
},
  "geometry": {"coordinates":[8.2749652863,46.8995361328],"type":"Point"}
}