{
  "type": "Feature",
  "properties": {
    "iso:country":"CH",
    "sg:address":"Stazione Viale 6500 Bellinzona. Postfach Casa Postale",
    "sg:city":"Bellinzona",
    "sg:orig_category":"Politische Vereinigungen",
    "sg:postcode":"6500",
    "sg:province":"Ticino",
    "wof:name":"Unione Sindacale Di Bellinzona E Dintorni",
    "wof:placetype":"venue"
},
  "geometry": {"coordinates":[9.0284891129,46.1951522827],"type":"Point"}
}