{
  "type": "Feature",
  "properties": {
    "iso:country":"CH",
    "sg:address":"Bergstrasse 65",
    "sg:city":"Oberentfelden",
    "sg:orig_category":"Aktivit\u00e4ten der Generalunternehmen im Baugewerbe Erschliessung Kauf U Verkauf von Immobilien",
    "sg:phone":"+41 62 724 05 56",
    "sg:postcode":"5036",
    "sg:province":"Aargau",
    "wof:name":"Landolfi + Fischer Immobilien Und Generalunternehmung Gmbh",
    "wof:placetype":"venue"
},
  "geometry": {"coordinates":[8.061042,47.352264],"type":"Point"}
}