{
  "type": "Feature",
  "properties": {
    "iso:country":"CH",
    "sg:address":"Rosenbergstrasse 23",
    "sg:city":"Zug",
    "sg:orig_category":"Unternehmensberatung",
    "sg:phone":"+41 41 712 15 10",
    "sg:postcode":"6300",
    "sg:province":"Zug",
    "wof:name":"Dr.erika Bernold Consulting",
    "wof:placetype":"venue"
},
  "geometry": {"coordinates":[8.5232620239,47.1668815613],"type":"Point"}
}