{
  "type": "Feature",
  "properties": {
    "iso:country":"CH",
    "sg:address":"Sumatrastrasse 5",
    "sg:city":"Z\u00fcrich",
    "sg:orig_category":"Non-Classified Establishments",
    "sg:phone":"+41 12520094",
    "sg:postcode":"8006",
    "sg:province":"Z\u00fcrich",
    "wof:name":"Keiser-shop Keiser Elektrische Apparate Ag",
    "wof:placetype":"venue"
},
  "geometry": {"coordinates":[8.5433483124,47.3803291321],"type":"Point"}
}