{
  "type": "Feature",
  "properties": {
    "iso:country":"CH",
    "sg:address":"Via Gismonda 10",
    "sg:city":"Mendrisio",
    "sg:orig_category":"Detailhandel mit Schreib U Papeteriewaren Herstellung von Schreibwaren U B\u00fcrobedarf aus Papier, Kart",
    "sg:phone":"+41 71 911 45 65",
    "sg:postcode":"6850",
    "sg:province":"Ticino",
    "wof:name":"Hagen, Papeterie Und B\u00fcrobedarf",
    "wof:placetype":"venue"
},
  "geometry": {"coordinates":[9.0479755402,47.4658584595],"type":"Point"}
}