{
  "type": "Feature",
  "properties": {
    "iso:country":"CH",
    "sg:address":"Waldheim",
    "sg:city":"Ennetmoos",
    "sg:orig_category":"R\u00fcckgewinnung U Vorbereitung f\u00fcr die Wiederverwertung Recycling von Schrott",
    "sg:phone":"+41 41 610 45 05",
    "sg:postcode":"6372",
    "sg:province":"Nidwalden",
    "wof:name":"Tony Karli Autoverwertung",
    "wof:placetype":"venue"
},
  "geometry": {"coordinates":[8.3153877258,46.9393997192],"type":"Point"}
}