{
  "type": "Feature",
  "properties": {
    "iso:country":"CH",
    "sg:address":"Winkelweg 8",
    "sg:city":"Ostermundigen",
    "sg:orig_category":"Grosshandel mit Nahrungsmitteln, Getr\u00e4nken U Tabakwaren ohne ausgepr\u00e4gten Schwerpunkt Grosshandel mi",
    "sg:postcode":"3072",
    "sg:province":"Bern",
    "wof:name":"Fritz Zahnd",
    "wof:placetype":"venue"
},
  "geometry": {"coordinates":[7.4899082184,46.9511489868],"type":"Point"}
}