{
  "type": "Feature",
  "properties": {
    "iso:country":"CH",
    "sg:address":"1222",
    "sg:city":"V\u00e9senaz",
    "sg:orig_category":"Religi\u00f6se Vereinigungen divers",
    "sg:postcode":"1222",
    "sg:province":"Gen\u00e8ve",
    "wof:name":"Cercle Protestant De Carouge",
    "wof:placetype":"venue"
},
  "geometry": {"coordinates":[6.1375799179,46.1852836609],"type":"Point"}
}