{
  "type": "Feature",
  "properties": {
    "iso:country":"CH",
    "sg:address":"Weltpoststrasse 18/165",
    "sg:city":"Bern",
    "sg:orig_category":"Verm\u00f6gensverwaltung",
    "sg:phone":"+41 41 210 29 55",
    "sg:postcode":"3015",
    "sg:province":"Bern",
    "wof:name":"Rosmarie Amrein Verm\u00f6gensverwaltung",
    "wof:placetype":"venue"
},
  "geometry": {"coordinates":[8.3029117584,47.0501785278],"type":"Point"}
}