{
  "type": "Feature",
  "properties": {
    "iso:country":"CH",
    "sg:address":"Soodrain 4",
    "sg:city":"Adliswil",
    "sg:orig_category":"Kosmetikinstitute",
    "sg:phone":"+41 33 951 44 40",
    "sg:postcode":"8134",
    "sg:province":"Z\u00fcrich",
    "wof:name":"Monika Kohler Les Trois Coiffure & Kosmetik",
    "wof:placetype":"venue"
},
  "geometry": {"coordinates":[8.0438308716,46.7544250488],"type":"Point"}
}