{
  "type": "Feature",
  "properties": {
    "iso:country":"CH",
    "sg:address":"Dorfstrasse 3a",
    "sg:city":"Niederbipp",
    "sg:orig_category":"Arztpraxen",
    "sg:phone":"+41 32 633 13 86",
    "sg:postcode":"4704",
    "sg:province":"Bern",
    "wof:name":"Dr.med.rosemarie Hubler Spezial\u00e4rztin Fmh",
    "wof:placetype":"venue"
},
  "geometry": {"coordinates":[7.693756,47.268833],"type":"Point"}
}