{
  "type": "Feature",
  "properties": {
    "iso:country":"CH",
    "sg:address":"Bachstrasse 8",
    "sg:city":"Kreuzlingen",
    "sg:orig_category":"Reiseb\u00fcros U Reiseveranstalter",
    "sg:postcode":"8280",
    "sg:province":"Thurgau",
    "wof:name":"Flug Und Reiseladen Albrecht",
    "wof:placetype":"venue"
},
  "geometry": {"coordinates":[9.169719696,47.6462059021],"type":"Point"}
}