{
  "type": "Feature",
  "properties": {
    "iso:country":"CH",
    "sg:address":"Belalpstrasse 12",
    "sg:city":"Naters",
    "sg:orig_category":"RESTAURANTS: TEA-ROOMS",
    "sg:postcode":"3904",
    "sg:province":"Valais",
    "wof:name":"Restaurant Orni Ag",
    "wof:placetype":"venue"
},
  "geometry": {"coordinates":[7.9883360863,46.3251190186],"type":"Point"}
}