{
  "type": "Feature",
  "properties": {
    "iso:country":"CH",
    "sg:address":"Landstrasse 14",
    "sg:city":"B\u00fctschwil",
    "sg:orig_category":"Architektur U Ingenieurb\u00fcros",
    "sg:phone":"+41 71 983 34 25",
    "sg:postcode":"9606",
    "sg:province":"St. Gallen",
    "wof:name":"Ingenieurb\u00fcro Alex Keller Ag",
    "wof:placetype":"venue"
},
  "geometry": {"coordinates":[9.073518,47.359005],"type":"Point"}
}