{
  "type": "Feature",
  "properties": {
    "iso:country":"CH",
    "sg:address":"Route De Vernier 186 1214 Vernier Case Postale 426",
    "sg:city":"Vernier",
    "sg:orig_category":"Grosshandel mit B\u00fcromaschinen Grosshandel mit B\u00fcromaschinen U einrichtungen",
    "sg:phone":"+41 848 804 904",
    "sg:postcode":"1214",
    "sg:province":"Gen\u00e8ve",
    "wof:name":"Burex Sa",
    "wof:placetype":"venue"
},
  "geometry": {"coordinates":[6.0874080658,46.21717453],"type":"Point"}
}