{
  "type": "Feature",
  "properties": {
    "iso:country":"CH",
    "sg:address":"Haus Solaris",
    "sg:city":"Raron",
    "sg:orig_category":"Sanit\u00e4r, Heizungs U L\u00fcftungsinstallation",
    "sg:phone":"+41 71 636 13 27",
    "sg:postcode":"3942",
    "sg:province":"Valais",
    "wof:name":"Fischbacher Hans",
    "wof:placetype":"venue"
},
  "geometry": {"coordinates":[9.1664276123,47.5733528137],"type":"Point"}
}