{
  "type": "Feature",
  "properties": {
    "iso:country":"CH",
    "sg:address":"Via Trevano 71",
    "sg:city":"Lugano",
    "sg:orig_category":"Kosmetikinstitute",
    "sg:phone":"+41 91 972 63 13",
    "sg:postcode":"6900",
    "sg:province":"Ticino",
    "wof:name":"Giovanna Pellegrino Instituto Di Estetica",
    "wof:placetype":"venue"
},
  "geometry": {"coordinates":[8.9568901062,46.0188293457],"type":"Point"}
}