{
  "type": "Feature",
  "properties": {
    "iso:country":"CH",
    "sg:address":"Bahnhofstrasse 17",
    "sg:city":"Brunnen",
    "sg:orig_category":"Detailhandel mit B\u00fcromaschinen U einrichtungen Schreib U \u00dcbersetzungsb\u00fcros",
    "sg:phone":"+41 41 825 61 61",
    "sg:postcode":"6440",
    "sg:province":"Schwyz",
    "wof:name":"Bos - Business Office Stocker",
    "wof:placetype":"venue"
},
  "geometry": {"coordinates":[8.606072,46.995193],"type":"Point"}
}