{
  "type": "Feature",
  "properties": {
    "iso:country":"CH",
    "sg:address":"1142",
    "sg:city":"Pampigny",
    "sg:orig_category":"Wirtschaftspr\u00fcfung, Steuerberatung U Treuhand",
    "sg:postcode":"1142",
    "sg:province":"Vaud",
    "wof:name":"Fiduciaire Philippe Z\u00fcrcher",
    "wof:placetype":"venue"
},
  "geometry": {"coordinates":[6.4278230667,46.5800819397],"type":"Point"}
}