{
  "type": "Feature",
  "properties": {
    "addr:full":"Hammerstrasse 141 Basel Basel-Stadt 4057",
    "addr:housenumber":"141",
    "addr:postcode":"4057",
    "addr:street":"Hammerstrasse",
    "iso:country":"CH",
    "sg:address":"Hammerstrasse 141",
    "sg:city":"Basel",
    "sg:orig_category":"Detailhandel mit Brot, Back U S\u00fcsswaren",
    "sg:phone":"+41 61 692 46 80",
    "sg:postcode":"4057",
    "sg:province":"Basel-Stadt",
    "wof:name":"Bachstube Ge.m.a. Genossenschaft Mensch & Arbeit",
    "wof:placetype":"venue"
},
  "geometry": {"coordinates":[7.594802,47.567657],"type":"Point"}
}