{
  "type": "Feature",
  "properties": {
    "iso:country":"CH",
    "sg:address":"Doggilochstrasse 1",
    "sg:city":"Klosters",
    "sg:orig_category":"Fuhrhaltereien",
    "sg:phone":"+41 79 405 90 29",
    "sg:postcode":"7250",
    "sg:province":"Graubunden",
    "wof:name":"Christian Fl\u00fctsch Fuhrhalterei",
    "wof:placetype":"venue"
},
  "geometry": {"coordinates":[9.8828468323,46.8646888733],"type":"Point"}
}