{
  "type": "Feature",
  "properties": {
    "iso:country":"CH",
    "sg:address":"Rigiweg 1",
    "sg:city":"Volketswil",
    "sg:orig_category":"Vermittlung von Immobilien Verwaltung von Immobilien",
    "sg:phone":"+41 13859000",
    "sg:postcode":"8604",
    "sg:province":"Z\u00fcrich",
    "wof:name":"Z\u00fcri-see Immobilien Gschwind Bruno, Eidg. Dipl. Immobilien-treuh\u00e4nder",
    "wof:placetype":"venue"
},
  "geometry": {"coordinates":[8.5398006439,47.3320617676],"type":"Point"}
}