{
  "type": "Feature",
  "properties": {
    "iso:country":"CH",
    "sg:address":"Hauptstrasse 53",
    "sg:city":"Frick",
    "sg:orig_category":"Interessenvertretungen",
    "sg:postcode":"5070",
    "sg:province":"Aargau",
    "wof:name":"Stalla Comunitaria Gerra Verzasca",
    "wof:placetype":"venue"
},
  "geometry": {"coordinates":[8.8010902405,46.3217811584],"type":"Point"}
}