{
  "type": "Feature",
  "properties": {
    "iso:country":"CH",
    "sg:address":"Dorfgasse 20 3073 G\u00fcmligen. Postfach",
    "sg:city":"G\u00fcmligen",
    "sg:orig_category":"Allgemeinbildende weiterf\u00fchrende Schulen",
    "sg:postcode":"3073",
    "sg:province":"Bern",
    "wof:name":"The British School Gmbh",
    "wof:placetype":"venue"
},
  "geometry": {"coordinates":[7.51362,46.934292],"type":"Point"}
}