{
  "type": "Feature",
  "properties": {
    "iso:country":"CH",
    "sg:address":"Industriestrasse 9",
    "sg:city":"Nieder\u00f6nz",
    "sg:orig_category":"Non-Classified Establishments",
    "sg:phone":"+41 62 961 31 14",
    "sg:postcode":"3362",
    "sg:province":"Bern",
    "wof:name":"Schweizerischer Schafzuchtverband",
    "wof:placetype":"venue"
},
  "geometry": {"coordinates":[7.6931180954,47.1907997131],"type":"Point"}
}