{
  "type": "Feature",
  "properties": {
    "iso:country":"CH",
    "sg:address":"K\u00e4ppeliweg 72",
    "sg:city":"Muttenz",
    "sg:orig_category":"Maurerarbeiten Sonstiger spezialisierter Hoch U Tiefbau",
    "sg:phone":"+41 61 311 10 35",
    "sg:postcode":"4132",
    "sg:province":"Basel-Landschaft",
    "wof:name":"Zg Minibau-service Zaugg Roger",
    "wof:placetype":"venue"
},
  "geometry": {"coordinates":[7.6250247955,47.5357551575],"type":"Point"}
}