{
  "type": "Feature",
  "properties": {
    "iso:country":"CH",
    "sg:address":"Rue Saint-maurice 7",
    "sg:city":"Del\u00e9mont",
    "sg:orig_category":"Architektur U Ingenieurb\u00fcros Architekturb\u00fcros",
    "sg:phone":"+41 79 422 57 38",
    "sg:postcode":"2800",
    "sg:province":"Jura",
    "wof:name":"Chavanne Etienne Sa",
    "wof:placetype":"venue"
},
  "geometry": {"coordinates":[7.341978,47.352543],"type":"Point"}
}