{
  "type": "Feature",
  "properties": {
    "addr:full":"Treichlerstrasse 4 Z\u00fcrich Z\u00fcrich 8032",
    "addr:housenumber":"4",
    "addr:postcode":"8032",
    "addr:street":"Treichlerstrasse",
    "iso:country":"CH",
    "sg:address":"Treichlerstrasse 4",
    "sg:city":"Z\u00fcrich",
    "sg:orig_category":"Arztpraxen",
    "sg:phone":"+41 12520004",
    "sg:postcode":"8032",
    "sg:province":"Z\u00fcrich",
    "wof:name":"Dr.med.helena Blancpain Spezial\u00e4rztin Fmh",
    "wof:placetype":"venue"
},
  "geometry": {"coordinates":[8.557611,47.370537],"type":"Point"}
}