{
  "type": "Feature",
  "properties": {
    "iso:country":"CH",
    "sg:address":"Rue De La Gare 19 1030 Bussigny-lausanne Case Postale 155",
    "sg:city":"Bussigny-lausanne",
    "sg:orig_category":"Drogerien",
    "sg:phone":"+41 21 701 21 90",
    "sg:postcode":"1030",
    "sg:province":"Vaud",
    "wof:name":"Guy Carrel Droguerie De Bussigny",
    "wof:placetype":"venue"
},
  "geometry": {"coordinates":[6.5524411201,46.5493164062],"type":"Point"}
}