{
  "type": "Feature",
  "properties": {
    "iso:country":"CH",
    "sg:address":"Route De Puidoux 1091 Grandvaux Case Postale 3",
    "sg:city":"Grandvaux",
    "sg:orig_category":"Interessenvertretungen U sonstige Vereinigungen Organisationen der Wohlfahrtspflege",
    "sg:phone":"+41 21 799 30 91",
    "sg:postcode":"1091",
    "sg:province":"Vaud",
    "wof:name":"F\u00e9d.suisse Des Sourds",
    "wof:placetype":"venue"
},
  "geometry": {"coordinates":[6.7259721756,46.4998092651],"type":"Point"}
}