{
  "type": "Feature",
  "properties": {
    "iso:country":"CH",
    "sg:address":"Holzr\u00fcti 2 8840 Einsiedeln. Postfach",
    "sg:city":"Einsiedeln",
    "sg:classifiers":[
        {
            "category":"Professional",
            "subcategory":"Employment Agencies",
            "type":"Services"
        }
    ],
    "sg:phone":"+41 71 222 41 11",
    "sg:postcode":"8840",
    "sg:province":"Schwyz",
    "sg:tags":[
        "personal",
        "u",
        "stellenvermittlung"
    ],
    "wof:name":"Abp Brassel Personalmanagement Beratung & Kaderselektion",
    "wof:placetype":"venue"
},
  "geometry": {"coordinates":[9.3715467453,47.4225196838],"type":"Point"}
}