{
  "type": "Feature",
  "properties": {
    "iso:country":"CH",
    "sg:address":"Bergstrasse 23",
    "sg:city":"Herisau",
    "sg:orig_category":"Tierarztpraxis",
    "sg:phone":"+41 71 352 22 90",
    "sg:postcode":"9100",
    "sg:province":"Appenzell Ausserrhoden",
    "wof:name":"Dr. Med. Vet. Konrad Zemp Tierarzt",
    "wof:placetype":"venue"
},
  "geometry": {"coordinates":[9.2804965973,47.3830795288],"type":"Point"}
}