{
  "type": "Feature",
  "properties": {
    "iso:country":"CH",
    "sg:address":"Weingartenstrasse 21",
    "sg:city":"Naters",
    "sg:orig_category":"Erbringung von sonstigen Dienstleistungen f\u00fcr Unterhaltung, Erholung U Freizeit Konzert- and Theater",
    "sg:phone":"+41 27 923 23 27",
    "sg:postcode":"3904",
    "sg:province":"Valais",
    "wof:name":"D'alpaos Gmbh",
    "wof:placetype":"venue"
},
  "geometry": {"coordinates":[8.0010471344,46.3266716003],"type":"Point"}
}