{
  "type": "Feature",
  "properties": {
    "iso:country":"CH",
    "sg:address":"Eggweg 3",
    "sg:city":"Ormalingen",
    "sg:orig_category":"Massagestudios P\u00e9dicure",
    "sg:phone":"+41 61 981 57 97",
    "sg:postcode":"4466",
    "sg:province":"Basel-Landschaft",
    "wof:name":"Esther Meier & Helen Gersbach",
    "wof:placetype":"venue"
},
  "geometry": {"coordinates":[7.8749299049,47.471534729],"type":"Point"}
}