{
  "type": "Feature",
  "properties": {
    "iso:country":"CH",
    "sg:address":"Bohrerhofstrasse 9",
    "sg:city":"Allschwil",
    "sg:orig_category":"Sanit\u00e4rinstallation",
    "sg:phone":"+41 61 302 51 76",
    "sg:postcode":"4123",
    "sg:province":"Basel-Landschaft",
    "wof:name":"Max Straub Sanit\u00e4r-installationen",
    "wof:placetype":"venue"
},
  "geometry": {"coordinates":[7.5617928505,47.5543708801],"type":"Point"}
}