{
  "type": "Feature",
  "properties": {
    "iso:country":"CH",
    "sg:address":"Badenerstrasse 90",
    "sg:city":"Schlieren",
    "sg:orig_category":"Handel mit Automobilen",
    "sg:phone":"+41 32 373 22 62",
    "sg:postcode":"8952",
    "sg:province":"Z\u00fcrich",
    "wof:name":"Ital Auto S\u00e0rl",
    "wof:placetype":"venue"
},
  "geometry": {"coordinates":[7.2972021103,47.1166877747],"type":"Point"}
}