{
  "type": "Feature",
  "properties": {
    "addr:full":"Rue Des Fahys 9 Neuch\u00e2tel Neuch\u00e2tel 2000",
    "addr:housenumber":"9",
    "addr:postcode":"2000",
    "addr:street":"Rue Des Fahys",
    "iso:country":"CH",
    "sg:address":"Rue Des Fahys 9",
    "sg:city":"Neuch\u00e2tel",
    "sg:orig_category":"Architektur U Ingenieurb\u00fcros",
    "sg:phone":"+41 32 724 64 78",
    "sg:postcode":"2000",
    "sg:province":"Neuch\u00e2tel",
    "wof:name":"Thuillard Jean-pierre, Bureau D'ing\u00e9nieurs Civils Sa",
    "wof:placetype":"venue"
},
  "geometry": {"coordinates":[6.939018,46.998734],"type":"Point"}
}