{
  "type": "Feature",
  "properties": {
    "iso:country":"CH",
    "sg:address":"Route De Nendaz",
    "sg:city":"Salins",
    "sg:orig_category":"Alkoholbrennerei Herstellung von Spirituosen",
    "sg:phone":"+41 27 203 41 82",
    "sg:postcode":"1991",
    "sg:province":"Valais",
    "wof:name":"Denis Sauthier Distillerie De Chandoline",
    "wof:placetype":"venue"
},
  "geometry": {"coordinates":[7.361336,46.218716],"type":"Point"}
}