{
  "type": "Feature",
  "properties": {
    "iso:country":"CH",
    "sg:address":"Platz 1 9100 Herisau. Postfach",
    "sg:city":"Herisau",
    "sg:orig_category":"Versicherungen Hauptagenturen",
    "sg:phone":"+41 71 351 32 93",
    "sg:postcode":"9102",
    "sg:province":"Appenzell Ausserrhoden",
    "wof:name":"Winterthur-versicherungen Hauptagentur",
    "wof:placetype":"venue"
},
  "geometry": {"coordinates":[9.278169632,47.3851013184],"type":"Point"}
}