{
  "type": "Feature",
  "properties": {
    "iso:country":"CH",
    "sg:address":"Bernstrasse 4 4562 Biberist. Postfach 216",
    "sg:city":"Biberist",
    "sg:orig_category":"Interessenvertretungen",
    "sg:postcode":"4562",
    "sg:province":"Solothurn",
    "wof:name":"Moos-flury-stiftung",
    "wof:placetype":"venue"
},
  "geometry": {"coordinates":[7.5566720963,47.1814079285],"type":"Point"}
}