{
  "type": "Feature",
  "properties": {
    "iso:country":"CH",
    "sg:address":"Burghaldenstrasse 19",
    "sg:city":"Lenzburg",
    "sg:orig_category":"Pensionskassen",
    "sg:phone":"+41 62 892 10 88",
    "sg:postcode":"5600",
    "sg:province":"Aargau",
    "wof:name":"Personalf\u00fcrsorge-fonds Der Wgw Immobilien Ag",
    "wof:placetype":"venue"
},
  "geometry": {"coordinates":[8.1795711517,47.3857269287],"type":"Point"}
}