{
  "type": "Feature",
  "properties": {
    "iso:country":"CH",
    "sg:address":"Genolier Route De",
    "sg:city":"Tr\u00e9lex",
    "sg:orig_category":"Herstellung von Teppichen",
    "sg:postcode":"1270",
    "sg:province":"Vaud",
    "wof:name":"Canal Jos\u00e9.",
    "wof:placetype":"venue"
},
  "geometry": {"coordinates":[6.2075648308,46.4184684753],"type":"Point"}
}