{
  "type": "Feature",
  "properties": {
    "iso:country":"CH",
    "sg:address":"Juin Rue Du Vingt-trois 32",
    "sg:city":"Del\u00e9mont",
    "sg:classifiers":[
        {
            "category":"Travel",
            "subcategory":"Hotels & Motels",
            "type":"Entertainment"
        }
    ],
    "sg:phone":"+41 79 310 58 29",
    "sg:postcode":"2800",
    "sg:province":"Jura",
    "sg:tags":[
        "hotels",
        "mit",
        "restaurant"
    ],
    "wof:name":"H\u00f4tel-restaurant La Grappe, New Life Caf\u00e9 S\u00e0rl",
    "wof:placetype":"venue"
},
  "geometry": {"coordinates":[7.1641640663,46.6192207336],"type":"Point"}
}