{
  "type": "Feature",
  "properties": {
    "iso:country":"CH",
    "sg:address":"Etzelstrasse 2",
    "sg:city":"Tuggen",
    "sg:orig_category":"Herstellung von sonstigen landwirtschaftlichen Maschinen Mechanische Werkst\u00e4tten",
    "sg:phone":"+41 79 206 16 84",
    "sg:postcode":"8856",
    "sg:province":"Schwyz",
    "wof:name":"Hummel Gmbh",
    "wof:placetype":"venue"
},
  "geometry": {"coordinates":[8.1524505615,47.5604476929],"type":"Point"}
}