{
  "type": "Feature",
  "properties": {
    "iso:country":"CH",
    "sg:address":"Wilerstrasse 196b",
    "sg:city":"Flawil",
    "sg:classifiers":[
        {
            "category":"Banks & Credit Unions",
            "subcategory":"Bank",
            "type":"Services"
        }
    ],
    "sg:phone":"+41 4171836360",
    "sg:postcode":"9230",
    "sg:province":"St. Gallen",
    "wof:name":"Schweiz. Mobiliar",
    "wof:placetype":"venue"
},
  "geometry": {"coordinates":[9.173159,47.416862],"type":"Point"}
}