{
  "type": "Feature",
  "properties": {
    "iso:country":"CH",
    "sg:address":"Z\u00fcrcherstrasse 125 8952 Schlieren. Postfach",
    "sg:city":"Schlieren",
    "sg:orig_category":"Grosshandel mit Holz U Baustoffen Verlegen von Fliesen U Platten",
    "sg:phone":"+41 17324444",
    "sg:postcode":"8952",
    "sg:province":"Z\u00fcrich",
    "wof:name":"Hg Commerciale Handelsgen. Des Schweiz. Baumeisterverband Sponagel Baukeramik",
    "wof:placetype":"venue"
},
  "geometry": {"coordinates":[8.4637174606,47.3976860046],"type":"Point"}
}