{
  "type": "Feature",
  "properties": {
    "iso:country":"CH",
    "sg:address":"Sportweg 38",
    "sg:city":"Liebefeld",
    "sg:orig_category":"Herstellung von Holzstoff, Papier, Karton U Pappe Papier U Kartongewerbe",
    "sg:phone":"+41 31 978 88 11",
    "sg:postcode":"3097",
    "sg:province":"Bern",
    "wof:name":"I.group Ag",
    "wof:placetype":"venue"
},
  "geometry": {"coordinates":[7.4169631004,46.9339447021],"type":"Point"}
}