{
  "type": "Feature",
  "properties": {
    "addr:full":"Lerchenstrasse 22a 9304 Bernhardzell. Postfach Bernhardzell St. Gallen 9304",
    "addr:housenumber":"22a",
    "addr:postcode":"9304;9304",
    "addr:street":"Lerchenstrasse;Postfach Bernhardzell",
    "iso:country":"CH",
    "sg:address":"Lerchenstrasse 22a 9304 Bernhardzell. Postfach",
    "sg:city":"Bernhardzell",
    "sg:orig_category":"Bausteine Fabrikation, Handel",
    "sg:phone":"+41 41 630 02 29",
    "sg:postcode":"9304",
    "sg:province":"St. Gallen",
    "wof:name":"Estrolith Gmbh",
    "wof:placetype":"venue"
},
  "geometry": {"coordinates":[8.312002,46.990639],"type":"Point"}
}