{
  "type": "Feature",
  "properties": {
    "iso:country":"CH",
    "sg:address":"Lido Via Al 8",
    "sg:city":"Viganello",
    "sg:orig_category":"Herstellung von Kaltprofilen",
    "sg:postcode":"6962",
    "sg:province":"Ticino",
    "wof:name":"L'idea Arreda Sagl",
    "wof:placetype":"venue"
},
  "geometry": {"coordinates":[8.9708967209,46.0149879456],"type":"Point"}
}