{
  "type": "Feature",
  "properties": {
    "iso:country":"CH",
    "sg:address":"Hauptstrasse 34",
    "sg:city":"Reiden",
    "sg:orig_category":"Detailhandel mit Fahrr\u00e4dern Handel mit Motorr\u00e4dern, Teilen U Zubeh\u00f6r Instandhaltung U Reparatur von ",
    "sg:phone":"+41 62 758 38 27",
    "sg:postcode":"6260",
    "sg:province":"Luzern",
    "wof:name":"Othmar Hofmann Velos-mofas",
    "wof:placetype":"venue"
},
  "geometry": {"coordinates":[7.9716920853,47.2456626892],"type":"Point"}
}