{
  "type": "Feature",
  "properties": {
    "addr:full":"Gerretta Via 4 Bellinzona Ticino 6500",
    "addr:postcode":"6500",
    "addr:street":"Via 4",
    "iso:country":"CH",
    "sg:address":"Gerretta Via 4",
    "sg:city":"Bellinzona",
    "sg:orig_category":"Bau von Strassen, Sportanlagen U Bahnverkehrsstrecken",
    "sg:postcode":"6500",
    "sg:province":"Ticino",
    "wof:name":"De Lay Ausilio Sa",
    "wof:placetype":"venue"
},
  "geometry": {"coordinates":[9.030015,46.199787],"type":"Point"}
}