{
  "type": "Feature",
  "properties": {
    "iso:country":"CH",
    "sg:address":"Ronalpstrasse 92",
    "sg:city":"B\u00fcrchen",
    "sg:orig_category":"Kantonalbanken",
    "sg:phone":"+41 27 934 30 41",
    "sg:postcode":"3935",
    "sg:province":"Valais",
    "wof:name":"Banque Cantonale Du Valais",
    "wof:placetype":"venue"
},
  "geometry": {"coordinates":[7.8260478973,46.2751274109],"type":"Point"}
}