{
  "type": "Feature",
  "properties": {
    "iso:country":"CH",
    "sg:address":"Molard Place Du 6",
    "sg:city":"Gen\u00e8ve",
    "sg:orig_category":"Unclassifiable Establishments",
    "sg:postcode":"1204",
    "sg:province":"Gen\u00e8ve",
    "wof:name":"Junon Sa",
    "wof:placetype":"venue"
},
  "geometry": {"coordinates":[6.1484570503,46.2032814026],"type":"Point"}
}