{
  "type": "Feature",
  "properties": {
    "iso:country":"CH",
    "sg:address":"Eidgenossenweg 16 4052 Basel. Postfach",
    "sg:city":"Basel",
    "sg:orig_category":"Grosshandel mit Getr\u00e4nken Grosshandel mit Wein U Spirituosen",
    "sg:phone":"+41 61 311 75 06",
    "sg:postcode":"4008",
    "sg:province":"Basel-Stadt",
    "wof:name":"Mazza & Isler, Les Amis Du Bon Vin",
    "wof:placetype":"venue"
},
  "geometry": {"coordinates":[7.6163449287,47.541809082],"type":"Point"}
}