{
  "type": "Feature",
  "properties": {
    "iso:country":"CH",
    "sg:address":"Vicolo Fontanile 9",
    "sg:city":"Stabio",
    "sg:orig_category":"Non-Classified Establishments",
    "sg:postcode":"6855",
    "sg:province":"Ticino",
    "wof:name":"Accompagna Sagl",
    "wof:placetype":"venue"
},
  "geometry": {"coordinates":[8.937877655,45.851234436],"type":"Point"}
}