{
  "type": "Feature",
  "properties": {
    "iso:country":"CH",
    "sg:address":"Hohlgasse 34",
    "sg:city":"Laufen",
    "sg:orig_category":"Architekturb\u00fcros",
    "sg:phone":"+41 61 761 67 21",
    "sg:postcode":"4242",
    "sg:province":"Basel-Landschaft",
    "wof:name":"Eggenschwiler Gerster Ag Architekturb\u00fcro",
    "wof:placetype":"venue"
},
  "geometry": {"coordinates":[7.501697,47.41861],"type":"Point"}
}