{
  "type": "Feature",
  "properties": {
    "iso:country":"CH",
    "sg:address":"Via Buonamano 22",
    "sg:city":"Ascona",
    "sg:orig_category":"Betrieb von Taxis",
    "sg:phone":"+41 91 792 27 47",
    "sg:postcode":"6612",
    "sg:province":"Ticino",
    "wof:name":"Yvonne Sasselli Tassi",
    "wof:placetype":"venue"
},
  "geometry": {"coordinates":[8.773979,46.157162],"type":"Point"}
}