{
  "type": "Feature",
  "properties": {
    "iso:country":"CH",
    "sg:address":"Gewerbestrasse 10",
    "sg:city":"Sissach",
    "sg:classifiers":[
        {
            "category":"Insurance",
            "subcategory":"Insurance Agent",
            "type":"Services"
        }
    ],
    "sg:phone":"+41 61 926 97 77",
    "sg:postcode":"4450",
    "sg:province":"Basel-Landschaft",
    "sg:tags":[
        "versicherungsagenturen",
        "-broker"
    ],
    "wof:name":"Winterthur-leben Agentur Sissach",
    "wof:placetype":"venue"
},
  "geometry": {"coordinates":[7.8033361435,47.4669570923],"type":"Point"}
}