{
  "type": "Feature",
  "properties": {
    "iso:country":"CH",
    "sg:address":"Uferstrasse 90 4057 Basel. Postfach",
    "sg:city":"Basel",
    "sg:orig_category":"Grosshandel mit medizinischen U orthop\u00e4dischen Artikeln Grosshandel mit pharmazeutischen Erzeugnisse",
    "sg:phone":"+41 61 631 03 00",
    "sg:postcode":"4019",
    "sg:province":"Basel-Stadt",
    "wof:name":"Life Technologies Ag Zell-& Molekularbiologie",
    "wof:placetype":"venue"
},
  "geometry": {"coordinates":[7.587141037,47.5822372437],"type":"Point"}
}