{
  "type": "Feature",
  "properties": {
    "iso:country":"CH",
    "sg:address":"Bellerivestrasse 31",
    "sg:city":"Luzern",
    "sg:orig_category":"Fotografische Ateliers",
    "sg:phone":"+41 41 370 93 10",
    "sg:postcode":"6006",
    "sg:province":"Luzern",
    "wof:name":"Peter Rast Fotografisches Atelier",
    "wof:placetype":"venue"
},
  "geometry": {"coordinates":[8.3321466446,47.0569839478],"type":"Point"}
}