{
  "type": "Feature",
  "properties": {
    "iso:country":"CH",
    "sg:address":"St-jakob 18",
    "sg:city":"B\u00f6singen",
    "sg:orig_category":"Sportvereine Eissport Eishockey",
    "sg:phone":"+41 31 744 71 35",
    "sg:postcode":"3178",
    "sg:province":"Fribourg",
    "wof:name":"Eishockey-club B\u00f6singen-kriechenwil",
    "wof:placetype":"venue"
},
  "geometry": {"coordinates":[7.228413105,46.8918952942],"type":"Point"}
}