{
  "type": "Feature",
  "properties": {
    "iso:country":"CH",
    "sg:address":"Eichwiesstrasse 20",
    "sg:city":"Jona",
    "sg:orig_category":"Dienstleistungen im Gartenbau Elektroinstallation",
    "sg:phone":"+41 81 723 12 20",
    "sg:postcode":"8645",
    "sg:province":"St. Gallen",
    "wof:name":"Iss Commultiservice Ag",
    "wof:placetype":"venue"
},
  "geometry": {"coordinates":[8.8376483917,47.2301635742],"type":"Point"}
}