{
  "type": "Feature",
  "properties": {
    "iso:country":"CH",
    "sg:address":"Rue Du Grand-pont 10",
    "sg:city":"Orbe",
    "sg:orig_category":"Instandhaltung U Reparatur von Automobilen",
    "sg:phone":"+41 71 278 61 67",
    "sg:postcode":"1350",
    "sg:province":"Vaud",
    "wof:name":"Siegmann A. Garage Autoelektrik-elektronik",
    "wof:placetype":"venue"
},
  "geometry": {"coordinates":[9.3371334076,47.4124565125],"type":"Point"}
}