{
  "type": "Feature",
  "properties": {
    "iso:country":"CH",
    "sg:address":"Bahnhofstrasse 21",
    "sg:city":"Zug",
    "sg:orig_category":"Revision Wirtschaftspr\u00fcfung, Steuerberatung U Treuhand",
    "sg:phone":"+41 55 420 39 40",
    "sg:postcode":"6300",
    "sg:province":"Zug",
    "wof:name":"Retax Gmbh",
    "wof:placetype":"venue"
},
  "geometry": {"coordinates":[8.7900953293,47.2021484375],"type":"Point"}
}