{
  "type": "Feature",
  "properties": {
    "iso:country":"CH",
    "sg:address":"Haute-nendaz 1997 Haute-nendaz. Postfach",
    "sg:city":"Haute-nendaz",
    "sg:orig_category":"Beherbergungsgewerbe",
    "sg:postcode":"1997",
    "sg:province":"Valais",
    "wof:name":"Sun & Snow S\u00e0rl",
    "wof:placetype":"venue"
},
  "geometry": {"coordinates":[7.295837,46.186962],"type":"Point"}
}