{
  "type": "Feature",
  "properties": {
    "iso:country":"CH",
    "sg:address":"Rathausstrasse 59",
    "sg:city":"Liestal",
    "sg:orig_category":"Warenh\u00e4user",
    "sg:phone":"+41 61 921 25 33",
    "sg:postcode":"4410",
    "sg:province":"Basel-Landschaft",
    "wof:name":"Manor",
    "wof:placetype":"venue"
},
  "geometry": {"coordinates":[7.735517025,47.483581543],"type":"Point"}
}