{
  "type": "Feature",
  "properties": {
    "iso:country":"CH",
    "sg:address":"Seestrasse 129",
    "sg:city":"St\u00e4fa",
    "sg:orig_category":"Handelsvermittlung U Grosshandel Reiseb\u00fcros U Reiseveranstalter",
    "sg:phone":"+41 19266757",
    "sg:postcode":"8712",
    "sg:province":"Z\u00fcrich",
    "wof:name":"Ntc-nashashibi",
    "wof:placetype":"venue"
},
  "geometry": {"coordinates":[8.7307386398,47.2360076904],"type":"Point"}
}