{
  "type": "Feature",
  "properties": {
    "iso:country":"CH",
    "sg:address":"Schmidtenbaumgarten 10 8917 Oberlunkhofen. Postfach",
    "sg:city":"Oberlunkhofen",
    "sg:orig_category":"Grosshandel mit sonstigen Maschinen U Ausr\u00fcstungen f\u00fcr Industrie, Handel U Schiffahrt Treppenbau",
    "sg:phone":"+41 17345656",
    "sg:postcode":"8917",
    "sg:province":"Aargau",
    "wof:name":"Ilmatech Gmbh",
    "wof:placetype":"venue"
},
  "geometry": {"coordinates":[8.3883829117,47.3124275208],"type":"Point"}
}