{
  "type": "Feature",
  "properties": {
    "iso:country":"CH",
    "sg:address":"Steindlerstrasse 3",
    "sg:city":"Unterseen",
    "sg:orig_category":"Bezirks, Sekundar, Realschulen, Oberstufe der Primarschulen",
    "sg:postcode":"3800",
    "sg:province":"Bern",
    "wof:name":"Sekundarschule",
    "wof:placetype":"venue"
},
  "geometry": {"coordinates":[7.429563,46.92971],"type":"Point"}
}