{
  "type": "Feature",
  "properties": {
    "iso:country":"CH",
    "sg:address":"Im Tal 213",
    "sg:city":"Oberstammheim",
    "sg:orig_category":"Grosshandel mit keramischen Erzeugnissen, Glaswaren U Reinigungsmitteln",
    "sg:postcode":"8477",
    "sg:province":"Z\u00fcrich",
    "wof:name":"Walltex, Sch\u00fcller",
    "wof:placetype":"venue"
},
  "geometry": {"coordinates":[8.6009473801,47.3227844238],"type":"Point"}
}