{
  "type": "Feature",
  "properties": {
    "addr:full":"Po Box 958 Rue Du Rh\u00f4ne 40 Geneva Gen\u00e8ve 1204",
    "addr:housenumber":"po;40",
    "addr:postcode":"1204",
    "addr:street":"Box 958 Rue Du Rho\u0302Ne",
    "iso:country":"CH",
    "sg:address":"Po Box 958 Rue Du Rh\u00f4ne 40",
    "sg:city":"Geneva",
    "sg:classifiers":[
        {
            "category":"Banks & Credit Unions",
            "subcategory":"Bank",
            "type":"Services"
        }
    ],
    "sg:postcode":"1204",
    "sg:province":"Gen\u00e8ve",
    "wof:name":"Ubp Gestion Institutionnelle",
    "wof:placetype":"venue"
},
  "geometry": {"coordinates":[6.151101,46.203136],"type":"Point"}
}