{
  "type": "Feature",
  "properties": {
    "iso:country":"CH",
    "sg:address":"Steinacherstrasse 4 8614 Bertschikon. Postfach",
    "sg:city":"Bertschikon",
    "sg:orig_category":"Elektroinstallation",
    "sg:phone":"+41 56 225 04 30",
    "sg:postcode":"8614",
    "sg:province":"Z\u00fcrich",
    "wof:name":"Sidler Elektro Gmbh",
    "wof:placetype":"venue"
},
  "geometry": {"coordinates":[8.2475223541,47.4623222351],"type":"Point"}
}