{
  "type": "Feature",
  "properties": {
    "iso:country":"CH",
    "sg:address":"Rossweid",
    "sg:city":"Gisikon",
    "sg:orig_category":"Verwertung von Milch",
    "sg:phone":"+41 21 800 55 65",
    "sg:postcode":"6038",
    "sg:province":"Luzern",
    "wof:name":"Genoud Nicolas",
    "wof:placetype":"venue"
},
  "geometry": {"coordinates":[6.4529600143,46.5753707886],"type":"Point"}
}