{
  "type": "Feature",
  "properties": {
    "iso:country":"CH",
    "sg:address":"Dorfstrasse 3",
    "sg:city":"Wuppenau",
    "sg:orig_category":"Strassenbau",
    "sg:phone":"+41 71 622 42 42",
    "sg:postcode":"9514",
    "sg:province":"Thurgau",
    "wof:name":"Egolf Ag Strassen-& Tiefbau",
    "wof:placetype":"venue"
},
  "geometry": {"coordinates":[9.1088275909,47.4970855713],"type":"Point"}
}