{
  "type": "Feature",
  "properties": {
    "iso:country":"CH",
    "sg:address":"Im Sonnenhof 2 8753 Mollis. Postfach",
    "sg:city":"Cham",
    "sg:orig_category":"Detailhandel mit Metallwaren, Anstrichmitteln, Glaswaren, Bau U Heimwerkerbedarf",
    "sg:postcode":"6330",
    "sg:province":"Zug",
    "wof:name":"Otc Ag",
    "wof:placetype":"venue"
},
  "geometry": {"coordinates":[9.0704689026,47.0925712585],"type":"Point"}
}