{
  "type": "Feature",
  "properties": {
    "iso:country":"CH",
    "sg:address":"Pl. De L'eglise 1872 Troistorrents. Postfach",
    "sg:city":"Morgins",
    "sg:orig_category":"RESTAURANTS: TEA-ROOMS",
    "sg:postcode":"1875",
    "sg:province":"Valais",
    "wof:name":"Stefanelli Antonio",
    "wof:placetype":"venue"
},
  "geometry": {"coordinates":[6.8573541641,46.2376594543],"type":"Point"}
}