{
  "type": "Feature",
  "properties": {
    "iso:country":"CH",
    "sg:address":"Communes R\u00e9unies Av. Des 84",
    "sg:city":"Grand-lancy",
    "sg:orig_category":"Mechanik",
    "sg:phone":"+41 22 794 18 88",
    "sg:postcode":"1212",
    "sg:province":"Gen\u00e8ve",
    "wof:name":"Garage Pelleriti S\u00e9bastien",
    "wof:placetype":"venue"
},
  "geometry": {"coordinates":[6.1219911575,46.1726493835],"type":"Point"}
}