{
  "type": "Feature",
  "properties": {
    "iso:country":"CH",
    "sg:address":"Gl\u00e4rnischstrasse 8",
    "sg:city":"B\u00e4retswil",
    "sg:orig_category":"Herstellung von Kunststoffwaren",
    "sg:phone":"+41 79 447 90 39",
    "sg:postcode":"8344",
    "sg:province":"Z\u00fcrich",
    "wof:name":"Industrie Technik B\u00e4retswil Itb Ag",
    "wof:placetype":"venue"
},
  "geometry": {"coordinates":[8.8506422043,47.3401794434],"type":"Point"}
}