{
  "type": "Feature",
  "properties": {
    "iso:country":"CH",
    "sg:address":"Emmersbergstrasse 1 8200 Schaffhausen. Postfach 566",
    "sg:city":"Schaffhausen",
    "sg:orig_category":"G\u00fcterbef\u00f6rderung im Strassenverkehr",
    "sg:phone":"+41 71 463 18 81",
    "sg:postcode":"8201",
    "sg:province":"Schaffhausen",
    "wof:name":"Gondrand Ag",
    "wof:placetype":"venue"
},
  "geometry": {"coordinates":[9.3734302521,47.5567817688],"type":"Point"}
}