{
  "type": "Feature",
  "properties": {
    "iso:country":"CH",
    "sg:address":"Hauptstrasse 60",
    "sg:city":"Ober\u00e4geri",
    "sg:classifiers":[
        {
            "category":"Restaurant",
            "type":"Food & Drink"
        }
    ],
    "sg:phone":"+41 41 750 15 57",
    "sg:postcode":"6315",
    "sg:province":"Zug",
    "wof:name":"Restaurant Aegerisee",
    "wof:placetype":"venue"
},
  "geometry": {"coordinates":[8.6045589447,47.1374702454],"type":"Point"}
}