{
  "type": "Feature",
  "properties": {
    "iso:country":"CH",
    "sg:address":"Z\u00fcrichstrasse 234",
    "sg:city":"Binz",
    "sg:orig_category":"Dachdeckerei Zimmerei, Dachdeckerei, Bauspenglerei U Abdichtung",
    "sg:phone":"+41 19805758",
    "sg:postcode":"8122",
    "sg:province":"Z\u00fcrich",
    "wof:name":"Vogel Christian Bedachungen, Vormals Markwalder Hans",
    "wof:placetype":"venue"
},
  "geometry": {"coordinates":[8.628479,47.356773],"type":"Point"}
}