{
  "type": "Feature",
  "properties": {
    "iso:country":"CH",
    "sg:address":"Ludetswilerstrasse 2 8322 Madetswil. Postfach",
    "sg:city":"Madetswil",
    "sg:orig_category":"RESTAURANTS: TEA-ROOMS",
    "sg:postcode":"8322",
    "sg:province":"Z\u00fcrich",
    "wof:name":"Diener's Heurigen Gmbh",
    "wof:placetype":"venue"
},
  "geometry": {"coordinates":[8.793545723,47.4112319946],"type":"Point"}
}