{
  "type": "Feature",
  "properties": {
    "iso:country":"CH",
    "sg:address":"Hauptstrasse 69",
    "sg:city":"Degersheim",
    "sg:classifiers":[
        {
            "category":"Restaurant",
            "type":"Food & Drink"
        }
    ],
    "sg:phone":"+41 71 371 13 71",
    "sg:postcode":"9113",
    "sg:province":"St. Gallen",
    "wof:name":"Gasthaus Sch\u00e4fli",
    "wof:placetype":"venue"
},
  "geometry": {"coordinates":[9.1978883743,47.3732795715],"type":"Point"}
}