{
  "type": "Feature",
  "properties": {
    "iso:country":"CH",
    "sg:address":"Gonenstein 21",
    "sg:city":"Leukerbad",
    "sg:orig_category":"Druck ohne Zeitungsdruck",
    "sg:postcode":"3954",
    "sg:province":"Valais",
    "wof:name":"Amori Edition, Rexhep Berisha",
    "wof:placetype":"venue"
},
  "geometry": {"coordinates":[7.6253261566,46.3759307861],"type":"Point"}
}