{
  "type": "Feature",
  "properties": {
    "iso:country":"CH",
    "sg:address":"Brunnenplatz 8",
    "sg:city":"Huttwil",
    "sg:orig_category":"Detailhandel mit Textilien Detailhandel mit elektrischen Haushaltsger\u00e4ten",
    "sg:phone":"+41 62 962 23 39",
    "sg:postcode":"4950",
    "sg:province":"Bern",
    "wof:name":"Heinz Leuenberger Bernina-n\u00e4hcenter",
    "wof:placetype":"venue"
},
  "geometry": {"coordinates":[7.8496441841,47.113368988],"type":"Point"}
}