{
  "type": "Feature",
  "properties": {
    "iso:country":"CH",
    "sg:address":"Sonnengrund 5a",
    "sg:city":"Willisau",
    "sg:orig_category":"Sportvereine Ballsport Squash",
    "sg:phone":"+41 71 970 07 62",
    "sg:postcode":"6130",
    "sg:province":"Luzern",
    "wof:name":"Squash Club Quattro Willisau",
    "wof:placetype":"venue"
},
  "geometry": {"coordinates":[7.9842071533,47.1205215454],"type":"Point"}
}