{
  "type": "Feature",
  "properties": {
    "iso:country":"CH",
    "sg:address":"Thunstrasse 8",
    "sg:city":"Tafers",
    "sg:orig_category":"Bauschreinerei Herstellung von Konstruktionsteilen, Fertigbauteilen U Ausbauelementen aus Holz",
    "sg:phone":"+41 26 494 04 94",
    "sg:postcode":"1712",
    "sg:province":"Fribourg",
    "wof:name":"Gallus Riedo M\u00f6bel & Innenausbau",
    "wof:placetype":"venue"
},
  "geometry": {"coordinates":[7.21927,46.815739],"type":"Point"}
}