{
  "type": "Feature",
  "properties": {
    "iso:country":"CH",
    "sg:address":"Menznauerstrasse 16 6130 Willisau. Postfach",
    "sg:city":"Willisau",
    "sg:orig_category":"Grosshandel mit Spielwaren Herstellung von elektronischen Bauelementen",
    "sg:phone":"+41 17619906",
    "sg:postcode":"6130",
    "sg:province":"Luzern",
    "wof:name":"Gerber, Elektronische Modellbauartikel.",
    "wof:placetype":"venue"
},
  "geometry": {"coordinates":[8.450258255,47.2794799805],"type":"Point"}
}