{
  "type": "Feature",
  "properties": {
    "iso:country":"CH",
    "sg:address":"Rue Des P\u00e2quis 46",
    "sg:city":"Gen\u00e8ve",
    "sg:orig_category":"Detailhandel mit Tabakwaren Detailhandel mit Zeitungen U Zeitschriften Kioske",
    "sg:postcode":"1201",
    "sg:province":"Gen\u00e8ve",
    "wof:name":"A.-m. & M.-j. Alberti Tabacs Journaux",
    "wof:placetype":"venue"
},
  "geometry": {"coordinates":[6.1507081985,46.2135162354],"type":"Point"}
}