{
  "type": "Feature",
  "properties": {
    "iso:country":"CH",
    "sg:address":"En Redon",
    "sg:city":"Avry-devant-pont",
    "sg:orig_category":"Fischzucht, Teichwirtschaft",
    "sg:phone":"+41 26 915 21 44",
    "sg:postcode":"1644",
    "sg:province":"Fribourg",
    "wof:name":"Garde-p\u00eache & Pisciculture Du Lac De La Gruy\u00e8re",
    "wof:placetype":"venue"
},
  "geometry": {"coordinates":[7.086250782,46.6852798462],"type":"Point"}
}