{
  "type": "Feature",
  "properties": {
    "iso:country":"CH",
    "sg:address":"Br\u00fchlmattweg 37 3044 Innerberg-s\u00e4riswil. Postfach",
    "sg:city":"Innerberg-s\u00e4riswil",
    "sg:orig_category":"Softwareentwicklung U beratung",
    "sg:phone":"+41 31 829 29 23",
    "sg:postcode":"3044",
    "sg:province":"Bern",
    "wof:name":"Baringanet Gmbh Dienstleistungen Im Bereich Der Informationstechnologie Bzw. Elektronischen Datenverarbeitung Usw.",
    "wof:placetype":"venue"
},
  "geometry": {"coordinates":[7.3388080597,46.9928283691],"type":"Point"}
}