{
  "type": "Feature",
  "properties": {
    "iso:country":"CH",
    "sg:address":"Chesletenrain 16",
    "sg:city":"Biberstein",
    "sg:orig_category":"Grosshandel mit B\u00fcromaschinen Grosshandel mit Datenverarbeitungsger\u00e4ten",
    "sg:phone":"+41 32 757 26 26",
    "sg:postcode":"5023",
    "sg:province":"Aargau",
    "wof:name":"Datagest Sa",
    "wof:placetype":"venue"
},
  "geometry": {"coordinates":[7.0246648788,47.0372657776],"type":"Point"}
}