{
  "type": "Feature",
  "properties": {
    "iso:country":"CH",
    "sg:address":"Hubstrasse 8",
    "sg:city":"Rorschach",
    "sg:orig_category":"Detailhandel mit Brot, Back U S\u00fcsswaren",
    "sg:phone":"+41 19321353",
    "sg:postcode":"9400",
    "sg:province":"St. Gallen",
    "wof:name":"Fritz Bolliger B\u00e4ckerei-konditorei",
    "wof:placetype":"venue"
},
  "geometry": {"coordinates":[8.792951,47.319599],"type":"Point"}
}