{
  "type": "Feature",
  "properties": {
    "iso:country":"CH",
    "sg:address":"Sumpfstrasse 26 6300 Zug. Postfach",
    "sg:city":"Zug",
    "sg:classifiers":[
        {
            "category":"Travel",
            "subcategory":"Hotels & Motels",
            "type":"Entertainment"
        }
    ],
    "sg:postcode":"6300",
    "sg:province":"Zug",
    "sg:tags":[
        "hotels",
        "mit",
        "restaurant"
    ],
    "wof:name":"Business Academy K\u00f6berle Markus Seminare Im Unternehmensbereich",
    "wof:placetype":"venue"
},
  "geometry": {"coordinates":[8.4851512909,47.1778526306],"type":"Point"}
}