{
  "type": "Feature",
  "properties": {
    "iso:country":"CH",
    "sg:address":"Alte Wangenstrasse 3",
    "sg:city":"Wiedlisbach",
    "sg:orig_category":"Detailhandel mit Fahrr\u00e4dern Handel mit Motorr\u00e4dern, Teilen U Zubeh\u00f6r Instandhaltung U Reparatur von ",
    "sg:phone":"+41 32 636 31 38",
    "sg:postcode":"4537",
    "sg:province":"Bern",
    "wof:name":"Max Weber Velos Motos",
    "wof:placetype":"venue"
},
  "geometry": {"coordinates":[7.6454930305,47.2507362366],"type":"Point"}
}