{
  "type": "Feature",
  "properties": {
    "iso:country":"CH",
    "sg:address":"Chemin Des Recourbes 12",
    "sg:city":"Bex",
    "sg:orig_category":"Malerei Stukkateurgewerbe, Gipserei U Verputzerei",
    "sg:phone":"+41 24 463 32 52",
    "sg:postcode":"1880",
    "sg:province":"Vaud",
    "wof:name":"Arimondi Peinture Pl\u00e2trerie-peinture Et Pose De Papiers Peints",
    "wof:placetype":"venue"
},
  "geometry": {"coordinates":[7.0156807899,46.2502593994],"type":"Point"}
}