{
  "type": "Feature",
  "properties": {
    "iso:country":"CH",
    "sg:address":"Les Tuileries",
    "sg:city":"Grandson",
    "sg:orig_category":"Unclassifiable Establishments",
    "sg:postcode":"1422",
    "sg:province":"Vaud",
    "wof:name":"Martha Brunner",
    "wof:placetype":"venue"
},
  "geometry": {"coordinates":[6.6459851265,46.8093681335],"type":"Point"}
}