{
  "type": "Feature",
  "properties": {
    "iso:country":"CH",
    "sg:address":"Bachtelstrasse 12 8302 Kloten. Postfach",
    "sg:city":"Kloten",
    "sg:orig_category":"Sonstige Kurierdienste",
    "sg:postcode":"8302",
    "sg:province":"Z\u00fcrich",
    "wof:name":"Speed-kurier Piediscalzi",
    "wof:placetype":"venue"
},
  "geometry": {"coordinates":[8.5947904587,47.452091217],"type":"Point"}
}