{
  "type": "Feature",
  "properties": {
    "iso:country":"CH",
    "sg:address":"Wysistrasse 16",
    "sg:city":"Schwyz",
    "sg:orig_category":"Vermietung U Verpachtung von eigenen Immobilien",
    "sg:phone":"+41 41 811 52 42",
    "sg:postcode":"6430",
    "sg:province":"Schwyz",
    "wof:name":"Bolfing Martin Immobilien Ag Schwyz",
    "wof:placetype":"venue"
},
  "geometry": {"coordinates":[8.6637353897,47.0191383362],"type":"Point"}
}