{
  "type": "Feature",
  "properties": {
    "iso:country":"CH",
    "sg:address":"Chemin De Vuarrens 4",
    "sg:city":"Bex",
    "sg:orig_category":"Sportvereine Flug Aero-Club",
    "sg:phone":"+41 24 463 12 26",
    "sg:postcode":"1880",
    "sg:province":"Vaud",
    "wof:name":"Groupe De Vol \u00e0 Moteur Aecs",
    "wof:placetype":"venue"
},
  "geometry": {"coordinates":[7.0138959885,46.2473258972],"type":"Point"}
}