{
  "type": "Feature",
  "properties": {
    "iso:country":"CH",
    "sg:address":"Jurastrasse 11",
    "sg:city":"Dulliken",
    "sg:orig_category":"Physiotherapie",
    "sg:phone":"+41 62 295 03 53",
    "sg:postcode":"4657",
    "sg:province":"Solothurn",
    "wof:name":"Ruedi Huser Physiotherapie",
    "wof:placetype":"venue"
},
  "geometry": {"coordinates":[7.9447607994,47.3537712097],"type":"Point"}
}