{
  "type": "Feature",
  "properties": {
    "iso:country":"CH",
    "sg:address":"Neudorf.",
    "sg:city":"Sennwald",
    "sg:orig_category":"Detailhandel mit Fleisch U Fleischwaren",
    "sg:phone":"+41 81 757 11 50",
    "sg:postcode":"9466",
    "sg:province":"St. Gallen",
    "wof:name":"Metzgerei Kaufmann Ag.",
    "wof:placetype":"venue"
},
  "geometry": {"coordinates":[9.5036201477,47.2606582642],"type":"Point"}
}