{
  "type": "Feature",
  "properties": {
    "iso:country":"CH",
    "sg:address":"Lindenstrasse 8",
    "sg:city":"Nieder\u00f6nz",
    "sg:orig_category":"Sportvereine Eissport Eishockey",
    "sg:phone":"+41 62 962 31 84",
    "sg:postcode":"3362",
    "sg:province":"Bern",
    "wof:name":"Eishockey-club Huttwil",
    "wof:placetype":"venue"
},
  "geometry": {"coordinates":[7.8282489777,47.1072311401],"type":"Point"}
}