{
  "type": "Feature",
  "properties": {
    "iso:country":"CH",
    "sg:address":"Pourpoint 8 2605 Sonceboz-sombeval. Postfach",
    "sg:city":"Sonceboz-sombeval",
    "sg:orig_category":"Softwareentwicklung U beratung",
    "sg:postcode":"2605",
    "sg:province":"Bern",
    "wof:name":"Pc - Gatway Marti Patrick",
    "wof:placetype":"venue"
},
  "geometry": {"coordinates":[7.1740589142,47.1925125122],"type":"Point"}
}