{
  "type": "Feature",
  "properties": {
    "addr:full":"Th\u00e9\u00e2tre Rue Du 9 Montreux Vaud 1820",
    "addr:postcode":"1820",
    "addr:street":"Rue Du 9",
    "iso:country":"CH",
    "sg:address":"Th\u00e9\u00e2tre Rue Du 9",
    "sg:city":"Montreux",
    "sg:orig_category":"Betrieb U technische Hilfsdienste des Kultur U Unterhaltungswesens",
    "sg:postcode":"1820",
    "sg:province":"Vaud",
    "wof:name":"Mov-x Gmbh",
    "wof:placetype":"venue"
},
  "geometry": {"coordinates":[8.207842,47.265862],"type":"Point"}
}