{
  "type": "Feature",
  "properties": {
    "iso:country":"CH",
    "sg:address":"M\u00fcnstergasse 45",
    "sg:city":"Bern",
    "sg:orig_category":"Detailhandel mit Bekleidung Detailhandel mit Textilien",
    "sg:phone":"+41 31 311 14 74",
    "sg:postcode":"3011",
    "sg:province":"Bern",
    "wof:name":"Meister Couture",
    "wof:placetype":"venue"
},
  "geometry": {"coordinates":[7.449985981,46.9473304749],"type":"Point"}
}