{
  "type": "Feature",
  "properties": {
    "iso:country":"CH",
    "sg:address":"Weissensteinstrasse 75",
    "sg:city":"Bern",
    "sg:orig_category":"Kaminfeger",
    "sg:phone":"+41 31 371 15 23",
    "sg:postcode":"3007",
    "sg:province":"Bern",
    "wof:name":"Eduard Locher Kaminfegermeister",
    "wof:placetype":"venue"
},
  "geometry": {"coordinates":[7.4295868874,46.9378242493],"type":"Point"}
}