{
  "type": "Feature",
  "properties": {
    "iso:country":"CH",
    "sg:address":"Oberdorfstrasse 7",
    "sg:city":"Arch",
    "sg:classifiers":[
        {
            "category":"Professional",
            "subcategory":"Advertising",
            "type":"Services"
        }
    ],
    "sg:phone":"+41 32 679 00 25",
    "sg:postcode":"3296",
    "sg:province":"Bern",
    "sg:tags":[
        "watch",
        "purpose",
        "clock"
    ],
    "wof:name":"B-line Watch Ag Pointer Switzerland",
    "wof:placetype":"venue"
},
  "geometry": {"coordinates":[7.4287729263,47.1667900085],"type":"Point"}
}