{
  "type": "Feature",
  "properties": {
    "iso:country":"CH",
    "sg:address":"Neugasse 9",
    "sg:city":"Interlaken",
    "sg:orig_category":"Offsetdruck",
    "sg:phone":"+41 33 822 34 36",
    "sg:postcode":"3800",
    "sg:province":"Bern",
    "wof:name":"Balmer Druck Ag",
    "wof:placetype":"venue"
},
  "geometry": {"coordinates":[7.8540577888,46.6866340637],"type":"Point"}
}