{
  "type": "Feature",
  "properties": {
    "iso:country":"CH",
    "sg:address":"K\u00e4sereistrasse 6",
    "sg:city":"Ermensee",
    "sg:orig_category":"Verarbeitung von Milch Verwertung von Milch",
    "sg:postcode":"6294",
    "sg:province":"Luzern",
    "wof:name":"K\u00e4sereigenossenschaft Ermensee",
    "wof:placetype":"venue"
},
  "geometry": {"coordinates":[8.2393302917,47.2272872925],"type":"Point"}
}