{
  "type": "Feature",
  "properties": {
    "iso:country":"CH",
    "sg:address":"Gasse 51",
    "sg:city":"G\u00fcnsberg",
    "sg:orig_category":"Herstellung von Konstruktionsteilen, Fertigbauteilen U Ausbauelementen aus Holz",
    "sg:phone":"+41 32 637 20 17",
    "sg:postcode":"4524",
    "sg:province":"Solothurn",
    "wof:name":"Scherler Bau",
    "wof:placetype":"venue"
},
  "geometry": {"coordinates":[7.5808711052,47.2589797974],"type":"Point"}
}