{
  "type": "Feature",
  "properties": {
    "iso:country":"CH",
    "sg:address":"Bvd Georges-favon 6",
    "sg:city":"Gen\u00e8ve",
    "sg:orig_category":"Reiseb\u00fcros",
    "sg:phone":"+41 32 652 13 59",
    "sg:postcode":"1204",
    "sg:province":"Gen\u00e8ve",
    "wof:name":"Edi's Team Reiseb\u00fcro",
    "wof:placetype":"venue"
},
  "geometry": {"coordinates":[7.3664398193,47.1824989319],"type":"Point"}
}