{
  "type": "Feature",
  "properties": {
    "iso:country":"CH",
    "sg:address":"Thunstrasse 19",
    "sg:city":"Rubigen",
    "sg:orig_category":"Detailhandel mit Fleisch U Fleischwaren",
    "sg:phone":"+41 31 721 40 57",
    "sg:postcode":"3113",
    "sg:province":"Bern",
    "wof:name":"Markus Hodel",
    "wof:placetype":"venue"
},
  "geometry": {"coordinates":[7.545404911,46.8972854614],"type":"Point"}
}