{
  "type": "Feature",
  "properties": {
    "iso:country":"CH",
    "sg:address":"Rorschacher Strasse 204",
    "sg:city":"St.gallen",
    "sg:orig_category":"Malerei",
    "sg:phone":"+41 71 245 56 29",
    "sg:postcode":"9000",
    "sg:province":"St. Gallen",
    "wof:name":"Maler Thaler Gmbh Malerei",
    "wof:placetype":"venue"
},
  "geometry": {"coordinates":[9.4011230469,47.4341239929],"type":"Point"}
}