{
  "type": "Feature",
  "properties": {
    "addr:full":"Dufourstrasse 110 Z\u00fcrich Z\u00fcrich 8008",
    "addr:housenumber":"110",
    "addr:postcode":"8008",
    "addr:street":"Dufourstrasse",
    "iso:country":"CH",
    "sg:address":"Dufourstrasse 110",
    "sg:city":"Z\u00fcrich",
    "sg:orig_category":"Architektur U Ingenieurb\u00fcros",
    "sg:phone":"+41 13800630",
    "sg:postcode":"8008",
    "sg:province":"Z\u00fcrich",
    "wof:name":"Nisco Engineering Ag Verfahrenstechnik Usw.; Ingenieur- U. Entwicklungsarbeit",
    "wof:placetype":"venue"
},
  "geometry": {"coordinates":[8.552034,47.358063],"type":"Point"}
}