{
  "type": "Feature",
  "properties": {
    "iso:country":"CH",
    "sg:address":"Benkenstrasse 10",
    "sg:city":"B\u00e4ttwil",
    "sg:orig_category":"Grosshandel mit Wein U Spirituosen Wein Detailhandel",
    "sg:phone":"+41 61 735 98 98",
    "sg:postcode":"4112",
    "sg:province":"Solothurn",
    "wof:name":"Kaufmann Getr\u00e4nke-& Weinhandlung Ag",
    "wof:placetype":"venue"
},
  "geometry": {"coordinates":[7.5128369331,47.490447998],"type":"Point"}
}