{
  "type": "Feature",
  "properties": {
    "iso:country":"CH",
    "sg:address":"Ohne Domizil",
    "sg:city":"W\u00fcnnewil",
    "sg:orig_category":"Grosshandel mit Textilien",
    "sg:phone":"+41 26 496 20 53",
    "sg:postcode":"3184",
    "sg:province":"Fribourg",
    "wof:name":"Leemann & Co Ag",
    "wof:placetype":"venue"
},
  "geometry": {"coordinates":[7.2761421204,46.8746261597],"type":"Point"}
}