{
  "type": "Feature",
  "properties": {
    "addr:full":"Gehrenweg 15 Oberlunkhofen Aargau 8917",
    "addr:housenumber":"15",
    "addr:postcode":"8917",
    "addr:street":"Gehrenweg",
    "iso:country":"CH",
    "sg:address":"Gehrenweg 15",
    "sg:city":"Oberlunkhofen",
    "sg:orig_category":"Architekturb\u00fcros",
    "sg:phone":"+41 56 634 30 00",
    "sg:postcode":"8917",
    "sg:province":"Aargau",
    "wof:name":"Werner Koch Architekturb\u00fcro",
    "wof:placetype":"venue"
},
  "geometry": {"coordinates":[8.394839,47.310349],"type":"Point"}
}