{
  "type": "Feature",
  "properties": {
    "iso:country":"CH",
    "sg:address":"Via Muraccio 47",
    "sg:city":"Ascona",
    "sg:orig_category":"Detailhandel mit M\u00f6beln U Haushaltsgegenst\u00e4nden Innendekorationsateliers",
    "sg:phone":"+41 19101919",
    "sg:postcode":"6612",
    "sg:province":"Ticino",
    "wof:name":"Ambiente Ag",
    "wof:placetype":"venue"
},
  "geometry": {"coordinates":[8.5877189636,47.3249702454],"type":"Point"}
}