{
  "type": "Feature",
  "properties": {
    "iso:country":"CH",
    "sg:address":"3463",
    "sg:city":"H\u00e4usernmoos",
    "sg:orig_category":"Primarschulen",
    "sg:postcode":"3463",
    "sg:province":"Bern",
    "wof:name":"Primarschule Gassen",
    "wof:placetype":"venue"
},
  "geometry": {"coordinates":[7.7493782043,47.0795173645],"type":"Point"}
}