{
  "type": "Feature",
  "properties": {
    "iso:country":"CH",
    "sg:address":"Place De La Palud 13",
    "sg:city":"Lausanne",
    "sg:classifiers":[
        {
            "category":"Professional",
            "subcategory":"Business Services",
            "type":"Services"
        }
    ],
    "sg:phone":"+41 21 324 00 74",
    "sg:postcode":"1003",
    "sg:province":"Vaud",
    "sg:tags":[
        "data"
    ],
    "wof:name":"Daily-soft Lltd",
    "wof:placetype":"venue"
},
  "geometry": {"coordinates":[6.632253,46.522423],"type":"Point"}
}