{
  "type": "Feature",
  "properties": {
    "iso:country":"CH",
    "sg:address":"H\u00f6henweg 15",
    "sg:city":"Attiswil",
    "sg:orig_category":"Haltung von Schafen, Ziegen, Pferden U Eseln",
    "sg:postcode":"4536",
    "sg:province":"Bern",
    "wof:name":"Haflingerpferdezucht-genossenschaft Ostschweiz",
    "wof:placetype":"venue"
},
  "geometry": {"coordinates":[9.3737154007,47.4263916016],"type":"Point"}
}