{
  "type": "Feature",
  "properties": {
    "iso:country":"CH",
    "sg:address":"Wachth\u00fcgel 117",
    "sg:city":"Walzenhausen",
    "sg:orig_category":"Herstellung von medizinischen U chirurgischen Ger\u00e4ten sowie orthop\u00e4dischen Vorrichtungen",
    "sg:postcode":"9428",
    "sg:province":"Appenzell Ausserrhoden",
    "wof:name":"Inter-pain",
    "wof:placetype":"venue"
},
  "geometry": {"coordinates":[9.6042127609,47.4506225586],"type":"Point"}
}