{
  "type": "Feature",
  "properties": {
    "iso:country":"CH",
    "sg:address":"Alpes Avenue Des 9",
    "sg:city":"Sierre",
    "sg:orig_category":"Herstellung von Seifen, Wasch U Reinigungsmitteln",
    "sg:postcode":"3960",
    "sg:province":"Valais",
    "wof:name":"Viachem Ag",
    "wof:placetype":"venue"
},
  "geometry": {"coordinates":[9.4850931168,47.1655502319],"type":"Point"}
}