{
  "type": "Feature",
  "properties": {
    "iso:country":"CH",
    "sg:address":"Greifengasse 14",
    "sg:city":"Basel",
    "sg:orig_category":"Unclassifiable Establishments",
    "sg:phone":"+41 61 681 20 16",
    "sg:postcode":"4058",
    "sg:province":"Basel-Stadt",
    "wof:name":"L\u00f6wen Apotheke Basel, Erben Dr. P. Giezendanner",
    "wof:placetype":"venue"
},
  "geometry": {"coordinates":[7.5918698311,47.5609130859],"type":"Point"}
}