{
  "type": "Feature",
  "properties": {
    "iso:country":"CH",
    "sg:address":"Dorfstrasse 29",
    "sg:city":"Neuendorf",
    "sg:orig_category":"Sanit\u00e4r, Heizungs U L\u00fcftungsinstallation",
    "sg:phone":"+41 62 398 33 22",
    "sg:postcode":"4623",
    "sg:province":"Solothurn",
    "wof:name":"Berger Heizung-sanit\u00e4r Gmbh",
    "wof:placetype":"venue"
},
  "geometry": {"coordinates":[7.7891869545,47.3003921509],"type":"Point"}
}