{
  "type": "Feature",
  "properties": {
    "iso:country":"CH",
    "sg:address":"Scuole Via Delle 18",
    "sg:city":"Pregassona",
    "sg:orig_category":"Sonstige mit Sport verbundene T\u00e4tigkeiten",
    "sg:postcode":"6963",
    "sg:province":"Ticino",
    "wof:name":"Associazione Gruppo Aerostatico Ticino",
    "wof:placetype":"venue"
},
  "geometry": {"coordinates":[8.9713754654,46.0199508667],"type":"Point"}
}