{
  "type": "Feature",
  "properties": {
    "iso:country":"CH",
    "sg:address":"Alpsteinstrasse 15c",
    "sg:city":"Herisau",
    "sg:orig_category":"Detailhandel mit Getr\u00e4nken Grosshandel mit Getr\u00e4nken",
    "sg:phone":"+41 71 351 13 24",
    "sg:postcode":"9100",
    "sg:province":"Appenzell Ausserrhoden",
    "wof:name":"Hans-ulrich Fischbacher",
    "wof:placetype":"venue"
},
  "geometry": {"coordinates":[9.2790699005,47.3781700134],"type":"Point"}
}