{
  "type": "Feature",
  "properties": {
    "addr:full":"B\u00fchl Gontenbad Gonten Appenzell Innerhoden 9108",
    "addr:postcode":"9108",
    "addr:street":"Buehl",
    "iso:country":"CH",
    "sg:address":"B\u00fchl Gontenbad",
    "sg:city":"Gonten",
    "sg:orig_category":"Betrieb von Sportanlagen",
    "sg:phone":"+41 71 795 40 60",
    "sg:postcode":"9108",
    "sg:province":"Appenzell Innerhoden",
    "wof:name":"Golf Und Country Ag",
    "wof:placetype":"venue"
},
  "geometry": {"coordinates":[9.343704,47.32608],"type":"Point"}
}