{
  "type": "Feature",
  "properties": {
    "iso:country":"CH",
    "sg:address":"Industriestrasse 10a",
    "sg:city":"M\u00fcnsingen",
    "sg:orig_category":"Elektroinstallation",
    "sg:phone":"+41 79 355 27 42",
    "sg:postcode":"3110",
    "sg:province":"Bern",
    "wof:name":"Stalder Pierre & Co \u00e9l\u00e9ctricit\u00e9 & T\u00e9l\u00e9matique",
    "wof:placetype":"venue"
},
  "geometry": {"coordinates":[6.8456931114,47.0926971436],"type":"Point"}
}