{
  "type": "Feature",
  "properties": {
    "iso:country":"CH",
    "sg:address":"Unter\u00e4schstrasse 3",
    "sg:city":"M\u00f6riken",
    "sg:classifiers":[
        {
            "category":"Building & Trades",
            "subcategory":"Cleaning & Sanitation",
            "type":"Services"
        }
    ],
    "sg:phone":"+41 62 893 32 50",
    "sg:postcode":"5103",
    "sg:province":"Aargau",
    "sg:tags":[
        "technical",
        "services"
    ],
    "wof:name":"H.u.b.i. Geb\u00e4udereinigungen Ag",
    "wof:placetype":"venue"
},
  "geometry": {"coordinates":[8.181177,47.415462],"type":"Point"}
}