{
  "type": "Feature",
  "properties": {
    "iso:country":"CH",
    "sg:address":"Huebstrasse 4",
    "sg:city":"Ipsach",
    "sg:orig_category":"Allgemeiner Hoch U Tiefbau",
    "sg:postcode":"2563",
    "sg:province":"Bern",
    "wof:name":"Lurati Ernesto.",
    "wof:placetype":"venue"
},
  "geometry": {"coordinates":[9.12836,46.237598],"type":"Point"}
}