{
  "type": "Feature",
  "properties": {
    "iso:country":"CH",
    "sg:address":"Via Simen 56",
    "sg:city":"Minusio",
    "sg:orig_category":"HOTELS: OHNE RESTAURANT Instandhaltung U Reparatur von Automobilen",
    "sg:phone":"+41 91 735 89 31",
    "sg:postcode":"6648",
    "sg:province":"Ticino",
    "wof:name":"Albergo Rivapiana",
    "wof:placetype":"venue"
},
  "geometry": {"coordinates":[8.819562912,46.1756095886],"type":"Point"}
}