{
  "type": "Feature",
  "properties": {
    "iso:country":"CH",
    "sg:address":"Chemin De Mornex 2",
    "sg:city":"Lausanne",
    "sg:orig_category":"Softwareentwicklung U beratung",
    "sg:phone":"+41 21 312 88 02",
    "sg:postcode":"1003",
    "sg:province":"Vaud",
    "wof:name":"Thien Ha-minh Pattern Recognition",
    "wof:placetype":"venue"
},
  "geometry": {"coordinates":[6.6295008659,46.5183753967],"type":"Point"}
}