{
  "type": "Feature",
  "properties": {
    "iso:country":"CH",
    "sg:address":"Bellacherstrasse 5",
    "sg:city":"Langendorf",
    "sg:orig_category":"Gesundheitswesen Kinesiologie",
    "sg:phone":"+41 27 946 86 56",
    "sg:postcode":"4513",
    "sg:province":"Solothurn",
    "wof:name":"Zentrum F\u00fcr Kinesiologie Visp, Amherd Hans-peter",
    "wof:placetype":"venue"
},
  "geometry": {"coordinates":[7.512556076,47.2159385681],"type":"Point"}
}