{
  "type": "Feature",
  "properties": {
    "iso:country":"CH",
    "sg:address":"Felmisrain 4",
    "sg:city":"Horw",
    "sg:orig_category":"Fotografische Ateliers",
    "sg:phone":"+41 41 340 77 14",
    "sg:postcode":"6048",
    "sg:province":"Luzern",
    "wof:name":"Peter Fischli Fotograf",
    "wof:placetype":"venue"
},
  "geometry": {"coordinates":[8.3234643936,47.0240402222],"type":"Point"}
}