{
  "type": "Feature",
  "properties": {
    "iso:country":"CH",
    "sg:address":"Grand-rue 87",
    "sg:city":"Chavornay",
    "sg:classifiers":[
        {
            "category":"Banks & Credit Unions",
            "subcategory":"Bank",
            "type":"Services"
        }
    ],
    "sg:phone":"+41 24 441 73 43",
    "sg:postcode":"1373",
    "sg:province":"Vaud",
    "wof:name":"Raiffeisen De La Plaine De L'orbe",
    "wof:placetype":"venue"
},
  "geometry": {"coordinates":[6.57049,46.708946],"type":"Point"}
}