{
  "type": "Feature",
  "properties": {
    "iso:country":"CH",
    "sg:address":"R\u00f6tistrasse 17 4500 Solothurn. Postfach",
    "sg:city":"Solothurn",
    "sg:orig_category":"Forst\u00e4mter",
    "sg:phone":"+41 52 741 42 34",
    "sg:postcode":"4502",
    "sg:province":"Solothurn",
    "wof:name":"Stadtforstverwaltung",
    "wof:placetype":"venue"
},
  "geometry": {"coordinates":[8.8593502045,47.6593933105],"type":"Point"}
}