{
  "type": "Feature",
  "properties": {
    "iso:country":"CH",
    "sg:address":"Hinterwuhrstrasse 17",
    "sg:city":"Andelfingen",
    "sg:orig_category":"Gartenbau",
    "sg:phone":"+41 52 317 12 06",
    "sg:postcode":"8450",
    "sg:province":"Z\u00fcrich",
    "wof:name":"Edwin Huber Gartenbaubetrieb",
    "wof:placetype":"venue"
},
  "geometry": {"coordinates":[8.6815576553,47.5923805237],"type":"Point"}
}