{
  "type": "Feature",
  "properties": {
    "iso:country":"CH",
    "sg:address":"Leimbachstrasse 107",
    "sg:city":"Z\u00fcrich",
    "sg:orig_category":"Sonstige Personenbef\u00f6rderung im Landverkehr Sonstige pers\u00f6nliche Dienstleistungen",
    "sg:phone":"+41 79 404 17 00",
    "sg:postcode":"8041",
    "sg:province":"Z\u00fcrich",
    "wof:name":"Al Car Limousine Bus-service, Horne Fredy",
    "wof:placetype":"venue"
},
  "geometry": {"coordinates":[8.5155639648,47.3302764893],"type":"Point"}
}