{
  "type": "Feature",
  "properties": {
    "iso:country":"CH",
    "sg:address":"Florimont Avenue De 6 1006 Lausanne. Postfach",
    "sg:city":"Lausanne",
    "sg:orig_category":"Grosshandel mit Werkzeugmaschinen",
    "sg:phone":"+41 32 968 64 50",
    "sg:postcode":"1006",
    "sg:province":"Vaud",
    "wof:name":"Ferner Machines Machines-outils",
    "wof:placetype":"venue"
},
  "geometry": {"coordinates":[6.8296809196,47.1061592102],"type":"Point"}
}