{
  "type": "Feature",
  "properties": {
    "iso:country":"CH",
    "sg:address":"3175",
    "sg:city":"Flamatt",
    "sg:orig_category":"Organisationen des Gesundheitswesen",
    "sg:phone":"+41 31 819 20 92",
    "sg:postcode":"3175",
    "sg:province":"Fribourg",
    "wof:name":"Samariterverein",
    "wof:placetype":"venue"
},
  "geometry": {"coordinates":[7.3235998154,46.8852806091],"type":"Point"}
}