{
  "type": "Feature",
  "properties": {
    "iso:country":"CH",
    "sg:address":"Rigistrasse 19",
    "sg:city":"Dierikon",
    "sg:orig_category":"Sonstiger spezialisierter Hoch U Tiefbau",
    "sg:phone":"+41 41 910 30 44",
    "sg:postcode":"6036",
    "sg:province":"Luzern",
    "wof:name":"Medi-tech Mengi Hans-ulrich Fugentechnik",
    "wof:placetype":"venue"
},
  "geometry": {"coordinates":[8.3702907562,47.0968132019],"type":"Point"}
}