{
  "type": "Feature",
  "properties": {
    "addr:full":"3971 Chermignon Valais 3971",
    "addr:postcode":"3971;3971",
    "iso:country":"CH",
    "sg:address":"3971",
    "sg:city":"Chermignon",
    "sg:orig_category":"Allgemeiner Hoch U Tiefbau",
    "sg:phone":"+41 79 628 56 62",
    "sg:postcode":"3971",
    "sg:province":"Valais",
    "wof:name":"Clivaz Charles.",
    "wof:placetype":"venue"
},
  "geometry": {"coordinates":[7.47849,46.283951],"type":"Point"}
}