{
  "type": "Feature",
  "properties": {
    "iso:country":"CH",
    "sg:address":"Avenue Rosemont 9",
    "sg:city":"Gen\u00e8ve",
    "sg:orig_category":"Datenverarbeitungsdienste",
    "sg:phone":"+41 22 735 77 87",
    "sg:postcode":"1208",
    "sg:province":"Gen\u00e8ve",
    "wof:name":"Image & Cie Multim\u00e9dia-switzerland",
    "wof:placetype":"venue"
},
  "geometry": {"coordinates":[6.172135,46.202232],"type":"Point"}
}