{
  "type": "Feature",
  "properties": {
    "addr:full":"Sch\u00fctzengasse 32 Grenchen Solothurn 2540",
    "addr:housenumber":"32",
    "addr:postcode":"2540",
    "addr:street":"Schuetzengasse",
    "iso:country":"CH",
    "sg:address":"Sch\u00fctzengasse 32",
    "sg:city":"Grenchen",
    "sg:classifiers":[
        {
            "category":"Manufacturing",
            "subcategory":"Tools & Machinery",
            "type":"Manufacturing & Wholesale Goods"
        }
    ],
    "sg:phone":"+41 32 655 71 71",
    "sg:postcode":"2540",
    "sg:province":"Solothurn",
    "sg:tags":[
        "part",
        "turned",
        "cnc"
    ],
    "wof:name":"Michel A Division Of Eta Sa",
    "wof:placetype":"venue"
},
  "geometry": {"coordinates":[7.391545,47.193264],"type":"Point"}
}