{
  "type": "Feature",
  "properties": {
    "iso:country":"CH",
    "sg:address":"Rue De Gen\u00e8ve 6",
    "sg:city":"Ch\u00eane-bourg",
    "sg:orig_category":"Detailhandel mit Geschenkartikeln U Souvenirs",
    "sg:phone":"+41 71 223 74 77",
    "sg:postcode":"1225",
    "sg:province":"Gen\u00e8ve",
    "wof:name":"Maria Nonnis Underground Trend-store",
    "wof:placetype":"venue"
},
  "geometry": {"coordinates":[9.3784675598,47.4250526428],"type":"Point"}
}