{
  "type": "Feature",
  "properties": {
    "iso:country":"CH",
    "sg:address":"Bleicheweg 5",
    "sg:city":"Dottikon",
    "sg:orig_category":"Sonstiger Grosshandel",
    "sg:phone":"+41 56 624 41 00",
    "sg:postcode":"5605",
    "sg:province":"Aargau",
    "wof:name":"Tudosit Gmbh",
    "wof:placetype":"venue"
},
  "geometry": {"coordinates":[8.2377958298,47.3839416504],"type":"Point"}
}