{
  "type": "Feature",
  "properties": {
    "iso:country":"CH",
    "sg:address":"Rue De Savoie 3c",
    "sg:city":"Gland",
    "sg:orig_category":"Unternehmensberatung",
    "sg:phone":"+41 22 364 63 70",
    "sg:postcode":"1196",
    "sg:province":"Vaud",
    "wof:name":"Mcd Conseil Sa",
    "wof:placetype":"venue"
},
  "geometry": {"coordinates":[6.2669801712,46.4212493896],"type":"Point"}
}