{
  "type": "Feature",
  "properties": {
    "iso:country":"CH",
    "sg:address":"Rue A.-ribaux 7",
    "sg:city":"Bevaix",
    "sg:orig_category":"Drogerien",
    "sg:phone":"+41 32 846 23 76",
    "sg:postcode":"2022",
    "sg:province":"Neuch\u00e2tel",
    "wof:name":"Agn\u00e8s Ir\u00e8ne Bigler Droguerie La Tisani\u00e8re",
    "wof:placetype":"venue"
},
  "geometry": {"coordinates":[6.8142910004,46.9309768677],"type":"Point"}
}