{
  "type": "Feature",
  "properties": {
    "iso:country":"CH",
    "sg:address":"Sonnegg",
    "sg:city":"Udligenswil",
    "sg:orig_category":"Haltung von Schweinen",
    "sg:phone":"+41 41 371 05 25",
    "sg:postcode":"6044",
    "sg:province":"Luzern",
    "wof:name":"Fritz Lustenberger Schweinem\u00e4sterei",
    "wof:placetype":"venue"
},
  "geometry": {"coordinates":[8.3981952667,47.0962715149],"type":"Point"}
}