{
  "type": "Feature",
  "properties": {
    "iso:country":"CH",
    "sg:address":"Neuhaus",
    "sg:city":"Ochlenberg",
    "sg:orig_category":"Primarschulen",
    "sg:phone":"+41 62 961 71 50",
    "sg:postcode":"3367",
    "sg:province":"Bern",
    "wof:name":"Primarschule",
    "wof:placetype":"venue"
},
  "geometry": {"coordinates":[7.7518978119,47.1551971436],"type":"Point"}
}