{
  "type": "Feature",
  "properties": {
    "iso:country":"CH",
    "sg:address":"6967 Dino. Postfach",
    "sg:city":"Sonvico",
    "sg:orig_category":"Non-Classified Establishments",
    "sg:phone":"+41 91 943 67 77",
    "sg:postcode":"6968",
    "sg:province":"Ticino",
    "wof:name":"Meneghelli Monumenti Funebri Sagl Monumenti Funebri, Marmi, Graniti; Comm.",
    "wof:placetype":"venue"
},
  "geometry": {"coordinates":[8.9861059189,46.0532226562],"type":"Point"}
}