{
  "type": "Feature",
  "properties": {
    "iso:country":"CH",
    "sg:address":"Chemin De L'epignau 28",
    "sg:city":"Chavornay",
    "sg:orig_category":"Sonstiger Grosshandel",
    "sg:phone":"+41 24 441 07 82",
    "sg:postcode":"1373",
    "sg:province":"Vaud",
    "wof:name":"Werner Gans Gmt Trading",
    "wof:placetype":"venue"
},
  "geometry": {"coordinates":[6.57020998,46.7084503174],"type":"Point"}
}