{
  "type": "Feature",
  "properties": {
    "iso:country":"CH",
    "sg:address":"Route De Saillon 1926 Fully Case Postale 126",
    "sg:city":"Fully",
    "sg:orig_category":"Grosshandel mit Obst U Gem\u00fcse",
    "sg:phone":"+41 27 746 36 52",
    "sg:postcode":"1926",
    "sg:province":"Valais",
    "wof:name":"Michel & Samuel Granges Fruits & L\u00e9gumes",
    "wof:placetype":"venue"
},
  "geometry": {"coordinates":[7.1190600395,46.1393203735],"type":"Point"}
}