{
  "type": "Feature",
  "properties": {
    "iso:country":"CH",
    "sg:address":"Fronhofen",
    "sg:city":"Stansstad",
    "sg:orig_category":"Bauschreinerei Herstellung von M\u00f6beln verschiedener Art",
    "sg:phone":"+41 41 610 13 04",
    "sg:postcode":"6362",
    "sg:province":"Nidwalden",
    "wof:name":"Walter & Richard Z'rotz Bau-& M\u00f6belschreinerei",
    "wof:placetype":"venue"
},
  "geometry": {"coordinates":[8.350397,46.970692],"type":"Point"}
}