{
  "type": "Feature",
  "properties": {
    "iso:country":"CH",
    "sg:address":"Rue Marterey 2",
    "sg:city":"Lausanne",
    "sg:orig_category":"Detailhandel mit Bekleidung Detailhandel mit Geschenkartikeln U Souvenirs",
    "sg:phone":"+41 21 312 92 30",
    "sg:postcode":"1005",
    "sg:province":"Vaud",
    "wof:name":"Boutique Centaure S\u00e0rl",
    "wof:placetype":"venue"
},
  "geometry": {"coordinates":[6.637825,46.51973],"type":"Point"}
}