{
  "type": "Feature",
  "properties": {
    "iso:country":"CH",
    "sg:address":"Silbergasse 8",
    "sg:city":"Biel/bienne",
    "sg:orig_category":"Detailhandel mit Haustieren U zoologischem Bedarf Fachdetailhandel in Verkaufsr\u00e4umen",
    "sg:phone":"+41 32 325 31 15",
    "sg:postcode":"2502",
    "sg:province":"Bern",
    "wof:name":"Aare-shop Gmbh",
    "wof:placetype":"venue"
},
  "geometry": {"coordinates":[7.2466950417,47.1338691711],"type":"Point"}
}