{
  "type": "Feature",
  "properties": {
    "iso:country":"CH",
    "sg:address":"Mulchlingerstrasse 135 8400 Winterthur. Postfach",
    "sg:city":"Seen",
    "sg:orig_category":"Elektrizit\u00e4tsversorgung",
    "sg:phone":"+41 71 755 38 32",
    "sg:postcode":"8405",
    "sg:province":"Z\u00fcrich",
    "wof:name":"Alka-tech Langenegger A.",
    "wof:placetype":"venue"
},
  "geometry": {"coordinates":[9.6193599701,47.3676338196],"type":"Point"}
}