{
  "type": "Feature",
  "properties": {
    "iso:country":"CH",
    "sg:address":"M\u00fchle 381",
    "sg:city":"Biembach",
    "sg:orig_category":"Sportvereine Sch\u00fctzen",
    "sg:postcode":"3419",
    "sg:province":"Bern",
    "wof:name":"Sch\u00fctzengesellschaft Mirchel",
    "wof:placetype":"venue"
},
  "geometry": {"coordinates":[7.628308773,47.0022506714],"type":"Point"}
}