{
  "type": "Feature",
  "properties": {
    "iso:country":"CH",
    "sg:address":"Grossmatte 10",
    "sg:city":"Reiden",
    "sg:orig_category":"Erbringung von sonstigen Dienstleistungen f\u00fcr Unterhaltung, Erholung U Freizeit",
    "sg:phone":"+41 41 850 42 60",
    "sg:postcode":"6260",
    "sg:province":"Luzern",
    "wof:name":"Briventa Show-agentur J. Zemp",
    "wof:placetype":"venue"
},
  "geometry": {"coordinates":[7.9698271751,47.2406272888],"type":"Point"}
}