{
  "type": "Feature",
  "properties": {
    "iso:country":"CH",
    "sg:address":"Nonnenweg 51",
    "sg:city":"Basel",
    "sg:orig_category":"Werbegrafikateliers",
    "sg:phone":"+41 61 261 35 05",
    "sg:postcode":"4055",
    "sg:province":"Basel-Stadt",
    "wof:name":"Christoph Aeppli Grafiker",
    "wof:placetype":"venue"
},
  "geometry": {"coordinates":[7.5750508308,47.5592384338],"type":"Point"}
}