{
  "type": "Feature",
  "properties": {
    "iso:country":"CH",
    "sg:address":"Gr\u00fcnaustrasse 7 9326 Horn. Postfach",
    "sg:city":"Horn",
    "sg:orig_category":"Unclassifiable Establishments",
    "sg:postcode":"9326",
    "sg:province":"Thurgau",
    "wof:name":"Plt Personal Language Trainer Gmbh Anbieten Von Personalisiertem Sprach- U. Kommunikationstraining Usw",
    "wof:placetype":"venue"
},
  "geometry": {"coordinates":[9.457367897,47.4921035767],"type":"Point"}
}