{
  "type": "Feature",
  "properties": {
    "iso:country":"CH",
    "sg:address":"Dorfstrasse 35",
    "sg:city":"Seeberg",
    "sg:orig_category":"Elektro- and elektronische Maschinen Grosshandel",
    "sg:phone":"+41 62 968 17 57",
    "sg:postcode":"3365",
    "sg:province":"Bern",
    "wof:name":"Porag Ag F\u00fcr Alternativenergiesysteme",
    "wof:placetype":"venue"
},
  "geometry": {"coordinates":[7.6665067673,47.1547584534],"type":"Point"}
}