{
  "type": "Feature",
  "properties": {
    "iso:country":"CH",
    "sg:address":"Dammweg 7",
    "sg:city":"Rupperswil",
    "sg:orig_category":"Unclassifiable Establishments",
    "sg:postcode":"5102",
    "sg:province":"Aargau",
    "wof:name":"Gloor Engineering And Consulting",
    "wof:placetype":"venue"
},
  "geometry": {"coordinates":[8.1308059692,47.4048347473],"type":"Point"}
}