{
  "type": "Feature",
  "properties": {
    "iso:country":"CH",
    "sg:address":"Talackerstrasse 15",
    "sg:city":"Uster",
    "sg:orig_category":"Geb\u00e4ude, Wohnungsreinigung",
    "sg:phone":"+41 19405869",
    "sg:postcode":"8610",
    "sg:province":"Z\u00fcrich",
    "wof:name":"Hermine Thum Reinigungen",
    "wof:placetype":"venue"
},
  "geometry": {"coordinates":[8.7164087296,47.3444442749],"type":"Point"}
}