{
  "type": "Feature",
  "properties": {
    "iso:country":"CH",
    "sg:address":"Austrasse 2",
    "sg:city":"Oberwichtrach",
    "sg:orig_category":"Mit dem Versicherungsgewerbe verbundene T\u00e4tigkeiten Vermittlung von Immobilien",
    "sg:phone":"+41 79 301 81 82",
    "sg:postcode":"3114",
    "sg:province":"Bern",
    "wof:name":"Ava Concept Ag",
    "wof:placetype":"venue"
},
  "geometry": {"coordinates":[7.5765061378,46.8433647156],"type":"Point"}
}