{
  "type": "Feature",
  "properties": {
    "iso:country":"CH",
    "sg:address":"Rue Du Village 12",
    "sg:city":"Mies",
    "sg:orig_category":"Kosmetikinstitute",
    "sg:phone":"+41 22 779 05 95",
    "sg:postcode":"1295",
    "sg:province":"Vaud",
    "wof:name":"Sylvie Maurer Institut De Beaut\u00e9 Scarlett",
    "wof:placetype":"venue"
},
  "geometry": {"coordinates":[6.1714510918,46.3052558899],"type":"Point"}
}