{
  "type": "Feature",
  "properties": {
    "iso:country":"CH",
    "sg:address":"Oetlingerstrasse 10",
    "sg:city":"Basel",
    "sg:orig_category":"Datenverarbeitungsdienste Logistikberatung",
    "sg:phone":"+41 56 641 02 82",
    "sg:postcode":"4057",
    "sg:province":"Basel-Stadt",
    "wof:name":"Hug Logistic Consulting Gmbh",
    "wof:placetype":"venue"
},
  "geometry": {"coordinates":[8.38646,47.335228],"type":"Point"}
}