{
  "type": "Feature",
  "properties": {
    "addr:full":"Chemin Poya Oron-la-ville Vaud 1610",
    "addr:postcode":"1610",
    "addr:street":"Chemin Poya",
    "iso:country":"CH",
    "sg:address":"Chemin Poya",
    "sg:city":"Oron-la-ville",
    "sg:orig_category":"Bauschreinerei Herstellung von M\u00f6beln verschiedener Art",
    "sg:phone":"+41 21 907 72 46",
    "sg:postcode":"1610",
    "sg:province":"Vaud",
    "wof:name":"Pierre T\u00e9saury & Fils Menuiserie & \u00e9b\u00e9nisterie",
    "wof:placetype":"venue"
},
  "geometry": {"coordinates":[6.827612,46.572205],"type":"Point"}
}