{
  "type": "Feature",
  "properties": {
    "iso:country":"CH",
    "sg:address":"Chrosweg 127",
    "sg:city":"Twann",
    "sg:orig_category":"Sonstiges Gesundheitswesen",
    "sg:phone":"+41 32 315 21 45",
    "sg:postcode":"2513",
    "sg:province":"Bern",
    "wof:name":"Krankenmobilienmagazin",
    "wof:placetype":"venue"
},
  "geometry": {"coordinates":[7.1596560478,47.0954055786],"type":"Point"}
}