{
  "type": "Feature",
  "properties": {
    "iso:country":"CH",
    "sg:address":"Hofrain 18",
    "sg:city":"Unterehrendingen",
    "sg:orig_category":"Herstellung von Hebezeugen U F\u00f6rdermitteln Vermietung von Baumaschinen U ger\u00e4ten mit Bedienungsperso",
    "sg:phone":"+41 56 222 45 11",
    "sg:postcode":"5424",
    "wof:name":"Kaufmann Kranservice Gmbh",
    "wof:placetype":"venue"
},
  "geometry": {"coordinates":[8.3500461578,47.4990921021],"type":"Point"}
}