{
  "type": "Feature",
  "properties": {
    "iso:country":"CH",
    "sg:address":"Freiburgstrasse 49",
    "sg:city":"Biel/bienne",
    "sg:classifiers":[
        {
            "category":"Manufacturing",
            "subcategory":"Glass & Minerals",
            "type":"Manufacturing & Wholesale Goods"
        }
    ],
    "sg:phone":"+41 32 322 28 44",
    "sg:postcode":"2503",
    "sg:province":"Bern",
    "sg:tags":[
        "flat"
    ],
    "wof:name":"Jean M\u00fcller Glas Ag",
    "wof:placetype":"venue"
},
  "geometry": {"coordinates":[7.2500982285,47.1330947876],"type":"Point"}
}