{
  "type": "Feature",
  "properties": {
    "iso:country":"CH",
    "sg:address":"Via Frasca 3",
    "sg:city":"Lugano",
    "sg:orig_category":"Handel mit Automobilteilen U Zubeh\u00f6r Handelsvermittlung U Grosshandel mit Automobilen",
    "sg:phone":"+41 91 921 30 16",
    "sg:postcode":"6900",
    "sg:province":"Ticino",
    "wof:name":"Rizzi Ing. Onorato Sa",
    "wof:placetype":"venue"
},
  "geometry": {"coordinates":[8.9546527863,46.0062141418],"type":"Point"}
}