{
  "type": "Feature",
  "properties": {
    "iso:country":"CH",
    "sg:address":"Maiholzstrasse 19",
    "sg:city":"Frauenfeld",
    "sg:orig_category":"Wirtschaftspr\u00fcfung, Steuerberatung U Treuhand",
    "sg:phone":"+41 21 944 69 74",
    "sg:postcode":"8500",
    "sg:province":"Thurgau",
    "wof:name":"Alexandre Vodoz Bureau De Comptabilit\u00e9",
    "wof:placetype":"venue"
},
  "geometry": {"coordinates":[6.8571882248,46.4576644897],"type":"Point"}
}