{
  "type": "Feature",
  "properties": {
    "iso:country":"CH",
    "sg:address":"Eschenring 13",
    "sg:city":"Zug",
    "sg:orig_category":"Unternehmensberatung Wirtschaftspr\u00fcfung, Steuerberatung U Treuhand",
    "sg:phone":"+41 41 711 12 79",
    "sg:postcode":"6300",
    "sg:province":"Zug",
    "wof:name":"Cinic Ag",
    "wof:placetype":"venue"
},
  "geometry": {"coordinates":[8.5176277161,47.1820678711],"type":"Point"}
}