{
  "type": "Feature",
  "properties": {
    "iso:country":"CH",
    "sg:address":"R\u00fcbackerstrasse 22",
    "sg:city":"R\u00f6schenz",
    "sg:orig_category":"Architektur U Ingenieurb\u00fcros",
    "sg:phone":"+41 91 857 89 45",
    "sg:postcode":"4244",
    "sg:province":"Basel-Landschaft",
    "wof:name":"Guidotti Giacomo & Guidotti Riccarda Architetti Dipl. Epfl/sia",
    "wof:placetype":"venue"
},
  "geometry": {"coordinates":[8.995528,46.187714],"type":"Point"}
}