{
  "type": "Feature",
  "properties": {
    "iso:country":"CH",
    "sg:address":"Bogenstrasse 14",
    "sg:city":"Oberhelfenschwil",
    "sg:orig_category":"Sanit\u00e4rinstallation U Spenglerei Zimmerei, Dachdeckerei, Bauspenglerei U Abdichtung",
    "sg:phone":"+41 71 374 27 65",
    "sg:postcode":"9621",
    "sg:province":"St. Gallen",
    "wof:name":"K\u00fchne Fritz Bedachungen + Spenglerei",
    "wof:placetype":"venue"
},
  "geometry": {"coordinates":[9.1100273132,47.3555145264],"type":"Point"}
}