{
  "type": "Feature",
  "properties": {
    "iso:country":"CH",
    "sg:address":"Rue Antoine-carteret 7",
    "sg:city":"Gen\u00e8ve",
    "sg:orig_category":"Malerei",
    "sg:phone":"+41 22 733 22 83",
    "sg:postcode":"1202",
    "sg:province":"Gen\u00e8ve",
    "wof:name":"Giacomo Panozzo Entreprise De Peinture",
    "wof:placetype":"venue"
},
  "geometry": {"coordinates":[6.1322312355,46.211643219],"type":"Point"}
}