{
  "type": "Feature",
  "properties": {
    "iso:country":"CH",
    "sg:address":"Hedwigstrasse 3 8000 Z\u00fcrich. Postfach 8032 Z\u00fcrich",
    "sg:city":"Zust",
    "sg:orig_category":"Unternehmensberatung",
    "sg:postcode":"32",
    "wof:name":"Hrs Human Resource Services Zemp Rolf",
    "wof:placetype":"venue"
},
  "geometry": {"coordinates":[8.5626602173,47.36120224],"type":"Point"}
}