{
  "type": "Feature",
  "properties": {
    "iso:country":"CH",
    "sg:address":"Bahnhofstrasse 8",
    "sg:city":"Herzogenbuchsee",
    "sg:orig_category":"Softwareentwicklung U beratung",
    "sg:phone":"+41 62 961 93 70",
    "sg:postcode":"3360",
    "sg:province":"Bern",
    "wof:name":"Wysh Computers Gmbh",
    "wof:placetype":"venue"
},
  "geometry": {"coordinates":[7.7033519745,47.1877975464],"type":"Point"}
}