{
  "type": "Feature",
  "properties": {
    "iso:country":"CH",
    "sg:address":"Rheinparkstrasse 10",
    "sg:city":"Birsfelden",
    "sg:orig_category":"Vorschulen, Kinderg\u00e4rten",
    "sg:phone":"+41 61 311 60 04",
    "sg:postcode":"4127",
    "sg:province":"Basel-Landschaft",
    "wof:name":"Kindergarten Stieracker",
    "wof:placetype":"venue"
},
  "geometry": {"coordinates":[7.6227459908,47.5569229126],"type":"Point"}
}