{
  "type": "Feature",
  "properties": {
    "iso:country":"CH",
    "sg:address":"Stelzenstrasse 4",
    "sg:city":"Glattbrugg",
    "sg:orig_category":"Unclassifiable Establishments",
    "sg:postcode":"8152",
    "sg:province":"Z\u00fcrich",
    "wof:name":"Ekeauzamd Holding",
    "wof:placetype":"venue"
},
  "geometry": {"coordinates":[8.55950737,47.4252357483],"type":"Point"}
}