{
  "type": "Feature",
  "properties": {
    "addr:full":"Verenaweg 7 M\u00e4nnedorf Z\u00fcrich 8708",
    "addr:housenumber":"7",
    "addr:postcode":"8708",
    "addr:street":"Verenaweg;Zuerich",
    "iso:country":"CH",
    "sg:address":"Verenaweg 7",
    "sg:city":"M\u00e4nnedorf",
    "sg:orig_category":"Detailhandel mit Damenbekleidung",
    "sg:phone":"+41 19200235",
    "sg:postcode":"8708",
    "sg:province":"Z\u00fcrich",
    "wof:name":"Corinne Perriard Couture",
    "wof:placetype":"venue"
},
  "geometry": {"coordinates":[8.689703,47.25491],"type":"Point"}
}