{
  "type": "Feature",
  "properties": {
    "iso:country":"CH",
    "sg:address":"Bahnhofplatz",
    "sg:city":"Lauterbrunnen",
    "sg:orig_category":"Reiseb\u00fcros U Reiseveranstalter",
    "sg:phone":"+41 33 822 08 24",
    "sg:postcode":"3822",
    "sg:province":"Bern",
    "wof:name":"Wenger Reisen Ag",
    "wof:placetype":"venue"
},
  "geometry": {"coordinates":[7.8619971275,46.6743774414],"type":"Point"}
}