{
  "type": "Feature",
  "properties": {
    "iso:country":"CH",
    "sg:address":"Rue Des Casernes 36",
    "sg:city":"Sion",
    "sg:orig_category":"Detailhandel mit Zeitungen U Zeitschriften Kioske",
    "sg:phone":"+41 27 203 36 46",
    "sg:postcode":"1950",
    "sg:province":"Valais",
    "wof:name":"Jacqueline De Preux Kiosque De Casernes",
    "wof:placetype":"venue"
},
  "geometry": {"coordinates":[7.3756680489,46.2277526855],"type":"Point"}
}