{
  "type": "Feature",
  "properties": {
    "iso:country":"CH",
    "sg:address":"Luzernstrasse 60 4553 Subingen. Postfach 243",
    "sg:city":"Subingen",
    "sg:orig_category":"Autogaragen",
    "sg:phone":"+41 32 614 17 53",
    "sg:postcode":"4553",
    "sg:province":"Solothurn",
    "wof:name":"Roland M\u00fcller Autogarage",
    "wof:placetype":"venue"
},
  "geometry": {"coordinates":[7.622155,47.193562],"type":"Point"}
}