{
  "type": "Feature",
  "properties": {
    "iso:country":"CH",
    "sg:address":"Kanalstrasse 8",
    "sg:city":"Dietikon",
    "sg:orig_category":"Grosshandel mit B\u00fcromaschinen Grosshandel mit Datenverarbeitungsger\u00e4ten",
    "sg:phone":"+41 32 653 00 12",
    "sg:postcode":"8953",
    "sg:province":"Z\u00fcrich",
    "wof:name":"Wato-soft Ag Edv - Hard - & Softwarel\u00f6sungen",
    "wof:placetype":"venue"
},
  "geometry": {"coordinates":[7.3626418114,47.1810264587],"type":"Point"}
}