{
  "type": "Feature",
  "properties": {
    "iso:country":"CH",
    "sg:address":"Moosstrasse 25",
    "sg:city":"Z\u00fcrich",
    "sg:orig_category":"Vereine Frauen",
    "sg:postcode":"8038",
    "sg:province":"Z\u00fcrich",
    "wof:name":"Frauenpodium Z\u00fcrich 2",
    "wof:placetype":"venue"
},
  "geometry": {"coordinates":[8.5289306641,47.3385162354],"type":"Point"}
}