{
  "type": "Feature",
  "properties": {
    "iso:country":"CH",
    "sg:address":"Wittlingerstrasse 138 4058 Basel. Postfach",
    "sg:city":"Riehen",
    "sg:orig_category":"Grosshandel mit chemischen Erzeugnissen",
    "sg:phone":"+41 91 608 10 41",
    "sg:postcode":"4125",
    "sg:province":"Basel-Stadt",
    "wof:name":"Maricelli Angela",
    "wof:placetype":"venue"
},
  "geometry": {"coordinates":[8.8408298492,46.0080795288],"type":"Point"}
}