{
  "type": "Feature",
  "properties": {
    "iso:country":"CH",
    "sg:address":"Freiburgstrasse 576",
    "sg:city":"Niederwangen",
    "sg:classifiers":[
        {
            "category":"Government",
            "subcategory":"Police Station",
            "type":"Public Place"
        }
    ],
    "sg:phone":"+41 31 981 29 39",
    "sg:postcode":"3172",
    "sg:province":"Bern",
    "sg:tags":[
        "anodizing"
    ],
    "wof:name":"Schlierholz Eloxal Ag",
    "wof:placetype":"venue"
},
  "geometry": {"coordinates":[7.375572,46.923904],"type":"Point"}
}