{
  "type": "Feature",
  "properties": {
    "iso:country":"CH",
    "sg:address":"Kannenfeldstrasse 12",
    "sg:city":"Basel",
    "sg:orig_category":"Herstellung von nachrichtentechnischen Ger\u00e4ten U Einrichtungen",
    "sg:phone":"+41 61 321 03 73",
    "sg:postcode":"4056",
    "sg:province":"Basel-Stadt",
    "wof:name":"Intermedia-com Midik Erol",
    "wof:placetype":"venue"
},
  "geometry": {"coordinates":[7.5740270615,47.5625572205],"type":"Point"}
}