{
  "type": "Feature",
  "properties": {
    "iso:country":"CH",
    "sg:address":"Chemin Des Chalets 5 1279 Chavannes-de-bogis. Postfach",
    "sg:city":"Bogis-bossey",
    "sg:orig_category":"Public-Relations-Agenturen",
    "sg:phone":"+41 22 776 90 85",
    "sg:postcode":"1279",
    "sg:province":"Vaud",
    "wof:name":"Adequasys Sa Inc., Wilmington, Succursale De Chavannes-de-bogis",
    "wof:placetype":"venue"
},
  "geometry": {"coordinates":[6.1632637978,46.3424301147],"type":"Point"}
}