{
  "type": "Feature",
  "properties": {
    "iso:country":"CH",
    "sg:address":"B\u00e4rschwilerstrasse 4",
    "sg:city":"Basel",
    "sg:orig_category":"Detailhandel mit M\u00f6beln U Haushaltsgegenst\u00e4nden Detailhandel mit Teppichen",
    "sg:phone":"+41 61 361 04 05",
    "sg:postcode":"4000",
    "sg:province":"Basel-Stadt",
    "wof:name":"Rezvani Orientteppich-galerie",
    "wof:placetype":"venue"
},
  "geometry": {"coordinates":[7.5955238342,47.5423812866],"type":"Point"}
}