{
  "type": "Feature",
  "properties": {
    "addr:full":"Pury Place 7 Neuch\u00e2tel Neuch\u00e2tel 2000",
    "addr:housenumber":"7",
    "addr:postcode":"2000",
    "addr:street":"Pury Place",
    "iso:country":"CH",
    "sg:address":"Pury Place 7",
    "sg:city":"Neuch\u00e2tel",
    "sg:orig_category":"Architektur U Ingenieurb\u00fcros",
    "sg:postcode":"2000",
    "sg:province":"Neuch\u00e2tel",
    "wof:name":"Creas Architecture, Hasler Reynald Et Brun Roger",
    "wof:placetype":"venue"
},
  "geometry": {"coordinates":[6.929794,46.989944],"type":"Point"}
}