{
  "type": "Feature",
  "properties": {
    "iso:country":"CH",
    "sg:address":"Signalstrasse 9",
    "sg:city":"Rorschach",
    "sg:classifiers":[
        {
            "category":"Professional",
            "subcategory":"Employment Agencies",
            "type":"Services"
        }
    ],
    "sg:phone":"+41 71 223 18 23",
    "sg:postcode":"9400",
    "sg:province":"St. Gallen",
    "sg:tags":[
        "personal",
        "u",
        "stellenvermittlung"
    ],
    "wof:name":"Polygon Personal",
    "wof:placetype":"venue"
},
  "geometry": {"coordinates":[9.4921884537,47.4775123596],"type":"Point"}
}