{
  "type": "Feature",
  "properties": {
    "iso:country":"CH",
    "sg:address":"Grenzstrasse 40",
    "sg:city":"Fischbach-g\u00f6slikon",
    "sg:orig_category":"Geb\u00e4ude, Wohnungsreinigung",
    "sg:phone":"+41 56 611 03 86",
    "sg:postcode":"5525",
    "sg:province":"Aargau",
    "wof:name":"Snezana Pesic Geb\u00e4udereinigung",
    "wof:placetype":"venue"
},
  "geometry": {"coordinates":[8.3015451431,47.3749961853],"type":"Point"}
}