{
  "type": "Feature",
  "properties": {
    "iso:country":"CH",
    "sg:address":"Farnacker",
    "sg:city":"Riedst\u00e4tt",
    "sg:orig_category":"Sportvereine Sch\u00fctzen",
    "sg:phone":"+41 31 731 28 67",
    "sg:postcode":"3159",
    "sg:province":"Bern",
    "wof:name":"Sch\u00fctzengellschaft",
    "wof:placetype":"venue"
},
  "geometry": {"coordinates":[7.3200678825,46.7836265564],"type":"Point"}
}