{
  "type": "Feature",
  "properties": {
    "addr:full":"Im Br\u00fcggli 1 Arisdorf Basel-Landschaft 4422",
    "addr:housenumber":"1",
    "addr:postcode":"4422",
    "addr:street":"Im Brueggli",
    "iso:country":"CH",
    "sg:address":"Im Br\u00fcggli 1",
    "sg:city":"Arisdorf",
    "sg:orig_category":"Arztpraxen",
    "sg:phone":"+41 61 811 50 24",
    "sg:postcode":"4422",
    "sg:province":"Basel-Landschaft",
    "wof:name":"Dr.med.dieter M\u00fcller Arzt F\u00fcr Allgemeine Medizin",
    "wof:placetype":"venue"
},
  "geometry": {"coordinates":[7.76961,47.513069],"type":"Point"}
}