{
  "type": "Feature",
  "properties": {
    "iso:country":"CH",
    "sg:address":"3655",
    "sg:city":"Sigriswil",
    "sg:orig_category":"Detailhandel mit Waren verschiedener Art, Hauptrichtung Nahrungsmittel",
    "sg:postcode":"3655",
    "sg:province":"Bern",
    "wof:name":"Landwirtschaftliche Genossenschaft Siselen",
    "wof:placetype":"venue"
},
  "geometry": {"coordinates":[7.1840701103,47.0295181274],"type":"Point"}
}