{
  "type": "Feature",
  "properties": {
    "iso:country":"CH",
    "sg:address":"Le Ch\u00e2teau",
    "sg:city":"Allens",
    "sg:orig_category":"Ingenieurb\u00fcros Umwelttechnik and \u00d6kologie",
    "sg:phone":"+41 62 891 23 64",
    "sg:postcode":"1304",
    "sg:province":"Vaud",
    "wof:name":"Burger & Stocker Umweltberatung",
    "wof:placetype":"venue"
},
  "geometry": {"coordinates":[8.1729640961,47.3912353516],"type":"Point"}
}