{
  "type": "Feature",
  "properties": {
    "iso:country":"CH",
    "sg:address":"Steinwiesenstrasse 1 8952 Schlieren. Postfach",
    "sg:city":"Rorschacherberg",
    "sg:orig_category":"Unternehmensberatung",
    "sg:postcode":"9404",
    "sg:province":"St. Gallen",
    "wof:name":"Kmu Treuhand Limmattal Gmbh",
    "wof:placetype":"venue"
},
  "geometry": {"coordinates":[8.4412603378,47.3976783752],"type":"Point"}
}