{
  "type": "Feature",
  "properties": {
    "iso:country":"CH",
    "sg:address":"Alpenstrasse 3 8000 Z\u00fcrich. Postfach",
    "sg:city":"Z\u00fcrich",
    "sg:orig_category":"Pensionskassen",
    "sg:postcode":"8000",
    "sg:province":"Z\u00fcrich",
    "wof:name":"Personalvorsorgestiftung Der Mckinsey & Company, Inc. (switzerland), Wilmington, Glattbrugg Branch",
    "wof:placetype":"venue"
},
  "geometry": {"coordinates":[8.4809503555,47.3614616394],"type":"Point"}
}