{
  "type": "Feature",
  "properties": {
    "iso:country":"CH",
    "sg:address":"Neueretstrasse",
    "sg:city":"Gstaad",
    "sg:classifiers":[
        {
            "category":"Travel",
            "subcategory":"Hotels & Motels",
            "type":"Entertainment"
        }
    ],
    "sg:phone":"+41 33 744 34 22",
    "sg:postcode":"3780",
    "sg:province":"Bern",
    "sg:tags":[
        "hotels",
        "mit",
        "restaurant"
    ],
    "wof:name":"Hotel Le Grand Chalet",
    "wof:placetype":"venue"
},
  "geometry": {"coordinates":[7.2843160629,46.4778556824],"type":"Point"}
}