{
  "type": "Feature",
  "properties": {
    "iso:country":"CH",
    "sg:address":"Burgstrasse 4",
    "sg:city":"Z\u00fcrich",
    "sg:orig_category":"Erschliessung von Grundst\u00fccken",
    "sg:postcode":"8037",
    "sg:province":"Z\u00fcrich",
    "wof:name":"Genossenschaft Iglu Preisg\u00fcnstige Wohnungen F\u00fcr Ihre Mitglieder",
    "wof:placetype":"venue"
},
  "geometry": {"coordinates":[8.5277557373,47.3910102844],"type":"Point"}
}