{
  "type": "Feature",
  "properties": {
    "iso:country":"CH",
    "sg:address":"Blumenweg 8",
    "sg:city":"Thayngen",
    "sg:orig_category":"Landwirtschaftliche Genossenschaften",
    "sg:phone":"+41 52 649 16 02",
    "sg:postcode":"8240",
    "sg:province":"Schaffhausen",
    "wof:name":"Landw.genossenschaft Thayngen",
    "wof:placetype":"venue"
},
  "geometry": {"coordinates":[8.7034196854,47.7462005615],"type":"Point"}
}