{
  "type": "Feature",
  "properties": {
    "iso:country":"CH",
    "sg:address":"Piazza Besso 1 6900 Lugano. Postfach",
    "sg:city":"Lugano",
    "sg:classifiers":[
        {
            "category":"Bars & Pubs",
            "type":"Food & Drink"
        }
    ],
    "sg:phone":"+41 91 966 16 77",
    "sg:postcode":"6903",
    "sg:province":"Ticino",
    "sg:tags":[
        "restaurant"
    ],
    "wof:name":"Ristorante & Bar Giardino",
    "wof:placetype":"venue"
},
  "geometry": {"coordinates":[8.944524,46.005707],"type":"Point"}
}