{
  "type": "Feature",
  "properties": {
    "iso:country":"CH",
    "sg:address":"Gottardo Via San 53 6877 Coldrerio. Postfach",
    "sg:city":"Coldrerio",
    "sg:orig_category":"Reiseb\u00fcros U Reiseveranstalter",
    "sg:phone":"+41 32 341 43 35",
    "sg:postcode":"6877",
    "sg:province":"Ticino",
    "wof:name":"Vevav\u00e9lovacances Sagl Promozione, Sviluppo, Comm. Di Ogni Attivit\u00e0 Nel Sett. Del Turismo Ecc",
    "wof:placetype":"venue"
},
  "geometry": {"coordinates":[8.9825630188,45.8591957092],"type":"Point"}
}