{
  "type": "Feature",
  "properties": {
    "iso:country":"CH",
    "sg:address":"Schwendi 3818 Grindelwald. Postfach 74",
    "sg:city":"Grindelwald",
    "sg:classifiers":[
        {
            "category":"Restaurant",
            "type":"Food & Drink"
        }
    ],
    "sg:phone":"+41 79 656 53 18",
    "sg:postcode":"3818",
    "sg:province":"Bern",
    "wof:name":"Bergrestaurant Stieregg",
    "wof:placetype":"venue"
},
  "geometry": {"coordinates":[8.0026569366,46.6316947937],"type":"Point"}
}