{
  "type": "Feature",
  "properties": {
    "iso:country":"CH",
    "sg:address":"Avenue G\u00e9n\u00e9ral-guisan 44",
    "sg:city":"Vevey",
    "sg:orig_category":"Detailhandel mit Radio U Fernsehger\u00e4ten",
    "sg:phone":"+41 21 671 30 71",
    "sg:postcode":"1800",
    "sg:province":"Vaud",
    "wof:name":"Privatel Vd Sa",
    "wof:placetype":"venue"
},
  "geometry": {"coordinates":[6.5803780556,46.5378608704],"type":"Point"}
}