{
  "type": "Feature",
  "properties": {
    "iso:country":"CH",
    "sg:address":"Engelwisstrasse 3 8180 B\u00fclach. Postfach 58",
    "sg:city":"B\u00fclach",
    "sg:orig_category":"Mechanik Mechanische Werkst\u00e4tten",
    "sg:phone":"+41 56 282 17 70",
    "sg:postcode":"8180",
    "sg:province":"Z\u00fcrich",
    "wof:name":"Suhm Heinrich",
    "wof:placetype":"venue"
},
  "geometry": {"coordinates":[8.2746763229,47.4930534363],"type":"Point"}
}