{
  "type": "Feature",
  "properties": {
    "iso:country":"CH",
    "sg:address":"Florastrasse 32a 8610 Uster. Postfach",
    "sg:city":"Uster",
    "sg:orig_category":"Berufsberatungen Personal U Stellenvermittlung",
    "sg:phone":"+41 19943055",
    "sg:postcode":"8610",
    "sg:province":"Z\u00fcrich",
    "wof:name":"Peter Gisler Laufbahn-& Personalberatung",
    "wof:placetype":"venue"
},
  "geometry": {"coordinates":[8.723404,47.346664],"type":"Point"}
}