{
  "type": "Feature",
  "properties": {
    "iso:country":"CH",
    "sg:address":"6873",
    "sg:city":"Corteglia",
    "sg:orig_category":"Herstellung von Maschinen f\u00fcr das Druckgewerbe Herstellung von Metallerzeugnissen ohne Maschinenbau",
    "sg:phone":"+41 91 683 64 43",
    "sg:postcode":"6873",
    "sg:province":"Ticino",
    "wof:name":"Saturn Sa Fabbr.di Macchine & Apparecchi",
    "wof:placetype":"venue"
},
  "geometry": {"coordinates":[8.9946899414,45.8618392944],"type":"Point"}
}