{
  "type": "Feature",
  "properties": {
    "iso:country":"CH",
    "sg:address":"Thuraustrasse 3",
    "sg:city":"Wattwil",
    "sg:orig_category":"Detailhandel mit Uhren U Schmuck Fachdetailhandel in Verkaufsr\u00e4umen",
    "sg:phone":"+41 71 988 19 88",
    "sg:postcode":"9630",
    "sg:province":"St. Gallen",
    "wof:name":"Oberlin Alois",
    "wof:placetype":"venue"
},
  "geometry": {"coordinates":[9.0881061554,47.2997512817],"type":"Point"}
}