{
  "type": "Feature",
  "properties": {
    "iso:country":"CH",
    "sg:address":"Kanzleistrasse 10",
    "sg:city":"Wynau",
    "sg:orig_category":"Unclassifiable Establishments",
    "sg:postcode":"4923",
    "sg:province":"Bern",
    "wof:name":"Burkhalter Kleintransport",
    "wof:placetype":"venue"
},
  "geometry": {"coordinates":[7.8175339699,47.2556266785],"type":"Point"}
}