{
  "type": "Feature",
  "properties": {
    "iso:country":"CH",
    "sg:address":"Aarauerstrasse 101 5015 Niedererlinsbach. Postfach",
    "sg:city":"Niedererlinsbach",
    "sg:classifiers":[
        {
            "category":"Communications",
            "subcategory":"Radio Station",
            "type":"Services"
        }
    ],
    "sg:phone":"+41 62 844 40 24",
    "sg:postcode":"5015",
    "sg:province":"Solothurn",
    "sg:tags":[
        "fernsehanstalten",
        "u"
    ],
    "wof:name":"Skyvision Gmbh Dienstleistungen Im Bereich Rundfunk, Fernsehen U. Telekommunikation, Bes. Handel Mit Medienprodukten, Medienrechte Usw",
    "wof:placetype":"venue"
},
  "geometry": {"coordinates":[8.0088539124,47.3971252441],"type":"Point"}
}