{
  "type": "Feature",
  "properties": {
    "iso:country":"CH",
    "sg:address":"Hauptstrasse 39",
    "sg:city":"Kreuzlingen",
    "sg:orig_category":"Interessenvertretungen",
    "sg:postcode":"8280",
    "sg:province":"Thurgau",
    "wof:name":"Rotary Stiftung Kreuzlingen-konstanz",
    "wof:placetype":"venue"
},
  "geometry": {"coordinates":[9.1746692657,47.6502876282],"type":"Point"}
}