{
  "type": "Feature",
  "properties": {
    "iso:country":"CH",
    "sg:address":"H\u00f6henstrasse 26",
    "sg:city":"Ramlinsburg",
    "sg:orig_category":"Unternehmensberatung",
    "sg:phone":"+41 61 933 96 60",
    "sg:postcode":"4433",
    "sg:province":"Basel-Landschaft",
    "wof:name":"Cb Pharma Engineering Ag",
    "wof:placetype":"venue"
},
  "geometry": {"coordinates":[7.7688860893,47.4507255554],"type":"Point"}
}