{
  "type": "Feature",
  "properties": {
    "iso:country":"CH",
    "sg:address":"Gasstrasse 7",
    "sg:city":"Basel",
    "sg:orig_category":"Detailhandel mit elektrischen Haushalts-,Radio U Fernsehger\u00e4ten sowie Musikinstrumenten Detailhandel",
    "sg:phone":"+41 61 322 47 80",
    "sg:postcode":"4056",
    "sg:province":"Basel-Stadt",
    "wof:name":"Electronova Basel Gmbh",
    "wof:placetype":"venue"
},
  "geometry": {"coordinates":[7.5774469376,47.5703086853],"type":"Point"}
}