{
  "type": "Feature",
  "properties": {
    "iso:country":"CH",
    "sg:address":"Solothurnstrasse 76",
    "sg:city":"Oensingen",
    "sg:orig_category":"Nationale Postdienste",
    "sg:phone":"+41 62 396 24 20",
    "sg:postcode":"4702",
    "sg:province":"Solothurn",
    "wof:name":"Die Schweizerische Post",
    "wof:placetype":"venue"
},
  "geometry": {"coordinates":[7.7153968811,47.2897109985],"type":"Point"}
}