{
  "type": "Feature",
  "properties": {
    "iso:country":"CH",
    "sg:address":"Saint-pierre Rue 2 1003 Lausanne. Postfach",
    "sg:city":"Lausanne",
    "sg:orig_category":"Kauf U Verkauf von Immobilien auf eigene Rechnung",
    "sg:phone":"+41 21 312 00 34",
    "sg:postcode":"1003",
    "sg:province":"Vaud",
    "wof:name":"Jayet P. Courtier Patent\u00e9 En Immeubles.",
    "wof:placetype":"venue"
},
  "geometry": {"coordinates":[6.6367921829,46.5196075439],"type":"Point"}
}