{
  "type": "Feature",
  "properties": {
    "iso:country":"CH",
    "sg:address":"Haus Furri 3914 Blatten B. Naters. Postfach",
    "sg:city":"Visp",
    "sg:orig_category":"Detailhandel mit Waren verschiedener Art, Hauptrichtung Nahrungsmittel",
    "sg:postcode":"3930",
    "sg:province":"Valais",
    "wof:name":"Cabani Handels Gmbh",
    "wof:placetype":"venue"
},
  "geometry": {"coordinates":[7.9766812325,46.3631248474],"type":"Point"}
}