{
  "type": "Feature",
  "properties": {
    "iso:country":"CH",
    "sg:address":"Via Lucomagno 83",
    "sg:city":"Biasca",
    "sg:orig_category":"Malerei",
    "sg:phone":"+41 91 862 23 03",
    "sg:postcode":"6710",
    "sg:province":"Ticino",
    "wof:name":"Claude Cavaglieri Impresa Di Pittura",
    "wof:placetype":"venue"
},
  "geometry": {"coordinates":[8.9701004028,46.3646278381],"type":"Point"}
}