{
  "type": "Feature",
  "properties": {
    "iso:country":"CH",
    "sg:address":"Ursy-centre",
    "sg:city":"Ursy",
    "sg:classifiers":[
        {
            "category":"Restaurant",
            "type":"Food & Drink"
        }
    ],
    "sg:phone":"+41 21 909 00 98",
    "sg:postcode":"1670",
    "sg:province":"Fribourg",
    "wof:name":"Caf\u00e9-restaurant Le Flamboyant",
    "wof:placetype":"venue"
},
  "geometry": {"coordinates":[6.8359251022,46.6341934204],"type":"Point"}
}