{
  "type": "Feature",
  "properties": {
    "iso:country":"CH",
    "sg:address":"Aarauerstrasse 18",
    "sg:city":"Sch\u00f6ftland",
    "sg:orig_category":"Detailhandel mit Radio U Fernsehger\u00e4ten Detailhandel mit fotografischen Artikeln",
    "sg:phone":"+41 62 721 14 61",
    "sg:postcode":"5040",
    "sg:province":"Aargau",
    "wof:name":"Ernst L\u00fcscher Foto-video & Radio-tv",
    "wof:placetype":"venue"
},
  "geometry": {"coordinates":[8.051451683,47.3114242554],"type":"Point"}
}