{
  "type": "Feature",
  "properties": {
    "iso:country":"CH",
    "sg:address":"Hauptstrasse 1",
    "sg:city":"Worben",
    "sg:orig_category":"HOTELS: MIT RESTAURANT Kongress- and Tagungshotels mit Restaurant",
    "sg:phone":"+41 32 384 67 67",
    "sg:postcode":"3252",
    "sg:province":"Bern",
    "wof:name":"Seminarhotel Worbenbad",
    "wof:placetype":"venue"
},
  "geometry": {"coordinates":[7.2949929237,47.1021232605],"type":"Point"}
}