{
  "type": "Feature",
  "properties": {
    "iso:country":"CH",
    "sg:address":"Sch\u00fctzenhaus",
    "sg:city":"Beckenried",
    "sg:orig_category":"Sportvereine Sch\u00fctzen",
    "sg:phone":"+41 41 620 22 52",
    "sg:postcode":"6375",
    "sg:province":"Nidwalden",
    "wof:name":"Sch\u00fctzengesellschaft",
    "wof:placetype":"venue"
},
  "geometry": {"coordinates":[8.473195076,46.9684066772],"type":"Point"}
}