{
  "type": "Feature",
  "properties": {
    "iso:country":"CH",
    "sg:address":"Rebstockhalde 56",
    "sg:city":"Luzern",
    "sg:orig_category":"Architekturb\u00fcros",
    "sg:phone":"+41 41 370 34 35",
    "sg:postcode":"6006",
    "sg:province":"Luzern",
    "wof:name":"Peter Etter Architekturb\u00fcro",
    "wof:placetype":"venue"
},
  "geometry": {"coordinates":[8.350226,47.045311],"type":"Point"}
}