{
  "type": "Feature",
  "properties": {
    "iso:country":"CH",
    "sg:address":"Albisriederstrasse 278",
    "sg:city":"Z\u00fcrich",
    "sg:orig_category":"Pensionskassen",
    "sg:postcode":"8047",
    "sg:province":"Z\u00fcrich",
    "wof:name":"Fonds F\u00fcr Die Angestellten Und Arbeiter Der Firma Conrad & W\u00fcrmli Ag",
    "wof:placetype":"venue"
},
  "geometry": {"coordinates":[8.4915647507,47.377784729],"type":"Point"}
}