{
  "type": "Feature",
  "properties": {
    "iso:country":"CH",
    "sg:address":"Frauenfelderstrasse 5",
    "sg:city":"W\u00e4ngi",
    "sg:orig_category":"Herstellung von Metallkonstruktionen Innenausbau",
    "sg:phone":"+41 52 378 24 66",
    "sg:postcode":"9545",
    "sg:province":"Thurgau",
    "wof:name":"Rustika Gmbh",
    "wof:placetype":"venue"
},
  "geometry": {"coordinates":[8.952498436,47.4968643188],"type":"Point"}
}