{
  "type": "Feature",
  "properties": {
    "iso:country":"CH",
    "sg:address":"6344",
    "sg:city":"Meierskappel",
    "sg:orig_category":"Primarschulen",
    "sg:postcode":"6344",
    "sg:province":"Luzern",
    "wof:name":"Primarschule",
    "wof:placetype":"venue"
},
  "geometry": {"coordinates":[8.44328022,47.1246833801],"type":"Point"}
}