{
  "type": "Feature",
  "properties": {
    "addr:full":"K\u00f6nizstrasse 226 3097 Liebefeld. Postfach Liebefeld Bern 3097",
    "addr:housenumber":"226",
    "addr:postcode":"3097;postfach;3097",
    "addr:street":"Koenizstrasse",
    "iso:country":"CH",
    "sg:address":"K\u00f6nizstrasse 226 3097 Liebefeld. Postfach",
    "sg:city":"Liebefeld",
    "sg:orig_category":"Detailhandel mit B\u00fcchern, Zeitungen, Schreib U Papeteriewaren",
    "sg:phone":"+41 31 971 05 77",
    "sg:postcode":"3097",
    "sg:province":"Bern",
    "wof:name":"Papet Ag",
    "wof:placetype":"venue"
},
  "geometry": {"coordinates":[7.415993,46.930756],"type":"Point"}
}