{
  "type": "Feature",
  "properties": {
    "iso:country":"CH",
    "sg:address":"Via Ai Grotti 34",
    "sg:city":"Biasca",
    "sg:classifiers":[
        {
            "category":"Restaurant",
            "type":"Food & Drink"
        }
    ],
    "sg:phone":"+41 91 862 12 21",
    "sg:postcode":"6710",
    "sg:province":"Ticino",
    "wof:name":"Grotto Pini",
    "wof:placetype":"venue"
},
  "geometry": {"coordinates":[8.9753074646,46.365737915],"type":"Point"}
}