{
  "type": "Feature",
  "properties": {
    "iso:country":"CH",
    "sg:address":"Rothschild Rue 73 1202 Gen\u00e8ve. Postfach",
    "sg:city":"Gen\u00e8ve",
    "sg:orig_category":"Allgemeinbildende weiterf\u00fchrende Schulen",
    "sg:postcode":"1202",
    "sg:province":"Gen\u00e8ve",
    "wof:name":"Mutuelle D'ecoles Secondaires Alternatives (m.e.s.a.)",
    "wof:placetype":"venue"
},
  "geometry": {"coordinates":[6.14593,46.21619],"type":"Point"}
}