{
  "type": "Feature",
  "properties": {
    "iso:country":"CH",
    "sg:address":"Sporrengasse 4",
    "sg:city":"Schaffhausen",
    "sg:orig_category":"Detailhandel mit Geschenkartikeln U Souvenirs",
    "sg:phone":"+41 27 323 43 43",
    "sg:postcode":"8200",
    "sg:province":"Schaffhausen",
    "wof:name":"Edith Bovier Boutique Color Me",
    "wof:placetype":"venue"
},
  "geometry": {"coordinates":[7.3603730202,46.2344245911],"type":"Point"}
}