{
  "type": "Feature",
  "properties": {
    "iso:country":"CH",
    "sg:address":"Wilerstrasse 41",
    "sg:city":"Wattwil",
    "sg:orig_category":"Vermietung U Verpachtung von eigenen Immobilien Vermittlung von Immobilien",
    "sg:phone":"+41 55 410 55 66",
    "sg:postcode":"9630",
    "sg:province":"St. Gallen",
    "wof:name":"Diethelm & Kesselring Immobilien",
    "wof:placetype":"venue"
},
  "geometry": {"coordinates":[8.7947559357,47.2041931152],"type":"Point"}
}