{
  "type": "Feature",
  "properties": {
    "iso:country":"CH",
    "sg:address":"Leuholz 11",
    "sg:city":"Wangen",
    "sg:classifiers":[
        {
            "category":"Building & Trades",
            "subcategory":"Construction",
            "type":"Services"
        }
    ],
    "sg:phone":"+41 55 440 22 51",
    "sg:postcode":"8855",
    "sg:province":"Schwyz",
    "sg:tags":[
        "interior",
        "work"
    ],
    "wof:name":"Jost Stricker Holzbau",
    "wof:placetype":"venue"
},
  "geometry": {"coordinates":[8.8798856735,47.1935081482],"type":"Point"}
}