{
  "type": "Feature",
  "properties": {
    "iso:country":"CH",
    "sg:address":"6313",
    "sg:city":"Edlibach",
    "sg:classifiers":[
        {
            "category":"Travel",
            "subcategory":"Hotels & Motels",
            "type":"Entertainment"
        }
    ],
    "sg:phone":"+41 41 755 16 77",
    "sg:postcode":"6313",
    "sg:province":"Zug",
    "sg:tags":[
        "hotels",
        "mit",
        "restaurant"
    ],
    "wof:name":"Hotel Edlibacherhof",
    "wof:placetype":"venue"
},
  "geometry": {"coordinates":[8.5711402893,47.1822891235],"type":"Point"}
}