{
  "type": "Feature",
  "properties": {
    "iso:country":"CH",
    "sg:address":"Bahnhofstrasse 32",
    "sg:city":"N\u00e4fels",
    "sg:orig_category":"Wirtschaftspr\u00fcfung, Steuerberatung U Treuhand",
    "sg:postcode":"8752",
    "sg:province":"Glarus",
    "wof:name":"Treuhand L\u00fcdin, Nachfolger Balli Bruno",
    "wof:placetype":"venue"
},
  "geometry": {"coordinates":[7.864467144,46.6801986694],"type":"Point"}
}