{
  "type": "Feature",
  "properties": {
    "iso:country":"CH",
    "sg:address":"6527",
    "sg:city":"Lodrino",
    "sg:orig_category":"Primarschulen",
    "sg:phone":"+41 91 827 30 86",
    "sg:postcode":"6527",
    "sg:province":"Ticino",
    "wof:name":"Scuola Elementare",
    "wof:placetype":"venue"
},
  "geometry": {"coordinates":[9.1283597946,46.2375984192],"type":"Point"}
}