{
  "type": "Feature",
  "properties": {
    "iso:country":"CH",
    "sg:address":"Chemin Vignes 4",
    "sg:city":"Mont-sur-rolle",
    "sg:orig_category":"Physiotherapie",
    "sg:phone":"+41 21 826 04 12",
    "sg:postcode":"1185",
    "sg:province":"Vaud",
    "wof:name":"Elisabeth Ballenegger Physioth\u00e9rapie",
    "wof:placetype":"venue"
},
  "geometry": {"coordinates":[6.3479199409,46.4644203186],"type":"Point"}
}