{
  "type": "Feature",
  "properties": {
    "iso:country":"CH",
    "sg:address":"Altschulhaus",
    "sg:city":"Buchrain",
    "sg:orig_category":"Vorschulen, Kinderg\u00e4rten",
    "sg:phone":"+41 41 440 26 10",
    "sg:postcode":"6033",
    "sg:province":"Luzern",
    "wof:name":"Kindergarten",
    "wof:placetype":"venue"
},
  "geometry": {"coordinates":[8.3469352722,47.0954933167],"type":"Point"}
}