{
  "type": "Feature",
  "properties": {
    "iso:country":"CH",
    "sg:address":"Les Moulins 13 2608 Courtelary. Postfach",
    "sg:city":"Courtelary",
    "sg:orig_category":"Vermittlung von Immobilien Verwaltung von Immobilien",
    "sg:phone":"+41 79 358 61 49",
    "sg:postcode":"2608",
    "sg:province":"Bern",
    "wof:name":"Graber Comptabilit\u00e9",
    "wof:placetype":"venue"
},
  "geometry": {"coordinates":[7.0691480637,47.1786766052],"type":"Point"}
}