{
  "type": "Feature",
  "properties": {
    "iso:country":"CH",
    "sg:address":"Dorfstrasse 71",
    "sg:city":"Bolligen",
    "sg:orig_category":"Bauschreinerei",
    "sg:phone":"+41 31 921 90 62",
    "sg:postcode":"3065",
    "sg:province":"Bern",
    "wof:name":"Mauro Collalti Schreinerei",
    "wof:placetype":"venue"
},
  "geometry": {"coordinates":[7.50332,46.984539],"type":"Point"}
}