{
  "type": "Feature",
  "properties": {
    "iso:country":"CH",
    "sg:address":"Sch\u00f6nmattweg 30",
    "sg:city":"Belp",
    "sg:orig_category":"Technische B\u00fcros Hoch-& Tiefbau",
    "sg:phone":"+41 31 819 59 78",
    "sg:postcode":"3123",
    "sg:province":"Bern",
    "wof:name":"Bau & Planungsb\u00fcro Schmidt",
    "wof:placetype":"venue"
},
  "geometry": {"coordinates":[7.4999318123,46.8986167908],"type":"Point"}
}