{
  "type": "Feature",
  "properties": {
    "iso:country":"CH",
    "sg:address":"1338",
    "sg:city":"Ballaigues",
    "sg:orig_category":"Mechanik Mechanische Werkst\u00e4tten",
    "sg:phone":"+41 21 843 25 34",
    "sg:postcode":"1338",
    "sg:province":"Vaud",
    "wof:name":"Atelier M\u00e9canique Bise Et Chevalier.",
    "wof:placetype":"venue"
},
  "geometry": {"coordinates":[6.4168510437,46.7296981812],"type":"Point"}
}