{
  "type": "Feature",
  "properties": {
    "iso:country":"CH",
    "sg:address":"Pestalozziplatz 30 4552 Derendingen. Postfach",
    "sg:city":"Derendingen",
    "sg:orig_category":"Detailhandel mit Brot, Back U S\u00fcsswaren",
    "sg:phone":"+41 32 682 20 49",
    "sg:postcode":"4552",
    "sg:province":"Solothurn",
    "wof:name":"B\u00e4ckerei-konditorei Oesch",
    "wof:placetype":"venue"
},
  "geometry": {"coordinates":[7.59006,47.200336],"type":"Point"}
}