{
  "type": "Feature",
  "properties": {
    "iso:country":"CH",
    "sg:address":"Grundacherstrasse",
    "sg:city":"Nottwil",
    "sg:orig_category":"Handel mit Automobilen",
    "sg:phone":"+41 62 216 46 64",
    "sg:postcode":"6207",
    "sg:province":"Luzern",
    "wof:name":"H\u00e4usler Ren\u00e9 Automobile",
    "wof:placetype":"venue"
},
  "geometry": {"coordinates":[7.9852499962,47.3504867554],"type":"Point"}
}