{
  "type": "Feature",
  "properties": {
    "iso:country":"CH",
    "sg:address":"Ziegelfeldstr. 60",
    "sg:city":"Olten",
    "sg:classifiers":[
        {
            "category":"Professional",
            "subcategory":"Printing & Photocopies",
            "type":"Services"
        }
    ],
    "sg:phone":"+41 62 205 75 75",
    "sg:postcode":"4601",
    "sg:province":"Solothurn",
    "sg:tags":[
        "publishing"
    ],
    "wof:name":"Dietschi Ag",
    "wof:placetype":"venue"
},
  "geometry": {"coordinates":[7.897227,47.35157],"type":"Point"}
}