{
  "type": "Feature",
  "properties": {
    "iso:country":"CH",
    "sg:address":"Schmiedgasse 20",
    "sg:city":"Herisau",
    "sg:orig_category":"Kosmetikinstitute",
    "sg:phone":"+41 71 351 10 10",
    "sg:postcode":"9100",
    "sg:province":"Appenzell Ausserrhoden",
    "wof:name":"Beaurty Inn Ag",
    "wof:placetype":"venue"
},
  "geometry": {"coordinates":[9.2767953873,47.3852653503],"type":"Point"}
}