{
  "type": "Feature",
  "properties": {
    "iso:country":"CH",
    "sg:address":"Dorf 2 9107 Urn\u00e4sch. Postfach 161",
    "sg:city":"Urn\u00e4sch",
    "sg:orig_category":"Verwaltung der Rechtspflege, Gerichte",
    "sg:phone":"+41 71 891 15 07",
    "sg:postcode":"9107",
    "sg:province":"Appenzell Ausserrhoden",
    "wof:name":"Grundbuchamt",
    "wof:placetype":"venue"
},
  "geometry": {"coordinates":[9.5725831985,47.4196472168],"type":"Point"}
}