{
  "type": "Feature",
  "properties": {
    "iso:country":"CH",
    "sg:address":"Klosterstrasse 9",
    "sg:city":"Luzern",
    "sg:orig_category":"Druckweiterverarbeitung",
    "sg:phone":"+41 41 240 34 60",
    "sg:postcode":"6003",
    "sg:province":"Luzern",
    "wof:name":"Buchbinderei Schlapfer, Inhaber Ruepp Ceno",
    "wof:placetype":"venue"
},
  "geometry": {"coordinates":[8.3012304306,47.0494422913],"type":"Point"}
}