{
  "type": "Feature",
  "properties": {
    "iso:country":"CH",
    "sg:address":"Bechburgstrasse 29",
    "sg:city":"Zuchwil",
    "sg:orig_category":"Herstellung von elektrischen Lampen U Leuchten",
    "sg:phone":"+41 79 214 48 54",
    "sg:postcode":"4528",
    "sg:province":"Solothurn",
    "wof:name":"Pyramidex Ag",
    "wof:placetype":"venue"
},
  "geometry": {"coordinates":[7.5476799011,47.2057304382],"type":"Point"}
}