{
  "type": "Feature",
  "properties": {
    "iso:country":"CH",
    "sg:address":"Kastanienbaumstrasse 294",
    "sg:city":"Kastanienbaum",
    "sg:orig_category":"Reiseb\u00fcros U Reiseveranstalter",
    "sg:phone":"+41 41 340 32 62",
    "sg:postcode":"6047",
    "sg:province":"Luzern",
    "wof:name":"Individuelle Reiseberatung Metzler Ursula",
    "wof:placetype":"venue"
},
  "geometry": {"coordinates":[8.3381700516,47.0080604553],"type":"Point"}
}