{
  "type": "Feature",
  "properties": {
    "iso:country":"CH",
    "sg:address":"4469",
    "sg:city":"Anwil",
    "sg:classifiers":[
        {
            "category":"Restaurant",
            "type":"Food & Drink"
        }
    ],
    "sg:phone":"+41 61 991 01 27",
    "sg:postcode":"4469",
    "sg:province":"Basel-Landschaft",
    "wof:name":"Restaurant Reblaube",
    "wof:placetype":"venue"
},
  "geometry": {"coordinates":[7.9405698776,47.4523086548],"type":"Point"}
}