{
  "type": "Feature",
  "properties": {
    "iso:country":"CH",
    "sg:address":"Feldhofstrasse 2",
    "sg:city":"Uster",
    "sg:orig_category":"Tankstellen",
    "sg:postcode":"8610",
    "sg:province":"Z\u00fcrich",
    "wof:name":"Shell-service-station Im Brunnen, F. Roschi.",
    "wof:placetype":"venue"
},
  "geometry": {"coordinates":[8.7227134705,47.3521575928],"type":"Point"}
}