{
  "type": "Feature",
  "properties": {
    "iso:country":"CH",
    "sg:address":"Schossenrietstrasse 2 9442 Berneck. Postfach",
    "sg:city":"Berneck",
    "sg:orig_category":"Chemin\u00e9e- and Ofenbau",
    "sg:phone":"+41 71 744 19 19",
    "sg:postcode":"9442",
    "sg:province":"St. Gallen",
    "wof:name":"Scherrer Peter",
    "wof:placetype":"venue"
},
  "geometry": {"coordinates":[9.609984,47.422665],"type":"Point"}
}