{
  "type": "Feature",
  "properties": {
    "iso:country":"CH",
    "sg:address":"Birkenweg 26",
    "sg:city":"Worben",
    "sg:orig_category":"Reinigungsgewerbe",
    "sg:phone":"+41 32 385 13 89",
    "sg:postcode":"3252",
    "sg:province":"Bern",
    "wof:name":"Mbw Reinigungsservice, M. + M. Berlincourt",
    "wof:placetype":"venue"
},
  "geometry": {"coordinates":[7.3015680313,47.1025428772],"type":"Point"}
}