{
  "type": "Feature",
  "properties": {
    "iso:country":"CH",
    "sg:address":"Friedliweg 2",
    "sg:city":"Winterthur",
    "sg:orig_category":"Sportvereine Turnen Vereine Damen",
    "sg:phone":"+41 52 202 11 58",
    "sg:postcode":"8406",
    "sg:province":"Z\u00fcrich",
    "wof:name":"Frauenriege T\u00f6ss",
    "wof:placetype":"venue"
},
  "geometry": {"coordinates":[8.70499897,47.4948005676],"type":"Point"}
}