{
  "type": "Feature",
  "properties": {
    "iso:country":"CH",
    "sg:address":"Bahnhofstrasse 17 Wangs 7324 Vilters. Postfach",
    "sg:city":"Wangs",
    "sg:orig_category":"Non-Classified Establishments",
    "sg:postcode":"7323",
    "sg:province":"St. Gallen",
    "wof:name":"P & S Consulting Gmbh",
    "wof:placetype":"venue"
},
  "geometry": {"coordinates":[9.4516687393,47.0246124268],"type":"Point"}
}