{
  "type": "Feature",
  "properties": {
    "iso:country":"CH",
    "sg:address":"Obereyfeldweg 8",
    "sg:city":"Ittigen",
    "sg:orig_category":"Vorschulen, Kinderg\u00e4rten",
    "sg:phone":"+41 71 744 23 35",
    "sg:postcode":"3063",
    "sg:province":"Bern",
    "wof:name":"Kindergarten Fahr I & Ii",
    "wof:placetype":"venue"
},
  "geometry": {"coordinates":[9.6348695755,47.4514694214],"type":"Point"}
}