{
  "type": "Feature",
  "properties": {
    "iso:country":"CH",
    "sg:address":"Sch\u00fctzenrainweg 10 4125 Riehen. Postfach",
    "sg:city":"Riehen",
    "sg:orig_category":"Werbung",
    "sg:phone":"+41 61 641 60 30",
    "sg:postcode":"4125",
    "sg:province":"Basel-Stadt",
    "wof:name":"Hutter & Partner",
    "wof:placetype":"venue"
},
  "geometry": {"coordinates":[7.6548938751,47.5834121704],"type":"Point"}
}