{
  "type": "Feature",
  "properties": {
    "iso:country":"CH",
    "sg:address":"Hohlstrasse 534 8048 Z\u00fcrich. Postfach 838",
    "sg:city":"Z\u00fcrich",
    "sg:orig_category":"Softwareentwicklung U beratung Sonstige mit der Informatik verbundene T\u00e4tigkeiten",
    "sg:phone":"+41 14394500",
    "sg:postcode":"8048",
    "sg:province":"Z\u00fcrich",
    "wof:name":"Cognos (schweiz) Ag",
    "wof:placetype":"venue"
},
  "geometry": {"coordinates":[8.4923477173,47.389957428],"type":"Point"}
}