{
  "type": "Feature",
  "properties": {
    "iso:country":"CH",
    "sg:address":"Delfterstrasse 25/9 5004 Aarau. Postfach",
    "sg:city":"Aarau",
    "sg:orig_category":"Werbung",
    "sg:postcode":"5004",
    "sg:province":"Aargau",
    "wof:name":"Rewe Ag Werbeagentur, Handel M. Druckerzeugnissen Usw.",
    "wof:placetype":"venue"
},
  "geometry": {"coordinates":[8.060634613,47.4001655579],"type":"Point"}
}