{
  "type": "Feature",
  "properties": {
    "iso:country":"CH",
    "sg:address":"Via Maggio 1",
    "sg:city":"Lugano",
    "sg:orig_category":"Non-Classified Establishments",
    "sg:postcode":"6900",
    "sg:province":"Ticino",
    "wof:name":"Afit, Atelier F\u00fcr Illustration & Typografie, B\u00fcrgi & Partner",
    "wof:placetype":"venue"
},
  "geometry": {"coordinates":[8.5090780258,47.47265625],"type":"Point"}
}