{
  "type": "Feature",
  "properties": {
    "iso:country":"CH",
    "sg:address":"Rosenweg 8b",
    "sg:city":"Baar",
    "sg:orig_category":"Unclassifiable Establishments",
    "sg:postcode":"6340",
    "sg:province":"Zug",
    "wof:name":"Tax Solutions Gmbh",
    "wof:placetype":"venue"
},
  "geometry": {"coordinates":[7.4150500298,46.9140090942],"type":"Point"}
}