{
  "type": "Feature",
  "properties": {
    "iso:country":"CH",
    "sg:address":"Bahnhofstrasse 25",
    "sg:city":"Chur",
    "sg:classifiers":[
        {
            "category":"Travel",
            "subcategory":"Travel Agent",
            "type":"Entertainment"
        }
    ],
    "sg:postcode":"7002",
    "sg:province":"Graubunden",
    "wof:name":"Best Western Hotel Bahnhof",
    "wof:placetype":"venue"
},
  "geometry": {"coordinates":[8.6333179474,47.698387146],"type":"Point"}
}