{
  "type": "Feature",
  "properties": {
    "iso:country":"CH",
    "sg:address":"Schaffhauserstrasse 98",
    "sg:city":"Z\u00fcrich",
    "sg:orig_category":"Reinigungsgewerbe",
    "sg:postcode":"8057",
    "sg:province":"Z\u00fcrich",
    "wof:name":"Reinigungsinstitut Papatheodorou",
    "wof:placetype":"venue"
},
  "geometry": {"coordinates":[8.5398645401,47.394744873],"type":"Point"}
}