{
  "type": "Feature",
  "properties": {
    "iso:country":"CH",
    "sg:address":"Viale Alessandro Volta 2a",
    "sg:city":"Chiasso",
    "sg:orig_category":"Effektenvermittlung Broker Finanzierungsinstitutionen",
    "sg:phone":"+41 91 682 10 60",
    "sg:postcode":"6830",
    "sg:province":"Ticino",
    "wof:name":"Novaquotering Sa",
    "wof:placetype":"venue"
},
  "geometry": {"coordinates":[9.0317182541,45.833656311],"type":"Point"}
}