{
  "type": "Feature",
  "properties": {
    "iso:country":"CH",
    "sg:address":"Rue De La Servette 55",
    "sg:city":"Gen\u00e8ve",
    "sg:orig_category":"Detailhandel mit Schuhen Detailhandel mit Schuhen U Lederwaren",
    "sg:phone":"+41 22 734 96 90",
    "sg:postcode":"1202",
    "sg:province":"Gen\u00e8ve",
    "wof:name":"Sabot D'argent Commerce De Chaussures",
    "wof:placetype":"venue"
},
  "geometry": {"coordinates":[6.1343379021,46.211315155],"type":"Point"}
}