{
  "type": "Feature",
  "properties": {
    "iso:country":"CH",
    "sg:address":"D\u00fcnnernstrasse 376",
    "sg:city":"Matzendorf",
    "sg:orig_category":"Herstellung von Konstruktionsteilen, Fertigbauteilen U Ausbauelementen aus Holz",
    "sg:phone":"+41 27 475 17 38",
    "sg:postcode":"4713",
    "sg:province":"Solothurn",
    "wof:name":"Melly Gabriel",
    "wof:placetype":"venue"
},
  "geometry": {"coordinates":[7.6151399612,46.1528205872],"type":"Point"}
}