{
  "type": "Feature",
  "properties": {
    "iso:country":"CH",
    "sg:address":"5080",
    "sg:city":"Laufenburg",
    "sg:orig_category":"Bibliotheken U Archive Universit\u00e4tsspit\u00e4ler, Spit\u00e4ler f\u00fcr allgemeine Pflege",
    "sg:phone":"+41 62 874 03 33",
    "sg:postcode":"5080",
    "sg:province":"Aargau",
    "wof:name":"Regionalspital Laufenburg",
    "wof:placetype":"venue"
},
  "geometry": {"coordinates":[8.05965,47.5564],"type":"Point"}
}