{
  "type": "Feature",
  "properties": {
    "iso:country":"CH",
    "sg:address":"Bahnhofstrasse 1",
    "sg:city":"Wettingen",
    "sg:orig_category":"Herstellung von sonstigen M\u00f6beln Kunsthandel",
    "sg:phone":"+41 56 426 40 10",
    "sg:postcode":"5430",
    "sg:province":"Aargau",
    "wof:name":"Bild Und Rahmen Diehl Sibylle",
    "wof:placetype":"venue"
},
  "geometry": {"coordinates":[8.3182029724,47.4589958191],"type":"Point"}
}