{
  "type": "Feature",
  "properties": {
    "iso:country":"CH",
    "sg:address":"Route D'allaman",
    "sg:city":"Etoy",
    "sg:orig_category":"Rebbau",
    "sg:phone":"+41 21 808 76 52",
    "sg:postcode":"1163",
    "sg:province":"Vaud",
    "wof:name":"Aim\u00e9 Giriens Viticulteur",
    "wof:placetype":"venue"
},
  "geometry": {"coordinates":[6.4129710197,46.475025177],"type":"Point"}
}