{
  "type": "Feature",
  "properties": {
    "iso:country":"CH",
    "sg:address":"Theaterstrasse 20",
    "sg:city":"Basel",
    "sg:orig_category":"Softwareentwicklung U beratung",
    "sg:postcode":"4051",
    "sg:province":"Basel-Stadt",
    "wof:name":"Medianetcafe Schneider",
    "wof:placetype":"venue"
},
  "geometry": {"coordinates":[7.5895161629,47.5527191162],"type":"Point"}
}