{
  "type": "Feature",
  "properties": {
    "iso:country":"CH",
    "sg:address":"Rue Jacques-grosselin 25",
    "sg:city":"Carouge",
    "sg:classifiers":[
        {
            "category":"Professional",
            "subcategory":"Computer Services",
            "type":"Services"
        }
    ],
    "sg:phone":"+41 22 307 99 00",
    "sg:postcode":"1227",
    "sg:province":"Gen\u00e8ve",
    "sg:tags":[
        "development",
        "software"
    ],
    "wof:name":"Gestronic Sa",
    "wof:placetype":"venue"
},
  "geometry": {"coordinates":[6.13664,46.182159],"type":"Point"}
}