{
  "type": "Feature",
  "properties": {
    "iso:country":"CH",
    "sg:address":"Buchenstrasse 2",
    "sg:city":"Waldkirch",
    "sg:orig_category":"Herstellung von Teppichen",
    "sg:postcode":"9205",
    "sg:province":"St. Gallen",
    "wof:name":"Ebneter Guido Handelsagentur Gmbh",
    "wof:placetype":"venue"
},
  "geometry": {"coordinates":[9.2857542038,47.4670066833],"type":"Point"}
}