{
  "type": "Feature",
  "properties": {
    "iso:country":"CH",
    "sg:address":"Luzernerstrasse 34",
    "sg:city":"Kriens",
    "sg:orig_category":"Detailhandel mit M\u00f6beln U Haushaltsgegenst\u00e4nden Verlegen von Fussboden",
    "sg:phone":"+41 41 310 40 66",
    "sg:postcode":"6010",
    "sg:province":"Luzern",
    "wof:name":"Tedy Ag",
    "wof:placetype":"venue"
},
  "geometry": {"coordinates":[8.2840585709,47.0340843201],"type":"Point"}
}