{
  "type": "Feature",
  "properties": {
    "iso:country":"CH",
    "sg:address":"Schiffm\u00fchle 4 5300 Turgi. Postfach",
    "sg:city":"Turgi",
    "sg:orig_category":"Elektroinstallation Herstellung von sonstigen elektrischen Ausr\u00fcstungen",
    "sg:phone":"+41 71 866 16 77",
    "sg:postcode":"5300",
    "sg:province":"Aargau",
    "wof:name":"Elektroservice Grebenicek Laslo.",
    "wof:placetype":"venue"
},
  "geometry": {"coordinates":[9.5429334641,47.4775428772],"type":"Point"}
}