{
  "type": "Feature",
  "properties": {
    "iso:country":"CH",
    "sg:address":"Am G\u00e4ssli 49",
    "sg:city":"Oberhallau",
    "sg:orig_category":"Handel mit Motorr\u00e4dern, Teilen U Zubeh\u00f6r Instandhaltung U Reparatur von Motorr\u00e4dern Mechanische Werk",
    "sg:phone":"+41 52 681 36 30",
    "sg:postcode":"8216",
    "sg:province":"Schaffhausen",
    "wof:name":"Ernst M\u00fcller",
    "wof:placetype":"venue"
},
  "geometry": {"coordinates":[8.4772720337,47.7052955627],"type":"Point"}
}