{
  "type": "Feature",
  "properties": {
    "addr:full":"K\u00e4sgaden Gais Appenzell Ausserrhoden 9056",
    "addr:postcode":"9056",
    "addr:street":"Kaesgaden;Appenzell Ausserrhoden",
    "iso:country":"CH",
    "sg:address":"K\u00e4sgaden",
    "sg:city":"Gais",
    "sg:orig_category":"Autogaragen Instandhaltung U Reparatur von Automobilen",
    "sg:phone":"+41 71 790 09 79",
    "sg:postcode":"9056",
    "sg:province":"Appenzell Ausserrhoden",
    "wof:name":"Garage Heierli",
    "wof:placetype":"venue"
},
  "geometry": {"coordinates":[9.438607,47.361633],"type":"Point"}
}