{
  "type": "Feature",
  "properties": {
    "iso:country":"CH",
    "sg:address":"Poststrasse 117",
    "sg:city":"Spreitenbach",
    "sg:orig_category":"Non-Classified Establishments",
    "sg:postcode":"8957",
    "sg:province":"Aargau",
    "wof:name":"Unternehmensberatung John-peter Forbes",
    "wof:placetype":"venue"
},
  "geometry": {"coordinates":[8.3595962524,47.425151825],"type":"Point"}
}