{
  "type": "Feature",
  "properties": {
    "iso:country":"CH",
    "sg:address":"Emmentalstrasse 67",
    "sg:city":"Konolfingen",
    "sg:orig_category":"Herstellung von Metallkonstruktionen Mechanik",
    "sg:phone":"+41 31 791 06 52",
    "sg:postcode":"3510",
    "sg:province":"Bern",
    "wof:name":"Sch\u00e4fer H. Ag",
    "wof:placetype":"venue"
},
  "geometry": {"coordinates":[7.6320409775,46.8848876953],"type":"Point"}
}