{
  "type": "Feature",
  "properties": {
    "iso:country":"CH",
    "sg:address":"Route De Denges 36",
    "sg:city":"Lonay",
    "sg:orig_category":"Pensionskassen",
    "sg:phone":"+41 21 811 44 44",
    "sg:postcode":"1027",
    "sg:province":"Vaud",
    "wof:name":"Faigle Ren\u00e9 Sa",
    "wof:placetype":"venue"
},
  "geometry": {"coordinates":[6.5306339264,46.5280342102],"type":"Point"}
}