{
  "type": "Feature",
  "properties": {
    "iso:country":"CH",
    "sg:address":"Burghalden 10",
    "sg:city":"Bichelsee",
    "sg:orig_category":"Interessenvertretungen",
    "sg:postcode":"8363",
    "sg:province":"Thurgau",
    "wof:name":"Metzler-stiftung Franz",
    "wof:placetype":"venue"
},
  "geometry": {"coordinates":[8.9199562073,47.4460525513],"type":"Point"}
}