{
  "type": "Feature",
  "properties": {
    "iso:country":"CH",
    "sg:address":"Unterdorf 66",
    "sg:city":"Gurbr\u00fc",
    "sg:orig_category":"Betrieb U technische Hilfsdienste des Kultur U Unterhaltungswesens",
    "sg:postcode":"3208",
    "sg:province":"Bern",
    "wof:name":"Fun & Action Gmbh",
    "wof:placetype":"venue"
},
  "geometry": {"coordinates":[7.216905,46.963978],"type":"Point"}
}