{
  "type": "Feature",
  "properties": {
    "iso:country":"CH",
    "sg:address":"Via Rovere 11",
    "sg:city":"Breganzona",
    "sg:orig_category":"Grosshandel mit Nahrungsmitteln, Getr\u00e4nken U Tabakwaren ohne ausgepr\u00e4gten Schwerpunkt",
    "sg:postcode":"6932",
    "sg:province":"Ticino",
    "wof:name":"Basso Jurin",
    "wof:placetype":"venue"
},
  "geometry": {"coordinates":[8.9349212646,46.008556366],"type":"Point"}
}