{
  "type": "Feature",
  "properties": {
    "iso:country":"CH",
    "sg:address":"1632",
    "sg:city":"Riaz",
    "sg:classifiers":[
        {
            "category":"Education",
            "subcategory":"Library",
            "type":"Public Place"
        }
    ],
    "sg:phone":"+41 24 473 33 33",
    "sg:postcode":"1632",
    "sg:province":"Fribourg",
    "sg:tags":[
        "u",
        "bibliotheken",
        "archive"
    ],
    "wof:name":"H\u00f4pital De Mal\u00e9voz",
    "wof:placetype":"venue"
},
  "geometry": {"coordinates":[6.944616,46.25568],"type":"Point"}
}