{
  "type": "Feature",
  "properties": {
    "iso:country":"CH",
    "sg:address":"1417",
    "sg:city":"Essertines-yverdon",
    "sg:orig_category":"Herstellung von sonstigen Holzwaren",
    "sg:phone":"+41 24 435 12 44",
    "sg:postcode":"1417",
    "sg:province":"Vaud",
    "wof:name":"Aviolat, Jean",
    "wof:placetype":"venue"
},
  "geometry": {"coordinates":[6.6399297714,46.7164115906],"type":"Point"}
}