{
  "type": "Feature",
  "properties": {
    "iso:country":"CH",
    "sg:address":"Simplon Route Du",
    "sg:city":"Charrat",
    "sg:orig_category":"Detailhandel mit Waren verschiedener Art, Hauptrichtung Nahrungsmittel",
    "sg:phone":"+41 27 746 43 00",
    "sg:postcode":"1906",
    "sg:province":"Valais",
    "wof:name":"Frimar S\u00e0rl",
    "wof:placetype":"venue"
},
  "geometry": {"coordinates":[7.1296892166,46.1249885559],"type":"Point"}
}