{
  "type": "Feature",
  "properties": {
    "iso:country":"CH",
    "sg:address":"F\u00fcrstenlandstrasse 109 9014 St. Gallen. Postfach 9014 St. Gallen",
    "sg:city":"Zust",
    "sg:orig_category":"Markt U Meinungsforschung",
    "sg:postcode":"14",
    "wof:name":"Infohall Gmbh",
    "wof:placetype":"venue"
},
  "geometry": {"coordinates":[9.3427124023,47.4118690491],"type":"Point"}
}