{
  "type": "Feature",
  "properties": {
    "iso:country":"CH",
    "sg:address":"Alpenstrasse 8 3072 Ostermundigen. Postfach",
    "sg:city":"Ostermundigen",
    "sg:orig_category":"Unternehmensberatung Werbeberatung",
    "sg:phone":"+41 79 652 48 42",
    "sg:postcode":"3072",
    "sg:province":"Bern",
    "wof:name":"M\u00fcller Charles Kommunikation Grafische Gewerbe U. Werbung; Akquisition, Verkauf, Beratung Usw.",
    "wof:placetype":"venue"
},
  "geometry": {"coordinates":[7.485396862,46.9563751221],"type":"Point"}
}