{
  "type": "Feature",
  "properties": {
    "addr:full":"Besso Via 7 Lugano Ticino 6900",
    "addr:housenumber":"7",
    "addr:postcode":"6900",
    "addr:street":"Via",
    "iso:country":"CH",
    "sg:address":"Besso Via 7",
    "sg:city":"Lugano",
    "sg:orig_category":"Architektur U Ingenieurb\u00fcros",
    "sg:postcode":"6900",
    "sg:province":"Ticino",
    "wof:name":"Pino Marc Architecte Sia",
    "wof:placetype":"venue"
},
  "geometry": {"coordinates":[6.145507,46.183105],"type":"Point"}
}