{
  "type": "Feature",
  "properties": {
    "addr:full":"S\u00e9cheron Avenue De 1 1202 Gen\u00e8ve Case Postale 270 Gen\u00e8ve Gen\u00e8ve 1202",
    "addr:housenumber":"1;270",
    "addr:postcode":"1202;1202",
    "addr:street":"Se\u0301Cheron Avenue De;Postale",
    "iso:country":"CH",
    "sg:address":"S\u00e9cheron Avenue De 1 1202 Gen\u00e8ve Case Postale 270",
    "sg:city":"Gen\u00e8ve",
    "sg:orig_category":"Berufsorganisationen",
    "sg:phone":"+41 22 731 24 70",
    "sg:postcode":"1202",
    "sg:province":"Gen\u00e8ve",
    "wof:name":"Transax Sa",
    "wof:placetype":"venue"
},
  "geometry": {"coordinates":[6.142701,46.208359],"type":"Point"}
}