{
  "type": "Feature",
  "properties": {
    "iso:country":"CH",
    "sg:address":"Chemin Des C\u00e8dres 13",
    "sg:city":"Lausanne",
    "sg:orig_category":"Unclassifiable Establishments",
    "sg:postcode":"1004",
    "sg:province":"Vaud",
    "wof:name":"Dr M\u00e9d. Catherine Rouiller M\u00e9decin Sp\u00e9cialiste Fmh",
    "wof:placetype":"venue"
},
  "geometry": {"coordinates":[6.6278600693,46.5261802673],"type":"Point"}
}