{
  "type": "Feature",
  "properties": {
    "iso:country":"CH",
    "sg:address":"Hofackerstrasse 12",
    "sg:city":"Adliswil",
    "sg:orig_category":"Handelsvermittlung Unternehmensberatung",
    "sg:phone":"+41 17713366",
    "sg:postcode":"8134",
    "sg:province":"Z\u00fcrich",
    "wof:name":"Faith Gmbh Financial Arrangements",
    "wof:placetype":"venue"
},
  "geometry": {"coordinates":[8.5332355499,47.3157043457],"type":"Point"}
}