{
  "type": "Feature",
  "properties": {
    "addr:full":"Via Peri 16 Lugano Ticino 6900",
    "addr:housenumber":"16",
    "addr:postcode":"6900",
    "addr:street":"Via Peri",
    "iso:country":"CH",
    "sg:address":"Via Peri 16",
    "sg:city":"Lugano",
    "sg:orig_category":"Detailhandel mit Damenbekleidung",
    "sg:phone":"+41 91 923 61 60",
    "sg:postcode":"6900",
    "sg:province":"Ticino",
    "wof:name":"Boutique Intimoda Rosa Di Ortelli",
    "wof:placetype":"venue"
},
  "geometry": {"coordinates":[8.950866,46.006104],"type":"Point"}
}