{
  "type": "Feature",
  "properties": {
    "iso:country":"CH",
    "sg:address":"Melonenstrasse 4",
    "sg:city":"Herisau",
    "sg:orig_category":"Sportvereine Turnen Damen",
    "sg:phone":"+41 71 994 17 22",
    "sg:postcode":"9100",
    "sg:province":"Appenzell Ausserrhoden",
    "wof:name":"Damenturnverein Nesslau-neu St.johann",
    "wof:placetype":"venue"
},
  "geometry": {"coordinates":[9.1946878433,47.2309265137],"type":"Point"}
}