{
  "type": "Feature",
  "properties": {
    "iso:country":"CH",
    "sg:address":"Via Della Posta",
    "sg:city":"Bioggio",
    "sg:orig_category":"Herstellung von Kunststoffwaren Satzherstellung U Reproduktion",
    "sg:phone":"+41 91 611 50 10",
    "sg:postcode":"6934",
    "sg:province":"Ticino",
    "wof:name":"Finser Sa Costruzione Stampi",
    "wof:placetype":"venue"
},
  "geometry": {"coordinates":[8.9105949402,46.0146942139],"type":"Point"}
}