{
  "type": "Feature",
  "properties": {
    "iso:country":"CH",
    "sg:address":"Rohrstrasse 51",
    "sg:city":"Biglen",
    "sg:orig_category":"Detailhandel mit Waren verschiedener Art, Hauptrichtung Nahrungsmittel",
    "sg:phone":"+41 31 701 37 35",
    "sg:postcode":"3507",
    "sg:province":"Bern",
    "wof:name":"Denner-satellit Lebensmittel-discount",
    "wof:placetype":"venue"
},
  "geometry": {"coordinates":[7.6287460327,46.9252090454],"type":"Point"}
}