{
  "type": "Feature",
  "properties": {
    "iso:country":"CH",
    "sg:address":"Adligenswilerstrasse 15 6006 Luzern. Postfach",
    "sg:city":"Luzern",
    "sg:orig_category":"Institutionen des Sozialwesens ohne Beherbergung",
    "sg:postcode":"6003",
    "sg:province":"Luzern",
    "wof:name":"Pro Operariis. Unterst\u00fct. Mittelloser Priester- U. Laienkandidaten, Zinslose Darlehen An Bed\u00fcrftige Arb.",
    "wof:placetype":"venue"
},
  "geometry": {"coordinates":[8.3156757355,47.0559921265],"type":"Point"}
}