{
  "type": "Feature",
  "properties": {
    "iso:country":"CH",
    "sg:address":"Ruessenstrasse 6",
    "sg:city":"Baar",
    "sg:orig_category":"Unclassifiable Establishments",
    "sg:phone":"+41 41 761 02 31",
    "sg:postcode":"6340",
    "sg:province":"Zug",
    "wof:name":"Ax4 Holding Ag",
    "wof:placetype":"venue"
},
  "geometry": {"coordinates":[8.5604944229,47.2117652893],"type":"Point"}
}