{
  "type": "Feature",
  "properties": {
    "iso:country":"CH",
    "sg:address":"Hofwies 11",
    "sg:city":"Bonstetten",
    "sg:orig_category":"Betrieb von Taxis",
    "sg:phone":"+41 17002020",
    "sg:postcode":"8906",
    "sg:province":"Z\u00fcrich",
    "wof:name":"Gaetano Lucenti Taxi",
    "wof:placetype":"venue"
},
  "geometry": {"coordinates":[8.468428,47.315002],"type":"Point"}
}