{
  "type": "Feature",
  "properties": {
    "iso:country":"CH",
    "sg:address":"Effingerstrasse 85",
    "sg:city":"Bern",
    "sg:orig_category":"Maler U Glasergewerbe Stukkateurgewerbe, Gipserei U Verputzerei",
    "sg:phone":"+41 31 381 33 75",
    "sg:postcode":"3008",
    "sg:province":"Bern",
    "wof:name":"R. Brenner",
    "wof:placetype":"venue"
},
  "geometry": {"coordinates":[7.4217600822,46.9446487427],"type":"Point"}
}