{
  "type": "Feature",
  "properties": {
    "iso:country":"CH",
    "sg:address":"Chemin De Vaux 3",
    "sg:city":"Penthaz",
    "sg:orig_category":"Sonstige k\u00fcnstlerische U schriftstellerische T\u00e4tigkeiten U Darbietungen",
    "sg:phone":"+41 21 862 71 60",
    "sg:postcode":"1303",
    "sg:province":"Vaud",
    "wof:name":"Marie-christine Rodriquez Peinture Sur Tissus",
    "wof:placetype":"venue"
},
  "geometry": {"coordinates":[6.5358982086,46.6021995544],"type":"Point"}
}