{
  "type": "Feature",
  "properties": {
    "iso:country":"CH",
    "sg:address":"Siggernweg 5",
    "sg:city":"Hubersdorf",
    "sg:orig_category":"Maschinen-Fabrikation",
    "sg:phone":"+41 32 637 16 43",
    "sg:postcode":"4535",
    "sg:province":"Solothurn",
    "wof:name":"Combi-service Schwander Walter",
    "wof:placetype":"venue"
},
  "geometry": {"coordinates":[7.5877389908,47.2473945618],"type":"Point"}
}