{
  "type": "Feature",
  "properties": {
    "iso:country":"CH",
    "sg:address":"Grand-rue 27",
    "sg:city":"Attalens",
    "sg:classifiers":[
        {
            "category":"Travel",
            "subcategory":"Hotels & Motels",
            "type":"Entertainment"
        }
    ],
    "sg:phone":"+41 21 947 41 08",
    "sg:postcode":"1616",
    "sg:province":"Fribourg",
    "sg:tags":[
        "hotels",
        "mit",
        "restaurant"
    ],
    "wof:name":"H\u00f4tel De L'ange",
    "wof:placetype":"venue"
},
  "geometry": {"coordinates":[6.8487501144,46.5093803406],"type":"Point"}
}