{
  "type": "Feature",
  "properties": {
    "iso:country":"CH",
    "sg:address":"Via Como 1",
    "sg:city":"Chiasso",
    "sg:orig_category":"Herstellung der Ausstattung von Uhren",
    "sg:phone":"+41 22 823 28 10",
    "sg:postcode":"6830",
    "sg:province":"Ticino",
    "wof:name":"Serge Belli Atelier De Sertissage",
    "wof:placetype":"venue"
},
  "geometry": {"coordinates":[6.1429309845,46.1799545288],"type":"Point"}
}