{
  "type": "Feature",
  "properties": {
    "addr:full":"Freiburgstrasse 17 Flamatt Fribourg 3175",
    "addr:housenumber":"17",
    "addr:postcode":"3175",
    "addr:street":"Freiburgstrasse",
    "iso:country":"CH",
    "sg:address":"Freiburgstrasse 17",
    "sg:city":"Flamatt",
    "sg:orig_category":"Autogaragen Handel mit Motorr\u00e4dern, Teilen U Zubeh\u00f6r Instandhaltung U Reparatur von Motorr\u00e4dern",
    "sg:phone":"+41 32 968 57 28",
    "sg:postcode":"3175",
    "sg:province":"Fribourg",
    "wof:name":"Cosimo Guglielmo",
    "wof:placetype":"venue"
},
  "geometry": {"coordinates":[6.831287,47.108631],"type":"Point"}
}