{
  "type": "Feature",
  "properties": {
    "iso:country":"CH",
    "sg:address":"Stiegelschwandstrasse 55",
    "sg:city":"Adelboden",
    "sg:orig_category":"Sportvereine Turnen Vereine Damen",
    "sg:phone":"+41 33 673 37 67",
    "sg:postcode":"3715",
    "sg:province":"Bern",
    "wof:name":"Damenturnverein Stv Adelboden",
    "wof:placetype":"venue"
},
  "geometry": {"coordinates":[7.5273399353,46.4889564514],"type":"Point"}
}