{
  "type": "Feature",
  "properties": {
    "iso:country":"CH",
    "sg:address":"Alpenstrasse 2",
    "sg:city":"Zug",
    "sg:orig_category":"Unclassifiable Establishments",
    "sg:postcode":"6300",
    "sg:province":"Zug",
    "wof:name":"Jega Ag",
    "wof:placetype":"venue"
},
  "geometry": {"coordinates":[9.1522407532,47.5501747131],"type":"Point"}
}