{
  "type": "Feature",
  "properties": {
    "addr:full":"Hauptstrasse 47 8840 Einsiedeln. Postfach 456 Einsiedeln Schwyz 8840",
    "addr:housenumber":"47;456",
    "addr:postcode":"8840;8840",
    "addr:street":"Hauptstrasse;Postfach;Schwyz",
    "iso:country":"CH",
    "sg:address":"Hauptstrasse 47 8840 Einsiedeln. Postfach 456",
    "sg:city":"Einsiedeln",
    "sg:orig_category":"Detailhandel mit B\u00fcchern, Zeitungen, Schreib U Papeteriewaren",
    "sg:phone":"+41 55 412 24 87",
    "sg:postcode":"8840",
    "sg:province":"Schwyz",
    "wof:name":"Schnyder Einsiedeln Inhaberin Frau Margaretha Roesle-schnyder",
    "wof:placetype":"venue"
},
  "geometry": {"coordinates":[8.747183,47.127171],"type":"Point"}
}