{
  "type": "Feature",
  "properties": {
    "addr:full":"Route De Croix 106 1899 Torgon. Postfach Torgon Valais 1899",
    "addr:housenumber":"106",
    "addr:postcode":"1899;1899",
    "addr:street":"Route De Croix;Postfach",
    "iso:country":"CH",
    "sg:address":"Route De Croix 106 1899 Torgon. Postfach",
    "sg:city":"Torgon",
    "sg:orig_category":"Allgemeiner Hoch U Tiefbau",
    "sg:phone":"+41 24 481 31 07",
    "sg:postcode":"1899",
    "sg:province":"Valais",
    "wof:name":"Gex-collet & Vannay Sa",
    "wof:placetype":"venue"
},
  "geometry": {"coordinates":[6.873557,46.318348],"type":"Point"}
}