{
  "type": "Feature",
  "properties": {
    "iso:country":"CH",
    "sg:address":"Sunnetalstr. 31",
    "sg:city":"F\u00e4llanden",
    "sg:orig_category":"Unternehmensberatung",
    "sg:phone":"+41 18251274",
    "sg:postcode":"8117",
    "sg:province":"Z\u00fcrich",
    "wof:name":"Bmc Bornatico Consulting & Co",
    "wof:placetype":"venue"
},
  "geometry": {"coordinates":[8.6439113617,47.3721427917],"type":"Point"}
}