{
  "type": "Feature",
  "properties": {
    "iso:country":"CH",
    "sg:address":"Birmensdorferstrasse 15",
    "sg:city":"Dietikon",
    "sg:orig_category":"G\u00fcterbef\u00f6rderung im Strassenverkehr",
    "sg:phone":"+41 17411195",
    "sg:postcode":"8953",
    "sg:province":"Z\u00fcrich",
    "wof:name":"Alfred N\u00f6tzli Transporte",
    "wof:placetype":"venue"
},
  "geometry": {"coordinates":[8.4179420471,47.3967094421],"type":"Point"}
}