{
  "type": "Feature",
  "properties": {
    "iso:country":"CH",
    "sg:address":"Rorschacherstrasse 66 9450 L\u00fcchingen. Postfach",
    "sg:city":"L\u00fcchingen",
    "sg:orig_category":"Sanit\u00e4r, Heizungs U L\u00fcftungsinstallation",
    "sg:postcode":"9450",
    "sg:province":"St. Gallen",
    "wof:name":"W\u00fcst K. Sanit\u00e4r & Heizungen Gmbh Heizungen & Sanit\u00e4re Anlagen; Projektierungen U. Montage Usw",
    "wof:placetype":"venue"
},
  "geometry": {"coordinates":[9.5502462387,47.3844490051],"type":"Point"}
}