{
  "type": "Feature",
  "properties": {
    "iso:country":"CH",
    "sg:address":"Nelkenweg 12",
    "sg:city":"Kreuzlingen",
    "sg:orig_category":"Vereine Musik/Blasmusik",
    "sg:phone":"+41 71 672 49 80",
    "sg:postcode":"8280",
    "sg:province":"Thurgau",
    "wof:name":"Musik-& Literatur-gesellschaft",
    "wof:placetype":"venue"
},
  "geometry": {"coordinates":[9.1628217697,47.6447753906],"type":"Point"}
}