{
  "type": "Feature",
  "properties": {
    "iso:country":"CH",
    "sg:address":"Schlossstrasse 20 8207 Schaffhausen. Postfach",
    "sg:city":"Schaffhausen",
    "sg:classifiers":[
        {
            "category":"Travel",
            "subcategory":"Hotels & Motels",
            "type":"Entertainment"
        }
    ],
    "sg:phone":"+41 52 643 23 23",
    "sg:postcode":"8207",
    "sg:province":"Schaffhausen",
    "sg:tags":[
        "hotels",
        "mit",
        "restaurant"
    ],
    "wof:name":"Hotel Hirschen",
    "wof:placetype":"venue"
},
  "geometry": {"coordinates":[8.6630983353,47.723941803],"type":"Point"}
}