{
  "type": "Feature",
  "properties": {
    "iso:country":"CH",
    "sg:address":"Pr\u00e9 Rond 22",
    "sg:city":"Malleray",
    "sg:orig_category":"Erdbewegungsarbeiten G\u00fcterbef\u00f6rderung im Strassenverkehr",
    "sg:phone":"+41 91 646 42 56",
    "sg:postcode":"2735",
    "sg:province":"Bern",
    "wof:name":"Pietro Puricelli & Figli Sagl Trasporti & Scavi",
    "wof:placetype":"venue"
},
  "geometry": {"coordinates":[8.9712047577,45.8932266235],"type":"Point"}
}