{
  "type": "Feature",
  "properties": {
    "iso:country":"CH",
    "sg:address":"Neuengasse 39 3011 Bern. Postfach",
    "sg:city":"Bern",
    "sg:orig_category":"Kauf U Verkauf von Immobilien auf eigene Rechnung",
    "sg:postcode":"3005",
    "sg:province":"Bern",
    "wof:name":"W. Hollenweger",
    "wof:placetype":"venue"
},
  "geometry": {"coordinates":[8.2688484192,47.3510437012],"type":"Point"}
}