{
  "type": "Feature",
  "properties": {
    "iso:country":"CH",
    "sg:address":"Teienstrasse 41",
    "sg:city":"Meilen",
    "sg:orig_category":"Technische B\u00fcros Elektro",
    "sg:phone":"+41 19235817",
    "sg:postcode":"8706",
    "sg:province":"Z\u00fcrich",
    "wof:name":"Baier Elektroplanungen",
    "wof:placetype":"venue"
},
  "geometry": {"coordinates":[8.6161031723,47.2810287476],"type":"Point"}
}