{
  "type": "Feature",
  "properties": {
    "iso:country":"CH",
    "sg:address":"Steinen",
    "sg:city":"Signau",
    "sg:orig_category":"Herstellung von Schreinerwaren ohne ausgepr\u00e4gten Schwerpunkt Herstellung von sonstigen Fahrzeugen",
    "sg:phone":"+41 34 497 11 76",
    "sg:postcode":"3534",
    "sg:province":"Bern",
    "wof:name":"Fritz Kurth Schreinerei & Wagnerei",
    "wof:placetype":"venue"
},
  "geometry": {"coordinates":[7.7166800499,46.9052886963],"type":"Point"}
}