{
  "type": "Feature",
  "properties": {
    "iso:country":"CH",
    "sg:address":"Augustin Kellerstrasse 21",
    "sg:city":"Lenzburg",
    "sg:orig_category":"W\u00e4scherei U chemische Reinigung",
    "sg:phone":"+41 62 891 15 79",
    "sg:postcode":"5600",
    "sg:province":"Aargau",
    "wof:name":"Frei Urs, Textilpflege-center",
    "wof:placetype":"venue"
},
  "geometry": {"coordinates":[8.1704292297,47.3892288208],"type":"Point"}
}