{
  "type": "Feature",
  "properties": {
    "addr:full":"Haselrain 31 D\u00fcdingen Fribourg 3186",
    "addr:housenumber":"31",
    "addr:postcode":"3186",
    "addr:street":"Haselrain;Fribourg",
    "iso:country":"CH",
    "sg:address":"Haselrain 31",
    "sg:city":"D\u00fcdingen",
    "sg:orig_category":"Allgemeiner Hoch U Tiefbau",
    "sg:postcode":"3186",
    "sg:province":"Fribourg",
    "wof:name":"Rs Generalunternehmung Obersaxen Ag",
    "wof:placetype":"venue"
},
  "geometry": {"coordinates":[9.12251,46.756142],"type":"Point"}
}