{
  "type": "Feature",
  "properties": {
    "iso:country":"CH",
    "sg:address":"Schulstrasse 10",
    "sg:city":"Magden",
    "sg:orig_category":"Elektroinstallation Herstellung von Elektromotoren, Generatoren U Transformatoren",
    "sg:phone":"+41 61 841 17 00",
    "sg:postcode":"4312",
    "sg:province":"Aargau",
    "wof:name":"W. Holer",
    "wof:placetype":"venue"
},
  "geometry": {"coordinates":[7.8132138252,47.5280914307],"type":"Point"}
}