{
  "type": "Feature",
  "properties": {
    "iso:country":"CH",
    "sg:address":"Chemin Du Pro-de-narre",
    "sg:city":"Saxon",
    "sg:orig_category":"Physiotherapie",
    "sg:phone":"+41 27 744 27 85",
    "sg:postcode":"1907",
    "sg:province":"Valais",
    "wof:name":"Trudi Dupont Physioth\u00e9rapie",
    "wof:placetype":"venue"
},
  "geometry": {"coordinates":[7.1806168556,46.1470832825],"type":"Point"}
}