{
  "type": "Feature",
  "properties": {
    "iso:country":"CH",
    "sg:address":"En Bulandoz",
    "sg:city":"Arnex-sur-orbe",
    "sg:orig_category":"Abbruch U Sprenggewerbe, Erdbewegungsarbeiten Gartenbau",
    "sg:phone":"+41 79 353 60 70",
    "sg:postcode":"1321",
    "sg:province":"Vaud",
    "wof:name":"Guy-daniel Monnier Entreprise De Terrassements",
    "wof:placetype":"venue"
},
  "geometry": {"coordinates":[6.514968,46.69099],"type":"Point"}
}