{
  "type": "Feature",
  "properties": {
    "iso:country":"CH",
    "sg:address":"Obere Geerenstrasse 48",
    "sg:city":"Gockhausen",
    "sg:orig_category":"Herstellung von Kunststoffwaren",
    "sg:phone":"+41 18214093",
    "sg:postcode":"8044",
    "sg:province":"Z\u00fcrich",
    "wof:name":"Hofm\u00e4nner Ag",
    "wof:placetype":"venue"
},
  "geometry": {"coordinates":[8.6045637131,47.3778953552],"type":"Point"}
}