{
  "type": "Feature",
  "properties": {
    "iso:country":"CH",
    "sg:address":"Sch\u00fcrmatte 10",
    "sg:city":"Nebikon",
    "sg:orig_category":"Grosshandel mit sonstigen Getr\u00e4nken",
    "sg:phone":"+41 62 748 50 50",
    "sg:postcode":"6244",
    "sg:province":"Luzern",
    "wof:name":"Brauerei Eichhof Bier-& Mineralwasserdepot",
    "wof:placetype":"venue"
},
  "geometry": {"coordinates":[7.9745678902,47.1962471008],"type":"Point"}
}