{
  "type": "Feature",
  "properties": {
    "iso:country":"CH",
    "sg:address":"Niederlenzer Kirchweg",
    "sg:city":"Lenzburg",
    "sg:orig_category":"Ingenieurb\u00fcros divers Planer f\u00fcr Energiekonzepte",
    "sg:phone":"+41 62 892 44 00",
    "sg:postcode":"5600",
    "sg:province":"Aargau",
    "wof:name":"Rmb Ag Lenzburg Ingenieurb\u00fcro",
    "wof:placetype":"venue"
},
  "geometry": {"coordinates":[8.1734609604,47.3915863037],"type":"Point"}
}