{
  "type": "Feature",
  "properties": {
    "iso:country":"CH",
    "sg:address":"Via Carlo Maderno 24 6900 Lugano. Postfach",
    "sg:city":"Lugano",
    "sg:orig_category":"Herstellung von sonstigen Nahrungsmitteln",
    "sg:postcode":"6900",
    "sg:province":"Ticino",
    "wof:name":"M. & B. Gastronomia Sagl",
    "wof:placetype":"venue"
},
  "geometry": {"coordinates":[8.9557409286,46.0110435486],"type":"Point"}
}