{
  "type": "Feature",
  "properties": {
    "iso:country":"CH",
    "sg:address":"Dornacherstrasse 210",
    "sg:city":"Basel",
    "sg:orig_category":"Grosshandel mit Erzen U Metallen",
    "sg:phone":"+41 61 332 32 33",
    "sg:postcode":"4053",
    "sg:province":"Basel-Stadt",
    "wof:name":"Balco Ag",
    "wof:placetype":"venue"
},
  "geometry": {"coordinates":[7.5945248604,47.5413208008],"type":"Point"}
}