{
  "type": "Feature",
  "properties": {
    "iso:country":"CH",
    "sg:address":"Industriestrasse",
    "sg:city":"Hendschiken",
    "sg:orig_category":"Detailhandel mit Gebrauchtwaren in Verkaufsr\u00e4umen",
    "sg:postcode":"5604",
    "sg:province":"Aargau",
    "wof:name":"Borckenstube Regenbogen Holenstein & Genovese",
    "wof:placetype":"venue"
},
  "geometry": {"coordinates":[8.2038345337,47.3895645142],"type":"Point"}
}