{
  "type": "Feature",
  "properties": {
    "iso:country":"CH",
    "sg:address":"Fellenbergstrasse 9 3053 M\u00fcnchenbuchsee. Postfach",
    "sg:city":"M\u00fcnchenbuchsee",
    "sg:orig_category":"F\u00fcrsorge\u00e4mter",
    "sg:phone":"+41 31 869 24 11",
    "sg:postcode":"3053",
    "sg:province":"Bern",
    "wof:name":"Sozialdienst M\u00fcnchenbuchsee",
    "wof:placetype":"venue"
},
  "geometry": {"coordinates":[7.4503760338,47.0200881958],"type":"Point"}
}