{
  "type": "Feature",
  "properties": {
    "iso:country":"CH",
    "sg:address":"Friedhofstr. 31",
    "sg:city":"B\u00fclach",
    "sg:orig_category":"Betrieb von Taxis",
    "sg:phone":"+41 18611640",
    "sg:postcode":"8180",
    "sg:province":"Z\u00fcrich",
    "wof:name":"Business Taxi & Limousine, Ambrosio Giuseppe",
    "wof:placetype":"venue"
},
  "geometry": {"coordinates":[8.546639,47.517319],"type":"Point"}
}