{
  "type": "Feature",
  "properties": {
    "iso:country":"CH",
    "sg:address":"Im Bitzi 15c",
    "sg:city":"Z\u00fcberwangen",
    "sg:orig_category":"Elektro- and elektronische Maschinen Grosshandel Elektroinstallation",
    "sg:phone":"+41 71 944 41 30",
    "sg:postcode":"9523",
    "sg:province":"St. Gallen",
    "wof:name":"Tyco Electronics (schweiz) Ag",
    "wof:placetype":"venue"
},
  "geometry": {"coordinates":[9.0941200256,47.4650306702],"type":"Point"}
}