{
  "type": "Feature",
  "properties": {
    "iso:country":"CH",
    "sg:address":"Obstadtstrasse",
    "sg:city":"Walenstadt",
    "sg:orig_category":"Vorschulen, Kinderg\u00e4rten",
    "sg:phone":"+41 81 735 24 04",
    "sg:postcode":"8880",
    "sg:province":"St. Gallen",
    "wof:name":"Kindergarten",
    "wof:placetype":"venue"
},
  "geometry": {"coordinates":[9.3144254684,47.125579834],"type":"Point"}
}