{
  "type": "Feature",
  "properties": {
    "iso:country":"CH",
    "sg:address":"Aeschen 605",
    "sg:city":"Amden",
    "sg:classifiers":[
        {
            "category":"Social Services",
            "subcategory":"Retirement Home",
            "type":"Services"
        }
    ],
    "sg:phone":"+41 55 611 11 76",
    "sg:postcode":"8873",
    "sg:province":"St. Gallen",
    "sg:tags":[
        "pflegeheime",
        "u",
        "alters"
    ],
    "wof:name":"Altersheim Aeschen",
    "wof:placetype":"venue"
},
  "geometry": {"coordinates":[9.13258,47.148232],"type":"Point"}
}