{
  "type": "Feature",
  "properties": {
    "iso:country":"CH",
    "sg:address":"Herrengasse 20",
    "sg:city":"Schwyz",
    "sg:orig_category":"Fussboden, Fliesen U Plattenlegerei, Tapeziererei Verlegen von Fussboden",
    "sg:phone":"+41 41 811 14 46",
    "sg:postcode":"6430",
    "sg:province":"Schwyz",
    "wof:name":"Franz Nider\u00f6st Bodenbel\u00e4ge Parkett",
    "wof:placetype":"venue"
},
  "geometry": {"coordinates":[8.6514949799,47.0221214294],"type":"Point"}
}