{
  "type": "Feature",
  "properties": {
    "iso:country":"CH",
    "sg:address":"Route De Veyrier 180e",
    "sg:city":"Vessy",
    "sg:orig_category":"Handelsvermittlung U Grosshandel",
    "sg:phone":"+41 22 784 48 54",
    "sg:postcode":"1234",
    "sg:province":"Gen\u00e8ve",
    "wof:name":"Agfimar Sa",
    "wof:placetype":"venue"
},
  "geometry": {"coordinates":[6.1668710709,46.1748428345],"type":"Point"}
}