{
  "type": "Feature",
  "properties": {
    "iso:country":"CH",
    "sg:address":"Grundlistrasse 8",
    "sg:city":"Engelberg",
    "sg:orig_category":"Unternehmensberatung",
    "sg:phone":"+41 41 630 43 20",
    "sg:postcode":"6390",
    "sg:province":"Obwalden",
    "wof:name":"Dsi Dr. Stange International Gmbh",
    "wof:placetype":"venue"
},
  "geometry": {"coordinates":[8.4236602783,46.8227310181],"type":"Point"}
}