{
  "type": "Feature",
  "properties": {
    "iso:country":"CH",
    "sg:address":"Sommergasse 23",
    "sg:city":"Basel",
    "sg:orig_category":"Arztpraxen",
    "sg:phone":"+41 61 322 24 00",
    "sg:postcode":"4056",
    "sg:province":"Basel-Stadt",
    "wof:name":"Dr.med. Judith Balasfalvy Spezial\u00e4rztin Fmh",
    "wof:placetype":"venue"
},
  "geometry": {"coordinates":[7.574652,47.56345],"type":"Point"}
}