{
  "type": "Feature",
  "properties": {
    "iso:country":"CH",
    "sg:address":"Pestalozzistrasse 5",
    "sg:city":"Arbon",
    "sg:orig_category":"Detektivb\u00fcros U \u00dcberwachung",
    "sg:postcode":"9320",
    "sg:province":"Thurgau",
    "wof:name":"Wachdienst Weber",
    "wof:placetype":"venue"
},
  "geometry": {"coordinates":[9.4272356033,47.5114784241],"type":"Point"}
}