{
  "type": "Feature",
  "properties": {
    "iso:country":"CH",
    "sg:address":"Lorrainestrasse 22",
    "sg:city":"Bern",
    "sg:classifiers":[
        {
            "category":"Restaurant",
            "type":"Food & Drink"
        }
    ],
    "sg:phone":"+41 31 332 24 97",
    "sg:postcode":"3013",
    "sg:province":"Bern",
    "wof:name":"Restaurant Feldschl\u00f6sschen",
    "wof:placetype":"venue"
},
  "geometry": {"coordinates":[7.4450001717,46.9564933777],"type":"Point"}
}