{
  "type": "Feature",
  "properties": {
    "iso:country":"CH",
    "sg:address":"Hauptstrasse",
    "sg:city":"Bowil",
    "sg:classifiers":[
        {
            "category":"Government",
            "subcategory":"Post Office",
            "type":"Public Place"
        }
    ],
    "sg:phone":"+41 31 711 17 59",
    "sg:postcode":"3533",
    "sg:province":"Bern",
    "sg:tags":[
        "caf\u00e9s",
        "tea-rooms"
    ],
    "wof:name":"Caf\u00e9 D\u00f6rfli",
    "wof:placetype":"venue"
},
  "geometry": {"coordinates":[7.6947770119,46.9005241394],"type":"Point"}
}