{
  "type": "Feature",
  "properties": {
    "iso:country":"CH",
    "sg:address":"Surbekstrasse 1",
    "sg:city":"Bern",
    "sg:orig_category":"Erbringung von Dienstleistungen f\u00fcr Unternehmen",
    "sg:phone":"+41 31 941 25 70",
    "sg:postcode":"3006",
    "sg:province":"Bern",
    "wof:name":"Deko Art Gmbh",
    "wof:placetype":"venue"
},
  "geometry": {"coordinates":[7.4763951302,46.9422683716],"type":"Point"}
}