{
  "type": "Feature",
  "properties": {
    "iso:country":"CH",
    "sg:address":"Poststrasse 94",
    "sg:city":"Spreitenbach",
    "sg:orig_category":"Politische Parteien CVP",
    "sg:phone":"+41 56 402 08 61",
    "sg:postcode":"8957",
    "sg:province":"Aargau",
    "wof:name":"Cvp Ortspartei Spreitenbach",
    "wof:placetype":"venue"
},
  "geometry": {"coordinates":[8.3609886169,47.4240875244],"type":"Point"}
}