{
  "type": "Feature",
  "properties": {
    "iso:country":"CH",
    "sg:address":"3792",
    "sg:city":"Saanen",
    "sg:orig_category":"Detailhandel mit Textilien",
    "sg:phone":"+41 52 337 33 66",
    "sg:postcode":"3792",
    "sg:province":"Bern",
    "wof:name":"Manuela Handarbeiten",
    "wof:placetype":"venue"
},
  "geometry": {"coordinates":[8.7960348129,47.5514411926],"type":"Point"}
}