{
  "type": "Feature",
  "properties": {
    "addr:full":"Bettenhausenstrasse 50 3360 Herzogenbuchsee. Postfach 128 Herzogenbuchsee Bern 3360",
    "addr:housenumber":"50;128",
    "addr:postcode":"3360 herzogenbuchsee.;3360",
    "addr:street":"Bettenhausenstrasse;Postfach;Bern",
    "iso:country":"CH",
    "sg:address":"Bettenhausenstrasse 50 3360 Herzogenbuchsee. Postfach 128",
    "sg:city":"Herzogenbuchsee",
    "sg:orig_category":"Aktivit\u00e4ten der Generalunternehmen im Baugewerbe Allgemeiner Hoch U Tiefbau",
    "sg:phone":"+41 71 913 96 40",
    "sg:postcode":"3360",
    "sg:province":"Bern",
    "wof:name":"Hh Management Ag",
    "wof:placetype":"venue"
},
  "geometry": {"coordinates":[7.706269,47.183445],"type":"Point"}
}