{
  "type": "Feature",
  "properties": {
    "iso:country":"CH",
    "sg:address":"Affolternstrasse 168",
    "sg:city":"Z\u00fcrich",
    "sg:orig_category":"Wirtschaftsverb\u00e4nde Gewerbeverb\u00e4nde/-vereine",
    "sg:phone":"+41 13119384",
    "sg:postcode":"8050",
    "sg:province":"Z\u00fcrich",
    "wof:name":"Gewerbeverein Zh-affoltern Herrn Urs Schudel",
    "wof:placetype":"venue"
},
  "geometry": {"coordinates":[8.5313978195,47.4114646912],"type":"Point"}
}