{
  "type": "Feature",
  "properties": {
    "iso:country":"CH",
    "sg:address":"R\u00fcchligweg 101",
    "sg:city":"Riehen",
    "sg:orig_category":"Forschung U Entwicklung im Bereich der Naturwissenschaften",
    "sg:phone":"+41 61 603 27 35",
    "sg:postcode":"4125",
    "sg:province":"Basel-Stadt",
    "wof:name":"Biovista Gmbh",
    "wof:placetype":"venue"
},
  "geometry": {"coordinates":[7.6356358528,47.5705223083],"type":"Point"}
}