{
  "type": "Feature",
  "properties": {
    "iso:country":"CH",
    "sg:address":"Avenue De Montchoisi 9",
    "sg:city":"Lausanne",
    "sg:orig_category":"RESTAURANTS: TEA-ROOMS",
    "sg:phone":"+41 21 616 16 26",
    "sg:postcode":"1006",
    "sg:province":"Vaud",
    "wof:name":"Chinadomicile S\u00e0rl",
    "wof:placetype":"venue"
},
  "geometry": {"coordinates":[6.6335268021,46.5129928589],"type":"Point"}
}