{
  "type": "Feature",
  "properties": {
    "iso:country":"CH",
    "sg:address":"Talackerstrasse 47",
    "sg:city":"Thun",
    "sg:orig_category":"Grosshandel mit Geschenkartikeln U Souvenirs Sonstiger Grosshandel",
    "sg:phone":"+41 62 209 57 70",
    "sg:postcode":"3604",
    "sg:province":"Bern",
    "wof:name":"Hagro H. Untersee & Chr. Gerber",
    "wof:placetype":"venue"
},
  "geometry": {"coordinates":[7.8549938202,47.3366966248],"type":"Point"}
}