{
  "type": "Feature",
  "properties": {
    "iso:country":"CH",
    "sg:address":"Artmattstrasse 26",
    "sg:city":"Gerlafingen",
    "sg:orig_category":"Herstellung von sonstigen organischen Grundstoffen U Chemikalien",
    "sg:phone":"+41 32 652 06 76",
    "sg:postcode":"4563",
    "sg:province":"Solothurn",
    "wof:name":"Nicotech Gmbh",
    "wof:placetype":"venue"
},
  "geometry": {"coordinates":[7.570371151,47.1731262207],"type":"Point"}
}