{
  "type": "Feature",
  "properties": {
    "iso:country":"CH",
    "sg:address":"Eichenrain 35",
    "sg:city":"Kehrsatz",
    "sg:orig_category":"Unternehmensberatung Verm\u00f6gensverwaltung",
    "sg:phone":"+41 31 961 09 61",
    "sg:postcode":"3122",
    "sg:province":"Bern",
    "wof:name":"Heinz H. Landolf Unternehmensberatung",
    "wof:placetype":"venue"
},
  "geometry": {"coordinates":[7.4745168686,46.9172401428],"type":"Point"}
}