{
  "type": "Feature",
  "properties": {
    "iso:country":"CH",
    "sg:address":"Gygerweg 18",
    "sg:city":"Spiez",
    "sg:classifiers":[
        {
            "category":"Restaurant",
            "type":"Food & Drink"
        }
    ],
    "sg:phone":"+41 33 650 12 60",
    "sg:postcode":"3700",
    "sg:province":"Bern",
    "wof:name":"Caf\u00e9 Wiler",
    "wof:placetype":"venue"
},
  "geometry": {"coordinates":[7.6654000282,46.6838722229],"type":"Point"}
}