{
  "type": "Feature",
  "properties": {
    "iso:country":"CH",
    "sg:address":"Bahnhofstrasse 62",
    "sg:city":"Z\u00fcrich",
    "sg:orig_category":"Mit dem Versicherungsgewerbe verbundene T\u00e4tigkeiten",
    "sg:phone":"+41 21 613 55 55",
    "sg:postcode":"8001",
    "sg:province":"Z\u00fcrich",
    "wof:name":"Courtagest Sa",
    "wof:placetype":"venue"
},
  "geometry": {"coordinates":[6.6385297775,46.5106391907],"type":"Point"}
}