{
  "type": "Feature",
  "properties": {
    "iso:country":"CH",
    "sg:address":"Feld 72",
    "sg:city":"Pragg-jenaz",
    "sg:orig_category":"Elektroinstallation Herstellung von Elektrizit\u00e4tsverteilungs U schalteinrichtungen",
    "sg:phone":"+41 81 332 22 45",
    "sg:postcode":"7231",
    "sg:province":"Graubunden",
    "wof:name":"Walser Ag Elektrotechnische Unternehmung",
    "wof:placetype":"venue"
},
  "geometry": {"coordinates":[9.7087306976,46.940032959],"type":"Point"}
}