{
  "type": "Feature",
  "properties": {
    "iso:country":"CH",
    "sg:address":"Hauptstrasse 27 8259 Kaltenbach. Postfach",
    "sg:city":"Kaltenbach",
    "sg:orig_category":"Herstellung von k\u00e4lte U lufttechnischen Erzeugnissen f\u00fcr gewerbliche Zwecke",
    "sg:phone":"+41 52 741 31 16",
    "sg:postcode":"8259",
    "sg:province":"Thurgau",
    "wof:name":"Forster W\u00e4rme Und K\u00e4lteisolation",
    "wof:placetype":"venue"
},
  "geometry": {"coordinates":[8.843914032,47.6527442932],"type":"Point"}
}