{
  "type": "Feature",
  "properties": {
    "iso:country":"CH",
    "sg:address":"Giacometti Via 1",
    "sg:city":"Lugano",
    "sg:orig_category":"Allgemeiner Hoch U Tiefbau",
    "sg:phone":"+41 91 973 57 10",
    "sg:postcode":"6900",
    "sg:province":"Ticino",
    "wof:name":"Immorenova Lugano Sa",
    "wof:placetype":"venue"
},
  "geometry": {"coordinates":[8.955469,46.007412],"type":"Point"}
}