{
  "type": "Feature",
  "properties": {
    "iso:country":"CH",
    "sg:address":"Affolternstrasse 3",
    "sg:city":"Ottenbach",
    "sg:orig_category":"Landesverteidigung, Sozialversicherung \u00d6ffentliche Verwaltung",
    "sg:phone":"+41 17612141",
    "sg:postcode":"8913",
    "sg:province":"Z\u00fcrich",
    "wof:name":"Zivilschutzstelle Ottenbach",
    "wof:placetype":"venue"
},
  "geometry": {"coordinates":[8.4043035507,47.2808952332],"type":"Point"}
}