{
  "type": "Feature",
  "properties": {
    "iso:country":"CH",
    "sg:address":"Sulzerstrasse 7 4054 Basel. Postfach",
    "sg:city":"Basel",
    "sg:orig_category":"Grosshandel mit B\u00fcromaschinen Grosshandel mit Datenverarbeitungsger\u00e4ten",
    "sg:phone":"+41 61 301 33 36",
    "sg:postcode":"4009",
    "sg:province":"Basel-Stadt",
    "wof:name":"Transoft Gmbh Edv; Dienstleistungen Usw",
    "wof:placetype":"venue"
},
  "geometry": {"coordinates":[7.572455883,47.5545272827],"type":"Point"}
}