{
  "type": "Feature",
  "properties": {
    "iso:country":"CH",
    "sg:address":"Erlenstrasse 9",
    "sg:city":"Winterthur",
    "sg:orig_category":"Organisationen des Gesundheitswesen",
    "sg:phone":"+41 62 291 19 33",
    "sg:postcode":"8408",
    "sg:province":"Z\u00fcrich",
    "wof:name":"Samariterverein D\u00e4niken",
    "wof:placetype":"venue"
},
  "geometry": {"coordinates":[7.987637043,47.3456497192],"type":"Point"}
}