{
  "type": "Feature",
  "properties": {
    "iso:country":"CH",
    "sg:address":"Galserschstrasse 9a",
    "sg:city":"Flums",
    "sg:orig_category":"Non-Classified Establishments",
    "sg:postcode":"8890",
    "sg:province":"St. Gallen",
    "wof:name":"St\u00e4hli Othmar Heizung - Sanit\u00e4r Ag",
    "wof:placetype":"venue"
},
  "geometry": {"coordinates":[9.3559579849,47.0975074768],"type":"Point"}
}