{
  "type": "Feature",
  "properties": {
    "iso:country":"CH",
    "sg:address":"Riedm\u00fchlestrasse 16",
    "sg:city":"Rickenbach-attikon",
    "sg:orig_category":"Wirtschaftsverb\u00e4nde Gewerbeverb\u00e4nde/-vereine",
    "sg:phone":"+41 41 930 36 32",
    "sg:postcode":"8544",
    "sg:province":"Z\u00fcrich",
    "wof:name":"Gewerbeverein Rickenbach Pr\u00e4s.herrn Anton Habermacher",
    "wof:placetype":"venue"
},
  "geometry": {"coordinates":[8.1586523056,47.2196846008],"type":"Point"}
}