{
  "type": "Feature",
  "properties": {
    "addr:full":"Immeuble Trianon A/1 Crans-sur-sierre Valais 3963",
    "addr:postcode":"3963",
    "addr:street":"Crans-Sur-Sierre",
    "iso:country":"CH",
    "sg:address":"Immeuble Trianon A/1",
    "sg:city":"Crans-sur-sierre",
    "sg:orig_category":"Bauschreinerei Herstellung von M\u00f6beln verschiedener Art",
    "sg:phone":"+41 32 373 13 53",
    "sg:postcode":"3963",
    "sg:province":"Valais",
    "wof:name":"J\u00fcrg Hug Schreinerei",
    "wof:placetype":"venue"
},
  "geometry": {"coordinates":[7.298731,47.107227],"type":"Point"}
}