{
  "type": "Feature",
  "properties": {
    "iso:country":"CH",
    "sg:address":"Cendrier Rue Du 6 1201 Gen\u00e8ve. Postfach",
    "sg:city":"Gen\u00e8ve",
    "sg:orig_category":"Detailhandel mit Bekleidung",
    "sg:postcode":"1201",
    "sg:province":"Gen\u00e8ve",
    "wof:name":"Cendrilaine Sa",
    "wof:placetype":"venue"
},
  "geometry": {"coordinates":[6.14468,46.206905],"type":"Point"}
}