{
  "type": "Feature",
  "properties": {
    "iso:country":"CH",
    "sg:address":"Rebenweg 3",
    "sg:city":"Dotzigen",
    "sg:orig_category":"Wirtschaftspr\u00fcfung, Steuerberatung U Treuhand",
    "sg:phone":"+41 81 416 56 46",
    "sg:postcode":"3293",
    "sg:province":"Bern",
    "wof:name":"Monnard Claude",
    "wof:placetype":"venue"
},
  "geometry": {"coordinates":[9.8537597656,46.8327331543],"type":"Point"}
}