{
  "type": "Feature",
  "properties": {
    "iso:country":"CH",
    "sg:address":"Palazzo Mocasa",
    "sg:city":"Agno",
    "sg:orig_category":"Grosshandel mit B\u00fcromaschinen Grosshandel mit Datenverarbeitungsger\u00e4ten",
    "sg:phone":"+41 91 605 10 32",
    "sg:postcode":"6982",
    "sg:province":"Ticino",
    "wof:name":"Cwt Ag",
    "wof:placetype":"venue"
},
  "geometry": {"coordinates":[8.8993301392,45.9967536926],"type":"Point"}
}