{
  "type": "Feature",
  "properties": {
    "iso:country":"CH",
    "sg:address":"Weieried 5",
    "sg:city":"Jens",
    "sg:orig_category":"Wirtschaftspr\u00fcfung, Steuerberatung U Treuhand",
    "sg:phone":"+41 32 333 20 08",
    "sg:postcode":"2565",
    "sg:province":"Bern",
    "wof:name":"Urs M\u00fcller Commenda",
    "wof:placetype":"venue"
},
  "geometry": {"coordinates":[7.2607297897,47.0992660522],"type":"Point"}
}