{
  "type": "Feature",
  "properties": {
    "addr:full":"Viale Verbano 11 Muralto Ticino 6600",
    "addr:housenumber":"11",
    "addr:postcode":"6600",
    "addr:street":"Viale Verbano",
    "iso:country":"CH",
    "sg:address":"Viale Verbano 11",
    "sg:city":"Muralto",
    "sg:orig_category":"Detailhandel mit Brot, Back U S\u00fcsswaren",
    "sg:phone":"+41 91 743 01 81",
    "sg:postcode":"6600",
    "sg:province":"Ticino",
    "wof:name":"Al Porto Pasticceria- Confetteria Kreuziger Sa",
    "wof:placetype":"venue"
},
  "geometry": {"coordinates":[8.801973,46.171631],"type":"Point"}
}