{
  "type": "Feature",
  "properties": {
    "iso:country":"CH",
    "sg:address":"Neuengasse 38 3011 Bern. Postfach",
    "sg:city":"Bern",
    "sg:orig_category":"Sonstiger Fachdetailhandel in Verkaufsr\u00e4umen",
    "sg:phone":"+41 31 311 70 24",
    "sg:postcode":"3001",
    "sg:province":"Bern",
    "wof:name":"M\u00fcller Johannes Ansichtskarten, Briefmarken, M\u00fcnzen, B\u00fccher, Gold, Silber; Handel",
    "wof:placetype":"venue"
},
  "geometry": {"coordinates":[7.4416389465,46.9490089417],"type":"Point"}
}