{
  "type": "Feature",
  "properties": {
    "iso:country":"CH",
    "sg:address":"Place De L'ile 1",
    "sg:city":"Gen\u00e8ve",
    "sg:orig_category":"Kunsthandel",
    "sg:phone":"+41 22 342 81 08",
    "sg:postcode":"1204",
    "sg:province":"Gen\u00e8ve",
    "wof:name":"Charles Leuba Brocante",
    "wof:placetype":"venue"
},
  "geometry": {"coordinates":[6.1362662315,46.183921814],"type":"Point"}
}