{
  "type": "Feature",
  "properties": {
    "iso:country":"CH",
    "sg:address":"Jurastrasse 20 4600 Olten. Postfach",
    "sg:city":"Olten",
    "sg:orig_category":"Wirtschaftspr\u00fcfung, Steuerberatung U Treuhand",
    "sg:phone":"+41 62 206 00 69",
    "sg:postcode":"4601",
    "sg:province":"Solothurn",
    "wof:name":"Veto Versicherungs-treuhand Olten Georges Bracher.",
    "wof:placetype":"venue"
},
  "geometry": {"coordinates":[7.9030690193,47.3530158997],"type":"Point"}
}