{
  "type": "Feature",
  "properties": {
    "iso:country":"CH",
    "sg:address":"Chemin Du Belv\u00e9d\u00e8re 3",
    "sg:city":"Yverdon-les-bains",
    "sg:orig_category":"Wirtschafts U Arbeitgeberverb\u00e4nde",
    "sg:phone":"+41 24 425 66 90",
    "sg:postcode":"1400",
    "sg:province":"Vaud",
    "wof:name":"Association Helvinam",
    "wof:placetype":"venue"
},
  "geometry": {"coordinates":[6.6651477814,46.7738037109],"type":"Point"}
}