{
  "type": "Feature",
  "properties": {
    "iso:country":"CH",
    "sg:address":"Speerstrasse 56 8820 W\u00e4denswil. Postfach",
    "sg:city":"W\u00e4denswil",
    "sg:orig_category":"Grosshandel mit lebenden Tieren",
    "sg:phone":"+41 17801292",
    "sg:postcode":"8820",
    "sg:province":"Z\u00fcrich",
    "wof:name":"Schafzuchtgenossenschaft W\u00e4denswil Und Umgebung",
    "wof:placetype":"venue"
},
  "geometry": {"coordinates":[8.6668777466,47.225440979],"type":"Point"}
}