{
  "type": "Feature",
  "properties": {
    "iso:country":"CH",
    "sg:address":"Eigerstrasse 55 3007 Bern. Postfach",
    "sg:city":"Bern",
    "sg:orig_category":"Fachdetailhandel mit pharmazeutischen Produkten",
    "sg:postcode":"3005",
    "sg:province":"Bern",
    "wof:name":"Dr. W. Hool Apotheke",
    "wof:placetype":"venue"
},
  "geometry": {"coordinates":[7.4367179871,46.9398574829],"type":"Point"}
}