{
  "type": "Feature",
  "properties": {
    "iso:country":"CH",
    "sg:address":"Montoiseau Chemin De 4",
    "sg:city":"Crans-pr\u00e8s-c\u00e9ligny",
    "sg:orig_category":"Non-Classified Establishments",
    "sg:phone":"+41 61 401 40 92",
    "sg:postcode":"1299",
    "sg:province":"Vaud",
    "wof:name":"Pr Project Gmbh",
    "wof:placetype":"venue"
},
  "geometry": {"coordinates":[7.5529699326,47.5197563171],"type":"Point"}
}