{
  "type": "Feature",
  "properties": {
    "iso:country":"CH",
    "sg:address":"1115",
    "sg:city":"Vullierens",
    "sg:orig_category":"Mechanische Werkst\u00e4tten",
    "sg:phone":"+41 91 646 12 55",
    "sg:postcode":"1115",
    "sg:province":"Vaud",
    "wof:name":"G. & E. Bernasconi Garage",
    "wof:placetype":"venue"
},
  "geometry": {"coordinates":[9.004034996,45.8632316589],"type":"Point"}
}