{
  "type": "Feature",
  "properties": {
    "iso:country":"CH",
    "sg:address":"Bernstrasse 35",
    "sg:city":"M\u00fcnsingen",
    "sg:orig_category":"Detailhandel mit Fahrr\u00e4dern Detailhandel mit Sportartikeln",
    "sg:phone":"+41 31 722 12 80",
    "sg:postcode":"3110",
    "sg:province":"Bern",
    "wof:name":"Bike & Snowboardcenter Hirschi & Hefti Gmbh",
    "wof:placetype":"venue"
},
  "geometry": {"coordinates":[7.5587630272,46.8808288574],"type":"Point"}
}