{
  "type": "Feature",
  "properties": {
    "addr:full":"Rheinstrasse 189 Chur Graubunden 7000",
    "addr:housenumber":"189",
    "addr:postcode":"7000",
    "addr:street":"Rheinstrasse",
    "iso:country":"CH",
    "sg:address":"Rheinstrasse 189",
    "sg:city":"Chur",
    "sg:orig_category":"Betrieb von Taxis",
    "sg:phone":"+41 81 250 66 66",
    "sg:postcode":"7000",
    "sg:province":"Graubunden",
    "wof:name":"Rhi Taxi Gmbh",
    "wof:placetype":"venue"
},
  "geometry": {"coordinates":[9.513135,46.862583],"type":"Point"}
}