{
  "type": "Feature",
  "properties": {
    "iso:country":"CH",
    "sg:address":"Hauptstrasse 110",
    "sg:city":"Binningen",
    "sg:orig_category":"Detailhandel mit B\u00fcchern Detailhandel mit B\u00fcchern, Zeitungen, Schreib U Papeteriewaren",
    "sg:phone":"+41 61 421 48 00",
    "sg:postcode":"4102",
    "sg:province":"Basel-Landschaft",
    "wof:name":"Birsig-buchhandlung H\u00e4ne & Co",
    "wof:placetype":"venue"
},
  "geometry": {"coordinates":[7.57225,47.539143],"type":"Point"}
}