{
  "type": "Feature",
  "properties": {
    "iso:country":"CH",
    "sg:address":"Alt Unterhaus",
    "sg:city":"Horgenberg",
    "sg:orig_category":"Unclassifiable Establishments",
    "sg:postcode":"8815",
    "sg:province":"Z\u00fcrich",
    "wof:name":"Team4you Gmbh",
    "wof:placetype":"venue"
},
  "geometry": {"coordinates":[8.5880098343,47.2476348877],"type":"Point"}
}