{
  "type": "Feature",
  "properties": {
    "iso:country":"CH",
    "sg:address":"Brunnenstrasse 2",
    "sg:city":"Uster",
    "sg:orig_category":"Architekturb\u00fcros",
    "sg:phone":"+41 19404382",
    "sg:postcode":"8610",
    "sg:province":"Z\u00fcrich",
    "wof:name":"Heinz Widmer Architekturb\u00fcro",
    "wof:placetype":"venue"
},
  "geometry": {"coordinates":[8.720005,47.349983],"type":"Point"}
}