{
  "type": "Feature",
  "properties": {
    "iso:country":"CH",
    "sg:address":"Klusstrasse 1",
    "sg:city":"Oensingen",
    "sg:classifiers":[
        {
            "category":"Personal",
            "subcategory":"Nail Salon",
            "type":"Services"
        }
    ],
    "sg:phone":"+41 22 300 47 89",
    "sg:postcode":"4702",
    "sg:province":"Solothurn",
    "sg:tags":[
        "manicure"
    ],
    "wof:name":"Eva Werner Nail Cosmetique",
    "wof:placetype":"venue"
},
  "geometry": {"coordinates":[6.1390371323,46.1849479675],"type":"Point"}
}