{
  "type": "Feature",
  "properties": {
    "iso:country":"CH",
    "sg:address":"Faubourg Rue Du 20",
    "sg:city":"Soral",
    "sg:orig_category":"Architektur U Ingenieurb\u00fcros",
    "sg:postcode":"1286",
    "sg:province":"Gen\u00e8ve",
    "wof:name":"Meichtry Jean",
    "wof:placetype":"venue"
},
  "geometry": {"coordinates":[6.041523,46.14257],"type":"Point"}
}