{
  "type": "Feature",
  "properties": {
    "iso:country":"CH",
    "sg:address":"Bahnhofstrasse 143",
    "sg:city":"Schiers",
    "sg:orig_category":"Arztpraxen",
    "sg:phone":"+41 81 410 60 70",
    "sg:postcode":"7220",
    "sg:province":"Graubunden",
    "wof:name":"Dr.med. Marc Kammann Spezialarzt Fmh",
    "wof:placetype":"venue"
},
  "geometry": {"coordinates":[9.687862,46.968102],"type":"Point"}
}