{
  "type": "Feature",
  "properties": {
    "iso:country":"CH",
    "sg:address":"Steinentorstrasse 30",
    "sg:city":"Basel",
    "sg:orig_category":"Allgemeinbildende weiterf\u00fchrende Schulen Maturit\u00e4tsschulen, Lehrerseminarien",
    "sg:phone":"+41 61 278 98 88",
    "sg:postcode":"4051",
    "sg:province":"Basel-Stadt",
    "wof:name":"Minerva Schulen Basel",
    "wof:placetype":"venue"
},
  "geometry": {"coordinates":[7.587408,47.551231],"type":"Point"}
}