{
  "type": "Feature",
  "properties": {
    "iso:country":"CH",
    "sg:address":"Route De Coinsins 1 1272 Genolier. Postfach",
    "sg:city":"Genolier",
    "sg:orig_category":"Finanzierungsinstitutionen",
    "sg:postcode":"1272",
    "sg:province":"Vaud",
    "wof:name":"Cbi Consultants In Banking And Insurance S\u00e0rl",
    "wof:placetype":"venue"
},
  "geometry": {"coordinates":[6.2189512253,46.4357376099],"type":"Point"}
}