{
  "type": "Feature",
  "properties": {
    "iso:country":"CH",
    "sg:address":"H\u00e4uslerstrasse 40",
    "sg:city":"Thalwil",
    "sg:orig_category":"Herstellung von keramischen Wand U Bodenfliesen U platten",
    "sg:postcode":"8800",
    "sg:province":"Z\u00fcrich",
    "wof:name":"R\u00fcegg Ernst Keram. Wand Und Bodenbel\u00e4ge",
    "wof:placetype":"venue"
},
  "geometry": {"coordinates":[9.0491952896,47.2206306458],"type":"Point"}
}