{
  "type": "Feature",
  "properties": {
    "iso:country":"CH",
    "sg:address":"R\u00f6ssligasse 19",
    "sg:city":"Gelterkinden",
    "sg:orig_category":"Non-Classified Establishments",
    "sg:phone":"+41 61 983 03 14",
    "sg:postcode":"4460",
    "sg:province":"Basel-Landschaft",
    "wof:name":"Da Sabatino",
    "wof:placetype":"venue"
},
  "geometry": {"coordinates":[7.8541808128,47.465461731],"type":"Point"}
}