{
  "type": "Feature",
  "properties": {
    "iso:country":"CH",
    "sg:address":"Landstrasse 15",
    "sg:city":"Schaan",
    "sg:orig_category":"Detailhandel mit Schreib U Papeteriewaren Druckweiterverarbeitung",
    "sg:phone":"+423 232 19 31",
    "sg:postcode":"9494",
    "wof:name":"Wolfgang Matt",
    "wof:placetype":"venue"
},
  "geometry": {"coordinates":[9.5096006393,47.1662902832],"type":"Point"}
}