{
  "type": "Feature",
  "properties": {
    "iso:country":"CH",
    "sg:address":"Freiestrasse 36",
    "sg:city":"Z\u00fcrich",
    "sg:orig_category":"Bibliotheken U Archive Universit\u00e4ten, Hochschulen",
    "sg:phone":"+41 12572233",
    "sg:postcode":"8032",
    "sg:province":"Z\u00fcrich",
    "wof:name":"Rechtswissenschaftl.institut",
    "wof:placetype":"venue"
},
  "geometry": {"coordinates":[8.554083,47.371094],"type":"Point"}
}