{
  "type": "Feature",
  "properties": {
    "addr:full":"Im Holderbaum 2 Bauma Z\u00fcrich 8494",
    "addr:housenumber":"2",
    "addr:postcode":"8494",
    "addr:street":"Im Holderbaum",
    "iso:country":"CH",
    "sg:address":"Im Holderbaum 2",
    "sg:city":"Bauma",
    "sg:orig_category":"Bauingenieurb\u00fcros allgemein",
    "sg:phone":"+41 52 386 24 81",
    "sg:postcode":"8494",
    "sg:province":"Z\u00fcrich",
    "wof:name":"Gerd-ulrich Wulff Ingenieurb\u00fcro",
    "wof:placetype":"venue"
},
  "geometry": {"coordinates":[8.884532,47.366066],"type":"Point"}
}