{
  "type": "Feature",
  "properties": {
    "iso:country":"CH",
    "sg:address":"Sch\u00e4nzlihalde 31 3013 Bern. Postfach",
    "sg:city":"Bern",
    "sg:orig_category":"Kantinen",
    "sg:phone":"+41 31 331 78 92",
    "sg:postcode":"3005",
    "sg:province":"Bern",
    "wof:name":"H. Sch\u00f6nberg Betrieb Der Erfrischungsr\u00e4ume Der Kunstgewerbeschule Bern",
    "wof:placetype":"venue"
},
  "geometry": {"coordinates":[7.4463410378,46.9538078308],"type":"Point"}
}