{
  "type": "Feature",
  "properties": {
    "iso:country":"CH",
    "sg:address":"Loch\u00e4ckerstrasse 37",
    "sg:city":"Kloten",
    "sg:orig_category":"Herstellung von Duft U K\u00f6rperpflegemitteln",
    "sg:postcode":"8302",
    "sg:province":"Z\u00fcrich",
    "wof:name":"Distroma Tc1 Gmbh",
    "wof:placetype":"venue"
},
  "geometry": {"coordinates":[8.5914983749,47.4442367554],"type":"Point"}
}