{
  "type": "Feature",
  "properties": {
    "iso:country":"CH",
    "sg:address":"Oberhausen",
    "sg:city":"Braunau",
    "sg:orig_category":"Verarbeitung von Milch Verwertung von Milch",
    "sg:phone":"+41 71 911 59 22",
    "sg:postcode":"9502",
    "sg:province":"Thurgau",
    "wof:name":"Heinz Kretz K\u00e4serei",
    "wof:placetype":"venue"
},
  "geometry": {"coordinates":[9.0732069016,47.502986908],"type":"Point"}
}