{
  "type": "Feature",
  "properties": {
    "iso:country":"CH",
    "sg:address":"Route De Gryon 31 1880 Bex Case Postale 277",
    "sg:city":"Bex",
    "sg:orig_category":"Gewinnung von Salz",
    "sg:phone":"+41 24 463 03 20",
    "sg:postcode":"1880",
    "sg:province":"Vaud",
    "wof:name":"Soci\u00e9t\u00e9 Vaudoise Des Mines Et Salines De Bex",
    "wof:placetype":"venue"
},
  "geometry": {"coordinates":[7.030755043,46.2593955994],"type":"Point"}
}