{
  "type": "Feature",
  "properties": {
    "iso:country":"CH",
    "sg:address":"Falknisstrasse 11b",
    "sg:city":"Sargans",
    "sg:orig_category":"Fahrr\u00e4der and Zubeh\u00f6r Grosshandel Handel mit Motorr\u00e4dern, Teilen U Zubeh\u00f6r Instandhaltung U Reparatu",
    "sg:postcode":"7320",
    "sg:province":"St. Gallen",
    "wof:name":"Urs Rybi Rybike Velowerkstatt",
    "wof:placetype":"venue"
},
  "geometry": {"coordinates":[8.7757968903,47.3678207397],"type":"Point"}
}