{
  "type": "Feature",
  "properties": {
    "iso:country":"CH",
    "sg:address":"Huber Avenue Max 10",
    "sg:city":"Sierre",
    "sg:orig_category":"Unclassifiable Establishments",
    "sg:postcode":"3960",
    "sg:province":"Valais",
    "wof:name":"Vacances Neige Sa No 40",
    "wof:placetype":"venue"
},
  "geometry": {"coordinates":[7.5306549072,46.2924041748],"type":"Point"}
}