{
  "type": "Feature",
  "properties": {
    "iso:country":"CH",
    "sg:address":"Saumstrasse 19",
    "sg:city":"Z\u00fcrich",
    "sg:orig_category":"Verwaltung von Immobilien",
    "sg:postcode":"8003",
    "sg:province":"Z\u00fcrich",
    "wof:name":"Imba Ag",
    "wof:placetype":"venue"
},
  "geometry": {"coordinates":[8.5130395889,47.371181488],"type":"Point"}
}