{
  "type": "Feature",
  "properties": {
    "iso:country":"CH",
    "sg:address":"Helblingstrasse 3",
    "sg:city":"Rothrist",
    "sg:classifiers":[
        {
            "category":"Manufacturing",
            "subcategory":"Wood Products",
            "type":"Manufacturing & Wholesale Goods"
        }
    ],
    "sg:phone":"+41 62 794 31 44",
    "sg:postcode":"4852",
    "sg:province":"Aargau",
    "sg:tags":[
        "interior",
        "fixture"
    ],
    "wof:name":"Bruno B\u00e4r Ag",
    "wof:placetype":"venue"
},
  "geometry": {"coordinates":[7.8924841881,47.3089256287],"type":"Point"}
}