{
  "type": "Feature",
  "properties": {
    "iso:country":"CH",
    "sg:address":"Chemin De Verdilloux 9",
    "sg:city":"Corminboeuf",
    "sg:orig_category":"Selbst\u00e4ndige bildende K\u00fcnstler",
    "sg:phone":"+41 26 402 22 49",
    "sg:postcode":"1720",
    "sg:province":"Fribourg",
    "wof:name":"Emile Ang\u00e9loz Sculpteur Sur Pierre",
    "wof:placetype":"venue"
},
  "geometry": {"coordinates":[7.0943422318,46.8010597229],"type":"Point"}
}