{
  "type": "Feature",
  "properties": {
    "iso:country":"CH",
    "sg:address":"Harmoniestrasse 2",
    "sg:city":"St\u00e4fa",
    "sg:orig_category":"RESTAURANTS: TEA-ROOMS",
    "sg:postcode":"8712",
    "sg:province":"Z\u00fcrich",
    "wof:name":"Mariba Gastro Gmbh",
    "wof:placetype":"venue"
},
  "geometry": {"coordinates":[8.722492218,47.2395820618],"type":"Point"}
}