{
  "type": "Feature",
  "properties": {
    "iso:country":"CH",
    "sg:address":"Chemin Du Pont 5",
    "sg:city":"Martigny",
    "sg:orig_category":"Stukkateurgewerbe, Gipserei U Verputzerei",
    "sg:phone":"+41 27 722 66 44",
    "sg:postcode":"1920",
    "sg:province":"Valais",
    "wof:name":"Bossetti Fr\u00e8res Gypserie & Peinture",
    "wof:placetype":"venue"
},
  "geometry": {"coordinates":[7.0718078613,46.1063156128],"type":"Point"}
}