{
  "type": "Feature",
  "properties": {
    "iso:country":"CH",
    "sg:address":"8499",
    "sg:city":"Sternenberg",
    "sg:orig_category":"Verwertung von Milch",
    "sg:postcode":"8499",
    "sg:province":"Z\u00fcrich",
    "wof:name":"Sennereigenossenschaft Aeugstertal",
    "wof:placetype":"venue"
},
  "geometry": {"coordinates":[8.4854745865,47.2676887512],"type":"Point"}
}