{
  "type": "Feature",
  "properties": {
    "iso:country":"CH",
    "sg:address":"Place Croix Blanche 3",
    "sg:city":"Epalinges",
    "sg:orig_category":"Physiotherapie",
    "sg:phone":"+41 21 784 49 49",
    "sg:postcode":"1066",
    "sg:province":"Vaud",
    "wof:name":"Alain Berset & J\u00e9r\u00f4me Urio Physioth\u00e9rapie",
    "wof:placetype":"venue"
},
  "geometry": {"coordinates":[6.6716017723,46.5481758118],"type":"Point"}
}