{
  "type": "Feature",
  "properties": {
    "iso:country":"CH",
    "sg:address":"Im H\u00f6fli D",
    "sg:city":"Regensberg",
    "sg:orig_category":"Sportvereine Orientierungslauf",
    "sg:phone":"+41 18530477",
    "sg:postcode":"8158",
    "sg:province":"Z\u00fcrich",
    "wof:name":"Olg Z\u00fcrinord",
    "wof:placetype":"venue"
},
  "geometry": {"coordinates":[8.4363718033,47.4825248718],"type":"Point"}
}