{
  "type": "Feature",
  "properties": {
    "iso:country":"CH",
    "sg:address":"Z\u00fcrichstrasse 25",
    "sg:city":"Winkel",
    "sg:classifiers":[
        {
            "category":"Restaurant",
            "type":"Food & Drink"
        }
    ],
    "sg:phone":"+41 81 833 30 22",
    "sg:postcode":"8185",
    "sg:province":"Z\u00fcrich",
    "sg:tags":[
        "tea-rooms",
        "restaurants"
    ],
    "wof:name":"Restaurant Zigane, Pianta F.",
    "wof:placetype":"venue"
},
  "geometry": {"coordinates":[9.8367776871,46.4863204956],"type":"Point"}
}