{
  "type": "Feature",
  "properties": {
    "iso:country":"CH",
    "sg:address":"Arbentalstrasse 226 8045 Z\u00fcrich",
    "sg:city":"Zust",
    "sg:orig_category":"Grosshandel mit Textilien",
    "sg:postcode":"45",
    "wof:name":"Fantastica Ag Warenimport U. -handel, Bes. Textilien Usw",
    "wof:placetype":"venue"
},
  "geometry": {"coordinates":[8.5118503571,47.3567810059],"type":"Point"}
}