{
  "type": "Feature",
  "properties": {
    "addr:full":"Friedenstrasse 8 9220 Bischofszell. Postfach Bischofszell Thurgau 9220",
    "addr:housenumber":"8",
    "addr:postcode":"9220 bischofszell. postfach;9220",
    "addr:street":"Friedenstrasse",
    "iso:country":"CH",
    "sg:address":"Friedenstrasse 8 9220 Bischofszell. Postfach",
    "sg:city":"Bischofszell",
    "sg:orig_category":"Architektur U Ingenieurb\u00fcros",
    "sg:phone":"+41 71 422 10 71",
    "sg:postcode":"9220",
    "sg:province":"Thurgau",
    "wof:name":"Ingenieurb\u00fcro Osterwalder Geisser & Brugger Ag",
    "wof:placetype":"venue"
},
  "geometry": {"coordinates":[9.247851,47.493233],"type":"Point"}
}