{
  "type": "Feature",
  "properties": {
    "iso:country":"CH",
    "sg:address":"Fl\u00f6sch\u00e4gerten 4",
    "sg:city":"M\u00fchlethurnen",
    "sg:classifiers":[
        {
            "category":"Utilities",
            "subcategory":"Water",
            "type":"Services"
        }
    ],
    "sg:phone":"+41 31 808 07 07",
    "sg:postcode":"3127",
    "sg:province":"Bern",
    "sg:tags":[
        "consulting",
        "software"
    ],
    "wof:name":"Allinfo Ag",
    "wof:placetype":"venue"
},
  "geometry": {"coordinates":[7.5063858032,46.8184623718],"type":"Point"}
}