{
  "type": "Feature",
  "properties": {
    "iso:country":"CH",
    "sg:address":"Viale Bartolomeo Papio 5",
    "sg:city":"Ascona",
    "sg:classifiers":[
        {
            "category":"Banks & Credit Unions",
            "subcategory":"Bank",
            "type":"Services"
        }
    ],
    "sg:phone":"+41 91 786 95 00",
    "sg:postcode":"6612",
    "sg:province":"Ticino",
    "wof:name":"Swiss Bank Corp.",
    "wof:placetype":"venue"
},
  "geometry": {"coordinates":[8.770001,46.156528],"type":"Point"}
}