{
  "type": "Feature",
  "properties": {
    "iso:country":"CH",
    "sg:address":"Pagaweg 3a",
    "sg:city":"Nidau",
    "sg:orig_category":"Handels-H\u00e4user U Gesellschaften",
    "sg:postcode":"2560",
    "sg:province":"Bern",
    "wof:name":"B\u00fcro Kneub\u00fchler",
    "wof:placetype":"venue"
},
  "geometry": {"coordinates":[8.5484037399,47.3217010498],"type":"Point"}
}