{
  "type": "Feature",
  "properties": {
    "iso:country":"CH",
    "sg:address":"Unterdorf 2 6018 Buttisholz. Postfach",
    "sg:city":"Buttisholz",
    "sg:orig_category":"Sanit\u00e4r, Heizungs U L\u00fcftungsinstallation",
    "sg:phone":"+41 12724123",
    "sg:postcode":"6018",
    "sg:province":"Luzern",
    "wof:name":"Hydros-plus S\u00e0rl",
    "wof:placetype":"venue"
},
  "geometry": {"coordinates":[5.1808700562,45.8973388672],"type":"Point"}
}