{
  "type": "Feature",
  "properties": {
    "iso:country":"CH",
    "sg:address":"Stolzestrasse 3",
    "sg:city":"Z\u00fcrich",
    "sg:classifiers":[
        {
            "category":"Wholesale",
            "subcategory":"Medical Equipment & Supplies",
            "type":"Manufacturing & Wholesale Goods"
        }
    ],
    "sg:phone":"+41 13633022",
    "sg:postcode":"8006",
    "sg:province":"Z\u00fcrich",
    "sg:tags":[
        "physicians",
        "hospital",
        "clothing",
        "surgical"
    ],
    "wof:name":"Faessler Ag",
    "wof:placetype":"venue"
},
  "geometry": {"coordinates":[8.546156,47.386208],"type":"Point"}
}