{
  "type": "Feature",
  "properties": {
    "addr:full":"Bernstrasse 4 3114 Oberwichtrach. Postfach 242 Oberwichtrach Bern 3114",
    "addr:housenumber":"4;242",
    "addr:postcode":"3114;3114",
    "addr:street":"Bernstrasse;Postfach",
    "iso:country":"CH",
    "sg:address":"Bernstrasse 4 3114 Oberwichtrach. Postfach 242",
    "sg:city":"Oberwichtrach",
    "sg:orig_category":"Architektur U Ingenieurb\u00fcros Herstellung von Werkzeugmaschinen",
    "sg:phone":"+41 31 780 24 24",
    "sg:postcode":"3114",
    "sg:province":"Bern",
    "wof:name":"Deleproject Ag",
    "wof:placetype":"venue"
},
  "geometry": {"coordinates":[7.576506,46.843365],"type":"Point"}
}