{
  "type": "Feature",
  "properties": {
    "iso:country":"CH",
    "sg:address":"3925 Gr\u00e4chen. Postfach 178",
    "sg:city":"Gr\u00e4chen",
    "sg:orig_category":"Detailhandel mit Brot, Back U S\u00fcsswaren",
    "sg:phone":"+41 27 956 22 55",
    "sg:postcode":"3925",
    "sg:province":"Valais",
    "wof:name":"Andreas Walter B\u00e4ckerei",
    "wof:placetype":"venue"
},
  "geometry": {"coordinates":[7.83924,46.196163],"type":"Point"}
}