{
  "type": "Feature",
  "properties": {
    "iso:country":"CH",
    "sg:address":"Untermattweg 8 3027 Bern. Postfach",
    "sg:city":"Bern",
    "sg:orig_category":"Dienstleistungen von Beteiligungsgesellschaften",
    "sg:postcode":"3001",
    "sg:province":"Bern",
    "wof:name":"Gallura Sa",
    "wof:placetype":"venue"
},
  "geometry": {"coordinates":[7.2124481201,46.0804595947],"type":"Point"}
}