{
  "type": "Feature",
  "properties": {
    "iso:country":"CH",
    "sg:address":"Seeblickstrasse 29",
    "sg:city":"T\u00fcbach",
    "sg:classifiers":[
        {
            "category":"Insurance",
            "subcategory":"Insurance Agent",
            "type":"Services"
        }
    ],
    "sg:phone":"+41 71 999 28 55",
    "sg:postcode":"9327",
    "sg:province":"St. Gallen",
    "sg:tags":[
        "versicherungsagenturen",
        "-broker"
    ],
    "wof:name":"Z\u00fcrich-versicherungen Agentur",
    "wof:placetype":"venue"
},
  "geometry": {"coordinates":[9.2497396469,47.1857299805],"type":"Point"}
}