{
  "type": "Feature",
  "properties": {
    "iso:country":"CH",
    "sg:address":"Bahnhofstrasse 2",
    "sg:city":"Oberr\u00fcti",
    "sg:orig_category":"Mechanik Mechanische Werkst\u00e4tten",
    "sg:phone":"+41 41 787 19 93",
    "sg:postcode":"5647",
    "sg:province":"Aargau",
    "wof:name":"Hess Kurt Pr\u00e4zisionsmechanik",
    "wof:placetype":"venue"
},
  "geometry": {"coordinates":[8.3948659897,47.1660346985],"type":"Point"}
}