{
  "type": "Feature",
  "properties": {
    "iso:country":"CH",
    "sg:address":"Rue De L'ecluse 1",
    "sg:city":"Moutier",
    "sg:orig_category":"Drogerien",
    "sg:phone":"+41 32 493 28 80",
    "sg:postcode":"2740",
    "sg:province":"Bern",
    "wof:name":"Droguerie Borel Sa",
    "wof:placetype":"venue"
},
  "geometry": {"coordinates":[7.382581234,47.2798233032],"type":"Point"}
}