{
  "type": "Feature",
  "properties": {
    "iso:country":"CH",
    "sg:address":"Postgasse 16",
    "sg:city":"Wattenwil",
    "sg:orig_category":"Sportvereine Turnen",
    "sg:phone":"+41 33 356 21 01",
    "sg:postcode":"3665",
    "sg:province":"Bern",
    "wof:name":"Turnverein Stv Thierachern",
    "wof:placetype":"venue"
},
  "geometry": {"coordinates":[7.5078020096,46.7682533264],"type":"Point"}
}