{
  "type": "Feature",
  "properties": {
    "iso:country":"CH",
    "sg:address":"Industriestrasse 42",
    "sg:city":"F\u00e4llanden",
    "sg:orig_category":"Druck ohne Zeitungsdruck Werbegrafikateliers",
    "sg:phone":"+41 18251819",
    "sg:postcode":"8117",
    "sg:province":"Z\u00fcrich",
    "wof:name":"Martin Bolt Bolt Graphix",
    "wof:placetype":"venue"
},
  "geometry": {"coordinates":[8.6448335648,47.3785552979],"type":"Point"}
}