{
  "type": "Feature",
  "properties": {
    "iso:country":"CH",
    "sg:address":"Englisch-gruss-strasse 1",
    "sg:city":"Glis",
    "sg:orig_category":"Arztpraxen",
    "sg:phone":"+41 27 923 49 37",
    "sg:postcode":"3902",
    "sg:province":"Valais",
    "wof:name":"Dr.med.diego Verasani Arzt F.allgemeine Medizin Fmh",
    "wof:placetype":"venue"
},
  "geometry": {"coordinates":[7.986967,46.315926],"type":"Point"}
}