{
  "type": "Feature",
  "properties": {
    "iso:country":"CH",
    "sg:address":"Rue Du Village 34",
    "sg:city":"Ecl\u00e9pens",
    "sg:orig_category":"Erbringung von Dienstleistungen f\u00fcr Unternehmen",
    "sg:phone":"+41 79 658 39 69",
    "sg:postcode":"1312",
    "sg:province":"Vaud",
    "wof:name":"Cma Concept, M\u00e9thodes Appliqu\u00e9es Sa",
    "wof:placetype":"venue"
},
  "geometry": {"coordinates":[6.5281891823,46.6511116028],"type":"Point"}
}