{
  "type": "Feature",
  "properties": {
    "iso:country":"CH",
    "sg:address":"Luzernstrasse 29",
    "sg:city":"Solothurn",
    "sg:orig_category":"Physiotherapie",
    "sg:phone":"+41 32 622 09 86",
    "sg:postcode":"4500",
    "sg:province":"Solothurn",
    "wof:name":"Heinz H\u00e4ner Physiotherapie",
    "wof:placetype":"venue"
},
  "geometry": {"coordinates":[7.5465660095,47.2051315308],"type":"Point"}
}