{
  "type": "Feature",
  "properties": {
    "iso:country":"CH",
    "sg:address":"St. Gallerstrasse 4",
    "sg:city":"Kronb\u00fchl",
    "sg:orig_category":"Nationale Postdienste",
    "sg:phone":"+41 71 298 22 66",
    "sg:postcode":"9302",
    "wof:name":"Die Schweizerische Post",
    "wof:placetype":"venue"
},
  "geometry": {"coordinates":[9.3955545425,47.4584732056],"type":"Point"}
}