{
  "type": "Feature",
  "properties": {
    "iso:country":"CH",
    "sg:address":"Tittwiesenstrasse 61 7000 Chur. Postfach",
    "sg:city":"Chur",
    "sg:orig_category":"Verwaltung von Immobilien",
    "sg:phone":"+41 79 658 90 72",
    "sg:postcode":"7000",
    "sg:province":"Graubunden",
    "wof:name":"Fux Treuhand & Beratungs Ag",
    "wof:placetype":"venue"
},
  "geometry": {"coordinates":[7.8021011353,46.1756629944],"type":"Point"}
}