{
  "type": "Feature",
  "properties": {
    "iso:country":"CH",
    "sg:address":"Dorfstr.",
    "sg:city":"Diemtigen",
    "sg:orig_category":"Detailhandel mit elektrischen Haushalts-,Radio U Fernsehger\u00e4ten sowie Musikinstrumenten",
    "sg:phone":"+41 33 681 24 19",
    "sg:postcode":"3754",
    "sg:province":"Bern",
    "wof:name":"Radio Berger Ag",
    "wof:placetype":"venue"
},
  "geometry": {"coordinates":[7.5777101517,46.661190033],"type":"Point"}
}