{
  "type": "Feature",
  "properties": {
    "iso:country":"CH",
    "sg:address":"Rue Centrale 59",
    "sg:city":"Moutier",
    "sg:orig_category":"Organisationen der Wohlfahrtspflege",
    "sg:phone":"+41 32 486 91 00",
    "sg:postcode":"2740",
    "sg:province":"Bern",
    "wof:name":"Centre Social Protestant Jurassien",
    "wof:placetype":"venue"
},
  "geometry": {"coordinates":[7.3719248772,47.2793121338],"type":"Point"}
}