{
  "type": "Feature",
  "properties": {
    "iso:country":"CH",
    "sg:address":"Hauptstrasse 95",
    "sg:city":"Zeglingen",
    "sg:orig_category":"Detektivb\u00fcros U \u00dcberwachung",
    "sg:phone":"+41 61 981 31 90",
    "sg:postcode":"4495",
    "sg:province":"Basel-Landschaft",
    "wof:name":"Agri Werner Ringele",
    "wof:placetype":"venue"
},
  "geometry": {"coordinates":[7.9073700905,47.4166984558],"type":"Point"}
}