{
  "type": "Feature",
  "properties": {
    "iso:country":"CH",
    "sg:address":"Morgenstrasse 136 3018 Bern. Postfach",
    "sg:city":"Bern",
    "sg:orig_category":"Unclassifiable Establishments",
    "sg:phone":"+41 31 994 20 25",
    "sg:postcode":"3018",
    "sg:province":"Bern",
    "wof:name":"Herzog Kull Group Bern Ag Haustechnische Installationen Von Geb\u00e4ude; Planung Usw.",
    "wof:placetype":"venue"
},
  "geometry": {"coordinates":[7.388299942,46.9342651367],"type":"Point"}
}