{
  "type": "Feature",
  "properties": {
    "iso:country":"CH",
    "sg:address":"Sustenstrasse 5",
    "sg:city":"Susten",
    "sg:orig_category":"Detailhandel mit Schuhen Detailhandel mit Schuhen U Lederwaren",
    "sg:phone":"+41 81 756 15 39",
    "sg:postcode":"3952",
    "sg:province":"Valais",
    "wof:name":"Schuhhaus Rutz Ag",
    "wof:placetype":"venue"
},
  "geometry": {"coordinates":[9.4738588333,47.1660614014],"type":"Point"}
}