{
  "type": "Feature",
  "properties": {
    "iso:country":"CH",
    "sg:address":"Avenue De Chailly 23",
    "sg:city":"Lausanne",
    "sg:orig_category":"Architekturb\u00fcros",
    "sg:phone":"+41 21 653 56 61",
    "sg:postcode":"1012",
    "sg:province":"Vaud",
    "wof:name":"Bureau D'architecture Knecht Richard.",
    "wof:placetype":"venue"
},
  "geometry": {"coordinates":[6.652741,46.525043],"type":"Point"}
}