{
  "type": "Feature",
  "properties": {
    "iso:country":"CH",
    "sg:address":"Oberwilerstrasse 20",
    "sg:city":"Basel",
    "sg:orig_category":"Shiatsu-Therapie",
    "sg:phone":"+41 41 850 37 33",
    "sg:postcode":"4054",
    "sg:province":"Basel-Stadt",
    "wof:name":"Dorothea Hansen Shiatsu",
    "wof:placetype":"venue"
},
  "geometry": {"coordinates":[8.4312448502,47.0851516724],"type":"Point"}
}