{
  "type": "Feature",
  "properties": {
    "iso:country":"CH",
    "sg:address":"Z\u00fcrichstrasse 201 8122 Binz. Postfach",
    "sg:city":"Binz",
    "sg:orig_category":"Fahrschulen, Flugschulen",
    "sg:phone":"+41 81 413 75 43",
    "sg:postcode":"8122",
    "sg:province":"Z\u00fcrich",
    "wof:name":"Avis Autovermietung Ag",
    "wof:placetype":"venue"
},
  "geometry": {"coordinates":[9.8246126175,46.7952690125],"type":"Point"}
}