{
  "type": "Feature",
  "properties": {
    "iso:country":"CH",
    "sg:address":"Rue Centrale 8",
    "sg:city":"Ste-croix",
    "sg:orig_category":"Detailhandel mit Waren verschiedener Art, Hauptrichtung Nahrungsmittel",
    "sg:phone":"+41 24 454 35 65",
    "sg:postcode":"1450",
    "sg:province":"Vaud",
    "wof:name":"Jaccard Fr\u00e8res Discount Abc",
    "wof:placetype":"venue"
},
  "geometry": {"coordinates":[6.5018029213,46.8234176636],"type":"Point"}
}