{
  "type": "Feature",
  "properties": {
    "iso:country":"CH",
    "sg:address":"Route De Satigny 56 1217 Meyrin Case Postale 135",
    "sg:city":"Satigny",
    "sg:orig_category":"Detailhandel mit Waren verschiedener Art, Hauptrichtung Nahrungsmittel Grosshandel mit Fleisch U Fle",
    "sg:phone":"+41 22 785 53 13",
    "sg:postcode":"1242",
    "sg:province":"Gen\u00e8ve",
    "wof:name":"Galliwag Sa",
    "wof:placetype":"venue"
},
  "geometry": {"coordinates":[6.0691370964,46.2185974121],"type":"Point"}
}