{
  "type": "Feature",
  "properties": {
    "iso:country":"CH",
    "sg:address":"B\u00fcsserachstrasse 148",
    "sg:city":"Fehren",
    "sg:orig_category":"Autogaragen",
    "sg:phone":"+41 61 791 09 88",
    "sg:postcode":"4232",
    "sg:province":"Solothurn",
    "wof:name":"Franz Hofer Jun. Autoreparaturen",
    "wof:placetype":"venue"
},
  "geometry": {"coordinates":[7.575208,47.394711],"type":"Point"}
}