{
  "type": "Feature",
  "properties": {
    "iso:country":"CH",
    "sg:address":"Route Des Addoz 9a",
    "sg:city":"Boudry",
    "sg:orig_category":"Allgemeiner Hoch U Tiefbau Maurerarbeiten",
    "sg:phone":"+41 32 842 44 86",
    "sg:postcode":"2017",
    "sg:province":"Neuch\u00e2tel",
    "wof:name":"Michel Morciano Entreprise De Carrelages",
    "wof:placetype":"venue"
},
  "geometry": {"coordinates":[6.829197,46.951363],"type":"Point"}
}