{
  "type": "Feature",
  "properties": {
    "iso:country":"CH",
    "sg:address":"Moosg\u00e4ssli 28",
    "sg:city":"Koppigen",
    "sg:orig_category":"Sonstige k\u00fcnstlerische U schriftstellerische T\u00e4tigkeiten U Darbietungen",
    "sg:phone":"+41 34 413 18 34",
    "sg:postcode":"3425",
    "sg:province":"Bern",
    "wof:name":"Bj\u00f6rn Hess Airbrushatelier",
    "wof:placetype":"venue"
},
  "geometry": {"coordinates":[7.6035861969,47.1296424866],"type":"Point"}
}