{
  "type": "Feature",
  "properties": {
    "iso:country":"CH",
    "sg:address":"Riedmattstrasse 10 6030 Ebikon. Postfach 349",
    "sg:city":"Ebikon",
    "sg:orig_category":"Wirtschaftspr\u00fcfung, Steuerberatung U Treuhand",
    "sg:phone":"+41 41 440 83 83",
    "sg:postcode":"6031",
    "sg:province":"Luzern",
    "wof:name":"Paul M\u00fcller Ag Treuhand Praxis",
    "wof:placetype":"venue"
},
  "geometry": {"coordinates":[8.3415565491,47.0829620361],"type":"Point"}
}