{
  "type": "Feature",
  "properties": {
    "iso:country":"CH",
    "sg:address":"Limmatplatz 2",
    "sg:city":"Z\u00fcrich",
    "sg:classifiers":[
        {
            "category":"Professional",
            "subcategory":"Employment Agencies",
            "type":"Services"
        }
    ],
    "sg:postcode":"8005",
    "sg:province":"Z\u00fcrich",
    "sg:tags":[
        "personal",
        "u",
        "stellenvermittlung"
    ],
    "wof:name":"Z - Akkord, Personalberatung, Schilling K., Zweigniederlassung St. Gallen",
    "wof:placetype":"venue"
},
  "geometry": {"coordinates":[9.3753356934,47.4239845276],"type":"Point"}
}