{
  "type": "Feature",
  "properties": {
    "iso:country":"CH",
    "sg:city":"Castasegna",
    "sg:classifiers":[
        {
            "category":"Banks & Credit Unions",
            "subcategory":"Bank",
            "type":"Services"
        }
    ],
    "sg:phone":"+41 41 824 14 88",
    "sg:postcode":"7608",
    "sg:province":"Graubunden",
    "wof:name":"Graub\u00fcndner, Kantonalbank",
    "wof:placetype":"venue"
},
  "geometry": {"coordinates":[9.516998,46.334145],"type":"Point"}
}