{
  "type": "Feature",
  "properties": {
    "iso:country":"CH",
    "sg:address":"Rue De La Fleur-de-lys 7",
    "sg:city":"Marin-epagnier",
    "sg:orig_category":"Sonstige Aktivit\u00e4ten der nicht-\u00e4rztlichen Medizinalberufe",
    "sg:phone":"+41 32 753 46 90",
    "sg:postcode":"2074",
    "sg:province":"Neuch\u00e2tel",
    "wof:name":"Yolande Vessaz Kin\u00e9siologie",
    "wof:placetype":"venue"
},
  "geometry": {"coordinates":[7.0021882057,47.0098190308],"type":"Point"}
}