{
  "type": "Feature",
  "properties": {
    "iso:country":"CH",
    "sg:address":"6943",
    "sg:city":"Vezia",
    "sg:orig_category":"Primarschulen",
    "sg:phone":"+41 91 943 33 73",
    "sg:postcode":"6943",
    "sg:province":"Ticino",
    "wof:name":"Scuola Elementare",
    "wof:placetype":"venue"
},
  "geometry": {"coordinates":[8.9356899261,46.0241584778],"type":"Point"}
}