{
  "type": "Feature",
  "properties": {
    "iso:country":"CH",
    "sg:address":"Merzenacker 65 3006 Bern. Postfach",
    "sg:city":"Bern",
    "sg:orig_category":"Fahrschulen, Flugschulen",
    "sg:postcode":"3005",
    "sg:province":"Bern",
    "wof:name":"Wings Gleitschirmschule Bern, E. Bischoff",
    "wof:placetype":"venue"
},
  "geometry": {"coordinates":[7.4820461273,46.944770813],"type":"Point"}
}