{
  "type": "Feature",
  "properties": {
    "addr:full":"Rouges-terres 2 Hauterive Neuch\u00e2tel 2068",
    "addr:housenumber":"2",
    "addr:postcode":"2068",
    "addr:street":"Rouges-Terres;Neucha\u0302Tel",
    "iso:country":"CH",
    "sg:address":"Rouges-terres 2",
    "sg:city":"Hauterive",
    "sg:orig_category":"Autotransporte M\u00f6bel Autotransporte international",
    "sg:phone":"+41 32 756 91 91",
    "sg:postcode":"2068",
    "sg:province":"Neuch\u00e2tel",
    "wof:name":"Von Bergen Sa Transports",
    "wof:placetype":"venue"
},
  "geometry": {"coordinates":[6.979548,47.013275],"type":"Point"}
}