{
  "type": "Feature",
  "properties": {
    "iso:country":"CH",
    "sg:address":"Seestrasse 3",
    "sg:city":"St\u00e4fa",
    "sg:orig_category":"Sonstige mit Sport verbundene T\u00e4tigkeiten",
    "sg:postcode":"8712",
    "sg:province":"Z\u00fcrich",
    "wof:name":"Prod Aqua Wadler Johann",
    "wof:placetype":"venue"
},
  "geometry": {"coordinates":[8.7141141891,47.2411613464],"type":"Point"}
}