{
  "type": "Feature",
  "properties": {
    "iso:country":"CH",
    "sg:address":"Sch\u00fctzengraben 36 4051 Basel. Postfach",
    "sg:city":"Basel",
    "sg:orig_category":"Elektroinstallation",
    "sg:phone":"+41 61 981 35 95",
    "sg:postcode":"4051",
    "sg:province":"Basel-Stadt",
    "wof:name":"Amberger + Nussbaumer Ag. Elektr. Installationen U. Apparatehandel.",
    "wof:placetype":"venue"
},
  "geometry": {"coordinates":[7.5825037956,47.5561752319],"type":"Point"}
}