{
  "type": "Feature",
  "properties": {
    "addr:full":"Dorfstr. 29 Etzgen Aargau 5275",
    "addr:housenumber":"29",
    "addr:postcode":"5275",
    "addr:street":"Dorfstr.",
    "iso:country":"CH",
    "sg:address":"Dorfstr. 29",
    "sg:city":"Etzgen",
    "sg:classifiers":[
        {
            "category":"Banks & Credit Unions",
            "subcategory":"Bank",
            "type":"Services"
        }
    ],
    "sg:phone":"+41 62 875 22 50",
    "sg:postcode":"5275",
    "sg:province":"Aargau",
    "wof:name":"Raiffeisenbank, Etzgen-mettau",
    "wof:placetype":"venue"
},
  "geometry": {"coordinates":[8.109967,47.571583],"type":"Point"}
}