{
  "type": "Feature",
  "properties": {
    "iso:country":"CH",
    "sg:address":"Haselstrasse 23",
    "sg:city":"Baden",
    "sg:orig_category":"Detailhandel mit Brot, Back U S\u00fcsswaren",
    "sg:phone":"+41 56 424 10 44",
    "sg:postcode":"5400",
    "sg:province":"Aargau",
    "wof:name":"Robert Arnet B\u00e4ckerei-konditorei",
    "wof:placetype":"venue"
},
  "geometry": {"coordinates":[8.305661,47.477711],"type":"Point"}
}