{
  "type": "Feature",
  "properties": {
    "iso:country":"CH",
    "sg:address":"Riehenstrasse 86",
    "sg:city":"Basel",
    "sg:orig_category":"Malerei Tapeziererei",
    "sg:phone":"+41 61 681 01 51",
    "sg:postcode":"4058",
    "sg:province":"Basel-Stadt",
    "wof:name":"Rolf Galli Maler-& Tapezierergesch\u00e4ft",
    "wof:placetype":"venue"
},
  "geometry": {"coordinates":[7.6023440361,47.5630111694],"type":"Point"}
}