{
  "type": "Feature",
  "properties": {
    "iso:country":"CH",
    "sg:address":"Bergstrasse 12",
    "sg:city":"Z\u00fcrich",
    "sg:orig_category":"Wirtschaftspr\u00fcfung, Steuerberatung U Treuhand",
    "sg:phone":"+41 12625656",
    "sg:postcode":"8044",
    "sg:province":"Z\u00fcrich",
    "wof:name":"Specker Treuhand + Immobilien",
    "wof:placetype":"venue"
},
  "geometry": {"coordinates":[8.5603618622,47.3750457764],"type":"Point"}
}