{
  "type": "Feature",
  "properties": {
    "iso:country":"CH",
    "sg:address":"Dietrichsguetstrasse 14",
    "sg:city":"Rheineck",
    "sg:orig_category":"Unclassifiable Establishments",
    "sg:phone":"+41 21 922 76 38",
    "sg:postcode":"9424",
    "sg:province":"St. Gallen",
    "wof:name":"Men\u00e9trey Sa",
    "wof:placetype":"venue"
},
  "geometry": {"coordinates":[5.1808700562,45.8973388672],"type":"Point"}
}