{
  "type": "Feature",
  "properties": {
    "iso:country":"CH",
    "sg:address":"Route De Corni\u00e8re 49",
    "sg:city":"Puplinge",
    "sg:orig_category":"Grosshandel mit Obst U Gem\u00fcse",
    "sg:phone":"+41 22 349 75 82",
    "sg:postcode":"1241",
    "sg:province":"Gen\u00e8ve",
    "wof:name":"G\u00e9rard Mossi\u00e8re Primeurs",
    "wof:placetype":"venue"
},
  "geometry": {"coordinates":[6.2341198921,46.2069015503],"type":"Point"}
}