{
  "type": "Feature",
  "properties": {
    "iso:country":"CH",
    "sg:address":"1908",
    "sg:city":"Riddes",
    "sg:classifiers":[
        {
            "category":"Restaurant",
            "type":"Food & Drink"
        }
    ],
    "sg:phone":"+41 27 306 25 44",
    "sg:postcode":"1908",
    "sg:province":"Valais",
    "wof:name":"Restaurant Val\u00e9sia",
    "wof:placetype":"venue"
},
  "geometry": {"coordinates":[7.2213292122,46.1717376709],"type":"Point"}
}