{
  "type": "Feature",
  "properties": {
    "iso:country":"CH",
    "sg:address":"G\u00fcterstrasse 8",
    "sg:city":"Bern",
    "sg:orig_category":"Detailhandel mit Radio U Fernsehger\u00e4ten",
    "sg:phone":"+41 31 381 50 55",
    "sg:postcode":"3008",
    "sg:province":"Bern",
    "wof:name":"J\u00fcrgen Strauss Elektroakustik",
    "wof:placetype":"venue"
},
  "geometry": {"coordinates":[7.4160680771,46.9481010437],"type":"Point"}
}