{
  "type": "Feature",
  "properties": {
    "iso:country":"CH",
    "sg:address":"Weinfelder Strasse 1",
    "sg:city":"Amriswil",
    "sg:orig_category":"Fachdetailhandel in Verkaufsr\u00e4umen Handel mit Motorr\u00e4dern, Teilen U Zubeh\u00f6r Instandhaltung U Reparat",
    "sg:phone":"+41 71 411 57 46",
    "sg:postcode":"8580",
    "sg:province":"Thurgau",
    "wof:name":"Satteld\u00e4sche Z\u00fcrcher Erika",
    "wof:placetype":"venue"
},
  "geometry": {"coordinates":[9.2985334396,47.5450057983],"type":"Point"}
}