{
  "type": "Feature",
  "properties": {
    "iso:country":"CH",
    "sg:address":"Paradiesstrasse 45",
    "sg:city":"Z\u00fcrich",
    "sg:orig_category":"Institutionen f\u00fcr Behinderte",
    "sg:phone":"+41 14873500",
    "sg:postcode":"8038",
    "sg:province":"Z\u00fcrich",
    "wof:name":"Krankenheim Entlisberg Abteilung F\u00fcr Chronischkranke",
    "wof:placetype":"venue"
},
  "geometry": {"coordinates":[8.5272035599,47.3348999023],"type":"Point"}
}