{
  "type": "Feature",
  "properties": {
    "iso:country":"CH",
    "sg:address":"Place Favez 1854 Leysin. Postfach",
    "sg:city":"Leysin",
    "sg:orig_category":"Fachdetailhandel in Verkaufsr\u00e4umen",
    "sg:postcode":"1854",
    "sg:province":"Vaud",
    "wof:name":"Vieceli Sports S\u00e0rl Magasin De Sports",
    "wof:placetype":"venue"
},
  "geometry": {"coordinates":[7.0116510391,46.3424377441],"type":"Point"}
}