{
  "type": "Feature",
  "properties": {
    "iso:country":"CH",
    "sg:address":"Frutigenstrasse 6",
    "sg:city":"Thun",
    "sg:classifiers":[
        {
            "category":"Education",
            "subcategory":"Library",
            "type":"Public Place"
        }
    ],
    "sg:phone":"+41 33 225 60 60",
    "sg:postcode":"3600",
    "sg:province":"Bern",
    "sg:tags":[
        "dictionary"
    ],
    "wof:name":"Duboux Editions Sa",
    "wof:placetype":"venue"
},
  "geometry": {"coordinates":[7.6290869713,46.7561340332],"type":"Point"}
}