{
  "type": "Feature",
  "properties": {
    "iso:country":"CH",
    "sg:address":"Blidegg Degenau",
    "sg:city":"Bischofszell",
    "sg:orig_category":"Allgemeiner Hoch U Tiefbau Mechanische Werkst\u00e4tten",
    "sg:phone":"+41 71 433 14 22",
    "sg:postcode":"9220",
    "sg:province":"Thurgau",
    "wof:name":"E. B\u00fcrgi + S\u00f6hne Ag",
    "wof:placetype":"venue"
},
  "geometry": {"coordinates":[9.240825,47.494225],"type":"Point"}
}