{
  "type": "Feature",
  "properties": {
    "iso:country":"CH",
    "sg:address":"Sentiero Chiosso Del Conte 8",
    "sg:city":"Ascona",
    "sg:orig_category":"Sanit\u00e4rinstallation",
    "sg:phone":"+41 91 791 75 89",
    "sg:postcode":"6612",
    "sg:province":"Ticino",
    "wof:name":"Vincenzo Campagnuolo Impianti Sanitari",
    "wof:placetype":"venue"
},
  "geometry": {"coordinates":[8.7759714127,46.1597213745],"type":"Point"}
}