{
  "type": "Feature",
  "properties": {
    "addr:full":"Rue Du Rh\u00f4ne 1 Martigny Valais 1920",
    "addr:housenumber":"1",
    "addr:postcode":"1920",
    "addr:street":"Rue Du Rho\u0302Ne",
    "iso:country":"CH",
    "sg:address":"Rue Du Rh\u00f4ne 1",
    "sg:city":"Martigny",
    "sg:orig_category":"Architekturb\u00fcros",
    "sg:phone":"+41 27 722 73 92",
    "sg:postcode":"1920",
    "sg:province":"Valais",
    "wof:name":"Jean-charles Roux Bureau D'architecture",
    "wof:placetype":"venue"
},
  "geometry": {"coordinates":[7.073267,46.10247],"type":"Point"}
}