{
  "type": "Feature",
  "properties": {
    "iso:country":"CH",
    "sg:address":"Rotfluhstrasse 52",
    "sg:city":"Zollikon",
    "sg:orig_category":"Herstellung von k\u00e4lte U lufttechnischen Erzeugnissen f\u00fcr gewerbliche Zwecke",
    "sg:postcode":"8702",
    "sg:province":"Z\u00fcrich",
    "wof:name":"Helfenberger Bruni, Verkauf Und Beratungen",
    "wof:placetype":"venue"
},
  "geometry": {"coordinates":[8.5768203735,47.3435096741],"type":"Point"}
}