{
  "type": "Feature",
  "properties": {
    "iso:country":"CH",
    "sg:address":"Oberer Badweg 25 5722 Gr\u00e4nichen. Postfach",
    "sg:city":"Gr\u00e4nichen",
    "sg:orig_category":"Wirtschaftspr\u00fcfung, Steuerberatung U Treuhand",
    "sg:postcode":"5722",
    "sg:province":"Aargau",
    "wof:name":"Constance Grimaud Sa",
    "wof:placetype":"venue"
},
  "geometry": {"coordinates":[8.7837238312,46.1734466553],"type":"Point"}
}