{
  "type": "Feature",
  "properties": {
    "iso:country":"CH",
    "sg:address":"Route Du Vignoble 1 2017 Boudry Case Postale 132",
    "sg:city":"Boudry",
    "sg:orig_category":"Druck ohne Zeitungsdruck Verlagsgewerbe",
    "sg:phone":"+41 32 842 10 32",
    "sg:postcode":"2017",
    "sg:province":"Neuch\u00e2tel",
    "wof:name":"Imprimerie Baillod Sa",
    "wof:placetype":"venue"
},
  "geometry": {"coordinates":[6.8434958458,46.9529647827],"type":"Point"}
}