{
  "type": "Feature",
  "properties": {
    "iso:country":"CH",
    "sg:address":"Sattelstrasse 4",
    "sg:city":"Steinerberg",
    "sg:classifiers":[
        {
            "category":"Travel",
            "subcategory":"Hotels & Motels",
            "type":"Entertainment"
        }
    ],
    "sg:phone":"+41 41 832 13 33",
    "sg:postcode":"6416",
    "sg:province":"Schwyz",
    "sg:tags":[
        "hotels",
        "mit",
        "restaurant"
    ],
    "wof:name":"Hotel L\u00f6wen",
    "wof:placetype":"venue"
},
  "geometry": {"coordinates":[8.5840816498,47.0528831482],"type":"Point"}
}