{
  "type": "Feature",
  "properties": {
    "iso:country":"CH",
    "sg:address":"Sch\u00fctzenhausstrasse 32",
    "sg:city":"Glarus",
    "sg:orig_category":"Herstellung von Teppichen",
    "sg:postcode":"8750",
    "sg:province":"Glarus",
    "wof:name":"Z\u00fcnd Hanspeter",
    "wof:placetype":"venue"
},
  "geometry": {"coordinates":[8.721414566,47.4147109985],"type":"Point"}
}