{
  "type": "Feature",
  "properties": {
    "iso:country":"CH",
    "sg:address":"Steinb\u00fchlweg 21",
    "sg:city":"Allschwil",
    "sg:orig_category":"Softwareentwicklung U beratung",
    "sg:postcode":"4123",
    "sg:province":"Basel-Landschaft",
    "wof:name":"Bly-fry Design Gmbh",
    "wof:placetype":"venue"
},
  "geometry": {"coordinates":[7.5507779121,47.5508460999],"type":"Point"}
}