{
  "type": "Feature",
  "properties": {
    "addr:full":"Via Mondari 15 Giubiasco Ticino 6512",
    "addr:housenumber":"15",
    "addr:postcode":"6512",
    "addr:street":"Via Mondari",
    "iso:country":"CH",
    "sg:address":"Via Mondari 15",
    "sg:city":"Giubiasco",
    "sg:orig_category":"Bauschreinerei Herstellung von M\u00f6beln verschiedener Art",
    "sg:phone":"+41 91 857 18 79",
    "sg:postcode":"6512",
    "sg:province":"Ticino",
    "wof:name":"Santini & Delbiaggio Sa",
    "wof:placetype":"venue"
},
  "geometry": {"coordinates":[8.993165,46.168797],"type":"Point"}
}