{
  "type": "Feature",
  "properties": {
    "iso:country":"CH",
    "sg:address":"8478",
    "sg:city":"Thalheim",
    "sg:orig_category":"Gemeindeverwaltungen",
    "sg:phone":"+41 56 443 12 84",
    "sg:postcode":"8478",
    "sg:province":"Z\u00fcrich",
    "wof:name":"Gemeindeverwaltung Thalheim",
    "wof:placetype":"venue"
},
  "geometry": {"coordinates":[8.1004190445,47.4358062744],"type":"Point"}
}