{
  "type": "Feature",
  "properties": {
    "iso:country":"CH",
    "sg:address":"Ipsachstrasse 16",
    "sg:city":"Ipsach",
    "sg:orig_category":"Non-Classified Establishments",
    "sg:phone":"+41 32 333 13 51",
    "sg:postcode":"2563",
    "sg:province":"Bern",
    "wof:name":"Gn\u00e4gi Christian",
    "wof:placetype":"venue"
},
  "geometry": {"coordinates":[7.23726511,47.1170387268],"type":"Point"}
}