{
  "type": "Feature",
  "properties": {
    "iso:country":"CH",
    "sg:address":"4303",
    "sg:city":"Kaiseraugst",
    "sg:orig_category":"Primarschulen",
    "sg:postcode":"4303",
    "sg:province":"Aargau",
    "wof:name":"Primarschule Liebr\u00fcti",
    "wof:placetype":"venue"
},
  "geometry": {"coordinates":[7.7361001968,47.5354118347],"type":"Point"}
}