{
  "type": "Feature",
  "properties": {
    "addr:full":"Grand-rue 19 Tavannes Bern 2710",
    "addr:housenumber":"19",
    "addr:postcode":"2710",
    "addr:street":"Grand-Rue",
    "iso:country":"CH",
    "sg:address":"Grand-rue 19",
    "sg:city":"Tavannes",
    "sg:classifiers":[
        {
            "category":"Education",
            "subcategory":"Library",
            "type":"Public Place"
        }
    ],
    "sg:phone":"+41 32 481 47 53",
    "sg:postcode":"2710",
    "sg:province":"Bern",
    "sg:tags":[
        "u",
        "bibliotheken",
        "archive"
    ],
    "wof:name":"Biblioth\u00e8que Des Jeunes",
    "wof:placetype":"venue"
},
  "geometry": {"coordinates":[7.200825,47.220821],"type":"Point"}
}