{
  "type": "Feature",
  "properties": {
    "iso:country":"CH",
    "sg:address":"Steinlerstrasse 30",
    "sg:city":"W\u00e4ngi",
    "sg:orig_category":"Werbevermittlung Werbung",
    "sg:phone":"+41 52 378 16 16",
    "sg:postcode":"9545",
    "sg:province":"Thurgau",
    "wof:name":"Werbeagentur Hug-sutz Ag",
    "wof:placetype":"venue"
},
  "geometry": {"coordinates":[8.9603633881,47.4977340698],"type":"Point"}
}