{
  "type": "Feature",
  "properties": {
    "iso:country":"CH",
    "sg:address":"Stampfeweg 1",
    "sg:city":"Oensingen",
    "sg:orig_category":"Handel mit Motorr\u00e4dern, Teilen U Zubeh\u00f6r Instandhaltung U Reparatur von Motorr\u00e4dern",
    "sg:phone":"+41 62 396 01 64",
    "sg:postcode":"4702",
    "sg:province":"Solothurn",
    "wof:name":"Moto Monobike Extrem Uebelhart",
    "wof:placetype":"venue"
},
  "geometry": {"coordinates":[7.7070808411,47.2859268188],"type":"Point"}
}