{
  "type": "Feature",
  "properties": {
    "addr:full":"Rugenaustrasse 3 Interlaken Bern 3800",
    "addr:housenumber":"3",
    "addr:postcode":"3800",
    "addr:street":"Rugenaustrasse",
    "iso:country":"CH",
    "sg:address":"Rugenaustrasse 3",
    "sg:city":"Interlaken",
    "sg:orig_category":"Allgemeiner Hoch U Tiefbau Strassenbau",
    "sg:phone":"+41 21 625 54 43",
    "sg:postcode":"3800",
    "sg:province":"Bern",
    "wof:name":"Frosio Roger Sa Succursale De Renens",
    "wof:placetype":"venue"
},
  "geometry": {"coordinates":[6.5977,46.526367],"type":"Point"}
}