{
  "type": "Feature",
  "properties": {
    "iso:country":"CH",
    "sg:address":"Landstrasse 115",
    "sg:city":"Wettingen",
    "sg:orig_category":"Arztpraxen",
    "sg:phone":"+41 56 427 05 27",
    "sg:postcode":"5430",
    "sg:province":"Aargau",
    "wof:name":"Dr.med.thomas M\u00fcller Spezialarzt Fmh",
    "wof:placetype":"venue"
},
  "geometry": {"coordinates":[8.329436,47.464771],"type":"Point"}
}