{
  "type": "Feature",
  "properties": {
    "iso:country":"CH",
    "sg:address":"3823",
    "sg:city":"Wengen",
    "sg:orig_category":"Personenbef\u00f6rderung im Linienverkehr zu Land",
    "sg:postcode":"3823",
    "sg:province":"Bern",
    "wof:name":"Luftseilbahn-genossenschaft Schattdorf-haldi",
    "wof:placetype":"venue"
},
  "geometry": {"coordinates":[8.65513134,46.8651542664],"type":"Point"}
}