{
  "type": "Feature",
  "properties": {
    "addr:full":"Aumatt 6 Flamatt Fribourg 3175",
    "addr:housenumber":"6",
    "addr:postcode":"3175",
    "addr:street":"Aumatt",
    "iso:country":"CH",
    "sg:address":"Aumatt 6",
    "sg:city":"Flamatt",
    "sg:orig_category":"Arztpraxen",
    "sg:phone":"+41 31 741 17 07",
    "sg:postcode":"3175",
    "sg:province":"Fribourg",
    "wof:name":"Dr.med.laurence Meer Aerztin F.allgemeine Medizin",
    "wof:placetype":"venue"
},
  "geometry": {"coordinates":[7.317999,46.890656],"type":"Point"}
}