{
  "type": "Feature",
  "properties": {
    "iso:country":"CH",
    "sg:address":"Clarastrasse 2 4058 Basel. Postfach 220",
    "sg:city":"Basel",
    "sg:orig_category":"Grosshandel mit sonstigen Halbwaren",
    "sg:phone":"+41 61 690 99 55",
    "sg:postcode":"4005",
    "sg:province":"Basel-Stadt",
    "wof:name":"Interel Ag Handels- U. Finanzgesch\u00e4fte. Immobiliengesch\u00e4fte Usw",
    "wof:placetype":"venue"
},
  "geometry": {"coordinates":[7.5948848724,47.5619506836],"type":"Point"}
}