{
  "type": "Feature",
  "properties": {
    "iso:country":"CH",
    "sg:address":"Baslerstrasse 19",
    "sg:city":"Bottmingen",
    "sg:orig_category":"RESTAURANTS: TEA-ROOMS",
    "sg:phone":"+41 61 421 11 68",
    "sg:postcode":"4103",
    "sg:province":"Basel-Landschaft",
    "wof:name":"Restaurant Sch\u00fctzen, Iris Hauri",
    "wof:placetype":"venue"
},
  "geometry": {"coordinates":[7.5722317696,47.5250701904],"type":"Point"}
}