{
  "type": "Feature",
  "properties": {
    "iso:country":"CH",
    "sg:address":"Aarbergstrasse 121a",
    "sg:city":"Biel/bienne",
    "sg:orig_category":"Einrahmungen Kunsthandel",
    "sg:postcode":"2502",
    "sg:province":"Bern",
    "wof:name":"Galleria Moderne Einrahmungen",
    "wof:placetype":"venue"
},
  "geometry": {"coordinates":[7.2426071167,47.1345062256],"type":"Point"}
}