{
  "type": "Feature",
  "properties": {
    "iso:country":"CH",
    "sg:address":"Hubstrasse 3",
    "sg:city":"Neftenbach",
    "sg:orig_category":"Allgemeiner Hochbau",
    "sg:phone":"+41 52 315 21 11",
    "sg:postcode":"8413",
    "sg:province":"Z\u00fcrich",
    "wof:name":"Kurz Renovations Ag",
    "wof:placetype":"venue"
},
  "geometry": {"coordinates":[8.637521,47.5299],"type":"Point"}
}