{
  "type": "Feature",
  "properties": {
    "iso:country":"CH",
    "sg:address":"Wehriwald 6",
    "sg:city":"Muotathal",
    "sg:orig_category":"Forstwirtschaft ohne Dienstleistungen in der Forstwirtschaft",
    "sg:phone":"+41 41 830 22 69",
    "sg:postcode":"6436",
    "sg:province":"Schwyz",
    "wof:name":"Eichhorn Thyl, Forstunternehmung",
    "wof:placetype":"venue"
},
  "geometry": {"coordinates":[8.7668104172,46.9731292725],"type":"Point"}
}