{
  "type": "Feature",
  "properties": {
    "iso:country":"CH",
    "sg:address":"Waffenplatzstrasse 70",
    "sg:city":"Z\u00fcrich",
    "sg:orig_category":"Architektur U Ingenieurb\u00fcros",
    "sg:phone":"+41 12026304",
    "sg:postcode":"8002",
    "sg:province":"Z\u00fcrich",
    "wof:name":"Vision Inspiration Produktion, F\u00fcllemann Martin",
    "wof:placetype":"venue"
},
  "geometry": {"coordinates":[8.526875,47.356976],"type":"Point"}
}