{
  "type": "Feature",
  "properties": {
    "iso:country":"CH",
    "sg:address":"Hertistrasse 51 5704 Egliswil. Postfach",
    "sg:city":"Egliswil",
    "sg:orig_category":"Maschinen-Fabrikation",
    "sg:postcode":"5704",
    "sg:province":"Aargau",
    "wof:name":"Serimin S\u00e0rl",
    "wof:placetype":"venue"
},
  "geometry": {"coordinates":[7.0994272232,47.0684127808],"type":"Point"}
}