{
  "type": "Feature",
  "properties": {
    "iso:country":"CH",
    "sg:address":"Madeleine Rue De La 13",
    "sg:city":"Gen\u00e8ve",
    "sg:orig_category":"Unclassifiable Establishments",
    "sg:postcode":"1204",
    "sg:province":"Gen\u00e8ve",
    "wof:name":"Kacem Noreddine",
    "wof:placetype":"venue"
},
  "geometry": {"coordinates":[6.1487398148,46.2023391724],"type":"Point"}
}