{
  "type": "Feature",
  "properties": {
    "iso:country":"CH",
    "sg:address":"Vormholz",
    "sg:city":"Grossaffoltern",
    "sg:orig_category":"Wohnheime",
    "sg:postcode":"3257",
    "sg:province":"Bern",
    "wof:name":"Genossenschaft Zur F\u00f6rderung Einer P\u00e4dagogischen Hofgemeinschaft",
    "wof:placetype":"venue"
},
  "geometry": {"coordinates":[7.3613591194,47.0663986206],"type":"Point"}
}