{
  "type": "Feature",
  "properties": {
    "iso:country":"CH",
    "sg:address":"Route De Malagny 36 1294 Creux-de-genthod Case Postale 40",
    "sg:city":"Creux-de-genthod",
    "sg:orig_category":"Interessenvertretungen Primarschulen",
    "sg:phone":"+41 71 923 19 64",
    "sg:postcode":"1294",
    "sg:province":"Gen\u00e8ve",
    "wof:name":"Schulreise-stiftung Der Primarschule B\u00fcrglen.",
    "wof:placetype":"venue"
},
  "geometry": {"coordinates":[9.0140800476,47.4496917725],"type":"Point"}
}