{
  "type": "Feature",
  "properties": {
    "iso:country":"CH",
    "sg:address":"Coulouvreni\u00e8re Rue De La 29 1204 Gen\u00e8ve. Postfach",
    "sg:city":"Gen\u00e8ve",
    "sg:orig_category":"Finanzierungsinstitutionen",
    "sg:postcode":"1204",
    "sg:province":"Gen\u00e8ve",
    "wof:name":"Kama Capital Ag",
    "wof:placetype":"venue"
},
  "geometry": {"coordinates":[8.7341480255,47.1973953247],"type":"Point"}
}