{
  "type": "Feature",
  "properties": {
    "iso:country":"CH",
    "sg:address":"Schlossstrasse 67 8200 Schaffhausen. Postfach 1070",
    "sg:city":"Schaffhausen",
    "sg:orig_category":"Detailhandel mit M\u00f6beln U Haushaltsgegenst\u00e4nden",
    "sg:phone":"+41 71 222 92 42",
    "sg:postcode":"8207",
    "sg:province":"Schaffhausen",
    "wof:name":"Koch Fabian M\u00f6bel- U. Innenausbau; Handel M. Kunstgewerbl. Artikeln.",
    "wof:placetype":"venue"
},
  "geometry": {"coordinates":[9.3883829117,47.4149398804],"type":"Point"}
}