{
  "type": "Feature",
  "properties": {
    "iso:country":"CH",
    "sg:address":"Neumatt 507",
    "sg:city":"Kleinl\u00fctzel",
    "sg:orig_category":"Sportvereine Turnen Vereine Damen",
    "sg:postcode":"4245",
    "sg:province":"Solothurn",
    "wof:name":"Damenriege Stv Kleinl\u00fctzel",
    "wof:placetype":"venue"
},
  "geometry": {"coordinates":[7.4056510925,47.4267807007],"type":"Point"}
}