{
  "type": "Feature",
  "properties": {
    "iso:country":"CH",
    "sg:address":"Schwellm\u00fchlestrasse 2",
    "sg:city":"Oberegg",
    "sg:orig_category":"S\u00e4gewerke Zimmerei, Dachdeckerei, Bauspenglerei U Abdichtung",
    "sg:phone":"+41 79 404 40 02",
    "sg:postcode":"9413",
    "sg:province":"Appenzell Innerhoden",
    "wof:name":"Breu Holzbau Ag Oberegg",
    "wof:placetype":"venue"
},
  "geometry": {"coordinates":[9.5549297333,47.4220619202],"type":"Point"}
}