{
  "type": "Feature",
  "properties": {
    "iso:country":"CH",
    "sg:address":"Weieracherstrasse 9 8184 Bachenb\u00fclach. Postfach 58",
    "sg:city":"Bachenb\u00fclach",
    "sg:orig_category":"Grosshandel mit M\u00f6beln, Wohnbedarf, Teppichen U Bodenbel\u00e4gen Herstellung von Arbeits U Berufsbekleid",
    "sg:phone":"+41 18727666",
    "sg:postcode":"8184",
    "sg:province":"Z\u00fcrich",
    "wof:name":"Nydegger Ag Teppichuterlagen, Schmutzschleusen, Bodenschutzmatten",
    "wof:placetype":"venue"
},
  "geometry": {"coordinates":[8.5377016068,47.5044174194],"type":"Point"}
}