{
  "type": "Feature",
  "properties": {
    "iso:country":"CH",
    "sg:address":"Chemin Dottrens 36",
    "sg:city":"Troinex",
    "sg:orig_category":"P\u00e9dicure",
    "sg:phone":"+41 21 691 93 08",
    "sg:postcode":"1256",
    "sg:province":"Gen\u00e8ve",
    "wof:name":"B\u00e9atrice Pittet P\u00e9dicure",
    "wof:placetype":"venue"
},
  "geometry": {"coordinates":[6.561442852,46.5212974548],"type":"Point"}
}