{
  "type": "Feature",
  "properties": {
    "iso:country":"CH",
    "sg:address":"Rosenauweg 29",
    "sg:city":"Wettingen",
    "sg:orig_category":"Vorschulen, Kinderg\u00e4rten",
    "sg:phone":"+41 41 870 60 66",
    "sg:postcode":"5430",
    "sg:province":"Aargau",
    "wof:name":"Kindergarten Rosenberg",
    "wof:placetype":"venue"
},
  "geometry": {"coordinates":[8.639749527,46.8880310059],"type":"Point"}
}