{
  "type": "Feature",
  "properties": {
    "iso:country":"CH",
    "sg:address":"Zollstrasse 16 9494 Schaan. Postfach 661",
    "sg:city":"Schaan",
    "sg:orig_category":"Werbevermittlung",
    "sg:phone":"+423 232 00 32",
    "sg:postcode":"9494",
    "wof:name":"Publicitas Ag",
    "wof:placetype":"venue"
},
  "geometry": {"coordinates":[9.5049905777,47.1680755615],"type":"Point"}
}