{
  "type": "Feature",
  "properties": {
    "iso:country":"CH",
    "sg:address":"Jurastrasse 48 2500 Biel/bienne. Postfach",
    "sg:city":"Biel/bienne",
    "sg:orig_category":"Unclassifiable Establishments",
    "sg:phone":"+41 32 323 09 34",
    "sg:postcode":"2502",
    "sg:province":"Bern",
    "wof:name":"Schlechten J\u00fcrg",
    "wof:placetype":"venue"
},
  "geometry": {"coordinates":[7.2530012131,47.1389007568],"type":"Point"}
}