{
  "type": "Feature",
  "properties": {
    "iso:country":"CH",
    "sg:address":"H\u00f6fliweg 8",
    "sg:city":"Z\u00fcrich",
    "sg:orig_category":"Non-Classified Establishments",
    "sg:postcode":"8055",
    "sg:province":"Z\u00fcrich",
    "wof:name":"Dedic",
    "wof:placetype":"venue"
},
  "geometry": {"coordinates":[8.5104875565,47.3683433533],"type":"Point"}
}