{
  "type": "Feature",
  "properties": {
    "iso:country":"CH",
    "sg:address":"B\u00fcrgliweg 15c",
    "sg:city":"Richterswil",
    "sg:orig_category":"Unclassifiable Establishments",
    "sg:postcode":"8805",
    "sg:province":"Z\u00fcrich",
    "wof:name":"Alc Relations, Angela Von Lerber",
    "wof:placetype":"venue"
},
  "geometry": {"coordinates":[8.7005710602,47.2094764709],"type":"Point"}
}