{
  "type": "Feature",
  "properties": {
    "iso:country":"CH",
    "sg:address":"Marguerite-weidauer-weg 9 2500 Biel/bienne. Postfach",
    "sg:city":"Biel/bienne",
    "sg:orig_category":"Unternehmensberatung",
    "sg:postcode":"2505",
    "sg:province":"Bern",
    "wof:name":"Riedwyl Hans J\u00f6rg",
    "wof:placetype":"venue"
},
  "geometry": {"coordinates":[7.2671480179,47.1310577393],"type":"Point"}
}