{
  "type": "Feature",
  "properties": {
    "iso:country":"CH",
    "sg:address":"Br\u00fcnismatt 1",
    "sg:city":"Meierskappel",
    "sg:orig_category":"Grosshandel mit sonstigen Maschinen U Ausr\u00fcstungen f\u00fcr Industrie, Handel U Schiffahrt Handelsvermitt",
    "sg:phone":"+41 41 790 44 30",
    "sg:postcode":"6344",
    "sg:province":"Luzern",
    "wof:name":"Markus Ribary Auto- & Industriebedarf",
    "wof:placetype":"venue"
},
  "geometry": {"coordinates":[8.4473848343,47.1248474121],"type":"Point"}
}