{
  "type": "Feature",
  "properties": {
    "iso:country":"CH",
    "sg:address":"Mangelegg 98",
    "sg:city":"Schwyz",
    "sg:orig_category":"Non-Classified Establishments",
    "sg:postcode":"6430",
    "sg:province":"Schwyz",
    "wof:name":"Eu Zweitausend 2000 Ag",
    "wof:placetype":"venue"
},
  "geometry": {"coordinates":[8.6563253403,47.0289993286],"type":"Point"}
}