{
  "type": "Feature",
  "properties": {
    "iso:country":"CH",
    "sg:address":"Kirchstrasse 3",
    "sg:city":"Kappelen",
    "sg:orig_category":"Detailhandel mit Getr\u00e4nken Detailhandel mit Waren verschiedener Art, Hauptrichtung Nahrungsmittel",
    "sg:phone":"+41 55 440 12 39",
    "sg:postcode":"3273",
    "sg:province":"Bern",
    "wof:name":"Hilda Bamert Lebensmittel Weine",
    "wof:placetype":"venue"
},
  "geometry": {"coordinates":[8.8936452866,47.1917877197],"type":"Point"}
}