{
  "type": "Feature",
  "properties": {
    "iso:country":"CH",
    "sg:address":"G\u00fcterstrasse 8",
    "sg:city":"Frenkendorf",
    "sg:orig_category":"Herstellung von Kakao U Schokoladeerzeugnissen Herstellung von Kakao, Schokoladeerzeugnissen U Zucke",
    "sg:phone":"+41 61 901 62 63",
    "sg:postcode":"4402",
    "sg:province":"Basel-Landschaft",
    "wof:name":"Sch\u00f6nenberger Schokoladenspezialit\u00e4ten Ag",
    "wof:placetype":"venue"
},
  "geometry": {"coordinates":[7.7196369171,47.5005683899],"type":"Point"}
}