{
  "type": "Feature",
  "properties": {
    "iso:country":"CH",
    "sg:address":"Weinbergstrasse 116",
    "sg:city":"Z\u00fcrich",
    "sg:orig_category":"G\u00fcterbef\u00f6rderung im Strassenverkehr",
    "sg:phone":"+41 18102606",
    "sg:postcode":"8006",
    "sg:province":"Z\u00fcrich",
    "wof:name":"Crossborders Ag",
    "wof:placetype":"venue"
},
  "geometry": {"coordinates":[8.5418615341,47.3865013123],"type":"Point"}
}