{
  "type": "Feature",
  "properties": {
    "iso:country":"CH",
    "sg:address":"Ambar 3 6275 Ballwil. Postfach 103",
    "sg:city":"Ballwil",
    "sg:orig_category":"Bauschreinerei M\u00f6belschreinerei",
    "sg:phone":"+41 41 448 10 84",
    "sg:postcode":"6275",
    "sg:province":"Luzern",
    "wof:name":"Bruno Manzocchi Bau-& M\u00f6belschreinerei",
    "wof:placetype":"venue"
},
  "geometry": {"coordinates":[8.323459,47.153389],"type":"Point"}
}