{
  "type": "Feature",
  "properties": {
    "iso:country":"CH",
    "sg:address":"M\u00f6slistrasse 10",
    "sg:city":"Feldbrunnen",
    "sg:classifiers":[
        {
            "category":"Shopping",
            "subcategory":"Books",
            "type":"Retail Goods"
        }
    ],
    "sg:phone":"+41 32 623 44 55",
    "sg:postcode":"4532",
    "sg:province":"Solothurn",
    "sg:tags":[
        "text",
        "school",
        "books",
        "material",
        "learning"
    ],
    "wof:name":"Hlv Heilp\u00e4dagogischer Lehrmittelverlag Ag",
    "wof:placetype":"venue"
},
  "geometry": {"coordinates":[7.5539488792,47.2200393677],"type":"Point"}
}