{
  "type": "Feature",
  "properties": {
    "iso:country":"CH",
    "sg:address":"Birmensdorferstrasse 427",
    "sg:city":"Z\u00fcrich",
    "sg:classifiers":[
        {
            "category":"Restaurant",
            "type":"Food & Drink"
        }
    ],
    "sg:phone":"+41 19501416",
    "sg:postcode":"8055",
    "sg:province":"Z\u00fcrich",
    "wof:name":"Restaurant Z. Brauerei",
    "wof:placetype":"venue"
},
  "geometry": {"coordinates":[8.7816200256,47.3658638],"type":"Point"}
}