{
  "type": "Feature",
  "properties": {
    "iso:country":"CH",
    "sg:address":"Ziegelstrasse 9",
    "sg:city":"Z\u00fcrich",
    "sg:orig_category":"Sonstiger Grosshandel",
    "sg:phone":"+41 14813182",
    "sg:postcode":"8038",
    "sg:province":"Z\u00fcrich",
    "wof:name":"Rofrima Ag",
    "wof:placetype":"venue"
},
  "geometry": {"coordinates":[8.5291175842,47.3406562805],"type":"Point"}
}