{
  "type": "Feature",
  "properties": {
    "iso:country":"CH",
    "sg:address":"Via Collegio 6",
    "sg:city":"Ascona",
    "sg:orig_category":"Detailhandel mit Spielwaren",
    "sg:phone":"+41 91 791 34 35",
    "sg:postcode":"6612",
    "sg:province":"Ticino",
    "wof:name":"Andrea Fl\u00fctsch Giocattoli L'agnellino",
    "wof:placetype":"venue"
},
  "geometry": {"coordinates":[8.7707929611,46.1556930542],"type":"Point"}
}