{
  "type": "Feature",
  "properties": {
    "iso:country":"CH",
    "sg:address":"3911",
    "sg:city":"Ried-brig",
    "sg:orig_category":"Sanit\u00e4r, Heizungs U L\u00fcftungsinstallation",
    "sg:phone":"+41 27 923 42 44",
    "sg:postcode":"3911",
    "sg:province":"Valais",
    "wof:name":"Arnold, Anton",
    "wof:placetype":"venue"
},
  "geometry": {"coordinates":[8.0152349472,46.3151245117],"type":"Point"}
}