{
  "type": "Feature",
  "properties": {
    "iso:country":"CH",
    "sg:address":"Atlantis Center",
    "sg:city":"Vuadens",
    "sg:orig_category":"Herstellung von sonstigen Metallwaren Siebdruck",
    "sg:phone":"+41 32 968 02 02",
    "sg:postcode":"1628",
    "sg:province":"Fribourg",
    "wof:name":"Megapub Pesse & Cie",
    "wof:placetype":"venue"
},
  "geometry": {"coordinates":[6.8369669914,47.103767395],"type":"Point"}
}