{
  "type": "Feature",
  "properties": {
    "iso:country":"CH",
    "sg:address":"Wengistrasse 12",
    "sg:city":"Solothurn",
    "sg:orig_category":"Zahnarztpraxen",
    "sg:phone":"+41 32 622 58 40",
    "sg:postcode":"4500",
    "sg:province":"Solothurn",
    "wof:name":"Dr. Med. Dent. Jvan Fr\u00f6hlicher Zahnarzt",
    "wof:placetype":"venue"
},
  "geometry": {"coordinates":[7.5337128639,47.2069549561],"type":"Point"}
}