{
  "type": "Feature",
  "properties": {
    "iso:country":"CH",
    "sg:address":"Nelkenweg 21",
    "sg:city":"Lyss",
    "sg:orig_category":"Detailhandel mit B\u00fcchern, Zeitungen, Schreib U Papeteriewaren",
    "sg:phone":"+41 32 373 72 45",
    "sg:postcode":"3250",
    "sg:province":"Bern",
    "wof:name":"Siegenthaler Fritz E.",
    "wof:placetype":"venue"
},
  "geometry": {"coordinates":[7.304695,47.070271],"type":"Point"}
}