{
  "type": "Feature",
  "properties": {
    "iso:country":"CH",
    "sg:address":"Bremgarterstrasse 37",
    "sg:city":"Widen",
    "sg:orig_category":"Herstellung von Elektrizit\u00e4tsverteilungs U schalteinrichtungen Unternehmensberatung",
    "sg:phone":"+41 55 240 58 64",
    "sg:postcode":"8967",
    "sg:province":"Aargau",
    "wof:name":"Oeko Control Von Ow",
    "wof:placetype":"venue"
},
  "geometry": {"coordinates":[8.3601255417,47.3660087585],"type":"Point"}
}