{
  "type": "Feature",
  "properties": {
    "addr:full":"Place De La Riponne 5 Lausanne Vaud 1005",
    "addr:housenumber":"5",
    "addr:postcode":"1005",
    "addr:street":"Place De La Riponne",
    "iso:country":"CH",
    "sg:address":"Place De La Riponne 5",
    "sg:city":"Lausanne",
    "sg:orig_category":"Arztpraxen",
    "sg:phone":"+41 21 944 15 55",
    "sg:postcode":"1005",
    "sg:province":"Vaud",
    "wof:name":"Dr M\u00e9d. Pierre M\u00e9an M\u00e9decin Sp\u00e9cialiste Fmh",
    "wof:placetype":"venue"
},
  "geometry": {"coordinates":[6.86676,46.460106],"type":"Point"}
}