{
  "type": "Feature",
  "properties": {
    "iso:country":"CH",
    "sg:address":"Ringstrasse 14",
    "sg:city":"Chur",
    "sg:orig_category":"Zimmerei, Dachdeckerei, Bauspenglerei U Abdichtung",
    "sg:phone":"+41 32 841 24 26",
    "sg:postcode":"7000",
    "sg:province":"Graubunden",
    "wof:name":"Mentha Jean-paul",
    "wof:placetype":"venue"
},
  "geometry": {"coordinates":[6.857986927,46.9656143188],"type":"Point"}
}