{
  "type": "Feature",
  "properties": {
    "iso:country":"CH",
    "sg:address":"Bahnhofplatz 7",
    "sg:city":"Visp",
    "sg:orig_category":"Vermittlung von Immobilien Wirtschaftspr\u00fcfung, Steuerberatung U Treuhand",
    "sg:phone":"+41 55 442 40 44",
    "sg:postcode":"3930",
    "sg:province":"Valais",
    "wof:name":"Betschart Walter Ag",
    "wof:placetype":"venue"
},
  "geometry": {"coordinates":[8.8553752899,47.1940612793],"type":"Point"}
}