{
  "type": "Feature",
  "properties": {
    "iso:country":"CH",
    "sg:address":"Le Cr\u00eat",
    "sg:city":"Bavois",
    "sg:orig_category":"Sonstiger Grosshandel",
    "sg:postcode":"1372",
    "sg:province":"Vaud",
    "wof:name":"Brunetti Vito, Vitob Diffusion",
    "wof:placetype":"venue"
},
  "geometry": {"coordinates":[6.565223217,46.6858901978],"type":"Point"}
}