{
  "type": "Feature",
  "properties": {
    "iso:country":"CH",
    "sg:address":"Chemin Du Cr\u00eat-de-la-palud",
    "sg:city":"St-l\u00e9gier",
    "sg:orig_category":"Mit Sport verbundene T\u00e4tigkeiten",
    "sg:phone":"+41 31 324 12 11",
    "sg:postcode":"1806",
    "sg:province":"Vaud",
    "wof:name":"Eidg.milit\u00e4rpferdeanstalt Reitanstalt",
    "wof:placetype":"venue"
},
  "geometry": {"coordinates":[7.4631371498,46.9580726624],"type":"Point"}
}