{
  "type": "Feature",
  "properties": {
    "iso:country":"CH",
    "sg:address":"Industriestrasse 1 4922 B\u00fctzberg. Postfach 132",
    "sg:city":"B\u00fctzberg",
    "sg:orig_category":"Elektroinstallation Herstellung von Elektrizit\u00e4tsverteilungs U schalteinrichtungen",
    "sg:postcode":"4922",
    "sg:province":"Bern",
    "wof:name":"Mettler Elektrik Ag Automation",
    "wof:placetype":"venue"
},
  "geometry": {"coordinates":[9.0009021759,47.1954574585],"type":"Point"}
}