{
  "type": "Feature",
  "properties": {
    "iso:country":"CH",
    "sg:address":"Grubenstieg 7",
    "sg:city":"Schaffhausen",
    "sg:orig_category":"Erschliessung von Grundst\u00fccken",
    "sg:postcode":"8200",
    "sg:province":"Schaffhausen",
    "wof:name":"Wohnbaugenossenschaft Des Eidg. Personals, R\u00fcti.",
    "wof:placetype":"venue"
},
  "geometry": {"coordinates":[8.8584327698,47.2616844177],"type":"Point"}
}