{
  "type": "Feature",
  "properties": {
    "iso:country":"CH",
    "sg:address":"Via Industria",
    "sg:city":"Lamone",
    "sg:orig_category":"Herstellung von Elektromotoren, Generatoren U Transformatoren Mechanische Werkst\u00e4tten",
    "sg:phone":"+41 91 605 53 70",
    "sg:postcode":"6814",
    "sg:province":"Ticino",
    "wof:name":"Gianfranco Carcano Sa",
    "wof:placetype":"venue"
},
  "geometry": {"coordinates":[8.9248304367,46.0384063721],"type":"Point"}
}