{
  "type": "Feature",
  "properties": {
    "addr:full":"St. Martin St. Martin Valais 1969",
    "addr:postcode":"1969",
    "addr:street":"St. Martin",
    "iso:country":"CH",
    "sg:address":"St. Martin",
    "sg:city":"St. Martin",
    "sg:classifiers":[
        {
            "category":"Banks & Credit Unions",
            "subcategory":"Bank",
            "type":"Services"
        }
    ],
    "sg:phone":"+41 27 281 35 35",
    "sg:postcode":"1969",
    "sg:province":"Valais",
    "wof:name":"Banque Cantonale Du Valais, Crettaz Bruno Bureau",
    "wof:placetype":"venue"
},
  "geometry": {"coordinates":[7.438925,46.177898],"type":"Point"}
}