{
  "type": "Feature",
  "properties": {
    "iso:country":"CH",
    "sg:address":"Winterthurerstrasse 73",
    "sg:city":"Z\u00fcrich",
    "sg:orig_category":"Herstellung von Schmuck, Gold U Silberschmiedwaren Herstellung von sonstigen M\u00f6beln",
    "sg:phone":"+41 13629284",
    "sg:postcode":"8006",
    "sg:province":"Z\u00fcrich",
    "wof:name":"Atelier Zart Ammann M.",
    "wof:placetype":"venue"
},
  "geometry": {"coordinates":[8.5456752777,47.3898086548],"type":"Point"}
}