{
  "type": "Feature",
  "properties": {
    "iso:country":"CH",
    "sg:address":"Fronwagplatz 1 8200 Schaffhausen. Postfach",
    "sg:city":"Schaffhausen",
    "sg:orig_category":"Warenh\u00e4user",
    "sg:phone":"+41 52 632 06 99",
    "sg:postcode":"8201",
    "sg:province":"Schaffhausen",
    "wof:name":"Manor",
    "wof:placetype":"venue"
},
  "geometry": {"coordinates":[8.6334571838,47.696472168],"type":"Point"}
}