{
  "type": "Feature",
  "properties": {
    "iso:country":"CH",
    "sg:address":"4704 Niederbipp. Postfach",
    "sg:city":"Niederbipp",
    "sg:orig_category":"Unclassifiable Establishments",
    "sg:postcode":"4704",
    "sg:province":"Bern",
    "wof:name":"K\u00fcnzler Swiss Gmbh",
    "wof:placetype":"venue"
},
  "geometry": {"coordinates":[9.6412591934,47.4458045959],"type":"Point"}
}