{
  "type": "Feature",
  "properties": {
    "iso:country":"CH",
    "sg:address":"Grand-ch\u00e9zard 5",
    "sg:city":"Ch\u00e9zard-st-martin",
    "sg:orig_category":"Handel mit Automobilen",
    "sg:postcode":"2054",
    "sg:province":"Neuch\u00e2tel",
    "wof:name":"S + O, Hauser Pierre, Heintz Patrick Et Hofer Nelson",
    "wof:placetype":"venue"
},
  "geometry": {"coordinates":[6.9201140404,47.0651016235],"type":"Point"}
}