{
  "type": "Feature",
  "properties": {
    "iso:country":"CH",
    "sg:address":"Via Angelo Maspoli 18 6850 Mendrisio. Postfach",
    "sg:city":"Mendrisio",
    "sg:orig_category":"Detailhandel mit Bekleidung",
    "sg:postcode":"6850",
    "sg:province":"Ticino",
    "wof:name":"Okbs Sagl",
    "wof:placetype":"venue"
},
  "geometry": {"coordinates":[8.978729,45.875259],"type":"Point"}
}