{
  "type": "Feature",
  "properties": {
    "iso:country":"CH",
    "sg:address":"Z\u00fcrcherstrasse 63",
    "sg:city":"Thalwil",
    "sg:orig_category":"Instandhaltung U Reparatur von Automobilen",
    "sg:phone":"+41 17209655",
    "sg:postcode":"8800",
    "sg:province":"Z\u00fcrich",
    "wof:name":"Tisch & Co, Garage, Inh. Tisch Alfred Jun., 8800 Thalwil",
    "wof:placetype":"venue"
},
  "geometry": {"coordinates":[8.5654392242,47.2844467163],"type":"Point"}
}