{
  "type": "Feature",
  "properties": {
    "addr:full":"Dorfstrasse Matten(st.stephan) Bern 3773",
    "addr:postcode":"3773",
    "addr:street":"Dorfstrasse",
    "iso:country":"CH",
    "sg:address":"Dorfstrasse",
    "sg:city":"Matten(st.stephan)",
    "sg:orig_category":"Detailhandel mit Brot, Back U S\u00fcsswaren Detailhandel mit Waren verschiedener Art, Hauptrichtung Nahr",
    "sg:phone":"+41 33 722 19 89",
    "sg:postcode":"3773",
    "sg:province":"Bern",
    "wof:name":"Luise Pfander",
    "wof:placetype":"venue"
},
  "geometry": {"coordinates":[7.422602,46.497105],"type":"Point"}
}