{
  "type": "Feature",
  "properties": {
    "iso:country":"CH",
    "sg:address":"6850",
    "sg:city":"Mendrisio",
    "sg:orig_category":"Sportvereine Turnen",
    "sg:phone":"+41 91 646 56 39",
    "sg:postcode":"6850",
    "sg:province":"Ticino",
    "wof:name":"Societ\u00e0 Ginnastica Federale",
    "wof:placetype":"venue"
},
  "geometry": {"coordinates":[8.9789495468,45.876991272],"type":"Point"}
}