{
  "type": "Feature",
  "properties": {
    "iso:country":"CH",
    "sg:address":"Haldenweg 9",
    "sg:city":"Arlesheim",
    "sg:orig_category":"Herstellung von medizinischen U chirurgischen Ger\u00e4ten sowie orthop\u00e4dischen Vorrichtungen",
    "sg:phone":"+41 61 702 17 78",
    "sg:postcode":"4144",
    "sg:province":"Basel-Landschaft",
    "wof:name":"Walter Engineering",
    "wof:placetype":"venue"
},
  "geometry": {"coordinates":[7.6219058037,47.502456665],"type":"Point"}
}