{
  "type": "Feature",
  "properties": {
    "iso:country":"CH",
    "sg:address":"M\u00f6nchweg 8",
    "sg:city":"Biberist",
    "sg:orig_category":"Hardwareberatung",
    "sg:phone":"+41 32 672 00 05",
    "sg:postcode":"4562",
    "sg:province":"Solothurn",
    "wof:name":"Moser Mikroelektronik",
    "wof:placetype":"venue"
},
  "geometry": {"coordinates":[7.5483407974,47.1848144531],"type":"Point"}
}