{
  "type": "Feature",
  "properties": {
    "iso:country":"CH",
    "sg:address":"Le Bioley",
    "sg:city":"Salvan",
    "sg:orig_category":"Betrieb von Taxis Sonstige Personenbef\u00f6rderung im Landverkehr",
    "sg:phone":"+41 27 761 21 21",
    "sg:postcode":"1922",
    "sg:province":"Valais",
    "wof:name":"Arcar Lucien Vaucher",
    "wof:placetype":"venue"
},
  "geometry": {"coordinates":[7.021746,46.122593],"type":"Point"}
}