{
  "type": "Feature",
  "properties": {
    "iso:country":"CH",
    "sg:address":"Rue Du Sex 4",
    "sg:city":"Sion",
    "sg:orig_category":"Architektur U Ingenieurb\u00fcros Architekturb\u00fcros",
    "sg:phone":"+41 79 216 87 89",
    "sg:postcode":"1950",
    "sg:province":"Valais",
    "wof:name":"Darioly Andr\u00e9 Sa, Atelier D'architecture",
    "wof:placetype":"venue"
},
  "geometry": {"coordinates":[7.362773,46.231647],"type":"Point"}
}