{
  "type": "Feature",
  "properties": {
    "iso:country":"CH",
    "sg:address":"Schanzackerstrasse 11 8000 Z\u00fcrich. Postfach",
    "sg:city":"Z\u00fcrich",
    "sg:orig_category":"Unternehmensberatung",
    "sg:postcode":"8001",
    "sg:province":"Z\u00fcrich",
    "wof:name":"Hendry Veronika, Lic. Phil. I, Organisationsberaterin/supervisorin Iap/bso",
    "wof:placetype":"venue"
},
  "geometry": {"coordinates":[8.5472269058,47.3906822205],"type":"Point"}
}