{
  "type": "Feature",
  "properties": {
    "iso:country":"CH",
    "sg:address":"1037",
    "sg:city":"Etagni\u00e8res",
    "sg:orig_category":"Malerei Stukkateurgewerbe, Gipserei U Verputzerei",
    "sg:phone":"+41 21 731 14 10",
    "sg:postcode":"1037",
    "sg:province":"Vaud",
    "wof:name":"Gaston Gilli\u00e9ron Gypserie & Peinture",
    "wof:placetype":"venue"
},
  "geometry": {"coordinates":[6.6100001335,46.6005897522],"type":"Point"}
}