{
  "type": "Feature",
  "properties": {
    "iso:country":"CH",
    "sg:address":"Avenue Du Rawyl",
    "sg:city":"Montana-vermala",
    "sg:orig_category":"Detailhandel mit Pelzwaren",
    "sg:phone":"+41 27 481 80 70",
    "sg:postcode":"3962",
    "wof:name":"Tsonas-furs Fourrures",
    "wof:placetype":"venue"
},
  "geometry": {"coordinates":[7.4924340248,46.3144187927],"type":"Point"}
}