{
  "type": "Feature",
  "properties": {
    "iso:country":"CH",
    "sg:address":"Hofmattstrasse 37a",
    "sg:city":"Huttwil",
    "sg:orig_category":"Baugewerbe",
    "sg:phone":"+41 32 346 11 11",
    "sg:postcode":"4950",
    "sg:province":"Bern",
    "wof:name":"Hartmann + Co. Ag",
    "wof:placetype":"venue"
},
  "geometry": {"coordinates":[7.264234,47.142292],"type":"Point"}
}