{
  "type": "Feature",
  "properties": {
    "iso:country":"CH",
    "sg:address":"Feldstrasse 11",
    "sg:city":"Urdorf",
    "sg:orig_category":"Innendekorationsateliers",
    "sg:phone":"+41 17340842",
    "sg:postcode":"8902",
    "sg:province":"Z\u00fcrich",
    "wof:name":"Florido R. Giunchi Innendekorationen",
    "wof:placetype":"venue"
},
  "geometry": {"coordinates":[8.426361084,47.3905792236],"type":"Point"}
}