{
  "type": "Feature",
  "properties": {
    "iso:country":"CH",
    "sg:address":"Flurstrasse 4 7205 Zizers. Postfach 70",
    "sg:city":"Zizers",
    "sg:orig_category":"Sonstiger spezialisierter Hoch U Tiefbau",
    "sg:phone":"+41 81 322 41 62",
    "sg:postcode":"7205",
    "sg:province":"Graubunden",
    "wof:name":"Gramatica F., Kaminbau + Sanierungen",
    "wof:placetype":"venue"
},
  "geometry": {"coordinates":[9.5571432114,46.9349021912],"type":"Point"}
}