{
  "type": "Feature",
  "properties": {
    "iso:country":"CH",
    "sg:address":"L\u00e4sserweg 4",
    "sg:city":"Rothrist",
    "sg:orig_category":"Sportvereine Sch\u00fctzen",
    "sg:phone":"+41 32 351 30 33",
    "sg:postcode":"4852",
    "sg:province":"Aargau",
    "wof:name":"Stadtsch\u00fctzengesellschaft",
    "wof:placetype":"venue"
},
  "geometry": {"coordinates":[7.3718671799,47.1398963928],"type":"Point"}
}