{
  "type": "Feature",
  "properties": {
    "iso:country":"CH",
    "sg:address":"N\u00e4hseydi 6",
    "sg:city":"Buochs",
    "sg:orig_category":"Non-Classified Establishments",
    "sg:phone":"+41 41 620 80 70",
    "sg:postcode":"6374",
    "sg:province":"Nidwalden",
    "wof:name":"Viva Drogerie Krummenacher",
    "wof:placetype":"venue"
},
  "geometry": {"coordinates":[8.4183101654,46.9787101746],"type":"Point"}
}