{
  "type": "Feature",
  "properties": {
    "iso:country":"CH",
    "sg:address":"R\u00fctistrasse 2 5400 Baden. Postfach 523",
    "sg:city":"Baden",
    "sg:orig_category":"Physiotherapie",
    "sg:phone":"+41 71 911 66 40",
    "sg:postcode":"5401",
    "sg:province":"Aargau",
    "wof:name":"M. Keller & G. Visser Physiotherapie",
    "wof:placetype":"venue"
},
  "geometry": {"coordinates":[9.0420417786,47.464630127],"type":"Point"}
}