{
  "type": "Feature",
  "properties": {
    "iso:country":"CH",
    "sg:address":"Bergackerweg 1",
    "sg:city":"Sch\u00fcpfen",
    "sg:orig_category":"Non-Classified Establishments",
    "sg:postcode":"3054",
    "sg:province":"Bern",
    "wof:name":"Gasthof B\u00e4ren Sch\u00fcpfen Vincent Daamen",
    "wof:placetype":"venue"
},
  "geometry": {"coordinates":[7.3763709068,47.0361862183],"type":"Point"}
}