{
  "type": "Feature",
  "properties": {
    "iso:country":"CH",
    "sg:address":"Bahnhofstrasse 21 6300 Zug. Postfach",
    "sg:city":"Zug",
    "sg:orig_category":"Unternehmensberatung",
    "sg:postcode":"6300",
    "sg:province":"Zug",
    "wof:name":"Meier Benno J. Organisationsberatung Unternehmensberatung, Bes. Auf Den Gebieten Management, Organisation, Edv U. Personal",
    "wof:placetype":"venue"
},
  "geometry": {"coordinates":[8.5156917572,47.1697540283],"type":"Point"}
}