{
  "type": "Feature",
  "properties": {
    "iso:country":"CH",
    "sg:address":"Hauptstrasse 36",
    "sg:city":"Thundorf",
    "sg:orig_category":"Herstellung von Elektrizit\u00e4tsverteilungs U schalteinrichtungen",
    "sg:phone":"+41 52 722 40 80",
    "sg:postcode":"8512",
    "sg:province":"Thurgau",
    "wof:name":"Daniel Kirchmeier Schaltanlagen",
    "wof:placetype":"venue"
},
  "geometry": {"coordinates":[8.9663248062,47.5461540222],"type":"Point"}
}