{
  "type": "Feature",
  "properties": {
    "iso:country":"CH",
    "sg:address":"La Voie-creuse 16",
    "sg:city":"Gen\u00e8ve",
    "sg:orig_category":"Detailhandel mit Bekleidung Detailhandel mit Geschenkartikeln U Souvenirs",
    "sg:phone":"+41 79 624 21 92",
    "sg:postcode":"1202",
    "sg:province":"Gen\u00e8ve",
    "wof:name":"Les Galeries Du Lac Sa",
    "wof:placetype":"venue"
},
  "geometry": {"coordinates":[6.142939,46.219608],"type":"Point"}
}