{
  "type": "Feature",
  "properties": {
    "iso:country":"CH",
    "sg:address":"Sch\u00fctzenstrasse 28",
    "sg:city":"Dietikon",
    "sg:orig_category":"Detailhandel mit Getr\u00e4nken Grosshandel mit Getr\u00e4nken",
    "sg:phone":"+41 12260123",
    "sg:postcode":"8953",
    "sg:province":"Z\u00fcrich",
    "wof:name":"Gut Donat Weinkellerei",
    "wof:placetype":"venue"
},
  "geometry": {"coordinates":[8.7952785492,47.3630638123],"type":"Point"}
}