{
  "type": "Feature",
  "properties": {
    "iso:country":"CH",
    "sg:address":"Quai De L'avan\u00e7on 25",
    "sg:city":"Bex",
    "sg:classifiers":[
        {
            "category":"Restaurant",
            "type":"Food & Drink"
        }
    ],
    "sg:phone":"+41 32 968 38 04",
    "sg:postcode":"1880",
    "sg:province":"Vaud",
    "wof:name":"Caf\u00e9 Des Faucheurs",
    "wof:placetype":"venue"
},
  "geometry": {"coordinates":[6.8337550163,47.1033782959],"type":"Point"}
}