{
  "type": "Feature",
  "properties": {
    "iso:country":"CH",
    "sg:address":"R\u00fctistrasse 13",
    "sg:city":"Schlieren",
    "sg:classifiers":[
        {
            "category":"Structure",
            "subcategory":"Office Building",
            "type":"Public Place"
        }
    ],
    "sg:phone":"+41 17338111",
    "sg:postcode":"8952",
    "sg:province":"Z\u00fcrich",
    "sg:tags":[
        "information",
        "orientation",
        "system"
    ],
    "wof:name":"Ruf Telematik Ag",
    "wof:placetype":"venue"
},
  "geometry": {"coordinates":[8.4525289536,47.4009437561],"type":"Point"}
}