{
  "type": "Feature",
  "properties": {
    "iso:country":"CH",
    "sg:address":"Stammrain 73",
    "sg:city":"Staffelbach",
    "sg:orig_category":"Herstellung von Maschinen f\u00fcr die Nahrungsmittel, Getr\u00e4nkeherstellung U die Tabakverarbeitung",
    "sg:phone":"+41 62 721 38 18",
    "sg:postcode":"5053",
    "sg:province":"Aargau",
    "wof:name":"Maweb B\u00e4ckger\u00e4te Fischer Karl",
    "wof:placetype":"venue"
},
  "geometry": {"coordinates":[8.0440092087,47.2833175659],"type":"Point"}
}