{
  "type": "Feature",
  "properties": {
    "iso:country":"CH",
    "sg:address":"Ringstrasse 1",
    "sg:city":"Ostermundigen",
    "sg:orig_category":"Sportvereine Velo Rad-& Motorfahrer-Bund SRB",
    "sg:phone":"+41 31 932 33 54",
    "sg:postcode":"3072",
    "sg:province":"Bern",
    "wof:name":"Radfahrerverein Langenthal",
    "wof:placetype":"venue"
},
  "geometry": {"coordinates":[7.4788298607,46.9544410706],"type":"Point"}
}