{
  "type": "Feature",
  "properties": {
    "iso:country":"CH",
    "sg:address":"Chemin Du Pont-de-ville 7 1224 Ch\u00eane-bougeries. Postfach",
    "sg:city":"Ch\u00eane-bougeries",
    "sg:orig_category":"Non-Classified Establishments",
    "sg:postcode":"1224",
    "sg:province":"Gen\u00e8ve",
    "wof:name":"Handicap Mobil Service, Blandin",
    "wof:placetype":"venue"
},
  "geometry": {"coordinates":[6.1910729408,46.1972045898],"type":"Point"}
}