{
  "type": "Feature",
  "properties": {
    "iso:country":"CH",
    "sg:address":"Platy Route Du 7a",
    "sg:city":"Villars-sur-gl\u00e2ne",
    "sg:orig_category":"Sonstiger Grosshandel",
    "sg:phone":"+41 32 931 44 80",
    "sg:postcode":"1752",
    "sg:province":"Fribourg",
    "wof:name":"Msm Diffusion Sa",
    "wof:placetype":"venue"
},
  "geometry": {"coordinates":[6.7668180466,47.064289093],"type":"Point"}
}