{
  "type": "Feature",
  "properties": {
    "iso:country":"CH",
    "sg:address":"Im Sch\u00e4nzli 103 B 4132 Muttenz. Postfach",
    "sg:city":"Muttenz",
    "sg:orig_category":"Softwareentwicklung U beratung",
    "sg:postcode":"4132",
    "sg:province":"Basel-Landschaft",
    "wof:name":"Cad Pro Gmbh",
    "wof:placetype":"venue"
},
  "geometry": {"coordinates":[7.6254291534,47.5380706787],"type":"Point"}
}