{
  "type": "Feature",
  "properties": {
    "iso:country":"CH",
    "sg:address":"3823",
    "sg:city":"Wengen",
    "sg:orig_category":"Non-Classified Establishments",
    "sg:postcode":"3823",
    "sg:province":"Bern",
    "wof:name":"Wengen Tourismus",
    "wof:placetype":"venue"
},
  "geometry": {"coordinates":[7.921599865,46.6051902771],"type":"Point"}
}