{
  "type": "Feature",
  "properties": {
    "iso:country":"CH",
    "sg:address":"Bruggerstrasse 69 5400 Baden. Postfach",
    "sg:city":"Baden",
    "sg:orig_category":"Softwareentwicklung U beratung",
    "sg:phone":"+41 22 366 83 20",
    "sg:postcode":"5400",
    "sg:province":"Aargau",
    "wof:name":"Prism Solutions S\u00e0rl",
    "wof:placetype":"venue"
},
  "geometry": {"coordinates":[6.2354798317,46.4775047302],"type":"Point"}
}