{
  "type": "Feature",
  "properties": {
    "iso:country":"CH",
    "sg:address":"5742",
    "sg:city":"K\u00f6lliken",
    "sg:orig_category":"Schulpflegen",
    "sg:postcode":"5742",
    "sg:province":"Aargau",
    "wof:name":"Schulpflege Der Gemeinde K\u00f6lliken",
    "wof:placetype":"venue"
},
  "geometry": {"coordinates":[8.0244512558,47.3365325928],"type":"Point"}
}