{
  "type": "Feature",
  "properties": {
    "addr:full":"Mainaustrasse 21 Z\u00fcrich Z\u00fcrich 8008",
    "addr:housenumber":"21",
    "addr:postcode":"8008",
    "addr:street":"Mainaustrasse",
    "iso:country":"CH",
    "sg:address":"Mainaustrasse 21",
    "sg:city":"Z\u00fcrich",
    "sg:classifiers":[
        {
            "category":"Cinema",
            "subcategory":"Movie Rental",
            "type":"Entertainment"
        }
    ],
    "sg:phone":"+41 13815901",
    "sg:postcode":"8008",
    "sg:province":"Z\u00fcrich",
    "sg:tags":[
        "film",
        "computer",
        "video",
        "animation",
        "cinematic"
    ],
    "wof:name":"Wigwam Gmbh",
    "wof:placetype":"venue"
},
  "geometry": {"coordinates":[8.549724,47.360615],"type":"Point"}
}