{
  "type": "Feature",
  "properties": {
    "iso:country":"CH",
    "sg:address":"Waldst\u00e4tterstrasse 16 6003 Luzern. Postfach",
    "sg:city":"Luzern",
    "sg:classifiers":[
        {
            "category":"Professional",
            "subcategory":"Accounting & Tax Preparation",
            "type":"Services"
        }
    ],
    "sg:postcode":"6003",
    "sg:province":"Luzern",
    "sg:tags":[
        "u",
        "yachtbau",
        "boot"
    ],
    "wof:name":"Gruppo Sportivo Di Vela Alto Mare F\u00f6rderung D. Yachtsport Auf See Usw.",
    "wof:placetype":"venue"
},
  "geometry": {"coordinates":[8.309003,47.046593],"type":"Point"}
}