{
  "type": "Feature",
  "properties": {
    "iso:country":"CH",
    "sg:address":"Osterwald Quai 2",
    "sg:city":"Neuenburg",
    "sg:orig_category":"Unclassifiable Establishments",
    "sg:postcode":"2000",
    "sg:province":"Neuch\u00e2tel",
    "wof:name":"Cashstar International S.a.",
    "wof:placetype":"venue"
},
  "geometry": {"coordinates":[6.9304962158,46.989315033],"type":"Point"}
}