{
  "type": "Feature",
  "properties": {
    "iso:country":"CH",
    "sg:address":"Sandrain 14",
    "sg:city":"H\u00e4gendorf",
    "sg:orig_category":"Korrespondenz U Nachrichtenb\u00fcros, selbst\u00e4ndige Journalisten",
    "sg:phone":"+41 62 216 88 42",
    "sg:postcode":"4614",
    "sg:province":"Solothurn",
    "wof:name":"Klaffke & Dietschi 's Really Fine Ideas",
    "wof:placetype":"venue"
},
  "geometry": {"coordinates":[7.8451008797,47.3406829834],"type":"Point"}
}