{
  "type": "Feature",
  "properties": {
    "iso:country":"CH",
    "sg:address":"Espenstrasse 1",
    "sg:city":"Niederurnen",
    "sg:orig_category":"Sportvereine Wassersport Segeln",
    "sg:phone":"+41 55 610 12 70",
    "sg:postcode":"8867",
    "sg:province":"Glarus",
    "wof:name":"Segelcl.glarnerl.& Walens.scgw",
    "wof:placetype":"venue"
},
  "geometry": {"coordinates":[9.0573167801,47.1247825623],"type":"Point"}
}