{
  "type": "Feature",
  "properties": {
    "iso:country":"CH",
    "sg:address":"Luzernerstr. 26",
    "sg:city":"Ermensee",
    "sg:classifiers":[
        {
            "category":"Professional",
            "subcategory":"Engineering",
            "type":"Services"
        }
    ],
    "sg:phone":"+41 41 919 90 20",
    "sg:postcode":"6294",
    "sg:province":"Luzern",
    "sg:tags":[
        "machine",
        "-",
        "mechanical"
    ],
    "wof:name":"Ineichen Ag",
    "wof:placetype":"venue"
},
  "geometry": {"coordinates":[8.2494506836,47.2241401672],"type":"Point"}
}