{
  "type": "Feature",
  "properties": {
    "iso:country":"CH",
    "sg:address":"Worblentalstrasse 35",
    "sg:city":"Ittigen",
    "sg:orig_category":"G\u00fcterbef\u00f6rderung im Strassenverkehr",
    "sg:postcode":"3063",
    "sg:province":"Bern",
    "wof:name":"Leite Herbert.",
    "wof:placetype":"venue"
},
  "geometry": {"coordinates":[7.4719572067,46.978225708],"type":"Point"}
}