{
  "type": "Feature",
  "properties": {
    "iso:country":"CH",
    "sg:address":"Pr\u00e9 Fleuri Rue 3",
    "sg:city":"Del\u00e9mont",
    "sg:orig_category":"Fachdetailhandel in Verkaufsr\u00e4umen",
    "sg:phone":"+41 19500022",
    "sg:postcode":"2800",
    "sg:province":"Jura",
    "wof:name":"Marcel Sem, Tier-importeur",
    "wof:placetype":"venue"
},
  "geometry": {"coordinates":[8.7205848694,47.2775268555],"type":"Point"}
}