{
  "type": "Feature",
  "properties": {
    "addr:full":"Verbier 1936 Verbier. Postfach Verbier Valais 1936",
    "addr:postcode":"1936;postfach;1936",
    "addr:street":"Verbier.",
    "iso:country":"CH",
    "sg:address":"Verbier 1936 Verbier. Postfach",
    "sg:city":"Verbier",
    "sg:orig_category":"Betrieb von Sportanlagen",
    "sg:postcode":"1936",
    "sg:province":"Valais",
    "wof:name":"Verbier Sport Management Sa",
    "wof:placetype":"venue"
},
  "geometry": {"coordinates":[7.219276,46.096146],"type":"Point"}
}