{
  "type": "Feature",
  "properties": {
    "addr:full":"Schulstrasse 81 Hellikon Aargau 4316",
    "addr:housenumber":"81",
    "addr:postcode":"4316",
    "addr:street":"Schulstrasse",
    "iso:country":"CH",
    "sg:address":"Schulstrasse 81",
    "sg:city":"Hellikon",
    "sg:classifiers":[
        {
            "category":"Banks & Credit Unions",
            "subcategory":"Bank",
            "type":"Services"
        }
    ],
    "sg:phone":"+41 61 871 06 74",
    "sg:postcode":"4316",
    "sg:province":"Aargau",
    "wof:name":"Schweiz. Mobiliar",
    "wof:placetype":"venue"
},
  "geometry": {"coordinates":[7.923724,47.509636],"type":"Point"}
}