{
  "type": "Feature",
  "properties": {
    "iso:country":"CH",
    "sg:address":"Thunstrasse 4 3510 Konolfingen. Postfach 139",
    "sg:city":"Konolfingen",
    "sg:orig_category":"Brillen Detailhandel Fachdetailhandel in Verkaufsr\u00e4umen",
    "sg:phone":"+41 31 792 01 01",
    "sg:postcode":"3510",
    "sg:province":"Bern",
    "wof:name":"Schuster Optik",
    "wof:placetype":"venue"
},
  "geometry": {"coordinates":[7.620484,46.877586],"type":"Point"}
}