{
  "type": "Feature",
  "properties": {
    "iso:country":"CH",
    "sg:address":"Martinstrasse 20",
    "sg:city":"Thun",
    "sg:orig_category":"Sportvereine Turnen",
    "sg:phone":"+41 52 203 61 67",
    "sg:postcode":"3600",
    "sg:province":"Bern",
    "wof:name":"Turnverein T\u00f6ss",
    "wof:placetype":"venue"
},
  "geometry": {"coordinates":[8.7435436249,47.4562454224],"type":"Point"}
}