{
  "type": "Feature",
  "properties": {
    "iso:country":"CH",
    "sg:address":"Kurz\u00e4ckerlistrasse 228",
    "sg:city":"B\u00e4rschwil",
    "sg:orig_category":"Maler U Glasergewerbe Malerei",
    "sg:phone":"+41 61 761 66 02",
    "sg:postcode":"4252",
    "sg:province":"Solothurn",
    "wof:name":"Theo Henz Malergesch\u00e4ft",
    "wof:placetype":"venue"
},
  "geometry": {"coordinates":[7.4702892303,47.3852233887],"type":"Point"}
}