{
  "type": "Feature",
  "properties": {
    "iso:country":"CH",
    "sg:address":"Romont Rue De 35 1700 Fribourg. Postfach",
    "sg:city":"Freiburg",
    "sg:orig_category":"Erwachsenenbildung U Unterricht",
    "sg:phone":"+41 26 347 16 30",
    "sg:postcode":"1700",
    "sg:province":"Fribourg",
    "wof:name":"Serviplan Sa Assistance, Conseil Etc. En Toutes Mati\u00e8res, Notamm. En Mati\u00e8re De Management, De Marketing, D'\u00e9tudes De March\u00e9, Publicit\u00e9",
    "wof:placetype":"venue"
},
  "geometry": {"coordinates":[7.1539649963,46.8043441772],"type":"Point"}
}