{
  "type": "Feature",
  "properties": {
    "iso:country":"CH",
    "sg:address":"Mulino Via 6",
    "sg:city":"Stabio",
    "sg:orig_category":"Grosshandel mit Getr\u00e4nken",
    "sg:phone":"+41 91 647 12 52",
    "sg:postcode":"6855",
    "sg:province":"Ticino",
    "wof:name":"Agri-vino Sagl",
    "wof:placetype":"venue"
},
  "geometry": {"coordinates":[8.9379882812,45.8471794128],"type":"Point"}
}