{
  "type": "Feature",
  "properties": {
    "iso:country":"CH",
    "sg:address":"Steinrain 15",
    "sg:city":"Fl\u00fch",
    "sg:orig_category":"Unternehmensberatung",
    "sg:phone":"+41 61 731 36 15",
    "sg:postcode":"4112",
    "sg:province":"Solothurn",
    "wof:name":"Paul Schoenenberger Wirtschafts-& Steuerberatung",
    "wof:placetype":"venue"
},
  "geometry": {"coordinates":[7.497877121,47.4871520996],"type":"Point"}
}