{
  "type": "Feature",
  "properties": {
    "iso:country":"CH",
    "sg:address":"Maiholzstrasse 30",
    "sg:city":"Frauenfeld",
    "sg:orig_category":"Detailhandel mit Fahrr\u00e4dern Handel mit Motorr\u00e4dern, Teilen U Zubeh\u00f6r Instandhaltung U Reparatur von ",
    "sg:phone":"+41 52 720 66 64",
    "sg:postcode":"8500",
    "sg:province":"Thurgau",
    "wof:name":"Paul Badertscher Velos-motos",
    "wof:placetype":"venue"
},
  "geometry": {"coordinates":[8.8859081268,47.5596046448],"type":"Point"}
}