{
  "type": "Feature",
  "properties": {
    "iso:country":"CH",
    "sg:address":"Route Louis-braille 10-12 1763 Granges-paccot Case Postale 590",
    "sg:city":"Fribourg",
    "sg:orig_category":"Finanzierungsinstitutionen",
    "sg:phone":"+41 22 731 97 13",
    "sg:postcode":"1701",
    "sg:province":"Fribourg",
    "wof:name":"Compagnie Financi\u00e8re M\u00e9diterran\u00e9e Cofimed Sa",
    "wof:placetype":"venue"
},
  "geometry": {"coordinates":[6.1470899582,46.2071266174],"type":"Point"}
}