{
  "type": "Feature",
  "properties": {
    "iso:country":"CH",
    "sg:address":"Longirod Route De 3",
    "sg:city":"Gimel",
    "sg:orig_category":"Herstellung von keramischen Wand U Bodenfliesen U platten",
    "sg:phone":"+41 21 828 32 01",
    "sg:postcode":"1188",
    "sg:province":"Vaud",
    "wof:name":"Glp Pasche G\u00e9rald",
    "wof:placetype":"venue"
},
  "geometry": {"coordinates":[6.3015890121,46.5075263977],"type":"Point"}
}