{
  "type": "Feature",
  "properties": {
    "addr:full":"Industriestrasse 2 Giswil Obwalden 6074",
    "addr:housenumber":"2",
    "addr:postcode":"6074",
    "addr:street":"Industriestrasse",
    "iso:country":"CH",
    "sg:address":"Industriestrasse 2",
    "sg:city":"Giswil",
    "sg:orig_category":"Allgemeiner Hoch U Tiefbau",
    "sg:phone":"+41 41 666 25 15",
    "sg:postcode":"6074",
    "sg:province":"Obwalden",
    "wof:name":"Fallegger Hoch- + Tiefbau Ag",
    "wof:placetype":"venue"
},
  "geometry": {"coordinates":[8.182702,46.842052],"type":"Point"}
}