{
  "type": "Feature",
  "properties": {
    "iso:country":"CH",
    "sg:address":"Via Ai Ronchi",
    "sg:city":"Vezia",
    "sg:orig_category":"Kaminfeger Reinigungsgewerbe",
    "sg:phone":"+41 91 866 14 75",
    "sg:postcode":"6943",
    "sg:province":"Ticino",
    "wof:name":"Kauz Fritz",
    "wof:placetype":"venue"
},
  "geometry": {"coordinates":[8.9388113022,46.0273323059],"type":"Point"}
}