{
  "type": "Feature",
  "properties": {
    "iso:country":"CH",
    "sg:address":"Blumenstrasse 15",
    "sg:city":"G\u00e4hwil",
    "sg:orig_category":"Architektur U Ingenieurb\u00fcros",
    "sg:phone":"+41 71 931 34 67",
    "sg:postcode":"9534",
    "sg:province":"St. Gallen",
    "wof:name":"Rutz Andreas Bauplanungen",
    "wof:placetype":"venue"
},
  "geometry": {"coordinates":[9.003508,47.39909],"type":"Point"}
}