{
  "type": "Feature",
  "properties": {
    "iso:country":"CH",
    "sg:address":"En Bornuit",
    "sg:city":"Bex",
    "sg:orig_category":"Erwachsenenbildung U Unterricht",
    "sg:postcode":"1880",
    "sg:province":"Vaud",
    "wof:name":"Aea S\u00e9jours Linguistiques - Dupuis Andr\u00e9 P.",
    "wof:placetype":"venue"
},
  "geometry": {"coordinates":[7.0156807899,46.2502593994],"type":"Point"}
}