{
  "type": "Feature",
  "properties": {
    "iso:country":"CH",
    "sg:address":"Stierenmattweg 6",
    "sg:city":"Sissach",
    "sg:orig_category":"Bauschreinerei Herstellung von Konstruktionsteilen, Fertigbauteilen U Ausbauelementen aus Holz",
    "sg:phone":"+41 79 235 81 80",
    "sg:postcode":"4450",
    "sg:province":"Basel-Landschaft",
    "wof:name":"Maendly Menuiserie S\u00e0rl",
    "wof:placetype":"venue"
},
  "geometry": {"coordinates":[6.830818,46.813274],"type":"Point"}
}