{
  "type": "Feature",
  "properties": {
    "iso:country":"CH",
    "sg:address":"Coll\u00e8ge Route Du",
    "sg:city":"Corcelles-payerne",
    "sg:orig_category":"Erschliessung von Grundst\u00fccken",
    "sg:postcode":"1562",
    "sg:province":"Vaud",
    "wof:name":"Le Grand Chemin Soci\u00e9t\u00e9 Coop\u00e9rative D'habitation",
    "wof:placetype":"venue"
},
  "geometry": {"coordinates":[6.9615449905,46.8308105469],"type":"Point"}
}