{
  "type": "Feature",
  "properties": {
    "iso:country":"CH",
    "sg:address":"Freudenbergstrasse 30",
    "sg:city":"Z\u00fcrich",
    "sg:orig_category":"Unclassifiable Establishments",
    "sg:phone":"+41 12603262",
    "sg:postcode":"8044",
    "sg:province":"Z\u00fcrich",
    "wof:name":"Schellenberg Communications Ag Beteiligungen Usw",
    "wof:placetype":"venue"
},
  "geometry": {"coordinates":[8.5588312149,47.3819580078],"type":"Point"}
}