{
  "type": "Feature",
  "properties": {
    "iso:country":"CH",
    "sg:address":"Holzh\u00e4usern 8514 Amlikon-bissegg. Postfach",
    "sg:city":"Bissegg",
    "sg:orig_category":"G\u00fcterbef\u00f6rderung im Strassenverkehr",
    "sg:phone":"+41 71 651 11 64",
    "sg:postcode":"8514",
    "sg:province":"Thurgau",
    "wof:name":"A. Wellauer Gmbh, Transporte, Bissegg",
    "wof:placetype":"venue"
},
  "geometry": {"coordinates":[9.0498600006,47.553188324],"type":"Point"}
}