{
  "type": "Feature",
  "properties": {
    "iso:country":"CH",
    "sg:address":"Zone Horticole Versvey 1853 Yvorne. Postfach",
    "sg:city":"Chavannes-renens",
    "sg:orig_category":"Herstellung von Mess U Kontrollinstrumenten U vorrichtungen",
    "sg:postcode":"1022",
    "sg:province":"Vaud",
    "wof:name":"Brunetti Vito Atelier De M\u00e9canique De Pr\u00e9cision",
    "wof:placetype":"venue"
},
  "geometry": {"coordinates":[6.9371399879,46.3436584473],"type":"Point"}
}