{
  "type": "Feature",
  "properties": {
    "iso:country":"CH",
    "sg:address":"Triemlistrasse 112",
    "sg:city":"Z\u00fcrich",
    "sg:orig_category":"Sportvereine Eissport Eishockey",
    "sg:phone":"+41 14922893",
    "sg:postcode":"8047",
    "sg:province":"Z\u00fcrich",
    "wof:name":"Eislaufclub Heurired",
    "wof:placetype":"venue"
},
  "geometry": {"coordinates":[8.4903812408,47.3692207336],"type":"Point"}
}