{
  "type": "Feature",
  "properties": {
    "iso:country":"CH",
    "sg:address":"Tramstrasse 41",
    "sg:city":"Suhr",
    "sg:orig_category":"Detailhandel mit Textilien",
    "sg:phone":"+41 62 842 17 71",
    "sg:postcode":"5034",
    "sg:province":"Aargau",
    "wof:name":"Mina Bianchi Wolle & Mercerie",
    "wof:placetype":"venue"
},
  "geometry": {"coordinates":[8.0779075623,47.3761978149],"type":"Point"}
}