{
  "type": "Feature",
  "properties": {
    "addr:full":"Sternenweg 2 Villmergen Aargau 5612",
    "addr:housenumber":"2",
    "addr:postcode":"5612",
    "addr:street":"Sternenweg",
    "iso:country":"CH",
    "sg:address":"Sternenweg 2",
    "sg:city":"Villmergen",
    "sg:orig_category":"Bauschreinerei Herstellung von K\u00fcchenm\u00f6beln",
    "sg:phone":"+41 56 622 24 03",
    "sg:postcode":"5612",
    "sg:province":"Aargau",
    "wof:name":"Schmid H. R.",
    "wof:placetype":"venue"
},
  "geometry": {"coordinates":[8.247295,47.34861],"type":"Point"}
}