{
  "type": "Feature",
  "properties": {
    "iso:country":"CH",
    "sg:address":"Bahnhofstrasse 57",
    "sg:city":"Ramsen",
    "sg:classifiers":[
        {
            "category":"Bars & Pubs",
            "type":"Food & Drink"
        }
    ],
    "sg:phone":"+41 52 743 11 40",
    "sg:postcode":"8262",
    "sg:province":"Schaffhausen",
    "sg:tags":[
        "restaurant"
    ],
    "wof:name":"Restaurant-bar Eisenbahn",
    "wof:placetype":"venue"
},
  "geometry": {"coordinates":[8.819615,47.707272],"type":"Point"}
}