{
  "type": "Feature",
  "properties": {
    "iso:country":"CH",
    "sg:address":"Schwarzackerstrasse 29",
    "sg:city":"Seltisberg",
    "sg:orig_category":"Fachdetailhandel in Verkaufsr\u00e4umen",
    "sg:phone":"+41 61 911 80 90",
    "sg:postcode":"4411",
    "sg:province":"Basel-Landschaft",
    "wof:name":"L\u00f6w Fine Art",
    "wof:placetype":"venue"
},
  "geometry": {"coordinates":[7.7145028114,47.4579811096],"type":"Point"}
}