{
  "type": "Feature",
  "properties": {
    "iso:country":"CH",
    "sg:address":"Jurastrasse 9",
    "sg:city":"Olten",
    "sg:orig_category":"Non-Classified Establishments",
    "sg:postcode":"4600",
    "sg:province":"Solothurn",
    "wof:name":"Marianne Huber Xundheitspraxis",
    "wof:placetype":"venue"
},
  "geometry": {"coordinates":[7.9041361809,47.3527297974],"type":"Point"}
}