{
  "type": "Feature",
  "properties": {
    "iso:country":"CH",
    "sg:address":"Niedern 641",
    "sg:city":"Trogen",
    "sg:orig_category":"Non-Classified Establishments",
    "sg:postcode":"9043",
    "sg:province":"Appenzell Ausserrhoden",
    "wof:name":"Ekthesis Expo Gmbh",
    "wof:placetype":"venue"
},
  "geometry": {"coordinates":[7.3006091118,47.107837677],"type":"Point"}
}