{
  "type": "Feature",
  "properties": {
    "iso:country":"CH",
    "sg:address":"Industriestrasse 19",
    "sg:city":"Otelfingen",
    "sg:orig_category":"Elektrischer Leitungsbau",
    "sg:phone":"+41 18475211",
    "sg:postcode":"8112",
    "sg:province":"Z\u00fcrich",
    "wof:name":"Cablecom Engineering Ag",
    "wof:placetype":"venue"
},
  "geometry": {"coordinates":[8.405538559,47.4566764832],"type":"Point"}
}