{
  "type": "Feature",
  "properties": {
    "iso:country":"CH",
    "sg:address":"Schreinerstrasse 1",
    "sg:city":"St.gallen",
    "sg:orig_category":"Herstellung von medizinischen U chirurgischen Ger\u00e4ten sowie orthop\u00e4dischen Vorrichtungen",
    "sg:postcode":"9000",
    "sg:province":"St. Gallen",
    "wof:name":"C-stat, Mettler Reto Und Simone",
    "wof:placetype":"venue"
},
  "geometry": {"coordinates":[9.934305191,46.5725212097],"type":"Point"}
}