{
  "type": "Feature",
  "properties": {
    "iso:country":"CH",
    "sg:address":"9103",
    "sg:city":"Schwellbrunn",
    "sg:classifiers":[
        {
            "category":"Education",
            "subcategory":"Vocational School",
            "type":"Public Place"
        }
    ],
    "sg:phone":"+41 71 377 12 21",
    "sg:postcode":"9103",
    "sg:province":"Appenzell Ausserrhoden",
    "sg:tags":[
        "koch-",
        "haushaltschulen"
    ],
    "wof:name":"Haushaltungsschule",
    "wof:placetype":"venue"
},
  "geometry": {"coordinates":[9.249505043,47.3522186279],"type":"Point"}
}