{
  "type": "Feature",
  "properties": {
    "iso:country":"CH",
    "sg:address":"Harpe Place De La 2",
    "sg:city":"Rolle",
    "sg:orig_category":"Zimmerei, Dachdeckerei, Bauspenglerei U Abdichtung",
    "sg:phone":"+41 21 825 10 20",
    "sg:postcode":"1180",
    "sg:province":"Vaud",
    "wof:name":"Jotterand Guy Sa",
    "wof:placetype":"venue"
},
  "geometry": {"coordinates":[6.3380351067,46.4575614929],"type":"Point"}
}