{
  "type": "Feature",
  "properties": {
    "iso:country":"CH",
    "sg:address":"Limmattalstrasse 130",
    "sg:city":"Z\u00fcrich",
    "sg:orig_category":"Detailhandel mit Uhren U Schmuck Reparatur von Uhren U Schmuck",
    "sg:phone":"+41 31 311 08 87",
    "sg:postcode":"8049",
    "sg:province":"Z\u00fcrich",
    "wof:name":"Uhren Und Bijouterie Nickl\u00e8s, Inhaber Nikles D. Uhren, Schmuck, Edelsteine; Handel",
    "wof:placetype":"venue"
},
  "geometry": {"coordinates":[7.4472751617,46.9482841492],"type":"Point"}
}