{
  "type": "Feature",
  "properties": {
    "iso:country":"CH",
    "sg:address":"Hohle 1",
    "sg:city":"Biglen",
    "sg:orig_category":"Detailhandel mit Milcherzeugnissen U Eiern Verarbeitung von Milch",
    "sg:phone":"+41 31 701 17 64",
    "sg:postcode":"3507",
    "sg:province":"Bern",
    "wof:name":"K\u00e4serei Biglen",
    "wof:placetype":"venue"
},
  "geometry": {"coordinates":[7.6263179779,46.9260292053],"type":"Point"}
}