{
  "type": "Feature",
  "properties": {
    "iso:country":"CH",
    "sg:address":"Josefstrasse 91",
    "sg:city":"Z\u00fcrich",
    "sg:orig_category":"Organisationen der Wohlfahrtspflege",
    "sg:phone":"+41 12721833",
    "sg:postcode":"8005",
    "sg:province":"Z\u00fcrich",
    "wof:name":"Z\u00fcrcher Fachstelle F\u00fcr Alkoholprobleme",
    "wof:placetype":"venue"
},
  "geometry": {"coordinates":[8.5306882858,47.3829421997],"type":"Point"}
}