{
  "type": "Feature",
  "properties": {
    "iso:country":"CH",
    "sg:address":"Lindenplatz 6",
    "sg:city":"Zofingen",
    "sg:classifiers":[
        {
            "category":"Professional",
            "subcategory":"Employment Agencies",
            "type":"Services"
        }
    ],
    "sg:phone":"+41 62 752 35 35",
    "sg:postcode":"4800",
    "sg:province":"Aargau",
    "sg:tags":[
        "personal",
        "u",
        "stellenvermittlung"
    ],
    "wof:name":"Workout Personal Gmbh Vermittlung Und Personalverleih Von Kaufm\u00e4nnischem, Technischem Und Hilfs-personal",
    "wof:placetype":"venue"
},
  "geometry": {"coordinates":[7.9445061684,47.289730072],"type":"Point"}
}