{
  "type": "Feature",
  "properties": {
    "iso:country":"CH",
    "sg:address":"Gliserallee 63",
    "sg:city":"Glis",
    "sg:classifiers":[
        {
            "category":"Building & Trades",
            "subcategory":"Cleaning & Sanitation",
            "type":"Services"
        }
    ],
    "sg:phone":"+41 79 206 61 02",
    "sg:postcode":"3902",
    "sg:province":"Valais",
    "sg:tags":[
        "device"
    ],
    "wof:name":"Resys-reinigungssysteme Gmbh",
    "wof:placetype":"venue"
},
  "geometry": {"coordinates":[7.984614,46.314178],"type":"Point"}
}