{
  "type": "Feature",
  "properties": {
    "iso:country":"CH",
    "sg:address":"Muristrasse 19 3006 Bern. Postfach",
    "sg:city":"Bern",
    "sg:orig_category":"Detailhandel mit B\u00fcchern, Zeitungen, Schreib U Papeteriewaren",
    "sg:postcode":"3005",
    "sg:province":"Bern",
    "wof:name":"Kurt Dill Kiosk, Souvenirs, Milchprodukte, Backwaren Usw",
    "wof:placetype":"venue"
},
  "geometry": {"coordinates":[7.460539,46.944695],"type":"Point"}
}