{
  "type": "Feature",
  "properties": {
    "iso:country":"CH",
    "sg:address":"Bachstrasse 1",
    "sg:city":"T\u00fcbach",
    "sg:orig_category":"Tierarztpraxis",
    "sg:phone":"+41 71 841 22 44",
    "sg:postcode":"9327",
    "sg:province":"St. Gallen",
    "wof:name":"Dr. Med. Vet. Viktor Bischoff Tierarzt",
    "wof:placetype":"venue"
},
  "geometry": {"coordinates":[9.4519081116,47.4850540161],"type":"Point"}
}