{
  "type": "Feature",
  "properties": {
    "iso:country":"CH",
    "sg:address":"4226",
    "sg:city":"Breitenbach",
    "sg:orig_category":"Bezirks, Sekundar, Realschulen, Oberstufe der Primarschulen",
    "sg:phone":"+41 61 781 13 16",
    "sg:postcode":"4226",
    "sg:province":"Solothurn",
    "wof:name":"Sekundarschule Schwedenschulhaus",
    "wof:placetype":"venue"
},
  "geometry": {"coordinates":[7.543707,47.408173],"type":"Point"}
}