{
  "type": "Feature",
  "properties": {
    "iso:country":"CH",
    "sg:address":"Gr\u00fct 163 9055 B\u00fchler. Postfach 72",
    "sg:city":"B\u00fchler",
    "sg:orig_category":"Non-Classified Establishments",
    "sg:phone":"+41 71 793 10 11",
    "sg:postcode":"9055",
    "sg:province":"Appenzell Ausserrhoden",
    "wof:name":"Tisca, Tischhauser & Co. Ag Textilwerke",
    "wof:placetype":"venue"
},
  "geometry": {"coordinates":[9.4214391708,47.3740615845],"type":"Point"}
}