{
  "type": "Feature",
  "properties": {
    "iso:country":"CH",
    "sg:address":"S\u00e4listrasse 35 6000 Luzern. Postfach",
    "sg:city":"Luzern",
    "sg:orig_category":"Sonstiger Grosshandel",
    "sg:postcode":"6003",
    "sg:province":"Luzern",
    "wof:name":"Lavapol Achermann J.",
    "wof:placetype":"venue"
},
  "geometry": {"coordinates":[8.2984857559,47.0458831787],"type":"Point"}
}