{
  "type": "Feature",
  "properties": {
    "iso:country":"CH",
    "sg:address":"Bahnhofstrasse 113",
    "sg:city":"Uzwil",
    "sg:orig_category":"Non-Classified Establishments",
    "sg:postcode":"9240",
    "sg:province":"St. Gallen",
    "wof:name":"Mock Rudolf.",
    "wof:placetype":"venue"
},
  "geometry": {"coordinates":[9.1375770569,47.4410591125],"type":"Point"}
}