{
  "type": "Feature",
  "properties": {
    "iso:country":"CH",
    "sg:address":"Dorfstrasse 27 3715 Adelboden. Postfach 205",
    "sg:city":"Adelboden",
    "sg:orig_category":"Detailhandel mit Brot, Back U S\u00fcsswaren",
    "sg:phone":"+41 33 673 12 34",
    "sg:postcode":"3715",
    "sg:province":"Bern",
    "wof:name":"Gerhard Haueter B\u00e4ckerei-konditorei",
    "wof:placetype":"venue"
},
  "geometry": {"coordinates":[7.558716,46.492256],"type":"Point"}
}