{
  "type": "Feature",
  "properties": {
    "iso:country":"CH",
    "sg:address":"Plaz 24",
    "sg:city":"Ramosch",
    "sg:orig_category":"Physiotherapie",
    "sg:phone":"+41 81 866 37 66",
    "sg:postcode":"7556",
    "sg:province":"Graubunden",
    "wof:name":"Priska Cotti Fisioterapia",
    "wof:placetype":"venue"
},
  "geometry": {"coordinates":[10.382900238,46.8344573975],"type":"Point"}
}