{
  "type": "Feature",
  "properties": {
    "iso:country":"CH",
    "sg:address":"Roteb\u00fcelweg",
    "sg:city":"Krattigen",
    "sg:classifiers":[
        {
            "category":"Mining & Drilling",
            "type":"Manufacturing & Wholesale Goods"
        }
    ],
    "sg:phone":"+41 33 654 89 49",
    "sg:postcode":"3704",
    "sg:province":"Bern",
    "sg:tags":[
        "test",
        "sondierbohrungen",
        "u"
    ],
    "wof:name":"Kohler Roland",
    "wof:placetype":"venue"
},
  "geometry": {"coordinates":[7.7385010719,46.6572532654],"type":"Point"}
}