{
  "type": "Feature",
  "properties": {
    "iso:country":"CH",
    "sg:city":"Surava",
    "sg:classifiers":[
        {
            "category":"Banks & Credit Unions",
            "subcategory":"Bank",
            "type":"Services"
        }
    ],
    "sg:phone":"+41 4181751436",
    "sg:postcode":"7456",
    "sg:province":"Graubunden",
    "wof:name":"Raiffeisenkasse",
    "wof:placetype":"venue"
},
  "geometry": {"coordinates":[9.64358,46.496971],"type":"Point"}
}