{
  "type": "Feature",
  "properties": {
    "iso:country":"CH",
    "sg:address":"Riedmattstrasse 22",
    "sg:city":"Wernetshausen",
    "sg:orig_category":"Sonstige Institutionen des Sozialwesens ohne Beherbergung",
    "sg:phone":"+41 19505331",
    "sg:postcode":"8342",
    "sg:province":"Z\u00fcrich",
    "wof:name":"Kirchlicher Verein F\u00fcr Jugendberatung",
    "wof:placetype":"venue"
},
  "geometry": {"coordinates":[8.862496376,47.2994003296],"type":"Point"}
}