{
  "type": "Feature",
  "properties": {
    "iso:country":"CH",
    "sg:address":"Viale Stazione 14 6500 Bellinzona Casella Postale 2444",
    "sg:city":"Bellinzona",
    "sg:orig_category":"Vermittlung von Immobilien Wirtschaftspr\u00fcfung, Steuerberatung U Treuhand",
    "sg:phone":"+41 91 825 25 45",
    "sg:postcode":"6500",
    "sg:province":"Ticino",
    "wof:name":"Reviamco Sa",
    "wof:placetype":"venue"
},
  "geometry": {"coordinates":[9.0241193771,46.1944618225],"type":"Point"}
}