{
  "type": "Feature",
  "properties": {
    "iso:country":"CH",
    "sg:address":"Hauptstrasse 57",
    "sg:city":"Einsiedeln",
    "sg:orig_category":"Detailhandel mit fotografischen Artikeln Fotografisches Gewerbe U fotografische Laboratorien",
    "sg:phone":"+41 61 711 28 11",
    "sg:postcode":"8840",
    "sg:province":"Schwyz",
    "wof:name":"Grahamer Josef",
    "wof:placetype":"venue"
},
  "geometry": {"coordinates":[7.5894579887,47.4934310913],"type":"Point"}
}