{
  "type": "Feature",
  "properties": {
    "iso:country":"CH",
    "sg:address":"6707",
    "sg:city":"Iragna",
    "sg:orig_category":"Gewinnung von Natursteinen f\u00fcr den Bau Herstellung von sonstigen Produkten aus nichtmetallischen Min",
    "sg:phone":"+41 24 471 21 22",
    "sg:postcode":"6707",
    "sg:province":"Ticino",
    "wof:name":"Gr\u00e8sval S\u00e0rl.",
    "wof:placetype":"venue"
},
  "geometry": {"coordinates":[6.9504208565,46.2534637451],"type":"Point"}
}