{
  "type": "Feature",
  "properties": {
    "iso:country":"CH",
    "sg:address":"Thundorgerstrasse 150",
    "sg:city":"Frauenfeld",
    "sg:orig_category":"Vorschulen, Kinderg\u00e4rten",
    "sg:phone":"+41 52 722 24 29",
    "sg:postcode":"8500",
    "sg:province":"Thurgau",
    "wof:name":"Kindergarten Huben",
    "wof:placetype":"venue"
},
  "geometry": {"coordinates":[8.9139003754,47.5445709229],"type":"Point"}
}