{
  "type": "Feature",
  "properties": {
    "iso:country":"CH",
    "sg:address":"Chemin Auguste-pidou 8",
    "sg:city":"Lausanne",
    "sg:orig_category":"Fachdetailhandel in Verkaufsr\u00e4umen Grosshandel mit Sportartikeln",
    "sg:phone":"+41 21 635 66 12",
    "sg:postcode":"1007",
    "sg:province":"Vaud",
    "wof:name":"Fast Distribution Sa",
    "wof:placetype":"venue"
},
  "geometry": {"coordinates":[6.6246728897,46.5094451904],"type":"Point"}
}