{
  "type": "Feature",
  "properties": {
    "iso:country":"CH",
    "sg:address":"Avenue Des Neuvilles 18",
    "sg:city":"Martigny",
    "sg:orig_category":"Wirtschaftspr\u00fcfung, Steuerberatung U Treuhand",
    "sg:phone":"+41 27 723 57 75",
    "sg:postcode":"1920",
    "sg:province":"Valais",
    "wof:name":"Octodure Consulting Sa",
    "wof:placetype":"venue"
},
  "geometry": {"coordinates":[7.081193924,46.101184845],"type":"Point"}
}