{
  "type": "Feature",
  "properties": {
    "iso:country":"CH",
    "sg:address":"Wiesstrasse 4",
    "sg:city":"Mollis",
    "sg:orig_category":"Unclassifiable Establishments",
    "sg:phone":"+41 79 413 07 76",
    "sg:postcode":"8753",
    "sg:province":"Glarus",
    "wof:name":"Ruedi Weiss",
    "wof:placetype":"venue"
},
  "geometry": {"coordinates":[9.0754365921,47.0886535645],"type":"Point"}
}