{
  "type": "Feature",
  "properties": {
    "iso:country":"CH",
    "sg:address":"Cossonay Route De 36b 1040 Echallens Case Postale 325",
    "sg:city":"Echallens",
    "sg:orig_category":"Unclassifiable Establishments",
    "sg:phone":"+41 21 881 46 69",
    "sg:postcode":"1040",
    "sg:province":"Vaud",
    "wof:name":"Agruplast S\u00e0rl",
    "wof:placetype":"venue"
},
  "geometry": {"coordinates":[6.6230587959,46.6416511536],"type":"Point"}
}