{
  "type": "Feature",
  "properties": {
    "iso:country":"CH",
    "sg:address":"Burghalden",
    "sg:city":"Fischenthal",
    "sg:orig_category":"Unternehmensberatung",
    "sg:phone":"+41 55 245 12 34",
    "sg:postcode":"8497",
    "sg:province":"Z\u00fcrich",
    "wof:name":"Thalmann Bruno, Textile Consulting",
    "wof:placetype":"venue"
},
  "geometry": {"coordinates":[8.9302120209,47.3432731628],"type":"Point"}
}