{
  "type": "Feature",
  "properties": {
    "iso:country":"CH",
    "sg:address":"Schlossstrasse 1",
    "sg:city":"M\u00fcnsingen",
    "sg:orig_category":"Interessenvertretungen",
    "sg:postcode":"3110",
    "sg:province":"Bern",
    "wof:name":"Stiftung F\u00fcr Betagte, Br\u00fcgg",
    "wof:placetype":"venue"
},
  "geometry": {"coordinates":[7.2785029411,47.1245613098],"type":"Point"}
}