{
  "type": "Feature",
  "properties": {
    "iso:country":"CH",
    "sg:address":"Falkenstrasse 5",
    "sg:city":"Bronschhofen",
    "sg:orig_category":"Grosshandel mit sonstigen Halbwaren",
    "sg:phone":"+41 91 612 24 24",
    "sg:postcode":"9552",
    "sg:province":"St. Gallen",
    "wof:name":"Neupack Produkte Ag",
    "wof:placetype":"venue"
},
  "geometry": {"coordinates":[7.8090510368,47.2483177185],"type":"Point"}
}