{
  "type": "Feature",
  "properties": {
    "iso:country":"CH",
    "sg:address":"Bramantino Via 1",
    "sg:city":"Locarno",
    "sg:orig_category":"Unclassifiable Establishments",
    "sg:postcode":"6600",
    "sg:province":"Ticino",
    "wof:name":"Goldinger Immobilien Treuhand St. Gallen Ag",
    "wof:placetype":"venue"
},
  "geometry": {"coordinates":[9.3146133423,47.4092216492],"type":"Point"}
}