{
  "type": "Feature",
  "properties": {
    "iso:country":"CH",
    "sg:address":"G\u00e4ssliacherweg 6",
    "sg:city":"Schafisheim",
    "sg:orig_category":"Informatikschulen",
    "sg:phone":"+41 16878151",
    "sg:postcode":"5503",
    "sg:province":"Aargau",
    "wof:name":"Michael Vontobel Wings Software",
    "wof:placetype":"venue"
},
  "geometry": {"coordinates":[8.7323598862,47.1966896057],"type":"Point"}
}