{
  "type": "Feature",
  "properties": {
    "iso:country":"CH",
    "sg:address":"Alte Buchserstrasse 11",
    "sg:city":"D\u00e4llikon",
    "sg:orig_category":"Gartenbau",
    "sg:phone":"+41 18440249",
    "sg:postcode":"8108",
    "sg:province":"Z\u00fcrich",
    "wof:name":"Emil Meier G\u00e4rtnerei",
    "wof:placetype":"venue"
},
  "geometry": {"coordinates":[8.4398145676,47.4429855347],"type":"Point"}
}