{
  "type": "Feature",
  "properties": {
    "addr:full":"Sagenstrasse 13 Ebikon Luzern 6030",
    "addr:housenumber":"13",
    "addr:postcode":"6030",
    "addr:street":"Sagenstrasse",
    "iso:country":"CH",
    "sg:address":"Sagenstrasse 13",
    "sg:city":"Ebikon",
    "sg:orig_category":"Allgemeiner Hoch U Tiefbau Sanit\u00e4rinstallation",
    "sg:phone":"+41 41 440 60 23",
    "sg:postcode":"6030",
    "sg:province":"Luzern",
    "wof:name":"Malis Eduard, Dipl. Ing. Eth Generalbauunternehmung",
    "wof:placetype":"venue"
},
  "geometry": {"coordinates":[8.339207,47.076694],"type":"Point"}
}