{
  "type": "Feature",
  "properties": {
    "iso:country":"CH",
    "sg:address":"Britternmatte Rinderbach",
    "sg:city":"R\u00fcegsbach",
    "sg:orig_category":"Detailhandel mit Waren verschiedener Art, Hauptrichtung Nahrungsmittel",
    "sg:phone":"+41 33 336 11 76",
    "sg:postcode":"3418",
    "sg:province":"Bern",
    "wof:name":"Hans Tribelhorn Lebensmittel",
    "wof:placetype":"venue"
},
  "geometry": {"coordinates":[7.6259498596,46.7172088623],"type":"Point"}
}