{
  "type": "Feature",
  "properties": {
    "iso:country":"CH",
    "sg:address":"Dorfstrasse 11 6442 Gersau. Postfach 106",
    "sg:city":"Gersau",
    "sg:classifiers":[
        {
            "category":"Travel",
            "subcategory":"Hotels & Motels",
            "type":"Entertainment"
        }
    ],
    "sg:phone":"+41 41 828 11 66",
    "sg:postcode":"6442",
    "sg:province":"Schwyz",
    "sg:tags":[
        "hotels",
        "mit",
        "restaurant"
    ],
    "wof:name":"Hotel Adler",
    "wof:placetype":"venue"
},
  "geometry": {"coordinates":[8.5269441605,46.991443634],"type":"Point"}
}