{
  "type": "Feature",
  "properties": {
    "iso:country":"CH",
    "sg:address":"Terrassenweg 17",
    "sg:city":"Ober\u00e4geri",
    "sg:orig_category":"Fachdetailhandel in Verkaufsr\u00e4umen",
    "sg:phone":"+41 41 750 44 75",
    "sg:postcode":"6315",
    "sg:province":"Zug",
    "wof:name":"Themis - Alpha Ag Generalunternehmung, Warenhandel Usw",
    "wof:placetype":"venue"
},
  "geometry": {"coordinates":[8.6243286133,47.1349525452],"type":"Point"}
}