{
  "type": "Feature",
  "properties": {
    "iso:country":"CH",
    "sg:address":"Rain 35 5000 Aarau. Postfach",
    "sg:city":"Aarau",
    "sg:orig_category":"Reiseb\u00fcros U Reiseveranstalter",
    "sg:postcode":"5000",
    "sg:province":"Aargau",
    "wof:name":"Nova Reisen, Paul W\u00e4lti, Filiale Aarau Vermittlung V. Reisen; Verwaltungen; Buchhaltungen",
    "wof:placetype":"venue"
},
  "geometry": {"coordinates":[8.043762207,47.3898506165],"type":"Point"}
}