{
  "type": "Feature",
  "properties": {
    "iso:country":"CH",
    "sg:address":"Reichsgasse 59 7000 Chur. Postfach 373",
    "sg:city":"Chur",
    "sg:orig_category":"Advokaturb\u00fcros",
    "sg:phone":"+41 81 254 38 88",
    "sg:postcode":"7002",
    "sg:province":"Graubunden",
    "wof:name":"Dr.guido J\u00f6rg Advokaturb\u00fcro",
    "wof:placetype":"venue"
},
  "geometry": {"coordinates":[9.532994,46.849094],"type":"Point"}
}