{
  "type": "Feature",
  "properties": {
    "iso:country":"CH",
    "sg:address":"M\u00fchlegasse 42a",
    "sg:city":"K\u00fcblis",
    "sg:orig_category":"Detailhandel mit Getr\u00e4nken G\u00fcterbef\u00f6rderung im Strassenverkehr",
    "sg:phone":"+41 55 293 32 32",
    "sg:postcode":"7240",
    "sg:province":"Graubunden",
    "wof:name":"K\u00fchne A. & Sohn Ag",
    "wof:placetype":"venue"
},
  "geometry": {"coordinates":[9.0052013397,47.1989440918],"type":"Point"}
}