{
  "type": "Feature",
  "properties": {
    "iso:country":"CH",
    "sg:address":"Rue Du 1er-mars 29",
    "sg:city":"Geneveys-coffrane",
    "sg:orig_category":"Nationale Postdienste",
    "sg:phone":"+41 32 857 16 44",
    "sg:postcode":"2206",
    "sg:province":"Neuch\u00e2tel",
    "wof:name":"La Poste Suisse",
    "wof:placetype":"venue"
},
  "geometry": {"coordinates":[6.8501930237,47.0146789551],"type":"Point"}
}