{
  "type": "Feature",
  "properties": {
    "iso:country":"CH",
    "sg:address":"Hirschengraben 41",
    "sg:city":"Luzern",
    "sg:orig_category":"Detailhandel mit Waren verschiedener Art, Hauptrichtung Nahrungsmittel",
    "sg:phone":"+41 41 240 55 71",
    "sg:postcode":"6003",
    "sg:province":"Luzern",
    "wof:name":"M Fundgrube Letzihof",
    "wof:placetype":"venue"
},
  "geometry": {"coordinates":[8.30148983,47.0501899719],"type":"Point"}
}