{
  "type": "Feature",
  "properties": {
    "iso:country":"CH",
    "sg:address":"Cortivallo Via 32 6900 Lugano. Postfach",
    "sg:city":"Lugano",
    "sg:orig_category":"Detailhandel mit B\u00fcchern, Zeitungen, Schreib U Papeteriewaren",
    "sg:postcode":"6900",
    "sg:province":"Ticino",
    "wof:name":"Fenice 2001 Sagl Edicole Ecc",
    "wof:placetype":"venue"
},
  "geometry": {"coordinates":[8.937223,46.005203],"type":"Point"}
}