{
  "type": "Feature",
  "properties": {
    "iso:country":"CH",
    "sg:address":"Quai Du Seujet 32",
    "sg:city":"Gen\u00e8ve",
    "sg:orig_category":"Detailhandel mit Lederwaren U Reiseartikeln",
    "sg:phone":"+41 22 731 31 75",
    "sg:postcode":"1201",
    "sg:province":"Gen\u00e8ve",
    "wof:name":"Jean-pierre Rollier Roselmar",
    "wof:placetype":"venue"
},
  "geometry": {"coordinates":[6.1337838173,46.2042236328],"type":"Point"}
}