{
  "type": "Feature",
  "properties": {
    "iso:country":"CH",
    "sg:address":"Fronwagplatz 10 Zum Schild 8200 Schaffhausen. Postfach 310",
    "sg:city":"Schaffhausen",
    "sg:orig_category":"Vermietung U Verpachtung von eigenen Immobilien",
    "sg:postcode":"8200",
    "sg:province":"Schaffhausen",
    "wof:name":"Immobilien Ag Zum Schild",
    "wof:placetype":"venue"
},
  "geometry": {"coordinates":[8.6315612793,47.6953048706],"type":"Point"}
}