{
  "type": "Feature",
  "properties": {
    "iso:country":"CH",
    "sg:address":"Repfergasse 17",
    "sg:city":"Schaffhausen",
    "sg:classifiers":[
        {
            "category":"Restaurant",
            "type":"Food & Drink"
        }
    ],
    "sg:phone":"+41 52 624 18 30",
    "sg:postcode":"8200",
    "sg:province":"Schaffhausen",
    "wof:name":"Snack-bar-tabu",
    "wof:placetype":"venue"
},
  "geometry": {"coordinates":[8.6357402802,47.6977119446],"type":"Point"}
}