{
  "type": "Feature",
  "properties": {
    "iso:country":"CH",
    "sg:address":"Obstgartenweg 3a",
    "sg:city":"Bertschikon",
    "sg:orig_category":"Malerei",
    "sg:phone":"+41 19352417",
    "sg:postcode":"8614",
    "sg:province":"Z\u00fcrich",
    "wof:name":"Gerold Tschochner Malergesch\u00e4ft",
    "wof:placetype":"venue"
},
  "geometry": {"coordinates":[8.7580785751,47.3242988586],"type":"Point"}
}