{
  "type": "Feature",
  "properties": {
    "iso:country":"CH",
    "sg:address":"Place De L'eglise 35",
    "sg:city":"V\u00e9troz",
    "sg:orig_category":"Grosshandel mit Getr\u00e4nken Rebbau",
    "sg:phone":"+41 27 346 34 91",
    "sg:postcode":"1963",
    "sg:province":"Valais",
    "wof:name":"Abbaye De V\u00e9troz Sa",
    "wof:placetype":"venue"
},
  "geometry": {"coordinates":[7.2825698853,46.2257385254],"type":"Point"}
}