{
  "type": "Feature",
  "properties": {
    "addr:full":"Holzgasse 6 8002 Z\u00fcrich. Postfach Z\u00fcrich Z\u00fcrich 8001",
    "addr:housenumber":"6",
    "addr:postcode":"8002 zuerich. postfach;8001",
    "addr:street":"Holzgasse",
    "iso:country":"CH",
    "sg:address":"Holzgasse 6 8002 Z\u00fcrich. Postfach",
    "sg:city":"Z\u00fcrich",
    "sg:orig_category":"Architektur U Ingenieurb\u00fcros",
    "sg:phone":"+41 12015684",
    "sg:postcode":"8001",
    "sg:province":"Z\u00fcrich",
    "wof:name":"M\u00fcller Andreas, Dipl. Architekt Eth, Architekturb\u00fcro Sia Architektur, S\u00e4dtebau, Design, Raumplanung, Usw",
    "wof:placetype":"venue"
},
  "geometry": {"coordinates":[8.530932,47.369621],"type":"Point"}
}