{
  "type": "Feature",
  "properties": {
    "iso:country":"CH",
    "sg:address":"Chaumontweg 9",
    "sg:city":"Lyss",
    "sg:orig_category":"Architekturb\u00fcros",
    "sg:phone":"+41 32 384 48 43",
    "sg:postcode":"3250",
    "sg:province":"Bern",
    "wof:name":"Ulrich Streit Architekturb\u00fcro",
    "wof:placetype":"venue"
},
  "geometry": {"coordinates":[7.314917,47.075909],"type":"Point"}
}