{
  "type": "Feature",
  "properties": {
    "addr:full":"Landstrasse 41 9494 Schaan. Postfach 91 Schaan 9494",
    "addr:housenumber":"41;91",
    "addr:postcode":"9494;9494",
    "addr:street":"Landstrasse;Postfach",
    "iso:country":"CH",
    "sg:address":"Landstrasse 41 9494 Schaan. Postfach 91",
    "sg:city":"Schaan",
    "sg:orig_category":"Detailhandel mit B\u00fcchern Detailhandel mit Schreib U Papeteriewaren",
    "sg:phone":"+41 27 973 17 81",
    "sg:postcode":"9494",
    "wof:name":"Hubert Zehner Papeterie Buchhandlung",
    "wof:placetype":"venue"
},
  "geometry": {"coordinates":[8.261838,46.486759],"type":"Point"}
}