{
  "type": "Feature",
  "properties": {
    "iso:country":"CH",
    "sg:address":"Hauptstrasse 1",
    "sg:city":"Balterswil",
    "sg:orig_category":"Sonstiger Grosshandel",
    "sg:phone":"+41 71 971 15 15",
    "sg:postcode":"8362",
    "sg:province":"Thurgau",
    "wof:name":"Br\u00fchwiler Maschinen Ag",
    "wof:placetype":"venue"
},
  "geometry": {"coordinates":[8.9310417175,47.4505500793],"type":"Point"}
}