{
  "type": "Feature",
  "properties": {
    "iso:country":"CH",
    "sg:address":"Bahnhofstrasse 168",
    "sg:city":"M\u00f6hlin",
    "sg:orig_category":"Grosshandel mit Holz U Bauelementen aus Holz Grosshandel mit Holz U Baustoffen",
    "sg:phone":"+41 61 851 57 51",
    "sg:postcode":"4313",
    "sg:province":"Aargau",
    "wof:name":"Holzparadies-holzhandel Gmbh",
    "wof:placetype":"venue"
},
  "geometry": {"coordinates":[7.8517308235,47.5525169373],"type":"Point"}
}