{
  "type": "Feature",
  "properties": {
    "iso:country":"CH",
    "sg:address":"8962",
    "sg:city":"Bergdietikon",
    "sg:orig_category":"Sportvereine Sch\u00fctzen",
    "sg:phone":"+41 56 631 78 73",
    "sg:postcode":"8962",
    "sg:province":"Aargau",
    "wof:name":"Sch\u00fctzengesellschaft",
    "wof:placetype":"venue"
},
  "geometry": {"coordinates":[8.382399559,47.3830795288],"type":"Point"}
}