{
  "type": "Feature",
  "properties": {
    "iso:country":"CH",
    "sg:address":"Weberstrasse 7",
    "sg:city":"Z\u00fcrich",
    "sg:orig_category":"Non-Classified Establishments",
    "sg:phone":"+41 31 332 88 44",
    "sg:postcode":"8004",
    "sg:province":"Z\u00fcrich",
    "wof:name":"G\u00fcnter Richter Energie-& Klimatechnik Zweigniederlassung",
    "wof:placetype":"venue"
},
  "geometry": {"coordinates":[7.4695868492,46.954788208],"type":"Point"}
}