{
  "type": "Feature",
  "properties": {
    "addr:full":"Av De Savoie 61 Vouvry Valais 1896",
    "addr:housenumber":"61",
    "addr:postcode":"1896",
    "addr:street":"Av De Savoie",
    "iso:country":"CH",
    "sg:address":"Av De Savoie 61",
    "sg:city":"Vouvry",
    "sg:classifiers":[
        {
            "category":"Manufacturing",
            "subcategory":"Rubber & Plastics",
            "type":"Manufacturing & Wholesale Goods"
        }
    ],
    "sg:phone":"+41 24 482 01 10",
    "sg:postcode":"1896",
    "sg:province":"Valais",
    "sg:tags":[
        "metallurgy",
        "pipe",
        "metalworking",
        "sheet"
    ],
    "wof:name":"Aisa Automation Industrielle Sa",
    "wof:placetype":"venue"
},
  "geometry": {"coordinates":[6.888772,46.343403],"type":"Point"}
}