{
  "type": "Feature",
  "properties": {
    "iso:country":"CH",
    "sg:address":"De-candolle Rue 20",
    "sg:city":"Gen\u00e8ve",
    "sg:orig_category":"Non-Classified Establishments",
    "sg:postcode":"1205",
    "sg:province":"Gen\u00e8ve",
    "wof:name":"Caroll International Suisse",
    "wof:placetype":"venue"
},
  "geometry": {"coordinates":[6.145154953,46.197845459],"type":"Point"}
}