{
  "type": "Feature",
  "properties": {
    "iso:country":"CH",
    "sg:address":"Rebenstrasse 9",
    "sg:city":"Arbon",
    "sg:classifiers":[
        {
            "category":"Bars & Pubs",
            "type":"Food & Drink"
        }
    ],
    "sg:phone":"+41 41 670 27 21",
    "sg:postcode":"9320",
    "sg:province":"Thurgau",
    "wof:name":"Billard-pub",
    "wof:placetype":"venue"
},
  "geometry": {"coordinates":[8.270891,46.94165],"type":"Point"}
}