{
  "type": "Feature",
  "properties": {
    "iso:country":"CH",
    "sg:address":"Carouge Rue De 57 1205 Gen\u00e8ve. Postfach",
    "sg:city":"Gen\u00e8ve",
    "sg:orig_category":"Grosshandel mit Textilien",
    "sg:postcode":"1205",
    "sg:province":"Gen\u00e8ve",
    "wof:name":"Mod Azur Sa",
    "wof:placetype":"venue"
},
  "geometry": {"coordinates":[6.1440792084,46.1927146912],"type":"Point"}
}