{
  "type": "Feature",
  "properties": {
    "iso:country":"CH",
    "sg:address":"Baarerstrasse 23",
    "sg:city":"Zug",
    "sg:orig_category":"Detailhandel mit Geschenkartikeln U Souvenirs Fachdetailhandel in Verkaufsr\u00e4umen",
    "sg:phone":"+41 27 957 20 17",
    "sg:postcode":"6300",
    "sg:province":"Zug",
    "wof:name":"Adelbert Zurbriggen Geschenk-boutique",
    "wof:placetype":"venue"
},
  "geometry": {"coordinates":[7.9367241859,46.1232452393],"type":"Point"}
}