{
  "type": "Feature",
  "properties": {
    "iso:country":"CH",
    "sg:address":"Fimmelsberg",
    "sg:city":"Bissegg",
    "sg:classifiers":[
        {
            "category":"Restaurant",
            "type":"Food & Drink"
        }
    ],
    "sg:phone":"+41 71 651 11 53",
    "sg:postcode":"8514",
    "sg:province":"Thurgau",
    "wof:name":"Restaurant Frohsinn",
    "wof:placetype":"venue"
},
  "geometry": {"coordinates":[9.0454864502,47.5620269775],"type":"Point"}
}