{
  "type": "Feature",
  "properties": {
    "iso:country":"CH",
    "sg:address":"Bahnhofstrasse 10",
    "sg:city":"Oensingen",
    "sg:orig_category":"Unclassifiable Establishments",
    "sg:postcode":"4702",
    "sg:province":"Solothurn",
    "wof:name":"Roger Gugelmann",
    "wof:placetype":"venue"
},
  "geometry": {"coordinates":[7.7081408501,47.2856216431],"type":"Point"}
}