{
  "type": "Feature",
  "properties": {
    "iso:country":"CH",
    "sg:address":"Industriestrasse 28",
    "sg:city":"Wittenbach",
    "sg:orig_category":"Herstellung von sonstigen organischen Grundstoffen U Chemikalien",
    "sg:phone":"+41 71 298 17 77",
    "sg:postcode":"9303",
    "wof:name":"Boss Chemie Ag",
    "wof:placetype":"venue"
},
  "geometry": {"coordinates":[9.3932647705,47.4628143311],"type":"Point"}
}