{
  "type": "Feature",
  "properties": {
    "iso:country":"CH",
    "sg:address":"Klosterstrasse 8",
    "sg:city":"Engelberg",
    "sg:orig_category":"Fachdetailhandel in Verkaufsr\u00e4umen",
    "sg:postcode":"6390",
    "sg:province":"Obwalden",
    "wof:name":"Arndt-sport",
    "wof:placetype":"venue"
},
  "geometry": {"coordinates":[8.4057998657,46.8203277588],"type":"Point"}
}