{
  "type": "Feature",
  "properties": {
    "iso:country":"CH",
    "sg:address":"Rue Des Tilleuls 19",
    "sg:city":"Geneveys-coffrane",
    "sg:orig_category":"Grosshandel mit sonstigen Nahrungsmitteln",
    "sg:postcode":"2206",
    "sg:province":"Neuch\u00e2tel",
    "wof:name":"Simeoni Pierre-poissonnerie Du Littoral",
    "wof:placetype":"venue"
},
  "geometry": {"coordinates":[6.8532118797,47.0137176514],"type":"Point"}
}