{
  "type": "Feature",
  "properties": {
    "iso:country":"CH",
    "sg:address":"Bvd Georges-favon 7 1200 Genf. Postfach",
    "sg:city":"Gen\u00e8ve",
    "sg:orig_category":"Unclassifiable Establishments",
    "sg:postcode":"1204",
    "sg:province":"Gen\u00e8ve",
    "wof:name":"Si 65 Chemin De La Montagne",
    "wof:placetype":"venue"
},
  "geometry": {"coordinates":[6.1401891708,46.2032012939],"type":"Point"}
}