{
  "type": "Feature",
  "properties": {
    "iso:country":"CH",
    "sg:address":"Place Du Cirque 3",
    "sg:city":"Gen\u00e8ve",
    "sg:orig_category":"Wirtschaftspr\u00fcfung, Steuerberatung U Treuhand",
    "sg:phone":"+41 22 320 40 36",
    "sg:postcode":"1204",
    "sg:province":"Gen\u00e8ve",
    "wof:name":"La Loupe, Soci\u00e9t\u00e9 Fiduciaire Sarl",
    "wof:placetype":"venue"
},
  "geometry": {"coordinates":[6.1401247978,46.2014808655],"type":"Point"}
}