{
  "type": "Feature",
  "properties": {
    "iso:country":"CH",
    "sg:address":"3065",
    "sg:city":"Bolligen",
    "sg:orig_category":"F\u00fcrsorge\u00e4mter",
    "sg:phone":"+41 71 463 31 22",
    "sg:postcode":"3065",
    "sg:province":"Bern",
    "wof:name":"F\u00fcrsorgeamt &-kommission",
    "wof:placetype":"venue"
},
  "geometry": {"coordinates":[9.3788089752,47.5655593872],"type":"Point"}
}