{
  "type": "Feature",
  "properties": {
    "iso:country":"CH",
    "sg:address":"Scheidgasse 2",
    "sg:city":"K\u00f6lliken",
    "sg:orig_category":"Herstellung von Teppichen Verlegen von Fussboden",
    "sg:phone":"+41 62 723 40 89",
    "sg:postcode":"5742",
    "sg:province":"Aargau",
    "wof:name":"Antonio Mazzara Bodenbel\u00e4ge",
    "wof:placetype":"venue"
},
  "geometry": {"coordinates":[8.0241537094,47.3333854675],"type":"Point"}
}