{
  "type": "Feature",
  "properties": {
    "iso:country":"CH",
    "sg:address":"Strada Ponte Di Valle",
    "sg:city":"Davesco-soragno",
    "sg:orig_category":"Autogaragen",
    "sg:phone":"+41 91 942 85 69",
    "sg:postcode":"6964",
    "sg:province":"Ticino",
    "wof:name":"Roma Racing Sagl Garage",
    "wof:placetype":"venue"
},
  "geometry": {"coordinates":[8.978402,46.039158],"type":"Point"}
}