{
  "type": "Feature",
  "properties": {
    "iso:country":"CH",
    "sg:address":"General Wille-strasse 10",
    "sg:city":"Z\u00fcrich",
    "sg:orig_category":"Unclassifiable Establishments",
    "sg:postcode":"8002",
    "sg:province":"Z\u00fcrich",
    "wof:name":"Park Lane Racing Ag",
    "wof:placetype":"venue"
},
  "geometry": {"coordinates":[8.5333032608,47.3635520935],"type":"Point"}
}