{
  "type": "Feature",
  "properties": {
    "iso:country":"CH",
    "sg:address":"Avenue C.-f.-ramuz 92",
    "sg:city":"Pully",
    "sg:orig_category":"Herstellung von Schreibwaren U B\u00fcrobedarf aus Papier, Karton U Pappe",
    "sg:phone":"+41 21 728 78 31",
    "sg:postcode":"1009",
    "sg:province":"Vaud",
    "wof:name":"Bourcart Jean",
    "wof:placetype":"venue"
},
  "geometry": {"coordinates":[6.6424298286,46.5097389221],"type":"Point"}
}