{
  "type": "Feature",
  "properties": {
    "iso:country":"CH",
    "sg:address":"7452",
    "sg:city":"Cunter",
    "sg:orig_category":"Abwasserreinigung",
    "sg:phone":"+41 27 952 22 53",
    "sg:postcode":"7452",
    "sg:province":"Graubunden",
    "wof:name":"Ara Stalden-staldenried- T\u00f6rbel-zeneggen",
    "wof:placetype":"venue"
},
  "geometry": {"coordinates":[7.86643,46.231522],"type":"Point"}
}