{
  "type": "Feature",
  "properties": {
    "iso:country":"CH",
    "sg:address":"2900",
    "sg:city":"Porrentruy",
    "sg:orig_category":"Vorschulen, Kinderg\u00e4rten",
    "sg:phone":"+41 32 926 86 69",
    "sg:postcode":"2900",
    "sg:province":"Jura",
    "wof:name":"Ecole Enfantine Coll\u00e8ge Cernil-antoine",
    "wof:placetype":"venue"
},
  "geometry": {"coordinates":[6.8146128654,47.0966491699],"type":"Point"}
}