{
  "type": "Feature",
  "properties": {
    "iso:country":"CH",
    "sg:address":"Ergolzstrasse 14",
    "sg:city":"Gelterkinden",
    "sg:orig_category":"Zahnarztpraxen",
    "sg:phone":"+41 61 421 82 84",
    "sg:postcode":"4460",
    "sg:province":"Basel-Landschaft",
    "wof:name":"Dr. Med. Dent. Andreas Seitz Zahnarzt",
    "wof:placetype":"venue"
},
  "geometry": {"coordinates":[7.856192112,47.4661865234],"type":"Point"}
}