{
  "type": "Feature",
  "properties": {
    "iso:country":"CH",
    "sg:address":"Hinterdorfstrasse 3b 8309 N\u00fcrensdorf. Postfach",
    "sg:city":"N\u00fcrensdorf",
    "sg:orig_category":"Instandhaltung U Reparatur von Automobilen",
    "sg:postcode":"8309",
    "sg:province":"Z\u00fcrich",
    "wof:name":"Rtec Sport Tuning, Gerl R.",
    "wof:placetype":"venue"
},
  "geometry": {"coordinates":[8.6480150223,47.4470176697],"type":"Point"}
}