{
  "type": "Feature",
  "properties": {
    "addr:full":"Hardstrasse 2 Lenzburg Aargau 5600",
    "addr:housenumber":"2",
    "addr:postcode":"5600",
    "addr:street":"Hardstrasse",
    "iso:country":"CH",
    "sg:address":"Hardstrasse 2",
    "sg:city":"Lenzburg",
    "sg:classifiers":[
        {
            "category":"Manufacturing",
            "subcategory":"Wood Products",
            "type":"Manufacturing & Wholesale Goods"
        }
    ],
    "sg:phone":"+41 32 926 95 95",
    "sg:postcode":"5600",
    "sg:province":"Aargau",
    "sg:tags":[
        "tool",
        "carbide",
        "working"
    ],
    "wof:name":"Michael Weinig S.a.",
    "wof:placetype":"venue"
},
  "geometry": {"coordinates":[6.83984,47.115108],"type":"Point"}
}