{
  "type": "Feature",
  "properties": {
    "addr:full":"Chaumontweg 2 Lyss Bern 3250",
    "addr:housenumber":"2",
    "addr:postcode":"3250",
    "addr:street":"Chaumontweg;Bern",
    "iso:country":"CH",
    "sg:address":"Chaumontweg 2",
    "sg:city":"Lyss",
    "sg:orig_category":"Allgemeinbildende weiterf\u00fchrende Schulen Sonderschulen",
    "sg:phone":"+41 32 384 45 44",
    "sg:postcode":"3250",
    "sg:province":"Bern",
    "wof:name":"Stiftung Heilp\u00e4dagogische Schule Lyss",
    "wof:placetype":"venue"
},
  "geometry": {"coordinates":[7.315268,47.076481],"type":"Point"}
}