{
  "type": "Feature",
  "properties": {
    "iso:country":"CH",
    "sg:address":"Via San Gottardo 26",
    "sg:city":"Lugano",
    "sg:orig_category":"Vermietung U Verpachtung von eigenen Immobilien",
    "sg:phone":"+41 91 923 49 25",
    "sg:postcode":"6900",
    "sg:province":"Ticino",
    "wof:name":"Holiday Hotel Select Sa",
    "wof:placetype":"venue"
},
  "geometry": {"coordinates":[8.9468984604,46.0074195862],"type":"Point"}
}