{
  "type": "Feature",
  "properties": {
    "iso:country":"CH",
    "sg:address":"Bahnhofstrasse 67",
    "sg:city":"Wettingen",
    "sg:classifiers":[
        {
            "category":"Insurance",
            "subcategory":"Insurance Agent",
            "type":"Services"
        }
    ],
    "sg:phone":"+41 91 945 32 34",
    "sg:postcode":"5430",
    "sg:province":"Aargau",
    "sg:tags":[
        "versicherungsagenturen",
        "-broker"
    ],
    "wof:name":"Nando Bozzini Consulenze Assicurative",
    "wof:placetype":"venue"
},
  "geometry": {"coordinates":[8.9522676468,46.0581092834],"type":"Point"}
}