{
  "type": "Feature",
  "properties": {
    "iso:country":"CH",
    "sg:address":"Hegibergstrasse 111",
    "sg:city":"Trimbach",
    "sg:orig_category":"Non-Classified Establishments",
    "sg:postcode":"4632",
    "sg:province":"Solothurn",
    "wof:name":"D.code Gmbh",
    "wof:placetype":"venue"
},
  "geometry": {"coordinates":[7.9008989334,47.3675193787],"type":"Point"}
}