{
  "type": "Feature",
  "properties": {
    "iso:country":"CH",
    "sg:address":"Rappenhalde 16",
    "sg:city":"Effretikon",
    "sg:orig_category":"Grosshandel mit elektrischen Haushaltsger\u00e4ten, Radio U Fernsehger\u00e4ten",
    "sg:phone":"+41 52 343 57 83",
    "sg:postcode":"8307",
    "sg:province":"Z\u00fcrich",
    "wof:name":"Sik Gmbh",
    "wof:placetype":"venue"
},
  "geometry": {"coordinates":[8.6980371475,47.4214668274],"type":"Point"}
}