{
  "type": "Feature",
  "properties": {
    "iso:country":"CH",
    "sg:address":"Avenue Du Grey 40",
    "sg:city":"Lausanne",
    "sg:classifiers":[
        {
            "category":"Government",
            "subcategory":"Fire Station",
            "type":"Public Place"
        }
    ],
    "sg:phone":"+41 21 624 72 40",
    "sg:postcode":"1004",
    "sg:province":"Vaud",
    "sg:tags":[
        "insulation",
        "drying",
        "flat-roof"
    ],
    "wof:name":"Jean Meyer Sa",
    "wof:placetype":"venue"
},
  "geometry": {"coordinates":[6.6206851006,46.5338401794],"type":"Point"}
}