{
  "type": "Feature",
  "properties": {
    "iso:country":"CH",
    "sg:address":"Le Bey",
    "sg:city":"Montagny-yverdon",
    "sg:orig_category":"Instandhaltung U Reparatur von Automobilen",
    "sg:phone":"+41 32 968 35 80",
    "sg:postcode":"1442",
    "sg:province":"Vaud",
    "wof:name":"Fr\u00e9d\u00e9ric Winkelmann Fils Garage Du Puits",
    "wof:placetype":"venue"
},
  "geometry": {"coordinates":[6.8321008682,47.1054649353],"type":"Point"}
}