{
  "type": "Feature",
  "properties": {
    "iso:country":"CH",
    "sg:address":"Verrerie Rue De La 5a",
    "sg:city":"Monthey",
    "sg:orig_category":"Detailhandel mit M\u00f6beln U Haushaltsgegenst\u00e4nden",
    "sg:phone":"+41 24 499 21 88",
    "sg:postcode":"1870",
    "sg:province":"Valais",
    "wof:name":"Boutique Velum, Danielle Paratte",
    "wof:placetype":"venue"
},
  "geometry": {"coordinates":[6.9471468925,46.2516288757],"type":"Point"}
}