{
  "type": "Feature",
  "properties": {
    "iso:country":"CH",
    "sg:address":"Bahnhofstr. 244",
    "sg:city":"Dagmersellen",
    "sg:orig_category":"Interessenvertretungen",
    "sg:postcode":"6252",
    "sg:province":"Luzern",
    "wof:name":"Wechsler Katharina-stiftung.",
    "wof:placetype":"venue"
},
  "geometry": {"coordinates":[7.9796199799,47.2184791565],"type":"Point"}
}