{
  "type": "Feature",
  "properties": {
    "iso:country":"CH",
    "sg:address":"Bubikonerstrasse 1",
    "sg:city":"D\u00fcrnten",
    "sg:classifiers":[
        {
            "category":"Insurance",
            "subcategory":"Insurance Agent",
            "type":"Services"
        }
    ],
    "sg:phone":"+41 55 240 51 80",
    "sg:postcode":"8635",
    "sg:province":"Z\u00fcrich",
    "sg:tags":[
        "versicherungsagenturen",
        "-broker"
    ],
    "wof:name":"Winterthur-leben Agentur",
    "wof:placetype":"venue"
},
  "geometry": {"coordinates":[8.841714859,47.2774391174],"type":"Point"}
}