{
  "type": "Feature",
  "properties": {
    "iso:country":"CH",
    "sg:address":"Le Muveran 1884 Villars-sur-ollon. Postfach",
    "sg:city":"Villars-sur-ollon",
    "sg:orig_category":"Vermietung U Verpachtung von eigenen Immobilien",
    "sg:postcode":"1884",
    "sg:province":"Vaud",
    "wof:name":"Abv Analyse Beratung Vermittlung Gmbh",
    "wof:placetype":"venue"
},
  "geometry": {"coordinates":[7.7464680672,46.3153152466],"type":"Point"}
}