{
  "type": "Feature",
  "properties": {
    "iso:country":"CH",
    "sg:address":"Spiegelbergstrasse 24",
    "sg:city":"Basel",
    "sg:orig_category":"Erwachsenenbildung U Unterricht",
    "sg:phone":"+41 61 333 10 20",
    "sg:postcode":"4059",
    "sg:province":"Basel-Stadt",
    "wof:name":"Management Und Schulungen Im Gesundheitswesen Ochsner Cornelia",
    "wof:placetype":"venue"
},
  "geometry": {"coordinates":[7.5963830948,47.5346565247],"type":"Point"}
}