{
  "type": "Feature",
  "properties": {
    "iso:country":"CH",
    "sg:address":"Hinterbergstrasse 2 8873 Amden. Postfach",
    "sg:city":"Amden",
    "sg:orig_category":"Kauf U Verkauf von Immobilien auf eigene Rechnung",
    "sg:postcode":"8873",
    "sg:province":"St. Gallen",
    "wof:name":"Ruestell Amden Ag",
    "wof:placetype":"venue"
},
  "geometry": {"coordinates":[9.142947197,47.1497421265],"type":"Point"}
}