{
  "type": "Feature",
  "properties": {
    "iso:country":"CH",
    "sg:address":"Obere Hauptstrasse 58 4665 Oftringen. Postfach",
    "sg:city":"Oftringen",
    "sg:orig_category":"Fussboden, Fliesen U Plattenlegerei, Tapeziererei",
    "sg:postcode":"4665",
    "sg:province":"Aargau",
    "wof:name":"Diva Parkett Und Bodenbelag Gmbh",
    "wof:placetype":"venue"
},
  "geometry": {"coordinates":[7.9443860054,47.2978591919],"type":"Point"}
}