{
  "type": "Feature",
  "properties": {
    "iso:country":"CH",
    "sg:address":"Vattel Rue Emer-de- 17",
    "sg:city":"Neuenburg",
    "sg:orig_category":"Verwaltung von Immobilien",
    "sg:postcode":"2000",
    "sg:province":"Neuch\u00e2tel",
    "wof:name":"Ocsid Sa",
    "wof:placetype":"venue"
},
  "geometry": {"coordinates":[6.9146580696,46.9933319092],"type":"Point"}
}