{
  "type": "Feature",
  "properties": {
    "iso:country":"CH",
    "sg:address":"Fabrikstrasse 27",
    "sg:city":"Grabs",
    "sg:orig_category":"Herstellung von Drahtwaren",
    "sg:phone":"+41 41 875 38 00",
    "sg:postcode":"9472",
    "sg:province":"St. Gallen",
    "wof:name":"Kaved Ag",
    "wof:placetype":"venue"
},
  "geometry": {"coordinates":[8.6461086273,46.8775749207],"type":"Point"}
}