{
  "type": "Feature",
  "properties": {
    "iso:country":"CH",
    "sg:address":"Buchenweg 4",
    "sg:city":"W\u00e4ngi",
    "sg:orig_category":"Hardwareberatung Softwareentwicklung U beratung",
    "sg:phone":"+41 52 366 45 20",
    "sg:postcode":"9545",
    "sg:province":"Thurgau",
    "wof:name":"Welcom Consulting Ag",
    "wof:placetype":"venue"
},
  "geometry": {"coordinates":[8.9530677795,47.502117157],"type":"Point"}
}