{
  "type": "Feature",
  "properties": {
    "iso:country":"CH",
    "sg:address":"Wiler Strasse 135",
    "sg:city":"Lichtensteig",
    "sg:orig_category":"Organisationen des Gesundheitswesen",
    "sg:phone":"+41 71 988 27 67",
    "sg:postcode":"9620",
    "sg:province":"St. Gallen",
    "wof:name":"Samariterverein Wattwil",
    "wof:placetype":"venue"
},
  "geometry": {"coordinates":[9.0877408981,47.3240470886],"type":"Point"}
}