{
  "type": "Feature",
  "properties": {
    "iso:country":"CH",
    "sg:address":"Von Roll-strasse 24",
    "sg:city":"Olten",
    "sg:orig_category":"Herstellung von Elektrizit\u00e4tsverteilungs U schalteinrichtungen",
    "sg:phone":"+41 61 272 40 44",
    "sg:postcode":"4600",
    "sg:province":"Solothurn",
    "wof:name":"Markasub Ag",
    "wof:placetype":"venue"
},
  "geometry": {"coordinates":[7.9081258774,47.3473167419],"type":"Point"}
}