{
  "type": "Feature",
  "properties": {
    "iso:country":"CH",
    "sg:address":"Rue Du Simplon 7",
    "sg:city":"Lausanne",
    "sg:classifiers":[
        {
            "category":"Restaurant",
            "type":"Food & Drink"
        }
    ],
    "sg:phone":"+41 21 616 38 22",
    "sg:postcode":"1006",
    "sg:province":"Vaud",
    "wof:name":"Caf\u00e9 Les Trois Rois",
    "wof:placetype":"venue"
},
  "geometry": {"coordinates":[6.6308732033,46.5155754089],"type":"Point"}
}