{
  "type": "Feature",
  "properties": {
    "iso:country":"CH",
    "sg:address":"Brunnackerstrasse 2",
    "sg:city":"Ipsach",
    "sg:orig_category":"Sonstige mit der Informatik verbundene T\u00e4tigkeiten",
    "sg:postcode":"2563",
    "sg:province":"Bern",
    "wof:name":"Teda Treuhandb\u00fcro - Edv-beratungen, Egger Thierry",
    "wof:placetype":"venue"
},
  "geometry": {"coordinates":[7.2343230247,47.1113166809],"type":"Point"}
}