{
  "type": "Feature",
  "properties": {
    "iso:country":"CH",
    "sg:address":"La Barraz",
    "sg:city":"Chermignon",
    "sg:orig_category":"Schlossereien",
    "sg:phone":"+41 79 213 27 09",
    "sg:postcode":"3971",
    "sg:province":"Valais",
    "wof:name":"Eric Lagger Serrurerie",
    "wof:placetype":"venue"
},
  "geometry": {"coordinates":[7.473965168,46.2884407043],"type":"Point"}
}