{
  "type": "Feature",
  "properties": {
    "iso:country":"CH",
    "sg:address":"Oberdorfstrasse 26",
    "sg:city":"Herisau",
    "sg:orig_category":"Detailhandel mit Uhren U Schmuck Herstellung von Schmuck, Gold U Silberschmiedwaren",
    "sg:phone":"+41 71 351 70 05",
    "sg:postcode":"9100",
    "sg:province":"Appenzell Ausserrhoden",
    "wof:name":"Atelier Brand Goldschmiede Ag",
    "wof:placetype":"venue"
},
  "geometry": {"coordinates":[9.2804918289,47.3850402832],"type":"Point"}
}