{
  "type": "Feature",
  "properties": {
    "iso:country":"CH",
    "sg:address":"Gibelinstrasse 25",
    "sg:city":"Solothurn",
    "sg:orig_category":"Herstellung von Besen U B\u00fcrsten",
    "sg:phone":"+41 32 621 48 26",
    "sg:postcode":"4500",
    "sg:province":"Solothurn",
    "wof:name":"Walther",
    "wof:placetype":"venue"
},
  "geometry": {"coordinates":[7.5257458687,47.2085266113],"type":"Point"}
}