{
  "type": "Feature",
  "properties": {
    "iso:country":"CH",
    "sg:address":"Rue De La Prairie",
    "sg:city":"Montmollin",
    "sg:orig_category":"Unclassifiable Establishments",
    "sg:postcode":"2205",
    "wof:name":"Muntanella Sa",
    "wof:placetype":"venue"
},
  "geometry": {"coordinates":[9.8381910324,46.4970664978],"type":"Point"}
}