{
  "type": "Feature",
  "properties": {
    "iso:country":"CH",
    "sg:address":"Europe Avenue De L' 53",
    "sg:city":"Monthey",
    "sg:orig_category":"Stukkateurgewerbe, Gipserei U Verputzerei",
    "sg:phone":"+41 24 471 99 40",
    "sg:postcode":"1870",
    "sg:province":"Valais",
    "wof:name":"Alain Alexandre",
    "wof:placetype":"venue"
},
  "geometry": {"coordinates":[6.9471402168,46.2516212463],"type":"Point"}
}