{
  "type": "Feature",
  "properties": {
    "iso:country":"CH",
    "sg:address":"Isenbachweg 28",
    "sg:city":"Breitenbach",
    "sg:orig_category":"Vereine Musik/Blasmusik",
    "sg:phone":"+41 61 781 15 54",
    "sg:postcode":"4226",
    "sg:province":"Solothurn",
    "wof:name":"Musikgesellschaft",
    "wof:placetype":"venue"
},
  "geometry": {"coordinates":[7.5523052216,47.4090118408],"type":"Point"}
}