{
  "type": "Feature",
  "properties": {
    "iso:country":"CH",
    "sg:address":"Rue Du Scex 2 1950 Sion Case Postale 37",
    "sg:city":"Sion",
    "sg:orig_category":"Advokaturb\u00fcros Notariate",
    "sg:phone":"+41 27 322 40 88",
    "sg:postcode":"1951",
    "sg:province":"Valais",
    "wof:name":"Bernard Ambord Etude D'avocat & Notaire",
    "wof:placetype":"venue"
},
  "geometry": {"coordinates":[7.362569,46.231602],"type":"Point"}
}