{
  "type": "Feature",
  "properties": {
    "iso:country":"CH",
    "sg:address":"Route De Bossey 20 1256 Troinex. Postfach",
    "sg:city":"Troinex",
    "sg:orig_category":"Detailhandel mit M\u00f6beln U Haushaltsgegenst\u00e4nden Gartenbau",
    "sg:phone":"+41 22 784 31 60",
    "sg:postcode":"1256",
    "sg:province":"Gen\u00e8ve",
    "wof:name":"Espaces Verts Entreprise Paysagiste",
    "wof:placetype":"venue"
},
  "geometry": {"coordinates":[6.1570339203,46.1602096558],"type":"Point"}
}