{
  "type": "Feature",
  "properties": {
    "iso:country":"CH",
    "sg:address":"Isenrietstr. 1",
    "sg:city":"M\u00f6nchaltorf",
    "sg:classifiers":[
        {
            "category":"Manufacturing",
            "subcategory":"Tools & Machinery",
            "type":"Manufacturing & Wholesale Goods"
        }
    ],
    "sg:phone":"+41 4119491666",
    "sg:postcode":"8617",
    "sg:province":"Z\u00fcrich",
    "sg:tags":[
        "metallurgy",
        "metalworking"
    ],
    "wof:name":"Werner Pfister Handels Ag",
    "wof:placetype":"venue"
},
  "geometry": {"coordinates":[8.7192249298,47.3012123108],"type":"Point"}
}