{
  "type": "Feature",
  "properties": {
    "addr:full":"Ch. De La P\u00e9pini\u00e8re 8 1212 Grand-lancy. Postfach Petit-lancy Gen\u00e8ve 1213",
    "addr:housenumber":"8",
    "addr:postcode":"1212;petit-lancy;1213",
    "addr:street":"Ch. De La Pe\u0301Pinie\u0300Re",
    "iso:country":"CH",
    "sg:address":"Ch. De La P\u00e9pini\u00e8re 8 1212 Grand-lancy. Postfach",
    "sg:city":"Petit-lancy",
    "sg:orig_category":"Architektur U Ingenieurb\u00fcros",
    "sg:phone":"+41 22 793 46 56",
    "sg:postcode":"1213",
    "sg:province":"Gen\u00e8ve",
    "wof:name":"Paul-andr\u00e9 Rey",
    "wof:placetype":"venue"
},
  "geometry": {"coordinates":[6.1205,46.182808],"type":"Point"}
}