{
  "type": "Feature",
  "properties": {
    "iso:country":"CH",
    "sg:address":"Via Arch Pisoni 16",
    "sg:city":"Ascona",
    "sg:orig_category":"Architektur U Ingenieurb\u00fcros",
    "sg:postcode":"6612",
    "sg:province":"Ticino",
    "wof:name":"Studio D'ingegneria Anastasi Dott.ing. Eth/sia/otia Giuliano",
    "wof:placetype":"venue"
},
  "geometry": {"coordinates":[8.775686,46.152866],"type":"Point"}
}