{
  "type": "Feature",
  "properties": {
    "iso:country":"CH",
    "sg:address":"Hohlstrasse 699 8048 Z\u00fcrich. Postfach",
    "sg:city":"Z\u00fcrich",
    "sg:orig_category":"Maler U Glasergewerbe",
    "sg:postcode":"8048",
    "sg:province":"Z\u00fcrich",
    "wof:name":"Huseini D. Maler- U. Gipserarbeiten",
    "wof:placetype":"venue"
},
  "geometry": {"coordinates":[8.4796619415,47.3909034729],"type":"Point"}
}