{
  "type": "Feature",
  "properties": {
    "iso:country":"CH",
    "sg:address":"Strada Regina 94",
    "sg:city":"Agno",
    "sg:orig_category":"Geb\u00e4ude, Wohnungsreinigung Reinigungsgewerbe",
    "sg:phone":"+41 27 323 75 24",
    "sg:postcode":"6982",
    "sg:province":"Ticino",
    "wof:name":"Iss Facility Services Sa",
    "wof:placetype":"venue"
},
  "geometry": {"coordinates":[7.3598861694,46.2263870239],"type":"Point"}
}