{
  "type": "Feature",
  "properties": {
    "addr:full":"Hauptgasse 1 Willisau Luzern 6130",
    "addr:housenumber":"1",
    "addr:postcode":"6130",
    "addr:street":"Hauptgasse",
    "iso:country":"CH",
    "sg:address":"Hauptgasse 1",
    "sg:city":"Willisau",
    "sg:orig_category":"Detailhandel mit Brot, Back U S\u00fcsswaren",
    "sg:phone":"+41 41 970 12 01",
    "sg:postcode":"6130",
    "sg:province":"Luzern",
    "wof:name":"Schwegler B\u00e4ckerei Gmbh",
    "wof:placetype":"venue"
},
  "geometry": {"coordinates":[7.991808,47.120785],"type":"Point"}
}