{
  "type": "Feature",
  "properties": {
    "iso:country":"CH",
    "sg:address":"Einsiedlerstrasse 24",
    "sg:city":"Horgen",
    "sg:orig_category":"Primarschulen",
    "sg:phone":"+41 17255100",
    "sg:postcode":"8810",
    "sg:province":"Z\u00fcrich",
    "wof:name":"Primarschule Tannenbach",
    "wof:placetype":"venue"
},
  "geometry": {"coordinates":[8.5838985443,47.2674713135],"type":"Point"}
}