{
  "type": "Feature",
  "properties": {
    "iso:country":"CH",
    "sg:address":"Engadinstrasse",
    "sg:city":"Susch",
    "sg:orig_category":"Vermietung U Verpachtung von eigenen Immobilien",
    "sg:postcode":"7542",
    "sg:province":"Graubunden",
    "wof:name":"Crusch-alba Susch Sa",
    "wof:placetype":"venue"
},
  "geometry": {"coordinates":[10.0803976059,46.7506256104],"type":"Point"}
}