{
  "type": "Feature",
  "properties": {
    "iso:country":"CH",
    "sg:address":"Landstrasse 104",
    "sg:city":"Wettingen",
    "sg:orig_category":"Softwareentwicklung U beratung",
    "sg:postcode":"5430",
    "sg:province":"Aargau",
    "wof:name":"It-land Gmbh",
    "wof:placetype":"venue"
},
  "geometry": {"coordinates":[8.3275060654,47.4653244019],"type":"Point"}
}