{
  "type": "Feature",
  "properties": {
    "iso:country":"CH",
    "sg:address":"B\u00e4chelweg 8",
    "sg:city":"Niederhasli",
    "sg:orig_category":"Sanit\u00e4r, Heizungs U L\u00fcftungsinstallation Sanit\u00e4rinstallation",
    "sg:phone":"+41 17840277",
    "sg:postcode":"8155",
    "sg:province":"Z\u00fcrich",
    "wof:name":"Hiestand & Co.",
    "wof:placetype":"venue"
},
  "geometry": {"coordinates":[8.7295503616,47.2018661499],"type":"Point"}
}