{
  "type": "Feature",
  "properties": {
    "iso:country":"CH",
    "sg:address":"Selnaustrasse 15 8002 Z\u00fcrich. Postfach",
    "sg:city":"Z\u00fcrich",
    "sg:orig_category":"Wirtschaftspr\u00fcfung, Steuerberatung U Treuhand",
    "sg:phone":"+41 12019050",
    "sg:postcode":"8039",
    "wof:name":"Lippuner W. & Co, Revisions, Treuhand- & Buchhaltungsgesellschaft, Nachf. Fasser & Leuenberger",
    "wof:placetype":"venue"
},
  "geometry": {"coordinates":[8.5321578979,47.3704147339],"type":"Point"}
}