{
  "type": "Feature",
  "properties": {
    "iso:country":"CH",
    "sg:address":"Jura Rue Du 13",
    "sg:city":"Gland",
    "sg:orig_category":"Reiseb\u00fcros U Reiseveranstalter",
    "sg:postcode":"1196",
    "sg:province":"Vaud",
    "wof:name":"Wasserchraft Gbmh",
    "wof:placetype":"venue"
},
  "geometry": {"coordinates":[9.267829895,46.8157691956],"type":"Point"}
}