{
  "type": "Feature",
  "properties": {
    "iso:country":"CH",
    "sg:address":"Gaisgass 6",
    "sg:city":"Rheineck",
    "sg:orig_category":"Unclassifiable Establishments",
    "sg:postcode":"9424",
    "sg:province":"St. Gallen",
    "wof:name":"Bushbear Ag",
    "wof:placetype":"venue"
},
  "geometry": {"coordinates":[9.1025400162,47.4770584106],"type":"Point"}
}