{
  "type": "Feature",
  "properties": {
    "iso:country":"CH",
    "sg:address":"Rue Arthur Parchet 6",
    "sg:city":"Vouvry",
    "sg:orig_category":"Detailhandel mit Fleisch U Fleischwaren",
    "sg:phone":"+41 24 481 14 44",
    "sg:postcode":"1896",
    "sg:province":"Valais",
    "wof:name":"Frauchiger Ernest",
    "wof:placetype":"venue"
},
  "geometry": {"coordinates":[6.8907160759,46.3365974426],"type":"Point"}
}