{
  "type": "Feature",
  "properties": {
    "iso:country":"CH",
    "sg:address":"St. Jakobs-Strasse 96",
    "sg:city":"Basel",
    "sg:classifiers":[
        {
            "category":"Professional",
            "subcategory":"Computer Services",
            "type":"Services"
        }
    ],
    "sg:postcode":"4052",
    "sg:tags":[
        "library",
        "libraries",
        "archives",
        "museums",
        "bibliographic-information",
        "bibliographic-records",
        "cataloging",
        "ill",
        "inter-library-loan",
        "metadata",
        "book-data"
    ],
    "sg:website":"http://www.oclc.org/",
    "wof:name":"OCLC",
    "wof:placetype":"venue"
},
  "geometry": {"coordinates":[7.6015152,47.5459945],"type":"Point"}
}