{
  "type": "Feature",
  "properties": {
    "iso:country":"CH",
    "sg:address":"Schaffhauserstrasse 10",
    "sg:city":"Z\u00fcrich",
    "sg:orig_category":"Kosmetikinstitute",
    "sg:phone":"+41 13636336",
    "sg:postcode":"8006",
    "sg:province":"Z\u00fcrich",
    "wof:name":"Colony, Rubli-braun Susi",
    "wof:placetype":"venue"
},
  "geometry": {"coordinates":[8.539191246,47.3887252808],"type":"Point"}
}