{
  "type": "Feature",
  "properties": {
    "iso:country":"CH",
    "sg:address":"Weiermattstrasse 3",
    "sg:city":"Bottenwil",
    "sg:orig_category":"Instandhaltung U Reparatur von Automobilen",
    "sg:phone":"+41 52 385 50 81",
    "sg:postcode":"4814",
    "sg:province":"Aargau",
    "wof:name":"Steven's Garage Gmbh Autogarage Mit Reparaturwerkst\u00e4tte, Motorfahrzeughandel",
    "wof:placetype":"venue"
},
  "geometry": {"coordinates":[8.8512887955,47.4170532227],"type":"Point"}
}