{
  "type": "Feature",
  "properties": {
    "iso:country":"CH",
    "sg:address":"Gyrischachen",
    "sg:city":"Burgdorf",
    "sg:orig_category":"Grosshandel mit Nahrungsmitteln, Getr\u00e4nken U Tabakwaren ohne ausgepr\u00e4gten Schwerpunkt",
    "sg:postcode":"3400",
    "sg:province":"Bern",
    "wof:name":"Imhof Ch.",
    "wof:placetype":"venue"
},
  "geometry": {"coordinates":[7.6296749115,47.0638542175],"type":"Point"}
}