{
  "type": "Feature",
  "properties": {
    "iso:country":"CH",
    "sg:address":"Bahnhofstrasse 30",
    "sg:city":"Biel/bienne",
    "sg:orig_category":"Kinos",
    "sg:postcode":"2505",
    "sg:province":"Bern",
    "wof:name":"Cinevital Ag",
    "wof:placetype":"venue"
},
  "geometry": {"coordinates":[7.2451071739,47.1352806091],"type":"Point"}
}