{
  "type": "Feature",
  "properties": {
    "iso:country":"CH",
    "sg:address":"Dorfstrasse 67",
    "sg:city":"Kleinl\u00fctzel",
    "sg:orig_category":"Erbringung von sonstigen Dienstleistungen f\u00fcr Unterhaltung, Erholung U Freizeit Sonstige Hilfsdienst",
    "sg:phone":"+41 81 833 62 70",
    "sg:postcode":"4245",
    "sg:province":"Solothurn",
    "wof:name":"Engel's Inn Musik",
    "wof:placetype":"venue"
},
  "geometry": {"coordinates":[9.8375387192,46.4845733643],"type":"Point"}
}