{
  "type": "Feature",
  "properties": {
    "iso:country":"CH",
    "sg:address":"Pont Rue Du 35",
    "sg:city":"Montreux",
    "sg:orig_category":"Rechtsberatung",
    "sg:phone":"+41 32 968 46 46",
    "sg:postcode":"1820",
    "sg:province":"Vaud",
    "wof:name":"Andr\u00e9 Perret Conseils Juridiques",
    "wof:placetype":"venue"
},
  "geometry": {"coordinates":[6.8304710388,47.1052627563],"type":"Point"}
}