{
  "type": "Feature",
  "properties": {
    "iso:country":"CH",
    "sg:address":"Burgenrain",
    "sg:city":"Villnachern",
    "sg:orig_category":"Hoch U Tiefbau Personal U Stellenvermittlung",
    "sg:phone":"+41 56 460 80 91",
    "sg:postcode":"5213",
    "sg:province":"Aargau",
    "wof:name":"Faoro Ag",
    "wof:placetype":"venue"
},
  "geometry": {"coordinates":[8.1665916443,47.4714584351],"type":"Point"}
}