{
  "type": "Feature",
  "properties": {
    "iso:country":"CH",
    "sg:address":"B\u00e4ndlistrasse 31",
    "sg:city":"Z\u00fcrich",
    "sg:orig_category":"Sonstiger Grosshandel",
    "sg:phone":"+41 43 311 99 35",
    "sg:postcode":"8064",
    "sg:province":"Z\u00fcrich",
    "wof:name":"Makrys Gmbh",
    "wof:placetype":"venue"
},
  "geometry": {"coordinates":[8.4862709045,47.395778656],"type":"Point"}
}