{
  "type": "Feature",
  "properties": {
    "iso:country":"CH",
    "sg:address":"Landstrasse 19",
    "sg:city":"Kaiseraugst",
    "sg:orig_category":"Vermietung U Verpachtung von eigenen Immobilien Vermittlung von Immobilien",
    "sg:phone":"+41 61 811 67 25",
    "sg:postcode":"4303",
    "sg:province":"Aargau",
    "wof:name":"Immoka Immobilien Ag",
    "wof:placetype":"venue"
},
  "geometry": {"coordinates":[7.7216949463,47.5368080139],"type":"Point"}
}