{
  "type": "Feature",
  "properties": {
    "iso:country":"CH",
    "sg:address":"Savoie Rue Louis De 45 1110 Morges. Postfach",
    "sg:city":"Morges",
    "sg:orig_category":"Unclassifiable Establishments",
    "sg:postcode":"1110",
    "sg:province":"Vaud",
    "wof:name":"Le Savoie Tabacs, Dugravot Tabacs, Journaux Etc.; Commerce",
    "wof:placetype":"venue"
},
  "geometry": {"coordinates":[6.4990549088,46.5085792542],"type":"Point"}
}