{
  "type": "Feature",
  "properties": {
    "iso:country":"CH",
    "sg:address":"Truttikerstrasse 28",
    "sg:city":"Ossingen",
    "sg:orig_category":"Sportvereine Turnen Vereine Damen",
    "sg:phone":"+41 52 317 04 81",
    "sg:postcode":"8475",
    "sg:province":"Z\u00fcrich",
    "wof:name":"Damen-& Frauenriege Ossingen",
    "wof:placetype":"venue"
},
  "geometry": {"coordinates":[8.7263345718,47.6136627197],"type":"Point"}
}