{
  "type": "Feature",
  "properties": {
    "iso:country":"CH",
    "sg:address":"Im Heuried 74",
    "sg:city":"Z\u00fcrich",
    "sg:orig_category":"Grosshandel mit Obst U Gem\u00fcse",
    "sg:postcode":"8055",
    "sg:province":"Z\u00fcrich",
    "wof:name":"Duriska Milan, Fr\u00fcchte Und Gem\u00fcse",
    "wof:placetype":"venue"
},
  "geometry": {"coordinates":[8.5068883896,47.3678970337],"type":"Point"}
}