{
  "type": "Feature",
  "properties": {
    "iso:country":"CH",
    "sg:address":"Via Al Ronchetto 21 B",
    "sg:city":"Lugano",
    "sg:orig_category":"Pneus Detailhandel",
    "sg:phone":"+41 91 971 38 34",
    "sg:postcode":"6900",
    "sg:province":"Ticino",
    "wof:name":"Agom Sa Pneumatici",
    "wof:placetype":"venue"
},
  "geometry": {"coordinates":[8.9579601288,46.0218887329],"type":"Point"}
}