{
  "type": "Feature",
  "properties": {
    "iso:country":"CH",
    "sg:address":"K\u00f6llikerstrasse 17 5036 Oberentfelden. Postfach 142",
    "sg:city":"Oberentfelden",
    "sg:orig_category":"Herstellung von Medikamenten U sonstigen pharmazeutischen Erzeugnissen Textilgewerbe",
    "sg:phone":"+41 32 351 44 20",
    "sg:postcode":"5036",
    "sg:province":"Aargau",
    "wof:name":"W.e. Gilomen & Cie Hyga-wattefabrik",
    "wof:placetype":"venue"
},
  "geometry": {"coordinates":[7.4038858414,47.156375885],"type":"Point"}
}