{
  "type": "Feature",
  "properties": {
    "iso:country":"CH",
    "sg:address":"Place Bel-air 1",
    "sg:city":"Lausanne",
    "sg:orig_category":"Arztpraxen",
    "sg:phone":"+41 21 323 56 68",
    "sg:postcode":"1003",
    "sg:province":"Vaud",
    "wof:name":"Dr M\u00e9d. Wolfgang Schueppen M\u00e9decin Sp\u00e9cialiste Fmh",
    "wof:placetype":"venue"
},
  "geometry": {"coordinates":[6.629222,46.522095],"type":"Point"}
}