{
  "type": "Feature",
  "properties": {
    "iso:country":"CH",
    "sg:address":"Route De Malagnou 8",
    "sg:city":"Gen\u00e8ve",
    "sg:orig_category":"Innenarchitekturb\u00fcros",
    "sg:phone":"+41 22 347 38 95",
    "sg:postcode":"1208",
    "sg:province":"Gen\u00e8ve",
    "wof:name":"Philippe V\u00e9rolet Architecture D'int\u00e9rieur",
    "wof:placetype":"venue"
},
  "geometry": {"coordinates":[6.1576929092,46.1983032227],"type":"Point"}
}