{
  "type": "Feature",
  "properties": {
    "iso:country":"CH",
    "sg:address":"St. Alban-vorstadt 104",
    "sg:city":"Basel",
    "sg:orig_category":"Druck ohne Zeitungsdruck Satzherstellung U Reproduktion",
    "sg:phone":"+41 61 273 40 55",
    "sg:postcode":"4052",
    "sg:province":"Basel-Stadt",
    "wof:name":"Atelier Urs + Thomas Dillier",
    "wof:placetype":"venue"
},
  "geometry": {"coordinates":[7.6026701927,47.5533981323],"type":"Point"}
}