{
  "type": "Feature",
  "properties": {
    "iso:country":"CH",
    "sg:address":"Baarerstrasse 113",
    "sg:city":"Zug",
    "sg:orig_category":"Grosshandel mit B\u00fcromaschinen Grosshandel mit Datenverarbeitungsger\u00e4ten",
    "sg:phone":"+41 41 763 13 13",
    "sg:postcode":"6300",
    "sg:province":"Zug",
    "wof:name":"Cositron Ag",
    "wof:placetype":"venue"
},
  "geometry": {"coordinates":[8.5184078217,47.1795272827],"type":"Point"}
}