{
  "type": "Feature",
  "properties": {
    "iso:country":"CH",
    "sg:address":"Friedhofweg 40 4950 Huttwil. Postfach 486",
    "sg:city":"Huttwil",
    "sg:orig_category":"Herstellung von Metallkonstruktionen Mechanische Werkst\u00e4tten",
    "sg:phone":"+41 62 962 11 44",
    "sg:postcode":"4950",
    "sg:province":"Bern",
    "wof:name":"A. Lanz Ag",
    "wof:placetype":"venue"
},
  "geometry": {"coordinates":[7.8549318314,47.1111183167],"type":"Point"}
}