{
  "type": "Feature",
  "properties": {
    "iso:country":"CH",
    "sg:address":"Rue De Clendy 33",
    "sg:city":"Yverdon-les-bains",
    "sg:orig_category":"Non-Classified Establishments",
    "sg:postcode":"1400",
    "sg:province":"Vaud",
    "wof:name":"Rsnv \u00ac Bobillier",
    "wof:placetype":"venue"
},
  "geometry": {"coordinates":[6.6538338661,46.7785453796],"type":"Point"}
}