{
  "type": "Feature",
  "properties": {
    "iso:country":"CH",
    "sg:address":"Gl\u00e4ng",
    "sg:city":"Sch\u00f6tz",
    "sg:classifiers":[
        {
            "category":"Building & Trades",
            "subcategory":"Landfill",
            "type":"Services"
        }
    ],
    "sg:phone":"+41 62 748 22 22",
    "sg:postcode":"6247",
    "sg:province":"Luzern",
    "sg:tags":[
        "floor",
        "laying",
        "parquet"
    ],
    "wof:name":"Renggli Ag",
    "wof:placetype":"venue"
},
  "geometry": {"coordinates":[7.9893198013,47.1706314087],"type":"Point"}
}