{
  "type": "Feature",
  "properties": {
    "addr:full":"Rue Du Milieu 3 Buttes Neuch\u00e2tel 2115",
    "addr:housenumber":"3",
    "addr:postcode":"buttes;2115",
    "addr:street":"Rue Du Milieu",
    "iso:country":"CH",
    "sg:address":"Rue Du Milieu 3",
    "sg:city":"Buttes",
    "sg:orig_category":"Bahnhofbuffets Restaurants",
    "sg:phone":"+41 32 841 11 98",
    "sg:postcode":"2115",
    "sg:province":"Neuch\u00e2tel",
    "wof:name":"Buffet Du Tram",
    "wof:placetype":"venue"
},
  "geometry": {"coordinates":[6.865442,46.966141],"type":"Point"}
}