{
  "type": "Feature",
  "properties": {
    "iso:country":"CH",
    "sg:address":"Place Du Bourg 10",
    "sg:city":"Martigny",
    "sg:orig_category":"Tapezierer/Dekorateure",
    "sg:phone":"+41 27 723 23 13",
    "sg:postcode":"1920",
    "sg:province":"Valais",
    "wof:name":"Marco Chiarelli Votre D\u00e9corateur D'int\u00e9rieur",
    "wof:placetype":"venue"
},
  "geometry": {"coordinates":[7.0655059814,46.0916137695],"type":"Point"}
}