{
  "type": "Feature",
  "properties": {
    "iso:country":"CH",
    "sg:address":"Chalet Marie-christine",
    "sg:city":"Montana",
    "sg:orig_category":"Vermietung U Verpachtung von eigenen Immobilien",
    "sg:postcode":"3962",
    "wof:name":"C\u00e9r\u00e9monia Sa",
    "wof:placetype":"venue"
},
  "geometry": {"coordinates":[-149.1455078125,61.604019165],"type":"Point"}
}