{
  "type": "Feature",
  "properties": {
    "iso:country":"CH",
    "sg:address":"Grundstrasse 14",
    "sg:city":"Z\u00fcrich",
    "sg:classifiers":[
        {
            "category":"Bars & Pubs",
            "type":"Food & Drink"
        }
    ],
    "sg:postcode":"8048",
    "sg:province":"Z\u00fcrich",
    "wof:name":"Ours African Pub & Restaurant, Ukwu+ Co",
    "wof:placetype":"venue"
},
  "geometry": {"coordinates":[8.499349,47.38485],"type":"Point"}
}