{
  "type": "Feature",
  "properties": {
    "iso:country":"CH",
    "sg:address":"Breitenweg 8",
    "sg:city":"Rheinau",
    "sg:orig_category":"Sonstige mit der Informatik verbundene T\u00e4tigkeiten",
    "sg:postcode":"8462",
    "sg:province":"Z\u00fcrich",
    "wof:name":"Kohler Engineering",
    "wof:placetype":"venue"
},
  "geometry": {"coordinates":[8.601102829,47.6371307373],"type":"Point"}
}