{
  "type": "Feature",
  "properties": {
    "iso:country":"CH",
    "sg:address":"7014",
    "sg:city":"Trin",
    "sg:classifiers":[
        {
            "category":"Bars & Pubs",
            "type":"Food & Drink"
        }
    ],
    "sg:phone":"+41 81 635 11 44",
    "sg:postcode":"7014",
    "sg:province":"Graubunden",
    "wof:name":"Bar Mirada",
    "wof:placetype":"venue"
},
  "geometry": {"coordinates":[9.362039,46.828285],"type":"Point"}
}