{
  "type": "Feature",
  "properties": {
    "addr:full":"Wiesendamm 4 4057 Basel. Postfach Basel Basel-Stadt 4019",
    "addr:housenumber":"4",
    "addr:postcode":"4057;4019",
    "addr:street":"Wiesendamm;Postfach",
    "iso:country":"CH",
    "sg:address":"Wiesendamm 4 4057 Basel. Postfach",
    "sg:city":"Basel",
    "sg:orig_category":"Binnenschiffahrt",
    "sg:phone":"+41 61 639 33 33",
    "sg:postcode":"4019",
    "sg:province":"Basel-Stadt",
    "wof:name":"Penta Container Line Ag",
    "wof:placetype":"venue"
},
  "geometry": {"coordinates":[7.589662,47.582142],"type":"Point"}
}