{
  "type": "Feature",
  "properties": {
    "iso:country":"CH",
    "sg:address":"Langacher",
    "sg:city":"Greifensee",
    "sg:orig_category":"Unclassifiable Establishments",
    "sg:phone":"+41 19442211",
    "sg:postcode":"8606",
    "sg:province":"Z\u00fcrich",
    "wof:name":"Mettler-toledo Holding Ag",
    "wof:placetype":"venue"
},
  "geometry": {"coordinates":[8.6826152802,47.3654708862],"type":"Point"}
}