{
  "type": "Feature",
  "properties": {
    "iso:country":"CH",
    "sg:address":"8152",
    "sg:city":"Glattbrugg",
    "sg:orig_category":"Grosshandel mit Wasch U Reinigungsmitteln Instandhaltung U Reparatur von Automobilen",
    "sg:phone":"+41 56 640 16 71",
    "sg:postcode":"8152",
    "sg:province":"Z\u00fcrich",
    "wof:name":"Tracofin Ag Chemisch / Technische Produkte",
    "wof:placetype":"venue"
},
  "geometry": {"coordinates":[8.5638904572,47.432308197],"type":"Point"}
}