{
  "type": "Feature",
  "properties": {
    "iso:country":"CH",
    "sg:address":"Z\u00fcrichstrasse 44 8306 Br\u00fcttisellen. Postfach",
    "sg:city":"Br\u00fcttisellen",
    "sg:classifiers":[
        {
            "category":"Travel",
            "subcategory":"Hotels & Motels",
            "type":"Entertainment"
        }
    ],
    "sg:postcode":"8306",
    "sg:province":"Z\u00fcrich",
    "sg:tags":[
        "hotels",
        "mit",
        "restaurant"
    ],
    "wof:name":"Alaska Pool Gmbh Gastst\u00e4tten, Unterhaltungsbetriebe U. Apparate",
    "wof:placetype":"venue"
},
  "geometry": {"coordinates":[8.6278524399,47.4217643738],"type":"Point"}
}