{
  "type": "Feature",
  "properties": {
    "iso:country":"CH",
    "sg:address":"Schubertweg 3 3073 G\u00fcmligen. Postfach",
    "sg:city":"G\u00fcmligen",
    "sg:orig_category":"Unternehmensberatung",
    "sg:phone":"+41 31 951 98 91",
    "sg:postcode":"3073",
    "sg:province":"Bern",
    "wof:name":"W & M Weiss Und M\u00fcllener Ag Unternehmensentwicklung",
    "wof:placetype":"venue"
},
  "geometry": {"coordinates":[7.4951548576,46.9317054749],"type":"Point"}
}