{
  "type": "Feature",
  "properties": {
    "iso:country":"CH",
    "sg:address":"Bahnhofstrasse 3",
    "sg:city":"Langenthal",
    "sg:orig_category":"Reiseb\u00fcros",
    "sg:phone":"+41 81 755 62 62",
    "sg:postcode":"4900",
    "sg:province":"Bern",
    "wof:name":"Kuoni Reisen Ag",
    "wof:placetype":"venue"
},
  "geometry": {"coordinates":[9.4711694717,47.1657333374],"type":"Point"}
}