{
  "type": "Feature",
  "properties": {
    "iso:country":"CH",
    "sg:address":"2563",
    "sg:city":"Ipsach",
    "sg:orig_category":"Schwimmb\u00e4der",
    "sg:phone":"+41 32 331 91 30",
    "sg:postcode":"2563",
    "sg:province":"Bern",
    "wof:name":"Primarschulhaus Betriebsleitung Hallenbad",
    "wof:placetype":"venue"
},
  "geometry": {"coordinates":[7.2283501625,47.1150588989],"type":"Point"}
}