{
  "type": "Feature",
  "properties": {
    "iso:country":"CH",
    "sg:address":"6987",
    "sg:city":"Caslano",
    "sg:orig_category":"Vermietung U Verpachtung von eigenen Immobilien",
    "sg:postcode":"6987",
    "sg:province":"Ticino",
    "wof:name":"Forsythia Sa",
    "wof:placetype":"venue"
},
  "geometry": {"coordinates":[8.8819198608,45.9710006714],"type":"Point"}
}