{
  "type": "Feature",
  "properties": {
    "iso:country":"CH",
    "sg:address":"Z\u00fcrcherstrasse 10",
    "sg:city":"Altendorf",
    "sg:orig_category":"Zahnarztpraxen",
    "sg:phone":"+41 55 442 81 51",
    "sg:postcode":"8852",
    "sg:province":"Schwyz",
    "wof:name":"Dr. Med. Dent. Boris Okmian Zahnarzt",
    "wof:placetype":"venue"
},
  "geometry": {"coordinates":[8.8289060593,47.1927490234],"type":"Point"}
}