{
  "type": "Feature",
  "properties": {
    "iso:country":"CH",
    "sg:address":"Rue Pestalozzi 9",
    "sg:city":"Gen\u00e8ve",
    "sg:orig_category":"Tankstellen",
    "sg:phone":"+41 17615087",
    "sg:postcode":"1202",
    "sg:province":"Gen\u00e8ve",
    "wof:name":"Nussbaumer Engelbert Ag",
    "wof:placetype":"venue"
},
  "geometry": {"coordinates":[8.4514551163,47.2886924744],"type":"Point"}
}