{
  "type": "Feature",
  "properties": {
    "iso:country":"CH",
    "sg:address":"Burgdorfstr. 1",
    "sg:city":"Ersigen",
    "sg:orig_category":"RESTAURANTS: TEA-ROOMS",
    "sg:phone":"+41 34 445 46 44",
    "sg:postcode":"3423",
    "sg:province":"Bern",
    "wof:name":"Basler-hofer Rita",
    "wof:placetype":"venue"
},
  "geometry": {"coordinates":[7.5948209763,47.0919837952],"type":"Point"}
}