{
  "type": "Feature",
  "properties": {
    "iso:country":"CH",
    "sg:address":"Hinterbergstrasse 91",
    "sg:city":"Z\u00fcrich",
    "sg:orig_category":"Interessenvertretungen",
    "sg:phone":"+41 12111332",
    "sg:postcode":"8044",
    "sg:province":"Z\u00fcrich",
    "wof:name":"Vogt Alfred-stiftung Zur F\u00f6rderung Der Augenheilkunde Unterst\u00fctzt Finanziell Die Bestrebung V. Forschern Auf Dem Gebiet D. Wissenschaftl. Augenheilkunde Usw",
    "wof:placetype":"venue"
},
  "geometry": {"coordinates":[8.5576448441,47.3843688965],"type":"Point"}
}