{
  "type": "Feature",
  "properties": {
    "iso:country":"CH",
    "sg:address":"Breitenweg 8",
    "sg:city":"Oberhasli",
    "sg:orig_category":"Bauspenglerei Dachdeckerei",
    "sg:phone":"+41 41 711 68 48",
    "sg:postcode":"8156",
    "sg:province":"Z\u00fcrich",
    "wof:name":"Peter M\u00fcller Spenglerei Blitzschutz Dachservice Gmbh",
    "wof:placetype":"venue"
},
  "geometry": {"coordinates":[8.508153,47.143066],"type":"Point"}
}