{
  "type": "Feature",
  "properties": {
    "iso:country":"CH",
    "sg:address":"Gotthardstrasse 115",
    "sg:city":"Silenen",
    "sg:orig_category":"Detailhandel mit Brot, Back U S\u00fcsswaren",
    "sg:postcode":"6473",
    "sg:province":"Uri",
    "wof:name":"Widmer Bruno",
    "wof:placetype":"venue"
},
  "geometry": {"coordinates":[8.276273,47.351452],"type":"Point"}
}