{
  "type": "Feature",
  "properties": {
    "iso:country":"CH",
    "sg:address":"Ch. De Grand Montfleury 4",
    "sg:city":"Versoix",
    "sg:orig_category":"Sonstiger Grosshandel",
    "sg:postcode":"1290",
    "sg:province":"Gen\u00e8ve",
    "wof:name":"Etablissement Commercial Imsab Sabounghi Y.",
    "wof:placetype":"venue"
},
  "geometry": {"coordinates":[6.1624031067,46.2918167114],"type":"Point"}
}