{
  "type": "Feature",
  "properties": {
    "iso:country":"CH",
    "sg:address":"Haltenstrasse 3715 Adelboden. Postfach",
    "sg:city":"Adelboden",
    "sg:orig_category":"Wirtschaftspr\u00fcfung, Steuerberatung U Treuhand",
    "sg:postcode":"3715",
    "sg:province":"Bern",
    "wof:name":"S. Inniger",
    "wof:placetype":"venue"
},
  "geometry": {"coordinates":[7.5583591461,46.4943695068],"type":"Point"}
}