{
  "type": "Feature",
  "properties": {
    "iso:country":"CH",
    "sg:address":"Via Valmara 14",
    "sg:city":"Brissago",
    "sg:orig_category":"Tankstellen",
    "sg:phone":"+41 91 793 14 85",
    "sg:postcode":"6614",
    "sg:province":"Ticino",
    "wof:name":"Emilio De-bortoli Stazione Di Servizio Fina",
    "wof:placetype":"venue"
},
  "geometry": {"coordinates":[8.7038230896,46.1119880676],"type":"Point"}
}