{
  "type": "Feature",
  "properties": {
    "iso:country":"CH",
    "sg:address":"Bassersdorferstrasse 8302 Kloten. Postfach",
    "sg:city":"Kloten",
    "sg:orig_category":"Herstellung von Transportbeton",
    "sg:postcode":"8302",
    "sg:province":"Z\u00fcrich",
    "wof:name":"Beton Ag Kloten",
    "wof:placetype":"venue"
},
  "geometry": {"coordinates":[8.5960969925,47.4502716064],"type":"Point"}
}