{
  "type": "Feature",
  "properties": {
    "iso:country":"CH",
    "sg:address":"Oberneuhofstrasse 6",
    "sg:city":"Baar",
    "sg:orig_category":"Rechtsberatung",
    "sg:postcode":"6340",
    "sg:province":"Zug",
    "wof:name":"Triple E Intermandate Ag Mandate F\u00fcr Internationale Unternehmensberatung U. Unternehmensdienstleistungen Usw",
    "wof:placetype":"venue"
},
  "geometry": {"coordinates":[9.0747652054,47.4425849915],"type":"Point"}
}