{
  "type": "Feature",
  "properties": {
    "iso:country":"CH",
    "sg:address":"Via Al Mulino",
    "sg:city":"Vezia",
    "sg:orig_category":"W\u00e4scherei U chemische Reinigung",
    "sg:phone":"+41 91 968 21 50",
    "sg:postcode":"6943",
    "sg:province":"Ticino",
    "wof:name":"Lis Linen Supply Sa",
    "wof:placetype":"venue"
},
  "geometry": {"coordinates":[8.9311752319,46.0267944336],"type":"Point"}
}