{
  "type": "Feature",
  "properties": {
    "iso:country":"CH",
    "sg:address":"Bernstrasse 24",
    "sg:city":"M\u00fcnsingen",
    "sg:orig_category":"Non-Classified Establishments",
    "sg:phone":"+41 31 722 18 36",
    "sg:postcode":"3110",
    "sg:province":"Bern",
    "wof:name":"Webstar Ag",
    "wof:placetype":"venue"
},
  "geometry": {"coordinates":[7.5613799095,46.8784255981],"type":"Point"}
}