{
  "type": "Feature",
  "properties": {
    "iso:country":"CH",
    "sg:address":"Bundesrat R. Mingerstrasse 1",
    "sg:city":"Sch\u00fcpfen",
    "sg:orig_category":"Bauspenglerei Sanit\u00e4rinstallation",
    "sg:phone":"+41 32 384 12 48",
    "sg:postcode":"3054",
    "sg:province":"Bern",
    "wof:name":"Murri & Gilomen Ag Spenglerei Sanit\u00e4r Heizung",
    "wof:placetype":"venue"
},
  "geometry": {"coordinates":[7.378786,47.037033],"type":"Point"}
}