{
  "type": "Feature",
  "properties": {
    "iso:country":"CH",
    "sg:address":"Kapellstrasse 7 8854 Siebnen. Postfach",
    "sg:city":"Siebnen",
    "sg:orig_category":"Herstellung von Elektromotoren, Generatoren U Transformatoren",
    "sg:postcode":"8854",
    "sg:province":"Schwyz",
    "wof:name":"Elektro Rhyner Ag, Zweigniederlassung Siebnen, Gemeinde Sch\u00fcbelbach Starkstrom- U. Elektrische Anlagen; Projektierung, Ausf\u00fchrung. Elektrische Apparate U. Anlagen; Reparatur Usw",
    "wof:placetype":"venue"
},
  "geometry": {"coordinates":[8.8998746872,47.17710495],"type":"Point"}
}