{
  "type": "Feature",
  "properties": {
    "iso:country":"CH",
    "sg:address":"Route De Vandoeuvres 125",
    "sg:city":"Vandoeuvres",
    "sg:orig_category":"Detailhandel mit M\u00f6beln Detailhandel mit M\u00f6beln U Haushaltsgegenst\u00e4nden",
    "sg:phone":"+41 22 750 16 57",
    "sg:postcode":"1253",
    "sg:province":"Gen\u00e8ve",
    "wof:name":"La Pin\u00e8de, Diane Et Christine Turrettini",
    "wof:placetype":"venue"
},
  "geometry": {"coordinates":[6.2022199631,46.2213897705],"type":"Point"}
}