{
  "type": "Feature",
  "properties": {
    "iso:country":"CH",
    "sg:address":"Baslerstrasse 5",
    "sg:city":"Laufenburg",
    "sg:orig_category":"Pensionskassen",
    "sg:phone":"+41 71 966 22 22",
    "sg:postcode":"5080",
    "sg:province":"Aargau",
    "wof:name":"Wohlfahrtsstiftung Frischknecht Ag",
    "wof:placetype":"venue"
},
  "geometry": {"coordinates":[8.9958486557,47.4785575867],"type":"Point"}
}