{
  "type": "Feature",
  "properties": {
    "iso:country":"CH",
    "sg:address":"Via Bossi 12b",
    "sg:city":"Chiasso",
    "sg:orig_category":"Autotransporte international G\u00fcterbef\u00f6rderung im Strassenverkehr",
    "sg:phone":"+41 91 682 00 86",
    "sg:postcode":"6830",
    "sg:province":"Ticino",
    "wof:name":"Star Global Llc, Austin, Texas, Succursale Di Chiasso",
    "wof:placetype":"venue"
},
  "geometry": {"coordinates":[9.03149,45.834686],"type":"Point"}
}