{
  "type": "Feature",
  "properties": {
    "iso:country":"CH",
    "sg:address":"Langackerstrasse 4 Gundetswil 8546 Islikon. Postfach",
    "sg:city":"Islikon",
    "sg:orig_category":"Softwareentwicklung U beratung",
    "sg:postcode":"8546",
    "sg:province":"Thurgau",
    "wof:name":"Trendnet Gmbh",
    "wof:placetype":"venue"
},
  "geometry": {"coordinates":[8.8418302536,47.5454711914],"type":"Point"}
}