{
  "type": "Feature",
  "properties": {
    "iso:country":"CH",
    "sg:address":"Mariahilfstr. 6",
    "sg:city":"Tafers",
    "sg:orig_category":"Instandhaltung U Reparatur von Automobilen Tankstellen",
    "sg:phone":"+41 79 310 05 02",
    "sg:postcode":"1712",
    "sg:province":"Fribourg",
    "wof:name":"Garage Gobet Ag",
    "wof:placetype":"venue"
},
  "geometry": {"coordinates":[7.214838028,46.8172836304],"type":"Point"}
}