{
  "type": "Feature",
  "properties": {
    "iso:country":"CH",
    "sg:address":"Valdani Via 6830 Chiasso Casella Postale 326",
    "sg:city":"Chiasso",
    "sg:orig_category":"Wirtschaftspr\u00fcfung, Steuerberatung U Treuhand",
    "sg:phone":"+41 91 682 67 81",
    "sg:postcode":"6830",
    "sg:province":"Ticino",
    "wof:name":"Finafid Sa",
    "wof:placetype":"venue"
},
  "geometry": {"coordinates":[9.0313053131,45.8347244263],"type":"Point"}
}