{
  "type": "Feature",
  "properties": {
    "iso:country":"CH",
    "sg:address":"Alte Landstrasse 17",
    "sg:city":"Oetwil",
    "sg:orig_category":"Reinigungsgewerbe",
    "sg:postcode":"8955",
    "sg:province":"Z\u00fcrich",
    "wof:name":"Kaufmann Reinigungen",
    "wof:placetype":"venue"
},
  "geometry": {"coordinates":[8.3955154419,47.4278755188],"type":"Point"}
}