{
  "type": "Feature",
  "properties": {
    "iso:country":"CH",
    "sg:address":"Hubel",
    "sg:city":"Oberbalm",
    "sg:orig_category":"Grosshandel mit lebenden Tieren",
    "sg:phone":"+41 31 849 14 75",
    "sg:postcode":"3096",
    "sg:province":"Bern",
    "wof:name":"Gefl\u00fcgel Krebs",
    "wof:placetype":"venue"
},
  "geometry": {"coordinates":[7.4023132324,46.8748092651],"type":"Point"}
}