{
  "type": "Feature",
  "properties": {
    "iso:country":"CH",
    "sg:address":"Oberdorf.",
    "sg:city":"Giffers",
    "sg:orig_category":"Sonstiger Fachdetailhandel mit Nahrungsmitteln, Getr\u00e4nken U Tabak in Verkaufsr\u00e4umen",
    "sg:phone":"+41 26 418 13 38",
    "sg:postcode":"1735",
    "sg:province":"Fribourg",
    "wof:name":"B\u00fcrgy-rotzetter Marie-therese.",
    "wof:placetype":"venue"
},
  "geometry": {"coordinates":[7.2104501724,46.7604255676],"type":"Point"}
}