{
  "type": "Feature",
  "properties": {
    "iso:country":"CH",
    "sg:address":"Dorfplatz 2",
    "sg:city":"Gommiswald",
    "sg:orig_category":"Softwareentwicklung U beratung",
    "sg:postcode":"8737",
    "sg:province":"St. Gallen",
    "wof:name":"Rudzitis Software Solutions Rss",
    "wof:placetype":"venue"
},
  "geometry": {"coordinates":[9.0233240128,47.2314186096],"type":"Point"}
}