{
  "type": "Feature",
  "properties": {
    "iso:country":"CH",
    "sg:address":"Kantonsstrasse 320 3900 Gamsen. Postfach",
    "sg:city":"Glis",
    "sg:orig_category":"Einbau von Schreinerwaren Herstellung von K\u00fcchenm\u00f6beln",
    "sg:phone":"+41 79 449 27 79",
    "sg:postcode":"3902",
    "sg:province":"Valais",
    "wof:name":"K\u00fcchenstudio Schwestermann Andreas.",
    "wof:placetype":"venue"
},
  "geometry": {"coordinates":[7.9593172073,46.3059959412],"type":"Point"}
}