{
  "type": "Feature",
  "properties": {
    "iso:country":"CH",
    "sg:address":"Via San Gottardo 79",
    "sg:city":"Balerna",
    "sg:classifiers":[
        {
            "category":"Insurance",
            "subcategory":"Insurance Agent",
            "type":"Services"
        }
    ],
    "sg:phone":"+41 91 683 42 26",
    "sg:postcode":"6828",
    "sg:province":"Ticino",
    "sg:tags":[
        "versicherungsagenturen",
        "-broker"
    ],
    "wof:name":"Basilese Assicurazioni Agenzia Roberto Cavadini",
    "wof:placetype":"venue"
},
  "geometry": {"coordinates":[9.006354332,45.8507003784],"type":"Point"}
}