{
  "type": "Feature",
  "properties": {
    "iso:country":"CH",
    "sg:address":"Vogelsangstrasse 16",
    "sg:city":"Turgi",
    "sg:orig_category":"Fotografisches Gewerbe U fotografische Laboratorien",
    "sg:postcode":"5300",
    "sg:province":"Aargau",
    "wof:name":"Fresa Fineline, Heusler F. & Co",
    "wof:placetype":"venue"
},
  "geometry": {"coordinates":[8.2486343384,47.4934234619],"type":"Point"}
}