{
  "type": "Feature",
  "properties": {
    "iso:country":"CH",
    "sg:address":"Z\u00fcrcherstrasse 65",
    "sg:city":"Basel",
    "sg:orig_category":"Herstellung von Radio U Fernsehger\u00e4ten sowie phono U videotechnischen Ger\u00e4ten",
    "sg:phone":"+41 61 378 81 10",
    "sg:postcode":"4052",
    "sg:province":"Basel-Stadt",
    "wof:name":"Cdc It Ag Niederlassung Basel",
    "wof:placetype":"venue"
},
  "geometry": {"coordinates":[7.6095309258,47.554019928],"type":"Point"}
}