{
  "type": "Feature",
  "properties": {
    "iso:country":"CH",
    "sg:address":"Aarwangenstrasse 28 4900 Langenthal. Postfach",
    "sg:city":"Langenthal",
    "sg:orig_category":"Detailhandel mit Musikinstrumenten",
    "sg:phone":"+41 62 922 80 40",
    "sg:postcode":"4900",
    "sg:province":"Bern",
    "wof:name":"Ernst Kleinert Musikhaus",
    "wof:placetype":"venue"
},
  "geometry": {"coordinates":[7.7871460915,47.2171974182],"type":"Point"}
}