{
  "type": "Feature",
  "properties": {
    "iso:country":"CH",
    "sg:address":"Rue Du Grand-pr\u00e9 61",
    "sg:city":"Gen\u00e8ve",
    "sg:orig_category":"Handel mit Motorr\u00e4dern, Teilen U Zubeh\u00f6r Instandhaltung U Reparatur von Motorr\u00e4dern",
    "sg:phone":"+41 22 329 35 65",
    "sg:postcode":"1202",
    "sg:province":"Gen\u00e8ve",
    "wof:name":"Scooter Scoop S\u00e0rl",
    "wof:placetype":"venue"
},
  "geometry": {"coordinates":[6.1310567856,46.2156486511],"type":"Point"}
}