{
  "type": "Feature",
  "properties": {
    "addr:full":"Schwarzenburgstrasse 257 K\u00f6niz Bern 3098",
    "addr:housenumber":"257",
    "addr:postcode":"3098",
    "addr:street":"Schwarzenburgstrasse",
    "iso:country":"CH",
    "sg:address":"Schwarzenburgstrasse 257",
    "sg:city":"K\u00f6niz",
    "sg:orig_category":"Arztpraxen",
    "sg:phone":"+41 31 971 42 22",
    "sg:postcode":"3098",
    "sg:province":"Bern",
    "wof:name":"Dr.med.rolf Neuenschwander Spezialarzt Fmh",
    "wof:placetype":"venue"
},
  "geometry": {"coordinates":[7.416178,46.924034],"type":"Point"}
}