{
  "type": "Feature",
  "properties": {
    "iso:country":"CH",
    "sg:address":"Neum\u00fchlestrasse 54",
    "sg:city":"Winterthur",
    "sg:orig_category":"Vermietung U Verpachtung von eigenen Immobilien Vermittlung von Immobilien",
    "sg:phone":"+41 52 202 00 11",
    "sg:postcode":"8406",
    "sg:province":"Z\u00fcrich",
    "wof:name":"Meier Consulting",
    "wof:placetype":"venue"
},
  "geometry": {"coordinates":[8.7077159882,47.4828071594],"type":"Point"}
}