{
  "type": "Feature",
  "properties": {
    "iso:country":"CH",
    "sg:address":"Solothurnstrasse 79",
    "sg:city":"Biel/bienne",
    "sg:classifiers":[
        {
            "category":"Wholesale",
            "subcategory":"Auto Parts",
            "type":"Manufacturing & Wholesale Goods"
        }
    ],
    "sg:phone":"+41 32 341 14 51",
    "sg:postcode":"2504",
    "sg:province":"Bern",
    "sg:tags":[
        "automobile",
        "cover",
        "seat"
    ],
    "wof:name":"Zollhaus Automobiel S.a.r.l.",
    "wof:placetype":"venue"
},
  "geometry": {"coordinates":[7.272817,47.157272],"type":"Point"}
}