{
  "type": "Feature",
  "properties": {
    "iso:country":"CH",
    "sg:address":"Zukunftstrasse 14",
    "sg:city":"Biel/bienne",
    "sg:orig_category":"Zahnarztpraxen",
    "sg:phone":"+41 32 322 08 77",
    "sg:postcode":"2503",
    "sg:province":"Bern",
    "wof:name":"Dr. Med. Dent. Donald Greub Zahnarzt",
    "wof:placetype":"venue"
},
  "geometry": {"coordinates":[7.2476758957,47.1335525513],"type":"Point"}
}