{
  "type": "Feature",
  "properties": {
    "iso:country":"CH",
    "sg:address":"W\u00fcrenloserstrasse 3",
    "sg:city":"Killwangen",
    "sg:orig_category":"Abwasserreinigung",
    "sg:phone":"+41 56 401 36 49",
    "sg:postcode":"8956",
    "sg:province":"Aargau",
    "wof:name":"Abwasserreiningungsanlage Ara Killwang.-spreitenb.-w\u00fcrenlos",
    "wof:placetype":"venue"
},
  "geometry": {"coordinates":[8.354834,47.433918],"type":"Point"}
}