{
  "type": "Feature",
  "properties": {
    "iso:country":"CH",
    "sg:address":"En Budron H9 1052 Mont-sur-lausanne Case Postale 512",
    "sg:city":"Mont-sur-lausanne",
    "sg:orig_category":"Datenverarbeitungsdienste Dienstleistungen von Beteiligungsgesellschaften",
    "sg:phone":"+41 71 226 83 00",
    "sg:postcode":"1052",
    "sg:province":"Vaud",
    "wof:name":"Verwaltungsrechenzentrum Ag St. Gallen (vrsg)",
    "wof:placetype":"venue"
},
  "geometry": {"coordinates":[9.370863,47.423683],"type":"Point"}
}