{
  "type": "Feature",
  "properties": {
    "iso:country":"CH",
    "sg:address":"1252",
    "sg:city":"Meinier",
    "sg:orig_category":"Vereine Gesang",
    "sg:phone":"+41 22 752 14 30",
    "sg:postcode":"1252",
    "sg:province":"Gen\u00e8ve",
    "wof:name":"Chorale Catholique",
    "wof:placetype":"venue"
},
  "geometry": {"coordinates":[6.233148098,46.2461585999],"type":"Point"}
}