{
  "type": "Feature",
  "properties": {
    "iso:country":"CH",
    "sg:address":"Via Riviera 14 6976 Castagnola. Postfach",
    "sg:city":"Castagnola",
    "sg:orig_category":"Schiffsbau ohne Boots U Yachtbau",
    "sg:postcode":"6976",
    "sg:province":"Ticino",
    "wof:name":"Atlantic Sa Di Gestione E Noleggio Marittimi",
    "wof:placetype":"venue"
},
  "geometry": {"coordinates":[8.9713172913,46.0027580261],"type":"Point"}
}