{
  "type": "Feature",
  "properties": {
    "iso:country":"CH",
    "sg:address":"Ludretikonerstrasse 52",
    "sg:city":"Thalwil",
    "sg:orig_category":"G\u00fcterbef\u00f6rderung im Strassenverkehr",
    "sg:phone":"+41 17204314",
    "sg:postcode":"8800",
    "sg:province":"Z\u00fcrich",
    "wof:name":"Heinz M\u00fcller Transporte",
    "wof:placetype":"venue"
},
  "geometry": {"coordinates":[8.5607652664,47.2980232239],"type":"Point"}
}