{
  "type": "Feature",
  "properties": {
    "iso:country":"CH",
    "sg:address":"Bahnweg Nord 50",
    "sg:city":"Sevelen",
    "sg:orig_category":"Barometer Parts",
    "sg:phone":"+41 81 785 25 35",
    "sg:postcode":"9475",
    "sg:province":"St. Gallen",
    "wof:name":"Dme Druckmesselemente Ag",
    "wof:placetype":"venue"
},
  "geometry": {"coordinates":[9.493416,47.128082],"type":"Point"}
}