{
  "type": "Feature",
  "properties": {
    "iso:country":"CH",
    "sg:address":"Limmatquai 66",
    "sg:city":"Z\u00fcrich",
    "sg:classifiers":[
        {
            "category":"Government",
            "subcategory":"Post Office",
            "type":"Public Place"
        }
    ],
    "sg:phone":"+41 81 826 52 13",
    "sg:postcode":"8001",
    "sg:province":"Z\u00fcrich",
    "sg:tags":[
        "caf\u00e9s",
        "tea-rooms"
    ],
    "wof:name":"Grand Caf\u00e9 Puntschella",
    "wof:placetype":"venue"
},
  "geometry": {"coordinates":[9.764169693,46.4287605286],"type":"Point"}
}