{
  "type": "Feature",
  "properties": {
    "iso:country":"CH",
    "sg:address":"Industriestrasse 21 7000 Chur. Postfach 238",
    "sg:city":"Chur",
    "sg:orig_category":"Herstellung von Metallerzeugnissen ohne Maschinenbau Herstellung von sonstigen Maschinen f\u00fcr unspezi",
    "sg:phone":"+41 71 385 42 27",
    "sg:postcode":"7004",
    "sg:province":"Graubunden",
    "wof:name":"Weibel Ludwig",
    "wof:placetype":"venue"
},
  "geometry": {"coordinates":[9.2512674332,47.4072990417],"type":"Point"}
}