{
  "type": "Feature",
  "properties": {
    "iso:country":"CH",
    "sg:address":"Aarauerstrasse 2",
    "sg:city":"Wildegg",
    "sg:orig_category":"Sanit\u00e4r U Heizungsinstallation Sanit\u00e4rinstallation",
    "sg:phone":"+41 71 222 24 48",
    "sg:postcode":"5103",
    "sg:province":"Aargau",
    "wof:name":"Winiger-sanit\u00e4r Installationsarbeiten",
    "wof:placetype":"venue"
},
  "geometry": {"coordinates":[9.3850231171,47.4156341553],"type":"Point"}
}