{
  "type": "Feature",
  "properties": {
    "iso:country":"CH",
    "sg:address":"Lachen 765",
    "sg:city":"Walzenhausen",
    "sg:orig_category":"Institutionen f\u00fcr Behinderte Tagesheime f\u00fcr Behinderte, gesch\u00fctzte Werkst\u00e4tten",
    "sg:phone":"+41 71 888 29 61",
    "sg:postcode":"9428",
    "sg:province":"Appenzell Ausserrhoden",
    "wof:name":"Stiftung Waldheim Heim F.mehrfach Gebrechliche",
    "wof:placetype":"venue"
},
  "geometry": {"coordinates":[9.5821857452,47.4412078857],"type":"Point"}
}