{
  "type": "Feature",
  "properties": {
    "iso:country":"CH",
    "sg:address":"Jakobstrasse 2",
    "sg:city":"Uster",
    "sg:orig_category":"Vereine Fasnacht",
    "sg:postcode":"8610",
    "sg:province":"Z\u00fcrich",
    "wof:name":"Fasnachtsges.humoria Uster",
    "wof:placetype":"venue"
},
  "geometry": {"coordinates":[8.7105321884,47.3459434509],"type":"Point"}
}