{
  "type": "Feature",
  "properties": {
    "iso:country":"CH",
    "sg:address":"Poststrasse 4",
    "sg:city":"Lenzburg",
    "sg:classifiers":[
        {
            "category":"Professional",
            "subcategory":"Employment Agencies",
            "type":"Services"
        }
    ],
    "sg:phone":"+41 62 891 61 61",
    "sg:postcode":"5600",
    "sg:province":"Aargau",
    "sg:tags":[
        "personal",
        "u",
        "stellenvermittlung"
    ],
    "wof:name":"Randstad (schweiz) Ag",
    "wof:placetype":"venue"
},
  "geometry": {"coordinates":[8.1787481308,47.3874206543],"type":"Point"}
}