{
  "type": "Feature",
  "properties": {
    "iso:country":"CH",
    "sg:address":"Hauptstrasse 71 9214 Kradolf. Postfach 54",
    "sg:city":"Kradolf",
    "sg:orig_category":"Autogaragen",
    "sg:phone":"+41 71 642 14 01",
    "sg:postcode":"9214",
    "sg:province":"Thurgau",
    "wof:name":"Heinz Schwarzenbach Thur-garage",
    "wof:placetype":"venue"
},
  "geometry": {"coordinates":[9.205249,47.522457],"type":"Point"}
}