{
  "type": "Feature",
  "properties": {
    "iso:country":"CH",
    "sg:address":"Route De Pr\u00e9jeux 1950 Sion Case Postale",
    "sg:city":"Sion",
    "sg:orig_category":"Grosshandel mit Obst U Gem\u00fcse Wirtschafts U Arbeitgeberverb\u00e4nde",
    "sg:phone":"+41 91 606 43 41",
    "sg:postcode":"1951",
    "sg:province":"Valais",
    "wof:name":"Associazione Importatori Ortofrutticoli Assio",
    "wof:placetype":"venue"
},
  "geometry": {"coordinates":[8.8604135513,45.9691696167],"type":"Point"}
}