{
  "type": "Feature",
  "properties": {
    "iso:country":"CH",
    "sg:address":"Bernstrasse 31 3506 Grossh\u00f6chstetten. Postfach",
    "sg:city":"Grossh\u00f6chstetten",
    "sg:orig_category":"Instandhaltung U Reparatur von Automobilen",
    "sg:postcode":"3506",
    "sg:province":"Bern",
    "wof:name":"A. Felder",
    "wof:placetype":"venue"
},
  "geometry": {"coordinates":[7.6331310272,46.9098052979],"type":"Point"}
}