{
  "type": "Feature",
  "properties": {
    "iso:country":"CH",
    "sg:address":"Steinenring 53 4051 Basel. Postfach",
    "sg:city":"Basel",
    "sg:orig_category":"Binnenschiffahrt",
    "sg:phone":"+41 61 281 53 53",
    "sg:postcode":"4051",
    "sg:province":"Basel-Stadt",
    "wof:name":"Msc - Mediterranean Shipping Agency Ag Schiffe Usw; An, Verkauf, Vermietung, Vermittlung",
    "wof:placetype":"venue"
},
  "geometry": {"coordinates":[7.581189,47.550762],"type":"Point"}
}