{
  "type": "Feature",
  "properties": {
    "iso:country":"CH",
    "sg:address":"Bellinzona Via 31",
    "sg:city":"Giubiasco",
    "sg:orig_category":"Unclassifiable Establishments",
    "sg:postcode":"6512",
    "sg:province":"Ticino",
    "wof:name":"Info-sms Sa",
    "wof:placetype":"venue"
},
  "geometry": {"coordinates":[9.0137901306,46.1780967712],"type":"Point"}
}