{
  "type": "Feature",
  "properties": {
    "iso:country":"CH",
    "sg:address":"1958",
    "sg:city":"St-l\u00e9onard",
    "sg:orig_category":"Gemeindeverwaltungen",
    "sg:phone":"+41 21 907 86 88",
    "sg:postcode":"1958",
    "sg:province":"Valais",
    "wof:name":"Administration Communale De Saint-martin",
    "wof:placetype":"venue"
},
  "geometry": {"coordinates":[6.8814702034,46.5819587708],"type":"Point"}
}