{
  "type": "Feature",
  "properties": {
    "addr:full":"Z\u00fcrcherstrasse 15 Hedingen Z\u00fcrich 8908",
    "addr:housenumber":"15",
    "addr:postcode":"8908",
    "addr:street":"Zuercherstrasse",
    "iso:country":"CH",
    "sg:address":"Z\u00fcrcherstrasse 15",
    "sg:city":"Hedingen",
    "sg:orig_category":"Detailhandel mit Brot, Back U S\u00fcsswaren",
    "sg:phone":"+41 17616136",
    "sg:postcode":"8908",
    "sg:province":"Z\u00fcrich",
    "wof:name":"Andreas Pfyl B\u00e4ckerei-konditorei",
    "wof:placetype":"venue"
},
  "geometry": {"coordinates":[8.447914,47.298531],"type":"Point"}
}