{
  "type": "Feature",
  "properties": {
    "iso:country":"CH",
    "sg:address":"Chemin Du Bochet 8a",
    "sg:city":"Gland",
    "sg:orig_category":"Sonstiger spezialisierter Hoch U Tiefbau",
    "sg:phone":"+41 22 364 53 23",
    "sg:postcode":"1196",
    "sg:province":"Vaud",
    "wof:name":"Simoes Fr\u00e8res",
    "wof:placetype":"venue"
},
  "geometry": {"coordinates":[6.2749671936,46.416053772],"type":"Point"}
}