{
  "type": "Feature",
  "properties": {
    "addr:full":"Grundstrasse 130 6430 Schwyz. Postfach Schwyz Schwyz 6431",
    "addr:housenumber":"130",
    "addr:postcode":"6430;postfach;6431",
    "addr:street":"Grundstrasse",
    "iso:country":"CH",
    "sg:address":"Grundstrasse 130 6430 Schwyz. Postfach",
    "sg:city":"Schwyz",
    "sg:orig_category":"Autogaragen",
    "sg:phone":"+41 41 811 20 05",
    "sg:postcode":"6431",
    "sg:province":"Schwyz",
    "wof:name":"Ruedi Horat Ag Garage",
    "wof:placetype":"venue"
},
  "geometry": {"coordinates":[8.657944,47.009357],"type":"Point"}
}