{
  "type": "Feature",
  "properties": {
    "iso:country":"CH",
    "sg:address":"Passage Du Cardinal 2c 1700 Fribourg Case Postale 215",
    "sg:city":"Fribourg",
    "sg:orig_category":"Architektur U Ingenieurb\u00fcros Ingenieurb\u00fcros divers",
    "sg:phone":"+41 21 922 50 00",
    "sg:postcode":"1705",
    "sg:province":"Fribourg",
    "wof:name":"Sic 2000 Ing\u00e9nieurs-conseils S\u00e0rl",
    "wof:placetype":"venue"
},
  "geometry": {"coordinates":[5.18087,45.897339],"type":"Point"}
}