{
  "type": "Feature",
  "properties": {
    "iso:country":"CH",
    "sg:address":"Birmensdorferstrasse 126 8003 Z\u00fcrich. Postfach",
    "sg:city":"Z\u00fcrich",
    "sg:orig_category":"Herstellung von konfektionierten Textilwaren ohne Bekleidung",
    "sg:postcode":"8001",
    "sg:province":"Z\u00fcrich",
    "wof:name":"Schneiderei Schmiede-wiedikon Turgut Schneiderarbeiten, Bes. \u00c4nderungen. Annahmestelle F\u00fcr Die Chemische Reinigung",
    "wof:placetype":"venue"
},
  "geometry": {"coordinates":[8.5209007263,47.3701591492],"type":"Point"}
}