{
  "type": "Feature",
  "properties": {
    "addr:full":"Jurastrasse 8 R\u00fctihof Aargau 5406",
    "addr:housenumber":"8",
    "addr:postcode":"5406",
    "addr:street":"Jurastrasse",
    "iso:country":"CH",
    "sg:address":"Jurastrasse 8",
    "sg:city":"R\u00fctihof",
    "sg:orig_category":"Bauschreinerei Herstellung von Konstruktionsteilen, Fertigbauteilen U Ausbauelementen aus Holz",
    "sg:phone":"+41 56 493 12 85",
    "sg:postcode":"5406",
    "sg:province":"Aargau",
    "wof:name":"Schreinerei-innenausbau Eggert Rasso",
    "wof:placetype":"venue"
},
  "geometry": {"coordinates":[8.26905,47.437805],"type":"Point"}
}