{
  "type": "Feature",
  "properties": {
    "iso:country":"CH",
    "sg:address":"8241 Barzheim. Postfach 75",
    "sg:city":"Thayngen",
    "sg:orig_category":"Landwirtschaftliche Genossenschaften",
    "sg:postcode":"8240",
    "sg:province":"Schaffhausen",
    "wof:name":"Landw.genossenschaft",
    "wof:placetype":"venue"
},
  "geometry": {"coordinates":[9.2270298004,47.1988601685],"type":"Point"}
}