{
  "type": "Feature",
  "properties": {
    "iso:country":"CH",
    "sg:address":"Glutz-blotzstrasse 1 4500 Solothurn. Postfach 706",
    "sg:city":"Solothurn",
    "sg:orig_category":"Grosshandel mit medizinischen U orthop\u00e4dischen Artikeln Herstellung von medizinischen U chirurgische",
    "sg:phone":"+41 32 623 43 55",
    "sg:postcode":"4502",
    "sg:province":"Solothurn",
    "wof:name":"Mic Medical Instrument Corporation",
    "wof:placetype":"venue"
},
  "geometry": {"coordinates":[7.5290732384,47.2017784119],"type":"Point"}
}