{
  "type": "Feature",
  "properties": {
    "iso:country":"CH",
    "sg:address":"9503",
    "sg:city":"Stehrenberg",
    "sg:orig_category":"Vereine Gesang",
    "sg:postcode":"9503",
    "sg:province":"Thurgau",
    "wof:name":"Gemischter Chor Weingarten Weingarten Bei M\u00e4rwil",
    "wof:placetype":"venue"
},
  "geometry": {"coordinates":[9.0887298584,47.5232582092],"type":"Point"}
}