{
  "type": "Feature",
  "properties": {
    "iso:country":"CH",
    "sg:address":"Limmatquai 62",
    "sg:city":"Z\u00fcrich",
    "sg:orig_category":"Detailhandel mit Uhren U Schmuck",
    "sg:phone":"+41 12628484",
    "sg:postcode":"8001",
    "sg:province":"Z\u00fcrich",
    "wof:name":"Varga's Art Schmuck Bijouterie",
    "wof:placetype":"venue"
},
  "geometry": {"coordinates":[8.5430173874,47.3719558716],"type":"Point"}
}