{
  "type": "Feature",
  "properties": {
    "iso:country":"CH",
    "sg:address":"Frontenex Avenue De 32 1207 Gen\u00e8ve. Postfach",
    "sg:city":"Gen\u00e8ve",
    "sg:orig_category":"Pensionskassen",
    "sg:postcode":"1201",
    "sg:province":"Gen\u00e8ve",
    "wof:name":"La Collective De Pr\u00e9voyance - Copre",
    "wof:placetype":"venue"
},
  "geometry": {"coordinates":[6.1588449478,46.2014694214],"type":"Point"}
}