{
  "type": "Feature",
  "properties": {
    "iso:country":"CH",
    "sg:address":"Impasse De L'artisanat 2",
    "sg:city":"Grolley",
    "sg:orig_category":"Stukkateurgewerbe, Gipserei U Verputzerei Verlegen von Fliesen U Platten",
    "sg:phone":"+41 79 230 20 85",
    "sg:postcode":"1772",
    "sg:province":"Fribourg",
    "wof:name":"Michel Lommano Sa Peinture & Gypserie",
    "wof:placetype":"venue"
},
  "geometry": {"coordinates":[7.0596699715,46.8293952942],"type":"Point"}
}