{
  "type": "Feature",
  "properties": {
    "iso:country":"CH",
    "sg:address":"Eriswilstrasse 376",
    "sg:city":"Huttwil",
    "sg:classifiers":[
        {
            "category":"Autos & Motor Vehicles",
            "subcategory":"Auto Supplies",
            "type":"Retail Goods"
        }
    ],
    "sg:phone":"+41 62 962 06 16",
    "sg:postcode":"4950",
    "sg:province":"Bern",
    "sg:tags":[
        "body",
        "car",
        "truck",
        "trailer",
        "superstructure"
    ],
    "wof:name":"Anfa Anh\u00e4ngertechnik Ag",
    "wof:placetype":"venue"
},
  "geometry": {"coordinates":[7.854332,47.105492],"type":"Point"}
}