{
  "type": "Feature",
  "properties": {
    "iso:country":"CH",
    "sg:address":"Brown-boveri-strasse 8",
    "sg:city":"Z\u00fcrich",
    "sg:orig_category":"Informatikdienste Unternehmensberatung",
    "sg:phone":"+41 13121138",
    "sg:postcode":"8050",
    "sg:province":"Z\u00fcrich",
    "wof:name":"Itrend Consulting Gmbh",
    "wof:placetype":"venue"
},
  "geometry": {"coordinates":[8.5367650986,47.4154777527],"type":"Point"}
}