{
  "type": "Feature",
  "properties": {
    "iso:country":"CH",
    "sg:address":"Neugasse 20",
    "sg:city":"Kreuzlingen",
    "sg:orig_category":"Vereine Orchester",
    "sg:phone":"+41 71 672 38 30",
    "sg:postcode":"8280",
    "sg:province":"Thurgau",
    "wof:name":"Orchesterverein Kreuzlingen",
    "wof:placetype":"venue"
},
  "geometry": {"coordinates":[9.1683273315,47.6437530518],"type":"Point"}
}