{
  "type": "Feature",
  "properties": {
    "iso:country":"CH",
    "sg:address":"H\u00e4nsigr\u00fct 7",
    "sg:city":"Sachseln",
    "sg:orig_category":"Grosshandel mit Baumaschinen Vermietung von Baumaschinen U ger\u00e4ten mit Bedienungspersonal",
    "sg:phone":"+41 41 662 20 20",
    "sg:postcode":"6072",
    "sg:province":"Obwalden",
    "wof:name":"Rollende Werkstatt Kran Ag",
    "wof:placetype":"venue"
},
  "geometry": {"coordinates":[8.2197637558,46.8573417664],"type":"Point"}
}