{
  "type": "Feature",
  "properties": {
    "iso:country":"CH",
    "sg:address":"Rigastrasse 9",
    "sg:city":"Chur",
    "sg:orig_category":"Zahnarztpraxen",
    "sg:phone":"+41 81 253 53 50",
    "sg:postcode":"7000",
    "sg:province":"Graubunden",
    "wof:name":"Dr. Med. Dent. Markus Risch Zahnarzt",
    "wof:placetype":"venue"
},
  "geometry": {"coordinates":[9.5332326889,46.8556632996],"type":"Point"}
}