{
  "type": "Feature",
  "properties": {
    "iso:country":"CH",
    "sg:address":"Rheinstrasse 31 4410 Liestal. Postfach",
    "sg:city":"Liestal",
    "sg:orig_category":"Erziehungs\u00e4mter",
    "sg:phone":"+41 61 925 51 11",
    "sg:postcode":"4410",
    "sg:province":"Basel-Landschaft",
    "wof:name":"Kantonale Erziehungsdirektion",
    "wof:placetype":"venue"
},
  "geometry": {"coordinates":[7.7304692268,47.4870605469],"type":"Point"}
}