{
  "type": "Feature",
  "properties": {
    "addr:full":"1063 Chapelle-s-moudon Vaud 1063",
    "addr:housenumber":"1063",
    "addr:postcode":"1063",
    "addr:street":"Chapelle-S-Moudon",
    "iso:country":"CH",
    "sg:address":"1063",
    "sg:city":"Chapelle-s-moudon",
    "sg:orig_category":"Allgemeiner Hoch U Tiefbau",
    "sg:phone":"+41 21 905 32 77",
    "sg:postcode":"1063",
    "sg:province":"Vaud",
    "wof:name":"C\u00e9dric Martin S\u00e0rl",
    "wof:placetype":"venue"
},
  "geometry": {"coordinates":[6.737195,46.668659],"type":"Point"}
}