{
  "type": "Feature",
  "properties": {
    "iso:country":"CH",
    "sg:address":"Sonneggstrasse 48 8006 Z\u00fcrich. Postfach",
    "sg:city":"Z\u00fcrich",
    "sg:orig_category":"Sonstiger Grosshandel",
    "sg:postcode":"8001",
    "sg:province":"Z\u00fcrich",
    "wof:name":"Hausheer Import-export",
    "wof:placetype":"venue"
},
  "geometry": {"coordinates":[8.5460186005,47.3808822632],"type":"Point"}
}