{
  "type": "Feature",
  "properties": {
    "iso:country":"CH",
    "sg:address":"Kirchgasse 10",
    "sg:city":"Herzogenbuchsee",
    "sg:classifiers":[
        {
            "category":"Wholesale",
            "subcategory":"Books, Periodicals, & Newspapers",
            "type":"Manufacturing & Wholesale Goods"
        }
    ],
    "sg:phone":"+41 62 961 04 80",
    "sg:postcode":"3360",
    "sg:province":"Bern",
    "sg:tags":[
        "design",
        "paper",
        "sheet",
        "cardboard"
    ],
    "wof:name":"Farben- Und Bastelshop Grossen",
    "wof:placetype":"venue"
},
  "geometry": {"coordinates":[7.70666,47.187664],"type":"Point"}
}