{
  "type": "Feature",
  "properties": {
    "iso:country":"CH",
    "sg:address":"Tramstrasse 21 5034 Suhr. Postfach 89",
    "sg:city":"Suhr",
    "sg:orig_category":"Detailhandel mit Beleuchtungs U Haushaltsgegenst\u00e4nden Grosshandel mit Eisenwaren sowie Installations",
    "sg:postcode":"5034",
    "sg:province":"Aargau",
    "wof:name":"Rud. B\u00fchlmann",
    "wof:placetype":"venue"
},
  "geometry": {"coordinates":[8.031386,46.754318],"type":"Point"}
}