{
  "type": "Feature",
  "properties": {
    "iso:country":"CH",
    "sg:address":"Bleienbachstrasse 69",
    "sg:city":"Langenthal",
    "sg:orig_category":"Gartenbau",
    "sg:phone":"+41 56 241 11 58",
    "sg:postcode":"4900",
    "sg:province":"Bern",
    "wof:name":"Garten-center P. Hediger",
    "wof:placetype":"venue"
},
  "geometry": {"coordinates":[8.3280305862,47.5234832764],"type":"Point"}
}