{
  "type": "Feature",
  "properties": {
    "iso:country":"CH",
    "sg:address":"Hintergasse 5",
    "sg:city":"Villnachern",
    "sg:classifiers":[
        {
            "category":"Banks & Credit Unions",
            "subcategory":"Bank",
            "type":"Services"
        }
    ],
    "sg:phone":"+41 62 751 23 23",
    "sg:postcode":"5213",
    "sg:province":"Aargau",
    "wof:name":"Raiffeisenbank Vordemwald-strengelbach",
    "wof:placetype":"venue"
},
  "geometry": {"coordinates":[7.90151,47.275848],"type":"Point"}
}