{
  "type": "Feature",
  "properties": {
    "iso:country":"CH",
    "sg:address":"Lettenstrasse 7-9 6343 Rotkreuz. Postfach 65",
    "sg:city":"Rotkreuz",
    "sg:orig_category":"Grosshandel mit B\u00fcromaschinen Grosshandel mit Datenverarbeitungsger\u00e4ten",
    "sg:phone":"+41 79 434 56 59",
    "sg:postcode":"6343",
    "sg:province":"Zug",
    "wof:name":"Belfin Computer-systeme Ag",
    "wof:placetype":"venue"
},
  "geometry": {"coordinates":[8.1771268845,47.2635917664],"type":"Point"}
}