{
  "type": "Feature",
  "properties": {
    "iso:country":"CH",
    "sg:address":"Nielsenstrasse 6",
    "sg:city":"Buchrain",
    "sg:orig_category":"Sonstige mit Sport verbundene T\u00e4tigkeiten",
    "sg:phone":"+41 55 241 24 53",
    "sg:postcode":"6033",
    "sg:province":"Luzern",
    "wof:name":"Snowboardschule Fischenthal Herrn Thomas Egli",
    "wof:placetype":"venue"
},
  "geometry": {"coordinates":[8.8496837616,47.2578735352],"type":"Point"}
}