{
  "type": "Feature",
  "properties": {
    "iso:country":"CH",
    "sg:address":"Rue De La Faucille 5",
    "sg:city":"Gen\u00e8ve",
    "sg:orig_category":"Maler U Glasergewerbe Tapeziererei",
    "sg:phone":"+41 22 734 71 33",
    "sg:postcode":"1201",
    "sg:province":"Gen\u00e8ve",
    "wof:name":"Outeirino Angel",
    "wof:placetype":"venue"
},
  "geometry": {"coordinates":[6.139605999,46.2107810974],"type":"Point"}
}