{
  "type": "Feature",
  "properties": {
    "iso:country":"CH",
    "sg:address":"Hauptstrasse 59",
    "sg:city":"M\u00f6hlin",
    "sg:orig_category":"Allgemeiner Hoch U Tiefbau",
    "sg:phone":"+41 61 851 30 21",
    "sg:postcode":"4313",
    "sg:province":"Aargau",
    "wof:name":"Walo Bertschinger Ag",
    "wof:placetype":"venue"
},
  "geometry": {"coordinates":[7.843576,47.558525],"type":"Point"}
}