{
  "type": "Feature",
  "properties": {
    "iso:country":"CH",
    "sg:address":"Langackerstrasse 65",
    "sg:city":"Herrliberg",
    "sg:orig_category":"Mit dem Versicherungsgewerbe verbundene T\u00e4tigkeiten",
    "sg:phone":"+41 13917179",
    "sg:postcode":"8704",
    "sg:province":"Z\u00fcrich",
    "wof:name":"Ird Insurance Resource Development Ag",
    "wof:placetype":"venue"
},
  "geometry": {"coordinates":[8.6192646027,47.288898468],"type":"Point"}
}