{
  "type": "Feature",
  "properties": {
    "iso:country":"CH",
    "sg:address":"Via Pizzo Di Claro 7",
    "sg:city":"Bellinzona",
    "sg:orig_category":"Fachdetailhandel in Verkaufsr\u00e4umen",
    "sg:postcode":"6500",
    "sg:province":"Ticino",
    "wof:name":"Tutto Per Il Solare Di Minotti Margherita",
    "wof:placetype":"venue"
},
  "geometry": {"coordinates":[9.0213527679,46.2020874023],"type":"Point"}
}