{
  "type": "Feature",
  "properties": {
    "iso:country":"CH",
    "sg:address":"6832",
    "sg:city":"Seseglio",
    "sg:orig_category":"Detailhandel mit Brennstoffen U Heizmaterial Grosshandel mit festen Brennstoffen U Mineral\u00f6lerzeugni",
    "sg:phone":"+41 91 683 55 86",
    "sg:postcode":"6832",
    "sg:province":"Ticino",
    "wof:name":"Fulvio Balerna Combustibili",
    "wof:placetype":"venue"
},
  "geometry": {"coordinates":[8.99936,45.827068],"type":"Point"}
}