{
  "type": "Feature",
  "properties": {
    "iso:country":"CH",
    "sg:address":"Luzernerstrasse 16 6247 Sch\u00f6tz. Postfach",
    "sg:city":"Sch\u00f6tz",
    "sg:orig_category":"Elektroinstallation",
    "sg:phone":"+41 41 980 13 44",
    "sg:postcode":"6247",
    "sg:province":"Luzern",
    "wof:name":"Frey & Roth Ag",
    "wof:placetype":"venue"
},
  "geometry": {"coordinates":[7.9918260574,47.168712616],"type":"Point"}
}