{
  "type": "Feature",
  "properties": {
    "iso:country":"CH",
    "sg:address":"M\u00fchlestrasse 24",
    "sg:city":"Nieder\u00f6nz",
    "sg:orig_category":"Gartenbau",
    "sg:phone":"+41 62 961 64 86",
    "sg:postcode":"3362",
    "sg:province":"Bern",
    "wof:name":"Ernst Ryser Gartengestaltung",
    "wof:placetype":"venue"
},
  "geometry": {"coordinates":[7.6937842369,47.1887130737],"type":"Point"}
}