{
  "type": "Feature",
  "properties": {
    "iso:country":"CH",
    "sg:address":"Rue Plane-ville 5",
    "sg:city":"Chamoson",
    "sg:orig_category":"Detailhandel mit Zeitungen U Zeitschriften Kioske",
    "sg:phone":"+41 27 306 31 26",
    "sg:postcode":"1955",
    "sg:province":"Valais",
    "wof:name":"C\u00e9cile Pommaz Kiosque",
    "wof:placetype":"venue"
},
  "geometry": {"coordinates":[7.2258381844,46.2011604309],"type":"Point"}
}