{
  "type": "Feature",
  "properties": {
    "iso:country":"CH",
    "sg:address":"Wylandstrasse 10",
    "sg:city":"Winterthur",
    "sg:orig_category":"Sonstiger Grosshandel",
    "sg:phone":"+41 52 213 85 84",
    "sg:postcode":"8400",
    "sg:province":"Z\u00fcrich",
    "wof:name":"Litek Trading Ag Import Von Elektron.ger\u00e4ten",
    "wof:placetype":"venue"
},
  "geometry": {"coordinates":[8.7248258591,47.4908103943],"type":"Point"}
}