{
  "type": "Feature",
  "properties": {
    "iso:country":"CH",
    "sg:address":"B\u00fcmplizstrasse 8",
    "sg:city":"Bern",
    "sg:orig_category":"Unclassifiable Establishments",
    "sg:postcode":"3027",
    "sg:province":"Bern",
    "wof:name":"Esso Tankstelle Mit Shop Kopp Harri",
    "wof:placetype":"venue"
},
  "geometry": {"coordinates":[7.3967690468,46.9488487244],"type":"Point"}
}