{
  "type": "Feature",
  "properties": {
    "iso:country":"CH",
    "sg:address":"Frutigenstrasse 2",
    "sg:city":"Thun",
    "sg:orig_category":"Interessenvertretungen",
    "sg:postcode":"3600",
    "sg:province":"Bern",
    "wof:name":"Kasser-stiftung Elsbeth",
    "wof:placetype":"venue"
},
  "geometry": {"coordinates":[7.6293849945,46.7563247681],"type":"Point"}
}