{
  "type": "Feature",
  "properties": {
    "iso:country":"CH",
    "sg:address":"Talbachstrasse 15",
    "sg:city":"Altendorf",
    "sg:orig_category":"Herstellung von sonstigen Metallwaren Schlossereien",
    "sg:phone":"+41 55 442 77 91",
    "sg:postcode":"8852",
    "sg:province":"Schwyz",
    "wof:name":"Peter Schmucki Tresorbau & Bauschlosserei",
    "wof:placetype":"venue"
},
  "geometry": {"coordinates":[8.8074007034,47.1983604431],"type":"Point"}
}