{
  "type": "Feature",
  "properties": {
    "iso:country":"CH",
    "sg:address":"Neuquartierstrasse 29",
    "sg:city":"Biberist",
    "sg:orig_category":"Elektroinstallation Herstellung von sonstigen elektrischen Ausr\u00fcstungen",
    "sg:phone":"+41 32 671 61 61",
    "sg:postcode":"4562",
    "sg:province":"Solothurn",
    "wof:name":"Elektro Fontana Biberist Ag",
    "wof:placetype":"venue"
},
  "geometry": {"coordinates":[7.5671701431,47.1847648621],"type":"Point"}
}