{
  "type": "Feature",
  "properties": {
    "iso:country":"CH",
    "sg:address":"Rothschild Rue 57 1202 Gen\u00e8ve. Postfach",
    "sg:city":"Gen\u00e8ve",
    "sg:orig_category":"Non-Classified Establishments",
    "sg:postcode":"1202",
    "sg:province":"Gen\u00e8ve",
    "wof:name":"Les Films Concorde Sa",
    "wof:placetype":"venue"
},
  "geometry": {"coordinates":[6.1475777626,46.2153205872],"type":"Point"}
}