{
  "type": "Feature",
  "properties": {
    "iso:country":"CH",
    "sg:city":"Sch\u00fcbelbach",
    "sg:classifiers":[
        {
            "category":"Banks & Credit Unions",
            "subcategory":"Bank",
            "type":"Services"
        }
    ],
    "sg:phone":"+41 4155642018",
    "sg:postcode":"8862",
    "sg:province":"Schwyz",
    "wof:name":"Kantonalbank Schwyz",
    "wof:placetype":"venue"
},
  "geometry": {"coordinates":[8.929012,47.173405],"type":"Point"}
}