{
  "type": "Feature",
  "properties": {
    "iso:country":"CH",
    "sg:address":"Oberfeldweg 40",
    "sg:city":"Gunzgen",
    "sg:classifiers":[
        {
            "category":"Government",
            "subcategory":"Fire Station",
            "type":"Public Place"
        }
    ],
    "sg:phone":"+41 62 216 26 27",
    "sg:postcode":"4617",
    "sg:province":"Solothurn",
    "sg:tags":[
        "steel",
        "band",
        "sections",
        "punching",
        "dy"
    ],
    "wof:name":"Lsb Stanzformen Ag",
    "wof:placetype":"venue"
},
  "geometry": {"coordinates":[7.8315401077,47.3117408752],"type":"Point"}
}