{
  "type": "Feature",
  "properties": {
    "addr:full":"T\u00f6distrasse 1 Tuggen Schwyz 8856",
    "addr:housenumber":"1",
    "addr:postcode":"8856",
    "addr:street":"Toedistrasse;Schwyz",
    "iso:country":"CH",
    "sg:address":"T\u00f6distrasse 1",
    "sg:city":"Tuggen",
    "sg:orig_category":"Detailhandel mit Brot, Back U S\u00fcsswaren",
    "sg:postcode":"8856",
    "sg:province":"Schwyz",
    "wof:name":"B\u00e4ckerei-konditorei Jenni",
    "wof:placetype":"venue"
},
  "geometry": {"coordinates":[7.04263,47.020039],"type":"Point"}
}