{
  "type": "Feature",
  "properties": {
    "iso:country":"CH",
    "sg:address":"Bahnhofstrasse 17 3930 Visp Case Postale 56",
    "sg:city":"Visp",
    "sg:orig_category":"Fachdetailhandel mit pharmazeutischen Produkten",
    "sg:phone":"+41 21 881 19 80",
    "sg:postcode":"3930",
    "sg:province":"Valais",
    "wof:name":"Apotheke Db Worb Ag",
    "wof:placetype":"venue"
},
  "geometry": {"coordinates":[7.5629668236,46.9304542542],"type":"Point"}
}