{
  "type": "Feature",
  "properties": {
    "iso:country":"CH",
    "sg:address":"Bahnhofstrasse 88 5000 Aarau. Postfach",
    "sg:city":"Aarau",
    "sg:orig_category":"Kauf U Verkauf von Immobilien auf eigene Rechnung",
    "sg:postcode":"5004",
    "sg:province":"Aargau",
    "wof:name":"Horisberger Ag Liegenschaftengesch\u00e4fte Usw.",
    "wof:placetype":"venue"
},
  "geometry": {"coordinates":[8.0528650284,47.3924484253],"type":"Point"}
}