{
  "type": "Feature",
  "properties": {
    "iso:country":"CH",
    "sg:address":"5616",
    "sg:city":"Meisterschwanden",
    "sg:orig_category":"Pensionskassen",
    "sg:phone":"+41 71 313 94 00",
    "sg:postcode":"5616",
    "sg:province":"Aargau",
    "wof:name":"Personalf\u00fcrsorgestiftung Der Heer B. Ag, Verpackungen",
    "wof:placetype":"venue"
},
  "geometry": {"coordinates":[9.3123550415,47.4113883972],"type":"Point"}
}