{
  "type": "Feature",
  "properties": {
    "iso:country":"CH",
    "sg:address":"Corso Elvezia 22",
    "sg:city":"Lugano",
    "sg:orig_category":"Verlagsgewerbe",
    "sg:phone":"+41 91 922 97 57",
    "sg:postcode":"6900",
    "sg:province":"Ticino",
    "wof:name":"Neuer Johannes Verlag Rose Koch",
    "wof:placetype":"venue"
},
  "geometry": {"coordinates":[8.9561462402,46.0087776184],"type":"Point"}
}