{
  "type": "Feature",
  "properties": {
    "iso:country":"CH",
    "sg:address":"Salines Chemin Des 18a",
    "sg:city":"Aigle",
    "sg:orig_category":"Grosshandel mit sonstigen Maschinen U Ausr\u00fcstungen f\u00fcr Industrie, Handel U Schiffahrt",
    "sg:phone":"+41 24 466 49 19",
    "sg:postcode":"1860",
    "sg:province":"Vaud",
    "wof:name":"Grogg Jean-fran\u00e7ois S\u00e0rl",
    "wof:placetype":"venue"
},
  "geometry": {"coordinates":[6.9701099396,46.3175544739],"type":"Point"}
}