{
  "type": "Feature",
  "properties": {
    "iso:country":"CH",
    "sg:address":"Toches Chemin Des 1",
    "sg:city":"Echandens",
    "sg:orig_category":"Herstellung von Teppichen",
    "sg:postcode":"1026",
    "sg:province":"Vaud",
    "wof:name":"Bertolit Sa",
    "wof:placetype":"venue"
},
  "geometry": {"coordinates":[6.5408301353,46.534286499],"type":"Point"}
}