{
  "type": "Feature",
  "properties": {
    "iso:country":"CH",
    "sg:address":"Fetzislohstrasse 8",
    "sg:city":"Frasnacht",
    "sg:orig_category":"RESTAURANTS: TEA-ROOMS",
    "sg:phone":"+41 71 446 26 66",
    "sg:postcode":"9320",
    "sg:province":"Thurgau",
    "wof:name":"Dorfbeiz Zelg",
    "wof:placetype":"venue"
},
  "geometry": {"coordinates":[9.4035053253,47.5287857056],"type":"Point"}
}