{
  "type": "Feature",
  "properties": {
    "iso:country":"CH",
    "sg:address":"Vordere Hauptgasse 100",
    "sg:city":"Zofingen",
    "sg:orig_category":"Detailhandel mit Uhren U Schmuck Fachdetailhandel in Verkaufsr\u00e4umen",
    "sg:phone":"+41 62 751 11 06",
    "sg:postcode":"4800",
    "sg:province":"Aargau",
    "wof:name":"Droz",
    "wof:placetype":"venue"
},
  "geometry": {"coordinates":[7.9458141327,47.2871780396],"type":"Point"}
}