{
  "type": "Feature",
  "properties": {
    "iso:country":"CH",
    "sg:address":"Viale Stefano Franscini 1",
    "sg:city":"Lugano",
    "sg:orig_category":"Unclassifiable Establishments",
    "sg:postcode":"6900",
    "sg:province":"Ticino",
    "wof:name":"Fenaves Sa",
    "wof:placetype":"venue"
},
  "geometry": {"coordinates":[8.9525566101,46.0080795288],"type":"Point"}
}