{
  "type": "Feature",
  "properties": {
    "iso:country":"CH",
    "sg:address":"Rue De L'industrie 17",
    "sg:city":"Ste-croix",
    "sg:orig_category":"Instandhaltung U Reparatur von Automobilen",
    "sg:phone":"+41 24 454 29 09",
    "sg:postcode":"1450",
    "sg:province":"Vaud",
    "wof:name":"Garage Wyss M.",
    "wof:placetype":"venue"
},
  "geometry": {"coordinates":[6.5030360222,46.8204460144],"type":"Point"}
}