{
  "type": "Feature",
  "properties": {
    "iso:country":"CH",
    "sg:address":"Marktgasse 16",
    "sg:city":"Interlaken",
    "sg:orig_category":"Advokaturb\u00fcros",
    "sg:phone":"+41 33 822 10 15",
    "sg:postcode":"3800",
    "sg:province":"Bern",
    "wof:name":"Peter Hollinger Advokaturb\u00fcro",
    "wof:placetype":"venue"
},
  "geometry": {"coordinates":[7.853376,46.685707],"type":"Point"}
}