{
  "type": "Feature",
  "properties": {
    "iso:country":"CH",
    "sg:address":"Ackerstrasse 18",
    "sg:city":"Steckborn",
    "sg:orig_category":"Sonstige pers\u00f6nliche Dienstleistungen",
    "sg:phone":"+41 52 761 38 80",
    "sg:postcode":"8266",
    "sg:province":"Thurgau",
    "wof:name":"Kainos, Moser Christian",
    "wof:placetype":"venue"
},
  "geometry": {"coordinates":[8.9818077087,47.6635856628],"type":"Point"}
}