{
  "type": "Feature",
  "properties": {
    "iso:country":"CH",
    "sg:address":"Bielstrasse 95",
    "sg:city":"Solothurn",
    "sg:orig_category":"Saunas, Solarien, Fitnesszentren U \u00e4hnliches",
    "sg:postcode":"4500",
    "sg:province":"Solothurn",
    "wof:name":"Axis Fitnessclub Aesch Gmbh",
    "wof:placetype":"venue"
},
  "geometry": {"coordinates":[7.5975060463,47.4683036804],"type":"Point"}
}