{
  "type": "Feature",
  "properties": {
    "iso:country":"CH",
    "sg:address":"Probusweg 11",
    "sg:city":"Z\u00fcrich",
    "sg:orig_category":"Architekturb\u00fcros",
    "sg:phone":"+41 71 223 49 69",
    "sg:postcode":"8057",
    "sg:province":"Z\u00fcrich",
    "wof:name":"Frank May Architekturb\u00fcro",
    "wof:placetype":"venue"
},
  "geometry": {"coordinates":[9.377323,47.427757],"type":"Point"}
}