{
  "type": "Feature",
  "properties": {
    "iso:country":"CH",
    "sg:address":"Chemin De Val\u00e9rie 9",
    "sg:city":"Chamb\u00e9sy",
    "sg:orig_category":"Innenarchitekturb\u00fcros Innendekorationsateliers",
    "sg:phone":"+41 22 758 23 33",
    "sg:postcode":"1292",
    "sg:province":"Gen\u00e8ve",
    "wof:name":"Serge Mourreau Architecture D'int\u00e9rieur",
    "wof:placetype":"venue"
},
  "geometry": {"coordinates":[6.1417999268,46.2424697876],"type":"Point"}
}