{
  "type": "Feature",
  "properties": {
    "iso:country":"CH",
    "sg:address":"Fohlenweg 1 9230 Flawil. Postfach",
    "sg:city":"Flawil",
    "sg:orig_category":"Reiseb\u00fcros U Reiseveranstalter",
    "sg:phone":"+41 71 393 52 52",
    "sg:postcode":"9230",
    "sg:province":"St. Gallen",
    "wof:name":"Sepp Hegglin Carreisen",
    "wof:placetype":"venue"
},
  "geometry": {"coordinates":[9.172958374,47.4137535095],"type":"Point"}
}