{
  "type": "Feature",
  "properties": {
    "iso:country":"CH",
    "sg:address":"Sonnenweg 18",
    "sg:city":"Reinach",
    "sg:orig_category":"Dtp Applications",
    "sg:phone":"+41 62 771 72 38",
    "sg:postcode":"5734",
    "sg:province":"Aargau",
    "wof:name":"Coba Communication",
    "wof:placetype":"venue"
},
  "geometry": {"coordinates":[8.1907634735,47.2541694641],"type":"Point"}
}