{
  "type": "Feature",
  "properties": {
    "iso:country":"CH",
    "sg:address":"Liebetschwand",
    "sg:city":"Kerns",
    "sg:orig_category":"Abdichtung Herstellung von sonstigen Metallwaren",
    "sg:phone":"+41 41 661 08 59",
    "sg:postcode":"6064",
    "sg:province":"Obwalden",
    "wof:name":"Abdichtungsbau Durrer Gmbh",
    "wof:placetype":"venue"
},
  "geometry": {"coordinates":[8.275,46.900822],"type":"Point"}
}