{
  "type": "Feature",
  "properties": {
    "iso:country":"CH",
    "sg:address":"Rue Liotard 5",
    "sg:city":"Gen\u00e8ve",
    "sg:orig_category":"Autogaragen",
    "sg:phone":"+41 32 968 71 27",
    "sg:postcode":"1202",
    "sg:province":"Gen\u00e8ve",
    "wof:name":"Silvano Campoli Garage",
    "wof:placetype":"venue"
},
  "geometry": {"coordinates":[6.829892,47.106892],"type":"Point"}
}