{
  "type": "Feature",
  "properties": {
    "iso:country":"CH",
    "sg:address":"Simplonstrasse 37 3911 Ried-brig. Postfach",
    "sg:city":"Ried-brig",
    "sg:orig_category":"Detailhandel mit Brot, Back U S\u00fcsswaren",
    "sg:phone":"+41 27 923 13 14",
    "sg:postcode":"3911",
    "sg:province":"Valais",
    "wof:name":"Marie-toni Guntern B\u00e4ckerei-konditorei",
    "wof:placetype":"venue"
},
  "geometry": {"coordinates":[8.01647,46.316063],"type":"Point"}
}