{
  "type": "Feature",
  "properties": {
    "iso:country":"CH",
    "sg:address":"Thalgutstrasse 31",
    "sg:city":"Oberwichtrach",
    "sg:orig_category":"Non-Classified Establishments",
    "sg:postcode":"3114",
    "sg:province":"Bern",
    "wof:name":"Uw Consulting Gmbh",
    "wof:placetype":"venue"
},
  "geometry": {"coordinates":[7.5765061378,46.8433647156],"type":"Point"}
}