{
  "type": "Feature",
  "properties": {
    "iso:country":"CH",
    "sg:address":"Frontenex Avenue De 32 1207 Gen\u00e8ve. Postfach",
    "sg:city":"Gen\u00e8ve",
    "sg:orig_category":"RESTAURANTS: TEA-ROOMS",
    "sg:postcode":"1207",
    "sg:province":"Gen\u00e8ve",
    "wof:name":"Carlo Tritella",
    "wof:placetype":"venue"
},
  "geometry": {"coordinates":[7.5898418427,47.4933204651],"type":"Point"}
}