{
  "type": "Feature",
  "properties": {
    "iso:country":"CH",
    "sg:address":"7462",
    "sg:city":"Salouf",
    "sg:orig_category":"G\u00fcterbef\u00f6rderung im Strassenverkehr",
    "sg:phone":"+41 56 668 17 44",
    "sg:postcode":"7462",
    "sg:province":"Graubunden",
    "wof:name":"Stefan Furrer Transporte Gmbh",
    "wof:placetype":"venue"
},
  "geometry": {"coordinates":[8.3411598206,47.2294654846],"type":"Point"}
}