{
  "type": "Feature",
  "properties": {
    "iso:country":"CH",
    "sg:address":"Balderstrasse 30 3007 Bern. Postfach",
    "sg:city":"Bern",
    "sg:orig_category":"Vermietung U Verpachtung von eigenen Immobilien",
    "sg:postcode":"3005",
    "sg:province":"Bern",
    "wof:name":"Balder Immobilien Ag",
    "wof:placetype":"venue"
},
  "geometry": {"coordinates":[7.4238958359,46.9432296753],"type":"Point"}
}