{
  "type": "Feature",
  "properties": {
    "iso:country":"CH",
    "sg:address":"Rathausgasse 6",
    "sg:city":"Glarus",
    "sg:orig_category":"Maschinen-Fabrikation",
    "sg:phone":"+41 55 650 18 90",
    "sg:postcode":"8750",
    "sg:province":"Glarus",
    "wof:name":"Girotec Gmbh",
    "wof:placetype":"venue"
},
  "geometry": {"coordinates":[9.0666503906,47.0406913757],"type":"Point"}
}