{
  "type": "Feature",
  "properties": {
    "iso:country":"CH",
    "sg:address":"Schulstrasse 3",
    "sg:city":"Seengen",
    "sg:orig_category":"Druck ohne Zeitungsdruck Offsetdruck",
    "sg:phone":"+41 62 777 24 21",
    "sg:postcode":"5707",
    "sg:province":"Aargau",
    "wof:name":"Luckreina-druck Kurt H\u00e4uptli",
    "wof:placetype":"venue"
},
  "geometry": {"coordinates":[8.2048616409,47.3264350891],"type":"Point"}
}