{
  "type": "Feature",
  "properties": {
    "iso:country":"CH",
    "sg:address":"Hauptstrasse 70",
    "sg:city":"Bilten",
    "sg:orig_category":"Mit Sport verbundene T\u00e4tigkeiten",
    "sg:phone":"+41 55 615 21 09",
    "sg:postcode":"8865",
    "sg:province":"Glarus",
    "wof:name":"Marianne & Hansueli Sch\u00e4r Reitbetrieb",
    "wof:placetype":"venue"
},
  "geometry": {"coordinates":[9.0240812302,47.1454277039],"type":"Point"}
}