{
  "type": "Feature",
  "properties": {
    "iso:country":"CH",
    "sg:address":"Zugerstrasse 46 6340 Baar. Postfach",
    "sg:city":"Zug",
    "sg:orig_category":"Handelsvermittlung U Grosshandel",
    "sg:postcode":"6302",
    "sg:province":"Zug",
    "wof:name":"Isko Trend I. Kovacs Vertriebsagentur Import/export",
    "wof:placetype":"venue"
},
  "geometry": {"coordinates":[8.348241806,47.3481025696],"type":"Point"}
}