{
  "type": "Feature",
  "properties": {
    "iso:country":"CH",
    "sg:address":"Rothausstrasse 261",
    "sg:city":"Gampelen",
    "sg:orig_category":"Zimmerei, Dachdeckerei, Bauspenglerei U Abdichtung",
    "sg:postcode":"3236",
    "sg:province":"Bern",
    "wof:name":"Gehri E., Bedachungen Und Fassadenbau",
    "wof:placetype":"venue"
},
  "geometry": {"coordinates":[7.0319771767,47.0103492737],"type":"Point"}
}