{
  "type": "Feature",
  "properties": {
    "iso:country":"CH",
    "sg:address":"Moosb\u00fchlstrasse 37",
    "sg:city":"Moosseedorf",
    "sg:classifiers":[
        {
            "category":"Professional",
            "subcategory":"Engineering",
            "type":"Services"
        }
    ],
    "sg:phone":"+41 31 859 08 85",
    "sg:postcode":"3302",
    "sg:province":"Bern",
    "sg:tags":[
        "civil",
        "equipment",
        "machinery"
    ],
    "wof:name":"Christ Trading Ag",
    "wof:placetype":"venue"
},
  "geometry": {"coordinates":[7.486558,47.015942],"type":"Point"}
}