{
  "type": "Feature",
  "properties": {
    "iso:country":"CH",
    "sg:address":"Vieille-route 6 1338 Ballaigues. Postfach",
    "sg:city":"Grandevent",
    "sg:orig_category":"Herstellung von k\u00e4lte U lufttechnischen Erzeugnissen f\u00fcr gewerbliche Zwecke",
    "sg:phone":"+41 24 445 30 40",
    "sg:postcode":"1421",
    "sg:province":"Vaud",
    "wof:name":"Top-climat S\u00e0rl",
    "wof:placetype":"venue"
},
  "geometry": {"coordinates":[6.422522068,46.7299499512],"type":"Point"}
}