{
  "type": "Feature",
  "properties": {
    "iso:country":"CH",
    "sg:address":"Seeblick 1 6330 Cham. Postfach",
    "sg:city":"Cham",
    "sg:orig_category":"Grosshandel mit Nahrungsmitteln, Getr\u00e4nken U Tabakwaren ohne ausgepr\u00e4gten Schwerpunkt",
    "sg:phone":"+41 79 420 99 19",
    "sg:postcode":"6330",
    "sg:province":"Zug",
    "wof:name":"Uzun Markt",
    "wof:placetype":"venue"
},
  "geometry": {"coordinates":[9.0415687561,47.4641914368],"type":"Point"}
}