{
  "type": "Feature",
  "properties": {
    "iso:country":"CH",
    "sg:address":"Dorfstrasse 34 6340 Baar. Postfach 1058",
    "sg:city":"Baar",
    "sg:orig_category":"Herstellung von Teppichen Vermittlung von Immobilien",
    "sg:phone":"+41 41 761 19 66",
    "sg:postcode":"6341",
    "sg:province":"Zug",
    "wof:name":"Gr\u00fcter Immobilien Ag",
    "wof:placetype":"venue"
},
  "geometry": {"coordinates":[8.5235805511,47.1937446594],"type":"Point"}
}