{
  "type": "Feature",
  "properties": {
    "iso:country":"CH",
    "sg:address":"Zi La Foge C 1816 Chailly-montreux Case Postale 29",
    "sg:city":"Chailly-montreux",
    "sg:orig_category":"Grosshandel mit B\u00fcromaschinen Grosshandel mit Datenverarbeitungsger\u00e4ten",
    "sg:phone":"+41 21 964 73 32",
    "sg:postcode":"1816",
    "sg:province":"Vaud",
    "wof:name":"Ubc Informatik Ag",
    "wof:placetype":"venue"
},
  "geometry": {"coordinates":[6.8975777626,46.4502334595],"type":"Point"}
}