{
  "type": "Feature",
  "properties": {
    "iso:country":"CH",
    "sg:address":"Industriestrasse 16",
    "sg:city":"Zug",
    "sg:orig_category":"Grosshandel mit Erzen U Metallen",
    "sg:phone":"+41 41 710 47 70",
    "sg:postcode":"6300",
    "sg:province":"Zug",
    "wof:name":"Harlow & Jones Commodity Ag",
    "wof:placetype":"venue"
},
  "geometry": {"coordinates":[8.5188703537,47.1731300354],"type":"Point"}
}