{
  "type": "Feature",
  "properties": {
    "iso:country":"CH",
    "sg:address":"Wintersingerstrasse 4 4312 Magden. Postfach",
    "sg:city":"Magden",
    "sg:orig_category":"Detailhandel mit Radio U Fernsehger\u00e4ten Detailhandel mit elektrischen Haushalts-,Radio U Fernsehger\u00e4",
    "sg:postcode":"4312",
    "sg:province":"Aargau",
    "wof:name":"Greuter Konrad",
    "wof:placetype":"venue"
},
  "geometry": {"coordinates":[8.855550766,47.2565765381],"type":"Point"}
}