{
  "type": "Feature",
  "properties": {
    "iso:country":"CH",
    "sg:address":"Rue De Ch\u00eatre 2",
    "sg:city":"Del\u00e9mont",
    "sg:orig_category":"RESTAURANTS: TEA-ROOMS",
    "sg:postcode":"2800",
    "sg:province":"Jura",
    "wof:name":"Schumacher Und Ammann",
    "wof:placetype":"venue"
},
  "geometry": {"coordinates":[8.4185180664,47.5693397522],"type":"Point"}
}