{
  "type": "Feature",
  "properties": {
    "iso:country":"CH",
    "sg:address":"Ringstrasse 15a",
    "sg:city":"D\u00fcbendorf",
    "sg:orig_category":"Hardwareberatung Informatikdienste",
    "sg:phone":"+41 18245555",
    "sg:postcode":"8600",
    "sg:province":"Z\u00fcrich",
    "wof:name":"Also It-services Ag",
    "wof:placetype":"venue"
},
  "geometry": {"coordinates":[8.6053600311,47.3989067078],"type":"Point"}
}