{
  "type": "Feature",
  "properties": {
    "iso:country":"CH",
    "sg:address":"Industriestrasse 25",
    "sg:city":"B\u00f6singen",
    "sg:orig_category":"Sanit\u00e4r U Heizungsinstallation Sanit\u00e4r, Heizungs U L\u00fcftungsinstallation",
    "sg:phone":"+41 31 747 80 38",
    "sg:postcode":"3178",
    "sg:province":"Fribourg",
    "wof:name":"Baeriswyl & Perler Gmbh",
    "wof:placetype":"venue"
},
  "geometry": {"coordinates":[7.231361866,46.9003791809],"type":"Point"}
}