{
  "type": "Feature",
  "properties": {
    "iso:country":"CH",
    "sg:address":"Hauptstrasse 1 5015 Niedererlinsbach. Postfach 180",
    "sg:city":"Niedererlinsbach",
    "sg:orig_category":"Kauf U Verkauf von Immobilien auf eigene Rechnung",
    "sg:phone":"+41 62 844 46 46",
    "sg:postcode":"5015",
    "sg:province":"Solothurn",
    "wof:name":"Drmh Immobilien Gmbh",
    "wof:placetype":"venue"
},
  "geometry": {"coordinates":[8.0084104538,47.3970947266],"type":"Point"}
}