{
  "type": "Feature",
  "properties": {
    "iso:country":"CH",
    "sg:address":"Klosterstrasse 15",
    "sg:city":"Luzern",
    "sg:orig_category":"Herstellung von sonstigen Maschinen f\u00fcr bestimmte Verwendung",
    "sg:postcode":"6003",
    "sg:province":"Luzern",
    "wof:name":"Balance Gmbh",
    "wof:placetype":"venue"
},
  "geometry": {"coordinates":[8.3006505966,47.0492095947],"type":"Point"}
}