{
  "type": "Feature",
  "properties": {
    "iso:country":"CH",
    "sg:address":"Baarerstrasse 73",
    "sg:city":"Zug",
    "sg:orig_category":"Detailhandel mit Metallwaren, Anstrichmitteln, Glaswaren, Bau U Heimwerkerbedarf",
    "sg:postcode":"6300",
    "sg:province":"Zug",
    "wof:name":"Zeka Holding Ag",
    "wof:placetype":"venue"
},
  "geometry": {"coordinates":[8.5175857544,47.1768951416],"type":"Point"}
}