{
  "type": "Feature",
  "properties": {
    "iso:country":"CH",
    "sg:address":"Huebstrasse 1",
    "sg:city":"Wolfhausen",
    "sg:orig_category":"Herstellung von sonstigen chemischen Erzeugnissen Herstellung von sonstigen organischen Grundstoffen",
    "sg:phone":"+41 55 253 10 40",
    "sg:postcode":"8633",
    "sg:province":"Z\u00fcrich",
    "wof:name":"Thedra-z\u00fcrich Ag",
    "wof:placetype":"venue"
},
  "geometry": {"coordinates":[8.7955226898,47.2573318481],"type":"Point"}
}