{
  "type": "Feature",
  "properties": {
    "iso:country":"CH",
    "sg:address":"Hegenheimerstrasse 97 4055 Basel. Postfach",
    "sg:city":"Basel",
    "sg:orig_category":"G\u00fcterbef\u00f6rderung im Strassenverkehr",
    "sg:phone":"+41 61 381 39 43",
    "sg:postcode":"4012",
    "sg:province":"Basel-Stadt",
    "wof:name":"Zum Einhorn Vetsch J.",
    "wof:placetype":"venue"
},
  "geometry": {"coordinates":[7.5689578056,47.5612220764],"type":"Point"}
}