{
  "type": "Feature",
  "properties": {
    "iso:country":"CH",
    "sg:address":"Bernstrasse 112 3053 M\u00fcnchenbuchsee. Postfach 381",
    "sg:city":"Zollikofen",
    "sg:orig_category":"Herstellung von Metallkonstruktionen Stahl U Leichtmetallbau",
    "sg:phone":"+41 31 869 11 22",
    "sg:postcode":"3052",
    "sg:province":"Bern",
    "wof:name":"Gr\u00e4del Ag",
    "wof:placetype":"venue"
},
  "geometry": {"coordinates":[7.4596967697,47.0088157654],"type":"Point"}
}