{
  "type": "Feature",
  "properties": {
    "iso:country":"CH",
    "sg:address":"Erlenstrasse 4b",
    "sg:city":"Rotkreuz",
    "sg:orig_category":"Unternehmensberatung",
    "sg:phone":"+41 79 340 72 61",
    "sg:postcode":"6343",
    "sg:province":"Zug",
    "wof:name":"Burri Trade Support",
    "wof:placetype":"venue"
},
  "geometry": {"coordinates":[8.430431366,47.1490135193],"type":"Point"}
}