{
  "type": "Feature",
  "properties": {
    "iso:country":"CH",
    "sg:address":"4806",
    "sg:city":"Wikon",
    "sg:orig_category":"Gemeindeverwaltungen",
    "sg:phone":"+41 18691020",
    "sg:postcode":"4806",
    "sg:province":"Luzern",
    "wof:name":"Gemeindeverwaltung Wil",
    "wof:placetype":"venue"
},
  "geometry": {"coordinates":[8.5079927444,47.6052703857],"type":"Point"}
}