{
  "type": "Feature",
  "properties": {
    "addr:full":"Ziegelackerstrasse 9a Bern Bern 3027",
    "addr:housenumber":"9a",
    "addr:postcode":"3027",
    "addr:street":"Ziegelackerstrasse",
    "iso:country":"CH",
    "sg:address":"Ziegelackerstrasse 9a",
    "sg:city":"Bern",
    "sg:classifiers":[
        {
            "category":"Education",
            "subcategory":"Vocational School",
            "type":"Public Place"
        }
    ],
    "sg:phone":"+41 31 992 76 76",
    "sg:postcode":"3027",
    "sg:province":"Bern",
    "sg:tags":[
        "assembly",
        "testing",
        "printed",
        "circuit",
        "pcb",
        "board"
    ],
    "wof:name":"Ernst Roser Ag",
    "wof:placetype":"venue"
},
  "geometry": {"coordinates":[7.401937,46.948746],"type":"Point"}
}