{
  "type": "Feature",
  "properties": {
    "iso:country":"CH",
    "sg:address":"Avenue De La Fusion 92",
    "sg:city":"Martigny",
    "sg:orig_category":"Fahrschulen, Flugschulen",
    "sg:phone":"+41 27 722 18 86",
    "sg:postcode":"1920",
    "sg:province":"Valais",
    "wof:name":"Georges Vouilloz Auto-\u00e9cole",
    "wof:placetype":"venue"
},
  "geometry": {"coordinates":[7.0654101372,46.097858429],"type":"Point"}
}