{
  "type": "Feature",
  "properties": {
    "iso:country":"CH",
    "sg:address":"Via Del Fano",
    "sg:city":"Pazzallo",
    "sg:orig_category":"Primarschulen",
    "sg:phone":"+41 91 994 40 96",
    "sg:postcode":"6912",
    "sg:province":"Ticino",
    "wof:name":"Scuola Elementare Centro Scolastico",
    "wof:placetype":"venue"
},
  "geometry": {"coordinates":[8.9410200119,45.9836387634],"type":"Point"}
}