{
  "type": "Feature",
  "properties": {
    "iso:country":"CH",
    "sg:address":"Rebenweg 10",
    "sg:city":"Winterthur",
    "sg:orig_category":"Detektivb\u00fcros U \u00dcberwachung Herstellung von sonstigen Metallwaren",
    "sg:phone":"+41 52 226 05 25",
    "sg:postcode":"8408",
    "sg:province":"Z\u00fcrich",
    "wof:name":"Power Security, Eugen Hallauer",
    "wof:placetype":"venue"
},
  "geometry": {"coordinates":[8.6864624023,47.5146217346],"type":"Point"}
}