{
  "type": "Feature",
  "properties": {
    "iso:country":"CH",
    "sg:address":"Weggisg. 14",
    "sg:city":"Luzern",
    "sg:classifiers":[
        {
            "category":"Shopping",
            "subcategory":"Bicycles & Sporting Goods",
            "type":"Retail Goods"
        }
    ],
    "sg:phone":"+41 41 410 45 38",
    "sg:postcode":"6004",
    "sg:province":"Luzern",
    "sg:tags":[
        "product",
        "sport",
        "miscellaneous"
    ],
    "wof:name":"Bannwart Sport Ag",
    "wof:placetype":"venue"
},
  "geometry": {"coordinates":[8.3043746948,47.0495452881],"type":"Point"}
}