{
  "type": "Feature",
  "properties": {
    "iso:country":"CH",
    "sg:address":"Seedorfweg 12",
    "sg:city":"M\u00fcnchenbuchsee",
    "sg:orig_category":"Grosshandel mit festen Brennstoffen U Mineral\u00f6lerzeugnissen",
    "sg:phone":"+41 31693562",
    "sg:postcode":"3053",
    "sg:province":"Bern",
    "wof:name":"Hofer-graf Hanna",
    "wof:placetype":"venue"
},
  "geometry": {"coordinates":[7.455696106,47.0181846619],"type":"Point"}
}