{
  "type": "Feature",
  "properties": {
    "iso:country":"CH",
    "sg:address":"Tour-haldimand Av. De La 5",
    "sg:city":"Pully",
    "sg:orig_category":"Unternehmensberatung",
    "sg:postcode":"1009",
    "sg:province":"Vaud",
    "wof:name":"Ebc Bosshard Ernst Consulting Services",
    "wof:placetype":"venue"
},
  "geometry": {"coordinates":[8.7609901428,47.3074913025],"type":"Point"}
}