{
  "type": "Feature",
  "properties": {
    "iso:country":"CH",
    "sg:address":"B\u00e4rengasse 10",
    "sg:city":"Z\u00fcrich",
    "sg:orig_category":"Detailhandel mit Geschenkartikeln U Souvenirs",
    "sg:phone":"+41 12210122",
    "sg:postcode":"8001",
    "sg:province":"Z\u00fcrich",
    "wof:name":"Brunschwig & Cie Sa Bon G\u00e9nie Les Boutiques",
    "wof:placetype":"venue"
},
  "geometry": {"coordinates":[8.5371713638,47.3700218201],"type":"Point"}
}