{
  "type": "Feature",
  "properties": {
    "iso:country":"CH",
    "sg:address":"Br\u00fchlstrasse 103",
    "sg:city":"Arbon",
    "sg:orig_category":"Vereine Radio, Film and Foto",
    "sg:postcode":"9320",
    "sg:province":"Thurgau",
    "wof:name":"Amateur-film-klub Aarau",
    "wof:placetype":"venue"
},
  "geometry": {"coordinates":[8.3174819946,47.2825775146],"type":"Point"}
}