{
  "type": "Feature",
  "properties": {
    "iso:country":"CH",
    "sg:address":"Silbergasse 2",
    "sg:city":"Biel/bienne",
    "sg:orig_category":"Kosmetikinstitute",
    "sg:phone":"+41 32 323 19 82",
    "sg:postcode":"2502",
    "sg:province":"Bern",
    "wof:name":"Josefina Alonso Kosmetikinstitut",
    "wof:placetype":"venue"
},
  "geometry": {"coordinates":[7.2452769279,47.1341209412],"type":"Point"}
}