{
  "type": "Feature",
  "properties": {
    "iso:country":"CH",
    "sg:address":"Le Closel",
    "sg:city":"Bossonnens",
    "sg:orig_category":"Gemeindeverwaltungen",
    "sg:phone":"+41 21 947 44 88",
    "sg:postcode":"1615",
    "sg:province":"Fribourg",
    "wof:name":"Administration Communale De Bossonnens",
    "wof:placetype":"venue"
},
  "geometry": {"coordinates":[6.8522148132,46.5260009766],"type":"Point"}
}