{
  "type": "Feature",
  "properties": {
    "iso:country":"CH",
    "sg:address":"Wildsbergstrasse 44 8606 Greifensee. Postfach",
    "sg:city":"N\u00e4nikon",
    "sg:orig_category":"Handel mit Automobilen",
    "sg:postcode":"8606",
    "sg:province":"Z\u00fcrich",
    "wof:name":"Weidmann B. Automobilie Ag",
    "wof:placetype":"venue"
},
  "geometry": {"coordinates":[8.6915531158,47.3570594788],"type":"Point"}
}