{
  "type": "Feature",
  "properties": {
    "iso:country":"CH",
    "sg:address":"Industriestrasse 16",
    "sg:city":"St\u00e4fa",
    "sg:orig_category":"Herstellung von Konstruktionsteilen, Fertigbauteilen U Ausbauelementen aus Holz",
    "sg:phone":"+41 17962633",
    "sg:postcode":"8712",
    "sg:province":"Z\u00fcrich",
    "wof:name":"Bz Holz Gmbh",
    "wof:placetype":"venue"
},
  "geometry": {"coordinates":[8.742225647,47.2377243042],"type":"Point"}
}