{
  "type": "Feature",
  "properties": {
    "iso:country":"CH",
    "sg:address":"Chemin Louis Degallier 6",
    "sg:city":"Versoix",
    "sg:orig_category":"Sanit\u00e4r, Heizungs U L\u00fcftungsinstallation",
    "sg:phone":"+41 22 755 19 27",
    "sg:postcode":"1290",
    "sg:province":"Gen\u00e8ve",
    "wof:name":"Zahnd Werner.",
    "wof:placetype":"venue"
},
  "geometry": {"coordinates":[6.1634111404,46.2816810608],"type":"Point"}
}