{
  "type": "Feature",
  "properties": {
    "iso:country":"CH",
    "sg:address":"Contrat-social Rue Du 9 1203 Gen\u00e8ve. Postfach",
    "sg:city":"Gen\u00e8ve",
    "sg:orig_category":"Herstellung von Kork, Flecht U Korbwaren",
    "sg:postcode":"1203",
    "sg:province":"Gen\u00e8ve",
    "wof:name":"Conterio Claude.",
    "wof:placetype":"venue"
},
  "geometry": {"coordinates":[6.1219968796,46.2052307129],"type":"Point"}
}