{
  "type": "Feature",
  "properties": {
    "iso:country":"CH",
    "sg:address":"Frohnibiel",
    "sg:city":"Birgisch",
    "sg:orig_category":"Sportvereine Unihockey",
    "sg:phone":"+41 79 344 37 00",
    "sg:postcode":"3901",
    "sg:province":"Valais",
    "wof:name":"Uhc Niederhasli",
    "wof:placetype":"venue"
},
  "geometry": {"coordinates":[8.4974508286,47.4923553467],"type":"Point"}
}