{
  "type": "Feature",
  "properties": {
    "iso:country":"CH",
    "sg:address":"Zeughausgasse 7a",
    "sg:city":"Zug",
    "sg:orig_category":"Unclassifiable Establishments",
    "sg:postcode":"6300",
    "sg:province":"Zug",
    "wof:name":"Aswenta Holding Ag",
    "wof:placetype":"venue"
},
  "geometry": {"coordinates":[8.5161848068,47.1671218872],"type":"Point"}
}