{
  "type": "Feature",
  "properties": {
    "iso:country":"CH",
    "sg:address":"Clarahofweg 16",
    "sg:city":"Basel",
    "sg:orig_category":"Werbeberatung Werbung",
    "sg:phone":"+41 61 273 23 32",
    "sg:postcode":"4058",
    "sg:province":"Basel-Stadt",
    "wof:name":"Brandcom Bernardis Claudio",
    "wof:placetype":"venue"
},
  "geometry": {"coordinates":[7.5967288017,47.561580658],"type":"Point"}
}