{
  "type": "Feature",
  "properties": {
    "iso:country":"CH",
    "sg:address":"Z\u00fcrcherstrasse 106",
    "sg:city":"Oberengstringen",
    "sg:classifiers":[
        {
            "category":"Restaurant",
            "type":"Food & Drink"
        }
    ],
    "sg:phone":"+41 26 672 12 22",
    "sg:postcode":"8102",
    "sg:province":"Z\u00fcrich",
    "wof:name":"Restaurant Freiburger-falle",
    "wof:placetype":"venue"
},
  "geometry": {"coordinates":[7.1084527969,46.9252319336],"type":"Point"}
}