{
  "type": "Feature",
  "properties": {
    "iso:country":"CH",
    "sg:address":"M\u00fcnstergasse 51",
    "sg:city":"Bern",
    "sg:orig_category":"Detailhandel mit Bekleidung Detailhandel mit Uhren U Schmuck",
    "sg:phone":"+41 31 311 61 06",
    "sg:postcode":"3011",
    "sg:province":"Bern",
    "wof:name":"Tend\u00f6l Losinger Tibet Lhasa-laden",
    "wof:placetype":"venue"
},
  "geometry": {"coordinates":[7.44971,46.947327],"type":"Point"}
}