{
  "type": "Feature",
  "properties": {
    "iso:country":"CH",
    "sg:address":"Kesswilerstr. 20",
    "sg:city":"Uttwil",
    "sg:classifiers":[
        {
            "category":"Autos & Motor Vehicles",
            "subcategory":"Boat Sales",
            "type":"Retail Goods"
        }
    ],
    "sg:phone":"+41 4117151344",
    "sg:postcode":"8592",
    "sg:province":"Thurgau",
    "sg:tags":[
        "equipment",
        "transport"
    ],
    "wof:name":"Boesch Motorboote Ag",
    "wof:placetype":"venue"
},
  "geometry": {"coordinates":[9.28226,53.687328],"type":"Point"}
}