{
  "type": "Feature",
  "properties": {
    "iso:country":"CH",
    "sg:address":"Marstallweg 9 8005 Z\u00fcrich. Postfach",
    "sg:city":"Z\u00fcrich",
    "sg:orig_category":"Herstellung von k\u00e4lte U lufttechnischen Erzeugnissen f\u00fcr gewerbliche Zwecke",
    "sg:postcode":"8001",
    "sg:province":"Z\u00fcrich",
    "wof:name":"Climacraft, Bruderer Matthias Klima, K\u00e4ltemaschinen Usw; Install., Handel",
    "wof:placetype":"venue"
},
  "geometry": {"coordinates":[8.5328998566,47.3828430176],"type":"Point"}
}