{
  "type": "Feature",
  "properties": {
    "iso:country":"CH",
    "sg:address":"Sonnenbergstrasse 237",
    "sg:city":"Remigen",
    "sg:orig_category":"Herstellung von Reiseartikeln, Leder U Sattlerwaren Innendekorationsateliers",
    "sg:phone":"+41 56 284 21 75",
    "sg:postcode":"5236",
    "sg:province":"Aargau",
    "wof:name":"Felix M\u00e4rki Sattler & Tapezierer",
    "wof:placetype":"venue"
},
  "geometry": {"coordinates":[8.1918554306,47.5172042847],"type":"Point"}
}