{
  "type": "Feature",
  "properties": {
    "iso:country":"CH",
    "sg:address":"Hofjistrasse 1",
    "sg:city":"Glis",
    "sg:orig_category":"Installation von Heizungs, L\u00fcftungs U Klimaanlagen",
    "sg:phone":"+41 27 923 90 86",
    "sg:postcode":"3902",
    "sg:province":"Valais",
    "wof:name":"Erich Stelljes K\u00e4lteservice Glis",
    "wof:placetype":"venue"
},
  "geometry": {"coordinates":[7.9776821136,46.3108596802],"type":"Point"}
}