{
  "type": "Feature",
  "properties": {
    "iso:country":"CH",
    "sg:address":"Z\u00fcrcherstrasse 85 8730 Uznach. Postfach 140",
    "sg:city":"Uznach",
    "sg:orig_category":"Grosshandel mit Tabakwaren",
    "sg:phone":"+41 55 280 21 06",
    "sg:postcode":"8730",
    "sg:province":"St. Gallen",
    "wof:name":"Tabak Frehner Ag, Uznach",
    "wof:placetype":"venue"
},
  "geometry": {"coordinates":[8.9686031342,47.2287101746],"type":"Point"}
}