{
  "type": "Feature",
  "properties": {
    "iso:country":"CH",
    "sg:address":"Largo Bustelli",
    "sg:city":"Besazio",
    "sg:orig_category":"Detailhandel mit Waren verschiedener Art, Hauptrichtung Nahrungsmittel Grosshandel mit Nahrungsmitte",
    "sg:phone":"+41 91 646 00 65",
    "sg:postcode":"6863",
    "sg:province":"Ticino",
    "wof:name":"Negozio Alimentari Di Giovanni Di Marco",
    "wof:placetype":"venue"
},
  "geometry": {"coordinates":[8.9532632828,45.8726463318],"type":"Point"}
}