{
  "type": "Feature",
  "properties": {
    "iso:country":"CH",
    "sg:address":"Wildeggstrasse 5",
    "sg:city":"St.gallen",
    "sg:orig_category":"Vereine Orchester",
    "sg:phone":"+41 71 245 11 58",
    "sg:postcode":"9000",
    "sg:province":"St. Gallen",
    "wof:name":"Collegium Musicum St.gallen Kammerorchester",
    "wof:placetype":"venue"
},
  "geometry": {"coordinates":[9.390627861,47.4304122925],"type":"Point"}
}