{
  "type": "Feature",
  "properties": {
    "iso:country":"CH",
    "sg:address":"G\u00fcterstrasse 116",
    "sg:city":"Basel",
    "sg:orig_category":"Kantonalbanken",
    "sg:phone":"+41 61 266 33 88",
    "sg:postcode":"4053",
    "sg:province":"Basel-Stadt",
    "wof:name":"Basler Kantonalbank - Bkb Agentur G\u00fcterstrasse",
    "wof:placetype":"venue"
},
  "geometry": {"coordinates":[7.5875029564,47.5454063416],"type":"Point"}
}