{
  "type": "Feature",
  "properties": {
    "iso:country":"CH",
    "sg:address":"Avenue D'echallens 82",
    "sg:city":"Lausanne",
    "sg:classifiers":[
        {
            "category":"Restaurant",
            "type":"Food & Drink"
        }
    ],
    "sg:phone":"+41 21 922 42 52",
    "sg:postcode":"1004",
    "sg:province":"Vaud",
    "wof:name":"Caf\u00e9 L'alternative",
    "wof:placetype":"venue"
},
  "geometry": {"coordinates":[5.6025900841,45.9854125977],"type":"Point"}
}