{
  "type": "Feature",
  "properties": {
    "iso:country":"CH",
    "sg:address":"Baselstrasse 2",
    "sg:city":"Liesberg",
    "sg:orig_category":"Institutionen f\u00fcr Behinderte Tagesheime f\u00fcr Behinderte, gesch\u00fctzte Werkst\u00e4tten",
    "sg:phone":"+41 61 771 90 95",
    "sg:postcode":"4253",
    "sg:province":"Basel-Landschaft",
    "wof:name":"Wohn-& Besch\u00e4ftigungsheim Hirsacker",
    "wof:placetype":"venue"
},
  "geometry": {"coordinates":[7.4458470345,47.4014930725],"type":"Point"}
}