{
  "type": "Feature",
  "properties": {
    "iso:country":"CH",
    "sg:address":"Wolfacker 721",
    "sg:city":"Egerkingen",
    "sg:classifiers":[
        {
            "category":"Autos & Motor Vehicles",
            "subcategory":"Recreational Vehicle Sales",
            "type":"Retail Goods"
        }
    ],
    "sg:phone":"+41 62 398 21 21",
    "sg:postcode":"4622",
    "sg:province":"Solothurn",
    "sg:tags":[
        "sportvereine",
        "go-kart",
        "kart"
    ],
    "wof:name":"Kart-club Rothrist",
    "wof:placetype":"venue"
},
  "geometry": {"coordinates":[7.8007998466,47.3170089722],"type":"Point"}
}