{
  "type": "Feature",
  "properties": {
    "iso:country":"CH",
    "sg:address":"Rainstrasse 81",
    "sg:city":"St\u00e4fa",
    "sg:orig_category":"Herstellung von Konstruktionsteilen, Fertigbauteilen U Ausbauelementen aus Holz",
    "sg:postcode":"8712",
    "sg:province":"Z\u00fcrich",
    "wof:name":"Schenk Ernst, Eidg. Dipl. M\u00f6belschreiner.",
    "wof:placetype":"venue"
},
  "geometry": {"coordinates":[8.7196426392,47.2489204407],"type":"Point"}
}