{
  "type": "Feature",
  "properties": {
    "iso:country":"CH",
    "sg:address":"Chollerstrasse 35",
    "sg:city":"Zug",
    "sg:orig_category":"Hardwareberatung",
    "sg:postcode":"6300",
    "sg:province":"Zug",
    "wof:name":"Fix Computers Ag",
    "wof:placetype":"venue"
},
  "geometry": {"coordinates":[8.4913597107,47.1862449646],"type":"Point"}
}