{
  "type": "Feature",
  "properties": {
    "iso:country":"CH",
    "sg:address":"Route De Chamblioux 15",
    "sg:city":"Granges-paccot",
    "sg:orig_category":"Instandhaltung U Reparatur von Automobilen",
    "sg:phone":"+41 26 466 39 19",
    "sg:postcode":"1763",
    "sg:province":"Fribourg",
    "wof:name":"Garage Daniel Scherer Ag",
    "wof:placetype":"venue"
},
  "geometry": {"coordinates":[7.139526844,46.8126487732],"type":"Point"}
}