{
  "type": "Feature",
  "properties": {
    "addr:full":"Hasli 56 3132 Riggisberg. Postfach Riggisberg Bern 3132",
    "addr:housenumber":"56",
    "addr:postcode":"3132 riggisberg. postfach;3132",
    "addr:street":"Hasli",
    "iso:country":"CH",
    "sg:address":"Hasli 56 3132 Riggisberg. Postfach",
    "sg:city":"Riggisberg",
    "sg:orig_category":"Allgemeiner Hoch U Tiefbau",
    "sg:phone":"+41 31 809 15 66",
    "sg:postcode":"3132",
    "sg:province":"Bern",
    "wof:name":"Botta Andres Baugesch\u00e4ft Gmbh",
    "wof:placetype":"venue"
},
  "geometry": {"coordinates":[7.47643,46.809311],"type":"Point"}
}