{
  "type": "Feature",
  "properties": {
    "iso:country":"CH",
    "sg:address":"Via Bagutti 18",
    "sg:city":"Lugano",
    "sg:orig_category":"Grosshandel mit Datenverarbeitungsger\u00e4ten Grosshandel mit Software",
    "sg:phone":"+41 91 976 10 00",
    "sg:postcode":"6900",
    "sg:province":"Ticino",
    "wof:name":"Ticino Computer Express Sagl",
    "wof:placetype":"venue"
},
  "geometry": {"coordinates":[8.9567298889,46.0153694153],"type":"Point"}
}