{
  "type": "Feature",
  "properties": {
    "iso:country":"CH",
    "sg:address":"Grundrebenstrasse 109",
    "sg:city":"Mettmenstetten",
    "sg:orig_category":"Sonstiger Grosshandel",
    "sg:postcode":"8932",
    "sg:province":"Z\u00fcrich",
    "wof:name":"East West Import Export Malmstr\u00f6m",
    "wof:placetype":"venue"
},
  "geometry": {"coordinates":[8.4665298462,47.2486381531],"type":"Point"}
}