{
  "type": "Feature",
  "properties": {
    "iso:country":"CH",
    "sg:address":"Via Ai Ronchi 17.",
    "sg:city":"Vezia",
    "sg:orig_category":"Wirtschaftspr\u00fcfung, Steuerberatung U Treuhand",
    "sg:phone":"+41 32 677 04 55",
    "sg:postcode":"6943",
    "sg:province":"Ticino",
    "wof:name":"Lemag Treuhand & Partner Gmbh",
    "wof:placetype":"venue"
},
  "geometry": {"coordinates":[7.524810791,47.1698150635],"type":"Point"}
}