{
  "type": "Feature",
  "properties": {
    "iso:country":"CH",
    "sg:address":"Landstrasse 3 5322 Koblenz. Postfach 32",
    "sg:city":"Koblenz",
    "sg:orig_category":"Vermittlung von Immobilien Verwaltung von Immobilien",
    "sg:phone":"+41 71 929 50 50",
    "sg:postcode":"5322",
    "sg:province":"Aargau",
    "wof:name":"Zoller & Partner Immobilien-management Ag",
    "wof:placetype":"venue"
},
  "geometry": {"coordinates":[9.0491724014,47.4549369812],"type":"Point"}
}