{
  "type": "Feature",
  "properties": {
    "iso:country":"CH",
    "sg:address":"T\u00f6rliweg 1",
    "sg:city":"Maienfeld",
    "sg:orig_category":"Kantonalbanken",
    "sg:phone":"+41 81 302 18 57",
    "sg:postcode":"7304",
    "sg:province":"Graubunden",
    "wof:name":"Graub\u00fcndner Kantonalbank",
    "wof:placetype":"venue"
},
  "geometry": {"coordinates":[9.5304698944,47.0059280396],"type":"Point"}
}