{
  "type": "Feature",
  "properties": {
    "iso:country":"CH",
    "sg:address":"Lake-placid",
    "sg:city":"Haute-nendaz",
    "sg:orig_category":"Detailhandel mit Damenbekleidung",
    "sg:phone":"+41 71 944 25 22",
    "sg:postcode":"1997",
    "sg:province":"Valais",
    "wof:name":"Margrit Civiletto Brautmode Margrit",
    "wof:placetype":"venue"
},
  "geometry": {"coordinates":[9.113257,47.476776],"type":"Point"}
}