{
  "type": "Feature",
  "properties": {
    "iso:country":"CH",
    "sg:address":"Dorfgasse 16",
    "sg:city":"Horgen",
    "sg:orig_category":"Fachdetailhandel in Verkaufsr\u00e4umen",
    "sg:postcode":"8810",
    "sg:province":"Z\u00fcrich",
    "wof:name":"Collactions Gmbh",
    "wof:placetype":"venue"
},
  "geometry": {"coordinates":[8.599070549,47.2603912354],"type":"Point"}
}