{
  "type": "Feature",
  "properties": {
    "iso:country":"CH",
    "sg:address":"Burgerstrasse 1",
    "sg:city":"Luzern",
    "sg:orig_category":"Non-Classified Establishments",
    "sg:postcode":"6000",
    "sg:province":"Luzern",
    "wof:name":"R\u00fcss-st\u00e4g Optik Gmbh",
    "wof:placetype":"venue"
},
  "geometry": {"coordinates":[8.3030395508,47.0509490967],"type":"Point"}
}