{
  "type": "Feature",
  "properties": {
    "iso:country":"CH",
    "sg:address":"Aecherlistrasse",
    "sg:city":"Kerns",
    "sg:orig_category":"Detailhandel mit Milcherzeugnissen U Eiern Verarbeitung von Milch",
    "sg:phone":"+41 41 660 23 26",
    "sg:postcode":"6064",
    "sg:province":"Obwalden",
    "wof:name":"Alois Wagner Gmbh Sennerei",
    "wof:placetype":"venue"
},
  "geometry": {"coordinates":[8.2931251526,46.9087409973],"type":"Point"}
}