{
  "type": "Feature",
  "properties": {
    "iso:country":"CH",
    "sg:address":"Obere Matt",
    "sg:city":"St\u00e4fa",
    "sg:orig_category":"Detailhandel mit Fleisch U Fleischwaren",
    "sg:postcode":"8712",
    "sg:province":"Z\u00fcrich",
    "wof:name":"Baggenstos Ag",
    "wof:placetype":"venue"
},
  "geometry": {"coordinates":[8.7154979706,47.2480735779],"type":"Point"}
}