{
  "type": "Feature",
  "properties": {
    "addr:full":"Heidemurweg 30 Kaiseraugst Aargau 4303",
    "addr:housenumber":"30",
    "addr:postcode":"4303",
    "addr:street":"Heidemurweg",
    "iso:country":"CH",
    "sg:address":"Heidemurweg 30",
    "sg:city":"Kaiseraugst",
    "sg:classifiers":[
        {
            "category":"Education",
            "subcategory":"Library",
            "type":"Public Place"
        }
    ],
    "sg:phone":"+41 61 811 15 85",
    "sg:postcode":"4303",
    "sg:province":"Aargau",
    "sg:tags":[
        "u",
        "bibliotheken",
        "archive"
    ],
    "wof:name":"Katholische Pfarrbibliothek",
    "wof:placetype":"venue"
},
  "geometry": {"coordinates":[7.724539,47.53986],"type":"Point"}
}