{
  "type": "Feature",
  "properties": {
    "iso:country":"CH",
    "sg:address":"Hofstetten",
    "sg:city":"Schenkon",
    "sg:orig_category":"Grosshandel mit lebenden Tieren",
    "sg:postcode":"6214",
    "sg:province":"Luzern",
    "wof:name":"Schmid Josef Viehvermarktung",
    "wof:placetype":"venue"
},
  "geometry": {"coordinates":[8.127532959,47.1833724976],"type":"Point"}
}