{
  "type": "Feature",
  "properties": {
    "iso:country":"CH",
    "sg:address":"Graswinkelstrasse 3",
    "sg:city":"Kloten",
    "sg:orig_category":"Finanzierungsinstitutionen",
    "sg:phone":"+41 18130462",
    "sg:postcode":"8302",
    "sg:province":"Z\u00fcrich",
    "wof:name":"Eco Finanz-& Umweltberatung Thea Maria Hefti",
    "wof:placetype":"venue"
},
  "geometry": {"coordinates":[8.5960435867,47.4513702393],"type":"Point"}
}