{
  "type": "Feature",
  "properties": {
    "iso:country":"CH",
    "sg:address":"Flugbrunnen",
    "sg:city":"Bolligen",
    "sg:orig_category":"Blumen U Zierpflanzenbau Detailhandel mit Blumen U Pflanzen",
    "sg:phone":"+41 31 921 76 80",
    "sg:postcode":"3065",
    "sg:province":"Bern",
    "wof:name":"Werner Bergmann G\u00e4rtnerei",
    "wof:placetype":"venue"
},
  "geometry": {"coordinates":[7.50879,46.974258],"type":"Point"}
}