{
  "type": "Feature",
  "properties": {
    "iso:country":"CH",
    "sg:address":"Platz 8",
    "sg:city":"Herisau",
    "sg:orig_category":"Unclassifiable Establishments",
    "sg:postcode":"9100",
    "sg:province":"Appenzell Ausserrhoden",
    "wof:name":"Th. Tschuor",
    "wof:placetype":"venue"
},
  "geometry": {"coordinates":[9.1225099564,46.7561416626],"type":"Point"}
}