{
  "type": "Feature",
  "properties": {
    "iso:country":"CH",
    "sg:address":"Hungerb\u00fchl 36",
    "sg:city":"Salmsach",
    "sg:orig_category":"Gem\u00fcsebau",
    "sg:phone":"+41 71 463 55 61",
    "sg:postcode":"8599",
    "sg:province":"Thurgau",
    "wof:name":"Ralph B\u00f6tsch Gem\u00fcsebau Z.m\u00fchle",
    "wof:placetype":"venue"
},
  "geometry": {"coordinates":[9.3709411621,47.5535392761],"type":"Point"}
}