{
  "type": "Feature",
  "properties": {
    "iso:country":"CH",
    "sg:address":"Unterb\u00fcntelistrasse 12",
    "sg:city":"Widnau",
    "sg:orig_category":"Detailhandel mit Brennstoffen U Heizmaterial Grosshandel mit festen Brennstoffen U Mineral\u00f6lerzeugni",
    "sg:phone":"+41 71 722 16 39",
    "sg:postcode":"9443",
    "sg:province":"St. Gallen",
    "wof:name":"Eugster Gottlieb",
    "wof:placetype":"venue"
},
  "geometry": {"coordinates":[9.642889,47.406452],"type":"Point"}
}