{
  "type": "Feature",
  "properties": {
    "iso:country":"CH",
    "sg:address":"Talackerstrasse 17",
    "sg:city":"Glattbrugg",
    "sg:orig_category":"Fahrr\u00e4der and Zubeh\u00f6r Grosshandel",
    "sg:phone":"+41 18292334",
    "sg:postcode":"8152",
    "sg:province":"Z\u00fcrich",
    "wof:name":"Velok Ag",
    "wof:placetype":"venue"
},
  "geometry": {"coordinates":[8.5612001419,47.4258499146],"type":"Point"}
}