{
  "type": "Feature",
  "properties": {
    "iso:country":"CH",
    "sg:address":"Fischmarkt 5",
    "sg:city":"Basel",
    "sg:orig_category":"Detailhandel mit Herrenbekleidung Herstellung von sonstiger Bekleidung U Bekleidungszubeh\u00f6r",
    "sg:phone":"+41 61 261 07 55",
    "sg:postcode":"4051",
    "sg:province":"Basel-Stadt",
    "wof:name":"Classic Herrenmode Grauwiler Mode Ag",
    "wof:placetype":"venue"
},
  "geometry": {"coordinates":[7.5869560242,47.5591926575],"type":"Point"}
}