{
  "type": "Feature",
  "properties": {
    "iso:country":"CH",
    "sg:address":"Br\u00fcckenstrasse 4a",
    "sg:city":"Huttwil",
    "sg:orig_category":"Sanit\u00e4r, Heizungs U L\u00fcftungsinstallation Sanit\u00e4rinstallation",
    "sg:postcode":"4950",
    "sg:province":"Bern",
    "wof:name":"Werner Burkhardt",
    "wof:placetype":"venue"
},
  "geometry": {"coordinates":[7.8635730743,47.1151161194],"type":"Point"}
}