{
  "type": "Feature",
  "properties": {
    "iso:country":"CH",
    "sg:address":"Wiesentalstrasse 126",
    "sg:city":"Chur",
    "sg:orig_category":"Herstellung von Papier, Karton U Pappe",
    "sg:phone":"+41 81 353 79 39",
    "sg:postcode":"7000",
    "sg:province":"Graubunden",
    "wof:name":"Icar Ag",
    "wof:placetype":"venue"
},
  "geometry": {"coordinates":[9.5304498672,46.8637886047],"type":"Point"}
}