{
  "type": "Feature",
  "properties": {
    "iso:country":"CH",
    "sg:address":"Bahnhofstrasse 17a",
    "sg:city":"Wigoltingen",
    "sg:orig_category":"Sportvereine Ballsport Tennis",
    "sg:phone":"+41 52 763 12 12",
    "sg:postcode":"8556",
    "sg:province":"Thurgau",
    "wof:name":"Tc M\u00fcllheim",
    "wof:placetype":"venue"
},
  "geometry": {"coordinates":[9.0196914673,47.5919380188],"type":"Point"}
}