{
  "type": "Feature",
  "properties": {
    "iso:country":"CH",
    "sg:address":"Berglistrasse 28",
    "sg:city":"Arbon",
    "sg:orig_category":"Detailhandel mit Fleisch U Fleischwaren",
    "sg:phone":"+41 71 446 10 57",
    "sg:postcode":"9320",
    "sg:province":"Thurgau",
    "wof:name":"Lutz Max",
    "wof:placetype":"venue"
},
  "geometry": {"coordinates":[9.4276180267,47.5163269043],"type":"Point"}
}