{
  "type": "Feature",
  "properties": {
    "iso:country":"CH",
    "sg:address":"Hauptstrasse 45-47",
    "sg:city":"Zuchwil",
    "sg:orig_category":"Detailhandel mit Sportartikeln",
    "sg:phone":"+41 32 685 27 65",
    "sg:postcode":"4528",
    "sg:province":"Solothurn",
    "wof:name":"Horseland Felix B\u00fchler Ag",
    "wof:placetype":"venue"
},
  "geometry": {"coordinates":[7.5532689095,47.2026481628],"type":"Point"}
}