{
  "type": "Feature",
  "properties": {
    "iso:country":"CH",
    "sg:address":"Frohmattrain 433",
    "sg:city":"Kleinl\u00fctzel",
    "sg:orig_category":"Autoreiseunternehmen",
    "sg:phone":"+41 61 771 06 89",
    "sg:postcode":"4245",
    "sg:province":"Solothurn",
    "wof:name":"Walter Borer Autoreiseunternehmen",
    "wof:placetype":"venue"
},
  "geometry": {"coordinates":[7.417202,47.425259],"type":"Point"}
}