{
  "type": "Feature",
  "properties": {
    "addr:full":"Frohmattrain 433 Kleinl\u00fctzel Solothurn 4245",
    "addr:housenumber":"433;4245",
    "addr:street":"Frohmattrain;Solothurn",
    "iso:country":"CH",
    "sg:address":"Frohmattrain 433",
    "sg:city":"Kleinl\u00fctzel",
    "sg:orig_category":"Autoreiseunternehmen",
    "sg:phone":"+41 61 771 06 89",
    "sg:postcode":"4245",
    "sg:province":"Solothurn",
    "wof:name":"Walter Borer Autoreiseunternehmen",
    "wof:placetype":"venue"
},
  "geometry": {"coordinates":[7.417202,47.425259],"type":"Point"}
}