{
  "type": "Feature",
  "properties": {
    "iso:country":"CH",
    "sg:address":"Kasernenplatz 2",
    "sg:city":"Luzern",
    "sg:orig_category":"Unclassifiable Establishments",
    "sg:phone":"+41 17776661",
    "sg:postcode":"6000",
    "sg:province":"Luzern",
    "wof:name":"Accessoires Novel-team",
    "wof:placetype":"venue"
},
  "geometry": {"coordinates":[8.4368495941,47.3533096313],"type":"Point"}
}