{
  "type": "Feature",
  "properties": {
    "iso:country":"CH",
    "sg:address":"Neugasse 42 8000 Z\u00fcrich. Postfach",
    "sg:city":"Z\u00fcrich",
    "sg:orig_category":"RESTAURANTS: TEA-ROOMS",
    "sg:postcode":"8001",
    "sg:province":"Z\u00fcrich",
    "wof:name":"Cetojevic Nedeljko Chicago Snack-bar",
    "wof:placetype":"venue"
},
  "geometry": {"coordinates":[8.5300788879,47.38256073],"type":"Point"}
}