{
  "type": "Feature",
  "properties": {
    "iso:country":"CH",
    "sg:address":"Baumgartenweg 1",
    "sg:city":"Oberentfelden",
    "sg:orig_category":"Unternehmensberatung",
    "sg:phone":"+41 62 723 65 76",
    "sg:postcode":"5036",
    "sg:province":"Aargau",
    "wof:name":"Chatterjee Intercon Services",
    "wof:placetype":"venue"
},
  "geometry": {"coordinates":[8.0465946198,47.3586082458],"type":"Point"}
}