{
  "type": "Feature",
  "properties": {
    "iso:country":"CH",
    "sg:address":"Rue De Torry 5",
    "sg:city":"Granges-paccot",
    "sg:orig_category":"Vermietung U Verpachtung von eigenen Immobilien",
    "sg:phone":"+41 26 466 46 31",
    "sg:postcode":"1763",
    "sg:province":"Fribourg",
    "wof:name":"Nydegger Eric R.",
    "wof:placetype":"venue"
},
  "geometry": {"coordinates":[7.1439538002,46.8174743652],"type":"Point"}
}