{
  "type": "Feature",
  "properties": {
    "iso:country":"CH",
    "sg:address":"Tanngasse 36",
    "sg:city":"Oberentfelden",
    "sg:orig_category":"Vorschulen, Kinderg\u00e4rten",
    "sg:phone":"+41 62 737 52 06",
    "sg:postcode":"5036",
    "sg:province":"Aargau",
    "wof:name":"Kindergarten",
    "wof:placetype":"venue"
},
  "geometry": {"coordinates":[8.0384740829,47.3538627625],"type":"Point"}
}