{
  "type": "Feature",
  "properties": {
    "iso:country":"CH",
    "sg:address":"Hofgarten 24",
    "sg:city":"Oberweningen",
    "sg:orig_category":"Detailhandel mit Bekleidung",
    "sg:postcode":"8165",
    "sg:province":"Z\u00fcrich",
    "wof:name":"Exclusiv Lady K Wollmoden Karin Wagner",
    "wof:placetype":"venue"
},
  "geometry": {"coordinates":[8.40369,47.500477],"type":"Point"}
}