{
  "type": "Feature",
  "properties": {
    "iso:country":"CH",
    "sg:address":"6714",
    "sg:city":"Semione",
    "sg:orig_category":"Schulpflegen",
    "sg:postcode":"6714",
    "sg:province":"Ticino",
    "wof:name":"Delegazione Scolastica Del Comune Di Semione",
    "wof:placetype":"venue"
},
  "geometry": {"coordinates":[8.9714298248,46.4069595337],"type":"Point"}
}