{
  "type": "Feature",
  "properties": {
    "iso:country":"CH",
    "sg:address":"B\u00e4lliz 21",
    "sg:city":"Thun",
    "sg:orig_category":"Detailhandel mit Schuhen",
    "sg:phone":"+41 33 223 05 80",
    "sg:postcode":"3600",
    "sg:province":"Bern",
    "wof:name":"Karl V\u00f6gele Ag",
    "wof:placetype":"venue"
},
  "geometry": {"coordinates":[7.6271739006,46.7591552734],"type":"Point"}
}