{
  "type": "Feature",
  "properties": {
    "addr:full":"Hauptstrasse 20 L\u00e4ufelfingen Basel-Landschaft 4448",
    "addr:housenumber":"20",
    "addr:postcode":"4448",
    "addr:street":"Hauptstrasse",
    "iso:country":"CH",
    "sg:address":"Hauptstrasse 20",
    "sg:city":"L\u00e4ufelfingen",
    "sg:orig_category":"Blumen U Zierpflanzenbau Detailhandel mit Blumen U Pflanzen",
    "sg:phone":"+41 21 944 44 44",
    "sg:postcode":"4448",
    "sg:province":"Basel-Landschaft",
    "wof:name":"Brunner Fr\u00e8res Horlogerie-bijouterie",
    "wof:placetype":"venue"
},
  "geometry": {"coordinates":[6.867092,46.457115],"type":"Point"}
}