{
  "type": "Feature",
  "properties": {
    "iso:country":"CH",
    "sg:address":"Klosterweg 78",
    "sg:city":"Ilanz",
    "sg:orig_category":"Interessenvertretungen",
    "sg:phone":"+41 81 925 17 38",
    "sg:postcode":"7130",
    "sg:province":"Graubunden",
    "wof:name":"Institut St. Josef",
    "wof:placetype":"venue"
},
  "geometry": {"coordinates":[9.199379921,46.7778587341],"type":"Point"}
}