{
  "type": "Feature",
  "properties": {
    "iso:country":"CH",
    "sg:address":"Funtenenstrasse 1 3860 Meiringen. Postfach",
    "sg:city":"Meiringen",
    "sg:orig_category":"Kauf U Verkauf von Immobilien auf eigene Rechnung",
    "sg:postcode":"3860",
    "sg:province":"Bern",
    "wof:name":"Gfb Gesellschaft F\u00fcr Bau Ag Liegenschaften Usw",
    "wof:placetype":"venue"
},
  "geometry": {"coordinates":[9.0328617096,47.4650878906],"type":"Point"}
}