{
  "type": "Feature",
  "properties": {
    "addr:full":"Hauptstrasse 51 Bretzwil Basel-Landschaft 4207",
    "addr:housenumber":"51",
    "addr:postcode":"4207",
    "addr:street":"Hauptstrasse",
    "iso:country":"CH",
    "sg:address":"Hauptstrasse 51",
    "sg:city":"Bretzwil",
    "sg:orig_category":"Allgemeiner Hoch U Tiefbau",
    "sg:postcode":"4207",
    "sg:province":"Basel-Landschaft",
    "wof:name":"Othmar Stebler Ag, Bauunternehmung, Zweigniederlassung Bretzwil",
    "wof:placetype":"venue"
},
  "geometry": {"coordinates":[7.649952,47.396255],"type":"Point"}
}