{
  "type": "Feature",
  "properties": {
    "iso:country":"CH",
    "sg:address":"Voie-creuse La 14 1202 Gen\u00e8ve. Postfach",
    "sg:city":"Gen\u00e8ve",
    "sg:orig_category":"Pensionskassen",
    "sg:postcode":"1202",
    "sg:province":"Gen\u00e8ve",
    "wof:name":"Fondation De Pr\u00e9voyance De Vedia Sa",
    "wof:placetype":"venue"
},
  "geometry": {"coordinates":[6.1429100037,46.2192726135],"type":"Point"}
}