{
  "type": "Feature",
  "properties": {
    "iso:country":"CH",
    "sg:address":"Centre Commercial",
    "sg:city":"Haute-nendaz",
    "sg:orig_category":"Herstellung von W\u00e4sche",
    "sg:phone":"+41 27882319",
    "sg:postcode":"1997",
    "sg:province":"Valais",
    "wof:name":"Boutique L'enfant, Loye Ginette",
    "wof:placetype":"venue"
},
  "geometry": {"coordinates":[7.2981119156,46.1841583252],"type":"Point"}
}