{
  "type": "Feature",
  "properties": {
    "iso:country":"CH",
    "sg:address":"R\u00fcderswilstrasse 1",
    "sg:city":"Zollbr\u00fcck",
    "sg:orig_category":"Shopping U Fachgesch\u00e4fte, Bekleidung",
    "sg:phone":"+41 34 496 88 10",
    "sg:postcode":"3436",
    "sg:province":"Bern",
    "wof:name":"Home Cinema",
    "wof:placetype":"venue"
},
  "geometry": {"coordinates":[7.738125,46.974495],"type":"Point"}
}