{
  "type": "Feature",
  "properties": {
    "iso:country":"CH",
    "sg:address":"Brandschenkestrasse 2 8002 Z\u00fcrich. Postfach 982",
    "sg:city":"Z\u00fcrich",
    "sg:orig_category":"Grosshandel mit Textilien Grosshandel mit Uhren",
    "sg:phone":"+41 12091111",
    "sg:postcode":"8039",
    "wof:name":"Desco Von Schulthess Ag Import, Export- U. Transitgesch\u00e4fte Usw",
    "wof:placetype":"venue"
},
  "geometry": {"coordinates":[8.5284080505,47.3673057556],"type":"Point"}
}