{
  "type": "Feature",
  "properties": {
    "iso:country":"CH",
    "sg:address":"Bernstrasse 6",
    "sg:city":"Herzogenbuchsee",
    "sg:classifiers":[
        {
            "category":"Shopping",
            "subcategory":"Gifts & Souvenirs",
            "type":"Retail Goods"
        }
    ],
    "sg:phone":"+41 62 961 45 35",
    "sg:postcode":"3360",
    "sg:province":"Bern",
    "sg:tags":[
        "item"
    ],
    "wof:name":"Rosmarie Meyer Papeterie",
    "wof:placetype":"venue"
},
  "geometry": {"coordinates":[7.70516,47.187843],"type":"Point"}
}