{
  "type": "Feature",
  "properties": {
    "iso:country":"CH",
    "sg:address":"Fr\u00f6belstrasse 10",
    "sg:city":"Z\u00fcrich",
    "sg:classifiers":[
        {
            "category":"Professional",
            "subcategory":"Engineering",
            "type":"Services"
        }
    ],
    "sg:phone":"+41 14226622",
    "sg:postcode":"8032",
    "sg:province":"Z\u00fcrich",
    "sg:tags":[
        "civil"
    ],
    "wof:name":"Beag-engineering Ag",
    "wof:placetype":"venue"
},
  "geometry": {"coordinates":[8.56608,47.361664],"type":"Point"}
}