{
  "type": "Feature",
  "properties": {
    "iso:country":"CH",
    "sg:address":"6982",
    "sg:city":"Agno",
    "sg:orig_category":"Schulpflegen",
    "sg:postcode":"6982",
    "sg:province":"Ticino",
    "wof:name":"Delegazione Scolastica Del Comune Di Agno",
    "wof:placetype":"venue"
},
  "geometry": {"coordinates":[8.8993301392,45.9967536926],"type":"Point"}
}