{
  "type": "Feature",
  "properties": {
    "iso:country":"CH",
    "sg:address":"Weyermannsstrasse 12",
    "sg:city":"Bern",
    "sg:orig_category":"Zoll- and Grenzb\u00fcros",
    "sg:phone":"+41 31 322 68 70",
    "sg:postcode":"3008",
    "sg:province":"Bern",
    "wof:name":"Zollamt Bern Zollfreilager/luftfracht",
    "wof:placetype":"venue"
},
  "geometry": {"coordinates":[7.4166269302,46.9490242004],"type":"Point"}
}