{
  "type": "Feature",
  "properties": {
    "iso:country":"CH",
    "sg:address":"Hauptstr. 488",
    "sg:city":"Oberbuchsiten",
    "sg:orig_category":"Instandhaltung U Reparatur von Automobilen",
    "sg:phone":"+41 62 393 16 36",
    "sg:postcode":"4625",
    "sg:province":"Solothurn",
    "wof:name":"Garage Rose G",
    "wof:placetype":"venue"
},
  "geometry": {"coordinates":[7.7609257698,47.3057632446],"type":"Point"}
}