{
  "type": "Feature",
  "properties": {
    "iso:country":"CH",
    "sg:address":"Bahnhofstrasse 15",
    "sg:city":"B\u00fctschwil",
    "sg:classifiers":[
        {
            "category":"Restaurant",
            "type":"Food & Drink"
        }
    ],
    "sg:phone":"+41 71 983 15 02",
    "sg:postcode":"9606",
    "sg:province":"St. Gallen",
    "wof:name":"Restaurant Bahnhof",
    "wof:placetype":"venue"
},
  "geometry": {"coordinates":[9.074842453,47.3598098755],"type":"Point"}
}