{
  "type": "Feature",
  "properties": {
    "addr:full":"Fluppe 26 Bad Ragaz St. Gallen 7310",
    "addr:housenumber":"26",
    "addr:postcode":"7310",
    "addr:street":"Fluppe;Ragaz",
    "iso:country":"CH",
    "sg:address":"Fluppe 26",
    "sg:city":"Bad Ragaz",
    "sg:orig_category":"Wirtschaft U Handel, Arbeit, Aus- U Weiterbildung",
    "sg:phone":"+41 81 302 13 13",
    "sg:postcode":"7310",
    "sg:province":"St. Gallen",
    "wof:name":"Gerstel Rarit\u00e4ten",
    "wof:placetype":"venue"
},
  "geometry": {"coordinates":[9.517194,46.992146],"type":"Point"}
}