{
  "type": "Feature",
  "properties": {
    "iso:country":"CH",
    "sg:address":"6862",
    "sg:city":"Rancate",
    "sg:orig_category":"Schulpflegen",
    "sg:postcode":"6862",
    "sg:province":"Ticino",
    "wof:name":"Delegazione Scolastica Del Comune Di Rancate",
    "wof:placetype":"venue"
},
  "geometry": {"coordinates":[8.9705495834,45.8745193481],"type":"Point"}
}