{
  "type": "Feature",
  "properties": {
    "addr:full":"Oberer Graben 3 St.gallen St. Gallen 9000",
    "addr:housenumber":"3",
    "addr:postcode":"9000",
    "addr:street":"Oberer Graben",
    "iso:country":"CH",
    "sg:address":"Oberer Graben 3",
    "sg:city":"St.gallen",
    "sg:orig_category":"Betrieb U technische Hilfsdienste des Kultur U Unterhaltungswesens",
    "sg:postcode":"9000",
    "sg:province":"St. Gallen",
    "wof:name":"Univent Universal Entertainments Hauser",
    "wof:placetype":"venue"
},
  "geometry": {"coordinates":[9.374541,47.42569],"type":"Point"}
}