{
  "type": "Feature",
  "properties": {
    "iso:country":"CH",
    "sg:address":"Obergasse 38",
    "sg:city":"Uznach",
    "sg:orig_category":"Sanit\u00e4r, Heizungs U L\u00fcftungsinstallation",
    "sg:postcode":"8730",
    "sg:province":"St. Gallen",
    "wof:name":"Savary C. S\u00e0rl Conseiller, R\u00e9aliser Et Maintenir Des Installations Dans Le Dom. Des Chauffages, Des Sanitaires, Des Ventilations Etc",
    "wof:placetype":"venue"
},
  "geometry": {"coordinates":[6.9744057655,46.6355400085],"type":"Point"}
}