{
  "type": "Feature",
  "properties": {
    "iso:country":"CH",
    "sg:address":"St\u00e4dtli 4",
    "sg:city":"Werdenberg",
    "sg:orig_category":"Architekturb\u00fcros",
    "sg:phone":"+41 81 771 31 61",
    "sg:postcode":"9470",
    "sg:province":"St. Gallen",
    "wof:name":"Hansruedi Dietschi Architekturb\u00fcro",
    "wof:placetype":"venue"
},
  "geometry": {"coordinates":[9.463091,47.168079],"type":"Point"}
}