{
  "type": "Feature",
  "properties": {
    "iso:country":"CH",
    "sg:address":"Neuenkirchstrasse 32",
    "sg:city":"Ruswil",
    "sg:orig_category":"Schlossereien",
    "sg:phone":"+41 41 495 15 48",
    "sg:postcode":"6017",
    "sg:province":"Luzern",
    "wof:name":"Josef M\u00fcller Bau-& Kunstschlosserei",
    "wof:placetype":"venue"
},
  "geometry": {"coordinates":[8.1309919357,47.0843162537],"type":"Point"}
}