{
  "type": "Feature",
  "properties": {
    "iso:country":"CH",
    "sg:address":"Toreggstrasse 32",
    "sg:city":"Arnegg",
    "sg:orig_category":"Markt U Meinungsforschung",
    "sg:phone":"+41 71 380 08 80",
    "sg:postcode":"9212",
    "sg:province":"St. Gallen",
    "wof:name":"Lieskamp Management Services",
    "wof:placetype":"venue"
},
  "geometry": {"coordinates":[9.2577362061,47.4455604553],"type":"Point"}
}