{
  "type": "Feature",
  "properties": {
    "iso:country":"CH",
    "sg:address":"6967",
    "sg:city":"Dino",
    "sg:orig_category":"Schulpflegen",
    "sg:postcode":"6967",
    "sg:province":"Ticino",
    "wof:name":"Delegazione Scolastica Del Comune Di Dino",
    "wof:placetype":"venue"
},
  "geometry": {"coordinates":[8.9861001968,46.0532188416],"type":"Point"}
}