{
  "type": "Feature",
  "properties": {
    "addr:full":"Schaffhauserstrasse 3 Frauenfeld Thurgau 8500",
    "addr:housenumber":"3",
    "addr:postcode":"8500",
    "addr:street":"Schaffhauserstrasse",
    "iso:country":"CH",
    "sg:address":"Schaffhauserstrasse 3",
    "sg:city":"Frauenfeld",
    "sg:orig_category":"Allgemeiner Hoch U Tiefbau",
    "sg:phone":"+41 52 725 04 04",
    "sg:postcode":"8500",
    "sg:province":"Thurgau",
    "wof:name":"Goldinger Generalbau Ag",
    "wof:placetype":"venue"
},
  "geometry": {"coordinates":[8.88925,47.561031],"type":"Point"}
}