{
  "type": "Feature",
  "properties": {
    "iso:country":"CH",
    "sg:address":"Postgasse 4",
    "sg:city":"Sissach",
    "sg:orig_category":"Zahnarztpraxen",
    "sg:phone":"+41 61 971 35 50",
    "sg:postcode":"4450",
    "sg:province":"Basel-Landschaft",
    "wof:name":"Dr. Med. Dent. Mihajlo Balic Zahnarzt",
    "wof:placetype":"venue"
},
  "geometry": {"coordinates":[7.8112621307,47.4636306763],"type":"Point"}
}