{
  "type": "Feature",
  "properties": {
    "iso:country":"CH",
    "sg:address":"Ecluse Rue De L' 14",
    "sg:city":"Neuch\u00e2tel",
    "sg:orig_category":"Nahrungsmittel-Industrie: Rohstoffe",
    "sg:phone":"+41 32 721 47 22",
    "sg:postcode":"2000",
    "sg:province":"Neuch\u00e2tel",
    "wof:name":"Alimentation Higino",
    "wof:placetype":"venue"
},
  "geometry": {"coordinates":[6.9272999763,46.9934310913],"type":"Point"}
}