{
  "type": "Feature",
  "properties": {
    "iso:country":"CH",
    "sg:address":"Altikerstrasse 11 8525 Niederneunforn. Postfach",
    "sg:city":"Niederneunforn",
    "sg:orig_category":"Grosshandel mit Nahrungsmitteln, Getr\u00e4nken U Tabakwaren ohne ausgepr\u00e4gten Schwerpunkt",
    "sg:phone":"+41 52 745 12 41",
    "sg:postcode":"8525",
    "sg:province":"Thurgau",
    "wof:name":"Genossenschaft Dorfladen Niederneunforn",
    "wof:placetype":"venue"
},
  "geometry": {"coordinates":[8.7824440002,47.5958557129],"type":"Point"}
}