{
  "type": "Feature",
  "properties": {
    "iso:country":"CH",
    "sg:address":"Kanalstrasse 15",
    "sg:city":"Glattbrugg",
    "sg:orig_category":"Satzherstellung U Reproduktion Werbung",
    "sg:phone":"+41 22 783 01 11",
    "sg:postcode":"8152",
    "sg:province":"Z\u00fcrich",
    "wof:name":"Rrp, Eric Ratzenberger",
    "wof:placetype":"venue"
},
  "geometry": {"coordinates":[6.1341581345,46.1822624207],"type":"Point"}
}