{
  "type": "Feature",
  "properties": {
    "iso:country":"CH",
    "sg:address":"Immeuble La Fr\u00e9gate",
    "sg:city":"Montana",
    "sg:classifiers":[
        {
            "category":"Travel",
            "subcategory":"Hotels & Motels",
            "type":"Entertainment"
        }
    ],
    "sg:phone":"+41 27 783 11 77",
    "sg:postcode":"3962",
    "sg:tags":[
        "hotels",
        "mit",
        "restaurant"
    ],
    "wof:name":"Grand H\u00f4tel Du Val Ferret",
    "wof:placetype":"venue"
},
  "geometry": {"coordinates":[7.1071767807,45.9557151794],"type":"Point"}
}