{
  "type": "Feature",
  "properties": {
    "iso:country":"CH",
    "sg:address":"Seestrasse 54",
    "sg:city":"Oberrieden",
    "sg:orig_category":"Herstellung von k\u00e4lte U lufttechnischen Erzeugnissen f\u00fcr gewerbliche Zwecke",
    "sg:phone":"+41 17221983",
    "sg:postcode":"8942",
    "sg:province":"Z\u00fcrich",
    "wof:name":"Or Filter Gmbh",
    "wof:placetype":"venue"
},
  "geometry": {"coordinates":[8.5818443298,47.2751464844],"type":"Point"}
}