{
  "type": "Feature",
  "properties": {
    "iso:country":"CH",
    "sg:address":"Route De Tramelan 16",
    "sg:city":"St-imier",
    "sg:orig_category":"Elektrizit\u00e4tsversorgung Herstellung von Elektromotoren, Generatoren U Transformatoren",
    "sg:phone":"+41 32 942 41 11",
    "sg:postcode":"2610",
    "sg:province":"Bern",
    "wof:name":"Soci\u00e9t\u00e9 Des Forces Electriques De La Goule",
    "wof:placetype":"venue"
},
  "geometry": {"coordinates":[6.9583330154,47.224697113],"type":"Point"}
}