{
  "type": "Feature",
  "properties": {
    "iso:country":"CH",
    "sg:address":"Ilgenstrasse 25",
    "sg:city":"Kreuzlingen",
    "sg:orig_category":"Fahrschulen, Flugschulen",
    "sg:phone":"+41 79 438 44 19",
    "sg:postcode":"8280",
    "sg:province":"Thurgau",
    "wof:name":"Hans Oberh\u00e4nsli Autofahrschule",
    "wof:placetype":"venue"
},
  "geometry": {"coordinates":[9.1774110794,47.6430587769],"type":"Point"}
}