{
  "type": "Feature",
  "properties": {
    "iso:country":"CH",
    "sg:address":"Rue Pierre-p\u00e9quignat 11",
    "sg:city":"Porrentruy",
    "sg:classifiers":[
        {
            "category":"Government",
            "subcategory":"Post Office",
            "type":"Public Place"
        }
    ],
    "sg:phone":"+41 32 466 13 26",
    "sg:postcode":"2900",
    "sg:province":"Jura",
    "sg:tags":[
        "caf\u00e9s",
        "tea-rooms"
    ],
    "wof:name":"Tea-room G\u00fcnther Maurer",
    "wof:placetype":"venue"
},
  "geometry": {"coordinates":[7.0740628242,47.417427063],"type":"Point"}
}