{
  "type": "Feature",
  "properties": {
    "iso:country":"CH",
    "sg:address":"Hardstrasse 91",
    "sg:city":"Birsfelden",
    "sg:orig_category":"Instandhaltung U Reparatur von Automobilen",
    "sg:phone":"+41 61 313 22 24",
    "sg:postcode":"4127",
    "sg:province":"Basel-Landschaft",
    "wof:name":"Moser Ernst",
    "wof:placetype":"venue"
},
  "geometry": {"coordinates":[7.6335802078,47.5505409241],"type":"Point"}
}