{
  "type": "Feature",
  "properties": {
    "addr:full":"Seilergraben 43 8001 Z\u00fcrich. Postfach Z\u00fcrich Z\u00fcrich 8024",
    "addr:housenumber":"43",
    "addr:postcode":"8001 zuerich. postfach;8024",
    "addr:street":"Seilergraben",
    "iso:country":"CH",
    "sg:address":"Seilergraben 43 8001 Z\u00fcrich. Postfach",
    "sg:city":"Z\u00fcrich",
    "sg:orig_category":"Detailhandel mit B\u00fcchern",
    "sg:phone":"+41 12620966",
    "sg:postcode":"8024",
    "sg:province":"Z\u00fcrich",
    "wof:name":"Libreria El Condor",
    "wof:placetype":"venue"
},
  "geometry": {"coordinates":[8.545552,47.374939],"type":"Point"}
}