{
  "type": "Feature",
  "properties": {
    "iso:country":"CH",
    "sg:address":"Amerbachstrasse 14",
    "sg:city":"Basel",
    "sg:classifiers":[
        {
            "category":"Restaurant",
            "type":"Food & Drink"
        }
    ],
    "sg:phone":"+41 56 633 28 80",
    "sg:postcode":"4057",
    "sg:province":"Basel-Stadt",
    "wof:name":"Restaurant Piazza",
    "wof:placetype":"venue"
},
  "geometry": {"coordinates":[8.3488235474,47.3519325256],"type":"Point"}
}