{
  "type": "Feature",
  "properties": {
    "iso:country":"CH",
    "sg:address":"Chemin Byron 6bis 1223 Cologny Case Postale 59",
    "sg:city":"Cologny",
    "sg:orig_category":"Handelsvermittlung U Grosshandel Sonstiger Grosshandel",
    "sg:phone":"+41 22 736 77 01",
    "sg:postcode":"1223",
    "sg:province":"Gen\u00e8ve",
    "wof:name":"Carni Sa",
    "wof:placetype":"venue"
},
  "geometry": {"coordinates":[6.1804862022,46.2208099365],"type":"Point"}
}