{
  "type": "Feature",
  "properties": {
    "iso:country":"CH",
    "sg:address":"Dolderstrasse 104 8032 Z\u00fcrich",
    "sg:city":"Zust",
    "sg:orig_category":"Werbung",
    "sg:phone":"+41 55 283 22 23",
    "sg:postcode":"32",
    "wof:name":"Gastrowerb Ag Werbung F\u00fcr Gastronomie",
    "wof:placetype":"venue"
},
  "geometry": {"coordinates":[9.0197029114,47.1895256042],"type":"Point"}
}