{
  "type": "Feature",
  "properties": {
    "iso:country":"CH",
    "sg:address":"Altfeldweg 8",
    "sg:city":"Niederlenz",
    "sg:orig_category":"Politische Parteien SVP",
    "sg:phone":"+41 56 622 60 13",
    "sg:postcode":"5702",
    "sg:province":"Aargau",
    "wof:name":"Svp Ortspartei Niederwil",
    "wof:placetype":"venue"
},
  "geometry": {"coordinates":[8.2930202484,47.3751564026],"type":"Point"}
}