{
  "type": "Feature",
  "properties": {
    "iso:country":"CH",
    "sg:address":"Chemin Des Cerisiers 3",
    "sg:city":"Tavannes",
    "sg:classifiers":[
        {
            "category":"Restaurant",
            "type":"Food & Drink"
        }
    ],
    "sg:phone":"+41 79 415 79 35",
    "sg:postcode":"2710",
    "sg:province":"Bern",
    "wof:name":"Pizzeria Chez Biagio",
    "wof:placetype":"venue"
},
  "geometry": {"coordinates":[7.20439291,47.2209854126],"type":"Point"}
}