{
  "type": "Feature",
  "properties": {
    "iso:country":"CH",
    "sg:address":"Au Villard Auddes",
    "sg:city":"Riddes",
    "sg:orig_category":"Herstellung von Duft U K\u00f6rperpflegemitteln",
    "sg:phone":"+41 27 306 63 49",
    "sg:postcode":"1908",
    "sg:province":"Valais",
    "wof:name":"Zotikos S\u00e0rl",
    "wof:placetype":"venue"
},
  "geometry": {"coordinates":[7.2213292122,46.1717376709],"type":"Point"}
}