{
  "type": "Feature",
  "properties": {
    "iso:country":"CH",
    "sg:address":"Hotelgasse 8",
    "sg:city":"Bern",
    "sg:orig_category":"Ausbaugewerbe",
    "sg:phone":"+41 31 311 26 25",
    "sg:postcode":"3011",
    "sg:province":"Bern",
    "wof:name":"Schweizer Rolf Innenarchitekt",
    "wof:placetype":"venue"
},
  "geometry": {"coordinates":[7.447899,46.947643],"type":"Point"}
}