{
  "type": "Feature",
  "properties": {
    "iso:country":"CH",
    "sg:address":"Maulbeerstrasse 66 4058 Basel. Postfach",
    "sg:city":"Basel",
    "sg:orig_category":"Technische, physikalische U chemische Untersuchung",
    "sg:phone":"+41 61 697 66 51",
    "sg:postcode":"4002",
    "sg:province":"Basel-Stadt",
    "wof:name":"Friedrich Miescher Institut",
    "wof:placetype":"venue"
},
  "geometry": {"coordinates":[7.6031508446,47.567905426],"type":"Point"}
}