{
  "type": "Feature",
  "properties": {
    "iso:country":"CH",
    "sg:address":"Zuchwilerstrasse 28 4500 Solothurn. Postfach",
    "sg:city":"Solothurn",
    "sg:orig_category":"P\u00e9dicure",
    "sg:phone":"+41 32 621 36 36",
    "sg:postcode":"4501",
    "sg:province":"Solothurn",
    "wof:name":"Monique Brechb\u00fchl Kosmetik El\u00e9gance",
    "wof:placetype":"venue"
},
  "geometry": {"coordinates":[7.5411200523,47.2029762268],"type":"Point"}
}