{
  "type": "Feature",
  "properties": {
    "iso:country":"CH",
    "sg:address":"Gr\u00fcndenstrasse 13",
    "sg:city":"Muttenz",
    "sg:orig_category":"Betrieb von Taxis",
    "sg:phone":"+41 61 461 62 30",
    "sg:postcode":"4132",
    "sg:province":"Basel-Landschaft",
    "wof:name":"Eschbach-car, Nachfolger Schl\u00e4ppi Hermann Car-reiseunternehmen",
    "wof:placetype":"venue"
},
  "geometry": {"coordinates":[7.645082,47.532341],"type":"Point"}
}