{
  "type": "Feature",
  "properties": {
    "iso:country":"CH",
    "sg:address":"Oberdorfstrasse 15",
    "sg:city":"W\u00e4denswil",
    "sg:orig_category":"Detailhandel mit Brot, Back U S\u00fcsswaren",
    "sg:phone":"+41 17803303",
    "sg:postcode":"8820",
    "sg:province":"Z\u00fcrich",
    "wof:name":"Beda Hengartner B\u00e4ckerei-konditorei",
    "wof:placetype":"venue"
},
  "geometry": {"coordinates":[8.669259,47.227894],"type":"Point"}
}