{
  "type": "Feature",
  "properties": {
    "iso:country":"CH",
    "sg:address":"Avenue Des Tilleuls 21",
    "sg:city":"Gen\u00e8ve",
    "sg:orig_category":"Herstellung von Teppichen Verlegen von Fussboden",
    "sg:phone":"+41 32 968 16 24",
    "sg:postcode":"1203",
    "sg:province":"Gen\u00e8ve",
    "wof:name":"Solheimo Sa",
    "wof:placetype":"venue"
},
  "geometry": {"coordinates":[6.8292350769,47.1039886475],"type":"Point"}
}