{
  "type": "Feature",
  "properties": {
    "iso:country":"CH",
    "sg:address":"Dorfstrasse 108 3911 Ried-brig. Postfach",
    "sg:city":"Ried-brig",
    "sg:orig_category":"Herstellung von elektronischen Bauelementen",
    "sg:postcode":"3911",
    "sg:province":"Valais",
    "wof:name":"Fox Elektronic - Fux Elektroteile, Elektronische Ger\u00e4te; Handel",
    "wof:placetype":"venue"
},
  "geometry": {"coordinates":[8.0144023895,46.3121490479],"type":"Point"}
}