{
  "type": "Feature",
  "properties": {
    "iso:country":"CH",
    "sg:address":"Vordere Kirchstrasse 1",
    "sg:city":"Diepoldsau",
    "sg:orig_category":"Nationale Postdienste",
    "sg:phone":"+41 71 733 11 42",
    "sg:postcode":"9444",
    "sg:province":"St. Gallen",
    "wof:name":"Die Schweizerische Post",
    "wof:placetype":"venue"
},
  "geometry": {"coordinates":[9.6547317505,47.3857269287],"type":"Point"}
}