{
  "type": "Feature",
  "properties": {
    "iso:country":"CH",
    "sg:address":"Dorfstrasse 14",
    "sg:city":"Habsburg",
    "sg:classifiers":[
        {
            "category":"Building & Trades",
            "subcategory":"Construction",
            "type":"Services"
        }
    ],
    "sg:phone":"+41 56 441 65 14",
    "sg:postcode":"5245",
    "sg:province":"Aargau",
    "sg:tags":[
        "carpenter's",
        "work",
        "supraregional"
    ],
    "wof:name":"Bichsel Schreinerei Ag",
    "wof:placetype":"venue"
},
  "geometry": {"coordinates":[8.184163,47.462219],"type":"Point"}
}