{
  "type": "Feature",
  "properties": {
    "iso:country":"CH",
    "sg:address":"Avenue Agassiz 2",
    "sg:city":"Lausanne",
    "sg:orig_category":"Wirtschafts- and Arbeitgeberverb\u00e4nde",
    "sg:phone":"+41 41 870 56 56",
    "sg:postcode":"1003",
    "sg:province":"Vaud",
    "wof:name":"Urner Anwaltsverband Herrn Lic.iur.mario Bachmann",
    "wof:placetype":"venue"
},
  "geometry": {"coordinates":[8.6443738937,46.8822174072],"type":"Point"}
}