{
  "type": "Feature",
  "properties": {
    "addr:full":"Aareweg 5/d. M\u00fcnsingen Bern 3110",
    "addr:housenumber":"5 / d.",
    "addr:postcode":"3110",
    "addr:street":"Aareweg",
    "iso:country":"CH",
    "sg:address":"Aareweg 5/d.",
    "sg:city":"M\u00fcnsingen",
    "sg:orig_category":"Architektur U Ingenieurb\u00fcros",
    "sg:phone":"+41 31 721 30 21",
    "sg:postcode":"3110",
    "sg:province":"Bern",
    "wof:name":"Andreoli - Ingenieurb\u00fcro",
    "wof:placetype":"venue"
},
  "geometry": {"coordinates":[7.547962,46.873867],"type":"Point"}
}