{
  "type": "Feature",
  "properties": {
    "iso:country":"CH",
    "sg:address":"Langmattweg 6",
    "sg:city":"Gelterkinden",
    "sg:orig_category":"Personenbef\u00f6rderung im Linienverkehr zu Land",
    "sg:phone":"+41 61 981 37 91",
    "sg:postcode":"4460",
    "sg:province":"Basel-Landschaft",
    "wof:name":"Jablanica-tours Kostic",
    "wof:placetype":"venue"
},
  "geometry": {"coordinates":[7.8566160202,47.4672431946],"type":"Point"}
}