{
  "type": "Feature",
  "properties": {
    "iso:country":"CH",
    "sg:address":"Bahnhofstrasse 20",
    "sg:city":"Ostermundigen",
    "sg:orig_category":"Herstellung von Elektromotoren, Generatoren U Transformatoren",
    "sg:phone":"+41 31 330 55 44",
    "sg:postcode":"3072",
    "sg:province":"Bern",
    "wof:name":"Bkw Isp Ag, Zweigniederlassung Ostermundigen",
    "wof:placetype":"venue"
},
  "geometry": {"coordinates":[7.4863948822,46.9544143677],"type":"Point"}
}