{
  "type": "Feature",
  "properties": {
    "iso:country":"CH",
    "sg:address":"Schulhausstr. 4",
    "sg:city":"Henau",
    "sg:classifiers":[
        {
            "category":"Home & Garden",
            "subcategory":"Furniture",
            "type":"Retail Goods"
        }
    ],
    "sg:phone":"+41 71 955 94 94",
    "sg:postcode":"9247",
    "sg:province":"St. Gallen",
    "sg:tags":[
        "household",
        "wood"
    ],
    "wof:name":"Modular Ag",
    "wof:placetype":"venue"
},
  "geometry": {"coordinates":[9.117351532,47.4542007446],"type":"Point"}
}