{
  "type": "Feature",
  "properties": {
    "iso:country":"CH",
    "sg:address":"1700",
    "sg:city":"Fribourg",
    "sg:orig_category":"Forschung U Entwicklung im Bereich der Naturwissenschaften",
    "sg:postcode":"1700",
    "sg:province":"Fribourg",
    "wof:name":"Fondation Feldpausch-de Boer Pour L'institut M\u00e9di\u00e9val De Fribourg",
    "wof:placetype":"venue"
},
  "geometry": {"coordinates":[7.1746201515,46.8062400818],"type":"Point"}
}