{
  "type": "Feature",
  "properties": {
    "iso:country":"CH",
    "sg:address":"Dorfstrasse 25 3232 Ins. Postfach",
    "sg:city":"Ins",
    "sg:orig_category":"Sanit\u00e4r, Heizungs U L\u00fcftungsinstallation",
    "sg:phone":"+41 32 313 15 59",
    "sg:postcode":"3232",
    "sg:province":"Bern",
    "wof:name":"Iseli-kappeler Max",
    "wof:placetype":"venue"
},
  "geometry": {"coordinates":[7.1040129662,47.0075416565],"type":"Point"}
}