{
  "type": "Feature",
  "properties": {
    "iso:country":"CH",
    "sg:address":"Corteglia 6874 Castel S. Pietro. Postfach",
    "sg:city":"Corteglia",
    "sg:orig_category":"Verwaltung von Immobilien",
    "sg:postcode":"6873",
    "sg:province":"Ticino",
    "wof:name":"Nebianclub Sa",
    "wof:placetype":"venue"
},
  "geometry": {"coordinates":[9.009595871,45.8600730896],"type":"Point"}
}