{
  "type": "Feature",
  "properties": {
    "iso:country":"CH",
    "sg:address":"Usterstrasse 120",
    "sg:city":"Esslingen",
    "sg:orig_category":"Herstellung von M\u00f6beln",
    "sg:phone":"+41 19840162",
    "sg:postcode":"8133",
    "sg:province":"Z\u00fcrich",
    "wof:name":"Ernst Hohl & Co M\u00f6belfabrik",
    "wof:placetype":"venue"
},
  "geometry": {"coordinates":[8.712720871,47.2898483276],"type":"Point"}
}