{
  "type": "Feature",
  "properties": {
    "iso:country":"CH",
    "sg:address":"Kasernenstrasse 15",
    "sg:city":"B\u00fclach",
    "sg:orig_category":"Wirtschaftspr\u00fcfung, Steuerberatung U Treuhand",
    "sg:phone":"+41 18627362",
    "sg:postcode":"8180",
    "sg:province":"Z\u00fcrich",
    "wof:name":"Treumag Treuhand Ag",
    "wof:placetype":"venue"
},
  "geometry": {"coordinates":[8.5386762619,47.5183029175],"type":"Point"}
}