{
  "type": "Feature",
  "properties": {
    "iso:country":"CH",
    "sg:address":"Via Zurigo 1",
    "sg:city":"Lugano",
    "sg:orig_category":"Detailhandel mit B\u00fcchern",
    "sg:phone":"+41 91 923 10 30",
    "sg:postcode":"6900",
    "sg:province":"Ticino",
    "wof:name":"Rosemarie Bernasconi Il Botteghino Negozio Libri",
    "wof:placetype":"venue"
},
  "geometry": {"coordinates":[8.956276,46.011272],"type":"Point"}
}