{
  "type": "Feature",
  "properties": {
    "iso:country":"CH",
    "sg:address":"Surlej",
    "sg:city":"Silvaplana",
    "sg:classifiers":[
        {
            "category":"Travel",
            "subcategory":"Hotels & Motels",
            "type":"Entertainment"
        }
    ],
    "sg:phone":"+41 81 826 50 50",
    "sg:postcode":"7513",
    "sg:province":"Graubunden",
    "sg:tags":[
        "hotels",
        "mit",
        "restaurant"
    ],
    "wof:name":"Hotel Chesa Margun Sils Ag",
    "wof:placetype":"venue"
},
  "geometry": {"coordinates":[9.7641716003,46.4287643433],"type":"Point"}
}