{
  "type": "Feature",
  "properties": {
    "iso:country":"CH",
    "sg:address":"Alleestrasse 20",
    "sg:city":"Romanshorn",
    "sg:orig_category":"Arztpraxen",
    "sg:phone":"+41 71 463 10 06",
    "sg:postcode":"8590",
    "sg:province":"Thurgau",
    "wof:name":"Dr.med.j\u00f6rg Vollenweider Arzt F.allgemeine Medizin Fmh",
    "wof:placetype":"venue"
},
  "geometry": {"coordinates":[9.377152,47.566929],"type":"Point"}
}