{
  "type": "Feature",
  "properties": {
    "iso:country":"CH",
    "sg:address":"8507 Salen-reutenen. Postfach",
    "sg:city":"Salen-reutenen",
    "sg:classifiers":[
        {
            "category":"Travel",
            "subcategory":"Hotels & Motels",
            "type":"Entertainment"
        }
    ],
    "sg:postcode":"8507",
    "sg:province":"Thurgau",
    "sg:tags":[
        "hotels",
        "mit",
        "restaurant"
    ],
    "wof:name":"Pius M\u00e4chler",
    "wof:placetype":"venue"
},
  "geometry": {"coordinates":[9.015458107,47.6503143311],"type":"Point"}
}