{
  "type": "Feature",
  "properties": {
    "iso:country":"CH",
    "sg:address":"Im B\u00fcntli 197",
    "sg:city":"Siglistorf",
    "sg:classifiers":[
        {
            "category":"Banks & Credit Unions",
            "subcategory":"Investment Brokerage",
            "type":"Services"
        }
    ],
    "sg:phone":"+41 56 243 12 71",
    "sg:postcode":"5462",
    "sg:province":"Aargau",
    "sg:tags":[
        "erp",
        "software",
        "planning",
        "resource",
        "enterprise"
    ],
    "wof:name":"Cbs Computer Business Service Gmbh",
    "wof:placetype":"venue"
},
  "geometry": {"coordinates":[8.3758420944,47.5433731079],"type":"Point"}
}