{
  "type": "Feature",
  "properties": {
    "iso:country":"CH",
    "sg:address":"1325",
    "sg:city":"Vaulion",
    "sg:orig_category":"S\u00e4ge, Hobel U Holzimpr\u00e4gnierwerke S\u00e4gewerke",
    "sg:phone":"+41 21 843 29 47",
    "sg:postcode":"1325",
    "sg:province":"Vaud",
    "wof:name":"Scierie Goy Sa",
    "wof:placetype":"venue"
},
  "geometry": {"coordinates":[6.3902349472,46.6893463135],"type":"Point"}
}