{
  "type": "Feature",
  "properties": {
    "addr:full":"Vorderdorf Merligen Bern 3658",
    "addr:postcode":"3658",
    "addr:street":"Vorderdorf;Bern",
    "iso:country":"CH",
    "sg:address":"Vorderdorf",
    "sg:city":"Merligen",
    "sg:orig_category":"Blumen U Zierpflanzenbau Detailhandel mit Blumen U Pflanzen",
    "sg:phone":"+41 33 251 22 27",
    "sg:postcode":"3658",
    "sg:province":"Bern",
    "wof:name":"Schertenleib & Rupp",
    "wof:placetype":"venue"
},
  "geometry": {"coordinates":[7.732545,46.702095],"type":"Point"}
}