{
  "type": "Feature",
  "properties": {
    "iso:country":"CH",
    "sg:address":"Kantonsstrasse 322",
    "sg:city":"Gamsen",
    "sg:orig_category":"Detailhandel mit Sportartikeln",
    "sg:phone":"+41 27 923 09 06",
    "sg:postcode":"3900",
    "sg:province":"Valais",
    "wof:name":"Sun-shine Sport Gmbh Sportgesch\u00e4ft",
    "wof:placetype":"venue"
},
  "geometry": {"coordinates":[7.9592161179,46.3059959412],"type":"Point"}
}