{
  "type": "Feature",
  "properties": {
    "iso:country":"CH",
    "sg:address":"Brunngasse",
    "sg:city":"M\u00f6hlin",
    "sg:orig_category":"Detailhandel mit Waren verschiedener Art, Hauptrichtung Nahrungsmittel",
    "sg:phone":"+41 61 851 12 17",
    "sg:postcode":"4313",
    "sg:province":"Aargau",
    "wof:name":"Migros-markt",
    "wof:placetype":"venue"
},
  "geometry": {"coordinates":[7.8459701538,47.5577888489],"type":"Point"}
}