{
  "type": "Feature",
  "properties": {
    "addr:full":"Hintere Gasse 14 Laufen Basel-Landschaft 4242",
    "addr:housenumber":"14",
    "addr:postcode":"4242",
    "addr:street":"Hintere Gasse",
    "iso:country":"CH",
    "sg:address":"Hintere Gasse 14",
    "sg:city":"Laufen",
    "sg:orig_category":"Detailhandel mit Antiquit\u00e4ten",
    "sg:phone":"+41 61 761 50 70",
    "sg:postcode":"4242",
    "sg:province":"Basel-Landschaft",
    "wof:name":"Hanni Imhof Antiquit\u00e4ten",
    "wof:placetype":"venue"
},
  "geometry": {"coordinates":[7.50129,47.421635],"type":"Point"}
}