{
  "type": "Feature",
  "properties": {
    "iso:country":"CH",
    "sg:address":"Stadtplatz 1",
    "sg:city":"Aarberg",
    "sg:orig_category":"Architekturb\u00fcros",
    "sg:phone":"+41 32 422 47 12",
    "sg:postcode":"3270",
    "sg:province":"Bern",
    "wof:name":"Adep Sa Architecture Et Construction",
    "wof:placetype":"venue"
},
  "geometry": {"coordinates":[7.353521,47.372921],"type":"Point"}
}