{
  "type": "Feature",
  "properties": {
    "iso:country":"CH",
    "sg:address":"Fellerstrasse 20 3027 Bern. Postfach 346",
    "sg:city":"Bern",
    "sg:orig_category":"Primarschulen",
    "sg:phone":"+41 71 222 96 45",
    "sg:postcode":"3027",
    "sg:province":"Bern",
    "wof:name":"Primarschule Tschudiwies",
    "wof:placetype":"venue"
},
  "geometry": {"coordinates":[9.365228653,47.4167823792],"type":"Point"}
}