{
  "type": "Feature",
  "properties": {
    "iso:country":"CH",
    "sg:address":"Im Baumgarten 8",
    "sg:city":"Bassersdorf",
    "sg:orig_category":"Handelsvermittlung U Grosshandel R\u00fcckgewinnung U Vorbereitung f\u00fcr die Wiederverwertung Recycling",
    "sg:phone":"+41 18366341",
    "sg:postcode":"8303",
    "sg:province":"Z\u00fcrich",
    "wof:name":"Hans Hertach Alteisen & Metalle",
    "wof:placetype":"venue"
},
  "geometry": {"coordinates":[8.6265974045,47.4392929077],"type":"Point"}
}