{
  "type": "Feature",
  "properties": {
    "iso:country":"CH",
    "sg:address":"Industriestrasse",
    "sg:city":"Spiez",
    "sg:orig_category":"Herstellung von \u00d6fen U Brennern Verlegen von Fliesen U Platten",
    "sg:phone":"+41 33 654 15 50",
    "sg:postcode":"3700",
    "sg:province":"Bern",
    "wof:name":"F. H\u00f6nger",
    "wof:placetype":"venue"
},
  "geometry": {"coordinates":[7.6418418884,46.6975708008],"type":"Point"}
}