{
  "type": "Feature",
  "properties": {
    "iso:country":"CH",
    "sg:address":"Place Dufour 9",
    "sg:city":"Morges",
    "sg:orig_category":"Sonstiger Grosshandel",
    "sg:phone":"+41 21 801 68 75",
    "sg:postcode":"1110",
    "sg:province":"Vaud",
    "wof:name":"Bm Diffusion, Maze Marianne",
    "wof:placetype":"venue"
},
  "geometry": {"coordinates":[6.4954781532,46.507270813],"type":"Point"}
}