{
  "type": "Feature",
  "properties": {
    "iso:country":"CH",
    "sg:address":"Rue De La Colombi\u00e8re 9",
    "sg:city":"Nyon",
    "sg:orig_category":"Sonstige Bauinstallation",
    "sg:phone":"+41 22 362 35 30",
    "sg:postcode":"1260",
    "sg:province":"Vaud",
    "wof:name":"Jean-g\u00e9rard Bontron Enseignes Lumineuses",
    "wof:placetype":"venue"
},
  "geometry": {"coordinates":[6.2415847778,46.3826637268],"type":"Point"}
}