{
  "type": "Feature",
  "properties": {
    "iso:country":"CH",
    "sg:address":"3961",
    "sg:city":"Grimentz",
    "sg:orig_category":"Detailhandel mit Sportartikeln Reparatur von Schuhen U Lederwaren",
    "sg:phone":"+41 27 283 11 59",
    "sg:postcode":"3961",
    "sg:province":"Valais",
    "wof:name":"Jean Chevrier",
    "wof:placetype":"venue"
},
  "geometry": {"coordinates":[7.508395195,46.0821838379],"type":"Point"}
}