{
  "type": "Feature",
  "properties": {
    "iso:country":"CH",
    "sg:address":"Schaffhauserstrasse 29 8152 Opfikon. Postfach",
    "sg:city":"Glattbrugg",
    "sg:orig_category":"Instandhaltung U Reparatur von Automobilen",
    "sg:postcode":"8152",
    "sg:province":"Z\u00fcrich",
    "wof:name":"L\u00f6tscher Carrosserie.",
    "wof:placetype":"venue"
},
  "geometry": {"coordinates":[7.6532797813,46.3069839478],"type":"Point"}
}