{
  "type": "Feature",
  "properties": {
    "iso:country":"CH",
    "sg:address":"Wohnhausen",
    "sg:city":"Rufi",
    "sg:orig_category":"Sportvereine Sch\u00fctzen",
    "sg:phone":"+41 56 621 15 46",
    "sg:postcode":"8723",
    "sg:province":"St. Gallen",
    "wof:name":"Feldwaffenverein",
    "wof:placetype":"venue"
},
  "geometry": {"coordinates":[8.2755680084,47.3156204224],"type":"Point"}
}