{
  "type": "Feature",
  "properties": {
    "iso:country":"CH",
    "sg:address":"Place Roland-b\u00e9guelin 10",
    "sg:city":"Del\u00e9mont",
    "sg:classifiers":[
        {
            "category":"Personal",
            "subcategory":"Piercing",
            "type":"Services"
        }
    ],
    "sg:phone":"+41 79 212 29 83",
    "sg:postcode":"2800",
    "sg:province":"Jura",
    "sg:tags":[
        "tattoo"
    ],
    "wof:name":"Body Piercing Studio",
    "wof:placetype":"venue"
},
  "geometry": {"coordinates":[6.8211460114,47.0983734131],"type":"Point"}
}