{
  "type": "Feature",
  "properties": {
    "iso:country":"CH",
    "sg:address":"Rue Du Pr\u00e9-de-la-fontaine 15",
    "sg:city":"Meyrin",
    "sg:orig_category":"Siebdruck",
    "sg:phone":"+41 79 785 71 33",
    "sg:postcode":"1217",
    "sg:province":"Gen\u00e8ve",
    "wof:name":"S\u00e9ri Team Zanette & Cie Atelier De S\u00e9rigraphie",
    "wof:placetype":"venue"
},
  "geometry": {"coordinates":[6.0722160339,46.2284431458],"type":"Point"}
}