{
  "type": "Feature",
  "properties": {
    "iso:country":"CH",
    "sg:address":"Chemin Rondelle 4",
    "sg:city":"Evilard",
    "sg:orig_category":"Kauf U Verkauf von Immobilien auf eigene Rechnung",
    "sg:phone":"+41 32 323 10 49",
    "sg:postcode":"2533",
    "sg:province":"Bern",
    "wof:name":"Grimm Alice",
    "wof:placetype":"venue"
},
  "geometry": {"coordinates":[7.2329602242,47.147441864],"type":"Point"}
}