{
  "type": "Feature",
  "properties": {
    "iso:country":"CH",
    "sg:address":"Rossbergstrasse 4",
    "sg:city":"Z\u00fcrich",
    "sg:orig_category":"Sportvereine Ballsport Handball",
    "sg:phone":"+41 12016885",
    "sg:postcode":"8002",
    "sg:province":"Z\u00fcrich",
    "wof:name":"Handballclub Tv Enge",
    "wof:placetype":"venue"
},
  "geometry": {"coordinates":[8.5275115967,47.3552360535],"type":"Point"}
}