{
  "type": "Feature",
  "properties": {
    "iso:country":"CH",
    "sg:address":"Nordringstrasse 16",
    "sg:city":"Oensingen",
    "sg:classifiers":[
        {
            "category":"Manufacturing",
            "subcategory":"Food",
            "type":"Manufacturing & Wholesale Goods"
        }
    ],
    "sg:phone":"+41 62 834 13 00",
    "sg:postcode":"4702",
    "sg:province":"Solothurn",
    "sg:tags":[
        "bottle",
        "label"
    ],
    "wof:name":"Huber + Anacker Ag",
    "wof:placetype":"venue"
},
  "geometry": {"coordinates":[7.712837,47.282482],"type":"Point"}
}