{
  "type": "Feature",
  "properties": {
    "iso:country":"CH",
    "sg:address":"Bahnhofstrasse 4 4852 Rothrist. Postfach",
    "sg:city":"Rothrist",
    "sg:orig_category":"Herstellung von Teppichen",
    "sg:postcode":"4852",
    "sg:province":"Aargau",
    "wof:name":"Lauper Gmbh",
    "wof:placetype":"venue"
},
  "geometry": {"coordinates":[7.8795552254,47.3058128357],"type":"Point"}
}