{
  "type": "Feature",
  "properties": {
    "iso:country":"CH",
    "sg:address":"Z\u00fcrcherstrasse 333",
    "sg:city":"Frauenfeld",
    "sg:orig_category":"Handel mit Automobilen",
    "sg:phone":"+41 52 721 12 13",
    "sg:postcode":"8500",
    "sg:province":"Thurgau",
    "wof:name":"Amoca Ag",
    "wof:placetype":"venue"
},
  "geometry": {"coordinates":[8.9133090973,47.5666007996],"type":"Point"}
}