{
  "type": "Feature",
  "properties": {
    "iso:country":"CH",
    "sg:address":"Dorf",
    "sg:city":"D\u00e4rligen",
    "sg:orig_category":"Granit",
    "sg:phone":"+41 33 657 80 20",
    "sg:postcode":"3707",
    "sg:province":"Bern",
    "wof:name":"Steinbr\u00fcche Herbrig Ag",
    "wof:placetype":"venue"
},
  "geometry": {"coordinates":[7.8128499985,46.660484314],"type":"Point"}
}