{
  "type": "Feature",
  "properties": {
    "addr:full":"Sonneggstrasse 15 Belp Bern 3123",
    "addr:housenumber":"15",
    "addr:postcode":"3123",
    "addr:street":"Sonneggstrasse",
    "iso:country":"CH",
    "sg:address":"Sonneggstrasse 15",
    "sg:city":"Belp",
    "sg:orig_category":"Advokaturb\u00fcros",
    "sg:phone":"+41 31 819 27 28",
    "sg:postcode":"3123",
    "sg:province":"Bern",
    "wof:name":"J\u00fcrg H\u00fcnerwadel Advokaturb\u00fcro",
    "wof:placetype":"venue"
},
  "geometry": {"coordinates":[7.49696,46.896751],"type":"Point"}
}