{
  "type": "Feature",
  "properties": {
    "addr:full":"Chemin De Malley 16 Lausanne Vaud 1007",
    "addr:housenumber":"16",
    "addr:postcode":"1007",
    "addr:street":"Chemin De Malley",
    "iso:country":"CH",
    "sg:address":"Chemin De Malley 16",
    "sg:city":"Lausanne",
    "sg:orig_category":"Arztpraxen",
    "sg:phone":"+41 21 625 76 33",
    "sg:postcode":"1007",
    "sg:province":"Vaud",
    "wof:name":"Dr M\u00e9d. Antoine Wachsmuth M\u00e9decin G\u00e9n\u00e9raliste",
    "wof:placetype":"venue"
},
  "geometry": {"coordinates":[6.60668,46.524128],"type":"Point"}
}