{
  "type": "Feature",
  "properties": {
    "iso:country":"CH",
    "sg:address":"Rain 19 8222 Beringen. Postfach",
    "sg:city":"Beringen",
    "sg:orig_category":"Technische, physikalische U chemische Untersuchung",
    "sg:postcode":"8222",
    "sg:province":"Schaffhausen",
    "wof:name":"Udg Umwelt Beratung Gmbh Beratung U. Coaching Von Umweltdiensten. Lizenzen; Verwertung Usw",
    "wof:placetype":"venue"
},
  "geometry": {"coordinates":[8.586265564,47.698348999],"type":"Point"}
}