{
  "type": "Feature",
  "properties": {
    "iso:country":"CH",
    "sg:address":"Fr\u00f6schenweg 15",
    "sg:city":"Birsfelden",
    "sg:classifiers":[
        {
            "category":"Banks & Credit Unions",
            "subcategory":"Investment Brokerage",
            "type":"Services"
        }
    ],
    "sg:phone":"+41 61 313 03 85",
    "sg:postcode":"4127",
    "sg:province":"Basel-Landschaft",
    "sg:tags":[
        "bearing",
        "ball"
    ],
    "wof:name":"Derol Ag",
    "wof:placetype":"venue"
},
  "geometry": {"coordinates":[7.624718,47.547131],"type":"Point"}
}