{
  "type": "Feature",
  "properties": {
    "addr:full":"Route De Reculan 1 Bussigny-lausanne Vaud 1030",
    "addr:housenumber":"1",
    "addr:postcode":"1030",
    "addr:street":"Route De Reculan",
    "iso:country":"CH",
    "sg:address":"Route De Reculan 1",
    "sg:city":"Bussigny-lausanne",
    "sg:orig_category":"Allgemeiner Hoch U Tiefbau Allgemeiner Hochbau",
    "sg:phone":"+41 62 771 34 33",
    "sg:postcode":"1030",
    "sg:province":"Vaud",
    "wof:name":"Ren\u00e9 Merz Ag",
    "wof:placetype":"venue"
},
  "geometry": {"coordinates":[8.179611,47.266674],"type":"Point"}
}