{
  "type": "Feature",
  "properties": {
    "iso:country":"CH",
    "sg:address":"Route De Chailly 1",
    "sg:city":"Clarens",
    "sg:orig_category":"Fussreflexzonenmassage",
    "sg:phone":"+41 21 964 16 51",
    "sg:postcode":"1815",
    "sg:province":"Vaud",
    "wof:name":"Marie-france Vernaz R\u00e9flexologie",
    "wof:placetype":"venue"
},
  "geometry": {"coordinates":[6.8935542107,46.4459533691],"type":"Point"}
}