{
  "type": "Feature",
  "properties": {
    "addr:full":"Haldenstrasse 5 Hedingen Z\u00fcrich 8908",
    "addr:housenumber":"5",
    "addr:postcode":"8908",
    "addr:street":"Haldenstrasse",
    "iso:country":"CH",
    "sg:address":"Haldenstrasse 5",
    "sg:city":"Hedingen",
    "sg:orig_category":"Arztpraxen",
    "sg:phone":"+41 17617177",
    "sg:postcode":"8908",
    "sg:province":"Z\u00fcrich",
    "wof:name":"Dres Med. M. & B. Kehrer Aerzte F\u00fcr Allg.medizin Fmh",
    "wof:placetype":"venue"
},
  "geometry": {"coordinates":[8.449381,47.297684],"type":"Point"}
}