{
  "type": "Feature",
  "properties": {
    "iso:country":"CH",
    "sg:address":"Av. Du G\u00e9n\u00e9ral-guisan 26",
    "sg:city":"Fribourg",
    "sg:orig_category":"Maler U Glasergewerbe",
    "sg:phone":"+41 26 466 32 62",
    "sg:postcode":"1700",
    "sg:province":"Fribourg",
    "wof:name":"Rotzetter Erwin",
    "wof:placetype":"venue"
},
  "geometry": {"coordinates":[7.1523561478,46.8118171692],"type":"Point"}
}