{
  "type": "Feature",
  "properties": {
    "iso:country":"CH",
    "sg:address":"Via Henri Guisan 3a",
    "sg:city":"Bellinzona",
    "sg:orig_category":"Mineralquellen, Herstellung von alkoholfreien Getr\u00e4nken",
    "sg:phone":"+41 91 825 14 42",
    "sg:postcode":"6500",
    "sg:province":"Ticino",
    "wof:name":"G. Coldesina F.carugati Succ.",
    "wof:placetype":"venue"
},
  "geometry": {"coordinates":[9.0244579315,46.1950645447],"type":"Point"}
}