{
  "type": "Feature",
  "properties": {
    "iso:country":"CH",
    "sg:address":"Oberdorfstrasse 22",
    "sg:city":"Thalwil",
    "sg:orig_category":"Maler U Glasergewerbe Malerei",
    "sg:phone":"+41 17209756",
    "sg:postcode":"8800",
    "sg:province":"Z\u00fcrich",
    "wof:name":"Andreas Pfarrmaier Malergesch\u00e4ft",
    "wof:placetype":"venue"
},
  "geometry": {"coordinates":[8.5656967163,47.2877044678],"type":"Point"}
}