{
  "type": "Feature",
  "properties": {
    "iso:country":"CH",
    "sg:address":"Benknerstrasse 12",
    "sg:city":"Uznach",
    "sg:orig_category":"Bauschreinerei Herstellung von Konstruktionsteilen, Fertigbauteilen U Ausbauelementen aus Holz",
    "sg:phone":"+41 55 280 32 55",
    "sg:postcode":"8730",
    "sg:province":"St. Gallen",
    "wof:name":"Widmer K\u00fcchen Schreinerei",
    "wof:placetype":"venue"
},
  "geometry": {"coordinates":[8.985084,47.220779],"type":"Point"}
}