{
  "type": "Feature",
  "properties": {
    "iso:country":"CH",
    "sg:address":"Traverse Chemin De La 4 1170 Aubonne. Postfach",
    "sg:city":"Aubonne",
    "sg:orig_category":"Elektroinstallation",
    "sg:phone":"+41 81 854 15 09",
    "sg:postcode":"1170",
    "sg:province":"Vaud",
    "wof:name":"Federspiel & Zala Sa Elektroinstallationen",
    "wof:placetype":"venue"
},
  "geometry": {"coordinates":[9.9249753952,46.5796699524],"type":"Point"}
}