{
  "type": "Feature",
  "properties": {
    "iso:country":"CH",
    "sg:address":"Sennhofstrasse 90",
    "sg:city":"Zollikerberg",
    "sg:orig_category":"Unclassifiable Establishments",
    "sg:postcode":"8125",
    "sg:province":"Z\u00fcrich",
    "wof:name":"Clemens Wieseotte Century Consult",
    "wof:placetype":"venue"
},
  "geometry": {"coordinates":[8.6186532974,47.3440628052],"type":"Point"}
}