{
  "type": "Feature",
  "properties": {
    "iso:country":"CH",
    "sg:address":"Steinhaldenstrasse 55 8002 Z\u00fcrich. Postfach",
    "sg:city":"Z\u00fcrich",
    "sg:orig_category":"Unclassifiable Establishments",
    "sg:postcode":"8001",
    "sg:province":"Z\u00fcrich",
    "wof:name":"Baumann Christian Software; Entwicklung U. Verkauf Usw.",
    "wof:placetype":"venue"
},
  "geometry": {"coordinates":[8.5280056,47.3590736389],"type":"Point"}
}