{
  "type": "Feature",
  "properties": {
    "iso:country":"CH",
    "sg:address":"Hauptstrasse 41",
    "sg:city":"Glarus",
    "sg:orig_category":"Detailhandel mit Bekleidung Fachdetailhandel in Verkaufsr\u00e4umen",
    "sg:phone":"+41 55 640 17 07",
    "sg:postcode":"8750",
    "sg:province":"Glarus",
    "wof:name":"Hefti-sport",
    "wof:placetype":"venue"
},
  "geometry": {"coordinates":[9.067325,47.040531],"type":"Point"}
}