{
  "type": "Feature",
  "properties": {
    "iso:country":"CH",
    "sg:address":"Herbstackerstrasse 77",
    "sg:city":"Seuzach",
    "sg:orig_category":"Sportvereine Turnen",
    "sg:phone":"+41 52 335 42 85",
    "sg:postcode":"8472",
    "sg:province":"Z\u00fcrich",
    "wof:name":"Turnverein Seen Winterthur",
    "wof:placetype":"venue"
},
  "geometry": {"coordinates":[8.738158226,47.5386428833],"type":"Point"}
}