{
  "type": "Feature",
  "properties": {
    "iso:country":"CH",
    "sg:address":"In Der Weid 2",
    "sg:city":"Seuzach",
    "sg:orig_category":"Erbringung von Dienstleistungen f\u00fcr Unternehmen",
    "sg:postcode":"8472",
    "sg:province":"Z\u00fcrich",
    "wof:name":"Newal Ag",
    "wof:placetype":"venue"
},
  "geometry": {"coordinates":[8.7395057678,47.5326499939],"type":"Point"}
}