{
  "type": "Feature",
  "properties": {
    "iso:country":"CH",
    "sg:address":"Dorfgasse 1",
    "sg:city":"Horgen",
    "sg:orig_category":"Detailhandel mit Textilien Detailhandel mit elektrischen Haushalts-,Radio U Fernsehger\u00e4ten sowie Mus",
    "sg:phone":"+41 17255503",
    "sg:postcode":"8810",
    "sg:province":"Z\u00fcrich",
    "wof:name":"Tanner Hans, Bernina-n\u00e4hcenter",
    "wof:placetype":"venue"
},
  "geometry": {"coordinates":[8.5986223221,47.2602233887],"type":"Point"}
}