{
  "type": "Feature",
  "properties": {
    "iso:country":"CH",
    "sg:address":"Auernweg 10",
    "sg:city":"N\u00e4fels",
    "sg:orig_category":"Sanit\u00e4r, Heizungs U L\u00fcftungsinstallation",
    "sg:postcode":"8752",
    "sg:province":"Glarus",
    "wof:name":"Marlise K\u00fcng-landolt, Sanit\u00e4rbedarfsartikel",
    "wof:placetype":"venue"
},
  "geometry": {"coordinates":[9.0605192184,47.0901794434],"type":"Point"}
}