{
  "type": "Feature",
  "properties": {
    "iso:country":"CH",
    "sg:address":"Bp 1248",
    "sg:city":"Sion",
    "sg:classifiers":[
        {
            "category":"Food Court",
            "type":"Food & Drink"
        }
    ],
    "sg:phone":"+41 27 346 41 05",
    "sg:postcode":"1951",
    "sg:province":"Valais",
    "sg:tags":[
        "product",
        "related"
    ],
    "wof:name":"Seba Aproz Sa",
    "wof:placetype":"venue"
},
  "geometry": {"coordinates":[7.3588571548,46.2280921936],"type":"Point"}
}