{
  "type": "Feature",
  "properties": {
    "iso:country":"CH",
    "sg:address":"Alleestrasse 58 8590 Romanshorn. Postfach 83",
    "sg:city":"Romanshorn",
    "sg:orig_category":"Verwaltung von Immobilien Wirtschaftspr\u00fcfung, Steuerberatung U Treuhand",
    "sg:phone":"+41 56 241 20 10",
    "sg:postcode":"8590",
    "sg:province":"Thurgau",
    "wof:name":"Sk Treuhand Ag",
    "wof:placetype":"venue"
},
  "geometry": {"coordinates":[8.3296632767,47.5207366943],"type":"Point"}
}