{
  "type": "Feature",
  "properties": {
    "iso:country":"CH",
    "sg:address":"H\u00f6libachstrasse 50",
    "sg:city":"Obfelden",
    "sg:orig_category":"Sonstiger Grosshandel",
    "sg:phone":"+41 56 443 33 26",
    "sg:postcode":"8912",
    "sg:province":"Z\u00fcrich",
    "wof:name":"Wintex Ag",
    "wof:placetype":"venue"
},
  "geometry": {"coordinates":[8.1419649124,47.4393424988],"type":"Point"}
}