{
  "type": "Feature",
  "properties": {
    "iso:country":"CH",
    "sg:address":"9107",
    "sg:city":"Urn\u00e4sch",
    "sg:orig_category":"Non-Classified Establishments",
    "sg:phone":"+41 81 332 12 18",
    "sg:postcode":"9107",
    "sg:province":"Appenzell Ausserrhoden",
    "wof:name":"Berghaus Alpenr\u00f6sli",
    "wof:placetype":"venue"
},
  "geometry": {"coordinates":[9.8581809998,46.9966583252],"type":"Point"}
}