{
  "type": "Feature",
  "properties": {
    "addr:full":"M\u00fcnchwilerstrasse 21 T\u00e4gerschen Thurgau 9554",
    "addr:housenumber":"21",
    "addr:postcode":"9554",
    "addr:street":"Muenchwilerstrasse;Thurgau",
    "iso:country":"CH",
    "sg:address":"M\u00fcnchwilerstrasse 21",
    "sg:city":"T\u00e4gerschen",
    "sg:classifiers":[
        {
            "category":"Manufacturing",
            "subcategory":"Tools & Machinery",
            "type":"Manufacturing & Wholesale Goods"
        }
    ],
    "sg:phone":"+41 71 918 60 70",
    "sg:postcode":"9554",
    "sg:province":"Thurgau",
    "sg:tags":[
        "part",
        "turned",
        "cnc"
    ],
    "wof:name":"F + L Bachmann Ag",
    "wof:placetype":"venue"
},
  "geometry": {"coordinates":[9.026564,47.507763],"type":"Point"}
}