{
  "type": "Feature",
  "properties": {
    "iso:country":"CH",
    "sg:address":"Seminarstrasse 73",
    "sg:city":"Wettingen",
    "sg:orig_category":"Detailhandel mit Metallwaren, Anstrichmitteln, Glaswaren, Bau U Heimwerkerbedarf Sonstige Bauinstall",
    "sg:phone":"+41 56 427 22 65",
    "sg:postcode":"5430",
    "sg:province":"Aargau",
    "wof:name":"Kme-technik Melion",
    "wof:placetype":"venue"
},
  "geometry": {"coordinates":[8.3138618469,47.4630317688],"type":"Point"}
}