{
  "type": "Feature",
  "properties": {
    "iso:country":"CH",
    "sg:address":"Bahnhofstrasse 180 4622 Egerkingen. Postfach",
    "sg:city":"Egerkingen",
    "sg:orig_category":"Non-Classified Establishments",
    "sg:postcode":"4622",
    "sg:province":"Solothurn",
    "wof:name":"Webin24 Gmbh Web-hosting, Web-design Usw",
    "wof:placetype":"venue"
},
  "geometry": {"coordinates":[7.7965598106,47.3174781799],"type":"Point"}
}