{
  "type": "Feature",
  "properties": {
    "iso:country":"CH",
    "sg:address":"Hauptstrasse 25 3186 D\u00fcdingen. Postfach",
    "sg:city":"D\u00fcdingen",
    "sg:classifiers":[
        {
            "category":"Travel",
            "subcategory":"Hotels & Motels",
            "type":"Entertainment"
        }
    ],
    "sg:phone":"+41 26 493 37 83",
    "sg:postcode":"3186",
    "sg:province":"Fribourg",
    "sg:tags":[
        "hotels",
        "mit",
        "restaurant"
    ],
    "wof:name":"E. Zosso Ag",
    "wof:placetype":"venue"
},
  "geometry": {"coordinates":[7.1898188591,46.8483085632],"type":"Point"}
}