{
  "type": "Feature",
  "properties": {
    "iso:country":"CH",
    "sg:address":"Kurvenstrasse 35",
    "sg:city":"Z\u00fcrich",
    "sg:orig_category":"Pensionskassen",
    "sg:phone":"+41 14881288",
    "sg:postcode":"8021",
    "sg:province":"Z\u00fcrich",
    "wof:name":"Personalf\u00fcrsorgestiftung Der Firma Henauer Und Gugler Ag, Ingenierunternehmen F\u00fcr Hoch Und Tiefbau",
    "wof:placetype":"venue"
},
  "geometry": {"coordinates":[8.5416078568,47.3851203918],"type":"Point"}
}