{
  "type": "Feature",
  "properties": {
    "iso:country":"CH",
    "sg:address":"Hauptgasse 4",
    "sg:city":"Appenzell",
    "sg:orig_category":"Verkehrs- and Tourismusb\u00fcros",
    "sg:phone":"+41 71 788 96 41",
    "sg:postcode":"9050",
    "sg:province":"Appenzell Innerhoden",
    "wof:name":"Appenzellerland Tourismus",
    "wof:placetype":"venue"
},
  "geometry": {"coordinates":[9.4098091125,47.3308486938],"type":"Point"}
}