{
  "type": "Feature",
  "properties": {
    "iso:country":"CH",
    "sg:address":"Baselstrasse 60",
    "sg:city":"Riehen",
    "sg:orig_category":"Grosshandel mit B\u00fcromaschinen Grosshandel mit Datenverarbeitungsger\u00e4ten",
    "sg:phone":"+41 18584045",
    "sg:postcode":"4125",
    "sg:province":"Basel-Stadt",
    "wof:name":"Artec Hard-& Software",
    "wof:placetype":"venue"
},
  "geometry": {"coordinates":[8.4186058044,47.5673446655],"type":"Point"}
}