{
  "type": "Feature",
  "properties": {
    "iso:country":"CH",
    "sg:address":"Hauptstrasse 1632",
    "sg:city":"Wildhaus",
    "sg:classifiers":[
        {
            "category":"Travel",
            "subcategory":"Hotels & Motels",
            "type":"Entertainment"
        }
    ],
    "sg:phone":"+41 81 826 52 92",
    "sg:postcode":"9658",
    "sg:province":"St. Gallen",
    "sg:tags":[
        "hotels",
        "mit",
        "restaurant"
    ],
    "wof:name":"Hotel Seraina Ag",
    "wof:placetype":"venue"
},
  "geometry": {"coordinates":[9.764169693,46.4287605286],"type":"Point"}
}