{
  "type": "Feature",
  "properties": {
    "iso:country":"CH",
    "sg:address":"Place De La Taconnerie 3",
    "sg:city":"Gen\u00e8ve",
    "sg:orig_category":"Finanzierungsinstitutionen",
    "sg:phone":"+41 22 341 74 00",
    "sg:postcode":"1204",
    "sg:province":"Gen\u00e8ve",
    "wof:name":"Ufi I Sa Gen\u00e8ve",
    "wof:placetype":"venue"
},
  "geometry": {"coordinates":[6.1481690407,46.2006912231],"type":"Point"}
}