{
  "type": "Feature",
  "properties": {
    "iso:country":"CH",
    "sg:address":"5704",
    "sg:city":"Egliswil",
    "sg:orig_category":"Primarschulen",
    "sg:phone":"+41 62 775 22 53",
    "sg:postcode":"5704",
    "sg:province":"Aargau",
    "wof:name":"Primarschule",
    "wof:placetype":"venue"
},
  "geometry": {"coordinates":[8.1889467239,47.3499946594],"type":"Point"}
}