{
  "type": "Feature",
  "properties": {
    "iso:country":"CH",
    "sg:address":"Dreihubelweg 79 3250 Lyss. Postfach",
    "sg:city":"Lyss",
    "sg:orig_category":"Fernmeldedienste Hardwareberatung",
    "sg:phone":"+41 32 384 69 30",
    "sg:postcode":"3250",
    "sg:province":"Bern",
    "wof:name":"Nanotronic Gmbh Dienstleistungen Im Ber. Der Elektronik- U. Kommunikationstechnik Usw.",
    "wof:placetype":"venue"
},
  "geometry": {"coordinates":[7.3188409805,47.0750350952],"type":"Point"}
}