{
  "type": "Feature",
  "properties": {
    "iso:country":"CH",
    "sg:address":"Graben 4",
    "sg:city":"Zug",
    "sg:orig_category":"Benzin, Heiz\u00f6l and Mineral\u00f6lprodukte Grosshandel Handelsvermittlung von Brennstoffen, Erzen, Metalle",
    "sg:postcode":"6300",
    "sg:province":"Zug",
    "wof:name":"Emc Handels Gmbh \u00d6l-handel",
    "wof:placetype":"venue"
},
  "geometry": {"coordinates":[8.514583,47.166531],"type":"Point"}
}