{
  "type": "Feature",
  "properties": {
    "iso:country":"CH",
    "sg:address":"Leischengasse 2 3714 Frutigen. Postfach",
    "sg:city":"Frutigen",
    "sg:orig_category":"P\u00e9dicure",
    "sg:phone":"+41 33 671 51 50",
    "sg:postcode":"3714",
    "sg:province":"Bern",
    "wof:name":"Michaela Schmid Pedicure",
    "wof:placetype":"venue"
},
  "geometry": {"coordinates":[7.6459012032,46.589263916],"type":"Point"}
}