{
  "type": "Feature",
  "properties": {
    "iso:country":"CH",
    "sg:address":"Industriestr. 8",
    "sg:city":"Bischofszell",
    "sg:classifiers":[
        {
            "category":"Food Court",
            "type":"Food & Drink"
        }
    ],
    "sg:phone":"+41 71 424 73 00",
    "sg:postcode":"9220",
    "sg:province":"Thurgau",
    "sg:tags":[
        "product",
        "related"
    ],
    "wof:name":"Obipektin Ag",
    "wof:placetype":"venue"
},
  "geometry": {"coordinates":[9.2368440628,47.5019721985],"type":"Point"}
}