{
  "type": "Feature",
  "properties": {
    "iso:country":"CH",
    "sg:address":"Dorfstrasse 7",
    "sg:city":"M\u00fcntschemier",
    "sg:orig_category":"Nationale Postdienste",
    "sg:phone":"+41 32 313 17 05",
    "sg:postcode":"3225",
    "sg:province":"Bern",
    "wof:name":"Die Schweizerische Post",
    "wof:placetype":"venue"
},
  "geometry": {"coordinates":[7.1450390816,46.9953613281],"type":"Point"}
}