{
  "type": "Feature",
  "properties": {
    "iso:country":"CH",
    "sg:address":"Schl\u00f6sslistrasse 1 3700 Spiez. Postfach 300",
    "sg:city":"Spiez",
    "sg:orig_category":"Gymnastik U Fitnesszentren Praxis f\u00fcr Atlaslogie",
    "sg:phone":"+41 71 755 44 28",
    "sg:postcode":"3700",
    "sg:province":"Bern",
    "wof:name":"Anne-lyse Burn",
    "wof:placetype":"venue"
},
  "geometry": {"coordinates":[9.549697876,47.375202179],"type":"Point"}
}