{
  "type": "Feature",
  "properties": {
    "iso:country":"CH",
    "sg:address":"Sonnmattrain 8",
    "sg:city":"Adligenswil",
    "sg:orig_category":"Vermietung U Verpachtung von eigenen Immobilien",
    "sg:postcode":"6043",
    "sg:province":"Luzern",
    "wof:name":"M\u00fcller A. Immobilien Ag, Zweigniederlassung Adligenswil",
    "wof:placetype":"venue"
},
  "geometry": {"coordinates":[8.3815736771,47.0755958557],"type":"Point"}
}