{
  "type": "Feature",
  "properties": {
    "iso:country":"CH",
    "sg:address":"Gartenstrasse 3",
    "sg:city":"Zug",
    "sg:orig_category":"Grosshandel mit sonstigen Maschinen U Ausr\u00fcstungen f\u00fcr Industrie, Handel U Schiffahrt",
    "sg:postcode":"6300",
    "sg:province":"Zug",
    "wof:name":"Tiberina Handels Ag",
    "wof:placetype":"venue"
},
  "geometry": {"coordinates":[8.5148210526,47.1700744629],"type":"Point"}
}