{
  "type": "Feature",
  "properties": {
    "iso:country":"CH",
    "sg:address":"W\u00e4ltigasse 8",
    "sg:city":"Mels",
    "sg:orig_category":"Elektrizit\u00e4tsversorgung Wasserversorgung",
    "sg:phone":"+41 81 723 14 17",
    "sg:postcode":"8887",
    "sg:province":"St. Gallen",
    "wof:name":"Elektrizit\u00e4ts-& Wasserwerk Mels",
    "wof:placetype":"venue"
},
  "geometry": {"coordinates":[9.417093277,47.0515441895],"type":"Point"}
}