{
  "type": "Feature",
  "properties": {
    "iso:country":"CH",
    "sg:address":"Route De Bi\u00e8re 26",
    "sg:city":"Apples",
    "sg:orig_category":"Sanit\u00e4r, Heizungs U L\u00fcftungsinstallation Sanit\u00e4rinstallation",
    "sg:phone":"+41 21 800 44 04",
    "sg:postcode":"1143",
    "sg:province":"Vaud",
    "wof:name":"Charly Zaradez Installations Sanitaires",
    "wof:placetype":"venue"
},
  "geometry": {"coordinates":[6.4253277779,46.5516586304],"type":"Point"}
}