{
  "type": "Feature",
  "properties": {
    "iso:country":"CH",
    "sg:address":"Oberwiesstrasse 5",
    "sg:city":"Jona",
    "sg:orig_category":"Sonstiger Grosshandel",
    "sg:postcode":"8645",
    "sg:province":"St. Gallen",
    "wof:name":"Aliu Julia Import & Export",
    "wof:placetype":"venue"
},
  "geometry": {"coordinates":[8.840681076,47.2319068909],"type":"Point"}
}