{
  "type": "Feature",
  "properties": {
    "iso:country":"CH",
    "sg:address":"Z\u00fcrcherstrasse 71 5432 Neuenhof. Postfach 204",
    "sg:city":"Neuenhof",
    "sg:orig_category":"Sicherheitsdienste",
    "sg:phone":"+41 56 406 07 30",
    "sg:postcode":"5432",
    "sg:province":"Aargau",
    "wof:name":"Sidi Group Sicherheitsunternehmen",
    "wof:placetype":"venue"
},
  "geometry": {"coordinates":[8.3229751587,47.4531669617],"type":"Point"}
}