{
  "type": "Feature",
  "properties": {
    "iso:country":"CH",
    "sg:address":"Rue De L'ecluse 21a",
    "sg:city":"Neuch\u00e2tel",
    "sg:classifiers":[
        {
            "category":"Insurance",
            "subcategory":"Insurance Agent",
            "type":"Services"
        }
    ],
    "sg:phone":"+41 32 725 78 26",
    "sg:postcode":"2000",
    "sg:province":"Neuch\u00e2tel",
    "sg:tags":[
        "versicherungsagenturen",
        "-broker"
    ],
    "wof:name":"Squar Sa Assurance",
    "wof:placetype":"venue"
},
  "geometry": {"coordinates":[6.9262571335,46.9927101135],"type":"Point"}
}