{
  "type": "Feature",
  "properties": {
    "iso:country":"CH",
    "sg:address":"Mutschellensrtasse 70",
    "sg:city":"Z\u00fcrich",
    "sg:orig_category":"Selbst\u00e4ndige bildende K\u00fcnstler Vermietung U Verpachtung von eigenen Immobilien",
    "sg:phone":"+41 13819300",
    "sg:postcode":"8038",
    "sg:province":"Z\u00fcrich",
    "wof:name":"Memor Ag",
    "wof:placetype":"venue"
},
  "geometry": {"coordinates":[8.5276050568,47.3502502441],"type":"Point"}
}