{
  "type": "Feature",
  "properties": {
    "iso:country":"CH",
    "sg:address":"Gr\u00fcenaustrasse 4",
    "sg:city":"Wattwil",
    "sg:orig_category":"Drogerien Sonstiger Fachdetailhandel mit Nahrungsmitteln, Getr\u00e4nken U Tabak in Verkaufsr\u00e4umen",
    "sg:phone":"+41 71 988 20 40",
    "sg:postcode":"9630",
    "sg:province":"St. Gallen",
    "wof:name":"Dropa Altherr Ag",
    "wof:placetype":"venue"
},
  "geometry": {"coordinates":[9.0860958099,47.3031997681],"type":"Point"}
}