{
  "type": "Feature",
  "properties": {
    "iso:country":"CH",
    "sg:address":"Letziweg 9",
    "sg:city":"Aarburg",
    "sg:orig_category":"Spielsalons",
    "sg:phone":"+41 41 630 12 88",
    "sg:postcode":"4663",
    "sg:province":"Aargau",
    "wof:name":"Billard-center Hollywood",
    "wof:placetype":"venue"
},
  "geometry": {"coordinates":[8.311249733,46.9841918945],"type":"Point"}
}