{
  "type": "Feature",
  "properties": {
    "iso:country":"CH",
    "sg:address":"Freiestrasse 12",
    "sg:city":"Amriswil",
    "sg:classifiers":[
        {
            "category":"Restaurant",
            "type":"Food & Drink"
        }
    ],
    "sg:phone":"+41 71 411 20 14",
    "sg:postcode":"8580",
    "sg:province":"Thurgau",
    "wof:name":"Restaurant Sch\u00f6ntal Amriswil",
    "wof:placetype":"venue"
},
  "geometry": {"coordinates":[9.3008384705,47.5484161377],"type":"Point"}
}