{
  "type": "Feature",
  "properties": {
    "iso:country":"CH",
    "sg:address":"Gare Avenue De La",
    "sg:city":"Fleurier",
    "sg:orig_category":"Unclassifiable Establishments",
    "sg:postcode":"2114",
    "sg:province":"Neuch\u00e2tel",
    "wof:name":"Donbov S\u00e0rl",
    "wof:placetype":"venue"
},
  "geometry": {"coordinates":[6.5804052353,46.9023094177],"type":"Point"}
}