{
  "type": "Feature",
  "properties": {
    "iso:country":"CH",
    "sg:address":"Chasa Sablunera 7562 Samnaun-compatsch. Postfach",
    "sg:city":"Samnaun-compatsch",
    "sg:orig_category":"Herstellung von Konstruktionsteilen, Fertigbauteilen U Ausbauelementen aus Holz",
    "sg:phone":"+41 79 467 66 41",
    "sg:postcode":"7562",
    "sg:province":"Graubunden",
    "wof:name":"Kuhn Roland",
    "wof:placetype":"venue"
},
  "geometry": {"coordinates":[7.3273501396,47.1881484985],"type":"Point"}
}