{
  "type": "Feature",
  "properties": {
    "iso:country":"CH",
    "sg:address":"Maria-bernarda-strasse 35",
    "sg:city":"Auw",
    "sg:orig_category":"Organisationen des Gesundheitswesen",
    "sg:phone":"+41 56 668 20 86",
    "sg:postcode":"5644",
    "sg:province":"Aargau",
    "wof:name":"Samariterverein Sins",
    "wof:placetype":"venue"
},
  "geometry": {"coordinates":[8.3741388321,47.2080307007],"type":"Point"}
}