{
  "type": "Feature",
  "properties": {
    "iso:country":"CH",
    "sg:address":"La Bagnardise 7 1936 Verbier. Postfach",
    "sg:city":"Verbier",
    "sg:orig_category":"Dienstleistungen von Beteiligungsgesellschaften",
    "sg:postcode":"1936",
    "sg:province":"Valais",
    "wof:name":"Proleg",
    "wof:placetype":"venue"
},
  "geometry": {"coordinates":[5.1808700562,45.8973388672],"type":"Point"}
}