{
  "type": "Feature",
  "properties": {
    "iso:country":"CH",
    "sg:address":"B\u00f6lli 4",
    "sg:city":"Rafz",
    "sg:orig_category":"Vorschulen, Kinderg\u00e4rten",
    "sg:phone":"+41 18690841",
    "sg:postcode":"8197",
    "sg:province":"Z\u00fcrich",
    "wof:name":"Kindergarten B\u00f6lli",
    "wof:placetype":"venue"
},
  "geometry": {"coordinates":[8.5410604477,47.6088790894],"type":"Point"}
}