{
  "type": "Feature",
  "properties": {
    "iso:country":"CH",
    "sg:address":"Badgasse 2 8400 Winterthur. Postfach",
    "sg:city":"Winterthur",
    "sg:orig_category":"Detailhandel mit B\u00fcchern, Zeitungen, Schreib U Papeteriewaren Herstellung von elektrischen Lampen U ",
    "sg:phone":"+41 61 701 43 25",
    "sg:postcode":"8400",
    "sg:province":"Z\u00fcrich",
    "wof:name":"D\u00f6rfler Rudolf",
    "wof:placetype":"venue"
},
  "geometry": {"coordinates":[7.621596,47.475124],"type":"Point"}
}