{
  "type": "Feature",
  "properties": {
    "iso:country":"CH",
    "sg:address":"Schmiedgasse 50",
    "sg:city":"Stans",
    "sg:orig_category":"Betrieb von Taxis",
    "sg:phone":"+41 41 610 66 33",
    "sg:postcode":"6370",
    "sg:province":"Nidwalden",
    "wof:name":"Marie-theres Gut Mini Taxi Stans",
    "wof:placetype":"venue"
},
  "geometry": {"coordinates":[8.370612,46.956364],"type":"Point"}
}