{
  "type": "Feature",
  "properties": {
    "iso:country":"CH",
    "sg:address":"Churerstrasse 28",
    "sg:city":"Altendorf",
    "sg:orig_category":"Handels-H\u00e4user U Gesellschaften",
    "sg:phone":"+41 55 462 19 46",
    "sg:postcode":"8852",
    "sg:province":"Schwyz",
    "wof:name":"Saint Georges Services Ag",
    "wof:placetype":"venue"
},
  "geometry": {"coordinates":[8.83548069,47.190486908],"type":"Point"}
}