{
  "type": "Feature",
  "properties": {
    "iso:country":"CH",
    "sg:address":"Bergstrasse 33",
    "sg:city":"Meggen",
    "sg:orig_category":"Detailhandel mit Schuhen U Lederwaren",
    "sg:phone":"+41 41 377 18 01",
    "sg:postcode":"6045",
    "sg:province":"Luzern",
    "wof:name":"Aiku Gmbh",
    "wof:placetype":"venue"
},
  "geometry": {"coordinates":[8.3804941177,47.0601768494],"type":"Point"}
}