{
  "type": "Feature",
  "properties": {
    "iso:country":"CH",
    "sg:address":"Avenue Louis-levade 6",
    "sg:city":"Vevey",
    "sg:orig_category":"Kinderkrippen U horte Vorschulen, Kinderg\u00e4rten",
    "sg:phone":"+41 21 925 53 25",
    "sg:postcode":"1800",
    "sg:province":"Vaud",
    "wof:name":"Garderie & Jardin D'enfants Les Marionnettes",
    "wof:placetype":"venue"
},
  "geometry": {"coordinates":[6.8498902321,46.4626159668],"type":"Point"}
}