{
  "type": "Feature",
  "properties": {
    "iso:country":"CH",
    "sg:address":"Seestrasse 247",
    "sg:city":"Herrliberg",
    "sg:classifiers":[
        {
            "category":"Restaurant",
            "type":"Food & Drink"
        }
    ],
    "sg:phone":"+41 19158110",
    "sg:postcode":"8704",
    "sg:province":"Z\u00fcrich",
    "wof:name":"Taverna Il Faro",
    "wof:placetype":"venue"
},
  "geometry": {"coordinates":[8.6099863052,47.2838020325],"type":"Point"}
}