{
  "type": "Feature",
  "properties": {
    "iso:country":"CH",
    "sg:address":"Seestrasse 431",
    "sg:city":"M\u00e4nnedorf",
    "sg:orig_category":"Non-Classified Establishments",
    "sg:phone":"+41 19206969",
    "sg:postcode":"8708",
    "sg:province":"Z\u00fcrich",
    "wof:name":"Global Online Speidel Und Szabo",
    "wof:placetype":"venue"
},
  "geometry": {"coordinates":[8.7072200775,47.2470016479],"type":"Point"}
}