{
  "type": "Feature",
  "properties": {
    "iso:country":"CH",
    "sg:address":"Talweg 2",
    "sg:city":"Ittigen",
    "sg:orig_category":"W\u00e4scherei U chemische Reinigung",
    "sg:phone":"+41 31 921 40 70",
    "sg:postcode":"3063",
    "sg:province":"Bern",
    "wof:name":"Wimag-reinigungen",
    "wof:placetype":"venue"
},
  "geometry": {"coordinates":[7.4847521782,46.9736633301],"type":"Point"}
}