{
  "type": "Feature",
  "properties": {
    "iso:country":"CH",
    "sg:address":"Hauptstrasse 19 Werdthof 3273 Kappelen. Postfach",
    "sg:city":"Kappelen",
    "sg:orig_category":"Unclassifiable Establishments",
    "sg:postcode":"3273",
    "sg:province":"Bern",
    "wof:name":"Bangerter Daniel, G\u00e4rtnerei Gem\u00fcse Und Schnittblumeng\u00e4rtnerei",
    "wof:placetype":"venue"
},
  "geometry": {"coordinates":[7.2617311478,47.055896759],"type":"Point"}
}