{
  "type": "Feature",
  "properties": {
    "iso:country":"CH",
    "sg:address":"Zugerstrasse 2",
    "sg:city":"Steinhausen",
    "sg:classifiers":[
        {
            "category":"Restaurant",
            "type":"Food & Drink"
        }
    ],
    "sg:phone":"+41 79 447 06 46",
    "sg:postcode":"6312",
    "sg:province":"Zug",
    "wof:name":"Restaurant Post",
    "wof:placetype":"venue"
},
  "geometry": {"coordinates":[8.484998703,47.1966323853],"type":"Point"}
}