{
  "type": "Feature",
  "properties": {
    "iso:country":"CH",
    "sg:address":"1905",
    "sg:city":"Dor\u00e9naz",
    "sg:orig_category":"Autogaragen Autospenglereien",
    "sg:phone":"+41 22 796 10 12",
    "sg:postcode":"1905",
    "sg:province":"Valais",
    "wof:name":"Vincente Correa Carrosserie-garage Ok",
    "wof:placetype":"venue"
},
  "geometry": {"coordinates":[6.100969,46.20533],"type":"Point"}
}