{
  "type": "Feature",
  "properties": {
    "addr:full":"Sch\u00e4dr\u00fctihalde 3 Luzern Luzern 6006",
    "addr:housenumber":"3",
    "addr:postcode":"6006",
    "addr:street":"Schaedruetihalde",
    "iso:country":"CH",
    "sg:address":"Sch\u00e4dr\u00fctihalde 3",
    "sg:city":"Luzern",
    "sg:orig_category":"Allgemeiner Hoch U Tiefbau",
    "sg:phone":"+41 41 210 31 38",
    "sg:postcode":"6006",
    "sg:province":"Luzern",
    "wof:name":"K\u00e4ppeli Gebr\u00fcder Ag",
    "wof:placetype":"venue"
},
  "geometry": {"coordinates":[8.344822,47.057495],"type":"Point"}
}