{
  "type": "Feature",
  "properties": {
    "iso:country":"CH",
    "sg:address":"Gewerbestrasse 11",
    "sg:city":"Cham",
    "sg:orig_category":"Herstellung von Elektromotoren, Generatoren U Transformatoren",
    "sg:phone":"+41 56 442 16 47",
    "sg:postcode":"6330",
    "sg:province":"Zug",
    "wof:name":"Simmen Energie",
    "wof:placetype":"venue"
},
  "geometry": {"coordinates":[8.2127361298,47.487537384],"type":"Point"}
}