{
  "type": "Feature",
  "properties": {
    "iso:country":"CH",
    "sg:address":"Spl\u00fcgenstrasse 6",
    "sg:city":"Z\u00fcrich",
    "sg:orig_category":"Unclassifiable Establishments",
    "sg:postcode":"8002",
    "sg:province":"Z\u00fcrich",
    "wof:name":"Mirrabella Ag",
    "wof:placetype":"venue"
},
  "geometry": {"coordinates":[8.5339794159,47.3645057678],"type":"Point"}
}