{
  "type": "Feature",
  "properties": {
    "iso:country":"CH",
    "sg:address":"Route D'ecublens 28",
    "sg:city":"Echandens",
    "sg:orig_category":"Instandhaltung U Reparatur von Automobilen",
    "sg:phone":"+41 21 701 54 50",
    "sg:postcode":"1026",
    "sg:province":"Vaud",
    "wof:name":"Monteleone Giuseppe",
    "wof:placetype":"venue"
},
  "geometry": {"coordinates":[6.5371398926,46.5320205688],"type":"Point"}
}