{
  "type": "Feature",
  "properties": {
    "iso:country":"CH",
    "sg:address":"Verger De Meruz 4",
    "sg:city":"Corsier-sur-vevey",
    "sg:orig_category":"Detailhandel mit Metallwaren, Anstrichmitteln, Glaswaren, Bau U Heimwerkerbedarf",
    "sg:phone":"+41 21 921 70 77",
    "sg:postcode":"1804",
    "sg:province":"Vaud",
    "wof:name":"Micro-finish Henn\u00e9 & Fils Sa Traitement De Surface",
    "wof:placetype":"venue"
},
  "geometry": {"coordinates":[6.8399682045,46.4696388245],"type":"Point"}
}