{
  "type": "Feature",
  "properties": {
    "iso:country":"CH",
    "sg:address":"Hindervorm\u00fcli",
    "sg:city":"Sch\u00fcpfheim",
    "sg:orig_category":"Herstellung von sonstigen landwirtschaftlichen Maschinen Mechanische Werkst\u00e4tten",
    "sg:phone":"+41 62 891 30 64",
    "sg:postcode":"6170",
    "sg:province":"Luzern",
    "wof:name":"Fredy Amweg Reparaturwerkst\u00e4tte",
    "wof:placetype":"venue"
},
  "geometry": {"coordinates":[8.200958252,47.3689651489],"type":"Point"}
}