{
  "type": "Feature",
  "properties": {
    "iso:country":"CH",
    "sg:address":"Rankstrasse 5",
    "sg:city":"Ebikon",
    "sg:orig_category":"Architektur U Ingenieurb\u00fcros",
    "sg:phone":"+41 32 422 52 89",
    "sg:postcode":"6030",
    "sg:province":"Luzern",
    "wof:name":"Stampbach G\u00e9rard Sa",
    "wof:placetype":"venue"
},
  "geometry": {"coordinates":[7.356116,47.369057],"type":"Point"}
}