{
  "type": "Feature",
  "properties": {
    "addr:full":"Centro Commerciale 6594 Contone. Postfach Contone Ticino 6594",
    "addr:housenumber":"6594",
    "addr:postcode":"6594",
    "addr:street":"Contone. Postfach;Ticino",
    "iso:country":"CH",
    "sg:address":"Centro Commerciale 6594 Contone. Postfach",
    "sg:city":"Contone",
    "sg:orig_category":"Alarm- and Sicherheitsanlagen Grosshandel Herstellung von sonstigen elektrischen Ausr\u00fcstungen",
    "sg:phone":"+41 91 840 14 50",
    "sg:postcode":"6594",
    "sg:province":"Ticino",
    "wof:name":"Az Sicurezza Sagl Sistemi Di Sicurezza; Importazione, Vendita E Assistenza",
    "wof:placetype":"venue"
},
  "geometry": {"coordinates":[8.926075,46.148525],"type":"Point"}
}