{
  "type": "Feature",
  "properties": {
    "iso:country":"CH",
    "sg:address":"Via Canonica",
    "sg:city":"Tesserete",
    "sg:orig_category":"Bestattungswesen",
    "sg:phone":"+41 91 924 92 00",
    "sg:postcode":"6950",
    "sg:province":"Ticino",
    "wof:name":"Michele Biancardi Sa Onoranze Funebri",
    "wof:placetype":"venue"
},
  "geometry": {"coordinates":[8.966892,46.067051],"type":"Point"}
}