{
  "type": "Feature",
  "properties": {
    "addr:full":"Voa Sporz 19a Lenzerheide/lai Graubunden 7078",
    "addr:housenumber":"19a",
    "addr:postcode":"7078",
    "addr:street":"Sporz",
    "iso:country":"CH",
    "sg:address":"Voa Sporz 19a",
    "sg:city":"Lenzerheide/lai",
    "sg:orig_category":"Architektur U Ingenieurb\u00fcros",
    "sg:phone":"+41 77813495",
    "sg:postcode":"7078",
    "sg:province":"Graubunden",
    "wof:name":"Quintus Ag",
    "wof:placetype":"venue"
},
  "geometry": {"coordinates":[9.553463,46.728096],"type":"Point"}
}