{
  "type": "Feature",
  "properties": {
    "iso:country":"CH",
    "sg:address":"Chemin Du Tessin 26",
    "sg:city":"Mont-sur-lausanne",
    "sg:orig_category":"Sportvereine Ski",
    "sg:phone":"+41 79 606 44 73",
    "sg:postcode":"1052",
    "sg:province":"Vaud",
    "wof:name":"Ski Chalet-\u00e0-gobet L.ecureuils",
    "wof:placetype":"venue"
},
  "geometry": {"coordinates":[6.62789011,46.5581130981],"type":"Point"}
}