{
  "type": "Feature",
  "properties": {
    "iso:country":"CH",
    "sg:address":"Cassarde Rue De La 10",
    "sg:city":"Neuch\u00e2tel",
    "sg:orig_category":"Detailhandel mit B\u00fcchern, Zeitungen, Schreib U Papeteriewaren",
    "sg:postcode":"2000",
    "sg:province":"Neuch\u00e2tel",
    "wof:name":"Sanchez Alfonso",
    "wof:placetype":"venue"
},
  "geometry": {"coordinates":[6.931085,46.990334],"type":"Point"}
}