{
  "type": "Feature",
  "properties": {
    "iso:country":"CH",
    "sg:address":"Bahnhofstrasse 37",
    "sg:city":"Z\u00fcrich",
    "sg:orig_category":"Vermietung U Verpachtung von eigenen Immobilien",
    "sg:postcode":"8001",
    "sg:province":"Z\u00fcrich",
    "wof:name":"Fless Medizintechnik Ag",
    "wof:placetype":"venue"
},
  "geometry": {"coordinates":[8.5385026932,47.3713111877],"type":"Point"}
}