{
  "type": "Feature",
  "properties": {
    "iso:country":"CH",
    "sg:address":"Ottenr\u00fcti",
    "sg:city":"Rothenburg",
    "sg:orig_category":"Sportvereine Schwingen",
    "sg:phone":"+41 41 280 96 63",
    "sg:postcode":"6023",
    "sg:province":"Luzern",
    "wof:name":"Schwingclub Rothenburg",
    "wof:placetype":"venue"
},
  "geometry": {"coordinates":[8.291217804,47.1085624695],"type":"Point"}
}