{
  "type": "Feature",
  "properties": {
    "iso:country":"CH",
    "sg:address":"Avenue De Cour 16",
    "sg:city":"Lausanne",
    "sg:orig_category":"Kinderkrippen U horte",
    "sg:phone":"+41 21 613 44 00",
    "sg:postcode":"1007",
    "sg:province":"Vaud",
    "wof:name":"Cr\u00e8che Municipale La Chenille",
    "wof:placetype":"venue"
},
  "geometry": {"coordinates":[6.622276783,46.5130844116],"type":"Point"}
}