{
  "type": "Feature",
  "properties": {
    "iso:country":"CH",
    "sg:address":"Via Merlina 11",
    "sg:city":"Viganello",
    "sg:orig_category":"Erbringung von Dienstleistungen f\u00fcr Unternehmen Sonstige k\u00fcnstlerische U schriftstellerische T\u00e4tigke",
    "sg:phone":"+41 91 971 05 77",
    "sg:postcode":"6962",
    "sg:province":"Ticino",
    "wof:name":"Il Modello Di Ivan Kunz Sagl",
    "wof:placetype":"venue"
},
  "geometry": {"coordinates":[8.9628648758,46.0133171082],"type":"Point"}
}