{
  "type": "Feature",
  "properties": {
    "iso:country":"CH",
    "sg:address":"Schwarzwaldallee 215 4058 Basel. Postfach",
    "sg:city":"Basel",
    "sg:orig_category":"Pensionskassen",
    "sg:phone":"+41 71 383 13 66",
    "sg:postcode":"4058",
    "sg:province":"Basel-Stadt",
    "wof:name":"S\u00e4ntis Kadervorsorge",
    "wof:placetype":"venue"
},
  "geometry": {"coordinates":[9.2514562607,47.4134788513],"type":"Point"}
}