{
  "type": "Feature",
  "properties": {
    "iso:country":"CH",
    "sg:address":"Lion-d'or Rue Du 5-7 1003 Lausanne. Postfach",
    "sg:city":"Lausanne",
    "sg:orig_category":"Vermietung U Verpachtung von eigenen Immobilien",
    "sg:postcode":"1003",
    "sg:province":"Vaud",
    "wof:name":"Valerio Sa",
    "wof:placetype":"venue"
},
  "geometry": {"coordinates":[9.8393983841,46.4979629517],"type":"Point"}
}