{
  "type": "Feature",
  "properties": {
    "iso:country":"CH",
    "sg:address":"1337 Vallorbe Case Postale 135",
    "sg:city":"Vallorbe",
    "sg:orig_category":"Sportvereine Ballsport Tennis",
    "sg:phone":"+41 24 441 71 98",
    "sg:postcode":"1337",
    "sg:province":"Vaud",
    "wof:name":"Tennis-club Vallorbe",
    "wof:placetype":"venue"
},
  "geometry": {"coordinates":[6.3790950775,46.7119598389],"type":"Point"}
}