{
  "type": "Feature",
  "properties": {
    "iso:country":"CH",
    "sg:address":"Hohlstrasse 100",
    "sg:city":"Z\u00fcrich",
    "sg:classifiers":[
        {
            "category":"Autos & Motor Vehicles",
            "subcategory":"Auto Supplies",
            "type":"Retail Goods"
        }
    ],
    "sg:phone":"+41 56 297 10 20",
    "sg:postcode":"8004",
    "sg:province":"Z\u00fcrich",
    "sg:tags":[
        "automobile",
        "accessory"
    ],
    "wof:name":"B\u00e4chli Automobile Ag",
    "wof:placetype":"venue"
},
  "geometry": {"coordinates":[8.243054,47.521675],"type":"Point"}
}