{
  "type": "Feature",
  "properties": {
    "iso:country":"CH",
    "sg:address":"Albisriederstrasse 80 8003 Z\u00fcrich. Postfach",
    "sg:city":"Z\u00fcrich",
    "sg:orig_category":"Vermittlung von Immobilien Verwaltung von Immobilien",
    "sg:phone":"+41 14921400",
    "sg:postcode":"8040",
    "sg:province":"Z\u00fcrich",
    "wof:name":"Schaufelberger Immobilien Ag",
    "wof:placetype":"venue"
},
  "geometry": {"coordinates":[8.5046644211,47.3776931763],"type":"Point"}
}