{
  "type": "Feature",
  "properties": {
    "iso:country":"CH",
    "sg:address":"Rue Du Pays-d'enhaut 21",
    "sg:city":"Bulle",
    "sg:orig_category":"Alters U Pflegeheime Pensionskassen",
    "sg:phone":"+41 26 912 53 83",
    "sg:postcode":"1630",
    "sg:province":"Fribourg",
    "wof:name":"Fondation Angel Monf\u00e9rini",
    "wof:placetype":"venue"
},
  "geometry": {"coordinates":[-75.62336,37.827072],"type":"Point"}
}