{
  "type": "Feature",
  "properties": {
    "iso:country":"CH",
    "sg:address":"R\u00f6hrliberg 48",
    "sg:city":"Cham",
    "sg:orig_category":"Bauschreinerei Innenausbau",
    "sg:phone":"+41 41 781 02 69",
    "sg:postcode":"6330",
    "sg:province":"Zug",
    "wof:name":"Reto Bollier Schreinerei & Innenausbau",
    "wof:placetype":"venue"
},
  "geometry": {"coordinates":[8.453255,47.184757],"type":"Point"}
}