{
  "type": "Feature",
  "properties": {
    "iso:country":"CH",
    "sg:address":"Marktgasse 14",
    "sg:city":"Interlaken",
    "sg:orig_category":"Handel mit Automobilen",
    "sg:phone":"+41 33 823 53 53",
    "sg:postcode":"3800",
    "sg:province":"Bern",
    "wof:name":"Nci New Car Import Gmbh",
    "wof:placetype":"venue"
},
  "geometry": {"coordinates":[7.8534431458,46.6856918335],"type":"Point"}
}