{
  "type": "Feature",
  "properties": {
    "iso:country":"CH",
    "sg:city":"Schwyz",
    "sg:orig_category":"Freizeit, Spiel U Spa\u00df",
    "sg:postcode":"6430",
    "sg:province":"Schwyz",
    "wof:name":"Ferienpass Schwyz",
    "wof:placetype":"venue"
},
  "geometry": {"coordinates":[8.652429,47.021667],"type":"Point"}
}