{
  "type": "Feature",
  "properties": {
    "iso:country":"CH",
    "sg:address":"G\u00e4belbachstrasse 37",
    "sg:city":"Bern",
    "sg:orig_category":"Architektur U Ingenieurb\u00fcros",
    "sg:phone":"+41 31 982 00 82",
    "sg:postcode":"3027",
    "sg:province":"Bern",
    "wof:name":"Zahnd Beratende Ingenieure Ag",
    "wof:placetype":"venue"
},
  "geometry": {"coordinates":[7.376483,46.94899],"type":"Point"}
}