{
  "type": "Feature",
  "properties": {
    "iso:country":"CH",
    "sg:address":"Winterthurerstrasse 4",
    "sg:city":"Sirnach",
    "sg:orig_category":"Sonstiges Versicherungsgewerbe",
    "sg:phone":"+41 41 874 19 19",
    "sg:postcode":"8370",
    "sg:province":"Thurgau",
    "wof:name":"Schweizerische Mobiliar Versicherungsgesellschaft Generalagentur Altdorf Zgraggen Richard",
    "wof:placetype":"venue"
},
  "geometry": {"coordinates":[8.6451444626,46.8806152344],"type":"Point"}
}