{
  "type": "Feature",
  "properties": {
    "iso:country":"CH",
    "sg:address":"F\u00e4rberstrasse 7",
    "sg:city":"Basel",
    "sg:orig_category":"Sportvereine Turnen",
    "sg:postcode":"4057",
    "sg:province":"Basel-Stadt",
    "wof:name":"Turnverein Kleinh\u00fcningen Basel",
    "wof:placetype":"venue"
},
  "geometry": {"coordinates":[7.5924482346,47.5765800476],"type":"Point"}
}