{
  "type": "Feature",
  "properties": {
    "iso:country":"CH",
    "sg:address":"In Der Breiti 5",
    "sg:city":"Urdorf",
    "sg:orig_category":"Pensionskassen",
    "sg:phone":"+41 79 402 13 22",
    "sg:postcode":"8902",
    "sg:province":"Z\u00fcrich",
    "wof:name":"Personalvorsorgestiftung Der Firma Q-out Ag, Urdorf",
    "wof:placetype":"venue"
},
  "geometry": {"coordinates":[8.4280929565,47.3866271973],"type":"Point"}
}