{
  "type": "Feature",
  "properties": {
    "iso:country":"CH",
    "sg:address":"Hauptstrasse 54",
    "sg:city":"Sch\u00f6nengrund",
    "sg:orig_category":"Nationale Postdienste",
    "sg:phone":"+41 71 361 11 54",
    "sg:postcode":"9105",
    "sg:province":"Appenzell Ausserrhoden",
    "wof:name":"Die Schweizerische Post",
    "wof:placetype":"venue"
},
  "geometry": {"coordinates":[9.2275695801,47.3296318054],"type":"Point"}
}