{
  "type": "Feature",
  "properties": {
    "iso:country":"CH",
    "sg:address":"Damiano Via San 8",
    "sg:city":"Mendrisio",
    "sg:orig_category":"RESTAURANTS: TEA-ROOMS",
    "sg:phone":"+41 71 385 11 46",
    "sg:postcode":"6850",
    "sg:province":"Ticino",
    "wof:name":"Fribo Gossau Ag",
    "wof:placetype":"venue"
},
  "geometry": {"coordinates":[9.2489900589,47.4141426086],"type":"Point"}
}