{
  "type": "Feature",
  "properties": {
    "iso:country":"CH",
    "sg:address":"Route Des Avouillons 4",
    "sg:city":"Gland",
    "sg:orig_category":"Sonstiger Fachdetailhandel mit Nahrungsmitteln, Getr\u00e4nken U Tabak in Verkaufsr\u00e4umen",
    "sg:phone":"+41 22 364 04 20",
    "sg:postcode":"1196",
    "sg:province":"Vaud",
    "wof:name":"Baffo Traiteur S\u00e0rl",
    "wof:placetype":"venue"
},
  "geometry": {"coordinates":[6.2690029144,46.4162101746],"type":"Point"}
}