{
  "type": "Feature",
  "properties": {
    "iso:country":"CH",
    "sg:address":"Reichenmattestrasse 13 3714 Frutigen. Postfach 43",
    "sg:city":"Frutigen",
    "sg:orig_category":"Wirtschaftspr\u00fcfung, Steuerberatung U Treuhand",
    "sg:phone":"+41 79 222 59 24",
    "sg:postcode":"3714",
    "sg:province":"Bern",
    "wof:name":"Landmesser Treuhand Ag - Latag Frutigen",
    "wof:placetype":"venue"
},
  "geometry": {"coordinates":[7.6373581886,46.5850028992],"type":"Point"}
}