{
  "type": "Feature",
  "properties": {
    "iso:country":"CH",
    "sg:address":"Kannenfeldstrasse 10",
    "sg:city":"Basel",
    "sg:orig_category":"Grosshandel mit Obst U Gem\u00fcse",
    "sg:phone":"+41 61 321 06 67",
    "sg:postcode":"4056",
    "sg:province":"Basel-Stadt",
    "wof:name":"Azte-ku-mex Ag",
    "wof:placetype":"venue"
},
  "geometry": {"coordinates":[7.5740699768,47.5624542236],"type":"Point"}
}