{
  "type": "Feature",
  "properties": {
    "iso:country":"CH",
    "sg:address":"Obertor 19",
    "sg:city":"Winterthur",
    "sg:orig_category":"Detailhandel mit Musikinstrumenten Fachdetailhandel in Verkaufsr\u00e4umen",
    "sg:phone":"+41 52 213 30 50",
    "sg:postcode":"8400",
    "sg:province":"Z\u00fcrich",
    "wof:name":"Musik Baur Ag Das Haus Der Tasteninstrumente",
    "wof:placetype":"venue"
},
  "geometry": {"coordinates":[8.7321691513,47.4998893738],"type":"Point"}
}