{
  "type": "Feature",
  "properties": {
    "iso:country":"CH",
    "sg:address":"M\u00fchlegasse 15 8001 Z\u00fcrich. Postfach",
    "sg:city":"Z\u00fcrich",
    "sg:orig_category":"Betrieb U technische Hilfsdienste des Kultur U Unterhaltungswesens Vermietung von Gebrauchsg\u00fctern",
    "sg:phone":"+41 62 875 32 32",
    "sg:postcode":"8025",
    "wof:name":"Stage-conzept Showtechnik Licht, Laser, Ton, Video, Feuerwerk",
    "wof:placetype":"venue"
},
  "geometry": {"coordinates":[8.1031808853,47.5422592163],"type":"Point"}
}