{
  "type": "Feature",
  "properties": {
    "iso:country":"CH",
    "sg:address":"Bahnhofstrasse 8 7304 Maienfeld. Postfach",
    "sg:city":"Kloten",
    "sg:orig_category":"Werbung",
    "sg:postcode":"8302",
    "sg:province":"Z\u00fcrich",
    "wof:name":"Victor Zindel & Partner Gmbh",
    "wof:placetype":"venue"
},
  "geometry": {"coordinates":[9.5292730331,47.0048065186],"type":"Point"}
}