{
  "type": "Feature",
  "properties": {
    "iso:country":"CH",
    "sg:address":"Amriswilerstrasse 18",
    "sg:city":"Weinfelden",
    "sg:orig_category":"Detailhandel mit Schuhen U Lederwaren Reparatur von Schuhen U Lederwaren",
    "sg:phone":"+41 71 622 45 93",
    "sg:postcode":"8570",
    "sg:province":"Thurgau",
    "wof:name":"Antonio Mente Schuhmacherei",
    "wof:placetype":"venue"
},
  "geometry": {"coordinates":[9.1122283936,47.5676841736],"type":"Point"}
}