{
  "type": "Feature",
  "properties": {
    "addr:full":"Winkelriedstrasse 25 6003 Luzern. Postfach Luzern Luzern 6002",
    "addr:housenumber":"25",
    "addr:postcode":"6003;postfach;6002",
    "addr:street":"Winkelriedstrasse",
    "iso:country":"CH",
    "sg:address":"Winkelriedstrasse 25 6003 Luzern. Postfach",
    "sg:city":"Luzern",
    "sg:orig_category":"Detailhandel mit Brillen U anderen Sehhilfen Fachdetailhandel in Verkaufsr\u00e4umen",
    "sg:phone":"+41 41 210 44 13",
    "sg:postcode":"6002",
    "sg:province":"Luzern",
    "wof:name":"B\u00fchlmann Optik Ag",
    "wof:placetype":"venue"
},
  "geometry": {"coordinates":[8.306119,47.048023],"type":"Point"}
}