{
  "type": "Feature",
  "properties": {
    "iso:country":"CH",
    "sg:address":"Ligni\u00e8res Route De 1 2072 St-blaise Case Postale 258",
    "sg:city":"St-blaise",
    "sg:orig_category":"Grosshandel mit Getr\u00e4nken",
    "sg:phone":"+41 32 753 29 29",
    "sg:postcode":"2072",
    "sg:province":"Neuch\u00e2tel",
    "wof:name":"Caveau Des Deux Tilleuls Sa",
    "wof:placetype":"venue"
},
  "geometry": {"coordinates":[6.988743782,47.0171203613],"type":"Point"}
}