{
  "type": "Feature",
  "properties": {
    "iso:country":"CH",
    "sg:address":"Bahnhofstrasse 13",
    "sg:city":"Langenthal",
    "sg:orig_category":"Non-Classified Establishments",
    "sg:postcode":"4900",
    "sg:province":"Bern",
    "wof:name":"Meex Versicherungsbroker Ag",
    "wof:placetype":"venue"
},
  "geometry": {"coordinates":[7.7873468399,47.2131958008],"type":"Point"}
}