{
  "type": "Feature",
  "properties": {
    "addr:full":"Ifang Fl\u00fceli-ranft Obwalden 6073",
    "addr:postcode":"6073",
    "iso:country":"CH",
    "sg:address":"Ifang",
    "sg:city":"Fl\u00fceli-ranft",
    "sg:orig_category":"Bauschreinerei",
    "sg:phone":"+41 41 660 31 24",
    "sg:postcode":"6073",
    "sg:province":"Obwalden",
    "wof:name":"Alfred Rohrer Schreinerei",
    "wof:placetype":"venue"
},
  "geometry": {"coordinates":[8.228328,46.860973],"type":"Point"}
}