{
  "type": "Feature",
  "properties": {
    "iso:country":"CH",
    "sg:address":"Badmatte 2",
    "sg:city":"Oberburg",
    "sg:orig_category":"Vorschulen, Kinderg\u00e4rten",
    "sg:phone":"+41 34 422 14 60",
    "sg:postcode":"3414",
    "sg:province":"Bern",
    "wof:name":"Kindergarten Badmatte",
    "wof:placetype":"venue"
},
  "geometry": {"coordinates":[7.6263427734,47.0345230103],"type":"Point"}
}