{
  "type": "Feature",
  "properties": {
    "iso:country":"CH",
    "sg:address":"Plattenstrasse 94 8706 Meilen. Postfach 227",
    "sg:city":"Meilen",
    "sg:orig_category":"Non-Classified Establishments",
    "sg:phone":"+41 19221500",
    "sg:postcode":"8706",
    "sg:province":"Z\u00fcrich",
    "wof:name":"Toller & Loher Ag",
    "wof:placetype":"venue"
},
  "geometry": {"coordinates":[8.6386260986,47.2750015259],"type":"Point"}
}