{
  "type": "Feature",
  "properties": {
    "iso:country":"CH",
    "sg:address":"Spitalstrasse 6",
    "sg:city":"Luzern",
    "sg:orig_category":"Allgemeinbildende weiterf\u00fchrende Schulen",
    "sg:phone":"+41 41 240 91 66",
    "sg:postcode":"6004",
    "sg:province":"Luzern",
    "wof:name":"D M Swiss Consulting Basso",
    "wof:placetype":"venue"
},
  "geometry": {"coordinates":[8.302354,47.059799],"type":"Point"}
}