{
  "type": "Feature",
  "properties": {
    "iso:country":"CH",
    "sg:address":"Birmensdorferstrasse 55",
    "sg:city":"Z\u00fcrich",
    "sg:orig_category":"Chiropraktik",
    "sg:phone":"+41 12424252",
    "sg:postcode":"8004",
    "sg:province":"Z\u00fcrich",
    "wof:name":"Dres Siegenthaler & Vomacka Chiropraktoren",
    "wof:placetype":"venue"
},
  "geometry": {"coordinates":[8.525045,47.371445],"type":"Point"}
}