{
  "type": "Feature",
  "properties": {
    "addr:full":"Birmensdorferstrasse 55 Z\u00fcrich Z\u00fcrich 8004",
    "addr:housenumber":"55",
    "addr:postcode":"8004",
    "addr:street":"Birmensdorferstrasse",
    "iso:country":"CH",
    "sg:address":"Birmensdorferstrasse 55",
    "sg:city":"Z\u00fcrich",
    "sg:orig_category":"Chiropraktik",
    "sg:phone":"+41 12424252",
    "sg:postcode":"8004",
    "sg:province":"Z\u00fcrich",
    "wof:name":"Dres Siegenthaler & Vomacka Chiropraktoren",
    "wof:placetype":"venue"
},
  "geometry": {"coordinates":[8.525045,47.371445],"type":"Point"}
}