{
  "type": "Feature",
  "properties": {
    "addr:full":"Chamerstrasse 18 Zug Zug 6300",
    "addr:housenumber":"18",
    "addr:postcode":"6300",
    "addr:street":"Chamerstrasse;Zug",
    "iso:country":"CH",
    "sg:address":"Chamerstrasse 18",
    "sg:city":"Zug",
    "sg:orig_category":"Architektur U Ingenieurb\u00fcros",
    "sg:phone":"+41 19103694",
    "sg:postcode":"6300",
    "sg:province":"Zug",
    "wof:name":"Nooria Ag Ingenieurb\u00fcro",
    "wof:placetype":"venue"
},
  "geometry": {"coordinates":[8.596949,47.324474],"type":"Point"}
}