{
  "type": "Feature",
  "properties": {
    "iso:country":"CH",
    "sg:address":"Oberwilerstrasse 2 4102 Binningen. Postfach",
    "sg:city":"Binningen",
    "sg:orig_category":"Interessenvertretungen",
    "sg:postcode":"4102",
    "sg:province":"Basel-Landschaft",
    "wof:name":"Marius Und Louise Hess-betton-wohlfahrtsstiftung",
    "wof:placetype":"venue"
},
  "geometry": {"coordinates":[7.5712928772,47.5376434326],"type":"Point"}
}