{
  "type": "Feature",
  "properties": {
    "iso:country":"CH",
    "sg:address":"Dorfstrasse 16",
    "sg:city":"Richterswil",
    "sg:orig_category":"Werbegrafikateliers",
    "sg:phone":"+41 17846036",
    "sg:postcode":"8805",
    "sg:province":"Z\u00fcrich",
    "wof:name":"Maggie Zimmermann Grafik",
    "wof:placetype":"venue"
},
  "geometry": {"coordinates":[8.7064037323,47.2064552307],"type":"Point"}
}