{
  "type": "Feature",
  "properties": {
    "iso:country":"CH",
    "sg:address":"Lichtstrasse 35 4056 Basel. Postfach",
    "sg:city":"Basel",
    "sg:orig_category":"Unternehmensberatung",
    "sg:postcode":"4051",
    "sg:province":"Basel-Stadt",
    "wof:name":"Novavia Ag Unterst\u00fctzung Von Gewerbe- U. Handelsbetrieben Durch Dienstleistungen In Den Bereichen Rechnungswesen, Management U. Finanzierung Usw",
    "wof:placetype":"venue"
},
  "geometry": {"coordinates":[8.8536300659,47.1859970093],"type":"Point"}
}