{
  "type": "Feature",
  "properties": {
    "iso:country":"CH",
    "sg:address":"Chemin Mo\u00efse-duboule 43",
    "sg:city":"Gen\u00e8ve",
    "sg:orig_category":"Gartenbau Landschaftsplanungsb\u00fcros U Gartenarchitekturb\u00fcros",
    "sg:phone":"+41 22 798 91 70",
    "sg:postcode":"1209",
    "sg:province":"Gen\u00e8ve",
    "wof:name":"Jaromir & Helena Stvan Architecte-paysagiste",
    "wof:placetype":"venue"
},
  "geometry": {"coordinates":[6.1245250702,46.2252349854],"type":"Point"}
}