{
  "type": "Feature",
  "properties": {
    "iso:country":"CH",
    "sg:address":"Kirchgasse 20",
    "sg:city":"Diessenhofen",
    "sg:orig_category":"Detailhandel mit Brot, Back U S\u00fcsswaren",
    "sg:phone":"+41 52 657 12 10",
    "sg:postcode":"8253",
    "sg:province":"Thurgau",
    "wof:name":"B\u00e4ckermeisterver.diessenhofen & Umgebung Herrn Rolf Kern",
    "wof:placetype":"venue"
},
  "geometry": {"coordinates":[8.749234,47.689705],"type":"Point"}
}