{
  "type": "Feature",
  "properties": {
    "iso:country":"CH",
    "sg:address":"Welletenstrasse 376",
    "sg:city":"Biberstein",
    "sg:orig_category":"Bau U Wohngenossenschaften",
    "sg:phone":"+41 62 827 32 31",
    "sg:postcode":"5023",
    "sg:province":"Aargau",
    "wof:name":"Wohnbaugen.biberstein",
    "wof:placetype":"venue"
},
  "geometry": {"coordinates":[8.08429,47.41737],"type":"Point"}
}