{
  "type": "Feature",
  "properties": {
    "iso:country":"CH",
    "sg:address":"Arbonerstrasse 51 9302 Kronb\u00fchl. Postfach 147",
    "sg:city":"Kronb\u00fchl",
    "sg:classifiers":[
        {
            "category":"Restaurant",
            "type":"Food & Drink"
        }
    ],
    "sg:phone":"+41 71 298 17 27",
    "sg:postcode":"9302",
    "wof:name":"Restaurant Sonnental",
    "wof:placetype":"venue"
},
  "geometry": {"coordinates":[9.3943624496,47.4626731873],"type":"Point"}
}