{
  "type": "Feature",
  "properties": {
    "iso:country":"CH",
    "sg:address":"Nauenstrasse 24c",
    "sg:city":"Tann",
    "sg:orig_category":"Organisationen des Gesundheitswesen",
    "sg:phone":"+41 55 240 81 56",
    "sg:postcode":"8632",
    "sg:province":"Z\u00fcrich",
    "wof:name":"Samariterverein",
    "wof:placetype":"venue"
},
  "geometry": {"coordinates":[8.8544797897,47.2718391418],"type":"Point"}
}