{
  "type": "Feature",
  "properties": {
    "iso:country":"CH",
    "sg:address":"Wilhelmstrasse 2 8005 Z\u00fcrich. Postfach 971",
    "sg:city":"Z\u00fcrich",
    "sg:orig_category":"Grosshandel mit B\u00fcromaschinen Grosshandel mit Datenverarbeitungsger\u00e4ten",
    "sg:phone":"+41 12722856",
    "sg:postcode":"8045",
    "sg:province":"Z\u00fcrich",
    "wof:name":"Dd - Edv-dienstleistungen Ag Edv-dienstleistungen, Software Usw; Beratung",
    "wof:placetype":"venue"
},
  "geometry": {"coordinates":[8.5232172012,47.3901557922],"type":"Point"}
}