{
  "type": "Feature",
  "properties": {
    "iso:country":"CH",
    "sg:address":"Kuniberg 14 3954 Leukerbad. Postfach",
    "sg:city":"Leukerbad",
    "sg:orig_category":"Kauf U Verkauf von Immobilien auf eigene Rechnung",
    "sg:postcode":"3954",
    "sg:province":"Valais",
    "wof:name":"B\u00f6hlen G. + F. Liegenschaftsverwaltung",
    "wof:placetype":"venue"
},
  "geometry": {"coordinates":[7.6280388832,46.3813476562],"type":"Point"}
}