{
  "type": "Feature",
  "properties": {
    "iso:country":"CH",
    "sg:address":"Talstrasse 43",
    "sg:city":"Etzgen",
    "sg:orig_category":"Unclassifiable Establishments",
    "sg:postcode":"5275",
    "sg:province":"Aargau",
    "wof:name":"Spearhead S\u00e0rl",
    "wof:placetype":"venue"
},
  "geometry": {"coordinates":[6.9953799248,46.2966117859],"type":"Point"}
}