{
  "type": "Feature",
  "properties": {
    "iso:country":"CH",
    "sg:address":"Zone Industrielle",
    "sg:city":"V\u00e9troz",
    "sg:classifiers":[
        {
            "category":"Manufacturing",
            "subcategory":"Printing",
            "type":"Manufacturing & Wholesale Goods"
        }
    ],
    "sg:phone":"+41 27 346 10 23",
    "sg:postcode":"1963",
    "sg:province":"Valais",
    "sg:tags":[
        "ink",
        "offset"
    ],
    "wof:name":"Imp\u00e9rial Produits",
    "wof:placetype":"venue"
},
  "geometry": {"coordinates":[7.2825698853,46.2257461548],"type":"Point"}
}