{
  "type": "Feature",
  "properties": {
    "iso:country":"CH",
    "sg:address":"H\u00fcnibachstrasse 106 3626 H\u00fcnibach. Postfach",
    "sg:city":"H\u00fcnibach",
    "sg:orig_category":"Wirtschaftspr\u00fcfung, Steuerberatung U Treuhand",
    "sg:postcode":"3626",
    "sg:province":"Bern",
    "wof:name":"Mhr Huber-roost Margrit Buchhaltungsb\u00fcro. Buchhaltungs- U. Sekretariatsarbeiten Usw.",
    "wof:placetype":"venue"
},
  "geometry": {"coordinates":[7.6502289772,46.7470855713],"type":"Point"}
}