{
  "type": "Feature",
  "properties": {
    "iso:country":"CH",
    "sg:address":"Zrydsbr\u00fccke 4",
    "sg:city":"Frutigen",
    "sg:orig_category":"Environment - machinery and equipment Goods handling - material and equipment Mechanical Engineering",
    "sg:phone":"+41 33 672 80 40",
    "sg:postcode":"3714",
    "sg:province":"Bern",
    "wof:name":"Trumag Aufbereitungstechnik Ag",
    "wof:placetype":"venue"
},
  "geometry": {"coordinates":[7.6440448761,46.588924408],"type":"Point"}
}