{
  "type": "Feature",
  "properties": {
    "iso:country":"CH",
    "sg:address":"5622",
    "sg:city":"Waltenschwil",
    "sg:orig_category":"Vereine Musik/Blasmusik",
    "sg:phone":"+41 56 611 08 21",
    "sg:postcode":"5622",
    "sg:province":"Aargau",
    "wof:name":"Musikgesellschaft",
    "wof:placetype":"venue"
},
  "geometry": {"coordinates":[8.2980098724,47.3340110779],"type":"Point"}
}