{
  "type": "Feature",
  "properties": {
    "iso:country":"CH",
    "sg:address":"Beitenwil",
    "sg:city":"Rubigen",
    "sg:orig_category":"Technische, physikalische U chemische Untersuchung",
    "sg:phone":"+41 31 839 08 93",
    "sg:postcode":"3113",
    "sg:province":"Bern",
    "wof:name":"Qualis Laboratorium F\u00fcr Qualit\u00e4tsuntersuchungen Von Lebens Und Heilmitteln Gmbh",
    "wof:placetype":"venue"
},
  "geometry": {"coordinates":[7.5584001541,46.9102592468],"type":"Point"}
}