{
  "type": "Feature",
  "properties": {
    "iso:country":"CH",
    "sg:address":"Kantonsstrasse 63 A 3930 Visp. Postfach",
    "sg:city":"Visp",
    "sg:orig_category":"Sonstige mit Sport verbundene T\u00e4tigkeiten",
    "sg:postcode":"3930",
    "sg:province":"Valais",
    "wof:name":"Ehc Visp Sport Ag Spielbetrieb Des Eishockeyclubs, Bes. Die Erste Mannschaft, Elitejunioren Etc.; Organisation, Durchf\u00fchrung, Leitung",
    "wof:placetype":"venue"
},
  "geometry": {"coordinates":[7.8966288567,46.2946090698],"type":"Point"}
}