{
  "type": "Feature",
  "properties": {
    "iso:country":"CH",
    "sg:address":"Route Robellaz",
    "sg:city":"Essertines-yverdon",
    "sg:orig_category":"Grosshandel mit B\u00fcromaschinen Grosshandel mit Datenverarbeitungsger\u00e4ten",
    "sg:phone":"+41 24 435 17 07",
    "sg:postcode":"1417",
    "sg:province":"Vaud",
    "wof:name":"Diffusoft Ordinateurs & Programmes",
    "wof:placetype":"venue"
},
  "geometry": {"coordinates":[6.6374840736,46.7136802673],"type":"Point"}
}