{
  "type": "Feature",
  "properties": {
    "iso:country":"CH",
    "sg:address":"Bernstrasse 29",
    "sg:city":"B\u00fctzberg",
    "sg:orig_category":"Nationale Postdienste",
    "sg:phone":"+41 62 963 11 85",
    "sg:postcode":"4922",
    "sg:province":"Bern",
    "wof:name":"Die Schweizerische Post",
    "wof:placetype":"venue"
},
  "geometry": {"coordinates":[7.7447690964,47.2148208618],"type":"Point"}
}