{
  "type": "Feature",
  "properties": {
    "iso:country":"CH",
    "sg:address":"Casa De Tann",
    "sg:city":"Maloja",
    "sg:orig_category":"Detailhandel mit Zeitungen U Zeitschriften Kioske",
    "sg:phone":"+41 81 322 13 22",
    "sg:postcode":"7516",
    "sg:province":"Graubunden",
    "wof:name":"Agnes Caseli Kiosk-shop Piz Alunblick",
    "wof:placetype":"venue"
},
  "geometry": {"coordinates":[9.5658102036,46.956035614],"type":"Point"}
}