{
  "type": "Feature",
  "properties": {
    "iso:country":"CH",
    "sg:address":"Gewerbestrasse 18",
    "sg:city":"Bern",
    "sg:orig_category":"Detailhandel mit Fleisch U Fleischwaren",
    "sg:phone":"+41 31 301 45 56",
    "sg:postcode":"3012",
    "sg:province":"Bern",
    "wof:name":"Max Junker",
    "wof:placetype":"venue"
},
  "geometry": {"coordinates":[7.4278960228,46.9542655945],"type":"Point"}
}