{
  "type": "Feature",
  "properties": {
    "iso:country":"CH",
    "sg:address":"1775",
    "sg:city":"Mannens",
    "sg:orig_category":"Schulpflegen",
    "sg:phone":"+41 26 660 82 65",
    "sg:postcode":"1775",
    "sg:province":"Fribourg",
    "wof:name":"Commission Scolaire De L'ecole Primaire",
    "wof:placetype":"venue"
},
  "geometry": {"coordinates":[6.9685797691,46.7935905457],"type":"Point"}
}