{
  "type": "Feature",
  "properties": {
    "iso:country":"CH",
    "sg:address":"3283",
    "sg:city":"Kallnach",
    "sg:classifiers":[
        {
            "category":"Education",
            "subcategory":"Vocational School",
            "type":"Public Place"
        }
    ],
    "sg:phone":"+41 32 392 64 78",
    "sg:postcode":"3283",
    "sg:province":"Bern",
    "sg:tags":[
        "koch-",
        "haushaltschulen"
    ],
    "wof:name":"Haushaltungsschule",
    "wof:placetype":"venue"
},
  "geometry": {"coordinates":[7.2354297638,47.019153595],"type":"Point"}
}