{
  "type": "Feature",
  "properties": {
    "iso:country":"CH",
    "sg:address":"Alte Simplonstrasse 22",
    "sg:city":"Brig",
    "sg:orig_category":"Detailhandel mit B\u00fcchern Detailhandel mit B\u00fcchern, Zeitungen, Schreib U Papeteriewaren",
    "sg:phone":"+41 71 622 65 20",
    "sg:postcode":"3900",
    "sg:province":"Valais",
    "wof:name":"Buchhandlung Akzente Ag",
    "wof:placetype":"venue"
},
  "geometry": {"coordinates":[9.138185,47.566669],"type":"Point"}
}