{
  "type": "Feature",
  "properties": {
    "iso:country":"CH",
    "sg:address":"Couteaux Les B2",
    "sg:city":"St-cergue",
    "sg:classifiers":[
        {
            "category":"Communications",
            "subcategory":"Radio Station",
            "type":"Services"
        }
    ],
    "sg:phone":"+41 22 360 24 90",
    "sg:postcode":"1264",
    "sg:province":"Vaud",
    "sg:tags":[
        "fernsehanstalten",
        "u"
    ],
    "wof:name":"B 2 Productions, Lydia Breen",
    "wof:placetype":"venue"
},
  "geometry": {"coordinates":[6.1575808525,46.4464187622],"type":"Point"}
}