{
  "type": "Feature",
  "properties": {
    "iso:country":"CH",
    "sg:address":"Klosbachstrasse 111",
    "sg:city":"Z\u00fcrich",
    "sg:classifiers":[
        {
            "category":"Manufacturing",
            "subcategory":"Tools & Machinery",
            "type":"Manufacturing & Wholesale Goods"
        }
    ],
    "sg:phone":"+41 12615911",
    "sg:postcode":"8030",
    "sg:tags":[
        "part",
        "turned",
        "cnc"
    ],
    "wof:name":"Intrec Ag",
    "wof:placetype":"venue"
},
  "geometry": {"coordinates":[8.562032,47.36871],"type":"Point"}
}