{
  "type": "Feature",
  "properties": {
    "iso:country":"CH",
    "sg:address":"Karl-neuhaus-strasse 40 2502 Biel/bienne Case Postale 162",
    "sg:city":"Biel/bienne",
    "sg:orig_category":"Advokaturb\u00fcros",
    "sg:phone":"+41 31 312 23 21",
    "sg:postcode":"2501",
    "sg:province":"Bern",
    "wof:name":"Ulrich Frehner Advokaturb\u00fcro",
    "wof:placetype":"venue"
},
  "geometry": {"coordinates":[7.562318,46.932652],"type":"Point"}
}