{
  "type": "Feature",
  "properties": {
    "iso:country":"CH",
    "sg:address":"Avenue De Lucens 30",
    "sg:city":"Moudon",
    "sg:classifiers":[
        {
            "category":"Organizations",
            "subcategory":"Labor Organization",
            "type":"Services"
        }
    ],
    "sg:phone":"+41 21 905 17 70",
    "sg:postcode":"1510",
    "sg:province":"Vaud",
    "sg:tags":[
        "work",
        "assembling",
        "assembly",
        "contract"
    ],
    "wof:name":"G.u. Montage S.\u00e0.r.l.",
    "wof:placetype":"venue"
},
  "geometry": {"coordinates":[6.806589,46.673252],"type":"Point"}
}