{
  "type": "Feature",
  "properties": {
    "iso:country":"CH",
    "sg:address":"Schlossackerstrasse 16",
    "sg:city":"Oberneunforn",
    "sg:orig_category":"Sonstige mit der Informatik verbundene T\u00e4tigkeiten",
    "sg:phone":"+41 17132425",
    "sg:postcode":"8526",
    "sg:province":"Thurgau",
    "wof:name":"Hotz Peter",
    "wof:placetype":"venue"
},
  "geometry": {"coordinates":[8.5390825272,47.286567688],"type":"Point"}
}