{
  "type": "Feature",
  "properties": {
    "iso:country":"CH",
    "sg:address":"Schmiedenstrasse 31",
    "sg:city":"Einsiedeln",
    "sg:orig_category":"RESTAURANTS: TEA-ROOMS",
    "sg:phone":"+41 55 412 48 12",
    "sg:postcode":"8840",
    "sg:province":"Schwyz",
    "wof:name":"Pizzeria & Bar Grottino 87",
    "wof:placetype":"venue"
},
  "geometry": {"coordinates":[8.7496957779,47.1280288696],"type":"Point"}
}