{
  "type": "Feature",
  "properties": {
    "iso:country":"CH",
    "sg:address":"Grenzacherstrasse 223",
    "sg:city":"Basel",
    "sg:orig_category":"RESTAURANTS: TEA-ROOMS",
    "sg:phone":"+41 61 681 53 15",
    "sg:postcode":"4058",
    "sg:province":"Basel-Stadt",
    "wof:name":"Mustafa Calik",
    "wof:placetype":"venue"
},
  "geometry": {"coordinates":[7.6113557816,47.5598602295],"type":"Point"}
}