{
  "type": "Feature",
  "properties": {
    "iso:country":"CH",
    "sg:address":"Schneckelerstrasse 18",
    "sg:city":"F\u00fcllinsdorf",
    "sg:orig_category":"Handel mit Motorr\u00e4dern, Teilen U Zubeh\u00f6r Instandhaltung U Reparatur von Automobilen Instandhaltung U",
    "sg:phone":"+41 55 643 19 55",
    "sg:postcode":"4414",
    "sg:province":"Basel-Landschaft",
    "wof:name":"Albert Wittenwiler",
    "wof:placetype":"venue"
},
  "geometry": {"coordinates":[9.0061674118,46.9284286499],"type":"Point"}
}