{
  "type": "Feature",
  "properties": {
    "iso:country":"CH",
    "sg:address":"Bahnhofstrasse 8",
    "sg:city":"Brig",
    "sg:orig_category":"Detailhandel mit Uhren U Schmuck Reparatur von Uhren U Schmuck",
    "sg:phone":"+41 27 923 12 20",
    "sg:postcode":"3900",
    "sg:province":"Valais",
    "wof:name":"Kurt Karlen Uhren & Bijouterie",
    "wof:placetype":"venue"
},
  "geometry": {"coordinates":[7.9879999161,46.3177223206],"type":"Point"}
}