{
  "type": "Feature",
  "properties": {
    "iso:country":"CH",
    "sg:address":"Guntibachstrasse 614",
    "sg:city":"Ossingen",
    "sg:orig_category":"Wohnheime",
    "sg:phone":"+41 52 305 28 50",
    "sg:postcode":"8475",
    "sg:province":"Z\u00fcrich",
    "wof:name":"Stiftung Langeneggerhaus F\u00fcr Behinderte, Ossingen",
    "wof:placetype":"venue"
},
  "geometry": {"coordinates":[8.7306060791,47.6122283936],"type":"Point"}
}