{
  "type": "Feature",
  "properties": {
    "iso:country":"CH",
    "sg:address":"Chemin Des Sorbiers 21",
    "sg:city":"Chardonne",
    "sg:orig_category":"Naturheil\u00e4rzte and Heilpraktiker",
    "sg:phone":"+41 21 921 32 97",
    "sg:postcode":"1803",
    "sg:province":"Vaud",
    "wof:name":"Brigitte Marion Th\u00e9rapies Naturelles",
    "wof:placetype":"venue"
},
  "geometry": {"coordinates":[6.8349871635,46.4780845642],"type":"Point"}
}