{
  "type": "Feature",
  "properties": {
    "iso:country":"CH",
    "sg:address":"Liestalstrasse 7a",
    "sg:city":"Gempen",
    "sg:orig_category":"Mechanik",
    "sg:postcode":"4145",
    "sg:province":"Solothurn",
    "wof:name":"Mvt Metallverarbeitungstechnik Gmbh",
    "wof:placetype":"venue"
},
  "geometry": {"coordinates":[9.1500415802,47.5475578308],"type":"Point"}
}