{
  "type": "Feature",
  "properties": {
    "iso:country":"CH",
    "sg:address":"Dancet Rue 3 1205 Gen\u00e8ve. Postfach",
    "sg:city":"Gen\u00e8ve",
    "sg:orig_category":"Non-Classified Establishments",
    "sg:postcode":"1205",
    "sg:province":"Gen\u00e8ve",
    "wof:name":"D\u00fcrrenberger Mathias",
    "wof:placetype":"venue"
},
  "geometry": {"coordinates":[6.1422381401,46.1944007874],"type":"Point"}
}