{
  "type": "Feature",
  "properties": {
    "iso:country":"CH",
    "sg:address":"Steinhofstrasse 41a",
    "sg:city":"Burgdorf",
    "sg:orig_category":"Maler U Glasergewerbe Stukkateurgewerbe, Gipserei U Verputzerei",
    "sg:phone":"+41 34 423 19 70",
    "sg:postcode":"3400",
    "sg:province":"Bern",
    "wof:name":"Antonio Zizzari Malerei & Gipserei",
    "wof:placetype":"venue"
},
  "geometry": {"coordinates":[7.6131567955,47.0555534363],"type":"Point"}
}