{
  "type": "Feature",
  "properties": {
    "iso:country":"CH",
    "sg:address":"Hauptstrasse 70",
    "sg:city":"Langwiesen",
    "sg:orig_category":"Mechanik Mechanische Werkst\u00e4tten",
    "sg:phone":"+41 52 659 25 83",
    "sg:postcode":"8246",
    "sg:province":"Z\u00fcrich",
    "wof:name":"Lehmann Rudolf",
    "wof:placetype":"venue"
},
  "geometry": {"coordinates":[8.6605195999,47.6844482422],"type":"Point"}
}