{
  "type": "Feature",
  "properties": {
    "iso:country":"CH",
    "sg:address":"Grand-rue 38",
    "sg:city":"Courtelary",
    "sg:orig_category":"Detailhandel mit Beleuchtungs U Haushaltsgegenst\u00e4nden Detailhandel mit elektrischen Haushalts-,Radio",
    "sg:phone":"+41 32 944 10 55",
    "sg:postcode":"2608",
    "sg:province":"Bern",
    "wof:name":"Electrom\u00e9nager \u00e0 L'emporter, Pozzoli Mireille",
    "wof:placetype":"venue"
},
  "geometry": {"coordinates":[7.07075,47.177029],"type":"Point"}
}