{
  "type": "Feature",
  "properties": {
    "iso:country":"CH",
    "sg:address":"Poststrasse 7",
    "sg:city":"Killwangen",
    "sg:classifiers":[
        {
            "category":"Insurance",
            "subcategory":"Insurance Agent",
            "type":"Services"
        }
    ],
    "sg:phone":"+41 56 401 38 80",
    "sg:postcode":"8956",
    "sg:province":"Aargau",
    "sg:tags":[
        "versicherungsagenturen",
        "-broker"
    ],
    "wof:name":"Rentenanstalt/swiss Life Spezialagentur",
    "wof:placetype":"venue"
},
  "geometry": {"coordinates":[8.3555240631,47.4302177429],"type":"Point"}
}