{
  "type": "Feature",
  "properties": {
    "iso:country":"CH",
    "sg:address":"Rue St-jean 16",
    "sg:city":"Nyon",
    "sg:orig_category":"Wirtschaftspr\u00fcfung, Steuerberatung U Treuhand",
    "sg:phone":"+41 22 343 13 72",
    "sg:postcode":"1260",
    "sg:province":"Vaud",
    "wof:name":"Bureau Fiduciaire Dentand G\u00e9rald",
    "wof:placetype":"venue"
},
  "geometry": {"coordinates":[6.1369071007,46.1835021973],"type":"Point"}
}