{
  "type": "Feature",
  "properties": {
    "iso:country":"CH",
    "sg:address":"Stadthausstrasse 123 8400 Winterthur. Postfach 367",
    "sg:city":"Winterthur",
    "sg:orig_category":"Mit dem Versicherungsgewerbe verbundene T\u00e4tigkeiten Unternehmensberatung",
    "sg:phone":"+41 52 212 33 11",
    "sg:postcode":"8401",
    "sg:province":"Z\u00fcrich",
    "wof:name":"Ufs Union Finance Of Switzerland Russo",
    "wof:placetype":"venue"
},
  "geometry": {"coordinates":[8.7260560989,47.499710083],"type":"Point"}
}