{
  "type": "Feature",
  "properties": {
    "iso:country":"CH",
    "sg:address":"C\u00e9ard Rue Robert- 13",
    "sg:city":"Gen\u00e8ve",
    "sg:orig_category":"Non-Classified Establishments",
    "sg:postcode":"1204",
    "sg:province":"Gen\u00e8ve",
    "wof:name":"Marie Laetitia Sa",
    "wof:placetype":"venue"
},
  "geometry": {"coordinates":[6.1488480568,46.2028388977],"type":"Point"}
}