{
  "type": "Feature",
  "properties": {
    "addr:full":"Stationsstrasse 10b Rickenbach-attikon Z\u00fcrich 8544",
    "addr:housenumber":"10b rickenbach-attikon",
    "addr:postcode":"8544",
    "addr:street":"Stationsstrasse",
    "iso:country":"CH",
    "sg:address":"Stationsstrasse 10b",
    "sg:city":"Rickenbach-attikon",
    "sg:orig_category":"Arztpraxen",
    "sg:phone":"+41 52 337 27 17",
    "sg:postcode":"8544",
    "sg:province":"Z\u00fcrich",
    "wof:name":"Dr.med.alfred Pfiffner Arzt F.allgemeine Medizin Fmh",
    "wof:placetype":"venue"
},
  "geometry": {"coordinates":[8.797455,47.535873],"type":"Point"}
}