{
  "type": "Feature",
  "properties": {
    "iso:country":"CH",
    "sg:address":"K\u00f6llikerstrasse 95",
    "sg:city":"Gretzenbach",
    "sg:orig_category":"Sanit\u00e4r, Heizungs U L\u00fcftungsinstallation Sanit\u00e4rinstallation",
    "sg:phone":"+41 62 849 33 55",
    "sg:postcode":"5014",
    "sg:province":"Solothurn",
    "wof:name":"Amsler Erhard Sanit\u00e4re Anlagen Und Reparaturen",
    "wof:placetype":"venue"
},
  "geometry": {"coordinates":[8.0006246567,47.3523025513],"type":"Point"}
}