{
  "type": "Feature",
  "properties": {
    "iso:country":"CH",
    "sg:address":"Grand-rue 37",
    "sg:city":"Gen\u00e8ve",
    "sg:orig_category":"Detailhandel mit B\u00fcchern Kunsthandel",
    "sg:phone":"+41 22 311 67 19",
    "sg:postcode":"1204",
    "sg:province":"Gen\u00e8ve",
    "wof:name":"Monique Huguenin",
    "wof:placetype":"venue"
},
  "geometry": {"coordinates":[6.14689,46.201378],"type":"Point"}
}