{
  "type": "Feature",
  "properties": {
    "iso:country":"CH",
    "sg:address":"T\u00e4germoosstrasse 3",
    "sg:city":"Kreuzlingen",
    "sg:orig_category":"Sonstige Verkehrsvermittlung",
    "sg:phone":"+41 71 688 11 59",
    "sg:postcode":"8280",
    "sg:province":"Thurgau",
    "wof:name":"Rvz Ag",
    "wof:placetype":"venue"
},
  "geometry": {"coordinates":[9.1681194305,47.6559066772],"type":"Point"}
}