{
  "type": "Feature",
  "properties": {
    "iso:country":"CH",
    "sg:address":"Auweg 40",
    "sg:city":"Uttigen",
    "sg:orig_category":"Non-Classified Establishments",
    "sg:phone":"+41 33 345 16 54",
    "sg:postcode":"3628",
    "sg:province":"Bern",
    "wof:name":"Pro Ruchti Tec Gmbh",
    "wof:placetype":"venue"
},
  "geometry": {"coordinates":[7.5797348022,46.7955131531],"type":"Point"}
}