{
  "type": "Feature",
  "properties": {
    "iso:country":"CH",
    "sg:address":"Eggstrasse Samstagern",
    "sg:city":"Richterswil",
    "sg:orig_category":"Herstellung von Konstruktionsteilen, Fertigbauteilen U Ausbauelementen aus Holz",
    "sg:postcode":"8805",
    "sg:province":"Z\u00fcrich",
    "wof:name":"H\u00f6hn Walter",
    "wof:placetype":"venue"
},
  "geometry": {"coordinates":[8.7051200867,47.2075004578],"type":"Point"}
}