{
  "type": "Feature",
  "properties": {
    "addr:full":"Rikonerstrasse 18 Effretikon Z\u00fcrich 8307",
    "addr:housenumber":"18",
    "addr:postcode":"8307",
    "addr:street":"Rikonerstrasse",
    "iso:country":"CH",
    "sg:address":"Rikonerstrasse 18",
    "sg:city":"Effretikon",
    "sg:orig_category":"Arztpraxen",
    "sg:phone":"+41 52 343 55 44",
    "sg:postcode":"8307",
    "sg:province":"Z\u00fcrich",
    "wof:name":"Dr.med.peter Moeschlin Arzt F.allgemeine Medizin Fmh",
    "wof:placetype":"venue"
},
  "geometry": {"coordinates":[8.686859,47.429138],"type":"Point"}
}