{
  "type": "Feature",
  "properties": {
    "iso:country":"CH",
    "sg:address":"Bieschgarten",
    "sg:city":"Raron",
    "sg:orig_category":"Fussboden, Fliesen U Plattenlegerei, Tapeziererei Verlegen von Fliesen U Platten",
    "sg:phone":"+41 27 934 16 45",
    "sg:postcode":"3942",
    "sg:province":"Valais",
    "wof:name":"Burgener Reinhold & Co Plattenlegergesch\u00e4ft",
    "wof:placetype":"venue"
},
  "geometry": {"coordinates":[7.7967429161,46.3099784851],"type":"Point"}
}