{
  "type": "Feature",
  "properties": {
    "iso:country":"CH",
    "sg:address":"Route De La Gemmi 67",
    "sg:city":"Sierre",
    "sg:orig_category":"Mechanik Mechanische Werkst\u00e4tten",
    "sg:phone":"+41 27 456 46 47",
    "sg:postcode":"3960",
    "sg:province":"Valais",
    "wof:name":"O.s. Technique S\u00e0rl",
    "wof:placetype":"venue"
},
  "geometry": {"coordinates":[7.5562939644,46.3006019592],"type":"Point"}
}