{
  "type": "Feature",
  "properties": {
    "iso:country":"CH",
    "sg:address":"Artherstrasse 27 6300 Zug. Postfach",
    "sg:city":"Zug",
    "sg:orig_category":"Gesundheitswesen",
    "sg:postcode":"6300",
    "sg:province":"Zug",
    "wof:name":"Violab Zug Ag",
    "wof:placetype":"venue"
},
  "geometry": {"coordinates":[8.5129089355,47.1600418091],"type":"Point"}
}