{
  "type": "Feature",
  "properties": {
    "iso:country":"CH",
    "sg:address":"Industriestrasse 1",
    "sg:city":"Bonaduz",
    "sg:orig_category":"Herstellung von Metallkonstruktionen",
    "sg:phone":"+41 81 641 14 44",
    "sg:postcode":"7402",
    "sg:province":"Graubunden",
    "wof:name":"Stiefenhofer H.",
    "wof:placetype":"venue"
},
  "geometry": {"coordinates":[9.386051178,46.8100013733],"type":"Point"}
}