{
  "type": "Feature",
  "properties": {
    "addr:full":"6656 Golino Ticino 6656",
    "addr:postcode":"6656;6656",
    "iso:country":"CH",
    "sg:address":"6656",
    "sg:city":"Golino",
    "sg:orig_category":"Allgemeiner Hoch U Tiefbau Hoch U Tiefbau",
    "sg:phone":"+41 91 796 21 56",
    "sg:postcode":"6656",
    "sg:province":"Ticino",
    "wof:name":"Guillod Kurt",
    "wof:placetype":"venue"
},
  "geometry": {"coordinates":[8.71339,46.178501],"type":"Point"}
}