{
  "type": "Feature",
  "properties": {
    "iso:country":"CH",
    "sg:address":"Effingerstrasse 23",
    "sg:city":"Bern",
    "sg:orig_category":"Detailhandel mit Bekleidung Detailhandel mit Damenbekleidung",
    "sg:phone":"+41 31 311 05 96",
    "sg:postcode":"3008",
    "sg:province":"Bern",
    "wof:name":"Rasanti Store Hosen Saloon Thommen Ag",
    "wof:placetype":"venue"
},
  "geometry": {"coordinates":[7.42176,46.944649],"type":"Point"}
}