{
  "type": "Feature",
  "properties": {
    "iso:country":"CH",
    "sg:address":"Weber Avenue Th\u00e9odore- 5 1208 Gen\u00e8ve. Postfach",
    "sg:city":"Gen\u00e8ve",
    "sg:orig_category":"Finanzierungsinstitutionen",
    "sg:postcode":"1208",
    "sg:province":"Gen\u00e8ve",
    "wof:name":"Helsmoortel Twainy Marie",
    "wof:placetype":"venue"
},
  "geometry": {"coordinates":[6.162569046,46.1994781494],"type":"Point"}
}