{
  "type": "Feature",
  "properties": {
    "iso:country":"CH",
    "sg:address":"Feldstrasse 25 4663 Aarburg. Postfach 128",
    "sg:city":"Aarburg",
    "sg:orig_category":"Detailhandel mit elektrischen Haushalts-,Radio U Fernsehger\u00e4ten sowie Musikinstrumenten",
    "sg:phone":"+41 62 787 20 80",
    "sg:postcode":"4663",
    "sg:province":"Aargau",
    "wof:name":"Blanco Gmbh & Co Kg, Oberderdingen, Zweigniederlassung Aarburg",
    "wof:placetype":"venue"
},
  "geometry": {"coordinates":[7.9029507637,47.3329734802],"type":"Point"}
}