{
  "type": "Feature",
  "properties": {
    "iso:country":"CH",
    "sg:address":"Rue De L'industrie 10 1950 Sion Case Postale 1261",
    "sg:city":"Sion",
    "sg:orig_category":"Herstellung von Hebezeugen U F\u00f6rdermitteln Herstellung von Mess U Kontrollinstrumenten U vorrichtung",
    "sg:phone":"+41 27 323 09 10",
    "sg:postcode":"1951",
    "sg:province":"Valais",
    "wof:name":"Sportaccess Kudelski Sa",
    "wof:placetype":"venue"
},
  "geometry": {"coordinates":[7.3598861694,46.2263870239],"type":"Point"}
}