{
  "type": "Feature",
  "properties": {
    "iso:country":"CH",
    "sg:address":"Flurstrasse 30/f 706",
    "sg:city":"Z\u00fcrich",
    "sg:orig_category":"Unternehmensberatung",
    "sg:phone":"+41 2070562",
    "sg:postcode":"8047",
    "sg:province":"Z\u00fcrich",
    "wof:name":"Scg Gmbh",
    "wof:placetype":"venue"
},
  "geometry": {"coordinates":[8.4874601364,47.3748207092],"type":"Point"}
}