{
  "type": "Feature",
  "properties": {
    "iso:country":"CH",
    "sg:address":"Haus Terra",
    "sg:city":"Unterterzen",
    "sg:orig_category":"Architektur U Ingenieurb\u00fcros",
    "sg:phone":"+41 81 738 19 16",
    "sg:postcode":"8882",
    "sg:province":"St. Gallen",
    "wof:name":"Ingenieurb\u00fcro Gubser Kurt Und Partner Ag",
    "wof:placetype":"venue"
},
  "geometry": {"coordinates":[9.25304,47.113514],"type":"Point"}
}