{
  "type": "Feature",
  "properties": {
    "addr:full":"Strickstrasse 15 Uster Z\u00fcrich 8610",
    "addr:housenumber":"15",
    "addr:postcode":"8610",
    "addr:street":"Strickstrasse",
    "iso:country":"CH",
    "sg:address":"Strickstrasse 15",
    "sg:city":"Uster",
    "sg:orig_category":"Architektur U Ingenieurb\u00fcros",
    "sg:phone":"+41 19406165",
    "sg:postcode":"8610",
    "sg:province":"Z\u00fcrich",
    "wof:name":"Engineering Team Kohler + Partner",
    "wof:placetype":"venue"
},
  "geometry": {"coordinates":[8.71022,47.356361],"type":"Point"}
}