{
  "type": "Feature",
  "properties": {
    "iso:country":"CH",
    "sg:address":"Blumenrain 3",
    "sg:city":"Basel",
    "sg:orig_category":"Detailhandel mit Antiquit\u00e4ten Herstellung von sonstigen M\u00f6beln",
    "sg:phone":"+41 61 261 68 37",
    "sg:postcode":"4051",
    "sg:province":"Basel-Stadt",
    "wof:name":"Nordfrid Steiner",
    "wof:placetype":"venue"
},
  "geometry": {"coordinates":[7.587271,47.560345],"type":"Point"}
}