{
  "type": "Feature",
  "properties": {
    "iso:country":"CH",
    "sg:address":"Schwarzbachstrasse 8",
    "sg:city":"Rubigen",
    "sg:orig_category":"Selbst\u00e4ndige bildende K\u00fcnstler",
    "sg:phone":"+41 31 721 26 99",
    "sg:postcode":"3113",
    "sg:province":"Bern",
    "wof:name":"Marianne Grunder Steinbildhauerin",
    "wof:placetype":"venue"
},
  "geometry": {"coordinates":[7.5399241447,46.902797699],"type":"Point"}
}