{
  "type": "Feature",
  "properties": {
    "iso:country":"CH",
    "sg:address":"Grossfeldstrasse 16a",
    "sg:city":"Sargans",
    "sg:orig_category":"Non-Classified Establishments",
    "sg:postcode":"7320",
    "sg:province":"St. Gallen",
    "wof:name":"The Original, Yvette Bucher",
    "wof:placetype":"venue"
},
  "geometry": {"coordinates":[8.3074598312,46.9915618896],"type":"Point"}
}