{
  "type": "Feature",
  "properties": {
    "iso:country":"CH",
    "sg:address":"Corso Elvezia 20",
    "sg:city":"Lugano",
    "sg:orig_category":"Zahnarztpraxen",
    "sg:phone":"+41 91 922 22 80",
    "sg:postcode":"6900",
    "sg:province":"Ticino",
    "wof:name":"Dott.med.dent.h. Breitenmoser Dentista",
    "wof:placetype":"venue"
},
  "geometry": {"coordinates":[8.9560871124,46.0086021423],"type":"Point"}
}