{
  "type": "Feature",
  "properties": {
    "iso:country":"CH",
    "sg:address":"Gassen\u00e4ckerstrasse 5",
    "sg:city":"Amriswil",
    "sg:orig_category":"Baugewerbe Fussboden, Fliesen U Plattenlegerei, Tapeziererei",
    "sg:phone":"+41 71 411 22 74",
    "sg:postcode":"8580",
    "sg:province":"Thurgau",
    "wof:name":"Rinox Ag Baukeramik Naturstein",
    "wof:placetype":"venue"
},
  "geometry": {"coordinates":[9.306301,47.539848],"type":"Point"}
}