{
  "type": "Feature",
  "properties": {
    "iso:country":"CH",
    "sg:address":"Codeborgo Via 17",
    "sg:city":"Bellinzona",
    "sg:orig_category":"RESTAURANTS: TEA-ROOMS",
    "sg:phone":"+41 18332603",
    "sg:postcode":"6500",
    "sg:province":"Ticino",
    "wof:name":"Settimio & Co",
    "wof:placetype":"venue"
},
  "geometry": {"coordinates":[8.6344070435,47.4164199829],"type":"Point"}
}