{
  "type": "Feature",
  "properties": {
    "iso:country":"CH",
    "sg:address":"Kirchgasse 5 9220 Bischofszell. Postfach",
    "sg:city":"Bischofszell",
    "sg:orig_category":"Verwaltung der Rechtspflege, Gerichte",
    "sg:phone":"+41 71 422 16 01",
    "sg:postcode":"9220",
    "sg:province":"Thurgau",
    "wof:name":"Grundbuchamt Kreis Bischofszell",
    "wof:placetype":"venue"
},
  "geometry": {"coordinates":[9.2401323318,47.493221283],"type":"Point"}
}