{
  "type": "Feature",
  "properties": {
    "iso:country":"CH",
    "sg:address":"Rue De La Toule",
    "sg:city":"Saxon",
    "sg:orig_category":"Stukkateurgewerbe, Gipserei U Verputzerei",
    "sg:postcode":"1907",
    "sg:province":"Valais",
    "wof:name":"Baudin Johann.",
    "wof:placetype":"venue"
},
  "geometry": {"coordinates":[7.1819300652,46.1889343262],"type":"Point"}
}