{
  "type": "Feature",
  "properties": {
    "iso:country":"CH",
    "sg:address":"Gartenstrasse 99",
    "sg:city":"Basel",
    "sg:orig_category":"Softwareentwicklung U beratung",
    "sg:postcode":"4052",
    "sg:province":"Basel-Stadt",
    "wof:name":"Saletti-software Martin Werner",
    "wof:placetype":"venue"
},
  "geometry": {"coordinates":[7.5934619904,47.5480995178],"type":"Point"}
}