{
  "type": "Feature",
  "properties": {
    "iso:country":"CH",
    "sg:address":"Austrasse 38",
    "sg:city":"Z\u00fcrich",
    "sg:orig_category":"Grosshandel mit Kaffee, Tee, Kakao U Gew\u00fcrzen Verarbeitung von Tee U Kaffee",
    "sg:postcode":"8045",
    "sg:province":"Z\u00fcrich",
    "wof:name":"Walter Stoll Kaffee-r\u00f6sterei",
    "wof:placetype":"venue"
},
  "geometry": {"coordinates":[8.5195493698,47.3650741577],"type":"Point"}
}