{
  "type": "Feature",
  "properties": {
    "iso:country":"CH",
    "sg:address":"Bibersteinerstrasse 34",
    "sg:city":"Rombach",
    "sg:orig_category":"Malerei",
    "sg:phone":"+41 62 827 14 38",
    "sg:postcode":"5022",
    "sg:province":"Aargau",
    "wof:name":"Walter D\u00e4twyler Malerservice",
    "wof:placetype":"venue"
},
  "geometry": {"coordinates":[8.0478191376,47.4031333923],"type":"Point"}
}