{
  "type": "Feature",
  "properties": {
    "iso:country":"CH",
    "sg:address":"Zentrumsplatz 8",
    "sg:city":"Sch\u00f6nb\u00fchl-urtenen",
    "sg:classifiers":[
        {
            "category":"Education",
            "subcategory":"Library",
            "type":"Public Place"
        }
    ],
    "sg:phone":"+41 31 859 26 27",
    "sg:postcode":"3322",
    "sg:province":"Bern",
    "sg:tags":[
        "u",
        "bibliotheken",
        "archive"
    ],
    "wof:name":"Gemeindebibliothek",
    "wof:placetype":"venue"
},
  "geometry": {"coordinates":[7.498723,47.021027],"type":"Point"}
}