{
  "type": "Feature",
  "properties": {
    "iso:country":"CH",
    "sg:address":"Oekingenstr. 134",
    "sg:city":"Kriegstetten",
    "sg:orig_category":"Grosshandel mit lebenden Tieren",
    "sg:postcode":"4566",
    "sg:province":"Solothurn",
    "wof:name":"Schafzuchtgenossenschaft Solothurn-wasseramt.",
    "wof:placetype":"venue"
},
  "geometry": {"coordinates":[7.6027002335,47.1759910583],"type":"Point"}
}