{
  "type": "Feature",
  "properties": {
    "iso:country":"CH",
    "sg:address":"Seestrasse 41",
    "sg:city":"W\u00e4denswil",
    "sg:classifiers":[
        {
            "category":"Restaurant",
            "type":"Food & Drink"
        }
    ],
    "sg:phone":"+41 17808140",
    "sg:postcode":"8820",
    "sg:province":"Z\u00fcrich",
    "wof:name":"Restaurant Bierquelle",
    "wof:placetype":"venue"
},
  "geometry": {"coordinates":[8.6810846329,47.2243309021],"type":"Point"}
}