{
  "type": "Feature",
  "properties": {
    "iso:country":"CH",
    "sg:address":"Zugerstrasse 53",
    "sg:city":"Cham",
    "sg:orig_category":"Informatikschulen Softwareentwicklung U beratung",
    "sg:phone":"+41 41 784 00 11",
    "sg:postcode":"6330",
    "sg:province":"Zug",
    "wof:name":"Righetti Informatik Training",
    "wof:placetype":"venue"
},
  "geometry": {"coordinates":[8.4676876068,47.1821250916],"type":"Point"}
}