{
  "type": "Feature",
  "properties": {
    "iso:country":"CH",
    "sg:address":"Rue Des Verdiers 5",
    "sg:city":"Del\u00e9mont",
    "sg:orig_category":"Organisationen des Gesundheitswesen",
    "sg:phone":"+41 32 422 88 61",
    "sg:postcode":"2800",
    "sg:province":"Jura",
    "wof:name":"St\u00e9 Samar.choindez-courrendlin",
    "wof:placetype":"venue"
},
  "geometry": {"coordinates":[7.3529820442,47.3582229614],"type":"Point"}
}