{
  "type": "Feature",
  "properties": {
    "addr:full":"Hauptstrasse 22 Luterbach Solothurn 4542",
    "addr:housenumber":"22",
    "addr:postcode":"4542",
    "addr:street":"Hauptstrasse",
    "iso:country":"CH",
    "sg:address":"Hauptstrasse 22",
    "sg:city":"Luterbach",
    "sg:orig_category":"Detailhandel mit Brot, Back U S\u00fcsswaren",
    "sg:postcode":"4542",
    "sg:province":"Solothurn",
    "wof:name":"L\u00f6rtscher Andr\u00e9",
    "wof:placetype":"venue"
},
  "geometry": {"coordinates":[7.587582,47.216167],"type":"Point"}
}