{
  "type": "Feature",
  "properties": {
    "iso:country":"CH",
    "sg:address":"Ausserfeld 51",
    "sg:city":"B\u00fctschwil",
    "sg:classifiers":[
        {
            "category":"Restaurant",
            "type":"Food & Drink"
        }
    ],
    "sg:phone":"+41 71 983 10 11",
    "sg:postcode":"9606",
    "sg:province":"St. Gallen",
    "wof:name":"Restaurant Feld",
    "wof:placetype":"venue"
},
  "geometry": {"coordinates":[9.0773887634,47.350276947],"type":"Point"}
}