{
  "type": "Feature",
  "properties": {
    "iso:country":"CH",
    "sg:address":"Bettlistrasse 28 8600 D\u00fcbendorf. Postfach 610",
    "sg:city":"D\u00fcbendorf",
    "sg:orig_category":"Wirtschaftspr\u00fcfung, Steuerberatung U Treuhand",
    "sg:phone":"+41 71 755 56 57",
    "sg:postcode":"8600",
    "sg:province":"Z\u00fcrich",
    "wof:name":"Eugster Treuhand",
    "wof:placetype":"venue"
},
  "geometry": {"coordinates":[9.5413970947,47.3785514832],"type":"Point"}
}