{
  "type": "Feature",
  "properties": {
    "iso:country":"CH",
    "sg:address":"Boulevard De Grancy 36",
    "sg:city":"Lausanne",
    "sg:orig_category":"P\u00e9dicure",
    "sg:phone":"+41 21 616 04 77",
    "sg:postcode":"1006",
    "sg:province":"Vaud",
    "wof:name":"Simone Durussel P\u00e9dicure",
    "wof:placetype":"venue"
},
  "geometry": {"coordinates":[6.6277351379,46.5159988403],"type":"Point"}
}