{
  "type": "Feature",
  "properties": {
    "iso:country":"CH",
    "sg:address":"Rue Principale 2 2735 B\u00e9vilard. Postfach",
    "sg:city":"B\u00e9vilard",
    "sg:orig_category":"Architektur U Ingenieurb\u00fcros Baumaterial and Do-it-yourself Detailhandel",
    "sg:phone":"+41 32 492 11 92",
    "sg:postcode":"2735",
    "sg:province":"Bern",
    "wof:name":"Traitacolor S\u00e0rl Atelier De Traitement Industriel De Surface Etc.",
    "wof:placetype":"venue"
},
  "geometry": {"coordinates":[7.2789697647,47.2373428345],"type":"Point"}
}