{
  "type": "Feature",
  "properties": {
    "iso:country":"CH",
    "sg:address":"Pace Via Della 1",
    "sg:city":"Locarno",
    "sg:orig_category":"Detailhandel mit Bekleidung",
    "sg:phone":"+41 79 427 75 29",
    "sg:postcode":"6600",
    "sg:province":"Ticino",
    "wof:name":"Pool Distribution Sagl",
    "wof:placetype":"venue"
},
  "geometry": {"coordinates":[8.798657,46.168781],"type":"Point"}
}