{
  "type": "Feature",
  "properties": {
    "iso:country":"CH",
    "sg:address":"Laufenburgerstrasse 16/11",
    "sg:city":"Rheinfelden",
    "sg:orig_category":"Sanit\u00e4r U Heizungsinstallation Sanit\u00e4r, Heizungs U L\u00fcftungsinstallation",
    "sg:phone":"+41 79 205 97 64",
    "sg:postcode":"4310",
    "sg:province":"Aargau",
    "wof:name":"Christian V\u00f6gtli Heizungsbau &-reparaturen",
    "wof:placetype":"venue"
},
  "geometry": {"coordinates":[7.7683582306,47.5480079651],"type":"Point"}
}