{
  "type": "Feature",
  "properties": {
    "iso:country":"CH",
    "sg:address":"Rue De Neuch\u00e2tel 34",
    "sg:city":"Peseux",
    "sg:orig_category":"Detailhandel mit Textilien Sonstiges Textilgewerbe",
    "sg:phone":"+41 32 730 58 30",
    "sg:postcode":"2034",
    "sg:province":"Neuch\u00e2tel",
    "wof:name":"Textiles Ambiance Sa",
    "wof:placetype":"venue"
},
  "geometry": {"coordinates":[6.8968491554,46.9884529114],"type":"Point"}
}