{
  "type": "Feature",
  "properties": {
    "iso:country":"CH",
    "sg:address":"Washingtonstrasse 41",
    "sg:city":"Rorschach",
    "sg:orig_category":"Herstellung von sonstigen elektrischen Ausr\u00fcstungen",
    "sg:phone":"+41 71 841 07 39",
    "sg:postcode":"9400",
    "sg:province":"St. Gallen",
    "wof:name":"Prader & Co. Bio-elektrotechnik",
    "wof:placetype":"venue"
},
  "geometry": {"coordinates":[9.4894256592,47.4729728699],"type":"Point"}
}