{
  "type": "Feature",
  "properties": {
    "iso:country":"CH",
    "sg:address":"Dorfstrasse",
    "sg:city":"Altenrhein",
    "sg:orig_category":"Vorschulen, Kinderg\u00e4rten",
    "sg:phone":"+41 75 392 19 33",
    "sg:postcode":"9423",
    "sg:province":"St. Gallen",
    "wof:name":"Kindergarten",
    "wof:placetype":"venue"
},
  "geometry": {"coordinates":[9.5552587509,47.4902763367],"type":"Point"}
}