{
  "type": "Feature",
  "properties": {
    "iso:country":"CH",
    "sg:address":"Gottfried-keller-strasse 11",
    "sg:city":"St.gallen",
    "sg:orig_category":"Markt U Meinungsforschung Werbeberatung",
    "sg:phone":"+41 71 222 18 54",
    "sg:postcode":"9000",
    "sg:province":"St. Gallen",
    "wof:name":"Mpp - Marketing Service - Kern Willy G.",
    "wof:placetype":"venue"
},
  "geometry": {"coordinates":[9.3754940033,47.4199638367],"type":"Point"}
}