{
  "type": "Feature",
  "properties": {
    "iso:country":"CH",
    "sg:address":"Dorf 10",
    "sg:city":"Milken",
    "sg:orig_category":"Herstellung von sonstigen landwirtschaftlichen Maschinen Instandhaltung U Reparatur von Automobilen",
    "sg:phone":"+41 31 731 12 03",
    "sg:postcode":"3157",
    "sg:province":"Bern",
    "wof:name":"Zahnd Ag",
    "wof:placetype":"venue"
},
  "geometry": {"coordinates":[7.3592910767,46.7935256958],"type":"Point"}
}