{
  "type": "Feature",
  "properties": {
    "iso:country":"CH",
    "sg:address":"Z\u00fcrcherstrasse 66-68 8800 Thalwil. Postfach 179",
    "sg:city":"Thalwil",
    "sg:orig_category":"Sonstiges Versicherungsgewerbe",
    "sg:phone":"+41 81 911 10 25",
    "sg:postcode":"8800",
    "sg:province":"Z\u00fcrich",
    "wof:name":"Oeffentl.krankenkasse Flims",
    "wof:placetype":"venue"
},
  "geometry": {"coordinates":[9.2852306366,46.8366928101],"type":"Point"}
}