{
  "type": "Feature",
  "properties": {
    "addr:full":"Lenzenhausstrasse 9 Erlen Thurgau 8586",
    "addr:housenumber":"9",
    "addr:postcode":"8586",
    "addr:street":"Lenzenhausstrasse",
    "iso:country":"CH",
    "sg:address":"Lenzenhausstrasse 9",
    "sg:city":"Erlen",
    "sg:orig_category":"Blumen U Zierpflanzenbau",
    "sg:phone":"+41 71 648 13 32",
    "sg:postcode":"8586",
    "sg:province":"Thurgau",
    "wof:name":"Markus Neubauer G\u00e4rtnerei",
    "wof:placetype":"venue"
},
  "geometry": {"coordinates":[9.22291,47.555336],"type":"Point"}
}