{
  "type": "Feature",
  "properties": {
    "iso:country":"CH",
    "sg:address":"Heinrichsgasse 10",
    "sg:city":"Basel",
    "sg:orig_category":"Fotografische Ateliers",
    "sg:phone":"+41 61 274 03 29",
    "sg:postcode":"4055",
    "sg:province":"Basel-Stadt",
    "wof:name":"Erik Schmidt Fotografisches Atelier",
    "wof:placetype":"venue"
},
  "geometry": {"coordinates":[7.5765028,47.5566482544],"type":"Point"}
}