{
  "type": "Feature",
  "properties": {
    "iso:country":"CH",
    "sg:address":"Chemin D'entre-bois 59",
    "sg:city":"Lausanne",
    "sg:orig_category":"Kosmetikinstitute",
    "sg:phone":"+41 21 647 33 90",
    "sg:postcode":"1018",
    "sg:province":"Vaud",
    "wof:name":"Maria Nagy Institut De Beaut\u00e9",
    "wof:placetype":"venue"
},
  "geometry": {"coordinates":[6.634540081,46.5387687683],"type":"Point"}
}