{
  "type": "Feature",
  "properties": {
    "iso:country":"CH",
    "sg:address":"Karlihof 8a",
    "sg:city":"Malans",
    "sg:classifiers":[
        {
            "category":"Professional",
            "subcategory":"Printing & Photocopies",
            "type":"Services"
        }
    ],
    "sg:phone":"+41 81 322 21 94",
    "sg:postcode":"7208",
    "sg:province":"Graubunden",
    "sg:tags":[
        "batik",
        "ink"
    ],
    "wof:name":"W\u00fcma Fritz W\u00fcstemann Ag",
    "wof:placetype":"venue"
},
  "geometry": {"coordinates":[9.560423,46.971886],"type":"Point"}
}