{
  "type": "Feature",
  "properties": {
    "iso:country":"CH",
    "sg:address":"Chemin Du Trabandan 28 1006 Lausanne Case Postale",
    "sg:city":"Lausanne",
    "sg:orig_category":"Wirtschaftspr\u00fcfung, Steuerberatung U Treuhand",
    "sg:phone":"+41 21 323 77 22",
    "sg:postcode":"1001",
    "sg:province":"Vaud",
    "wof:name":"Pfefferl\u00e9, Sulmoni & Associ\u00e9s Sa",
    "wof:placetype":"venue"
},
  "geometry": {"coordinates":[6.6438469887,46.5135231018],"type":"Point"}
}