{
  "type": "Feature",
  "properties": {
    "iso:country":"CH",
    "sg:address":"Schwerstrasse 9",
    "sg:city":"Schaffhausen",
    "sg:orig_category":"Non-Classified Establishments",
    "sg:postcode":"8202",
    "sg:province":"Schaffhausen",
    "wof:name":"Tyco Group S\u00e0rl, Luxemburg (l), Zweigniederlassung Schaffhausen Beteiligungen Usw",
    "wof:placetype":"venue"
},
  "geometry": {"coordinates":[8.6325616837,47.6972923279],"type":"Point"}
}