{
  "type": "Feature",
  "properties": {
    "iso:country":"CH",
    "sg:address":"Robert Luterbacherstrasse 3 2540 Grenchen. Postfach",
    "sg:city":"Grenchen",
    "sg:orig_category":"Fachdetailhandel in Verkaufsr\u00e4umen",
    "sg:postcode":"2540",
    "sg:province":"Solothurn",
    "wof:name":"Taj Asian Shop & Travel Gmbh Asiatische Produkte, Lebensmittel, Getr\u00e4nke, Schmuck Usw.; Verkauf",
    "wof:placetype":"venue"
},
  "geometry": {"coordinates":[7.394094944,47.1929397583],"type":"Point"}
}