{
  "type": "Feature",
  "properties": {
    "iso:country":"CH",
    "sg:address":"Bonnstrasse 28",
    "sg:city":"D\u00fcdingen",
    "sg:orig_category":"Steinbildhauereien",
    "sg:postcode":"3186",
    "sg:province":"Fribourg",
    "wof:name":"Marba Hayoz & M\u00fcller Grabmale & Natursteinarbeiten",
    "wof:placetype":"venue"
},
  "geometry": {"coordinates":[7.185942173,46.858127594],"type":"Point"}
}