{
  "type": "Feature",
  "properties": {
    "iso:country":"CH",
    "sg:address":"Cassinone",
    "sg:city":"Molinazzo",
    "sg:classifiers":[
        {
            "category":"Restaurant",
            "type":"Food & Drink"
        }
    ],
    "sg:phone":"+41 91 608 25 64",
    "sg:postcode":"6995",
    "sg:province":"Ticino",
    "wof:name":"Osteria Cavagno",
    "wof:placetype":"venue"
},
  "geometry": {"coordinates":[8.8205404282,45.990020752],"type":"Point"}
}