{
  "type": "Feature",
  "properties": {
    "iso:country":"CH",
    "sg:address":"Etzelstrasse 19",
    "sg:city":"Wettingen",
    "sg:orig_category":"Sonstiger Grosshandel",
    "sg:postcode":"5430",
    "sg:province":"Aargau",
    "wof:name":"Hunziker-tubio Ag",
    "wof:placetype":"venue"
},
  "geometry": {"coordinates":[8.3181676865,47.4631958008],"type":"Point"}
}