{
  "type": "Feature",
  "properties": {
    "iso:country":"CH",
    "sg:address":"Hinterdorfstrasse 51",
    "sg:city":"Dintikon",
    "sg:orig_category":"Sportvereine Turnen",
    "sg:postcode":"5606",
    "sg:province":"Aargau",
    "wof:name":"Turnverein Stv Dintikon",
    "wof:placetype":"venue"
},
  "geometry": {"coordinates":[8.2259559631,47.3614120483],"type":"Point"}
}