{
  "type": "Feature",
  "properties": {
    "iso:country":"CH",
    "sg:address":"Obere Kirchgasse 12",
    "sg:city":"Winterthur",
    "sg:orig_category":"Detailhandel mit Damenbekleidung Herstellung von konfektionierten Textilwaren ohne Bekleidung",
    "sg:phone":"+41 52 212 92 93",
    "sg:postcode":"8400",
    "sg:province":"Z\u00fcrich",
    "wof:name":"Boa Couture",
    "wof:placetype":"venue"
},
  "geometry": {"coordinates":[8.7293510437,47.4989318848],"type":"Point"}
}