{
  "type": "Feature",
  "properties": {
    "iso:country":"CH",
    "sg:address":"Ryfweg 2",
    "sg:city":"Ins",
    "sg:orig_category":"Wasserversorgung",
    "sg:postcode":"3232",
    "sg:province":"Bern",
    "wof:name":"Wasser Erdgas Kl\u00f6tzli Gmbh",
    "wof:placetype":"venue"
},
  "geometry": {"coordinates":[9.4727878571,47.1602554321],"type":"Point"}
}