{
  "type": "Feature",
  "properties": {
    "iso:country":"CH",
    "sg:address":"Oberdorfstr. 17",
    "sg:city":"Knonau",
    "sg:classifiers":[
        {
            "category":"Government",
            "subcategory":"Department Of Motor Vehicles",
            "type":"Public Place"
        }
    ],
    "sg:phone":"+41 4117685454",
    "sg:postcode":"8934",
    "sg:province":"Z\u00fcrich",
    "sg:tags":[
        "equipment",
        "industrial",
        "transport",
        "motor-cars"
    ],
    "wof:name":"Sahli Ag",
    "wof:placetype":"venue"
},
  "geometry": {"coordinates":[8.4626970291,47.2253799438],"type":"Point"}
}