{
  "type": "Feature",
  "properties": {
    "iso:country":"CH",
    "sg:address":"Lettenstrasse 11",
    "sg:city":"Rotkreuz",
    "sg:orig_category":"Herstellung von Werkzeugen Mechanische Werkst\u00e4tten",
    "sg:phone":"+41 41 790 31 88",
    "sg:postcode":"6343",
    "sg:province":"Zug",
    "wof:name":"B\u00fcrgler Und Partner Gmbh",
    "wof:placetype":"venue"
},
  "geometry": {"coordinates":[8.4307203293,47.147518158],"type":"Point"}
}