{
  "type": "Feature",
  "properties": {
    "iso:country":"CH",
    "sg:address":"S. Michele",
    "sg:city":"Arogno",
    "sg:orig_category":"Finanzierungsinstitutionen",
    "sg:phone":"+41 91 649 71 43",
    "sg:postcode":"6822",
    "sg:province":"Ticino",
    "wof:name":"Lupi Giorgio",
    "wof:placetype":"venue"
},
  "geometry": {"coordinates":[8.9908075333,45.955368042],"type":"Point"}
}