{
  "type": "Feature",
  "properties": {
    "iso:country":"CH",
    "sg:address":"Leso Sopra",
    "sg:city":"Mesocco",
    "sg:orig_category":"Softwareentwicklung U beratung",
    "sg:postcode":"6563",
    "sg:province":"Graubunden",
    "wof:name":"Farlos, Farina L.",
    "wof:placetype":"venue"
},
  "geometry": {"coordinates":[9.2303304672,46.3937149048],"type":"Point"}
}