{
  "type": "Feature",
  "properties": {
    "iso:country":"CH",
    "sg:address":"Piazza Colombaro 5",
    "sg:city":"Canobbio",
    "sg:orig_category":"Detailhandel mit Fleisch U Fleischwaren",
    "sg:phone":"+41 91 940 45 60",
    "sg:postcode":"6952",
    "sg:province":"Ticino",
    "wof:name":"Stefano Masneri Macelleria-salumeria",
    "wof:placetype":"venue"
},
  "geometry": {"coordinates":[8.9681720734,46.0342407227],"type":"Point"}
}