{
  "type": "Feature",
  "properties": {
    "iso:country":"CH",
    "sg:address":"Ibelweg 18a",
    "sg:city":"Baar",
    "sg:orig_category":"Unclassifiable Establishments",
    "sg:postcode":"6340",
    "sg:province":"Zug",
    "wof:name":"Partekk Handels Ag",
    "wof:placetype":"venue"
},
  "geometry": {"coordinates":[8.5254907608,47.1805229187],"type":"Point"}
}