{
  "type": "Feature",
  "properties": {
    "iso:country":"CH",
    "sg:address":"Aarwangenstrasse 30",
    "sg:city":"Bannwil",
    "sg:orig_category":"Sonstiger Grosshandel",
    "sg:postcode":"4913",
    "sg:province":"Bern",
    "wof:name":"Hans J\u00fcrg Meyer",
    "wof:placetype":"venue"
},
  "geometry": {"coordinates":[7.7391982079,47.2418022156],"type":"Point"}
}