{
  "type": "Feature",
  "properties": {
    "iso:country":"CH",
    "sg:address":"Waldhausweg 108",
    "sg:city":"G\u00fcmligen",
    "sg:orig_category":"Ingenieurb\u00fcros Geologie",
    "sg:phone":"+41 31 952 60 33",
    "sg:postcode":"3073",
    "sg:province":"Bern",
    "wof:name":"Dr.hans-peter Weiss Geologisches B\u00fcro",
    "wof:placetype":"venue"
},
  "geometry": {"coordinates":[7.505420208,46.9365615845],"type":"Point"}
}