{
  "type": "Feature",
  "properties": {
    "iso:country":"CH",
    "sg:address":"Place De La Gare 11",
    "sg:city":"Nyon",
    "sg:orig_category":"Zahnarztpraxen",
    "sg:phone":"+41 26 436 24 44",
    "sg:postcode":"1260",
    "sg:province":"Vaud",
    "wof:name":"Dr M\u00e9d. Dent. Kalman Sz\u00fcts M\u00e9decin-dentiste",
    "wof:placetype":"venue"
},
  "geometry": {"coordinates":[7.1513872147,46.7834777832],"type":"Point"}
}