{
  "type": "Feature",
  "properties": {
    "addr:full":"Route D'englisberg 7 Granges-paccot Fribourg 1763",
    "addr:housenumber":"7",
    "addr:postcode":"1763",
    "addr:street":"Route D'Englisberg",
    "iso:country":"CH",
    "sg:address":"Route D'englisberg 7",
    "sg:city":"Granges-paccot",
    "sg:orig_category":"Detailhandel mit elektrischen Haushalts-,Radio U Fernsehger\u00e4ten sowie Musikinstrumenten Herstellung ",
    "sg:phone":"+41 19300940",
    "sg:postcode":"1763",
    "sg:province":"Fribourg",
    "wof:name":"Ark Guitar-service, Margharitis A. & Co",
    "wof:placetype":"venue"
},
  "geometry": {"coordinates":[8.798503,47.326855],"type":"Point"}
}