{
  "type": "Feature",
  "properties": {
    "iso:country":"CH",
    "sg:address":"Z\u00fcrichstrasse 38",
    "sg:city":"Br\u00fcttisellen",
    "sg:orig_category":"Detailhandel mit M\u00f6beln U Haushaltsgegenst\u00e4nden Verlegen von Fussboden",
    "sg:phone":"+41 71 636 11 68",
    "sg:postcode":"8306",
    "sg:province":"Z\u00fcrich",
    "wof:name":"Rast Paul",
    "wof:placetype":"venue"
},
  "geometry": {"coordinates":[9.1694402695,47.5813865662],"type":"Point"}
}