{
  "type": "Feature",
  "properties": {
    "iso:country":"CH",
    "sg:address":"Manessestrasse 97",
    "sg:city":"Z\u00fcrich",
    "sg:orig_category":"Detailhandel mit Tabakwaren",
    "sg:phone":"+41 14621584",
    "sg:postcode":"8045",
    "sg:province":"Z\u00fcrich",
    "wof:name":"Alice Wehrli Zigarrengesch\u00e4ft",
    "wof:placetype":"venue"
},
  "geometry": {"coordinates":[8.5221424103,47.3641777039],"type":"Point"}
}