{
  "type": "Feature",
  "properties": {
    "iso:country":"CH",
    "sg:address":"Fraum\u00fcnsterstrasse 11",
    "sg:city":"Z\u00fcrich",
    "sg:orig_category":"Sonstige pers\u00f6nliche Dienstleistungen",
    "sg:phone":"+41 12112526",
    "sg:postcode":"8001",
    "sg:province":"Z\u00fcrich",
    "wof:name":"Hmd Consulting Dreher Hugo M.",
    "wof:placetype":"venue"
},
  "geometry": {"coordinates":[8.5406799316,47.3687438965],"type":"Point"}
}