{
  "type": "Feature",
  "properties": {
    "iso:country":"CH",
    "sg:address":"Kupfergasse 10",
    "sg:city":"Chur",
    "sg:orig_category":"Grosshandel mit Tabakwaren",
    "sg:postcode":"7000",
    "sg:province":"Graubunden",
    "wof:name":"D\u00e9lez Michel",
    "wof:placetype":"venue"
},
  "geometry": {"coordinates":[7.020275116,46.1201057434],"type":"Point"}
}