{
  "type": "Feature",
  "properties": {
    "iso:country":"CH",
    "sg:address":"1744 Ch\u00e9nens Case Postale 11",
    "sg:city":"Ch\u00e9nens",
    "sg:orig_category":"Instandhaltung U Reparatur von Automobilen",
    "sg:phone":"+41 26 477 15 15",
    "sg:postcode":"1744",
    "sg:province":"Fribourg",
    "wof:name":"Garage-carrosserie Du Ch\u00eane, Giuliani Vincent",
    "wof:placetype":"venue"
},
  "geometry": {"coordinates":[6.9955101013,46.7425613403],"type":"Point"}
}