{
  "type": "Feature",
  "properties": {
    "iso:country":"CH",
    "sg:address":"Rheinfelsstrasse 1",
    "sg:city":"Chur",
    "sg:orig_category":"Handels-H\u00e4user U Gesellschaften",
    "sg:phone":"+41 800 188 999",
    "sg:postcode":"7000",
    "sg:province":"Graubunden",
    "wof:name":"Freecall24 Gmbh",
    "wof:placetype":"venue"
},
  "geometry": {"coordinates":[9.5129718781,46.8509368896],"type":"Point"}
}