{
  "type": "Feature",
  "properties": {
    "iso:country":"CH",
    "sg:address":"Z\u00fcrichstrasse 5",
    "sg:city":"F\u00e4llanden",
    "sg:orig_category":"Herstellung von Reiseartikeln, Leder U Sattlerwaren",
    "sg:phone":"+41 26 652 14 86",
    "sg:postcode":"8117",
    "sg:province":"Z\u00fcrich",
    "wof:name":"Gremaud Jean-fran\u00e7ois.",
    "wof:placetype":"venue"
},
  "geometry": {"coordinates":[6.9225969315,46.6997261047],"type":"Point"}
}