{
  "type": "Feature",
  "properties": {
    "iso:country":"CH",
    "sg:address":"Via St. Maria 27 6596 Gordola. Postfach Caselle Postale 148",
    "sg:city":"Gordola",
    "sg:orig_category":"Berufliche Weiterbildung, Erwachsenenbildung",
    "sg:phone":"+41 91 745 01 31",
    "sg:postcode":"6596",
    "sg:province":"Ticino",
    "wof:name":"Centro Formazione Profess. Della Ssic,sezione Ticino",
    "wof:placetype":"venue"
},
  "geometry": {"coordinates":[8.865675,46.174908],"type":"Point"}
}