{
  "type": "Feature",
  "properties": {
    "iso:country":"CH",
    "sg:address":"F\u00fcrfelderstrasse 36",
    "sg:city":"Riehen",
    "sg:orig_category":"Wirtschafts- and Arbeitgeberverb\u00e4nde",
    "sg:phone":"+41 31 311 76 28",
    "sg:postcode":"4125",
    "sg:province":"Basel-Stadt",
    "wof:name":"Schweiz.zahn\u00e4rzte-gesellsch.",
    "wof:placetype":"venue"
},
  "geometry": {"coordinates":[7.4471549988,46.9472122192],"type":"Point"}
}