{
  "type": "Feature",
  "properties": {
    "iso:country":"CH",
    "sg:address":"Avenue Eug\u00e8ne Lance 11",
    "sg:city":"Grand-lancy",
    "sg:orig_category":"Detailhandel mit Metallwaren, Anstrichmitteln, Glaswaren, Bau U Heimwerkerbedarf",
    "sg:phone":"+41 32964160",
    "sg:postcode":"1212",
    "sg:province":"Gen\u00e8ve",
    "wof:name":"Alsa F. Aeschbacher",
    "wof:placetype":"venue"
},
  "geometry": {"coordinates":[7.1808519363,47.0276451111],"type":"Point"}
}