{
  "type": "Feature",
  "properties": {
    "iso:country":"CH",
    "sg:address":"Rietstrasse 157",
    "sg:city":"Schaffhausen",
    "sg:orig_category":"Unclassifiable Establishments",
    "sg:postcode":"8200",
    "sg:province":"Schaffhausen",
    "wof:name":"Restaurant Risiko, Boss Doris",
    "wof:placetype":"venue"
},
  "geometry": {"coordinates":[7.729932785,46.7567596436],"type":"Point"}
}