{
  "type": "Feature",
  "properties": {
    "iso:country":"CH",
    "sg:address":"Dorfstrasse 48",
    "sg:city":"Engelberg",
    "sg:classifiers":[
        {
            "category":"Travel",
            "subcategory":"Hotels & Motels",
            "type":"Entertainment"
        }
    ],
    "sg:phone":"+41 41 637 32 32",
    "sg:postcode":"6390",
    "sg:province":"Obwalden",
    "sg:tags":[
        "hotels",
        "mit",
        "restaurant"
    ],
    "wof:name":"Hotel Central Ag",
    "wof:placetype":"venue"
},
  "geometry": {"coordinates":[8.4004192352,46.8200645447],"type":"Point"}
}