{
  "type": "Feature",
  "properties": {
    "iso:country":"CH",
    "sg:address":"G\u00fcterstrasse 1",
    "sg:city":"Feuerthalen",
    "sg:classifiers":[
        {
            "category":"Insurance",
            "subcategory":"Insurance Agent",
            "type":"Services"
        }
    ],
    "sg:phone":"+41 32 351 33 33",
    "sg:postcode":"8245",
    "sg:province":"Z\u00fcrich",
    "sg:tags":[
        "versicherungsagenturen",
        "-broker"
    ],
    "wof:name":"Winterthur-versicherungen Agentur",
    "wof:placetype":"venue"
},
  "geometry": {"coordinates":[7.372148037,47.1399879456],"type":"Point"}
}