{
  "type": "Feature",
  "properties": {
    "addr:full":"Bahnhofstrasse 73 Hallau Schaffhausen 8215",
    "addr:housenumber":"73",
    "addr:postcode":"8215",
    "addr:street":"Bahnhofstrasse",
    "iso:country":"CH",
    "sg:address":"Bahnhofstrasse 73",
    "sg:city":"Hallau",
    "sg:orig_category":"Arztpraxen",
    "sg:phone":"+41 52 681 31 05",
    "sg:postcode":"8215",
    "sg:province":"Schaffhausen",
    "wof:name":"Dres Med. R. & U. Craviolini Spezial\u00e4rzte Fmh",
    "wof:placetype":"venue"
},
  "geometry": {"coordinates":[8.457762,47.692833],"type":"Point"}
}