{
  "type": "Feature",
  "properties": {
    "iso:country":"CH",
    "sg:address":"Z\u00fcrichstrasse 67",
    "sg:city":"Adliswil",
    "sg:orig_category":"Dauerkulturbau",
    "sg:phone":"+41 17106757",
    "sg:postcode":"8134",
    "sg:province":"Z\u00fcrich",
    "wof:name":"Adv Acad\u00e9mie Du Vin Sa",
    "wof:placetype":"venue"
},
  "geometry": {"coordinates":[8.528593,47.321091],"type":"Point"}
}