{
  "type": "Feature",
  "properties": {
    "iso:country":"CH",
    "sg:address":"Dienerstrasse 43",
    "sg:city":"Z\u00fcrich",
    "sg:orig_category":"Arztpraxen",
    "sg:phone":"+41 12421140",
    "sg:postcode":"8004",
    "sg:province":"Z\u00fcrich",
    "wof:name":"Dr.med.urs Schneider Arzt F.allgemeine Medizin Fmh",
    "wof:placetype":"venue"
},
  "geometry": {"coordinates":[8.526858,47.378468],"type":"Point"}
}