{
  "type": "Feature",
  "properties": {
    "addr:full":"Via Nassa 9 Lugano Ticino 6900",
    "addr:housenumber":"9",
    "addr:postcode":"6900",
    "addr:street":"Via Nassa",
    "iso:country":"CH",
    "sg:address":"Via Nassa 9",
    "sg:city":"Lugano",
    "sg:orig_category":"Detailhandel mit Brot, Back U S\u00fcsswaren",
    "sg:phone":"+41 91 922 09 61",
    "sg:postcode":"6900",
    "sg:province":"Ticino",
    "wof:name":"Giuseppe Vanini Sa",
    "wof:placetype":"venue"
},
  "geometry": {"coordinates":[8.950015,46.002697],"type":"Point"}
}