{
  "type": "Feature",
  "properties": {
    "iso:country":"CH",
    "sg:address":"Ramiswilerstrasse 713",
    "sg:city":"M\u00fcmliswil",
    "sg:orig_category":"Darlehenskassen U Raiffeisenbanken",
    "sg:phone":"+41 71 995 50 66",
    "sg:postcode":"4717",
    "sg:province":"Solothurn",
    "wof:name":"Raiffeisenbank Nesslau-krummenau-stein",
    "wof:placetype":"venue"
},
  "geometry": {"coordinates":[9.194419,47.229698],"type":"Point"}
}