{
  "type": "Feature",
  "properties": {
    "iso:country":"CH",
    "sg:address":"Hofstrasse 1a",
    "sg:city":"Zug",
    "sg:orig_category":"Kauf U Verkauf von Immobilien auf eigene Rechnung",
    "sg:postcode":"6300",
    "sg:province":"Zug",
    "wof:name":"Veritas Immobilien Ag",
    "wof:placetype":"venue"
},
  "geometry": {"coordinates":[8.5158700943,47.1615180969],"type":"Point"}
}