{
  "type": "Feature",
  "properties": {
    "iso:country":"CH",
    "sg:address":"Seestrasse 690",
    "sg:city":"Meilen",
    "sg:orig_category":"Pensionskassen",
    "sg:phone":"+41 19233447",
    "sg:postcode":"8706",
    "sg:province":"Z\u00fcrich",
    "wof:name":"Gisler Kaspar Und Doris-stiftung",
    "wof:placetype":"venue"
},
  "geometry": {"coordinates":[8.6479177475,47.2677307129],"type":"Point"}
}