{
  "type": "Feature",
  "properties": {
    "addr:full":"Grubenstrasse 4 Urdorf Z\u00fcrich 8902",
    "addr:housenumber":"4",
    "addr:postcode":"8902",
    "addr:street":"Grubenstrasse",
    "iso:country":"CH",
    "sg:address":"Grubenstrasse 4",
    "sg:city":"Urdorf",
    "sg:orig_category":"Berufsorganisationen",
    "sg:postcode":"8902",
    "sg:province":"Z\u00fcrich",
    "wof:name":"Genossenschaft Gewerbehaus Urdorf.",
    "wof:placetype":"venue"
},
  "geometry": {"coordinates":[8.42012,47.392197],"type":"Point"}
}