{
  "type": "Feature",
  "properties": {
    "iso:country":"CH",
    "sg:address":"Sonnenterrasse 15",
    "sg:city":"Greppen",
    "sg:orig_category":"Gartenbau",
    "sg:phone":"+41 79 211 06 11",
    "sg:postcode":"6404",
    "sg:province":"Luzern",
    "wof:name":"Galliker G. Gartenbau Ag",
    "wof:placetype":"venue"
},
  "geometry": {"coordinates":[8.4284849167,47.0524787903],"type":"Point"}
}