{
  "type": "Feature",
  "properties": {
    "iso:country":"CH",
    "sg:address":"Galgacker 117",
    "sg:city":"Amsoldingen",
    "sg:orig_category":"Maurerarbeiten Verlegen von Fliesen U Platten",
    "sg:phone":"+41 33 341 13 43",
    "sg:postcode":"3633",
    "sg:province":"Bern",
    "wof:name":"Bernhard Peter Maurer-& Plattengesch\u00e4ft",
    "wof:placetype":"venue"
},
  "geometry": {"coordinates":[7.5870900154,46.7299804688],"type":"Point"}
}