{
  "type": "Feature",
  "properties": {
    "iso:country":"CH",
    "sg:address":"Ebnatstrasse 111",
    "sg:city":"Schaffhausen",
    "sg:orig_category":"Allgemeiner Hoch U Tiefbau",
    "sg:phone":"+41 52 631 11 11",
    "sg:postcode":"8200",
    "sg:province":"Schaffhausen",
    "wof:name":"Fischer Georg Haustechnik Ag",
    "wof:placetype":"venue"
},
  "geometry": {"coordinates":[8.649926,47.709827],"type":"Point"}
}