{
  "type": "Feature",
  "properties": {
    "iso:country":"CH",
    "sg:address":"Hardgutstrasse 18",
    "sg:city":"Z\u00fcrich",
    "sg:orig_category":"Interessenvertretungen",
    "sg:postcode":"8000",
    "sg:province":"Z\u00fcrich",
    "wof:name":"Wegunterhaltsgenossenschaft Matten-dorf",
    "wof:placetype":"venue"
},
  "geometry": {"coordinates":[7.3968458176,46.5076065063],"type":"Point"}
}