{
  "type": "Feature",
  "properties": {
    "iso:country":"CH",
    "sg:address":"Dorfstrasse 56 8706 Meilen. Postfach 421",
    "sg:city":"Meilen",
    "sg:orig_category":"Bauschreinerei Herstellung von Konstruktionsteilen, Fertigbauteilen U Ausbauelementen aus Holz",
    "sg:phone":"+41 19235240",
    "sg:postcode":"8706",
    "sg:province":"Z\u00fcrich",
    "wof:name":"Schreinerei Pernet Inh. Mathis Hugo",
    "wof:placetype":"venue"
},
  "geometry": {"coordinates":[8.640927,47.269966],"type":"Point"}
}