{
  "type": "Feature",
  "properties": {
    "addr:full":"Hofenstrasse 27 Kronb\u00fchl 9302",
    "addr:housenumber":"27",
    "addr:postcode":"9302",
    "addr:street":"Hofenstrasse",
    "iso:country":"CH",
    "sg:address":"Hofenstrasse 27",
    "sg:city":"Kronb\u00fchl",
    "sg:orig_category":"Allgemeiner Hochbau Strassenbau",
    "sg:phone":"+41 55 282 36 68",
    "sg:postcode":"9302",
    "wof:name":"Walo Bertschinger Ag Bauunternehmung",
    "wof:placetype":"venue"
},
  "geometry": {"coordinates":[8.930541,47.2407],"type":"Point"}
}