{
  "type": "Feature",
  "properties": {
    "iso:country":"CH",
    "sg:address":"R\u00fctistrasse 76",
    "sg:city":"D\u00fcbendorf",
    "sg:orig_category":"Erbringung von Dienstleistungen f\u00fcr Unternehmen",
    "sg:postcode":"8600",
    "sg:province":"Z\u00fcrich",
    "wof:name":"Reinhard Design Ag",
    "wof:placetype":"venue"
},
  "geometry": {"coordinates":[8.6114997864,47.3701858521],"type":"Point"}
}