{
  "type": "Feature",
  "properties": {
    "iso:country":"CH",
    "sg:address":"8184",
    "sg:city":"Bachenb\u00fclach",
    "sg:orig_category":"Sportvereine Sch\u00fctzen",
    "sg:phone":"+41 18691515",
    "sg:postcode":"8184",
    "sg:province":"Z\u00fcrich",
    "wof:name":"Schiessverein",
    "wof:placetype":"venue"
},
  "geometry": {"coordinates":[8.5445899963,47.5010681152],"type":"Point"}
}