{
  "type": "Feature",
  "properties": {
    "iso:country":"CH",
    "sg:address":"Steinacker 6",
    "sg:city":"Gempen",
    "sg:orig_category":"Abbruch U Sprenggewerbe, Erdbewegungsarbeiten",
    "sg:phone":"+41 61 701 11 39",
    "sg:postcode":"4145",
    "sg:province":"Solothurn",
    "wof:name":"Wenger Aushub Und Abbruch",
    "wof:placetype":"venue"
},
  "geometry": {"coordinates":[7.657694,47.472031],"type":"Point"}
}