{
  "type": "Feature",
  "properties": {
    "iso:country":"CH",
    "sg:address":"3533",
    "sg:city":"Bowil",
    "sg:orig_category":"Wasserversorgung",
    "sg:phone":"+41 31 302 24 40",
    "sg:postcode":"3533",
    "sg:province":"Bern",
    "wof:name":"Wasserversorgung Der Gemeinde Bremgarten",
    "wof:placetype":"venue"
},
  "geometry": {"coordinates":[7.4361581802,46.9776229858],"type":"Point"}
}