{
  "type": "Feature",
  "properties": {
    "iso:country":"CH",
    "sg:address":"B\u00e4ulerwisenstrasse 3",
    "sg:city":"Glattbrugg",
    "sg:orig_category":"Grosshandel mit Datenverarbeitungsger\u00e4ten Softwareentwicklung U beratung",
    "sg:phone":"+41 32 652 43 81",
    "sg:postcode":"8152",
    "sg:province":"Z\u00fcrich",
    "wof:name":"Chd Consulting Del\u00e9vaux Christoph Computerhard- U. -software; Handel Usw",
    "wof:placetype":"venue"
},
  "geometry": {"coordinates":[7.3640727997,47.1803474426],"type":"Point"}
}