{
  "type": "Feature",
  "properties": {
    "iso:country":"CH",
    "sg:address":"Les Friques",
    "sg:city":"Villars-le-grand",
    "sg:classifiers":[
        {
            "category":"Professional",
            "subcategory":"Engineering",
            "type":"Services"
        }
    ],
    "sg:phone":"+41 26 677 11 48",
    "sg:postcode":"1584",
    "sg:province":"Vaud",
    "sg:tags":[
        "machine",
        "-",
        "mechanical"
    ],
    "wof:name":"J Bovet Sa",
    "wof:placetype":"venue"
},
  "geometry": {"coordinates":[6.9901652336,46.9052009583],"type":"Point"}
}