{
  "type": "Feature",
  "properties": {
    "iso:country":"CH",
    "sg:address":"Weinfelderstrasse 37",
    "sg:city":"Amriswil",
    "sg:orig_category":"Unclassifiable Establishments",
    "sg:postcode":"8580",
    "sg:province":"Thurgau",
    "wof:name":"Crea-design Wenger",
    "wof:placetype":"venue"
},
  "geometry": {"coordinates":[9.291311264,47.5447540283],"type":"Point"}
}