{
  "type": "Feature",
  "properties": {
    "iso:country":"CH",
    "sg:address":"Unterdorfstrasse",
    "sg:city":"Berikon",
    "sg:orig_category":"Sonstige mit der Informatik verbundene T\u00e4tigkeiten",
    "sg:phone":"+41 56 633 97 89",
    "sg:postcode":"8965",
    "sg:province":"Aargau",
    "wof:name":"Circleweb Tanner P. Edv-dienstleistungen",
    "wof:placetype":"venue"
},
  "geometry": {"coordinates":[8.3737249374,47.3511314392],"type":"Point"}
}