{
  "type": "Feature",
  "properties": {
    "iso:country":"CH",
    "sg:address":"Hauptstrasse 35 2533 Evilard. Postfach",
    "sg:city":"Evilard",
    "sg:orig_category":"Non-Classified Establishments",
    "sg:phone":"+41 32 322 45 11",
    "sg:postcode":"2533",
    "sg:province":"Bern",
    "wof:name":"Funic Transport Von Personen, Gep\u00e4ck U. G\u00fctern Als Konzessionierte U. Freie Transportunternehmerin Usw.",
    "wof:placetype":"venue"
},
  "geometry": {"coordinates":[7.2276802063,47.1464614868],"type":"Point"}
}