{
  "type": "Feature",
  "properties": {
    "iso:country":"CH",
    "sg:address":"T\u00f6distrasse 17",
    "sg:city":"Dietlikon",
    "sg:orig_category":"Sonstiger Grosshandel",
    "sg:postcode":"8305",
    "sg:province":"Z\u00fcrich",
    "wof:name":"Mewil-star, Meier & Co.",
    "wof:placetype":"venue"
},
  "geometry": {"coordinates":[8.6165618896,47.4191246033],"type":"Point"}
}