{
  "type": "Feature",
  "properties": {
    "iso:country":"CH",
    "sg:address":"Mattfeldstrasse 4",
    "sg:city":"Rickenbach",
    "sg:classifiers":[
        {
            "category":"Professional",
            "subcategory":"Advertising",
            "type":"Services"
        }
    ],
    "sg:phone":"+41 71 913 47 11",
    "sg:postcode":"9532",
    "sg:province":"Thurgau",
    "sg:tags":[
        "postcard"
    ],
    "wof:name":"Zehnder Print Ag",
    "wof:placetype":"venue"
},
  "geometry": {"coordinates":[-75.973755,40.4305],"type":"Point"}
}