{
  "type": "Feature",
  "properties": {
    "iso:country":"CH",
    "sg:address":"Staatsstrasse",
    "sg:city":"Grabs",
    "sg:orig_category":"Instandhaltung U Reparatur von Automobilen",
    "sg:phone":"+41 62 291 31 21",
    "sg:postcode":"9472",
    "sg:province":"St. Gallen",
    "wof:name":"Garage K\u00fcng Ag D\u00e4niken",
    "wof:placetype":"venue"
},
  "geometry": {"coordinates":[7.9842047691,47.3579711914],"type":"Point"}
}