{
  "type": "Feature",
  "properties": {
    "iso:country":"CH",
    "sg:address":"Rorschacher Strasse 63 9003 St. Gallen. Postfach 72",
    "sg:city":"St.gallen",
    "sg:orig_category":"Rechts U Unternehmensberatung, Buchf\u00fchrung Wirtschaftspr\u00fcfung, Steuerberatung U Treuhand",
    "sg:phone":"+41 71 243 34 34",
    "sg:postcode":"9000",
    "sg:province":"St. Gallen",
    "wof:name":"Obt Ag",
    "wof:placetype":"venue"
},
  "geometry": {"coordinates":[9.3737096786,47.4263916016],"type":"Point"}
}