{
  "type": "Feature",
  "properties": {
    "iso:country":"CH",
    "sg:address":"Bundentalstrasse 3",
    "sg:city":"Schlieren",
    "sg:orig_category":"Finanzierungsinstitutionen",
    "sg:postcode":"8952",
    "sg:province":"Z\u00fcrich",
    "wof:name":"Heidemann Consulting",
    "wof:placetype":"venue"
},
  "geometry": {"coordinates":[8.4275379181,47.3929214478],"type":"Point"}
}