{
  "type": "Feature",
  "properties": {
    "addr:full":"Im Sch\u00f6rli 4 D\u00fcbendorf Z\u00fcrich 8600",
    "addr:housenumber":"4",
    "addr:postcode":"8600",
    "addr:street":"Im Schoerli;Zuerich",
    "iso:country":"CH",
    "sg:address":"Im Sch\u00f6rli 4",
    "sg:city":"D\u00fcbendorf",
    "sg:classifiers":[
        {
            "category":"Home & Garden",
            "subcategory":"Furniture",
            "type":"Retail Goods"
        }
    ],
    "sg:phone":"+41 18021212",
    "sg:postcode":"8600",
    "sg:province":"Z\u00fcrich",
    "sg:tags":[
        "aluminium"
    ],
    "wof:name":"Lehni Ag",
    "wof:placetype":"venue"
},
  "geometry": {"coordinates":[8.639803,47.394894],"type":"Point"}
}