{
  "type": "Feature",
  "properties": {
    "iso:country":"CH",
    "sg:address":"Piazza San Pietro 10",
    "sg:city":"Ascona",
    "sg:orig_category":"Detailhandel mit Lederwaren U Reiseartikeln",
    "sg:phone":"+41 91 791 36 26",
    "sg:postcode":"6612",
    "sg:province":"Ticino",
    "wof:name":"Gian Paolo Brunoni Boutique Star's Pelletteria",
    "wof:placetype":"venue"
},
  "geometry": {"coordinates":[8.7681589127,46.1548728943],"type":"Point"}
}