{
  "type": "Feature",
  "properties": {
    "iso:country":"CH",
    "sg:address":"2943",
    "sg:city":"Vendlincourt",
    "sg:orig_category":"Herstellung von k\u00e4lte U lufttechnischen Erzeugnissen f\u00fcr gewerbliche Zwecke",
    "sg:postcode":"2943",
    "sg:province":"Jura",
    "wof:name":"Chauffage - Sanitaire Corbat R\u00e9gis.",
    "wof:placetype":"venue"
},
  "geometry": {"coordinates":[7.1505169868,47.4510688782],"type":"Point"}
}