{
  "type": "Feature",
  "properties": {
    "iso:country":"CH",
    "sg:address":"Gubelstrasse 15",
    "sg:city":"Zug",
    "sg:orig_category":"Architektur U Ingenieurb\u00fcros",
    "sg:postcode":"6300",
    "sg:province":"Zug",
    "wof:name":"Frimi Dienstleistungs Und Beratungs-ag",
    "wof:placetype":"venue"
},
  "geometry": {"coordinates":[8.312817,46.987144],"type":"Point"}
}