{
  "type": "Feature",
  "properties": {
    "iso:country":"CH",
    "sg:address":"Knonauerstrasse 56",
    "sg:city":"Cham",
    "sg:orig_category":"Vermietung von Automobilen",
    "sg:phone":"+41 21 635 71 86",
    "sg:postcode":"6330",
    "sg:province":"Zug",
    "wof:name":"Rolf Mauerhofer Rmc Carevasion",
    "wof:placetype":"venue"
},
  "geometry": {"coordinates":[6.5897340775,46.5291900635],"type":"Point"}
}