{
  "type": "Feature",
  "properties": {
    "iso:country":"CH",
    "sg:address":"Rieterstrasse 57",
    "sg:city":"Z\u00fcrich",
    "sg:orig_category":"Wirtschaftspr\u00fcfung, Steuerberatung U Treuhand",
    "sg:postcode":"8038",
    "sg:province":"Z\u00fcrich",
    "wof:name":"Z\u00fcnti Joseph M., Steuer- & Finanzberatung",
    "wof:placetype":"venue"
},
  "geometry": {"coordinates":[8.5263271332,47.3570213318],"type":"Point"}
}