{
  "type": "Feature",
  "properties": {
    "iso:country":"CH",
    "sg:address":"Rue Gustave Amweg 7",
    "sg:city":"Porrentruy",
    "sg:orig_category":"D\u00e4mmung gegen K\u00e4lte, W\u00e4rme, Schall U Ersch\u00fctterung Stukkateurgewerbe, Gipserei U Verputzerei",
    "sg:phone":"+41 32 466 91 52",
    "sg:postcode":"2900",
    "sg:province":"Jura",
    "wof:name":"Entreprise De Gypserie-peinture Meyer Michel, Succ. D'emile Lapaire",
    "wof:placetype":"venue"
},
  "geometry": {"coordinates":[7.0764417648,47.4179954529],"type":"Point"}
}