{
  "type": "Feature",
  "properties": {
    "iso:country":"CH",
    "sg:address":"Oberdorf 1",
    "sg:city":"Buttisholz",
    "sg:orig_category":"Nationale Postdienste",
    "sg:phone":"+41 41 928 14 21",
    "sg:postcode":"6018",
    "sg:province":"Luzern",
    "wof:name":"Die Schweizerische Post",
    "wof:placetype":"venue"
},
  "geometry": {"coordinates":[8.0946378708,47.1145935059],"type":"Point"}
}