{
  "type": "Feature",
  "properties": {
    "iso:country":"CH",
    "sg:address":"Hofstrasse 101",
    "sg:city":"Wetzikon",
    "sg:orig_category":"High-Precision Cylindrical Grinding Services",
    "sg:phone":"+41 19322184",
    "sg:postcode":"8620",
    "sg:province":"Z\u00fcrich",
    "wof:name":"Paul Wyss",
    "wof:placetype":"venue"
},
  "geometry": {"coordinates":[8.7945261002,47.3101501465],"type":"Point"}
}