{
  "type": "Feature",
  "properties": {
    "iso:country":"CH",
    "sg:address":"Industriering 43",
    "sg:city":"Lyss",
    "sg:orig_category":"Architektur U Ingenieurb\u00fcros",
    "sg:phone":"+41 32 386 70 80",
    "sg:postcode":"3250",
    "sg:province":"Bern",
    "wof:name":"Homologation Consulting Matter",
    "wof:placetype":"venue"
},
  "geometry": {"coordinates":[7.305722,47.087769],"type":"Point"}
}