{
  "type": "Feature",
  "properties": {
    "iso:country":"CH",
    "sg:address":"Rue De La Poya 41",
    "sg:city":"Conthey",
    "sg:classifiers":[
        {
            "category":"Restaurant",
            "type":"Food & Drink"
        }
    ],
    "sg:phone":"+41 21 695 25 00",
    "sg:postcode":"1964",
    "sg:province":"Valais",
    "wof:name":"Caf\u00e9 De L'abordage",
    "wof:placetype":"venue"
},
  "geometry": {"coordinates":[6.5707111359,46.5138168335],"type":"Point"}
}