{
  "type": "Feature",
  "properties": {
    "iso:country":"CH",
    "sg:address":"Hauptstrasse 257",
    "sg:city":"Hellikon",
    "sg:orig_category":"Religi\u00f6se Vereinigungen divers Vereine Gemeinn\u00fctzige",
    "sg:phone":"+41 61 871 04 16",
    "sg:postcode":"4316",
    "sg:province":"Aargau",
    "wof:name":"Christkath.frauenverein",
    "wof:placetype":"venue"
},
  "geometry": {"coordinates":[7.9283838272,47.5052947998],"type":"Point"}
}