{
  "type": "Feature",
  "properties": {
    "iso:country":"CH",
    "sg:address":"Loorenstrasse 11",
    "sg:city":"Dietlikon",
    "sg:orig_category":"Grosshandel mit sonstigen Konsumg\u00fctern Grosshandel mit sonstigen Maschinen U Ausr\u00fcstungen f\u00fcr Indust",
    "sg:phone":"+41 18341522",
    "sg:postcode":"8305",
    "sg:province":"Z\u00fcrich",
    "wof:name":"Lis Ly-impex Service",
    "wof:placetype":"venue"
},
  "geometry": {"coordinates":[8.6143302917,47.4256782532],"type":"Point"}
}