{
  "type": "Feature",
  "properties": {
    "iso:country":"CH",
    "sg:address":"Tomenrain 3 8605 Gutenswil. Postfach",
    "sg:city":"Z\u00fcrich",
    "sg:orig_category":"Softwareentwicklung U beratung",
    "sg:postcode":"8057",
    "sg:province":"Z\u00fcrich",
    "wof:name":"Seneca Consulting Group Ag",
    "wof:placetype":"venue"
},
  "geometry": {"coordinates":[8.7155704498,47.3862609863],"type":"Point"}
}