{
  "type": "Feature",
  "properties": {
    "iso:country":"CH",
    "sg:address":"Samstagernstrasse 31",
    "sg:city":"Wollerau",
    "sg:classifiers":[
        {
            "category":"Professional",
            "subcategory":"Business Services",
            "type":"Services"
        }
    ],
    "sg:phone":"+41 17845311",
    "sg:postcode":"8832",
    "sg:province":"Schwyz",
    "sg:tags":[
        "marketing",
        "agency"
    ],
    "wof:name":"Duft Marketing Gmbh",
    "wof:placetype":"venue"
},
  "geometry": {"coordinates":[8.7098865509,47.1902122498],"type":"Point"}
}