{
  "type": "Feature",
  "properties": {
    "iso:country":"CH",
    "sg:address":"3148",
    "sg:city":"Lanzenh\u00e4usern",
    "sg:orig_category":"Schulpflegen",
    "sg:postcode":"3148",
    "sg:province":"Bern",
    "wof:name":"Primarschulkommission Der Gemeinde Steinhof So",
    "wof:placetype":"venue"
},
  "geometry": {"coordinates":[7.6868100166,47.1614303589],"type":"Point"}
}