{
  "type": "Feature",
  "properties": {
    "iso:country":"CH",
    "sg:address":"Bramenstrasse 4 8184 Bachenb\u00fclach. Postfach",
    "sg:city":"Bachenb\u00fclach",
    "sg:orig_category":"Grosshandel mit Werkzeugmaschinen Grosshandel mit sonstigen Maschinen U Ausr\u00fcstungen f\u00fcr Industrie, ",
    "sg:phone":"+41 18605577",
    "sg:postcode":"8184",
    "sg:province":"Z\u00fcrich",
    "wof:name":"Auer Walter Ag",
    "wof:placetype":"venue"
},
  "geometry": {"coordinates":[8.5402488708,47.5042228699],"type":"Point"}
}