{
  "type": "Feature",
  "properties": {
    "iso:country":"CH",
    "sg:address":"6102 Blatten (malters). Postfach",
    "sg:city":"Malters",
    "sg:orig_category":"Herstellung von Reiseartikeln, Leder U Sattlerwaren",
    "sg:postcode":"6102",
    "sg:province":"Luzern",
    "wof:name":"Brugger W.",
    "wof:placetype":"venue"
},
  "geometry": {"coordinates":[8.2251195908,47.0404815674],"type":"Point"}
}