{
  "type": "Feature",
  "properties": {
    "iso:country":"CH",
    "sg:address":"Faubourg De L'h\u00f4pital 44",
    "sg:city":"Neuch\u00e2tel",
    "sg:classifiers":[
        {
            "category":"Professional",
            "subcategory":"Employment Agencies",
            "type":"Services"
        }
    ],
    "sg:phone":"+41 32 725 02 20",
    "sg:postcode":"2000",
    "sg:province":"Neuch\u00e2tel",
    "sg:tags":[
        "personal",
        "u",
        "stellenvermittlung"
    ],
    "wof:name":"Magnetic Emplois Sa",
    "wof:placetype":"venue"
},
  "geometry": {"coordinates":[6.9363808632,46.9942970276],"type":"Point"}
}