{
  "type": "Feature",
  "properties": {
    "iso:country":"CH",
    "sg:address":"Aarauerstrasse 39",
    "sg:city":"Rupperswil",
    "sg:orig_category":"Herstellung von konfektionierten Textilwaren ohne Bekleidung",
    "sg:phone":"+41 79 431 14 03",
    "sg:postcode":"5102",
    "sg:province":"Aargau",
    "wof:name":"Kessler Hans Ag",
    "wof:placetype":"venue"
},
  "geometry": {"coordinates":[8.8875751495,47.195022583],"type":"Point"}
}