{
  "type": "Feature",
  "properties": {
    "iso:country":"CH",
    "sg:address":"Gassa Sut\u00f2 43",
    "sg:city":"Domat/ems",
    "sg:orig_category":"Grafikateliers, Design Lackiererei",
    "sg:phone":"+41 81 630 38 40",
    "sg:postcode":"7013",
    "sg:province":"Graubunden",
    "wof:name":"Giorgio Fetz Lackierungen",
    "wof:placetype":"venue"
},
  "geometry": {"coordinates":[9.453666687,46.8351402283],"type":"Point"}
}