{
  "type": "Feature",
  "properties": {
    "addr:full":"Rue Rosselet-challandes 4 Sonceboz-sombeval Bern 2605",
    "addr:housenumber":"4",
    "addr:postcode":"2605",
    "addr:street":"Rue Rosselet-Challandes",
    "iso:country":"CH",
    "sg:address":"Rue Rosselet-challandes 4",
    "sg:city":"Sonceboz-sombeval",
    "sg:orig_category":"Allgemeiner Hoch U Tiefbau",
    "sg:phone":"+41 81 756 49 65",
    "sg:postcode":"2605",
    "sg:province":"Bern",
    "wof:name":"Saseco Graf Hans",
    "wof:placetype":"venue"
},
  "geometry": {"coordinates":[9.482451,47.166],"type":"Point"}
}