{
  "type": "Feature",
  "properties": {
    "iso:country":"CH",
    "sg:address":"Dorfstrasse 35",
    "sg:city":"Baar",
    "sg:orig_category":"Schreib U \u00dcbersetzungsb\u00fcros",
    "sg:phone":"+41 41 760 42 55",
    "sg:postcode":"6340",
    "sg:province":"Zug",
    "wof:name":"Aac-multimedia Uebersetzungen Gmbh",
    "wof:placetype":"venue"
},
  "geometry": {"coordinates":[8.5232839584,47.1934394836],"type":"Point"}
}