{
  "type": "Feature",
  "properties": {
    "iso:country":"CH",
    "sg:address":"Via Delle Scuole 12 6900 Lugano Casella Postale 83 6906 Lugano",
    "sg:city":"Caselle",
    "sg:orig_category":"Grosshandel mit Fleisch U Fleischwaren Grosshandel mit Nahrungsmitteln, Getr\u00e4nken U Tabakwaren",
    "sg:phone":"+41 55 415 56 56",
    "sg:postcode":"6",
    "wof:name":"Delimpex Ag",
    "wof:placetype":"venue"
},
  "geometry": {"coordinates":[8.7781352997,47.2013778687],"type":"Point"}
}