{
  "type": "Feature",
  "properties": {
    "addr:full":"Rte De Champ\u00e9ry Val-d'illiez Valais 1873",
    "addr:postcode":"1873",
    "addr:street":"Rte De Champe\u0301Ry",
    "iso:country":"CH",
    "sg:address":"Rte De Champ\u00e9ry",
    "sg:city":"Val-d'illiez",
    "sg:orig_category":"Bauschreinerei Herstellung von Konstruktionsteilen, Fertigbauteilen U Ausbauelementen aus Holz",
    "sg:phone":"+41 24 477 11 30",
    "sg:postcode":"1873",
    "sg:province":"Valais",
    "wof:name":"Gex-fabry Emmanuel",
    "wof:placetype":"venue"
},
  "geometry": {"coordinates":[6.87068,46.179401],"type":"Point"}
}