{
  "type": "Feature",
  "properties": {
    "addr:full":"Via Cassarinetta 29 Lugano Ticino 6900",
    "addr:housenumber":"29",
    "addr:postcode":"6900",
    "addr:street":"Via Cassarinetta",
    "iso:country":"CH",
    "sg:address":"Via Cassarinetta 29",
    "sg:city":"Lugano",
    "sg:orig_category":"Architektur U Ingenieurb\u00fcros Architekturb\u00fcros",
    "sg:phone":"+41 91 993 14 77",
    "sg:postcode":"6900",
    "sg:province":"Ticino",
    "wof:name":"Mario Campi Architetto Fas & Associati Sa",
    "wof:placetype":"venue"
},
  "geometry": {"coordinates":[8.94096,45.991673],"type":"Point"}
}