{
  "type": "Feature",
  "properties": {
    "iso:country":"CH",
    "sg:address":"Tourronde Chemin De 6",
    "sg:city":"Pully",
    "sg:orig_category":"Unternehmensberatung",
    "sg:phone":"+41 21 729 32 88",
    "sg:postcode":"1009",
    "sg:province":"Vaud",
    "wof:name":"Joye Denise, Conseils, Organisation Et Gestion De Soci\u00e9t\u00e9s",
    "wof:placetype":"venue"
},
  "geometry": {"coordinates":[6.6485619545,46.5074996948],"type":"Point"}
}