{
  "type": "Feature",
  "properties": {
    "iso:country":"CH",
    "sg:address":"Zweierstrasse 165",
    "sg:city":"Z\u00fcrich",
    "sg:orig_category":"Detailhandel mit Ton U Bildtr\u00e4gern",
    "sg:phone":"+41 21 845 42 24",
    "sg:postcode":"8003",
    "sg:province":"Z\u00fcrich",
    "wof:name":"Marco Rochat Commerce De Disques Vinyl Shop",
    "wof:placetype":"venue"
},
  "geometry": {"coordinates":[6.2288379669,46.606010437],"type":"Point"}
}