{
  "type": "Feature",
  "properties": {
    "iso:country":"CH",
    "sg:address":"Saint-hubert Chemin",
    "sg:city":"Sion",
    "sg:orig_category":"Instandhaltung U Reparatur von Automobilen",
    "sg:phone":"+41 27 327 30 70",
    "sg:postcode":"1950",
    "sg:province":"Valais",
    "wof:name":"Urfer Claude Sa",
    "wof:placetype":"venue"
},
  "geometry": {"coordinates":[7.3525881767,46.222492218],"type":"Point"}
}