{
  "type": "Feature",
  "properties": {
    "iso:country":"CH",
    "sg:address":"Untere Weidstrasse 12",
    "sg:city":"Rotkreuz",
    "sg:orig_category":"Unclassifiable Establishments",
    "sg:postcode":"6343",
    "sg:province":"Zug",
    "wof:name":"Mixage Boutique Gmbh",
    "wof:placetype":"venue"
},
  "geometry": {"coordinates":[8.4305324554,47.1364250183],"type":"Point"}
}