{
  "type": "Feature",
  "properties": {
    "iso:country":"CH",
    "sg:address":"Maienzugstrasse 32",
    "sg:city":"Aarau",
    "sg:orig_category":"Grosshandel mit sonstigen Maschinen U Ausr\u00fcstungen f\u00fcr Industrie, Handel U Schiffahrt",
    "sg:postcode":"5000",
    "sg:province":"Aargau",
    "wof:name":"Technology-transfer Vranjesevic Dragan",
    "wof:placetype":"venue"
},
  "geometry": {"coordinates":[8.0567541122,47.3991966248],"type":"Point"}
}