{
  "type": "Feature",
  "properties": {
    "iso:country":"CH",
    "sg:address":"M\u00fcliholzstrasse 2",
    "sg:city":"M\u00fchleberg",
    "sg:orig_category":"Herstellung von Konstruktionsteilen, Fertigbauteilen U Ausbauelementen aus Holz",
    "sg:phone":"+41 31 859 39 59",
    "sg:postcode":"3203",
    "sg:province":"Bern",
    "wof:name":"Schreinerei Gerber H. R.",
    "wof:placetype":"venue"
},
  "geometry": {"coordinates":[7.5291180611,47.0173873901],"type":"Point"}
}