{
  "type": "Feature",
  "properties": {
    "iso:country":"CH",
    "sg:address":"Biberiststrasse 27",
    "sg:city":"Derendingen",
    "sg:orig_category":"Maler U Glasergewerbe",
    "sg:postcode":"4552",
    "sg:province":"Solothurn",
    "wof:name":"Malergesch\u00e4ft E. W\u00e4lti",
    "wof:placetype":"venue"
},
  "geometry": {"coordinates":[7.5822401047,47.1862792969],"type":"Point"}
}