{
  "type": "Feature",
  "properties": {
    "iso:country":"CH",
    "sg:address":"Tschuopisstrasse 7",
    "sg:city":"Altendorf",
    "sg:orig_category":"Bauschreinerei Herstellung von Konstruktionsteilen, Fertigbauteilen U Ausbauelementen aus Holz",
    "sg:phone":"+41 55 442 10 44",
    "sg:postcode":"8852",
    "sg:province":"Schwyz",
    "wof:name":"Fleischmann Fensterbau & Co",
    "wof:placetype":"venue"
},
  "geometry": {"coordinates":[8.848705,47.185112],"type":"Point"}
}