{
  "type": "Feature",
  "properties": {
    "iso:country":"CH",
    "sg:address":"Dozwilerstrasse 46",
    "sg:city":"Kesswil",
    "sg:orig_category":"Unclassifiable Establishments",
    "sg:phone":"+41 56 611 01 03",
    "sg:postcode":"8593",
    "sg:province":"Thurgau",
    "wof:name":"Knupp Drogerie Ag",
    "wof:placetype":"venue"
},
  "geometry": {"coordinates":[8.2717924118,47.3504600525],"type":"Point"}
}