{
  "type": "Feature",
  "properties": {
    "iso:country":"CH",
    "sg:address":"Steinweg 10",
    "sg:city":"Lyss",
    "sg:orig_category":"Grosshandel mit Eisenwaren sowie Installationsbedarf f\u00fcr Gas, Wasser U Heizung Herstellung von Schle",
    "sg:phone":"+41 32 384 88 08",
    "sg:postcode":"3250",
    "sg:province":"Bern",
    "wof:name":"Sma Ag",
    "wof:placetype":"venue"
},
  "geometry": {"coordinates":[7.3041100502,47.0777206421],"type":"Point"}
}