{
  "type": "Feature",
  "properties": {
    "addr:full":"In Der Rehweid 8 Pfaffhausen 8117 F\u00e4llanden. Postfach Binz Z\u00fcrich 8122",
    "addr:housenumber":"8",
    "addr:postcode":"8117 faellanden. postfach;8122",
    "addr:street":"In Der Rehweid",
    "iso:country":"CH",
    "sg:address":"In Der Rehweid 8 Pfaffhausen 8117 F\u00e4llanden. Postfach",
    "sg:city":"Binz",
    "sg:orig_category":"Architektur U Ingenieurb\u00fcros",
    "sg:postcode":"8122",
    "sg:province":"Z\u00fcrich",
    "wof:name":"Weber, Fritz, Dipl. Elektroingenieur Eth.",
    "wof:placetype":"venue"
},
  "geometry": {"coordinates":[8.639795,47.37149],"type":"Point"}
}