{
  "type": "Feature",
  "properties": {
    "iso:country":"CH",
    "sg:address":"1794",
    "sg:city":"Salvenach",
    "sg:orig_category":"Sonstiger Fachdetailhandel mit Nahrungsmitteln, Getr\u00e4nken U Tabak in Verkaufsr\u00e4umen",
    "sg:phone":"+41 26 674 12 38",
    "sg:postcode":"1794",
    "sg:province":"Fribourg",
    "wof:name":"Wieland Peter",
    "wof:placetype":"venue"
},
  "geometry": {"coordinates":[7.1499700546,46.9124183655],"type":"Point"}
}