{
  "type": "Feature",
  "properties": {
    "iso:country":"CH",
    "sg:address":"H\u00f6fle 47",
    "sg:city":"Balzers",
    "sg:classifiers":[
        {
            "category":"Restaurant",
            "type":"Food & Drink"
        }
    ],
    "sg:phone":"+423 384 12 01",
    "sg:postcode":"9496",
    "wof:name":"Restaurant Engel",
    "wof:placetype":"venue"
},
  "geometry": {"coordinates":[9.5069847107,47.0682792664],"type":"Point"}
}