{
  "type": "Feature",
  "properties": {
    "iso:country":"CH",
    "sg:address":"Stansstaderstrasse 49a 6370 Stans. Postfach",
    "sg:city":"Stans",
    "sg:orig_category":"Architektur U Ingenieurb\u00fcros",
    "sg:phone":"+41 61 712 02 02",
    "sg:postcode":"6371",
    "sg:province":"Nidwalden",
    "wof:name":"Up Universal Project Ag",
    "wof:placetype":"venue"
},
  "geometry": {"coordinates":[7.597107,47.507706],"type":"Point"}
}