{
  "type": "Feature",
  "properties": {
    "iso:country":"CH",
    "sg:address":"Landenbergerstrasse 1",
    "sg:city":"D\u00f6rflingen",
    "sg:orig_category":"G\u00fcterbef\u00f6rderung im Strassenverkehr",
    "sg:phone":"+41 52 657 28 56",
    "sg:postcode":"8239",
    "sg:province":"Schaffhausen",
    "wof:name":"Walter B\u00fcrgin Transporte",
    "wof:placetype":"venue"
},
  "geometry": {"coordinates":[8.7234373093,47.711605072],"type":"Point"}
}