{
  "type": "Feature",
  "properties": {
    "iso:country":"CH",
    "sg:address":"Gewerbestrasse 8",
    "sg:city":"Cham",
    "sg:orig_category":"D\u00e4mmung gegen K\u00e4lte, W\u00e4rme, Schall U Ersch\u00fctterung",
    "sg:phone":"+41 56 624 42 70",
    "sg:postcode":"6330",
    "sg:province":"Zug",
    "wof:name":"Lambda D\u00e4mmtechnik Ag Cham",
    "wof:placetype":"venue"
},
  "geometry": {"coordinates":[8.4724349976,47.1890296936],"type":"Point"}
}