{
  "type": "Feature",
  "properties": {
    "iso:country":"CH",
    "sg:address":"Route De Frontenex 122 1200 Gen\u00e8ve. Postfach",
    "sg:city":"Gen\u00e8ve",
    "sg:orig_category":"RESTAURANTS: TEA-ROOMS",
    "sg:phone":"+41 21 968 17 17",
    "sg:postcode":"1208",
    "sg:province":"Gen\u00e8ve",
    "wof:name":"Frossard Jean-pierre",
    "wof:placetype":"venue"
},
  "geometry": {"coordinates":[6.9261350632,46.39818573],"type":"Point"}
}