{
  "type": "Feature",
  "properties": {
    "iso:country":"CH",
    "sg:address":"Fenkrieden",
    "sg:city":"Aettenschwil",
    "sg:classifiers":[
        {
            "category":"Restaurant",
            "type":"Food & Drink"
        }
    ],
    "sg:phone":"+41 56 245 15 70",
    "sg:postcode":"5645",
    "sg:province":"Aargau",
    "wof:name":"Restaurant Waldheim",
    "wof:placetype":"venue"
},
  "geometry": {"coordinates":[8.3718385696,47.1843795776],"type":"Point"}
}