{
  "type": "Feature",
  "properties": {
    "iso:country":"CH",
    "sg:address":"Gotthardstrasse 62",
    "sg:city":"Thalwil",
    "sg:orig_category":"Detailhandel mit Getr\u00e4nken Detailhandel mit Waren verschiedener Art, Hauptrichtung Nahrungsmittel",
    "sg:phone":"+41 17208790",
    "sg:postcode":"8800",
    "sg:province":"Z\u00fcrich",
    "wof:name":"Franco De Biase Darjo-delikatessen Weinhandel",
    "wof:placetype":"venue"
},
  "geometry": {"coordinates":[8.5616550446,47.298160553],"type":"Point"}
}