{
  "type": "Feature",
  "properties": {
    "iso:country":"CH",
    "sg:address":"Hauptstrasse 41",
    "sg:city":"K\u00f6lliken",
    "sg:orig_category":"G\u00fcterbef\u00f6rderung im Strassenverkehr",
    "sg:postcode":"5742",
    "sg:province":"Aargau",
    "wof:name":"Hans Suter",
    "wof:placetype":"venue"
},
  "geometry": {"coordinates":[8.0245141983,47.3346366882],"type":"Point"}
}