{
  "type": "Feature",
  "properties": {
    "iso:country":"CH",
    "sg:address":"Pany 7243 Pany. Postfach",
    "sg:city":"Pany",
    "sg:orig_category":"Herstellung von Konstruktionsteilen, Fertigbauteilen U Ausbauelementen aus Holz",
    "sg:postcode":"7243",
    "sg:province":"Graubunden",
    "wof:name":"Conzett-baumann Peter Schreinereiarbeiten",
    "wof:placetype":"venue"
},
  "geometry": {"coordinates":[9.7704133987,46.9283599854],"type":"Point"}
}