{
  "type": "Feature",
  "properties": {
    "iso:country":"CH",
    "sg:address":"Albulastrasse 37",
    "sg:city":"Chur",
    "sg:orig_category":"Wirtschaftspr\u00fcfung, Steuerberatung U Treuhand",
    "sg:phone":"+41 81 250 61 90",
    "sg:postcode":"7000",
    "sg:province":"Graubunden",
    "wof:name":"Pernollet Denise Buchhaltungen + Steuerberatung",
    "wof:placetype":"venue"
},
  "geometry": {"coordinates":[9.5200443268,46.8592567444],"type":"Point"}
}