{
  "type": "Feature",
  "properties": {
    "iso:country":"CH",
    "sg:address":"Z\u00fcrcherstrasse",
    "sg:city":"Tuggen",
    "sg:orig_category":"Kauf U Verkauf von Immobilien auf eigene Rechnung",
    "sg:phone":"+41 55 465 65 62",
    "sg:postcode":"8856",
    "sg:province":"Schwyz",
    "wof:name":"Bamert Hugo Ag Immobilien",
    "wof:placetype":"venue"
},
  "geometry": {"coordinates":[8.9400501251,47.2023162842],"type":"Point"}
}