{
  "type": "Feature",
  "properties": {
    "iso:country":"CH",
    "sg:address":"Gundeldingerstrasse 171 4053 Basel. Postfach",
    "sg:city":"Basel",
    "sg:orig_category":"Fachdetailhandel mit pharmazeutischen Produkten",
    "sg:phone":"+41 61 361 45 00",
    "sg:postcode":"4051",
    "sg:province":"Basel-Stadt",
    "wof:name":"Brc Biomedical Research Consultants Ag Klinische Pr\u00fcfungen M. Pharmaz. Pr\u00e4paraten; Planung, Organisation Usw",
    "wof:placetype":"venue"
},
  "geometry": {"coordinates":[7.5893268585,47.5413627625],"type":"Point"}
}