{
  "type": "Feature",
  "properties": {
    "iso:country":"CH",
    "sg:address":"Hertizentrum 8 6300 Zug. Postfach 3356",
    "sg:city":"Zug",
    "sg:orig_category":"Grosshandel mit Nahrungsmitteln, Getr\u00e4nken U Tabakwaren Schlachten ohne Schlachten von Gefl\u00fcgel",
    "sg:phone":"+41 41 711 42 53",
    "sg:postcode":"6303",
    "sg:province":"Zug",
    "wof:name":"Smit A. & Zoon Ag",
    "wof:placetype":"venue"
},
  "geometry": {"coordinates":[8.5063419342,47.1783447266],"type":"Point"}
}