{
  "type": "Feature",
  "properties": {
    "addr:full":"Bahnhofplatz 2 Baden Aargau 5400",
    "addr:housenumber":"2",
    "addr:postcode":"5400",
    "addr:street":"Bahnhofplatz",
    "iso:country":"CH",
    "sg:address":"Bahnhofplatz 2",
    "sg:city":"Baden",
    "sg:classifiers":[
        {
            "category":"Banks & Credit Unions",
            "subcategory":"Bank",
            "type":"Services"
        }
    ],
    "sg:phone":"+41 56 203 01 01",
    "sg:postcode":"5400",
    "sg:province":"Aargau",
    "wof:name":"Aargauische Kantonalbank",
    "wof:placetype":"venue"
},
  "geometry": {"coordinates":[8.308693,47.476639],"type":"Point"}
}