{
  "type": "Feature",
  "properties": {
    "iso:country":"CH",
    "sg:address":"Spillstatt",
    "sg:city":"Grindelwald",
    "sg:orig_category":"Verarbeitung von Milch Verwertung von Milch",
    "sg:phone":"+41 33 853 12 92",
    "sg:postcode":"3818",
    "sg:province":"Bern",
    "wof:name":"Gertsch Peter",
    "wof:placetype":"venue"
},
  "geometry": {"coordinates":[8.0272884369,46.6262817383],"type":"Point"}
}