{
  "type": "Feature",
  "properties": {
    "iso:country":"CH",
    "sg:address":"Postgasse 45",
    "sg:city":"Interlaken",
    "sg:orig_category":"Sonstiger spezialisierter Hoch U Tiefbau",
    "sg:phone":"+41 33 822 63 67",
    "sg:postcode":"3800",
    "sg:province":"Bern",
    "wof:name":"Express-kundenmaurerbetrieb, Deda Zef",
    "wof:placetype":"venue"
},
  "geometry": {"coordinates":[7.8540859222,46.6880187988],"type":"Point"}
}