{
  "type": "Feature",
  "properties": {
    "iso:country":"CH",
    "sg:address":"8424 Embrach. Postfach 379",
    "sg:city":"Embrach",
    "sg:orig_category":"Sportvereine Ballsport Fussball",
    "sg:phone":"+41 18650084",
    "sg:postcode":"8424",
    "sg:province":"Z\u00fcrich",
    "wof:name":"Fc Embrach",
    "wof:placetype":"venue"
},
  "geometry": {"coordinates":[8.5988798141,47.5108795166],"type":"Point"}
}