{
  "type": "Feature",
  "properties": {
    "addr:full":"Winkelstrasse 19 Laupen Z\u00fcrich 8637",
    "addr:housenumber":"19",
    "addr:postcode":"8637",
    "addr:street":"Winkelstrasse",
    "iso:country":"CH",
    "sg:address":"Winkelstrasse 19",
    "sg:city":"Laupen",
    "sg:classifiers":[
        {
            "category":"Manufacturing",
            "subcategory":"Paper Products",
            "type":"Manufacturing & Wholesale Goods"
        }
    ],
    "sg:phone":"+41 55 246 61 05",
    "sg:postcode":"8637",
    "sg:province":"Z\u00fcrich",
    "sg:tags":[
        "cardboard",
        "package"
    ],
    "wof:name":"Tradepack Ag",
    "wof:placetype":"venue"
},
  "geometry": {"coordinates":[8.933226,47.26165],"type":"Point"}
}