{
  "type": "Feature",
  "properties": {
    "iso:country":"CH",
    "sg:address":"Jupiterstrasse 25",
    "sg:city":"Bern",
    "sg:orig_category":"Erschliessung von Grundst\u00fccken",
    "sg:phone":"+41 31 941 19 25",
    "sg:postcode":"3015",
    "sg:province":"Bern",
    "wof:name":"Wohnbaugen.murifeld",
    "wof:placetype":"venue"
},
  "geometry": {"coordinates":[7.4818811417,46.9404067993],"type":"Point"}
}