{
  "type": "Feature",
  "properties": {
    "iso:country":"CH",
    "sg:address":"Husackerstrasse 5",
    "sg:city":"N\u00fcrensdorf",
    "sg:orig_category":"Grosshandel mit Holz U Baustoffen Wirtschaftspr\u00fcfung, Steuerberatung U Treuhand",
    "sg:phone":"+41 18370400",
    "sg:postcode":"8309",
    "sg:province":"Z\u00fcrich",
    "wof:name":"Franceschetti Ag",
    "wof:placetype":"venue"
},
  "geometry": {"coordinates":[8.6633043289,47.4605140686],"type":"Point"}
}