{
  "type": "Feature",
  "properties": {
    "iso:country":"CH",
    "sg:address":"Siblinger Randen",
    "sg:city":"Siblingen",
    "sg:classifiers":[
        {
            "category":"Restaurant",
            "type":"Food & Drink"
        }
    ],
    "sg:phone":"+41 52 685 27 37",
    "sg:postcode":"8225",
    "sg:province":"Schaffhausen",
    "wof:name":"Restaurant Randenhaus",
    "wof:placetype":"venue"
},
  "geometry": {"coordinates":[8.5010242462,47.7244415283],"type":"Point"}
}