{
  "type": "Feature",
  "properties": {
    "iso:country":"CH",
    "sg:address":"Notkerstrasse 10",
    "sg:city":"St.gallen",
    "sg:orig_category":"Grosshandel mit Maschinen U Ausr\u00fcstungen Herstellung von k\u00e4lte U lufttechnischen Erzeugnissen f\u00fcr ge",
    "sg:phone":"+41 71 243 18 18",
    "sg:postcode":"9000",
    "sg:province":"St. Gallen",
    "wof:name":"Fm Filtermaschinenbau Ag",
    "wof:placetype":"venue"
},
  "geometry": {"coordinates":[9.3801469803,47.4281578064],"type":"Point"}
}