{
  "type": "Feature",
  "properties": {
    "iso:country":"CH",
    "sg:address":"Oberalpstrasse 28",
    "sg:city":"Chur",
    "sg:orig_category":"Architektur U Ingenieurb\u00fcros Architekturb\u00fcros",
    "sg:phone":"+41 81 250 34 04",
    "sg:postcode":"7000",
    "sg:province":"Graubunden",
    "wof:name":"Architekturb\u00fcro Linda Kant",
    "wof:placetype":"venue"
},
  "geometry": {"coordinates":[9.52433,46.854641],"type":"Point"}
}