{
  "type": "Feature",
  "properties": {
    "iso:country":"CH",
    "sg:address":"Tivoli",
    "sg:city":"Spreitenbach",
    "sg:orig_category":"Gymnastik U Fitnesszentren",
    "sg:phone":"+41 56 402 00 10",
    "sg:postcode":"8957",
    "sg:province":"Aargau",
    "wof:name":"Fitness Emotion Ag Gesundheitsorientierte Trainingeszentren; F\u00fchrung. Warenhandel",
    "wof:placetype":"venue"
},
  "geometry": {"coordinates":[8.3656835556,47.4180450439],"type":"Point"}
}