{
  "type": "Feature",
  "properties": {
    "iso:country":"CH",
    "sg:address":"Bahnhofstrasse 48",
    "sg:city":"Z\u00fcrich",
    "sg:orig_category":"Detailhandel mit Uhren U Schmuck Fachdetailhandel in Verkaufsr\u00e4umen",
    "sg:phone":"+41 21 944 15 23",
    "sg:postcode":"8001",
    "sg:province":"Z\u00fcrich",
    "wof:name":"Raymond Bellisi Horlogerie Bijouterie",
    "wof:placetype":"venue"
},
  "geometry": {"coordinates":[6.858877182,46.45470047],"type":"Point"}
}