{
  "type": "Feature",
  "properties": {
    "iso:country":"CH",
    "sg:address":"Feldstrasse 12",
    "sg:city":"D\u00e4nikon",
    "sg:orig_category":"Fresh Vegetables, Lettuces, And Potatoes",
    "sg:phone":"+41 18473400",
    "sg:postcode":"8114",
    "sg:province":"Z\u00fcrich",
    "wof:name":"Leuenberger K\u00fcchenfertige Produkte Ag",
    "wof:placetype":"venue"
},
  "geometry": {"coordinates":[8.4049654007,47.4481544495],"type":"Point"}
}