{
  "type": "Feature",
  "properties": {
    "iso:country":"CH",
    "sg:address":"8752",
    "sg:city":"N\u00e4fels",
    "sg:orig_category":"Vorschulen, Kinderg\u00e4rten",
    "sg:phone":"+41 55 612 20 50",
    "sg:postcode":"8752",
    "sg:province":"Glarus",
    "wof:name":"Kindergarten Dorf I & Ii",
    "wof:placetype":"venue"
},
  "geometry": {"coordinates":[9.0625753403,47.0999641418],"type":"Point"}
}