{
  "type": "Feature",
  "properties": {
    "iso:country":"CH",
    "sg:address":"Maupas Rue Du 10 1004 Lausanne. Postfach",
    "sg:city":"Lausanne",
    "sg:orig_category":"Detailhandel mit elektrischen Haushalts-,Radio U Fernsehger\u00e4ten sowie Musikinstrumenten",
    "sg:phone":"+41 21 646 72 05",
    "sg:postcode":"1003",
    "sg:province":"Vaud",
    "wof:name":"Fontaine Adolphe Quincaillerie, Outillage Et Articles De M\u00e9nage; Comm",
    "wof:placetype":"venue"
},
  "geometry": {"coordinates":[6.62687397,46.5242881775],"type":"Point"}
}