{
  "type": "Feature",
  "properties": {
    "iso:country":"CH",
    "sg:address":"B\u00f6zingenstrasse 167",
    "sg:city":"Biel/bienne",
    "sg:orig_category":"Detailhandel mit Blumen U Pflanzen",
    "sg:phone":"+41 32 341 72 20",
    "sg:postcode":"2504",
    "sg:province":"Bern",
    "wof:name":"Margrit Struchen Blumen Ritter",
    "wof:placetype":"venue"
},
  "geometry": {"coordinates":[7.265918,47.152191],"type":"Point"}
}