{
  "type": "Feature",
  "properties": {
    "iso:country":"CH",
    "sg:address":"Hinterdorfstrasse 9",
    "sg:city":"Schwyz",
    "sg:orig_category":"RESTAURANTS: TEA-ROOMS",
    "sg:postcode":"6430",
    "sg:province":"Schwyz",
    "wof:name":"Rickenbacher Peter",
    "wof:placetype":"venue"
},
  "geometry": {"coordinates":[8.6281871796,47.0197029114],"type":"Point"}
}