{
  "type": "Feature",
  "properties": {
    "iso:country":"CH",
    "sg:address":"Alte Strasse 19",
    "sg:city":"Dittingen",
    "sg:orig_category":"Herstellung von Ausbauelementen aus Metall Herstellung von Betonerzeugnissen f\u00fcr den Bau",
    "sg:phone":"+41 61 761 34 44",
    "sg:postcode":"4243",
    "sg:province":"Basel-Landschaft",
    "wof:name":"Huber Ag, Briefkastenanlagen",
    "wof:placetype":"venue"
},
  "geometry": {"coordinates":[7.5035200119,47.4362831116],"type":"Point"}
}