{
  "type": "Feature",
  "properties": {
    "iso:country":"CH",
    "sg:address":"Hinterhagweg",
    "sg:city":"Gr\u00e4nichen",
    "sg:orig_category":"Herstellung von Werkzeugen",
    "sg:phone":"+41 62 842 21 77",
    "sg:postcode":"5722",
    "sg:province":"Aargau",
    "wof:name":"Brunner Kurt Ag.",
    "wof:placetype":"venue"
},
  "geometry": {"coordinates":[8.097746,47.358856],"type":"Point"}
}