{
  "type": "Feature",
  "properties": {
    "iso:country":"CH",
    "sg:address":"Feerstrasse 8",
    "sg:city":"Aarau",
    "sg:orig_category":"Pensionskassen",
    "sg:phone":"+41 62 822 16 22",
    "sg:postcode":"5000",
    "sg:province":"Aargau",
    "wof:name":"Pensionskasse Der R\u00f6misch-katholischen Landeskirche Des Kantons Aargau",
    "wof:placetype":"venue"
},
  "geometry": {"coordinates":[8.0509710312,47.3932609558],"type":"Point"}
}