{
  "type": "Feature",
  "properties": {
    "addr:full":"Via Vedeggio 6814 Lamone. Postfach Cadempino Ticino 6814",
    "addr:postcode":"6814 lamone. postfach;6814",
    "addr:street":"Via Vedeggio",
    "iso:country":"CH",
    "sg:address":"Via Vedeggio 6814 Lamone. Postfach",
    "sg:city":"Cadempino",
    "sg:orig_category":"Datenverarbeitungsdienste Radio U Fernsehanstalten",
    "sg:phone":"+41 91 950 86 16",
    "sg:postcode":"6814",
    "sg:province":"Ticino",
    "wof:name":"Spark Digital Factory Sa Prodotti Multimediali; Produzione Specializzata E Professionale Ecc",
    "wof:placetype":"venue"
},
  "geometry": {"coordinates":[8.930297,46.039398],"type":"Point"}
}