{
  "type": "Feature",
  "properties": {
    "iso:country":"CH",
    "sg:address":"Dornacherstrasse 48 4500 Solothurn. Postfach",
    "sg:city":"Solothurn",
    "sg:orig_category":"Personenbef\u00f6rderung im Linienverkehr zu Land Personenbef\u00f6rderung im Nahverkehr",
    "sg:phone":"+41 32 622 37 22",
    "sg:postcode":"4501",
    "sg:province":"Solothurn",
    "wof:name":"Busbetrieb Solothurn Und Umgebung",
    "wof:placetype":"venue"
},
  "geometry": {"coordinates":[7.5430521965,47.2044258118],"type":"Point"}
}