{
  "type": "Feature",
  "properties": {
    "iso:country":"CH",
    "sg:address":"Platz 7312 Pf\u00e4fers. Postfach",
    "sg:city":"V\u00e4ttis",
    "sg:orig_category":"G\u00fcterbef\u00f6rderung im Strassenverkehr",
    "sg:phone":"+41 81 306 11 51",
    "sg:postcode":"7315",
    "sg:province":"St. Gallen",
    "wof:name":"Bonderer Gebr\u00fcder, Autotransporte",
    "wof:placetype":"venue"
},
  "geometry": {"coordinates":[9.5004520416,46.9888420105],"type":"Point"}
}