{
  "type": "Feature",
  "properties": {
    "iso:country":"CH",
    "sg:address":"Bachtobelstrasse 3",
    "sg:city":"Ebmatingen",
    "sg:orig_category":"Non-Classified Establishments",
    "sg:postcode":"8123",
    "sg:province":"Z\u00fcrich",
    "wof:name":"Clean Team Carelli",
    "wof:placetype":"venue"
},
  "geometry": {"coordinates":[8.6409158707,47.3525466919],"type":"Point"}
}