{
  "type": "Feature",
  "properties": {
    "iso:country":"CH",
    "sg:address":"Kirchgasse 4",
    "sg:city":"Olten",
    "sg:orig_category":"Detailhandel mit Schuhen",
    "sg:phone":"+41 62 212 72 31",
    "sg:postcode":"4600",
    "sg:province":"Solothurn",
    "wof:name":"Karl V\u00f6gele Ag",
    "wof:placetype":"venue"
},
  "geometry": {"coordinates":[7.9017419815,47.3499488831],"type":"Point"}
}