{
  "type": "Feature",
  "properties": {
    "iso:country":"CH",
    "sg:address":"Bahnhofplatz 12",
    "sg:city":"Winterthur",
    "sg:orig_category":"Unternehmensberatung",
    "sg:phone":"+41 71 447 52 82",
    "sg:postcode":"8401",
    "sg:province":"Z\u00fcrich",
    "wof:name":"Saurer Management Ag",
    "wof:placetype":"venue"
},
  "geometry": {"coordinates":[8.7248458862,47.5006942749],"type":"Point"}
}