{
  "type": "Feature",
  "properties": {
    "iso:country":"CH",
    "sg:address":"Rue Saint-germain 5",
    "sg:city":"Bussigny-lausanne",
    "sg:orig_category":"Arztpraxen",
    "sg:phone":"+41 21 701 22 33",
    "sg:postcode":"1030",
    "sg:province":"Vaud",
    "wof:name":"Dr M\u00e9d. Michel Corth\u00e9sy M\u00e9decin G\u00e9n\u00e9raliste",
    "wof:placetype":"venue"
},
  "geometry": {"coordinates":[6.550207,46.550251],"type":"Point"}
}