{
  "type": "Feature",
  "properties": {
    "iso:country":"CH",
    "sg:address":"Eggb\u00fchlstrasse 20 8050 Z\u00fcrich. Postfach 8050 Z\u00fcrich",
    "sg:city":"Zust",
    "sg:orig_category":"Datenverarbeitungsdienste Softwareentwicklung U beratung",
    "sg:phone":"+41 13053030",
    "sg:postcode":"50",
    "wof:name":"Cubus Ag",
    "wof:placetype":"venue"
},
  "geometry": {"coordinates":[8.542979,47.41637],"type":"Point"}
}