{
  "type": "Feature",
  "properties": {
    "addr:full":"Rohrerstrasse 3 5000 Aarau. Postfach Aarau Aargau 5001",
    "addr:housenumber":"3",
    "addr:postcode":"5000 aarau. postfach;5001",
    "addr:street":"Rohrerstrasse",
    "iso:country":"CH",
    "sg:address":"Rohrerstrasse 3 5000 Aarau. Postfach",
    "sg:city":"Aarau",
    "sg:orig_category":"Architektur U Ingenieurb\u00fcros",
    "sg:phone":"+41 41 811 50 38",
    "sg:postcode":"5001",
    "sg:province":"Aargau",
    "wof:name":"Ces Bauingenieur Ag Stalder + Wey",
    "wof:placetype":"venue"
},
  "geometry": {"coordinates":[8.632342,47.027618],"type":"Point"}
}