{
  "type": "Feature",
  "properties": {
    "iso:country":"CH",
    "sg:address":"Les Zittes 3966 Chalais. Postfach",
    "sg:city":"Chalais",
    "sg:orig_category":"Instandhaltung U Reparatur von Automobilen",
    "sg:phone":"+41 32 331 85 29",
    "sg:postcode":"3966",
    "sg:province":"Valais",
    "wof:name":"Garage Carrosserie Hetzel Jean-pierre",
    "wof:placetype":"venue"
},
  "geometry": {"coordinates":[7.5153598785,46.2706031799],"type":"Point"}
}