{
  "type": "Feature",
  "properties": {
    "iso:country":"CH",
    "sg:address":"Route De Lavaux 103",
    "sg:city":"Lutry",
    "sg:orig_category":"Herstellung von konfektionierten Textilwaren ohne Bekleidung",
    "sg:phone":"+41 21 791 45 46",
    "sg:postcode":"1095",
    "sg:province":"Vaud",
    "wof:name":"Wagni\u00e8res Pierre, Stores",
    "wof:placetype":"venue"
},
  "geometry": {"coordinates":[6.6826000214,46.5044403076],"type":"Point"}
}