{
  "type": "Feature",
  "properties": {
    "iso:country":"CH",
    "sg:address":"R\u00f6ntgenstrasse 6 8005 Z\u00fcrich. Postfach",
    "sg:city":"Z\u00fcrich",
    "sg:orig_category":"Herstellung von elektrischen Lampen U Leuchten",
    "sg:phone":"+41 32 751 22 05",
    "sg:postcode":"8031",
    "sg:province":"Z\u00fcrich",
    "wof:name":"Jelosil Quartz Lampes Sa",
    "wof:placetype":"venue"
},
  "geometry": {"coordinates":[7.0782690048,47.0592651367],"type":"Point"}
}