{
  "type": "Feature",
  "properties": {
    "addr:full":"Hornstrasse 9a Ermatingen Thurgau 8272",
    "addr:housenumber":"9a",
    "addr:postcode":"8272",
    "addr:street":"Hornstrasse",
    "iso:country":"CH",
    "sg:address":"Hornstrasse 9a",
    "sg:city":"Ermatingen",
    "sg:classifiers":[
        {
            "category":"Professional",
            "subcategory":"Accounting & Tax Preparation",
            "type":"Services"
        }
    ],
    "sg:phone":"+41 71 663 70 70",
    "sg:postcode":"8272",
    "sg:province":"Thurgau",
    "sg:tags":[
        "balance"
    ],
    "wof:name":"Ammann Waagen & Co",
    "wof:placetype":"venue"
},
  "geometry": {"coordinates":[9.086172,47.672047],"type":"Point"}
}