{
  "type": "Feature",
  "properties": {
    "iso:country":"CH",
    "sg:address":"Route De Ch\u00e2tillon 10",
    "sg:city":"Courrendlin",
    "sg:orig_category":"Arztpraxen",
    "sg:phone":"+41 32 435 55 55",
    "sg:postcode":"2830",
    "sg:province":"Jura",
    "wof:name":"Dr M\u00e9d. Bruno Boillat M\u00e9decin Sp\u00e9cialiste",
    "wof:placetype":"venue"
},
  "geometry": {"coordinates":[7.371751,47.338631],"type":"Point"}
}