{
  "type": "Feature",
  "properties": {
    "iso:country":"CH",
    "sg:address":"Lindenstrasse 7 6005 Luzern. Postfach",
    "sg:city":"Luzern",
    "sg:orig_category":"Herstellung von k\u00e4lte U lufttechnischen Erzeugnissen f\u00fcr gewerbliche Zwecke Sanit\u00e4r U Heizungsinstal",
    "sg:phone":"+41 41 310 84 84",
    "sg:postcode":"6002",
    "sg:province":"Luzern",
    "wof:name":"Huber Hans K. Ag",
    "wof:placetype":"venue"
},
  "geometry": {"coordinates":[8.3043241501,47.0415763855],"type":"Point"}
}