{
  "type": "Feature",
  "properties": {
    "iso:country":"CH",
    "sg:address":"Durisolstrasse 3",
    "sg:city":"Villmergen",
    "sg:orig_category":"Fachdetailhandel in Verkaufsr\u00e4umen",
    "sg:phone":"+41 56 622 86 31",
    "sg:postcode":"5612",
    "sg:province":"Aargau",
    "wof:name":"Sportivo Shop Gmbh",
    "wof:placetype":"venue"
},
  "geometry": {"coordinates":[8.2513828278,47.3545570374],"type":"Point"}
}