{
  "type": "Feature",
  "properties": {
    "iso:country":"CH",
    "sg:address":"1483",
    "sg:city":"Vesin",
    "sg:orig_category":"Bauschreinerei Herstellung von Konstruktionsteilen, Fertigbauteilen U Ausbauelementen aus Holz",
    "sg:phone":"+41 26 665 11 93",
    "sg:postcode":"1483",
    "sg:province":"Fribourg",
    "wof:name":"Maillard Maurice, Menuiserie",
    "wof:placetype":"venue"
},
  "geometry": {"coordinates":[6.87349,46.80854],"type":"Point"}
}