{
  "type": "Feature",
  "properties": {
    "addr:full":"Rue De Lausanne 91 Gen\u00e8ve Gen\u00e8ve 1202",
    "addr:housenumber":"91",
    "addr:postcode":"1202",
    "addr:street":"Rue De Lausanne",
    "iso:country":"CH",
    "sg:address":"Rue De Lausanne 91",
    "sg:city":"Gen\u00e8ve",
    "sg:orig_category":"B\u00e4ckereien Konditoreien",
    "sg:phone":"+41 22 732 78 80",
    "sg:postcode":"1202",
    "sg:province":"Gen\u00e8ve",
    "wof:name":"Georges Loichet Boulangerie-p\u00e2tisserie",
    "wof:placetype":"venue"
},
  "geometry": {"coordinates":[6.148004,46.217831],"type":"Point"}
}