{
  "type": "Feature",
  "properties": {
    "iso:country":"CH",
    "sg:address":"St. Galler Strasse 3",
    "sg:city":"Engelburg",
    "sg:orig_category":"Herstellung von K\u00e4se",
    "sg:phone":"+41 21 800 55 65",
    "sg:postcode":"9032",
    "sg:province":"St. Gallen",
    "wof:name":"Rudolf Kaempf Fromagerie La Senoge",
    "wof:placetype":"venue"
},
  "geometry": {"coordinates":[6.4549489021,46.5780487061],"type":"Point"}
}