{
  "type": "Feature",
  "properties": {
    "addr:full":"Rue De La Coulouvreni\u00e8re 17 Gen\u00e8ve Gen\u00e8ve 1204",
    "addr:housenumber":"17",
    "addr:postcode":"1204",
    "addr:street":"Rue De La Coulouvrenie\u0300Re",
    "iso:country":"CH",
    "sg:address":"Rue De La Coulouvreni\u00e8re 17",
    "sg:city":"Gen\u00e8ve",
    "sg:orig_category":"Detailhandel mit Damenbekleidung",
    "sg:phone":"+41 22 329 49 11",
    "sg:postcode":"1204",
    "sg:province":"Gen\u00e8ve",
    "wof:name":"Barbare Boutique V\u00eatements M.favre & A.berthouzoz Imfeld",
    "wof:placetype":"venue"
},
  "geometry": {"coordinates":[6.137146,46.204037],"type":"Point"}
}