{
  "type": "Feature",
  "properties": {
    "iso:country":"CH",
    "sg:address":"Rigiweg 1",
    "sg:city":"Volketswil",
    "sg:orig_category":"Innenarchitekturb\u00fcros",
    "sg:phone":"+41 19455336",
    "sg:postcode":"8604",
    "sg:province":"Z\u00fcrich",
    "wof:name":"Claude Vetter Innenarchitektur",
    "wof:placetype":"venue"
},
  "geometry": {"coordinates":[8.6817865372,47.3918380737],"type":"Point"}
}