{
  "type": "Feature",
  "properties": {
    "iso:country":"CH",
    "sg:address":"Auhafen",
    "sg:city":"Birsfelden",
    "sg:orig_category":"Mechanische Werkst\u00e4tten",
    "sg:phone":"+41 61 313 11 97",
    "sg:postcode":"4127",
    "sg:province":"Basel-Landschaft",
    "wof:name":"Edoardo Dolzadelli Feinmechanische Werkstatt",
    "wof:placetype":"venue"
},
  "geometry": {"coordinates":[7.6585698128,47.5411186218],"type":"Point"}
}