{
  "type": "Feature",
  "properties": {
    "iso:country":"CH",
    "sg:address":"Route Cantonale 9",
    "sg:city":"Conthey",
    "sg:orig_category":"Herstellung von M\u00f6beln",
    "sg:phone":"+41 27 346 55 36",
    "sg:postcode":"1964",
    "sg:province":"Valais",
    "wof:name":"Gertschen Sa Fabrication De Meubles",
    "wof:placetype":"venue"
},
  "geometry": {"coordinates":[7.2951078415,46.2253684998],"type":"Point"}
}