{
  "type": "Feature",
  "properties": {
    "iso:country":"CH",
    "sg:address":"Birmensdorferstrasse 93/95 8003 Z\u00fcrich. Postfach 8852",
    "sg:city":"Z\u00fcrich",
    "sg:orig_category":"Detailhandel mit M\u00f6beln U Haushaltsgegenst\u00e4nden Herstellung von Teppichen",
    "sg:phone":"+41 91 606 16 88",
    "sg:postcode":"8036",
    "sg:province":"Z\u00fcrich",
    "wof:name":"Manifattura Tappeti Sa",
    "wof:placetype":"venue"
},
  "geometry": {"coordinates":[8.862950325,45.9702606201],"type":"Point"}
}