{
  "type": "Feature",
  "properties": {
    "iso:country":"CH",
    "sg:address":"Friedensgasse 17",
    "sg:city":"Birsfelden",
    "sg:orig_category":"Fahrschulen, Flugschulen",
    "sg:phone":"+41 61 313 88 31",
    "sg:postcode":"4127",
    "sg:province":"Basel-Landschaft",
    "wof:name":"J\u00f6rg Niederberger Autofahrschule Mestre",
    "wof:placetype":"venue"
},
  "geometry": {"coordinates":[7.6251602173,47.5498504639],"type":"Point"}
}