{
  "type": "Feature",
  "properties": {
    "iso:country":"CH",
    "sg:address":"Bruderholzstrasse 42 4053 Basel. Postfach",
    "sg:city":"Basel",
    "sg:orig_category":"Brillen Detailhandel Fachdetailhandel in Verkaufsr\u00e4umen",
    "sg:phone":"+41 32 637 37 36",
    "sg:postcode":"4018",
    "sg:province":"Basel-Stadt",
    "wof:name":"Brillenservice Briggen Therry",
    "wof:placetype":"venue"
},
  "geometry": {"coordinates":[7.571678,47.25032],"type":"Point"}
}