{
  "type": "Feature",
  "properties": {
    "iso:country":"CH",
    "sg:address":"March\u00e9 Rue Du 13 1204 Gen\u00e8ve. Postfach",
    "sg:city":"Gen\u00e8ve",
    "sg:orig_category":"Fachdetailhandel in Verkaufsr\u00e4umen",
    "sg:postcode":"1204",
    "sg:province":"Gen\u00e8ve",
    "wof:name":"Rappaport Pierre Et Roger",
    "wof:placetype":"venue"
},
  "geometry": {"coordinates":[6.1472821236,46.2032165527],"type":"Point"}
}