{
  "type": "Feature",
  "properties": {
    "iso:country":"CH",
    "sg:address":"M\u00e4rktgass 17",
    "sg:city":"Rafz",
    "sg:orig_category":"Herstellung von Bergwerks U Baumaschinen Strassenbau",
    "sg:phone":"+41 18690826",
    "sg:postcode":"8197",
    "sg:province":"Z\u00fcrich",
    "wof:name":"Frike Ger\u00e4te Rafz, Bieli G.",
    "wof:placetype":"venue"
},
  "geometry": {"coordinates":[8.5396194458,47.6124572754],"type":"Point"}
}