{
  "type": "Feature",
  "properties": {
    "addr:full":"Industriestrasse 1801c Spiez Bern 3700",
    "addr:housenumber":"1801c",
    "addr:postcode":"3700",
    "addr:street":"Industriestrasse",
    "iso:country":"CH",
    "sg:address":"Industriestrasse 1801c",
    "sg:city":"Spiez",
    "sg:orig_category":"Autogaragen Instandhaltung U Reparatur von Automobilen",
    "sg:phone":"+41 79 656 08 77",
    "sg:postcode":"3700",
    "sg:province":"Bern",
    "wof:name":"Dtm Garage Schl\u00e4ppi",
    "wof:placetype":"venue"
},
  "geometry": {"coordinates":[7.640822,46.697887],"type":"Point"}
}