{
  "type": "Feature",
  "properties": {
    "iso:country":"CH",
    "sg:address":"Kalkofenstrasse 25 8810 Horgen. Postfach",
    "sg:city":"Horgen",
    "sg:orig_category":"Unternehmensberatung",
    "sg:postcode":"8810",
    "sg:province":"Z\u00fcrich",
    "wof:name":"Inderbitzin O.a. Consulting & Finanzplanung Wirtschafts Und Fondsberatung, Finanzplanung F\u00fcr Private Haushalte",
    "wof:placetype":"venue"
},
  "geometry": {"coordinates":[8.607334137,47.247467041],"type":"Point"}
}