{
  "type": "Feature",
  "properties": {
    "iso:country":"CH",
    "sg:address":"Grand-rue 52",
    "sg:city":"Fribourg",
    "sg:orig_category":"Finanzierungsinstitutionen",
    "sg:phone":"+41 26 322 97 40",
    "sg:postcode":"1700",
    "sg:province":"Fribourg",
    "wof:name":"Swissfinance, Angelical",
    "wof:placetype":"venue"
},
  "geometry": {"coordinates":[7.1636681557,46.8055496216],"type":"Point"}
}