{
  "type": "Feature",
  "properties": {
    "iso:country":"CH",
    "sg:address":"Ring 16",
    "sg:city":"Biel/bienne",
    "sg:classifiers":[
        {
            "category":"Restaurant",
            "type":"Food & Drink"
        }
    ],
    "sg:phone":"+41 32 322 81 08",
    "sg:postcode":"2502",
    "sg:province":"Bern",
    "wof:name":"Restaurant Ring",
    "wof:placetype":"venue"
},
  "geometry": {"coordinates":[7.2465381622,47.1417732239],"type":"Point"}
}