{
  "type": "Feature",
  "properties": {
    "iso:country":"CH",
    "sg:address":"In Der Fuchsh\u00fctte 22",
    "sg:city":"D\u00fcbendorf",
    "sg:orig_category":"Vereine Milit\u00e4r",
    "sg:phone":"+41 61 931 25 24",
    "sg:postcode":"8600",
    "sg:province":"Z\u00fcrich",
    "wof:name":"Unteroffiziersverein",
    "wof:placetype":"venue"
},
  "geometry": {"coordinates":[8.6151151657,47.4069290161],"type":"Point"}
}