{
  "type": "Feature",
  "properties": {
    "iso:country":"CH",
    "sg:address":"Allmeindstrasse 10 8716 Schmerikon. Postfach",
    "sg:city":"Schmerikon",
    "sg:orig_category":"G\u00fcterbef\u00f6rderung im Strassenverkehr",
    "sg:phone":"+41 55 282 50 44",
    "sg:postcode":"8716",
    "sg:province":"St. Gallen",
    "wof:name":"Wespe & Cie Ag, Schmerikon",
    "wof:placetype":"venue"
},
  "geometry": {"coordinates":[8.9475774765,47.2252426147],"type":"Point"}
}