{
  "type": "Feature",
  "properties": {
    "iso:country":"CH",
    "sg:address":"Rheinstrasse 219",
    "sg:city":"Chur",
    "sg:classifiers":[
        {
            "category":"Home & Garden",
            "subcategory":"Building Materials",
            "type":"Retail Goods"
        }
    ],
    "sg:phone":"+41 81 286 34 30",
    "sg:postcode":"7000",
    "sg:province":"Graubunden",
    "sg:tags":[
        "ready-mixed",
        "fresh",
        "concrete"
    ],
    "wof:name":"Calanda-beton Ag",
    "wof:placetype":"venue"
},
  "geometry": {"coordinates":[9.5109481812,46.8640403748],"type":"Point"}
}