{
  "type": "Feature",
  "properties": {
    "iso:country":"CH",
    "sg:address":"Bahnhofplatz",
    "sg:city":"G\u00f6schenen",
    "sg:orig_category":"RESTAURANTS: TEA-ROOMS",
    "sg:postcode":"6487",
    "sg:province":"Uri",
    "wof:name":"W\u00e4fler-greiner Ursula",
    "wof:placetype":"venue"
},
  "geometry": {"coordinates":[8.588760376,46.6663513184],"type":"Point"}
}