{
  "type": "Feature",
  "properties": {
    "iso:country":"CH",
    "sg:address":"Heidenloch",
    "sg:city":"Triengen",
    "sg:orig_category":"Chalet- and Holzbau Zimmerei, Dachdeckerei, Bauspenglerei U Abdichtung",
    "sg:phone":"+41 41 933 00 69",
    "sg:postcode":"6234",
    "sg:province":"Luzern",
    "wof:name":"Helfenstein + B\u00e4ttig Holzbau Gmbh",
    "wof:placetype":"venue"
},
  "geometry": {"coordinates":[8.071247,47.246368],"type":"Point"}
}