{
  "type": "Feature",
  "properties": {
    "iso:country":"CH",
    "sg:address":"Industriestrasse 23 4922 B\u00fctzberg. Postfach",
    "sg:city":"B\u00fctzberg",
    "sg:orig_category":"Bau U Wohngenossenschaften",
    "sg:postcode":"4922",
    "sg:province":"Bern",
    "wof:name":"Baugen.b\u00fctikoferhaus",
    "wof:placetype":"venue"
},
  "geometry": {"coordinates":[7.811757,47.236217],"type":"Point"}
}