{
  "type": "Feature",
  "properties": {
    "iso:country":"CH",
    "sg:address":"Impass\u00e9e De Motte-ch\u00e2tel 7",
    "sg:city":"Estavayer-le-lac",
    "sg:orig_category":"Sanit\u00e4r, Heizungs U L\u00fcftungsinstallation Sanit\u00e4rinstallation",
    "sg:phone":"+41 26 663 24 56",
    "sg:postcode":"1470",
    "sg:province":"Fribourg",
    "wof:name":"Jpk Sanitaire Jean-philippe Kaiser",
    "wof:placetype":"venue"
},
  "geometry": {"coordinates":[6.846362114,46.8500862122],"type":"Point"}
}