{
  "type": "Feature",
  "properties": {
    "iso:country":"CH",
    "sg:address":"Bahnhofstrasse 10 3900 Brig. Postfach 315",
    "sg:city":"Brig",
    "sg:orig_category":"Advokaturb\u00fcros Notariate",
    "sg:phone":"+41 27 923 19 14",
    "sg:postcode":"3900",
    "sg:province":"Valais",
    "wof:name":"Dr.odilo Guntern Advokatur-& Notariatsb\u00fcro",
    "wof:placetype":"venue"
},
  "geometry": {"coordinates":[7.988025,46.317554],"type":"Point"}
}