{
  "type": "Feature",
  "properties": {
    "iso:country":"CH",
    "sg:address":"Kantonsstrasse 4",
    "sg:city":"Nottwil",
    "sg:orig_category":"Autogaragen Instandhaltung U Reparatur von Automobilen",
    "sg:phone":"+41 71 244 09 59",
    "sg:postcode":"6207",
    "sg:province":"Luzern",
    "wof:name":"Teka-garage, Sitaras-raftopulos Argiri",
    "wof:placetype":"venue"
},
  "geometry": {"coordinates":[9.396382,47.444138],"type":"Point"}
}