{
  "type": "Feature",
  "properties": {
    "iso:country":"CH",
    "sg:address":"Obstgartenstr. 8",
    "sg:city":"Kloten",
    "sg:orig_category":"Internet, Webseiten U -systeme",
    "sg:phone":"+41 4118153035",
    "sg:postcode":"8302",
    "sg:province":"Z\u00fcrich",
    "wof:name":"Gratis Kleinanzeiger Schweiz",
    "wof:placetype":"venue"
},
  "geometry": {"coordinates":[8.580395,47.449909],"type":"Point"}
}