{
  "type": "Feature",
  "properties": {
    "iso:country":"CH",
    "sg:address":"Industriestrasse 51b",
    "sg:city":"B\u00f6singen",
    "sg:orig_category":"Herstellung von Metallerzeugnissen ohne Maschinenbau Herstellung von Rohren",
    "sg:phone":"+41 18179070",
    "sg:postcode":"3178",
    "sg:province":"Fribourg",
    "wof:name":"Lindab-bartholet Ag",
    "wof:placetype":"venue"
},
  "geometry": {"coordinates":[7.2289171219,46.9006538391],"type":"Point"}
}