{
  "type": "Feature",
  "properties": {
    "iso:country":"CH",
    "sg:address":"4617",
    "sg:city":"Gunzgen",
    "sg:orig_category":"Vereine Musik/Blasmusik",
    "sg:phone":"+41 62 286 83 07",
    "sg:postcode":"4617",
    "sg:province":"Solothurn",
    "wof:name":"Musikgesellschaft",
    "wof:placetype":"venue"
},
  "geometry": {"coordinates":[7.8343100548,47.310710907],"type":"Point"}
}