{
  "type": "Feature",
  "properties": {
    "iso:country":"CH",
    "sg:address":"Lausanne Rue De 94",
    "sg:city":"Gen\u00e8ve",
    "sg:classifiers":[
        {
            "category":"Professional",
            "subcategory":"Employment Agencies",
            "type":"Services"
        }
    ],
    "sg:phone":"+41 22 361 35 60",
    "sg:postcode":"1202",
    "sg:province":"Gen\u00e8ve",
    "sg:tags":[
        "personal",
        "u",
        "stellenvermittlung"
    ],
    "wof:name":"Fast-track, Sullivan Mitch",
    "wof:placetype":"venue"
},
  "geometry": {"coordinates":[6.1484088898,46.2175445557],"type":"Point"}
}