{
  "type": "Feature",
  "properties": {
    "iso:country":"CH",
    "sg:address":"7744",
    "sg:city":"Campocologno",
    "sg:orig_category":"Pensionen mit Restaurant",
    "sg:phone":"+41 91 791 26 32",
    "sg:postcode":"7744",
    "sg:province":"Graubunden",
    "wof:name":"Pensione Posta Al Lago",
    "wof:placetype":"venue"
},
  "geometry": {"coordinates":[8.7280597687,46.1414794922],"type":"Point"}
}