{
  "type": "Feature",
  "properties": {
    "iso:country":"CH",
    "sg:address":"Allmenr\u00fctti",
    "sg:city":"Schwendibach",
    "sg:orig_category":"Autogaragen Autospenglereien",
    "sg:phone":"+41 33 442 13 50",
    "sg:postcode":"3624",
    "sg:province":"Bern",
    "wof:name":"Ulrich Meyer Carrosserie & Autoreparaturen",
    "wof:placetype":"venue"
},
  "geometry": {"coordinates":[7.65323,46.770275],"type":"Point"}
}