{
  "type": "Feature",
  "properties": {
    "iso:country":"CH",
    "sg:address":"S\u00e4ntisstrasse 61",
    "sg:city":"Schaffhausen",
    "sg:orig_category":"Grosshandel mit Getreide, Saatgut U Futtermitteln",
    "sg:postcode":"8200",
    "sg:province":"Schaffhausen",
    "wof:name":"Fertag",
    "wof:placetype":"venue"
},
  "geometry": {"coordinates":[8.6454210281,47.6967849731],"type":"Point"}
}