{
  "type": "Feature",
  "properties": {
    "iso:country":"CH",
    "sg:address":"Dorngasse 39",
    "sg:city":"Widen",
    "sg:orig_category":"Herstellung von Seifen, Wasch, Reinigungs, Duft U K\u00f6rperpflegemitteln",
    "sg:phone":"+41 56 633 20 25",
    "sg:postcode":"8967",
    "sg:province":"Aargau",
    "wof:name":"Sanolife Gmbh Bio-energetische Produkte",
    "wof:placetype":"venue"
},
  "geometry": {"coordinates":[8.3602933884,47.3650474548],"type":"Point"}
}