{
  "type": "Feature",
  "properties": {
    "iso:country":"CH",
    "sg:address":"Neutalstrasse 2",
    "sg:city":"Altendorf",
    "sg:orig_category":"Sonstiger Grosshandel",
    "sg:postcode":"8852",
    "sg:province":"Schwyz",
    "wof:name":"Marty Martin Rheinbacher-steinl\u00e4dchen",
    "wof:placetype":"venue"
},
  "geometry": {"coordinates":[8.8225879669,47.1927452087],"type":"Point"}
}