{
  "type": "Feature",
  "properties": {
    "iso:country":"CH",
    "sg:address":"Talgut-zentrum 26",
    "sg:city":"Ittigen",
    "sg:orig_category":"Fahrschulen, Flugschulen",
    "sg:phone":"+41 31 921 00 58",
    "sg:postcode":"3063",
    "sg:province":"Bern",
    "wof:name":"Arno Berger Autofahrschule",
    "wof:placetype":"venue"
},
  "geometry": {"coordinates":[7.4801430702,46.9747161865],"type":"Point"}
}