{
  "type": "Feature",
  "properties": {
    "addr:full":"Bahnhofstrasse 1 Altendorf Schwyz 8852",
    "addr:housenumber":"1",
    "addr:postcode":"8852",
    "addr:street":"Bahnhofstrasse",
    "iso:country":"CH",
    "sg:address":"Bahnhofstrasse 1",
    "sg:city":"Altendorf",
    "sg:orig_category":"Calcium Nitrate",
    "sg:phone":"+41 55 451 15 55",
    "sg:postcode":"8852",
    "sg:province":"Schwyz",
    "wof:name":"Transammonia Ag",
    "wof:placetype":"venue"
},
  "geometry": {"coordinates":[8.82265,47.192902],"type":"Point"}
}