{
  "type": "Feature",
  "properties": {
    "iso:country":"CH",
    "sg:address":"3951",
    "sg:city":"Agarn",
    "sg:orig_category":"Maler U Glasergewerbe",
    "sg:phone":"+41 27 473 26 85",
    "sg:postcode":"3951",
    "sg:province":"Valais",
    "wof:name":"Beney Erhard, Maler Und Gipsergesch\u00e4ft Ag",
    "wof:placetype":"venue"
},
  "geometry": {"coordinates":[7.6635918617,46.2969512939],"type":"Point"}
}