{
  "type": "Feature",
  "properties": {
    "iso:country":"CH",
    "sg:address":"Dorfstr.",
    "sg:city":"Wengen",
    "sg:classifiers":[
        {
            "category":"Banks & Credit Unions",
            "subcategory":"Bank",
            "type":"Services"
        }
    ],
    "sg:phone":"+41 36551218",
    "sg:postcode":"3823",
    "sg:province":"Bern",
    "wof:name":"Kantonalbank Von Bern",
    "wof:placetype":"venue"
},
  "geometry": {"coordinates":[7.9216,46.605194],"type":"Point"}
}