{
  "type": "Feature",
  "properties": {
    "iso:country":"CH",
    "sg:address":"Chemin De La Source 27b",
    "sg:city":"Romanel-s-lausanne",
    "sg:orig_category":"Stukkateurgewerbe, Gipserei U Verputzerei",
    "sg:postcode":"1032",
    "sg:province":"Vaud",
    "wof:name":"Dumas Rhapha\u00ebl & Fils Sa",
    "wof:placetype":"venue"
},
  "geometry": {"coordinates":[6.9275698662,46.6799888611],"type":"Point"}
}