{
  "type": "Feature",
  "properties": {
    "iso:country":"CH",
    "sg:address":"Buristrasse 21",
    "sg:city":"Bern",
    "sg:orig_category":"Werbevermittlung",
    "sg:phone":"+41 31 352 77 22",
    "sg:postcode":"3006",
    "sg:province":"Bern",
    "wof:name":"Werbeagentur Rohner Hans Und Brechtb\u00fchl Annemarie",
    "wof:placetype":"venue"
},
  "geometry": {"coordinates":[7.4758257866,46.9448165894],"type":"Point"}
}