{
  "type": "Feature",
  "properties": {
    "iso:country":"CH",
    "sg:address":"Aarb\u00fchlstrasse 7 3084 Gurten. Postfach",
    "sg:city":"Wabern",
    "sg:orig_category":"Wirtschaftspr\u00fcfung, Steuerberatung U Treuhand",
    "sg:postcode":"3084",
    "sg:province":"Bern",
    "wof:name":"Bucons Treuhand U. Geiser",
    "wof:placetype":"venue"
},
  "geometry": {"coordinates":[7.4508399963,46.9290351868],"type":"Point"}
}