{
  "type": "Feature",
  "properties": {
    "iso:country":"CH",
    "sg:address":"Meylandstrasse 42",
    "sg:city":"Murten",
    "sg:classifiers":[
        {
            "category":"Social Services",
            "subcategory":"Retirement Home",
            "type":"Services"
        }
    ],
    "sg:phone":"+41 26 670 43 43",
    "sg:postcode":"3280",
    "sg:province":"Fribourg",
    "sg:tags":[
        "pflegeheime",
        "u",
        "alters"
    ],
    "wof:name":"Alterszentrum Der Hermann & Elisabeth Liechti Stiftung",
    "wof:placetype":"venue"
},
  "geometry": {"coordinates":[7.120547,46.928291],"type":"Point"}
}