{
  "type": "Feature",
  "properties": {
    "iso:country":"CH",
    "sg:address":"Pretorio Via 21 6900 Lugano. Postfach",
    "sg:city":"Lugano",
    "sg:orig_category":"Detailhandel mit Bekleidung",
    "sg:phone":"+41 71 890 05 54",
    "sg:postcode":"6900",
    "sg:province":"Ticino",
    "wof:name":"Gehrer Felix & Co Waren, Bes. Bekleidungsartikel Aus Textilien Und Leder Usw.; Handel",
    "wof:placetype":"venue"
},
  "geometry": {"coordinates":[9.511549,47.446697],"type":"Point"}
}