{
  "type": "Feature",
  "properties": {
    "iso:country":"CH",
    "sg:address":"Bellinzona Via 26",
    "sg:city":"Biasca",
    "sg:orig_category":"Erbringung von sonstigen Dienstleistungen f\u00fcr Unterhaltung, Erholung U Freizeit",
    "sg:postcode":"6710",
    "sg:province":"Ticino",
    "wof:name":"T&t Group Sagl",
    "wof:placetype":"venue"
},
  "geometry": {"coordinates":[8.9737958908,46.3516044617],"type":"Point"}
}