{
  "type": "Feature",
  "properties": {
    "iso:country":"CH",
    "sg:address":"Rocher Rue Du 6",
    "sg:city":"Neuch\u00e2tel",
    "sg:orig_category":"Sonstiger Fachdetailhandel mit Nahrungsmitteln, Getr\u00e4nken U Tabak in Verkaufsr\u00e4umen",
    "sg:postcode":"2000",
    "sg:province":"Neuch\u00e2tel",
    "wof:name":"Fl\u00fchmann Lina",
    "wof:placetype":"venue"
},
  "geometry": {"coordinates":[6.936647892,46.9984703064],"type":"Point"}
}