{
  "type": "Feature",
  "properties": {
    "iso:country":"CH",
    "sg:address":"Oltingerstrasse 13",
    "sg:city":"Rodersdorf",
    "sg:orig_category":"Herstellung von sonstigen elektrischen Ausr\u00fcstungen",
    "sg:phone":"+41 61 733 01 44",
    "sg:postcode":"4118",
    "sg:province":"Solothurn",
    "wof:name":"Fischer Peter",
    "wof:placetype":"venue"
},
  "geometry": {"coordinates":[7.4533548355,47.4836463928],"type":"Point"}
}