{
  "type": "Feature",
  "properties": {
    "iso:country":"CH",
    "sg:address":"General Guisan-strasse 23 23",
    "sg:city":"Arlesheim",
    "sg:orig_category":"Gesundheitswesen",
    "sg:postcode":"4144",
    "sg:province":"Basel-Landschaft",
    "wof:name":"Massage-mobil L\u00e4ng Corinne",
    "wof:placetype":"venue"
},
  "geometry": {"coordinates":[7.614648819,47.4995155334],"type":"Point"}
}