{
  "type": "Feature",
  "properties": {
    "iso:country":"CH",
    "sg:address":"Ansermet Quai Ernest- 20",
    "sg:city":"Genf",
    "sg:classifiers":[
        {
            "category":"Communications",
            "subcategory":"Radio Station",
            "type":"Services"
        }
    ],
    "sg:phone":"+41 71 367 12 14",
    "sg:postcode":"1200",
    "sg:province":"Gen\u00e8ve",
    "sg:tags":[
        "fernsehanstalten",
        "u"
    ],
    "wof:name":"Fsp Werbetech.ch Ag Print, Digital-erzeugnisse; Beratung, Gestaltung, Ausf\u00fchrung Usw",
    "wof:placetype":"venue"
},
  "geometry": {"coordinates":[9.3420372009,47.3746604919],"type":"Point"}
}