{
  "type": "Feature",
  "properties": {
    "addr:full":"Kramgasse 16 Bern Bern 3011",
    "addr:housenumber":"16",
    "addr:postcode":"3011",
    "addr:street":"Kramgasse",
    "iso:country":"CH",
    "sg:address":"Kramgasse 16",
    "sg:city":"Bern",
    "sg:orig_category":"Arztpraxen",
    "sg:phone":"+41 71 244 51 81",
    "sg:postcode":"3011",
    "sg:province":"Bern",
    "wof:name":"Dr.med.andreas Paky Spezialarzt Fmh",
    "wof:placetype":"venue"
},
  "geometry": {"coordinates":[9.381368,47.4282],"type":"Point"}
}