{
  "type": "Feature",
  "properties": {
    "iso:country":"CH",
    "sg:address":"Im D\u00f6rfli 8",
    "sg:city":"Finstersee",
    "sg:orig_category":"Primarschulen",
    "sg:phone":"+41 41 755 36 02",
    "sg:postcode":"6313",
    "sg:province":"Zug",
    "wof:name":"Primarschule Finstersee",
    "wof:placetype":"venue"
},
  "geometry": {"coordinates":[8.6301841736,47.1671104431],"type":"Point"}
}