{
  "type": "Feature",
  "properties": {
    "iso:country":"CH",
    "sg:address":"Rue Gachoud 3 1700 Fribourg. Postfach",
    "sg:city":"Fribourg",
    "sg:orig_category":"Pensionskassen",
    "sg:postcode":"1701",
    "sg:province":"Fribourg",
    "wof:name":"Fondation Du Personnel De La Maison Voumard Machines Co S.a.",
    "wof:placetype":"venue"
},
  "geometry": {"coordinates":[6.8131051064,47.0944824219],"type":"Point"}
}