{
  "type": "Feature",
  "properties": {
    "iso:country":"CH",
    "sg:address":"Ch. Des Suzettes 77.",
    "sg:city":"Bernex",
    "sg:orig_category":"Pulvermetallurgie Schmieden, Pressen, Stanzen U Profilwalzen von Metallen",
    "sg:phone":"+41 22 757 14 06",
    "sg:postcode":"1233",
    "sg:province":"Gen\u00e8ve",
    "wof:name":"Claude Bays",
    "wof:placetype":"venue"
},
  "geometry": {"coordinates":[6.0810351372,46.1812362671],"type":"Point"}
}