{
  "type": "Feature",
  "properties": {
    "iso:country":"CH",
    "sg:address":"Dorfstrasse 43",
    "sg:city":"Bollingen",
    "sg:classifiers":[
        {
            "category":"Restaurant",
            "type":"Food & Drink"
        }
    ],
    "sg:phone":"+41 55 212 33 16",
    "sg:postcode":"8715",
    "sg:province":"St. Gallen",
    "wof:name":"Restaurant Schiffahrt",
    "wof:placetype":"venue"
},
  "geometry": {"coordinates":[8.8946971893,47.2190856934],"type":"Point"}
}