{
  "type": "Feature",
  "properties": {
    "iso:country":"CH",
    "sg:address":"Rue Des Racettes 51",
    "sg:city":"Onex",
    "sg:orig_category":"G\u00fcterbef\u00f6rderung im Strassenverkehr",
    "sg:phone":"+41 22 792 45 68",
    "sg:postcode":"1213",
    "sg:province":"Gen\u00e8ve",
    "wof:name":"Pegase Transports, Burri Patrick",
    "wof:placetype":"venue"
},
  "geometry": {"coordinates":[6.1061601639,46.1922492981],"type":"Point"}
}