{
  "type": "Feature",
  "properties": {
    "iso:country":"CH",
    "sg:address":"Schwarzenburgstrasse 1041",
    "sg:city":"Mittelh\u00e4usern",
    "sg:orig_category":"Allgemeiner Hoch U Tiefbau Hoch U Tiefbau",
    "sg:phone":"+41 79 656 81 71",
    "sg:postcode":"3147",
    "sg:province":"Bern",
    "wof:name":"Bowee Bau Ag",
    "wof:placetype":"venue"
},
  "geometry": {"coordinates":[7.44137,46.456959],"type":"Point"}
}