{
  "type": "Feature",
  "properties": {
    "iso:country":"CH",
    "sg:address":"Dassier Rue Jean- 16 1201 Gen\u00e8ve. Postfach",
    "sg:city":"Gen\u00e8ve",
    "sg:orig_category":"Interessenvertretungen",
    "sg:postcode":"1201",
    "sg:province":"Gen\u00e8ve",
    "wof:name":"Iglesia Ni Cristo",
    "wof:placetype":"venue"
},
  "geometry": {"coordinates":[6.1391630173,46.2086372375],"type":"Point"}
}