{
  "type": "Feature",
  "properties": {
    "iso:country":"CH",
    "sg:address":"Glattalstrasse 41",
    "sg:city":"Z\u00fcrich",
    "sg:orig_category":"Schwimmb\u00e4der",
    "sg:phone":"+41 13026166",
    "sg:postcode":"8052",
    "sg:province":"Z\u00fcrich",
    "wof:name":"Freibad Seebach",
    "wof:placetype":"venue"
},
  "geometry": {"coordinates":[8.5483808517,47.4241447449],"type":"Point"}
}