{
  "type": "Feature",
  "properties": {
    "iso:country":"CH",
    "sg:address":"Avenue De Florissant 37",
    "sg:city":"Prilly",
    "sg:orig_category":"Malerei Malerei-Gipserei",
    "sg:phone":"+41 21 625 98 61",
    "sg:postcode":"1008",
    "sg:province":"Vaud",
    "wof:name":"Jean-pierre Masson Pl\u00e2trerie-peinture",
    "wof:placetype":"venue"
},
  "geometry": {"coordinates":[6.5984997749,46.5326805115],"type":"Point"}
}