{
  "type": "Feature",
  "properties": {
    "iso:country":"CH",
    "sg:address":"Veia Granda 1",
    "sg:city":"Andeer",
    "sg:orig_category":"Erwachsenenbildung U Unterricht",
    "sg:phone":"+41 81 661 11 51",
    "sg:postcode":"7440",
    "sg:province":"Graubunden",
    "wof:name":"Fravi Christian H.",
    "wof:placetype":"venue"
},
  "geometry": {"coordinates":[9.4265604019,46.6048355103],"type":"Point"}
}