{
  "type": "Feature",
  "properties": {
    "iso:country":"CH",
    "sg:address":"Hofwiesenstrasse 6 8634 Hombrechtikon. Postfach",
    "sg:city":"Hombrechtikon",
    "sg:orig_category":"Fachdetailhandel in Verkaufsr\u00e4umen Grosshandel mit medizinischen U orthop\u00e4dischen Artikeln",
    "sg:phone":"+41 52 672 22 66",
    "sg:postcode":"8634",
    "sg:province":"Z\u00fcrich",
    "wof:name":"Heine (schweiz) Ag",
    "wof:placetype":"venue"
},
  "geometry": {"coordinates":[8.6040496826,47.6762733459],"type":"Point"}
}