{
  "type": "Feature",
  "properties": {
    "iso:country":"CH",
    "sg:address":"Les Arbognes 1774 Montagny-les-monts. Postfach",
    "sg:city":"Cousset",
    "sg:orig_category":"RESTAURANTS: TEA-ROOMS",
    "sg:postcode":"1774",
    "sg:province":"Fribourg",
    "wof:name":"Raymonde Chardonnens",
    "wof:placetype":"venue"
},
  "geometry": {"coordinates":[6.9879221916,46.8122138977],"type":"Point"}
}