{
  "type": "Feature",
  "properties": {
    "iso:country":"CH",
    "sg:address":"St. Galler Strasse 21 9042 Speicher. Postfach 47",
    "sg:city":"Speicher",
    "sg:orig_category":"Mechanik Mechanische Werkst\u00e4tten",
    "sg:phone":"+41 71 343 70 43",
    "sg:postcode":"9042",
    "sg:province":"Appenzell Ausserrhoden",
    "wof:name":"Mako Ag.",
    "wof:placetype":"venue"
},
  "geometry": {"coordinates":[9.4335632324,47.4170417786],"type":"Point"}
}