{
  "type": "Feature",
  "properties": {
    "iso:country":"CH",
    "sg:address":"Bodenfeld",
    "sg:city":"Menziken",
    "sg:classifiers":[
        {
            "category":"Manufacturing",
            "subcategory":"Metals",
            "type":"Manufacturing & Wholesale Goods"
        }
    ],
    "sg:phone":"+41 62 771 77 44",
    "sg:postcode":"5737",
    "sg:province":"Aargau",
    "sg:tags":[
        "metallurgy",
        "metalworking",
        "processing"
    ],
    "wof:name":"Metal Paint Ag",
    "wof:placetype":"venue"
},
  "geometry": {"coordinates":[8.1920166016,47.2420463562],"type":"Point"}
}