{
  "type": "Feature",
  "properties": {
    "iso:country":"CH",
    "sg:address":"Hackenrainstrasse 6 6010 Kriens. Postfach",
    "sg:city":"Kriens",
    "sg:orig_category":"Non-Classified Establishments",
    "sg:postcode":"6010",
    "sg:province":"Luzern",
    "wof:name":"Nsm New Swiss Media Gmbh",
    "wof:placetype":"venue"
},
  "geometry": {"coordinates":[8.2669706345,47.0327148438],"type":"Point"}
}