{
  "type": "Feature",
  "properties": {
    "iso:country":"CH",
    "sg:address":"Huggerwaldstrasse 311",
    "sg:city":"Kleinl\u00fctzel",
    "sg:orig_category":"Softwareentwicklung U beratung",
    "sg:phone":"+41 61 773 90 73",
    "sg:postcode":"4245",
    "sg:province":"Solothurn",
    "wof:name":"Gyro-comp Computerservice Robert Gyger",
    "wof:placetype":"venue"
},
  "geometry": {"coordinates":[7.4190940857,47.4204673767],"type":"Point"}
}