{
  "type": "Feature",
  "properties": {
    "iso:country":"CH",
    "sg:address":"Wasserfurristrasse 11",
    "sg:city":"Winterthur",
    "sg:orig_category":"Bauschreinerei Innenausbau",
    "sg:phone":"+41 52 202 21 94",
    "sg:postcode":"8406",
    "sg:province":"Z\u00fcrich",
    "wof:name":"Karl Walder Schreinerei & Innenausbau",
    "wof:placetype":"venue"
},
  "geometry": {"coordinates":[8.712374,47.491779],"type":"Point"}
}