{
  "type": "Feature",
  "properties": {
    "iso:country":"CH",
    "sg:address":"Mont-blanc Rue Du 26 1201 Gen\u00e8ve. Postfach",
    "sg:city":"Gen\u00e8ve",
    "sg:orig_category":"Wirtschaftspr\u00fcfung, Steuerberatung U Treuhand",
    "sg:phone":"+41 56 631 92 30",
    "sg:postcode":"1201",
    "sg:province":"Gen\u00e8ve",
    "wof:name":"Sf Treuhand + Beratung F\u00fcglistaler Sonja",
    "wof:placetype":"venue"
},
  "geometry": {"coordinates":[8.3372688293,47.3501243591],"type":"Point"}
}