{
  "type": "Feature",
  "properties": {
    "iso:country":"CH",
    "sg:address":"Hinterm\u00e4ttlistrasse 3 5506 M\u00e4genwil. Postfach 64",
    "sg:city":"M\u00e4genwil",
    "sg:orig_category":"Herstellung von Metallerzeugnissen ohne Maschinenbau",
    "sg:phone":"+41 62 889 77 77",
    "sg:postcode":"5506",
    "sg:province":"Aargau",
    "wof:name":"Rockwell Automation Ag",
    "wof:placetype":"venue"
},
  "geometry": {"coordinates":[8.2237968445,47.4103050232],"type":"Point"}
}