{
  "type": "Feature",
  "properties": {
    "iso:country":"CH",
    "sg:address":"Rue De La Gare 5",
    "sg:city":"Fribourg",
    "sg:orig_category":"Bau U Wohngenossenschaften",
    "sg:postcode":"1700",
    "sg:province":"Fribourg",
    "wof:name":"Coop.de B\u00e2tisse De Bellevue C/o Fidurevision Sa",
    "wof:placetype":"venue"
},
  "geometry": {"coordinates":[7.150392,46.801826],"type":"Point"}
}