{
  "type": "Feature",
  "properties": {
    "addr:full":"Viale Stazione 17a Bellinzona Ticino 6500",
    "addr:housenumber":"17a",
    "addr:postcode":"6500",
    "addr:street":"Viale Stazione",
    "iso:country":"CH",
    "sg:address":"Viale Stazione 17a",
    "sg:city":"Bellinzona",
    "sg:orig_category":"Arbeitnehmerverb\u00e4nde",
    "sg:phone":"+41 91 825 01 15",
    "sg:postcode":"6500",
    "sg:province":"Ticino",
    "wof:name":"Fed.svizzera D.ferrovieri Sev Segretariato Del Ticino",
    "wof:placetype":"venue"
},
  "geometry": {"coordinates":[9.026184,46.193733],"type":"Point"}
}