{
  "type": "Feature",
  "properties": {
    "iso:country":"CH",
    "sg:address":"Z\u00fcrcherstrasse 47",
    "sg:city":"Sargans",
    "sg:orig_category":"Politische Parteien CVP",
    "sg:phone":"+41 81 723 21 67",
    "sg:postcode":"7320",
    "sg:province":"St. Gallen",
    "wof:name":"Cvp Ortspartei Sargans",
    "wof:placetype":"venue"
},
  "geometry": {"coordinates":[9.4339666367,47.0491333008],"type":"Point"}
}