{
  "type": "Feature",
  "properties": {
    "iso:country":"CH",
    "sg:address":"Dorfstrasse 40",
    "sg:city":"Matzendorf",
    "sg:classifiers":[
        {
            "category":"Banks & Credit Unions",
            "subcategory":"Bank",
            "type":"Services"
        }
    ],
    "sg:phone":"+41 4162741414",
    "sg:postcode":"4713",
    "sg:province":"Solothurn",
    "wof:name":"Raiffeisenbank Matzendorf",
    "wof:placetype":"venue"
},
  "geometry": {"coordinates":[7.629426,47.306503],"type":"Point"}
}