{
  "type": "Feature",
  "properties": {
    "iso:country":"CH",
    "sg:address":"B\u00e4chigenstrasse 24",
    "sg:city":"Arnegg",
    "sg:classifiers":[
        {
            "category":"Restaurant",
            "type":"Food & Drink"
        }
    ],
    "sg:phone":"+41 71 385 12 71",
    "sg:postcode":"9212",
    "sg:province":"St. Gallen",
    "wof:name":"Restaurant Bahnhof",
    "wof:placetype":"venue"
},
  "geometry": {"coordinates":[9.2528867722,47.4433288574],"type":"Point"}
}