{
  "type": "Feature",
  "properties": {
    "iso:country":"CH",
    "sg:address":"Aarauerstrasse 101",
    "sg:city":"Niedererlinsbach",
    "sg:orig_category":"Detailhandel mit Bekleidung",
    "sg:phone":"+41 56 441 18 45",
    "sg:postcode":"5015",
    "sg:province":"Solothurn",
    "wof:name":"Von D\u00e4niken Mode",
    "wof:placetype":"venue"
},
  "geometry": {"coordinates":[8.208605,47.483135],"type":"Point"}
}