{
  "type": "Feature",
  "properties": {
    "iso:country":"CH",
    "sg:address":"Gibelinstrasse 13",
    "sg:city":"Solothurn",
    "sg:orig_category":"Unternehmensberatung",
    "sg:phone":"+41 22 317 73 73",
    "sg:postcode":"4500",
    "sg:province":"Solothurn",
    "wof:name":"Nwt Management Sa",
    "wof:placetype":"venue"
},
  "geometry": {"coordinates":[6.1459059715,46.2022972107],"type":"Point"}
}