{
  "type": "Feature",
  "properties": {
    "iso:country":"CH",
    "sg:address":"Tellstrasse 30",
    "sg:city":"Flawil",
    "sg:orig_category":"Elektroinstallation Sonstige Bauinstallation",
    "sg:phone":"+41 71 393 42 73",
    "sg:postcode":"9230",
    "sg:province":"St. Gallen",
    "wof:name":"Baumontagen & Storenservice J.sch\u00e4dler",
    "wof:placetype":"venue"
},
  "geometry": {"coordinates":[9.1830034256,47.4107017517],"type":"Point"}
}