{
  "type": "Feature",
  "properties": {
    "iso:country":"CH",
    "sg:address":"Rue Peillonnex 36",
    "sg:city":"Ch\u00eane-bourg",
    "sg:orig_category":"Bauspenglerei Zimmerei, Dachdeckerei, Bauspenglerei U Abdichtung",
    "sg:phone":"+41 22 348 67 35",
    "sg:postcode":"1225",
    "sg:province":"Gen\u00e8ve",
    "wof:name":"Entreprise Monney Bernard Sa",
    "wof:placetype":"venue"
},
  "geometry": {"coordinates":[6.198456,46.19529],"type":"Point"}
}