{
  "type": "Feature",
  "properties": {
    "iso:country":"CH",
    "sg:address":"R\u00fcmelinsplatz 13 4001 Basel. Postfach",
    "sg:city":"Basel",
    "sg:orig_category":"Detailhandel mit Brillen U anderen Sehhilfen",
    "sg:phone":"+41 21 312 16 85",
    "sg:postcode":"4001",
    "sg:province":"Basel-Stadt",
    "wof:name":"Jacques Gani\u00e8re Lunetterie De L'ale",
    "wof:placetype":"venue"
},
  "geometry": {"coordinates":[6.62778,46.52401],"type":"Point"}
}