{
  "type": "Feature",
  "properties": {
    "iso:country":"CH",
    "sg:address":"Courvoisier Chemin Cesar 14 1290 Versoix. Postfach",
    "sg:city":"Versoix",
    "sg:orig_category":"M\u00f6belschreinereien",
    "sg:postcode":"1290",
    "sg:province":"Gen\u00e8ve",
    "wof:name":"Sousa Da Silva Carlos Eb\u00e9nisterie-menuiserie",
    "wof:placetype":"venue"
},
  "geometry": {"coordinates":[6.1672201157,46.278793335],"type":"Point"}
}