{
  "type": "Feature",
  "properties": {
    "iso:country":"CH",
    "sg:address":"G\u00fctli 166",
    "sg:city":"Walzenhausen",
    "sg:orig_category":"Pulvermetallurgie Schmieden, Pressen, Stanzen U Profilwalzen von Metallen Stahl U Leichtmetallbau",
    "sg:phone":"+41 71 886 48 10",
    "sg:postcode":"9428",
    "sg:province":"Appenzell Ausserrhoden",
    "wof:name":"Hbb Biegetechnik Ag",
    "wof:placetype":"venue"
},
  "geometry": {"coordinates":[9.6069688797,47.4482002258],"type":"Point"}
}