{
  "type": "Feature",
  "properties": {
    "iso:country":"CH",
    "sg:address":"Rheinstrasse 57",
    "sg:city":"Felsberg",
    "sg:orig_category":"Fotografische Ateliers",
    "sg:phone":"+41 81 252 23 66",
    "sg:postcode":"7012",
    "sg:province":"Graubunden",
    "wof:name":"Reto Reinhardt Fotografisches Atelier",
    "wof:placetype":"venue"
},
  "geometry": {"coordinates":[9.486738205,46.847114563],"type":"Point"}
}