{
  "type": "Feature",
  "properties": {
    "iso:country":"CH",
    "sg:address":"Bergstrasse 3",
    "sg:city":"Otelfingen",
    "sg:orig_category":"Sportvereine Sch\u00fctzen",
    "sg:phone":"+41 79 247 88 66",
    "sg:postcode":"8112",
    "sg:province":"Z\u00fcrich",
    "wof:name":"Milit\u00e4rschiessverein R'dorf",
    "wof:placetype":"venue"
},
  "geometry": {"coordinates":[8.3868274689,47.4652481079],"type":"Point"}
}