{
  "type": "Feature",
  "properties": {
    "iso:country":"CH",
    "sg:address":"W\u00e4sserwies 12 8712 St\u00e4fa. Postfach 108",
    "sg:city":"Uerikon",
    "sg:orig_category":"Fernmeldedienste",
    "sg:postcode":"8713",
    "sg:province":"Z\u00fcrich",
    "wof:name":"Kabelfernseh-service Anhorn & Burkard",
    "wof:placetype":"venue"
},
  "geometry": {"coordinates":[8.7260389328,47.2435417175],"type":"Point"}
}