{
  "type": "Feature",
  "properties": {
    "iso:country":"CH",
    "sg:address":"R\u00fcttimatt 130 4148 Pfeffingen. Postfach",
    "sg:city":"Pfeffingen",
    "sg:orig_category":"Futtermittel, Heu and Stroh Grosshandel Grosshandel mit Getreide, Saatgut U Futtermitteln",
    "sg:phone":"+41 61 751 75 01",
    "sg:postcode":"4148",
    "sg:province":"Basel-Landschaft",
    "wof:name":"Nutrivet Gmbh Futtermittel, Futtermittelzus\u00e4tze; Handel, Produktion",
    "wof:placetype":"venue"
},
  "geometry": {"coordinates":[7.5897011757,47.4589424133],"type":"Point"}
}