{
  "type": "Feature",
  "properties": {
    "iso:country":"CH",
    "sg:address":"Rebbergstrasse 2",
    "sg:city":"Henggart",
    "sg:orig_category":"Softwareentwicklung U beratung",
    "sg:phone":"+41 14015505",
    "sg:postcode":"8444",
    "sg:province":"Z\u00fcrich",
    "wof:name":"Mss Meier Software Solutions Gmbh",
    "wof:placetype":"venue"
},
  "geometry": {"coordinates":[8.6814699173,47.5617027283],"type":"Point"}
}