{
  "type": "Feature",
  "properties": {
    "iso:country":"CH",
    "sg:address":"Rigistrasse 9",
    "sg:city":"Sursee",
    "sg:orig_category":"Non-Classified Establishments",
    "sg:postcode":"6210",
    "sg:province":"Luzern",
    "wof:name":"Zoo-boutique Corinne Gut",
    "wof:placetype":"venue"
},
  "geometry": {"coordinates":[8.1022109985,47.1686668396],"type":"Point"}
}