{
  "type": "Feature",
  "properties": {
    "iso:country":"CH",
    "sg:address":"Feld 11",
    "sg:city":"N\u00e4fels",
    "sg:orig_category":"Unclassifiable Establishments",
    "sg:postcode":"8752",
    "sg:province":"Glarus",
    "wof:name":"Gida Gmbh Versicherungs- & Vorsorgeberatung",
    "wof:placetype":"venue"
},
  "geometry": {"coordinates":[9.0613031387,47.0943374634],"type":"Point"}
}