{
  "type": "Feature",
  "properties": {
    "iso:country":"CH",
    "sg:address":"M\u00fchlebach 2 6362 Stansstad. Postfach 58",
    "sg:city":"Stansstad",
    "sg:orig_category":"Bauingenieurb\u00fcros Heizung L\u00fcftung Klima Bauingenieurb\u00fcros Sanit\u00e4r",
    "sg:phone":"+41 41 612 01 41",
    "sg:postcode":"6362",
    "sg:province":"Nidwalden",
    "wof:name":"W. & A. Engineering",
    "wof:placetype":"venue"
},
  "geometry": {"coordinates":[8.344231,46.974762],"type":"Point"}
}