{
  "type": "Feature",
  "properties": {
    "addr:full":"Wilhofstrasse 14 Russikon Z\u00fcrich 8332",
    "addr:housenumber":"14",
    "addr:postcode":"8332",
    "addr:street":"Wilhofstrasse",
    "iso:country":"CH",
    "sg:address":"Wilhofstrasse 14",
    "sg:city":"Russikon",
    "sg:orig_category":"Allgemeiner Hoch U Tiefbau Hoch U Tiefbau",
    "sg:phone":"+41 81 416 39 59",
    "sg:postcode":"8332",
    "sg:province":"Z\u00fcrich",
    "wof:name":"Bossi Romano.",
    "wof:placetype":"venue"
},
  "geometry": {"coordinates":[9.837489,46.810406],"type":"Point"}
}