{
  "type": "Feature",
  "properties": {
    "iso:country":"CH",
    "sg:address":"Dorfstrasse 9 8904 Aesch. Postfach",
    "sg:city":"Aesch",
    "sg:orig_category":"Interessenvertretungen U sonstige Vereinigungen Sonstige mit Sport verbundene T\u00e4tigkeiten",
    "sg:phone":"+41 17373792",
    "sg:postcode":"8904",
    "sg:province":"Z\u00fcrich",
    "wof:name":"Interverband F\u00fcr Schwimmen (ivsch)",
    "wof:placetype":"venue"
},
  "geometry": {"coordinates":[8.4384145737,47.3371353149],"type":"Point"}
}