{
  "type": "Feature",
  "properties": {
    "iso:country":"CH",
    "sg:address":"Hauptstr. 51",
    "sg:city":"Aetingen",
    "sg:orig_category":"Mechanik",
    "sg:phone":"+41 32 661 19 64",
    "sg:postcode":"4587",
    "sg:province":"Solothurn",
    "wof:name":"Misteli Markus",
    "wof:placetype":"venue"
},
  "geometry": {"coordinates":[7.5054388046,47.1319694519],"type":"Point"}
}