{
  "type": "Feature",
  "properties": {
    "iso:country":"CH",
    "sg:address":"Gewerbestrasse 7",
    "sg:city":"Cham",
    "sg:orig_category":"Unclassifiable Establishments",
    "sg:phone":"+41 41 748 20 40",
    "sg:postcode":"6330",
    "sg:province":"Zug",
    "wof:name":"Adtcom Holdings Ag",
    "wof:placetype":"venue"
},
  "geometry": {"coordinates":[8.473233223,47.1885604858],"type":"Point"}
}