{
  "type": "Feature",
  "properties": {
    "iso:country":"CH",
    "sg:address":"Aubrigstrasse 10",
    "sg:city":"Horgen",
    "sg:orig_category":"Unternehmensberatung",
    "sg:phone":"+41 17257124",
    "sg:postcode":"8810",
    "sg:province":"Z\u00fcrich",
    "wof:name":"S. Imboden Consulting",
    "wof:placetype":"venue"
},
  "geometry": {"coordinates":[8.6021938324,47.2541618347],"type":"Point"}
}