{
  "type": "Feature",
  "properties": {
    "iso:country":"CH",
    "sg:address":"2076",
    "sg:city":"Gals",
    "sg:orig_category":"Organisationen des Gesundheitswesen",
    "sg:phone":"+41 32 338 25 21",
    "sg:postcode":"2076",
    "wof:name":"St\u00e9 Des Samaritains Gals",
    "wof:placetype":"venue"
},
  "geometry": {"coordinates":[7.0563502312,47.0308303833],"type":"Point"}
}