{
  "type": "Feature",
  "properties": {
    "iso:country":"CH",
    "sg:address":"Bahnhofplatz 6",
    "sg:city":"Baden",
    "sg:orig_category":"Vermietung U Verpachtung von eigenen Immobilien",
    "sg:postcode":"5400",
    "sg:province":"Aargau",
    "wof:name":"Ferimob Sa",
    "wof:placetype":"venue"
},
  "geometry": {"coordinates":[6.8929100037,47.1429443359],"type":"Point"}
}