{
  "type": "Feature",
  "properties": {
    "iso:country":"CH",
    "sg:address":"F\u00e4hrhaus Niederneunforn 8526 Neunforn. Postfach",
    "sg:city":"Niederneunforn",
    "sg:orig_category":"Softwareentwicklung U beratung",
    "sg:phone":"+41 52 745 29 33",
    "sg:postcode":"8525",
    "sg:province":"Thurgau",
    "wof:name":"Etafin Sa",
    "wof:placetype":"venue"
},
  "geometry": {"coordinates":[8.7669754028,47.6066246033],"type":"Point"}
}