{
  "type": "Feature",
  "properties": {
    "iso:country":"CH",
    "sg:address":"Westerholz 14",
    "sg:city":"Biel/bienne",
    "sg:orig_category":"Allgemeiner Hoch U Tiefbau Vermietung von Gebrauchsg\u00fctern",
    "sg:phone":"+41 79 432 06 22",
    "sg:postcode":"2504",
    "sg:province":"Bern",
    "wof:name":"H\u00e4ni Ag",
    "wof:placetype":"venue"
},
  "geometry": {"coordinates":[7.272936,47.150642],"type":"Point"}
}