{
  "type": "Feature",
  "properties": {
    "addr:full":"Minervastrasse 118 Z\u00fcrich Z\u00fcrich 8032",
    "addr:housenumber":"118",
    "addr:postcode":"8032",
    "addr:street":"Minervastrasse",
    "iso:country":"CH",
    "sg:address":"Minervastrasse 118",
    "sg:city":"Z\u00fcrich",
    "sg:orig_category":"Arztpraxen",
    "sg:phone":"+41 13833433",
    "sg:postcode":"8032",
    "sg:province":"Z\u00fcrich",
    "wof:name":"Dr.med.magdalena Isler Spezial\u00e4rztin Fmh",
    "wof:placetype":"venue"
},
  "geometry": {"coordinates":[8.558058,47.363895],"type":"Point"}
}