{
  "type": "Feature",
  "properties": {
    "iso:country":"CH",
    "sg:address":"Steinmattweg 9",
    "sg:city":"Dornach",
    "sg:orig_category":"Sonstige mit der Informatik verbundene T\u00e4tigkeiten",
    "sg:phone":"+41 61 702 07 31",
    "sg:postcode":"4143",
    "sg:province":"Solothurn",
    "wof:name":"Henzi Consulting",
    "wof:placetype":"venue"
},
  "geometry": {"coordinates":[7.6105651855,47.4757461548],"type":"Point"}
}