{
  "type": "Feature",
  "properties": {
    "iso:country":"CH",
    "sg:address":"Seidenweg 5 3012 Bern. Postfach",
    "sg:city":"Bern",
    "sg:orig_category":"Fussboden, Fliesen U Plattenlegerei, Tapeziererei",
    "sg:phone":"+41 31 302 77 50",
    "sg:postcode":"3005",
    "sg:province":"Bern",
    "wof:name":"Sedag, Peker Reyhan & Sedat Wand- U Deckenmontage",
    "wof:placetype":"venue"
},
  "geometry": {"coordinates":[7.4323630333,46.9540748596],"type":"Point"}
}