{
  "type": "Feature",
  "properties": {
    "iso:country":"CH",
    "sg:address":"Feldeggstrasse 2",
    "sg:city":"Glattbrugg",
    "sg:orig_category":"Dienstleistungen von Beteiligungsgesellschaften",
    "sg:phone":"+41 18087209",
    "sg:postcode":"8152",
    "sg:province":"Z\u00fcrich",
    "wof:name":"Tier\u00e4rztliche Verrechnungsstelle Gst Ag",
    "wof:placetype":"venue"
},
  "geometry": {"coordinates":[8.5611810684,47.4336967468],"type":"Point"}
}