{
  "type": "Feature",
  "properties": {
    "iso:country":"CH",
    "sg:address":"Route De Ch\u00e9salles 60",
    "sg:city":"Marly",
    "sg:orig_category":"Ingenieurb\u00fcros Datenverarbeitung",
    "sg:phone":"+41 26 436 43 83",
    "sg:postcode":"1723",
    "sg:province":"Fribourg",
    "wof:name":"Proform Sa Prototypage Rapide",
    "wof:placetype":"venue"
},
  "geometry": {"coordinates":[7.1525812149,46.7727355957],"type":"Point"}
}