{
  "type": "Feature",
  "properties": {
    "iso:country":"CH",
    "sg:address":"Dufourstrasse 153",
    "sg:city":"Z\u00fcrich",
    "sg:orig_category":"Fahrschulen, Flugschulen",
    "sg:phone":"+41 32 853 50 80",
    "sg:postcode":"8008",
    "sg:province":"Z\u00fcrich",
    "wof:name":"Willy Stauber Auto-\u00e9cole",
    "wof:placetype":"venue"
},
  "geometry": {"coordinates":[6.9187231064,47.0202217102],"type":"Point"}
}