{
  "type": "Feature",
  "properties": {
    "iso:country":"CH",
    "sg:address":"Rue Colonel-hoffmeyer 15",
    "sg:city":"Bassecourt",
    "sg:orig_category":"RESTAURANTS: TEA-ROOMS",
    "sg:postcode":"2854",
    "sg:province":"Jura",
    "wof:name":"Wyss Bernadette",
    "wof:placetype":"venue"
},
  "geometry": {"coordinates":[7.2431349754,47.3375663757],"type":"Point"}
}