{
  "type": "Feature",
  "properties": {
    "iso:country":"CH",
    "sg:address":"Via Nizzola 2",
    "sg:city":"Lugano",
    "sg:orig_category":"RESTAURANTS: TEA-ROOMS",
    "sg:phone":"+41 91 923 23 38",
    "sg:postcode":"6900",
    "sg:province":"Ticino",
    "wof:name":"Ristorante Orologio Sa Bar, Ristoranti Ecc",
    "wof:placetype":"venue"
},
  "geometry": {"coordinates":[8.9531526566,46.0057067871],"type":"Point"}
}