{
  "type": "Feature",
  "properties": {
    "iso:country":"CH",
    "sg:address":"Gutstrasse 12",
    "sg:city":"Z\u00fcrich",
    "sg:orig_category":"Architektur U Ingenieurb\u00fcros Unternehmensberatung",
    "sg:phone":"+41 12618700",
    "sg:postcode":"8055",
    "sg:province":"Z\u00fcrich",
    "wof:name":"Ren\u00e9 C. Dalla Corte Bauherren-beratung & Baumanagement",
    "wof:placetype":"venue"
},
  "geometry": {"coordinates":[8.508932,47.370754],"type":"Point"}
}