{
  "type": "Feature",
  "properties": {
    "iso:country":"CH",
    "sg:address":"Bahnhofstrasse 3",
    "sg:city":"Kerzers",
    "sg:orig_category":"Detailhandel mit Brot, Back U S\u00fcsswaren",
    "sg:phone":"+41 31 755 51 29",
    "sg:postcode":"3210",
    "sg:province":"Fribourg",
    "wof:name":"Ingold Rolf",
    "wof:placetype":"venue"
},
  "geometry": {"coordinates":[7.194058,46.974831],"type":"Point"}
}