{
  "type": "Feature",
  "properties": {
    "iso:country":"CH",
    "sg:address":"Oberdorfstrasse 28",
    "sg:city":"Flaach",
    "sg:orig_category":"Softwareentwicklung U beratung",
    "sg:phone":"+41 52 301 33 01",
    "sg:postcode":"8416",
    "sg:province":"Z\u00fcrich",
    "wof:name":"Prolingua Chris M\u00fcller Edv-dienstleistung & Software",
    "wof:placetype":"venue"
},
  "geometry": {"coordinates":[8.6144914627,47.5751724243],"type":"Point"}
}