{
  "type": "Feature",
  "properties": {
    "iso:country":"CH",
    "sg:address":"Bellerivestrasse 25 6006 Luzern. Postfach",
    "sg:city":"Luzern",
    "sg:orig_category":"Pensionskassen",
    "sg:postcode":"6004",
    "sg:province":"Luzern",
    "wof:name":"Personalf\u00fcrsorgestiftung Der Ehemaligen Bosshardt & Co Ag Luzern",
    "wof:placetype":"venue"
},
  "geometry": {"coordinates":[8.3317060471,47.0567550659],"type":"Point"}
}