{
  "type": "Feature",
  "properties": {
    "iso:country":"CH",
    "sg:address":"Aachstrasse 20",
    "sg:city":"Horn",
    "sg:orig_category":"Sonstige mit der Informatik verbundene T\u00e4tigkeiten",
    "sg:phone":"+41 71 845 23 63",
    "sg:postcode":"9326",
    "sg:province":"Thurgau",
    "wof:name":"Kecom Keller",
    "wof:placetype":"venue"
},
  "geometry": {"coordinates":[9.4632616043,47.4897994995],"type":"Point"}
}