{
  "type": "Feature",
  "properties": {
    "iso:country":"CH",
    "sg:address":"Route De Mervelier 2828 Montsevelier. Postfach",
    "sg:city":"Montsevelier",
    "sg:orig_category":"Sanit\u00e4r, Heizungs U L\u00fcftungsinstallation",
    "sg:phone":"+41 71 911 24 60",
    "sg:postcode":"2828",
    "sg:province":"Jura",
    "wof:name":"Koller Richard",
    "wof:placetype":"venue"
},
  "geometry": {"coordinates":[9.061425209,47.4653129578],"type":"Point"}
}