{
  "type": "Feature",
  "properties": {
    "iso:country":"CH",
    "sg:address":"Scheuchzerstrasse 46",
    "sg:city":"Z\u00fcrich",
    "sg:orig_category":"Fussreflexzonenmassage",
    "sg:phone":"+41 61 711 12 21",
    "sg:postcode":"8006",
    "sg:province":"Z\u00fcrich",
    "wof:name":"Ruedi Eggimann Fussreflexzonen-massage",
    "wof:placetype":"venue"
},
  "geometry": {"coordinates":[7.5880961418,47.4913902283],"type":"Point"}
}