{
  "type": "Feature",
  "properties": {
    "iso:country":"CH",
    "sg:address":"Niederernen",
    "sg:city":"Ernen",
    "sg:orig_category":"RESTAURANTS: TEA-ROOMS",
    "sg:phone":"+41 27 971 29 71",
    "sg:postcode":"3995",
    "sg:province":"Valais",
    "wof:name":"Restaurant Gommerstuba",
    "wof:placetype":"venue"
},
  "geometry": {"coordinates":[8.1366157532,46.3921165466],"type":"Point"}
}