{
  "type": "Feature",
  "properties": {
    "iso:country":"CH",
    "sg:address":"Schermenweg 9 3014 Bern. Postfach",
    "sg:city":"Bern",
    "sg:orig_category":"RESTAURANTS: TEA-ROOMS",
    "sg:postcode":"3005",
    "sg:province":"Bern",
    "wof:name":"Grunder Ruth Tea-room Polex",
    "wof:placetype":"venue"
},
  "geometry": {"coordinates":[7.4708828926,46.9644126892],"type":"Point"}
}