{
  "type": "Feature",
  "properties": {
    "iso:country":"CH",
    "sg:address":"Badenerstrasse 701 8048 Z\u00fcrich. Postfach",
    "sg:city":"Z\u00fcrich",
    "sg:orig_category":"G\u00fcterbef\u00f6rderung im Strassenverkehr",
    "sg:phone":"+41 55 410 48 78",
    "sg:postcode":"8048",
    "sg:province":"Z\u00fcrich",
    "wof:name":"Wirz Transport Ag",
    "wof:placetype":"venue"
},
  "geometry": {"coordinates":[8.7995347977,47.2133331299],"type":"Point"}
}