{
  "type": "Feature",
  "properties": {
    "iso:country":"CH",
    "sg:address":"Stutz",
    "sg:city":"Isenthal",
    "sg:orig_category":"Wasserversorgung",
    "sg:postcode":"6461",
    "sg:province":"Uri",
    "wof:name":"Wassergenossenschaft Haldi",
    "wof:placetype":"venue"
},
  "geometry": {"coordinates":[8.6788625717,46.8607788086],"type":"Point"}
}