{
  "type": "Feature",
  "properties": {
    "iso:country":"CH",
    "sg:address":"Talacher 9",
    "sg:city":"Gr\u00fcningen",
    "sg:orig_category":"Sonstige Aktivit\u00e4ten der nicht-\u00e4rztlichen Medizinalberufe",
    "sg:phone":"+41 19352268",
    "sg:postcode":"8627",
    "sg:province":"Z\u00fcrich",
    "wof:name":"Margrit B\u00f6lsterli Ern\u00e4hrungsberatung & Massagen",
    "wof:placetype":"venue"
},
  "geometry": {"coordinates":[8.7704076767,47.2837371826],"type":"Point"}
}