{
  "type": "Feature",
  "properties": {
    "iso:country":"CH",
    "sg:address":"Wydlerweg 6 8000 Z\u00fcrich. Postfach",
    "sg:city":"Z\u00fcrich",
    "sg:orig_category":"Vermietung U Verpachtung von eigenen Immobilien",
    "sg:postcode":"8047",
    "sg:province":"Z\u00fcrich",
    "wof:name":"Alpha Immobilien Und Verwaltungs Gmbh",
    "wof:placetype":"venue"
},
  "geometry": {"coordinates":[8.4853363037,47.375743866],"type":"Point"}
}