{
  "type": "Feature",
  "properties": {
    "iso:country":"CH",
    "sg:address":"Br\u00fcggackerstrasse 4 3303 Jegenstorf. Postfach",
    "sg:city":"Jegenstorf",
    "sg:orig_category":"Elektroinstallation",
    "sg:phone":"+41 31 761 14 44",
    "sg:postcode":"3303",
    "sg:province":"Bern",
    "wof:name":"D\u00fcrig & Partner Ag, Jegenstorf",
    "wof:placetype":"venue"
},
  "geometry": {"coordinates":[7.5096111298,47.0488052368],"type":"Point"}
}