{
  "type": "Feature",
  "properties": {
    "iso:country":"CH",
    "sg:address":"Heidenriedstrasse 12",
    "sg:city":"D\u00fcbendorf",
    "sg:orig_category":"Erdbewegungsarbeiten G\u00fcterbef\u00f6rderung im Strassenverkehr",
    "sg:phone":"+41 18218797",
    "sg:postcode":"8600",
    "sg:province":"Z\u00fcrich",
    "wof:name":"Walter Meier Trax-& Transportunternehmung",
    "wof:placetype":"venue"
},
  "geometry": {"coordinates":[8.6506843567,47.3934936523],"type":"Point"}
}