{
  "type": "Feature",
  "properties": {
    "iso:country":"CH",
    "sg:address":"Schweizergasse 6 8001 Z\u00fcrich. Postfach",
    "sg:city":"Z\u00fcrich",
    "sg:orig_category":"Advokaturb\u00fcros",
    "sg:phone":"+41 12114157",
    "sg:postcode":"8023",
    "sg:province":"Z\u00fcrich",
    "wof:name":"Feigel & Schlegel Advokaturb\u00fcro",
    "wof:placetype":"venue"
},
  "geometry": {"coordinates":[8.538424,47.376076],"type":"Point"}
}