{
  "type": "Feature",
  "properties": {
    "iso:country":"CH",
    "sg:address":"Hagenfirst 5317 Hettenschwil. Postfach",
    "sg:city":"Hettenschwil",
    "sg:orig_category":"Haltung von Rindern",
    "sg:postcode":"5317",
    "sg:province":"Aargau",
    "wof:name":"Fleckviehzuchtgenossenschaft Leuggern",
    "wof:placetype":"venue"
},
  "geometry": {"coordinates":[8.198184967,47.5773696899],"type":"Point"}
}