{
  "type": "Feature",
  "properties": {
    "iso:country":"CH",
    "sg:address":"Richemont Rue De 5 1202 Gen\u00e8ve. Postfach",
    "sg:city":"Gen\u00e8ve",
    "sg:orig_category":"Non-Classified Establishments",
    "sg:postcode":"1202",
    "sg:province":"Gen\u00e8ve",
    "wof:name":"Norbert Demont",
    "wof:placetype":"venue"
},
  "geometry": {"coordinates":[6.1473650932,46.2143478394],"type":"Point"}
}