{
  "type": "Feature",
  "properties": {
    "iso:country":"CH",
    "sg:address":"Solothurnstrasse 8",
    "sg:city":"Attiswil",
    "sg:orig_category":"Politische Parteien FDP",
    "sg:phone":"+41 32 637 14 93",
    "sg:postcode":"4536",
    "sg:province":"Bern",
    "wof:name":"Fdp Ortspartei Attiswil",
    "wof:placetype":"venue"
},
  "geometry": {"coordinates":[7.6124081612,47.2469367981],"type":"Point"}
}