{
  "type": "Feature",
  "properties": {
    "iso:country":"CH",
    "sg:address":"Molard Place Du 3 1204 Gen\u00e8ve. Postfach",
    "sg:city":"Gen\u00e8ve",
    "sg:orig_category":"Unclassifiable Establishments",
    "sg:postcode":"1201",
    "sg:province":"Gen\u00e8ve",
    "wof:name":"Soci\u00e9t\u00e9 De Gestion Immobili\u00e8re Et De Publicit\u00e9",
    "wof:placetype":"venue"
},
  "geometry": {"coordinates":[6.1482810974,46.2035903931],"type":"Point"}
}