{
  "type": "Feature",
  "properties": {
    "iso:country":"CH",
    "sg:address":"Bachstrasse 4",
    "sg:city":"Boniswil",
    "sg:orig_category":"Herstellung von k\u00e4lte U lufttechnischen Erzeugnissen f\u00fcr gewerbliche Zwecke",
    "sg:phone":"+41 71 755 58 88",
    "sg:postcode":"5706",
    "sg:province":"Aargau",
    "wof:name":"Schenk, Bruhin + Co Ag Altst\u00e4tten",
    "wof:placetype":"venue"
},
  "geometry": {"coordinates":[9.5554761887,47.3748550415],"type":"Point"}
}