{
  "type": "Feature",
  "properties": {
    "iso:country":"CH",
    "sg:address":"Plattenstrasse 37",
    "sg:city":"Menziken",
    "sg:orig_category":"Bauschreinerei Herstellung von Konstruktionsteilen, Fertigbauteilen U Ausbauelementen aus Holz",
    "sg:phone":"+41 62 771 19 28",
    "sg:postcode":"5737",
    "sg:province":"Aargau",
    "wof:name":"Max D\u00f6beli Ag, Bauschreinerei",
    "wof:placetype":"venue"
},
  "geometry": {"coordinates":[8.181401,47.241219],"type":"Point"}
}