{
  "type": "Feature",
  "properties": {
    "iso:country":"CH",
    "sg:address":"B\u00e4umleingasse 9 4051 Basel. Postfach",
    "sg:city":"Basel",
    "sg:orig_category":"Fachdetailhandel in Verkaufsr\u00e4umen",
    "sg:phone":"+41 61 206 97 00",
    "sg:postcode":"4051",
    "sg:province":"Basel-Stadt",
    "wof:name":"Galerie Beyeler",
    "wof:placetype":"venue"
},
  "geometry": {"coordinates":[7.5925140381,47.555065155],"type":"Point"}
}