{
  "type": "Feature",
  "properties": {
    "iso:country":"CH",
    "sg:address":"Albert-minder-weg 9",
    "sg:city":"Burgdorf",
    "sg:orig_category":"Interessenvertretungen",
    "sg:postcode":"3400",
    "sg:province":"Bern",
    "wof:name":"Obrecht Hans-stiftung",
    "wof:placetype":"venue"
},
  "geometry": {"coordinates":[7.6170978546,47.0536804199],"type":"Point"}
}