{
  "type": "Feature",
  "properties": {
    "iso:country":"CH",
    "sg:address":"Baurenacker 13",
    "sg:city":"Urdorf",
    "sg:orig_category":"Erbringung von Dienstleistungen f\u00fcr Unternehmen",
    "sg:phone":"+41 17342969",
    "sg:postcode":"8902",
    "sg:province":"Z\u00fcrich",
    "wof:name":"Decotti Gmbh",
    "wof:placetype":"venue"
},
  "geometry": {"coordinates":[8.4300546646,47.3891181946],"type":"Point"}
}