{
  "type": "Feature",
  "properties": {
    "iso:country":"CH",
    "sg:address":"Belchenstrasse 18",
    "sg:city":"Olten",
    "sg:orig_category":"Gesundheitswesen",
    "sg:phone":"+41 62 212 82 26",
    "sg:postcode":"4600",
    "sg:province":"Solothurn",
    "wof:name":"Rodiag",
    "wof:placetype":"venue"
},
  "geometry": {"coordinates":[7.90350914,47.3537864685],"type":"Point"}
}