{
  "type": "Feature",
  "properties": {
    "iso:country":"CH",
    "sg:address":"Ueberlandstrasse 14",
    "sg:city":"Z\u00fcrich",
    "sg:orig_category":"RESTAURANTS: TEA-ROOMS",
    "sg:postcode":"8051",
    "sg:province":"Z\u00fcrich",
    "wof:name":"Taverna Turf Apollo Griechische Spezialit\u00e4ten, Marinis & Co",
    "wof:placetype":"venue"
},
  "geometry": {"coordinates":[8.5663700104,47.4073181152],"type":"Point"}
}