{
  "type": "Feature",
  "properties": {
    "iso:country":"CH",
    "sg:address":"Rindermarkt 3",
    "sg:city":"Z\u00fcrich",
    "sg:orig_category":"Detailhandel mit Uhren U Schmuck",
    "sg:phone":"+41 12613388",
    "sg:postcode":"8001",
    "sg:province":"Z\u00fcrich",
    "wof:name":"Teddy Friedmann Goldschmiede",
    "wof:placetype":"venue"
},
  "geometry": {"coordinates":[8.543970108,47.3723907471],"type":"Point"}
}