{
  "type": "Feature",
  "properties": {
    "iso:country":"CH",
    "sg:address":"Grand-rue 1071 Chexbres Case Postale 38",
    "sg:city":"Chexbres",
    "sg:orig_category":"Detailhandel mit Radio U Fernsehger\u00e4ten",
    "sg:phone":"+41 21 946 30 77",
    "sg:postcode":"1071",
    "sg:province":"Vaud",
    "wof:name":"Paul Jacoby Radio-tv",
    "wof:placetype":"venue"
},
  "geometry": {"coordinates":[6.7769379616,46.4816894531],"type":"Point"}
}