{
  "type": "Feature",
  "properties": {
    "iso:country":"CH",
    "sg:address":"Sandgrube",
    "sg:city":"Grossdietwil",
    "sg:orig_category":"G\u00fcterbef\u00f6rderung im Strassenverkehr",
    "sg:phone":"+41 62 927 13 56",
    "sg:postcode":"6146",
    "sg:province":"Luzern",
    "wof:name":"Blum Pius Transporte",
    "wof:placetype":"venue"
},
  "geometry": {"coordinates":[7.8844628334,47.172958374],"type":"Point"}
}