{
  "type": "Feature",
  "properties": {
    "iso:country":"CH",
    "sg:address":"Altes Riedg\u00e4ssli 28 3113 Rubigen. Postfach 198",
    "sg:city":"Rubigen",
    "sg:orig_category":"Herstellung von Metallerzeugnissen ohne Maschinenbau Herstellung von k\u00e4lte U lufttechnischen Erzeugn",
    "sg:phone":"+41 21 731 22 65",
    "sg:postcode":"3113",
    "sg:province":"Bern",
    "wof:name":"Isolux Sa",
    "wof:placetype":"venue"
},
  "geometry": {"coordinates":[6.6639499664,46.5902061462],"type":"Point"}
}