{
  "type": "Feature",
  "properties": {
    "iso:country":"CH",
    "sg:address":"Alte Landstrasse 31b",
    "sg:city":"Rehetobel",
    "sg:orig_category":"Zimmerei, Dachdeckerei, Bauspenglerei U Abdichtung",
    "sg:phone":"+41 71 870 01 66",
    "sg:postcode":"9038",
    "sg:province":"Appenzell Ausserrhoden",
    "wof:name":"Gm\u00fcr Dach + Wand Gmbh",
    "wof:placetype":"venue"
},
  "geometry": {"coordinates":[9.4900770187,47.4255867004],"type":"Point"}
}