{
  "type": "Feature",
  "properties": {
    "iso:country":"CH",
    "sg:address":"Les Baumes Chandossel",
    "sg:city":"Villarepos",
    "sg:orig_category":"Landw. Genossenschaften Dresch",
    "sg:phone":"+41 26 675 13 69",
    "sg:postcode":"1583",
    "sg:province":"Fribourg",
    "wof:name":"Gottlieb Maeder Battoir",
    "wof:placetype":"venue"
},
  "geometry": {"coordinates":[7.080766201,46.8909759521],"type":"Point"}
}