{
  "type": "Feature",
  "properties": {
    "iso:country":"CH",
    "sg:address":"Gotthelfstrasse 44",
    "sg:city":"Z\u00fcrich",
    "sg:orig_category":"Detailhandel mit elektrischen Haushalts, Radio U Fernsehger\u00e4ten ohne ausgepr\u00e4gten Schwerpunkt",
    "sg:phone":"+41 14639400",
    "sg:postcode":"8003",
    "sg:province":"Z\u00fcrich",
    "wof:name":"Hovelec, Howald H. Elektroapparate; Handel, Reparatur Usw.",
    "wof:placetype":"venue"
},
  "geometry": {"coordinates":[8.5208053589,47.3687362671],"type":"Point"}
}