{
  "type": "Feature",
  "properties": {
    "iso:country":"CH",
    "sg:address":"Hauptstrasse 17",
    "sg:city":"Einsiedeln",
    "sg:orig_category":"Detailhandel mit Blumen U Pflanzen Fachdetailhandel in Verkaufsr\u00e4umen",
    "sg:phone":"+41 55 412 30 44",
    "sg:postcode":"8840",
    "sg:province":"Schwyz",
    "wof:name":"K\u00e4lin-steiner Alice",
    "wof:placetype":"venue"
},
  "geometry": {"coordinates":[8.744774,47.12759],"type":"Point"}
}