{
  "type": "Feature",
  "properties": {
    "iso:country":"CH",
    "sg:address":"Bollwiesstrasse 16",
    "sg:city":"Jona",
    "sg:orig_category":"Herstellung von Konstruktionsteilen, Fertigbauteilen U Ausbauelementen aus Holz",
    "sg:phone":"+41 55 212 49 94",
    "sg:postcode":"8645",
    "sg:province":"St. Gallen",
    "wof:name":"B\u00e4renzaun Hauser Max Garten Und Landschaftsarchitekt Htl/slpa",
    "wof:placetype":"venue"
},
  "geometry": {"coordinates":[8.8444290161,47.2309684753],"type":"Point"}
}