{
  "type": "Feature",
  "properties": {
    "iso:country":"CH",
    "sg:address":"Piz Lagalb",
    "sg:city":"Pontresina",
    "sg:classifiers":[
        {
            "category":"Restaurant",
            "type":"Food & Drink"
        }
    ],
    "sg:phone":"+41 81 842 61 82",
    "sg:postcode":"7504",
    "sg:province":"Graubunden",
    "wof:name":"Bergrestaurant Piz Lagalb",
    "wof:placetype":"venue"
},
  "geometry": {"coordinates":[9.8989448547,46.4966964722],"type":"Point"}
}