{
  "type": "Feature",
  "properties": {
    "iso:country":"CH",
    "sg:address":"G\u00e4nsackerstrasse 27",
    "sg:city":"K\u00fcttigen",
    "sg:orig_category":"Erdbewegungsarbeiten",
    "sg:phone":"+41 62 827 27 60",
    "sg:postcode":"5024",
    "sg:province":"Aargau",
    "wof:name":"J\u00f6rg Iberg Traxbetrieb",
    "wof:placetype":"venue"
},
  "geometry": {"coordinates":[8.0510959625,47.4143333435],"type":"Point"}
}