{
  "type": "Feature",
  "properties": {
    "iso:country":"CH",
    "sg:address":"Sandweg 52",
    "sg:city":"Allschwil",
    "sg:classifiers":[
        {
            "category":"Wholesale",
            "subcategory":"Construction Materials",
            "type":"Manufacturing & Wholesale Goods"
        }
    ],
    "sg:phone":"+41 61 307 90 00",
    "sg:postcode":"4123",
    "sg:province":"Basel-Landschaft",
    "sg:tags":[
        "bandaging",
        "materials",
        "dressing"
    ],
    "wof:name":"Eisenhut - Vet Ag",
    "wof:placetype":"venue"
},
  "geometry": {"coordinates":[7.557654,47.551147],"type":"Point"}
}