{
  "type": "Feature",
  "properties": {
    "iso:country":"CH",
    "sg:address":"Chemin Des Cornillons 18",
    "sg:city":"Chamb\u00e9sy",
    "sg:orig_category":"Fachdetailhandel in Verkaufsr\u00e4umen",
    "sg:postcode":"1292",
    "sg:province":"Gen\u00e8ve",
    "wof:name":"Beyeler Gaby",
    "wof:placetype":"venue"
},
  "geometry": {"coordinates":[6.1450099945,46.2405700684],"type":"Point"}
}