{
  "type": "Feature",
  "properties": {
    "iso:country":"CH",
    "sg:address":"Constituante Rue De La 5",
    "sg:city":"Del\u00e9mont",
    "sg:orig_category":"RESTAURANTS: TEA-ROOMS",
    "sg:postcode":"2800",
    "sg:province":"Jura",
    "wof:name":"Gesyja S\u00e0rl",
    "wof:placetype":"venue"
},
  "geometry": {"coordinates":[7.3419671059,47.3648223877],"type":"Point"}
}