{
  "type": "Feature",
  "properties": {
    "iso:country":"CH",
    "sg:address":"6913",
    "sg:city":"Carabbia",
    "sg:orig_category":"Grosshandel mit Holz U Baustoffen",
    "sg:phone":"+41 24 499 23 16",
    "sg:postcode":"6913",
    "sg:province":"Ticino",
    "wof:name":"Commerce De Bois Du Chablais Cbc S\u00e0rl",
    "wof:placetype":"venue"
},
  "geometry": {"coordinates":[6.9991388321,46.287311554],"type":"Point"}
}