{
  "type": "Feature",
  "properties": {
    "iso:country":"CH",
    "sg:address":"Steinengraben 71",
    "sg:city":"Basel",
    "sg:orig_category":"Nahrungsmittel-Industrie: Rohstoffe",
    "sg:postcode":"4051",
    "sg:province":"Basel-Stadt",
    "wof:name":"Ayasofya, Koc Sami",
    "wof:placetype":"venue"
},
  "geometry": {"coordinates":[7.58685112,47.5529136658],"type":"Point"}
}