{
  "type": "Feature",
  "properties": {
    "iso:country":"CH",
    "sg:address":"Zopfm\u00e4ttli 10",
    "sg:city":"Sch\u00fcpfheim",
    "sg:orig_category":"Non-Classified Establishments",
    "sg:postcode":"6170",
    "sg:province":"Luzern",
    "wof:name":"Stadelmann Immobilien",
    "wof:placetype":"venue"
},
  "geometry": {"coordinates":[8.0190982819,46.9502105713],"type":"Point"}
}