{
  "type": "Feature",
  "properties": {
    "iso:country":"CH",
    "sg:address":"Rathausgasse 9",
    "sg:city":"Aarau",
    "sg:orig_category":"Innenarchitekturb\u00fcros",
    "sg:phone":"+41 62 822 57 10",
    "sg:postcode":"5000",
    "sg:province":"Aargau",
    "wof:name":"Fridolin Menzi Innenarchitektur",
    "wof:placetype":"venue"
},
  "geometry": {"coordinates":[8.0436544418,47.3930511475],"type":"Point"}
}