{
  "type": "Feature",
  "properties": {
    "iso:country":"CH",
    "sg:address":"Alpsteinstrasse 10a 9100 Herisau. Postfach",
    "sg:city":"Herisau",
    "sg:orig_category":"Grosshandel mit Erzen U Metallen",
    "sg:phone":"+41 71 351 12 26",
    "sg:postcode":"9101",
    "sg:province":"Appenzell Ausserrhoden",
    "wof:name":"Dobler Eisenwaren Ag",
    "wof:placetype":"venue"
},
  "geometry": {"coordinates":[9.2789354324,47.3784637451],"type":"Point"}
}