{
  "type": "Feature",
  "properties": {
    "iso:country":"CH",
    "sg:address":"Rue Fran\u00e7ois-bonivard 10",
    "sg:city":"Gen\u00e8ve",
    "sg:orig_category":"Unternehmensberatung",
    "sg:phone":"+41 22 309 47 00",
    "sg:postcode":"1204",
    "sg:province":"Gen\u00e8ve",
    "wof:name":"Orga Consult Sa Etudes, Conseil Et R\u00e9alisation Dans Les Dom. De L'organisation D'entreprises Etc",
    "wof:placetype":"venue"
},
  "geometry": {"coordinates":[6.1473870277,46.2083854675],"type":"Point"}
}