{
  "type": "Feature",
  "properties": {
    "iso:country":"CH",
    "sg:address":"B\u00e4renhubelstrasse 36",
    "sg:city":"Zofingen",
    "sg:orig_category":"Politische Parteien FDP Vereine Damen",
    "sg:phone":"+41 62 751 26 75",
    "sg:postcode":"4800",
    "sg:province":"Aargau",
    "wof:name":"Fdp Frauengruppe Zofingen",
    "wof:placetype":"venue"
},
  "geometry": {"coordinates":[7.9507708549,47.2926368713],"type":"Point"}
}