{
  "type": "Feature",
  "properties": {
    "iso:country":"CH",
    "sg:address":"Hitsch-huus",
    "sg:city":"Fanas",
    "sg:classifiers":[
        {
            "category":"Travel",
            "subcategory":"Hotels & Motels",
            "type":"Entertainment"
        }
    ],
    "sg:phone":"+41 18445585",
    "sg:postcode":"7215",
    "sg:province":"Graubunden",
    "sg:tags":[
        "hotels",
        "mit",
        "restaurant"
    ],
    "wof:name":"Abv, Andrea Brunner Veranstaltungsorganisationen",
    "wof:placetype":"venue"
},
  "geometry": {"coordinates":[8.4358196259,47.4598426819],"type":"Point"}
}