{
  "type": "Feature",
  "properties": {
    "iso:country":"CH",
    "sg:address":"Budron En E4",
    "sg:city":"Mont-sur-lausanne",
    "sg:orig_category":"Druckweiterverarbeitung",
    "sg:postcode":"1052",
    "sg:province":"Vaud",
    "wof:name":"Miao Sa",
    "wof:placetype":"venue"
},
  "geometry": {"coordinates":[9.128364563,46.2376060486],"type":"Point"}
}