{
  "type": "Feature",
  "properties": {
    "iso:country":"CH",
    "sg:address":"Wiesenstr. 5",
    "sg:city":"T\u00fcbach",
    "sg:classifiers":[
        {
            "category":"Shopping",
            "subcategory":"Crafts & Fabrics",
            "type":"Retail Goods"
        }
    ],
    "sg:phone":"+41 71 841 47 21",
    "sg:postcode":"9327",
    "sg:province":"St. Gallen",
    "sg:tags":[
        "textile",
        "clothing"
    ],
    "wof:name":"Vorhang K\u00d6ppel",
    "wof:placetype":"venue"
},
  "geometry": {"coordinates":[9.4597787857,47.4857673645],"type":"Point"}
}