{
  "type": "Feature",
  "properties": {
    "addr:full":"Via Muraccio 7 Ascona Ticino 6612",
    "addr:housenumber":"7",
    "addr:postcode":"6612",
    "addr:street":"Via Muraccio",
    "iso:country":"CH",
    "sg:address":"Via Muraccio 7",
    "sg:city":"Ascona",
    "sg:orig_category":"Datenverarbeitungsdienste Sonstige mit der Informatik verbundene T\u00e4tigkeiten",
    "sg:phone":"+41 19203258",
    "sg:postcode":"6612",
    "sg:province":"Ticino",
    "wof:name":"Wfe Fuchs Werner Engineering",
    "wof:placetype":"venue"
},
  "geometry": {"coordinates":[8.773571,46.154457],"type":"Point"}
}