{
  "type": "Feature",
  "properties": {
    "iso:country":"CH",
    "sg:address":"Brunnenweg 5",
    "sg:city":"M\u00fcnchenbuchsee",
    "sg:orig_category":"Politische Parteien SVP",
    "sg:phone":"+41 31 869 10 70",
    "sg:postcode":"3053",
    "sg:province":"Bern",
    "wof:name":"Svp Ortspartei M\u00fcnchenbuchsee",
    "wof:placetype":"venue"
},
  "geometry": {"coordinates":[7.4496469498,47.0188064575],"type":"Point"}
}