{
  "type": "Feature",
  "properties": {
    "iso:country":"CH",
    "sg:address":"Guggiweg 3",
    "sg:city":"Luzern",
    "sg:orig_category":"Herstellung von sonstigen elektrischen Ausr\u00fcstungen",
    "sg:phone":"+41 41 317 20 50",
    "sg:postcode":"6005",
    "sg:province":"Luzern",
    "wof:name":"Conwys Ag",
    "wof:placetype":"venue"
},
  "geometry": {"coordinates":[8.2998542786,47.0433807373],"type":"Point"}
}