{
  "type": "Feature",
  "properties": {
    "iso:country":"CH",
    "sg:address":"Bernstrasse Ost 52 5034 Suhr. Postfach 248",
    "sg:city":"Suhr",
    "sg:orig_category":"Textilveredlung",
    "sg:phone":"+41 62 842 09 10",
    "sg:postcode":"5034",
    "sg:province":"Aargau",
    "wof:name":"Tds Textildruckerei Suhr Ag",
    "wof:placetype":"venue"
},
  "geometry": {"coordinates":[8.0817070007,47.3726043701],"type":"Point"}
}