{
  "type": "Feature",
  "properties": {
    "iso:country":"CH",
    "sg:address":"Am Rotsee",
    "sg:city":"Luzern",
    "sg:orig_category":"Unclassifiable Establishments",
    "sg:phone":"+41 41 210 11 44",
    "sg:postcode":"6000",
    "sg:province":"Luzern",
    "wof:name":"Ps Holding Ag",
    "wof:placetype":"venue"
},
  "geometry": {"coordinates":[8.4066858292,46.9998283386],"type":"Point"}
}