{
  "type": "Feature",
  "properties": {
    "iso:country":"CH",
    "sg:address":"Casa S.damiano Via Maraini 58",
    "sg:city":"Savosa",
    "sg:orig_category":"Sonstige k\u00fcnstlerische U schriftstellerische T\u00e4tigkeiten U Darbietungen",
    "sg:phone":"+41 91 967 26 86",
    "sg:postcode":"6942",
    "sg:province":"Ticino",
    "wof:name":"Brigitta Enz Atelier Di Pittura",
    "wof:placetype":"venue"
},
  "geometry": {"coordinates":[8.9505434036,46.0234375],"type":"Point"}
}