{
  "type": "Feature",
  "properties": {
    "iso:country":"CH",
    "sg:address":"Hauptstrasse 15 2562 Port. Postfach",
    "sg:city":"Port",
    "sg:orig_category":"RESTAURANTS: TEA-ROOMS",
    "sg:phone":"+41 32 333 71 13",
    "sg:postcode":"2562",
    "sg:province":"Bern",
    "wof:name":"Guggisberg-schneider Ernst",
    "wof:placetype":"venue"
},
  "geometry": {"coordinates":[7.2521209717,47.1163330078],"type":"Point"}
}