{
  "type": "Feature",
  "properties": {
    "iso:country":"CH",
    "sg:address":"Murtenstrasse 221",
    "sg:city":"Bern",
    "sg:orig_category":"Non-Classified Establishments",
    "sg:postcode":"3027",
    "sg:province":"Bern",
    "wof:name":"Veloladen Bern Gmbh J\u00f6rgensen",
    "wof:placetype":"venue"
},
  "geometry": {"coordinates":[7.3988227844,46.9491195679],"type":"Point"}
}