{
  "type": "Feature",
  "properties": {
    "iso:country":"CH",
    "sg:address":"Riedstrasse 10",
    "sg:city":"Dietikon",
    "sg:orig_category":"Spielsalons",
    "sg:phone":"+41 17415262",
    "sg:postcode":"8953",
    "sg:province":"Z\u00fcrich",
    "wof:name":"Stefan Holenstein Billard-center Pink Billino",
    "wof:placetype":"venue"
},
  "geometry": {"coordinates":[8.3948001862,47.42004776],"type":"Point"}
}