{
  "type": "Feature",
  "properties": {
    "iso:country":"CH",
    "sg:address":"Seefeldstrasse 329",
    "sg:city":"Z\u00fcrich",
    "sg:orig_category":"Maler U Glasergewerbe",
    "sg:phone":"+41 13818714",
    "sg:postcode":"8008",
    "sg:province":"Z\u00fcrich",
    "wof:name":"Corti + Felger Malergesch\u00e4fte Gmbh",
    "wof:placetype":"venue"
},
  "geometry": {"coordinates":[8.5650539398,47.3468170166],"type":"Point"}
}