{
  "type": "Feature",
  "properties": {
    "addr:full":"Niklaus Konrad-strasse 25 Solothurn Solothurn 4500",
    "addr:housenumber":"25",
    "addr:postcode":"4500",
    "addr:street":"Niklaus Konrad-Strasse",
    "iso:country":"CH",
    "sg:address":"Niklaus Konrad-strasse 25",
    "sg:city":"Solothurn",
    "sg:orig_category":"Arztpraxen",
    "sg:phone":"+41 32 622 73 44",
    "sg:postcode":"4500",
    "sg:province":"Solothurn",
    "wof:name":"Dr.med.anton Meyer Spezialarzt Fmh",
    "wof:placetype":"venue"
},
  "geometry": {"coordinates":[7.54201,47.205055],"type":"Point"}
}