{
  "type": "Feature",
  "properties": {
    "iso:country":"CH",
    "sg:address":"Langenjohnstrasse 9 7000 Chur. Postfach",
    "sg:city":"Chur",
    "sg:orig_category":"Non-Classified Establishments",
    "sg:phone":"+41 81 252 38 90",
    "sg:postcode":"7000",
    "sg:province":"Graubunden",
    "wof:name":"Controll-spedition-organisation Conspedo Ag",
    "wof:placetype":"venue"
},
  "geometry": {"coordinates":[9.5405721664,46.8563957214],"type":"Point"}
}