{
  "type": "Feature",
  "properties": {
    "addr:full":"Lausanne Rue De 5 Fribourg Fribourg 1700",
    "addr:housenumber":"5",
    "addr:postcode":"1700",
    "addr:street":"Rue De",
    "iso:country":"CH",
    "sg:address":"Lausanne Rue De 5",
    "sg:city":"Fribourg",
    "sg:orig_category":"Bau von Strassen, Sportanlagen U Bahnverkehrsstrecken",
    "sg:phone":"+41 26 436 39 40",
    "sg:postcode":"1700",
    "sg:province":"Fribourg",
    "wof:name":"Deco Piscine S\u00e0rl",
    "wof:placetype":"venue"
},
  "geometry": {"coordinates":[7.160615,46.806194],"type":"Point"}
}