{
  "type": "Feature",
  "properties": {
    "iso:country":"CH",
    "sg:address":"Limmattalstrasse 195",
    "sg:city":"Z\u00fcrich",
    "sg:orig_category":"Fachdetailhandel in Verkaufsr\u00e4umen",
    "sg:phone":"+41 13419669",
    "sg:postcode":"8049",
    "sg:province":"Z\u00fcrich",
    "wof:name":"File 1, Inhaber Scarcia G.",
    "wof:placetype":"venue"
},
  "geometry": {"coordinates":[8.4981031418,47.4019126892],"type":"Point"}
}