{
  "type": "Feature",
  "properties": {
    "iso:country":"CH",
    "sg:address":"Rue Auguste-bachelin 1",
    "sg:city":"Marin-epagnier",
    "sg:orig_category":"Physiotherapie",
    "sg:phone":"+41 32 753 66 60",
    "sg:postcode":"2074",
    "sg:province":"Neuch\u00e2tel",
    "wof:name":"Doroth\u00e9e Duplain Physioth\u00e9rapie",
    "wof:placetype":"venue"
},
  "geometry": {"coordinates":[6.9997940063,47.0093154907],"type":"Point"}
}