{
  "type": "Feature",
  "properties": {
    "iso:country":"CH",
    "sg:address":"Waldheim",
    "sg:city":"Vitznau",
    "sg:classifiers":[
        {
            "category":"Travel",
            "subcategory":"Hotels & Motels",
            "type":"Entertainment"
        }
    ],
    "sg:phone":"+41 41 397 11 74",
    "sg:postcode":"6354",
    "sg:province":"Luzern",
    "sg:tags":[
        "hotels",
        "mit",
        "restaurant"
    ],
    "wof:name":"H\u00e4ner, Kurt",
    "wof:placetype":"venue"
},
  "geometry": {"coordinates":[8.4833097458,47.0103416443],"type":"Point"}
}