{
  "type": "Feature",
  "properties": {
    "iso:country":"CH",
    "sg:address":"Ober-schluck 123 Hofstatt 6156 Luthern. Postfach",
    "sg:city":"Hofstatt",
    "sg:orig_category":"Non-Classified Establishments",
    "sg:postcode":"6154",
    "sg:province":"Luzern",
    "wof:name":"Gartenbau Alt, Ihr Partner F\u00fcr Unterhalt Und Gestaltung",
    "wof:placetype":"venue"
},
  "geometry": {"coordinates":[7.9161782265,47.059223175],"type":"Point"}
}