{
  "type": "Feature",
  "properties": {
    "iso:country":"CH",
    "sg:address":"Oberdorfstrasse 10",
    "sg:city":"Hunzenschwil",
    "sg:orig_category":"Vermittlung von Immobilien",
    "sg:phone":"+41 62 897 29 04",
    "sg:postcode":"5502",
    "sg:province":"Aargau",
    "wof:name":"Immobilien Ag",
    "wof:placetype":"venue"
},
  "geometry": {"coordinates":[8.1180229187,47.3809890747],"type":"Point"}
}