{
  "type": "Feature",
  "properties": {
    "iso:country":"CH",
    "sg:address":"Bahnhofplatz 1 3011 Bern. Postfach",
    "sg:city":"Bern",
    "sg:orig_category":"Advokaturb\u00fcros",
    "sg:phone":"+41 55 442 13 21",
    "sg:postcode":"3001",
    "sg:province":"Bern",
    "wof:name":"Dr.alois Dobler Advokaturb\u00fcro",
    "wof:placetype":"venue"
},
  "geometry": {"coordinates":[8.852939,47.188793],"type":"Point"}
}