{
  "type": "Feature",
  "properties": {
    "iso:country":"CH",
    "sg:address":"Haldenstrasse 5",
    "sg:city":"Baar",
    "sg:orig_category":"Grosshandel mit Eisenwaren sowie Installationsbedarf f\u00fcr Gas, Wasser U Heizung Herstellung von k\u00e4lte",
    "sg:phone":"+41 41 761 10 10",
    "sg:postcode":"6340",
    "sg:province":"Zug",
    "wof:name":"Bertair Ag",
    "wof:placetype":"venue"
},
  "geometry": {"coordinates":[8.5383815765,47.1966171265],"type":"Point"}
}