{
  "type": "Feature",
  "properties": {
    "iso:country":"CH",
    "sg:address":"Nussbomstuck",
    "sg:city":"Gr\u00fcsch",
    "sg:orig_category":"Sportvereine Turnen Vereine Damen",
    "sg:postcode":"7214",
    "sg:province":"Graubunden",
    "wof:name":"Damenturnverein Landquart",
    "wof:placetype":"venue"
},
  "geometry": {"coordinates":[9.6476259232,46.9786338806],"type":"Point"}
}