{
  "type": "Feature",
  "properties": {
    "iso:country":"CH",
    "sg:address":"1720",
    "sg:city":"Corminboeuf",
    "sg:orig_category":"Vorschulen, Kinderg\u00e4rten",
    "sg:phone":"+41 26 660 46 33",
    "sg:postcode":"1720",
    "sg:province":"Fribourg",
    "wof:name":"Ecole Enfantine",
    "wof:placetype":"venue"
},
  "geometry": {"coordinates":[7.1783599854,46.7523612976],"type":"Point"}
}