{
  "type": "Feature",
  "properties": {
    "iso:country":"CH",
    "sg:address":"1648",
    "sg:city":"Hauteville",
    "sg:orig_category":"Darlehenskassen U Raiffeisenbanken",
    "sg:phone":"+41 26 927 19 53",
    "sg:postcode":"1648",
    "sg:province":"Fribourg",
    "wof:name":"Banque Raiffeisen",
    "wof:placetype":"venue"
},
  "geometry": {"coordinates":[7.15779,46.633709],"type":"Point"}
}