{
  "type": "Feature",
  "properties": {
    "iso:country":"CH",
    "sg:address":"Meierh\u00f6flistrasse 3",
    "sg:city":"Emmenbr\u00fccke",
    "sg:orig_category":"Detailhandel mit Brot, Back U S\u00fcsswaren",
    "sg:phone":"+41 41 260 33 23",
    "sg:postcode":"6020",
    "sg:province":"Luzern",
    "wof:name":"Beck Koch Ag B\u00e4ckerei-konditorei",
    "wof:placetype":"venue"
},
  "geometry": {"coordinates":[8.287773,47.071354],"type":"Point"}
}