{
  "type": "Feature",
  "properties": {
    "iso:country":"CH",
    "sg:address":"9490",
    "sg:city":"Vaduz",
    "sg:orig_category":"Strassenverkehrs\u00e4mter and -inspektorate",
    "sg:postcode":"9490",
    "wof:name":"Motorfahrzeugkontrolle Des F\u00fcrstentums Liechtenstein",
    "wof:placetype":"venue"
},
  "geometry": {"coordinates":[9.5218658447,47.1378669739],"type":"Point"}
}