{
  "type": "Feature",
  "properties": {
    "iso:country":"CH",
    "sg:address":"Zwinglistrasse 28",
    "sg:city":"St.gallen",
    "sg:orig_category":"Sportvereine Turnen Vereine Damen",
    "sg:phone":"+41 71 858 50 68",
    "sg:postcode":"9000",
    "sg:province":"St. Gallen",
    "wof:name":"Damenriege Staad",
    "wof:placetype":"venue"
},
  "geometry": {"coordinates":[9.5361146927,47.4780311584],"type":"Point"}
}