{
  "type": "Feature",
  "properties": {
    "iso:country":"CH",
    "sg:address":"T\u00fcffenwies 16",
    "sg:city":"Z\u00fcrich",
    "sg:orig_category":"Polyolefins",
    "sg:phone":"+41 14364040",
    "sg:postcode":"8048",
    "sg:province":"Z\u00fcrich",
    "wof:name":"Sika Schweiz Ag",
    "wof:placetype":"venue"
},
  "geometry": {"coordinates":[8.4787302017,47.3856201172],"type":"Point"}
}