{
  "type": "Feature",
  "properties": {
    "addr:full":"Rigistrasse 10 Wettingen Aargau 5430",
    "addr:housenumber":"10",
    "addr:postcode":"5430",
    "addr:street":"Rigistrasse",
    "iso:country":"CH",
    "sg:address":"Rigistrasse 10",
    "sg:city":"Wettingen",
    "sg:orig_category":"Aktivit\u00e4ten der Krankenschwestern U Hebammen, Hauspflege Organisationen des Gesundheitswesen",
    "sg:phone":"+41 56 426 30 20",
    "sg:postcode":"5430",
    "sg:province":"Aargau",
    "wof:name":"Spitex Haus-& Krankenpflegeverein",
    "wof:placetype":"venue"
},
  "geometry": {"coordinates":[8.320708,47.466438],"type":"Point"}
}