{
  "type": "Feature",
  "properties": {
    "iso:country":"CH",
    "sg:address":"1812",
    "sg:city":"Rivaz",
    "sg:orig_category":"Landesverteidigung, Sozialversicherung \u00d6ffentliche Verwaltung",
    "sg:phone":"+41 21 946 16 95",
    "sg:postcode":"1812",
    "wof:name":"Administration Communale Protection Civile",
    "wof:placetype":"venue"
},
  "geometry": {"coordinates":[6.7786898613,46.4763259888],"type":"Point"}
}