{
  "type": "Feature",
  "properties": {
    "iso:country":"CH",
    "sg:address":"Schulhausstrasse 31",
    "sg:city":"Kriegstetten",
    "sg:orig_category":"Herstellung von Metallkonstruktionen Mechanik",
    "sg:phone":"+41 32 675 59 49",
    "sg:postcode":"4566",
    "sg:province":"Solothurn",
    "wof:name":"Otto Kofmel Schlosserei & Metallbau",
    "wof:placetype":"venue"
},
  "geometry": {"coordinates":[7.6015601158,47.1760139465],"type":"Point"}
}