{
  "type": "Feature",
  "properties": {
    "iso:country":"CH",
    "sg:address":"Haus Baptist Blatter",
    "sg:city":"Ulrichen",
    "sg:orig_category":"Allgemeiner Hoch U Tiefbau",
    "sg:postcode":"3988",
    "sg:province":"Valais",
    "wof:name":"Bau Ag Ulrichen",
    "wof:placetype":"venue"
},
  "geometry": {"coordinates":[8.30434,46.506405],"type":"Point"}
}