{
  "type": "Feature",
  "properties": {
    "iso:country":"CH",
    "sg:address":"Schaffhauserstrasse 76 8302 Kloten. Postfach 1111",
    "sg:city":"Kloten",
    "sg:orig_category":"Fachdetailhandel in Verkaufsr\u00e4umen",
    "sg:phone":"+41 18132336",
    "sg:postcode":"8302",
    "sg:province":"Z\u00fcrich",
    "wof:name":"Schneider Uhren Bijouterie Kloten",
    "wof:placetype":"venue"
},
  "geometry": {"coordinates":[8.5800275803,47.4461746216],"type":"Point"}
}