{
  "type": "Feature",
  "properties": {
    "iso:country":"CH",
    "sg:address":"Gewerbestrasse 19 4512 Bellach. Postfach",
    "sg:city":"Bellach",
    "sg:orig_category":"Wirtschafts- and Arbeitgeberverb\u00e4nde",
    "sg:postcode":"4512",
    "sg:province":"Solothurn",
    "wof:name":"Metall-union Der Stadt So C/o Mab Amsler Ag",
    "wof:placetype":"venue"
},
  "geometry": {"coordinates":[7.4972038269,47.2104797363],"type":"Point"}
}