{
  "type": "Feature",
  "properties": {
    "iso:country":"CH",
    "sg:address":"3053",
    "sg:city":"M\u00fcnchenbuchsee",
    "sg:orig_category":"Verwertung von Milch",
    "sg:postcode":"3053",
    "sg:province":"Bern",
    "wof:name":"K\u00e4sereigenossenschaft M\u00fcnchenbuchsee",
    "wof:placetype":"venue"
},
  "geometry": {"coordinates":[7.4505391121,47.0214271545],"type":"Point"}
}