{
  "type": "Feature",
  "properties": {
    "iso:country":"CH",
    "sg:address":"Zone Artisanale La Chaux 1430 Orges. Postfach",
    "sg:city":"Orges",
    "sg:orig_category":"Non-Classified Establishments",
    "sg:phone":"+41 24 445 05 74",
    "sg:postcode":"1430",
    "sg:province":"Vaud",
    "wof:name":"H. Services S\u00e0rl Transport De Mat\u00e9riel, Logistique Etc",
    "wof:placetype":"venue"
},
  "geometry": {"coordinates":[6.5868592262,46.8078918457],"type":"Point"}
}