{
  "type": "Feature",
  "properties": {
    "iso:country":"CH",
    "sg:address":"Via Zurigo 1",
    "sg:city":"Lugano",
    "sg:orig_category":"Non-Classified Establishments",
    "sg:postcode":"6900",
    "sg:province":"Ticino",
    "wof:name":"Di Marco Sebastiano",
    "wof:placetype":"venue"
},
  "geometry": {"coordinates":[8.9562759399,46.0112724304],"type":"Point"}
}