{
  "type": "Feature",
  "properties": {
    "iso:country":"CH",
    "sg:address":"Weinbergstrasse 2",
    "sg:city":"Baar",
    "sg:orig_category":"Sonstige mit Sport verbundene T\u00e4tigkeiten",
    "sg:postcode":"6340",
    "sg:province":"Zug",
    "wof:name":"Graf Sport",
    "wof:placetype":"venue"
},
  "geometry": {"coordinates":[8.5363292694,47.1847267151],"type":"Point"}
}