{
  "type": "Feature",
  "properties": {
    "iso:country":"CH",
    "sg:address":"Rain 225",
    "sg:city":"Niederbuchsiten",
    "sg:orig_category":"Autotransporte international",
    "sg:phone":"+41 79 330 22 31",
    "sg:postcode":"4626",
    "sg:province":"Solothurn",
    "wof:name":"Josef Brunner Internationale Transporte",
    "wof:placetype":"venue"
},
  "geometry": {"coordinates":[7.783617,47.291927],"type":"Point"}
}