{
  "type": "Feature",
  "properties": {
    "iso:country":"CH",
    "sg:address":"Rue Des Parcs 56",
    "sg:city":"Neuch\u00e2tel",
    "sg:orig_category":"W\u00e4scherei U chemische Reinigung",
    "sg:phone":"+41 32 725 04 14",
    "sg:postcode":"2000",
    "sg:province":"Neuch\u00e2tel",
    "wof:name":"Roger Golay Blanchisserie Des Parcs",
    "wof:placetype":"venue"
},
  "geometry": {"coordinates":[6.9192380905,46.9923362732],"type":"Point"}
}