{
  "type": "Feature",
  "properties": {
    "iso:country":"CH",
    "sg:address":"Rue De Conthey 15",
    "sg:city":"Sion",
    "sg:orig_category":"Tanzschulen, Tanzlehrer",
    "sg:phone":"+41 27 322 14 87",
    "sg:postcode":"1950",
    "sg:province":"Valais",
    "wof:name":"St\u00e9phanie Roduit Ecole De Danse & De Ballet",
    "wof:placetype":"venue"
},
  "geometry": {"coordinates":[7.3589248657,46.2329025269],"type":"Point"}
}