{
  "type": "Feature",
  "properties": {
    "iso:country":"CH",
    "sg:address":"Seeweg 18",
    "sg:city":"Romanshorn",
    "sg:orig_category":"Sonstige pers\u00f6nliche Dienstleistungen",
    "sg:phone":"+41 71 737 81 04",
    "sg:postcode":"8590",
    "sg:province":"Thurgau",
    "wof:name":"Pegus Ag",
    "wof:placetype":"venue"
},
  "geometry": {"coordinates":[9.3677129745,47.5761756897],"type":"Point"}
}