{
  "type": "Feature",
  "properties": {
    "iso:country":"CH",
    "sg:address":"Tr\u00fcttlikon",
    "sg:city":"Uesslingen",
    "sg:orig_category":"Wasserversorgung",
    "sg:postcode":"8524",
    "sg:province":"Thurgau",
    "wof:name":"Wasser&elektrakorporation Tr\u00dcttlikon",
    "wof:placetype":"venue"
},
  "geometry": {"coordinates":[8.8176841736,47.5967102051],"type":"Point"}
}