{
  "type": "Feature",
  "properties": {
    "iso:country":"CH",
    "sg:address":"Liebeggweg 21",
    "sg:city":"Bern",
    "sg:orig_category":"Wohnheime f\u00fcr Kinder U Jugendliche",
    "sg:phone":"+41 31 351 25 07",
    "sg:postcode":"3006",
    "sg:province":"Bern",
    "wof:name":"Wohngruppe Liebegg",
    "wof:placetype":"venue"
},
  "geometry": {"coordinates":[7.4605717659,46.945110321],"type":"Point"}
}