{
  "type": "Feature",
  "properties": {
    "iso:country":"CH",
    "sg:address":"Obere Hauptgasse 49",
    "sg:city":"Thun",
    "sg:orig_category":"RESTAURANTS: TEA-ROOMS",
    "sg:postcode":"3600",
    "sg:province":"Bern",
    "wof:name":"Restaurant Pomme Gmbh",
    "wof:placetype":"venue"
},
  "geometry": {"coordinates":[7.630338192,46.7585296631],"type":"Point"}
}