{
  "type": "Feature",
  "properties": {
    "iso:country":"CH",
    "sg:address":"Route Des Marches 6 1636 Broc Case Postale 36",
    "sg:city":"Broc",
    "sg:orig_category":"Sportvereine Ballsport Tennis",
    "sg:phone":"+41 26 921 33 95",
    "sg:postcode":"1636",
    "sg:province":"Fribourg",
    "wof:name":"Tennisclub Broc",
    "wof:placetype":"venue"
},
  "geometry": {"coordinates":[7.0954670906,46.600818634],"type":"Point"}
}