{
  "type": "Feature",
  "properties": {
    "iso:country":"CH",
    "sg:address":"Blatten",
    "sg:city":"Speicher",
    "sg:orig_category":"Landw. Genossenschaften Viehzucht",
    "sg:phone":"+41 71 344 21 31",
    "sg:postcode":"9042",
    "sg:province":"Appenzell Ausserrhoden",
    "wof:name":"Viehzuchtgenossenschaft Trogen-speicher K.zellweger",
    "wof:placetype":"venue"
},
  "geometry": {"coordinates":[9.4430751801,47.406288147],"type":"Point"}
}