{
  "type": "Feature",
  "properties": {
    "iso:country":"CH",
    "sg:address":"G\u00fcterstrasse 5",
    "sg:city":"Schwarzenburg",
    "sg:orig_category":"Landwirtschaftliche Genossenschaften",
    "sg:phone":"+41 41 811 13 83",
    "sg:postcode":"3150",
    "sg:province":"Bern",
    "wof:name":"Landi Schwyz",
    "wof:placetype":"venue"
},
  "geometry": {"coordinates":[8.6293945312,47.0329742432],"type":"Point"}
}