{
  "type": "Feature",
  "properties": {
    "iso:country":"CH",
    "sg:address":"Wunderklingerstrasse 31",
    "sg:city":"Hallau",
    "sg:orig_category":"Arztpraxen",
    "sg:phone":"+41 52 681 17 67",
    "sg:postcode":"8215",
    "sg:province":"Schaffhausen",
    "wof:name":"Dr.med.beat L\u00e4mmli Spezialarzt Fmh",
    "wof:placetype":"venue"
},
  "geometry": {"coordinates":[8.454643,47.696342],"type":"Point"}
}