{
  "type": "Feature",
  "properties": {
    "iso:country":"CH",
    "sg:address":"Avenue Des Huttins 2",
    "sg:city":"Prilly",
    "sg:orig_category":"Fahrschulen, Flugschulen",
    "sg:phone":"+41 79 606 37 38",
    "sg:postcode":"1008",
    "sg:province":"Vaud",
    "wof:name":"Alain Pianaro Auto-\u00e9cole",
    "wof:placetype":"venue"
},
  "geometry": {"coordinates":[6.8711500168,46.9839897156],"type":"Point"}
}