{
  "type": "Feature",
  "properties": {
    "iso:country":"CH",
    "sg:address":"Roggiana Via 29",
    "sg:city":"Vacallo",
    "sg:orig_category":"Detailhandel mit Waren verschiedener Art, Hauptrichtung Nahrungsmittel",
    "sg:postcode":"6833",
    "sg:province":"Ticino",
    "wof:name":"Fromita Sa",
    "wof:placetype":"venue"
},
  "geometry": {"coordinates":[9.0343160629,45.8479804993],"type":"Point"}
}