{
  "type": "Feature",
  "properties": {
    "iso:country":"CH",
    "sg:address":"Erlimattweg 30",
    "sg:city":"Olten",
    "sg:orig_category":"Sportvereine Velo Rad-& Motorfahrer-Bund SRB",
    "sg:postcode":"4600",
    "sg:province":"Solothurn",
    "wof:name":"Rad-renn-club Olten",
    "wof:placetype":"venue"
},
  "geometry": {"coordinates":[7.8999948502,47.3417854309],"type":"Point"}
}