{
  "type": "Feature",
  "properties": {
    "iso:country":"CH",
    "sg:address":"N\u00e4felserstrasse 34 4055 Basel. Postfach",
    "sg:city":"Basel",
    "sg:orig_category":"Interessenvertretungen",
    "sg:phone":"+41 61 302 66 50",
    "sg:postcode":"4051",
    "sg:province":"Basel-Stadt",
    "wof:name":"Blindendienst Der Advents-mission F\u00f6rderung Gemeinn\u00fctziger Aktionen F Blinde U Sehbehinderte",
    "wof:placetype":"venue"
},
  "geometry": {"coordinates":[7.5650138855,47.5577850342],"type":"Point"}
}