{
  "type": "Feature",
  "properties": {
    "iso:country":"CH",
    "sg:address":"Avenue De Morges 25",
    "sg:city":"Lonay",
    "sg:orig_category":"Detailhandel mit Brot, Back U S\u00fcsswaren",
    "sg:phone":"+41 21 801 30 32",
    "sg:postcode":"1027",
    "sg:province":"Vaud",
    "wof:name":"Fernand Bourquin Boulangerie & P\u00e2tisserie",
    "wof:placetype":"venue"
},
  "geometry": {"coordinates":[6.513784,46.522411],"type":"Point"}
}