{
  "type": "Feature",
  "properties": {
    "iso:country":"CH",
    "sg:address":"Chemin Des Bresoleys 18",
    "sg:city":"Vouvry",
    "sg:orig_category":"G\u00fcterbef\u00f6rderung im Strassenverkehr",
    "sg:postcode":"1896",
    "sg:province":"Valais",
    "wof:name":"Ruffieux Michel",
    "wof:placetype":"venue"
},
  "geometry": {"coordinates":[6.8940901756,46.3345184326],"type":"Point"}
}