{
  "type": "Feature",
  "properties": {
    "iso:country":"CH",
    "sg:address":"Pestalozzistrasse 2 3400 Burgdorf. Postfach",
    "sg:city":"Burgdorf",
    "sg:orig_category":"Herstellung von Anstrichmitteln, Druckfarben U Kitten",
    "sg:phone":"+41 34 422 60 40",
    "sg:postcode":"3402",
    "sg:province":"Bern",
    "wof:name":"Trigon-lacke Schoch F.",
    "wof:placetype":"venue"
},
  "geometry": {"coordinates":[7.6228032112,47.0555458069],"type":"Point"}
}