{
  "type": "Feature",
  "properties": {
    "iso:country":"CH",
    "sg:address":"Rue Du Rh\u00f4ne 29",
    "sg:city":"Gen\u00e8ve",
    "sg:orig_category":"Grosshandel mit Erzen U Metallen Grosshandel mit chemischen Erzeugnissen",
    "sg:phone":"+41 22 311 80 80",
    "sg:postcode":"1204",
    "sg:province":"Gen\u00e8ve",
    "wof:name":"Timber Resources Sa",
    "wof:placetype":"venue"
},
  "geometry": {"coordinates":[6.1475429535,46.2043037415],"type":"Point"}
}