{
  "type": "Feature",
  "properties": {
    "iso:country":"CH",
    "sg:address":"Fischmattweg 11",
    "sg:city":"Arth",
    "sg:orig_category":"Unternehmensberatung",
    "sg:phone":"+41 41 855 34 27",
    "sg:postcode":"6415",
    "sg:province":"Schwyz",
    "wof:name":"Rusch E., Consulting.",
    "wof:placetype":"venue"
},
  "geometry": {"coordinates":[8.5311994553,47.0686759949],"type":"Point"}
}