{
  "type": "Feature",
  "properties": {
    "iso:country":"CH",
    "sg:address":"Via Ronco 14",
    "sg:city":"Agno",
    "sg:orig_category":"Verlagsgewerbe Werbung",
    "sg:phone":"+41 17161777",
    "sg:postcode":"6982",
    "sg:province":"Ticino",
    "wof:name":"Media Annoncen Ag",
    "wof:placetype":"venue"
},
  "geometry": {"coordinates":[8.5416374207,47.3285179138],"type":"Point"}
}