{
  "type": "Feature",
  "properties": {
    "iso:country":"CH",
    "sg:address":"Rue Vautier 17c",
    "sg:city":"Carouge",
    "sg:orig_category":"Management Information Systems",
    "sg:phone":"+41 22 301 62 00",
    "sg:postcode":"1227",
    "sg:province":"Gen\u00e8ve",
    "wof:name":"Cobise S.a.",
    "wof:placetype":"venue"
},
  "geometry": {"coordinates":[6.1423869133,46.1847877502],"type":"Point"}
}