{
  "type": "Feature",
  "properties": {
    "iso:country":"CH",
    "sg:address":"3365",
    "sg:city":"Seeberg",
    "sg:classifiers":[
        {
            "category":"Education",
            "subcategory":"Vocational School",
            "type":"Public Place"
        }
    ],
    "sg:phone":"+41 32 665 42 63",
    "sg:postcode":"3365",
    "sg:province":"Bern",
    "sg:tags":[
        "koch-",
        "haushaltschulen"
    ],
    "wof:name":"Haushaltungsschule",
    "wof:placetype":"venue"
},
  "geometry": {"coordinates":[7.6654877663,47.1548919678],"type":"Point"}
}