{
  "type": "Feature",
  "properties": {
    "iso:country":"CH",
    "sg:address":"Chalet Kli-klou",
    "sg:city":"Verbier",
    "sg:classifiers":[
        {
            "category":"Communications",
            "subcategory":"Film & Video Production",
            "type":"Services"
        }
    ],
    "sg:phone":"+41 27 771 37 03",
    "sg:postcode":"1936",
    "sg:province":"Valais",
    "sg:tags":[
        "videofilmherstellung",
        "u"
    ],
    "wof:name":"Espace Production Sa",
    "wof:placetype":"venue"
},
  "geometry": {"coordinates":[7.2229619026,46.0967292786],"type":"Point"}
}