{
  "type": "Feature",
  "properties": {
    "iso:country":"CH",
    "sg:address":"4453",
    "sg:city":"Nusshof",
    "sg:orig_category":"Vorschulen, Kinderg\u00e4rten",
    "sg:phone":"+41 61 971 52 35",
    "sg:postcode":"4453",
    "sg:province":"Basel-Landschaft",
    "wof:name":"Kindergarten",
    "wof:placetype":"venue"
},
  "geometry": {"coordinates":[7.7978100777,47.4916496277],"type":"Point"}
}