{
  "type": "Feature",
  "properties": {
    "iso:country":"CH",
    "sg:address":"Oberdorfstr. 7 4950 Huttwil. Postfach 27",
    "sg:city":"Huttwil",
    "sg:orig_category":"Erbringung von Dienstleistungen f\u00fcr Unternehmen",
    "sg:phone":"+41 62 962 19 64",
    "sg:postcode":"4950",
    "sg:province":"Bern",
    "wof:name":"Spotti Gottardo, Int\u00e9rieur Naturel.",
    "wof:placetype":"venue"
},
  "geometry": {"coordinates":[7.8498821259,47.112701416],"type":"Point"}
}