{
  "type": "Feature",
  "properties": {
    "iso:country":"CH",
    "sg:address":"9230",
    "sg:city":"Flawil",
    "sg:orig_category":"Detailhandel mit Milcherzeugnissen U Eiern Verarbeitung von Milch",
    "sg:phone":"+41 71 393 11 55",
    "sg:postcode":"9230",
    "sg:province":"St. Gallen",
    "wof:name":"Max Isenegger K\u00e4serei Burgau",
    "wof:placetype":"venue"
},
  "geometry": {"coordinates":[9.1888751984,47.4148368835],"type":"Point"}
}