{
  "type": "Feature",
  "properties": {
    "iso:country":"CH",
    "sg:address":"Im Finsteren Boden 11",
    "sg:city":"Riehen",
    "sg:orig_category":"Sonstiges Versicherungsgewerbe",
    "sg:phone":"+41 61 601 24 41",
    "sg:postcode":"4125",
    "sg:province":"Basel-Stadt",
    "wof:name":"Generalagent Der Genfer Versicherungen",
    "wof:placetype":"venue"
},
  "geometry": {"coordinates":[7.6454758644,47.5668869019],"type":"Point"}
}