{
  "type": "Feature",
  "properties": {
    "iso:country":"CH",
    "sg:address":"Poststr. 50",
    "sg:city":"Jenins",
    "sg:orig_category":"Herstellung von Konstruktionsteilen, Fertigbauteilen U Ausbauelementen aus Holz",
    "sg:postcode":"7307",
    "sg:province":"Graubunden",
    "wof:name":"G\u00f6ldi C.",
    "wof:placetype":"venue"
},
  "geometry": {"coordinates":[9.5577096939,47.0004615784],"type":"Point"}
}