{
  "type": "Feature",
  "properties": {
    "iso:country":"CH",
    "sg:address":"Kannenfeldplatz 2 4056 Basel. Postfach",
    "sg:city":"Basel",
    "sg:orig_category":"Detailhandel mit Teppichen Einbau von Schreinerwaren",
    "sg:phone":"+41 61 321 37 13",
    "sg:postcode":"4012",
    "sg:province":"Basel-Stadt",
    "wof:name":"Edi Gamper Innendekoration Tapeten, Vorh\u00e4nge, Teppiche Usw; Handel",
    "wof:placetype":"venue"
},
  "geometry": {"coordinates":[7.5740470886,47.5620040894],"type":"Point"}
}