{
  "type": "Feature",
  "properties": {
    "iso:country":"CH",
    "sg:address":"Place Du March\u00e9 15",
    "sg:city":"Aubonne",
    "sg:classifiers":[
        {
            "category":"Travel",
            "subcategory":"Hotels & Motels",
            "type":"Entertainment"
        }
    ],
    "sg:phone":"+41 21 808 50 90",
    "sg:postcode":"1170",
    "sg:province":"Vaud",
    "sg:tags":[
        "hotels",
        "mit",
        "restaurant"
    ],
    "wof:name":"H\u00f4tel Du Lion D'or",
    "wof:placetype":"venue"
},
  "geometry": {"coordinates":[6.3911042213,46.4952125549],"type":"Point"}
}