{
  "type": "Feature",
  "properties": {
    "iso:country":"CH",
    "sg:address":"6156 Luthern. Postfach",
    "sg:city":"Luthern",
    "sg:orig_category":"Fachdetailhandel in Verkaufsr\u00e4umen",
    "sg:phone":"+41 77888938",
    "sg:postcode":"6156",
    "sg:province":"Luzern",
    "wof:name":"St\u00fcbi Martin Gmbh",
    "wof:placetype":"venue"
},
  "geometry": {"coordinates":[8.3057041168,46.9848480225],"type":"Point"}
}