{
  "type": "Feature",
  "properties": {
    "iso:country":"CH",
    "sg:address":"Sennweg 11 3000 Bern. Postfach",
    "sg:city":"Bern",
    "sg:orig_category":"Schiffsbau ohne Boots U Yachtbau",
    "sg:postcode":"3005",
    "sg:province":"Bern",
    "wof:name":"Mv Sabina Ag",
    "wof:placetype":"venue"
},
  "geometry": {"coordinates":[7.434431076,46.9530258179],"type":"Point"}
}