{
  "type": "Feature",
  "properties": {
    "iso:country":"CH",
    "sg:address":"Winkelacker 4",
    "sg:city":"Altnau",
    "sg:orig_category":"G\u00fcterbef\u00f6rderung im Strassenverkehr",
    "sg:phone":"+41 71 695 21 71",
    "sg:postcode":"8595",
    "sg:province":"Thurgau",
    "wof:name":"Ren\u00e9 Mundschin Transporte",
    "wof:placetype":"venue"
},
  "geometry": {"coordinates":[9.2574310303,47.6121139526],"type":"Point"}
}