{
  "type": "Feature",
  "properties": {
    "iso:country":"CH",
    "sg:address":"Pfisterplatz 1 7000 Chur. Postfach 155",
    "sg:city":"Chur",
    "sg:orig_category":"Detailhandel mit Geschenkartikeln U Souvenirs Kunsthandel",
    "sg:phone":"+41 81 252 10 77",
    "sg:postcode":"7002",
    "sg:province":"Graubunden",
    "wof:name":"Etniko",
    "wof:placetype":"venue"
},
  "geometry": {"coordinates":[9.5310678482,46.8485031128],"type":"Point"}
}