{
  "type": "Feature",
  "properties": {
    "iso:country":"CH",
    "sg:address":"Dorf",
    "sg:city":"Kaltbach",
    "sg:classifiers":[
        {
            "category":"Banks & Credit Unions",
            "subcategory":"Investment Brokerage",
            "type":"Services"
        }
    ],
    "sg:phone":"+41 41 921 65 65",
    "sg:postcode":"6212",
    "sg:province":"Luzern",
    "sg:tags":[
        "work",
        "edging"
    ],
    "wof:name":"M\u00dcller Kaltbach Inosteel Ag",
    "wof:placetype":"venue"
},
  "geometry": {"coordinates":[8.0637779236,47.1824798584],"type":"Point"}
}