{
  "type": "Feature",
  "properties": {
    "iso:country":"CH",
    "sg:address":"Obere Industrie 9",
    "sg:city":"Maienfeld",
    "sg:classifiers":[
        {
            "category":"Manufacturing",
            "subcategory":"Rubber & Plastics",
            "type":"Manufacturing & Wholesale Goods"
        }
    ],
    "sg:phone":"+41 41 760 12 12",
    "sg:postcode":"7304",
    "sg:province":"Graubunden",
    "wof:name":"Karochemie Ag",
    "wof:placetype":"venue"
},
  "geometry": {"coordinates":[8.5704450607,47.2153015137],"type":"Point"}
}