{
  "type": "Feature",
  "properties": {
    "iso:country":"CH",
    "sg:address":"Landstrasse 2",
    "sg:city":"W\u00fcrenlos",
    "sg:orig_category":"G\u00fcterbef\u00f6rderung im Strassenverkehr Lagerung",
    "sg:phone":"+41 55 246 63 63",
    "sg:postcode":"5436",
    "sg:province":"Aargau",
    "wof:name":"O. Kindlimann Ag Transporte & Lagerungen",
    "wof:placetype":"venue"
},
  "geometry": {"coordinates":[8.9277210236,47.2684211731],"type":"Point"}
}