{
  "type": "Feature",
  "properties": {
    "iso:country":"CH",
    "sg:address":"Hauptstrasse 112",
    "sg:city":"Wintersingen",
    "sg:orig_category":"Herstellung von Ger\u00e4ten der Elektrizit\u00e4tserzeugung, -verteilung u.\u00e4. -Herstellung von sonstigen elek",
    "sg:phone":"+41 32 366 54 60",
    "sg:postcode":"4451",
    "sg:province":"Basel-Landschaft",
    "wof:name":"Ginova Ag",
    "wof:placetype":"venue"
},
  "geometry": {"coordinates":[7.2592320442,47.1212043762],"type":"Point"}
}