{
  "type": "Feature",
  "properties": {
    "iso:country":"CH",
    "sg:address":"Via San Gottardo 56",
    "sg:city":"Lugano",
    "sg:orig_category":"Markt U Meinungsforschung",
    "sg:phone":"+41 17372958",
    "sg:postcode":"6900",
    "sg:province":"Ticino",
    "wof:name":"Bernhard & Doris Lips Werbung & Marktanalysen",
    "wof:placetype":"venue"
},
  "geometry": {"coordinates":[8.4486198425,47.3560180664],"type":"Point"}
}