{
  "type": "Feature",
  "properties": {
    "iso:country":"CH",
    "sg:address":"Niederfeld 44 9320 Stachen. Postfach 59",
    "sg:city":"Arbon",
    "sg:orig_category":"Satzherstellung U Reproduktion",
    "sg:phone":"+41 71 440 03 40",
    "sg:postcode":"9320",
    "sg:province":"Thurgau",
    "wof:name":"Seelitho Ag",
    "wof:placetype":"venue"
},
  "geometry": {"coordinates":[9.4109611511,47.5033760071],"type":"Point"}
}