{
  "type": "Feature",
  "properties": {
    "addr:full":"Rietstrasse 5 Widnau St. Gallen 9443",
    "addr:housenumber":"5",
    "addr:postcode":"9443",
    "addr:street":"Rietstrasse",
    "iso:country":"CH",
    "sg:address":"Rietstrasse 5",
    "sg:city":"Widnau",
    "sg:orig_category":"Architektur U Ingenieurb\u00fcros",
    "sg:phone":"+41 17154347",
    "sg:postcode":"9443",
    "sg:province":"St. Gallen",
    "wof:name":"Emil Weber Ingenieurb\u00fcro",
    "wof:placetype":"venue"
},
  "geometry": {"coordinates":[8.540846,47.332226],"type":"Point"}
}