{
  "type": "Feature",
  "properties": {
    "iso:country":"CH",
    "sg:address":"Sonnhalde 5",
    "sg:city":"D\u00e4ttlikon",
    "sg:orig_category":"Elektroinstallation",
    "sg:postcode":"8421",
    "sg:province":"Z\u00fcrich",
    "wof:name":"Calendo Gebr\u00fcder Ag, Elektro-planungsb\u00fcro, Zweigniederlassungen",
    "wof:placetype":"venue"
},
  "geometry": {"coordinates":[8.7677335739,47.1986656189],"type":"Point"}
}