{
  "type": "Feature",
  "properties": {
    "iso:country":"CH",
    "sg:address":"Stotzhalten",
    "sg:city":"Grindelwald",
    "sg:orig_category":"HOTELS: OHNE RESTAURANT",
    "sg:phone":"+41 81 302 25 88",
    "sg:postcode":"3818",
    "sg:province":"Bern",
    "wof:name":"Hotel Ursalina",
    "wof:placetype":"venue"
},
  "geometry": {"coordinates":[9.5037755966,47.0043716431],"type":"Point"}
}