{
  "type": "Feature",
  "properties": {
    "iso:country":"CH",
    "sg:address":"Kehlhofhalde 8",
    "sg:city":"Adligenswil",
    "sg:orig_category":"Grosshandel mit sonstigen Gebrauchs U Verbrauchsg\u00fctern",
    "sg:phone":"+41 41 370 30 57",
    "sg:postcode":"6043",
    "sg:province":"Luzern",
    "wof:name":"Bahr Gerhard Juwelenfasser",
    "wof:placetype":"venue"
},
  "geometry": {"coordinates":[8.3631782532,47.0761833191],"type":"Point"}
}