{
  "type": "Feature",
  "properties": {
    "iso:country":"CH",
    "sg:address":"3618",
    "sg:city":"S\u00fcderen",
    "sg:orig_category":"Sportvereine Sch\u00fctzen",
    "sg:phone":"+41 32 631 19 60",
    "sg:postcode":"3618",
    "sg:province":"Bern",
    "wof:name":"Sch\u00fctzenges.wangen A.d.aare",
    "wof:placetype":"venue"
},
  "geometry": {"coordinates":[7.6548519135,47.2356948853],"type":"Point"}
}