{
  "type": "Feature",
  "properties": {
    "iso:country":"CH",
    "sg:address":"Chemin Des Graviers 1290 Versoix Case Postale 328",
    "sg:city":"Versoix",
    "sg:orig_category":"Sportvereine Wassersport Segeln",
    "sg:phone":"+41 22 755 38 55",
    "sg:postcode":"1290",
    "sg:province":"Gen\u00e8ve",
    "wof:name":"Club Nautique De Versoix",
    "wof:placetype":"venue"
},
  "geometry": {"coordinates":[6.1687541008,46.2890014648],"type":"Point"}
}