{
  "type": "Feature",
  "properties": {
    "iso:country":"CH",
    "sg:address":"Waldstrasse 5",
    "sg:city":"Emmenbr\u00fccke",
    "sg:orig_category":"Malerei-Gipserei Stukkateurgewerbe, Gipserei U Verputzerei",
    "sg:phone":"+41 52 383 17 81",
    "sg:postcode":"6020",
    "sg:province":"Luzern",
    "wof:name":"Dino Lanzicher Gipsergesch\u00e4ft",
    "wof:placetype":"venue"
},
  "geometry": {"coordinates":[8.8238601685,47.4476203918],"type":"Point"}
}