{
  "type": "Feature",
  "properties": {
    "iso:country":"CH",
    "sg:address":"Wiesenstrasse 10",
    "sg:city":"Umiken",
    "sg:orig_category":"Vereine Gesang",
    "sg:phone":"+41 56 441 58 58",
    "sg:postcode":"5222",
    "sg:province":"Aargau",
    "wof:name":"Ref. Kirchenchor Brugg",
    "wof:placetype":"venue"
},
  "geometry": {"coordinates":[8.1884002686,47.4812507629],"type":"Point"}
}