{
  "type": "Feature",
  "properties": {
    "iso:country":"CH",
    "sg:address":"Theatergasse 26 4500 Solothurn. Postfach",
    "sg:city":"Solothurn",
    "sg:orig_category":"Herstellung von sonstigen Erzeugnissen",
    "sg:postcode":"4500",
    "sg:province":"Solothurn",
    "wof:name":"Med. Hair-center Gmbh Zweithaar-center F\u00fcr Nat\u00fcrlichen U. K\u00fcnstlichen Haarersatz Unter Fachmedizinischer Anleitung; Entwicklung, Anwendung, Betrieb Usw",
    "wof:placetype":"venue"
},
  "geometry": {"coordinates":[7.5386099815,47.2071304321],"type":"Point"}
}