{
  "type": "Feature",
  "properties": {
    "iso:country":"CH",
    "sg:address":"Via Rinaldo Simen 9",
    "sg:city":"Chiasso",
    "sg:orig_category":"Architekturb\u00fcros",
    "sg:phone":"+41 91 683 62 39",
    "sg:postcode":"6830",
    "sg:province":"Ticino",
    "wof:name":"Franco & Claudio Lupi Studio D'architettura",
    "wof:placetype":"venue"
},
  "geometry": {"coordinates":[9.025523,45.838127],"type":"Point"}
}