{
  "type": "Feature",
  "properties": {
    "iso:country":"CH",
    "sg:address":"Bahnhofstrasse 31 7130 Ilanz. Postfach",
    "sg:city":"Ilanz",
    "sg:orig_category":"HOTELS: MIT RESTAURANT Kongress- and Tagungshotels mit Restaurant",
    "sg:phone":"+41 81 925 51 51",
    "sg:postcode":"7130",
    "sg:province":"Graubunden",
    "wof:name":"Hotel Eden Montana",
    "wof:placetype":"venue"
},
  "geometry": {"coordinates":[9.2082414627,46.774848938],"type":"Point"}
}