{
  "type": "Feature",
  "properties": {
    "iso:country":"CH",
    "sg:address":"Oberdorfstrasse",
    "sg:city":"Niederrohrdorf",
    "sg:orig_category":"Primarschulen",
    "sg:phone":"+41 34 402 12 85",
    "sg:postcode":"5443",
    "sg:province":"Aargau",
    "wof:name":"Primarschule Dorf",
    "wof:placetype":"venue"
},
  "geometry": {"coordinates":[7.757589817,46.9491271973],"type":"Point"}
}