{
  "type": "Feature",
  "properties": {
    "iso:country":"CH",
    "sg:address":"Chemin De La Bruy\u00e8re 2",
    "sg:city":"Pully",
    "sg:orig_category":"Architekturb\u00fcros",
    "sg:phone":"+41 21 728 69 68",
    "sg:postcode":"1009",
    "sg:province":"Vaud",
    "wof:name":"Atelier Alpha Daphn\u00e9 Walter Bureau D'architecture",
    "wof:placetype":"venue"
},
  "geometry": {"coordinates":[6.662171,46.521954],"type":"Point"}
}