{
  "type": "Feature",
  "properties": {
    "iso:country":"CH",
    "sg:address":"Sonnenterrasse Chalet",
    "sg:city":"Gr\u00e4chen",
    "sg:orig_category":"Fussboden, Fliesen U Plattenlegerei, Tapeziererei",
    "sg:phone":"+41 79 632 55 70",
    "sg:postcode":"3925",
    "sg:province":"Valais",
    "wof:name":"Gruber R.+b., Plattengesch\u00e4ft-hafnerei-maurerarbeiten",
    "wof:placetype":"venue"
},
  "geometry": {"coordinates":[7.8392400742,46.1961631775],"type":"Point"}
}