{
  "type": "Feature",
  "properties": {
    "iso:country":"CH",
    "sg:address":"Alte Landstrasse 74",
    "sg:city":"Rebstein",
    "sg:classifiers":[
        {
            "category":"Travel",
            "subcategory":"Hotels & Motels",
            "type":"Entertainment"
        }
    ],
    "sg:phone":"+41 71 777 11 53",
    "sg:postcode":"9445",
    "sg:province":"St. Gallen",
    "sg:tags":[
        "hotels",
        "mit",
        "restaurant"
    ],
    "wof:name":"Gasthaus Rebstock Z. Keel",
    "wof:placetype":"venue"
},
  "geometry": {"coordinates":[9.5827064514,47.3985786438],"type":"Point"}
}