{
  "type": "Feature",
  "properties": {
    "iso:country":"CH",
    "sg:address":"Giardino Via 2",
    "sg:city":"Arbedo",
    "sg:orig_category":"G\u00fcterbef\u00f6rderung im Strassenverkehr",
    "sg:postcode":"6517",
    "sg:province":"Ticino",
    "wof:name":"Tisinpex Trasporti Sagl",
    "wof:placetype":"venue"
},
  "geometry": {"coordinates":[9.0447492599,46.2173881531],"type":"Point"}
}