{
  "type": "Feature",
  "properties": {
    "iso:country":"CH",
    "sg:address":"Br\u00fcnigstrasse 213 6072 Sachseln. Postfach 221",
    "sg:city":"Sachseln",
    "sg:orig_category":"Herstellung von k\u00e4lte U lufttechnischen Erzeugnissen f\u00fcr gewerbliche Zwecke Sanit\u00e4r U Heizungsinstal",
    "sg:phone":"+41 41 660 50 60",
    "sg:postcode":"6072",
    "sg:province":"Obwalden",
    "wof:name":"Waser Heizungen Gmbh",
    "wof:placetype":"venue"
},
  "geometry": {"coordinates":[8.2217302322,46.8596458435],"type":"Point"}
}