{
  "type": "Feature",
  "properties": {
    "iso:country":"CH",
    "sg:address":"R\u00fctistrasse 28 8952 Schlieren. Postfach",
    "sg:city":"Schlieren",
    "sg:orig_category":"Herstellung von sonstigen Gummiwaren",
    "sg:phone":"+41 56 633 53 54",
    "sg:postcode":"8952",
    "sg:province":"Z\u00fcrich",
    "wof:name":"G. Notter Ag Sperrholzplatten & Isoliermat.",
    "wof:placetype":"venue"
},
  "geometry": {"coordinates":[8.327422,47.352894],"type":"Point"}
}