{
  "type": "Feature",
  "properties": {
    "iso:country":"CH",
    "sg:address":"Grundstrasse 33",
    "sg:city":"Olten",
    "sg:orig_category":"Architektur U Ingenieurb\u00fcros",
    "sg:phone":"+41 62 212 10 58",
    "sg:postcode":"4600",
    "sg:province":"Solothurn",
    "wof:name":"Frey, Strub Ag, Dipl. Ingenieure",
    "wof:placetype":"venue"
},
  "geometry": {"coordinates":[7.896539,47.352737],"type":"Point"}
}