{
  "type": "Feature",
  "properties": {
    "addr:full":"Chemin De Baugy 12 Clarens Vaud 1815",
    "addr:housenumber":"12",
    "addr:postcode":"1815",
    "addr:street":"Chemin De Baugy",
    "iso:country":"CH",
    "sg:address":"Chemin De Baugy 12",
    "sg:city":"Clarens",
    "sg:orig_category":"Ausbaugewerbe",
    "sg:postcode":"1815",
    "sg:province":"Vaud",
    "wof:name":"Lounag Assainissement S\u00e0rl",
    "wof:placetype":"venue"
},
  "geometry": {"coordinates":[6.890805,46.440945],"type":"Point"}
}