{
  "type": "Feature",
  "properties": {
    "iso:country":"CH",
    "sg:address":"Endlikerstrasse 76",
    "sg:city":"Winterthur",
    "sg:orig_category":"Fachdetailhandel in Verkaufsr\u00e4umen Selbst\u00e4ndige bildende K\u00fcnstler",
    "sg:phone":"+41 91 743 56 74",
    "sg:postcode":"8400",
    "sg:province":"Z\u00fcrich",
    "wof:name":"Atelier Kofmehl Sagl",
    "wof:placetype":"venue"
},
  "geometry": {"coordinates":[8.8300590515,46.1852149963],"type":"Point"}
}