{
  "type": "Feature",
  "properties": {
    "iso:country":"CH",
    "sg:address":"Gr\u00fcnaustrasse 21",
    "sg:city":"Dietikon",
    "sg:orig_category":"Base Sheetings For Parquet",
    "sg:phone":"+41 17464300",
    "sg:postcode":"8953",
    "sg:province":"Z\u00fcrich",
    "wof:name":"Balterschwiler Ag",
    "wof:placetype":"venue"
},
  "geometry": {"coordinates":[8.403019,47.410835],"type":"Point"}
}