{
  "type": "Feature",
  "properties": {
    "addr:full":"Murzlenstrasse 74 Niederweningen Z\u00fcrich 8166",
    "addr:housenumber":"74",
    "addr:postcode":"8166",
    "addr:street":"Murzlenstrasse",
    "iso:country":"CH",
    "sg:address":"Murzlenstrasse 74",
    "sg:city":"Niederweningen",
    "sg:classifiers":[
        {
            "category":"Bars & Pubs",
            "type":"Food & Drink"
        }
    ],
    "sg:phone":"+41 27 957 10 01",
    "sg:postcode":"8166",
    "sg:province":"Z\u00fcrich",
    "wof:name":"John's Pub",
    "wof:placetype":"venue"
},
  "geometry": {"coordinates":[7.933673,46.111717],"type":"Point"}
}