{
  "type": "Feature",
  "properties": {
    "iso:country":"CH",
    "sg:address":"Seestrasse 18",
    "sg:city":"Kilchberg",
    "sg:classifiers":[
        {
            "category":"Home & Garden",
            "subcategory":"Garden Supply",
            "type":"Retail Goods"
        }
    ],
    "sg:phone":"+41 17165544",
    "sg:postcode":"8802",
    "sg:province":"Z\u00fcrich",
    "sg:tags":[
        "aerator"
    ],
    "wof:name":"Klimawatt Ag",
    "wof:placetype":"venue"
},
  "geometry": {"coordinates":[8.543256,47.333519],"type":"Point"}
}