{
  "type": "Feature",
  "properties": {
    "iso:country":"CH",
    "sg:address":"Adligenswilerstrasse 22",
    "sg:city":"Luzern",
    "sg:orig_category":"Pensionskassen",
    "sg:phone":"+41 41 410 65 65",
    "sg:postcode":"6006",
    "sg:province":"Luzern",
    "wof:name":"Personalf\u00fcrsorgestiftung Der Hotel Montana Ag",
    "wof:placetype":"venue"
},
  "geometry": {"coordinates":[8.319984436,47.0564956665],"type":"Point"}
}