{
  "type": "Feature",
  "properties": {
    "iso:country":"CH",
    "sg:address":"7165",
    "sg:city":"Breil/brigels",
    "sg:orig_category":"Sportvereine Eissport Bob, Schlitteln and Skeleton",
    "sg:phone":"+41 71 999 28 15",
    "sg:postcode":"7165",
    "sg:province":"Graubunden",
    "wof:name":"Hornschlittencl.alt St.johann",
    "wof:placetype":"venue"
},
  "geometry": {"coordinates":[9.2849197388,47.1935844421],"type":"Point"}
}