{
  "type": "Feature",
  "properties": {
    "iso:country":"CH",
    "sg:address":"Hauptstrasse 14",
    "sg:city":"Herbligen",
    "sg:orig_category":"RESTAURANTS: TEA-ROOMS",
    "sg:phone":"+41 31 771 01 86",
    "sg:postcode":"3671",
    "sg:province":"Bern",
    "wof:name":"Restaurant Frohsinn Beutler-marti A. + R.",
    "wof:placetype":"venue"
},
  "geometry": {"coordinates":[7.6085910797,46.8271751404],"type":"Point"}
}