{
  "type": "Feature",
  "properties": {
    "iso:country":"CH",
    "sg:address":"St. Alban-vorstadt 69",
    "sg:city":"Basel",
    "sg:orig_category":"Interessenvertretungen",
    "sg:postcode":"4052",
    "sg:province":"Basel-Stadt",
    "wof:name":"Basler Aids Stiftung",
    "wof:placetype":"venue"
},
  "geometry": {"coordinates":[7.5991888046,47.5542411804],"type":"Point"}
}