{
  "type": "Feature",
  "properties": {
    "iso:country":"CH",
    "sg:address":"Kornhausgasse 12",
    "sg:city":"Basel",
    "sg:orig_category":"RESTAURANTS: TEA-ROOMS",
    "sg:postcode":"4051",
    "sg:province":"Basel-Stadt",
    "wof:name":"Roth-melly Chantal",
    "wof:placetype":"venue"
},
  "geometry": {"coordinates":[7.603741169,46.1775054932],"type":"Point"}
}