{
  "type": "Feature",
  "properties": {
    "iso:country":"CH",
    "sg:address":"M\u00fchlestrasse 1",
    "sg:city":"Biglen",
    "sg:orig_category":"Detailhandel mit Fleisch U Fleischwaren",
    "sg:phone":"+41 33 654 23 47",
    "sg:postcode":"3507",
    "sg:province":"Bern",
    "wof:name":"Lengacher Peter.",
    "wof:placetype":"venue"
},
  "geometry": {"coordinates":[7.6955251694,46.6565361023],"type":"Point"}
}