{
  "type": "Feature",
  "properties": {
    "iso:country":"CH",
    "sg:address":"Schulhaus Tellenmatt",
    "sg:city":"Stans",
    "sg:orig_category":"Interessenvertretungen",
    "sg:postcode":"6370",
    "sg:province":"Nidwalden",
    "wof:name":"Jann-stiftung, Ida",
    "wof:placetype":"venue"
},
  "geometry": {"coordinates":[8.3674945831,46.9570732117],"type":"Point"}
}