{
  "type": "Feature",
  "properties": {
    "iso:country":"CH",
    "sg:address":"Ottenbergstrasse 16",
    "sg:city":"Z\u00fcrich",
    "sg:orig_category":"Herstellung von Seifen, Wasch U Reinigungsmitteln",
    "sg:postcode":"8049",
    "sg:province":"Z\u00fcrich",
    "wof:name":"Faddoul G., Handelsagentur Reinigungsprodukte; Handel",
    "wof:placetype":"venue"
},
  "geometry": {"coordinates":[8.5129575729,47.3970985413],"type":"Point"}
}