{
  "type": "Feature",
  "properties": {
    "iso:country":"CH",
    "sg:address":"1615",
    "sg:city":"Bossonnens",
    "sg:orig_category":"Vorschulen, Kinderg\u00e4rten",
    "sg:phone":"+41 21 947 55 88",
    "sg:postcode":"1615",
    "sg:province":"Fribourg",
    "wof:name":"Ecole Enfantine",
    "wof:placetype":"venue"
},
  "geometry": {"coordinates":[6.8484401703,46.529209137],"type":"Point"}
}