{
  "type": "Feature",
  "properties": {
    "addr:full":"3952 Susten Valais 3952",
    "addr:postcode":"3952;3952",
    "iso:country":"CH",
    "sg:address":"3952",
    "sg:city":"Susten",
    "sg:orig_category":"Bauschreinerei Innenausbau",
    "sg:phone":"+41 79 417 54 91",
    "sg:postcode":"3952",
    "sg:province":"Valais",
    "wof:name":"Valentin Metry Schreinerei Innenausbau",
    "wof:placetype":"venue"
},
  "geometry": {"coordinates":[7.64202,46.311508],"type":"Point"}
}