{
  "type": "Feature",
  "properties": {
    "addr:full":"Parkstr. 13 Goldau Schwyz 6410",
    "addr:housenumber":"13",
    "addr:postcode":"6410",
    "addr:street":"Parkstr.;Schwyz",
    "iso:country":"CH",
    "sg:address":"Parkstr. 13",
    "sg:city":"Goldau",
    "sg:classifiers":[
        {
            "category":"Banks & Credit Unions",
            "subcategory":"Bank",
            "type":"Services"
        }
    ],
    "sg:phone":"+41 41 819 02 50",
    "sg:postcode":"6410",
    "sg:province":"Schwyz",
    "wof:name":"Sparkasse Schwyz",
    "wof:placetype":"venue"
},
  "geometry": {"coordinates":[8.65351,47.020988],"type":"Point"}
}