{
  "type": "Feature",
  "properties": {
    "iso:country":"CH",
    "sg:address":"Rue Les P\u00e2les 3",
    "sg:city":"Courgenay",
    "sg:orig_category":"Galvanische Betriebe Grosshandel mit Erzen U Metallen",
    "sg:phone":"+41 32 471 18 45",
    "sg:postcode":"2950",
    "sg:province":"Jura",
    "wof:name":"Aluconcept Sa",
    "wof:placetype":"venue"
},
  "geometry": {"coordinates":[7.1319208145,47.4062614441],"type":"Point"}
}