{
  "type": "Feature",
  "properties": {
    "iso:country":"CH",
    "sg:address":"Bahnhofstrasse 61",
    "sg:city":"D\u00fcbendorf",
    "sg:orig_category":"Detailhandel mit Geschenkartikeln U Souvenirs",
    "sg:phone":"+41 18203920",
    "sg:postcode":"8600",
    "sg:province":"Z\u00fcrich",
    "wof:name":"Margrit Reich Modeboutique Shop 61",
    "wof:placetype":"venue"
},
  "geometry": {"coordinates":[8.6222057343,47.3999443054],"type":"Point"}
}