{
  "type": "Feature",
  "properties": {
    "iso:country":"CH",
    "sg:address":"Metzgergasse 4",
    "sg:city":"Aarau",
    "sg:orig_category":"Detailhandel mit Bekleidung Detailhandel mit Damenbekleidung",
    "sg:phone":"+41 62 822 65 51",
    "sg:postcode":"5000",
    "sg:province":"Aargau",
    "wof:name":"Modehaus Utzinger Vivienne Inh. Moser-utzinger A. + B.",
    "wof:placetype":"venue"
},
  "geometry": {"coordinates":[8.044369,47.393261],"type":"Point"}
}