{
  "type": "Feature",
  "properties": {
    "iso:country":"CH",
    "sg:address":"Seegartenstrasse 65",
    "sg:city":"Horgen",
    "sg:orig_category":"Gartenbau",
    "sg:phone":"+41 17257878",
    "sg:postcode":"8810",
    "sg:province":"Z\u00fcrich",
    "wof:name":"Tr\u00fcb Ag, Horgen",
    "wof:placetype":"venue"
},
  "geometry": {"coordinates":[8.5901269913,47.2652244568],"type":"Point"}
}