{
  "type": "Feature",
  "properties": {
    "iso:country":"CH",
    "sg:address":"Berghof",
    "sg:city":"Wiesendangen",
    "sg:orig_category":"Rebbau",
    "sg:phone":"+41 52 337 11 40",
    "sg:postcode":"8542",
    "sg:province":"Z\u00fcrich",
    "wof:name":"Benjamin Kindhauser Weinbau",
    "wof:placetype":"venue"
},
  "geometry": {"coordinates":[8.7986860275,47.5274505615],"type":"Point"}
}