{
  "type": "Feature",
  "properties": {
    "iso:country":"CH",
    "sg:address":"S\u00e4genstrasse 5",
    "sg:city":"Landquart",
    "sg:orig_category":"Grosshandel mit Milch, Milcherzeugnissen, Eiern, Speise\u00f6len U Nahrungsfetten",
    "sg:phone":"+41 81 300 08 77",
    "sg:postcode":"7302",
    "sg:province":"Graubunden",
    "wof:name":"L\u00fcchinger + Schmid Ag, Eier & Eiprodukte",
    "wof:placetype":"venue"
},
  "geometry": {"coordinates":[9.5619735718,46.9588546753],"type":"Point"}
}