{
  "type": "Feature",
  "properties": {
    "iso:country":"CH",
    "sg:address":"Rue Saint-honor\u00e9 12",
    "sg:city":"Neuch\u00e2tel",
    "sg:orig_category":"P\u00e9dicure",
    "sg:phone":"+41 32 725 25 15",
    "sg:postcode":"2000",
    "sg:province":"Neuch\u00e2tel",
    "wof:name":"Fran\u00e7oise Wildbolz P\u00e9dicure",
    "wof:placetype":"venue"
},
  "geometry": {"coordinates":[6.9306731224,46.990776062],"type":"Point"}
}