{
  "type": "Feature",
  "properties": {
    "iso:country":"CH",
    "sg:address":"Steinerstrasse",
    "sg:city":"Diessenhofen",
    "sg:orig_category":"Detailhandel mit Getr\u00e4nken",
    "sg:phone":"+41 52 657 29 00",
    "sg:postcode":"8253",
    "sg:province":"Thurgau",
    "wof:name":"Getr\u00e4nkehandel Fehr Beatrice & Karl Gr\u00e4nicher",
    "wof:placetype":"venue"
},
  "geometry": {"coordinates":[8.7551460266,47.6879310608],"type":"Point"}
}