{
  "type": "Feature",
  "properties": {
    "iso:country":"CH",
    "sg:address":"Kurzfeldstrasse 11",
    "sg:city":"Frauenfeld",
    "sg:orig_category":"Non-Classified Establishments",
    "sg:phone":"+41 52 720 15 42",
    "sg:postcode":"8500",
    "sg:province":"Thurgau",
    "wof:name":"Consulenza Menzi Armin",
    "wof:placetype":"venue"
},
  "geometry": {"coordinates":[8.8918142319,47.5577659607],"type":"Point"}
}