{
  "type": "Feature",
  "properties": {
    "iso:country":"CH",
    "sg:address":"Winterhaldenstr. 2",
    "sg:city":"Heimberg",
    "sg:classifiers":[
        {
            "category":"Manufacturing",
            "subcategory":"Printing",
            "type":"Manufacturing & Wholesale Goods"
        }
    ],
    "sg:phone":"+41 33 437 76 76",
    "sg:postcode":"3627",
    "sg:province":"Bern",
    "sg:tags":[
        "publishing"
    ],
    "wof:name":"Wittwer Offset Ag",
    "wof:placetype":"venue"
},
  "geometry": {"coordinates":[7.6031618118,46.7974853516],"type":"Point"}
}