{
  "type": "Feature",
  "properties": {
    "iso:country":"CH",
    "sg:address":"Route De Bernex 313 1233 Bernex Case Postale 242",
    "sg:city":"Bernex",
    "sg:orig_category":"Kinderkrippen U horte",
    "sg:phone":"+41 22 757 34 31",
    "sg:postcode":"1233",
    "sg:province":"Gen\u00e8ve",
    "wof:name":"Garderie D'enfants Bizules",
    "wof:placetype":"venue"
},
  "geometry": {"coordinates":[6.0722570419,46.1743049622],"type":"Point"}
}