{
  "type": "Feature",
  "properties": {
    "iso:country":"CH",
    "sg:address":"Lehnmattstrasse 23",
    "sg:city":"Appenzell",
    "sg:orig_category":"Grosshandel mit Tabakwaren",
    "sg:postcode":"9050",
    "sg:province":"Appenzell Innerhoden",
    "wof:name":"Tabak Koller",
    "wof:placetype":"venue"
},
  "geometry": {"coordinates":[9.4077301025,47.3367385864],"type":"Point"}
}