{
  "type": "Feature",
  "properties": {
    "iso:country":"CH",
    "sg:address":"Breitenbachstrasse 17",
    "sg:city":"Laufen",
    "sg:orig_category":"Sanit\u00e4r, Heizungs U L\u00fcftungsinstallation Sanit\u00e4rinstallation",
    "sg:phone":"+41 91 795 14 42",
    "sg:postcode":"4242",
    "sg:province":"Basel-Landschaft",
    "wof:name":"V. Luraschi Sa Imp.sanitari & Riscaldamenti",
    "wof:placetype":"venue"
},
  "geometry": {"coordinates":[8.8414697647,46.1437950134],"type":"Point"}
}