{
  "type": "Feature",
  "properties": {
    "iso:country":"CH",
    "sg:address":"Marktgasse 16",
    "sg:city":"Interlaken",
    "sg:orig_category":"Revision Steuerberatung",
    "sg:phone":"+41 33 822 02 90",
    "sg:postcode":"3800",
    "sg:province":"Bern",
    "wof:name":"T. Schweizer Ag Treuhand & Revision",
    "wof:placetype":"venue"
},
  "geometry": {"coordinates":[7.8533759117,46.6857070923],"type":"Point"}
}