{
  "type": "Feature",
  "properties": {
    "iso:country":"CH",
    "sg:address":"Juravorstadt 7",
    "sg:city":"Biel/bienne",
    "sg:orig_category":"Hobel U Holzimpr\u00e4gnierwerke Selbst\u00e4ndige bildende K\u00fcnstler",
    "sg:phone":"+41 32 323 19 32",
    "sg:postcode":"2502",
    "sg:province":"Bern",
    "wof:name":"Thomas Blaser & Anja Schr\u00f6der Drechslerei & Holzbildhauerei",
    "wof:placetype":"venue"
},
  "geometry": {"coordinates":[7.2473359108,47.1431732178],"type":"Point"}
}