{
  "type": "Feature",
  "properties": {
    "iso:country":"CH",
    "sg:address":"Via Serafino Balestra 18",
    "sg:city":"Lugano",
    "sg:orig_category":"Wirtschaftspr\u00fcfung, Steuerberatung U Treuhand",
    "sg:postcode":"6900",
    "sg:province":"Ticino",
    "wof:name":"Isfi Sa",
    "wof:placetype":"venue"
},
  "geometry": {"coordinates":[8.957780838,46.0076789856],"type":"Point"}
}