{
  "type": "Feature",
  "properties": {
    "iso:country":"CH",
    "sg:address":"Postplatz 3",
    "sg:city":"Schwyz",
    "sg:orig_category":"Architektur U Ingenieurb\u00fcros",
    "sg:phone":"+41 41 811 54 00",
    "sg:postcode":"6430",
    "sg:province":"Schwyz",
    "wof:name":"Pius Weber Ingenieurb\u00fcro",
    "wof:placetype":"venue"
},
  "geometry": {"coordinates":[8.652942,47.020401],"type":"Point"}
}