{
  "type": "Feature",
  "properties": {
    "iso:country":"CH",
    "sg:address":"Grey Avenue Du 76 1018 Lausanne. Postfach",
    "sg:city":"Lausanne",
    "sg:orig_category":"Stukkateurgewerbe, Gipserei U Verputzerei",
    "sg:phone":"+41 24 492 39 32",
    "sg:postcode":"1018",
    "sg:province":"Vaud",
    "wof:name":"Jaccoud Ed. Sa, Succursale Des Diablerets",
    "wof:placetype":"venue"
},
  "geometry": {"coordinates":[7.1587119102,46.3500404358],"type":"Point"}
}