{
  "type": "Feature",
  "properties": {
    "iso:country":"CH",
    "sg:address":"Mattenweg 21",
    "sg:city":"Niederlenz",
    "sg:orig_category":"Sonstige mit der Informatik verbundene T\u00e4tigkeiten",
    "sg:phone":"+41 62 892 91 81",
    "sg:postcode":"5702",
    "sg:province":"Aargau",
    "wof:name":"Humard Michel",
    "wof:placetype":"venue"
},
  "geometry": {"coordinates":[8.1726312637,47.4073753357],"type":"Point"}
}