{
  "type": "Feature",
  "properties": {
    "iso:country":"CH",
    "sg:address":"Au Moulin 132",
    "sg:city":"Ch\u00e9nens",
    "sg:orig_category":"Grosshandel mit lebenden Tieren",
    "sg:phone":"+41 26 477 11 42",
    "sg:postcode":"1744",
    "sg:province":"Fribourg",
    "wof:name":"Alphonse Gander Commerce De Porcs",
    "wof:placetype":"venue"
},
  "geometry": {"coordinates":[7.0056557655,46.7329826355],"type":"Point"}
}