{
  "type": "Feature",
  "properties": {
    "iso:country":"CH",
    "sg:address":"Bernstrasse 7",
    "sg:city":"Kehrsatz",
    "sg:classifiers":[
        {
            "category":"Insurance",
            "subcategory":"Insurance Agent",
            "type":"Services"
        }
    ],
    "sg:phone":"+41 31 838 39 39",
    "sg:postcode":"3122",
    "sg:province":"Bern",
    "sg:tags":[
        "versicherungsagenturen",
        "-broker"
    ],
    "wof:name":"Winterthur Leben Agentur Familienversicherung",
    "wof:placetype":"venue"
},
  "geometry": {"coordinates":[7.4709219933,46.9103279114],"type":"Point"}
}