{
  "type": "Feature",
  "properties": {
    "iso:country":"CH",
    "sg:address":"L\u00f6wen-terrasse 1 6000 Luzern. Postfach",
    "sg:city":"Luzern",
    "sg:orig_category":"Erbringung von Dienstleistungen f\u00fcr Unternehmen",
    "sg:postcode":"6004",
    "sg:province":"Luzern",
    "wof:name":"Pf\u00e4ffli Hansj\u00f6rg Grafik Und Illustration",
    "wof:placetype":"venue"
},
  "geometry": {"coordinates":[8.3113412857,47.057346344],"type":"Point"}
}