{
  "type": "Feature",
  "properties": {
    "iso:country":"CH",
    "sg:address":"Drize Chemin De 25 1256 Troinex. Postfach",
    "sg:city":"Troinex",
    "sg:orig_category":"Architektur U Ingenieurb\u00fcros",
    "sg:phone":"+41 22 343 44 34",
    "sg:postcode":"1256",
    "sg:province":"Gen\u00e8ve",
    "wof:name":"Schaefer Sarl, Archideco Bureau D'architectes Etc",
    "wof:placetype":"venue"
},
  "geometry": {"coordinates":[6.148541,46.160435],"type":"Point"}
}