{
  "type": "Feature",
  "properties": {
    "iso:country":"CH",
    "sg:address":"Kapplergasse 11",
    "sg:city":"Z\u00fcrich",
    "sg:classifiers":[
        {
            "category":"Banks & Credit Unions",
            "subcategory":"Bank",
            "type":"Services"
        }
    ],
    "sg:phone":"+41 12125400",
    "sg:postcode":"8001",
    "sg:province":"Z\u00fcrich",
    "wof:name":"T\u00fcrkiye Halk, Bankasi As",
    "wof:placetype":"venue"
},
  "geometry": {"coordinates":[8.540664,47.368874],"type":"Point"}
}