{
  "type": "Feature",
  "properties": {
    "iso:country":"CH",
    "sg:address":"Ebnatstrasse 68",
    "sg:city":"Schaffhausen",
    "sg:classifiers":[
        {
            "category":"Restaurant",
            "type":"Food & Drink"
        }
    ],
    "sg:phone":"+41 52 625 26 56",
    "sg:postcode":"8200",
    "sg:province":"Schaffhausen",
    "wof:name":"Restaurant Waldesruh",
    "wof:placetype":"venue"
},
  "geometry": {"coordinates":[8.6443014145,47.7072296143],"type":"Point"}
}