{
  "type": "Feature",
  "properties": {
    "iso:country":"CH",
    "sg:address":"Strada Bagion 3",
    "sg:city":"Pambio-noranco",
    "sg:orig_category":"Bauschreinerei",
    "sg:phone":"+41 91 994 56 93",
    "sg:postcode":"6915",
    "sg:province":"Ticino",
    "wof:name":"Fabio Zoffoli Falegnameria",
    "wof:placetype":"venue"
},
  "geometry": {"coordinates":[8.933685,45.988312],"type":"Point"}
}