{
  "type": "Feature",
  "properties": {
    "iso:country":"CH",
    "sg:address":"Industriestrasse 635",
    "sg:city":"Egerkingen",
    "sg:orig_category":"Unclassifiable Establishments",
    "sg:postcode":"4622",
    "sg:province":"Solothurn",
    "wof:name":"Br\u00e4ker Holding Ag",
    "wof:placetype":"venue"
},
  "geometry": {"coordinates":[7.7948098183,47.3161468506],"type":"Point"}
}