{
  "type": "Feature",
  "properties": {
    "iso:country":"CH",
    "sg:address":"St. Antonstrasse",
    "sg:city":"Oberegg",
    "sg:orig_category":"Kauf U Verkauf von Immobilien auf eigene Rechnung",
    "sg:postcode":"9413",
    "sg:province":"Appenzell Innerhoden",
    "wof:name":"Hambi Ag",
    "wof:placetype":"venue"
},
  "geometry": {"coordinates":[9.5500297546,47.4220581055],"type":"Point"}
}