{
  "type": "Feature",
  "properties": {
    "iso:country":"CH",
    "sg:address":"Susenbergstrasse 108 8000 Z\u00fcrich. Postfach",
    "sg:city":"Z\u00fcrich",
    "sg:orig_category":"Verwaltung von Immobilien",
    "sg:postcode":"8044",
    "sg:province":"Z\u00fcrich",
    "wof:name":"West-park Z\u00fcrich Ag",
    "wof:placetype":"venue"
},
  "geometry": {"coordinates":[8.5622386932,47.3833045959],"type":"Point"}
}