{
  "type": "Feature",
  "properties": {
    "iso:country":"CH",
    "sg:address":"Rebgasse 7",
    "sg:city":"Frenkendorf",
    "sg:orig_category":"Zahnarztpraxen",
    "sg:phone":"+41 61 901 48 84",
    "sg:postcode":"4402",
    "sg:province":"Basel-Landschaft",
    "wof:name":"Dr. Med. Dent. Werner Thommen Zahnarzt",
    "wof:placetype":"venue"
},
  "geometry": {"coordinates":[7.7200169563,47.504524231],"type":"Point"}
}