{
  "type": "Feature",
  "properties": {
    "iso:country":"CH",
    "sg:address":"B\u00e4lliz 25",
    "sg:city":"Thun",
    "sg:orig_category":"Wirtschaftspr\u00fcfung, Steuerberatung U Treuhand",
    "sg:postcode":"3600",
    "sg:province":"Bern",
    "wof:name":"L\u00e4derach J\u00fcrg.",
    "wof:placetype":"venue"
},
  "geometry": {"coordinates":[7.6272478104,46.7590370178],"type":"Point"}
}