{
  "type": "Feature",
  "properties": {
    "iso:country":"CH",
    "sg:address":"Rue De L'avenir 12 2800 Delsberg. Postfach",
    "sg:city":"Delsberg",
    "sg:orig_category":"Non-Classified Establishments",
    "sg:postcode":"2800",
    "sg:province":"Jura",
    "wof:name":"Avenir Holding Sa",
    "wof:placetype":"venue"
},
  "geometry": {"coordinates":[7.3490409851,47.3645515442],"type":"Point"}
}