{
  "type": "Feature",
  "properties": {
    "iso:country":"CH",
    "sg:address":"Oberdorf 13",
    "sg:city":"Beringen",
    "sg:classifiers":[
        {
            "category":"Restaurant",
            "type":"Food & Drink"
        }
    ],
    "sg:phone":"+41 55 282 35 86",
    "sg:postcode":"8222",
    "sg:province":"Schaffhausen",
    "wof:name":"Gasthaus Ochsen",
    "wof:placetype":"venue"
},
  "geometry": {"coordinates":[8.9473638535,47.2431869507],"type":"Point"}
}