{
  "type": "Feature",
  "properties": {
    "iso:country":"CH",
    "sg:address":"Emmentalstrasse 127 B",
    "sg:city":"Oberburg",
    "sg:orig_category":"Handel mit Motorr\u00e4dern, Teilen U Zubeh\u00f6r Instandhaltung U Reparatur von Motorr\u00e4dern",
    "sg:phone":"+41 34 431 24 15",
    "sg:postcode":"3414",
    "sg:province":"Bern",
    "wof:name":"Brechb\u00fchl Kawasaki-motos Motorr\u00e4der, Motorrollern, Reparaturen Verkauf",
    "wof:placetype":"venue"
},
  "geometry": {"coordinates":[7.6337041855,47.0318260193],"type":"Point"}
}