{
  "type": "Feature",
  "properties": {
    "iso:country":"CH",
    "sg:address":"Walchestrasse 28",
    "sg:city":"Z\u00fcrich",
    "sg:orig_category":"Herstellung von sonstigen elektrischen Ausr\u00fcstungen Sonstige Bauinstallation",
    "sg:phone":"+41 16876810",
    "sg:postcode":"8006",
    "sg:province":"Z\u00fcrich",
    "wof:name":"Eets Gmbh Dienstleistungen F\u00fcr Planung, Realisation U. Unterhalt Von Strassenverkehrstechnischen Systemen",
    "wof:placetype":"venue"
},
  "geometry": {"coordinates":[8.7341480255,47.1973953247],"type":"Point"}
}