{
  "type": "Feature",
  "properties": {
    "addr:full":"Z\u00fcrichstrasse 38b Br\u00fcttisellen Z\u00fcrich 8306",
    "addr:housenumber":"38b bruettisellen",
    "addr:postcode":"8306",
    "addr:street":"Zuerichstrasse",
    "iso:country":"CH",
    "sg:address":"Z\u00fcrichstrasse 38b",
    "sg:city":"Br\u00fcttisellen",
    "sg:classifiers":[
        {
            "category":"Professional",
            "subcategory":"Advertising",
            "type":"Services"
        }
    ],
    "sg:phone":"+41 18055252",
    "sg:postcode":"8306",
    "sg:province":"Z\u00fcrich",
    "sg:tags":[
        "agency"
    ],
    "wof:name":"Fabritastika Gestaltungsatelier Ag",
    "wof:placetype":"venue"
},
  "geometry": {"coordinates":[8.628574,47.422379],"type":"Point"}
}