{
  "type": "Feature",
  "properties": {
    "iso:country":"CH",
    "sg:address":"Via Camminata 5",
    "sg:city":"Bellinzona",
    "sg:orig_category":"Drogerien Sonstiger Fachdetailhandel mit Nahrungsmitteln, Getr\u00e4nken U Tabak in Verkaufsr\u00e4umen",
    "sg:phone":"+41 71 333 37 67",
    "sg:postcode":"6500",
    "sg:province":"Ticino",
    "wof:name":"Ren\u00e9 Wichser Vital Drogerie",
    "wof:placetype":"venue"
},
  "geometry": {"coordinates":[9.3621683121,47.3862419128],"type":"Point"}
}