{
  "type": "Feature",
  "properties": {
    "iso:country":"CH",
    "sg:address":"Breitibachstrasse 21",
    "sg:city":"D\u00fcbendorf",
    "sg:orig_category":"Herstellung von Spielwaren",
    "sg:phone":"+41 18218441",
    "sg:postcode":"8600",
    "sg:province":"Z\u00fcrich",
    "wof:name":"Pastel Design",
    "wof:placetype":"venue"
},
  "geometry": {"coordinates":[8.6080217361,47.392780304],"type":"Point"}
}