{
  "type": "Feature",
  "properties": {
    "iso:country":"CH",
    "sg:address":"Gottardo Via San 82 6828 Balerna. Postfach",
    "sg:city":"Balerna",
    "sg:orig_category":"Verwaltung von Immobilien",
    "sg:phone":"+41 91 683 38 28",
    "sg:postcode":"6828",
    "sg:province":"Ticino",
    "wof:name":"Sapori Di Mare Sagl Esercizi Pubblici",
    "wof:placetype":"venue"
},
  "geometry": {"coordinates":[9.0067138672,45.8462524414],"type":"Point"}
}