{
  "type": "Feature",
  "properties": {
    "iso:country":"CH",
    "sg:address":"Murtenstrasse 37",
    "sg:city":"G\u00fcmmenen",
    "sg:orig_category":"Vereine Musik/Blasmusik",
    "sg:phone":"+41 31 751 11 72",
    "sg:postcode":"3205",
    "sg:province":"Bern",
    "wof:name":"Musikgesellschaft Ferenbalm",
    "wof:placetype":"venue"
},
  "geometry": {"coordinates":[7.2443580627,46.9445915222],"type":"Point"}
}