{
  "type": "Feature",
  "properties": {
    "iso:country":"CH",
    "sg:address":"9402",
    "sg:city":"M\u00f6rschwil",
    "sg:orig_category":"Landw. Genossenschaften Viehzucht",
    "sg:postcode":"9402",
    "sg:province":"St. Gallen",
    "wof:name":"Viehzuchtgenossenschaft",
    "wof:placetype":"venue"
},
  "geometry": {"coordinates":[9.564620018,47.3203887939],"type":"Point"}
}