{
  "type": "Feature",
  "properties": {
    "iso:country":"CH",
    "sg:address":"Galactinastrasse 2",
    "sg:city":"Belp",
    "sg:orig_category":"Sonstige k\u00fcnstlerische U schriftstellerische T\u00e4tigkeiten U Darbietungen",
    "sg:phone":"+41 79 218 46 69",
    "sg:postcode":"3123",
    "sg:province":"Bern",
    "wof:name":"Elisabeth Graber Atelier F\u00fcr Malen & Gestalten",
    "wof:placetype":"venue"
},
  "geometry": {"coordinates":[7.4992852211,46.8883209229],"type":"Point"}
}