{
  "type": "Feature",
  "properties": {
    "iso:country":"CH",
    "sg:address":"Feldg\u00fcetliweg 152",
    "sg:city":"Meilen",
    "sg:orig_category":"Sonstige mit der Informatik verbundene T\u00e4tigkeiten",
    "sg:phone":"+41 19237103",
    "sg:postcode":"8706",
    "sg:province":"Z\u00fcrich",
    "wof:name":"Ruzicka Peter Informatik",
    "wof:placetype":"venue"
},
  "geometry": {"coordinates":[8.6289196014,47.2733650208],"type":"Point"}
}