{
  "type": "Feature",
  "properties": {
    "iso:country":"CH",
    "sg:address":"Hintergasse 15",
    "sg:city":"Herzogenbuchsee",
    "sg:orig_category":"Herstellung von Duft U K\u00f6rperpflegemitteln",
    "sg:postcode":"3360",
    "sg:province":"Bern",
    "wof:name":"Kosmetik Vuoto",
    "wof:placetype":"venue"
},
  "geometry": {"coordinates":[7.7076969147,47.1886634827],"type":"Point"}
}