{
  "type": "Feature",
  "properties": {
    "iso:country":"CH",
    "sg:address":"Meissenrain 73",
    "sg:city":"Gockhausen",
    "sg:orig_category":"Sonstiges Textilgewerbe Textilveredlung",
    "sg:phone":"+41 14818522",
    "sg:postcode":"8044",
    "sg:province":"Z\u00fcrich",
    "wof:name":"Evolutione Textil Gmbh",
    "wof:placetype":"venue"
},
  "geometry": {"coordinates":[8.5983161926,47.3854255676],"type":"Point"}
}