{
  "type": "Feature",
  "properties": {
    "iso:country":"CH",
    "sg:address":"Rue Centrale 27 1350 Orbe. Postfach",
    "sg:city":"Orbe",
    "sg:orig_category":"Detailhandel mit Geschenkartikeln U Souvenirs Detailhandel mit Tabakwaren",
    "sg:phone":"+41 56 622 23 74",
    "sg:postcode":"1350",
    "sg:province":"Vaud",
    "wof:name":"Beatrix Wolf Tabakwaren & Geschenkartikel",
    "wof:placetype":"venue"
},
  "geometry": {"coordinates":[8.2777080536,47.3521118164],"type":"Point"}
}