{
  "type": "Feature",
  "properties": {
    "iso:country":"CH",
    "sg:address":"Belpstrasse 49",
    "sg:city":"Bern",
    "sg:orig_category":"Interessenvertretungen",
    "sg:phone":"+41 31 382 12 82",
    "sg:postcode":"3007",
    "sg:province":"Bern",
    "wof:name":"Sfjk Stiftung Schweizer Jugendkarte",
    "wof:placetype":"venue"
},
  "geometry": {"coordinates":[7.4316658974,46.9425201416],"type":"Point"}
}