{
  "type": "Feature",
  "properties": {
    "iso:country":"CH",
    "sg:address":"Hinterergeten",
    "sg:city":"Wolfhalden",
    "sg:classifiers":[
        {
            "category":"Home & Garden",
            "subcategory":"Furniture",
            "type":"Retail Goods"
        }
    ],
    "sg:phone":"+41 71 898 82 30",
    "sg:postcode":"9427",
    "sg:province":"Appenzell Ausserrhoden",
    "sg:tags":[
        "professional",
        "household",
        "wood"
    ],
    "wof:name":"Bach Heiden Ag",
    "wof:placetype":"venue"
},
  "geometry": {"coordinates":[9.5507450104,47.4537811279],"type":"Point"}
}