{
  "type": "Feature",
  "properties": {
    "iso:country":"CH",
    "sg:address":"Dorfstrasse 17",
    "sg:city":"Windisch",
    "sg:orig_category":"Physiotherapie",
    "sg:phone":"+41 56 442 03 23",
    "sg:postcode":"5210",
    "sg:province":"Aargau",
    "wof:name":"Physiotherapie Winters",
    "wof:placetype":"venue"
},
  "geometry": {"coordinates":[8.2219829559,47.4810142517],"type":"Point"}
}