{
  "type": "Feature",
  "properties": {
    "iso:country":"CH",
    "sg:address":"Othmarstrasse 8",
    "sg:city":"Z\u00fcrich",
    "sg:orig_category":"Pensionskassen",
    "sg:phone":"+41 32 374 14 14",
    "sg:postcode":"8008",
    "sg:province":"Z\u00fcrich",
    "wof:name":"Personalvorsorgestiftung Der Atlas Copco (schweiz) Ag",
    "wof:placetype":"venue"
},
  "geometry": {"coordinates":[7.3147788048,47.1114120483],"type":"Point"}
}