{
  "type": "Feature",
  "properties": {
    "iso:country":"CH",
    "sg:address":"Constant Place Benjamin- 2 1003 Lausanne. Postfach",
    "sg:city":"Lausanne",
    "sg:orig_category":"Non-Classified Establishments",
    "sg:postcode":"1003",
    "sg:province":"Vaud",
    "wof:name":"Hynatec Conseils Techniques",
    "wof:placetype":"venue"
},
  "geometry": {"coordinates":[-0.2772659957,48.6453056335],"type":"Point"}
}