{
  "type": "Feature",
  "properties": {
    "iso:country":"CH",
    "sg:address":"Fbg Ph. Suchard 7",
    "sg:city":"Boudry",
    "sg:classifiers":[
        {
            "category":"Home & Garden",
            "subcategory":"Furniture",
            "type":"Retail Goods"
        }
    ],
    "sg:phone":"+41 32 842 10 58",
    "sg:postcode":"2017",
    "sg:province":"Neuch\u00e2tel",
    "sg:tags":[
        "household",
        "wood"
    ],
    "wof:name":"Rossetti Meubles Sa",
    "wof:placetype":"venue"
},
  "geometry": {"coordinates":[6.833099,46.95356],"type":"Point"}
}