{
  "type": "Feature",
  "properties": {
    "iso:country":"CH",
    "sg:address":"Widen 7",
    "sg:city":"Bauma",
    "sg:orig_category":"Freizeit, Spiel U Spa\u00df",
    "sg:phone":"+41 52 386 31 18",
    "sg:postcode":"8494",
    "sg:province":"Z\u00fcrich",
    "wof:name":"Hampi\u00b4s Spielbus",
    "wof:placetype":"venue"
},
  "geometry": {"coordinates":[8.866107,47.370182],"type":"Point"}
}