{
  "type": "Feature",
  "properties": {
    "iso:country":"CH",
    "sg:address":"Rue Centrale 25",
    "sg:city":"Avenches",
    "sg:orig_category":"Detailhandel mit Milcherzeugnissen U Eiern Sonstiger Fachdetailhandel mit Nahrungsmitteln, Getr\u00e4nken",
    "sg:postcode":"1580",
    "sg:province":"Vaud",
    "wof:name":"Laiterie Chautems A.",
    "wof:placetype":"venue"
},
  "geometry": {"coordinates":[7.0411372185,46.8801422119],"type":"Point"}
}