{
  "type": "Feature",
  "properties": {
    "iso:country":"CH",
    "sg:address":"Dorfstrasse 10",
    "sg:city":"W\u00fcrenlingen",
    "sg:orig_category":"Werbeagenturen",
    "sg:phone":"+41 56 281 15 00",
    "sg:postcode":"5303",
    "sg:province":"Aargau",
    "wof:name":"Andr\u00e9 Signer Werbeagentur",
    "wof:placetype":"venue"
},
  "geometry": {"coordinates":[8.2569789886,47.532333374],"type":"Point"}
}