{
  "type": "Feature",
  "properties": {
    "iso:country":"CH",
    "sg:address":"W\u00e4ndh\u00fcslen",
    "sg:city":"Bubikon",
    "sg:orig_category":"Vermietung von Luftfahrzeugen",
    "sg:postcode":"8608",
    "sg:province":"Z\u00fcrich",
    "wof:name":"Ig Pci Ag",
    "wof:placetype":"venue"
},
  "geometry": {"coordinates":[8.8173131943,47.2808380127],"type":"Point"}
}