{
  "type": "Feature",
  "properties": {
    "iso:country":"CH",
    "sg:address":"Haldenstrasse 58 8904 Aesch. Postfach",
    "sg:city":"Aesch",
    "sg:orig_category":"Vermietung U Verpachtung von eigenen Immobilien",
    "sg:postcode":"8904",
    "sg:province":"Z\u00fcrich",
    "wof:name":"Ita Immobilien Trust Aesch Ag",
    "wof:placetype":"venue"
},
  "geometry": {"coordinates":[8.4442405701,47.3357810974],"type":"Point"}
}