{
  "type": "Feature",
  "properties": {
    "iso:country":"CH",
    "sg:address":"T\u00fcfiweg 4",
    "sg:city":"Bassersdorf",
    "sg:orig_category":"Gartenbau",
    "sg:phone":"+41 18365984",
    "sg:postcode":"8303",
    "sg:province":"Z\u00fcrich",
    "wof:name":"Friedrich Sommer G\u00e4rtnerei & Gartenbau",
    "wof:placetype":"venue"
},
  "geometry": {"coordinates":[8.6402206421,47.4306526184],"type":"Point"}
}