{
  "type": "Feature",
  "properties": {
    "iso:country":"CH",
    "sg:address":"6780",
    "sg:city":"Airolo",
    "sg:orig_category":"Detailhandel mit Waren verschiedener Art, Hauptrichtung Nahrungsmittel",
    "sg:phone":"+41 91 683 14 09",
    "sg:postcode":"6780",
    "sg:province":"Ticino",
    "wof:name":"Coop Ticino",
    "wof:placetype":"venue"
},
  "geometry": {"coordinates":[9.0213098526,45.8488502502],"type":"Point"}
}