{
  "type": "Feature",
  "properties": {
    "addr:full":"Rue De L'est 6 Gen\u00e8ve Gen\u00e8ve 1207",
    "addr:housenumber":"6",
    "addr:postcode":"1207",
    "addr:street":"Rue De L'Est",
    "iso:country":"CH",
    "sg:address":"Rue De L'est 6",
    "sg:city":"Gen\u00e8ve",
    "sg:orig_category":"Arztpraxen",
    "sg:phone":"+41 22 735 83 26",
    "sg:postcode":"1207",
    "sg:province":"Gen\u00e8ve",
    "wof:name":"Dr M\u00e9d. Jos\u00e9-manuel Arroja M\u00e9decin Sp\u00e9cialiste Fmh",
    "wof:placetype":"venue"
},
  "geometry": {"coordinates":[6.155522,46.199749],"type":"Point"}
}