{
  "type": "Feature",
  "properties": {
    "iso:country":"CH",
    "sg:address":"Turmatthof 51",
    "sg:city":"Stans",
    "sg:orig_category":"Markt U Meinungsforschung",
    "sg:postcode":"6370",
    "sg:province":"Nidwalden",
    "wof:name":"Steiger Marketingberatung",
    "wof:placetype":"venue"
},
  "geometry": {"coordinates":[8.3632507324,46.9624938965],"type":"Point"}
}