{
  "type": "Feature",
  "properties": {
    "iso:country":"CH",
    "sg:address":"4628",
    "sg:city":"Wolfwil",
    "sg:orig_category":"Landesverteidigung, Sozialversicherung \u00d6ffentliche Verwaltung",
    "sg:phone":"+41 62 926 37 60",
    "sg:postcode":"4628",
    "sg:province":"Solothurn",
    "wof:name":"Zivilschutzstelle Wolfwil",
    "wof:placetype":"venue"
},
  "geometry": {"coordinates":[7.7994689941,47.2698783875],"type":"Point"}
}