{
  "type": "Feature",
  "properties": {
    "iso:country":"CH",
    "sg:address":"Quaderstrasse 16",
    "sg:city":"Chur",
    "sg:orig_category":"Grosshandel mit sonstigen Maschinen U Ausr\u00fcstungen f\u00fcr Industrie, Handel U Schiffahrt",
    "sg:phone":"+41 55 450 60 00",
    "sg:postcode":"7000",
    "sg:province":"Graubunden",
    "wof:name":"Bios Ag, Bio Und Steriltechnik",
    "wof:placetype":"venue"
},
  "geometry": {"coordinates":[8.8952970505,47.1959686279],"type":"Point"}
}