{
  "type": "Feature",
  "properties": {
    "iso:country":"CH",
    "sg:address":"Rue Auguste-bachelin 14",
    "sg:city":"Marin-epagnier",
    "sg:orig_category":"Vorschulen, Kinderg\u00e4rten",
    "sg:phone":"+41 32 753 42 60",
    "sg:postcode":"2074",
    "sg:province":"Neuch\u00e2tel",
    "wof:name":"Ecole Enfantine I-iii",
    "wof:placetype":"venue"
},
  "geometry": {"coordinates":[7.0009980202,47.0090751648],"type":"Point"}
}