{
  "type": "Feature",
  "properties": {
    "iso:country":"CH",
    "sg:address":"Avenue Du Mont-blanc 14a",
    "sg:city":"Gland",
    "sg:orig_category":"Kantonalbanken",
    "sg:postcode":"1196",
    "sg:province":"Vaud",
    "wof:name":"Banque Cantonale Vaudoise",
    "wof:placetype":"venue"
},
  "geometry": {"coordinates":[6.262360096,46.4211158752],"type":"Point"}
}