{
  "type": "Feature",
  "properties": {
    "iso:country":"CH",
    "sg:address":"Gstadstrasse 25",
    "sg:city":"Zollikon",
    "sg:orig_category":"Betrieb von Taxis",
    "sg:phone":"+41 13414162",
    "sg:postcode":"8702",
    "sg:province":"Z\u00fcrich",
    "wof:name":"Limousine Service Beat Weber",
    "wof:placetype":"venue"
},
  "geometry": {"coordinates":[8.570424,47.339695],"type":"Point"}
}