{
  "type": "Feature",
  "properties": {
    "iso:country":"CH",
    "sg:address":"Metallstrasse 9a 6300 Zug. Postfach 4657",
    "sg:city":"Zug",
    "sg:orig_category":"Handelsvermittlung U Grosshandel Sonstiger Grosshandel",
    "sg:phone":"+41 41 726 56 06",
    "sg:postcode":"6304",
    "sg:province":"Zug",
    "wof:name":"Rigitrade Ag",
    "wof:placetype":"venue"
},
  "geometry": {"coordinates":[8.5183458328,47.1736183167],"type":"Point"}
}