{
  "type": "Feature",
  "properties": {
    "iso:country":"CH",
    "sg:address":"Muraz-sierre",
    "sg:city":"Sierre",
    "sg:orig_category":"Interessenvertretungen",
    "sg:postcode":"3960",
    "sg:province":"Valais",
    "wof:name":"Fondation Edelweiss Muraz-sierre",
    "wof:placetype":"venue"
},
  "geometry": {"coordinates":[7.5288901329,46.2974510193],"type":"Point"}
}