{
  "type": "Feature",
  "properties": {
    "iso:country":"CH",
    "sg:address":"Farnen",
    "sg:city":"Sax",
    "sg:orig_category":"Bauschreinerei",
    "sg:phone":"+41 81 757 25 70",
    "sg:postcode":"9468",
    "sg:province":"St. Gallen",
    "wof:name":"Josef Kaiser Schreinerei",
    "wof:placetype":"venue"
},
  "geometry": {"coordinates":[9.452435,47.222324],"type":"Point"}
}