{
  "type": "Feature",
  "properties": {
    "iso:country":"CH",
    "sg:address":"Langackerstrasse 25",
    "sg:city":"Cham",
    "sg:orig_category":"Handelsvermittlung U Grosshandel Sonstiger Grosshandel",
    "sg:phone":"+41 41 783 27 27",
    "sg:postcode":"6330",
    "sg:province":"Zug",
    "wof:name":"Alteco Gmbh",
    "wof:placetype":"venue"
},
  "geometry": {"coordinates":[8.4543180466,47.1972427368],"type":"Point"}
}