{
  "type": "Feature",
  "properties": {
    "iso:country":"CH",
    "sg:address":"Ruessenstrasse 5 6340 Baar. Postfach 1113",
    "sg:city":"Zug",
    "sg:orig_category":"Handelsvermittlung U Grosshandel Sonstiger Grosshandel",
    "sg:phone":"+41 18500500",
    "sg:postcode":"6301",
    "sg:province":"Zug",
    "wof:name":"Addon Gmbh",
    "wof:placetype":"venue"
},
  "geometry": {"coordinates":[8.4971370697,47.4868202209],"type":"Point"}
}