{
  "type": "Feature",
  "properties": {
    "iso:country":"CH",
    "sg:address":"Sablons Rue Des 39",
    "sg:city":"Neuch\u00e2tel",
    "sg:orig_category":"Softwareentwicklung U beratung",
    "sg:phone":"+41 32 725 43 82",
    "sg:postcode":"2000",
    "sg:province":"Neuch\u00e2tel",
    "wof:name":"Msd D\u00e9veloppements S\u00e0rl",
    "wof:placetype":"venue"
},
  "geometry": {"coordinates":[6.9311738014,46.9959335327],"type":"Point"}
}