{
  "type": "Feature",
  "properties": {
    "iso:country":"CH",
    "sg:address":"Rue Des Remparts 17",
    "sg:city":"Yverdon",
    "sg:classifiers":[
        {
            "category":"Banks & Credit Unions",
            "subcategory":"Bank",
            "type":"Services"
        }
    ],
    "sg:phone":"+41 24238511",
    "sg:postcode":"1400",
    "sg:province":"Vaud",
    "wof:name":"Banque Cantonale Vaudoise",
    "wof:placetype":"venue"
},
  "geometry": {"coordinates":[6.670759,46.781742],"type":"Point"}
}