{
  "type": "Feature",
  "properties": {
    "iso:country":"CH",
    "sg:address":"B\u00fcchsenweg 10",
    "sg:city":"Dulliken",
    "sg:orig_category":"Elektrizit\u00e4tsversorgung",
    "sg:postcode":"4657",
    "sg:province":"Solothurn",
    "wof:name":"Remac Umwelttechnik R. Mark",
    "wof:placetype":"venue"
},
  "geometry": {"coordinates":[7.9446549416,47.3462867737],"type":"Point"}
}