{
  "type": "Feature",
  "properties": {
    "iso:country":"CH",
    "sg:address":"Bellevuestrasse 6",
    "sg:city":"Hochdorf",
    "sg:orig_category":"Detailhandel mit Waren verschiedener Art, Hauptrichtung Nahrungsmittel",
    "sg:phone":"+41 41 910 10 43",
    "sg:postcode":"6280",
    "sg:province":"Luzern",
    "wof:name":"Coop Center",
    "wof:placetype":"venue"
},
  "geometry": {"coordinates":[8.2883672714,47.1693878174],"type":"Point"}
}