{
  "type": "Feature",
  "properties": {
    "iso:country":"CH",
    "sg:address":"Pallatex Route De 17 1163 Etoy. Postfach",
    "sg:city":"Etoy",
    "sg:orig_category":"Institutionen des Sozialwesens ohne Beherbergung",
    "sg:phone":"+41 21 821 31 11",
    "sg:postcode":"1163",
    "sg:province":"Vaud",
    "wof:name":"Fondation De Pr\u00e9voyance En Faveur Du Personnel De Ucar Sa Pr\u00e9munir Le Personnel Contre Les Cons\u00e9quences \u00e9conomiques R\u00e9sultant De La Vieillesse Etc",
    "wof:placetype":"venue"
},
  "geometry": {"coordinates":[6.4193058014,46.4849510193],"type":"Point"}
}