{
  "type": "Feature",
  "properties": {
    "iso:country":"CH",
    "sg:address":"Blumenmatt 537",
    "sg:city":"Kestenholz",
    "sg:orig_category":"Unternehmensberatung",
    "sg:phone":"+41 62 393 29 57",
    "sg:postcode":"4703",
    "sg:province":"Solothurn",
    "wof:name":"Bosec Borer",
    "wof:placetype":"venue"
},
  "geometry": {"coordinates":[7.7520899773,47.2794189453],"type":"Point"}
}