{
  "type": "Feature",
  "properties": {
    "iso:country":"CH",
    "sg:address":"Neumattstrasse 14",
    "sg:city":"Urdorf",
    "sg:orig_category":"Vorschulen, Kinderg\u00e4rten",
    "sg:phone":"+41 17344679",
    "sg:postcode":"8902",
    "sg:province":"Z\u00fcrich",
    "wof:name":"Kindergarten",
    "wof:placetype":"venue"
},
  "geometry": {"coordinates":[8.4214134216,47.3889656067],"type":"Point"}
}