{
  "type": "Feature",
  "properties": {
    "iso:country":"CH",
    "sg:address":"Haldengasse 27",
    "sg:city":"Zeiningen",
    "sg:orig_category":"Zimmerei, Dachdeckerei, Bauspenglerei U Abdichtung",
    "sg:phone":"+41 61 851 12 13",
    "sg:postcode":"4314",
    "sg:province":"Aargau",
    "wof:name":"Leo Merz Ag Holzbau",
    "wof:placetype":"venue"
},
  "geometry": {"coordinates":[7.870704174,47.5445823669],"type":"Point"}
}