{
  "type": "Feature",
  "properties": {
    "iso:country":"CH",
    "sg:address":"Place Du Ch\u00e2teau",
    "sg:city":"Grandson",
    "sg:orig_category":"Museen",
    "sg:phone":"+41 24 445 29 26",
    "sg:postcode":"1422",
    "sg:province":"Vaud",
    "wof:name":"Mus\u00e9e Du Ch\u00e2teau",
    "wof:placetype":"venue"
},
  "geometry": {"coordinates":[6.6454977989,46.8093414307],"type":"Point"}
}