{
  "type": "Feature",
  "properties": {
    "addr:full":"Wolleraustrasse 11a 8807 Freienbach. Postfach Freienbach Schwyz 8807",
    "addr:housenumber":"11a",
    "addr:postcode":"8807;8807",
    "addr:street":"Wolleraustrasse;Postfach;Schwyz",
    "iso:country":"CH",
    "sg:address":"Wolleraustrasse 11a 8807 Freienbach. Postfach",
    "sg:city":"Freienbach",
    "sg:orig_category":"Architektur U Ingenieurb\u00fcros Verlegen von Fliesen U Platten",
    "sg:phone":"+41 81 756 22 49",
    "sg:postcode":"8807",
    "sg:province":"Schwyz",
    "wof:name":"Schlegel Ulrich Gmbh Architektur, Hoch, Tiefbau, Orts, Regional, Landesplanung Usw.; Planung, Dienstleistungen, Forschung, Beratung",
    "wof:placetype":"venue"
},
  "geometry": {"coordinates":[9.473055,47.168755],"type":"Point"}
}