{
  "type": "Feature",
  "properties": {
    "iso:country":"CH",
    "sg:address":"Grabackerstrasse 18",
    "sg:city":"Kriegstetten",
    "sg:orig_category":"Detailhandel mit Schreib U Papeteriewaren",
    "sg:phone":"+41 32 675 43 23",
    "sg:postcode":"4566",
    "sg:province":"Solothurn",
    "wof:name":"Curt Beutler Papeterie",
    "wof:placetype":"venue"
},
  "geometry": {"coordinates":[7.5974240303,47.1798057556],"type":"Point"}
}