{
  "type": "Feature",
  "properties": {
    "addr:full":"Blumenwies 2 Gais Appenzell Ausserrhoden 9056",
    "addr:housenumber":"2",
    "addr:postcode":"9056",
    "addr:street":"Blumenwies;Appenzell Ausserrhoden",
    "iso:country":"CH",
    "sg:address":"Blumenwies 2",
    "sg:city":"Gais",
    "sg:orig_category":"Blumen U Zierpflanzenbau Detailhandel mit Blumen U Pflanzen",
    "sg:phone":"+41 71 367 20 49",
    "sg:postcode":"9056",
    "sg:province":"Appenzell Ausserrhoden",
    "wof:name":"J\u00fcrg N\u00fcnlist Blumengesch\u00e4ft",
    "wof:placetype":"venue"
},
  "geometry": {"coordinates":[9.468556,47.368038],"type":"Point"}
}