{
  "type": "Feature",
  "properties": {
    "addr:full":"Centre Commercial Marly Fribourg 1723",
    "addr:postcode":"1723",
    "iso:country":"CH",
    "sg:address":"Centre Commercial",
    "sg:city":"Marly",
    "sg:classifiers":[
        {
            "category":"Banks & Credit Unions",
            "subcategory":"Bank",
            "type":"Services"
        }
    ],
    "sg:phone":"+41 37461384",
    "sg:postcode":"1723",
    "sg:province":"Fribourg",
    "wof:name":"Union De Banques Suisses",
    "wof:placetype":"venue"
},
  "geometry": {"coordinates":[7.160805,46.776611],"type":"Point"}
}