{
  "type": "Feature",
  "properties": {
    "iso:country":"CH",
    "sg:address":"Baslerstrasse 32b",
    "sg:city":"Umiken",
    "sg:orig_category":"Herstellung von Konstruktionsteilen, Fertigbauteilen U Ausbauelementen aus Holz Innenausbau",
    "sg:phone":"+41 56 442 15 52",
    "sg:postcode":"5222",
    "sg:province":"Aargau",
    "wof:name":"Spicher M. Schreinerei",
    "wof:placetype":"venue"
},
  "geometry": {"coordinates":[8.1913795471,47.4832038879],"type":"Point"}
}