{
  "type": "Feature",
  "properties": {
    "iso:country":"CH",
    "sg:address":"Via Fiorita 13 6977 Ruvigliana. Postfach",
    "sg:city":"Ruvigliana",
    "sg:orig_category":"Vermietung U Verpachtung von eigenen Immobilien",
    "sg:postcode":"6977",
    "sg:province":"Ticino",
    "wof:name":"Rosatua Sa",
    "wof:placetype":"venue"
},
  "geometry": {"coordinates":[8.9779396057,46.0064659119],"type":"Point"}
}