{
  "type": "Feature",
  "properties": {
    "iso:country":"CH",
    "sg:address":"4207",
    "sg:city":"Bretzwil",
    "sg:orig_category":"Vereine Vogel-& Naturschutz",
    "sg:postcode":"4207",
    "sg:province":"Basel-Landschaft",
    "wof:name":"Vogelschutzverein",
    "wof:placetype":"venue"
},
  "geometry": {"coordinates":[7.6527900696,47.3977088928],"type":"Point"}
}