{
  "type": "Feature",
  "properties": {
    "iso:country":"CH",
    "sg:address":"Hardfeldstrasse 10",
    "sg:city":"Olten",
    "sg:orig_category":"Non-Classified Establishments",
    "sg:postcode":"4600",
    "sg:province":"Solothurn",
    "wof:name":"Immobilien Von Arx G. S\u00f6hne",
    "wof:placetype":"venue"
},
  "geometry": {"coordinates":[7.90878582,47.3500785828],"type":"Point"}
}