{
  "type": "Feature",
  "properties": {
    "iso:country":"CH",
    "sg:address":"Spillstatt",
    "sg:city":"Grindelwald",
    "sg:orig_category":"Malerei",
    "sg:phone":"+41 33 853 10 40",
    "sg:postcode":"3818",
    "sg:province":"Bern",
    "wof:name":"Fred Moser Ag Malergesch\u00e4ft",
    "wof:placetype":"venue"
},
  "geometry": {"coordinates":[8.0272884369,46.6262817383],"type":"Point"}
}