{
  "type": "Feature",
  "properties": {
    "iso:country":"CH",
    "sg:address":"R\u00f6schibachstrasse 55",
    "sg:city":"Z\u00fcrich",
    "sg:orig_category":"Grosshandel mit Nahrungsmitteln, Getr\u00e4nken U Tabakwaren ohne ausgepr\u00e4gten Schwerpunkt",
    "sg:postcode":"8037",
    "sg:province":"Z\u00fcrich",
    "wof:name":"T\u00fclek, Import Und Export Lebensmittel Aller Art, Spirituosen; Import, Export, Handel Usw.",
    "wof:placetype":"venue"
},
  "geometry": {"coordinates":[8.526515007,47.3936309814],"type":"Point"}
}