{
  "type": "Feature",
  "properties": {
    "iso:country":"CH",
    "sg:address":"Gossauerstrasse 39",
    "sg:city":"Herisau",
    "sg:classifiers":[
        {
            "category":"Restaurant",
            "type":"Food & Drink"
        }
    ],
    "sg:phone":"+41 71 351 23 47",
    "sg:postcode":"9100",
    "sg:province":"Appenzell Ausserrhoden",
    "wof:name":"Restaurant Schwanen",
    "wof:placetype":"venue"
},
  "geometry": {"coordinates":[9.2763710022,47.3871116638],"type":"Point"}
}