{
  "type": "Feature",
  "properties": {
    "addr:full":"Rue De La Gare 1860 Aigle Case Postale 429 Aigle Vaud 1860",
    "addr:housenumber":"429",
    "addr:postcode":"1860;1860",
    "addr:street":"Rue De La Gare;Case Postale",
    "iso:country":"CH",
    "sg:address":"Rue De La Gare 1860 Aigle Case Postale 429",
    "sg:city":"Aigle",
    "sg:orig_category":"Bahnhofbuffets Restaurants",
    "sg:phone":"+41 24 466 26 61",
    "sg:postcode":"1860",
    "sg:province":"Vaud",
    "wof:name":"Buffet De La Gare",
    "wof:placetype":"venue"
},
  "geometry": {"coordinates":[6.96805,46.318008],"type":"Point"}
}