{
  "type": "Feature",
  "properties": {
    "iso:country":"CH",
    "sg:address":"Stauffacherstrasse 177",
    "sg:city":"Z\u00fcrich",
    "sg:orig_category":"Elektroinstallation",
    "sg:phone":"+41 12429090",
    "sg:postcode":"8004",
    "sg:province":"Z\u00fcrich",
    "wof:name":"Rolf Kuster Elektrische Installationen",
    "wof:placetype":"venue"
},
  "geometry": {"coordinates":[8.5202302933,47.3782157898],"type":"Point"}
}