{
  "type": "Feature",
  "properties": {
    "iso:country":"CH",
    "sg:address":"6713",
    "sg:city":"Malvaglia",
    "sg:orig_category":"Herstellung von Metallkonstruktionen",
    "sg:phone":"+41 91 870 14 68",
    "sg:postcode":"6713",
    "sg:province":"Ticino",
    "wof:name":"Galizzi Giancarlo",
    "wof:placetype":"venue"
},
  "geometry": {"coordinates":[8.9809846878,46.4114151001],"type":"Point"}
}