{
  "type": "Feature",
  "properties": {
    "iso:country":"CH",
    "sg:address":"Hauptstrasse 85",
    "sg:city":"Muntelier",
    "sg:orig_category":"Fernmeldedienste",
    "sg:postcode":"3286",
    "sg:province":"Fribourg",
    "wof:name":"Red Communications Cannon & Hornisberger",
    "wof:placetype":"venue"
},
  "geometry": {"coordinates":[7.1270580292,46.9370193481],"type":"Point"}
}