{
  "type": "Feature",
  "properties": {
    "iso:country":"CH",
    "sg:address":"Bachstrasse 53 5000 Aarau. Postfach",
    "sg:city":"Aarau",
    "sg:orig_category":"Werbung",
    "sg:phone":"+41 62 824 94 84",
    "sg:postcode":"5001",
    "sg:province":"Aargau",
    "wof:name":"Renzen & Partner Ag",
    "wof:placetype":"venue"
},
  "geometry": {"coordinates":[8.0502576828,47.3894386292],"type":"Point"}
}