{
  "type": "Feature",
  "properties": {
    "iso:country":"CH",
    "sg:address":"Bireggstrasse 30",
    "sg:city":"Luzern",
    "sg:orig_category":"Maschinen-Fabrikation",
    "sg:phone":"+41 41 743 16 50",
    "sg:postcode":"6003",
    "sg:province":"Luzern",
    "wof:name":"Qfs Gmbh",
    "wof:placetype":"venue"
},
  "geometry": {"coordinates":[8.3061828613,47.0417404175],"type":"Point"}
}