{
  "type": "Feature",
  "properties": {
    "iso:country":"CH",
    "sg:address":"Corso San Gottardo 72",
    "sg:city":"Chiasso",
    "sg:orig_category":"Grosshandel mit Schmuck Herstellung von Schmuck, Gold U Silberschmiedwaren",
    "sg:phone":"+41 91 683 07 74",
    "sg:postcode":"6830",
    "sg:province":"Ticino",
    "wof:name":"Meridor Sa",
    "wof:placetype":"venue"
},
  "geometry": {"coordinates":[9.026974678,45.8357658386],"type":"Point"}
}