{
  "type": "Feature",
  "properties": {
    "iso:country":"CH",
    "sg:address":"Eibenstrasse 4",
    "sg:city":"Z\u00fcrich",
    "sg:orig_category":"Werbeagenturen Werbung",
    "sg:phone":"+41 19336194",
    "sg:postcode":"8045",
    "sg:province":"Z\u00fcrich",
    "wof:name":"Gaudio & Partner Ag",
    "wof:placetype":"venue"
},
  "geometry": {"coordinates":[8.7852602005,47.3258209229],"type":"Point"}
}