{
  "type": "Feature",
  "properties": {
    "iso:country":"CH",
    "sg:address":"Kasernenstrasse 23",
    "sg:city":"B\u00fclach",
    "sg:orig_category":"Unternehmensberatung",
    "sg:phone":"+41 79 646 05 77",
    "sg:postcode":"8180",
    "sg:province":"Z\u00fcrich",
    "wof:name":"Berra Lyss Unternehmensberatung",
    "wof:placetype":"venue"
},
  "geometry": {"coordinates":[8.537612915,47.5179176331],"type":"Point"}
}