{
  "type": "Feature",
  "properties": {
    "iso:country":"CH",
    "sg:address":"4226",
    "sg:city":"Breitenbach",
    "sg:orig_category":"Primarschulen",
    "sg:phone":"+41 41 811 44 02",
    "sg:postcode":"4226",
    "sg:province":"Solothurn",
    "wof:name":"Primarschule Aufiberg",
    "wof:placetype":"venue"
},
  "geometry": {"coordinates":[8.6681699753,47.0146789551],"type":"Point"}
}