{
  "type": "Feature",
  "properties": {
    "iso:country":"CH",
    "sg:address":"Hauptstrasse",
    "sg:city":"Raron",
    "sg:orig_category":"Instandhaltung U Reparatur von Automobilen",
    "sg:phone":"+41 27 934 33 03",
    "sg:postcode":"3942",
    "sg:province":"Valais",
    "wof:name":"Abc Carrosserie, Ventz Und Co.",
    "wof:placetype":"venue"
},
  "geometry": {"coordinates":[7.8000950813,46.3097190857],"type":"Point"}
}