{
  "type": "Feature",
  "properties": {
    "iso:country":"CH",
    "sg:address":"Ch\u00eane Route De 36",
    "sg:city":"Gen\u00e8ve",
    "sg:orig_category":"Erschliessung von Grundst\u00fccken",
    "sg:postcode":"1208",
    "sg:province":"Gen\u00e8ve",
    "wof:name":"Cooplog, Soci\u00e9t\u00e9 Pour La Cr\u00e9ation De Coop\u00e9ratives D'habitation",
    "wof:placetype":"venue"
},
  "geometry": {"coordinates":[6.1414251328,46.1833114624],"type":"Point"}
}