{
  "type": "Feature",
  "properties": {
    "iso:country":"CH",
    "sg:address":"Tellstrasse 31",
    "sg:city":"Z\u00fcrich",
    "sg:orig_category":"Detailhandel mit Sportartikeln Fachdetailhandel in Verkaufsr\u00e4umen",
    "sg:phone":"+41 12734664",
    "sg:postcode":"8000",
    "sg:province":"Z\u00fcrich",
    "wof:name":"Boardclinic Stirnimann & Co",
    "wof:placetype":"venue"
},
  "geometry": {"coordinates":[8.5291204453,47.379196167],"type":"Point"}
}