{
  "type": "Feature",
  "properties": {
    "iso:country":"CH",
    "sg:address":"H\u00f6henstrasse 6",
    "sg:city":"Reussb\u00fchl",
    "sg:orig_category":"Technische B\u00fcros Heizung, L\u00fcftung, Klima",
    "sg:phone":"+41 41 622 13 22",
    "sg:postcode":"6015",
    "sg:province":"Luzern",
    "wof:name":"Hle-konzepte Gmbh",
    "wof:placetype":"venue"
},
  "geometry": {"coordinates":[8.2836933136,47.0620346069],"type":"Point"}
}