{
  "type": "Feature",
  "properties": {
    "iso:country":"CH",
    "sg:address":"R\u00fcfistrasse 14",
    "sg:city":"Flums",
    "sg:orig_category":"Non-Classified Establishments",
    "sg:postcode":"8890",
    "sg:province":"St. Gallen",
    "wof:name":"Metall & Kunstschlosserei Gienuth Sandy",
    "wof:placetype":"venue"
},
  "geometry": {"coordinates":[9.3448390961,47.0858192444],"type":"Point"}
}