{
  "type": "Feature",
  "properties": {
    "iso:country":"CH",
    "sg:address":"Sonnenbergstrasse 4",
    "sg:city":"Uster",
    "sg:orig_category":"Maler U Glasergewerbe Malerei",
    "sg:phone":"+41 19411137",
    "sg:postcode":"8610",
    "sg:province":"Z\u00fcrich",
    "wof:name":"Malermeister Gallati O. Gmbh",
    "wof:placetype":"venue"
},
  "geometry": {"coordinates":[8.7037401199,47.3506698608],"type":"Point"}
}