{
  "type": "Feature",
  "properties": {
    "iso:country":"CH",
    "sg:address":"Weinfelder Strasse 16",
    "sg:city":"Rothenhausen",
    "sg:orig_category":"Landesverteidigung, Sozialversicherung \u00d6ffentliche Verwaltung",
    "sg:phone":"+41 71 626 58 10",
    "sg:postcode":"9565",
    "sg:province":"Thurgau",
    "wof:name":"Zivilschutzstelle Bussnang",
    "wof:placetype":"venue"
},
  "geometry": {"coordinates":[9.101776123,47.5506782532],"type":"Point"}
}