{
  "type": "Feature",
  "properties": {
    "iso:country":"CH",
    "sg:address":"Feutersoey 3785 Gsteig B. Gstaad. Postfach",
    "sg:city":"Feutersoey",
    "sg:classifiers":[
        {
            "category":"Travel",
            "subcategory":"Hotels & Motels",
            "type":"Entertainment"
        }
    ],
    "sg:postcode":"3784",
    "sg:province":"Bern",
    "sg:tags":[
        "hotels",
        "mit",
        "restaurant"
    ],
    "wof:name":"Reichenbach Hubert, Gasthaus R\u00f6ssli",
    "wof:placetype":"venue"
},
  "geometry": {"coordinates":[7.2674098015,46.3868637085],"type":"Point"}
}