{
  "type": "Feature",
  "properties": {
    "iso:country":"CH",
    "sg:address":"Ackersteinstrasse 199",
    "sg:city":"Z\u00fcrich",
    "sg:orig_category":"Hardwareberatung",
    "sg:phone":"+41 13413777",
    "sg:postcode":"8049",
    "sg:province":"Z\u00fcrich",
    "wof:name":"Gerteis Electronic",
    "wof:placetype":"venue"
},
  "geometry": {"coordinates":[8.4992084503,47.4012565613],"type":"Point"}
}