{
  "type": "Feature",
  "properties": {
    "iso:country":"CH",
    "sg:address":"T\u00f6sstalstrasse 28",
    "sg:city":"Kollbrunn",
    "sg:orig_category":"Detailhandel mit Milcherzeugnissen U Eiern",
    "sg:phone":"+41 52 383 12 33",
    "sg:postcode":"8483",
    "sg:province":"Z\u00fcrich",
    "wof:name":"Werner Stoll Milchprodukte",
    "wof:placetype":"venue"
},
  "geometry": {"coordinates":[8.7712955475,47.4575653076],"type":"Point"}
}