{
  "type": "Feature",
  "properties": {
    "iso:country":"CH",
    "sg:address":"Stauffacherstrasse 130",
    "sg:city":"Bern",
    "sg:orig_category":"Herstellung von konfektionierten Textilwaren ohne Bekleidung",
    "sg:phone":"+41 32 341 70 14",
    "sg:postcode":"3014",
    "sg:province":"Bern",
    "wof:name":"Schenker Storen Ag Biel",
    "wof:placetype":"venue"
},
  "geometry": {"coordinates":[7.2648139,47.1512870789],"type":"Point"}
}