{
  "type": "Feature",
  "properties": {
    "iso:country":"CH",
    "sg:address":"Place Beaulieu 10",
    "sg:city":"Sierre",
    "sg:orig_category":"Sportvereine Billard",
    "sg:phone":"+41 27 455 21 98",
    "sg:postcode":"3960",
    "sg:province":"Valais",
    "wof:name":"Billard Club Sierrois",
    "wof:placetype":"venue"
},
  "geometry": {"coordinates":[7.5290188789,46.2907562256],"type":"Point"}
}