{
  "type": "Feature",
  "properties": {
    "iso:country":"CH",
    "sg:address":"Collina D'oro Via 58 6926 Montagnola. Postfach",
    "sg:city":"Montagnola",
    "sg:orig_category":"Allgemeiner Hoch U Tiefbau",
    "sg:postcode":"6926",
    "sg:province":"Ticino",
    "wof:name":"Motta Giovanni Impresa Generale Ecc",
    "wof:placetype":"venue"
},
  "geometry": {"coordinates":[8.917031,45.984642],"type":"Point"}
}