{
  "type": "Feature",
  "properties": {
    "iso:country":"CH",
    "sg:address":"Chemin Des Grands-pr\u00e9s 7",
    "sg:city":"Mies-tannay",
    "sg:orig_category":"Grosshandel mit elektrischen Haushaltsger\u00e4ten, Radio U Fernsehger\u00e4ten Herstellung von sonstigen elek",
    "sg:phone":"+41 22 776 44 83",
    "sg:postcode":"1295",
    "sg:province":"Vaud",
    "wof:name":"Mc Tech Sa",
    "wof:placetype":"venue"
},
  "geometry": {"coordinates":[6.1724500656,46.3060684204],"type":"Point"}
}