{
  "type": "Feature",
  "properties": {
    "iso:country":"CH",
    "sg:address":"Vechigen Dorf",
    "sg:city":"Boll",
    "sg:orig_category":"Verarbeitung von Milch Verwertung von Milch",
    "sg:postcode":"3067",
    "sg:province":"Bern",
    "wof:name":"Milchgenossenschaft Vechigen",
    "wof:placetype":"venue"
},
  "geometry": {"coordinates":[7.5616650581,46.9468002319],"type":"Point"}
}