{
  "type": "Feature",
  "properties": {
    "iso:country":"CH",
    "sg:address":"Arisd\u00f6rferstrasse 94",
    "sg:city":"Liestal",
    "sg:orig_category":"Elektrizit\u00e4tsversorgung",
    "sg:phone":"+41 61 923 00 31",
    "sg:postcode":"4410",
    "sg:province":"Basel-Landschaft",
    "wof:name":"Eicher Hanspeter",
    "wof:placetype":"venue"
},
  "geometry": {"coordinates":[7.750289917,47.4844779968],"type":"Point"}
}