{
  "type": "Feature",
  "properties": {
    "iso:country":"CH",
    "sg:address":"Sumpfstrasse 32 6312 Steinhausen. Postfach 348",
    "sg:city":"Steinhausen",
    "sg:orig_category":"Handelsvermittlung U Grosshandel Handelsvermittlung von Brennstoffen, Erzen, Metallen U Chemikalien",
    "sg:phone":"+41 22 827 98 00",
    "sg:postcode":"6312",
    "sg:province":"Zug",
    "wof:name":"Progico Sa",
    "wof:placetype":"venue"
},
  "geometry": {"coordinates":[6.1356110573,46.187084198],"type":"Point"}
}