{
  "type": "Feature",
  "properties": {
    "iso:country":"CH",
    "sg:address":"Thunstrasse 10 1712 Tafers. Postfach",
    "sg:city":"Tafers",
    "sg:orig_category":"Gesundheitswesen",
    "sg:postcode":"1712",
    "sg:province":"Fribourg",
    "wof:name":"Intihuatana Blanchard Rita Gesundheitspraxis",
    "wof:placetype":"venue"
},
  "geometry": {"coordinates":[7.2199368477,46.8161468506],"type":"Point"}
}