{
  "type": "Feature",
  "properties": {
    "addr:full":"Titliszentrum 6 Engelberg Obwalden 6390",
    "addr:housenumber":"6",
    "addr:postcode":"6390",
    "addr:street":"Titliszentrum",
    "iso:country":"CH",
    "sg:address":"Titliszentrum 6",
    "sg:city":"Engelberg",
    "sg:orig_category":"Detailhandel mit Bekleidung Detailhandel mit Textilien",
    "sg:phone":"+41 41 637 14 65",
    "sg:postcode":"6390",
    "sg:province":"Obwalden",
    "wof:name":"Rita's Wull\u00e4-egg\u00e4 Handarbeiten Berufskleider",
    "wof:placetype":"venue"
},
  "geometry": {"coordinates":[8.404034,46.820492],"type":"Point"}
}