{
  "type": "Feature",
  "properties": {
    "iso:country":"CH",
    "sg:address":"Neumarkt 5",
    "sg:city":"Z\u00fcrich",
    "sg:orig_category":"Unclassifiable Establishments",
    "sg:phone":"+41 12527939",
    "sg:postcode":"8001",
    "sg:province":"Z\u00fcrich",
    "wof:name":"Restaurant Zunfthaus Am Neumarkt",
    "wof:placetype":"venue"
},
  "geometry": {"coordinates":[8.5457267761,47.3726043701],"type":"Point"}
}