{
  "type": "Feature",
  "properties": {
    "iso:country":"CH",
    "sg:address":"Route De Porrentruy 2",
    "sg:city":"Del\u00e9mont",
    "sg:orig_category":"Vermittlung von Immobilien Wirtschaftspr\u00fcfung, Steuerberatung U Treuhand",
    "sg:phone":"+41 32 422 32 23",
    "sg:postcode":"2800",
    "sg:province":"Jura",
    "wof:name":"Chapatte Fran\u00e7ois Sa",
    "wof:placetype":"venue"
},
  "geometry": {"coordinates":[7.3415799141,47.363861084],"type":"Point"}
}