{
  "type": "Feature",
  "properties": {
    "iso:country":"CH",
    "sg:address":"Einschlagweg 67",
    "sg:city":"Burgdorf",
    "sg:orig_category":"D\u00e4mmung gegen K\u00e4lte, W\u00e4rme, Schall U Ersch\u00fctterung Zimmerei, Dachdeckerei, Bauspenglerei U Abdichtun",
    "sg:phone":"+41 34 422 22 21",
    "sg:postcode":"3400",
    "sg:province":"Bern",
    "wof:name":"Neuhaus Bedachungen Ag Burgdorf",
    "wof:placetype":"venue"
},
  "geometry": {"coordinates":[7.6287670135,47.0472488403],"type":"Point"}
}