{
  "type": "Feature",
  "properties": {
    "iso:country":"CH",
    "sg:address":"Steinbruchstrasse 12",
    "sg:city":"Chur",
    "sg:orig_category":"Erbringung von sonstigen Dienstleistungen f\u00fcr Unterhaltung, Erholung U Freizeit",
    "sg:phone":"+41 81 253 06 53",
    "sg:postcode":"7000",
    "sg:province":"Graubunden",
    "wof:name":"Kom - King Of Magic Ag",
    "wof:placetype":"venue"
},
  "geometry": {"coordinates":[9.5354919434,46.8517990112],"type":"Point"}
}