{
  "type": "Feature",
  "properties": {
    "iso:country":"CH",
    "sg:address":"Oberhochb\u00fchl 4",
    "sg:city":"Luzern",
    "sg:orig_category":"Fotografische Ateliers",
    "sg:phone":"+41 41 240 50 33",
    "sg:postcode":"6003",
    "sg:province":"Luzern",
    "wof:name":"Rolf W\u00fcest Fotografisches Atelier",
    "wof:placetype":"venue"
},
  "geometry": {"coordinates":[8.2961654663,47.0488433838],"type":"Point"}
}