{
  "type": "Feature",
  "properties": {
    "iso:country":"CH",
    "sg:address":"Klybeckstrasse 53 4057 Basel. Postfach",
    "sg:city":"Birsfelden",
    "sg:orig_category":"Sanit\u00e4r, Heizungs U L\u00fcftungsinstallation Sanit\u00e4rinstallation",
    "sg:phone":"+41 61 693 35 93",
    "sg:postcode":"4127",
    "sg:province":"Basel-Landschaft",
    "wof:name":"Jordi + Zurfluh",
    "wof:placetype":"venue"
},
  "geometry": {"coordinates":[7.5906410217,47.5669784546],"type":"Point"}
}