{
  "type": "Feature",
  "properties": {
    "iso:country":"CH",
    "sg:address":"R\u00fctistrasse 26a",
    "sg:city":"Amriswil",
    "sg:orig_category":"Sportvereine Behindertensport",
    "sg:postcode":"8580",
    "sg:province":"Thurgau",
    "wof:name":"Behinderten-sport-gruppe",
    "wof:placetype":"venue"
},
  "geometry": {"coordinates":[9.2963600159,47.5481491089],"type":"Point"}
}