{
  "type": "Feature",
  "properties": {
    "iso:country":"CH",
    "sg:address":"Rue Du Petit-chasseur 27",
    "sg:city":"Sion",
    "sg:orig_category":"Handels-H\u00e4user U Gesellschaften",
    "sg:phone":"+41 27 322 98 04",
    "sg:postcode":"1950",
    "sg:province":"Valais",
    "wof:name":"Favre Ren\u00e9-pierre",
    "wof:placetype":"venue"
},
  "geometry": {"coordinates":[7.3527598381,46.2331047058],"type":"Point"}
}