{
  "type": "Feature",
  "properties": {
    "iso:country":"CH",
    "sg:address":"Avenue De Montoie 26",
    "sg:city":"Lausanne",
    "sg:orig_category":"Detailhandel mit Fleisch U Fleischwaren",
    "sg:phone":"+41 21 323 37 56",
    "sg:postcode":"1007",
    "sg:province":"Vaud",
    "wof:name":"Placide Seydoux",
    "wof:placetype":"venue"
},
  "geometry": {"coordinates":[6.6118431091,46.5197067261],"type":"Point"}
}