{
  "type": "Feature",
  "properties": {
    "iso:country":"CH",
    "sg:address":"Oberdorfstrasse 18",
    "sg:city":"W\u00e4denswil",
    "sg:orig_category":"Detailhandel mit B\u00fcchern Sonstiger Fachdetailhandel in Verkaufsr\u00e4umen",
    "sg:phone":"+41 17804525",
    "sg:postcode":"8820",
    "sg:province":"Z\u00fcrich",
    "wof:name":"Maya Helfenstein Buchhandlung Mineralien",
    "wof:placetype":"venue"
},
  "geometry": {"coordinates":[8.669248,47.228313],"type":"Point"}
}