{
  "type": "Feature",
  "properties": {
    "iso:country":"CH",
    "sg:address":"Chabeliweg 536 5616 Meisterschwanden. Postfach",
    "sg:city":"Meisterschwanden",
    "sg:orig_category":"Detailhandel mit elektrischen Haushalts-,Radio U Fernsehger\u00e4ten sowie Musikinstrumenten",
    "sg:phone":"+41 56 667 22 82",
    "sg:postcode":"5616",
    "sg:province":"Aargau",
    "wof:name":"Z\u00f6llig Elektronik",
    "wof:placetype":"venue"
},
  "geometry": {"coordinates":[8.2314500809,47.2975883484],"type":"Point"}
}