{
  "type": "Feature",
  "properties": {
    "addr:full":"Obere Stallstrasse 11 7430 Thusis. Postfach 27 Thusis Graubunden 7430",
    "addr:housenumber":"11;27",
    "addr:postcode":"7430 thusis.;7430",
    "addr:street":"Obere Stallstrasse;Postfach",
    "iso:country":"CH",
    "sg:address":"Obere Stallstrasse 11 7430 Thusis. Postfach 27",
    "sg:city":"Thusis",
    "sg:orig_category":"Arztpraxen",
    "sg:phone":"+41 52 741 28 38",
    "sg:postcode":"7430",
    "sg:province":"Graubunden",
    "wof:name":"Dr.med.andreas R. Dieterle Spezialarzt Fmh",
    "wof:placetype":"venue"
},
  "geometry": {"coordinates":[8.859567,47.660294],"type":"Point"}
}