{
  "type": "Feature",
  "properties": {
    "iso:country":"CH",
    "sg:address":"Quaderstrasse 19",
    "sg:city":"Chur",
    "sg:orig_category":"Unclassifiable Establishments",
    "sg:postcode":"7000",
    "sg:province":"Graubunden",
    "wof:name":"Tribble Holding Ag",
    "wof:placetype":"venue"
},
  "geometry": {"coordinates":[9.5333309174,46.8525428772],"type":"Point"}
}