{
  "type": "Feature",
  "properties": {
    "iso:country":"CH",
    "sg:address":"Rue De La Poste 24",
    "sg:city":"Pully",
    "sg:orig_category":"Detailhandel mit Tabakwaren",
    "sg:phone":"+41 32 841 21 67",
    "sg:postcode":"1009",
    "sg:province":"Vaud",
    "wof:name":"Christian Liengme Chez Popeye",
    "wof:placetype":"venue"
},
  "geometry": {"coordinates":[6.8607530594,46.966003418],"type":"Point"}
}