{
  "type": "Feature",
  "properties": {
    "iso:country":"CH",
    "sg:address":"Turnerstrasse 1",
    "sg:city":"Winterthur",
    "sg:orig_category":"Unclassifiable Establishments",
    "sg:phone":"+41 71 385 98 71",
    "sg:postcode":"8400",
    "sg:province":"Z\u00fcrich",
    "wof:name":"Partner - Promotion By Zellweger",
    "wof:placetype":"venue"
},
  "geometry": {"coordinates":[9.2504673004,47.406955719],"type":"Point"}
}