{
  "type": "Feature",
  "properties": {
    "iso:country":"CH",
    "sg:address":"Dorfstrasse 22",
    "sg:city":"Wabern",
    "sg:orig_category":"Detailhandel mit Waren verschiedener Art, Hauptrichtung Nahrungsmittel",
    "sg:phone":"+41 71 877 13 53",
    "sg:postcode":"3084",
    "sg:province":"Bern",
    "wof:name":"Spar Supermarkt Peter Kaufmann",
    "wof:placetype":"venue"
},
  "geometry": {"coordinates":[9.4905719757,47.4157562256],"type":"Point"}
}