{
  "type": "Feature",
  "properties": {
    "iso:country":"CH",
    "sg:address":"Weite Gasse 23 5400 Baden. Postfach",
    "sg:city":"Baden",
    "sg:orig_category":"RESTAURANTS: TEA-ROOMS",
    "sg:phone":"+41 62 216 12 63",
    "sg:postcode":"5402",
    "sg:province":"Aargau",
    "wof:name":"Restaurant Rose Senyurt N.",
    "wof:placetype":"venue"
},
  "geometry": {"coordinates":[7.8545498848,47.3280143738],"type":"Point"}
}