{
  "type": "Feature",
  "properties": {
    "addr:full":"Gewerbestrasse 17b Unter\u00e4geri Zug 6314",
    "addr:housenumber":"17b",
    "addr:postcode":"6314",
    "addr:street":"Gewerbestrasse;Unteraegeri Zug",
    "iso:country":"CH",
    "sg:address":"Gewerbestrasse 17b",
    "sg:city":"Unter\u00e4geri",
    "sg:orig_category":"Allgemeiner Hoch U Tiefbau Allgemeiner Hochbau",
    "sg:phone":"+41 41 750 32 82",
    "sg:postcode":"6314",
    "sg:province":"Zug",
    "wof:name":"Arnold Alois Ag.",
    "wof:placetype":"venue"
},
  "geometry": {"coordinates":[8.5733,47.133667],"type":"Point"}
}