{
  "type": "Feature",
  "properties": {
    "iso:country":"CH",
    "sg:address":"7605",
    "sg:city":"Stampa",
    "sg:classifiers":[
        {
            "category":"Education",
            "subcategory":"Vocational School",
            "type":"Public Place"
        }
    ],
    "sg:phone":"+41 81 822 12 81",
    "sg:postcode":"7605",
    "sg:province":"Graubunden",
    "sg:tags":[
        "koch-",
        "haushaltschulen"
    ],
    "wof:name":"Scuola Di Economia Domestica",
    "wof:placetype":"venue"
},
  "geometry": {"coordinates":[9.5913915634,46.3435287476],"type":"Point"}
}