{
  "type": "Feature",
  "properties": {
    "iso:country":"CH",
    "sg:address":"Avenue Du The\u00e2tre 8",
    "sg:city":"Lausanne",
    "sg:orig_category":"Unclassifiable Establishments",
    "sg:postcode":"1000",
    "sg:province":"Vaud",
    "wof:name":"Martinella Renzo",
    "wof:placetype":"venue"
},
  "geometry": {"coordinates":[6.6361269951,46.5183753967],"type":"Point"}
}