{
  "type": "Feature",
  "properties": {
    "iso:country":"CH",
    "sg:address":"Rue De Pirazilina",
    "sg:city":"Crans-sur-sierre",
    "sg:classifiers":[
        {
            "category":"Insurance",
            "subcategory":"Insurance Agent",
            "type":"Services"
        }
    ],
    "sg:phone":"+41 79 447 44 69",
    "sg:postcode":"3963",
    "sg:province":"Valais",
    "sg:tags":[
        "versicherungsagenturen",
        "-broker"
    ],
    "wof:name":"Helvetia Patria Assurances Agence Locale",
    "wof:placetype":"venue"
},
  "geometry": {"coordinates":[7.4716038704,46.2988624573],"type":"Point"}
}