{
  "type": "Feature",
  "properties": {
    "iso:country":"CH",
    "sg:address":"Flughafen Kloten Terminal B 8000 Z\u00fcrich. Postfach",
    "sg:city":"Z\u00fcrich",
    "sg:orig_category":"Herstellung von nachrichtentechnischen Ger\u00e4ten U Einrichtungen",
    "sg:postcode":"8000",
    "sg:province":"Z\u00fcrich",
    "wof:name":"Hb-yacht, Huser Norbert",
    "wof:placetype":"venue"
},
  "geometry": {"coordinates":[8.8290300369,47.2267799377],"type":"Point"}
}