{
  "type": "Feature",
  "properties": {
    "iso:country":"CH",
    "sg:address":"Aarefeldstrasse 19 3600 Thun. Postfach 2011",
    "sg:city":"Thun",
    "sg:orig_category":"Versicherungen Hauptagenturen",
    "sg:phone":"+41 33 223 31 07",
    "sg:postcode":"3601",
    "sg:province":"Bern",
    "wof:name":"Alpina Versicherungen",
    "wof:placetype":"venue"
},
  "geometry": {"coordinates":[7.6310501099,46.7555885315],"type":"Point"}
}