{
  "type": "Feature",
  "properties": {
    "iso:country":"CH",
    "sg:address":"Juchstrasse 31",
    "sg:city":"Frauenfeld",
    "sg:orig_category":"Herstellung von Tanks U Sammelbeh\u00e4ltern aus Metall",
    "sg:phone":"+41 52 720 74 40",
    "sg:postcode":"8500",
    "sg:province":"Thurgau",
    "wof:name":"G\u00f6ldi & Borsari Ag Tank- & Beschichtungssysteme",
    "wof:placetype":"venue"
},
  "geometry": {"coordinates":[8.9102525711,47.570224762],"type":"Point"}
}