{
  "type": "Feature",
  "properties": {
    "iso:country":"CH",
    "sg:address":"Via Pasquale Lucchini 6",
    "sg:city":"Lugano",
    "sg:orig_category":"Zahnarztpraxen",
    "sg:phone":"+41 91 922 63 22",
    "sg:postcode":"6900",
    "sg:province":"Ticino",
    "wof:name":"Dott. Med. Dent. Dan Kraus Dentista",
    "wof:placetype":"venue"
},
  "geometry": {"coordinates":[8.9575824738,46.0063209534],"type":"Point"}
}