{
  "type": "Feature",
  "properties": {
    "iso:country":"CH",
    "sg:address":"Kilchmattstrasse 4",
    "sg:city":"Niederdorf",
    "sg:orig_category":"Vorschulen, Kinderg\u00e4rten",
    "sg:phone":"+41 56 443 18 31",
    "sg:postcode":"4435",
    "sg:province":"Basel-Landschaft",
    "wof:name":"Kindergarten",
    "wof:placetype":"venue"
},
  "geometry": {"coordinates":[8.1718921661,47.448425293],"type":"Point"}
}