{
  "type": "Feature",
  "properties": {
    "iso:country":"CH",
    "sg:address":"Schreinergasse 3a",
    "sg:city":"Derendingen",
    "sg:orig_category":"Fische and Fischprodukte Grosshandel Grosshandel mit sonstigen Nahrungsmitteln",
    "sg:phone":"+41 32 682 06 92",
    "sg:postcode":"4552",
    "sg:province":"Solothurn",
    "wof:name":"Lachsimport Wittmer Gitte",
    "wof:placetype":"venue"
},
  "geometry": {"coordinates":[7.5865421295,47.1969032288],"type":"Point"}
}