{
  "type": "Feature",
  "properties": {
    "iso:country":"CH",
    "sg:address":"Grenzacherstrasse 231 4058 Basel. Postfach",
    "sg:city":"Basel",
    "sg:orig_category":"Rolladen- and Storenmontage",
    "sg:phone":"+41 61 681 01 23",
    "sg:postcode":"4016",
    "sg:province":"Basel-Stadt",
    "wof:name":"Bruno Singer Storen & Rolladen",
    "wof:placetype":"venue"
},
  "geometry": {"coordinates":[7.6120219231,47.5599975586],"type":"Point"}
}