{
  "type": "Feature",
  "properties": {
    "iso:country":"CH",
    "sg:address":"Kirchbergstrasse 105",
    "sg:city":"Burgdorf",
    "sg:orig_category":"Verwaltung von Immobilien",
    "sg:phone":"+41 34 422 78 33",
    "sg:postcode":"3400",
    "sg:province":"Bern",
    "wof:name":"Sch\u00e4r, Immobilien Verwaltungen",
    "wof:placetype":"venue"
},
  "geometry": {"coordinates":[7.6122832298,47.0634078979],"type":"Point"}
}