{
  "type": "Feature",
  "properties": {
    "iso:country":"CH",
    "sg:address":"Arbenzstrasse 5",
    "sg:city":"Z\u00fcrich",
    "sg:orig_category":"Softwareentwicklung U beratung",
    "sg:postcode":"8008",
    "sg:province":"Z\u00fcrich",
    "wof:name":"Chibber Gmbh",
    "wof:placetype":"venue"
},
  "geometry": {"coordinates":[8.5557041168,47.358543396],"type":"Point"}
}