{
  "type": "Feature",
  "properties": {
    "iso:country":"CH",
    "sg:address":"Route Du Petit-moncor 1 1752 Villars-sur-gl\u00e2ne Case Postale",
    "sg:city":"Villars-sur-gl\u00e2ne",
    "sg:orig_category":"Fachdetailhandel in Verkaufsr\u00e4umen Grosshandel mit Geschenkartikeln U Souvenirs",
    "sg:phone":"+41 26 401 09 09",
    "sg:postcode":"1752",
    "sg:province":"Fribourg",
    "wof:name":"Sc Surplus-commerce Sa",
    "wof:placetype":"venue"
},
  "geometry": {"coordinates":[7.119822979,46.7985496521],"type":"Point"}
}