{
  "type": "Feature",
  "properties": {
    "iso:country":"CH",
    "sg:address":"Ilgenstrasse 11",
    "sg:city":"Z\u00fcrich",
    "sg:orig_category":"Kinderkrippen U horte",
    "sg:phone":"+41 14610038",
    "sg:postcode":"8032",
    "sg:province":"Z\u00fcrich",
    "wof:name":"Hort Des Schulamtes Der Stadt Z\u00fcrich",
    "wof:placetype":"venue"
},
  "geometry": {"coordinates":[8.5590763092,47.3696136475],"type":"Point"}
}