{
  "type": "Feature",
  "properties": {
    "iso:country":"CH",
    "sg:address":"Au Petit-ch\u00e9zard",
    "sg:city":"Ch\u00e9zard-st-martin",
    "sg:orig_category":"Interessenvertretungen",
    "sg:postcode":"2054",
    "sg:province":"Neuch\u00e2tel",
    "wof:name":"Soci\u00e9t\u00e9 De Fromagerie De Ch\u00e9zard-saint-martin",
    "wof:placetype":"venue"
},
  "geometry": {"coordinates":[6.9202132225,47.0651550293],"type":"Point"}
}