{
  "type": "Feature",
  "properties": {
    "iso:country":"CH",
    "sg:address":"Gr\u00e4nicherstrasse 1",
    "sg:city":"Suhr",
    "sg:orig_category":"Druckweiterverarbeitung Handelsvermittlung U Grosshandel",
    "sg:phone":"+41 62 842 27 80",
    "sg:postcode":"5034",
    "sg:province":"Aargau",
    "wof:name":"Sigtech Ag Verpackungs- & Kennzeichnungstechnik",
    "wof:placetype":"venue"
},
  "geometry": {"coordinates":[8.079750061,47.3702545166],"type":"Point"}
}