{
  "type": "Feature",
  "properties": {
    "iso:country":"CH",
    "sg:address":"Erlosen",
    "sg:city":"Hinwil",
    "sg:orig_category":"Bridge Dehydration",
    "sg:phone":"+41 19381212",
    "sg:postcode":"8340",
    "sg:province":"Z\u00fcrich",
    "wof:name":"Etasa Ag",
    "wof:placetype":"venue"
},
  "geometry": {"coordinates":[8.82106,47.31456],"type":"Point"}
}