{
  "type": "Feature",
  "properties": {
    "iso:country":"CH",
    "sg:address":"Schwyzerstrasse 16",
    "sg:city":"Brunnen",
    "sg:orig_category":"G\u00fcterbef\u00f6rderung im Strassenverkehr",
    "sg:phone":"+41 41 820 10 01",
    "sg:postcode":"6440",
    "sg:province":"Schwyz",
    "wof:name":"Betschart Hugo.",
    "wof:placetype":"venue"
},
  "geometry": {"coordinates":[8.6139593124,47.0006523132],"type":"Point"}
}