{
  "type": "Feature",
  "properties": {
    "iso:country":"CH",
    "sg:address":"Haselrainstrasse 6",
    "sg:city":"Uster",
    "sg:orig_category":"D\u00e4mmung gegen K\u00e4lte, W\u00e4rme, Schall U Ersch\u00fctterung Herstellung von k\u00e4lte U lufttechnischen Erzeugnis",
    "sg:phone":"+41 22 300 30 11",
    "sg:postcode":"8610",
    "sg:province":"Z\u00fcrich",
    "wof:name":"Inotherm Sa",
    "wof:placetype":"venue"
},
  "geometry": {"coordinates":[6.1397547722,46.1816978455],"type":"Point"}
}