{
  "type": "Feature",
  "properties": {
    "iso:country":"CH",
    "sg:address":"Oberstm\u00fchle 2",
    "sg:city":"Stans",
    "sg:classifiers":[
        {
            "category":"Wholesale",
            "subcategory":"Plants",
            "type":"Manufacturing & Wholesale Goods"
        }
    ],
    "sg:phone":"+41 41 618 05 05",
    "sg:postcode":"6370",
    "sg:province":"Nidwalden",
    "sg:tags":[
        "water",
        "abrasive",
        "cutting",
        "jet"
    ],
    "wof:name":"Allfi Ag Wasserstrahl- Und Hochdrucktechnik",
    "wof:placetype":"venue"
},
  "geometry": {"coordinates":[8.357326,46.96809],"type":"Point"}
}