{
  "type": "Feature",
  "properties": {
    "iso:country":"CH",
    "sg:address":"Oetlingerstrasse 1",
    "sg:city":"Basel",
    "sg:orig_category":"Unternehmensberatung",
    "sg:phone":"+41 61 691 02 00",
    "sg:postcode":"4057",
    "sg:province":"Basel-Stadt",
    "wof:name":"Ibc - Institut F\u00fcr Bankmanagement Und Controlling Gmbh",
    "wof:placetype":"venue"
},
  "geometry": {"coordinates":[7.5868139267,47.5673828125],"type":"Point"}
}