{
  "type": "Feature",
  "properties": {
    "iso:country":"CH",
    "sg:address":"3722",
    "sg:city":"Scharnachtal",
    "sg:classifiers":[
        {
            "category":"Government",
            "subcategory":"Post Office",
            "type":"Public Place"
        }
    ],
    "sg:phone":"+41 33 676 12 04",
    "sg:postcode":"3722",
    "sg:province":"Bern",
    "sg:tags":[
        "die",
        "poststellen"
    ],
    "wof:name":"Die Post",
    "wof:placetype":"venue"
},
  "geometry": {"coordinates":[7.7011098862,46.6115493774],"type":"Point"}
}