{
  "type": "Feature",
  "properties": {
    "iso:country":"CH",
    "sg:address":"Quartiere La Sguancia",
    "sg:city":"Lugano",
    "sg:orig_category":"Grosshandel mit Wein U Spirituosen",
    "sg:phone":"+41 91 994 70 32",
    "sg:postcode":"6900",
    "sg:province":"Ticino",
    "wof:name":"Giacomo Provaso Commercio Vini",
    "wof:placetype":"venue"
},
  "geometry": {"coordinates":[8.9366540909,45.9854507446],"type":"Point"}
}