{
  "type": "Feature",
  "properties": {
    "iso:country":"CH",
    "sg:address":"Speerstrasse 8",
    "sg:city":"Dietlikon",
    "sg:orig_category":"Softwareentwicklung U beratung",
    "sg:phone":"+41 18333229",
    "sg:postcode":"8305",
    "sg:province":"Z\u00fcrich",
    "wof:name":"Frecosoft",
    "wof:placetype":"venue"
},
  "geometry": {"coordinates":[8.6173191071,47.4203720093],"type":"Point"}
}