{
  "type": "Feature",
  "properties": {
    "iso:country":"CH",
    "sg:address":"Hinterdorf",
    "sg:city":"Engi",
    "sg:orig_category":"Detailhandel mit Blumen U Pflanzen",
    "sg:phone":"+41 55 642 13 02",
    "sg:postcode":"8765",
    "sg:province":"Glarus",
    "wof:name":"Hans B\u00e4bler Blumengesch\u00e4ft",
    "wof:placetype":"venue"
},
  "geometry": {"coordinates":[9.159854,46.974625],"type":"Point"}
}