{
  "type": "Feature",
  "properties": {
    "iso:country":"CH",
    "sg:address":"Montagne Chemin De La 136",
    "sg:city":"Ch\u00eane-bougeries",
    "sg:orig_category":"Erwachsenenbildung U Unterricht",
    "sg:postcode":"1224",
    "sg:province":"Gen\u00e8ve",
    "wof:name":"Helma",
    "wof:placetype":"venue"
},
  "geometry": {"coordinates":[-110.0444717407,46.6794395447],"type":"Point"}
}