{
  "type": "Feature",
  "properties": {
    "iso:country":"CH",
    "sg:address":"Langenwilweg 3150 Schwarzenburg. Postfach 34",
    "sg:city":"Schwarzenburg",
    "sg:orig_category":"Institutionen f\u00fcr Behinderte Wohnheime",
    "sg:phone":"+41 31 731 17 77",
    "sg:postcode":"3150",
    "sg:province":"Bern",
    "wof:name":"Stiftung Bernaville",
    "wof:placetype":"venue"
},
  "geometry": {"coordinates":[7.3376951218,46.8144683838],"type":"Point"}
}