{
  "type": "Feature",
  "properties": {
    "iso:country":"CH",
    "sg:address":"Place Centrale 7",
    "sg:city":"Martigny",
    "sg:orig_category":"Detailhandel mit Uhren U Schmuck Fachdetailhandel in Verkaufsr\u00e4umen",
    "sg:phone":"+41 27 722 68 00",
    "sg:postcode":"1920",
    "sg:province":"Valais",
    "wof:name":"Jacot Yves",
    "wof:placetype":"venue"
},
  "geometry": {"coordinates":[7.07295084,46.1008987427],"type":"Point"}
}