{
  "type": "Feature",
  "properties": {
    "iso:country":"CH",
    "sg:address":"Zentralstrasse 27",
    "sg:city":"Neuhausen",
    "sg:orig_category":"Fachdetailhandel in Verkaufsr\u00e4umen",
    "sg:phone":"+41 19915035",
    "sg:postcode":"8212",
    "sg:province":"Schaffhausen",
    "wof:name":"Arces Art Experts Ltd",
    "wof:placetype":"venue"
},
  "geometry": {"coordinates":[8.6190357208,47.6811828613],"type":"Point"}
}