{
  "type": "Feature",
  "properties": {
    "iso:country":"CH",
    "sg:address":"Dufour Rue Du G\u00e9n\u00e9ral- 20 1204 Gen\u00e8ve. Postfach",
    "sg:city":"Gen\u00e8ve",
    "sg:orig_category":"Elektroinstallation",
    "sg:postcode":"1204",
    "sg:province":"Gen\u00e8ve",
    "wof:name":"Petite Ed.",
    "wof:placetype":"venue"
},
  "geometry": {"coordinates":[6.1422162056,46.2003250122],"type":"Point"}
}