{
  "type": "Feature",
  "properties": {
    "iso:country":"CH",
    "sg:address":"Adlerstrasse 44 4052 Basel. Postfach",
    "sg:city":"Basel",
    "sg:orig_category":"Wirtschaftspr\u00fcfung, Steuerberatung U Treuhand",
    "sg:phone":"+41 61 311 47 71",
    "sg:postcode":"4051",
    "sg:province":"Basel-Stadt",
    "wof:name":"Eit Edv Immobilien Treuhand Susanne Weisskopf Liegenschaftenhandel, Treuhandgesch\u00e4fte",
    "wof:placetype":"venue"
},
  "geometry": {"coordinates":[7.6104660034,47.5463142395],"type":"Point"}
}