{
  "type": "Feature",
  "properties": {
    "iso:country":"CH",
    "sg:address":"Route De Pr\u00e9verenges 1 1027 Lonay Case Postale 90",
    "sg:city":"Lonay",
    "sg:orig_category":"G\u00fcterbef\u00f6rderung im Strassenverkehr",
    "sg:postcode":"1027",
    "sg:province":"Vaud",
    "wof:name":"Eur\u00eaka D\u00e9m\u00e9nagements S\u00e0rl",
    "wof:placetype":"venue"
},
  "geometry": {"coordinates":[6.5223379135,46.5226173401],"type":"Point"}
}