{
  "type": "Feature",
  "properties": {
    "iso:country":"CH",
    "sg:address":"Konsumstrasse 3 3414 Oberburg. Postfach",
    "sg:city":"Oberburg",
    "sg:orig_category":"RESTAURANTS: TEA-ROOMS",
    "sg:phone":"+41 55 282 14 06",
    "sg:postcode":"3414",
    "sg:province":"Bern",
    "wof:name":"Restaurant Adler Renzo Cozzio",
    "wof:placetype":"venue"
},
  "geometry": {"coordinates":[8.9235715866,47.2412834167],"type":"Point"}
}