{
  "type": "Feature",
  "properties": {
    "iso:country":"CH",
    "sg:address":"Hegi 23",
    "sg:city":"Rafz",
    "sg:orig_category":"Datenverarbeitungsdienste Personal U Stellenvermittlung",
    "sg:phone":"+41 31 311 64 02",
    "sg:postcode":"8197",
    "sg:province":"Z\u00fcrich",
    "wof:name":"Computer Brainware Advisors Bern Ag Dienstleistungen, Bes Organisation, Informatik, Automation",
    "wof:placetype":"venue"
},
  "geometry": {"coordinates":[7.444645,46.948235],"type":"Point"}
}