{
  "type": "Feature",
  "properties": {
    "iso:country":"CH",
    "sg:address":"Eichenstrasse 15",
    "sg:city":"Wittenbach",
    "sg:orig_category":"Arztpraxen",
    "sg:phone":"+41 71 292 33 22",
    "sg:postcode":"9303",
    "wof:name":"Dr.med. Susanne Zurfluh \u00c4rztin F.allgemeine Medizin",
    "wof:placetype":"venue"
},
  "geometry": {"coordinates":[9.384364,47.460953],"type":"Point"}
}