{
  "type": "Feature",
  "properties": {
    "iso:country":"CH",
    "sg:address":"Westbahnhofstrasse 1 4500 Solothurn. Postfach",
    "sg:city":"Solothurn",
    "sg:orig_category":"Berufsbildende weiterf\u00fchrende Schulen",
    "sg:postcode":"4500",
    "sg:province":"Solothurn",
    "wof:name":"Covema Gmbh Schulungsseminare F\u00fcr Mitarbeiter Und Kaderkategorien Mit Markt Und Kunden Gerichteter T\u00e4tigkeit Usw",
    "wof:placetype":"venue"
},
  "geometry": {"coordinates":[7.532398,47.207253],"type":"Point"}
}