{
  "type": "Feature",
  "properties": {
    "iso:country":"CH",
    "sg:address":"Gliserallee 92",
    "sg:city":"Glis",
    "sg:orig_category":"Hoch U Tiefbau",
    "sg:phone":"+41 27 923 41 37",
    "sg:postcode":"3902",
    "sg:province":"Valais",
    "wof:name":"Theler Ag Bauunternehmung",
    "wof:placetype":"venue"
},
  "geometry": {"coordinates":[7.9824819565,46.313331604],"type":"Point"}
}