{
  "type": "Feature",
  "properties": {
    "iso:country":"CH",
    "sg:address":"Rue Des Jordils 29",
    "sg:city":"Yverdon-les-bains",
    "sg:orig_category":"Lichtpause U Reprografiebetriebe Satzherstellung U Reproduktion",
    "sg:phone":"+41 55 442 48 48",
    "sg:postcode":"1400",
    "sg:province":"Vaud",
    "wof:name":"Irma Th\u00f6ni Billco Lichtpausen",
    "wof:placetype":"venue"
},
  "geometry": {"coordinates":[8.8533906937,47.1918678284],"type":"Point"}
}