{
  "type": "Feature",
  "properties": {
    "iso:country":"CH",
    "sg:address":"Z\u00fcrichstrasse 52",
    "sg:city":"Herzogenbuchsee",
    "sg:orig_category":"Sportvereine Turnen",
    "sg:postcode":"3360",
    "sg:province":"Bern",
    "wof:name":"M\u00e4nnerturnverein",
    "wof:placetype":"venue"
},
  "geometry": {"coordinates":[7.7093958855,47.1925811768],"type":"Point"}
}