{
  "type": "Feature",
  "properties": {
    "iso:country":"CH",
    "sg:address":"Dorfstrasse 48",
    "sg:city":"Weisslingen",
    "sg:orig_category":"Herstellung von sonstigen M\u00f6beln Kunsthandel",
    "sg:phone":"+41 52 384 17 87",
    "sg:postcode":"8484",
    "sg:province":"Z\u00fcrich",
    "wof:name":"Haus Zum Rahmen, Frei",
    "wof:placetype":"venue"
},
  "geometry": {"coordinates":[8.7635269165,47.4338989258],"type":"Point"}
}