{
  "type": "Feature",
  "properties": {
    "addr:full":"Konkordiastrasse 12 Z\u00fcrich Z\u00fcrich 8032",
    "addr:housenumber":"12",
    "addr:postcode":"8032",
    "addr:street":"Konkordiastrasse",
    "iso:country":"CH",
    "sg:address":"Konkordiastrasse 12",
    "sg:city":"Z\u00fcrich",
    "sg:orig_category":"Arztpraxen",
    "sg:phone":"+41 55 240 85 35",
    "sg:postcode":"8032",
    "sg:province":"Z\u00fcrich",
    "wof:name":"Dr.med.marianne Bleuler Spezial\u00e4rztin Fmh",
    "wof:placetype":"venue"
},
  "geometry": {"coordinates":[8.857818,47.249809],"type":"Point"}
}