{
  "type": "Feature",
  "properties": {
    "iso:country":"CH",
    "sg:address":"Restelbergstrasse 16",
    "sg:city":"Z\u00fcrich",
    "sg:orig_category":"Herstellung von Medikamenten U sonstigen pharmazeutischen Erzeugnissen",
    "sg:phone":"+41 12531680",
    "sg:postcode":"8044",
    "sg:province":"Z\u00fcrich",
    "wof:name":"Vetparcs Veterinary Parasitology Consulting And Services Gmbh",
    "wof:placetype":"venue"
},
  "geometry": {"coordinates":[8.5582590103,47.3808631897],"type":"Point"}
}