{
  "type": "Feature",
  "properties": {
    "iso:country":"CH",
    "sg:address":"Niederwilerstrasse 10",
    "sg:city":"T\u00e4gerig",
    "sg:classifiers":[
        {
            "category":"Travel",
            "subcategory":"Hotels & Motels",
            "type":"Entertainment"
        }
    ],
    "sg:postcode":"5522",
    "sg:province":"Aargau",
    "sg:tags":[
        "hotels",
        "mit",
        "restaurant"
    ],
    "wof:name":"M\u00fcller Josef.",
    "wof:placetype":"venue"
},
  "geometry": {"coordinates":[8.2794427872,47.403049469],"type":"Point"}
}