{
  "type": "Feature",
  "properties": {
    "addr:full":"Hirschengraben 15 Luzern Luzern 6003",
    "addr:housenumber":"15",
    "addr:postcode":"6003",
    "addr:street":"Hirschengraben",
    "iso:country":"CH",
    "sg:address":"Hirschengraben 15",
    "sg:city":"Luzern",
    "sg:orig_category":"Detailhandel mit Brillen U anderen Sehhilfen Fachdetailhandel in Verkaufsr\u00e4umen",
    "sg:phone":"+41 16876280",
    "sg:postcode":"6003",
    "sg:province":"Luzern",
    "wof:name":"M\u00e4chler Roland Optik Brillen, Kontaktlinsen U. Instrumente; Beratung, Anpassung U. Verkauf",
    "wof:placetype":"venue"
},
  "geometry": {"coordinates":[8.734148,47.197395],"type":"Point"}
}