{
  "type": "Feature",
  "properties": {
    "iso:country":"CH",
    "sg:address":"Solothurnerstrasse 240",
    "sg:city":"Olten",
    "sg:orig_category":"Non-Classified Establishments",
    "sg:postcode":"4600",
    "sg:province":"Solothurn",
    "wof:name":"Dobler Druck Ag",
    "wof:placetype":"venue"
},
  "geometry": {"coordinates":[7.887857914,47.3478851318],"type":"Point"}
}