{
  "type": "Feature",
  "properties": {
    "iso:country":"CH",
    "sg:address":"Ulrich Hegner-strasse 4 8400 Winterthur. Postfach 467",
    "sg:city":"Winterthur",
    "sg:orig_category":"Reiseb\u00fcros U Reiseveranstalter",
    "sg:phone":"+41 52 203 11 73",
    "sg:postcode":"8401",
    "sg:province":"Z\u00fcrich",
    "wof:name":"Voyages Wasteels Sa Zweigniederlassung Winterthur",
    "wof:placetype":"venue"
},
  "geometry": {"coordinates":[8.7155323029,47.4976196289],"type":"Point"}
}