{
  "type": "Feature",
  "properties": {
    "iso:country":"CH",
    "sg:address":"Im Leh 15",
    "sg:city":"Stachen",
    "sg:orig_category":"Non-Classified Establishments",
    "sg:postcode":"9320",
    "sg:province":"Thurgau",
    "wof:name":"Petralli Gartengestaltung Ag",
    "wof:placetype":"venue"
},
  "geometry": {"coordinates":[9.4086866379,47.5078125],"type":"Point"}
}