{
  "type": "Feature",
  "properties": {
    "iso:country":"CH",
    "sg:address":"Krattigstrasse 1a",
    "sg:city":"Spiez",
    "sg:orig_category":"Locomotive Accessories And Parts",
    "sg:phone":"+41 33 650 36 11",
    "sg:postcode":"3700",
    "sg:province":"Bern",
    "wof:name":"Bls L\u00f6tschbergbahn Ag Werkst\u00e4tte Spiez",
    "wof:placetype":"venue"
},
  "geometry": {"coordinates":[7.6855459213,46.6813087463],"type":"Point"}
}