{
  "type": "Feature",
  "properties": {
    "iso:country":"CH",
    "sg:address":"Hauptstrasse 15a",
    "sg:city":"M\u00fclchi",
    "sg:orig_category":"RESTAURANTS: TEA-ROOMS",
    "sg:postcode":"3317",
    "sg:province":"Bern",
    "wof:name":"Restaurant L\u00f6wen, Hunziker Ruth",
    "wof:placetype":"venue"
},
  "geometry": {"coordinates":[7.4781541824,47.1012382507],"type":"Point"}
}