{
  "type": "Feature",
  "properties": {
    "iso:country":"CH",
    "sg:address":"Hagenacherstrasse 19 8307 Effretikon. Postfach",
    "sg:city":"Effretikon",
    "sg:orig_category":"Softwareentwicklung U beratung",
    "sg:postcode":"8307",
    "sg:province":"Z\u00fcrich",
    "wof:name":"Pc Network Dekany T.",
    "wof:placetype":"venue"
},
  "geometry": {"coordinates":[8.6846437454,47.426071167],"type":"Point"}
}