{
  "type": "Feature",
  "properties": {
    "iso:country":"CH",
    "sg:address":"Kugelgasse 21 8708 M\u00e4nnedorf. Postfach",
    "sg:city":"M\u00e4nnedorf",
    "sg:orig_category":"Museen",
    "sg:phone":"+41 19267651",
    "sg:postcode":"8708",
    "sg:province":"Z\u00fcrich",
    "wof:name":"Schifffahrtsmuseum M\u00e4nnedorf",
    "wof:placetype":"venue"
},
  "geometry": {"coordinates":[8.6912870407,47.2546806335],"type":"Point"}
}