{
  "type": "Feature",
  "properties": {
    "iso:country":"CH",
    "sg:address":"Wehrlen",
    "sg:city":"D\u00fcbendorf",
    "sg:orig_category":"Non-Classified Establishments",
    "sg:postcode":"8600",
    "sg:province":"Z\u00fcrich",
    "wof:name":"Video Night S\u00e0rl",
    "wof:placetype":"venue"
},
  "geometry": {"coordinates":[6.7470259666,47.0566253662],"type":"Point"}
}