{
  "type": "Feature",
  "properties": {
    "iso:country":"CH",
    "sg:address":"Beatenbergstrasse 35a",
    "sg:city":"Unterseen",
    "sg:orig_category":"Kosmetikinstitute",
    "sg:phone":"+41 33 822 33 31",
    "sg:postcode":"3800",
    "sg:province":"Bern",
    "wof:name":"Ruth B\u00fchler Kosmetikinstitut",
    "wof:placetype":"venue"
},
  "geometry": {"coordinates":[7.8454518318,46.6878662109],"type":"Point"}
}