{
  "type": "Feature",
  "properties": {
    "iso:country":"CH",
    "sg:address":"Grand Rue 98",
    "sg:city":"Montreux",
    "sg:orig_category":"Bijouterien Fachdetailhandel in Verkaufsr\u00e4umen",
    "sg:phone":"+41 21 963 95 20",
    "sg:postcode":"1820",
    "sg:province":"Vaud",
    "wof:name":"Suter Alexandre Bijouterie",
    "wof:placetype":"venue"
},
  "geometry": {"coordinates":[6.907883,46.43763],"type":"Point"}
}