{
  "type": "Feature",
  "properties": {
    "iso:country":"CH",
    "sg:address":"Lindenb\u00fchlstrasse 9",
    "sg:city":"D\u00fcbendorf",
    "sg:orig_category":"G\u00fcterbef\u00f6rderung im Strassenverkehr",
    "sg:phone":"+41 71 633 33 54",
    "sg:postcode":"8600",
    "sg:province":"Z\u00fcrich",
    "wof:name":"Wilhelm Koch Gmbh",
    "wof:placetype":"venue"
},
  "geometry": {"coordinates":[8.7834119797,47.5724067688],"type":"Point"}
}