{
  "type": "Feature",
  "properties": {
    "iso:country":"CH",
    "sg:address":"Auf Dem Berg 5",
    "sg:city":"Meinisberg",
    "sg:orig_category":"Campingpl\u00e4tze Detailhandel mit Zeitungen U Zeitschriften Kioske",
    "sg:phone":"+41 17640328",
    "sg:postcode":"2554",
    "sg:province":"Bern",
    "wof:name":"Strandbad Am T\u00fcrlersee",
    "wof:placetype":"venue"
},
  "geometry": {"coordinates":[8.51321,47.267574],"type":"Point"}
}