{
  "type": "Feature",
  "properties": {
    "iso:country":"CH",
    "sg:address":"Sonnenstrasse 4",
    "sg:city":"Brig",
    "sg:orig_category":"Interessenvertretungen",
    "sg:postcode":"3900",
    "sg:province":"Valais",
    "wof:name":"Stiftung Von Stockalper Fernanda",
    "wof:placetype":"venue"
},
  "geometry": {"coordinates":[7.9874629974,46.3181800842],"type":"Point"}
}