{
  "type": "Feature",
  "properties": {
    "iso:country":"CH",
    "sg:address":"Gartenstrasse 5 8805 Richterswil. Postfach",
    "sg:city":"Richterswil",
    "sg:orig_category":"Siebdruck Sonstiges Textilgewerbe",
    "sg:phone":"+41 17841162",
    "sg:postcode":"8805",
    "sg:province":"Z\u00fcrich",
    "wof:name":"Strebel-walz Ag",
    "wof:placetype":"venue"
},
  "geometry": {"coordinates":[8.7089996338,47.2064781189],"type":"Point"}
}