{
  "type": "Feature",
  "properties": {
    "iso:country":"CH",
    "sg:address":"Bernstrasse 35",
    "sg:city":"Rothrist",
    "sg:orig_category":"Textilgewerbe",
    "sg:phone":"+41 22 342 04 70",
    "sg:postcode":"4852",
    "sg:province":"Aargau",
    "wof:name":"Bottiglieri Sa Manufacture De Stores Et De Fermetures, Commerce De Tous Produits Et Articles Se Rattachant \u00e0 La Construction",
    "wof:placetype":"venue"
},
  "geometry": {"coordinates":[6.1354060173,46.1796722412],"type":"Point"}
}