{
  "type": "Feature",
  "properties": {
    "iso:country":"CH",
    "sg:address":"Sonnenstrasse 12",
    "sg:city":"Amriswil",
    "sg:orig_category":"Zahntechnische Laboratorien",
    "sg:phone":"+41 71 411 47 60",
    "sg:postcode":"8580",
    "sg:province":"Thurgau",
    "wof:name":"Martin G\u00fcbeli Zahntechnisches Labor",
    "wof:placetype":"venue"
},
  "geometry": {"coordinates":[9.2906618118,47.5431213379],"type":"Point"}
}