{
  "type": "Feature",
  "properties": {
    "iso:country":"CH",
    "sg:address":"Sattelgasse 1",
    "sg:city":"Basel",
    "sg:orig_category":"Architekturb\u00fcros",
    "sg:phone":"+41 61 681 37 29",
    "sg:postcode":"4051",
    "sg:province":"Basel-Stadt",
    "wof:name":"Dieter Lehner Architekturb\u00fcro Eth Sia",
    "wof:placetype":"venue"
},
  "geometry": {"coordinates":[7.587453,47.558197],"type":"Point"}
}