{
  "type": "Feature",
  "properties": {
    "iso:country":"CH",
    "sg:address":"Rue Du Simplon 18",
    "sg:city":"Vevey",
    "sg:orig_category":"Zahnarztpraxen",
    "sg:phone":"+41 21 921 11 90",
    "sg:postcode":"1800",
    "sg:province":"Vaud",
    "wof:name":"Dr M\u00e9d. Dent. Robert Brodmann M\u00e9decin-dentiste",
    "wof:placetype":"venue"
},
  "geometry": {"coordinates":[6.8459730148,46.4596481323],"type":"Point"}
}