{
  "type": "Feature",
  "properties": {
    "iso:country":"CH",
    "sg:address":"In Den Neusatzreben 3",
    "sg:city":"Pratteln",
    "sg:orig_category":"Massagestudios",
    "sg:phone":"+41 61 821 74 81",
    "sg:postcode":"4133",
    "sg:province":"Basel-Landschaft",
    "wof:name":"Walter Berger Sportmassagen",
    "wof:placetype":"venue"
},
  "geometry": {"coordinates":[7.709883213,47.52293396],"type":"Point"}
}