{
  "type": "Feature",
  "properties": {
    "iso:country":"CH",
    "sg:address":"Industriestr. 29",
    "sg:city":"Volketswil",
    "sg:classifiers":[
        {
            "category":"Professional",
            "subcategory":"Engineering",
            "type":"Services"
        }
    ],
    "sg:phone":"+41 4119472211",
    "sg:postcode":"8604",
    "sg:province":"Z\u00fcrich",
    "sg:tags":[
        "machine",
        "pharmacy",
        "-",
        "mechanical"
    ],
    "wof:name":"Wipf Ag",
    "wof:placetype":"venue"
},
  "geometry": {"coordinates":[8.679432869,47.3800239563],"type":"Point"}
}