{
  "type": "Feature",
  "properties": {
    "iso:country":"CH",
    "sg:address":"Nierenw\u00e4ldliweg 21",
    "sg:city":"R\u00fcttenen",
    "sg:orig_category":"Bauschreinerei Herstellung von Konstruktionsteilen, Fertigbauteilen U Ausbauelementen aus Holz",
    "sg:phone":"+41 81 933 12 60",
    "sg:postcode":"4522",
    "sg:province":"Solothurn",
    "wof:name":"Thomas Tschuor Schreinerei & Innenausbau",
    "wof:placetype":"venue"
},
  "geometry": {"coordinates":[9.08154,46.744202],"type":"Point"}
}