{
  "type": "Feature",
  "properties": {
    "iso:country":"CH",
    "sg:address":"Industrie Rue De L' 15",
    "sg:city":"Sion",
    "sg:orig_category":"Herstellung von elektrischen Lampen U Leuchten",
    "sg:phone":"+41 26 677 38 10",
    "sg:postcode":"1950",
    "sg:province":"Valais",
    "wof:name":"Lumin-ball Sarl",
    "wof:placetype":"venue"
},
  "geometry": {"coordinates":[6.9800829887,46.8900337219],"type":"Point"}
}