{
  "type": "Feature",
  "properties": {
    "iso:country":"CH",
    "sg:address":"B\u00fcrgenstockstrasse 56",
    "sg:city":"Ennetb\u00fcrgen",
    "sg:orig_category":"Hochschulen U h\u00f6here Ausbildung",
    "sg:postcode":"6373",
    "sg:province":"Nidwalden",
    "wof:name":"Gemako Gmbh",
    "wof:placetype":"venue"
},
  "geometry": {"coordinates":[8.420170784,46.9895706177],"type":"Point"}
}