{
  "type": "Feature",
  "properties": {
    "iso:country":"CH",
    "sg:address":"1733",
    "sg:city":"Treyvaux",
    "sg:orig_category":"Grosshandel mit elektrischen Haushaltsger\u00e4ten Grosshandel mit elektrischen Haushaltsger\u00e4ten, Radio U",
    "sg:phone":"+41 22 970 16 70",
    "sg:postcode":"1733",
    "sg:province":"Fribourg",
    "wof:name":"Griot Andr\u00e9 Et Cie",
    "wof:placetype":"venue"
},
  "geometry": {"coordinates":[6.1002898216,46.2071914673],"type":"Point"}
}