{
  "type": "Feature",
  "properties": {
    "iso:country":"CH",
    "sg:address":"Milit\u00e4rstrasse 43",
    "sg:city":"Luzern",
    "sg:orig_category":"Einzelhandel mit Automobilteilen U Zubeh\u00f6r",
    "sg:phone":"+41 74332150",
    "sg:postcode":"6003",
    "sg:province":"Luzern",
    "wof:name":"Bruno H\u00fcppin Garage & Pneuhandel",
    "wof:placetype":"venue"
},
  "geometry": {"coordinates":[8.8964147568,47.1912956238],"type":"Point"}
}