{
  "type": "Feature",
  "properties": {
    "iso:country":"CH",
    "sg:address":"4703",
    "sg:city":"Kestenholz",
    "sg:orig_category":"Sportvereine Sch\u00fctzen",
    "sg:phone":"+41 62 393 19 38",
    "sg:postcode":"4703",
    "sg:province":"Solothurn",
    "wof:name":"Feldsch\u00fctzengesellschaft",
    "wof:placetype":"venue"
},
  "geometry": {"coordinates":[7.7537951469,47.2831115723],"type":"Point"}
}