{
  "type": "Feature",
  "properties": {
    "iso:country":"CH",
    "sg:address":"Feldstrasse 14",
    "sg:city":"Urdorf",
    "sg:orig_category":"Aktivit\u00e4ten der Krankenschwestern U Hebammen, Hauspflege Organisationen des Gesundheitswesen",
    "sg:phone":"+41 17343330",
    "sg:postcode":"8902",
    "sg:province":"Z\u00fcrich",
    "wof:name":"Zentrum Spitex Kranken-& Hauspflege",
    "wof:placetype":"venue"
},
  "geometry": {"coordinates":[8.425515,47.390018],"type":"Point"}
}