{
  "type": "Feature",
  "properties": {
    "iso:country":"CH",
    "sg:address":"Avenue Muret 1",
    "sg:city":"Morges",
    "sg:orig_category":"Arztpraxen",
    "sg:phone":"+41 21 801 65 35",
    "sg:postcode":"1110",
    "sg:province":"Vaud",
    "wof:name":"Dr M\u00e9d. Martin Knizka M\u00e9decin Sp\u00e9cialiste Fmh",
    "wof:placetype":"venue"
},
  "geometry": {"coordinates":[6.503133,46.519199],"type":"Point"}
}