{
  "type": "Feature",
  "properties": {
    "iso:country":"CH",
    "sg:address":"Wilenstrasse 23",
    "sg:city":"Rickenbach",
    "sg:classifiers":[
        {
            "category":"Banks & Credit Unions",
            "subcategory":"Bank",
            "type":"Services"
        }
    ],
    "sg:phone":"+41 33 828 61 61",
    "sg:postcode":"9532",
    "sg:province":"Thurgau",
    "wof:name":"Raiffeisenbank Ringgenberg",
    "wof:placetype":"venue"
},
  "geometry": {"coordinates":[7.89547,46.701931],"type":"Point"}
}