{
  "type": "Feature",
  "properties": {
    "iso:country":"CH",
    "sg:address":"Landstrasse 31",
    "sg:city":"Seuzach",
    "sg:orig_category":"Fachdetailhandel in Verkaufsr\u00e4umen",
    "sg:phone":"+41 52 335 18 14",
    "sg:postcode":"8472",
    "sg:province":"Z\u00fcrich",
    "wof:name":"Oldamar Ag",
    "wof:placetype":"venue"
},
  "geometry": {"coordinates":[8.7327766418,47.5382728577],"type":"Point"}
}