{
  "type": "Feature",
  "properties": {
    "addr:full":"Breitistrasse Greifensee Z\u00fcrich 8606",
    "addr:postcode":"8606",
    "addr:street":"Breitistrasse",
    "iso:country":"CH",
    "sg:address":"Breitistrasse",
    "sg:city":"Greifensee",
    "sg:orig_category":"Bildung and Forschung, Museen",
    "sg:phone":"+41 4119055200",
    "sg:postcode":"8606",
    "sg:province":"Z\u00fcrich",
    "wof:name":"Diakonenhaus Greifensee",
    "wof:placetype":"venue"
},
  "geometry": {"coordinates":[8.677233,47.367397],"type":"Point"}
}