{
  "type": "Feature",
  "properties": {
    "iso:country":"CH",
    "sg:address":"Galeries Rue Des 3",
    "sg:city":"Hermance",
    "sg:orig_category":"Grosshandel mit Eisenwaren sowie Installationsbedarf f\u00fcr Gas, Wasser U Heizung",
    "sg:phone":"+41 79 626 77 07",
    "sg:postcode":"1248",
    "sg:province":"Gen\u00e8ve",
    "wof:name":"Pfortner Philippe",
    "wof:placetype":"venue"
},
  "geometry": {"coordinates":[6.2420620918,46.3024139404],"type":"Point"}
}