{
  "type": "Feature",
  "properties": {
    "iso:country":"CH",
    "sg:address":"Engelsteinstrasse 28",
    "sg:city":"B\u00e4retswil",
    "sg:orig_category":"Zimmerei, Dachdeckerei, Bauspenglerei U Abdichtung",
    "sg:postcode":"8344",
    "sg:province":"Z\u00fcrich",
    "wof:name":"Meyer Innenausbau",
    "wof:placetype":"venue"
},
  "geometry": {"coordinates":[8.8471975327,47.3402938843],"type":"Point"}
}