{
  "type": "Feature",
  "properties": {
    "iso:country":"CH",
    "sg:address":"1143",
    "sg:city":"Apples",
    "sg:orig_category":"Stukkateurgewerbe, Gipserei U Verputzerei",
    "sg:postcode":"1143",
    "sg:province":"Vaud",
    "wof:name":"Prera Philippe",
    "wof:placetype":"venue"
},
  "geometry": {"coordinates":[6.4290990829,46.5518035889],"type":"Point"}
}