{
  "type": "Feature",
  "properties": {
    "iso:country":"CH",
    "sg:address":"Z\u00fcrcherstrasse 91",
    "sg:city":"Basel",
    "sg:orig_category":"Elektroinstallation",
    "sg:phone":"+41 61 312 47 93",
    "sg:postcode":"4052",
    "sg:province":"Basel-Stadt",
    "wof:name":"Jungo U. Ag, Elektrische Installationen",
    "wof:placetype":"venue"
},
  "geometry": {"coordinates":[7.6107859612,47.5546340942],"type":"Point"}
}