{
  "type": "Feature",
  "properties": {
    "iso:country":"CH",
    "sg:address":"Leonhard Ragaz-weg 1 8055 Z\u00fcrich. Postfach 725",
    "sg:city":"Z\u00fcrich",
    "sg:orig_category":"Werbeagenturen",
    "sg:phone":"+41 14638050",
    "sg:postcode":"8055",
    "sg:province":"Z\u00fcrich",
    "wof:name":"Helen Fieramonte Werbeagentur",
    "wof:placetype":"venue"
},
  "geometry": {"coordinates":[8.5084848404,47.371055603],"type":"Point"}
}