{
  "type": "Feature",
  "properties": {
    "iso:country":"CH",
    "sg:address":"Hauptgasse 46",
    "sg:city":"Solothurn",
    "sg:orig_category":"Werbegrafikateliers",
    "sg:phone":"+41 313011",
    "sg:postcode":"4500",
    "sg:province":"Solothurn",
    "wof:name":"Ruth Levy Graphic-design",
    "wof:placetype":"venue"
},
  "geometry": {"coordinates":[8.6000099182,47.3237838745],"type":"Point"}
}