{
  "type": "Feature",
  "properties": {
    "iso:country":"CH",
    "sg:address":"Forchstrasse 59",
    "sg:city":"Z\u00fcrich",
    "sg:classifiers":[
        {
            "category":"Manufacturing",
            "subcategory":"Petroleum Products",
            "type":"Manufacturing & Wholesale Goods"
        }
    ],
    "sg:phone":"+41 22 300 50 20",
    "sg:postcode":"8032",
    "sg:province":"Z\u00fcrich",
    "sg:tags":[
        "low-noise",
        "asphalt"
    ],
    "wof:name":"Georges Dentan Gen\u00e8ve Sa",
    "wof:placetype":"venue"
},
  "geometry": {"coordinates":[6.141425,46.183311],"type":"Point"}
}