{
  "type": "Feature",
  "properties": {
    "iso:country":"CH",
    "sg:address":"Bahnhofstrasse",
    "sg:city":"W\u00fcnnewil",
    "sg:orig_category":"Herstellung von Arbeits U Berufsbekleidung",
    "sg:postcode":"3184",
    "sg:province":"Fribourg",
    "wof:name":"Tips Spicher X. & Pescador H.",
    "wof:placetype":"venue"
},
  "geometry": {"coordinates":[7.3207697868,46.8884506226],"type":"Point"}
}