{
  "type": "Feature",
  "properties": {
    "iso:country":"CH",
    "sg:address":"Stampfgasse 30 8750 Glarus. Postfach",
    "sg:city":"Glarus",
    "sg:orig_category":"Druck ohne Zeitungsdruck Offsetdruck",
    "sg:phone":"+41 55 640 19 30",
    "sg:postcode":"8750",
    "sg:province":"Glarus",
    "wof:name":"Sp\u00e4lti Druck Ag",
    "wof:placetype":"venue"
},
  "geometry": {"coordinates":[9.0691328049,47.0414047241],"type":"Point"}
}