{
  "type": "Feature",
  "properties": {
    "iso:country":"CH",
    "sg:address":"8600 D\u00fcbendorf. Postfach 511",
    "sg:city":"D\u00fcbendorf",
    "sg:classifiers":[
        {
            "category":"Arena",
            "subcategory":"Sports Club",
            "type":"Entertainment"
        }
    ],
    "sg:postcode":"8600",
    "sg:province":"Z\u00fcrich",
    "sg:tags":[
        "karate",
        "judo",
        "sportvereine"
    ],
    "wof:name":"Jjjc D\u00fcbendorf",
    "wof:placetype":"venue"
},
  "geometry": {"coordinates":[8.6222238541,47.3997840881],"type":"Point"}
}