{
  "type": "Feature",
  "properties": {
    "iso:country":"CH",
    "sg:address":"Cantonale Via 11",
    "sg:city":"Lugano",
    "sg:orig_category":"Herstellung von Werkzeugmaschinen",
    "sg:phone":"+41 91 922 77 76",
    "sg:postcode":"6900",
    "sg:province":"Ticino",
    "wof:name":"Salvagnini Nederland Bv, Oisterwijk, Succursale Di Lugano",
    "wof:placetype":"venue"
},
  "geometry": {"coordinates":[8.9500131607,46.007900238],"type":"Point"}
}