{
  "type": "Feature",
  "properties": {
    "iso:country":"CH",
    "sg:address":"Wegackerstrasse 6",
    "sg:city":"Z\u00fcrich",
    "sg:orig_category":"Unternehmensberatung",
    "sg:phone":"+41 26 411 21 44",
    "sg:postcode":"8041",
    "sg:province":"Z\u00fcrich",
    "wof:name":"Gagnaux Jacques Consulting S\u00e0rl Conseils En Gestion D'entreprise, En Gestion De Production Etc",
    "wof:placetype":"venue"
},
  "geometry": {"coordinates":[7.09953022,46.7241897583],"type":"Point"}
}