{
  "type": "Feature",
  "properties": {
    "iso:country":"CH",
    "sg:address":"Eichlistrasse 2",
    "sg:city":"Immensee",
    "sg:orig_category":"Grosshandel mit Nahrungsmitteln, Getr\u00e4nken U Tabakwaren ohne ausgepr\u00e4gten Schwerpunkt",
    "sg:phone":"+41 71 385 72 06",
    "sg:postcode":"6405",
    "sg:province":"Schwyz",
    "wof:name":"Scherrer Rolf Ag",
    "wof:placetype":"venue"
},
  "geometry": {"coordinates":[9.2610683441,47.4398078918],"type":"Point"}
}