{
  "type": "Feature",
  "properties": {
    "iso:country":"CH",
    "sg:address":"Via Cantonale 6",
    "sg:city":"Bedano",
    "sg:orig_category":"Fussboden, Fliesen U Plattenlegerei, Tapeziererei",
    "sg:postcode":"6930",
    "sg:province":"Ticino",
    "wof:name":"Volkart Plattenbel\u00e4ge",
    "wof:placetype":"venue"
},
  "geometry": {"coordinates":[9.8358440399,46.4932403564],"type":"Point"}
}