{
  "type": "Feature",
  "properties": {
    "iso:country":"CH",
    "sg:address":"Schweizeraustrasse 40",
    "sg:city":"Muttenz",
    "sg:orig_category":"Vereine Harmonika and Akkordeon",
    "sg:phone":"+41 61 731 36 33",
    "sg:postcode":"4132",
    "sg:province":"Basel-Landschaft",
    "wof:name":"Akkordeon-orchester Muttenz",
    "wof:placetype":"venue"
},
  "geometry": {"coordinates":[7.6295609474,47.5392303467],"type":"Point"}
}