{
  "type": "Feature",
  "properties": {
    "iso:country":"CH",
    "sg:address":"Emil Kl\u00f6ti-strasse 17",
    "sg:city":"Z\u00fcrich",
    "sg:orig_category":"Universit\u00e4tsspit\u00e4ler, Spit\u00e4ler f\u00fcr allgemeine Pflege",
    "sg:phone":"+41 12768040",
    "sg:postcode":"8037",
    "sg:province":"Z\u00fcrich",
    "wof:name":"Rheumabad K\u00e4ferberg",
    "wof:placetype":"venue"
},
  "geometry": {"coordinates":[8.5177316666,47.3994827271],"type":"Point"}
}