{
  "type": "Feature",
  "properties": {
    "iso:country":"CH",
    "sg:address":"Greischi",
    "sg:city":"Morschach",
    "sg:orig_category":"Haltung von Rindern",
    "sg:postcode":"6443",
    "sg:province":"Schwyz",
    "wof:name":"Viehzuchtgenossenschaft Morschach.",
    "wof:placetype":"venue"
},
  "geometry": {"coordinates":[8.6183691025,46.9815864563],"type":"Point"}
}