{
  "type": "Feature",
  "properties": {
    "iso:country":"CH",
    "sg:address":"Bahnhofstrasse 7",
    "sg:city":"Wattwil",
    "sg:orig_category":"Grosshandel mit B\u00fcromaschinen Grosshandel mit Datenverarbeitungsger\u00e4ten",
    "sg:phone":"+41 71 988 77 12",
    "sg:postcode":"9630",
    "sg:province":"St. Gallen",
    "wof:name":"Sunshine Computers Computerhandel Hardware Softw.",
    "wof:placetype":"venue"
},
  "geometry": {"coordinates":[9.0864391327,47.3009567261],"type":"Point"}
}