{
  "type": "Feature",
  "properties": {
    "iso:country":"CH",
    "sg:address":"Rebackerweg 32",
    "sg:city":"Lupsingen",
    "sg:orig_category":"Vermittlung von Immobilien Verwaltung von Immobilien",
    "sg:phone":"+41 21 321 12 80",
    "sg:postcode":"4419",
    "sg:province":"Basel-Landschaft",
    "wof:name":"Gerfidex",
    "wof:placetype":"venue"
},
  "geometry": {"coordinates":[6.6283040047,46.5226783752],"type":"Point"}
}