{
  "type": "Feature",
  "properties": {
    "iso:country":"CH",
    "sg:address":"Bernstr. 18",
    "sg:city":"Huttwil",
    "sg:classifiers":[
        {
            "category":"Food & Beverages",
            "subcategory":"Groceries & Convenience Stores",
            "type":"Retail Goods"
        }
    ],
    "sg:phone":"+41 62 959 83 83",
    "sg:postcode":"4950",
    "sg:province":"Bern",
    "sg:tags":[
        "product",
        "related"
    ],
    "wof:name":"Walter Leuenberger Ag",
    "wof:placetype":"venue"
},
  "geometry": {"coordinates":[7.8383197784,47.1132202148],"type":"Point"}
}