{
  "type": "Feature",
  "properties": {
    "iso:country":"CH",
    "sg:address":"Binzm\u00fchlestrasse 13",
    "sg:city":"Z\u00fcrich",
    "sg:orig_category":"Fernmeldedienste",
    "sg:phone":"+41 13053900",
    "sg:postcode":"8050",
    "sg:province":"Z\u00fcrich",
    "wof:name":"Teleglobe Switzerland Sa",
    "wof:placetype":"venue"
},
  "geometry": {"coordinates":[8.5484457016,47.4138221741],"type":"Point"}
}