{
  "type": "Feature",
  "properties": {
    "iso:country":"CH",
    "sg:address":"Teichweg 35",
    "sg:city":"Bubendorf",
    "sg:orig_category":"Museen",
    "sg:phone":"+41 61 931 39 51",
    "sg:postcode":"4416",
    "sg:province":"Basel-Landschaft",
    "wof:name":"Krippen-& Spielzeugmuseum Herrn Emil Wahl",
    "wof:placetype":"venue"
},
  "geometry": {"coordinates":[7.736468792,47.4487762451],"type":"Point"}
}