{
  "type": "Feature",
  "properties": {
    "addr:full":"Hauptstrasse 114 Wyssachen Bern 4954",
    "addr:housenumber":"114",
    "addr:postcode":"4954",
    "addr:street":"Hauptstrasse",
    "iso:country":"CH",
    "sg:address":"Hauptstrasse 114",
    "sg:city":"Wyssachen",
    "sg:orig_category":"Detailhandel mit Bekleidung Detailhandel mit Textilien",
    "sg:phone":"+41 81 302 41 00",
    "sg:postcode":"4954",
    "sg:province":"Bern",
    "wof:name":"Vreni Friberg Modehaus",
    "wof:placetype":"venue"
},
  "geometry": {"coordinates":[9.50123,47.003124],"type":"Point"}
}