{
  "type": "Feature",
  "properties": {
    "iso:country":"CH",
    "sg:address":"Via Saleggi 31 6600 Locarno Casella Postale 22",
    "sg:city":"Locarno",
    "sg:orig_category":"Herstellung von Datenverarbeitungsger\u00e4ten U einrichtungen Softwareentwicklung U beratung",
    "sg:phone":"+41 91 751 85 76",
    "sg:postcode":"6601",
    "sg:province":"Ticino",
    "wof:name":"Microtecna Engineering Sagl Hardware, Software, Componenti; Acquisto, Vendita Ecc",
    "wof:placetype":"venue"
},
  "geometry": {"coordinates":[8.8003940582,46.1705741882],"type":"Point"}
}