{
  "type": "Feature",
  "properties": {
    "iso:country":"CH",
    "sg:address":"Gartenstrasse 6",
    "sg:city":"Dachsen",
    "sg:classifiers":[
        {
            "category":"Insurance",
            "subcategory":"Insurance Agent",
            "type":"Services"
        }
    ],
    "sg:phone":"+41 52 659 62 87",
    "sg:postcode":"8447",
    "sg:province":"Z\u00fcrich",
    "sg:tags":[
        "versicherungsagenturen",
        "-broker"
    ],
    "wof:name":"Koni Eggli Versicherungen",
    "wof:placetype":"venue"
},
  "geometry": {"coordinates":[8.6178445816,47.6639823914],"type":"Point"}
}