{
  "type": "Feature",
  "properties": {
    "iso:country":"CH",
    "sg:address":"Route De La-capite 45 1223 Cologny Case Postale 71",
    "sg:city":"Cologny",
    "sg:orig_category":"Unternehmensberatung",
    "sg:phone":"+41 22 310 81 11",
    "sg:postcode":"1223",
    "sg:province":"Gen\u00e8ve",
    "wof:name":"Nelmar Sa",
    "wof:placetype":"venue"
},
  "geometry": {"coordinates":[6.1839089394,46.2185783386],"type":"Point"}
}