{
  "type": "Feature",
  "properties": {
    "iso:country":"CH",
    "sg:address":"Hauptbahnhofstrasse 1",
    "sg:city":"Solothurn",
    "sg:orig_category":"RESTAURANTS: TEA-ROOMS",
    "sg:phone":"+41 32 621 44 65",
    "sg:postcode":"4500",
    "sg:province":"Solothurn",
    "wof:name":"Metro Pizza Veronica",
    "wof:placetype":"venue"
},
  "geometry": {"coordinates":[7.5404801369,47.2053108215],"type":"Point"}
}