{
  "type": "Feature",
  "properties": {
    "iso:country":"CH",
    "sg:address":"Schweizer Fernsehen Drs",
    "sg:city":"Z\u00fcrich",
    "sg:orig_category":"Sportvereine Ballsport Tennis",
    "sg:phone":"+41 19405140",
    "sg:postcode":"8052",
    "sg:province":"Z\u00fcrich",
    "wof:name":"Tc Fernsehen/radio",
    "wof:placetype":"venue"
},
  "geometry": {"coordinates":[8.5387096405,47.4295196533],"type":"Point"}
}