{
  "type": "Feature",
  "properties": {
    "addr:full":"Schoneggstrasse 21 Spiez Bern 3700",
    "addr:housenumber":"21",
    "addr:postcode":"3700",
    "addr:street":"Schoneggstrasse",
    "iso:country":"CH",
    "sg:address":"Schoneggstrasse 21",
    "sg:city":"Spiez",
    "sg:orig_category":"Arztpraxen",
    "sg:phone":"+41 33 655 05 05",
    "sg:postcode":"3700",
    "sg:province":"Bern",
    "wof:name":"Dr.med.hanspeter B\u00f6ss Spezialarzt Fmh",
    "wof:placetype":"venue"
},
  "geometry": {"coordinates":[7.684461,46.685627],"type":"Point"}
}