{
  "type": "Feature",
  "properties": {
    "iso:country":"CH",
    "sg:address":"Rue De Carouge 93",
    "sg:city":"Gen\u00e8ve",
    "sg:classifiers":[
        {
            "category":"Restaurant",
            "type":"Food & Drink"
        }
    ],
    "sg:phone":"+41 22 781 50 48",
    "sg:postcode":"1205",
    "sg:province":"Gen\u00e8ve",
    "wof:name":"Bar \u00e0 Caf\u00e9 Le Renvers\u00e9",
    "wof:placetype":"venue"
},
  "geometry": {"coordinates":[6.1432189941,46.1886787415],"type":"Point"}
}