{
  "type": "Feature",
  "properties": {
    "iso:country":"CH",
    "sg:address":"Avenue C.-f.-ramuz 43 1009 Pully. Postfach",
    "sg:city":"Pully",
    "sg:orig_category":"Herstellung von sonstigen Maschinen f\u00fcr unspezifische Verwendung Mechanische Werkst\u00e4tten",
    "sg:phone":"+41 21 721 11 61",
    "sg:postcode":"1009",
    "sg:province":"Vaud",
    "wof:name":"Aprel Automation & Processus Industriels Sa",
    "wof:placetype":"venue"
},
  "geometry": {"coordinates":[6.6502709389,46.509552002],"type":"Point"}
}