{
  "type": "Feature",
  "properties": {
    "iso:country":"CH",
    "sg:address":"Kriegstettenstrasse 5",
    "sg:city":"Gerlafingen",
    "sg:orig_category":"Detailhandel mit Waren verschiedener Art, Hauptrichtung Nahrungsmittel Grosshandel mit Nahrungsmitte",
    "sg:phone":"+41 32 675 69 33",
    "sg:postcode":"4563",
    "sg:province":"Solothurn",
    "wof:name":"Siragusa & Co Fr\u00fcchte & Gem\u00fcse",
    "wof:placetype":"venue"
},
  "geometry": {"coordinates":[7.5736498833,47.170879364],"type":"Point"}
}