{
  "type": "Feature",
  "properties": {
    "iso:country":"CH",
    "sg:address":"Schw\u00e4bisgasse 1",
    "sg:city":"Thun",
    "sg:orig_category":"RESTAURANTS: TEA-ROOMS",
    "sg:phone":"+41 33 225 03 10",
    "sg:postcode":"3600",
    "sg:province":"Bern",
    "wof:name":"Restaurant Turm Gmbh",
    "wof:placetype":"venue"
},
  "geometry": {"coordinates":[7.6269178391,46.7607536316],"type":"Point"}
}