{
  "type": "Feature",
  "properties": {
    "iso:country":"CH",
    "sg:address":"Avenue De Rumine 40",
    "sg:city":"Lausanne",
    "sg:classifiers":[
        {
            "category":"Insurance",
            "subcategory":"Insurance Agent",
            "type":"Services"
        }
    ],
    "sg:phone":"+41 21 323 47 41",
    "sg:postcode":"1005",
    "sg:province":"Vaud",
    "sg:tags":[
        "versicherungsagenturen",
        "-broker"
    ],
    "wof:name":"Valentine Albion Leu Bureau D'assurances",
    "wof:placetype":"venue"
},
  "geometry": {"coordinates":[6.6427798271,46.5158081055],"type":"Point"}
}