{
  "type": "Feature",
  "properties": {
    "addr:full":"Rue Chantrepoulet 25 Gen\u00e8ve Gen\u00e8ve 1211",
    "addr:housenumber":"25",
    "addr:postcode":"1211",
    "addr:street":"Rue Chantrepoulet",
    "iso:country":"CH",
    "sg:address":"Rue Chantrepoulet 25",
    "sg:city":"Gen\u00e8ve",
    "sg:classifiers":[
        {
            "category":"Banks & Credit Unions",
            "subcategory":"Bank",
            "type":"Services"
        }
    ],
    "sg:phone":"+41 22 732 22 00",
    "sg:postcode":"1211",
    "sg:province":"Gen\u00e8ve",
    "wof:name":"Commerzbank Ag",
    "wof:placetype":"venue"
},
  "geometry": {"coordinates":[6.13993,46.203819],"type":"Point"}
}