{
  "type": "Feature",
  "properties": {
    "addr:full":"M\u00fchlegasse 29 Z\u00fcrich Z\u00fcrich 8001",
    "addr:housenumber":"29",
    "addr:postcode":"8001",
    "addr:street":"Muehlegasse",
    "iso:country":"CH",
    "sg:address":"M\u00fchlegasse 29",
    "sg:city":"Z\u00fcrich",
    "sg:orig_category":"Detailhandel mit Computern U Software Sonstiger Grosshandel",
    "sg:phone":"+41 800 300 900",
    "sg:postcode":"8001",
    "sg:province":"Z\u00fcrich",
    "wof:name":"Portable Shop Z\u00fcrich Mobile Computer",
    "wof:placetype":"venue"
},
  "geometry": {"coordinates":[8.54525,47.374603],"type":"Point"}
}