{
  "type": "Feature",
  "properties": {
    "iso:country":"CH",
    "sg:address":"Franscini Viale 40 6900 Lugano. Postfach",
    "sg:city":"Lugano",
    "sg:orig_category":"Technische, physikalische U chemische Untersuchung",
    "sg:postcode":"6900",
    "sg:province":"Ticino",
    "wof:name":"Swisstest Sa Procedimenti E Metodi Tecnici Di Collaudo, Controllo Ed Ispezione Di Materiali Ecc",
    "wof:placetype":"venue"
},
  "geometry": {"coordinates":[8.9548912048,46.0112876892],"type":"Point"}
}