{
  "type": "Feature",
  "properties": {
    "iso:country":"CH",
    "sg:address":"Steinhauserstrasse 70",
    "sg:city":"Zug",
    "sg:orig_category":"Dienstleistungen von Beteiligungsgesellschaften",
    "sg:phone":"+41 41 749 66 11",
    "sg:postcode":"6300",
    "sg:province":"Zug",
    "wof:name":"Bossard International Ag",
    "wof:placetype":"venue"
},
  "geometry": {"coordinates":[8.4942007065,47.186164856],"type":"Point"}
}