{
  "type": "Feature",
  "properties": {
    "iso:country":"CH",
    "sg:address":"H\u00e4gelerstrasse 30",
    "sg:city":"Baden",
    "sg:orig_category":"Sportvereine Turnen Vereine Damen",
    "sg:phone":"+41 56 222 22 34",
    "sg:postcode":"5400",
    "sg:province":"Aargau",
    "wof:name":"Frauen-& Turngruppe Baden",
    "wof:placetype":"venue"
},
  "geometry": {"coordinates":[8.2948617935,47.475025177],"type":"Point"}
}