{
  "type": "Feature",
  "properties": {
    "iso:country":"CH",
    "sg:address":"Roule Route Du 45",
    "sg:city":"Marly",
    "sg:orig_category":"Fachdetailhandel in Verkaufsr\u00e4umen",
    "sg:phone":"+41 32972354",
    "sg:postcode":"1723",
    "sg:province":"Fribourg",
    "wof:name":"Duilio Disler",
    "wof:placetype":"venue"
},
  "geometry": {"coordinates":[7.1608052254,46.7766113281],"type":"Point"}
}