{
  "type": "Feature",
  "properties": {
    "iso:country":"CH",
    "sg:address":"Nessi Via Angelo 38b",
    "sg:city":"Locarno",
    "sg:orig_category":"Verwaltung von Immobilien",
    "sg:postcode":"6600",
    "sg:province":"Ticino",
    "wof:name":"Aliresto S\u00e0rl",
    "wof:placetype":"venue"
},
  "geometry": {"coordinates":[6.5128378868,46.6583976746],"type":"Point"}
}