{
  "type": "Feature",
  "properties": {
    "iso:country":"CH",
    "sg:address":"Furkastrasse 25 3904 Naters. Postfach",
    "sg:city":"Naters",
    "sg:orig_category":"HERSTELLUNG VON GER\u00c4TEN DER ELEKTRIZIT\u00c4TSERZEUGUNG, -VERTEILUNG U.\u00c4 Herstellung von k\u00e4lte U lufttech",
    "sg:phone":"+41 56 243 14 32",
    "sg:postcode":"3904",
    "sg:province":"Valais",
    "wof:name":"Tanner Ag Induktionsw\u00e4rme & Prozessk\u00fchlsysteme",
    "wof:placetype":"venue"
},
  "geometry": {"coordinates":[8.3787078857,47.5648193359],"type":"Point"}
}