{
  "type": "Feature",
  "properties": {
    "iso:country":"CH",
    "sg:address":"Rue Du Mont-blanc 5",
    "sg:city":"Gen\u00e8ve",
    "sg:orig_category":"Luftfahrt",
    "sg:phone":"+41 22 731 53 34",
    "sg:postcode":"1201",
    "sg:province":"Gen\u00e8ve",
    "wof:name":"Tunisair",
    "wof:placetype":"venue"
},
  "geometry": {"coordinates":[6.1465139389,46.2074241638],"type":"Point"}
}