{
  "type": "Feature",
  "properties": {
    "iso:country":"CH",
    "sg:address":"Mittlerer Kreis 35",
    "sg:city":"Therwil",
    "sg:orig_category":"Innendekorationsateliers",
    "sg:phone":"+41 61 721 66 60",
    "sg:postcode":"4106",
    "sg:province":"Basel-Landschaft",
    "wof:name":"Roland Gschwind Innendekorationen",
    "wof:placetype":"venue"
},
  "geometry": {"coordinates":[7.551856041,47.497718811],"type":"Point"}
}