{
  "type": "Feature",
  "properties": {
    "iso:country":"CH",
    "sg:address":"Suleggstrasse 4",
    "sg:city":"Interlaken",
    "sg:orig_category":"Kauf U Verkauf von Immobilien auf eigene Rechnung",
    "sg:postcode":"3800",
    "sg:province":"Bern",
    "wof:name":"Hutmac-ag",
    "wof:placetype":"venue"
},
  "geometry": {"coordinates":[7.8540010452,46.6813468933],"type":"Point"}
}