{
  "type": "Feature",
  "properties": {
    "iso:country":"CH",
    "sg:address":"Regensdorferstrasse 160 8049 Z\u00fcrich. Postfach",
    "sg:city":"Z\u00fcrich",
    "sg:orig_category":"Unclassifiable Establishments",
    "sg:phone":"+41 13416222",
    "sg:postcode":"8049",
    "sg:province":"Z\u00fcrich",
    "wof:name":"Haussener Consulting B\u00fcro Z\u00fcrich",
    "wof:placetype":"venue"
},
  "geometry": {"coordinates":[8.486536026,47.4103736877],"type":"Point"}
}