{
  "type": "Feature",
  "properties": {
    "iso:country":"CH",
    "sg:address":"Helvetiaplatz 6",
    "sg:city":"Bern",
    "sg:orig_category":"Religi\u00f6se Vereinigungen divers",
    "sg:phone":"+41 31 351 01 21",
    "sg:postcode":"3005",
    "sg:province":"Bern",
    "wof:name":"First Church Of Christ Scientist,bern",
    "wof:placetype":"venue"
},
  "geometry": {"coordinates":[7.4480509758,46.9437828064],"type":"Point"}
}