{
  "type": "Feature",
  "properties": {
    "iso:country":"CH",
    "sg:address":"Schulgasse",
    "sg:city":"Wegenstetten",
    "sg:orig_category":"Vorschulen, Kinderg\u00e4rten",
    "sg:postcode":"4317",
    "sg:province":"Aargau",
    "wof:name":"Kindergarten Schulhaus",
    "wof:placetype":"venue"
},
  "geometry": {"coordinates":[7.9338412285,47.4989814758],"type":"Point"}
}