{
  "type": "Feature",
  "properties": {
    "iso:country":"CH",
    "sg:address":"Bahnhofstrasse 21",
    "sg:city":"Thalwil",
    "sg:orig_category":"RESTAURANTS: TEA-ROOMS",
    "sg:postcode":"8800",
    "sg:province":"Z\u00fcrich",
    "wof:name":"Mega Imbiss Gmbh",
    "wof:placetype":"venue"
},
  "geometry": {"coordinates":[8.5647592545,47.296081543],"type":"Point"}
}