{
  "type": "Feature",
  "properties": {
    "iso:country":"CH",
    "sg:address":"Zollikerstrasse 226 8000 Z\u00fcrich. Postfach 53",
    "sg:city":"Z\u00fcrich",
    "sg:orig_category":"Sonstiger Fachdetailhandel in Verkaufsr\u00e4umen",
    "sg:phone":"+41 13899191",
    "sg:postcode":"8008",
    "sg:province":"Z\u00fcrich",
    "wof:name":"Corinphila Auktionen Ag Briefmarken, -sammlungen; An, Verkauf, Bes. Bei Auktionen",
    "wof:placetype":"venue"
},
  "geometry": {"coordinates":[8.5652885437,47.3485412598],"type":"Point"}
}