{
  "type": "Feature",
  "properties": {
    "iso:country":"CH",
    "sg:address":"8574",
    "sg:city":"Lengwil-oberhofen",
    "sg:orig_category":"Pensionskassen",
    "sg:postcode":"8574",
    "sg:province":"Thurgau",
    "wof:name":"F\u00fcrsorgestiftung Der Hoch- U. Tiefbau Bertet Und Marti Ag",
    "wof:placetype":"venue"
},
  "geometry": {"coordinates":[9.1937198639,47.6241111755],"type":"Point"}
}