{
  "type": "Feature",
  "properties": {
    "iso:country":"CH",
    "sg:address":"Bahnhofstrasse 15 6430 Schwyz. Postfach 321",
    "sg:city":"Schwyz",
    "sg:orig_category":"Arbeits\u00e4mter",
    "sg:phone":"+41 41 819 11 24",
    "sg:postcode":"6431",
    "sg:province":"Schwyz",
    "wof:name":"Kant. Arbeitsinspektorat",
    "wof:placetype":"venue"
},
  "geometry": {"coordinates":[8.649298,47.021427],"type":"Point"}
}