{
  "type": "Feature",
  "properties": {
    "iso:country":"CH",
    "sg:address":"Luzernerstrasse 19 6030 Ebikon. Postfach 351",
    "sg:city":"Ebikon",
    "sg:orig_category":"Grosshandel mit Eisenwaren sowie Installationsbedarf f\u00fcr Gas, Wasser U Heizung Sanit\u00e4r, Heizungs U L",
    "sg:phone":"+41 41 444 33 99",
    "sg:postcode":"6031",
    "sg:province":"Luzern",
    "wof:name":"Schaco Ag",
    "wof:placetype":"venue"
},
  "geometry": {"coordinates":[8.3342533112,47.0774269104],"type":"Point"}
}