{
  "type": "Feature",
  "properties": {
    "iso:country":"CH",
    "sg:address":"Kreuzplatz 2",
    "sg:city":"Thayngen",
    "sg:orig_category":"RESTAURANTS: TEA-ROOMS",
    "sg:postcode":"8240",
    "sg:province":"Schaffhausen",
    "wof:name":"Tschudin Bruno",
    "wof:placetype":"venue"
},
  "geometry": {"coordinates":[8.7076416016,47.7472457886],"type":"Point"}
}