{
  "type": "Feature",
  "properties": {
    "iso:country":"CH",
    "sg:address":"Sagenstrasse",
    "sg:city":"Ebikon",
    "sg:orig_category":"Vorschulen, Kinderg\u00e4rten",
    "sg:phone":"+41 41 440 74 13",
    "sg:postcode":"6030",
    "sg:province":"Luzern",
    "wof:name":"Kindergarten Sagen",
    "wof:placetype":"venue"
},
  "geometry": {"coordinates":[8.3414506912,47.0775604248],"type":"Point"}
}