{
  "type": "Feature",
  "properties": {
    "iso:country":"CH",
    "sg:address":"Ober Emmenweid 46 6020 Emmenbr\u00fccke. Postfach",
    "sg:city":"Emmenbr\u00fccke",
    "sg:orig_category":"Kauf U Verkauf von Immobilien auf eigene Rechnung",
    "sg:postcode":"6020",
    "sg:province":"Luzern",
    "wof:name":"Advopark Ag",
    "wof:placetype":"venue"
},
  "geometry": {"coordinates":[8.2659778595,47.0738677979],"type":"Point"}
}