{
  "type": "Feature",
  "properties": {
    "iso:country":"CH",
    "sg:address":"Lochriet 8890 Flums. Postfach",
    "sg:city":"Flums",
    "sg:orig_category":"Herstellung von Metallkonstruktionen",
    "sg:postcode":"8890",
    "sg:province":"St. Gallen",
    "wof:name":"Wiga-tec Gmbh",
    "wof:placetype":"venue"
},
  "geometry": {"coordinates":[9.3509302139,47.0996437073],"type":"Point"}
}