{
  "type": "Feature",
  "properties": {
    "iso:country":"CH",
    "sg:address":"Kirchgass 12",
    "sg:city":"Berneck",
    "sg:orig_category":"Rolladen- and Storenmontage",
    "sg:phone":"+41 71 744 50 72",
    "sg:postcode":"9442",
    "sg:province":"St. Gallen",
    "wof:name":"Oswald Tobler Storen Und Rollladen",
    "wof:placetype":"venue"
},
  "geometry": {"coordinates":[9.6131000519,47.4244194031],"type":"Point"}
}