{
  "type": "Feature",
  "properties": {
    "iso:country":"CH",
    "sg:address":"Place Du Port 1",
    "sg:city":"Gen\u00e8ve",
    "sg:orig_category":"Zahnarztpraxen",
    "sg:phone":"+41 32 731 23 55",
    "sg:postcode":"1204",
    "sg:province":"Gen\u00e8ve",
    "wof:name":"Dr M\u00e9d.dent. Marc-a. Kaufmann M\u00e9decin-dentiste",
    "wof:placetype":"venue"
},
  "geometry": {"coordinates":[6.8845658302,46.9837188721],"type":"Point"}
}