{
  "type": "Feature",
  "properties": {
    "iso:country":"CH",
    "sg:address":"Portone Viale 4",
    "sg:city":"Bellinzona",
    "sg:orig_category":"Abwasserreinigung, Abfallbeseitigung U sonstige Entsorgung",
    "sg:phone":"+41 22 308 46 00",
    "sg:postcode":"6500",
    "sg:province":"Ticino",
    "wof:name":"Sogetri Sa",
    "wof:placetype":"venue"
},
  "geometry": {"coordinates":[6.141425,46.183311],"type":"Point"}
}