{
  "type": "Feature",
  "properties": {
    "iso:country":"CH",
    "sg:address":"Holzgasse 13a",
    "sg:city":"Wiedlisbach",
    "sg:orig_category":"Malerei-Gipserei Verarbeitung U Veredlung von Flachglas",
    "sg:phone":"+41 79 432 07 33",
    "sg:postcode":"4537",
    "sg:province":"Bern",
    "wof:name":"Duma Glas, Doudin & Nyfeler",
    "wof:placetype":"venue"
},
  "geometry": {"coordinates":[7.6518278122,47.2506103516],"type":"Point"}
}