{
  "type": "Feature",
  "properties": {
    "iso:country":"CH",
    "sg:address":"Thunstrasse 3",
    "sg:city":"Uetendorf",
    "sg:orig_category":"Elektroinstallation",
    "sg:phone":"+41 33 345 19 52",
    "sg:postcode":"3661",
    "sg:province":"Bern",
    "wof:name":"J\u00fcrg Gertsch Elektro-installationen",
    "wof:placetype":"venue"
},
  "geometry": {"coordinates":[7.5804228783,46.771270752],"type":"Point"}
}