{
  "type": "Feature",
  "properties": {
    "iso:country":"CH",
    "sg:address":"Sonnenhalde 9",
    "sg:city":"Schwerzenbach",
    "sg:classifiers":[
        {
            "category":"Insurance",
            "subcategory":"Insurance Agent",
            "type":"Services"
        }
    ],
    "sg:phone":"+41 18253750",
    "sg:postcode":"8603",
    "sg:province":"Z\u00fcrich",
    "sg:tags":[
        "versicherungsagenturen",
        "-broker"
    ],
    "wof:name":"Fredy Gross Versicherungen",
    "wof:placetype":"venue"
},
  "geometry": {"coordinates":[8.6502943039,47.3819236755],"type":"Point"}
}