{
  "type": "Feature",
  "properties": {
    "iso:country":"CH",
    "sg:address":"Gotthardstrasse 88",
    "sg:city":"Amsteg",
    "sg:classifiers":[
        {
            "category":"Travel",
            "subcategory":"Hotels & Motels",
            "type":"Entertainment"
        }
    ],
    "sg:phone":"+41 41 883 14 40",
    "sg:postcode":"6474",
    "sg:province":"Uri",
    "sg:tags":[
        "hotels",
        "mit",
        "restaurant"
    ],
    "wof:name":"Hotel Stern & Post",
    "wof:placetype":"venue"
},
  "geometry": {"coordinates":[8.6712627411,46.769317627],"type":"Point"}
}