{
  "type": "Feature",
  "properties": {
    "iso:country":"CH",
    "sg:address":"Avenue De France 90 1004 Lausanne. Postfach",
    "sg:city":"Lausanne",
    "sg:orig_category":"Fernmeldedienste",
    "sg:phone":"+41 21 646 34 36",
    "sg:postcode":"1003",
    "sg:province":"Vaud",
    "wof:name":"Global Call Concept S\u00e0rl Produits Dans Le Dom. Des T\u00e9l\u00e9communications, Etc.; Promotion Et Vente",
    "wof:placetype":"venue"
},
  "geometry": {"coordinates":[6.6154470444,46.5318565369],"type":"Point"}
}