{
  "type": "Feature",
  "properties": {
    "iso:country":"CH",
    "sg:address":"Lausenerstrasse 22",
    "sg:city":"Liestal",
    "sg:orig_category":"Architektur U Ingenieurb\u00fcros Architekturb\u00fcros",
    "sg:phone":"+41 32 677 22 41",
    "sg:postcode":"4410",
    "sg:province":"Basel-Landschaft",
    "wof:name":"Bauraum Ren\u00e9 Marti Lebensenergie & Architektur",
    "wof:placetype":"venue"
},
  "geometry": {"coordinates":[7.524811,47.169815],"type":"Point"}
}