{
  "type": "Feature",
  "properties": {
    "iso:country":"CH",
    "sg:address":"Rietstrasse 31",
    "sg:city":"Zollikon",
    "sg:orig_category":"Softwareentwicklung U beratung",
    "sg:phone":"+41 13083615",
    "sg:postcode":"8702",
    "sg:province":"Z\u00fcrich",
    "wof:name":"Tooltech Software Ag",
    "wof:placetype":"venue"
},
  "geometry": {"coordinates":[8.5761632919,47.3441162109],"type":"Point"}
}