{
  "type": "Feature",
  "properties": {
    "iso:country":"CH",
    "sg:address":"Valleures",
    "sg:city":"Noville",
    "sg:orig_category":"Herstellung von Metallkonstruktionen Installation von Heizungs, L\u00fcftungs U Klimaanlagen",
    "sg:phone":"+41 21 960 19 48",
    "sg:postcode":"1845",
    "sg:province":"Vaud",
    "wof:name":"Chaperon Philippe Et Cie",
    "wof:placetype":"venue"
},
  "geometry": {"coordinates":[6.8991661072,46.381565094],"type":"Point"}
}