{
  "type": "Feature",
  "properties": {
    "iso:country":"CH",
    "sg:address":"Via San Giobbe 4",
    "sg:city":"Giubiasco",
    "sg:orig_category":"Bauingenieurb\u00fcros allgemein",
    "sg:phone":"+41 76 320 10 58",
    "sg:postcode":"6512",
    "sg:province":"Ticino",
    "wof:name":"Enrico Spiesberger Studio D'ingegneria",
    "wof:placetype":"venue"
},
  "geometry": {"coordinates":[9.008736,46.172863],"type":"Point"}
}