{
  "type": "Feature",
  "properties": {
    "iso:country":"CH",
    "sg:address":"Hofjistrasse 4",
    "sg:city":"Brig",
    "sg:orig_category":"Arztpraxen",
    "sg:phone":"+41 27 923 11 35",
    "sg:postcode":"3900",
    "sg:province":"Valais",
    "wof:name":"Dr.med.erwin Willa Arzt F.allgemeine Medizin Fmh",
    "wof:placetype":"venue"
},
  "geometry": {"coordinates":[7.991285,46.315483],"type":"Point"}
}