{
  "type": "Feature",
  "properties": {
    "addr:full":"Blauenstrasse 3 M\u00fcnchenstein Basel-Landschaft 4142",
    "addr:housenumber":"3",
    "addr:postcode":"4142",
    "addr:street":"Blauenstrasse",
    "iso:country":"CH",
    "sg:address":"Blauenstrasse 3",
    "sg:city":"M\u00fcnchenstein",
    "sg:orig_category":"Bauschreinerei Herstellung von Konstruktionsteilen, Fertigbauteilen U Ausbauelementen aus Holz",
    "sg:phone":"+41 61 411 08 38",
    "sg:postcode":"4142",
    "sg:province":"Basel-Landschaft",
    "wof:name":"Schreinerei Ringli Ag",
    "wof:placetype":"venue"
},
  "geometry": {"coordinates":[7.618451,47.51115],"type":"Point"}
}