{
  "type": "Feature",
  "properties": {
    "iso:country":"CH",
    "sg:address":"Cully Route De 1091 Grandvaux. Postfach",
    "sg:city":"Grandvaux",
    "sg:orig_category":"Grosshandel mit Getr\u00e4nken",
    "sg:postcode":"1091",
    "sg:province":"Vaud",
    "wof:name":"Vitis Vinifera Sa",
    "wof:placetype":"venue"
},
  "geometry": {"coordinates":[6.7161297798,46.4935798645],"type":"Point"}
}