{
  "type": "Feature",
  "properties": {
    "iso:country":"CH",
    "sg:address":"Bergacher 14 3325 Hettiswil. Postfach",
    "sg:city":"Hettiswil",
    "sg:orig_category":"Sonstige pers\u00f6nliche Dienstleistungen",
    "sg:phone":"+41 21 973 11 01",
    "sg:postcode":"3325",
    "sg:province":"Bern",
    "wof:name":"Sogeni Sa",
    "wof:placetype":"venue"
},
  "geometry": {"coordinates":[6.8761329651,46.4478721619],"type":"Point"}
}