{
  "type": "Feature",
  "properties": {
    "iso:country":"CH",
    "sg:address":"6593",
    "sg:city":"Cadenazzo",
    "sg:orig_category":"Blumen U Zierpflanzenbau Gem\u00fcsebau",
    "sg:phone":"+41 71 951 87 15",
    "sg:postcode":"6593",
    "sg:province":"Ticino",
    "wof:name":"Blumen Seydel Ag",
    "wof:placetype":"venue"
},
  "geometry": {"coordinates":[9.132955,47.437145],"type":"Point"}
}