{
  "type": "Feature",
  "properties": {
    "iso:country":"CH",
    "sg:address":"Krummeneichstr. 60",
    "sg:city":"Pratteln",
    "sg:classifiers":[
        {
            "category":"Professional",
            "type":"Services"
        }
    ],
    "sg:phone":"+41 61 821 89 67",
    "sg:postcode":"4133",
    "sg:province":"Basel-Landschaft",
    "sg:tags":[
        "transport",
        "road"
    ],
    "wof:name":"Bruno Burgener",
    "wof:placetype":"venue"
},
  "geometry": {"coordinates":[7.7103281021,47.5230674744],"type":"Point"}
}