{
  "type": "Feature",
  "properties": {
    "iso:country":"CH",
    "sg:address":"Via Emilio Bossi 4 6830 Chiasso. Postfach",
    "sg:city":"Lugano",
    "sg:orig_category":"Mit dem Versicherungsgewerbe verbundene T\u00e4tigkeiten Steuerberatung",
    "sg:phone":"+41 91 690 11 97",
    "sg:postcode":"6900",
    "sg:province":"Ticino",
    "wof:name":"Hera Swiss Consulting Sagl Consulenza Assicurativa E Finanziaria Ecc",
    "wof:placetype":"venue"
},
  "geometry": {"coordinates":[9.0310878754,45.8338317871],"type":"Point"}
}