{
  "type": "Feature",
  "properties": {
    "iso:country":"CH",
    "sg:address":"Obere Bahnhofstrasse",
    "sg:city":"Zermatt",
    "sg:classifiers":[
        {
            "category":"Bars & Pubs",
            "type":"Food & Drink"
        }
    ],
    "sg:phone":"+41 27 967 21 00",
    "sg:postcode":"3920",
    "sg:province":"Valais",
    "wof:name":"Little-bar",
    "wof:placetype":"venue"
},
  "geometry": {"coordinates":[7.74624,46.020145],"type":"Point"}
}