{
  "type": "Feature",
  "properties": {
    "iso:country":"CH",
    "sg:address":"Via Ceresio 57 6963 Pregassona. Postfach",
    "sg:city":"Pregassona",
    "sg:orig_category":"Maler U Glasergewerbe",
    "sg:postcode":"6963",
    "sg:province":"Ticino",
    "wof:name":"Arcobaleno Impresa Di Pittura Sagl",
    "wof:placetype":"venue"
},
  "geometry": {"coordinates":[8.9678058624,46.0233573914],"type":"Point"}
}