{
  "type": "Feature",
  "properties": {
    "iso:country":"CH",
    "sg:address":"Nesslerenweg 82",
    "sg:city":"K\u00f6niz",
    "sg:orig_category":"Handel mit Automobilen",
    "sg:postcode":"3098",
    "sg:province":"Bern",
    "wof:name":"Carimpex Kujundzic Karlo",
    "wof:placetype":"venue"
},
  "geometry": {"coordinates":[7.4647598267,46.9205207825],"type":"Point"}
}