{
  "type": "Feature",
  "properties": {
    "iso:country":"CH",
    "sg:address":"Luzernstrasse 11",
    "sg:city":"Huttwil",
    "sg:orig_category":"Herstellung von gewirktem U gestricktem Stoff",
    "sg:phone":"+41 62 959 70 70",
    "sg:postcode":"4950",
    "sg:province":"Bern",
    "wof:name":"Textil Ag Huttwil",
    "wof:placetype":"venue"
},
  "geometry": {"coordinates":[7.8518509865,47.1135406494],"type":"Point"}
}