{
  "type": "Feature",
  "properties": {
    "addr:full":"R\u00fcchligstrasse 21 Obfelden Z\u00fcrich 8912",
    "addr:housenumber":"21",
    "addr:postcode":"8912",
    "addr:street":"Ruechligstrasse",
    "iso:country":"CH",
    "sg:address":"R\u00fcchligstrasse 21",
    "sg:city":"Obfelden",
    "sg:orig_category":"Datenverarbeitungsdienste Informatikschulen",
    "sg:phone":"+41 18883215",
    "sg:postcode":"8912",
    "sg:province":"Z\u00fcrich",
    "wof:name":"Gabriella Ronchi Schulung Beratung Support",
    "wof:placetype":"venue"
},
  "geometry": {"coordinates":[8.426314,47.263309],"type":"Point"}
}