{
  "type": "Feature",
  "properties": {
    "iso:country":"CH",
    "sg:address":"Hinterburgstrasse 24",
    "sg:city":"Berneck",
    "sg:orig_category":"Dauerkulturbau",
    "sg:postcode":"9442",
    "sg:province":"St. Gallen",
    "wof:name":"Schmutz A. & Fils Sa Vignes, Vinification. Vins Etc.; Commerce",
    "wof:placetype":"venue"
},
  "geometry": {"coordinates":[7.098061,46.953068],"type":"Point"}
}