{
  "type": "Feature",
  "properties": {
    "iso:country":"CH",
    "sg:address":"8603",
    "sg:city":"Schwerzenbach",
    "sg:orig_category":"Schulpflegen",
    "sg:phone":"+41 18255200",
    "sg:postcode":"8603",
    "sg:province":"Z\u00fcrich",
    "wof:name":"Schulpflege Der Gemeinde Schwerzenbach",
    "wof:placetype":"venue"
},
  "geometry": {"coordinates":[8.6575098038,47.3808097839],"type":"Point"}
}