{
  "type": "Feature",
  "properties": {
    "iso:country":"CH",
    "sg:address":"Plazza Da Cum\u00fcn",
    "sg:city":"Poschiavo",
    "sg:orig_category":"Verkehrs- and Tourismusb\u00fcros",
    "sg:phone":"+41 33 733 31 31",
    "sg:postcode":"7742",
    "sg:province":"Graubunden",
    "wof:name":"Tourist Center",
    "wof:placetype":"venue"
},
  "geometry": {"coordinates":[7.4413700104,46.4569587708],"type":"Point"}
}