{
  "type": "Feature",
  "properties": {
    "iso:country":"CH",
    "sg:address":"Plattenstrasse 24",
    "sg:city":"Dottikon",
    "sg:orig_category":"Wirtschaftspr\u00fcfung, Steuerberatung U Treuhand",
    "sg:phone":"+41 56 610 15 15",
    "sg:postcode":"5605",
    "sg:province":"Aargau",
    "wof:name":"Christoph Mutzner Mutzner Treuhand",
    "wof:placetype":"venue"
},
  "geometry": {"coordinates":[8.2349405289,47.3777198792],"type":"Point"}
}