{
  "type": "Feature",
  "properties": {
    "iso:country":"CH",
    "sg:address":"Avenue De Chillon 37",
    "sg:city":"Territet-veytaux",
    "sg:orig_category":"Vermietung von Automobilen",
    "sg:postcode":"1820",
    "sg:province":"Vaud",
    "wof:name":"Briatico Sa",
    "wof:placetype":"venue"
},
  "geometry": {"coordinates":[6.9275169373,46.4190940857],"type":"Point"}
}