{
  "type": "Feature",
  "properties": {
    "iso:country":"CH",
    "sg:address":"Proz-de-conthey Rue 1",
    "sg:city":"Ardon",
    "sg:orig_category":"Allgemeiner Hoch U Tiefbau",
    "sg:postcode":"1957",
    "sg:province":"Valais",
    "wof:name":"Gasser Charles Sa, Succursale D'ardon",
    "wof:placetype":"venue"
},
  "geometry": {"coordinates":[7.255632,46.206329],"type":"Point"}
}