{
  "type": "Feature",
  "properties": {
    "iso:country":"CH",
    "sg:address":"Grellingerstrasse 23",
    "sg:city":"Nunningen",
    "sg:orig_category":"Zimmerei Zimmerei, Dachdeckerei, Bauspenglerei U Abdichtung",
    "sg:phone":"+41 33 251 19 09",
    "sg:postcode":"4208",
    "sg:province":"Solothurn",
    "wof:name":"Loosli Holzbau Ag",
    "wof:placetype":"venue"
},
  "geometry": {"coordinates":[7.7002100945,46.7196578979],"type":"Point"}
}