{
  "type": "Feature",
  "properties": {
    "iso:country":"CH",
    "sg:address":"1261",
    "sg:city":"Burtigny",
    "sg:orig_category":"Primarschulen",
    "sg:phone":"+41 26 912 60 81",
    "sg:postcode":"1261",
    "sg:province":"Vaud",
    "wof:name":"Ecole Primaire",
    "wof:placetype":"venue"
},
  "geometry": {"coordinates":[6.2592358589,46.4656448364],"type":"Point"}
}