{
  "type": "Feature",
  "properties": {
    "iso:country":"CH",
    "sg:address":"Kirchweg 60 8750 Glarus. Postfach",
    "sg:city":"Glarus",
    "sg:orig_category":"RESTAURANTS: TEA-ROOMS",
    "sg:postcode":"8750",
    "sg:province":"Glarus",
    "wof:name":"Gerardi Loredana Restaurantbetrieb",
    "wof:placetype":"venue"
},
  "geometry": {"coordinates":[9.0712823868,47.0373458862],"type":"Point"}
}