{
  "type": "Feature",
  "properties": {
    "iso:country":"CH",
    "sg:address":"Rue De Fer 6",
    "sg:city":"Del\u00e9mont",
    "sg:orig_category":"Gasversorgung Herstellung von Industriegasen",
    "sg:phone":"+41 79 251 17 86",
    "sg:postcode":"2800",
    "sg:province":"Jura",
    "wof:name":"R\u00e9giogaz Sa",
    "wof:placetype":"venue"
},
  "geometry": {"coordinates":[7.3431568146,47.3654212952],"type":"Point"}
}