{
  "type": "Feature",
  "properties": {
    "iso:country":"CH",
    "sg:address":"Bahnhofstrasse 25",
    "sg:city":"Zollikon",
    "sg:orig_category":"Kauf U Verkauf von Immobilien auf eigene Rechnung",
    "sg:postcode":"8702",
    "sg:province":"Z\u00fcrich",
    "wof:name":"Immorohn Gmbh",
    "wof:placetype":"venue"
},
  "geometry": {"coordinates":[9.5398807526,47.3787651062],"type":"Point"}
}