{
  "type": "Feature",
  "properties": {
    "iso:country":"CH",
    "sg:address":"Kutwilerstr. 4",
    "sg:city":"B\u00fcron",
    "sg:classifiers":[
        {
            "category":"Shopping",
            "subcategory":"Computers & Home Electronics",
            "type":"Retail Goods"
        }
    ],
    "sg:phone":"+41 41 933 00 74",
    "sg:postcode":"6233",
    "sg:province":"Luzern",
    "sg:tags":[
        "equipment",
        "household",
        "electrical",
        "appliance",
        "electronic"
    ],
    "wof:name":"Gebr. Wyss Ag",
    "wof:placetype":"venue"
},
  "geometry": {"coordinates":[8.0882024765,47.2093391418],"type":"Point"}
}