{
  "type": "Feature",
  "properties": {
    "iso:country":"CH",
    "sg:address":"Stierliweg 12",
    "sg:city":"Z\u00fcrich",
    "sg:orig_category":"Instandhaltung U Reparatur von Automobilen",
    "sg:phone":"+41 12427079",
    "sg:postcode":"8004",
    "sg:province":"Z\u00fcrich",
    "wof:name":"Garage Koradi",
    "wof:placetype":"venue"
},
  "geometry": {"coordinates":[8.5133447647,47.3780097961],"type":"Point"}
}