{
  "type": "Feature",
  "properties": {
    "iso:country":"CH",
    "sg:address":"Panoramaweg 12",
    "sg:city":"Remetschwil",
    "sg:classifiers":[
        {
            "category":"Communications",
            "subcategory":"Film & Video Production",
            "type":"Services"
        }
    ],
    "sg:phone":"+41 56 496 80 94",
    "sg:postcode":"5453",
    "sg:province":"Aargau",
    "sg:tags":[
        "videofilmherstellung",
        "u"
    ],
    "wof:name":"Marc Villiger Visual Productions",
    "wof:placetype":"venue"
},
  "geometry": {"coordinates":[8.3352546692,47.4070129395],"type":"Point"}
}