{
  "type": "Feature",
  "properties": {
    "iso:country":"CH",
    "sg:address":"Klosterplatz 9",
    "sg:city":"Olten",
    "sg:orig_category":"Detailhandel mit Textilien Detailhandel mit Waren verschiedener Art, Hauptrichtung Nichtnahrungsmitt",
    "sg:phone":"+41 62 212 73 15",
    "sg:postcode":"4600",
    "sg:province":"Solothurn",
    "wof:name":"Kaufhaus Klosterplatz",
    "wof:placetype":"venue"
},
  "geometry": {"coordinates":[7.9042921066,47.3503417969],"type":"Point"}
}