{
  "type": "Feature",
  "properties": {
    "iso:country":"CH",
    "sg:address":"Schwandstrasse 55",
    "sg:city":"Thierachern",
    "sg:orig_category":"Maler U Glasergewerbe",
    "sg:phone":"+41 33 345 52 21",
    "sg:postcode":"3634",
    "sg:province":"Bern",
    "wof:name":"Malerei Hubacher",
    "wof:placetype":"venue"
},
  "geometry": {"coordinates":[7.5784401894,46.7570304871],"type":"Point"}
}