{
  "type": "Feature",
  "properties": {
    "iso:country":"CH",
    "sg:address":"Ausserdorfstrasse 45",
    "sg:city":"Unterlunkhofen",
    "sg:orig_category":"Malerei",
    "sg:phone":"+41 56 634 28 07",
    "sg:postcode":"8918",
    "sg:province":"Aargau",
    "wof:name":"Hans Eisold Maleratelier",
    "wof:placetype":"venue"
},
  "geometry": {"coordinates":[8.3810195923,47.319858551],"type":"Point"}
}