{
  "type": "Feature",
  "properties": {
    "addr:full":"Lausanne Rue De 72 1202 Gen\u00e8ve. Postfach Gen\u00e8ve Gen\u00e8ve 1201",
    "addr:housenumber":"72",
    "addr:postcode":"1202;postfach;1201",
    "addr:street":"Rue De",
    "iso:country":"CH",
    "sg:address":"Lausanne Rue De 72 1202 Gen\u00e8ve. Postfach",
    "sg:city":"Gen\u00e8ve",
    "sg:orig_category":"Architektur U Ingenieurb\u00fcros",
    "sg:postcode":"1201",
    "sg:province":"Gen\u00e8ve",
    "wof:name":"Hydroserve, Candotti Ambleto",
    "wof:placetype":"venue"
},
  "geometry": {"coordinates":[6.147508,46.21571],"type":"Point"}
}