{
  "type": "Feature",
  "properties": {
    "iso:country":"CH",
    "sg:address":"Obere Kirchstrasse 35",
    "sg:city":"Wallisellen",
    "sg:orig_category":"Arztpraxen",
    "sg:phone":"+41 18302170",
    "sg:postcode":"8304",
    "sg:province":"Z\u00fcrich",
    "wof:name":"Dr.med.heinrich Tanner Spezialarzt Fmh",
    "wof:placetype":"venue"
},
  "geometry": {"coordinates":[8.597117,47.417278],"type":"Point"}
}