{
  "type": "Feature",
  "properties": {
    "iso:country":"CH",
    "sg:address":"Rue Louis Bornet 8",
    "sg:city":"Bulle",
    "sg:orig_category":"Detailhandel mit Spielwaren Erbringung von sonstigen Dienstleistungen f\u00fcr Unterhaltung, Erholung U F",
    "sg:phone":"+41 26 912 19 89",
    "sg:postcode":"1630",
    "sg:province":"Fribourg",
    "wof:name":"Guy Mossu Gdm Productions",
    "wof:placetype":"venue"
},
  "geometry": {"coordinates":[7.0492401123,46.6136436462],"type":"Point"}
}