{
  "type": "Feature",
  "properties": {
    "iso:country":"CH",
    "sg:address":"Kilchbergstrasse 5",
    "sg:city":"Adliswil",
    "sg:orig_category":"Detailhandel mit elektrischen Haushalts, Radio U Fernsehger\u00e4ten ohne ausgepr\u00e4gten Schwerpunkt Elektr",
    "sg:phone":"+41 34 437 37 37",
    "sg:postcode":"8134",
    "sg:province":"Z\u00fcrich",
    "wof:name":"Werner Hiltbrunner",
    "wof:placetype":"venue"
},
  "geometry": {"coordinates":[7.8018708229,47.0455856323],"type":"Point"}
}