{
  "type": "Feature",
  "properties": {
    "iso:country":"CH",
    "sg:address":"Chollerstrasse 3",
    "sg:city":"Zug",
    "sg:orig_category":"Architektur U Ingenieurb\u00fcros Architekturb\u00fcros",
    "sg:phone":"+41 62 866 11 66",
    "sg:postcode":"6300",
    "sg:province":"Zug",
    "wof:name":"Birri Ren\u00e9 & Partner Architektur Und Planung Ag",
    "wof:placetype":"venue"
},
  "geometry": {"coordinates":[7.953856,47.542194],"type":"Point"}
}