{
  "type": "Feature",
  "properties": {
    "iso:country":"CH",
    "sg:address":"Rue De La Paix 8",
    "sg:city":"Bulle",
    "sg:orig_category":"Stukkateurgewerbe, Gipserei U Verputzerei Tapeziererei",
    "sg:phone":"+41 26 912 99 35",
    "sg:postcode":"1630",
    "sg:province":"Fribourg",
    "wof:name":"Louis Marchina & Fils Sa",
    "wof:placetype":"venue"
},
  "geometry": {"coordinates":[7.064704895,46.6133918762],"type":"Point"}
}