{
  "type": "Feature",
  "properties": {
    "iso:country":"CH",
    "sg:address":"Sattlerstrasse 7",
    "sg:city":"Neuwilen",
    "sg:orig_category":"Unclassifiable Establishments",
    "sg:postcode":"8566",
    "sg:province":"Thurgau",
    "wof:name":"D\u00fcnner Transporte Gmbh",
    "wof:placetype":"venue"
},
  "geometry": {"coordinates":[9.1349086761,47.6226387024],"type":"Point"}
}