{
  "type": "Feature",
  "properties": {
    "iso:country":"CH",
    "sg:address":"Brunngasse 4",
    "sg:city":"Winterthur",
    "sg:orig_category":"Datenverarbeitungsdienste Informatikdienste",
    "sg:phone":"+41 31 308 10 10",
    "sg:postcode":"8400",
    "sg:province":"Z\u00fcrich",
    "wof:name":"Data Dynamic Ag",
    "wof:placetype":"venue"
},
  "geometry": {"coordinates":[7.430768,46.948551],"type":"Point"}
}