{
  "type": "Feature",
  "properties": {
    "iso:country":"CH",
    "sg:address":"Schwanden 324",
    "sg:city":"Oberhelfenschwil",
    "sg:orig_category":"Architektur U Ingenieurb\u00fcros",
    "sg:postcode":"9621",
    "sg:province":"St. Gallen",
    "wof:name":"Bm Plan Gmbh",
    "wof:placetype":"venue"
},
  "geometry": {"coordinates":[7.51681,47.398697],"type":"Point"}
}