{
  "type": "Feature",
  "properties": {
    "iso:country":"CH",
    "sg:address":"Bahnhofstrasse",
    "sg:city":"Horgen",
    "sg:classifiers":[
        {
            "category":"Restaurant",
            "type":"Food & Drink"
        }
    ],
    "sg:postcode":"8810",
    "sg:province":"Z\u00fcrich",
    "sg:tags":[
        "tea-rooms",
        "restaurants"
    ],
    "wof:name":"S\u00e4umersch\u00e4nki Gmbh",
    "wof:placetype":"venue"
},
  "geometry": {"coordinates":[8.5971698761,47.2613296509],"type":"Point"}
}