{
  "type": "Feature",
  "properties": {
    "iso:country":"CH",
    "sg:address":"Seefeldstrasse 6",
    "sg:city":"Uster",
    "sg:orig_category":"Herstellung von Kakao, Schokoladeerzeugnissen U Zuckerwaren",
    "sg:postcode":"8610",
    "sg:province":"Z\u00fcrich",
    "wof:name":"Intersweet Gmbh",
    "wof:placetype":"venue"
},
  "geometry": {"coordinates":[8.7043924332,47.3402366638],"type":"Point"}
}