{
  "type": "Feature",
  "properties": {
    "iso:country":"CH",
    "sg:address":"Stapferstrasse 1",
    "sg:city":"Z\u00fcrich",
    "sg:orig_category":"Softwareentwicklung U beratung",
    "sg:postcode":"8006",
    "sg:province":"Z\u00fcrich",
    "wof:name":"Bilderbank Ag",
    "wof:placetype":"venue"
},
  "geometry": {"coordinates":[7.5564408302,47.5117950439],"type":"Point"}
}