{
  "type": "Feature",
  "properties": {
    "iso:country":"CH",
    "sg:address":"1123",
    "sg:city":"Aclens",
    "sg:orig_category":"Maurerarbeiten",
    "sg:phone":"+41 24 491 15 08",
    "sg:postcode":"1123",
    "sg:province":"Vaud",
    "wof:name":"Marcel Chamorel Entreprise De Ma\u00e7onnerie",
    "wof:placetype":"venue"
},
  "geometry": {"coordinates":[7.0534849167,46.3616447449],"type":"Point"}
}