{
  "type": "Feature",
  "properties": {
    "iso:country":"CH",
    "sg:address":"D\u00fcrntnerstrasse 41 8626 Ottikon. Postfach",
    "sg:city":"Ottikon",
    "sg:orig_category":"Herstellung von Teppichen",
    "sg:phone":"+41 24 499 25 35",
    "sg:postcode":"8626",
    "sg:province":"Z\u00fcrich",
    "wof:name":"Service Sols - Maire Francis S\u00e0rl",
    "wof:placetype":"venue"
},
  "geometry": {"coordinates":[6.9953799248,46.2966117859],"type":"Point"}
}