{
  "type": "Feature",
  "properties": {
    "iso:country":"CH",
    "sg:address":"Via Cantonale",
    "sg:city":"Melide",
    "sg:orig_category":"Diskotheken, Dancings, Night Clubs Restaurants",
    "sg:phone":"+41 91 649 75 21",
    "sg:postcode":"6815",
    "sg:province":"Ticino",
    "wof:name":"Grottino La Romantica",
    "wof:placetype":"venue"
},
  "geometry": {"coordinates":[8.9523258209,45.9536743164],"type":"Point"}
}