{
  "type": "Feature",
  "properties": {
    "iso:country":"CH",
    "sg:address":"Hauptstr. 246",
    "sg:city":"Leutwil",
    "sg:orig_category":"Pensionskassen",
    "sg:postcode":"5725",
    "sg:province":"Aargau",
    "wof:name":"Personalf\u00fcrsorgestiftung Der Firma Gebr\u00fcder L\u00fcscher Ag",
    "wof:placetype":"venue"
},
  "geometry": {"coordinates":[8.1739883423,47.3088150024],"type":"Point"}
}