{
  "type": "Feature",
  "properties": {
    "iso:country":"CH",
    "sg:address":"Kloosweg 72 2500 Biel/bienne. Postfach",
    "sg:city":"Biel/bienne",
    "sg:orig_category":"RESTAURANTS: TEA-ROOMS",
    "sg:postcode":"2502",
    "sg:province":"Bern",
    "wof:name":"Weber Werner.",
    "wof:placetype":"venue"
},
  "geometry": {"coordinates":[7.2433972359,47.1454315186],"type":"Point"}
}