{
  "type": "Feature",
  "properties": {
    "iso:country":"CH",
    "sg:address":"Via San Gottardo 103a",
    "sg:city":"Balerna",
    "sg:orig_category":"Verwaltung von Immobilien",
    "sg:postcode":"6828",
    "sg:province":"Ticino",
    "wof:name":"Balerimmo Sa",
    "wof:placetype":"venue"
},
  "geometry": {"coordinates":[9.0031270981,45.8516578674],"type":"Point"}
}