{
  "type": "Feature",
  "properties": {
    "iso:country":"CH",
    "sg:address":"Kugelgasse 32a",
    "sg:city":"Diepoldsau",
    "sg:orig_category":"Sportvereine Turnen",
    "sg:phone":"+41 71 385 92 40",
    "sg:postcode":"9444",
    "sg:province":"St. Gallen",
    "wof:name":"Kunstturner-vereing.sg-appenz.",
    "wof:placetype":"venue"
},
  "geometry": {"coordinates":[9.2575540543,47.4188766479],"type":"Point"}
}