{
  "type": "Feature",
  "properties": {
    "iso:country":"CH",
    "sg:address":"Wagistrasse 13",
    "sg:city":"Schlieren",
    "sg:orig_category":"Erbringung von Dienstleistungen f\u00fcr Unternehmen Grafikateliers, Design",
    "sg:phone":"+41 17310320",
    "sg:postcode":"8952",
    "sg:province":"Z\u00fcrich",
    "wof:name":"Streuli Peter Schriften",
    "wof:placetype":"venue"
},
  "geometry": {"coordinates":[8.4569969177,47.3992919922],"type":"Point"}
}