{
  "type": "Feature",
  "properties": {
    "iso:country":"CH",
    "sg:address":"Le R\u00e9gent",
    "sg:city":"Crans-sur-sierre",
    "sg:orig_category":"Gymnastik U Fitnesszentren",
    "sg:phone":"+41 19335480",
    "sg:postcode":"3963",
    "sg:province":"Valais",
    "wof:name":"Fitness-gym-sch\u00f6neich",
    "wof:placetype":"venue"
},
  "geometry": {"coordinates":[8.7938747406,47.3109474182],"type":"Point"}
}