{
  "type": "Feature",
  "properties": {
    "iso:country":"CH",
    "sg:address":"Obergasse 10",
    "sg:city":"Biel/bienne",
    "sg:orig_category":"Non-Classified Establishments",
    "sg:postcode":"2502",
    "sg:province":"Bern",
    "wof:name":"Gianni Vasari, Inhaber H. Huber",
    "wof:placetype":"venue"
},
  "geometry": {"coordinates":[7.2466468811,47.1422195435],"type":"Point"}
}