{
  "type": "Feature",
  "properties": {
    "iso:country":"CH",
    "sg:address":"Grossholzweg 9",
    "sg:city":"G\u00fcmligen",
    "sg:orig_category":"Wohnheime f\u00fcr Kinder U Jugendliche",
    "sg:phone":"+41 41 874 13 00",
    "sg:postcode":"3073",
    "sg:province":"Bern",
    "wof:name":"Kinderheim Uri",
    "wof:placetype":"venue"
},
  "geometry": {"coordinates":[8.6442451477,46.8782920837],"type":"Point"}
}