{
  "type": "Feature",
  "properties": {
    "iso:country":"CH",
    "sg:address":"Poststrasse 4",
    "sg:city":"Neuheim",
    "sg:orig_category":"Instandhaltung U Reparatur von Automobilen",
    "sg:postcode":"6345",
    "sg:province":"Zug",
    "wof:name":"Fahrzeuge Imhof Beda",
    "wof:placetype":"venue"
},
  "geometry": {"coordinates":[8.5758152008,47.2043991089],"type":"Point"}
}