{
  "type": "Feature",
  "properties": {
    "iso:country":"CH",
    "sg:address":"Bucheggstrasse 6",
    "sg:city":"Lommis",
    "sg:orig_category":"Kauf U Verkauf von Immobilien auf eigene Rechnung",
    "sg:phone":"+41 52 376 21 89",
    "sg:postcode":"9506",
    "sg:province":"Thurgau",
    "wof:name":"G + S Wohnbauten Und Verwaltungen Ag",
    "wof:placetype":"venue"
},
  "geometry": {"coordinates":[8.9917154312,47.513633728],"type":"Point"}
}