{
  "type": "Feature",
  "properties": {
    "iso:country":"CH",
    "sg:address":"Campanules Chemin Des 3 1219 A\u00efre. Postfach",
    "sg:city":"A\u00efre",
    "sg:orig_category":"Forschung U Entwicklung im Bereich der Naturwissenschaften",
    "sg:phone":"+41 22 795 75 75",
    "sg:postcode":"1219",
    "sg:province":"Gen\u00e8ve",
    "wof:name":"Bmi Technologies Sa",
    "wof:placetype":"venue"
},
  "geometry": {"coordinates":[6.0983500481,46.1966629028],"type":"Point"}
}