{
  "type": "Feature",
  "properties": {
    "iso:country":"CH",
    "sg:address":"Route De Saint-julien 161",
    "sg:city":"Plan-les-ouates",
    "sg:orig_category":"Detailhandel mit Antiquit\u00e4ten Kunsthandel",
    "sg:phone":"+41 19322586",
    "sg:postcode":"1228",
    "sg:province":"Gen\u00e8ve",
    "wof:name":"Josef Bachmann Antiquit\u00e4ten Kunsthandel",
    "wof:placetype":"venue"
},
  "geometry": {"coordinates":[8.786402,47.311375],"type":"Point"}
}