{
  "type": "Feature",
  "properties": {
    "iso:country":"CH",
    "sg:address":"Seestrasse 100",
    "sg:city":"Uster",
    "sg:orig_category":"Sonstige mit der Informatik verbundene T\u00e4tigkeiten",
    "sg:postcode":"8610",
    "sg:province":"Z\u00fcrich",
    "wof:name":"Greber Consulting",
    "wof:placetype":"venue"
},
  "geometry": {"coordinates":[8.8506250381,47.4172973633],"type":"Point"}
}