{
  "type": "Feature",
  "properties": {
    "iso:country":"CH",
    "sg:address":"Vordergasse 37",
    "sg:city":"Neunkirch",
    "sg:orig_category":"Elektroinstallation",
    "sg:phone":"+41 52 682 23 63",
    "sg:postcode":"8213",
    "sg:province":"Schaffhausen",
    "wof:name":"N\u00e4f & Weber Elektroinstallationen",
    "wof:placetype":"venue"
},
  "geometry": {"coordinates":[8.4981069565,47.6900978088],"type":"Point"}
}