{
  "type": "Feature",
  "properties": {
    "iso:country":"CH",
    "sg:address":"Altweg 16",
    "sg:city":"Frauenfeld",
    "sg:orig_category":"Sonstige Institutionen des Sozialwesens ohne Beherbergung",
    "sg:phone":"+41 52 721 85 60",
    "sg:postcode":"8500",
    "sg:province":"Thurgau",
    "wof:name":"M\u00fctter-& V\u00e4terberatungsverein Bezirk Frauenfeld",
    "wof:placetype":"venue"
},
  "geometry": {"coordinates":[8.8928050995,47.5552139282],"type":"Point"}
}