{
  "type": "Feature",
  "properties": {
    "iso:country":"CH",
    "sg:address":"Fuchshagweg 30",
    "sg:city":"Bottmingen",
    "sg:orig_category":"Werbung",
    "sg:phone":"+41 61 421 00 30",
    "sg:postcode":"4103",
    "sg:province":"Basel-Landschaft",
    "wof:name":"Zahner Otto",
    "wof:placetype":"venue"
},
  "geometry": {"coordinates":[7.5653009415,47.5290107727],"type":"Point"}
}