{
  "type": "Feature",
  "properties": {
    "iso:country":"CH",
    "sg:address":"Winkelriedstrasse 3",
    "sg:city":"Luzern",
    "sg:orig_category":"Detailhandel mit Brillen U anderen Sehhilfen Grosshandel mit Sportartikeln",
    "sg:phone":"+41 41 210 11 78",
    "sg:postcode":"6003",
    "sg:province":"Luzern",
    "wof:name":"Zimmermann Waffen Und Jagdoptik Ag Waffen Und Jagdoptik; Fabrikation, Handel Usw",
    "wof:placetype":"venue"
},
  "geometry": {"coordinates":[8.304798,47.049568],"type":"Point"}
}