{
  "type": "Feature",
  "properties": {
    "iso:country":"CH",
    "sg:address":"Route Mon-repos 5c 1700 Fribourg. Postfach",
    "sg:city":"Fribourg",
    "sg:orig_category":"Arztpraxen",
    "sg:phone":"+41 26 481 18 89",
    "sg:postcode":"1707",
    "sg:province":"Fribourg",
    "wof:name":"Dr M\u00e9d. Christophe Werlen M\u00e9decin Sp\u00e9cialiste Fmh",
    "wof:placetype":"venue"
},
  "geometry": {"coordinates":[7.173443,46.808926],"type":"Point"}
}