{
  "type": "Feature",
  "properties": {
    "iso:country":"CH",
    "sg:address":"En Vannel A",
    "sg:city":"Bex",
    "sg:orig_category":"Autogaragen",
    "sg:phone":"+41 24 463 59 63",
    "sg:postcode":"1880",
    "sg:province":"Vaud",
    "wof:name":"Mamin Automobiles Garage",
    "wof:placetype":"venue"
},
  "geometry": {"coordinates":[6.999065,46.248344],"type":"Point"}
}