{
  "type": "Feature",
  "properties": {
    "iso:country":"CH",
    "sg:address":"Sonnenstrasse 36",
    "sg:city":"Port",
    "sg:orig_category":"Fahrschulen, Flugschulen",
    "sg:phone":"+41 32 331 67 02",
    "sg:postcode":"2562",
    "sg:province":"Bern",
    "wof:name":"Johann Zwinggi Autofahrlehrer",
    "wof:placetype":"venue"
},
  "geometry": {"coordinates":[7.2568740845,47.1138305664],"type":"Point"}
}