{
  "type": "Feature",
  "properties": {
    "iso:country":"CH",
    "sg:address":"Kirchenfeldstrasse 50",
    "sg:city":"Bern",
    "sg:orig_category":"Softwareentwicklung U beratung",
    "sg:phone":"+41 31 351 15 93",
    "sg:postcode":"3005",
    "sg:province":"Bern",
    "wof:name":"Dbf Informatik Schlupp R. Informationssysteme; Entwicklung",
    "wof:placetype":"venue"
},
  "geometry": {"coordinates":[7.4538612366,46.9401435852],"type":"Point"}
}