{
  "type": "Feature",
  "properties": {
    "iso:country":"CH",
    "sg:address":"Witikonerstrasse 37",
    "sg:city":"Z\u00fcrich",
    "sg:orig_category":"Public-Relations-Agenturen",
    "sg:phone":"+41 13805272",
    "sg:postcode":"8032",
    "sg:province":"Z\u00fcrich",
    "wof:name":"Albert Ernst A.e. Marketing",
    "wof:placetype":"venue"
},
  "geometry": {"coordinates":[8.5675649643,47.3633422852],"type":"Point"}
}