{
  "type": "Feature",
  "properties": {
    "iso:country":"CH",
    "sg:address":"Marktgasse 12",
    "sg:city":"Langenthal",
    "sg:orig_category":"Reiseb\u00fcros U Reiseveranstalter",
    "sg:phone":"+41 12778111",
    "sg:postcode":"4900",
    "sg:province":"Bern",
    "wof:name":"Hotelplan Internationale Reiseorganisation Ag",
    "wof:placetype":"venue"
},
  "geometry": {"coordinates":[7.7890958786,47.212387085],"type":"Point"}
}