{
  "type": "Feature",
  "properties": {
    "iso:country":"CH",
    "sg:address":"M\u00fchlebachstrasse 8/10 8008 Z\u00fcrich. Postfach",
    "sg:city":"Z\u00fcrich",
    "sg:orig_category":"Pensionskassen",
    "sg:postcode":"8001",
    "sg:province":"Z\u00fcrich",
    "wof:name":"F\u00fcrsorgestiftung Der Firma K\u00e4mpfen-hieronymi & Co., Z\u00fcrich",
    "wof:placetype":"venue"
},
  "geometry": {"coordinates":[8.5494594574,47.3655128479],"type":"Point"}
}