{
  "type": "Feature",
  "properties": {
    "addr:full":"Bechburgerstrasse 9 Balsthal Solothurn 4710",
    "addr:housenumber":"9",
    "addr:postcode":"4710",
    "addr:street":"Bechburgerstrasse",
    "iso:country":"CH",
    "sg:address":"Bechburgerstrasse 9",
    "sg:city":"Balsthal",
    "sg:orig_category":"Arbeitnehmerverb\u00e4nde",
    "sg:phone":"+41 62 391 37 52",
    "sg:postcode":"4710",
    "sg:province":"Solothurn",
    "wof:name":"Schweiz.typograph.vereinigung Sekt.olten,herrn Roger Gertsch",
    "wof:placetype":"venue"
},
  "geometry": {"coordinates":[7.693334,47.311062],"type":"Point"}
}