{
  "type": "Feature",
  "properties": {
    "iso:country":"CH",
    "sg:address":"Falkenplatz 11",
    "sg:city":"Bern",
    "sg:classifiers":[
        {
            "category":"Manufacturing",
            "subcategory":"Printing",
            "type":"Manufacturing & Wholesale Goods"
        }
    ],
    "sg:phone":"+41 31 301 24 34",
    "sg:postcode":"3001",
    "sg:province":"Bern",
    "sg:tags":[
        "publishing"
    ],
    "wof:name":"Paul Haupt Ag",
    "wof:placetype":"venue"
},
  "geometry": {"coordinates":[7.4350199699,46.951210022],"type":"Point"}
}