{
  "type": "Feature",
  "properties": {
    "iso:country":"CH",
    "sg:address":"8607",
    "sg:city":"Aathal-seegr\u00e4ben",
    "sg:orig_category":"Vereine Frauen Vereine Gemeinn\u00fctzige",
    "sg:phone":"+41 71 891 15 03",
    "sg:postcode":"8607",
    "sg:province":"Z\u00fcrich",
    "wof:name":"Frauenverein",
    "wof:placetype":"venue"
},
  "geometry": {"coordinates":[9.5699796677,47.4089813232],"type":"Point"}
}