{
  "type": "Feature",
  "properties": {
    "addr:full":"K\u00e4sereistrasse 6 Niederscherli Bern 3145",
    "addr:housenumber":"6",
    "addr:postcode":"3145",
    "addr:street":"Kaesereistrasse",
    "iso:country":"CH",
    "sg:address":"K\u00e4sereistrasse 6",
    "sg:city":"Niederscherli",
    "sg:orig_category":"Bauschreinerei Herstellung von Konstruktionsteilen, Fertigbauteilen U Ausbauelementen aus Holz",
    "sg:phone":"+41 79 658 34 91",
    "sg:postcode":"3145",
    "sg:province":"Bern",
    "wof:name":"M&m Holztechnik Gmbh",
    "wof:placetype":"venue"
},
  "geometry": {"coordinates":[7.38783,46.885963],"type":"Point"}
}