{
  "type": "Feature",
  "properties": {
    "iso:country":"CH",
    "sg:address":"Via Lorenzo Vela",
    "sg:city":"Ligornetto",
    "sg:orig_category":"Arztpraxen",
    "sg:phone":"+41 91 647 19 52",
    "sg:postcode":"6853",
    "sg:province":"Ticino",
    "wof:name":"Dott.med.carlo-enrico Pusterla Specialista Fmh",
    "wof:placetype":"venue"
},
  "geometry": {"coordinates":[8.949035,45.863655],"type":"Point"}
}