{
  "type": "Feature",
  "properties": {
    "iso:country":"CH",
    "sg:address":"Chemin De L'avanchet 16",
    "sg:city":"Cointrin",
    "sg:orig_category":"Innendekorationsateliers",
    "sg:phone":"+41 22 798 80 96",
    "sg:postcode":"1216",
    "sg:province":"Gen\u00e8ve",
    "wof:name":"Gilbert Buchilly Tapissier-d\u00e9corateur",
    "wof:placetype":"venue"
},
  "geometry": {"coordinates":[-0.6152780056,48.4583053589],"type":"Point"}
}