{
  "type": "Feature",
  "properties": {
    "iso:country":"CH",
    "sg:address":"Steineggstrasse 9",
    "sg:city":"Degersheim",
    "sg:orig_category":"Arztpraxen",
    "sg:phone":"+41 71 371 24 24",
    "sg:postcode":"9113",
    "sg:province":"St. Gallen",
    "wof:name":"Dr.med.j\u00fcrg W. Weber Arzt F.allgemeine Medizin Fmh",
    "wof:placetype":"venue"
},
  "geometry": {"coordinates":[9.198905,47.374599],"type":"Point"}
}