{
  "type": "Feature",
  "properties": {
    "iso:country":"CH",
    "sg:address":"Ey-ch\u00fcpfen 7",
    "sg:city":"Schnottwil",
    "sg:orig_category":"Sonstiger Fachdetailhandel in Verkaufsr\u00e4umen",
    "sg:phone":"+41 32 351 35 78",
    "sg:postcode":"3253",
    "sg:province":"Solothurn",
    "wof:name":"Erwin Marti Briefmarken",
    "wof:placetype":"venue"
},
  "geometry": {"coordinates":[7.3894619942,47.1068763733],"type":"Point"}
}