{
  "type": "Feature",
  "properties": {
    "iso:country":"CH",
    "sg:address":"Bennwilerstrasse 15",
    "sg:city":"H\u00f6lstein",
    "sg:orig_category":"Sonstige mit der Informatik verbundene T\u00e4tigkeiten",
    "sg:phone":"+41 61 951 13 18",
    "sg:postcode":"4434",
    "sg:province":"Basel-Landschaft",
    "wof:name":"Timemaster Gmbh",
    "wof:placetype":"venue"
},
  "geometry": {"coordinates":[7.770606041,47.4233055115],"type":"Point"}
}