{
  "type": "Feature",
  "properties": {
    "iso:country":"CH",
    "sg:address":"3439",
    "sg:city":"Ranfl\u00fch",
    "sg:orig_category":"Landw. Genossenschaften Pferdezucht Landw. Genossenschaften Viehzucht",
    "sg:phone":"+41 31 311 56 24",
    "sg:postcode":"3439",
    "sg:province":"Bern",
    "wof:name":"Schweizerischer Pferdezuchtverband",
    "wof:placetype":"venue"
},
  "geometry": {"coordinates":[7.4495668411,46.948097229],"type":"Point"}
}