{
  "type": "Feature",
  "properties": {
    "iso:country":"CH",
    "sg:address":"Schulhausstr. 8",
    "sg:city":"Cham",
    "sg:classifiers":[
        {
            "category":"Banks & Credit Unions",
            "subcategory":"Bank",
            "type":"Services"
        }
    ],
    "sg:phone":"+41 41 785 05 05",
    "sg:postcode":"6330",
    "sg:province":"Zug",
    "wof:name":"Raiffeisenbank Cham",
    "wof:placetype":"venue"
},
  "geometry": {"coordinates":[8.458098,47.181152],"type":"Point"}
}