{
  "type": "Feature",
  "properties": {
    "iso:country":"CH",
    "sg:address":"Burstwiesenstrasse 3 8606 Greifensee. Postfach 52",
    "sg:city":"Greifensee",
    "sg:classifiers":[
        {
            "category":"Restaurant",
            "type":"Food & Drink"
        }
    ],
    "sg:phone":"+41 17813471",
    "sg:postcode":"8606",
    "sg:province":"Z\u00fcrich",
    "wof:name":"Restaurant Meilibach",
    "wof:placetype":"venue"
},
  "geometry": {"coordinates":[8.6493587494,47.2459144592],"type":"Point"}
}