{
  "type": "Feature",
  "properties": {
    "iso:country":"CH",
    "sg:address":"Leutschenbachstr. 95",
    "sg:city":"Z\u00fcrich",
    "sg:classifiers":[
        {
            "category":"Professional",
            "subcategory":"Computer Services",
            "type":"Services"
        }
    ],
    "sg:phone":"+41 22 309 00 50",
    "sg:postcode":"8050",
    "sg:province":"Z\u00fcrich",
    "sg:tags":[
        "information",
        "technology",
        "software"
    ],
    "wof:name":"Cast Sarl",
    "wof:placetype":"venue"
},
  "geometry": {"coordinates":[6.1357808113,46.1903953552],"type":"Point"}
}