{
  "type": "Feature",
  "properties": {
    "iso:country":"CH",
    "sg:address":"Schwand 3110 M\u00fcnsingen. Postfach",
    "sg:city":"M\u00fcnsingen",
    "sg:orig_category":"Unclassifiable Establishments",
    "sg:postcode":"3110",
    "sg:province":"Bern",
    "wof:name":"G\u00e4rtnerei, Gartencenter First Gartenmann Heinz",
    "wof:placetype":"venue"
},
  "geometry": {"coordinates":[8.747595787,47.187297821],"type":"Point"}
}