{
  "type": "Feature",
  "properties": {
    "iso:country":"CH",
    "sg:address":"Varenstrasse 65",
    "sg:city":"Salgesch",
    "sg:orig_category":"Grosshandel mit Getr\u00e4nken Rebbau",
    "sg:phone":"+41 79 213 45 66",
    "sg:postcode":"3970",
    "sg:province":"Valais",
    "wof:name":"St.martinskellerei, Kuonen Beat & Barbara",
    "wof:placetype":"venue"
},
  "geometry": {"coordinates":[7.5768232346,46.3131332397],"type":"Point"}
}