{
  "type": "Feature",
  "properties": {
    "addr:full":"Willisau Willisau Luzern 6130",
    "addr:postcode":"6130",
    "iso:country":"CH",
    "sg:address":"Willisau",
    "sg:city":"Willisau",
    "sg:classifiers":[
        {
            "category":"Banks & Credit Unions",
            "subcategory":"Bank",
            "type":"Services"
        }
    ],
    "sg:phone":"+41 45813636",
    "sg:postcode":"6130",
    "sg:province":"Luzern",
    "wof:name":"Luzerner Landbank Ag",
    "wof:placetype":"venue"
},
  "geometry": {"coordinates":[7.992884,47.122223],"type":"Point"}
}