{
  "type": "Feature",
  "properties": {
    "iso:country":"CH",
    "sg:address":"Hauptstrasse 174",
    "sg:city":"Ermatingen",
    "sg:orig_category":"Detailhandel mit M\u00f6beln U Haushaltsgegenst\u00e4nden",
    "sg:postcode":"8272",
    "sg:province":"Thurgau",
    "wof:name":"Lona, N\u00e4f E.",
    "wof:placetype":"venue"
},
  "geometry": {"coordinates":[8.3140583038,46.9888916016],"type":"Point"}
}