{
  "type": "Feature",
  "properties": {
    "iso:country":"CH",
    "sg:address":"Avenue Du Grand-champsec 80 1950 Sion Case Postale 510",
    "sg:city":"Sion",
    "sg:orig_category":"Universit\u00e4tsspit\u00e4ler, Spit\u00e4ler f\u00fcr allgemeine Pflege",
    "sg:phone":"+41 22 327 43 91",
    "sg:postcode":"1951",
    "sg:province":"Valais",
    "wof:name":"H\u00f4pitaux Universitaires Service M\u00e9dico-p\u00e9dagogique",
    "wof:placetype":"venue"
},
  "geometry": {"coordinates":[6.1329140663,46.2011756897],"type":"Point"}
}