{
  "type": "Feature",
  "properties": {
    "iso:country":"CH",
    "sg:address":"Buzibachstrasse 31",
    "sg:city":"Rothenburg",
    "sg:classifiers":[
        {
            "category":"Professional",
            "subcategory":"Advertising",
            "type":"Services"
        }
    ],
    "sg:phone":"+41 71 272 77 77",
    "sg:postcode":"6023",
    "sg:province":"Luzern",
    "sg:tags":[
        "calendar",
        "purpose"
    ],
    "wof:name":"Zollikofer Ag",
    "wof:placetype":"venue"
},
  "geometry": {"coordinates":[9.340496,47.411499],"type":"Point"}
}