{
  "type": "Feature",
  "properties": {
    "iso:country":"CH",
    "sg:address":"Le P\u00e9cat 84 2853 Courfaivre. Postfach",
    "sg:city":"Courfaivre",
    "sg:orig_category":"Grosshandel mit Nahrungsmitteln, Getr\u00e4nken U Tabakwaren ohne ausgepr\u00e4gten Schwerpunkt",
    "sg:postcode":"2853",
    "sg:province":"Jura",
    "wof:name":"Nouvel Horizon Alimentation S\u00e0rl Magasin D'alimentation",
    "wof:placetype":"venue"
},
  "geometry": {"coordinates":[7.2798600197,47.3349685669],"type":"Point"}
}