{
  "type": "Feature",
  "properties": {
    "iso:country":"CH",
    "sg:address":"Tuileries Chemin Des 28",
    "sg:city":"Bellevue",
    "sg:orig_category":"Unternehmensberatung",
    "sg:phone":"+41 22 958 01 14",
    "sg:postcode":"1293",
    "sg:province":"Gen\u00e8ve",
    "wof:name":"Intersource S\u00e0rl",
    "wof:placetype":"venue"
},
  "geometry": {"coordinates":[6.1551737785,46.2550239563],"type":"Point"}
}