{
  "type": "Feature",
  "properties": {
    "iso:country":"CH",
    "sg:address":"Schellenbergstrasse 42",
    "sg:city":"Ruggell",
    "sg:orig_category":"Architektur U Ingenieurb\u00fcros",
    "sg:phone":"+423 373 69 29",
    "sg:postcode":"9491",
    "wof:name":"Heureka Norbert G\u00e4rtner Ingenieurb\u00fcro",
    "wof:placetype":"venue"
},
  "geometry": {"coordinates":[9.530805,47.240273],"type":"Point"}
}