{
  "type": "Feature",
  "properties": {
    "addr:full":"Dorfstrasse 12 Hinterkappelen Bern 3032",
    "addr:housenumber":"12",
    "addr:postcode":"3032",
    "addr:street":"Dorfstrasse",
    "iso:country":"CH",
    "sg:address":"Dorfstrasse 12",
    "sg:city":"Hinterkappelen",
    "sg:orig_category":"Arztpraxen",
    "sg:phone":"+41 31 901 09 50",
    "sg:postcode":"3032",
    "sg:province":"Bern",
    "wof:name":"Dres Med. U. & K. Zulliger Aerzte F\u00fcr Allg.medizin Fmh",
    "wof:placetype":"venue"
},
  "geometry": {"coordinates":[7.378905,46.967888],"type":"Point"}
}