{
  "type": "Feature",
  "properties": {
    "iso:country":"CH",
    "sg:address":"Dorf",
    "sg:city":"Heitenried",
    "sg:orig_category":"Mechanische Werkst\u00e4tten Schlossereien",
    "sg:phone":"+41 26 495 12 29",
    "sg:postcode":"1714",
    "sg:province":"Fribourg",
    "wof:name":"Roland Vonlanthen Mech.werkstatt & Landmaschinen",
    "wof:placetype":"venue"
},
  "geometry": {"coordinates":[7.2986240387,46.8276405334],"type":"Point"}
}