{
  "type": "Feature",
  "properties": {
    "iso:country":"CH",
    "sg:address":"Bergstrasse 37 8708 M\u00e4nnedorf. Postfach",
    "sg:city":"Z\u00fcrich",
    "sg:orig_category":"Grosshandel mit sonstigen Gebrauchs U Verbrauchsg\u00fctern",
    "sg:postcode":"8051",
    "sg:province":"Z\u00fcrich",
    "wof:name":"Swwwiss Dot Com Gmbh",
    "wof:placetype":"venue"
},
  "geometry": {"coordinates":[8.6952514648,47.2524452209],"type":"Point"}
}