{
  "type": "Feature",
  "properties": {
    "iso:country":"CH",
    "sg:address":"Zielstrasse 2",
    "sg:city":"Appenzell",
    "sg:orig_category":"Detailhandel mit Blumen U Pflanzen",
    "sg:phone":"+41 71 394 47 27",
    "sg:postcode":"9050",
    "sg:province":"Appenzell Innerhoden",
    "wof:name":"Barbara Meienberger Blumen Barbara",
    "wof:placetype":"venue"
},
  "geometry": {"coordinates":[9.408205,47.331905],"type":"Point"}
}