{
  "type": "Feature",
  "properties": {
    "iso:country":"CH",
    "sg:city":"Z\u00fcrich",
    "sg:orig_category":"Industrie, Maschinenbau",
    "sg:postcode":"8707",
    "sg:province":"Z\u00fcrich",
    "wof:name":"Feinwerktechnik - Feinmechanische Pr\u00e4zisionsteile",
    "wof:placetype":"venue"
},
  "geometry": {"coordinates":[8.676278,47.266357],"type":"Point"}
}