{
  "type": "Feature",
  "properties": {
    "iso:country":"CH",
    "sg:address":"Hofackerstrasse 13",
    "sg:city":"Adliswil",
    "sg:orig_category":"Maler U Glasergewerbe",
    "sg:postcode":"8134",
    "sg:province":"Z\u00fcrich",
    "wof:name":"Willi Baumberger Ag, Malergesch\u00e4ft",
    "wof:placetype":"venue"
},
  "geometry": {"coordinates":[8.5339508057,47.3159255981],"type":"Point"}
}