{
  "type": "Feature",
  "properties": {
    "iso:country":"CH",
    "sg:address":"Rue De La Cond\u00e9mine 6",
    "sg:city":"Bulle",
    "sg:orig_category":"Fotografische Ateliers",
    "sg:phone":"+41 26 912 93 73",
    "sg:postcode":"1630",
    "sg:province":"Fribourg",
    "wof:name":"Jo\u00ebl Gapany Atelier De Photographie",
    "wof:placetype":"venue"
},
  "geometry": {"coordinates":[7.0590400696,46.6148681641],"type":"Point"}
}