{
  "type": "Feature",
  "properties": {
    "iso:country":"CH",
    "sg:address":"Im Hofacker 3",
    "sg:city":"Thalheim",
    "sg:orig_category":"Sportvereine Turnen Vereine Damen",
    "sg:phone":"+41 52 336 20 01",
    "sg:postcode":"8478",
    "sg:province":"Z\u00fcrich",
    "wof:name":"Damenturnverein Ellikon A/thur",
    "wof:placetype":"venue"
},
  "geometry": {"coordinates":[8.7304792404,47.5873298645],"type":"Point"}
}