{
  "type": "Feature",
  "properties": {
    "iso:country":"CH",
    "sg:address":"Z\u00fcrcherstrasse 15",
    "sg:city":"Oberengstringen",
    "sg:orig_category":"RESTAURANTS: TEA-ROOMS",
    "sg:phone":"+41 17505716",
    "sg:postcode":"8102",
    "sg:province":"Z\u00fcrich",
    "wof:name":"Mia's Traditional Cuisine Mtc, Take Away, Acena",
    "wof:placetype":"venue"
},
  "geometry": {"coordinates":[8.4757471085,47.4052429199],"type":"Point"}
}