{
  "type": "Feature",
  "properties": {
    "iso:country":"CH",
    "sg:address":"14 Chemin Rieu 1211",
    "sg:city":"Geneva",
    "sg:classifiers":[
        {
            "category":"Industrial Area",
            "type":"Public Place"
        }
    ],
    "sg:phone":"+41 22 709 21 11",
    "sg:postcode":"17",
    "sg:tags":[
        "large",
        "private"
    ],
    "wof:name":"Lombard Odier Darier Hentsch",
    "wof:placetype":"venue"
},
  "geometry": {"coordinates":[6.143584,46.202621],"type":"Point"}
}