{
  "type": "Feature",
  "properties": {
    "iso:country":"CH",
    "sg:address":"Grammetstrasse 14",
    "sg:city":"Liestal",
    "sg:orig_category":"Unclassifiable Establishments",
    "sg:postcode":"4410",
    "sg:province":"Basel-Landschaft",
    "wof:name":"Rudin Immobilien",
    "wof:placetype":"venue"
},
  "geometry": {"coordinates":[7.7481250763,47.4784355164],"type":"Point"}
}