{
  "type": "Feature",
  "properties": {
    "iso:country":"CH",
    "sg:address":"1450",
    "sg:city":"Ste-croix",
    "sg:orig_category":"Sonstiges Versicherungsgewerbe",
    "sg:phone":"+41 71 228 34 34",
    "sg:postcode":"1450",
    "sg:province":"Vaud",
    "wof:name":"La Suisse Versicherungen, Generalagentur Mitterer Guido",
    "wof:placetype":"venue"
},
  "geometry": {"coordinates":[9.3733549118,47.4235572815],"type":"Point"}
}