{
  "type": "Feature",
  "properties": {
    "iso:country":"CH",
    "sg:address":"1906",
    "sg:city":"Charrat",
    "sg:orig_category":"Grosshandel mit Getr\u00e4nken",
    "sg:phone":"+41 31 333 08 07",
    "sg:postcode":"1906",
    "sg:province":"Valais",
    "wof:name":"Mabillard Raphy.",
    "wof:placetype":"venue"
},
  "geometry": {"coordinates":[7.1296892166,46.1249885559],"type":"Point"}
}