{
  "type": "Feature",
  "properties": {
    "iso:country":"CH",
    "sg:address":"Sumpfstrasse 26 6312 Steinhausen. Postfach",
    "sg:city":"Steinhausen",
    "sg:orig_category":"Herstellung von sonstigen Erzeugnissen",
    "sg:postcode":"6312",
    "sg:province":"Zug",
    "wof:name":"Dusk Switzerland Ag",
    "wof:placetype":"venue"
},
  "geometry": {"coordinates":[8.4870157242,47.1867179871],"type":"Point"}
}