{
  "type": "Feature",
  "properties": {
    "iso:country":"CH",
    "sg:address":"R\u00e4tenberg 952",
    "sg:city":"Niederb\u00fcren",
    "sg:orig_category":"Haltung von Rindern",
    "sg:postcode":"9246",
    "sg:province":"St. Gallen",
    "wof:name":"Burg Viehzucht Ag",
    "wof:placetype":"venue"
},
  "geometry": {"coordinates":[9.203909874,47.4610290527],"type":"Point"}
}