{
  "type": "Feature",
  "properties": {
    "iso:country":"CH",
    "sg:address":"Stallikerstrasse 20",
    "sg:city":"Bonstetten",
    "sg:orig_category":"Detailhandel mit Blumen U Pflanzen Fachdetailhandel in Verkaufsr\u00e4umen",
    "sg:phone":"+41 17002794",
    "sg:postcode":"8906",
    "sg:province":"Z\u00fcrich",
    "wof:name":"Blumeegge Bissig",
    "wof:placetype":"venue"
},
  "geometry": {"coordinates":[8.472503,47.325794],"type":"Point"}
}