{
  "type": "Feature",
  "properties": {
    "iso:country":"CH",
    "sg:address":"Bruderholzstrasse 17",
    "sg:city":"Binningen",
    "sg:orig_category":"Handelsvermittlung von Brennstoffen, Erzen, Metallen U Chemikalien",
    "sg:phone":"+41 61 421 57 21",
    "sg:postcode":"4102",
    "sg:province":"Basel-Landschaft",
    "wof:name":"Solarmetall Handels Ag",
    "wof:placetype":"venue"
},
  "geometry": {"coordinates":[7.5768852234,47.5375823975],"type":"Point"}
}