{
  "type": "Feature",
  "properties": {
    "iso:country":"CH",
    "sg:address":"Bernstrasse 8",
    "sg:city":"Oberwichtrach",
    "sg:orig_category":"Zimmerei, Dachdeckerei, Bauspenglerei U Abdichtung Zimmerei, Ingenieurholzbau",
    "sg:phone":"+41 31 781 15 76",
    "sg:postcode":"3114",
    "sg:province":"Bern",
    "wof:name":"Kohler & M\u00fcller, Holzbau",
    "wof:placetype":"venue"
},
  "geometry": {"coordinates":[7.5767550468,46.8455886841],"type":"Point"}
}