{
  "type": "Feature",
  "properties": {
    "iso:country":"CH",
    "sg:address":"Unterer R\u00fctschetenweg 49",
    "sg:city":"Pratteln",
    "sg:orig_category":"Fahrschulen, Flugschulen",
    "sg:phone":"+41 79 210 36 36",
    "sg:postcode":"4133",
    "sg:province":"Basel-Landschaft",
    "wof:name":"Werner Koch Autofahrschule",
    "wof:placetype":"venue"
},
  "geometry": {"coordinates":[7.6812520027,47.5173072815],"type":"Point"}
}