{
  "type": "Feature",
  "properties": {
    "iso:country":"CH",
    "sg:address":"Loretostrasse 52 Postfach 261",
    "sg:city":"Lichtensteig",
    "sg:classifiers":[
        {
            "category":"Bakery",
            "type":"Food & Drink"
        }
    ],
    "sg:phone":"+41 41 870 22 06",
    "sg:postcode":"9620",
    "sg:province":"St. Gallen",
    "sg:tags":[
        "cake",
        "product",
        "related",
        "bread"
    ],
    "wof:name":"Lehn Beck Ag",
    "wof:placetype":"venue"
},
  "geometry": {"coordinates":[8.65083,46.871815],"type":"Point"}
}