{
  "type": "Feature",
  "properties": {
    "iso:country":"CH",
    "sg:address":"Sentier De La Contr\u00e9e",
    "sg:city":"Veyras",
    "sg:orig_category":"G\u00fcterbef\u00f6rderung im Strassenverkehr",
    "sg:phone":"+41 27 455 12 06",
    "sg:postcode":"3968",
    "sg:province":"Valais",
    "wof:name":"Marcel Gaillard Entreprise De Transports",
    "wof:placetype":"venue"
},
  "geometry": {"coordinates":[7.5355248451,46.3026771545],"type":"Point"}
}