{
  "type": "Feature",
  "properties": {
    "addr:full":"Industriestrasse 19 Appenzell Appenzell Innerhoden 9050",
    "addr:housenumber":"19",
    "addr:postcode":"9050",
    "addr:street":"Industriestrasse",
    "iso:country":"CH",
    "sg:address":"Industriestrasse 19",
    "sg:city":"Appenzell",
    "sg:orig_category":"Plastic Constructions",
    "sg:phone":"+41 22 796 28 97",
    "sg:postcode":"9050",
    "sg:province":"Appenzell Innerhoden",
    "wof:name":"Freddy Lecoultre Travail \u00e0 Fa\u00e7on",
    "wof:placetype":"venue"
},
  "geometry": {"coordinates":[6.098924,46.207272],"type":"Point"}
}