{
  "type": "Feature",
  "properties": {
    "iso:country":"CH",
    "sg:address":"August Keller-strasse 22",
    "sg:city":"Lenzburg",
    "sg:orig_category":"Detailhandel mit Brillen U anderen Sehhilfen Detailhandel mit medizinischen U orthop\u00e4dischen Artikel",
    "sg:phone":"+41 62 885 40 60",
    "sg:postcode":"5600",
    "sg:province":"Aargau",
    "wof:name":"Aare-h\u00f6rzentralen Ag",
    "wof:placetype":"venue"
},
  "geometry": {"coordinates":[8.170711,47.389042],"type":"Point"}
}