{
  "type": "Feature",
  "properties": {
    "iso:country":"CH",
    "sg:address":"3663",
    "sg:city":"Gurzelen",
    "sg:orig_category":"Vereine Damen Vereine Gesang",
    "sg:phone":"+41 33 345 16 56",
    "sg:postcode":"3663",
    "sg:province":"Bern",
    "wof:name":"Frauenchor Gurzelen",
    "wof:placetype":"venue"
},
  "geometry": {"coordinates":[7.5350899696,46.772819519],"type":"Point"}
}