{
  "type": "Feature",
  "properties": {
    "iso:country":"CH",
    "sg:address":"Bahnhofstrasse 13",
    "sg:city":"Pf\u00e4ffikon",
    "sg:classifiers":[
        {
            "category":"Professional",
            "subcategory":"Detective & Security Services",
            "type":"Services"
        }
    ],
    "sg:phone":"+41 55 420 39 49",
    "sg:postcode":"8808",
    "sg:province":"Schwyz",
    "sg:tags":[
        "back-up",
        "data"
    ],
    "wof:name":"Software System Solutions Gmbh",
    "wof:placetype":"venue"
},
  "geometry": {"coordinates":[8.778427,47.202431],"type":"Point"}
}