{
  "type": "Feature",
  "properties": {
    "iso:country":"CH",
    "sg:address":"Sonnenplatz 4 6020 Emmenbr\u00fccke. Postfach",
    "sg:city":"Emmenbr\u00fccke",
    "sg:orig_category":"Unternehmensberatung",
    "sg:phone":"+41 41 260 85 05",
    "sg:postcode":"6020",
    "sg:province":"Luzern",
    "wof:name":"Gubser Rolf Edwin Krisen Und Personalmanagement F\u00fcr Einzelpersonen Und Unternehmungen",
    "wof:placetype":"venue"
},
  "geometry": {"coordinates":[8.2753295898,47.0780105591],"type":"Point"}
}