{
  "type": "Feature",
  "properties": {
    "iso:country":"CH",
    "sg:address":"Ritter-weg 8",
    "sg:city":"Biel/bienne",
    "sg:orig_category":"Herstellung von sonstigen Maschinen f\u00fcr unspezifische Verwendung",
    "sg:phone":"+41 32 345 14 92",
    "sg:postcode":"2502",
    "sg:province":"Bern",
    "wof:name":"Walpen Kuvertzuf\u00fchr-maschinen Superfeeder",
    "wof:placetype":"venue"
},
  "geometry": {"coordinates":[7.252204895,47.1398124695],"type":"Point"}
}