{
  "type": "Feature",
  "properties": {
    "iso:country":"CH",
    "sg:address":"Oberhofen 8488 Turbenthal. Postfach",
    "sg:city":"Turbenthal",
    "sg:orig_category":"Grosshandel mit Blumen U Pflanzen",
    "sg:postcode":"8488",
    "sg:province":"Z\u00fcrich",
    "wof:name":"Tropetopf Gmbh",
    "wof:placetype":"venue"
},
  "geometry": {"coordinates":[8.847366333,47.4357910156],"type":"Point"}
}