{
  "type": "Feature",
  "properties": {
    "iso:country":"CH",
    "sg:address":"Hauptgasse 1",
    "sg:city":"Solothurn",
    "sg:orig_category":"Detailhandel mit Beleuchtungs U Haushaltsgegenst\u00e4nden Detailhandel mit elektrischen Haushalts-,Radio",
    "sg:phone":"+41 32 622 63 64",
    "sg:postcode":"4500",
    "sg:province":"Solothurn",
    "wof:name":"Chuchilade Wagmann Christine",
    "wof:placetype":"venue"
},
  "geometry": {"coordinates":[7.535448,47.206547],"type":"Point"}
}