{
  "type": "Feature",
  "properties": {
    "iso:country":"CH",
    "sg:address":"General Wille-strasse 18 8000 Z\u00fcrich. Postfach",
    "sg:city":"Z\u00fcrich",
    "sg:orig_category":"RESTAURANTS: TEA-ROOMS",
    "sg:postcode":"8001",
    "sg:province":"Z\u00fcrich",
    "wof:name":"Remund Bensaid & Bensaid, Tifo Caf\u00e9 Bistro",
    "wof:placetype":"venue"
},
  "geometry": {"coordinates":[8.5324144363,47.3637733459],"type":"Point"}
}