{
  "type": "Feature",
  "properties": {
    "iso:country":"CH",
    "sg:address":"Landstrasse 48 5430 Wettingen. Postfach 3112",
    "sg:city":"Wettingen",
    "sg:orig_category":"Detailhandel mit Bekleidung",
    "sg:phone":"+41 56 426 66 74",
    "sg:postcode":"5430",
    "sg:province":"Aargau",
    "wof:name":"Kleider M\u00fcller",
    "wof:placetype":"venue"
},
  "geometry": {"coordinates":[8.321538,47.467953],"type":"Point"}
}