{
  "type": "Feature",
  "properties": {
    "iso:country":"CH",
    "sg:address":"Sch\u00f6neggstrasse 30",
    "sg:city":"Neuhausen",
    "sg:orig_category":"Tierarztpraxis",
    "sg:phone":"+41 71 245 33 14",
    "sg:postcode":"8212",
    "sg:province":"Schaffhausen",
    "wof:name":"Dr. Med. Vet. Oskar Z\u00fcrrer Tierarzt",
    "wof:placetype":"venue"
},
  "geometry": {"coordinates":[9.3892736435,47.4395675659],"type":"Point"}
}