{
  "type": "Feature",
  "properties": {
    "iso:country":"CH",
    "sg:address":"Rue Du Borgeaud 10",
    "sg:city":"Gland",
    "sg:orig_category":"Benzin, Heiz\u00f6l and Mineral\u00f6lprodukte Grosshandel Detailhandel mit Brennstoffen U Heizmaterial",
    "sg:postcode":"1196",
    "sg:province":"Vaud",
    "wof:name":"Deville-mazout S\u00e0rl",
    "wof:placetype":"venue"
},
  "geometry": {"coordinates":[6.262065,46.423546],"type":"Point"}
}