{
  "type": "Feature",
  "properties": {
    "iso:country":"CH",
    "sg:address":"Chemin Du Pont 5",
    "sg:city":"Perly",
    "sg:orig_category":"Druck ohne Zeitungsdruck Offsetdruck",
    "sg:phone":"+41 22 771 23 23",
    "sg:postcode":"1258",
    "sg:province":"Gen\u00e8ve",
    "wof:name":"Ripari Georges",
    "wof:placetype":"venue"
},
  "geometry": {"coordinates":[6.0806207657,46.1539840698],"type":"Point"}
}