{
  "type": "Feature",
  "properties": {
    "iso:country":"CH",
    "sg:address":"Herbstweg 18 8050 Z\u00fcrich",
    "sg:city":"Zust",
    "sg:orig_category":"Druck ohne Zeitungsdruck",
    "sg:postcode":"50",
    "wof:name":"Boder Druck",
    "wof:placetype":"venue"
},
  "geometry": {"coordinates":[8.5024929047,47.4818725586],"type":"Point"}
}