{
  "type": "Feature",
  "properties": {
    "iso:country":"CH",
    "sg:address":"Nordstrasse 185",
    "sg:city":"Z\u00fcrich",
    "sg:classifiers":[
        {
            "category":"Professional",
            "subcategory":"Employment Agencies",
            "type":"Services"
        }
    ],
    "sg:phone":"+41 13628421",
    "sg:postcode":"8037",
    "sg:province":"Z\u00fcrich",
    "sg:tags":[
        "personal",
        "u",
        "stellenvermittlung"
    ],
    "wof:name":"Abs Schumacher Stellen-& Kaderselektion",
    "wof:placetype":"venue"
},
  "geometry": {"coordinates":[8.5311422348,47.3922271729],"type":"Point"}
}