{
  "type": "Feature",
  "properties": {
    "iso:country":"CH",
    "sg:address":"Chalet Bergheim",
    "sg:city":"Rosswald",
    "sg:orig_category":"Bauschreinerei",
    "sg:phone":"+41 27 923 83 89",
    "sg:postcode":"3913",
    "sg:province":"Valais",
    "wof:name":"Toni Gemmet Schreinerei",
    "wof:placetype":"venue"
},
  "geometry": {"coordinates":[8.051945,46.30468],"type":"Point"}
}