{
  "type": "Feature",
  "properties": {
    "iso:country":"CH",
    "sg:address":"Lukmaniergasse 10 7000 Chur. Postfach 27",
    "sg:city":"Chur",
    "sg:orig_category":"Vermittlung von Immobilien Wirtschaftspr\u00fcfung, Steuerberatung U Treuhand",
    "sg:phone":"+41 81 252 82 49",
    "sg:postcode":"7002",
    "sg:province":"Graubunden",
    "wof:name":"B\u00fcchele-treuhand Ag",
    "wof:placetype":"venue"
},
  "geometry": {"coordinates":[9.5327596664,46.8503913879],"type":"Point"}
}