{
  "type": "Feature",
  "properties": {
    "iso:country":"CH",
    "sg:address":"Schaffhauserstrasse 64",
    "sg:city":"Kloten",
    "sg:orig_category":"Detailhandel mit Textilien Grosshandel mit Textilien",
    "sg:phone":"+41 18132566",
    "sg:postcode":"8302",
    "sg:province":"Z\u00fcrich",
    "wof:name":"Doris J\u00f6rg, Stoffe + Wolle",
    "wof:placetype":"venue"
},
  "geometry": {"coordinates":[8.5793199539,47.4445648193],"type":"Point"}
}