{
  "type": "Feature",
  "properties": {
    "iso:country":"CH",
    "sg:address":"Bergli-wis",
    "sg:city":"Wattwil",
    "sg:orig_category":"Fahrschulen, Flugschulen",
    "sg:phone":"+41 79 601 11 30",
    "sg:postcode":"9630",
    "sg:province":"St. Gallen",
    "wof:name":"Jasmin Ziegler Autofahrschule",
    "wof:placetype":"venue"
},
  "geometry": {"coordinates":[9.0876150131,47.3101387024],"type":"Point"}
}