{
  "type": "Feature",
  "properties": {
    "iso:country":"CH",
    "sg:address":"Dossello Via 15a",
    "sg:city":"Coldrerio",
    "sg:orig_category":"Detailhandel mit elektrischen Haushalts-,Radio U Fernsehger\u00e4ten sowie Musikinstrumenten",
    "sg:postcode":"6877",
    "sg:province":"Ticino",
    "wof:name":"Audio Otto Ottorino Cavadini",
    "wof:placetype":"venue"
},
  "geometry": {"coordinates":[8.9948301315,45.8562316895],"type":"Point"}
}