{
  "type": "Feature",
  "properties": {
    "addr:full":"Zypressenstrasse 56 8004 Z\u00fcrich. Postfach Z\u00fcrich Z\u00fcrich 8026",
    "addr:housenumber":"56",
    "addr:postcode":"8004 zuerich. postfach;8026",
    "addr:street":"Zypressenstrasse",
    "iso:country":"CH",
    "sg:address":"Zypressenstrasse 56 8004 Z\u00fcrich. Postfach",
    "sg:city":"Z\u00fcrich",
    "sg:classifiers":[
        {
            "category":"Bars & Pubs",
            "type":"Food & Drink"
        }
    ],
    "sg:postcode":"8026",
    "sg:province":"Z\u00fcrich",
    "wof:name":"Gastro 2011 Gmbh",
    "wof:placetype":"venue"
},
  "geometry": {"coordinates":[8.513527,47.377647],"type":"Point"}
}