{
  "type": "Feature",
  "properties": {
    "iso:country":"CH",
    "sg:address":"Goldregenweg 11",
    "sg:city":"Z\u00fcrich",
    "sg:orig_category":"Vereine Stenographen",
    "sg:phone":"+41 13124389",
    "sg:postcode":"8050",
    "sg:province":"Z\u00fcrich",
    "wof:name":"Arbeiter-stenografen",
    "wof:placetype":"venue"
},
  "geometry": {"coordinates":[8.5323209763,47.4083747864],"type":"Point"}
}