{
  "type": "Feature",
  "properties": {
    "iso:country":"CH",
    "sg:address":"Lindenweg 1",
    "sg:city":"Turbenthal",
    "sg:orig_category":"Hardwareberatung",
    "sg:postcode":"8488",
    "sg:province":"Z\u00fcrich",
    "wof:name":"Pc Helpcom, Edv-computer Dienstleistung Aller Art, Vukomanovic Vlado",
    "wof:placetype":"venue"
},
  "geometry": {"coordinates":[8.7237882614,47.2662887573],"type":"Point"}
}