{
  "type": "Feature",
  "properties": {
    "iso:country":"CH",
    "sg:address":"3965",
    "sg:city":"Chippis",
    "sg:orig_category":"Giessereiindustrie Herstellung von Metallerzeugnissen ohne Maschinenbau",
    "sg:phone":"+41 71 633 24 20",
    "sg:postcode":"3965",
    "sg:province":"Valais",
    "wof:name":"Algisa Ag, 8575 B\u00fcrglen",
    "wof:placetype":"venue"
},
  "geometry": {"coordinates":[9.1484422684,47.5487518311],"type":"Point"}
}