{
  "type": "Feature",
  "properties": {
    "iso:country":"CH",
    "sg:address":"Goldbrunnenstrasse 73",
    "sg:city":"Z\u00fcrich",
    "sg:orig_category":"Interessenvertretungen",
    "sg:postcode":"8055",
    "sg:province":"Z\u00fcrich",
    "wof:name":"F\u00fcrsorgestiftung Der Freimaurerloge Aurora Humanitatis, Z\u00fcrich",
    "wof:placetype":"venue"
},
  "geometry": {"coordinates":[8.5151090622,47.3684082031],"type":"Point"}
}