{
  "type": "Feature",
  "properties": {
    "iso:country":"CH",
    "sg:address":"Zugerstrasse 74 6340 Baar. Postfach 657",
    "sg:city":"Baar",
    "sg:orig_category":"Werbeberatung",
    "sg:postcode":"6341",
    "sg:province":"Zug",
    "wof:name":"Cr\u00e9avision Guido Capecchi",
    "wof:placetype":"venue"
},
  "geometry": {"coordinates":[8.5197763443,47.1836051941],"type":"Point"}
}