{
  "type": "Feature",
  "properties": {
    "iso:country":"CH",
    "sg:address":"Erlibergstrasse 9",
    "sg:city":"Unter\u00e4geri",
    "sg:orig_category":"Elektroinstallation",
    "sg:phone":"+41 41 750 55 74",
    "sg:postcode":"6314",
    "sg:province":"Zug",
    "wof:name":"Ats Approvals Technical-services Ag",
    "wof:placetype":"venue"
},
  "geometry": {"coordinates":[8.5970458984,47.1386909485],"type":"Point"}
}