{
  "type": "Feature",
  "properties": {
    "iso:country":"CH",
    "sg:address":"Rue Du M\u00f4le 36",
    "sg:city":"Gen\u00e8ve",
    "sg:orig_category":"Kosmetikinstitute",
    "sg:phone":"+41 22 731 39 08",
    "sg:postcode":"1201",
    "sg:province":"Gen\u00e8ve",
    "wof:name":"Marlyse Scheiben Institut De Beaut\u00e9",
    "wof:placetype":"venue"
},
  "geometry": {"coordinates":[6.146999836,46.2131958008],"type":"Point"}
}