{
  "type": "Feature",
  "properties": {
    "iso:country":"CH",
    "sg:address":"B\u00e4lliz 13",
    "sg:city":"Thun",
    "sg:orig_category":"Architekturb\u00fcros",
    "sg:phone":"+41 33 222 32 19",
    "sg:postcode":"3600",
    "sg:province":"Bern",
    "wof:name":"Straubhaar Architekten Htl",
    "wof:placetype":"venue"
},
  "geometry": {"coordinates":[7.627025,46.759392],"type":"Point"}
}