{
  "type": "Feature",
  "properties": {
    "iso:country":"CH",
    "sg:address":"Fabrikstrasse 1",
    "sg:city":"Lengnau",
    "sg:classifiers":[
        {
            "category":"Shopping",
            "subcategory":"Crafts & Fabrics",
            "type":"Retail Goods"
        }
    ],
    "sg:phone":"+41 52 741 27 28",
    "sg:postcode":"2543",
    "sg:province":"Bern",
    "sg:tags":[
        "nappy"
    ],
    "wof:name":"Kiosk Charregass",
    "wof:placetype":"venue"
},
  "geometry": {"coordinates":[8.8610582352,47.6591644287],"type":"Point"}
}