{
  "type": "Feature",
  "properties": {
    "iso:country":"CH",
    "sg:address":"Bains Rue Des 65",
    "sg:city":"Gen\u00e8ve",
    "sg:orig_category":"RESTAURANTS: TEA-ROOMS",
    "sg:phone":"+41 71 222 76 74",
    "sg:postcode":"1205",
    "sg:province":"Gen\u00e8ve",
    "wof:name":"Lama's Tandoori Indian-restaurant",
    "wof:placetype":"venue"
},
  "geometry": {"coordinates":[9.3727407455,47.4217338562],"type":"Point"}
}