{
  "type": "Feature",
  "properties": {
    "iso:country":"CH",
    "sg:address":"Moosgasse 77 3305 Iffwil. Postfach",
    "sg:city":"Iffwil",
    "sg:orig_category":"Wirtschaftspr\u00fcfung, Steuerberatung U Treuhand",
    "sg:phone":"+41 31 761 31 53",
    "sg:postcode":"3305",
    "sg:province":"Bern",
    "wof:name":"Treuhand Und Beratung K\u00f6nig Andreas",
    "wof:placetype":"venue"
},
  "geometry": {"coordinates":[7.4780440331,47.064491272],"type":"Point"}
}