{
  "type": "Feature",
  "properties": {
    "iso:country":"CH",
    "sg:address":"Rosengartenstrasse 1a 8037 Z\u00fcrich. Postfach",
    "sg:city":"Z\u00fcrich",
    "sg:orig_category":"Unclassifiable Establishments",
    "sg:postcode":"8037",
    "sg:province":"Z\u00fcrich",
    "wof:name":"Projectteam Cavin, Pilar & Rivas",
    "wof:placetype":"venue"
},
  "geometry": {"coordinates":[6.5951161385,46.5269317627],"type":"Point"}
}