{
  "type": "Feature",
  "properties": {
    "addr:full":"Gibelinstrasse 13 Solothurn Solothurn 4500",
    "addr:housenumber":"13",
    "addr:postcode":"4500",
    "addr:street":"Gibelinstrasse",
    "iso:country":"CH",
    "sg:address":"Gibelinstrasse 13",
    "sg:city":"Solothurn",
    "sg:orig_category":"Allgemeiner Hoch U Tiefbau",
    "sg:phone":"+41 81 868 56 58",
    "sg:postcode":"4500",
    "sg:province":"Solothurn",
    "wof:name":"Zeblas Bau Ag Samnaun",
    "wof:placetype":"venue"
},
  "geometry": {"coordinates":[10.37101,46.944328],"type":"Point"}
}