{
  "type": "Feature",
  "properties": {
    "iso:country":"CH",
    "sg:address":"Hauptstrasse 10",
    "sg:city":"Hemmental",
    "sg:classifiers":[
        {
            "category":"Restaurant",
            "type":"Food & Drink"
        }
    ],
    "sg:phone":"+41 52 685 40 25",
    "sg:postcode":"8231",
    "sg:province":"Schaffhausen",
    "wof:name":"Restaurant Frieden",
    "wof:placetype":"venue"
},
  "geometry": {"coordinates":[8.5820379257,47.7338485718],"type":"Point"}
}