{
  "type": "Feature",
  "properties": {
    "iso:country":"CH",
    "sg:address":"Gl\u00e4rnischweg Hintergoldingen",
    "sg:city":"Goldingen",
    "sg:orig_category":"Sportvereine Sch\u00fctzen",
    "sg:postcode":"8638",
    "sg:province":"St. Gallen",
    "wof:name":"Milit\u00e4rsch\u00fctzenverein Uznach",
    "wof:placetype":"venue"
},
  "geometry": {"coordinates":[8.9639005661,47.2631149292],"type":"Point"}
}