{
  "type": "Feature",
  "properties": {
    "iso:country":"CH",
    "sg:address":"Ch. Rey 13 1282 Dardagny. Postfach",
    "sg:city":"Dardagny",
    "sg:orig_category":"Herstellung von k\u00e4lte U lufttechnischen Erzeugnissen f\u00fcr gewerbliche Zwecke",
    "sg:postcode":"1282",
    "wof:name":"Beck J.-p.",
    "wof:placetype":"venue"
},
  "geometry": {"coordinates":[8.2241401672,46.8130912781],"type":"Point"}
}