{
  "type": "Feature",
  "properties": {
    "iso:country":"CH",
    "sg:address":"Route Du Mandement 140 1242 Satigny. Postfach",
    "sg:city":"Satigny",
    "sg:orig_category":"Grosshandel mit Getr\u00e4nken Rebbau",
    "sg:phone":"+41 22 752 15 33",
    "sg:postcode":"1242",
    "sg:province":"Gen\u00e8ve",
    "wof:name":"La Cave De Gen\u00e8ve Sa",
    "wof:placetype":"venue"
},
  "geometry": {"coordinates":[6.0326189995,46.2150306702],"type":"Point"}
}