{
  "type": "Feature",
  "properties": {
    "iso:country":"CH",
    "sg:address":"Route Des Paccots",
    "sg:city":"Ch\u00e2tel-st-denis",
    "sg:orig_category":"Herstellung von sonstigen landwirtschaftlichen Maschinen",
    "sg:postcode":"1618",
    "sg:province":"Fribourg",
    "wof:name":"Liaudat D. Mat\u00e9riel Forestier",
    "wof:placetype":"venue"
},
  "geometry": {"coordinates":[6.9188947678,46.5245399475],"type":"Point"}
}