{
  "type": "Feature",
  "properties": {
    "iso:country":"CH",
    "sg:address":"Hofwiesenstrasse 20",
    "sg:city":"R\u00fcmlang",
    "sg:orig_category":"Herstellung von sonstigen elektrischen Ausr\u00fcstungen",
    "sg:phone":"+41 18171122",
    "sg:postcode":"8153",
    "sg:province":"Z\u00fcrich",
    "wof:name":"Preswiss Gmbh",
    "wof:placetype":"venue"
},
  "geometry": {"coordinates":[8.5363788605,47.4529190063],"type":"Point"}
}