{
  "type": "Feature",
  "properties": {
    "iso:country":"CH",
    "sg:address":"Bahnhofstrasse 1",
    "sg:city":"Lyss",
    "sg:orig_category":"Sonstiges Versicherungsgewerbe",
    "sg:phone":"+41 32 387 45 45",
    "sg:postcode":"3250",
    "sg:province":"Bern",
    "wof:name":"Schweizerische Mobiliar Versicherungsgesellschaft, Generalagentur Lyss, Hadorn Ulrich",
    "wof:placetype":"venue"
},
  "geometry": {"coordinates":[7.306178093,47.0748596191],"type":"Point"}
}