{
  "type": "Feature",
  "properties": {
    "iso:country":"CH",
    "sg:address":"6170",
    "sg:city":"Sch\u00fcpfheim",
    "sg:orig_category":"Vereine Gesang",
    "sg:postcode":"6170",
    "sg:province":"Luzern",
    "wof:name":"C\u00e4cilienverein",
    "wof:placetype":"venue"
},
  "geometry": {"coordinates":[8.0194749832,46.9536094666],"type":"Point"}
}