{
  "type": "Feature",
  "properties": {
    "iso:country":"CH",
    "sg:address":"Beaumont Route De 20 1700 Fribourg. Postfach",
    "sg:city":"Freiburg",
    "sg:orig_category":"Softwareentwicklung U beratung",
    "sg:postcode":"1700",
    "sg:province":"Fribourg",
    "wof:name":"Invescons Sa",
    "wof:placetype":"venue"
},
  "geometry": {"coordinates":[7.1406259537,46.796672821],"type":"Point"}
}