{
  "type": "Feature",
  "properties": {
    "iso:country":"CH",
    "sg:address":"B\u00e4renfelserstrasse 21",
    "sg:city":"Basel",
    "sg:orig_category":"Grosshandel mit Erzen U Metallen",
    "sg:phone":"+41 61 692 14 86",
    "sg:postcode":"4057",
    "sg:province":"Basel-Stadt",
    "wof:name":"Knoblauch M\u00f6b.-hausbeschl\u00e4ge W.l\u00fcchinger",
    "wof:placetype":"venue"
},
  "geometry": {"coordinates":[7.5876111984,47.5670280457],"type":"Point"}
}