{
  "type": "Feature",
  "properties": {
    "iso:country":"CH",
    "sg:address":"Pflugstrasse 4",
    "sg:city":"Schlieren",
    "sg:orig_category":"Sportvereine Ballsport Handball",
    "sg:phone":"+41 17307536",
    "sg:postcode":"8952",
    "sg:province":"Z\u00fcrich",
    "wof:name":"Hbs-tv Schlieren",
    "wof:placetype":"venue"
},
  "geometry": {"coordinates":[8.4337806702,47.3962860107],"type":"Point"}
}