{
  "type": "Feature",
  "properties": {
    "iso:country":"CH",
    "sg:address":"Schwelle 603",
    "sg:city":"Eggiwil",
    "sg:orig_category":"Werbung",
    "sg:phone":"+41 34 491 17 58",
    "sg:postcode":"3537",
    "sg:province":"Bern",
    "wof:name":"Zaugg-siegenthaler",
    "wof:placetype":"venue"
},
  "geometry": {"coordinates":[7.789935112,46.8806648254],"type":"Point"}
}