{
  "type": "Feature",
  "properties": {
    "iso:country":"CH",
    "sg:address":"Holenbachstrasse 21 8105 Regensdorf. Postfach",
    "sg:city":"Regensdorf",
    "sg:orig_category":"Finanzierungsinstitutionen",
    "sg:phone":"+41 18701427",
    "sg:postcode":"8105",
    "sg:province":"Z\u00fcrich",
    "wof:name":"V\u00f6hringer Finanz Consulting Beratung Im Allfinanzbereich. Finanzdienstleistungsservice",
    "wof:placetype":"venue"
},
  "geometry": {"coordinates":[8.4608469009,47.4308052063],"type":"Point"}
}