{
  "type": "Feature",
  "properties": {
    "iso:country":"CH",
    "sg:address":"Altstadtgasse 7 6210 Sursee. Postfach",
    "sg:city":"Sursee",
    "sg:orig_category":"Architektur U Ingenieurb\u00fcros",
    "sg:postcode":"6210",
    "sg:province":"Luzern",
    "wof:name":"Top Service Bau Gmbh",
    "wof:placetype":"venue"
},
  "geometry": {"coordinates":[8.109932,47.171871],"type":"Point"}
}