{
  "type": "Feature",
  "properties": {
    "iso:country":"CH",
    "sg:address":"Reuchenettestrasse 19",
    "sg:city":"Biel/bienne",
    "sg:orig_category":"Herstellung U Zusammensetzung von Uhren Herstellung von Uhren",
    "sg:phone":"+41 32 342 34 21",
    "sg:postcode":"2502",
    "sg:province":"Bern",
    "wof:name":"Fabrique Des Montres Milus, Paul Junod Sa",
    "wof:placetype":"venue"
},
  "geometry": {"coordinates":[7.2538280487,47.1473312378],"type":"Point"}
}