{
  "type": "Feature",
  "properties": {
    "iso:country":"CH",
    "sg:address":"Dorfstrasse 37 8873 Amden. Postfach 10",
    "sg:city":"Amden",
    "sg:classifiers":[
        {
            "category":"Travel",
            "subcategory":"Hotels & Motels",
            "type":"Entertainment"
        }
    ],
    "sg:postcode":"8873",
    "sg:province":"St. Gallen",
    "sg:tags":[
        "hotels",
        "mit",
        "restaurant"
    ],
    "wof:name":"Eberl\u00e9 Ulrike",
    "wof:placetype":"venue"
},
  "geometry": {"coordinates":[6.3947701454,48.0577583313],"type":"Point"}
}