{
  "type": "Feature",
  "properties": {
    "iso:country":"CH",
    "sg:address":"Rheinstrasse 85",
    "sg:city":"Widnau",
    "sg:orig_category":"Zoll- and Grenzb\u00fcros",
    "sg:phone":"+41 71 722 21 26",
    "sg:postcode":"9443",
    "sg:province":"St. Gallen",
    "wof:name":"Zollamt Widnau",
    "wof:placetype":"venue"
},
  "geometry": {"coordinates":[9.6504878998,47.4088630676],"type":"Point"}
}