{
  "type": "Feature",
  "properties": {
    "iso:country":"CH",
    "sg:address":"Landstrasse 12",
    "sg:city":"W\u00e4ngi",
    "sg:orig_category":"Herstellung von elektrischen Lampen U Leuchten",
    "sg:postcode":"9545",
    "sg:province":"Thurgau",
    "wof:name":"Bluemax, Balmer Event Technics",
    "wof:placetype":"venue"
},
  "geometry": {"coordinates":[7.8931908607,46.7000427246],"type":"Point"}
}