{
  "type": "Feature",
  "properties": {
    "iso:country":"CH",
    "sg:address":"Rue De La Gare 6 1860 Aigle Case Postale 338",
    "sg:city":"Aigle",
    "sg:orig_category":"Zahnarztpraxen",
    "sg:phone":"+41 24 466 48 92",
    "sg:postcode":"1860",
    "sg:province":"Vaud",
    "wof:name":"Dr M\u00e9d. Dent. Josu\u00e9 Esteve M\u00e9decin-dentiste",
    "wof:placetype":"venue"
},
  "geometry": {"coordinates":[6.9678168297,46.3180885315],"type":"Point"}
}