{
  "type": "Feature",
  "properties": {
    "iso:country":"CH",
    "sg:address":"Bruderholzallee 42 4059 Basel. Postfach",
    "sg:city":"Basel",
    "sg:orig_category":"RESTAURANTS: TEA-ROOMS",
    "sg:phone":"+41 61 361 82 22",
    "sg:postcode":"4051",
    "sg:province":"Basel-Stadt",
    "wof:name":"Hans Stucki Restaurant.",
    "wof:placetype":"venue"
},
  "geometry": {"coordinates":[7.5872020721,47.5336837769],"type":"Point"}
}