{
  "type": "Feature",
  "properties": {
    "iso:country":"CH",
    "sg:address":"1905",
    "sg:city":"Dor\u00e9naz",
    "sg:orig_category":"Unclassifiable Establishments",
    "sg:phone":"+41 27 785 15 28",
    "sg:postcode":"1905",
    "sg:province":"Valais",
    "wof:name":"Jordan Jean-marc",
    "wof:placetype":"venue"
},
  "geometry": {"coordinates":[7.0422902107,46.1487998962],"type":"Point"}
}