{
  "type": "Feature",
  "properties": {
    "iso:country":"CH",
    "sg:address":"Via Pessina 8",
    "sg:city":"Lugano",
    "sg:orig_category":"Grosshandel mit medizinischen U orthop\u00e4dischen Artikeln Herstellung von medizinischen U chirurgische",
    "sg:phone":"+41 55 451 71 11",
    "sg:postcode":"6900",
    "sg:province":"Ticino",
    "wof:name":"Allergan Ag",
    "wof:placetype":"venue"
},
  "geometry": {"coordinates":[8.8623628616,47.1888160706],"type":"Point"}
}