{
  "type": "Feature",
  "properties": {
    "iso:country":"CH",
    "sg:address":"Bottigenstrasse 243 3019 Bern. Postfach",
    "sg:city":"Bern",
    "sg:orig_category":"Unclassifiable Establishments",
    "sg:postcode":"3019",
    "sg:province":"Bern",
    "wof:name":"Abschleppdienst Koch",
    "wof:placetype":"venue"
},
  "geometry": {"coordinates":[7.356967926,46.9357757568],"type":"Point"}
}