{
  "type": "Feature",
  "properties": {
    "iso:country":"CH",
    "sg:address":"Le Poyet 1170 Aubonne Case Postale 28",
    "sg:city":"Aubonne",
    "sg:orig_category":"Herstellung der Ausstattung von Uhren Herstellung von Metallerzeugnissen ohne Maschinenbau",
    "sg:phone":"+41 21 808 50 68",
    "sg:postcode":"1170",
    "sg:province":"Vaud",
    "wof:name":"Denis Giger Fabr.de Roues D'horlogerie",
    "wof:placetype":"venue"
},
  "geometry": {"coordinates":[6.391699791,46.4952468872],"type":"Point"}
}