{
  "type": "Feature",
  "properties": {
    "iso:country":"CH",
    "sg:address":"Bahnhofstrasse 53",
    "sg:city":"Frauenfeld",
    "sg:orig_category":"RESTAURANTS: TEA-ROOMS",
    "sg:phone":"+41 52 722 41 76",
    "sg:postcode":"8500",
    "sg:province":"Thurgau",
    "wof:name":"Kebap Bar Altintas Gmbh Imbissstand, Warenhandel",
    "wof:placetype":"venue"
},
  "geometry": {"coordinates":[8.8935346603,47.556022644],"type":"Point"}
}