{
  "type": "Feature",
  "properties": {
    "iso:country":"CH",
    "sg:address":"Laubgasse 43",
    "sg:city":"Frauenfeld",
    "sg:orig_category":"Unclassifiable Establishments",
    "sg:postcode":"8500",
    "sg:province":"Thurgau",
    "wof:name":"A. K\u00fcnzle",
    "wof:placetype":"venue"
},
  "geometry": {"coordinates":[8.8896875381,47.5577697754],"type":"Point"}
}