{
  "type": "Feature",
  "properties": {
    "iso:country":"CH",
    "sg:address":"Canonica Via 11",
    "sg:city":"Lugano",
    "sg:orig_category":"Grosshandel mit Erzen U Metallen",
    "sg:phone":"+41 91 911 71 11",
    "sg:postcode":"6900",
    "sg:province":"Ticino",
    "wof:name":"Union Metals Sa, Lussemburgo, Succursale Di Lugano",
    "wof:placetype":"venue"
},
  "geometry": {"coordinates":[8.9586572647,46.0069198608],"type":"Point"}
}