{
  "type": "Feature",
  "properties": {
    "addr:full":"Rue Antoine-saladin 3b 1299 Crans-pr\u00e8s-c\u00e9ligny. Postfach Crans-pr\u00e8s-c\u00e9ligny Vaud 1299",
    "addr:housenumber":"3b",
    "addr:postcode":"1299 crans-pre\u0300s-ce\u0301ligny. postfach crans-pre\u0300s-ce\u0301ligny;1299",
    "addr:street":"Rue Antoine-Saladin",
    "iso:country":"CH",
    "sg:address":"Rue Antoine-saladin 3b 1299 Crans-pr\u00e8s-c\u00e9ligny. Postfach",
    "sg:city":"Crans-pr\u00e8s-c\u00e9ligny",
    "sg:orig_category":"Baumwollaufbereitung U spinnerei Textilfasern Grosshandel",
    "sg:phone":"+423 776 77 06",
    "sg:postcode":"1299",
    "sg:province":"Vaud",
    "wof:name":"Mambo (suisse) Sa Coton Brut Etc.; Commerce, Courtage",
    "wof:placetype":"venue"
},
  "geometry": {"coordinates":[6.205592,46.356598],"type":"Point"}
}