{
  "type": "Feature",
  "properties": {
    "addr:full":"Wildbrunnstrasse Kaltbrunn St. Gallen 8722",
    "addr:postcode":"8722",
    "addr:street":"Wildbrunnstrasse Kaltbrunn",
    "iso:country":"CH",
    "sg:address":"Wildbrunnstrasse",
    "sg:city":"Kaltbrunn",
    "sg:orig_category":"Bauschreinerei Innenausbau",
    "sg:phone":"+41 55 293 57 40",
    "sg:postcode":"8722",
    "sg:province":"St. Gallen",
    "wof:name":"Urs Moos Innenausbau K\u00fcchenbau",
    "wof:placetype":"venue"
},
  "geometry": {"coordinates":[9.009036,47.216465],"type":"Point"}
}