{
  "type": "Feature",
  "properties": {
    "iso:country":"CH",
    "sg:address":"Wolfwilerstrasse 5",
    "sg:city":"Fulenbach",
    "sg:orig_category":"Politische Parteien FDP",
    "sg:phone":"+41 32 675 12 94",
    "sg:postcode":"4629",
    "sg:province":"Solothurn",
    "wof:name":"Fdp Ortspartei Fulenbach",
    "wof:placetype":"venue"
},
  "geometry": {"coordinates":[7.828001976,47.2735671997],"type":"Point"}
}