{
  "type": "Feature",
  "properties": {
    "addr:full":"Weiherstrasse 9 Seuzach Z\u00fcrich 8472",
    "addr:housenumber":"9",
    "addr:postcode":"8472",
    "addr:street":"Weiherstrasse",
    "iso:country":"CH",
    "sg:address":"Weiherstrasse 9",
    "sg:city":"Seuzach",
    "sg:orig_category":"Allgemeiner Hochbau Herstellung von Metallkonstruktionen",
    "sg:phone":"+41 52 335 11 57",
    "sg:postcode":"8472",
    "sg:province":"Z\u00fcrich",
    "wof:name":"Frei & Breitschmid Ag Spenglerei & Fassadenbau",
    "wof:placetype":"venue"
},
  "geometry": {"coordinates":[8.732175,47.537712],"type":"Point"}
}