{
  "type": "Feature",
  "properties": {
    "iso:country":"CH",
    "sg:address":"Kanalstrasse 3 8753 Mollis. Postfach",
    "sg:city":"Mollis",
    "sg:orig_category":"Grosshandel mit Getr\u00e4nken",
    "sg:postcode":"8753",
    "sg:province":"Glarus",
    "wof:name":"Berger Ute",
    "wof:placetype":"venue"
},
  "geometry": {"coordinates":[9.0719776154,47.0954666138],"type":"Point"}
}