{
  "type": "Feature",
  "properties": {
    "iso:country":"CH",
    "sg:address":"Heidenstrasse 38",
    "sg:city":"M\u00fcnchenstein",
    "sg:orig_category":"Sportvereine Flug Aero-Club",
    "sg:phone":"+41 55 282 13 10",
    "sg:postcode":"4142",
    "sg:province":"Basel-Landschaft",
    "wof:name":"Ae.c.s.modellfluggr.rappersw.",
    "wof:placetype":"venue"
},
  "geometry": {"coordinates":[8.9172286987,47.2351646423],"type":"Point"}
}