{
  "type": "Feature",
  "properties": {
    "iso:country":"CH",
    "sg:address":"Zunacherstrasse 4",
    "sg:city":"Kriens",
    "sg:orig_category":"Kinderkrippen U horte",
    "sg:phone":"+41 41 310 64 44",
    "sg:postcode":"6010",
    "sg:province":"Luzern",
    "wof:name":"Sch\u00fcelerhuus Zunacher Tagesheim F.primarschulkinder",
    "wof:placetype":"venue"
},
  "geometry": {"coordinates":[8.2858228683,47.0327262878],"type":"Point"}
}