{
  "type": "Feature",
  "properties": {
    "iso:country":"CH",
    "sg:address":"Chemin Des Pr\u00e9lets 3 1027 Lonay. Postfach",
    "sg:city":"Lonay",
    "sg:orig_category":"Detailhandel mit elektrischen Haushalts-,Radio U Fernsehger\u00e4ten sowie Musikinstrumenten Elektroinsta",
    "sg:phone":"+41 21 801 18 48",
    "sg:postcode":"1027",
    "sg:province":"Vaud",
    "wof:name":"Sistrade S\u00e0rl Mat\u00e9riel Audiovisuel Etc.; Commerce, Distribution",
    "wof:placetype":"venue"
},
  "geometry": {"coordinates":[6.5272698402,46.529712677],"type":"Point"}
}