{
  "type": "Feature",
  "properties": {
    "iso:country":"CH",
    "sg:address":"Untere Stapfengasse 1",
    "sg:city":"Visp",
    "sg:orig_category":"Detailhandel mit Antiquit\u00e4ten U Gebrauchtwaren in Verkaufsr\u00e4umen",
    "sg:postcode":"3930",
    "sg:province":"Valais",
    "wof:name":"Antiquitaeten Gottsponer & Burgener",
    "wof:placetype":"venue"
},
  "geometry": {"coordinates":[7.881198,46.291149],"type":"Point"}
}