{
  "type": "Feature",
  "properties": {
    "addr:full":"Wallisellerstrasse 131 Opfikon Z\u00fcrich 8152",
    "addr:housenumber":"131",
    "addr:postcode":"8152",
    "addr:street":"Wallisellerstrasse",
    "iso:country":"CH",
    "sg:address":"Wallisellerstrasse 131",
    "sg:city":"Opfikon",
    "sg:orig_category":"Detailhandel mit Computern U Software Informatikschulen",
    "sg:phone":"+41 18109636",
    "sg:postcode":"8152",
    "sg:province":"Z\u00fcrich",
    "wof:name":"Briner J\u00fcrg Project Consulting",
    "wof:placetype":"venue"
},
  "geometry": {"coordinates":[8.574941,47.426571],"type":"Point"}
}