{
  "type": "Feature",
  "properties": {
    "iso:country":"CH",
    "sg:address":"Rue Du Village 74",
    "sg:city":"Vernier",
    "sg:classifiers":[
        {
            "category":"Restaurant",
            "type":"Food & Drink"
        }
    ],
    "sg:phone":"+41 22 341 02 80",
    "sg:postcode":"1214",
    "sg:province":"Gen\u00e8ve",
    "wof:name":"Cheval Blanc Caf\u00e9-restaurant Du",
    "wof:placetype":"venue"
},
  "geometry": {"coordinates":[6.0799589157,46.2121620178],"type":"Point"}
}