{
  "type": "Feature",
  "properties": {
    "iso:country":"CH",
    "sg:address":"1633",
    "sg:city":"Marsens",
    "sg:orig_category":"Non-Classified Establishments",
    "sg:postcode":"1633",
    "sg:province":"Fribourg",
    "wof:name":"Clerc-elia S\u00e0rl",
    "wof:placetype":"venue"
},
  "geometry": {"coordinates":[7.0701651573,46.7708892822],"type":"Point"}
}