{
  "type": "Feature",
  "properties": {
    "iso:country":"CH",
    "sg:address":"Temple-neuf Rue Du 4",
    "sg:city":"Neuenburg",
    "sg:orig_category":"Herstellung von Uhren Herstellung von sonstigen Kunststoffwaren",
    "sg:phone":"+41 32 926 72 72",
    "sg:postcode":"2000",
    "sg:province":"Neuch\u00e2tel",
    "wof:name":"Inca Sa",
    "wof:placetype":"venue"
},
  "geometry": {"coordinates":[6.8104639053,47.0943984985],"type":"Point"}
}