{
  "type": "Feature",
  "properties": {
    "iso:country":"CH",
    "sg:address":"Holzackerweg 6 3902 Glis. Postfach",
    "sg:city":"Glis",
    "sg:orig_category":"Interessenvertretungen",
    "sg:postcode":"3902",
    "sg:province":"Valais",
    "wof:name":"Looser-stiftung Hugo",
    "wof:placetype":"venue"
},
  "geometry": {"coordinates":[8.6456451416,47.4106559753],"type":"Point"}
}