{
  "type": "Feature",
  "properties": {
    "iso:country":"CH",
    "sg:address":"Hauptstrasse 23",
    "sg:city":"Laufen",
    "sg:orig_category":"RESTAURANTS: TEA-ROOMS",
    "sg:postcode":"4242",
    "sg:province":"Basel-Landschaft",
    "wof:name":"Procea Gmbh",
    "wof:placetype":"venue"
},
  "geometry": {"coordinates":[7.5004348755,47.422039032],"type":"Point"}
}