{
  "type": "Feature",
  "properties": {
    "iso:country":"CH",
    "sg:address":"Unterholzstrasse 7",
    "sg:city":"Herzogenbuchsee",
    "sg:orig_category":"Interessenvertretungen",
    "sg:phone":"+41 55 220 71 71",
    "sg:postcode":"3360",
    "sg:province":"Bern",
    "wof:name":"Stiftung Futur",
    "wof:placetype":"venue"
},
  "geometry": {"coordinates":[8.8180141449,47.2277946472],"type":"Point"}
}