{
  "type": "Feature",
  "properties": {
    "iso:country":"CH",
    "sg:address":"Kronengasse 10",
    "sg:city":"Baden",
    "sg:orig_category":"Kinderkrippen U horte",
    "sg:phone":"+41 56 222 62 28",
    "sg:postcode":"5400",
    "sg:province":"Aargau",
    "wof:name":"Kindertreff Kornhaus",
    "wof:placetype":"venue"
},
  "geometry": {"coordinates":[8.3098888397,47.4729003906],"type":"Point"}
}