{
  "type": "Feature",
  "properties": {
    "iso:country":"CH",
    "sg:address":"Schulhausstrasse 11",
    "sg:city":"H\u00f6ri",
    "sg:orig_category":"Primarschulen",
    "sg:phone":"+41 18603094",
    "sg:postcode":"8181",
    "sg:province":"Z\u00fcrich",
    "wof:name":"Primarschule",
    "wof:placetype":"venue"
},
  "geometry": {"coordinates":[8.5062484741,47.5085105896],"type":"Point"}
}