{
  "type": "Feature",
  "properties": {
    "iso:country":"CH",
    "sg:address":"Brasi\u00e8re Chemin De La 26",
    "sg:city":"Gy",
    "sg:orig_category":"Sonstiger Grosshandel",
    "sg:phone":"+41 22 759 00 19",
    "sg:postcode":"1251",
    "sg:province":"Gen\u00e8ve",
    "wof:name":"Lt Loca Tentes S\u00e0rl",
    "wof:placetype":"venue"
},
  "geometry": {"coordinates":[6.257301,46.252033],"type":"Point"}
}