{
  "type": "Feature",
  "properties": {
    "iso:country":"CH",
    "sg:address":"Via Balestra 7",
    "sg:city":"Lugano",
    "sg:orig_category":"Wirtschaftspr\u00fcfung, Steuerberatung U Treuhand",
    "sg:phone":"+41 41 632 53 70",
    "sg:postcode":"6900",
    "sg:province":"Ticino",
    "wof:name":"Caplazi-treuhand Treuhand, Immobilien- U. Baumanagementgesch\u00e4fte",
    "wof:placetype":"venue"
},
  "geometry": {"coordinates":[8.3114833832,46.9857254028],"type":"Point"}
}