{
  "type": "Feature",
  "properties": {
    "iso:country":"CH",
    "sg:address":"Avenue De La Gare 15",
    "sg:city":"Sion",
    "sg:orig_category":"Detailhandel mit Waren verschiedener Art, Hauptrichtung Nahrungsmittel",
    "sg:phone":"+41 27 323 61 00",
    "sg:postcode":"1950",
    "sg:province":"Valais",
    "wof:name":"Pam Sa",
    "wof:placetype":"venue"
},
  "geometry": {"coordinates":[7.3583698273,46.2295036316],"type":"Point"}
}