{
  "type": "Feature",
  "properties": {
    "iso:country":"CH",
    "sg:address":"San Gottardo Corso 32",
    "sg:city":"Chiasso",
    "sg:orig_category":"Sonstige mit Sport verbundene T\u00e4tigkeiten",
    "sg:postcode":"6830",
    "sg:province":"Ticino",
    "wof:name":"Dance Club Wohlen Ag",
    "wof:placetype":"venue"
},
  "geometry": {"coordinates":[8.2689533234,47.3500976562],"type":"Point"}
}