{
  "type": "Feature",
  "properties": {
    "iso:country":"CH",
    "sg:address":"Mattweg 14a 4144 Arlesheim. Postfach 361",
    "sg:city":"Arlesheim",
    "sg:orig_category":"Grosshandel mit keramischen Erzeugnissen,Glaswaren U Tapeten Herstellung von sonstigen keramischen E",
    "sg:phone":"+41 61 701 68 68",
    "sg:postcode":"4144",
    "sg:province":"Basel-Landschaft",
    "wof:name":"Geraets Keramik Keramikprodukte, Bes. Namensbecher U. Sparschweine; Handel",
    "wof:placetype":"venue"
},
  "geometry": {"coordinates":[7.6187291145,47.495677948],"type":"Point"}
}