{
  "type": "Feature",
  "properties": {
    "addr:full":"Z\u00fcrcherstrasse 20 5210 Windisch. Postfach Windisch Aargau 5210",
    "addr:housenumber":"20",
    "addr:postcode":"5210;postfach;5210",
    "addr:street":"Zuercherstrasse",
    "iso:country":"CH",
    "sg:address":"Z\u00fcrcherstrasse 20 5210 Windisch. Postfach",
    "sg:city":"Windisch",
    "sg:orig_category":"Detailhandel mit Brillen U anderen Sehhilfen Detailhandel mit Uhren U Schmuck",
    "sg:phone":"+41 56 441 12 31",
    "sg:postcode":"5210",
    "sg:province":"Aargau",
    "wof:name":"Fritz Obrist Uhren/bijouterie Optik",
    "wof:placetype":"venue"
},
  "geometry": {"coordinates":[8.216473,47.478813],"type":"Point"}
}