{
  "type": "Feature",
  "properties": {
    "iso:country":"CH",
    "sg:address":"Kreuzgasse 4",
    "sg:city":"Solothurn",
    "sg:orig_category":"Non-Classified Establishments",
    "sg:postcode":"4500",
    "sg:province":"Solothurn",
    "wof:name":"Lebendiger Landhausquai Gmbh",
    "wof:placetype":"venue"
},
  "geometry": {"coordinates":[7.5377569199,47.2067108154],"type":"Point"}
}