{
  "type": "Feature",
  "properties": {
    "addr:full":"Thunstrasse 97 3006 Bern. Postfach Bern Bern 3006",
    "addr:housenumber":"97",
    "addr:postcode":"3006;postfach;3006",
    "addr:street":"Thunstrasse",
    "iso:country":"CH",
    "sg:address":"Thunstrasse 97 3006 Bern. Postfach",
    "sg:city":"Bern",
    "sg:orig_category":"Architektur U Ingenieurb\u00fcros",
    "sg:postcode":"3006",
    "sg:province":"Bern",
    "wof:name":"Archineering Gmbh Architekturb\u00fcro Usw.",
    "wof:placetype":"venue"
},
  "geometry": {"coordinates":[7.463426,46.94138],"type":"Point"}
}