{
  "type": "Feature",
  "properties": {
    "iso:country":"CH",
    "sg:address":"Rue De L'eglise 83",
    "sg:city":"Bonfol",
    "sg:orig_category":"Detailhandel mit Waren verschiedener Art, Hauptrichtung Nahrungsmittel",
    "sg:phone":"+41 32 474 44 23",
    "sg:postcode":"2944",
    "sg:province":"Jura",
    "wof:name":"Coop Neuch\u00e2tel-jura",
    "wof:placetype":"venue"
},
  "geometry": {"coordinates":[7.1490430832,47.4786605835],"type":"Point"}
}