{
  "type": "Feature",
  "properties": {
    "iso:country":"CH",
    "sg:address":"Via Tesserete 65",
    "sg:city":"Lugano",
    "sg:classifiers":[
        {
            "category":"Restaurant",
            "type":"Food & Drink"
        }
    ],
    "sg:phone":"+41 91 966 74 21",
    "sg:postcode":"6900",
    "sg:province":"Ticino",
    "wof:name":"Ristorante Calanda",
    "wof:placetype":"venue"
},
  "geometry": {"coordinates":[8.9508991241,46.0166358948],"type":"Point"}
}