{
  "type": "Feature",
  "properties": {
    "iso:country":"CH",
    "sg:address":"Wengistrasse 17",
    "sg:city":"Solothurn",
    "sg:orig_category":"Detailhandel mit Schuhen",
    "sg:phone":"+41 32 622 82 81",
    "sg:postcode":"4500",
    "sg:province":"Solothurn",
    "wof:name":"Paul Wyss Schuhhaus Central",
    "wof:placetype":"venue"
},
  "geometry": {"coordinates":[7.532913208,47.2070922852],"type":"Point"}
}