{
  "type": "Feature",
  "properties": {
    "iso:country":"CH",
    "sg:address":"Plazzet 25",
    "sg:city":"Samedan",
    "sg:orig_category":"Versicherungen Hauptagenturen",
    "sg:phone":"+41 56 221 01 11",
    "sg:postcode":"7503",
    "sg:province":"Graubunden",
    "wof:name":"Alba Versicherung Hauptagentur",
    "wof:placetype":"venue"
},
  "geometry": {"coordinates":[8.3250780106,47.5272712708],"type":"Point"}
}