{
  "type": "Feature",
  "properties": {
    "iso:country":"CH",
    "sg:address":"Holzikofenweg 22",
    "sg:city":"Bern",
    "sg:classifiers":[
        {
            "category":"Professional",
            "subcategory":"Employment Agencies",
            "type":"Services"
        }
    ],
    "sg:postcode":"3007",
    "sg:province":"Bern",
    "sg:tags":[
        "personal",
        "u",
        "stellenvermittlung"
    ],
    "wof:name":"Fairent Ag",
    "wof:placetype":"venue"
},
  "geometry": {"coordinates":[7.4352998734,46.9366340637],"type":"Point"}
}