{
  "type": "Feature",
  "properties": {
    "iso:country":"CH",
    "sg:address":"H\u00fcserenstrasse 12",
    "sg:city":"Z\u00fcberwangen",
    "sg:orig_category":"Sportvereine Behindertensport",
    "sg:phone":"+41 71 944 34 54",
    "sg:postcode":"9523",
    "sg:province":"St. Gallen",
    "wof:name":"Svbs Bischofszell Siv",
    "wof:placetype":"venue"
},
  "geometry": {"coordinates":[9.0931797028,47.4647216797],"type":"Point"}
}