{
  "type": "Feature",
  "properties": {
    "iso:country":"CH",
    "sg:address":"Seestrasse 78",
    "sg:city":"Uster",
    "sg:orig_category":"Instandhaltung U Reparatur von Automobilen",
    "sg:postcode":"8610",
    "sg:province":"Z\u00fcrich",
    "wof:name":"Daniel Hadorn Renault - Garage",
    "wof:placetype":"venue"
},
  "geometry": {"coordinates":[7.5478610992,46.8207168579],"type":"Point"}
}