{
  "type": "Feature",
  "properties": {
    "iso:country":"CH",
    "sg:address":"Hauptstrasse 106",
    "sg:city":"Ermatingen",
    "sg:orig_category":"Elektroinstallation",
    "sg:phone":"+41 91 864 18 53",
    "sg:postcode":"8272",
    "sg:province":"Thurgau",
    "wof:name":"Raffaele Imelli Impianti Elettrici",
    "wof:placetype":"venue"
},
  "geometry": {"coordinates":[8.9163999557,46.3774032593],"type":"Point"}
}