{
  "type": "Feature",
  "properties": {
    "iso:country":"CH",
    "sg:address":"Landstrasse 44",
    "sg:city":"Glarus",
    "sg:orig_category":"D\u00e4mmung gegen K\u00e4lte, W\u00e4rme, Schall U Ersch\u00fctterung Handelsvermittlung U Grosshandel",
    "sg:phone":"+41 55 640 44 22",
    "sg:postcode":"8750",
    "sg:province":"Glarus",
    "wof:name":"Hp Pelzer Ag",
    "wof:placetype":"venue"
},
  "geometry": {"coordinates":[9.0616598129,47.0446205139],"type":"Point"}
}