{
  "type": "Feature",
  "properties": {
    "iso:country":"CH",
    "sg:address":"Bernstrasse 7a",
    "sg:city":"Oftringen",
    "sg:orig_category":"Grosshandel mit keramischen Erzeugnissen, Glaswaren U Reinigungsmitteln Herstellung U Veredlung von ",
    "sg:phone":"+41 17619461",
    "sg:postcode":"4665",
    "sg:province":"Aargau",
    "wof:name":"Metroglas Ag",
    "wof:placetype":"venue"
},
  "geometry": {"coordinates":[8.4405708313,47.2756309509],"type":"Point"}
}