{
  "type": "Feature",
  "properties": {
    "iso:country":"CH",
    "sg:address":"Industriestr. 3",
    "sg:city":"Kleind\u00f6ttingen",
    "sg:classifiers":[
        {
            "category":"Professional",
            "subcategory":"Engineering",
            "type":"Services"
        }
    ],
    "sg:phone":"+41 56 245 50 05",
    "sg:postcode":"5314",
    "sg:province":"Aargau",
    "sg:tags":[
        "machine",
        "-",
        "mechanical"
    ],
    "wof:name":"Robo-mat Ag",
    "wof:placetype":"venue"
},
  "geometry": {"coordinates":[8.237695694,47.575969696],"type":"Point"}
}