{
  "type": "Feature",
  "properties": {
    "addr:full":"Loretostrasse 35 Solothurn Solothurn 4500",
    "addr:housenumber":"35",
    "addr:postcode":"4500",
    "addr:street":"Loretostrasse",
    "iso:country":"CH",
    "sg:address":"Loretostrasse 35",
    "sg:city":"Solothurn",
    "sg:orig_category":"Architektur U Ingenieurb\u00fcros",
    "sg:phone":"+41 32 623 33 38",
    "sg:postcode":"4500",
    "sg:province":"Solothurn",
    "wof:name":"Dr.andr\u00e9 Z. Wasowski Ingenieurb\u00fcro",
    "wof:placetype":"venue"
},
  "geometry": {"coordinates":[7.528602,47.21106],"type":"Point"}
}