{
  "type": "Feature",
  "properties": {
    "iso:country":"CH",
    "sg:address":"Neuweg 3",
    "sg:city":"Luzern",
    "sg:orig_category":"Detailhandel mit Sportartikeln",
    "sg:phone":"+41 41 210 18 28",
    "sg:postcode":"6003",
    "sg:province":"Luzern",
    "wof:name":"Strebel Bogensport Ag Bogensportartikel Usw; Fabr., Handel",
    "wof:placetype":"venue"
},
  "geometry": {"coordinates":[8.3082437515,47.0439491272],"type":"Point"}
}