{
  "type": "Feature",
  "properties": {
    "iso:country":"CH",
    "sg:address":"Mittlerer Talackerweg 12",
    "sg:city":"Villmergen",
    "sg:orig_category":"Pensionskassen",
    "sg:postcode":"5612",
    "sg:province":"Aargau",
    "wof:name":"Koch-berner-stiftung",
    "wof:placetype":"venue"
},
  "geometry": {"coordinates":[8.24629879,47.340877533],"type":"Point"}
}