{
  "type": "Feature",
  "properties": {
    "iso:country":"CH",
    "sg:address":"Bahnhofallee 9",
    "sg:city":"Oensingen",
    "sg:orig_category":"Grosshandel mit chemischen Erzeugnissen S\u00e4ge, Hobel U Holzimpr\u00e4gnierwerke",
    "sg:phone":"+41 26 402 51 71",
    "sg:postcode":"4702",
    "sg:province":"Solothurn",
    "wof:name":"Polatect Sa",
    "wof:placetype":"venue"
},
  "geometry": {"coordinates":[7.1243638992,46.8008842468],"type":"Point"}
}