{
  "type": "Feature",
  "properties": {
    "iso:country":"CH",
    "sg:address":"Friesenbergstrasse 13 8055 Z\u00fcrich. Postfach",
    "sg:city":"Z\u00fcrich",
    "sg:orig_category":"Finanzierungsinstitutionen",
    "sg:postcode":"8055",
    "sg:province":"Z\u00fcrich",
    "wof:name":"High Line Classic Cars Ag",
    "wof:placetype":"venue"
},
  "geometry": {"coordinates":[8.5138759613,47.3698043823],"type":"Point"}
}