{
  "type": "Feature",
  "properties": {
    "iso:country":"CH",
    "sg:address":"Gerberngasse 12 3011 Bern. Postfach",
    "sg:city":"Bern",
    "sg:orig_category":"Erbringung von sonstigen Dienstleistungen f\u00fcr Unterhaltung, Erholung U Freizeit",
    "sg:phone":"+41 31 333 88 89",
    "sg:postcode":"3005",
    "sg:province":"Bern",
    "wof:name":"Aida Vernastaltungen, Werbemittel, K\u00fcnstlerkontakt Freiburghaus-bracher Mich\u00e8le",
    "wof:placetype":"venue"
},
  "geometry": {"coordinates":[7.4572730064,46.9480667114],"type":"Point"}
}