{
  "type": "Feature",
  "properties": {
    "iso:country":"CH",
    "sg:address":"Grenchenstrasse 27",
    "sg:city":"Solothurn",
    "sg:orig_category":"Wohnheime",
    "sg:phone":"+41 32 623 38 12",
    "sg:postcode":"4500",
    "sg:province":"Solothurn",
    "wof:name":"Kloster Visitation",
    "wof:placetype":"venue"
},
  "geometry": {"coordinates":[7.529501915,47.2129974365],"type":"Point"}
}