{
  "type": "Feature",
  "properties": {
    "iso:country":"CH",
    "sg:address":"Chemin De Renens 53",
    "sg:city":"Lausanne",
    "sg:classifiers":[
        {
            "category":"Restaurant",
            "type":"Food & Drink"
        }
    ],
    "sg:phone":"+41 22 342 31 55",
    "sg:postcode":"1004",
    "sg:province":"Vaud",
    "wof:name":"Caf\u00e9-restaurant La Ruota",
    "wof:placetype":"venue"
},
  "geometry": {"coordinates":[6.1344838142,46.1894760132],"type":"Point"}
}