{
  "type": "Feature",
  "properties": {
    "iso:country":"CH",
    "sg:address":"Freudenberg",
    "sg:city":"Stettfurt",
    "sg:orig_category":"Wirtschafts- and Arbeitgeberverb\u00e4nde",
    "sg:phone":"+41 52 369 60 96",
    "sg:postcode":"9507",
    "sg:province":"Thurgau",
    "wof:name":"Wirteverein Frauenfeld & Umgebung",
    "wof:placetype":"venue"
},
  "geometry": {"coordinates":[8.9515752792,47.5323600769],"type":"Point"}
}