{
  "type": "Feature",
  "properties": {
    "addr:full":"Hauptstrasse 29 8355 Aadorf. Postfach Aadorf Thurgau 8355",
    "addr:housenumber":"29",
    "addr:postcode":"8355 aadorf. postfach;8355",
    "addr:street":"Hauptstrasse",
    "iso:country":"CH",
    "sg:address":"Hauptstrasse 29 8355 Aadorf. Postfach",
    "sg:city":"Aadorf",
    "sg:orig_category":"Detailhandel mit Bekleidung",
    "sg:postcode":"8355",
    "sg:province":"Thurgau",
    "wof:name":"Cn Sport Gmbh Konsumg\u00fcter, Bes. Kleider, Schuhe, Brillen; Handel, Verkauf",
    "wof:placetype":"venue"
},
  "geometry": {"coordinates":[8.895897,47.492058],"type":"Point"}
}