{
  "type": "Feature",
  "properties": {
    "iso:country":"CH",
    "sg:address":"Bahnhofplatz 2",
    "sg:city":"Zermatt",
    "sg:orig_category":"Advokaturb\u00fcros Notariate",
    "sg:phone":"+41 27 967 66 56",
    "sg:postcode":"3920",
    "sg:province":"Valais",
    "wof:name":"Mark Aufdenblatten Advokatur-& Notariatsb\u00fcro",
    "wof:placetype":"venue"
},
  "geometry": {"coordinates":[7.747976,46.023678],"type":"Point"}
}