{
  "type": "Feature",
  "properties": {
    "iso:country":"CH",
    "sg:address":"Tour Rue De La 12",
    "sg:city":"Sion",
    "sg:orig_category":"Unclassifiable Establishments",
    "sg:postcode":"1950",
    "sg:province":"Valais",
    "wof:name":"Gemma Association Catholique Pour La R\u00e9habilitation De Victimes De La Drogue",
    "wof:placetype":"venue"
},
  "geometry": {"coordinates":[7.3588571548,46.2280921936],"type":"Point"}
}