{
  "type": "Feature",
  "properties": {
    "iso:country":"CH",
    "sg:address":"Gellertstrasse 151 4052 Basel. Postfach",
    "sg:city":"Basel",
    "sg:orig_category":"Markt U Meinungsforschung Public-Relations-Agenturen",
    "sg:phone":"+41 61 313 50 60",
    "sg:postcode":"4028",
    "wof:name":"Tschopp Edwin + Dani\u00e8le, Marketing + Kommunikation",
    "wof:placetype":"venue"
},
  "geometry": {"coordinates":[7.6187858582,47.5471916199],"type":"Point"}
}