{
  "type": "Feature",
  "properties": {
    "iso:country":"CH",
    "sg:address":"Seidenweg 72 3012 Bern. Postfach",
    "sg:city":"Bern",
    "sg:orig_category":"Herstellung von sonstigen elektrischen Ausr\u00fcstungen",
    "sg:postcode":"3005",
    "sg:province":"Bern",
    "wof:name":"Von Der Aa J. Elektr. Apparate Usw; Import, Handel",
    "wof:placetype":"venue"
},
  "geometry": {"coordinates":[7.4341669083,46.9567604065],"type":"Point"}
}