{
  "type": "Feature",
  "properties": {
    "iso:country":"CH",
    "sg:address":"Landhusweg 10",
    "sg:city":"Z\u00fcrich",
    "sg:orig_category":"Maler U Glasergewerbe Malerei",
    "sg:phone":"+41 79 631 32 37",
    "sg:postcode":"8052",
    "sg:province":"Z\u00fcrich",
    "wof:name":"Hofer Ch. Maler Gmbh Malergesch\u00e4ft",
    "wof:placetype":"venue"
},
  "geometry": {"coordinates":[8.5483484268,47.4208068848],"type":"Point"}
}