{
  "type": "Feature",
  "properties": {
    "iso:country":"CH",
    "sg:address":"Rue Adrien-lachenal 3",
    "sg:city":"Gen\u00e8ve",
    "sg:orig_category":"Arztpraxen",
    "sg:phone":"+41 22 347 53 43",
    "sg:postcode":"1207",
    "sg:province":"Gen\u00e8ve",
    "wof:name":"Dr M\u00e9d. Anne-lise Robert M\u00e9decin Sp\u00e9cialiste Fmh",
    "wof:placetype":"venue"
},
  "geometry": {"coordinates":[6.155975,46.2006],"type":"Point"}
}