{
  "type": "Feature",
  "properties": {
    "iso:country":"CH",
    "sg:address":"L\u00e4ttichstr. 6",
    "sg:city":"Baar",
    "sg:classifiers":[
        {
            "category":"Shopping",
            "subcategory":"Computers & Home Electronics",
            "type":"Retail Goods"
        }
    ],
    "sg:phone":"+41 21 781 17 85",
    "sg:postcode":"6341",
    "sg:province":"Zug",
    "sg:tags":[
        "equipment",
        "household",
        "electrical",
        "appliance",
        "electronic"
    ],
    "wof:name":"Menagros Sa",
    "wof:placetype":"venue"
},
  "geometry": {"coordinates":[6.7556619644,46.5451927185],"type":"Point"}
}