{
  "type": "Feature",
  "properties": {
    "iso:country":"CH",
    "sg:address":"5025",
    "sg:city":"Asp",
    "sg:orig_category":"Detailhandel mit Milcherzeugnissen U Eiern Verarbeitung von Milch",
    "sg:postcode":"5025",
    "sg:province":"Aargau",
    "wof:name":"Milchgenossenschaft Asp",
    "wof:placetype":"venue"
},
  "geometry": {"coordinates":[8.0537996292,47.4421386719],"type":"Point"}
}