{
  "type": "Feature",
  "properties": {
    "iso:country":"CH",
    "sg:address":"Egelbergstrasse 1",
    "sg:city":"Bern",
    "sg:classifiers":[
        {
            "category":"Communications",
            "subcategory":"Film & Video Production",
            "type":"Services"
        }
    ],
    "sg:phone":"+41 31 351 91 22",
    "sg:postcode":"3006",
    "sg:province":"Bern",
    "sg:tags":[
        "videofilmherstellung",
        "u"
    ],
    "wof:name":"Alba-film Mamin & Rupp",
    "wof:placetype":"venue"
},
  "geometry": {"coordinates":[7.4628272057,46.9446563721],"type":"Point"}
}