{
  "type": "Feature",
  "properties": {
    "iso:country":"CH",
    "sg:address":"Nussbaumstrasse 12",
    "sg:city":"Z\u00fcrich",
    "sg:orig_category":"Detailhandel mit Antiquit\u00e4ten",
    "sg:phone":"+41 14617087",
    "sg:postcode":"8003",
    "sg:province":"Z\u00fcrich",
    "wof:name":"Ruth Steudler Antiquit\u00e4ten",
    "wof:placetype":"venue"
},
  "geometry": {"coordinates":[8.5143,47.371658],"type":"Point"}
}