{
  "type": "Feature",
  "properties": {
    "iso:country":"CH",
    "sg:address":"Kreuzhaldenstrasse 29",
    "sg:city":"Glattfelden",
    "sg:orig_category":"Hoch U Tiefbau",
    "sg:phone":"+41 18673209",
    "sg:postcode":"8192",
    "sg:province":"Z\u00fcrich",
    "wof:name":"Gerhard Hidegh Baugesch\u00e4ft",
    "wof:placetype":"venue"
},
  "geometry": {"coordinates":[8.4982309341,47.5620727539],"type":"Point"}
}