{
  "type": "Feature",
  "properties": {
    "iso:country":"CH",
    "sg:address":"Moya Rue De La 8",
    "sg:city":"Martigny",
    "sg:orig_category":"Stukkateurgewerbe, Gipserei U Verputzerei",
    "sg:postcode":"1920",
    "sg:province":"Valais",
    "wof:name":"Canta & Jacquier Sa",
    "wof:placetype":"venue"
},
  "geometry": {"coordinates":[7.0729198456,46.1013793945],"type":"Point"}
}