{
  "type": "Feature",
  "properties": {
    "addr:full":"Merzenacker 21 Bern Bern 3006",
    "addr:housenumber":"21",
    "addr:postcode":"3006",
    "addr:street":"Merzenacker",
    "iso:country":"CH",
    "sg:address":"Merzenacker 21",
    "sg:city":"Bern",
    "sg:orig_category":"Architektur U Ingenieurb\u00fcros",
    "sg:phone":"+41 31 941 09 09",
    "sg:postcode":"3006",
    "sg:province":"Bern",
    "wof:name":"Herrmann-chong Architekten Ag",
    "wof:placetype":"venue"
},
  "geometry": {"coordinates":[7.48115,46.944099],"type":"Point"}
}