{
  "type": "Feature",
  "properties": {
    "iso:country":"CH",
    "sg:address":"Rue Du Simplon 45 1920 Martigny Case Postale 736",
    "sg:city":"Martigny",
    "sg:orig_category":"Detailhandel mit Waren verschiedener Art, Hauptrichtung Nahrungsmittel Sonstiger Detailhandel mit Me",
    "sg:phone":"+41 79 301 16 17",
    "sg:postcode":"1920",
    "sg:province":"Valais",
    "wof:name":"Migros",
    "wof:placetype":"venue"
},
  "geometry": {"coordinates":[7.1225390434,46.124130249],"type":"Point"}
}