{
  "type": "Feature",
  "properties": {
    "iso:country":"CH",
    "sg:address":"Bahnhofstrasse 4",
    "sg:city":"Lotzwil",
    "sg:orig_category":"Elektrizit\u00e4tsversorgung Wasserversorgung",
    "sg:phone":"+41 62 916 00 42",
    "sg:postcode":"4932",
    "sg:province":"Bern",
    "wof:name":"Gemeindebetriebe Lotzwil Energie-& Wasserversorgung",
    "wof:placetype":"venue"
},
  "geometry": {"coordinates":[7.7893900871,47.1900520325],"type":"Point"}
}