{
  "type": "Feature",
  "properties": {
    "iso:country":"CH",
    "sg:address":"Chemin Des Eterpeys 22",
    "sg:city":"Lausanne",
    "sg:orig_category":"Elektroinstallation",
    "sg:phone":"+41 21 653 53 09",
    "sg:postcode":"1010",
    "sg:province":"Vaud",
    "wof:name":"Willi Rotach Installations \u00e9lectriques",
    "wof:placetype":"venue"
},
  "geometry": {"coordinates":[6.6609940529,46.5367202759],"type":"Point"}
}