{
  "type": "Feature",
  "properties": {
    "iso:country":"CH",
    "sg:address":"R\u00f6telnweg 6",
    "sg:city":"Nunningen",
    "sg:classifiers":[
        {
            "category":"Insurance",
            "subcategory":"Insurance Agent",
            "type":"Services"
        }
    ],
    "sg:phone":"+41 61 793 01 10",
    "sg:postcode":"4208",
    "sg:province":"Solothurn",
    "sg:tags":[
        "versicherungsagenturen",
        "-broker"
    ],
    "wof:name":"Waadt Versicherungen Agentur Nunningen",
    "wof:placetype":"venue"
},
  "geometry": {"coordinates":[7.6167402267,47.3914642334],"type":"Point"}
}