{
  "type": "Feature",
  "properties": {
    "iso:country":"CH",
    "sg:address":"Sandreuterweg 8",
    "sg:city":"Riehen",
    "sg:orig_category":"Sonstige pers\u00f6nliche Dienstleistungen",
    "sg:phone":"+41 61 601 37 30",
    "sg:postcode":"4125",
    "sg:province":"Basel-Stadt",
    "wof:name":"B\u00fcro Rendez-vous Girod Partnervermittlung",
    "wof:placetype":"venue"
},
  "geometry": {"coordinates":[7.652244091,47.5794181824],"type":"Point"}
}