{
  "type": "Feature",
  "properties": {
    "iso:country":"CH",
    "sg:address":"Centrale Rue 24 1003 Lausanne. Postfach",
    "sg:city":"Lausanne",
    "sg:orig_category":"Unclassifiable Establishments",
    "sg:postcode":"1003",
    "sg:province":"Vaud",
    "wof:name":"Si La Paisible",
    "wof:placetype":"venue"
},
  "geometry": {"coordinates":[6.6348500252,46.5205917358],"type":"Point"}
}