{
  "type": "Feature",
  "properties": {
    "iso:country":"CH",
    "sg:address":"Schwyzerstrasse 26",
    "sg:city":"Brunnen",
    "sg:orig_category":"Detailhandel mit M\u00f6beln U Haushaltsgegenst\u00e4nden",
    "sg:postcode":"6440",
    "sg:province":"Schwyz",
    "wof:name":"M\u00f6bel Schnyder",
    "wof:placetype":"venue"
},
  "geometry": {"coordinates":[8.8404169083,47.3063392639],"type":"Point"}
}