{
  "type": "Feature",
  "properties": {
    "iso:country":"CH",
    "sg:address":"Dachsweg 3",
    "sg:city":"Niederbipp",
    "sg:orig_category":"Grosshandel mit B\u00fcromaschinen Grosshandel mit Datenverarbeitungsger\u00e4ten",
    "sg:phone":"+41 32 633 00 50",
    "sg:postcode":"4704",
    "sg:province":"Bern",
    "wof:name":"S.e.s Siegenthaler Edv Service Gmbh",
    "wof:placetype":"venue"
},
  "geometry": {"coordinates":[7.6963682175,47.2694015503],"type":"Point"}
}