{
  "type": "Feature",
  "properties": {
    "iso:country":"CH",
    "sg:address":"Grand-rue 8 2108 Couvet Case Postale 211",
    "sg:city":"Couvet",
    "sg:orig_category":"Arztpraxen",
    "sg:phone":"+41 32 863 16 26",
    "sg:postcode":"2108",
    "sg:province":"Neuch\u00e2tel",
    "wof:name":"Dr M\u00e9d. Jean-pierre Monod M\u00e9decin G\u00e9n\u00e9raliste Fmh",
    "wof:placetype":"venue"
},
  "geometry": {"coordinates":[6.633658,46.92403],"type":"Point"}
}