{
  "type": "Feature",
  "properties": {
    "addr:full":"Ceresio Via 4 Pregassona Ticino 6963",
    "addr:postcode":"6963",
    "addr:street":"Via 4",
    "iso:country":"CH",
    "sg:address":"Ceresio Via 4",
    "sg:city":"Pregassona",
    "sg:orig_category":"Allgemeiner Hoch U Tiefbau",
    "sg:postcode":"6963",
    "sg:province":"Ticino",
    "wof:name":"Tomi Mont Sagl",
    "wof:placetype":"venue"
},
  "geometry": {"coordinates":[8.964896,46.016239],"type":"Point"}
}