{
  "type": "Feature",
  "properties": {
    "iso:country":"CH",
    "sg:address":"Burgmatt 22",
    "sg:city":"Baar",
    "sg:orig_category":"Verwaltung von Immobilien",
    "sg:phone":"+41 41 761 39 61",
    "sg:postcode":"6340",
    "sg:province":"Zug",
    "wof:name":"Gossweiler Fredy, Verwaltungen",
    "wof:placetype":"venue"
},
  "geometry": {"coordinates":[8.5380268097,47.1923866272],"type":"Point"}
}