{
  "type": "Feature",
  "properties": {
    "iso:country":"CH",
    "sg:address":"Mellingerstrasse 12",
    "sg:city":"Niederrohrdorf",
    "sg:orig_category":"Softwareentwicklung U beratung",
    "sg:phone":"+41 56 496 01 55",
    "sg:postcode":"5443",
    "sg:province":"Aargau",
    "wof:name":"Elsys Ag",
    "wof:placetype":"venue"
},
  "geometry": {"coordinates":[8.300028801,47.424949646],"type":"Point"}
}