{
  "type": "Feature",
  "properties": {
    "iso:country":"CH",
    "sg:address":"Seetalstrasse 29",
    "sg:city":"Seon",
    "sg:orig_category":"Detailhandel mit Radio U Fernsehger\u00e4ten Detailhandel mit elektrischen Haushalts-,Radio U Fernsehger\u00e4",
    "sg:phone":"+41 62 775 10 75",
    "sg:postcode":"5703",
    "sg:province":"Aargau",
    "wof:name":"Peter Walti Radio-tv",
    "wof:placetype":"venue"
},
  "geometry": {"coordinates":[8.1591882706,47.3491897583],"type":"Point"}
}