{
  "type": "Feature",
  "properties": {
    "iso:country":"CH",
    "sg:address":"Grafenauweg 10",
    "sg:city":"Zug",
    "sg:classifiers":[
        {
            "category":"Banks & Credit Unions",
            "subcategory":"Investment Brokerage",
            "type":"Services"
        }
    ],
    "sg:phone":"+41 71 966 43 43",
    "sg:postcode":"6300",
    "sg:province":"Zug",
    "sg:tags":[
        "preparation",
        "asthma"
    ],
    "wof:name":"Highpower Gmbh",
    "wof:placetype":"venue"
},
  "geometry": {"coordinates":[9.00007,47.488045],"type":"Point"}
}