{
  "type": "Feature",
  "properties": {
    "iso:country":"CH",
    "sg:address":"Auf Salenrain 12",
    "sg:city":"St\u00e4fa",
    "sg:orig_category":"Architektur U Ingenieurb\u00fcros",
    "sg:phone":"+41 19267040",
    "sg:postcode":"8712",
    "sg:province":"Z\u00fcrich",
    "wof:name":"Giesbrecht Produkt-konzepte",
    "wof:placetype":"venue"
},
  "geometry": {"coordinates":[8.720349,47.243301],"type":"Point"}
}