{
  "type": "Feature",
  "properties": {
    "iso:country":"CH",
    "sg:address":"Lang\u00e4ckerstrasse 27 8125 Zollikerberg. Postfach",
    "sg:city":"Zollikerberg",
    "sg:orig_category":"Kauf U Verkauf von Immobilien auf eigene Rechnung",
    "sg:postcode":"8125",
    "sg:province":"Z\u00fcrich",
    "wof:name":"Wipf Arnold Ag",
    "wof:placetype":"venue"
},
  "geometry": {"coordinates":[8.6015110016,47.3463973999],"type":"Point"}
}