{
  "type": "Feature",
  "properties": {
    "iso:country":"CH",
    "sg:address":"Boulevard Du Pont-d'arve 20",
    "sg:city":"Gen\u00e8ve",
    "sg:classifiers":[
        {
            "category":"Restaurant",
            "type":"Food & Drink"
        }
    ],
    "sg:phone":"+41 19322325",
    "sg:postcode":"1205",
    "sg:province":"Gen\u00e8ve",
    "wof:name":"Nullgleis-nullbuffet",
    "wof:placetype":"venue"
},
  "geometry": {"coordinates":[8.7910518646,47.3177604675],"type":"Point"}
}