{
  "type": "Feature",
  "properties": {
    "iso:country":"CH",
    "sg:address":"Morgentalstr. 8",
    "sg:city":"Aadorf",
    "sg:classifiers":[
        {
            "category":"Manufacturing",
            "subcategory":"Tools & Machinery",
            "type":"Manufacturing & Wholesale Goods"
        }
    ],
    "sg:phone":"+41 52 368 22 22",
    "sg:postcode":"8355",
    "sg:province":"Thurgau",
    "sg:tags":[
        "metallurgy",
        "metalworking"
    ],
    "wof:name":"Baiter Ag",
    "wof:placetype":"venue"
},
  "geometry": {"coordinates":[8.899338,47.491829],"type":"Point"}
}