{
  "type": "Feature",
  "properties": {
    "iso:country":"CH",
    "sg:address":"Sihlbruggstrasse 105 6340 Baar. Postfach",
    "sg:city":"Zug",
    "sg:orig_category":"Rechtsberatung",
    "sg:postcode":"6300",
    "sg:province":"Zug",
    "wof:name":"Ascot Pack Ag",
    "wof:placetype":"venue"
},
  "geometry": {"coordinates":[8.5390930176,47.1977767944],"type":"Point"}
}