{
  "type": "Feature",
  "properties": {
    "iso:country":"CH",
    "sg:address":"Route De La Gl\u00e2ne 9b",
    "sg:city":"Fribourg",
    "sg:orig_category":"Unternehmensberatung Wirtschaftspr\u00fcfung, Steuerberatung U Treuhand",
    "sg:phone":"+41 26 424 04 09",
    "sg:postcode":"1700",
    "sg:province":"Fribourg",
    "wof:name":"Bc Consulting, Creux Bernard",
    "wof:placetype":"venue"
},
  "geometry": {"coordinates":[7.1457409859,46.7963676453],"type":"Point"}
}