{
  "type": "Feature",
  "properties": {
    "iso:country":"CH",
    "sg:address":"Dorfstrasse 46",
    "sg:city":"Embrach",
    "sg:orig_category":"Finanzierungsinstitutionen",
    "sg:phone":"+41 18654920",
    "sg:postcode":"8424",
    "sg:province":"Z\u00fcrich",
    "wof:name":"Lobo Ag, Beteiligungs Und Finanzierungsgesellschaft",
    "wof:placetype":"venue"
},
  "geometry": {"coordinates":[8.5943908691,47.5043487549],"type":"Point"}
}