{
  "type": "Feature",
  "properties": {
    "addr:full":"Kreuzplatz 4 3510 Konolfingen. Postfach 155 Konolfingen Bern 3510",
    "addr:housenumber":"4;155",
    "addr:postcode":"3510 konolfingen.;3510",
    "addr:street":"Kreuzplatz;Postfach;Bern",
    "iso:country":"CH",
    "sg:address":"Kreuzplatz 4 3510 Konolfingen. Postfach 155",
    "sg:city":"Konolfingen",
    "sg:orig_category":"Architektur U Ingenieurb\u00fcros Architekturb\u00fcros",
    "sg:phone":"+41 31 791 22 11",
    "sg:postcode":"3510",
    "sg:province":"Bern",
    "wof:name":"Wittwer + Pulfer Architekten Ag",
    "wof:placetype":"venue"
},
  "geometry": {"coordinates":[7.620874,46.879318],"type":"Point"}
}