{
  "type": "Feature",
  "properties": {
    "iso:country":"CH",
    "sg:address":"Neue Winterthurerstrasse 26 8304 Wallisellen. Postfach",
    "sg:city":"Wallisellen",
    "sg:orig_category":"Grosshandel mit sonstigen Maschinen U Ausr\u00fcstungen f\u00fcr Industrie, Handel U Schiffahrt",
    "sg:phone":"+41 18300231",
    "sg:postcode":"8304",
    "sg:province":"Z\u00fcrich",
    "wof:name":"Pamax Automation Ag",
    "wof:placetype":"venue"
},
  "geometry": {"coordinates":[8.6078386307,47.4107322693],"type":"Point"}
}