{
  "type": "Feature",
  "properties": {
    "iso:country":"CH",
    "sg:address":"Freiestrasse 7",
    "sg:city":"Uster",
    "sg:orig_category":"Grosshandel mit elektrischen Haushaltsger\u00e4ten",
    "sg:phone":"+41 17878890",
    "sg:postcode":"8610",
    "sg:province":"Z\u00fcrich",
    "wof:name":"Jacques Frei Handels Ag",
    "wof:placetype":"venue"
},
  "geometry": {"coordinates":[8.7207193375,47.1887245178],"type":"Point"}
}