{
  "type": "Feature",
  "properties": {
    "iso:country":"CH",
    "sg:address":"1580",
    "sg:city":"Oleyres",
    "sg:orig_category":"Bauschreinerei",
    "sg:phone":"+41 26 675 11 07",
    "sg:postcode":"1580",
    "sg:province":"Vaud",
    "wof:name":"Kaltenrieder, Bernard",
    "wof:placetype":"venue"
},
  "geometry": {"coordinates":[7.037512,46.854038],"type":"Point"}
}