{
  "type": "Feature",
  "properties": {
    "iso:country":"CH",
    "sg:address":"Birkenweg 1",
    "sg:city":"Eggersriet",
    "sg:orig_category":"Physiotherapie",
    "sg:phone":"+41 71 877 23 86",
    "sg:postcode":"9034",
    "sg:province":"St. Gallen",
    "wof:name":"Katalin Andreotti Physiotherapie",
    "wof:placetype":"venue"
},
  "geometry": {"coordinates":[9.4713315964,47.4437484741],"type":"Point"}
}