{
  "type": "Feature",
  "properties": {
    "iso:country":"CH",
    "sg:address":"Riva Sole",
    "sg:city":"Astano",
    "sg:orig_category":"Mit Sport verbundene T\u00e4tigkeiten",
    "sg:phone":"+41 91 608 12 83",
    "sg:postcode":"6999",
    "sg:province":"Ticino",
    "wof:name":"P. Schneider & M.-th.krijense Equitazione",
    "wof:placetype":"venue"
},
  "geometry": {"coordinates":[8.8184947968,46.011806488],"type":"Point"}
}