{
  "type": "Feature",
  "properties": {
    "iso:country":"CH",
    "sg:address":"Luzernstrasse 31",
    "sg:city":"Derendingen",
    "sg:orig_category":"Sanit\u00e4r, Heizungs U L\u00fcftungsinstallation Sanit\u00e4rinstallation",
    "sg:phone":"+41 32 682 02 02",
    "sg:postcode":"4552",
    "sg:province":"Solothurn",
    "wof:name":"Coldebella Haustechnik",
    "wof:placetype":"venue"
},
  "geometry": {"coordinates":[7.5865478516,47.2008781433],"type":"Point"}
}