{
  "type": "Feature",
  "properties": {
    "iso:country":"CH",
    "sg:address":"D\u00f6rflistrasse 34",
    "sg:city":"Zweidlen",
    "sg:orig_category":"Grosshandel mit landwirtschaftlichen Maschinen U Ger\u00e4ten Herstellung von k\u00e4lte U lufttechnischen Erz",
    "sg:phone":"+41 18670573",
    "sg:postcode":"8192",
    "sg:province":"Z\u00fcrich",
    "wof:name":"Maag, Sanafil",
    "wof:placetype":"venue"
},
  "geometry": {"coordinates":[8.4692296982,47.5624465942],"type":"Point"}
}