{
  "type": "Feature",
  "properties": {
    "iso:country":"CH",
    "sg:address":"Rue De Gen\u00e8ve 18",
    "sg:city":"Gen\u00e8ve",
    "sg:orig_category":"Grossbanken",
    "sg:phone":"+41 21 631 38 11",
    "sg:postcode":"1204",
    "sg:province":"Gen\u00e8ve",
    "wof:name":"Ubs Sa",
    "wof:placetype":"venue"
},
  "geometry": {"coordinates":[6.5803041458,46.5372543335],"type":"Point"}
}