{
  "type": "Feature",
  "properties": {
    "iso:country":"CH",
    "sg:address":"Neuhofstrasse 23 6340 Baar. Postfach 344",
    "sg:city":"Baar",
    "sg:orig_category":"Herstellung von Duft U K\u00f6rperpflegemitteln",
    "sg:phone":"+41 41 766 04 66",
    "sg:postcode":"6341",
    "sg:province":"Zug",
    "wof:name":"Laboratoires Estiloc Sa",
    "wof:placetype":"venue"
},
  "geometry": {"coordinates":[8.5154466629,47.1893730164],"type":"Point"}
}