{
  "type": "Feature",
  "properties": {
    "iso:country":"CH",
    "sg:address":"Sempacherstrasse 12",
    "sg:city":"Z\u00fcrich",
    "sg:orig_category":"Kosmetikinstitute",
    "sg:phone":"+41 13824477",
    "sg:postcode":"8032",
    "sg:province":"Z\u00fcrich",
    "wof:name":"Regina Risch Kosmetikinstitut",
    "wof:placetype":"venue"
},
  "geometry": {"coordinates":[8.5662736893,47.3634719849],"type":"Point"}
}