{
  "type": "Feature",
  "properties": {
    "iso:country":"CH",
    "sg:address":"Rue Dizerens 11",
    "sg:city":"Gen\u00e8ve",
    "sg:orig_category":"Herstellung von Metallkonstruktionen Schlossereien",
    "sg:phone":"+41 22 786 24 23",
    "sg:postcode":"1205",
    "sg:province":"Gen\u00e8ve",
    "wof:name":"Alain Favre Coffrecl\u00e9s-service",
    "wof:placetype":"venue"
},
  "geometry": {"coordinates":[6.1433968544,46.19298172],"type":"Point"}
}