{
  "type": "Feature",
  "properties": {
    "iso:country":"CH",
    "sg:address":"Avenue De Morges 33",
    "sg:city":"Lausanne",
    "sg:classifiers":[
        {
            "category":"Park",
            "subcategory":"Provincial",
            "type":"Public Place"
        }
    ],
    "sg:phone":"+41 22 796 55 89",
    "sg:postcode":"1004",
    "sg:province":"Vaud",
    "sg:tags":[
        "birthday",
        "card"
    ],
    "wof:name":"Editions Coloris Jaeger Sa",
    "wof:placetype":"venue"
},
  "geometry": {"coordinates":[6.098924,46.207272],"type":"Point"}
}