{
  "type": "Feature",
  "properties": {
    "iso:country":"CH",
    "sg:address":"M\u00e4derstrasse 8 5400 Baden. Postfach",
    "sg:city":"Baden",
    "sg:orig_category":"Architektur U Ingenieurb\u00fcros",
    "sg:phone":"+41 56 222 09 45",
    "sg:postcode":"5400",
    "sg:province":"Aargau",
    "wof:name":"Matousek, Baumann & Niggli Ag",
    "wof:placetype":"venue"
},
  "geometry": {"coordinates":[8.303153,47.477322],"type":"Point"}
}