{
  "type": "Feature",
  "properties": {
    "iso:country":"CH",
    "sg:address":"Baumgartenweg 7",
    "sg:city":"Galgenen",
    "sg:orig_category":"Verlegen von Fliesen U Platten",
    "sg:phone":"+41 55 440 41 34",
    "sg:postcode":"8854",
    "sg:province":"Schwyz",
    "wof:name":"A. Zumstein Ag Plattengesch\u00e4ft",
    "wof:placetype":"venue"
},
  "geometry": {"coordinates":[8.8773107529,47.1826324463],"type":"Point"}
}