{
  "type": "Feature",
  "properties": {
    "iso:country":"CH",
    "sg:address":"2738",
    "sg:city":"Court",
    "sg:classifiers":[
        {
            "category":"Travel",
            "subcategory":"Hotels & Motels",
            "type":"Entertainment"
        }
    ],
    "sg:phone":"+41 32 497 90 61",
    "sg:postcode":"2738",
    "sg:province":"Bern",
    "sg:tags":[
        "hotels",
        "mit",
        "restaurant"
    ],
    "wof:name":"H\u00f4tel Harzer",
    "wof:placetype":"venue"
},
  "geometry": {"coordinates":[7.3414521217,47.2410430908],"type":"Point"}
}