{
  "type": "Feature",
  "properties": {
    "iso:country":"CH",
    "sg:address":"Breitmattweg 63",
    "sg:city":"Rheinfelden",
    "sg:orig_category":"Spezieller Tiefbau",
    "sg:phone":"+41 61 831 80 20",
    "sg:postcode":"4310",
    "sg:province":"Aargau",
    "wof:name":"Aroluba Ag Rohr-& Anlagenbau",
    "wof:placetype":"venue"
},
  "geometry": {"coordinates":[7.7802009583,47.5458106995],"type":"Point"}
}