{
  "type": "Feature",
  "properties": {
    "iso:country":"CH",
    "sg:address":"Giessh\u00fcbelstr. 45",
    "sg:city":"Z\u00fcrich",
    "sg:orig_category":"Business advice and other services Mechanical Engineering - machines Miscellaneous Products Sport",
    "sg:phone":"+41 4114682444",
    "sg:postcode":"8045",
    "sg:province":"Z\u00fcrich",
    "wof:name":"Conzzeta Holding",
    "wof:placetype":"venue"
},
  "geometry": {"coordinates":[8.520117,47.357716],"type":"Point"}
}