{
  "type": "Feature",
  "properties": {
    "iso:country":"CH",
    "sg:address":"Hinterwies 42",
    "sg:city":"Speicher",
    "sg:orig_category":"Sonstiger Grosshandel",
    "sg:phone":"+41 17603011",
    "sg:postcode":"9042",
    "sg:province":"Appenzell Ausserrhoden",
    "wof:name":"4 Plus Gmbh",
    "wof:placetype":"venue"
},
  "geometry": {"coordinates":[8.4515981674,47.2790336609],"type":"Point"}
}