{
  "type": "Feature",
  "properties": {
    "iso:country":"CH",
    "sg:address":"Avenue Louis-ruchonnet 10",
    "sg:city":"Lausanne",
    "sg:orig_category":"Fahrschulen, Flugschulen",
    "sg:phone":"+41 21 312 11 17",
    "sg:postcode":"1003",
    "sg:province":"Vaud",
    "wof:name":"Eca L'auto-\u00e9cole, Jaquier Marcel",
    "wof:placetype":"venue"
},
  "geometry": {"coordinates":[6.6265969276,46.5184364319],"type":"Point"}
}