{
  "type": "Feature",
  "properties": {
    "iso:country":"CH",
    "sg:address":"Z\u00fcrcherstrasse 212 8406 Winterthur. Postfach 143",
    "sg:city":"Winterthur",
    "sg:orig_category":"Detailhandel mit Brot, Back U S\u00fcsswaren",
    "sg:phone":"+41 52 202 93 33",
    "sg:postcode":"8406",
    "sg:province":"Z\u00fcrich",
    "wof:name":"Lienhard Roger",
    "wof:placetype":"venue"
},
  "geometry": {"coordinates":[8.70775,47.460693],"type":"Point"}
}