{
  "type": "Feature",
  "properties": {
    "iso:country":"CH",
    "sg:address":"Kantonsstrasse 35 8864 Reichenburg. Postfach 162",
    "sg:city":"Reichenburg",
    "sg:orig_category":"Detailhandel mit Fleisch U Fleischwaren",
    "sg:phone":"+41 62 758 12 89",
    "sg:postcode":"8864",
    "sg:province":"Schwyz",
    "wof:name":"Dorfmetzg Langnau Ag",
    "wof:placetype":"venue"
},
  "geometry": {"coordinates":[7.9617819786,47.230052948],"type":"Point"}
}