{
  "type": "Feature",
  "properties": {
    "iso:country":"CH",
    "sg:address":"D\u00f6nlerstrasse 3",
    "sg:city":"Fulenbach",
    "sg:orig_category":"Herstellung von Konstruktionsteilen, Fertigbauteilen U Ausbauelementen aus Holz",
    "sg:phone":"+41 62 926 28 30",
    "sg:postcode":"4629",
    "sg:province":"Solothurn",
    "wof:name":"Meiku-service",
    "wof:placetype":"venue"
},
  "geometry": {"coordinates":[7.8321590424,47.2763175964],"type":"Point"}
}