{
  "type": "Feature",
  "properties": {
    "iso:country":"CH",
    "sg:address":"Grubenstrasse 9",
    "sg:city":"Urdorf",
    "sg:orig_category":"Herstellung von k\u00e4lte U lufttechnischen Erzeugnissen f\u00fcr gewerbliche Zwecke",
    "sg:phone":"+41 17772292",
    "sg:postcode":"8902",
    "sg:province":"Z\u00fcrich",
    "wof:name":"Nrf Switzerland Ag",
    "wof:placetype":"venue"
},
  "geometry": {"coordinates":[8.4191904068,47.3919181824],"type":"Point"}
}