{
  "type": "Feature",
  "properties": {
    "iso:country":"CH",
    "sg:address":"Cantonale Via 74d",
    "sg:city":"Pregassona",
    "sg:orig_category":"Wirtschaftspr\u00fcfung, Steuerberatung U Treuhand",
    "sg:phone":"+41 91 913 42 20",
    "sg:postcode":"6963",
    "sg:province":"Ticino",
    "wof:name":"Finetic Sa",
    "wof:placetype":"venue"
},
  "geometry": {"coordinates":[8.9771242142,46.0286750793],"type":"Point"}
}