{
  "type": "Feature",
  "properties": {
    "iso:country":"CH",
    "sg:address":"Z\u00fcrichstrasse 47",
    "sg:city":"Merenschwand",
    "sg:orig_category":"Herstellung von Metallerzeugnissen ohne Maschinenbau Herstellung von sonstigen Metallwaren",
    "sg:phone":"+41 56 664 16 27",
    "sg:postcode":"5634",
    "sg:province":"Aargau",
    "wof:name":"Leo Ernst Metallwaren Ag",
    "wof:placetype":"venue"
},
  "geometry": {"coordinates":[8.3959302902,47.2636985779],"type":"Point"}
}