{
  "type": "Feature",
  "properties": {
    "addr:full":"Edletenstrasse 10c Lausen Basel-Landschaft 4415",
    "addr:housenumber":"10c",
    "addr:postcode":"4415",
    "addr:street":"Edletenstrasse",
    "iso:country":"CH",
    "sg:address":"Edletenstrasse 10c",
    "sg:city":"Lausen",
    "sg:orig_category":"Detailhandel mit B\u00fcchern, Zeitungen, Schreib U Papeteriewaren",
    "sg:postcode":"4415",
    "sg:province":"Basel-Landschaft",
    "wof:name":"Pane Di Vita Italiano",
    "wof:placetype":"venue"
},
  "geometry": {"coordinates":[7.767952,47.474487],"type":"Point"}
}