{
  "type": "Feature",
  "properties": {
    "addr:full":"Viale Verbano 33 Muralto Ticino 6600",
    "addr:housenumber":"33",
    "addr:postcode":"6600",
    "addr:street":"Viale Verbano",
    "iso:country":"CH",
    "sg:address":"Viale Verbano 33",
    "sg:city":"Muralto",
    "sg:orig_category":"Detailhandel mit Antiquit\u00e4ten Detailhandel mit Geschenkartikeln U Souvenirs",
    "sg:phone":"+41 91 743 81 61",
    "sg:postcode":"6600",
    "sg:province":"Ticino",
    "wof:name":"Maria Luisa Cavargna La Fonte Artigianato-antichit\u00e0",
    "wof:placetype":"venue"
},
  "geometry": {"coordinates":[8.805235,46.171608],"type":"Point"}
}