{
  "type": "Feature",
  "properties": {
    "iso:country":"CH",
    "sg:city":"Gohl",
    "sg:classifiers":[
        {
            "category":"Banks & Credit Unions",
            "subcategory":"Bank",
            "type":"Services"
        }
    ],
    "sg:phone":"+41 41 352 10 08",
    "sg:postcode":"3553",
    "sg:province":"Bern",
    "wof:name":"Bank In Langnau",
    "wof:placetype":"venue"
},
  "geometry": {"coordinates":[7.806979,46.954929],"type":"Point"}
}