{
  "type": "Feature",
  "properties": {
    "iso:country":"CH",
    "sg:address":"Weststrasse 7",
    "sg:city":"Zug",
    "sg:orig_category":"Sonstige mit der Informatik verbundene T\u00e4tigkeiten",
    "sg:postcode":"6300",
    "sg:province":"Zug",
    "wof:name":"Easywin Informatik Gmbh",
    "wof:placetype":"venue"
},
  "geometry": {"coordinates":[8.5098428726,47.1766815186],"type":"Point"}
}