{
  "type": "Feature",
  "properties": {
    "iso:country":"CH",
    "sg:address":"L\u00e4rchenweg 3",
    "sg:city":"N\u00fcrensdorf",
    "sg:classifiers":[
        {
            "category":"Organizations",
            "subcategory":"Labor Organization",
            "type":"Services"
        }
    ],
    "sg:phone":"+41 18368245",
    "sg:postcode":"8309",
    "sg:province":"Z\u00fcrich",
    "sg:tags":[
        "data",
        "gsm",
        "system",
        "transfer"
    ],
    "wof:name":"Sifax Ag",
    "wof:placetype":"venue"
},
  "geometry": {"coordinates":[8.6403284073,47.460521698],"type":"Point"}
}