{
  "type": "Feature",
  "properties": {
    "iso:country":"CH",
    "sg:address":"Loostrasse 5 8803 R\u00fcschlikon. Postfach 223",
    "sg:city":"R\u00fcschlikon",
    "sg:orig_category":"Pensionskassen",
    "sg:phone":"+41 17245040",
    "sg:postcode":"8803",
    "sg:province":"Z\u00fcrich",
    "wof:name":"Unabh\u00e4ngige Gemeinschaftsstiftung Z\u00fcrich Ugz",
    "wof:placetype":"venue"
},
  "geometry": {"coordinates":[8.5438127518,47.3068237305],"type":"Point"}
}