{
  "type": "Feature",
  "properties": {
    "iso:country":"CH",
    "sg:address":"Bahnhofstrasse 8 4144 Arlesheim. Postfach 127",
    "sg:city":"Arlesheim",
    "sg:orig_category":"G\u00fcterbef\u00f6rderung im Strassenverkehr Reiseb\u00fcros U Reiseveranstalter",
    "sg:phone":"+41 61 701 79 79",
    "sg:postcode":"4144",
    "sg:province":"Basel-Landschaft",
    "wof:name":"Rudolf Meier Birseck-reisen & Transporte",
    "wof:placetype":"venue"
},
  "geometry": {"coordinates":[7.6105952263,47.4907608032],"type":"Point"}
}