{
  "type": "Feature",
  "properties": {
    "iso:country":"CH",
    "sg:address":"Vogelsangstrasse 39",
    "sg:city":"Esslingen",
    "sg:orig_category":"Detailhandel mit Blumen U Pflanzen",
    "sg:phone":"+41 55 643 39 77",
    "sg:postcode":"8133",
    "sg:province":"Z\u00fcrich",
    "wof:name":"Blumen Emmi",
    "wof:placetype":"venue"
},
  "geometry": {"coordinates":[9.02758,46.946323],"type":"Point"}
}