{
  "type": "Feature",
  "properties": {
    "iso:country":"CH",
    "sg:address":"7503",
    "sg:city":"Samedan",
    "sg:orig_category":"Pensionskassen",
    "sg:postcode":"7503",
    "sg:province":"Graubunden",
    "wof:name":"Personalf\u00fcrsorgestiftung Der Firma Gebr\u00fcder V\u00f6gtli, Schreinerei",
    "wof:placetype":"venue"
},
  "geometry": {"coordinates":[7.9947161674,47.3377456665],"type":"Point"}
}