{
  "type": "Feature",
  "properties": {
    "iso:country":"CH",
    "sg:address":"Gen\u00e8ve Rue De 12",
    "sg:city":"Ch\u00eane-bourg",
    "sg:orig_category":"Instandhaltung U Reparatur von Automobilen",
    "sg:phone":"+41 22 349 52 29",
    "sg:postcode":"1225",
    "sg:province":"Gen\u00e8ve",
    "wof:name":"Station De La Place, Castelbou",
    "wof:placetype":"venue"
},
  "geometry": {"coordinates":[6.1934227943,46.194770813],"type":"Point"}
}