{
  "type": "Feature",
  "properties": {
    "iso:country":"CH",
    "sg:address":"Hauptstrasse 7",
    "sg:city":"Port",
    "sg:orig_category":"Nationale Postdienste",
    "sg:phone":"+41 32 331 01 05",
    "sg:postcode":"2562",
    "sg:province":"Bern",
    "wof:name":"Die Schweizerische Post",
    "wof:placetype":"venue"
},
  "geometry": {"coordinates":[7.2535281181,47.1164207458],"type":"Point"}
}