{
  "type": "Feature",
  "properties": {
    "iso:country":"CH",
    "sg:address":"Route De Gen\u00e8ve 50",
    "sg:city":"Pr\u00e9verenges",
    "sg:orig_category":"Grosshandel mit Textilien",
    "sg:postcode":"1028",
    "sg:province":"Vaud",
    "wof:name":"Genoud Jean-louis",
    "wof:placetype":"venue"
},
  "geometry": {"coordinates":[6.5303688049,46.5164108276],"type":"Point"}
}