{
  "type": "Feature",
  "properties": {
    "iso:country":"CH",
    "sg:address":"8404",
    "sg:city":"Stadel(winterthur)",
    "sg:orig_category":"Softwareentwicklung U beratung",
    "sg:phone":"+41 52 246 01 60",
    "sg:postcode":"8404",
    "sg:province":"Z\u00fcrich",
    "wof:name":"Icad Gmbh Software-entwicklung",
    "wof:placetype":"venue"
},
  "geometry": {"coordinates":[8.7616548538,47.5344810486],"type":"Point"}
}