{
  "type": "Feature",
  "properties": {
    "iso:country":"CH",
    "sg:address":"B\u00fcnenweg 166",
    "sg:city":"Neuendorf",
    "sg:orig_category":"Herstellung von sonstigen elektrischen Ausr\u00fcstungen",
    "sg:phone":"+41 62 398 21 08",
    "sg:postcode":"4623",
    "sg:province":"Solothurn",
    "wof:name":"Ehmann Erich",
    "wof:placetype":"venue"
},
  "geometry": {"coordinates":[7.8003702164,47.297088623],"type":"Point"}
}