{
  "type": "Feature",
  "properties": {
    "iso:country":"CH",
    "sg:address":"August-d\u00fcr-weg 8",
    "sg:city":"Burgdorf",
    "sg:orig_category":"Pensionskassen",
    "sg:phone":"+41 34 422 07 55",
    "sg:postcode":"3400",
    "sg:province":"Bern",
    "wof:name":"Personalvorsorgestiftung Der Versicherungs-revisions-b\u00fcro Trees Ag",
    "wof:placetype":"venue"
},
  "geometry": {"coordinates":[7.6207442284,47.0544929504],"type":"Point"}
}