{
  "type": "Feature",
  "properties": {
    "iso:country":"CH",
    "sg:address":"Dancet Rue 1 1205 Gen\u00e8ve. Postfach",
    "sg:city":"Gen\u00e8ve",
    "sg:orig_category":"Allgemeiner Hoch U Tiefbau",
    "sg:phone":"+41 22 329 17 81",
    "sg:postcode":"1201",
    "sg:province":"Gen\u00e8ve",
    "wof:name":"Pitco, Barbieri Mario Tuyauterie Industrielle",
    "wof:placetype":"venue"
},
  "geometry": {"coordinates":[6.142161,46.194618],"type":"Point"}
}