{
  "type": "Feature",
  "properties": {
    "iso:country":"CH",
    "sg:address":"Landoltstrasse 1",
    "sg:city":"Bern",
    "sg:orig_category":"Caterer Fast-Foodrestaurants",
    "sg:phone":"+41 31 832 79 79",
    "sg:postcode":"3007",
    "sg:province":"Bern",
    "wof:name":"Paradies Pizza Express Cinki",
    "wof:placetype":"venue"
},
  "geometry": {"coordinates":[7.532713,46.930286],"type":"Point"}
}