{
  "type": "Feature",
  "properties": {
    "iso:country":"CH",
    "sg:address":"Rue De Cossonay",
    "sg:city":"Crissier",
    "sg:orig_category":"Tankstellen",
    "sg:phone":"+41 21 636 15 18",
    "sg:postcode":"1023",
    "sg:province":"Vaud",
    "wof:name":"Bp (switzerland)",
    "wof:placetype":"venue"
},
  "geometry": {"coordinates":[6.5677337646,46.5601654053],"type":"Point"}
}