{
  "type": "Feature",
  "properties": {
    "iso:country":"CH",
    "sg:address":"Kohlenberg 1 4051 Basel. Postfach",
    "sg:city":"Basel",
    "sg:orig_category":"Berufliche Weiterbildung, Erwachsenenbildung Sprachschulen",
    "sg:phone":"+41 22 807 30 00",
    "sg:postcode":"4001",
    "sg:province":"Basel-Stadt",
    "wof:name":"Ifage Augustins Institut De Formation Des Adultes Gen\u00e8ve",
    "wof:placetype":"venue"
},
  "geometry": {"coordinates":[6.144179,46.191017],"type":"Point"}
}