{
  "type": "Feature",
  "properties": {
    "iso:country":"CH",
    "sg:address":"Musy Avenue Jean-marie- 24",
    "sg:city":"Freiburg",
    "sg:orig_category":"Sonstiger spezialisierter Hoch U Tiefbau",
    "sg:postcode":"1700",
    "sg:province":"Fribourg",
    "wof:name":"Diego D'agostino Entreprise De Ma\u00e7onnerie",
    "wof:placetype":"venue"
},
  "geometry": {"coordinates":[7.1777639389,46.8094406128],"type":"Point"}
}