{
  "type": "Feature",
  "properties": {
    "iso:country":"CH",
    "sg:address":"Im Vogelsang",
    "sg:city":"Twann",
    "sg:orig_category":"Rebbau",
    "sg:phone":"+41 32 315 23 45",
    "sg:postcode":"2513",
    "sg:province":"Bern",
    "wof:name":"Manuel Krebs Weinbau",
    "wof:placetype":"venue"
},
  "geometry": {"coordinates":[7.1760549545,47.1039581299],"type":"Point"}
}