{
  "type": "Feature",
  "properties": {
    "iso:country":"CH",
    "sg:address":"Sous Le Ch\u00e2teau-grillet",
    "sg:city":"Vich",
    "sg:orig_category":"HOTELS: MIT RESTAURANT RESTAURANTS: NICHT EIGENST\u00c4NDIG",
    "sg:phone":"+41 22 366 67 00",
    "sg:postcode":"1267",
    "sg:province":"Vaud",
    "wof:name":"H\u00f4tel Richemond H\u00e9ritage Sa",
    "wof:placetype":"venue"
},
  "geometry": {"coordinates":[6.2421088219,46.4333763123],"type":"Point"}
}