{
  "type": "Feature",
  "properties": {
    "iso:country":"CH",
    "sg:address":"Lidostrasse 5",
    "sg:city":"Luzern",
    "sg:orig_category":"Interessenvertretungen",
    "sg:phone":"+41 41 370 33 88",
    "sg:postcode":"6006",
    "sg:province":"Luzern",
    "wof:name":"Erni Hans-stiftung",
    "wof:placetype":"venue"
},
  "geometry": {"coordinates":[8.3355970383,47.0526161194],"type":"Point"}
}