{
  "type": "Feature",
  "properties": {
    "iso:country":"CH",
    "sg:address":"W\u00e4ngirain 19",
    "sg:city":"Herrliberg",
    "sg:orig_category":"Unternehmensberatung",
    "sg:postcode":"8704",
    "sg:province":"Z\u00fcrich",
    "wof:name":"Paso Beratungs Ag",
    "wof:placetype":"venue"
},
  "geometry": {"coordinates":[8.6181020737,47.2910766602],"type":"Point"}
}