{
  "type": "Feature",
  "properties": {
    "iso:country":"CH",
    "sg:address":"Ringstrasse 35b 7000 Chur. Postfach 30",
    "sg:city":"Chur",
    "sg:orig_category":"Werbevermittlung",
    "sg:phone":"+41 79 301 43 10",
    "sg:postcode":"7004",
    "sg:province":"Graubunden",
    "wof:name":"Apg/sga Allgemeine Plakatgesellschaft",
    "wof:placetype":"venue"
},
  "geometry": {"coordinates":[6.8132882118,47.0927391052],"type":"Point"}
}