{
  "type": "Feature",
  "properties": {
    "addr:full":"Monbijoustrasse 73 Bern Bern 3007",
    "addr:housenumber":"73",
    "addr:postcode":"3007",
    "addr:street":"Monbijoustrasse",
    "iso:country":"CH",
    "sg:address":"Monbijoustrasse 73",
    "sg:city":"Bern",
    "sg:orig_category":"Advokaturb\u00fcros",
    "sg:phone":"+41 31 378 17 17",
    "sg:postcode":"3007",
    "sg:province":"Bern",
    "wof:name":"Schmocker & Scheurer Advokaturb\u00fcro",
    "wof:placetype":"venue"
},
  "geometry": {"coordinates":[7.435998,46.940235],"type":"Point"}
}