{
  "type": "Feature",
  "properties": {
    "iso:country":"CH",
    "sg:address":"Bergli",
    "sg:city":"D\u00fcrrenroth",
    "sg:orig_category":"Kaminfeger",
    "sg:phone":"+41 62 964 12 68",
    "sg:postcode":"3465",
    "sg:province":"Bern",
    "wof:name":"Markus Sch\u00e4r Kaminfeger",
    "wof:placetype":"venue"
},
  "geometry": {"coordinates":[7.791601181,47.0899848938],"type":"Point"}
}