{
  "type": "Feature",
  "properties": {
    "iso:country":"CH",
    "sg:address":"Meinier Route De 6 1253 Vandoeuvres. Postfach",
    "sg:city":"Vandoeuvres",
    "sg:orig_category":"Herstellung von sonstigen Erzeugnissen",
    "sg:postcode":"1253",
    "sg:province":"Gen\u00e8ve",
    "wof:name":"Morillas Claudine Mizensir Bougies Parfum\u00e9es; Fabrication Et Vente",
    "wof:placetype":"venue"
},
  "geometry": {"coordinates":[6.2022547722,46.2213287354],"type":"Point"}
}