{
  "type": "Feature",
  "properties": {
    "iso:country":"CH",
    "sg:address":"Jurastrasse 26",
    "sg:city":"Laufen",
    "sg:orig_category":"Erschliessung von Grundst\u00fccken",
    "sg:postcode":"4242",
    "sg:province":"Basel-Landschaft",
    "wof:name":"Bau Und Verwaltungsgenossenschaft Bleiholle",
    "wof:placetype":"venue"
},
  "geometry": {"coordinates":[7.512155056,47.4222145081],"type":"Point"}
}