{
  "type": "Feature",
  "properties": {
    "iso:country":"CH",
    "sg:address":"Masanserstrasse 4",
    "sg:city":"Chur",
    "sg:orig_category":"Schweineaufzucht U mast",
    "sg:phone":"+41 71 385 28 76",
    "sg:postcode":"7000",
    "sg:province":"Graubunden",
    "wof:name":"Schweinezucht H\u00f6frig Gmbh",
    "wof:placetype":"venue"
},
  "geometry": {"coordinates":[9.2210578918,47.4160842896],"type":"Point"}
}