{
  "type": "Feature",
  "properties": {
    "addr:full":"1874 Champ\u00e9ry Valais 1874",
    "addr:housenumber":"1874",
    "addr:postcode":"1874",
    "iso:country":"CH",
    "sg:address":"1874",
    "sg:city":"Champ\u00e9ry",
    "sg:orig_category":"Detailhandel an Verkaufsst\u00e4nden U auf M\u00e4rkten",
    "sg:postcode":"1874",
    "sg:province":"Valais",
    "wof:name":"Z\u00fcrcher-gapan Gilda",
    "wof:placetype":"venue"
},
  "geometry": {"coordinates":[7.403656,47.151005],"type":"Point"}
}