{
  "type": "Feature",
  "properties": {
    "iso:country":"CH",
    "sg:address":"Dorfstr. 49",
    "sg:city":"Weisslingen",
    "sg:classifiers":[
        {
            "category":"Home & Garden",
            "subcategory":"Furniture",
            "type":"Retail Goods"
        }
    ],
    "sg:phone":"+41 52 384 11 31",
    "sg:postcode":"8484",
    "sg:province":"Z\u00fcrich",
    "sg:tags":[
        "household",
        "wood"
    ],
    "wof:name":"Freba-m\u00d6bel Ag",
    "wof:placetype":"venue"
},
  "geometry": {"coordinates":[8.763133049,47.4339370728],"type":"Point"}
}