{
  "type": "Feature",
  "properties": {
    "iso:country":"CH",
    "sg:address":"8816",
    "sg:city":"Hirzel",
    "sg:orig_category":"Sportvereine Sch\u00fctzen Pistolen-& Gewehr",
    "sg:postcode":"8816",
    "sg:province":"Z\u00fcrich",
    "wof:name":"Sch\u00fctzenverein",
    "wof:placetype":"venue"
},
  "geometry": {"coordinates":[8.6067199707,47.2151374817],"type":"Point"}
}