{
  "type": "Feature",
  "properties": {
    "iso:country":"CH",
    "sg:address":"Via Casate 6883 Novazzano. Postfach",
    "sg:city":"Novazzano",
    "sg:orig_category":"Handels-H\u00e4user U Gesellschaften",
    "sg:postcode":"6883",
    "sg:province":"Ticino",
    "wof:name":"Grubex Anstalt, Vaduz, Succursale Di Novazzano Commercio, Finanziamento Ecc",
    "wof:placetype":"venue"
},
  "geometry": {"coordinates":[8.9732513428,45.8430938721],"type":"Point"}
}