{
  "type": "Feature",
  "properties": {
    "iso:country":"CH",
    "sg:address":"Via Cantonale",
    "sg:city":"Riazzino",
    "sg:orig_category":"Non-Classified Establishments",
    "sg:postcode":"6595",
    "sg:province":"Ticino",
    "wof:name":"Termocolor Sagl",
    "wof:placetype":"venue"
},
  "geometry": {"coordinates":[8.9000196457,46.1742401123],"type":"Point"}
}