{
  "type": "Feature",
  "properties": {
    "iso:country":"CH",
    "sg:address":"Rue De La Gare 11 1260 Nyon. Postfach",
    "sg:city":"Nyon",
    "sg:orig_category":"Fachdetailhandel in Verkaufsr\u00e4umen",
    "sg:postcode":"1260",
    "sg:province":"Vaud",
    "wof:name":"Hobbyland Mod\u00e9lisme S\u00e0rl",
    "wof:placetype":"venue"
},
  "geometry": {"coordinates":[6.2381367683,46.3825073242],"type":"Point"}
}