{
  "type": "Feature",
  "properties": {
    "iso:country":"CH",
    "sg:address":"Vordergasse 80-84 8200 Schaffhausen. Postfach 66",
    "sg:city":"Schaffhausen",
    "sg:orig_category":"Detailhandel mit Uhren U Schmuck Fachdetailhandel in Verkaufsr\u00e4umen",
    "sg:phone":"+41 52 625 36 94",
    "sg:postcode":"8201",
    "sg:province":"Schaffhausen",
    "wof:name":"Bertsche & Reschek",
    "wof:placetype":"venue"
},
  "geometry": {"coordinates":[8.6339693069,47.6965255737],"type":"Point"}
}