{
  "type": "Feature",
  "properties": {
    "iso:country":"CH",
    "sg:address":"Bernstrasse 124",
    "sg:city":"Steffisburg",
    "sg:orig_category":"Religi\u00f6se Vereinigungen divers",
    "sg:phone":"+41 81 833 44 65",
    "sg:postcode":"3613",
    "sg:province":"Bern",
    "wof:name":"Freimaurer-zirkel Aurora",
    "wof:placetype":"venue"
},
  "geometry": {"coordinates":[9.8381900787,46.4970588684],"type":"Point"}
}