{
  "type": "Feature",
  "properties": {
    "iso:country":"CH",
    "sg:address":"1233 Bernex Case Postale 371",
    "sg:city":"Bernex",
    "sg:orig_category":"Schulpflegen",
    "sg:postcode":"1233",
    "sg:province":"Gen\u00e8ve",
    "wof:name":"Commission Scolaire De L'\u00e9cole Secondaire",
    "wof:placetype":"venue"
},
  "geometry": {"coordinates":[6.0726900101,46.1749458313],"type":"Point"}
}