{
  "type": "Feature",
  "properties": {
    "iso:country":"CH",
    "sg:address":"Goethestrasse 16",
    "sg:city":"Z\u00fcrich",
    "sg:orig_category":"Physiotherapie",
    "sg:phone":"+41 12521230",
    "sg:postcode":"8001",
    "sg:province":"Z\u00fcrich",
    "wof:name":"Linda & Jiri Andreska Physiotherapie",
    "wof:placetype":"venue"
},
  "geometry": {"coordinates":[8.5478544235,47.3658065796],"type":"Point"}
}