{
  "type": "Feature",
  "properties": {
    "iso:country":"CH",
    "sg:address":"Asylstrasse 58 8032 Z\u00fcrich. Postfach",
    "sg:city":"Z\u00fcrich",
    "sg:orig_category":"Fachdetailhandel mit pharmazeutischen Produkten",
    "sg:phone":"+41 12516010",
    "sg:postcode":"8030",
    "wof:name":"R\u00f6merhof-apotheke, Schaub Dr. E.",
    "wof:placetype":"venue"
},
  "geometry": {"coordinates":[8.5597505569,47.3681373596],"type":"Point"}
}