{
  "type": "Feature",
  "properties": {
    "iso:country":"CH",
    "sg:address":"8884",
    "sg:city":"Oberterzen",
    "sg:orig_category":"Sportvereine Sch\u00fctzen",
    "sg:phone":"+41 81 784 63 82",
    "sg:postcode":"8884",
    "sg:province":"St. Gallen",
    "wof:name":"Sch\u00fctzengesellschaft",
    "wof:placetype":"venue"
},
  "geometry": {"coordinates":[9.2594003677,47.0967788696],"type":"Point"}
}