{
  "type": "Feature",
  "properties": {
    "iso:country":"CH",
    "sg:address":"St\u00e4dtchen 35",
    "sg:city":"Aarburg",
    "sg:orig_category":"Museen",
    "sg:phone":"+41 62 791 30 51",
    "sg:postcode":"4663",
    "sg:province":"Aargau",
    "wof:name":"Heimatmuseum Aarburg",
    "wof:placetype":"venue"
},
  "geometry": {"coordinates":[7.8989200592,47.3215904236],"type":"Point"}
}