{
  "type": "Feature",
  "properties": {
    "iso:country":"CH",
    "sg:address":"Colline Rue De La 10 1205 Gen\u00e8ve. Postfach",
    "sg:city":"Gen\u00e8ve",
    "sg:orig_category":"M\u00f6belschreinereien",
    "sg:postcode":"1205",
    "sg:province":"Gen\u00e8ve",
    "wof:name":"Atelier Meuble, Benedetti",
    "wof:placetype":"venue"
},
  "geometry": {"coordinates":[6.142701149,46.2083587646],"type":"Point"}
}