{
  "type": "Feature",
  "properties": {
    "iso:country":"CH",
    "sg:address":"Bahnhofstrasse 16",
    "sg:city":"Lyssach",
    "sg:classifiers":[
        {
            "category":"Restaurant",
            "type":"Food & Drink"
        }
    ],
    "sg:phone":"+41 34 445 25 12",
    "sg:postcode":"3421",
    "sg:province":"Bern",
    "wof:name":"Restaurant Zur Krone",
    "wof:placetype":"venue"
},
  "geometry": {"coordinates":[7.5811538696,47.0639953613],"type":"Point"}
}