{
  "type": "Feature",
  "properties": {
    "iso:country":"CH",
    "sg:address":"Rue Du Coppet 4",
    "sg:city":"Monthey",
    "sg:orig_category":"Detailhandel mit Fleisch U Fleischwaren",
    "sg:phone":"+41 24 471 43 45",
    "sg:postcode":"1870",
    "sg:province":"Valais",
    "wof:name":"Boucherie Souvel Sa",
    "wof:placetype":"venue"
},
  "geometry": {"coordinates":[6.9491910934,46.2522583008],"type":"Point"}
}