{
  "type": "Feature",
  "properties": {
    "iso:country":"CH",
    "sg:address":"Col-des-planches",
    "sg:city":"Chemin",
    "sg:classifiers":[
        {
            "category":"Restaurant",
            "type":"Food & Drink"
        }
    ],
    "sg:phone":"+41 27 785 15 50",
    "sg:postcode":"1927",
    "sg:province":"Valais",
    "wof:name":"Restaurant Col-des-planches",
    "wof:placetype":"venue"
},
  "geometry": {"coordinates":[7.0961899757,46.0895690918],"type":"Point"}
}