{
  "type": "Feature",
  "properties": {
    "iso:country":"CH",
    "sg:address":"H\u00f4pital Rue De L' 11 1920 Martigny. Postfach",
    "sg:city":"Martigny",
    "sg:orig_category":"Sonstiger Grosshandel",
    "sg:postcode":"1920",
    "sg:province":"Valais",
    "wof:name":"Laboratoire D. Roland Genes Sa",
    "wof:placetype":"venue"
},
  "geometry": {"coordinates":[1.2019699812,49.8808860779],"type":"Point"}
}