{
  "type": "Feature",
  "properties": {
    "iso:country":"CH",
    "sg:address":"Chemin De La Boine 31",
    "sg:city":"Neuch\u00e2tel",
    "sg:orig_category":"Sonstige Kultur U Unterhaltungseinrichtungen",
    "sg:phone":"+41 32 725 47 25",
    "sg:postcode":"2000",
    "sg:province":"Neuch\u00e2tel",
    "wof:name":"Centre De Loisirs",
    "wof:placetype":"venue"
},
  "geometry": {"coordinates":[6.9285597801,46.9942207336],"type":"Point"}
}