{
  "type": "Feature",
  "properties": {
    "iso:country":"CH",
    "sg:address":"Thurgauerstrasse 40 8050 Z\u00fcrich 50 Zust. Postfach 8050 Z\u00fcrich",
    "sg:city":"Zust",
    "sg:orig_category":"Finanzierungsinstitutionen",
    "sg:phone":"+41 71 243 33 53",
    "sg:postcode":"50",
    "wof:name":"Firuma Investment Ag Investitionsgesch\u00e4fte Usw",
    "wof:placetype":"venue"
},
  "geometry": {"coordinates":[9.3975152969,47.4400367737],"type":"Point"}
}