{
  "type": "Feature",
  "properties": {
    "iso:country":"CH",
    "sg:address":"Rebackerstrasse 17",
    "sg:city":"Horgen",
    "sg:orig_category":"Non-Classified Establishments",
    "sg:postcode":"8810",
    "sg:province":"Z\u00fcrich",
    "wof:name":"Business Linx Gmbh",
    "wof:placetype":"venue"
},
  "geometry": {"coordinates":[8.5902633667,47.2590141296],"type":"Point"}
}