{
  "type": "Feature",
  "properties": {
    "iso:country":"CH",
    "sg:address":"Centre Du Village 4",
    "sg:city":"Boudevilliers",
    "sg:orig_category":"Non-Classified Establishments",
    "sg:postcode":"2043",
    "sg:province":"Neuch\u00e2tel",
    "wof:name":"Balmer & Fils Sa",
    "wof:placetype":"venue"
},
  "geometry": {"coordinates":[6.8892989159,47.0264320374],"type":"Point"}
}