{
  "type": "Feature",
  "properties": {
    "iso:country":"CH",
    "sg:address":"Schmittengasse 4",
    "sg:city":"Bettlach",
    "sg:orig_category":"Mechanik Schlossereien",
    "sg:phone":"+41 32 645 32 34",
    "sg:postcode":"2544",
    "sg:province":"Solothurn",
    "wof:name":"Eggimann E. + F.",
    "wof:placetype":"venue"
},
  "geometry": {"coordinates":[7.4228839874,47.2026863098],"type":"Point"}
}