{
  "type": "Feature",
  "properties": {
    "iso:country":"CH",
    "sg:address":"Beim Bahnhof 3970 Salgesch. Postfach",
    "sg:city":"Salgesch",
    "sg:orig_category":"Grosshandel mit Getr\u00e4nken Rebbau",
    "sg:phone":"+41 27 455 17 57",
    "sg:postcode":"3970",
    "sg:province":"Valais",
    "wof:name":"Mathier Franz-josef Ag Weinproduzenten Und Weinhandlung",
    "wof:placetype":"venue"
},
  "geometry": {"coordinates":[7.5726728439,46.3110084534],"type":"Point"}
}