{
  "type": "Feature",
  "properties": {
    "iso:country":"CH",
    "sg:address":"Borromini Via Francesco 20a",
    "sg:city":"Mendrisio",
    "sg:orig_category":"Saunas, Solarien, Fitnesszentren U \u00e4hnliches",
    "sg:postcode":"6850",
    "sg:province":"Ticino",
    "wof:name":"Quality Di Medolago Paolo",
    "wof:placetype":"venue"
},
  "geometry": {"coordinates":[8.9743938446,45.8692169189],"type":"Point"}
}