{
  "type": "Feature",
  "properties": {
    "iso:country":"CH",
    "sg:address":"Ziegelbr\u00fcckstrasse 35",
    "sg:city":"Niederurnen",
    "sg:orig_category":"Polizei",
    "sg:phone":"+41 55 644 10 93",
    "sg:postcode":"8867",
    "sg:province":"Glarus",
    "wof:name":"Polizeistation",
    "wof:placetype":"venue"
},
  "geometry": {"coordinates":[9.0725097656,46.9936103821],"type":"Point"}
}