{
  "type": "Feature",
  "properties": {
    "iso:country":"CH",
    "sg:address":"Bettengasse 69",
    "sg:city":"Wilchingen",
    "sg:orig_category":"Bauschreinerei Herstellung von Konstruktionsteilen, Fertigbauteilen U Ausbauelementen aus Holz",
    "sg:phone":"+41 71 855 15 42",
    "sg:postcode":"8217",
    "sg:province":"Schaffhausen",
    "wof:name":"G\u00e4hler Holz Ag Staad",
    "wof:placetype":"venue"
},
  "geometry": {"coordinates":[9.542868,47.483376],"type":"Point"}
}