{
  "type": "Feature",
  "properties": {
    "iso:country":"CH",
    "sg:address":"9473 Gams. Postfach 55",
    "sg:city":"Gams",
    "sg:orig_category":"Sportvereine Ballsport Fussball",
    "sg:phone":"+41 81 771 24 00",
    "sg:postcode":"9473",
    "sg:province":"St. Gallen",
    "wof:name":"Fc Gams",
    "wof:placetype":"venue"
},
  "geometry": {"coordinates":[9.4422750473,47.2040710449],"type":"Point"}
}