{
  "type": "Feature",
  "properties": {
    "iso:country":"CH",
    "sg:address":"Hasenberg 77",
    "sg:city":"Widen",
    "sg:orig_category":"Interessenvertretungen",
    "sg:phone":"+41 56 649 25 25",
    "sg:postcode":"8967",
    "sg:province":"Aargau",
    "wof:name":"Stiftung Haus Morgenstern",
    "wof:placetype":"venue"
},
  "geometry": {"coordinates":[8.3638181686,47.3789787292],"type":"Point"}
}