{
  "type": "Feature",
  "properties": {
    "iso:country":"CH",
    "sg:address":"Monbijoustrasse 33 3011 Bern. Postfach 6336",
    "sg:city":"Bern",
    "sg:orig_category":"Arbeitnehmerverb\u00e4nde",
    "sg:phone":"+41 41 210 47 77",
    "sg:postcode":"3001",
    "sg:province":"Bern",
    "wof:name":"Comedia Mediengewerkschaft Sektion Luzern,sekretariat",
    "wof:placetype":"venue"
},
  "geometry": {"coordinates":[8.30693,47.044781],"type":"Point"}
}