{
  "type": "Feature",
  "properties": {
    "iso:country":"CH",
    "sg:address":"Irchelstrasse 16",
    "sg:city":"Embrach",
    "sg:orig_category":"Religi\u00f6se Vereinigungen divers",
    "sg:phone":"+41 52 720 44 64",
    "sg:postcode":"8424",
    "sg:province":"Z\u00fcrich",
    "wof:name":"Cvjm",
    "wof:placetype":"venue"
},
  "geometry": {"coordinates":[8.5908813477,47.5161819458],"type":"Point"}
}