{
  "type": "Feature",
  "properties": {
    "iso:country":"CH",
    "sg:address":"Dorfgasse 12",
    "sg:city":"Niederdorf",
    "sg:orig_category":"Herstellung von Metallerzeugnissen ohne Maschinenbau Herstellung von Verbrennungsmotoren U Turbinen ",
    "sg:phone":"+41 61 956 24 73",
    "sg:postcode":"4435",
    "sg:province":"Basel-Landschaft",
    "wof:name":"Menag Service Ag",
    "wof:placetype":"venue"
},
  "geometry": {"coordinates":[7.7514410019,47.4032859802],"type":"Point"}
}