{
  "type": "Feature",
  "properties": {
    "iso:country":"CH",
    "sg:address":"Achseten Steg",
    "sg:city":"Frutigen",
    "sg:orig_category":"Detailhandel mit Brot, Back U S\u00fcsswaren",
    "sg:postcode":"3714",
    "sg:province":"Bern",
    "wof:name":"Albert Lauber-bircher",
    "wof:placetype":"venue"
},
  "geometry": {"coordinates":[7.622759,46.550728],"type":"Point"}
}