{
  "type": "Feature",
  "properties": {
    "iso:country":"CH",
    "sg:address":"Albisweg 8",
    "sg:city":"Boswil",
    "sg:orig_category":"Allgemeiner Hoch U Tiefbau Allgemeiner Hochbau",
    "sg:phone":"+41 56 666 16 08",
    "sg:postcode":"5623",
    "sg:province":"Aargau",
    "wof:name":"Bucher & Joho Ag",
    "wof:placetype":"venue"
},
  "geometry": {"coordinates":[8.31911,47.296013],"type":"Point"}
}