{
  "type": "Feature",
  "properties": {
    "iso:country":"CH",
    "sg:address":"Lowmattweg 6",
    "sg:city":"Udligenswil",
    "sg:orig_category":"Herstellung von Elektrizit\u00e4tsverteilungs U schalteinrichtungen",
    "sg:phone":"+41 41 371 11 46",
    "sg:postcode":"6044",
    "sg:province":"Luzern",
    "wof:name":"Balzaretti & Frey Ag",
    "wof:placetype":"venue"
},
  "geometry": {"coordinates":[8.404841423,47.0913276672],"type":"Point"}
}