{
  "type": "Feature",
  "properties": {
    "iso:country":"CH",
    "sg:address":"3949",
    "sg:city":"Hohtenn",
    "sg:orig_category":"Detailhandel mit Waren verschiedener Art, Hauptrichtung Nahrungsmittel",
    "sg:phone":"+41 27 932 16 23",
    "sg:postcode":"3949",
    "sg:province":"Valais",
    "wof:name":"Josef Kalbermatten Handlung",
    "wof:placetype":"venue"
},
  "geometry": {"coordinates":[7.7569499016,46.3188095093],"type":"Point"}
}