{
  "type": "Feature",
  "properties": {
    "iso:country":"CH",
    "sg:address":"Im Dorf 79b",
    "sg:city":"Schellenberg",
    "sg:orig_category":"Rechtsberatung Unternehmensberatung",
    "sg:phone":"+41 79 213 12 32",
    "sg:postcode":"9488",
    "wof:name":"Dr. Wohlwend Treuunternehmen Reg.",
    "wof:placetype":"venue"
},
  "geometry": {"coordinates":[9.5476284027,47.2328643799],"type":"Point"}
}