{
  "type": "Feature",
  "properties": {
    "iso:country":"CH",
    "sg:address":"Ludetswil",
    "sg:city":"Russikon",
    "sg:orig_category":"Grosshandel mit lebenden Tieren",
    "sg:postcode":"8332",
    "sg:province":"Z\u00fcrich",
    "wof:name":"Aeschlimann Fritz",
    "wof:placetype":"venue"
},
  "geometry": {"coordinates":[8.8001346588,47.4192428589],"type":"Point"}
}