{
  "type": "Feature",
  "properties": {
    "iso:country":"CH",
    "sg:address":"Katharinengasse 21",
    "sg:city":"St.gallen",
    "sg:orig_category":"Religi\u00f6se Vereinigungen",
    "sg:phone":"+41 71 222 37 90",
    "sg:postcode":"9000",
    "sg:province":"St. Gallen",
    "wof:name":"Stadtmission, Freie Evangelische Gemeinde, St. Gallen, Filiale Vadian Buchhandlung",
    "wof:placetype":"venue"
},
  "geometry": {"coordinates":[9.3769855499,47.4273338318],"type":"Point"}
}