{
  "type": "Feature",
  "properties": {
    "iso:country":"CH",
    "sg:address":"Plam Dil Bl\u00e4si",
    "sg:city":"Lenzerheide/lai",
    "sg:orig_category":"Vermittlung von Immobilien Verwaltung von Immobilien",
    "sg:phone":"+41 81 384 45 50",
    "sg:postcode":"7078",
    "sg:province":"Graubunden",
    "wof:name":"Bergason Immobilien Ag",
    "wof:placetype":"venue"
},
  "geometry": {"coordinates":[9.559217453,46.7203407288],"type":"Point"}
}