{
  "type": "Feature",
  "properties": {
    "iso:country":"CH",
    "sg:address":"Via S.gottardo",
    "sg:city":"Gordola",
    "sg:orig_category":"Herstellung von Metallkonstruktionen Mechanik",
    "sg:phone":"+41 91 745 44 89",
    "sg:postcode":"6596",
    "sg:province":"Ticino",
    "wof:name":"Pezzolla E G\u00fcnter",
    "wof:placetype":"venue"
},
  "geometry": {"coordinates":[8.858505249,46.1816749573],"type":"Point"}
}