{
  "type": "Feature",
  "properties": {
    "iso:country":"CH",
    "sg:address":"Bifangweg 7",
    "sg:city":"Rothrist",
    "sg:orig_category":"Elektroinstallation Herstellung von Elektromotoren, Generatoren U Transformatoren",
    "sg:phone":"+41 79 406 45 18",
    "sg:postcode":"4852",
    "sg:province":"Aargau",
    "wof:name":"Elektro-technik Sch\u00f6n G.",
    "wof:placetype":"venue"
},
  "geometry": {"coordinates":[8.7978916168,47.3218612671],"type":"Point"}
}