{
  "type": "Feature",
  "properties": {
    "iso:country":"CH",
    "sg:address":"H\u00f6lderlistrasse 17",
    "sg:city":"Schleitheim",
    "sg:orig_category":"Verkehrs- and Tourismusb\u00fcros",
    "sg:phone":"+41 52 680 18 67",
    "sg:postcode":"8226",
    "sg:province":"Schaffhausen",
    "wof:name":"Verkehrsverein Schleitheim Pr\u00e4s.herrn Rudolf Keller",
    "wof:placetype":"venue"
},
  "geometry": {"coordinates":[8.475435257,47.7478256226],"type":"Point"}
}