{
  "type": "Feature",
  "properties": {
    "iso:country":"CH",
    "sg:address":"Hauptstrasse 100",
    "sg:city":"Wallbach",
    "sg:orig_category":"RESTAURANTS: TEA-ROOMS",
    "sg:postcode":"4323",
    "sg:province":"Aargau",
    "wof:name":"M\u00fcller + Co.",
    "wof:placetype":"venue"
},
  "geometry": {"coordinates":[7.9057660103,47.5572624207],"type":"Point"}
}