{
  "type": "Feature",
  "properties": {
    "iso:country":"CH",
    "sg:address":"Fendringen",
    "sg:city":"B\u00f6singen",
    "sg:orig_category":"Unclassifiable Establishments",
    "sg:postcode":"3178",
    "sg:province":"Fribourg",
    "wof:name":"Bertei Irene + Luigi",
    "wof:placetype":"venue"
},
  "geometry": {"coordinates":[7.2416858673,46.8834190369],"type":"Point"}
}