{
  "type": "Feature",
  "properties": {
    "iso:country":"CH",
    "sg:address":"Zentralstrasse 13",
    "sg:city":"Biel/bienne",
    "sg:orig_category":"Detailhandel mit Geschenkartikeln U Souvenirs",
    "sg:phone":"+41 32 322 10 58",
    "sg:postcode":"2502",
    "sg:province":"Bern",
    "wof:name":"Lucie Paratte Potier Chez Lucie",
    "wof:placetype":"venue"
},
  "geometry": {"coordinates":[7.2446241379,47.1390800476],"type":"Point"}
}