{
  "type": "Feature",
  "properties": {
    "iso:country":"CH",
    "sg:address":"Rheinstrasse 30",
    "sg:city":"Schaffhausen",
    "sg:orig_category":"Sonstiger Grosshandel",
    "sg:phone":"+41 52 620 27 17",
    "sg:postcode":"8200",
    "sg:province":"Schaffhausen",
    "wof:name":"Pedale Velos & Zubeh\u00f6r",
    "wof:placetype":"venue"
},
  "geometry": {"coordinates":[8.6329431534,47.6939353943],"type":"Point"}
}