{
  "type": "Feature",
  "properties": {
    "addr:full":"Kreuzgutweg 22 Schaffhausen Schaffhausen 8207",
    "addr:housenumber":"22",
    "addr:postcode":"8207",
    "addr:street":"Kreuzgutweg",
    "iso:country":"CH",
    "sg:address":"Kreuzgutweg 22",
    "sg:city":"Schaffhausen",
    "sg:orig_category":"Datenverarbeitungsdienste",
    "sg:phone":"+41 52 643 68 80",
    "sg:postcode":"8207",
    "sg:province":"Schaffhausen",
    "wof:name":"Daseco Ag",
    "wof:placetype":"venue"
},
  "geometry": {"coordinates":[8.658975,47.724545],"type":"Point"}
}