{
  "type": "Feature",
  "properties": {
    "iso:country":"CH",
    "sg:address":"Im Ifang 10 Effretikon 8308 Horben B. Illnau. Postfach",
    "sg:city":"Tagelswangen",
    "sg:orig_category":"Herstellung von elektronischen Bauelementen",
    "sg:postcode":"8317",
    "sg:province":"Z\u00fcrich",
    "wof:name":"Valevoag",
    "wof:placetype":"venue"
},
  "geometry": {"coordinates":[8.7239246368,47.4074707031],"type":"Point"}
}