{
  "type": "Feature",
  "properties": {
    "iso:country":"CH",
    "sg:address":"Ruopigenh\u00f6he 11",
    "sg:city":"Reussb\u00fchl",
    "sg:orig_category":"Allgemeiner Hoch U Tiefbau Hoch U Tiefbau",
    "sg:phone":"+41 41 250 07 47",
    "sg:postcode":"6015",
    "sg:province":"Luzern",
    "wof:name":"A. Stirnimann Bauunternehmung",
    "wof:placetype":"venue"
},
  "geometry": {"coordinates":[8.27462,47.059902],"type":"Point"}
}