{
  "type": "Feature",
  "properties": {
    "iso:country":"CH",
    "sg:address":"Hummelwaldstrasse 28 8865 Bilten. Postfach",
    "sg:city":"Bilten",
    "sg:orig_category":"Allgemeiner Hochbau Verwaltung von Immobilien",
    "sg:phone":"+41 56 619 50 40",
    "sg:postcode":"8865",
    "sg:province":"Glarus",
    "wof:name":"A. Stenz Immobilien Niederwil",
    "wof:placetype":"venue"
},
  "geometry": {"coordinates":[8.296142,47.38419],"type":"Point"}
}