{
  "type": "Feature",
  "properties": {
    "iso:country":"CH",
    "sg:address":"Obermattweg 1",
    "sg:city":"Meinisberg",
    "sg:orig_category":"Betrieb von Sportanlagen",
    "sg:phone":"+41 32 377 20 47",
    "sg:postcode":"2554",
    "sg:province":"Bern",
    "wof:name":"Reitanlage Zur Alten Aare",
    "wof:placetype":"venue"
},
  "geometry": {"coordinates":[7.342574,47.152969],"type":"Point"}
}