{
  "type": "Feature",
  "properties": {
    "iso:country":"CH",
    "sg:address":"Inzlingerstrasse 61",
    "sg:city":"Riehen",
    "sg:orig_category":"Ingenieurb\u00fcros Schwer-& Leichtmetall",
    "sg:phone":"+41 61 643 25 85",
    "sg:postcode":"4125",
    "sg:province":"Basel-Stadt",
    "wof:name":"Philippe Petignat Pp Engineering Petignat",
    "wof:placetype":"venue"
},
  "geometry": {"coordinates":[7.6546740532,47.5878105164],"type":"Point"}
}