{
  "type": "Feature",
  "properties": {
    "iso:country":"CH",
    "sg:address":"Bahnhofstr. 48",
    "sg:city":"Buchs",
    "sg:classifiers":[
        {
            "category":"Banks & Credit Unions",
            "subcategory":"Bank",
            "type":"Services"
        }
    ],
    "sg:phone":"+41 41 856 34 22",
    "sg:postcode":"9470",
    "sg:province":"St. Gallen",
    "wof:name":"Cr\u00e9dit Suisse",
    "wof:placetype":"venue"
},
  "geometry": {"coordinates":[9.47194,47.165924],"type":"Point"}
}