{
  "type": "Feature",
  "properties": {
    "iso:country":"CH",
    "sg:address":"Rue Des Pr\u00e9jures 8",
    "sg:city":"Tavannes",
    "sg:orig_category":"Stukkateurgewerbe, Gipserei U Verputzerei",
    "sg:phone":"+41 32 932 10 63",
    "sg:postcode":"2710",
    "sg:province":"Bern",
    "wof:name":"Dannecker Bernard, Pl\u00e2trerie Et Peinture",
    "wof:placetype":"venue"
},
  "geometry": {"coordinates":[6.7093629837,47.0703392029],"type":"Point"}
}