{
  "type": "Feature",
  "properties": {
    "iso:country":"CH",
    "sg:address":"In Der Schappe 22",
    "sg:city":"Arlesheim",
    "sg:orig_category":"Unternehmensberatung",
    "sg:phone":"+41 61 701 74 57",
    "sg:postcode":"4144",
    "sg:province":"Basel-Landschaft",
    "wof:name":"Bscrm Company Gmbh",
    "wof:placetype":"venue"
},
  "geometry": {"coordinates":[7.6070899963,47.4935417175],"type":"Point"}
}