{
  "type": "Feature",
  "properties": {
    "addr:full":"Allschwilerstrasse 50 Basel Basel-Stadt 4055",
    "addr:housenumber":"50",
    "addr:postcode":"4055",
    "addr:street":"Allschwilerstrasse",
    "iso:country":"CH",
    "sg:address":"Allschwilerstrasse 50",
    "sg:city":"Basel",
    "sg:orig_category":"Betrieb von Taxis",
    "sg:phone":"+41 61 302 46 66",
    "sg:postcode":"4055",
    "sg:province":"Basel-Stadt",
    "wof:name":"Ren\u00e9 Abt Taxi",
    "wof:placetype":"venue"
},
  "geometry": {"coordinates":[7.571954,47.556759],"type":"Point"}
}