{
  "type": "Feature",
  "properties": {
    "iso:country":"CH",
    "sg:address":"Chemin Des Carrels 11d",
    "sg:city":"Peseux",
    "sg:orig_category":"Kaminfeger",
    "sg:phone":"+41 32 731 77 37",
    "sg:postcode":"2034",
    "sg:province":"Neuch\u00e2tel",
    "wof:name":"Daniel Villommet Maitre Ramoneur",
    "wof:placetype":"venue"
},
  "geometry": {"coordinates":[6.8981790543,46.9893112183],"type":"Point"}
}