{
  "type": "Feature",
  "properties": {
    "iso:country":"CH",
    "sg:address":"Stetterstrasse 25",
    "sg:city":"Mellingen",
    "sg:orig_category":"Gymnastik U Fitnesszentren",
    "sg:phone":"+41 56 491 22 20",
    "sg:postcode":"5507",
    "sg:province":"Aargau",
    "wof:name":"Sport-arena Fitness-center",
    "wof:placetype":"venue"
},
  "geometry": {"coordinates":[8.2784357071,47.4184036255],"type":"Point"}
}