{
  "type": "Feature",
  "properties": {
    "addr:full":"1812 Rivaz 1812",
    "addr:housenumber":"1812",
    "addr:postcode":"1812",
    "addr:street":"Rivaz",
    "iso:country":"CH",
    "sg:address":"1812",
    "sg:city":"Rivaz",
    "sg:orig_category":"Dauerkulturbau",
    "sg:postcode":"1812",
    "wof:name":"Cave Du Manoir Sa",
    "wof:placetype":"venue"
},
  "geometry": {"coordinates":[7.18193,46.188934],"type":"Point"}
}