{
  "type": "Feature",
  "properties": {
    "iso:country":"CH",
    "sg:address":"Dorfstrasse 56",
    "sg:city":"Rifferswil",
    "sg:orig_category":"Erbringung von Dienstleistungen f\u00fcr Unternehmen",
    "sg:postcode":"8911",
    "sg:province":"Z\u00fcrich",
    "wof:name":"Klema Gmbh",
    "wof:placetype":"venue"
},
  "geometry": {"coordinates":[8.495349884,47.2406311035],"type":"Point"}
}