{
  "type": "Feature",
  "properties": {
    "iso:country":"CH",
    "sg:address":"Rue De Cossonay 1",
    "sg:city":"Crissier",
    "sg:classifiers":[
        {
            "category":"Shopping",
            "subcategory":"Shoes",
            "type":"Retail Goods"
        }
    ],
    "sg:phone":"+41 21 635 56 30",
    "sg:postcode":"1023",
    "sg:province":"Vaud",
    "sg:tags":[
        "moccasin"
    ],
    "wof:name":"Asd Diffusion S.a.",
    "wof:placetype":"venue"
},
  "geometry": {"coordinates":[6.5712399483,46.5573005676],"type":"Point"}
}