{
  "type": "Feature",
  "properties": {
    "iso:country":"CH",
    "sg:address":"Dufourstrasse 5",
    "sg:city":"Wil",
    "sg:classifiers":[
        {
            "category":"Manufacturing",
            "subcategory":"Printing",
            "type":"Manufacturing & Wholesale Goods"
        }
    ],
    "sg:phone":"+41 71 911 39 24",
    "sg:postcode":"9500",
    "sg:province":"St. Gallen",
    "sg:tags":[
        "house",
        "book"
    ],
    "wof:name":"Buchdruckerei Oberholzer Ag",
    "wof:placetype":"venue"
},
  "geometry": {"coordinates":[9.043979,47.465199],"type":"Point"}
}