{
  "type": "Feature",
  "properties": {
    "iso:country":"CH",
    "sg:address":"W\u00fcrzenbachstrasse 8",
    "sg:city":"Luzern",
    "sg:classifiers":[
        {
            "category":"Insurance",
            "subcategory":"Insurance Agent",
            "type":"Services"
        }
    ],
    "sg:phone":"+41 41 370 38 38",
    "sg:postcode":"6006",
    "sg:province":"Luzern",
    "sg:tags":[
        "versicherungsagenturen",
        "-broker"
    ],
    "wof:name":"Winterthur Versicherungen Agentur",
    "wof:placetype":"venue"
},
  "geometry": {"coordinates":[8.3425149918,47.0546455383],"type":"Point"}
}