{
  "type": "Feature",
  "properties": {
    "iso:country":"CH",
    "sg:address":"Mittelstrasse 24",
    "sg:city":"Nidau",
    "sg:orig_category":"Unclassifiable Establishments",
    "sg:postcode":"2560",
    "sg:province":"Bern",
    "wof:name":"Feroutil Ag",
    "wof:placetype":"venue"
},
  "geometry": {"coordinates":[7.238158226,47.1252098083],"type":"Point"}
}