{
  "type": "Feature",
  "properties": {
    "iso:country":"CH",
    "sg:address":"Dorfstrasse 4",
    "sg:city":"Adligenswil",
    "sg:orig_category":"Nationale Postdienste",
    "sg:phone":"+41 41 370 26 21",
    "sg:postcode":"6043",
    "sg:province":"Luzern",
    "wof:name":"Die Schweizerische Post",
    "wof:placetype":"venue"
},
  "geometry": {"coordinates":[8.3630218506,47.0715141296],"type":"Point"}
}