{
  "type": "Feature",
  "properties": {
    "iso:country":"CH",
    "sg:address":"Milit\u00e4rstrasse 9a",
    "sg:city":"Thun",
    "sg:orig_category":"Architektur U Ingenieurb\u00fcros",
    "sg:phone":"+41 33 225 20 20",
    "sg:postcode":"3600",
    "sg:province":"Bern",
    "wof:name":"Burri Viktor Ag Architekten",
    "wof:placetype":"venue"
},
  "geometry": {"coordinates":[7.61606,46.75713],"type":"Point"}
}