{
  "type": "Feature",
  "properties": {
    "iso:country":"CH",
    "sg:address":"Alpenstrasse 41",
    "sg:city":"Burgdorf",
    "sg:orig_category":"Vermietung U Verpachtung von eigenen Immobilien",
    "sg:postcode":"3400",
    "sg:province":"Bern",
    "wof:name":"Z\u00fcblin Bau Und Liegenschaftentreuhand",
    "wof:placetype":"venue"
},
  "geometry": {"coordinates":[9.2486505508,47.4084243774],"type":"Point"}
}