{
  "type": "Feature",
  "properties": {
    "iso:country":"CH",
    "sg:address":"Schulhausstrasse",
    "sg:city":"Sch\u00f6nb\u00fchl-urtenen",
    "sg:orig_category":"Herstellung von Frucht U Gem\u00fcses\u00e4ften",
    "sg:postcode":"3322",
    "sg:province":"Bern",
    "wof:name":"Mostereigenossenschaft Urtenen Und Umgebung",
    "wof:placetype":"venue"
},
  "geometry": {"coordinates":[7.5014519691,47.0290184021],"type":"Point"}
}