{
  "type": "Feature",
  "properties": {
    "iso:country":"CH",
    "sg:address":"Soleweg 4",
    "sg:city":"M\u00f6hlin",
    "sg:orig_category":"Unternehmensberatung",
    "sg:phone":"+41 56 225 23 81",
    "sg:postcode":"4313",
    "sg:province":"Aargau",
    "wof:name":"Ferm Industrie-unternehmensberatung F. M\u00fcller",
    "wof:placetype":"venue"
},
  "geometry": {"coordinates":[8.2574729919,47.4590988159],"type":"Point"}
}