{
  "type": "Feature",
  "properties": {
    "iso:country":"CH",
    "sg:address":"1413",
    "sg:city":"Oppens",
    "sg:orig_category":"Landesverteidigung, Sozialversicherung \u00d6ffentliche Verwaltung",
    "sg:phone":"+41 21 887 83 13",
    "sg:postcode":"1413",
    "sg:province":"Vaud",
    "wof:name":"Centre De Protection Civile",
    "wof:placetype":"venue"
},
  "geometry": {"coordinates":[6.6920819283,46.7139930725],"type":"Point"}
}