{
  "type": "Feature",
  "properties": {
    "iso:country":"CH",
    "sg:address":"Obstgartenstrasse 28 8006 Z\u00fcrich. Postfach",
    "sg:city":"Z\u00fcrich",
    "sg:orig_category":"Rechtsberatung Unternehmensberatung",
    "sg:phone":"+41 13611900",
    "sg:postcode":"8035",
    "sg:province":"Z\u00fcrich",
    "wof:name":"Bolliger Dr. Rudolf Mba",
    "wof:placetype":"venue"
},
  "geometry": {"coordinates":[8.5427417755,47.3828048706],"type":"Point"}
}