{
  "type": "Feature",
  "properties": {
    "iso:country":"CH",
    "sg:address":"Freie Strasse 59",
    "sg:city":"Basel",
    "sg:orig_category":"Detailhandel mit Geschenkartikeln U Souvenirs",
    "sg:phone":"+41 61 261 11 70",
    "sg:postcode":"4001",
    "sg:province":"Basel-Stadt",
    "wof:name":"Tridag Ag United Colors Of Benetton",
    "wof:placetype":"venue"
},
  "geometry": {"coordinates":[7.5904378891,47.5559616089],"type":"Point"}
}