{
  "type": "Feature",
  "properties": {
    "iso:country":"CH",
    "sg:address":"Grenzstrasse 16",
    "sg:city":"Lyss",
    "sg:orig_category":"Pensionskassen",
    "sg:postcode":"3250",
    "sg:province":"Bern",
    "wof:name":"Personalf\u00fcrsorgestiftung Der Firma Tschudi, M\u00fchlen Und Maschinenbau Ag",
    "wof:placetype":"venue"
},
  "geometry": {"coordinates":[7.292825222,47.0697135925],"type":"Point"}
}