{
  "type": "Feature",
  "properties": {
    "addr:full":"Bernstrasse 101 3052 Zollikofen. Postfach Zollikofen Bern 3052",
    "addr:housenumber":"101",
    "addr:postcode":"3052 zollikofen. postfach;3052",
    "addr:street":"Bernstrasse",
    "iso:country":"CH",
    "sg:address":"Bernstrasse 101 3052 Zollikofen. Postfach",
    "sg:city":"Zollikofen",
    "sg:orig_category":"Advokaturb\u00fcros",
    "sg:phone":"+41 71 913 80 30",
    "sg:postcode":"3052",
    "sg:province":"Bern",
    "wof:name":"Urs M\u00fcller Advokaturb\u00fcro",
    "wof:placetype":"venue"
},
  "geometry": {"coordinates":[9.047713,47.461533],"type":"Point"}
}