{
  "type": "Feature",
  "properties": {
    "iso:country":"CH",
    "sg:address":"Campingplatz Aue",
    "sg:city":"Baden",
    "sg:orig_category":"Vereine Camping",
    "sg:phone":"+41 56 221 63 00",
    "sg:postcode":"5400",
    "sg:province":"Aargau",
    "wof:name":"Camping-& Caravanning Club",
    "wof:placetype":"venue"
},
  "geometry": {"coordinates":[8.3064451218,47.4743309021],"type":"Point"}
}