{
  "type": "Feature",
  "properties": {
    "iso:country":"CH",
    "sg:address":"Oberer Hobackerweg 461",
    "sg:city":"Zetzwil",
    "sg:orig_category":"Allgemeiner Hoch U Tiefbau Hoch U Tiefbau",
    "sg:phone":"+41 62 773 14 11",
    "sg:postcode":"5732",
    "sg:province":"Aargau",
    "wof:name":"Hirt Karl Ag, Bau Und Gipsergesch\u00e4ft",
    "wof:placetype":"venue"
},
  "geometry": {"coordinates":[8.153501,47.289433],"type":"Point"}
}