{
  "type": "Feature",
  "properties": {
    "iso:country":"CH",
    "sg:address":"Altmattweg 57",
    "sg:city":"Olten",
    "sg:orig_category":"Hardwareberatung Softwareentwicklung U beratung",
    "sg:phone":"+41 56 670 99 60",
    "sg:postcode":"4600",
    "sg:province":"Solothurn",
    "wof:name":"Rs-computer Ralph Senger",
    "wof:placetype":"venue"
},
  "geometry": {"coordinates":[8.3174819946,47.2825775146],"type":"Point"}
}