{
  "type": "Feature",
  "properties": {
    "iso:country":"CH",
    "sg:address":"Kirchstrasse 5 9326 Horn. Postfach 105",
    "sg:city":"Horn",
    "sg:orig_category":"Grosshandel mit Bekleidung Grosshandel mit Lederwaren U Reiseartikeln",
    "sg:phone":"+41 21 691 67 88",
    "sg:postcode":"9326",
    "sg:province":"Thurgau",
    "wof:name":"Anne-marie Barraud D\u00e9chirure",
    "wof:placetype":"venue"
},
  "geometry": {"coordinates":[6.566628933,46.5344734192],"type":"Point"}
}