{
  "type": "Feature",
  "properties": {
    "iso:country":"CH",
    "sg:address":"Fidesstrasse 2",
    "sg:city":"St.gallen",
    "sg:orig_category":"Unclassifiable Establishments",
    "sg:postcode":"9000",
    "sg:province":"St. Gallen",
    "wof:name":"Dobrica Maja's Sport Caf\u00e9",
    "wof:placetype":"venue"
},
  "geometry": {"coordinates":[9.3934936523,47.4316596985],"type":"Point"}
}