{
  "type": "Feature",
  "properties": {
    "iso:country":"CH",
    "sg:address":"Luzernstrasse 23",
    "sg:city":"Etziken",
    "sg:orig_category":"Sonstiger Detailhandel nicht in Verkaufsr\u00e4umen",
    "sg:phone":"+41 32 614 06 17",
    "sg:postcode":"4554",
    "sg:province":"Solothurn",
    "wof:name":"Dispensa Automaten Und Produkte J\u00e4ggi Martin",
    "wof:placetype":"venue"
},
  "geometry": {"coordinates":[7.6432051659,47.1877059937],"type":"Point"}
}