{
  "type": "Feature",
  "properties": {
    "iso:country":"CH",
    "sg:address":"Gewerbestrasse 14",
    "sg:city":"Egg",
    "sg:classifiers":[
        {
            "category":"Home & Garden",
            "subcategory":"Building Materials",
            "type":"Retail Goods"
        }
    ],
    "sg:phone":"+41 19840095",
    "sg:postcode":"8132",
    "sg:province":"Z\u00fcrich",
    "sg:tags":[
        "steel",
        "metal",
        "made",
        "door",
        "gate"
    ],
    "wof:name":"Bixa Gmbh",
    "wof:placetype":"venue"
},
  "geometry": {"coordinates":[8.6929063797,47.3036422729],"type":"Point"}
}