{
  "type": "Feature",
  "properties": {
    "iso:country":"CH",
    "sg:address":"Hirzlistrasse 11",
    "sg:city":"Bilten",
    "sg:orig_category":"Wohnheime",
    "sg:postcode":"8865",
    "sg:province":"Glarus",
    "wof:name":"Stiftung Altersheim Bilten",
    "wof:placetype":"venue"
},
  "geometry": {"coordinates":[9.0249681473,47.1497421265],"type":"Point"}
}