{
  "type": "Feature",
  "properties": {
    "iso:country":"CH",
    "sg:address":"Rue De Clodevis",
    "sg:city":"Bramois",
    "sg:orig_category":"Grosshandel mit Eisenwaren sowie Installationsbedarf f\u00fcr Gas, Wasser U Heizung Herstellung von Armat",
    "sg:phone":"+41 27 203 13 26",
    "sg:postcode":"1967",
    "sg:province":"Valais",
    "wof:name":"Georges Bitschnau Appareils Sanitaires",
    "wof:placetype":"venue"
},
  "geometry": {"coordinates":[7.4047999382,46.2352981567],"type":"Point"}
}