{
  "type": "Feature",
  "properties": {
    "iso:country":"CH",
    "sg:address":"Dorf",
    "sg:city":"Rechthalten",
    "sg:orig_category":"RESTAURANTS: TEA-ROOMS",
    "sg:phone":"+41 26 418 11 31",
    "sg:postcode":"1718",
    "sg:province":"Fribourg",
    "wof:name":"Philipona Paul",
    "wof:placetype":"venue"
},
  "geometry": {"coordinates":[7.2403578758,46.7677192688],"type":"Point"}
}