{
  "type": "Feature",
  "properties": {
    "iso:country":"CH",
    "sg:address":"Au Grand-champ",
    "sg:city":"Grens",
    "sg:orig_category":"Grosshandel mit Holz U Baustoffen",
    "sg:phone":"+41 22 361 61 05",
    "sg:postcode":"1274",
    "sg:province":"Vaud",
    "wof:name":"Admico Sa",
    "wof:placetype":"venue"
},
  "geometry": {"coordinates":[6.1920938492,46.3949508667],"type":"Point"}
}