{
  "type": "Feature",
  "properties": {
    "iso:country":"CH",
    "sg:address":"Bernstrasse 135",
    "sg:city":"Zollikofen",
    "sg:orig_category":"Detailhandel mit Radio U Fernsehger\u00e4ten Detailhandel mit elektrischen Haushalts-,Radio U Fernsehger\u00e4",
    "sg:phone":"+41 31 915 15 15",
    "sg:postcode":"3052",
    "sg:province":"Bern",
    "wof:name":"Radio-tv-shop Rhyner Walter",
    "wof:placetype":"venue"
},
  "geometry": {"coordinates":[7.4583559036,46.9961051941],"type":"Point"}
}