{
  "type": "Feature",
  "properties": {
    "iso:country":"CH",
    "sg:address":"Im Bergli",
    "sg:city":"R\u00e4terschen",
    "sg:orig_category":"Detailhandel mit Blumen U Pflanzen",
    "sg:phone":"+41 52 363 11 30",
    "sg:postcode":"8352",
    "sg:province":"Z\u00fcrich",
    "wof:name":"Erwin N\u00fcssli Blumengesch\u00e4ft",
    "wof:placetype":"venue"
},
  "geometry": {"coordinates":[8.782392,47.505253],"type":"Point"}
}