{
  "type": "Feature",
  "properties": {
    "iso:country":"CH",
    "sg:address":"Sablons Rue Des 43",
    "sg:city":"Neuch\u00e2tel",
    "sg:orig_category":"Maler U Glasergewerbe",
    "sg:phone":"+41 32 725 20 80",
    "sg:postcode":"2000",
    "sg:province":"Neuch\u00e2tel",
    "wof:name":"Traceroute Sa, Succursale De Neuch\u00e2tel",
    "wof:placetype":"venue"
},
  "geometry": {"coordinates":[6.9314618111,46.9960365295],"type":"Point"}
}