{
  "type": "Feature",
  "properties": {
    "iso:country":"CH",
    "sg:address":"Rue De Neuch\u00e2tel 16",
    "sg:city":"Yverdon-les-bains",
    "sg:orig_category":"Herstellung von W\u00e4sche",
    "sg:postcode":"1400",
    "sg:province":"Vaud",
    "wof:name":"Martin-chaillou Mme",
    "wof:placetype":"venue"
},
  "geometry": {"coordinates":[6.6360602379,46.7815818787],"type":"Point"}
}