{
  "type": "Feature",
  "properties": {
    "iso:country":"CH",
    "sg:address":"Av. De La Tour-haldimand 3",
    "sg:city":"Pully",
    "sg:orig_category":"Museen",
    "sg:phone":"+41 21 728 05 34",
    "sg:postcode":"1009",
    "sg:province":"Vaud",
    "wof:name":"Janom, Bussien R.",
    "wof:placetype":"venue"
},
  "geometry": {"coordinates":[6.6422791481,46.5058174133],"type":"Point"}
}