{
  "type": "Feature",
  "properties": {
    "iso:country":"CH",
    "sg:address":"B\u00fcchelstrasse 18",
    "sg:city":"Widnau",
    "sg:classifiers":[
        {
            "category":"Restaurant",
            "type":"Food & Drink"
        }
    ],
    "sg:phone":"+41 71 722 24 91",
    "sg:postcode":"9443",
    "sg:province":"St. Gallen",
    "wof:name":"Restaurant Hecht",
    "wof:placetype":"venue"
},
  "geometry": {"coordinates":[9.6397228241,47.4024734497],"type":"Point"}
}