{
  "type": "Feature",
  "properties": {
    "iso:country":"CH",
    "sg:address":"Via Gerolamo Vegezzi 4 6900 Lugano Casella Postale 3141",
    "sg:city":"Lugano",
    "sg:orig_category":"Detailhandel mit B\u00fcchern, Zeitungen, Schreib U Papeteriewaren",
    "sg:phone":"+41 91 923 83 41",
    "sg:postcode":"6900",
    "sg:province":"Ticino",
    "wof:name":"Melisa-messaggerie Del Libro E Della Stampa Sa - Libreria Melisa",
    "wof:placetype":"venue"
},
  "geometry": {"coordinates":[8.951305,46.002975],"type":"Point"}
}