{
  "type": "Feature",
  "properties": {
    "iso:country":"CH",
    "sg:address":"Obere Bahnhofstrasse 24",
    "sg:city":"Wil",
    "sg:classifiers":[
        {
            "category":"Wholesale",
            "subcategory":"Construction Materials",
            "type":"Manufacturing & Wholesale Goods"
        }
    ],
    "sg:phone":"+41 71 911 37 22",
    "sg:postcode":"9500",
    "sg:province":"St. Gallen",
    "sg:tags":[
        "bridge",
        "temporary",
        "materials",
        "crown"
    ],
    "wof:name":"Vitek & Baumann Kg",
    "wof:placetype":"venue"
},
  "geometry": {"coordinates":[9.043756,47.464809],"type":"Point"}
}