{
  "type": "Feature",
  "properties": {
    "iso:country":"CH",
    "sg:address":"Dorf",
    "sg:city":"Realp",
    "sg:orig_category":"Allgemeiner Hoch U Tiefbau",
    "sg:postcode":"6491",
    "sg:province":"Uri",
    "wof:name":"Simmen & Cie, Bauunternehmung",
    "wof:placetype":"venue"
},
  "geometry": {"coordinates":[8.503005,46.598969],"type":"Point"}
}