{
  "type": "Feature",
  "properties": {
    "iso:country":"CH",
    "sg:address":"Schaffhauserstrasse 498",
    "sg:city":"Z\u00fcrich",
    "sg:orig_category":"Zahntechnische Laboratorien",
    "sg:phone":"+41 13010186",
    "sg:postcode":"8052",
    "sg:province":"Z\u00fcrich",
    "wof:name":"Marcus Wietlisbach Zahntechnisches Laboratorium",
    "wof:placetype":"venue"
},
  "geometry": {"coordinates":[8.5499277115,47.4211997986],"type":"Point"}
}