{
  "type": "Feature",
  "properties": {
    "iso:country":"CH",
    "sg:address":"Bahnhofstrasse 69a",
    "sg:city":"Z\u00fcrich",
    "sg:orig_category":"Detailhandel mit Uhren U Schmuck Haushaltartikel Detailhandel",
    "sg:phone":"+41 12116741",
    "sg:postcode":"8001",
    "sg:province":"Z\u00fcrich",
    "wof:name":"Robbe & Berking Silbermanufaktur Internat.gmbh Silber Detailverkauf",
    "wof:placetype":"venue"
},
  "geometry": {"coordinates":[8.5382175446,47.3740196228],"type":"Point"}
}