{
  "type": "Feature",
  "properties": {
    "iso:country":"CH",
    "sg:address":"Bossi\u00e8re Route De La 14 1197 Prangins. Postfach",
    "sg:city":"Prangins",
    "sg:orig_category":"Handelsvermittlung von Maschinen, technischem Bedarf, Wasser U Luftfahrzeugen",
    "sg:postcode":"1197",
    "sg:province":"Vaud",
    "wof:name":"Otreus Sa Activit\u00e9 Dans Les Domaines Industriel Et Informatique, Notamm. Conseils, Conception De Programmes Etc",
    "wof:placetype":"venue"
},
  "geometry": {"coordinates":[6.2490000725,46.3943252563],"type":"Point"}
}