{
  "type": "Feature",
  "properties": {
    "iso:country":"CH",
    "sg:address":"Rue Neuve 10",
    "sg:city":"Ste-croix",
    "sg:orig_category":"Arztpraxen",
    "sg:phone":"+41 24 454 10 20",
    "sg:postcode":"1450",
    "sg:province":"Vaud",
    "wof:name":"Dr M\u00e9d. Jules Zadory M\u00e9decin G\u00e9n\u00e9raliste",
    "wof:placetype":"venue"
},
  "geometry": {"coordinates":[6.501212,46.822495],"type":"Point"}
}