{
  "type": "Feature",
  "properties": {
    "iso:country":"CH",
    "sg:address":"Rodenbergstrasse 14",
    "sg:city":"Schlattingen",
    "sg:orig_category":"K\u00fcnstlerische Schulen",
    "sg:phone":"+41 52 657 32 42",
    "sg:postcode":"8255",
    "sg:province":"Thurgau",
    "wof:name":"Klaus Imhof Musikschule",
    "wof:placetype":"venue"
},
  "geometry": {"coordinates":[8.7696037292,47.669670105],"type":"Point"}
}