{
  "type": "Feature",
  "properties": {
    "iso:country":"CH",
    "sg:address":"Stauffacherstrasse 37",
    "sg:city":"Z\u00fcrich",
    "sg:orig_category":"Detailhandel mit Damenbekleidung Detailhandel mit Herrenbekleidung",
    "sg:phone":"+41 12412923",
    "sg:postcode":"8004",
    "sg:province":"Z\u00fcrich",
    "wof:name":"Neuburger Sport",
    "wof:placetype":"venue"
},
  "geometry": {"coordinates":[8.528383255,47.3738594055],"type":"Point"}
}