{
  "type": "Feature",
  "properties": {
    "addr:full":"Chellenstrasse 10 Goldach St. Gallen 9403",
    "addr:housenumber":"10",
    "addr:postcode":"9403",
    "addr:street":"Chellenstrasse",
    "iso:country":"CH",
    "sg:address":"Chellenstrasse 10",
    "sg:city":"Goldach",
    "sg:orig_category":"Architektur U Ingenieurb\u00fcros",
    "sg:phone":"+41 71 845 41 11",
    "sg:postcode":"9403",
    "sg:province":"St. Gallen",
    "wof:name":"Eska-tech, Schiffner E.",
    "wof:placetype":"venue"
},
  "geometry": {"coordinates":[9.478294,47.468307],"type":"Point"}
}