{
  "type": "Feature",
  "properties": {
    "iso:country":"CH",
    "sg:address":"Farmweg 9",
    "sg:city":"Steffisburg",
    "sg:orig_category":"Bauspenglerei Sanit\u00e4rinstallation U Spenglerei",
    "sg:phone":"+41 33 345 73 63",
    "sg:postcode":"3613",
    "sg:province":"Bern",
    "wof:name":"Kurt Joss Spenglerei",
    "wof:placetype":"venue"
},
  "geometry": {"coordinates":[7.609514,46.772369],"type":"Point"}
}