{
  "type": "Feature",
  "properties": {
    "iso:country":"CH",
    "sg:address":"Rietbr\u00fcelweg",
    "sg:city":"Wangs",
    "sg:orig_category":"Innenausbau",
    "sg:phone":"+41 81 723 59 05",
    "sg:postcode":"7323",
    "sg:province":"St. Gallen",
    "wof:name":"Von Ott Ag Innenausbau",
    "wof:placetype":"venue"
},
  "geometry": {"coordinates":[9.431183815,47.0347900391],"type":"Point"}
}