{
  "type": "Feature",
  "properties": {
    "iso:country":"CH",
    "sg:address":"Passwangstrasse 261 4719 Ramiswil. Postfach 24",
    "sg:city":"Ramiswil",
    "sg:orig_category":"Detailhandel mit Damenbekleidung Detailhandel mit Herrenbekleidung",
    "sg:phone":"+41 62 391 57 06",
    "sg:postcode":"4719",
    "sg:province":"Solothurn",
    "wof:name":"Rudolf Ackermann Damen-& Herrenmode",
    "wof:placetype":"venue"
},
  "geometry": {"coordinates":[7.6601672173,47.3452682495],"type":"Point"}
}