{
  "type": "Feature",
  "properties": {
    "addr:full":"Grand-rue 32a Dombresson Neuch\u00e2tel 2056",
    "addr:housenumber":"32a",
    "addr:postcode":"2056",
    "addr:street":"Grand-Rue;Neucha\u0302Tel",
    "iso:country":"CH",
    "sg:address":"Grand-rue 32a",
    "sg:city":"Dombresson",
    "sg:orig_category":"Bauschreinerei Zimmerei, Ingenieurholzbau",
    "sg:phone":"+41 79 206 65 90",
    "sg:postcode":"2056",
    "sg:province":"Neuch\u00e2tel",
    "wof:name":"Eric Mast Charpente & Couverture",
    "wof:placetype":"venue"
},
  "geometry": {"coordinates":[6.958589,47.071941],"type":"Point"}
}