{
  "type": "Feature",
  "properties": {
    "iso:country":"CH",
    "sg:address":"Bahnhofstrasse 42",
    "sg:city":"Horw",
    "sg:classifiers":[
        {
            "category":"Professional",
            "subcategory":"Advertising",
            "type":"Services"
        }
    ],
    "sg:phone":"+41 41 340 16 47",
    "sg:postcode":"6048",
    "sg:province":"Luzern",
    "sg:tags":[
        "imprint"
    ],
    "wof:name":"Eicher Druck Ag",
    "wof:placetype":"venue"
},
  "geometry": {"coordinates":[8.307373,47.017857],"type":"Point"}
}