{
  "type": "Feature",
  "properties": {
    "iso:country":"CH",
    "sg:address":"Ifangstrasse 90",
    "sg:city":"R\u00fcmlang",
    "sg:orig_category":"Sportvereine Boccia",
    "sg:phone":"+41 18171451",
    "sg:postcode":"8153",
    "sg:province":"Z\u00fcrich",
    "wof:name":"Boccia-club R\u00fcmlang",
    "wof:placetype":"venue"
},
  "geometry": {"coordinates":[8.537027359,47.4480667114],"type":"Point"}
}