{
  "type": "Feature",
  "properties": {
    "iso:country":"CH",
    "sg:address":"Rosengasse 8",
    "sg:city":"Schaffhausen",
    "sg:orig_category":"Energie\u00e4mter and -fachstellen",
    "sg:phone":"+41 71 224 56 76",
    "sg:postcode":"8200",
    "sg:province":"Schaffhausen",
    "wof:name":"Umweltschutzamt Der Stadt St.gallen",
    "wof:placetype":"venue"
},
  "geometry": {"coordinates":[9.3693466187,47.4220542908],"type":"Point"}
}