{
  "type": "Feature",
  "properties": {
    "iso:country":"CH",
    "sg:address":"Grabenstrasse 14",
    "sg:city":"Schlieren",
    "sg:orig_category":"Grosshandel mit Getr\u00e4nken Grosshandel mit Wein U Spirituosen",
    "sg:phone":"+41 17302221",
    "sg:postcode":"8952",
    "sg:province":"Z\u00fcrich",
    "wof:name":"Getr\u00e4nke Huber, Inh. Lienhard H.",
    "wof:placetype":"venue"
},
  "geometry": {"coordinates":[8.4504308701,47.3974533081],"type":"Point"}
}