{
  "type": "Feature",
  "properties": {
    "iso:country":"CH",
    "sg:address":"Spitalweg 9",
    "sg:city":"Glis",
    "sg:classifiers":[
        {
            "category":"Insurance",
            "subcategory":"Insurance Agent",
            "type":"Services"
        }
    ],
    "sg:phone":"+41 84888016",
    "sg:postcode":"3902",
    "sg:province":"Valais",
    "sg:tags":[
        "versicherungsagenturen",
        "-broker"
    ],
    "wof:name":"Generali Versicherungen Agentur",
    "wof:placetype":"venue"
},
  "geometry": {"coordinates":[7.9866299629,46.3162345886],"type":"Point"}
}