{
  "type": "Feature",
  "properties": {
    "iso:country":"CH",
    "sg:address":"Landstrasse 57",
    "sg:city":"Schaan",
    "sg:classifiers":[
        {
            "category":"Personal",
            "subcategory":"Nail Salon",
            "type":"Services"
        }
    ],
    "sg:postcode":"9494",
    "sg:tags":[
        "manicure"
    ],
    "wof:name":"Corina Eggenberger Nail-kosmetik",
    "wof:placetype":"venue"
},
  "geometry": {"coordinates":[9.5088090897,47.1639404297],"type":"Point"}
}