{
  "type": "Feature",
  "properties": {
    "iso:country":"CH",
    "sg:address":"Kugelgasse 7",
    "sg:city":"St.gallen",
    "sg:orig_category":"RESTAURANTS: TEA-ROOMS",
    "sg:phone":"+41 71 223 84 80",
    "sg:postcode":"9000",
    "sg:province":"St. Gallen",
    "wof:name":"San Lorenzo Ag Ristorante Italiano",
    "wof:placetype":"venue"
},
  "geometry": {"coordinates":[9.3775854111,47.4251976013],"type":"Point"}
}