{
  "type": "Feature",
  "properties": {
    "iso:country":"CH",
    "sg:address":"Murgenthalstrasse 15",
    "sg:city":"Langenthal",
    "sg:classifiers":[
        {
            "category":"Government",
            "subcategory":"Post Office",
            "type":"Public Place"
        }
    ],
    "sg:phone":"+41 62 922 02 43",
    "sg:postcode":"4900",
    "sg:province":"Bern",
    "sg:tags":[
        "lettering"
    ],
    "wof:name":"Hans-peter Spahr Druckerei",
    "wof:placetype":"venue"
},
  "geometry": {"coordinates":[7.7882928848,47.2176361084],"type":"Point"}
}