{
  "type": "Feature",
  "properties": {
    "iso:country":"CH",
    "sg:address":"Zweierstrasse 139",
    "sg:city":"Z\u00fcrich",
    "sg:orig_category":"Werbung",
    "sg:postcode":"8003",
    "sg:province":"Z\u00fcrich",
    "wof:name":"Micado Werbeagentur Brosi + Betzler",
    "wof:placetype":"venue"
},
  "geometry": {"coordinates":[8.5196561813,47.3706741333],"type":"Point"}
}