{
  "type": "Feature",
  "properties": {
    "iso:country":"CH",
    "sg:address":"Fl\u00fcelastr. 12",
    "sg:city":"Z\u00fcrich",
    "sg:classifiers":[
        {
            "category":"Manufacturing",
            "subcategory":"Paper Products",
            "type":"Manufacturing & Wholesale Goods"
        }
    ],
    "sg:phone":"+41 4114973232",
    "sg:postcode":"8048",
    "sg:province":"Z\u00fcrich",
    "sg:tags":[
        "packaging",
        "material",
        "-",
        "cardboard"
    ],
    "wof:name":"Brieger Verpackungen",
    "wof:placetype":"venue"
},
  "geometry": {"coordinates":[8.4966497421,47.3834915161],"type":"Point"}
}