{
  "type": "Feature",
  "properties": {
    "iso:country":"CH",
    "sg:address":"Badischer Bahnhof 4000 Basel. Postfach",
    "sg:city":"Basel",
    "sg:orig_category":"Vermietung von Automobilen",
    "sg:phone":"+41 61 683 59 89",
    "sg:postcode":"4016",
    "sg:province":"Basel-Stadt",
    "wof:name":"Sixt Ag",
    "wof:placetype":"venue"
},
  "geometry": {"coordinates":[7.6093010902,47.5636787415],"type":"Point"}
}