{
  "type": "Feature",
  "properties": {
    "iso:country":"CH",
    "sg:address":"Viale Castagnola 25 6900 Lugano. Postfach 6906 Lugano",
    "sg:city":"Caselle",
    "sg:orig_category":"Grosshandel mit medizinischen U orthop\u00e4dischen Artikeln",
    "sg:phone":"+41 91 972 67 13",
    "sg:postcode":"6",
    "wof:name":"Tecnisan Sa Arredamenti Medico-ospedaliere",
    "wof:placetype":"venue"
},
  "geometry": {"coordinates":[8.9673690796,46.0058517456],"type":"Point"}
}