{
  "type": "Feature",
  "properties": {
    "iso:country":"CH",
    "sg:address":"Bernstrasse 11 3175 Flamatt. Postfach 143",
    "sg:city":"Flamatt",
    "sg:orig_category":"Detailhandel mit Bekleidung",
    "sg:phone":"+41 31 741 02 02",
    "sg:postcode":"3175",
    "sg:province":"Fribourg",
    "wof:name":"Hildegard Friedli Jeans-shop & Kleiderb\u00f6rse",
    "wof:placetype":"venue"
},
  "geometry": {"coordinates":[7.312973,46.890026],"type":"Point"}
}