{
  "type": "Feature",
  "properties": {
    "iso:country":"CH",
    "sg:address":"Valfaye Chemin De 6",
    "sg:city":"Lausanne",
    "sg:orig_category":"Architektur U Ingenieurb\u00fcros",
    "sg:phone":"+41 21 652 88 03",
    "sg:postcode":"1010",
    "sg:province":"Vaud",
    "wof:name":"Espace Lotus, Kempf Eric",
    "wof:placetype":"venue"
},
  "geometry": {"coordinates":[6.65576,46.5359],"type":"Point"}
}