{
  "type": "Feature",
  "properties": {
    "iso:country":"CH",
    "sg:address":"Via Porta Cotschna 8",
    "sg:city":"Ilanz",
    "sg:orig_category":"Unternehmensberatung",
    "sg:phone":"+41 22 820 34 00",
    "sg:postcode":"7130",
    "sg:province":"Graubunden",
    "wof:name":"Domis Sa",
    "wof:placetype":"venue"
},
  "geometry": {"coordinates":[6.1413788795,46.1846542358],"type":"Point"}
}