{
  "type": "Feature",
  "properties": {
    "iso:country":"CH",
    "sg:address":"Harpe Avenue De La 25 1007 Lausanne. Postfach",
    "sg:city":"Lausanne",
    "sg:orig_category":"Sonstige mit der Informatik verbundene T\u00e4tigkeiten",
    "sg:postcode":"1007",
    "sg:province":"Vaud",
    "wof:name":"Campana S.",
    "wof:placetype":"venue"
},
  "geometry": {"coordinates":[6.7492198944,47.0575256348],"type":"Point"}
}