{
  "type": "Feature",
  "properties": {
    "iso:country":"CH",
    "sg:address":"Asylstrasse 68",
    "sg:city":"Z\u00fcrich",
    "sg:orig_category":"Detailhandel mit M\u00f6beln U Haushaltsgegenst\u00e4nden Innenausbau",
    "sg:phone":"+41 13832757",
    "sg:postcode":"8032",
    "sg:province":"Z\u00fcrich",
    "wof:name":"Wohnflex, Suter Beatrice & Co",
    "wof:placetype":"venue"
},
  "geometry": {"coordinates":[8.5606937408,47.3674354553],"type":"Point"}
}