{
  "type": "Feature",
  "properties": {
    "iso:country":"CH",
    "sg:address":"Via Carlo Maderno 18",
    "sg:city":"Lugano",
    "sg:orig_category":"Detailhandel mit Parf\u00fcmerieartikeln U K\u00f6rperpflegemitteln Grosshandel mit Parf\u00fcmerieartikeln U K\u00f6rpe",
    "sg:phone":"+41 91 921 24 54",
    "sg:postcode":"6900",
    "sg:province":"Ticino",
    "wof:name":"Percos Perfumes & Cosmetics Trading Sa",
    "wof:placetype":"venue"
},
  "geometry": {"coordinates":[8.9554033279,46.0099754333],"type":"Point"}
}