{
  "type": "Feature",
  "properties": {
    "iso:country":"CH",
    "sg:address":"T\u00f6nierweg 1",
    "sg:city":"Uznach",
    "sg:orig_category":"Grosshandel mit B\u00fcromaschinen Grosshandel mit Datenverarbeitungsger\u00e4ten",
    "sg:phone":"+41 55 290 20 20",
    "sg:postcode":"8730",
    "sg:province":"St. Gallen",
    "wof:name":"Comet System Gmbh",
    "wof:placetype":"venue"
},
  "geometry": {"coordinates":[8.9913139343,47.2240028381],"type":"Point"}
}