{
  "type": "Feature",
  "properties": {
    "iso:country":"CH",
    "sg:address":"1038",
    "sg:city":"Bercher",
    "sg:orig_category":"Detailhandel mit Waren verschiedener Art, Hauptrichtung Nahrungsmittel",
    "sg:postcode":"1038",
    "sg:province":"Vaud",
    "wof:name":"Soci\u00e9t\u00e9 Coop\u00e9rative De Producteurs De Pommes De Terre Du Gros-de-vaud",
    "wof:placetype":"venue"
},
  "geometry": {"coordinates":[6.7114901543,46.6916313171],"type":"Point"}
}