{
  "type": "Feature",
  "properties": {
    "addr:full":"K\u00fcferweg 6 Urdorf Z\u00fcrich 8902",
    "addr:housenumber":"6",
    "addr:postcode":"8902",
    "addr:street":"Kueferweg",
    "iso:country":"CH",
    "sg:address":"K\u00fcferweg 6",
    "sg:city":"Urdorf",
    "sg:orig_category":"Autogaragen",
    "sg:phone":"+41 17345852",
    "sg:postcode":"8902",
    "sg:province":"Z\u00fcrich",
    "wof:name":"K\u00fcfergarage Heinrich Aeberli",
    "wof:placetype":"venue"
},
  "geometry": {"coordinates":[8.422001,47.379475],"type":"Point"}
}