{
  "type": "Feature",
  "properties": {
    "iso:country":"CH",
    "sg:address":"Seefeldstrasse 116",
    "sg:city":"Z\u00fcrich",
    "sg:orig_category":"Advokaturb\u00fcros",
    "sg:phone":"+41 91 682 77 27",
    "sg:postcode":"8008",
    "sg:province":"Z\u00fcrich",
    "wof:name":"Irma Notti Studio Legale",
    "wof:placetype":"venue"
},
  "geometry": {"coordinates":[9.02861,45.847511],"type":"Point"}
}