{
  "type": "Feature",
  "properties": {
    "iso:country":"CH",
    "sg:address":"Rue Sismondi 13",
    "sg:city":"Gen\u00e8ve",
    "sg:orig_category":"Unclassifiable Establishments",
    "sg:postcode":"1201",
    "sg:province":"Gen\u00e8ve",
    "wof:name":"Coiffure Monika Keller",
    "wof:placetype":"venue"
},
  "geometry": {"coordinates":[9.0468301773,47.4202308655],"type":"Point"}
}