{
  "type": "Feature",
  "properties": {
    "iso:country":"CH",
    "sg:address":"Bvd Des Philosophes 9",
    "sg:city":"Gen\u00e8ve",
    "sg:orig_category":"Arztpraxen",
    "sg:phone":"+41 22 329 01 46",
    "sg:postcode":"1205",
    "sg:province":"Gen\u00e8ve",
    "wof:name":"Dr M\u00e9d. Jean Locher M\u00e9decin Sp\u00e9cialiste Fmh",
    "wof:placetype":"venue"
},
  "geometry": {"coordinates":[6.144311,46.197453],"type":"Point"}
}