{
  "type": "Feature",
  "properties": {
    "iso:country":"CH",
    "sg:address":"8226",
    "sg:city":"Schleitheim",
    "sg:classifiers":[
        {
            "category":"Education",
            "subcategory":"Vocational School",
            "type":"Public Place"
        }
    ],
    "sg:postcode":"8226",
    "sg:province":"Schaffhausen",
    "sg:tags":[
        "koch-",
        "haushaltschulen"
    ],
    "wof:name":"Haushaltungsschule",
    "wof:placetype":"venue"
},
  "geometry": {"coordinates":[8.4880142212,47.7504005432],"type":"Point"}
}