{
  "type": "Feature",
  "properties": {
    "iso:country":"CH",
    "sg:address":"Zentrumsplatz 2 8592 Uttwil. Postfach 63",
    "sg:city":"Uttwil",
    "sg:orig_category":"Verwaltung der Rechtspflege, Gerichte",
    "sg:phone":"+41 71 463 42 44",
    "sg:postcode":"8592",
    "sg:province":"Thurgau",
    "wof:name":"Grundbuchamt & Notariat Kreis Uttwil",
    "wof:placetype":"venue"
},
  "geometry": {"coordinates":[9.3402070999,47.5840415955],"type":"Point"}
}