{
  "type": "Feature",
  "properties": {
    "iso:country":"CH",
    "sg:address":"Casa Bea Via Ovega 14",
    "sg:city":"Brissago",
    "sg:orig_category":"Allgemeiner Hoch U Tiefbau",
    "sg:phone":"+41 91 793 00 15",
    "sg:postcode":"6614",
    "sg:province":"Ticino",
    "wof:name":"Andy Pagani Impresa Di Costruzioni",
    "wof:placetype":"venue"
},
  "geometry": {"coordinates":[8.710298,46.118977],"type":"Point"}
}