{
  "type": "Feature",
  "properties": {
    "iso:country":"CH",
    "sg:address":"Hauptstrasse 38",
    "sg:city":"Bettwiesen",
    "sg:classifiers":[
        {
            "category":"Restaurant",
            "type":"Food & Drink"
        }
    ],
    "sg:phone":"+41 71 911 18 14",
    "sg:postcode":"9553",
    "sg:province":"Thurgau",
    "wof:name":"Restaurant Wiesental",
    "wof:placetype":"venue"
},
  "geometry": {"coordinates":[9.0256156921,47.4952545166],"type":"Point"}
}