{
  "type": "Feature",
  "properties": {
    "iso:country":"CH",
    "sg:address":"Sch\u00f6n\u00f6rtli 9",
    "sg:city":"Gunten",
    "sg:classifiers":[
        {
            "category":"Social Services",
            "subcategory":"Retirement Home",
            "type":"Services"
        }
    ],
    "sg:phone":"+41 33 243 49 94",
    "sg:postcode":"3654",
    "sg:province":"Bern",
    "sg:tags":[
        "pflegeheime",
        "u",
        "alters"
    ],
    "wof:name":"Alters-& Pflegeheim",
    "wof:placetype":"venue"
},
  "geometry": {"coordinates":[7.687556,46.721455],"type":"Point"}
}