{
  "type": "Feature",
  "properties": {
    "addr:full":"Wisentalstrasse 9a Winkel Z\u00fcrich 8185",
    "addr:housenumber":"9a",
    "addr:postcode":"8185",
    "addr:street":"Wisentalstrasse",
    "iso:country":"CH",
    "sg:address":"Wisentalstrasse 9a",
    "sg:city":"Winkel",
    "sg:orig_category":"Aktivit\u00e4ten der Generalunternehmen im Baugewerbe Vermietung U Verpachtung von eigenen Immobilien",
    "sg:phone":"+41 56 493 51 03",
    "sg:postcode":"8185",
    "sg:province":"Z\u00fcrich",
    "wof:name":"Zit Ziegler Immobilien & Treuhand Gmbh",
    "wof:placetype":"venue"
},
  "geometry": {"coordinates":[8.552381,47.492634],"type":"Point"}
}