{
  "type": "Feature",
  "properties": {
    "iso:country":"CH",
    "sg:address":"Lehmenweg 26",
    "sg:city":"Dornach",
    "sg:orig_category":"Fachdetailhandel mit pharmazeutischen Produkten",
    "sg:phone":"+41 61 701 54 56",
    "sg:postcode":"4143",
    "sg:province":"Solothurn",
    "wof:name":"Regiopharm Ag.",
    "wof:placetype":"venue"
},
  "geometry": {"coordinates":[7.6207261086,47.4796676636],"type":"Point"}
}