{
  "type": "Feature",
  "properties": {
    "iso:country":"CH",
    "sg:address":"Eschenweg 4",
    "sg:city":"Hettlingen",
    "sg:orig_category":"Detailhandel mit Getr\u00e4nken",
    "sg:phone":"+41 21 784 16 18",
    "sg:postcode":"8442",
    "sg:province":"Z\u00fcrich",
    "wof:name":"Boissons Emile E.wachs",
    "wof:placetype":"venue"
},
  "geometry": {"coordinates":[6.6817159653,46.5583496094],"type":"Point"}
}