{
  "type": "Feature",
  "properties": {
    "iso:country":"CH",
    "sg:address":"Gerbestrasse 2 9050 Appenzell. Postfach",
    "sg:city":"Appenzell",
    "sg:orig_category":"Vermietung U Verpachtung von eigenen Immobilien",
    "sg:postcode":"9050",
    "sg:province":"Appenzell Innerhoden",
    "wof:name":"Hephaistos Ag",
    "wof:placetype":"venue"
},
  "geometry": {"coordinates":[9.4102945328,47.3303527832],"type":"Point"}
}