{
  "type": "Feature",
  "properties": {
    "iso:country":"CH",
    "sg:address":"Zubackerweg 21",
    "sg:city":"Herzogenbuchsee",
    "sg:orig_category":"Softwareentwicklung U beratung",
    "sg:phone":"+41 62 961 15 29",
    "sg:postcode":"3360",
    "sg:province":"Bern",
    "wof:name":"Billingy",
    "wof:placetype":"venue"
},
  "geometry": {"coordinates":[7.7073612213,47.1903495789],"type":"Point"}
}