{
  "type": "Feature",
  "properties": {
    "iso:country":"CH",
    "sg:address":"Kantonsstrasse 71",
    "sg:city":"Freienbach",
    "sg:orig_category":"Erbringung von Dienstleistungen f\u00fcr Unternehmen",
    "sg:postcode":"8807",
    "sg:province":"Schwyz",
    "wof:name":"Riva G. Valenta, Modellbau + Zubeh\u00f6r",
    "wof:placetype":"venue"
},
  "geometry": {"coordinates":[9.268204689,47.4144554138],"type":"Point"}
}