{
  "type": "Feature",
  "properties": {
    "iso:country":"CH",
    "sg:address":"Boveresses Avenue Des 31",
    "sg:city":"Lausanne",
    "sg:orig_category":"Wohnheime",
    "sg:postcode":"1010",
    "sg:province":"Vaud",
    "wof:name":"Ems Les Boveresses S\u00e0rl",
    "wof:placetype":"venue"
},
  "geometry": {"coordinates":[6.665517807,46.5370292664],"type":"Point"}
}