{
  "type": "Feature",
  "properties": {
    "iso:country":"CH",
    "sg:address":"Ar\u00e4lia",
    "sg:city":"Gr\u00fcsch",
    "sg:orig_category":"G\u00fcterbef\u00f6rderung im Strassenverkehr",
    "sg:phone":"+41 81 325 18 39",
    "sg:postcode":"7214",
    "sg:province":"Graubunden",
    "wof:name":"Andreas Th\u00f6ny Umz\u00fcge & Transporte",
    "wof:placetype":"venue"
},
  "geometry": {"coordinates":[9.6532688141,46.9805908203],"type":"Point"}
}