{
  "type": "Feature",
  "properties": {
    "iso:country":"CH",
    "sg:address":"A2 Luzern-s\u00fcd Schlundstrasse",
    "sg:city":"Kriens",
    "sg:classifiers":[
        {
            "category":"Travel",
            "subcategory":"Hotels & Motels",
            "type":"Entertainment"
        }
    ],
    "sg:phone":"+41 21 691 45 38",
    "sg:postcode":"6010",
    "sg:province":"Luzern",
    "sg:tags":[
        "hotels",
        "mit",
        "restaurant"
    ],
    "wof:name":"Moulin Claude.",
    "wof:placetype":"venue"
},
  "geometry": {"coordinates":[6.5707111359,46.5138168335],"type":"Point"}
}