{
  "type": "Feature",
  "properties": {
    "addr:full":"Holdernstrasse 1 Bilten Glarus 8865",
    "addr:housenumber":"1",
    "addr:postcode":"8865",
    "addr:street":"Holdernstrasse",
    "iso:country":"CH",
    "sg:address":"Holdernstrasse 1",
    "sg:city":"Bilten",
    "sg:orig_category":"Betrieb von Sportanlagen Spielsalons",
    "sg:phone":"+41 19381787",
    "sg:postcode":"8865",
    "sg:province":"Glarus",
    "wof:name":"Joe's Bowling Center, K\u00fcng Josef",
    "wof:placetype":"venue"
},
  "geometry": {"coordinates":[8.814511,47.307655],"type":"Point"}
}