{
  "type": "Feature",
  "properties": {
    "iso:country":"CH",
    "sg:address":"2023",
    "sg:city":"Gorgier",
    "sg:orig_category":"Vereine Gesang",
    "sg:postcode":"2023",
    "sg:province":"Neuch\u00e2tel",
    "wof:name":"St\u00e9 De Chant Helv\u00e9tienne",
    "wof:placetype":"venue"
},
  "geometry": {"coordinates":[6.7806100845,46.9030303955],"type":"Point"}
}