{
  "type": "Feature",
  "properties": {
    "addr:full":"B\u00fchl 314 Nesslau St. Gallen 9650",
    "addr:housenumber":"314;st.",
    "addr:postcode":"9650",
    "addr:street":"Buehl",
    "iso:country":"CH",
    "sg:address":"B\u00fchl 314",
    "sg:city":"Nesslau",
    "sg:classifiers":[
        {
            "category":"Banks & Credit Unions",
            "subcategory":"Atm",
            "type":"Services"
        }
    ],
    "sg:phone":"+41 71 994 11 66",
    "sg:postcode":"9650",
    "sg:province":"St. Gallen",
    "sg:tags":[
        "balance",
        "scale",
        "calibration"
    ],
    "wof:name":"Scherrer Werkzeugbau",
    "wof:placetype":"venue"
},
  "geometry": {"coordinates":[9.19936,47.22419],"type":"Point"}
}