{
  "type": "Feature",
  "properties": {
    "iso:country":"CH",
    "sg:address":"2075",
    "sg:city":"Thielle-wavre",
    "sg:classifiers":[
        {
            "category":"Restaurant",
            "type":"Food & Drink"
        }
    ],
    "sg:phone":"+41 32 313 24 23",
    "sg:postcode":"2075",
    "sg:province":"Neuch\u00e2tel",
    "wof:name":"Restaurant Rothaus",
    "wof:placetype":"venue"
},
  "geometry": {"coordinates":[7.0219497681,47.0200500488],"type":"Point"}
}