{
  "type": "Feature",
  "properties": {
    "iso:country":"CH",
    "sg:address":"Avenue De Montoie 38 1007 Lausanne. Postfach",
    "sg:city":"Lausanne",
    "sg:orig_category":"Versicherungen Generalagenturen",
    "sg:phone":"+41 21 623 22 22",
    "sg:postcode":"1001",
    "sg:province":"Vaud",
    "wof:name":"Alpina Assurances Agence G\u00e9n\u00e9rale Canton De Vaud",
    "wof:placetype":"venue"
},
  "geometry": {"coordinates":[6.6099200249,46.519493103],"type":"Point"}
}