{
  "type": "Feature",
  "properties": {
    "iso:country":"CH",
    "sg:address":"Moosmattstrasse 20c 6000 Luzern. Postfach 2628",
    "sg:city":"Luzern",
    "sg:orig_category":"Allgemeiner Hochbau Zimmerei, Dachdeckerei, Bauspenglerei U Abdichtung",
    "sg:phone":"+41 41 318 41 18",
    "sg:postcode":"6002",
    "sg:province":"Luzern",
    "wof:name":"Distel Ruedi Ag",
    "wof:placetype":"venue"
},
  "geometry": {"coordinates":[8.303725,47.039894],"type":"Point"}
}