{
  "type": "Feature",
  "properties": {
    "iso:country":"CH",
    "sg:address":"Sonnengasse",
    "sg:city":"St\u00e4fa",
    "sg:orig_category":"Tanzschulen, Tanzlehrer",
    "sg:phone":"+41 19268003",
    "sg:postcode":"8712",
    "sg:province":"Z\u00fcrich",
    "wof:name":"Tanzschule Nandikara Indischer Tanz",
    "wof:placetype":"venue"
},
  "geometry": {"coordinates":[8.7182197571,47.2394866943],"type":"Point"}
}