{
  "type": "Feature",
  "properties": {
    "iso:country":"CH",
    "sg:address":"3536",
    "sg:city":"Aeschau",
    "sg:orig_category":"Primarschulen",
    "sg:phone":"+41 31 951 72 43",
    "sg:postcode":"3536",
    "sg:province":"Bern",
    "wof:name":"Primarschule Horbern",
    "wof:placetype":"venue"
},
  "geometry": {"coordinates":[7.4871888161,46.9299354553],"type":"Point"}
}