{
  "type": "Feature",
  "properties": {
    "iso:country":"CH",
    "sg:address":"Gr\u00fcnaustrasse 50 3084 Wabern. Postfach",
    "sg:city":"Wabern",
    "sg:orig_category":"Unternehmensberatung Wirtschaftspr\u00fcfung, Steuerberatung U Treuhand",
    "sg:phone":"+41 71 313 57 57",
    "sg:postcode":"3084",
    "sg:province":"Bern",
    "wof:name":"Treviso Treuhand Ag St. Gallen",
    "wof:placetype":"venue"
},
  "geometry": {"coordinates":[9.3141546249,47.4150428772],"type":"Point"}
}