{
  "type": "Feature",
  "properties": {
    "iso:country":"CH",
    "sg:address":"6353",
    "sg:city":"Weggis",
    "sg:orig_category":"Sessellifte and Skilifte",
    "sg:phone":"+41 41 397 16 77",
    "sg:postcode":"6353",
    "sg:province":"Luzern",
    "wof:name":"Korporation Weggis Skilift Gratalp",
    "wof:placetype":"venue"
},
  "geometry": {"coordinates":[8.4343938828,47.0322952271],"type":"Point"}
}