{
  "type": "Feature",
  "properties": {
    "iso:country":"CH",
    "sg:address":"Avenue De Feuillasse 5",
    "sg:city":"Meyrin",
    "sg:orig_category":"Detailhandel mit M\u00f6beln U Haushaltsgegenst\u00e4nden",
    "sg:phone":"+41 79 206 89 16",
    "sg:postcode":"1217",
    "sg:province":"Gen\u00e8ve",
    "wof:name":"Giardini Carlo",
    "wof:placetype":"venue"
},
  "geometry": {"coordinates":[6.0838680267,46.2295379639],"type":"Point"}
}