{
  "type": "Feature",
  "properties": {
    "iso:country":"CH",
    "sg:address":"Dorflindenstrasse 4",
    "sg:city":"Z\u00fcrich",
    "sg:classifiers":[
        {
            "category":"Social Services",
            "subcategory":"Retirement Home",
            "type":"Services"
        }
    ],
    "sg:phone":"+41 13115022",
    "sg:postcode":"8050",
    "sg:province":"Z\u00fcrich",
    "sg:tags":[
        "pflegeheime",
        "u",
        "alters"
    ],
    "wof:name":"Dorflinde",
    "wof:placetype":"venue"
},
  "geometry": {"coordinates":[8.549191,47.407909],"type":"Point"}
}