{
  "type": "Feature",
  "properties": {
    "iso:country":"CH",
    "sg:address":"Schlossbergstrasse 5b 8820 W\u00e4denswil. Postfach",
    "sg:city":"W\u00e4denswil",
    "sg:orig_category":"Non-Classified Establishments",
    "sg:postcode":"8820",
    "sg:province":"Z\u00fcrich",
    "wof:name":"Absolut Internet, Mutti M.",
    "wof:placetype":"venue"
},
  "geometry": {"coordinates":[8.6759290695,47.22631073],"type":"Point"}
}