{
  "type": "Feature",
  "properties": {
    "iso:country":"CH",
    "sg:address":"Kyburgstrasse 29",
    "sg:city":"Z\u00fcrich",
    "sg:orig_category":"Druckweiterverarbeitung",
    "sg:phone":"+41 12717103",
    "sg:postcode":"8037",
    "sg:province":"Z\u00fcrich",
    "wof:name":"Caruso Graphic Design",
    "wof:placetype":"venue"
},
  "geometry": {"coordinates":[8.5261478424,47.3931007385],"type":"Point"}
}