{
  "type": "Feature",
  "properties": {
    "iso:country":"CH",
    "sg:address":"Laupenstrasse 17",
    "sg:city":"Bern",
    "sg:classifiers":[
        {
            "category":"Restaurant",
            "type":"Food & Drink"
        }
    ],
    "sg:phone":"+41 31 381 25 73",
    "sg:postcode":"3008",
    "sg:province":"Bern",
    "wof:name":"Pizzeria Locanda Ticinese",
    "wof:placetype":"venue"
},
  "geometry": {"coordinates":[7.4351100922,46.9471702576],"type":"Point"}
}