{
  "type": "Feature",
  "properties": {
    "iso:country":"CH",
    "sg:address":"Seestrasse 21",
    "sg:city":"Zollikon",
    "sg:orig_category":"Pensionskassen",
    "sg:postcode":"8702",
    "sg:province":"Z\u00fcrich",
    "wof:name":"B\u00fcttner Franz-stiftung",
    "wof:placetype":"venue"
},
  "geometry": {"coordinates":[8.6900548935,47.3005561829],"type":"Point"}
}