{
  "type": "Feature",
  "properties": {
    "iso:country":"CH",
    "sg:address":"Marquard Wocherstrasse 5",
    "sg:city":"Thun",
    "sg:orig_category":"Sonstige pers\u00f6nliche Dienstleistungen",
    "sg:phone":"+41 33 335 59 33",
    "sg:postcode":"3600",
    "sg:province":"Bern",
    "wof:name":"Beauty Way, Nagler Marlise",
    "wof:placetype":"venue"
},
  "geometry": {"coordinates":[7.6310038567,46.746799469],"type":"Point"}
}