{
  "type": "Feature",
  "properties": {
    "addr:full":"Vordergasse 14 Schaffhausen Schaffhausen 8200",
    "addr:housenumber":"14",
    "addr:postcode":"8200",
    "addr:street":"Vordergasse",
    "iso:country":"CH",
    "sg:address":"Vordergasse 14",
    "sg:city":"Schaffhausen",
    "sg:orig_category":"Architektur U Ingenieurb\u00fcros",
    "sg:phone":"+41 52 625 69 93",
    "sg:postcode":"8200",
    "sg:province":"Schaffhausen",
    "wof:name":"Ruh + Blum",
    "wof:placetype":"venue"
},
  "geometry": {"coordinates":[8.637248,47.696114],"type":"Point"}
}