{
  "type": "Feature",
  "properties": {
    "iso:country":"CH",
    "sg:address":"Seestrasse 58 3700 Spiez. Postfach 221",
    "sg:city":"Spiez",
    "sg:classifiers":[
        {
            "category":"Travel",
            "subcategory":"Hotels & Motels",
            "type":"Entertainment"
        }
    ],
    "sg:phone":"+41 33 654 11 54",
    "sg:postcode":"3700",
    "sg:province":"Bern",
    "sg:tags":[
        "hotels",
        "mit",
        "restaurant"
    ],
    "wof:name":"Edenhotel Z\u00f6lch Hotel Ag",
    "wof:placetype":"venue"
},
  "geometry": {"coordinates":[7.6820077896,46.6896057129],"type":"Point"}
}