{
  "type": "Feature",
  "properties": {
    "addr:full":"Dorfstrasse 25 8803 R\u00fcschlikon. Postfach R\u00fcschlikon Z\u00fcrich 8803",
    "addr:housenumber":"25",
    "addr:postcode":"8803;8803",
    "addr:street":"Dorfstrasse;Postfach Rueschlikon Zuerich",
    "iso:country":"CH",
    "sg:address":"Dorfstrasse 25 8803 R\u00fcschlikon. Postfach",
    "sg:city":"R\u00fcschlikon",
    "sg:orig_category":"Detailhandel mit Blumen U Pflanzen Fachdetailhandel in Verkaufsr\u00e4umen",
    "sg:phone":"+41 19106290",
    "sg:postcode":"8803",
    "sg:province":"Z\u00fcrich",
    "wof:name":"Blumengesch\u00e4ft Dolder, Inhaber Toni Steffen",
    "wof:placetype":"venue"
},
  "geometry": {"coordinates":[8.582899,47.317474],"type":"Point"}
}