{
  "type": "Feature",
  "properties": {
    "iso:country":"CH",
    "sg:address":"Langacher 6",
    "sg:city":"Hombrechtikon",
    "sg:classifiers":[
        {
            "category":"Restaurant",
            "type":"Food & Drink"
        }
    ],
    "sg:phone":"+41 62 771 12 57",
    "sg:postcode":"8634",
    "sg:province":"Z\u00fcrich",
    "wof:name":"Restaurant Sch\u00fctzenhaus",
    "wof:placetype":"venue"
},
  "geometry": {"coordinates":[8.1906728745,47.2570419312],"type":"Point"}
}