{
  "type": "Feature",
  "properties": {
    "iso:country":"CH",
    "sg:address":"Kirchstrasse 28",
    "sg:city":"Amriswil",
    "sg:orig_category":"Maschinenbau Mechanische Werkst\u00e4tten",
    "sg:phone":"+41 71 411 50 77",
    "sg:postcode":"8580",
    "sg:province":"Thurgau",
    "wof:name":"Extru-pr\u00e4zision Ag",
    "wof:placetype":"venue"
},
  "geometry": {"coordinates":[9.2998828888,47.5487174988],"type":"Point"}
}