{
  "type": "Feature",
  "properties": {
    "iso:country":"CH",
    "sg:address":"Freie Strasse 3-5 4001 Basel. Postfach",
    "sg:city":"Basel",
    "sg:orig_category":"Detailhandel mit Herrenbekleidung Herstellung von Oberbekleidung",
    "sg:phone":"+41 61 261 68 44",
    "sg:postcode":"4001",
    "sg:province":"Basel-Stadt",
    "wof:name":"Pkz Burger-kehl & Co. Aktiengesellschaft",
    "wof:placetype":"venue"
},
  "geometry": {"coordinates":[7.588616848,47.557723999],"type":"Point"}
}