{
  "type": "Feature",
  "properties": {
    "iso:country":"CH",
    "sg:address":"Korneliusstrasse 3 8008 Z\u00fcrich. Postfach",
    "sg:city":"Z\u00fcrich",
    "sg:orig_category":"Softwareentwicklung U beratung",
    "sg:phone":"+41 79 603 75 42",
    "sg:postcode":"8034",
    "sg:province":"Z\u00fcrich",
    "wof:name":"Cyber Ab-sys Gmbh Oracle Dba, Software-beratungsauftr\u00e4ge, Strategieentwicklung Usw",
    "wof:placetype":"venue"
},
  "geometry": {"coordinates":[8.5552587509,47.3552398682],"type":"Point"}
}