{
  "type": "Feature",
  "properties": {
    "iso:country":"CH",
    "sg:address":"Maulbeerstrasse 47",
    "sg:city":"Basel",
    "sg:orig_category":"Herstellung von Uhren",
    "sg:postcode":"4058",
    "sg:province":"Basel-Stadt",
    "wof:name":"Remak's Watches & Jewellery Gmbh",
    "wof:placetype":"venue"
},
  "geometry": {"coordinates":[7.6021571159,47.5676231384],"type":"Point"}
}