{
  "type": "Feature",
  "properties": {
    "iso:country":"CH",
    "sg:address":"Rietwiesenstrasse 34",
    "sg:city":"Kesswil",
    "sg:orig_category":"Grosshandel mit Eisenwaren sowie Installationsbedarf f\u00fcr Gas, Wasser U Heizung Instandhaltung U Repa",
    "sg:phone":"+41 71 460 06 62",
    "sg:postcode":"8593",
    "sg:province":"Thurgau",
    "wof:name":"Aemisegger",
    "wof:placetype":"venue"
},
  "geometry": {"coordinates":[9.3265428543,47.5925750732],"type":"Point"}
}