{
  "type": "Feature",
  "properties": {
    "iso:country":"CH",
    "sg:address":"Heimisbach Kramershaus.",
    "sg:city":"Trachselwald",
    "sg:orig_category":"Allgemeiner Hoch U Tiefbau",
    "sg:postcode":"3456",
    "sg:province":"Bern",
    "wof:name":"Reist, Hans.",
    "wof:placetype":"venue"
},
  "geometry": {"coordinates":[7.74111,47.014221],"type":"Point"}
}