{
  "type": "Feature",
  "properties": {
    "iso:country":"CH",
    "sg:address":"Mattenstrasse 7",
    "sg:city":"Riedholz",
    "sg:orig_category":"Fachdetailhandel in Verkaufsr\u00e4umen",
    "sg:postcode":"4533",
    "sg:province":"Solothurn",
    "wof:name":"K\u00e4sermann Renmann",
    "wof:placetype":"venue"
},
  "geometry": {"coordinates":[7.5674710274,47.231174469],"type":"Point"}
}