{
  "type": "Feature",
  "properties": {
    "addr:full":"Riva Caccia 1/a Lugano Ticino 6902",
    "addr:housenumber":"1 / a",
    "addr:postcode":"6902",
    "addr:street":"Riva Caccia",
    "iso:country":"CH",
    "sg:address":"Riva Caccia 1/a",
    "sg:city":"Lugano",
    "sg:classifiers":[
        {
            "category":"Banks & Credit Unions",
            "subcategory":"Bank",
            "type":"Services"
        }
    ],
    "sg:postcode":"6902",
    "sg:province":"Ticino",
    "wof:name":"Motor-columbus Ag",
    "wof:placetype":"venue"
},
  "geometry": {"coordinates":[8.30644,47.474319],"type":"Point"}
}