{
  "type": "Feature",
  "properties": {
    "iso:country":"CH",
    "sg:address":"Haus Olympia",
    "sg:city":"T\u00e4sch",
    "sg:orig_category":"Reiseb\u00fcros U Reiseveranstalter",
    "sg:postcode":"3929",
    "sg:province":"Valais",
    "wof:name":"Touristik Pro T\u00e4sch Ag",
    "wof:placetype":"venue"
},
  "geometry": {"coordinates":[7.7763252258,46.069694519],"type":"Point"}
}