{
  "type": "Feature",
  "properties": {
    "addr:full":"Hegmattenstrasse 20 Stadel(winterthur) Z\u00fcrich 8404",
    "addr:housenumber":"20",
    "addr:postcode":"8404",
    "addr:street":"Hegmattenstrasse",
    "iso:country":"CH",
    "sg:address":"Hegmattenstrasse 20",
    "sg:city":"Stadel(winterthur)",
    "sg:orig_category":"Abdichtung Oberfl\u00e4chenveredlung U W\u00e4rmebehandlung",
    "sg:phone":"+41 52 243 02 20",
    "sg:postcode":"8404",
    "sg:province":"Z\u00fcrich",
    "wof:name":"Isotech Beschichtungen Ag Winterthur",
    "wof:placetype":"venue"
},
  "geometry": {"coordinates":[8.758223,47.506569],"type":"Point"}
}