{
  "type": "Feature",
  "properties": {
    "iso:country":"CH",
    "sg:address":"Rairing 10",
    "sg:city":"D\u00e4llikon",
    "sg:orig_category":"Unternehmensberatung",
    "sg:phone":"+41 18450673",
    "sg:postcode":"8108",
    "sg:province":"Z\u00fcrich",
    "wof:name":"Wemas-consult, Werner Schneider",
    "wof:placetype":"venue"
},
  "geometry": {"coordinates":[8.4437236786,47.4368171692],"type":"Point"}
}