{
  "type": "Feature",
  "properties": {
    "iso:country":"CH",
    "sg:address":"Weizenfeldstrasse 7",
    "sg:city":"Derendingen",
    "sg:orig_category":"Herstellung von Ausbauelementen aus Metall",
    "sg:postcode":"4552",
    "sg:province":"Solothurn",
    "wof:name":"St\u00f6ckli Hugo",
    "wof:placetype":"venue"
},
  "geometry": {"coordinates":[7.5902919769,47.1905670166],"type":"Point"}
}