{
  "type": "Feature",
  "properties": {
    "iso:country":"CH",
    "sg:address":"Chalet Gamperdon",
    "sg:city":"Flums",
    "sg:orig_category":"Vermietung U Verpachtung von eigenen Immobilien",
    "sg:postcode":"8890",
    "sg:province":"St. Gallen",
    "wof:name":"Fimoran Ag",
    "wof:placetype":"venue"
},
  "geometry": {"coordinates":[9.3425388336,47.0917549133],"type":"Point"}
}