{
  "type": "Feature",
  "properties": {
    "iso:country":"CH",
    "sg:address":"Flurenstrasse 9",
    "sg:city":"Fahrwangen",
    "sg:orig_category":"Massagestudios P\u00e9dicure",
    "sg:phone":"+41 56 667 36 63",
    "sg:postcode":"5615",
    "sg:province":"Aargau",
    "wof:name":"Monika Stelzer P\u00e9dicure Massage",
    "wof:placetype":"venue"
},
  "geometry": {"coordinates":[8.2392148972,47.297492981],"type":"Point"}
}