{
  "type": "Feature",
  "properties": {
    "iso:country":"CH",
    "sg:address":"Centre",
    "sg:city":"Sion",
    "sg:orig_category":"Detailhandel mit Waren verschiedener Art in Verkaufsr\u00e4umen Fachdetailhandel mit Nahrungsmitteln, Get",
    "sg:phone":"+41 27 203 52 12",
    "sg:postcode":"1950",
    "sg:province":"Valais",
    "wof:name":"Otto's Ag",
    "wof:placetype":"venue"
},
  "geometry": {"coordinates":[7.3560781479,46.2369232178],"type":"Point"}
}