{
  "type": "Feature",
  "properties": {
    "iso:country":"CH",
    "sg:address":"Ch. G\u00e9rard-de-ternier 2",
    "sg:city":"Petit-lancy",
    "sg:classifiers":[
        {
            "category":"Organizations",
            "subcategory":"Labor Organization",
            "type":"Services"
        }
    ],
    "sg:phone":"+41 22 879 09 80",
    "sg:postcode":"1213",
    "sg:province":"Gen\u00e8ve",
    "sg:tags":[
        "work",
        "assembling",
        "assembly",
        "contract"
    ],
    "wof:name":"Born Sa",
    "wof:placetype":"venue"
},
  "geometry": {"coordinates":[6.1081,46.194466],"type":"Point"}
}