{
  "type": "Feature",
  "properties": {
    "iso:country":"CH",
    "sg:address":"Lindenstrasse 73",
    "sg:city":"St.gallen",
    "sg:orig_category":"Herstellung von Konstruktionsteilen, Fertigbauteilen U Ausbauelementen aus Holz Innenausbau",
    "sg:phone":"+41 79 222 81 80",
    "sg:postcode":"9000",
    "sg:province":"St. Gallen",
    "wof:name":"Urech M. & Co",
    "wof:placetype":"venue"
},
  "geometry": {"coordinates":[7.5253529549,47.5052146912],"type":"Point"}
}