{
  "type": "Feature",
  "properties": {
    "iso:country":"CH",
    "sg:address":"Zugerstrasse 77",
    "sg:city":"Baar",
    "sg:orig_category":"Grosshandel mit festen Brennstoffen U Mineral\u00f6lerzeugnissen",
    "sg:phone":"+41 41 766 07 55",
    "sg:postcode":"6340",
    "sg:province":"Zug",
    "wof:name":"Onyx Oil Ltd",
    "wof:placetype":"venue"
},
  "geometry": {"coordinates":[8.5199966431,47.1830482483],"type":"Point"}
}