{
  "type": "Feature",
  "properties": {
    "iso:country":"CH",
    "sg:address":"Route Du D\u00e9barcad\u00e8re 6 1470 Estavayer-le-lac. Postfach",
    "sg:city":"Estavayer-le-lac",
    "sg:classifiers":[
        {
            "category":"Travel",
            "subcategory":"Hotels & Motels",
            "type":"Entertainment"
        }
    ],
    "sg:phone":"+41 26 663 13 43",
    "sg:postcode":"1470",
    "sg:province":"Fribourg",
    "sg:tags":[
        "hotels",
        "mit",
        "restaurant"
    ],
    "wof:name":"H\u00f4tel Lac Au Port D'estavayer",
    "wof:placetype":"venue"
},
  "geometry": {"coordinates":[6.8403701782,46.8511886597],"type":"Point"}
}