{
  "type": "Feature",
  "properties": {
    "iso:country":"CH",
    "sg:address":"Avenue De France 38",
    "sg:city":"Lausanne",
    "sg:classifiers":[
        {
            "category":"Restaurant",
            "type":"Food & Drink"
        }
    ],
    "sg:phone":"+41 27 281 11 57",
    "sg:postcode":"1004",
    "sg:province":"Vaud",
    "wof:name":"Caf\u00e9 Cabane De La Matze",
    "wof:placetype":"venue"
},
  "geometry": {"coordinates":[7.3860898018,46.184841156],"type":"Point"}
}