{
  "type": "Feature",
  "properties": {
    "iso:country":"CH",
    "sg:address":"En Boverey Z.i.",
    "sg:city":"Collombey",
    "sg:orig_category":"Detailhandel Einzelhandel mit Automobilen Reparatur von Gebrauchsg\u00fctern",
    "sg:phone":"+41 24 472 80 30",
    "sg:postcode":"1868",
    "sg:province":"Valais",
    "wof:name":"Services Dewarrat Sa Caravanes",
    "wof:placetype":"venue"
},
  "geometry": {"coordinates":[6.945827961,46.2704734802],"type":"Point"}
}