{
  "type": "Feature",
  "properties": {
    "iso:country":"CH",
    "sg:address":"Haldenstrasse 22 8306 Br\u00fcttisellen. Postfach",
    "sg:city":"Br\u00fcttisellen",
    "sg:orig_category":"Wirtschaftspr\u00fcfung, Steuerberatung U Treuhand",
    "sg:postcode":"8306",
    "sg:province":"Z\u00fcrich",
    "wof:name":"Asa Treuhand, Sartori Roland",
    "wof:placetype":"venue"
},
  "geometry": {"coordinates":[8.6305570602,47.4197845459],"type":"Point"}
}