{
  "type": "Feature",
  "properties": {
    "iso:country":"CH",
    "sg:address":"2853",
    "sg:city":"Courfaivre",
    "sg:orig_category":"Landesverteidigung, Sozialversicherung \u00d6ffentliche Verwaltung",
    "sg:phone":"+41 32 426 71 80",
    "sg:postcode":"2853",
    "sg:province":"Jura",
    "wof:name":"Administration Communale Protection Civile",
    "wof:placetype":"venue"
},
  "geometry": {"coordinates":[7.2807021141,47.3344116211],"type":"Point"}
}