{
  "type": "Feature",
  "properties": {
    "iso:country":"CH",
    "sg:address":"Corso Bello 7",
    "sg:city":"Mendrisio",
    "sg:classifiers":[
        {
            "category":"Banks & Credit Unions",
            "subcategory":"Bank",
            "type":"Services"
        }
    ],
    "sg:phone":"+41 4191467380",
    "sg:postcode":"6850",
    "sg:province":"Ticino",
    "wof:name":"Banca Della Svizzera Italiana",
    "wof:placetype":"venue"
},
  "geometry": {"coordinates":[8.987768,45.869892],"type":"Point"}
}