{
  "type": "Feature",
  "properties": {
    "iso:country":"CH",
    "sg:address":"Z\u00fcrcherstrasse 80a",
    "sg:city":"Sargans",
    "sg:orig_category":"Architektur U Ingenieurb\u00fcros",
    "sg:phone":"+41 81 710 04 40",
    "sg:postcode":"7320",
    "sg:province":"St. Gallen",
    "wof:name":"Dieter Struber Technisches B\u00fcro",
    "wof:placetype":"venue"
},
  "geometry": {"coordinates":[9.430625,47.05162],"type":"Point"}
}