{
  "type": "Feature",
  "properties": {
    "iso:country":"CH",
    "sg:address":"Hertensteinstrasse 42",
    "sg:city":"Weggis",
    "sg:orig_category":"Wirtschafts- and Arbeitgeberverb\u00e4nde",
    "sg:phone":"+41 79 334 49 41",
    "sg:postcode":"6353",
    "sg:province":"Luzern",
    "wof:name":"Hotelier-verein Weggis Herrn Hans Hasler",
    "wof:placetype":"venue"
},
  "geometry": {"coordinates":[8.4202766418,47.0294570923],"type":"Point"}
}