{
  "type": "Feature",
  "properties": {
    "iso:country":"CH",
    "sg:address":"Steinhauserstrasse 33",
    "sg:city":"Zug",
    "sg:orig_category":"Sonstiger Grosshandel",
    "sg:postcode":"6300",
    "sg:province":"Zug",
    "wof:name":"Ground Resource Trading Ltd",
    "wof:placetype":"venue"
},
  "geometry": {"coordinates":[8.4939241409,47.1838951111],"type":"Point"}
}