{
  "type": "Feature",
  "properties": {
    "iso:country":"CH",
    "sg:address":"Chalet Arve",
    "sg:city":"Beatenberg",
    "sg:orig_category":"Dachdeckerei Zimmerei, Dachdeckerei, Bauspenglerei U Abdichtung",
    "sg:phone":"+41 62 771 13 59",
    "sg:postcode":"3803",
    "sg:province":"Bern",
    "wof:name":"Gr\u00fctter Bedachungen Ag",
    "wof:placetype":"venue"
},
  "geometry": {"coordinates":[8.201817,47.263561],"type":"Point"}
}