{
  "type": "Feature",
  "properties": {
    "iso:country":"CH",
    "sg:address":"La Pastorale",
    "sg:city":"Grandson",
    "sg:orig_category":"Notariate",
    "sg:phone":"+41 24 445 13 41",
    "sg:postcode":"1422",
    "sg:province":"Vaud",
    "wof:name":"Pierre Verrey Etude De Notaire",
    "wof:placetype":"venue"
},
  "geometry": {"coordinates":[6.6459851265,46.8093681335],"type":"Point"}
}