{
  "type": "Feature",
  "properties": {
    "iso:country":"CH",
    "sg:address":"Unterzelg",
    "sg:city":"Gr\u00fcningen",
    "sg:orig_category":"Herstellung von Elektrizit\u00e4tsverteilungs U schalteinrichtungen",
    "sg:phone":"+41 19354434",
    "sg:postcode":"8627",
    "sg:province":"Z\u00fcrich",
    "wof:name":"R\u00fcede Schalttableaubau Und Regelungen",
    "wof:placetype":"venue"
},
  "geometry": {"coordinates":[8.7560510635,47.2805900574],"type":"Point"}
}