{
  "type": "Feature",
  "properties": {
    "iso:country":"CH",
    "sg:address":"Saumhalde 5 9100 Herisau. Postfach 1556",
    "sg:city":"Herisau",
    "sg:orig_category":"Wirtschaftspr\u00fcfung, Steuerberatung U Treuhand",
    "sg:postcode":"9102",
    "sg:province":"Appenzell Ausserrhoden",
    "wof:name":"Zemp Dr. Treuhandgesellschaft Ag",
    "wof:placetype":"venue"
},
  "geometry": {"coordinates":[9.3941631317,47.4453048706],"type":"Point"}
}