{
  "type": "Feature",
  "properties": {
    "iso:country":"CH",
    "sg:address":"G\u00e4ssli 21",
    "sg:city":"Hunzenschwil",
    "sg:orig_category":"Grosshandel mit Datenverarbeitungsger\u00e4ten Hardwareberatung",
    "sg:phone":"+41 62 897 51 68",
    "sg:postcode":"5502",
    "sg:province":"Aargau",
    "wof:name":"Reycom Gmbh",
    "wof:placetype":"venue"
},
  "geometry": {"coordinates":[8.1211395264,47.3807258606],"type":"Point"}
}