{
  "type": "Feature",
  "properties": {
    "iso:country":"CH",
    "sg:address":"Neue Winterthurerstrasse 26",
    "sg:city":"Wallisellen",
    "sg:orig_category":"Immobilienwesen Kauf U Verkauf von Immobilien auf eigene Rechnung",
    "sg:phone":"+41 18302288",
    "sg:postcode":"8304",
    "sg:province":"Z\u00fcrich",
    "wof:name":"Fr\u00fch Immobilien Gmbh Verkauf Und Verwaltung",
    "wof:placetype":"venue"
},
  "geometry": {"coordinates":[8.6078386307,47.4107322693],"type":"Point"}
}