{
  "type": "Feature",
  "properties": {
    "iso:country":"CH",
    "sg:address":"Frauentalstrasse 1 Hagendorn 6330 Cham. Postfach",
    "sg:city":"Hagendorn",
    "sg:orig_category":"Allgemeiner Hoch U Tiefbau",
    "sg:phone":"+41 32 732 16 40",
    "sg:postcode":"6332",
    "sg:province":"Zug",
    "wof:name":"Losinger Construction Sa",
    "wof:placetype":"venue"
},
  "geometry": {"coordinates":[6.900601,46.989262],"type":"Point"}
}