{
  "type": "Feature",
  "properties": {
    "iso:country":"CH",
    "sg:address":"Rue Village 27",
    "sg:city":"Genthod",
    "sg:classifiers":[
        {
            "category":"Banks & Credit Unions",
            "subcategory":"Bank",
            "type":"Services"
        }
    ],
    "sg:phone":"+41 22 774 23 92",
    "sg:postcode":"1294",
    "sg:province":"Gen\u00e8ve",
    "wof:name":"Banque Raiffeisen, Genthod-bellevue",
    "wof:placetype":"venue"
},
  "geometry": {"coordinates":[6.156836,46.263805],"type":"Point"}
}