{
  "type": "Feature",
  "properties": {
    "iso:country":"CH",
    "sg:address":"Fauconnerie Chemin De La 5",
    "sg:city":"Plan-les-ouates",
    "sg:orig_category":"Sonstiger Grosshandel",
    "sg:phone":"+41 41 630 30 33",
    "sg:postcode":"1228",
    "sg:province":"Gen\u00e8ve",
    "wof:name":"Etc East Trading Corporation",
    "wof:placetype":"venue"
},
  "geometry": {"coordinates":[8.3128166199,46.9871444702],"type":"Point"}
}