{
  "type": "Feature",
  "properties": {
    "iso:country":"CH",
    "sg:address":"Oltnerstrasse 29",
    "sg:city":"H\u00e4gendorf",
    "sg:orig_category":"Handel mit Automobilteilen U Zubeh\u00f6r",
    "sg:postcode":"4614",
    "sg:province":"Solothurn",
    "wof:name":"Raceland Aerodynamic & Tuning Nussbaum",
    "wof:placetype":"venue"
},
  "geometry": {"coordinates":[7.8498048782,47.3355560303],"type":"Point"}
}