{
  "type": "Feature",
  "properties": {
    "iso:country":"CH",
    "sg:address":"Grossfeldstrasse 38",
    "sg:city":"Sargans",
    "sg:orig_category":"Arztpraxen",
    "sg:phone":"+41 81 723 66 96",
    "sg:postcode":"7320",
    "sg:province":"St. Gallen",
    "wof:name":"Dr.med.frantisek Jenik Spezialarzt Fmh",
    "wof:placetype":"venue"
},
  "geometry": {"coordinates":[9.436614,47.046677],"type":"Point"}
}