{
  "type": "Feature",
  "properties": {
    "iso:country":"CH",
    "sg:address":"Baumgartenstrasse 15",
    "sg:city":"Schaffhausen",
    "sg:orig_category":"Pensionskassen",
    "sg:postcode":"8200",
    "sg:province":"Schaffhausen",
    "wof:name":"Personalstiftung Mch",
    "wof:placetype":"venue"
},
  "geometry": {"coordinates":[8.6368761063,47.6945114136],"type":"Point"}
}