{
  "type": "Feature",
  "properties": {
    "iso:country":"CH",
    "sg:address":"Gysschlossweg 2",
    "sg:city":"Balsthal",
    "sg:orig_category":"Unclassifiable Establishments",
    "sg:postcode":"4710",
    "sg:province":"Solothurn",
    "wof:name":"Fun-pferdefutter Gmbh",
    "wof:placetype":"venue"
},
  "geometry": {"coordinates":[7.7016129494,47.3191871643],"type":"Point"}
}