{
  "type": "Feature",
  "properties": {
    "iso:country":"CH",
    "sg:address":"8877",
    "sg:city":"Murg",
    "sg:classifiers":[
        {
            "category":"Government",
            "subcategory":"Post Office",
            "type":"Public Place"
        }
    ],
    "sg:phone":"+41 81 738 11 97",
    "sg:postcode":"8877",
    "sg:province":"St. Gallen",
    "sg:tags":[
        "caf\u00e9s",
        "tea-rooms"
    ],
    "wof:name":"Caf\u00e9 Oess",
    "wof:placetype":"venue"
},
  "geometry": {"coordinates":[9.2161102295,47.1130218506],"type":"Point"}
}