{
  "type": "Feature",
  "properties": {
    "iso:country":"CH",
    "sg:address":"Murgstrasse 1",
    "sg:city":"W\u00e4ngi",
    "sg:classifiers":[
        {
            "category":"Restaurant",
            "type":"Food & Drink"
        }
    ],
    "sg:phone":"+41 52 378 12 69",
    "sg:postcode":"9545",
    "sg:province":"Thurgau",
    "wof:name":"Restaurant Sternen",
    "wof:placetype":"venue"
},
  "geometry": {"coordinates":[8.9517745972,47.4965553284],"type":"Point"}
}