{
  "type": "Feature",
  "properties": {
    "iso:country":"CH",
    "sg:address":"Gr\u00fcssenweg 4 4133 Pratteln. Postfach",
    "sg:city":"Pratteln",
    "sg:orig_category":"Non-Classified Establishments",
    "sg:postcode":"4133",
    "sg:province":"Basel-Landschaft",
    "wof:name":"Care.on Communications Gmbh",
    "wof:placetype":"venue"
},
  "geometry": {"coordinates":[7.6899881363,47.5279426575],"type":"Point"}
}