{
  "type": "Feature",
  "properties": {
    "iso:country":"CH",
    "sg:address":"Matterstrasse 4",
    "sg:city":"Bern",
    "sg:orig_category":"Malerei",
    "sg:phone":"+41 31 302 58 18",
    "sg:postcode":"3006",
    "sg:province":"Bern",
    "wof:name":"Fritz Leu Malergesch\u00e4ft",
    "wof:placetype":"venue"
},
  "geometry": {"coordinates":[7.4702801704,46.9354400635],"type":"Point"}
}