{
  "type": "Feature",
  "properties": {
    "iso:country":"CH",
    "sg:address":"Avenue D'echallens 35",
    "sg:city":"Lausanne",
    "sg:orig_category":"Arztpraxen",
    "sg:phone":"+41 21 626 39 37",
    "sg:postcode":"1004",
    "sg:province":"Vaud",
    "wof:name":"Dr M\u00e9d. Anne-b\u00e9atrice Maillard M\u00e9decin Sp\u00e9cialiste Fmh",
    "wof:placetype":"venue"
},
  "geometry": {"coordinates":[6.61873,46.533489],"type":"Point"}
}