{
  "type": "Feature",
  "properties": {
    "iso:country":"CH",
    "sg:address":"1131",
    "sg:city":"Tolochenaz",
    "sg:orig_category":"Pensionskassen",
    "sg:postcode":"1131",
    "sg:province":"Vaud",
    "wof:name":"Fonds De Pr\u00e9voyance Du Personnel De La F\u00e9d\u00e9ration Vaudoise Des Entrepreneurs (fve)",
    "wof:placetype":"venue"
},
  "geometry": {"coordinates":[6.4742050171,46.5053062439],"type":"Point"}
}