{
  "type": "Feature",
  "properties": {
    "iso:country":"CH",
    "sg:address":"S\u00fcessbl\u00e4tzstrasse",
    "sg:city":"Ebmatingen",
    "sg:orig_category":"Mit Sport verbundene T\u00e4tigkeiten Sonstige mit Sport verbundene T\u00e4tigkeiten",
    "sg:phone":"+41 71 761 25 57",
    "sg:postcode":"8123",
    "sg:province":"Z\u00fcrich",
    "wof:name":"Reitbahn Birkenau Gen.",
    "wof:placetype":"venue"
},
  "geometry": {"coordinates":[9.5670690536,47.3181724548],"type":"Point"}
}