{
  "type": "Feature",
  "properties": {
    "iso:country":"CH",
    "sg:address":"Route De Tsavez 2",
    "sg:city":"Chamoson",
    "sg:orig_category":"D\u00e4mmung gegen K\u00e4lte, W\u00e4rme, Schall U Ersch\u00fctterung Stukkateurgewerbe, Gipserei U Verputzerei",
    "sg:phone":"+41 27 306 49 50",
    "sg:postcode":"1955",
    "sg:province":"Valais",
    "wof:name":"Praz Nones & Fils",
    "wof:placetype":"venue"
},
  "geometry": {"coordinates":[7.2219209671,46.2063941956],"type":"Point"}
}