{
  "type": "Feature",
  "properties": {
    "iso:country":"CH",
    "sg:address":"Forelstrasse 3",
    "sg:city":"Ostermundigen",
    "sg:orig_category":"Detailhandel mit Waren verschiedener Art, Hauptrichtung Nahrungsmittel Grosshandel mit Nahrungsmitte",
    "sg:phone":"+41 71 385 40 66",
    "sg:postcode":"3072",
    "sg:province":"Bern",
    "wof:name":"Pierrot-lusso Ag",
    "wof:placetype":"venue"
},
  "geometry": {"coordinates":[9.2830886841,47.4082221985],"type":"Point"}
}