{
  "type": "Feature",
  "properties": {
    "iso:country":"CH",
    "sg:address":"Route Du Centre 13",
    "sg:city":"Corminboeuf",
    "sg:orig_category":"RESTAURANTS: TEA-ROOMS",
    "sg:phone":"+41 26 475 45 02",
    "sg:postcode":"1720",
    "sg:province":"Fribourg",
    "wof:name":"Tea-room Le Stress, Mme Caputo Maria",
    "wof:placetype":"venue"
},
  "geometry": {"coordinates":[7.1031208038,46.8078460693],"type":"Point"}
}