{
  "type": "Feature",
  "properties": {
    "addr:full":"Avenue Du Midi 9 Sion Valais 1950",
    "addr:housenumber":"9",
    "addr:postcode":"1950",
    "addr:street":"Avenue Du Midi",
    "iso:country":"CH",
    "sg:address":"Avenue Du Midi 9",
    "sg:city":"Sion",
    "sg:orig_category":"Detailhandel mit Beleuchtungs U Haushaltsgegenst\u00e4nden Detailhandel mit Geschenkartikeln U Souvenirs",
    "sg:phone":"+41 55 210 26 00",
    "sg:postcode":"1950",
    "sg:province":"Valais",
    "wof:name":"Das Depot Demosa Ag",
    "wof:placetype":"venue"
},
  "geometry": {"coordinates":[8.818786,47.226009],"type":"Point"}
}