{
  "type": "Feature",
  "properties": {
    "iso:country":"CH",
    "sg:address":"Nordstrasse 4f",
    "sg:city":"Luterbach",
    "sg:orig_category":"Erbringung von Dienstleistungen f\u00fcr Unternehmen",
    "sg:phone":"+41 32 682 19 16",
    "sg:postcode":"4542",
    "sg:province":"Solothurn",
    "wof:name":"Pneutronic Ag",
    "wof:placetype":"venue"
},
  "geometry": {"coordinates":[7.5780739784,47.2171783447],"type":"Point"}
}