{
  "type": "Feature",
  "properties": {
    "iso:country":"CH",
    "sg:address":"5703",
    "sg:city":"Seon",
    "sg:orig_category":"Vereine Vogel-& Naturschutz",
    "sg:postcode":"5703",
    "sg:province":"Aargau",
    "wof:name":"Vogelschutzverein",
    "wof:placetype":"venue"
},
  "geometry": {"coordinates":[8.1603841782,47.3467407227],"type":"Point"}
}