{
  "type": "Feature",
  "properties": {
    "iso:country":"CH",
    "sg:address":"Ringstrasse 2 9302 Kronb\u00fchl. Postfach",
    "sg:city":"Kronb\u00fchl",
    "sg:orig_category":"Herstellung von sonstigen elektrischen Ausr\u00fcstungen",
    "sg:postcode":"9302",
    "wof:name":"Mextec Brugger Elektronik; Import, Vertrieb",
    "wof:placetype":"venue"
},
  "geometry": {"coordinates":[9.3922901154,47.4609107971],"type":"Point"}
}