{
  "type": "Feature",
  "properties": {
    "iso:country":"CH",
    "sg:address":"Kirchgasse 6 6234 Triengen. Postfach 229",
    "sg:city":"Triengen",
    "sg:orig_category":"Polizei",
    "sg:phone":"+41 41 933 11 17",
    "sg:postcode":"6234",
    "sg:province":"Luzern",
    "wof:name":"Kantonale Polizei",
    "wof:placetype":"venue"
},
  "geometry": {"coordinates":[8.0775880814,47.2346191406],"type":"Point"}
}