{
  "type": "Feature",
  "properties": {
    "iso:country":"CH",
    "sg:address":"Dorf 27",
    "sg:city":"Urn\u00e4sch",
    "sg:orig_category":"Sportvereine Ballsport Basketball Vereine Damen",
    "sg:phone":"+41 71 364 10 58",
    "sg:postcode":"9107",
    "sg:province":"Appenzell Ausserrhoden",
    "wof:name":"Cvjm Basekt St.gallen",
    "wof:placetype":"venue"
},
  "geometry": {"coordinates":[9.2841997147,47.3178596497],"type":"Point"}
}