{
  "type": "Feature",
  "properties": {
    "addr:full":"Rebgasse 1 Basel Basel-Stadt 4058",
    "addr:housenumber":"1",
    "addr:postcode":"4058",
    "addr:street":"Rebgasse",
    "iso:country":"CH",
    "sg:address":"Rebgasse 1",
    "sg:city":"Basel",
    "sg:orig_category":"Detailhandel mit Blumen U Pflanzen",
    "sg:phone":"+41 61 691 86 53",
    "sg:postcode":"4058",
    "sg:province":"Basel-Stadt",
    "wof:name":"C\u00e9cile B\u00fcrgin Blumengesch\u00e4ft",
    "wof:placetype":"venue"
},
  "geometry": {"coordinates":[7.593751,47.561359],"type":"Point"}
}