{
  "type": "Feature",
  "properties": {
    "iso:country":"CH",
    "sg:address":"Solothurnerstrasse 19",
    "sg:city":"Basel",
    "sg:orig_category":"Detailhandel mit Fahrr\u00e4dern Reparatur von sonstigen Gebrauchsg\u00fctern",
    "sg:postcode":"4053",
    "sg:province":"Basel-Stadt",
    "wof:name":"Martin Gerber Gundeli Velos",
    "wof:placetype":"venue"
},
  "geometry": {"coordinates":[7.5913619995,47.5450897217],"type":"Point"}
}