{
  "type": "Feature",
  "properties": {
    "iso:country":"CH",
    "sg:address":"Morgentalstrasse 3",
    "sg:city":"Aadorf",
    "sg:orig_category":"G\u00fcterbef\u00f6rderung im Strassenverkehr",
    "sg:phone":"+41 52 365 19 73",
    "sg:postcode":"8355",
    "sg:province":"Thurgau",
    "wof:name":"Terezis-bandi R.",
    "wof:placetype":"venue"
},
  "geometry": {"coordinates":[8.899064064,47.4914894104],"type":"Point"}
}