{
  "type": "Feature",
  "properties": {
    "iso:country":"CH",
    "sg:address":"Quadern",
    "sg:city":"Mols",
    "sg:orig_category":"Sportschulen Wassersport",
    "sg:phone":"+41 81 738 19 58",
    "sg:postcode":"8885",
    "sg:province":"St. Gallen",
    "wof:name":"Bootsfahrschule Manhart",
    "wof:placetype":"venue"
},
  "geometry": {"coordinates":[9.2764253616,47.1129493713],"type":"Point"}
}