{
  "type": "Feature",
  "properties": {
    "iso:country":"CH",
    "sg:address":"Niederholzstrasse 68",
    "sg:city":"Riehen",
    "sg:orig_category":"Unternehmensberatung",
    "sg:postcode":"4125",
    "sg:province":"Basel-Stadt",
    "wof:name":"Bw-consulting Dr. B. Wittwer",
    "wof:placetype":"venue"
},
  "geometry": {"coordinates":[7.6344709396,47.5726013184],"type":"Point"}
}