{
  "type": "Feature",
  "properties": {
    "iso:country":"CH",
    "sg:address":"Dorfstrasse 368",
    "sg:city":"Wohlenschwil",
    "sg:orig_category":"Herstellung von sonstigen landwirtschaftlichen Maschinen",
    "sg:phone":"+41 56 491 10 75",
    "sg:postcode":"5512",
    "sg:province":"Aargau",
    "wof:name":"Friedli Peter Traktoren Und Landmaschinen",
    "wof:placetype":"venue"
},
  "geometry": {"coordinates":[8.2605791092,47.4208831787],"type":"Point"}
}