{
  "type": "Feature",
  "properties": {
    "iso:country":"CH",
    "sg:address":"Frutigenstrasse 50a",
    "sg:city":"Thun",
    "sg:orig_category":"Handel mit Automobilen",
    "sg:postcode":"3600",
    "sg:province":"Bern",
    "wof:name":"Www.webauto.ch, Gaisch Site Internet Pour Annonces Voitures D'occasion Et Publicit\u00e9",
    "wof:placetype":"venue"
},
  "geometry": {"coordinates":[6.8612399101,46.98828125],"type":"Point"}
}