{
  "type": "Feature",
  "properties": {
    "iso:country":"CH",
    "sg:address":"Sihlhof 8 8134 Adliswil. Postfach",
    "sg:city":"Adliswil",
    "sg:orig_category":"Fachdetailhandel in Verkaufsr\u00e4umen",
    "sg:postcode":"8134",
    "sg:province":"Z\u00fcrich",
    "wof:name":"Werner Landolt Zoo Sihlhof",
    "wof:placetype":"venue"
},
  "geometry": {"coordinates":[8.5220651627,47.3213043213],"type":"Point"}
}