{
  "type": "Feature",
  "properties": {
    "iso:country":"CH",
    "sg:address":"Rebbergstrasse 11",
    "sg:city":"Zurzach",
    "sg:orig_category":"Grosshandel mit Holz U Bauelementen aus Holz Grosshandel mit Holz U Baustoffen",
    "sg:phone":"+41 56 249 15 31",
    "sg:postcode":"5330",
    "sg:province":"Aargau",
    "wof:name":"Kurt Merki Holzhandel Ag",
    "wof:placetype":"venue"
},
  "geometry": {"coordinates":[8.2885074615,47.5864486694],"type":"Point"}
}