{
  "type": "Feature",
  "properties": {
    "iso:country":"CH",
    "sg:address":"Kantonsstrasse",
    "sg:city":"Dierikon",
    "sg:orig_category":"Gesundheitswesen",
    "sg:phone":"+41 41 450 16 33",
    "sg:postcode":"6036",
    "sg:province":"Luzern",
    "wof:name":"Racket-center Dierikon",
    "wof:placetype":"venue"
},
  "geometry": {"coordinates":[8.3615751266,47.0941467285],"type":"Point"}
}