{
  "type": "Feature",
  "properties": {
    "iso:country":"CH",
    "sg:address":"Rue Du Bugnon 6",
    "sg:city":"Lausanne",
    "sg:orig_category":"Detailhandel mit Brot, Back U S\u00fcsswaren",
    "sg:phone":"+41 26 912 81 17",
    "sg:postcode":"1005",
    "sg:province":"Vaud",
    "wof:name":"Boulangerie-p\u00e2tisserie F\u00fchrer S\u00e0rl",
    "wof:placetype":"venue"
},
  "geometry": {"coordinates":[0.658087,46.120537],"type":"Point"}
}