{
  "type": "Feature",
  "properties": {
    "iso:country":"CH",
    "sg:address":"H\u00f6heweg 13 3800 Interlaken. Postfach 187",
    "sg:city":"Interlaken",
    "sg:orig_category":"Grosshandel mit Werkzeugmaschinen Herstellung von Werkzeugen",
    "sg:phone":"+41 33 822 12 21",
    "sg:postcode":"3800",
    "sg:province":"Bern",
    "wof:name":"J\u00f6rg Julius Hartmetall Und Werkzeugtechnik Ag",
    "wof:placetype":"venue"
},
  "geometry": {"coordinates":[7.8553900719,46.6853599548],"type":"Point"}
}