{
  "type": "Feature",
  "properties": {
    "iso:country":"CH",
    "sg:address":"Rossackerstrasse 102",
    "sg:city":"Z\u00fcrich",
    "sg:orig_category":"Architektur U Ingenieurb\u00fcros",
    "sg:phone":"+41 14003101",
    "sg:postcode":"8047",
    "sg:province":"Z\u00fcrich",
    "wof:name":"Cadag Ag",
    "wof:placetype":"venue"
},
  "geometry": {"coordinates":[8.489167,47.369431],"type":"Point"}
}