{
  "type": "Feature",
  "properties": {
    "iso:country":"CH",
    "sg:address":"Bahnhofstrasse 3904 Naters. Postfach 432",
    "sg:city":"Naters",
    "sg:orig_category":"Wirtschaftspr\u00fcfung, Steuerberatung U Treuhand",
    "sg:phone":"+41 27 922 40 30",
    "sg:postcode":"3904",
    "sg:province":"Valais",
    "wof:name":"Treuhand Und Revisions Ag, Naters",
    "wof:placetype":"venue"
},
  "geometry": {"coordinates":[7.985490799,46.3229789734],"type":"Point"}
}