{
  "type": "Feature",
  "properties": {
    "iso:country":"CH",
    "sg:address":"Z\u00fcrcherstrasse 99 4051 Basel. Postfach",
    "sg:city":"Basel",
    "sg:orig_category":"Fachdetailhandel in Verkaufsr\u00e4umen",
    "sg:postcode":"4051",
    "sg:province":"Basel-Stadt",
    "wof:name":"El Ni\u00f1o-asian Shop, Crowe-dizon Marites Asiatische Lebensmittel Usw.; Verkauf, Handel",
    "wof:placetype":"venue"
},
  "geometry": {"coordinates":[7.6113929749,47.5548324585],"type":"Point"}
}