{
  "type": "Feature",
  "properties": {
    "iso:country":"CH",
    "sg:address":"5300 Turgi. Postfach",
    "sg:city":"Turgi",
    "sg:orig_category":"Sportvereine Turnen",
    "sg:postcode":"5300",
    "sg:province":"Aargau",
    "wof:name":"Turnverein Etv",
    "wof:placetype":"venue"
},
  "geometry": {"coordinates":[8.2524995804,47.4925689697],"type":"Point"}
}