{
  "type": "Feature",
  "properties": {
    "iso:country":"CH",
    "sg:address":"Weiherwiesstrasse 5",
    "sg:city":"Arnegg",
    "sg:orig_category":"Unternehmensberatung",
    "sg:phone":"+41 71 385 61 74",
    "sg:postcode":"9212",
    "sg:province":"St. Gallen",
    "wof:name":"Peter & Monika R\u00fcegger Marketingberatung",
    "wof:placetype":"venue"
},
  "geometry": {"coordinates":[9.2575550079,47.4390907288],"type":"Point"}
}