{
  "type": "Feature",
  "properties": {
    "iso:country":"CH",
    "sg:address":"Pierre Rue Saint- 4",
    "sg:city":"Freiburg",
    "sg:orig_category":"Unclassifiable Establishments",
    "sg:postcode":"1700",
    "sg:province":"Fribourg",
    "wof:name":"Carthago Sa",
    "wof:placetype":"venue"
},
  "geometry": {"coordinates":[7.1546912193,46.8035240173],"type":"Point"}
}