{
  "type": "Feature",
  "properties": {
    "iso:country":"CH",
    "sg:address":"Obsthaldenstrasse 88",
    "sg:city":"Z\u00fcrich",
    "sg:orig_category":"Vorschulen, Kinderg\u00e4rten",
    "sg:phone":"+41 13710137",
    "sg:postcode":"8046",
    "sg:province":"Z\u00fcrich",
    "wof:name":"St\u00e4dtischer Kindergarten",
    "wof:placetype":"venue"
},
  "geometry": {"coordinates":[8.5174093246,47.4140663147],"type":"Point"}
}