{
  "type": "Feature",
  "properties": {
    "iso:country":"CH",
    "sg:address":"Ueberlandstrasse 9",
    "sg:city":"Dietikon",
    "sg:orig_category":"Non-Classified Establishments",
    "sg:phone":"+41 17409940",
    "sg:postcode":"8953",
    "sg:province":"Z\u00fcrich",
    "wof:name":"Calonder Energie Ag",
    "wof:placetype":"venue"
},
  "geometry": {"coordinates":[8.4074716568,47.4079437256],"type":"Point"}
}