{
  "type": "Feature",
  "properties": {
    "iso:country":"CH",
    "sg:address":"Berg\u00e8re Rue De La 5 1217 Meyrin. Postfach",
    "sg:city":"Meyrin",
    "sg:orig_category":"Pensionskassen",
    "sg:phone":"+41 22 989 06 40",
    "sg:postcode":"1217",
    "sg:province":"Gen\u00e8ve",
    "wof:name":"Fondation De Pr\u00e9voyance En Faveur Du Personnel Administratifet Des Cadres De Honda Automobiles (suisse) Sa",
    "wof:placetype":"venue"
},
  "geometry": {"coordinates":[6.0722160339,46.2284431458],"type":"Point"}
}