{
  "type": "Feature",
  "properties": {
    "iso:country":"CH",
    "sg:address":"Bahnhof",
    "sg:city":"Glarus",
    "sg:orig_category":"Sonstiger Grosshandel",
    "sg:phone":"+41 52 368 65 58",
    "sg:postcode":"8750",
    "sg:province":"Glarus",
    "wof:name":"Bioting Ag",
    "wof:placetype":"venue"
},
  "geometry": {"coordinates":[9.0710496902,47.0398330688],"type":"Point"}
}