{
  "type": "Feature",
  "properties": {
    "iso:country":"CH",
    "sg:address":"Hauptstrasse 38",
    "sg:city":"Lyss",
    "sg:orig_category":"Verarbeitung von Milch Verwertung von Milch",
    "sg:phone":"+41 32 385 35 14",
    "sg:postcode":"3250",
    "sg:province":"Bern",
    "wof:name":"Wasserfallen Walter.",
    "wof:placetype":"venue"
},
  "geometry": {"coordinates":[7.3079857826,47.0715942383],"type":"Point"}
}