{
  "type": "Feature",
  "properties": {
    "iso:country":"CH",
    "sg:address":"Sonntagsteig 5",
    "sg:city":"Z\u00fcrich",
    "sg:orig_category":"Arztpraxen",
    "sg:phone":"+41 13629128",
    "sg:postcode":"8006",
    "sg:province":"Z\u00fcrich",
    "wof:name":"Dr.med.carl Leemann Spezialarzt Fmh",
    "wof:placetype":"venue"
},
  "geometry": {"coordinates":[8.545805,47.38385],"type":"Point"}
}