{
  "type": "Feature",
  "properties": {
    "iso:country":"CH",
    "sg:address":"Bahnhofstrasse 25",
    "sg:city":"M\u00e4rstetten",
    "sg:orig_category":"Innendekorationsateliers Maler U Glasergewerbe",
    "sg:phone":"+41 71 657 15 35",
    "sg:postcode":"8560",
    "sg:province":"Thurgau",
    "wof:name":"Lendenmann Rolf",
    "wof:placetype":"venue"
},
  "geometry": {"coordinates":[9.0631771088,47.5880889893],"type":"Point"}
}