{
  "type": "Feature",
  "properties": {
    "addr:full":"Rue De La Poste 1 2024 St-aubin-sauges. Postfach St-aubin-sauges Neuch\u00e2tel 2024",
    "addr:housenumber":"1",
    "addr:postcode":"2024;2024",
    "addr:street":"Rue De La Poste;Postfach St-Aubin-Sauges Neucha\u0302Tel",
    "iso:country":"CH",
    "sg:address":"Rue De La Poste 1 2024 St-aubin-sauges. Postfach",
    "sg:city":"St-aubin-sauges",
    "sg:orig_category":"Detailhandel mit Brillen U anderen Sehhilfen Fachdetailhandel in Verkaufsr\u00e4umen",
    "sg:phone":"+41 32 835 21 32",
    "sg:postcode":"2024",
    "sg:province":"Neuch\u00e2tel",
    "wof:name":"Optique De La B\u00e9roche Philippe Schwenck",
    "wof:placetype":"venue"
},
  "geometry": {"coordinates":[6.775962,46.894459],"type":"Point"}
}