{
  "type": "Feature",
  "properties": {
    "iso:country":"CH",
    "sg:address":"Zehntenfreistrasse 45",
    "sg:city":"Bottmingen",
    "sg:orig_category":"Grosshandel mit Baumaterialien Herstellung von Transportbeton",
    "sg:phone":"+41 61 421 62 31",
    "sg:postcode":"4103",
    "sg:province":"Basel-Landschaft",
    "wof:name":"B.i. Beton-import Ag",
    "wof:placetype":"venue"
},
  "geometry": {"coordinates":[7.5866909027,47.5252456665],"type":"Point"}
}