{
  "type": "Feature",
  "properties": {
    "iso:country":"CH",
    "sg:address":"Grand-rue",
    "sg:city":"Semsales",
    "sg:orig_category":"Detailhandel mit Brot, Back U S\u00fcsswaren",
    "sg:phone":"+41 26 918 58 85",
    "sg:postcode":"1623",
    "sg:province":"Fribourg",
    "wof:name":"Boulangerie-p\u00e2tisserie Giroud Jean-pierre",
    "wof:placetype":"venue"
},
  "geometry": {"coordinates":[6.92523,46.570526],"type":"Point"}
}