{
  "type": "Feature",
  "properties": {
    "iso:country":"CH",
    "sg:address":"Rue Thurmann 16",
    "sg:city":"Porrentruy",
    "sg:orig_category":"Universit\u00e4tsspit\u00e4ler, Spit\u00e4ler f\u00fcr allgemeine Pflege",
    "sg:phone":"+41 32 466 41 48",
    "sg:postcode":"2900",
    "sg:province":"Jura",
    "wof:name":"Centre M\u00e9dico-psychologique",
    "wof:placetype":"venue"
},
  "geometry": {"coordinates":[7.0757069588,47.4132881165],"type":"Point"}
}