{
  "type": "Feature",
  "properties": {
    "iso:country":"CH",
    "sg:address":"Hauptstrasse 6 G",
    "sg:city":"K\u00fcblis",
    "sg:orig_category":"Naturheil\u00e4rzte and Heilpraktiker",
    "sg:phone":"+41 81 332 26 16",
    "sg:postcode":"7240",
    "sg:province":"Graubunden",
    "wof:name":"Theres & Roger Bertoli Praxis F\u00fcr Hom\u00f6opathie",
    "wof:placetype":"venue"
},
  "geometry": {"coordinates":[9.7779302597,46.9144554138],"type":"Point"}
}