{
  "type": "Feature",
  "properties": {
    "iso:country":"CH",
    "sg:address":"Bahnhofstrasse 22 7130 Ilanz. Postfach",
    "sg:city":"Ilanz",
    "sg:orig_category":"Versicherungen Hauptagenturen",
    "sg:phone":"+41 56 460 90 80",
    "sg:postcode":"7130",
    "sg:province":"Graubunden",
    "wof:name":"National-versicherung Hauptagentur",
    "wof:placetype":"venue"
},
  "geometry": {"coordinates":[8.2075366974,47.4811706543],"type":"Point"}
}