{
  "type": "Feature",
  "properties": {
    "iso:country":"CH",
    "sg:address":"Unionstrasse 17",
    "sg:city":"Goldach",
    "sg:orig_category":"Sonstiger Grosshandel",
    "sg:postcode":"9403",
    "sg:province":"St. Gallen",
    "wof:name":"Elemento Gbmh Einrichtungsgegenst\u00e4nde, Schmuck, Textilien Usw.; Handel, Verkauf",
    "wof:placetype":"venue"
},
  "geometry": {"coordinates":[9.381975174,47.4342041016],"type":"Point"}
}