{
  "type": "Feature",
  "properties": {
    "iso:country":"CH",
    "sg:address":"Letzigraben 89",
    "sg:city":"Z\u00fcrich",
    "sg:orig_category":"Unclassifiable Establishments",
    "sg:postcode":"8003",
    "sg:province":"Z\u00fcrich",
    "wof:name":"Zeus Wirtschaftsbeteiligungen Ag",
    "wof:placetype":"venue"
},
  "geometry": {"coordinates":[8.4993000031,47.3780212402],"type":"Point"}
}