{
  "type": "Feature",
  "properties": {
    "addr:full":"M\u00fcnsterplatz 1 6210 Sursee. Postfach 3217 Sursee Luzern 6210",
    "addr:housenumber":"1",
    "addr:postcode":"6210 sursee. postfach 3217;6210",
    "addr:street":"Muensterplatz",
    "iso:country":"CH",
    "sg:address":"M\u00fcnsterplatz 1 6210 Sursee. Postfach 3217",
    "sg:city":"Sursee",
    "sg:orig_category":"Architektur U Ingenieurb\u00fcros Architekturb\u00fcros",
    "sg:phone":"+41 41 921 75 06",
    "sg:postcode":"6210",
    "sg:province":"Luzern",
    "wof:name":"Wey Architekten Ag",
    "wof:placetype":"venue"
},
  "geometry": {"coordinates":[8.111614,47.17152],"type":"Point"}
}