{
  "type": "Feature",
  "properties": {
    "iso:country":"CH",
    "sg:address":"Chemin Frank-thomas 26ter",
    "sg:city":"Gen\u00e8ve",
    "sg:orig_category":"Offsetdruck",
    "sg:phone":"+41 31 333 04 41",
    "sg:postcode":"1208",
    "sg:province":"Gen\u00e8ve",
    "wof:name":"Rebora & Bigler Druck Offset-und Buchdruck",
    "wof:placetype":"venue"
},
  "geometry": {"coordinates":[7.4464302063,46.9563331604],"type":"Point"}
}