{
  "type": "Feature",
  "properties": {
    "iso:country":"CH",
    "sg:address":"Niederfeld 79",
    "sg:city":"Aristau",
    "sg:orig_category":"K\u00fcnstlerische U schriftstellerische T\u00e4tigkeiten U Darbietungen",
    "sg:phone":"+41 71 311 53 28",
    "sg:postcode":"5628",
    "sg:province":"Aargau",
    "wof:name":"Pro Arte Bulgarica Gmbh",
    "wof:placetype":"venue"
},
  "geometry": {"coordinates":[9.3200101852,47.4232597351],"type":"Point"}
}