{
  "type": "Feature",
  "properties": {
    "iso:country":"CH",
    "sg:address":"B\u00e4nackerstrasse 3",
    "sg:city":"Madiswil",
    "sg:orig_category":"Grosshandel mit Holz U Baustoffen",
    "sg:postcode":"4934",
    "sg:province":"Bern",
    "wof:name":"Fritz J\u00e4ggi",
    "wof:placetype":"venue"
},
  "geometry": {"coordinates":[7.5922760963,47.080532074],"type":"Point"}
}