{
  "type": "Feature",
  "properties": {
    "iso:country":"CH",
    "sg:address":"Sarganserstrasse 5",
    "sg:city":"Vilters",
    "sg:orig_category":"Herstellung von Automobilen",
    "sg:phone":"+41 81 353 30 31",
    "sg:postcode":"7324",
    "sg:province":"St. Gallen",
    "wof:name":"Riederer & S\u00f6hne Ag",
    "wof:placetype":"venue"
},
  "geometry": {"coordinates":[9.4485874176,47.0369148254],"type":"Point"}
}