{
  "type": "Feature",
  "properties": {
    "addr:full":"Lachen 751 Walzenhausen Appenzell Ausserrhoden 9428",
    "addr:housenumber":"751",
    "addr:postcode":"9428",
    "addr:street":"Lachen;Ausserrhoden",
    "iso:country":"CH",
    "sg:address":"Lachen 751",
    "sg:city":"Walzenhausen",
    "sg:classifiers":[
        {
            "category":"Utilities",
            "subcategory":"Natural Gas",
            "type":"Services"
        }
    ],
    "sg:phone":"+41 71 888 17 75",
    "sg:postcode":"9428",
    "sg:province":"Appenzell Ausserrhoden",
    "sg:tags":[
        "processing",
        "metal",
        "cnc"
    ],
    "wof:name":"Niwa Mechanik Franz Niederer",
    "wof:placetype":"venue"
},
  "geometry": {"coordinates":[9.58497,47.440891],"type":"Point"}
}