{
  "type": "Feature",
  "properties": {
    "iso:country":"CH",
    "sg:address":"R\u00fceggisingerstrasse 29 6020 Emmenbr\u00fccke. Postfach",
    "sg:city":"Emmenbr\u00fccke",
    "sg:orig_category":"Non-Classified Establishments",
    "sg:phone":"+41 41 269 01 11",
    "sg:postcode":"6020",
    "sg:province":"Luzern",
    "wof:name":"B. Braun Holding Ag",
    "wof:placetype":"venue"
},
  "geometry": {"coordinates":[8.27758,47.078587],"type":"Point"}
}