{
  "type": "Feature",
  "properties": {
    "iso:country":"CH",
    "sg:address":"Herrenweg 17",
    "sg:city":"N\u00e4fels",
    "sg:orig_category":"Verlegen von Fliesen U Platten",
    "sg:phone":"+41 33 335 84 75",
    "sg:postcode":"8752",
    "sg:province":"Glarus",
    "wof:name":"Roland Liechti Kerasil/plattenbel\u00e4ge",
    "wof:placetype":"venue"
},
  "geometry": {"coordinates":[7.6179537773,46.7313461304],"type":"Point"}
}