{
  "type": "Feature",
  "properties": {
    "addr:full":"Br\u00fchlstrasse 66 Arbon Thurgau 9320",
    "addr:housenumber":"66",
    "addr:postcode":"9320",
    "addr:street":"Bruehlstrasse",
    "iso:country":"CH",
    "sg:address":"Br\u00fchlstrasse 66",
    "sg:city":"Arbon",
    "sg:orig_category":"Advokaturb\u00fcros",
    "sg:phone":"+41 71 755 56 50",
    "sg:postcode":"9320",
    "sg:province":"Thurgau",
    "wof:name":"Stefan Thalhammer",
    "wof:placetype":"venue"
},
  "geometry": {"coordinates":[9.549698,47.375202],"type":"Point"}
}