{
  "type": "Feature",
  "properties": {
    "iso:country":"CH",
    "sg:address":"Tilleuls Chemin Des 10",
    "sg:city":"Orbe",
    "sg:orig_category":"Softwareentwicklung U beratung",
    "sg:postcode":"1350",
    "sg:province":"Vaud",
    "wof:name":"Ergosystem, Liaudat Martina",
    "wof:placetype":"venue"
},
  "geometry": {"coordinates":[6.5309619904,46.7247772217],"type":"Point"}
}