{
  "type": "Feature",
  "properties": {
    "addr:full":"M\u00e9di\u00e8res Verbier Valais 1936",
    "addr:postcode":"1936",
    "addr:street":"Me\u0301Die\u0300Res",
    "iso:country":"CH",
    "sg:address":"M\u00e9di\u00e8res",
    "sg:city":"Verbier",
    "sg:orig_category":"Betrieb von Taxis",
    "sg:phone":"+41 79 606 09 66",
    "sg:postcode":"1936",
    "sg:province":"Valais",
    "wof:name":"Aa - Coquoz Pierrette",
    "wof:placetype":"venue"
},
  "geometry": {"coordinates":[7.230458,46.094276],"type":"Point"}
}