{
  "type": "Feature",
  "properties": {
    "iso:country":"CH",
    "sg:address":"5236",
    "sg:city":"Remigen",
    "sg:orig_category":"Vereine Musik/Blasmusik",
    "sg:phone":"+41 56 441 48 17",
    "sg:postcode":"5236",
    "sg:province":"Aargau",
    "wof:name":"Musikgesellschaft",
    "wof:placetype":"venue"
},
  "geometry": {"coordinates":[8.1892366409,47.5150871277],"type":"Point"}
}