{
  "type": "Feature",
  "properties": {
    "iso:country":"CH",
    "sg:address":"Bahnhofstrasse 45 6210 Sursee. Postfach 3350",
    "sg:city":"Sursee",
    "sg:orig_category":"Grosshandel mit B\u00fcromaschinen Grosshandel mit Datenverarbeitungsger\u00e4ten",
    "sg:phone":"+41 41 926 80 80",
    "sg:postcode":"6210",
    "sg:province":"Luzern",
    "wof:name":"Mtf Sursee Ag",
    "wof:placetype":"venue"
},
  "geometry": {"coordinates":[8.0989093781,47.1710586548],"type":"Point"}
}