{
  "type": "Feature",
  "properties": {
    "iso:country":"CH",
    "sg:address":"Vignes Chemin Des 9 1213 Petit-lancy. Postfach",
    "sg:city":"Gen\u00e8ve",
    "sg:orig_category":"Architektur U Ingenieurb\u00fcros",
    "sg:postcode":"1207",
    "sg:province":"Gen\u00e8ve",
    "wof:name":"Honegger Sa, Atelier D'architecture Et D'urbanisme, Bureau D'ing\u00e9nieurs",
    "wof:placetype":"venue"
},
  "geometry": {"coordinates":[6.100106,46.183716],"type":"Point"}
}