{
  "type": "Feature",
  "properties": {
    "iso:country":"CH",
    "sg:address":"Cholplatzweg 22",
    "sg:city":"Trimmis",
    "sg:orig_category":"Verlegen von Fussboden",
    "sg:phone":"+41 81 353 59 79",
    "sg:postcode":"7203",
    "sg:province":"Graubunden",
    "wof:name":"Gebr\u00fcder Pitaro Gmbh Unterlagsb\u00f6den",
    "wof:placetype":"venue"
},
  "geometry": {"coordinates":[9.5551433563,46.902053833],"type":"Point"}
}