{
  "type": "Feature",
  "properties": {
    "iso:country":"CH",
    "sg:address":"Rue Du Chauchy 1",
    "sg:city":"Denens",
    "sg:orig_category":"Allgemeiner Gartenbau",
    "sg:phone":"+41 21 801 11 79",
    "sg:postcode":"1135",
    "sg:province":"Vaud",
    "wof:name":"Jean-paul Genoux Jardinier-arboriculteur",
    "wof:placetype":"venue"
},
  "geometry": {"coordinates":[6.456778,46.517773],"type":"Point"}
}