{
  "type": "Feature",
  "properties": {
    "iso:country":"CH",
    "sg:address":"Sarganserstrasse 9",
    "sg:city":"Mels",
    "sg:orig_category":"Detailhandel mit Schreib U Papeteriewaren",
    "sg:phone":"+41 81 723 52 40",
    "sg:postcode":"8887",
    "sg:province":"St. Gallen",
    "wof:name":"Drucki-papeterie Sarganserl\u00e4nder Druck Ag",
    "wof:placetype":"venue"
},
  "geometry": {"coordinates":[9.4223632812,47.0479736328],"type":"Point"}
}