{
  "type": "Feature",
  "properties": {
    "iso:country":"CH",
    "sg:address":"8564 Wagerswil. Postfach",
    "sg:city":"Wagerswil",
    "sg:orig_category":"Detailhandel mit Waren verschiedener Art, Hauptrichtung Nahrungsmittel",
    "sg:phone":"+41 71 657 14 20",
    "sg:postcode":"8564",
    "sg:province":"Thurgau",
    "wof:name":"Alfred Peter Lebensmittel",
    "wof:placetype":"venue"
},
  "geometry": {"coordinates":[9.0642147064,47.6091003418],"type":"Point"}
}