{
  "type": "Feature",
  "properties": {
    "iso:country":"CH",
    "sg:address":"Bogenackerstrasse 5",
    "sg:city":"Tann",
    "sg:orig_category":"Architektur U Ingenieurb\u00fcros Film U Videofilmherstellung",
    "sg:phone":"+41 55 260 16 85",
    "sg:postcode":"8632",
    "sg:province":"Z\u00fcrich",
    "wof:name":"La Sph\u00e8re Sa",
    "wof:placetype":"venue"
},
  "geometry": {"coordinates":[8.851247,47.266495],"type":"Point"}
}