{
  "type": "Feature",
  "properties": {
    "iso:country":"CH",
    "sg:address":"Sandackerstrasse 10",
    "sg:city":"Oberb\u00fcren",
    "sg:orig_category":"Grosshandel mit Baumaterialien Grosshandel mit Holz U Baustoffen",
    "sg:phone":"+41 71 950 08 55",
    "sg:postcode":"9245",
    "sg:province":"St. Gallen",
    "wof:name":"Fero Keller + Fraefel",
    "wof:placetype":"venue"
},
  "geometry": {"coordinates":[9.1573581696,47.4517593384],"type":"Point"}
}