{
  "type": "Feature",
  "properties": {
    "addr:full":"Promenadenstrasse 11a Frauenfeld Thurgau 8500",
    "addr:housenumber":"11a",
    "addr:postcode":"8500",
    "addr:street":"Promenadenstrasse",
    "iso:country":"CH",
    "sg:address":"Promenadenstrasse 11a",
    "sg:city":"Frauenfeld",
    "sg:orig_category":"Arztpraxen",
    "sg:phone":"+41 19133535",
    "sg:postcode":"8500",
    "sg:province":"Thurgau",
    "wof:name":"Dr.med. Brigitte Meli Spezial\u00e4rztin Fmh",
    "wof:placetype":"venue"
},
  "geometry": {"coordinates":[8.581762,47.318027],"type":"Point"}
}