{
  "type": "Feature",
  "properties": {
    "iso:country":"CH",
    "sg:address":"Chemin Plein-sud 6",
    "sg:city":"Th\u00f4nex",
    "sg:orig_category":"Geb\u00e4ude, Wohnungsreinigung Reinigungsgewerbe",
    "sg:phone":"+41 22 348 29 61",
    "sg:postcode":"1226",
    "sg:province":"Gen\u00e8ve",
    "wof:name":"Cacheiro & Cie Entreprise De Nettoyages",
    "wof:placetype":"venue"
},
  "geometry": {"coordinates":[6.219080925,46.2029953003],"type":"Point"}
}