{
  "type": "Feature",
  "properties": {
    "iso:country":"CH",
    "sg:address":"Hohlegasse 8",
    "sg:city":"Binningen",
    "sg:orig_category":"Vorschulen, Kinderg\u00e4rten",
    "sg:phone":"+41 61 421 41 34",
    "sg:postcode":"4102",
    "sg:province":"Basel-Landschaft",
    "wof:name":"Kindergarten",
    "wof:placetype":"venue"
},
  "geometry": {"coordinates":[7.5726008415,47.5414962769],"type":"Point"}
}