{
  "type": "Feature",
  "properties": {
    "iso:country":"CH",
    "sg:address":"Zugerstrasse 186",
    "sg:city":"Neu\u00e4geri",
    "sg:orig_category":"Non-Classified Establishments",
    "sg:postcode":"6314",
    "sg:province":"Zug",
    "wof:name":"B&h R\u00fcckbau Gmbh",
    "wof:placetype":"venue"
},
  "geometry": {"coordinates":[8.5631809235,47.1525535583],"type":"Point"}
}