{
  "type": "Feature",
  "properties": {
    "iso:country":"CH",
    "sg:address":"Seestrasse 67 8712 St\u00e4fa. Postfach 422",
    "sg:city":"St\u00e4fa",
    "sg:orig_category":"Herstellung von Mess U Kontrollinstrumenten U vorrichtungen",
    "sg:phone":"+41 19282141",
    "sg:postcode":"8712",
    "sg:province":"Z\u00fcrich",
    "wof:name":"Jumo Mess- & Regeltechnik Ag",
    "wof:placetype":"venue"
},
  "geometry": {"coordinates":[8.7200403214,47.2390708923],"type":"Point"}
}