{
  "type": "Feature",
  "properties": {
    "iso:country":"CH",
    "sg:address":"Avenue Pictet-de-rochemont 7",
    "sg:city":"Gen\u00e8ve",
    "sg:orig_category":"Interessenvertretungen Internationale Organisationen mit Beh\u00f6rdecharakter",
    "sg:phone":"+41 22 786 56 55",
    "sg:postcode":"1207",
    "sg:province":"Gen\u00e8ve",
    "wof:name":"Welfare Association",
    "wof:placetype":"venue"
},
  "geometry": {"coordinates":[6.1577029228,46.2023925781],"type":"Point"}
}