{
  "type": "Feature",
  "properties": {
    "iso:country":"CH",
    "sg:address":"Stettbachstrasse 37 8600 D\u00fcbendorf. Postfach",
    "sg:city":"D\u00fcbendorf",
    "sg:orig_category":"Grosshandel mit Nahrungsmitteln, Getr\u00e4nken U Tabakwaren Grosshandel mit sonstigen Nahrungsmitteln",
    "sg:phone":"+41 56 266 50 61",
    "sg:postcode":"8600",
    "sg:province":"Z\u00fcrich",
    "wof:name":"Schlumpf Karl Ag",
    "wof:placetype":"venue"
},
  "geometry": {"coordinates":[8.3162708282,47.5282592773],"type":"Point"}
}