{
  "type": "Feature",
  "properties": {
    "iso:country":"CH",
    "sg:address":"Versamerstrasse 8",
    "sg:city":"Bonaduz",
    "sg:orig_category":"Sonstige Kurierdienste",
    "sg:phone":"+41 81 641 11 97",
    "sg:postcode":"7402",
    "sg:province":"Graubunden",
    "wof:name":"Dpd Direct Parcel Distribution Ag",
    "wof:placetype":"venue"
},
  "geometry": {"coordinates":[9.399564743,46.8125038147],"type":"Point"}
}