{
  "type": "Feature",
  "properties": {
    "iso:country":"CH",
    "sg:address":"Laubstenstrasse 18d",
    "sg:city":"St\u00e4fa",
    "sg:orig_category":"Saunas, Solarien, Fitnesszentren U \u00e4hnliches",
    "sg:phone":"+41 21 944 30 45",
    "sg:postcode":"8712",
    "sg:province":"Z\u00fcrich",
    "wof:name":"Gymnastique Aquatique Riviera, Patricia Hungerb\u00fchler",
    "wof:placetype":"venue"
},
  "geometry": {"coordinates":[6.8625779152,46.4597740173],"type":"Point"}
}