{
  "type": "Feature",
  "properties": {
    "iso:country":"CH",
    "sg:address":"Hessstrasse 47",
    "sg:city":"Liebefeld",
    "sg:orig_category":"RESTAURANTS: TEA-ROOMS",
    "sg:phone":"+41 31 971 17 77",
    "sg:postcode":"3097",
    "sg:province":"Bern",
    "wof:name":"Restaurant Pony",
    "wof:placetype":"venue"
},
  "geometry": {"coordinates":[7.4276180267,46.9305114746],"type":"Point"}
}