{
  "type": "Feature",
  "properties": {
    "iso:country":"CH",
    "sg:address":"Dufour Rue G\u00e9n\u00e9ral- 107 2502 Biel/bienne. Postfach",
    "sg:city":"Biel/bienne",
    "sg:orig_category":"RESTAURANTS: TEA-ROOMS",
    "sg:postcode":"2502",
    "sg:province":"Bern",
    "wof:name":"Zimmermann Walter",
    "wof:placetype":"venue"
},
  "geometry": {"coordinates":[7.2548818588,47.1433448792],"type":"Point"}
}