{
  "type": "Feature",
  "properties": {
    "iso:country":"CH",
    "sg:address":"Brunnmattstrasse 39",
    "sg:city":"Solothurn",
    "sg:classifiers":[
        {
            "category":"Communications",
            "subcategory":"Film & Video Production",
            "type":"Services"
        }
    ],
    "sg:phone":"+41 32 622 61 74",
    "sg:postcode":"4500",
    "sg:province":"Solothurn",
    "sg:tags":[
        "videofilmherstellung",
        "u"
    ],
    "wof:name":"Brun.",
    "wof:placetype":"venue"
},
  "geometry": {"coordinates":[7.5190548897,47.2049751282],"type":"Point"}
}