{
  "type": "Feature",
  "properties": {
    "iso:country":"CH",
    "sg:address":"Chemin De Praz-devant 6",
    "sg:city":"Romanel-sur-lausanne",
    "sg:classifiers":[
        {
            "category":"Building & Trades",
            "subcategory":"Construction",
            "type":"Services"
        }
    ],
    "sg:phone":"+41 21 731 31 30",
    "sg:postcode":"1032",
    "sg:province":"Vaud",
    "sg:tags":[
        "ceiling"
    ],
    "wof:name":"Duvoisin Sa",
    "wof:placetype":"venue"
},
  "geometry": {"coordinates":[6.603152,46.569782],"type":"Point"}
}