{
  "type": "Feature",
  "properties": {
    "iso:country":"CH",
    "sg:address":"De-luserna Avenue 40 1203 Gen\u00e8ve. Postfach",
    "sg:city":"Gen\u00e8ve",
    "sg:orig_category":"Reiseb\u00fcros U Reiseveranstalter",
    "sg:postcode":"1204",
    "sg:province":"Gen\u00e8ve",
    "wof:name":"Discovery Travel S\u00e0rl",
    "wof:placetype":"venue"
},
  "geometry": {"coordinates":[6.1238760948,46.2141036987],"type":"Point"}
}