{
  "type": "Feature",
  "properties": {
    "iso:country":"CH",
    "sg:address":"Hauptstrasse 1",
    "sg:city":"Worben",
    "sg:orig_category":"Nationale Postdienste",
    "sg:phone":"+41 32 384 12 05",
    "sg:postcode":"3252",
    "sg:province":"Bern",
    "wof:name":"Die Schweizerische Post",
    "wof:placetype":"venue"
},
  "geometry": {"coordinates":[7.2949929237,47.1021232605],"type":"Point"}
}