{
  "type": "Feature",
  "properties": {
    "addr:full":"Kalkbreitestrasse 33 Z\u00fcrich Z\u00fcrich 8003",
    "addr:housenumber":"33",
    "addr:postcode":"8003",
    "addr:street":"Kalkbreitestrasse",
    "iso:country":"CH",
    "sg:address":"Kalkbreitestrasse 33",
    "sg:city":"Z\u00fcrich",
    "sg:orig_category":"Architektur U Ingenieurb\u00fcros Architekturb\u00fcros",
    "sg:phone":"+41 14516181",
    "sg:postcode":"8003",
    "sg:province":"Z\u00fcrich",
    "wof:name":"Joos & Mathys Dipl. Architekten Eth/sia",
    "wof:placetype":"venue"
},
  "geometry": {"coordinates":[8.519638,47.373478],"type":"Point"}
}