{
  "type": "Feature",
  "properties": {
    "iso:country":"CH",
    "sg:address":"Salen",
    "sg:city":"Jonschwil",
    "sg:orig_category":"Grosshandel mit sonstigen Halbwaren",
    "sg:phone":"+41 71 929 59 59",
    "sg:postcode":"9243",
    "sg:province":"St. Gallen",
    "wof:name":"Toppac Ag",
    "wof:placetype":"venue"
},
  "geometry": {"coordinates":[9.085729599,47.4239006042],"type":"Point"}
}