{
  "type": "Feature",
  "properties": {
    "iso:country":"CH",
    "sg:address":"Allmendstrasse 140",
    "sg:city":"Z\u00fcrich",
    "sg:orig_category":"Softwareentwicklung U beratung",
    "sg:phone":"+41 14882605",
    "sg:postcode":"8041",
    "sg:province":"Z\u00fcrich",
    "wof:name":"Inventis Ag Telekommunikationsprod. U. -systeme; Entw., Herst., Projektierung Usw",
    "wof:placetype":"venue"
},
  "geometry": {"coordinates":[8.518614769,47.3385238647],"type":"Point"}
}