{
  "type": "Feature",
  "properties": {
    "iso:country":"CH",
    "sg:address":"Soodstrasse 55 8134 Adliswil. Postfach",
    "sg:city":"Adliswil",
    "sg:orig_category":"Fernmeldedienste Grosshandel mit Datenverarbeitungsger\u00e4ten",
    "sg:phone":"+41 19085757",
    "sg:postcode":"8134",
    "sg:province":"Z\u00fcrich",
    "wof:name":"Icns Ag",
    "wof:placetype":"venue"
},
  "geometry": {"coordinates":[8.7979202271,47.3224182129],"type":"Point"}
}