{
  "type": "Feature",
  "properties": {
    "iso:country":"CH",
    "sg:address":"Via A. Giovannini 15",
    "sg:city":"Biasca",
    "sg:orig_category":"Tierarztpraxis",
    "sg:phone":"+41 91 862 22 22",
    "sg:postcode":"6710",
    "sg:province":"Ticino",
    "wof:name":"Dott. Med. Vet. Delio D'andrea Veterinario",
    "wof:placetype":"venue"
},
  "geometry": {"coordinates":[8.9720344543,46.3586730957],"type":"Point"}
}