{
  "type": "Feature",
  "properties": {
    "iso:country":"CH",
    "sg:address":"Untere Dattenbergstr. 12",
    "sg:city":"Kriens",
    "sg:orig_category":"Interessenvertretungen",
    "sg:postcode":"6010",
    "sg:province":"Luzern",
    "wof:name":"L\u00fctolf Karl Paul-stiftung",
    "wof:placetype":"venue"
},
  "geometry": {"coordinates":[8.290646553,47.0395622253],"type":"Point"}
}