{
  "type": "Feature",
  "properties": {
    "iso:country":"CH",
    "sg:address":"Hohgantweg 14 3012 Bern. Postfach",
    "sg:city":"Bern",
    "sg:orig_category":"Herstellung von konfektionierten Textilwaren ohne Bekleidung",
    "sg:postcode":"3005",
    "sg:province":"Bern",
    "wof:name":"Rolf Hug, Bettwaren Bettwaren, M\u00f6bel, Aussteuerw\u00e4sche U. Wohnbedarf; Handel.",
    "wof:placetype":"venue"
},
  "geometry": {"coordinates":[7.4273428917,46.9541969299],"type":"Point"}
}