{
  "type": "Feature",
  "properties": {
    "iso:country":"CH",
    "sg:address":"St. Alban-rheinweg 52",
    "sg:city":"Basel",
    "sg:orig_category":"Herstellung von sonstigen M\u00f6beln",
    "sg:phone":"+41 61 272 27 10",
    "sg:postcode":"4052",
    "sg:province":"Basel-Stadt",
    "wof:name":"Frontstore Walther Stumpf Ruth",
    "wof:placetype":"venue"
},
  "geometry": {"coordinates":[7.6010608673,47.5547828674],"type":"Point"}
}