{
  "type": "Feature",
  "properties": {
    "iso:country":"CH",
    "sg:address":"Schmiedgasse 70",
    "sg:city":"Erstfeld",
    "sg:orig_category":"Advokaturb\u00fcros Notariate",
    "sg:phone":"+41 41 880 29 32",
    "sg:postcode":"6472",
    "sg:province":"Uri",
    "wof:name":"Walter A. St\u00f6ckli Advokatur-& Notariatsb\u00fcro",
    "wof:placetype":"venue"
},
  "geometry": {"coordinates":[8.652065,46.821133],"type":"Point"}
}