{
  "type": "Feature",
  "properties": {
    "iso:country":"CH",
    "sg:address":"Rue De La Synagogue 40",
    "sg:city":"Gen\u00e8ve",
    "sg:orig_category":"Vermietung U Verpachtung von eigenen Immobilien Vermittlung von Immobilien",
    "sg:phone":"+41 22 321 29 55",
    "sg:postcode":"1204",
    "sg:province":"Gen\u00e8ve",
    "wof:name":"Ccs & G. Compagnie Commerciale Services Et Gestion Sa",
    "wof:placetype":"venue"
},
  "geometry": {"coordinates":[6.1397461891,46.2025871277],"type":"Point"}
}