{
  "type": "Feature",
  "properties": {
    "iso:country":"CH",
    "sg:address":"K\u00e4ferholzstr. 256b",
    "sg:city":"Z\u00fcrich",
    "sg:orig_category":"Medizin, Pharmaprodukte",
    "sg:phone":"+41 4113719393",
    "sg:postcode":"8056",
    "wof:name":"Natour Gmbh",
    "wof:placetype":"venue"
},
  "geometry": {"coordinates":[8.523963,47.411072],"type":"Point"}
}