{
  "type": "Feature",
  "properties": {
    "iso:country":"CH",
    "sg:address":"H\u00f6henweg 34",
    "sg:city":"Pratteln",
    "sg:orig_category":"Unternehmensberatung",
    "sg:phone":"+41 61 823 01 00",
    "sg:postcode":"4133",
    "sg:province":"Basel-Landschaft",
    "wof:name":"Dr. Peter Wolf Management Support",
    "wof:placetype":"venue"
},
  "geometry": {"coordinates":[7.6972651482,47.5154876709],"type":"Point"}
}