{
  "type": "Feature",
  "properties": {
    "iso:country":"CH",
    "sg:address":"L\u00f6wenbergstrasse 38 4059 Basel. Postfach",
    "sg:city":"Basel",
    "sg:orig_category":"Markt U Meinungsforschung",
    "sg:phone":"+41 61 333 82 42",
    "sg:postcode":"4059",
    "sg:province":"Basel-Stadt",
    "wof:name":"Jaleel Consulting Gmbh Beratungsunternehmen F\u00fcr Marketing U. Public Relations, Bes. F\u00fcr Die Pharmazeutische Industrie Usw",
    "wof:placetype":"venue"
},
  "geometry": {"coordinates":[7.5966291428,47.5355911255],"type":"Point"}
}