{
  "type": "Feature",
  "properties": {
    "iso:country":"CH",
    "sg:address":"Dorfplatz",
    "sg:city":"Oppligen",
    "sg:orig_category":"Gewinnung von Kies U Sand",
    "sg:phone":"+41 31 780 22 20",
    "sg:postcode":"3629",
    "sg:province":"Bern",
    "wof:name":"Kieswerk Daepp Ag",
    "wof:placetype":"venue"
},
  "geometry": {"coordinates":[7.5948700905,46.8196563721],"type":"Point"}
}