{
  "type": "Feature",
  "properties": {
    "iso:country":"CH",
    "sg:address":"Untergasse 17",
    "sg:city":"Elgg",
    "sg:orig_category":"Sanit\u00e4r U Heizungsinstallation Sanit\u00e4rinstallation",
    "sg:phone":"+41 17805726",
    "sg:postcode":"8353",
    "sg:province":"Z\u00fcrich",
    "wof:name":"Max Schrott Heizungen & Sanit\u00e4re Anlagen",
    "wof:placetype":"venue"
},
  "geometry": {"coordinates":[8.6565551758,47.2380218506],"type":"Point"}
}