{
  "type": "Feature",
  "properties": {
    "iso:country":"CH",
    "sg:address":"Spalenring 40",
    "sg:city":"Basel",
    "sg:orig_category":"Unclassifiable Establishments",
    "sg:postcode":"4055",
    "sg:province":"Basel-Stadt",
    "wof:name":"Grafik-kiosk Gossweiler M\u00fcller + M\u00fcller",
    "wof:placetype":"venue"
},
  "geometry": {"coordinates":[8.5994195938,47.3291091919],"type":"Point"}
}