{
  "type": "Feature",
  "properties": {
    "iso:country":"CH",
    "sg:address":"Cantonale Via 51",
    "sg:city":"Magliaso",
    "sg:orig_category":"Instandhaltung U Reparatur von Automobilen",
    "sg:phone":"+41 79 216 89 74",
    "sg:postcode":"6983",
    "sg:province":"Ticino",
    "wof:name":"Demierre J. Marc",
    "wof:placetype":"venue"
},
  "geometry": {"coordinates":[7.0688948631,46.7700080872],"type":"Point"}
}