{
  "type": "Feature",
  "properties": {
    "iso:country":"CH",
    "sg:address":"Susenbergstrasse 208",
    "sg:city":"Z\u00fcrich",
    "sg:orig_category":"Unclassifiable Establishments",
    "sg:postcode":"8044",
    "sg:province":"Z\u00fcrich",
    "wof:name":"Alpag Ag",
    "wof:placetype":"venue"
},
  "geometry": {"coordinates":[8.8584098816,47.1940803528],"type":"Point"}
}