{
  "type": "Feature",
  "properties": {
    "iso:country":"CH",
    "sg:address":"Eymattweg 11",
    "sg:city":"Grossh\u00f6chstetten",
    "sg:orig_category":"Instandhaltung U Reparatur von Automobilen",
    "sg:postcode":"3506",
    "sg:province":"Bern",
    "wof:name":"Carrosserie-autospritzwerk Zehnder, Grossh\u00f6chstetten",
    "wof:placetype":"venue"
},
  "geometry": {"coordinates":[7.6349282265,46.8990936279],"type":"Point"}
}