{
  "type": "Feature",
  "properties": {
    "iso:country":"CH",
    "sg:address":"Route De La Bl\u00e9cherette 97",
    "sg:city":"Mont-sur-lausanne",
    "sg:orig_category":"Tankstellen",
    "sg:phone":"+41 22 771 12 14",
    "sg:postcode":"1052",
    "sg:province":"Vaud",
    "wof:name":"Antonio Cela Garage & Tamoil Station",
    "wof:placetype":"venue"
},
  "geometry": {"coordinates":[6.1271791458,46.1632080078],"type":"Point"}
}