{
  "type": "Feature",
  "properties": {
    "iso:country":"CH",
    "sg:address":"Neufeldstrasse 120",
    "sg:city":"Bern",
    "sg:orig_category":"Vereine Gesang Vereine Gesang and Jodler",
    "sg:phone":"+41 31 301 71 49",
    "sg:postcode":"3012",
    "sg:province":"Bern",
    "wof:name":"Jodler-doppelquart.worblaufen",
    "wof:placetype":"venue"
},
  "geometry": {"coordinates":[7.4342598915,46.9579696655],"type":"Point"}
}