{
  "type": "Feature",
  "properties": {
    "iso:country":"CH",
    "sg:address":"Aarbergergasse 16 3000 Bern. Postfach",
    "sg:city":"Bern",
    "sg:orig_category":"Mineral\u00f6lverarbeitung",
    "sg:phone":"+41 21 960 26 83",
    "sg:postcode":"3000",
    "sg:province":"Bern",
    "wof:name":"Lauer Friedbert",
    "wof:placetype":"venue"
},
  "geometry": {"coordinates":[6.9261350632,46.39818573],"type":"Point"}
}