{
  "type": "Feature",
  "properties": {
    "iso:country":"CH",
    "sg:address":"Staatsstrasse 75",
    "sg:city":"Grabs",
    "sg:orig_category":"B\u00e4ckereien Konditoreien",
    "sg:phone":"+41 81 771 40 36",
    "sg:postcode":"9472",
    "sg:province":"St. Gallen",
    "wof:name":"Reinhold Zwahlen B\u00e4ckerei-konditorei Filiale Feld",
    "wof:placetype":"venue"
},
  "geometry": {"coordinates":[9.442943,47.184055],"type":"Point"}
}