{
  "type": "Feature",
  "properties": {
    "iso:country":"CH",
    "sg:address":"Bleicherweg 19 8002 Z\u00fcrich. Postfach",
    "sg:city":"Z\u00fcrich",
    "sg:orig_category":"Finanzierungsinstitutionen",
    "sg:phone":"+41 12095111",
    "sg:postcode":"8002",
    "sg:province":"Z\u00fcrich",
    "wof:name":"Allianz Suisse Personal Financial Services Ag",
    "wof:placetype":"venue"
},
  "geometry": {"coordinates":[8.5361948013,47.3679771423],"type":"Point"}
}