{
  "type": "Feature",
  "properties": {
    "iso:country":"CH",
    "sg:address":"Bernstrasse 36",
    "sg:city":"Herrenschwanden",
    "sg:orig_category":"Instandhaltung U Reparatur von Automobilen",
    "sg:phone":"+41 55 282 55 44",
    "sg:postcode":"3037",
    "sg:province":"Bern",
    "wof:name":"Kuster & Schwegler Fahrzeuge Gmbh",
    "wof:placetype":"venue"
},
  "geometry": {"coordinates":[8.9331493378,47.2406921387],"type":"Point"}
}