{
  "type": "Feature",
  "properties": {
    "iso:country":"CH",
    "sg:address":"Dorfstrasse 69",
    "sg:city":"Leissigen",
    "sg:orig_category":"Detailhandel mit M\u00f6beln",
    "sg:phone":"+41 33 847 14 44",
    "sg:postcode":"3706",
    "sg:province":"Bern",
    "wof:name":"St\u00fcris Naturhus Sonja & Daniel Steuri",
    "wof:placetype":"venue"
},
  "geometry": {"coordinates":[7.7689590454,46.6545257568],"type":"Point"}
}