{
  "type": "Feature",
  "properties": {
    "addr:full":"Hardhofstrasse 15 Embrach Z\u00fcrich 8424",
    "addr:housenumber":"15",
    "addr:postcode":"8424",
    "addr:street":"Hardhofstrasse",
    "iso:country":"CH",
    "sg:address":"Hardhofstrasse 15",
    "sg:city":"Embrach",
    "sg:classifiers":[
        {
            "category":"Personal",
            "subcategory":"Shoe Repair & Shine",
            "type":"Services"
        }
    ],
    "sg:phone":"+41 18662090",
    "sg:postcode":"8424",
    "sg:province":"Z\u00fcrich",
    "sg:tags":[
        "filter",
        "belt"
    ],
    "wof:name":"Pitrag Technology Ltd.",
    "wof:placetype":"venue"
},
  "geometry": {"coordinates":[8.595051,47.51812],"type":"Point"}
}