{
  "type": "Feature",
  "properties": {
    "iso:country":"CH",
    "sg:address":"Via Lisano 3",
    "sg:city":"Massagno",
    "sg:orig_category":"Finanzierungsinstitutionen",
    "sg:postcode":"6900",
    "sg:province":"Ticino",
    "wof:name":"Obol Investment International Ltd, Tortola, Succursale Di Massagno",
    "wof:placetype":"venue"
},
  "geometry": {"coordinates":[8.9428453445,46.0092735291],"type":"Point"}
}