{
  "type": "Feature",
  "properties": {
    "iso:country":"CH",
    "sg:address":"Rue Pierre-alex 22",
    "sg:city":"Bulle",
    "sg:orig_category":"Detailhandel Einzelhandel mit Automobilteilen U Zubeh\u00f6r Reparatur von Gebrauchsg\u00fctern",
    "sg:phone":"+41 26 912 34 47",
    "sg:postcode":"1630",
    "sg:province":"Fribourg",
    "wof:name":"Croce Sebastiani Auto-accessoires",
    "wof:placetype":"venue"
},
  "geometry": {"coordinates":[7.0607872009,46.6239356995],"type":"Point"}
}