{
  "type": "Feature",
  "properties": {
    "iso:country":"CH",
    "sg:address":"Zelglistrasse 26",
    "sg:city":"Aarau",
    "sg:classifiers":[
        {
            "category":"Social Services",
            "subcategory":"Retirement Home",
            "type":"Services"
        }
    ],
    "sg:phone":"+41 62 822 37 28",
    "sg:postcode":"5000",
    "sg:province":"Aargau",
    "sg:tags":[
        "pflegeheime",
        "u",
        "alters"
    ],
    "wof:name":"Altersheim Zelgli",
    "wof:placetype":"venue"
},
  "geometry": {"coordinates":[8.045843,47.385929],"type":"Point"}
}