{
  "type": "Feature",
  "properties": {
    "iso:country":"CH",
    "sg:address":"Oberer Scheunenweg 28",
    "sg:city":"Lenzburg",
    "sg:orig_category":"Sanit\u00e4rinstallation U Spenglerei Zimmerei, Dachdeckerei, Bauspenglerei U Abdichtung",
    "sg:phone":"+41 62 888 13 88",
    "sg:postcode":"5600",
    "sg:province":"Aargau",
    "wof:name":"Widmer R. Ag Lenzburg",
    "wof:placetype":"venue"
},
  "geometry": {"coordinates":[8.1806535721,47.3867607117],"type":"Point"}
}