{
  "type": "Feature",
  "properties": {
    "iso:country":"CH",
    "sg:address":"8352 R\u00e4terschen. Postfach 134",
    "sg:city":"R\u00e4terschen",
    "sg:orig_category":"Sonderschulen Wohnheime f\u00fcr Kinder U Jugendliche",
    "sg:phone":"+41 52 363 11 24",
    "sg:postcode":"8352",
    "sg:province":"Z\u00fcrich",
    "wof:name":"Pestalozzihaus",
    "wof:placetype":"venue"
},
  "geometry": {"coordinates":[8.7931995392,47.4988098145],"type":"Point"}
}