{
  "type": "Feature",
  "properties": {
    "iso:country":"CH",
    "sg:address":"Sandackerstrasse 30",
    "sg:city":"Oberb\u00fcren",
    "sg:orig_category":"Detailhandel mit elektrischen Haushalts-,Radio U Fernsehger\u00e4ten sowie Musikinstrumenten Grosshandel ",
    "sg:phone":"+41 71 923 56 23",
    "sg:postcode":"9245",
    "sg:province":"St. Gallen",
    "wof:name":"Kirby Gebietsh\u00e4ndler, Nef Walter",
    "wof:placetype":"venue"
},
  "geometry": {"coordinates":[9.1559419632,47.4488067627],"type":"Point"}
}