{
  "type": "Feature",
  "properties": {
    "iso:country":"CH",
    "sg:address":"A\u00e9roport Route De L' 1 1217 Meyrin Case Postale 273",
    "sg:city":"Meyrin",
    "sg:orig_category":"Sonstiger Grosshandel",
    "sg:phone":"+41 22 920 12 12",
    "sg:postcode":"1217",
    "sg:province":"Gen\u00e8ve",
    "wof:name":"Expat Services R S\u00e0rl",
    "wof:placetype":"venue"
},
  "geometry": {"coordinates":[6.0722098351,46.2284393311],"type":"Point"}
}