{
  "type": "Feature",
  "properties": {
    "iso:country":"CH",
    "sg:address":"Seewjinenstrasse 2",
    "sg:city":"Visp",
    "sg:orig_category":"Herstellung von Ger\u00e4ten der Elektrizit\u00e4tserzeugung, -verteilung u.\u00e4. -Herstellung von Elektrizit\u00e4tsv",
    "sg:phone":"+41 27 946 80 18",
    "sg:postcode":"3930",
    "sg:province":"Valais",
    "wof:name":"Sysmatec, Yax Patrick",
    "wof:placetype":"venue"
},
  "geometry": {"coordinates":[7.8876409531,46.2923202515],"type":"Point"}
}