{
  "type": "Feature",
  "properties": {
    "iso:country":"CH",
    "sg:address":"Abtwilerstrasse 1",
    "sg:city":"Oberr\u00fcti",
    "sg:orig_category":"Detailhandel mit Milcherzeugnissen U Eiern Verarbeitung von Milch",
    "sg:phone":"+41 41 787 12 77",
    "sg:postcode":"5647",
    "sg:province":"Aargau",
    "wof:name":"Daniel Feller K\u00e4serei",
    "wof:placetype":"venue"
},
  "geometry": {"coordinates":[8.3925428391,47.1660881042],"type":"Point"}
}