{
  "type": "Feature",
  "properties": {
    "iso:country":"CH",
    "sg:address":"Avenue De La Gare 34",
    "sg:city":"Del\u00e9mont",
    "sg:orig_category":"Detailhandel mit Geschenkartikeln U Souvenirs",
    "sg:phone":"+41 32 422 61 43",
    "sg:postcode":"2800",
    "sg:province":"Jura",
    "wof:name":"Rosalie Guerra Boutique Rosalie",
    "wof:placetype":"venue"
},
  "geometry": {"coordinates":[7.3490672112,47.364364624],"type":"Point"}
}