{
  "type": "Feature",
  "properties": {
    "iso:country":"CH",
    "sg:address":"Fischmarkt 9",
    "sg:city":"Zug",
    "sg:orig_category":"Softwareentwicklung U beratung",
    "sg:phone":"+41 41 712 14 45",
    "sg:postcode":"6300",
    "sg:province":"Zug",
    "wof:name":"Rusch System Engineering Rse",
    "wof:placetype":"venue"
},
  "geometry": {"coordinates":[8.5146770477,47.1663246155],"type":"Point"}
}