{
  "type": "Feature",
  "properties": {
    "iso:country":"CH",
    "sg:address":"Lampenbergerstrasse 20a",
    "sg:city":"Niederdorf",
    "sg:orig_category":"Grosshandel mit B\u00fcromaschinen Grosshandel mit Datenverarbeitungsger\u00e4ten",
    "sg:phone":"+41 17822700",
    "sg:postcode":"4435",
    "sg:province":"Basel-Landschaft",
    "wof:name":"Secom Ag",
    "wof:placetype":"venue"
},
  "geometry": {"coordinates":[8.6413679123,47.2402915955],"type":"Point"}
}