{
  "type": "Feature",
  "properties": {
    "iso:country":"CH",
    "sg:address":"Eichstrasse 12",
    "sg:city":"Z\u00fcrich",
    "sg:orig_category":"Herstellung von k\u00e4lte U lufttechnischen Erzeugnissen f\u00fcr gewerbliche Zwecke Installation von Heizung",
    "sg:phone":"+41 14617111",
    "sg:postcode":"8045",
    "sg:province":"Z\u00fcrich",
    "wof:name":"Honegger & K\u00e4lin Ag",
    "wof:placetype":"venue"
},
  "geometry": {"coordinates":[8.5211858749,47.3629112244],"type":"Point"}
}