{
  "type": "Feature",
  "properties": {
    "iso:country":"CH",
    "sg:address":"Via Sottochiesa",
    "sg:city":"Rancate",
    "sg:orig_category":"Unclassifiable Establishments",
    "sg:postcode":"6862",
    "sg:province":"Ticino",
    "wof:name":"Caldelari Flavio",
    "wof:placetype":"venue"
},
  "geometry": {"coordinates":[8.9681348801,45.8714981079],"type":"Point"}
}