{
  "type": "Feature",
  "properties": {
    "iso:country":"CH",
    "sg:address":"Hauptstrasse 95",
    "sg:city":"Nidau",
    "sg:orig_category":"Architektur U Ingenieurb\u00fcros",
    "sg:phone":"+41 32 365 84 68",
    "sg:postcode":"2560",
    "sg:province":"Bern",
    "wof:name":"Rudolf Forster Ag",
    "wof:placetype":"venue"
},
  "geometry": {"coordinates":[7.242104,47.120186],"type":"Point"}
}