{
  "type": "Feature",
  "properties": {
    "iso:country":"CH",
    "sg:address":"Zw\u00e4ngiweg 21",
    "sg:city":"Z\u00fcrich",
    "sg:orig_category":"Herstellung von Spielwaren",
    "sg:postcode":"8038",
    "sg:province":"Z\u00fcrich",
    "wof:name":"Gotschan Mengis + Co Japanische Modellflugzeuge, -hubschrauber, -schiffe, -autos, Fernsteuerungen; Imp., Wiederverkauf, Reparaturen",
    "wof:placetype":"venue"
},
  "geometry": {"coordinates":[8.5339584351,47.330291748],"type":"Point"}
}