{
  "type": "Feature",
  "properties": {
    "iso:country":"CH",
    "sg:address":"1412",
    "sg:city":"Valeyres-ursins",
    "sg:orig_category":"Verwertung von Milch",
    "sg:postcode":"1412",
    "sg:province":"Vaud",
    "wof:name":"Soci\u00e9t\u00e9 De Laiterie De Valeyres-sous-ursins.",
    "wof:placetype":"venue"
},
  "geometry": {"coordinates":[6.6561899185,46.7472610474],"type":"Point"}
}