{
  "type": "Feature",
  "properties": {
    "iso:country":"CH",
    "sg:address":"Leonhardsgraben 8 4051 Basel. Postfach",
    "sg:city":"Basel",
    "sg:orig_category":"Unclassifiable Establishments",
    "sg:postcode":"4051",
    "sg:province":"Basel-Stadt",
    "wof:name":"Krea Invest Ag Beteiligungen Usw",
    "wof:placetype":"venue"
},
  "geometry": {"coordinates":[7.584031105,47.5565338135],"type":"Point"}
}