{
  "type": "Feature",
  "properties": {
    "iso:country":"CH",
    "sg:address":"Ettenb\u00fchlstr. 1 8400 Winterthur. Postfach",
    "sg:city":"Elgg",
    "sg:orig_category":"RESTAURANTS: TEA-ROOMS",
    "sg:phone":"+41 22 756 26 70",
    "sg:postcode":"8353",
    "sg:province":"Z\u00fcrich",
    "wof:name":"Casanova Yves",
    "wof:placetype":"venue"
},
  "geometry": {"coordinates":[6.0021800995,46.1544151306],"type":"Point"}
}