{
  "type": "Feature",
  "properties": {
    "iso:country":"CH",
    "sg:address":"Riedstrasse 7-9",
    "sg:city":"Cham",
    "sg:orig_category":"Detailhandel mit Parf\u00fcmerieartikeln U K\u00f6rperpflegemitteln",
    "sg:phone":"+41 41 741 70 60",
    "sg:postcode":"6330",
    "sg:province":"Zug",
    "wof:name":"The World Trade Perfume Sa",
    "wof:placetype":"venue"
},
  "geometry": {"coordinates":[8.4766769409,47.1891326904],"type":"Point"}
}