{
  "type": "Feature",
  "properties": {
    "iso:country":"CH",
    "sg:address":"Via Borromini 11 6943 Vezia. Postfach",
    "sg:city":"Mezzovico",
    "sg:orig_category":"Herstellung von Mess U Kontrollinstrumenten U vorrichtungen",
    "sg:postcode":"6805",
    "sg:province":"Ticino",
    "wof:name":"Roltec Sa",
    "wof:placetype":"venue"
},
  "geometry": {"coordinates":[8.9354686737,46.0196380615],"type":"Point"}
}