{
  "type": "Feature",
  "properties": {
    "iso:country":"CH",
    "sg:address":"Dorfplatz 6",
    "sg:city":"Stans",
    "sg:orig_category":"Physiotherapie",
    "sg:phone":"+41 41 610 50 64",
    "sg:postcode":"6370",
    "sg:province":"Nidwalden",
    "wof:name":"Ergotherapie-zentrum Schweiz.rotes Kreuz",
    "wof:placetype":"venue"
},
  "geometry": {"coordinates":[8.366109848,46.9570732117],"type":"Point"}
}