{
  "type": "Feature",
  "properties": {
    "iso:country":"CH",
    "sg:address":"Schulhausgasse 4 3860 Meiringen. Postfach 274",
    "sg:city":"Meiringen",
    "sg:orig_category":"Elektroinstallation",
    "sg:phone":"+41 79 403 17 17",
    "sg:postcode":"3860",
    "sg:province":"Bern",
    "wof:name":"Christen",
    "wof:placetype":"venue"
},
  "geometry": {"coordinates":[8.2172670364,47.4656524658],"type":"Point"}
}