{
  "type": "Feature",
  "properties": {
    "iso:country":"CH",
    "sg:address":"Passwangstrasse 35 4226 Breitenbach. Postfach",
    "sg:city":"Breitenbach",
    "sg:orig_category":"Herstellung von Kunststoffwaren",
    "sg:phone":"+41 34 461 49 24",
    "sg:postcode":"4226",
    "sg:province":"Solothurn",
    "wof:name":"Brunner H.",
    "wof:placetype":"venue"
},
  "geometry": {"coordinates":[7.6849250793,47.0063858032],"type":"Point"}
}