{
  "type": "Feature",
  "properties": {
    "iso:country":"CH",
    "sg:address":"Centralstrasse 27 3800 Interlaken. Postfach 553",
    "sg:city":"Interlaken",
    "sg:orig_category":"Detailhandel mit Schreib U Papeteriewaren Sonstiger Detailhandel mit Metallwaren, Anstrichmitteln, G",
    "sg:phone":"+41 33 822 32 36",
    "sg:postcode":"3800",
    "sg:province":"Bern",
    "wof:name":"Bhend Papeterie B\u00fcrobed & Co",
    "wof:placetype":"venue"
},
  "geometry": {"coordinates":[7.8549799919,46.6846618652],"type":"Point"}
}