{
  "type": "Feature",
  "properties": {
    "iso:country":"CH",
    "sg:address":"Industriestrasse 6",
    "sg:city":"Bischofszell",
    "sg:orig_category":"Grosshandel mit Getr\u00e4nken",
    "sg:phone":"+41 71 424 77 40",
    "sg:postcode":"9220",
    "sg:province":"Thurgau",
    "wof:name":"Cave Amann Sa",
    "wof:placetype":"venue"
},
  "geometry": {"coordinates":[9.2360486984,47.5013275146],"type":"Point"}
}