{
  "type": "Feature",
  "properties": {
    "iso:country":"CH",
    "sg:address":"Industrie Rue De L' 19",
    "sg:city":"Fleurier",
    "sg:orig_category":"Instandhaltung U Reparatur von Automobilen",
    "sg:postcode":"2114",
    "sg:province":"Neuch\u00e2tel",
    "wof:name":"Garages Hotz Sa",
    "wof:placetype":"venue"
},
  "geometry": {"coordinates":[6.57670784,46.8983078003],"type":"Point"}
}