{
  "type": "Feature",
  "properties": {
    "iso:country":"CH",
    "sg:address":"Rue De Gottefrey 20",
    "sg:city":"Mayens-de-saxon",
    "sg:orig_category":"Elektro- and elektronische Maschinen Grosshandel",
    "sg:phone":"+41 27 744 61 65",
    "sg:postcode":"1907",
    "sg:province":"Valais",
    "wof:name":"Algonet S\u00e0rl Cr\u00e9ation & Conception",
    "wof:placetype":"venue"
},
  "geometry": {"coordinates":[7.1747708321,46.1495895386],"type":"Point"}
}