{
  "type": "Feature",
  "properties": {
    "iso:country":"CH",
    "sg:address":"Falkenstrasse 2 8600 D\u00fcbendorf. Postfach",
    "sg:city":"D\u00fcbendorf",
    "sg:orig_category":"Vermietung U Verpachtung von eigenen Immobilien",
    "sg:phone":"+41 18220949",
    "sg:postcode":"8600",
    "sg:province":"Z\u00fcrich",
    "wof:name":"Tr\u00fcb Hans-j\u00f6rg Immobilien Immobilien Usw",
    "wof:placetype":"venue"
},
  "geometry": {"coordinates":[8.6281795502,47.392616272],"type":"Point"}
}