{
  "type": "Feature",
  "properties": {
    "addr:full":"3965 Chippis Valais 3965",
    "addr:postcode":"3965;3965",
    "iso:country":"CH",
    "sg:address":"3965",
    "sg:city":"Chippis",
    "sg:orig_category":"Detailhandel mit B\u00fcchern, Zeitungen, Schreib U Papeteriewaren",
    "sg:postcode":"3965",
    "sg:province":"Valais",
    "wof:name":"Ramseier Judith Et Rose-marie",
    "wof:placetype":"venue"
},
  "geometry": {"coordinates":[7.54196,46.274269],"type":"Point"}
}