{
  "type": "Feature",
  "properties": {
    "iso:country":"CH",
    "sg:address":"Bossi Via 9",
    "sg:city":"Lugano",
    "sg:orig_category":"Interessenvertretungen",
    "sg:postcode":"6900",
    "sg:province":"Ticino",
    "wof:name":"Fondazione Svizzera Madagascar (f.s.m.)",
    "wof:placetype":"venue"
},
  "geometry": {"coordinates":[8.9543409348,46.0070457458],"type":"Point"}
}