{
  "type": "Feature",
  "properties": {
    "iso:country":"CH",
    "sg:address":"Villa Les Bosquets Fontanivent",
    "sg:city":"Brent",
    "sg:orig_category":"Universit\u00e4ten, Hochschulen",
    "sg:phone":"+41 21 964 84 64",
    "sg:postcode":"1817",
    "sg:province":"Vaud",
    "wof:name":"European University",
    "wof:placetype":"venue"
},
  "geometry": {"coordinates":[6.9011001587,46.4577255249],"type":"Point"}
}