{
  "type": "Feature",
  "properties": {
    "iso:country":"CH",
    "sg:address":"Romegg 5",
    "sg:city":"Gipf-oberfrick",
    "sg:classifiers":[
        {
            "category":"Insurance",
            "subcategory":"Insurance Agent",
            "type":"Services"
        }
    ],
    "sg:phone":"+41 62 871 62 41",
    "sg:postcode":"5073",
    "sg:province":"Aargau",
    "sg:tags":[
        "versicherungsagenturen",
        "-broker"
    ],
    "wof:name":"Werner Reding Agentur W'thur-leben",
    "wof:placetype":"venue"
},
  "geometry": {"coordinates":[8.0031232834,47.5021247864],"type":"Point"}
}