{
  "type": "Feature",
  "properties": {
    "iso:country":"CH",
    "sg:address":"Neudorfstrasse. 9444 Diepoldsau. Postfach 258",
    "sg:city":"Diepoldsau",
    "sg:orig_category":"Grosshandel mit Holz U Baustoffen Hoch U Tiefbau",
    "sg:phone":"+41 71 733 11 46",
    "sg:postcode":"9444",
    "sg:province":"St. Gallen",
    "wof:name":"Lehner-frei B. Ag.",
    "wof:placetype":"venue"
},
  "geometry": {"coordinates":[9.6514501572,47.3826599121],"type":"Point"}
}