{
  "type": "Feature",
  "properties": {
    "iso:country":"CH",
    "sg:address":"Rue Du Poyet 3",
    "sg:city":"Moudon",
    "sg:orig_category":"Interessenvertretungen",
    "sg:postcode":"1510",
    "sg:province":"Vaud",
    "wof:name":"Fondation Du Poyet",
    "wof:placetype":"venue"
},
  "geometry": {"coordinates":[6.7987580299,46.6690368652],"type":"Point"}
}