{
  "type": "Feature",
  "properties": {
    "iso:country":"CH",
    "sg:address":"Haldenstrasse 23",
    "sg:city":"M\u00e4nnedorf",
    "sg:orig_category":"D\u00e4mmung gegen K\u00e4lte, W\u00e4rme, Schall U Ersch\u00fctterung",
    "sg:postcode":"8708",
    "sg:province":"Z\u00fcrich",
    "wof:name":"Robitec Di Baeriswyl R.",
    "wof:placetype":"venue"
},
  "geometry": {"coordinates":[8.8010902405,46.3217811584],"type":"Point"}
}