{
  "type": "Feature",
  "properties": {
    "iso:country":"CH",
    "sg:address":"Hauptstrasse 49",
    "sg:city":"Felben-wellhausen",
    "sg:orig_category":"Verwaltung der Rechtspflege, Gerichte",
    "sg:phone":"+41 52 765 19 17",
    "sg:postcode":"8552",
    "sg:province":"Thurgau",
    "wof:name":"Grundbuchamt & Notariat",
    "wof:placetype":"venue"
},
  "geometry": {"coordinates":[8.9435453415,47.5804252625],"type":"Point"}
}