{
  "type": "Feature",
  "properties": {
    "iso:country":"CH",
    "sg:address":"Saxgass 2",
    "sg:city":"Schaan",
    "sg:orig_category":"Detailhandel Reparatur von Gebrauchsg\u00fctern Vermietung von Gebrauchsg\u00fctern",
    "sg:phone":"+41 75 232 25 45",
    "sg:postcode":"9494",
    "wof:name":"Peter K\u00f6nigsdorfer Peter's Videothek",
    "wof:placetype":"venue"
},
  "geometry": {"coordinates":[9.5099973679,47.157951355],"type":"Point"}
}