{
  "type": "Feature",
  "properties": {
    "iso:country":"CH",
    "sg:address":"Schlossgasse 8",
    "sg:city":"Tr\u00fcllikon",
    "sg:orig_category":"Fachdetailhandel in Verkaufsr\u00e4umen",
    "sg:phone":"+41 31 981 34 11",
    "sg:postcode":"8466",
    "sg:province":"Z\u00fcrich",
    "wof:name":"Straub Velo Und Ski-center Ag",
    "wof:placetype":"venue"
},
  "geometry": {"coordinates":[7.3658127785,46.9181938171],"type":"Point"}
}