{
  "type": "Feature",
  "properties": {
    "iso:country":"CH",
    "sg:address":"Bod\u00e9rons Chemin Des 3",
    "sg:city":"Epalinges",
    "sg:orig_category":"Herstellung von Oberbekleidung",
    "sg:phone":"+41 21 784 34 36",
    "sg:postcode":"1066",
    "sg:province":"Vaud",
    "wof:name":"Interpel Sa",
    "wof:placetype":"venue"
},
  "geometry": {"coordinates":[6.6711440086,46.5477027893],"type":"Point"}
}