{
  "type": "Feature",
  "properties": {
    "iso:country":"CH",
    "sg:address":"Via Luigi Taddei 1",
    "sg:city":"Viganello",
    "sg:orig_category":"Fachdetailhandel mit pharmazeutischen Produkten Unternehmensberatung",
    "sg:phone":"+41 91 971 58 80",
    "sg:postcode":"6962",
    "sg:province":"Ticino",
    "wof:name":"Farmacia Viganello Sa",
    "wof:placetype":"venue"
},
  "geometry": {"coordinates":[8.9639415741,46.0119171143],"type":"Point"}
}