{
  "type": "Feature",
  "properties": {
    "iso:country":"CH",
    "sg:address":"Sch\u00fctzenweg 3",
    "sg:city":"Luterbach",
    "sg:orig_category":"Abbruch U Sprenggewerbe, Erdbewegungsarbeiten Gewinnung von Kies U Sand",
    "sg:phone":"+41 32 682 11 42",
    "sg:postcode":"4542",
    "sg:province":"Solothurn",
    "wof:name":"Flury Ernst",
    "wof:placetype":"venue"
},
  "geometry": {"coordinates":[7.576628,47.215618],"type":"Point"}
}