{
  "type": "Feature",
  "properties": {
    "iso:country":"CH",
    "sg:address":"Hauptstrasse 88",
    "sg:city":"T\u00e4uffelen",
    "sg:orig_category":"Herstellung von Fahrr\u00e4dern",
    "sg:postcode":"2575",
    "sg:province":"Bern",
    "wof:name":"R\u00fcdlinger Werner",
    "wof:placetype":"venue"
},
  "geometry": {"coordinates":[7.199971199,47.0675849915],"type":"Point"}
}