{
  "type": "Feature",
  "properties": {
    "iso:country":"CH",
    "sg:address":"Thalerstrasse 64",
    "sg:city":"Rheineck",
    "sg:orig_category":"Sportvereine Turnen Vereine Damen",
    "sg:phone":"+41 79 436 49 01",
    "sg:postcode":"9424",
    "sg:province":"St. Gallen",
    "wof:name":"Frauenriege Rheineck",
    "wof:placetype":"venue"
},
  "geometry": {"coordinates":[9.5810489655,47.4666862488],"type":"Point"}
}