{
  "type": "Feature",
  "properties": {
    "iso:country":"CH",
    "sg:address":"Rue Rodolphe-toepffer 11bis 1200 Genf. Postfach",
    "sg:city":"Gen\u00e8ve",
    "sg:orig_category":"Herstellung von Sportger\u00e4ten",
    "sg:postcode":"1206",
    "sg:province":"Gen\u00e8ve",
    "wof:name":"Bluefin Sa",
    "wof:placetype":"venue"
},
  "geometry": {"coordinates":[6.1538829803,46.1985549927],"type":"Point"}
}