{
  "type": "Feature",
  "properties": {
    "iso:country":"CH",
    "sg:address":"Via Serafino Balestra 25",
    "sg:city":"Locarno",
    "sg:orig_category":"Herstellung von Betonerzeugnissen f\u00fcr den Bau Herstellung von Bettwaren",
    "sg:phone":"+41 91 751 14 36",
    "sg:postcode":"6600",
    "sg:province":"Ticino",
    "wof:name":"Cassina Sa Rivestimenti E Soffitti",
    "wof:placetype":"venue"
},
  "geometry": {"coordinates":[8.7981681824,46.1629714966],"type":"Point"}
}