{
  "type": "Feature",
  "properties": {
    "iso:country":"CH",
    "sg:address":"Rue Du Simplon 8",
    "sg:city":"Lausanne",
    "sg:orig_category":"Architektur U Ingenieurb\u00fcros",
    "sg:phone":"+41 21 616 10 78",
    "sg:postcode":"1006",
    "sg:province":"Vaud",
    "wof:name":"Robert-grandpierre Et Rapp Sa",
    "wof:placetype":"venue"
},
  "geometry": {"coordinates":[6.631671,46.515686],"type":"Point"}
}