{
  "type": "Feature",
  "properties": {
    "iso:country":"CH",
    "sg:address":"Innere Margarethenstrasse 7 4051 Basel. Postfach",
    "sg:city":"Basel",
    "sg:orig_category":"Grosshandel mit Getreide, Saatgut U Futtermitteln Grosshandel mit chemischen Erzeugnissen",
    "sg:phone":"+41 27 322 07 77",
    "sg:postcode":"4002",
    "sg:province":"Basel-Stadt",
    "wof:name":"Balet Georges, Successeur De W. Robert-tissot",
    "wof:placetype":"venue"
},
  "geometry": {"coordinates":[7.3586001396,46.2367401123],"type":"Point"}
}