{
  "type": "Feature",
  "properties": {
    "iso:country":"CH",
    "sg:address":"6672",
    "sg:city":"Gordevio",
    "sg:orig_category":"Sonstiges Versicherungsgewerbe",
    "sg:postcode":"6672",
    "sg:province":"Ticino",
    "wof:name":"Assicom Di Aldo Bianchi E Maurizio Pierini",
    "wof:placetype":"venue"
},
  "geometry": {"coordinates":[8.7423295975,46.225151062],"type":"Point"}
}