{
  "type": "Feature",
  "properties": {
    "iso:country":"CH",
    "sg:address":"Elisabethenstrasse 2",
    "sg:city":"Basel",
    "sg:orig_category":"Interessenvertretungen",
    "sg:postcode":"4051",
    "sg:province":"Basel-Stadt",
    "wof:name":"Albert Weitnauer-stiftung Zur F\u00f6rderung Klassischer Studien Begabter Sch\u00fcler Vorzugsweise Des Humanistischen Gymnasiums ...",
    "wof:placetype":"venue"
},
  "geometry": {"coordinates":[7.5917649269,47.5536270142],"type":"Point"}
}