{
  "type": "Feature",
  "properties": {
    "iso:country":"CH",
    "sg:address":"4461",
    "sg:city":"B\u00f6ckten",
    "sg:orig_category":"Primarschulen",
    "sg:postcode":"4461",
    "sg:province":"Basel-Landschaft",
    "wof:name":"Primarschule",
    "wof:placetype":"venue"
},
  "geometry": {"coordinates":[7.8342700005,47.4674606323],"type":"Point"}
}