{
  "type": "Feature",
  "properties": {
    "iso:country":"CH",
    "sg:address":"Burggartenstrasse 32",
    "sg:city":"Bottmingen",
    "sg:orig_category":"Detailhandel mit Getr\u00e4nken Grosshandel mit Getr\u00e4nken",
    "sg:phone":"+41 61 331 34 30",
    "sg:postcode":"4103",
    "sg:province":"Basel-Landschaft",
    "wof:name":"Domaine Bourdic Weinhandlung Gmbh",
    "wof:placetype":"venue"
},
  "geometry": {"coordinates":[7.5670819283,47.5218925476],"type":"Point"}
}