{
  "type": "Feature",
  "properties": {
    "iso:country":"CH",
    "sg:address":"Sch\u00f6neich",
    "sg:city":"Roggliswil",
    "sg:orig_category":"Detailhandel mit Metallwaren, Anstrichmitteln, Glaswaren, Bau U Heimwerkerbedarf",
    "sg:phone":"+41 62 747 30 40",
    "sg:postcode":"6265",
    "sg:province":"Luzern",
    "wof:name":"Pro-anlagentechnik Gmbh",
    "wof:placetype":"venue"
},
  "geometry": {"coordinates":[7.8770470619,47.2209091187],"type":"Point"}
}