{
  "type": "Feature",
  "properties": {
    "iso:country":"CH",
    "sg:address":"8932",
    "sg:city":"Mettmenstetten",
    "sg:orig_category":"Wasserversorgung",
    "sg:phone":"+41 41 930 20 30",
    "sg:postcode":"8932",
    "sg:province":"Z\u00fcrich",
    "wof:name":"Wasserversorgungs- Genossenschaft",
    "wof:placetype":"venue"
},
  "geometry": {"coordinates":[8.1522159576,47.220249176],"type":"Point"}
}