{
  "type": "Feature",
  "properties": {
    "iso:country":"CH",
    "sg:address":"Aadorferstrasse 38",
    "sg:city":"Elgg",
    "sg:orig_category":"Sportvereine Ballsport Squash",
    "sg:phone":"+41 52 364 18 68",
    "sg:postcode":"8353",
    "sg:province":"Z\u00fcrich",
    "wof:name":"Squash Club T\u00f6sstal",
    "wof:placetype":"venue"
},
  "geometry": {"coordinates":[8.8747854233,47.4945678711],"type":"Point"}
}