{
  "type": "Feature",
  "properties": {
    "iso:country":"CH",
    "sg:address":"Stationsstrasse 2",
    "sg:city":"Niederhasli",
    "sg:orig_category":"Detailhandel mit Musikinstrumenten Detailhandel mit elektrischen Haushalts-,Radio U Fernsehger\u00e4ten s",
    "sg:phone":"+41 79 666 52 53",
    "sg:postcode":"8155",
    "sg:province":"Z\u00fcrich",
    "wof:name":"Musik + Pianohaus Ammann H.",
    "wof:placetype":"venue"
},
  "geometry": {"coordinates":[8.4883842468,47.4793624878],"type":"Point"}
}