{
  "type": "Feature",
  "properties": {
    "iso:country":"CH",
    "sg:address":"1273",
    "sg:city":"Arzier",
    "sg:classifiers":[
        {
            "category":"Education",
            "subcategory":"Library",
            "type":"Public Place"
        }
    ],
    "sg:postcode":"1273",
    "sg:province":"Vaud",
    "sg:tags":[
        "u",
        "bibliotheken",
        "archive"
    ],
    "wof:name":"Biblioth\u00e8que Communale",
    "wof:placetype":"venue"
},
  "geometry": {"coordinates":[6.151809,46.381229],"type":"Point"}
}