{
  "type": "Feature",
  "properties": {
    "iso:country":"CH",
    "sg:address":"Steinenvorstadt 79",
    "sg:city":"Basel",
    "sg:classifiers":[
        {
            "category":"Restaurant",
            "type":"Food & Drink"
        }
    ],
    "sg:phone":"+41 62 771 37 73",
    "sg:postcode":"4051",
    "sg:province":"Basel-Stadt",
    "wof:name":"Pizzeria Wynenhof",
    "wof:placetype":"venue"
},
  "geometry": {"coordinates":[8.1840305328,47.2507095337],"type":"Point"}
}