{
  "type": "Feature",
  "properties": {
    "iso:country":"CH",
    "sg:address":"Gatterwies 18",
    "sg:city":"Wittenbach",
    "sg:orig_category":"Architektur U Ingenieurb\u00fcros Landschaftsplanungsb\u00fcros U Gartenarchitekturb\u00fcros",
    "sg:phone":"+41 71 290 02 55",
    "sg:postcode":"9303",
    "wof:name":"Rudolf L\u00fcthi Landschaftsarchitekt Htl Bsla",
    "wof:placetype":"venue"
},
  "geometry": {"coordinates":[9.370718956,47.44947052],"type":"Point"}
}