{
  "type": "Feature",
  "properties": {
    "iso:country":"CH",
    "sg:address":"Gross\u00e4cker 91",
    "sg:city":"B\u00f6bikon",
    "sg:orig_category":"Sonstige Aktivit\u00e4ten der nicht-\u00e4rztlichen Medizinalberufe",
    "sg:phone":"+41 56 249 37 82",
    "sg:postcode":"5334",
    "sg:province":"Aargau",
    "wof:name":"Rosmary Zambelli Atemtherapie",
    "wof:placetype":"venue"
},
  "geometry": {"coordinates":[8.3310403824,47.5531692505],"type":"Point"}
}