{
  "type": "Feature",
  "properties": {
    "iso:country":"CH",
    "sg:address":"Chemin Des Palettes 25",
    "sg:city":"Grand-lancy",
    "sg:orig_category":"Detailhandel mit Schuhen Detailhandel mit Sportartikeln",
    "sg:phone":"+41 22 794 53 41",
    "sg:postcode":"1212",
    "sg:province":"Gen\u00e8ve",
    "wof:name":"Ochsner Schuhe & Sport Ag",
    "wof:placetype":"venue"
},
  "geometry": {"coordinates":[6.119738102,46.1758270264],"type":"Point"}
}