{
  "type": "Feature",
  "properties": {
    "iso:country":"CH",
    "sg:address":"Chillon Avenue De 82",
    "sg:city":"Montreux",
    "sg:orig_category":"Detailhandel mit elektrischen Haushalts-,Radio U Fernsehger\u00e4ten sowie Musikinstrumenten",
    "sg:phone":"+41 79 446 07 07",
    "sg:postcode":"1820",
    "sg:province":"Vaud",
    "wof:name":"Elektro Dep, Castioni Raymond",
    "wof:placetype":"venue"
},
  "geometry": {"coordinates":[6.9105057716,46.4316940308],"type":"Point"}
}