{
  "type": "Feature",
  "properties": {
    "iso:country":"CH",
    "sg:address":"Bachstrasse 17",
    "sg:city":"Bachenb\u00fclach",
    "sg:orig_category":"Detailhandel mit Blumen U Pflanzen",
    "sg:phone":"+41 18609050",
    "sg:postcode":"8184",
    "sg:province":"Z\u00fcrich",
    "wof:name":"Anita Gugolz Anita's Blumenl\u00e4deli",
    "wof:placetype":"venue"
},
  "geometry": {"coordinates":[8.546428,47.504475],"type":"Point"}
}