{
  "type": "Feature",
  "properties": {
    "iso:country":"CH",
    "sg:address":"Rossorino 6614 Brissago. Postfach Caselle Postale 627",
    "sg:city":"Brissago",
    "sg:orig_category":"Herstellung von Teppichen Verlegen von Fliesen U Platten",
    "sg:phone":"+41 91 793 13 50",
    "sg:postcode":"6614",
    "sg:province":"Ticino",
    "wof:name":"Pozzorini Edi",
    "wof:placetype":"venue"
},
  "geometry": {"coordinates":[8.7099237442,46.1247825623],"type":"Point"}
}