{
  "type": "Feature",
  "properties": {
    "iso:country":"CH",
    "sg:address":"Ch\u00eanes Rue Des 12",
    "sg:city":"Court\u00e9telle",
    "sg:orig_category":"Allgemeiner Hoch U Tiefbau",
    "sg:phone":"+41 79 250 37 09",
    "sg:postcode":"2852",
    "sg:province":"Jura",
    "wof:name":"Icar Concept S\u00e0rl",
    "wof:placetype":"venue"
},
  "geometry": {"coordinates":[7.316772,47.342602],"type":"Point"}
}