{
  "type": "Feature",
  "properties": {
    "iso:country":"CH",
    "sg:address":"Schadaustr. 27",
    "sg:city":"Thun",
    "sg:orig_category":"Unclassifiable Establishments",
    "sg:phone":"+41 33 336 67 31",
    "sg:postcode":"3600",
    "sg:province":"Bern",
    "wof:name":"B\u00fcro F\u00fcr Freiraumgestaltung, Hugo Baumann, Landschaftsarchitekt Bsla",
    "wof:placetype":"venue"
},
  "geometry": {"coordinates":[7.6283349991,46.7471466064],"type":"Point"}
}