{
  "type": "Feature",
  "properties": {
    "addr:full":"Zellgut 6214 Schenkon. Postfach 695 Sursee Luzern 6210",
    "addr:housenumber":"695",
    "addr:postcode":"6214;6210",
    "addr:street":"Schenkon. Postfach",
    "iso:country":"CH",
    "sg:address":"Zellgut 6214 Schenkon. Postfach 695",
    "sg:city":"Sursee",
    "sg:orig_category":"Detailhandel mit Bekleidung Versandhandel",
    "sg:postcode":"6210",
    "sg:province":"Luzern",
    "wof:name":"Quelle Versand Ag",
    "wof:placetype":"venue"
},
  "geometry": {"coordinates":[9.350457,47.414181],"type":"Point"}
}