{
  "type": "Feature",
  "properties": {
    "addr:full":"G\u00fcterstrasse 137 4053 Basel. Postfach 3046 Basel Basel-Stadt 4002",
    "addr:housenumber":"137",
    "addr:postcode":"4053;3046;4002",
    "addr:street":"Gueterstrasse;Postfach",
    "iso:country":"CH",
    "sg:address":"G\u00fcterstrasse 137 4053 Basel. Postfach 3046",
    "sg:city":"Basel",
    "sg:orig_category":"Architektur U Ingenieurb\u00fcros",
    "sg:phone":"+41 61 367 95 95",
    "sg:postcode":"4002",
    "sg:province":"Basel-Stadt",
    "wof:name":"Gruneko Ag Ingenieurb\u00fcro, Bes. F\u00fcr Fernheizung, Energieversorgung Usw",
    "wof:placetype":"venue"
},
  "geometry": {"coordinates":[7.589582,47.544888],"type":"Point"}
}