{
  "type": "Feature",
  "properties": {
    "iso:country":"CH",
    "sg:address":"Oberdorfstrasse 44 8408 Winterthur. Postfach",
    "sg:city":"Winterthur",
    "sg:orig_category":"Erbringung von Dienstleistungen f\u00fcr Unternehmen",
    "sg:phone":"+41 52 222 03 33",
    "sg:postcode":"8408",
    "sg:province":"Z\u00fcrich",
    "wof:name":"Jenni - Gestaltung",
    "wof:placetype":"venue"
},
  "geometry": {"coordinates":[8.6954574585,47.5113487244],"type":"Point"}
}