{
  "type": "Feature",
  "properties": {
    "iso:country":"CH",
    "sg:address":"Dorfstrasse 42c",
    "sg:city":"Vinelz",
    "sg:orig_category":"Bauspenglerei Sanit\u00e4rinstallation U Spenglerei",
    "sg:phone":"+41 56 621 18 88",
    "sg:postcode":"3234",
    "sg:province":"Bern",
    "wof:name":"Viktor Isler Spenglerei",
    "wof:placetype":"venue"
},
  "geometry": {"coordinates":[8.273468,47.357708],"type":"Point"}
}