{
  "type": "Feature",
  "properties": {
    "iso:country":"CH",
    "sg:address":"Fauquez Route Aloys- 116 1018 Lausanne. Postfach",
    "sg:city":"Lausanne",
    "sg:orig_category":"Instandhaltung U Reparatur von Automobilen",
    "sg:phone":"+41 21 731 35 71",
    "sg:postcode":"1018",
    "sg:province":"Vaud",
    "wof:name":"Keller Max Garage, Atelier De R\u00e9parations Et Vente De Voitures Automobiles.",
    "wof:placetype":"venue"
},
  "geometry": {"coordinates":[6.6340408325,46.5384635925],"type":"Point"}
}