{
  "type": "Feature",
  "properties": {
    "iso:country":"CH",
    "sg:address":"Brauerstrasse 50",
    "sg:city":"Winterthur",
    "sg:orig_category":"Arztpraxen",
    "sg:phone":"+41 52 212 12 32",
    "sg:postcode":"8400",
    "sg:province":"Z\u00fcrich",
    "wof:name":"Dr.med.rudolf Hertli Arzt F.allgemeine Medizin Fmh",
    "wof:placetype":"venue"
},
  "geometry": {"coordinates":[8.725655,47.508682],"type":"Point"}
}