{
  "type": "Feature",
  "properties": {
    "iso:country":"CH",
    "sg:address":"Dorfzentrum 491",
    "sg:city":"Heitenried",
    "sg:orig_category":"Nationale Postdienste",
    "sg:phone":"+41 26 495 11 02",
    "sg:postcode":"1714",
    "sg:province":"Fribourg",
    "wof:name":"Die Schweizerische Post",
    "wof:placetype":"venue"
},
  "geometry": {"coordinates":[7.2994952202,46.8268508911],"type":"Point"}
}