{
  "type": "Feature",
  "properties": {
    "iso:country":"CH",
    "sg:address":"Gmeindstrasse 31",
    "sg:city":"Montlingen",
    "sg:orig_category":"Herstellung von Frucht U Gem\u00fcses\u00e4ften Herstellung von Obst U Fruchtweinen",
    "sg:phone":"+41 71 761 13 46",
    "sg:postcode":"9462",
    "sg:province":"St. Gallen",
    "wof:name":"Robert Loher Mosterei",
    "wof:placetype":"venue"
},
  "geometry": {"coordinates":[9.5856752396,47.3306617737],"type":"Point"}
}