{
  "type": "Feature",
  "properties": {
    "iso:country":"CH",
    "sg:address":"B\u00e4umlihofstrasse 455",
    "sg:city":"Riehen",
    "sg:orig_category":"Sanit\u00e4r U Heizungsinstallation Sanit\u00e4r, Heizungs U L\u00fcftungsinstallation",
    "sg:phone":"+41 61 601 39 25",
    "sg:postcode":"4125",
    "sg:province":"Basel-Stadt",
    "wof:name":"L\u00f6hrer + Toffol",
    "wof:placetype":"venue"
},
  "geometry": {"coordinates":[7.632434845,47.5731773376],"type":"Point"}
}