{
  "type": "Feature",
  "properties": {
    "addr:full":"Boulevard De P\u00e9rolles 8 Fribourg Fribourg 1700",
    "addr:housenumber":"8",
    "addr:postcode":"1700",
    "addr:street":"Boulevard De Pe\u0301Rolles",
    "iso:country":"CH",
    "sg:address":"Boulevard De P\u00e9rolles 8",
    "sg:city":"Fribourg",
    "sg:orig_category":"Arztpraxen",
    "sg:postcode":"1700",
    "sg:province":"Fribourg",
    "wof:name":"Dr M\u00e9d. Samuel B. Eduah M\u00e9decin Sp\u00e9cialiste Fmh",
    "wof:placetype":"venue"
},
  "geometry": {"coordinates":[7.151903,46.801758],"type":"Point"}
}