{
  "type": "Feature",
  "properties": {
    "iso:country":"CH",
    "sg:address":"Leonhardsstrasse 8",
    "sg:city":"Basel",
    "sg:orig_category":"Museen",
    "sg:phone":"+41 27 776 13 40",
    "sg:postcode":"4051",
    "sg:province":"Basel-Stadt",
    "wof:name":"Mus\u00e9e Nos Atro Bon Bagna",
    "wof:placetype":"venue"
},
  "geometry": {"coordinates":[7.2124481201,46.0804595947],"type":"Point"}
}