{
  "type": "Feature",
  "properties": {
    "iso:country":"CH",
    "sg:address":"Winterthurerstrasse 51",
    "sg:city":"Uster",
    "sg:orig_category":"Bauschreinerei",
    "sg:phone":"+41 33 849 13 44",
    "sg:postcode":"8610",
    "sg:province":"Z\u00fcrich",
    "wof:name":"Kurt Pfister Allroundservice Schreinerei",
    "wof:placetype":"venue"
},
  "geometry": {"coordinates":[7.92782,46.715622],"type":"Point"}
}