{
  "type": "Feature",
  "properties": {
    "iso:country":"CH",
    "sg:address":"Gurzelenstrasse 7",
    "sg:city":"Biel/bienne",
    "sg:orig_category":"Mechanische Werkst\u00e4tten",
    "sg:phone":"+41 32 341 61 75",
    "sg:postcode":"2502",
    "sg:province":"Bern",
    "wof:name":"Antonio Costa Pr\u00e4zisionsmechanik",
    "wof:placetype":"venue"
},
  "geometry": {"coordinates":[7.2555270195,47.1462135315],"type":"Point"}
}