{
  "type": "Feature",
  "properties": {
    "iso:country":"CH",
    "sg:address":"Hardstrasse 135",
    "sg:city":"Basel",
    "sg:orig_category":"Non-Classified Establishments",
    "sg:phone":"+41 56 443 00 00",
    "sg:postcode":"4052",
    "sg:province":"Basel-Stadt",
    "wof:name":"Rollag Willi Horlacher",
    "wof:placetype":"venue"
},
  "geometry": {"coordinates":[8.0965471268,47.4435882568],"type":"Point"}
}