{
  "type": "Feature",
  "properties": {
    "iso:country":"CH",
    "sg:address":"Wyler",
    "sg:city":"Helgisried",
    "sg:orig_category":"Maurerarbeiten",
    "sg:phone":"+41 31 809 18 48",
    "sg:postcode":"3155",
    "sg:province":"Bern",
    "wof:name":"Andreas Friedrich Maurergesch\u00e4ft",
    "wof:placetype":"venue"
},
  "geometry": {"coordinates":[7.4303541183,46.8146362305],"type":"Point"}
}