{
  "type": "Feature",
  "properties": {
    "iso:country":"CH",
    "sg:address":"Burgerweg 33.",
    "sg:city":"Herzogenbuchsee",
    "sg:orig_category":"Grosshandel mit lebenden Tieren",
    "sg:phone":"+41 62 961 43 39",
    "sg:postcode":"3360",
    "sg:province":"Bern",
    "wof:name":"Fr. Maurer-kohler",
    "wof:placetype":"venue"
},
  "geometry": {"coordinates":[7.7148189545,47.1923904419],"type":"Point"}
}