{
  "type": "Feature",
  "properties": {
    "iso:country":"CH",
    "sg:address":"Luzernerstrasse 105",
    "sg:city":"Littau",
    "sg:orig_category":"Fachdetailhandel in Verkaufsr\u00e4umen",
    "sg:postcode":"6014",
    "sg:province":"Luzern",
    "wof:name":"Verik S\u00e0rl",
    "wof:placetype":"venue"
},
  "geometry": {"coordinates":[6.8316140175,47.1046447754],"type":"Point"}
}