{
  "type": "Feature",
  "properties": {
    "iso:country":"CH",
    "sg:address":"Albulastrasse 57",
    "sg:city":"Z\u00fcrich",
    "sg:orig_category":"Technische, physikalische U chemische Untersuchung",
    "sg:postcode":"8048",
    "sg:province":"Z\u00fcrich",
    "wof:name":"Sanascan Haarlabor Brunner Medizinische Analysen, Bes. Haaranalysen",
    "wof:placetype":"venue"
},
  "geometry": {"coordinates":[-86.9059753418,37.11926651],"type":"Point"}
}