{
  "type": "Feature",
  "properties": {
    "iso:country":"CH",
    "sg:address":"Bahnhofstrasse 119a",
    "sg:city":"Schiers",
    "sg:orig_category":"Detailhandel mit Schreib U Papeteriewaren Detailhandel mit Spielwaren",
    "sg:phone":"+41 81 328 17 57",
    "sg:postcode":"7220",
    "sg:province":"Graubunden",
    "wof:name":"Anneliese Kappeler Papeterie & Spielwaren",
    "wof:placetype":"venue"
},
  "geometry": {"coordinates":[9.6878623962,46.9681015015],"type":"Point"}
}