{
  "type": "Feature",
  "properties": {
    "addr:full":"M\u00fchlmattstr. 56 Aarau Aargau 5001",
    "addr:housenumber":"56",
    "addr:postcode":"5001",
    "addr:street":"Muehlmattstr.",
    "iso:country":"CH",
    "sg:address":"M\u00fchlmattstr. 56",
    "sg:city":"Aarau",
    "sg:classifiers":[
        {
            "category":"Shopping",
            "subcategory":"Clothing, Apparel, & Fashions",
            "type":"Retail Goods"
        }
    ],
    "sg:phone":"+41 81 833 33 27",
    "sg:postcode":"5001",
    "sg:province":"Aargau",
    "sg:tags":[
        "textile",
        "accessory",
        "clothing",
        "clothes"
    ],
    "wof:name":"Kriemler-m\u00dcller Ag",
    "wof:placetype":"venue"
},
  "geometry": {"coordinates":[9.838916,46.497631],"type":"Point"}
}