{
  "type": "Feature",
  "properties": {
    "iso:country":"CH",
    "sg:address":"Bahnstrasse 5",
    "sg:city":"Schwerzenbach",
    "sg:classifiers":[
        {
            "category":"Bars & Pubs",
            "type":"Food & Drink"
        }
    ],
    "sg:phone":"+41 18250777",
    "sg:postcode":"8603",
    "sg:province":"Z\u00fcrich",
    "sg:tags":[
        "restaurant"
    ],
    "wof:name":"Restaurant & Bar Bahnh\u00f6fli",
    "wof:placetype":"venue"
},
  "geometry": {"coordinates":[8.660567,47.383888],"type":"Point"}
}