{
  "type": "Feature",
  "properties": {
    "iso:country":"CH",
    "sg:address":"Oberfeldstrasse 10",
    "sg:city":"Pratteln",
    "sg:orig_category":"Fahrschulen, Flugschulen",
    "sg:phone":"+41 61 821 14 51",
    "sg:postcode":"4133",
    "sg:province":"Basel-Landschaft",
    "wof:name":"Felix Kn\u00f6pfel Autofahrschule",
    "wof:placetype":"venue"
},
  "geometry": {"coordinates":[7.7006421089,47.5211715698],"type":"Point"}
}