{
  "type": "Feature",
  "properties": {
    "iso:country":"CH",
    "sg:address":"7083",
    "sg:city":"Lantsch/lenz",
    "sg:orig_category":"Primarschulen",
    "sg:postcode":"7083",
    "sg:province":"Graubunden",
    "wof:name":"Primarschule",
    "wof:placetype":"venue"
},
  "geometry": {"coordinates":[9.5632972717,46.6852493286],"type":"Point"}
}