{
  "type": "Feature",
  "properties": {
    "iso:country":"CH",
    "sg:address":"Via Quinta 15",
    "sg:city":"Biasca",
    "sg:orig_category":"Detailhandel mit Waren verschiedener Art, Hauptrichtung Nahrungsmittel",
    "sg:phone":"+41 91 862 29 25",
    "sg:postcode":"6710",
    "sg:province":"Ticino",
    "wof:name":"Denner Top Superdiscount",
    "wof:placetype":"venue"
},
  "geometry": {"coordinates":[8.9714946747,46.3531265259],"type":"Point"}
}