{
  "type": "Feature",
  "properties": {
    "iso:country":"CH",
    "sg:address":"K\u00fcngenhoschet 17 8755 Ennenda. Postfach 2",
    "sg:city":"Ennenda",
    "sg:orig_category":"HOTELS: MIT RESTAURANT Verm\u00f6gensverwaltung",
    "sg:phone":"+41 55 640 71 76",
    "sg:postcode":"8755",
    "sg:province":"Glarus",
    "wof:name":"Ultaco Gmbh Seminare, Kurse, Veranstaltungen; Organisation Usw.",
    "wof:placetype":"venue"
},
  "geometry": {"coordinates":[9.0727872849,47.0433044434],"type":"Point"}
}