{
  "type": "Feature",
  "properties": {
    "iso:country":"CH",
    "sg:address":"Hauptstrasse 82",
    "sg:city":"Einigen",
    "sg:classifiers":[
        {
            "category":"Travel",
            "subcategory":"Hotels & Motels",
            "type":"Entertainment"
        }
    ],
    "sg:phone":"+41 33 654 32 72",
    "sg:postcode":"3646",
    "sg:province":"Bern",
    "sg:tags":[
        "mit",
        "restaurant"
    ],
    "wof:name":"Motel Kristal-grill",
    "wof:placetype":"venue"
},
  "geometry": {"coordinates":[7.6407351494,46.7117576599],"type":"Point"}
}