{
  "type": "Feature",
  "properties": {
    "iso:country":"CH",
    "sg:address":"Im Hackacker 21",
    "sg:city":"Urdorf",
    "sg:orig_category":"Instandhaltung U Reparatur von Automobilen",
    "sg:phone":"+41 17341200",
    "sg:postcode":"8902",
    "sg:province":"Z\u00fcrich",
    "wof:name":"Jan Soyka Garage",
    "wof:placetype":"venue"
},
  "geometry": {"coordinates":[8.4226350784,47.3915863037],"type":"Point"}
}