{
  "type": "Feature",
  "properties": {
    "iso:country":"CH",
    "sg:address":"Breitestrasse 65",
    "sg:city":"Winterthur",
    "sg:orig_category":"RESTAURANTS: TEA-ROOMS",
    "sg:phone":"+41 52 232 75 31",
    "sg:postcode":"8400",
    "sg:province":"Z\u00fcrich",
    "wof:name":"Restaurant Breite, A. + M. Bachmann",
    "wof:placetype":"venue"
},
  "geometry": {"coordinates":[8.7257356644,47.4901580811],"type":"Point"}
}