{
  "type": "Feature",
  "properties": {
    "iso:country":"CH",
    "sg:address":"Rue De Lausanne 32",
    "sg:city":"Sion",
    "sg:orig_category":"Physiotherapie",
    "sg:phone":"+41 27 322 67 00",
    "sg:postcode":"1950",
    "sg:province":"Valais",
    "wof:name":"Monique Schertenleib Physioth\u00e9rapie",
    "wof:placetype":"venue"
},
  "geometry": {"coordinates":[7.3548369408,46.2314033508],"type":"Point"}
}