{
  "type": "Feature",
  "properties": {
    "iso:country":"CH",
    "sg:address":"Heliosstrasse 12 8032 Z\u00fcrich. Postfach 182",
    "sg:city":"Z\u00fcrich",
    "sg:orig_category":"Grosshandel mit Textilien Vermietung von Luftfahrzeugen",
    "sg:phone":"+41 13855580",
    "sg:postcode":"8032",
    "sg:province":"Z\u00fcrich",
    "wof:name":"Bodmer H. & Co Ag",
    "wof:placetype":"venue"
},
  "geometry": {"coordinates":[8.5597715378,47.3633918762],"type":"Point"}
}