{
  "type": "Feature",
  "properties": {
    "iso:country":"CH",
    "sg:address":"Lamboing Route De 48e",
    "sg:city":"Diesse",
    "sg:orig_category":"Handels-H\u00e4user U Gesellschaften",
    "sg:phone":"+41 32 315 51 36",
    "sg:postcode":"2517",
    "sg:province":"Bern",
    "wof:name":"Denner Satellite, Bourquin Nelly",
    "wof:placetype":"venue"
},
  "geometry": {"coordinates":[7.1191477776,47.1136856079],"type":"Point"}
}