{
  "type": "Feature",
  "properties": {
    "iso:country":"CH",
    "sg:address":"6637",
    "sg:city":"Sonogno",
    "sg:orig_category":"Sportvereine Ski",
    "sg:phone":"+41 91 746 17 87",
    "sg:postcode":"6637",
    "sg:province":"Ticino",
    "wof:name":"Sci Club Verzasca",
    "wof:placetype":"venue"
},
  "geometry": {"coordinates":[8.787560463,46.3500366211],"type":"Point"}
}