{
  "type": "Feature",
  "properties": {
    "iso:country":"CH",
    "sg:address":"Vevey Route De 16 1071 Chexbres. Postfach",
    "sg:city":"Chexbres",
    "sg:orig_category":"Unclassifiable Establishments",
    "sg:postcode":"1071",
    "sg:province":"Vaud",
    "wof:name":"L\u00e9geret Etienne",
    "wof:placetype":"venue"
},
  "geometry": {"coordinates":[6.776239872,46.4821128845],"type":"Point"}
}