{
  "type": "Feature",
  "properties": {
    "iso:country":"CH",
    "sg:address":"Echostr. 18",
    "sg:city":"Neuhausen",
    "sg:orig_category":"Herstellung von Elektrizit\u00e4tsverteilungs U schalteinrichtungen",
    "sg:postcode":"8212",
    "sg:province":"Schaffhausen",
    "wof:name":"Haltec Halmo",
    "wof:placetype":"venue"
},
  "geometry": {"coordinates":[8.622674942,47.6840438843],"type":"Point"}
}