{
  "type": "Feature",
  "properties": {
    "iso:country":"CH",
    "sg:address":"Neue Bahnhofstrasse 3 3110 M\u00fcnsingen. Postfach 1251",
    "sg:city":"M\u00fcnsingen",
    "sg:orig_category":"Detailhandel mit Uhren U Schmuck Reparatur von Uhren U Schmuck",
    "sg:phone":"+41 31 721 10 39",
    "sg:postcode":"3110",
    "sg:province":"Bern",
    "wof:name":"Urs Kocher Uhren-bijouterie Goldschmiede",
    "wof:placetype":"venue"
},
  "geometry": {"coordinates":[7.5619440079,46.874256134],"type":"Point"}
}