{
  "type": "Feature",
  "properties": {
    "iso:country":"CH",
    "sg:address":"Ch. Des Pignets 4",
    "sg:city":"Pr\u00e9verenges",
    "sg:orig_category":"Sanit\u00e4r, Heizungs U L\u00fcftungsinstallation",
    "sg:phone":"+41 79 622 26 21",
    "sg:postcode":"1028",
    "sg:province":"Vaud",
    "wof:name":"Fernandez Antonio",
    "wof:placetype":"venue"
},
  "geometry": {"coordinates":[6.5284361839,46.5156173706],"type":"Point"}
}