{
  "type": "Feature",
  "properties": {
    "iso:country":"CH",
    "sg:address":"Bourgogne Chemin De 21",
    "sg:city":"Nyon",
    "sg:orig_category":"Vermietung U Verpachtung von eigenen Immobilien",
    "sg:postcode":"1260",
    "sg:province":"Vaud",
    "wof:name":"Tpc Un Toit Pour Chacun Sa",
    "wof:placetype":"venue"
},
  "geometry": {"coordinates":[6.2266511917,46.3934135437],"type":"Point"}
}