{
  "type": "Feature",
  "properties": {
    "iso:country":"CH",
    "sg:address":"Coll\u00e8ge Rue Du 9 1260 Nyon. Postfach",
    "sg:city":"Nyon",
    "sg:orig_category":"Grosshandel mit Nahrungsmitteln, Getr\u00e4nken U Tabakwaren ohne ausgepr\u00e4gten Schwerpunkt",
    "sg:phone":"+41 22 361 49 41",
    "sg:postcode":"1260",
    "sg:province":"Vaud",
    "wof:name":"Aux Produits D'italie, Forgione Daniela Produits Alimentaires D'italie, De Vins Et Boissons Alcoolis\u00e9es Ou Non",
    "wof:placetype":"venue"
},
  "geometry": {"coordinates":[6.2377181053,46.3821716309],"type":"Point"}
}