{
  "type": "Feature",
  "properties": {
    "addr:full":"Hinterdorfstrasse 20 8274 T\u00e4gerwilen. Postfach 129 T\u00e4gerwilen Thurgau 8274",
    "addr:housenumber":"20;129",
    "addr:postcode":"8274;8274",
    "addr:street":"Hinterdorfstrasse;Postfach;Thurgau",
    "iso:country":"CH",
    "sg:address":"Hinterdorfstrasse 20 8274 T\u00e4gerwilen. Postfach 129",
    "sg:city":"T\u00e4gerwilen",
    "sg:orig_category":"Bauschreinerei Herstellung von Metallkonstruktionen",
    "sg:phone":"+41 71 669 21 31",
    "sg:postcode":"8274",
    "sg:province":"Thurgau",
    "wof:name":"Hochuli K. Fassaden Und Holzbau",
    "wof:placetype":"venue"
},
  "geometry": {"coordinates":[9.136036,47.652657],"type":"Point"}
}