{
  "type": "Feature",
  "properties": {
    "iso:country":"CH",
    "sg:address":"Hauptstrasse 1 4313 M\u00f6hlin. Postfach",
    "sg:city":"M\u00f6hlin",
    "sg:orig_category":"Reinigungsgewerbe",
    "sg:phone":"+41 61 853 05 55",
    "sg:postcode":"4313",
    "sg:province":"Aargau",
    "wof:name":"Henztec Ag Reinigungstechnik",
    "wof:placetype":"venue"
},
  "geometry": {"coordinates":[7.8413491249,47.5636062622],"type":"Point"}
}