{
  "type": "Feature",
  "properties": {
    "iso:country":"CH",
    "sg:address":"Hohle 19",
    "sg:city":"Biglen",
    "sg:orig_category":"Organisationen des Gesundheitswesen",
    "sg:phone":"+41 31 701 12 04",
    "sg:postcode":"3507",
    "sg:province":"Bern",
    "wof:name":"Gemeindekrankenpflege",
    "wof:placetype":"venue"
},
  "geometry": {"coordinates":[7.6277527809,46.9276618958],"type":"Point"}
}