{
  "type": "Feature",
  "properties": {
    "iso:country":"CH",
    "sg:address":"Via Giuseppe Motta 18",
    "sg:city":"Chiasso",
    "sg:classifiers":[
        {
            "category":"Banks & Credit Unions",
            "subcategory":"Bank",
            "type":"Services"
        }
    ],
    "sg:phone":"+41 91 809 80 02",
    "sg:postcode":"6830",
    "sg:province":"Ticino",
    "wof:name":"Swiss Bank Corp., Societ\u00e0 Di Banca Svizzera",
    "wof:placetype":"venue"
},
  "geometry": {"coordinates":[9.0304,45.832821],"type":"Point"}
}