{
  "type": "Feature",
  "properties": {
    "iso:country":"CH",
    "sg:address":"Bonstetterstrasse",
    "sg:city":"Islisberg",
    "sg:orig_category":"Primarschulen",
    "sg:phone":"+41 56 634 23 15",
    "sg:postcode":"8905",
    "sg:province":"Aargau",
    "wof:name":"Primarschule",
    "wof:placetype":"venue"
},
  "geometry": {"coordinates":[8.4397220612,47.3229141235],"type":"Point"}
}