{
  "type": "Feature",
  "properties": {
    "addr:full":"Leimenstrasse 4 4051 Basel. Postfach Basel Basel-Stadt 4051",
    "addr:housenumber":"4",
    "addr:postcode":"4051;4051",
    "addr:street":"Leimenstrasse;Postfach",
    "iso:country":"CH",
    "sg:address":"Leimenstrasse 4 4051 Basel. Postfach",
    "sg:city":"Basel",
    "sg:orig_category":"Architektur U Ingenieurb\u00fcros",
    "sg:postcode":"4051",
    "sg:province":"Basel-Stadt",
    "wof:name":"Bethke Werner, Dipl. Architekt Sia Architekturbureau",
    "wof:placetype":"venue"
},
  "geometry": {"coordinates":[7.583557,47.555267],"type":"Point"}
}