{
  "type": "Feature",
  "properties": {
    "iso:country":"CH",
    "sg:address":"H\u00f6lderlinstrasse 8 8032 Z\u00fcrich. Postfach 8032 Z\u00fcrich",
    "sg:city":"Zust",
    "sg:orig_category":"Informatikschulen",
    "sg:phone":"+41 12521079",
    "sg:postcode":"32",
    "wof:name":"Lti Logoteach Informatik-schulung Ag",
    "wof:placetype":"venue"
},
  "geometry": {"coordinates":[8.5639133453,47.366268158],"type":"Point"}
}