{
  "type": "Feature",
  "properties": {
    "iso:country":"CH",
    "sg:address":"Oberlandstrasse 20 3700 Spiez. Postfach 354",
    "sg:city":"Spiez",
    "sg:orig_category":"Detailhandel mit Brot, Back U S\u00fcsswaren",
    "sg:phone":"+41 33 654 75 55",
    "sg:postcode":"3700",
    "sg:province":"Bern",
    "wof:name":"Markus Felder B\u00e4ckerei-konditorei",
    "wof:placetype":"venue"
},
  "geometry": {"coordinates":[7.677654,46.688747],"type":"Point"}
}