{
  "type": "Feature",
  "properties": {
    "iso:country":"CH",
    "sg:address":"Rue Centrale 1884 Villars-sur-ollon Case Postale 196",
    "sg:city":"Villars-sur-ollon",
    "sg:orig_category":"Versicherungen Hauptagenturen",
    "sg:phone":"+41 24 495 35 55",
    "sg:postcode":"1884",
    "sg:province":"Vaud",
    "wof:name":"Nationale Suisse Assurances Agence Principale",
    "wof:placetype":"venue"
},
  "geometry": {"coordinates":[7.0550079346,46.2969665527],"type":"Point"}
}