{
  "type": "Feature",
  "properties": {
    "iso:country":"CH",
    "sg:address":"Alte Landstrasse",
    "sg:city":"Walenstadt",
    "sg:orig_category":"Instandhaltung U Reparatur von Automobilen",
    "sg:phone":"+41 81 735 16 73",
    "sg:postcode":"8880",
    "sg:province":"St. Gallen",
    "wof:name":"Schmucki Hans",
    "wof:placetype":"venue"
},
  "geometry": {"coordinates":[9.3221788406,47.1211471558],"type":"Point"}
}