{
  "type": "Feature",
  "properties": {
    "iso:country":"CH",
    "sg:address":"B\u00e2timent Moderne 3962 Montana Case Postale 362",
    "sg:city":"Montana-vermala",
    "sg:orig_category":"Eisenbahnverkehr Personenbef\u00f6rderung im Nahverkehr",
    "sg:phone":"+41 27 481 23 48",
    "sg:postcode":"3962",
    "wof:name":"Compagnie De Chemin De Fer Et D'autobus Sierre-montana-crans (smc) Sa",
    "wof:placetype":"venue"
},
  "geometry": {"coordinates":[-110.0444717407,46.6794395447],"type":"Point"}
}