{
  "type": "Feature",
  "properties": {
    "iso:country":"CH",
    "sg:address":"Chlaffentalstrasse 102",
    "sg:city":"Neuhausen",
    "sg:orig_category":"Autospenglereien",
    "sg:phone":"+41 52 672 22 85",
    "sg:postcode":"8212",
    "sg:province":"Schaffhausen",
    "wof:name":"Manfred K\u00fcpfer Autospenglerei",
    "wof:placetype":"venue"
},
  "geometry": {"coordinates":[8.594711,47.673065],"type":"Point"}
}