{
  "type": "Feature",
  "properties": {
    "iso:country":"CH",
    "sg:address":"Eigerplatz 2 3015 Bern. Postfach",
    "sg:city":"Bern",
    "sg:orig_category":"Pensionskassen",
    "sg:postcode":"3005",
    "sg:province":"Bern",
    "wof:name":"Fonds De Pr\u00e9voyance En Faveur Du Personnel De Peugeot (suisse) Sa (bvg)",
    "wof:placetype":"venue"
},
  "geometry": {"coordinates":[7.4305739403,46.9415054321],"type":"Point"}
}