{
  "type": "Feature",
  "properties": {
    "iso:country":"CH",
    "sg:address":"Pilatusstrasse 8a 6003 Luzern. Postfach",
    "sg:city":"Luzern",
    "sg:orig_category":"Reiseb\u00fcros",
    "sg:phone":"+41 41 210 76 66",
    "sg:postcode":"6002",
    "sg:province":"Luzern",
    "wof:name":"Reiseb\u00fcro Flora Ag",
    "wof:placetype":"venue"
},
  "geometry": {"coordinates":[8.3078727722,47.0497894287],"type":"Point"}
}