{
  "type": "Feature",
  "properties": {
    "iso:country":"CH",
    "sg:address":"Entre Deux Chemins",
    "sg:city":"Riaz",
    "sg:orig_category":"Vereine Gesang",
    "sg:postcode":"1632",
    "sg:province":"Fribourg",
    "wof:name":"St\u00e9 De Chant L'esp\u00e9rance",
    "wof:placetype":"venue"
},
  "geometry": {"coordinates":[7.0631361008,46.6437950134],"type":"Point"}
}