{
  "type": "Feature",
  "properties": {
    "iso:country":"CH",
    "sg:address":"N\u00fcrenbergstrasse 5",
    "sg:city":"Z\u00fcrich",
    "sg:orig_category":"Personal U Stellenvermittlung Unternehmensberatung",
    "sg:phone":"+41 13613131",
    "sg:postcode":"8037",
    "sg:province":"Z\u00fcrich",
    "wof:name":"Hodel + Partner Management Consulting",
    "wof:placetype":"venue"
},
  "geometry": {"coordinates":[8.5322237015,47.3921508789],"type":"Point"}
}