{
  "type": "Feature",
  "properties": {
    "iso:country":"CH",
    "sg:address":"Valentin Rue Du 30 1004 Lausanne. Postfach",
    "sg:city":"Lausanne",
    "sg:orig_category":"Detailhandel mit M\u00f6beln U Haushaltsgegenst\u00e4nden",
    "sg:postcode":"1004",
    "sg:province":"Vaud",
    "wof:name":"Boutique Balhk Azizi H.",
    "wof:placetype":"venue"
},
  "geometry": {"coordinates":[6.6318998337,46.5241012573],"type":"Point"}
}