{
  "type": "Feature",
  "properties": {
    "iso:country":"CH",
    "sg:address":"Route Des Grives 45",
    "sg:city":"Granges-paccot",
    "sg:orig_category":"Markt U Meinungsforschung",
    "sg:phone":"+41 26 466 17 70",
    "sg:postcode":"1763",
    "sg:province":"Fribourg",
    "wof:name":"Pro Diffusion Roethlisberger P.",
    "wof:placetype":"venue"
},
  "geometry": {"coordinates":[7.1497387886,46.8214149475],"type":"Point"}
}