{
  "type": "Feature",
  "properties": {
    "iso:country":"CH",
    "sg:address":"Hauptstrasse 32 6315 Ober\u00e4geri. Postfach 203",
    "sg:city":"Ober\u00e4geri",
    "sg:orig_category":"Detailhandel mit Zeitungen U Zeitschriften Kioske",
    "sg:phone":"+41 41 750 29 29",
    "sg:postcode":"6315",
    "sg:province":"Zug",
    "wof:name":"Margrit H\u00e4usler Kiosk",
    "wof:placetype":"venue"
},
  "geometry": {"coordinates":[8.6099348068,47.135761261],"type":"Point"}
}