{
  "type": "Feature",
  "properties": {
    "iso:country":"CH",
    "sg:address":"Rosenegg",
    "sg:city":"Thun",
    "sg:orig_category":"Interessenvertretungen",
    "sg:postcode":"3600",
    "sg:province":"Bern",
    "wof:name":"Domus-historicus-stiftung",
    "wof:placetype":"venue"
},
  "geometry": {"coordinates":[7.6301851273,46.7569656372],"type":"Point"}
}