{
  "type": "Feature",
  "properties": {
    "iso:country":"CH",
    "sg:address":"Centrale Rue 1885 Chesi\u00e8res. Postfach",
    "sg:city":"Chesi\u00e8res",
    "sg:orig_category":"RESTAURANTS: TEA-ROOMS",
    "sg:postcode":"1885",
    "sg:province":"Vaud",
    "wof:name":"Allamand Sylvain",
    "wof:placetype":"venue"
},
  "geometry": {"coordinates":[7.0449409485,46.3016242981],"type":"Point"}
}