{
  "type": "Feature",
  "properties": {
    "iso:country":"CH",
    "sg:address":"Cerneux Gorg\u00e9s",
    "sg:city":"Moutier",
    "sg:orig_category":"Ausbaugewerbe",
    "sg:phone":"+41 32 493 21 51",
    "sg:postcode":"2740",
    "sg:province":"Bern",
    "wof:name":"Raymond Boegli Constructions De Chemin\u00e9es",
    "wof:placetype":"venue"
},
  "geometry": {"coordinates":[7.390111,47.269569],"type":"Point"}
}