{
  "type": "Feature",
  "properties": {
    "iso:country":"CH",
    "sg:address":"Guisan Av. Du G\u00e9n\u00e9ral",
    "sg:city":"Sierre",
    "sg:orig_category":"Elektroinstallation",
    "sg:postcode":"3960",
    "sg:province":"Valais",
    "wof:name":"Snc Essellier Ren\u00e9 Essellier Et Cie Successeurs",
    "wof:placetype":"venue"
},
  "geometry": {"coordinates":[7.5287752151,46.2919044495],"type":"Point"}
}