{
  "type": "Feature",
  "properties": {
    "iso:country":"CH",
    "sg:address":"Hardstrasse 41",
    "sg:city":"Wettingen",
    "sg:orig_category":"Herstellung von Armaturen Herstellung von Sanit\u00e4rkeramik",
    "sg:phone":"+41 91 835 01 05",
    "sg:postcode":"5430",
    "sg:province":"Aargau",
    "wof:name":"Ndw Neue Duschenwelt Ag",
    "wof:placetype":"venue"
},
  "geometry": {"coordinates":[9.0934152603,46.2361106873],"type":"Point"}
}