{
  "type": "Feature",
  "properties": {
    "iso:country":"CH",
    "sg:address":"Ortschwabenstrasse 2",
    "sg:city":"Uettligen",
    "sg:orig_category":"Instandhaltung U Reparatur von Automobilen",
    "sg:phone":"+41 71 310 08 40",
    "sg:postcode":"3043",
    "sg:province":"Bern",
    "wof:name":"Autocenter Winkeln Gmbh",
    "wof:placetype":"venue"
},
  "geometry": {"coordinates":[9.3035182953,47.4042205811],"type":"Point"}
}