{
  "type": "Feature",
  "properties": {
    "iso:country":"CH",
    "sg:address":"3815",
    "sg:city":"Zweil\u00fctschinen",
    "sg:orig_category":"Primarschulen",
    "sg:phone":"+41 33 855 24 88",
    "sg:postcode":"3815",
    "sg:province":"Bern",
    "wof:name":"Primarschule G\u00fcndlischwand",
    "wof:placetype":"venue"
},
  "geometry": {"coordinates":[7.9016690254,46.6308784485],"type":"Point"}
}