{
  "type": "Feature",
  "properties": {
    "iso:country":"CH",
    "sg:address":"5626",
    "sg:city":"Hermetschwil-staff",
    "sg:orig_category":"Detailhandel mit Brot, Back U S\u00fcsswaren Wohnheime",
    "sg:phone":"+41 56 633 15 27",
    "sg:postcode":"5626",
    "sg:province":"Aargau",
    "wof:name":"Frauenkloster St.martin",
    "wof:placetype":"venue"
},
  "geometry": {"coordinates":[8.34162,47.32988],"type":"Point"}
}