{
  "type": "Feature",
  "properties": {
    "iso:country":"CH",
    "sg:address":"Juraweg 14",
    "sg:city":"Sch\u00f6ftland",
    "sg:orig_category":"Bau U Wohngenossenschaften",
    "sg:phone":"+41 62 721 48 47",
    "sg:postcode":"5040",
    "sg:province":"Aargau",
    "wof:name":"Wohnbaugen.l\u00fctisb\u00fcel",
    "wof:placetype":"venue"
},
  "geometry": {"coordinates":[8.05477,47.307594],"type":"Point"}
}