{
  "type": "Feature",
  "properties": {
    "iso:country":"CH",
    "sg:address":"Untere Rebgasse 7 4058 Basel. Postfach",
    "sg:city":"Basel",
    "sg:orig_category":"Buchverlag Verlagsgewerbe",
    "sg:phone":"+41 61 691 06 66",
    "sg:postcode":"4005",
    "sg:province":"Basel-Stadt",
    "wof:name":"Sa-na Verlag Ag",
    "wof:placetype":"venue"
},
  "geometry": {"coordinates":[7.592859,47.561756],"type":"Point"}
}