{
  "type": "Feature",
  "properties": {
    "addr:full":"Emmentalstrasse 15 Konolfingen Bern 3510",
    "addr:housenumber":"15",
    "addr:postcode":"3510",
    "addr:street":"Emmentalstrasse;Bern",
    "iso:country":"CH",
    "sg:address":"Emmentalstrasse 15",
    "sg:city":"Konolfingen",
    "sg:orig_category":"B\u00e4ckereien Konditoreien",
    "sg:postcode":"3510",
    "sg:province":"Bern",
    "wof:name":"H. & J. Freudiger B\u00e4ckerei-konditorei",
    "wof:placetype":"venue"
},
  "geometry": {"coordinates":[7.623043,46.880592],"type":"Point"}
}