{
  "type": "Feature",
  "properties": {
    "iso:country":"CH",
    "sg:address":"Banco",
    "sg:city":"Banco",
    "sg:classifiers":[
        {
            "category":"Banks & Credit Unions",
            "subcategory":"Bank",
            "type":"Services"
        }
    ],
    "sg:phone":"+41 91 608 10 59",
    "sg:postcode":"6981",
    "sg:province":"Ticino",
    "wof:name":"Raiffeisen Di Bedigliora",
    "wof:placetype":"venue"
},
  "geometry": {"coordinates":[8.84083,46.00808],"type":"Point"}
}