{
  "type": "Feature",
  "properties": {
    "iso:country":"CH",
    "sg:address":"Hans Waldmannstrasse 11",
    "sg:city":"Baar",
    "sg:orig_category":"Mit dem Versicherungsgewerbe verbundene T\u00e4tigkeiten",
    "sg:postcode":"6340",
    "sg:province":"Zug",
    "wof:name":"Versicherungstreuhand Seeberger",
    "wof:placetype":"venue"
},
  "geometry": {"coordinates":[8.5158081055,47.2003555298],"type":"Point"}
}