{
  "type": "Feature",
  "properties": {
    "addr:full":"Rue Galil\u00e9e 9 Yverdon-les-bains Vaud 1400",
    "addr:housenumber":"9",
    "addr:postcode":"1400",
    "addr:street":"Rue Galile\u0301E",
    "iso:country":"CH",
    "sg:address":"Rue Galil\u00e9e 9",
    "sg:city":"Yverdon-les-bains",
    "sg:classifiers":[
        {
            "category":"Banks & Credit Unions",
            "subcategory":"Investment Brokerage",
            "type":"Services"
        }
    ],
    "sg:phone":"+41 24 423 96 01",
    "sg:postcode":"1400",
    "sg:province":"Vaud",
    "sg:tags":[
        "ceiling",
        "covering"
    ],
    "wof:name":"Clipso S.a.",
    "wof:placetype":"venue"
},
  "geometry": {"coordinates":[6.646473,46.76495],"type":"Point"}
}