{
  "type": "Feature",
  "properties": {
    "iso:country":"CH",
    "sg:address":"Via Pioda 12 6900 Lugano. Postfach",
    "sg:city":"Lugano",
    "sg:orig_category":"Unternehmensberatung Wirtschaftspr\u00fcfung, Steuerberatung U Treuhand",
    "sg:phone":"+41 22 849 83 40",
    "sg:postcode":"6901",
    "sg:province":"Ticino",
    "wof:name":"Ilex Trust Services Sa",
    "wof:placetype":"venue"
},
  "geometry": {"coordinates":[6.1558041573,46.2019233704],"type":"Point"}
}