{
  "type": "Feature",
  "properties": {
    "iso:country":"CH",
    "sg:address":"Zugerstrasse",
    "sg:city":"Baar",
    "sg:orig_category":"Kauf U Verkauf von Immobilien auf eigene Rechnung",
    "sg:postcode":"6340",
    "sg:province":"Zug",
    "wof:name":"Spisa Immobilien Ag",
    "wof:placetype":"venue"
},
  "geometry": {"coordinates":[8.4423046112,47.4186325073],"type":"Point"}
}