{
  "type": "Feature",
  "properties": {
    "addr:full":"Rue De La Poste 1926 Fully Case Postale 51 Fully Valais 1926",
    "addr:postcode":"1926;51;1926",
    "addr:street":"Rue De La Poste;Postale",
    "iso:country":"CH",
    "sg:address":"Rue De La Poste 1926 Fully Case Postale 51",
    "sg:city":"Fully",
    "sg:orig_category":"Detailhandel mit Brot, Back U S\u00fcsswaren",
    "sg:phone":"+41 27 746 29 66",
    "sg:postcode":"1926",
    "sg:province":"Valais",
    "wof:name":"Constantin Ren\u00e9.",
    "wof:placetype":"venue"
},
  "geometry": {"coordinates":[7.114775,46.137726],"type":"Point"}
}