{
  "type": "Feature",
  "properties": {
    "iso:country":"CH",
    "sg:address":"6340 Baar. Postfach",
    "sg:city":"Baar",
    "sg:orig_category":"Detailhandel mit Uhren U Schmuck Reparatur von Uhren U Schmuck",
    "sg:phone":"+41 41 756 01 34",
    "sg:postcode":"6342",
    "sg:province":"Zug",
    "wof:name":"Bruno Kobler Goldschmied, Silberschmied",
    "wof:placetype":"venue"
},
  "geometry": {"coordinates":[8.5406503677,47.1973190308],"type":"Point"}
}