{
  "type": "Feature",
  "properties": {
    "iso:country":"CH",
    "sg:address":"Gutenbergstrasse 25",
    "sg:city":"Bern",
    "sg:orig_category":"Datenbanken",
    "sg:phone":"+41 79 334 30 50",
    "sg:postcode":"3011",
    "sg:province":"Bern",
    "wof:name":"E-markt Consulting Wyser Dr. Beat D.",
    "wof:placetype":"venue"
},
  "geometry": {"coordinates":[7.43507,46.944153],"type":"Point"}
}