{
  "type": "Feature",
  "properties": {
    "addr:full":"Mattenhofstrasse 42 Bern Bern 3007",
    "addr:housenumber":"42",
    "addr:postcode":"3007",
    "addr:street":"Mattenhofstrasse",
    "iso:country":"CH",
    "sg:address":"Mattenhofstrasse 42",
    "sg:city":"Bern",
    "sg:orig_category":"Bauschreinerei Innenausbau",
    "sg:phone":"+41 19324042",
    "sg:postcode":"3007",
    "sg:province":"Bern",
    "wof:name":"Schreinerei Gubler Gmbh",
    "wof:placetype":"venue"
},
  "geometry": {"coordinates":[8.783534,47.329449],"type":"Point"}
}