{
  "type": "Feature",
  "properties": {
    "iso:country":"CH",
    "sg:address":"Via Galbisio 3",
    "sg:city":"Bellinzona",
    "sg:classifiers":[
        {
            "category":"Restaurant",
            "type":"Food & Drink"
        }
    ],
    "sg:phone":"+41 91 825 40 97",
    "sg:postcode":"6503",
    "sg:province":"Ticino",
    "wof:name":"Grotto Del Nando",
    "wof:placetype":"venue"
},
  "geometry": {"coordinates":[9.0150880814,46.203414917],"type":"Point"}
}