{
  "type": "Feature",
  "properties": {
    "iso:country":"CH",
    "sg:address":"Lavizzari Via Luigi 4",
    "sg:city":"Mendrisio",
    "sg:orig_category":"Grosshandel mit chemischen Erzeugnissen",
    "sg:phone":"+41 71 727 55 93",
    "sg:postcode":"6850",
    "sg:province":"Ticino",
    "wof:name":"Sfs Unimarket Ag",
    "wof:placetype":"venue"
},
  "geometry": {"coordinates":[9.6390552521,47.434009552],"type":"Point"}
}