{
  "type": "Feature",
  "properties": {
    "addr:full":"Riedikerstrasse Riedikon Z\u00fcrich 8616",
    "addr:postcode":"8616",
    "addr:street":"Riedikerstrasse",
    "iso:country":"CH",
    "sg:address":"Riedikerstrasse",
    "sg:city":"Riedikon",
    "sg:orig_category":"Chemin\u00e9e- and Ofenbau",
    "sg:phone":"+41 19413881",
    "sg:postcode":"8616",
    "sg:province":"Z\u00fcrich",
    "wof:name":"Urs Greutert Baugesch\u00e4ft Chemin\u00e9e",
    "wof:placetype":"venue"
},
  "geometry": {"coordinates":[8.710854,47.329815],"type":"Point"}
}