{
  "type": "Feature",
  "properties": {
    "iso:country":"CH",
    "sg:address":"Cantonale Via 8 6900 Lugano. Postfach",
    "sg:city":"Lugano",
    "sg:orig_category":"Finanzierungsinstitutionen",
    "sg:postcode":"6900",
    "sg:province":"Ticino",
    "wof:name":"Solid Direkt-finanztrading & Treuhand Ag Finanzdienstleistungen, Verm\u00f6gensverwaltung Usw",
    "wof:placetype":"venue"
},
  "geometry": {"coordinates":[9.376162529,47.4247741699],"type":"Point"}
}