{
  "type": "Feature",
  "properties": {
    "iso:country":"CH",
    "sg:address":"Nidereggweg 23",
    "sg:city":"Gutenswil",
    "sg:orig_category":"Grosshandel mit B\u00fcromaschinen Grosshandel mit Datenverarbeitungsger\u00e4ten",
    "sg:phone":"+41 19461083",
    "sg:postcode":"8605",
    "sg:province":"Z\u00fcrich",
    "wof:name":"Distrix Systems D\u00f6rpinghaus Peter",
    "wof:placetype":"venue"
},
  "geometry": {"coordinates":[8.7205028534,47.3857421875],"type":"Point"}
}