{
  "type": "Feature",
  "properties": {
    "iso:country":"CH",
    "sg:address":"Route Des H\u00f4tels 1884 Villars-sur-ollon Case Postale 166",
    "sg:city":"Villars-sur-ollon",
    "sg:orig_category":"Detailhandel mit Sportartikeln Fachdetailhandel in Verkaufsr\u00e4umen",
    "sg:phone":"+41 79 438 60 66",
    "sg:postcode":"1884",
    "sg:province":"Vaud",
    "wof:name":"Sport's House-villars Sa",
    "wof:placetype":"venue"
},
  "geometry": {"coordinates":[7.0569009781,46.2975578308],"type":"Point"}
}