{
  "type": "Feature",
  "properties": {
    "iso:country":"CH",
    "sg:address":"8892",
    "sg:city":"Berschis",
    "sg:orig_category":"Primarschulen",
    "sg:phone":"+41 56 634 14 64",
    "sg:postcode":"8892",
    "sg:province":"St. Gallen",
    "wof:name":"Primarschule",
    "wof:placetype":"venue"
},
  "geometry": {"coordinates":[8.4309101105,47.3179206848],"type":"Point"}
}