{
  "type": "Feature",
  "properties": {
    "iso:country":"CH",
    "sg:address":"Steinhauserstrasse 27",
    "sg:city":"Zug",
    "sg:orig_category":"Sonstige mit der Informatik verbundene T\u00e4tigkeiten",
    "sg:phone":"+41 79 400 21 07",
    "sg:postcode":"6300",
    "sg:province":"Zug",
    "wof:name":"Wolf Edv Gmbh",
    "wof:placetype":"venue"
},
  "geometry": {"coordinates":[8.4937744141,47.1836280823],"type":"Point"}
}