{
  "type": "Feature",
  "properties": {
    "addr:full":"Avenue De Villardin 7 1009 Pully. Postfach Pully Vaud 1009",
    "addr:housenumber":"7",
    "addr:postcode":"1009;postfach;1009",
    "addr:street":"Avenue De Villardin",
    "iso:country":"CH",
    "sg:address":"Avenue De Villardin 7 1009 Pully. Postfach",
    "sg:city":"Pully",
    "sg:orig_category":"Architektur U Ingenieurb\u00fcros Unternehmensberatung",
    "sg:phone":"+41 21 721 03 21",
    "sg:postcode":"1009",
    "sg:province":"Vaud",
    "wof:name":"Aldex Consulting Sa Prodiguer Des Conseils De Nature Technique, Juridique, Financi\u00e8re Etc",
    "wof:placetype":"venue"
},
  "geometry": {"coordinates":[6.654015,46.507137],"type":"Point"}
}