{
  "type": "Feature",
  "properties": {
    "iso:country":"CH",
    "sg:address":"Route De La Bruy\u00e8re",
    "sg:city":"Domdidier",
    "sg:orig_category":"Bauschreinerei Herstellung von Konstruktionsteilen, Fertigbauteilen U Ausbauelementen aus Holz",
    "sg:phone":"+41 79 434 92 20",
    "sg:postcode":"1564",
    "sg:province":"Fribourg",
    "wof:name":"Menuiserie Chardonnens S\u00e0rl",
    "wof:placetype":"venue"
},
  "geometry": {"coordinates":[7.010542,46.858402],"type":"Point"}
}