{
  "type": "Feature",
  "properties": {
    "iso:country":"CH",
    "sg:address":"Els\u00e4sserstrasse 34",
    "sg:city":"Basel",
    "sg:orig_category":"Bau U Wohngenossenschaften",
    "sg:postcode":"4056",
    "sg:province":"Basel-Stadt",
    "wof:name":"C+n Caprez+noger Beteiligungen Ag Beteiligungen, Dienstleistungen Im Bereich Administration, Organisatione Usw",
    "wof:placetype":"venue"
},
  "geometry": {"coordinates":[9.392027,47.440056],"type":"Point"}
}