{
  "type": "Feature",
  "properties": {
    "iso:country":"CH",
    "sg:address":"Mittelstrasse 20 2502 Biel/bienne. Postfach",
    "sg:city":"Biel/bienne",
    "sg:orig_category":"Herstellung von Uhren",
    "sg:phone":"+41 32 341 34 62",
    "sg:postcode":"2502",
    "sg:province":"Bern",
    "wof:name":"Horlogerie Schilling Roland",
    "wof:placetype":"venue"
},
  "geometry": {"coordinates":[7.2503871918,47.1416397095],"type":"Point"}
}