{
  "type": "Feature",
  "properties": {
    "iso:country":"CH",
    "sg:address":"Harderstrasse 25 3800 Interlaken. Postfach 524",
    "sg:city":"Interlaken",
    "sg:orig_category":"Instandhaltung U Reparatur von Automobilen Vermietung von Automobilen",
    "sg:phone":"+41 33 822 36 51",
    "sg:postcode":"3800",
    "sg:province":"Bern",
    "wof:name":"Ad-hardergarage Gmbh",
    "wof:placetype":"venue"
},
  "geometry": {"coordinates":[7.855038166,46.6874694824],"type":"Point"}
}