{
  "type": "Feature",
  "properties": {
    "iso:country":"CH",
    "sg:address":"Route D'yverdon 7",
    "sg:city":"Cheseaux-lausanne",
    "sg:orig_category":"Stukkateurgewerbe, Gipserei U Verputzerei",
    "sg:phone":"+41 32 968 55 28",
    "sg:postcode":"1033",
    "sg:province":"Vaud",
    "wof:name":"Martinelli, Jean-pierre.",
    "wof:placetype":"venue"
},
  "geometry": {"coordinates":[6.8226251602,47.1105995178],"type":"Point"}
}