{
  "type": "Feature",
  "properties": {
    "iso:country":"CH",
    "sg:address":"Waisenhausstrasse 3",
    "sg:city":"St.gallen",
    "sg:orig_category":"Detailhandel mit fotografischen Artikeln Fachdetailhandel in Verkaufsr\u00e4umen",
    "sg:phone":"+41 71 222 86 90",
    "sg:postcode":"9000",
    "sg:province":"St. Gallen",
    "wof:name":"Foto Lautenschlager + Co",
    "wof:placetype":"venue"
},
  "geometry": {"coordinates":[9.3732376099,47.4242210388],"type":"Point"}
}