{
  "type": "Feature",
  "properties": {
    "iso:country":"CH",
    "sg:address":"Oberdorfstrasse 6",
    "sg:city":"Opfikon",
    "sg:orig_category":"Fassadenbau Maurerarbeiten",
    "sg:phone":"+41 21 652 83 25",
    "sg:postcode":"8152",
    "sg:province":"Z\u00fcrich",
    "wof:name":"Genibat Sa Entreprise De Construction",
    "wof:placetype":"venue"
},
  "geometry": {"coordinates":[6.6540660858,46.5331954956],"type":"Point"}
}