{
  "type": "Feature",
  "properties": {
    "iso:country":"CH",
    "sg:address":"Allmendstrasse 1",
    "sg:city":"Sachseln",
    "sg:classifiers":[
        {
            "category":"Home & Garden",
            "subcategory":"Home Furnishings",
            "type":"Retail Goods"
        }
    ],
    "sg:phone":"+41 41 666 26 66",
    "sg:postcode":"6072",
    "sg:province":"Obwalden",
    "sg:tags":[
        "bathroom",
        "wc",
        "fitting"
    ],
    "wof:name":"Reinhard Ag",
    "wof:placetype":"venue"
},
  "geometry": {"coordinates":[8.24257,46.871387],"type":"Point"}
}