{
  "type": "Feature",
  "properties": {
    "iso:country":"CH",
    "sg:address":"Litternaweg",
    "sg:city":"Visp",
    "sg:orig_category":"Eisbahnen and Eissportpl\u00e4tze",
    "sg:phone":"+41 19323504",
    "sg:postcode":"3930",
    "sg:province":"Valais",
    "wof:name":"Kunsteisbahn Wetzikon Ag",
    "wof:placetype":"venue"
},
  "geometry": {"coordinates":[8.7989912033,47.3155708313],"type":"Point"}
}