{
  "type": "Feature",
  "properties": {
    "iso:country":"CH",
    "sg:address":"6678",
    "sg:city":"Lodano",
    "sg:orig_category":"Vereine Geselligkeit",
    "sg:postcode":"6678",
    "sg:province":"Ticino",
    "wof:name":"Gruppo Ricreativo Lodano",
    "wof:placetype":"venue"
},
  "geometry": {"coordinates":[8.6857700348,46.2593688965],"type":"Point"}
}