{
  "type": "Feature",
  "properties": {
    "iso:country":"CH",
    "sg:address":"Oberebenestr. 67",
    "sg:city":"Bremgarten",
    "sg:classifiers":[
        {
            "category":"Manufacturing",
            "subcategory":"Metals",
            "type":"Manufacturing & Wholesale Goods"
        }
    ],
    "sg:phone":"+41 56 633 66 88",
    "sg:postcode":"5620",
    "sg:province":"Aargau",
    "sg:tags":[
        "-",
        "machine",
        "equipment",
        "engineering",
        "machinery",
        "mechanical"
    ],
    "wof:name":"Stim-wermag Werkzeugmaschinen Ag",
    "wof:placetype":"venue"
},
  "geometry": {"coordinates":[8.3263607025,47.3529205322],"type":"Point"}
}