{
  "type": "Feature",
  "properties": {
    "addr:full":"Wiesengrundweg 21 Nesselnbach Aargau 5524",
    "addr:housenumber":"21",
    "addr:postcode":"5524",
    "addr:street":"Wiesengrundweg",
    "iso:country":"CH",
    "sg:address":"Wiesengrundweg 21",
    "sg:city":"Nesselnbach",
    "sg:orig_category":"Bauschreinerei Einbau von Schreinerwaren",
    "sg:phone":"+41 56 496 46 69",
    "sg:postcode":"5524",
    "sg:province":"Aargau",
    "wof:name":"Werner Fischer Schreinerei",
    "wof:placetype":"venue"
},
  "geometry": {"coordinates":[8.293582,47.387997],"type":"Point"}
}