{
  "type": "Feature",
  "properties": {
    "iso:country":"CH",
    "sg:address":"Falkensteinerstrasse 54",
    "sg:city":"Basel",
    "sg:orig_category":"Werbeagenturen Werbung",
    "sg:phone":"+41 62 823 39 01",
    "sg:postcode":"4053",
    "sg:province":"Basel-Stadt",
    "wof:name":"Creativ Work Gmbh Direct- U. Eventmarketing, Bes. Veranstaltung Von Promotions- U. Unterhaltungsanl\u00e4ssen Usw",
    "wof:placetype":"venue"
},
  "geometry": {"coordinates":[8.0687828064,47.4019966125],"type":"Point"}
}