{
  "type": "Feature",
  "properties": {
    "iso:country":"CH",
    "sg:address":"Lurweid 11 8132 Egg B. Z\u00fcrich. Postfach",
    "sg:city":"Esslingen",
    "sg:orig_category":"Haltung von Rindern",
    "sg:postcode":"8133",
    "sg:province":"Z\u00fcrich",
    "wof:name":"Holstein's Z\u00fcrcher-oberland Vzg",
    "wof:placetype":"venue"
},
  "geometry": {"coordinates":[8.6900548935,47.3005561829],"type":"Point"}
}