{
  "type": "Feature",
  "properties": {
    "iso:country":"CH",
    "sg:address":"Baarermattstrasse 10 6300 Zug. Postfach 2254",
    "sg:city":"Zug",
    "sg:orig_category":"Grosshandel mit B\u00fcromaschinen Grosshandel mit Datenverarbeitungsger\u00e4ten",
    "sg:phone":"+41 41 760 26 26",
    "sg:postcode":"6302",
    "sg:province":"Zug",
    "wof:name":"Mtf Baar Ag",
    "wof:placetype":"venue"
},
  "geometry": {"coordinates":[8.5264101028,47.1817588806],"type":"Point"}
}