{
  "type": "Feature",
  "properties": {
    "iso:country":"CH",
    "sg:address":"Neuenburgerstr. 19",
    "sg:city":"Gampelen",
    "sg:orig_category":"Instandhaltung U Reparatur von Automobilen",
    "sg:phone":"+41 32 313 17 54",
    "sg:postcode":"3236",
    "sg:province":"Bern",
    "wof:name":"Hasler Stefan",
    "wof:placetype":"venue"
},
  "geometry": {"coordinates":[7.0546908379,47.01537323],"type":"Point"}
}