{
  "type": "Feature",
  "properties": {
    "iso:country":"CH",
    "sg:address":"Chavannes Centre",
    "sg:city":"Chavannes-de-bogis",
    "sg:orig_category":"Detailhandel mit Bekleidung",
    "sg:postcode":"1279",
    "sg:province":"Vaud",
    "wof:name":"Mr. Xxl Ag",
    "wof:placetype":"venue"
},
  "geometry": {"coordinates":[9.373715,47.426392],"type":"Point"}
}