{
  "type": "Feature",
  "properties": {
    "iso:country":"CH",
    "sg:address":"Oberhardstrasse 31",
    "sg:city":"Langenthal",
    "sg:orig_category":"Vereine Hundedressur",
    "sg:postcode":"4900",
    "sg:province":"Bern",
    "wof:name":"Schweiz.shetland-sheepdog-club",
    "wof:placetype":"venue"
},
  "geometry": {"coordinates":[7.776995182,47.2174453735],"type":"Point"}
}