{
  "type": "Feature",
  "properties": {
    "iso:country":"CH",
    "sg:address":"Ausserdorf",
    "sg:city":"Mosnang",
    "sg:classifiers":[
        {
            "category":"Banks & Credit Unions",
            "subcategory":"Bank",
            "type":"Services"
        }
    ],
    "sg:phone":"+41 71 414 01 81",
    "sg:postcode":"9607",
    "sg:province":"St. Gallen",
    "wof:name":"Raiffeisenbank Muolen",
    "wof:placetype":"venue"
},
  "geometry": {"coordinates":[9.32687,47.519661],"type":"Point"}
}