{
  "type": "Feature",
  "properties": {
    "iso:country":"CH",
    "sg:address":"Rue Du Bourg 17",
    "sg:city":"Sierre",
    "sg:classifiers":[
        {
            "category":"Travel",
            "subcategory":"Hotels & Motels",
            "type":"Entertainment"
        }
    ],
    "sg:phone":"+41 27 455 15 67",
    "sg:postcode":"3960",
    "sg:province":"Valais",
    "sg:tags":[
        "hotels",
        "mit",
        "restaurant"
    ],
    "wof:name":"Berclaz Georges.",
    "wof:placetype":"venue"
},
  "geometry": {"coordinates":[7.5338339806,46.2934684753],"type":"Point"}
}