{
  "type": "Feature",
  "properties": {
    "iso:country":"CH",
    "sg:address":"Obermattweg 82",
    "sg:city":"H\u00e4felfingen",
    "sg:orig_category":"Architektur U Ingenieurb\u00fcros",
    "sg:postcode":"4445",
    "sg:province":"Basel-Landschaft",
    "wof:name":"Architekturb\u00fcro Fiechter Hanspeter",
    "wof:placetype":"venue"
},
  "geometry": {"coordinates":[7.863732,47.414352],"type":"Point"}
}