{
  "type": "Feature",
  "properties": {
    "iso:country":"CH",
    "sg:address":"Schulhaus Imbach",
    "sg:city":"W\u00e4ngi",
    "sg:classifiers":[
        {
            "category":"Education",
            "subcategory":"Library",
            "type":"Public Place"
        }
    ],
    "sg:postcode":"9545",
    "sg:province":"Thurgau",
    "sg:tags":[
        "u",
        "bibliotheken",
        "archive"
    ],
    "wof:name":"Gemeindebibliothek",
    "wof:placetype":"venue"
},
  "geometry": {"coordinates":[7.501605,47.23064],"type":"Point"}
}