{
  "type": "Feature",
  "properties": {
    "addr:full":"Aescherstrasse Fahrwangen Aargau 5615",
    "addr:postcode":"5615",
    "addr:street":"Aescherstrasse",
    "iso:country":"CH",
    "sg:address":"Aescherstrasse",
    "sg:city":"Fahrwangen",
    "sg:orig_category":"Bezirks, Sekundar, Realschulen, Oberstufe der Primarschulen",
    "sg:phone":"+41 56 667 13 73",
    "sg:postcode":"5615",
    "sg:province":"Aargau",
    "wof:name":"Bezirksschule",
    "wof:placetype":"venue"
},
  "geometry": {"coordinates":[8.24122,47.294315],"type":"Point"}
}