{
  "type": "Feature",
  "properties": {
    "iso:country":"CH",
    "sg:address":"Z\u00fcrichstrasse 63",
    "sg:city":"Luzern",
    "sg:orig_category":"Detailhandel mit Damenbekleidung",
    "sg:phone":"+41 41 410 11 15",
    "sg:postcode":"6004",
    "sg:province":"Luzern",
    "wof:name":"Al Secondo Kleiderb\u00f6rse",
    "wof:placetype":"venue"
},
  "geometry": {"coordinates":[8.309113,47.059452],"type":"Point"}
}