{
  "type": "Feature",
  "properties": {
    "iso:country":"CH",
    "sg:address":"Rue De Morat 16",
    "sg:city":"Fribourg",
    "sg:orig_category":"Wohnheime",
    "sg:phone":"+41 26 347 23 40",
    "sg:postcode":"1700",
    "sg:province":"Fribourg",
    "wof:name":"Monast\u00e8re De La Visitation",
    "wof:placetype":"venue"
},
  "geometry": {"coordinates":[7.1536831856,46.8037452698],"type":"Point"}
}