{
  "type": "Feature",
  "properties": {
    "addr:full":"Grange-canal Chemin De 24 C Ch\u00eane-bougeries Gen\u00e8ve 1224",
    "addr:housenumber":"24 c",
    "addr:postcode":"1224",
    "addr:street":"Chemin De",
    "iso:country":"CH",
    "sg:address":"Grange-canal Chemin De 24 C",
    "sg:city":"Ch\u00eane-bougeries",
    "sg:orig_category":"Detailhandel mit Antiquit\u00e4ten U Gebrauchtwaren in Verkaufsr\u00e4umen",
    "sg:postcode":"1224",
    "sg:province":"Gen\u00e8ve",
    "wof:name":"Testori Brocus",
    "wof:placetype":"venue"
},
  "geometry": {"coordinates":[6.187205,46.197926],"type":"Point"}
}