{
  "type": "Feature",
  "properties": {
    "addr:full":"Birmannsgasse 8 Basel Basel-Stadt 4009",
    "addr:housenumber":"8",
    "addr:postcode":"4009",
    "addr:street":"Birmannsgasse",
    "iso:country":"CH",
    "sg:address":"Birmannsgasse 8",
    "sg:city":"Basel",
    "sg:classifiers":[
        {
            "category":"Professional",
            "subcategory":"Detective & Security Services",
            "type":"Services"
        }
    ],
    "sg:phone":"+41 61 264 10 10",
    "sg:postcode":"4009",
    "sg:province":"Basel-Stadt",
    "sg:tags":[
        "alarm"
    ],
    "wof:name":"Sibalco W. Siegrist & Co. Ag",
    "wof:placetype":"venue"
},
  "geometry": {"coordinates":[7.578523,47.558224],"type":"Point"}
}