{
  "type": "Feature",
  "properties": {
    "iso:country":"CH",
    "sg:address":"5625",
    "sg:city":"Kallern",
    "sg:orig_category":"RESTAURANTS: TEA-ROOMS",
    "sg:phone":"+41 56 666 12 25",
    "sg:postcode":"5625",
    "sg:province":"Aargau",
    "wof:name":"Restaurant J\u00e4gerst\u00fcbli",
    "wof:placetype":"venue"
},
  "geometry": {"coordinates":[8.2949552536,47.3177261353],"type":"Point"}
}