{
  "type": "Feature",
  "properties": {
    "iso:country":"CH",
    "sg:address":"Pestalozzistrasse 15",
    "sg:city":"Windisch",
    "sg:orig_category":"Grosshandel mit Datenverarbeitungsger\u00e4ten Grosshandel mit Software",
    "sg:phone":"+41 56 451 10 35",
    "sg:postcode":"5210",
    "sg:province":"Aargau",
    "wof:name":"I.p.s Gmbh",
    "wof:placetype":"venue"
},
  "geometry": {"coordinates":[8.2140836716,47.471534729],"type":"Point"}
}