{
  "type": "Feature",
  "properties": {
    "iso:country":"CH",
    "sg:address":"Veilchenweg 8",
    "sg:city":"Bern",
    "sg:orig_category":"Herstellung von Metallkonstruktionen Schlossereien",
    "sg:phone":"+41 31 992 14 59",
    "sg:postcode":"3018",
    "sg:province":"Bern",
    "wof:name":"Fritz Thomann Schlosserei Metallbau",
    "wof:placetype":"venue"
},
  "geometry": {"coordinates":[7.3903031349,46.9423408508],"type":"Point"}
}