{
  "type": "Feature",
  "properties": {
    "addr:full":"Tafletenstrasse 15 Buttikon Schwyz 8863",
    "addr:housenumber":"15",
    "addr:postcode":"8863",
    "addr:street":"Tafletenstrasse;Schwyz",
    "iso:country":"CH",
    "sg:address":"Tafletenstrasse 15",
    "sg:city":"Buttikon",
    "sg:classifiers":[
        {
            "category":"Banks & Credit Unions",
            "subcategory":"Bank",
            "type":"Services"
        }
    ],
    "sg:phone":"+41 4155671776",
    "sg:postcode":"8863",
    "sg:province":"Schwyz",
    "wof:name":"Schweiz. National",
    "wof:placetype":"venue"
},
  "geometry": {"coordinates":[8.955879,47.172348],"type":"Point"}
}