{
  "type": "Feature",
  "properties": {
    "iso:country":"CH",
    "sg:address":"Feldeggstrasse",
    "sg:city":"Romanshorn",
    "sg:orig_category":"Druck ohne Zeitungsdruck",
    "sg:phone":"+41 56 622 80 00",
    "sg:postcode":"8590",
    "sg:province":"Thurgau",
    "wof:name":"Hutter Siebdruck Ag",
    "wof:placetype":"venue"
},
  "geometry": {"coordinates":[8.2700939178,47.3547363281],"type":"Point"}
}