{
  "type": "Feature",
  "properties": {
    "iso:country":"CH",
    "sg:address":"Pilatusstrasse 18",
    "sg:city":"Luzern",
    "sg:orig_category":"Detailhandel mit Antiquit\u00e4ten U Gebrauchtwaren in Verkaufsr\u00e4umen",
    "sg:postcode":"6003",
    "sg:province":"Luzern",
    "wof:name":"Gest Ag",
    "wof:placetype":"venue"
},
  "geometry": {"coordinates":[8.305908,47.048767],"type":"Point"}
}