{
  "type": "Feature",
  "properties": {
    "iso:country":"CH",
    "sg:address":"Bleumattstrasse 11 6233 B\u00fcron. Postfach 165",
    "sg:city":"B\u00fcron",
    "sg:orig_category":"Allgemeiner Hoch U Tiefbau Allgemeiner Hochbau",
    "sg:phone":"+41 41 933 10 55",
    "sg:postcode":"6233",
    "sg:province":"Luzern",
    "wof:name":"Waller Ag",
    "wof:placetype":"venue"
},
  "geometry": {"coordinates":[8.098513,47.213982],"type":"Point"}
}