{
  "type": "Feature",
  "properties": {
    "iso:country":"CH",
    "sg:address":"Poststrasse 7",
    "sg:city":"Uster",
    "sg:orig_category":"P\u00e9dicure",
    "sg:phone":"+41 19404893",
    "sg:postcode":"8610",
    "sg:province":"Z\u00fcrich",
    "wof:name":"Monika Amrhein Pedicure",
    "wof:placetype":"venue"
},
  "geometry": {"coordinates":[8.7176418304,47.3493537903],"type":"Point"}
}