{
  "type": "Feature",
  "properties": {
    "iso:country":"CH",
    "sg:address":"1040",
    "sg:city":"Villars-le-terroir",
    "sg:orig_category":"Sportvereine Ballsport Fussball",
    "sg:phone":"+41 21 881 25 46",
    "sg:postcode":"1040",
    "sg:province":"Vaud",
    "wof:name":"Fc Villars-le-terroir",
    "wof:placetype":"venue"
},
  "geometry": {"coordinates":[6.638879776,46.6560058594],"type":"Point"}
}