{
  "type": "Feature",
  "properties": {
    "iso:country":"CH",
    "sg:address":"Rue Du Grand-pont 5 1003 Lausanne. Postfach",
    "sg:city":"Lausanne",
    "sg:orig_category":"Detailhandel mit Radio U Fernsehger\u00e4ten Herstellung von Radio U Fernsehger\u00e4ten sowie phono U videote",
    "sg:phone":"+41 71 970 04 70",
    "sg:postcode":"1002",
    "sg:province":"Vaud",
    "wof:name":"Rfs Radio-foto-shop Eschlikon Ag",
    "wof:placetype":"venue"
},
  "geometry": {"coordinates":[8.963092804,47.4629974365],"type":"Point"}
}