{
  "type": "Feature",
  "properties": {
    "iso:country":"CH",
    "sg:address":"Via Bossi 12",
    "sg:city":"Chiasso",
    "sg:orig_category":"Elektro- and elektronische Maschinen Grosshandel Handelsvermittlung von Maschinen, technischem Bedar",
    "sg:phone":"+41 91 697 63 33",
    "sg:postcode":"6830",
    "sg:province":"Ticino",
    "wof:name":"B.t.r. Bureau Torre Rappresentanze Sagl",
    "wof:placetype":"venue"
},
  "geometry": {"coordinates":[9.0314903259,45.8346862793],"type":"Point"}
}