{
  "type": "Feature",
  "properties": {
    "iso:country":"CH",
    "sg:address":"B\u00e4renacker 4",
    "sg:city":"Beringen",
    "sg:orig_category":"Bauschreinerei Herstellung von Konstruktionsteilen, Fertigbauteilen U Ausbauelementen aus Holz",
    "sg:phone":"+41 52 685 11 96",
    "sg:postcode":"8222",
    "sg:province":"Schaffhausen",
    "wof:name":"Bollinger Schreinerei Ag",
    "wof:placetype":"venue"
},
  "geometry": {"coordinates":[8.572025,47.697502],"type":"Point"}
}