{
  "type": "Feature",
  "properties": {
    "iso:country":"CH",
    "sg:address":"Hauptstrasse 6",
    "sg:city":"Lostorf",
    "sg:orig_category":"Autogaragen",
    "sg:phone":"+41 62 298 25 62",
    "sg:postcode":"4654",
    "sg:province":"Solothurn",
    "wof:name":"Peter Peier Garage Pneu-service",
    "wof:placetype":"venue"
},
  "geometry": {"coordinates":[7.948748,47.37727],"type":"Point"}
}