{
  "type": "Feature",
  "properties": {
    "iso:country":"CH",
    "sg:address":"Fellenr\u00fcti-fach 100",
    "sg:city":"Engelberg",
    "sg:orig_category":"Non-Classified Establishments",
    "sg:postcode":"6390",
    "sg:province":"Obwalden",
    "wof:name":"Ebag Engelberg Ag",
    "wof:placetype":"venue"
},
  "geometry": {"coordinates":[8.3983373642,46.8269386292],"type":"Point"}
}