{
  "type": "Feature",
  "properties": {
    "iso:country":"CH",
    "sg:address":"Marktgasse 24 4310 Rheinfelden. Postfach",
    "sg:city":"Rheinfelden",
    "sg:orig_category":"Detailhandel mit Uhren U Schmuck Reparatur von Uhren U Schmuck",
    "sg:phone":"+41 61 831 50 10",
    "sg:postcode":"4310",
    "sg:province":"Aargau",
    "wof:name":"Johann Frey Ag Optik Uhren Bijouterie",
    "wof:placetype":"venue"
},
  "geometry": {"coordinates":[7.792825222,47.5553627014],"type":"Point"}
}