{
  "type": "Feature",
  "properties": {
    "iso:country":"CH",
    "sg:address":"In Der Bettenen 2",
    "sg:city":"Feldmeilen",
    "sg:orig_category":"Herstellung von k\u00e4lte U lufttechnischen Erzeugnissen f\u00fcr gewerbliche Zwecke Pulvermetallurgie Schmie",
    "sg:phone":"+41 61 691 44 11",
    "sg:postcode":"8706",
    "sg:province":"Z\u00fcrich",
    "wof:name":"St\u00fccklin & Cie Ag",
    "wof:placetype":"venue"
},
  "geometry": {"coordinates":[6.5101180077,46.6539344788],"type":"Point"}
}