{
  "type": "Feature",
  "properties": {
    "iso:country":"CH",
    "sg:address":"Grandfey Route De 34",
    "sg:city":"Fribourg",
    "sg:orig_category":"Herstellung von Karosserien U Anh\u00e4ngern",
    "sg:phone":"+41 26 323 21 64",
    "sg:postcode":"1700",
    "sg:province":"Fribourg",
    "wof:name":"Zumwald Marcel",
    "wof:placetype":"venue"
},
  "geometry": {"coordinates":[7.160586834,46.8188858032],"type":"Point"}
}