{
  "type": "Feature",
  "properties": {
    "iso:country":"CH",
    "sg:address":"Grand-rue 36",
    "sg:city":"Freiburg",
    "sg:orig_category":"Non-Classified Establishments",
    "sg:postcode":"1700",
    "sg:province":"Fribourg",
    "wof:name":"Quartenoud Ban Thai",
    "wof:placetype":"venue"
},
  "geometry": {"coordinates":[7.1616339684,46.8041152954],"type":"Point"}
}