{
  "type": "Feature",
  "properties": {
    "iso:country":"CH",
    "sg:address":"Le Ruz 291",
    "sg:city":"Hauteville",
    "sg:orig_category":"Grosshandel mit Eisenwaren sowie Installationsbedarf f\u00fcr Gas, Wasser U Heizung",
    "sg:phone":"+41 33 951 32 72",
    "sg:postcode":"1648",
    "sg:province":"Fribourg",
    "wof:name":"Hobag Brienz Ag F\u00fcr Automatische Feuerungen Vollautomat. Feuerungen, Ger\u00e4te F\u00fcr Energienutzung Usw; Herstellung, Vertrieb",
    "wof:placetype":"venue"
},
  "geometry": {"coordinates":[8.0603904724,46.7495765686],"type":"Point"}
}