{
  "type": "Feature",
  "properties": {
    "addr:full":"Casin\u00f2 Viale Al 6865 Tremona. Postfach Tremona Ticino 6865",
    "addr:housenumber":"6865",
    "addr:postcode":"tremona.;6865",
    "addr:street":"Viale Al",
    "iso:country":"CH",
    "sg:address":"Casin\u00f2 Viale Al 6865 Tremona. Postfach",
    "sg:city":"Tremona",
    "sg:orig_category":"Detailhandel mit Bekleidung",
    "sg:phone":"+41 91 640 95 05",
    "sg:postcode":"6865",
    "sg:province":"Ticino",
    "wof:name":"Joshoop Sagl Abbigliamento E Prodotti Affini; Acquisto, Vendita Ecc",
    "wof:placetype":"venue"
},
  "geometry": {"coordinates":[8.95786,45.881207],"type":"Point"}
}