{
  "type": "Feature",
  "properties": {
    "iso:country":"CH",
    "sg:address":"Bahnhofstrasse 4",
    "sg:city":"Feldbach",
    "sg:orig_category":"Datenverarbeitungsdienste Sonstige mit der Informatik verbundene T\u00e4tigkeiten",
    "sg:phone":"+41 55 244 43 58",
    "sg:postcode":"8714",
    "sg:province":"Z\u00fcrich",
    "wof:name":"Syrocom Edv-betriebsorganisation Rohner Walter",
    "wof:placetype":"venue"
},
  "geometry": {"coordinates":[8.785732,47.239685],"type":"Point"}
}