{
  "type": "Feature",
  "properties": {
    "iso:country":"CH",
    "sg:address":"F\u00fcsslistrasse 4",
    "sg:city":"Z\u00fcrich",
    "sg:orig_category":"Grosshandel mit Radio U Fernsehger\u00e4ten Vermietung von Gebrauchsg\u00fctern",
    "sg:phone":"+41 12213737",
    "sg:postcode":"8001",
    "sg:province":"Z\u00fcrich",
    "wof:name":"Hitz Thomas Ag",
    "wof:placetype":"venue"
},
  "geometry": {"coordinates":[8.5372571945,47.3732757568],"type":"Point"}
}