{
  "type": "Feature",
  "properties": {
    "iso:country":"CH",
    "sg:address":"Adligenswilerstrasse 29/22",
    "sg:city":"Luzern",
    "sg:orig_category":"Pensionskassen",
    "sg:postcode":"6006",
    "sg:province":"Luzern",
    "wof:name":"Altersgeldkasse Der Hotel & Gastro Union",
    "wof:placetype":"venue"
},
  "geometry": {"coordinates":[8.3189973831,47.0566177368],"type":"Point"}
}