{
  "type": "Feature",
  "properties": {
    "iso:country":"CH",
    "sg:address":"Landstrasse 36/38",
    "sg:city":"Schaan",
    "sg:classifiers":[
        {
            "category":"Banks & Credit Unions",
            "subcategory":"Bank",
            "type":"Services"
        }
    ],
    "sg:phone":"+41 75 236 99 11",
    "sg:postcode":"9494",
    "wof:name":"Liechtensteinische, Landesbank Ag",
    "wof:placetype":"venue"
},
  "geometry": {"coordinates":[9.5086,47.165016],"type":"Point"}
}