{
  "type": "Feature",
  "properties": {
    "iso:country":"CH",
    "sg:address":"Steinstrasse 72",
    "sg:city":"R\u00fctihof",
    "sg:orig_category":"Gem\u00fcsebau",
    "sg:phone":"+41 56 493 11 12",
    "sg:postcode":"5406",
    "sg:province":"Aargau",
    "wof:name":"Paul & Ruedi Meier Gem\u00fcsebau",
    "wof:placetype":"venue"
},
  "geometry": {"coordinates":[8.2654151917,47.4345855713],"type":"Point"}
}