{
  "type": "Feature",
  "properties": {
    "iso:country":"CH",
    "sg:address":"Route De France",
    "sg:city":"Morgins",
    "sg:orig_category":"Architekturb\u00fcros",
    "sg:phone":"+41 24 477 63 16",
    "sg:postcode":"1875",
    "sg:province":"Valais",
    "wof:name":"Jean-charles Domenge-vieu Immo-concept",
    "wof:placetype":"venue"
},
  "geometry": {"coordinates":[6.850763,46.243599],"type":"Point"}
}