{
  "type": "Feature",
  "properties": {
    "iso:country":"CH",
    "sg:address":"Chuematt 3 6072 Sachseln. Postfach 19",
    "sg:city":"Sachseln",
    "sg:orig_category":"Sanit\u00e4r, Heizungs U L\u00fcftungsinstallation Schlossereien",
    "sg:phone":"+41 41 660 12 51",
    "sg:postcode":"6072",
    "sg:province":"Obwalden",
    "wof:name":"Von Moos J. Sanit\u00e4r Ag",
    "wof:placetype":"venue"
},
  "geometry": {"coordinates":[8.2413244247,46.8689537048],"type":"Point"}
}