{
  "type": "Feature",
  "properties": {
    "iso:country":"CH",
    "sg:address":"8868",
    "sg:city":"Oberurnen",
    "sg:orig_category":"Primarschulen",
    "sg:postcode":"8868",
    "sg:province":"Glarus",
    "wof:name":"Primarschule Rauti",
    "wof:placetype":"venue"
},
  "geometry": {"coordinates":[9.0593395233,47.1152076721],"type":"Point"}
}