{
  "type": "Feature",
  "properties": {
    "iso:country":"CH",
    "sg:address":"Neugasse 52 8005 Z\u00fcrich. Postfach 3165",
    "sg:city":"Z\u00fcrich",
    "sg:orig_category":"Herstellung von Tanks U Sammelbeh\u00e4ltern aus Metall",
    "sg:phone":"+41 26 912 35 39",
    "sg:postcode":"8031",
    "sg:province":"Z\u00fcrich",
    "wof:name":"Krummenacher-helvecit Sa Revision De Citernes",
    "wof:placetype":"venue"
},
  "geometry": {"coordinates":[7.0555691719,46.6174583435],"type":"Point"}
}