{
  "type": "Feature",
  "properties": {
    "iso:country":"CH",
    "sg:address":"Aux Tuileries De Grandson 1422 Grandson. Postfach",
    "sg:city":"Grandson",
    "sg:orig_category":"Elektroinstallation",
    "sg:postcode":"1422",
    "sg:province":"Vaud",
    "wof:name":"Laussueur Gilbert",
    "wof:placetype":"venue"
},
  "geometry": {"coordinates":[6.6459851265,46.8093681335],"type":"Point"}
}