{
  "type": "Feature",
  "properties": {
    "iso:country":"CH",
    "sg:address":"Rue John-grasset 9",
    "sg:city":"Gen\u00e8ve",
    "sg:classifiers":[
        {
            "category":"Restaurant",
            "type":"Food & Drink"
        }
    ],
    "sg:phone":"+41 22 329 94 49",
    "sg:postcode":"1205",
    "sg:province":"Gen\u00e8ve",
    "wof:name":"Brasserie L'acluse",
    "wof:placetype":"venue"
},
  "geometry": {"coordinates":[6.1457118988,46.1911430359],"type":"Point"}
}