{
  "type": "Feature",
  "properties": {
    "iso:country":"CH",
    "sg:address":"Beckenhofstrasse 35 8001 Z\u00fcrich. Postfach",
    "sg:city":"Adliswil",
    "sg:orig_category":"Sonstige mit Sport verbundene T\u00e4tigkeiten",
    "sg:phone":"+41 21 311 26 90",
    "sg:postcode":"8134",
    "sg:province":"Z\u00fcrich",
    "wof:name":"Zmc Amicitia Z\u00fcrich",
    "wof:placetype":"venue"
},
  "geometry": {"coordinates":[8.541261673,47.3849830627],"type":"Point"}
}