{
  "type": "Feature",
  "properties": {
    "iso:country":"CH",
    "sg:address":"Breitlandstrasse 1",
    "sg:city":"Geroldswil",
    "sg:orig_category":"Markt U Meinungsforschung",
    "sg:postcode":"8954",
    "sg:province":"Z\u00fcrich",
    "wof:name":"Jub Marketing Ig, Br\u00f6nimann Ulrich",
    "wof:placetype":"venue"
},
  "geometry": {"coordinates":[8.4100513458,47.4247093201],"type":"Point"}
}