{
  "type": "Feature",
  "properties": {
    "iso:country":"CH",
    "sg:address":"Hauptstr. 4",
    "sg:city":"Kriegstetten",
    "sg:orig_category":"G\u00fcterbef\u00f6rderung im Strassenverkehr",
    "sg:postcode":"4566",
    "sg:province":"Solothurn",
    "wof:name":"Anderegg Michael",
    "wof:placetype":"venue"
},
  "geometry": {"coordinates":[7.5962147713,47.1807975769],"type":"Point"}
}