{
  "type": "Feature",
  "properties": {
    "iso:country":"CH",
    "sg:address":"Spitalstrasse 8",
    "sg:city":"Basel",
    "sg:orig_category":"Architektur U Ingenieurb\u00fcros Architekturb\u00fcros",
    "sg:phone":"+41 61 269 95 45",
    "sg:postcode":"4056",
    "sg:province":"Basel-Stadt",
    "wof:name":"Morger & Degelo Ag",
    "wof:placetype":"venue"
},
  "geometry": {"coordinates":[7.584357,47.562279],"type":"Point"}
}