{
  "type": "Feature",
  "properties": {
    "iso:country":"CH",
    "sg:address":"B\u00f6sgasse 6",
    "sg:city":"Seengen",
    "sg:orig_category":"Unclassifiable Establishments",
    "sg:postcode":"5707",
    "sg:province":"Aargau",
    "wof:name":"Sd Shop Service Ag",
    "wof:placetype":"venue"
},
  "geometry": {"coordinates":[8.2100353241,47.3219146729],"type":"Point"}
}