{
  "type": "Feature",
  "properties": {
    "iso:country":"CH",
    "sg:address":"Kirchstr. 17 9425 Thal. Postfach",
    "sg:city":"Altenrhein",
    "sg:orig_category":"Handel mit Automobilteilen U Zubeh\u00f6r",
    "sg:postcode":"9423",
    "sg:province":"St. Gallen",
    "wof:name":"Rohner Tuning",
    "wof:placetype":"venue"
},
  "geometry": {"coordinates":[9.5689716339,47.4652404785],"type":"Point"}
}