{
  "type": "Feature",
  "properties": {
    "iso:country":"CH",
    "sg:address":"Tannenweg 8",
    "sg:city":"Derendingen",
    "sg:orig_category":"Non-Classified Establishments",
    "sg:postcode":"4552",
    "sg:province":"Solothurn",
    "wof:name":"A.n.e Herrmann",
    "wof:placetype":"venue"
},
  "geometry": {"coordinates":[7.5914878845,47.1841163635],"type":"Point"}
}