{
  "type": "Feature",
  "properties": {
    "iso:country":"CH",
    "sg:address":"Buchenweg 6",
    "sg:city":"Ipsach",
    "sg:orig_category":"Allgemeiner Hoch U Tiefbau",
    "sg:phone":"+41 32 331 52 31",
    "sg:postcode":"2563",
    "sg:province":"Bern",
    "wof:name":"Pronova Ag",
    "wof:placetype":"venue"
},
  "geometry": {"coordinates":[7.232561,47.112865],"type":"Point"}
}