{
  "type": "Feature",
  "properties": {
    "iso:country":"CH",
    "sg:address":"Wehntalerstrasse 29",
    "sg:city":"Dielsdorf",
    "sg:orig_category":"Detailhandel mit Textilien Detailhandel mit elektrischen Haushaltsger\u00e4ten",
    "sg:phone":"+41 18530520",
    "sg:postcode":"8157",
    "sg:province":"Z\u00fcrich",
    "wof:name":"Rose-marie Birrer Wolle Mercerie N\u00e4hmaschinen",
    "wof:placetype":"venue"
},
  "geometry": {"coordinates":[8.4534959793,47.4830513],"type":"Point"}
}