{
  "type": "Feature",
  "properties": {
    "iso:country":"CH",
    "sg:address":"Hinterkirchweg 29",
    "sg:city":"Therwil",
    "sg:orig_category":"Vorschulen, Kinderg\u00e4rten",
    "sg:phone":"+41 61 721 38 16",
    "sg:postcode":"4106",
    "sg:province":"Basel-Landschaft",
    "wof:name":"Kindergarten",
    "wof:placetype":"venue"
},
  "geometry": {"coordinates":[7.5541658401,47.497051239],"type":"Point"}
}