{
  "type": "Feature",
  "properties": {
    "iso:country":"CH",
    "sg:address":"Neuweg 17 3902 Glis. Postfach",
    "sg:city":"Glis",
    "sg:orig_category":"Wirtschaftspr\u00fcfung, Steuerberatung U Treuhand",
    "sg:postcode":"3902",
    "sg:province":"Valais",
    "wof:name":"Treuhandb\u00fcro Bumann",
    "wof:placetype":"venue"
},
  "geometry": {"coordinates":[7.9867677689,46.3103103638],"type":"Point"}
}