{
  "type": "Feature",
  "properties": {
    "iso:country":"CH",
    "sg:address":"Bahnhofstrasse 4563 Gerlafingen. Postfach",
    "sg:city":"Winterthur",
    "sg:orig_category":"Detailhandel mit Metallwaren, Anstrichmitteln, Glaswaren, Bau U Heimwerkerbedarf",
    "sg:postcode":"8406",
    "sg:province":"Z\u00fcrich",
    "wof:name":"Von Roll Itec Ag",
    "wof:placetype":"venue"
},
  "geometry": {"coordinates":[7.5676550865,47.170715332],"type":"Point"}
}