{
  "type": "Feature",
  "properties": {
    "iso:country":"CH",
    "sg:address":"Grandes-rames 14 1700 Fribourg Case Postale 39",
    "sg:city":"Fribourg",
    "sg:orig_category":"Druck ohne Zeitungsdruck Offsetdruck",
    "sg:phone":"+41 21 635 86 81",
    "sg:postcode":"1704",
    "sg:province":"Fribourg",
    "wof:name":"Imprimerie R\u00e9",
    "wof:placetype":"venue"
},
  "geometry": {"coordinates":[6.5820388794,46.5398521423],"type":"Point"}
}