{
  "type": "Feature",
  "properties": {
    "iso:country":"CH",
    "sg:address":"Bachstrasse 298 8585 Zuben. Postfach",
    "sg:city":"Zuben",
    "sg:orig_category":"Fernmeldedienste",
    "sg:phone":"+41 71 695 37 44",
    "sg:postcode":"8585",
    "sg:province":"Thurgau",
    "wof:name":"Datasis Gmbh Dienstl., Handel Bez\u00fcglich Der Mit Der Telekommunikation In Verbindung Stehenden Peripherieger\u00e4ten Usw",
    "wof:placetype":"venue"
},
  "geometry": {"coordinates":[9.2345676422,47.608543396],"type":"Point"}
}