{
  "type": "Feature",
  "properties": {
    "iso:country":"CH",
    "sg:address":"Sichternstrasse 12",
    "sg:city":"Nuglar",
    "sg:orig_category":"Mechanische Werkst\u00e4tten",
    "sg:phone":"+41 61 911 90 02",
    "sg:postcode":"4412",
    "sg:province":"Solothurn",
    "wof:name":"Heinz Brunner Mechanische Werkst\u00e4tte",
    "wof:placetype":"venue"
},
  "geometry": {"coordinates":[7.6933917999,47.4733734131],"type":"Point"}
}