{
  "type": "Feature",
  "properties": {
    "iso:country":"CH",
    "sg:address":"Beethovenstrasse 20-24 8002 Z\u00fcrich. Postfach",
    "sg:city":"Z\u00fcrich",
    "sg:orig_category":"Effektenvermittlung U verwaltung Finanzierungsinstitutionen",
    "sg:phone":"+41 17874800",
    "sg:postcode":"8039",
    "wof:name":"Ameco Financial Services Ag",
    "wof:placetype":"venue"
},
  "geometry": {"coordinates":[8.7285766602,47.2015762329],"type":"Point"}
}