{
  "type": "Feature",
  "properties": {
    "iso:country":"CH",
    "sg:address":"Finkenhubelweg 9",
    "sg:city":"Bern",
    "sg:orig_category":"Sportvereine Turnen",
    "sg:phone":"+41 31 305 79 09",
    "sg:postcode":"3012",
    "sg:province":"Bern",
    "wof:name":"M\u00e4nnerriege St.marien",
    "wof:placetype":"venue"
},
  "geometry": {"coordinates":[7.4310321808,46.9491691589],"type":"Point"}
}