{
  "type": "Feature",
  "properties": {
    "iso:country":"CH",
    "sg:address":"Buttikon",
    "sg:city":"Buttikon",
    "sg:classifiers":[
        {
            "category":"Banks & Credit Unions",
            "subcategory":"Bank",
            "type":"Services"
        }
    ],
    "sg:phone":"+41 55672057",
    "sg:postcode":"8863",
    "sg:province":"Schwyz",
    "wof:name":"Kantonalbank Schwyz",
    "wof:placetype":"venue"
},
  "geometry": {"coordinates":[8.95279,47.175179],"type":"Point"}
}