{
  "type": "Feature",
  "properties": {
    "iso:country":"CH",
    "sg:address":"Marktweg 183",
    "sg:city":"Osterfingen",
    "sg:orig_category":"Finanzierungsinstitutionen",
    "sg:phone":"+41 52 681 30 63",
    "sg:postcode":"8218",
    "sg:province":"Schaffhausen",
    "wof:name":"Richli Finanz-consulting Gmbh",
    "wof:placetype":"venue"
},
  "geometry": {"coordinates":[8.4851541519,47.6635551453],"type":"Point"}
}