{
  "type": "Feature",
  "properties": {
    "iso:country":"CH",
    "sg:address":"Schulhausstrasse 10",
    "sg:city":"Horw",
    "sg:orig_category":"Architektur U Ingenieurb\u00fcros",
    "sg:phone":"+41 71 311 54 55",
    "sg:postcode":"6048",
    "sg:province":"Luzern",
    "wof:name":"Ingenieurb\u00fcro Vogt K. Ag",
    "wof:placetype":"venue"
},
  "geometry": {"coordinates":[9.273506,47.439404],"type":"Point"}
}