{
  "type": "Feature",
  "properties": {
    "addr:full":"1523 Granges-marnand Vaud 1523",
    "addr:housenumber":"1523",
    "addr:postcode":"1523",
    "addr:street":"Granges-Marnand",
    "iso:country":"CH",
    "sg:address":"1523",
    "sg:city":"Granges-marnand",
    "sg:classifiers":[
        {
            "category":"Education",
            "subcategory":"Library",
            "type":"Public Place"
        }
    ],
    "sg:phone":"+41 26 668 23 27",
    "sg:postcode":"1523",
    "sg:province":"Vaud",
    "sg:tags":[
        "u",
        "bibliotheken",
        "archive"
    ],
    "wof:name":"Biblioth\u00e8que Communale",
    "wof:placetype":"venue"
},
  "geometry": {"coordinates":[6.88752,46.76358],"type":"Point"}
}