{
  "type": "Feature",
  "properties": {
    "iso:country":"CH",
    "sg:address":"Moulin 1774 Cousset Case Postale",
    "sg:city":"Cousset",
    "sg:orig_category":"Grosshandel mit Getreide, Saatgut U Futtermitteln Herstellung von Futtermitteln f\u00fcr Nutztiere",
    "sg:phone":"+41 26 660 26 83",
    "sg:postcode":"1774",
    "sg:province":"Fribourg",
    "wof:name":"Bossy Cereales Sa",
    "wof:placetype":"venue"
},
  "geometry": {"coordinates":[6.9772849083,46.8183364868],"type":"Point"}
}