{
  "type": "Feature",
  "properties": {
    "iso:country":"CH",
    "sg:address":"Tieftalweg 71 6405 Immensee. Postfach",
    "sg:city":"Immensee",
    "sg:orig_category":"Filmverleih U Videoprogrammanbieter",
    "sg:phone":"+41 22 823 03 03",
    "sg:postcode":"6405",
    "sg:province":"Schwyz",
    "wof:name":"Agora Films Sarl",
    "wof:placetype":"venue"
},
  "geometry": {"coordinates":[6.1425948143,46.1827392578],"type":"Point"}
}