{
  "type": "Feature",
  "properties": {
    "iso:country":"CH",
    "sg:address":"Freie Strasse 20",
    "sg:city":"Basel",
    "sg:orig_category":"Sonstige pers\u00f6nliche Dienstleistungen Unternehmensberatung",
    "sg:postcode":"4001",
    "sg:province":"Basel-Stadt",
    "wof:name":"Ingrid Bachmann, Consulting",
    "wof:placetype":"venue"
},
  "geometry": {"coordinates":[7.5929179192,47.4882278442],"type":"Point"}
}