{
  "type": "Feature",
  "properties": {
    "iso:country":"CH",
    "sg:address":"Weidmattstrasse 33",
    "sg:city":"Lausen",
    "sg:orig_category":"Datenverarbeitungsdienste",
    "sg:phone":"+41 61 926 95 16",
    "sg:postcode":"4415",
    "sg:province":"Basel-Landschaft",
    "wof:name":"Uniloc Logistics Ag",
    "wof:placetype":"venue"
},
  "geometry": {"coordinates":[7.755166,47.476696],"type":"Point"}
}