{
  "type": "Feature",
  "properties": {
    "iso:country":"CH",
    "sg:address":"L\u00e4nderpark",
    "sg:city":"Stans",
    "sg:orig_category":"Detailhandel mit Waren verschiedener Art, Hauptrichtung Nahrungsmittel",
    "sg:phone":"+41 71 911 18 21",
    "sg:postcode":"6370",
    "sg:province":"Nidwalden",
    "wof:name":"Merkur Ag",
    "wof:placetype":"venue"
},
  "geometry": {"coordinates":[9.0442876816,47.4649658203],"type":"Point"}
}