{
  "type": "Feature",
  "properties": {
    "iso:country":"CH",
    "sg:address":"Denkmalstrasse 1",
    "sg:city":"Neuenegg",
    "sg:classifiers":[
        {
            "category":"Travel",
            "subcategory":"Hotels & Motels",
            "type":"Entertainment"
        }
    ],
    "sg:phone":"+41 31 331 12 26",
    "sg:postcode":"3176",
    "sg:province":"Bern",
    "sg:tags":[
        "hotels",
        "mit",
        "restaurant"
    ],
    "wof:name":"B\u00e4ren Ag",
    "wof:placetype":"venue"
},
  "geometry": {"coordinates":[7.3039608002,46.8950691223],"type":"Point"}
}