{
  "type": "Feature",
  "properties": {
    "iso:country":"CH",
    "sg:address":"Steinmaurstrasse",
    "sg:city":"Neerach",
    "sg:orig_category":"Wasserversorgung",
    "sg:phone":"+41 18582438",
    "sg:postcode":"8173",
    "sg:province":"Z\u00fcrich",
    "wof:name":"Wasserversorgung",
    "wof:placetype":"venue"
},
  "geometry": {"coordinates":[8.4678573608,47.5106277466],"type":"Point"}
}