{
  "type": "Feature",
  "properties": {
    "iso:country":"CH",
    "sg:address":"Werkhofstrasse 2",
    "sg:city":"Triesen",
    "sg:orig_category":"Wasserversorgung",
    "sg:phone":"+41 75 392 31 28",
    "sg:postcode":"9495",
    "wof:name":"Wasserversorgung Der Gemeinde Triesen",
    "wof:placetype":"venue"
},
  "geometry": {"coordinates":[9.5216274261,47.1104316711],"type":"Point"}
}