{
  "type": "Feature",
  "properties": {
    "iso:country":"CH",
    "sg:address":"Oberwaldstrasse 174a",
    "sg:city":"D\u00fcrrenroth",
    "sg:orig_category":"Elektroinstallation",
    "sg:phone":"+41 62 964 10 50",
    "sg:postcode":"3465",
    "sg:province":"Bern",
    "wof:name":"Hans-rudolf K\u00fcng Elektrische Installationen",
    "wof:placetype":"venue"
},
  "geometry": {"coordinates":[7.7920179367,47.0896568298],"type":"Point"}
}