{
  "type": "Feature",
  "properties": {
    "iso:country":"CH",
    "sg:address":"Witellikerstrasse 45",
    "sg:city":"Z\u00fcrich",
    "sg:orig_category":"Organisationen der Wohlfahrtspflege Wohnheime",
    "sg:phone":"+41 13811570",
    "sg:postcode":"8008",
    "sg:province":"Z\u00fcrich",
    "wof:name":"Stiftung Hirslanden, Sozialp\u00e4dagogisches Zentrum F\u00fcr Junge Frauen",
    "wof:placetype":"venue"
},
  "geometry": {"coordinates":[8.5774011612,47.3505554199],"type":"Point"}
}