{
  "type": "Feature",
  "properties": {
    "iso:country":"CH",
    "sg:address":"B\u00fcntenstrasse 7",
    "sg:city":"Wangs",
    "sg:orig_category":"Bauspenglerei Sanit\u00e4rinstallation",
    "sg:phone":"+41 81 723 16 03",
    "sg:postcode":"7323",
    "sg:province":"St. Gallen",
    "wof:name":"Innozenz Vogler San.installationen Spenglerei",
    "wof:placetype":"venue"
},
  "geometry": {"coordinates":[9.432622,47.032413],"type":"Point"}
}