{
  "type": "Feature",
  "properties": {
    "iso:country":"CH",
    "sg:address":"Hauptstrasse 62",
    "sg:city":"Kriegstetten",
    "sg:classifiers":[
        {
            "category":"Restaurant",
            "type":"Food & Drink"
        }
    ],
    "sg:phone":"+41 32 661 10 23",
    "sg:postcode":"4566",
    "sg:province":"Solothurn",
    "wof:name":"Restaurant Kreuz",
    "wof:placetype":"venue"
},
  "geometry": {"coordinates":[7.5979242325,47.1745262146],"type":"Point"}
}