{
  "type": "Feature",
  "properties": {
    "iso:country":"CH",
    "sg:address":"Rue Du Ch\u00e2teau",
    "sg:city":"Sullens",
    "sg:orig_category":"Landesverteidigung, Sozialversicherung \u00d6ffentliche Verwaltung",
    "sg:phone":"+41 21 731 26 53",
    "sg:postcode":"1036",
    "sg:province":"Vaud",
    "wof:name":"Office De Protection Civile",
    "wof:placetype":"venue"
},
  "geometry": {"coordinates":[6.5671691895,46.5941352844],"type":"Point"}
}