{
  "type": "Feature",
  "properties": {
    "iso:country":"CH",
    "sg:address":"9056 Gais. Postfach",
    "sg:city":"Gais",
    "sg:orig_category":"Primarschulen",
    "sg:phone":"+41 71 891 28 32",
    "sg:postcode":"9056",
    "sg:province":"Appenzell Ausserrhoden",
    "wof:name":"Primarschule Dorf",
    "wof:placetype":"venue"
},
  "geometry": {"coordinates":[9.5699796677,47.4089813232],"type":"Point"}
}