{
  "type": "Feature",
  "properties": {
    "iso:country":"CH",
    "sg:address":"Diamantstrasse 1-5",
    "sg:city":"Biel/bienne",
    "sg:orig_category":"Detailhandel mit Fahrr\u00e4dern Handel mit Motorr\u00e4dern, Teilen U Zubeh\u00f6r Instandhaltung U Reparatur von ",
    "sg:phone":"+41 32 323 19 03",
    "sg:postcode":"2503",
    "sg:province":"Bern",
    "wof:name":"Martin Siegenthaler Velos Motos",
    "wof:placetype":"venue"
},
  "geometry": {"coordinates":[7.2505030632,47.1382637024],"type":"Point"}
}