{
  "type": "Feature",
  "properties": {
    "iso:country":"CH",
    "sg:address":"M\u00fchleschlucht",
    "sg:city":"Gadmen",
    "sg:orig_category":"Sportvereine Ski",
    "sg:phone":"+41 33 336 48 02",
    "sg:postcode":"3863",
    "sg:province":"Bern",
    "wof:name":"Nordischer Skiclub Thun",
    "wof:placetype":"venue"
},
  "geometry": {"coordinates":[7.6254758835,46.731262207],"type":"Point"}
}