{
  "type": "Feature",
  "properties": {
    "iso:country":"CH",
    "sg:address":"B\u00e4renfelserstrasse 21",
    "sg:city":"Basel",
    "sg:orig_category":"Erschliessung von Grundst\u00fccken",
    "sg:postcode":"4057",
    "sg:province":"Basel-Stadt",
    "wof:name":"Cohabitat Wohnbaugenossenschaft",
    "wof:placetype":"venue"
},
  "geometry": {"coordinates":[7.5876111984,47.5670280457],"type":"Point"}
}