{
  "type": "Feature",
  "properties": {
    "iso:country":"CH",
    "sg:address":"In Der Gandstrasse 30",
    "sg:city":"Zumikon",
    "sg:orig_category":"Architektur U Ingenieurb\u00fcros",
    "sg:postcode":"8126",
    "sg:province":"Z\u00fcrich",
    "wof:name":"Danilo Morellini Architekt Htl",
    "wof:placetype":"venue"
},
  "geometry": {"coordinates":[8.614176,47.337078],"type":"Point"}
}