{
  "type": "Feature",
  "properties": {
    "iso:country":"CH",
    "sg:address":"G\u00e4rischstrasse 18/20",
    "sg:city":"Bellach",
    "sg:orig_category":"Unclassifiable Establishments",
    "sg:postcode":"4512",
    "sg:province":"Solothurn",
    "wof:name":"Denner-satellit, A. + M. Wyss",
    "wof:placetype":"venue"
},
  "geometry": {"coordinates":[7.5018010139,47.2151374817],"type":"Point"}
}