{
  "type": "Feature",
  "properties": {
    "iso:country":"CH",
    "sg:address":"Im Stumpen 5",
    "sg:city":"B\u00fclach",
    "sg:orig_category":"Vorschulen, Kinderg\u00e4rten",
    "sg:phone":"+41 71 923 20 36",
    "sg:postcode":"8180",
    "sg:province":"Z\u00fcrich",
    "wof:name":"Kindergarten Sonderschule",
    "wof:placetype":"venue"
},
  "geometry": {"coordinates":[9.0409536362,47.4582901001],"type":"Point"}
}