{
  "type": "Feature",
  "properties": {
    "iso:country":"CH",
    "sg:address":"Margarethenstrasse 7a 4450 Sissach. Postfach",
    "sg:city":"Sissach",
    "sg:orig_category":"Grosshandel mit pharmazeutischen Erzeugnissen, medizinischen U orthop\u00e4dischen Artikeln",
    "sg:postcode":"4450",
    "sg:province":"Basel-Landschaft",
    "wof:name":"Voodoo Botanics Schaub",
    "wof:placetype":"venue"
},
  "geometry": {"coordinates":[7.8110060692,47.4617500305],"type":"Point"}
}