{
  "type": "Feature",
  "properties": {
    "addr:full":"Kreuzbuchstrasse 108 6045 Meggen. Postfach Meggen Luzern 6045",
    "addr:housenumber":"108",
    "addr:postcode":"6045 meggen. postfach;6045",
    "addr:street":"Kreuzbuchstrasse",
    "iso:country":"CH",
    "sg:address":"Kreuzbuchstrasse 108 6045 Meggen. Postfach",
    "sg:city":"Meggen",
    "sg:orig_category":"Architektur U Ingenieurb\u00fcros",
    "sg:phone":"+41 41 377 46 10",
    "sg:postcode":"6045",
    "sg:province":"Luzern",
    "wof:name":"Bsp Ingenieure + Planer Ag, Zweigniederlassung Meggen Ingenieurarbeiten In Hoch Und Tiefbau",
    "wof:placetype":"venue"
},
  "geometry": {"coordinates":[8.36384,47.050446],"type":"Point"}
}