{
  "type": "Feature",
  "properties": {
    "iso:country":"CH",
    "sg:address":"B\u00fcrerfeldstrasse 8",
    "sg:city":"Oberb\u00fcren",
    "sg:orig_category":"Grosshandel mit Textilien",
    "sg:postcode":"9245",
    "sg:province":"St. Gallen",
    "wof:name":"Stickerei Wehrli Und Handels Gmbh Stickerei; Fabrikation, Handel Usw",
    "wof:placetype":"venue"
},
  "geometry": {"coordinates":[9.532699585,47.4808540344],"type":"Point"}
}