{
  "type": "Feature",
  "properties": {
    "iso:country":"CH",
    "sg:address":"Centre De La Gottaz 32",
    "sg:city":"Morges",
    "sg:orig_category":"Ingenieurb\u00fcros Elektro",
    "sg:phone":"+41 21 801 08 96",
    "sg:postcode":"1110",
    "sg:province":"Vaud",
    "wof:name":"Jean-pierre Mabillard Mab Ing\u00e9nierie",
    "wof:placetype":"venue"
},
  "geometry": {"coordinates":[6.4849729538,46.5072364807],"type":"Point"}
}