{
  "type": "Feature",
  "properties": {
    "iso:country":"CH",
    "sg:address":"G\u00fctighuserstrasse 12",
    "sg:city":"Ossingen",
    "sg:orig_category":"Non-Classified Establishments",
    "sg:postcode":"8475",
    "sg:province":"Z\u00fcrich",
    "wof:name":"Vitas Ag",
    "wof:placetype":"venue"
},
  "geometry": {"coordinates":[7.9761419296,47.3588180542],"type":"Point"}
}