{
  "type": "Feature",
  "properties": {
    "iso:country":"CH",
    "sg:address":"Im Hof 15 8355 Aadorf. Postfach",
    "sg:city":"Aadorf",
    "sg:orig_category":"Werbung",
    "sg:postcode":"8355",
    "sg:province":"Thurgau",
    "wof:name":"Voiceleasing - Marti",
    "wof:placetype":"venue"
},
  "geometry": {"coordinates":[8.9057378769,47.4913520813],"type":"Point"}
}