{
  "type": "Feature",
  "properties": {
    "iso:country":"CH",
    "sg:address":"2925",
    "sg:city":"Buix",
    "sg:orig_category":"G\u00fcterbef\u00f6rderung im Strassenverkehr",
    "sg:phone":"+41 32 475 58 76",
    "sg:postcode":"2925",
    "sg:province":"Jura",
    "wof:name":"Transports Jean-michel Erard",
    "wof:placetype":"venue"
},
  "geometry": {"coordinates":[7.0287761688,47.4831924438],"type":"Point"}
}