{
  "type": "Feature",
  "properties": {
    "iso:country":"CH",
    "sg:address":"Efringerstrasse 81",
    "sg:city":"Basel",
    "sg:orig_category":"W\u00e4schereien",
    "sg:phone":"+41 61 692 64 11",
    "sg:postcode":"4057",
    "sg:province":"Basel-Stadt",
    "wof:name":"Meier's Naist\u00fcbli W\u00e4scherei",
    "wof:placetype":"venue"
},
  "geometry": {"coordinates":[7.5960111618,47.5698814392],"type":"Point"}
}