{
  "type": "Feature",
  "properties": {
    "iso:country":"CH",
    "sg:address":"Austrasse 85",
    "sg:city":"Basel",
    "sg:orig_category":"Arztpraxen",
    "sg:phone":"+41 61 270 80 70",
    "sg:postcode":"4051",
    "sg:province":"Basel-Stadt",
    "wof:name":"Dr.med.hansj\u00f6rg N\u00e4nni Spezialarzt",
    "wof:placetype":"venue"
},
  "geometry": {"coordinates":[7.577885,47.555016],"type":"Point"}
}