{
  "type": "Feature",
  "properties": {
    "iso:country":"CH",
    "sg:address":"Gotthardstrasse 10a 8800 Thalwil. Postfach",
    "sg:city":"Thalwil",
    "sg:orig_category":"Softwareentwicklung U beratung",
    "sg:postcode":"8800",
    "sg:province":"Z\u00fcrich",
    "wof:name":"Xonos Ag Informatikl\u00f6sungen Usw.; Entwicklung, Beratung, Herstellung U. Vertrieb",
    "wof:placetype":"venue"
},
  "geometry": {"coordinates":[8.5654668808,47.2941398621],"type":"Point"}
}