{
  "type": "Feature",
  "properties": {
    "addr:full":"Hauptstrasse Brienz/brinzauls Graubunden 7084",
    "addr:postcode":"7084",
    "addr:street":"Hauptstrasse;Graubunden",
    "iso:country":"CH",
    "sg:address":"Hauptstrasse",
    "sg:city":"Brienz/brinzauls",
    "sg:orig_category":"Allgemeiner Hoch U Tiefbau",
    "sg:phone":"+41 26 677 21 21",
    "sg:postcode":"7084",
    "sg:province":"Graubunden",
    "wof:name":"C. Gailland Roulin Sarl, Atelier De Bobinage",
    "wof:placetype":"venue"
},
  "geometry": {"coordinates":[6.98008,46.89003],"type":"Point"}
}