{
  "type": "Feature",
  "properties": {
    "iso:country":"CH",
    "sg:address":"Haltenstrasse 12",
    "sg:city":"K\u00fcnten",
    "sg:orig_category":"Vereine Gesang Vereine Trachten",
    "sg:phone":"+41 56 496 18 05",
    "sg:postcode":"5444",
    "sg:province":"Aargau",
    "wof:name":"Berner Trachtenchor",
    "wof:placetype":"venue"
},
  "geometry": {"coordinates":[8.3237361908,47.3861045837],"type":"Point"}
}