{
  "type": "Feature",
  "properties": {
    "iso:country":"CH",
    "sg:address":"Landstrasse 166",
    "sg:city":"Wettingen",
    "sg:orig_category":"Pensionskassen",
    "sg:phone":"+41 56 426 03 24",
    "sg:postcode":"5430",
    "sg:province":"Aargau",
    "wof:name":"Patronale Personalf\u00fcrsorgestiftung Wirba-vredag.",
    "wof:placetype":"venue"
},
  "geometry": {"coordinates":[8.3356208801,47.4616737366],"type":"Point"}
}