{
  "type": "Feature",
  "properties": {
    "iso:country":"CH",
    "sg:address":"Werdstrasse 56",
    "sg:city":"Z\u00fcrich",
    "sg:orig_category":"Unclassifiable Establishments",
    "sg:postcode":"8004",
    "sg:province":"Z\u00fcrich",
    "wof:name":"To Brasil Tours Ag",
    "wof:placetype":"venue"
},
  "geometry": {"coordinates":[8.528544426,47.3726501465],"type":"Point"}
}