{
  "type": "Feature",
  "properties": {
    "iso:country":"CH",
    "sg:address":"3947",
    "sg:city":"Ergisch",
    "sg:classifiers":[
        {
            "category":"Insurance",
            "subcategory":"Insurance Agent",
            "type":"Services"
        }
    ],
    "sg:phone":"+41 27 932 14 07",
    "sg:postcode":"3947",
    "sg:province":"Valais",
    "sg:tags":[
        "versicherungsagenturen",
        "-broker"
    ],
    "wof:name":"Die Mobiliar Versicherungen & Vorsorge",
    "wof:placetype":"venue"
},
  "geometry": {"coordinates":[7.7135820389,46.2933235168],"type":"Point"}
}