{
  "type": "Feature",
  "properties": {
    "iso:country":"CH",
    "sg:address":"Gewerbestrasse 14",
    "sg:city":"Siblingen",
    "sg:orig_category":"Handelsvermittlung U Grosshandel Sonstiger Grosshandel",
    "sg:phone":"+41 52 685 36 35",
    "sg:postcode":"8225",
    "sg:province":"Schaffhausen",
    "wof:name":"Orgaver Verkaufs Und Servicestelle Fischer & K\u00fcbler",
    "wof:placetype":"venue"
},
  "geometry": {"coordinates":[8.5164518356,47.7132644653],"type":"Point"}
}