{
  "type": "Feature",
  "properties": {
    "iso:country":"CH",
    "sg:address":"3929",
    "sg:city":"T\u00e4sch",
    "sg:orig_category":"Detailhandel mit B\u00fcchern, Zeitungen, Schreib U Papeteriewaren Detailhandel mit Getr\u00e4nken",
    "sg:phone":"+41 27 967 36 61",
    "sg:postcode":"3929",
    "sg:province":"Valais",
    "wof:name":"Lauber Leonhard & Co, Kiosk-souvenirs & Boutique Crystal",
    "wof:placetype":"venue"
},
  "geometry": {"coordinates":[7.776325,46.069695],"type":"Point"}
}