{
  "type": "Feature",
  "properties": {
    "iso:country":"CH",
    "sg:address":"Rue Des Mouettes 16",
    "sg:city":"Yverdon-les-bains",
    "sg:orig_category":"Softwareentwicklung U beratung",
    "sg:phone":"+41 56 451 14 11",
    "sg:postcode":"1400",
    "sg:province":"Vaud",
    "wof:name":"Dubois Digital Consulting",
    "wof:placetype":"venue"
},
  "geometry": {"coordinates":[8.2221879959,47.4937591553],"type":"Point"}
}