{
  "type": "Feature",
  "properties": {
    "iso:country":"CH",
    "sg:address":"Place De La Gare 10",
    "sg:city":"Lausanne",
    "sg:orig_category":"Konsulate",
    "sg:phone":"+41 22 311 83 75",
    "sg:postcode":"1003",
    "sg:province":"Vaud",
    "wof:name":"Consulat De Finlande",
    "wof:placetype":"venue"
},
  "geometry": {"coordinates":[6.1460838318,46.2018203735],"type":"Point"}
}