{
  "type": "Feature",
  "properties": {
    "iso:country":"CH",
    "sg:address":"Rue Adrien-lachenal 12",
    "sg:city":"Gen\u00e8ve",
    "sg:orig_category":"Reiseb\u00fcros U Reiseveranstalter",
    "sg:phone":"+41 22 787 57 67",
    "sg:postcode":"1207",
    "sg:province":"Gen\u00e8ve",
    "wof:name":"Voyages Plus Sa",
    "wof:placetype":"venue"
},
  "geometry": {"coordinates":[6.1559228897,46.2000541687],"type":"Point"}
}