{
  "type": "Feature",
  "properties": {
    "iso:country":"CH",
    "sg:address":"Saffretweg 26",
    "sg:city":"Dornach",
    "sg:orig_category":"Fachdetailhandel in Verkaufsr\u00e4umen",
    "sg:phone":"+41 61 701 40 62",
    "sg:postcode":"4143",
    "sg:province":"Solothurn",
    "wof:name":"Jane's Buess Angela J.",
    "wof:placetype":"venue"
},
  "geometry": {"coordinates":[7.6145558357,47.4756126404],"type":"Point"}
}