{
  "type": "Feature",
  "properties": {
    "iso:country":"CH",
    "sg:address":"Place De La Fusterie 14 1204 Gen\u00e8ve. Postfach",
    "sg:city":"Gen\u00e8ve",
    "sg:orig_category":"Effektenvermittlung Broker Finanzierungsinstitutionen",
    "sg:phone":"+41 22 318 87 00",
    "sg:postcode":"1201",
    "sg:province":"Gen\u00e8ve",
    "wof:name":"Xerof Financial Services Sa",
    "wof:placetype":"venue"
},
  "geometry": {"coordinates":[6.1454148293,46.2038230896],"type":"Point"}
}