{
  "type": "Feature",
  "properties": {
    "iso:country":"CH",
    "sg:address":"Bachstrasse 63",
    "sg:city":"Kloten",
    "sg:orig_category":"Grosshandel mit Bekleidung Herstellung von Oberbekleidung",
    "sg:phone":"+41 18142479",
    "sg:postcode":"8302",
    "sg:province":"Z\u00fcrich",
    "wof:name":"Giaquinto & Co Damenkonfektion",
    "wof:placetype":"venue"
},
  "geometry": {"coordinates":[8.590092659,47.4502296448],"type":"Point"}
}