{
  "type": "Feature",
  "properties": {
    "iso:country":"CH",
    "sg:address":"Via Gaggini Da Bissone 16",
    "sg:city":"Lugano",
    "sg:orig_category":"Detailhandel mit elektrischen Haushalts-,Radio U Fernsehger\u00e4ten sowie Musikinstrumenten",
    "sg:postcode":"6900",
    "sg:province":"Ticino",
    "wof:name":"Audio Globo Di Casanova S.",
    "wof:placetype":"venue"
},
  "geometry": {"coordinates":[8.9441757202,45.9960174561],"type":"Point"}
}