{
  "type": "Feature",
  "properties": {
    "iso:country":"CH",
    "sg:address":"Gewerbestrasse 17 4553 Subingen. Postfach 256",
    "sg:city":"Subingen",
    "sg:orig_category":"Bauspenglerei Sanit\u00e4rinstallation",
    "sg:phone":"+41 32 614 15 44",
    "sg:postcode":"4553",
    "sg:province":"Solothurn",
    "wof:name":"Heinz Wirz Spenglerei San.installationen",
    "wof:placetype":"venue"
},
  "geometry": {"coordinates":[7.602756,47.197365],"type":"Point"}
}