{
  "type": "Feature",
  "properties": {
    "iso:country":"CH",
    "sg:address":"Reichenauerstrasse 33",
    "sg:city":"Domat/ems",
    "sg:orig_category":"RESTAURANTS: TEA-ROOMS",
    "sg:phone":"+41 81 633 12 62",
    "sg:postcode":"7013",
    "sg:province":"Graubunden",
    "wof:name":"Restaurant Roda",
    "wof:placetype":"venue"
},
  "geometry": {"coordinates":[9.4447383881,46.8326263428],"type":"Point"}
}