{
  "type": "Feature",
  "properties": {
    "iso:country":"CH",
    "sg:address":"Ausstellungsstrasse 102 8005 Z\u00fcrich. Postfach",
    "sg:city":"Z\u00fcrich",
    "sg:orig_category":"Berufliche Weiterbildung, Erwachsenenbildung",
    "sg:phone":"+41 12717761",
    "sg:postcode":"8031",
    "sg:province":"Z\u00fcrich",
    "wof:name":"Iac Stiftung Integratives Ausbildungszentrum",
    "wof:placetype":"venue"
},
  "geometry": {"coordinates":[8.533302,47.384624],"type":"Point"}
}