{
  "type": "Feature",
  "properties": {
    "iso:country":"CH",
    "sg:address":"Kirchgasse 23",
    "sg:city":"Sissach",
    "sg:classifiers":[
        {
            "category":"Professional",
            "subcategory":"Computer Services",
            "type":"Services"
        }
    ],
    "sg:phone":"+41 61 975 81 00",
    "sg:postcode":"4450",
    "sg:province":"Basel-Landschaft",
    "sg:tags":[
        "administration",
        "software"
    ],
    "wof:name":"Gse Gisin Software-engineering & Co",
    "wof:placetype":"venue"
},
  "geometry": {"coordinates":[7.810513,47.465511],"type":"Point"}
}