{
  "type": "Feature",
  "properties": {
    "iso:country":"CH",
    "sg:address":"3628",
    "sg:city":"Uttigen",
    "sg:orig_category":"Verarbeitung von Milch Verwertung von Milch",
    "sg:postcode":"3628",
    "sg:province":"Bern",
    "wof:name":"Milchgenossenschaft Uttigen-kienersr\u00fcti",
    "wof:placetype":"venue"
},
  "geometry": {"coordinates":[7.5753898621,46.7966308594],"type":"Point"}
}