{
  "type": "Feature",
  "properties": {
    "iso:country":"CH",
    "sg:address":"Gr\u00fcttstrasse 108",
    "sg:city":"Biberist",
    "sg:orig_category":"Herstellung von Werkzeugen",
    "sg:phone":"+41 32 682 50 12",
    "sg:postcode":"4562",
    "sg:province":"Solothurn",
    "wof:name":"J\u00f6rg Isch Formenbau",
    "wof:placetype":"venue"
},
  "geometry": {"coordinates":[7.5732707977,47.177646637],"type":"Point"}
}