{
  "type": "Feature",
  "properties": {
    "iso:country":"CH",
    "sg:address":"Bachstrasse 10",
    "sg:city":"Schaffhausen",
    "sg:orig_category":"Detailhandel mit Geschenkartikeln U Souvenirs",
    "sg:phone":"+41 52 625 38 20",
    "sg:postcode":"8200",
    "sg:province":"Schaffhausen",
    "wof:name":"Gerberplatz-boutique",
    "wof:placetype":"venue"
},
  "geometry": {"coordinates":[8.638428688,47.6960754395],"type":"Point"}
}