{
  "type": "Feature",
  "properties": {
    "iso:country":"CH",
    "sg:address":"9050",
    "sg:city":"Appenzell",
    "sg:orig_category":"Vorschulen, Kinderg\u00e4rten",
    "sg:postcode":"9050",
    "sg:province":"Appenzell Innerhoden",
    "wof:name":"Kindergarten Schulhaus Gringel",
    "wof:placetype":"venue"
},
  "geometry": {"coordinates":[9.4076833725,47.3314361572],"type":"Point"}
}