{
  "type": "Feature",
  "properties": {
    "iso:country":"CH",
    "sg:address":"Tgampi 173a",
    "sg:city":"Lantsch/lenz",
    "sg:orig_category":"Architekturb\u00fcros",
    "sg:phone":"+41 81 681 17 12",
    "sg:postcode":"7083",
    "sg:province":"Graubunden",
    "wof:name":"Toni Brunner Architekturb\u00fcro",
    "wof:placetype":"venue"
},
  "geometry": {"coordinates":[9.56152,46.686703],"type":"Point"}
}