{
  "type": "Feature",
  "properties": {
    "iso:country":"CH",
    "sg:address":"Br\u00fchlstrasse 52",
    "sg:city":"Lausen",
    "sg:orig_category":"Detailhandel mit Waren verschiedener Art, Hauptrichtung Nahrungsmittel",
    "sg:phone":"+41 61 921 66 81",
    "sg:postcode":"4415",
    "sg:province":"Basel-Landschaft",
    "wof:name":"Coop Center",
    "wof:placetype":"venue"
},
  "geometry": {"coordinates":[7.7587361336,47.472946167],"type":"Point"}
}