{
  "type": "Feature",
  "properties": {
    "iso:country":"CH",
    "sg:address":"Wilgasse 51",
    "sg:city":"Lenzburg",
    "sg:orig_category":"P\u00e9dicure",
    "sg:phone":"+41 61 711 85 13",
    "sg:postcode":"5600",
    "sg:province":"Aargau",
    "wof:name":"Silvia Gr\u00fctter P\u00e9dicure",
    "wof:placetype":"venue"
},
  "geometry": {"coordinates":[7.5994977951,47.5042381287],"type":"Point"}
}