{
  "type": "Feature",
  "properties": {
    "iso:country":"CH",
    "sg:address":"Les Vergers",
    "sg:city":"Valeyres-montagny",
    "sg:orig_category":"Elektroinstallation",
    "sg:phone":"+41 24 446 21 62",
    "sg:postcode":"1441",
    "sg:province":"Vaud",
    "wof:name":"Bovard-services",
    "wof:placetype":"venue"
},
  "geometry": {"coordinates":[6.6073799133,46.7997436523],"type":"Point"}
}