{
  "type": "Feature",
  "properties": {
    "iso:country":"CH",
    "sg:address":"Bahnhofstrasse 26",
    "sg:city":"Arbon",
    "sg:orig_category":"Gesundheitswesen",
    "sg:phone":"+41 71 446 04 65",
    "sg:postcode":"9320",
    "sg:province":"Thurgau",
    "wof:name":"Cura Manuum Gmbh",
    "wof:placetype":"venue"
},
  "geometry": {"coordinates":[9.4336853027,47.5125007629],"type":"Point"}
}