{
  "type": "Feature",
  "properties": {
    "iso:country":"CH",
    "sg:address":"Route De Lausanne",
    "sg:city":"Oron-la-ville",
    "sg:orig_category":"Detailhandel mit Waren verschiedener Art, Hauptrichtung Nahrungsmittel Grosshandel mit Wein U Spirit",
    "sg:phone":"+41 21 907 90 10",
    "sg:postcode":"1610",
    "sg:province":"Vaud",
    "wof:name":"Georges Smyrliadis Import Vins-alimentation",
    "wof:placetype":"venue"
},
  "geometry": {"coordinates":[6.8232750893,46.5718154907],"type":"Point"}
}