{
  "type": "Feature",
  "properties": {
    "iso:country":"CH",
    "sg:address":"Grundackerweg 108",
    "sg:city":"Berikon",
    "sg:orig_category":"Non-Classified Establishments",
    "sg:postcode":"8965",
    "sg:province":"Aargau",
    "wof:name":"Regional-taxi-mutschellen Milo Hafner",
    "wof:placetype":"venue"
},
  "geometry": {"coordinates":[8.3673219681,47.3577079773],"type":"Point"}
}