{
  "type": "Feature",
  "properties": {
    "iso:country":"CH",
    "sg:address":"Neumattstrasse 6 3127 M\u00fchlethurnen. Postfach",
    "sg:city":"M\u00fchlethurnen",
    "sg:orig_category":"Softwareentwicklung U beratung",
    "sg:postcode":"3127",
    "sg:province":"Bern",
    "wof:name":"Loosli Urs. P. - Edv",
    "wof:placetype":"venue"
},
  "geometry": {"coordinates":[7.5148391724,46.8134841919],"type":"Point"}
}