{
  "type": "Feature",
  "properties": {
    "iso:country":"CH",
    "sg:address":"L\u00e4rchenweg 3 8500 Frauenfeld. Postfach",
    "sg:city":"Frauenfeld",
    "sg:orig_category":"Forschung U Entwicklung im Bereich der Naturwissenschaften",
    "sg:postcode":"8503",
    "sg:province":"Thurgau",
    "wof:name":"Tach-lon Ur-lebenskraft Gmbh Energetische Produkte Zum Schutz Vor Technischen Umwelt-emissionen; Erforschung, Herstellung, Handel, Vertreib Usw",
    "wof:placetype":"venue"
},
  "geometry": {"coordinates":[8.8775196075,47.5528831482],"type":"Point"}
}