{
  "type": "Feature",
  "properties": {
    "iso:country":"CH",
    "sg:address":"Rue Mauborget 9",
    "sg:city":"Yverdon-les-bains",
    "sg:orig_category":"Gem\u00fcsebau",
    "sg:phone":"+41 24 425 40 12",
    "sg:postcode":"1400",
    "sg:province":"Vaud",
    "wof:name":"Henri Thuner Mara\u00eecher",
    "wof:placetype":"venue"
},
  "geometry": {"coordinates":[6.6280369759,46.7798080444],"type":"Point"}
}