{
  "type": "Feature",
  "properties": {
    "addr:full":"Bernerstrasse 27 Baden Aargau 5400",
    "addr:housenumber":"27",
    "addr:postcode":"5400",
    "addr:street":"Bernerstrasse",
    "iso:country":"CH",
    "sg:address":"Bernerstrasse 27",
    "sg:city":"Baden",
    "sg:orig_category":"Arztpraxen",
    "sg:phone":"+41 56 221 59 59",
    "sg:postcode":"5400",
    "sg:province":"Aargau",
    "wof:name":"Dr. Med. Tony Pfyl Spezialarzt Fmh Chirurgie",
    "wof:placetype":"venue"
},
  "geometry": {"coordinates":[8.296583,47.46767],"type":"Point"}
}