{
  "type": "Feature",
  "properties": {
    "iso:country":"CH",
    "sg:address":"Grand-rue 8",
    "sg:city":"Gen\u00e8ve",
    "sg:orig_category":"Handelsvermittlung U Grosshandel Handelsvermittlung von Brennstoffen, Erzen, Metallen U Chemikalien",
    "sg:phone":"+41 22 818 72 80",
    "sg:postcode":"1204",
    "sg:province":"Gen\u00e8ve",
    "wof:name":"Tempo Trade Sa",
    "wof:placetype":"venue"
},
  "geometry": {"coordinates":[6.1449518204,46.202129364],"type":"Point"}
}