{
  "type": "Feature",
  "properties": {
    "iso:country":"CH",
    "sg:address":"3971",
    "sg:city":"Chermignon",
    "sg:orig_category":"RESTAURANTS: TEA-ROOMS",
    "sg:postcode":"3971",
    "sg:province":"Valais",
    "wof:name":"Gebr. Patrik, Rolf & Stefan Bucher",
    "wof:placetype":"venue"
},
  "geometry": {"coordinates":[8.6449594498,46.8809318542],"type":"Point"}
}