{
  "type": "Feature",
  "properties": {
    "iso:country":"CH",
    "sg:address":"Gewerbestrasse 11",
    "sg:city":"Cham",
    "sg:orig_category":"Vermietung U Verpachtung von eigenen Immobilien",
    "sg:phone":"+41 41 743 24 25",
    "sg:postcode":"6330",
    "sg:province":"Zug",
    "wof:name":"United Investment Corporation Zweigniederlassung Cham",
    "wof:placetype":"venue"
},
  "geometry": {"coordinates":[8.4720430374,47.1886940002],"type":"Point"}
}