{
  "type": "Feature",
  "properties": {
    "iso:country":"CH",
    "sg:address":"Meieriedstrasse 9",
    "sg:city":"Burgdorf",
    "sg:orig_category":"Betrieb von Sportanlagen",
    "sg:postcode":"3400",
    "sg:province":"Bern",
    "wof:name":"Sportplatzgenossenschaft Burgdorf",
    "wof:placetype":"venue"
},
  "geometry": {"coordinates":[7.603665,47.062092],"type":"Point"}
}