{
  "type": "Feature",
  "properties": {
    "iso:country":"CH",
    "sg:address":"Im Zwinggarten 9",
    "sg:city":"D\u00fcbendorf",
    "sg:orig_category":"Kinderkrippen U horte",
    "sg:phone":"+41 18211480",
    "sg:postcode":"8600",
    "sg:province":"Z\u00fcrich",
    "wof:name":"Kinderhort Zwinggarten",
    "wof:placetype":"venue"
},
  "geometry": {"coordinates":[8.618645668,47.4034538269],"type":"Point"}
}