{
  "type": "Feature",
  "properties": {
    "iso:country":"CH",
    "sg:address":"Via Tesserete 67",
    "sg:city":"Savosa",
    "sg:orig_category":"Vermietung U Verpachtung von eigenen Immobilien",
    "sg:postcode":"6942",
    "sg:province":"Ticino",
    "wof:name":"Sumolin Sa",
    "wof:placetype":"venue"
},
  "geometry": {"coordinates":[6.7489261627,47.0584068298],"type":"Point"}
}