{
  "type": "Feature",
  "properties": {
    "iso:country":"CH",
    "sg:address":"Schl\u00f6sslistrasse 19 5408 Ennetbaden. Postfach 19",
    "sg:city":"Ennetbaden",
    "sg:orig_category":"Baugewerbe Sonstige mit der Informatik verbundene T\u00e4tigkeiten",
    "sg:phone":"+41 56 460 02 02",
    "sg:postcode":"5408",
    "sg:province":"Aargau",
    "wof:name":"Pto Bauinformatik",
    "wof:placetype":"venue"
},
  "geometry": {"coordinates":[8.210832,47.468533],"type":"Point"}
}