{
  "type": "Feature",
  "properties": {
    "iso:country":"CH",
    "sg:address":"Blumenweg 20",
    "sg:city":"Grabs",
    "sg:orig_category":"Fachdetailhandel in Verkaufsr\u00e4umen",
    "sg:phone":"+41 81 771 37 77",
    "sg:postcode":"9472",
    "sg:province":"St. Gallen",
    "wof:name":"Stolz Hiskia",
    "wof:placetype":"venue"
},
  "geometry": {"coordinates":[9.4547472,47.1782302856],"type":"Point"}
}