{
  "type": "Feature",
  "properties": {
    "addr:full":"Europastrasse 17 Glattbrugg Z\u00fcrich 8152",
    "addr:housenumber":"17",
    "addr:postcode":"8152",
    "addr:street":"Europastrasse",
    "iso:country":"CH",
    "sg:address":"Europastrasse 17",
    "sg:city":"Glattbrugg",
    "sg:classifiers":[
        {
            "category":"Banks & Credit Unions",
            "subcategory":"Investment Brokerage",
            "type":"Services"
        }
    ],
    "sg:phone":"+41 18295161",
    "sg:postcode":"8152",
    "sg:province":"Z\u00fcrich",
    "sg:tags":[
        "consulting"
    ],
    "wof:name":"Travex Versicherungstreuhand Ag",
    "wof:placetype":"venue"
},
  "geometry": {"coordinates":[8.561501,47.432713],"type":"Point"}
}