{
  "type": "Feature",
  "properties": {
    "iso:country":"CH",
    "sg:address":"Hirschelenstrasse",
    "sg:city":"Rebstein",
    "sg:orig_category":"Organisationen des Gesundheitswesen",
    "sg:phone":"+41 71 777 19 17",
    "sg:postcode":"9445",
    "sg:province":"St. Gallen",
    "wof:name":"Samariterverein Rebstein",
    "wof:placetype":"venue"
},
  "geometry": {"coordinates":[9.5747089386,47.3991851807],"type":"Point"}
}