{
  "type": "Feature",
  "properties": {
    "iso:country":"CH",
    "sg:address":"Landererstrasse 9",
    "sg:city":"Reinach",
    "sg:classifiers":[
        {
            "category":"Building & Trades",
            "subcategory":"Cleaning & Sanitation",
            "type":"Services"
        }
    ],
    "sg:phone":"+41 61 711 11 31",
    "sg:postcode":"4153",
    "sg:province":"Basel-Landschaft",
    "sg:tags":[
        "carpet"
    ],
    "wof:name":"Hemo-reinigungsunternehmen Gmbh",
    "wof:placetype":"venue"
},
  "geometry": {"coordinates":[7.591403,47.495018],"type":"Point"}
}