{
  "type": "Feature",
  "properties": {
    "iso:country":"CH",
    "sg:address":"Bahnhofstrasse 17",
    "sg:city":"Dielsdorf",
    "sg:orig_category":"Unclassifiable Establishments",
    "sg:postcode":"8157",
    "sg:province":"Z\u00fcrich",
    "wof:name":"Spillmann U., Drogerie Am Lindenplatz, Zweigniederlassung Dielsdorf",
    "wof:placetype":"venue"
},
  "geometry": {"coordinates":[8.4564743042,47.4824028015],"type":"Point"}
}