{
  "type": "Feature",
  "properties": {
    "iso:country":"CH",
    "sg:address":"Blumenaustrasse 17",
    "sg:city":"Winterthur",
    "sg:orig_category":"Detailhandel mit Blumen U Pflanzen",
    "sg:phone":"+41 52 222 31 35",
    "sg:postcode":"8400",
    "sg:province":"Z\u00fcrich",
    "wof:name":"Blumen-bertschinger",
    "wof:placetype":"venue"
},
  "geometry": {"coordinates":[8.710692,47.505917],"type":"Point"}
}