{
  "type": "Feature",
  "properties": {
    "iso:country":"CH",
    "sg:address":"Bahnhofstrasse 17",
    "sg:city":"Uetendorf",
    "sg:orig_category":"Wasserversorgung",
    "sg:phone":"+41 33 345 63 90",
    "sg:postcode":"3661",
    "sg:province":"Bern",
    "wof:name":"Aqua Pur Engineering Ag",
    "wof:placetype":"venue"
},
  "geometry": {"coordinates":[7.5730109215,46.7749176025],"type":"Point"}
}