{
  "type": "Feature",
  "properties": {
    "iso:country":"CH",
    "sg:address":"Via Croce Campagna 17",
    "sg:city":"Stabio",
    "sg:orig_category":"Herstellung von M\u00f6beln",
    "sg:phone":"+41 91 647 27 65",
    "sg:postcode":"6855",
    "sg:province":"Ticino",
    "wof:name":"Alberto Broggi Mobili & Serramenti",
    "wof:placetype":"venue"
},
  "geometry": {"coordinates":[8.9513502121,45.8554534912],"type":"Point"}
}