{
  "type": "Feature",
  "properties": {
    "iso:country":"CH",
    "sg:address":"Casa Comunale",
    "sg:city":"Iragna",
    "sg:orig_category":"Vorschulen, Kinderg\u00e4rten",
    "sg:postcode":"6707",
    "sg:province":"Ticino",
    "wof:name":"Scuola Materna",
    "wof:placetype":"venue"
},
  "geometry": {"coordinates":[9.0590686798,46.0849113464],"type":"Point"}
}