{
  "type": "Feature",
  "properties": {
    "iso:country":"CH",
    "sg:address":"Inselgasse 1 3003 Bern. Postfach",
    "sg:city":"Bern",
    "sg:orig_category":"Verwaltung Inneres",
    "sg:phone":"+41 31 322 91 11",
    "sg:postcode":"3003",
    "sg:province":"Bern",
    "wof:name":"Eidgen\u00f6ssisches Departement Des Innern - Edi",
    "wof:placetype":"venue"
},
  "geometry": {"coordinates":[7.4459447861,46.9470863342],"type":"Point"}
}