{
  "type": "Feature",
  "properties": {
    "iso:country":"CH",
    "sg:address":"Wiedenstrasse 15 9323 Steinach. Postfach",
    "sg:city":"Steinach",
    "sg:orig_category":"Grosshandel mit B\u00fcrom\u00f6beln Herstellung von Hebezeugen U F\u00f6rdermitteln",
    "sg:phone":"+41 71 446 65 15",
    "sg:postcode":"9323",
    "sg:province":"St. Gallen",
    "wof:name":"Schemotec Ag F\u00f6rder, Lager Und Betriebseinrichtungen; Projektierung, Ausf\u00fchrung Und Vertrieb",
    "wof:placetype":"venue"
},
  "geometry": {"coordinates":[9.434387207,47.5032920837],"type":"Point"}
}