{
  "type": "Feature",
  "properties": {
    "iso:country":"CH",
    "sg:address":"Gewerbezone Kappelengand",
    "sg:city":"M\u00fclenen",
    "sg:orig_category":"Herstellung von sonstigen landwirtschaftlichen Maschinen Instandhaltung U Reparatur von Automobilen",
    "sg:phone":"+41 33 676 10 00",
    "sg:postcode":"3711",
    "sg:province":"Bern",
    "wof:name":"Kratzer Markus",
    "wof:placetype":"venue"
},
  "geometry": {"coordinates":[7.691660881,46.6384048462],"type":"Point"}
}