{
  "type": "Feature",
  "properties": {
    "iso:country":"CH",
    "sg:address":"4207",
    "sg:city":"Bretzwil",
    "sg:orig_category":"Landesverteidigung, Sozialversicherung \u00d6ffentliche Verwaltung",
    "sg:phone":"+41 33 951 26 42",
    "sg:postcode":"4207",
    "sg:province":"Basel-Landschaft",
    "wof:name":"Zivilschutzstelle Brienz",
    "wof:placetype":"venue"
},
  "geometry": {"coordinates":[8.0454683304,46.7534065247],"type":"Point"}
}