{
  "type": "Feature",
  "properties": {
    "iso:country":"CH",
    "sg:address":"Kamorstrasse 8",
    "sg:city":"Rorschach",
    "sg:orig_category":"Sonstige Kultur U Unterhaltungseinrichtungen Tanzschulen, Tanzlehrer",
    "sg:phone":"+41 71 841 11 33",
    "sg:postcode":"9400",
    "sg:province":"St. Gallen",
    "wof:name":"Dance Loft Tanz-& Ballettschulen",
    "wof:placetype":"venue"
},
  "geometry": {"coordinates":[9.4825878143,47.4767227173],"type":"Point"}
}