{
  "type": "Feature",
  "properties": {
    "iso:country":"CH",
    "sg:address":"Wilenstrasse 1",
    "sg:city":"Kaltbrunn",
    "sg:orig_category":"Non-Classified Establishments",
    "sg:phone":"+41 55 283 19 46",
    "sg:postcode":"8722",
    "sg:province":"St. Gallen",
    "wof:name":"Destra Holding Ag.",
    "wof:placetype":"venue"
},
  "geometry": {"coordinates":[9.0374202728,47.2095794678],"type":"Point"}
}