{
  "type": "Feature",
  "properties": {
    "iso:country":"CH",
    "sg:address":"Am Brotkorb 14",
    "sg:city":"H\u00e4gendorf",
    "sg:orig_category":"Unclassifiable Establishments",
    "sg:postcode":"4614",
    "sg:province":"Solothurn",
    "wof:name":"Provital Affolter & Fonti Physio, Manual Und Trainingstherapie",
    "wof:placetype":"venue"
},
  "geometry": {"coordinates":[8.6900548935,47.3005561829],"type":"Point"}
}