{
  "type": "Feature",
  "properties": {
    "iso:country":"CH",
    "sg:address":"6850 Mendrisio. Postfach Caselle Postale 11",
    "sg:city":"Mendrisio",
    "sg:orig_category":"Sportvereine Ski",
    "sg:phone":"+41 91 646 30 67",
    "sg:postcode":"6850",
    "sg:province":"Ticino",
    "wof:name":"Sci Club Mendrisio",
    "wof:placetype":"venue"
},
  "geometry": {"coordinates":[8.9789495468,45.876991272],"type":"Point"}
}