{
  "type": "Feature",
  "properties": {
    "iso:country":"CH",
    "sg:address":"Marly-centre 1723 Marly. Postfach",
    "sg:city":"Marly",
    "sg:orig_category":"Fachdetailhandel in Verkaufsr\u00e4umen",
    "sg:postcode":"1723",
    "sg:province":"Fribourg",
    "wof:name":"Sciboz G\u00e9rald",
    "wof:placetype":"venue"
},
  "geometry": {"coordinates":[7.1575598717,46.7824287415],"type":"Point"}
}