{
  "type": "Feature",
  "properties": {
    "addr:full":"Egelgasse 56 Bern Bern 3006",
    "addr:housenumber":"56",
    "addr:postcode":"3006",
    "addr:street":"Egelgasse",
    "iso:country":"CH",
    "sg:address":"Egelgasse 56",
    "sg:city":"Bern",
    "sg:orig_category":"Arztpraxen",
    "sg:phone":"+41 31 351 64 93",
    "sg:postcode":"3006",
    "sg:province":"Bern",
    "wof:name":"Dr.med.hansruedi Leuenberger Spezialarzt Fmh",
    "wof:placetype":"venue"
},
  "geometry": {"coordinates":[7.467348,46.944378],"type":"Point"}
}