{
  "type": "Feature",
  "properties": {
    "iso:country":"CH",
    "sg:address":"Stadlerstrasse 48 8404 Stadel(winterthur). Postfach 3020",
    "sg:city":"Stadel(winterthur)",
    "sg:orig_category":"Binnenschiffahrt",
    "sg:phone":"+41 52 242 14 42",
    "sg:postcode":"8404",
    "sg:province":"Z\u00fcrich",
    "wof:name":"Wagner Frachtschiffreisen",
    "wof:placetype":"venue"
},
  "geometry": {"coordinates":[8.761498,47.534218],"type":"Point"}
}