{
  "type": "Feature",
  "properties": {
    "addr:full":"In Lampitz\u00e4ckern 60 Dietlikon Z\u00fcrich 8305",
    "addr:housenumber":"60",
    "addr:postcode":"8305",
    "iso:country":"CH",
    "sg:address":"In Lampitz\u00e4ckern 60",
    "sg:city":"Dietlikon",
    "sg:orig_category":"Allgemeiner Hoch U Tiefbau Grosshandel mit Baumaterialien",
    "sg:postcode":"8305",
    "sg:province":"Z\u00fcrich",
    "wof:name":"Bautrupp Gmbh Baugesch\u00e4ft",
    "wof:placetype":"venue"
},
  "geometry": {"coordinates":[8.613698,47.414909],"type":"Point"}
}