{
  "type": "Feature",
  "properties": {
    "iso:country":"CH",
    "sg:address":"Herbstackerstrasse 82",
    "sg:city":"Seuzach",
    "sg:orig_category":"Wirtschaftsverb\u00e4nde Gewerbeverb\u00e4nde/-vereine",
    "sg:phone":"+41 52 335 18 42",
    "sg:postcode":"8472",
    "sg:province":"Z\u00fcrich",
    "wof:name":"Gewerbeverein Seuzach-ohringen Herr Gustav Steinmann",
    "wof:placetype":"venue"
},
  "geometry": {"coordinates":[8.7382497787,47.5389938354],"type":"Point"}
}