{
  "type": "Feature",
  "properties": {
    "iso:country":"CH",
    "sg:address":"Avenue D'ouchy 60 1000 Lausanne. Postfach",
    "sg:city":"Lausanne",
    "sg:orig_category":"Fotografisches Gewerbe U fotografische Laboratorien",
    "sg:postcode":"1003",
    "sg:province":"Vaud",
    "wof:name":"Vision Du Ciel, Ch Sarl",
    "wof:placetype":"venue"
},
  "geometry": {"coordinates":[6.6876702309,46.559551239],"type":"Point"}
}