{
  "type": "Feature",
  "properties": {
    "addr:full":"Rue Du March\u00e9 40 Gen\u00e8ve Gen\u00e8ve 1204",
    "addr:housenumber":"40",
    "addr:postcode":"1204",
    "addr:street":"Rue Du Marche\u0301",
    "iso:country":"CH",
    "sg:address":"Rue Du March\u00e9 40",
    "sg:city":"Gen\u00e8ve",
    "sg:classifiers":[
        {
            "category":"Banks & Credit Unions",
            "subcategory":"Bank",
            "type":"Services"
        }
    ],
    "sg:phone":"+41 22 311 89 33",
    "sg:postcode":"1204",
    "sg:province":"Gen\u00e8ve",
    "wof:name":"Bank Of America, National & Trust & Savings Ass.",
    "wof:placetype":"venue"
},
  "geometry": {"coordinates":[6.14754,46.203018],"type":"Point"}
}