{
  "type": "Feature",
  "properties": {
    "iso:country":"CH",
    "sg:address":"Rte Cantonale 18",
    "sg:city":"V\u00e9troz",
    "sg:orig_category":"Wirtschaftspr\u00fcfung, Steuerberatung U Treuhand",
    "sg:phone":"+41 27 722 34 22",
    "sg:postcode":"1963",
    "sg:province":"Valais",
    "wof:name":"Soci\u00e9t\u00e9 Fiduciaire Des Alpes Sa",
    "wof:placetype":"venue"
},
  "geometry": {"coordinates":[7.2934241295,46.2255401611],"type":"Point"}
}