{
  "type": "Feature",
  "properties": {
    "iso:country":"CH",
    "sg:address":"Gr\u00fctstrasse 45",
    "sg:city":"Herrliberg",
    "sg:orig_category":"Erbringung von Dienstleistungen f\u00fcr Unternehmen",
    "sg:postcode":"8704",
    "sg:province":"Z\u00fcrich",
    "wof:name":"Margolis & Associate Consulting",
    "wof:placetype":"venue"
},
  "geometry": {"coordinates":[8.6079072952,47.2878990173],"type":"Point"}
}