{
  "type": "Feature",
  "properties": {
    "iso:country":"CH",
    "sg:address":"Joliette Chemin De La 2 1006 Lausanne. Postfach",
    "sg:city":"Lausanne",
    "sg:orig_category":"Unclassifiable Establishments",
    "sg:postcode":"1006",
    "sg:province":"Vaud",
    "wof:name":"Si Rue Madeleine No 22 Vevey Sa",
    "wof:placetype":"venue"
},
  "geometry": {"coordinates":[5.1808700562,45.8973388672],"type":"Point"}
}