{
  "type": "Feature",
  "properties": {
    "iso:country":"CH",
    "sg:address":"Str\u00e4ttligerweg 3 3626 H\u00fcnibach. Postfach",
    "sg:city":"H\u00fcnibach",
    "sg:orig_category":"Non-Classified Establishments",
    "sg:phone":"+41 33 243 42 61",
    "sg:postcode":"3626",
    "sg:province":"Bern",
    "wof:name":"Saecom Computer-systems Helfenstein-sae Lim Franz",
    "wof:placetype":"venue"
},
  "geometry": {"coordinates":[7.644701004,46.7444992065],"type":"Point"}
}