{
  "type": "Feature",
  "properties": {
    "iso:country":"CH",
    "sg:address":"Rathausg\u00e4ssli 6",
    "sg:city":"Biel/bienne",
    "sg:orig_category":"Physiotherapie",
    "sg:phone":"+41 32 384 63 01",
    "sg:postcode":"2502",
    "sg:province":"Bern",
    "wof:name":"Werner M\u00fcller Osteopathie",
    "wof:placetype":"venue"
},
  "geometry": {"coordinates":[7.2458901405,47.1411437988],"type":"Point"}
}