{
  "type": "Feature",
  "properties": {
    "iso:country":"CH",
    "sg:address":"Dorfstrasse 17",
    "sg:city":"Untersiggenthal",
    "sg:orig_category":"Elektroinstallation Herstellung von Elektromotoren, Generatoren U Transformatoren",
    "sg:phone":"+41 32 931 67 67",
    "sg:postcode":"5417",
    "sg:province":"Aargau",
    "wof:name":"Schiess-electricit\u00e9-t\u00e9l\u00e9phone Sa",
    "wof:placetype":"venue"
},
  "geometry": {"coordinates":[6.7447371483,47.0533218384],"type":"Point"}
}