{
  "type": "Feature",
  "properties": {
    "iso:country":"CH",
    "sg:address":"P\u00e9rolles Boulevard De 7",
    "sg:city":"Fribourg",
    "sg:orig_category":"Herstellung von Papier, Karton U Pappe",
    "sg:phone":"+41 81 307 90 90",
    "sg:postcode":"1700",
    "sg:province":"Fribourg",
    "wof:name":"Landqart",
    "wof:placetype":"venue"
},
  "geometry": {"coordinates":[9.5664892197,46.9523963928],"type":"Point"}
}