{
  "type": "Feature",
  "properties": {
    "iso:country":"CH",
    "sg:address":"Kirchgasse 8 5612 Villmergen. Postfach 45",
    "sg:city":"Villmergen",
    "sg:classifiers":[
        {
            "category":"Restaurant",
            "type":"Food & Drink"
        }
    ],
    "sg:phone":"+41 71 222 23 64",
    "sg:postcode":"5612",
    "sg:province":"Aargau",
    "wof:name":"Restaurant Waldegg Am Bach",
    "wof:placetype":"venue"
},
  "geometry": {"coordinates":[9.4011898041,47.4155197144],"type":"Point"}
}