{
  "type": "Feature",
  "properties": {
    "iso:country":"CH",
    "sg:address":"Rte Croix-blanche 44",
    "sg:city":"Epalinges",
    "sg:classifiers":[
        {
            "category":"Banks & Credit Unions",
            "subcategory":"Bank",
            "type":"Services"
        }
    ],
    "sg:phone":"+41 21 784 06 07",
    "sg:postcode":"1066",
    "sg:province":"Vaud",
    "wof:name":"Banque Raiffeisen",
    "wof:placetype":"venue"
},
  "geometry": {"coordinates":[6.673983,46.548248],"type":"Point"}
}