{
  "type": "Feature",
  "properties": {
    "iso:country":"CH",
    "sg:address":"Rosenbergstrasse 45",
    "sg:city":"Neuhausen",
    "sg:orig_category":"Instandhaltung U Reparatur von Automobilen",
    "sg:phone":"+41 52 672 65 79",
    "sg:postcode":"8212",
    "sg:province":"Schaffhausen",
    "wof:name":"Soos Robert R / S Trade Service",
    "wof:placetype":"venue"
},
  "geometry": {"coordinates":[8.6174898148,47.6862678528],"type":"Point"}
}