{
  "type": "Feature",
  "properties": {
    "iso:country":"CH",
    "sg:address":"Forchstrasse 173",
    "sg:city":"Zollikerberg",
    "sg:orig_category":"Sonstiger Grosshandel",
    "sg:phone":"+41 13901520",
    "sg:postcode":"8125",
    "sg:province":"Z\u00fcrich",
    "wof:name":"Pacel Ag",
    "wof:placetype":"venue"
},
  "geometry": {"coordinates":[8.6005411148,47.3468055725],"type":"Point"}
}