{
  "type": "Feature",
  "properties": {
    "iso:country":"CH",
    "sg:address":"Unterm\u00fcli 9",
    "sg:city":"Zug",
    "sg:orig_category":"Handelsvermittlung von Brennstoffen, Erzen, Metallen U Chemikalien",
    "sg:phone":"+41 22 827 02 40",
    "sg:postcode":"6300",
    "sg:province":"Zug",
    "wof:name":"Botrop Finances Sa",
    "wof:placetype":"venue"
},
  "geometry": {"coordinates":[6.1420788765,46.1867980957],"type":"Point"}
}