{
  "type": "Feature",
  "properties": {
    "iso:country":"CH",
    "sg:address":"Obere Zollgasse 45",
    "sg:city":"Ostermundigen",
    "sg:orig_category":"Maler U Glasergewerbe",
    "sg:phone":"+41 31 931 20 14",
    "sg:postcode":"3072",
    "sg:province":"Bern",
    "wof:name":"Kohler & Weibel",
    "wof:placetype":"venue"
},
  "geometry": {"coordinates":[7.4855499268,46.9528884888],"type":"Point"}
}