{
  "type": "Feature",
  "properties": {
    "iso:country":"CH",
    "sg:address":"Route De Ch\u00e9rard 1 1027 Lonay. Postfach",
    "sg:city":"Lonay",
    "sg:classifiers":[
        {
            "category":"Insurance",
            "subcategory":"Insurance Agent",
            "type":"Services"
        }
    ],
    "sg:phone":"+41 21 801 16 32",
    "sg:postcode":"1027",
    "sg:province":"Vaud",
    "sg:tags":[
        "versicherungsagenturen",
        "-broker"
    ],
    "wof:name":"Michel Infantolino Rentenanstalt Swiss Life Ass.",
    "wof:placetype":"venue"
},
  "geometry": {"coordinates":[6.5204148293,46.5265235901],"type":"Point"}
}