{
  "type": "Feature",
  "properties": {
    "iso:country":"CH",
    "sg:address":"Route De St-julien 261 1258 Perly Case Postale 139",
    "sg:city":"Perly",
    "sg:orig_category":"Malerei Stukkateurgewerbe, Gipserei U Verputzerei",
    "sg:phone":"+41 22 721 10 40",
    "sg:postcode":"1258",
    "sg:province":"Gen\u00e8ve",
    "wof:name":"Nobile & Cie",
    "wof:placetype":"venue"
},
  "geometry": {"coordinates":[6.097509861,46.157535553],"type":"Point"}
}