{
  "type": "Feature",
  "properties": {
    "iso:country":"CH",
    "sg:address":"Fribourg Route De 5",
    "sg:city":"Marly",
    "sg:orig_category":"Sonstige Hilfs U Nebent\u00e4tigkeiten f\u00fcr die Schiffahrt",
    "sg:phone":"+41 26 439 99 20",
    "sg:postcode":"1723",
    "sg:province":"Fribourg",
    "wof:name":"Sbm Offshore Contractors Inc",
    "wof:placetype":"venue"
},
  "geometry": {"coordinates":[7.1554899216,46.7783432007],"type":"Point"}
}