{
  "type": "Feature",
  "properties": {
    "iso:country":"CH",
    "sg:address":"Bleuen 18",
    "sg:city":"Oeschenbach",
    "sg:orig_category":"Gemeindeverwaltungen",
    "sg:phone":"+41 62 965 24 34",
    "sg:postcode":"4943",
    "sg:province":"Bern",
    "wof:name":"Gemeindeverwaltung Oeschenbach",
    "wof:placetype":"venue"
},
  "geometry": {"coordinates":[7.7543940544,47.11561203],"type":"Point"}
}