{
  "type": "Feature",
  "properties": {
    "iso:country":"CH",
    "sg:address":"Obere T\u00e4schenstrasse 1b",
    "sg:city":"Heiden",
    "sg:orig_category":"Maurerarbeiten",
    "sg:phone":"+41 71 891 28 17",
    "sg:postcode":"9410",
    "sg:province":"Appenzell Ausserrhoden",
    "wof:name":"Franz Schwarz Maurergesch\u00e4ft",
    "wof:placetype":"venue"
},
  "geometry": {"coordinates":[9.5302886963,47.4385070801],"type":"Point"}
}