{
  "type": "Feature",
  "properties": {
    "iso:country":"CH",
    "sg:address":"1070",
    "sg:city":"Puidoux",
    "sg:orig_category":"Herstellung von elektrischen Lampen U Leuchten",
    "sg:phone":"+41 31 972 54 53",
    "sg:postcode":"1070",
    "sg:province":"Vaud",
    "wof:name":"Hofschneider Licht, Technik Und Gestaltung",
    "wof:placetype":"venue"
},
  "geometry": {"coordinates":[7.5663838387,46.8787765503],"type":"Point"}
}