{
  "type": "Feature",
  "properties": {
    "iso:country":"CH",
    "sg:address":"Schl\u00f6sslistrasse 34 6045 Meggen. Postfach 754",
    "sg:city":"Meggen",
    "sg:orig_category":"Hardwareberatung",
    "sg:phone":"+41 41 378 03 78",
    "sg:postcode":"6045",
    "sg:province":"Luzern",
    "wof:name":"Bl\u00e4ttler Computer-service Bcs",
    "wof:placetype":"venue"
},
  "geometry": {"coordinates":[8.3694448471,47.0488624573],"type":"Point"}
}