{
  "type": "Feature",
  "properties": {
    "iso:country":"CH",
    "sg:address":"Gratte-semelle 29",
    "sg:city":"Neuch\u00e2tel",
    "sg:orig_category":"Sportvereine Ballsport Tischtennis",
    "sg:phone":"+41 32 931 21 24",
    "sg:postcode":"2000",
    "sg:province":"Neuch\u00e2tel",
    "wof:name":"Ctt Le Locle",
    "wof:placetype":"venue"
},
  "geometry": {"coordinates":[6.7536702156,47.060962677],"type":"Point"}
}