{
  "type": "Feature",
  "properties": {
    "iso:country":"CH",
    "sg:address":"Route De Neuch\u00e2tel",
    "sg:city":"Payerne",
    "sg:orig_category":"Herstellung von Karosserien U Anh\u00e4ngern",
    "sg:phone":"+41 26 660 55 60",
    "sg:postcode":"1530",
    "sg:province":"Vaud",
    "wof:name":"Carrosserie Nouvelle - Decorges Fernand",
    "wof:placetype":"venue"
},
  "geometry": {"coordinates":[6.9384999275,46.8247947693],"type":"Point"}
}