{
  "type": "Feature",
  "properties": {
    "iso:country":"CH",
    "sg:address":"Kellersackerstrasse 17 8424 Embrach. Postfach 162",
    "sg:city":"Embrach",
    "sg:orig_category":"Fachdetailhandel in Verkaufsr\u00e4umen Grosshandel mit Sportartikeln",
    "sg:phone":"+41 18654751",
    "sg:postcode":"8424",
    "sg:province":"Z\u00fcrich",
    "wof:name":"Mad Products Gmbh",
    "wof:placetype":"venue"
},
  "geometry": {"coordinates":[8.5921163559,47.514541626],"type":"Point"}
}