{
  "type": "Feature",
  "properties": {
    "iso:country":"CH",
    "sg:address":"Gerbestrasse 12",
    "sg:city":"R\u00fcegsauschachen",
    "sg:orig_category":"Detailhandel mit Fleisch U Fleischwaren Grosshandel mit lebenden Tieren",
    "sg:phone":"+41 34 461 11 43",
    "sg:postcode":"3415",
    "sg:province":"Bern",
    "wof:name":"H\u00e4hni Urs",
    "wof:placetype":"venue"
},
  "geometry": {"coordinates":[7.6622300148,47.0172195435],"type":"Point"}
}