{
  "type": "Feature",
  "properties": {
    "iso:country":"CH",
    "sg:address":"Piazza Indipendenza 1",
    "sg:city":"Lugano",
    "sg:orig_category":"Detailhandel mit Antiquit\u00e4ten Detailhandel mit B\u00fcchern",
    "sg:phone":"+41 91 922 68 21",
    "sg:postcode":"6900",
    "sg:province":"Ticino",
    "wof:name":"La Bottega Delle Stampa",
    "wof:placetype":"venue"
},
  "geometry": {"coordinates":[8.954657,46.005035],"type":"Point"}
}