{
  "type": "Feature",
  "properties": {
    "iso:country":"CH",
    "sg:address":"Kanzleistrasse 5",
    "sg:city":"Berneck",
    "sg:orig_category":"Darlehenskassen U Raiffeisenbanken",
    "sg:phone":"+41 71 747 55 66",
    "sg:postcode":"9442",
    "sg:province":"St. Gallen",
    "wof:name":"Raiffeisenbank Berneck-au",
    "wof:placetype":"venue"
},
  "geometry": {"coordinates":[9.6103,47.424633],"type":"Point"}
}