{
  "type": "Feature",
  "properties": {
    "iso:country":"CH",
    "sg:address":"Victor Von Bruns-strasse",
    "sg:city":"Neuhausen",
    "sg:orig_category":"Bau U Wohngenossenschaften",
    "sg:postcode":"8212",
    "sg:province":"Schaffhausen",
    "wof:name":"Wohnbaugen.der Internationalen Verbandstoffabrik",
    "wof:placetype":"venue"
},
  "geometry": {"coordinates":[8.62411,47.680225],"type":"Point"}
}