{
  "type": "Feature",
  "properties": {
    "iso:country":"CH",
    "sg:address":"Via Trevano 89a",
    "sg:city":"Lugano",
    "sg:classifiers":[
        {
            "category":"Bars & Pubs",
            "type":"Food & Drink"
        }
    ],
    "sg:phone":"+41 21 636 24 28",
    "sg:postcode":"6900",
    "sg:province":"Ticino",
    "wof:name":"Bar Apollo 2000",
    "wof:placetype":"venue"
},
  "geometry": {"coordinates":[6.583743,46.54509],"type":"Point"}
}