{
  "type": "Feature",
  "properties": {
    "iso:country":"CH",
    "sg:address":"Griesernweg 16",
    "sg:city":"Z\u00fcrich",
    "sg:orig_category":"Unternehmensberatung Werbevermittlung",
    "sg:phone":"+41 12716080",
    "sg:postcode":"8037",
    "sg:province":"Z\u00fcrich",
    "wof:name":"Dr.franz Suter Marketingberatung",
    "wof:placetype":"venue"
},
  "geometry": {"coordinates":[8.5197267532,47.3970527649],"type":"Point"}
}