{
  "type": "Feature",
  "properties": {
    "iso:country":"CH",
    "sg:address":"Grand-champs",
    "sg:city":"Porrentruy",
    "sg:orig_category":"Herstellung von Uhren",
    "sg:phone":"+41 32 466 87 61",
    "sg:postcode":"2900",
    "sg:province":"Jura",
    "wof:name":"Mulcor S\u00e0rl",
    "wof:placetype":"venue"
},
  "geometry": {"coordinates":[7.0688447952,47.4155693054],"type":"Point"}
}