{
  "type": "Feature",
  "properties": {
    "iso:country":"CH",
    "sg:address":"Via Zurigo 7",
    "sg:city":"Lugano",
    "sg:classifiers":[
        {
            "category":"Restaurant",
            "type":"Food & Drink"
        }
    ],
    "sg:phone":"+41 91 923 27 26",
    "sg:postcode":"6900",
    "sg:province":"Ticino",
    "wof:name":"Ristorante Cinese Shanghai",
    "wof:placetype":"venue"
},
  "geometry": {"coordinates":[8.9549274445,46.0114746094],"type":"Point"}
}