{
  "type": "Feature",
  "properties": {
    "iso:country":"CH",
    "sg:address":"Bergstrasse 20",
    "sg:city":"Safnern",
    "sg:orig_category":"Vorschulen, Kinderg\u00e4rten",
    "sg:phone":"+41 32 355 14 72",
    "sg:postcode":"2553",
    "sg:province":"Bern",
    "wof:name":"Kindergarten Schulhaus R\u00e4bli",
    "wof:placetype":"venue"
},
  "geometry": {"coordinates":[7.3211140633,47.1527938843],"type":"Point"}
}