{
  "type": "Feature",
  "properties": {
    "iso:country":"CH",
    "sg:address":"Rue Des Voisins 11 1205 Gen\u00e8ve. Postfach",
    "sg:city":"Gen\u00e8ve",
    "sg:orig_category":"Detailhandel mit Radio U Fernsehger\u00e4ten Detailhandel mit elektrischen Haushalts-,Radio U Fernsehger\u00e4",
    "sg:phone":"+41 22 800 27 20",
    "sg:postcode":"1201",
    "sg:province":"Gen\u00e8ve",
    "wof:name":"Inout Num\u00e9rique, Beney Philippe Stations De Montage Vid\u00e9o Virtuelles, Cam\u00e9ras Dv Etc.; Vente",
    "wof:placetype":"venue"
},
  "geometry": {"coordinates":[6.1445250511,46.19581604],"type":"Point"}
}