{
  "type": "Feature",
  "properties": {
    "iso:country":"CH",
    "sg:address":"Br\u00fcgglistrasse 52",
    "sg:city":"Altendorf",
    "sg:classifiers":[
        {
            "category":"Restaurant",
            "type":"Food & Drink"
        }
    ],
    "sg:phone":"+41 55 442 11 49",
    "sg:postcode":"8852",
    "sg:province":"Schwyz",
    "wof:name":"Restaurant Br\u00fcggli",
    "wof:placetype":"venue"
},
  "geometry": {"coordinates":[8.8463306427,47.1868782043],"type":"Point"}
}