{
  "type": "Feature",
  "properties": {
    "iso:country":"CH",
    "sg:address":"K\u00e4sereistrasse 6 Niederscherli 3098 K\u00f6niz. Postfach",
    "sg:city":"Niederscherli",
    "sg:orig_category":"Herstellung von Betonerzeugnissen f\u00fcr den Bau",
    "sg:postcode":"3145",
    "sg:province":"Bern",
    "wof:name":"Tschaggelar Bau Und Normelemente Gmbh",
    "wof:placetype":"venue"
},
  "geometry": {"coordinates":[7.414276123,46.9228744507],"type":"Point"}
}