{
  "type": "Feature",
  "properties": {
    "iso:country":"CH",
    "sg:address":"Ceresstrasse 17",
    "sg:city":"Z\u00fcrich",
    "sg:orig_category":"Schreib U \u00dcbersetzungsb\u00fcros -\u00dcbersetzungsb\u00fcros",
    "sg:phone":"+41 52 763 33 66",
    "sg:postcode":"8008",
    "sg:province":"Z\u00fcrich",
    "wof:name":"Ibs Business Services Ag",
    "wof:placetype":"venue"
},
  "geometry": {"coordinates":[8.9984264374,47.6059341431],"type":"Point"}
}