{
  "type": "Feature",
  "properties": {
    "iso:country":"CH",
    "sg:address":"Rebbergstrasse 29",
    "sg:city":"Zofingen",
    "sg:orig_category":"Herstellung von Maschinen f\u00fcr das Papiergewerbe",
    "sg:phone":"+41 62 751 47 28",
    "sg:postcode":"4800",
    "sg:province":"Aargau",
    "wof:name":"Verfag Ag",
    "wof:placetype":"venue"
},
  "geometry": {"coordinates":[7.9518141747,47.2915267944],"type":"Point"}
}