{
  "type": "Feature",
  "properties": {
    "iso:country":"CH",
    "sg:address":"1148",
    "sg:city":"L'isle",
    "sg:orig_category":"Herstellung von Konstruktionsteilen, Fertigbauteilen U Ausbauelementen aus Holz",
    "sg:postcode":"1148",
    "sg:province":"Vaud",
    "wof:name":"Bernard G\u00e9rald Menuiserie Charpente",
    "wof:placetype":"venue"
},
  "geometry": {"coordinates":[-93.47286224370001,46.1380386353],"type":"Point"}
}