{
  "type": "Feature",
  "properties": {
    "iso:country":"CH",
    "sg:address":"Hagmattstrasse 15",
    "sg:city":"Allschwil",
    "sg:orig_category":"Instandhaltung U Reparatur von Automobilen",
    "sg:phone":"+41 61 481 81 40",
    "sg:postcode":"4123",
    "sg:province":"Basel-Landschaft",
    "wof:name":"Garage Antonucci Gmbh",
    "wof:placetype":"venue"
},
  "geometry": {"coordinates":[7.542427063,47.5566940308],"type":"Point"}
}