{
  "type": "Feature",
  "properties": {
    "iso:country":"CH",
    "sg:address":"Unterdorfstrasse 44",
    "sg:city":"Igis",
    "sg:orig_category":"Bauingenieurb\u00fcros Sanit\u00e4r",
    "sg:phone":"+41 41 498 08 62",
    "sg:postcode":"7206",
    "sg:province":"Graubunden",
    "wof:name":"Erwin Portmann Planungsb\u00fcro Sanit\u00e4r",
    "wof:placetype":"venue"
},
  "geometry": {"coordinates":[8.182725,47.036816],"type":"Point"}
}