{
  "type": "Feature",
  "properties": {
    "iso:country":"CH",
    "sg:address":"Brunnenstrasse 27",
    "sg:city":"Uster",
    "sg:orig_category":"Kunsthandel",
    "sg:phone":"+41 19415120",
    "sg:postcode":"8610",
    "sg:province":"Z\u00fcrich",
    "wof:name":"Monika Hoppe Galerie Villa Bianchi",
    "wof:placetype":"venue"
},
  "geometry": {"coordinates":[8.7225141525,47.3526268005],"type":"Point"}
}