{
  "type": "Feature",
  "properties": {
    "iso:country":"CH",
    "sg:address":"Dugglistrasse 25",
    "sg:city":"Cham",
    "sg:orig_category":"Verwaltung von Immobilien",
    "sg:postcode":"6330",
    "sg:province":"Zug",
    "wof:name":"\u00abst\u00e4dtli\u00bb Bau Ag",
    "wof:placetype":"venue"
},
  "geometry": {"coordinates":[8.4692106247,47.1851081848],"type":"Point"}
}