{
  "type": "Feature",
  "properties": {
    "iso:country":"CH",
    "sg:address":"Hotel-restaurant Stechelberg 3822 Lauterbrunnen. Postfach",
    "sg:city":"Stechelberg",
    "sg:classifiers":[
        {
            "category":"Travel",
            "subcategory":"Hotels & Motels",
            "type":"Entertainment"
        }
    ],
    "sg:phone":"+41 61 721 10 32",
    "sg:postcode":"3824",
    "sg:province":"Bern",
    "sg:tags":[
        "hotels",
        "mit",
        "restaurant"
    ],
    "wof:name":"Gertsch-aeschlimann Walter Und Annarosa.",
    "wof:placetype":"venue"
},
  "geometry": {"coordinates":[7.5203027725,47.5030403137],"type":"Point"}
}