{
  "type": "Feature",
  "properties": {
    "iso:country":"CH",
    "sg:address":"Freiburgstrasse 123",
    "sg:city":"Bern",
    "sg:orig_category":"Herstellung von Konstruktionsteilen, Fertigbauteilen U Ausbauelementen aus Holz",
    "sg:postcode":"3008",
    "sg:province":"Bern",
    "wof:name":"Schmutz + Loosli",
    "wof:placetype":"venue"
},
  "geometry": {"coordinates":[7.4106497765,46.9428596497],"type":"Point"}
}