{
  "type": "Feature",
  "properties": {
    "iso:country":"CH",
    "sg:address":"Oberholzweg 16",
    "sg:city":"Herzogenbuchsee",
    "sg:orig_category":"Institutionen f\u00fcr Behinderte Institutionen f\u00fcr psychosoziale F\u00e4lle",
    "sg:phone":"+41 62 961 14 15",
    "sg:postcode":"3360",
    "sg:province":"Bern",
    "wof:name":"Raz Regionales Arbeitszentrum",
    "wof:placetype":"venue"
},
  "geometry": {"coordinates":[7.7169079781,47.1855583191],"type":"Point"}
}