{
  "type": "Feature",
  "properties": {
    "iso:country":"CH",
    "sg:address":"Grand-rue 139",
    "sg:city":"Tramelan",
    "sg:orig_category":"Parf\u00fcmerien U sonstiger Detailhandel mit kosmetischen Artikeln U K\u00f6rperpflegemitteln",
    "sg:phone":"+41 32 487 62 10",
    "sg:postcode":"2720",
    "sg:province":"Bern",
    "wof:name":"Parfumerie Monique Monique Strahm",
    "wof:placetype":"venue"
},
  "geometry": {"coordinates":[7.1008358002,47.223110199],"type":"Point"}
}