{
  "type": "Feature",
  "properties": {
    "iso:country":"CH",
    "sg:address":"Turmhaldenstrasse 6",
    "sg:city":"Winterthur",
    "sg:orig_category":"Architektur U Ingenieurb\u00fcros Architekturb\u00fcros",
    "sg:phone":"+41 71 925 11 41",
    "sg:postcode":"8400",
    "sg:province":"Z\u00fcrich",
    "wof:name":"Egeter Remo Architektur & Planung Gmbh",
    "wof:placetype":"venue"
},
  "geometry": {"coordinates":[9.043986,47.460114],"type":"Point"}
}