{
  "type": "Feature",
  "properties": {
    "iso:country":"CH",
    "sg:address":"Rue Du Cheminet 21",
    "sg:city":"Yverdon-les-bains",
    "sg:orig_category":"Herstellung von Tanks U Sammelbeh\u00e4ltern aus Metall Sanit\u00e4r, Heizungs U L\u00fcftungsinstallation",
    "sg:phone":"+41 24 425 81 79",
    "sg:postcode":"1400",
    "sg:province":"Vaud",
    "wof:name":"Ecuyer Sa Yverdon",
    "wof:placetype":"venue"
},
  "geometry": {"coordinates":[6.6311311722,46.7817573547],"type":"Point"}
}