{
  "type": "Feature",
  "properties": {
    "iso:country":"CH",
    "sg:address":"Gerbergasse 5",
    "sg:city":"Luzern",
    "sg:orig_category":"Bijouterien Detailhandel mit Bekleidung",
    "sg:phone":"+41 41 410 58 03",
    "sg:postcode":"6004",
    "sg:province":"Luzern",
    "wof:name":"Tucano Schmuck & Textil Ag",
    "wof:placetype":"venue"
},
  "geometry": {"coordinates":[8.308357,47.053051],"type":"Point"}
}