{
  "type": "Feature",
  "properties": {
    "iso:country":"CH",
    "sg:address":"Landstrasse 31",
    "sg:city":"Oberurnen",
    "sg:orig_category":"Detailhandel mit Getr\u00e4nken Detailhandel mit Waren verschiedener Art, Hauptrichtung Nahrungsmittel",
    "sg:phone":"+41 55 610 17 29",
    "sg:postcode":"8868",
    "sg:province":"Glarus",
    "wof:name":"Elisabeth Sulser Lebensmittel Getr\u00e4nke",
    "wof:placetype":"venue"
},
  "geometry": {"coordinates":[9.0599031448,47.1145706177],"type":"Point"}
}