{
  "type": "Feature",
  "properties": {
    "addr:full":"Bieh\u00fcbeliweg 27 3012 Bern. Postfach Bern Bern 3005",
    "addr:housenumber":"27",
    "addr:postcode":"3012;postfach;3005",
    "addr:street":"Biehuebeliweg",
    "iso:country":"CH",
    "sg:address":"Bieh\u00fcbeliweg 27 3012 Bern. Postfach",
    "sg:city":"Bern",
    "sg:orig_category":"Architektur U Ingenieurb\u00fcros Innenarchitekturb\u00fcros",
    "sg:phone":"+41 31 302 58 85",
    "sg:postcode":"3005",
    "sg:province":"Bern",
    "wof:name":"Kn\u00d6pfel, Weiss Innenarchitekten Vsi. Asai",
    "wof:placetype":"venue"
},
  "geometry": {"coordinates":[7.43805,46.956039],"type":"Point"}
}