{
  "type": "Feature",
  "properties": {
    "iso:country":"CH",
    "sg:address":"Hinterrain 45",
    "sg:city":"W\u00f6lflinswil",
    "sg:orig_category":"Politische Parteien SVP",
    "sg:postcode":"5063",
    "sg:province":"Aargau",
    "wof:name":"Svp Ortspartei W\u00f6flinswil",
    "wof:placetype":"venue"
},
  "geometry": {"coordinates":[7.9949440956,47.4630584717],"type":"Point"}
}