{
  "type": "Feature",
  "properties": {
    "iso:country":"CH",
    "sg:address":"Haldenstrasse 19",
    "sg:city":"K\u00f6lliken",
    "sg:orig_category":"LANDW. GENOSSENSCHAFTEN GRASTROCKNUNGSANL",
    "sg:phone":"+41 62 723 19 56",
    "sg:postcode":"5742",
    "sg:province":"Aargau",
    "wof:name":"Bruno Widmer Grastrocknerei",
    "wof:placetype":"venue"
},
  "geometry": {"coordinates":[8.0172977448,47.3353233337],"type":"Point"}
}