{
  "type": "Feature",
  "properties": {
    "iso:country":"CH",
    "sg:address":"1880",
    "sg:city":"Bex",
    "sg:orig_category":"Oberfl\u00e4chenveredlung U W\u00e4rmebehandlung",
    "sg:phone":"+41 24 463 18 28",
    "sg:postcode":"1880",
    "sg:province":"Vaud",
    "wof:name":"Sutech Traitement De Surface Sa",
    "wof:placetype":"venue"
},
  "geometry": {"coordinates":[7.0156807899,46.2502593994],"type":"Point"}
}