{
  "type": "Feature",
  "properties": {
    "iso:country":"CH",
    "sg:address":"Oristalstrasse 87a 4410 Liestal. Postfach 440",
    "sg:city":"Liestal",
    "sg:orig_category":"Vermittlung von Immobilien",
    "sg:phone":"+41 19101642",
    "sg:postcode":"4410",
    "sg:province":"Basel-Landschaft",
    "wof:name":"Gastu Ag Immobilien",
    "wof:placetype":"venue"
},
  "geometry": {"coordinates":[8.5915107727,47.3229675293],"type":"Point"}
}