{
  "type": "Feature",
  "properties": {
    "iso:country":"CH",
    "sg:address":"Neumarkt 2",
    "sg:city":"St.gallen",
    "sg:orig_category":"Grosshandel mit B\u00fcrom\u00f6beln",
    "sg:phone":"+41 31 352 26 38",
    "sg:postcode":"9000",
    "sg:province":"St. Gallen",
    "wof:name":"Aeschimann Safe Gmbh Kassenschr\u00e4nke, Sicherheitssysteme Usw; Im, Export, Handel",
    "wof:placetype":"venue"
},
  "geometry": {"coordinates":[7.4464998245,46.9414291382],"type":"Point"}
}