{
  "type": "Feature",
  "properties": {
    "iso:country":"CH",
    "sg:address":"Aubrigstrasse 7 8857 Vorderthal. Postfach 58",
    "sg:city":"Vorderthal",
    "sg:orig_category":"Handelsvermittlung U Grosshandel Installation von Heizungs, L\u00fcftungs U Klimaanlagen",
    "sg:phone":"+41 61 723 17 77",
    "sg:postcode":"8857",
    "sg:province":"Schwyz",
    "wof:name":"Aircon Gmbh",
    "wof:placetype":"venue"
},
  "geometry": {"coordinates":[7.5253500938,47.5052108765],"type":"Point"}
}