{
  "type": "Feature",
  "properties": {
    "iso:country":"CH",
    "sg:address":"Beethovenstrasse 24 8002 Z\u00fcrich. Postfach 4080",
    "sg:city":"Z\u00fcrich",
    "sg:orig_category":"Privatbanken",
    "sg:phone":"+41 22 317 45 55",
    "sg:postcode":"8022",
    "sg:province":"Z\u00fcrich",
    "wof:name":"Banque Safra Jacob (suisse) Sa Bankgesch\u00e4fte",
    "wof:placetype":"venue"
},
  "geometry": {"coordinates":[8.5365257263,47.366809845],"type":"Point"}
}