{
  "type": "Feature",
  "properties": {
    "iso:country":"CH",
    "sg:address":"Haldenstrasse 21",
    "sg:city":"Luzern",
    "sg:orig_category":"Unclassifiable Establishments",
    "sg:postcode":"6006",
    "sg:province":"Luzern",
    "wof:name":"Disco Garage Ag",
    "wof:placetype":"venue"
},
  "geometry": {"coordinates":[8.3152990341,47.0551300049],"type":"Point"}
}