{
  "type": "Feature",
  "properties": {
    "iso:country":"CH",
    "sg:address":"Oltnerstrasse 4 5012 Sch\u00f6nenwerd. Postfach Postfach 149",
    "sg:city":"Sch\u00f6nenwerd",
    "sg:orig_category":"Schreib U \u00dcbersetzungsb\u00fcros -\u00dcbersetzungsb\u00fcros",
    "sg:phone":"+41 62 849 20 18",
    "sg:postcode":"5012",
    "sg:province":"Solothurn",
    "wof:name":"Maximas Gmbh \u00dcbersetzungen Und Sprachkurse",
    "wof:placetype":"venue"
},
  "geometry": {"coordinates":[8.0022602081,47.371963501],"type":"Point"}
}