{
  "type": "Feature",
  "properties": {
    "iso:country":"CH",
    "sg:address":"Saatlenstrasse 140",
    "sg:city":"Z\u00fcrich",
    "sg:orig_category":"Hoch U Tiefbau",
    "sg:phone":"+41 13220734",
    "sg:postcode":"8050",
    "sg:province":"Z\u00fcrich",
    "wof:name":"Blaser Thomas Baugesch\u00e4ft Sowie Kundenarbeiten In Der Bauwirtschaft.",
    "wof:placetype":"venue"
},
  "geometry": {"coordinates":[8.5650615692,47.4088745117],"type":"Point"}
}