{
  "type": "Feature",
  "properties": {
    "iso:country":"CH",
    "sg:address":"Bleicherweg 62",
    "sg:city":"Z\u00fcrich",
    "sg:orig_category":"Interessenvertretungen",
    "sg:postcode":"8001",
    "sg:province":"Z\u00fcrich",
    "wof:name":"Pro-medico",
    "wof:placetype":"venue"
},
  "geometry": {"coordinates":[6.8314437866,47.1028022766],"type":"Point"}
}