{
  "type": "Feature",
  "properties": {
    "iso:country":"CH",
    "sg:address":"Reichsstrasse 18",
    "sg:city":"Schwyz",
    "sg:classifiers":[
        {
            "category":"Professional",
            "subcategory":"Employment Agencies",
            "type":"Services"
        }
    ],
    "sg:phone":"+41 41 819 70 30",
    "sg:postcode":"6430",
    "sg:province":"Schwyz",
    "sg:tags":[
        "personal",
        "u",
        "stellenvermittlung"
    ],
    "wof:name":"Swiss Jobs Ltd",
    "wof:placetype":"venue"
},
  "geometry": {"coordinates":[8.655421257,47.0207138062],"type":"Point"}
}