{
  "type": "Feature",
  "properties": {
    "iso:country":"CH",
    "sg:address":"Langgasse 49",
    "sg:city":"Baar",
    "sg:orig_category":"Softwareentwicklung U beratung",
    "sg:phone":"+41 41 763 36 36",
    "sg:postcode":"6340",
    "sg:province":"Zug",
    "wof:name":"Variatrading Ulrich",
    "wof:placetype":"venue"
},
  "geometry": {"coordinates":[8.53723526,47.1968574524],"type":"Point"}
}