{
  "type": "Feature",
  "properties": {
    "iso:country":"CH",
    "sg:address":"Rosenweg 20 E",
    "sg:city":"M\u00fcnsingen",
    "sg:orig_category":"Herstellung von Medikamenten U sonstigen pharmazeutischen Erzeugnissen",
    "sg:postcode":"3110",
    "sg:province":"Bern",
    "wof:name":"C-pharma Qa W\u00fcthrich Dr. C.",
    "wof:placetype":"venue"
},
  "geometry": {"coordinates":[7.5629019737,46.8749542236],"type":"Point"}
}