{
  "type": "Feature",
  "properties": {
    "iso:country":"CH",
    "sg:address":"Heimstrasse",
    "sg:city":"Alchenfl\u00fch",
    "sg:orig_category":"Vorschulen, Kinderg\u00e4rten",
    "sg:phone":"+41 34 445 44 73",
    "sg:postcode":"3422",
    "sg:province":"Bern",
    "wof:name":"Kindergarten",
    "wof:placetype":"venue"
},
  "geometry": {"coordinates":[7.5763602257,47.0867462158],"type":"Point"}
}