{
  "type": "Feature",
  "properties": {
    "iso:country":"CH",
    "sg:address":"Webergasse 24",
    "sg:city":"St.gallen",
    "sg:orig_category":"Vereine Gesang",
    "sg:phone":"+41 71 222 67 47",
    "sg:postcode":"9000",
    "sg:province":"St. Gallen",
    "wof:name":"M\u00e4nnerchor Gallus-kantorei",
    "wof:placetype":"venue"
},
  "geometry": {"coordinates":[9.3751831055,47.4227142334],"type":"Point"}
}