{
  "type": "Feature",
  "properties": {
    "iso:country":"CH",
    "sg:address":"Scheibenstrasse 8",
    "sg:city":"Thun",
    "sg:orig_category":"RESTAURANTS: TEA-ROOMS",
    "sg:postcode":"3600",
    "sg:province":"Bern",
    "wof:name":"Planzer-imhof G., Restaurant Sch\u00fctzenhaus.",
    "wof:placetype":"venue"
},
  "geometry": {"coordinates":[8.6637849808,46.8756256104],"type":"Point"}
}