{
  "type": "Feature",
  "properties": {
    "addr:full":"6780 Airolo Ticino 6780",
    "addr:postcode":"6780;6780",
    "iso:country":"CH",
    "sg:address":"6780",
    "sg:city":"Airolo",
    "sg:classifiers":[
        {
            "category":"Bars & Pubs",
            "type":"Food & Drink"
        }
    ],
    "sg:phone":"+41 91 606 72 97",
    "sg:postcode":"6780",
    "sg:province":"Ticino",
    "wof:name":"Bar Sport",
    "wof:placetype":"venue"
},
  "geometry": {"coordinates":[8.85895,45.967636],"type":"Point"}
}