{
  "type": "Feature",
  "properties": {
    "iso:country":"CH",
    "sg:address":"Zelgliweg 1",
    "sg:city":"Itingen",
    "sg:orig_category":"Sonstige Finanzierungsinstitutionen Unternehmensberatung",
    "sg:phone":"+41 31 980 84 44",
    "sg:postcode":"4452",
    "sg:province":"Basel-Landschaft",
    "wof:name":"Adval Tech Management Ag",
    "wof:placetype":"venue"
},
  "geometry": {"coordinates":[7.3748221397,46.9243469238],"type":"Point"}
}