{
  "type": "Feature",
  "properties": {
    "addr:full":"Chemin Furet 71 Gen\u00e8ve Gen\u00e8ve 1203",
    "addr:housenumber":"71",
    "addr:postcode":"1203",
    "addr:street":"Chemin Furet",
    "iso:country":"CH",
    "sg:address":"Chemin Furet 71",
    "sg:city":"Gen\u00e8ve",
    "sg:orig_category":"Blumen U Zierpflanzenbau",
    "sg:phone":"+41 22 771 24 02",
    "sg:postcode":"1203",
    "sg:province":"Gen\u00e8ve",
    "wof:name":"Ethenoz & Cie",
    "wof:placetype":"venue"
},
  "geometry": {"coordinates":[6.118166,46.207809],"type":"Point"}
}