{
  "type": "Feature",
  "properties": {
    "addr:full":"Gotthardstrasse 3 6300 Zug. Postfach 4562 Zug Zug 6304",
    "addr:housenumber":"3",
    "addr:postcode":"6300;4562;6304",
    "addr:street":"Gotthardstrasse;Postfach;Zug",
    "iso:country":"CH",
    "sg:address":"Gotthardstrasse 3 6300 Zug. Postfach 4562",
    "sg:city":"Zug",
    "sg:orig_category":"Advokaturb\u00fcros Notariate",
    "sg:phone":"+41 41 729 39 00",
    "sg:postcode":"6304",
    "sg:province":"Zug",
    "wof:name":"Nick & Ineichen Advokatur & Notariat",
    "wof:placetype":"venue"
},
  "geometry": {"coordinates":[8.517567,47.171585],"type":"Point"}
}