{
  "type": "Feature",
  "properties": {
    "iso:country":"CH",
    "sg:address":"Wohlenstrasse 14",
    "sg:city":"Uettligen",
    "sg:orig_category":"Instandhaltung U Reparatur von Automobilen",
    "sg:phone":"+41 31 829 22 00",
    "sg:postcode":"3043",
    "sg:province":"Bern",
    "wof:name":"Garage R. K\u00fcnti",
    "wof:placetype":"venue"
},
  "geometry": {"coordinates":[7.3836350441,46.98670578],"type":"Point"}
}