{
  "type": "Feature",
  "properties": {
    "iso:country":"CH",
    "sg:address":"G\u00fcterstrasse 29 2505 Biel/bienne. Postfach",
    "sg:city":"Biel/bienne",
    "sg:orig_category":"RESTAURANTS: TEA-ROOMS",
    "sg:postcode":"2502",
    "sg:province":"Bern",
    "wof:name":"Mola & Co Restaurant B\u00f6rse Chez Enzo",
    "wof:placetype":"venue"
},
  "geometry": {"coordinates":[7.2478561401,47.135471344],"type":"Point"}
}