{
  "type": "Feature",
  "properties": {
    "iso:country":"CH",
    "sg:address":"Zopfstrasse 10",
    "sg:city":"Berikon",
    "sg:orig_category":"Druck ohne Zeitungsdruck",
    "sg:phone":"+41 56 631 80 74",
    "sg:postcode":"8965",
    "sg:province":"Aargau",
    "wof:name":"Vita Vera Verlags-gmbh",
    "wof:placetype":"venue"
},
  "geometry": {"coordinates":[8.3729486465,47.3529167175],"type":"Point"}
}