{
  "type": "Feature",
  "properties": {
    "iso:country":"CH",
    "sg:address":"Lyssachstrase 23",
    "sg:city":"Burgdorf",
    "sg:orig_category":"Non-Classified Establishments",
    "sg:phone":"+41 34 423 32 13",
    "sg:postcode":"3400",
    "sg:province":"Bern",
    "wof:name":"Imbiss D\u00f6ner-express",
    "wof:placetype":"venue"
},
  "geometry": {"coordinates":[7.6217179298,47.0590591431],"type":"Point"}
}