{
  "type": "Feature",
  "properties": {
    "iso:country":"CH",
    "sg:address":"Alte Kantonsstrasse",
    "sg:city":"Susten",
    "sg:orig_category":"Advokaturb\u00fcros Notariate",
    "sg:phone":"+41 27 473 12 15",
    "sg:postcode":"3952",
    "sg:province":"Valais",
    "wof:name":"Alwin Steiner Advokatur- & Notariatsb\u00fcro",
    "wof:placetype":"venue"
},
  "geometry": {"coordinates":[7.637647,46.311516],"type":"Point"}
}