{
  "type": "Feature",
  "properties": {
    "iso:country":"CH",
    "sg:address":"Blumenweg 4d",
    "sg:city":"Ittigen",
    "sg:orig_category":"Erbringung von Dienstleistungen f\u00fcr Unternehmen Werbevermittlung",
    "sg:phone":"+41 31 921 23 29",
    "sg:postcode":"3063",
    "sg:province":"Bern",
    "wof:name":"Welte M. & G.",
    "wof:placetype":"venue"
},
  "geometry": {"coordinates":[7.472869873,46.9717712402],"type":"Point"}
}