{
  "type": "Feature",
  "properties": {
    "addr:full":"Corso San Gottardo 32 Chiasso Ticino 6830",
    "addr:housenumber":"32",
    "addr:postcode":"6830",
    "addr:street":"Corso San Gottardo;Ticino",
    "iso:country":"CH",
    "sg:address":"Corso San Gottardo 32",
    "sg:city":"Chiasso",
    "sg:orig_category":"Architektur U Ingenieurb\u00fcros",
    "sg:postcode":"6830",
    "sg:province":"Ticino",
    "wof:name":"Kartoservice Ltd, Dublino, Succurale Di Chiasso",
    "wof:placetype":"venue"
},
  "geometry": {"coordinates":[9.029879,45.834133],"type":"Point"}
}