{
  "type": "Feature",
  "properties": {
    "iso:country":"CH",
    "sg:address":"Via Monte Br\u00e8 9",
    "sg:city":"Lugano",
    "sg:orig_category":"Wirtschaftsverb\u00e4nde Industrie, Handel and Gewerbe",
    "sg:phone":"+41 91 923 38 28",
    "sg:postcode":"6900",
    "sg:province":"Ticino",
    "wof:name":"Soc.dei Maestri Panettieri- Pasticcieri Del Cantone Ti",
    "wof:placetype":"venue"
},
  "geometry": {"coordinates":[8.958111763,46.0122871399],"type":"Point"}
}