{
  "type": "Feature",
  "properties": {
    "iso:country":"CH",
    "sg:address":"Rue Verdaine 15",
    "sg:city":"Lutry",
    "sg:orig_category":"Detailhandel mit Geschenkartikeln U Souvenirs",
    "sg:phone":"+41 21 791 29 57",
    "sg:postcode":"1095",
    "sg:province":"Vaud",
    "wof:name":"Claudine De Siebenthal Boutique Diagonal",
    "wof:placetype":"venue"
},
  "geometry": {"coordinates":[6.6856098175,46.5026741028],"type":"Point"}
}