{
  "type": "Feature",
  "properties": {
    "iso:country":"CH",
    "sg:address":"Communes-r\u00e9unies Avenue Des 74 1212 Grand-lancy. Postfach",
    "sg:city":"Arare",
    "sg:orig_category":"Reinigungsgewerbe",
    "sg:postcode":"1212",
    "sg:province":"Gen\u00e8ve",
    "wof:name":"G & P Services, Perez Entreprise De Nettoyage, Services De Conciergerie Etc",
    "wof:placetype":"venue"
},
  "geometry": {"coordinates":[6.1229958534,46.1728553772],"type":"Point"}
}