{
  "type": "Feature",
  "properties": {
    "iso:country":"CH",
    "sg:address":"Buechstrasse 6",
    "sg:city":"Jona",
    "sg:orig_category":"Herstellung von sonstigen elektrischen Ausr\u00fcstungen Mechanische Werkst\u00e4tten",
    "sg:phone":"+41 32 344 21 21",
    "sg:postcode":"8645",
    "sg:province":"St. Gallen",
    "wof:name":"Harting Ag",
    "wof:placetype":"venue"
},
  "geometry": {"coordinates":[7.2897667885,47.1643218994],"type":"Point"}
}