{
  "type": "Feature",
  "properties": {
    "iso:country":"CH",
    "sg:address":"Unterdorf 9",
    "sg:city":"Treiten",
    "sg:orig_category":"Landesverteidigung, Sozialversicherung \u00d6ffentliche Verwaltung",
    "sg:phone":"+41 32 313 18 93",
    "sg:postcode":"3226",
    "sg:province":"Bern",
    "wof:name":"Zivilschutzstelle Treiten",
    "wof:placetype":"venue"
},
  "geometry": {"coordinates":[7.1599011421,47.0083007812],"type":"Point"}
}