{
  "type": "Feature",
  "properties": {
    "iso:country":"CH",
    "sg:address":"Rue Du Closillon 33a",
    "sg:city":"Monthey",
    "sg:orig_category":"Stukkateurgewerbe, Gipserei U Verputzerei",
    "sg:phone":"+41 24 471 83 63",
    "sg:postcode":"1870",
    "sg:province":"Valais",
    "wof:name":"Tony Peinture - Mottola A.",
    "wof:placetype":"venue"
},
  "geometry": {"coordinates":[6.9605259895,46.2580528259],"type":"Point"}
}