{
  "type": "Feature",
  "properties": {
    "addr:full":"Heidenhubelstrasse 26 Solothurn Solothurn 4500",
    "addr:housenumber":"26",
    "addr:postcode":"4500",
    "addr:street":"Heidenhubelstrasse",
    "iso:country":"CH",
    "sg:address":"Heidenhubelstrasse 26",
    "sg:city":"Solothurn",
    "sg:orig_category":"Architektur U Ingenieurb\u00fcros",
    "sg:phone":"+41 32 623 22 02",
    "sg:postcode":"4500",
    "sg:province":"Solothurn",
    "wof:name":"Gygli Heinz Ag",
    "wof:placetype":"venue"
},
  "geometry": {"coordinates":[7.521545,47.213085],"type":"Point"}
}