{
  "type": "Feature",
  "properties": {
    "iso:country":"CH",
    "sg:address":"Hauptstrasse 53",
    "sg:city":"Birsfelden",
    "sg:orig_category":"Vermietung U Verpachtung von eigenen Immobilien",
    "sg:postcode":"4127",
    "sg:province":"Basel-Landschaft",
    "wof:name":"Widder Ag",
    "wof:placetype":"venue"
},
  "geometry": {"coordinates":[7.6214599609,47.5535087585],"type":"Point"}
}