{
  "type": "Feature",
  "properties": {
    "iso:country":"CH",
    "sg:address":"Hohriedstrasse",
    "sg:city":"Pfaffnau",
    "sg:orig_category":"Bauschreinerei Herstellung von M\u00f6beln verschiedener Art",
    "sg:phone":"+41 52 365 22 74",
    "sg:postcode":"6264",
    "sg:province":"Luzern",
    "wof:name":"Alois Zehnder M\u00f6belfabrik & Schreinerei",
    "wof:placetype":"venue"
},
  "geometry": {"coordinates":[8.894044,47.477989],"type":"Point"}
}