{
  "type": "Feature",
  "properties": {
    "iso:country":"CH",
    "sg:address":"Baumackerstrasse 35 8050 Z\u00fcrich. Postfach 8050 Z\u00fcrich",
    "sg:city":"Zust",
    "sg:classifiers":[
        {
            "category":"Personal",
            "subcategory":"Nail Salon",
            "type":"Services"
        }
    ],
    "sg:phone":"+41 13132323",
    "sg:postcode":"50",
    "sg:tags":[
        "manicure"
    ],
    "wof:name":"Nail Total Burki Gra\u00e7a Nagelkosmetik, Manicure. Modeschmuck; Vertrieb Usw",
    "wof:placetype":"venue"
},
  "geometry": {"coordinates":[8.5433197021,47.4092483521],"type":"Point"}
}