{
  "type": "Feature",
  "properties": {
    "iso:country":"CH",
    "sg:address":"2713",
    "sg:city":"Bellelay",
    "sg:orig_category":"Landwirtschaft, Jagd U damit verbundene Dienstleistungen",
    "sg:phone":"+41 32 484 91 26",
    "sg:postcode":"2713",
    "sg:province":"Bern",
    "wof:name":"Domaine Agricole",
    "wof:placetype":"venue"
},
  "geometry": {"coordinates":[7.1673998833,47.2626800537],"type":"Point"}
}