{
  "type": "Feature",
  "properties": {
    "iso:country":"CH",
    "sg:address":"Enzbergh\u00f6he 12",
    "sg:city":"Gipf-oberfrick",
    "sg:orig_category":"Wirtschaftspr\u00fcfung, Steuerberatung U Treuhand",
    "sg:postcode":"5073",
    "sg:province":"Aargau",
    "wof:name":"Mrg Beratungs-ag",
    "wof:placetype":"venue"
},
  "geometry": {"coordinates":[8.0103940964,47.4987411499],"type":"Point"}
}