{
  "type": "Feature",
  "properties": {
    "iso:country":"CH",
    "sg:address":"Germaniastrasse 62 8006 Z\u00fcrich. Postfach",
    "sg:city":"Z\u00fcrich",
    "sg:orig_category":"Non-Classified Establishments",
    "sg:postcode":"8001",
    "sg:province":"Z\u00fcrich",
    "wof:name":"Fidupar Holding Ag Beteiligungen, Verm\u00f6gensverwaltungen, Immob.-gesch\u00e4fte Usw",
    "wof:placetype":"venue"
},
  "geometry": {"coordinates":[8.552362442,47.3870887756],"type":"Point"}
}