{
  "type": "Feature",
  "properties": {
    "iso:country":"CH",
    "sg:address":"Mettmenstetterstrasse 15",
    "sg:city":"Obfelden",
    "sg:orig_category":"Sportvereine Turnen Damen",
    "sg:phone":"+41 17601660",
    "sg:postcode":"8912",
    "sg:province":"Z\u00fcrich",
    "wof:name":"Damenturnverein Hedingen",
    "wof:placetype":"venue"
},
  "geometry": {"coordinates":[8.4329147339,47.2631492615],"type":"Point"}
}