{
  "type": "Feature",
  "properties": {
    "iso:country":"CH",
    "sg:address":"Niedermattstrasse 18",
    "sg:city":"Glattfelden",
    "sg:orig_category":"Vereine Abstinenten",
    "sg:phone":"+41 18671797",
    "sg:postcode":"8192",
    "sg:province":"Z\u00fcrich",
    "wof:name":"Blaues Kreuz",
    "wof:placetype":"venue"
},
  "geometry": {"coordinates":[8.4927921295,47.5630531311],"type":"Point"}
}