{
  "type": "Feature",
  "properties": {
    "iso:country":"CH",
    "sg:address":"Sagenplatz 3",
    "sg:city":"Einsiedeln",
    "sg:orig_category":"RESTAURANTS: TEA-ROOMS",
    "sg:phone":"+41 55 412 28 25",
    "sg:postcode":"8840",
    "sg:province":"Schwyz",
    "wof:name":"Restaurant Iseb\u00e4hnli",
    "wof:placetype":"venue"
},
  "geometry": {"coordinates":[8.7448835373,47.1278038025],"type":"Point"}
}