{
  "type": "Feature",
  "properties": {
    "iso:country":"CH",
    "sg:address":"Rue Du Milieu 3",
    "sg:city":"Buttes",
    "sg:orig_category":"Betrieb von Taxis",
    "sg:postcode":"2115",
    "sg:province":"Neuch\u00e2tel",
    "wof:name":"Michel Froidevaux Taxi Littoral Vegas",
    "wof:placetype":"venue"
},
  "geometry": {"coordinates":[6.552043,46.888035],"type":"Point"}
}