{
  "type": "Feature",
  "properties": {
    "addr:full":"1304 Cossonay-ville Vaud 1304",
    "addr:postcode":"1304;1304",
    "iso:country":"CH",
    "sg:address":"1304",
    "sg:city":"Cossonay-ville",
    "sg:classifiers":[
        {
            "category":"Education",
            "subcategory":"Library",
            "type":"Public Place"
        }
    ],
    "sg:phone":"+41 21 861 07 07",
    "sg:postcode":"1304",
    "sg:province":"Vaud",
    "sg:tags":[
        "u",
        "bibliotheken",
        "archive"
    ],
    "wof:name":"Biblioth\u00e8que Communale",
    "wof:placetype":"venue"
},
  "geometry": {"coordinates":[6.50771,46.613819],"type":"Point"}
}