{
  "type": "Feature",
  "properties": {
    "iso:country":"CH",
    "sg:address":"Hardstrasse 47c 5430 Wettingen. Postfach 173",
    "sg:city":"Wettingen",
    "sg:orig_category":"Ingenieurb\u00fcros Datenverarbeitung",
    "sg:phone":"+41 56 426 54 44",
    "sg:postcode":"5430",
    "sg:province":"Aargau",
    "wof:name":"Hadzi-manovic, Rale",
    "wof:placetype":"venue"
},
  "geometry": {"coordinates":[8.3331537247,47.4586143494],"type":"Point"}
}