{
  "type": "Feature",
  "properties": {
    "iso:country":"CH",
    "sg:address":"Uttenberg 261",
    "sg:city":"Knonau",
    "sg:orig_category":"Sportvereine Unihockey",
    "sg:phone":"+41 81 252 24 57",
    "sg:postcode":"8934",
    "sg:province":"Z\u00fcrich",
    "wof:name":"Uhc Dynamo Malix",
    "wof:placetype":"venue"
},
  "geometry": {"coordinates":[9.5334653854,46.815120697],"type":"Point"}
}