{
  "type": "Feature",
  "properties": {
    "iso:country":"CH",
    "sg:address":"Kalchb\u00fchlstrasse 18",
    "sg:city":"Chur",
    "sg:orig_category":"Sonstiger Grosshandel",
    "sg:postcode":"7000",
    "sg:province":"Graubunden",
    "wof:name":"Kellim Ag",
    "wof:placetype":"venue"
},
  "geometry": {"coordinates":[9.5095748901,46.8463973999],"type":"Point"}
}