{
  "type": "Feature",
  "properties": {
    "addr:full":"S\u00e4ntisstrasse 9 Arbon Thurgau 9320",
    "addr:housenumber":"9",
    "addr:postcode":"9320",
    "addr:street":"Saentisstrasse",
    "iso:country":"CH",
    "sg:address":"S\u00e4ntisstrasse 9",
    "sg:city":"Arbon",
    "sg:orig_category":"Detailhandel mit Brot, Back U S\u00fcsswaren",
    "sg:phone":"+41 71 446 06 58",
    "sg:postcode":"9320",
    "sg:province":"Thurgau",
    "wof:name":"Rolf Hebeisen B\u00e4ckerei-konditorei",
    "wof:placetype":"venue"
},
  "geometry": {"coordinates":[9.426882,47.515987],"type":"Point"}
}