{
  "type": "Feature",
  "properties": {
    "iso:country":"CH",
    "sg:address":"Avenue De Riant-mont 12",
    "sg:city":"Lausanne",
    "sg:classifiers":[
        {
            "category":"Shopping",
            "subcategory":"Books",
            "type":"Retail Goods"
        }
    ],
    "sg:phone":"+41 21 311 93 40",
    "sg:postcode":"1004",
    "sg:province":"Vaud",
    "wof:name":"Editions Antipodes S\u00e0rl",
    "wof:placetype":"venue"
},
  "geometry": {"coordinates":[6.632707,46.525032],"type":"Point"}
}