{
  "type": "Feature",
  "properties": {
    "iso:country":"CH",
    "sg:address":"1237 Avully Case Postale 7",
    "sg:city":"Avully",
    "sg:orig_category":"Sportvereine P\u00e9tanque",
    "sg:postcode":"1237",
    "sg:province":"Gen\u00e8ve",
    "wof:name":"P\u00e9tanque-club La Chancynoise",
    "wof:placetype":"venue"
},
  "geometry": {"coordinates":[5.998000145,46.1665306091],"type":"Point"}
}