{
  "type": "Feature",
  "properties": {
    "iso:country":"CH",
    "sg:address":"Hauptstrasse 78",
    "sg:city":"Nidau",
    "sg:orig_category":"Versicherungen Hauptagenturen",
    "sg:phone":"+41 32 331 13 83",
    "sg:postcode":"2560",
    "sg:province":"Bern",
    "wof:name":"Die Mobiliar Versicherungen & Vorsorge",
    "wof:placetype":"venue"
},
  "geometry": {"coordinates":[7.2419109344,47.1226768494],"type":"Point"}
}