{
  "type": "Feature",
  "properties": {
    "iso:country":"CH",
    "sg:address":"Erlachstrasse 5 3012 Bern. Postfach",
    "sg:city":"Z\u00fcrich",
    "sg:orig_category":"Architektur U Ingenieurb\u00fcros",
    "sg:phone":"+41 31 302 50 13",
    "sg:postcode":"8026",
    "sg:province":"Z\u00fcrich",
    "wof:name":"Ingenieurb\u00fcro Hans Frei",
    "wof:placetype":"venue"
},
  "geometry": {"coordinates":[7.434149,46.951355],"type":"Point"}
}