{
  "type": "Feature",
  "properties": {
    "iso:country":"CH",
    "sg:address":"Route Du Monterri 14",
    "sg:city":"Courgenay",
    "sg:classifiers":[
        {
            "category":"Shopping",
            "subcategory":"Stationery & Office Supplies",
            "type":"Retail Goods"
        }
    ],
    "sg:phone":"+41 32 471 22 20",
    "sg:postcode":"2950",
    "sg:province":"Jura",
    "sg:tags":[
        "watchmaker's"
    ],
    "wof:name":"Andr\u00e9 Liechti",
    "wof:placetype":"venue"
},
  "geometry": {"coordinates":[7.1311721802,47.4006118774],"type":"Point"}
}