{
  "type": "Feature",
  "properties": {
    "iso:country":"CH",
    "sg:address":"Pfaffarcherweg 189",
    "sg:city":"Scherz",
    "sg:classifiers":[
        {
            "category":"Professional",
            "subcategory":"Advertising",
            "type":"Services"
        }
    ],
    "sg:phone":"+41 56 619 52 52",
    "sg:postcode":"5246",
    "sg:province":"Aargau",
    "sg:tags":[
        "marketing",
        "direct"
    ],
    "wof:name":"Sigimedia Ag",
    "wof:placetype":"venue"
},
  "geometry": {"coordinates":[8.1851196289,47.4469718933],"type":"Point"}
}