{
  "type": "Feature",
  "properties": {
    "iso:country":"CH",
    "sg:address":"Route Du Bugnon 39",
    "sg:city":"Villars-sur-gl\u00e2ne",
    "sg:orig_category":"Non-Classified Establishments",
    "sg:postcode":"1752",
    "sg:province":"Fribourg",
    "wof:name":"Institut Solaria, Edith Amarasinha-baeriswyl",
    "wof:placetype":"venue"
},
  "geometry": {"coordinates":[7.1115698814,46.7942771912],"type":"Point"}
}