{
  "type": "Feature",
  "properties": {
    "iso:country":"CH",
    "sg:address":"Grabenstrasse 20",
    "sg:city":"Schlieren",
    "sg:orig_category":"Massagestudios",
    "sg:phone":"+41 17309071",
    "sg:postcode":"8952",
    "sg:province":"Z\u00fcrich",
    "wof:name":"Susanne B\u00e4nninger Gesundheitsmassagen",
    "wof:placetype":"venue"
},
  "geometry": {"coordinates":[8.4506721497,47.3968734741],"type":"Point"}
}