{
  "type": "Feature",
  "properties": {
    "iso:country":"CH",
    "sg:address":"Steinmattstrasse 7",
    "sg:city":"Zermatt",
    "sg:orig_category":"Reiseb\u00fcros",
    "sg:phone":"+41 27 967 48 75",
    "sg:postcode":"3920",
    "sg:province":"Valais",
    "wof:name":"Mountain Memories Org.v.berg-ski-& Klettertouren",
    "wof:placetype":"venue"
},
  "geometry": {"coordinates":[7.7499427795,46.0203208923],"type":"Point"}
}