{
  "type": "Feature",
  "properties": {
    "iso:country":"CH",
    "sg:address":"Les Prises Champ-bettens",
    "sg:city":"Gorgier",
    "sg:orig_category":"Herstellung von Schrauben, Nieten, Ketten U Federn Mechanische Werkst\u00e4tten",
    "sg:phone":"+41 32 835 22 18",
    "sg:postcode":"2023",
    "sg:province":"Neuch\u00e2tel",
    "wof:name":"Decobar, Locatelli & Cie",
    "wof:placetype":"venue"
},
  "geometry": {"coordinates":[6.7658238411,46.9183616638],"type":"Point"}
}