{
  "type": "Feature",
  "properties": {
    "iso:country":"CH",
    "sg:address":"Blumenrain 10",
    "sg:city":"Luzern",
    "sg:orig_category":"Betrieb U technische Hilfsdienste des Kultur U Unterhaltungswesens",
    "sg:phone":"+41 41 422 02 92",
    "sg:postcode":"6006",
    "sg:province":"Luzern",
    "wof:name":"Mts Events & Services Saltori",
    "wof:placetype":"venue"
},
  "geometry": {"coordinates":[8.311017,47.06377],"type":"Point"}
}