{
  "type": "Feature",
  "properties": {
    "iso:country":"CH",
    "sg:address":"Fuchsloch 8",
    "sg:city":"Biberstein",
    "sg:orig_category":"Detailhandel nicht in Verkaufsr\u00e4umen",
    "sg:phone":"+41 62 827 45 11",
    "sg:postcode":"5023",
    "sg:province":"Aargau",
    "wof:name":"Omnirep Gmbh",
    "wof:placetype":"venue"
},
  "geometry": {"coordinates":[8.0751209259,47.4142112732],"type":"Point"}
}