{
  "type": "Feature",
  "properties": {
    "iso:country":"CH",
    "sg:address":"Rue De Lausanne 2",
    "sg:city":"Sion",
    "sg:orig_category":"Detailhandel mit Antiquit\u00e4ten U Gebrauchtwaren in Verkaufsr\u00e4umen Detailhandel mit Boden U Wandbel\u00e4ge",
    "sg:phone":"+41 27 321 28 41",
    "sg:postcode":"1950",
    "sg:province":"Valais",
    "wof:name":"Tapis Maret Sa",
    "wof:placetype":"venue"
},
  "geometry": {"coordinates":[7.360308,46.233097],"type":"Point"}
}