{
  "type": "Feature",
  "properties": {
    "addr:full":"Grossweid 92 Aathal-seegr\u00e4ben Z\u00fcrich 8607",
    "addr:housenumber":"92",
    "addr:postcode":"8607",
    "addr:street":"Grossweid;Zuerich",
    "iso:country":"CH",
    "sg:address":"Grossweid 92",
    "sg:city":"Aathal-seegr\u00e4ben",
    "sg:orig_category":"Architektur U Ingenieurb\u00fcros",
    "sg:postcode":"8607",
    "sg:province":"Z\u00fcrich",
    "wof:name":"Swicon Ag",
    "wof:placetype":"venue"
},
  "geometry": {"coordinates":[8.768485,47.335884],"type":"Point"}
}