{
  "type": "Feature",
  "properties": {
    "iso:country":"CH",
    "sg:address":"Mailand-strasse 41",
    "sg:city":"Basel",
    "sg:orig_category":"Bauschreinerei Herstellung von Konstruktionsteilen, Fertigbauteilen U Ausbauelementen aus Holz",
    "sg:phone":"+41 61 338 88 38",
    "sg:postcode":"4053",
    "sg:province":"Basel-Stadt",
    "wof:name":"Ren\u00e9 Schweizer Ag",
    "wof:placetype":"venue"
},
  "geometry": {"coordinates":[7.606437,47.53207],"type":"Point"}
}