{
  "type": "Feature",
  "properties": {
    "iso:country":"CH",
    "sg:address":"Carouge Rue De 58-60 1205 Gen\u00e8ve. Postfach",
    "sg:city":"Gen\u00e8ve",
    "sg:orig_category":"Softwareentwicklung U beratung",
    "sg:postcode":"1205",
    "sg:province":"Gen\u00e8ve",
    "wof:name":"Icrcom Ag Informatik, Unternehmensmanagement; Beratung, Handel, Schulung, Support Usw",
    "wof:placetype":"venue"
},
  "geometry": {"coordinates":[9.0476093292,47.4658126831],"type":"Point"}
}