{
  "type": "Feature",
  "properties": {
    "iso:country":"CH",
    "sg:address":"Z\u00fcrcherstrasse 12 8193 Eglisau. Postfach",
    "sg:city":"Eglisau",
    "sg:orig_category":"Fachdetailhandel in Verkaufsr\u00e4umen",
    "sg:postcode":"8193",
    "sg:province":"Z\u00fcrich",
    "wof:name":"Pit's Bootsservice, Peter Gantner",
    "wof:placetype":"venue"
},
  "geometry": {"coordinates":[8.5228881836,47.5726051331],"type":"Point"}
}