{
  "type": "Feature",
  "properties": {
    "iso:country":"CH",
    "sg:address":"Hammerstrasse 62a 8032 Z\u00fcrich. Postfach 8032 Z\u00fcrich",
    "sg:city":"Zust",
    "sg:orig_category":"Unclassifiable Establishments",
    "sg:postcode":"32",
    "wof:name":"Wellstein Reden.ch",
    "wof:placetype":"venue"
},
  "geometry": {"coordinates":[8.5626020432,47.3601531982],"type":"Point"}
}