{
  "type": "Feature",
  "properties": {
    "iso:country":"CH",
    "sg:address":"Via Della Posta",
    "sg:city":"Bioggio",
    "sg:classifiers":[
        {
            "category":"Insurance",
            "subcategory":"Insurance Agent",
            "type":"Services"
        }
    ],
    "sg:phone":"+41 22 751 88 85",
    "sg:postcode":"6934",
    "sg:province":"Ticino",
    "sg:tags":[
        "versicherungsagenturen",
        "-broker"
    ],
    "wof:name":"Antonio Somolinos Courtier En Assurances",
    "wof:placetype":"venue"
},
  "geometry": {"coordinates":[6.2236971855,46.2640991211],"type":"Point"}
}