{
  "type": "Feature",
  "properties": {
    "iso:country":"CH",
    "sg:address":"Rohnen 105",
    "sg:city":"Schachen",
    "sg:classifiers":[
        {
            "category":"Manufacturing",
            "subcategory":"Chemicals & Compounds",
            "type":"Manufacturing & Wholesale Goods"
        }
    ],
    "sg:phone":"+41 71 891 57 65",
    "sg:postcode":"9414",
    "sg:province":"Appenzell Ausserrhoden",
    "sg:tags":[
        "pharmaceutical",
        "chemistry"
    ],
    "wof:name":"Bilena Gmbh",
    "wof:placetype":"venue"
},
  "geometry": {"coordinates":[8.094067,47.603687],"type":"Point"}
}