{
  "type": "Feature",
  "properties": {
    "iso:country":"CH",
    "sg:address":"Rte De La Louvi\u00e8re 18. 1243 Presinge. Postfach",
    "sg:city":"Presinge",
    "sg:orig_category":"Beherbergungsgewerbe",
    "sg:postcode":"1243",
    "sg:province":"Gen\u00e8ve",
    "wof:name":"Chollet M. Et Mme.",
    "wof:placetype":"venue"
},
  "geometry": {"coordinates":[6.254677,46.219151],"type":"Point"}
}