{
  "type": "Feature",
  "properties": {
    "iso:country":"CH",
    "sg:address":"Br\u00fcnigstrasse 105",
    "sg:city":"Lungern",
    "sg:orig_category":"Reiseb\u00fcros U Reiseveranstalter",
    "sg:postcode":"6078",
    "sg:province":"Obwalden",
    "wof:name":"Kur Und Verkehrsverein Lungern-sch\u00f6nb\u00fcel",
    "wof:placetype":"venue"
},
  "geometry": {"coordinates":[8.1593599319,46.7838401794],"type":"Point"}
}