{
  "type": "Feature",
  "properties": {
    "iso:country":"CH",
    "sg:address":"9240",
    "sg:city":"Uzwil",
    "sg:orig_category":"Landesverteidigung, Sozialversicherung \u00d6ffentliche Verwaltung",
    "sg:phone":"+41 71 955 44 06",
    "sg:postcode":"9240",
    "sg:province":"St. Gallen",
    "wof:name":"Zivilschutzstelle Uzwil",
    "wof:placetype":"venue"
},
  "geometry": {"coordinates":[9.1329545975,47.4371452332],"type":"Point"}
}