{
  "type": "Feature",
  "properties": {
    "iso:country":"CH",
    "sg:address":"6600",
    "sg:city":"Locarno",
    "sg:orig_category":"Sportvereine Turnen",
    "sg:phone":"+41 91 751 90 35",
    "sg:postcode":"6600",
    "sg:province":"Ticino",
    "wof:name":"St\u00e0 Locarnese Di Ginnastica Sez.fed.c/o Palazzo Sport Fevi",
    "wof:placetype":"venue"
},
  "geometry": {"coordinates":[8.7908401489,46.1678886414],"type":"Point"}
}