{
  "type": "Feature",
  "properties": {
    "iso:country":"CH",
    "sg:address":"Delsbergstrasse 2 4203 Grellingen. Postfach",
    "sg:city":"Grellingen",
    "sg:orig_category":"Detailhandel mit M\u00f6beln Innendekorationsateliers",
    "sg:phone":"+41 61 741 13 22",
    "sg:postcode":"4203",
    "sg:province":"Basel-Landschaft",
    "wof:name":"Albert Egli M\u00f6bel & Tapezierergesch\u00e4ft",
    "wof:placetype":"venue"
},
  "geometry": {"coordinates":[7.5890040398,47.4420814514],"type":"Point"}
}