{
  "type": "Feature",
  "properties": {
    "iso:country":"CH",
    "sg:address":"Rue Mauborget 27",
    "sg:city":"Moudon",
    "sg:orig_category":"Pensionskassen",
    "sg:postcode":"1510",
    "sg:province":"Vaud",
    "wof:name":"Fonds De Pr\u00e9voyance En Faveur Du Personnel De La Maison Braillard-fers, Moudon",
    "wof:placetype":"venue"
},
  "geometry": {"coordinates":[6.7975401878,46.6670913696],"type":"Point"}
}