{
  "type": "Feature",
  "properties": {
    "iso:country":"CH",
    "sg:address":"8957 Spreitenbach. Postfach 370",
    "sg:city":"Spreitenbach",
    "sg:orig_category":"Sportvereine Ballsport Fussball",
    "sg:phone":"+41 21 882 50 92",
    "sg:postcode":"8957",
    "sg:province":"Aargau",
    "wof:name":"Fc St-barth\u00e9lemy",
    "wof:placetype":"venue"
},
  "geometry": {"coordinates":[6.6014800072,46.6362991333],"type":"Point"}
}