{
  "type": "Feature",
  "properties": {
    "iso:country":"CH",
    "sg:address":"Gemeindeplatz 1",
    "sg:city":"Diepoldsau",
    "sg:orig_category":"Gemeindeverwaltungen",
    "sg:phone":"+41 7377363",
    "sg:postcode":"9444",
    "sg:province":"St. Gallen",
    "wof:name":"Gemeindeverwaltung Diepoldsau",
    "wof:placetype":"venue"
},
  "geometry": {"coordinates":[9.6552476883,47.3860588074],"type":"Point"}
}