{
  "type": "Feature",
  "properties": {
    "iso:country":"CH",
    "sg:address":"Robinia Vicolo 1",
    "sg:city":"Minusio",
    "sg:orig_category":"Architektur U Ingenieurb\u00fcros",
    "sg:phone":"+41 91 743 48 68",
    "sg:postcode":"6648",
    "sg:province":"Ticino",
    "wof:name":"Di Marino Vincenzo",
    "wof:placetype":"venue"
},
  "geometry": {"coordinates":[8.824764,46.178551],"type":"Point"}
}