{
  "type": "Feature",
  "properties": {
    "iso:country":"CH",
    "sg:address":"1587",
    "sg:city":"Montmagny",
    "sg:classifiers":[
        {
            "category":"Restaurant",
            "type":"Food & Drink"
        }
    ],
    "sg:phone":"+41 27 395 32 34",
    "sg:postcode":"1587",
    "sg:province":"Vaud",
    "wof:name":"Caf\u00e9 Vieux-stand",
    "wof:placetype":"venue"
},
  "geometry": {"coordinates":[14.0925502777,56.0013504028],"type":"Point"}
}