{
  "type": "Feature",
  "properties": {
    "iso:country":"CH",
    "sg:address":"Enzenb\u00fchlstrasse 45",
    "sg:city":"Z\u00fcrich",
    "sg:orig_category":"Schreib U \u00dcbersetzungsb\u00fcros -\u00dcbersetzungsb\u00fcros",
    "sg:phone":"+41 13814808",
    "sg:postcode":"8008",
    "sg:province":"Z\u00fcrich",
    "wof:name":"Angora \u00dcbersetzungen, Sami Hayim",
    "wof:placetype":"venue"
},
  "geometry": {"coordinates":[8.5754585266,47.3499069214],"type":"Point"}
}