{
  "type": "Feature",
  "properties": {
    "iso:country":"CH",
    "sg:address":"Marchairuz Route Du",
    "sg:city":"Bi\u00e8re",
    "sg:orig_category":"Herstellung von sonstigen landwirtschaftlichen Maschinen",
    "sg:phone":"+41 21 809 54 67",
    "sg:postcode":"1145",
    "sg:province":"Vaud",
    "wof:name":"Rochat P.-a., Motoculture - Machines",
    "wof:placetype":"venue"
},
  "geometry": {"coordinates":[6.3322110176,46.5387496948],"type":"Point"}
}