{
  "type": "Feature",
  "properties": {
    "iso:country":"CH",
    "sg:address":"Saint-honor\u00e9 Rue 3 2000 Neuch\u00e2tel. Postfach",
    "sg:city":"Neuenburg",
    "sg:orig_category":"Non-Classified Establishments",
    "sg:postcode":"2000",
    "sg:province":"Neuch\u00e2tel",
    "wof:name":"Si Jaquet Droz 7 Sa",
    "wof:placetype":"venue"
},
  "geometry": {"coordinates":[6.8230748177,47.0989723206],"type":"Point"}
}