{
  "type": "Feature",
  "properties": {
    "iso:country":"CH",
    "sg:address":"Gerberngasse 3",
    "sg:city":"Thun",
    "sg:orig_category":"Finanzierungsinstitutionen",
    "sg:postcode":"3601",
    "sg:province":"Bern",
    "wof:name":"Thun Invest Ag",
    "wof:placetype":"venue"
},
  "geometry": {"coordinates":[7.6281509399,46.7597732544],"type":"Point"}
}