{
  "type": "Feature",
  "properties": {
    "iso:country":"CH",
    "sg:address":"Chemin Des Aulx 18",
    "sg:city":"Plan-les-ouates",
    "sg:orig_category":"Grosshandel mit B\u00fcromaschinen Grosshandel mit Datenverarbeitungsger\u00e4ten",
    "sg:phone":"+41 22 706 22 88",
    "sg:postcode":"1228",
    "sg:province":"Gen\u00e8ve",
    "wof:name":"Dfi Service Sa",
    "wof:placetype":"venue"
},
  "geometry": {"coordinates":[6.1043782234,46.1676292419],"type":"Point"}
}