{
  "type": "Feature",
  "properties": {
    "iso:country":"CH",
    "sg:address":"Via Bascira",
    "sg:city":"Agno",
    "sg:orig_category":"Autotransporte international",
    "sg:phone":"+41 91 605 56 50",
    "sg:postcode":"6982",
    "sg:province":"Ticino",
    "wof:name":"Fracht Sa Transports Internationaux",
    "wof:placetype":"venue"
},
  "geometry": {"coordinates":[8.900997,45.997448],"type":"Point"}
}