{
  "type": "Feature",
  "properties": {
    "iso:country":"CH",
    "sg:address":"St. Galler-ring 218",
    "sg:city":"Basel",
    "sg:orig_category":"Handelsvermittlung Kauf U Verkauf von Immobilien auf eigene Rechnung",
    "sg:phone":"+41 61 302 66 02",
    "sg:postcode":"4054",
    "sg:province":"Basel-Stadt",
    "wof:name":"Gallmi Ag",
    "wof:placetype":"venue"
},
  "geometry": {"coordinates":[7.5686402321,47.5500984192],"type":"Point"}
}