{
  "type": "Feature",
  "properties": {
    "iso:country":"CH",
    "sg:address":"Tanneggerstrasse 30 8374 Dussnang. Postfach",
    "sg:city":"Dussnang",
    "sg:orig_category":"Herstellung von Pumpen U Kompressoren",
    "sg:postcode":"8374",
    "sg:province":"Thurgau",
    "wof:name":"Werner Forrer",
    "wof:placetype":"venue"
},
  "geometry": {"coordinates":[8.9535903931,47.4288406372],"type":"Point"}
}