{
  "type": "Feature",
  "properties": {
    "iso:country":"CH",
    "sg:address":"Rue Granges 13",
    "sg:city":"Estavayer-le-lac",
    "sg:orig_category":"Dachdeckerei Zimmerei, Dachdeckerei, Bauspenglerei U Abdichtung",
    "sg:phone":"+41 26 663 18 64",
    "sg:postcode":"1470",
    "sg:province":"Fribourg",
    "wof:name":"Bise Alfred & Fils Sa",
    "wof:placetype":"venue"
},
  "geometry": {"coordinates":[6.849091,46.850197],"type":"Point"}
}