{
  "type": "Feature",
  "properties": {
    "iso:country":"CH",
    "sg:address":"Kirchstrasse 1 8304 Wallisellen. Postfach",
    "sg:city":"Wallisellen",
    "sg:orig_category":"Wirtschaftspr\u00fcfung, Steuerberatung U Treuhand",
    "sg:phone":"+41 18304640",
    "sg:postcode":"8304",
    "sg:province":"Z\u00fcrich",
    "wof:name":"Robat Ag",
    "wof:placetype":"venue"
},
  "geometry": {"coordinates":[8.5924978256,47.4137954712],"type":"Point"}
}