{
  "type": "Feature",
  "properties": {
    "iso:country":"CH",
    "sg:address":"3600",
    "sg:city":"Thun",
    "sg:orig_category":"Sportvereine Ski",
    "sg:phone":"+41 32 223 43 29",
    "sg:postcode":"3600",
    "sg:province":"Bern",
    "wof:name":"Skiclub Thun",
    "wof:placetype":"venue"
},
  "geometry": {"coordinates":[7.6217298508,46.7510414124],"type":"Point"}
}