{
  "type": "Feature",
  "properties": {
    "iso:country":"CH",
    "sg:address":"Croix-du-p\u00e9age",
    "sg:city":"Villars-ste-croix",
    "sg:orig_category":"Instandhaltung U Reparatur von Automobilen",
    "sg:phone":"+41 21 944 23 62",
    "sg:postcode":"1029",
    "sg:province":"Vaud",
    "wof:name":"Garage De La Tour Ribordy O. S\u00e0rl",
    "wof:placetype":"venue"
},
  "geometry": {"coordinates":[6.8602228165,46.4529037476],"type":"Point"}
}