{
  "type": "Feature",
  "properties": {
    "iso:country":"CH",
    "sg:address":"Route Des Esserts 4 B",
    "sg:city":"Duillier",
    "sg:orig_category":"Unclassifiable Establishments",
    "sg:postcode":"1266",
    "sg:province":"Vaud",
    "wof:name":"Rasan Gmbh",
    "wof:placetype":"venue"
},
  "geometry": {"coordinates":[8.1827249527,47.0368156433],"type":"Point"}
}