{
  "type": "Feature",
  "properties": {
    "iso:country":"CH",
    "sg:address":"Avenue Louis-casa\u00ef 27 1214 Vernier. Postfach",
    "sg:city":"Vernier",
    "sg:orig_category":"Fachdetailhandel in Verkaufsr\u00e4umen",
    "sg:postcode":"1214",
    "sg:province":"Gen\u00e8ve",
    "wof:name":"Bondat Sholeh",
    "wof:placetype":"venue"
},
  "geometry": {"coordinates":[6.1143360138,46.2193374634],"type":"Point"}
}