{
  "type": "Feature",
  "properties": {
    "iso:country":"CH",
    "sg:address":"Kasernenstrasse 32 4058 Basel. Postfach",
    "sg:city":"Basel",
    "sg:orig_category":"Druck ohne Zeitungsdruck Offsetdruck",
    "sg:phone":"+41 91 683 21 50",
    "sg:postcode":"4005",
    "sg:province":"Basel-Stadt",
    "wof:name":"Grosa Offset-tipografia Sa",
    "wof:placetype":"venue"
},
  "geometry": {"coordinates":[9.022769928,45.8420143127],"type":"Point"}
}