{
  "type": "Feature",
  "properties": {
    "addr:full":"Route De Gen\u00e8ve 80 Pr\u00e9verenges Vaud 1028",
    "addr:housenumber":"80",
    "addr:postcode":"1028",
    "addr:street":"Route De Gene\u0300Ve",
    "iso:country":"CH",
    "sg:address":"Route De Gen\u00e8ve 80",
    "sg:city":"Pr\u00e9verenges",
    "sg:orig_category":"Allgemeiner Hoch U Tiefbau",
    "sg:phone":"+41 21 802 38 71",
    "sg:postcode":"1028",
    "sg:province":"Vaud",
    "wof:name":"Helfer Daniel",
    "wof:placetype":"venue"
},
  "geometry": {"coordinates":[6.537607,46.514725],"type":"Point"}
}