{
  "type": "Feature",
  "properties": {
    "iso:country":"CH",
    "sg:address":"Sportzentrum Saane Sense",
    "sg:city":"B\u00f6singen",
    "sg:orig_category":"RESTAURANTS: TEA-ROOMS",
    "sg:phone":"+41 31479392",
    "sg:postcode":"3178",
    "sg:province":"Fribourg",
    "wof:name":"Bloise & Bloise",
    "wof:placetype":"venue"
},
  "geometry": {"coordinates":[7.2279667854,46.8925971985],"type":"Point"}
}