{
  "type": "Feature",
  "properties": {
    "iso:country":"CH",
    "sg:address":"Chemin De La Vuarpilli\u00e8re 29",
    "sg:city":"Nyon",
    "sg:orig_category":"Wirtschaftspr\u00fcfung, Steuerberatung U Treuhand",
    "sg:phone":"+41 22 362 39 40",
    "sg:postcode":"1260",
    "sg:province":"Vaud",
    "wof:name":"Fiduciaire Ecofis Sa",
    "wof:placetype":"venue"
},
  "geometry": {"coordinates":[6.2174501419,46.3993835449],"type":"Point"}
}