{
  "type": "Feature",
  "properties": {
    "iso:country":"CH",
    "sg:address":"Zeughausplatz 26",
    "sg:city":"Liestal",
    "sg:orig_category":"Reparatur von Uhren U Schmuck",
    "sg:phone":"+41 32 913 81 18",
    "sg:postcode":"4410",
    "sg:province":"Basel-Landschaft",
    "wof:name":"William Schmid Horlogerie",
    "wof:placetype":"venue"
},
  "geometry": {"coordinates":[6.8257160187,47.1000175476],"type":"Point"}
}