{
  "type": "Feature",
  "properties": {
    "iso:country":"CH",
    "sg:address":"Z\u00fcrcherstrasse 1 8730 Uznach. Postfach 455",
    "sg:city":"Uznach",
    "sg:orig_category":"Malerei",
    "sg:phone":"+41 55 280 31 31",
    "sg:postcode":"8730",
    "sg:province":"St. Gallen",
    "wof:name":"Jakob Zehnder Malergesch\u00e4ft",
    "wof:placetype":"venue"
},
  "geometry": {"coordinates":[8.983549118,47.2246246338],"type":"Point"}
}