{
  "type": "Feature",
  "properties": {
    "iso:country":"CH",
    "sg:address":"B\u00fcmplizstrasse 101 3018 Bern. Postfach 546",
    "sg:city":"Bern",
    "sg:orig_category":"Buchverlag Verlagsgewerbe",
    "sg:phone":"+41 31 747 87 77",
    "sg:postcode":"3018",
    "sg:province":"Bern",
    "wof:name":"Mastermedia Verlagsgenossenschaft",
    "wof:placetype":"venue"
},
  "geometry": {"coordinates":[7.236317,46.905712],"type":"Point"}
}