{
  "type": "Feature",
  "properties": {
    "iso:country":"CH",
    "sg:address":"Castelrotto Via 15 6600 Locarno. Postfach",
    "sg:city":"Locarno",
    "sg:orig_category":"Softwareentwicklung U beratung",
    "sg:postcode":"6600",
    "sg:province":"Ticino",
    "wof:name":"Alfio Sa",
    "wof:placetype":"venue"
},
  "geometry": {"coordinates":[8.7918348312,46.1688842773],"type":"Point"}
}