{
  "type": "Feature",
  "properties": {
    "iso:country":"CH",
    "sg:address":"Postgasse 26",
    "sg:city":"Pieterlen",
    "sg:classifiers":[
        {
            "category":"Manufacturing",
            "subcategory":"Glass & Minerals",
            "type":"Manufacturing & Wholesale Goods"
        }
    ],
    "sg:phone":"+41 32 377 29 27",
    "sg:postcode":"2542",
    "sg:province":"Bern",
    "sg:tags":[
        "frame"
    ],
    "wof:name":"Combicolor Ag",
    "wof:placetype":"venue"
},
  "geometry": {"coordinates":[7.3369441032,47.1737098694],"type":"Point"}
}