{
  "type": "Feature",
  "properties": {
    "addr:full":"Aarauerstrasse 2 Oberentfelden Aargau 5036",
    "addr:housenumber":"2",
    "addr:postcode":"5036",
    "addr:street":"Aarauerstrasse",
    "iso:country":"CH",
    "sg:address":"Aarauerstrasse 2",
    "sg:city":"Oberentfelden",
    "sg:orig_category":"Chemische Reinigung",
    "sg:phone":"+41 62 723 42 77",
    "sg:postcode":"5036",
    "sg:province":"Aargau",
    "wof:name":"Josiane Hofer Textilreinigung",
    "wof:placetype":"venue"
},
  "geometry": {"coordinates":[8.046927,47.35704],"type":"Point"}
}