{
  "type": "Feature",
  "properties": {
    "iso:country":"CH",
    "sg:address":"Unterackerweg 452",
    "sg:city":"M\u00fcmliswil",
    "sg:orig_category":"Druck ohne Zeitungsdruck",
    "sg:phone":"+41 62 391 04 58",
    "sg:postcode":"4717",
    "sg:province":"Solothurn",
    "wof:name":"Martypo Marty Andreas",
    "wof:placetype":"venue"
},
  "geometry": {"coordinates":[7.7011628151,47.3448181152],"type":"Point"}
}