{
  "type": "Feature",
  "properties": {
    "iso:country":"CH",
    "sg:address":"5316",
    "sg:city":"Leuggern",
    "sg:classifiers":[
        {
            "category":"Education",
            "subcategory":"Vocational School",
            "type":"Public Place"
        }
    ],
    "sg:phone":"+41 71 377 12 21",
    "sg:postcode":"5316",
    "sg:province":"Aargau",
    "sg:tags":[
        "koch-",
        "haushaltschulen"
    ],
    "wof:name":"Haushaltungsschule",
    "wof:placetype":"venue"
},
  "geometry": {"coordinates":[8.2197446823,47.5788726807],"type":"Point"}
}