{
  "type": "Feature",
  "properties": {
    "addr:full":"Hohr\u00fctistrasse 52 Kloten Z\u00fcrich 8302",
    "addr:housenumber":"52",
    "addr:postcode":"8302",
    "addr:street":"Hohruetistrasse",
    "iso:country":"CH",
    "sg:address":"Hohr\u00fctistrasse 52",
    "sg:city":"Kloten",
    "sg:orig_category":"Allgemeiner Hoch U Tiefbau Hoch U Tiefbau",
    "sg:phone":"+41 18140322",
    "sg:postcode":"8302",
    "sg:province":"Z\u00fcrich",
    "wof:name":"M. Musci Ag",
    "wof:placetype":"venue"
},
  "geometry": {"coordinates":[8.584563,47.464748],"type":"Point"}
}