{
  "type": "Feature",
  "properties": {
    "iso:country":"CH",
    "sg:address":"Birsigstrasse 122 4054 Basel. Postfach 142",
    "sg:city":"Basel",
    "sg:orig_category":"Architektur U Ingenieurb\u00fcros Architekturb\u00fcros",
    "sg:phone":"+41 61 225 26 26",
    "sg:postcode":"4011",
    "sg:province":"Basel-Stadt",
    "wof:name":"Flubacher, Nyfeler + Partner Architekten Gmbh",
    "wof:placetype":"venue"
},
  "geometry": {"coordinates":[7.577719,47.550652],"type":"Point"}
}