{
  "type": "Feature",
  "properties": {
    "iso:country":"CH",
    "sg:address":"8212",
    "sg:city":"Neuhausen",
    "sg:classifiers":[
        {
            "category":"Education",
            "subcategory":"Vocational School",
            "type":"Public Place"
        }
    ],
    "sg:postcode":"8212",
    "sg:province":"Schaffhausen",
    "sg:tags":[
        "koch-",
        "haushaltschulen"
    ],
    "wof:name":"Haushaltungsschule",
    "wof:placetype":"venue"
},
  "geometry": {"coordinates":[8.6196098328,47.6815681458],"type":"Point"}
}