{
  "type": "Feature",
  "properties": {
    "iso:country":"CH",
    "sg:address":"Rue Du Simplon 4",
    "sg:city":"Vevey",
    "sg:orig_category":"Detailhandel mit Bekleidung Detailhandel mit Pelzwaren",
    "sg:phone":"+41 21 921 20 23",
    "sg:postcode":"1800",
    "sg:province":"Vaud",
    "wof:name":"Fritsch\u00e9 Fourrures Sa",
    "wof:placetype":"venue"
},
  "geometry": {"coordinates":[6.846969,46.45916],"type":"Point"}
}