{
  "type": "Feature",
  "properties": {
    "iso:country":"CH",
    "sg:address":"Sonnmattstrasse 2",
    "sg:city":"Mosnang",
    "sg:orig_category":"Grosshandel mit Getreide, Saatgut U Futtermitteln",
    "sg:phone":"+41 71 983 16 65",
    "sg:postcode":"9607",
    "sg:province":"St. Gallen",
    "wof:name":"Bamert W., Futterkonzentrate",
    "wof:placetype":"venue"
},
  "geometry": {"coordinates":[9.0518846512,47.3645362854],"type":"Point"}
}