{
  "type": "Feature",
  "properties": {
    "iso:country":"CH",
    "sg:address":"Stansstaderstrasse 17",
    "sg:city":"Stans",
    "sg:orig_category":"Kauf U Verkauf von Immobilien auf eigene Rechnung",
    "sg:phone":"+41 41 630 30 30",
    "sg:postcode":"6370",
    "sg:province":"Nidwalden",
    "wof:name":"Feldmoos Ag",
    "wof:placetype":"venue"
},
  "geometry": {"coordinates":[8.3638143539,46.9586029053],"type":"Point"}
}