{
  "type": "Feature",
  "properties": {
    "iso:country":"CH",
    "sg:address":"Via Stazione 2",
    "sg:city":"Lamone",
    "sg:orig_category":"Grosshandel mit Holz U Bauelementen aus Holz Grosshandel mit Holz U Baustoffen",
    "sg:phone":"+41 27 722 28 85",
    "sg:postcode":"6814",
    "sg:province":"Ticino",
    "wof:name":"Marti Mat\u00e9riaux Sa",
    "wof:placetype":"venue"
},
  "geometry": {"coordinates":[7.0735569,46.1060066223],"type":"Point"}
}