{
  "type": "Feature",
  "properties": {
    "iso:country":"CH",
    "sg:address":"Retica Via",
    "sg:city":"Samedan",
    "sg:orig_category":"Unclassifiable Establishments",
    "sg:postcode":"7503",
    "sg:province":"Graubunden",
    "wof:name":"L\u00fcthi Beteiligungs + Immobilien Ag",
    "wof:placetype":"venue"
},
  "geometry": {"coordinates":[9.8707799911,46.5317687988],"type":"Point"}
}