{
  "type": "Feature",
  "properties": {
    "iso:country":"CH",
    "sg:address":"Route De Vernier 94",
    "sg:city":"Ch\u00e2telaine",
    "sg:orig_category":"Stukkateurgewerbe, Gipserei U Verputzerei Tapeziererei",
    "sg:phone":"+41 22 797 00 85",
    "sg:postcode":"1219",
    "sg:province":"Gen\u00e8ve",
    "wof:name":"R\u00e9novation Immobili\u00e8re Valletta & Soltani",
    "wof:placetype":"venue"
},
  "geometry": {"coordinates":[6.1079711914,46.2116127014],"type":"Point"}
}