{
  "type": "Feature",
  "properties": {
    "iso:country":"CH",
    "sg:address":"Milit\u00e4rstrasse 6 3600 Thun. Postfach 1442",
    "sg:city":"Thun",
    "sg:orig_category":"Vermittlung von Immobilien Verwaltung von Immobilien",
    "sg:phone":"+41 33 223 11 23",
    "sg:postcode":"3601",
    "sg:province":"Bern",
    "wof:name":"Deyhle & Partner Gmbh",
    "wof:placetype":"venue"
},
  "geometry": {"coordinates":[7.6161141396,46.7567672729],"type":"Point"}
}