{
  "type": "Feature",
  "properties": {
    "iso:country":"CH",
    "sg:address":"Bahnhofstrasse 49",
    "sg:city":"R\u00fcschlikon",
    "sg:orig_category":"Nationale Postdienste",
    "sg:phone":"+41 17240000",
    "sg:postcode":"8803",
    "sg:province":"Z\u00fcrich",
    "wof:name":"Die Schweizerische Post",
    "wof:placetype":"venue"
},
  "geometry": {"coordinates":[8.5555276871,47.3073501587],"type":"Point"}
}