{
  "type": "Feature",
  "properties": {
    "iso:country":"CH",
    "sg:address":"Jaquettes Rue Des",
    "sg:city":"Baulmes",
    "sg:orig_category":"Fachdetailhandel in Verkaufsr\u00e4umen",
    "sg:postcode":"1446",
    "sg:province":"Vaud",
    "wof:name":"La Boutique Du Mur, Pinilla Francisco",
    "wof:placetype":"venue"
},
  "geometry": {"coordinates":[6.5238251686,46.7907867432],"type":"Point"}
}