{
  "type": "Feature",
  "properties": {
    "iso:country":"CH",
    "sg:address":"R\u00f6tistrasse 2a",
    "sg:city":"Feldbrunnen",
    "sg:orig_category":"Informatikdienste",
    "sg:phone":"+41 32 372 12 12",
    "sg:postcode":"4532",
    "sg:province":"Solothurn",
    "wof:name":"Digi Fee Kurt Fessler",
    "wof:placetype":"venue"
},
  "geometry": {"coordinates":[7.277451992,47.1250648499],"type":"Point"}
}