{
  "type": "Feature",
  "properties": {
    "iso:country":"CH",
    "sg:address":"Lagerhausweg 0",
    "sg:city":"Bern",
    "sg:orig_category":"Softwareentwicklung U beratung",
    "sg:phone":"+41 31 991 78 74",
    "sg:postcode":"3018",
    "sg:province":"Bern",
    "wof:name":"B&c Computer Gmbh",
    "wof:placetype":"venue"
},
  "geometry": {"coordinates":[7.3924298286,46.9359092712],"type":"Point"}
}