{
  "type": "Feature",
  "properties": {
    "iso:country":"CH",
    "sg:address":"Seestrasse 184",
    "sg:city":"M\u00e4nnedorf",
    "sg:orig_category":"Sonstiger spezialisierter Hoch U Tiefbau",
    "sg:postcode":"8708",
    "sg:province":"Z\u00fcrich",
    "wof:name":"Holenstein Bruno",
    "wof:placetype":"venue"
},
  "geometry": {"coordinates":[8.6889543533,47.2543487549],"type":"Point"}
}