{
  "type": "Feature",
  "properties": {
    "iso:country":"CH",
    "sg:address":"Marktgasse 1 3800 Interlaken. Postfach 51",
    "sg:city":"Interlaken",
    "sg:orig_category":"R\u00fcckgewinnung U Vorbereitung f\u00fcr die Wiederverwertung Recycling Sonstiger spezialisierter Hoch U Tie",
    "sg:phone":"+41 41 660 66 80",
    "sg:postcode":"3800",
    "sg:province":"Bern",
    "wof:name":"Bernhard Walther Demontagen & Entsorgungs Ag",
    "wof:placetype":"venue"
},
  "geometry": {"coordinates":[8.26728,46.929138],"type":"Point"}
}