{
  "type": "Feature",
  "properties": {
    "iso:country":"CH",
    "sg:address":"Haldenstrasse 26b 8306 Br\u00fcttisellen. Postfach",
    "sg:city":"Br\u00fcttisellen",
    "sg:orig_category":"Grosshandel mit sonstigen Maschinen U Ausr\u00fcstungen f\u00fcr Industrie, Handel U Schiffahrt",
    "sg:phone":"+41 41 854 50 10",
    "sg:postcode":"8306",
    "sg:province":"Z\u00fcrich",
    "wof:name":"Handelsagentur Walt Ag",
    "wof:placetype":"venue"
},
  "geometry": {"coordinates":[8.4415683746,47.0812110901],"type":"Point"}
}