{
  "type": "Feature",
  "properties": {
    "iso:country":"CH",
    "sg:address":"1753",
    "sg:city":"Matran",
    "sg:orig_category":"Herstellung von Metallerzeugnissen ohne Maschinenbau Maschinenbau",
    "sg:phone":"+41 26 402 20 96",
    "sg:postcode":"1753",
    "sg:province":"Fribourg",
    "wof:name":"Boschung Marcel, Fabrication De Machines Communales Sa, Matran",
    "wof:placetype":"venue"
},
  "geometry": {"coordinates":[7.0887098312,46.7851715088],"type":"Point"}
}