{
  "type": "Feature",
  "properties": {
    "iso:country":"CH",
    "sg:address":"Industrie Eschmatt Gibswil 8497 Fischenthal. Postfach",
    "sg:city":"Gibswil",
    "sg:orig_category":"Herstellung von k\u00e4lte U lufttechnischen Erzeugnissen f\u00fcr gewerbliche Zwecke",
    "sg:postcode":"8498",
    "sg:province":"Z\u00fcrich",
    "wof:name":"Belimo Fensterl\u00fcftungssysteme Ag",
    "wof:placetype":"venue"
},
  "geometry": {"coordinates":[8.793598175,47.3154792786],"type":"Point"}
}