{
  "type": "Feature",
  "properties": {
    "iso:country":"CH",
    "sg:address":"Rte De Jussy 280",
    "sg:city":"Jussy",
    "sg:orig_category":"Unclassifiable Establishments",
    "sg:postcode":"1254",
    "sg:province":"Gen\u00e8ve",
    "wof:name":"Vaugnat Anne",
    "wof:placetype":"venue"
},
  "geometry": {"coordinates":[6.2606210709,46.2351608276],"type":"Point"}
}