{
  "type": "Feature",
  "properties": {
    "iso:country":"CH",
    "sg:address":"Petit-cortaillod",
    "sg:city":"Cortaillod",
    "sg:orig_category":"HOTELS: MIT RESTAURANT Kongress- and Tagungshotels mit Restaurant",
    "sg:phone":"+41 22 731 62 50",
    "sg:postcode":"2016",
    "sg:province":"Neuch\u00e2tel",
    "wof:name":"H\u00f4tel Le Warwick",
    "wof:placetype":"venue"
},
  "geometry": {"coordinates":[6.144329071,46.2107887268],"type":"Point"}
}