{
  "type": "Feature",
  "properties": {
    "iso:country":"CH",
    "sg:address":"Derrey-la-velaz 1058 Villars-tiercelin. Postfach",
    "sg:city":"Villars-tiercelin",
    "sg:orig_category":"Markt U Meinungsforschung",
    "sg:postcode":"1058",
    "sg:province":"Vaud",
    "wof:name":"Zenger Consulting S\u00e0rl Prestations Li\u00e9es Au Marketing Dans Le Domaine De La Vente Etc",
    "wof:placetype":"venue"
},
  "geometry": {"coordinates":[6.7050600052,46.625038147],"type":"Point"}
}