{
  "type": "Feature",
  "properties": {
    "iso:country":"CH",
    "sg:address":"Langackerstrasse 25",
    "sg:city":"Cham",
    "sg:orig_category":"Handelsvermittlung U Grosshandel",
    "sg:phone":"+41 41 610 29 05",
    "sg:postcode":"6330",
    "sg:province":"Zug",
    "wof:name":"Eduard Amstad Landesprodukte",
    "wof:placetype":"venue"
},
  "geometry": {"coordinates":[8.3777961731,46.9575767517],"type":"Point"}
}