{
  "type": "Feature",
  "properties": {
    "iso:country":"CH",
    "sg:address":"Goliathgasse 37",
    "sg:city":"St.gallen",
    "sg:orig_category":"Herstellung von Schmuck, Gold U Silberschmiedwaren Herstellung von sonstigen Metallwaren",
    "sg:phone":"+41 71 244 05 91",
    "sg:postcode":"9000",
    "sg:province":"St. Gallen",
    "wof:name":"Brunner Gravuren",
    "wof:placetype":"venue"
},
  "geometry": {"coordinates":[9.3771190643,47.4278717041],"type":"Point"}
}