{
  "type": "Feature",
  "properties": {
    "iso:country":"CH",
    "sg:address":"Via Al Parco 18",
    "sg:city":"Orselina",
    "sg:orig_category":"Landesverteidigung, Sozialversicherung \u00d6ffentliche Verwaltung",
    "sg:phone":"+41 91 743 22 73",
    "sg:postcode":"6644",
    "sg:province":"Ticino",
    "wof:name":"Centro Di Protezione Civile Di Orselina",
    "wof:placetype":"venue"
},
  "geometry": {"coordinates":[8.7994213104,46.1791152954],"type":"Point"}
}