{
  "type": "Feature",
  "properties": {
    "iso:country":"CH",
    "sg:address":"Dorfstrasse 11",
    "sg:city":"W\u00e4ngi",
    "sg:orig_category":"Detailhandel mit Waren verschiedener Art, Hauptrichtung Nahrungsmittel",
    "sg:phone":"+41 71 969 47 50",
    "sg:postcode":"9545",
    "sg:province":"Thurgau",
    "wof:name":"Coop Winterthur",
    "wof:placetype":"venue"
},
  "geometry": {"coordinates":[8.9954986572,47.4791984558],"type":"Point"}
}