{
  "type": "Feature",
  "properties": {
    "iso:country":"CH",
    "sg:address":"Sagen",
    "sg:city":"Gunzwil",
    "sg:orig_category":"Schlachten U Fleischverarbeitung",
    "sg:phone":"+41 41 930 21 07",
    "sg:postcode":"6222",
    "sg:province":"Luzern",
    "wof:name":"Heinrich Estermann Schlachthaus",
    "wof:placetype":"venue"
},
  "geometry": {"coordinates":[8.1788654327,47.2114143372],"type":"Point"}
}