{
  "type": "Feature",
  "properties": {
    "addr:full":"Bernerh\u00f6he Goldau Schwyz 6410",
    "addr:postcode":"6410",
    "addr:street":"Schwyz",
    "iso:country":"CH",
    "sg:address":"Bernerh\u00f6he",
    "sg:city":"Goldau",
    "sg:orig_category":"Detailhandel mit Antiquit\u00e4ten Schmieden",
    "sg:phone":"+41 41 855 17 50",
    "sg:postcode":"6410",
    "sg:province":"Schwyz",
    "wof:name":"Rudolf Pfister",
    "wof:placetype":"venue"
},
  "geometry": {"coordinates":[8.552717,47.042747],"type":"Point"}
}