{
  "type": "Feature",
  "properties": {
    "iso:country":"CH",
    "sg:address":"9512",
    "sg:city":"Rossr\u00fcti",
    "sg:orig_category":"Primarschulen",
    "sg:phone":"+41 55 643 34 72",
    "sg:postcode":"9512",
    "sg:province":"St. Gallen",
    "wof:name":"Primarschule Rossr\u00fcti",
    "wof:placetype":"venue"
},
  "geometry": {"coordinates":[9.0608825684,47.4741821289],"type":"Point"}
}