{
  "type": "Feature",
  "properties": {
    "addr:full":"Masanserstrasse 35 7000 Chur. Postfach Chur Graubunden 7001",
    "addr:housenumber":"35",
    "addr:postcode":"7000;postfach;7001",
    "addr:street":"Masanserstrasse",
    "iso:country":"CH",
    "sg:address":"Masanserstrasse 35 7000 Chur. Postfach",
    "sg:city":"Chur",
    "sg:orig_category":"Advokaturb\u00fcros",
    "sg:phone":"+41 81 257 03 80",
    "sg:postcode":"7001",
    "sg:province":"Graubunden",
    "wof:name":"Martin Buchli Advokaturb\u00fcro",
    "wof:placetype":"venue"
},
  "geometry": {"coordinates":[9.534607,46.854759],"type":"Point"}
}