{
  "type": "Feature",
  "properties": {
    "iso:country":"CH",
    "sg:address":"Falknerstrasse 9 4001 Basel. Postfach",
    "sg:city":"Basel",
    "sg:orig_category":"Detailhandel mit Blumen U Pflanzen Fachdetailhandel in Verkaufsr\u00e4umen",
    "sg:phone":"+41 61 261 45 77",
    "sg:postcode":"4001",
    "sg:province":"Basel-Stadt",
    "wof:name":"Blumen Dufour Bei Der Hauptpost Ag",
    "wof:placetype":"venue"
},
  "geometry": {"coordinates":[7.589151,47.556248],"type":"Point"}
}