{
  "type": "Feature",
  "properties": {
    "iso:country":"CH",
    "sg:address":"Schulhausstrasse 18",
    "sg:city":"Unterseen",
    "sg:orig_category":"Unternehmensberatung",
    "sg:phone":"+41 33 822 73 79",
    "sg:postcode":"3800",
    "sg:province":"Bern",
    "wof:name":"Anderegg Treuhand",
    "wof:placetype":"venue"
},
  "geometry": {"coordinates":[7.8439588547,46.684879303],"type":"Point"}
}