{
  "type": "Feature",
  "properties": {
    "iso:country":"CH",
    "sg:address":"Place Du Ch\u00e2teau 3",
    "sg:city":"Nyon",
    "sg:orig_category":"Non-Classified Establishments",
    "sg:postcode":"1260",
    "sg:province":"Vaud",
    "wof:name":"Gais Logis",
    "wof:placetype":"venue"
},
  "geometry": {"coordinates":[6.2400751114,46.3822555542],"type":"Point"}
}