{
  "type": "Feature",
  "properties": {
    "iso:country":"CH",
    "sg:address":"Sources Rue Des 8 1205 Gen\u00e8ve. Postfach",
    "sg:city":"Gen\u00e8ve",
    "sg:orig_category":"RESTAURANTS: TEA-ROOMS",
    "sg:phone":"+41 62 822 39 77",
    "sg:postcode":"1205",
    "sg:province":"Gen\u00e8ve",
    "wof:name":"Quellengrund Ag",
    "wof:placetype":"venue"
},
  "geometry": {"coordinates":[8.0819072723,47.402507782],"type":"Point"}
}