{
  "type": "Feature",
  "properties": {
    "iso:country":"CH",
    "sg:address":"Bahnhofstrasse 43",
    "sg:city":"Schaffhausen",
    "sg:orig_category":"Hardwareberatung",
    "sg:postcode":"8200",
    "sg:province":"Schaffhausen",
    "wof:name":"Sch\u00fctz Hansj\u00f6rg",
    "wof:placetype":"venue"
},
  "geometry": {"coordinates":[8.6333303452,47.698261261],"type":"Point"}
}