{
  "type": "Feature",
  "properties": {
    "iso:country":"CH",
    "sg:address":"Bahnhofzentrum 3186 D\u00fcdingen. Postfach",
    "sg:city":"D\u00fcdingen",
    "sg:orig_category":"Architektur U Ingenieurb\u00fcros",
    "sg:postcode":"3186",
    "sg:province":"Fribourg",
    "wof:name":"Curty + Marty Ag",
    "wof:placetype":"venue"
},
  "geometry": {"coordinates":[7.190075,46.85041],"type":"Point"}
}