{
  "type": "Feature",
  "properties": {
    "iso:country":"CH",
    "sg:address":"Kirchbergstrasse 25",
    "sg:city":"Burgdorf",
    "sg:orig_category":"Detailhandel mit elektrischen Haushalts-,Radio U Fernsehger\u00e4ten sowie Musikinstrumenten Grosshandel ",
    "sg:postcode":"3400",
    "sg:province":"Bern",
    "wof:name":"Rdx Music Systems, Berger Lukas",
    "wof:placetype":"venue"
},
  "geometry": {"coordinates":[7.6206297874,47.061958313],"type":"Point"}
}