{
  "type": "Feature",
  "properties": {
    "iso:country":"CH",
    "sg:address":"Schulweg 7",
    "sg:city":"Spiez",
    "sg:orig_category":"Kaminfeger",
    "sg:phone":"+41 79 358 44 40",
    "sg:postcode":"3700",
    "sg:province":"Bern",
    "wof:name":"Paul Maurer Kreiskaminfegermeister",
    "wof:placetype":"venue"
},
  "geometry": {"coordinates":[7.6694121361,46.6914558411],"type":"Point"}
}