{
  "type": "Feature",
  "properties": {
    "addr:full":"Binzstrasse 15 8045 Z\u00fcrich. Postfach Z\u00fcrich Z\u00fcrich 8045",
    "addr:housenumber":"15",
    "addr:postcode":"8045 zuerich. postfach;8045",
    "addr:street":"Binzstrasse",
    "iso:country":"CH",
    "sg:address":"Binzstrasse 15 8045 Z\u00fcrich. Postfach",
    "sg:city":"Z\u00fcrich",
    "sg:orig_category":"Bauingenieurb\u00fcros Heizung L\u00fcftung Klima Planer f\u00fcr Alternativenergie and Solararchitektur",
    "sg:phone":"+41 41 377 54 54",
    "sg:postcode":"8045",
    "sg:province":"Z\u00fcrich",
    "wof:name":"Ingenieurb\u00fcro Wettstein M. Ingenieurb\u00fcro F. Haustechnik U. Energiemanagement",
    "wof:placetype":"venue"
},
  "geometry": {"coordinates":[8.441315,47.085278],"type":"Point"}
}