{
  "type": "Feature",
  "properties": {
    "iso:country":"CH",
    "sg:address":"Chemin Des Collines 2",
    "sg:city":"Sion",
    "sg:orig_category":"Detektivb\u00fcros U \u00dcberwachung Sicherheitsdienste",
    "sg:phone":"+41 27 323 40 10",
    "sg:postcode":"1950",
    "sg:province":"Valais",
    "wof:name":"Fm S\u00e9curit\u00e9, Frizzi Maurice",
    "wof:placetype":"venue"
},
  "geometry": {"coordinates":[7.3566160202,46.2329406738],"type":"Point"}
}