{
  "type": "Feature",
  "properties": {
    "addr:full":"Rue De La Boverie 36 1530 Payerne Case Postale 429 Payerne Vaud 1530",
    "addr:housenumber":"36",
    "addr:postcode":"1530;1530",
    "addr:street":"Rue De La Boverie;Postale 429",
    "iso:country":"CH",
    "sg:address":"Rue De La Boverie 36 1530 Payerne Case Postale 429",
    "sg:city":"Payerne",
    "sg:orig_category":"Grosshandel mit Tabakwaren Tabakverarbeitung",
    "sg:phone":"+41 26 662 43 21",
    "sg:postcode":"1530",
    "sg:province":"Vaud",
    "wof:name":"Fermenta Sa Payerne",
    "wof:placetype":"venue"
},
  "geometry": {"coordinates":[6.933589,46.816639],"type":"Point"}
}