{
  "type": "Feature",
  "properties": {
    "iso:country":"CH",
    "sg:address":"Bleicherweg 18",
    "sg:city":"Z\u00fcrich",
    "sg:classifiers":[
        {
            "category":"Banks & Credit Unions",
            "subcategory":"Bank",
            "type":"Services"
        }
    ],
    "sg:phone":"+41 81 257 08 40",
    "sg:postcode":"8039",
    "wof:name":"Privatbank Vermag Ag",
    "wof:placetype":"venue"
},
  "geometry": {"coordinates":[9.53225,46.849579],"type":"Point"}
}