{
  "type": "Feature",
  "properties": {
    "iso:country":"CH",
    "sg:address":"Artherstrasse 6",
    "sg:city":"Walchwil",
    "sg:classifiers":[
        {
            "category":"Restaurant",
            "type":"Food & Drink"
        }
    ],
    "sg:phone":"+41 61 711 77 33",
    "sg:postcode":"6318",
    "sg:province":"Zug",
    "wof:name":"Restaurant Zuggerzange",
    "wof:placetype":"venue"
},
  "geometry": {"coordinates":[7.5969581604,47.5022964478],"type":"Point"}
}