{
  "type": "Feature",
  "properties": {
    "iso:country":"CH",
    "sg:address":"Chemin De Bottai",
    "sg:city":"Chernex",
    "sg:orig_category":"Detailhandel mit M\u00f6beln U Haushaltsgegenst\u00e4nden",
    "sg:postcode":"1822",
    "sg:province":"Vaud",
    "wof:name":"Asb Marketing Sa",
    "wof:placetype":"venue"
},
  "geometry": {"coordinates":[6.9033031464,46.4478416443],"type":"Point"}
}