{
  "type": "Feature",
  "properties": {
    "iso:country":"CH",
    "sg:address":"Via Alla Tenza",
    "sg:city":"Castione",
    "sg:classifiers":[
        {
            "category":"Restaurant",
            "type":"Food & Drink"
        }
    ],
    "sg:phone":"+41 91 829 13 91",
    "sg:postcode":"6532",
    "sg:province":"Ticino",
    "wof:name":"Ristorante Tenza",
    "wof:placetype":"venue"
},
  "geometry": {"coordinates":[9.0476427078,46.2271461487],"type":"Point"}
}