{
  "type": "Feature",
  "properties": {
    "iso:country":"CH",
    "sg:address":"Haldenrain 2",
    "sg:city":"Luzern",
    "sg:orig_category":"Detailhandel mit elektrischen Haushalts-,Radio U Fernsehger\u00e4ten sowie Musikinstrumenten",
    "sg:phone":"+41 41 370 12 08",
    "sg:postcode":"6006",
    "sg:province":"Luzern",
    "wof:name":"Rotach + Co",
    "wof:placetype":"venue"
},
  "geometry": {"coordinates":[8.3256883621,47.056476593],"type":"Point"}
}