{
  "type": "Feature",
  "properties": {
    "iso:country":"CH",
    "sg:address":"Chemin De La Grosse-pierre",
    "sg:city":"Morges",
    "sg:orig_category":"Sonstige pers\u00f6nliche Dienstleistungen",
    "sg:phone":"+41 24 471 12 87",
    "sg:postcode":"1110",
    "sg:province":"Vaud",
    "wof:name":"Pressing Pronto, Romiti Sergio",
    "wof:placetype":"venue"
},
  "geometry": {"coordinates":[6.9524278641,46.2509803772],"type":"Point"}
}