{
  "type": "Feature",
  "properties": {
    "iso:country":"CH",
    "sg:address":"Weinfelder Strasse 7",
    "sg:city":"M\u00e4rstetten",
    "sg:orig_category":"Grosshandel mit Tabakwaren",
    "sg:phone":"+41 71 659 01 35",
    "sg:postcode":"8560",
    "sg:province":"Thurgau",
    "wof:name":"Best-of Handels Gmbh Cigarren Import",
    "wof:placetype":"venue"
},
  "geometry": {"coordinates":[9.0620222092,47.5832862854],"type":"Point"}
}