{
  "type": "Feature",
  "properties": {
    "iso:country":"CH",
    "sg:address":"Italie Rue D' 6 1204 Gen\u00e8ve. Postfach",
    "sg:city":"Gen\u00e8ve",
    "sg:orig_category":"Architektur U Ingenieurb\u00fcros",
    "sg:postcode":"1201",
    "sg:province":"Gen\u00e8ve",
    "wof:name":"Geta Sa",
    "wof:placetype":"venue"
},
  "geometry": {"coordinates":[6.1515,46.204948],"type":"Point"}
}