{
  "type": "Feature",
  "properties": {
    "iso:country":"CH",
    "sg:address":"Limmatquai 94 8000 Z\u00fcrich. Postfach",
    "sg:city":"Z\u00fcrich",
    "sg:orig_category":"Vermietung U Verpachtung von eigenen Immobilien",
    "sg:postcode":"8001",
    "sg:province":"Z\u00fcrich",
    "wof:name":"Interregio-immobilien Ag",
    "wof:placetype":"venue"
},
  "geometry": {"coordinates":[8.2775468826,47.3483123779],"type":"Point"}
}