{
  "type": "Feature",
  "properties": {
    "iso:country":"CH",
    "sg:address":"Zwinglistrasse 33",
    "sg:city":"Winterthur",
    "sg:orig_category":"Hardwareberatung",
    "sg:phone":"+41 52 232 59 60",
    "sg:postcode":"8400",
    "sg:province":"Z\u00fcrich",
    "wof:name":"Diko Handels Ag",
    "wof:placetype":"venue"
},
  "geometry": {"coordinates":[8.7429742813,47.491481781],"type":"Point"}
}