{
  "type": "Feature",
  "properties": {
    "iso:country":"CH",
    "sg:address":"Kannenb\u00fchlstrasse 23",
    "sg:city":"Hochdorf",
    "sg:orig_category":"Herstellung von Bier",
    "sg:phone":"+41 41 910 18 12",
    "sg:postcode":"6280",
    "sg:province":"Luzern",
    "wof:name":"Seetaler Bier Gmbh",
    "wof:placetype":"venue"
},
  "geometry": {"coordinates":[8.2925701141,47.171749115],"type":"Point"}
}