{
  "type": "Feature",
  "properties": {
    "iso:country":"CH",
    "sg:address":"Grossmatte 21",
    "sg:city":"Littau",
    "sg:orig_category":"Grosshandel mit Eisenwaren sowie Installationsbedarf f\u00fcr Gas, Wasser U Heizung",
    "sg:phone":"+41 31 747 90 10",
    "sg:postcode":"6014",
    "sg:province":"Luzern",
    "wof:name":"Negro Laupen",
    "wof:placetype":"venue"
},
  "geometry": {"coordinates":[7.2389650345,46.9029998779],"type":"Point"}
}