{
  "type": "Feature",
  "properties": {
    "iso:country":"CH",
    "sg:address":"Am D\u00fcrrbach 211",
    "sg:city":"Engelberg",
    "sg:orig_category":"Druckweiterverarbeitung",
    "sg:phone":"+41 61 271 71 84",
    "sg:postcode":"6390",
    "sg:province":"Obwalden",
    "wof:name":"Skivertex Ag",
    "wof:placetype":"venue"
},
  "geometry": {"coordinates":[8.4170598984,46.8185195923],"type":"Point"}
}