{
  "type": "Feature",
  "properties": {
    "iso:country":"CH",
    "sg:address":"Fabrikstrasse 50 8005 Z\u00fcrich. Postfach",
    "sg:city":"Z\u00fcrich",
    "sg:orig_category":"Interessenvertretungen",
    "sg:postcode":"8001",
    "sg:province":"Z\u00fcrich",
    "wof:name":"Paul Schiller-stiftung",
    "wof:placetype":"venue"
},
  "geometry": {"coordinates":[8.525604248,47.3845787048],"type":"Point"}
}