{
  "type": "Feature",
  "properties": {
    "iso:country":"CH",
    "sg:address":"Geretta Via 3 6900 Paradiso. Postfach",
    "sg:city":"Paradiso",
    "sg:orig_category":"Detailhandel mit elektrischen Haushalts-,Radio U Fernsehger\u00e4ten sowie Musikinstrumenten",
    "sg:postcode":"6900",
    "sg:province":"Ticino",
    "wof:name":"Feldmann-koller K. N\u00e4hcenter",
    "wof:placetype":"venue"
},
  "geometry": {"coordinates":[8.9413003922,47.2884101868],"type":"Point"}
}