{
  "type": "Feature",
  "properties": {
    "iso:country":"CH",
    "sg:address":"Favrestock",
    "sg:city":"Walkringen",
    "sg:orig_category":"Architekturb\u00fcros",
    "sg:phone":"+41 31 701 08 81",
    "sg:postcode":"3512",
    "sg:province":"Bern",
    "wof:name":"Manfred Andres Architekturb\u00fcro",
    "wof:placetype":"venue"
},
  "geometry": {"coordinates":[7.617578,46.942455],"type":"Point"}
}