{
  "type": "Feature",
  "properties": {
    "iso:country":"CH",
    "sg:address":"Parkstrasse 1",
    "sg:city":"Bern",
    "sg:orig_category":"Erschliessung von Grundst\u00fccken",
    "sg:postcode":"3014",
    "sg:province":"Bern",
    "wof:name":"Wohnbaugenossenschaft Mushafen",
    "wof:placetype":"venue"
},
  "geometry": {"coordinates":[7.4589061737,46.9590873718],"type":"Point"}
}