{
  "type": "Feature",
  "properties": {
    "iso:country":"CH",
    "sg:address":"Riedl\u00f6ser 7302 Landquart. Postfach 277",
    "sg:city":"Landquart",
    "sg:orig_category":"Detailhandel mit Fleisch U Fleischwaren Fleischverarbeitung",
    "sg:phone":"+41 81 322 72 01",
    "sg:postcode":"7302",
    "sg:province":"Graubunden",
    "wof:name":"Sfw-fleischwaren Ag",
    "wof:placetype":"venue"
},
  "geometry": {"coordinates":[9.5626602173,46.9677810669],"type":"Point"}
}