{
  "type": "Feature",
  "properties": {
    "iso:country":"CH",
    "sg:address":"Rue Du Temple 16",
    "sg:city":"Cartigny",
    "sg:orig_category":"Innenausbau Zimmerei, Dachdeckerei, Bauspenglerei U Abdichtung",
    "sg:phone":"+41 22 756 18 59",
    "sg:postcode":"1236",
    "sg:province":"Gen\u00e8ve",
    "wof:name":"Jaunin Sa",
    "wof:placetype":"venue"
},
  "geometry": {"coordinates":[6.0177030563,46.1746330261],"type":"Point"}
}