{
  "type": "Feature",
  "properties": {
    "iso:country":"CH",
    "sg:address":"Route Du Mandement 540",
    "sg:city":"Dardagny",
    "sg:orig_category":"Rebbau Wein Detailhandel",
    "sg:phone":"+41 21 799 16 93",
    "sg:postcode":"1282",
    "wof:name":"Ren\u00e9 Ponnaz",
    "wof:placetype":"venue"
},
  "geometry": {"coordinates":[-6.1175508499,53.2615394592],"type":"Point"}
}