{
  "type": "Feature",
  "properties": {
    "iso:country":"CH",
    "sg:address":"Lausanne Rue De 116",
    "sg:city":"Sion",
    "sg:orig_category":"RESTAURANTS: TEA-ROOMS",
    "sg:postcode":"1950",
    "sg:province":"Valais",
    "wof:name":"Cisternino-dayen N.",
    "wof:placetype":"venue"
},
  "geometry": {"coordinates":[7.34329319,46.2282714844],"type":"Point"}
}