{
  "type": "Feature",
  "properties": {
    "iso:country":"CH",
    "sg:address":"Piazza Cioccaro 7 6900 Lugano. Postfach",
    "sg:city":"Lugano",
    "sg:orig_category":"Herstellung von sonstigen Nahrungsmitteln",
    "sg:postcode":"6900",
    "sg:province":"Ticino",
    "wof:name":"Di Deluca Sa",
    "wof:placetype":"venue"
},
  "geometry": {"coordinates":[8.9498748779,46.0043830872],"type":"Point"}
}