{
  "type": "Feature",
  "properties": {
    "iso:country":"CH",
    "sg:address":"Zeisigweg 1",
    "sg:city":"D\u00fcbendorf",
    "sg:orig_category":"Grosshandel mit Getr\u00e4nken",
    "sg:postcode":"8600",
    "sg:province":"Z\u00fcrich",
    "wof:name":"Mykonos Geha K. Michos",
    "wof:placetype":"venue"
},
  "geometry": {"coordinates":[8.6117553711,47.3955154419],"type":"Point"}
}