{
  "type": "Feature",
  "properties": {
    "iso:country":"CH",
    "sg:address":"Route De Boudry 22 2016 Cortaillod Case Postale",
    "sg:city":"Cortaillod",
    "sg:orig_category":"Instandhaltung U Reparatur von Automobilen",
    "sg:phone":"+41 55 444 18 10",
    "sg:postcode":"2016",
    "sg:province":"Neuch\u00e2tel",
    "wof:name":"Garage Auer Gmbh",
    "wof:placetype":"venue"
},
  "geometry": {"coordinates":[8.9527902603,47.1751785278],"type":"Point"}
}