{
  "type": "Feature",
  "properties": {
    "addr:full":"Langstrasse 149 Z\u00fcrich Z\u00fcrich 8004",
    "addr:housenumber":"149",
    "addr:postcode":"8004",
    "addr:street":"Langstrasse",
    "iso:country":"CH",
    "sg:address":"Langstrasse 149",
    "sg:city":"Z\u00fcrich",
    "sg:classifiers":[
        {
            "category":"Manufacturing",
            "subcategory":"Printing",
            "type":"Manufacturing & Wholesale Goods"
        }
    ],
    "sg:phone":"+41 12913222",
    "sg:postcode":"8004",
    "sg:province":"Z\u00fcrich",
    "sg:tags":[
        "house",
        "book"
    ],
    "wof:name":"Dps Direct Print Service",
    "wof:placetype":"venue"
},
  "geometry": {"coordinates":[8.527888,47.380367],"type":"Point"}
}