{
  "type": "Feature",
  "properties": {
    "iso:country":"CH",
    "sg:address":"Bergstrasse 4b",
    "sg:city":"Attiswil",
    "sg:orig_category":"Bauingenieurb\u00fcros allgemein",
    "sg:phone":"+41 32 637 18 92",
    "sg:postcode":"4536",
    "sg:province":"Bern",
    "wof:name":"Hansj\u00f6rg Fischer Ingenieurb\u00fcro",
    "wof:placetype":"venue"
},
  "geometry": {"coordinates":[7.612929,47.250973],"type":"Point"}
}