{
  "type": "Feature",
  "properties": {
    "iso:country":"CH",
    "sg:address":"Kreuzgasse",
    "sg:city":"Latterbach",
    "sg:orig_category":"Druck ohne Zeitungsdruck Offsetdruck",
    "sg:phone":"+41 33 681 11 70",
    "sg:postcode":"3758",
    "sg:province":"Bern",
    "wof:name":"Druckerei Gempeler",
    "wof:placetype":"venue"
},
  "geometry": {"coordinates":[7.5780501366,46.6639938354],"type":"Point"}
}