{
  "type": "Feature",
  "properties": {
    "iso:country":"CH",
    "sg:address":"Route De Buchillon 3",
    "sg:city":"St-prex",
    "sg:orig_category":"Oberfl\u00e4chenveredlung U W\u00e4rmebehandlung",
    "sg:phone":"+41 71 761 16 83",
    "sg:postcode":"1162",
    "sg:province":"Vaud",
    "wof:name":"Jh Strahl Und Pulvertechnik Ag",
    "wof:placetype":"venue"
},
  "geometry": {"coordinates":[9.5626440048,47.3216362],"type":"Point"}
}