{
  "type": "Feature",
  "properties": {
    "iso:country":"CH",
    "sg:address":"Korneliusstrasse 1 8008 Z\u00fcrich. Postfach",
    "sg:city":"Z\u00fcrich",
    "sg:orig_category":"Handelsvermittlung von Textilien, Bekleidung, Schuhen U Lederwaren",
    "sg:postcode":"8001",
    "sg:province":"Z\u00fcrich",
    "wof:name":"Cepperulo Lucio Textilien; Vertretung",
    "wof:placetype":"venue"
},
  "geometry": {"coordinates":[8.554889679,47.3553695679],"type":"Point"}
}