{
  "type": "Feature",
  "properties": {
    "iso:country":"CH",
    "sg:address":"Weiherweg 3",
    "sg:city":"Oberwil",
    "sg:classifiers":[
        {
            "category":"Professional",
            "subcategory":"Computer Services",
            "type":"Services"
        }
    ],
    "sg:phone":"+41 61 406 95 50",
    "sg:postcode":"4104",
    "sg:province":"Basel-Landschaft",
    "sg:tags":[
        "administration",
        "software"
    ],
    "wof:name":"Panchaud Edv-beratung",
    "wof:placetype":"venue"
},
  "geometry": {"coordinates":[7.55884,47.513706],"type":"Point"}
}