{
  "type": "Feature",
  "properties": {
    "iso:country":"CH",
    "sg:address":"Hus\u00e4cherstrasse 2 8907 Wettswil. Postfach",
    "sg:city":"Wettswil",
    "sg:orig_category":"Nationale Postdienste",
    "sg:phone":"+41 61 731 10 53",
    "sg:postcode":"8907",
    "sg:province":"Z\u00fcrich",
    "wof:name":"Die Schweizerische Post",
    "wof:placetype":"venue"
},
  "geometry": {"coordinates":[7.5131268501,47.475112915],"type":"Point"}
}