{
  "type": "Feature",
  "properties": {
    "iso:country":"CH",
    "sg:address":"Hammerallee 25 4600 Olten. Postfach",
    "sg:city":"Olten",
    "sg:orig_category":"RESTAURANTS: TEA-ROOMS",
    "sg:phone":"+41 62 212 60 04",
    "sg:postcode":"4603",
    "sg:province":"Solothurn",
    "wof:name":"Pizzeria G\u00e4ubahn, Von Rohr Bruno",
    "wof:placetype":"venue"
},
  "geometry": {"coordinates":[7.8982601166,47.3488082886],"type":"Point"}
}