{
  "type": "Feature",
  "properties": {
    "iso:country":"CH",
    "sg:address":"Niederholzstrasse 5",
    "sg:city":"Fahrweid",
    "sg:orig_category":"Herstellung von Werkzeugen Mechanische Werkst\u00e4tten",
    "sg:phone":"+41 17482131",
    "sg:postcode":"8951",
    "sg:province":"Z\u00fcrich",
    "wof:name":"Alfred Strohmeier Werkzeugbau",
    "wof:placetype":"venue"
},
  "geometry": {"coordinates":[8.4122209549,47.4075088501],"type":"Point"}
}