{
  "type": "Feature",
  "properties": {
    "iso:country":"CH",
    "sg:address":"Pont Rue Du 6d",
    "sg:city":"St-imier",
    "sg:orig_category":"Saunas, Solarien, Fitnesszentren U \u00e4hnliches",
    "sg:phone":"+41 32 941 48 28",
    "sg:postcode":"2610",
    "sg:province":"Bern",
    "wof:name":"Swisspool Balneo Sa",
    "wof:placetype":"venue"
},
  "geometry": {"coordinates":[6.9958171844,47.1520423889],"type":"Point"}
}