{
  "type": "Feature",
  "properties": {
    "iso:country":"CH",
    "sg:address":"1015",
    "sg:city":"Lausanne",
    "sg:orig_category":"Studenten Organisationen",
    "sg:postcode":"1015",
    "sg:province":"Vaud",
    "wof:name":"Assoc.amicale Anciens \u00e9l\u00e8ves Ecole D'ing\u00e9nieurs Universit\u00e9",
    "wof:placetype":"venue"
},
  "geometry": {"coordinates":[6.5793399811,46.520160675],"type":"Point"}
}