{
  "type": "Feature",
  "properties": {
    "iso:country":"CH",
    "sg:address":"Br\u00fcckreutiweg 108",
    "sg:city":"M\u00fcnsingen",
    "sg:classifiers":[
        {
            "category":"Insurance",
            "subcategory":"Insurance Agent",
            "type":"Services"
        }
    ],
    "sg:phone":"+41 17152973",
    "sg:postcode":"3110",
    "sg:province":"Bern",
    "sg:tags":[
        "versicherungsagenturen",
        "-broker"
    ],
    "wof:name":"Thomas A. Osterwalder Z\u00fcrich Versicherungen",
    "wof:placetype":"venue"
},
  "geometry": {"coordinates":[8.5489320755,47.3246574402],"type":"Point"}
}