{
  "type": "Feature",
  "properties": {
    "iso:country":"CH",
    "sg:address":"Avenue Des Epineys 10",
    "sg:city":"Martigny",
    "sg:orig_category":"Geb\u00e4ude, Wohnungsreinigung Reinigungsgewerbe",
    "sg:phone":"+41 27 722 00 64",
    "sg:postcode":"1920",
    "sg:province":"Valais",
    "wof:name":"Dany Payot Entreprise De Nettoyages",
    "wof:placetype":"venue"
},
  "geometry": {"coordinates":[7.066947937,46.0977363586],"type":"Point"}
}