{
  "type": "Feature",
  "properties": {
    "iso:country":"CH",
    "sg:address":"Stampfenbachstrasse 109",
    "sg:city":"Z\u00fcrich",
    "sg:orig_category":"Herstellung von Pumpen U Kompressoren",
    "sg:phone":"+41 71 923 30 77",
    "sg:postcode":"8006",
    "sg:province":"Z\u00fcrich",
    "wof:name":"Bwu Betonpumpen Ag Wil",
    "wof:placetype":"venue"
},
  "geometry": {"coordinates":[9.0398225784,47.4596862793],"type":"Point"}
}