{
  "type": "Feature",
  "properties": {
    "iso:country":"CH",
    "sg:address":"Via Motta 10 6830 Chiasso Casella Postale 1672",
    "sg:city":"Chiasso",
    "sg:orig_category":"Herstellung von industriellen Prozesssteuerungsanlagen Herstellung von sonstigen elektrischen Ausr\u00fcs",
    "sg:phone":"+41 91 682 20 30",
    "sg:postcode":"6830",
    "sg:province":"Ticino",
    "wof:name":"Banking Automation System Sa",
    "wof:placetype":"venue"
},
  "geometry": {"coordinates":[9.0313053131,45.8347244263],"type":"Point"}
}