{
  "type": "Feature",
  "properties": {
    "iso:country":"CH",
    "sg:address":"Schwalbenstrasse 9",
    "sg:city":"Dussnang",
    "sg:orig_category":"Installation von Heizungs, L\u00fcftungs U Klimaanlagen Sanit\u00e4r U Heizungsinstallation",
    "sg:phone":"+41 71 977 21 31",
    "sg:postcode":"8374",
    "sg:province":"Thurgau",
    "wof:name":"Adolf B\u00fcchi Heizung L\u00fcftung Klima",
    "wof:placetype":"venue"
},
  "geometry": {"coordinates":[8.9611244202,47.430316925],"type":"Point"}
}