{
  "type": "Feature",
  "properties": {
    "iso:country":"CH",
    "sg:address":"Hagweg 22",
    "sg:city":"Z\u00e4ziwil",
    "sg:orig_category":"Sonstige mit Sport verbundene T\u00e4tigkeiten",
    "sg:postcode":"3532",
    "sg:province":"Bern",
    "wof:name":"Budo Zentrum Hara St. Gallen, Kelmendi Naim",
    "wof:placetype":"venue"
},
  "geometry": {"coordinates":[9.3859615326,47.4351768494],"type":"Point"}
}