{
  "type": "Feature",
  "properties": {
    "iso:country":"CH",
    "sg:address":"Chemin De Verney 21",
    "sg:city":"Pully",
    "sg:orig_category":"Wirtschaftspr\u00fcfung, Steuerberatung U Treuhand",
    "sg:phone":"+41 21 728 65 58",
    "sg:postcode":"1009",
    "sg:province":"Vaud",
    "wof:name":"Sideral Finance Sa",
    "wof:placetype":"venue"
},
  "geometry": {"coordinates":[6.6507878304,46.5067977905],"type":"Point"}
}