{
  "type": "Feature",
  "properties": {
    "iso:country":"CH",
    "sg:address":"Igelweidstrasse 3",
    "sg:city":"H\u00e4gglingen",
    "sg:orig_category":"Druck ohne Zeitungsdruck Verlagsgewerbe",
    "sg:phone":"+41 56 610 19 19",
    "sg:postcode":"5607",
    "sg:province":"Aargau",
    "wof:name":"Frey. Kurt Ag",
    "wof:placetype":"venue"
},
  "geometry": {"coordinates":[8.2495746613,47.3973999023],"type":"Point"}
}