{
  "type": "Feature",
  "properties": {
    "iso:country":"CH",
    "sg:address":"Mettlenwaldweg 18 E",
    "sg:city":"Herrenschwanden",
    "sg:orig_category":"Architektur U Ingenieurb\u00fcros",
    "sg:postcode":"3037",
    "sg:province":"Bern",
    "wof:name":"Ruch & Partner Gmbh",
    "wof:placetype":"venue"
},
  "geometry": {"coordinates":[7.41809,46.978031],"type":"Point"}
}