{
  "type": "Feature",
  "properties": {
    "iso:country":"CH",
    "sg:address":"6713",
    "sg:city":"Malvaglia",
    "sg:orig_category":"G\u00fcterbef\u00f6rderung im Strassenverkehr",
    "sg:phone":"+41 32 924 24 24",
    "sg:postcode":"6713",
    "sg:province":"Ticino",
    "wof:name":"Trn Sa",
    "wof:placetype":"venue"
},
  "geometry": {"coordinates":[6.8013339043,47.0817146301],"type":"Point"}
}