{
  "type": "Feature",
  "properties": {
    "iso:country":"CH",
    "sg:address":"Rue Peillonnex 39 1225 Ch\u00eane-bourg. Postfach",
    "sg:city":"Gen\u00e8ve",
    "sg:orig_category":"Softwareentwicklung U beratung Sonstige mit der Informatik verbundene T\u00e4tigkeiten",
    "sg:phone":"+41 22 860 26 74",
    "sg:postcode":"1205",
    "sg:province":"Gen\u00e8ve",
    "wof:name":"Kalyss Sa Informatique Etc.; Prestations, Service, Conseils, Exploit., Commerce, Consulting",
    "wof:placetype":"venue"
},
  "geometry": {"coordinates":[6.1988129616,46.1953926086],"type":"Point"}
}