{
  "type": "Feature",
  "properties": {
    "iso:country":"CH",
    "sg:address":"Kirchweg",
    "sg:city":"Steinach",
    "sg:orig_category":"Vorschulen, Kinderg\u00e4rten",
    "sg:phone":"+41 71 411 57 93",
    "sg:postcode":"9323",
    "sg:province":"St. Gallen",
    "wof:name":"Kindergarten I & Ii",
    "wof:placetype":"venue"
},
  "geometry": {"coordinates":[9.4393777847,47.5026664734],"type":"Point"}
}