{
  "type": "Feature",
  "properties": {
    "iso:country":"CH",
    "sg:address":"Via S.bernardino 6532 Castione Casella Postale",
    "sg:city":"Bellinzona",
    "sg:orig_category":"D\u00e4mmung gegen K\u00e4lte, W\u00e4rme, Schall U Ersch\u00fctterung Grosshandel mit Holz U Baustoffen",
    "sg:phone":"+41 17601300",
    "sg:postcode":"6500",
    "sg:province":"Ticino",
    "wof:name":"Lindner Ag Decken, Boden, Trennwandsysteme, Arnstorf, Zweignieder- Lassung Affoltern Am Albis",
    "wof:placetype":"venue"
},
  "geometry": {"coordinates":[8.4511070251,47.2804031372],"type":"Point"}
}