{
  "type": "Feature",
  "properties": {
    "iso:country":"CH",
    "sg:address":"Cond.monte Verde",
    "sg:city":"Brissago",
    "sg:orig_category":"S\u00e4gewerke",
    "sg:phone":"+41 79 664 88 38",
    "sg:postcode":"6614",
    "sg:province":"Ticino",
    "wof:name":"Ernst Schilliger Ag Segheria",
    "wof:placetype":"venue"
},
  "geometry": {"coordinates":[8.7102975845,46.118976593],"type":"Point"}
}