{
  "type": "Feature",
  "properties": {
    "iso:country":"CH",
    "sg:address":"Bovel",
    "sg:city":"Maienfeld",
    "sg:orig_category":"G\u00fcterbef\u00f6rderung im Strassenverkehr",
    "sg:phone":"+41 81 302 30 22",
    "sg:postcode":"7304",
    "sg:province":"Graubunden",
    "wof:name":"Tanner Transporte Gmbh",
    "wof:placetype":"venue"
},
  "geometry": {"coordinates":[9.5439252853,47.0166893005],"type":"Point"}
}