{
  "type": "Feature",
  "properties": {
    "iso:country":"CH",
    "sg:address":"Fl\u00fcelistrasse",
    "sg:city":"Sarnen",
    "sg:orig_category":"Sportvereine Sch\u00fctzen",
    "sg:phone":"+41 41 660 17 62",
    "sg:postcode":"6060",
    "sg:province":"Obwalden",
    "wof:name":"Sch\u00fctzengesellschaft Sarnen Sch\u00fctzenhaus Riedli",
    "wof:placetype":"venue"
},
  "geometry": {"coordinates":[8.2500801086,46.8909187317],"type":"Point"}
}