{
  "type": "Feature",
  "properties": {
    "iso:country":"CH",
    "sg:address":"Im Chaltacher 9",
    "sg:city":"Steinmaur",
    "sg:orig_category":"Detailhandel mit Teppichen Verlegen von Fussboden",
    "sg:phone":"+41 18533941",
    "sg:postcode":"8162",
    "sg:province":"Z\u00fcrich",
    "wof:name":"Peter Locher Teppichladen",
    "wof:placetype":"venue"
},
  "geometry": {"coordinates":[8.4502401352,47.4946861267],"type":"Point"}
}