{
  "type": "Feature",
  "properties": {
    "iso:country":"CH",
    "sg:address":"Schnetzletb\u00fchlstrasse 14",
    "sg:city":"Hinwil",
    "sg:orig_category":"Sportvereine Minigolf",
    "sg:phone":"+41 19371315",
    "sg:postcode":"8340",
    "sg:province":"Z\u00fcrich",
    "wof:name":"Mc Wetzikon",
    "wof:placetype":"venue"
},
  "geometry": {"coordinates":[8.8369379044,47.3054847717],"type":"Point"}
}