{
  "type": "Feature",
  "properties": {
    "iso:country":"CH",
    "sg:address":"Obere Windegg",
    "sg:city":"Sch\u00e4nis",
    "sg:orig_category":"Herstellung von Werkzeugen Mechanische Werkst\u00e4tten",
    "sg:phone":"+41 79 285 62 03",
    "sg:postcode":"8718",
    "sg:province":"St. Gallen",
    "wof:name":"Atrena Ag Pr\u00e4zisions-& Werkzeugbau",
    "wof:placetype":"venue"
},
  "geometry": {"coordinates":[9.0544061661,47.1395225525],"type":"Point"}
}