{
  "type": "Feature",
  "properties": {
    "iso:country":"CH",
    "sg:address":"3943",
    "sg:city":"Eischoll",
    "sg:classifiers":[
        {
            "category":"Insurance",
            "subcategory":"Insurance Agent",
            "type":"Services"
        }
    ],
    "sg:phone":"+41 27 934 13 50",
    "sg:postcode":"3943",
    "sg:province":"Valais",
    "sg:tags":[
        "versicherungsagenturen",
        "-broker"
    ],
    "wof:name":"Alfred Bayard Versicherungen",
    "wof:placetype":"venue"
},
  "geometry": {"coordinates":[7.7804951668,46.2933311462],"type":"Point"}
}