{
  "type": "Feature",
  "properties": {
    "iso:country":"CH",
    "sg:address":"Alte Landstrasse 33 8912 Obfelden. Postfach",
    "sg:city":"Obfelden",
    "sg:orig_category":"Aktivit\u00e4ten der Krankenschwestern U Hebammen, Hauspflege Organisationen des Gesundheitswesen",
    "sg:phone":"+41 17600671",
    "sg:postcode":"8912",
    "sg:province":"Z\u00fcrich",
    "wof:name":"Spitex Gemeindekrankenpflege",
    "wof:placetype":"venue"
},
  "geometry": {"coordinates":[8.429793,47.266304],"type":"Point"}
}