{
  "type": "Feature",
  "properties": {
    "iso:country":"CH",
    "sg:address":"Zwidellen 3",
    "sg:city":"Frick",
    "sg:orig_category":"Arztpraxen",
    "sg:phone":"+41 62 865 70 00",
    "sg:postcode":"5070",
    "sg:province":"Aargau",
    "wof:name":"Dr.med.manuel Simonett Spezialarzt Fmh",
    "wof:placetype":"venue"
},
  "geometry": {"coordinates":[8.020129,47.507332],"type":"Point"}
}