{
  "type": "Feature",
  "properties": {
    "iso:country":"CH",
    "sg:address":"Les Uttins",
    "sg:city":"Ch\u00e9serex",
    "sg:orig_category":"Sonstige mit der Informatik verbundene T\u00e4tigkeiten",
    "sg:postcode":"1275",
    "sg:province":"Vaud",
    "wof:name":"Rb Consulting B\u00fcchi Roger",
    "wof:placetype":"venue"
},
  "geometry": {"coordinates":[9.3191003799,47.4219245911],"type":"Point"}
}