{
  "type": "Feature",
  "properties": {
    "addr:full":"Binningerstrasse 84 Allschwil Basel-Landschaft 4123",
    "addr:housenumber":"84",
    "addr:postcode":"4123",
    "addr:street":"Binningerstrasse",
    "iso:country":"CH",
    "sg:address":"Binningerstrasse 84",
    "sg:city":"Allschwil",
    "sg:classifiers":[
        {
            "category":"Banks & Credit Unions",
            "subcategory":"Investment Brokerage",
            "type":"Services"
        }
    ],
    "sg:phone":"+41 61 487 44 11",
    "sg:postcode":"4123",
    "sg:province":"Basel-Landschaft",
    "sg:tags":[
        "axial",
        "fan"
    ],
    "wof:name":"Meidinger Ag",
    "wof:placetype":"venue"
},
  "geometry": {"coordinates":[7.547152,47.547684],"type":"Point"}
}