{
  "type": "Feature",
  "properties": {
    "iso:country":"CH",
    "sg:address":"Schwarzackerstrasse 2 8304 Wallisellen. Postfach",
    "sg:city":"Wallisellen",
    "sg:orig_category":"Erwachsenenbildung U Unterricht",
    "sg:phone":"+41 18832575",
    "sg:postcode":"8304",
    "sg:province":"Z\u00fcrich",
    "wof:name":"Linguaplus, Die Andere Sprachschule Von Stalder Hannelore Sprachschule",
    "wof:placetype":"venue"
},
  "geometry": {"coordinates":[8.5918951035,47.4130096436],"type":"Point"}
}