{
  "type": "Feature",
  "properties": {
    "iso:country":"CH",
    "sg:address":"1700 Fribourg. Postfach",
    "sg:city":"Fribourg",
    "sg:orig_category":"Interessenvertretungen Universit\u00e4tsspit\u00e4ler, Spit\u00e4ler f\u00fcr allgemeine Pflege",
    "sg:phone":"+41 26 426 81 80",
    "sg:postcode":"1708",
    "sg:province":"Fribourg",
    "wof:name":"Fondation Pour L'am\u00e9nagement Artistique De L'h\u00f4pital Cantonal",
    "wof:placetype":"venue"
},
  "geometry": {"coordinates":[7.1746201515,46.8062400818],"type":"Point"}
}