{
  "type": "Feature",
  "properties": {
    "iso:country":"CH",
    "sg:address":"Gourgas Rue 1 1205 Gen\u00e8ve. Postfach",
    "sg:city":"Gen\u00e8ve",
    "sg:orig_category":"Interessenvertretungen",
    "sg:phone":"+41 22 807 17 92",
    "sg:postcode":"1201",
    "sg:province":"Gen\u00e8ve",
    "wof:name":"Association Arpege",
    "wof:placetype":"venue"
},
  "geometry": {"coordinates":[6.1390881538,46.1990852356],"type":"Point"}
}