{
  "type": "Feature",
  "properties": {
    "iso:country":"CH",
    "sg:address":"Strandbadweg 5",
    "sg:city":"Uster",
    "sg:orig_category":"Einbau von Schreinerwaren",
    "sg:phone":"+41 19406687",
    "sg:postcode":"8610",
    "sg:province":"Z\u00fcrich",
    "wof:name":"Robert Spichiger System-trennw\u00e4nde Baumontagen",
    "wof:placetype":"venue"
},
  "geometry": {"coordinates":[8.6967353821,47.344707489],"type":"Point"}
}