{
  "type": "Feature",
  "properties": {
    "iso:country":"CH",
    "sg:address":"Ziegelgasse 12",
    "sg:city":"Frutigen",
    "sg:classifiers":[
        {
            "category":"Manufacturing",
            "subcategory":"Rubber & Plastics",
            "type":"Manufacturing & Wholesale Goods"
        }
    ],
    "sg:phone":"+41 33 671 53 61",
    "sg:postcode":"3714",
    "sg:province":"Bern",
    "sg:tags":[
        "insulated",
        "piping"
    ],
    "wof:name":"Scherz Handels- Und Verkaufs-gmbh",
    "wof:placetype":"venue"
},
  "geometry": {"coordinates":[7.6467108727,46.590549469],"type":"Point"}
}