{
  "type": "Feature",
  "properties": {
    "iso:country":"CH",
    "sg:address":"Via Al Campanile 9 6962 Viganello. Postfach",
    "sg:city":"Viganello",
    "sg:orig_category":"Unclassifiable Establishments",
    "sg:postcode":"6962",
    "sg:province":"Ticino",
    "wof:name":"Pereira & Delmenico Sagl",
    "wof:placetype":"venue"
},
  "geometry": {"coordinates":[8.9731826782,46.0161094666],"type":"Point"}
}