{
  "type": "Feature",
  "properties": {
    "iso:country":"CH",
    "sg:address":"Mellingerstrasse 126",
    "sg:city":"Baden",
    "sg:orig_category":"Arztpraxen",
    "sg:phone":"+41 56 222 18 44",
    "sg:postcode":"5400",
    "sg:province":"Aargau",
    "wof:name":"Dr.med.frank Rossier Arzt F.allgemeine Medizin Fmh",
    "wof:placetype":"venue"
},
  "geometry": {"coordinates":[8.295362,47.46806],"type":"Point"}
}