{
  "type": "Feature",
  "properties": {
    "iso:country":"CH",
    "sg:address":"Rainacher 1",
    "sg:city":"Egolzwil",
    "sg:orig_category":"Massagestudios",
    "sg:phone":"+41 55 240 76 02",
    "sg:postcode":"6243",
    "sg:province":"Luzern",
    "wof:name":"Lisbeth Landolt Massagen",
    "wof:placetype":"venue"
},
  "geometry": {"coordinates":[8.8403205872,47.2534561157],"type":"Point"}
}