{
  "type": "Feature",
  "properties": {
    "iso:country":"CH",
    "sg:address":"Steinackerstrasse 36 8902 Urdorf. Postfach",
    "sg:city":"Urdorf",
    "sg:orig_category":"Grosshandel mit elektrischen Haushaltsger\u00e4ten, Radio U Fernsehger\u00e4ten Herstellung von sonstigen elek",
    "sg:phone":"+41 19409955",
    "sg:postcode":"8902",
    "sg:province":"Z\u00fcrich",
    "wof:name":"Gloor Instruments Ag",
    "wof:placetype":"venue"
},
  "geometry": {"coordinates":[8.7188453674,47.3458824158],"type":"Point"}
}