{
  "type": "Feature",
  "properties": {
    "iso:country":"CH",
    "sg:address":"Mont-blanc Rue Du 4 1201 Gen\u00e8ve. Postfach",
    "sg:city":"Gen\u00e8ve",
    "sg:orig_category":"Unclassifiable Establishments",
    "sg:phone":"+41 91 826 27 01",
    "sg:postcode":"1201",
    "sg:province":"Gen\u00e8ve",
    "wof:name":"Adhesive Service Sa",
    "wof:placetype":"venue"
},
  "geometry": {"coordinates":[8.9789562225,46.1534881592],"type":"Point"}
}