{
  "type": "Feature",
  "properties": {
    "addr:full":"Pumpwerkstrasse 25 Regensdorf Z\u00fcrich 8105",
    "addr:housenumber":"25",
    "addr:postcode":"8105",
    "addr:street":"Pumpwerkstrasse",
    "iso:country":"CH",
    "sg:address":"Pumpwerkstrasse 25",
    "sg:city":"Regensdorf",
    "sg:orig_category":"Autogaragen",
    "sg:phone":"+41 18406815",
    "sg:postcode":"8105",
    "sg:province":"Z\u00fcrich",
    "wof:name":"Garage Ueli F\u00e4h Garage",
    "wof:placetype":"venue"
},
  "geometry": {"coordinates":[8.459602,47.444485],"type":"Point"}
}