{
  "type": "Feature",
  "properties": {
    "iso:country":"CH",
    "sg:address":"4448",
    "sg:city":"L\u00e4ufelfingen",
    "sg:orig_category":"Vereine Musik/Blasmusik",
    "sg:postcode":"4448",
    "sg:province":"Basel-Landschaft",
    "wof:name":"Musikgesellschaft",
    "wof:placetype":"venue"
},
  "geometry": {"coordinates":[7.8551549911,47.3954811096],"type":"Point"}
}