{
  "type": "Feature",
  "properties": {
    "iso:country":"CH",
    "sg:address":"Landstrasse 74",
    "sg:city":"Wettingen",
    "sg:orig_category":"Physiotherapie",
    "sg:phone":"+41 56 427 06 03",
    "sg:postcode":"5430",
    "sg:province":"Aargau",
    "wof:name":"C. Carnier & G. Itin Physiotherapie",
    "wof:placetype":"venue"
},
  "geometry": {"coordinates":[8.3237409592,47.4670295715],"type":"Point"}
}