{
  "type": "Feature",
  "properties": {
    "iso:country":"CH",
    "sg:address":"Bahnhofstrasse",
    "sg:city":"Zermatt",
    "sg:orig_category":"Unclassifiable Establishments",
    "sg:postcode":"3920",
    "sg:province":"Valais",
    "wof:name":"Frifina Sa.",
    "wof:placetype":"venue"
},
  "geometry": {"coordinates":[7.746240139,46.0201454163],"type":"Point"}
}