{
  "type": "Feature",
  "properties": {
    "addr:full":"Lettenstrasse 8 Rotkreuz Zug 6343",
    "addr:housenumber":"8",
    "addr:postcode":"6343",
    "addr:street":"Lettenstrasse;Zug",
    "iso:country":"CH",
    "sg:address":"Lettenstrasse 8",
    "sg:city":"Rotkreuz",
    "sg:classifiers":[
        {
            "category":"Government",
            "subcategory":"Post Office",
            "type":"Public Place"
        }
    ],
    "sg:phone":"+41 41 790 56 35",
    "sg:postcode":"6343",
    "sg:province":"Zug",
    "sg:tags":[
        "component",
        "assembly",
        "standardized",
        "prefabricated"
    ],
    "wof:name":"De Meeuw Kombi-raumsysteme Ag",
    "wof:placetype":"venue"
},
  "geometry": {"coordinates":[8.43143,47.147682],"type":"Point"}
}