{
  "type": "Feature",
  "properties": {
    "iso:country":"CH",
    "sg:address":"Burggasse 17",
    "sg:city":"Biel/bienne",
    "sg:classifiers":[
        {
            "category":"Restaurant",
            "type":"Food & Drink"
        }
    ],
    "sg:phone":"+41 32 323 50 44",
    "sg:postcode":"2502",
    "sg:province":"Bern",
    "wof:name":"Restaurant La Traviata",
    "wof:placetype":"venue"
},
  "geometry": {"coordinates":[7.2452039719,47.1410903931],"type":"Point"}
}