{
  "type": "Feature",
  "properties": {
    "iso:country":"CH",
    "sg:address":"Allmendweg Rickenbach",
    "sg:city":"Merenschwand",
    "sg:orig_category":"Allgemeiner Hoch U Tiefbau",
    "sg:phone":"+41 56 664 31 28",
    "sg:postcode":"5634",
    "sg:province":"Aargau",
    "wof:name":"K. Niederberger",
    "wof:placetype":"venue"
},
  "geometry": {"coordinates":[8.372106,47.260845],"type":"Point"}
}