{
  "type": "Feature",
  "properties": {
    "iso:country":"CH",
    "sg:address":"Efringerstrasse 5 4000 Basel. Postfach",
    "sg:city":"Basel",
    "sg:orig_category":"Herstellung von Radio U Fernsehger\u00e4ten sowie phono U videotechnischen Ger\u00e4ten",
    "sg:postcode":"4051",
    "sg:province":"Basel-Stadt",
    "wof:name":"Ferlisi",
    "wof:placetype":"venue"
},
  "geometry": {"coordinates":[7.5962557793,47.5675048828],"type":"Point"}
}