{
  "type": "Feature",
  "properties": {
    "iso:country":"CH",
    "sg:address":"Rue Maison De Commune 23",
    "sg:city":"Fully",
    "sg:orig_category":"Detailhandel mit Bekleidung",
    "sg:phone":"+41 27 746 46 16",
    "sg:postcode":"1926",
    "sg:province":"Valais",
    "wof:name":"Giorgio Morandin Y & G Lingerie",
    "wof:placetype":"venue"
},
  "geometry": {"coordinates":[7.114708,46.138481],"type":"Point"}
}