{
  "type": "Feature",
  "properties": {
    "iso:country":"CH",
    "sg:address":"Zugerstrasse 73",
    "sg:city":"Arth",
    "sg:orig_category":"Schiffs U Bootsbau",
    "sg:phone":"+41 41 855 31 36",
    "sg:postcode":"6415",
    "sg:province":"Schwyz",
    "wof:name":"Roger Kr\u00e4henb\u00fchl Bootswerft Aazopf",
    "wof:placetype":"venue"
},
  "geometry": {"coordinates":[8.5257396698,47.0680580139],"type":"Point"}
}