{
  "type": "Feature",
  "properties": {
    "iso:country":"CH",
    "sg:address":"Rue Des Granges",
    "sg:city":"Riddes",
    "sg:orig_category":"Rebbau",
    "sg:phone":"+41 27 306 46 60",
    "sg:postcode":"1908",
    "sg:province":"Valais",
    "wof:name":"Christophe Laurenti Cave Des Ponts",
    "wof:placetype":"venue"
},
  "geometry": {"coordinates":[7.2218251228,46.1727600098],"type":"Point"}
}