{
  "type": "Feature",
  "properties": {
    "iso:country":"CH",
    "sg:address":"Kornhausplatz 7",
    "sg:city":"Bern",
    "sg:orig_category":"Chemische Reinigung Detailhandel mit Waren verschiedener Art, Hauptrichtung Nahrungsmittel",
    "sg:phone":"+41 26 652 27 37",
    "sg:postcode":"3011",
    "sg:province":"Bern",
    "wof:name":"Pressing De Romont S. \u00e0 R.l.",
    "wof:placetype":"venue"
},
  "geometry": {"coordinates":[6.919873,46.696556],"type":"Point"}
}