{
  "type": "Feature",
  "properties": {
    "iso:country":"CH",
    "sg:address":"R\u00e4mistr. 23",
    "sg:city":"Z\u00fcrich",
    "sg:classifiers":[
        {
            "category":"Banks & Credit Unions",
            "subcategory":"Bank",
            "type":"Services"
        }
    ],
    "sg:phone":"+41 12686161",
    "sg:postcode":"8001",
    "sg:province":"Z\u00fcrich",
    "wof:name":"Gewerbebank Z\u00fcrich",
    "wof:placetype":"venue"
},
  "geometry": {"coordinates":[8.546926,47.368446],"type":"Point"}
}