{
  "type": "Feature",
  "properties": {
    "iso:country":"CH",
    "sg:address":"Alpenstrasse 10",
    "sg:city":"Luzern",
    "sg:orig_category":"Detailhandel Fachdetailhandel in Verkaufsr\u00e4umen Reparatur von Gebrauchsg\u00fctern",
    "sg:phone":"+41 52 234 06 66",
    "sg:postcode":"6004",
    "sg:province":"Luzern",
    "wof:name":"Beate Uhse Erotik-megastore",
    "wof:placetype":"venue"
},
  "geometry": {"coordinates":[8.3107995987,47.0557670593],"type":"Point"}
}