{
  "type": "Feature",
  "properties": {
    "iso:country":"CH",
    "sg:address":"Hauptstrasse 80",
    "sg:city":"Sissach",
    "sg:orig_category":"Drogerien",
    "sg:phone":"+41 61 971 10 59",
    "sg:postcode":"4450",
    "sg:province":"Basel-Landschaft",
    "wof:name":"Drogerie Martin",
    "wof:placetype":"venue"
},
  "geometry": {"coordinates":[7.8106188774,47.4644470215],"type":"Point"}
}