{
  "type": "Feature",
  "properties": {
    "iso:country":"CH",
    "sg:address":"Metzgergasse 2 3400 Burgdorf. Postfach",
    "sg:city":"Burgdorf",
    "sg:orig_category":"Grosshandel mit sonstigen Gebrauchs U Verbrauchsg\u00fctern",
    "sg:phone":"+41 34 422 27 67",
    "sg:postcode":"3400",
    "sg:province":"Bern",
    "wof:name":"Messerli Werbe- & Printshop",
    "wof:placetype":"venue"
},
  "geometry": {"coordinates":[7.6279139519,47.0578041077],"type":"Point"}
}