{
  "type": "Feature",
  "properties": {
    "iso:country":"CH",
    "sg:address":"2514",
    "sg:city":"Ligerz",
    "sg:orig_category":"Sportvereine Sch\u00fctzen",
    "sg:phone":"+41 31 791 38 28",
    "sg:postcode":"2514",
    "sg:province":"Bern",
    "wof:name":"Feldsch\u00fctzengesellschaft",
    "wof:placetype":"venue"
},
  "geometry": {"coordinates":[7.1352510452,47.0840110779],"type":"Point"}
}