{
  "type": "Feature",
  "properties": {
    "iso:country":"CH",
    "sg:address":"Steinacher",
    "sg:city":"Pfaffnau",
    "sg:orig_category":"Herstellung von sonstigen landwirtschaftlichen Maschinen Schmieden",
    "sg:phone":"+41 79 410 36 43",
    "sg:postcode":"6264",
    "sg:province":"Luzern",
    "wof:name":"Walter Ruckstuhl Mech.schmiede Landmaschinen",
    "wof:placetype":"venue"
},
  "geometry": {"coordinates":[7.8928799629,47.2241096497],"type":"Point"}
}