{
  "type": "Feature",
  "properties": {
    "iso:country":"CH",
    "sg:address":"S\u00e4gestrasse 73 3098 K\u00f6niz. Postfach",
    "sg:city":"K\u00f6niz",
    "sg:orig_category":"Grosshandel mit Geschenkartikeln U Souvenirs Herstellung von Kunststoffwaren",
    "sg:phone":"+41 31 972 16 66",
    "sg:postcode":"3098",
    "sg:province":"Bern",
    "wof:name":"Frelaplast Ag Kunststoff, B\u00fcro- U. Werbeartikel; Herstellung, Handel Usw.",
    "wof:placetype":"venue"
},
  "geometry": {"coordinates":[7.4135332108,46.9247245789],"type":"Point"}
}