{
  "type": "Feature",
  "properties": {
    "iso:country":"CH",
    "sg:address":"Grub 773 9052 Niederteufen. Postfach",
    "sg:city":"Niederteufen",
    "sg:orig_category":"Sanit\u00e4r, Heizungs U L\u00fcftungsinstallation",
    "sg:phone":"+41 41 497 28 23",
    "sg:postcode":"9052",
    "sg:province":"Appenzell Ausserrhoden",
    "wof:name":"Nussbaum Peter",
    "wof:placetype":"venue"
},
  "geometry": {"coordinates":[8.1827249527,47.0368156433],"type":"Point"}
}