{
  "type": "Feature",
  "properties": {
    "iso:country":"CH",
    "sg:address":"Unterweg 18e",
    "sg:city":"B\u00fclach",
    "sg:orig_category":"Softwareentwicklung U beratung",
    "sg:phone":"+41 18863080",
    "sg:postcode":"8180",
    "sg:province":"Z\u00fcrich",
    "wof:name":"Resulting Services Gmbh",
    "wof:placetype":"venue"
},
  "geometry": {"coordinates":[8.5427894592,47.5228424072],"type":"Point"}
}