{
  "type": "Feature",
  "properties": {
    "iso:country":"CH",
    "sg:address":"Gewerbestrasse 3",
    "sg:city":"Subingen",
    "sg:classifiers":[
        {
            "category":"Manufacturing",
            "subcategory":"Motor Vehicles & Parts",
            "type":"Manufacturing & Wholesale Goods"
        }
    ],
    "sg:phone":"+41 32 613 33 33",
    "sg:postcode":"4553",
    "sg:province":"Solothurn",
    "sg:tags":[
        "wheel",
        "wheel-sets"
    ],
    "wof:name":"Gebr. Schaad Ag",
    "wof:placetype":"venue"
},
  "geometry": {"coordinates":[7.607704,47.195461],"type":"Point"}
}