{
  "type": "Feature",
  "properties": {
    "iso:country":"CH",
    "sg:address":"Rue Des Coteaux 2",
    "sg:city":"Cortaillod",
    "sg:classifiers":[
        {
            "category":"Travel",
            "subcategory":"Hotels & Motels",
            "type":"Entertainment"
        }
    ],
    "sg:phone":"+41 32 842 11 17",
    "sg:postcode":"2016",
    "sg:province":"Neuch\u00e2tel",
    "sg:tags":[
        "hotels",
        "mit",
        "restaurant"
    ],
    "wof:name":"H\u00f4tel De Commune",
    "wof:placetype":"venue"
},
  "geometry": {"coordinates":[6.846121788,46.9427604675],"type":"Point"}
}