{
  "type": "Feature",
  "properties": {
    "iso:country":"CH",
    "sg:address":"1860 Aigle Case Postale 482",
    "sg:city":"Aigle",
    "sg:orig_category":"Landesverteidigung",
    "sg:phone":"+41 24 468 22 11",
    "sg:postcode":"1860",
    "sg:province":"Vaud",
    "wof:name":"Arsenal F\u00e9d\u00e9ral Aigle/st-maurice",
    "wof:placetype":"venue"
},
  "geometry": {"coordinates":[6.9701099396,46.3175544739],"type":"Point"}
}