{
  "type": "Feature",
  "properties": {
    "iso:country":"CH",
    "sg:address":"Bleichiweg 7a",
    "sg:city":"Teufen",
    "sg:orig_category":"Christmas Tree Stands",
    "sg:phone":"+41 71 370 04 05",
    "sg:postcode":"9053",
    "sg:province":"Appenzell Ausserrhoden",
    "wof:name":"Alba-krapf Ag",
    "wof:placetype":"venue"
},
  "geometry": {"coordinates":[9.393429,47.388275],"type":"Point"}
}