{
  "type": "Feature",
  "properties": {
    "iso:country":"CH",
    "sg:address":"N\u00f6ggel 234",
    "sg:city":"B\u00fchler",
    "sg:orig_category":"Instandhaltung U Reparatur von Automobilen",
    "sg:phone":"+41 79 601 07 02",
    "sg:postcode":"9055",
    "sg:province":"Appenzell Ausserrhoden",
    "wof:name":"Hans-peter Gyr S\u00e4ntis-garage",
    "wof:placetype":"venue"
},
  "geometry": {"coordinates":[9.4172058105,47.3732948303],"type":"Point"}
}