{
  "type": "Feature",
  "properties": {
    "iso:country":"CH",
    "sg:address":"Luzernerstrasse 11 5642 M\u00fchlau. Postfach",
    "sg:city":"M\u00fchlau",
    "sg:orig_category":"Instandhaltung U Reparatur von Automobilen Tankstellen",
    "sg:phone":"+41 56 668 10 22",
    "sg:postcode":"5642",
    "sg:province":"Aargau",
    "wof:name":"Garage B. R\u00fctter",
    "wof:placetype":"venue"
},
  "geometry": {"coordinates":[8.3901109695,47.2286491394],"type":"Point"}
}