{
  "type": "Feature",
  "properties": {
    "iso:country":"CH",
    "sg:address":"En F\u00e9lezin",
    "sg:city":"Romanel-s-lausanne",
    "sg:orig_category":"Detailhandel mit Brillen U anderen Sehhilfen Fachdetailhandel in Verkaufsr\u00e4umen",
    "sg:phone":"+41 21 636 30 00",
    "sg:postcode":"1032",
    "sg:province":"Vaud",
    "wof:name":"Visilab Renens Sa",
    "wof:placetype":"venue"
},
  "geometry": {"coordinates":[6.580768,46.538422],"type":"Point"}
}