{
  "type": "Feature",
  "properties": {
    "iso:country":"CH",
    "sg:address":"R\u00f6ssligasse 15",
    "sg:city":"Rothenfluh",
    "sg:orig_category":"Unclassifiable Establishments",
    "sg:postcode":"4467",
    "sg:province":"Basel-Landschaft",
    "wof:name":"Rieder-trans Gmbh",
    "wof:placetype":"venue"
},
  "geometry": {"coordinates":[7.9151182175,47.4599876404],"type":"Point"}
}