{
  "type": "Feature",
  "properties": {
    "iso:country":"CH",
    "sg:address":"Herzogstrasse 1",
    "sg:city":"Z\u00fcrich",
    "sg:orig_category":"Architekturb\u00fcros",
    "sg:phone":"+41 12611500",
    "sg:postcode":"8044",
    "sg:province":"Z\u00fcrich",
    "wof:name":"Lorenzo Weiss Architekturb\u00fcro",
    "wof:placetype":"venue"
},
  "geometry": {"coordinates":[8.556368,47.379936],"type":"Point"}
}