{
  "type": "Feature",
  "properties": {
    "addr:full":"Schaffhauserstrasse 91 Frauenfeld Thurgau 8500",
    "addr:housenumber":"91",
    "addr:postcode":"8500",
    "addr:street":"Schaffhauserstrasse",
    "iso:country":"CH",
    "sg:address":"Schaffhauserstrasse 91",
    "sg:city":"Frauenfeld",
    "sg:classifiers":[
        {
            "category":"Professional",
            "subcategory":"Advertising",
            "type":"Services"
        }
    ],
    "sg:phone":"+41 52 730 07 27",
    "sg:postcode":"8500",
    "sg:province":"Thurgau",
    "sg:tags":[
        "agency"
    ],
    "wof:name":"Richtblick Gmbh",
    "wof:placetype":"venue"
},
  "geometry": {"coordinates":[8.87925,47.562851],"type":"Point"}
}