{
  "type": "Feature",
  "properties": {
    "iso:country":"CH",
    "sg:address":"Av. Veillon 1 Case Postale 101",
    "sg:city":"Aigle",
    "sg:classifiers":[
        {
            "category":"Utilities",
            "subcategory":"Electric",
            "type":"Services"
        }
    ],
    "sg:phone":"+41 24 468 24 22",
    "sg:postcode":"1860",
    "sg:province":"Vaud",
    "sg:tags":[
        "electricity",
        "raw",
        "energy",
        "material"
    ],
    "wof:name":"Romande Energie",
    "wof:placetype":"venue"
},
  "geometry": {"coordinates":[15.0666999817,40.9967689514],"type":"Point"}
}