{
  "type": "Feature",
  "properties": {
    "iso:country":"CH",
    "sg:address":"3994",
    "sg:city":"Lax",
    "sg:orig_category":"Herstellung von sonstigen landwirtschaftlichen Maschinen",
    "sg:phone":"+41 27 971 23 39",
    "sg:postcode":"3994",
    "sg:province":"Valais",
    "wof:name":"Walther Ag Landmaschinenservice",
    "wof:placetype":"venue"
},
  "geometry": {"coordinates":[8.1170253754,46.3876533508],"type":"Point"}
}