{
  "type": "Feature",
  "properties": {
    "iso:country":"CH",
    "sg:address":"Rue Du Bourg 44",
    "sg:city":"Martigny",
    "sg:orig_category":"Architektur U Ingenieurb\u00fcros Architekturb\u00fcros",
    "sg:phone":"+41 27 722 81 78",
    "sg:postcode":"1920",
    "sg:province":"Valais",
    "wof:name":"Yvan Joris Bureau D'architecture",
    "wof:placetype":"venue"
},
  "geometry": {"coordinates":[7.063431,46.090347],"type":"Point"}
}