{
  "type": "Feature",
  "properties": {
    "iso:country":"CH",
    "sg:address":"Scheurenweg 11 2504 Biel/bienne. Postfach",
    "sg:city":"Biel/bienne",
    "sg:orig_category":"Instandhaltung U Reparatur von Automobilen",
    "sg:phone":"+41 32 342 00 35",
    "sg:postcode":"2504",
    "sg:province":"Bern",
    "wof:name":"Rianboss Gmbh",
    "wof:placetype":"venue"
},
  "geometry": {"coordinates":[7.2808489799,47.1443023682],"type":"Point"}
}