{
  "type": "Feature",
  "properties": {
    "iso:country":"CH",
    "sg:address":"Oberdettingerstrasse 10 3043 Uettligen. Postfach",
    "sg:city":"Uettligen",
    "sg:orig_category":"Sonstige mit der Informatik verbundene T\u00e4tigkeiten",
    "sg:phone":"+41 31 996 97 90",
    "sg:postcode":"3043",
    "sg:province":"Bern",
    "wof:name":"Didata Schlachter Christian",
    "wof:placetype":"venue"
},
  "geometry": {"coordinates":[7.3859081268,46.9855041504],"type":"Point"}
}