{
  "type": "Feature",
  "properties": {
    "iso:country":"CH",
    "sg:address":"Engestrasse 3 3012 Bern. Postfach",
    "sg:city":"Bern",
    "sg:orig_category":"Pensionskassen",
    "sg:postcode":"3005",
    "sg:province":"Bern",
    "wof:name":"Pensionsversicherung Des Verbandes Des Schweizerischen Spirituosengewerbes",
    "wof:placetype":"venue"
},
  "geometry": {"coordinates":[7.4377918243,46.9571304321],"type":"Point"}
}