{
  "type": "Feature",
  "properties": {
    "iso:country":"CH",
    "sg:address":"Via Verzino 2",
    "sg:city":"Muzzano",
    "sg:classifiers":[
        {
            "category":"Professional",
            "subcategory":"Employment Agencies",
            "type":"Services"
        }
    ],
    "sg:postcode":"6933",
    "sg:province":"Ticino",
    "sg:tags":[
        "personal",
        "u",
        "stellenvermittlung"
    ],
    "wof:name":"Swisspresence Dot Com Sagl",
    "wof:placetype":"venue"
},
  "geometry": {"coordinates":[8.9242668152,45.9981269836],"type":"Point"}
}