{
  "type": "Feature",
  "properties": {
    "iso:country":"CH",
    "sg:address":"Pfannenstilstrasse 29",
    "sg:city":"W\u00e4denswil",
    "sg:orig_category":"Personal U Stellenvermittlung Unternehmensberatung",
    "sg:phone":"+41 17808267",
    "sg:postcode":"8820",
    "sg:province":"Z\u00fcrich",
    "wof:name":"Topcom Consulting M\u00fcller Bettina",
    "wof:placetype":"venue"
},
  "geometry": {"coordinates":[8.6502361298,47.2343406677],"type":"Point"}
}