{
  "type": "Feature",
  "properties": {
    "iso:country":"CH",
    "sg:address":"Rue De Collombey 7",
    "sg:city":"Chamoson",
    "sg:orig_category":"Physiotherapie",
    "sg:phone":"+41 27 306 31 01",
    "sg:postcode":"1955",
    "sg:province":"Valais",
    "wof:name":"Marie-jos\u00e9 Gaist Physioth\u00e9rapie",
    "wof:placetype":"venue"
},
  "geometry": {"coordinates":[7.2347569466,46.1930732727],"type":"Point"}
}