{
  "type": "Feature",
  "properties": {
    "iso:country":"CH",
    "sg:address":"Gasse 8840 Einsiedeln. Postfach",
    "sg:city":"Willerzell",
    "sg:orig_category":"Zimmerei, Dachdeckerei, Bauspenglerei U Abdichtung",
    "sg:postcode":"8846",
    "sg:province":"Schwyz",
    "wof:name":"Sch\u00f6nb\u00e4chler Paul, 1954, Zimmerei",
    "wof:placetype":"venue"
},
  "geometry": {"coordinates":[8.7460803986,47.1273155212],"type":"Point"}
}