{
  "type": "Feature",
  "properties": {
    "iso:country":"CH",
    "sg:address":"Marktstrasse 22",
    "sg:city":"Sarmenstorf",
    "sg:orig_category":"Primarschulen",
    "sg:phone":"+41 56 667 17 44",
    "sg:postcode":"5614",
    "sg:province":"Aargau",
    "wof:name":"Primarschule Mitteldorf",
    "wof:placetype":"venue"
},
  "geometry": {"coordinates":[8.2498645782,47.3097114563],"type":"Point"}
}