{
  "type": "Feature",
  "properties": {
    "iso:country":"CH",
    "sg:address":"Lebernstrasse 32a",
    "sg:city":"Bettlach",
    "sg:orig_category":"Allgemeiner Hoch U Tiefbau",
    "sg:phone":"+41 65552728",
    "sg:postcode":"2544",
    "sg:province":"Solothurn",
    "wof:name":"Hr Marti Ag",
    "wof:placetype":"venue"
},
  "geometry": {"coordinates":[7.418528,47.194576],"type":"Point"}
}