{
  "type": "Feature",
  "properties": {
    "iso:country":"CH",
    "sg:address":"Bonstettenstrasse 5 3012 Bern. Postfach",
    "sg:city":"Bern",
    "sg:orig_category":"Herstellung von sonstigen elektrischen Ausr\u00fcstungen",
    "sg:phone":"+41 31450827",
    "sg:postcode":"3005",
    "sg:province":"Bern",
    "wof:name":"Vogt Elektronik Elektron. Ger\u00e4te; Reparatur, Entw.",
    "wof:placetype":"venue"
},
  "geometry": {"coordinates":[7.437456131,46.9579620361],"type":"Point"}
}