{
  "type": "Feature",
  "properties": {
    "addr:full":"Lindenhofstrasse 8 B\u00fclach Z\u00fcrich 8180",
    "addr:housenumber":"8",
    "addr:postcode":"8180",
    "addr:street":"Lindenhofstrasse;Zuerich",
    "iso:country":"CH",
    "sg:address":"Lindenhofstrasse 8",
    "sg:city":"B\u00fclach",
    "sg:orig_category":"Bauingenieurb\u00fcros Hochbau Bauingenieurb\u00fcros allgemein",
    "sg:phone":"+41 18605076",
    "sg:postcode":"8180",
    "sg:province":"Z\u00fcrich",
    "wof:name":"Beat Kocher Ingenieurb\u00fcro",
    "wof:placetype":"venue"
},
  "geometry": {"coordinates":[8.538738,47.520203],"type":"Point"}
}