{
  "type": "Feature",
  "properties": {
    "iso:country":"CH",
    "sg:address":"Bahnhofstrasse 2 8953 Dietikon. Postfach",
    "sg:city":"Dietikon",
    "sg:orig_category":"RESTAURANTS: TEA-ROOMS",
    "sg:postcode":"8953",
    "sg:province":"Z\u00fcrich",
    "wof:name":"Restaurant Casa Da Vinci Meier Heinz",
    "wof:placetype":"venue"
},
  "geometry": {"coordinates":[8.405166626,47.4044685364],"type":"Point"}
}