{
  "type": "Feature",
  "properties": {
    "iso:country":"CH",
    "sg:address":"Ador Quai Gustave- 60 1207 Gen\u00e8ve. Postfach",
    "sg:city":"Gen\u00e8ve",
    "sg:orig_category":"Grosshandel mit sonstigen Gebrauchs U Verbrauchsg\u00fctern",
    "sg:phone":"+41 22 788 14 60",
    "sg:postcode":"1207",
    "sg:province":"Gen\u00e8ve",
    "wof:name":"Onyx Financial Advisors Sa",
    "wof:placetype":"venue"
},
  "geometry": {"coordinates":[6.126830101,46.2368164062],"type":"Point"}
}