{
  "type": "Feature",
  "properties": {
    "iso:country":"CH",
    "sg:address":"Laurenzenvorstadt 90 5000 Aarau. Postfach",
    "sg:city":"Aarau",
    "sg:orig_category":"Grosshandel mit sonstigen Maschinen U Ausr\u00fcstungen f\u00fcr Industrie, Handel U Schiffahrt",
    "sg:postcode":"5000",
    "sg:province":"Aargau",
    "wof:name":"Nordeck Ag",
    "wof:placetype":"venue"
},
  "geometry": {"coordinates":[8.050778389,47.3940467834],"type":"Point"}
}