{
  "type": "Feature",
  "properties": {
    "iso:country":"CH",
    "sg:address":"Via Cassarinetta 29",
    "sg:city":"Lugano",
    "sg:orig_category":"Architektur U Ingenieurb\u00fcros Architekturb\u00fcros",
    "sg:phone":"+41 81 833 34 44",
    "sg:postcode":"6900",
    "sg:province":"Ticino",
    "wof:name":"Mario Verdieri Ag, Architekturb\u00fcro",
    "wof:placetype":"venue"
},
  "geometry": {"coordinates":[9.838391,46.499882],"type":"Point"}
}