{
  "type": "Feature",
  "properties": {
    "iso:country":"CH",
    "sg:address":"Gerbestrasse 11",
    "sg:city":"Appenzell",
    "sg:orig_category":"Versicherungen Hauptagenturen",
    "sg:phone":"+41 71 787 52 22",
    "sg:postcode":"9050",
    "sg:province":"Appenzell Innerhoden",
    "wof:name":"Z\u00fcrich-versicherungen Hauptagentur",
    "wof:placetype":"venue"
},
  "geometry": {"coordinates":[9.4099111557,47.3299598694],"type":"Point"}
}