{
  "type": "Feature",
  "properties": {
    "iso:country":"CH",
    "sg:address":"Br\u00fcnnelih\u00f6hestrasse 14 8400 Winterthur. Postfach",
    "sg:city":"Winterthur",
    "sg:orig_category":"Erbringung von Dienstleistungen f\u00fcr Unternehmen",
    "sg:phone":"+41 52 208 11 11",
    "sg:postcode":"8400",
    "sg:province":"Z\u00fcrich",
    "wof:name":"Dns-net Gmbh",
    "wof:placetype":"venue"
},
  "geometry": {"coordinates":[8.706615448,47.4971351624],"type":"Point"}
}