{
  "type": "Feature",
  "properties": {
    "iso:country":"CH",
    "sg:address":"Kapelle",
    "sg:city":"Signau",
    "sg:orig_category":"Religi\u00f6se Vereinigungen divers",
    "sg:postcode":"3534",
    "sg:province":"Bern",
    "wof:name":"Cvjm",
    "wof:placetype":"venue"
},
  "geometry": {"coordinates":[7.7206711769,46.916934967],"type":"Point"}
}