{
  "type": "Feature",
  "properties": {
    "iso:country":"CH",
    "sg:address":"Via Da Mez 181",
    "sg:city":"Poschiavo",
    "sg:orig_category":"Vermittlung von Immobilien Wirtschaftspr\u00fcfung, Steuerberatung U Treuhand",
    "sg:phone":"+41 81 844 06 37",
    "sg:postcode":"7742",
    "sg:province":"Graubunden",
    "wof:name":"Fiduciaria Fernando Costa",
    "wof:placetype":"venue"
},
  "geometry": {"coordinates":[10.0578508377,46.3231658936],"type":"Point"}
}