{
  "type": "Feature",
  "properties": {
    "iso:country":"CH",
    "sg:address":"Zollikerstrasse 27 8000 Z\u00fcrich. Postfach 8032 Z\u00fcrich",
    "sg:city":"Zust",
    "sg:orig_category":"K\u00fcnstlerische U schriftstellerische T\u00e4tigkeiten U Darbietungen",
    "sg:postcode":"32",
    "wof:name":"Ath\u00c9n\u00c9e Productions Ag",
    "wof:placetype":"venue"
},
  "geometry": {"coordinates":[8.5552062988,47.3632125854],"type":"Point"}
}