{
  "type": "Feature",
  "properties": {
    "addr:full":"Schweissbergweg 53 Binningen Basel-Landschaft 4102",
    "addr:housenumber":"53",
    "addr:postcode":"4102",
    "addr:street":"Schweissbergweg",
    "iso:country":"CH",
    "sg:address":"Schweissbergweg 53",
    "sg:city":"Binningen",
    "sg:orig_category":"Arztpraxen",
    "sg:phone":"+41 61 281 79 97",
    "sg:postcode":"4102",
    "sg:province":"Basel-Landschaft",
    "wof:name":"Dr.med. Barbara Leutenegger Spezial\u00e4rztin Fmh",
    "wof:placetype":"venue"
},
  "geometry": {"coordinates":[7.575669,47.533401],"type":"Point"}
}