{
  "type": "Feature",
  "properties": {
    "iso:country":"CH",
    "sg:address":"3825",
    "sg:city":"M\u00fcrren",
    "sg:orig_category":"Sportvereine Jagd",
    "sg:phone":"+41 81 416 23 12",
    "sg:postcode":"3825",
    "sg:province":"Bern",
    "wof:name":"J\u00e4gerverein Sekt.davos Bkpjv",
    "wof:placetype":"venue"
},
  "geometry": {"coordinates":[9.8591117859,46.8307533264],"type":"Point"}
}