{
  "type": "Feature",
  "properties": {
    "iso:country":"CH",
    "sg:address":"Schlossstrasse 10",
    "sg:city":"Oberdiessbach",
    "sg:orig_category":"G\u00fcterbef\u00f6rderung im Strassenverkehr",
    "sg:phone":"+41 31 711 10 21",
    "sg:postcode":"3672",
    "sg:province":"Bern",
    "wof:name":"Mta Transport Ag",
    "wof:placetype":"venue"
},
  "geometry": {"coordinates":[7.6196141243,46.839214325],"type":"Point"}
}