{
  "type": "Feature",
  "properties": {
    "iso:country":"CH",
    "sg:address":"Hauptstrasse 35",
    "sg:city":"L\u00f6hningen",
    "sg:orig_category":"Detailhandel mit Waren verschiedener Art, Hauptrichtung Nahrungsmittel",
    "sg:phone":"+41 52 264 26 16",
    "sg:postcode":"8224",
    "sg:province":"Schaffhausen",
    "wof:name":"Volg Detailhandels Ag",
    "wof:placetype":"venue"
},
  "geometry": {"coordinates":[8.5527791977,47.7011451721],"type":"Point"}
}