{
  "type": "Feature",
  "properties": {
    "iso:country":"CH",
    "sg:address":"Sch\u00f6nenhofstrasse 19",
    "sg:city":"Frauenfeld",
    "sg:orig_category":"Einbau von Schreinerwaren Herstellung von K\u00fcchenm\u00f6beln",
    "sg:phone":"+41 21 728 13 54",
    "sg:postcode":"8500",
    "sg:province":"Thurgau",
    "wof:name":"Flach Andr\u00e9 Sa",
    "wof:placetype":"venue"
},
  "geometry": {"coordinates":[6.640226841,46.5103149414],"type":"Point"}
}