{
  "type": "Feature",
  "properties": {
    "addr:full":"Rue Des Usines 21 Neuch\u00e2tel Neuch\u00e2tel 2000",
    "addr:housenumber":"21",
    "addr:postcode":"2000",
    "addr:street":"Rue Des Usines",
    "iso:country":"CH",
    "sg:address":"Rue Des Usines 21",
    "sg:city":"Neuch\u00e2tel",
    "sg:orig_category":"Detailhandel mit Brennstoffen U Heizmaterial",
    "sg:phone":"+41 32 731 65 31",
    "sg:postcode":"2000",
    "sg:province":"Neuch\u00e2tel",
    "wof:name":"Alfred Meyer Sa Ferrements Visserie Outillage",
    "wof:placetype":"venue"
},
  "geometry": {"coordinates":[6.903407,46.982857],"type":"Point"}
}