{
  "type": "Feature",
  "properties": {
    "iso:country":"CH",
    "sg:address":"Route Andr\u00e9 Piller 37 1720 Corminboeuf Case Postale 58",
    "sg:city":"Corminboeuf",
    "sg:orig_category":"Herstellung von homogenisierten U di\u00e4tetischen Nahrungsmitteln Herstellung von sonstigen Nahrungsmit",
    "sg:phone":"+41 26 460 83 00",
    "sg:postcode":"1720",
    "sg:province":"Fribourg",
    "wof:name":"New Sundiet Sa Produits Alimentaires; Fabrication Et Commercialisation. Brevets, Proc\u00e9d\u00e9s Etc.; Acquisition Et Exploitation",
    "wof:placetype":"venue"
},
  "geometry": {"coordinates":[7.1130042076,46.8115234375],"type":"Point"}
}