{
  "type": "Feature",
  "properties": {
    "iso:country":"CH",
    "sg:address":"Rue De La Gare 21 1860 Aigle. Postfach",
    "sg:city":"Aigle",
    "sg:orig_category":"Allgemeinbildende weiterf\u00fchrende Schulen Bezirks, Sekundar, Realschulen, Oberstufe der Primarschulen",
    "sg:phone":"+41 24 466 21 12",
    "sg:postcode":"1860",
    "sg:province":"Vaud",
    "wof:name":"Coll\u00e8ge Secondaire De Mon S\u00e9jour",
    "wof:placetype":"venue"
},
  "geometry": {"coordinates":[6.965805,46.317223],"type":"Point"}
}