{
  "type": "Feature",
  "properties": {
    "iso:country":"CH",
    "sg:address":"Industriestrasse 18",
    "sg:city":"Zwingen",
    "sg:orig_category":"Herstellung von sonstigen chemischen Erzeugnissen Herstellung von sonstigen organischen Grundstoffen",
    "sg:phone":"+41 61 761 22 44",
    "sg:postcode":"4222",
    "sg:province":"Basel-Landschaft",
    "wof:name":"Thedra Ag",
    "wof:placetype":"venue"
},
  "geometry": {"coordinates":[7.5138511658,47.4303665161],"type":"Point"}
}