{
  "type": "Feature",
  "properties": {
    "iso:country":"CH",
    "sg:address":"Schulweg 4",
    "sg:city":"Hitzkirch",
    "sg:classifiers":[
        {
            "category":"Banks & Credit Unions",
            "subcategory":"Bank",
            "type":"Services"
        }
    ],
    "sg:phone":"+41 4141852025",
    "sg:postcode":"6285",
    "sg:province":"Luzern",
    "wof:name":"Schweiz. Mobiliar",
    "wof:placetype":"venue"
},
  "geometry": {"coordinates":[8.260297,47.224945],"type":"Point"}
}