{
  "type": "Feature",
  "properties": {
    "iso:country":"CH",
    "sg:address":"Sonnenterrasse 38",
    "sg:city":"Ebikon",
    "sg:orig_category":"Erschliessung von Grundst\u00fccken",
    "sg:postcode":"6030",
    "sg:province":"Luzern",
    "wof:name":"Liberale Wohngenossenschaft Sonnenterrasse Ebikon",
    "wof:placetype":"venue"
},
  "geometry": {"coordinates":[8.3369264603,47.0852622986],"type":"Point"}
}