{
  "type": "Feature",
  "properties": {
    "iso:country":"CH",
    "sg:address":"Rue Du Simplon 4",
    "sg:city":"Payerne",
    "sg:orig_category":"Sonstiger Fachdetailhandel mit Nahrungsmitteln, Getr\u00e4nken U Tabak in Verkaufsr\u00e4umen",
    "sg:phone":"+41 31 859 04 10",
    "sg:postcode":"1530",
    "sg:province":"Vaud",
    "wof:name":"Hugo Gasser",
    "wof:placetype":"venue"
},
  "geometry": {"coordinates":[7.5341072083,47.0222091675],"type":"Point"}
}