{
  "type": "Feature",
  "properties": {
    "iso:country":"CH",
    "sg:address":"Sch\u00fctzenstrasse 3",
    "sg:city":"Lausen",
    "sg:orig_category":"Vereine Fasnacht",
    "sg:postcode":"4415",
    "sg:province":"Basel-Landschaft",
    "wof:name":"Fraenke-schraenzer",
    "wof:placetype":"venue"
},
  "geometry": {"coordinates":[7.7577672005,47.4741821289],"type":"Point"}
}