{
  "type": "Feature",
  "properties": {
    "iso:country":"CH",
    "sg:address":"8585",
    "sg:city":"Birwinken",
    "sg:orig_category":"Verwertung von Milch",
    "sg:postcode":"8585",
    "sg:province":"Thurgau",
    "wof:name":"Klarer R.",
    "wof:placetype":"venue"
},
  "geometry": {"coordinates":[9.1965341568,47.5826263428],"type":"Point"}
}