{
  "type": "Feature",
  "properties": {
    "iso:country":"CH",
    "sg:address":"Buchenstrasse 4 6020 Emmenbr\u00fccke. Postfach",
    "sg:city":"Emmenbr\u00fccke",
    "sg:orig_category":"Saunas, Solarien, Fitnesszentren U \u00e4hnliches",
    "sg:postcode":"6020",
    "sg:province":"Luzern",
    "wof:name":"Flex-sy Gym S\u00e0rl",
    "wof:placetype":"venue"
},
  "geometry": {"coordinates":[6.5797610283,46.5395202637],"type":"Point"}
}