{
  "type": "Feature",
  "properties": {
    "iso:country":"CH",
    "sg:address":"Petit-cortaillod 2",
    "sg:city":"Cortaillod",
    "sg:orig_category":"Erbringung von Dienstleistungen f\u00fcr Unternehmen",
    "sg:phone":"+41 32 845 03 60",
    "sg:postcode":"2016",
    "sg:province":"Neuch\u00e2tel",
    "wof:name":"Glauser Christian",
    "wof:placetype":"venue"
},
  "geometry": {"coordinates":[6.8513407707,46.9415054321],"type":"Point"}
}