{
  "type": "Feature",
  "properties": {
    "iso:country":"CH",
    "sg:address":"Rue Des Chanoines 9 1700 Fribourg Case Postale 69",
    "sg:city":"Fribourg",
    "sg:classifiers":[
        {
            "category":"Restaurant",
            "type":"Food & Drink"
        }
    ],
    "sg:phone":"+41 26 322 33 33",
    "sg:postcode":"1702",
    "sg:province":"Fribourg",
    "wof:name":"Restaurant Des Mar\u00e9chaux",
    "wof:placetype":"venue"
},
  "geometry": {"coordinates":[7.1633791924,46.8064422607],"type":"Point"}
}