{
  "type": "Feature",
  "properties": {
    "iso:country":"CH",
    "sg:address":"Route De Gen\u00e8ve 9c",
    "sg:city":"Commugny",
    "sg:orig_category":"Handelsvermittlung U Grosshandel Sonstiger Grosshandel",
    "sg:phone":"+41 22 776 04 76",
    "sg:postcode":"1291",
    "sg:province":"Vaud",
    "wof:name":"Strong Import-export Sa",
    "wof:placetype":"venue"
},
  "geometry": {"coordinates":[6.1737442017,46.3177337646],"type":"Point"}
}