{
  "type": "Feature",
  "properties": {
    "iso:country":"CH",
    "sg:address":"Rosenweg 8b",
    "sg:city":"Baar",
    "sg:orig_category":"Unclassifiable Establishments",
    "sg:postcode":"6340",
    "sg:province":"Zug",
    "wof:name":"Taxi & Kleintransporte, Imboden Paula",
    "wof:placetype":"venue"
},
  "geometry": {"coordinates":[7.8021001816,46.1756591797],"type":"Point"}
}