{
  "type": "Feature",
  "properties": {
    "addr:full":"Wannerstrasse 15/29 Z\u00fcrich Z\u00fcrich 8045",
    "addr:housenumber":"15 / 29",
    "addr:postcode":"8045",
    "addr:street":"Wannerstrasse",
    "iso:country":"CH",
    "sg:address":"Wannerstrasse 15/29",
    "sg:city":"Z\u00fcrich",
    "sg:orig_category":"Architekturb\u00fcros",
    "sg:phone":"+41 14511510",
    "sg:postcode":"8045",
    "sg:province":"Z\u00fcrich",
    "wof:name":"Praxmarer Baumanagement",
    "wof:placetype":"venue"
},
  "geometry": {"coordinates":[8.518404,47.357552],"type":"Point"}
}