{
  "type": "Feature",
  "properties": {
    "iso:country":"CH",
    "sg:address":"Rue Des Romains 1",
    "sg:city":"Develier",
    "sg:orig_category":"Sonstige Aktivit\u00e4ten der nicht-\u00e4rztlichen Medizinalberufe",
    "sg:phone":"+41 32 423 19 40",
    "sg:postcode":"2802",
    "sg:province":"Jura",
    "wof:name":"Willy Kl\u00f6tzli Kin\u00e9siologie & Massage",
    "wof:placetype":"venue"
},
  "geometry": {"coordinates":[7.3043279648,47.3610954285],"type":"Point"}
}