{
  "type": "Feature",
  "properties": {
    "iso:country":"CH",
    "sg:address":"3714",
    "sg:city":"Frutigen",
    "sg:orig_category":"Non-Classified Establishments",
    "sg:phone":"+41 33 672 72 72",
    "sg:postcode":"3714",
    "sg:province":"Bern",
    "wof:name":"Wandfluh Holding Ag",
    "wof:placetype":"venue"
},
  "geometry": {"coordinates":[7.6423301697,46.5800285339],"type":"Point"}
}