{
  "type": "Feature",
  "properties": {
    "iso:country":"CH",
    "sg:address":"Baldingerstrasse 16",
    "sg:city":"Endingen",
    "sg:orig_category":"Sportvereine Ballsport Handball",
    "sg:phone":"+41 56 242 10 74",
    "sg:postcode":"5304",
    "sg:province":"Aargau",
    "wof:name":"Tv Endingen",
    "wof:placetype":"venue"
},
  "geometry": {"coordinates":[8.2996263504,47.5368728638],"type":"Point"}
}