{
  "type": "Feature",
  "properties": {
    "iso:country":"CH",
    "sg:address":"Libloseweg 9",
    "sg:city":"Thayngen",
    "sg:orig_category":"Vermietung U Verpachtung von eigenen Immobilien",
    "sg:phone":"+41 52 649 22 33",
    "sg:postcode":"8240",
    "sg:province":"Schaffhausen",
    "wof:name":"Unger M. & Co",
    "wof:placetype":"venue"
},
  "geometry": {"coordinates":[8.7063560486,47.7480812073],"type":"Point"}
}