{
  "type": "Feature",
  "properties": {
    "addr:full":"Tivoli Spreitenbach Aargau 8957",
    "addr:postcode":"8957",
    "iso:country":"CH",
    "sg:address":"Tivoli",
    "sg:city":"Spreitenbach",
    "sg:orig_category":"Detailhandel mit B\u00fcchern, Zeitungen, Schreib U Papeteriewaren Detailhandel mit Schreib U Papeteriewa",
    "sg:phone":"+41 56 401 56 38",
    "sg:postcode":"8957",
    "sg:province":"Aargau",
    "wof:name":"H\u00f6chli Ag Papeterie B\u00fcrobedarf",
    "wof:placetype":"venue"
},
  "geometry": {"coordinates":[8.365684,47.418045],"type":"Point"}
}