{
  "type": "Feature",
  "properties": {
    "iso:country":"CH",
    "sg:address":"Chamerstrasse 30 6300 Zug. Postfach 4635",
    "sg:city":"Zug",
    "sg:orig_category":"Grosshandel mit sonstigen Maschinen U Ausr\u00fcstungen f\u00fcr Industrie, Handel U Schiffahrt Handelsvermitt",
    "sg:phone":"+41 41 720 20 31",
    "sg:postcode":"6304",
    "sg:province":"Zug",
    "wof:name":"Aquarius Water Management Ag",
    "wof:placetype":"venue"
},
  "geometry": {"coordinates":[8.5089349747,47.1728401184],"type":"Point"}
}