{
  "type": "Feature",
  "properties": {
    "iso:country":"CH",
    "sg:address":"Glattalstrasse 63 8052 Z\u00fcrich. Postfach",
    "sg:city":"Z\u00fcrich",
    "sg:orig_category":"Herstellung von Ger\u00e4ten der Elektrizit\u00e4tserzeugung, -verteilung u.\u00e4. -Energieversorgung",
    "sg:phone":"+41 13023535",
    "sg:postcode":"8052",
    "sg:province":"Z\u00fcrich",
    "wof:name":"Gmc-instruments Schweiz Ag",
    "wof:placetype":"venue"
},
  "geometry": {"coordinates":[8.5475053787,47.425567627],"type":"Point"}
}