{
  "type": "Feature",
  "properties": {
    "iso:country":"CH",
    "sg:address":"Diepoldsauer Strasse 27",
    "sg:city":"Widnau",
    "sg:orig_category":"Herstellung von Lederbekleidung Herstellung von Lederwaren U Schuhen",
    "sg:phone":"+41 71 722 10 90",
    "sg:postcode":"9443",
    "sg:province":"St. Gallen",
    "wof:name":"Ursula B\u00fcrgi Lederatelier",
    "wof:placetype":"venue"
},
  "geometry": {"coordinates":[9.639216423,47.3990821838],"type":"Point"}
}