{
  "type": "Feature",
  "properties": {
    "iso:country":"CH",
    "sg:address":"Zinal 3961 Zinal. Postfach",
    "sg:city":"Zinal",
    "sg:classifiers":[
        {
            "category":"Travel",
            "subcategory":"Hotels & Motels",
            "type":"Entertainment"
        }
    ],
    "sg:phone":"+41 27 475 11 64",
    "sg:postcode":"3961",
    "sg:province":"Valais",
    "sg:tags":[
        "hotels",
        "mit",
        "restaurant"
    ],
    "wof:name":"H\u00f4tel \u00e0 La Pointe De Zinal, Melly Serge",
    "wof:placetype":"venue"
},
  "geometry": {"coordinates":[7.6285200119,46.1362037659],"type":"Point"}
}