{
  "type": "Feature",
  "properties": {
    "iso:country":"CH",
    "sg:address":"Chemin Des Epinettes 22 1007 Lausanne. Postfach",
    "sg:city":"Lausanne",
    "sg:orig_category":"Erbringung von Dienstleistungen f\u00fcr Unternehmen",
    "sg:postcode":"1007",
    "sg:province":"Vaud",
    "wof:name":"Gerth Jean-michel.",
    "wof:placetype":"venue"
},
  "geometry": {"coordinates":[6.6244149208,46.5173072815],"type":"Point"}
}