{
  "type": "Feature",
  "properties": {
    "iso:country":"CH",
    "sg:address":"Unterdorf",
    "sg:city":"Alberswil",
    "sg:orig_category":"Malerei",
    "sg:phone":"+41 41 980 52 23",
    "sg:postcode":"6248",
    "sg:province":"Luzern",
    "wof:name":"Birrer Malerei Ag",
    "wof:placetype":"venue"
},
  "geometry": {"coordinates":[7.9999580383,47.1571807861],"type":"Point"}
}