{
  "type": "Feature",
  "properties": {
    "iso:country":"CH",
    "sg:address":"Bleichestrasse 7",
    "sg:city":"Basel",
    "sg:orig_category":"Maurerarbeiten",
    "sg:phone":"+41 61 692 13 90",
    "sg:postcode":"4058",
    "sg:province":"Basel-Stadt",
    "wof:name":"G\u00fcnter Messerli Maurergesch\u00e4ft",
    "wof:placetype":"venue"
},
  "geometry": {"coordinates":[7.6002092361,47.5658836365],"type":"Point"}
}