{
  "type": "Feature",
  "properties": {
    "iso:country":"CH",
    "sg:address":"La Massellaz 1126 Vaux-sur-morges. Postfach",
    "sg:city":"Vaux-sur-morges",
    "sg:orig_category":"Interessenvertretungen",
    "sg:postcode":"1126",
    "sg:province":"Vaud",
    "wof:name":"Fondation Harafi Promotion De La Culture, Notamm. Les Arts Plastiques Etc",
    "wof:placetype":"venue"
},
  "geometry": {"coordinates":[6.4654688835,46.5352478027],"type":"Point"}
}