{
  "type": "Feature",
  "properties": {
    "iso:country":"CH",
    "sg:address":"Gare Sentier De La",
    "sg:city":"Pully",
    "sg:orig_category":"Grosshandel mit Getr\u00e4nken",
    "sg:postcode":"1009",
    "sg:province":"Vaud",
    "wof:name":"In Vino Veritas, Michele Palazzo",
    "wof:placetype":"venue"
},
  "geometry": {"coordinates":[6.6598000526,46.5102577209],"type":"Point"}
}