{
  "type": "Feature",
  "properties": {
    "iso:country":"CH",
    "sg:address":"Place Roland B\u00e9guelin 4",
    "sg:city":"Del\u00e9mont",
    "sg:orig_category":"Detailhandel mit Uhren U Schmuck",
    "sg:phone":"+41 32 422 84 40",
    "sg:postcode":"2800",
    "sg:province":"Jura",
    "wof:name":"Bijoux-atelier Caroline Friedli",
    "wof:placetype":"venue"
},
  "geometry": {"coordinates":[7.343462944,47.3657608032],"type":"Point"}
}