{
  "type": "Feature",
  "properties": {
    "iso:country":"CH",
    "sg:address":"Bimerweg 53",
    "sg:city":"Jegenstorf",
    "sg:orig_category":"K\u00fcnstlerische Schulen",
    "sg:phone":"+41 31 761 26 70",
    "sg:postcode":"3303",
    "sg:province":"Bern",
    "wof:name":"Musikschule Jegenstorf Kirsti & Erwin L\u00e4tsch",
    "wof:placetype":"venue"
},
  "geometry": {"coordinates":[7.5038981438,47.0544700623],"type":"Point"}
}