{
  "type": "Feature",
  "properties": {
    "iso:country":"CH",
    "sg:address":"Auenrainstrasse 44",
    "sg:city":"Winterthur",
    "sg:orig_category":"Sonstige pers\u00f6nliche Dienstleistungen",
    "sg:phone":"+41 55 210 00 23",
    "sg:postcode":"8406",
    "sg:province":"Z\u00fcrich",
    "wof:name":"Schiess Eng Ag",
    "wof:placetype":"venue"
},
  "geometry": {"coordinates":[8.8181171417,47.2343444824],"type":"Point"}
}