{
  "type": "Feature",
  "properties": {
    "iso:country":"CH",
    "sg:address":"Baumgartenweg 4 8605 Gutenswil. Postfach",
    "sg:city":"Gutenswil",
    "sg:orig_category":"Softwareentwicklung U beratung",
    "sg:postcode":"8605",
    "sg:province":"Z\u00fcrich",
    "wof:name":"Askus Betschart Beratung, Schulung U. Marketing Im Bereiche Von Edv-hard, Software Usw",
    "wof:placetype":"venue"
},
  "geometry": {"coordinates":[8.7167606354,47.3827590942],"type":"Point"}
}