{
  "type": "Feature",
  "properties": {
    "iso:country":"CH",
    "sg:address":"Oberneuhofstrasse 8",
    "sg:city":"Baar",
    "sg:orig_category":"Unclassifiable Establishments",
    "sg:postcode":"6340",
    "sg:province":"Zug",
    "wof:name":"Kuster Netcom Ag",
    "wof:placetype":"venue"
},
  "geometry": {"coordinates":[8.5162916183,47.1882781982],"type":"Point"}
}