{
  "type": "Feature",
  "properties": {
    "iso:country":"CH",
    "sg:address":"Unter Blapbach",
    "sg:city":"Trubschachen",
    "sg:orig_category":"Hochschulen U h\u00f6here Ausbildung",
    "sg:postcode":"3555",
    "sg:province":"Bern",
    "wof:name":"Holderbank-stiftung Zur F\u00f6rderung Der Wissenschaftlichen Fortbildung",
    "wof:placetype":"venue"
},
  "geometry": {"coordinates":[8.1667671204,47.4319190979],"type":"Point"}
}