{
  "type": "Feature",
  "properties": {
    "iso:country":"CH",
    "sg:address":"Maiengr\u00fcnweg 7",
    "sg:city":"Niederlenz",
    "sg:orig_category":"Unternehmensberatung",
    "sg:postcode":"5702",
    "sg:province":"Aargau",
    "wof:name":"Schulz Unternehmensberatung",
    "wof:placetype":"venue"
},
  "geometry": {"coordinates":[8.1735677719,47.397441864],"type":"Point"}
}