{
  "type": "Feature",
  "properties": {
    "iso:country":"CH",
    "sg:address":"Rue Des Fleurs 7",
    "sg:city":"St-imier",
    "sg:orig_category":"Handel mit Automobilen",
    "sg:postcode":"2610",
    "sg:province":"Bern",
    "wof:name":"Automobiles Distribution Ad Sa",
    "wof:placetype":"venue"
},
  "geometry": {"coordinates":[6.9919681549,47.1512451172],"type":"Point"}
}