{
  "type": "Feature",
  "properties": {
    "addr:full":"3235 Erlach Bern 3235",
    "addr:postcode":"3235;3235",
    "iso:country":"CH",
    "sg:address":"3235",
    "sg:city":"Erlach",
    "sg:orig_category":"Bezirks, Sekundar, Realschulen, Oberstufe der Primarschulen",
    "sg:phone":"+41 32 631 00 82",
    "sg:postcode":"3235",
    "sg:province":"Bern",
    "wof:name":"Sekundarschule",
    "wof:placetype":"venue"
},
  "geometry": {"coordinates":[7.654852,47.235695],"type":"Point"}
}