{
  "type": "Feature",
  "properties": {
    "iso:country":"CH",
    "sg:address":"Hauptgasse 7",
    "sg:city":"Murten",
    "sg:orig_category":"Detailhandel mit Bekleidung",
    "sg:phone":"+41 26 670 15 42",
    "sg:postcode":"3280",
    "sg:province":"Fribourg",
    "wof:name":"Lilly L\u00fcthi Chapellerie",
    "wof:placetype":"venue"
},
  "geometry": {"coordinates":[7.116455,46.928101],"type":"Point"}
}