{
  "type": "Feature",
  "properties": {
    "iso:country":"CH",
    "sg:address":"1422",
    "sg:city":"Grandson",
    "sg:orig_category":"RESTAURANTS: TEA-ROOMS",
    "sg:phone":"+41 24 445 44 35",
    "sg:postcode":"1422",
    "sg:province":"Vaud",
    "wof:name":"Mayor Jean-paul Et Lise",
    "wof:placetype":"venue"
},
  "geometry": {"coordinates":[6.6459851265,46.8093681335],"type":"Point"}
}