{
  "type": "Feature",
  "properties": {
    "iso:country":"CH",
    "sg:address":"Piazza Dante 8",
    "sg:city":"Lugano",
    "sg:orig_category":"Advokaturb\u00fcros",
    "sg:phone":"+41 71 245 66 63",
    "sg:postcode":"6900",
    "sg:province":"Ticino",
    "wof:name":"F\u00e4ssler Schubiger Conzett & Kellenberger",
    "wof:placetype":"venue"
},
  "geometry": {"coordinates":[9.378781,47.428776],"type":"Point"}
}