{
  "type": "Feature",
  "properties": {
    "iso:country":"CH",
    "sg:address":"Obmoos 5",
    "sg:city":"Zug",
    "sg:orig_category":"Softwareentwicklung U beratung",
    "sg:phone":"+41 79 341 92 86",
    "sg:postcode":"6300",
    "sg:province":"Zug",
    "wof:name":"Sinusoft Gmbh",
    "wof:placetype":"venue"
},
  "geometry": {"coordinates":[8.5222291946,47.1673698425],"type":"Point"}
}