{
  "type": "Feature",
  "properties": {
    "iso:country":"CH",
    "sg:address":"S\u00fcdstrasse 8 3110 M\u00fcnsingen. Postfach 1124",
    "sg:city":"M\u00fcnsingen",
    "sg:orig_category":"Abwasserreinigung",
    "sg:phone":"+41 31 721 62 62",
    "sg:postcode":"3110",
    "sg:province":"Bern",
    "wof:name":"Rohr-reinigungs-service Ag Rohr-max",
    "wof:placetype":"venue"
},
  "geometry": {"coordinates":[7.563089,46.86776],"type":"Point"}
}