{
  "type": "Feature",
  "properties": {
    "iso:country":"CH",
    "sg:address":"Riedhofstrasse 378",
    "sg:city":"Z\u00fcrich",
    "sg:orig_category":"Erwachsenenbildung U Unterricht",
    "sg:postcode":"8049",
    "sg:province":"Z\u00fcrich",
    "wof:name":"Comutech, Wolff & Co Kommunikations- U. F\u00fchrungstechnik; Schulungskurse",
    "wof:placetype":"venue"
},
  "geometry": {"coordinates":[8.480928421,47.4095230103],"type":"Point"}
}