{
  "type": "Feature",
  "properties": {
    "iso:country":"CH",
    "sg:address":"Contrada Maggiore 23",
    "sg:city":"Ascona",
    "sg:classifiers":[
        {
            "category":"Restaurant",
            "type":"Food & Drink"
        }
    ],
    "sg:phone":"+41 91 791 13 96",
    "sg:postcode":"6612",
    "sg:province":"Ticino",
    "wof:name":"Antica Osteria Vacchini Ristorante",
    "wof:placetype":"venue"
},
  "geometry": {"coordinates":[8.7684926987,46.1550445557],"type":"Point"}
}