{
  "type": "Feature",
  "properties": {
    "iso:country":"CH",
    "sg:address":"Rue Du Vieux-moulin 4",
    "sg:city":"Sion",
    "sg:classifiers":[
        {
            "category":"Education",
            "subcategory":"Library",
            "type":"Public Place"
        }
    ],
    "sg:phone":"+41 27 322 69 59",
    "sg:postcode":"1950",
    "sg:province":"Valais",
    "sg:tags":[
        "u",
        "bibliotheken",
        "archive"
    ],
    "wof:name":"Biblioth\u00e8que De La Paroisse Reform\u00e9e Evang\u00e9lique",
    "wof:placetype":"venue"
},
  "geometry": {"coordinates":[7.361367,46.236729],"type":"Point"}
}