{
  "type": "Feature",
  "properties": {
    "iso:country":"CH",
    "sg:address":"Delfterstrasse 43",
    "sg:city":"Aarau",
    "sg:orig_category":"Non-Classified Establishments",
    "sg:phone":"+41 91 825 88 52",
    "sg:postcode":"5004",
    "sg:province":"Aargau",
    "wof:name":"Mirno Sa",
    "wof:placetype":"venue"
},
  "geometry": {"coordinates":[8.9955282211,46.187713623],"type":"Point"}
}