{
  "type": "Feature",
  "properties": {
    "iso:country":"CH",
    "sg:address":"Chemin De Plan-manon 2",
    "sg:city":"Territet-veytaux",
    "sg:orig_category":"Ger\u00fcstbau Sonstiger spezialisierter Hoch U Tiefbau",
    "sg:phone":"+41 32 914 42 86",
    "sg:postcode":"1820",
    "sg:province":"Vaud",
    "wof:name":"Echamont Sa",
    "wof:placetype":"venue"
},
  "geometry": {"coordinates":[6.8178610802,47.1051673889],"type":"Point"}
}