{
  "type": "Feature",
  "properties": {
    "iso:country":"CH",
    "sg:address":"Dorfstr. 33 8259 Rheinklingen. Postfach",
    "sg:city":"Rheinklingen",
    "sg:orig_category":"Architektur U Ingenieurb\u00fcros",
    "sg:postcode":"8259",
    "sg:province":"Thurgau",
    "wof:name":"Gloor + Winzeler",
    "wof:placetype":"venue"
},
  "geometry": {"coordinates":[8.807396,47.67511],"type":"Point"}
}