{
  "type": "Feature",
  "properties": {
    "iso:country":"CH",
    "sg:address":"Regina Via 3",
    "sg:city":"Vezia",
    "sg:orig_category":"Sonstige mit der Informatik verbundene T\u00e4tigkeiten",
    "sg:phone":"+41 91 950 09 81",
    "sg:postcode":"6943",
    "sg:province":"Ticino",
    "wof:name":"Taddei Giovanni, Consulenze In Sistemi Informativi",
    "wof:placetype":"venue"
},
  "geometry": {"coordinates":[8.9383382797,46.0223731995],"type":"Point"}
}