{
  "type": "Feature",
  "properties": {
    "iso:country":"CH",
    "sg:address":"Tonchet Avenue 32 B",
    "sg:city":"Th\u00f4nex",
    "sg:orig_category":"RESTAURANTS: TEA-ROOMS",
    "sg:postcode":"1226",
    "sg:province":"Gen\u00e8ve",
    "wof:name":"Sdiri Dani\u00e8le",
    "wof:placetype":"venue"
},
  "geometry": {"coordinates":[6.2058300972,46.195640564],"type":"Point"}
}