{
  "type": "Feature",
  "properties": {
    "iso:country":"CH",
    "sg:address":"St. Peterstrasse 17",
    "sg:city":"Z\u00fcrich",
    "sg:orig_category":"Architektur U Ingenieurb\u00fcros",
    "sg:phone":"+41 22 751 09 72",
    "sg:postcode":"8001",
    "sg:province":"Z\u00fcrich",
    "wof:name":"Schenker Claude L.-ing\u00e9nieur Eig-consultant Ing\u00e9nieur, Consultant Pour Techniques Du B\u00e2timents Etc",
    "wof:placetype":"venue"
},
  "geometry": {"coordinates":[6.215185,46.26506],"type":"Point"}
}