{
  "type": "Feature",
  "properties": {
    "iso:country":"CH",
    "sg:address":"5442 Fislisbach. Postfach 2",
    "sg:city":"Fislisbach",
    "sg:orig_category":"Sportvereine Ballsport Fussball",
    "sg:phone":"+41 56 436 63 03",
    "sg:postcode":"5442",
    "sg:province":"Aargau",
    "wof:name":"Fc Fislisbach",
    "wof:placetype":"venue"
},
  "geometry": {"coordinates":[8.2914400101,47.4361915588],"type":"Point"}
}