{
  "type": "Feature",
  "properties": {
    "iso:country":"CH",
    "sg:address":"L\u00f6wenstrasse 61 8001 Z\u00fcrich. Postfach",
    "sg:city":"Z\u00fcrich",
    "sg:orig_category":"Grosshandel mit Foto U Kinoger\u00e4ten, feinmechanischen U optischen Erzeugnissen Interessenvertretungen",
    "sg:phone":"+41 12246677",
    "sg:postcode":"8023",
    "sg:province":"Z\u00fcrich",
    "wof:name":"Interessengemeinschaft Schweizerischer Foto-kino-lieferanten",
    "wof:placetype":"venue"
},
  "geometry": {"coordinates":[8.5380430222,47.3769683838],"type":"Point"}
}