{
  "type": "Feature",
  "properties": {
    "iso:country":"CH",
    "sg:address":"8645",
    "sg:city":"Jona",
    "sg:orig_category":"Schwimmb\u00e4der",
    "sg:phone":"+41 55 210 35 23",
    "sg:postcode":"8645",
    "sg:province":"St. Gallen",
    "wof:name":"Schulhaus Paradies Lenggis Betriebsleitung Schwimmhalle",
    "wof:placetype":"venue"
},
  "geometry": {"coordinates":[8.8452396393,47.2296905518],"type":"Point"}
}