{
  "type": "Feature",
  "properties": {
    "addr:full":"Z.i. Mont-de-faux Villars-ste-croix Vaud 1029",
    "addr:postcode":"1029",
    "addr:street":"Z.I.",
    "iso:country":"CH",
    "sg:address":"Z.i. Mont-de-faux",
    "sg:city":"Villars-ste-croix",
    "sg:classifiers":[
        {
            "category":"Utilities",
            "subcategory":"Cable",
            "type":"Services"
        }
    ],
    "sg:phone":"+41 21 637 37 77",
    "sg:postcode":"1029",
    "sg:province":"Vaud",
    "sg:tags":[
        "conduit",
        "protection"
    ],
    "wof:name":"Canplast Sa",
    "wof:placetype":"venue"
},
  "geometry": {"coordinates":[6.561737,46.568027],"type":"Point"}
}