{
  "type": "Feature",
  "properties": {
    "iso:country":"CH",
    "sg:address":"Hulfteggstrasse 7",
    "sg:city":"Winterthur",
    "sg:orig_category":"Grosshandel mit sonstigen Nahrungsmitteln",
    "sg:phone":"+41 91 827 40 83",
    "sg:postcode":"8400",
    "sg:province":"Z\u00fcrich",
    "wof:name":"Tiefk\u00fchlservice Maggi Attilio",
    "wof:placetype":"venue"
},
  "geometry": {"coordinates":[9.128364563,46.2376060486],"type":"Point"}
}