{
  "type": "Feature",
  "properties": {
    "iso:country":"CH",
    "sg:address":"S\u00e4gegasse 14",
    "sg:city":"Burgdorf",
    "sg:orig_category":"Verbraucherm\u00e4rkte > 2500 m2",
    "sg:phone":"+41 34 422 07 55",
    "sg:postcode":"3400",
    "sg:province":"Bern",
    "wof:name":"Waro Ag",
    "wof:placetype":"venue"
},
  "geometry": {"coordinates":[7.6296868324,47.0570793152],"type":"Point"}
}