{
  "type": "Feature",
  "properties": {
    "iso:country":"CH",
    "sg:address":"Tessenbergstrasse 58",
    "sg:city":"Biel/bienne",
    "sg:orig_category":"Erbringung von sonstigen Dienstleistungen f\u00fcr Unterhaltung, Erholung U Freizeit",
    "sg:phone":"+41 32 725 13 13",
    "sg:postcode":"2505",
    "sg:province":"Bern",
    "wof:name":"Actuel-agency Gmbh",
    "wof:placetype":"venue"
},
  "geometry": {"coordinates":[7.2189297676,47.1306648254],"type":"Point"}
}