{
  "type": "Feature",
  "properties": {
    "iso:country":"CH",
    "sg:address":"Landstrasse 104 9490 Vaduz. Postfach 128",
    "sg:city":"Vaduz",
    "sg:orig_category":"Unternehmensberatung",
    "sg:phone":"+423 232 05 11",
    "sg:postcode":"9490",
    "wof:name":"Audina Treuhand Ag",
    "wof:placetype":"venue"
},
  "geometry": {"coordinates":[9.5114221573,47.1511268616],"type":"Point"}
}