{
  "type": "Feature",
  "properties": {
    "iso:country":"CH",
    "sg:address":"Bahnhofstrasse 20",
    "sg:city":"Krummenau",
    "sg:classifiers":[
        {
            "category":"Restaurant",
            "type":"Food & Drink"
        }
    ],
    "sg:phone":"+41 71 994 10 04",
    "sg:postcode":"9643",
    "sg:province":"St. Gallen",
    "wof:name":"Restaurant Bahnhof",
    "wof:placetype":"venue"
},
  "geometry": {"coordinates":[9.1685037613,47.248260498],"type":"Point"}
}