{
  "type": "Feature",
  "properties": {
    "iso:country":"CH",
    "sg:address":"Wiesenweg 11",
    "sg:city":"Belp",
    "sg:orig_category":"Bau U Wohngenossenschaften",
    "sg:postcode":"3123",
    "sg:province":"Bern",
    "wof:name":"Wohn-& Baugen.wiesenweg",
    "wof:placetype":"venue"
},
  "geometry": {"coordinates":[7.49464,46.897343],"type":"Point"}
}