{
  "type": "Feature",
  "properties": {
    "iso:country":"CH",
    "sg:address":"Fachstrasse 80",
    "sg:city":"Oberrieden",
    "sg:orig_category":"Wirtschaftspr\u00fcfung, Steuerberatung U Treuhand",
    "sg:postcode":"8942",
    "sg:province":"Z\u00fcrich",
    "wof:name":"Cremonini H. & Co",
    "wof:placetype":"venue"
},
  "geometry": {"coordinates":[8.5814685822,47.2723350525],"type":"Point"}
}