{
  "type": "Feature",
  "properties": {
    "iso:country":"CH",
    "sg:address":"Junkholzweg 1",
    "sg:city":"Kaiseraugst",
    "sg:orig_category":"Non-Classified Establishments",
    "sg:phone":"+41 71 911 87 55",
    "sg:postcode":"4303",
    "sg:province":"Aargau",
    "wof:name":"Euro-finanz-holding Ag",
    "wof:placetype":"venue"
},
  "geometry": {"coordinates":[9.0328617096,47.4650878906],"type":"Point"}
}