{
  "type": "Feature",
  "properties": {
    "addr:full":"Feldkircherstrasse 39 Schaan 9494",
    "addr:housenumber":"39",
    "addr:postcode":"9494",
    "addr:street":"Feldkircherstrasse",
    "iso:country":"CH",
    "sg:address":"Feldkircherstrasse 39",
    "sg:city":"Schaan",
    "sg:orig_category":"Architekturb\u00fcros",
    "sg:phone":"+423 232 02 34",
    "sg:postcode":"9494",
    "wof:name":"Willy Marxer Architekturb\u00fcro Ag",
    "wof:placetype":"venue"
},
  "geometry": {"coordinates":[9.514281,47.169434],"type":"Point"}
}