{
  "type": "Feature",
  "properties": {
    "iso:country":"CH",
    "sg:address":"Vogesenstrasse 81",
    "sg:city":"Basel",
    "sg:orig_category":"Geb\u00e4ude, Wohnungsreinigung Teppichreinigung",
    "sg:phone":"+41 27 207 25 14",
    "sg:postcode":"4056",
    "sg:province":"Basel-Stadt",
    "wof:name":"La Main Blanche Entreprise De Nettoyage",
    "wof:placetype":"venue"
},
  "geometry": {"coordinates":[7.3580350876,46.2108764648],"type":"Point"}
}