{
  "type": "Feature",
  "properties": {
    "iso:country":"CH",
    "sg:address":"Industriestrasse 10",
    "sg:city":"B\u00f6singen",
    "sg:orig_category":"Autogaragen",
    "sg:phone":"+41 31 747 91 91",
    "sg:postcode":"3178",
    "sg:province":"Fribourg",
    "wof:name":"Max Etter Garage",
    "wof:placetype":"venue"
},
  "geometry": {"coordinates":[7.229775,46.900913],"type":"Point"}
}