{
  "type": "Feature",
  "properties": {
    "iso:country":"CH",
    "sg:address":"Euggihof 551",
    "sg:city":"Schleitheim",
    "sg:orig_category":"G\u00fcterbef\u00f6rderung im Strassenverkehr",
    "sg:phone":"+41 52 680 21 35",
    "sg:postcode":"8226",
    "sg:province":"Schaffhausen",
    "wof:name":"Wanner Gebr\u00fcder, Transporte",
    "wof:placetype":"venue"
},
  "geometry": {"coordinates":[8.5039930344,47.744354248],"type":"Point"}
}