{
  "type": "Feature",
  "properties": {
    "iso:country":"CH",
    "sg:address":"Im Trichtisal 51",
    "sg:city":"Z\u00fcrich",
    "sg:orig_category":"Allgemeiner Hoch U Tiefbau Vermittlung von Immobilien",
    "sg:phone":"+41 13822021",
    "sg:postcode":"8053",
    "sg:province":"Z\u00fcrich",
    "wof:name":"Geissb\u00fchler Bautreuhand Gmbh",
    "wof:placetype":"venue"
},
  "geometry": {"coordinates":[8.602857,47.354431],"type":"Point"}
}