{
  "type": "Feature",
  "properties": {
    "iso:country":"CH",
    "sg:address":"Bahnweg 4",
    "sg:city":"Urn\u00e4sch",
    "sg:orig_category":"Erschliessung von Grundst\u00fccken",
    "sg:postcode":"9107",
    "sg:province":"Appenzell Ausserrhoden",
    "wof:name":"Baugesellschaft Moos Ag",
    "wof:placetype":"venue"
},
  "geometry": {"coordinates":[9.2857131958,47.317615509],"type":"Point"}
}