{
  "type": "Feature",
  "properties": {
    "iso:country":"CH",
    "sg:address":"Schlachthofstrasse 10 4056 Basel. Postfach",
    "sg:city":"Basel",
    "sg:orig_category":"Vermietung U Verpachtung von eigenen Immobilien",
    "sg:postcode":"4051",
    "sg:province":"Basel-Stadt",
    "wof:name":"Lysb\u00fcchel Verwaltungen Ag Verm\u00f6genswerte Bes. Immobilien; Erwerb, Verwaltung, Realisierung",
    "wof:placetype":"venue"
},
  "geometry": {"coordinates":[7.5715751648,47.5765419006],"type":"Point"}
}