{
  "type": "Feature",
  "properties": {
    "iso:country":"CH",
    "sg:address":"Sonnenstrasse 3",
    "sg:city":"Bischofszell",
    "sg:orig_category":"Herstellung von Konstruktionsteilen, Fertigbauteilen U Ausbauelementen aus Holz Herstellung von Schr",
    "sg:phone":"+41 71 422 40 85",
    "sg:postcode":"9220",
    "sg:province":"Thurgau",
    "wof:name":"Daniel Meier Schreinerarbeiten Gitarrenbau",
    "wof:placetype":"venue"
},
  "geometry": {"coordinates":[9.2390947342,47.4916343689],"type":"Point"}
}