{
  "type": "Feature",
  "properties": {
    "iso:country":"CH",
    "sg:address":"Schaffhauserstrasse 443",
    "sg:city":"Z\u00fcrich",
    "sg:orig_category":"Coiffeursalons U Kosmetikinstitute Kosmetikinstitute",
    "sg:phone":"+41 13027200",
    "sg:postcode":"8050",
    "sg:province":"Z\u00fcrich",
    "wof:name":"Serna Coiffure Gmbh",
    "wof:placetype":"venue"
},
  "geometry": {"coordinates":[8.545237,47.416931],"type":"Point"}
}