{
  "type": "Feature",
  "properties": {
    "iso:country":"CH",
    "sg:address":"3401 Burgdorf. Postfach",
    "sg:city":"Burgdorf",
    "sg:orig_category":"Sportvereine Eissport Eishockey",
    "sg:phone":"+41 34 422 09 63",
    "sg:postcode":"3401",
    "sg:province":"Bern",
    "wof:name":"Eislauf-club Burgdorf",
    "wof:placetype":"venue"
},
  "geometry": {"coordinates":[7.6269898415,47.056438446],"type":"Point"}
}