{
  "type": "Feature",
  "properties": {
    "iso:country":"CH",
    "sg:address":"Oberdorfstrasse 18",
    "sg:city":"Stettlen",
    "sg:orig_category":"Herstellung von keramischen Wand U Bodenfliesen U platten Maurerarbeiten",
    "sg:phone":"+41 79 358 45 44",
    "sg:postcode":"3066",
    "sg:province":"Bern",
    "wof:name":"Jonas Feller Keramische Wand-& Bodenbel\u00e4ge",
    "wof:placetype":"venue"
},
  "geometry": {"coordinates":[7.5258069038,46.9594078064],"type":"Point"}
}