{
  "type": "Feature",
  "properties": {
    "iso:country":"CH",
    "sg:address":"Feldkircherstrasse 33",
    "sg:city":"Schaan",
    "sg:orig_category":"Detailhandel mit Geschenkartikeln U Souvenirs",
    "sg:phone":"+423 232 29 11",
    "sg:postcode":"9494",
    "wof:name":"T\u00f6pferl\u00e4dile C.quaderer",
    "wof:placetype":"venue"
},
  "geometry": {"coordinates":[9.5132341385,47.1688804626],"type":"Point"}
}