{
  "type": "Feature",
  "properties": {
    "iso:country":"CH",
    "sg:address":"Chalet Eden 1937 Orsi\u00e8res. Postfach",
    "sg:city":"Orsi\u00e8res",
    "sg:orig_category":"Interessenvertretungen",
    "sg:postcode":"1937",
    "sg:province":"Valais",
    "wof:name":"E.v.a.t. / Europa Pour La Vie Et Aide Pour Tous Venir En Aide \u00e0 Des Personnes Dans Le Besoin, Plus Particul. \u00e0 Des Handicap\u00e9s Physiques Etc",
    "wof:placetype":"venue"
},
  "geometry": {"coordinates":[7.1462898254,46.0306968689],"type":"Point"}
}