{
  "type": "Feature",
  "properties": {
    "iso:country":"CH",
    "sg:address":"Traubenweg 8",
    "sg:city":"Chur",
    "sg:orig_category":"Innenarchitekturb\u00fcros",
    "sg:phone":"+41 81 353 75 21",
    "sg:postcode":"7000",
    "sg:province":"Graubunden",
    "wof:name":"Janni Weibel Innenarchitektur",
    "wof:placetype":"venue"
},
  "geometry": {"coordinates":[9.5396671295,46.8599357605],"type":"Point"}
}