{
  "type": "Feature",
  "properties": {
    "iso:country":"CH",
    "sg:address":"Langwattstrasse 46",
    "sg:city":"Zollikerberg",
    "sg:orig_category":"Vorschulen, Kinderg\u00e4rten",
    "sg:phone":"+41 55 246 30 91",
    "sg:postcode":"8125",
    "sg:province":"Z\u00fcrich",
    "wof:name":"Kindergarten Laupen",
    "wof:placetype":"venue"
},
  "geometry": {"coordinates":[8.9313602448,47.2676391602],"type":"Point"}
}