{
  "type": "Feature",
  "properties": {
    "iso:country":"CH",
    "sg:address":"Montagny-les-monts",
    "sg:city":"Cousset",
    "sg:orig_category":"Herstellung von Konstruktionsteilen, Fertigbauteilen U Ausbauelementen aus Holz",
    "sg:postcode":"1774",
    "sg:province":"Fribourg",
    "wof:name":"Rapin Plafonds Suspendus",
    "wof:placetype":"venue"
},
  "geometry": {"coordinates":[6.9772849083,46.8183364868],"type":"Point"}
}