{
  "type": "Feature",
  "properties": {
    "iso:country":"CH",
    "sg:address":"Route D'oron 2 1010 Lausanne Case Postale 167",
    "sg:city":"Lausanne",
    "sg:orig_category":"Wirtschaftspr\u00fcfung, Steuerberatung U Treuhand",
    "sg:phone":"+41 21 651 06 06",
    "sg:postcode":"1010",
    "sg:province":"Vaud",
    "wof:name":"Fiduciaire Corola Sa",
    "wof:placetype":"venue"
},
  "geometry": {"coordinates":[6.6660060883,46.5069389343],"type":"Point"}
}