{
  "type": "Feature",
  "properties": {
    "iso:country":"CH",
    "sg:address":"Ifangweg 2",
    "sg:city":"Uster",
    "sg:orig_category":"Sanit\u00e4r, Heizungs U L\u00fcftungsinstallation Sanit\u00e4rinstallation",
    "sg:phone":"+41 19415355",
    "sg:postcode":"8610",
    "sg:province":"Z\u00fcrich",
    "wof:name":"Markus Ott Sanit\u00e4r-reparatur-service",
    "wof:placetype":"venue"
},
  "geometry": {"coordinates":[8.7135677338,47.3583488464],"type":"Point"}
}