{
  "type": "Feature",
  "properties": {
    "addr:full":"Rue De Romont 33 Fribourg Fribourg 1700",
    "addr:housenumber":"33",
    "addr:postcode":"1700",
    "addr:street":"Rue De Romont",
    "iso:country":"CH",
    "sg:address":"Rue De Romont 33",
    "sg:city":"Fribourg",
    "sg:orig_category":"Detailhandel mit Damenbekleidung Detailhandel mit Herrenbekleidung",
    "sg:phone":"+41 26 341 77 88",
    "sg:postcode":"1700",
    "sg:province":"Fribourg",
    "wof:name":"Ang\u00e9loz Mode Sa Mode Masculine & F\u00e9minine",
    "wof:placetype":"venue"
},
  "geometry": {"coordinates":[7.154137,46.80444],"type":"Point"}
}