{
  "type": "Feature",
  "properties": {
    "iso:country":"CH",
    "sg:address":"Unterdorf 6277 Kleinwangen. Postfach",
    "sg:city":"Kleinwangen",
    "sg:orig_category":"Wasserversorgung",
    "sg:postcode":"6277",
    "sg:province":"Luzern",
    "wof:name":"Wasserversorgungsgenossenschaft Kleinwangen",
    "wof:placetype":"venue"
},
  "geometry": {"coordinates":[8.2985229492,47.2076644897],"type":"Point"}
}