{
  "type": "Feature",
  "properties": {
    "iso:country":"CH",
    "sg:address":"L\u00f6wenplatz 5 4222 Zwingen. Postfach",
    "sg:city":"Zwingen",
    "sg:orig_category":"Erzeugung U Erstbearbeitung von Aluminium Grosshandel mit Baumaterialien",
    "sg:phone":"+41 61 763 08 77",
    "sg:postcode":"4222",
    "sg:province":"Basel-Landschaft",
    "wof:name":"Alu-plan Gmbh Hochwertige Bauprodukte, Bes. Aluminium-sockelprofile; Handel Usw",
    "wof:placetype":"venue"
},
  "geometry": {"coordinates":[7.5301060677,47.4382858276],"type":"Point"}
}