{
  "type": "Feature",
  "properties": {
    "iso:country":"CH",
    "sg:address":"Weinfelderstrasse 59a",
    "sg:city":"Amriswil",
    "sg:orig_category":"Vereine Gesang",
    "sg:phone":"+41 71 411 11 78",
    "sg:postcode":"8580",
    "sg:province":"Thurgau",
    "wof:name":"M\u00e4nnerchor Hemmerswil",
    "wof:placetype":"venue"
},
  "geometry": {"coordinates":[9.2867107391,47.5442810059],"type":"Point"}
}