{
  "type": "Feature",
  "properties": {
    "iso:country":"CH",
    "sg:address":"Hintermattstrasse 4",
    "sg:city":"Ziefen",
    "sg:orig_category":"Fachdetailhandel mit pharmazeutischen Produkten Grosshandel mit pharmazeutischen Erzeugnissen",
    "sg:phone":"+41 61 931 46 31",
    "sg:postcode":"4417",
    "sg:province":"Basel-Landschaft",
    "wof:name":"Curano-service Gmbh",
    "wof:placetype":"venue"
},
  "geometry": {"coordinates":[7.7036108971,47.4323654175],"type":"Point"}
}