{
  "type": "Feature",
  "properties": {
    "iso:country":"CH",
    "sg:address":"Gottlieberstrasse 5 8274 T\u00e4gerwilen. Postfach",
    "sg:city":"T\u00e4gerwilen",
    "sg:orig_category":"RESTAURANTS: TEA-ROOMS",
    "sg:phone":"+41 71 669 11 17",
    "sg:postcode":"8274",
    "sg:province":"Thurgau",
    "wof:name":"Restaurant Ochsen B\u00fcrgi Ernst",
    "wof:placetype":"venue"
},
  "geometry": {"coordinates":[9.1354503632,47.6597671509],"type":"Point"}
}