{
  "type": "Feature",
  "properties": {
    "iso:country":"CH",
    "sg:address":"Camara Via 46",
    "sg:city":"Breganzona",
    "sg:orig_category":"Herstellung von sonstigen keramischen Erzeugnissen f\u00fcr technische Zwecke",
    "sg:phone":"+41 91 967 38 55",
    "sg:postcode":"6932",
    "sg:province":"Ticino",
    "wof:name":"Ceramex Di Francesco Fabris",
    "wof:placetype":"venue"
},
  "geometry": {"coordinates":[8.9302215576,46.011428833],"type":"Point"}
}