{
  "type": "Feature",
  "properties": {
    "iso:country":"CH",
    "sg:address":"Chemin De Fontadel 33 1008 Prilly Case Postale 59",
    "sg:city":"Prilly",
    "sg:orig_category":"Fachdetailhandel in Verkaufsr\u00e4umen",
    "sg:phone":"+41 21 625 84 83",
    "sg:postcode":"1008",
    "sg:province":"Vaud",
    "wof:name":"Baur Pierre",
    "wof:placetype":"venue"
},
  "geometry": {"coordinates":[6.6079311371,46.5371665955],"type":"Point"}
}