{
  "type": "Feature",
  "properties": {
    "iso:country":"CH",
    "sg:address":"Route De Bertigny 22",
    "sg:city":"Fribourg",
    "sg:orig_category":"Detailhandel mit B\u00fcchern, Zeitungen, Schreib U Papeteriewaren",
    "sg:postcode":"1700",
    "sg:province":"Fribourg",
    "wof:name":"Papeterie - Bricolage - Cadeaux, Muller Jean",
    "wof:placetype":"venue"
},
  "geometry": {"coordinates":[7.141971,46.802101],"type":"Point"}
}