{
  "type": "Feature",
  "properties": {
    "iso:country":"CH",
    "sg:address":"Industriestrasse 130 4600 Olten. Postfach",
    "sg:city":"Olten",
    "sg:orig_category":"Grosshandel mit Erzen U Metallen Herstellung von Armaturen",
    "sg:phone":"+41 62 287 60 60",
    "sg:postcode":"4601",
    "sg:province":"Solothurn",
    "wof:name":"Hipreco Ag",
    "wof:placetype":"venue"
},
  "geometry": {"coordinates":[7.9149250984,47.3623924255],"type":"Point"}
}