{
  "type": "Feature",
  "properties": {
    "iso:country":"CH",
    "sg:address":"Via Manzoni 19",
    "sg:city":"Mendrisio",
    "sg:orig_category":"Herstellung von Teppichen Verlegen von Fliesen U Platten",
    "sg:phone":"+41 26 652 30 73",
    "sg:postcode":"6850",
    "sg:province":"Ticino",
    "wof:name":"Charles Grosset Entreprise De Carrelage",
    "wof:placetype":"venue"
},
  "geometry": {"coordinates":[6.9065208435,46.6968688965],"type":"Point"}
}