{
  "type": "Feature",
  "properties": {
    "iso:country":"CH",
    "sg:address":"Le Rendez-vous Rue Centrale 1564 Domdidier. Postfach",
    "sg:city":"Domdidier",
    "sg:orig_category":"RESTAURANTS: TEA-ROOMS",
    "sg:postcode":"1564",
    "sg:province":"Fribourg",
    "wof:name":"Chardonnens Carmen S\u00e0rl",
    "wof:placetype":"venue"
},
  "geometry": {"coordinates":[7.0151348114,46.8653068542],"type":"Point"}
}