{
  "type": "Feature",
  "properties": {
    "iso:country":"CH",
    "sg:address":"7530",
    "sg:city":"Zernez",
    "sg:orig_category":"Primarschulen",
    "sg:phone":"+41 81 856 13 50",
    "sg:postcode":"7530",
    "sg:province":"Graubunden",
    "wof:name":"Primarschule",
    "wof:placetype":"venue"
},
  "geometry": {"coordinates":[10.0946302414,46.7002983093],"type":"Point"}
}