{
  "type": "Feature",
  "properties": {
    "iso:country":"CH",
    "sg:address":"Taux Chemin Du 5 1820 Montreux. Postfach",
    "sg:city":"Corseaux",
    "sg:orig_category":"Herstellung von k\u00e4lte U lufttechnischen Erzeugnissen f\u00fcr gewerbliche Zwecke",
    "sg:postcode":"1802",
    "sg:province":"Vaud",
    "wof:name":"Mab Ing\u00e9nieur Conseils, Marcel-alain Berset",
    "wof:placetype":"venue"
},
  "geometry": {"coordinates":[7.1649050713,46.7464141846],"type":"Point"}
}