{
  "type": "Feature",
  "properties": {
    "iso:country":"CH",
    "sg:address":"Rue D'etraz 5",
    "sg:city":"Montreux",
    "sg:orig_category":"Vorschulen, Kinderg\u00e4rten",
    "sg:phone":"+41 32 913 73 52",
    "sg:postcode":"1820",
    "sg:province":"Vaud",
    "wof:name":"Ecole Enfantine Ferme-gallet",
    "wof:placetype":"venue"
},
  "geometry": {"coordinates":[6.8269748688,47.0968704224],"type":"Point"}
}