{
  "type": "Feature",
  "properties": {
    "iso:country":"CH",
    "sg:address":"M\u00e4tteli 165",
    "sg:city":"Olsberg",
    "sg:orig_category":"Non-Classified Establishments",
    "sg:postcode":"4305",
    "sg:province":"Aargau",
    "wof:name":"Elektra Roggwil",
    "wof:placetype":"venue"
},
  "geometry": {"coordinates":[9.3965301514,47.5006713867],"type":"Point"}
}