{
  "type": "Feature",
  "properties": {
    "iso:country":"CH",
    "sg:address":"Hinterdorfstrasse 11",
    "sg:city":"Truttikon",
    "sg:orig_category":"Allgemeiner Hochbau Herstellung von Metallkonstruktionen",
    "sg:phone":"+41 79 697 26 77",
    "sg:postcode":"8467",
    "sg:province":"Z\u00fcrich",
    "wof:name":"Stamm Fassadenbau Ag",
    "wof:placetype":"venue"
},
  "geometry": {"coordinates":[9.566731,47.320259],"type":"Point"}
}