{
  "type": "Feature",
  "properties": {
    "iso:country":"CH",
    "sg:address":"Waldsiedlung 6",
    "sg:city":"Balterswil",
    "sg:orig_category":"Wohnheime f\u00fcr Kinder U Jugendliche",
    "sg:phone":"+41 55 246 34 01",
    "sg:postcode":"8362",
    "sg:province":"Thurgau",
    "wof:name":"Pfadiheim Hischwil",
    "wof:placetype":"venue"
},
  "geometry": {"coordinates":[8.9134502411,47.2743301392],"type":"Point"}
}