{
  "type": "Feature",
  "properties": {
    "iso:country":"CH",
    "sg:address":"Via Alla Chiesa",
    "sg:city":"Melano",
    "sg:orig_category":"Unclassifiable Establishments",
    "sg:postcode":"6818",
    "sg:province":"Ticino",
    "wof:name":"Idm Immobiliare Di Melano Sa",
    "wof:placetype":"venue"
},
  "geometry": {"coordinates":[8.9861249924,45.919128418],"type":"Point"}
}