{
  "type": "Feature",
  "properties": {
    "iso:country":"CH",
    "sg:address":"Im Ifang 6",
    "sg:city":"Effretikon",
    "sg:orig_category":"Unclassifiable Establishments",
    "sg:postcode":"8307",
    "sg:province":"Z\u00fcrich",
    "wof:name":"Liwatec Ag",
    "wof:placetype":"venue"
},
  "geometry": {"coordinates":[8.6892929077,47.4312133789],"type":"Point"}
}