{
  "type": "Feature",
  "properties": {
    "iso:country":"CH",
    "sg:address":"5224 Unterb\u00f6zberg. Postfach 2",
    "sg:city":"Unterb\u00f6zberg",
    "sg:orig_category":"Unternehmensberatung",
    "sg:phone":"+41 56 483 02 20",
    "sg:postcode":"5224",
    "sg:province":"Aargau",
    "wof:name":"Saracus Consulting Ag",
    "wof:placetype":"venue"
},
  "geometry": {"coordinates":[8.2927656174,47.4490814209],"type":"Point"}
}