{
  "type": "Feature",
  "properties": {
    "iso:country":"CH",
    "sg:address":"Rishaldenweg 61",
    "sg:city":"Rothrist",
    "sg:orig_category":"Grosshandel mit Datenverarbeitungsger\u00e4ten Hardwareberatung",
    "sg:phone":"+41 62 794 57 27",
    "sg:postcode":"4852",
    "sg:province":"Aargau",
    "wof:name":"Mbs Multimedia & Business Systems, Brand R.",
    "wof:placetype":"venue"
},
  "geometry": {"coordinates":[7.8888092041,47.3095588684],"type":"Point"}
}