{
  "type": "Feature",
  "properties": {
    "iso:country":"CH",
    "sg:address":"Chemin Des Rochettes 50",
    "sg:city":"St-blaise",
    "sg:orig_category":"Instandhaltung U Reparatur von Automobilen",
    "sg:phone":"+41 32 753 10 32",
    "sg:postcode":"2072",
    "sg:province":"Neuch\u00e2tel",
    "wof:name":"Fritz Winkler Auto-\u00e9lectro-service",
    "wof:placetype":"venue"
},
  "geometry": {"coordinates":[6.988093853,47.0214004517],"type":"Point"}
}