{
  "type": "Feature",
  "properties": {
    "iso:country":"CH",
    "sg:address":"Adlerstrasse 21",
    "sg:city":"Basel",
    "sg:orig_category":"Sportvereine Alpinismus Sportvereine Ski",
    "sg:phone":"+41 61 313 39 55",
    "sg:postcode":"4052",
    "sg:province":"Basel-Stadt",
    "wof:name":"Ski-& Alpenclub Schneest\u00e4rn",
    "wof:placetype":"venue"
},
  "geometry": {"coordinates":[7.6105418205,47.5468101501],"type":"Point"}
}