{
  "type": "Feature",
  "properties": {
    "iso:country":"CH",
    "sg:address":"Piazzetta S. Carlo 2",
    "sg:city":"Lugano",
    "sg:orig_category":"Aktivit\u00e4t der Bankinstitute",
    "sg:phone":"+41 91 922 26 21",
    "sg:postcode":"6900",
    "sg:province":"Ticino",
    "wof:name":"Bank Maerki Baumann & Co Ag",
    "wof:placetype":"venue"
},
  "geometry": {"coordinates":[8.949938,46.003124],"type":"Point"}
}