{
  "type": "Feature",
  "properties": {
    "iso:country":"CH",
    "sg:address":"Allschwilerstrasse 119 4055 Basel. Postfach",
    "sg:city":"Basel",
    "sg:orig_category":"Unclassifiable Establishments",
    "sg:phone":"+41 61 302 88 88",
    "sg:postcode":"4055",
    "sg:province":"Basel-Stadt",
    "wof:name":"Cofa Facqueur & Co. Gmbh B\u00fcromaschinen, B\u00fcrozubeh\u00f6r U. B\u00fcromaterial; Handel Usw",
    "wof:placetype":"venue"
},
  "geometry": {"coordinates":[7.5665421486,47.5570755005],"type":"Point"}
}