{
  "type": "Feature",
  "properties": {
    "iso:country":"CH",
    "sg:address":"Grimselstrasse",
    "sg:city":"Innertkirchen",
    "sg:orig_category":"Landesverteidigung, Sozialversicherung \u00d6ffentliche Verwaltung",
    "sg:phone":"+41 33 971 10 14",
    "sg:postcode":"3862",
    "sg:province":"Bern",
    "wof:name":"Zivilschutzstelle Innertkirchen",
    "wof:placetype":"venue"
},
  "geometry": {"coordinates":[8.2321052551,46.7014389038],"type":"Point"}
}