{
  "type": "Feature",
  "properties": {
    "addr:full":"Rosenmattstrasse 17 4133 Pratteln. Postfach Pratteln Basel-Landschaft 4133",
    "addr:housenumber":"17",
    "addr:postcode":"4133 pratteln. postfach;4133",
    "addr:street":"Rosenmattstrasse",
    "iso:country":"CH",
    "sg:address":"Rosenmattstrasse 17 4133 Pratteln. Postfach",
    "sg:city":"Pratteln",
    "sg:orig_category":"Architektur U Ingenieurb\u00fcros",
    "sg:phone":"+41 61 821 30 29",
    "sg:postcode":"4133",
    "sg:province":"Basel-Landschaft",
    "wof:name":"Techn. Zeichnungsb\u00fcro, M. Bettina Siegenthaler Svaizer",
    "wof:placetype":"venue"
},
  "geometry": {"coordinates":[7.688021,47.517635],"type":"Point"}
}