{
  "type": "Feature",
  "properties": {
    "iso:country":"CH",
    "sg:address":"Lettenstrasse 7",
    "sg:city":"Rotkreuz",
    "sg:orig_category":"Unclassifiable Establishments",
    "sg:postcode":"6343",
    "sg:province":"Zug",
    "wof:name":"Galypso Ag",
    "wof:placetype":"venue"
},
  "geometry": {"coordinates":[8.4318199158,47.1470794678],"type":"Point"}
}