{
  "type": "Feature",
  "properties": {
    "iso:country":"CH",
    "sg:address":"8424",
    "sg:city":"Embrach",
    "sg:orig_category":"Vereine Abstinenten",
    "sg:postcode":"8424",
    "sg:province":"Z\u00fcrich",
    "wof:name":"Blaues Kreuz",
    "wof:placetype":"venue"
},
  "geometry": {"coordinates":[8.5988798141,47.5108795166],"type":"Point"}
}