{
  "type": "Feature",
  "properties": {
    "iso:country":"CH",
    "sg:address":"Hinter-bramberg 4",
    "sg:city":"Luzern",
    "sg:orig_category":"Fotografische Ateliers Fotografisches Gewerbe U fotografische Laboratorien",
    "sg:phone":"+41 41 410 91 86",
    "sg:postcode":"6004",
    "sg:province":"Luzern",
    "wof:name":"Foto Pelikan Renggli J.",
    "wof:placetype":"venue"
},
  "geometry": {"coordinates":[8.3020505905,47.0579872131],"type":"Point"}
}