{
  "type": "Feature",
  "properties": {
    "iso:country":"CH",
    "sg:address":"Place Dufour 1 1110 Morges Case Postale 539",
    "sg:city":"Morges",
    "sg:orig_category":"Vermietung U Verpachtung von eigenen Immobilien Vermittlung von Immobilien",
    "sg:phone":"+41 21 801 14 15",
    "sg:postcode":"1110",
    "sg:province":"Vaud",
    "wof:name":"G\u00e9rances De Luze Sa",
    "wof:placetype":"venue"
},
  "geometry": {"coordinates":[6.4964389801,46.5076713562],"type":"Point"}
}