{
  "type": "Feature",
  "properties": {
    "iso:country":"CH",
    "sg:address":"7554",
    "sg:city":"Sent",
    "sg:orig_category":"Vorschulen, Kinderg\u00e4rten",
    "sg:phone":"+41 81 864 00 49",
    "sg:postcode":"7554",
    "sg:province":"Graubunden",
    "wof:name":"Kindergarten",
    "wof:placetype":"venue"
},
  "geometry": {"coordinates":[10.3378353119,46.8167915344],"type":"Point"}
}