{
  "type": "Feature",
  "properties": {
    "iso:country":"CH",
    "sg:address":"Lachmattstrasse 69",
    "sg:city":"Muttenz",
    "sg:orig_category":"Handelsvermittlung von Brennstoffen, Erzen, Metallen U Chemikalien",
    "sg:phone":"+41 61 463 84 64",
    "sg:postcode":"4132",
    "sg:province":"Basel-Landschaft",
    "wof:name":"Mohamed Chine Chine Pharma Mohamed Chine",
    "wof:placetype":"venue"
},
  "geometry": {"coordinates":[7.6576108932,47.5245246887],"type":"Point"}
}