{
  "type": "Feature",
  "properties": {
    "iso:country":"CH",
    "sg:address":"Pulverm\u00fchlestrasse 12",
    "sg:city":"Chur",
    "sg:orig_category":"Handels-H\u00e4user U Gesellschaften",
    "sg:postcode":"7000",
    "sg:province":"Graubunden",
    "wof:name":"Sipo Handelsgesellschaft Mbh & Co Import-export Kg, In Emmendingen. Zweigniederlassung Davos",
    "wof:placetype":"venue"
},
  "geometry": {"coordinates":[9.8209161758,46.7938766479],"type":"Point"}
}