{
  "type": "Feature",
  "properties": {
    "iso:country":"CH",
    "sg:address":"Winkelgasse 1 4512 Bellach. Postfach",
    "sg:city":"Bellach",
    "sg:orig_category":"Chemin\u00e9e- and Ofenbau",
    "sg:phone":"+41 32 617 40 10",
    "sg:postcode":"4512",
    "sg:province":"Solothurn",
    "wof:name":"Hans Odermatt Ag Ofen-& Chemin\u00e9ebau",
    "wof:placetype":"venue"
},
  "geometry": {"coordinates":[7.492828,47.212597],"type":"Point"}
}