{
  "type": "Feature",
  "properties": {
    "iso:country":"CH",
    "sg:address":"Zollhausstrasse 62b",
    "sg:city":"Biel/bienne",
    "sg:orig_category":"Politische Parteien Gr\u00fcne Partei",
    "sg:phone":"+41 61 422 05 06",
    "sg:postcode":"2504",
    "sg:province":"Bern",
    "wof:name":"Freie Gr\u00fcne Liste Bl",
    "wof:placetype":"venue"
},
  "geometry": {"coordinates":[7.5752072334,47.5391159058],"type":"Point"}
}