{
  "type": "Feature",
  "properties": {
    "iso:country":"CH",
    "sg:address":"Gotthardstrasse 29 8800 Thalwil. Postfach 1329",
    "sg:city":"Thalwil",
    "sg:orig_category":"Grosshandel mit keramischen Erzeugnissen, Glaswaren U Reinigungsmitteln",
    "sg:phone":"+41 17202862",
    "sg:postcode":"8800",
    "sg:province":"Z\u00fcrich",
    "wof:name":"M\u00fcller Max Ag",
    "wof:placetype":"venue"
},
  "geometry": {"coordinates":[8.5632276535,47.2959594727],"type":"Point"}
}