{
  "type": "Feature",
  "properties": {
    "iso:country":"CH",
    "sg:address":"Muhlernstrasse 443",
    "sg:city":"Gasel",
    "sg:classifiers":[
        {
            "category":"Manufacturing",
            "subcategory":"Signs",
            "type":"Manufacturing & Wholesale Goods"
        }
    ],
    "sg:phone":"+41 31 849 15 84",
    "sg:postcode":"3144",
    "sg:province":"Bern",
    "sg:tags":[
        "aluminium"
    ],
    "wof:name":"Kohli Ag",
    "wof:placetype":"venue"
},
  "geometry": {"coordinates":[7.401854,46.899948],"type":"Point"}
}