{
  "type": "Feature",
  "properties": {
    "addr:full":"Bahnhofplatz 1 Z\u00fcrich Z\u00fcrich 8001",
    "addr:housenumber":"1",
    "addr:postcode":"8001",
    "addr:street":"Bahnhofplatz",
    "iso:country":"CH",
    "sg:address":"Bahnhofplatz 1",
    "sg:city":"Z\u00fcrich",
    "sg:classifiers":[
        {
            "category":"Banks & Credit Unions",
            "subcategory":"Bank",
            "type":"Services"
        }
    ],
    "sg:phone":"+41 12195111",
    "sg:postcode":"8001",
    "sg:province":"Z\u00fcrich",
    "wof:name":"Bank Of Tokyo (schweiz) Sa",
    "wof:placetype":"venue"
},
  "geometry": {"coordinates":[8.541209,47.376812],"type":"Point"}
}