{
  "type": "Feature",
  "properties": {
    "iso:country":"CH",
    "sg:address":"Piazza Concordia 2",
    "sg:city":"Verscio",
    "sg:orig_category":"Nationale Postdienste",
    "sg:phone":"+41 91 796 11 59",
    "sg:postcode":"6653",
    "sg:province":"Ticino",
    "wof:name":"La Posta Svizzera",
    "wof:placetype":"venue"
},
  "geometry": {"coordinates":[8.7313642502,46.1861305237],"type":"Point"}
}