{
  "type": "Feature",
  "properties": {
    "iso:country":"CH",
    "sg:address":"Mugerenstrasse 66",
    "sg:city":"Cham",
    "sg:orig_category":"Non-Classified Establishments",
    "sg:postcode":"6330",
    "sg:province":"Zug",
    "wof:name":"Hartman Consulting",
    "wof:placetype":"venue"
},
  "geometry": {"coordinates":[8.4676933289,47.1850891113],"type":"Point"}
}