{
  "type": "Feature",
  "properties": {
    "addr:full":"Schnurrenm\u00fchle 127 Rossh\u00e4usern Bern 3204",
    "addr:housenumber":"127",
    "addr:postcode":"3204",
    "addr:street":"Rosshaeusern Bern",
    "iso:country":"CH",
    "sg:address":"Schnurrenm\u00fchle 127",
    "sg:city":"Rossh\u00e4usern",
    "sg:orig_category":"Allgemeiner Gartenbau Landschaftsplanungsb\u00fcros U Gartenarchitekturb\u00fcros",
    "sg:phone":"+41 31 751 22 89",
    "sg:postcode":"3204",
    "sg:province":"Bern",
    "wof:name":"Ren\u00e9 & Rosmarie Jakob Baumpflege & Gartengestaltung",
    "wof:placetype":"venue"
},
  "geometry": {"coordinates":[7.268981,46.919567],"type":"Point"}
}