{
  "type": "Feature",
  "properties": {
    "iso:country":"CH",
    "sg:address":"L\u00e4ttichstrasse 11",
    "sg:city":"Baar",
    "sg:orig_category":"Softwareentwicklung U beratung",
    "sg:phone":"+41 64247470",
    "sg:postcode":"6340",
    "sg:province":"Zug",
    "wof:name":"Ardutech Software Engineering Consultancy Asec Dutt A.",
    "wof:placetype":"venue"
},
  "geometry": {"coordinates":[8.5379686356,47.199672699],"type":"Point"}
}