{
  "type": "Feature",
  "properties": {
    "iso:country":"CH",
    "sg:address":"Rue De La Paix 14",
    "sg:city":"Tramelan",
    "sg:orig_category":"Zahnarztpraxen",
    "sg:phone":"+41 32 487 44 17",
    "sg:postcode":"2720",
    "sg:province":"Bern",
    "wof:name":"Dr M\u00e9d. Dent. Andrew Keene M\u00e9decin-dentiste",
    "wof:placetype":"venue"
},
  "geometry": {"coordinates":[7.1017971039,47.2240905762],"type":"Point"}
}