{
  "type": "Feature",
  "properties": {
    "iso:country":"CH",
    "sg:address":"3053",
    "sg:city":"M\u00fcnchenbuchsee",
    "sg:classifiers":[
        {
            "category":"Restaurant",
            "type":"Food & Drink"
        }
    ],
    "sg:phone":"+41 31 869 02 94",
    "sg:postcode":"3053",
    "sg:province":"Bern",
    "wof:name":"Restaurant Sch\u00f6nbrunnen",
    "wof:placetype":"venue"
},
  "geometry": {"coordinates":[7.4505391121,47.0214271545],"type":"Point"}
}