{
  "type": "Feature",
  "properties": {
    "iso:country":"CH",
    "sg:address":"Route Des Vuarennes",
    "sg:city":"Granges-marnand",
    "sg:orig_category":"Instandhaltung U Reparatur von Automobilen",
    "sg:postcode":"1523",
    "sg:province":"Vaud",
    "wof:name":"Carrosserie Azur, Chautemps Laurent",
    "wof:placetype":"venue"
},
  "geometry": {"coordinates":[6.8825349808,46.7560386658],"type":"Point"}
}