{
  "type": "Feature",
  "properties": {
    "iso:country":"CH",
    "sg:address":"Bahnhofstrasse 7 8942 Oberrieden. Postfach",
    "sg:city":"Oberrieden",
    "sg:orig_category":"Grosshandel mit Textilien",
    "sg:postcode":"8942",
    "sg:province":"Z\u00fcrich",
    "wof:name":"Vogex Fashion Ag",
    "wof:placetype":"venue"
},
  "geometry": {"coordinates":[8.5804815292,47.2776489258],"type":"Point"}
}