{
  "type": "Feature",
  "properties": {
    "iso:country":"CH",
    "sg:address":"Meierhofstrasse 5",
    "sg:city":"Vaduz",
    "sg:orig_category":"Wett U Lotteriewesen",
    "sg:phone":"+423 237 50 20",
    "sg:postcode":"9490",
    "wof:name":"Interlotto",
    "wof:placetype":"venue"
},
  "geometry": {"coordinates":[9.5242891312,47.1283531189],"type":"Point"}
}