{
  "type": "Feature",
  "properties": {
    "iso:country":"CH",
    "sg:address":"Avenue Ernest-pictet 38",
    "sg:city":"Gen\u00e8ve",
    "sg:orig_category":"Oberfl\u00e4chenveredlung U W\u00e4rmebehandlung",
    "sg:phone":"+41 22 345 03 20",
    "sg:postcode":"1203",
    "sg:province":"Gen\u00e8ve",
    "wof:name":"Estrell Email, Serniguet J.-j.",
    "wof:placetype":"venue"
},
  "geometry": {"coordinates":[6.1232857704,46.2132644653],"type":"Point"}
}