{
  "type": "Feature",
  "properties": {
    "iso:country":"CH",
    "sg:address":"8810",
    "sg:city":"Horgen",
    "sg:orig_category":"Schwimmb\u00e4der",
    "sg:phone":"+41 17257318",
    "sg:postcode":"8810",
    "sg:province":"Z\u00fcrich",
    "wof:name":"Schulhaus Bergli Kleinschwimmhalle",
    "wof:placetype":"venue"
},
  "geometry": {"coordinates":[8.6040897369,47.249420166],"type":"Point"}
}