{
  "type": "Feature",
  "properties": {
    "iso:country":"CH",
    "sg:address":"Nebikerstrsse 58 6247 Sch\u00f6tz. Postfach 136",
    "sg:city":"Sch\u00f6tz",
    "sg:orig_category":"Herstellung von elektrischen Lampen U Leuchten",
    "sg:phone":"+41 41 982 05 50",
    "sg:postcode":"6247",
    "sg:province":"Luzern",
    "wof:name":"Kruwill Beleuchtungen",
    "wof:placetype":"venue"
},
  "geometry": {"coordinates":[7.9853811264,47.1780281067],"type":"Point"}
}