{
  "type": "Feature",
  "properties": {
    "iso:country":"CH",
    "sg:address":"Rue De L'avenir 12",
    "sg:city":"Del\u00e9mont",
    "sg:orig_category":"Unternehmensberatung Wirtschaftspr\u00fcfung, Steuerberatung U Treuhand",
    "sg:phone":"+41 32 422 10 74",
    "sg:postcode":"2800",
    "sg:province":"Jura",
    "wof:name":"Sofirom Soci\u00e9t\u00e9 Fiduciaire",
    "wof:placetype":"venue"
},
  "geometry": {"coordinates":[7.3490409851,47.3645515442],"type":"Point"}
}