{
  "type": "Feature",
  "properties": {
    "addr:full":"Oerlikonerstrasse 88 Z\u00fcrich Z\u00fcrich 8057",
    "addr:housenumber":"88",
    "addr:postcode":"8057",
    "addr:street":"Oerlikonerstrasse",
    "iso:country":"CH",
    "sg:address":"Oerlikonerstrasse 88",
    "sg:city":"Z\u00fcrich",
    "sg:orig_category":"Architektur U Ingenieurb\u00fcros Softwareentwicklung U beratung",
    "sg:phone":"+41 13101155",
    "sg:postcode":"8057",
    "sg:province":"Z\u00fcrich",
    "wof:name":"S\u00e4gesser Engineering Z\u00fcrich",
    "wof:placetype":"venue"
},
  "geometry": {"coordinates":[8.546589,47.405033],"type":"Point"}
}