{
  "type": "Feature",
  "properties": {
    "iso:country":"CH",
    "sg:address":"Emmentalstrasse 14",
    "sg:city":"Konolfingen",
    "sg:orig_category":"Organisationen der Wohlfahrtspflege",
    "sg:phone":"+41 31 791 16 48",
    "sg:postcode":"3510",
    "sg:province":"Bern",
    "wof:name":"Pro Juventute Bezirk Konolfingen",
    "wof:placetype":"venue"
},
  "geometry": {"coordinates":[7.6231417656,46.879699707],"type":"Point"}
}