{
  "type": "Feature",
  "properties": {
    "iso:country":"CH",
    "sg:address":"G\u00fctschh\u00f6he 4",
    "sg:city":"Ballwil",
    "sg:orig_category":"Haltung von Schweinen",
    "sg:phone":"+41 71 393 65 03",
    "sg:postcode":"6275",
    "sg:province":"Luzern",
    "wof:name":"Walter Bucher Schweinezucht",
    "wof:placetype":"venue"
},
  "geometry": {"coordinates":[9.2117004395,47.4424667358],"type":"Point"}
}