{
  "type": "Feature",
  "properties": {
    "addr:full":"Kirschgartenweg 32 Lupsingen Basel-Landschaft 4419",
    "addr:housenumber":"32",
    "addr:postcode":"4419",
    "addr:street":"Kirschgartenweg",
    "iso:country":"CH",
    "sg:address":"Kirschgartenweg 32",
    "sg:city":"Lupsingen",
    "sg:orig_category":"Allgemeiner Hoch U Tiefbau",
    "sg:phone":"+41 61 931 16 17",
    "sg:postcode":"4419",
    "sg:province":"Basel-Landschaft",
    "wof:name":"Kiefer + Cie Bau-sanierungs-technik",
    "wof:placetype":"venue"
},
  "geometry": {"coordinates":[7.694212,47.448963],"type":"Point"}
}