{
  "type": "Feature",
  "properties": {
    "iso:country":"CH",
    "sg:address":"Geissburghalde 10a",
    "sg:city":"Willisau",
    "sg:orig_category":"Unternehmensberatung",
    "sg:phone":"+41 41 971 00 41",
    "sg:postcode":"6130",
    "sg:province":"Luzern",
    "wof:name":"Amrein Consulting + Finanz Ag",
    "wof:placetype":"venue"
},
  "geometry": {"coordinates":[7.9860610962,47.1179847717],"type":"Point"}
}