{
  "type": "Feature",
  "properties": {
    "iso:country":"CH",
    "sg:address":"Route De Montsevelier 171",
    "sg:city":"Mervelier",
    "sg:classifiers":[
        {
            "category":"Insurance",
            "subcategory":"Insurance Agent",
            "type":"Services"
        }
    ],
    "sg:phone":"+41 32 422 57 57",
    "sg:postcode":"2827",
    "sg:province":"Bern",
    "sg:tags":[
        "versicherungsagenturen",
        "-broker"
    ],
    "wof:name":"La Mobili\u00e8re Assurances & Pr\u00e9voyance",
    "wof:placetype":"venue"
},
  "geometry": {"coordinates":[7.5007920265,47.3458557129],"type":"Point"}
}