{
  "type": "Feature",
  "properties": {
    "iso:country":"CH",
    "sg:address":"Gemeindemattenstrasse 20 3860 Meiringen. Postfach 674",
    "sg:city":"Meiringen",
    "sg:orig_category":"Bau von Strassen, Sportanlagen U Bahnverkehrsstrecken Strassenbau",
    "sg:phone":"+41 33 971 31 41",
    "sg:postcode":"3860",
    "sg:province":"Bern",
    "wof:name":"Batigroup Ag",
    "wof:placetype":"venue"
},
  "geometry": {"coordinates":[8.189304,46.724449],"type":"Point"}
}