{
  "type": "Feature",
  "properties": {
    "iso:country":"CH",
    "sg:address":"La Croix",
    "sg:city":"Chabrey",
    "sg:orig_category":"Autogaragen Autospenglereien",
    "sg:phone":"+41 26 677 37 91",
    "sg:postcode":"1589",
    "sg:province":"Vaud",
    "wof:name":"Pascal Aeby Garage Carrosserie Du Lac",
    "wof:placetype":"venue"
},
  "geometry": {"coordinates":[6.978667,46.924759],"type":"Point"}
}