{
  "type": "Feature",
  "properties": {
    "iso:country":"CH",
    "sg:address":"1442",
    "sg:city":"Montagny-yverdon",
    "sg:orig_category":"Sportvereine Turnen",
    "sg:postcode":"1442",
    "sg:province":"Vaud",
    "wof:name":"St\u00e9 De Gymnastique",
    "wof:placetype":"venue"
},
  "geometry": {"coordinates":[6.5610051155,46.8027954102],"type":"Point"}
}