{
  "type": "Feature",
  "properties": {
    "iso:country":"CH",
    "sg:address":"Schneidergasse 20 4051 Basel. Postfach",
    "sg:city":"Basel",
    "sg:orig_category":"RESTAURANTS: TEA-ROOMS",
    "sg:phone":"+41 71 923 50 12",
    "sg:postcode":"4051",
    "sg:province":"Basel-Stadt",
    "wof:name":"Schwengeler Doris",
    "wof:placetype":"venue"
},
  "geometry": {"coordinates":[9.0359191895,47.451423645],"type":"Point"}
}