{
  "type": "Feature",
  "properties": {
    "addr:full":"Unterer Kanalweg 61 2562 Port. Postfach Nidau Bern 2560",
    "addr:housenumber":"61",
    "addr:postcode":"2562;2560",
    "addr:street":"Unterer Kanalweg",
    "iso:country":"CH",
    "sg:address":"Unterer Kanalweg 61 2562 Port. Postfach",
    "sg:city":"Nidau",
    "sg:orig_category":"Architektur U Ingenieurb\u00fcros",
    "sg:phone":"+41 31 839 04 75",
    "sg:postcode":"2560",
    "sg:province":"Bern",
    "wof:name":"Portner Erich Ag",
    "wof:placetype":"venue"
},
  "geometry": {"coordinates":[7.563228,46.935371],"type":"Point"}
}