{
  "type": "Feature",
  "properties": {
    "iso:country":"CH",
    "sg:address":"Unterdorfstrasse 19",
    "sg:city":"Anglikon",
    "sg:orig_category":"Vereine Frauen Vereine Gemeinn\u00fctzige",
    "sg:postcode":"5611",
    "sg:province":"Aargau",
    "wof:name":"Coop Frauenbund Sekt.worb",
    "wof:placetype":"venue"
},
  "geometry": {"coordinates":[7.5743331909,46.9255218506],"type":"Point"}
}