{
  "type": "Feature",
  "properties": {
    "iso:country":"CH",
    "sg:address":"R\u00fctihofstrasse 17",
    "sg:city":"Z\u00fcrich",
    "sg:orig_category":"Herstellung von k\u00e4lte U lufttechnischen Erzeugnissen f\u00fcr gewerbliche Zwecke Sanit\u00e4r U Heizungsinstal",
    "sg:phone":"+41 13410027",
    "sg:postcode":"8049",
    "sg:province":"Z\u00fcrich",
    "wof:name":"City Calor Ag",
    "wof:placetype":"venue"
},
  "geometry": {"coordinates":[8.4791440964,47.4138755798],"type":"Point"}
}