{
  "type": "Feature",
  "properties": {
    "iso:country":"CH",
    "sg:address":"Im B\u00e4renmoos 4",
    "sg:city":"Oberrieden",
    "sg:orig_category":"Kosmetikinstitute",
    "sg:phone":"+41 17204252",
    "sg:postcode":"8942",
    "sg:province":"Z\u00fcrich",
    "wof:name":"Yvonne Huber Kosmetikinstitut Claire",
    "wof:placetype":"venue"
},
  "geometry": {"coordinates":[8.5777511597,47.273235321],"type":"Point"}
}