{
  "type": "Feature",
  "properties": {
    "addr:full":"Rue Rosselet-challandes 5 2605 Sonceboz-sombeval Case Postale 7 Sonceboz-sombeval Bern 2605",
    "addr:housenumber":"5;7",
    "addr:postcode":"2605;2605",
    "addr:street":"Rue Rosselet-Challandes;Case Postale",
    "iso:country":"CH",
    "sg:address":"Rue Rosselet-challandes 5 2605 Sonceboz-sombeval Case Postale 7",
    "sg:city":"Sonceboz-sombeval",
    "sg:orig_category":"Herstellung von Mess U Kontrollinstrumenten U vorrichtungen Mechanische Werkst\u00e4tten",
    "sg:phone":"+41 32 488 11 11",
    "sg:postcode":"2605",
    "sg:province":"Bern",
    "wof:name":"Soci\u00e9t\u00e9 Industrielle De Sonceboz Sa",
    "wof:placetype":"venue"
},
  "geometry": {"coordinates":[7.176567,47.193069],"type":"Point"}
}