{
  "type": "Feature",
  "properties": {
    "iso:country":"CH",
    "sg:address":"Bahnhofstrasse 54 7302 Landquart. Postfach",
    "sg:city":"Landquart",
    "sg:orig_category":"Fachdetailhandel mit pharmazeutischen Produkten",
    "sg:phone":"+41 81 330 03 30",
    "sg:postcode":"7302",
    "sg:province":"Graubunden",
    "wof:name":"Falknis Apotheke Gmbh",
    "wof:placetype":"venue"
},
  "geometry": {"coordinates":[9.5619878769,46.9679985046],"type":"Point"}
}