{
  "type": "Feature",
  "properties": {
    "iso:country":"CH",
    "sg:address":"Chemin De La Colline 5bis 1007 Lausanne Case Postale 349",
    "sg:city":"Mont-sur-lausanne",
    "sg:orig_category":"G\u00fcterbef\u00f6rderung im Strassenverkehr Lagerung",
    "sg:phone":"+41 21 620 03 40",
    "sg:postcode":"1052",
    "sg:province":"Vaud",
    "wof:name":"Mat Securitas Express Sa, Succursale Du Mont-sur-lausanne",
    "wof:placetype":"venue"
},
  "geometry": {"coordinates":[6.6120100021,46.5214347839],"type":"Point"}
}