{
  "type": "Feature",
  "properties": {
    "iso:country":"CH",
    "sg:address":"Franches-montagnes",
    "sg:city":"Saignel\u00e9gier",
    "sg:orig_category":"Wasserversorgung",
    "sg:phone":"+41 81 302 82 81",
    "sg:postcode":"2350",
    "sg:province":"Jura",
    "wof:name":"Tbs Gmbh",
    "wof:placetype":"venue"
},
  "geometry": {"coordinates":[9.5179948807,46.9924240112],"type":"Point"}
}