{
  "type": "Feature",
  "properties": {
    "iso:country":"CH",
    "sg:address":"Rte De Recolaine 13 Case Postale",
    "sg:city":"Vicques",
    "sg:classifiers":[
        {
            "category":"Professional",
            "subcategory":"Engineering",
            "type":"Services"
        }
    ],
    "sg:phone":"+41 71 761 21 21",
    "sg:postcode":"2824",
    "sg:province":"Jura",
    "sg:tags":[
        "machine",
        "-",
        "mechanical"
    ],
    "wof:name":"Walter Mattle Ag",
    "wof:placetype":"venue"
},
  "geometry": {"coordinates":[9.5739545822,47.3270149231],"type":"Point"}
}