{
  "type": "Feature",
  "properties": {
    "iso:country":"CH",
    "sg:address":"Neuch\u00e2tel Route De 1",
    "sg:city":"Cernier",
    "sg:orig_category":"Druck ohne Zeitungsdruck",
    "sg:phone":"+41 19302460",
    "sg:postcode":"2053",
    "sg:province":"Neuch\u00e2tel",
    "wof:name":"Infolabel Ag",
    "wof:placetype":"venue"
},
  "geometry": {"coordinates":[8.7910909653,47.3316078186],"type":"Point"}
}