{
  "type": "Feature",
  "properties": {
    "iso:country":"CH",
    "sg:address":"3439",
    "sg:city":"Ranfl\u00fch",
    "sg:orig_category":"Landw. Genossenschaften Viehzucht",
    "sg:phone":"+41 34 594 34 36",
    "sg:postcode":"3439",
    "sg:province":"Bern",
    "wof:name":"Viehzuchtgenossenschaft",
    "wof:placetype":"venue"
},
  "geometry": {"coordinates":[7.739025116,46.9888801575],"type":"Point"}
}