{
  "type": "Feature",
  "properties": {
    "addr:full":"Arinstrasse 471 Sevelen St. Gallen 9475",
    "addr:housenumber":"471",
    "addr:postcode":"9475",
    "addr:street":"Arinstrasse",
    "iso:country":"CH",
    "sg:address":"Arinstrasse 471",
    "sg:city":"Sevelen",
    "sg:orig_category":"Autogaragen Einzelhandel mit Automobilen",
    "sg:phone":"+41 81 785 21 21",
    "sg:postcode":"9475",
    "sg:province":"St. Gallen",
    "wof:name":"Tr-cars Gmbh Garage",
    "wof:placetype":"venue"
},
  "geometry": {"coordinates":[9.491128,47.127464],"type":"Point"}
}