{
  "type": "Feature",
  "properties": {
    "iso:country":"CH",
    "sg:address":"8522",
    "sg:city":"H\u00e4uslenen",
    "sg:orig_category":"Sportvereine Sch\u00fctzen",
    "sg:phone":"+41 52 721 86 57",
    "sg:postcode":"8522",
    "sg:province":"Thurgau",
    "wof:name":"Sch\u00fctzengesellschaft",
    "wof:placetype":"venue"
},
  "geometry": {"coordinates":[8.9001302719,47.5204582214],"type":"Point"}
}