{
  "type": "Feature",
  "properties": {
    "addr:full":"1981 Vex Valais 1981",
    "addr:housenumber":"1981",
    "addr:postcode":"1981",
    "addr:street":"Vex Valais",
    "iso:country":"CH",
    "sg:address":"1981",
    "sg:city":"Vex",
    "sg:orig_category":"Campingpl\u00e4tze Detailhandel mit Zeitungen U Zeitschriften Kioske",
    "sg:phone":"+41 27 207 19 85",
    "sg:postcode":"1981",
    "sg:province":"Valais",
    "wof:name":"Camping Du Val D'h\u00e9rens",
    "wof:placetype":"venue"
},
  "geometry": {"coordinates":[7.39541,46.205479],"type":"Point"}
}