{
  "type": "Feature",
  "properties": {
    "iso:country":"CH",
    "sg:address":"Parkstrasse 34 4102 Binningen. Postfach",
    "sg:city":"Binningen",
    "sg:orig_category":"Gesundheitswesen",
    "sg:postcode":"4102",
    "sg:province":"Basel-Landschaft",
    "wof:name":"Fahrni Consulting",
    "wof:placetype":"venue"
},
  "geometry": {"coordinates":[7.5725669861,47.5344200134],"type":"Point"}
}