{
  "type": "Feature",
  "properties": {
    "iso:country":"CH",
    "sg:address":"Monthoux Rue De 58 1200 Genf. Postfach",
    "sg:city":"Gen\u00e8ve",
    "sg:orig_category":"Unclassifiable Establishments",
    "sg:postcode":"1201",
    "sg:province":"Gen\u00e8ve",
    "wof:name":"Connections-4-u Gmbh",
    "wof:placetype":"venue"
},
  "geometry": {"coordinates":[7.6031570435,47.5039520264],"type":"Point"}
}