{
  "type": "Feature",
  "properties": {
    "iso:country":"CH",
    "sg:address":"Fuhrenmatte",
    "sg:city":"Boltigen",
    "sg:orig_category":"Arztpraxen",
    "sg:phone":"+41 33 773 66 55",
    "sg:postcode":"3766",
    "sg:province":"Bern",
    "wof:name":"Dr.med.robert H\u00e4rri Arzt F.allgemeine Medizin Fmh",
    "wof:placetype":"venue"
},
  "geometry": {"coordinates":[7.391058,46.628529],"type":"Point"}
}