{
  "type": "Feature",
  "properties": {
    "iso:country":"CH",
    "sg:address":"Fabrikstrasse 29",
    "sg:city":"Glattbrugg",
    "sg:orig_category":"Elektroinstallation Herstellung von sonstigen elektrischen Ausr\u00fcstungen",
    "sg:phone":"+41 12676565",
    "sg:postcode":"8152",
    "sg:province":"Z\u00fcrich",
    "wof:name":"Jakob Kowner Ag Elektrotechnische Unternehmung",
    "wof:placetype":"venue"
},
  "geometry": {"coordinates":[8.5912475586,47.3028678894],"type":"Point"}
}