{
  "type": "Feature",
  "properties": {
    "iso:country":"CH",
    "sg:address":"Rathausgasse 14",
    "sg:city":"Baden",
    "sg:orig_category":"Unclassifiable Establishments",
    "sg:postcode":"5400",
    "sg:province":"Aargau",
    "wof:name":"Gouider + De Carlo",
    "wof:placetype":"venue"
},
  "geometry": {"coordinates":[8.3085803986,47.4730262756],"type":"Point"}
}