{
  "type": "Feature",
  "properties": {
    "iso:country":"CH",
    "sg:address":"Nidaug. 38.",
    "sg:city":"Biel/bienne",
    "sg:orig_category":"Zurichtung U F\u00e4rben von Fellen, Herstellung von Pelzwaren",
    "sg:postcode":"2500",
    "sg:province":"Bern",
    "wof:name":"Dunkelmann, Pelzhaus Panther Ag Filiale Biel",
    "wof:placetype":"venue"
},
  "geometry": {"coordinates":[7.2899799347,47.1467399597],"type":"Point"}
}