{
  "type": "Feature",
  "properties": {
    "iso:country":"CH",
    "sg:address":"Via Cesarea 32",
    "sg:city":"Stabio",
    "sg:orig_category":"Autogaragen",
    "sg:phone":"+41 91 647 15 72",
    "sg:postcode":"6855",
    "sg:province":"Ticino",
    "wof:name":"Luigi Binaghi Garage",
    "wof:placetype":"venue"
},
  "geometry": {"coordinates":[8.942429,45.850357],"type":"Point"}
}