{
  "type": "Feature",
  "properties": {
    "iso:country":"CH",
    "sg:address":"Eigerplatz 5",
    "sg:city":"Bern",
    "sg:classifiers":[
        {
            "category":"Banks & Credit Unions",
            "subcategory":"Bank",
            "type":"Services"
        }
    ],
    "sg:phone":"+41 31 371 26 26",
    "sg:postcode":"3007",
    "sg:province":"Bern",
    "wof:name":"Berner Kantonalbank",
    "wof:placetype":"venue"
},
  "geometry": {"coordinates":[7.431457,46.940823],"type":"Point"}
}