{
  "type": "Feature",
  "properties": {
    "addr:full":"Bahnhofstrasse 20 M\u00e4nnedorf Z\u00fcrich 8708",
    "addr:housenumber":"20",
    "addr:postcode":"8708",
    "addr:street":"Bahnhofstrasse;Zuerich",
    "iso:country":"CH",
    "sg:address":"Bahnhofstrasse 20",
    "sg:city":"M\u00e4nnedorf",
    "sg:orig_category":"Arztpraxen",
    "sg:phone":"+41 19204555",
    "sg:postcode":"8708",
    "sg:province":"Z\u00fcrich",
    "wof:name":"Dr.med.udo D\u00f6hmann Spezialarzt Fmh",
    "wof:placetype":"venue"
},
  "geometry": {"coordinates":[8.692317,47.253071],"type":"Point"}
}