{
  "type": "Feature",
  "properties": {
    "iso:country":"CH",
    "sg:address":"Route D'agy 126",
    "sg:city":"Granges-paccot",
    "sg:orig_category":"Detailhandel mit elektrischen Haushalts-,Radio U Fernsehger\u00e4ten sowie Musikinstrumenten",
    "sg:phone":"+41 26 465 15 65",
    "sg:postcode":"1763",
    "sg:province":"Fribourg",
    "wof:name":"Boutique La Maison Proven\u00e7ale",
    "wof:placetype":"venue"
},
  "geometry": {"coordinates":[7.1482000351,46.8223991394],"type":"Point"}
}