{
  "type": "Feature",
  "properties": {
    "iso:country":"CH",
    "sg:address":"Fenette Chemin De 1808 Corsier-les-monts. Postfach",
    "sg:city":"Monts-de-corsier",
    "sg:orig_category":"Unclassifiable Establishments",
    "sg:postcode":"1808",
    "sg:province":"Vaud",
    "wof:name":"Les Ecuries Du Ch\u00eane S\u00e0rl",
    "wof:placetype":"venue"
},
  "geometry": {"coordinates":[6.8812398911,46.5034866333],"type":"Point"}
}