{
  "type": "Feature",
  "properties": {
    "iso:country":"CH",
    "sg:address":"Neudorfstrasse 2",
    "sg:city":"Uzwil",
    "sg:orig_category":"Arztpraxen",
    "sg:phone":"+41 71 950 15 50",
    "sg:postcode":"9240",
    "sg:province":"St. Gallen",
    "wof:name":"Dr.med. Jakob Schenk Spezialarzt Fmh",
    "wof:placetype":"venue"
},
  "geometry": {"coordinates":[9.132904,47.437908],"type":"Point"}
}