{
  "type": "Feature",
  "properties": {
    "iso:country":"CH",
    "sg:address":"6930",
    "sg:city":"Bedano",
    "sg:orig_category":"Herstellung von sonstigen elektrischen Ausr\u00fcstungen",
    "sg:postcode":"6930",
    "sg:province":"Ticino",
    "wof:name":"Tecno S\u00e9curit\u00e9, Habegger Bruno, Lebet Michel",
    "wof:placetype":"venue"
},
  "geometry": {"coordinates":[7.0912280083,47.0631065369],"type":"Point"}
}