{
  "type": "Feature",
  "properties": {
    "iso:country":"CH",
    "sg:address":"Coste Via Le 12",
    "sg:city":"Porza",
    "sg:orig_category":"Softwareentwicklung U beratung",
    "sg:postcode":"6948",
    "sg:province":"Ticino",
    "wof:name":"G & J System Sagl",
    "wof:placetype":"venue"
},
  "geometry": {"coordinates":[8.95216465,46.0259933472],"type":"Point"}
}