{
  "type": "Feature",
  "properties": {
    "iso:country":"CH",
    "sg:address":"Flughafen 8302 Kloten. Postfach 1444",
    "sg:city":"Z\u00fcrich",
    "sg:orig_category":"Fachdetailhandel mit pharmazeutischen Produkten",
    "sg:phone":"+41 31 311 15 81",
    "sg:postcode":"8058",
    "sg:province":"Z\u00fcrich",
    "wof:name":"Internationale Apotheke Noyer Dr.",
    "wof:placetype":"venue"
},
  "geometry": {"coordinates":[7.4443869591,46.9490509033],"type":"Point"}
}