{
  "type": "Feature",
  "properties": {
    "iso:country":"CH",
    "sg:address":"Aubrigstrasse 13",
    "sg:city":"Wolfhausen",
    "sg:classifiers":[
        {
            "category":"Transit Center",
            "subcategory":"Freight",
            "type":"Transportation"
        }
    ],
    "sg:phone":"+41 32 913 73 22",
    "sg:postcode":"8633",
    "sg:province":"Z\u00fcrich",
    "sg:tags":[
        "elevator"
    ],
    "wof:name":"Jean Chervaz",
    "wof:placetype":"venue"
},
  "geometry": {"coordinates":[6.8163838387,47.1000938416],"type":"Point"}
}