{
  "type": "Feature",
  "properties": {
    "addr:full":"Piazza Indipendenza 1 Bellinzona Ticino 6500",
    "addr:housenumber":"1",
    "addr:postcode":"6500",
    "addr:street":"Piazza Indipendenza",
    "iso:country":"CH",
    "sg:address":"Piazza Indipendenza 1",
    "sg:city":"Bellinzona",
    "sg:classifiers":[
        {
            "category":"Bars & Pubs",
            "type":"Food & Drink"
        }
    ],
    "sg:phone":"+41 91 826 49 02",
    "sg:postcode":"6500",
    "sg:province":"Ticino",
    "wof:name":"Pub Indipendenza",
    "wof:placetype":"venue"
},
  "geometry": {"coordinates":[9.022611,46.190071],"type":"Point"}
}