{
  "type": "Feature",
  "properties": {
    "iso:country":"CH",
    "sg:address":"Haldenstr. 28",
    "sg:city":"Wetzikon",
    "sg:classifiers":[
        {
            "category":"Manufacturing",
            "subcategory":"Printing",
            "type":"Manufacturing & Wholesale Goods"
        }
    ],
    "sg:phone":"+41 4119332211",
    "sg:postcode":"8620",
    "sg:province":"Z\u00fcrich",
    "sg:tags":[
        "publishing"
    ],
    "wof:name":"Printlink Ag",
    "wof:placetype":"venue"
},
  "geometry": {"coordinates":[8.7857179642,47.3260574341],"type":"Point"}
}