{
  "type": "Feature",
  "properties": {
    "iso:country":"CH",
    "sg:address":"Im Gapetsch 17",
    "sg:city":"Schaan",
    "sg:orig_category":"Sonstiges Gesundheitswesen",
    "sg:phone":"+423 233 34 19",
    "sg:postcode":"9494",
    "wof:name":"Krankenmobilienmagazin Frau Elsa Wenaweser",
    "wof:placetype":"venue"
},
  "geometry": {"coordinates":[9.5068416595,47.1611671448],"type":"Point"}
}