{
  "type": "Feature",
  "properties": {
    "iso:country":"CH",
    "sg:address":"Allmendstrasse 29",
    "sg:city":"Wohlen",
    "sg:classifiers":[
        {
            "category":"Banks & Credit Unions",
            "subcategory":"Investment Brokerage",
            "type":"Services"
        }
    ],
    "sg:phone":"+41 56 622 80 00",
    "sg:postcode":"5610",
    "sg:province":"Aargau",
    "sg:tags":[
        "logo",
        "adhesive",
        "letters",
        "character"
    ],
    "wof:name":"Hutter Siebdruck Ag",
    "wof:placetype":"venue"
},
  "geometry": {"coordinates":[8.270094,47.354736],"type":"Point"}
}