{
  "type": "Feature",
  "properties": {
    "iso:country":"CH",
    "sg:address":"Cit\u00e9-devant Rue 8 1005 Lausanne. Postfach",
    "sg:city":"Lausanne",
    "sg:orig_category":"Fachdetailhandel in Verkaufsr\u00e4umen",
    "sg:postcode":"1005",
    "sg:province":"Vaud",
    "wof:name":"Mar\u00e9chal Jacques",
    "wof:placetype":"venue"
},
  "geometry": {"coordinates":[6.6354169846,46.5233650208],"type":"Point"}
}