{
  "type": "Feature",
  "properties": {
    "iso:country":"CH",
    "sg:address":"Zugerstr. 160",
    "sg:city":"W\u00e4denswil",
    "sg:classifiers":[
        {
            "category":"Manufacturing",
            "subcategory":"Metals",
            "type":"Manufacturing & Wholesale Goods"
        }
    ],
    "sg:phone":"+41 4117826767",
    "sg:postcode":"8820",
    "sg:province":"Z\u00fcrich",
    "sg:tags":[
        "metallurgy",
        "metalworking",
        "processing"
    ],
    "wof:name":"Galvanic W\u00c4denswil Feusi + Federer Ag",
    "wof:placetype":"venue"
},
  "geometry": {"coordinates":[8.6412401199,47.2380599976],"type":"Point"}
}