{
  "type": "Feature",
  "properties": {
    "iso:country":"CH",
    "sg:address":"Kirchfeldstrasse 11",
    "sg:city":"Emmen",
    "sg:orig_category":"Bauschreinerei Herstellung von M\u00f6beln verschiedener Art",
    "sg:phone":"+41 79 444 40 01",
    "sg:postcode":"6032",
    "sg:province":"Luzern",
    "wof:name":"Roberto K\u00f6chli Mobili & Serramenti",
    "wof:placetype":"venue"
},
  "geometry": {"coordinates":[8.971205,45.893227],"type":"Point"}
}