{
  "type": "Feature",
  "properties": {
    "addr:full":"Innerer Giessenweg 12b M\u00fcnsingen Bern 3110",
    "addr:housenumber":"12b",
    "addr:postcode":"3110",
    "addr:street":"Innerer Giessenweg",
    "iso:country":"CH",
    "sg:address":"Innerer Giessenweg 12b",
    "sg:city":"M\u00fcnsingen",
    "sg:orig_category":"Architektur U Ingenieurb\u00fcros Architekturb\u00fcros",
    "sg:phone":"+41 31 721 15 09",
    "sg:postcode":"3110",
    "sg:province":"Bern",
    "wof:name":"Wegm\u00fcller Architekturb\u00fcro Ag",
    "wof:placetype":"venue"
},
  "geometry": {"coordinates":[7.549168,46.873344],"type":"Point"}
}