{
  "type": "Feature",
  "properties": {
    "iso:country":"CH",
    "sg:address":"Neuwiesenstrasse 10a 8610 Uster. Postfach",
    "sg:city":"Uster",
    "sg:orig_category":"Unternehmensberatung Wirtschaftspr\u00fcfung, Steuerberatung U Treuhand",
    "sg:phone":"+41 19419963",
    "sg:postcode":"8610",
    "sg:province":"Z\u00fcrich",
    "wof:name":"Nameit Ag Unternehmensberatung. Dienstleistungen. Informationstechnologie Usw",
    "wof:placetype":"venue"
},
  "geometry": {"coordinates":[8.7217502594,47.3496208191],"type":"Point"}
}