{
  "type": "Feature",
  "properties": {
    "iso:country":"CH",
    "sg:address":"Dorfstrasse 25",
    "sg:city":"Amden",
    "sg:orig_category":"G\u00fcterbef\u00f6rderung im Strassenverkehr Personenbef\u00f6rderung im Nahverkehr",
    "sg:phone":"+41 79 416 19 22",
    "sg:postcode":"8873",
    "sg:province":"St. Gallen",
    "wof:name":"Autobetrieb Weesen-amden Personen-g\u00fctertransporte",
    "wof:placetype":"venue"
},
  "geometry": {"coordinates":[9.1425600052,47.1493453979],"type":"Point"}
}