{
  "type": "Feature",
  "properties": {
    "iso:country":"CH",
    "sg:address":"Oberlandstrasse 99",
    "sg:city":"Uster",
    "sg:orig_category":"Freizeit, Hobbies U Vereine",
    "sg:postcode":"8610",
    "sg:province":"Z\u00fcrich",
    "wof:name":"Kunst-art Der Kuenstlertreff",
    "wof:placetype":"venue"
},
  "geometry": {"coordinates":[8.718757,47.35268],"type":"Point"}
}