{
  "type": "Feature",
  "properties": {
    "iso:country":"CH",
    "sg:address":"Neudorfstrasse 90 4056 Basel. Postfach",
    "sg:city":"Basel",
    "sg:orig_category":"G\u00fcterbef\u00f6rderung im Strassenverkehr",
    "sg:postcode":"4056",
    "sg:province":"Basel-Stadt",
    "wof:name":"Friko-trans Fritsche Bruno",
    "wof:placetype":"venue"
},
  "geometry": {"coordinates":[9.5429334641,47.4775428772],"type":"Point"}
}