{
  "type": "Feature",
  "properties": {
    "iso:country":"CH",
    "sg:address":"Piazzetta Dei Riformati 1",
    "sg:city":"Locarno",
    "sg:orig_category":"Architekturb\u00fcros",
    "sg:phone":"+41 79 247 58 44",
    "sg:postcode":"6600",
    "sg:province":"Ticino",
    "wof:name":"Bardelli B\u00fcchler & Bardelli Studio D'architettura",
    "wof:placetype":"venue"
},
  "geometry": {"coordinates":[8.7936439514,46.1697883606],"type":"Point"}
}