{
  "type": "Feature",
  "properties": {
    "iso:country":"CH",
    "sg:address":"Cottorado Via Al",
    "sg:city":"Gentilino",
    "sg:orig_category":"RESTAURANTS: TEA-ROOMS",
    "sg:phone":"+41 91 994 69 19",
    "sg:postcode":"6925",
    "sg:province":"Ticino",
    "wof:name":"Grotto Certenago Sagl",
    "wof:placetype":"venue"
},
  "geometry": {"coordinates":[8.9318351746,45.9904594421],"type":"Point"}
}