{
  "type": "Feature",
  "properties": {
    "iso:country":"CH",
    "sg:address":"Rickenbachstrasse 72",
    "sg:city":"Schwyz",
    "sg:orig_category":"Grosshandel mit Textilien Grosshandel mit sonstigen Halbwaren",
    "sg:phone":"+41 41 811 74 24",
    "sg:postcode":"6430",
    "sg:province":"Schwyz",
    "wof:name":"Celeste Ag",
    "wof:placetype":"venue"
},
  "geometry": {"coordinates":[8.6614999771,47.0208854675],"type":"Point"}
}