{
  "type": "Feature",
  "properties": {
    "iso:country":"CH",
    "sg:address":"Poststrasse 2",
    "sg:city":"Richterswil",
    "sg:orig_category":"Verkehrs- and Tourismusb\u00fcros",
    "sg:phone":"+41 41 397 11 28",
    "sg:postcode":"8805",
    "sg:province":"Z\u00fcrich",
    "wof:name":"Verkehrsb\u00fcro Rigi",
    "wof:placetype":"venue"
},
  "geometry": {"coordinates":[8.4673700333,47.0442047119],"type":"Point"}
}