{
  "type": "Feature",
  "properties": {
    "iso:country":"CH",
    "sg:address":"St. Johanns-vorstadt 58",
    "sg:city":"Basel",
    "sg:orig_category":"Zahnarztpraxen",
    "sg:phone":"+41 61 322 03 37",
    "sg:postcode":"4056",
    "sg:province":"Basel-Stadt",
    "wof:name":"Dr. Med. Dent. Nicolas Gabutti Zahnarzt",
    "wof:placetype":"venue"
},
  "geometry": {"coordinates":[7.5839319229,47.5644302368],"type":"Point"}
}