{
  "type": "Feature",
  "properties": {
    "iso:country":"CH",
    "sg:address":"Rue De Monthoux 34",
    "sg:city":"Gen\u00e8ve",
    "sg:orig_category":"Detailhandel mit M\u00f6beln Detailhandel mit M\u00f6beln U Haushaltsgegenst\u00e4nden",
    "sg:phone":"+41 21 807 41 00",
    "sg:postcode":"1201",
    "sg:province":"Gen\u00e8ve",
    "wof:name":"Makoura Claude Schmutz",
    "wof:placetype":"venue"
},
  "geometry": {"coordinates":[6.1482110023,46.2107696533],"type":"Point"}
}