{
  "type": "Feature",
  "properties": {
    "iso:country":"CH",
    "sg:address":"Spitalstrasse 5",
    "sg:city":"Brig",
    "sg:orig_category":"Sonstige Institutionen des Sozialwesens ohne Beherbergung",
    "sg:phone":"+41 56 222 49 66",
    "sg:postcode":"3900",
    "sg:province":"Valais",
    "wof:name":"Erziehungsberatungsstelle Baden,brugg & Zurzach",
    "wof:placetype":"venue"
},
  "geometry": {"coordinates":[8.2060117722,47.4836006165],"type":"Point"}
}