{
  "type": "Feature",
  "properties": {
    "iso:country":"CH",
    "sg:address":"Au Village 34",
    "sg:city":"Glovelier",
    "sg:classifiers":[
        {
            "category":"Restaurant",
            "type":"Food & Drink"
        }
    ],
    "sg:phone":"+41 32 426 72 44",
    "sg:postcode":"2855",
    "sg:province":"Jura",
    "wof:name":"Caf\u00e9 De La Crosse De B\u00e2le",
    "wof:placetype":"venue"
},
  "geometry": {"coordinates":[7.199285984,47.3327713013],"type":"Point"}
}