{
  "type": "Feature",
  "properties": {
    "iso:country":"CH",
    "sg:address":"6146",
    "sg:city":"Grossdietwil",
    "sg:orig_category":"Detailhandel mit Fleisch U Fleischwaren",
    "sg:phone":"+41 62 927 22 33",
    "sg:postcode":"6146",
    "sg:province":"Luzern",
    "wof:name":"Metzgerei Und Restaurant Spatz, M\u00fcler Bruno Und Jean",
    "wof:placetype":"venue"
},
  "geometry": {"coordinates":[7.8880729675,47.1702079773],"type":"Point"}
}