{
  "type": "Feature",
  "properties": {
    "iso:country":"CH",
    "sg:address":"Hirschgartenstrasse 2",
    "sg:city":"Waldkirch",
    "sg:orig_category":"S\u00e4ge, Hobel U Holzimpr\u00e4gnierwerke S\u00e4gewerke",
    "sg:phone":"+41 71 433 11 53",
    "sg:postcode":"9205",
    "sg:province":"St. Gallen",
    "wof:name":"Werz Josef Ag",
    "wof:placetype":"venue"
},
  "geometry": {"coordinates":[9.2838754654,47.4701499939],"type":"Point"}
}