{
  "type": "Feature",
  "properties": {
    "iso:country":"CH",
    "sg:address":"Chemin De La Cure 1",
    "sg:city":"Belmont-lausanne",
    "sg:orig_category":"Vermietung U Verpachtung von eigenen Immobilien",
    "sg:phone":"+41 21 711 13 13",
    "sg:postcode":"1092",
    "sg:province":"Vaud",
    "wof:name":"Madil Sa",
    "wof:placetype":"venue"
},
  "geometry": {"coordinates":[6.6790590286,46.5193748474],"type":"Point"}
}