{
  "type": "Feature",
  "properties": {
    "iso:country":"CH",
    "sg:address":"Dorfstrasse 29 8037 Z\u00fcrich. Postfach",
    "sg:city":"Z\u00fcrich",
    "sg:orig_category":"Unclassifiable Establishments",
    "sg:phone":"+41 14468380",
    "sg:postcode":"8037",
    "sg:province":"Z\u00fcrich",
    "wof:name":"Multimedia Solutions Ag Multimedia-agentur",
    "wof:placetype":"venue"
},
  "geometry": {"coordinates":[8.5227537155,47.3941993713],"type":"Point"}
}