{
  "type": "Feature",
  "properties": {
    "iso:country":"CH",
    "sg:address":"Poststrasse 5",
    "sg:city":"Sarnen",
    "sg:orig_category":"Detailhandel mit Bekleidung",
    "sg:postcode":"6060",
    "sg:province":"Obwalden",
    "wof:name":"Mathis Frau Katja, Modegesch\u00e4ft",
    "wof:placetype":"venue"
},
  "geometry": {"coordinates":[8.247073,46.89576],"type":"Point"}
}