{
  "type": "Feature",
  "properties": {
    "iso:country":"CH",
    "sg:address":"Bartolom\u00e4usweg 27 2500 Biel/bienne. Postfach",
    "sg:city":"Biel/bienne",
    "sg:orig_category":"Sonstige mit Sport verbundene T\u00e4tigkeiten",
    "sg:postcode":"2504",
    "sg:province":"Bern",
    "wof:name":"Capoeira Mestre Carlito Formiga Da Concei\u00e7\u00e3o Silva",
    "wof:placetype":"venue"
},
  "geometry": {"coordinates":[7.2845258713,47.1483802795],"type":"Point"}
}