{
  "type": "Feature",
  "properties": {
    "iso:country":"CH",
    "sg:address":"Langenthalstrasse 63",
    "sg:city":"Lotzwil",
    "sg:orig_category":"Non-Classified Establishments",
    "sg:postcode":"4932",
    "sg:province":"Bern",
    "wof:name":"Elmo Lotzwil Gmbh",
    "wof:placetype":"venue"
},
  "geometry": {"coordinates":[7.7885642052,47.196144104],"type":"Point"}
}