{
  "type": "Feature",
  "properties": {
    "iso:country":"CH",
    "sg:address":"Oberroth",
    "sg:city":"Grosswangen",
    "sg:orig_category":"Verwertung von Milch",
    "sg:postcode":"6022",
    "sg:province":"Luzern",
    "wof:name":"K\u00e4sereigenossenschaft Roth",
    "wof:placetype":"venue"
},
  "geometry": {"coordinates":[8.0656719208,47.1305580139],"type":"Point"}
}