{
  "type": "Feature",
  "properties": {
    "addr:full":"8342 Wernetshausen Z\u00fcrich 8342",
    "addr:postcode":"8342;8342",
    "iso:country":"CH",
    "sg:address":"8342",
    "sg:city":"Wernetshausen",
    "sg:classifiers":[
        {
            "category":"Education",
            "subcategory":"Library",
            "type":"Public Place"
        }
    ],
    "sg:phone":"+41 19371026",
    "sg:postcode":"8342",
    "sg:province":"Z\u00fcrich",
    "sg:tags":[
        "u",
        "bibliotheken",
        "archive"
    ],
    "wof:name":"Gemeindebibliothek",
    "wof:placetype":"venue"
},
  "geometry": {"coordinates":[8.86645,47.298752],"type":"Point"}
}