{
  "type": "Feature",
  "properties": {
    "iso:country":"CH",
    "sg:address":"Herrenfeld",
    "sg:city":"Maienfeld",
    "sg:orig_category":"Architektur U Ingenieurb\u00fcros",
    "sg:phone":"+41 81 302 35 66",
    "sg:postcode":"7304",
    "sg:province":"Graubunden",
    "wof:name":"B\u00e4nziger & K\u00f6ppel & Br\u00e4ndli & Partner Ingenieur & Planer Sia Usic",
    "wof:placetype":"venue"
},
  "geometry": {"coordinates":[9.53224,47.006863],"type":"Point"}
}