{
  "type": "Feature",
  "properties": {
    "iso:country":"CH",
    "sg:address":"Kemptnerstrasse 4",
    "sg:city":"Adetswil",
    "sg:orig_category":"Innenarchitekturb\u00fcros",
    "sg:phone":"+41 12802282",
    "sg:postcode":"8345",
    "sg:province":"Z\u00fcrich",
    "wof:name":"Roger B\u00e4chtold P. 5",
    "wof:placetype":"venue"
},
  "geometry": {"coordinates":[8.8382997513,47.3388366699],"type":"Point"}
}