{
  "type": "Feature",
  "properties": {
    "iso:country":"CH",
    "sg:address":"Winterthurerstr. 681",
    "sg:city":"Z\u00fcrich",
    "sg:orig_category":"Grosshandel mit Bekleidung",
    "sg:phone":"+41 13912541",
    "sg:postcode":"8051",
    "sg:province":"Z\u00fcrich",
    "wof:name":"Goldschmid Erika Oberbekleidung; Herst",
    "wof:placetype":"venue"
},
  "geometry": {"coordinates":[8.5826740265,47.406337738],"type":"Point"}
}