{
  "type": "Feature",
  "properties": {
    "iso:country":"CH",
    "sg:address":"Gotthardstrasse 65",
    "sg:city":"Andermatt",
    "sg:orig_category":"RESTAURANTS: TEA-ROOMS",
    "sg:postcode":"6490",
    "sg:province":"Uri",
    "wof:name":"Holzhauser",
    "wof:placetype":"venue"
},
  "geometry": {"coordinates":[8.5973329544,46.6342277527],"type":"Point"}
}