{
  "type": "Feature",
  "properties": {
    "iso:country":"CH",
    "sg:address":"Rue Des Remparts 14",
    "sg:city":"Sion",
    "sg:orig_category":"Physiotherapie",
    "sg:phone":"+41 21 960 40 00",
    "sg:postcode":"1950",
    "sg:province":"Valais",
    "wof:name":"Val\u00e9rie Aveni Physioth\u00e9rapie",
    "wof:placetype":"venue"
},
  "geometry": {"coordinates":[6.9258089066,46.3980026245],"type":"Point"}
}