{
  "type": "Feature",
  "properties": {
    "iso:country":"CH",
    "sg:address":"Entenweidstrasse 90",
    "sg:city":"Basel",
    "sg:orig_category":"Reiseb\u00fcros U Reiseveranstalter",
    "sg:postcode":"4056",
    "sg:province":"Basel-Stadt",
    "wof:name":"Hylaj Isa",
    "wof:placetype":"venue"
},
  "geometry": {"coordinates":[7.5736069679,47.569732666],"type":"Point"}
}