{
  "type": "Feature",
  "properties": {
    "iso:country":"CH",
    "sg:address":"Sch\u00f6llerstrasse 6",
    "sg:city":"Derendingen",
    "sg:orig_category":"Sonstige mit Sport verbundene T\u00e4tigkeiten",
    "sg:postcode":"4552",
    "sg:province":"Solothurn",
    "wof:name":"Tennisschule Strehlau",
    "wof:placetype":"venue"
},
  "geometry": {"coordinates":[7.5869998932,47.2042312622],"type":"Point"}
}