{
  "type": "Feature",
  "properties": {
    "iso:country":"CH",
    "sg:address":"Technikumstrasse 82 8400 Winterthur. Postfach",
    "sg:city":"Winterthur",
    "sg:orig_category":"Reiseb\u00fcros U Reiseveranstalter",
    "sg:postcode":"8400",
    "sg:province":"Z\u00fcrich",
    "wof:name":"Hiltebrand's Reisen",
    "wof:placetype":"venue"
},
  "geometry": {"coordinates":[8.4371776581,47.353553772],"type":"Point"}
}