{
  "type": "Feature",
  "properties": {
    "addr:full":"6122 Menznau Luzern 6122",
    "addr:postcode":"6122;6122",
    "iso:country":"CH",
    "sg:address":"6122",
    "sg:city":"Menznau",
    "sg:orig_category":"Bezirks, Sekundar, Realschulen, Oberstufe der Primarschulen",
    "sg:phone":"+41 41 488 00 53",
    "sg:postcode":"6122",
    "sg:province":"Luzern",
    "wof:name":"Realschule",
    "wof:placetype":"venue"
},
  "geometry": {"coordinates":[8.016077,46.883495],"type":"Point"}
}