{
  "type": "Feature",
  "properties": {
    "iso:country":"CH",
    "sg:address":"Bahnhofstr. 15",
    "sg:city":"Frick",
    "sg:classifiers":[
        {
            "category":"Professional",
            "type":"Services"
        }
    ],
    "sg:phone":"+41 62 871 16 33",
    "sg:postcode":"5070",
    "sg:province":"Aargau",
    "sg:tags":[
        "transport",
        "road"
    ],
    "wof:name":"Rieser Transport Ag",
    "wof:placetype":"venue"
},
  "geometry": {"coordinates":[8.0160017014,47.5079841614],"type":"Point"}
}