{
  "type": "Feature",
  "properties": {
    "iso:country":"CH",
    "sg:address":"Via Canva 9a",
    "sg:city":"Savosa",
    "sg:orig_category":"Herstellung von sonstigen elektrischen Ausr\u00fcstungen Sonstiger Grosshandel",
    "sg:phone":"+41 79 602 31 34",
    "sg:postcode":"6942",
    "sg:province":"Ticino",
    "wof:name":"Securplus Sa",
    "wof:placetype":"venue"
},
  "geometry": {"coordinates":[8.9410543442,46.0176925659],"type":"Point"}
}