{
  "type": "Feature",
  "properties": {
    "iso:country":"CH",
    "sg:address":"Ppe Marjolin Ch\u00e2ble-croix",
    "sg:city":"Aigle",
    "sg:orig_category":"Interessenvertretungen",
    "sg:postcode":"1860",
    "sg:province":"Vaud",
    "wof:name":"Fondation Herzog Dr. Paul",
    "wof:placetype":"venue"
},
  "geometry": {"coordinates":[6.8834300041,46.4704742432],"type":"Point"}
}