{
  "type": "Feature",
  "properties": {
    "iso:country":"CH",
    "sg:address":"Froburgstrasse 22 4052 Basel. Postfach",
    "sg:city":"Basel",
    "sg:orig_category":"Malerei-Gipserei Stukkateurgewerbe, Gipserei U Verputzerei",
    "sg:phone":"+41 34 445 29 93",
    "sg:postcode":"4006",
    "wof:name":"Lehmann Ernst Ag",
    "wof:placetype":"venue"
},
  "geometry": {"coordinates":[7.5812931061,47.0881652832],"type":"Point"}
}