{
  "type": "Feature",
  "properties": {
    "addr:full":"Centralstrasse 14 6410 Goldau. Postfach 279 Goldau Schwyz 6410",
    "addr:housenumber":"14;279",
    "addr:postcode":"6410 goldau.;6410",
    "addr:street":"Centralstrasse;Postfach;Schwyz",
    "iso:country":"CH",
    "sg:address":"Centralstrasse 14 6410 Goldau. Postfach 279",
    "sg:city":"Goldau",
    "sg:orig_category":"Allgemeiner Hoch U Tiefbau Hoch U Tiefbau",
    "sg:phone":"+41 41 855 11 93",
    "sg:postcode":"6410",
    "sg:province":"Schwyz",
    "wof:name":"Contratto & Cie",
    "wof:placetype":"venue"
},
  "geometry": {"coordinates":[8.550477,47.050125],"type":"Point"}
}