{
  "type": "Feature",
  "properties": {
    "iso:country":"CH",
    "sg:address":"Henauerstrasse 62",
    "sg:city":"Niederuzwil",
    "sg:orig_category":"Fussreflexzonenmassage",
    "sg:phone":"+41 71 951 88 41",
    "sg:postcode":"9244",
    "sg:province":"St. Gallen",
    "wof:name":"Elisabeth B\u00fchler Fussreflexmassage",
    "wof:placetype":"venue"
},
  "geometry": {"coordinates":[9.1306657791,47.4493331909],"type":"Point"}
}