{
  "type": "Feature",
  "properties": {
    "iso:country":"CH",
    "sg:address":"1535",
    "sg:city":"Combremont-grand",
    "sg:orig_category":"Instandhaltung U Reparatur von Automobilen",
    "sg:phone":"+41 26 666 12 53",
    "sg:postcode":"1535",
    "sg:province":"Vaud",
    "wof:name":"Garage-carrosserie Du Coll\u00e8ge, Bader Eric Et Pierre-alain.",
    "wof:placetype":"venue"
},
  "geometry": {"coordinates":[6.8175902367,46.7612991333],"type":"Point"}
}