{
  "type": "Feature",
  "properties": {
    "iso:country":"CH",
    "sg:address":"Rue Des Anciennes-postes",
    "sg:city":"Noville",
    "sg:orig_category":"Werbung",
    "sg:postcode":"1845",
    "sg:province":"Vaud",
    "wof:name":"Hans-peter Trefalt",
    "wof:placetype":"venue"
},
  "geometry": {"coordinates":[6.8994750977,46.3812484741],"type":"Point"}
}