{
  "type": "Feature",
  "properties": {
    "iso:country":"CH",
    "sg:address":"Hauptstrasse 20",
    "sg:city":"Utzenstorf",
    "sg:orig_category":"Eisenwaren Detailhandel Haushaltartikel Detailhandel",
    "sg:phone":"+41 32 665 01 51",
    "sg:postcode":"3427",
    "sg:province":"Bern",
    "wof:name":"Paul Luder",
    "wof:placetype":"venue"
},
  "geometry": {"coordinates":[7.5576658249,47.1288261414],"type":"Point"}
}