{
  "type": "Feature",
  "properties": {
    "addr:full":"P\u00e9rolles Boulevard De 12 Fribourg Fribourg 1700",
    "addr:housenumber":"12",
    "addr:postcode":"1700",
    "addr:street":"Pe\u0301Rolles Boulevard De",
    "iso:country":"CH",
    "sg:address":"P\u00e9rolles Boulevard De 12",
    "sg:city":"Fribourg",
    "sg:orig_category":"Binnenschiffahrt",
    "sg:postcode":"1700",
    "sg:province":"Fribourg",
    "wof:name":"Serfour Sa",
    "wof:placetype":"venue"
},
  "geometry": {"coordinates":[7.153683,46.803745],"type":"Point"}
}