{
  "type": "Feature",
  "properties": {
    "iso:country":"CH",
    "sg:address":"Rudenzweg 14",
    "sg:city":"Z\u00fcrich",
    "sg:orig_category":"Unternehmensberatung Wirtschaftspr\u00fcfung, Steuerberatung U Treuhand",
    "sg:phone":"+41 14923430",
    "sg:postcode":"8048",
    "sg:province":"Z\u00fcrich",
    "wof:name":"Joaquim Jorge Fortunato Jf Consulting",
    "wof:placetype":"venue"
},
  "geometry": {"coordinates":[8.4983215332,47.3846130371],"type":"Point"}
}