{
  "type": "Feature",
  "properties": {
    "iso:country":"CH",
    "sg:address":"Seestrasse 120a",
    "sg:city":"Steckborn",
    "sg:orig_category":"Vermietung U Verpachtung von eigenen Immobilien",
    "sg:phone":"+41 52 761 15 55",
    "sg:postcode":"8266",
    "sg:province":"Thurgau",
    "wof:name":"Roth Immobilien",
    "wof:placetype":"venue"
},
  "geometry": {"coordinates":[8.9812602997,47.6673851013],"type":"Point"}
}