{
  "type": "Feature",
  "properties": {
    "iso:country":"CH",
    "sg:address":"Obergrundstrasse 65a",
    "sg:city":"Luzern",
    "sg:orig_category":"Bauingenieurb\u00fcros allgemein",
    "sg:phone":"+41 33 335 46 00",
    "sg:postcode":"6003",
    "sg:province":"Luzern",
    "wof:name":"Eduard Semadeni Ingenieurb\u00fcro",
    "wof:placetype":"venue"
},
  "geometry": {"coordinates":[7.616495,46.723625],"type":"Point"}
}