{
  "type": "Feature",
  "properties": {
    "iso:country":"CH",
    "sg:address":"Trottenstrasse 24 8000 Z\u00fcrich. Postfach",
    "sg:city":"Z\u00fcrich",
    "sg:orig_category":"Fachdetailhandel in Verkaufsr\u00e4umen",
    "sg:postcode":"8037",
    "sg:province":"Z\u00fcrich",
    "wof:name":"Haefeli Blumen Vision",
    "wof:placetype":"venue"
},
  "geometry": {"coordinates":[8.5215091705,47.3954429626],"type":"Point"}
}