{
  "type": "Feature",
  "properties": {
    "iso:country":"CH",
    "sg:address":"Birchstrasse 11",
    "sg:city":"Z\u00fcrich",
    "sg:orig_category":"R\u00fcckgewinnung U Vorbereitung f\u00fcr die Wiederverwertung Recycling von nichtmetallischen Altmaterialien",
    "sg:postcode":"8057",
    "sg:province":"Z\u00fcrich",
    "wof:name":"Mitt Ag Entsorgung, Recycling; Herstellung Von Spezialmaschinen Usw.",
    "wof:placetype":"venue"
},
  "geometry": {"coordinates":[8.5345563889,47.404499054],"type":"Point"}
}