{
  "type": "Feature",
  "properties": {
    "iso:country":"CH",
    "sg:address":"6855",
    "sg:city":"Stabio",
    "sg:orig_category":"Maler U Glasergewerbe",
    "sg:phone":"+41 91 647 17 44",
    "sg:postcode":"6855",
    "sg:province":"Ticino",
    "wof:name":"Rizzo Filippo.",
    "wof:placetype":"venue"
},
  "geometry": {"coordinates":[8.9393825531,45.8523521423],"type":"Point"}
}