{
  "type": "Feature",
  "properties": {
    "iso:country":"CH",
    "sg:address":"Landstrasse 41",
    "sg:city":"Glarus",
    "sg:orig_category":"Unclassifiable Establishments",
    "sg:phone":"+41 55 650 19 30",
    "sg:postcode":"8750",
    "sg:province":"Glarus",
    "wof:name":"Swisspublic Gmbh",
    "wof:placetype":"venue"
},
  "geometry": {"coordinates":[9.0614881516,47.0440368652],"type":"Point"}
}