{
  "type": "Feature",
  "properties": {
    "iso:country":"CH",
    "sg:address":"Weissensteinweg 6",
    "sg:city":"Fraubrunnen",
    "sg:orig_category":"Fachdetailhandel in Verkaufsr\u00e4umen",
    "sg:phone":"+41 31 767 93 66",
    "sg:postcode":"3312",
    "sg:province":"Bern",
    "wof:name":"Hans-ulrich Sieber",
    "wof:placetype":"venue"
},
  "geometry": {"coordinates":[7.5239028931,47.0895881653],"type":"Point"}
}