{
  "type": "Feature",
  "properties": {
    "iso:country":"CH",
    "sg:address":"Emmentalstrasse 11",
    "sg:city":"Oberburg",
    "sg:orig_category":"Wasserversorgung",
    "sg:phone":"+41 34 422 23 17",
    "sg:postcode":"3414",
    "sg:province":"Bern",
    "wof:name":"Wasserversorgung Oberburg",
    "wof:placetype":"venue"
},
  "geometry": {"coordinates":[7.6256461143,47.039642334],"type":"Point"}
}