{
  "type": "Feature",
  "properties": {
    "addr:full":"Via Industria Zone 3 Bioggio Ticino 6934",
    "addr:postcode":"6934",
    "addr:street":"Via Industria",
    "iso:country":"CH",
    "sg:address":"Via Industria Zone 3",
    "sg:city":"Bioggio",
    "sg:classifiers":[
        {
            "category":"Community Center",
            "subcategory":"Social",
            "type":"Public Place"
        }
    ],
    "sg:phone":"+41 91 605 65 38",
    "sg:postcode":"6934",
    "sg:province":"Ticino",
    "sg:tags":[
        "pen",
        "ball",
        "point"
    ],
    "wof:name":"Star Point Sa",
    "wof:placetype":"venue"
},
  "geometry": {"coordinates":[8.908655,46.014397],"type":"Point"}
}