{
  "type": "Feature",
  "properties": {
    "iso:country":"CH",
    "sg:address":"Heidenkellerweg 4 8902 Urdorf. Postfach",
    "sg:city":"Urdorf",
    "sg:classifiers":[
        {
            "category":"Professional",
            "subcategory":"Employment Agencies",
            "type":"Services"
        }
    ],
    "sg:phone":"+41 17346666",
    "sg:postcode":"8902",
    "sg:province":"Z\u00fcrich",
    "sg:tags":[
        "personal",
        "u",
        "stellenvermittlung"
    ],
    "wof:name":"Step By Step Stellenvermittlung Imesch & Partner Vermittlung Von Fach Und Kaderpersonal",
    "wof:placetype":"venue"
},
  "geometry": {"coordinates":[8.4262113571,47.3844947815],"type":"Point"}
}