{
  "type": "Feature",
  "properties": {
    "iso:country":"CH",
    "sg:address":"8765",
    "sg:city":"Engi",
    "sg:classifiers":[
        {
            "category":"Education",
            "subcategory":"Vocational School",
            "type":"Public Place"
        }
    ],
    "sg:phone":"+41 71 377 12 21",
    "sg:postcode":"8765",
    "sg:province":"Glarus",
    "sg:tags":[
        "koch-",
        "haushaltschulen"
    ],
    "wof:name":"Haushaltungsschule",
    "wof:placetype":"venue"
},
  "geometry": {"coordinates":[9.1517906189,46.9848136902],"type":"Point"}
}