{
  "type": "Feature",
  "properties": {
    "iso:country":"CH",
    "sg:address":"Zurlindenstrasse 29",
    "sg:city":"Pratteln",
    "sg:orig_category":"Grosshandel mit Datenverarbeitungsger\u00e4ten Softwareentwicklung U beratung",
    "sg:phone":"+41 81 750 06 40",
    "sg:postcode":"4133",
    "sg:province":"Basel-Landschaft",
    "wof:name":"Imt Information Management Technology Ag",
    "wof:placetype":"venue"
},
  "geometry": {"coordinates":[9.482093811,47.1734733582],"type":"Point"}
}