{
  "type": "Feature",
  "properties": {
    "iso:country":"CH",
    "sg:address":"Sonnenhofstrasse 5",
    "sg:city":"Oberuzwil",
    "sg:classifiers":[
        {
            "category":"Social Services",
            "subcategory":"Child Care",
            "type":"Services"
        }
    ],
    "sg:phone":"+41 71 950 05 92",
    "sg:postcode":"9242",
    "sg:province":"St. Gallen",
    "sg:tags":[
        "baby",
        "product"
    ],
    "wof:name":"Mamis Windelmarkt",
    "wof:placetype":"venue"
},
  "geometry": {"coordinates":[9.115874,47.431747],"type":"Point"}
}