{
  "type": "Feature",
  "properties": {
    "iso:country":"CH",
    "sg:address":"Obermatt 6",
    "sg:city":"Rupperswil",
    "sg:orig_category":"Grosshandel mit Holz U Baustoffen",
    "sg:phone":"+41 79 407 67 61",
    "sg:postcode":"5102",
    "sg:province":"Aargau",
    "wof:name":"Bivag Bauinventar-vermittlung Ag",
    "wof:placetype":"venue"
},
  "geometry": {"coordinates":[8.1288881302,47.3969039917],"type":"Point"}
}