{
  "type": "Feature",
  "properties": {
    "iso:country":"CH",
    "sg:address":"Grabenweg 10 4242 Laufen. Postfach",
    "sg:city":"Laufen",
    "sg:orig_category":"Arztpraxen",
    "sg:phone":"+41 18410787",
    "sg:postcode":"4242",
    "sg:province":"Basel-Landschaft",
    "wof:name":"Dr.med.daniel Gerber Arzt F.allgemeine Medizin Fmh",
    "wof:placetype":"venue"
},
  "geometry": {"coordinates":[8.463144,47.451862],"type":"Point"}
}