{
  "type": "Feature",
  "properties": {
    "iso:country":"CH",
    "sg:address":"6018",
    "sg:city":"Buttisholz",
    "sg:orig_category":"Interessenvertretungen",
    "sg:postcode":"6018",
    "sg:province":"Luzern",
    "wof:name":"Meyer-steger Vinz. Stipendien-stiftung",
    "wof:placetype":"venue"
},
  "geometry": {"coordinates":[8.0937595367,47.1144142151],"type":"Point"}
}