{
  "type": "Feature",
  "properties": {
    "iso:country":"CH",
    "sg:address":"Rue Des Acacias 8",
    "sg:city":"Neuch\u00e2tel",
    "sg:orig_category":"Sportvereine Sch\u00fctzen Pistolen-& Gewehr",
    "sg:postcode":"2000",
    "sg:province":"Neuch\u00e2tel",
    "wof:name":"Ste De Tir L'inf.sect.pistolet",
    "wof:placetype":"venue"
},
  "geometry": {"coordinates":[6.9216580391,47.0004501343],"type":"Point"}
}