{
  "type": "Feature",
  "properties": {
    "iso:country":"CH",
    "sg:address":"Rue De La Fontaine",
    "sg:city":"Fully",
    "sg:orig_category":"RESTAURANTS: TEA-ROOMS",
    "sg:phone":"+41 27 746 37 71",
    "sg:postcode":"1926",
    "sg:province":"Valais",
    "wof:name":"Roduit Denis",
    "wof:placetype":"venue"
},
  "geometry": {"coordinates":[7.1115407944,46.1398239136],"type":"Point"}
}