{
  "type": "Feature",
  "properties": {
    "iso:country":"CH",
    "sg:address":"Weidackerstrasse 5",
    "sg:city":"Langenthal",
    "sg:orig_category":"Herstellung von Metallerzeugnissen ohne Maschinenbau Herstellung von elektrischen Haushaltsger\u00e4ten",
    "sg:phone":"+41 62 922 77 14",
    "sg:postcode":"4900",
    "sg:province":"Bern",
    "wof:name":"Ren\u00e9 Von Gunten Ag Fahrzeug-& Industriek\u00fchler",
    "wof:placetype":"venue"
},
  "geometry": {"coordinates":[7.7704977989,47.2153816223],"type":"Point"}
}