{
  "type": "Feature",
  "properties": {
    "iso:country":"CH",
    "sg:address":"Bertastrasse 14",
    "sg:city":"Dietikon",
    "sg:orig_category":"Bauschreinerei Herstellung von Konstruktionsteilen, Fertigbauteilen U Ausbauelementen aus Holz",
    "sg:phone":"+41 17402497",
    "sg:postcode":"8953",
    "sg:province":"Z\u00fcrich",
    "wof:name":"Oechslin Ag Schreinerei & Innenausbau",
    "wof:placetype":"venue"
},
  "geometry": {"coordinates":[8.403104,47.402084],"type":"Point"}
}