{
  "type": "Feature",
  "properties": {
    "iso:country":"CH",
    "sg:address":"Wiesenstrasse 7",
    "sg:city":"Bichelsee",
    "sg:orig_category":"Naturheil\u00e4rzte and Heilpraktiker",
    "sg:phone":"+41 71 971 38 07",
    "sg:postcode":"8363",
    "sg:province":"Thurgau",
    "wof:name":"Rolf Nick Hom\u00f6opathie",
    "wof:placetype":"venue"
},
  "geometry": {"coordinates":[8.9278106689,47.4503479004],"type":"Point"}
}