{
  "type": "Feature",
  "properties": {
    "addr:full":"Chemin De L'esplanade 22 Vernier Gen\u00e8ve 1214",
    "addr:housenumber":"22",
    "addr:postcode":"1214",
    "addr:street":"Chemin De L'Esplanade",
    "iso:country":"CH",
    "sg:address":"Chemin De L'esplanade 22",
    "sg:city":"Vernier",
    "sg:orig_category":"Architekturb\u00fcros",
    "sg:phone":"+41 22 341 24 89",
    "sg:postcode":"1214",
    "sg:province":"Gen\u00e8ve",
    "wof:name":"Carl Kleiner Bureau D'architecture",
    "wof:placetype":"venue"
},
  "geometry": {"coordinates":[6.088913,46.215656],"type":"Point"}
}