{
  "type": "Feature",
  "properties": {
    "addr:full":"Leukerbad Valais 3954",
    "addr:postcode":"3954",
    "iso:country":"CH",
    "sg:city":"Leukerbad",
    "sg:classifiers":[
        {
            "category":"Banks & Credit Unions",
            "subcategory":"Bank",
            "type":"Services"
        }
    ],
    "sg:phone":"+41 27 472 78 80",
    "sg:postcode":"3954",
    "sg:province":"Valais",
    "wof:name":"Raiffeisenbank",
    "wof:placetype":"venue"
},
  "geometry": {"coordinates":[7.625326,46.375931],"type":"Point"}
}