{
  "type": "Feature",
  "properties": {
    "iso:country":"CH",
    "sg:address":"Niederfeldstrasse 53",
    "sg:city":"Winterthur",
    "sg:orig_category":"Autogaragen Autospenglereien",
    "sg:phone":"+41 52 222 68 88",
    "sg:postcode":"8408",
    "sg:province":"Z\u00fcrich",
    "wof:name":"Guido B\u00fcchel Autoreparaturen & Carrosserie",
    "wof:placetype":"venue"
},
  "geometry": {"coordinates":[8.677257,47.510288],"type":"Point"}
}