{
  "type": "Feature",
  "properties": {
    "iso:country":"CH",
    "sg:address":"Av. Cardinal- Mermillod 6",
    "sg:city":"Carouge",
    "sg:classifiers":[
        {
            "category":"Shopping",
            "subcategory":"Computers & Home Electronics",
            "type":"Retail Goods"
        }
    ],
    "sg:phone":"+41 26 347 12 20",
    "sg:postcode":"1227",
    "sg:province":"Gen\u00e8ve",
    "sg:tags":[
        "chamber",
        "commerce"
    ],
    "wof:name":"Fribourg Chamber Of Commerce And Industry",
    "wof:placetype":"venue"
},
  "geometry": {"coordinates":[5.732222,46.70163],"type":"Point"}
}