{
  "type": "Feature",
  "properties": {
    "iso:country":"CH",
    "sg:address":"T\u00f6distrasse 27 8002 Z\u00fcrich. Postfach",
    "sg:city":"Z\u00fcrich",
    "sg:orig_category":"Unclassifiable Establishments",
    "sg:phone":"+41 12835900",
    "sg:postcode":"8001",
    "sg:province":"Z\u00fcrich",
    "wof:name":"Vontobel Holding Ag",
    "wof:placetype":"venue"
},
  "geometry": {"coordinates":[8.5348043442,47.3657341003],"type":"Point"}
}