{
  "type": "Feature",
  "properties": {
    "iso:country":"CH",
    "sg:address":"Seefeldweg 1",
    "sg:city":"Grellingen",
    "sg:orig_category":"Unclassifiable Establishments",
    "sg:postcode":"4203",
    "sg:province":"Basel-Landschaft",
    "wof:name":"R. Schweizer, Treuhand Und Consulting",
    "wof:placetype":"venue"
},
  "geometry": {"coordinates":[7.5962018967,47.4398345947],"type":"Point"}
}