{
  "type": "Feature",
  "properties": {
    "iso:country":"CH",
    "sg:address":"Feldblumenstrasse 33",
    "sg:city":"Adliswil",
    "sg:orig_category":"Elektroinstallation",
    "sg:phone":"+41 17103543",
    "sg:postcode":"8134",
    "sg:province":"Z\u00fcrich",
    "wof:name":"Weyermann Arthur",
    "wof:placetype":"venue"
},
  "geometry": {"coordinates":[8.5160551071,47.3150062561],"type":"Point"}
}