{
  "type": "Feature",
  "properties": {
    "iso:country":"CH",
    "sg:address":"Chalet En Avouillon",
    "sg:city":"Leysin",
    "sg:orig_category":"Forstwirtschaft ohne Dienstleistungen in der Forstwirtschaft",
    "sg:phone":"+41 24 494 10 68",
    "sg:postcode":"1854",
    "sg:province":"Vaud",
    "wof:name":"Baumberger Guy",
    "wof:placetype":"venue"
},
  "geometry": {"coordinates":[7.0123200417,46.3469238281],"type":"Point"}
}