{
  "type": "Feature",
  "properties": {
    "iso:country":"CH",
    "sg:address":"Hauptstrasse 67",
    "sg:city":"Niederg\u00f6sgen",
    "sg:orig_category":"Unternehmensberatung",
    "sg:phone":"+41 62 849 00 11",
    "sg:postcode":"5013",
    "sg:province":"Solothurn",
    "wof:name":"B & D Consulting + Services Gmbh",
    "wof:placetype":"venue"
},
  "geometry": {"coordinates":[7.9898881912,47.372013092],"type":"Point"}
}