{
  "type": "Feature",
  "properties": {
    "iso:country":"CH",
    "sg:address":"Avenue De La Gare 1",
    "sg:city":"Fribourg",
    "sg:orig_category":"Detailhandel mit Schuhen",
    "sg:phone":"+41 26 323 36 91",
    "sg:postcode":"1700",
    "sg:province":"Fribourg",
    "wof:name":"Vincenzo Carbone Chaussures Enzo-enzo",
    "wof:placetype":"venue"
},
  "geometry": {"coordinates":[7.1512551308,46.8025474548],"type":"Point"}
}