{
  "type": "Feature",
  "properties": {
    "iso:country":"CH",
    "sg:address":"Oberdorfstrasse 93",
    "sg:city":"Grasswil",
    "sg:orig_category":"Detailhandel mit Waren verschiedener Art, Hauptrichtung Nahrungsmittel",
    "sg:phone":"+41 62 968 11 24",
    "sg:postcode":"3365",
    "sg:province":"Bern",
    "wof:name":"Greti Buchser Handlung",
    "wof:placetype":"venue"
},
  "geometry": {"coordinates":[7.6688871384,47.1410064697],"type":"Point"}
}