{
  "type": "Feature",
  "properties": {
    "iso:country":"CH",
    "sg:address":"Lindenstrasse 45",
    "sg:city":"Grenchen",
    "sg:orig_category":"Herstellung U Zusammensetzung von Uhren",
    "sg:phone":"+41 32 653 33 60",
    "sg:postcode":"2540",
    "sg:province":"Solothurn",
    "wof:name":"Franz Forster Terminages-atelier",
    "wof:placetype":"venue"
},
  "geometry": {"coordinates":[7.3889780045,47.1904525757],"type":"Point"}
}