{
  "type": "Feature",
  "properties": {
    "iso:country":"CH",
    "sg:address":"Schulstrasse 1",
    "sg:city":"Neuenhof",
    "sg:orig_category":"Verwaltung von Immobilien Wirtschaftspr\u00fcfung, Steuerberatung U Treuhand",
    "sg:phone":"+41 56 410 00 51",
    "sg:postcode":"5432",
    "sg:province":"Aargau",
    "wof:name":"Interna Treuhandgesellschaft",
    "wof:placetype":"venue"
},
  "geometry": {"coordinates":[8.3239297867,47.4535217285],"type":"Point"}
}