{
  "type": "Feature",
  "properties": {
    "iso:country":"CH",
    "sg:address":"Monthoux Rue De 23 1201 Gen\u00e8ve. Postfach",
    "sg:city":"Gen\u00e8ve",
    "sg:classifiers":[
        {
            "category":"Bars & Pubs",
            "type":"Food & Drink"
        }
    ],
    "sg:postcode":"1201",
    "sg:province":"Gen\u00e8ve",
    "wof:name":"Masisa, Michelizza Bar New Titanic",
    "wof:placetype":"venue"
},
  "geometry": {"coordinates":[6.148152,46.210491],"type":"Point"}
}