{
  "type": "Feature",
  "properties": {
    "iso:country":"CH",
    "sg:address":"Ringstrasse 9 4123 Allschwil. Postfach",
    "sg:city":"Allschwil",
    "sg:orig_category":"Grosshandel mit Textilien",
    "sg:phone":"+41 41 917 23 58",
    "sg:postcode":"4123",
    "sg:province":"Basel-Landschaft",
    "wof:name":"Bimbo-tex-versand Ren\u00e9 J. Stoffel",
    "wof:placetype":"venue"
},
  "geometry": {"coordinates":[8.2346000671,47.2583198547],"type":"Point"}
}