{
  "type": "Feature",
  "properties": {
    "iso:country":"CH",
    "sg:address":"6777",
    "sg:city":"Quinto",
    "sg:orig_category":"Grosshandel mit Getr\u00e4nken",
    "sg:postcode":"6777",
    "sg:province":"Ticino",
    "wof:name":"Zamberlani Graziella.",
    "wof:placetype":"venue"
},
  "geometry": {"coordinates":[8.713385582,46.5107307434],"type":"Point"}
}