{
  "type": "Feature",
  "properties": {
    "iso:country":"CH",
    "sg:address":"R\u00f6ssligasse 10 4132 Muttenz. Postfach 358",
    "sg:city":"Muttenz",
    "sg:orig_category":"Grosshandel mit Holz U Baustoffen",
    "sg:phone":"+41 61 943 10 25",
    "sg:postcode":"4132",
    "sg:province":"Basel-Landschaft",
    "wof:name":"Hess Martin Natursteine Gmbh",
    "wof:placetype":"venue"
},
  "geometry": {"coordinates":[7.6490430832,47.5249137878],"type":"Point"}
}