{
  "type": "Feature",
  "properties": {
    "addr:full":"Auf Den Fl\u00fchen 3157 Milken. Postfach Milken Bern 3157",
    "addr:postcode":"3157;3157",
    "addr:street":"Auf Den Fluehen;Postfach",
    "iso:country":"CH",
    "sg:address":"Auf Den Fl\u00fchen 3157 Milken. Postfach",
    "sg:city":"Milken",
    "sg:orig_category":"Allgemeiner Hoch U Tiefbau",
    "sg:phone":"+41 31355276",
    "sg:postcode":"3157",
    "sg:province":"Bern",
    "wof:name":"Stoll Daniel, Hoch Und Tiefbau",
    "wof:placetype":"venue"
},
  "geometry": {"coordinates":[7.359111,46.793095],"type":"Point"}
}