{
  "type": "Feature",
  "properties": {
    "iso:country":"CH",
    "sg:address":"Hinterbergstrasse 40",
    "sg:city":"Steinhausen",
    "sg:orig_category":"Unclassifiable Establishments",
    "sg:phone":"+41 41 743 17 60",
    "sg:postcode":"6312",
    "sg:province":"Zug",
    "wof:name":"Beldoro Ag",
    "wof:placetype":"venue"
},
  "geometry": {"coordinates":[8.477312088,47.1912994385],"type":"Point"}
}