{
  "type": "Feature",
  "properties": {
    "iso:country":"CH",
    "sg:address":"Chemin De Muraz",
    "sg:city":"Clarens",
    "sg:orig_category":"Schulpflegen",
    "sg:postcode":"1815",
    "sg:province":"Vaud",
    "wof:name":"Commission Scolaire De L'\u00e9cole Primaire",
    "wof:placetype":"venue"
},
  "geometry": {"coordinates":[6.8969202042,46.4435806274],"type":"Point"}
}