{
  "type": "Feature",
  "properties": {
    "addr:full":"Sageboden 1737 Plasselb. Postfach Plasselb Fribourg 1737",
    "addr:postcode":"1737 plasselb. postfach;1737",
    "addr:street":"Sageboden",
    "iso:country":"CH",
    "sg:address":"Sageboden 1737 Plasselb. Postfach",
    "sg:city":"Plasselb",
    "sg:classifiers":[
        {
            "category":"Bars & Pubs",
            "type":"Food & Drink"
        }
    ],
    "sg:postcode":"1737",
    "sg:province":"Fribourg",
    "wof:name":"P\u00fcrro Felix-josef Und Anita Buvette-betrieb Und Massagen",
    "wof:placetype":"venue"
},
  "geometry": {"coordinates":[7.249298,46.730507],"type":"Point"}
}