{
  "type": "Feature",
  "properties": {
    "iso:country":"CH",
    "sg:address":"Neuhofstrasse 6",
    "sg:city":"Baar",
    "sg:orig_category":"Pensionskassen",
    "sg:phone":"+41 71 387 40 40",
    "sg:postcode":"6340",
    "sg:province":"Zug",
    "wof:name":"Pensionskasse Der Bubenhofer Karl Ag",
    "wof:placetype":"venue"
},
  "geometry": {"coordinates":[9.2547521591,47.4144287109],"type":"Point"}
}