{
  "type": "Feature",
  "properties": {
    "iso:country":"CH",
    "sg:address":"6595",
    "sg:city":"Riazzino",
    "sg:orig_category":"Detailhandel mit Schuhen",
    "sg:phone":"+41 91 840 91 20",
    "sg:postcode":"6595",
    "sg:province":"Ticino",
    "wof:name":"Dosenbach Calzature",
    "wof:placetype":"venue"
},
  "geometry": {"coordinates":[8.897600174,46.1745605469],"type":"Point"}
}