{
  "type": "Feature",
  "properties": {
    "iso:country":"CH",
    "sg:address":"Nidaugasse 50 2500 Biel/bienne. Postfach",
    "sg:city":"Biel/bienne",
    "sg:orig_category":"Sonstiger Grosshandel",
    "sg:postcode":"2502",
    "sg:province":"Bern",
    "wof:name":"Dino, Niederh\u00e4user Stella & Br\u00fcnisholz Verena",
    "wof:placetype":"venue"
},
  "geometry": {"coordinates":[7.2464189529,47.1385955811],"type":"Point"}
}