{
  "type": "Feature",
  "properties": {
    "iso:country":"CH",
    "sg:address":"Schiblismattstrasse 6",
    "sg:city":"Ettingen",
    "sg:orig_category":"Sonstiges Versicherungsgewerbe",
    "sg:phone":"+41 61 721 49 91",
    "sg:postcode":"4107",
    "sg:province":"Basel-Landschaft",
    "wof:name":"Generalagentur Martino Vincenzo",
    "wof:placetype":"venue"
},
  "geometry": {"coordinates":[7.5511617661,47.4843559265],"type":"Point"}
}