{
  "type": "Feature",
  "properties": {
    "iso:country":"CH",
    "sg:address":"Via Giuseppe Motta 15",
    "sg:city":"Lugano",
    "sg:orig_category":"Ern\u00e4hrungsberatung",
    "sg:phone":"+41 91 921 15 41",
    "sg:postcode":"6900",
    "sg:province":"Ticino",
    "wof:name":"Studio Di Consulenza E Terapia Dietetica",
    "wof:placetype":"venue"
},
  "geometry": {"coordinates":[8.9495391846,46.0026168823],"type":"Point"}
}