{
  "type": "Feature",
  "properties": {
    "iso:country":"CH",
    "sg:address":"Grand'rue 52",
    "sg:city":"Rolle",
    "sg:orig_category":"Detailhandel mit Uhren U Schmuck Fachdetailhandel in Verkaufsr\u00e4umen",
    "sg:phone":"+41 21 825 38 29",
    "sg:postcode":"1180",
    "sg:province":"Vaud",
    "wof:name":"Argentum Zarina Gutowski Argenterie & Objets D'arts",
    "wof:placetype":"venue"
},
  "geometry": {"coordinates":[6.3382320404,46.4575157166],"type":"Point"}
}