{
  "type": "Feature",
  "properties": {
    "iso:country":"CH",
    "sg:address":"Birkenweg 11",
    "sg:city":"D\u00fcbendorf",
    "sg:orig_category":"Non-Classified Establishments",
    "sg:postcode":"8600",
    "sg:province":"Z\u00fcrich",
    "wof:name":"Sisu Gmbh",
    "wof:placetype":"venue"
},
  "geometry": {"coordinates":[8.6290845871,47.4056434631],"type":"Point"}
}