{
  "type": "Feature",
  "properties": {
    "iso:country":"CH",
    "sg:address":"Kirchgasse",
    "sg:city":"Bonaduz",
    "sg:classifiers":[
        {
            "category":"Travel",
            "subcategory":"Hotels & Motels",
            "type":"Entertainment"
        }
    ],
    "sg:phone":"+41 81 641 27 17",
    "sg:postcode":"7402",
    "sg:province":"Graubunden",
    "sg:tags":[
        "equipment",
        "hotels",
        "restaurant"
    ],
    "wof:name":"Eugster Hotelbedarf Ag",
    "wof:placetype":"venue"
},
  "geometry": {"coordinates":[9.4015951157,46.8121604919],"type":"Point"}
}