{
  "type": "Feature",
  "properties": {
    "iso:country":"CH",
    "sg:address":"Ristenb\u00fchl-matzingen.",
    "sg:city":"Matzingen",
    "sg:orig_category":"Kalb U Schweine-M\u00e4sterei U Zucht",
    "sg:postcode":"9548",
    "sg:province":"Thurgau",
    "wof:name":"Amsler + Oberle Mastbetriebe",
    "wof:placetype":"venue"
},
  "geometry": {"coordinates":[8.1901035309,47.4134101868],"type":"Point"}
}