{
  "type": "Feature",
  "properties": {
    "iso:country":"CH",
    "sg:address":"Steinenweg 10",
    "sg:city":"Zunzgen",
    "sg:orig_category":"Bauschreinerei Einbau von Schreinerwaren",
    "sg:phone":"+41 61 971 48 00",
    "sg:postcode":"4455",
    "sg:province":"Basel-Landschaft",
    "wof:name":"Lukas Hofer Schreinerei & K\u00fcchenbau",
    "wof:placetype":"venue"
},
  "geometry": {"coordinates":[7.805009,47.451061],"type":"Point"}
}