{
  "type": "Feature",
  "properties": {
    "iso:country":"CH",
    "sg:address":"7084",
    "sg:city":"Brienz/brinzauls",
    "sg:orig_category":"Lagerung",
    "sg:postcode":"7084",
    "sg:province":"Graubunden",
    "wof:name":"Tiefk\u00fchlanlage-genossenschaft Brienz.",
    "wof:placetype":"venue"
},
  "geometry": {"coordinates":[9.5956497192,46.6689834595],"type":"Point"}
}