{
  "type": "Feature",
  "properties": {
    "iso:country":"CH",
    "sg:address":"3975 Bluche-randogne. Postfach",
    "sg:city":"Montana-vermala",
    "sg:orig_category":"Erbringung von Dienstleistungen f\u00fcr Unternehmen",
    "sg:postcode":"3962",
    "wof:name":"Mirel Nevin Mme.",
    "wof:placetype":"venue"
},
  "geometry": {"coordinates":[7.5151138306,46.2997512817],"type":"Point"}
}