{
  "type": "Feature",
  "properties": {
    "iso:country":"CH",
    "sg:address":"Bahnhofstrasse 42 2502 Biel/bienne Case Postale 184",
    "sg:city":"Biel/bienne",
    "sg:orig_category":"Herstellung von Schmuck, Gold U Silberschmiedwaren Herstellung von sonstigen Metallwaren",
    "sg:phone":"+41 32 323 30 50",
    "sg:postcode":"2501",
    "sg:province":"Bern",
    "wof:name":"Sch\u00fcll Gravuren",
    "wof:placetype":"venue"
},
  "geometry": {"coordinates":[7.2458691597,47.1358604431],"type":"Point"}
}