{
  "type": "Feature",
  "properties": {
    "iso:country":"CH",
    "sg:address":"W\u00fcrzenbachstrasse 17",
    "sg:city":"Luzern",
    "sg:orig_category":"Non-Classified Establishments",
    "sg:postcode":"6006",
    "sg:province":"Luzern",
    "wof:name":"Dr.med.hansjost Bucher Spezialarzt Fmh",
    "wof:placetype":"venue"
},
  "geometry": {"coordinates":[8.3435163498,47.0549850464],"type":"Point"}
}