{
  "type": "Feature",
  "properties": {
    "iso:country":"CH",
    "sg:address":"Engelwisstrasse 3 8180 B\u00fclach. Postfach 58",
    "sg:city":"B\u00fclach",
    "sg:orig_category":"Mechanik Mechanische Werkst\u00e4tten",
    "sg:phone":"+41 18601689",
    "sg:postcode":"8180",
    "sg:province":"Z\u00fcrich",
    "wof:name":"Stutz Mechanik Ag",
    "wof:placetype":"venue"
},
  "geometry": {"coordinates":[8.5371160507,47.5101509094],"type":"Point"}
}