{
  "type": "Feature",
  "properties": {
    "iso:country":"CH",
    "sg:address":"Merkurstrasse 34",
    "sg:city":"Z\u00fcrich",
    "sg:orig_category":"Unclassifiable Establishments",
    "sg:phone":"+41 12522129",
    "sg:postcode":"8032",
    "sg:province":"Z\u00fcrich",
    "wof:name":"Alliance Fran\u00e7aise De Zurich",
    "wof:placetype":"venue"
},
  "geometry": {"coordinates":[8.5540456772,47.3669128418],"type":"Point"}
}