{
  "type": "Feature",
  "properties": {
    "iso:country":"CH",
    "sg:address":"L\u00e4nggassstrasse 47",
    "sg:city":"Bern",
    "sg:orig_category":"Detailhandel mit Waren verschiedener Art, Hauptrichtung Nahrungsmittel",
    "sg:phone":"+41 31 302 15 28",
    "sg:postcode":"3012",
    "sg:province":"Bern",
    "wof:name":"L\u00e4nggass-tee Lange Katrin Und Gerhard",
    "wof:placetype":"venue"
},
  "geometry": {"coordinates":[7.430729866,46.9545097351],"type":"Point"}
}