{
  "type": "Feature",
  "properties": {
    "addr:full":"Gartenstrasse 12 Neuenegg Bern 3176",
    "addr:housenumber":"12",
    "addr:postcode":"3176",
    "addr:street":"Gartenstrasse;Bern",
    "iso:country":"CH",
    "sg:address":"Gartenstrasse 12",
    "sg:city":"Neuenegg",
    "sg:orig_category":"Detailhandel mit Blumen U Pflanzen",
    "sg:phone":"+41 31 839 00 40",
    "sg:postcode":"3176",
    "sg:province":"Bern",
    "wof:name":"Monika Ajvazi Blumenhaus Beim Schl\u00f6ssli",
    "wof:placetype":"venue"
},
  "geometry": {"coordinates":[7.531106,46.930614],"type":"Point"}
}