{
  "type": "Feature",
  "properties": {
    "iso:country":"CH",
    "sg:address":"Avenue De Jurigoz 13bis",
    "sg:city":"Lausanne",
    "sg:orig_category":"Geb\u00e4ude, Wohnungsreinigung Reinigungsgewerbe",
    "sg:phone":"+41 21 617 08 39",
    "sg:postcode":"1006",
    "sg:province":"Vaud",
    "wof:name":"Albos S\u00e0rl",
    "wof:placetype":"venue"
},
  "geometry": {"coordinates":[6.6373457909,46.511932373],"type":"Point"}
}