{
  "type": "Feature",
  "properties": {
    "iso:country":"CH",
    "sg:address":"Rue De La Poste 6a",
    "sg:city":"Martigny",
    "sg:orig_category":"Fachdetailhandel in Verkaufsr\u00e4umen",
    "sg:postcode":"1920",
    "sg:province":"Valais",
    "wof:name":"Betschart & Rosskopf, Dipl. Augenoptiker",
    "wof:placetype":"venue"
},
  "geometry": {"coordinates":[9.0455789566,47.4650382996],"type":"Point"}
}