{
  "type": "Feature",
  "properties": {
    "addr:full":"Pl. H\u00f4tel-de-ville 2 Morges Vaud 1110",
    "addr:housenumber":"2",
    "addr:postcode":"1110",
    "addr:street":"Pl. Ho\u0302Tel-De-Ville",
    "iso:country":"CH",
    "sg:address":"Pl. H\u00f4tel-de-ville 2",
    "sg:city":"Morges",
    "sg:classifiers":[
        {
            "category":"Banks & Credit Unions",
            "subcategory":"Bank",
            "type":"Services"
        }
    ],
    "sg:phone":"+41 21 804 05 55",
    "sg:postcode":"1110",
    "sg:province":"Vaud",
    "wof:name":"Banque Cantonale Vaudoise",
    "wof:placetype":"venue"
},
  "geometry": {"coordinates":[6.497665,46.507919],"type":"Point"}
}