{
  "type": "Feature",
  "properties": {
    "iso:country":"CH",
    "sg:address":"Hohlenweg 2",
    "sg:city":"Bellmund",
    "sg:orig_category":"Stukkateurgewerbe, Gipserei U Verputzerei",
    "sg:postcode":"2564",
    "sg:province":"Bern",
    "wof:name":"Egli Ag Gips Und Fassadensysteme",
    "wof:placetype":"venue"
},
  "geometry": {"coordinates":[7.2452368736,47.1071128845],"type":"Point"}
}