{
  "type": "Feature",
  "properties": {
    "iso:country":"CH",
    "sg:address":"St-pierre Route 3",
    "sg:city":"Estavayer-le-lac",
    "sg:orig_category":"Wirtschaftspr\u00fcfung, Steuerberatung U Treuhand",
    "sg:postcode":"1470",
    "sg:province":"Fribourg",
    "wof:name":"Chanez D. S\u00e0rl",
    "wof:placetype":"venue"
},
  "geometry": {"coordinates":[6.8451771736,46.8469543457],"type":"Point"}
}