{
  "type": "Feature",
  "properties": {
    "iso:country":"CH",
    "sg:address":"Luzernerstrasse 80",
    "sg:city":"Cham",
    "sg:orig_category":"Verm\u00f6gensverwaltung",
    "sg:phone":"+41 77678334",
    "sg:postcode":"6330",
    "sg:province":"Zug",
    "wof:name":"Ruedi Lehmann",
    "wof:placetype":"venue"
},
  "geometry": {"coordinates":[8.4508399963,47.1750717163],"type":"Point"}
}