{
  "type": "Feature",
  "properties": {
    "iso:country":"CH",
    "sg:address":"Halten",
    "sg:city":"Saanen",
    "sg:orig_category":"Bau von Strassen, Sportanlagen U Bahnverkehrsstrecken",
    "sg:postcode":"3792",
    "sg:province":"Bern",
    "wof:name":"Weggenossenschaft Halten-saanen.",
    "wof:placetype":"venue"
},
  "geometry": {"coordinates":[7.266528,46.493717],"type":"Point"}
}