{
  "type": "Feature",
  "properties": {
    "iso:country":"CH",
    "sg:address":"Weinfelderstrasse 30 8580 Amriswil. Postfach",
    "sg:city":"Amriswil",
    "sg:orig_category":"Malerei",
    "sg:phone":"+41 71 411 30 22",
    "sg:postcode":"8580",
    "sg:province":"Thurgau",
    "wof:name":"Maurer Ag Malerarbeiten",
    "wof:placetype":"venue"
},
  "geometry": {"coordinates":[9.2937164307,47.5453834534],"type":"Point"}
}