{
  "type": "Feature",
  "properties": {
    "iso:country":"CH",
    "sg:address":"Martin Rue Camille- 17 1203 Gen\u00e8ve. Postfach",
    "sg:city":"Gen\u00e8ve",
    "sg:orig_category":"Druckweiterverarbeitung",
    "sg:phone":"+41 22 345 53 22",
    "sg:postcode":"1203",
    "sg:province":"Gen\u00e8ve",
    "wof:name":"Oeuvray Jean-fran\u00e7ois",
    "wof:placetype":"venue"
},
  "geometry": {"coordinates":[6.115773201,46.2069664001],"type":"Point"}
}