{
  "type": "Feature",
  "properties": {
    "iso:country":"CH",
    "sg:address":"Cassarate 6900 Lugano. Postfach 6906 Lugano",
    "sg:city":"Caselle",
    "sg:orig_category":"Sanit\u00e4r, Heizungs U L\u00fcftungsinstallation",
    "sg:postcode":"6",
    "wof:name":"Gavazzini Emilio",
    "wof:placetype":"venue"
},
  "geometry": {"coordinates":[8.9600763321,46.0083770752],"type":"Point"}
}