{
  "type": "Feature",
  "properties": {
    "iso:country":"CH",
    "sg:address":"Rue Du Ch\u00e2tillon",
    "sg:city":"P\u00e9ry",
    "sg:orig_category":"Organisationen des Gesundheitswesen",
    "sg:phone":"+41 32 485 15 75",
    "sg:postcode":"2603",
    "sg:province":"Bern",
    "wof:name":"St\u00e9 Des Samaritains P\u00e9ry-la Heutte",
    "wof:placetype":"venue"
},
  "geometry": {"coordinates":[7.2503299713,47.1911125183],"type":"Point"}
}