{
  "type": "Feature",
  "properties": {
    "iso:country":"CH",
    "sg:address":"Hochstrasse 26",
    "sg:city":"Z\u00fcrich",
    "sg:orig_category":"Wirtschaftspr\u00fcfung, Steuerberatung U Treuhand",
    "sg:phone":"+41 12615545",
    "sg:postcode":"8044",
    "sg:province":"Z\u00fcrich",
    "wof:name":"Rema Versicherungs-treuhand Gmbh",
    "wof:placetype":"venue"
},
  "geometry": {"coordinates":[8.5517950058,47.3805084229],"type":"Point"}
}