{
  "type": "Feature",
  "properties": {
    "iso:country":"CH",
    "sg:address":"Zeughausgasse 9a 6300 Zug. Postfach",
    "sg:city":"Zug",
    "sg:orig_category":"Unclassifiable Establishments",
    "sg:postcode":"6300",
    "sg:province":"Zug",
    "wof:name":"Krassim Ag Beteiligungen Usw",
    "wof:placetype":"venue"
},
  "geometry": {"coordinates":[8.5162611008,47.1669158936],"type":"Point"}
}