{
  "type": "Feature",
  "properties": {
    "addr:full":"Th\u00fcringstrasse 23/e7 Bern Bern 3018",
    "addr:housenumber":"23 / e7",
    "addr:postcode":"3018",
    "addr:street":"Thueringstrasse",
    "iso:country":"CH",
    "sg:address":"Th\u00fcringstrasse 23/e7",
    "sg:city":"Bern",
    "sg:orig_category":"Bauspenglerei Dachdeckerei",
    "sg:phone":"+41 32 757 21 31",
    "sg:postcode":"3018",
    "sg:province":"Bern",
    "wof:name":"R\u00e9my Favre Echafaudages Sa Ferblanterie & Couverture",
    "wof:placetype":"venue"
},
  "geometry": {"coordinates":[7.029662,47.036442],"type":"Point"}
}