{
  "type": "Feature",
  "properties": {
    "iso:country":"CH",
    "sg:address":"Hauptstrasse 64",
    "sg:city":"Menziken",
    "sg:orig_category":"Detailhandel mit Fahrr\u00e4dern Fachdetailhandel in Verkaufsr\u00e4umen",
    "sg:phone":"+41 90559560",
    "sg:postcode":"5737",
    "sg:province":"Aargau",
    "wof:name":"Technosurf",
    "wof:placetype":"venue"
},
  "geometry": {"coordinates":[6.124751091,46.2348861694],"type":"Point"}
}