{
  "type": "Feature",
  "properties": {
    "iso:country":"CH",
    "sg:address":"Aareckstrasse 6",
    "sg:city":"Interlaken",
    "sg:orig_category":"Versicherungen Hauptagenturen",
    "sg:phone":"+41 55 415 70 05",
    "sg:postcode":"3800",
    "sg:province":"Bern",
    "wof:name":"Basler Versicherungen Hauptagentur",
    "wof:placetype":"venue"
},
  "geometry": {"coordinates":[8.7781352997,47.2013778687],"type":"Point"}
}