{
  "type": "Feature",
  "properties": {
    "iso:country":"CH",
    "sg:address":"Postplatz 2 6064 Kerns. Postfach 24",
    "sg:city":"Kerns",
    "sg:orig_category":"Werbegrafikateliers",
    "sg:phone":"+41 41 662 05 00",
    "sg:postcode":"6064",
    "sg:province":"Obwalden",
    "wof:name":"Gaas Grafisches Atelier",
    "wof:placetype":"venue"
},
  "geometry": {"coordinates":[8.2747364044,46.9009513855],"type":"Point"}
}