{
  "type": "Feature",
  "properties": {
    "iso:country":"CH",
    "sg:address":"Isenegg 5",
    "sg:city":"Tobel",
    "sg:orig_category":"Unclassifiable Establishments",
    "sg:postcode":"9555",
    "sg:province":"Thurgau",
    "wof:name":"Etz Gmbh",
    "wof:placetype":"venue"
},
  "geometry": {"coordinates":[9.0303897858,47.5119667053],"type":"Point"}
}