{
  "type": "Feature",
  "properties": {
    "iso:country":"CH",
    "sg:address":"Terbinerstrasse 12 3930 Visp. Postfach 344",
    "sg:city":"Visp",
    "sg:orig_category":"D\u00e4mmung gegen K\u00e4lte, W\u00e4rme, Schall U Ersch\u00fctterung Herstellung von sonstigen Metallwaren",
    "sg:phone":"+41 21 624 22 88",
    "sg:postcode":"3930",
    "sg:province":"Valais",
    "wof:name":"Alraun O.",
    "wof:placetype":"venue"
},
  "geometry": {"coordinates":[6.5984740257,46.5304641724],"type":"Point"}
}