{
  "type": "Feature",
  "properties": {
    "iso:country":"CH",
    "sg:address":"Murtenstrasse 33",
    "sg:city":"Biel/bienne",
    "sg:orig_category":"Gesundheitswesen Physiotherapie",
    "sg:phone":"+41 32 323 26 02",
    "sg:postcode":"2503",
    "sg:province":"Bern",
    "wof:name":"Lavanchy Marcel",
    "wof:placetype":"venue"
},
  "geometry": {"coordinates":[7.2466750145,47.1348648071],"type":"Point"}
}