{
  "type": "Feature",
  "properties": {
    "iso:country":"CH",
    "sg:address":"Oetlingerstrasse 50",
    "sg:city":"Basel",
    "sg:orig_category":"Kosmetikinstitute",
    "sg:phone":"+41 61 692 87 18",
    "sg:postcode":"4057",
    "sg:province":"Basel-Stadt",
    "wof:name":"Roswitha Hirlemann Kosmetikinstitut Yon-ka",
    "wof:placetype":"venue"
},
  "geometry": {"coordinates":[7.5895881653,47.567401886],"type":"Point"}
}