{
  "type": "Feature",
  "properties": {
    "iso:country":"CH",
    "sg:address":"Cadonaustrasse 75 7000 Chur. Postfach",
    "sg:city":"Chur",
    "sg:orig_category":"Unclassifiable Establishments",
    "sg:phone":"+41 81 354 56 26",
    "sg:postcode":"7000",
    "sg:province":"Graubunden",
    "wof:name":"Samardzic Paketdienst Gmbh Transportunternehmen, Bes. F\u00fcr Pakete. Handelsgesch\u00e4fte Usw",
    "wof:placetype":"venue"
},
  "geometry": {"coordinates":[9.5393896103,46.8663787842],"type":"Point"}
}