{
  "type": "Feature",
  "properties": {
    "iso:country":"CH",
    "sg:address":"Dorfwisenstrasse 14",
    "sg:city":"Sch\u00f6fflisdorf",
    "sg:orig_category":"Kantonalbanken",
    "sg:phone":"+41 19383737",
    "sg:postcode":"8165",
    "sg:province":"Z\u00fcrich",
    "wof:name":"Z\u00fcrcher Kantonalbank",
    "wof:placetype":"venue"
},
  "geometry": {"coordinates":[8.8433914185,47.3016853333],"type":"Point"}
}