{
  "type": "Feature",
  "properties": {
    "iso:country":"CH",
    "sg:address":"Zentralstrasse 156",
    "sg:city":"Z\u00fcrich",
    "sg:orig_category":"Druck ohne Zeitungsdruck Offsetdruck",
    "sg:phone":"+41 14506969",
    "sg:postcode":"8003",
    "sg:province":"Z\u00fcrich",
    "wof:name":"Inka Druck Ag",
    "wof:placetype":"venue"
},
  "geometry": {"coordinates":[8.5144996643,47.375869751],"type":"Point"}
}