{
  "type": "Feature",
  "properties": {
    "iso:country":"CH",
    "sg:address":"Taponnet Chemin 12",
    "sg:city":"Commugny",
    "sg:orig_category":"Sonstige mit der Informatik verbundene T\u00e4tigkeiten",
    "sg:phone":"+41 22 776 34 44",
    "sg:postcode":"1291",
    "sg:province":"Vaud",
    "wof:name":"Atmexpert, Paul-a. Tschopp",
    "wof:placetype":"venue"
},
  "geometry": {"coordinates":[6.1775698662,46.3259048462],"type":"Point"}
}