{
  "type": "Feature",
  "properties": {
    "iso:country":"CH",
    "sg:address":"Fehlwiesstrasse 13",
    "sg:city":"Amriswil",
    "sg:orig_category":"Betrieb von Taxis",
    "sg:phone":"+41 71 911 33 22",
    "sg:postcode":"8580",
    "sg:province":"Thurgau",
    "wof:name":"Bruno H\u00e4ne Bahnhof-taxi",
    "wof:placetype":"venue"
},
  "geometry": {"coordinates":[9.03714,47.478973],"type":"Point"}
}