{
  "type": "Feature",
  "properties": {
    "iso:country":"CH",
    "sg:address":"7202",
    "sg:city":"Says",
    "sg:orig_category":"Sportvereine Sch\u00fctzen",
    "sg:phone":"+41 62 293 52 29",
    "sg:postcode":"7202",
    "sg:province":"Graubunden",
    "wof:name":"Feldsch\u00fctzengesellschaft",
    "wof:placetype":"venue"
},
  "geometry": {"coordinates":[9.5821199417,46.9068107605],"type":"Point"}
}