{
  "type": "Feature",
  "properties": {
    "addr:full":"Krombach 3 9100 Herisau. Postfach Herisau Appenzell Ausserrhoden 9101",
    "addr:housenumber":"3",
    "addr:postcode":"9100 herisau. postfach;9101",
    "addr:street":"Ausserrhoden",
    "iso:country":"CH",
    "sg:address":"Krombach 3 9100 Herisau. Postfach",
    "sg:city":"Herisau",
    "sg:classifiers":[
        {
            "category":"Education",
            "subcategory":"Library",
            "type":"Public Place"
        }
    ],
    "sg:phone":"+41 71 353 81 11",
    "sg:postcode":"9101",
    "sg:province":"Appenzell Ausserrhoden",
    "sg:tags":[
        "u",
        "bibliotheken",
        "archive"
    ],
    "wof:name":"Psychiatrische Klinik Herisau",
    "wof:placetype":"venue"
},
  "geometry": {"coordinates":[9.264654,47.386105],"type":"Point"}
}