{
  "type": "Feature",
  "properties": {
    "iso:country":"CH",
    "sg:address":"Bahnhofstrasse 31",
    "sg:city":"Baden",
    "sg:orig_category":"Sprachschulen",
    "sg:phone":"+41 56 209 12 16",
    "sg:postcode":"5400",
    "sg:province":"Aargau",
    "wof:name":"Matilde Blum-calderon La Escuela De Espa\u00f1ol",
    "wof:placetype":"venue"
},
  "geometry": {"coordinates":[8.3083076477,47.4773483276],"type":"Point"}
}