{
  "type": "Feature",
  "properties": {
    "iso:country":"CH",
    "sg:address":"Wangserstrasse 10",
    "sg:city":"Mels",
    "sg:orig_category":"Nationale Postdienste",
    "sg:phone":"+41 81 723 12 02",
    "sg:postcode":"8887",
    "sg:province":"St. Gallen",
    "wof:name":"Die Schweizerische Post",
    "wof:placetype":"venue"
},
  "geometry": {"coordinates":[9.4198637009,47.0462417603],"type":"Point"}
}