{
  "type": "Feature",
  "properties": {
    "iso:country":"CH",
    "sg:address":"Rte Moncor 6",
    "sg:city":"Fribourg",
    "sg:classifiers":[
        {
            "category":"Food & Beverages",
            "subcategory":"Dairy",
            "type":"Retail Goods"
        }
    ],
    "sg:phone":"+41 34 435 16 11",
    "sg:postcode":"1701",
    "sg:province":"Fribourg",
    "sg:tags":[
        "product",
        "related"
    ],
    "wof:name":"Emmentaler Schauk\u00c4serei Ag",
    "wof:placetype":"venue"
},
  "geometry": {"coordinates":[7.730618,47.065247],"type":"Point"}
}