{
  "type": "Feature",
  "properties": {
    "iso:country":"CH",
    "sg:address":"Rautistrasse 165",
    "sg:city":"Z\u00fcrich",
    "sg:orig_category":"Einbau von Schreinerwaren",
    "sg:phone":"+41 14313893",
    "sg:postcode":"8048",
    "sg:province":"Z\u00fcrich",
    "wof:name":"Herbert Schneider K\u00fccheneinrichtungen",
    "wof:placetype":"venue"
},
  "geometry": {"coordinates":[8.4813137054,47.3842811584],"type":"Point"}
}