{
  "type": "Feature",
  "properties": {
    "iso:country":"CH",
    "sg:address":"Maishaldenstrasse 3",
    "sg:city":"Amriswil",
    "sg:orig_category":"Vereine Tierschutz",
    "sg:phone":"+41 71 411 67 43",
    "sg:postcode":"8580",
    "sg:province":"Thurgau",
    "wof:name":"Tierschutzv.amriswil & Umg.",
    "wof:placetype":"venue"
},
  "geometry": {"coordinates":[9.2995681763,47.54504776],"type":"Point"}
}