{
  "type": "Feature",
  "properties": {
    "iso:country":"CH",
    "sg:address":"Olivier Rue Juste 18",
    "sg:city":"Nyon",
    "sg:orig_category":"Non-Classified Establishments",
    "sg:phone":"+41 22 361 97 61",
    "sg:postcode":"1260",
    "sg:province":"Vaud",
    "wof:name":"Si Face Au Lac",
    "wof:placetype":"venue"
},
  "geometry": {"coordinates":[6.2377147675,46.3846588135],"type":"Point"}
}