{
  "type": "Feature",
  "properties": {
    "iso:country":"CH",
    "sg:address":"Rue Du Pont-mur\u00e9 20",
    "sg:city":"Fribourg",
    "sg:orig_category":"Fachdetailhandel mit pharmazeutischen Produkten",
    "sg:phone":"+41 26 322 23 73",
    "sg:postcode":"1700",
    "sg:province":"Fribourg",
    "wof:name":"Pharmacie Du Tilleul Sa",
    "wof:placetype":"venue"
},
  "geometry": {"coordinates":[7.1618452072,46.8062133789],"type":"Point"}
}