{
  "type": "Feature",
  "properties": {
    "iso:country":"CH",
    "sg:address":"Kyburgerweg 4",
    "sg:city":"Dietlikon",
    "sg:orig_category":"Herstellung von sonstigen keramischen Erzeugnissen",
    "sg:phone":"+41 18304878",
    "sg:postcode":"8305",
    "sg:province":"Z\u00fcrich",
    "wof:name":"Lisberg Gmbh",
    "wof:placetype":"venue"
},
  "geometry": {"coordinates":[8.6180238724,47.4266891479],"type":"Point"}
}