{
  "type": "Feature",
  "properties": {
    "iso:country":"CH",
    "sg:address":"Stockerstrasse 17",
    "sg:city":"Z\u00fcrich",
    "sg:classifiers":[
        {
            "category":"Travel",
            "subcategory":"Hotels & Motels",
            "type":"Entertainment"
        }
    ],
    "sg:phone":"+41 31 301 03 05",
    "sg:postcode":"8002",
    "sg:province":"Z\u00fcrich",
    "sg:tags":[
        "hotels",
        "mit",
        "restaurant"
    ],
    "wof:name":"Arabelle Hotel Schauss Raymond",
    "wof:placetype":"venue"
},
  "geometry": {"coordinates":[7.4326639175,46.9537086487],"type":"Point"}
}