{
  "type": "Feature",
  "properties": {
    "addr:full":"Dorfstrasse 64 Adelboden Bern 3715",
    "addr:housenumber":"64",
    "addr:postcode":"3715",
    "addr:street":"Dorfstrasse",
    "iso:country":"CH",
    "sg:address":"Dorfstrasse 64",
    "sg:city":"Adelboden",
    "sg:orig_category":"Detailhandel mit Blumen U Pflanzen Fachdetailhandel in Verkaufsr\u00e4umen",
    "sg:phone":"+41 33 673 27 27",
    "sg:postcode":"3715",
    "sg:province":"Bern",
    "wof:name":"Floribunda, Gubler Andrea",
    "wof:placetype":"venue"
},
  "geometry": {"coordinates":[7.556075,46.490562],"type":"Point"}
}