{
  "type": "Feature",
  "properties": {
    "iso:country":"CH",
    "sg:address":"Br\u00fcnigstrasse 6072 Sachseln. Postfach 28",
    "sg:city":"Sachseln",
    "sg:orig_category":"Revision Unternehmensberatung",
    "sg:phone":"+41 41 660 83 42",
    "sg:postcode":"6072",
    "sg:province":"Obwalden",
    "wof:name":"B & B Partner Gmbh",
    "wof:placetype":"venue"
},
  "geometry": {"coordinates":[8.2377910614,46.8683547974],"type":"Point"}
}