{
  "type": "Feature",
  "properties": {
    "iso:country":"CH",
    "sg:address":"H\u00fchnerhubel 81",
    "sg:city":"Belp",
    "sg:orig_category":"Architektur U Ingenieurb\u00fcros Herstellung von Metallerzeugnissen ohne Maschinenbau",
    "sg:phone":"+41 31 818 85 85",
    "sg:postcode":"3123",
    "sg:province":"Bern",
    "wof:name":"Jenni Georg Ag",
    "wof:placetype":"venue"
},
  "geometry": {"coordinates":[7.493936,46.905094],"type":"Point"}
}