{
  "type": "Feature",
  "properties": {
    "iso:country":"CH",
    "sg:address":"Hanflandstrasse 83 8125 Zollikerberg. Postfach",
    "sg:city":"Zollikerberg",
    "sg:orig_category":"Non-Classified Establishments",
    "sg:postcode":"8125",
    "sg:province":"Z\u00fcrich",
    "wof:name":"W & B Print Holding Ag",
    "wof:placetype":"venue"
},
  "geometry": {"coordinates":[8.3042135239,46.9895820618],"type":"Point"}
}