{
  "type": "Feature",
  "properties": {
    "iso:country":"CH",
    "sg:address":"Gottaz Avenue De La 32 1110 Morges. Postfach",
    "sg:city":"Morges",
    "sg:orig_category":"Erwachsenenbildung U Unterricht",
    "sg:phone":"+41 14010301",
    "sg:postcode":"1110",
    "sg:province":"Vaud",
    "wof:name":"Q-source Dr. Baumann Bruno C.",
    "wof:placetype":"venue"
},
  "geometry": {"coordinates":[8.4659919739,47.362953186],"type":"Point"}
}