{
  "type": "Feature",
  "properties": {
    "iso:country":"CH",
    "sg:address":"7553",
    "sg:city":"Tarasp",
    "sg:orig_category":"G\u00fcterbef\u00f6rderung im Strassenverkehr",
    "sg:phone":"+41 81 864 15 91",
    "sg:postcode":"7553",
    "sg:province":"Graubunden",
    "wof:name":"Andrea Grass Transporte",
    "wof:placetype":"venue"
},
  "geometry": {"coordinates":[10.2696971893,46.782043457],"type":"Point"}
}