{
  "type": "Feature",
  "properties": {
    "iso:country":"CH",
    "sg:address":"Marktgasse 50",
    "sg:city":"Langenthal",
    "sg:orig_category":"Detailhandel mit Metallwaren, Anstrichmitteln, Glaswaren, Bau U Heimwerkerbedarf",
    "sg:phone":"+41 62 922 20 25",
    "sg:postcode":"4900",
    "sg:province":"Bern",
    "wof:name":"W\u00e4rchst\u00fcbli Gmbh",
    "wof:placetype":"venue"
},
  "geometry": {"coordinates":[7.7880029678,47.2104949951],"type":"Point"}
}