{
  "type": "Feature",
  "properties": {
    "iso:country":"CH",
    "sg:address":"B\u00fcriswilen 606",
    "sg:city":"Oberegg",
    "sg:orig_category":"Unternehmensberatung",
    "sg:postcode":"9413",
    "sg:province":"Appenzell Innerhoden",
    "wof:name":"Kreutzinger Johann",
    "wof:placetype":"venue"
},
  "geometry": {"coordinates":[9.5503931046,47.4226455688],"type":"Point"}
}