{
  "type": "Feature",
  "properties": {
    "iso:country":"CH",
    "sg:address":"Stutzenb\u00fchlstrasse 11 9242 Oberuzwil. Postfach",
    "sg:city":"Oberuzwil",
    "sg:orig_category":"Softwareentwicklung U beratung",
    "sg:postcode":"9242",
    "sg:province":"St. Gallen",
    "wof:name":"Ibb Informatik Gmbh",
    "wof:placetype":"venue"
},
  "geometry": {"coordinates":[8.6900548935,47.3005561829],"type":"Point"}
}