{
  "type": "Feature",
  "properties": {
    "iso:country":"CH",
    "sg:address":"Holderenstrasse 35",
    "sg:city":"Rehetobel",
    "sg:classifiers":[
        {
            "category":"Industrial Area",
            "type":"Public Place"
        }
    ],
    "sg:phone":"+41 71 877 12 89",
    "sg:postcode":"9038",
    "sg:province":"Appenzell Ausserrhoden",
    "sg:tags":[
        "belt",
        "purpose",
        "strap"
    ],
    "wof:name":"Gebr\u00fcder Solenthaler Ag",
    "wof:placetype":"venue"
},
  "geometry": {"coordinates":[9.4799,47.425819],"type":"Point"}
}