{
  "type": "Feature",
  "properties": {
    "iso:country":"CH",
    "sg:address":"Rue Marterey 5",
    "sg:city":"Lausanne",
    "sg:orig_category":"Bauschreinerei Herstellung von M\u00f6beln verschiedener Art",
    "sg:phone":"+41 27 458 38 58",
    "sg:postcode":"1005",
    "sg:province":"Vaud",
    "wof:name":"Jean Genoud Eb\u00e9nisterie",
    "wof:placetype":"venue"
},
  "geometry": {"coordinates":[7.463645,46.258438],"type":"Point"}
}