{
  "type": "Feature",
  "properties": {
    "addr:full":"Bahnhofstrasse 25 Felsenau Aargau 5316",
    "addr:housenumber":"25",
    "addr:postcode":"5316",
    "addr:street":"Bahnhofstrasse",
    "iso:country":"CH",
    "sg:address":"Bahnhofstrasse 25",
    "sg:city":"Felsenau",
    "sg:classifiers":[
        {
            "category":"Structure",
            "subcategory":"Office Building",
            "type":"Public Place"
        }
    ],
    "sg:phone":"+41 56 246 16 40",
    "sg:postcode":"5316",
    "sg:province":"Aargau",
    "sg:tags":[
        "curved",
        "door",
        "sliding"
    ],
    "wof:name":"K. Winkler Ag",
    "wof:placetype":"venue"
},
  "geometry": {"coordinates":[8.220649,47.60387],"type":"Point"}
}