{
  "type": "Feature",
  "properties": {
    "iso:country":"CH",
    "sg:address":"Talstrasse 77",
    "sg:city":"Altendorf",
    "sg:orig_category":"Grosshandel mit Datenverarbeitungsger\u00e4ten Grosshandel mit Software",
    "sg:phone":"+41 55 462 37 74",
    "sg:postcode":"8852",
    "sg:province":"Schwyz",
    "wof:name":"Itpriority Ag Ben Rageth",
    "wof:placetype":"venue"
},
  "geometry": {"coordinates":[8.8014860153,47.1932487488],"type":"Point"}
}