{
  "type": "Feature",
  "properties": {
    "iso:country":"CH",
    "sg:address":"Prom.des Champs-fr\u00e9chets 17",
    "sg:city":"Meyrin",
    "sg:orig_category":"Gymnastik U Fitnesszentren Werbung",
    "sg:phone":"+41 41 870 52 25",
    "sg:postcode":"1217",
    "sg:province":"Gen\u00e8ve",
    "wof:name":"Martin Furrer, Werbe- & Reklameatelier",
    "wof:placetype":"venue"
},
  "geometry": {"coordinates":[8.6608448029,46.8737754822],"type":"Point"}
}