{
  "type": "Feature",
  "properties": {
    "iso:country":"CH",
    "sg:address":"Bellevuestrasse 3",
    "sg:city":"Adelboden",
    "sg:orig_category":"Gartenbau",
    "sg:phone":"+41 33 673 22 00",
    "sg:postcode":"3715",
    "sg:province":"Bern",
    "wof:name":"Manfred Burri Gartenunterhalt",
    "wof:placetype":"venue"
},
  "geometry": {"coordinates":[7.5564441681,46.4908714294],"type":"Point"}
}