{
  "type": "Feature",
  "properties": {
    "iso:country":"CH",
    "sg:address":"Landstrasse 32 6276 Hohenrain. Postfach",
    "sg:city":"Hohenrain",
    "sg:orig_category":"Erschliessung von Grundst\u00fccken",
    "sg:postcode":"6276",
    "sg:province":"Luzern",
    "wof:name":"Genossenschaft Habilon",
    "wof:placetype":"venue"
},
  "geometry": {"coordinates":[9.4015712738,47.4305076599],"type":"Point"}
}