{
  "type": "Feature",
  "properties": {
    "iso:country":"CH",
    "sg:address":"B\u00e4renplatz 6",
    "sg:city":"Fahrwangen",
    "sg:orig_category":"Wirtschaftspr\u00fcfung, Steuerberatung U Treuhand",
    "sg:postcode":"5615",
    "sg:province":"Aargau",
    "wof:name":"Levi Treuhand Und Finanzen, Weibel Beat, Eidg. Dipl. Buchhalter",
    "wof:placetype":"venue"
},
  "geometry": {"coordinates":[8.2419710159,47.2947845459],"type":"Point"}
}