{
  "type": "Feature",
  "properties": {
    "iso:country":"CH",
    "sg:address":"Seeblick 2",
    "sg:city":"Meierskappel",
    "sg:orig_category":"Massagestudios",
    "sg:phone":"+41 41 790 20 38",
    "sg:postcode":"6344",
    "sg:province":"Luzern",
    "wof:name":"Paul Suter Massagen",
    "wof:placetype":"venue"
},
  "geometry": {"coordinates":[8.4437427521,47.1261177063],"type":"Point"}
}