{
  "type": "Feature",
  "properties": {
    "iso:country":"CH",
    "sg:address":"6353",
    "sg:city":"Weggis",
    "sg:classifiers":[
        {
            "category":"Travel",
            "subcategory":"Hotels & Motels",
            "type":"Entertainment"
        }
    ],
    "sg:postcode":"6353",
    "sg:province":"Luzern",
    "sg:tags":[
        "hotels",
        "mit",
        "restaurant"
    ],
    "wof:name":"Hostellerie Rigi Ag",
    "wof:placetype":"venue"
},
  "geometry": {"coordinates":[8.4343938828,47.0322952271],"type":"Point"}
}