{
  "type": "Feature",
  "properties": {
    "iso:country":"CH",
    "sg:address":"Weststrasse 87",
    "sg:city":"Unter\u00e4geri",
    "sg:orig_category":"Gesundheitswesen",
    "sg:postcode":"6314",
    "sg:province":"Zug",
    "wof:name":"Sinomed Ag",
    "wof:placetype":"venue"
},
  "geometry": {"coordinates":[8.8199644089,47.2292785645],"type":"Point"}
}