{
  "type": "Feature",
  "properties": {
    "iso:country":"CH",
    "sg:address":"Hauptstrasse 76",
    "sg:city":"Steinach",
    "sg:orig_category":"Herstellung von sonstigen Maschinen f\u00fcr bestimmte Verwendung",
    "sg:phone":"+41 71 446 07 07",
    "sg:postcode":"9323",
    "sg:province":"St. Gallen",
    "wof:name":"Dreamworld Freizeit Und Unterhaltungspark Ag",
    "wof:placetype":"venue"
},
  "geometry": {"coordinates":[9.447842598,47.5009078979],"type":"Point"}
}