{
  "type": "Feature",
  "properties": {
    "iso:country":"CH",
    "sg:address":"Obergmeind",
    "sg:city":"Tschappina",
    "sg:orig_category":"Sportschulen Ski-& Snowboardschulen",
    "sg:phone":"+41 81 651 13 22",
    "sg:postcode":"7428",
    "sg:province":"Graubunden",
    "wof:name":"Robert Amb\u00fchl Schweiz.skischule Tschappina",
    "wof:placetype":"venue"
},
  "geometry": {"coordinates":[9.3602237701,46.6919403076],"type":"Point"}
}