{
  "type": "Feature",
  "properties": {
    "iso:country":"CH",
    "sg:address":"Gl\u00e2ne Route De 107",
    "sg:city":"Villars-sur-gl\u00e2ne",
    "sg:orig_category":"Grosshandel mit Tabakwaren",
    "sg:phone":"+41 26 402 92 81",
    "sg:postcode":"1752",
    "sg:province":"Fribourg",
    "wof:name":"Intertab Sa",
    "wof:placetype":"venue"
},
  "geometry": {"coordinates":[7.130428791,46.7955818176],"type":"Point"}
}