{
  "type": "Feature",
  "properties": {
    "iso:country":"CH",
    "sg:address":"Hauptstrasse 4",
    "sg:city":"Diegten",
    "sg:orig_category":"Mechanik Mechanische Werkst\u00e4tten",
    "sg:phone":"+41 61 973 03 23",
    "sg:postcode":"4457",
    "sg:province":"Basel-Landschaft",
    "wof:name":"Johannes Iberg Mech.werkst\u00e4tte & Maschinenbau",
    "wof:placetype":"venue"
},
  "geometry": {"coordinates":[7.8097648621,47.4040184021],"type":"Point"}
}