{
  "type": "Feature",
  "properties": {
    "iso:country":"CH",
    "sg:address":"Nebikerstrasse 42",
    "sg:city":"Sch\u00f6tz",
    "sg:orig_category":"Mahl U Sch\u00e4lm\u00fchlen",
    "sg:postcode":"6247",
    "sg:province":"Luzern",
    "wof:name":"Muri E. & S\u00f6hne Ag, Dorfm\u00fchle Sch\u00f6tz",
    "wof:placetype":"venue"
},
  "geometry": {"coordinates":[7.9878578186,47.1759986877],"type":"Point"}
}