{
  "type": "Feature",
  "properties": {
    "iso:country":"CH",
    "sg:address":"Sch\u00fcrmattweg 2",
    "sg:city":"Olten",
    "sg:classifiers":[
        {
            "category":"Wholesale",
            "subcategory":"Medical Equipment & Supplies",
            "type":"Manufacturing & Wholesale Goods"
        }
    ],
    "sg:phone":"+41 62 207 06 50",
    "sg:postcode":"4600",
    "sg:province":"Solothurn",
    "sg:tags":[
        "physicians",
        "hospital",
        "clothing",
        "surgical"
    ],
    "wof:name":"H\u00e4lg Textil & Co",
    "wof:placetype":"venue"
},
  "geometry": {"coordinates":[7.900381,47.349457],"type":"Point"}
}