{
  "type": "Feature",
  "properties": {
    "iso:country":"CH",
    "sg:address":"Via Dufour 2",
    "sg:city":"Lugano",
    "sg:orig_category":"Psychotherapie",
    "sg:postcode":"6900",
    "sg:province":"Ticino",
    "wof:name":"Partick Surdez Psychoth\u00e9rapie",
    "wof:placetype":"venue"
},
  "geometry": {"coordinates":[6.8259382248,47.1063690186],"type":"Point"}
}