{
  "type": "Feature",
  "properties": {
    "iso:country":"CH",
    "sg:address":"Rue Du Temple 3",
    "sg:city":"St-imier",
    "sg:orig_category":"Detailhandel mit Waren verschiedener Art, Hauptrichtung Nahrungsmittel Verwertung von Milch",
    "sg:postcode":"2610",
    "sg:province":"Bern",
    "wof:name":"Demont, Benjamin",
    "wof:placetype":"venue"
},
  "geometry": {"coordinates":[6.9965238571,47.1528091431],"type":"Point"}
}