{
  "type": "Feature",
  "properties": {
    "addr:full":"Gr\u00e4bligasse 1 Z\u00fcrich Z\u00fcrich 8001",
    "addr:housenumber":"1",
    "addr:postcode":"8001",
    "addr:street":"Graebligasse",
    "iso:country":"CH",
    "sg:address":"Gr\u00e4bligasse 1",
    "sg:city":"Z\u00fcrich",
    "sg:classifiers":[
        {
            "category":"Bars & Pubs",
            "type":"Food & Drink"
        }
    ],
    "sg:phone":"+41 12519595",
    "sg:postcode":"8001",
    "sg:province":"Z\u00fcrich",
    "wof:name":"Gr\u00e4bli-bar",
    "wof:placetype":"venue"
},
  "geometry": {"coordinates":[8.544169,47.375641],"type":"Point"}
}