{
  "type": "Feature",
  "properties": {
    "iso:country":"CH",
    "sg:address":"Hinterbirchstrasse 6",
    "sg:city":"B\u00fclach",
    "sg:orig_category":"Sportvereine Sch\u00fctzen",
    "sg:phone":"+41 19300653",
    "sg:postcode":"8180",
    "sg:province":"Z\u00fcrich",
    "wof:name":"Sch\u00fctzengesellschaft",
    "wof:placetype":"venue"
},
  "geometry": {"coordinates":[8.5311851501,47.5206756592],"type":"Point"}
}