{
  "type": "Feature",
  "properties": {
    "iso:country":"CH",
    "sg:address":"Seemattstrasse 64",
    "sg:city":"Cham",
    "sg:orig_category":"Sonstige mit Sport verbundene T\u00e4tigkeiten",
    "sg:postcode":"6330",
    "sg:province":"Zug",
    "wof:name":"Isa Interschool Of Aqua-fit Gmbh",
    "wof:placetype":"venue"
},
  "geometry": {"coordinates":[8.4524908066,47.1756629944],"type":"Point"}
}