{
  "type": "Feature",
  "properties": {
    "addr:full":"Leutschenbachstrasse 45 8008 Z\u00fcrich. Postfach Z\u00fcrich Z\u00fcrich 8008",
    "addr:housenumber":"45",
    "addr:postcode":"8008 zuerich. postfach;8008",
    "addr:street":"Leutschenbachstrasse",
    "iso:country":"CH",
    "sg:address":"Leutschenbachstrasse 45 8008 Z\u00fcrich. Postfach",
    "sg:city":"Z\u00fcrich",
    "sg:orig_category":"Architektur U Ingenieurb\u00fcros",
    "sg:postcode":"8008",
    "sg:province":"Z\u00fcrich",
    "wof:name":"Intep Ag",
    "wof:placetype":"venue"
},
  "geometry": {"coordinates":[8.553216,47.415108],"type":"Point"}
}