{
  "type": "Feature",
  "properties": {
    "iso:country":"CH",
    "sg:address":"Talackerstr. 43",
    "sg:city":"Glattbrugg",
    "sg:orig_category":"Sonstiger Grosshandel",
    "sg:postcode":"8152",
    "sg:province":"Z\u00fcrich",
    "wof:name":"Manotrade Dobek & Co",
    "wof:placetype":"venue"
},
  "geometry": {"coordinates":[8.5615329742,47.4267845154],"type":"Point"}
}