{
  "type": "Feature",
  "properties": {
    "addr:full":"Nauengasse 43a Rorbas Z\u00fcrich 8427",
    "addr:housenumber":"43a",
    "addr:postcode":"8427",
    "addr:street":"Nauengasse",
    "iso:country":"CH",
    "sg:address":"Nauengasse 43a",
    "sg:city":"Rorbas",
    "sg:orig_category":"Architektur U Ingenieurb\u00fcros",
    "sg:phone":"+41 21 944 39 78",
    "sg:postcode":"8427",
    "sg:province":"Z\u00fcrich",
    "wof:name":"Zed Design & Technologies, Zoller Jean-pierre Produits Et Services De Nouvelle Technologies; D\u00e9veloppement, Planification Et Commercialisation. Prototypes; Design Etc",
    "wof:placetype":"venue"
},
  "geometry": {"coordinates":[6.856867,46.453026],"type":"Point"}
}