{
  "type": "Feature",
  "properties": {
    "iso:country":"CH",
    "sg:address":"Seftigenstrasse 225 3084 Wabern. Postfach",
    "sg:city":"Wabern",
    "sg:orig_category":"Saunas, Solarien, Fitnesszentren U \u00e4hnliches",
    "sg:phone":"+41 31 961 73 70",
    "sg:postcode":"3084",
    "sg:province":"Bern",
    "wof:name":"Ergo-sunline Gmbh",
    "wof:placetype":"venue"
},
  "geometry": {"coordinates":[7.4498147964,46.9300918579],"type":"Point"}
}