{
  "type": "Feature",
  "properties": {
    "iso:country":"CH",
    "sg:address":"Chemin Mont-de-faux 6",
    "sg:city":"Crissier",
    "sg:classifiers":[
        {
            "category":"Military Area",
            "subcategory":"Army Base",
            "type":"Public Place"
        }
    ],
    "sg:phone":"+41 21 634 07 08",
    "sg:postcode":"1023",
    "sg:province":"Vaud",
    "sg:tags":[
        "electrostatic",
        "coating",
        "powder"
    ],
    "wof:name":"Thermolaquage De Crissier S\u00e0rl",
    "wof:placetype":"venue"
},
  "geometry": {"coordinates":[6.5678400993,46.5629272461],"type":"Point"}
}