{
  "type": "Feature",
  "properties": {
    "iso:country":"CH",
    "sg:address":"6772",
    "sg:city":"Rodi-fiesso",
    "sg:orig_category":"Detailhandel mit Waren verschiedener Art, Hauptrichtung Nahrungsmittel",
    "sg:phone":"+41 91 791 42 33",
    "sg:postcode":"6772",
    "sg:province":"Ticino",
    "wof:name":"Flavio Materni Negozio Alimentari",
    "wof:placetype":"venue"
},
  "geometry": {"coordinates":[8.7273330688,46.1435546875],"type":"Point"}
}