{
  "type": "Feature",
  "properties": {
    "iso:country":"CH",
    "sg:city":"Unterems",
    "sg:classifiers":[
        {
            "category":"Banks & Credit Unions",
            "subcategory":"Bank",
            "type":"Services"
        }
    ],
    "sg:phone":"+41 27 932 35 93",
    "sg:postcode":"3948",
    "sg:province":"Valais",
    "wof:name":"Walliser Kantonalbank",
    "wof:placetype":"venue"
},
  "geometry": {"coordinates":[7.695819,46.29052],"type":"Point"}
}