{
  "type": "Feature",
  "properties": {
    "iso:country":"CH",
    "sg:address":"Hintere Bergstrasse 46",
    "sg:city":"Oberrieden",
    "sg:orig_category":"Grosshandel mit Getr\u00e4nken",
    "sg:phone":"+41 55 444 17 34",
    "sg:postcode":"8942",
    "sg:province":"Z\u00fcrich",
    "wof:name":"Doctor's Winery Gmbh",
    "wof:placetype":"venue"
},
  "geometry": {"coordinates":[8.5689735413,47.2766227722],"type":"Point"}
}