{
  "type": "Feature",
  "properties": {
    "iso:country":"CH",
    "sg:address":"P\u00e9rolles Boulevard De 37",
    "sg:city":"Fribourg",
    "sg:orig_category":"Pensionskassen",
    "sg:phone":"+41 26 424 44 33",
    "sg:postcode":"1700",
    "sg:province":"Fribourg",
    "wof:name":"Fonds De Pr\u00e9voyance En Faveur Du Personnel De Eca Experts Comptables Associ\u00e9s Sa Et De Sorefisa Fribourg, Soci\u00e9t\u00e9 De Revision Et De Fiscalit\u00e9 Sa",
    "wof:placetype":"venue"
},
  "geometry": {"coordinates":[7.1536831856,46.8037452698],"type":"Point"}
}