{
  "type": "Feature",
  "properties": {
    "iso:country":"CH",
    "sg:address":"Grundstrasse 14",
    "sg:city":"Rotkreuz",
    "sg:orig_category":"Software Commercialization",
    "sg:phone":"+41 41 798 33 55",
    "sg:postcode":"6343",
    "sg:province":"Zug",
    "wof:name":"Hicomp Software Ag",
    "wof:placetype":"venue"
},
  "geometry": {"coordinates":[8.4304237366,47.145866394],"type":"Point"}
}