{
  "type": "Feature",
  "properties": {
    "iso:country":"CH",
    "sg:address":"Randenstrasse 42",
    "sg:city":"Schleitheim",
    "sg:orig_category":"Erbringung von Dienstleistungen f\u00fcr Unternehmen",
    "sg:phone":"+41 79 227 18 90",
    "sg:postcode":"8226",
    "sg:province":"Schaffhausen",
    "wof:name":"Tavo-vorrichtungsbau Bernhard Hans Peter",
    "wof:placetype":"venue"
},
  "geometry": {"coordinates":[8.4921264648,47.7520370483],"type":"Point"}
}