{
  "type": "Feature",
  "properties": {
    "iso:country":"CH",
    "sg:address":"Hauptstr. 36",
    "sg:city":"Brunegg",
    "sg:orig_category":"Vermietung U Verpachtung von eigenen Immobilien",
    "sg:phone":"+41 62 896 10 03",
    "sg:postcode":"5505",
    "sg:province":"Aargau",
    "wof:name":"Hauri Immobilien Brunegg Ag",
    "wof:placetype":"venue"
},
  "geometry": {"coordinates":[8.217663765,47.4193496704],"type":"Point"}
}