{
  "type": "Feature",
  "properties": {
    "iso:country":"CH",
    "sg:address":"Dattenmattstrasse 16a",
    "sg:city":"Kriens",
    "sg:orig_category":"Maschinen and Apparate divers Grosshandel",
    "sg:phone":"+41 79 240 50 04",
    "sg:postcode":"6010",
    "sg:province":"Luzern",
    "wof:name":"Claude Boillat Cbs Service",
    "wof:placetype":"venue"
},
  "geometry": {"coordinates":[6.8283500671,47.1076126099],"type":"Point"}
}