{
  "type": "Feature",
  "properties": {
    "iso:country":"CH",
    "sg:address":"Gotthardstrasse 20",
    "sg:city":"Thalwil",
    "sg:orig_category":"Unclassifiable Establishments",
    "sg:postcode":"8800",
    "sg:province":"Z\u00fcrich",
    "wof:name":"Mode-boutique Sunshine Gabriela M\u00fcller",
    "wof:placetype":"venue"
},
  "geometry": {"coordinates":[8.2933578491,47.3772850037],"type":"Point"}
}