{
  "type": "Feature",
  "properties": {
    "iso:country":"CH",
    "sg:address":"5237",
    "sg:city":"M\u00f6nthal",
    "sg:classifiers":[
        {
            "category":"Education",
            "subcategory":"Library",
            "type":"Public Place"
        }
    ],
    "sg:postcode":"5237",
    "sg:province":"Aargau",
    "sg:tags":[
        "u",
        "bibliotheken",
        "archive"
    ],
    "wof:name":"Gemeindebibliothek",
    "wof:placetype":"venue"
},
  "geometry": {"coordinates":[8.13544,47.51453],"type":"Point"}
}