{
  "type": "Feature",
  "properties": {
    "addr:full":"C\u00f4te Des Vaux 1312 Ecl\u00e9pens Case Postale 13 Ecl\u00e9pens Vaud 1312",
    "addr:housenumber":"1312;13",
    "addr:postcode":"1312",
    "addr:street":"Co\u0302Te Des Vaux;Case Postale",
    "iso:country":"CH",
    "sg:address":"C\u00f4te Des Vaux 1312 Ecl\u00e9pens Case Postale 13",
    "sg:city":"Ecl\u00e9pens",
    "sg:orig_category":"R\u00fcckgewinnung U Vorbereitung f\u00fcr die Wiederverwertung Recycling R\u00fcckgewinnung U Vorbereitung f\u00fcr die",
    "sg:phone":"+41 21 866 03 00",
    "sg:postcode":"1312",
    "sg:province":"Vaud",
    "wof:name":"Cridec, Centre De Ramassage Et D'identification Des D\u00e9chets Sp\u00e9ciaux Sa",
    "wof:placetype":"venue"
},
  "geometry": {"coordinates":[6.52898,46.651104],"type":"Point"}
}