{
  "type": "Feature",
  "properties": {
    "iso:country":"CH",
    "sg:address":"Untergasse 48 2502 Biel/bienne. Postfach",
    "sg:city":"Biel/bienne",
    "sg:orig_category":"Grosshandel mit Kaffee, Tee, Kakao U Gew\u00fcrzen",
    "sg:postcode":"2502",
    "sg:province":"Bern",
    "wof:name":"Tea House M\u00fchle R. Tee- U. Naturprodukte; Handel",
    "wof:placetype":"venue"
},
  "geometry": {"coordinates":[7.2475891113,47.1422996521],"type":"Point"}
}