{
  "type": "Feature",
  "properties": {
    "iso:country":"CH",
    "sg:address":"Route De La Maladi\u00e8re 4",
    "sg:city":"Chavannes-renens",
    "sg:orig_category":"Herstellung von Armaturen Herstellung von Metallerzeugnissen ohne Maschinenbau",
    "sg:phone":"+41 21 691 40 11",
    "sg:postcode":"1022",
    "sg:province":"Vaud",
    "wof:name":"Vincent Graf Hydrotechnique",
    "wof:placetype":"venue"
},
  "geometry": {"coordinates":[6.5686421394,46.5280838013],"type":"Point"}
}