{
  "type": "Feature",
  "properties": {
    "iso:country":"CH",
    "sg:address":"Untere Allmendstrasse 11",
    "sg:city":"Steinhausen",
    "sg:classifiers":[
        {
            "category":"Health Services",
            "subcategory":"Medical Lab",
            "type":"Services"
        }
    ],
    "sg:phone":"+41 41 740 09 09",
    "sg:postcode":"6312",
    "sg:province":"Zug",
    "sg:tags":[
        "appliance",
        "system"
    ],
    "wof:name":"Conis Ag",
    "wof:placetype":"venue"
},
  "geometry": {"coordinates":[8.4956245422,47.1924285889],"type":"Point"}
}