{
  "type": "Feature",
  "properties": {
    "iso:country":"CH",
    "sg:address":"Gartenweg 7",
    "sg:city":"Wohlenschwil",
    "sg:orig_category":"Schreib U \u00dcbersetzungsb\u00fcros",
    "sg:phone":"+41 56 491 30 32",
    "sg:postcode":"5512",
    "sg:province":"Aargau",
    "wof:name":"B\u00fcwo-text B\u00fcrgler-wohlgemuth Ingrid",
    "wof:placetype":"venue"
},
  "geometry": {"coordinates":[8.2597618103,47.4112739563],"type":"Point"}
}