{
  "type": "Feature",
  "properties": {
    "iso:country":"CH",
    "sg:address":"Schmidshof",
    "sg:city":"Bussnang",
    "sg:classifiers":[
        {
            "category":"Travel",
            "subcategory":"Hotels & Motels",
            "type":"Entertainment"
        }
    ],
    "sg:postcode":"9565",
    "sg:province":"Thurgau",
    "sg:tags":[
        "hotels",
        "mit",
        "restaurant"
    ],
    "wof:name":"Drusatscha Park Ag",
    "wof:placetype":"venue"
},
  "geometry": {"coordinates":[9.8222503662,46.7972831726],"type":"Point"}
}