{
  "type": "Feature",
  "properties": {
    "iso:country":"CH",
    "sg:address":"Lindenweg 1a",
    "sg:city":"Goldach",
    "sg:orig_category":"Vereine Musik/Blasmusik",
    "sg:phone":"+41 71 841 24 18",
    "sg:postcode":"9403",
    "sg:province":"St. Gallen",
    "wof:name":"Musikverein Rorschacherberg",
    "wof:placetype":"venue"
},
  "geometry": {"coordinates":[9.4728593826,47.4785423279],"type":"Point"}
}