{
  "type": "Feature",
  "properties": {
    "iso:country":"CH",
    "sg:address":"Bahnhofwiese 20",
    "sg:city":"St\u00e4fa",
    "sg:orig_category":"Sanit\u00e4r, Heizungs U L\u00fcftungsinstallation",
    "sg:postcode":"8712",
    "sg:province":"Z\u00fcrich",
    "wof:name":"Sanit\u00e4r Vogt",
    "wof:placetype":"venue"
},
  "geometry": {"coordinates":[9.0042800903,47.4870986938],"type":"Point"}
}