{
  "type": "Feature",
  "properties": {
    "iso:country":"CH",
    "sg:address":"Hohlstrasse 211 8004 Z\u00fcrich. Postfach",
    "sg:city":"Z\u00fcrich",
    "sg:orig_category":"Erschliessung von Grundst\u00fccken",
    "sg:postcode":"8001",
    "sg:province":"Z\u00fcrich",
    "wof:name":"Baugesellschaft Sihlfeld",
    "wof:placetype":"venue"
},
  "geometry": {"coordinates":[8.516919136,47.3813934326],"type":"Point"}
}