{
  "type": "Feature",
  "properties": {
    "iso:country":"CH",
    "sg:address":"Rue Du Rh\u00f4ne 2",
    "sg:city":"Fully",
    "sg:orig_category":"Unclassifiable Establishments",
    "sg:postcode":"1926",
    "sg:province":"Valais",
    "wof:name":"Fleutry Claudy",
    "wof:placetype":"venue"
},
  "geometry": {"coordinates":[7.1008110046,46.1294136047],"type":"Point"}
}