{
  "type": "Feature",
  "properties": {
    "addr:full":"Baarerstrasse 60 Zug Zug 6300",
    "addr:housenumber":"60",
    "addr:postcode":"6300",
    "addr:street":"Baarerstrasse;Zug",
    "iso:country":"CH",
    "sg:address":"Baarerstrasse 60",
    "sg:city":"Zug",
    "sg:orig_category":"Architektur U Ingenieurb\u00fcros",
    "sg:postcode":"6300",
    "sg:province":"Zug",
    "wof:name":"Concept-engineering Henggeler Fred H.",
    "wof:placetype":"venue"
},
  "geometry": {"coordinates":[8.517654,47.175804],"type":"Point"}
}