{
  "type": "Feature",
  "properties": {
    "iso:country":"CH",
    "sg:address":"Lindenstrasse 4a",
    "sg:city":"Kollbrunn",
    "sg:orig_category":"Sonstiger Grosshandel",
    "sg:phone":"+41 52 383 30 34",
    "sg:postcode":"8483",
    "sg:province":"Z\u00fcrich",
    "wof:name":"Biowell Service Gmbh",
    "wof:placetype":"venue"
},
  "geometry": {"coordinates":[8.7763204575,47.4567642212],"type":"Point"}
}