{
  "type": "Feature",
  "properties": {
    "iso:country":"CH",
    "sg:address":"Chemin Du Couchant 31",
    "sg:city":"Lausanne",
    "sg:orig_category":"Bauschreinerei Herstellung von Konstruktionsteilen, Fertigbauteilen U Ausbauelementen aus Holz",
    "sg:phone":"+41 21 624 05 37",
    "sg:postcode":"1007",
    "sg:province":"Vaud",
    "wof:name":"Menuiserie Suarato S\u00e0rl",
    "wof:placetype":"venue"
},
  "geometry": {"coordinates":[6.606985,46.520657],"type":"Point"}
}