{
  "type": "Feature",
  "properties": {
    "iso:country":"CH",
    "sg:address":"Kleinfeldstrasse 19",
    "sg:city":"Mels",
    "sg:orig_category":"Herstellung von \u00d6fen U Brennern",
    "sg:postcode":"8887",
    "sg:province":"St. Gallen",
    "wof:name":"Kohler Bruno",
    "wof:placetype":"venue"
},
  "geometry": {"coordinates":[9.4228992462,47.0497665405],"type":"Point"}
}