{
  "type": "Feature",
  "properties": {
    "iso:country":"CH",
    "sg:address":"Les Coteaux",
    "sg:city":"St-george",
    "sg:orig_category":"Unternehmensberatung",
    "sg:postcode":"1261",
    "sg:province":"Vaud",
    "wof:name":"Buschbeck D\u00e9veloppement",
    "wof:placetype":"venue"
},
  "geometry": {"coordinates":[6.2677898407,46.5146026611],"type":"Point"}
}