{
  "type": "Feature",
  "properties": {
    "iso:country":"CH",
    "sg:address":"Husmattstrasse 26",
    "sg:city":"Steinerberg",
    "sg:orig_category":"Gartenbau Hoch U Tiefbau",
    "sg:phone":"+41 79 415 50 91",
    "sg:postcode":"6416",
    "sg:province":"Schwyz",
    "wof:name":"Franz Kn\u00fcsel Gmbh Bauunternehmung & Gartenbau",
    "wof:placetype":"venue"
},
  "geometry": {"coordinates":[8.5878705978,47.0564537048],"type":"Point"}
}