{
  "type": "Feature",
  "properties": {
    "addr:full":"Rue De Bourg 24 Lausanne Vaud 1002",
    "addr:housenumber":"24",
    "addr:postcode":"1002",
    "addr:street":"Rue De Bourg",
    "iso:country":"CH",
    "sg:address":"Rue De Bourg 24",
    "sg:city":"Lausanne",
    "sg:classifiers":[
        {
            "category":"Shopping",
            "subcategory":"Clothing, Apparel, & Fashions",
            "type":"Retail Goods"
        }
    ],
    "sg:phone":"+41 21 312 41 16",
    "sg:postcode":"1002",
    "sg:province":"Vaud",
    "sg:tags":[
        "textile",
        "clothing",
        "clothes"
    ],
    "wof:name":"Anabelle Elegance Sa",
    "wof:placetype":"venue"
},
  "geometry": {"coordinates":[6.635938,46.519943],"type":"Point"}
}