{
  "type": "Feature",
  "properties": {
    "iso:country":"CH",
    "sg:address":"Dorf 19",
    "sg:city":"R\u00fctschelen",
    "sg:orig_category":"Architektur U Ingenieurb\u00fcros",
    "sg:phone":"+41 62 923 91 05",
    "sg:postcode":"4933",
    "sg:province":"Bern",
    "wof:name":"Architekturb\u00fcro Kurth",
    "wof:placetype":"venue"
},
  "geometry": {"coordinates":[7.774419,47.174149],"type":"Point"}
}