{
  "type": "Feature",
  "properties": {
    "iso:country":"CH",
    "sg:address":"Via Mondasc 64a",
    "sg:city":"Sementina",
    "sg:orig_category":"Sportvereine Ballsport Tischtennis",
    "sg:phone":"+41 91 857 16 55",
    "sg:postcode":"6514",
    "sg:province":"Ticino",
    "wof:name":"Abtt Bellinzona",
    "wof:placetype":"venue"
},
  "geometry": {"coordinates":[8.9977874756,46.180103302],"type":"Point"}
}