{
  "type": "Feature",
  "properties": {
    "iso:country":"CH",
    "sg:address":"Eisenbahnstrasse 41",
    "sg:city":"Rorschach",
    "sg:orig_category":"Vermietung U Verpachtung von eigenen Immobilien",
    "sg:postcode":"9400",
    "sg:province":"St. Gallen",
    "wof:name":"Andar Sa",
    "wof:placetype":"venue"
},
  "geometry": {"coordinates":[9.4925899506,47.4757537842],"type":"Point"}
}