{
  "type": "Feature",
  "properties": {
    "iso:country":"CH",
    "sg:address":"Stampfenbachstrasse 109 8006 Z\u00fcrich. Postfach",
    "sg:city":"Z\u00fcrich",
    "sg:orig_category":"Unclassifiable Establishments",
    "sg:phone":"+41 32 666 23 33",
    "sg:postcode":"8001",
    "sg:province":"Z\u00fcrich",
    "wof:name":"Buser Holding Ag",
    "wof:placetype":"venue"
},
  "geometry": {"coordinates":[7.5573868752,47.1511878967],"type":"Point"}
}