{
  "type": "Feature",
  "properties": {
    "iso:country":"CH",
    "sg:address":"Oberg\u00e4ssli 4",
    "sg:city":"Mels",
    "sg:orig_category":"Unclassifiable Establishments",
    "sg:postcode":"8887",
    "sg:province":"St. Gallen",
    "wof:name":"Klaro Online",
    "wof:placetype":"venue"
},
  "geometry": {"coordinates":[9.4197769165,47.0460166931],"type":"Point"}
}