{
  "type": "Feature",
  "properties": {
    "iso:country":"CH",
    "sg:address":"2016",
    "sg:city":"Cortaillod",
    "sg:orig_category":"Sportvereine Sch\u00fctzen",
    "sg:phone":"+41 32 842 29 05",
    "sg:postcode":"2016",
    "sg:province":"Neuch\u00e2tel",
    "wof:name":"St\u00e9 De Tir Les Mousquetaires",
    "wof:placetype":"venue"
},
  "geometry": {"coordinates":[6.8464298248,46.943031311],"type":"Point"}
}