{
  "type": "Feature",
  "properties": {
    "iso:country":"CH",
    "sg:address":"Kasinostrasse 19",
    "sg:city":"Aarau",
    "sg:orig_category":"Herstellung von Teppichen",
    "sg:phone":"+41 62 822 14 22",
    "sg:postcode":"5000",
    "sg:province":"Aargau",
    "wof:name":"Hassler Hans Ag",
    "wof:placetype":"venue"
},
  "geometry": {"coordinates":[8.0468330383,47.3927230835],"type":"Point"}
}