{
  "type": "Feature",
  "properties": {
    "iso:country":"CH",
    "sg:address":"Via Nassa 52",
    "sg:city":"Lugano",
    "sg:orig_category":"Detailhandel mit Uhren U Schmuck Fachdetailhandel in Verkaufsr\u00e4umen",
    "sg:phone":"+41 91 911 66 00",
    "sg:postcode":"6900",
    "sg:province":"Ticino",
    "wof:name":"Gioielleria Bcr Sa",
    "wof:placetype":"venue"
},
  "geometry": {"coordinates":[8.9493875504,46.0014915466],"type":"Point"}
}