{
  "type": "Feature",
  "properties": {
    "iso:country":"CH",
    "sg:address":"Landstrasse 43a",
    "sg:city":"Andelfingen",
    "sg:orig_category":"Non-Classified Establishments",
    "sg:postcode":"8450",
    "sg:province":"Z\u00fcrich",
    "wof:name":"Stuve Sa",
    "wof:placetype":"venue"
},
  "geometry": {"coordinates":[9.125254631,46.236076355],"type":"Point"}
}