{
  "type": "Feature",
  "properties": {
    "iso:country":"CH",
    "sg:address":"1695",
    "sg:city":"Rueyres-st-laurent",
    "sg:orig_category":"Bauspenglerei Dachdeckerei",
    "sg:phone":"+41 26 411 17 01",
    "sg:postcode":"1695",
    "sg:province":"Fribourg",
    "wof:name":"Joye Fr\u00e8res Sa Ferblanterie & Couverture",
    "wof:placetype":"venue"
},
  "geometry": {"coordinates":[7.03308,46.715511],"type":"Point"}
}