{
  "type": "Feature",
  "properties": {
    "iso:country":"CH",
    "sg:address":"Rue De Chantepoulet 1-3",
    "sg:city":"Gen\u00e8ve",
    "sg:orig_category":"Luftfahrt Sonstige Hilfs U Nebent\u00e4tigkeiten f\u00fcr die Luftfahrt",
    "sg:phone":"+41 22 732 05 60",
    "sg:postcode":"1201",
    "sg:province":"Gen\u00e8ve",
    "wof:name":"Atash Sa",
    "wof:placetype":"venue"
},
  "geometry": {"coordinates":[6.1454720497,46.2079353333],"type":"Point"}
}