{
  "type": "Feature",
  "properties": {
    "iso:country":"CH",
    "sg:address":"B\u00fcchnerstrasse 19",
    "sg:city":"Z\u00fcrich",
    "sg:orig_category":"Kosmetikinstitute",
    "sg:phone":"+41 13613066",
    "sg:postcode":"8006",
    "sg:province":"Z\u00fcrich",
    "wof:name":"Carla Br\u00fctsch Kosmetikinstitut",
    "wof:placetype":"venue"
},
  "geometry": {"coordinates":[8.5509052277,47.3835830688],"type":"Point"}
}