{
  "type": "Feature",
  "properties": {
    "iso:country":"CH",
    "sg:address":"Viale Cassone",
    "sg:city":"Pregassona",
    "sg:orig_category":"Vorschulen, Kinderg\u00e4rten",
    "sg:phone":"+41 81 844 19 37",
    "sg:postcode":"6963",
    "sg:province":"Ticino",
    "wof:name":"Scuola Materna S.antonio",
    "wof:placetype":"venue"
},
  "geometry": {"coordinates":[10.0633096695,46.3106498718],"type":"Point"}
}