{
  "type": "Feature",
  "properties": {
    "iso:country":"CH",
    "sg:address":"Passage Du Cardinal 2d",
    "sg:city":"Fribourg",
    "sg:orig_category":"Architektur U Ingenieurb\u00fcros",
    "sg:phone":"+41 26 470 26 56",
    "sg:postcode":"1700",
    "sg:province":"Fribourg",
    "wof:name":"Jacques Gantner Eco-consult Engineering",
    "wof:placetype":"venue"
},
  "geometry": {"coordinates":[7.147241,46.798702],"type":"Point"}
}