{
  "type": "Feature",
  "properties": {
    "iso:country":"CH",
    "sg:address":"Althardstrasse 224",
    "sg:city":"Regensdorf",
    "sg:orig_category":"Detailhandel mit elektrischen Haushalts-,Radio U Fernsehger\u00e4ten sowie Musikinstrumenten HERSTELLUNG ",
    "sg:phone":"+41 32 435 72 72",
    "sg:postcode":"8105",
    "sg:province":"Z\u00fcrich",
    "wof:name":"Cin\u00e9 Media Technologies Sa",
    "wof:placetype":"venue"
},
  "geometry": {"coordinates":[7.2434949875,47.1374168396],"type":"Point"}
}