{
  "type": "Feature",
  "properties": {
    "iso:country":"CH",
    "sg:address":"Kreuzgasse 6",
    "sg:city":"Solothurn",
    "sg:orig_category":"Detailhandel mit Damenbekleidung",
    "sg:phone":"+41 32 622 76 73",
    "sg:postcode":"4500",
    "sg:province":"Solothurn",
    "wof:name":"Renate M\u00fchleisen Boutique Renata",
    "wof:placetype":"venue"
},
  "geometry": {"coordinates":[7.53786,47.20673],"type":"Point"}
}