{
  "type": "Feature",
  "properties": {
    "iso:country":"CH",
    "sg:address":"Sihlhaldenstrasse 9",
    "sg:city":"R\u00fcschlikon",
    "sg:orig_category":"Geb\u00e4ude, Wohnungsreinigung Reinigungsgewerbe",
    "sg:phone":"+41 17240604",
    "sg:postcode":"8803",
    "sg:province":"Z\u00fcrich",
    "wof:name":"Spiso Reinigungen Gmbh",
    "wof:placetype":"venue"
},
  "geometry": {"coordinates":[8.5475530624,47.2979164124],"type":"Point"}
}