{
  "type": "Feature",
  "properties": {
    "iso:country":"CH",
    "sg:address":"Beckenhofstrasse 1 8006 Z\u00fcrich. Postfach 374",
    "sg:city":"Z\u00fcrich",
    "sg:orig_category":"Aktivit\u00e4t der Bankinstitute Kreditinstitute ohne Spezialkreditinstitute",
    "sg:phone":"+41 13653434",
    "sg:postcode":"8035",
    "sg:province":"Z\u00fcrich",
    "wof:name":"Habibsons Bank Ltd, London, Zweigniederlassung Z\u00fcrich",
    "wof:placetype":"venue"
},
  "geometry": {"coordinates":[8.541441,47.382889],"type":"Point"}
}