{
  "type": "Feature",
  "properties": {
    "addr:full":"Hagenbachstrasse Vogelsang Dussnang Thurgau 8374",
    "addr:postcode":"8374",
    "addr:street":"Hagenbachstrasse",
    "iso:country":"CH",
    "sg:address":"Hagenbachstrasse Vogelsang",
    "sg:city":"Dussnang",
    "sg:orig_category":"Bauschreinerei Innenausbau",
    "sg:phone":"+41 71 977 18 31",
    "sg:postcode":"8374",
    "sg:province":"Thurgau",
    "wof:name":"Bruno Siegfried Schreinerei",
    "wof:placetype":"venue"
},
  "geometry": {"coordinates":[8.961124,47.430317],"type":"Point"}
}