{
  "type": "Feature",
  "properties": {
    "iso:country":"CH",
    "sg:address":"6579",
    "sg:city":"Piazzogna",
    "sg:orig_category":"RESTAURANTS: TEA-ROOMS",
    "sg:phone":"+41 91 795 18 64",
    "sg:postcode":"6579",
    "sg:province":"Ticino",
    "wof:name":"Pelloni Giuseppe",
    "wof:placetype":"venue"
},
  "geometry": {"coordinates":[8.8294000626,46.1273612976],"type":"Point"}
}