{
  "type": "Feature",
  "properties": {
    "iso:country":"CH",
    "sg:address":"Schwalbenstrasse 9",
    "sg:city":"Dussnang",
    "sg:orig_category":"Installation von Heizungs, L\u00fcftungs U Klimaanlagen Sanit\u00e4r U Heizungsinstallation",
    "sg:phone":"+41 71 385 41 51",
    "sg:postcode":"8374",
    "sg:province":"Thurgau",
    "wof:name":"Adrian Keller Haustechnik",
    "wof:placetype":"venue"
},
  "geometry": {"coordinates":[9.2448835373,47.411907196],"type":"Point"}
}