{
  "type": "Feature",
  "properties": {
    "addr:full":"Rue Du Stade 14 1630 Bulle Case Postale 533 Bulle Fribourg 1630",
    "addr:housenumber":"14;533",
    "addr:postcode":"1630;1630",
    "addr:street":"Rue Du Stade;Postale",
    "iso:country":"CH",
    "sg:address":"Rue Du Stade 14 1630 Bulle Case Postale 533",
    "sg:city":"Bulle",
    "sg:orig_category":"Betrieb von Sportanlagen",
    "sg:phone":"+41 26 913 97 40",
    "sg:postcode":"1630",
    "sg:province":"Fribourg",
    "wof:name":"Centre De Tennis Bulle Ctb Sa",
    "wof:placetype":"venue"
},
  "geometry": {"coordinates":[7.065108,46.616695],"type":"Point"}
}