{
  "type": "Feature",
  "properties": {
    "iso:country":"CH",
    "sg:address":"Grand-places 1",
    "sg:city":"Fribourg",
    "sg:orig_category":"Architektur U Ingenieurb\u00fcros",
    "sg:postcode":"1700",
    "sg:province":"Fribourg",
    "wof:name":"Codem Sa",
    "wof:placetype":"venue"
},
  "geometry": {"coordinates":[7.154585,46.803219],"type":"Point"}
}