{
  "type": "Feature",
  "properties": {
    "iso:country":"CH",
    "sg:address":"7513",
    "sg:city":"Silvaplana",
    "sg:orig_category":"Seilbahnen Sessellifte and Skilifte",
    "sg:phone":"+41 81 828 82 45",
    "sg:postcode":"7513",
    "sg:province":"Graubunden",
    "wof:name":"Luftseilbahn Surlej- Silvaplana-corvatsch Ag",
    "wof:placetype":"venue"
},
  "geometry": {"coordinates":[9.7956190109,46.460105896],"type":"Point"}
}