{
  "type": "Feature",
  "properties": {
    "iso:country":"CH",
    "sg:address":"Untere Gasse 21",
    "sg:city":"Chur",
    "sg:orig_category":"Detailhandel mit Damenbekleidung Grosshandel mit H\u00e4uten, Fellen U Leder",
    "sg:phone":"+41 81 252 20 21",
    "sg:postcode":"7000",
    "sg:province":"Graubunden",
    "wof:name":"Varia Leder & Kaschmir",
    "wof:placetype":"venue"
},
  "geometry": {"coordinates":[9.5300989151,46.8485374451],"type":"Point"}
}