{
  "type": "Feature",
  "properties": {
    "iso:country":"CH",
    "sg:address":"Avenue Dapples 40",
    "sg:city":"Lausanne",
    "sg:orig_category":"Informatikschulen",
    "sg:phone":"+41 21 601 45 30",
    "sg:postcode":"1006",
    "sg:province":"Vaud",
    "wof:name":"Women Investors Club Cours De Bourse",
    "wof:placetype":"venue"
},
  "geometry": {"coordinates":[6.6273479462,46.5148773193],"type":"Point"}
}