{
  "type": "Feature",
  "properties": {
    "iso:country":"CH",
    "sg:address":"Seerosenstrasse 26",
    "sg:city":"Stansstad",
    "sg:orig_category":"Malerei",
    "sg:phone":"+41 71 222 65 65",
    "sg:postcode":"6362",
    "sg:province":"Nidwalden",
    "wof:name":"Malerei Schurr Ag Malergesch\u00e4ft",
    "wof:placetype":"venue"
},
  "geometry": {"coordinates":[9.3737154007,47.4263916016],"type":"Point"}
}