{
  "type": "Feature",
  "properties": {
    "iso:country":"CH",
    "sg:address":"Gravelone Rue De 81",
    "sg:city":"Sion",
    "sg:orig_category":"Architektur U Ingenieurb\u00fcros",
    "sg:postcode":"1950",
    "sg:province":"Valais",
    "wof:name":"Lami Sa Bureau D'\u00e9tude Et Atelier De Dessin, Succursale De Sion",
    "wof:placetype":"venue"
},
  "geometry": {"coordinates":[7.347867,46.233597],"type":"Point"}
}