{
  "type": "Feature",
  "properties": {
    "iso:country":"CH",
    "sg:address":"Haslistrasse 1",
    "sg:city":"M\u00fcllheim-wigoltgn",
    "sg:orig_category":"Gasth\u00f6fe/Gasth\u00e4user mit Restaurant",
    "sg:phone":"+41 52 763 16 31",
    "sg:postcode":"8554",
    "sg:province":"Thurgau",
    "wof:name":"Landgasthof Wartegg",
    "wof:placetype":"venue"
},
  "geometry": {"coordinates":[9.0265274048,47.5829925537],"type":"Point"}
}