{
  "type": "Feature",
  "properties": {
    "iso:country":"CH",
    "sg:address":"Route De Saint-georges 73",
    "sg:city":"Petit-lancy",
    "sg:classifiers":[
        {
            "category":"Restaurant",
            "type":"Food & Drink"
        }
    ],
    "sg:phone":"+41 22 870 02 10",
    "sg:postcode":"1213",
    "sg:province":"Gen\u00e8ve",
    "wof:name":"Caf\u00e9 La Terrasse Saint-georges",
    "wof:placetype":"venue"
},
  "geometry": {"coordinates":[6.1170978546,46.1964645386],"type":"Point"}
}