{
  "type": "Feature",
  "properties": {
    "iso:country":"CH",
    "sg:address":"Sur La C\u00f4te 105",
    "sg:city":"Bressaucourt",
    "sg:orig_category":"Stukkateurgewerbe, Gipserei U Verputzerei",
    "sg:phone":"+41 32 466 91 57",
    "sg:postcode":"2904",
    "sg:province":"Jura",
    "wof:name":"B\u00e4rtschi Paul, Gypserie, Peinture",
    "wof:placetype":"venue"
},
  "geometry": {"coordinates":[7.0350022316,47.3889579773],"type":"Point"}
}