{
  "type": "Feature",
  "properties": {
    "iso:country":"CH",
    "sg:address":"Brunnenmattstrasse 7",
    "sg:city":"Oberwil",
    "sg:classifiers":[
        {
            "category":"Community Center",
            "subcategory":"Social",
            "type":"Public Place"
        }
    ],
    "sg:phone":"+41 41 711 21 48",
    "sg:postcode":"6317",
    "sg:province":"Zug",
    "sg:tags":[
        "function",
        "hiring",
        "room",
        "event"
    ],
    "wof:name":"Sch\u00f6nenberger S\u00f6hne Ag",
    "wof:placetype":"venue"
},
  "geometry": {"coordinates":[8.5092639923,47.1486930847],"type":"Point"}
}