{
  "type": "Feature",
  "properties": {
    "iso:country":"CH",
    "sg:address":"Neugasse 29",
    "sg:city":"Zug",
    "sg:orig_category":"Unclassifiable Establishments",
    "sg:postcode":"6300",
    "sg:province":"Zug",
    "wof:name":"Cortesi G. + Co Landschaftsg\u00e4rtnerei; Planung, Ausf\u00fchrung. G\u00e4rtnerei, Umgebungsgestaltung",
    "wof:placetype":"venue"
},
  "geometry": {"coordinates":[9.8444271088,46.4890403748],"type":"Point"}
}