{
  "type": "Feature",
  "properties": {
    "iso:country":"CH",
    "sg:address":"Sunnebode 79",
    "sg:city":"Leimiswil",
    "sg:classifiers":[
        {
            "category":"Personal",
            "subcategory":"Hair Removal",
            "type":"Services"
        }
    ],
    "sg:phone":"+41 62 965 31 13",
    "sg:postcode":"4935",
    "sg:province":"Bern",
    "sg:tags":[
        "brush"
    ],
    "wof:name":"Indola Haarkosmetik & Coiffeurbedarf",
    "wof:placetype":"venue"
},
  "geometry": {"coordinates":[7.7642140388,47.1500701904],"type":"Point"}
}