{
  "type": "Feature",
  "properties": {
    "iso:country":"CH",
    "sg:address":"Leisibachstrasse",
    "sg:city":"Root",
    "sg:orig_category":"Mit Sport verbundene T\u00e4tigkeiten Sonstige mit Sport verbundene T\u00e4tigkeiten",
    "sg:phone":"+41 55 282 34 20",
    "sg:postcode":"6037",
    "sg:province":"Luzern",
    "wof:name":"Reitzentrum Twirrenhof Ag",
    "wof:placetype":"venue"
},
  "geometry": {"coordinates":[8.9330854416,47.2403106689],"type":"Point"}
}