{
  "type": "Feature",
  "properties": {
    "iso:country":"CH",
    "sg:address":"Sonnenbergstrasse 45",
    "sg:city":"Sarnen",
    "sg:orig_category":"Herstellung von Metallerzeugnissen ohne Maschinenbau Herstellung von Zahnr\u00e4dern U Antriebselementen",
    "sg:phone":"+41 41 661 19 70",
    "sg:postcode":"6060",
    "sg:province":"Obwalden",
    "wof:name":"Multi Tech Precision Ag Pr\u00e4zisionstechnik",
    "wof:placetype":"venue"
},
  "geometry": {"coordinates":[8.2404060364,46.8971366882],"type":"Point"}
}