{
  "type": "Feature",
  "properties": {
    "iso:country":"CH",
    "sg:address":"Quai Gustave-ador 10",
    "sg:city":"Gen\u00e8ve",
    "sg:orig_category":"Finanzierungsinstitutionen Handelsvermittlung U Grosshandel",
    "sg:phone":"+41 62 873 33 23",
    "sg:postcode":"1207",
    "sg:province":"Gen\u00e8ve",
    "wof:name":"Wilba Gmbh",
    "wof:placetype":"venue"
},
  "geometry": {"coordinates":[7.9921221733,47.547504425],"type":"Point"}
}