{
  "type": "Feature",
  "properties": {
    "iso:country":"CH",
    "sg:address":"Sch\u00fctzenstrasse 43",
    "sg:city":"Winterthur",
    "sg:classifiers":[
        {
            "category":"Restaurant",
            "type":"Food & Drink"
        }
    ],
    "sg:phone":"+41 52 222 85 76",
    "sg:postcode":"8400",
    "sg:province":"Z\u00fcrich",
    "wof:name":"Restaurant Chili Mex",
    "wof:placetype":"venue"
},
  "geometry": {"coordinates":[8.7195796967,47.5047683716],"type":"Point"}
}