{
  "type": "Feature",
  "properties": {
    "iso:country":"CH",
    "sg:address":"Hofacker 325",
    "sg:city":"Schlossrued",
    "sg:orig_category":"Hoch U Tiefbau",
    "sg:phone":"+41 62 721 23 57",
    "sg:postcode":"5044",
    "sg:province":"Aargau",
    "wof:name":"Kurt Suter Baugesch\u00e4ft",
    "wof:placetype":"venue"
},
  "geometry": {"coordinates":[8.0849657059,47.2933731079],"type":"Point"}
}