{
  "type": "Feature",
  "properties": {
    "iso:country":"CH",
    "sg:address":"Schlatterstrasse",
    "sg:city":"Schlatt",
    "sg:orig_category":"Sportvereine Sch\u00fctzen",
    "sg:phone":"+41 52 363 27 70",
    "sg:postcode":"8418",
    "sg:province":"Z\u00fcrich",
    "wof:name":"Bezirkssch\u00fctzenverband W'thur",
    "wof:placetype":"venue"
},
  "geometry": {"coordinates":[8.8125648499,47.4860801697],"type":"Point"}
}