{
  "type": "Feature",
  "properties": {
    "iso:country":"CH",
    "sg:address":"Vollikerstrasse 24",
    "sg:city":"Esslingen",
    "sg:classifiers":[
        {
            "category":"Communications",
            "subcategory":"Film & Video Production",
            "type":"Services"
        }
    ],
    "sg:phone":"+41 19842485",
    "sg:postcode":"8133",
    "sg:province":"Z\u00fcrich",
    "sg:tags":[
        "videofilmherstellung",
        "u"
    ],
    "wof:name":"Bahl Hansj\u00f6rg, Duo-film",
    "wof:placetype":"venue"
},
  "geometry": {"coordinates":[8.7113571167,47.2842826843],"type":"Point"}
}