{
  "type": "Feature",
  "properties": {
    "iso:country":"CH",
    "sg:address":"Route De Chardonne",
    "sg:city":"Puidoux",
    "sg:orig_category":"Injection Cannulas",
    "sg:phone":"+41 21 946 04 80",
    "sg:postcode":"1070",
    "sg:province":"Vaud",
    "wof:name":"Medelec Minimeca Sa",
    "wof:placetype":"venue"
},
  "geometry": {"coordinates":[6.7702088356,46.490852356],"type":"Point"}
}