{
  "type": "Feature",
  "properties": {
    "iso:country":"CH",
    "sg:address":"Via San Gottardo 23",
    "sg:city":"Vezia",
    "sg:orig_category":"Herstellung von Seifen, Wasch U Reinigungsmitteln",
    "sg:phone":"+41 77856026",
    "sg:postcode":"6943",
    "sg:province":"Ticino",
    "wof:name":"Dudler Sa",
    "wof:placetype":"venue"
},
  "geometry": {"coordinates":[8.9370727539,46.0246276855],"type":"Point"}
}