{
  "type": "Feature",
  "properties": {
    "iso:country":"CH",
    "sg:address":"Rathausstrasse 58 4410 Liestal. Postfach 326",
    "sg:city":"Liestal",
    "sg:classifiers":[
        {
            "category":"Professional",
            "subcategory":"Employment Agencies",
            "type":"Services"
        }
    ],
    "sg:phone":"+41 61 922 22 66",
    "sg:postcode":"4410",
    "sg:province":"Basel-Landschaft",
    "sg:tags":[
        "personal",
        "u",
        "stellenvermittlung"
    ],
    "wof:name":"Elan Personal Ag Liestal",
    "wof:placetype":"venue"
},
  "geometry": {"coordinates":[7.7350621223,47.4836463928],"type":"Point"}
}