{
  "type": "Feature",
  "properties": {
    "addr:full":"Moosbachweg 13 Zug Zug 6300",
    "addr:housenumber":"13",
    "addr:postcode":"6300",
    "addr:street":"Moosbachweg;Zug",
    "iso:country":"CH",
    "sg:address":"Moosbachweg 13",
    "sg:city":"Zug",
    "sg:orig_category":"Allgemeiner Hoch U Tiefbau Hoch U Tiefbau",
    "sg:phone":"+41 79 341 94 47",
    "sg:postcode":"6300",
    "sg:province":"Zug",
    "wof:name":"Urban Fuchs Bau Ag",
    "wof:placetype":"venue"
},
  "geometry": {"coordinates":[8.521304,47.168709],"type":"Point"}
}