{
  "type": "Feature",
  "properties": {
    "iso:country":"CH",
    "sg:address":"Kirchgasse 36 8302 Kloten. Postfach",
    "sg:city":"Kloten",
    "sg:classifiers":[
        {
            "category":"Restaurant",
            "type":"Food & Drink"
        }
    ],
    "sg:phone":"+41 18137284",
    "sg:postcode":"8302",
    "sg:province":"Z\u00fcrich",
    "wof:name":"Restaurant Sternen",
    "wof:placetype":"venue"
},
  "geometry": {"coordinates":[8.5836248398,47.4528274536],"type":"Point"}
}