{
  "type": "Feature",
  "properties": {
    "iso:country":"CH",
    "sg:address":"St. Gallerstrasse 1",
    "sg:city":"Tuggen",
    "sg:classifiers":[
        {
            "category":"Restaurant",
            "type":"Food & Drink"
        }
    ],
    "sg:phone":"+41 71 385 16 88",
    "sg:postcode":"8856",
    "sg:province":"Schwyz",
    "wof:name":"Restaurant Hirschen",
    "wof:placetype":"venue"
},
  "geometry": {"coordinates":[9.2550849915,47.4166526794],"type":"Point"}
}