{
  "type": "Feature",
  "properties": {
    "iso:country":"CH",
    "sg:address":"Via Bora Da Besa",
    "sg:city":"Gentilino",
    "sg:orig_category":"Vereine Musik/Blasmusik",
    "sg:phone":"+41 91 994 91 79",
    "sg:postcode":"6925",
    "sg:province":"Ticino",
    "wof:name":"Filarmonica Liberale Radicale Della Collina D'oro",
    "wof:placetype":"venue"
},
  "geometry": {"coordinates":[8.9305830002,45.9907913208],"type":"Point"}
}