{
  "type": "Feature",
  "properties": {
    "iso:country":"CH",
    "sg:address":"Obergasse 7",
    "sg:city":"Schmerikon",
    "sg:orig_category":"Fussboden, Fliesen U Plattenlegerei, Tapeziererei Verlegen von Fliesen U Platten",
    "sg:phone":"+41 55 282 39 78",
    "sg:postcode":"8716",
    "sg:province":"St. Gallen",
    "wof:name":"Carminati Plattenbel\u00e4ge Gmbh",
    "wof:placetype":"venue"
},
  "geometry": {"coordinates":[8.9460840225,47.2267456055],"type":"Point"}
}