{
  "type": "Feature",
  "properties": {
    "iso:country":"CH",
    "sg:address":"Chemin De Saux 2b",
    "sg:city":"Tolochenaz",
    "sg:orig_category":"D\u00e4mmung gegen K\u00e4lte, W\u00e4rme, Schall U Ersch\u00fctterung Fussboden, Fliesen U Plattenlegerei, Tapeziererei",
    "sg:phone":"+41 76 567 60 71",
    "sg:postcode":"1131",
    "sg:province":"Vaud",
    "wof:name":"Plafonds Miro Bozic",
    "wof:placetype":"venue"
},
  "geometry": {"coordinates":[6.4752998352,46.4988517761],"type":"Point"}
}