{
  "type": "Feature",
  "properties": {
    "iso:country":"CH",
    "sg:address":"Hohlengasse 16",
    "sg:city":"Uetendorf",
    "sg:orig_category":"Detailhandel mit medizinischen U orthop\u00e4dischen Artikeln Reparatur von Schuhen U Lederwaren",
    "sg:phone":"+41 33 345 59 45",
    "sg:postcode":"3661",
    "sg:province":"Bern",
    "wof:name":"Peter B\u00e4hler",
    "wof:placetype":"venue"
},
  "geometry": {"coordinates":[7.5694417953,46.7722663879],"type":"Point"}
}