{
  "type": "Feature",
  "properties": {
    "iso:country":"CH",
    "sg:address":"1525",
    "sg:city":"Henniez",
    "sg:orig_category":"Mineralquellen, Herstellung von alkoholfreien Getr\u00e4nken",
    "sg:postcode":"1525",
    "sg:province":"Vaud",
    "wof:name":"Speed Powerdrink Ag",
    "wof:placetype":"venue"
},
  "geometry": {"coordinates":[8.3148832321,46.9920654297],"type":"Point"}
}