{
  "type": "Feature",
  "properties": {
    "iso:country":"CH",
    "sg:address":"Rheinm\u00fchleweg 84",
    "sg:city":"Chur",
    "sg:orig_category":"Tierheime",
    "sg:phone":"+41 81 353 19 29",
    "sg:postcode":"7000",
    "sg:province":"Graubunden",
    "wof:name":"Tierheim Chur",
    "wof:placetype":"venue"
},
  "geometry": {"coordinates":[9.5291442871,46.8693656921],"type":"Point"}
}