{
  "type": "Feature",
  "properties": {
    "iso:country":"CH",
    "sg:address":"Gartenweg 1-3",
    "sg:city":"Arlesheim",
    "sg:classifiers":[
        {
            "category":"Building & Trades",
            "subcategory":"Electrical",
            "type":"Services"
        }
    ],
    "sg:phone":"+41 61 701 16 16",
    "sg:postcode":"4144",
    "sg:province":"Basel-Landschaft",
    "sg:tags":[
        "installation"
    ],
    "wof:name":"Kellenberger Elektrofachgesch\u00e4ft Ag",
    "wof:placetype":"venue"
},
  "geometry": {"coordinates":[7.6200828552,47.4950294495],"type":"Point"}
}