{
  "type": "Feature",
  "properties": {
    "iso:country":"CH",
    "sg:address":"Z\u00fcrcherstrasse 35",
    "sg:city":"Basel",
    "sg:orig_category":"Malerei",
    "sg:phone":"+41 61 312 52 54",
    "sg:postcode":"4052",
    "sg:province":"Basel-Stadt",
    "wof:name":"Marcel Cigada Malergesch\u00e4ft",
    "wof:placetype":"venue"
},
  "geometry": {"coordinates":[7.6089677811,47.5539016724],"type":"Point"}
}