{
  "type": "Feature",
  "properties": {
    "iso:country":"CH",
    "sg:address":"Tuschgenweg 50 8041 Z\u00fcrich. Postfach",
    "sg:city":"Z\u00fcrich",
    "sg:orig_category":"K\u00fcnstlerische U schriftstellerische T\u00e4tigkeiten U Darbietungen",
    "sg:postcode":"8041",
    "sg:province":"Z\u00fcrich",
    "wof:name":"Mc Shine Lilo, Seidenmalatelier",
    "wof:placetype":"venue"
},
  "geometry": {"coordinates":[8.5145435333,47.3309593201],"type":"Point"}
}