{
  "type": "Feature",
  "properties": {
    "iso:country":"CH",
    "sg:address":"Ringstrasse 12 7324 Vilters. Postfach",
    "sg:city":"Vilters",
    "sg:orig_category":"Allgemeiner Hoch U Tiefbau",
    "sg:postcode":"7324",
    "sg:province":"St. Gallen",
    "wof:name":"Gr\u00fcnenfelder Tiefbau Ag Bauunternehmen",
    "wof:placetype":"venue"
},
  "geometry": {"coordinates":[9.454676,47.025524],"type":"Point"}
}