{
  "type": "Feature",
  "properties": {
    "iso:country":"CH",
    "sg:address":"Soodstrasse 57",
    "sg:city":"Adliswil",
    "sg:orig_category":"Grosshandel mit sonstigen Gebrauchs U Verbrauchsg\u00fctern Satzherstellung U Reproduktion",
    "sg:phone":"+41 17100045",
    "sg:postcode":"8134",
    "sg:province":"Z\u00fcrich",
    "wof:name":"Realfot-gr\u00e4miger Ag",
    "wof:placetype":"venue"
},
  "geometry": {"coordinates":[8.5226287842,47.3190956116],"type":"Point"}
}