{
  "type": "Feature",
  "properties": {
    "iso:country":"CH",
    "sg:address":"Haldenstrasse 2",
    "sg:city":"Baar",
    "sg:orig_category":"Sportvereine Turnen",
    "sg:phone":"+41 41 761 05 74",
    "sg:postcode":"6340",
    "sg:province":"Zug",
    "wof:name":"Turnverein Ktv Concordia",
    "wof:placetype":"venue"
},
  "geometry": {"coordinates":[8.5350227356,47.1960411072],"type":"Point"}
}