{
  "type": "Feature",
  "properties": {
    "iso:country":"CH",
    "sg:address":"Hofstettenstrasse 41",
    "sg:city":"Thun",
    "sg:orig_category":"Architektur U Ingenieurb\u00fcros",
    "sg:phone":"+41 33 222 22 91",
    "sg:postcode":"3600",
    "sg:province":"Bern",
    "wof:name":"Hebler Peter, Planungsb\u00fcro F\u00fcr Fassaden Und Metallbau",
    "wof:placetype":"venue"
},
  "geometry": {"coordinates":[7.636731,46.753494],"type":"Point"}
}