{
  "type": "Feature",
  "properties": {
    "iso:country":"CH",
    "sg:address":"Moserstrasse 22",
    "sg:city":"Schaffhausen",
    "sg:orig_category":"Grosshandel mit B\u00fcromaschinen Grosshandel mit Datenverarbeitungsger\u00e4ten",
    "sg:phone":"+41 52 620 02 91",
    "sg:postcode":"8200",
    "sg:province":"Schaffhausen",
    "wof:name":"K\u00fcng Computer Computer Hard-& Software",
    "wof:placetype":"venue"
},
  "geometry": {"coordinates":[8.6389303207,47.6951789856],"type":"Point"}
}