{
  "type": "Feature",
  "properties": {
    "iso:country":"CH",
    "sg:address":"Kn\u00fcslihubelweg 20",
    "sg:city":"Bern",
    "sg:orig_category":"Zahntechnische Laboratorien",
    "sg:phone":"+41 71 278 26 54",
    "sg:postcode":"3007",
    "sg:province":"Bern",
    "wof:name":"David Zweifel Zahntechnisches Labor",
    "wof:placetype":"venue"
},
  "geometry": {"coordinates":[9.3646774292,47.4173965454],"type":"Point"}
}