{
  "type": "Feature",
  "properties": {
    "iso:country":"CH",
    "sg:address":"Route D'avully",
    "sg:city":"Avully",
    "sg:orig_category":"Detailhandel mit Fleisch U Fleischwaren",
    "sg:postcode":"1237",
    "sg:province":"Gen\u00e8ve",
    "wof:name":"Sm Viandes Sarl",
    "wof:placetype":"venue"
},
  "geometry": {"coordinates":[6.0031518936,46.1682167053],"type":"Point"}
}