{
  "type": "Feature",
  "properties": {
    "iso:country":"CH",
    "sg:address":"Leimeng\u00e4ssli 5",
    "sg:city":"Niederscherli",
    "sg:classifiers":[
        {
            "category":"Restaurant",
            "type":"Food & Drink"
        }
    ],
    "sg:phone":"+41 31 849 01 45",
    "sg:postcode":"3145",
    "sg:province":"Bern",
    "wof:name":"Restaurant Scherliau",
    "wof:placetype":"venue"
},
  "geometry": {"coordinates":[7.3885068893,46.8849906921],"type":"Point"}
}