{
  "type": "Feature",
  "properties": {
    "iso:country":"CH",
    "sg:address":"Rue Du Ch\u00e2teau",
    "sg:city":"Tramelan",
    "sg:orig_category":"Restaurants Schwimmb\u00e4der",
    "sg:phone":"+41 32 487 59 26",
    "sg:postcode":"2720",
    "sg:province":"Bern",
    "wof:name":"Piscine Communale",
    "wof:placetype":"venue"
},
  "geometry": {"coordinates":[7.1144652367,47.2238121033],"type":"Point"}
}