{
  "type": "Feature",
  "properties": {
    "iso:country":"CH",
    "sg:address":"Buchacker 50",
    "sg:city":"Hellsau",
    "sg:orig_category":"Film U Videofilmherstellung Filmverleih U Videoprogrammanbieter",
    "sg:phone":"+41 71 385 09 08",
    "sg:postcode":"3429",
    "sg:province":"Bern",
    "wof:name":"B + S Film Gmbh",
    "wof:placetype":"venue"
},
  "geometry": {"coordinates":[9.2585515976,47.4163398743],"type":"Point"}
}