{
  "type": "Feature",
  "properties": {
    "iso:country":"CH",
    "sg:address":"5444 K\u00fcnten. Postfach",
    "sg:city":"K\u00fcnten",
    "sg:orig_category":"Vereine Fasnacht",
    "sg:phone":"+41 56 496 55 83",
    "sg:postcode":"5444",
    "sg:province":"Aargau",
    "wof:name":"Guggenmusik Mu-m\u00e2-f\u00e4ger",
    "wof:placetype":"venue"
},
  "geometry": {"coordinates":[8.3263196945,47.3879318237],"type":"Point"}
}