{
  "type": "Feature",
  "properties": {
    "iso:country":"CH",
    "sg:address":"Avenue Des Pins 3",
    "sg:city":"Yvonand",
    "sg:orig_category":"Reiseb\u00fcros U Reiseveranstalter",
    "sg:phone":"+41 61 915 91 31",
    "sg:postcode":"1462",
    "sg:province":"Vaud",
    "wof:name":"V\u00f6gtli Reisen Ag",
    "wof:placetype":"venue"
},
  "geometry": {"coordinates":[7.6543989182,47.4347801208],"type":"Point"}
}