{
  "type": "Feature",
  "properties": {
    "addr:full":"Rue De La Gare 9 Cully Vaud 1096",
    "addr:housenumber":"9",
    "addr:postcode":"1096",
    "addr:street":"Rue De La Gare",
    "iso:country":"CH",
    "sg:address":"Rue De La Gare 9",
    "sg:city":"Cully",
    "sg:orig_category":"Bauspenglerei Dachdeckerei",
    "sg:phone":"+41 21 799 24 97",
    "sg:postcode":"1096",
    "sg:province":"Vaud",
    "wof:name":"Albert Br\u00fcgger Sa Ferblanterie & Couverture",
    "wof:placetype":"venue"
},
  "geometry": {"coordinates":[6.727892,46.488659],"type":"Point"}
}