{
  "type": "Feature",
  "properties": {
    "iso:country":"CH",
    "sg:address":"Via Linoleum",
    "sg:city":"Giubiasco",
    "sg:orig_category":"Mahl U Sch\u00e4lm\u00fchlen",
    "sg:phone":"+41 91 857 88 88",
    "sg:postcode":"6512",
    "sg:province":"Ticino",
    "wof:name":"Molini Ticinesi Riuniti Sa",
    "wof:placetype":"venue"
},
  "geometry": {"coordinates":[9.0077953339,46.1743011475],"type":"Point"}
}