{
  "type": "Feature",
  "properties": {
    "iso:country":"CH",
    "sg:address":"Martastrasse 8",
    "sg:city":"Dietikon",
    "sg:orig_category":"Eisenbahnverkehr",
    "sg:postcode":"8953",
    "sg:province":"Z\u00fcrich",
    "wof:name":"Stauffer Schienen Und Spezialfahrzeuge",
    "wof:placetype":"venue"
},
  "geometry": {"coordinates":[8.4057378769,47.4072494507],"type":"Point"}
}