{
  "type": "Feature",
  "properties": {
    "iso:country":"CH",
    "sg:address":"Ebnatstrasse 29",
    "sg:city":"Schaffhausen",
    "sg:orig_category":"RESTAURANTS: TEA-ROOMS",
    "sg:postcode":"8200",
    "sg:province":"Schaffhausen",
    "wof:name":"Basilea Gastronomica Ag",
    "wof:placetype":"venue"
},
  "geometry": {"coordinates":[7.556178093,47.5139923096],"type":"Point"}
}