{
  "type": "Feature",
  "properties": {
    "iso:country":"CH",
    "sg:address":"Murtenstrasse 54",
    "sg:city":"Bern",
    "sg:orig_category":"Detailhandel mit Blumen U Pflanzen Fachdetailhandel in Verkaufsr\u00e4umen",
    "sg:phone":"+41 31 381 96 87",
    "sg:postcode":"3008",
    "sg:province":"Bern",
    "wof:name":"Blumengesch\u00e4ft Schwab, Inhaber Badertscher Werner",
    "wof:placetype":"venue"
},
  "geometry": {"coordinates":[7.424448,46.950344],"type":"Point"}
}