{
  "type": "Feature",
  "properties": {
    "iso:country":"CH",
    "sg:address":"Im Langsamstig 2",
    "sg:city":"Dietikon",
    "sg:orig_category":"Sportvereine Triathlon Laufen, Schwimmen, Velo",
    "sg:phone":"+41 17402879",
    "sg:postcode":"8953",
    "sg:province":"Z\u00fcrich",
    "wof:name":"Triathlon Team Altstetten",
    "wof:placetype":"venue"
},
  "geometry": {"coordinates":[8.4019432068,47.3984680176],"type":"Point"}
}