{
  "type": "Feature",
  "properties": {
    "iso:country":"CH",
    "sg:address":"H\u00f6henweg 22 8836 Bennau. Postfach",
    "sg:city":"Bennau",
    "sg:orig_category":"Grosshandel mit Getr\u00e4nken",
    "sg:phone":"+41 55 412 82 36",
    "sg:postcode":"8836",
    "sg:province":"Schwyz",
    "wof:name":"Vinova Christian Jud",
    "wof:placetype":"venue"
},
  "geometry": {"coordinates":[8.7297849655,47.1484451294],"type":"Point"}
}