{
  "type": "Feature",
  "properties": {
    "iso:country":"CH",
    "sg:address":"Aargauerstrasse 16 8048 Z\u00fcrich. Postfach",
    "sg:city":"Z\u00fcrich",
    "sg:orig_category":"Sonstiger Detailhandel nicht in Verkaufsr\u00e4umen",
    "sg:postcode":"8048",
    "sg:province":"Z\u00fcrich",
    "wof:name":"Karin's Snack-bar, Schaffner Snack-bar Mit Kalter Und Warmer K\u00fcche Usw",
    "wof:placetype":"venue"
},
  "geometry": {"coordinates":[8.5008354187,47.3923072815],"type":"Point"}
}