{
  "type": "Feature",
  "properties": {
    "iso:country":"CH",
    "sg:address":"Hohle Gasse 13",
    "sg:city":"Frutigen",
    "sg:orig_category":"Herstellung von Tanks U Sammelbeh\u00e4ltern aus Metall",
    "sg:phone":"+41 33 671 16 93",
    "sg:postcode":"3714",
    "sg:province":"Bern",
    "wof:name":"Egger & Co Tankrevisionen",
    "wof:placetype":"venue"
},
  "geometry": {"coordinates":[7.643684864,46.5896263123],"type":"Point"}
}