{
  "type": "Feature",
  "properties": {
    "iso:country":"CH",
    "sg:address":"Langhagstrasse 16",
    "sg:city":"Olten",
    "sg:orig_category":"Detailhandel mit Damenbekleidung Detailhandel mit Herrenbekleidung",
    "sg:postcode":"4600",
    "sg:province":"Solothurn",
    "wof:name":"Karin Bohrer Schloss-l\u00e4deli",
    "wof:placetype":"venue"
},
  "geometry": {"coordinates":[7.9206609726,47.3472747803],"type":"Point"}
}