{
  "type": "Feature",
  "properties": {
    "iso:country":"CH",
    "sg:address":"Steinackerstrasse 6 4853 Murgenthal. Postfach",
    "sg:city":"Murgenthal",
    "sg:orig_category":"Unclassifiable Establishments",
    "sg:postcode":"4853",
    "sg:province":"Aargau",
    "wof:name":"Wullisan, Wullschleger P.",
    "wof:placetype":"venue"
},
  "geometry": {"coordinates":[7.8451662064,47.2722854614],"type":"Point"}
}