{
  "type": "Feature",
  "properties": {
    "iso:country":"CH",
    "sg:address":"Gottardo Via San 6",
    "sg:city":"Balerna",
    "sg:orig_category":"Handel mit Automobilen",
    "sg:phone":"+41 91 683 33 53",
    "sg:postcode":"6828",
    "sg:province":"Ticino",
    "wof:name":"Agustoni Rolando Sa",
    "wof:placetype":"venue"
},
  "geometry": {"coordinates":[9.0075149536,45.8496818542],"type":"Point"}
}