{
  "type": "Feature",
  "properties": {
    "iso:country":"CH",
    "sg:address":"Haldenhof",
    "sg:city":"Hallwil",
    "sg:orig_category":"Verarbeitung von Milch Verwertung von Milch",
    "sg:postcode":"5705",
    "sg:province":"Aargau",
    "wof:name":"K\u00e4sereigenossenschaft Harschwil.",
    "wof:placetype":"venue"
},
  "geometry": {"coordinates":[9.2117004395,47.4424667358],"type":"Point"}
}