{
  "type": "Feature",
  "properties": {
    "iso:country":"CH",
    "sg:address":"Kybourg Chemin Des 1",
    "sg:city":"Fribourg",
    "sg:orig_category":"Sonstige mit der Informatik verbundene T\u00e4tigkeiten",
    "sg:postcode":"1700",
    "sg:province":"Fribourg",
    "wof:name":"Amel Consult Sa",
    "wof:placetype":"venue"
},
  "geometry": {"coordinates":[7.1536831856,46.8037452698],"type":"Point"}
}