{
  "type": "Feature",
  "properties": {
    "iso:country":"CH",
    "sg:address":"Subingenstrasse 28 4557 Horriwil. Postfach 5",
    "sg:city":"Horriwil",
    "sg:orig_category":"Mechanische Werkst\u00e4tten",
    "sg:phone":"+41 32 614 18 76",
    "sg:postcode":"4557",
    "sg:province":"Solothurn",
    "wof:name":"Albert Guldimann Mechanische Werkstatt",
    "wof:placetype":"venue"
},
  "geometry": {"coordinates":[7.6187281609,47.186252594],"type":"Point"}
}