{
  "type": "Feature",
  "properties": {
    "iso:country":"CH",
    "sg:address":"Seftigenstrasse 21 3007 Bern. Postfach 6",
    "sg:city":"Bern",
    "sg:orig_category":"Herstellung von Anstrichmitteln, Druckfarben U Kitten",
    "sg:phone":"+41 31 371 51 11",
    "sg:postcode":"3007",
    "sg:province":"Bern",
    "wof:name":"Peter Rieben Ag Farbwaren, Zubeh\u00f6r; Fabr, Handel. Malergesch\u00e4ft",
    "wof:placetype":"venue"
},
  "geometry": {"coordinates":[7.4323701859,46.9384346008],"type":"Point"}
}