{
  "type": "Feature",
  "properties": {
    "iso:country":"CH",
    "sg:address":"A4 Winterthur-schaffhausen",
    "sg:city":"Adlikon",
    "sg:orig_category":"Instandhaltung U Reparatur von Automobilen",
    "sg:phone":"+41 52 305 20 00",
    "sg:postcode":"8452",
    "sg:province":"Z\u00fcrich",
    "wof:name":"Autohaus Citro\u00ebn Nord Ag",
    "wof:placetype":"venue"
},
  "geometry": {"coordinates":[8.6925001144,47.5826721191],"type":"Point"}
}