{
  "type": "Feature",
  "properties": {
    "iso:country":"CH",
    "sg:address":"Chemin Du Reposoir 24",
    "sg:city":"Lausanne",
    "sg:orig_category":"Detailhandel mit Brot, Back U S\u00fcsswaren Sonstige Kurierdienste",
    "sg:phone":"+41 21 616 55 12",
    "sg:postcode":"1007",
    "sg:province":"Vaud",
    "wof:name":"Jackpizza Msd Sa Livraison \u00e0 Domicile",
    "wof:placetype":"venue"
},
  "geometry": {"coordinates":[6.614899,46.516552],"type":"Point"}
}