{
  "type": "Feature",
  "properties": {
    "iso:country":"CH",
    "sg:address":"Casa Ferrari",
    "sg:city":"Sessa",
    "sg:orig_category":"Hoch U Tiefbau",
    "sg:phone":"+41 91 608 18 79",
    "sg:postcode":"6997",
    "sg:province":"Ticino",
    "wof:name":"Luciano Ferrari Impresa Di Costruzioni",
    "wof:placetype":"venue"
},
  "geometry": {"coordinates":[8.8175354004,46.000289917],"type":"Point"}
}