{
  "type": "Feature",
  "properties": {
    "addr:full":"M\u00fchlestrasse 3 Niederlenz Aargau 5702",
    "addr:housenumber":"3",
    "addr:postcode":"5702",
    "addr:street":"Muehlestrasse",
    "iso:country":"CH",
    "sg:address":"M\u00fchlestrasse 3",
    "sg:city":"Niederlenz",
    "sg:orig_category":"Architektur U Ingenieurb\u00fcros",
    "sg:phone":"+41 62 891 67 87",
    "sg:postcode":"5702",
    "sg:province":"Aargau",
    "wof:name":"Tp Technische Planung Egger Werner",
    "wof:placetype":"venue"
},
  "geometry": {"coordinates":[8.175276,47.402267],"type":"Point"}
}