{
  "type": "Feature",
  "properties": {
    "iso:country":"CH",
    "sg:address":"Chemin Du Champ-de-ble 15",
    "sg:city":"Chamb\u00e9sy",
    "sg:orig_category":"Interessenvertretungen",
    "sg:postcode":"1292",
    "sg:province":"Gen\u00e8ve",
    "wof:name":"Association Des Chemins Champ De Bl\u00e9 Et Vengeron",
    "wof:placetype":"venue"
},
  "geometry": {"coordinates":[6.1497578621,46.2455215454],"type":"Point"}
}