{
  "type": "Feature",
  "properties": {
    "iso:country":"CH",
    "sg:address":"Brunnenstrasse 2 8610 Uster. Postfach",
    "sg:city":"Uster",
    "sg:orig_category":"Grosshandel mit Holz U Baustoffen",
    "sg:postcode":"8610",
    "sg:province":"Z\u00fcrich",
    "wof:name":"Kies Ag Bollenberg",
    "wof:placetype":"venue"
},
  "geometry": {"coordinates":[8.7755222321,47.2052307129],"type":"Point"}
}