{
  "type": "Feature",
  "properties": {
    "iso:country":"CH",
    "sg:address":"Neunbrunnenstr. 50",
    "sg:city":"Z\u00fcrich",
    "sg:orig_category":"Landverkehr Transport in Rohrfernleitungen",
    "sg:phone":"+41 13071414",
    "sg:postcode":"8050",
    "sg:province":"Z\u00fcrich",
    "wof:name":"Consel Autocontrol Gmbh The Solutions Company",
    "wof:placetype":"venue"
},
  "geometry": {"coordinates":[8.5392532349,47.4171333313],"type":"Point"}
}