{
  "type": "Feature",
  "properties": {
    "iso:country":"CH",
    "sg:address":"Hostattstrasse 11",
    "sg:city":"Sarnen",
    "sg:orig_category":"Finanzierungsinstitutionen",
    "sg:postcode":"6060",
    "sg:province":"Obwalden",
    "wof:name":"Five Stars Investments Ag",
    "wof:placetype":"venue"
},
  "geometry": {"coordinates":[8.2508239746,46.8950958252],"type":"Point"}
}