{
  "type": "Feature",
  "properties": {
    "iso:country":"CH",
    "sg:address":"Graben 2",
    "sg:city":"Aarau",
    "sg:orig_category":"Detailhandel mit Bekleidung Sonstiges Textilgewerbe",
    "sg:phone":"+41 33 951 11 22",
    "sg:postcode":"5000",
    "sg:province":"Aargau",
    "wof:name":"Rohner Katharina Und Hanni",
    "wof:placetype":"venue"
},
  "geometry": {"coordinates":[8.033474,46.754124],"type":"Point"}
}