{
  "type": "Feature",
  "properties": {
    "iso:country":"CH",
    "sg:address":"Hauptstrasse 77",
    "sg:city":"Leuggern",
    "sg:orig_category":"Detailhandel mit Blumen U Pflanzen",
    "sg:phone":"+41 56 245 79 60",
    "sg:postcode":"5316",
    "sg:province":"Aargau",
    "wof:name":"Silvia Maier Blumen-bistro",
    "wof:placetype":"venue"
},
  "geometry": {"coordinates":[8.212487,47.581676],"type":"Point"}
}