{
  "type": "Feature",
  "properties": {
    "iso:country":"CH",
    "sg:address":"M\u00fcnsterhof 9",
    "sg:city":"Z\u00fcrich",
    "sg:orig_category":"Herstellung von Schmuck, Gold U Silberschmiedwaren",
    "sg:postcode":"8001",
    "sg:province":"Z\u00fcrich",
    "wof:name":"Dinten Beatrice Goldschmiedeatelier",
    "wof:placetype":"venue"
},
  "geometry": {"coordinates":[8.5404033661,47.3702201843],"type":"Point"}
}