{
  "type": "Feature",
  "properties": {
    "iso:country":"CH",
    "sg:address":"Ettenbergstrasse 35",
    "sg:city":"Wettswil",
    "sg:orig_category":"Detailhandel mit Getr\u00e4nken",
    "sg:phone":"+41 71 385 54 15",
    "sg:postcode":"8907",
    "sg:province":"Z\u00fcrich",
    "wof:name":"Getr\u00e4nke Hengartner Daniel Kummer",
    "wof:placetype":"venue"
},
  "geometry": {"coordinates":[9.2753038406,47.4368476868],"type":"Point"}
}