{
  "type": "Feature",
  "properties": {
    "iso:country":"CH",
    "sg:address":"Lieberthaus",
    "sg:city":"Weiach",
    "sg:orig_category":"Museen",
    "sg:postcode":"8187",
    "sg:province":"Z\u00fcrich",
    "wof:name":"Ortsmuseum",
    "wof:placetype":"venue"
},
  "geometry": {"coordinates":[8.4358129501,47.5583152771],"type":"Point"}
}