{
  "type": "Feature",
  "properties": {
    "iso:country":"CH",
    "sg:address":"Arnold B\u00f6cklin-strasse 35",
    "sg:city":"Basel",
    "sg:orig_category":"Markt U Meinungsforschung",
    "sg:postcode":"4051",
    "sg:province":"Basel-Stadt",
    "wof:name":"Walder Immomarketing",
    "wof:placetype":"venue"
},
  "geometry": {"coordinates":[7.5765771866,47.5512886047],"type":"Point"}
}