{
  "type": "Feature",
  "properties": {
    "iso:country":"CH",
    "sg:address":"Weidhofstrasse 7",
    "sg:city":"Udligenswil",
    "sg:orig_category":"Malerei Zimmerei, Dachdeckerei, Bauspenglerei U Abdichtung",
    "sg:phone":"+41 41 371 01 04",
    "sg:postcode":"6044",
    "sg:province":"Luzern",
    "wof:name":"Walter Greter Malergesch\u00e4ft",
    "wof:placetype":"venue"
},
  "geometry": {"coordinates":[8.3958501816,47.0898361206],"type":"Point"}
}