{
  "type": "Feature",
  "properties": {
    "iso:country":"CH",
    "sg:address":"Via Fontana",
    "sg:city":"Bellinzona",
    "sg:orig_category":"Verlegen von Fliesen U Platten",
    "sg:phone":"+41 91 825 43 31",
    "sg:postcode":"6500",
    "sg:province":"Ticino",
    "wof:name":"Enrico Ferrario Posa Di Piastrelle",
    "wof:placetype":"venue"
},
  "geometry": {"coordinates":[9.014257431,46.1871185303],"type":"Point"}
}