{
  "type": "Feature",
  "properties": {
    "iso:country":"CH",
    "sg:address":"St. Karli-strasse 13a 6004 Luzern. Postfach",
    "sg:city":"Luzern",
    "sg:orig_category":"RESTAURANTS: TEA-ROOMS",
    "sg:phone":"+41 52 649 13 54",
    "sg:postcode":"6005",
    "sg:province":"Luzern",
    "wof:name":"Restaurant Gemeindehaus Lohn Welter Peter",
    "wof:placetype":"venue"
},
  "geometry": {"coordinates":[8.6692991257,47.7556800842],"type":"Point"}
}