{
  "type": "Feature",
  "properties": {
    "iso:country":"CH",
    "sg:address":"Welbrigstrasse 51",
    "sg:city":"Geroldswil",
    "sg:orig_category":"Architekturb\u00fcros",
    "sg:phone":"+41 26 494 21 60",
    "sg:postcode":"8954",
    "sg:province":"Z\u00fcrich",
    "wof:name":"Beat Baeriswyl Architekturb\u00fcro",
    "wof:placetype":"venue"
},
  "geometry": {"coordinates":[7.2517352104,46.7967453003],"type":"Point"}
}