{
  "type": "Feature",
  "properties": {
    "iso:country":"CH",
    "sg:address":"Haldenstrasse 3",
    "sg:city":"Baar",
    "sg:orig_category":"Diskotheken, Dancings, Night Clubs",
    "sg:phone":"+41 41 760 47 47",
    "sg:postcode":"6340",
    "sg:province":"Zug",
    "wof:name":"Dancing Aladin",
    "wof:placetype":"venue"
},
  "geometry": {"coordinates":[8.5370826721,47.1956443787],"type":"Point"}
}