{
  "type": "Feature",
  "properties": {
    "iso:country":"CH",
    "sg:address":"Duboule Chemin Mo\u00efse- 45 1209 Gen\u00e8ve. Postfach",
    "sg:city":"Gen\u00e8ve",
    "sg:orig_category":"Fotografisches Gewerbe U fotografische Laboratorien",
    "sg:postcode":"1209",
    "sg:province":"Gen\u00e8ve",
    "wof:name":"Environnement Photo Service, Farkas Tibor",
    "wof:placetype":"venue"
},
  "geometry": {"coordinates":[6.1243658066,46.2252998352],"type":"Point"}
}