{
  "type": "Feature",
  "properties": {
    "iso:country":"CH",
    "sg:address":"Ruckstuckstrasse 21",
    "sg:city":"Br\u00fcttisellen",
    "sg:orig_category":"Grosshandel mit Getr\u00e4nken",
    "sg:postcode":"8306",
    "sg:province":"Z\u00fcrich",
    "wof:name":"Swissaqua Gmbh",
    "wof:placetype":"venue"
},
  "geometry": {"coordinates":[8.6309289932,47.4172134399],"type":"Point"}
}