{
  "type": "Feature",
  "properties": {
    "iso:country":"CH",
    "sg:address":"F\u00fcrst Franz Josef Strasse 112 9490 Vaduz. Postfach 1137",
    "sg:city":"Vaduz",
    "sg:orig_category":"Grosshandel mit B\u00fcromaschinen Grosshandel mit Datenverarbeitungsger\u00e4ten",
    "sg:phone":"+423 237 26 26",
    "sg:postcode":"9490",
    "wof:name":"Adland Verwaltungs-anstalt",
    "wof:placetype":"venue"
},
  "geometry": {"coordinates":[9.5231142044,47.144947052],"type":"Point"}
}