{
  "type": "Feature",
  "properties": {
    "iso:country":"CH",
    "sg:address":"Industriestrasse 21 8305 Dietlikon. Postfach",
    "sg:city":"Dietlikon",
    "sg:orig_category":"Herstellung von medizinischen U chirurgischen Ger\u00e4ten sowie orthop\u00e4dischen Vorrichtungen",
    "sg:postcode":"8305",
    "sg:province":"Z\u00fcrich",
    "wof:name":"Zahntechnisches Labor Tadic",
    "wof:placetype":"venue"
},
  "geometry": {"coordinates":[8.6216573715,47.413974762],"type":"Point"}
}