{
  "type": "Feature",
  "properties": {
    "iso:country":"CH",
    "sg:address":"Via Balestra 11 6900 Lugano. Postfach Caselle Postale 2802",
    "sg:city":"Lugano",
    "sg:orig_category":"Aktivit\u00e4t der Bankinstitute Kreditinstitute ohne Spezialkreditinstitute",
    "sg:phone":"+41 22 715 12 11",
    "sg:postcode":"6901",
    "sg:province":"Ticino",
    "wof:name":"Arab Bank (switzerland)",
    "wof:placetype":"venue"
},
  "geometry": {"coordinates":[6.147694,46.207092],"type":"Point"}
}