{
  "type": "Feature",
  "properties": {
    "iso:country":"CH",
    "sg:address":"8890",
    "sg:city":"Flums",
    "sg:orig_category":"RESTAURANTS: TEA-ROOMS",
    "sg:postcode":"8890",
    "sg:province":"St. Gallen",
    "wof:name":"Gassner, H.",
    "wof:placetype":"venue"
},
  "geometry": {"coordinates":[9.3476495743,47.0880584717],"type":"Point"}
}