{
  "type": "Feature",
  "properties": {
    "iso:country":"CH",
    "sg:address":"Avenue De Cour 30",
    "sg:city":"Lausanne",
    "sg:classifiers":[
        {
            "category":"Professional",
            "subcategory":"Employment Agencies",
            "type":"Services"
        }
    ],
    "sg:phone":"+41 79 250 13 88",
    "sg:postcode":"1007",
    "sg:province":"Vaud",
    "sg:tags":[
        "personal",
        "u",
        "stellenvermittlung"
    ],
    "wof:name":"Dm Meyer Daniel Placement De Personnel",
    "wof:placetype":"venue"
},
  "geometry": {"coordinates":[6.6187229156,46.5151519775],"type":"Point"}
}