{
  "type": "Feature",
  "properties": {
    "iso:country":"CH",
    "sg:address":"Luzernerstrasse 19 6037 Root. Postfach 39",
    "sg:city":"Root",
    "sg:orig_category":"Druck ohne Zeitungsdruck Offsetdruck",
    "sg:phone":"+41 71 385 15 20",
    "sg:postcode":"6037",
    "sg:province":"Luzern",
    "wof:name":"Druckerei Br\u00fccker",
    "wof:placetype":"venue"
},
  "geometry": {"coordinates":[9.2454509735,47.4125022888],"type":"Point"}
}