{
  "type": "Feature",
  "properties": {
    "iso:country":"CH",
    "sg:address":"Gartenstrasse 12",
    "sg:city":"Bern",
    "sg:orig_category":"Unternehmensberatung",
    "sg:postcode":"3007",
    "sg:province":"Bern",
    "wof:name":"Spica Lanz M.",
    "wof:placetype":"venue"
},
  "geometry": {"coordinates":[7.4283809662,46.9453239441],"type":"Point"}
}