{
  "type": "Feature",
  "properties": {
    "iso:country":"CH",
    "sg:address":"Dufourstrasse 110",
    "sg:city":"Biel/bienne",
    "sg:classifiers":[
        {
            "category":"Travel",
            "subcategory":"Hotels & Motels",
            "type":"Entertainment"
        }
    ],
    "sg:phone":"+41 32 344 90 44",
    "sg:postcode":"2502",
    "sg:province":"Bern",
    "sg:tags":[
        "hotels",
        "mit",
        "restaurant"
    ],
    "wof:name":"Metropol Management Ag",
    "wof:placetype":"venue"
},
  "geometry": {"coordinates":[7.255739212,47.143409729],"type":"Point"}
}