{
  "type": "Feature",
  "properties": {
    "iso:country":"CH",
    "sg:address":"Schupfen 1",
    "sg:city":"Speicher",
    "sg:orig_category":"Vorschulen, Kinderg\u00e4rten",
    "sg:phone":"+41 71 344 38 53",
    "sg:postcode":"9042",
    "sg:province":"Appenzell Ausserrhoden",
    "wof:name":"Kindergarten Schupfen",
    "wof:placetype":"venue"
},
  "geometry": {"coordinates":[9.4442090988,47.4101676941],"type":"Point"}
}