{
  "type": "Feature",
  "properties": {
    "addr:full":"Neugasse 11 Zug Zug 6300",
    "addr:housenumber":"11",
    "addr:postcode":"6300",
    "addr:street":"Neugasse;Zug",
    "iso:country":"CH",
    "sg:address":"Neugasse 11",
    "sg:city":"Zug",
    "sg:orig_category":"Detailhandel mit Bekleidung",
    "sg:phone":"+41 41 710 27 20",
    "sg:postcode":"6300",
    "sg:province":"Zug",
    "wof:name":"Boutique Varel",
    "wof:placetype":"venue"
},
  "geometry": {"coordinates":[8.515777,47.167198],"type":"Point"}
}