{
  "type": "Feature",
  "properties": {
    "iso:country":"CH",
    "sg:address":"Mittleres Zelgli 86",
    "sg:city":"Habsburg",
    "sg:orig_category":"Bauingenieurb\u00fcros Hochbau Bauingenieurb\u00fcros allgemein",
    "sg:phone":"+41 56 441 75 86",
    "sg:postcode":"5245",
    "sg:province":"Aargau",
    "wof:name":"Joachim Andri Ingenieurb\u00fcro",
    "wof:placetype":"venue"
},
  "geometry": {"coordinates":[8.187139,47.461784],"type":"Point"}
}