{
  "type": "Feature",
  "properties": {
    "iso:country":"CH",
    "sg:address":"Obere Leihofstrasse 17",
    "sg:city":"W\u00e4denswil",
    "sg:orig_category":"Sonstige pers\u00f6nliche Dienstleistungen",
    "sg:phone":"+41 79 358 29 07",
    "sg:postcode":"8820",
    "sg:province":"Z\u00fcrich",
    "wof:name":"Biophanie Gmbh",
    "wof:placetype":"venue"
},
  "geometry": {"coordinates":[7.5434150696,47.5102653503],"type":"Point"}
}