{
  "type": "Feature",
  "properties": {
    "iso:country":"CH",
    "sg:address":"Sch\u00e4fligasse 1",
    "sg:city":"Arbon",
    "sg:orig_category":"Spielsalons",
    "sg:phone":"+41 71 446 84 98",
    "sg:postcode":"9320",
    "sg:province":"Thurgau",
    "wof:name":"Spielsalon Casino",
    "wof:placetype":"venue"
},
  "geometry": {"coordinates":[9.4345979691,47.5163345337],"type":"Point"}
}