{
  "type": "Feature",
  "properties": {
    "iso:country":"CH",
    "sg:address":"Unterforststrasse 4313 M\u00f6hlin. Postfach 216",
    "sg:city":"M\u00f6hlin",
    "sg:orig_category":"Architektur U Ingenieurb\u00fcros Grosshandel mit Maschinen U Ausr\u00fcstungen",
    "sg:phone":"+41 41 850 33 31",
    "sg:postcode":"4313",
    "sg:province":"Aargau",
    "wof:name":"Maricon Ag",
    "wof:placetype":"venue"
},
  "geometry": {"coordinates":[8.432774,47.085049],"type":"Point"}
}