{
  "type": "Feature",
  "properties": {
    "iso:country":"CH",
    "sg:address":"Z\u00fcrichstrasse 109",
    "sg:city":"N\u00e4nikon",
    "sg:orig_category":"Mechanische Werkst\u00e4tten",
    "sg:phone":"+41 56 493 20 05",
    "sg:postcode":"8606",
    "sg:province":"Z\u00fcrich",
    "wof:name":"Walter Rey Mechanische Werkst\u00e4tte",
    "wof:placetype":"venue"
},
  "geometry": {"coordinates":[8.2851352692,47.4528808594],"type":"Point"}
}