{
  "type": "Feature",
  "properties": {
    "addr:full":"Promenadenstrasse 17 Arbon Thurgau 9320",
    "addr:housenumber":"17",
    "addr:postcode":"9320",
    "addr:street":"Promenadenstrasse",
    "iso:country":"CH",
    "sg:address":"Promenadenstrasse 17",
    "sg:city":"Arbon",
    "sg:orig_category":"Bezirks, Sekundar, Realschulen, Oberstufe der Primarschulen",
    "sg:phone":"+41 71 446 55 65",
    "sg:postcode":"9320",
    "sg:province":"Thurgau",
    "wof:name":"Realschule Promenadenschulhaus",
    "wof:placetype":"venue"
},
  "geometry": {"coordinates":[9.433675,47.515659],"type":"Point"}
}